Compiled from "Collections2.java"
final class com.google.common.collect.Collections2$OrderedPermutationCollection<E> extends java.util.AbstractCollection<java.util.List<E>> {
  final com.google.common.collect.ImmutableList<E> inputList;

  final java.util.Comparator<? super E> comparator;

  final int size;

  com.google.common.collect.Collections2$OrderedPermutationCollection(java.lang.Iterable<E>, java.util.Comparator<? super E>);
    Code:
       0: aload_0
       1: invokespecial #1                  // Method java/util/AbstractCollection."<init>":()V
       4: aload_0
       5: aload_2
       6: aload_1
       7: invokestatic  #2                  // Method com/google/common/collect/ImmutableList.sortedCopyOf:(Ljava/util/Comparator;Ljava/lang/Iterable;)Lcom/google/common/collect/ImmutableList;
      10: putfield      #3                  // Field inputList:Lcom/google/common/collect/ImmutableList;
      13: aload_0
      14: aload_2
      15: putfield      #4                  // Field comparator:Ljava/util/Comparator;
      18: aload_0
      19: aload_0
      20: getfield      #3                  // Field inputList:Lcom/google/common/collect/ImmutableList;
      23: aload_2
      24: invokestatic  #5                  // Method calculateSize:(Ljava/util/List;Ljava/util/Comparator;)I
      27: putfield      #6                  // Field size:I
      30: return

  public int size();
    Code:
       0: aload_0
       1: getfield      #6                  // Field size:I
       4: ireturn

  public boolean isEmpty();
    Code:
       0: iconst_0
       1: ireturn

  public java.util.Iterator<java.util.List<E>> iterator();
    Code:
       0: new           #14                 // class com/google/common/collect/Collections2$OrderedPermutationIterator
       3: dup
       4: aload_0
       5: getfield      #3                  // Field inputList:Lcom/google/common/collect/ImmutableList;
       8: aload_0
       9: getfield      #4                  // Field comparator:Ljava/util/Comparator;
      12: invokespecial #15                 // Method com/google/common/collect/Collections2$OrderedPermutationIterator."<init>":(Ljava/util/List;Ljava/util/Comparator;)V
      15: areturn

  public boolean contains(java.lang.Object);
    Code:
       0: aload_1
       1: instanceof    #16                 // class java/util/List
       4: ifeq          21
       7: aload_1
       8: checkcast     #16                 // class java/util/List
      11: astore_2
      12: aload_0
      13: getfield      #3                  // Field inputList:Lcom/google/common/collect/ImmutableList;
      16: aload_2
      17: invokestatic  #17                 // Method com/google/common/collect/Collections2.access$000:(Ljava/util/List;Ljava/util/List;)Z
      20: ireturn
      21: iconst_0
      22: ireturn

  public java.lang.String toString();
    Code:
       0: new           #18                 // class java/lang/StringBuilder
       3: dup
       4: invokespecial #19                 // Method java/lang/StringBuilder."<init>":()V
       7: ldc           #20                 // String orderedPermutationCollection(
       9: invokevirtual #21                 // Method java/lang/StringBuilder.append:(Ljava/lang/String;)Ljava/lang/StringBuilder;
      12: aload_0
      13: getfield      #3                  // Field inputList:Lcom/google/common/collect/ImmutableList;
      16: invokevirtual #22                 // Method java/lang/StringBuilder.append:(Ljava/lang/Object;)Ljava/lang/StringBuilder;
      19: ldc           #23                 // String )
      21: invokevirtual #21                 // Method java/lang/StringBuilder.append:(Ljava/lang/String;)Ljava/lang/StringBuilder;
      24: invokevirtual #24                 // Method java/lang/StringBuilder.toString:()Ljava/lang/String;
      27: areturn
}
