Compiled from "CompactLinkedHashMap.java"
class com.google.common.collect.CompactLinkedHashMap$1KeySetImpl extends com.google.common.collect.CompactHashMap<K, V>.KeySetView {
  final com.google.common.collect.CompactLinkedHashMap this$0;

  com.google.common.collect.CompactLinkedHashMap$1KeySetImpl(com.google.common.collect.CompactLinkedHashMap);
    Code:
       0: aload_0
       1: aload_1
       2: putfield      #1                  // Field this$0:Lcom/google/common/collect/CompactLinkedHashMap;
       5: aload_0
       6: aload_1
       7: invokespecial #2                  // Method com/google/common/collect/CompactHashMap$KeySetView."<init>":(Lcom/google/common/collect/CompactHashMap;)V
      10: return

  public java.lang.Object[] toArray();
    Code:
       0: aload_0
       1: invokestatic  #3                  // Method com/google/common/collect/ObjectArrays.toArrayImpl:(Ljava/util/Collection;)[Ljava/lang/Object;
       4: areturn

  public <T> T[] toArray(T[]);
    Code:
       0: aload_0
       1: aload_1
       2: invokestatic  #4                  // Method com/google/common/collect/ObjectArrays.toArrayImpl:(Ljava/util/Collection;[Ljava/lang/Object;)[Ljava/lang/Object;
       5: areturn

  public java.util.Spliterator<K> spliterator();
    Code:
       0: aload_0
       1: bipush        17
       3: invokestatic  #6                  // Method java/util/Spliterators.spliterator:(Ljava/util/Collection;I)Ljava/util/Spliterator;
       6: areturn
}
