Compiled from "ExecutionSequencer.java"
class com.google.common.util.concurrent.ExecutionSequencer$4 implements java.lang.Runnable {
  final com.google.common.util.concurrent.ListenableFuture val$taskFuture;

  final com.google.common.util.concurrent.ListenableFuture val$outputFuture;

  final java.util.concurrent.atomic.AtomicReference val$runningState;

  final com.google.common.util.concurrent.SettableFuture val$newFuture;

  final com.google.common.util.concurrent.ListenableFuture val$oldFuture;

  final com.google.common.util.concurrent.ExecutionSequencer this$0;

  com.google.common.util.concurrent.ExecutionSequencer$4(com.google.common.util.concurrent.ExecutionSequencer, com.google.common.util.concurrent.ListenableFuture, com.google.common.util.concurrent.ListenableFuture, java.util.concurrent.atomic.AtomicReference, com.google.common.util.concurrent.SettableFuture, com.google.common.util.concurrent.ListenableFuture);
    Code:
       0: aload_0
       1: aload_1
       2: putfield      #1                  // Field this$0:Lcom/google/common/util/concurrent/ExecutionSequencer;
       5: aload_0
       6: aload_2
       7: putfield      #2                  // Field val$taskFuture:Lcom/google/common/util/concurrent/ListenableFuture;
      10: aload_0
      11: aload_3
      12: putfield      #3                  // Field val$outputFuture:Lcom/google/common/util/concurrent/ListenableFuture;
      15: aload_0
      16: aload         4
      18: putfield      #4                  // Field val$runningState:Ljava/util/concurrent/atomic/AtomicReference;
      21: aload_0
      22: aload         5
      24: putfield      #5                  // Field val$newFuture:Lcom/google/common/util/concurrent/SettableFuture;
      27: aload_0
      28: aload         6
      30: putfield      #6                  // Field val$oldFuture:Lcom/google/common/util/concurrent/ListenableFuture;
      33: aload_0
      34: invokespecial #7                  // Method java/lang/Object."<init>":()V
      37: return

  public void run();
    Code:
       0: aload_0
       1: getfield      #2                  // Field val$taskFuture:Lcom/google/common/util/concurrent/ListenableFuture;
       4: invokeinterface #8,  1            // InterfaceMethod com/google/common/util/concurrent/ListenableFuture.isDone:()Z
       9: ifne          40
      12: aload_0
      13: getfield      #3                  // Field val$outputFuture:Lcom/google/common/util/concurrent/ListenableFuture;
      16: invokeinterface #9,  1            // InterfaceMethod com/google/common/util/concurrent/ListenableFuture.isCancelled:()Z
      21: ifeq          52
      24: aload_0
      25: getfield      #4                  // Field val$runningState:Ljava/util/concurrent/atomic/AtomicReference;
      28: getstatic     #10                 // Field com/google/common/util/concurrent/ExecutionSequencer$RunningState.NOT_RUN:Lcom/google/common/util/concurrent/ExecutionSequencer$RunningState;
      31: getstatic     #11                 // Field com/google/common/util/concurrent/ExecutionSequencer$RunningState.CANCELLED:Lcom/google/common/util/concurrent/ExecutionSequencer$RunningState;
      34: invokevirtual #12                 // Method java/util/concurrent/atomic/AtomicReference.compareAndSet:(Ljava/lang/Object;Ljava/lang/Object;)Z
      37: ifeq          52
      40: aload_0
      41: getfield      #5                  // Field val$newFuture:Lcom/google/common/util/concurrent/SettableFuture;
      44: aload_0
      45: getfield      #6                  // Field val$oldFuture:Lcom/google/common/util/concurrent/ListenableFuture;
      48: invokevirtual #13                 // Method com/google/common/util/concurrent/SettableFuture.setFuture:(Lcom/google/common/util/concurrent/ListenableFuture;)Z
      51: pop
      52: return
}
