Compiled from "ExecutionSequencer.java"
class com.google.common.util.concurrent.ExecutionSequencer$2 implements com.google.common.util.concurrent.AsyncCallable<T> {
  final java.util.concurrent.atomic.AtomicReference val$runningState;

  final com.google.common.util.concurrent.AsyncCallable val$callable;

  final com.google.common.util.concurrent.ExecutionSequencer this$0;

  com.google.common.util.concurrent.ExecutionSequencer$2(com.google.common.util.concurrent.ExecutionSequencer, java.util.concurrent.atomic.AtomicReference, com.google.common.util.concurrent.AsyncCallable);
    Code:
       0: aload_0
       1: aload_1
       2: putfield      #1                  // Field this$0:Lcom/google/common/util/concurrent/ExecutionSequencer;
       5: aload_0
       6: aload_2
       7: putfield      #2                  // Field val$runningState:Ljava/util/concurrent/atomic/AtomicReference;
      10: aload_0
      11: aload_3
      12: putfield      #3                  // Field val$callable:Lcom/google/common/util/concurrent/AsyncCallable;
      15: aload_0
      16: invokespecial #4                  // Method java/lang/Object."<init>":()V
      19: return

  public com.google.common.util.concurrent.ListenableFuture<T> call() throws java.lang.Exception;
    Code:
       0: aload_0
       1: getfield      #2                  // Field val$runningState:Ljava/util/concurrent/atomic/AtomicReference;
       4: getstatic     #5                  // Field com/google/common/util/concurrent/ExecutionSequencer$RunningState.NOT_RUN:Lcom/google/common/util/concurrent/ExecutionSequencer$RunningState;
       7: getstatic     #6                  // Field com/google/common/util/concurrent/ExecutionSequencer$RunningState.STARTED:Lcom/google/common/util/concurrent/ExecutionSequencer$RunningState;
      10: invokevirtual #7                  // Method java/util/concurrent/atomic/AtomicReference.compareAndSet:(Ljava/lang/Object;Ljava/lang/Object;)Z
      13: ifne          20
      16: invokestatic  #8                  // Method com/google/common/util/concurrent/Futures.immediateCancelledFuture:()Lcom/google/common/util/concurrent/ListenableFuture;
      19: areturn
      20: aload_0
      21: getfield      #3                  // Field val$callable:Lcom/google/common/util/concurrent/AsyncCallable;
      24: invokeinterface #9,  1            // InterfaceMethod com/google/common/util/concurrent/AsyncCallable.call:()Lcom/google/common/util/concurrent/ListenableFuture;
      29: areturn

  public java.lang.String toString();
    Code:
       0: aload_0
       1: getfield      #3                  // Field val$callable:Lcom/google/common/util/concurrent/AsyncCallable;
       4: invokevirtual #10                 // Method java/lang/Object.toString:()Ljava/lang/String;
       7: areturn
}
