Compiled from "ImmutableNetwork.java"
public final class com.google.common.graph.ImmutableNetwork<N, E> extends com.google.common.graph.ConfigurableNetwork<N, E> {
  public static <N, E> com.google.common.graph.ImmutableNetwork<N, E> copyOf(com.google.common.graph.Network<N, E>);
    Code:
       0: aload_0
       1: instanceof    #5                  // class com/google/common/graph/ImmutableNetwork
       4: ifeq          14
       7: aload_0
       8: checkcast     #5                  // class com/google/common/graph/ImmutableNetwork
      11: goto          22
      14: new           #5                  // class com/google/common/graph/ImmutableNetwork
      17: dup
      18: aload_0
      19: invokespecial #6                  // Method "<init>":(Lcom/google/common/graph/Network;)V
      22: areturn

  public static <N, E> com.google.common.graph.ImmutableNetwork<N, E> copyOf(com.google.common.graph.ImmutableNetwork<N, E>);
    Code:
       0: aload_0
       1: invokestatic  #7                  // Method com/google/common/base/Preconditions.checkNotNull:(Ljava/lang/Object;)Ljava/lang/Object;
       4: checkcast     #5                  // class com/google/common/graph/ImmutableNetwork
       7: areturn

  public com.google.common.graph.ImmutableGraph<N> asGraph();
    Code:
       0: new           #8                  // class com/google/common/graph/ImmutableGraph
       3: dup
       4: aload_0
       5: invokespecial #9                  // Method com/google/common/graph/ConfigurableNetwork.asGraph:()Lcom/google/common/graph/Graph;
       8: invokespecial #10                 // Method com/google/common/graph/ImmutableGraph."<init>":(Lcom/google/common/graph/BaseGraph;)V
      11: areturn

  public java.util.Set successors(java.lang.Object);
    Code:
       0: aload_0
       1: aload_1
       2: invokespecial #43                 // Method com/google/common/graph/ConfigurableNetwork.successors:(Ljava/lang/Object;)Ljava/util/Set;
       5: areturn

  public java.util.Set predecessors(java.lang.Object);
    Code:
       0: aload_0
       1: aload_1
       2: invokespecial #44                 // Method com/google/common/graph/ConfigurableNetwork.predecessors:(Ljava/lang/Object;)Ljava/util/Set;
       5: areturn

  public java.util.Set outEdges(java.lang.Object);
    Code:
       0: aload_0
       1: aload_1
       2: invokespecial #45                 // Method com/google/common/graph/ConfigurableNetwork.outEdges:(Ljava/lang/Object;)Ljava/util/Set;
       5: areturn

  public java.util.Set inEdges(java.lang.Object);
    Code:
       0: aload_0
       1: aload_1
       2: invokespecial #46                 // Method com/google/common/graph/ConfigurableNetwork.inEdges:(Ljava/lang/Object;)Ljava/util/Set;
       5: areturn

  public java.util.Set edgesConnecting(java.lang.Object, java.lang.Object);
    Code:
       0: aload_0
       1: aload_1
       2: aload_2
       3: invokespecial #47                 // Method com/google/common/graph/ConfigurableNetwork.edgesConnecting:(Ljava/lang/Object;Ljava/lang/Object;)Ljava/util/Set;
       6: areturn

  public java.util.Set adjacentNodes(java.lang.Object);
    Code:
       0: aload_0
       1: aload_1
       2: invokespecial #48                 // Method com/google/common/graph/ConfigurableNetwork.adjacentNodes:(Ljava/lang/Object;)Ljava/util/Set;
       5: areturn

  public com.google.common.graph.EndpointPair incidentNodes(java.lang.Object);
    Code:
       0: aload_0
       1: aload_1
       2: invokespecial #49                 // Method com/google/common/graph/ConfigurableNetwork.incidentNodes:(Ljava/lang/Object;)Lcom/google/common/graph/EndpointPair;
       5: areturn

  public java.util.Set incidentEdges(java.lang.Object);
    Code:
       0: aload_0
       1: aload_1
       2: invokespecial #50                 // Method com/google/common/graph/ConfigurableNetwork.incidentEdges:(Ljava/lang/Object;)Ljava/util/Set;
       5: areturn

  public com.google.common.graph.ElementOrder edgeOrder();
    Code:
       0: aload_0
       1: invokespecial #51                 // Method com/google/common/graph/ConfigurableNetwork.edgeOrder:()Lcom/google/common/graph/ElementOrder;
       4: areturn

  public com.google.common.graph.ElementOrder nodeOrder();
    Code:
       0: aload_0
       1: invokespecial #52                 // Method com/google/common/graph/ConfigurableNetwork.nodeOrder:()Lcom/google/common/graph/ElementOrder;
       4: areturn

  public boolean allowsSelfLoops();
    Code:
       0: aload_0
       1: invokespecial #53                 // Method com/google/common/graph/ConfigurableNetwork.allowsSelfLoops:()Z
       4: ireturn

  public boolean allowsParallelEdges();
    Code:
       0: aload_0
       1: invokespecial #54                 // Method com/google/common/graph/ConfigurableNetwork.allowsParallelEdges:()Z
       4: ireturn

  public boolean isDirected();
    Code:
       0: aload_0
       1: invokespecial #55                 // Method com/google/common/graph/ConfigurableNetwork.isDirected:()Z
       4: ireturn

  public java.util.Set edges();
    Code:
       0: aload_0
       1: invokespecial #56                 // Method com/google/common/graph/ConfigurableNetwork.edges:()Ljava/util/Set;
       4: areturn

  public java.util.Set nodes();
    Code:
       0: aload_0
       1: invokespecial #57                 // Method com/google/common/graph/ConfigurableNetwork.nodes:()Ljava/util/Set;
       4: areturn

  public com.google.common.graph.Graph asGraph();
    Code:
       0: aload_0
       1: invokevirtual #58                 // Method asGraph:()Lcom/google/common/graph/ImmutableGraph;
       4: areturn
}
