Compiled from "ImmutableSetMultimap.java"
public class com.google.common.collect.ImmutableSetMultimap<K, V> extends com.google.common.collect.ImmutableMultimap<K, V> implements com.google.common.collect.SetMultimap<K, V> {
  public static <T, K, V> java.util.stream.Collector<T, ?, com.google.common.collect.ImmutableSetMultimap<K, V>> toImmutableSetMultimap(java.util.function.Function<? super T, ? extends K>, java.util.function.Function<? super T, ? extends V>);
    Code:
       0: aload_0
       1: ldc           #1                  // String keyFunction
       3: invokestatic  #2                  // Method com/google/common/base/Preconditions.checkNotNull:(Ljava/lang/Object;Ljava/lang/Object;)Ljava/lang/Object;
       6: pop
       7: aload_1
       8: ldc           #3                  // String valueFunction
      10: invokestatic  #2                  // Method com/google/common/base/Preconditions.checkNotNull:(Ljava/lang/Object;Ljava/lang/Object;)Ljava/lang/Object;
      13: pop
      14: invokedynamic #4,  0              // InvokeDynamic #0:get:()Ljava/util/function/Supplier;
      19: aload_0
      20: aload_1
      21: invokedynamic #5,  0              // InvokeDynamic #1:accept:(Ljava/util/function/Function;Ljava/util/function/Function;)Ljava/util/function/BiConsumer;
      26: invokedynamic #6,  0              // InvokeDynamic #2:apply:()Ljava/util/function/BinaryOperator;
      31: invokedynamic #7,  0              // InvokeDynamic #3:apply:()Ljava/util/function/Function;
      36: iconst_0
      37: anewarray     #8                  // class java/util/stream/Collector$Characteristics
      40: invokestatic  #9                  // InterfaceMethod java/util/stream/Collector.of:(Ljava/util/function/Supplier;Ljava/util/function/BiConsumer;Ljava/util/function/BinaryOperator;Ljava/util/function/Function;[Ljava/util/stream/Collector$Characteristics;)Ljava/util/stream/Collector;
      43: areturn

  public static <T, K, V> java.util.stream.Collector<T, ?, com.google.common.collect.ImmutableSetMultimap<K, V>> flatteningToImmutableSetMultimap(java.util.function.Function<? super T, ? extends K>, java.util.function.Function<? super T, ? extends java.util.stream.Stream<? extends V>>);
    Code:
       0: aload_0
       1: invokestatic  #10                 // Method com/google/common/base/Preconditions.checkNotNull:(Ljava/lang/Object;)Ljava/lang/Object;
       4: pop
       5: aload_1
       6: invokestatic  #10                 // Method com/google/common/base/Preconditions.checkNotNull:(Ljava/lang/Object;)Ljava/lang/Object;
       9: pop
      10: aload_0
      11: invokedynamic #11,  0             // InvokeDynamic #4:apply:(Ljava/util/function/Function;)Ljava/util/function/Function;
      16: aload_1
      17: invokedynamic #12,  0             // InvokeDynamic #5:apply:(Ljava/util/function/Function;)Ljava/util/function/Function;
      22: invokestatic  #13                 // Method com/google/common/collect/MultimapBuilder.linkedHashKeys:()Lcom/google/common/collect/MultimapBuilder$MultimapBuilderWithKeys;
      25: invokevirtual #14                 // Method com/google/common/collect/MultimapBuilder$MultimapBuilderWithKeys.linkedHashSetValues:()Lcom/google/common/collect/MultimapBuilder$SetMultimapBuilder;
      28: dup
      29: invokevirtual #15                 // Method java/lang/Object.getClass:()Ljava/lang/Class;
      32: pop
      33: invokedynamic #16,  0             // InvokeDynamic #6:get:(Lcom/google/common/collect/MultimapBuilder$SetMultimapBuilder;)Ljava/util/function/Supplier;
      38: invokestatic  #17                 // Method com/google/common/collect/Multimaps.flatteningToMultimap:(Ljava/util/function/Function;Ljava/util/function/Function;Ljava/util/function/Supplier;)Ljava/util/stream/Collector;
      41: invokedynamic #18,  0             // InvokeDynamic #7:apply:()Ljava/util/function/Function;
      46: invokestatic  #19                 // Method java/util/stream/Collectors.collectingAndThen:(Ljava/util/stream/Collector;Ljava/util/function/Function;)Ljava/util/stream/Collector;
      49: areturn

  public static <K, V> com.google.common.collect.ImmutableSetMultimap<K, V> of();
    Code:
       0: getstatic     #20                 // Field com/google/common/collect/EmptyImmutableSetMultimap.INSTANCE:Lcom/google/common/collect/EmptyImmutableSetMultimap;
       3: areturn

  public static <K, V> com.google.common.collect.ImmutableSetMultimap<K, V> of(K, V);
    Code:
       0: invokestatic  #21                 // Method builder:()Lcom/google/common/collect/ImmutableSetMultimap$Builder;
       3: astore_2
       4: aload_2
       5: aload_0
       6: aload_1
       7: invokevirtual #22                 // Method com/google/common/collect/ImmutableSetMultimap$Builder.put:(Ljava/lang/Object;Ljava/lang/Object;)Lcom/google/common/collect/ImmutableSetMultimap$Builder;
      10: pop
      11: aload_2
      12: invokevirtual #23                 // Method com/google/common/collect/ImmutableSetMultimap$Builder.build:()Lcom/google/common/collect/ImmutableSetMultimap;
      15: areturn

  public static <K, V> com.google.common.collect.ImmutableSetMultimap<K, V> of(K, V, K, V);
    Code:
       0: invokestatic  #21                 // Method builder:()Lcom/google/common/collect/ImmutableSetMultimap$Builder;
       3: astore        4
       5: aload         4
       7: aload_0
       8: aload_1
       9: invokevirtual #22                 // Method com/google/common/collect/ImmutableSetMultimap$Builder.put:(Ljava/lang/Object;Ljava/lang/Object;)Lcom/google/common/collect/ImmutableSetMultimap$Builder;
      12: pop
      13: aload         4
      15: aload_2
      16: aload_3
      17: invokevirtual #22                 // Method com/google/common/collect/ImmutableSetMultimap$Builder.put:(Ljava/lang/Object;Ljava/lang/Object;)Lcom/google/common/collect/ImmutableSetMultimap$Builder;
      20: pop
      21: aload         4
      23: invokevirtual #23                 // Method com/google/common/collect/ImmutableSetMultimap$Builder.build:()Lcom/google/common/collect/ImmutableSetMultimap;
      26: areturn

  public static <K, V> com.google.common.collect.ImmutableSetMultimap<K, V> of(K, V, K, V, K, V);
    Code:
       0: invokestatic  #21                 // Method builder:()Lcom/google/common/collect/ImmutableSetMultimap$Builder;
       3: astore        6
       5: aload         6
       7: aload_0
       8: aload_1
       9: invokevirtual #22                 // Method com/google/common/collect/ImmutableSetMultimap$Builder.put:(Ljava/lang/Object;Ljava/lang/Object;)Lcom/google/common/collect/ImmutableSetMultimap$Builder;
      12: pop
      13: aload         6
      15: aload_2
      16: aload_3
      17: invokevirtual #22                 // Method com/google/common/collect/ImmutableSetMultimap$Builder.put:(Ljava/lang/Object;Ljava/lang/Object;)Lcom/google/common/collect/ImmutableSetMultimap$Builder;
      20: pop
      21: aload         6
      23: aload         4
      25: aload         5
      27: invokevirtual #22                 // Method com/google/common/collect/ImmutableSetMultimap$Builder.put:(Ljava/lang/Object;Ljava/lang/Object;)Lcom/google/common/collect/ImmutableSetMultimap$Builder;
      30: pop
      31: aload         6
      33: invokevirtual #23                 // Method com/google/common/collect/ImmutableSetMultimap$Builder.build:()Lcom/google/common/collect/ImmutableSetMultimap;
      36: areturn

  public static <K, V> com.google.common.collect.ImmutableSetMultimap<K, V> of(K, V, K, V, K, V, K, V);
    Code:
       0: invokestatic  #21                 // Method builder:()Lcom/google/common/collect/ImmutableSetMultimap$Builder;
       3: astore        8
       5: aload         8
       7: aload_0
       8: aload_1
       9: invokevirtual #22                 // Method com/google/common/collect/ImmutableSetMultimap$Builder.put:(Ljava/lang/Object;Ljava/lang/Object;)Lcom/google/common/collect/ImmutableSetMultimap$Builder;
      12: pop
      13: aload         8
      15: aload_2
      16: aload_3
      17: invokevirtual #22                 // Method com/google/common/collect/ImmutableSetMultimap$Builder.put:(Ljava/lang/Object;Ljava/lang/Object;)Lcom/google/common/collect/ImmutableSetMultimap$Builder;
      20: pop
      21: aload         8
      23: aload         4
      25: aload         5
      27: invokevirtual #22                 // Method com/google/common/collect/ImmutableSetMultimap$Builder.put:(Ljava/lang/Object;Ljava/lang/Object;)Lcom/google/common/collect/ImmutableSetMultimap$Builder;
      30: pop
      31: aload         8
      33: aload         6
      35: aload         7
      37: invokevirtual #22                 // Method com/google/common/collect/ImmutableSetMultimap$Builder.put:(Ljava/lang/Object;Ljava/lang/Object;)Lcom/google/common/collect/ImmutableSetMultimap$Builder;
      40: pop
      41: aload         8
      43: invokevirtual #23                 // Method com/google/common/collect/ImmutableSetMultimap$Builder.build:()Lcom/google/common/collect/ImmutableSetMultimap;
      46: areturn

  public static <K, V> com.google.common.collect.ImmutableSetMultimap<K, V> of(K, V, K, V, K, V, K, V, K, V);
    Code:
       0: invokestatic  #21                 // Method builder:()Lcom/google/common/collect/ImmutableSetMultimap$Builder;
       3: astore        10
       5: aload         10
       7: aload_0
       8: aload_1
       9: invokevirtual #22                 // Method com/google/common/collect/ImmutableSetMultimap$Builder.put:(Ljava/lang/Object;Ljava/lang/Object;)Lcom/google/common/collect/ImmutableSetMultimap$Builder;
      12: pop
      13: aload         10
      15: aload_2
      16: aload_3
      17: invokevirtual #22                 // Method com/google/common/collect/ImmutableSetMultimap$Builder.put:(Ljava/lang/Object;Ljava/lang/Object;)Lcom/google/common/collect/ImmutableSetMultimap$Builder;
      20: pop
      21: aload         10
      23: aload         4
      25: aload         5
      27: invokevirtual #22                 // Method com/google/common/collect/ImmutableSetMultimap$Builder.put:(Ljava/lang/Object;Ljava/lang/Object;)Lcom/google/common/collect/ImmutableSetMultimap$Builder;
      30: pop
      31: aload         10
      33: aload         6
      35: aload         7
      37: invokevirtual #22                 // Method com/google/common/collect/ImmutableSetMultimap$Builder.put:(Ljava/lang/Object;Ljava/lang/Object;)Lcom/google/common/collect/ImmutableSetMultimap$Builder;
      40: pop
      41: aload         10
      43: aload         8
      45: aload         9
      47: invokevirtual #22                 // Method com/google/common/collect/ImmutableSetMultimap$Builder.put:(Ljava/lang/Object;Ljava/lang/Object;)Lcom/google/common/collect/ImmutableSetMultimap$Builder;
      50: pop
      51: aload         10
      53: invokevirtual #23                 // Method com/google/common/collect/ImmutableSetMultimap$Builder.build:()Lcom/google/common/collect/ImmutableSetMultimap;
      56: areturn

  public static <K, V> com.google.common.collect.ImmutableSetMultimap$Builder<K, V> builder();
    Code:
       0: new           #24                 // class com/google/common/collect/ImmutableSetMultimap$Builder
       3: dup
       4: invokespecial #25                 // Method com/google/common/collect/ImmutableSetMultimap$Builder."<init>":()V
       7: areturn

  public static <K, V> com.google.common.collect.ImmutableSetMultimap<K, V> copyOf(com.google.common.collect.Multimap<? extends K, ? extends V>);
    Code:
       0: aload_0
       1: aconst_null
       2: invokestatic  #26                 // Method copyOf:(Lcom/google/common/collect/Multimap;Ljava/util/Comparator;)Lcom/google/common/collect/ImmutableSetMultimap;
       5: areturn

  public static <K, V> com.google.common.collect.ImmutableSetMultimap<K, V> copyOf(java.lang.Iterable<? extends java.util.Map$Entry<? extends K, ? extends V>>);
    Code:
       0: new           #24                 // class com/google/common/collect/ImmutableSetMultimap$Builder
       3: dup
       4: invokespecial #25                 // Method com/google/common/collect/ImmutableSetMultimap$Builder."<init>":()V
       7: aload_0
       8: invokevirtual #34                 // Method com/google/common/collect/ImmutableSetMultimap$Builder.putAll:(Ljava/lang/Iterable;)Lcom/google/common/collect/ImmutableSetMultimap$Builder;
      11: invokevirtual #23                 // Method com/google/common/collect/ImmutableSetMultimap$Builder.build:()Lcom/google/common/collect/ImmutableSetMultimap;
      14: areturn

  static <K, V> com.google.common.collect.ImmutableSetMultimap<K, V> fromMapEntries(java.util.Collection<? extends java.util.Map$Entry<? extends K, ? extends java.util.Collection<? extends V>>>, java.util.Comparator<? super V>);
    Code:
       0: aload_0
       1: invokeinterface #35,  1           // InterfaceMethod java/util/Collection.isEmpty:()Z
       6: ifeq          13
       9: invokestatic  #28                 // Method of:()Lcom/google/common/collect/ImmutableSetMultimap;
      12: areturn
      13: new           #36                 // class com/google/common/collect/ImmutableMap$Builder
      16: dup
      17: aload_0
      18: invokeinterface #37,  1           // InterfaceMethod java/util/Collection.size:()I
      23: invokespecial #38                 // Method com/google/common/collect/ImmutableMap$Builder."<init>":(I)V
      26: astore_2
      27: iconst_0
      28: istore_3
      29: aload_0
      30: invokeinterface #39,  1           // InterfaceMethod java/util/Collection.iterator:()Ljava/util/Iterator;
      35: astore        4
      37: aload         4
      39: invokeinterface #40,  1           // InterfaceMethod java/util/Iterator.hasNext:()Z
      44: ifeq          116
      47: aload         4
      49: invokeinterface #41,  1           // InterfaceMethod java/util/Iterator.next:()Ljava/lang/Object;
      54: checkcast     #42                 // class java/util/Map$Entry
      57: astore        5
      59: aload         5
      61: invokeinterface #43,  1           // InterfaceMethod java/util/Map$Entry.getKey:()Ljava/lang/Object;
      66: astore        6
      68: aload         5
      70: invokeinterface #44,  1           // InterfaceMethod java/util/Map$Entry.getValue:()Ljava/lang/Object;
      75: checkcast     #45                 // class java/util/Collection
      78: astore        7
      80: aload_1
      81: aload         7
      83: invokestatic  #46                 // Method valueSet:(Ljava/util/Comparator;Ljava/util/Collection;)Lcom/google/common/collect/ImmutableSet;
      86: astore        8
      88: aload         8
      90: invokevirtual #47                 // Method com/google/common/collect/ImmutableSet.isEmpty:()Z
      93: ifne          113
      96: aload_2
      97: aload         6
      99: aload         8
     101: invokevirtual #48                 // Method com/google/common/collect/ImmutableMap$Builder.put:(Ljava/lang/Object;Ljava/lang/Object;)Lcom/google/common/collect/ImmutableMap$Builder;
     104: pop
     105: iload_3
     106: aload         8
     108: invokevirtual #49                 // Method com/google/common/collect/ImmutableSet.size:()I
     111: iadd
     112: istore_3
     113: goto          37
     116: new           #29                 // class com/google/common/collect/ImmutableSetMultimap
     119: dup
     120: aload_2
     121: invokevirtual #50                 // Method com/google/common/collect/ImmutableMap$Builder.build:()Lcom/google/common/collect/ImmutableMap;
     124: iload_3
     125: aload_1
     126: invokespecial #51                 // Method "<init>":(Lcom/google/common/collect/ImmutableMap;ILjava/util/Comparator;)V
     129: areturn

  com.google.common.collect.ImmutableSetMultimap(com.google.common.collect.ImmutableMap<K, com.google.common.collect.ImmutableSet<V>>, int, java.util.Comparator<? super V>);
    Code:
       0: aload_0
       1: aload_1
       2: iload_2
       3: invokespecial #52                 // Method com/google/common/collect/ImmutableMultimap."<init>":(Lcom/google/common/collect/ImmutableMap;I)V
       6: aload_0
       7: aload_3
       8: invokestatic  #53                 // Method emptySet:(Ljava/util/Comparator;)Lcom/google/common/collect/ImmutableSet;
      11: putfield      #54                 // Field emptySet:Lcom/google/common/collect/ImmutableSet;
      14: return

  public com.google.common.collect.ImmutableSet<V> get(K);
    Code:
       0: aload_0
       1: getfield      #55                 // Field map:Lcom/google/common/collect/ImmutableMap;
       4: aload_1
       5: invokevirtual #56                 // Method com/google/common/collect/ImmutableMap.get:(Ljava/lang/Object;)Ljava/lang/Object;
       8: checkcast     #57                 // class com/google/common/collect/ImmutableSet
      11: astore_2
      12: aload_2
      13: aload_0
      14: getfield      #54                 // Field emptySet:Lcom/google/common/collect/ImmutableSet;
      17: invokestatic  #58                 // Method com/google/common/base/MoreObjects.firstNonNull:(Ljava/lang/Object;Ljava/lang/Object;)Ljava/lang/Object;
      20: checkcast     #57                 // class com/google/common/collect/ImmutableSet
      23: areturn

  public com.google.common.collect.ImmutableSetMultimap<V, K> inverse();
    Code:
       0: aload_0
       1: getfield      #59                 // Field inverse:Lcom/google/common/collect/ImmutableSetMultimap;
       4: astore_1
       5: aload_1
       6: ifnonnull     21
       9: aload_0
      10: aload_0
      11: invokespecial #60                 // Method invert:()Lcom/google/common/collect/ImmutableSetMultimap;
      14: dup_x1
      15: putfield      #59                 // Field inverse:Lcom/google/common/collect/ImmutableSetMultimap;
      18: goto          22
      21: aload_1
      22: areturn

  public com.google.common.collect.ImmutableSet<V> removeAll(java.lang.Object);
    Code:
       0: new           #63                 // class java/lang/UnsupportedOperationException
       3: dup
       4: invokespecial #64                 // Method java/lang/UnsupportedOperationException."<init>":()V
       7: athrow

  public com.google.common.collect.ImmutableSet<V> replaceValues(K, java.lang.Iterable<? extends V>);
    Code:
       0: new           #63                 // class java/lang/UnsupportedOperationException
       3: dup
       4: invokespecial #64                 // Method java/lang/UnsupportedOperationException."<init>":()V
       7: athrow

  public com.google.common.collect.ImmutableSet<java.util.Map$Entry<K, V>> entries();
    Code:
       0: aload_0
       1: getfield      #65                 // Field entries:Lcom/google/common/collect/ImmutableSet;
       4: astore_1
       5: aload_1
       6: ifnonnull     25
       9: aload_0
      10: new           #66                 // class com/google/common/collect/ImmutableSetMultimap$EntrySet
      13: dup
      14: aload_0
      15: invokespecial #67                 // Method com/google/common/collect/ImmutableSetMultimap$EntrySet."<init>":(Lcom/google/common/collect/ImmutableSetMultimap;)V
      18: dup_x1
      19: putfield      #65                 // Field entries:Lcom/google/common/collect/ImmutableSet;
      22: goto          26
      25: aload_1
      26: areturn

  java.util.Comparator<? super V> valueComparator();
    Code:
       0: aload_0
       1: getfield      #54                 // Field emptySet:Lcom/google/common/collect/ImmutableSet;
       4: instanceof    #80                 // class com/google/common/collect/ImmutableSortedSet
       7: ifeq          23
      10: aload_0
      11: getfield      #54                 // Field emptySet:Lcom/google/common/collect/ImmutableSet;
      14: checkcast     #80                 // class com/google/common/collect/ImmutableSortedSet
      17: invokevirtual #81                 // Method com/google/common/collect/ImmutableSortedSet.comparator:()Ljava/util/Comparator;
      20: goto          24
      23: aconst_null
      24: areturn

  public com.google.common.collect.ImmutableCollection entries();
    Code:
       0: aload_0
       1: invokevirtual #61                 // Method entries:()Lcom/google/common/collect/ImmutableSet;
       4: areturn

  public com.google.common.collect.ImmutableMultimap inverse();
    Code:
       0: aload_0
       1: invokevirtual #109                // Method inverse:()Lcom/google/common/collect/ImmutableSetMultimap;
       4: areturn

  public com.google.common.collect.ImmutableCollection get(java.lang.Object);
    Code:
       0: aload_0
       1: aload_1
       2: invokevirtual #110                // Method get:(Ljava/lang/Object;)Lcom/google/common/collect/ImmutableSet;
       5: areturn

  public com.google.common.collect.ImmutableCollection replaceValues(java.lang.Object, java.lang.Iterable);
    Code:
       0: aload_0
       1: aload_1
       2: aload_2
       3: invokevirtual #111                // Method replaceValues:(Ljava/lang/Object;Ljava/lang/Iterable;)Lcom/google/common/collect/ImmutableSet;
       6: areturn

  public com.google.common.collect.ImmutableCollection removeAll(java.lang.Object);
    Code:
       0: aload_0
       1: aload_1
       2: invokevirtual #112                // Method removeAll:(Ljava/lang/Object;)Lcom/google/common/collect/ImmutableSet;
       5: areturn

  public java.util.Collection entries();
    Code:
       0: aload_0
       1: invokevirtual #61                 // Method entries:()Lcom/google/common/collect/ImmutableSet;
       4: areturn

  public java.util.Collection replaceValues(java.lang.Object, java.lang.Iterable);
    Code:
       0: aload_0
       1: aload_1
       2: aload_2
       3: invokevirtual #111                // Method replaceValues:(Ljava/lang/Object;Ljava/lang/Iterable;)Lcom/google/common/collect/ImmutableSet;
       6: areturn

  public java.util.Collection get(java.lang.Object);
    Code:
       0: aload_0
       1: aload_1
       2: invokevirtual #110                // Method get:(Ljava/lang/Object;)Lcom/google/common/collect/ImmutableSet;
       5: areturn

  public java.util.Collection removeAll(java.lang.Object);
    Code:
       0: aload_0
       1: aload_1
       2: invokevirtual #112                // Method removeAll:(Ljava/lang/Object;)Lcom/google/common/collect/ImmutableSet;
       5: areturn

  public java.util.Set entries();
    Code:
       0: aload_0
       1: invokevirtual #61                 // Method entries:()Lcom/google/common/collect/ImmutableSet;
       4: areturn

  public java.util.Set replaceValues(java.lang.Object, java.lang.Iterable);
    Code:
       0: aload_0
       1: aload_1
       2: aload_2
       3: invokevirtual #111                // Method replaceValues:(Ljava/lang/Object;Ljava/lang/Iterable;)Lcom/google/common/collect/ImmutableSet;
       6: areturn

  public java.util.Set removeAll(java.lang.Object);
    Code:
       0: aload_0
       1: aload_1
       2: invokevirtual #112                // Method removeAll:(Ljava/lang/Object;)Lcom/google/common/collect/ImmutableSet;
       5: areturn

  public java.util.Set get(java.lang.Object);
    Code:
       0: aload_0
       1: aload_1
       2: invokevirtual #110                // Method get:(Ljava/lang/Object;)Lcom/google/common/collect/ImmutableSet;
       5: areturn
}
