Compiled from "InetAddresses.java"
public final class com.google.common.net.InetAddresses {
  public static java.net.InetAddress forString(java.lang.String);
    Code:
       0: aload_0
       1: invokestatic  #7                  // Method ipStringToBytes:(Ljava/lang/String;)[B
       4: astore_1
       5: aload_1
       6: ifnonnull     23
       9: ldc           #8                  // String '%s' is not an IP string literal.
      11: iconst_1
      12: anewarray     #9                  // class java/lang/Object
      15: dup
      16: iconst_0
      17: aload_0
      18: aastore
      19: invokestatic  #10                 // Method formatIllegalArgumentException:(Ljava/lang/String;[Ljava/lang/Object;)Ljava/lang/IllegalArgumentException;
      22: athrow
      23: aload_1
      24: invokestatic  #5                  // Method bytesToInetAddress:([B)Ljava/net/InetAddress;
      27: areturn

  public static boolean isInetAddress(java.lang.String);
    Code:
       0: aload_0
       1: invokestatic  #7                  // Method ipStringToBytes:(Ljava/lang/String;)[B
       4: ifnull        11
       7: iconst_1
       8: goto          12
      11: iconst_0
      12: ireturn

  public static java.lang.String toAddrString(java.net.InetAddress);
    Code:
       0: aload_0
       1: invokestatic  #54                 // Method com/google/common/base/Preconditions.checkNotNull:(Ljava/lang/Object;)Ljava/lang/Object;
       4: pop
       5: aload_0
       6: instanceof    #6                  // class java/net/Inet4Address
       9: ifeq          17
      12: aload_0
      13: invokevirtual #55                 // Method java/net/InetAddress.getHostAddress:()Ljava/lang/String;
      16: areturn
      17: aload_0
      18: instanceof    #56                 // class java/net/Inet6Address
      21: invokestatic  #57                 // Method com/google/common/base/Preconditions.checkArgument:(Z)V
      24: aload_0
      25: invokevirtual #58                 // Method java/net/InetAddress.getAddress:()[B
      28: astore_1
      29: bipush        8
      31: newarray       int
      33: astore_2
      34: iconst_0
      35: istore_3
      36: iload_3
      37: aload_2
      38: arraylength
      39: if_icmpge     68
      42: aload_2
      43: iload_3
      44: iconst_0
      45: iconst_0
      46: aload_1
      47: iconst_2
      48: iload_3
      49: imul
      50: baload
      51: aload_1
      52: iconst_2
      53: iload_3
      54: imul
      55: iconst_1
      56: iadd
      57: baload
      58: invokestatic  #59                 // Method com/google/common/primitives/Ints.fromBytes:(BBBB)I
      61: iastore
      62: iinc          3, 1
      65: goto          36
      68: aload_2
      69: invokestatic  #60                 // Method compressLongestRunOfZeroes:([I)V
      72: aload_2
      73: invokestatic  #61                 // Method hextetsToIPv6String:([I)Ljava/lang/String;
      76: areturn

  public static java.lang.String toUriString(java.net.InetAddress);
    Code:
       0: aload_0
       1: instanceof    #56                 // class java/net/Inet6Address
       4: ifeq          35
       7: new           #39                 // class java/lang/StringBuilder
      10: dup
      11: invokespecial #40                 // Method java/lang/StringBuilder."<init>":()V
      14: ldc           #66                 // String [
      16: invokevirtual #41                 // Method java/lang/StringBuilder.append:(Ljava/lang/String;)Ljava/lang/StringBuilder;
      19: aload_0
      20: invokestatic  #67                 // Method toAddrString:(Ljava/net/InetAddress;)Ljava/lang/String;
      23: invokevirtual #41                 // Method java/lang/StringBuilder.append:(Ljava/lang/String;)Ljava/lang/StringBuilder;
      26: ldc           #68                 // String ]
      28: invokevirtual #41                 // Method java/lang/StringBuilder.append:(Ljava/lang/String;)Ljava/lang/StringBuilder;
      31: invokevirtual #43                 // Method java/lang/StringBuilder.toString:()Ljava/lang/String;
      34: areturn
      35: aload_0
      36: invokestatic  #67                 // Method toAddrString:(Ljava/net/InetAddress;)Ljava/lang/String;
      39: areturn

  public static java.net.InetAddress forUriString(java.lang.String);
    Code:
       0: aload_0
       1: invokestatic  #69                 // Method forUriStringNoThrow:(Ljava/lang/String;)Ljava/net/InetAddress;
       4: astore_1
       5: aload_1
       6: ifnonnull     23
       9: ldc           #70                 // String Not a valid URI IP literal: '%s'
      11: iconst_1
      12: anewarray     #9                  // class java/lang/Object
      15: dup
      16: iconst_0
      17: aload_0
      18: aastore
      19: invokestatic  #10                 // Method formatIllegalArgumentException:(Ljava/lang/String;[Ljava/lang/Object;)Ljava/lang/IllegalArgumentException;
      22: athrow
      23: aload_1
      24: areturn

  public static boolean isUriInetAddress(java.lang.String);
    Code:
       0: aload_0
       1: invokestatic  #69                 // Method forUriStringNoThrow:(Ljava/lang/String;)Ljava/net/InetAddress;
       4: ifnull        11
       7: iconst_1
       8: goto          12
      11: iconst_0
      12: ireturn

  public static boolean isCompatIPv4Address(java.net.Inet6Address);
    Code:
       0: aload_0
       1: invokevirtual #72                 // Method java/net/Inet6Address.isIPv4CompatibleAddress:()Z
       4: ifne          9
       7: iconst_0
       8: ireturn
       9: aload_0
      10: invokevirtual #73                 // Method java/net/Inet6Address.getAddress:()[B
      13: astore_1
      14: aload_1
      15: bipush        12
      17: baload
      18: ifne          52
      21: aload_1
      22: bipush        13
      24: baload
      25: ifne          52
      28: aload_1
      29: bipush        14
      31: baload
      32: ifne          52
      35: aload_1
      36: bipush        15
      38: baload
      39: ifeq          50
      42: aload_1
      43: bipush        15
      45: baload
      46: iconst_1
      47: if_icmpne     52
      50: iconst_0
      51: ireturn
      52: iconst_1
      53: ireturn

  public static java.net.Inet4Address getCompatIPv4Address(java.net.Inet6Address);
    Code:
       0: aload_0
       1: invokestatic  #74                 // Method isCompatIPv4Address:(Ljava/net/Inet6Address;)Z
       4: ldc           #75                 // String Address '%s' is not IPv4-compatible.
       6: aload_0
       7: invokestatic  #67                 // Method toAddrString:(Ljava/net/InetAddress;)Ljava/lang/String;
      10: invokestatic  #76                 // Method com/google/common/base/Preconditions.checkArgument:(ZLjava/lang/String;Ljava/lang/Object;)V
      13: aload_0
      14: invokevirtual #73                 // Method java/net/Inet6Address.getAddress:()[B
      17: bipush        12
      19: bipush        16
      21: invokestatic  #77                 // Method java/util/Arrays.copyOfRange:([BII)[B
      24: invokestatic  #78                 // Method getInet4Address:([B)Ljava/net/Inet4Address;
      27: areturn

  public static boolean is6to4Address(java.net.Inet6Address);
    Code:
       0: aload_0
       1: invokevirtual #73                 // Method java/net/Inet6Address.getAddress:()[B
       4: astore_1
       5: aload_1
       6: iconst_0
       7: baload
       8: bipush        32
      10: if_icmpne     24
      13: aload_1
      14: iconst_1
      15: baload
      16: iconst_2
      17: if_icmpne     24
      20: iconst_1
      21: goto          25
      24: iconst_0
      25: ireturn

  public static java.net.Inet4Address get6to4IPv4Address(java.net.Inet6Address);
    Code:
       0: aload_0
       1: invokestatic  #79                 // Method is6to4Address:(Ljava/net/Inet6Address;)Z
       4: ldc           #80                 // String Address '%s' is not a 6to4 address.
       6: aload_0
       7: invokestatic  #67                 // Method toAddrString:(Ljava/net/InetAddress;)Ljava/lang/String;
      10: invokestatic  #76                 // Method com/google/common/base/Preconditions.checkArgument:(ZLjava/lang/String;Ljava/lang/Object;)V
      13: aload_0
      14: invokevirtual #73                 // Method java/net/Inet6Address.getAddress:()[B
      17: iconst_2
      18: bipush        6
      20: invokestatic  #77                 // Method java/util/Arrays.copyOfRange:([BII)[B
      23: invokestatic  #78                 // Method getInet4Address:([B)Ljava/net/Inet4Address;
      26: areturn

  public static boolean isTeredoAddress(java.net.Inet6Address);
    Code:
       0: aload_0
       1: invokevirtual #73                 // Method java/net/Inet6Address.getAddress:()[B
       4: astore_1
       5: aload_1
       6: iconst_0
       7: baload
       8: bipush        32
      10: if_icmpne     36
      13: aload_1
      14: iconst_1
      15: baload
      16: iconst_1
      17: if_icmpne     36
      20: aload_1
      21: iconst_2
      22: baload
      23: ifne          36
      26: aload_1
      27: iconst_3
      28: baload
      29: ifne          36
      32: iconst_1
      33: goto          37
      36: iconst_0
      37: ireturn

  public static com.google.common.net.InetAddresses$TeredoInfo getTeredoInfo(java.net.Inet6Address);
    Code:
       0: aload_0
       1: invokestatic  #81                 // Method isTeredoAddress:(Ljava/net/Inet6Address;)Z
       4: ldc           #82                 // String Address '%s' is not a Teredo address.
       6: aload_0
       7: invokestatic  #67                 // Method toAddrString:(Ljava/net/InetAddress;)Ljava/lang/String;
      10: invokestatic  #76                 // Method com/google/common/base/Preconditions.checkArgument:(ZLjava/lang/String;Ljava/lang/Object;)V
      13: aload_0
      14: invokevirtual #73                 // Method java/net/Inet6Address.getAddress:()[B
      17: astore_1
      18: aload_1
      19: iconst_4
      20: bipush        8
      22: invokestatic  #77                 // Method java/util/Arrays.copyOfRange:([BII)[B
      25: invokestatic  #78                 // Method getInet4Address:([B)Ljava/net/Inet4Address;
      28: astore_2
      29: aload_1
      30: bipush        8
      32: invokestatic  #83                 // Method com/google/common/io/ByteStreams.newDataInput:([BI)Lcom/google/common/io/ByteArrayDataInput;
      35: invokeinterface #84,  1           // InterfaceMethod com/google/common/io/ByteArrayDataInput.readShort:()S
      40: ldc           #49                 // int 65535
      42: iand
      43: istore_3
      44: aload_1
      45: bipush        10
      47: invokestatic  #83                 // Method com/google/common/io/ByteStreams.newDataInput:([BI)Lcom/google/common/io/ByteArrayDataInput;
      50: invokeinterface #84,  1           // InterfaceMethod com/google/common/io/ByteArrayDataInput.readShort:()S
      55: iconst_m1
      56: ixor
      57: ldc           #49                 // int 65535
      59: iand
      60: istore        4
      62: aload_1
      63: bipush        12
      65: bipush        16
      67: invokestatic  #77                 // Method java/util/Arrays.copyOfRange:([BII)[B
      70: astore        5
      72: iconst_0
      73: istore        6
      75: iload         6
      77: aload         5
      79: arraylength
      80: if_icmpge     102
      83: aload         5
      85: iload         6
      87: aload         5
      89: iload         6
      91: baload
      92: iconst_m1
      93: ixor
      94: i2b
      95: bastore
      96: iinc          6, 1
      99: goto          75
     102: aload         5
     104: invokestatic  #78                 // Method getInet4Address:([B)Ljava/net/Inet4Address;
     107: astore        6
     109: new           #85                 // class com/google/common/net/InetAddresses$TeredoInfo
     112: dup
     113: aload_2
     114: aload         6
     116: iload         4
     118: iload_3
     119: invokespecial #86                 // Method com/google/common/net/InetAddresses$TeredoInfo."<init>":(Ljava/net/Inet4Address;Ljava/net/Inet4Address;II)V
     122: areturn

  public static boolean isIsatapAddress(java.net.Inet6Address);
    Code:
       0: aload_0
       1: invokestatic  #81                 // Method isTeredoAddress:(Ljava/net/Inet6Address;)Z
       4: ifeq          9
       7: iconst_0
       8: ireturn
       9: aload_0
      10: invokevirtual #73                 // Method java/net/Inet6Address.getAddress:()[B
      13: astore_1
      14: aload_1
      15: bipush        8
      17: baload
      18: iconst_3
      19: ior
      20: iconst_3
      21: if_icmpeq     26
      24: iconst_0
      25: ireturn
      26: aload_1
      27: bipush        9
      29: baload
      30: ifne          55
      33: aload_1
      34: bipush        10
      36: baload
      37: bipush        94
      39: if_icmpne     55
      42: aload_1
      43: bipush        11
      45: baload
      46: bipush        -2
      48: if_icmpne     55
      51: iconst_1
      52: goto          56
      55: iconst_0
      56: ireturn

  public static java.net.Inet4Address getIsatapIPv4Address(java.net.Inet6Address);
    Code:
       0: aload_0
       1: invokestatic  #87                 // Method isIsatapAddress:(Ljava/net/Inet6Address;)Z
       4: ldc           #88                 // String Address '%s' is not an ISATAP address.
       6: aload_0
       7: invokestatic  #67                 // Method toAddrString:(Ljava/net/InetAddress;)Ljava/lang/String;
      10: invokestatic  #76                 // Method com/google/common/base/Preconditions.checkArgument:(ZLjava/lang/String;Ljava/lang/Object;)V
      13: aload_0
      14: invokevirtual #73                 // Method java/net/Inet6Address.getAddress:()[B
      17: bipush        12
      19: bipush        16
      21: invokestatic  #77                 // Method java/util/Arrays.copyOfRange:([BII)[B
      24: invokestatic  #78                 // Method getInet4Address:([B)Ljava/net/Inet4Address;
      27: areturn

  public static boolean hasEmbeddedIPv4ClientAddress(java.net.Inet6Address);
    Code:
       0: aload_0
       1: invokestatic  #74                 // Method isCompatIPv4Address:(Ljava/net/Inet6Address;)Z
       4: ifne          21
       7: aload_0
       8: invokestatic  #79                 // Method is6to4Address:(Ljava/net/Inet6Address;)Z
      11: ifne          21
      14: aload_0
      15: invokestatic  #81                 // Method isTeredoAddress:(Ljava/net/Inet6Address;)Z
      18: ifeq          25
      21: iconst_1
      22: goto          26
      25: iconst_0
      26: ireturn

  public static java.net.Inet4Address getEmbeddedIPv4ClientAddress(java.net.Inet6Address);
    Code:
       0: aload_0
       1: invokestatic  #74                 // Method isCompatIPv4Address:(Ljava/net/Inet6Address;)Z
       4: ifeq          12
       7: aload_0
       8: invokestatic  #89                 // Method getCompatIPv4Address:(Ljava/net/Inet6Address;)Ljava/net/Inet4Address;
      11: areturn
      12: aload_0
      13: invokestatic  #79                 // Method is6to4Address:(Ljava/net/Inet6Address;)Z
      16: ifeq          24
      19: aload_0
      20: invokestatic  #90                 // Method get6to4IPv4Address:(Ljava/net/Inet6Address;)Ljava/net/Inet4Address;
      23: areturn
      24: aload_0
      25: invokestatic  #81                 // Method isTeredoAddress:(Ljava/net/Inet6Address;)Z
      28: ifeq          39
      31: aload_0
      32: invokestatic  #91                 // Method getTeredoInfo:(Ljava/net/Inet6Address;)Lcom/google/common/net/InetAddresses$TeredoInfo;
      35: invokevirtual #92                 // Method com/google/common/net/InetAddresses$TeredoInfo.getClient:()Ljava/net/Inet4Address;
      38: areturn
      39: ldc           #93                 // String '%s' has no embedded IPv4 address.
      41: iconst_1
      42: anewarray     #9                  // class java/lang/Object
      45: dup
      46: iconst_0
      47: aload_0
      48: invokestatic  #67                 // Method toAddrString:(Ljava/net/InetAddress;)Ljava/lang/String;
      51: aastore
      52: invokestatic  #10                 // Method formatIllegalArgumentException:(Ljava/lang/String;[Ljava/lang/Object;)Ljava/lang/IllegalArgumentException;
      55: athrow

  public static boolean isMappedIPv4Address(java.lang.String);
    Code:
       0: aload_0
       1: invokestatic  #7                  // Method ipStringToBytes:(Ljava/lang/String;)[B
       4: astore_1
       5: aload_1
       6: ifnull        64
       9: aload_1
      10: arraylength
      11: bipush        16
      13: if_icmpne     64
      16: iconst_0
      17: istore_2
      18: iload_2
      19: bipush        10
      21: if_icmpge     38
      24: aload_1
      25: iload_2
      26: baload
      27: ifeq          32
      30: iconst_0
      31: ireturn
      32: iinc          2, 1
      35: goto          18
      38: bipush        10
      40: istore_2
      41: iload_2
      42: bipush        12
      44: if_icmpge     62
      47: aload_1
      48: iload_2
      49: baload
      50: iconst_m1
      51: if_icmpeq     56
      54: iconst_0
      55: ireturn
      56: iinc          2, 1
      59: goto          41
      62: iconst_1
      63: ireturn
      64: iconst_0
      65: ireturn

  public static java.net.Inet4Address getCoercedIPv4Address(java.net.InetAddress);
    Code:
       0: aload_0
       1: instanceof    #6                  // class java/net/Inet4Address
       4: ifeq          12
       7: aload_0
       8: checkcast     #6                  // class java/net/Inet4Address
      11: areturn
      12: aload_0
      13: invokevirtual #58                 // Method java/net/InetAddress.getAddress:()[B
      16: astore_1
      17: iconst_1
      18: istore_2
      19: iconst_0
      20: istore_3
      21: iload_3
      22: bipush        15
      24: if_icmpge     44
      27: aload_1
      28: iload_3
      29: baload
      30: ifeq          38
      33: iconst_0
      34: istore_2
      35: goto          44
      38: iinc          3, 1
      41: goto          21
      44: iload_2
      45: ifeq          60
      48: aload_1
      49: bipush        15
      51: baload
      52: iconst_1
      53: if_icmpne     60
      56: getstatic     #94                 // Field LOOPBACK4:Ljava/net/Inet4Address;
      59: areturn
      60: iload_2
      61: ifeq          75
      64: aload_1
      65: bipush        15
      67: baload
      68: ifne          75
      71: getstatic     #1                  // Field ANY4:Ljava/net/Inet4Address;
      74: areturn
      75: aload_0
      76: checkcast     #56                 // class java/net/Inet6Address
      79: astore_3
      80: lconst_0
      81: lstore        4
      83: aload_3
      84: invokestatic  #95                 // Method hasEmbeddedIPv4ClientAddress:(Ljava/net/Inet6Address;)Z
      87: ifeq          103
      90: aload_3
      91: invokestatic  #96                 // Method getEmbeddedIPv4ClientAddress:(Ljava/net/Inet6Address;)Ljava/net/Inet4Address;
      94: invokevirtual #97                 // Method java/net/Inet4Address.hashCode:()I
      97: i2l
      98: lstore        4
     100: goto          118
     103: aload_3
     104: invokevirtual #73                 // Method java/net/Inet6Address.getAddress:()[B
     107: iconst_0
     108: bipush        8
     110: invokestatic  #98                 // Method java/nio/ByteBuffer.wrap:([BII)Ljava/nio/ByteBuffer;
     113: invokevirtual #99                 // Method java/nio/ByteBuffer.getLong:()J
     116: lstore        4
     118: invokestatic  #100                // Method com/google/common/hash/Hashing.murmur3_32:()Lcom/google/common/hash/HashFunction;
     121: lload         4
     123: invokeinterface #101,  3          // InterfaceMethod com/google/common/hash/HashFunction.hashLong:(J)Lcom/google/common/hash/HashCode;
     128: invokevirtual #102                // Method com/google/common/hash/HashCode.asInt:()I
     131: istore        6
     133: iload         6
     135: ldc           #103                // int -536870912
     137: ior
     138: istore        6
     140: iload         6
     142: iconst_m1
     143: if_icmpne     150
     146: bipush        -2
     148: istore        6
     150: iload         6
     152: invokestatic  #104                // Method com/google/common/primitives/Ints.toByteArray:(I)[B
     155: invokestatic  #78                 // Method getInet4Address:([B)Ljava/net/Inet4Address;
     158: areturn

  public static int coerceToInteger(java.net.InetAddress);
    Code:
       0: aload_0
       1: invokestatic  #105                // Method getCoercedIPv4Address:(Ljava/net/InetAddress;)Ljava/net/Inet4Address;
       4: invokevirtual #106                // Method java/net/Inet4Address.getAddress:()[B
       7: invokestatic  #107                // Method com/google/common/io/ByteStreams.newDataInput:([B)Lcom/google/common/io/ByteArrayDataInput;
      10: invokeinterface #108,  1          // InterfaceMethod com/google/common/io/ByteArrayDataInput.readInt:()I
      15: ireturn

  public static java.net.Inet4Address fromInteger(int);
    Code:
       0: iload_0
       1: invokestatic  #104                // Method com/google/common/primitives/Ints.toByteArray:(I)[B
       4: invokestatic  #78                 // Method getInet4Address:([B)Ljava/net/Inet4Address;
       7: areturn

  public static java.net.InetAddress fromLittleEndianByteArray(byte[]) throws java.net.UnknownHostException;
    Code:
       0: aload_0
       1: arraylength
       2: newarray       byte
       4: astore_1
       5: iconst_0
       6: istore_2
       7: iload_2
       8: aload_0
       9: arraylength
      10: if_icmpge     30
      13: aload_1
      14: iload_2
      15: aload_0
      16: aload_0
      17: arraylength
      18: iload_2
      19: isub
      20: iconst_1
      21: isub
      22: baload
      23: bastore
      24: iinc          2, 1
      27: goto          7
      30: aload_1
      31: invokestatic  #50                 // Method java/net/InetAddress.getByAddress:([B)Ljava/net/InetAddress;
      34: areturn

  public static java.net.InetAddress decrement(java.net.InetAddress);
    Code:
       0: aload_0
       1: invokevirtual #58                 // Method java/net/InetAddress.getAddress:()[B
       4: astore_1
       5: aload_1
       6: arraylength
       7: iconst_1
       8: isub
       9: istore_2
      10: iload_2
      11: iflt          30
      14: aload_1
      15: iload_2
      16: baload
      17: ifne          30
      20: aload_1
      21: iload_2
      22: iconst_m1
      23: bastore
      24: iinc          2, -1
      27: goto          10
      30: iload_2
      31: iflt          38
      34: iconst_1
      35: goto          39
      38: iconst_0
      39: ldc           #109                // String Decrementing %s would wrap.
      41: aload_0
      42: invokestatic  #76                 // Method com/google/common/base/Preconditions.checkArgument:(ZLjava/lang/String;Ljava/lang/Object;)V
      45: aload_1
      46: iload_2
      47: dup2
      48: baload
      49: iconst_1
      50: isub
      51: i2b
      52: bastore
      53: aload_1
      54: invokestatic  #5                  // Method bytesToInetAddress:([B)Ljava/net/InetAddress;
      57: areturn

  public static java.net.InetAddress increment(java.net.InetAddress);
    Code:
       0: aload_0
       1: invokevirtual #58                 // Method java/net/InetAddress.getAddress:()[B
       4: astore_1
       5: aload_1
       6: arraylength
       7: iconst_1
       8: isub
       9: istore_2
      10: iload_2
      11: iflt          31
      14: aload_1
      15: iload_2
      16: baload
      17: iconst_m1
      18: if_icmpne     31
      21: aload_1
      22: iload_2
      23: iconst_0
      24: bastore
      25: iinc          2, -1
      28: goto          10
      31: iload_2
      32: iflt          39
      35: iconst_1
      36: goto          40
      39: iconst_0
      40: ldc           #110                // String Incrementing %s would wrap.
      42: aload_0
      43: invokestatic  #76                 // Method com/google/common/base/Preconditions.checkArgument:(ZLjava/lang/String;Ljava/lang/Object;)V
      46: aload_1
      47: iload_2
      48: dup2
      49: baload
      50: iconst_1
      51: iadd
      52: i2b
      53: bastore
      54: aload_1
      55: invokestatic  #5                  // Method bytesToInetAddress:([B)Ljava/net/InetAddress;
      58: areturn

  public static boolean isMaximum(java.net.InetAddress);
    Code:
       0: aload_0
       1: invokevirtual #58                 // Method java/net/InetAddress.getAddress:()[B
       4: astore_1
       5: iconst_0
       6: istore_2
       7: iload_2
       8: aload_1
       9: arraylength
      10: if_icmpge     28
      13: aload_1
      14: iload_2
      15: baload
      16: iconst_m1
      17: if_icmpeq     22
      20: iconst_0
      21: ireturn
      22: iinc          2, 1
      25: goto          7
      28: iconst_1
      29: ireturn

  static java.net.Inet4Address access$000();
    Code:
       0: getstatic     #1                  // Field ANY4:Ljava/net/Inet4Address;
       3: areturn

  static {};
    Code:
       0: bipush        46
       2: invokestatic  #115                // Method com/google/common/base/Splitter.on:(C)Lcom/google/common/base/Splitter;
       5: iconst_4
       6: invokevirtual #116                // Method com/google/common/base/Splitter.limit:(I)Lcom/google/common/base/Splitter;
       9: putstatic     #18                 // Field IPV4_SPLITTER:Lcom/google/common/base/Splitter;
      12: bipush        58
      14: invokestatic  #115                // Method com/google/common/base/Splitter.on:(C)Lcom/google/common/base/Splitter;
      17: bipush        10
      19: invokevirtual #116                // Method com/google/common/base/Splitter.limit:(I)Lcom/google/common/base/Splitter;
      22: putstatic     #26                 // Field IPV6_SPLITTER:Lcom/google/common/base/Splitter;
      25: ldc           #117                // String 127.0.0.1
      27: invokestatic  #118                // Method forString:(Ljava/lang/String;)Ljava/net/InetAddress;
      30: checkcast     #6                  // class java/net/Inet4Address
      33: putstatic     #94                 // Field LOOPBACK4:Ljava/net/Inet4Address;
      36: ldc           #119                // String 0.0.0.0
      38: invokestatic  #118                // Method forString:(Ljava/lang/String;)Ljava/net/InetAddress;
      41: checkcast     #6                  // class java/net/Inet4Address
      44: putstatic     #1                  // Field ANY4:Ljava/net/Inet4Address;
      47: return
}
