Compiled from "Multimaps.java"
public final class com.google.common.collect.Multimaps {
  public static <T, K, V, M extends com.google.common.collect.Multimap<K, V>> java.util.stream.Collector<T, ?, M> toMultimap(java.util.function.Function<? super T, ? extends K>, java.util.function.Function<? super T, ? extends V>, java.util.function.Supplier<M>);
    Code:
       0: aload_0
       1: invokestatic  #4                  // Method com/google/common/base/Preconditions.checkNotNull:(Ljava/lang/Object;)Ljava/lang/Object;
       4: pop
       5: aload_1
       6: invokestatic  #4                  // Method com/google/common/base/Preconditions.checkNotNull:(Ljava/lang/Object;)Ljava/lang/Object;
       9: pop
      10: aload_2
      11: invokestatic  #4                  // Method com/google/common/base/Preconditions.checkNotNull:(Ljava/lang/Object;)Ljava/lang/Object;
      14: pop
      15: aload_2
      16: aload_0
      17: aload_1
      18: invokedynamic #5,  0              // InvokeDynamic #0:accept:(Ljava/util/function/Function;Ljava/util/function/Function;)Ljava/util/function/BiConsumer;
      23: invokedynamic #6,  0              // InvokeDynamic #1:apply:()Ljava/util/function/BinaryOperator;
      28: iconst_0
      29: anewarray     #7                  // class java/util/stream/Collector$Characteristics
      32: invokestatic  #8                  // InterfaceMethod java/util/stream/Collector.of:(Ljava/util/function/Supplier;Ljava/util/function/BiConsumer;Ljava/util/function/BinaryOperator;[Ljava/util/stream/Collector$Characteristics;)Ljava/util/stream/Collector;
      35: areturn

  public static <T, K, V, M extends com.google.common.collect.Multimap<K, V>> java.util.stream.Collector<T, ?, M> flatteningToMultimap(java.util.function.Function<? super T, ? extends K>, java.util.function.Function<? super T, ? extends java.util.stream.Stream<? extends V>>, java.util.function.Supplier<M>);
    Code:
       0: aload_0
       1: invokestatic  #4                  // Method com/google/common/base/Preconditions.checkNotNull:(Ljava/lang/Object;)Ljava/lang/Object;
       4: pop
       5: aload_1
       6: invokestatic  #4                  // Method com/google/common/base/Preconditions.checkNotNull:(Ljava/lang/Object;)Ljava/lang/Object;
       9: pop
      10: aload_2
      11: invokestatic  #4                  // Method com/google/common/base/Preconditions.checkNotNull:(Ljava/lang/Object;)Ljava/lang/Object;
      14: pop
      15: aload_2
      16: aload_0
      17: aload_1
      18: invokedynamic #9,  0              // InvokeDynamic #2:accept:(Ljava/util/function/Function;Ljava/util/function/Function;)Ljava/util/function/BiConsumer;
      23: invokedynamic #10,  0             // InvokeDynamic #3:apply:()Ljava/util/function/BinaryOperator;
      28: iconst_0
      29: anewarray     #7                  // class java/util/stream/Collector$Characteristics
      32: invokestatic  #8                  // InterfaceMethod java/util/stream/Collector.of:(Ljava/util/function/Supplier;Ljava/util/function/BiConsumer;Ljava/util/function/BinaryOperator;[Ljava/util/stream/Collector$Characteristics;)Ljava/util/stream/Collector;
      35: areturn

  public static <K, V> com.google.common.collect.Multimap<K, V> newMultimap(java.util.Map<K, java.util.Collection<V>>, com.google.common.base.Supplier<? extends java.util.Collection<V>>);
    Code:
       0: new           #11                 // class com/google/common/collect/Multimaps$CustomMultimap
       3: dup
       4: aload_0
       5: aload_1
       6: invokespecial #12                 // Method com/google/common/collect/Multimaps$CustomMultimap."<init>":(Ljava/util/Map;Lcom/google/common/base/Supplier;)V
       9: areturn

  public static <K, V> com.google.common.collect.ListMultimap<K, V> newListMultimap(java.util.Map<K, java.util.Collection<V>>, com.google.common.base.Supplier<? extends java.util.List<V>>);
    Code:
       0: new           #13                 // class com/google/common/collect/Multimaps$CustomListMultimap
       3: dup
       4: aload_0
       5: aload_1
       6: invokespecial #14                 // Method com/google/common/collect/Multimaps$CustomListMultimap."<init>":(Ljava/util/Map;Lcom/google/common/base/Supplier;)V
       9: areturn

  public static <K, V> com.google.common.collect.SetMultimap<K, V> newSetMultimap(java.util.Map<K, java.util.Collection<V>>, com.google.common.base.Supplier<? extends java.util.Set<V>>);
    Code:
       0: new           #15                 // class com/google/common/collect/Multimaps$CustomSetMultimap
       3: dup
       4: aload_0
       5: aload_1
       6: invokespecial #16                 // Method com/google/common/collect/Multimaps$CustomSetMultimap."<init>":(Ljava/util/Map;Lcom/google/common/base/Supplier;)V
       9: areturn

  public static <K, V> com.google.common.collect.SortedSetMultimap<K, V> newSortedSetMultimap(java.util.Map<K, java.util.Collection<V>>, com.google.common.base.Supplier<? extends java.util.SortedSet<V>>);
    Code:
       0: new           #17                 // class com/google/common/collect/Multimaps$CustomSortedSetMultimap
       3: dup
       4: aload_0
       5: aload_1
       6: invokespecial #18                 // Method com/google/common/collect/Multimaps$CustomSortedSetMultimap."<init>":(Ljava/util/Map;Lcom/google/common/base/Supplier;)V
       9: areturn

  public static <K, V, M extends com.google.common.collect.Multimap<K, V>> M invertFrom(com.google.common.collect.Multimap<? extends V, ? extends K>, M);
    Code:
       0: aload_1
       1: invokestatic  #4                  // Method com/google/common/base/Preconditions.checkNotNull:(Ljava/lang/Object;)Ljava/lang/Object;
       4: pop
       5: aload_0
       6: invokeinterface #19,  1           // InterfaceMethod com/google/common/collect/Multimap.entries:()Ljava/util/Collection;
      11: invokeinterface #20,  1           // InterfaceMethod java/util/Collection.iterator:()Ljava/util/Iterator;
      16: astore_2
      17: aload_2
      18: invokeinterface #21,  1           // InterfaceMethod java/util/Iterator.hasNext:()Z
      23: ifeq          58
      26: aload_2
      27: invokeinterface #22,  1           // InterfaceMethod java/util/Iterator.next:()Ljava/lang/Object;
      32: checkcast     #23                 // class java/util/Map$Entry
      35: astore_3
      36: aload_1
      37: aload_3
      38: invokeinterface #24,  1           // InterfaceMethod java/util/Map$Entry.getValue:()Ljava/lang/Object;
      43: aload_3
      44: invokeinterface #25,  1           // InterfaceMethod java/util/Map$Entry.getKey:()Ljava/lang/Object;
      49: invokeinterface #26,  3           // InterfaceMethod com/google/common/collect/Multimap.put:(Ljava/lang/Object;Ljava/lang/Object;)Z
      54: pop
      55: goto          17
      58: aload_1
      59: areturn

  public static <K, V> com.google.common.collect.Multimap<K, V> synchronizedMultimap(com.google.common.collect.Multimap<K, V>);
    Code:
       0: aload_0
       1: aconst_null
       2: invokestatic  #27                 // Method com/google/common/collect/Synchronized.multimap:(Lcom/google/common/collect/Multimap;Ljava/lang/Object;)Lcom/google/common/collect/Multimap;
       5: areturn

  public static <K, V> com.google.common.collect.Multimap<K, V> unmodifiableMultimap(com.google.common.collect.Multimap<K, V>);
    Code:
       0: aload_0
       1: instanceof    #28                 // class com/google/common/collect/Multimaps$UnmodifiableMultimap
       4: ifne          14
       7: aload_0
       8: instanceof    #29                 // class com/google/common/collect/ImmutableMultimap
      11: ifeq          16
      14: aload_0
      15: areturn
      16: new           #28                 // class com/google/common/collect/Multimaps$UnmodifiableMultimap
      19: dup
      20: aload_0
      21: invokespecial #30                 // Method com/google/common/collect/Multimaps$UnmodifiableMultimap."<init>":(Lcom/google/common/collect/Multimap;)V
      24: areturn

  public static <K, V> com.google.common.collect.Multimap<K, V> unmodifiableMultimap(com.google.common.collect.ImmutableMultimap<K, V>);
    Code:
       0: aload_0
       1: invokestatic  #4                  // Method com/google/common/base/Preconditions.checkNotNull:(Ljava/lang/Object;)Ljava/lang/Object;
       4: checkcast     #31                 // class com/google/common/collect/Multimap
       7: areturn

  public static <K, V> com.google.common.collect.SetMultimap<K, V> synchronizedSetMultimap(com.google.common.collect.SetMultimap<K, V>);
    Code:
       0: aload_0
       1: aconst_null
       2: invokestatic  #32                 // Method com/google/common/collect/Synchronized.setMultimap:(Lcom/google/common/collect/SetMultimap;Ljava/lang/Object;)Lcom/google/common/collect/SetMultimap;
       5: areturn

  public static <K, V> com.google.common.collect.SetMultimap<K, V> unmodifiableSetMultimap(com.google.common.collect.SetMultimap<K, V>);
    Code:
       0: aload_0
       1: instanceof    #33                 // class com/google/common/collect/Multimaps$UnmodifiableSetMultimap
       4: ifne          14
       7: aload_0
       8: instanceof    #34                 // class com/google/common/collect/ImmutableSetMultimap
      11: ifeq          16
      14: aload_0
      15: areturn
      16: new           #33                 // class com/google/common/collect/Multimaps$UnmodifiableSetMultimap
      19: dup
      20: aload_0
      21: invokespecial #35                 // Method com/google/common/collect/Multimaps$UnmodifiableSetMultimap."<init>":(Lcom/google/common/collect/SetMultimap;)V
      24: areturn

  public static <K, V> com.google.common.collect.SetMultimap<K, V> unmodifiableSetMultimap(com.google.common.collect.ImmutableSetMultimap<K, V>);
    Code:
       0: aload_0
       1: invokestatic  #4                  // Method com/google/common/base/Preconditions.checkNotNull:(Ljava/lang/Object;)Ljava/lang/Object;
       4: checkcast     #36                 // class com/google/common/collect/SetMultimap
       7: areturn

  public static <K, V> com.google.common.collect.SortedSetMultimap<K, V> synchronizedSortedSetMultimap(com.google.common.collect.SortedSetMultimap<K, V>);
    Code:
       0: aload_0
       1: aconst_null
       2: invokestatic  #37                 // Method com/google/common/collect/Synchronized.sortedSetMultimap:(Lcom/google/common/collect/SortedSetMultimap;Ljava/lang/Object;)Lcom/google/common/collect/SortedSetMultimap;
       5: areturn

  public static <K, V> com.google.common.collect.SortedSetMultimap<K, V> unmodifiableSortedSetMultimap(com.google.common.collect.SortedSetMultimap<K, V>);
    Code:
       0: aload_0
       1: instanceof    #38                 // class com/google/common/collect/Multimaps$UnmodifiableSortedSetMultimap
       4: ifeq          9
       7: aload_0
       8: areturn
       9: new           #38                 // class com/google/common/collect/Multimaps$UnmodifiableSortedSetMultimap
      12: dup
      13: aload_0
      14: invokespecial #39                 // Method com/google/common/collect/Multimaps$UnmodifiableSortedSetMultimap."<init>":(Lcom/google/common/collect/SortedSetMultimap;)V
      17: areturn

  public static <K, V> com.google.common.collect.ListMultimap<K, V> synchronizedListMultimap(com.google.common.collect.ListMultimap<K, V>);
    Code:
       0: aload_0
       1: aconst_null
       2: invokestatic  #40                 // Method com/google/common/collect/Synchronized.listMultimap:(Lcom/google/common/collect/ListMultimap;Ljava/lang/Object;)Lcom/google/common/collect/ListMultimap;
       5: areturn

  public static <K, V> com.google.common.collect.ListMultimap<K, V> unmodifiableListMultimap(com.google.common.collect.ListMultimap<K, V>);
    Code:
       0: aload_0
       1: instanceof    #41                 // class com/google/common/collect/Multimaps$UnmodifiableListMultimap
       4: ifne          14
       7: aload_0
       8: instanceof    #42                 // class com/google/common/collect/ImmutableListMultimap
      11: ifeq          16
      14: aload_0
      15: areturn
      16: new           #41                 // class com/google/common/collect/Multimaps$UnmodifiableListMultimap
      19: dup
      20: aload_0
      21: invokespecial #43                 // Method com/google/common/collect/Multimaps$UnmodifiableListMultimap."<init>":(Lcom/google/common/collect/ListMultimap;)V
      24: areturn

  public static <K, V> com.google.common.collect.ListMultimap<K, V> unmodifiableListMultimap(com.google.common.collect.ImmutableListMultimap<K, V>);
    Code:
       0: aload_0
       1: invokestatic  #4                  // Method com/google/common/base/Preconditions.checkNotNull:(Ljava/lang/Object;)Ljava/lang/Object;
       4: checkcast     #44                 // class com/google/common/collect/ListMultimap
       7: areturn

  public static <K, V> java.util.Map<K, java.util.List<V>> asMap(com.google.common.collect.ListMultimap<K, V>);
    Code:
       0: aload_0
       1: invokeinterface #55,  1           // InterfaceMethod com/google/common/collect/ListMultimap.asMap:()Ljava/util/Map;
       6: areturn

  public static <K, V> java.util.Map<K, java.util.Set<V>> asMap(com.google.common.collect.SetMultimap<K, V>);
    Code:
       0: aload_0
       1: invokeinterface #56,  1           // InterfaceMethod com/google/common/collect/SetMultimap.asMap:()Ljava/util/Map;
       6: areturn

  public static <K, V> java.util.Map<K, java.util.SortedSet<V>> asMap(com.google.common.collect.SortedSetMultimap<K, V>);
    Code:
       0: aload_0
       1: invokeinterface #57,  1           // InterfaceMethod com/google/common/collect/SortedSetMultimap.asMap:()Ljava/util/Map;
       6: areturn

  public static <K, V> java.util.Map<K, java.util.Collection<V>> asMap(com.google.common.collect.Multimap<K, V>);
    Code:
       0: aload_0
       1: invokeinterface #58,  1           // InterfaceMethod com/google/common/collect/Multimap.asMap:()Ljava/util/Map;
       6: areturn

  public static <K, V> com.google.common.collect.SetMultimap<K, V> forMap(java.util.Map<K, V>);
    Code:
       0: new           #59                 // class com/google/common/collect/Multimaps$MapMultimap
       3: dup
       4: aload_0
       5: invokespecial #60                 // Method com/google/common/collect/Multimaps$MapMultimap."<init>":(Ljava/util/Map;)V
       8: areturn

  public static <K, V1, V2> com.google.common.collect.Multimap<K, V2> transformValues(com.google.common.collect.Multimap<K, V1>, com.google.common.base.Function<? super V1, V2>);
    Code:
       0: aload_1
       1: invokestatic  #4                  // Method com/google/common/base/Preconditions.checkNotNull:(Ljava/lang/Object;)Ljava/lang/Object;
       4: pop
       5: aload_1
       6: invokestatic  #61                 // Method com/google/common/collect/Maps.asEntryTransformer:(Lcom/google/common/base/Function;)Lcom/google/common/collect/Maps$EntryTransformer;
       9: astore_2
      10: aload_0
      11: aload_2
      12: invokestatic  #62                 // Method transformEntries:(Lcom/google/common/collect/Multimap;Lcom/google/common/collect/Maps$EntryTransformer;)Lcom/google/common/collect/Multimap;
      15: areturn

  public static <K, V1, V2> com.google.common.collect.ListMultimap<K, V2> transformValues(com.google.common.collect.ListMultimap<K, V1>, com.google.common.base.Function<? super V1, V2>);
    Code:
       0: aload_1
       1: invokestatic  #4                  // Method com/google/common/base/Preconditions.checkNotNull:(Ljava/lang/Object;)Ljava/lang/Object;
       4: pop
       5: aload_1
       6: invokestatic  #61                 // Method com/google/common/collect/Maps.asEntryTransformer:(Lcom/google/common/base/Function;)Lcom/google/common/collect/Maps$EntryTransformer;
       9: astore_2
      10: aload_0
      11: aload_2
      12: invokestatic  #63                 // Method transformEntries:(Lcom/google/common/collect/ListMultimap;Lcom/google/common/collect/Maps$EntryTransformer;)Lcom/google/common/collect/ListMultimap;
      15: areturn

  public static <K, V1, V2> com.google.common.collect.Multimap<K, V2> transformEntries(com.google.common.collect.Multimap<K, V1>, com.google.common.collect.Maps$EntryTransformer<? super K, ? super V1, V2>);
    Code:
       0: new           #64                 // class com/google/common/collect/Multimaps$TransformedEntriesMultimap
       3: dup
       4: aload_0
       5: aload_1
       6: invokespecial #65                 // Method com/google/common/collect/Multimaps$TransformedEntriesMultimap."<init>":(Lcom/google/common/collect/Multimap;Lcom/google/common/collect/Maps$EntryTransformer;)V
       9: areturn

  public static <K, V1, V2> com.google.common.collect.ListMultimap<K, V2> transformEntries(com.google.common.collect.ListMultimap<K, V1>, com.google.common.collect.Maps$EntryTransformer<? super K, ? super V1, V2>);
    Code:
       0: new           #66                 // class com/google/common/collect/Multimaps$TransformedEntriesListMultimap
       3: dup
       4: aload_0
       5: aload_1
       6: invokespecial #67                 // Method com/google/common/collect/Multimaps$TransformedEntriesListMultimap."<init>":(Lcom/google/common/collect/ListMultimap;Lcom/google/common/collect/Maps$EntryTransformer;)V
       9: areturn

  public static <K, V> com.google.common.collect.ImmutableListMultimap<K, V> index(java.lang.Iterable<V>, com.google.common.base.Function<? super V, K>);
    Code:
       0: aload_0
       1: invokeinterface #68,  1           // InterfaceMethod java/lang/Iterable.iterator:()Ljava/util/Iterator;
       6: aload_1
       7: invokestatic  #69                 // Method index:(Ljava/util/Iterator;Lcom/google/common/base/Function;)Lcom/google/common/collect/ImmutableListMultimap;
      10: areturn

  public static <K, V> com.google.common.collect.ImmutableListMultimap<K, V> index(java.util.Iterator<V>, com.google.common.base.Function<? super V, K>);
    Code:
       0: aload_1
       1: invokestatic  #4                  // Method com/google/common/base/Preconditions.checkNotNull:(Ljava/lang/Object;)Ljava/lang/Object;
       4: pop
       5: invokestatic  #70                 // Method com/google/common/collect/ImmutableListMultimap.builder:()Lcom/google/common/collect/ImmutableListMultimap$Builder;
       8: astore_2
       9: aload_0
      10: invokeinterface #21,  1           // InterfaceMethod java/util/Iterator.hasNext:()Z
      15: ifeq          47
      18: aload_0
      19: invokeinterface #22,  1           // InterfaceMethod java/util/Iterator.next:()Ljava/lang/Object;
      24: astore_3
      25: aload_3
      26: aload_0
      27: invokestatic  #71                 // Method com/google/common/base/Preconditions.checkNotNull:(Ljava/lang/Object;Ljava/lang/Object;)Ljava/lang/Object;
      30: pop
      31: aload_2
      32: aload_1
      33: aload_3
      34: invokeinterface #72,  2           // InterfaceMethod com/google/common/base/Function.apply:(Ljava/lang/Object;)Ljava/lang/Object;
      39: aload_3
      40: invokevirtual #73                 // Method com/google/common/collect/ImmutableListMultimap$Builder.put:(Ljava/lang/Object;Ljava/lang/Object;)Lcom/google/common/collect/ImmutableListMultimap$Builder;
      43: pop
      44: goto          9
      47: aload_2
      48: invokevirtual #74                 // Method com/google/common/collect/ImmutableListMultimap$Builder.build:()Lcom/google/common/collect/ImmutableListMultimap;
      51: areturn

  public static <K, V> com.google.common.collect.Multimap<K, V> filterKeys(com.google.common.collect.Multimap<K, V>, com.google.common.base.Predicate<? super K>);
    Code:
       0: aload_0
       1: instanceof    #36                 // class com/google/common/collect/SetMultimap
       4: ifeq          16
       7: aload_0
       8: checkcast     #36                 // class com/google/common/collect/SetMultimap
      11: aload_1
      12: invokestatic  #75                 // Method filterKeys:(Lcom/google/common/collect/SetMultimap;Lcom/google/common/base/Predicate;)Lcom/google/common/collect/SetMultimap;
      15: areturn
      16: aload_0
      17: instanceof    #44                 // class com/google/common/collect/ListMultimap
      20: ifeq          32
      23: aload_0
      24: checkcast     #44                 // class com/google/common/collect/ListMultimap
      27: aload_1
      28: invokestatic  #76                 // Method filterKeys:(Lcom/google/common/collect/ListMultimap;Lcom/google/common/base/Predicate;)Lcom/google/common/collect/ListMultimap;
      31: areturn
      32: aload_0
      33: instanceof    #77                 // class com/google/common/collect/FilteredKeyMultimap
      36: ifeq          64
      39: aload_0
      40: checkcast     #77                 // class com/google/common/collect/FilteredKeyMultimap
      43: astore_2
      44: new           #77                 // class com/google/common/collect/FilteredKeyMultimap
      47: dup
      48: aload_2
      49: getfield      #78                 // Field com/google/common/collect/FilteredKeyMultimap.unfiltered:Lcom/google/common/collect/Multimap;
      52: aload_2
      53: getfield      #79                 // Field com/google/common/collect/FilteredKeyMultimap.keyPredicate:Lcom/google/common/base/Predicate;
      56: aload_1
      57: invokestatic  #80                 // Method com/google/common/base/Predicates.and:(Lcom/google/common/base/Predicate;Lcom/google/common/base/Predicate;)Lcom/google/common/base/Predicate;
      60: invokespecial #81                 // Method com/google/common/collect/FilteredKeyMultimap."<init>":(Lcom/google/common/collect/Multimap;Lcom/google/common/base/Predicate;)V
      63: areturn
      64: aload_0
      65: instanceof    #82                 // class com/google/common/collect/FilteredMultimap
      68: ifeq          85
      71: aload_0
      72: checkcast     #82                 // class com/google/common/collect/FilteredMultimap
      75: astore_2
      76: aload_2
      77: aload_1
      78: invokestatic  #83                 // Method com/google/common/collect/Maps.keyPredicateOnEntries:(Lcom/google/common/base/Predicate;)Lcom/google/common/base/Predicate;
      81: invokestatic  #84                 // Method filterFiltered:(Lcom/google/common/collect/FilteredMultimap;Lcom/google/common/base/Predicate;)Lcom/google/common/collect/Multimap;
      84: areturn
      85: new           #77                 // class com/google/common/collect/FilteredKeyMultimap
      88: dup
      89: aload_0
      90: aload_1
      91: invokespecial #81                 // Method com/google/common/collect/FilteredKeyMultimap."<init>":(Lcom/google/common/collect/Multimap;Lcom/google/common/base/Predicate;)V
      94: areturn

  public static <K, V> com.google.common.collect.SetMultimap<K, V> filterKeys(com.google.common.collect.SetMultimap<K, V>, com.google.common.base.Predicate<? super K>);
    Code:
       0: aload_0
       1: instanceof    #85                 // class com/google/common/collect/FilteredKeySetMultimap
       4: ifeq          32
       7: aload_0
       8: checkcast     #85                 // class com/google/common/collect/FilteredKeySetMultimap
      11: astore_2
      12: new           #85                 // class com/google/common/collect/FilteredKeySetMultimap
      15: dup
      16: aload_2
      17: invokevirtual #86                 // Method com/google/common/collect/FilteredKeySetMultimap.unfiltered:()Lcom/google/common/collect/SetMultimap;
      20: aload_2
      21: getfield      #87                 // Field com/google/common/collect/FilteredKeySetMultimap.keyPredicate:Lcom/google/common/base/Predicate;
      24: aload_1
      25: invokestatic  #80                 // Method com/google/common/base/Predicates.and:(Lcom/google/common/base/Predicate;Lcom/google/common/base/Predicate;)Lcom/google/common/base/Predicate;
      28: invokespecial #88                 // Method com/google/common/collect/FilteredKeySetMultimap."<init>":(Lcom/google/common/collect/SetMultimap;Lcom/google/common/base/Predicate;)V
      31: areturn
      32: aload_0
      33: instanceof    #89                 // class com/google/common/collect/FilteredSetMultimap
      36: ifeq          53
      39: aload_0
      40: checkcast     #89                 // class com/google/common/collect/FilteredSetMultimap
      43: astore_2
      44: aload_2
      45: aload_1
      46: invokestatic  #83                 // Method com/google/common/collect/Maps.keyPredicateOnEntries:(Lcom/google/common/base/Predicate;)Lcom/google/common/base/Predicate;
      49: invokestatic  #90                 // Method filterFiltered:(Lcom/google/common/collect/FilteredSetMultimap;Lcom/google/common/base/Predicate;)Lcom/google/common/collect/SetMultimap;
      52: areturn
      53: new           #85                 // class com/google/common/collect/FilteredKeySetMultimap
      56: dup
      57: aload_0
      58: aload_1
      59: invokespecial #88                 // Method com/google/common/collect/FilteredKeySetMultimap."<init>":(Lcom/google/common/collect/SetMultimap;Lcom/google/common/base/Predicate;)V
      62: areturn

  public static <K, V> com.google.common.collect.ListMultimap<K, V> filterKeys(com.google.common.collect.ListMultimap<K, V>, com.google.common.base.Predicate<? super K>);
    Code:
       0: aload_0
       1: instanceof    #91                 // class com/google/common/collect/FilteredKeyListMultimap
       4: ifeq          32
       7: aload_0
       8: checkcast     #91                 // class com/google/common/collect/FilteredKeyListMultimap
      11: astore_2
      12: new           #91                 // class com/google/common/collect/FilteredKeyListMultimap
      15: dup
      16: aload_2
      17: invokevirtual #92                 // Method com/google/common/collect/FilteredKeyListMultimap.unfiltered:()Lcom/google/common/collect/ListMultimap;
      20: aload_2
      21: getfield      #93                 // Field com/google/common/collect/FilteredKeyListMultimap.keyPredicate:Lcom/google/common/base/Predicate;
      24: aload_1
      25: invokestatic  #80                 // Method com/google/common/base/Predicates.and:(Lcom/google/common/base/Predicate;Lcom/google/common/base/Predicate;)Lcom/google/common/base/Predicate;
      28: invokespecial #94                 // Method com/google/common/collect/FilteredKeyListMultimap."<init>":(Lcom/google/common/collect/ListMultimap;Lcom/google/common/base/Predicate;)V
      31: areturn
      32: new           #91                 // class com/google/common/collect/FilteredKeyListMultimap
      35: dup
      36: aload_0
      37: aload_1
      38: invokespecial #94                 // Method com/google/common/collect/FilteredKeyListMultimap."<init>":(Lcom/google/common/collect/ListMultimap;Lcom/google/common/base/Predicate;)V
      41: areturn

  public static <K, V> com.google.common.collect.Multimap<K, V> filterValues(com.google.common.collect.Multimap<K, V>, com.google.common.base.Predicate<? super V>);
    Code:
       0: aload_0
       1: aload_1
       2: invokestatic  #95                 // Method com/google/common/collect/Maps.valuePredicateOnEntries:(Lcom/google/common/base/Predicate;)Lcom/google/common/base/Predicate;
       5: invokestatic  #96                 // Method filterEntries:(Lcom/google/common/collect/Multimap;Lcom/google/common/base/Predicate;)Lcom/google/common/collect/Multimap;
       8: areturn

  public static <K, V> com.google.common.collect.SetMultimap<K, V> filterValues(com.google.common.collect.SetMultimap<K, V>, com.google.common.base.Predicate<? super V>);
    Code:
       0: aload_0
       1: aload_1
       2: invokestatic  #95                 // Method com/google/common/collect/Maps.valuePredicateOnEntries:(Lcom/google/common/base/Predicate;)Lcom/google/common/base/Predicate;
       5: invokestatic  #97                 // Method filterEntries:(Lcom/google/common/collect/SetMultimap;Lcom/google/common/base/Predicate;)Lcom/google/common/collect/SetMultimap;
       8: areturn

  public static <K, V> com.google.common.collect.Multimap<K, V> filterEntries(com.google.common.collect.Multimap<K, V>, com.google.common.base.Predicate<? super java.util.Map$Entry<K, V>>);
    Code:
       0: aload_1
       1: invokestatic  #4                  // Method com/google/common/base/Preconditions.checkNotNull:(Ljava/lang/Object;)Ljava/lang/Object;
       4: pop
       5: aload_0
       6: instanceof    #36                 // class com/google/common/collect/SetMultimap
       9: ifeq          21
      12: aload_0
      13: checkcast     #36                 // class com/google/common/collect/SetMultimap
      16: aload_1
      17: invokestatic  #97                 // Method filterEntries:(Lcom/google/common/collect/SetMultimap;Lcom/google/common/base/Predicate;)Lcom/google/common/collect/SetMultimap;
      20: areturn
      21: aload_0
      22: instanceof    #82                 // class com/google/common/collect/FilteredMultimap
      25: ifeq          39
      28: aload_0
      29: checkcast     #82                 // class com/google/common/collect/FilteredMultimap
      32: aload_1
      33: invokestatic  #84                 // Method filterFiltered:(Lcom/google/common/collect/FilteredMultimap;Lcom/google/common/base/Predicate;)Lcom/google/common/collect/Multimap;
      36: goto          54
      39: new           #98                 // class com/google/common/collect/FilteredEntryMultimap
      42: dup
      43: aload_0
      44: invokestatic  #4                  // Method com/google/common/base/Preconditions.checkNotNull:(Ljava/lang/Object;)Ljava/lang/Object;
      47: checkcast     #31                 // class com/google/common/collect/Multimap
      50: aload_1
      51: invokespecial #99                 // Method com/google/common/collect/FilteredEntryMultimap."<init>":(Lcom/google/common/collect/Multimap;Lcom/google/common/base/Predicate;)V
      54: areturn

  public static <K, V> com.google.common.collect.SetMultimap<K, V> filterEntries(com.google.common.collect.SetMultimap<K, V>, com.google.common.base.Predicate<? super java.util.Map$Entry<K, V>>);
    Code:
       0: aload_1
       1: invokestatic  #4                  // Method com/google/common/base/Preconditions.checkNotNull:(Ljava/lang/Object;)Ljava/lang/Object;
       4: pop
       5: aload_0
       6: instanceof    #89                 // class com/google/common/collect/FilteredSetMultimap
       9: ifeq          23
      12: aload_0
      13: checkcast     #89                 // class com/google/common/collect/FilteredSetMultimap
      16: aload_1
      17: invokestatic  #90                 // Method filterFiltered:(Lcom/google/common/collect/FilteredSetMultimap;Lcom/google/common/base/Predicate;)Lcom/google/common/collect/SetMultimap;
      20: goto          38
      23: new           #100                // class com/google/common/collect/FilteredEntrySetMultimap
      26: dup
      27: aload_0
      28: invokestatic  #4                  // Method com/google/common/base/Preconditions.checkNotNull:(Ljava/lang/Object;)Ljava/lang/Object;
      31: checkcast     #36                 // class com/google/common/collect/SetMultimap
      34: aload_1
      35: invokespecial #101                // Method com/google/common/collect/FilteredEntrySetMultimap."<init>":(Lcom/google/common/collect/SetMultimap;Lcom/google/common/base/Predicate;)V
      38: areturn

  static boolean equalsImpl(com.google.common.collect.Multimap<?, ?>, java.lang.Object);
    Code:
       0: aload_1
       1: aload_0
       2: if_acmpne     7
       5: iconst_1
       6: ireturn
       7: aload_1
       8: instanceof    #31                 // class com/google/common/collect/Multimap
      11: ifeq          37
      14: aload_1
      15: checkcast     #31                 // class com/google/common/collect/Multimap
      18: astore_2
      19: aload_0
      20: invokeinterface #58,  1           // InterfaceMethod com/google/common/collect/Multimap.asMap:()Ljava/util/Map;
      25: aload_2
      26: invokeinterface #58,  1           // InterfaceMethod com/google/common/collect/Multimap.asMap:()Ljava/util/Map;
      31: invokeinterface #106,  2          // InterfaceMethod java/util/Map.equals:(Ljava/lang/Object;)Z
      36: ireturn
      37: iconst_0
      38: ireturn

  static java.util.Collection access$000(java.util.Collection);
    Code:
       0: aload_0
       1: invokestatic  #2                  // Method unmodifiableValueCollection:(Ljava/util/Collection;)Ljava/util/Collection;
       4: areturn

  static java.util.Collection access$100(java.util.Collection);
    Code:
       0: aload_0
       1: invokestatic  #1                  // Method unmodifiableEntries:(Ljava/util/Collection;)Ljava/util/Collection;
       4: areturn
}
