Compiled from "Murmur3_128HashFunction.java"
final class com.google.common.hash.Murmur3_128HashFunction$Murmur3_128Hasher extends com.google.common.hash.AbstractStreamingHasher {
  com.google.common.hash.Murmur3_128HashFunction$Murmur3_128Hasher(int);
    Code:
       0: aload_0
       1: bipush        16
       3: invokespecial #2                  // Method com/google/common/hash/AbstractStreamingHasher."<init>":(I)V
       6: aload_0
       7: iload_1
       8: i2l
       9: putfield      #3                  // Field h1:J
      12: aload_0
      13: iload_1
      14: i2l
      15: putfield      #4                  // Field h2:J
      18: aload_0
      19: iconst_0
      20: putfield      #5                  // Field length:I
      23: return

  protected void process(java.nio.ByteBuffer);
    Code:
       0: aload_1
       1: invokevirtual #6                  // Method java/nio/ByteBuffer.getLong:()J
       4: lstore_2
       5: aload_1
       6: invokevirtual #6                  // Method java/nio/ByteBuffer.getLong:()J
       9: lstore        4
      11: aload_0
      12: lload_2
      13: lload         4
      15: invokespecial #7                  // Method bmix64:(JJ)V
      18: aload_0
      19: dup
      20: getfield      #5                  // Field length:I
      23: bipush        16
      25: iadd
      26: putfield      #5                  // Field length:I
      29: return

  protected void processRemaining(java.nio.ByteBuffer);
    Code:
       0: lconst_0
       1: lstore_2
       2: lconst_0
       3: lstore        4
       5: aload_0
       6: dup
       7: getfield      #5                  // Field length:I
      10: aload_1
      11: invokevirtual #17                 // Method java/nio/ByteBuffer.remaining:()I
      14: iadd
      15: putfield      #5                  // Field length:I
      18: aload_1
      19: invokevirtual #17                 // Method java/nio/ByteBuffer.remaining:()I
      22: tableswitch   { // 1 to 15
                     1: 320
                     2: 305
                     3: 290
                     4: 275
                     5: 260
                     6: 245
                     7: 229
                     8: 219
                     9: 204
                    10: 186
                    11: 168
                    12: 150
                    13: 132
                    14: 114
                    15: 96
               default: 335
          }
      96: lload         4
      98: aload_1
      99: bipush        14
     101: invokevirtual #18                 // Method java/nio/ByteBuffer.get:(I)B
     104: invokestatic  #19                 // Method com/google/common/primitives/UnsignedBytes.toInt:(B)I
     107: i2l
     108: bipush        48
     110: lshl
     111: lxor
     112: lstore        4
     114: lload         4
     116: aload_1
     117: bipush        13
     119: invokevirtual #18                 // Method java/nio/ByteBuffer.get:(I)B
     122: invokestatic  #19                 // Method com/google/common/primitives/UnsignedBytes.toInt:(B)I
     125: i2l
     126: bipush        40
     128: lshl
     129: lxor
     130: lstore        4
     132: lload         4
     134: aload_1
     135: bipush        12
     137: invokevirtual #18                 // Method java/nio/ByteBuffer.get:(I)B
     140: invokestatic  #19                 // Method com/google/common/primitives/UnsignedBytes.toInt:(B)I
     143: i2l
     144: bipush        32
     146: lshl
     147: lxor
     148: lstore        4
     150: lload         4
     152: aload_1
     153: bipush        11
     155: invokevirtual #18                 // Method java/nio/ByteBuffer.get:(I)B
     158: invokestatic  #19                 // Method com/google/common/primitives/UnsignedBytes.toInt:(B)I
     161: i2l
     162: bipush        24
     164: lshl
     165: lxor
     166: lstore        4
     168: lload         4
     170: aload_1
     171: bipush        10
     173: invokevirtual #18                 // Method java/nio/ByteBuffer.get:(I)B
     176: invokestatic  #19                 // Method com/google/common/primitives/UnsignedBytes.toInt:(B)I
     179: i2l
     180: bipush        16
     182: lshl
     183: lxor
     184: lstore        4
     186: lload         4
     188: aload_1
     189: bipush        9
     191: invokevirtual #18                 // Method java/nio/ByteBuffer.get:(I)B
     194: invokestatic  #19                 // Method com/google/common/primitives/UnsignedBytes.toInt:(B)I
     197: i2l
     198: bipush        8
     200: lshl
     201: lxor
     202: lstore        4
     204: lload         4
     206: aload_1
     207: bipush        8
     209: invokevirtual #18                 // Method java/nio/ByteBuffer.get:(I)B
     212: invokestatic  #19                 // Method com/google/common/primitives/UnsignedBytes.toInt:(B)I
     215: i2l
     216: lxor
     217: lstore        4
     219: lload_2
     220: aload_1
     221: invokevirtual #6                  // Method java/nio/ByteBuffer.getLong:()J
     224: lxor
     225: lstore_2
     226: goto          345
     229: lload_2
     230: aload_1
     231: bipush        6
     233: invokevirtual #18                 // Method java/nio/ByteBuffer.get:(I)B
     236: invokestatic  #19                 // Method com/google/common/primitives/UnsignedBytes.toInt:(B)I
     239: i2l
     240: bipush        48
     242: lshl
     243: lxor
     244: lstore_2
     245: lload_2
     246: aload_1
     247: iconst_5
     248: invokevirtual #18                 // Method java/nio/ByteBuffer.get:(I)B
     251: invokestatic  #19                 // Method com/google/common/primitives/UnsignedBytes.toInt:(B)I
     254: i2l
     255: bipush        40
     257: lshl
     258: lxor
     259: lstore_2
     260: lload_2
     261: aload_1
     262: iconst_4
     263: invokevirtual #18                 // Method java/nio/ByteBuffer.get:(I)B
     266: invokestatic  #19                 // Method com/google/common/primitives/UnsignedBytes.toInt:(B)I
     269: i2l
     270: bipush        32
     272: lshl
     273: lxor
     274: lstore_2
     275: lload_2
     276: aload_1
     277: iconst_3
     278: invokevirtual #18                 // Method java/nio/ByteBuffer.get:(I)B
     281: invokestatic  #19                 // Method com/google/common/primitives/UnsignedBytes.toInt:(B)I
     284: i2l
     285: bipush        24
     287: lshl
     288: lxor
     289: lstore_2
     290: lload_2
     291: aload_1
     292: iconst_2
     293: invokevirtual #18                 // Method java/nio/ByteBuffer.get:(I)B
     296: invokestatic  #19                 // Method com/google/common/primitives/UnsignedBytes.toInt:(B)I
     299: i2l
     300: bipush        16
     302: lshl
     303: lxor
     304: lstore_2
     305: lload_2
     306: aload_1
     307: iconst_1
     308: invokevirtual #18                 // Method java/nio/ByteBuffer.get:(I)B
     311: invokestatic  #19                 // Method com/google/common/primitives/UnsignedBytes.toInt:(B)I
     314: i2l
     315: bipush        8
     317: lshl
     318: lxor
     319: lstore_2
     320: lload_2
     321: aload_1
     322: iconst_0
     323: invokevirtual #18                 // Method java/nio/ByteBuffer.get:(I)B
     326: invokestatic  #19                 // Method com/google/common/primitives/UnsignedBytes.toInt:(B)I
     329: i2l
     330: lxor
     331: lstore_2
     332: goto          345
     335: new           #20                 // class java/lang/AssertionError
     338: dup
     339: ldc           #21                 // String Should never get here.
     341: invokespecial #22                 // Method java/lang/AssertionError."<init>":(Ljava/lang/Object;)V
     344: athrow
     345: aload_0
     346: dup
     347: getfield      #3                  // Field h1:J
     350: lload_2
     351: invokestatic  #8                  // Method mixK1:(J)J
     354: lxor
     355: putfield      #3                  // Field h1:J
     358: aload_0
     359: dup
     360: getfield      #4                  // Field h2:J
     363: lload         4
     365: invokestatic  #14                 // Method mixK2:(J)J
     368: lxor
     369: putfield      #4                  // Field h2:J
     372: return

  public com.google.common.hash.HashCode makeHash();
    Code:
       0: aload_0
       1: dup
       2: getfield      #3                  // Field h1:J
       5: aload_0
       6: getfield      #5                  // Field length:I
       9: i2l
      10: lxor
      11: putfield      #3                  // Field h1:J
      14: aload_0
      15: dup
      16: getfield      #4                  // Field h2:J
      19: aload_0
      20: getfield      #5                  // Field length:I
      23: i2l
      24: lxor
      25: putfield      #4                  // Field h2:J
      28: aload_0
      29: dup
      30: getfield      #3                  // Field h1:J
      33: aload_0
      34: getfield      #4                  // Field h2:J
      37: ladd
      38: putfield      #3                  // Field h1:J
      41: aload_0
      42: dup
      43: getfield      #4                  // Field h2:J
      46: aload_0
      47: getfield      #3                  // Field h1:J
      50: ladd
      51: putfield      #4                  // Field h2:J
      54: aload_0
      55: aload_0
      56: getfield      #3                  // Field h1:J
      59: invokestatic  #23                 // Method fmix64:(J)J
      62: putfield      #3                  // Field h1:J
      65: aload_0
      66: aload_0
      67: getfield      #4                  // Field h2:J
      70: invokestatic  #23                 // Method fmix64:(J)J
      73: putfield      #4                  // Field h2:J
      76: aload_0
      77: dup
      78: getfield      #3                  // Field h1:J
      81: aload_0
      82: getfield      #4                  // Field h2:J
      85: ladd
      86: putfield      #3                  // Field h1:J
      89: aload_0
      90: dup
      91: getfield      #4                  // Field h2:J
      94: aload_0
      95: getfield      #3                  // Field h1:J
      98: ladd
      99: putfield      #4                  // Field h2:J
     102: bipush        16
     104: newarray       byte
     106: invokestatic  #24                 // Method java/nio/ByteBuffer.wrap:([B)Ljava/nio/ByteBuffer;
     109: getstatic     #25                 // Field java/nio/ByteOrder.LITTLE_ENDIAN:Ljava/nio/ByteOrder;
     112: invokevirtual #26                 // Method java/nio/ByteBuffer.order:(Ljava/nio/ByteOrder;)Ljava/nio/ByteBuffer;
     115: aload_0
     116: getfield      #3                  // Field h1:J
     119: invokevirtual #27                 // Method java/nio/ByteBuffer.putLong:(J)Ljava/nio/ByteBuffer;
     122: aload_0
     123: getfield      #4                  // Field h2:J
     126: invokevirtual #27                 // Method java/nio/ByteBuffer.putLong:(J)Ljava/nio/ByteBuffer;
     129: invokevirtual #28                 // Method java/nio/ByteBuffer.array:()[B
     132: invokestatic  #29                 // Method com/google/common/hash/HashCode.fromBytesNoCopy:([B)Lcom/google/common/hash/HashCode;
     135: areturn
}
