Compiled from "SimpleTimeLimiter.java"
public final class com.google.common.util.concurrent.SimpleTimeLimiter implements com.google.common.util.concurrent.TimeLimiter {
  public static com.google.common.util.concurrent.SimpleTimeLimiter create(java.util.concurrent.ExecutorService);
    Code:
       0: new           #7                  // class com/google/common/util/concurrent/SimpleTimeLimiter
       3: dup
       4: aload_0
       5: invokespecial #8                  // Method "<init>":(Ljava/util/concurrent/ExecutorService;)V
       8: areturn

  public <T> T newProxy(T, java.lang.Class<T>, long, java.util.concurrent.TimeUnit);
    Code:
       0: aload_1
       1: invokestatic  #4                  // Method com/google/common/base/Preconditions.checkNotNull:(Ljava/lang/Object;)Ljava/lang/Object;
       4: pop
       5: aload_2
       6: invokestatic  #4                  // Method com/google/common/base/Preconditions.checkNotNull:(Ljava/lang/Object;)Ljava/lang/Object;
       9: pop
      10: aload         5
      12: invokestatic  #4                  // Method com/google/common/base/Preconditions.checkNotNull:(Ljava/lang/Object;)Ljava/lang/Object;
      15: pop
      16: lload_3
      17: invokestatic  #9                  // Method checkPositiveTimeout:(J)V
      20: aload_2
      21: invokevirtual #10                 // Method java/lang/Class.isInterface:()Z
      24: ldc           #11                 // String interfaceType must be an interface type
      26: invokestatic  #12                 // Method com/google/common/base/Preconditions.checkArgument:(ZLjava/lang/Object;)V
      29: aload_2
      30: invokestatic  #13                 // Method findInterruptibleMethods:(Ljava/lang/Class;)Ljava/util/Set;
      33: astore        6
      35: new           #14                 // class com/google/common/util/concurrent/SimpleTimeLimiter$1
      38: dup
      39: aload_0
      40: aload_1
      41: lload_3
      42: aload         5
      44: aload         6
      46: invokespecial #15                 // Method com/google/common/util/concurrent/SimpleTimeLimiter$1."<init>":(Lcom/google/common/util/concurrent/SimpleTimeLimiter;Ljava/lang/Object;JLjava/util/concurrent/TimeUnit;Ljava/util/Set;)V
      49: astore        7
      51: aload_2
      52: aload         7
      54: invokestatic  #16                 // Method newProxy:(Ljava/lang/Class;Ljava/lang/reflect/InvocationHandler;)Ljava/lang/Object;
      57: areturn

  public <T> T callWithTimeout(java.util.concurrent.Callable<T>, long, java.util.concurrent.TimeUnit) throws java.util.concurrent.TimeoutException, java.lang.InterruptedException, java.util.concurrent.ExecutionException;
    Code:
       0: aload_1
       1: invokestatic  #4                  // Method com/google/common/base/Preconditions.checkNotNull:(Ljava/lang/Object;)Ljava/lang/Object;
       4: pop
       5: aload         4
       7: invokestatic  #4                  // Method com/google/common/base/Preconditions.checkNotNull:(Ljava/lang/Object;)Ljava/lang/Object;
      10: pop
      11: lload_2
      12: invokestatic  #9                  // Method checkPositiveTimeout:(J)V
      15: aload_0
      16: getfield      #6                  // Field executor:Ljava/util/concurrent/ExecutorService;
      19: aload_1
      20: invokeinterface #21,  2           // InterfaceMethod java/util/concurrent/ExecutorService.submit:(Ljava/util/concurrent/Callable;)Ljava/util/concurrent/Future;
      25: astore        5
      27: aload         5
      29: lload_2
      30: aload         4
      32: invokeinterface #22,  4           // InterfaceMethod java/util/concurrent/Future.get:(JLjava/util/concurrent/TimeUnit;)Ljava/lang/Object;
      37: areturn
      38: astore        6
      40: aload         5
      42: iconst_1
      43: invokeinterface #24,  2           // InterfaceMethod java/util/concurrent/Future.cancel:(Z)Z
      48: pop
      49: aload         6
      51: athrow
      52: astore        6
      54: aload_0
      55: aload         6
      57: invokevirtual #30                 // Method java/util/concurrent/ExecutionException.getCause:()Ljava/lang/Throwable;
      60: invokespecial #31                 // Method wrapAndThrowExecutionExceptionOrError:(Ljava/lang/Throwable;)V
      63: new           #32                 // class java/lang/AssertionError
      66: dup
      67: invokespecial #33                 // Method java/lang/AssertionError."<init>":()V
      70: athrow
    Exception table:
       from    to  target type
          27    37    38   Class java/lang/InterruptedException
          27    37    38   Class java/util/concurrent/TimeoutException
          27    37    52   Class java/util/concurrent/ExecutionException

  public <T> T callUninterruptiblyWithTimeout(java.util.concurrent.Callable<T>, long, java.util.concurrent.TimeUnit) throws java.util.concurrent.TimeoutException, java.util.concurrent.ExecutionException;
    Code:
       0: aload_1
       1: invokestatic  #4                  // Method com/google/common/base/Preconditions.checkNotNull:(Ljava/lang/Object;)Ljava/lang/Object;
       4: pop
       5: aload         4
       7: invokestatic  #4                  // Method com/google/common/base/Preconditions.checkNotNull:(Ljava/lang/Object;)Ljava/lang/Object;
      10: pop
      11: lload_2
      12: invokestatic  #9                  // Method checkPositiveTimeout:(J)V
      15: aload_0
      16: getfield      #6                  // Field executor:Ljava/util/concurrent/ExecutorService;
      19: aload_1
      20: invokeinterface #21,  2           // InterfaceMethod java/util/concurrent/ExecutorService.submit:(Ljava/util/concurrent/Callable;)Ljava/util/concurrent/Future;
      25: astore        5
      27: aload         5
      29: lload_2
      30: aload         4
      32: invokestatic  #25                 // Method com/google/common/util/concurrent/Uninterruptibles.getUninterruptibly:(Ljava/util/concurrent/Future;JLjava/util/concurrent/TimeUnit;)Ljava/lang/Object;
      35: areturn
      36: astore        6
      38: aload         5
      40: iconst_1
      41: invokeinterface #24,  2           // InterfaceMethod java/util/concurrent/Future.cancel:(Z)Z
      46: pop
      47: aload         6
      49: athrow
      50: astore        6
      52: aload_0
      53: aload         6
      55: invokevirtual #30                 // Method java/util/concurrent/ExecutionException.getCause:()Ljava/lang/Throwable;
      58: invokespecial #31                 // Method wrapAndThrowExecutionExceptionOrError:(Ljava/lang/Throwable;)V
      61: new           #32                 // class java/lang/AssertionError
      64: dup
      65: invokespecial #33                 // Method java/lang/AssertionError."<init>":()V
      68: athrow
    Exception table:
       from    to  target type
          27    35    36   Class java/util/concurrent/TimeoutException
          27    35    50   Class java/util/concurrent/ExecutionException

  public void runWithTimeout(java.lang.Runnable, long, java.util.concurrent.TimeUnit) throws java.util.concurrent.TimeoutException, java.lang.InterruptedException;
    Code:
       0: aload_1
       1: invokestatic  #4                  // Method com/google/common/base/Preconditions.checkNotNull:(Ljava/lang/Object;)Ljava/lang/Object;
       4: pop
       5: aload         4
       7: invokestatic  #4                  // Method com/google/common/base/Preconditions.checkNotNull:(Ljava/lang/Object;)Ljava/lang/Object;
      10: pop
      11: lload_2
      12: invokestatic  #9                  // Method checkPositiveTimeout:(J)V
      15: aload_0
      16: getfield      #6                  // Field executor:Ljava/util/concurrent/ExecutorService;
      19: aload_1
      20: invokeinterface #34,  2           // InterfaceMethod java/util/concurrent/ExecutorService.submit:(Ljava/lang/Runnable;)Ljava/util/concurrent/Future;
      25: astore        5
      27: aload         5
      29: lload_2
      30: aload         4
      32: invokeinterface #22,  4           // InterfaceMethod java/util/concurrent/Future.get:(JLjava/util/concurrent/TimeUnit;)Ljava/lang/Object;
      37: pop
      38: goto          74
      41: astore        6
      43: aload         5
      45: iconst_1
      46: invokeinterface #24,  2           // InterfaceMethod java/util/concurrent/Future.cancel:(Z)Z
      51: pop
      52: aload         6
      54: athrow
      55: astore        6
      57: aload_0
      58: aload         6
      60: invokevirtual #30                 // Method java/util/concurrent/ExecutionException.getCause:()Ljava/lang/Throwable;
      63: invokespecial #35                 // Method wrapAndThrowRuntimeExecutionExceptionOrError:(Ljava/lang/Throwable;)V
      66: new           #32                 // class java/lang/AssertionError
      69: dup
      70: invokespecial #33                 // Method java/lang/AssertionError."<init>":()V
      73: athrow
      74: return
    Exception table:
       from    to  target type
          27    38    41   Class java/lang/InterruptedException
          27    38    41   Class java/util/concurrent/TimeoutException
          27    38    55   Class java/util/concurrent/ExecutionException

  public void runUninterruptiblyWithTimeout(java.lang.Runnable, long, java.util.concurrent.TimeUnit) throws java.util.concurrent.TimeoutException;
    Code:
       0: aload_1
       1: invokestatic  #4                  // Method com/google/common/base/Preconditions.checkNotNull:(Ljava/lang/Object;)Ljava/lang/Object;
       4: pop
       5: aload         4
       7: invokestatic  #4                  // Method com/google/common/base/Preconditions.checkNotNull:(Ljava/lang/Object;)Ljava/lang/Object;
      10: pop
      11: lload_2
      12: invokestatic  #9                  // Method checkPositiveTimeout:(J)V
      15: aload_0
      16: getfield      #6                  // Field executor:Ljava/util/concurrent/ExecutorService;
      19: aload_1
      20: invokeinterface #34,  2           // InterfaceMethod java/util/concurrent/ExecutorService.submit:(Ljava/lang/Runnable;)Ljava/util/concurrent/Future;
      25: astore        5
      27: aload         5
      29: lload_2
      30: aload         4
      32: invokestatic  #25                 // Method com/google/common/util/concurrent/Uninterruptibles.getUninterruptibly:(Ljava/util/concurrent/Future;JLjava/util/concurrent/TimeUnit;)Ljava/lang/Object;
      35: pop
      36: goto          72
      39: astore        6
      41: aload         5
      43: iconst_1
      44: invokeinterface #24,  2           // InterfaceMethod java/util/concurrent/Future.cancel:(Z)Z
      49: pop
      50: aload         6
      52: athrow
      53: astore        6
      55: aload_0
      56: aload         6
      58: invokevirtual #30                 // Method java/util/concurrent/ExecutionException.getCause:()Ljava/lang/Throwable;
      61: invokespecial #35                 // Method wrapAndThrowRuntimeExecutionExceptionOrError:(Ljava/lang/Throwable;)V
      64: new           #32                 // class java/lang/AssertionError
      67: dup
      68: invokespecial #33                 // Method java/lang/AssertionError."<init>":()V
      71: athrow
      72: return
    Exception table:
       from    to  target type
          27    36    39   Class java/util/concurrent/TimeoutException
          27    36    53   Class java/util/concurrent/ExecutionException

  static java.lang.Exception access$000(java.lang.Exception, boolean) throws java.lang.Exception;
    Code:
       0: aload_0
       1: iload_1
       2: invokestatic  #2                  // Method throwCause:(Ljava/lang/Exception;Z)Ljava/lang/Exception;
       5: areturn

  static java.lang.Object access$100(com.google.common.util.concurrent.SimpleTimeLimiter, java.util.concurrent.Callable, long, java.util.concurrent.TimeUnit, boolean) throws java.lang.Exception;
    Code:
       0: aload_0
       1: aload_1
       2: lload_2
       3: aload         4
       5: iload         5
       7: invokespecial #1                  // Method callWithTimeout:(Ljava/util/concurrent/Callable;JLjava/util/concurrent/TimeUnit;Z)Ljava/lang/Object;
      10: areturn
}
