Compiled from "TreeRangeMap.java"
public final class com.google.common.collect.TreeRangeMap<K extends java.lang.Comparable, V> implements com.google.common.collect.RangeMap<K, V> {
  public static <K extends java.lang.Comparable, V> com.google.common.collect.TreeRangeMap<K, V> create();
    Code:
       0: new           #4                  // class com/google/common/collect/TreeRangeMap
       3: dup
       4: invokespecial #5                  // Method "<init>":()V
       7: areturn

  public V get(K);
    Code:
       0: aload_0
       1: aload_1
       2: invokevirtual #8                  // Method getEntry:(Ljava/lang/Comparable;)Ljava/util/Map$Entry;
       5: astore_2
       6: aload_2
       7: ifnonnull     14
      10: aconst_null
      11: goto          20
      14: aload_2
      15: invokeinterface #9,  1            // InterfaceMethod java/util/Map$Entry.getValue:()Ljava/lang/Object;
      20: areturn

  public java.util.Map$Entry<com.google.common.collect.Range<K>, V> getEntry(K);
    Code:
       0: aload_0
       1: getfield      #3                  // Field entriesByLowerBound:Ljava/util/NavigableMap;
       4: aload_1
       5: invokestatic  #10                 // Method com/google/common/collect/Cut.belowValue:(Ljava/lang/Comparable;)Lcom/google/common/collect/Cut;
       8: invokeinterface #11,  2           // InterfaceMethod java/util/NavigableMap.floorEntry:(Ljava/lang/Object;)Ljava/util/Map$Entry;
      13: astore_2
      14: aload_2
      15: ifnull        44
      18: aload_2
      19: invokeinterface #9,  1            // InterfaceMethod java/util/Map$Entry.getValue:()Ljava/lang/Object;
      24: checkcast     #12                 // class com/google/common/collect/TreeRangeMap$RangeMapEntry
      27: aload_1
      28: invokevirtual #13                 // Method com/google/common/collect/TreeRangeMap$RangeMapEntry.contains:(Ljava/lang/Comparable;)Z
      31: ifeq          44
      34: aload_2
      35: invokeinterface #9,  1            // InterfaceMethod java/util/Map$Entry.getValue:()Ljava/lang/Object;
      40: checkcast     #14                 // class java/util/Map$Entry
      43: areturn
      44: aconst_null
      45: areturn

  public void put(com.google.common.collect.Range<K>, V);
    Code:
       0: aload_1
       1: invokevirtual #15                 // Method com/google/common/collect/Range.isEmpty:()Z
       4: ifne          40
       7: aload_2
       8: invokestatic  #16                 // Method com/google/common/base/Preconditions.checkNotNull:(Ljava/lang/Object;)Ljava/lang/Object;
      11: pop
      12: aload_0
      13: aload_1
      14: invokevirtual #17                 // Method remove:(Lcom/google/common/collect/Range;)V
      17: aload_0
      18: getfield      #3                  // Field entriesByLowerBound:Ljava/util/NavigableMap;
      21: aload_1
      22: getfield      #18                 // Field com/google/common/collect/Range.lowerBound:Lcom/google/common/collect/Cut;
      25: new           #12                 // class com/google/common/collect/TreeRangeMap$RangeMapEntry
      28: dup
      29: aload_1
      30: aload_2
      31: invokespecial #19                 // Method com/google/common/collect/TreeRangeMap$RangeMapEntry."<init>":(Lcom/google/common/collect/Range;Ljava/lang/Object;)V
      34: invokeinterface #20,  3           // InterfaceMethod java/util/NavigableMap.put:(Ljava/lang/Object;Ljava/lang/Object;)Ljava/lang/Object;
      39: pop
      40: return

  public void putCoalescing(com.google.common.collect.Range<K>, V);
    Code:
       0: aload_0
       1: getfield      #3                  // Field entriesByLowerBound:Ljava/util/NavigableMap;
       4: invokeinterface #21,  1           // InterfaceMethod java/util/NavigableMap.isEmpty:()Z
       9: ifeq          19
      12: aload_0
      13: aload_1
      14: aload_2
      15: invokevirtual #22                 // Method put:(Lcom/google/common/collect/Range;Ljava/lang/Object;)V
      18: return
      19: aload_0
      20: aload_1
      21: aload_2
      22: invokestatic  #16                 // Method com/google/common/base/Preconditions.checkNotNull:(Ljava/lang/Object;)Ljava/lang/Object;
      25: invokespecial #2                  // Method coalescedRange:(Lcom/google/common/collect/Range;Ljava/lang/Object;)Lcom/google/common/collect/Range;
      28: astore_3
      29: aload_0
      30: aload_3
      31: aload_2
      32: invokevirtual #22                 // Method put:(Lcom/google/common/collect/Range;Ljava/lang/Object;)V
      35: return

  public void putAll(com.google.common.collect.RangeMap<K, V>);
    Code:
       0: aload_1
       1: invokeinterface #31,  1           // InterfaceMethod com/google/common/collect/RangeMap.asMapOfRanges:()Ljava/util/Map;
       6: invokeinterface #32,  1           // InterfaceMethod java/util/Map.entrySet:()Ljava/util/Set;
      11: invokeinterface #33,  1           // InterfaceMethod java/util/Set.iterator:()Ljava/util/Iterator;
      16: astore_2
      17: aload_2
      18: invokeinterface #34,  1           // InterfaceMethod java/util/Iterator.hasNext:()Z
      23: ifeq          58
      26: aload_2
      27: invokeinterface #35,  1           // InterfaceMethod java/util/Iterator.next:()Ljava/lang/Object;
      32: checkcast     #36                 // class java/util/Map$Entry
      35: astore_3
      36: aload_0
      37: aload_3
      38: invokeinterface #37,  1           // InterfaceMethod java/util/Map$Entry.getKey:()Ljava/lang/Object;
      43: checkcast     #38                 // class com/google/common/collect/Range
      46: aload_3
      47: invokeinterface #9,  1            // InterfaceMethod java/util/Map$Entry.getValue:()Ljava/lang/Object;
      52: invokevirtual #22                 // Method put:(Lcom/google/common/collect/Range;Ljava/lang/Object;)V
      55: goto          17
      58: return

  public void clear();
    Code:
       0: aload_0
       1: getfield      #3                  // Field entriesByLowerBound:Ljava/util/NavigableMap;
       4: invokeinterface #39,  1           // InterfaceMethod java/util/NavigableMap.clear:()V
       9: return

  public com.google.common.collect.Range<K> span();
    Code:
       0: aload_0
       1: getfield      #3                  // Field entriesByLowerBound:Ljava/util/NavigableMap;
       4: invokeinterface #40,  1           // InterfaceMethod java/util/NavigableMap.firstEntry:()Ljava/util/Map$Entry;
       9: astore_1
      10: aload_0
      11: getfield      #3                  // Field entriesByLowerBound:Ljava/util/NavigableMap;
      14: invokeinterface #41,  1           // InterfaceMethod java/util/NavigableMap.lastEntry:()Ljava/util/Map$Entry;
      19: astore_2
      20: aload_1
      21: ifnonnull     32
      24: new           #42                 // class java/util/NoSuchElementException
      27: dup
      28: invokespecial #43                 // Method java/util/NoSuchElementException."<init>":()V
      31: athrow
      32: aload_1
      33: invokeinterface #9,  1            // InterfaceMethod java/util/Map$Entry.getValue:()Ljava/lang/Object;
      38: checkcast     #12                 // class com/google/common/collect/TreeRangeMap$RangeMapEntry
      41: invokevirtual #26                 // Method com/google/common/collect/TreeRangeMap$RangeMapEntry.getKey:()Lcom/google/common/collect/Range;
      44: getfield      #18                 // Field com/google/common/collect/Range.lowerBound:Lcom/google/common/collect/Cut;
      47: aload_2
      48: invokeinterface #9,  1            // InterfaceMethod java/util/Map$Entry.getValue:()Ljava/lang/Object;
      53: checkcast     #12                 // class com/google/common/collect/TreeRangeMap$RangeMapEntry
      56: invokevirtual #26                 // Method com/google/common/collect/TreeRangeMap$RangeMapEntry.getKey:()Lcom/google/common/collect/Range;
      59: getfield      #25                 // Field com/google/common/collect/Range.upperBound:Lcom/google/common/collect/Cut;
      62: invokestatic  #44                 // Method com/google/common/collect/Range.create:(Lcom/google/common/collect/Cut;Lcom/google/common/collect/Cut;)Lcom/google/common/collect/Range;
      65: areturn

  public void remove(com.google.common.collect.Range<K>);
    Code:
       0: aload_1
       1: invokevirtual #15                 // Method com/google/common/collect/Range.isEmpty:()Z
       4: ifeq          8
       7: return
       8: aload_0
       9: getfield      #3                  // Field entriesByLowerBound:Ljava/util/NavigableMap;
      12: aload_1
      13: getfield      #18                 // Field com/google/common/collect/Range.lowerBound:Lcom/google/common/collect/Cut;
      16: invokeinterface #23,  2           // InterfaceMethod java/util/NavigableMap.lowerEntry:(Ljava/lang/Object;)Ljava/util/Map$Entry;
      21: astore_2
      22: aload_2
      23: ifnull        112
      26: aload_2
      27: invokeinterface #9,  1            // InterfaceMethod java/util/Map$Entry.getValue:()Ljava/lang/Object;
      32: checkcast     #12                 // class com/google/common/collect/TreeRangeMap$RangeMapEntry
      35: astore_3
      36: aload_3
      37: invokevirtual #46                 // Method com/google/common/collect/TreeRangeMap$RangeMapEntry.getUpperBound:()Lcom/google/common/collect/Cut;
      40: aload_1
      41: getfield      #18                 // Field com/google/common/collect/Range.lowerBound:Lcom/google/common/collect/Cut;
      44: invokevirtual #47                 // Method com/google/common/collect/Cut.compareTo:(Lcom/google/common/collect/Cut;)I
      47: ifle          112
      50: aload_3
      51: invokevirtual #46                 // Method com/google/common/collect/TreeRangeMap$RangeMapEntry.getUpperBound:()Lcom/google/common/collect/Cut;
      54: aload_1
      55: getfield      #25                 // Field com/google/common/collect/Range.upperBound:Lcom/google/common/collect/Cut;
      58: invokevirtual #47                 // Method com/google/common/collect/Cut.compareTo:(Lcom/google/common/collect/Cut;)I
      61: ifle          88
      64: aload_0
      65: aload_1
      66: getfield      #25                 // Field com/google/common/collect/Range.upperBound:Lcom/google/common/collect/Cut;
      69: aload_3
      70: invokevirtual #46                 // Method com/google/common/collect/TreeRangeMap$RangeMapEntry.getUpperBound:()Lcom/google/common/collect/Cut;
      73: aload_2
      74: invokeinterface #9,  1            // InterfaceMethod java/util/Map$Entry.getValue:()Ljava/lang/Object;
      79: checkcast     #12                 // class com/google/common/collect/TreeRangeMap$RangeMapEntry
      82: invokevirtual #28                 // Method com/google/common/collect/TreeRangeMap$RangeMapEntry.getValue:()Ljava/lang/Object;
      85: invokespecial #48                 // Method putRangeMapEntry:(Lcom/google/common/collect/Cut;Lcom/google/common/collect/Cut;Ljava/lang/Object;)V
      88: aload_0
      89: aload_3
      90: invokevirtual #49                 // Method com/google/common/collect/TreeRangeMap$RangeMapEntry.getLowerBound:()Lcom/google/common/collect/Cut;
      93: aload_1
      94: getfield      #18                 // Field com/google/common/collect/Range.lowerBound:Lcom/google/common/collect/Cut;
      97: aload_2
      98: invokeinterface #9,  1            // InterfaceMethod java/util/Map$Entry.getValue:()Ljava/lang/Object;
     103: checkcast     #12                 // class com/google/common/collect/TreeRangeMap$RangeMapEntry
     106: invokevirtual #28                 // Method com/google/common/collect/TreeRangeMap$RangeMapEntry.getValue:()Ljava/lang/Object;
     109: invokespecial #48                 // Method putRangeMapEntry:(Lcom/google/common/collect/Cut;Lcom/google/common/collect/Cut;Ljava/lang/Object;)V
     112: aload_0
     113: getfield      #3                  // Field entriesByLowerBound:Ljava/util/NavigableMap;
     116: aload_1
     117: getfield      #25                 // Field com/google/common/collect/Range.upperBound:Lcom/google/common/collect/Cut;
     120: invokeinterface #23,  2           // InterfaceMethod java/util/NavigableMap.lowerEntry:(Ljava/lang/Object;)Ljava/util/Map$Entry;
     125: astore_3
     126: aload_3
     127: ifnull        181
     130: aload_3
     131: invokeinterface #9,  1            // InterfaceMethod java/util/Map$Entry.getValue:()Ljava/lang/Object;
     136: checkcast     #12                 // class com/google/common/collect/TreeRangeMap$RangeMapEntry
     139: astore        4
     141: aload         4
     143: invokevirtual #46                 // Method com/google/common/collect/TreeRangeMap$RangeMapEntry.getUpperBound:()Lcom/google/common/collect/Cut;
     146: aload_1
     147: getfield      #25                 // Field com/google/common/collect/Range.upperBound:Lcom/google/common/collect/Cut;
     150: invokevirtual #47                 // Method com/google/common/collect/Cut.compareTo:(Lcom/google/common/collect/Cut;)I
     153: ifle          181
     156: aload_0
     157: aload_1
     158: getfield      #25                 // Field com/google/common/collect/Range.upperBound:Lcom/google/common/collect/Cut;
     161: aload         4
     163: invokevirtual #46                 // Method com/google/common/collect/TreeRangeMap$RangeMapEntry.getUpperBound:()Lcom/google/common/collect/Cut;
     166: aload_3
     167: invokeinterface #9,  1            // InterfaceMethod java/util/Map$Entry.getValue:()Ljava/lang/Object;
     172: checkcast     #12                 // class com/google/common/collect/TreeRangeMap$RangeMapEntry
     175: invokevirtual #28                 // Method com/google/common/collect/TreeRangeMap$RangeMapEntry.getValue:()Ljava/lang/Object;
     178: invokespecial #48                 // Method putRangeMapEntry:(Lcom/google/common/collect/Cut;Lcom/google/common/collect/Cut;Ljava/lang/Object;)V
     181: aload_0
     182: getfield      #3                  // Field entriesByLowerBound:Ljava/util/NavigableMap;
     185: aload_1
     186: getfield      #18                 // Field com/google/common/collect/Range.lowerBound:Lcom/google/common/collect/Cut;
     189: aload_1
     190: getfield      #25                 // Field com/google/common/collect/Range.upperBound:Lcom/google/common/collect/Cut;
     193: invokeinterface #50,  3           // InterfaceMethod java/util/NavigableMap.subMap:(Ljava/lang/Object;Ljava/lang/Object;)Ljava/util/SortedMap;
     198: invokeinterface #51,  1           // InterfaceMethod java/util/SortedMap.clear:()V
     203: return

  public java.util.Map<com.google.common.collect.Range<K>, V> asMapOfRanges();
    Code:
       0: new           #52                 // class com/google/common/collect/TreeRangeMap$AsMapOfRanges
       3: dup
       4: aload_0
       5: aload_0
       6: getfield      #3                  // Field entriesByLowerBound:Ljava/util/NavigableMap;
       9: invokeinterface #53,  1           // InterfaceMethod java/util/NavigableMap.values:()Ljava/util/Collection;
      14: invokespecial #54                 // Method com/google/common/collect/TreeRangeMap$AsMapOfRanges."<init>":(Lcom/google/common/collect/TreeRangeMap;Ljava/lang/Iterable;)V
      17: areturn

  public java.util.Map<com.google.common.collect.Range<K>, V> asDescendingMapOfRanges();
    Code:
       0: new           #52                 // class com/google/common/collect/TreeRangeMap$AsMapOfRanges
       3: dup
       4: aload_0
       5: aload_0
       6: getfield      #3                  // Field entriesByLowerBound:Ljava/util/NavigableMap;
       9: invokeinterface #55,  1           // InterfaceMethod java/util/NavigableMap.descendingMap:()Ljava/util/NavigableMap;
      14: invokeinterface #53,  1           // InterfaceMethod java/util/NavigableMap.values:()Ljava/util/Collection;
      19: invokespecial #54                 // Method com/google/common/collect/TreeRangeMap$AsMapOfRanges."<init>":(Lcom/google/common/collect/TreeRangeMap;Ljava/lang/Iterable;)V
      22: areturn

  public com.google.common.collect.RangeMap<K, V> subRangeMap(com.google.common.collect.Range<K>);
    Code:
       0: aload_1
       1: invokestatic  #56                 // Method com/google/common/collect/Range.all:()Lcom/google/common/collect/Range;
       4: invokevirtual #57                 // Method com/google/common/collect/Range.equals:(Ljava/lang/Object;)Z
       7: ifeq          12
      10: aload_0
      11: areturn
      12: new           #58                 // class com/google/common/collect/TreeRangeMap$SubRangeMap
      15: dup
      16: aload_0
      17: aload_1
      18: invokespecial #59                 // Method com/google/common/collect/TreeRangeMap$SubRangeMap."<init>":(Lcom/google/common/collect/TreeRangeMap;Lcom/google/common/collect/Range;)V
      21: areturn

  public boolean equals(java.lang.Object);
    Code:
       0: aload_1
       1: instanceof    #61                 // class com/google/common/collect/RangeMap
       4: ifeq          28
       7: aload_1
       8: checkcast     #61                 // class com/google/common/collect/RangeMap
      11: astore_2
      12: aload_0
      13: invokevirtual #62                 // Method asMapOfRanges:()Ljava/util/Map;
      16: aload_2
      17: invokeinterface #31,  1           // InterfaceMethod com/google/common/collect/RangeMap.asMapOfRanges:()Ljava/util/Map;
      22: invokeinterface #63,  2           // InterfaceMethod java/util/Map.equals:(Ljava/lang/Object;)Z
      27: ireturn
      28: iconst_0
      29: ireturn

  public int hashCode();
    Code:
       0: aload_0
       1: invokevirtual #62                 // Method asMapOfRanges:()Ljava/util/Map;
       4: invokeinterface #64,  1           // InterfaceMethod java/util/Map.hashCode:()I
       9: ireturn

  public java.lang.String toString();
    Code:
       0: aload_0
       1: getfield      #3                  // Field entriesByLowerBound:Ljava/util/NavigableMap;
       4: invokeinterface #53,  1           // InterfaceMethod java/util/NavigableMap.values:()Ljava/util/Collection;
       9: invokevirtual #65                 // Method java/lang/Object.toString:()Ljava/lang/String;
      12: areturn

  static java.util.NavigableMap access$000(com.google.common.collect.TreeRangeMap);
    Code:
       0: aload_0
       1: getfield      #3                  // Field entriesByLowerBound:Ljava/util/NavigableMap;
       4: areturn

  static com.google.common.collect.Range access$100(com.google.common.collect.TreeRangeMap, com.google.common.collect.Range, java.lang.Object);
    Code:
       0: aload_0
       1: aload_1
       2: aload_2
       3: invokespecial #2                  // Method coalescedRange:(Lcom/google/common/collect/Range;Ljava/lang/Object;)Lcom/google/common/collect/Range;
       6: areturn

  static com.google.common.collect.RangeMap access$200(com.google.common.collect.TreeRangeMap);
    Code:
       0: aload_0
       1: invokespecial #1                  // Method emptySubRangeMap:()Lcom/google/common/collect/RangeMap;
       4: areturn

  static {};
    Code:
       0: new           #66                 // class com/google/common/collect/TreeRangeMap$1
       3: dup
       4: invokespecial #67                 // Method com/google/common/collect/TreeRangeMap$1."<init>":()V
       7: putstatic     #60                 // Field EMPTY_SUB_RANGE_MAP:Lcom/google/common/collect/RangeMap;
      10: return
}
