Compiled from "TreeMultiset.java"
public final class com.google.common.collect.TreeMultiset<E> extends com.google.common.collect.AbstractSortedMultiset<E> implements java.io.Serializable {
  public static <E extends java.lang.Comparable> com.google.common.collect.TreeMultiset<E> create();
    Code:
       0: new           #8                  // class com/google/common/collect/TreeMultiset
       3: dup
       4: invokestatic  #9                  // Method com/google/common/collect/Ordering.natural:()Lcom/google/common/collect/Ordering;
       7: invokespecial #10                 // Method "<init>":(Ljava/util/Comparator;)V
      10: areturn

  public static <E> com.google.common.collect.TreeMultiset<E> create(java.util.Comparator<? super E>);
    Code:
       0: aload_0
       1: ifnonnull     17
       4: new           #8                  // class com/google/common/collect/TreeMultiset
       7: dup
       8: invokestatic  #9                  // Method com/google/common/collect/Ordering.natural:()Lcom/google/common/collect/Ordering;
      11: invokespecial #10                 // Method "<init>":(Ljava/util/Comparator;)V
      14: goto          25
      17: new           #8                  // class com/google/common/collect/TreeMultiset
      20: dup
      21: aload_0
      22: invokespecial #10                 // Method "<init>":(Ljava/util/Comparator;)V
      25: areturn

  public static <E extends java.lang.Comparable> com.google.common.collect.TreeMultiset<E> create(java.lang.Iterable<? extends E>);
    Code:
       0: invokestatic  #11                 // Method create:()Lcom/google/common/collect/TreeMultiset;
       3: astore_1
       4: aload_1
       5: aload_0
       6: invokestatic  #12                 // Method com/google/common/collect/Iterables.addAll:(Ljava/util/Collection;Ljava/lang/Iterable;)Z
       9: pop
      10: aload_1
      11: areturn

  com.google.common.collect.TreeMultiset(com.google.common.collect.TreeMultiset$Reference<com.google.common.collect.TreeMultiset$AvlNode<E>>, com.google.common.collect.GeneralRange<E>, com.google.common.collect.TreeMultiset$AvlNode<E>);
    Code:
       0: aload_0
       1: aload_2
       2: invokevirtual #13                 // Method com/google/common/collect/GeneralRange.comparator:()Ljava/util/Comparator;
       5: invokespecial #14                 // Method com/google/common/collect/AbstractSortedMultiset."<init>":(Ljava/util/Comparator;)V
       8: aload_0
       9: aload_1
      10: putfield      #15                 // Field rootReference:Lcom/google/common/collect/TreeMultiset$Reference;
      13: aload_0
      14: aload_2
      15: putfield      #6                  // Field range:Lcom/google/common/collect/GeneralRange;
      18: aload_0
      19: aload_3
      20: putfield      #4                  // Field header:Lcom/google/common/collect/TreeMultiset$AvlNode;
      23: return

  com.google.common.collect.TreeMultiset(java.util.Comparator<? super E>);
    Code:
       0: aload_0
       1: aload_1
       2: invokespecial #14                 // Method com/google/common/collect/AbstractSortedMultiset."<init>":(Ljava/util/Comparator;)V
       5: aload_0
       6: aload_1
       7: invokestatic  #16                 // Method com/google/common/collect/GeneralRange.all:(Ljava/util/Comparator;)Lcom/google/common/collect/GeneralRange;
      10: putfield      #6                  // Field range:Lcom/google/common/collect/GeneralRange;
      13: aload_0
      14: new           #17                 // class com/google/common/collect/TreeMultiset$AvlNode
      17: dup
      18: aconst_null
      19: iconst_1
      20: invokespecial #18                 // Method com/google/common/collect/TreeMultiset$AvlNode."<init>":(Ljava/lang/Object;I)V
      23: putfield      #4                  // Field header:Lcom/google/common/collect/TreeMultiset$AvlNode;
      26: aload_0
      27: getfield      #4                  // Field header:Lcom/google/common/collect/TreeMultiset$AvlNode;
      30: aload_0
      31: getfield      #4                  // Field header:Lcom/google/common/collect/TreeMultiset$AvlNode;
      34: invokestatic  #1                  // Method successor:(Lcom/google/common/collect/TreeMultiset$AvlNode;Lcom/google/common/collect/TreeMultiset$AvlNode;)V
      37: aload_0
      38: new           #19                 // class com/google/common/collect/TreeMultiset$Reference
      41: dup
      42: aconst_null
      43: invokespecial #20                 // Method com/google/common/collect/TreeMultiset$Reference."<init>":(Lcom/google/common/collect/TreeMultiset$1;)V
      46: putfield      #15                 // Field rootReference:Lcom/google/common/collect/TreeMultiset$Reference;
      49: return

  public int size();
    Code:
       0: aload_0
       1: getstatic     #41                 // Field com/google/common/collect/TreeMultiset$Aggregate.SIZE:Lcom/google/common/collect/TreeMultiset$Aggregate;
       4: invokespecial #42                 // Method aggregateForEntries:(Lcom/google/common/collect/TreeMultiset$Aggregate;)J
       7: invokestatic  #43                 // Method com/google/common/primitives/Ints.saturatedCast:(J)I
      10: ireturn

  int distinctElements();
    Code:
       0: aload_0
       1: getstatic     #44                 // Field com/google/common/collect/TreeMultiset$Aggregate.DISTINCT:Lcom/google/common/collect/TreeMultiset$Aggregate;
       4: invokespecial #42                 // Method aggregateForEntries:(Lcom/google/common/collect/TreeMultiset$Aggregate;)J
       7: invokestatic  #43                 // Method com/google/common/primitives/Ints.saturatedCast:(J)I
      10: ireturn

  static int distinctElements(com.google.common.collect.TreeMultiset$AvlNode<?>);
    Code:
       0: aload_0
       1: ifnonnull     8
       4: iconst_0
       5: goto          12
       8: aload_0
       9: invokestatic  #45                 // Method com/google/common/collect/TreeMultiset$AvlNode.access$400:(Lcom/google/common/collect/TreeMultiset$AvlNode;)I
      12: ireturn

  public int count(java.lang.Object);
    Code:
       0: aload_1
       1: astore_2
       2: aload_0
       3: getfield      #15                 // Field rootReference:Lcom/google/common/collect/TreeMultiset$Reference;
       6: invokevirtual #21                 // Method com/google/common/collect/TreeMultiset$Reference.get:()Ljava/lang/Object;
       9: checkcast     #17                 // class com/google/common/collect/TreeMultiset$AvlNode
      12: astore_3
      13: aload_0
      14: getfield      #6                  // Field range:Lcom/google/common/collect/GeneralRange;
      17: aload_2
      18: invokevirtual #46                 // Method com/google/common/collect/GeneralRange.contains:(Ljava/lang/Object;)Z
      21: ifeq          28
      24: aload_3
      25: ifnonnull     30
      28: iconst_0
      29: ireturn
      30: aload_3
      31: aload_0
      32: invokevirtual #27                 // Method comparator:()Ljava/util/Comparator;
      35: aload_2
      36: invokevirtual #47                 // Method com/google/common/collect/TreeMultiset$AvlNode.count:(Ljava/util/Comparator;Ljava/lang/Object;)I
      39: ireturn
      40: astore_2
      41: iconst_0
      42: ireturn
    Exception table:
       from    to  target type
           0    29    40   Class java/lang/ClassCastException
           0    29    40   Class java/lang/NullPointerException
          30    39    40   Class java/lang/ClassCastException
          30    39    40   Class java/lang/NullPointerException

  public int add(E, int);
    Code:
       0: iload_2
       1: ldc           #50                 // String occurrences
       3: invokestatic  #51                 // Method com/google/common/collect/CollectPreconditions.checkNonnegative:(ILjava/lang/String;)I
       6: pop
       7: iload_2
       8: ifne          17
      11: aload_0
      12: aload_1
      13: invokevirtual #52                 // Method count:(Ljava/lang/Object;)I
      16: ireturn
      17: aload_0
      18: getfield      #6                  // Field range:Lcom/google/common/collect/GeneralRange;
      21: aload_1
      22: invokevirtual #46                 // Method com/google/common/collect/GeneralRange.contains:(Ljava/lang/Object;)Z
      25: invokestatic  #53                 // Method com/google/common/base/Preconditions.checkArgument:(Z)V
      28: aload_0
      29: getfield      #15                 // Field rootReference:Lcom/google/common/collect/TreeMultiset$Reference;
      32: invokevirtual #21                 // Method com/google/common/collect/TreeMultiset$Reference.get:()Ljava/lang/Object;
      35: checkcast     #17                 // class com/google/common/collect/TreeMultiset$AvlNode
      38: astore_3
      39: aload_3
      40: ifnonnull     91
      43: aload_0
      44: invokevirtual #27                 // Method comparator:()Ljava/util/Comparator;
      47: aload_1
      48: aload_1
      49: invokeinterface #30,  3           // InterfaceMethod java/util/Comparator.compare:(Ljava/lang/Object;Ljava/lang/Object;)I
      54: pop
      55: new           #17                 // class com/google/common/collect/TreeMultiset$AvlNode
      58: dup
      59: aload_1
      60: iload_2
      61: invokespecial #18                 // Method com/google/common/collect/TreeMultiset$AvlNode."<init>":(Ljava/lang/Object;I)V
      64: astore        4
      66: aload_0
      67: getfield      #4                  // Field header:Lcom/google/common/collect/TreeMultiset$AvlNode;
      70: aload         4
      72: aload_0
      73: getfield      #4                  // Field header:Lcom/google/common/collect/TreeMultiset$AvlNode;
      76: invokestatic  #2                  // Method successor:(Lcom/google/common/collect/TreeMultiset$AvlNode;Lcom/google/common/collect/TreeMultiset$AvlNode;Lcom/google/common/collect/TreeMultiset$AvlNode;)V
      79: aload_0
      80: getfield      #15                 // Field rootReference:Lcom/google/common/collect/TreeMultiset$Reference;
      83: aload_3
      84: aload         4
      86: invokevirtual #54                 // Method com/google/common/collect/TreeMultiset$Reference.checkAndSet:(Ljava/lang/Object;Ljava/lang/Object;)V
      89: iconst_0
      90: ireturn
      91: iconst_1
      92: newarray       int
      94: astore        4
      96: aload_3
      97: aload_0
      98: invokevirtual #27                 // Method comparator:()Ljava/util/Comparator;
     101: aload_1
     102: iload_2
     103: aload         4
     105: invokevirtual #55                 // Method com/google/common/collect/TreeMultiset$AvlNode.add:(Ljava/util/Comparator;Ljava/lang/Object;I[I)Lcom/google/common/collect/TreeMultiset$AvlNode;
     108: astore        5
     110: aload_0
     111: getfield      #15                 // Field rootReference:Lcom/google/common/collect/TreeMultiset$Reference;
     114: aload_3
     115: aload         5
     117: invokevirtual #54                 // Method com/google/common/collect/TreeMultiset$Reference.checkAndSet:(Ljava/lang/Object;Ljava/lang/Object;)V
     120: aload         4
     122: iconst_0
     123: iaload
     124: ireturn

  public int remove(java.lang.Object, int);
    Code:
       0: iload_2
       1: ldc           #50                 // String occurrences
       3: invokestatic  #51                 // Method com/google/common/collect/CollectPreconditions.checkNonnegative:(ILjava/lang/String;)I
       6: pop
       7: iload_2
       8: ifne          17
      11: aload_0
      12: aload_1
      13: invokevirtual #52                 // Method count:(Ljava/lang/Object;)I
      16: ireturn
      17: aload_0
      18: getfield      #15                 // Field rootReference:Lcom/google/common/collect/TreeMultiset$Reference;
      21: invokevirtual #21                 // Method com/google/common/collect/TreeMultiset$Reference.get:()Ljava/lang/Object;
      24: checkcast     #17                 // class com/google/common/collect/TreeMultiset$AvlNode
      27: astore_3
      28: iconst_1
      29: newarray       int
      31: astore        4
      33: aload_1
      34: astore        6
      36: aload_0
      37: getfield      #6                  // Field range:Lcom/google/common/collect/GeneralRange;
      40: aload         6
      42: invokevirtual #46                 // Method com/google/common/collect/GeneralRange.contains:(Ljava/lang/Object;)Z
      45: ifeq          52
      48: aload_3
      49: ifnonnull     54
      52: iconst_0
      53: ireturn
      54: aload_3
      55: aload_0
      56: invokevirtual #27                 // Method comparator:()Ljava/util/Comparator;
      59: aload         6
      61: iload_2
      62: aload         4
      64: invokevirtual #56                 // Method com/google/common/collect/TreeMultiset$AvlNode.remove:(Ljava/util/Comparator;Ljava/lang/Object;I[I)Lcom/google/common/collect/TreeMultiset$AvlNode;
      67: astore        5
      69: goto          76
      72: astore        6
      74: iconst_0
      75: ireturn
      76: aload_0
      77: getfield      #15                 // Field rootReference:Lcom/google/common/collect/TreeMultiset$Reference;
      80: aload_3
      81: aload         5
      83: invokevirtual #54                 // Method com/google/common/collect/TreeMultiset$Reference.checkAndSet:(Ljava/lang/Object;Ljava/lang/Object;)V
      86: aload         4
      88: iconst_0
      89: iaload
      90: ireturn
    Exception table:
       from    to  target type
          33    53    72   Class java/lang/ClassCastException
          33    53    72   Class java/lang/NullPointerException
          54    69    72   Class java/lang/ClassCastException
          54    69    72   Class java/lang/NullPointerException

  public int setCount(E, int);
    Code:
       0: iload_2
       1: ldc           #57                 // String count
       3: invokestatic  #51                 // Method com/google/common/collect/CollectPreconditions.checkNonnegative:(ILjava/lang/String;)I
       6: pop
       7: aload_0
       8: getfield      #6                  // Field range:Lcom/google/common/collect/GeneralRange;
      11: aload_1
      12: invokevirtual #46                 // Method com/google/common/collect/GeneralRange.contains:(Ljava/lang/Object;)Z
      15: ifne          32
      18: iload_2
      19: ifne          26
      22: iconst_1
      23: goto          27
      26: iconst_0
      27: invokestatic  #53                 // Method com/google/common/base/Preconditions.checkArgument:(Z)V
      30: iconst_0
      31: ireturn
      32: aload_0
      33: getfield      #15                 // Field rootReference:Lcom/google/common/collect/TreeMultiset$Reference;
      36: invokevirtual #21                 // Method com/google/common/collect/TreeMultiset$Reference.get:()Ljava/lang/Object;
      39: checkcast     #17                 // class com/google/common/collect/TreeMultiset$AvlNode
      42: astore_3
      43: aload_3
      44: ifnonnull     60
      47: iload_2
      48: ifle          58
      51: aload_0
      52: aload_1
      53: iload_2
      54: invokevirtual #58                 // Method add:(Ljava/lang/Object;I)I
      57: pop
      58: iconst_0
      59: ireturn
      60: iconst_1
      61: newarray       int
      63: astore        4
      65: aload_3
      66: aload_0
      67: invokevirtual #27                 // Method comparator:()Ljava/util/Comparator;
      70: aload_1
      71: iload_2
      72: aload         4
      74: invokevirtual #59                 // Method com/google/common/collect/TreeMultiset$AvlNode.setCount:(Ljava/util/Comparator;Ljava/lang/Object;I[I)Lcom/google/common/collect/TreeMultiset$AvlNode;
      77: astore        5
      79: aload_0
      80: getfield      #15                 // Field rootReference:Lcom/google/common/collect/TreeMultiset$Reference;
      83: aload_3
      84: aload         5
      86: invokevirtual #54                 // Method com/google/common/collect/TreeMultiset$Reference.checkAndSet:(Ljava/lang/Object;Ljava/lang/Object;)V
      89: aload         4
      91: iconst_0
      92: iaload
      93: ireturn

  public boolean setCount(E, int, int);
    Code:
       0: iload_3
       1: ldc           #60                 // String newCount
       3: invokestatic  #51                 // Method com/google/common/collect/CollectPreconditions.checkNonnegative:(ILjava/lang/String;)I
       6: pop
       7: iload_2
       8: ldc           #61                 // String oldCount
      10: invokestatic  #51                 // Method com/google/common/collect/CollectPreconditions.checkNonnegative:(ILjava/lang/String;)I
      13: pop
      14: aload_0
      15: getfield      #6                  // Field range:Lcom/google/common/collect/GeneralRange;
      18: aload_1
      19: invokevirtual #46                 // Method com/google/common/collect/GeneralRange.contains:(Ljava/lang/Object;)Z
      22: invokestatic  #53                 // Method com/google/common/base/Preconditions.checkArgument:(Z)V
      25: aload_0
      26: getfield      #15                 // Field rootReference:Lcom/google/common/collect/TreeMultiset$Reference;
      29: invokevirtual #21                 // Method com/google/common/collect/TreeMultiset$Reference.get:()Ljava/lang/Object;
      32: checkcast     #17                 // class com/google/common/collect/TreeMultiset$AvlNode
      35: astore        4
      37: aload         4
      39: ifnonnull     61
      42: iload_2
      43: ifne          59
      46: iload_3
      47: ifle          57
      50: aload_0
      51: aload_1
      52: iload_3
      53: invokevirtual #58                 // Method add:(Ljava/lang/Object;I)I
      56: pop
      57: iconst_1
      58: ireturn
      59: iconst_0
      60: ireturn
      61: iconst_1
      62: newarray       int
      64: astore        5
      66: aload         4
      68: aload_0
      69: invokevirtual #27                 // Method comparator:()Ljava/util/Comparator;
      72: aload_1
      73: iload_2
      74: iload_3
      75: aload         5
      77: invokevirtual #62                 // Method com/google/common/collect/TreeMultiset$AvlNode.setCount:(Ljava/util/Comparator;Ljava/lang/Object;II[I)Lcom/google/common/collect/TreeMultiset$AvlNode;
      80: astore        6
      82: aload_0
      83: getfield      #15                 // Field rootReference:Lcom/google/common/collect/TreeMultiset$Reference;
      86: aload         4
      88: aload         6
      90: invokevirtual #54                 // Method com/google/common/collect/TreeMultiset$Reference.checkAndSet:(Ljava/lang/Object;Ljava/lang/Object;)V
      93: aload         5
      95: iconst_0
      96: iaload
      97: iload_2
      98: if_icmpne     105
     101: iconst_1
     102: goto          106
     105: iconst_0
     106: ireturn

  public void clear();
    Code:
       0: aload_0
       1: getfield      #6                  // Field range:Lcom/google/common/collect/GeneralRange;
       4: invokevirtual #23                 // Method com/google/common/collect/GeneralRange.hasLowerBound:()Z
       7: ifne          97
      10: aload_0
      11: getfield      #6                  // Field range:Lcom/google/common/collect/GeneralRange;
      14: invokevirtual #25                 // Method com/google/common/collect/GeneralRange.hasUpperBound:()Z
      17: ifne          97
      20: aload_0
      21: getfield      #4                  // Field header:Lcom/google/common/collect/TreeMultiset$AvlNode;
      24: invokestatic  #63                 // Method com/google/common/collect/TreeMultiset$AvlNode.access$800:(Lcom/google/common/collect/TreeMultiset$AvlNode;)Lcom/google/common/collect/TreeMultiset$AvlNode;
      27: astore_1
      28: aload_1
      29: aload_0
      30: getfield      #4                  // Field header:Lcom/google/common/collect/TreeMultiset$AvlNode;
      33: if_acmpeq     76
      36: aload_1
      37: invokestatic  #63                 // Method com/google/common/collect/TreeMultiset$AvlNode.access$800:(Lcom/google/common/collect/TreeMultiset$AvlNode;)Lcom/google/common/collect/TreeMultiset$AvlNode;
      40: astore_2
      41: aload_1
      42: iconst_0
      43: invokestatic  #64                 // Method com/google/common/collect/TreeMultiset$AvlNode.access$202:(Lcom/google/common/collect/TreeMultiset$AvlNode;I)I
      46: pop
      47: aload_1
      48: aconst_null
      49: invokestatic  #65                 // Method com/google/common/collect/TreeMultiset$AvlNode.access$602:(Lcom/google/common/collect/TreeMultiset$AvlNode;Lcom/google/common/collect/TreeMultiset$AvlNode;)Lcom/google/common/collect/TreeMultiset$AvlNode;
      52: pop
      53: aload_1
      54: aconst_null
      55: invokestatic  #66                 // Method com/google/common/collect/TreeMultiset$AvlNode.access$702:(Lcom/google/common/collect/TreeMultiset$AvlNode;Lcom/google/common/collect/TreeMultiset$AvlNode;)Lcom/google/common/collect/TreeMultiset$AvlNode;
      58: pop
      59: aload_1
      60: aconst_null
      61: invokestatic  #67                 // Method com/google/common/collect/TreeMultiset$AvlNode.access$902:(Lcom/google/common/collect/TreeMultiset$AvlNode;Lcom/google/common/collect/TreeMultiset$AvlNode;)Lcom/google/common/collect/TreeMultiset$AvlNode;
      64: pop
      65: aload_1
      66: aconst_null
      67: invokestatic  #68                 // Method com/google/common/collect/TreeMultiset$AvlNode.access$802:(Lcom/google/common/collect/TreeMultiset$AvlNode;Lcom/google/common/collect/TreeMultiset$AvlNode;)Lcom/google/common/collect/TreeMultiset$AvlNode;
      70: pop
      71: aload_2
      72: astore_1
      73: goto          28
      76: aload_0
      77: getfield      #4                  // Field header:Lcom/google/common/collect/TreeMultiset$AvlNode;
      80: aload_0
      81: getfield      #4                  // Field header:Lcom/google/common/collect/TreeMultiset$AvlNode;
      84: invokestatic  #1                  // Method successor:(Lcom/google/common/collect/TreeMultiset$AvlNode;Lcom/google/common/collect/TreeMultiset$AvlNode;)V
      87: aload_0
      88: getfield      #15                 // Field rootReference:Lcom/google/common/collect/TreeMultiset$Reference;
      91: invokevirtual #69                 // Method com/google/common/collect/TreeMultiset$Reference.clear:()V
      94: goto          104
      97: aload_0
      98: invokevirtual #70                 // Method entryIterator:()Ljava/util/Iterator;
     101: invokestatic  #71                 // Method com/google/common/collect/Iterators.clear:(Ljava/util/Iterator;)V
     104: return

  java.util.Iterator<E> elementIterator();
    Code:
       0: aload_0
       1: invokevirtual #70                 // Method entryIterator:()Ljava/util/Iterator;
       4: invokestatic  #79                 // Method com/google/common/collect/Multisets.elementIterator:(Ljava/util/Iterator;)Ljava/util/Iterator;
       7: areturn

  java.util.Iterator<com.google.common.collect.Multiset$Entry<E>> entryIterator();
    Code:
       0: new           #80                 // class com/google/common/collect/TreeMultiset$2
       3: dup
       4: aload_0
       5: invokespecial #81                 // Method com/google/common/collect/TreeMultiset$2."<init>":(Lcom/google/common/collect/TreeMultiset;)V
       8: areturn

  java.util.Iterator<com.google.common.collect.Multiset$Entry<E>> descendingEntryIterator();
    Code:
       0: new           #82                 // class com/google/common/collect/TreeMultiset$3
       3: dup
       4: aload_0
       5: invokespecial #83                 // Method com/google/common/collect/TreeMultiset$3."<init>":(Lcom/google/common/collect/TreeMultiset;)V
       8: areturn

  public void forEachEntry(java.util.function.ObjIntConsumer<? super E>);
    Code:
       0: aload_1
       1: invokestatic  #84                 // Method com/google/common/base/Preconditions.checkNotNull:(Ljava/lang/Object;)Ljava/lang/Object;
       4: pop
       5: aload_0
       6: invokespecial #7                  // Method firstNode:()Lcom/google/common/collect/TreeMultiset$AvlNode;
       9: astore_2
      10: aload_2
      11: aload_0
      12: getfield      #4                  // Field header:Lcom/google/common/collect/TreeMultiset$AvlNode;
      15: if_acmpeq     58
      18: aload_2
      19: ifnull        58
      22: aload_0
      23: getfield      #6                  // Field range:Lcom/google/common/collect/GeneralRange;
      26: aload_2
      27: invokevirtual #76                 // Method com/google/common/collect/TreeMultiset$AvlNode.getElement:()Ljava/lang/Object;
      30: invokevirtual #85                 // Method com/google/common/collect/GeneralRange.tooHigh:(Ljava/lang/Object;)Z
      33: ifne          58
      36: aload_1
      37: aload_2
      38: invokevirtual #76                 // Method com/google/common/collect/TreeMultiset$AvlNode.getElement:()Ljava/lang/Object;
      41: aload_2
      42: invokevirtual #86                 // Method com/google/common/collect/TreeMultiset$AvlNode.getCount:()I
      45: invokeinterface #87,  3           // InterfaceMethod java/util/function/ObjIntConsumer.accept:(Ljava/lang/Object;I)V
      50: aload_2
      51: invokestatic  #63                 // Method com/google/common/collect/TreeMultiset$AvlNode.access$800:(Lcom/google/common/collect/TreeMultiset$AvlNode;)Lcom/google/common/collect/TreeMultiset$AvlNode;
      54: astore_2
      55: goto          10
      58: return

  public java.util.Iterator<E> iterator();
    Code:
       0: aload_0
       1: invokestatic  #88                 // Method com/google/common/collect/Multisets.iteratorImpl:(Lcom/google/common/collect/Multiset;)Ljava/util/Iterator;
       4: areturn

  public com.google.common.collect.SortedMultiset<E> headMultiset(E, com.google.common.collect.BoundType);
    Code:
       0: new           #8                  // class com/google/common/collect/TreeMultiset
       3: dup
       4: aload_0
       5: getfield      #15                 // Field rootReference:Lcom/google/common/collect/TreeMultiset$Reference;
       8: aload_0
       9: getfield      #6                  // Field range:Lcom/google/common/collect/GeneralRange;
      12: aload_0
      13: invokevirtual #27                 // Method comparator:()Ljava/util/Comparator;
      16: aload_1
      17: aload_2
      18: invokestatic  #89                 // Method com/google/common/collect/GeneralRange.upTo:(Ljava/util/Comparator;Ljava/lang/Object;Lcom/google/common/collect/BoundType;)Lcom/google/common/collect/GeneralRange;
      21: invokevirtual #90                 // Method com/google/common/collect/GeneralRange.intersect:(Lcom/google/common/collect/GeneralRange;)Lcom/google/common/collect/GeneralRange;
      24: aload_0
      25: getfield      #4                  // Field header:Lcom/google/common/collect/TreeMultiset$AvlNode;
      28: invokespecial #91                 // Method "<init>":(Lcom/google/common/collect/TreeMultiset$Reference;Lcom/google/common/collect/GeneralRange;Lcom/google/common/collect/TreeMultiset$AvlNode;)V
      31: areturn

  public com.google.common.collect.SortedMultiset<E> tailMultiset(E, com.google.common.collect.BoundType);
    Code:
       0: new           #8                  // class com/google/common/collect/TreeMultiset
       3: dup
       4: aload_0
       5: getfield      #15                 // Field rootReference:Lcom/google/common/collect/TreeMultiset$Reference;
       8: aload_0
       9: getfield      #6                  // Field range:Lcom/google/common/collect/GeneralRange;
      12: aload_0
      13: invokevirtual #27                 // Method comparator:()Ljava/util/Comparator;
      16: aload_1
      17: aload_2
      18: invokestatic  #92                 // Method com/google/common/collect/GeneralRange.downTo:(Ljava/util/Comparator;Ljava/lang/Object;Lcom/google/common/collect/BoundType;)Lcom/google/common/collect/GeneralRange;
      21: invokevirtual #90                 // Method com/google/common/collect/GeneralRange.intersect:(Lcom/google/common/collect/GeneralRange;)Lcom/google/common/collect/GeneralRange;
      24: aload_0
      25: getfield      #4                  // Field header:Lcom/google/common/collect/TreeMultiset$AvlNode;
      28: invokespecial #91                 // Method "<init>":(Lcom/google/common/collect/TreeMultiset$Reference;Lcom/google/common/collect/GeneralRange;Lcom/google/common/collect/TreeMultiset$AvlNode;)V
      31: areturn

  public com.google.common.collect.SortedMultiset descendingMultiset();
    Code:
       0: aload_0
       1: invokespecial #109                // Method com/google/common/collect/AbstractSortedMultiset.descendingMultiset:()Lcom/google/common/collect/SortedMultiset;
       4: areturn

  public com.google.common.collect.SortedMultiset subMultiset(java.lang.Object, com.google.common.collect.BoundType, java.lang.Object, com.google.common.collect.BoundType);
    Code:
       0: aload_0
       1: aload_1
       2: aload_2
       3: aload_3
       4: aload         4
       6: invokespecial #110                // Method com/google/common/collect/AbstractSortedMultiset.subMultiset:(Ljava/lang/Object;Lcom/google/common/collect/BoundType;Ljava/lang/Object;Lcom/google/common/collect/BoundType;)Lcom/google/common/collect/SortedMultiset;
       9: areturn

  public com.google.common.collect.Multiset$Entry pollLastEntry();
    Code:
       0: aload_0
       1: invokespecial #111                // Method com/google/common/collect/AbstractSortedMultiset.pollLastEntry:()Lcom/google/common/collect/Multiset$Entry;
       4: areturn

  public com.google.common.collect.Multiset$Entry pollFirstEntry();
    Code:
       0: aload_0
       1: invokespecial #112                // Method com/google/common/collect/AbstractSortedMultiset.pollFirstEntry:()Lcom/google/common/collect/Multiset$Entry;
       4: areturn

  public com.google.common.collect.Multiset$Entry lastEntry();
    Code:
       0: aload_0
       1: invokespecial #113                // Method com/google/common/collect/AbstractSortedMultiset.lastEntry:()Lcom/google/common/collect/Multiset$Entry;
       4: areturn

  public com.google.common.collect.Multiset$Entry firstEntry();
    Code:
       0: aload_0
       1: invokespecial #114                // Method com/google/common/collect/AbstractSortedMultiset.firstEntry:()Lcom/google/common/collect/Multiset$Entry;
       4: areturn

  public java.util.Comparator comparator();
    Code:
       0: aload_0
       1: invokespecial #115                // Method com/google/common/collect/AbstractSortedMultiset.comparator:()Ljava/util/Comparator;
       4: areturn

  public java.util.NavigableSet elementSet();
    Code:
       0: aload_0
       1: invokespecial #116                // Method com/google/common/collect/AbstractSortedMultiset.elementSet:()Ljava/util/NavigableSet;
       4: areturn

  public java.util.Set entrySet();
    Code:
       0: aload_0
       1: invokespecial #117                // Method com/google/common/collect/AbstractSortedMultiset.entrySet:()Ljava/util/Set;
       4: areturn

  public boolean contains(java.lang.Object);
    Code:
       0: aload_0
       1: aload_1
       2: invokespecial #118                // Method com/google/common/collect/AbstractSortedMultiset.contains:(Ljava/lang/Object;)Z
       5: ireturn

  public boolean isEmpty();
    Code:
       0: aload_0
       1: invokespecial #119                // Method com/google/common/collect/AbstractSortedMultiset.isEmpty:()Z
       4: ireturn

  static com.google.common.collect.TreeMultiset$AvlNode access$1200(com.google.common.collect.TreeMultiset);
    Code:
       0: aload_0
       1: invokespecial #7                  // Method firstNode:()Lcom/google/common/collect/TreeMultiset$AvlNode;
       4: areturn

  static com.google.common.collect.GeneralRange access$1300(com.google.common.collect.TreeMultiset);
    Code:
       0: aload_0
       1: getfield      #6                  // Field range:Lcom/google/common/collect/GeneralRange;
       4: areturn

  static com.google.common.collect.Multiset$Entry access$1400(com.google.common.collect.TreeMultiset, com.google.common.collect.TreeMultiset$AvlNode);
    Code:
       0: aload_0
       1: aload_1
       2: invokespecial #5                  // Method wrapEntry:(Lcom/google/common/collect/TreeMultiset$AvlNode;)Lcom/google/common/collect/Multiset$Entry;
       5: areturn

  static com.google.common.collect.TreeMultiset$AvlNode access$1500(com.google.common.collect.TreeMultiset);
    Code:
       0: aload_0
       1: getfield      #4                  // Field header:Lcom/google/common/collect/TreeMultiset$AvlNode;
       4: areturn

  static com.google.common.collect.TreeMultiset$AvlNode access$1600(com.google.common.collect.TreeMultiset);
    Code:
       0: aload_0
       1: invokespecial #3                  // Method lastNode:()Lcom/google/common/collect/TreeMultiset$AvlNode;
       4: areturn

  static void access$1700(com.google.common.collect.TreeMultiset$AvlNode, com.google.common.collect.TreeMultiset$AvlNode, com.google.common.collect.TreeMultiset$AvlNode);
    Code:
       0: aload_0
       1: aload_1
       2: aload_2
       3: invokestatic  #2                  // Method successor:(Lcom/google/common/collect/TreeMultiset$AvlNode;Lcom/google/common/collect/TreeMultiset$AvlNode;Lcom/google/common/collect/TreeMultiset$AvlNode;)V
       6: return

  static void access$1800(com.google.common.collect.TreeMultiset$AvlNode, com.google.common.collect.TreeMultiset$AvlNode);
    Code:
       0: aload_0
       1: aload_1
       2: invokestatic  #1                  // Method successor:(Lcom/google/common/collect/TreeMultiset$AvlNode;Lcom/google/common/collect/TreeMultiset$AvlNode;)V
       5: return
}
