Compiled from "TypeUseLocation.java"
public final class org.checkerframework.framework.qual.TypeUseLocation extends java.lang.Enum<org.checkerframework.framework.qual.TypeUseLocation> {
  public static final org.checkerframework.framework.qual.TypeUseLocation TYPE_DECLARATION;

  public static final org.checkerframework.framework.qual.TypeUseLocation FIELD;

  public static final org.checkerframework.framework.qual.TypeUseLocation LOCAL_VARIABLE;

  public static final org.checkerframework.framework.qual.TypeUseLocation RESOURCE_VARIABLE;

  public static final org.checkerframework.framework.qual.TypeUseLocation EXCEPTION_PARAMETER;

  public static final org.checkerframework.framework.qual.TypeUseLocation RECEIVER;

  public static final org.checkerframework.framework.qual.TypeUseLocation PARAMETER;

  public static final org.checkerframework.framework.qual.TypeUseLocation RETURN;

  public static final org.checkerframework.framework.qual.TypeUseLocation CONSTRUCTOR_RESULT;

  public static final org.checkerframework.framework.qual.TypeUseLocation LOWER_BOUND;

  public static final org.checkerframework.framework.qual.TypeUseLocation EXPLICIT_LOWER_BOUND;

  public static final org.checkerframework.framework.qual.TypeUseLocation IMPLICIT_LOWER_BOUND;

  public static final org.checkerframework.framework.qual.TypeUseLocation UPPER_BOUND;

  public static final org.checkerframework.framework.qual.TypeUseLocation EXPLICIT_UPPER_BOUND;

  public static final org.checkerframework.framework.qual.TypeUseLocation IMPLICIT_UPPER_BOUND;

  public static final org.checkerframework.framework.qual.TypeUseLocation OTHERWISE;

  public static final org.checkerframework.framework.qual.TypeUseLocation ALL;

  public static org.checkerframework.framework.qual.TypeUseLocation[] values();
    Code:
       0: getstatic     #1                  // Field $VALUES:[Lorg/checkerframework/framework/qual/TypeUseLocation;
       3: invokevirtual #2                  // Method "[Lorg/checkerframework/framework/qual/TypeUseLocation;".clone:()Ljava/lang/Object;
       6: checkcast     #3                  // class "[Lorg/checkerframework/framework/qual/TypeUseLocation;"
       9: areturn

  public static org.checkerframework.framework.qual.TypeUseLocation valueOf(java.lang.String);
    Code:
       0: ldc           #4                  // class org/checkerframework/framework/qual/TypeUseLocation
       2: aload_0
       3: invokestatic  #5                  // Method java/lang/Enum.valueOf:(Ljava/lang/Class;Ljava/lang/String;)Ljava/lang/Enum;
       6: checkcast     #4                  // class org/checkerframework/framework/qual/TypeUseLocation
       9: areturn

  static {};
    Code:
       0: new           #4                  // class org/checkerframework/framework/qual/TypeUseLocation
       3: dup
       4: ldc           #7                  // String TYPE_DECLARATION
       6: iconst_0
       7: invokespecial #8                  // Method "<init>":(Ljava/lang/String;I)V
      10: putstatic     #9                  // Field TYPE_DECLARATION:Lorg/checkerframework/framework/qual/TypeUseLocation;
      13: new           #4                  // class org/checkerframework/framework/qual/TypeUseLocation
      16: dup
      17: ldc           #10                 // String FIELD
      19: iconst_1
      20: invokespecial #8                  // Method "<init>":(Ljava/lang/String;I)V
      23: putstatic     #11                 // Field FIELD:Lorg/checkerframework/framework/qual/TypeUseLocation;
      26: new           #4                  // class org/checkerframework/framework/qual/TypeUseLocation
      29: dup
      30: ldc           #12                 // String LOCAL_VARIABLE
      32: iconst_2
      33: invokespecial #8                  // Method "<init>":(Ljava/lang/String;I)V
      36: putstatic     #13                 // Field LOCAL_VARIABLE:Lorg/checkerframework/framework/qual/TypeUseLocation;
      39: new           #4                  // class org/checkerframework/framework/qual/TypeUseLocation
      42: dup
      43: ldc           #14                 // String RESOURCE_VARIABLE
      45: iconst_3
      46: invokespecial #8                  // Method "<init>":(Ljava/lang/String;I)V
      49: putstatic     #15                 // Field RESOURCE_VARIABLE:Lorg/checkerframework/framework/qual/TypeUseLocation;
      52: new           #4                  // class org/checkerframework/framework/qual/TypeUseLocation
      55: dup
      56: ldc           #16                 // String EXCEPTION_PARAMETER
      58: iconst_4
      59: invokespecial #8                  // Method "<init>":(Ljava/lang/String;I)V
      62: putstatic     #17                 // Field EXCEPTION_PARAMETER:Lorg/checkerframework/framework/qual/TypeUseLocation;
      65: new           #4                  // class org/checkerframework/framework/qual/TypeUseLocation
      68: dup
      69: ldc           #18                 // String RECEIVER
      71: iconst_5
      72: invokespecial #8                  // Method "<init>":(Ljava/lang/String;I)V
      75: putstatic     #19                 // Field RECEIVER:Lorg/checkerframework/framework/qual/TypeUseLocation;
      78: new           #4                  // class org/checkerframework/framework/qual/TypeUseLocation
      81: dup
      82: ldc           #20                 // String PARAMETER
      84: bipush        6
      86: invokespecial #8                  // Method "<init>":(Ljava/lang/String;I)V
      89: putstatic     #21                 // Field PARAMETER:Lorg/checkerframework/framework/qual/TypeUseLocation;
      92: new           #4                  // class org/checkerframework/framework/qual/TypeUseLocation
      95: dup
      96: ldc           #22                 // String RETURN
      98: bipush        7
     100: invokespecial #8                  // Method "<init>":(Ljava/lang/String;I)V
     103: putstatic     #23                 // Field RETURN:Lorg/checkerframework/framework/qual/TypeUseLocation;
     106: new           #4                  // class org/checkerframework/framework/qual/TypeUseLocation
     109: dup
     110: ldc           #24                 // String CONSTRUCTOR_RESULT
     112: bipush        8
     114: invokespecial #8                  // Method "<init>":(Ljava/lang/String;I)V
     117: putstatic     #25                 // Field CONSTRUCTOR_RESULT:Lorg/checkerframework/framework/qual/TypeUseLocation;
     120: new           #4                  // class org/checkerframework/framework/qual/TypeUseLocation
     123: dup
     124: ldc           #26                 // String LOWER_BOUND
     126: bipush        9
     128: invokespecial #8                  // Method "<init>":(Ljava/lang/String;I)V
     131: putstatic     #27                 // Field LOWER_BOUND:Lorg/checkerframework/framework/qual/TypeUseLocation;
     134: new           #4                  // class org/checkerframework/framework/qual/TypeUseLocation
     137: dup
     138: ldc           #28                 // String EXPLICIT_LOWER_BOUND
     140: bipush        10
     142: invokespecial #8                  // Method "<init>":(Ljava/lang/String;I)V
     145: putstatic     #29                 // Field EXPLICIT_LOWER_BOUND:Lorg/checkerframework/framework/qual/TypeUseLocation;
     148: new           #4                  // class org/checkerframework/framework/qual/TypeUseLocation
     151: dup
     152: ldc           #30                 // String IMPLICIT_LOWER_BOUND
     154: bipush        11
     156: invokespecial #8                  // Method "<init>":(Ljava/lang/String;I)V
     159: putstatic     #31                 // Field IMPLICIT_LOWER_BOUND:Lorg/checkerframework/framework/qual/TypeUseLocation;
     162: new           #4                  // class org/checkerframework/framework/qual/TypeUseLocation
     165: dup
     166: ldc           #32                 // String UPPER_BOUND
     168: bipush        12
     170: invokespecial #8                  // Method "<init>":(Ljava/lang/String;I)V
     173: putstatic     #33                 // Field UPPER_BOUND:Lorg/checkerframework/framework/qual/TypeUseLocation;
     176: new           #4                  // class org/checkerframework/framework/qual/TypeUseLocation
     179: dup
     180: ldc           #34                 // String EXPLICIT_UPPER_BOUND
     182: bipush        13
     184: invokespecial #8                  // Method "<init>":(Ljava/lang/String;I)V
     187: putstatic     #35                 // Field EXPLICIT_UPPER_BOUND:Lorg/checkerframework/framework/qual/TypeUseLocation;
     190: new           #4                  // class org/checkerframework/framework/qual/TypeUseLocation
     193: dup
     194: ldc           #36                 // String IMPLICIT_UPPER_BOUND
     196: bipush        14
     198: invokespecial #8                  // Method "<init>":(Ljava/lang/String;I)V
     201: putstatic     #37                 // Field IMPLICIT_UPPER_BOUND:Lorg/checkerframework/framework/qual/TypeUseLocation;
     204: new           #4                  // class org/checkerframework/framework/qual/TypeUseLocation
     207: dup
     208: ldc           #38                 // String OTHERWISE
     210: bipush        15
     212: invokespecial #8                  // Method "<init>":(Ljava/lang/String;I)V
     215: putstatic     #39                 // Field OTHERWISE:Lorg/checkerframework/framework/qual/TypeUseLocation;
     218: new           #4                  // class org/checkerframework/framework/qual/TypeUseLocation
     221: dup
     222: ldc           #40                 // String ALL
     224: bipush        16
     226: invokespecial #8                  // Method "<init>":(Ljava/lang/String;I)V
     229: putstatic     #41                 // Field ALL:Lorg/checkerframework/framework/qual/TypeUseLocation;
     232: bipush        17
     234: anewarray     #4                  // class org/checkerframework/framework/qual/TypeUseLocation
     237: dup
     238: iconst_0
     239: getstatic     #9                  // Field TYPE_DECLARATION:Lorg/checkerframework/framework/qual/TypeUseLocation;
     242: aastore
     243: dup
     244: iconst_1
     245: getstatic     #11                 // Field FIELD:Lorg/checkerframework/framework/qual/TypeUseLocation;
     248: aastore
     249: dup
     250: iconst_2
     251: getstatic     #13                 // Field LOCAL_VARIABLE:Lorg/checkerframework/framework/qual/TypeUseLocation;
     254: aastore
     255: dup
     256: iconst_3
     257: getstatic     #15                 // Field RESOURCE_VARIABLE:Lorg/checkerframework/framework/qual/TypeUseLocation;
     260: aastore
     261: dup
     262: iconst_4
     263: getstatic     #17                 // Field EXCEPTION_PARAMETER:Lorg/checkerframework/framework/qual/TypeUseLocation;
     266: aastore
     267: dup
     268: iconst_5
     269: getstatic     #19                 // Field RECEIVER:Lorg/checkerframework/framework/qual/TypeUseLocation;
     272: aastore
     273: dup
     274: bipush        6
     276: getstatic     #21                 // Field PARAMETER:Lorg/checkerframework/framework/qual/TypeUseLocation;
     279: aastore
     280: dup
     281: bipush        7
     283: getstatic     #23                 // Field RETURN:Lorg/checkerframework/framework/qual/TypeUseLocation;
     286: aastore
     287: dup
     288: bipush        8
     290: getstatic     #25                 // Field CONSTRUCTOR_RESULT:Lorg/checkerframework/framework/qual/TypeUseLocation;
     293: aastore
     294: dup
     295: bipush        9
     297: getstatic     #27                 // Field LOWER_BOUND:Lorg/checkerframework/framework/qual/TypeUseLocation;
     300: aastore
     301: dup
     302: bipush        10
     304: getstatic     #29                 // Field EXPLICIT_LOWER_BOUND:Lorg/checkerframework/framework/qual/TypeUseLocation;
     307: aastore
     308: dup
     309: bipush        11
     311: getstatic     #31                 // Field IMPLICIT_LOWER_BOUND:Lorg/checkerframework/framework/qual/TypeUseLocation;
     314: aastore
     315: dup
     316: bipush        12
     318: getstatic     #33                 // Field UPPER_BOUND:Lorg/checkerframework/framework/qual/TypeUseLocation;
     321: aastore
     322: dup
     323: bipush        13
     325: getstatic     #35                 // Field EXPLICIT_UPPER_BOUND:Lorg/checkerframework/framework/qual/TypeUseLocation;
     328: aastore
     329: dup
     330: bipush        14
     332: getstatic     #37                 // Field IMPLICIT_UPPER_BOUND:Lorg/checkerframework/framework/qual/TypeUseLocation;
     335: aastore
     336: dup
     337: bipush        15
     339: getstatic     #39                 // Field OTHERWISE:Lorg/checkerframework/framework/qual/TypeUseLocation;
     342: aastore
     343: dup
     344: bipush        16
     346: getstatic     #41                 // Field ALL:Lorg/checkerframework/framework/qual/TypeUseLocation;
     349: aastore
     350: putstatic     #1                  // Field $VALUES:[Lorg/checkerframework/framework/qual/TypeUseLocation;
     353: return
}
