Compiled from "TypeToken.java"
public abstract class com.google.common.reflect.TypeToken<T> extends com.google.common.reflect.TypeCapture<T> implements java.io.Serializable {
  protected com.google.common.reflect.TypeToken();
    Code:
       0: aload_0
       1: invokespecial #6                  // Method com/google/common/reflect/TypeCapture."<init>":()V
       4: aload_0
       5: aload_0
       6: invokevirtual #7                  // Method capture:()Ljava/lang/reflect/Type;
       9: putfield      #2                  // Field runtimeType:Ljava/lang/reflect/Type;
      12: aload_0
      13: getfield      #2                  // Field runtimeType:Ljava/lang/reflect/Type;
      16: instanceof    #8                  // class java/lang/reflect/TypeVariable
      19: ifne          26
      22: iconst_1
      23: goto          27
      26: iconst_0
      27: ldc           #9                  // String Cannot construct a TypeToken for a type variable.\nYou probably meant to call new TypeToken<%s>(getClass()) that can resolve the type variable for you.\nIf you do need to create a TypeToken of a type variable, please use TypeToken.of() instead.
      29: aload_0
      30: getfield      #2                  // Field runtimeType:Ljava/lang/reflect/Type;
      33: invokestatic  #10                 // Method com/google/common/base/Preconditions.checkState:(ZLjava/lang/String;Ljava/lang/Object;)V
      36: return

  protected com.google.common.reflect.TypeToken(java.lang.Class<?>);
    Code:
       0: aload_0
       1: invokespecial #6                  // Method com/google/common/reflect/TypeCapture."<init>":()V
       4: aload_0
       5: invokespecial #11                 // Method com/google/common/reflect/TypeCapture.capture:()Ljava/lang/reflect/Type;
       8: astore_2
       9: aload_2
      10: instanceof    #12                 // class java/lang/Class
      13: ifeq          24
      16: aload_0
      17: aload_2
      18: putfield      #2                  // Field runtimeType:Ljava/lang/reflect/Type;
      21: goto          36
      24: aload_0
      25: aload_1
      26: invokestatic  #13                 // Method com/google/common/reflect/TypeResolver.covariantly:(Ljava/lang/reflect/Type;)Lcom/google/common/reflect/TypeResolver;
      29: aload_2
      30: invokevirtual #14                 // Method com/google/common/reflect/TypeResolver.resolveType:(Ljava/lang/reflect/Type;)Ljava/lang/reflect/Type;
      33: putfield      #2                  // Field runtimeType:Ljava/lang/reflect/Type;
      36: return

  public static <T> com.google.common.reflect.TypeToken<T> of(java.lang.Class<T>);
    Code:
       0: new           #17                 // class com/google/common/reflect/TypeToken$SimpleTypeToken
       3: dup
       4: aload_0
       5: invokespecial #18                 // Method com/google/common/reflect/TypeToken$SimpleTypeToken."<init>":(Ljava/lang/reflect/Type;)V
       8: areturn

  public static com.google.common.reflect.TypeToken<?> of(java.lang.reflect.Type);
    Code:
       0: new           #17                 // class com/google/common/reflect/TypeToken$SimpleTypeToken
       3: dup
       4: aload_0
       5: invokespecial #18                 // Method com/google/common/reflect/TypeToken$SimpleTypeToken."<init>":(Ljava/lang/reflect/Type;)V
       8: areturn

  public final java.lang.Class<? super T> getRawType();
    Code:
       0: aload_0
       1: invokespecial #3                  // Method getRawTypes:()Lcom/google/common/collect/ImmutableSet;
       4: invokevirtual #19                 // Method com/google/common/collect/ImmutableSet.iterator:()Lcom/google/common/collect/UnmodifiableIterator;
       7: invokevirtual #20                 // Method com/google/common/collect/UnmodifiableIterator.next:()Ljava/lang/Object;
      10: checkcast     #12                 // class java/lang/Class
      13: astore_1
      14: aload_1
      15: astore_2
      16: aload_2
      17: areturn

  public final java.lang.reflect.Type getType();
    Code:
       0: aload_0
       1: getfield      #2                  // Field runtimeType:Ljava/lang/reflect/Type;
       4: areturn

  public final <X> com.google.common.reflect.TypeToken<T> where(com.google.common.reflect.TypeParameter<X>, com.google.common.reflect.TypeToken<X>);
    Code:
       0: new           #21                 // class com/google/common/reflect/TypeResolver
       3: dup
       4: invokespecial #22                 // Method com/google/common/reflect/TypeResolver."<init>":()V
       7: new           #23                 // class com/google/common/reflect/TypeResolver$TypeVariableKey
      10: dup
      11: aload_1
      12: getfield      #24                 // Field com/google/common/reflect/TypeParameter.typeVariable:Ljava/lang/reflect/TypeVariable;
      15: invokespecial #25                 // Method com/google/common/reflect/TypeResolver$TypeVariableKey."<init>":(Ljava/lang/reflect/TypeVariable;)V
      18: aload_2
      19: getfield      #2                  // Field runtimeType:Ljava/lang/reflect/Type;
      22: invokestatic  #26                 // Method com/google/common/collect/ImmutableMap.of:(Ljava/lang/Object;Ljava/lang/Object;)Lcom/google/common/collect/ImmutableMap;
      25: invokevirtual #27                 // Method com/google/common/reflect/TypeResolver.where:(Ljava/util/Map;)Lcom/google/common/reflect/TypeResolver;
      28: astore_3
      29: new           #17                 // class com/google/common/reflect/TypeToken$SimpleTypeToken
      32: dup
      33: aload_3
      34: aload_0
      35: getfield      #2                  // Field runtimeType:Ljava/lang/reflect/Type;
      38: invokevirtual #14                 // Method com/google/common/reflect/TypeResolver.resolveType:(Ljava/lang/reflect/Type;)Ljava/lang/reflect/Type;
      41: invokespecial #18                 // Method com/google/common/reflect/TypeToken$SimpleTypeToken."<init>":(Ljava/lang/reflect/Type;)V
      44: areturn

  public final <X> com.google.common.reflect.TypeToken<T> where(com.google.common.reflect.TypeParameter<X>, java.lang.Class<X>);
    Code:
       0: aload_0
       1: aload_1
       2: aload_2
       3: invokestatic  #28                 // Method of:(Ljava/lang/Class;)Lcom/google/common/reflect/TypeToken;
       6: invokevirtual #29                 // Method where:(Lcom/google/common/reflect/TypeParameter;Lcom/google/common/reflect/TypeToken;)Lcom/google/common/reflect/TypeToken;
       9: areturn

  public final com.google.common.reflect.TypeToken<?> resolveType(java.lang.reflect.Type);
    Code:
       0: aload_1
       1: invokestatic  #15                 // Method com/google/common/base/Preconditions.checkNotNull:(Ljava/lang/Object;)Ljava/lang/Object;
       4: pop
       5: aload_0
       6: invokespecial #4                  // Method getInvariantTypeResolver:()Lcom/google/common/reflect/TypeResolver;
       9: aload_1
      10: invokevirtual #14                 // Method com/google/common/reflect/TypeResolver.resolveType:(Ljava/lang/reflect/Type;)Ljava/lang/reflect/Type;
      13: invokestatic  #30                 // Method of:(Ljava/lang/reflect/Type;)Lcom/google/common/reflect/TypeToken;
      16: areturn

  final com.google.common.reflect.TypeToken<? super T> getGenericSuperclass();
    Code:
       0: aload_0
       1: getfield      #2                  // Field runtimeType:Ljava/lang/reflect/Type;
       4: instanceof    #8                  // class java/lang/reflect/TypeVariable
       7: ifeq          29
      10: aload_0
      11: aload_0
      12: getfield      #2                  // Field runtimeType:Ljava/lang/reflect/Type;
      15: checkcast     #8                  // class java/lang/reflect/TypeVariable
      18: invokeinterface #33,  1           // InterfaceMethod java/lang/reflect/TypeVariable.getBounds:()[Ljava/lang/reflect/Type;
      23: iconst_0
      24: aaload
      25: invokespecial #34                 // Method boundAsSuperclass:(Ljava/lang/reflect/Type;)Lcom/google/common/reflect/TypeToken;
      28: areturn
      29: aload_0
      30: getfield      #2                  // Field runtimeType:Ljava/lang/reflect/Type;
      33: instanceof    #35                 // class java/lang/reflect/WildcardType
      36: ifeq          58
      39: aload_0
      40: aload_0
      41: getfield      #2                  // Field runtimeType:Ljava/lang/reflect/Type;
      44: checkcast     #35                 // class java/lang/reflect/WildcardType
      47: invokeinterface #36,  1           // InterfaceMethod java/lang/reflect/WildcardType.getUpperBounds:()[Ljava/lang/reflect/Type;
      52: iconst_0
      53: aaload
      54: invokespecial #34                 // Method boundAsSuperclass:(Ljava/lang/reflect/Type;)Lcom/google/common/reflect/TypeToken;
      57: areturn
      58: aload_0
      59: invokevirtual #37                 // Method getRawType:()Ljava/lang/Class;
      62: invokevirtual #38                 // Method java/lang/Class.getGenericSuperclass:()Ljava/lang/reflect/Type;
      65: astore_1
      66: aload_1
      67: ifnonnull     72
      70: aconst_null
      71: areturn
      72: aload_0
      73: aload_1
      74: invokespecial #39                 // Method resolveSupertype:(Ljava/lang/reflect/Type;)Lcom/google/common/reflect/TypeToken;
      77: astore_2
      78: aload_2
      79: areturn

  final com.google.common.collect.ImmutableList<com.google.common.reflect.TypeToken<? super T>> getGenericInterfaces();
    Code:
       0: aload_0
       1: getfield      #2                  // Field runtimeType:Ljava/lang/reflect/Type;
       4: instanceof    #8                  // class java/lang/reflect/TypeVariable
       7: ifeq          27
      10: aload_0
      11: aload_0
      12: getfield      #2                  // Field runtimeType:Ljava/lang/reflect/Type;
      15: checkcast     #8                  // class java/lang/reflect/TypeVariable
      18: invokeinterface #33,  1           // InterfaceMethod java/lang/reflect/TypeVariable.getBounds:()[Ljava/lang/reflect/Type;
      23: invokespecial #41                 // Method boundsAsInterfaces:([Ljava/lang/reflect/Type;)Lcom/google/common/collect/ImmutableList;
      26: areturn
      27: aload_0
      28: getfield      #2                  // Field runtimeType:Ljava/lang/reflect/Type;
      31: instanceof    #35                 // class java/lang/reflect/WildcardType
      34: ifeq          54
      37: aload_0
      38: aload_0
      39: getfield      #2                  // Field runtimeType:Ljava/lang/reflect/Type;
      42: checkcast     #35                 // class java/lang/reflect/WildcardType
      45: invokeinterface #36,  1           // InterfaceMethod java/lang/reflect/WildcardType.getUpperBounds:()[Ljava/lang/reflect/Type;
      50: invokespecial #41                 // Method boundsAsInterfaces:([Ljava/lang/reflect/Type;)Lcom/google/common/collect/ImmutableList;
      53: areturn
      54: invokestatic  #42                 // Method com/google/common/collect/ImmutableList.builder:()Lcom/google/common/collect/ImmutableList$Builder;
      57: astore_1
      58: aload_0
      59: invokevirtual #37                 // Method getRawType:()Ljava/lang/Class;
      62: invokevirtual #43                 // Method java/lang/Class.getGenericInterfaces:()[Ljava/lang/reflect/Type;
      65: astore_2
      66: aload_2
      67: arraylength
      68: istore_3
      69: iconst_0
      70: istore        4
      72: iload         4
      74: iload_3
      75: if_icmpge     105
      78: aload_2
      79: iload         4
      81: aaload
      82: astore        5
      84: aload_0
      85: aload         5
      87: invokespecial #39                 // Method resolveSupertype:(Ljava/lang/reflect/Type;)Lcom/google/common/reflect/TypeToken;
      90: astore        6
      92: aload_1
      93: aload         6
      95: invokevirtual #44                 // Method com/google/common/collect/ImmutableList$Builder.add:(Ljava/lang/Object;)Lcom/google/common/collect/ImmutableList$Builder;
      98: pop
      99: iinc          4, 1
     102: goto          72
     105: aload_1
     106: invokevirtual #45                 // Method com/google/common/collect/ImmutableList$Builder.build:()Lcom/google/common/collect/ImmutableList;
     109: areturn

  public final com.google.common.reflect.TypeToken<T>.TypeSet getTypes();
    Code:
       0: new           #46                 // class com/google/common/reflect/TypeToken$TypeSet
       3: dup
       4: aload_0
       5: invokespecial #47                 // Method com/google/common/reflect/TypeToken$TypeSet."<init>":(Lcom/google/common/reflect/TypeToken;)V
       8: areturn

  public final com.google.common.reflect.TypeToken<? super T> getSupertype(java.lang.Class<? super T>);
    Code:
       0: aload_0
       1: aload_1
       2: invokespecial #48                 // Method someRawTypeIsSubclassOf:(Ljava/lang/Class;)Z
       5: ldc           #49                 // String %s is not a super class of %s
       7: aload_1
       8: aload_0
       9: invokestatic  #50                 // Method com/google/common/base/Preconditions.checkArgument:(ZLjava/lang/String;Ljava/lang/Object;Ljava/lang/Object;)V
      12: aload_0
      13: getfield      #2                  // Field runtimeType:Ljava/lang/reflect/Type;
      16: instanceof    #8                  // class java/lang/reflect/TypeVariable
      19: ifeq          40
      22: aload_0
      23: aload_1
      24: aload_0
      25: getfield      #2                  // Field runtimeType:Ljava/lang/reflect/Type;
      28: checkcast     #8                  // class java/lang/reflect/TypeVariable
      31: invokeinterface #33,  1           // InterfaceMethod java/lang/reflect/TypeVariable.getBounds:()[Ljava/lang/reflect/Type;
      36: invokespecial #51                 // Method getSupertypeFromUpperBounds:(Ljava/lang/Class;[Ljava/lang/reflect/Type;)Lcom/google/common/reflect/TypeToken;
      39: areturn
      40: aload_0
      41: getfield      #2                  // Field runtimeType:Ljava/lang/reflect/Type;
      44: instanceof    #35                 // class java/lang/reflect/WildcardType
      47: ifeq          68
      50: aload_0
      51: aload_1
      52: aload_0
      53: getfield      #2                  // Field runtimeType:Ljava/lang/reflect/Type;
      56: checkcast     #35                 // class java/lang/reflect/WildcardType
      59: invokeinterface #36,  1           // InterfaceMethod java/lang/reflect/WildcardType.getUpperBounds:()[Ljava/lang/reflect/Type;
      64: invokespecial #51                 // Method getSupertypeFromUpperBounds:(Ljava/lang/Class;[Ljava/lang/reflect/Type;)Lcom/google/common/reflect/TypeToken;
      67: areturn
      68: aload_1
      69: invokevirtual #52                 // Method java/lang/Class.isArray:()Z
      72: ifeq          81
      75: aload_0
      76: aload_1
      77: invokespecial #53                 // Method getArraySupertype:(Ljava/lang/Class;)Lcom/google/common/reflect/TypeToken;
      80: areturn
      81: aload_0
      82: aload_1
      83: invokestatic  #54                 // Method toGenericType:(Ljava/lang/Class;)Lcom/google/common/reflect/TypeToken;
      86: getfield      #2                  // Field runtimeType:Ljava/lang/reflect/Type;
      89: invokespecial #39                 // Method resolveSupertype:(Ljava/lang/reflect/Type;)Lcom/google/common/reflect/TypeToken;
      92: astore_2
      93: aload_2
      94: areturn

  public final com.google.common.reflect.TypeToken<? extends T> getSubtype(java.lang.Class<?>);
    Code:
       0: aload_0
       1: getfield      #2                  // Field runtimeType:Ljava/lang/reflect/Type;
       4: instanceof    #8                  // class java/lang/reflect/TypeVariable
       7: ifne          14
      10: iconst_1
      11: goto          15
      14: iconst_0
      15: ldc           #55                 // String Cannot get subtype of type variable <%s>
      17: aload_0
      18: invokestatic  #56                 // Method com/google/common/base/Preconditions.checkArgument:(ZLjava/lang/String;Ljava/lang/Object;)V
      21: aload_0
      22: getfield      #2                  // Field runtimeType:Ljava/lang/reflect/Type;
      25: instanceof    #35                 // class java/lang/reflect/WildcardType
      28: ifeq          49
      31: aload_0
      32: aload_1
      33: aload_0
      34: getfield      #2                  // Field runtimeType:Ljava/lang/reflect/Type;
      37: checkcast     #35                 // class java/lang/reflect/WildcardType
      40: invokeinterface #57,  1           // InterfaceMethod java/lang/reflect/WildcardType.getLowerBounds:()[Ljava/lang/reflect/Type;
      45: invokespecial #58                 // Method getSubtypeFromLowerBounds:(Ljava/lang/Class;[Ljava/lang/reflect/Type;)Lcom/google/common/reflect/TypeToken;
      48: areturn
      49: aload_0
      50: invokevirtual #59                 // Method isArray:()Z
      53: ifeq          62
      56: aload_0
      57: aload_1
      58: invokespecial #60                 // Method getArraySubtype:(Ljava/lang/Class;)Lcom/google/common/reflect/TypeToken;
      61: areturn
      62: aload_0
      63: invokevirtual #37                 // Method getRawType:()Ljava/lang/Class;
      66: aload_1
      67: invokevirtual #61                 // Method java/lang/Class.isAssignableFrom:(Ljava/lang/Class;)Z
      70: ldc           #62                 // String %s isn't a subclass of %s
      72: aload_1
      73: aload_0
      74: invokestatic  #50                 // Method com/google/common/base/Preconditions.checkArgument:(ZLjava/lang/String;Ljava/lang/Object;Ljava/lang/Object;)V
      77: aload_0
      78: aload_1
      79: invokespecial #63                 // Method resolveTypeArgsForSubclass:(Ljava/lang/Class;)Ljava/lang/reflect/Type;
      82: astore_2
      83: aload_2
      84: invokestatic  #30                 // Method of:(Ljava/lang/reflect/Type;)Lcom/google/common/reflect/TypeToken;
      87: astore_3
      88: aload_3
      89: aload_0
      90: invokevirtual #64                 // Method isSubtypeOf:(Lcom/google/common/reflect/TypeToken;)Z
      93: ldc           #65                 // String %s does not appear to be a subtype of %s
      95: aload_3
      96: aload_0
      97: invokestatic  #50                 // Method com/google/common/base/Preconditions.checkArgument:(ZLjava/lang/String;Ljava/lang/Object;Ljava/lang/Object;)V
     100: aload_3
     101: areturn

  public final boolean isSupertypeOf(com.google.common.reflect.TypeToken<?>);
    Code:
       0: aload_1
       1: aload_0
       2: invokevirtual #66                 // Method getType:()Ljava/lang/reflect/Type;
       5: invokevirtual #67                 // Method isSubtypeOf:(Ljava/lang/reflect/Type;)Z
       8: ireturn

  public final boolean isSupertypeOf(java.lang.reflect.Type);
    Code:
       0: aload_1
       1: invokestatic  #30                 // Method of:(Ljava/lang/reflect/Type;)Lcom/google/common/reflect/TypeToken;
       4: aload_0
       5: invokevirtual #66                 // Method getType:()Ljava/lang/reflect/Type;
       8: invokevirtual #67                 // Method isSubtypeOf:(Ljava/lang/reflect/Type;)Z
      11: ireturn

  public final boolean isSubtypeOf(com.google.common.reflect.TypeToken<?>);
    Code:
       0: aload_0
       1: aload_1
       2: invokevirtual #66                 // Method getType:()Ljava/lang/reflect/Type;
       5: invokevirtual #67                 // Method isSubtypeOf:(Ljava/lang/reflect/Type;)Z
       8: ireturn

  public final boolean isSubtypeOf(java.lang.reflect.Type);
    Code:
       0: aload_1
       1: invokestatic  #15                 // Method com/google/common/base/Preconditions.checkNotNull:(Ljava/lang/Object;)Ljava/lang/Object;
       4: pop
       5: aload_1
       6: instanceof    #35                 // class java/lang/reflect/WildcardType
       9: ifeq          32
      12: aload_1
      13: checkcast     #35                 // class java/lang/reflect/WildcardType
      16: invokeinterface #57,  1           // InterfaceMethod java/lang/reflect/WildcardType.getLowerBounds:()[Ljava/lang/reflect/Type;
      21: invokestatic  #68                 // Method any:([Ljava/lang/reflect/Type;)Lcom/google/common/reflect/TypeToken$Bounds;
      24: aload_0
      25: getfield      #2                  // Field runtimeType:Ljava/lang/reflect/Type;
      28: invokevirtual #69                 // Method com/google/common/reflect/TypeToken$Bounds.isSupertypeOf:(Ljava/lang/reflect/Type;)Z
      31: ireturn
      32: aload_0
      33: getfield      #2                  // Field runtimeType:Ljava/lang/reflect/Type;
      36: instanceof    #35                 // class java/lang/reflect/WildcardType
      39: ifeq          62
      42: aload_0
      43: getfield      #2                  // Field runtimeType:Ljava/lang/reflect/Type;
      46: checkcast     #35                 // class java/lang/reflect/WildcardType
      49: invokeinterface #36,  1           // InterfaceMethod java/lang/reflect/WildcardType.getUpperBounds:()[Ljava/lang/reflect/Type;
      54: invokestatic  #68                 // Method any:([Ljava/lang/reflect/Type;)Lcom/google/common/reflect/TypeToken$Bounds;
      57: aload_1
      58: invokevirtual #70                 // Method com/google/common/reflect/TypeToken$Bounds.isSubtypeOf:(Ljava/lang/reflect/Type;)Z
      61: ireturn
      62: aload_0
      63: getfield      #2                  // Field runtimeType:Ljava/lang/reflect/Type;
      66: instanceof    #8                  // class java/lang/reflect/TypeVariable
      69: ifeq          111
      72: aload_0
      73: getfield      #2                  // Field runtimeType:Ljava/lang/reflect/Type;
      76: aload_1
      77: invokevirtual #71                 // Method java/lang/Object.equals:(Ljava/lang/Object;)Z
      80: ifne          105
      83: aload_0
      84: getfield      #2                  // Field runtimeType:Ljava/lang/reflect/Type;
      87: checkcast     #8                  // class java/lang/reflect/TypeVariable
      90: invokeinterface #33,  1           // InterfaceMethod java/lang/reflect/TypeVariable.getBounds:()[Ljava/lang/reflect/Type;
      95: invokestatic  #68                 // Method any:([Ljava/lang/reflect/Type;)Lcom/google/common/reflect/TypeToken$Bounds;
      98: aload_1
      99: invokevirtual #70                 // Method com/google/common/reflect/TypeToken$Bounds.isSubtypeOf:(Ljava/lang/reflect/Type;)Z
     102: ifeq          109
     105: iconst_1
     106: goto          110
     109: iconst_0
     110: ireturn
     111: aload_0
     112: getfield      #2                  // Field runtimeType:Ljava/lang/reflect/Type;
     115: instanceof    #72                 // class java/lang/reflect/GenericArrayType
     118: ifeq          136
     121: aload_1
     122: invokestatic  #30                 // Method of:(Ljava/lang/reflect/Type;)Lcom/google/common/reflect/TypeToken;
     125: aload_0
     126: getfield      #2                  // Field runtimeType:Ljava/lang/reflect/Type;
     129: checkcast     #72                 // class java/lang/reflect/GenericArrayType
     132: invokespecial #73                 // Method isSupertypeOfArray:(Ljava/lang/reflect/GenericArrayType;)Z
     135: ireturn
     136: aload_1
     137: instanceof    #12                 // class java/lang/Class
     140: ifeq          152
     143: aload_0
     144: aload_1
     145: checkcast     #12                 // class java/lang/Class
     148: invokespecial #48                 // Method someRawTypeIsSubclassOf:(Ljava/lang/Class;)Z
     151: ireturn
     152: aload_1
     153: instanceof    #74                 // class java/lang/reflect/ParameterizedType
     156: ifeq          168
     159: aload_0
     160: aload_1
     161: checkcast     #74                 // class java/lang/reflect/ParameterizedType
     164: invokespecial #75                 // Method isSubtypeOfParameterizedType:(Ljava/lang/reflect/ParameterizedType;)Z
     167: ireturn
     168: aload_1
     169: instanceof    #72                 // class java/lang/reflect/GenericArrayType
     172: ifeq          184
     175: aload_0
     176: aload_1
     177: checkcast     #72                 // class java/lang/reflect/GenericArrayType
     180: invokespecial #76                 // Method isSubtypeOfArrayType:(Ljava/lang/reflect/GenericArrayType;)Z
     183: ireturn
     184: iconst_0
     185: ireturn

  public final boolean isArray();
    Code:
       0: aload_0
       1: invokevirtual #77                 // Method getComponentType:()Lcom/google/common/reflect/TypeToken;
       4: ifnull        11
       7: iconst_1
       8: goto          12
      11: iconst_0
      12: ireturn

  public final boolean isPrimitive();
    Code:
       0: aload_0
       1: getfield      #2                  // Field runtimeType:Ljava/lang/reflect/Type;
       4: instanceof    #12                 // class java/lang/Class
       7: ifeq          27
      10: aload_0
      11: getfield      #2                  // Field runtimeType:Ljava/lang/reflect/Type;
      14: checkcast     #12                 // class java/lang/Class
      17: invokevirtual #78                 // Method java/lang/Class.isPrimitive:()Z
      20: ifeq          27
      23: iconst_1
      24: goto          28
      27: iconst_0
      28: ireturn

  public final com.google.common.reflect.TypeToken<T> wrap();
    Code:
       0: aload_0
       1: invokevirtual #79                 // Method isPrimitive:()Z
       4: ifeq          23
       7: aload_0
       8: getfield      #2                  // Field runtimeType:Ljava/lang/reflect/Type;
      11: checkcast     #12                 // class java/lang/Class
      14: astore_1
      15: aload_1
      16: invokestatic  #80                 // Method com/google/common/primitives/Primitives.wrap:(Ljava/lang/Class;)Ljava/lang/Class;
      19: invokestatic  #28                 // Method of:(Ljava/lang/Class;)Lcom/google/common/reflect/TypeToken;
      22: areturn
      23: aload_0
      24: areturn

  public final com.google.common.reflect.TypeToken<T> unwrap();
    Code:
       0: aload_0
       1: invokespecial #83                 // Method isWrapper:()Z
       4: ifeq          23
       7: aload_0
       8: getfield      #2                  // Field runtimeType:Ljava/lang/reflect/Type;
      11: checkcast     #12                 // class java/lang/Class
      14: astore_1
      15: aload_1
      16: invokestatic  #84                 // Method com/google/common/primitives/Primitives.unwrap:(Ljava/lang/Class;)Ljava/lang/Class;
      19: invokestatic  #28                 // Method of:(Ljava/lang/Class;)Lcom/google/common/reflect/TypeToken;
      22: areturn
      23: aload_0
      24: areturn

  public final com.google.common.reflect.TypeToken<?> getComponentType();
    Code:
       0: aload_0
       1: getfield      #2                  // Field runtimeType:Ljava/lang/reflect/Type;
       4: invokestatic  #85                 // Method com/google/common/reflect/Types.getComponentType:(Ljava/lang/reflect/Type;)Ljava/lang/reflect/Type;
       7: astore_1
       8: aload_1
       9: ifnonnull     14
      12: aconst_null
      13: areturn
      14: aload_1
      15: invokestatic  #30                 // Method of:(Ljava/lang/reflect/Type;)Lcom/google/common/reflect/TypeToken;
      18: areturn

  public final com.google.common.reflect.Invokable<T, java.lang.Object> method(java.lang.reflect.Method);
    Code:
       0: aload_0
       1: aload_1
       2: invokevirtual #86                 // Method java/lang/reflect/Method.getDeclaringClass:()Ljava/lang/Class;
       5: invokespecial #48                 // Method someRawTypeIsSubclassOf:(Ljava/lang/Class;)Z
       8: ldc           #87                 // String %s not declared by %s
      10: aload_1
      11: aload_0
      12: invokestatic  #50                 // Method com/google/common/base/Preconditions.checkArgument:(ZLjava/lang/String;Ljava/lang/Object;Ljava/lang/Object;)V
      15: new           #88                 // class com/google/common/reflect/TypeToken$1
      18: dup
      19: aload_0
      20: aload_1
      21: invokespecial #89                 // Method com/google/common/reflect/TypeToken$1."<init>":(Lcom/google/common/reflect/TypeToken;Ljava/lang/reflect/Method;)V
      24: areturn

  public final com.google.common.reflect.Invokable<T, T> constructor(java.lang.reflect.Constructor<?>);
    Code:
       0: aload_1
       1: invokevirtual #90                 // Method java/lang/reflect/Constructor.getDeclaringClass:()Ljava/lang/Class;
       4: aload_0
       5: invokevirtual #37                 // Method getRawType:()Ljava/lang/Class;
       8: if_acmpne     15
      11: iconst_1
      12: goto          16
      15: iconst_0
      16: ldc           #87                 // String %s not declared by %s
      18: aload_1
      19: aload_0
      20: invokevirtual #37                 // Method getRawType:()Ljava/lang/Class;
      23: invokestatic  #50                 // Method com/google/common/base/Preconditions.checkArgument:(ZLjava/lang/String;Ljava/lang/Object;Ljava/lang/Object;)V
      26: new           #91                 // class com/google/common/reflect/TypeToken$2
      29: dup
      30: aload_0
      31: aload_1
      32: invokespecial #92                 // Method com/google/common/reflect/TypeToken$2."<init>":(Lcom/google/common/reflect/TypeToken;Ljava/lang/reflect/Constructor;)V
      35: areturn

  public boolean equals(java.lang.Object);
    Code:
       0: aload_1
       1: instanceof    #93                 // class com/google/common/reflect/TypeToken
       4: ifeq          24
       7: aload_1
       8: checkcast     #93                 // class com/google/common/reflect/TypeToken
      11: astore_2
      12: aload_0
      13: getfield      #2                  // Field runtimeType:Ljava/lang/reflect/Type;
      16: aload_2
      17: getfield      #2                  // Field runtimeType:Ljava/lang/reflect/Type;
      20: invokevirtual #71                 // Method java/lang/Object.equals:(Ljava/lang/Object;)Z
      23: ireturn
      24: iconst_0
      25: ireturn

  public int hashCode();
    Code:
       0: aload_0
       1: getfield      #2                  // Field runtimeType:Ljava/lang/reflect/Type;
       4: invokevirtual #94                 // Method java/lang/Object.hashCode:()I
       7: ireturn

  public java.lang.String toString();
    Code:
       0: aload_0
       1: getfield      #2                  // Field runtimeType:Ljava/lang/reflect/Type;
       4: invokestatic  #95                 // Method com/google/common/reflect/Types.toString:(Ljava/lang/reflect/Type;)Ljava/lang/String;
       7: areturn

  protected java.lang.Object writeReplace();
    Code:
       0: new           #21                 // class com/google/common/reflect/TypeResolver
       3: dup
       4: invokespecial #22                 // Method com/google/common/reflect/TypeResolver."<init>":()V
       7: aload_0
       8: getfield      #2                  // Field runtimeType:Ljava/lang/reflect/Type;
      11: invokevirtual #14                 // Method com/google/common/reflect/TypeResolver.resolveType:(Ljava/lang/reflect/Type;)Ljava/lang/reflect/Type;
      14: invokestatic  #30                 // Method of:(Ljava/lang/reflect/Type;)Lcom/google/common/reflect/TypeToken;
      17: areturn

  final com.google.common.reflect.TypeToken<T> rejectTypeVariables();
    Code:
       0: new           #96                 // class com/google/common/reflect/TypeToken$3
       3: dup
       4: aload_0
       5: invokespecial #97                 // Method com/google/common/reflect/TypeToken$3."<init>":(Lcom/google/common/reflect/TypeToken;)V
       8: iconst_1
       9: anewarray     #16                 // class java/lang/reflect/Type
      12: dup
      13: iconst_0
      14: aload_0
      15: getfield      #2                  // Field runtimeType:Ljava/lang/reflect/Type;
      18: aastore
      19: invokevirtual #98                 // Method com/google/common/reflect/TypeToken$3.visit:([Ljava/lang/reflect/Type;)V
      22: aload_0
      23: areturn

  static <T> com.google.common.reflect.TypeToken<? extends T> toGenericType(java.lang.Class<T>);
    Code:
       0: aload_0
       1: invokevirtual #52                 // Method java/lang/Class.isArray:()Z
       4: ifeq          28
       7: aload_0
       8: invokevirtual #109                // Method java/lang/Class.getComponentType:()Ljava/lang/Class;
      11: invokestatic  #54                 // Method toGenericType:(Ljava/lang/Class;)Lcom/google/common/reflect/TypeToken;
      14: getfield      #2                  // Field runtimeType:Ljava/lang/reflect/Type;
      17: invokestatic  #116                // Method com/google/common/reflect/Types.newArrayType:(Ljava/lang/reflect/Type;)Ljava/lang/reflect/Type;
      20: astore_1
      21: aload_1
      22: invokestatic  #30                 // Method of:(Ljava/lang/reflect/Type;)Lcom/google/common/reflect/TypeToken;
      25: astore_2
      26: aload_2
      27: areturn
      28: aload_0
      29: invokevirtual #101                // Method java/lang/Class.getTypeParameters:()[Ljava/lang/reflect/TypeVariable;
      32: astore_1
      33: aload_0
      34: invokevirtual #137                // Method java/lang/Class.isMemberClass:()Z
      37: ifeq          63
      40: aload_0
      41: invokevirtual #105                // Method java/lang/Class.getModifiers:()I
      44: invokestatic  #106                // Method java/lang/reflect/Modifier.isStatic:(I)Z
      47: ifne          63
      50: aload_0
      51: invokevirtual #136                // Method java/lang/Class.getEnclosingClass:()Ljava/lang/Class;
      54: invokestatic  #54                 // Method toGenericType:(Ljava/lang/Class;)Lcom/google/common/reflect/TypeToken;
      57: getfield      #2                  // Field runtimeType:Ljava/lang/reflect/Type;
      60: goto          64
      63: aconst_null
      64: astore_2
      65: aload_1
      66: arraylength
      67: ifgt          82
      70: aload_2
      71: ifnull        94
      74: aload_2
      75: aload_0
      76: invokevirtual #136                // Method java/lang/Class.getEnclosingClass:()Ljava/lang/Class;
      79: if_acmpeq     94
      82: aload_2
      83: aload_0
      84: aload_1
      85: invokestatic  #125                // Method com/google/common/reflect/Types.newParameterizedTypeWithOwner:(Ljava/lang/reflect/Type;Ljava/lang/Class;[Ljava/lang/reflect/Type;)Ljava/lang/reflect/ParameterizedType;
      88: invokestatic  #30                 // Method of:(Ljava/lang/reflect/Type;)Lcom/google/common/reflect/TypeToken;
      91: astore_3
      92: aload_3
      93: areturn
      94: aload_0
      95: invokestatic  #28                 // Method of:(Ljava/lang/Class;)Lcom/google/common/reflect/TypeToken;
      98: areturn

  static com.google.common.reflect.TypeResolver access$000(com.google.common.reflect.TypeToken);
    Code:
       0: aload_0
       1: invokespecial #5                  // Method getCovariantTypeResolver:()Lcom/google/common/reflect/TypeResolver;
       4: areturn

  static com.google.common.reflect.TypeResolver access$100(com.google.common.reflect.TypeToken);
    Code:
       0: aload_0
       1: invokespecial #4                  // Method getInvariantTypeResolver:()Lcom/google/common/reflect/TypeResolver;
       4: areturn

  static com.google.common.collect.ImmutableSet access$300(com.google.common.reflect.TypeToken);
    Code:
       0: aload_0
       1: invokespecial #3                  // Method getRawTypes:()Lcom/google/common/collect/ImmutableSet;
       4: areturn

  static java.lang.reflect.Type access$500(com.google.common.reflect.TypeToken);
    Code:
       0: aload_0
       1: getfield      #2                  // Field runtimeType:Ljava/lang/reflect/Type;
       4: areturn

  com.google.common.reflect.TypeToken(java.lang.reflect.Type, com.google.common.reflect.TypeToken$1);
    Code:
       0: aload_0
       1: aload_1
       2: invokespecial #1                  // Method "<init>":(Ljava/lang/reflect/Type;)V
       5: return
}
