Compiled from "UsingToStringOrdering.java"
final class com.google.common.collect.UsingToStringOrdering extends com.google.common.collect.Ordering<java.lang.Object> implements java.io.Serializable {
  static final com.google.common.collect.UsingToStringOrdering INSTANCE;

  public int compare(java.lang.Object, java.lang.Object);
    Code:
       0: aload_1
       1: invokevirtual #1                  // Method java/lang/Object.toString:()Ljava/lang/String;
       4: aload_2
       5: invokevirtual #1                  // Method java/lang/Object.toString:()Ljava/lang/String;
       8: invokevirtual #2                  // Method java/lang/String.compareTo:(Ljava/lang/String;)I
      11: ireturn

  public java.lang.String toString();
    Code:
       0: ldc           #4                  // String Ordering.usingToString()
       2: areturn

  static {};
    Code:
       0: new           #6                  // class com/google/common/collect/UsingToStringOrdering
       3: dup
       4: invokespecial #7                  // Method "<init>":()V
       7: putstatic     #3                  // Field INSTANCE:Lcom/google/common/collect/UsingToStringOrdering;
      10: return
}
