Compiled from "ValueGraphBuilder.java"
public final class com.google.common.graph.ValueGraphBuilder<N, V> extends com.google.common.graph.AbstractGraphBuilder<N> {
  public static com.google.common.graph.ValueGraphBuilder<java.lang.Object, java.lang.Object> directed();
    Code:
       0: new           #2                  // class com/google/common/graph/ValueGraphBuilder
       3: dup
       4: iconst_1
       5: invokespecial #3                  // Method "<init>":(Z)V
       8: areturn

  public static com.google.common.graph.ValueGraphBuilder<java.lang.Object, java.lang.Object> undirected();
    Code:
       0: new           #2                  // class com/google/common/graph/ValueGraphBuilder
       3: dup
       4: iconst_0
       5: invokespecial #3                  // Method "<init>":(Z)V
       8: areturn

  public static <N, V> com.google.common.graph.ValueGraphBuilder<N, V> from(com.google.common.graph.ValueGraph<N, V>);
    Code:
       0: new           #2                  // class com/google/common/graph/ValueGraphBuilder
       3: dup
       4: aload_0
       5: invokeinterface #4,  1            // InterfaceMethod com/google/common/graph/ValueGraph.isDirected:()Z
      10: invokespecial #3                  // Method "<init>":(Z)V
      13: aload_0
      14: invokeinterface #5,  1            // InterfaceMethod com/google/common/graph/ValueGraph.allowsSelfLoops:()Z
      19: invokevirtual #6                  // Method allowsSelfLoops:(Z)Lcom/google/common/graph/ValueGraphBuilder;
      22: aload_0
      23: invokeinterface #7,  1            // InterfaceMethod com/google/common/graph/ValueGraph.nodeOrder:()Lcom/google/common/graph/ElementOrder;
      28: invokevirtual #8                  // Method nodeOrder:(Lcom/google/common/graph/ElementOrder;)Lcom/google/common/graph/ValueGraphBuilder;
      31: areturn

  public <N1 extends N, V1 extends V> com.google.common.graph.ImmutableValueGraph$Builder<N1, V1> immutable();
    Code:
       0: aload_0
       1: invokespecial #9                  // Method cast:()Lcom/google/common/graph/ValueGraphBuilder;
       4: astore_1
       5: new           #10                 // class com/google/common/graph/ImmutableValueGraph$Builder
       8: dup
       9: aload_1
      10: invokespecial #11                 // Method com/google/common/graph/ImmutableValueGraph$Builder."<init>":(Lcom/google/common/graph/ValueGraphBuilder;)V
      13: areturn

  public com.google.common.graph.ValueGraphBuilder<N, V> allowsSelfLoops(boolean);
    Code:
       0: aload_0
       1: iload_1
       2: putfield      #12                 // Field allowsSelfLoops:Z
       5: aload_0
       6: areturn

  public com.google.common.graph.ValueGraphBuilder<N, V> expectedNodeCount(int);
    Code:
       0: aload_0
       1: iload_1
       2: invokestatic  #13                 // Method com/google/common/graph/Graphs.checkNonNegative:(I)I
       5: invokestatic  #14                 // Method java/lang/Integer.valueOf:(I)Ljava/lang/Integer;
       8: invokestatic  #15                 // Method com/google/common/base/Optional.of:(Ljava/lang/Object;)Lcom/google/common/base/Optional;
      11: putfield      #16                 // Field expectedNodeCount:Lcom/google/common/base/Optional;
      14: aload_0
      15: areturn

  public <N1 extends N> com.google.common.graph.ValueGraphBuilder<N1, V> nodeOrder(com.google.common.graph.ElementOrder<N1>);
    Code:
       0: aload_0
       1: invokespecial #9                  // Method cast:()Lcom/google/common/graph/ValueGraphBuilder;
       4: astore_2
       5: aload_2
       6: aload_1
       7: invokestatic  #17                 // Method com/google/common/base/Preconditions.checkNotNull:(Ljava/lang/Object;)Ljava/lang/Object;
      10: checkcast     #18                 // class com/google/common/graph/ElementOrder
      13: putfield      #19                 // Field nodeOrder:Lcom/google/common/graph/ElementOrder;
      16: aload_2
      17: areturn

  public <N1 extends N, V1 extends V> com.google.common.graph.MutableValueGraph<N1, V1> build();
    Code:
       0: new           #20                 // class com/google/common/graph/ConfigurableMutableValueGraph
       3: dup
       4: aload_0
       5: invokespecial #21                 // Method com/google/common/graph/ConfigurableMutableValueGraph."<init>":(Lcom/google/common/graph/AbstractGraphBuilder;)V
       8: areturn
}
