Compiled from "AbstractBiMap.java"
class com.google.common.collect.AbstractBiMap$Inverse<K, V> extends com.google.common.collect.AbstractBiMap<K, V> {
  com.google.common.collect.AbstractBiMap$Inverse(java.util.Map<K, V>, com.google.common.collect.AbstractBiMap<V, K>);
    Code:
       0: aload_0
       1: aload_1
       2: aload_2
       3: aconst_null
       4: invokespecial #1                  // Method com/google/common/collect/AbstractBiMap."<init>":(Ljava/util/Map;Lcom/google/common/collect/AbstractBiMap;Lcom/google/common/collect/AbstractBiMap$1;)V
       7: return

  K checkKey(K);
    Code:
       0: aload_0
       1: getfield      #2                  // Field inverse:Lcom/google/common/collect/AbstractBiMap;
       4: aload_1
       5: invokevirtual #3                  // Method com/google/common/collect/AbstractBiMap.checkValue:(Ljava/lang/Object;)Ljava/lang/Object;
       8: areturn

  V checkValue(V);
    Code:
       0: aload_0
       1: getfield      #2                  // Field inverse:Lcom/google/common/collect/AbstractBiMap;
       4: aload_1
       5: invokevirtual #4                  // Method com/google/common/collect/AbstractBiMap.checkKey:(Ljava/lang/Object;)Ljava/lang/Object;
       8: areturn

  java.lang.Object readResolve();
    Code:
       0: aload_0
       1: invokevirtual #6                  // Method inverse:()Lcom/google/common/collect/BiMap;
       4: invokeinterface #12,  1           // InterfaceMethod com/google/common/collect/BiMap.inverse:()Lcom/google/common/collect/BiMap;
       9: areturn

  public java.util.Collection values();
    Code:
       0: aload_0
       1: invokespecial #13                 // Method com/google/common/collect/AbstractBiMap.values:()Ljava/util/Set;
       4: areturn

  protected java.lang.Object delegate();
    Code:
       0: aload_0
       1: invokespecial #14                 // Method com/google/common/collect/AbstractBiMap.delegate:()Ljava/util/Map;
       4: areturn
}
