Compiled from "HashBiMap.java"
public final class com.google.common.collect.HashBiMap<K, V> extends com.google.common.collect.Maps$IteratorBasedAbstractMap<K, V> implements com.google.common.collect.BiMap<K, V>, java.io.Serializable {
  public static <K, V> com.google.common.collect.HashBiMap<K, V> create();
    Code:
       0: bipush        16
       2: invokestatic  #9                  // Method create:(I)Lcom/google/common/collect/HashBiMap;
       5: areturn

  public static <K, V> com.google.common.collect.HashBiMap<K, V> create(int);
    Code:
       0: new           #10                 // class com/google/common/collect/HashBiMap
       3: dup
       4: iload_0
       5: invokespecial #11                 // Method "<init>":(I)V
       8: areturn

  public static <K, V> com.google.common.collect.HashBiMap<K, V> create(java.util.Map<? extends K, ? extends V>);
    Code:
       0: aload_0
       1: invokeinterface #12,  1           // InterfaceMethod java/util/Map.size:()I
       6: invokestatic  #9                  // Method create:(I)Lcom/google/common/collect/HashBiMap;
       9: astore_1
      10: aload_1
      11: aload_0
      12: invokevirtual #13                 // Method putAll:(Ljava/util/Map;)V
      15: aload_1
      16: areturn

  public boolean containsKey(java.lang.Object);
    Code:
       0: aload_0
       1: aload_1
       2: aload_1
       3: invokestatic  #33                 // Method com/google/common/collect/Hashing.smearedHash:(Ljava/lang/Object;)I
       6: invokespecial #5                  // Method seekByKey:(Ljava/lang/Object;I)Lcom/google/common/collect/HashBiMap$BiEntry;
       9: ifnull        16
      12: iconst_1
      13: goto          17
      16: iconst_0
      17: ireturn

  public boolean containsValue(java.lang.Object);
    Code:
       0: aload_0
       1: aload_1
       2: aload_1
       3: invokestatic  #33                 // Method com/google/common/collect/Hashing.smearedHash:(Ljava/lang/Object;)I
       6: invokespecial #4                  // Method seekByValue:(Ljava/lang/Object;I)Lcom/google/common/collect/HashBiMap$BiEntry;
       9: ifnull        16
      12: iconst_1
      13: goto          17
      16: iconst_0
      17: ireturn

  public V get(java.lang.Object);
    Code:
       0: aload_0
       1: aload_1
       2: aload_1
       3: invokestatic  #33                 // Method com/google/common/collect/Hashing.smearedHash:(Ljava/lang/Object;)I
       6: invokespecial #5                  // Method seekByKey:(Ljava/lang/Object;I)Lcom/google/common/collect/HashBiMap$BiEntry;
       9: invokestatic  #34                 // Method com/google/common/collect/Maps.valueOrNull:(Ljava/util/Map$Entry;)Ljava/lang/Object;
      12: areturn

  public V put(K, V);
    Code:
       0: aload_0
       1: aload_1
       2: aload_2
       3: iconst_0
       4: invokespecial #35                 // Method put:(Ljava/lang/Object;Ljava/lang/Object;Z)Ljava/lang/Object;
       7: areturn

  public V forcePut(K, V);
    Code:
       0: aload_0
       1: aload_1
       2: aload_2
       3: iconst_1
       4: invokespecial #35                 // Method put:(Ljava/lang/Object;Ljava/lang/Object;Z)Ljava/lang/Object;
       7: areturn

  public V remove(java.lang.Object);
    Code:
       0: aload_0
       1: aload_1
       2: aload_1
       3: invokestatic  #33                 // Method com/google/common/collect/Hashing.smearedHash:(Ljava/lang/Object;)I
       6: invokespecial #5                  // Method seekByKey:(Ljava/lang/Object;I)Lcom/google/common/collect/HashBiMap$BiEntry;
       9: astore_2
      10: aload_2
      11: ifnonnull     16
      14: aconst_null
      15: areturn
      16: aload_0
      17: aload_2
      18: invokespecial #6                  // Method delete:(Lcom/google/common/collect/HashBiMap$BiEntry;)V
      21: aload_2
      22: aconst_null
      23: putfield      #28                 // Field com/google/common/collect/HashBiMap$BiEntry.prevInKeyInsertionOrder:Lcom/google/common/collect/HashBiMap$BiEntry;
      26: aload_2
      27: aconst_null
      28: putfield      #29                 // Field com/google/common/collect/HashBiMap$BiEntry.nextInKeyInsertionOrder:Lcom/google/common/collect/HashBiMap$BiEntry;
      31: aload_2
      32: getfield      #32                 // Field com/google/common/collect/HashBiMap$BiEntry.value:Ljava/lang/Object;
      35: areturn

  public void clear();
    Code:
       0: aload_0
       1: iconst_0
       2: putfield      #2                  // Field size:I
       5: aload_0
       6: getfield      #20                 // Field hashTableKToV:[Lcom/google/common/collect/HashBiMap$BiEntry;
       9: aconst_null
      10: invokestatic  #50                 // Method java/util/Arrays.fill:([Ljava/lang/Object;Ljava/lang/Object;)V
      13: aload_0
      14: getfield      #21                 // Field hashTableVToK:[Lcom/google/common/collect/HashBiMap$BiEntry;
      17: aconst_null
      18: invokestatic  #50                 // Method java/util/Arrays.fill:([Ljava/lang/Object;Ljava/lang/Object;)V
      21: aload_0
      22: aconst_null
      23: putfield      #8                  // Field firstInKeyInsertionOrder:Lcom/google/common/collect/HashBiMap$BiEntry;
      26: aload_0
      27: aconst_null
      28: putfield      #22                 // Field lastInKeyInsertionOrder:Lcom/google/common/collect/HashBiMap$BiEntry;
      31: aload_0
      32: dup
      33: getfield      #7                  // Field modCount:I
      36: iconst_1
      37: iadd
      38: putfield      #7                  // Field modCount:I
      41: return

  public int size();
    Code:
       0: aload_0
       1: getfield      #2                  // Field size:I
       4: ireturn

  public java.util.Set<K> keySet();
    Code:
       0: new           #51                 // class com/google/common/collect/HashBiMap$KeySet
       3: dup
       4: aload_0
       5: invokespecial #52                 // Method com/google/common/collect/HashBiMap$KeySet."<init>":(Lcom/google/common/collect/HashBiMap;)V
       8: areturn

  public java.util.Set<V> values();
    Code:
       0: aload_0
       1: invokevirtual #53                 // Method inverse:()Lcom/google/common/collect/BiMap;
       4: invokeinterface #54,  1           // InterfaceMethod com/google/common/collect/BiMap.keySet:()Ljava/util/Set;
       9: areturn

  java.util.Iterator<java.util.Map$Entry<K, V>> entryIterator();
    Code:
       0: new           #55                 // class com/google/common/collect/HashBiMap$1
       3: dup
       4: aload_0
       5: invokespecial #56                 // Method com/google/common/collect/HashBiMap$1."<init>":(Lcom/google/common/collect/HashBiMap;)V
       8: areturn

  public void forEach(java.util.function.BiConsumer<? super K, ? super V>);
    Code:
       0: aload_1
       1: invokestatic  #57                 // Method com/google/common/base/Preconditions.checkNotNull:(Ljava/lang/Object;)Ljava/lang/Object;
       4: pop
       5: aload_0
       6: getfield      #8                  // Field firstInKeyInsertionOrder:Lcom/google/common/collect/HashBiMap$BiEntry;
       9: astore_2
      10: aload_2
      11: ifnull        36
      14: aload_1
      15: aload_2
      16: getfield      #30                 // Field com/google/common/collect/HashBiMap$BiEntry.key:Ljava/lang/Object;
      19: aload_2
      20: getfield      #32                 // Field com/google/common/collect/HashBiMap$BiEntry.value:Ljava/lang/Object;
      23: invokeinterface #58,  3           // InterfaceMethod java/util/function/BiConsumer.accept:(Ljava/lang/Object;Ljava/lang/Object;)V
      28: aload_2
      29: getfield      #29                 // Field com/google/common/collect/HashBiMap$BiEntry.nextInKeyInsertionOrder:Lcom/google/common/collect/HashBiMap$BiEntry;
      32: astore_2
      33: goto          10
      36: return

  public void replaceAll(java.util.function.BiFunction<? super K, ? super V, ? extends V>);
    Code:
       0: aload_1
       1: invokestatic  #57                 // Method com/google/common/base/Preconditions.checkNotNull:(Ljava/lang/Object;)Ljava/lang/Object;
       4: pop
       5: aload_0
       6: getfield      #8                  // Field firstInKeyInsertionOrder:Lcom/google/common/collect/HashBiMap$BiEntry;
       9: astore_2
      10: aload_0
      11: invokevirtual #59                 // Method clear:()V
      14: aload_2
      15: astore_3
      16: aload_3
      17: ifnull        51
      20: aload_0
      21: aload_3
      22: getfield      #30                 // Field com/google/common/collect/HashBiMap$BiEntry.key:Ljava/lang/Object;
      25: aload_1
      26: aload_3
      27: getfield      #30                 // Field com/google/common/collect/HashBiMap$BiEntry.key:Ljava/lang/Object;
      30: aload_3
      31: getfield      #32                 // Field com/google/common/collect/HashBiMap$BiEntry.value:Ljava/lang/Object;
      34: invokeinterface #60,  3           // InterfaceMethod java/util/function/BiFunction.apply:(Ljava/lang/Object;Ljava/lang/Object;)Ljava/lang/Object;
      39: invokevirtual #61                 // Method put:(Ljava/lang/Object;Ljava/lang/Object;)Ljava/lang/Object;
      42: pop
      43: aload_3
      44: getfield      #29                 // Field com/google/common/collect/HashBiMap$BiEntry.nextInKeyInsertionOrder:Lcom/google/common/collect/HashBiMap$BiEntry;
      47: astore_3
      48: goto          16
      51: return

  public com.google.common.collect.BiMap<V, K> inverse();
    Code:
       0: aload_0
       1: getfield      #62                 // Field inverse:Lcom/google/common/collect/BiMap;
       4: astore_1
       5: aload_1
       6: ifnonnull     26
       9: aload_0
      10: new           #63                 // class com/google/common/collect/HashBiMap$Inverse
      13: dup
      14: aload_0
      15: aconst_null
      16: invokespecial #64                 // Method com/google/common/collect/HashBiMap$Inverse."<init>":(Lcom/google/common/collect/HashBiMap;Lcom/google/common/collect/HashBiMap$1;)V
      19: dup_x1
      20: putfield      #62                 // Field inverse:Lcom/google/common/collect/BiMap;
      23: goto          27
      26: aload_1
      27: areturn

  public java.util.Set entrySet();
    Code:
       0: aload_0
       1: invokespecial #70                 // Method com/google/common/collect/Maps$IteratorBasedAbstractMap.entrySet:()Ljava/util/Set;
       4: areturn

  public java.util.Collection values();
    Code:
       0: aload_0
       1: invokevirtual #71                 // Method values:()Ljava/util/Set;
       4: areturn

  static com.google.common.collect.HashBiMap$BiEntry access$000(com.google.common.collect.HashBiMap);
    Code:
       0: aload_0
       1: getfield      #8                  // Field firstInKeyInsertionOrder:Lcom/google/common/collect/HashBiMap$BiEntry;
       4: areturn

  static int access$100(com.google.common.collect.HashBiMap);
    Code:
       0: aload_0
       1: getfield      #7                  // Field modCount:I
       4: ireturn

  static void access$200(com.google.common.collect.HashBiMap, com.google.common.collect.HashBiMap$BiEntry);
    Code:
       0: aload_0
       1: aload_1
       2: invokespecial #6                  // Method delete:(Lcom/google/common/collect/HashBiMap$BiEntry;)V
       5: return

  static com.google.common.collect.HashBiMap$BiEntry access$300(com.google.common.collect.HashBiMap, java.lang.Object, int);
    Code:
       0: aload_0
       1: aload_1
       2: iload_2
       3: invokespecial #5                  // Method seekByKey:(Ljava/lang/Object;I)Lcom/google/common/collect/HashBiMap$BiEntry;
       6: areturn

  static com.google.common.collect.HashBiMap$BiEntry access$400(com.google.common.collect.HashBiMap, java.lang.Object, int);
    Code:
       0: aload_0
       1: aload_1
       2: iload_2
       3: invokespecial #4                  // Method seekByValue:(Ljava/lang/Object;I)Lcom/google/common/collect/HashBiMap$BiEntry;
       6: areturn

  static void access$500(com.google.common.collect.HashBiMap, com.google.common.collect.HashBiMap$BiEntry, com.google.common.collect.HashBiMap$BiEntry);
    Code:
       0: aload_0
       1: aload_1
       2: aload_2
       3: invokespecial #3                  // Method insert:(Lcom/google/common/collect/HashBiMap$BiEntry;Lcom/google/common/collect/HashBiMap$BiEntry;)V
       6: return

  static int access$700(com.google.common.collect.HashBiMap);
    Code:
       0: aload_0
       1: getfield      #2                  // Field size:I
       4: ireturn

  static java.lang.Object access$800(com.google.common.collect.HashBiMap, java.lang.Object, java.lang.Object, boolean);
    Code:
       0: aload_0
       1: aload_1
       2: aload_2
       3: iload_3
       4: invokespecial #1                  // Method putInverse:(Ljava/lang/Object;Ljava/lang/Object;Z)Ljava/lang/Object;
       7: areturn
}
