Compiled from "HashMultiset.java"
public final class com.google.common.collect.HashMultiset<E> extends com.google.common.collect.AbstractMapBasedMultiset<E> {
  public static <E> com.google.common.collect.HashMultiset<E> create();
    Code:
       0: new           #1                  // class com/google/common/collect/HashMultiset
       3: dup
       4: invokespecial #2                  // Method "<init>":()V
       7: areturn

  public static <E> com.google.common.collect.HashMultiset<E> create(int);
    Code:
       0: new           #1                  // class com/google/common/collect/HashMultiset
       3: dup
       4: iload_0
       5: invokespecial #3                  // Method "<init>":(I)V
       8: areturn

  public static <E> com.google.common.collect.HashMultiset<E> create(java.lang.Iterable<? extends E>);
    Code:
       0: aload_0
       1: invokestatic  #4                  // Method com/google/common/collect/Multisets.inferDistinctElements:(Ljava/lang/Iterable;)I
       4: invokestatic  #5                  // Method create:(I)Lcom/google/common/collect/HashMultiset;
       7: astore_1
       8: aload_1
       9: aload_0
      10: invokestatic  #6                  // Method com/google/common/collect/Iterables.addAll:(Ljava/util/Collection;Ljava/lang/Iterable;)Z
      13: pop
      14: aload_1
      15: areturn

  public int setCount(java.lang.Object, int);
    Code:
       0: aload_0
       1: aload_1
       2: iload_2
       3: invokespecial #18                 // Method com/google/common/collect/AbstractMapBasedMultiset.setCount:(Ljava/lang/Object;I)I
       6: ireturn

  public int remove(java.lang.Object, int);
    Code:
       0: aload_0
       1: aload_1
       2: iload_2
       3: invokespecial #19                 // Method com/google/common/collect/AbstractMapBasedMultiset.remove:(Ljava/lang/Object;I)I
       6: ireturn

  public int add(java.lang.Object, int);
    Code:
       0: aload_0
       1: aload_1
       2: iload_2
       3: invokespecial #20                 // Method com/google/common/collect/AbstractMapBasedMultiset.add:(Ljava/lang/Object;I)I
       6: ireturn

  public int count(java.lang.Object);
    Code:
       0: aload_0
       1: aload_1
       2: invokespecial #21                 // Method com/google/common/collect/AbstractMapBasedMultiset.count:(Ljava/lang/Object;)I
       5: ireturn

  public java.util.Iterator iterator();
    Code:
       0: aload_0
       1: invokespecial #22                 // Method com/google/common/collect/AbstractMapBasedMultiset.iterator:()Ljava/util/Iterator;
       4: areturn

  public int size();
    Code:
       0: aload_0
       1: invokespecial #23                 // Method com/google/common/collect/AbstractMapBasedMultiset.size:()I
       4: ireturn

  public void clear();
    Code:
       0: aload_0
       1: invokespecial #24                 // Method com/google/common/collect/AbstractMapBasedMultiset.clear:()V
       4: return

  public void forEachEntry(java.util.function.ObjIntConsumer);
    Code:
       0: aload_0
       1: aload_1
       2: invokespecial #25                 // Method com/google/common/collect/AbstractMapBasedMultiset.forEachEntry:(Ljava/util/function/ObjIntConsumer;)V
       5: return

  public java.util.Set entrySet();
    Code:
       0: aload_0
       1: invokespecial #26                 // Method com/google/common/collect/AbstractMapBasedMultiset.entrySet:()Ljava/util/Set;
       4: areturn

  public java.util.Set elementSet();
    Code:
       0: aload_0
       1: invokespecial #27                 // Method com/google/common/collect/AbstractMapBasedMultiset.elementSet:()Ljava/util/Set;
       4: areturn

  public boolean setCount(java.lang.Object, int, int);
    Code:
       0: aload_0
       1: aload_1
       2: iload_2
       3: iload_3
       4: invokespecial #28                 // Method com/google/common/collect/AbstractMapBasedMultiset.setCount:(Ljava/lang/Object;II)Z
       7: ireturn

  public boolean contains(java.lang.Object);
    Code:
       0: aload_0
       1: aload_1
       2: invokespecial #29                 // Method com/google/common/collect/AbstractMapBasedMultiset.contains:(Ljava/lang/Object;)Z
       5: ireturn

  public boolean isEmpty();
    Code:
       0: aload_0
       1: invokespecial #30                 // Method com/google/common/collect/AbstractMapBasedMultiset.isEmpty:()Z
       4: ireturn
}
