Compiled from "I18nFormatUtil.java"
class org.checkerframework.checker.i18nformatter.I18nFormatUtil$MessageFormatParser {
  public static int maxOffset;

  public static org.checkerframework.checker.i18nformatter.I18nFormatUtil$I18nConversion[] parse(java.lang.String);
    Code:
       0: new           #2                  // class java/util/ArrayList
       3: dup
       4: invokespecial #3                  // Method java/util/ArrayList."<init>":()V
       7: putstatic     #4                  // Field categories:Ljava/util/List;
      10: new           #2                  // class java/util/ArrayList
      13: dup
      14: invokespecial #3                  // Method java/util/ArrayList."<init>":()V
      17: putstatic     #5                  // Field argumentIndices:Ljava/util/List;
      20: getstatic     #6                  // Field java/util/Locale$Category.FORMAT:Ljava/util/Locale$Category;
      23: invokestatic  #7                  // Method java/util/Locale.getDefault:(Ljava/util/Locale$Category;)Ljava/util/Locale;
      26: putstatic     #8                  // Field locale:Ljava/util/Locale;
      29: aload_0
      30: invokestatic  #9                  // Method applyPattern:(Ljava/lang/String;)V
      33: getstatic     #10                 // Field numFormat:I
      36: anewarray     #11                 // class org/checkerframework/checker/i18nformatter/I18nFormatUtil$I18nConversion
      39: astore_1
      40: iconst_0
      41: istore_2
      42: iload_2
      43: getstatic     #10                 // Field numFormat:I
      46: if_icmpge     92
      49: aload_1
      50: iload_2
      51: new           #11                 // class org/checkerframework/checker/i18nformatter/I18nFormatUtil$I18nConversion
      54: dup
      55: getstatic     #5                  // Field argumentIndices:Ljava/util/List;
      58: iload_2
      59: invokeinterface #12,  2           // InterfaceMethod java/util/List.get:(I)Ljava/lang/Object;
      64: checkcast     #13                 // class java/lang/Integer
      67: invokevirtual #14                 // Method java/lang/Integer.intValue:()I
      70: getstatic     #4                  // Field categories:Ljava/util/List;
      73: iload_2
      74: invokeinterface #12,  2           // InterfaceMethod java/util/List.get:(I)Ljava/lang/Object;
      79: checkcast     #15                 // class org/checkerframework/checker/i18nformatter/qual/I18nConversionCategory
      82: invokespecial #16                 // Method org/checkerframework/checker/i18nformatter/I18nFormatUtil$I18nConversion."<init>":(ILorg/checkerframework/checker/i18nformatter/qual/I18nConversionCategory;)V
      85: aastore
      86: iinc          2, 1
      89: goto          42
      92: aload_1
      93: areturn

  static {};
    Code:
       0: iconst_5
       1: anewarray     #29                 // class java/lang/String
       4: dup
       5: iconst_0
       6: ldc           #31                 // String
       8: aastore
       9: dup
      10: iconst_1
      11: ldc           #63                 // String number
      13: aastore
      14: dup
      15: iconst_2
      16: ldc           #64                 // String date
      18: aastore
      19: dup
      20: iconst_3
      21: ldc           #65                 // String time
      23: aastore
      24: dup
      25: iconst_4
      26: ldc           #66                 // String choice
      28: aastore
      29: putstatic     #41                 // Field TYPE_KEYWORDS:[Ljava/lang/String;
      32: iconst_4
      33: anewarray     #29                 // class java/lang/String
      36: dup
      37: iconst_0
      38: ldc           #31                 // String
      40: aastore
      41: dup
      42: iconst_1
      43: ldc           #67                 // String currency
      45: aastore
      46: dup
      47: iconst_2
      48: ldc           #68                 // String percent
      50: aastore
      51: dup
      52: iconst_3
      53: ldc           #69                 // String integer
      55: aastore
      56: putstatic     #44                 // Field NUMBER_MODIFIER_KEYWORDS:[Ljava/lang/String;
      59: iconst_5
      60: anewarray     #29                 // class java/lang/String
      63: dup
      64: iconst_0
      65: ldc           #31                 // String
      67: aastore
      68: dup
      69: iconst_1
      70: ldc           #70                 // String short
      72: aastore
      73: dup
      74: iconst_2
      75: ldc           #71                 // String medium
      77: aastore
      78: dup
      79: iconst_3
      80: ldc           #72                 // String long
      82: aastore
      83: dup
      84: iconst_4
      85: ldc           #73                 // String full
      87: aastore
      88: putstatic     #49                 // Field DATE_TIME_MODIFIER_KEYWORDS:[Ljava/lang/String;
      91: return
}
