Compiled from "ImmutableGraph.java"
public class com.google.common.graph.ImmutableGraph<N> extends com.google.common.graph.ForwardingGraph<N> {
  com.google.common.graph.ImmutableGraph(com.google.common.graph.BaseGraph<N>);
    Code:
       0: aload_0
       1: invokespecial #1                  // Method com/google/common/graph/ForwardingGraph."<init>":()V
       4: aload_0
       5: aload_1
       6: putfield      #2                  // Field backingGraph:Lcom/google/common/graph/BaseGraph;
       9: return

  public static <N> com.google.common.graph.ImmutableGraph<N> copyOf(com.google.common.graph.Graph<N>);
    Code:
       0: aload_0
       1: instanceof    #3                  // class com/google/common/graph/ImmutableGraph
       4: ifeq          14
       7: aload_0
       8: checkcast     #3                  // class com/google/common/graph/ImmutableGraph
      11: goto          48
      14: new           #3                  // class com/google/common/graph/ImmutableGraph
      17: dup
      18: new           #4                  // class com/google/common/graph/ConfigurableValueGraph
      21: dup
      22: aload_0
      23: invokestatic  #5                  // Method com/google/common/graph/GraphBuilder.from:(Lcom/google/common/graph/Graph;)Lcom/google/common/graph/GraphBuilder;
      26: aload_0
      27: invokestatic  #6                  // Method getNodeConnections:(Lcom/google/common/graph/Graph;)Lcom/google/common/collect/ImmutableMap;
      30: aload_0
      31: invokeinterface #7,  1            // InterfaceMethod com/google/common/graph/Graph.edges:()Ljava/util/Set;
      36: invokeinterface #8,  1            // InterfaceMethod java/util/Set.size:()I
      41: i2l
      42: invokespecial #9                  // Method com/google/common/graph/ConfigurableValueGraph."<init>":(Lcom/google/common/graph/AbstractGraphBuilder;Ljava/util/Map;J)V
      45: invokespecial #10                 // Method "<init>":(Lcom/google/common/graph/BaseGraph;)V
      48: areturn

  public static <N> com.google.common.graph.ImmutableGraph<N> copyOf(com.google.common.graph.ImmutableGraph<N>);
    Code:
       0: aload_0
       1: invokestatic  #11                 // Method com/google/common/base/Preconditions.checkNotNull:(Ljava/lang/Object;)Ljava/lang/Object;
       4: checkcast     #3                  // class com/google/common/graph/ImmutableGraph
       7: areturn

  protected com.google.common.graph.BaseGraph<N> delegate();
    Code:
       0: aload_0
       1: getfield      #2                  // Field backingGraph:Lcom/google/common/graph/BaseGraph;
       4: areturn

  public boolean hasEdgeConnecting(com.google.common.graph.EndpointPair);
    Code:
       0: aload_0
       1: aload_1
       2: invokespecial #29                 // Method com/google/common/graph/ForwardingGraph.hasEdgeConnecting:(Lcom/google/common/graph/EndpointPair;)Z
       5: ireturn

  public boolean hasEdgeConnecting(java.lang.Object, java.lang.Object);
    Code:
       0: aload_0
       1: aload_1
       2: aload_2
       3: invokespecial #30                 // Method com/google/common/graph/ForwardingGraph.hasEdgeConnecting:(Ljava/lang/Object;Ljava/lang/Object;)Z
       6: ireturn

  public int outDegree(java.lang.Object);
    Code:
       0: aload_0
       1: aload_1
       2: invokespecial #31                 // Method com/google/common/graph/ForwardingGraph.outDegree:(Ljava/lang/Object;)I
       5: ireturn

  public int inDegree(java.lang.Object);
    Code:
       0: aload_0
       1: aload_1
       2: invokespecial #32                 // Method com/google/common/graph/ForwardingGraph.inDegree:(Ljava/lang/Object;)I
       5: ireturn

  public int degree(java.lang.Object);
    Code:
       0: aload_0
       1: aload_1
       2: invokespecial #33                 // Method com/google/common/graph/ForwardingGraph.degree:(Ljava/lang/Object;)I
       5: ireturn

  public java.util.Set successors(java.lang.Object);
    Code:
       0: aload_0
       1: aload_1
       2: invokespecial #34                 // Method com/google/common/graph/ForwardingGraph.successors:(Ljava/lang/Object;)Ljava/util/Set;
       5: areturn

  public java.util.Set predecessors(java.lang.Object);
    Code:
       0: aload_0
       1: aload_1
       2: invokespecial #35                 // Method com/google/common/graph/ForwardingGraph.predecessors:(Ljava/lang/Object;)Ljava/util/Set;
       5: areturn

  public java.util.Set adjacentNodes(java.lang.Object);
    Code:
       0: aload_0
       1: aload_1
       2: invokespecial #36                 // Method com/google/common/graph/ForwardingGraph.adjacentNodes:(Ljava/lang/Object;)Ljava/util/Set;
       5: areturn

  public com.google.common.graph.ElementOrder nodeOrder();
    Code:
       0: aload_0
       1: invokespecial #37                 // Method com/google/common/graph/ForwardingGraph.nodeOrder:()Lcom/google/common/graph/ElementOrder;
       4: areturn

  public boolean allowsSelfLoops();
    Code:
       0: aload_0
       1: invokespecial #38                 // Method com/google/common/graph/ForwardingGraph.allowsSelfLoops:()Z
       4: ireturn

  public boolean isDirected();
    Code:
       0: aload_0
       1: invokespecial #39                 // Method com/google/common/graph/ForwardingGraph.isDirected:()Z
       4: ireturn

  public java.util.Set nodes();
    Code:
       0: aload_0
       1: invokespecial #40                 // Method com/google/common/graph/ForwardingGraph.nodes:()Ljava/util/Set;
       4: areturn
}
