Compiled from "ImmutableSortedMap.java"
public final class com.google.common.collect.ImmutableSortedMap<K, V> extends com.google.common.collect.ImmutableSortedMapFauxverideShim<K, V> implements java.util.NavigableMap<K, V> {
  public static <T, K, V> java.util.stream.Collector<T, ?, com.google.common.collect.ImmutableSortedMap<K, V>> toImmutableSortedMap(java.util.Comparator<? super K>, java.util.function.Function<? super T, ? extends K>, java.util.function.Function<? super T, ? extends V>);
    Code:
       0: aload_0
       1: aload_1
       2: aload_2
       3: invokestatic  #5                  // Method com/google/common/collect/CollectCollectors.toImmutableSortedMap:(Ljava/util/Comparator;Ljava/util/function/Function;Ljava/util/function/Function;)Ljava/util/stream/Collector;
       6: areturn

  public static <T, K, V> java.util.stream.Collector<T, ?, com.google.common.collect.ImmutableSortedMap<K, V>> toImmutableSortedMap(java.util.Comparator<? super K>, java.util.function.Function<? super T, ? extends K>, java.util.function.Function<? super T, ? extends V>, java.util.function.BinaryOperator<V>);
    Code:
       0: aload_0
       1: invokestatic  #6                  // Method com/google/common/base/Preconditions.checkNotNull:(Ljava/lang/Object;)Ljava/lang/Object;
       4: pop
       5: aload_1
       6: invokestatic  #6                  // Method com/google/common/base/Preconditions.checkNotNull:(Ljava/lang/Object;)Ljava/lang/Object;
       9: pop
      10: aload_2
      11: invokestatic  #6                  // Method com/google/common/base/Preconditions.checkNotNull:(Ljava/lang/Object;)Ljava/lang/Object;
      14: pop
      15: aload_3
      16: invokestatic  #6                  // Method com/google/common/base/Preconditions.checkNotNull:(Ljava/lang/Object;)Ljava/lang/Object;
      19: pop
      20: aload_1
      21: aload_2
      22: aload_3
      23: aload_0
      24: invokedynamic #7,  0              // InvokeDynamic #0:get:(Ljava/util/Comparator;)Ljava/util/function/Supplier;
      29: invokestatic  #8                  // Method java/util/stream/Collectors.toMap:(Ljava/util/function/Function;Ljava/util/function/Function;Ljava/util/function/BinaryOperator;Ljava/util/function/Supplier;)Ljava/util/stream/Collector;
      32: invokedynamic #9,  0              // InvokeDynamic #1:apply:()Ljava/util/function/Function;
      37: invokestatic  #10                 // Method java/util/stream/Collectors.collectingAndThen:(Ljava/util/stream/Collector;Ljava/util/function/Function;)Ljava/util/stream/Collector;
      40: areturn

  static <K, V> com.google.common.collect.ImmutableSortedMap<K, V> emptyMap(java.util.Comparator<? super K>);
    Code:
       0: invokestatic  #11                 // Method com/google/common/collect/Ordering.natural:()Lcom/google/common/collect/Ordering;
       3: aload_0
       4: invokevirtual #12                 // Method java/lang/Object.equals:(Ljava/lang/Object;)Z
       7: ifeq          14
      10: invokestatic  #13                 // Method of:()Lcom/google/common/collect/ImmutableSortedMap;
      13: areturn
      14: new           #14                 // class com/google/common/collect/ImmutableSortedMap
      17: dup
      18: aload_0
      19: invokestatic  #15                 // Method com/google/common/collect/ImmutableSortedSet.emptySet:(Ljava/util/Comparator;)Lcom/google/common/collect/RegularImmutableSortedSet;
      22: invokestatic  #16                 // Method com/google/common/collect/ImmutableList.of:()Lcom/google/common/collect/ImmutableList;
      25: invokespecial #17                 // Method "<init>":(Lcom/google/common/collect/RegularImmutableSortedSet;Lcom/google/common/collect/ImmutableList;)V
      28: areturn

  public static <K, V> com.google.common.collect.ImmutableSortedMap<K, V> of();
    Code:
       0: getstatic     #18                 // Field NATURAL_EMPTY_MAP:Lcom/google/common/collect/ImmutableSortedMap;
       3: areturn

  public static <K extends java.lang.Comparable<? super K>, V> com.google.common.collect.ImmutableSortedMap<K, V> of(K, V);
    Code:
       0: invokestatic  #11                 // Method com/google/common/collect/Ordering.natural:()Lcom/google/common/collect/Ordering;
       3: aload_0
       4: aload_1
       5: invokestatic  #4                  // Method of:(Ljava/util/Comparator;Ljava/lang/Object;Ljava/lang/Object;)Lcom/google/common/collect/ImmutableSortedMap;
       8: areturn

  public static <K extends java.lang.Comparable<? super K>, V> com.google.common.collect.ImmutableSortedMap<K, V> of(K, V, K, V);
    Code:
       0: iconst_2
       1: anewarray     #23                 // class java/util/Map$Entry
       4: dup
       5: iconst_0
       6: aload_0
       7: aload_1
       8: invokestatic  #24                 // Method entryOf:(Ljava/lang/Object;Ljava/lang/Object;)Ljava/util/Map$Entry;
      11: aastore
      12: dup
      13: iconst_1
      14: aload_2
      15: aload_3
      16: invokestatic  #24                 // Method entryOf:(Ljava/lang/Object;Ljava/lang/Object;)Ljava/util/Map$Entry;
      19: aastore
      20: invokestatic  #25                 // Method ofEntries:([Ljava/util/Map$Entry;)Lcom/google/common/collect/ImmutableSortedMap;
      23: areturn

  public static <K extends java.lang.Comparable<? super K>, V> com.google.common.collect.ImmutableSortedMap<K, V> of(K, V, K, V, K, V);
    Code:
       0: iconst_3
       1: anewarray     #23                 // class java/util/Map$Entry
       4: dup
       5: iconst_0
       6: aload_0
       7: aload_1
       8: invokestatic  #24                 // Method entryOf:(Ljava/lang/Object;Ljava/lang/Object;)Ljava/util/Map$Entry;
      11: aastore
      12: dup
      13: iconst_1
      14: aload_2
      15: aload_3
      16: invokestatic  #24                 // Method entryOf:(Ljava/lang/Object;Ljava/lang/Object;)Ljava/util/Map$Entry;
      19: aastore
      20: dup
      21: iconst_2
      22: aload         4
      24: aload         5
      26: invokestatic  #24                 // Method entryOf:(Ljava/lang/Object;Ljava/lang/Object;)Ljava/util/Map$Entry;
      29: aastore
      30: invokestatic  #25                 // Method ofEntries:([Ljava/util/Map$Entry;)Lcom/google/common/collect/ImmutableSortedMap;
      33: areturn

  public static <K extends java.lang.Comparable<? super K>, V> com.google.common.collect.ImmutableSortedMap<K, V> of(K, V, K, V, K, V, K, V);
    Code:
       0: iconst_4
       1: anewarray     #23                 // class java/util/Map$Entry
       4: dup
       5: iconst_0
       6: aload_0
       7: aload_1
       8: invokestatic  #24                 // Method entryOf:(Ljava/lang/Object;Ljava/lang/Object;)Ljava/util/Map$Entry;
      11: aastore
      12: dup
      13: iconst_1
      14: aload_2
      15: aload_3
      16: invokestatic  #24                 // Method entryOf:(Ljava/lang/Object;Ljava/lang/Object;)Ljava/util/Map$Entry;
      19: aastore
      20: dup
      21: iconst_2
      22: aload         4
      24: aload         5
      26: invokestatic  #24                 // Method entryOf:(Ljava/lang/Object;Ljava/lang/Object;)Ljava/util/Map$Entry;
      29: aastore
      30: dup
      31: iconst_3
      32: aload         6
      34: aload         7
      36: invokestatic  #24                 // Method entryOf:(Ljava/lang/Object;Ljava/lang/Object;)Ljava/util/Map$Entry;
      39: aastore
      40: invokestatic  #25                 // Method ofEntries:([Ljava/util/Map$Entry;)Lcom/google/common/collect/ImmutableSortedMap;
      43: areturn

  public static <K extends java.lang.Comparable<? super K>, V> com.google.common.collect.ImmutableSortedMap<K, V> of(K, V, K, V, K, V, K, V, K, V);
    Code:
       0: iconst_5
       1: anewarray     #23                 // class java/util/Map$Entry
       4: dup
       5: iconst_0
       6: aload_0
       7: aload_1
       8: invokestatic  #24                 // Method entryOf:(Ljava/lang/Object;Ljava/lang/Object;)Ljava/util/Map$Entry;
      11: aastore
      12: dup
      13: iconst_1
      14: aload_2
      15: aload_3
      16: invokestatic  #24                 // Method entryOf:(Ljava/lang/Object;Ljava/lang/Object;)Ljava/util/Map$Entry;
      19: aastore
      20: dup
      21: iconst_2
      22: aload         4
      24: aload         5
      26: invokestatic  #24                 // Method entryOf:(Ljava/lang/Object;Ljava/lang/Object;)Ljava/util/Map$Entry;
      29: aastore
      30: dup
      31: iconst_3
      32: aload         6
      34: aload         7
      36: invokestatic  #24                 // Method entryOf:(Ljava/lang/Object;Ljava/lang/Object;)Ljava/util/Map$Entry;
      39: aastore
      40: dup
      41: iconst_4
      42: aload         8
      44: aload         9
      46: invokestatic  #24                 // Method entryOf:(Ljava/lang/Object;Ljava/lang/Object;)Ljava/util/Map$Entry;
      49: aastore
      50: invokestatic  #25                 // Method ofEntries:([Ljava/util/Map$Entry;)Lcom/google/common/collect/ImmutableSortedMap;
      53: areturn

  public static <K, V> com.google.common.collect.ImmutableSortedMap<K, V> copyOf(java.util.Map<? extends K, ? extends V>);
    Code:
       0: getstatic     #26                 // Field NATURAL_ORDER:Ljava/util/Comparator;
       3: checkcast     #27                 // class com/google/common/collect/Ordering
       6: astore_1
       7: aload_0
       8: aload_1
       9: invokestatic  #28                 // Method copyOfInternal:(Ljava/util/Map;Ljava/util/Comparator;)Lcom/google/common/collect/ImmutableSortedMap;
      12: areturn

  public static <K, V> com.google.common.collect.ImmutableSortedMap<K, V> copyOf(java.util.Map<? extends K, ? extends V>, java.util.Comparator<? super K>);
    Code:
       0: aload_0
       1: aload_1
       2: invokestatic  #6                  // Method com/google/common/base/Preconditions.checkNotNull:(Ljava/lang/Object;)Ljava/lang/Object;
       5: checkcast     #21                 // class java/util/Comparator
       8: invokestatic  #28                 // Method copyOfInternal:(Ljava/util/Map;Ljava/util/Comparator;)Lcom/google/common/collect/ImmutableSortedMap;
      11: areturn

  public static <K, V> com.google.common.collect.ImmutableSortedMap<K, V> copyOf(java.lang.Iterable<? extends java.util.Map$Entry<? extends K, ? extends V>>);
    Code:
       0: getstatic     #26                 // Field NATURAL_ORDER:Ljava/util/Comparator;
       3: checkcast     #27                 // class com/google/common/collect/Ordering
       6: astore_1
       7: aload_0
       8: aload_1
       9: invokestatic  #29                 // Method copyOf:(Ljava/lang/Iterable;Ljava/util/Comparator;)Lcom/google/common/collect/ImmutableSortedMap;
      12: areturn

  public static <K, V> com.google.common.collect.ImmutableSortedMap<K, V> copyOf(java.lang.Iterable<? extends java.util.Map$Entry<? extends K, ? extends V>>, java.util.Comparator<? super K>);
    Code:
       0: aload_1
       1: invokestatic  #6                  // Method com/google/common/base/Preconditions.checkNotNull:(Ljava/lang/Object;)Ljava/lang/Object;
       4: checkcast     #21                 // class java/util/Comparator
       7: iconst_0
       8: aload_0
       9: invokestatic  #30                 // Method fromEntries:(Ljava/util/Comparator;ZLjava/lang/Iterable;)Lcom/google/common/collect/ImmutableSortedMap;
      12: areturn

  public static <K, V> com.google.common.collect.ImmutableSortedMap<K, V> copyOfSorted(java.util.SortedMap<K, ? extends V>);
    Code:
       0: aload_0
       1: invokeinterface #31,  1           // InterfaceMethod java/util/SortedMap.comparator:()Ljava/util/Comparator;
       6: astore_1
       7: aload_1
       8: ifnonnull     15
      11: getstatic     #26                 // Field NATURAL_ORDER:Ljava/util/Comparator;
      14: astore_1
      15: aload_0
      16: instanceof    #14                 // class com/google/common/collect/ImmutableSortedMap
      19: ifeq          36
      22: aload_0
      23: checkcast     #14                 // class com/google/common/collect/ImmutableSortedMap
      26: astore_2
      27: aload_2
      28: invokevirtual #32                 // Method isPartialView:()Z
      31: ifne          36
      34: aload_2
      35: areturn
      36: aload_1
      37: iconst_1
      38: aload_0
      39: invokeinterface #33,  1           // InterfaceMethod java/util/SortedMap.entrySet:()Ljava/util/Set;
      44: invokestatic  #30                 // Method fromEntries:(Ljava/util/Comparator;ZLjava/lang/Iterable;)Lcom/google/common/collect/ImmutableSortedMap;
      47: areturn

  public static <K extends java.lang.Comparable<?>, V> com.google.common.collect.ImmutableSortedMap$Builder<K, V> naturalOrder();
    Code:
       0: new           #53                 // class com/google/common/collect/ImmutableSortedMap$Builder
       3: dup
       4: invokestatic  #11                 // Method com/google/common/collect/Ordering.natural:()Lcom/google/common/collect/Ordering;
       7: invokespecial #54                 // Method com/google/common/collect/ImmutableSortedMap$Builder."<init>":(Ljava/util/Comparator;)V
      10: areturn

  public static <K, V> com.google.common.collect.ImmutableSortedMap$Builder<K, V> orderedBy(java.util.Comparator<K>);
    Code:
       0: new           #53                 // class com/google/common/collect/ImmutableSortedMap$Builder
       3: dup
       4: aload_0
       5: invokespecial #54                 // Method com/google/common/collect/ImmutableSortedMap$Builder."<init>":(Ljava/util/Comparator;)V
       8: areturn

  public static <K extends java.lang.Comparable<?>, V> com.google.common.collect.ImmutableSortedMap$Builder<K, V> reverseOrder();
    Code:
       0: new           #53                 // class com/google/common/collect/ImmutableSortedMap$Builder
       3: dup
       4: invokestatic  #11                 // Method com/google/common/collect/Ordering.natural:()Lcom/google/common/collect/Ordering;
       7: invokevirtual #55                 // Method com/google/common/collect/Ordering.reverse:()Lcom/google/common/collect/Ordering;
      10: invokespecial #54                 // Method com/google/common/collect/ImmutableSortedMap$Builder."<init>":(Ljava/util/Comparator;)V
      13: areturn

  com.google.common.collect.ImmutableSortedMap(com.google.common.collect.RegularImmutableSortedSet<K>, com.google.common.collect.ImmutableList<V>);
    Code:
       0: aload_0
       1: aload_1
       2: aload_2
       3: aconst_null
       4: invokespecial #56                 // Method "<init>":(Lcom/google/common/collect/RegularImmutableSortedSet;Lcom/google/common/collect/ImmutableList;Lcom/google/common/collect/ImmutableSortedMap;)V
       7: return

  com.google.common.collect.ImmutableSortedMap(com.google.common.collect.RegularImmutableSortedSet<K>, com.google.common.collect.ImmutableList<V>, com.google.common.collect.ImmutableSortedMap<K, V>);
    Code:
       0: aload_0
       1: invokespecial #57                 // Method com/google/common/collect/ImmutableSortedMapFauxverideShim."<init>":()V
       4: aload_0
       5: aload_1
       6: putfield      #2                  // Field keySet:Lcom/google/common/collect/RegularImmutableSortedSet;
       9: aload_0
      10: aload_2
      11: putfield      #1                  // Field valueList:Lcom/google/common/collect/ImmutableList;
      14: aload_0
      15: aload_3
      16: putfield      #58                 // Field descendingMap:Lcom/google/common/collect/ImmutableSortedMap;
      19: return

  public int size();
    Code:
       0: aload_0
       1: getfield      #1                  // Field valueList:Lcom/google/common/collect/ImmutableList;
       4: invokevirtual #59                 // Method com/google/common/collect/ImmutableList.size:()I
       7: ireturn

  public void forEach(java.util.function.BiConsumer<? super K, ? super V>);
    Code:
       0: aload_1
       1: invokestatic  #6                  // Method com/google/common/base/Preconditions.checkNotNull:(Ljava/lang/Object;)Ljava/lang/Object;
       4: pop
       5: aload_0
       6: getfield      #2                  // Field keySet:Lcom/google/common/collect/RegularImmutableSortedSet;
       9: invokevirtual #60                 // Method com/google/common/collect/RegularImmutableSortedSet.asList:()Lcom/google/common/collect/ImmutableList;
      12: astore_2
      13: iconst_0
      14: istore_3
      15: iload_3
      16: aload_0
      17: invokevirtual #61                 // Method size:()I
      20: if_icmpge     48
      23: aload_1
      24: aload_2
      25: iload_3
      26: invokevirtual #62                 // Method com/google/common/collect/ImmutableList.get:(I)Ljava/lang/Object;
      29: aload_0
      30: getfield      #1                  // Field valueList:Lcom/google/common/collect/ImmutableList;
      33: iload_3
      34: invokevirtual #62                 // Method com/google/common/collect/ImmutableList.get:(I)Ljava/lang/Object;
      37: invokeinterface #63,  3           // InterfaceMethod java/util/function/BiConsumer.accept:(Ljava/lang/Object;Ljava/lang/Object;)V
      42: iinc          3, 1
      45: goto          15
      48: return

  public V get(java.lang.Object);
    Code:
       0: aload_0
       1: getfield      #2                  // Field keySet:Lcom/google/common/collect/RegularImmutableSortedSet;
       4: aload_1
       5: invokevirtual #64                 // Method com/google/common/collect/RegularImmutableSortedSet.indexOf:(Ljava/lang/Object;)I
       8: istore_2
       9: iload_2
      10: iconst_m1
      11: if_icmpne     18
      14: aconst_null
      15: goto          26
      18: aload_0
      19: getfield      #1                  // Field valueList:Lcom/google/common/collect/ImmutableList;
      22: iload_2
      23: invokevirtual #62                 // Method com/google/common/collect/ImmutableList.get:(I)Ljava/lang/Object;
      26: areturn

  boolean isPartialView();
    Code:
       0: aload_0
       1: getfield      #2                  // Field keySet:Lcom/google/common/collect/RegularImmutableSortedSet;
       4: invokevirtual #65                 // Method com/google/common/collect/RegularImmutableSortedSet.isPartialView:()Z
       7: ifne          20
      10: aload_0
      11: getfield      #1                  // Field valueList:Lcom/google/common/collect/ImmutableList;
      14: invokevirtual #66                 // Method com/google/common/collect/ImmutableList.isPartialView:()Z
      17: ifeq          24
      20: iconst_1
      21: goto          25
      24: iconst_0
      25: ireturn

  public com.google.common.collect.ImmutableSet<java.util.Map$Entry<K, V>> entrySet();
    Code:
       0: aload_0
       1: invokespecial #67                 // Method com/google/common/collect/ImmutableSortedMapFauxverideShim.entrySet:()Lcom/google/common/collect/ImmutableSet;
       4: areturn

  com.google.common.collect.ImmutableSet<java.util.Map$Entry<K, V>> createEntrySet();
    Code:
       0: aload_0
       1: invokevirtual #68                 // Method isEmpty:()Z
       4: ifeq          13
       7: invokestatic  #69                 // Method com/google/common/collect/ImmutableSet.of:()Lcom/google/common/collect/ImmutableSet;
      10: goto          21
      13: new           #70                 // class com/google/common/collect/ImmutableSortedMap$1EntrySet
      16: dup
      17: aload_0
      18: invokespecial #71                 // Method com/google/common/collect/ImmutableSortedMap$1EntrySet."<init>":(Lcom/google/common/collect/ImmutableSortedMap;)V
      21: areturn

  public com.google.common.collect.ImmutableSortedSet<K> keySet();
    Code:
       0: aload_0
       1: getfield      #2                  // Field keySet:Lcom/google/common/collect/RegularImmutableSortedSet;
       4: areturn

  com.google.common.collect.ImmutableSet<K> createKeySet();
    Code:
       0: new           #72                 // class java/lang/AssertionError
       3: dup
       4: ldc           #73                 // String should never be called
       6: invokespecial #74                 // Method java/lang/AssertionError."<init>":(Ljava/lang/Object;)V
       9: athrow

  public com.google.common.collect.ImmutableCollection<V> values();
    Code:
       0: aload_0
       1: getfield      #1                  // Field valueList:Lcom/google/common/collect/ImmutableList;
       4: areturn

  com.google.common.collect.ImmutableCollection<V> createValues();
    Code:
       0: new           #72                 // class java/lang/AssertionError
       3: dup
       4: ldc           #73                 // String should never be called
       6: invokespecial #74                 // Method java/lang/AssertionError."<init>":(Ljava/lang/Object;)V
       9: athrow

  public java.util.Comparator<? super K> comparator();
    Code:
       0: aload_0
       1: invokevirtual #75                 // Method keySet:()Lcom/google/common/collect/ImmutableSortedSet;
       4: invokevirtual #76                 // Method com/google/common/collect/ImmutableSortedSet.comparator:()Ljava/util/Comparator;
       7: areturn

  public K firstKey();
    Code:
       0: aload_0
       1: invokevirtual #75                 // Method keySet:()Lcom/google/common/collect/ImmutableSortedSet;
       4: invokevirtual #77                 // Method com/google/common/collect/ImmutableSortedSet.first:()Ljava/lang/Object;
       7: areturn

  public K lastKey();
    Code:
       0: aload_0
       1: invokevirtual #75                 // Method keySet:()Lcom/google/common/collect/ImmutableSortedSet;
       4: invokevirtual #78                 // Method com/google/common/collect/ImmutableSortedSet.last:()Ljava/lang/Object;
       7: areturn

  public com.google.common.collect.ImmutableSortedMap<K, V> headMap(K);
    Code:
       0: aload_0
       1: aload_1
       2: iconst_0
       3: invokevirtual #82                 // Method headMap:(Ljava/lang/Object;Z)Lcom/google/common/collect/ImmutableSortedMap;
       6: areturn

  public com.google.common.collect.ImmutableSortedMap<K, V> headMap(K, boolean);
    Code:
       0: aload_0
       1: iconst_0
       2: aload_0
       3: getfield      #2                  // Field keySet:Lcom/google/common/collect/RegularImmutableSortedSet;
       6: aload_1
       7: invokestatic  #6                  // Method com/google/common/base/Preconditions.checkNotNull:(Ljava/lang/Object;)Ljava/lang/Object;
      10: iload_2
      11: invokevirtual #83                 // Method com/google/common/collect/RegularImmutableSortedSet.headIndex:(Ljava/lang/Object;Z)I
      14: invokespecial #84                 // Method getSubMap:(II)Lcom/google/common/collect/ImmutableSortedMap;
      17: areturn

  public com.google.common.collect.ImmutableSortedMap<K, V> subMap(K, K);
    Code:
       0: aload_0
       1: aload_1
       2: iconst_1
       3: aload_2
       4: iconst_0
       5: invokevirtual #85                 // Method subMap:(Ljava/lang/Object;ZLjava/lang/Object;Z)Lcom/google/common/collect/ImmutableSortedMap;
       8: areturn

  public com.google.common.collect.ImmutableSortedMap<K, V> subMap(K, boolean, K, boolean);
    Code:
       0: aload_1
       1: invokestatic  #6                  // Method com/google/common/base/Preconditions.checkNotNull:(Ljava/lang/Object;)Ljava/lang/Object;
       4: pop
       5: aload_3
       6: invokestatic  #6                  // Method com/google/common/base/Preconditions.checkNotNull:(Ljava/lang/Object;)Ljava/lang/Object;
       9: pop
      10: aload_0
      11: invokevirtual #79                 // Method comparator:()Ljava/util/Comparator;
      14: aload_1
      15: aload_3
      16: invokeinterface #48,  3           // InterfaceMethod java/util/Comparator.compare:(Ljava/lang/Object;Ljava/lang/Object;)I
      21: ifgt          28
      24: iconst_1
      25: goto          29
      28: iconst_0
      29: ldc           #86                 // String expected fromKey <= toKey but %s > %s
      31: aload_1
      32: aload_3
      33: invokestatic  #87                 // Method com/google/common/base/Preconditions.checkArgument:(ZLjava/lang/String;Ljava/lang/Object;Ljava/lang/Object;)V
      36: aload_0
      37: aload_3
      38: iload         4
      40: invokevirtual #82                 // Method headMap:(Ljava/lang/Object;Z)Lcom/google/common/collect/ImmutableSortedMap;
      43: aload_1
      44: iload_2
      45: invokevirtual #88                 // Method tailMap:(Ljava/lang/Object;Z)Lcom/google/common/collect/ImmutableSortedMap;
      48: areturn

  public com.google.common.collect.ImmutableSortedMap<K, V> tailMap(K);
    Code:
       0: aload_0
       1: aload_1
       2: iconst_1
       3: invokevirtual #88                 // Method tailMap:(Ljava/lang/Object;Z)Lcom/google/common/collect/ImmutableSortedMap;
       6: areturn

  public com.google.common.collect.ImmutableSortedMap<K, V> tailMap(K, boolean);
    Code:
       0: aload_0
       1: aload_0
       2: getfield      #2                  // Field keySet:Lcom/google/common/collect/RegularImmutableSortedSet;
       5: aload_1
       6: invokestatic  #6                  // Method com/google/common/base/Preconditions.checkNotNull:(Ljava/lang/Object;)Ljava/lang/Object;
       9: iload_2
      10: invokevirtual #89                 // Method com/google/common/collect/RegularImmutableSortedSet.tailIndex:(Ljava/lang/Object;Z)I
      13: aload_0
      14: invokevirtual #61                 // Method size:()I
      17: invokespecial #84                 // Method getSubMap:(II)Lcom/google/common/collect/ImmutableSortedMap;
      20: areturn

  public java.util.Map$Entry<K, V> lowerEntry(K);
    Code:
       0: aload_0
       1: aload_1
       2: iconst_0
       3: invokevirtual #82                 // Method headMap:(Ljava/lang/Object;Z)Lcom/google/common/collect/ImmutableSortedMap;
       6: invokevirtual #90                 // Method lastEntry:()Ljava/util/Map$Entry;
       9: areturn

  public K lowerKey(K);
    Code:
       0: aload_0
       1: aload_1
       2: invokevirtual #91                 // Method lowerEntry:(Ljava/lang/Object;)Ljava/util/Map$Entry;
       5: invokestatic  #92                 // Method com/google/common/collect/Maps.keyOrNull:(Ljava/util/Map$Entry;)Ljava/lang/Object;
       8: areturn

  public java.util.Map$Entry<K, V> floorEntry(K);
    Code:
       0: aload_0
       1: aload_1
       2: iconst_1
       3: invokevirtual #82                 // Method headMap:(Ljava/lang/Object;Z)Lcom/google/common/collect/ImmutableSortedMap;
       6: invokevirtual #90                 // Method lastEntry:()Ljava/util/Map$Entry;
       9: areturn

  public K floorKey(K);
    Code:
       0: aload_0
       1: aload_1
       2: invokevirtual #93                 // Method floorEntry:(Ljava/lang/Object;)Ljava/util/Map$Entry;
       5: invokestatic  #92                 // Method com/google/common/collect/Maps.keyOrNull:(Ljava/util/Map$Entry;)Ljava/lang/Object;
       8: areturn

  public java.util.Map$Entry<K, V> ceilingEntry(K);
    Code:
       0: aload_0
       1: aload_1
       2: iconst_1
       3: invokevirtual #88                 // Method tailMap:(Ljava/lang/Object;Z)Lcom/google/common/collect/ImmutableSortedMap;
       6: invokevirtual #94                 // Method firstEntry:()Ljava/util/Map$Entry;
       9: areturn

  public K ceilingKey(K);
    Code:
       0: aload_0
       1: aload_1
       2: invokevirtual #95                 // Method ceilingEntry:(Ljava/lang/Object;)Ljava/util/Map$Entry;
       5: invokestatic  #92                 // Method com/google/common/collect/Maps.keyOrNull:(Ljava/util/Map$Entry;)Ljava/lang/Object;
       8: areturn

  public java.util.Map$Entry<K, V> higherEntry(K);
    Code:
       0: aload_0
       1: aload_1
       2: iconst_0
       3: invokevirtual #88                 // Method tailMap:(Ljava/lang/Object;Z)Lcom/google/common/collect/ImmutableSortedMap;
       6: invokevirtual #94                 // Method firstEntry:()Ljava/util/Map$Entry;
       9: areturn

  public K higherKey(K);
    Code:
       0: aload_0
       1: aload_1
       2: invokevirtual #96                 // Method higherEntry:(Ljava/lang/Object;)Ljava/util/Map$Entry;
       5: invokestatic  #92                 // Method com/google/common/collect/Maps.keyOrNull:(Ljava/util/Map$Entry;)Ljava/lang/Object;
       8: areturn

  public java.util.Map$Entry<K, V> firstEntry();
    Code:
       0: aload_0
       1: invokevirtual #68                 // Method isEmpty:()Z
       4: ifeq          11
       7: aconst_null
       8: goto          25
      11: aload_0
      12: invokevirtual #97                 // Method entrySet:()Lcom/google/common/collect/ImmutableSet;
      15: invokevirtual #98                 // Method com/google/common/collect/ImmutableSet.asList:()Lcom/google/common/collect/ImmutableList;
      18: iconst_0
      19: invokevirtual #62                 // Method com/google/common/collect/ImmutableList.get:(I)Ljava/lang/Object;
      22: checkcast     #23                 // class java/util/Map$Entry
      25: areturn

  public java.util.Map$Entry<K, V> lastEntry();
    Code:
       0: aload_0
       1: invokevirtual #68                 // Method isEmpty:()Z
       4: ifeq          11
       7: aconst_null
       8: goto          30
      11: aload_0
      12: invokevirtual #97                 // Method entrySet:()Lcom/google/common/collect/ImmutableSet;
      15: invokevirtual #98                 // Method com/google/common/collect/ImmutableSet.asList:()Lcom/google/common/collect/ImmutableList;
      18: aload_0
      19: invokevirtual #61                 // Method size:()I
      22: iconst_1
      23: isub
      24: invokevirtual #62                 // Method com/google/common/collect/ImmutableList.get:(I)Ljava/lang/Object;
      27: checkcast     #23                 // class java/util/Map$Entry
      30: areturn

  public final java.util.Map$Entry<K, V> pollFirstEntry();
    Code:
       0: new           #99                 // class java/lang/UnsupportedOperationException
       3: dup
       4: invokespecial #100                // Method java/lang/UnsupportedOperationException."<init>":()V
       7: athrow

  public final java.util.Map$Entry<K, V> pollLastEntry();
    Code:
       0: new           #99                 // class java/lang/UnsupportedOperationException
       3: dup
       4: invokespecial #100                // Method java/lang/UnsupportedOperationException."<init>":()V
       7: athrow

  public com.google.common.collect.ImmutableSortedMap<K, V> descendingMap();
    Code:
       0: aload_0
       1: getfield      #58                 // Field descendingMap:Lcom/google/common/collect/ImmutableSortedMap;
       4: astore_1
       5: aload_1
       6: ifnonnull     60
       9: aload_0
      10: invokevirtual #68                 // Method isEmpty:()Z
      13: ifeq          32
      16: aload_0
      17: invokevirtual #79                 // Method comparator:()Ljava/util/Comparator;
      20: invokestatic  #101                // Method com/google/common/collect/Ordering.from:(Ljava/util/Comparator;)Lcom/google/common/collect/Ordering;
      23: invokevirtual #55                 // Method com/google/common/collect/Ordering.reverse:()Lcom/google/common/collect/Ordering;
      26: invokestatic  #40                 // Method emptyMap:(Ljava/util/Comparator;)Lcom/google/common/collect/ImmutableSortedMap;
      29: dup
      30: astore_1
      31: areturn
      32: new           #14                 // class com/google/common/collect/ImmutableSortedMap
      35: dup
      36: aload_0
      37: getfield      #2                  // Field keySet:Lcom/google/common/collect/RegularImmutableSortedSet;
      40: invokevirtual #102                // Method com/google/common/collect/RegularImmutableSortedSet.descendingSet:()Lcom/google/common/collect/ImmutableSortedSet;
      43: checkcast     #19                 // class com/google/common/collect/RegularImmutableSortedSet
      46: aload_0
      47: getfield      #1                  // Field valueList:Lcom/google/common/collect/ImmutableList;
      50: invokevirtual #103                // Method com/google/common/collect/ImmutableList.reverse:()Lcom/google/common/collect/ImmutableList;
      53: aload_0
      54: invokespecial #56                 // Method "<init>":(Lcom/google/common/collect/RegularImmutableSortedSet;Lcom/google/common/collect/ImmutableList;Lcom/google/common/collect/ImmutableSortedMap;)V
      57: dup
      58: astore_1
      59: areturn
      60: aload_1
      61: areturn

  public com.google.common.collect.ImmutableSortedSet<K> navigableKeySet();
    Code:
       0: aload_0
       1: getfield      #2                  // Field keySet:Lcom/google/common/collect/RegularImmutableSortedSet;
       4: areturn

  public com.google.common.collect.ImmutableSortedSet<K> descendingKeySet();
    Code:
       0: aload_0
       1: getfield      #2                  // Field keySet:Lcom/google/common/collect/RegularImmutableSortedSet;
       4: invokevirtual #102                // Method com/google/common/collect/RegularImmutableSortedSet.descendingSet:()Lcom/google/common/collect/ImmutableSortedSet;
       7: areturn

  java.lang.Object writeReplace();
    Code:
       0: new           #104                // class com/google/common/collect/ImmutableSortedMap$SerializedForm
       3: dup
       4: aload_0
       5: invokespecial #105                // Method com/google/common/collect/ImmutableSortedMap$SerializedForm."<init>":(Lcom/google/common/collect/ImmutableSortedMap;)V
       8: areturn

  public com.google.common.collect.ImmutableSet keySet();
    Code:
       0: aload_0
       1: invokevirtual #75                 // Method keySet:()Lcom/google/common/collect/ImmutableSortedSet;
       4: areturn

  public java.util.Set entrySet();
    Code:
       0: aload_0
       1: invokevirtual #97                 // Method entrySet:()Lcom/google/common/collect/ImmutableSet;
       4: areturn

  public java.util.Collection values();
    Code:
       0: aload_0
       1: invokevirtual #106                // Method values:()Lcom/google/common/collect/ImmutableCollection;
       4: areturn

  public java.util.Set keySet();
    Code:
       0: aload_0
       1: invokevirtual #75                 // Method keySet:()Lcom/google/common/collect/ImmutableSortedSet;
       4: areturn

  public java.util.SortedMap tailMap(java.lang.Object);
    Code:
       0: aload_0
       1: aload_1
       2: invokevirtual #107                // Method tailMap:(Ljava/lang/Object;)Lcom/google/common/collect/ImmutableSortedMap;
       5: areturn

  public java.util.SortedMap headMap(java.lang.Object);
    Code:
       0: aload_0
       1: aload_1
       2: invokevirtual #108                // Method headMap:(Ljava/lang/Object;)Lcom/google/common/collect/ImmutableSortedMap;
       5: areturn

  public java.util.SortedMap subMap(java.lang.Object, java.lang.Object);
    Code:
       0: aload_0
       1: aload_1
       2: aload_2
       3: invokevirtual #109                // Method subMap:(Ljava/lang/Object;Ljava/lang/Object;)Lcom/google/common/collect/ImmutableSortedMap;
       6: areturn

  public java.util.NavigableMap tailMap(java.lang.Object, boolean);
    Code:
       0: aload_0
       1: aload_1
       2: iload_2
       3: invokevirtual #88                 // Method tailMap:(Ljava/lang/Object;Z)Lcom/google/common/collect/ImmutableSortedMap;
       6: areturn

  public java.util.NavigableMap headMap(java.lang.Object, boolean);
    Code:
       0: aload_0
       1: aload_1
       2: iload_2
       3: invokevirtual #82                 // Method headMap:(Ljava/lang/Object;Z)Lcom/google/common/collect/ImmutableSortedMap;
       6: areturn

  public java.util.NavigableMap subMap(java.lang.Object, boolean, java.lang.Object, boolean);
    Code:
       0: aload_0
       1: aload_1
       2: iload_2
       3: aload_3
       4: iload         4
       6: invokevirtual #85                 // Method subMap:(Ljava/lang/Object;ZLjava/lang/Object;Z)Lcom/google/common/collect/ImmutableSortedMap;
       9: areturn

  public java.util.NavigableSet descendingKeySet();
    Code:
       0: aload_0
       1: invokevirtual #110                // Method descendingKeySet:()Lcom/google/common/collect/ImmutableSortedSet;
       4: areturn

  public java.util.NavigableSet navigableKeySet();
    Code:
       0: aload_0
       1: invokevirtual #111                // Method navigableKeySet:()Lcom/google/common/collect/ImmutableSortedSet;
       4: areturn

  public java.util.NavigableMap descendingMap();
    Code:
       0: aload_0
       1: invokevirtual #112                // Method descendingMap:()Lcom/google/common/collect/ImmutableSortedMap;
       4: areturn

  static com.google.common.collect.ImmutableSortedMap access$000(java.util.Comparator, java.lang.Object, java.lang.Object);
    Code:
       0: aload_0
       1: aload_1
       2: aload_2
       3: invokestatic  #4                  // Method of:(Ljava/util/Comparator;Ljava/lang/Object;Ljava/lang/Object;)Lcom/google/common/collect/ImmutableSortedMap;
       6: areturn

  static com.google.common.collect.ImmutableSortedMap access$100(java.util.Comparator, boolean, java.util.Map$Entry[], int);
    Code:
       0: aload_0
       1: iload_1
       2: aload_2
       3: iload_3
       4: invokestatic  #3                  // Method fromEntries:(Ljava/util/Comparator;Z[Ljava/util/Map$Entry;I)Lcom/google/common/collect/ImmutableSortedMap;
       7: areturn

  static com.google.common.collect.RegularImmutableSortedSet access$200(com.google.common.collect.ImmutableSortedMap);
    Code:
       0: aload_0
       1: getfield      #2                  // Field keySet:Lcom/google/common/collect/RegularImmutableSortedSet;
       4: areturn

  static com.google.common.collect.ImmutableList access$300(com.google.common.collect.ImmutableSortedMap);
    Code:
       0: aload_0
       1: getfield      #1                  // Field valueList:Lcom/google/common/collect/ImmutableList;
       4: areturn

  static {};
    Code:
       0: invokestatic  #11                 // Method com/google/common/collect/Ordering.natural:()Lcom/google/common/collect/Ordering;
       3: putstatic     #26                 // Field NATURAL_ORDER:Ljava/util/Comparator;
       6: new           #14                 // class com/google/common/collect/ImmutableSortedMap
       9: dup
      10: invokestatic  #11                 // Method com/google/common/collect/Ordering.natural:()Lcom/google/common/collect/Ordering;
      13: invokestatic  #15                 // Method com/google/common/collect/ImmutableSortedSet.emptySet:(Ljava/util/Comparator;)Lcom/google/common/collect/RegularImmutableSortedSet;
      16: invokestatic  #16                 // Method com/google/common/collect/ImmutableList.of:()Lcom/google/common/collect/ImmutableList;
      19: invokespecial #17                 // Method "<init>":(Lcom/google/common/collect/RegularImmutableSortedSet;Lcom/google/common/collect/ImmutableList;)V
      22: putstatic     #18                 // Field NATURAL_EMPTY_MAP:Lcom/google/common/collect/ImmutableSortedMap;
      25: return
}
