Compiled from "SipHashFunction.java"
final class com.google.common.hash.SipHashFunction$SipHasher extends com.google.common.hash.AbstractStreamingHasher {
  com.google.common.hash.SipHashFunction$SipHasher(int, int, long, long);
    Code:
       0: aload_0
       1: bipush        8
       3: invokespecial #2                  // Method com/google/common/hash/AbstractStreamingHasher."<init>":(I)V
       6: aload_0
       7: ldc2_w        #3                  // long 8317987319222330741l
      10: putfield      #5                  // Field v0:J
      13: aload_0
      14: ldc2_w        #6                  // long 7237128888997146477l
      17: putfield      #8                  // Field v1:J
      20: aload_0
      21: ldc2_w        #9                  // long 7816392313619706465l
      24: putfield      #11                 // Field v2:J
      27: aload_0
      28: ldc2_w        #12                 // long 8387220255154660723l
      31: putfield      #14                 // Field v3:J
      34: aload_0
      35: lconst_0
      36: putfield      #15                 // Field b:J
      39: aload_0
      40: lconst_0
      41: putfield      #16                 // Field finalM:J
      44: aload_0
      45: iload_1
      46: putfield      #17                 // Field c:I
      49: aload_0
      50: iload_2
      51: putfield      #18                 // Field d:I
      54: aload_0
      55: dup
      56: getfield      #5                  // Field v0:J
      59: lload_3
      60: lxor
      61: putfield      #5                  // Field v0:J
      64: aload_0
      65: dup
      66: getfield      #8                  // Field v1:J
      69: lload         5
      71: lxor
      72: putfield      #8                  // Field v1:J
      75: aload_0
      76: dup
      77: getfield      #11                 // Field v2:J
      80: lload_3
      81: lxor
      82: putfield      #11                 // Field v2:J
      85: aload_0
      86: dup
      87: getfield      #14                 // Field v3:J
      90: lload         5
      92: lxor
      93: putfield      #14                 // Field v3:J
      96: return

  protected void process(java.nio.ByteBuffer);
    Code:
       0: aload_0
       1: dup
       2: getfield      #15                 // Field b:J
       5: ldc2_w        #19                 // long 8l
       8: ladd
       9: putfield      #15                 // Field b:J
      12: aload_0
      13: aload_1
      14: invokevirtual #21                 // Method java/nio/ByteBuffer.getLong:()J
      17: invokespecial #22                 // Method processM:(J)V
      20: return

  protected void processRemaining(java.nio.ByteBuffer);
    Code:
       0: aload_0
       1: dup
       2: getfield      #15                 // Field b:J
       5: aload_1
       6: invokevirtual #23                 // Method java/nio/ByteBuffer.remaining:()I
       9: i2l
      10: ladd
      11: putfield      #15                 // Field b:J
      14: iconst_0
      15: istore_2
      16: aload_1
      17: invokevirtual #24                 // Method java/nio/ByteBuffer.hasRemaining:()Z
      20: ifeq          49
      23: aload_0
      24: dup
      25: getfield      #16                 // Field finalM:J
      28: aload_1
      29: invokevirtual #25                 // Method java/nio/ByteBuffer.get:()B
      32: i2l
      33: ldc2_w        #26                 // long 255l
      36: land
      37: iload_2
      38: lshl
      39: lxor
      40: putfield      #16                 // Field finalM:J
      43: iinc          2, 8
      46: goto          16
      49: return

  public com.google.common.hash.HashCode makeHash();
    Code:
       0: aload_0
       1: dup
       2: getfield      #16                 // Field finalM:J
       5: aload_0
       6: getfield      #15                 // Field b:J
       9: bipush        56
      11: lshl
      12: lxor
      13: putfield      #16                 // Field finalM:J
      16: aload_0
      17: aload_0
      18: getfield      #16                 // Field finalM:J
      21: invokespecial #22                 // Method processM:(J)V
      24: aload_0
      25: dup
      26: getfield      #11                 // Field v2:J
      29: ldc2_w        #26                 // long 255l
      32: lxor
      33: putfield      #11                 // Field v2:J
      36: aload_0
      37: aload_0
      38: getfield      #18                 // Field d:I
      41: invokespecial #28                 // Method sipRound:(I)V
      44: aload_0
      45: getfield      #5                  // Field v0:J
      48: aload_0
      49: getfield      #8                  // Field v1:J
      52: lxor
      53: aload_0
      54: getfield      #11                 // Field v2:J
      57: lxor
      58: aload_0
      59: getfield      #14                 // Field v3:J
      62: lxor
      63: invokestatic  #29                 // Method com/google/common/hash/HashCode.fromLong:(J)Lcom/google/common/hash/HashCode;
      66: areturn
}
