Compiled from "Stopwatch.java"
public final class com.google.common.base.Stopwatch {
  public static com.google.common.base.Stopwatch createUnstarted();
    Code:
       0: new           #1                  // class com/google/common/base/Stopwatch
       3: dup
       4: invokespecial #2                  // Method "<init>":()V
       7: areturn

  public static com.google.common.base.Stopwatch createUnstarted(com.google.common.base.Ticker);
    Code:
       0: new           #1                  // class com/google/common/base/Stopwatch
       3: dup
       4: aload_0
       5: invokespecial #3                  // Method "<init>":(Lcom/google/common/base/Ticker;)V
       8: areturn

  public static com.google.common.base.Stopwatch createStarted();
    Code:
       0: new           #1                  // class com/google/common/base/Stopwatch
       3: dup
       4: invokespecial #2                  // Method "<init>":()V
       7: invokevirtual #4                  // Method start:()Lcom/google/common/base/Stopwatch;
      10: areturn

  public static com.google.common.base.Stopwatch createStarted(com.google.common.base.Ticker);
    Code:
       0: new           #1                  // class com/google/common/base/Stopwatch
       3: dup
       4: aload_0
       5: invokespecial #3                  // Method "<init>":(Lcom/google/common/base/Ticker;)V
       8: invokevirtual #4                  // Method start:()Lcom/google/common/base/Stopwatch;
      11: areturn

  com.google.common.base.Stopwatch();
    Code:
       0: aload_0
       1: invokespecial #5                  // Method java/lang/Object."<init>":()V
       4: aload_0
       5: invokestatic  #6                  // Method com/google/common/base/Ticker.systemTicker:()Lcom/google/common/base/Ticker;
       8: putfield      #7                  // Field ticker:Lcom/google/common/base/Ticker;
      11: return

  com.google.common.base.Stopwatch(com.google.common.base.Ticker);
    Code:
       0: aload_0
       1: invokespecial #5                  // Method java/lang/Object."<init>":()V
       4: aload_0
       5: aload_1
       6: ldc           #8                  // String ticker
       8: invokestatic  #9                  // Method com/google/common/base/Preconditions.checkNotNull:(Ljava/lang/Object;Ljava/lang/Object;)Ljava/lang/Object;
      11: checkcast     #10                 // class com/google/common/base/Ticker
      14: putfield      #7                  // Field ticker:Lcom/google/common/base/Ticker;
      17: return

  public boolean isRunning();
    Code:
       0: aload_0
       1: getfield      #11                 // Field isRunning:Z
       4: ireturn

  public com.google.common.base.Stopwatch start();
    Code:
       0: aload_0
       1: getfield      #11                 // Field isRunning:Z
       4: ifne          11
       7: iconst_1
       8: goto          12
      11: iconst_0
      12: ldc           #12                 // String This stopwatch is already running.
      14: invokestatic  #13                 // Method com/google/common/base/Preconditions.checkState:(ZLjava/lang/Object;)V
      17: aload_0
      18: iconst_1
      19: putfield      #11                 // Field isRunning:Z
      22: aload_0
      23: aload_0
      24: getfield      #7                  // Field ticker:Lcom/google/common/base/Ticker;
      27: invokevirtual #14                 // Method com/google/common/base/Ticker.read:()J
      30: putfield      #15                 // Field startTick:J
      33: aload_0
      34: areturn

  public com.google.common.base.Stopwatch stop();
    Code:
       0: aload_0
       1: getfield      #7                  // Field ticker:Lcom/google/common/base/Ticker;
       4: invokevirtual #14                 // Method com/google/common/base/Ticker.read:()J
       7: lstore_1
       8: aload_0
       9: getfield      #11                 // Field isRunning:Z
      12: ldc           #16                 // String This stopwatch is already stopped.
      14: invokestatic  #13                 // Method com/google/common/base/Preconditions.checkState:(ZLjava/lang/Object;)V
      17: aload_0
      18: iconst_0
      19: putfield      #11                 // Field isRunning:Z
      22: aload_0
      23: dup
      24: getfield      #17                 // Field elapsedNanos:J
      27: lload_1
      28: aload_0
      29: getfield      #15                 // Field startTick:J
      32: lsub
      33: ladd
      34: putfield      #17                 // Field elapsedNanos:J
      37: aload_0
      38: areturn

  public com.google.common.base.Stopwatch reset();
    Code:
       0: aload_0
       1: lconst_0
       2: putfield      #17                 // Field elapsedNanos:J
       5: aload_0
       6: iconst_0
       7: putfield      #11                 // Field isRunning:Z
      10: aload_0
      11: areturn

  public long elapsed(java.util.concurrent.TimeUnit);
    Code:
       0: aload_1
       1: aload_0
       2: invokespecial #18                 // Method elapsedNanos:()J
       5: getstatic     #19                 // Field java/util/concurrent/TimeUnit.NANOSECONDS:Ljava/util/concurrent/TimeUnit;
       8: invokevirtual #20                 // Method java/util/concurrent/TimeUnit.convert:(JLjava/util/concurrent/TimeUnit;)J
      11: lreturn

  public java.time.Duration elapsed();
    Code:
       0: aload_0
       1: invokespecial #18                 // Method elapsedNanos:()J
       4: invokestatic  #21                 // Method java/time/Duration.ofNanos:(J)Ljava/time/Duration;
       7: areturn

  public java.lang.String toString();
    Code:
       0: aload_0
       1: invokespecial #18                 // Method elapsedNanos:()J
       4: lstore_1
       5: lload_1
       6: invokestatic  #22                 // Method chooseUnit:(J)Ljava/util/concurrent/TimeUnit;
       9: astore_3
      10: lload_1
      11: l2d
      12: getstatic     #19                 // Field java/util/concurrent/TimeUnit.NANOSECONDS:Ljava/util/concurrent/TimeUnit;
      15: lconst_1
      16: aload_3
      17: invokevirtual #20                 // Method java/util/concurrent/TimeUnit.convert:(JLjava/util/concurrent/TimeUnit;)J
      20: l2d
      21: ddiv
      22: dstore        4
      24: new           #23                 // class java/lang/StringBuilder
      27: dup
      28: invokespecial #24                 // Method java/lang/StringBuilder."<init>":()V
      31: dload         4
      33: invokestatic  #25                 // Method com/google/common/base/Platform.formatCompact4Digits:(D)Ljava/lang/String;
      36: invokevirtual #26                 // Method java/lang/StringBuilder.append:(Ljava/lang/String;)Ljava/lang/StringBuilder;
      39: ldc           #27                 // String
      41: invokevirtual #26                 // Method java/lang/StringBuilder.append:(Ljava/lang/String;)Ljava/lang/StringBuilder;
      44: aload_3
      45: invokestatic  #28                 // Method abbreviate:(Ljava/util/concurrent/TimeUnit;)Ljava/lang/String;
      48: invokevirtual #26                 // Method java/lang/StringBuilder.append:(Ljava/lang/String;)Ljava/lang/StringBuilder;
      51: invokevirtual #29                 // Method java/lang/StringBuilder.toString:()Ljava/lang/String;
      54: areturn
}
