Compiled from "Synchronized.java"
class com.google.common.collect.Synchronized$SynchronizedObject implements java.io.Serializable {
  final java.lang.Object delegate;

  final java.lang.Object mutex;

  com.google.common.collect.Synchronized$SynchronizedObject(java.lang.Object, java.lang.Object);
    Code:
       0: aload_0
       1: invokespecial #1                  // Method java/lang/Object."<init>":()V
       4: aload_0
       5: aload_1
       6: invokestatic  #2                  // Method com/google/common/base/Preconditions.checkNotNull:(Ljava/lang/Object;)Ljava/lang/Object;
       9: putfield      #3                  // Field delegate:Ljava/lang/Object;
      12: aload_0
      13: aload_2
      14: ifnonnull     21
      17: aload_0
      18: goto          22
      21: aload_2
      22: putfield      #4                  // Field mutex:Ljava/lang/Object;
      25: return

  java.lang.Object delegate();
    Code:
       0: aload_0
       1: getfield      #3                  // Field delegate:Ljava/lang/Object;
       4: areturn

  public java.lang.String toString();
    Code:
       0: aload_0
       1: getfield      #4                  // Field mutex:Ljava/lang/Object;
       4: dup
       5: astore_1
       6: monitorenter
       7: aload_0
       8: getfield      #3                  // Field delegate:Ljava/lang/Object;
      11: invokevirtual #5                  // Method java/lang/Object.toString:()Ljava/lang/String;
      14: aload_1
      15: monitorexit
      16: areturn
      17: astore_2
      18: aload_1
      19: monitorexit
      20: aload_2
      21: athrow
    Exception table:
       from    to  target type
           7    16    17   any
          17    20    17   any
}
