Compiled from "AbstractTestCITimeout.java"
public class org.apache.hadoop.hbase.client.AbstractTestCITimeout$SleepCoprocessor implements org.apache.hadoop.hbase.coprocessor.RegionCoprocessor,org.apache.hadoop.hbase.coprocessor.RegionObserver {
  public static final int SLEEP_TIME;

  public org.apache.hadoop.hbase.client.AbstractTestCITimeout$SleepCoprocessor();
    Code:
       0: aload_0
       1: invokespecial #1                  // Method java/lang/Object."<init>":()V
       4: return

  public java.util.Optional<org.apache.hadoop.hbase.coprocessor.RegionObserver> getRegionObserver();
    Code:
       0: aload_0
       1: invokestatic  #2                  // Method java/util/Optional.of:(Ljava/lang/Object;)Ljava/util/Optional;
       4: areturn

  public void preGetOp(org.apache.hadoop.hbase.coprocessor.ObserverContext<org.apache.hadoop.hbase.coprocessor.RegionCoprocessorEnvironment>, org.apache.hadoop.hbase.client.Get, java.util.List<org.apache.hadoop.hbase.Cell>) throws java.io.IOException;
    Code:
       0: ldc2_w        #4                  // long 5000l
       3: invokestatic  #6                  // Method org/apache/hadoop/hbase/util/Threads.sleep:(J)V
       6: return

  public void prePut(org.apache.hadoop.hbase.coprocessor.ObserverContext<org.apache.hadoop.hbase.coprocessor.RegionCoprocessorEnvironment>, org.apache.hadoop.hbase.client.Put, org.apache.hadoop.hbase.wal.WALEdit, org.apache.hadoop.hbase.client.Durability) throws java.io.IOException;
    Code:
       0: ldc2_w        #4                  // long 5000l
       3: invokestatic  #6                  // Method org/apache/hadoop/hbase/util/Threads.sleep:(J)V
       6: return

  public org.apache.hadoop.hbase.client.Result preIncrement(org.apache.hadoop.hbase.coprocessor.ObserverContext<org.apache.hadoop.hbase.coprocessor.RegionCoprocessorEnvironment>, org.apache.hadoop.hbase.client.Increment) throws java.io.IOException;
    Code:
       0: ldc2_w        #4                  // long 5000l
       3: invokestatic  #6                  // Method org/apache/hadoop/hbase/util/Threads.sleep:(J)V
       6: aconst_null
       7: areturn

  public void preDelete(org.apache.hadoop.hbase.coprocessor.ObserverContext<org.apache.hadoop.hbase.coprocessor.RegionCoprocessorEnvironment>, org.apache.hadoop.hbase.client.Delete, org.apache.hadoop.hbase.wal.WALEdit, org.apache.hadoop.hbase.client.Durability) throws java.io.IOException;
    Code:
       0: ldc2_w        #4                  // long 5000l
       3: invokestatic  #6                  // Method org/apache/hadoop/hbase/util/Threads.sleep:(J)V
       6: return
}
