Compiled from "AbstractTestFSWAL.java"
public abstract class org.apache.hadoop.hbase.regionserver.wal.AbstractTestFSWAL {
  protected static final org.slf4j.Logger LOG;

  protected static org.apache.hadoop.conf.Configuration CONF;

  protected static org.apache.hadoop.fs.FileSystem FS;

  protected static org.apache.hadoop.fs.Path DIR;

  protected static final org.apache.hadoop.hbase.HBaseTestingUtility TEST_UTIL;

  public final org.junit.rules.TestName currentTest;

  public org.apache.hadoop.hbase.regionserver.wal.AbstractTestFSWAL();
    Code:
       0: aload_0
       1: invokespecial #1                  // Method java/lang/Object."<init>":()V
       4: aload_0
       5: new           #2                  // class org/junit/rules/TestName
       8: dup
       9: invokespecial #3                  // Method org/junit/rules/TestName."<init>":()V
      12: putfield      #4                  // Field currentTest:Lorg/junit/rules/TestName;
      15: return

  public void setUp() throws java.lang.Exception;
    Code:
       0: getstatic     #5                  // Field FS:Lorg/apache/hadoop/fs/FileSystem;
       3: new           #6                  // class org/apache/hadoop/fs/Path
       6: dup
       7: ldc           #7                  // String /
       9: invokespecial #8                  // Method org/apache/hadoop/fs/Path."<init>":(Ljava/lang/String;)V
      12: invokevirtual #9                  // Method org/apache/hadoop/fs/FileSystem.listStatus:(Lorg/apache/hadoop/fs/Path;)[Lorg/apache/hadoop/fs/FileStatus;
      15: astore_1
      16: aload_1
      17: astore_2
      18: aload_2
      19: arraylength
      20: istore_3
      21: iconst_0
      22: istore        4
      24: iload         4
      26: iload_3
      27: if_icmpge     55
      30: aload_2
      31: iload         4
      33: aaload
      34: astore        5
      36: getstatic     #5                  // Field FS:Lorg/apache/hadoop/fs/FileSystem;
      39: aload         5
      41: invokevirtual #10                 // Method org/apache/hadoop/fs/FileStatus.getPath:()Lorg/apache/hadoop/fs/Path;
      44: iconst_1
      45: invokevirtual #11                 // Method org/apache/hadoop/fs/FileSystem.delete:(Lorg/apache/hadoop/fs/Path;Z)Z
      48: pop
      49: iinc          4, 1
      52: goto          24
      55: getstatic     #12                 // Field TEST_UTIL:Lorg/apache/hadoop/hbase/HBaseTestingUtility;
      58: invokevirtual #13                 // Method org/apache/hadoop/hbase/HBaseTestingUtility.createRootDir:()Lorg/apache/hadoop/fs/Path;
      61: astore_2
      62: getstatic     #12                 // Field TEST_UTIL:Lorg/apache/hadoop/hbase/HBaseTestingUtility;
      65: invokevirtual #14                 // Method org/apache/hadoop/hbase/HBaseTestingUtility.createWALRootDir:()Lorg/apache/hadoop/fs/Path;
      68: astore_3
      69: new           #6                  // class org/apache/hadoop/fs/Path
      72: dup
      73: aload_3
      74: aload_0
      75: getfield      #4                  // Field currentTest:Lorg/junit/rules/TestName;
      78: invokevirtual #15                 // Method org/junit/rules/TestName.getMethodName:()Ljava/lang/String;
      81: invokespecial #16                 // Method org/apache/hadoop/fs/Path."<init>":(Lorg/apache/hadoop/fs/Path;Ljava/lang/String;)V
      84: putstatic     #17                 // Field DIR:Lorg/apache/hadoop/fs/Path;
      87: aload_2
      88: aload_3
      89: invokestatic  #18                 // Method org/junit/Assert.assertNotEquals:(Ljava/lang/Object;Ljava/lang/Object;)V
      92: return

  public static void setUpBeforeClass() throws java.lang.Exception;
    Code:
       0: getstatic     #12                 // Field TEST_UTIL:Lorg/apache/hadoop/hbase/HBaseTestingUtility;
       3: invokevirtual #19                 // Method org/apache/hadoop/hbase/HBaseTestingUtility.getConfiguration:()Lorg/apache/hadoop/conf/Configuration;
       6: ldc           #20                 // String dfs.blocksize
       8: ldc           #21                 // int 1048576
      10: invokevirtual #22                 // Method org/apache/hadoop/conf/Configuration.setInt:(Ljava/lang/String;I)V
      13: getstatic     #12                 // Field TEST_UTIL:Lorg/apache/hadoop/hbase/HBaseTestingUtility;
      16: invokevirtual #19                 // Method org/apache/hadoop/hbase/HBaseTestingUtility.getConfiguration:()Lorg/apache/hadoop/conf/Configuration;
      19: ldc           #23                 // String dfs.namenode.heartbeat.recheck-interval
      21: sipush        5000
      24: invokevirtual #22                 // Method org/apache/hadoop/conf/Configuration.setInt:(Ljava/lang/String;I)V
      27: getstatic     #12                 // Field TEST_UTIL:Lorg/apache/hadoop/hbase/HBaseTestingUtility;
      30: invokevirtual #19                 // Method org/apache/hadoop/hbase/HBaseTestingUtility.getConfiguration:()Lorg/apache/hadoop/conf/Configuration;
      33: ldc           #24                 // String dfs.heartbeat.interval
      35: iconst_1
      36: invokevirtual #22                 // Method org/apache/hadoop/conf/Configuration.setInt:(Ljava/lang/String;I)V
      39: getstatic     #12                 // Field TEST_UTIL:Lorg/apache/hadoop/hbase/HBaseTestingUtility;
      42: invokevirtual #19                 // Method org/apache/hadoop/hbase/HBaseTestingUtility.getConfiguration:()Lorg/apache/hadoop/conf/Configuration;
      45: ldc           #25                 // String dfs.client.socket-timeout
      47: sipush        5000
      50: invokevirtual #22                 // Method org/apache/hadoop/conf/Configuration.setInt:(Ljava/lang/String;I)V
      53: getstatic     #12                 // Field TEST_UTIL:Lorg/apache/hadoop/hbase/HBaseTestingUtility;
      56: invokevirtual #19                 // Method org/apache/hadoop/hbase/HBaseTestingUtility.getConfiguration:()Lorg/apache/hadoop/conf/Configuration;
      59: ldc           #26                 // String hbase.ipc.client.connect.max.retries
      61: iconst_1
      62: invokevirtual #22                 // Method org/apache/hadoop/conf/Configuration.setInt:(Ljava/lang/String;I)V
      65: getstatic     #12                 // Field TEST_UTIL:Lorg/apache/hadoop/hbase/HBaseTestingUtility;
      68: invokevirtual #19                 // Method org/apache/hadoop/hbase/HBaseTestingUtility.getConfiguration:()Lorg/apache/hadoop/conf/Configuration;
      71: ldc           #27                 // String dfs.client.block.recovery.retries
      73: iconst_1
      74: invokevirtual #22                 // Method org/apache/hadoop/conf/Configuration.setInt:(Ljava/lang/String;I)V
      77: getstatic     #12                 // Field TEST_UTIL:Lorg/apache/hadoop/hbase/HBaseTestingUtility;
      80: invokevirtual #19                 // Method org/apache/hadoop/hbase/HBaseTestingUtility.getConfiguration:()Lorg/apache/hadoop/conf/Configuration;
      83: ldc           #28                 // String hbase.ipc.client.connection.maxidletime
      85: sipush        500
      88: invokevirtual #22                 // Method org/apache/hadoop/conf/Configuration.setInt:(Ljava/lang/String;I)V
      91: getstatic     #12                 // Field TEST_UTIL:Lorg/apache/hadoop/hbase/HBaseTestingUtility;
      94: invokevirtual #19                 // Method org/apache/hadoop/hbase/HBaseTestingUtility.getConfiguration:()Lorg/apache/hadoop/conf/Configuration;
      97: ldc           #30                 // String hbase.coprocessor.wal.classes
      99: ldc           #31                 // class org/apache/hadoop/hbase/coprocessor/SampleRegionWALCoprocessor
     101: invokevirtual #32                 // Method java/lang/Class.getName:()Ljava/lang/String;
     104: invokevirtual #33                 // Method org/apache/hadoop/conf/Configuration.set:(Ljava/lang/String;Ljava/lang/String;)V
     107: getstatic     #12                 // Field TEST_UTIL:Lorg/apache/hadoop/hbase/HBaseTestingUtility;
     110: iconst_3
     111: invokevirtual #34                 // Method org/apache/hadoop/hbase/HBaseTestingUtility.startMiniDFSCluster:(I)Lorg/apache/hadoop/hdfs/MiniDFSCluster;
     114: pop
     115: getstatic     #12                 // Field TEST_UTIL:Lorg/apache/hadoop/hbase/HBaseTestingUtility;
     118: invokevirtual #19                 // Method org/apache/hadoop/hbase/HBaseTestingUtility.getConfiguration:()Lorg/apache/hadoop/conf/Configuration;
     121: putstatic     #35                 // Field CONF:Lorg/apache/hadoop/conf/Configuration;
     124: getstatic     #12                 // Field TEST_UTIL:Lorg/apache/hadoop/hbase/HBaseTestingUtility;
     127: invokevirtual #36                 // Method org/apache/hadoop/hbase/HBaseTestingUtility.getDFSCluster:()Lorg/apache/hadoop/hdfs/MiniDFSCluster;
     130: invokevirtual #37                 // Method org/apache/hadoop/hdfs/MiniDFSCluster.getFileSystem:()Lorg/apache/hadoop/hdfs/DistributedFileSystem;
     133: putstatic     #5                  // Field FS:Lorg/apache/hadoop/fs/FileSystem;
     136: return

  public static void tearDownAfterClass() throws java.lang.Exception;
    Code:
       0: getstatic     #12                 // Field TEST_UTIL:Lorg/apache/hadoop/hbase/HBaseTestingUtility;
       3: invokevirtual #38                 // Method org/apache/hadoop/hbase/HBaseTestingUtility.shutdownMiniCluster:()V
       6: return

  protected abstract org.apache.hadoop.hbase.regionserver.wal.AbstractFSWAL<?> newWAL(org.apache.hadoop.fs.FileSystem, org.apache.hadoop.fs.Path, java.lang.String, java.lang.String, org.apache.hadoop.conf.Configuration, java.util.List<org.apache.hadoop.hbase.regionserver.wal.WALActionsListener>, boolean, java.lang.String, java.lang.String) throws java.io.IOException;

  protected abstract org.apache.hadoop.hbase.regionserver.wal.AbstractFSWAL<?> newSlowWAL(org.apache.hadoop.fs.FileSystem, org.apache.hadoop.fs.Path, java.lang.String, java.lang.String, org.apache.hadoop.conf.Configuration, java.util.List<org.apache.hadoop.hbase.regionserver.wal.WALActionsListener>, boolean, java.lang.String, java.lang.String, java.lang.Runnable) throws java.io.IOException;

  public void testWALCoprocessorLoaded() throws java.lang.Exception;
    Code:
       0: aconst_null
       1: astore_1
       2: aload_0
       3: getstatic     #5                  // Field FS:Lorg/apache/hadoop/fs/FileSystem;
       6: getstatic     #35                 // Field CONF:Lorg/apache/hadoop/conf/Configuration;
       9: invokestatic  #39                 // Method org/apache/hadoop/hbase/util/CommonFSUtils.getWALRootDir:(Lorg/apache/hadoop/conf/Configuration;)Lorg/apache/hadoop/fs/Path;
      12: getstatic     #17                 // Field DIR:Lorg/apache/hadoop/fs/Path;
      15: invokevirtual #40                 // Method org/apache/hadoop/fs/Path.toString:()Ljava/lang/String;
      18: ldc           #42                 // String oldWALs
      20: getstatic     #35                 // Field CONF:Lorg/apache/hadoop/conf/Configuration;
      23: aconst_null
      24: iconst_1
      25: aconst_null
      26: aconst_null
      27: invokevirtual #43                 // Method newWAL:(Lorg/apache/hadoop/fs/FileSystem;Lorg/apache/hadoop/fs/Path;Ljava/lang/String;Ljava/lang/String;Lorg/apache/hadoop/conf/Configuration;Ljava/util/List;ZLjava/lang/String;Ljava/lang/String;)Lorg/apache/hadoop/hbase/regionserver/wal/AbstractFSWAL;
      30: astore_1
      31: aload_1
      32: invokevirtual #44                 // Method org/apache/hadoop/hbase/regionserver/wal/AbstractFSWAL.getCoprocessorHost:()Lorg/apache/hadoop/hbase/regionserver/wal/WALCoprocessorHost;
      35: astore_2
      36: aload_2
      37: ldc           #31                 // class org/apache/hadoop/hbase/coprocessor/SampleRegionWALCoprocessor
      39: invokevirtual #45                 // Method org/apache/hadoop/hbase/regionserver/wal/WALCoprocessorHost.findCoprocessor:(Ljava/lang/Class;)Lorg/apache/hadoop/hbase/Coprocessor;
      42: astore_3
      43: aload_3
      44: invokestatic  #46                 // Method org/junit/Assert.assertNotNull:(Ljava/lang/Object;)V
      47: aload_1
      48: ifnull        71
      51: aload_1
      52: invokevirtual #47                 // Method org/apache/hadoop/hbase/regionserver/wal/AbstractFSWAL.close:()V
      55: goto          71
      58: astore        4
      60: aload_1
      61: ifnull        68
      64: aload_1
      65: invokevirtual #47                 // Method org/apache/hadoop/hbase/regionserver/wal/AbstractFSWAL.close:()V
      68: aload         4
      70: athrow
      71: return
    Exception table:
       from    to  target type
           2    47    58   any
          58    60    58   any

  protected void addEdits(org.apache.hadoop.hbase.wal.WAL, org.apache.hadoop.hbase.client.RegionInfo, org.apache.hadoop.hbase.client.TableDescriptor, int, org.apache.hadoop.hbase.regionserver.MultiVersionConcurrencyControl, java.util.NavigableMap<byte[], java.lang.Integer>) throws java.io.IOException;
    Code:
       0: ldc           #48                 // String row
       2: invokestatic  #49                 // Method org/apache/hadoop/hbase/util/Bytes.toBytes:(Ljava/lang/String;)[B
       5: astore        7
       7: iconst_0
       8: istore        8
      10: iload         8
      12: iload         4
      14: if_icmpge     108
      17: invokestatic  #50                 // Method java/lang/System.currentTimeMillis:()J
      20: lstore        9
      22: new           #51                 // class org/apache/hadoop/hbase/wal/WALEdit
      25: dup
      26: invokespecial #52                 // Method org/apache/hadoop/hbase/wal/WALEdit."<init>":()V
      29: astore        11
      31: aload         11
      33: new           #53                 // class org/apache/hadoop/hbase/KeyValue
      36: dup
      37: aload         7
      39: aload         7
      41: aload         7
      43: lload         9
      45: aload         7
      47: invokespecial #54                 // Method org/apache/hadoop/hbase/KeyValue."<init>":([B[B[BJ[B)V
      50: invokevirtual #55                 // Method org/apache/hadoop/hbase/wal/WALEdit.add:(Lorg/apache/hadoop/hbase/Cell;)Lorg/apache/hadoop/hbase/wal/WALEdit;
      53: pop
      54: new           #56                 // class org/apache/hadoop/hbase/wal/WALKeyImpl
      57: dup
      58: aload_2
      59: invokeinterface #57,  1           // InterfaceMethod org/apache/hadoop/hbase/client/RegionInfo.getEncodedNameAsBytes:()[B
      64: aload_3
      65: invokeinterface #58,  1           // InterfaceMethod org/apache/hadoop/hbase/client/TableDescriptor.getTableName:()Lorg/apache/hadoop/hbase/TableName;
      70: ldc2_w        #60                 // long -1l
      73: lload         9
      75: getstatic     #62                 // Field org/apache/hadoop/hbase/wal/WALKey.EMPTY_UUIDS:Ljava/util/List;
      78: lconst_0
      79: lconst_0
      80: aload         5
      82: aload         6
      84: invokespecial #63                 // Method org/apache/hadoop/hbase/wal/WALKeyImpl."<init>":([BLorg/apache/hadoop/hbase/TableName;JJLjava/util/List;JJLorg/apache/hadoop/hbase/regionserver/MultiVersionConcurrencyControl;Ljava/util/NavigableMap;)V
      87: astore        12
      89: aload_1
      90: aload_2
      91: aload         12
      93: aload         11
      95: iconst_1
      96: invokeinterface #64,  5           // InterfaceMethod org/apache/hadoop/hbase/wal/WAL.append:(Lorg/apache/hadoop/hbase/client/RegionInfo;Lorg/apache/hadoop/hbase/wal/WALKeyImpl;Lorg/apache/hadoop/hbase/wal/WALEdit;Z)J
     101: pop2
     102: iinc          8, 1
     105: goto          10
     108: aload_1
     109: invokeinterface #65,  1           // InterfaceMethod org/apache/hadoop/hbase/wal/WAL.sync:()V
     114: return

  protected void flushRegion(org.apache.hadoop.hbase.wal.WAL, byte[], java.util.Set<byte[]>);
    Code:
       0: aload_1
       1: aload_2
       2: aload_3
       3: invokeinterface #66,  3           // InterfaceMethod org/apache/hadoop/hbase/wal/WAL.startCacheFlush:([BLjava/util/Set;)Ljava/lang/Long;
       8: pop
       9: aload_1
      10: aload_2
      11: invokeinterface #67,  2           // InterfaceMethod org/apache/hadoop/hbase/wal/WAL.completeCacheFlush:([B)V
      16: return

  public void testWALComparator() throws java.lang.Exception;
    Code:
       0: aconst_null
       1: astore_1
       2: aconst_null
       3: astore_2
       4: aload_0
       5: getstatic     #5                  // Field FS:Lorg/apache/hadoop/fs/FileSystem;
       8: getstatic     #35                 // Field CONF:Lorg/apache/hadoop/conf/Configuration;
      11: invokestatic  #39                 // Method org/apache/hadoop/hbase/util/CommonFSUtils.getWALRootDir:(Lorg/apache/hadoop/conf/Configuration;)Lorg/apache/hadoop/fs/Path;
      14: getstatic     #17                 // Field DIR:Lorg/apache/hadoop/fs/Path;
      17: invokevirtual #40                 // Method org/apache/hadoop/fs/Path.toString:()Ljava/lang/String;
      20: ldc           #42                 // String oldWALs
      22: getstatic     #35                 // Field CONF:Lorg/apache/hadoop/conf/Configuration;
      25: aconst_null
      26: iconst_1
      27: aconst_null
      28: aconst_null
      29: invokevirtual #43                 // Method newWAL:(Lorg/apache/hadoop/fs/FileSystem;Lorg/apache/hadoop/fs/Path;Ljava/lang/String;Ljava/lang/String;Lorg/apache/hadoop/conf/Configuration;Ljava/util/List;ZLjava/lang/String;Ljava/lang/String;)Lorg/apache/hadoop/hbase/regionserver/wal/AbstractFSWAL;
      32: astore_1
      33: getstatic     #68                 // Field LOG:Lorg/slf4j/Logger;
      36: new           #69                 // class java/lang/StringBuilder
      39: dup
      40: invokespecial #70                 // Method java/lang/StringBuilder."<init>":()V
      43: ldc           #71                 // String Log obtained is:
      45: invokevirtual #72                 // Method java/lang/StringBuilder.append:(Ljava/lang/String;)Ljava/lang/StringBuilder;
      48: aload_1
      49: invokevirtual #73                 // Method java/lang/StringBuilder.append:(Ljava/lang/Object;)Ljava/lang/StringBuilder;
      52: invokevirtual #74                 // Method java/lang/StringBuilder.toString:()Ljava/lang/String;
      55: invokeinterface #75,  2           // InterfaceMethod org/slf4j/Logger.debug:(Ljava/lang/String;)V
      60: aload_1
      61: getfield      #76                 // Field org/apache/hadoop/hbase/regionserver/wal/AbstractFSWAL.LOG_NAME_COMPARATOR:Ljava/util/Comparator;
      64: astore_3
      65: aload_1
      66: ldc2_w        #77                 // long 11l
      69: invokevirtual #79                 // Method org/apache/hadoop/hbase/regionserver/wal/AbstractFSWAL.computeFilename:(J)Lorg/apache/hadoop/fs/Path;
      72: astore        4
      74: aload_1
      75: ldc2_w        #80                 // long 12l
      78: invokevirtual #79                 // Method org/apache/hadoop/hbase/regionserver/wal/AbstractFSWAL.computeFilename:(J)Lorg/apache/hadoop/fs/Path;
      81: astore        5
      83: aload_3
      84: aload         4
      86: aload         4
      88: invokeinterface #82,  3           // InterfaceMethod java/util/Comparator.compare:(Ljava/lang/Object;Ljava/lang/Object;)I
      93: ifne          100
      96: iconst_1
      97: goto          101
     100: iconst_0
     101: invokestatic  #83                 // Method org/junit/Assert.assertTrue:(Z)V
     104: aload_3
     105: aload         4
     107: aload         5
     109: invokeinterface #82,  3           // InterfaceMethod java/util/Comparator.compare:(Ljava/lang/Object;Ljava/lang/Object;)I
     114: ifge          121
     117: iconst_1
     118: goto          122
     121: iconst_0
     122: invokestatic  #83                 // Method org/junit/Assert.assertTrue:(Z)V
     125: aload_0
     126: getstatic     #5                  // Field FS:Lorg/apache/hadoop/fs/FileSystem;
     129: getstatic     #35                 // Field CONF:Lorg/apache/hadoop/conf/Configuration;
     132: invokestatic  #39                 // Method org/apache/hadoop/hbase/util/CommonFSUtils.getWALRootDir:(Lorg/apache/hadoop/conf/Configuration;)Lorg/apache/hadoop/fs/Path;
     135: getstatic     #17                 // Field DIR:Lorg/apache/hadoop/fs/Path;
     138: invokevirtual #40                 // Method org/apache/hadoop/fs/Path.toString:()Ljava/lang/String;
     141: ldc           #42                 // String oldWALs
     143: getstatic     #35                 // Field CONF:Lorg/apache/hadoop/conf/Configuration;
     146: aconst_null
     147: iconst_1
     148: aconst_null
     149: ldc           #85                 // String .meta
     151: invokevirtual #43                 // Method newWAL:(Lorg/apache/hadoop/fs/FileSystem;Lorg/apache/hadoop/fs/Path;Ljava/lang/String;Ljava/lang/String;Lorg/apache/hadoop/conf/Configuration;Ljava/util/List;ZLjava/lang/String;Ljava/lang/String;)Lorg/apache/hadoop/hbase/regionserver/wal/AbstractFSWAL;
     154: astore_2
     155: aload_2
     156: getfield      #76                 // Field org/apache/hadoop/hbase/regionserver/wal/AbstractFSWAL.LOG_NAME_COMPARATOR:Ljava/util/Comparator;
     159: astore        6
     161: aload_2
     162: ldc2_w        #77                 // long 11l
     165: invokevirtual #79                 // Method org/apache/hadoop/hbase/regionserver/wal/AbstractFSWAL.computeFilename:(J)Lorg/apache/hadoop/fs/Path;
     168: astore        7
     170: aload_2
     171: ldc2_w        #80                 // long 12l
     174: invokevirtual #79                 // Method org/apache/hadoop/hbase/regionserver/wal/AbstractFSWAL.computeFilename:(J)Lorg/apache/hadoop/fs/Path;
     177: astore        8
     179: aload         6
     181: aload         7
     183: aload         7
     185: invokeinterface #82,  3           // InterfaceMethod java/util/Comparator.compare:(Ljava/lang/Object;Ljava/lang/Object;)I
     190: ifne          197
     193: iconst_1
     194: goto          198
     197: iconst_0
     198: invokestatic  #83                 // Method org/junit/Assert.assertTrue:(Z)V
     201: aload         6
     203: aload         7
     205: aload         8
     207: invokeinterface #82,  3           // InterfaceMethod java/util/Comparator.compare:(Ljava/lang/Object;Ljava/lang/Object;)I
     212: ifge          219
     215: iconst_1
     216: goto          220
     219: iconst_0
     220: invokestatic  #83                 // Method org/junit/Assert.assertTrue:(Z)V
     223: iconst_0
     224: istore        9
     226: aload_3
     227: aload         7
     229: aload         5
     231: invokeinterface #82,  3           // InterfaceMethod java/util/Comparator.compare:(Ljava/lang/Object;Ljava/lang/Object;)I
     236: pop
     237: goto          245
     240: astore        10
     242: iconst_1
     243: istore        9
     245: ldc           #87                 // String Comparator doesn't complain while checking meta log files
     247: iload         9
     249: invokestatic  #88                 // Method org/junit/Assert.assertTrue:(Ljava/lang/String;Z)V
     252: iconst_0
     253: istore        10
     255: aload         6
     257: aload         7
     259: aload         5
     261: invokeinterface #82,  3           // InterfaceMethod java/util/Comparator.compare:(Ljava/lang/Object;Ljava/lang/Object;)I
     266: pop
     267: goto          275
     270: astore        11
     272: iconst_1
     273: istore        10
     275: ldc           #89                 // String Meta comparator doesn't complain while checking log files
     277: iload         10
     279: invokestatic  #88                 // Method org/junit/Assert.assertTrue:(Ljava/lang/String;Z)V
     282: aload_1
     283: ifnull        290
     286: aload_1
     287: invokevirtual #47                 // Method org/apache/hadoop/hbase/regionserver/wal/AbstractFSWAL.close:()V
     290: aload_2
     291: ifnull        322
     294: aload_2
     295: invokevirtual #47                 // Method org/apache/hadoop/hbase/regionserver/wal/AbstractFSWAL.close:()V
     298: goto          322
     301: astore        12
     303: aload_1
     304: ifnull        311
     307: aload_1
     308: invokevirtual #47                 // Method org/apache/hadoop/hbase/regionserver/wal/AbstractFSWAL.close:()V
     311: aload_2
     312: ifnull        319
     315: aload_2
     316: invokevirtual #47                 // Method org/apache/hadoop/hbase/regionserver/wal/AbstractFSWAL.close:()V
     319: aload         12
     321: athrow
     322: return
    Exception table:
       from    to  target type
         226   237   240   Class java/lang/IllegalArgumentException
         255   267   270   Class java/lang/IllegalArgumentException
           4   282   301   any
         301   303   301   any

  public void testFindMemStoresEligibleForFlush() throws java.lang.Exception;
    Code:
       0: getstatic     #68                 // Field LOG:Lorg/slf4j/Logger;
       3: ldc           #90                 // String testFindMemStoresEligibleForFlush
       5: invokeinterface #75,  2           // InterfaceMethod org/slf4j/Logger.debug:(Ljava/lang/String;)V
      10: getstatic     #35                 // Field CONF:Lorg/apache/hadoop/conf/Configuration;
      13: invokestatic  #91                 // Method org/apache/hadoop/hbase/HBaseConfiguration.create:(Lorg/apache/hadoop/conf/Configuration;)Lorg/apache/hadoop/conf/Configuration;
      16: astore_1
      17: aload_1
      18: ldc           #92                 // String hbase.regionserver.maxlogs
      20: iconst_1
      21: invokevirtual #22                 // Method org/apache/hadoop/conf/Configuration.setInt:(Ljava/lang/String;I)V
      24: aload_0
      25: getstatic     #5                  // Field FS:Lorg/apache/hadoop/fs/FileSystem;
      28: aload_1
      29: invokestatic  #39                 // Method org/apache/hadoop/hbase/util/CommonFSUtils.getWALRootDir:(Lorg/apache/hadoop/conf/Configuration;)Lorg/apache/hadoop/fs/Path;
      32: getstatic     #17                 // Field DIR:Lorg/apache/hadoop/fs/Path;
      35: invokevirtual #40                 // Method org/apache/hadoop/fs/Path.toString:()Ljava/lang/String;
      38: ldc           #42                 // String oldWALs
      40: aload_1
      41: aconst_null
      42: iconst_1
      43: aconst_null
      44: aconst_null
      45: invokevirtual #43                 // Method newWAL:(Lorg/apache/hadoop/fs/FileSystem;Lorg/apache/hadoop/fs/Path;Ljava/lang/String;Ljava/lang/String;Lorg/apache/hadoop/conf/Configuration;Ljava/util/List;ZLjava/lang/String;Ljava/lang/String;)Lorg/apache/hadoop/hbase/regionserver/wal/AbstractFSWAL;
      48: astore_2
      49: ldc           #93                 // String t1
      51: invokestatic  #94                 // Method org/apache/hadoop/hbase/TableName.valueOf:(Ljava/lang/String;)Lorg/apache/hadoop/hbase/TableName;
      54: invokestatic  #95                 // Method org/apache/hadoop/hbase/client/TableDescriptorBuilder.newBuilder:(Lorg/apache/hadoop/hbase/TableName;)Lorg/apache/hadoop/hbase/client/TableDescriptorBuilder;
      57: ldc           #48                 // String row
      59: invokestatic  #96                 // Method org/apache/hadoop/hbase/client/ColumnFamilyDescriptorBuilder.of:(Ljava/lang/String;)Lorg/apache/hadoop/hbase/client/ColumnFamilyDescriptor;
      62: invokevirtual #97                 // Method org/apache/hadoop/hbase/client/TableDescriptorBuilder.setColumnFamily:(Lorg/apache/hadoop/hbase/client/ColumnFamilyDescriptor;)Lorg/apache/hadoop/hbase/client/TableDescriptorBuilder;
      65: invokevirtual #98                 // Method org/apache/hadoop/hbase/client/TableDescriptorBuilder.build:()Lorg/apache/hadoop/hbase/client/TableDescriptor;
      68: astore_3
      69: ldc           #99                 // String t2
      71: invokestatic  #94                 // Method org/apache/hadoop/hbase/TableName.valueOf:(Ljava/lang/String;)Lorg/apache/hadoop/hbase/TableName;
      74: invokestatic  #95                 // Method org/apache/hadoop/hbase/client/TableDescriptorBuilder.newBuilder:(Lorg/apache/hadoop/hbase/TableName;)Lorg/apache/hadoop/hbase/client/TableDescriptorBuilder;
      77: ldc           #48                 // String row
      79: invokestatic  #96                 // Method org/apache/hadoop/hbase/client/ColumnFamilyDescriptorBuilder.of:(Ljava/lang/String;)Lorg/apache/hadoop/hbase/client/ColumnFamilyDescriptor;
      82: invokevirtual #97                 // Method org/apache/hadoop/hbase/client/TableDescriptorBuilder.setColumnFamily:(Lorg/apache/hadoop/hbase/client/ColumnFamilyDescriptor;)Lorg/apache/hadoop/hbase/client/TableDescriptorBuilder;
      85: invokevirtual #98                 // Method org/apache/hadoop/hbase/client/TableDescriptorBuilder.build:()Lorg/apache/hadoop/hbase/client/TableDescriptor;
      88: astore        4
      90: aload_3
      91: invokeinterface #58,  1           // InterfaceMethod org/apache/hadoop/hbase/client/TableDescriptor.getTableName:()Lorg/apache/hadoop/hbase/TableName;
      96: invokestatic  #100                // Method org/apache/hadoop/hbase/client/RegionInfoBuilder.newBuilder:(Lorg/apache/hadoop/hbase/TableName;)Lorg/apache/hadoop/hbase/client/RegionInfoBuilder;
      99: invokevirtual #101                // Method org/apache/hadoop/hbase/client/RegionInfoBuilder.build:()Lorg/apache/hadoop/hbase/client/RegionInfo;
     102: astore        5
     104: aload         4
     106: invokeinterface #58,  1           // InterfaceMethod org/apache/hadoop/hbase/client/TableDescriptor.getTableName:()Lorg/apache/hadoop/hbase/TableName;
     111: invokestatic  #100                // Method org/apache/hadoop/hbase/client/RegionInfoBuilder.newBuilder:(Lorg/apache/hadoop/hbase/TableName;)Lorg/apache/hadoop/hbase/client/RegionInfoBuilder;
     114: invokevirtual #101                // Method org/apache/hadoop/hbase/client/RegionInfoBuilder.build:()Lorg/apache/hadoop/hbase/client/RegionInfo;
     117: astore        6
     119: new           #102                // class org/apache/hadoop/hbase/regionserver/MultiVersionConcurrencyControl
     122: dup
     123: invokespecial #103                // Method org/apache/hadoop/hbase/regionserver/MultiVersionConcurrencyControl."<init>":()V
     126: astore        7
     128: new           #104                // class java/util/TreeMap
     131: dup
     132: getstatic     #105                // Field org/apache/hadoop/hbase/util/Bytes.BYTES_COMPARATOR:Ljava/util/Comparator;
     135: invokespecial #106                // Method java/util/TreeMap."<init>":(Ljava/util/Comparator;)V
     138: astore        8
     140: aload_3
     141: invokeinterface #107,  1          // InterfaceMethod org/apache/hadoop/hbase/client/TableDescriptor.getColumnFamilyNames:()Ljava/util/Set;
     146: invokeinterface #108,  1          // InterfaceMethod java/util/Set.iterator:()Ljava/util/Iterator;
     151: astore        9
     153: aload         9
     155: invokeinterface #109,  1          // InterfaceMethod java/util/Iterator.hasNext:()Z
     160: ifeq          192
     163: aload         9
     165: invokeinterface #110,  1          // InterfaceMethod java/util/Iterator.next:()Ljava/lang/Object;
     170: checkcast     #111                // class "[B"
     173: astore        10
     175: aload         8
     177: aload         10
     179: iconst_0
     180: invokestatic  #112                // Method java/lang/Integer.valueOf:(I)Ljava/lang/Integer;
     183: invokeinterface #113,  3          // InterfaceMethod java/util/NavigableMap.put:(Ljava/lang/Object;Ljava/lang/Object;)Ljava/lang/Object;
     188: pop
     189: goto          153
     192: new           #104                // class java/util/TreeMap
     195: dup
     196: getstatic     #105                // Field org/apache/hadoop/hbase/util/Bytes.BYTES_COMPARATOR:Ljava/util/Comparator;
     199: invokespecial #106                // Method java/util/TreeMap."<init>":(Ljava/util/Comparator;)V
     202: astore        9
     204: aload         4
     206: invokeinterface #107,  1          // InterfaceMethod org/apache/hadoop/hbase/client/TableDescriptor.getColumnFamilyNames:()Ljava/util/Set;
     211: invokeinterface #108,  1          // InterfaceMethod java/util/Set.iterator:()Ljava/util/Iterator;
     216: astore        10
     218: aload         10
     220: invokeinterface #109,  1          // InterfaceMethod java/util/Iterator.hasNext:()Z
     225: ifeq          257
     228: aload         10
     230: invokeinterface #110,  1          // InterfaceMethod java/util/Iterator.next:()Ljava/lang/Object;
     235: checkcast     #111                // class "[B"
     238: astore        11
     240: aload         9
     242: aload         11
     244: iconst_0
     245: invokestatic  #112                // Method java/lang/Integer.valueOf:(I)Ljava/lang/Integer;
     248: invokeinterface #113,  3          // InterfaceMethod java/util/NavigableMap.put:(Ljava/lang/Object;Ljava/lang/Object;)Ljava/lang/Object;
     253: pop
     254: goto          218
     257: aload_0
     258: aload_2
     259: aload         5
     261: aload_3
     262: iconst_2
     263: aload         7
     265: aload         8
     267: invokevirtual #114                // Method addEdits:(Lorg/apache/hadoop/hbase/wal/WAL;Lorg/apache/hadoop/hbase/client/RegionInfo;Lorg/apache/hadoop/hbase/client/TableDescriptor;ILorg/apache/hadoop/hbase/regionserver/MultiVersionConcurrencyControl;Ljava/util/NavigableMap;)V
     270: aload_2
     271: invokevirtual #115                // Method org/apache/hadoop/hbase/regionserver/wal/AbstractFSWAL.rollWriter:()[[B
     274: pop
     275: aload_0
     276: aload_2
     277: aload         5
     279: aload_3
     280: iconst_2
     281: aload         7
     283: aload         8
     285: invokevirtual #114                // Method addEdits:(Lorg/apache/hadoop/hbase/wal/WAL;Lorg/apache/hadoop/hbase/client/RegionInfo;Lorg/apache/hadoop/hbase/client/TableDescriptor;ILorg/apache/hadoop/hbase/regionserver/MultiVersionConcurrencyControl;Ljava/util/NavigableMap;)V
     288: aload_2
     289: invokevirtual #115                // Method org/apache/hadoop/hbase/regionserver/wal/AbstractFSWAL.rollWriter:()[[B
     292: pop
     293: aload_2
     294: invokevirtual #116                // Method org/apache/hadoop/hbase/regionserver/wal/AbstractFSWAL.getNumRolledLogFiles:()I
     297: iconst_2
     298: if_icmpne     305
     301: iconst_1
     302: goto          306
     305: iconst_0
     306: invokestatic  #83                 // Method org/junit/Assert.assertTrue:(Z)V
     309: aload_2
     310: invokevirtual #117                // Method org/apache/hadoop/hbase/regionserver/wal/AbstractFSWAL.findRegionsToForceFlush:()[[B
     313: astore        10
     315: lconst_1
     316: aload         10
     318: arraylength
     319: i2l
     320: invokestatic  #118                // Method org/junit/Assert.assertEquals:(JJ)V
     323: aload         5
     325: invokeinterface #57,  1           // InterfaceMethod org/apache/hadoop/hbase/client/RegionInfo.getEncodedNameAsBytes:()[B
     330: aload         10
     332: iconst_0
     333: aaload
     334: invokestatic  #119                // Method org/junit/Assert.assertEquals:(Ljava/lang/Object;Ljava/lang/Object;)V
     337: aload_0
     338: aload_2
     339: aload         6
     341: aload         4
     343: iconst_2
     344: aload         7
     346: aload         9
     348: invokevirtual #114                // Method addEdits:(Lorg/apache/hadoop/hbase/wal/WAL;Lorg/apache/hadoop/hbase/client/RegionInfo;Lorg/apache/hadoop/hbase/client/TableDescriptor;ILorg/apache/hadoop/hbase/regionserver/MultiVersionConcurrencyControl;Ljava/util/NavigableMap;)V
     351: aload_2
     352: invokevirtual #117                // Method org/apache/hadoop/hbase/regionserver/wal/AbstractFSWAL.findRegionsToForceFlush:()[[B
     355: astore        10
     357: lconst_1
     358: aload         10
     360: arraylength
     361: i2l
     362: invokestatic  #118                // Method org/junit/Assert.assertEquals:(JJ)V
     365: aload         5
     367: invokeinterface #57,  1           // InterfaceMethod org/apache/hadoop/hbase/client/RegionInfo.getEncodedNameAsBytes:()[B
     372: aload         10
     374: iconst_0
     375: aaload
     376: invokestatic  #119                // Method org/junit/Assert.assertEquals:(Ljava/lang/Object;Ljava/lang/Object;)V
     379: aload_0
     380: aload_2
     381: aload         5
     383: invokeinterface #57,  1           // InterfaceMethod org/apache/hadoop/hbase/client/RegionInfo.getEncodedNameAsBytes:()[B
     388: aload_3
     389: invokeinterface #107,  1          // InterfaceMethod org/apache/hadoop/hbase/client/TableDescriptor.getColumnFamilyNames:()Ljava/util/Set;
     394: invokevirtual #120                // Method flushRegion:(Lorg/apache/hadoop/hbase/wal/WAL;[BLjava/util/Set;)V
     397: aload_2
     398: invokevirtual #115                // Method org/apache/hadoop/hbase/regionserver/wal/AbstractFSWAL.rollWriter:()[[B
     401: pop
     402: lconst_1
     403: aload_2
     404: invokevirtual #116                // Method org/apache/hadoop/hbase/regionserver/wal/AbstractFSWAL.getNumRolledLogFiles:()I
     407: i2l
     408: invokestatic  #118                // Method org/junit/Assert.assertEquals:(JJ)V
     411: aload_0
     412: aload_2
     413: aload         6
     415: invokeinterface #57,  1           // InterfaceMethod org/apache/hadoop/hbase/client/RegionInfo.getEncodedNameAsBytes:()[B
     420: aload         4
     422: invokeinterface #107,  1          // InterfaceMethod org/apache/hadoop/hbase/client/TableDescriptor.getColumnFamilyNames:()Ljava/util/Set;
     427: invokevirtual #120                // Method flushRegion:(Lorg/apache/hadoop/hbase/wal/WAL;[BLjava/util/Set;)V
     430: aload_2
     431: iconst_1
     432: invokevirtual #121                // Method org/apache/hadoop/hbase/regionserver/wal/AbstractFSWAL.rollWriter:(Z)[[B
     435: pop
     436: lconst_0
     437: aload_2
     438: invokevirtual #116                // Method org/apache/hadoop/hbase/regionserver/wal/AbstractFSWAL.getNumRolledLogFiles:()I
     441: i2l
     442: invokestatic  #118                // Method org/junit/Assert.assertEquals:(JJ)V
     445: aload_0
     446: aload_2
     447: aload         5
     449: aload_3
     450: iconst_2
     451: aload         7
     453: aload         8
     455: invokevirtual #114                // Method addEdits:(Lorg/apache/hadoop/hbase/wal/WAL;Lorg/apache/hadoop/hbase/client/RegionInfo;Lorg/apache/hadoop/hbase/client/TableDescriptor;ILorg/apache/hadoop/hbase/regionserver/MultiVersionConcurrencyControl;Ljava/util/NavigableMap;)V
     458: aload_0
     459: aload_2
     460: aload         6
     462: aload         4
     464: iconst_2
     465: aload         7
     467: aload         9
     469: invokevirtual #114                // Method addEdits:(Lorg/apache/hadoop/hbase/wal/WAL;Lorg/apache/hadoop/hbase/client/RegionInfo;Lorg/apache/hadoop/hbase/client/TableDescriptor;ILorg/apache/hadoop/hbase/regionserver/MultiVersionConcurrencyControl;Ljava/util/NavigableMap;)V
     472: aload_2
     473: invokevirtual #115                // Method org/apache/hadoop/hbase/regionserver/wal/AbstractFSWAL.rollWriter:()[[B
     476: pop
     477: lconst_1
     478: aload_2
     479: invokevirtual #116                // Method org/apache/hadoop/hbase/regionserver/wal/AbstractFSWAL.getNumRolledLogFiles:()I
     482: i2l
     483: invokestatic  #118                // Method org/junit/Assert.assertEquals:(JJ)V
     486: aload_0
     487: aload_2
     488: aload         5
     490: aload_3
     491: iconst_2
     492: aload         7
     494: aload         8
     496: invokevirtual #114                // Method addEdits:(Lorg/apache/hadoop/hbase/wal/WAL;Lorg/apache/hadoop/hbase/client/RegionInfo;Lorg/apache/hadoop/hbase/client/TableDescriptor;ILorg/apache/hadoop/hbase/regionserver/MultiVersionConcurrencyControl;Ljava/util/NavigableMap;)V
     499: aload_2
     500: invokevirtual #115                // Method org/apache/hadoop/hbase/regionserver/wal/AbstractFSWAL.rollWriter:()[[B
     503: pop
     504: aload_2
     505: invokevirtual #117                // Method org/apache/hadoop/hbase/regionserver/wal/AbstractFSWAL.findRegionsToForceFlush:()[[B
     508: astore        10
     510: ldc2_w        #122                // long 2l
     513: aload         10
     515: arraylength
     516: i2l
     517: invokestatic  #118                // Method org/junit/Assert.assertEquals:(JJ)V
     520: aload_0
     521: aload_2
     522: aload         5
     524: invokeinterface #57,  1           // InterfaceMethod org/apache/hadoop/hbase/client/RegionInfo.getEncodedNameAsBytes:()[B
     529: aload_3
     530: invokeinterface #107,  1          // InterfaceMethod org/apache/hadoop/hbase/client/TableDescriptor.getColumnFamilyNames:()Ljava/util/Set;
     535: invokevirtual #120                // Method flushRegion:(Lorg/apache/hadoop/hbase/wal/WAL;[BLjava/util/Set;)V
     538: aload_0
     539: aload_2
     540: aload         6
     542: invokeinterface #57,  1           // InterfaceMethod org/apache/hadoop/hbase/client/RegionInfo.getEncodedNameAsBytes:()[B
     547: aload         4
     549: invokeinterface #107,  1          // InterfaceMethod org/apache/hadoop/hbase/client/TableDescriptor.getColumnFamilyNames:()Ljava/util/Set;
     554: invokevirtual #120                // Method flushRegion:(Lorg/apache/hadoop/hbase/wal/WAL;[BLjava/util/Set;)V
     557: aload_2
     558: iconst_1
     559: invokevirtual #121                // Method org/apache/hadoop/hbase/regionserver/wal/AbstractFSWAL.rollWriter:(Z)[[B
     562: pop
     563: lconst_0
     564: aload_2
     565: invokevirtual #116                // Method org/apache/hadoop/hbase/regionserver/wal/AbstractFSWAL.getNumRolledLogFiles:()I
     568: i2l
     569: invokestatic  #118                // Method org/junit/Assert.assertEquals:(JJ)V
     572: aload_0
     573: aload_2
     574: aload         5
     576: aload_3
     577: iconst_2
     578: aload         7
     580: aload         8
     582: invokevirtual #114                // Method addEdits:(Lorg/apache/hadoop/hbase/wal/WAL;Lorg/apache/hadoop/hbase/client/RegionInfo;Lorg/apache/hadoop/hbase/client/TableDescriptor;ILorg/apache/hadoop/hbase/regionserver/MultiVersionConcurrencyControl;Ljava/util/NavigableMap;)V
     585: aload_2
     586: aload         5
     588: invokeinterface #57,  1           // InterfaceMethod org/apache/hadoop/hbase/client/RegionInfo.getEncodedNameAsBytes:()[B
     593: aload_3
     594: invokeinterface #107,  1          // InterfaceMethod org/apache/hadoop/hbase/client/TableDescriptor.getColumnFamilyNames:()Ljava/util/Set;
     599: invokevirtual #124                // Method org/apache/hadoop/hbase/regionserver/wal/AbstractFSWAL.startCacheFlush:([BLjava/util/Set;)Ljava/lang/Long;
     602: pop
     603: aload_2
     604: invokevirtual #115                // Method org/apache/hadoop/hbase/regionserver/wal/AbstractFSWAL.rollWriter:()[[B
     607: pop
     608: aload_2
     609: aload         5
     611: invokeinterface #57,  1           // InterfaceMethod org/apache/hadoop/hbase/client/RegionInfo.getEncodedNameAsBytes:()[B
     616: invokevirtual #125                // Method org/apache/hadoop/hbase/regionserver/wal/AbstractFSWAL.completeCacheFlush:([B)V
     619: lconst_1
     620: aload_2
     621: invokevirtual #116                // Method org/apache/hadoop/hbase/regionserver/wal/AbstractFSWAL.getNumRolledLogFiles:()I
     624: i2l
     625: invokestatic  #118                // Method org/junit/Assert.assertEquals:(JJ)V
     628: aload_2
     629: ifnull        652
     632: aload_2
     633: invokevirtual #47                 // Method org/apache/hadoop/hbase/regionserver/wal/AbstractFSWAL.close:()V
     636: goto          652
     639: astore        12
     641: aload_2
     642: ifnull        649
     645: aload_2
     646: invokevirtual #47                 // Method org/apache/hadoop/hbase/regionserver/wal/AbstractFSWAL.close:()V
     649: aload         12
     651: athrow
     652: return
    Exception table:
       from    to  target type
         257   628   639   any
         639   641   639   any

  public void testFailedToCreateWALIfParentRenamed() throws java.io.IOException, org.apache.hadoop.hbase.util.CommonFSUtils$StreamLacksCapabilityException;
    Code:
       0: ldc           #126                // String testFailedToCreateWALIfParentRenamed
       2: astore_1
       3: aload_0
       4: getstatic     #5                  // Field FS:Lorg/apache/hadoop/fs/FileSystem;
       7: getstatic     #35                 // Field CONF:Lorg/apache/hadoop/conf/Configuration;
      10: invokestatic  #39                 // Method org/apache/hadoop/hbase/util/CommonFSUtils.getWALRootDir:(Lorg/apache/hadoop/conf/Configuration;)Lorg/apache/hadoop/fs/Path;
      13: ldc           #126                // String testFailedToCreateWALIfParentRenamed
      15: ldc           #42                 // String oldWALs
      17: getstatic     #35                 // Field CONF:Lorg/apache/hadoop/conf/Configuration;
      20: aconst_null
      21: iconst_1
      22: aconst_null
      23: aconst_null
      24: invokevirtual #43                 // Method newWAL:(Lorg/apache/hadoop/fs/FileSystem;Lorg/apache/hadoop/fs/Path;Ljava/lang/String;Ljava/lang/String;Lorg/apache/hadoop/conf/Configuration;Ljava/util/List;ZLjava/lang/String;Ljava/lang/String;)Lorg/apache/hadoop/hbase/regionserver/wal/AbstractFSWAL;
      27: astore_2
      28: invokestatic  #50                 // Method java/lang/System.currentTimeMillis:()J
      31: lstore_3
      32: aload_2
      33: lload_3
      34: invokevirtual #79                 // Method org/apache/hadoop/hbase/regionserver/wal/AbstractFSWAL.computeFilename:(J)Lorg/apache/hadoop/fs/Path;
      37: astore        5
      39: aload_2
      40: aload         5
      42: invokevirtual #127                // Method org/apache/hadoop/hbase/regionserver/wal/AbstractFSWAL.createWriterInstance:(Lorg/apache/hadoop/fs/Path;)Lorg/apache/hadoop/hbase/wal/WALProvider$WriterBase;
      45: pop
      46: aload         5
      48: invokevirtual #128                // Method org/apache/hadoop/fs/Path.getParent:()Lorg/apache/hadoop/fs/Path;
      51: astore        6
      53: aload_2
      54: lload_3
      55: lconst_1
      56: ladd
      57: invokevirtual #79                 // Method org/apache/hadoop/hbase/regionserver/wal/AbstractFSWAL.computeFilename:(J)Lorg/apache/hadoop/fs/Path;
      60: astore        5
      62: new           #6                  // class org/apache/hadoop/fs/Path
      65: dup
      66: aload         6
      68: invokevirtual #128                // Method org/apache/hadoop/fs/Path.getParent:()Lorg/apache/hadoop/fs/Path;
      71: new           #69                 // class java/lang/StringBuilder
      74: dup
      75: invokespecial #70                 // Method java/lang/StringBuilder."<init>":()V
      78: aload         6
      80: invokevirtual #129                // Method org/apache/hadoop/fs/Path.getName:()Ljava/lang/String;
      83: invokevirtual #72                 // Method java/lang/StringBuilder.append:(Ljava/lang/String;)Ljava/lang/StringBuilder;
      86: ldc           #130                // String -splitting
      88: invokevirtual #72                 // Method java/lang/StringBuilder.append:(Ljava/lang/String;)Ljava/lang/StringBuilder;
      91: invokevirtual #74                 // Method java/lang/StringBuilder.toString:()Ljava/lang/String;
      94: invokespecial #16                 // Method org/apache/hadoop/fs/Path."<init>":(Lorg/apache/hadoop/fs/Path;Ljava/lang/String;)V
      97: astore        7
      99: getstatic     #5                  // Field FS:Lorg/apache/hadoop/fs/FileSystem;
     102: aload         6
     104: aload         7
     106: invokevirtual #131                // Method org/apache/hadoop/fs/FileSystem.rename:(Lorg/apache/hadoop/fs/Path;Lorg/apache/hadoop/fs/Path;)Z
     109: pop
     110: aload_2
     111: aload         5
     113: invokevirtual #127                // Method org/apache/hadoop/hbase/regionserver/wal/AbstractFSWAL.createWriterInstance:(Lorg/apache/hadoop/fs/Path;)Lorg/apache/hadoop/hbase/wal/WALProvider$WriterBase;
     116: pop
     117: ldc           #132                // String It should fail to create the new WAL
     119: invokestatic  #133                // Method org/junit/Assert.fail:(Ljava/lang/String;)V
     122: return

  public void testFlushSequenceIdIsGreaterThanAllEditsInHFile() throws java.io.IOException;
    Code:
       0: aload_0
       1: getfield      #4                  // Field currentTest:Lorg/junit/rules/TestName;
       4: invokevirtual #15                 // Method org/junit/rules/TestName.getMethodName:()Ljava/lang/String;
       7: astore_1
       8: aload_1
       9: invokestatic  #94                 // Method org/apache/hadoop/hbase/TableName.valueOf:(Ljava/lang/String;)Lorg/apache/hadoop/hbase/TableName;
      12: astore_2
      13: aload_2
      14: invokestatic  #100                // Method org/apache/hadoop/hbase/client/RegionInfoBuilder.newBuilder:(Lorg/apache/hadoop/hbase/TableName;)Lorg/apache/hadoop/hbase/client/RegionInfoBuilder;
      17: invokevirtual #101                // Method org/apache/hadoop/hbase/client/RegionInfoBuilder.build:()Lorg/apache/hadoop/hbase/client/RegionInfo;
      20: astore_3
      21: aload_2
      22: invokevirtual #134                // Method org/apache/hadoop/hbase/TableName.getName:()[B
      25: astore        4
      27: aload_2
      28: invokestatic  #95                 // Method org/apache/hadoop/hbase/client/TableDescriptorBuilder.newBuilder:(Lorg/apache/hadoop/hbase/TableName;)Lorg/apache/hadoop/hbase/client/TableDescriptorBuilder;
      31: ldc           #135                // String f
      33: invokestatic  #96                 // Method org/apache/hadoop/hbase/client/ColumnFamilyDescriptorBuilder.of:(Ljava/lang/String;)Lorg/apache/hadoop/hbase/client/ColumnFamilyDescriptor;
      36: invokevirtual #97                 // Method org/apache/hadoop/hbase/client/TableDescriptorBuilder.setColumnFamily:(Lorg/apache/hadoop/hbase/client/ColumnFamilyDescriptor;)Lorg/apache/hadoop/hbase/client/TableDescriptorBuilder;
      39: invokevirtual #98                 // Method org/apache/hadoop/hbase/client/TableDescriptorBuilder.build:()Lorg/apache/hadoop/hbase/client/TableDescriptor;
      42: astore        5
      44: aload_3
      45: getstatic     #12                 // Field TEST_UTIL:Lorg/apache/hadoop/hbase/HBaseTestingUtility;
      48: invokevirtual #136                // Method org/apache/hadoop/hbase/HBaseTestingUtility.getDefaultRootDirPath:()Lorg/apache/hadoop/fs/Path;
      51: getstatic     #12                 // Field TEST_UTIL:Lorg/apache/hadoop/hbase/HBaseTestingUtility;
      54: invokevirtual #19                 // Method org/apache/hadoop/hbase/HBaseTestingUtility.getConfiguration:()Lorg/apache/hadoop/conf/Configuration;
      57: aload         5
      59: invokestatic  #137                // Method org/apache/hadoop/hbase/HBaseTestingUtility.createRegionAndWAL:(Lorg/apache/hadoop/hbase/client/RegionInfo;Lorg/apache/hadoop/fs/Path;Lorg/apache/hadoop/conf/Configuration;Lorg/apache/hadoop/hbase/client/TableDescriptor;)Lorg/apache/hadoop/hbase/regionserver/HRegion;
      62: astore        6
      64: aload         6
      66: invokestatic  #138                // Method org/apache/hadoop/hbase/HBaseTestingUtility.closeRegionAndWAL:(Lorg/apache/hadoop/hbase/regionserver/HRegion;)V
      69: bipush        10
      71: istore        7
      73: new           #139                // class java/util/concurrent/atomic/AtomicBoolean
      76: dup
      77: iconst_0
      78: invokespecial #140                // Method java/util/concurrent/atomic/AtomicBoolean."<init>":(Z)V
      81: astore        8
      83: new           #104                // class java/util/TreeMap
      86: dup
      87: getstatic     #105                // Field org/apache/hadoop/hbase/util/Bytes.BYTES_COMPARATOR:Ljava/util/Comparator;
      90: invokespecial #106                // Method java/util/TreeMap."<init>":(Ljava/util/Comparator;)V
      93: astore        9
      95: aload         5
      97: invokeinterface #107,  1          // InterfaceMethod org/apache/hadoop/hbase/client/TableDescriptor.getColumnFamilyNames:()Ljava/util/Set;
     102: invokeinterface #108,  1          // InterfaceMethod java/util/Set.iterator:()Ljava/util/Iterator;
     107: astore        10
     109: aload         10
     111: invokeinterface #109,  1          // InterfaceMethod java/util/Iterator.hasNext:()Z
     116: ifeq          148
     119: aload         10
     121: invokeinterface #110,  1          // InterfaceMethod java/util/Iterator.next:()Ljava/lang/Object;
     126: checkcast     #111                // class "[B"
     129: astore        11
     131: aload         9
     133: aload         11
     135: iconst_0
     136: invokestatic  #112                // Method java/lang/Integer.valueOf:(I)Ljava/lang/Integer;
     139: invokeinterface #113,  3          // InterfaceMethod java/util/NavigableMap.put:(Ljava/lang/Object;Ljava/lang/Object;)Ljava/lang/Object;
     144: pop
     145: goto          109
     148: aload_0
     149: getstatic     #5                  // Field FS:Lorg/apache/hadoop/fs/FileSystem;
     152: getstatic     #35                 // Field CONF:Lorg/apache/hadoop/conf/Configuration;
     155: invokestatic  #39                 // Method org/apache/hadoop/hbase/util/CommonFSUtils.getWALRootDir:(Lorg/apache/hadoop/conf/Configuration;)Lorg/apache/hadoop/fs/Path;
     158: getstatic     #17                 // Field DIR:Lorg/apache/hadoop/fs/Path;
     161: invokevirtual #40                 // Method org/apache/hadoop/fs/Path.toString:()Ljava/lang/String;
     164: aload_1
     165: getstatic     #35                 // Field CONF:Lorg/apache/hadoop/conf/Configuration;
     168: aconst_null
     169: iconst_1
     170: aconst_null
     171: aconst_null
     172: new           #141                // class org/apache/hadoop/hbase/regionserver/wal/AbstractTestFSWAL$1
     175: dup
     176: aload_0
     177: aload         8
     179: invokespecial #142                // Method org/apache/hadoop/hbase/regionserver/wal/AbstractTestFSWAL$1."<init>":(Lorg/apache/hadoop/hbase/regionserver/wal/AbstractTestFSWAL;Ljava/util/concurrent/atomic/AtomicBoolean;)V
     182: invokevirtual #143                // Method newSlowWAL:(Lorg/apache/hadoop/fs/FileSystem;Lorg/apache/hadoop/fs/Path;Ljava/lang/String;Ljava/lang/String;Lorg/apache/hadoop/conf/Configuration;Ljava/util/List;ZLjava/lang/String;Ljava/lang/String;Ljava/lang/Runnable;)Lorg/apache/hadoop/hbase/regionserver/wal/AbstractFSWAL;
     185: astore        10
     187: getstatic     #12                 // Field TEST_UTIL:Lorg/apache/hadoop/hbase/HBaseTestingUtility;
     190: invokevirtual #19                 // Method org/apache/hadoop/hbase/HBaseTestingUtility.getConfiguration:()Lorg/apache/hadoop/conf/Configuration;
     193: getstatic     #12                 // Field TEST_UTIL:Lorg/apache/hadoop/hbase/HBaseTestingUtility;
     196: invokevirtual #144                // Method org/apache/hadoop/hbase/HBaseTestingUtility.getTestFileSystem:()Lorg/apache/hadoop/fs/FileSystem;
     199: getstatic     #12                 // Field TEST_UTIL:Lorg/apache/hadoop/hbase/HBaseTestingUtility;
     202: invokevirtual #136                // Method org/apache/hadoop/hbase/HBaseTestingUtility.getDefaultRootDirPath:()Lorg/apache/hadoop/fs/Path;
     205: aload_3
     206: aload         5
     208: aload         10
     210: invokestatic  #145                // Method org/apache/hadoop/hbase/regionserver/HRegion.openHRegion:(Lorg/apache/hadoop/conf/Configuration;Lorg/apache/hadoop/fs/FileSystem;Lorg/apache/hadoop/fs/Path;Lorg/apache/hadoop/hbase/client/RegionInfo;Lorg/apache/hadoop/hbase/client/TableDescriptor;Lorg/apache/hadoop/hbase/wal/WAL;)Lorg/apache/hadoop/hbase/regionserver/HRegion;
     213: astore        11
     215: invokestatic  #146                // Method org/apache/hadoop/hbase/util/EnvironmentEdgeManager.getDelegate:()Lorg/apache/hadoop/hbase/util/EnvironmentEdge;
     218: astore        12
     220: aconst_null
     221: astore        13
     223: aload         5
     225: invokeinterface #107,  1          // InterfaceMethod org/apache/hadoop/hbase/client/TableDescriptor.getColumnFamilyNames:()Ljava/util/Set;
     230: invokeinterface #108,  1          // InterfaceMethod java/util/Set.iterator:()Ljava/util/Iterator;
     235: astore        14
     237: aload         14
     239: invokeinterface #109,  1          // InterfaceMethod java/util/Iterator.hasNext:()Z
     244: ifeq          279
     247: aload         14
     249: invokeinterface #110,  1          // InterfaceMethod java/util/Iterator.next:()Ljava/lang/Object;
     254: checkcast     #111                // class "[B"
     257: astore        15
     259: aload         4
     261: aload         15
     263: bipush        10
     265: aload         12
     267: aload         11
     269: ldc           #147                // String x
     271: invokestatic  #148                // Method org/apache/hadoop/hbase/regionserver/wal/TestWALReplay.addRegionEdits:([B[BILorg/apache/hadoop/hbase/util/EnvironmentEdge;Lorg/apache/hadoop/hbase/regionserver/Region;Ljava/lang/String;)Ljava/util/List;
     274: astore        13
     276: goto          237
     279: new           #149                // class org/apache/hadoop/hbase/client/Get
     282: dup
     283: aload         4
     285: invokespecial #150                // Method org/apache/hadoop/hbase/client/Get."<init>":([B)V
     288: astore        14
     290: aload         11
     292: aload         14
     294: invokevirtual #151                // Method org/apache/hadoop/hbase/regionserver/HRegion.get:(Lorg/apache/hadoop/hbase/client/Get;)Lorg/apache/hadoop/hbase/client/Result;
     297: astore        15
     299: bipush        10
     301: aload         5
     303: invokeinterface #107,  1          // InterfaceMethod org/apache/hadoop/hbase/client/TableDescriptor.getColumnFamilyNames:()Ljava/util/Set;
     308: invokeinterface #152,  1          // InterfaceMethod java/util/Set.size:()I
     313: imul
     314: i2l
     315: aload         15
     317: invokevirtual #153                // Method org/apache/hadoop/hbase/client/Result.size:()I
     320: i2l
     321: invokestatic  #118                // Method org/junit/Assert.assertEquals:(JJ)V
     324: new           #51                 // class org/apache/hadoop/hbase/wal/WALEdit
     327: dup
     328: invokespecial #52                 // Method org/apache/hadoop/hbase/wal/WALEdit."<init>":()V
     331: astore        16
     333: aload         13
     335: invokeinterface #154,  1          // InterfaceMethod java/util/List.iterator:()Ljava/util/Iterator;
     340: astore        17
     342: aload         17
     344: invokeinterface #109,  1          // InterfaceMethod java/util/Iterator.hasNext:()Z
     349: ifeq          400
     352: aload         17
     354: invokeinterface #110,  1          // InterfaceMethod java/util/Iterator.next:()Ljava/lang/Object;
     359: checkcast     #155                // class org/apache/hadoop/hbase/client/Put
     362: astore        18
     364: aload         18
     366: invokevirtual #156                // Method org/apache/hadoop/hbase/client/Put.cellScanner:()Lorg/apache/hadoop/hbase/CellScanner;
     369: astore        19
     371: aload         19
     373: invokeinterface #157,  1          // InterfaceMethod org/apache/hadoop/hbase/CellScanner.advance:()Z
     378: ifeq          397
     381: aload         16
     383: aload         19
     385: invokeinterface #158,  1          // InterfaceMethod org/apache/hadoop/hbase/CellScanner.current:()Lorg/apache/hadoop/hbase/Cell;
     390: invokevirtual #55                 // Method org/apache/hadoop/hbase/wal/WALEdit.add:(Lorg/apache/hadoop/hbase/Cell;)Lorg/apache/hadoop/hbase/wal/WALEdit;
     393: pop
     394: goto          371
     397: goto          342
     400: new           #159                // class java/util/ArrayList
     403: dup
     404: iconst_1
     405: invokespecial #160                // Method java/util/ArrayList."<init>":(I)V
     408: astore        17
     410: aload         17
     412: getstatic     #12                 // Field TEST_UTIL:Lorg/apache/hadoop/hbase/HBaseTestingUtility;
     415: invokevirtual #161                // Method org/apache/hadoop/hbase/HBaseTestingUtility.getRandomUUID:()Ljava/util/UUID;
     418: invokeinterface #162,  2          // InterfaceMethod java/util/List.add:(Ljava/lang/Object;)Z
     423: pop
     424: aload         8
     426: iconst_1
     427: invokevirtual #163                // Method java/util/concurrent/atomic/AtomicBoolean.set:(Z)V
     430: iconst_0
     431: istore        18
     433: iload         18
     435: bipush        10
     437: if_icmpge     514
     440: aload         11
     442: invokevirtual #164                // Method org/apache/hadoop/hbase/regionserver/HRegion.getRegionInfo:()Lorg/apache/hadoop/hbase/client/RegionInfo;
     445: astore        19
     447: new           #56                 // class org/apache/hadoop/hbase/wal/WALKeyImpl
     450: dup
     451: aload         19
     453: invokeinterface #57,  1           // InterfaceMethod org/apache/hadoop/hbase/client/RegionInfo.getEncodedNameAsBytes:()[B
     458: aload_2
     459: invokestatic  #50                 // Method java/lang/System.currentTimeMillis:()J
     462: aload         17
     464: ldc2_w        #60                 // long -1l
     467: ldc2_w        #60                 // long -1l
     470: aload         11
     472: invokevirtual #165                // Method org/apache/hadoop/hbase/regionserver/HRegion.getMVCC:()Lorg/apache/hadoop/hbase/regionserver/MultiVersionConcurrencyControl;
     475: aload         9
     477: invokespecial #166                // Method org/apache/hadoop/hbase/wal/WALKeyImpl."<init>":([BLorg/apache/hadoop/hbase/TableName;JLjava/util/List;JJLorg/apache/hadoop/hbase/regionserver/MultiVersionConcurrencyControl;Ljava/util/NavigableMap;)V
     480: astore        20
     482: aload         10
     484: aload         19
     486: aload         20
     488: aload         16
     490: iconst_1
     491: invokevirtual #167                // Method org/apache/hadoop/hbase/regionserver/wal/AbstractFSWAL.append:(Lorg/apache/hadoop/hbase/client/RegionInfo;Lorg/apache/hadoop/hbase/wal/WALKeyImpl;Lorg/apache/hadoop/hbase/wal/WALEdit;Z)J
     494: pop2
     495: aload         11
     497: invokevirtual #165                // Method org/apache/hadoop/hbase/regionserver/HRegion.getMVCC:()Lorg/apache/hadoop/hbase/regionserver/MultiVersionConcurrencyControl;
     500: aload         20
     502: invokevirtual #168                // Method org/apache/hadoop/hbase/wal/WALKeyImpl.getWriteEntry:()Lorg/apache/hadoop/hbase/regionserver/MultiVersionConcurrencyControl$WriteEntry;
     505: invokevirtual #169                // Method org/apache/hadoop/hbase/regionserver/MultiVersionConcurrencyControl.completeAndWait:(Lorg/apache/hadoop/hbase/regionserver/MultiVersionConcurrencyControl$WriteEntry;)V
     508: iinc          18, 1
     511: goto          433
     514: aload         11
     516: iconst_1
     517: invokevirtual #170                // Method org/apache/hadoop/hbase/regionserver/HRegion.flush:(Z)Lorg/apache/hadoop/hbase/regionserver/HRegion$FlushResult;
     520: pop
     521: aload         11
     523: aconst_null
     524: invokevirtual #171                // Method org/apache/hadoop/hbase/regionserver/HRegion.getReadPoint:(Lorg/apache/hadoop/hbase/client/IsolationLevel;)J
     527: lstore        18
     529: aload         8
     531: iconst_0
     532: invokevirtual #163                // Method java/util/concurrent/atomic/AtomicBoolean.set:(Z)V
     535: lload         18
     537: aload         11
     539: aconst_null
     540: invokevirtual #171                // Method org/apache/hadoop/hbase/regionserver/HRegion.getReadPoint:(Lorg/apache/hadoop/hbase/client/IsolationLevel;)J
     543: lcmp
     544: iflt          551
     547: iconst_1
     548: goto          552
     551: iconst_0
     552: invokestatic  #83                 // Method org/junit/Assert.assertTrue:(Z)V
     555: aload         11
     557: iconst_1
     558: invokevirtual #172                // Method org/apache/hadoop/hbase/regionserver/HRegion.close:(Z)Ljava/util/Map;
     561: pop
     562: aload         10
     564: invokevirtual #47                 // Method org/apache/hadoop/hbase/regionserver/wal/AbstractFSWAL.close:()V
     567: goto          587
     570: astore        21
     572: aload         11
     574: iconst_1
     575: invokevirtual #172                // Method org/apache/hadoop/hbase/regionserver/HRegion.close:(Z)Ljava/util/Map;
     578: pop
     579: aload         10
     581: invokevirtual #47                 // Method org/apache/hadoop/hbase/regionserver/wal/AbstractFSWAL.close:()V
     584: aload         21
     586: athrow
     587: return
    Exception table:
       from    to  target type
         220   555   570   any
         570   572   570   any

  public void testSyncNoAppend() throws java.io.IOException;
    Code:
       0: aload_0
       1: getfield      #4                  // Field currentTest:Lorg/junit/rules/TestName;
       4: invokevirtual #15                 // Method org/junit/rules/TestName.getMethodName:()Ljava/lang/String;
       7: astore_1
       8: aload_0
       9: getstatic     #5                  // Field FS:Lorg/apache/hadoop/fs/FileSystem;
      12: getstatic     #35                 // Field CONF:Lorg/apache/hadoop/conf/Configuration;
      15: invokestatic  #39                 // Method org/apache/hadoop/hbase/util/CommonFSUtils.getWALRootDir:(Lorg/apache/hadoop/conf/Configuration;)Lorg/apache/hadoop/fs/Path;
      18: getstatic     #17                 // Field DIR:Lorg/apache/hadoop/fs/Path;
      21: invokevirtual #40                 // Method org/apache/hadoop/fs/Path.toString:()Ljava/lang/String;
      24: aload_1
      25: getstatic     #35                 // Field CONF:Lorg/apache/hadoop/conf/Configuration;
      28: aconst_null
      29: iconst_1
      30: aconst_null
      31: aconst_null
      32: invokevirtual #43                 // Method newWAL:(Lorg/apache/hadoop/fs/FileSystem;Lorg/apache/hadoop/fs/Path;Ljava/lang/String;Ljava/lang/String;Lorg/apache/hadoop/conf/Configuration;Ljava/util/List;ZLjava/lang/String;Ljava/lang/String;)Lorg/apache/hadoop/hbase/regionserver/wal/AbstractFSWAL;
      35: astore_2
      36: aload_2
      37: invokevirtual #173                // Method org/apache/hadoop/hbase/regionserver/wal/AbstractFSWAL.sync:()V
      40: aload_2
      41: invokevirtual #47                 // Method org/apache/hadoop/hbase/regionserver/wal/AbstractFSWAL.close:()V
      44: goto          54
      47: astore_3
      48: aload_2
      49: invokevirtual #47                 // Method org/apache/hadoop/hbase/regionserver/wal/AbstractFSWAL.close:()V
      52: aload_3
      53: athrow
      54: return
    Exception table:
       from    to  target type
          36    40    47   any

  public void testWriteEntryCanBeNull() throws java.io.IOException;
    Code:
       0: aload_0
       1: getfield      #4                  // Field currentTest:Lorg/junit/rules/TestName;
       4: invokevirtual #15                 // Method org/junit/rules/TestName.getMethodName:()Ljava/lang/String;
       7: astore_1
       8: aload_0
       9: getstatic     #5                  // Field FS:Lorg/apache/hadoop/fs/FileSystem;
      12: getstatic     #35                 // Field CONF:Lorg/apache/hadoop/conf/Configuration;
      15: invokestatic  #39                 // Method org/apache/hadoop/hbase/util/CommonFSUtils.getWALRootDir:(Lorg/apache/hadoop/conf/Configuration;)Lorg/apache/hadoop/fs/Path;
      18: getstatic     #17                 // Field DIR:Lorg/apache/hadoop/fs/Path;
      21: invokevirtual #40                 // Method org/apache/hadoop/fs/Path.toString:()Ljava/lang/String;
      24: aload_1
      25: getstatic     #35                 // Field CONF:Lorg/apache/hadoop/conf/Configuration;
      28: aconst_null
      29: iconst_1
      30: aconst_null
      31: aconst_null
      32: invokevirtual #43                 // Method newWAL:(Lorg/apache/hadoop/fs/FileSystem;Lorg/apache/hadoop/fs/Path;Ljava/lang/String;Ljava/lang/String;Lorg/apache/hadoop/conf/Configuration;Ljava/util/List;ZLjava/lang/String;Ljava/lang/String;)Lorg/apache/hadoop/hbase/regionserver/wal/AbstractFSWAL;
      35: astore_2
      36: aload_2
      37: invokevirtual #47                 // Method org/apache/hadoop/hbase/regionserver/wal/AbstractFSWAL.close:()V
      40: ldc           #174                // String table
      42: invokestatic  #94                 // Method org/apache/hadoop/hbase/TableName.valueOf:(Ljava/lang/String;)Lorg/apache/hadoop/hbase/TableName;
      45: invokestatic  #95                 // Method org/apache/hadoop/hbase/client/TableDescriptorBuilder.newBuilder:(Lorg/apache/hadoop/hbase/TableName;)Lorg/apache/hadoop/hbase/client/TableDescriptorBuilder;
      48: ldc           #48                 // String row
      50: invokestatic  #96                 // Method org/apache/hadoop/hbase/client/ColumnFamilyDescriptorBuilder.of:(Ljava/lang/String;)Lorg/apache/hadoop/hbase/client/ColumnFamilyDescriptor;
      53: invokevirtual #97                 // Method org/apache/hadoop/hbase/client/TableDescriptorBuilder.setColumnFamily:(Lorg/apache/hadoop/hbase/client/ColumnFamilyDescriptor;)Lorg/apache/hadoop/hbase/client/TableDescriptorBuilder;
      56: invokevirtual #98                 // Method org/apache/hadoop/hbase/client/TableDescriptorBuilder.build:()Lorg/apache/hadoop/hbase/client/TableDescriptor;
      59: astore_3
      60: aload_3
      61: invokeinterface #58,  1           // InterfaceMethod org/apache/hadoop/hbase/client/TableDescriptor.getTableName:()Lorg/apache/hadoop/hbase/TableName;
      66: invokestatic  #100                // Method org/apache/hadoop/hbase/client/RegionInfoBuilder.newBuilder:(Lorg/apache/hadoop/hbase/TableName;)Lorg/apache/hadoop/hbase/client/RegionInfoBuilder;
      69: invokevirtual #101                // Method org/apache/hadoop/hbase/client/RegionInfoBuilder.build:()Lorg/apache/hadoop/hbase/client/RegionInfo;
      72: astore        4
      74: new           #102                // class org/apache/hadoop/hbase/regionserver/MultiVersionConcurrencyControl
      77: dup
      78: invokespecial #103                // Method org/apache/hadoop/hbase/regionserver/MultiVersionConcurrencyControl."<init>":()V
      81: astore        5
      83: new           #104                // class java/util/TreeMap
      86: dup
      87: getstatic     #105                // Field org/apache/hadoop/hbase/util/Bytes.BYTES_COMPARATOR:Ljava/util/Comparator;
      90: invokespecial #106                // Method java/util/TreeMap."<init>":(Ljava/util/Comparator;)V
      93: astore        6
      95: aload_3
      96: invokeinterface #107,  1          // InterfaceMethod org/apache/hadoop/hbase/client/TableDescriptor.getColumnFamilyNames:()Ljava/util/Set;
     101: invokeinterface #108,  1          // InterfaceMethod java/util/Set.iterator:()Ljava/util/Iterator;
     106: astore        7
     108: aload         7
     110: invokeinterface #109,  1          // InterfaceMethod java/util/Iterator.hasNext:()Z
     115: ifeq          147
     118: aload         7
     120: invokeinterface #110,  1          // InterfaceMethod java/util/Iterator.next:()Ljava/lang/Object;
     125: checkcast     #111                // class "[B"
     128: astore        8
     130: aload         6
     132: aload         8
     134: iconst_0
     135: invokestatic  #112                // Method java/lang/Integer.valueOf:(I)Ljava/lang/Integer;
     138: invokeinterface #113,  3          // InterfaceMethod java/util/NavigableMap.put:(Ljava/lang/Object;Ljava/lang/Object;)Ljava/lang/Object;
     143: pop
     144: goto          108
     147: invokestatic  #50                 // Method java/lang/System.currentTimeMillis:()J
     150: lstore        7
     152: ldc           #48                 // String row
     154: invokestatic  #49                 // Method org/apache/hadoop/hbase/util/Bytes.toBytes:(Ljava/lang/String;)[B
     157: astore        9
     159: new           #51                 // class org/apache/hadoop/hbase/wal/WALEdit
     162: dup
     163: invokespecial #52                 // Method org/apache/hadoop/hbase/wal/WALEdit."<init>":()V
     166: astore        10
     168: aload         10
     170: new           #53                 // class org/apache/hadoop/hbase/KeyValue
     173: dup
     174: aload         9
     176: aload         9
     178: aload         9
     180: lload         7
     182: aload         9
     184: invokespecial #54                 // Method org/apache/hadoop/hbase/KeyValue."<init>":([B[B[BJ[B)V
     187: invokevirtual #55                 // Method org/apache/hadoop/hbase/wal/WALEdit.add:(Lorg/apache/hadoop/hbase/Cell;)Lorg/apache/hadoop/hbase/wal/WALEdit;
     190: pop
     191: new           #56                 // class org/apache/hadoop/hbase/wal/WALKeyImpl
     194: dup
     195: aload         4
     197: invokeinterface #57,  1           // InterfaceMethod org/apache/hadoop/hbase/client/RegionInfo.getEncodedNameAsBytes:()[B
     202: aload_3
     203: invokeinterface #58,  1           // InterfaceMethod org/apache/hadoop/hbase/client/TableDescriptor.getTableName:()Lorg/apache/hadoop/hbase/TableName;
     208: ldc2_w        #60                 // long -1l
     211: lload         7
     213: getstatic     #62                 // Field org/apache/hadoop/hbase/wal/WALKey.EMPTY_UUIDS:Ljava/util/List;
     216: lconst_0
     217: lconst_0
     218: aload         5
     220: aload         6
     222: invokespecial #63                 // Method org/apache/hadoop/hbase/wal/WALKeyImpl."<init>":([BLorg/apache/hadoop/hbase/TableName;JJLjava/util/List;JJLorg/apache/hadoop/hbase/regionserver/MultiVersionConcurrencyControl;Ljava/util/NavigableMap;)V
     225: astore        11
     227: aload_2
     228: aload         4
     230: aload         11
     232: aload         10
     234: iconst_1
     235: invokevirtual #167                // Method org/apache/hadoop/hbase/regionserver/wal/AbstractFSWAL.append:(Lorg/apache/hadoop/hbase/client/RegionInfo;Lorg/apache/hadoop/hbase/wal/WALKeyImpl;Lorg/apache/hadoop/hbase/wal/WALEdit;Z)J
     238: pop2
     239: ldc           #175                // String Should fail since the wal has already been closed
     241: invokestatic  #133                // Method org/junit/Assert.fail:(Ljava/lang/String;)V
     244: goto          270
     247: astore        12
     249: aload         12
     251: invokevirtual #177                // Method java/io/IOException.getMessage:()Ljava/lang/String;
     254: ldc           #178                // String log is closed
     256: invokestatic  #179                // Method org/hamcrest/CoreMatchers.containsString:(Ljava/lang/String;)Lorg/hamcrest/Matcher;
     259: invokestatic  #180                // Method org/junit/Assert.assertThat:(Ljava/lang/Object;Lorg/hamcrest/Matcher;)V
     262: aload         11
     264: invokevirtual #168                // Method org/apache/hadoop/hbase/wal/WALKeyImpl.getWriteEntry:()Lorg/apache/hadoop/hbase/regionserver/MultiVersionConcurrencyControl$WriteEntry;
     267: invokestatic  #181                // Method org/junit/Assert.assertNull:(Ljava/lang/Object;)V
     270: return
    Exception table:
       from    to  target type
         227   244   247   Class java/io/IOException

  public void testRollWriterForClosedWAL() throws java.io.IOException;
    Code:
       0: aload_0
       1: getfield      #4                  // Field currentTest:Lorg/junit/rules/TestName;
       4: invokevirtual #15                 // Method org/junit/rules/TestName.getMethodName:()Ljava/lang/String;
       7: astore_1
       8: aload_0
       9: getstatic     #5                  // Field FS:Lorg/apache/hadoop/fs/FileSystem;
      12: getstatic     #35                 // Field CONF:Lorg/apache/hadoop/conf/Configuration;
      15: invokestatic  #39                 // Method org/apache/hadoop/hbase/util/CommonFSUtils.getWALRootDir:(Lorg/apache/hadoop/conf/Configuration;)Lorg/apache/hadoop/fs/Path;
      18: getstatic     #17                 // Field DIR:Lorg/apache/hadoop/fs/Path;
      21: invokevirtual #40                 // Method org/apache/hadoop/fs/Path.toString:()Ljava/lang/String;
      24: aload_1
      25: getstatic     #35                 // Field CONF:Lorg/apache/hadoop/conf/Configuration;
      28: aconst_null
      29: iconst_1
      30: aconst_null
      31: aconst_null
      32: invokevirtual #43                 // Method newWAL:(Lorg/apache/hadoop/fs/FileSystem;Lorg/apache/hadoop/fs/Path;Ljava/lang/String;Ljava/lang/String;Lorg/apache/hadoop/conf/Configuration;Ljava/util/List;ZLjava/lang/String;Ljava/lang/String;)Lorg/apache/hadoop/hbase/regionserver/wal/AbstractFSWAL;
      35: astore_2
      36: aload_2
      37: invokevirtual #47                 // Method org/apache/hadoop/hbase/regionserver/wal/AbstractFSWAL.close:()V
      40: aload_2
      41: invokevirtual #115                // Method org/apache/hadoop/hbase/regionserver/wal/AbstractFSWAL.rollWriter:()[[B
      44: pop
      45: return

  static {};
    Code:
       0: ldc           #182                // class org/apache/hadoop/hbase/regionserver/wal/AbstractTestFSWAL
       2: invokestatic  #183                // Method org/slf4j/LoggerFactory.getLogger:(Ljava/lang/Class;)Lorg/slf4j/Logger;
       5: putstatic     #68                 // Field LOG:Lorg/slf4j/Logger;
       8: new           #184                // class org/apache/hadoop/hbase/HBaseTestingUtility
      11: dup
      12: invokespecial #185                // Method org/apache/hadoop/hbase/HBaseTestingUtility."<init>":()V
      15: putstatic     #12                 // Field TEST_UTIL:Lorg/apache/hadoop/hbase/HBaseTestingUtility;
      18: return
}
