Compiled from "AbstractTestLogRollPeriod.java"
public abstract class org.apache.hadoop.hbase.regionserver.wal.AbstractTestLogRollPeriod {
  protected static final org.apache.hadoop.hbase.HBaseTestingUtility TEST_UTIL;

  public org.apache.hadoop.hbase.regionserver.wal.AbstractTestLogRollPeriod();
    Code:
       0: aload_0
       1: invokespecial #2                  // Method java/lang/Object."<init>":()V
       4: return

  public static void setUpBeforeClass() throws java.lang.Exception;
    Code:
       0: getstatic     #3                  // Field TEST_UTIL:Lorg/apache/hadoop/hbase/HBaseTestingUtility;
       3: invokevirtual #4                  // Method org/apache/hadoop/hbase/HBaseTestingUtility.getConfiguration:()Lorg/apache/hadoop/conf/Configuration;
       6: ldc           #5                  // String hbase.regionsever.info.port
       8: iconst_m1
       9: invokevirtual #6                  // Method org/apache/hadoop/conf/Configuration.setInt:(Ljava/lang/String;I)V
      12: getstatic     #3                  // Field TEST_UTIL:Lorg/apache/hadoop/hbase/HBaseTestingUtility;
      15: invokevirtual #4                  // Method org/apache/hadoop/hbase/HBaseTestingUtility.getConfiguration:()Lorg/apache/hadoop/conf/Configuration;
      18: ldc           #7                  // String hbase.regionserver.logroll.period
      20: ldc2_w        #9                  // long 4000l
      23: invokevirtual #11                 // Method org/apache/hadoop/conf/Configuration.setLong:(Ljava/lang/String;J)V
      26: getstatic     #3                  // Field TEST_UTIL:Lorg/apache/hadoop/hbase/HBaseTestingUtility;
      29: invokevirtual #12                 // Method org/apache/hadoop/hbase/HBaseTestingUtility.startMiniCluster:()Lorg/apache/hadoop/hbase/MiniHBaseCluster;
      32: pop
      33: return

  public static void tearDownAfterClass() throws java.lang.Exception;
    Code:
       0: getstatic     #3                  // Field TEST_UTIL:Lorg/apache/hadoop/hbase/HBaseTestingUtility;
       3: invokevirtual #13                 // Method org/apache/hadoop/hbase/HBaseTestingUtility.shutdownMiniCluster:()V
       6: return

  public void testNoEdits() throws java.lang.Exception;
    Code:
       0: ldc           #14                 // String TestLogRollPeriodNoEdits
       2: invokestatic  #15                 // Method org/apache/hadoop/hbase/TableName.valueOf:(Ljava/lang/String;)Lorg/apache/hadoop/hbase/TableName;
       5: astore_1
       6: getstatic     #3                  // Field TEST_UTIL:Lorg/apache/hadoop/hbase/HBaseTestingUtility;
       9: aload_1
      10: ldc           #16                 // String cf
      12: invokevirtual #17                 // Method org/apache/hadoop/hbase/HBaseTestingUtility.createTable:(Lorg/apache/hadoop/hbase/TableName;Ljava/lang/String;)Lorg/apache/hadoop/hbase/client/Table;
      15: pop
      16: getstatic     #3                  // Field TEST_UTIL:Lorg/apache/hadoop/hbase/HBaseTestingUtility;
      19: invokevirtual #18                 // Method org/apache/hadoop/hbase/HBaseTestingUtility.getConnection:()Lorg/apache/hadoop/hbase/client/Connection;
      22: aload_1
      23: invokeinterface #19,  2           // InterfaceMethod org/apache/hadoop/hbase/client/Connection.getTable:(Lorg/apache/hadoop/hbase/TableName;)Lorg/apache/hadoop/hbase/client/Table;
      28: astore_2
      29: getstatic     #3                  // Field TEST_UTIL:Lorg/apache/hadoop/hbase/HBaseTestingUtility;
      32: aload_1
      33: invokevirtual #20                 // Method org/apache/hadoop/hbase/HBaseTestingUtility.getRSForFirstRegionInTable:(Lorg/apache/hadoop/hbase/TableName;)Lorg/apache/hadoop/hbase/regionserver/HRegionServer;
      36: astore_3
      37: aload_3
      38: aconst_null
      39: invokevirtual #21                 // Method org/apache/hadoop/hbase/regionserver/HRegionServer.getWAL:(Lorg/apache/hadoop/hbase/client/RegionInfo;)Lorg/apache/hadoop/hbase/wal/WAL;
      42: astore        4
      44: aload_0
      45: aload         4
      47: iconst_5
      48: invokespecial #22                 // Method checkMinLogRolls:(Lorg/apache/hadoop/hbase/wal/WAL;I)V
      51: aload_2
      52: invokeinterface #23,  1           // InterfaceMethod org/apache/hadoop/hbase/client/Table.close:()V
      57: goto          71
      60: astore        5
      62: aload_2
      63: invokeinterface #23,  1           // InterfaceMethod org/apache/hadoop/hbase/client/Table.close:()V
      68: aload         5
      70: athrow
      71: getstatic     #3                  // Field TEST_UTIL:Lorg/apache/hadoop/hbase/HBaseTestingUtility;
      74: aload_1
      75: invokevirtual #24                 // Method org/apache/hadoop/hbase/HBaseTestingUtility.deleteTable:(Lorg/apache/hadoop/hbase/TableName;)V
      78: goto          93
      81: astore        6
      83: getstatic     #3                  // Field TEST_UTIL:Lorg/apache/hadoop/hbase/HBaseTestingUtility;
      86: aload_1
      87: invokevirtual #24                 // Method org/apache/hadoop/hbase/HBaseTestingUtility.deleteTable:(Lorg/apache/hadoop/hbase/TableName;)V
      90: aload         6
      92: athrow
      93: return
    Exception table:
       from    to  target type
          29    51    60   any
          60    62    60   any
          16    71    81   any
          81    83    81   any

  public void testWithEdits() throws java.lang.Exception;
    Code:
       0: ldc           #25                 // String TestLogRollPeriodWithEdits
       2: invokestatic  #15                 // Method org/apache/hadoop/hbase/TableName.valueOf:(Ljava/lang/String;)Lorg/apache/hadoop/hbase/TableName;
       5: astore_1
       6: ldc           #16                 // String cf
       8: astore_2
       9: getstatic     #3                  // Field TEST_UTIL:Lorg/apache/hadoop/hbase/HBaseTestingUtility;
      12: aload_1
      13: ldc           #16                 // String cf
      15: invokevirtual #17                 // Method org/apache/hadoop/hbase/HBaseTestingUtility.createTable:(Lorg/apache/hadoop/hbase/TableName;Ljava/lang/String;)Lorg/apache/hadoop/hbase/client/Table;
      18: pop
      19: getstatic     #3                  // Field TEST_UTIL:Lorg/apache/hadoop/hbase/HBaseTestingUtility;
      22: aload_1
      23: invokevirtual #20                 // Method org/apache/hadoop/hbase/HBaseTestingUtility.getRSForFirstRegionInTable:(Lorg/apache/hadoop/hbase/TableName;)Lorg/apache/hadoop/hbase/regionserver/HRegionServer;
      26: astore_3
      27: aload_3
      28: aconst_null
      29: invokevirtual #21                 // Method org/apache/hadoop/hbase/regionserver/HRegionServer.getWAL:(Lorg/apache/hadoop/hbase/client/RegionInfo;)Lorg/apache/hadoop/hbase/wal/WAL;
      32: astore        4
      34: getstatic     #3                  // Field TEST_UTIL:Lorg/apache/hadoop/hbase/HBaseTestingUtility;
      37: invokevirtual #18                 // Method org/apache/hadoop/hbase/HBaseTestingUtility.getConnection:()Lorg/apache/hadoop/hbase/client/Connection;
      40: aload_1
      41: invokeinterface #19,  2           // InterfaceMethod org/apache/hadoop/hbase/client/Connection.getTable:(Lorg/apache/hadoop/hbase/TableName;)Lorg/apache/hadoop/hbase/client/Table;
      46: astore        5
      48: new           #26                 // class org/apache/hadoop/hbase/regionserver/wal/AbstractTestLogRollPeriod$1
      51: dup
      52: aload_0
      53: ldc           #27                 // String writer
      55: aload         5
      57: invokespecial #28                 // Method org/apache/hadoop/hbase/regionserver/wal/AbstractTestLogRollPeriod$1."<init>":(Lorg/apache/hadoop/hbase/regionserver/wal/AbstractTestLogRollPeriod;Ljava/lang/String;Lorg/apache/hadoop/hbase/client/Table;)V
      60: astore        6
      62: aload         6
      64: invokevirtual #29                 // Method java/lang/Thread.start:()V
      67: aload_0
      68: aload         4
      70: iconst_5
      71: invokespecial #22                 // Method checkMinLogRolls:(Lorg/apache/hadoop/hbase/wal/WAL;I)V
      74: aload         6
      76: invokevirtual #30                 // Method java/lang/Thread.interrupt:()V
      79: aload         6
      81: invokevirtual #31                 // Method java/lang/Thread.join:()V
      84: aload         5
      86: invokeinterface #23,  1           // InterfaceMethod org/apache/hadoop/hbase/client/Table.close:()V
      91: goto          116
      94: astore        7
      96: aload         6
      98: invokevirtual #30                 // Method java/lang/Thread.interrupt:()V
     101: aload         6
     103: invokevirtual #31                 // Method java/lang/Thread.join:()V
     106: aload         5
     108: invokeinterface #23,  1           // InterfaceMethod org/apache/hadoop/hbase/client/Table.close:()V
     113: aload         7
     115: athrow
     116: getstatic     #3                  // Field TEST_UTIL:Lorg/apache/hadoop/hbase/HBaseTestingUtility;
     119: aload_1
     120: invokevirtual #24                 // Method org/apache/hadoop/hbase/HBaseTestingUtility.deleteTable:(Lorg/apache/hadoop/hbase/TableName;)V
     123: goto          138
     126: astore        8
     128: getstatic     #3                  // Field TEST_UTIL:Lorg/apache/hadoop/hbase/HBaseTestingUtility;
     131: aload_1
     132: invokevirtual #24                 // Method org/apache/hadoop/hbase/HBaseTestingUtility.deleteTable:(Lorg/apache/hadoop/hbase/TableName;)V
     135: aload         8
     137: athrow
     138: return
    Exception table:
       from    to  target type
          62    74    94   any
          94    96    94   any
          19   116   126   any
         126   128   126   any

  static org.slf4j.Logger access$000();
    Code:
       0: getstatic     #1                  // Field LOG:Lorg/slf4j/Logger;
       3: areturn

  static {};
    Code:
       0: ldc           #8                  // class org/apache/hadoop/hbase/regionserver/wal/AbstractTestLogRollPeriod
       2: invokestatic  #49                 // Method org/slf4j/LoggerFactory.getLogger:(Ljava/lang/Class;)Lorg/slf4j/Logger;
       5: putstatic     #1                  // Field LOG:Lorg/slf4j/Logger;
       8: new           #50                 // class org/apache/hadoop/hbase/HBaseTestingUtility
      11: dup
      12: invokespecial #51                 // Method org/apache/hadoop/hbase/HBaseTestingUtility."<init>":()V
      15: putstatic     #3                  // Field TEST_UTIL:Lorg/apache/hadoop/hbase/HBaseTestingUtility;
      18: return
}
