Compiled from "AbstractRpcClient.java"
class org.apache.hadoop.hbase.ipc.AbstractRpcClient$AbstractRpcChannel {
  protected final java.net.InetSocketAddress addr;

  protected final org.apache.hadoop.hbase.ipc.AbstractRpcClient<?> rpcClient;

  protected final org.apache.hadoop.hbase.security.User ticket;

  protected final int rpcTimeout;

  protected org.apache.hadoop.hbase.ipc.AbstractRpcClient$AbstractRpcChannel(org.apache.hadoop.hbase.ipc.AbstractRpcClient<?>, java.net.InetSocketAddress, org.apache.hadoop.hbase.security.User, int);
    Code:
       0: aload_0
       1: invokespecial #1                  // Method java/lang/Object."<init>":()V
       4: aload_0
       5: aload_2
       6: putfield      #2                  // Field addr:Ljava/net/InetSocketAddress;
       9: aload_0
      10: aload_1
      11: putfield      #3                  // Field rpcClient:Lorg/apache/hadoop/hbase/ipc/AbstractRpcClient;
      14: aload_0
      15: aload_3
      16: putfield      #4                  // Field ticket:Lorg/apache/hadoop/hbase/security/User;
      19: aload_0
      20: iload         4
      22: putfield      #5                  // Field rpcTimeout:I
      25: return

  protected org.apache.hadoop.hbase.ipc.HBaseRpcController configureRpcController(org.apache.hbase.thirdparty.com.google.protobuf.RpcController);
    Code:
       0: aload_1
       1: ifnull        38
       4: aload_1
       5: instanceof    #6                  // class org/apache/hadoop/hbase/ipc/HBaseRpcController
       8: ifeq          38
      11: aload_1
      12: checkcast     #6                  // class org/apache/hadoop/hbase/ipc/HBaseRpcController
      15: astore_2
      16: aload_2
      17: invokeinterface #7,  1            // InterfaceMethod org/apache/hadoop/hbase/ipc/HBaseRpcController.hasCallTimeout:()Z
      22: ifne          56
      25: aload_2
      26: aload_0
      27: getfield      #5                  // Field rpcTimeout:I
      30: invokeinterface #8,  2            // InterfaceMethod org/apache/hadoop/hbase/ipc/HBaseRpcController.setCallTimeout:(I)V
      35: goto          56
      38: new           #9                  // class org/apache/hadoop/hbase/ipc/HBaseRpcControllerImpl
      41: dup
      42: invokespecial #10                 // Method org/apache/hadoop/hbase/ipc/HBaseRpcControllerImpl."<init>":()V
      45: astore_2
      46: aload_2
      47: aload_0
      48: getfield      #5                  // Field rpcTimeout:I
      51: invokeinterface #8,  2            // InterfaceMethod org/apache/hadoop/hbase/ipc/HBaseRpcController.setCallTimeout:(I)V
      56: aload_2
      57: areturn
}
