Compiled from "AbstractTestAsyncTableScan.java"
public abstract class org.apache.hadoop.hbase.client.AbstractTestAsyncTableScan {
  protected static final org.apache.hadoop.hbase.HBaseTestingUtility TEST_UTIL;

  protected static org.apache.hadoop.hbase.TableName TABLE_NAME;

  protected static byte[] FAMILY;

  protected static byte[] CQ1;

  protected static byte[] CQ2;

  protected static int COUNT;

  protected static org.apache.hadoop.hbase.client.AsyncConnection ASYNC_CONN;

  public org.apache.hadoop.hbase.client.AbstractTestAsyncTableScan();
    Code:
       0: aload_0
       1: invokespecial #1                  // Method java/lang/Object."<init>":()V
       4: return

  public static void setUp() throws java.lang.Exception;
    Code:
       0: getstatic     #2                  // Field TEST_UTIL:Lorg/apache/hadoop/hbase/HBaseTestingUtility;
       3: iconst_3
       4: invokevirtual #3                  // Method org/apache/hadoop/hbase/HBaseTestingUtility.startMiniCluster:(I)Lorg/apache/hadoop/hbase/MiniHBaseCluster;
       7: pop
       8: bipush        8
      10: anewarray     #4                  // class "[B"
      13: astore_0
      14: bipush        111
      16: istore_1
      17: iload_1
      18: sipush        999
      21: if_icmpge     57
      24: aload_0
      25: iload_1
      26: bipush        111
      28: idiv
      29: iconst_1
      30: isub
      31: ldc           #5                  // String %03d
      33: iconst_1
      34: anewarray     #6                  // class java/lang/Object
      37: dup
      38: iconst_0
      39: iload_1
      40: invokestatic  #7                  // Method java/lang/Integer.valueOf:(I)Ljava/lang/Integer;
      43: aastore
      44: invokestatic  #8                  // Method java/lang/String.format:(Ljava/lang/String;[Ljava/lang/Object;)Ljava/lang/String;
      47: invokestatic  #9                  // Method org/apache/hadoop/hbase/util/Bytes.toBytes:(Ljava/lang/String;)[B
      50: aastore
      51: iinc          1, 111
      54: goto          17
      57: getstatic     #2                  // Field TEST_UTIL:Lorg/apache/hadoop/hbase/HBaseTestingUtility;
      60: getstatic     #10                 // Field TABLE_NAME:Lorg/apache/hadoop/hbase/TableName;
      63: getstatic     #11                 // Field FAMILY:[B
      66: aload_0
      67: invokevirtual #12                 // Method org/apache/hadoop/hbase/HBaseTestingUtility.createTable:(Lorg/apache/hadoop/hbase/TableName;[B[[B)Lorg/apache/hadoop/hbase/client/Table;
      70: pop
      71: getstatic     #2                  // Field TEST_UTIL:Lorg/apache/hadoop/hbase/HBaseTestingUtility;
      74: getstatic     #10                 // Field TABLE_NAME:Lorg/apache/hadoop/hbase/TableName;
      77: invokevirtual #13                 // Method org/apache/hadoop/hbase/HBaseTestingUtility.waitTableAvailable:(Lorg/apache/hadoop/hbase/TableName;)V
      80: getstatic     #2                  // Field TEST_UTIL:Lorg/apache/hadoop/hbase/HBaseTestingUtility;
      83: invokevirtual #14                 // Method org/apache/hadoop/hbase/HBaseTestingUtility.getConfiguration:()Lorg/apache/hadoop/conf/Configuration;
      86: invokestatic  #15                 // Method org/apache/hadoop/hbase/client/ConnectionFactory.createAsyncConnection:(Lorg/apache/hadoop/conf/Configuration;)Ljava/util/concurrent/CompletableFuture;
      89: invokevirtual #16                 // Method java/util/concurrent/CompletableFuture.get:()Ljava/lang/Object;
      92: checkcast     #17                 // class org/apache/hadoop/hbase/client/AsyncConnection
      95: putstatic     #18                 // Field ASYNC_CONN:Lorg/apache/hadoop/hbase/client/AsyncConnection;
      98: getstatic     #18                 // Field ASYNC_CONN:Lorg/apache/hadoop/hbase/client/AsyncConnection;
     101: getstatic     #10                 // Field TABLE_NAME:Lorg/apache/hadoop/hbase/TableName;
     104: invokeinterface #19,  2           // InterfaceMethod org/apache/hadoop/hbase/client/AsyncConnection.getTable:(Lorg/apache/hadoop/hbase/TableName;)Lorg/apache/hadoop/hbase/client/AsyncTable;
     109: iconst_0
     110: getstatic     #20                 // Field COUNT:I
     113: invokestatic  #21                 // InterfaceMethod java/util/stream/IntStream.range:(II)Ljava/util/stream/IntStream;
     116: invokedynamic #22,  0             // InvokeDynamic #0:apply:()Ljava/util/function/IntFunction;
     121: invokeinterface #23,  2           // InterfaceMethod java/util/stream/IntStream.mapToObj:(Ljava/util/function/IntFunction;)Ljava/util/stream/Stream;
     126: invokestatic  #24                 // Method java/util/stream/Collectors.toList:()Ljava/util/stream/Collector;
     129: invokeinterface #25,  2           // InterfaceMethod java/util/stream/Stream.collect:(Ljava/util/stream/Collector;)Ljava/lang/Object;
     134: checkcast     #26                 // class java/util/List
     137: invokeinterface #27,  2           // InterfaceMethod org/apache/hadoop/hbase/client/AsyncTable.putAll:(Ljava/util/List;)Ljava/util/concurrent/CompletableFuture;
     142: invokevirtual #16                 // Method java/util/concurrent/CompletableFuture.get:()Ljava/lang/Object;
     145: pop
     146: return

  public static void tearDown() throws java.lang.Exception;
    Code:
       0: getstatic     #18                 // Field ASYNC_CONN:Lorg/apache/hadoop/hbase/client/AsyncConnection;
       3: invokeinterface #28,  1           // InterfaceMethod org/apache/hadoop/hbase/client/AsyncConnection.close:()V
       8: getstatic     #2                  // Field TEST_UTIL:Lorg/apache/hadoop/hbase/HBaseTestingUtility;
      11: invokevirtual #29                 // Method org/apache/hadoop/hbase/HBaseTestingUtility.shutdownMiniCluster:()V
      14: return

  protected static org.apache.hadoop.hbase.client.Scan createNormalScan();
    Code:
       0: new           #30                 // class org/apache/hadoop/hbase/client/Scan
       3: dup
       4: invokespecial #31                 // Method org/apache/hadoop/hbase/client/Scan."<init>":()V
       7: areturn

  protected static org.apache.hadoop.hbase.client.Scan createBatchScan();
    Code:
       0: new           #30                 // class org/apache/hadoop/hbase/client/Scan
       3: dup
       4: invokespecial #31                 // Method org/apache/hadoop/hbase/client/Scan."<init>":()V
       7: iconst_1
       8: invokevirtual #32                 // Method org/apache/hadoop/hbase/client/Scan.setBatch:(I)Lorg/apache/hadoop/hbase/client/Scan;
      11: areturn

  protected static org.apache.hadoop.hbase.client.Scan createSmallResultSizeScan();
    Code:
       0: new           #30                 // class org/apache/hadoop/hbase/client/Scan
       3: dup
       4: invokespecial #31                 // Method org/apache/hadoop/hbase/client/Scan."<init>":()V
       7: lconst_1
       8: invokevirtual #33                 // Method org/apache/hadoop/hbase/client/Scan.setMaxResultSize:(J)Lorg/apache/hadoop/hbase/client/Scan;
      11: areturn

  protected static org.apache.hadoop.hbase.client.Scan createBatchSmallResultSizeScan();
    Code:
       0: new           #30                 // class org/apache/hadoop/hbase/client/Scan
       3: dup
       4: invokespecial #31                 // Method org/apache/hadoop/hbase/client/Scan."<init>":()V
       7: iconst_1
       8: invokevirtual #32                 // Method org/apache/hadoop/hbase/client/Scan.setBatch:(I)Lorg/apache/hadoop/hbase/client/Scan;
      11: lconst_1
      12: invokevirtual #33                 // Method org/apache/hadoop/hbase/client/Scan.setMaxResultSize:(J)Lorg/apache/hadoop/hbase/client/Scan;
      15: areturn

  protected static org.apache.hadoop.hbase.client.AsyncTable<?> getRawTable();
    Code:
       0: getstatic     #18                 // Field ASYNC_CONN:Lorg/apache/hadoop/hbase/client/AsyncConnection;
       3: getstatic     #10                 // Field TABLE_NAME:Lorg/apache/hadoop/hbase/TableName;
       6: invokeinterface #19,  2           // InterfaceMethod org/apache/hadoop/hbase/client/AsyncConnection.getTable:(Lorg/apache/hadoop/hbase/TableName;)Lorg/apache/hadoop/hbase/client/AsyncTable;
      11: areturn

  protected static org.apache.hadoop.hbase.client.AsyncTable<?> getTable();
    Code:
       0: getstatic     #18                 // Field ASYNC_CONN:Lorg/apache/hadoop/hbase/client/AsyncConnection;
       3: getstatic     #10                 // Field TABLE_NAME:Lorg/apache/hadoop/hbase/TableName;
       6: invokestatic  #34                 // Method java/util/concurrent/ForkJoinPool.commonPool:()Ljava/util/concurrent/ForkJoinPool;
       9: invokeinterface #35,  3           // InterfaceMethod org/apache/hadoop/hbase/client/AsyncConnection.getTable:(Lorg/apache/hadoop/hbase/TableName;Ljava/util/concurrent/ExecutorService;)Lorg/apache/hadoop/hbase/client/AsyncTable;
      14: areturn

  protected static java.util.List<java.lang.Object[]> getScanCreatorParams();
    Code:
       0: invokestatic  #47                 // Method getScanCreator:()Ljava/util/List;
       3: invokeinterface #48,  1           // InterfaceMethod java/util/List.stream:()Ljava/util/stream/Stream;
       8: invokedynamic #49,  0             // InvokeDynamic #5:apply:()Ljava/util/function/Function;
      13: invokeinterface #50,  2           // InterfaceMethod java/util/stream/Stream.map:(Ljava/util/function/Function;)Ljava/util/stream/Stream;
      18: invokestatic  #24                 // Method java/util/stream/Collectors.toList:()Ljava/util/stream/Collector;
      21: invokeinterface #25,  2           // InterfaceMethod java/util/stream/Stream.collect:(Ljava/util/stream/Collector;)Ljava/lang/Object;
      26: checkcast     #26                 // class java/util/List
      29: areturn

  protected static java.util.List<java.lang.Object[]> getTableAndScanCreatorParams();
    Code:
       0: invokestatic  #54                 // Method getTableCreator:()Ljava/util/List;
       3: astore_0
       4: invokestatic  #47                 // Method getScanCreator:()Ljava/util/List;
       7: astore_1
       8: aload_0
       9: invokeinterface #48,  1           // InterfaceMethod java/util/List.stream:()Ljava/util/stream/Stream;
      14: aload_1
      15: invokedynamic #55,  0             // InvokeDynamic #8:apply:(Ljava/util/List;)Ljava/util/function/Function;
      20: invokeinterface #56,  2           // InterfaceMethod java/util/stream/Stream.flatMap:(Ljava/util/function/Function;)Ljava/util/stream/Stream;
      25: invokestatic  #24                 // Method java/util/stream/Collectors.toList:()Ljava/util/stream/Collector;
      28: invokeinterface #25,  2           // InterfaceMethod java/util/stream/Stream.collect:(Ljava/util/stream/Collector;)Ljava/lang/Object;
      33: checkcast     #26                 // class java/util/List
      36: areturn

  protected abstract org.apache.hadoop.hbase.client.Scan createScan();

  protected abstract java.util.List<org.apache.hadoop.hbase.client.Result> doScan(org.apache.hadoop.hbase.client.Scan) throws java.lang.Exception;

  protected final java.util.List<org.apache.hadoop.hbase.client.Result> convertFromBatchResult(java.util.List<org.apache.hadoop.hbase.client.Result>);
    Code:
       0: aload_1
       1: invokeinterface #57,  1           // InterfaceMethod java/util/List.size:()I
       6: iconst_2
       7: irem
       8: ifne          15
      11: iconst_1
      12: goto          16
      15: iconst_0
      16: invokestatic  #58                 // Method org/junit/Assert.assertTrue:(Z)V
      19: iconst_0
      20: aload_1
      21: invokeinterface #57,  1           // InterfaceMethod java/util/List.size:()I
      26: iconst_2
      27: idiv
      28: invokestatic  #21                 // InterfaceMethod java/util/stream/IntStream.range:(II)Ljava/util/stream/IntStream;
      31: aload_1
      32: invokedynamic #59,  0             // InvokeDynamic #9:apply:(Ljava/util/List;)Ljava/util/function/IntFunction;
      37: invokeinterface #23,  2           // InterfaceMethod java/util/stream/IntStream.mapToObj:(Ljava/util/function/IntFunction;)Ljava/util/stream/Stream;
      42: invokestatic  #24                 // Method java/util/stream/Collectors.toList:()Ljava/util/stream/Collector;
      45: invokeinterface #25,  2           // InterfaceMethod java/util/stream/Stream.collect:(Ljava/util/stream/Collector;)Ljava/lang/Object;
      50: checkcast     #26                 // class java/util/List
      53: areturn

  public void testScanAll() throws java.lang.Exception;
    Code:
       0: aload_0
       1: aload_0
       2: invokevirtual #60                 // Method createScan:()Lorg/apache/hadoop/hbase/client/Scan;
       5: invokevirtual #61                 // Method doScan:(Lorg/apache/hadoop/hbase/client/Scan;)Ljava/util/List;
       8: astore_1
       9: getstatic     #2                  // Field TEST_UTIL:Lorg/apache/hadoop/hbase/HBaseTestingUtility;
      12: invokevirtual #62                 // Method org/apache/hadoop/hbase/HBaseTestingUtility.getHBaseCluster:()Lorg/apache/hadoop/hbase/MiniHBaseCluster;
      15: invokevirtual #63                 // Method org/apache/hadoop/hbase/MiniHBaseCluster.getRegionServerThreads:()Ljava/util/List;
      18: invokeinterface #48,  1           // InterfaceMethod java/util/List.stream:()Ljava/util/stream/Stream;
      23: invokedynamic #64,  0             // InvokeDynamic #10:apply:()Ljava/util/function/Function;
      28: invokeinterface #50,  2           // InterfaceMethod java/util/stream/Stream.map:(Ljava/util/function/Function;)Ljava/util/stream/Stream;
      33: invokedynamic #65,  0             // InvokeDynamic #11:accept:()Ljava/util/function/Consumer;
      38: invokeinterface #66,  2           // InterfaceMethod java/util/stream/Stream.forEach:(Ljava/util/function/Consumer;)V
      43: getstatic     #20                 // Field COUNT:I
      46: i2l
      47: aload_1
      48: invokeinterface #57,  1           // InterfaceMethod java/util/List.size:()I
      53: i2l
      54: invokestatic  #67                 // Method org/junit/Assert.assertEquals:(JJ)V
      57: iconst_0
      58: getstatic     #20                 // Field COUNT:I
      61: invokestatic  #21                 // InterfaceMethod java/util/stream/IntStream.range:(II)Ljava/util/stream/IntStream;
      64: aload_1
      65: invokedynamic #68,  0             // InvokeDynamic #12:accept:(Ljava/util/List;)Ljava/util/function/IntConsumer;
      70: invokeinterface #69,  2           // InterfaceMethod java/util/stream/IntStream.forEach:(Ljava/util/function/IntConsumer;)V
      75: return

  public void testReversedScanAll() throws java.lang.Exception;
    Code:
       0: aload_0
       1: aload_0
       2: invokevirtual #60                 // Method createScan:()Lorg/apache/hadoop/hbase/client/Scan;
       5: iconst_1
       6: invokevirtual #77                 // Method org/apache/hadoop/hbase/client/Scan.setReversed:(Z)Lorg/apache/hadoop/hbase/client/Scan;
       9: invokevirtual #61                 // Method doScan:(Lorg/apache/hadoop/hbase/client/Scan;)Ljava/util/List;
      12: astore_1
      13: getstatic     #20                 // Field COUNT:I
      16: i2l
      17: aload_1
      18: invokeinterface #57,  1           // InterfaceMethod java/util/List.size:()I
      23: i2l
      24: invokestatic  #67                 // Method org/junit/Assert.assertEquals:(JJ)V
      27: iconst_0
      28: getstatic     #20                 // Field COUNT:I
      31: invokestatic  #21                 // InterfaceMethod java/util/stream/IntStream.range:(II)Ljava/util/stream/IntStream;
      34: aload_0
      35: aload_1
      36: invokedynamic #78,  0             // InvokeDynamic #13:accept:(Lorg/apache/hadoop/hbase/client/AbstractTestAsyncTableScan;Ljava/util/List;)Ljava/util/function/IntConsumer;
      41: invokeinterface #69,  2           // InterfaceMethod java/util/stream/IntStream.forEach:(Ljava/util/function/IntConsumer;)V
      46: return

  public void testScanNoStopKey() throws java.lang.Exception;
    Code:
       0: sipush        345
       3: istore_1
       4: aload_0
       5: aload_0
       6: invokevirtual #60                 // Method createScan:()Lorg/apache/hadoop/hbase/client/Scan;
       9: ldc           #5                  // String %03d
      11: iconst_1
      12: anewarray     #6                  // class java/lang/Object
      15: dup
      16: iconst_0
      17: iload_1
      18: invokestatic  #7                  // Method java/lang/Integer.valueOf:(I)Ljava/lang/Integer;
      21: aastore
      22: invokestatic  #8                  // Method java/lang/String.format:(Ljava/lang/String;[Ljava/lang/Object;)Ljava/lang/String;
      25: invokestatic  #9                  // Method org/apache/hadoop/hbase/util/Bytes.toBytes:(Ljava/lang/String;)[B
      28: invokevirtual #79                 // Method org/apache/hadoop/hbase/client/Scan.withStartRow:([B)Lorg/apache/hadoop/hbase/client/Scan;
      31: invokevirtual #61                 // Method doScan:(Lorg/apache/hadoop/hbase/client/Scan;)Ljava/util/List;
      34: astore_2
      35: getstatic     #20                 // Field COUNT:I
      38: iload_1
      39: isub
      40: i2l
      41: aload_2
      42: invokeinterface #57,  1           // InterfaceMethod java/util/List.size:()I
      47: i2l
      48: invokestatic  #67                 // Method org/junit/Assert.assertEquals:(JJ)V
      51: iconst_0
      52: getstatic     #20                 // Field COUNT:I
      55: iload_1
      56: isub
      57: invokestatic  #21                 // InterfaceMethod java/util/stream/IntStream.range:(II)Ljava/util/stream/IntStream;
      60: aload_0
      61: aload_2
      62: iload_1
      63: invokedynamic #80,  0             // InvokeDynamic #14:accept:(Lorg/apache/hadoop/hbase/client/AbstractTestAsyncTableScan;Ljava/util/List;I)Ljava/util/function/IntConsumer;
      68: invokeinterface #69,  2           // InterfaceMethod java/util/stream/IntStream.forEach:(Ljava/util/function/IntConsumer;)V
      73: return

  public void testReverseScanNoStopKey() throws java.lang.Exception;
    Code:
       0: sipush        765
       3: istore_1
       4: aload_0
       5: aload_0
       6: invokevirtual #60                 // Method createScan:()Lorg/apache/hadoop/hbase/client/Scan;
       9: ldc           #5                  // String %03d
      11: iconst_1
      12: anewarray     #6                  // class java/lang/Object
      15: dup
      16: iconst_0
      17: iload_1
      18: invokestatic  #7                  // Method java/lang/Integer.valueOf:(I)Ljava/lang/Integer;
      21: aastore
      22: invokestatic  #8                  // Method java/lang/String.format:(Ljava/lang/String;[Ljava/lang/Object;)Ljava/lang/String;
      25: invokestatic  #9                  // Method org/apache/hadoop/hbase/util/Bytes.toBytes:(Ljava/lang/String;)[B
      28: invokevirtual #79                 // Method org/apache/hadoop/hbase/client/Scan.withStartRow:([B)Lorg/apache/hadoop/hbase/client/Scan;
      31: iconst_1
      32: invokevirtual #77                 // Method org/apache/hadoop/hbase/client/Scan.setReversed:(Z)Lorg/apache/hadoop/hbase/client/Scan;
      35: invokevirtual #61                 // Method doScan:(Lorg/apache/hadoop/hbase/client/Scan;)Ljava/util/List;
      38: astore_2
      39: iload_1
      40: iconst_1
      41: iadd
      42: i2l
      43: aload_2
      44: invokeinterface #57,  1           // InterfaceMethod java/util/List.size:()I
      49: i2l
      50: invokestatic  #67                 // Method org/junit/Assert.assertEquals:(JJ)V
      53: iconst_0
      54: iload_1
      55: iconst_1
      56: iadd
      57: invokestatic  #21                 // InterfaceMethod java/util/stream/IntStream.range:(II)Ljava/util/stream/IntStream;
      60: aload_0
      61: aload_2
      62: iload_1
      63: invokedynamic #81,  0             // InvokeDynamic #15:accept:(Lorg/apache/hadoop/hbase/client/AbstractTestAsyncTableScan;Ljava/util/List;I)Ljava/util/function/IntConsumer;
      68: invokeinterface #69,  2           // InterfaceMethod java/util/stream/IntStream.forEach:(Ljava/util/function/IntConsumer;)V
      73: return

  public void testScanWrongColumnFamily() throws java.lang.Exception;
    Code:
       0: aload_0
       1: aload_0
       2: invokevirtual #60                 // Method createScan:()Lorg/apache/hadoop/hbase/client/Scan;
       5: ldc           #82                 // String WrongColumnFamily
       7: invokestatic  #9                  // Method org/apache/hadoop/hbase/util/Bytes.toBytes:(Ljava/lang/String;)[B
      10: invokevirtual #83                 // Method org/apache/hadoop/hbase/client/Scan.addFamily:([B)Lorg/apache/hadoop/hbase/client/Scan;
      13: invokevirtual #61                 // Method doScan:(Lorg/apache/hadoop/hbase/client/Scan;)Ljava/util/List;
      16: pop
      17: goto          46
      20: astore_1
      21: aload_1
      22: instanceof    #85                 // class org/apache/hadoop/hbase/regionserver/NoSuchColumnFamilyException
      25: ifne          38
      28: aload_1
      29: invokevirtual #86                 // Method java/lang/Exception.getCause:()Ljava/lang/Throwable;
      32: instanceof    #85                 // class org/apache/hadoop/hbase/regionserver/NoSuchColumnFamilyException
      35: ifeq          42
      38: iconst_1
      39: goto          43
      42: iconst_0
      43: invokestatic  #58                 // Method org/junit/Assert.assertTrue:(Z)V
      46: return
    Exception table:
       from    to  target type
           0    17    20   Class java/lang/Exception

  public void testScanWithStartKeyAndStopKey() throws java.lang.Exception;
    Code:
       0: aload_0
       1: iconst_1
       2: iconst_1
       3: sipush        998
       6: iconst_0
       7: iconst_m1
       8: invokespecial #93                 // Method testScan:(IZIZI)V
      11: aload_0
      12: bipush        123
      14: iconst_1
      15: sipush        345
      18: iconst_1
      19: iconst_m1
      20: invokespecial #93                 // Method testScan:(IZIZI)V
      23: aload_0
      24: sipush        234
      27: iconst_1
      28: sipush        456
      31: iconst_0
      32: iconst_m1
      33: invokespecial #93                 // Method testScan:(IZIZI)V
      36: aload_0
      37: sipush        345
      40: iconst_0
      41: sipush        567
      44: iconst_1
      45: iconst_m1
      46: invokespecial #93                 // Method testScan:(IZIZI)V
      49: aload_0
      50: sipush        456
      53: iconst_0
      54: sipush        678
      57: iconst_0
      58: iconst_m1
      59: invokespecial #93                 // Method testScan:(IZIZI)V
      62: return

  public void testReversedScanWithStartKeyAndStopKey() throws java.lang.Exception;
    Code:
       0: aload_0
       1: sipush        998
       4: iconst_1
       5: iconst_1
       6: iconst_0
       7: iconst_m1
       8: invokespecial #94                 // Method testReversedScan:(IZIZI)V
      11: aload_0
      12: sipush        543
      15: iconst_1
      16: sipush        321
      19: iconst_1
      20: iconst_m1
      21: invokespecial #94                 // Method testReversedScan:(IZIZI)V
      24: aload_0
      25: sipush        654
      28: iconst_1
      29: sipush        432
      32: iconst_0
      33: iconst_m1
      34: invokespecial #94                 // Method testReversedScan:(IZIZI)V
      37: aload_0
      38: sipush        765
      41: iconst_0
      42: sipush        543
      45: iconst_1
      46: iconst_m1
      47: invokespecial #94                 // Method testReversedScan:(IZIZI)V
      50: aload_0
      51: sipush        876
      54: iconst_0
      55: sipush        654
      58: iconst_0
      59: iconst_m1
      60: invokespecial #94                 // Method testReversedScan:(IZIZI)V
      63: return

  public void testScanAtRegionBoundary() throws java.lang.Exception;
    Code:
       0: aload_0
       1: sipush        222
       4: iconst_1
       5: sipush        333
       8: iconst_1
       9: iconst_m1
      10: invokespecial #93                 // Method testScan:(IZIZI)V
      13: aload_0
      14: sipush        333
      17: iconst_1
      18: sipush        444
      21: iconst_0
      22: iconst_m1
      23: invokespecial #93                 // Method testScan:(IZIZI)V
      26: aload_0
      27: sipush        444
      30: iconst_0
      31: sipush        555
      34: iconst_1
      35: iconst_m1
      36: invokespecial #93                 // Method testScan:(IZIZI)V
      39: aload_0
      40: sipush        555
      43: iconst_0
      44: sipush        666
      47: iconst_0
      48: iconst_m1
      49: invokespecial #93                 // Method testScan:(IZIZI)V
      52: return

  public void testReversedScanAtRegionBoundary() throws java.lang.Exception;
    Code:
       0: aload_0
       1: sipush        333
       4: iconst_1
       5: sipush        222
       8: iconst_1
       9: iconst_m1
      10: invokespecial #94                 // Method testReversedScan:(IZIZI)V
      13: aload_0
      14: sipush        444
      17: iconst_1
      18: sipush        333
      21: iconst_0
      22: iconst_m1
      23: invokespecial #94                 // Method testReversedScan:(IZIZI)V
      26: aload_0
      27: sipush        555
      30: iconst_0
      31: sipush        444
      34: iconst_1
      35: iconst_m1
      36: invokespecial #94                 // Method testReversedScan:(IZIZI)V
      39: aload_0
      40: sipush        666
      43: iconst_0
      44: sipush        555
      47: iconst_0
      48: iconst_m1
      49: invokespecial #94                 // Method testReversedScan:(IZIZI)V
      52: return

  public void testScanWithLimit() throws java.lang.Exception;
    Code:
       0: aload_0
       1: iconst_1
       2: iconst_1
       3: sipush        998
       6: iconst_0
       7: sipush        900
      10: invokespecial #93                 // Method testScan:(IZIZI)V
      13: aload_0
      14: bipush        123
      16: iconst_1
      17: sipush        234
      20: iconst_1
      21: bipush        100
      23: invokespecial #93                 // Method testScan:(IZIZI)V
      26: aload_0
      27: sipush        234
      30: iconst_1
      31: sipush        456
      34: iconst_0
      35: bipush        100
      37: invokespecial #93                 // Method testScan:(IZIZI)V
      40: aload_0
      41: sipush        345
      44: iconst_0
      45: sipush        567
      48: iconst_1
      49: bipush        100
      51: invokespecial #93                 // Method testScan:(IZIZI)V
      54: aload_0
      55: sipush        456
      58: iconst_0
      59: sipush        678
      62: iconst_0
      63: bipush        100
      65: invokespecial #93                 // Method testScan:(IZIZI)V
      68: return

  public void testScanWithLimitGreaterThanActualCount() throws java.lang.Exception;
    Code:
       0: aload_0
       1: iconst_1
       2: iconst_1
       3: sipush        998
       6: iconst_0
       7: sipush        1000
      10: invokespecial #93                 // Method testScan:(IZIZI)V
      13: aload_0
      14: bipush        123
      16: iconst_1
      17: sipush        345
      20: iconst_1
      21: sipush        200
      24: invokespecial #93                 // Method testScan:(IZIZI)V
      27: aload_0
      28: sipush        234
      31: iconst_1
      32: sipush        456
      35: iconst_0
      36: sipush        200
      39: invokespecial #93                 // Method testScan:(IZIZI)V
      42: aload_0
      43: sipush        345
      46: iconst_0
      47: sipush        567
      50: iconst_1
      51: sipush        200
      54: invokespecial #93                 // Method testScan:(IZIZI)V
      57: aload_0
      58: sipush        456
      61: iconst_0
      62: sipush        678
      65: iconst_0
      66: sipush        200
      69: invokespecial #93                 // Method testScan:(IZIZI)V
      72: return

  public void testReversedScanWithLimit() throws java.lang.Exception;
    Code:
       0: aload_0
       1: sipush        998
       4: iconst_1
       5: iconst_1
       6: iconst_0
       7: sipush        900
      10: invokespecial #94                 // Method testReversedScan:(IZIZI)V
      13: aload_0
      14: sipush        543
      17: iconst_1
      18: sipush        321
      21: iconst_1
      22: bipush        100
      24: invokespecial #94                 // Method testReversedScan:(IZIZI)V
      27: aload_0
      28: sipush        654
      31: iconst_1
      32: sipush        432
      35: iconst_0
      36: bipush        100
      38: invokespecial #94                 // Method testReversedScan:(IZIZI)V
      41: aload_0
      42: sipush        765
      45: iconst_0
      46: sipush        543
      49: iconst_1
      50: bipush        100
      52: invokespecial #94                 // Method testReversedScan:(IZIZI)V
      55: aload_0
      56: sipush        876
      59: iconst_0
      60: sipush        654
      63: iconst_0
      64: bipush        100
      66: invokespecial #94                 // Method testReversedScan:(IZIZI)V
      69: return

  public void testReversedScanWithLimitGreaterThanActualCount() throws java.lang.Exception;
    Code:
       0: aload_0
       1: sipush        998
       4: iconst_1
       5: iconst_1
       6: iconst_0
       7: sipush        1000
      10: invokespecial #94                 // Method testReversedScan:(IZIZI)V
      13: aload_0
      14: sipush        543
      17: iconst_1
      18: sipush        321
      21: iconst_1
      22: sipush        200
      25: invokespecial #94                 // Method testReversedScan:(IZIZI)V
      28: aload_0
      29: sipush        654
      32: iconst_1
      33: sipush        432
      36: iconst_0
      37: sipush        200
      40: invokespecial #94                 // Method testReversedScan:(IZIZI)V
      43: aload_0
      44: sipush        765
      47: iconst_0
      48: sipush        543
      51: iconst_1
      52: sipush        200
      55: invokespecial #94                 // Method testReversedScan:(IZIZI)V
      58: aload_0
      59: sipush        876
      62: iconst_0
      63: sipush        654
      66: iconst_0
      67: sipush        200
      70: invokespecial #94                 // Method testReversedScan:(IZIZI)V
      73: return

  static {};
    Code:
       0: new           #122                // class org/apache/hadoop/hbase/HBaseTestingUtility
       3: dup
       4: invokespecial #123                // Method org/apache/hadoop/hbase/HBaseTestingUtility."<init>":()V
       7: putstatic     #2                  // Field TEST_UTIL:Lorg/apache/hadoop/hbase/HBaseTestingUtility;
      10: ldc           #124                // String async
      12: invokestatic  #125                // Method org/apache/hadoop/hbase/TableName.valueOf:(Ljava/lang/String;)Lorg/apache/hadoop/hbase/TableName;
      15: putstatic     #10                 // Field TABLE_NAME:Lorg/apache/hadoop/hbase/TableName;
      18: ldc           #126                // String cf
      20: invokestatic  #9                  // Method org/apache/hadoop/hbase/util/Bytes.toBytes:(Ljava/lang/String;)[B
      23: putstatic     #11                 // Field FAMILY:[B
      26: ldc           #127                // String cq1
      28: invokestatic  #9                  // Method org/apache/hadoop/hbase/util/Bytes.toBytes:(Ljava/lang/String;)[B
      31: putstatic     #73                 // Field CQ1:[B
      34: ldc           #128                // String cq2
      36: invokestatic  #9                  // Method org/apache/hadoop/hbase/util/Bytes.toBytes:(Ljava/lang/String;)[B
      39: putstatic     #76                 // Field CQ2:[B
      42: sipush        1000
      45: putstatic     #20                 // Field COUNT:I
      48: return
}
