Compiled from "AbstractFileStatusFilter.java"
public abstract class org.apache.hadoop.hbase.util.AbstractFileStatusFilter implements org.apache.hadoop.fs.PathFilter,org.apache.hadoop.hbase.util.FileStatusFilter {
  public org.apache.hadoop.hbase.util.AbstractFileStatusFilter();
    Code:
       0: aload_0
       1: invokespecial #1                  // Method java/lang/Object."<init>":()V
       4: return

  protected abstract boolean accept(org.apache.hadoop.fs.Path, java.lang.Boolean);

  public boolean accept(org.apache.hadoop.fs.FileStatus);
    Code:
       0: aload_0
       1: aload_1
       2: invokevirtual #2                  // Method org/apache/hadoop/fs/FileStatus.getPath:()Lorg/apache/hadoop/fs/Path;
       5: aload_1
       6: invokevirtual #3                  // Method org/apache/hadoop/fs/FileStatus.isDirectory:()Z
       9: invokestatic  #4                  // Method java/lang/Boolean.valueOf:(Z)Ljava/lang/Boolean;
      12: invokevirtual #5                  // Method accept:(Lorg/apache/hadoop/fs/Path;Ljava/lang/Boolean;)Z
      15: ireturn

  public boolean accept(org.apache.hadoop.fs.Path);
    Code:
       0: aload_0
       1: aload_1
       2: aconst_null
       3: invokevirtual #5                  // Method accept:(Lorg/apache/hadoop/fs/Path;Ljava/lang/Boolean;)Z
       6: ireturn

  protected boolean isFile(org.apache.hadoop.fs.FileSystem, java.lang.Boolean, org.apache.hadoop.fs.Path) throws java.io.IOException;
    Code:
       0: aload_0
       1: aload_1
       2: aload_2
       3: aload_3
       4: invokevirtual #6                  // Method isDirectory:(Lorg/apache/hadoop/fs/FileSystem;Ljava/lang/Boolean;Lorg/apache/hadoop/fs/Path;)Z
       7: ifne          14
      10: iconst_1
      11: goto          15
      14: iconst_0
      15: ireturn

  protected boolean isDirectory(org.apache.hadoop.fs.FileSystem, java.lang.Boolean, org.apache.hadoop.fs.Path) throws java.io.IOException;
    Code:
       0: aload_2
       1: ifnull        11
       4: aload_2
       5: invokevirtual #7                  // Method java/lang/Boolean.booleanValue:()Z
       8: goto          16
      11: aload_1
      12: aload_3
      13: invokevirtual #8                  // Method org/apache/hadoop/fs/FileSystem.isDirectory:(Lorg/apache/hadoop/fs/Path;)Z
      16: ireturn
}
