Compiled from "AbstractTestWALReplay.java"
class org.apache.hadoop.hbase.regionserver.wal.AbstractTestWALReplay$TestFlusher implements org.apache.hadoop.hbase.regionserver.FlushRequester {
  org.apache.hadoop.hbase.regionserver.wal.AbstractTestWALReplay$TestFlusher();
    Code:
       0: aload_0
       1: invokespecial #1                  // Method java/lang/Object."<init>":()V
       4: return

  public boolean requestFlush(org.apache.hadoop.hbase.regionserver.HRegion, boolean, org.apache.hadoop.hbase.regionserver.FlushLifeCycleTracker);
    Code:
       0: aload_0
       1: getfield      #2                  // Field r:Lorg/apache/hadoop/hbase/regionserver/HRegion;
       4: iload_2
       5: invokevirtual #3                  // Method org/apache/hadoop/hbase/regionserver/HRegion.flush:(Z)Lorg/apache/hadoop/hbase/regionserver/HRegion$FlushResult;
       8: pop
       9: iconst_1
      10: ireturn
      11: astore        4
      13: new           #5                  // class java/lang/RuntimeException
      16: dup
      17: ldc           #6                  // String Exception flushing
      19: aload         4
      21: invokespecial #7                  // Method java/lang/RuntimeException."<init>":(Ljava/lang/String;Ljava/lang/Throwable;)V
      24: athrow
    Exception table:
       from    to  target type
           0    10    11   Class java/io/IOException

  public boolean requestDelayedFlush(org.apache.hadoop.hbase.regionserver.HRegion, long, boolean);
    Code:
       0: iconst_1
       1: ireturn

  public void registerFlushRequestListener(org.apache.hadoop.hbase.regionserver.FlushRequestListener);
    Code:
       0: return

  public boolean unregisterFlushRequestListener(org.apache.hadoop.hbase.regionserver.FlushRequestListener);
    Code:
       0: iconst_0
       1: ireturn

  public void setGlobalMemStoreLimit(long);
    Code:
       0: return
}
