Compiled from "AbstractTestWALReplay.java"
class org.apache.hadoop.hbase.regionserver.wal.AbstractTestWALReplay$6$1 implements org.mockito.stubbing.Answer<java.lang.Integer> {
  final org.apache.hadoop.hbase.regionserver.wal.AbstractTestWALReplay$6 this$1;

  org.apache.hadoop.hbase.regionserver.wal.AbstractTestWALReplay$6$1(org.apache.hadoop.hbase.regionserver.wal.AbstractTestWALReplay$6);
    Code:
       0: aload_0
       1: aload_1
       2: putfield      #1                  // Field this$1:Lorg/apache/hadoop/hbase/regionserver/wal/AbstractTestWALReplay$6;
       5: aload_0
       6: invokespecial #2                  // Method java/lang/Object."<init>":()V
       9: return

  public java.lang.Integer answer(org.mockito.invocation.InvocationOnMock) throws java.lang.Throwable;
    Code:
       0: aload_0
       1: getfield      #3                  // Field pos:J
       4: aload_0
       5: getfield      #1                  // Field this$1:Lorg/apache/hadoop/hbase/regionserver/wal/AbstractTestWALReplay$6;
       8: getfield      #4                  // Field org/apache/hadoop/hbase/regionserver/wal/AbstractTestWALReplay$6.val$headerLength:J
      11: lcmp
      12: iflt          25
      15: new           #5                  // class java/io/IOException
      18: dup
      19: ldc           #6                  // String read over limit
      21: invokespecial #7                  // Method java/io/IOException."<init>":(Ljava/lang/String;)V
      24: athrow
      25: aload_1
      26: invokeinterface #8,  1            // InterfaceMethod org/mockito/invocation/InvocationOnMock.callRealMethod:()Ljava/lang/Object;
      31: checkcast     #9                  // class java/lang/Integer
      34: invokevirtual #10                 // Method java/lang/Integer.intValue:()I
      37: istore_2
      38: iload_2
      39: ifle          53
      42: aload_0
      43: dup
      44: getfield      #3                  // Field pos:J
      47: iload_2
      48: i2l
      49: ladd
      50: putfield      #3                  // Field pos:J
      53: iload_2
      54: invokestatic  #11                 // Method java/lang/Integer.valueOf:(I)Ljava/lang/Integer;
      57: areturn

  public java.lang.Object answer(org.mockito.invocation.InvocationOnMock) throws java.lang.Throwable;
    Code:
       0: aload_0
       1: aload_1
       2: invokevirtual #12                 // Method answer:(Lorg/mockito/invocation/InvocationOnMock;)Ljava/lang/Integer;
       5: areturn
}
