Compiled from "AbstractTestWALReplay.java"
class org.apache.hadoop.hbase.regionserver.wal.AbstractTestWALReplay$6$2 implements org.mockito.stubbing.Answer<java.lang.Void> {
  final org.apache.hadoop.hdfs.DFSInputStream val$in;

  final org.apache.hadoop.hbase.regionserver.wal.AbstractTestWALReplay$6 this$1;

  org.apache.hadoop.hbase.regionserver.wal.AbstractTestWALReplay$6$2(org.apache.hadoop.hbase.regionserver.wal.AbstractTestWALReplay$6, org.apache.hadoop.hdfs.DFSInputStream);
    Code:
       0: aload_0
       1: aload_1
       2: putfield      #1                  // Field this$1:Lorg/apache/hadoop/hbase/regionserver/wal/AbstractTestWALReplay$6;
       5: aload_0
       6: aload_2
       7: putfield      #2                  // Field val$in:Lorg/apache/hadoop/hdfs/DFSInputStream;
      10: aload_0
      11: invokespecial #3                  // Method java/lang/Object."<init>":()V
      14: return

  public java.lang.Void answer(org.mockito.invocation.InvocationOnMock) throws java.lang.Throwable;
    Code:
       0: aload_1
       1: invokeinterface #4,  1            // InterfaceMethod org/mockito/invocation/InvocationOnMock.callRealMethod:()Ljava/lang/Object;
       6: pop
       7: aload_0
       8: getfield      #2                  // Field val$in:Lorg/apache/hadoop/hdfs/DFSInputStream;
      11: invokevirtual #5                  // Method org/apache/hadoop/hdfs/DFSInputStream.close:()V
      14: aconst_null
      15: areturn

  public java.lang.Object answer(org.mockito.invocation.InvocationOnMock) throws java.lang.Throwable;
    Code:
       0: aload_0
       1: aload_1
       2: invokevirtual #6                  // Method answer:(Lorg/mockito/invocation/InvocationOnMock;)Ljava/lang/Void;
       5: areturn
}
