Compiled from "AbstractTestWALReplay.java"
public class org.apache.hadoop.hbase.regionserver.wal.AbstractTestWALReplay$CustomStoreFlusher extends org.apache.hadoop.hbase.regionserver.DefaultStoreFlusher {
  static final java.util.concurrent.atomic.AtomicBoolean throwExceptionWhenFlushing;

  public org.apache.hadoop.hbase.regionserver.wal.AbstractTestWALReplay$CustomStoreFlusher(org.apache.hadoop.conf.Configuration, org.apache.hadoop.hbase.regionserver.HStore);
    Code:
       0: aload_0
       1: aload_1
       2: aload_2
       3: invokespecial #1                  // Method org/apache/hadoop/hbase/regionserver/DefaultStoreFlusher."<init>":(Lorg/apache/hadoop/conf/Configuration;Lorg/apache/hadoop/hbase/regionserver/HStore;)V
       6: return

  public java.util.List<org.apache.hadoop.fs.Path> flushSnapshot(org.apache.hadoop.hbase.regionserver.MemStoreSnapshot, long, org.apache.hadoop.hbase.monitoring.MonitoredTask, org.apache.hadoop.hbase.regionserver.throttle.ThroughputController, org.apache.hadoop.hbase.regionserver.FlushLifeCycleTracker) throws java.io.IOException;
    Code:
       0: getstatic     #2                  // Field throwExceptionWhenFlushing:Ljava/util/concurrent/atomic/AtomicBoolean;
       3: invokevirtual #3                  // Method java/util/concurrent/atomic/AtomicBoolean.get:()Z
       6: ifeq          19
       9: new           #4                  // class java/io/IOException
      12: dup
      13: ldc           #5                  // String Simulated exception by tests
      15: invokespecial #6                  // Method java/io/IOException."<init>":(Ljava/lang/String;)V
      18: athrow
      19: aload_0
      20: aload_1
      21: lload_2
      22: aload         4
      24: aload         5
      26: aload         6
      28: invokespecial #7                  // Method org/apache/hadoop/hbase/regionserver/DefaultStoreFlusher.flushSnapshot:(Lorg/apache/hadoop/hbase/regionserver/MemStoreSnapshot;JLorg/apache/hadoop/hbase/monitoring/MonitoredTask;Lorg/apache/hadoop/hbase/regionserver/throttle/ThroughputController;Lorg/apache/hadoop/hbase/regionserver/FlushLifeCycleTracker;)Ljava/util/List;
      31: areturn

  static {};
    Code:
       0: new           #8                  // class java/util/concurrent/atomic/AtomicBoolean
       3: dup
       4: iconst_0
       5: invokespecial #9                  // Method java/util/concurrent/atomic/AtomicBoolean."<init>":(Z)V
       8: putstatic     #2                  // Field throwExceptionWhenFlushing:Ljava/util/concurrent/atomic/AtomicBoolean;
      11: return
}
