Compiled from "AcidGuaranteesTestTool.java"
class org.apache.hadoop.hbase.AcidGuaranteesTestTool$1 extends org.apache.hadoop.hbase.MultithreadedTestUtil$RepeatingTestThread {
  final org.apache.hadoop.hbase.client.Admin val$admin;

  final org.apache.hadoop.hbase.AcidGuaranteesTestTool this$0;

  org.apache.hadoop.hbase.AcidGuaranteesTestTool$1(org.apache.hadoop.hbase.AcidGuaranteesTestTool, org.apache.hadoop.hbase.MultithreadedTestUtil$TestContext, org.apache.hadoop.hbase.client.Admin);
    Code:
       0: aload_0
       1: aload_1
       2: putfield      #1                  // Field this$0:Lorg/apache/hadoop/hbase/AcidGuaranteesTestTool;
       5: aload_0
       6: aload_3
       7: putfield      #2                  // Field val$admin:Lorg/apache/hadoop/hbase/client/Admin;
      10: aload_0
      11: aload_2
      12: invokespecial #3                  // Method org/apache/hadoop/hbase/MultithreadedTestUtil$RepeatingTestThread."<init>":(Lorg/apache/hadoop/hbase/MultithreadedTestUtil$TestContext;)V
      15: return

  public void doAnAction() throws java.lang.Exception;
    Code:
       0: aload_0
       1: getfield      #2                  // Field val$admin:Lorg/apache/hadoop/hbase/client/Admin;
       4: getstatic     #4                  // Field org/apache/hadoop/hbase/AcidGuaranteesTestTool.TABLE_NAME:Lorg/apache/hadoop/hbase/TableName;
       7: invokeinterface #5,  2            // InterfaceMethod org/apache/hadoop/hbase/client/Admin.flush:(Lorg/apache/hadoop/hbase/TableName;)V
      12: goto          46
      15: astore_1
      16: invokestatic  #7                  // Method org/apache/hadoop/hbase/AcidGuaranteesTestTool.access$000:()Lorg/slf4j/Logger;
      19: new           #8                  // class java/lang/StringBuilder
      22: dup
      23: invokespecial #9                  // Method java/lang/StringBuilder."<init>":()V
      26: ldc           #10                 // String Ignoring exception while flushing:
      28: invokevirtual #11                 // Method java/lang/StringBuilder.append:(Ljava/lang/String;)Ljava/lang/StringBuilder;
      31: aload_1
      32: invokestatic  #12                 // Method org/apache/hadoop/util/StringUtils.stringifyException:(Ljava/lang/Throwable;)Ljava/lang/String;
      35: invokevirtual #11                 // Method java/lang/StringBuilder.append:(Ljava/lang/String;)Ljava/lang/StringBuilder;
      38: invokevirtual #13                 // Method java/lang/StringBuilder.toString:()Ljava/lang/String;
      41: invokeinterface #14,  2           // InterfaceMethod org/slf4j/Logger.warn:(Ljava/lang/String;)V
      46: aload_0
      47: getfield      #1                  // Field this$0:Lorg/apache/hadoop/hbase/AcidGuaranteesTestTool;
      50: invokestatic  #15                 // Method org/apache/hadoop/hbase/AcidGuaranteesTestTool.access$100:(Lorg/apache/hadoop/hbase/AcidGuaranteesTestTool;)Z
      53: ifne          62
      56: ldc2_w        #16                 // long 60000l
      59: invokestatic  #18                 // Method java/lang/Thread.sleep:(J)V
      62: return
    Exception table:
       from    to  target type
           0    12    15   Class java/io/IOException
}
