Compiled from "AdaptiveMemStoreCompactionStrategy.java"
public class org.apache.hadoop.hbase.regionserver.AdaptiveMemStoreCompactionStrategy extends org.apache.hadoop.hbase.regionserver.MemStoreCompactionStrategy {
  public static final java.lang.String ADAPTIVE_COMPACTION_THRESHOLD_KEY;

  public static final java.lang.String ADAPTIVE_INITIAL_COMPACTION_PROBABILITY_KEY;

  public org.apache.hadoop.hbase.regionserver.AdaptiveMemStoreCompactionStrategy(org.apache.hadoop.conf.Configuration, java.lang.String);
    Code:
       0: aload_0
       1: aload_1
       2: aload_2
       3: invokespecial #1                  // Method org/apache/hadoop/hbase/regionserver/MemStoreCompactionStrategy."<init>":(Lorg/apache/hadoop/conf/Configuration;Ljava/lang/String;)V
       6: aload_0
       7: new           #2                  // class java/util/Random
      10: dup
      11: invokespecial #3                  // Method java/util/Random."<init>":()V
      14: putfield      #4                  // Field rand:Ljava/util/Random;
      17: aload_0
      18: dconst_0
      19: putfield      #5                  // Field numCellsInVersionedList:D
      22: aload_0
      23: iconst_0
      24: putfield      #6                  // Field compacted:Z
      27: aload_0
      28: aload_1
      29: ldc           #8                  // String hbase.hregion.compacting.memstore.adaptive.compaction.threshold
      31: ldc2_w        #9                  // double 0.5d
      34: invokevirtual #11                 // Method org/apache/hadoop/conf/Configuration.getDouble:(Ljava/lang/String;D)D
      37: putfield      #12                 // Field compactionThreshold:D
      40: aload_0
      41: aload_1
      42: ldc           #13                 // String hbase.hregion.compacting.memstore.adaptive.compaction.probability
      44: ldc2_w        #9                  // double 0.5d
      47: invokevirtual #11                 // Method org/apache/hadoop/conf/Configuration.getDouble:(Ljava/lang/String;D)D
      50: putfield      #14                 // Field initialCompactionProbability:D
      53: aload_0
      54: invokevirtual #15                 // Method resetStats:()V
      57: return

  public org.apache.hadoop.hbase.regionserver.MemStoreCompactionStrategy$Action getAction(org.apache.hadoop.hbase.regionserver.VersionedSegmentsList);
    Code:
       0: aload_1
       1: invokevirtual #16                 // Method org/apache/hadoop/hbase/regionserver/VersionedSegmentsList.getEstimatedUniquesFrac:()D
       4: dconst_1
       5: aload_0
       6: getfield      #12                 // Field compactionThreshold:D
       9: dsub
      10: dcmpg
      11: ifge          85
      14: aload_0
      15: getfield      #4                  // Field rand:Ljava/util/Random;
      18: invokevirtual #17                 // Method java/util/Random.nextDouble:()D
      21: dstore_2
      22: dload_2
      23: aload_0
      24: getfield      #18                 // Field compactionProbability:D
      27: dcmpg
      28: ifge          85
      31: aload_0
      32: aload_1
      33: invokevirtual #19                 // Method org/apache/hadoop/hbase/regionserver/VersionedSegmentsList.getNumOfCells:()I
      36: i2d
      37: putfield      #5                  // Field numCellsInVersionedList:D
      40: aload_0
      41: iconst_1
      42: putfield      #6                  // Field compacted:Z
      45: aload_0
      46: aload_1
      47: new           #20                 // class java/lang/StringBuilder
      50: dup
      51: invokespecial #21                 // Method java/lang/StringBuilder."<init>":()V
      54: aload_0
      55: invokevirtual #22                 // Method getName:()Ljava/lang/String;
      58: invokevirtual #23                 // Method java/lang/StringBuilder.append:(Ljava/lang/String;)Ljava/lang/StringBuilder;
      61: ldc           #24                 // String  (compaction probability=
      63: invokevirtual #23                 // Method java/lang/StringBuilder.append:(Ljava/lang/String;)Ljava/lang/StringBuilder;
      66: aload_0
      67: getfield      #18                 // Field compactionProbability:D
      70: invokevirtual #25                 // Method java/lang/StringBuilder.append:(D)Ljava/lang/StringBuilder;
      73: ldc           #26                 // String )
      75: invokevirtual #23                 // Method java/lang/StringBuilder.append:(Ljava/lang/String;)Ljava/lang/StringBuilder;
      78: invokevirtual #27                 // Method java/lang/StringBuilder.toString:()Ljava/lang/String;
      81: invokevirtual #28                 // Method compact:(Lorg/apache/hadoop/hbase/regionserver/VersionedSegmentsList;Ljava/lang/String;)Lorg/apache/hadoop/hbase/regionserver/MemStoreCompactionStrategy$Action;
      84: areturn
      85: aload_0
      86: iconst_0
      87: putfield      #6                  // Field compacted:Z
      90: aload_0
      91: aload_1
      92: new           #20                 // class java/lang/StringBuilder
      95: dup
      96: invokespecial #21                 // Method java/lang/StringBuilder."<init>":()V
      99: aload_0
     100: invokevirtual #22                 // Method getName:()Ljava/lang/String;
     103: invokevirtual #23                 // Method java/lang/StringBuilder.append:(Ljava/lang/String;)Ljava/lang/StringBuilder;
     106: ldc           #24                 // String  (compaction probability=
     108: invokevirtual #23                 // Method java/lang/StringBuilder.append:(Ljava/lang/String;)Ljava/lang/StringBuilder;
     111: aload_0
     112: getfield      #18                 // Field compactionProbability:D
     115: invokevirtual #25                 // Method java/lang/StringBuilder.append:(D)Ljava/lang/StringBuilder;
     118: ldc           #26                 // String )
     120: invokevirtual #23                 // Method java/lang/StringBuilder.append:(Ljava/lang/String;)Ljava/lang/StringBuilder;
     123: invokevirtual #27                 // Method java/lang/StringBuilder.toString:()Ljava/lang/String;
     126: invokevirtual #29                 // Method simpleMergeOrFlatten:(Lorg/apache/hadoop/hbase/regionserver/VersionedSegmentsList;Ljava/lang/String;)Lorg/apache/hadoop/hbase/regionserver/MemStoreCompactionStrategy$Action;
     129: areturn

  public void updateStats(org.apache.hadoop.hbase.regionserver.Segment);
    Code:
       0: aload_0
       1: getfield      #6                  // Field compacted:Z
       4: ifeq          68
       7: aload_1
       8: invokevirtual #30                 // Method org/apache/hadoop/hbase/regionserver/Segment.getCellsCount:()I
      11: i2d
      12: aload_0
      13: getfield      #5                  // Field numCellsInVersionedList:D
      16: ddiv
      17: dconst_1
      18: aload_0
      19: getfield      #12                 // Field compactionThreshold:D
      22: dsub
      23: dcmpg
      24: ifge          56
      27: aload_0
      28: dup
      29: getfield      #18                 // Field compactionProbability:D
      32: ldc2_w        #31                 // double 1.02d
      35: dmul
      36: putfield      #18                 // Field compactionProbability:D
      39: aload_0
      40: getfield      #18                 // Field compactionProbability:D
      43: dconst_1
      44: dcmpl
      45: ifle          68
      48: aload_0
      49: dconst_1
      50: putfield      #18                 // Field compactionProbability:D
      53: goto          68
      56: aload_0
      57: dup
      58: getfield      #18                 // Field compactionProbability:D
      61: ldc2_w        #31                 // double 1.02d
      64: ddiv
      65: putfield      #18                 // Field compactionProbability:D
      68: return

  public void resetStats();
    Code:
       0: aload_0
       1: aload_0
       2: getfield      #14                 // Field initialCompactionProbability:D
       5: putfield      #18                 // Field compactionProbability:D
       8: return

  protected org.apache.hadoop.hbase.regionserver.MemStoreCompactionStrategy$Action getMergingAction();
    Code:
       0: getstatic     #33                 // Field org/apache/hadoop/hbase/regionserver/MemStoreCompactionStrategy$Action.MERGE_COUNT_UNIQUE_KEYS:Lorg/apache/hadoop/hbase/regionserver/MemStoreCompactionStrategy$Action;
       3: areturn

  protected org.apache.hadoop.hbase.regionserver.MemStoreCompactionStrategy$Action getFlattenAction();
    Code:
       0: getstatic     #34                 // Field org/apache/hadoop/hbase/regionserver/MemStoreCompactionStrategy$Action.FLATTEN:Lorg/apache/hadoop/hbase/regionserver/MemStoreCompactionStrategy$Action;
       3: areturn

  protected java.lang.String getName();
    Code:
       0: ldc           #35                 // String ADAPTIVE
       2: areturn
}
