Compiled from "AddPeerProcedure.java"
public class org.apache.hadoop.hbase.master.replication.AddPeerProcedure extends org.apache.hadoop.hbase.master.replication.ModifyPeerProcedure {
  public org.apache.hadoop.hbase.master.replication.AddPeerProcedure();
    Code:
       0: aload_0
       1: invokespecial #1                  // Method org/apache/hadoop/hbase/master/replication/ModifyPeerProcedure."<init>":()V
       4: return

  public org.apache.hadoop.hbase.master.replication.AddPeerProcedure(java.lang.String, org.apache.hadoop.hbase.replication.ReplicationPeerConfig, boolean);
    Code:
       0: aload_0
       1: aload_1
       2: invokespecial #2                  // Method org/apache/hadoop/hbase/master/replication/ModifyPeerProcedure."<init>":(Ljava/lang/String;)V
       5: aload_0
       6: aload_2
       7: putfield      #3                  // Field peerConfig:Lorg/apache/hadoop/hbase/replication/ReplicationPeerConfig;
      10: aload_0
      11: iload_3
      12: putfield      #4                  // Field enabled:Z
      15: return

  public org.apache.hadoop.hbase.master.procedure.PeerProcedureInterface$PeerOperationType getPeerOperationType();
    Code:
       0: getstatic     #5                  // Field org/apache/hadoop/hbase/master/procedure/PeerProcedureInterface$PeerOperationType.ADD:Lorg/apache/hadoop/hbase/master/procedure/PeerProcedureInterface$PeerOperationType;
       3: areturn

  protected org.apache.hadoop.hbase.shaded.protobuf.generated.MasterProcedureProtos$PeerModificationState nextStateAfterRefresh();
    Code:
       0: aload_0
       1: getfield      #3                  // Field peerConfig:Lorg/apache/hadoop/hbase/replication/ReplicationPeerConfig;
       4: invokevirtual #6                  // Method org/apache/hadoop/hbase/replication/ReplicationPeerConfig.isSerial:()Z
       7: ifeq          16
      10: getstatic     #7                  // Field org/apache/hadoop/hbase/shaded/protobuf/generated/MasterProcedureProtos$PeerModificationState.SERIAL_PEER_REOPEN_REGIONS:Lorg/apache/hadoop/hbase/shaded/protobuf/generated/MasterProcedureProtos$PeerModificationState;
      13: goto          20
      16: aload_0
      17: invokespecial #8                  // Method org/apache/hadoop/hbase/master/replication/ModifyPeerProcedure.nextStateAfterRefresh:()Lorg/apache/hadoop/hbase/shaded/protobuf/generated/MasterProcedureProtos$PeerModificationState;
      20: areturn

  protected void updateLastPushedSequenceIdForSerialPeer(org.apache.hadoop.hbase.master.procedure.MasterProcedureEnv) throws java.io.IOException, org.apache.hadoop.hbase.replication.ReplicationException;
    Code:
       0: aload_0
       1: aload_1
       2: aload_0
       3: getfield      #3                  // Field peerConfig:Lorg/apache/hadoop/hbase/replication/ReplicationPeerConfig;
       6: invokevirtual #9                  // Method setLastPushedSequenceId:(Lorg/apache/hadoop/hbase/master/procedure/MasterProcedureEnv;Lorg/apache/hadoop/hbase/replication/ReplicationPeerConfig;)V
       9: return

  protected boolean enablePeerBeforeFinish();
    Code:
       0: aload_0
       1: getfield      #4                  // Field enabled:Z
       4: ireturn

  protected org.apache.hadoop.hbase.replication.ReplicationPeerConfig getNewPeerConfig();
    Code:
       0: aload_0
       1: getfield      #3                  // Field peerConfig:Lorg/apache/hadoop/hbase/replication/ReplicationPeerConfig;
       4: areturn

  protected void releaseLatch(org.apache.hadoop.hbase.master.procedure.MasterProcedureEnv);
    Code:
       0: aload_0
       1: getfield      #3                  // Field peerConfig:Lorg/apache/hadoop/hbase/replication/ReplicationPeerConfig;
       4: invokevirtual #10                 // Method org/apache/hadoop/hbase/replication/ReplicationPeerConfig.isSyncReplication:()Z
       7: ifeq          17
      10: aload_1
      11: invokevirtual #11                 // Method org/apache/hadoop/hbase/master/procedure/MasterProcedureEnv.getReplicationPeerManager:()Lorg/apache/hadoop/hbase/master/replication/ReplicationPeerManager;
      14: invokevirtual #12                 // Method org/apache/hadoop/hbase/master/replication/ReplicationPeerManager.releaseSyncReplicationPeerLock:()V
      17: aload_0
      18: getfield      #13                 // Field latch:Lorg/apache/hadoop/hbase/master/procedure/ProcedurePrepareLatch;
      21: aload_0
      22: invokestatic  #14                 // Method org/apache/hadoop/hbase/master/procedure/ProcedurePrepareLatch.releaseLatch:(Lorg/apache/hadoop/hbase/master/procedure/ProcedurePrepareLatch;Lorg/apache/hadoop/hbase/procedure2/Procedure;)V
      25: return

  protected void prePeerModification(org.apache.hadoop.hbase.master.procedure.MasterProcedureEnv) throws java.io.IOException, org.apache.hadoop.hbase.replication.ReplicationException, java.lang.InterruptedException;
    Code:
       0: aload_1
       1: invokevirtual #15                 // Method org/apache/hadoop/hbase/master/procedure/MasterProcedureEnv.getMasterCoprocessorHost:()Lorg/apache/hadoop/hbase/master/MasterCoprocessorHost;
       4: astore_2
       5: aload_2
       6: ifnull        21
       9: aload_2
      10: aload_0
      11: getfield      #16                 // Field peerId:Ljava/lang/String;
      14: aload_0
      15: getfield      #3                  // Field peerConfig:Lorg/apache/hadoop/hbase/replication/ReplicationPeerConfig;
      18: invokevirtual #17                 // Method org/apache/hadoop/hbase/master/MasterCoprocessorHost.preAddReplicationPeer:(Ljava/lang/String;Lorg/apache/hadoop/hbase/replication/ReplicationPeerConfig;)V
      21: aload_0
      22: getfield      #3                  // Field peerConfig:Lorg/apache/hadoop/hbase/replication/ReplicationPeerConfig;
      25: invokevirtual #10                 // Method org/apache/hadoop/hbase/replication/ReplicationPeerConfig.isSyncReplication:()Z
      28: ifeq          38
      31: aload_1
      32: invokevirtual #11                 // Method org/apache/hadoop/hbase/master/procedure/MasterProcedureEnv.getReplicationPeerManager:()Lorg/apache/hadoop/hbase/master/replication/ReplicationPeerManager;
      35: invokevirtual #18                 // Method org/apache/hadoop/hbase/master/replication/ReplicationPeerManager.acquireSyncReplicationPeerLock:()V
      38: aload_1
      39: invokevirtual #11                 // Method org/apache/hadoop/hbase/master/procedure/MasterProcedureEnv.getReplicationPeerManager:()Lorg/apache/hadoop/hbase/master/replication/ReplicationPeerManager;
      42: aload_0
      43: getfield      #16                 // Field peerId:Ljava/lang/String;
      46: aload_0
      47: getfield      #3                  // Field peerConfig:Lorg/apache/hadoop/hbase/replication/ReplicationPeerConfig;
      50: invokevirtual #19                 // Method org/apache/hadoop/hbase/master/replication/ReplicationPeerManager.preAddPeer:(Ljava/lang/String;Lorg/apache/hadoop/hbase/replication/ReplicationPeerConfig;)V
      53: return

  protected void updatePeerStorage(org.apache.hadoop.hbase.master.procedure.MasterProcedureEnv) throws org.apache.hadoop.hbase.replication.ReplicationException;
    Code:
       0: aload_1
       1: invokevirtual #11                 // Method org/apache/hadoop/hbase/master/procedure/MasterProcedureEnv.getReplicationPeerManager:()Lorg/apache/hadoop/hbase/master/replication/ReplicationPeerManager;
       4: aload_0
       5: getfield      #16                 // Field peerId:Ljava/lang/String;
       8: aload_0
       9: getfield      #3                  // Field peerConfig:Lorg/apache/hadoop/hbase/replication/ReplicationPeerConfig;
      12: aload_0
      13: getfield      #3                  // Field peerConfig:Lorg/apache/hadoop/hbase/replication/ReplicationPeerConfig;
      16: invokevirtual #6                  // Method org/apache/hadoop/hbase/replication/ReplicationPeerConfig.isSerial:()Z
      19: ifeq          26
      22: iconst_0
      23: goto          30
      26: aload_0
      27: getfield      #4                  // Field enabled:Z
      30: invokevirtual #20                 // Method org/apache/hadoop/hbase/master/replication/ReplicationPeerManager.addPeer:(Ljava/lang/String;Lorg/apache/hadoop/hbase/replication/ReplicationPeerConfig;Z)V
      33: return

  protected void postPeerModification(org.apache.hadoop.hbase.master.procedure.MasterProcedureEnv) throws java.io.IOException, org.apache.hadoop.hbase.replication.ReplicationException;
    Code:
       0: getstatic     #21                 // Field LOG:Lorg/slf4j/Logger;
       3: ldc           #22                 // String Successfully added {} peer {}, config {}
       5: iconst_3
       6: anewarray     #23                 // class java/lang/Object
       9: dup
      10: iconst_0
      11: aload_0
      12: getfield      #4                  // Field enabled:Z
      15: ifeq          23
      18: ldc           #24                 // String ENABLED
      20: goto          25
      23: ldc           #25                 // String DISABLED
      25: aastore
      26: dup
      27: iconst_1
      28: aload_0
      29: getfield      #16                 // Field peerId:Ljava/lang/String;
      32: aastore
      33: dup
      34: iconst_2
      35: aload_0
      36: getfield      #3                  // Field peerConfig:Lorg/apache/hadoop/hbase/replication/ReplicationPeerConfig;
      39: aastore
      40: invokeinterface #26,  3           // InterfaceMethod org/slf4j/Logger.info:(Ljava/lang/String;[Ljava/lang/Object;)V
      45: aload_1
      46: invokevirtual #15                 // Method org/apache/hadoop/hbase/master/procedure/MasterProcedureEnv.getMasterCoprocessorHost:()Lorg/apache/hadoop/hbase/master/MasterCoprocessorHost;
      49: astore_2
      50: aload_2
      51: ifnull        69
      54: aload_1
      55: invokevirtual #15                 // Method org/apache/hadoop/hbase/master/procedure/MasterProcedureEnv.getMasterCoprocessorHost:()Lorg/apache/hadoop/hbase/master/MasterCoprocessorHost;
      58: aload_0
      59: getfield      #16                 // Field peerId:Ljava/lang/String;
      62: aload_0
      63: getfield      #3                  // Field peerConfig:Lorg/apache/hadoop/hbase/replication/ReplicationPeerConfig;
      66: invokevirtual #27                 // Method org/apache/hadoop/hbase/master/MasterCoprocessorHost.postAddReplicationPeer:(Ljava/lang/String;Lorg/apache/hadoop/hbase/replication/ReplicationPeerConfig;)V
      69: return

  protected void serializeStateData(org.apache.hadoop.hbase.procedure2.ProcedureStateSerializer) throws java.io.IOException;
    Code:
       0: aload_0
       1: aload_1
       2: invokespecial #28                 // Method org/apache/hadoop/hbase/master/replication/ModifyPeerProcedure.serializeStateData:(Lorg/apache/hadoop/hbase/procedure2/ProcedureStateSerializer;)V
       5: aload_1
       6: invokestatic  #29                 // Method org/apache/hadoop/hbase/shaded/protobuf/generated/MasterProcedureProtos$AddPeerStateData.newBuilder:()Lorg/apache/hadoop/hbase/shaded/protobuf/generated/MasterProcedureProtos$AddPeerStateData$Builder;
       9: aload_0
      10: getfield      #3                  // Field peerConfig:Lorg/apache/hadoop/hbase/replication/ReplicationPeerConfig;
      13: invokestatic  #30                 // Method org/apache/hadoop/hbase/client/replication/ReplicationPeerConfigUtil.convert:(Lorg/apache/hadoop/hbase/replication/ReplicationPeerConfig;)Lorg/apache/hadoop/hbase/shaded/protobuf/generated/ReplicationProtos$ReplicationPeer;
      16: invokevirtual #31                 // Method org/apache/hadoop/hbase/shaded/protobuf/generated/MasterProcedureProtos$AddPeerStateData$Builder.setPeerConfig:(Lorg/apache/hadoop/hbase/shaded/protobuf/generated/ReplicationProtos$ReplicationPeer;)Lorg/apache/hadoop/hbase/shaded/protobuf/generated/MasterProcedureProtos$AddPeerStateData$Builder;
      19: aload_0
      20: getfield      #4                  // Field enabled:Z
      23: invokevirtual #32                 // Method org/apache/hadoop/hbase/shaded/protobuf/generated/MasterProcedureProtos$AddPeerStateData$Builder.setEnabled:(Z)Lorg/apache/hadoop/hbase/shaded/protobuf/generated/MasterProcedureProtos$AddPeerStateData$Builder;
      26: invokevirtual #33                 // Method org/apache/hadoop/hbase/shaded/protobuf/generated/MasterProcedureProtos$AddPeerStateData$Builder.build:()Lorg/apache/hadoop/hbase/shaded/protobuf/generated/MasterProcedureProtos$AddPeerStateData;
      29: invokeinterface #34,  2           // InterfaceMethod org/apache/hadoop/hbase/procedure2/ProcedureStateSerializer.serialize:(Lorg/apache/hbase/thirdparty/com/google/protobuf/Message;)V
      34: return

  protected void deserializeStateData(org.apache.hadoop.hbase.procedure2.ProcedureStateSerializer) throws java.io.IOException;
    Code:
       0: aload_0
       1: aload_1
       2: invokespecial #35                 // Method org/apache/hadoop/hbase/master/replication/ModifyPeerProcedure.deserializeStateData:(Lorg/apache/hadoop/hbase/procedure2/ProcedureStateSerializer;)V
       5: aload_1
       6: ldc           #36                 // class org/apache/hadoop/hbase/shaded/protobuf/generated/MasterProcedureProtos$AddPeerStateData
       8: invokeinterface #37,  2           // InterfaceMethod org/apache/hadoop/hbase/procedure2/ProcedureStateSerializer.deserialize:(Ljava/lang/Class;)Lorg/apache/hbase/thirdparty/com/google/protobuf/Message;
      13: checkcast     #36                 // class org/apache/hadoop/hbase/shaded/protobuf/generated/MasterProcedureProtos$AddPeerStateData
      16: astore_2
      17: aload_0
      18: aload_2
      19: invokevirtual #38                 // Method org/apache/hadoop/hbase/shaded/protobuf/generated/MasterProcedureProtos$AddPeerStateData.getPeerConfig:()Lorg/apache/hadoop/hbase/shaded/protobuf/generated/ReplicationProtos$ReplicationPeer;
      22: invokestatic  #39                 // Method org/apache/hadoop/hbase/client/replication/ReplicationPeerConfigUtil.convert:(Lorg/apache/hadoop/hbase/shaded/protobuf/generated/ReplicationProtos$ReplicationPeer;)Lorg/apache/hadoop/hbase/replication/ReplicationPeerConfig;
      25: putfield      #3                  // Field peerConfig:Lorg/apache/hadoop/hbase/replication/ReplicationPeerConfig;
      28: aload_0
      29: aload_2
      30: invokevirtual #40                 // Method org/apache/hadoop/hbase/shaded/protobuf/generated/MasterProcedureProtos$AddPeerStateData.getEnabled:()Z
      33: putfield      #4                  // Field enabled:Z
      36: return

  static {};
    Code:
       0: ldc           #41                 // class org/apache/hadoop/hbase/master/replication/AddPeerProcedure
       2: invokestatic  #42                 // Method org/slf4j/LoggerFactory.getLogger:(Ljava/lang/Class;)Lorg/slf4j/Logger;
       5: putstatic     #21                 // Field LOG:Lorg/slf4j/Logger;
       8: return
}
