Compiled from "AdminProtos.java"
final class org.apache.hadoop.hbase.protobuf.generated.AdminProtos$AdminService$2 implements com.google.protobuf.BlockingService {
  final org.apache.hadoop.hbase.protobuf.generated.AdminProtos$AdminService$BlockingInterface val$impl;

  org.apache.hadoop.hbase.protobuf.generated.AdminProtos$AdminService$2(org.apache.hadoop.hbase.protobuf.generated.AdminProtos$AdminService$BlockingInterface);
    Code:
       0: aload_0
       1: aload_1
       2: putfield      #1                  // Field val$impl:Lorg/apache/hadoop/hbase/protobuf/generated/AdminProtos$AdminService$BlockingInterface;
       5: aload_0
       6: invokespecial #2                  // Method java/lang/Object."<init>":()V
       9: return

  public final com.google.protobuf.Descriptors$ServiceDescriptor getDescriptorForType();
    Code:
       0: invokestatic  #3                  // Method org/apache/hadoop/hbase/protobuf/generated/AdminProtos$AdminService.getDescriptor:()Lcom/google/protobuf/Descriptors$ServiceDescriptor;
       3: areturn

  public final com.google.protobuf.Message callBlockingMethod(com.google.protobuf.Descriptors$MethodDescriptor, com.google.protobuf.RpcController, com.google.protobuf.Message) throws com.google.protobuf.ServiceException;
    Code:
       0: aload_1
       1: invokevirtual #4                  // Method com/google/protobuf/Descriptors$MethodDescriptor.getService:()Lcom/google/protobuf/Descriptors$ServiceDescriptor;
       4: invokestatic  #3                  // Method org/apache/hadoop/hbase/protobuf/generated/AdminProtos$AdminService.getDescriptor:()Lcom/google/protobuf/Descriptors$ServiceDescriptor;
       7: if_acmpeq     20
      10: new           #5                  // class java/lang/IllegalArgumentException
      13: dup
      14: ldc           #6                  // String Service.callBlockingMethod() given method descriptor for wrong service type.
      16: invokespecial #7                  // Method java/lang/IllegalArgumentException."<init>":(Ljava/lang/String;)V
      19: athrow
      20: aload_1
      21: invokevirtual #8                  // Method com/google/protobuf/Descriptors$MethodDescriptor.getIndex:()I
      24: tableswitch   { // 0 to 16
                     0: 108
                     1: 123
                     2: 138
                     3: 153
                     4: 168
                     5: 183
                     6: 198
                     7: 213
                     8: 228
                     9: 243
                    10: 258
                    11: 273
                    12: 288
                    13: 303
                    14: 318
                    15: 333
                    16: 348
               default: 363
          }
     108: aload_0
     109: getfield      #1                  // Field val$impl:Lorg/apache/hadoop/hbase/protobuf/generated/AdminProtos$AdminService$BlockingInterface;
     112: aload_2
     113: aload_3
     114: checkcast     #9                  // class org/apache/hadoop/hbase/protobuf/generated/AdminProtos$GetRegionInfoRequest
     117: invokeinterface #10,  3           // InterfaceMethod org/apache/hadoop/hbase/protobuf/generated/AdminProtos$AdminService$BlockingInterface.getRegionInfo:(Lcom/google/protobuf/RpcController;Lorg/apache/hadoop/hbase/protobuf/generated/AdminProtos$GetRegionInfoRequest;)Lorg/apache/hadoop/hbase/protobuf/generated/AdminProtos$GetRegionInfoResponse;
     122: areturn
     123: aload_0
     124: getfield      #1                  // Field val$impl:Lorg/apache/hadoop/hbase/protobuf/generated/AdminProtos$AdminService$BlockingInterface;
     127: aload_2
     128: aload_3
     129: checkcast     #11                 // class org/apache/hadoop/hbase/protobuf/generated/AdminProtos$GetStoreFileRequest
     132: invokeinterface #12,  3           // InterfaceMethod org/apache/hadoop/hbase/protobuf/generated/AdminProtos$AdminService$BlockingInterface.getStoreFile:(Lcom/google/protobuf/RpcController;Lorg/apache/hadoop/hbase/protobuf/generated/AdminProtos$GetStoreFileRequest;)Lorg/apache/hadoop/hbase/protobuf/generated/AdminProtos$GetStoreFileResponse;
     137: areturn
     138: aload_0
     139: getfield      #1                  // Field val$impl:Lorg/apache/hadoop/hbase/protobuf/generated/AdminProtos$AdminService$BlockingInterface;
     142: aload_2
     143: aload_3
     144: checkcast     #13                 // class org/apache/hadoop/hbase/protobuf/generated/AdminProtos$GetOnlineRegionRequest
     147: invokeinterface #14,  3           // InterfaceMethod org/apache/hadoop/hbase/protobuf/generated/AdminProtos$AdminService$BlockingInterface.getOnlineRegion:(Lcom/google/protobuf/RpcController;Lorg/apache/hadoop/hbase/protobuf/generated/AdminProtos$GetOnlineRegionRequest;)Lorg/apache/hadoop/hbase/protobuf/generated/AdminProtos$GetOnlineRegionResponse;
     152: areturn
     153: aload_0
     154: getfield      #1                  // Field val$impl:Lorg/apache/hadoop/hbase/protobuf/generated/AdminProtos$AdminService$BlockingInterface;
     157: aload_2
     158: aload_3
     159: checkcast     #15                 // class org/apache/hadoop/hbase/protobuf/generated/AdminProtos$OpenRegionRequest
     162: invokeinterface #16,  3           // InterfaceMethod org/apache/hadoop/hbase/protobuf/generated/AdminProtos$AdminService$BlockingInterface.openRegion:(Lcom/google/protobuf/RpcController;Lorg/apache/hadoop/hbase/protobuf/generated/AdminProtos$OpenRegionRequest;)Lorg/apache/hadoop/hbase/protobuf/generated/AdminProtos$OpenRegionResponse;
     167: areturn
     168: aload_0
     169: getfield      #1                  // Field val$impl:Lorg/apache/hadoop/hbase/protobuf/generated/AdminProtos$AdminService$BlockingInterface;
     172: aload_2
     173: aload_3
     174: checkcast     #17                 // class org/apache/hadoop/hbase/protobuf/generated/AdminProtos$WarmupRegionRequest
     177: invokeinterface #18,  3           // InterfaceMethod org/apache/hadoop/hbase/protobuf/generated/AdminProtos$AdminService$BlockingInterface.warmupRegion:(Lcom/google/protobuf/RpcController;Lorg/apache/hadoop/hbase/protobuf/generated/AdminProtos$WarmupRegionRequest;)Lorg/apache/hadoop/hbase/protobuf/generated/AdminProtos$WarmupRegionResponse;
     182: areturn
     183: aload_0
     184: getfield      #1                  // Field val$impl:Lorg/apache/hadoop/hbase/protobuf/generated/AdminProtos$AdminService$BlockingInterface;
     187: aload_2
     188: aload_3
     189: checkcast     #19                 // class org/apache/hadoop/hbase/protobuf/generated/AdminProtos$CloseRegionRequest
     192: invokeinterface #20,  3           // InterfaceMethod org/apache/hadoop/hbase/protobuf/generated/AdminProtos$AdminService$BlockingInterface.closeRegion:(Lcom/google/protobuf/RpcController;Lorg/apache/hadoop/hbase/protobuf/generated/AdminProtos$CloseRegionRequest;)Lorg/apache/hadoop/hbase/protobuf/generated/AdminProtos$CloseRegionResponse;
     197: areturn
     198: aload_0
     199: getfield      #1                  // Field val$impl:Lorg/apache/hadoop/hbase/protobuf/generated/AdminProtos$AdminService$BlockingInterface;
     202: aload_2
     203: aload_3
     204: checkcast     #21                 // class org/apache/hadoop/hbase/protobuf/generated/AdminProtos$FlushRegionRequest
     207: invokeinterface #22,  3           // InterfaceMethod org/apache/hadoop/hbase/protobuf/generated/AdminProtos$AdminService$BlockingInterface.flushRegion:(Lcom/google/protobuf/RpcController;Lorg/apache/hadoop/hbase/protobuf/generated/AdminProtos$FlushRegionRequest;)Lorg/apache/hadoop/hbase/protobuf/generated/AdminProtos$FlushRegionResponse;
     212: areturn
     213: aload_0
     214: getfield      #1                  // Field val$impl:Lorg/apache/hadoop/hbase/protobuf/generated/AdminProtos$AdminService$BlockingInterface;
     217: aload_2
     218: aload_3
     219: checkcast     #23                 // class org/apache/hadoop/hbase/protobuf/generated/AdminProtos$SplitRegionRequest
     222: invokeinterface #24,  3           // InterfaceMethod org/apache/hadoop/hbase/protobuf/generated/AdminProtos$AdminService$BlockingInterface.splitRegion:(Lcom/google/protobuf/RpcController;Lorg/apache/hadoop/hbase/protobuf/generated/AdminProtos$SplitRegionRequest;)Lorg/apache/hadoop/hbase/protobuf/generated/AdminProtos$SplitRegionResponse;
     227: areturn
     228: aload_0
     229: getfield      #1                  // Field val$impl:Lorg/apache/hadoop/hbase/protobuf/generated/AdminProtos$AdminService$BlockingInterface;
     232: aload_2
     233: aload_3
     234: checkcast     #25                 // class org/apache/hadoop/hbase/protobuf/generated/AdminProtos$CompactRegionRequest
     237: invokeinterface #26,  3           // InterfaceMethod org/apache/hadoop/hbase/protobuf/generated/AdminProtos$AdminService$BlockingInterface.compactRegion:(Lcom/google/protobuf/RpcController;Lorg/apache/hadoop/hbase/protobuf/generated/AdminProtos$CompactRegionRequest;)Lorg/apache/hadoop/hbase/protobuf/generated/AdminProtos$CompactRegionResponse;
     242: areturn
     243: aload_0
     244: getfield      #1                  // Field val$impl:Lorg/apache/hadoop/hbase/protobuf/generated/AdminProtos$AdminService$BlockingInterface;
     247: aload_2
     248: aload_3
     249: checkcast     #27                 // class org/apache/hadoop/hbase/protobuf/generated/AdminProtos$MergeRegionsRequest
     252: invokeinterface #28,  3           // InterfaceMethod org/apache/hadoop/hbase/protobuf/generated/AdminProtos$AdminService$BlockingInterface.mergeRegions:(Lcom/google/protobuf/RpcController;Lorg/apache/hadoop/hbase/protobuf/generated/AdminProtos$MergeRegionsRequest;)Lorg/apache/hadoop/hbase/protobuf/generated/AdminProtos$MergeRegionsResponse;
     257: areturn
     258: aload_0
     259: getfield      #1                  // Field val$impl:Lorg/apache/hadoop/hbase/protobuf/generated/AdminProtos$AdminService$BlockingInterface;
     262: aload_2
     263: aload_3
     264: checkcast     #29                 // class org/apache/hadoop/hbase/protobuf/generated/AdminProtos$ReplicateWALEntryRequest
     267: invokeinterface #30,  3           // InterfaceMethod org/apache/hadoop/hbase/protobuf/generated/AdminProtos$AdminService$BlockingInterface.replicateWALEntry:(Lcom/google/protobuf/RpcController;Lorg/apache/hadoop/hbase/protobuf/generated/AdminProtos$ReplicateWALEntryRequest;)Lorg/apache/hadoop/hbase/protobuf/generated/AdminProtos$ReplicateWALEntryResponse;
     272: areturn
     273: aload_0
     274: getfield      #1                  // Field val$impl:Lorg/apache/hadoop/hbase/protobuf/generated/AdminProtos$AdminService$BlockingInterface;
     277: aload_2
     278: aload_3
     279: checkcast     #29                 // class org/apache/hadoop/hbase/protobuf/generated/AdminProtos$ReplicateWALEntryRequest
     282: invokeinterface #31,  3           // InterfaceMethod org/apache/hadoop/hbase/protobuf/generated/AdminProtos$AdminService$BlockingInterface.replay:(Lcom/google/protobuf/RpcController;Lorg/apache/hadoop/hbase/protobuf/generated/AdminProtos$ReplicateWALEntryRequest;)Lorg/apache/hadoop/hbase/protobuf/generated/AdminProtos$ReplicateWALEntryResponse;
     287: areturn
     288: aload_0
     289: getfield      #1                  // Field val$impl:Lorg/apache/hadoop/hbase/protobuf/generated/AdminProtos$AdminService$BlockingInterface;
     292: aload_2
     293: aload_3
     294: checkcast     #32                 // class org/apache/hadoop/hbase/protobuf/generated/AdminProtos$RollWALWriterRequest
     297: invokeinterface #33,  3           // InterfaceMethod org/apache/hadoop/hbase/protobuf/generated/AdminProtos$AdminService$BlockingInterface.rollWALWriter:(Lcom/google/protobuf/RpcController;Lorg/apache/hadoop/hbase/protobuf/generated/AdminProtos$RollWALWriterRequest;)Lorg/apache/hadoop/hbase/protobuf/generated/AdminProtos$RollWALWriterResponse;
     302: areturn
     303: aload_0
     304: getfield      #1                  // Field val$impl:Lorg/apache/hadoop/hbase/protobuf/generated/AdminProtos$AdminService$BlockingInterface;
     307: aload_2
     308: aload_3
     309: checkcast     #34                 // class org/apache/hadoop/hbase/protobuf/generated/AdminProtos$GetServerInfoRequest
     312: invokeinterface #35,  3           // InterfaceMethod org/apache/hadoop/hbase/protobuf/generated/AdminProtos$AdminService$BlockingInterface.getServerInfo:(Lcom/google/protobuf/RpcController;Lorg/apache/hadoop/hbase/protobuf/generated/AdminProtos$GetServerInfoRequest;)Lorg/apache/hadoop/hbase/protobuf/generated/AdminProtos$GetServerInfoResponse;
     317: areturn
     318: aload_0
     319: getfield      #1                  // Field val$impl:Lorg/apache/hadoop/hbase/protobuf/generated/AdminProtos$AdminService$BlockingInterface;
     322: aload_2
     323: aload_3
     324: checkcast     #36                 // class org/apache/hadoop/hbase/protobuf/generated/AdminProtos$StopServerRequest
     327: invokeinterface #37,  3           // InterfaceMethod org/apache/hadoop/hbase/protobuf/generated/AdminProtos$AdminService$BlockingInterface.stopServer:(Lcom/google/protobuf/RpcController;Lorg/apache/hadoop/hbase/protobuf/generated/AdminProtos$StopServerRequest;)Lorg/apache/hadoop/hbase/protobuf/generated/AdminProtos$StopServerResponse;
     332: areturn
     333: aload_0
     334: getfield      #1                  // Field val$impl:Lorg/apache/hadoop/hbase/protobuf/generated/AdminProtos$AdminService$BlockingInterface;
     337: aload_2
     338: aload_3
     339: checkcast     #38                 // class org/apache/hadoop/hbase/protobuf/generated/AdminProtos$UpdateFavoredNodesRequest
     342: invokeinterface #39,  3           // InterfaceMethod org/apache/hadoop/hbase/protobuf/generated/AdminProtos$AdminService$BlockingInterface.updateFavoredNodes:(Lcom/google/protobuf/RpcController;Lorg/apache/hadoop/hbase/protobuf/generated/AdminProtos$UpdateFavoredNodesRequest;)Lorg/apache/hadoop/hbase/protobuf/generated/AdminProtos$UpdateFavoredNodesResponse;
     347: areturn
     348: aload_0
     349: getfield      #1                  // Field val$impl:Lorg/apache/hadoop/hbase/protobuf/generated/AdminProtos$AdminService$BlockingInterface;
     352: aload_2
     353: aload_3
     354: checkcast     #40                 // class org/apache/hadoop/hbase/protobuf/generated/AdminProtos$UpdateConfigurationRequest
     357: invokeinterface #41,  3           // InterfaceMethod org/apache/hadoop/hbase/protobuf/generated/AdminProtos$AdminService$BlockingInterface.updateConfiguration:(Lcom/google/protobuf/RpcController;Lorg/apache/hadoop/hbase/protobuf/generated/AdminProtos$UpdateConfigurationRequest;)Lorg/apache/hadoop/hbase/protobuf/generated/AdminProtos$UpdateConfigurationResponse;
     362: areturn
     363: new           #42                 // class java/lang/AssertionError
     366: dup
     367: ldc           #43                 // String Can't get here.
     369: invokespecial #44                 // Method java/lang/AssertionError."<init>":(Ljava/lang/Object;)V
     372: athrow

  public final com.google.protobuf.Message getRequestPrototype(com.google.protobuf.Descriptors$MethodDescriptor);
    Code:
       0: aload_1
       1: invokevirtual #4                  // Method com/google/protobuf/Descriptors$MethodDescriptor.getService:()Lcom/google/protobuf/Descriptors$ServiceDescriptor;
       4: invokestatic  #3                  // Method org/apache/hadoop/hbase/protobuf/generated/AdminProtos$AdminService.getDescriptor:()Lcom/google/protobuf/Descriptors$ServiceDescriptor;
       7: if_acmpeq     20
      10: new           #5                  // class java/lang/IllegalArgumentException
      13: dup
      14: ldc           #45                 // String Service.getRequestPrototype() given method descriptor for wrong service type.
      16: invokespecial #7                  // Method java/lang/IllegalArgumentException."<init>":(Ljava/lang/String;)V
      19: athrow
      20: aload_1
      21: invokevirtual #8                  // Method com/google/protobuf/Descriptors$MethodDescriptor.getIndex:()I
      24: tableswitch   { // 0 to 16
                     0: 108
                     1: 112
                     2: 116
                     3: 120
                     4: 124
                     5: 128
                     6: 132
                     7: 136
                     8: 140
                     9: 144
                    10: 148
                    11: 152
                    12: 156
                    13: 160
                    14: 164
                    15: 168
                    16: 172
               default: 176
          }
     108: invokestatic  #46                 // Method org/apache/hadoop/hbase/protobuf/generated/AdminProtos$GetRegionInfoRequest.getDefaultInstance:()Lorg/apache/hadoop/hbase/protobuf/generated/AdminProtos$GetRegionInfoRequest;
     111: areturn
     112: invokestatic  #47                 // Method org/apache/hadoop/hbase/protobuf/generated/AdminProtos$GetStoreFileRequest.getDefaultInstance:()Lorg/apache/hadoop/hbase/protobuf/generated/AdminProtos$GetStoreFileRequest;
     115: areturn
     116: invokestatic  #48                 // Method org/apache/hadoop/hbase/protobuf/generated/AdminProtos$GetOnlineRegionRequest.getDefaultInstance:()Lorg/apache/hadoop/hbase/protobuf/generated/AdminProtos$GetOnlineRegionRequest;
     119: areturn
     120: invokestatic  #49                 // Method org/apache/hadoop/hbase/protobuf/generated/AdminProtos$OpenRegionRequest.getDefaultInstance:()Lorg/apache/hadoop/hbase/protobuf/generated/AdminProtos$OpenRegionRequest;
     123: areturn
     124: invokestatic  #50                 // Method org/apache/hadoop/hbase/protobuf/generated/AdminProtos$WarmupRegionRequest.getDefaultInstance:()Lorg/apache/hadoop/hbase/protobuf/generated/AdminProtos$WarmupRegionRequest;
     127: areturn
     128: invokestatic  #51                 // Method org/apache/hadoop/hbase/protobuf/generated/AdminProtos$CloseRegionRequest.getDefaultInstance:()Lorg/apache/hadoop/hbase/protobuf/generated/AdminProtos$CloseRegionRequest;
     131: areturn
     132: invokestatic  #52                 // Method org/apache/hadoop/hbase/protobuf/generated/AdminProtos$FlushRegionRequest.getDefaultInstance:()Lorg/apache/hadoop/hbase/protobuf/generated/AdminProtos$FlushRegionRequest;
     135: areturn
     136: invokestatic  #53                 // Method org/apache/hadoop/hbase/protobuf/generated/AdminProtos$SplitRegionRequest.getDefaultInstance:()Lorg/apache/hadoop/hbase/protobuf/generated/AdminProtos$SplitRegionRequest;
     139: areturn
     140: invokestatic  #54                 // Method org/apache/hadoop/hbase/protobuf/generated/AdminProtos$CompactRegionRequest.getDefaultInstance:()Lorg/apache/hadoop/hbase/protobuf/generated/AdminProtos$CompactRegionRequest;
     143: areturn
     144: invokestatic  #55                 // Method org/apache/hadoop/hbase/protobuf/generated/AdminProtos$MergeRegionsRequest.getDefaultInstance:()Lorg/apache/hadoop/hbase/protobuf/generated/AdminProtos$MergeRegionsRequest;
     147: areturn
     148: invokestatic  #56                 // Method org/apache/hadoop/hbase/protobuf/generated/AdminProtos$ReplicateWALEntryRequest.getDefaultInstance:()Lorg/apache/hadoop/hbase/protobuf/generated/AdminProtos$ReplicateWALEntryRequest;
     151: areturn
     152: invokestatic  #56                 // Method org/apache/hadoop/hbase/protobuf/generated/AdminProtos$ReplicateWALEntryRequest.getDefaultInstance:()Lorg/apache/hadoop/hbase/protobuf/generated/AdminProtos$ReplicateWALEntryRequest;
     155: areturn
     156: invokestatic  #57                 // Method org/apache/hadoop/hbase/protobuf/generated/AdminProtos$RollWALWriterRequest.getDefaultInstance:()Lorg/apache/hadoop/hbase/protobuf/generated/AdminProtos$RollWALWriterRequest;
     159: areturn
     160: invokestatic  #58                 // Method org/apache/hadoop/hbase/protobuf/generated/AdminProtos$GetServerInfoRequest.getDefaultInstance:()Lorg/apache/hadoop/hbase/protobuf/generated/AdminProtos$GetServerInfoRequest;
     163: areturn
     164: invokestatic  #59                 // Method org/apache/hadoop/hbase/protobuf/generated/AdminProtos$StopServerRequest.getDefaultInstance:()Lorg/apache/hadoop/hbase/protobuf/generated/AdminProtos$StopServerRequest;
     167: areturn
     168: invokestatic  #60                 // Method org/apache/hadoop/hbase/protobuf/generated/AdminProtos$UpdateFavoredNodesRequest.getDefaultInstance:()Lorg/apache/hadoop/hbase/protobuf/generated/AdminProtos$UpdateFavoredNodesRequest;
     171: areturn
     172: invokestatic  #61                 // Method org/apache/hadoop/hbase/protobuf/generated/AdminProtos$UpdateConfigurationRequest.getDefaultInstance:()Lorg/apache/hadoop/hbase/protobuf/generated/AdminProtos$UpdateConfigurationRequest;
     175: areturn
     176: new           #42                 // class java/lang/AssertionError
     179: dup
     180: ldc           #43                 // String Can't get here.
     182: invokespecial #44                 // Method java/lang/AssertionError."<init>":(Ljava/lang/Object;)V
     185: athrow

  public final com.google.protobuf.Message getResponsePrototype(com.google.protobuf.Descriptors$MethodDescriptor);
    Code:
       0: aload_1
       1: invokevirtual #4                  // Method com/google/protobuf/Descriptors$MethodDescriptor.getService:()Lcom/google/protobuf/Descriptors$ServiceDescriptor;
       4: invokestatic  #3                  // Method org/apache/hadoop/hbase/protobuf/generated/AdminProtos$AdminService.getDescriptor:()Lcom/google/protobuf/Descriptors$ServiceDescriptor;
       7: if_acmpeq     20
      10: new           #5                  // class java/lang/IllegalArgumentException
      13: dup
      14: ldc           #62                 // String Service.getResponsePrototype() given method descriptor for wrong service type.
      16: invokespecial #7                  // Method java/lang/IllegalArgumentException."<init>":(Ljava/lang/String;)V
      19: athrow
      20: aload_1
      21: invokevirtual #8                  // Method com/google/protobuf/Descriptors$MethodDescriptor.getIndex:()I
      24: tableswitch   { // 0 to 16
                     0: 108
                     1: 112
                     2: 116
                     3: 120
                     4: 124
                     5: 128
                     6: 132
                     7: 136
                     8: 140
                     9: 144
                    10: 148
                    11: 152
                    12: 156
                    13: 160
                    14: 164
                    15: 168
                    16: 172
               default: 176
          }
     108: invokestatic  #63                 // Method org/apache/hadoop/hbase/protobuf/generated/AdminProtos$GetRegionInfoResponse.getDefaultInstance:()Lorg/apache/hadoop/hbase/protobuf/generated/AdminProtos$GetRegionInfoResponse;
     111: areturn
     112: invokestatic  #64                 // Method org/apache/hadoop/hbase/protobuf/generated/AdminProtos$GetStoreFileResponse.getDefaultInstance:()Lorg/apache/hadoop/hbase/protobuf/generated/AdminProtos$GetStoreFileResponse;
     115: areturn
     116: invokestatic  #65                 // Method org/apache/hadoop/hbase/protobuf/generated/AdminProtos$GetOnlineRegionResponse.getDefaultInstance:()Lorg/apache/hadoop/hbase/protobuf/generated/AdminProtos$GetOnlineRegionResponse;
     119: areturn
     120: invokestatic  #66                 // Method org/apache/hadoop/hbase/protobuf/generated/AdminProtos$OpenRegionResponse.getDefaultInstance:()Lorg/apache/hadoop/hbase/protobuf/generated/AdminProtos$OpenRegionResponse;
     123: areturn
     124: invokestatic  #67                 // Method org/apache/hadoop/hbase/protobuf/generated/AdminProtos$WarmupRegionResponse.getDefaultInstance:()Lorg/apache/hadoop/hbase/protobuf/generated/AdminProtos$WarmupRegionResponse;
     127: areturn
     128: invokestatic  #68                 // Method org/apache/hadoop/hbase/protobuf/generated/AdminProtos$CloseRegionResponse.getDefaultInstance:()Lorg/apache/hadoop/hbase/protobuf/generated/AdminProtos$CloseRegionResponse;
     131: areturn
     132: invokestatic  #69                 // Method org/apache/hadoop/hbase/protobuf/generated/AdminProtos$FlushRegionResponse.getDefaultInstance:()Lorg/apache/hadoop/hbase/protobuf/generated/AdminProtos$FlushRegionResponse;
     135: areturn
     136: invokestatic  #70                 // Method org/apache/hadoop/hbase/protobuf/generated/AdminProtos$SplitRegionResponse.getDefaultInstance:()Lorg/apache/hadoop/hbase/protobuf/generated/AdminProtos$SplitRegionResponse;
     139: areturn
     140: invokestatic  #71                 // Method org/apache/hadoop/hbase/protobuf/generated/AdminProtos$CompactRegionResponse.getDefaultInstance:()Lorg/apache/hadoop/hbase/protobuf/generated/AdminProtos$CompactRegionResponse;
     143: areturn
     144: invokestatic  #72                 // Method org/apache/hadoop/hbase/protobuf/generated/AdminProtos$MergeRegionsResponse.getDefaultInstance:()Lorg/apache/hadoop/hbase/protobuf/generated/AdminProtos$MergeRegionsResponse;
     147: areturn
     148: invokestatic  #73                 // Method org/apache/hadoop/hbase/protobuf/generated/AdminProtos$ReplicateWALEntryResponse.getDefaultInstance:()Lorg/apache/hadoop/hbase/protobuf/generated/AdminProtos$ReplicateWALEntryResponse;
     151: areturn
     152: invokestatic  #73                 // Method org/apache/hadoop/hbase/protobuf/generated/AdminProtos$ReplicateWALEntryResponse.getDefaultInstance:()Lorg/apache/hadoop/hbase/protobuf/generated/AdminProtos$ReplicateWALEntryResponse;
     155: areturn
     156: invokestatic  #74                 // Method org/apache/hadoop/hbase/protobuf/generated/AdminProtos$RollWALWriterResponse.getDefaultInstance:()Lorg/apache/hadoop/hbase/protobuf/generated/AdminProtos$RollWALWriterResponse;
     159: areturn
     160: invokestatic  #75                 // Method org/apache/hadoop/hbase/protobuf/generated/AdminProtos$GetServerInfoResponse.getDefaultInstance:()Lorg/apache/hadoop/hbase/protobuf/generated/AdminProtos$GetServerInfoResponse;
     163: areturn
     164: invokestatic  #76                 // Method org/apache/hadoop/hbase/protobuf/generated/AdminProtos$StopServerResponse.getDefaultInstance:()Lorg/apache/hadoop/hbase/protobuf/generated/AdminProtos$StopServerResponse;
     167: areturn
     168: invokestatic  #77                 // Method org/apache/hadoop/hbase/protobuf/generated/AdminProtos$UpdateFavoredNodesResponse.getDefaultInstance:()Lorg/apache/hadoop/hbase/protobuf/generated/AdminProtos$UpdateFavoredNodesResponse;
     171: areturn
     172: invokestatic  #78                 // Method org/apache/hadoop/hbase/protobuf/generated/AdminProtos$UpdateConfigurationResponse.getDefaultInstance:()Lorg/apache/hadoop/hbase/protobuf/generated/AdminProtos$UpdateConfigurationResponse;
     175: areturn
     176: new           #42                 // class java/lang/AssertionError
     179: dup
     180: ldc           #43                 // String Can't get here.
     182: invokespecial #44                 // Method java/lang/AssertionError."<init>":(Ljava/lang/Object;)V
     185: athrow
}
