Compiled from "AdminProtos.java"
final class org.apache.hadoop.hbase.protobuf.generated.AdminProtos$AdminService$BlockingStub implements org.apache.hadoop.hbase.protobuf.generated.AdminProtos$AdminService$BlockingInterface {
  public org.apache.hadoop.hbase.protobuf.generated.AdminProtos$GetRegionInfoResponse getRegionInfo(com.google.protobuf.RpcController, org.apache.hadoop.hbase.protobuf.generated.AdminProtos$GetRegionInfoRequest) throws com.google.protobuf.ServiceException;
    Code:
       0: aload_0
       1: getfield      #3                  // Field channel:Lcom/google/protobuf/BlockingRpcChannel;
       4: invokestatic  #4                  // Method org/apache/hadoop/hbase/protobuf/generated/AdminProtos$AdminService.getDescriptor:()Lcom/google/protobuf/Descriptors$ServiceDescriptor;
       7: invokevirtual #5                  // Method com/google/protobuf/Descriptors$ServiceDescriptor.getMethods:()Ljava/util/List;
      10: iconst_0
      11: invokeinterface #6,  2            // InterfaceMethod java/util/List.get:(I)Ljava/lang/Object;
      16: checkcast     #7                  // class com/google/protobuf/Descriptors$MethodDescriptor
      19: aload_1
      20: aload_2
      21: invokestatic  #8                  // Method org/apache/hadoop/hbase/protobuf/generated/AdminProtos$GetRegionInfoResponse.getDefaultInstance:()Lorg/apache/hadoop/hbase/protobuf/generated/AdminProtos$GetRegionInfoResponse;
      24: invokeinterface #9,  5            // InterfaceMethod com/google/protobuf/BlockingRpcChannel.callBlockingMethod:(Lcom/google/protobuf/Descriptors$MethodDescriptor;Lcom/google/protobuf/RpcController;Lcom/google/protobuf/Message;Lcom/google/protobuf/Message;)Lcom/google/protobuf/Message;
      29: checkcast     #10                 // class org/apache/hadoop/hbase/protobuf/generated/AdminProtos$GetRegionInfoResponse
      32: areturn

  public org.apache.hadoop.hbase.protobuf.generated.AdminProtos$GetStoreFileResponse getStoreFile(com.google.protobuf.RpcController, org.apache.hadoop.hbase.protobuf.generated.AdminProtos$GetStoreFileRequest) throws com.google.protobuf.ServiceException;
    Code:
       0: aload_0
       1: getfield      #3                  // Field channel:Lcom/google/protobuf/BlockingRpcChannel;
       4: invokestatic  #4                  // Method org/apache/hadoop/hbase/protobuf/generated/AdminProtos$AdminService.getDescriptor:()Lcom/google/protobuf/Descriptors$ServiceDescriptor;
       7: invokevirtual #5                  // Method com/google/protobuf/Descriptors$ServiceDescriptor.getMethods:()Ljava/util/List;
      10: iconst_1
      11: invokeinterface #6,  2            // InterfaceMethod java/util/List.get:(I)Ljava/lang/Object;
      16: checkcast     #7                  // class com/google/protobuf/Descriptors$MethodDescriptor
      19: aload_1
      20: aload_2
      21: invokestatic  #11                 // Method org/apache/hadoop/hbase/protobuf/generated/AdminProtos$GetStoreFileResponse.getDefaultInstance:()Lorg/apache/hadoop/hbase/protobuf/generated/AdminProtos$GetStoreFileResponse;
      24: invokeinterface #9,  5            // InterfaceMethod com/google/protobuf/BlockingRpcChannel.callBlockingMethod:(Lcom/google/protobuf/Descriptors$MethodDescriptor;Lcom/google/protobuf/RpcController;Lcom/google/protobuf/Message;Lcom/google/protobuf/Message;)Lcom/google/protobuf/Message;
      29: checkcast     #12                 // class org/apache/hadoop/hbase/protobuf/generated/AdminProtos$GetStoreFileResponse
      32: areturn

  public org.apache.hadoop.hbase.protobuf.generated.AdminProtos$GetOnlineRegionResponse getOnlineRegion(com.google.protobuf.RpcController, org.apache.hadoop.hbase.protobuf.generated.AdminProtos$GetOnlineRegionRequest) throws com.google.protobuf.ServiceException;
    Code:
       0: aload_0
       1: getfield      #3                  // Field channel:Lcom/google/protobuf/BlockingRpcChannel;
       4: invokestatic  #4                  // Method org/apache/hadoop/hbase/protobuf/generated/AdminProtos$AdminService.getDescriptor:()Lcom/google/protobuf/Descriptors$ServiceDescriptor;
       7: invokevirtual #5                  // Method com/google/protobuf/Descriptors$ServiceDescriptor.getMethods:()Ljava/util/List;
      10: iconst_2
      11: invokeinterface #6,  2            // InterfaceMethod java/util/List.get:(I)Ljava/lang/Object;
      16: checkcast     #7                  // class com/google/protobuf/Descriptors$MethodDescriptor
      19: aload_1
      20: aload_2
      21: invokestatic  #13                 // Method org/apache/hadoop/hbase/protobuf/generated/AdminProtos$GetOnlineRegionResponse.getDefaultInstance:()Lorg/apache/hadoop/hbase/protobuf/generated/AdminProtos$GetOnlineRegionResponse;
      24: invokeinterface #9,  5            // InterfaceMethod com/google/protobuf/BlockingRpcChannel.callBlockingMethod:(Lcom/google/protobuf/Descriptors$MethodDescriptor;Lcom/google/protobuf/RpcController;Lcom/google/protobuf/Message;Lcom/google/protobuf/Message;)Lcom/google/protobuf/Message;
      29: checkcast     #14                 // class org/apache/hadoop/hbase/protobuf/generated/AdminProtos$GetOnlineRegionResponse
      32: areturn

  public org.apache.hadoop.hbase.protobuf.generated.AdminProtos$OpenRegionResponse openRegion(com.google.protobuf.RpcController, org.apache.hadoop.hbase.protobuf.generated.AdminProtos$OpenRegionRequest) throws com.google.protobuf.ServiceException;
    Code:
       0: aload_0
       1: getfield      #3                  // Field channel:Lcom/google/protobuf/BlockingRpcChannel;
       4: invokestatic  #4                  // Method org/apache/hadoop/hbase/protobuf/generated/AdminProtos$AdminService.getDescriptor:()Lcom/google/protobuf/Descriptors$ServiceDescriptor;
       7: invokevirtual #5                  // Method com/google/protobuf/Descriptors$ServiceDescriptor.getMethods:()Ljava/util/List;
      10: iconst_3
      11: invokeinterface #6,  2            // InterfaceMethod java/util/List.get:(I)Ljava/lang/Object;
      16: checkcast     #7                  // class com/google/protobuf/Descriptors$MethodDescriptor
      19: aload_1
      20: aload_2
      21: invokestatic  #15                 // Method org/apache/hadoop/hbase/protobuf/generated/AdminProtos$OpenRegionResponse.getDefaultInstance:()Lorg/apache/hadoop/hbase/protobuf/generated/AdminProtos$OpenRegionResponse;
      24: invokeinterface #9,  5            // InterfaceMethod com/google/protobuf/BlockingRpcChannel.callBlockingMethod:(Lcom/google/protobuf/Descriptors$MethodDescriptor;Lcom/google/protobuf/RpcController;Lcom/google/protobuf/Message;Lcom/google/protobuf/Message;)Lcom/google/protobuf/Message;
      29: checkcast     #16                 // class org/apache/hadoop/hbase/protobuf/generated/AdminProtos$OpenRegionResponse
      32: areturn

  public org.apache.hadoop.hbase.protobuf.generated.AdminProtos$WarmupRegionResponse warmupRegion(com.google.protobuf.RpcController, org.apache.hadoop.hbase.protobuf.generated.AdminProtos$WarmupRegionRequest) throws com.google.protobuf.ServiceException;
    Code:
       0: aload_0
       1: getfield      #3                  // Field channel:Lcom/google/protobuf/BlockingRpcChannel;
       4: invokestatic  #4                  // Method org/apache/hadoop/hbase/protobuf/generated/AdminProtos$AdminService.getDescriptor:()Lcom/google/protobuf/Descriptors$ServiceDescriptor;
       7: invokevirtual #5                  // Method com/google/protobuf/Descriptors$ServiceDescriptor.getMethods:()Ljava/util/List;
      10: iconst_4
      11: invokeinterface #6,  2            // InterfaceMethod java/util/List.get:(I)Ljava/lang/Object;
      16: checkcast     #7                  // class com/google/protobuf/Descriptors$MethodDescriptor
      19: aload_1
      20: aload_2
      21: invokestatic  #17                 // Method org/apache/hadoop/hbase/protobuf/generated/AdminProtos$WarmupRegionResponse.getDefaultInstance:()Lorg/apache/hadoop/hbase/protobuf/generated/AdminProtos$WarmupRegionResponse;
      24: invokeinterface #9,  5            // InterfaceMethod com/google/protobuf/BlockingRpcChannel.callBlockingMethod:(Lcom/google/protobuf/Descriptors$MethodDescriptor;Lcom/google/protobuf/RpcController;Lcom/google/protobuf/Message;Lcom/google/protobuf/Message;)Lcom/google/protobuf/Message;
      29: checkcast     #18                 // class org/apache/hadoop/hbase/protobuf/generated/AdminProtos$WarmupRegionResponse
      32: areturn

  public org.apache.hadoop.hbase.protobuf.generated.AdminProtos$CloseRegionResponse closeRegion(com.google.protobuf.RpcController, org.apache.hadoop.hbase.protobuf.generated.AdminProtos$CloseRegionRequest) throws com.google.protobuf.ServiceException;
    Code:
       0: aload_0
       1: getfield      #3                  // Field channel:Lcom/google/protobuf/BlockingRpcChannel;
       4: invokestatic  #4                  // Method org/apache/hadoop/hbase/protobuf/generated/AdminProtos$AdminService.getDescriptor:()Lcom/google/protobuf/Descriptors$ServiceDescriptor;
       7: invokevirtual #5                  // Method com/google/protobuf/Descriptors$ServiceDescriptor.getMethods:()Ljava/util/List;
      10: iconst_5
      11: invokeinterface #6,  2            // InterfaceMethod java/util/List.get:(I)Ljava/lang/Object;
      16: checkcast     #7                  // class com/google/protobuf/Descriptors$MethodDescriptor
      19: aload_1
      20: aload_2
      21: invokestatic  #19                 // Method org/apache/hadoop/hbase/protobuf/generated/AdminProtos$CloseRegionResponse.getDefaultInstance:()Lorg/apache/hadoop/hbase/protobuf/generated/AdminProtos$CloseRegionResponse;
      24: invokeinterface #9,  5            // InterfaceMethod com/google/protobuf/BlockingRpcChannel.callBlockingMethod:(Lcom/google/protobuf/Descriptors$MethodDescriptor;Lcom/google/protobuf/RpcController;Lcom/google/protobuf/Message;Lcom/google/protobuf/Message;)Lcom/google/protobuf/Message;
      29: checkcast     #20                 // class org/apache/hadoop/hbase/protobuf/generated/AdminProtos$CloseRegionResponse
      32: areturn

  public org.apache.hadoop.hbase.protobuf.generated.AdminProtos$FlushRegionResponse flushRegion(com.google.protobuf.RpcController, org.apache.hadoop.hbase.protobuf.generated.AdminProtos$FlushRegionRequest) throws com.google.protobuf.ServiceException;
    Code:
       0: aload_0
       1: getfield      #3                  // Field channel:Lcom/google/protobuf/BlockingRpcChannel;
       4: invokestatic  #4                  // Method org/apache/hadoop/hbase/protobuf/generated/AdminProtos$AdminService.getDescriptor:()Lcom/google/protobuf/Descriptors$ServiceDescriptor;
       7: invokevirtual #5                  // Method com/google/protobuf/Descriptors$ServiceDescriptor.getMethods:()Ljava/util/List;
      10: bipush        6
      12: invokeinterface #6,  2            // InterfaceMethod java/util/List.get:(I)Ljava/lang/Object;
      17: checkcast     #7                  // class com/google/protobuf/Descriptors$MethodDescriptor
      20: aload_1
      21: aload_2
      22: invokestatic  #21                 // Method org/apache/hadoop/hbase/protobuf/generated/AdminProtos$FlushRegionResponse.getDefaultInstance:()Lorg/apache/hadoop/hbase/protobuf/generated/AdminProtos$FlushRegionResponse;
      25: invokeinterface #9,  5            // InterfaceMethod com/google/protobuf/BlockingRpcChannel.callBlockingMethod:(Lcom/google/protobuf/Descriptors$MethodDescriptor;Lcom/google/protobuf/RpcController;Lcom/google/protobuf/Message;Lcom/google/protobuf/Message;)Lcom/google/protobuf/Message;
      30: checkcast     #22                 // class org/apache/hadoop/hbase/protobuf/generated/AdminProtos$FlushRegionResponse
      33: areturn

  public org.apache.hadoop.hbase.protobuf.generated.AdminProtos$SplitRegionResponse splitRegion(com.google.protobuf.RpcController, org.apache.hadoop.hbase.protobuf.generated.AdminProtos$SplitRegionRequest) throws com.google.protobuf.ServiceException;
    Code:
       0: aload_0
       1: getfield      #3                  // Field channel:Lcom/google/protobuf/BlockingRpcChannel;
       4: invokestatic  #4                  // Method org/apache/hadoop/hbase/protobuf/generated/AdminProtos$AdminService.getDescriptor:()Lcom/google/protobuf/Descriptors$ServiceDescriptor;
       7: invokevirtual #5                  // Method com/google/protobuf/Descriptors$ServiceDescriptor.getMethods:()Ljava/util/List;
      10: bipush        7
      12: invokeinterface #6,  2            // InterfaceMethod java/util/List.get:(I)Ljava/lang/Object;
      17: checkcast     #7                  // class com/google/protobuf/Descriptors$MethodDescriptor
      20: aload_1
      21: aload_2
      22: invokestatic  #23                 // Method org/apache/hadoop/hbase/protobuf/generated/AdminProtos$SplitRegionResponse.getDefaultInstance:()Lorg/apache/hadoop/hbase/protobuf/generated/AdminProtos$SplitRegionResponse;
      25: invokeinterface #9,  5            // InterfaceMethod com/google/protobuf/BlockingRpcChannel.callBlockingMethod:(Lcom/google/protobuf/Descriptors$MethodDescriptor;Lcom/google/protobuf/RpcController;Lcom/google/protobuf/Message;Lcom/google/protobuf/Message;)Lcom/google/protobuf/Message;
      30: checkcast     #24                 // class org/apache/hadoop/hbase/protobuf/generated/AdminProtos$SplitRegionResponse
      33: areturn

  public org.apache.hadoop.hbase.protobuf.generated.AdminProtos$CompactRegionResponse compactRegion(com.google.protobuf.RpcController, org.apache.hadoop.hbase.protobuf.generated.AdminProtos$CompactRegionRequest) throws com.google.protobuf.ServiceException;
    Code:
       0: aload_0
       1: getfield      #3                  // Field channel:Lcom/google/protobuf/BlockingRpcChannel;
       4: invokestatic  #4                  // Method org/apache/hadoop/hbase/protobuf/generated/AdminProtos$AdminService.getDescriptor:()Lcom/google/protobuf/Descriptors$ServiceDescriptor;
       7: invokevirtual #5                  // Method com/google/protobuf/Descriptors$ServiceDescriptor.getMethods:()Ljava/util/List;
      10: bipush        8
      12: invokeinterface #6,  2            // InterfaceMethod java/util/List.get:(I)Ljava/lang/Object;
      17: checkcast     #7                  // class com/google/protobuf/Descriptors$MethodDescriptor
      20: aload_1
      21: aload_2
      22: invokestatic  #25                 // Method org/apache/hadoop/hbase/protobuf/generated/AdminProtos$CompactRegionResponse.getDefaultInstance:()Lorg/apache/hadoop/hbase/protobuf/generated/AdminProtos$CompactRegionResponse;
      25: invokeinterface #9,  5            // InterfaceMethod com/google/protobuf/BlockingRpcChannel.callBlockingMethod:(Lcom/google/protobuf/Descriptors$MethodDescriptor;Lcom/google/protobuf/RpcController;Lcom/google/protobuf/Message;Lcom/google/protobuf/Message;)Lcom/google/protobuf/Message;
      30: checkcast     #26                 // class org/apache/hadoop/hbase/protobuf/generated/AdminProtos$CompactRegionResponse
      33: areturn

  public org.apache.hadoop.hbase.protobuf.generated.AdminProtos$MergeRegionsResponse mergeRegions(com.google.protobuf.RpcController, org.apache.hadoop.hbase.protobuf.generated.AdminProtos$MergeRegionsRequest) throws com.google.protobuf.ServiceException;
    Code:
       0: aload_0
       1: getfield      #3                  // Field channel:Lcom/google/protobuf/BlockingRpcChannel;
       4: invokestatic  #4                  // Method org/apache/hadoop/hbase/protobuf/generated/AdminProtos$AdminService.getDescriptor:()Lcom/google/protobuf/Descriptors$ServiceDescriptor;
       7: invokevirtual #5                  // Method com/google/protobuf/Descriptors$ServiceDescriptor.getMethods:()Ljava/util/List;
      10: bipush        9
      12: invokeinterface #6,  2            // InterfaceMethod java/util/List.get:(I)Ljava/lang/Object;
      17: checkcast     #7                  // class com/google/protobuf/Descriptors$MethodDescriptor
      20: aload_1
      21: aload_2
      22: invokestatic  #27                 // Method org/apache/hadoop/hbase/protobuf/generated/AdminProtos$MergeRegionsResponse.getDefaultInstance:()Lorg/apache/hadoop/hbase/protobuf/generated/AdminProtos$MergeRegionsResponse;
      25: invokeinterface #9,  5            // InterfaceMethod com/google/protobuf/BlockingRpcChannel.callBlockingMethod:(Lcom/google/protobuf/Descriptors$MethodDescriptor;Lcom/google/protobuf/RpcController;Lcom/google/protobuf/Message;Lcom/google/protobuf/Message;)Lcom/google/protobuf/Message;
      30: checkcast     #28                 // class org/apache/hadoop/hbase/protobuf/generated/AdminProtos$MergeRegionsResponse
      33: areturn

  public org.apache.hadoop.hbase.protobuf.generated.AdminProtos$ReplicateWALEntryResponse replicateWALEntry(com.google.protobuf.RpcController, org.apache.hadoop.hbase.protobuf.generated.AdminProtos$ReplicateWALEntryRequest) throws com.google.protobuf.ServiceException;
    Code:
       0: aload_0
       1: getfield      #3                  // Field channel:Lcom/google/protobuf/BlockingRpcChannel;
       4: invokestatic  #4                  // Method org/apache/hadoop/hbase/protobuf/generated/AdminProtos$AdminService.getDescriptor:()Lcom/google/protobuf/Descriptors$ServiceDescriptor;
       7: invokevirtual #5                  // Method com/google/protobuf/Descriptors$ServiceDescriptor.getMethods:()Ljava/util/List;
      10: bipush        10
      12: invokeinterface #6,  2            // InterfaceMethod java/util/List.get:(I)Ljava/lang/Object;
      17: checkcast     #7                  // class com/google/protobuf/Descriptors$MethodDescriptor
      20: aload_1
      21: aload_2
      22: invokestatic  #29                 // Method org/apache/hadoop/hbase/protobuf/generated/AdminProtos$ReplicateWALEntryResponse.getDefaultInstance:()Lorg/apache/hadoop/hbase/protobuf/generated/AdminProtos$ReplicateWALEntryResponse;
      25: invokeinterface #9,  5            // InterfaceMethod com/google/protobuf/BlockingRpcChannel.callBlockingMethod:(Lcom/google/protobuf/Descriptors$MethodDescriptor;Lcom/google/protobuf/RpcController;Lcom/google/protobuf/Message;Lcom/google/protobuf/Message;)Lcom/google/protobuf/Message;
      30: checkcast     #30                 // class org/apache/hadoop/hbase/protobuf/generated/AdminProtos$ReplicateWALEntryResponse
      33: areturn

  public org.apache.hadoop.hbase.protobuf.generated.AdminProtos$ReplicateWALEntryResponse replay(com.google.protobuf.RpcController, org.apache.hadoop.hbase.protobuf.generated.AdminProtos$ReplicateWALEntryRequest) throws com.google.protobuf.ServiceException;
    Code:
       0: aload_0
       1: getfield      #3                  // Field channel:Lcom/google/protobuf/BlockingRpcChannel;
       4: invokestatic  #4                  // Method org/apache/hadoop/hbase/protobuf/generated/AdminProtos$AdminService.getDescriptor:()Lcom/google/protobuf/Descriptors$ServiceDescriptor;
       7: invokevirtual #5                  // Method com/google/protobuf/Descriptors$ServiceDescriptor.getMethods:()Ljava/util/List;
      10: bipush        11
      12: invokeinterface #6,  2            // InterfaceMethod java/util/List.get:(I)Ljava/lang/Object;
      17: checkcast     #7                  // class com/google/protobuf/Descriptors$MethodDescriptor
      20: aload_1
      21: aload_2
      22: invokestatic  #29                 // Method org/apache/hadoop/hbase/protobuf/generated/AdminProtos$ReplicateWALEntryResponse.getDefaultInstance:()Lorg/apache/hadoop/hbase/protobuf/generated/AdminProtos$ReplicateWALEntryResponse;
      25: invokeinterface #9,  5            // InterfaceMethod com/google/protobuf/BlockingRpcChannel.callBlockingMethod:(Lcom/google/protobuf/Descriptors$MethodDescriptor;Lcom/google/protobuf/RpcController;Lcom/google/protobuf/Message;Lcom/google/protobuf/Message;)Lcom/google/protobuf/Message;
      30: checkcast     #30                 // class org/apache/hadoop/hbase/protobuf/generated/AdminProtos$ReplicateWALEntryResponse
      33: areturn

  public org.apache.hadoop.hbase.protobuf.generated.AdminProtos$RollWALWriterResponse rollWALWriter(com.google.protobuf.RpcController, org.apache.hadoop.hbase.protobuf.generated.AdminProtos$RollWALWriterRequest) throws com.google.protobuf.ServiceException;
    Code:
       0: aload_0
       1: getfield      #3                  // Field channel:Lcom/google/protobuf/BlockingRpcChannel;
       4: invokestatic  #4                  // Method org/apache/hadoop/hbase/protobuf/generated/AdminProtos$AdminService.getDescriptor:()Lcom/google/protobuf/Descriptors$ServiceDescriptor;
       7: invokevirtual #5                  // Method com/google/protobuf/Descriptors$ServiceDescriptor.getMethods:()Ljava/util/List;
      10: bipush        12
      12: invokeinterface #6,  2            // InterfaceMethod java/util/List.get:(I)Ljava/lang/Object;
      17: checkcast     #7                  // class com/google/protobuf/Descriptors$MethodDescriptor
      20: aload_1
      21: aload_2
      22: invokestatic  #31                 // Method org/apache/hadoop/hbase/protobuf/generated/AdminProtos$RollWALWriterResponse.getDefaultInstance:()Lorg/apache/hadoop/hbase/protobuf/generated/AdminProtos$RollWALWriterResponse;
      25: invokeinterface #9,  5            // InterfaceMethod com/google/protobuf/BlockingRpcChannel.callBlockingMethod:(Lcom/google/protobuf/Descriptors$MethodDescriptor;Lcom/google/protobuf/RpcController;Lcom/google/protobuf/Message;Lcom/google/protobuf/Message;)Lcom/google/protobuf/Message;
      30: checkcast     #32                 // class org/apache/hadoop/hbase/protobuf/generated/AdminProtos$RollWALWriterResponse
      33: areturn

  public org.apache.hadoop.hbase.protobuf.generated.AdminProtos$GetServerInfoResponse getServerInfo(com.google.protobuf.RpcController, org.apache.hadoop.hbase.protobuf.generated.AdminProtos$GetServerInfoRequest) throws com.google.protobuf.ServiceException;
    Code:
       0: aload_0
       1: getfield      #3                  // Field channel:Lcom/google/protobuf/BlockingRpcChannel;
       4: invokestatic  #4                  // Method org/apache/hadoop/hbase/protobuf/generated/AdminProtos$AdminService.getDescriptor:()Lcom/google/protobuf/Descriptors$ServiceDescriptor;
       7: invokevirtual #5                  // Method com/google/protobuf/Descriptors$ServiceDescriptor.getMethods:()Ljava/util/List;
      10: bipush        13
      12: invokeinterface #6,  2            // InterfaceMethod java/util/List.get:(I)Ljava/lang/Object;
      17: checkcast     #7                  // class com/google/protobuf/Descriptors$MethodDescriptor
      20: aload_1
      21: aload_2
      22: invokestatic  #33                 // Method org/apache/hadoop/hbase/protobuf/generated/AdminProtos$GetServerInfoResponse.getDefaultInstance:()Lorg/apache/hadoop/hbase/protobuf/generated/AdminProtos$GetServerInfoResponse;
      25: invokeinterface #9,  5            // InterfaceMethod com/google/protobuf/BlockingRpcChannel.callBlockingMethod:(Lcom/google/protobuf/Descriptors$MethodDescriptor;Lcom/google/protobuf/RpcController;Lcom/google/protobuf/Message;Lcom/google/protobuf/Message;)Lcom/google/protobuf/Message;
      30: checkcast     #34                 // class org/apache/hadoop/hbase/protobuf/generated/AdminProtos$GetServerInfoResponse
      33: areturn

  public org.apache.hadoop.hbase.protobuf.generated.AdminProtos$StopServerResponse stopServer(com.google.protobuf.RpcController, org.apache.hadoop.hbase.protobuf.generated.AdminProtos$StopServerRequest) throws com.google.protobuf.ServiceException;
    Code:
       0: aload_0
       1: getfield      #3                  // Field channel:Lcom/google/protobuf/BlockingRpcChannel;
       4: invokestatic  #4                  // Method org/apache/hadoop/hbase/protobuf/generated/AdminProtos$AdminService.getDescriptor:()Lcom/google/protobuf/Descriptors$ServiceDescriptor;
       7: invokevirtual #5                  // Method com/google/protobuf/Descriptors$ServiceDescriptor.getMethods:()Ljava/util/List;
      10: bipush        14
      12: invokeinterface #6,  2            // InterfaceMethod java/util/List.get:(I)Ljava/lang/Object;
      17: checkcast     #7                  // class com/google/protobuf/Descriptors$MethodDescriptor
      20: aload_1
      21: aload_2
      22: invokestatic  #35                 // Method org/apache/hadoop/hbase/protobuf/generated/AdminProtos$StopServerResponse.getDefaultInstance:()Lorg/apache/hadoop/hbase/protobuf/generated/AdminProtos$StopServerResponse;
      25: invokeinterface #9,  5            // InterfaceMethod com/google/protobuf/BlockingRpcChannel.callBlockingMethod:(Lcom/google/protobuf/Descriptors$MethodDescriptor;Lcom/google/protobuf/RpcController;Lcom/google/protobuf/Message;Lcom/google/protobuf/Message;)Lcom/google/protobuf/Message;
      30: checkcast     #36                 // class org/apache/hadoop/hbase/protobuf/generated/AdminProtos$StopServerResponse
      33: areturn

  public org.apache.hadoop.hbase.protobuf.generated.AdminProtos$UpdateFavoredNodesResponse updateFavoredNodes(com.google.protobuf.RpcController, org.apache.hadoop.hbase.protobuf.generated.AdminProtos$UpdateFavoredNodesRequest) throws com.google.protobuf.ServiceException;
    Code:
       0: aload_0
       1: getfield      #3                  // Field channel:Lcom/google/protobuf/BlockingRpcChannel;
       4: invokestatic  #4                  // Method org/apache/hadoop/hbase/protobuf/generated/AdminProtos$AdminService.getDescriptor:()Lcom/google/protobuf/Descriptors$ServiceDescriptor;
       7: invokevirtual #5                  // Method com/google/protobuf/Descriptors$ServiceDescriptor.getMethods:()Ljava/util/List;
      10: bipush        15
      12: invokeinterface #6,  2            // InterfaceMethod java/util/List.get:(I)Ljava/lang/Object;
      17: checkcast     #7                  // class com/google/protobuf/Descriptors$MethodDescriptor
      20: aload_1
      21: aload_2
      22: invokestatic  #37                 // Method org/apache/hadoop/hbase/protobuf/generated/AdminProtos$UpdateFavoredNodesResponse.getDefaultInstance:()Lorg/apache/hadoop/hbase/protobuf/generated/AdminProtos$UpdateFavoredNodesResponse;
      25: invokeinterface #9,  5            // InterfaceMethod com/google/protobuf/BlockingRpcChannel.callBlockingMethod:(Lcom/google/protobuf/Descriptors$MethodDescriptor;Lcom/google/protobuf/RpcController;Lcom/google/protobuf/Message;Lcom/google/protobuf/Message;)Lcom/google/protobuf/Message;
      30: checkcast     #38                 // class org/apache/hadoop/hbase/protobuf/generated/AdminProtos$UpdateFavoredNodesResponse
      33: areturn

  public org.apache.hadoop.hbase.protobuf.generated.AdminProtos$UpdateConfigurationResponse updateConfiguration(com.google.protobuf.RpcController, org.apache.hadoop.hbase.protobuf.generated.AdminProtos$UpdateConfigurationRequest) throws com.google.protobuf.ServiceException;
    Code:
       0: aload_0
       1: getfield      #3                  // Field channel:Lcom/google/protobuf/BlockingRpcChannel;
       4: invokestatic  #4                  // Method org/apache/hadoop/hbase/protobuf/generated/AdminProtos$AdminService.getDescriptor:()Lcom/google/protobuf/Descriptors$ServiceDescriptor;
       7: invokevirtual #5                  // Method com/google/protobuf/Descriptors$ServiceDescriptor.getMethods:()Ljava/util/List;
      10: bipush        16
      12: invokeinterface #6,  2            // InterfaceMethod java/util/List.get:(I)Ljava/lang/Object;
      17: checkcast     #7                  // class com/google/protobuf/Descriptors$MethodDescriptor
      20: aload_1
      21: aload_2
      22: invokestatic  #39                 // Method org/apache/hadoop/hbase/protobuf/generated/AdminProtos$UpdateConfigurationResponse.getDefaultInstance:()Lorg/apache/hadoop/hbase/protobuf/generated/AdminProtos$UpdateConfigurationResponse;
      25: invokeinterface #9,  5            // InterfaceMethod com/google/protobuf/BlockingRpcChannel.callBlockingMethod:(Lcom/google/protobuf/Descriptors$MethodDescriptor;Lcom/google/protobuf/RpcController;Lcom/google/protobuf/Message;Lcom/google/protobuf/Message;)Lcom/google/protobuf/Message;
      30: checkcast     #40                 // class org/apache/hadoop/hbase/protobuf/generated/AdminProtos$UpdateConfigurationResponse
      33: areturn

  org.apache.hadoop.hbase.protobuf.generated.AdminProtos$AdminService$BlockingStub(com.google.protobuf.BlockingRpcChannel, org.apache.hadoop.hbase.protobuf.generated.AdminProtos$1);
    Code:
       0: aload_0
       1: aload_1
       2: invokespecial #1                  // Method "<init>":(Lcom/google/protobuf/BlockingRpcChannel;)V
       5: return
}
