Compiled from "AdminProtos.java"
public final class org.apache.hadoop.hbase.protobuf.generated.AdminProtos$MergeRegionsRequest$Builder extends com.google.protobuf.GeneratedMessage$Builder<org.apache.hadoop.hbase.protobuf.generated.AdminProtos$MergeRegionsRequest$Builder> implements org.apache.hadoop.hbase.protobuf.generated.AdminProtos$MergeRegionsRequestOrBuilder {
  public static final com.google.protobuf.Descriptors$Descriptor getDescriptor();
    Code:
       0: invokestatic  #3                  // Method org/apache/hadoop/hbase/protobuf/generated/AdminProtos.access$21000:()Lcom/google/protobuf/Descriptors$Descriptor;
       3: areturn

  protected com.google.protobuf.GeneratedMessage$FieldAccessorTable internalGetFieldAccessorTable();
    Code:
       0: invokestatic  #4                  // Method org/apache/hadoop/hbase/protobuf/generated/AdminProtos.access$21100:()Lcom/google/protobuf/GeneratedMessage$FieldAccessorTable;
       3: ldc           #5                  // class org/apache/hadoop/hbase/protobuf/generated/AdminProtos$MergeRegionsRequest
       5: ldc           #6                  // class org/apache/hadoop/hbase/protobuf/generated/AdminProtos$MergeRegionsRequest$Builder
       7: invokevirtual #7                  // Method com/google/protobuf/GeneratedMessage$FieldAccessorTable.ensureFieldAccessorsInitialized:(Ljava/lang/Class;Ljava/lang/Class;)Lcom/google/protobuf/GeneratedMessage$FieldAccessorTable;
      10: areturn

  public org.apache.hadoop.hbase.protobuf.generated.AdminProtos$MergeRegionsRequest$Builder clear();
    Code:
       0: aload_0
       1: invokespecial #18                 // Method com/google/protobuf/GeneratedMessage$Builder.clear:()Lcom/google/protobuf/GeneratedMessage$Builder;
       4: pop
       5: aload_0
       6: getfield      #19                 // Field regionABuilder_:Lcom/google/protobuf/SingleFieldBuilder;
       9: ifnonnull     22
      12: aload_0
      13: invokestatic  #9                  // Method org/apache/hadoop/hbase/protobuf/generated/HBaseProtos$RegionSpecifier.getDefaultInstance:()Lorg/apache/hadoop/hbase/protobuf/generated/HBaseProtos$RegionSpecifier;
      16: putfield      #10                 // Field regionA_:Lorg/apache/hadoop/hbase/protobuf/generated/HBaseProtos$RegionSpecifier;
      19: goto          30
      22: aload_0
      23: getfield      #19                 // Field regionABuilder_:Lcom/google/protobuf/SingleFieldBuilder;
      26: invokevirtual #20                 // Method com/google/protobuf/SingleFieldBuilder.clear:()Lcom/google/protobuf/SingleFieldBuilder;
      29: pop
      30: aload_0
      31: aload_0
      32: getfield      #21                 // Field bitField0_:I
      35: bipush        -2
      37: iand
      38: putfield      #21                 // Field bitField0_:I
      41: aload_0
      42: getfield      #22                 // Field regionBBuilder_:Lcom/google/protobuf/SingleFieldBuilder;
      45: ifnonnull     58
      48: aload_0
      49: invokestatic  #9                  // Method org/apache/hadoop/hbase/protobuf/generated/HBaseProtos$RegionSpecifier.getDefaultInstance:()Lorg/apache/hadoop/hbase/protobuf/generated/HBaseProtos$RegionSpecifier;
      52: putfield      #11                 // Field regionB_:Lorg/apache/hadoop/hbase/protobuf/generated/HBaseProtos$RegionSpecifier;
      55: goto          66
      58: aload_0
      59: getfield      #22                 // Field regionBBuilder_:Lcom/google/protobuf/SingleFieldBuilder;
      62: invokevirtual #20                 // Method com/google/protobuf/SingleFieldBuilder.clear:()Lcom/google/protobuf/SingleFieldBuilder;
      65: pop
      66: aload_0
      67: aload_0
      68: getfield      #21                 // Field bitField0_:I
      71: bipush        -3
      73: iand
      74: putfield      #21                 // Field bitField0_:I
      77: aload_0
      78: iconst_0
      79: putfield      #23                 // Field forcible_:Z
      82: aload_0
      83: aload_0
      84: getfield      #21                 // Field bitField0_:I
      87: bipush        -5
      89: iand
      90: putfield      #21                 // Field bitField0_:I
      93: aload_0
      94: lconst_0
      95: putfield      #24                 // Field masterSystemTime_:J
      98: aload_0
      99: aload_0
     100: getfield      #21                 // Field bitField0_:I
     103: bipush        -9
     105: iand
     106: putfield      #21                 // Field bitField0_:I
     109: aload_0
     110: areturn

  public org.apache.hadoop.hbase.protobuf.generated.AdminProtos$MergeRegionsRequest$Builder clone();
    Code:
       0: invokestatic  #2                  // Method create:()Lorg/apache/hadoop/hbase/protobuf/generated/AdminProtos$MergeRegionsRequest$Builder;
       3: aload_0
       4: invokevirtual #25                 // Method buildPartial:()Lorg/apache/hadoop/hbase/protobuf/generated/AdminProtos$MergeRegionsRequest;
       7: invokevirtual #26                 // Method mergeFrom:(Lorg/apache/hadoop/hbase/protobuf/generated/AdminProtos$MergeRegionsRequest;)Lorg/apache/hadoop/hbase/protobuf/generated/AdminProtos$MergeRegionsRequest$Builder;
      10: areturn

  public com.google.protobuf.Descriptors$Descriptor getDescriptorForType();
    Code:
       0: invokestatic  #3                  // Method org/apache/hadoop/hbase/protobuf/generated/AdminProtos.access$21000:()Lcom/google/protobuf/Descriptors$Descriptor;
       3: areturn

  public org.apache.hadoop.hbase.protobuf.generated.AdminProtos$MergeRegionsRequest getDefaultInstanceForType();
    Code:
       0: invokestatic  #27                 // Method org/apache/hadoop/hbase/protobuf/generated/AdminProtos$MergeRegionsRequest.getDefaultInstance:()Lorg/apache/hadoop/hbase/protobuf/generated/AdminProtos$MergeRegionsRequest;
       3: areturn

  public org.apache.hadoop.hbase.protobuf.generated.AdminProtos$MergeRegionsRequest build();
    Code:
       0: aload_0
       1: invokevirtual #25                 // Method buildPartial:()Lorg/apache/hadoop/hbase/protobuf/generated/AdminProtos$MergeRegionsRequest;
       4: astore_1
       5: aload_1
       6: invokevirtual #28                 // Method org/apache/hadoop/hbase/protobuf/generated/AdminProtos$MergeRegionsRequest.isInitialized:()Z
       9: ifne          17
      12: aload_1
      13: invokestatic  #29                 // Method newUninitializedMessageException:(Lcom/google/protobuf/Message;)Lcom/google/protobuf/UninitializedMessageException;
      16: athrow
      17: aload_1
      18: areturn

  public org.apache.hadoop.hbase.protobuf.generated.AdminProtos$MergeRegionsRequest buildPartial();
    Code:
       0: new           #5                  // class org/apache/hadoop/hbase/protobuf/generated/AdminProtos$MergeRegionsRequest
       3: dup
       4: aload_0
       5: aconst_null
       6: invokespecial #30                 // Method org/apache/hadoop/hbase/protobuf/generated/AdminProtos$MergeRegionsRequest."<init>":(Lcom/google/protobuf/GeneratedMessage$Builder;Lorg/apache/hadoop/hbase/protobuf/generated/AdminProtos$1;)V
       9: astore_1
      10: aload_0
      11: getfield      #21                 // Field bitField0_:I
      14: istore_2
      15: iconst_0
      16: istore_3
      17: iload_2
      18: iconst_1
      19: iand
      20: iconst_1
      21: if_icmpne     28
      24: iload_3
      25: iconst_1
      26: ior
      27: istore_3
      28: aload_0
      29: getfield      #19                 // Field regionABuilder_:Lcom/google/protobuf/SingleFieldBuilder;
      32: ifnonnull     47
      35: aload_1
      36: aload_0
      37: getfield      #10                 // Field regionA_:Lorg/apache/hadoop/hbase/protobuf/generated/HBaseProtos$RegionSpecifier;
      40: invokestatic  #31                 // Method org/apache/hadoop/hbase/protobuf/generated/AdminProtos$MergeRegionsRequest.access$21702:(Lorg/apache/hadoop/hbase/protobuf/generated/AdminProtos$MergeRegionsRequest;Lorg/apache/hadoop/hbase/protobuf/generated/HBaseProtos$RegionSpecifier;)Lorg/apache/hadoop/hbase/protobuf/generated/HBaseProtos$RegionSpecifier;
      43: pop
      44: goto          62
      47: aload_1
      48: aload_0
      49: getfield      #19                 // Field regionABuilder_:Lcom/google/protobuf/SingleFieldBuilder;
      52: invokevirtual #32                 // Method com/google/protobuf/SingleFieldBuilder.build:()Lcom/google/protobuf/GeneratedMessage;
      55: checkcast     #33                 // class org/apache/hadoop/hbase/protobuf/generated/HBaseProtos$RegionSpecifier
      58: invokestatic  #31                 // Method org/apache/hadoop/hbase/protobuf/generated/AdminProtos$MergeRegionsRequest.access$21702:(Lorg/apache/hadoop/hbase/protobuf/generated/AdminProtos$MergeRegionsRequest;Lorg/apache/hadoop/hbase/protobuf/generated/HBaseProtos$RegionSpecifier;)Lorg/apache/hadoop/hbase/protobuf/generated/HBaseProtos$RegionSpecifier;
      61: pop
      62: iload_2
      63: iconst_2
      64: iand
      65: iconst_2
      66: if_icmpne     73
      69: iload_3
      70: iconst_2
      71: ior
      72: istore_3
      73: aload_0
      74: getfield      #22                 // Field regionBBuilder_:Lcom/google/protobuf/SingleFieldBuilder;
      77: ifnonnull     92
      80: aload_1
      81: aload_0
      82: getfield      #11                 // Field regionB_:Lorg/apache/hadoop/hbase/protobuf/generated/HBaseProtos$RegionSpecifier;
      85: invokestatic  #34                 // Method org/apache/hadoop/hbase/protobuf/generated/AdminProtos$MergeRegionsRequest.access$21802:(Lorg/apache/hadoop/hbase/protobuf/generated/AdminProtos$MergeRegionsRequest;Lorg/apache/hadoop/hbase/protobuf/generated/HBaseProtos$RegionSpecifier;)Lorg/apache/hadoop/hbase/protobuf/generated/HBaseProtos$RegionSpecifier;
      88: pop
      89: goto          107
      92: aload_1
      93: aload_0
      94: getfield      #22                 // Field regionBBuilder_:Lcom/google/protobuf/SingleFieldBuilder;
      97: invokevirtual #32                 // Method com/google/protobuf/SingleFieldBuilder.build:()Lcom/google/protobuf/GeneratedMessage;
     100: checkcast     #33                 // class org/apache/hadoop/hbase/protobuf/generated/HBaseProtos$RegionSpecifier
     103: invokestatic  #34                 // Method org/apache/hadoop/hbase/protobuf/generated/AdminProtos$MergeRegionsRequest.access$21802:(Lorg/apache/hadoop/hbase/protobuf/generated/AdminProtos$MergeRegionsRequest;Lorg/apache/hadoop/hbase/protobuf/generated/HBaseProtos$RegionSpecifier;)Lorg/apache/hadoop/hbase/protobuf/generated/HBaseProtos$RegionSpecifier;
     106: pop
     107: iload_2
     108: iconst_4
     109: iand
     110: iconst_4
     111: if_icmpne     118
     114: iload_3
     115: iconst_4
     116: ior
     117: istore_3
     118: aload_1
     119: aload_0
     120: getfield      #23                 // Field forcible_:Z
     123: invokestatic  #35                 // Method org/apache/hadoop/hbase/protobuf/generated/AdminProtos$MergeRegionsRequest.access$21902:(Lorg/apache/hadoop/hbase/protobuf/generated/AdminProtos$MergeRegionsRequest;Z)Z
     126: pop
     127: iload_2
     128: bipush        8
     130: iand
     131: bipush        8
     133: if_icmpne     141
     136: iload_3
     137: bipush        8
     139: ior
     140: istore_3
     141: aload_1
     142: aload_0
     143: getfield      #24                 // Field masterSystemTime_:J
     146: invokestatic  #36                 // Method org/apache/hadoop/hbase/protobuf/generated/AdminProtos$MergeRegionsRequest.access$22002:(Lorg/apache/hadoop/hbase/protobuf/generated/AdminProtos$MergeRegionsRequest;J)J
     149: pop2
     150: aload_1
     151: iload_3
     152: invokestatic  #37                 // Method org/apache/hadoop/hbase/protobuf/generated/AdminProtos$MergeRegionsRequest.access$22102:(Lorg/apache/hadoop/hbase/protobuf/generated/AdminProtos$MergeRegionsRequest;I)I
     155: pop
     156: aload_0
     157: invokevirtual #38                 // Method onBuilt:()V
     160: aload_1
     161: areturn

  public org.apache.hadoop.hbase.protobuf.generated.AdminProtos$MergeRegionsRequest$Builder mergeFrom(com.google.protobuf.Message);
    Code:
       0: aload_1
       1: instanceof    #5                  // class org/apache/hadoop/hbase/protobuf/generated/AdminProtos$MergeRegionsRequest
       4: ifeq          16
       7: aload_0
       8: aload_1
       9: checkcast     #5                  // class org/apache/hadoop/hbase/protobuf/generated/AdminProtos$MergeRegionsRequest
      12: invokevirtual #26                 // Method mergeFrom:(Lorg/apache/hadoop/hbase/protobuf/generated/AdminProtos$MergeRegionsRequest;)Lorg/apache/hadoop/hbase/protobuf/generated/AdminProtos$MergeRegionsRequest$Builder;
      15: areturn
      16: aload_0
      17: aload_1
      18: invokespecial #39                 // Method com/google/protobuf/GeneratedMessage$Builder.mergeFrom:(Lcom/google/protobuf/Message;)Lcom/google/protobuf/AbstractMessage$Builder;
      21: pop
      22: aload_0
      23: areturn

  public org.apache.hadoop.hbase.protobuf.generated.AdminProtos$MergeRegionsRequest$Builder mergeFrom(org.apache.hadoop.hbase.protobuf.generated.AdminProtos$MergeRegionsRequest);
    Code:
       0: aload_1
       1: invokestatic  #27                 // Method org/apache/hadoop/hbase/protobuf/generated/AdminProtos$MergeRegionsRequest.getDefaultInstance:()Lorg/apache/hadoop/hbase/protobuf/generated/AdminProtos$MergeRegionsRequest;
       4: if_acmpne     9
       7: aload_0
       8: areturn
       9: aload_1
      10: invokevirtual #40                 // Method org/apache/hadoop/hbase/protobuf/generated/AdminProtos$MergeRegionsRequest.hasRegionA:()Z
      13: ifeq          25
      16: aload_0
      17: aload_1
      18: invokevirtual #41                 // Method org/apache/hadoop/hbase/protobuf/generated/AdminProtos$MergeRegionsRequest.getRegionA:()Lorg/apache/hadoop/hbase/protobuf/generated/HBaseProtos$RegionSpecifier;
      21: invokevirtual #42                 // Method mergeRegionA:(Lorg/apache/hadoop/hbase/protobuf/generated/HBaseProtos$RegionSpecifier;)Lorg/apache/hadoop/hbase/protobuf/generated/AdminProtos$MergeRegionsRequest$Builder;
      24: pop
      25: aload_1
      26: invokevirtual #43                 // Method org/apache/hadoop/hbase/protobuf/generated/AdminProtos$MergeRegionsRequest.hasRegionB:()Z
      29: ifeq          41
      32: aload_0
      33: aload_1
      34: invokevirtual #44                 // Method org/apache/hadoop/hbase/protobuf/generated/AdminProtos$MergeRegionsRequest.getRegionB:()Lorg/apache/hadoop/hbase/protobuf/generated/HBaseProtos$RegionSpecifier;
      37: invokevirtual #45                 // Method mergeRegionB:(Lorg/apache/hadoop/hbase/protobuf/generated/HBaseProtos$RegionSpecifier;)Lorg/apache/hadoop/hbase/protobuf/generated/AdminProtos$MergeRegionsRequest$Builder;
      40: pop
      41: aload_1
      42: invokevirtual #46                 // Method org/apache/hadoop/hbase/protobuf/generated/AdminProtos$MergeRegionsRequest.hasForcible:()Z
      45: ifeq          57
      48: aload_0
      49: aload_1
      50: invokevirtual #47                 // Method org/apache/hadoop/hbase/protobuf/generated/AdminProtos$MergeRegionsRequest.getForcible:()Z
      53: invokevirtual #48                 // Method setForcible:(Z)Lorg/apache/hadoop/hbase/protobuf/generated/AdminProtos$MergeRegionsRequest$Builder;
      56: pop
      57: aload_1
      58: invokevirtual #49                 // Method org/apache/hadoop/hbase/protobuf/generated/AdminProtos$MergeRegionsRequest.hasMasterSystemTime:()Z
      61: ifeq          73
      64: aload_0
      65: aload_1
      66: invokevirtual #50                 // Method org/apache/hadoop/hbase/protobuf/generated/AdminProtos$MergeRegionsRequest.getMasterSystemTime:()J
      69: invokevirtual #51                 // Method setMasterSystemTime:(J)Lorg/apache/hadoop/hbase/protobuf/generated/AdminProtos$MergeRegionsRequest$Builder;
      72: pop
      73: aload_0
      74: aload_1
      75: invokevirtual #52                 // Method org/apache/hadoop/hbase/protobuf/generated/AdminProtos$MergeRegionsRequest.getUnknownFields:()Lcom/google/protobuf/UnknownFieldSet;
      78: invokevirtual #53                 // Method mergeUnknownFields:(Lcom/google/protobuf/UnknownFieldSet;)Lcom/google/protobuf/GeneratedMessage$Builder;
      81: pop
      82: aload_0
      83: areturn

  public final boolean isInitialized();
    Code:
       0: aload_0
       1: invokevirtual #54                 // Method hasRegionA:()Z
       4: ifne          9
       7: iconst_0
       8: ireturn
       9: aload_0
      10: invokevirtual #55                 // Method hasRegionB:()Z
      13: ifne          18
      16: iconst_0
      17: ireturn
      18: aload_0
      19: invokevirtual #56                 // Method getRegionA:()Lorg/apache/hadoop/hbase/protobuf/generated/HBaseProtos$RegionSpecifier;
      22: invokevirtual #57                 // Method org/apache/hadoop/hbase/protobuf/generated/HBaseProtos$RegionSpecifier.isInitialized:()Z
      25: ifne          30
      28: iconst_0
      29: ireturn
      30: aload_0
      31: invokevirtual #58                 // Method getRegionB:()Lorg/apache/hadoop/hbase/protobuf/generated/HBaseProtos$RegionSpecifier;
      34: invokevirtual #57                 // Method org/apache/hadoop/hbase/protobuf/generated/HBaseProtos$RegionSpecifier.isInitialized:()Z
      37: ifne          42
      40: iconst_0
      41: ireturn
      42: iconst_1
      43: ireturn

  public org.apache.hadoop.hbase.protobuf.generated.AdminProtos$MergeRegionsRequest$Builder mergeFrom(com.google.protobuf.CodedInputStream, com.google.protobuf.ExtensionRegistryLite) throws java.io.IOException;
    Code:
       0: aconst_null
       1: astore_3
       2: getstatic     #59                 // Field org/apache/hadoop/hbase/protobuf/generated/AdminProtos$MergeRegionsRequest.PARSER:Lcom/google/protobuf/Parser;
       5: aload_1
       6: aload_2
       7: invokeinterface #60,  3           // InterfaceMethod com/google/protobuf/Parser.parsePartialFrom:(Lcom/google/protobuf/CodedInputStream;Lcom/google/protobuf/ExtensionRegistryLite;)Ljava/lang/Object;
      12: checkcast     #5                  // class org/apache/hadoop/hbase/protobuf/generated/AdminProtos$MergeRegionsRequest
      15: astore_3
      16: aload_3
      17: ifnull        58
      20: aload_0
      21: aload_3
      22: invokevirtual #26                 // Method mergeFrom:(Lorg/apache/hadoop/hbase/protobuf/generated/AdminProtos$MergeRegionsRequest;)Lorg/apache/hadoop/hbase/protobuf/generated/AdminProtos$MergeRegionsRequest$Builder;
      25: pop
      26: goto          58
      29: astore        4
      31: aload         4
      33: invokevirtual #62                 // Method com/google/protobuf/InvalidProtocolBufferException.getUnfinishedMessage:()Lcom/google/protobuf/MessageLite;
      36: checkcast     #5                  // class org/apache/hadoop/hbase/protobuf/generated/AdminProtos$MergeRegionsRequest
      39: astore_3
      40: aload         4
      42: athrow
      43: astore        5
      45: aload_3
      46: ifnull        55
      49: aload_0
      50: aload_3
      51: invokevirtual #26                 // Method mergeFrom:(Lorg/apache/hadoop/hbase/protobuf/generated/AdminProtos$MergeRegionsRequest;)Lorg/apache/hadoop/hbase/protobuf/generated/AdminProtos$MergeRegionsRequest$Builder;
      54: pop
      55: aload         5
      57: athrow
      58: aload_0
      59: areturn
    Exception table:
       from    to  target type
           2    16    29   Class com/google/protobuf/InvalidProtocolBufferException
           2    16    43   any
          29    45    43   any

  public boolean hasRegionA();
    Code:
       0: aload_0
       1: getfield      #21                 // Field bitField0_:I
       4: iconst_1
       5: iand
       6: iconst_1
       7: if_icmpne     14
      10: iconst_1
      11: goto          15
      14: iconst_0
      15: ireturn

  public org.apache.hadoop.hbase.protobuf.generated.HBaseProtos$RegionSpecifier getRegionA();
    Code:
       0: aload_0
       1: getfield      #19                 // Field regionABuilder_:Lcom/google/protobuf/SingleFieldBuilder;
       4: ifnonnull     12
       7: aload_0
       8: getfield      #10                 // Field regionA_:Lorg/apache/hadoop/hbase/protobuf/generated/HBaseProtos$RegionSpecifier;
      11: areturn
      12: aload_0
      13: getfield      #19                 // Field regionABuilder_:Lcom/google/protobuf/SingleFieldBuilder;
      16: invokevirtual #63                 // Method com/google/protobuf/SingleFieldBuilder.getMessage:()Lcom/google/protobuf/GeneratedMessage;
      19: checkcast     #33                 // class org/apache/hadoop/hbase/protobuf/generated/HBaseProtos$RegionSpecifier
      22: areturn

  public org.apache.hadoop.hbase.protobuf.generated.AdminProtos$MergeRegionsRequest$Builder setRegionA(org.apache.hadoop.hbase.protobuf.generated.HBaseProtos$RegionSpecifier);
    Code:
       0: aload_0
       1: getfield      #19                 // Field regionABuilder_:Lcom/google/protobuf/SingleFieldBuilder;
       4: ifnonnull     31
       7: aload_1
       8: ifnonnull     19
      11: new           #64                 // class java/lang/NullPointerException
      14: dup
      15: invokespecial #65                 // Method java/lang/NullPointerException."<init>":()V
      18: athrow
      19: aload_0
      20: aload_1
      21: putfield      #10                 // Field regionA_:Lorg/apache/hadoop/hbase/protobuf/generated/HBaseProtos$RegionSpecifier;
      24: aload_0
      25: invokevirtual #66                 // Method onChanged:()V
      28: goto          40
      31: aload_0
      32: getfield      #19                 // Field regionABuilder_:Lcom/google/protobuf/SingleFieldBuilder;
      35: aload_1
      36: invokevirtual #67                 // Method com/google/protobuf/SingleFieldBuilder.setMessage:(Lcom/google/protobuf/GeneratedMessage;)Lcom/google/protobuf/SingleFieldBuilder;
      39: pop
      40: aload_0
      41: dup
      42: getfield      #21                 // Field bitField0_:I
      45: iconst_1
      46: ior
      47: putfield      #21                 // Field bitField0_:I
      50: aload_0
      51: areturn

  public org.apache.hadoop.hbase.protobuf.generated.AdminProtos$MergeRegionsRequest$Builder setRegionA(org.apache.hadoop.hbase.protobuf.generated.HBaseProtos$RegionSpecifier$Builder);
    Code:
       0: aload_0
       1: getfield      #19                 // Field regionABuilder_:Lcom/google/protobuf/SingleFieldBuilder;
       4: ifnonnull     22
       7: aload_0
       8: aload_1
       9: invokevirtual #68                 // Method org/apache/hadoop/hbase/protobuf/generated/HBaseProtos$RegionSpecifier$Builder.build:()Lorg/apache/hadoop/hbase/protobuf/generated/HBaseProtos$RegionSpecifier;
      12: putfield      #10                 // Field regionA_:Lorg/apache/hadoop/hbase/protobuf/generated/HBaseProtos$RegionSpecifier;
      15: aload_0
      16: invokevirtual #66                 // Method onChanged:()V
      19: goto          34
      22: aload_0
      23: getfield      #19                 // Field regionABuilder_:Lcom/google/protobuf/SingleFieldBuilder;
      26: aload_1
      27: invokevirtual #68                 // Method org/apache/hadoop/hbase/protobuf/generated/HBaseProtos$RegionSpecifier$Builder.build:()Lorg/apache/hadoop/hbase/protobuf/generated/HBaseProtos$RegionSpecifier;
      30: invokevirtual #67                 // Method com/google/protobuf/SingleFieldBuilder.setMessage:(Lcom/google/protobuf/GeneratedMessage;)Lcom/google/protobuf/SingleFieldBuilder;
      33: pop
      34: aload_0
      35: dup
      36: getfield      #21                 // Field bitField0_:I
      39: iconst_1
      40: ior
      41: putfield      #21                 // Field bitField0_:I
      44: aload_0
      45: areturn

  public org.apache.hadoop.hbase.protobuf.generated.AdminProtos$MergeRegionsRequest$Builder mergeRegionA(org.apache.hadoop.hbase.protobuf.generated.HBaseProtos$RegionSpecifier);
    Code:
       0: aload_0
       1: getfield      #19                 // Field regionABuilder_:Lcom/google/protobuf/SingleFieldBuilder;
       4: ifnonnull     60
       7: aload_0
       8: getfield      #21                 // Field bitField0_:I
      11: iconst_1
      12: iand
      13: iconst_1
      14: if_icmpne     48
      17: aload_0
      18: getfield      #10                 // Field regionA_:Lorg/apache/hadoop/hbase/protobuf/generated/HBaseProtos$RegionSpecifier;
      21: invokestatic  #9                  // Method org/apache/hadoop/hbase/protobuf/generated/HBaseProtos$RegionSpecifier.getDefaultInstance:()Lorg/apache/hadoop/hbase/protobuf/generated/HBaseProtos$RegionSpecifier;
      24: if_acmpeq     48
      27: aload_0
      28: aload_0
      29: getfield      #10                 // Field regionA_:Lorg/apache/hadoop/hbase/protobuf/generated/HBaseProtos$RegionSpecifier;
      32: invokestatic  #69                 // Method org/apache/hadoop/hbase/protobuf/generated/HBaseProtos$RegionSpecifier.newBuilder:(Lorg/apache/hadoop/hbase/protobuf/generated/HBaseProtos$RegionSpecifier;)Lorg/apache/hadoop/hbase/protobuf/generated/HBaseProtos$RegionSpecifier$Builder;
      35: aload_1
      36: invokevirtual #70                 // Method org/apache/hadoop/hbase/protobuf/generated/HBaseProtos$RegionSpecifier$Builder.mergeFrom:(Lorg/apache/hadoop/hbase/protobuf/generated/HBaseProtos$RegionSpecifier;)Lorg/apache/hadoop/hbase/protobuf/generated/HBaseProtos$RegionSpecifier$Builder;
      39: invokevirtual #71                 // Method org/apache/hadoop/hbase/protobuf/generated/HBaseProtos$RegionSpecifier$Builder.buildPartial:()Lorg/apache/hadoop/hbase/protobuf/generated/HBaseProtos$RegionSpecifier;
      42: putfield      #10                 // Field regionA_:Lorg/apache/hadoop/hbase/protobuf/generated/HBaseProtos$RegionSpecifier;
      45: goto          53
      48: aload_0
      49: aload_1
      50: putfield      #10                 // Field regionA_:Lorg/apache/hadoop/hbase/protobuf/generated/HBaseProtos$RegionSpecifier;
      53: aload_0
      54: invokevirtual #66                 // Method onChanged:()V
      57: goto          69
      60: aload_0
      61: getfield      #19                 // Field regionABuilder_:Lcom/google/protobuf/SingleFieldBuilder;
      64: aload_1
      65: invokevirtual #72                 // Method com/google/protobuf/SingleFieldBuilder.mergeFrom:(Lcom/google/protobuf/GeneratedMessage;)Lcom/google/protobuf/SingleFieldBuilder;
      68: pop
      69: aload_0
      70: dup
      71: getfield      #21                 // Field bitField0_:I
      74: iconst_1
      75: ior
      76: putfield      #21                 // Field bitField0_:I
      79: aload_0
      80: areturn

  public org.apache.hadoop.hbase.protobuf.generated.AdminProtos$MergeRegionsRequest$Builder clearRegionA();
    Code:
       0: aload_0
       1: getfield      #19                 // Field regionABuilder_:Lcom/google/protobuf/SingleFieldBuilder;
       4: ifnonnull     21
       7: aload_0
       8: invokestatic  #9                  // Method org/apache/hadoop/hbase/protobuf/generated/HBaseProtos$RegionSpecifier.getDefaultInstance:()Lorg/apache/hadoop/hbase/protobuf/generated/HBaseProtos$RegionSpecifier;
      11: putfield      #10                 // Field regionA_:Lorg/apache/hadoop/hbase/protobuf/generated/HBaseProtos$RegionSpecifier;
      14: aload_0
      15: invokevirtual #66                 // Method onChanged:()V
      18: goto          29
      21: aload_0
      22: getfield      #19                 // Field regionABuilder_:Lcom/google/protobuf/SingleFieldBuilder;
      25: invokevirtual #20                 // Method com/google/protobuf/SingleFieldBuilder.clear:()Lcom/google/protobuf/SingleFieldBuilder;
      28: pop
      29: aload_0
      30: aload_0
      31: getfield      #21                 // Field bitField0_:I
      34: bipush        -2
      36: iand
      37: putfield      #21                 // Field bitField0_:I
      40: aload_0
      41: areturn

  public org.apache.hadoop.hbase.protobuf.generated.HBaseProtos$RegionSpecifier$Builder getRegionABuilder();
    Code:
       0: aload_0
       1: dup
       2: getfield      #21                 // Field bitField0_:I
       5: iconst_1
       6: ior
       7: putfield      #21                 // Field bitField0_:I
      10: aload_0
      11: invokevirtual #66                 // Method onChanged:()V
      14: aload_0
      15: invokespecial #15                 // Method getRegionAFieldBuilder:()Lcom/google/protobuf/SingleFieldBuilder;
      18: invokevirtual #73                 // Method com/google/protobuf/SingleFieldBuilder.getBuilder:()Lcom/google/protobuf/GeneratedMessage$Builder;
      21: checkcast     #74                 // class org/apache/hadoop/hbase/protobuf/generated/HBaseProtos$RegionSpecifier$Builder
      24: areturn

  public org.apache.hadoop.hbase.protobuf.generated.HBaseProtos$RegionSpecifierOrBuilder getRegionAOrBuilder();
    Code:
       0: aload_0
       1: getfield      #19                 // Field regionABuilder_:Lcom/google/protobuf/SingleFieldBuilder;
       4: ifnull        18
       7: aload_0
       8: getfield      #19                 // Field regionABuilder_:Lcom/google/protobuf/SingleFieldBuilder;
      11: invokevirtual #75                 // Method com/google/protobuf/SingleFieldBuilder.getMessageOrBuilder:()Lcom/google/protobuf/MessageOrBuilder;
      14: checkcast     #76                 // class org/apache/hadoop/hbase/protobuf/generated/HBaseProtos$RegionSpecifierOrBuilder
      17: areturn
      18: aload_0
      19: getfield      #10                 // Field regionA_:Lorg/apache/hadoop/hbase/protobuf/generated/HBaseProtos$RegionSpecifier;
      22: areturn

  public boolean hasRegionB();
    Code:
       0: aload_0
       1: getfield      #21                 // Field bitField0_:I
       4: iconst_2
       5: iand
       6: iconst_2
       7: if_icmpne     14
      10: iconst_1
      11: goto          15
      14: iconst_0
      15: ireturn

  public org.apache.hadoop.hbase.protobuf.generated.HBaseProtos$RegionSpecifier getRegionB();
    Code:
       0: aload_0
       1: getfield      #22                 // Field regionBBuilder_:Lcom/google/protobuf/SingleFieldBuilder;
       4: ifnonnull     12
       7: aload_0
       8: getfield      #11                 // Field regionB_:Lorg/apache/hadoop/hbase/protobuf/generated/HBaseProtos$RegionSpecifier;
      11: areturn
      12: aload_0
      13: getfield      #22                 // Field regionBBuilder_:Lcom/google/protobuf/SingleFieldBuilder;
      16: invokevirtual #63                 // Method com/google/protobuf/SingleFieldBuilder.getMessage:()Lcom/google/protobuf/GeneratedMessage;
      19: checkcast     #33                 // class org/apache/hadoop/hbase/protobuf/generated/HBaseProtos$RegionSpecifier
      22: areturn

  public org.apache.hadoop.hbase.protobuf.generated.AdminProtos$MergeRegionsRequest$Builder setRegionB(org.apache.hadoop.hbase.protobuf.generated.HBaseProtos$RegionSpecifier);
    Code:
       0: aload_0
       1: getfield      #22                 // Field regionBBuilder_:Lcom/google/protobuf/SingleFieldBuilder;
       4: ifnonnull     31
       7: aload_1
       8: ifnonnull     19
      11: new           #64                 // class java/lang/NullPointerException
      14: dup
      15: invokespecial #65                 // Method java/lang/NullPointerException."<init>":()V
      18: athrow
      19: aload_0
      20: aload_1
      21: putfield      #11                 // Field regionB_:Lorg/apache/hadoop/hbase/protobuf/generated/HBaseProtos$RegionSpecifier;
      24: aload_0
      25: invokevirtual #66                 // Method onChanged:()V
      28: goto          40
      31: aload_0
      32: getfield      #22                 // Field regionBBuilder_:Lcom/google/protobuf/SingleFieldBuilder;
      35: aload_1
      36: invokevirtual #67                 // Method com/google/protobuf/SingleFieldBuilder.setMessage:(Lcom/google/protobuf/GeneratedMessage;)Lcom/google/protobuf/SingleFieldBuilder;
      39: pop
      40: aload_0
      41: dup
      42: getfield      #21                 // Field bitField0_:I
      45: iconst_2
      46: ior
      47: putfield      #21                 // Field bitField0_:I
      50: aload_0
      51: areturn

  public org.apache.hadoop.hbase.protobuf.generated.AdminProtos$MergeRegionsRequest$Builder setRegionB(org.apache.hadoop.hbase.protobuf.generated.HBaseProtos$RegionSpecifier$Builder);
    Code:
       0: aload_0
       1: getfield      #22                 // Field regionBBuilder_:Lcom/google/protobuf/SingleFieldBuilder;
       4: ifnonnull     22
       7: aload_0
       8: aload_1
       9: invokevirtual #68                 // Method org/apache/hadoop/hbase/protobuf/generated/HBaseProtos$RegionSpecifier$Builder.build:()Lorg/apache/hadoop/hbase/protobuf/generated/HBaseProtos$RegionSpecifier;
      12: putfield      #11                 // Field regionB_:Lorg/apache/hadoop/hbase/protobuf/generated/HBaseProtos$RegionSpecifier;
      15: aload_0
      16: invokevirtual #66                 // Method onChanged:()V
      19: goto          34
      22: aload_0
      23: getfield      #22                 // Field regionBBuilder_:Lcom/google/protobuf/SingleFieldBuilder;
      26: aload_1
      27: invokevirtual #68                 // Method org/apache/hadoop/hbase/protobuf/generated/HBaseProtos$RegionSpecifier$Builder.build:()Lorg/apache/hadoop/hbase/protobuf/generated/HBaseProtos$RegionSpecifier;
      30: invokevirtual #67                 // Method com/google/protobuf/SingleFieldBuilder.setMessage:(Lcom/google/protobuf/GeneratedMessage;)Lcom/google/protobuf/SingleFieldBuilder;
      33: pop
      34: aload_0
      35: dup
      36: getfield      #21                 // Field bitField0_:I
      39: iconst_2
      40: ior
      41: putfield      #21                 // Field bitField0_:I
      44: aload_0
      45: areturn

  public org.apache.hadoop.hbase.protobuf.generated.AdminProtos$MergeRegionsRequest$Builder mergeRegionB(org.apache.hadoop.hbase.protobuf.generated.HBaseProtos$RegionSpecifier);
    Code:
       0: aload_0
       1: getfield      #22                 // Field regionBBuilder_:Lcom/google/protobuf/SingleFieldBuilder;
       4: ifnonnull     60
       7: aload_0
       8: getfield      #21                 // Field bitField0_:I
      11: iconst_2
      12: iand
      13: iconst_2
      14: if_icmpne     48
      17: aload_0
      18: getfield      #11                 // Field regionB_:Lorg/apache/hadoop/hbase/protobuf/generated/HBaseProtos$RegionSpecifier;
      21: invokestatic  #9                  // Method org/apache/hadoop/hbase/protobuf/generated/HBaseProtos$RegionSpecifier.getDefaultInstance:()Lorg/apache/hadoop/hbase/protobuf/generated/HBaseProtos$RegionSpecifier;
      24: if_acmpeq     48
      27: aload_0
      28: aload_0
      29: getfield      #11                 // Field regionB_:Lorg/apache/hadoop/hbase/protobuf/generated/HBaseProtos$RegionSpecifier;
      32: invokestatic  #69                 // Method org/apache/hadoop/hbase/protobuf/generated/HBaseProtos$RegionSpecifier.newBuilder:(Lorg/apache/hadoop/hbase/protobuf/generated/HBaseProtos$RegionSpecifier;)Lorg/apache/hadoop/hbase/protobuf/generated/HBaseProtos$RegionSpecifier$Builder;
      35: aload_1
      36: invokevirtual #70                 // Method org/apache/hadoop/hbase/protobuf/generated/HBaseProtos$RegionSpecifier$Builder.mergeFrom:(Lorg/apache/hadoop/hbase/protobuf/generated/HBaseProtos$RegionSpecifier;)Lorg/apache/hadoop/hbase/protobuf/generated/HBaseProtos$RegionSpecifier$Builder;
      39: invokevirtual #71                 // Method org/apache/hadoop/hbase/protobuf/generated/HBaseProtos$RegionSpecifier$Builder.buildPartial:()Lorg/apache/hadoop/hbase/protobuf/generated/HBaseProtos$RegionSpecifier;
      42: putfield      #11                 // Field regionB_:Lorg/apache/hadoop/hbase/protobuf/generated/HBaseProtos$RegionSpecifier;
      45: goto          53
      48: aload_0
      49: aload_1
      50: putfield      #11                 // Field regionB_:Lorg/apache/hadoop/hbase/protobuf/generated/HBaseProtos$RegionSpecifier;
      53: aload_0
      54: invokevirtual #66                 // Method onChanged:()V
      57: goto          69
      60: aload_0
      61: getfield      #22                 // Field regionBBuilder_:Lcom/google/protobuf/SingleFieldBuilder;
      64: aload_1
      65: invokevirtual #72                 // Method com/google/protobuf/SingleFieldBuilder.mergeFrom:(Lcom/google/protobuf/GeneratedMessage;)Lcom/google/protobuf/SingleFieldBuilder;
      68: pop
      69: aload_0
      70: dup
      71: getfield      #21                 // Field bitField0_:I
      74: iconst_2
      75: ior
      76: putfield      #21                 // Field bitField0_:I
      79: aload_0
      80: areturn

  public org.apache.hadoop.hbase.protobuf.generated.AdminProtos$MergeRegionsRequest$Builder clearRegionB();
    Code:
       0: aload_0
       1: getfield      #22                 // Field regionBBuilder_:Lcom/google/protobuf/SingleFieldBuilder;
       4: ifnonnull     21
       7: aload_0
       8: invokestatic  #9                  // Method org/apache/hadoop/hbase/protobuf/generated/HBaseProtos$RegionSpecifier.getDefaultInstance:()Lorg/apache/hadoop/hbase/protobuf/generated/HBaseProtos$RegionSpecifier;
      11: putfield      #11                 // Field regionB_:Lorg/apache/hadoop/hbase/protobuf/generated/HBaseProtos$RegionSpecifier;
      14: aload_0
      15: invokevirtual #66                 // Method onChanged:()V
      18: goto          29
      21: aload_0
      22: getfield      #22                 // Field regionBBuilder_:Lcom/google/protobuf/SingleFieldBuilder;
      25: invokevirtual #20                 // Method com/google/protobuf/SingleFieldBuilder.clear:()Lcom/google/protobuf/SingleFieldBuilder;
      28: pop
      29: aload_0
      30: aload_0
      31: getfield      #21                 // Field bitField0_:I
      34: bipush        -3
      36: iand
      37: putfield      #21                 // Field bitField0_:I
      40: aload_0
      41: areturn

  public org.apache.hadoop.hbase.protobuf.generated.HBaseProtos$RegionSpecifier$Builder getRegionBBuilder();
    Code:
       0: aload_0
       1: dup
       2: getfield      #21                 // Field bitField0_:I
       5: iconst_2
       6: ior
       7: putfield      #21                 // Field bitField0_:I
      10: aload_0
      11: invokevirtual #66                 // Method onChanged:()V
      14: aload_0
      15: invokespecial #16                 // Method getRegionBFieldBuilder:()Lcom/google/protobuf/SingleFieldBuilder;
      18: invokevirtual #73                 // Method com/google/protobuf/SingleFieldBuilder.getBuilder:()Lcom/google/protobuf/GeneratedMessage$Builder;
      21: checkcast     #74                 // class org/apache/hadoop/hbase/protobuf/generated/HBaseProtos$RegionSpecifier$Builder
      24: areturn

  public org.apache.hadoop.hbase.protobuf.generated.HBaseProtos$RegionSpecifierOrBuilder getRegionBOrBuilder();
    Code:
       0: aload_0
       1: getfield      #22                 // Field regionBBuilder_:Lcom/google/protobuf/SingleFieldBuilder;
       4: ifnull        18
       7: aload_0
       8: getfield      #22                 // Field regionBBuilder_:Lcom/google/protobuf/SingleFieldBuilder;
      11: invokevirtual #75                 // Method com/google/protobuf/SingleFieldBuilder.getMessageOrBuilder:()Lcom/google/protobuf/MessageOrBuilder;
      14: checkcast     #76                 // class org/apache/hadoop/hbase/protobuf/generated/HBaseProtos$RegionSpecifierOrBuilder
      17: areturn
      18: aload_0
      19: getfield      #11                 // Field regionB_:Lorg/apache/hadoop/hbase/protobuf/generated/HBaseProtos$RegionSpecifier;
      22: areturn

  public boolean hasForcible();
    Code:
       0: aload_0
       1: getfield      #21                 // Field bitField0_:I
       4: iconst_4
       5: iand
       6: iconst_4
       7: if_icmpne     14
      10: iconst_1
      11: goto          15
      14: iconst_0
      15: ireturn

  public boolean getForcible();
    Code:
       0: aload_0
       1: getfield      #23                 // Field forcible_:Z
       4: ireturn

  public org.apache.hadoop.hbase.protobuf.generated.AdminProtos$MergeRegionsRequest$Builder setForcible(boolean);
    Code:
       0: aload_0
       1: dup
       2: getfield      #21                 // Field bitField0_:I
       5: iconst_4
       6: ior
       7: putfield      #21                 // Field bitField0_:I
      10: aload_0
      11: iload_1
      12: putfield      #23                 // Field forcible_:Z
      15: aload_0
      16: invokevirtual #66                 // Method onChanged:()V
      19: aload_0
      20: areturn

  public org.apache.hadoop.hbase.protobuf.generated.AdminProtos$MergeRegionsRequest$Builder clearForcible();
    Code:
       0: aload_0
       1: aload_0
       2: getfield      #21                 // Field bitField0_:I
       5: bipush        -5
       7: iand
       8: putfield      #21                 // Field bitField0_:I
      11: aload_0
      12: iconst_0
      13: putfield      #23                 // Field forcible_:Z
      16: aload_0
      17: invokevirtual #66                 // Method onChanged:()V
      20: aload_0
      21: areturn

  public boolean hasMasterSystemTime();
    Code:
       0: aload_0
       1: getfield      #21                 // Field bitField0_:I
       4: bipush        8
       6: iand
       7: bipush        8
       9: if_icmpne     16
      12: iconst_1
      13: goto          17
      16: iconst_0
      17: ireturn

  public long getMasterSystemTime();
    Code:
       0: aload_0
       1: getfield      #24                 // Field masterSystemTime_:J
       4: lreturn

  public org.apache.hadoop.hbase.protobuf.generated.AdminProtos$MergeRegionsRequest$Builder setMasterSystemTime(long);
    Code:
       0: aload_0
       1: dup
       2: getfield      #21                 // Field bitField0_:I
       5: bipush        8
       7: ior
       8: putfield      #21                 // Field bitField0_:I
      11: aload_0
      12: lload_1
      13: putfield      #24                 // Field masterSystemTime_:J
      16: aload_0
      17: invokevirtual #66                 // Method onChanged:()V
      20: aload_0
      21: areturn

  public org.apache.hadoop.hbase.protobuf.generated.AdminProtos$MergeRegionsRequest$Builder clearMasterSystemTime();
    Code:
       0: aload_0
       1: aload_0
       2: getfield      #21                 // Field bitField0_:I
       5: bipush        -9
       7: iand
       8: putfield      #21                 // Field bitField0_:I
      11: aload_0
      12: lconst_0
      13: putfield      #24                 // Field masterSystemTime_:J
      16: aload_0
      17: invokevirtual #66                 // Method onChanged:()V
      20: aload_0
      21: areturn

  public com.google.protobuf.GeneratedMessage$Builder clear();
    Code:
       0: aload_0
       1: invokevirtual #81                 // Method clear:()Lorg/apache/hadoop/hbase/protobuf/generated/AdminProtos$MergeRegionsRequest$Builder;
       4: areturn

  public com.google.protobuf.GeneratedMessage$Builder clone();
    Code:
       0: aload_0
       1: invokevirtual #82                 // Method clone:()Lorg/apache/hadoop/hbase/protobuf/generated/AdminProtos$MergeRegionsRequest$Builder;
       4: areturn

  public com.google.protobuf.AbstractMessage$Builder mergeFrom(com.google.protobuf.CodedInputStream, com.google.protobuf.ExtensionRegistryLite) throws java.io.IOException;
    Code:
       0: aload_0
       1: aload_1
       2: aload_2
       3: invokevirtual #83                 // Method mergeFrom:(Lcom/google/protobuf/CodedInputStream;Lcom/google/protobuf/ExtensionRegistryLite;)Lorg/apache/hadoop/hbase/protobuf/generated/AdminProtos$MergeRegionsRequest$Builder;
       6: areturn

  public com.google.protobuf.AbstractMessage$Builder mergeFrom(com.google.protobuf.Message);
    Code:
       0: aload_0
       1: aload_1
       2: invokevirtual #84                 // Method mergeFrom:(Lcom/google/protobuf/Message;)Lorg/apache/hadoop/hbase/protobuf/generated/AdminProtos$MergeRegionsRequest$Builder;
       5: areturn

  public com.google.protobuf.AbstractMessage$Builder clear();
    Code:
       0: aload_0
       1: invokevirtual #81                 // Method clear:()Lorg/apache/hadoop/hbase/protobuf/generated/AdminProtos$MergeRegionsRequest$Builder;
       4: areturn

  public com.google.protobuf.AbstractMessage$Builder clone();
    Code:
       0: aload_0
       1: invokevirtual #82                 // Method clone:()Lorg/apache/hadoop/hbase/protobuf/generated/AdminProtos$MergeRegionsRequest$Builder;
       4: areturn

  public com.google.protobuf.Message$Builder mergeFrom(com.google.protobuf.CodedInputStream, com.google.protobuf.ExtensionRegistryLite) throws java.io.IOException;
    Code:
       0: aload_0
       1: aload_1
       2: aload_2
       3: invokevirtual #83                 // Method mergeFrom:(Lcom/google/protobuf/CodedInputStream;Lcom/google/protobuf/ExtensionRegistryLite;)Lorg/apache/hadoop/hbase/protobuf/generated/AdminProtos$MergeRegionsRequest$Builder;
       6: areturn

  public com.google.protobuf.Message$Builder clone();
    Code:
       0: aload_0
       1: invokevirtual #82                 // Method clone:()Lorg/apache/hadoop/hbase/protobuf/generated/AdminProtos$MergeRegionsRequest$Builder;
       4: areturn

  public com.google.protobuf.Message buildPartial();
    Code:
       0: aload_0
       1: invokevirtual #25                 // Method buildPartial:()Lorg/apache/hadoop/hbase/protobuf/generated/AdminProtos$MergeRegionsRequest;
       4: areturn

  public com.google.protobuf.Message build();
    Code:
       0: aload_0
       1: invokevirtual #85                 // Method build:()Lorg/apache/hadoop/hbase/protobuf/generated/AdminProtos$MergeRegionsRequest;
       4: areturn

  public com.google.protobuf.Message$Builder mergeFrom(com.google.protobuf.Message);
    Code:
       0: aload_0
       1: aload_1
       2: invokevirtual #84                 // Method mergeFrom:(Lcom/google/protobuf/Message;)Lorg/apache/hadoop/hbase/protobuf/generated/AdminProtos$MergeRegionsRequest$Builder;
       5: areturn

  public com.google.protobuf.Message$Builder clear();
    Code:
       0: aload_0
       1: invokevirtual #81                 // Method clear:()Lorg/apache/hadoop/hbase/protobuf/generated/AdminProtos$MergeRegionsRequest$Builder;
       4: areturn

  public com.google.protobuf.MessageLite$Builder mergeFrom(com.google.protobuf.CodedInputStream, com.google.protobuf.ExtensionRegistryLite) throws java.io.IOException;
    Code:
       0: aload_0
       1: aload_1
       2: aload_2
       3: invokevirtual #83                 // Method mergeFrom:(Lcom/google/protobuf/CodedInputStream;Lcom/google/protobuf/ExtensionRegistryLite;)Lorg/apache/hadoop/hbase/protobuf/generated/AdminProtos$MergeRegionsRequest$Builder;
       6: areturn

  public com.google.protobuf.MessageLite$Builder clone();
    Code:
       0: aload_0
       1: invokevirtual #82                 // Method clone:()Lorg/apache/hadoop/hbase/protobuf/generated/AdminProtos$MergeRegionsRequest$Builder;
       4: areturn

  public com.google.protobuf.MessageLite buildPartial();
    Code:
       0: aload_0
       1: invokevirtual #25                 // Method buildPartial:()Lorg/apache/hadoop/hbase/protobuf/generated/AdminProtos$MergeRegionsRequest;
       4: areturn

  public com.google.protobuf.MessageLite build();
    Code:
       0: aload_0
       1: invokevirtual #85                 // Method build:()Lorg/apache/hadoop/hbase/protobuf/generated/AdminProtos$MergeRegionsRequest;
       4: areturn

  public com.google.protobuf.MessageLite$Builder clear();
    Code:
       0: aload_0
       1: invokevirtual #81                 // Method clear:()Lorg/apache/hadoop/hbase/protobuf/generated/AdminProtos$MergeRegionsRequest$Builder;
       4: areturn

  public com.google.protobuf.MessageLite getDefaultInstanceForType();
    Code:
       0: aload_0
       1: invokevirtual #86                 // Method getDefaultInstanceForType:()Lorg/apache/hadoop/hbase/protobuf/generated/AdminProtos$MergeRegionsRequest;
       4: areturn

  public com.google.protobuf.Message getDefaultInstanceForType();
    Code:
       0: aload_0
       1: invokevirtual #86                 // Method getDefaultInstanceForType:()Lorg/apache/hadoop/hbase/protobuf/generated/AdminProtos$MergeRegionsRequest;
       4: areturn

  public com.google.protobuf.AbstractMessageLite$Builder mergeFrom(com.google.protobuf.CodedInputStream, com.google.protobuf.ExtensionRegistryLite) throws java.io.IOException;
    Code:
       0: aload_0
       1: aload_1
       2: aload_2
       3: invokevirtual #83                 // Method mergeFrom:(Lcom/google/protobuf/CodedInputStream;Lcom/google/protobuf/ExtensionRegistryLite;)Lorg/apache/hadoop/hbase/protobuf/generated/AdminProtos$MergeRegionsRequest$Builder;
       6: areturn

  public com.google.protobuf.AbstractMessageLite$Builder clone();
    Code:
       0: aload_0
       1: invokevirtual #82                 // Method clone:()Lorg/apache/hadoop/hbase/protobuf/generated/AdminProtos$MergeRegionsRequest$Builder;
       4: areturn

  public java.lang.Object clone() throws java.lang.CloneNotSupportedException;
    Code:
       0: aload_0
       1: invokevirtual #82                 // Method clone:()Lorg/apache/hadoop/hbase/protobuf/generated/AdminProtos$MergeRegionsRequest$Builder;
       4: areturn

  static org.apache.hadoop.hbase.protobuf.generated.AdminProtos$MergeRegionsRequest$Builder access$21300();
    Code:
       0: invokestatic  #2                  // Method create:()Lorg/apache/hadoop/hbase/protobuf/generated/AdminProtos$MergeRegionsRequest$Builder;
       3: areturn

  org.apache.hadoop.hbase.protobuf.generated.AdminProtos$MergeRegionsRequest$Builder(com.google.protobuf.GeneratedMessage$BuilderParent, org.apache.hadoop.hbase.protobuf.generated.AdminProtos$1);
    Code:
       0: aload_0
       1: aload_1
       2: invokespecial #1                  // Method "<init>":(Lcom/google/protobuf/GeneratedMessage$BuilderParent;)V
       5: return
}
