Compiled from "AESDecryptor.java"
public class org.apache.hadoop.hbase.io.crypto.aes.AESDecryptor implements org.apache.hadoop.hbase.io.crypto.Decryptor {
  public org.apache.hadoop.hbase.io.crypto.aes.AESDecryptor(javax.crypto.Cipher);
    Code:
       0: aload_0
       1: invokespecial #1                  // Method java/lang/Object."<init>":()V
       4: aload_0
       5: iconst_0
       6: putfield      #2                  // Field initialized:Z
       9: aload_0
      10: aload_1
      11: putfield      #3                  // Field cipher:Ljavax/crypto/Cipher;
      14: return

  javax.crypto.Cipher getCipher();
    Code:
       0: aload_0
       1: getfield      #3                  // Field cipher:Ljavax/crypto/Cipher;
       4: areturn

  public void setKey(java.security.Key);
    Code:
       0: aload_1
       1: ldc           #4                  // String Key cannot be null
       3: invokestatic  #5                  // Method org/apache/hbase/thirdparty/com/google/common/base/Preconditions.checkNotNull:(Ljava/lang/Object;Ljava/lang/Object;)Ljava/lang/Object;
       6: pop
       7: aload_0
       8: aload_1
       9: putfield      #6                  // Field key:Ljava/security/Key;
      12: return

  public int getIvLength();
    Code:
       0: bipush        16
       2: ireturn

  public int getBlockSize();
    Code:
       0: bipush        16
       2: ireturn

  public void setIv(byte[]);
    Code:
       0: aload_1
       1: ldc           #8                  // String IV cannot be null
       3: invokestatic  #5                  // Method org/apache/hbase/thirdparty/com/google/common/base/Preconditions.checkNotNull:(Ljava/lang/Object;Ljava/lang/Object;)Ljava/lang/Object;
       6: pop
       7: aload_1
       8: arraylength
       9: bipush        16
      11: if_icmpne     18
      14: iconst_1
      15: goto          19
      18: iconst_0
      19: ldc           #9                  // String Invalid IV length
      21: invokestatic  #10                 // Method org/apache/hbase/thirdparty/com/google/common/base/Preconditions.checkArgument:(ZLjava/lang/Object;)V
      24: aload_0
      25: aload_1
      26: putfield      #11                 // Field iv:[B
      29: return

  public java.io.InputStream createDecryptionStream(java.io.InputStream);
    Code:
       0: aload_0
       1: getfield      #2                  // Field initialized:Z
       4: ifne          11
       7: aload_0
       8: invokevirtual #12                 // Method init:()V
      11: new           #13                 // class javax/crypto/CipherInputStream
      14: dup
      15: aload_1
      16: aload_0
      17: getfield      #3                  // Field cipher:Ljavax/crypto/Cipher;
      20: invokespecial #14                 // Method javax/crypto/CipherInputStream."<init>":(Ljava/io/InputStream;Ljavax/crypto/Cipher;)V
      23: areturn

  public void reset();
    Code:
       0: aload_0
       1: invokevirtual #12                 // Method init:()V
       4: return

  protected void init();
    Code:
       0: aload_0
       1: getfield      #11                 // Field iv:[B
       4: ifnonnull     17
       7: new           #15                 // class java/lang/NullPointerException
      10: dup
      11: ldc           #16                 // String IV is null
      13: invokespecial #17                 // Method java/lang/NullPointerException."<init>":(Ljava/lang/String;)V
      16: athrow
      17: aload_0
      18: getfield      #3                  // Field cipher:Ljavax/crypto/Cipher;
      21: iconst_2
      22: aload_0
      23: getfield      #6                  // Field key:Ljava/security/Key;
      26: new           #19                 // class javax/crypto/spec/IvParameterSpec
      29: dup
      30: aload_0
      31: getfield      #11                 // Field iv:[B
      34: invokespecial #20                 // Method javax/crypto/spec/IvParameterSpec."<init>":([B)V
      37: invokevirtual #21                 // Method javax/crypto/Cipher.init:(ILjava/security/Key;Ljava/security/spec/AlgorithmParameterSpec;)V
      40: goto          63
      43: astore_1
      44: new           #23                 // class java/lang/RuntimeException
      47: dup
      48: aload_1
      49: invokespecial #24                 // Method java/lang/RuntimeException."<init>":(Ljava/lang/Throwable;)V
      52: athrow
      53: astore_1
      54: new           #23                 // class java/lang/RuntimeException
      57: dup
      58: aload_1
      59: invokespecial #24                 // Method java/lang/RuntimeException."<init>":(Ljava/lang/Throwable;)V
      62: athrow
      63: aload_0
      64: iconst_1
      65: putfield      #2                  // Field initialized:Z
      68: return
    Exception table:
       from    to  target type
           0    40    43   Class java/security/InvalidKeyException
           0    40    53   Class java/security/InvalidAlgorithmParameterException
}
