Compiled from "AnnotationReadingPriorityFunction.java"
public class org.apache.hadoop.hbase.regionserver.AnnotationReadingPriorityFunction implements org.apache.hadoop.hbase.ipc.PriorityFunction {
  public static final java.lang.String SCAN_VTIME_WEIGHT_CONF_KEY;

  protected final java.util.Map<java.lang.String, java.lang.Integer> annotatedQos;

  public org.apache.hadoop.hbase.regionserver.AnnotationReadingPriorityFunction(org.apache.hadoop.hbase.regionserver.RSRpcServices);
    Code:
       0: aload_0
       1: aload_1
       2: aload_1
       3: invokevirtual #1                  // Method java/lang/Object.getClass:()Ljava/lang/Class;
       6: invokespecial #2                  // Method "<init>":(Lorg/apache/hadoop/hbase/regionserver/RSRpcServices;Ljava/lang/Class;)V
       9: return

  public org.apache.hadoop.hbase.regionserver.AnnotationReadingPriorityFunction(org.apache.hadoop.hbase.regionserver.RSRpcServices, java.lang.Class<? extends org.apache.hadoop.hbase.regionserver.RSRpcServices>);
    Code:
       0: aload_0
       1: invokespecial #3                  // Method java/lang/Object."<init>":()V
       4: aload_0
       5: bipush        8
       7: anewarray     #4                  // class java/lang/Class
      10: dup
      11: iconst_0
      12: ldc           #5                  // class org/apache/hadoop/hbase/shaded/protobuf/generated/AdminProtos$GetRegionInfoRequest
      14: aastore
      15: dup
      16: iconst_1
      17: ldc           #6                  // class org/apache/hadoop/hbase/shaded/protobuf/generated/AdminProtos$GetStoreFileRequest
      19: aastore
      20: dup
      21: iconst_2
      22: ldc           #7                  // class org/apache/hadoop/hbase/shaded/protobuf/generated/AdminProtos$CloseRegionRequest
      24: aastore
      25: dup
      26: iconst_3
      27: ldc           #8                  // class org/apache/hadoop/hbase/shaded/protobuf/generated/AdminProtos$FlushRegionRequest
      29: aastore
      30: dup
      31: iconst_4
      32: ldc           #9                  // class org/apache/hadoop/hbase/shaded/protobuf/generated/AdminProtos$CompactRegionRequest
      34: aastore
      35: dup
      36: iconst_5
      37: ldc           #10                 // class org/apache/hadoop/hbase/shaded/protobuf/generated/ClientProtos$GetRequest
      39: aastore
      40: dup
      41: bipush        6
      43: ldc           #11                 // class org/apache/hadoop/hbase/shaded/protobuf/generated/ClientProtos$MutateRequest
      45: aastore
      46: dup
      47: bipush        7
      49: ldc           #12                 // class org/apache/hadoop/hbase/shaded/protobuf/generated/ClientProtos$ScanRequest
      51: aastore
      52: putfield      #13                 // Field knownArgumentClasses:[Ljava/lang/Class;
      55: aload_0
      56: new           #14                 // class java/util/HashMap
      59: dup
      60: invokespecial #15                 // Method java/util/HashMap."<init>":()V
      63: putfield      #16                 // Field argumentToClassMap:Ljava/util/Map;
      66: aload_0
      67: new           #14                 // class java/util/HashMap
      70: dup
      71: invokespecial #15                 // Method java/util/HashMap."<init>":()V
      74: putfield      #17                 // Field methodMap:Ljava/util/Map;
      77: new           #14                 // class java/util/HashMap
      80: dup
      81: invokespecial #15                 // Method java/util/HashMap."<init>":()V
      84: astore_3
      85: aload_2
      86: invokevirtual #18                 // Method java/lang/Class.getMethods:()[Ljava/lang/reflect/Method;
      89: astore        4
      91: aload         4
      93: arraylength
      94: istore        5
      96: iconst_0
      97: istore        6
      99: iload         6
     101: iload         5
     103: if_icmpge     166
     106: aload         4
     108: iload         6
     110: aaload
     111: astore        7
     113: aload         7
     115: ldc           #19                 // class org/apache/hadoop/hbase/ipc/QosPriority
     117: invokevirtual #20                 // Method java/lang/reflect/Method.getAnnotation:(Ljava/lang/Class;)Ljava/lang/annotation/Annotation;
     120: checkcast     #19                 // class org/apache/hadoop/hbase/ipc/QosPriority
     123: astore        8
     125: aload         8
     127: ifnull        160
     130: aload_0
     131: aload         7
     133: invokevirtual #21                 // Method java/lang/reflect/Method.getName:()Ljava/lang/String;
     136: invokespecial #22                 // Method capitalize:(Ljava/lang/String;)Ljava/lang/String;
     139: astore        9
     141: aload_3
     142: aload         9
     144: aload         8
     146: invokeinterface #23,  1           // InterfaceMethod org/apache/hadoop/hbase/ipc/QosPriority.priority:()I
     151: invokestatic  #24                 // Method java/lang/Integer.valueOf:(I)Ljava/lang/Integer;
     154: invokeinterface #25,  3           // InterfaceMethod java/util/Map.put:(Ljava/lang/Object;Ljava/lang/Object;)Ljava/lang/Object;
     159: pop
     160: iinc          6, 1
     163: goto          99
     166: aload_0
     167: aload_1
     168: putfield      #26                 // Field rpcServices:Lorg/apache/hadoop/hbase/regionserver/RSRpcServices;
     171: aload_0
     172: aload_3
     173: putfield      #27                 // Field annotatedQos:Ljava/util/Map;
     176: aload_0
     177: getfield      #17                 // Field methodMap:Ljava/util/Map;
     180: ldc           #28                 // String getRegion
     182: invokeinterface #29,  2           // InterfaceMethod java/util/Map.get:(Ljava/lang/Object;)Ljava/lang/Object;
     187: ifnonnull     228
     190: aload_0
     191: getfield      #17                 // Field methodMap:Ljava/util/Map;
     194: ldc           #30                 // String hasRegion
     196: new           #14                 // class java/util/HashMap
     199: dup
     200: invokespecial #15                 // Method java/util/HashMap."<init>":()V
     203: invokeinterface #25,  3           // InterfaceMethod java/util/Map.put:(Ljava/lang/Object;Ljava/lang/Object;)Ljava/lang/Object;
     208: pop
     209: aload_0
     210: getfield      #17                 // Field methodMap:Ljava/util/Map;
     213: ldc           #28                 // String getRegion
     215: new           #14                 // class java/util/HashMap
     218: dup
     219: invokespecial #15                 // Method java/util/HashMap."<init>":()V
     222: invokeinterface #25,  3           // InterfaceMethod java/util/Map.put:(Ljava/lang/Object;Ljava/lang/Object;)Ljava/lang/Object;
     227: pop
     228: aload_0
     229: getfield      #13                 // Field knownArgumentClasses:[Ljava/lang/Class;
     232: astore        4
     234: aload         4
     236: arraylength
     237: istore        5
     239: iconst_0
     240: istore        6
     242: iload         6
     244: iload         5
     246: if_icmpge     360
     249: aload         4
     251: iload         6
     253: aaload
     254: astore        7
     256: aload_0
     257: getfield      #16                 // Field argumentToClassMap:Ljava/util/Map;
     260: aload         7
     262: invokevirtual #31                 // Method java/lang/Class.getName:()Ljava/lang/String;
     265: aload         7
     267: invokeinterface #25,  3           // InterfaceMethod java/util/Map.put:(Ljava/lang/Object;Ljava/lang/Object;)Ljava/lang/Object;
     272: pop
     273: aload_0
     274: getfield      #17                 // Field methodMap:Ljava/util/Map;
     277: ldc           #30                 // String hasRegion
     279: invokeinterface #29,  2           // InterfaceMethod java/util/Map.get:(Ljava/lang/Object;)Ljava/lang/Object;
     284: checkcast     #32                 // class java/util/Map
     287: aload         7
     289: aload         7
     291: ldc           #30                 // String hasRegion
     293: iconst_0
     294: anewarray     #4                  // class java/lang/Class
     297: invokevirtual #33                 // Method java/lang/Class.getDeclaredMethod:(Ljava/lang/String;[Ljava/lang/Class;)Ljava/lang/reflect/Method;
     300: invokeinterface #25,  3           // InterfaceMethod java/util/Map.put:(Ljava/lang/Object;Ljava/lang/Object;)Ljava/lang/Object;
     305: pop
     306: aload_0
     307: getfield      #17                 // Field methodMap:Ljava/util/Map;
     310: ldc           #28                 // String getRegion
     312: invokeinterface #29,  2           // InterfaceMethod java/util/Map.get:(Ljava/lang/Object;)Ljava/lang/Object;
     317: checkcast     #32                 // class java/util/Map
     320: aload         7
     322: aload         7
     324: ldc           #28                 // String getRegion
     326: iconst_0
     327: anewarray     #4                  // class java/lang/Class
     330: invokevirtual #33                 // Method java/lang/Class.getDeclaredMethod:(Ljava/lang/String;[Ljava/lang/Class;)Ljava/lang/reflect/Method;
     333: invokeinterface #25,  3           // InterfaceMethod java/util/Map.put:(Ljava/lang/Object;Ljava/lang/Object;)Ljava/lang/Object;
     338: pop
     339: goto          354
     342: astore        8
     344: new           #35                 // class java/lang/RuntimeException
     347: dup
     348: aload         8
     350: invokespecial #36                 // Method java/lang/RuntimeException."<init>":(Ljava/lang/Throwable;)V
     353: athrow
     354: iinc          6, 1
     357: goto          242
     360: aload_1
     361: invokevirtual #37                 // Method org/apache/hadoop/hbase/regionserver/RSRpcServices.getConfiguration:()Lorg/apache/hadoop/conf/Configuration;
     364: astore        4
     366: aload_0
     367: aload         4
     369: ldc           #39                 // String hbase.ipc.server.scan.vtime.weight
     371: fconst_1
     372: invokevirtual #40                 // Method org/apache/hadoop/conf/Configuration.getFloat:(Ljava/lang/String;F)F
     375: putfield      #41                 // Field scanVirtualTimeWeight:F
     378: return
    Exception table:
       from    to  target type
         273   339   342   Class java/lang/Exception

  public int getPriority(org.apache.hadoop.hbase.shaded.protobuf.generated.RPCProtos$RequestHeader, org.apache.hbase.thirdparty.com.google.protobuf.Message, org.apache.hadoop.hbase.security.User);
    Code:
       0: aload_0
       1: aload_1
       2: invokevirtual #48                 // Method getAnnotatedPriority:(Lorg/apache/hadoop/hbase/shaded/protobuf/generated/RPCProtos$RequestHeader;)I
       5: istore        4
       7: iload         4
       9: iflt          15
      12: iload         4
      14: ireturn
      15: aload_0
      16: aload_1
      17: aload_2
      18: invokevirtual #49                 // Method getBasePriority:(Lorg/apache/hadoop/hbase/shaded/protobuf/generated/RPCProtos$RequestHeader;Lorg/apache/hbase/thirdparty/com/google/protobuf/Message;)I
      21: ireturn

  protected int getAnnotatedPriority(org.apache.hadoop.hbase.shaded.protobuf.generated.RPCProtos$RequestHeader);
    Code:
       0: aload_1
       1: invokevirtual #50                 // Method org/apache/hadoop/hbase/shaded/protobuf/generated/RPCProtos$RequestHeader.getMethodName:()Ljava/lang/String;
       4: astore_2
       5: aload_0
       6: getfield      #27                 // Field annotatedQos:Ljava/util/Map;
       9: aload_2
      10: invokeinterface #29,  2           // InterfaceMethod java/util/Map.get:(Ljava/lang/Object;)Ljava/lang/Object;
      15: checkcast     #51                 // class java/lang/Integer
      18: astore_3
      19: aload_3
      20: ifnull        28
      23: aload_3
      24: invokevirtual #52                 // Method java/lang/Integer.intValue:()I
      27: ireturn
      28: iconst_m1
      29: ireturn

  protected int getBasePriority(org.apache.hadoop.hbase.shaded.protobuf.generated.RPCProtos$RequestHeader, org.apache.hbase.thirdparty.com.google.protobuf.Message);
    Code:
       0: aload_2
       1: ifnonnull     6
       4: iconst_0
       5: ireturn
       6: aload_1
       7: invokevirtual #54                 // Method org/apache/hadoop/hbase/shaded/protobuf/generated/RPCProtos$RequestHeader.hasPriority:()Z
      10: ifeq          18
      13: aload_1
      14: invokevirtual #55                 // Method org/apache/hadoop/hbase/shaded/protobuf/generated/RPCProtos$RequestHeader.getPriority:()I
      17: ireturn
      18: aload_2
      19: invokevirtual #1                  // Method java/lang/Object.getClass:()Ljava/lang/Class;
      22: invokevirtual #31                 // Method java/lang/Class.getName:()Ljava/lang/String;
      25: astore_3
      26: aload_0
      27: getfield      #16                 // Field argumentToClassMap:Ljava/util/Map;
      30: aload_3
      31: invokeinterface #29,  2           // InterfaceMethod java/util/Map.get:(Ljava/lang/Object;)Ljava/lang/Object;
      36: checkcast     #4                  // class java/lang/Class
      39: astore        4
      41: aconst_null
      42: astore        5
      44: aload_0
      45: getfield      #17                 // Field methodMap:Ljava/util/Map;
      48: ldc           #30                 // String hasRegion
      50: invokeinterface #29,  2           // InterfaceMethod java/util/Map.get:(Ljava/lang/Object;)Ljava/lang/Object;
      55: checkcast     #32                 // class java/util/Map
      58: aload         4
      60: invokeinterface #29,  2           // InterfaceMethod java/util/Map.get:(Ljava/lang/Object;)Ljava/lang/Object;
      65: checkcast     #56                 // class java/lang/reflect/Method
      68: astore        6
      70: aload         6
      72: ifnull        217
      75: aload         6
      77: aload_2
      78: aconst_null
      79: checkcast     #57                 // class "[Ljava/lang/Object;"
      82: invokevirtual #58                 // Method java/lang/reflect/Method.invoke:(Ljava/lang/Object;[Ljava/lang/Object;)Ljava/lang/Object;
      85: checkcast     #59                 // class java/lang/Boolean
      88: invokevirtual #60                 // Method java/lang/Boolean.booleanValue:()Z
      91: ifeq          217
      94: aload_0
      95: getfield      #17                 // Field methodMap:Ljava/util/Map;
      98: ldc           #28                 // String getRegion
     100: invokeinterface #29,  2           // InterfaceMethod java/util/Map.get:(Ljava/lang/Object;)Ljava/lang/Object;
     105: checkcast     #32                 // class java/util/Map
     108: aload         4
     110: invokeinterface #29,  2           // InterfaceMethod java/util/Map.get:(Ljava/lang/Object;)Ljava/lang/Object;
     115: checkcast     #56                 // class java/lang/reflect/Method
     118: astore        7
     120: aload         7
     122: aload_2
     123: aconst_null
     124: checkcast     #57                 // class "[Ljava/lang/Object;"
     127: invokevirtual #58                 // Method java/lang/reflect/Method.invoke:(Ljava/lang/Object;[Ljava/lang/Object;)Ljava/lang/Object;
     130: checkcast     #61                 // class org/apache/hadoop/hbase/shaded/protobuf/generated/HBaseProtos$RegionSpecifier
     133: astore        5
     135: aload_0
     136: getfield      #26                 // Field rpcServices:Lorg/apache/hadoop/hbase/regionserver/RSRpcServices;
     139: aload         5
     141: invokevirtual #62                 // Method org/apache/hadoop/hbase/regionserver/RSRpcServices.getRegion:(Lorg/apache/hadoop/hbase/shaded/protobuf/generated/HBaseProtos$RegionSpecifier;)Lorg/apache/hadoop/hbase/regionserver/HRegion;
     144: astore        8
     146: aload         8
     148: invokeinterface #63,  1           // InterfaceMethod org/apache/hadoop/hbase/regionserver/Region.getRegionInfo:()Lorg/apache/hadoop/hbase/client/RegionInfo;
     153: invokeinterface #64,  1           // InterfaceMethod org/apache/hadoop/hbase/client/RegionInfo.getTable:()Lorg/apache/hadoop/hbase/TableName;
     158: invokevirtual #65                 // Method org/apache/hadoop/hbase/TableName.isSystemTable:()Z
     161: ifeq          217
     164: getstatic     #66                 // Field LOG:Lorg/slf4j/Logger;
     167: invokeinterface #67,  1           // InterfaceMethod org/slf4j/Logger.isTraceEnabled:()Z
     172: ifeq          213
     175: getstatic     #66                 // Field LOG:Lorg/slf4j/Logger;
     178: new           #42                 // class java/lang/StringBuilder
     181: dup
     182: invokespecial #68                 // Method java/lang/StringBuilder."<init>":()V
     185: ldc           #69                 // String High priority because region=
     187: invokevirtual #70                 // Method java/lang/StringBuilder.append:(Ljava/lang/String;)Ljava/lang/StringBuilder;
     190: aload         8
     192: invokeinterface #63,  1           // InterfaceMethod org/apache/hadoop/hbase/regionserver/Region.getRegionInfo:()Lorg/apache/hadoop/hbase/client/RegionInfo;
     197: invokeinterface #71,  1           // InterfaceMethod org/apache/hadoop/hbase/client/RegionInfo.getRegionNameAsString:()Ljava/lang/String;
     202: invokevirtual #70                 // Method java/lang/StringBuilder.append:(Ljava/lang/String;)Ljava/lang/StringBuilder;
     205: invokevirtual #47                 // Method java/lang/StringBuilder.toString:()Ljava/lang/String;
     208: invokeinterface #72,  2           // InterfaceMethod org/slf4j/Logger.trace:(Ljava/lang/String;)V
     213: sipush        200
     216: ireturn
     217: goto          263
     220: astore        6
     222: getstatic     #66                 // Field LOG:Lorg/slf4j/Logger;
     225: invokeinterface #67,  1           // InterfaceMethod org/slf4j/Logger.isTraceEnabled:()Z
     230: ifeq          261
     233: getstatic     #66                 // Field LOG:Lorg/slf4j/Logger;
     236: new           #42                 // class java/lang/StringBuilder
     239: dup
     240: invokespecial #68                 // Method java/lang/StringBuilder."<init>":()V
     243: ldc           #73                 // String Marking normal priority after getting exception=
     245: invokevirtual #70                 // Method java/lang/StringBuilder.append:(Ljava/lang/String;)Ljava/lang/StringBuilder;
     248: aload         6
     250: invokevirtual #74                 // Method java/lang/StringBuilder.append:(Ljava/lang/Object;)Ljava/lang/StringBuilder;
     253: invokevirtual #47                 // Method java/lang/StringBuilder.toString:()Ljava/lang/String;
     256: invokeinterface #72,  2           // InterfaceMethod org/slf4j/Logger.trace:(Ljava/lang/String;)V
     261: iconst_0
     262: ireturn
     263: aload_2
     264: instanceof    #12                 // class org/apache/hadoop/hbase/shaded/protobuf/generated/ClientProtos$ScanRequest
     267: ifeq          369
     270: aload_2
     271: checkcast     #12                 // class org/apache/hadoop/hbase/shaded/protobuf/generated/ClientProtos$ScanRequest
     274: astore        6
     276: aload         6
     278: invokevirtual #75                 // Method org/apache/hadoop/hbase/shaded/protobuf/generated/ClientProtos$ScanRequest.hasScannerId:()Z
     281: ifne          286
     284: iconst_0
     285: ireturn
     286: aload_0
     287: getfield      #26                 // Field rpcServices:Lorg/apache/hadoop/hbase/regionserver/RSRpcServices;
     290: aload         6
     292: invokevirtual #76                 // Method org/apache/hadoop/hbase/shaded/protobuf/generated/ClientProtos$ScanRequest.getScannerId:()J
     295: invokevirtual #77                 // Method org/apache/hadoop/hbase/regionserver/RSRpcServices.getScanner:(J)Lorg/apache/hadoop/hbase/regionserver/RegionScanner;
     298: astore        7
     300: aload         7
     302: ifnull        369
     305: aload         7
     307: invokeinterface #78,  1           // InterfaceMethod org/apache/hadoop/hbase/regionserver/RegionScanner.getRegionInfo:()Lorg/apache/hadoop/hbase/client/RegionInfo;
     312: invokeinterface #64,  1           // InterfaceMethod org/apache/hadoop/hbase/client/RegionInfo.getTable:()Lorg/apache/hadoop/hbase/TableName;
     317: invokevirtual #65                 // Method org/apache/hadoop/hbase/TableName.isSystemTable:()Z
     320: ifeq          369
     323: getstatic     #66                 // Field LOG:Lorg/slf4j/Logger;
     326: invokeinterface #67,  1           // InterfaceMethod org/slf4j/Logger.isTraceEnabled:()Z
     331: ifeq          365
     334: getstatic     #66                 // Field LOG:Lorg/slf4j/Logger;
     337: new           #42                 // class java/lang/StringBuilder
     340: dup
     341: invokespecial #68                 // Method java/lang/StringBuilder."<init>":()V
     344: ldc           #79                 // String High priority scanner request
     346: invokevirtual #70                 // Method java/lang/StringBuilder.append:(Ljava/lang/String;)Ljava/lang/StringBuilder;
     349: aload         6
     351: invokestatic  #80                 // Method org/apache/hbase/thirdparty/com/google/protobuf/TextFormat.shortDebugString:(Lorg/apache/hbase/thirdparty/com/google/protobuf/MessageOrBuilder;)Ljava/lang/String;
     354: invokevirtual #70                 // Method java/lang/StringBuilder.append:(Ljava/lang/String;)Ljava/lang/StringBuilder;
     357: invokevirtual #47                 // Method java/lang/StringBuilder.toString:()Ljava/lang/String;
     360: invokeinterface #72,  2           // InterfaceMethod org/slf4j/Logger.trace:(Ljava/lang/String;)V
     365: sipush        200
     368: ireturn
     369: iconst_0
     370: ireturn
    Exception table:
       from    to  target type
          44   216   220   Class java/lang/Exception

  public long getDeadline(org.apache.hadoop.hbase.shaded.protobuf.generated.RPCProtos$RequestHeader, org.apache.hbase.thirdparty.com.google.protobuf.Message);
    Code:
       0: aload_2
       1: instanceof    #12                 // class org/apache/hadoop/hbase/shaded/protobuf/generated/ClientProtos$ScanRequest
       4: ifeq          50
       7: aload_2
       8: checkcast     #12                 // class org/apache/hadoop/hbase/shaded/protobuf/generated/ClientProtos$ScanRequest
      11: astore_3
      12: aload_3
      13: invokevirtual #75                 // Method org/apache/hadoop/hbase/shaded/protobuf/generated/ClientProtos$ScanRequest.hasScannerId:()Z
      16: ifne          21
      19: lconst_0
      20: lreturn
      21: aload_0
      22: getfield      #26                 // Field rpcServices:Lorg/apache/hadoop/hbase/regionserver/RSRpcServices;
      25: aload_3
      26: invokevirtual #76                 // Method org/apache/hadoop/hbase/shaded/protobuf/generated/ClientProtos$ScanRequest.getScannerId:()J
      29: invokevirtual #81                 // Method org/apache/hadoop/hbase/regionserver/RSRpcServices.getScannerVirtualTime:(J)J
      32: lstore        4
      34: lload         4
      36: l2f
      37: aload_0
      38: getfield      #41                 // Field scanVirtualTimeWeight:F
      41: fmul
      42: f2d
      43: invokestatic  #82                 // Method java/lang/Math.sqrt:(D)D
      46: invokestatic  #83                 // Method java/lang/Math.round:(D)J
      49: lreturn
      50: lconst_0
      51: lreturn

  void setRegionServer(org.apache.hadoop.hbase.regionserver.HRegionServer);
    Code:
       0: aload_0
       1: aload_1
       2: invokevirtual #84                 // Method org/apache/hadoop/hbase/regionserver/HRegionServer.getRSRpcServices:()Lorg/apache/hadoop/hbase/regionserver/RSRpcServices;
       5: putfield      #26                 // Field rpcServices:Lorg/apache/hadoop/hbase/regionserver/RSRpcServices;
       8: return

  static {};
    Code:
       0: ldc           #38                 // class org/apache/hadoop/hbase/regionserver/AnnotationReadingPriorityFunction
       2: invokevirtual #31                 // Method java/lang/Class.getName:()Ljava/lang/String;
       5: invokestatic  #85                 // Method org/slf4j/LoggerFactory.getLogger:(Ljava/lang/String;)Lorg/slf4j/Logger;
       8: putstatic     #66                 // Field LOG:Lorg/slf4j/Logger;
      11: return
}
