Compiled from "AssignmentManager.java"
public class org.apache.hadoop.hbase.master.assignment.AssignmentManager$RegionInTransitionStat {
  public org.apache.hadoop.hbase.master.assignment.AssignmentManager$RegionInTransitionStat(org.apache.hadoop.conf.Configuration);
    Code:
       0: aload_0
       1: invokespecial #2                  // Method java/lang/Object."<init>":()V
       4: aload_0
       5: aconst_null
       6: putfield      #3                  // Field ritsOverThreshold:Ljava/util/HashMap;
       9: aload_0
      10: lconst_0
      11: putfield      #4                  // Field oldestRITTime:J
      14: aload_0
      15: iconst_0
      16: putfield      #5                  // Field totalRITsTwiceThreshold:I
      19: aload_0
      20: iconst_0
      21: putfield      #6                  // Field totalRITs:I
      24: aload_0
      25: aload_1
      26: ldc           #7                  // String hbase.metrics.rit.stuck.warning.threshold
      28: ldc           #8                  // int 60000
      30: invokevirtual #9                  // Method org/apache/hadoop/conf/Configuration.getInt:(Ljava/lang/String;I)I
      33: putfield      #10                 // Field ritThreshold:I
      36: return

  public int getRITThreshold();
    Code:
       0: aload_0
       1: getfield      #10                 // Field ritThreshold:I
       4: ireturn

  public long getTimestamp();
    Code:
       0: aload_0
       1: getfield      #11                 // Field statTimestamp:J
       4: lreturn

  public int getTotalRITs();
    Code:
       0: aload_0
       1: getfield      #6                  // Field totalRITs:I
       4: ireturn

  public long getOldestRITTime();
    Code:
       0: aload_0
       1: getfield      #4                  // Field oldestRITTime:J
       4: lreturn

  public int getTotalRITsOverThreshold();
    Code:
       0: aload_0
       1: getfield      #3                  // Field ritsOverThreshold:Ljava/util/HashMap;
       4: astore_1
       5: aload_1
       6: ifnull        18
       9: aload_1
      10: invokeinterface #12,  1           // InterfaceMethod java/util/Map.size:()I
      15: goto          19
      18: iconst_0
      19: ireturn

  public boolean hasRegionsTwiceOverThreshold();
    Code:
       0: aload_0
       1: getfield      #5                  // Field totalRITsTwiceThreshold:I
       4: ifle          11
       7: iconst_1
       8: goto          12
      11: iconst_0
      12: ireturn

  public boolean hasRegionsOverThreshold();
    Code:
       0: aload_0
       1: getfield      #3                  // Field ritsOverThreshold:Ljava/util/HashMap;
       4: astore_1
       5: aload_1
       6: ifnull        22
       9: aload_1
      10: invokeinterface #13,  1           // InterfaceMethod java/util/Map.isEmpty:()Z
      15: ifne          22
      18: iconst_1
      19: goto          23
      22: iconst_0
      23: ireturn

  public java.util.Collection<org.apache.hadoop.hbase.master.RegionState> getRegionOverThreshold();
    Code:
       0: aload_0
       1: getfield      #3                  // Field ritsOverThreshold:Ljava/util/HashMap;
       4: astore_1
       5: aload_1
       6: ifnull        18
       9: aload_1
      10: invokeinterface #14,  1           // InterfaceMethod java/util/Map.values:()Ljava/util/Collection;
      15: goto          21
      18: invokestatic  #15                 // Method java/util/Collections.emptySet:()Ljava/util/Set;
      21: areturn

  public boolean isRegionOverThreshold(org.apache.hadoop.hbase.client.RegionInfo);
    Code:
       0: aload_0
       1: getfield      #3                  // Field ritsOverThreshold:Ljava/util/HashMap;
       4: astore_2
       5: aload_2
       6: ifnull        28
       9: aload_2
      10: aload_1
      11: invokeinterface #16,  1           // InterfaceMethod org/apache/hadoop/hbase/client/RegionInfo.getEncodedName:()Ljava/lang/String;
      16: invokeinterface #17,  2           // InterfaceMethod java/util/Map.containsKey:(Ljava/lang/Object;)Z
      21: ifeq          28
      24: iconst_1
      25: goto          29
      28: iconst_0
      29: ireturn

  public boolean isRegionTwiceOverThreshold(org.apache.hadoop.hbase.client.RegionInfo);
    Code:
       0: aload_0
       1: getfield      #3                  // Field ritsOverThreshold:Ljava/util/HashMap;
       4: astore_2
       5: aload_2
       6: ifnonnull     11
       9: iconst_0
      10: ireturn
      11: aload_2
      12: aload_1
      13: invokeinterface #16,  1           // InterfaceMethod org/apache/hadoop/hbase/client/RegionInfo.getEncodedName:()Ljava/lang/String;
      18: invokeinterface #18,  2           // InterfaceMethod java/util/Map.get:(Ljava/lang/Object;)Ljava/lang/Object;
      23: checkcast     #19                 // class org/apache/hadoop/hbase/master/RegionState
      26: astore_3
      27: aload_3
      28: ifnonnull     33
      31: iconst_0
      32: ireturn
      33: aload_0
      34: getfield      #11                 // Field statTimestamp:J
      37: aload_3
      38: invokevirtual #20                 // Method org/apache/hadoop/hbase/master/RegionState.getStamp:()J
      41: lsub
      42: aload_0
      43: getfield      #10                 // Field ritThreshold:I
      46: iconst_2
      47: imul
      48: i2l
      49: lcmp
      50: ifle          57
      53: iconst_1
      54: goto          58
      57: iconst_0
      58: ireturn

  protected void update(org.apache.hadoop.hbase.master.assignment.AssignmentManager);
    Code:
       0: aload_1
       1: invokevirtual #21                 // Method org/apache/hadoop/hbase/master/assignment/AssignmentManager.getRegionStates:()Lorg/apache/hadoop/hbase/master/assignment/RegionStates;
       4: astore_2
       5: aload_0
       6: invokestatic  #22                 // Method org/apache/hadoop/hbase/util/EnvironmentEdgeManager.currentTime:()J
       9: putfield      #11                 // Field statTimestamp:J
      12: aload_0
      13: aload_2
      14: invokevirtual #23                 // Method org/apache/hadoop/hbase/master/assignment/RegionStates.getRegionsStateInTransition:()Ljava/util/List;
      17: aload_0
      18: getfield      #11                 // Field statTimestamp:J
      21: invokespecial #24                 // Method update:(Ljava/util/Collection;J)V
      24: aload_0
      25: aload_2
      26: invokevirtual #25                 // Method org/apache/hadoop/hbase/master/assignment/RegionStates.getRegionFailedOpen:()Ljava/util/List;
      29: aload_0
      30: getfield      #11                 // Field statTimestamp:J
      33: invokespecial #24                 // Method update:(Ljava/util/Collection;J)V
      36: return
}
