Compiled from "AssignmentManager.java"
class org.apache.hadoop.hbase.master.assignment.AssignmentManager$RegionInTransitionChore extends org.apache.hadoop.hbase.procedure2.ProcedureInMemoryChore<org.apache.hadoop.hbase.master.procedure.MasterProcedureEnv> {
  public org.apache.hadoop.hbase.master.assignment.AssignmentManager$RegionInTransitionChore(int);
    Code:
       0: aload_0
       1: iload_1
       2: invokespecial #1                  // Method org/apache/hadoop/hbase/procedure2/ProcedureInMemoryChore."<init>":(I)V
       5: return

  protected void periodicExecute(org.apache.hadoop.hbase.master.procedure.MasterProcedureEnv);
    Code:
       0: aload_1
       1: invokevirtual #2                  // Method org/apache/hadoop/hbase/master/procedure/MasterProcedureEnv.getAssignmentManager:()Lorg/apache/hadoop/hbase/master/assignment/AssignmentManager;
       4: astore_2
       5: aload_2
       6: invokevirtual #3                  // Method org/apache/hadoop/hbase/master/assignment/AssignmentManager.computeRegionInTransitionStat:()Lorg/apache/hadoop/hbase/master/assignment/AssignmentManager$RegionInTransitionStat;
       9: astore_3
      10: aload_3
      11: invokevirtual #4                  // Method org/apache/hadoop/hbase/master/assignment/AssignmentManager$RegionInTransitionStat.hasRegionsOverThreshold:()Z
      14: ifeq          62
      17: aload_3
      18: invokevirtual #5                  // Method org/apache/hadoop/hbase/master/assignment/AssignmentManager$RegionInTransitionStat.getRegionOverThreshold:()Ljava/util/Collection;
      21: invokeinterface #6,  1            // InterfaceMethod java/util/Collection.iterator:()Ljava/util/Iterator;
      26: astore        4
      28: aload         4
      30: invokeinterface #7,  1            // InterfaceMethod java/util/Iterator.hasNext:()Z
      35: ifeq          62
      38: aload         4
      40: invokeinterface #8,  1            // InterfaceMethod java/util/Iterator.next:()Ljava/lang/Object;
      45: checkcast     #9                  // class org/apache/hadoop/hbase/master/RegionState
      48: astore        5
      50: aload_2
      51: aload         5
      53: invokevirtual #10                 // Method org/apache/hadoop/hbase/master/RegionState.getRegion:()Lorg/apache/hadoop/hbase/client/RegionInfo;
      56: invokestatic  #11                 // Method org/apache/hadoop/hbase/master/assignment/AssignmentManager.access$000:(Lorg/apache/hadoop/hbase/master/assignment/AssignmentManager;Lorg/apache/hadoop/hbase/client/RegionInfo;)V
      59: goto          28
      62: aload_2
      63: aload_3
      64: invokestatic  #12                 // Method org/apache/hadoop/hbase/master/assignment/AssignmentManager.access$100:(Lorg/apache/hadoop/hbase/master/assignment/AssignmentManager;Lorg/apache/hadoop/hbase/master/assignment/AssignmentManager$RegionInTransitionStat;)V
      67: return

  protected void periodicExecute(java.lang.Object);
    Code:
       0: aload_0
       1: aload_1
       2: checkcast     #13                 // class org/apache/hadoop/hbase/master/procedure/MasterProcedureEnv
       5: invokevirtual #14                 // Method periodicExecute:(Lorg/apache/hadoop/hbase/master/procedure/MasterProcedureEnv;)V
       8: return
}
