Compiled from "AsyncNonMetaRegionLocator.java"
final class org.apache.hadoop.hbase.client.AsyncNonMetaRegionLocator$TableCache {
  static final boolean $assertionsDisabled;

  public boolean hasQuota(int);
    Code:
       0: aload_0
       1: getfield      #3                  // Field pendingRequests:Ljava/util/Set;
       4: invokeinterface #13,  1           // InterfaceMethod java/util/Set.size:()I
       9: iload_1
      10: if_icmpge     17
      13: iconst_1
      14: goto          18
      17: iconst_0
      18: ireturn

  public boolean isPending(org.apache.hadoop.hbase.client.AsyncNonMetaRegionLocator$LocateRequest);
    Code:
       0: aload_0
       1: getfield      #3                  // Field pendingRequests:Ljava/util/Set;
       4: aload_1
       5: invokeinterface #14,  2           // InterfaceMethod java/util/Set.contains:(Ljava/lang/Object;)Z
      10: ireturn

  public void send(org.apache.hadoop.hbase.client.AsyncNonMetaRegionLocator$LocateRequest);
    Code:
       0: aload_0
       1: getfield      #3                  // Field pendingRequests:Ljava/util/Set;
       4: aload_1
       5: invokeinterface #15,  2           // InterfaceMethod java/util/Set.add:(Ljava/lang/Object;)Z
      10: pop
      11: return

  public java.util.Optional<org.apache.hadoop.hbase.client.AsyncNonMetaRegionLocator$LocateRequest> getCandidate();
    Code:
       0: aload_0
       1: getfield      #2                  // Field allRequests:Ljava/util/Map;
       4: invokeinterface #16,  1           // InterfaceMethod java/util/Map.keySet:()Ljava/util/Set;
       9: invokeinterface #17,  1           // InterfaceMethod java/util/Set.stream:()Ljava/util/stream/Stream;
      14: aload_0
      15: invokedynamic #18,  0             // InvokeDynamic #0:test:(Lorg/apache/hadoop/hbase/client/AsyncNonMetaRegionLocator$TableCache;)Ljava/util/function/Predicate;
      20: invokeinterface #19,  2           // InterfaceMethod java/util/stream/Stream.filter:(Ljava/util/function/Predicate;)Ljava/util/stream/Stream;
      25: invokeinterface #20,  1           // InterfaceMethod java/util/stream/Stream.findFirst:()Ljava/util/Optional;
      30: areturn

  public void clearCompletedRequests(java.util.Optional<org.apache.hadoop.hbase.RegionLocations>);
    Code:
       0: aload_0
       1: getfield      #2                  // Field allRequests:Ljava/util/Map;
       4: invokeinterface #21,  1           // InterfaceMethod java/util/Map.entrySet:()Ljava/util/Set;
       9: invokeinterface #22,  1           // InterfaceMethod java/util/Set.iterator:()Ljava/util/Iterator;
      14: astore_2
      15: aload_2
      16: invokeinterface #23,  1           // InterfaceMethod java/util/Iterator.hasNext:()Z
      21: ifeq          69
      24: aload_2
      25: invokeinterface #24,  1           // InterfaceMethod java/util/Iterator.next:()Ljava/lang/Object;
      30: checkcast     #25                 // class java/util/Map$Entry
      33: astore_3
      34: aload_0
      35: aload_3
      36: invokeinterface #26,  1           // InterfaceMethod java/util/Map$Entry.getKey:()Ljava/lang/Object;
      41: checkcast     #27                 // class org/apache/hadoop/hbase/client/AsyncNonMetaRegionLocator$LocateRequest
      44: aload_3
      45: invokeinterface #28,  1           // InterfaceMethod java/util/Map$Entry.getValue:()Ljava/lang/Object;
      50: checkcast     #29                 // class java/util/concurrent/CompletableFuture
      53: aload_1
      54: invokespecial #30                 // Method tryComplete:(Lorg/apache/hadoop/hbase/client/AsyncNonMetaRegionLocator$LocateRequest;Ljava/util/concurrent/CompletableFuture;Ljava/util/Optional;)Z
      57: ifeq          66
      60: aload_2
      61: invokeinterface #31,  1           // InterfaceMethod java/util/Iterator.remove:()V
      66: goto          15
      69: return

  static java.util.concurrent.ConcurrentNavigableMap access$200(org.apache.hadoop.hbase.client.AsyncNonMetaRegionLocator$TableCache);
    Code:
       0: aload_0
       1: getfield      #4                  // Field cache:Ljava/util/concurrent/ConcurrentNavigableMap;
       4: areturn

  static java.util.Set access$300(org.apache.hadoop.hbase.client.AsyncNonMetaRegionLocator$TableCache);
    Code:
       0: aload_0
       1: getfield      #3                  // Field pendingRequests:Ljava/util/Set;
       4: areturn

  static java.util.Map access$400(org.apache.hadoop.hbase.client.AsyncNonMetaRegionLocator$TableCache);
    Code:
       0: aload_0
       1: getfield      #2                  // Field allRequests:Ljava/util/Map;
       4: areturn

  org.apache.hadoop.hbase.client.AsyncNonMetaRegionLocator$TableCache(org.apache.hadoop.hbase.client.AsyncNonMetaRegionLocator$1);
    Code:
       0: aload_0
       1: invokespecial #1                  // Method "<init>":()V
       4: return

  static {};
    Code:
       0: ldc           #55                 // class org/apache/hadoop/hbase/client/AsyncNonMetaRegionLocator
       2: invokevirtual #56                 // Method java/lang/Class.desiredAssertionStatus:()Z
       5: ifne          12
       8: iconst_1
       9: goto          13
      12: iconst_0
      13: putstatic     #39                 // Field $assertionsDisabled:Z
      16: return
}
