Compiled from "AsyncBufferedMutatorImpl.java"
class org.apache.hadoop.hbase.client.AsyncBufferedMutatorImpl implements org.apache.hadoop.hbase.client.AsyncBufferedMutator {
  org.apache.hbase.thirdparty.io.netty.util.Timeout periodicFlushTask;

  static final boolean $assertionsDisabled;

  org.apache.hadoop.hbase.client.AsyncBufferedMutatorImpl(org.apache.hbase.thirdparty.io.netty.util.HashedWheelTimer, org.apache.hadoop.hbase.client.AsyncTable<?>, long, long, int);
    Code:
       0: aload_0
       1: invokespecial #1                  // Method java/lang/Object."<init>":()V
       4: aload_0
       5: new           #2                  // class java/util/ArrayList
       8: dup
       9: invokespecial #3                  // Method java/util/ArrayList."<init>":()V
      12: putfield      #4                  // Field mutations:Ljava/util/List;
      15: aload_0
      16: new           #2                  // class java/util/ArrayList
      19: dup
      20: invokespecial #3                  // Method java/util/ArrayList."<init>":()V
      23: putfield      #5                  // Field futures:Ljava/util/List;
      26: aload_0
      27: aload_1
      28: putfield      #6                  // Field periodicalFlushTimer:Lorg/apache/hbase/thirdparty/io/netty/util/HashedWheelTimer;
      31: aload_0
      32: aload_2
      33: putfield      #7                  // Field table:Lorg/apache/hadoop/hbase/client/AsyncTable;
      36: aload_0
      37: lload_3
      38: putfield      #8                  // Field writeBufferSize:J
      41: aload_0
      42: lload         5
      44: putfield      #9                  // Field periodicFlushTimeoutNs:J
      47: aload_0
      48: iload         7
      50: putfield      #10                 // Field maxKeyValueSize:I
      53: return

  public org.apache.hadoop.hbase.TableName getName();
    Code:
       0: aload_0
       1: getfield      #7                  // Field table:Lorg/apache/hadoop/hbase/client/AsyncTable;
       4: invokeinterface #11,  1           // InterfaceMethod org/apache/hadoop/hbase/client/AsyncTable.getName:()Lorg/apache/hadoop/hbase/TableName;
       9: areturn

  public org.apache.hadoop.conf.Configuration getConfiguration();
    Code:
       0: aload_0
       1: getfield      #7                  // Field table:Lorg/apache/hadoop/hbase/client/AsyncTable;
       4: invokeinterface #12,  1           // InterfaceMethod org/apache/hadoop/hbase/client/AsyncTable.getConfiguration:()Lorg/apache/hadoop/conf/Configuration;
       9: areturn

  protected void internalFlush();
    Code:
       0: aload_0
       1: getfield      #13                 // Field periodicFlushTask:Lorg/apache/hbase/thirdparty/io/netty/util/Timeout;
       4: ifnull        22
       7: aload_0
       8: getfield      #13                 // Field periodicFlushTask:Lorg/apache/hbase/thirdparty/io/netty/util/Timeout;
      11: invokeinterface #14,  1           // InterfaceMethod org/apache/hbase/thirdparty/io/netty/util/Timeout.cancel:()Z
      16: pop
      17: aload_0
      18: aconst_null
      19: putfield      #13                 // Field periodicFlushTask:Lorg/apache/hbase/thirdparty/io/netty/util/Timeout;
      22: aload_0
      23: getfield      #4                  // Field mutations:Ljava/util/List;
      26: astore_1
      27: aload_1
      28: invokeinterface #15,  1           // InterfaceMethod java/util/List.isEmpty:()Z
      33: ifeq          37
      36: return
      37: aload_0
      38: getfield      #5                  // Field futures:Ljava/util/List;
      41: astore_2
      42: getstatic     #16                 // Field $assertionsDisabled:Z
      45: ifne          71
      48: aload_1
      49: invokeinterface #17,  1           // InterfaceMethod java/util/List.size:()I
      54: aload_2
      55: invokeinterface #17,  1           // InterfaceMethod java/util/List.size:()I
      60: if_icmpeq     71
      63: new           #18                 // class java/lang/AssertionError
      66: dup
      67: invokespecial #19                 // Method java/lang/AssertionError."<init>":()V
      70: athrow
      71: aload_0
      72: new           #2                  // class java/util/ArrayList
      75: dup
      76: invokespecial #3                  // Method java/util/ArrayList."<init>":()V
      79: putfield      #4                  // Field mutations:Ljava/util/List;
      82: aload_0
      83: new           #2                  // class java/util/ArrayList
      86: dup
      87: invokespecial #3                  // Method java/util/ArrayList."<init>":()V
      90: putfield      #5                  // Field futures:Ljava/util/List;
      93: aload_0
      94: lconst_0
      95: putfield      #20                 // Field bufferedSize:J
      98: aload_2
      99: invokeinterface #21,  1           // InterfaceMethod java/util/List.iterator:()Ljava/util/Iterator;
     104: astore_3
     105: aload_0
     106: getfield      #7                  // Field table:Lorg/apache/hadoop/hbase/client/AsyncTable;
     109: aload_1
     110: invokeinterface #22,  2           // InterfaceMethod org/apache/hadoop/hbase/client/AsyncTable.batch:(Ljava/util/List;)Ljava/util/List;
     115: invokeinterface #21,  1           // InterfaceMethod java/util/List.iterator:()Ljava/util/Iterator;
     120: astore        4
     122: aload         4
     124: invokeinterface #23,  1           // InterfaceMethod java/util/Iterator.hasNext:()Z
     129: ifeq          170
     132: aload         4
     134: invokeinterface #24,  1           // InterfaceMethod java/util/Iterator.next:()Ljava/lang/Object;
     139: checkcast     #25                 // class java/util/concurrent/CompletableFuture
     142: astore        5
     144: aload_3
     145: invokeinterface #24,  1           // InterfaceMethod java/util/Iterator.next:()Ljava/lang/Object;
     150: checkcast     #25                 // class java/util/concurrent/CompletableFuture
     153: astore        6
     155: aload         5
     157: aload         6
     159: invokedynamic #26,  0             // InvokeDynamic #0:accept:(Ljava/util/concurrent/CompletableFuture;)Ljava/util/function/BiConsumer;
     164: invokestatic  #27                 // Method org/apache/hadoop/hbase/util/FutureUtils.addListener:(Ljava/util/concurrent/CompletableFuture;Ljava/util/function/BiConsumer;)V
     167: goto          122
     170: return

  public java.util.List<java.util.concurrent.CompletableFuture<java.lang.Void>> mutate(java.util.List<? extends org.apache.hadoop.hbase.client.Mutation>);
    Code:
       0: invokedynamic #28,  0             // InvokeDynamic #1:get:()Ljava/util/function/Supplier;
       5: invokestatic  #29                 // InterfaceMethod java/util/stream/Stream.generate:(Ljava/util/function/Supplier;)Ljava/util/stream/Stream;
       8: aload_1
       9: invokeinterface #17,  1           // InterfaceMethod java/util/List.size:()I
      14: i2l
      15: invokeinterface #30,  3           // InterfaceMethod java/util/stream/Stream.limit:(J)Ljava/util/stream/Stream;
      20: invokestatic  #31                 // Method java/util/stream/Collectors.toList:()Ljava/util/stream/Collector;
      23: invokeinterface #32,  2           // InterfaceMethod java/util/stream/Stream.collect:(Ljava/util/stream/Collector;)Ljava/lang/Object;
      28: checkcast     #33                 // class java/util/List
      31: astore_2
      32: lconst_0
      33: lstore_3
      34: aload_1
      35: invokeinterface #21,  1           // InterfaceMethod java/util/List.iterator:()Ljava/util/Iterator;
      40: astore        5
      42: aload         5
      44: invokeinterface #23,  1           // InterfaceMethod java/util/Iterator.hasNext:()Z
      49: ifeq          95
      52: aload         5
      54: invokeinterface #24,  1           // InterfaceMethod java/util/Iterator.next:()Ljava/lang/Object;
      59: checkcast     #34                 // class org/apache/hadoop/hbase/client/Mutation
      62: astore        6
      64: lload_3
      65: aload         6
      67: invokevirtual #35                 // Method org/apache/hadoop/hbase/client/Mutation.heapSize:()J
      70: ladd
      71: lstore_3
      72: aload         6
      74: instanceof    #36                 // class org/apache/hadoop/hbase/client/Put
      77: ifeq          92
      80: aload         6
      82: checkcast     #36                 // class org/apache/hadoop/hbase/client/Put
      85: aload_0
      86: getfield      #10                 // Field maxKeyValueSize:I
      89: invokestatic  #37                 // Method org/apache/hadoop/hbase/client/ConnectionUtils.validatePut:(Lorg/apache/hadoop/hbase/client/Put;I)V
      92: goto          42
      95: aload_0
      96: dup
      97: astore        5
      99: monitorenter
     100: aload_0
     101: getfield      #38                 // Field closed:Z
     104: ifeq          136
     107: new           #39                 // class java/io/IOException
     110: dup
     111: ldc           #40                 // String Already closed
     113: invokespecial #41                 // Method java/io/IOException."<init>":(Ljava/lang/String;)V
     116: astore        6
     118: aload_2
     119: aload         6
     121: invokedynamic #42,  0             // InvokeDynamic #2:accept:(Ljava/io/IOException;)Ljava/util/function/Consumer;
     126: invokeinterface #43,  2           // InterfaceMethod java/util/List.forEach:(Ljava/util/function/Consumer;)V
     131: aload_2
     132: aload         5
     134: monitorexit
     135: areturn
     136: aload_0
     137: getfield      #4                  // Field mutations:Ljava/util/List;
     140: invokeinterface #15,  1           // InterfaceMethod java/util/List.isEmpty:()Z
     145: ifeq          181
     148: aload_0
     149: getfield      #9                  // Field periodicFlushTimeoutNs:J
     152: lconst_0
     153: lcmp
     154: ifle          181
     157: aload_0
     158: aload_0
     159: getfield      #6                  // Field periodicalFlushTimer:Lorg/apache/hbase/thirdparty/io/netty/util/HashedWheelTimer;
     162: aload_0
     163: invokedynamic #44,  0             // InvokeDynamic #3:run:(Lorg/apache/hadoop/hbase/client/AsyncBufferedMutatorImpl;)Lorg/apache/hbase/thirdparty/io/netty/util/TimerTask;
     168: aload_0
     169: getfield      #9                  // Field periodicFlushTimeoutNs:J
     172: getstatic     #45                 // Field java/util/concurrent/TimeUnit.NANOSECONDS:Ljava/util/concurrent/TimeUnit;
     175: invokevirtual #46                 // Method org/apache/hbase/thirdparty/io/netty/util/HashedWheelTimer.newTimeout:(Lorg/apache/hbase/thirdparty/io/netty/util/TimerTask;JLjava/util/concurrent/TimeUnit;)Lorg/apache/hbase/thirdparty/io/netty/util/Timeout;
     178: putfield      #13                 // Field periodicFlushTask:Lorg/apache/hbase/thirdparty/io/netty/util/Timeout;
     181: aload_0
     182: getfield      #4                  // Field mutations:Ljava/util/List;
     185: aload_1
     186: invokeinterface #47,  2           // InterfaceMethod java/util/List.addAll:(Ljava/util/Collection;)Z
     191: pop
     192: aload_0
     193: getfield      #5                  // Field futures:Ljava/util/List;
     196: aload_2
     197: invokeinterface #47,  2           // InterfaceMethod java/util/List.addAll:(Ljava/util/Collection;)Z
     202: pop
     203: aload_0
     204: dup
     205: getfield      #20                 // Field bufferedSize:J
     208: lload_3
     209: ladd
     210: putfield      #20                 // Field bufferedSize:J
     213: aload_0
     214: getfield      #20                 // Field bufferedSize:J
     217: aload_0
     218: getfield      #8                  // Field writeBufferSize:J
     221: lcmp
     222: iflt          229
     225: aload_0
     226: invokevirtual #48                 // Method internalFlush:()V
     229: aload         5
     231: monitorexit
     232: goto          243
     235: astore        7
     237: aload         5
     239: monitorexit
     240: aload         7
     242: athrow
     243: aload_2
     244: areturn
    Exception table:
       from    to  target type
         100   135   235   any
         136   232   235   any
         235   240   235   any

  public synchronized void flush();
    Code:
       0: aload_0
       1: invokevirtual #48                 // Method internalFlush:()V
       4: return

  public synchronized void close();
    Code:
       0: aload_0
       1: invokevirtual #48                 // Method internalFlush:()V
       4: aload_0
       5: iconst_1
       6: putfield      #38                 // Field closed:Z
       9: return

  public long getWriteBufferSize();
    Code:
       0: aload_0
       1: getfield      #8                  // Field writeBufferSize:J
       4: lreturn

  public long getPeriodicalFlushTimeout(java.util.concurrent.TimeUnit);
    Code:
       0: aload_1
       1: aload_0
       2: getfield      #9                  // Field periodicFlushTimeoutNs:J
       5: getstatic     #45                 // Field java/util/concurrent/TimeUnit.NANOSECONDS:Ljava/util/concurrent/TimeUnit;
       8: invokevirtual #49                 // Method java/util/concurrent/TimeUnit.convert:(JLjava/util/concurrent/TimeUnit;)J
      11: lreturn

  static {};
    Code:
       0: ldc           #52                 // class org/apache/hadoop/hbase/client/AsyncBufferedMutatorImpl
       2: invokevirtual #53                 // Method java/lang/Class.desiredAssertionStatus:()Z
       5: ifne          12
       8: iconst_1
       9: goto          13
      12: iconst_0
      13: putstatic     #16                 // Field $assertionsDisabled:Z
      16: return
}
