Compiled from "AsyncRegistryFactory.java"
final class org.apache.hadoop.hbase.client.AsyncRegistryFactory {
  static final java.lang.String REGISTRY_IMPL_CONF_KEY;

  static org.apache.hadoop.hbase.client.AsyncRegistry getRegistry(org.apache.hadoop.conf.Configuration);
    Code:
       0: aload_0
       1: ldc           #3                  // String hbase.client.registry.impl
       3: ldc           #4                  // class org/apache/hadoop/hbase/client/ZKAsyncRegistry
       5: ldc           #5                  // class org/apache/hadoop/hbase/client/AsyncRegistry
       7: invokevirtual #6                  // Method org/apache/hadoop/conf/Configuration.getClass:(Ljava/lang/String;Ljava/lang/Class;Ljava/lang/Class;)Ljava/lang/Class;
      10: astore_1
      11: aload_1
      12: iconst_1
      13: anewarray     #7                  // class java/lang/Object
      16: dup
      17: iconst_0
      18: aload_0
      19: aastore
      20: invokestatic  #8                  // Method org/apache/hadoop/hbase/util/ReflectionUtils.newInstance:(Ljava/lang/Class;[Ljava/lang/Object;)Ljava/lang/Object;
      23: checkcast     #5                  // class org/apache/hadoop/hbase/client/AsyncRegistry
      26: areturn
}
