Compiled from "AsyncTableRegionLocatorImpl.java"
class org.apache.hadoop.hbase.client.AsyncTableRegionLocatorImpl implements org.apache.hadoop.hbase.client.AsyncTableRegionLocator {
  public org.apache.hadoop.hbase.client.AsyncTableRegionLocatorImpl(org.apache.hadoop.hbase.TableName, org.apache.hadoop.hbase.client.AsyncConnectionImpl);
    Code:
       0: aload_0
       1: invokespecial #1                  // Method java/lang/Object."<init>":()V
       4: aload_0
       5: aload_1
       6: putfield      #2                  // Field tableName:Lorg/apache/hadoop/hbase/TableName;
       9: aload_0
      10: aload_2
      11: putfield      #3                  // Field conn:Lorg/apache/hadoop/hbase/client/AsyncConnectionImpl;
      14: return

  public org.apache.hadoop.hbase.TableName getName();
    Code:
       0: aload_0
       1: getfield      #2                  // Field tableName:Lorg/apache/hadoop/hbase/TableName;
       4: areturn

  public java.util.concurrent.CompletableFuture<org.apache.hadoop.hbase.HRegionLocation> getRegionLocation(byte[], int, boolean);
    Code:
       0: aload_0
       1: getfield      #3                  // Field conn:Lorg/apache/hadoop/hbase/client/AsyncConnectionImpl;
       4: invokevirtual #4                  // Method org/apache/hadoop/hbase/client/AsyncConnectionImpl.getLocator:()Lorg/apache/hadoop/hbase/client/AsyncRegionLocator;
       7: aload_0
       8: getfield      #2                  // Field tableName:Lorg/apache/hadoop/hbase/TableName;
      11: aload_1
      12: iload_2
      13: getstatic     #5                  // Field org/apache/hadoop/hbase/client/RegionLocateType.CURRENT:Lorg/apache/hadoop/hbase/client/RegionLocateType;
      16: iload_3
      17: ldc2_w        #6                  // long -1l
      20: invokevirtual #8                  // Method org/apache/hadoop/hbase/client/AsyncRegionLocator.getRegionLocation:(Lorg/apache/hadoop/hbase/TableName;[BILorg/apache/hadoop/hbase/client/RegionLocateType;ZJ)Ljava/util/concurrent/CompletableFuture;
      23: areturn

  public java.util.concurrent.CompletableFuture<java.util.List<org.apache.hadoop.hbase.HRegionLocation>> getAllRegionLocations();
    Code:
       0: aload_0
       1: getfield      #2                  // Field tableName:Lorg/apache/hadoop/hbase/TableName;
       4: invokestatic  #9                  // Method org/apache/hadoop/hbase/TableName.isMetaTableName:(Lorg/apache/hadoop/hbase/TableName;)Z
       7: ifeq          31
      10: aload_0
      11: getfield      #3                  // Field conn:Lorg/apache/hadoop/hbase/client/AsyncConnectionImpl;
      14: getfield      #10                 // Field org/apache/hadoop/hbase/client/AsyncConnectionImpl.registry:Lorg/apache/hadoop/hbase/client/AsyncRegistry;
      17: invokeinterface #11,  1           // InterfaceMethod org/apache/hadoop/hbase/client/AsyncRegistry.getMetaRegionLocation:()Ljava/util/concurrent/CompletableFuture;
      22: invokedynamic #12,  0             // InvokeDynamic #0:apply:()Ljava/util/function/Function;
      27: invokevirtual #13                 // Method java/util/concurrent/CompletableFuture.thenApply:(Ljava/util/function/Function;)Ljava/util/concurrent/CompletableFuture;
      30: areturn
      31: aload_0
      32: getfield      #3                  // Field conn:Lorg/apache/hadoop/hbase/client/AsyncConnectionImpl;
      35: getstatic     #14                 // Field org/apache/hadoop/hbase/TableName.META_TABLE_NAME:Lorg/apache/hadoop/hbase/TableName;
      38: invokevirtual #15                 // Method org/apache/hadoop/hbase/client/AsyncConnectionImpl.getTable:(Lorg/apache/hadoop/hbase/TableName;)Lorg/apache/hadoop/hbase/client/AsyncTable;
      41: aload_0
      42: getfield      #2                  // Field tableName:Lorg/apache/hadoop/hbase/TableName;
      45: invokestatic  #16                 // Method java/util/Optional.of:(Ljava/lang/Object;)Ljava/util/Optional;
      48: invokestatic  #17                 // Method org/apache/hadoop/hbase/AsyncMetaTableAccessor.getTableHRegionLocations:(Lorg/apache/hadoop/hbase/client/AsyncTable;Ljava/util/Optional;)Ljava/util/concurrent/CompletableFuture;
      51: areturn

  public java.util.concurrent.CompletableFuture<java.util.List<org.apache.hadoop.hbase.HRegionLocation>> getRegionLocations(byte[], boolean);
    Code:
       0: aload_0
       1: getfield      #3                  // Field conn:Lorg/apache/hadoop/hbase/client/AsyncConnectionImpl;
       4: invokevirtual #4                  // Method org/apache/hadoop/hbase/client/AsyncConnectionImpl.getLocator:()Lorg/apache/hadoop/hbase/client/AsyncRegionLocator;
       7: aload_0
       8: getfield      #2                  // Field tableName:Lorg/apache/hadoop/hbase/TableName;
      11: aload_1
      12: getstatic     #5                  // Field org/apache/hadoop/hbase/client/RegionLocateType.CURRENT:Lorg/apache/hadoop/hbase/client/RegionLocateType;
      15: iload_2
      16: ldc2_w        #6                  // long -1l
      19: invokevirtual #18                 // Method org/apache/hadoop/hbase/client/AsyncRegionLocator.getRegionLocations:(Lorg/apache/hadoop/hbase/TableName;[BLorg/apache/hadoop/hbase/client/RegionLocateType;ZJ)Ljava/util/concurrent/CompletableFuture;
      22: invokedynamic #19,  0             // InvokeDynamic #1:apply:()Ljava/util/function/Function;
      27: invokevirtual #13                 // Method java/util/concurrent/CompletableFuture.thenApply:(Ljava/util/function/Function;)Ljava/util/concurrent/CompletableFuture;
      30: areturn

  public void clearRegionLocationCache();
    Code:
       0: aload_0
       1: getfield      #3                  // Field conn:Lorg/apache/hadoop/hbase/client/AsyncConnectionImpl;
       4: invokevirtual #4                  // Method org/apache/hadoop/hbase/client/AsyncConnectionImpl.getLocator:()Lorg/apache/hadoop/hbase/client/AsyncRegionLocator;
       7: aload_0
       8: getfield      #2                  // Field tableName:Lorg/apache/hadoop/hbase/TableName;
      11: invokevirtual #20                 // Method org/apache/hadoop/hbase/client/AsyncRegionLocator.clearCache:(Lorg/apache/hadoop/hbase/TableName;)V
      14: return
}
