Compiled from "AsyncBufferedMutatorBuilderImpl.java"
class org.apache.hadoop.hbase.client.AsyncBufferedMutatorBuilderImpl implements org.apache.hadoop.hbase.client.AsyncBufferedMutatorBuilder {
  public org.apache.hadoop.hbase.client.AsyncBufferedMutatorBuilderImpl(org.apache.hadoop.hbase.client.AsyncConnectionConfiguration, org.apache.hadoop.hbase.client.AsyncTableBuilder<?>, org.apache.hbase.thirdparty.io.netty.util.HashedWheelTimer);
    Code:
       0: aload_0
       1: invokespecial #1                  // Method java/lang/Object."<init>":()V
       4: aload_0
       5: aload_2
       6: putfield      #2                  // Field tableBuilder:Lorg/apache/hadoop/hbase/client/AsyncTableBuilder;
       9: aload_0
      10: aload_1
      11: invokevirtual #3                  // Method org/apache/hadoop/hbase/client/AsyncConnectionConfiguration.getWriteBufferSize:()J
      14: putfield      #4                  // Field writeBufferSize:J
      17: aload_0
      18: aload_1
      19: invokevirtual #5                  // Method org/apache/hadoop/hbase/client/AsyncConnectionConfiguration.getWriteBufferPeriodicFlushTimeoutNs:()J
      22: putfield      #6                  // Field periodicFlushTimeoutNs:J
      25: aload_0
      26: aload_1
      27: invokevirtual #7                  // Method org/apache/hadoop/hbase/client/AsyncConnectionConfiguration.getMaxKeyValueSize:()I
      30: putfield      #8                  // Field maxKeyValueSize:I
      33: aload_0
      34: aload_3
      35: putfield      #9                  // Field periodicalFlushTimer:Lorg/apache/hbase/thirdparty/io/netty/util/HashedWheelTimer;
      38: return

  public org.apache.hadoop.hbase.client.AsyncBufferedMutatorBuilder setOperationTimeout(long, java.util.concurrent.TimeUnit);
    Code:
       0: aload_0
       1: getfield      #2                  // Field tableBuilder:Lorg/apache/hadoop/hbase/client/AsyncTableBuilder;
       4: lload_1
       5: aload_3
       6: invokeinterface #10,  4           // InterfaceMethod org/apache/hadoop/hbase/client/AsyncTableBuilder.setOperationTimeout:(JLjava/util/concurrent/TimeUnit;)Lorg/apache/hadoop/hbase/client/AsyncTableBuilder;
      11: pop
      12: aload_0
      13: areturn

  public org.apache.hadoop.hbase.client.AsyncBufferedMutatorBuilder setRpcTimeout(long, java.util.concurrent.TimeUnit);
    Code:
       0: aload_0
       1: getfield      #2                  // Field tableBuilder:Lorg/apache/hadoop/hbase/client/AsyncTableBuilder;
       4: lload_1
       5: aload_3
       6: invokeinterface #11,  4           // InterfaceMethod org/apache/hadoop/hbase/client/AsyncTableBuilder.setRpcTimeout:(JLjava/util/concurrent/TimeUnit;)Lorg/apache/hadoop/hbase/client/AsyncTableBuilder;
      11: pop
      12: aload_0
      13: areturn

  public org.apache.hadoop.hbase.client.AsyncBufferedMutatorBuilder setRetryPause(long, java.util.concurrent.TimeUnit);
    Code:
       0: aload_0
       1: getfield      #2                  // Field tableBuilder:Lorg/apache/hadoop/hbase/client/AsyncTableBuilder;
       4: lload_1
       5: aload_3
       6: invokeinterface #12,  4           // InterfaceMethod org/apache/hadoop/hbase/client/AsyncTableBuilder.setRetryPause:(JLjava/util/concurrent/TimeUnit;)Lorg/apache/hadoop/hbase/client/AsyncTableBuilder;
      11: pop
      12: aload_0
      13: areturn

  public org.apache.hadoop.hbase.client.AsyncBufferedMutatorBuilder setMaxAttempts(int);
    Code:
       0: aload_0
       1: getfield      #2                  // Field tableBuilder:Lorg/apache/hadoop/hbase/client/AsyncTableBuilder;
       4: iload_1
       5: invokeinterface #13,  2           // InterfaceMethod org/apache/hadoop/hbase/client/AsyncTableBuilder.setMaxAttempts:(I)Lorg/apache/hadoop/hbase/client/AsyncTableBuilder;
      10: pop
      11: aload_0
      12: areturn

  public org.apache.hadoop.hbase.client.AsyncBufferedMutatorBuilder setStartLogErrorsCnt(int);
    Code:
       0: aload_0
       1: getfield      #2                  // Field tableBuilder:Lorg/apache/hadoop/hbase/client/AsyncTableBuilder;
       4: iload_1
       5: invokeinterface #14,  2           // InterfaceMethod org/apache/hadoop/hbase/client/AsyncTableBuilder.setStartLogErrorsCnt:(I)Lorg/apache/hadoop/hbase/client/AsyncTableBuilder;
      10: pop
      11: aload_0
      12: areturn

  public org.apache.hadoop.hbase.client.AsyncBufferedMutatorBuilder setWriteBufferSize(long);
    Code:
       0: lload_1
       1: lconst_0
       2: lcmp
       3: ifle          10
       6: iconst_1
       7: goto          11
      10: iconst_0
      11: ldc           #15                 // String writeBufferSize %d must be > 0
      13: lload_1
      14: invokestatic  #16                 // Method org/apache/hbase/thirdparty/com/google/common/base/Preconditions.checkArgument:(ZLjava/lang/String;J)V
      17: aload_0
      18: lload_1
      19: putfield      #4                  // Field writeBufferSize:J
      22: aload_0
      23: areturn

  public org.apache.hadoop.hbase.client.AsyncBufferedMutatorBuilder setWriteBufferPeriodicFlush(long, java.util.concurrent.TimeUnit);
    Code:
       0: aload_0
       1: aload_3
       2: lload_1
       3: invokevirtual #17                 // Method java/util/concurrent/TimeUnit.toNanos:(J)J
       6: putfield      #6                  // Field periodicFlushTimeoutNs:J
       9: aload_0
      10: areturn

  public org.apache.hadoop.hbase.client.AsyncBufferedMutatorBuilder setMaxKeyValueSize(int);
    Code:
       0: iload_1
       1: ifle          8
       4: iconst_1
       5: goto          9
       8: iconst_0
       9: ldc           #18                 // String maxKeyValueSize %d must be > 0
      11: iload_1
      12: invokestatic  #19                 // Method org/apache/hbase/thirdparty/com/google/common/base/Preconditions.checkArgument:(ZLjava/lang/String;I)V
      15: aload_0
      16: iload_1
      17: putfield      #8                  // Field maxKeyValueSize:I
      20: aload_0
      21: areturn

  public org.apache.hadoop.hbase.client.AsyncBufferedMutator build();
    Code:
       0: new           #20                 // class org/apache/hadoop/hbase/client/AsyncBufferedMutatorImpl
       3: dup
       4: aload_0
       5: getfield      #9                  // Field periodicalFlushTimer:Lorg/apache/hbase/thirdparty/io/netty/util/HashedWheelTimer;
       8: aload_0
       9: getfield      #2                  // Field tableBuilder:Lorg/apache/hadoop/hbase/client/AsyncTableBuilder;
      12: invokeinterface #21,  1           // InterfaceMethod org/apache/hadoop/hbase/client/AsyncTableBuilder.build:()Lorg/apache/hadoop/hbase/client/AsyncTable;
      17: aload_0
      18: getfield      #4                  // Field writeBufferSize:J
      21: aload_0
      22: getfield      #6                  // Field periodicFlushTimeoutNs:J
      25: aload_0
      26: getfield      #8                  // Field maxKeyValueSize:I
      29: invokespecial #22                 // Method org/apache/hadoop/hbase/client/AsyncBufferedMutatorImpl."<init>":(Lorg/apache/hbase/thirdparty/io/netty/util/HashedWheelTimer;Lorg/apache/hadoop/hbase/client/AsyncTable;JJI)V
      32: areturn
}
