Compiled from "AsyncClientScanner.java"
class org.apache.hadoop.hbase.client.AsyncClientScanner {
  public org.apache.hadoop.hbase.client.AsyncClientScanner(org.apache.hadoop.hbase.client.Scan, org.apache.hadoop.hbase.client.AdvancedScanResultConsumer, org.apache.hadoop.hbase.TableName, org.apache.hadoop.hbase.client.AsyncConnectionImpl, org.apache.hbase.thirdparty.io.netty.util.Timer, long, long, int, long, long, int);
    Code:
       0: aload_0
       1: invokespecial #1                  // Method java/lang/Object."<init>":()V
       4: aload_0
       5: new           #2                  // class java/util/concurrent/atomic/AtomicInteger
       8: dup
       9: invokespecial #3                  // Method java/util/concurrent/atomic/AtomicInteger."<init>":()V
      12: putfield      #4                  // Field openScannerTries:Ljava/util/concurrent/atomic/AtomicInteger;
      15: aload_1
      16: invokevirtual #5                  // Method org/apache/hadoop/hbase/client/Scan.getStartRow:()[B
      19: ifnonnull     34
      22: aload_1
      23: getstatic     #6                  // Field org/apache/hadoop/hbase/HConstants.EMPTY_START_ROW:[B
      26: aload_1
      27: invokevirtual #7                  // Method org/apache/hadoop/hbase/client/Scan.includeStartRow:()Z
      30: invokevirtual #8                  // Method org/apache/hadoop/hbase/client/Scan.withStartRow:([BZ)Lorg/apache/hadoop/hbase/client/Scan;
      33: pop
      34: aload_1
      35: invokevirtual #9                  // Method org/apache/hadoop/hbase/client/Scan.getStopRow:()[B
      38: ifnonnull     53
      41: aload_1
      42: getstatic     #10                 // Field org/apache/hadoop/hbase/HConstants.EMPTY_END_ROW:[B
      45: aload_1
      46: invokevirtual #11                 // Method org/apache/hadoop/hbase/client/Scan.includeStopRow:()Z
      49: invokevirtual #12                 // Method org/apache/hadoop/hbase/client/Scan.withStopRow:([BZ)Lorg/apache/hadoop/hbase/client/Scan;
      52: pop
      53: aload_0
      54: aload_1
      55: putfield      #13                 // Field scan:Lorg/apache/hadoop/hbase/client/Scan;
      58: aload_0
      59: aload_2
      60: putfield      #14                 // Field consumer:Lorg/apache/hadoop/hbase/client/AdvancedScanResultConsumer;
      63: aload_0
      64: aload_3
      65: putfield      #15                 // Field tableName:Lorg/apache/hadoop/hbase/TableName;
      68: aload_0
      69: aload         4
      71: putfield      #16                 // Field conn:Lorg/apache/hadoop/hbase/client/AsyncConnectionImpl;
      74: aload_0
      75: aload         5
      77: putfield      #17                 // Field retryTimer:Lorg/apache/hbase/thirdparty/io/netty/util/Timer;
      80: aload_0
      81: lload         6
      83: putfield      #18                 // Field pauseNs:J
      86: aload_0
      87: lload         8
      89: putfield      #19                 // Field pauseForCQTBENs:J
      92: aload_0
      93: iload         10
      95: putfield      #20                 // Field maxAttempts:I
      98: aload_0
      99: lload         11
     101: putfield      #21                 // Field scanTimeoutNs:J
     104: aload_0
     105: lload         13
     107: putfield      #22                 // Field rpcTimeoutNs:J
     110: aload_0
     111: iload         15
     113: putfield      #23                 // Field startLogErrorsCnt:I
     116: aload_0
     117: aload_1
     118: invokestatic  #24                 // Method org/apache/hadoop/hbase/client/ConnectionUtils.createScanResultCache:(Lorg/apache/hadoop/hbase/client/Scan;)Lorg/apache/hadoop/hbase/client/ScanResultCache;
     121: putfield      #25                 // Field resultCache:Lorg/apache/hadoop/hbase/client/ScanResultCache;
     124: aload_1
     125: invokevirtual #26                 // Method org/apache/hadoop/hbase/client/Scan.isScanMetricsEnabled:()Z
     128: ifeq          155
     131: aload_0
     132: new           #27                 // class org/apache/hadoop/hbase/client/metrics/ScanMetrics
     135: dup
     136: invokespecial #28                 // Method org/apache/hadoop/hbase/client/metrics/ScanMetrics."<init>":()V
     139: putfield      #29                 // Field scanMetrics:Lorg/apache/hadoop/hbase/client/metrics/ScanMetrics;
     142: aload_2
     143: aload_0
     144: getfield      #29                 // Field scanMetrics:Lorg/apache/hadoop/hbase/client/metrics/ScanMetrics;
     147: invokeinterface #30,  2           // InterfaceMethod org/apache/hadoop/hbase/client/AdvancedScanResultConsumer.onScanMetricsCreated:(Lorg/apache/hadoop/hbase/client/metrics/ScanMetrics;)V
     152: goto          160
     155: aload_0
     156: aconst_null
     157: putfield      #29                 // Field scanMetrics:Lorg/apache/hadoop/hbase/client/metrics/ScanMetrics;
     160: return

  public void start();
    Code:
       0: aload_0
       1: invokespecial #102                // Method openScanner:()V
       4: return
}
