Compiled from "AsyncMetaTableAccessor.java"
public class org.apache.hadoop.hbase.AsyncMetaTableAccessor {
  public org.apache.hadoop.hbase.AsyncMetaTableAccessor();
    Code:
       0: aload_0
       1: invokespecial #3                  // Method java/lang/Object."<init>":()V
       4: return

  public static java.util.concurrent.CompletableFuture<java.lang.Boolean> tableExists(org.apache.hadoop.hbase.client.AsyncTable<?>, org.apache.hadoop.hbase.TableName);
    Code:
       0: aload_0
       1: aload_1
       2: invokestatic  #4                  // Method getTableState:(Lorg/apache/hadoop/hbase/client/AsyncTable;Lorg/apache/hadoop/hbase/TableName;)Ljava/util/concurrent/CompletableFuture;
       5: invokedynamic #5,  0              // InvokeDynamic #0:apply:()Ljava/util/function/Function;
      10: invokevirtual #6                  // Method java/util/concurrent/CompletableFuture.thenApply:(Ljava/util/function/Function;)Ljava/util/concurrent/CompletableFuture;
      13: areturn

  public static java.util.concurrent.CompletableFuture<java.util.Optional<org.apache.hadoop.hbase.client.TableState>> getTableState(org.apache.hadoop.hbase.client.AsyncTable<?>, org.apache.hadoop.hbase.TableName);
    Code:
       0: new           #7                  // class java/util/concurrent/CompletableFuture
       3: dup
       4: invokespecial #8                  // Method java/util/concurrent/CompletableFuture."<init>":()V
       7: astore_2
       8: new           #9                  // class org/apache/hadoop/hbase/client/Get
      11: dup
      12: aload_1
      13: invokevirtual #10                 // Method org/apache/hadoop/hbase/TableName.getName:()[B
      16: invokespecial #11                 // Method org/apache/hadoop/hbase/client/Get."<init>":([B)V
      19: invokestatic  #12                 // Method getTableFamily:()[B
      22: invokestatic  #13                 // Method getStateColumn:()[B
      25: invokevirtual #14                 // Method org/apache/hadoop/hbase/client/Get.addColumn:([B[B)Lorg/apache/hadoop/hbase/client/Get;
      28: astore_3
      29: invokestatic  #15                 // Method org/apache/hadoop/hbase/util/EnvironmentEdgeManager.currentTime:()J
      32: lstore        4
      34: aload_3
      35: lconst_0
      36: lload         4
      38: invokevirtual #16                 // Method org/apache/hadoop/hbase/client/Get.setTimeRange:(JJ)Lorg/apache/hadoop/hbase/client/Get;
      41: pop
      42: aload_0
      43: aload_3
      44: invokeinterface #17,  2           // InterfaceMethod org/apache/hadoop/hbase/client/AsyncTable.get:(Lorg/apache/hadoop/hbase/client/Get;)Ljava/util/concurrent/CompletableFuture;
      49: aload_2
      50: invokedynamic #18,  0             // InvokeDynamic #1:accept:(Ljava/util/concurrent/CompletableFuture;)Ljava/util/function/BiConsumer;
      55: invokestatic  #19                 // Method org/apache/hadoop/hbase/util/FutureUtils.addListener:(Ljava/util/concurrent/CompletableFuture;Ljava/util/function/BiConsumer;)V
      58: goto          70
      61: astore        6
      63: aload_2
      64: aload         6
      66: invokevirtual #21                 // Method java/util/concurrent/CompletableFuture.completeExceptionally:(Ljava/lang/Throwable;)Z
      69: pop
      70: aload_2
      71: areturn
    Exception table:
       from    to  target type
          34    58    61   Class java/io/IOException

  public static java.util.concurrent.CompletableFuture<java.util.Optional<org.apache.hadoop.hbase.HRegionLocation>> getRegionLocation(org.apache.hadoop.hbase.client.AsyncTable<?>, byte[]);
    Code:
       0: new           #7                  // class java/util/concurrent/CompletableFuture
       3: dup
       4: invokespecial #8                  // Method java/util/concurrent/CompletableFuture."<init>":()V
       7: astore_2
       8: aload_1
       9: invokestatic  #22                 // Method org/apache/hadoop/hbase/MetaTableAccessor.parseRegionInfoFromRegionName:([B)Lorg/apache/hadoop/hbase/client/RegionInfo;
      12: astore_3
      13: aload_0
      14: new           #9                  // class org/apache/hadoop/hbase/client/Get
      17: dup
      18: aload_3
      19: invokestatic  #23                 // Method org/apache/hadoop/hbase/MetaTableAccessor.getMetaKeyForRegion:(Lorg/apache/hadoop/hbase/client/RegionInfo;)[B
      22: invokespecial #11                 // Method org/apache/hadoop/hbase/client/Get."<init>":([B)V
      25: getstatic     #24                 // Field org/apache/hadoop/hbase/HConstants.CATALOG_FAMILY:[B
      28: invokevirtual #25                 // Method org/apache/hadoop/hbase/client/Get.addFamily:([B)Lorg/apache/hadoop/hbase/client/Get;
      31: invokeinterface #17,  2           // InterfaceMethod org/apache/hadoop/hbase/client/AsyncTable.get:(Lorg/apache/hadoop/hbase/client/Get;)Ljava/util/concurrent/CompletableFuture;
      36: aload_2
      37: aload_3
      38: invokedynamic #26,  0             // InvokeDynamic #2:accept:(Ljava/util/concurrent/CompletableFuture;Lorg/apache/hadoop/hbase/client/RegionInfo;)Ljava/util/function/BiConsumer;
      43: invokestatic  #19                 // Method org/apache/hadoop/hbase/util/FutureUtils.addListener:(Ljava/util/concurrent/CompletableFuture;Ljava/util/function/BiConsumer;)V
      46: goto          86
      49: astore_3
      50: getstatic     #1                  // Field LOG:Lorg/slf4j/Logger;
      53: new           #27                 // class java/lang/StringBuilder
      56: dup
      57: invokespecial #28                 // Method java/lang/StringBuilder."<init>":()V
      60: ldc           #29                 // String Failed to parse the passed region name:
      62: invokevirtual #30                 // Method java/lang/StringBuilder.append:(Ljava/lang/String;)Ljava/lang/StringBuilder;
      65: aload_1
      66: invokestatic  #31                 // Method org/apache/hadoop/hbase/util/Bytes.toStringBinary:([B)Ljava/lang/String;
      69: invokevirtual #30                 // Method java/lang/StringBuilder.append:(Ljava/lang/String;)Ljava/lang/StringBuilder;
      72: invokevirtual #32                 // Method java/lang/StringBuilder.toString:()Ljava/lang/String;
      75: invokeinterface #33,  2           // InterfaceMethod org/slf4j/Logger.warn:(Ljava/lang/String;)V
      80: aload_2
      81: aload_3
      82: invokevirtual #21                 // Method java/util/concurrent/CompletableFuture.completeExceptionally:(Ljava/lang/Throwable;)Z
      85: pop
      86: aload_2
      87: areturn
    Exception table:
       from    to  target type
           8    46    49   Class java/io/IOException

  public static java.util.concurrent.CompletableFuture<java.util.Optional<org.apache.hadoop.hbase.HRegionLocation>> getRegionLocationWithEncodedName(org.apache.hadoop.hbase.client.AsyncTable<?>, byte[]);
    Code:
       0: new           #7                  // class java/util/concurrent/CompletableFuture
       3: dup
       4: invokespecial #8                  // Method java/util/concurrent/CompletableFuture."<init>":()V
       7: astore_2
       8: aload_0
       9: new           #34                 // class org/apache/hadoop/hbase/client/Scan
      12: dup
      13: invokespecial #35                 // Method org/apache/hadoop/hbase/client/Scan."<init>":()V
      16: getstatic     #36                 // Field org/apache/hadoop/hbase/client/Scan$ReadType.PREAD:Lorg/apache/hadoop/hbase/client/Scan$ReadType;
      19: invokevirtual #37                 // Method org/apache/hadoop/hbase/client/Scan.setReadType:(Lorg/apache/hadoop/hbase/client/Scan$ReadType;)Lorg/apache/hadoop/hbase/client/Scan;
      22: getstatic     #24                 // Field org/apache/hadoop/hbase/HConstants.CATALOG_FAMILY:[B
      25: invokevirtual #38                 // Method org/apache/hadoop/hbase/client/Scan.addFamily:([B)Lorg/apache/hadoop/hbase/client/Scan;
      28: invokeinterface #39,  2           // InterfaceMethod org/apache/hadoop/hbase/client/AsyncTable.scanAll:(Lorg/apache/hadoop/hbase/client/Scan;)Ljava/util/concurrent/CompletableFuture;
      33: aload_2
      34: aload_1
      35: invokedynamic #40,  0             // InvokeDynamic #3:accept:(Ljava/util/concurrent/CompletableFuture;[B)Ljava/util/function/BiConsumer;
      40: invokestatic  #19                 // Method org/apache/hadoop/hbase/util/FutureUtils.addListener:(Ljava/util/concurrent/CompletableFuture;Ljava/util/function/BiConsumer;)V
      43: aload_2
      44: areturn

  public static java.util.concurrent.CompletableFuture<java.util.List<org.apache.hadoop.hbase.HRegionLocation>> getTableHRegionLocations(org.apache.hadoop.hbase.client.AsyncTable<org.apache.hadoop.hbase.client.AdvancedScanResultConsumer>, java.util.Optional<org.apache.hadoop.hbase.TableName>);
    Code:
       0: new           #7                  // class java/util/concurrent/CompletableFuture
       3: dup
       4: invokespecial #8                  // Method java/util/concurrent/CompletableFuture."<init>":()V
       7: astore_2
       8: aload_0
       9: aload_1
      10: iconst_1
      11: invokestatic  #55                 // Method getTableRegionsAndLocations:(Lorg/apache/hadoop/hbase/client/AsyncTable;Ljava/util/Optional;Z)Ljava/util/concurrent/CompletableFuture;
      14: aload_2
      15: invokedynamic #56,  0             // InvokeDynamic #4:accept:(Ljava/util/concurrent/CompletableFuture;)Ljava/util/function/BiConsumer;
      20: invokestatic  #19                 // Method org/apache/hadoop/hbase/util/FutureUtils.addListener:(Ljava/util/concurrent/CompletableFuture;Ljava/util/function/BiConsumer;)V
      23: aload_2
      24: areturn

  static java.util.Optional access$000(org.apache.hadoop.hbase.client.Result);
    Code:
       0: aload_0
       1: invokestatic  #2                  // Method getRegionLocations:(Lorg/apache/hadoop/hbase/client/Result;)Ljava/util/Optional;
       4: areturn

  static org.slf4j.Logger access$100();
    Code:
       0: getstatic     #1                  // Field LOG:Lorg/slf4j/Logger;
       3: areturn

  static {};
    Code:
       0: ldc           #155                // class org/apache/hadoop/hbase/AsyncMetaTableAccessor
       2: invokestatic  #209                // Method org/slf4j/LoggerFactory.getLogger:(Ljava/lang/Class;)Lorg/slf4j/Logger;
       5: putstatic     #1                  // Field LOG:Lorg/slf4j/Logger;
       8: ldc           #210                // String ^server(_[0-9a-fA-F]{4})?$
      10: invokestatic  #211                // Method java/util/regex/Pattern.compile:(Ljava/lang/String;)Ljava/util/regex/Pattern;
      13: putstatic     #167                // Field SERVER_COLUMN_PATTERN:Ljava/util/regex/Pattern;
      16: return
}
