Compiled from "AuthMethod.java"
public final class org.apache.hadoop.hbase.security.AuthMethod extends java.lang.Enum<org.apache.hadoop.hbase.security.AuthMethod> {
  public static final org.apache.hadoop.hbase.security.AuthMethod SIMPLE;

  public static final org.apache.hadoop.hbase.security.AuthMethod KERBEROS;

  public static final org.apache.hadoop.hbase.security.AuthMethod DIGEST;

  public final byte code;

  public final java.lang.String mechanismName;

  public final org.apache.hadoop.security.UserGroupInformation$AuthenticationMethod authenticationMethod;

  public static org.apache.hadoop.hbase.security.AuthMethod[] values();
    Code:
       0: getstatic     #1                  // Field $VALUES:[Lorg/apache/hadoop/hbase/security/AuthMethod;
       3: invokevirtual #2                  // Method "[Lorg/apache/hadoop/hbase/security/AuthMethod;".clone:()Ljava/lang/Object;
       6: checkcast     #3                  // class "[Lorg/apache/hadoop/hbase/security/AuthMethod;"
       9: areturn

  public static org.apache.hadoop.hbase.security.AuthMethod valueOf(java.lang.String);
    Code:
       0: ldc           #4                  // class org/apache/hadoop/hbase/security/AuthMethod
       2: aload_0
       3: invokestatic  #5                  // Method java/lang/Enum.valueOf:(Ljava/lang/Class;Ljava/lang/String;)Ljava/lang/Enum;
       6: checkcast     #4                  // class org/apache/hadoop/hbase/security/AuthMethod
       9: areturn

  public static org.apache.hadoop.hbase.security.AuthMethod valueOf(byte);
    Code:
       0: iload_0
       1: sipush        255
       4: iand
       5: getstatic     #10                 // Field FIRST_CODE:I
       8: isub
       9: istore_1
      10: iload_1
      11: iflt          22
      14: iload_1
      15: invokestatic  #11                 // Method values:()[Lorg/apache/hadoop/hbase/security/AuthMethod;
      18: arraylength
      19: if_icmplt     26
      22: aconst_null
      23: goto          31
      26: invokestatic  #11                 // Method values:()[Lorg/apache/hadoop/hbase/security/AuthMethod;
      29: iload_1
      30: aaload
      31: areturn

  public java.lang.String getMechanismName();
    Code:
       0: aload_0
       1: getfield      #8                  // Field mechanismName:Ljava/lang/String;
       4: areturn

  public static org.apache.hadoop.hbase.security.AuthMethod read(java.io.DataInput) throws java.io.IOException;
    Code:
       0: aload_0
       1: invokeinterface #12,  1           // InterfaceMethod java/io/DataInput.readByte:()B
       6: invokestatic  #13                 // Method valueOf:(B)Lorg/apache/hadoop/hbase/security/AuthMethod;
       9: areturn

  public void write(java.io.DataOutput) throws java.io.IOException;
    Code:
       0: aload_1
       1: aload_0
       2: getfield      #7                  // Field code:B
       5: invokeinterface #14,  2           // InterfaceMethod java/io/DataOutput.write:(I)V
      10: return

  static {};
    Code:
       0: new           #4                  // class org/apache/hadoop/hbase/security/AuthMethod
       3: dup
       4: ldc           #15                 // String SIMPLE
       6: iconst_0
       7: bipush        80
       9: ldc           #16                 // String
      11: getstatic     #17                 // Field org/apache/hadoop/security/UserGroupInformation$AuthenticationMethod.SIMPLE:Lorg/apache/hadoop/security/UserGroupInformation$AuthenticationMethod;
      14: invokespecial #18                 // Method "<init>":(Ljava/lang/String;IBLjava/lang/String;Lorg/apache/hadoop/security/UserGroupInformation$AuthenticationMethod;)V
      17: putstatic     #19                 // Field SIMPLE:Lorg/apache/hadoop/hbase/security/AuthMethod;
      20: new           #4                  // class org/apache/hadoop/hbase/security/AuthMethod
      23: dup
      24: ldc           #20                 // String KERBEROS
      26: iconst_1
      27: bipush        81
      29: ldc           #21                 // String GSSAPI
      31: getstatic     #22                 // Field org/apache/hadoop/security/UserGroupInformation$AuthenticationMethod.KERBEROS:Lorg/apache/hadoop/security/UserGroupInformation$AuthenticationMethod;
      34: invokespecial #18                 // Method "<init>":(Ljava/lang/String;IBLjava/lang/String;Lorg/apache/hadoop/security/UserGroupInformation$AuthenticationMethod;)V
      37: putstatic     #23                 // Field KERBEROS:Lorg/apache/hadoop/hbase/security/AuthMethod;
      40: new           #4                  // class org/apache/hadoop/hbase/security/AuthMethod
      43: dup
      44: ldc           #24                 // String DIGEST
      46: iconst_2
      47: bipush        82
      49: ldc           #25                 // String DIGEST-MD5
      51: getstatic     #26                 // Field org/apache/hadoop/security/UserGroupInformation$AuthenticationMethod.TOKEN:Lorg/apache/hadoop/security/UserGroupInformation$AuthenticationMethod;
      54: invokespecial #18                 // Method "<init>":(Ljava/lang/String;IBLjava/lang/String;Lorg/apache/hadoop/security/UserGroupInformation$AuthenticationMethod;)V
      57: putstatic     #27                 // Field DIGEST:Lorg/apache/hadoop/hbase/security/AuthMethod;
      60: iconst_3
      61: anewarray     #4                  // class org/apache/hadoop/hbase/security/AuthMethod
      64: dup
      65: iconst_0
      66: getstatic     #19                 // Field SIMPLE:Lorg/apache/hadoop/hbase/security/AuthMethod;
      69: aastore
      70: dup
      71: iconst_1
      72: getstatic     #23                 // Field KERBEROS:Lorg/apache/hadoop/hbase/security/AuthMethod;
      75: aastore
      76: dup
      77: iconst_2
      78: getstatic     #27                 // Field DIGEST:Lorg/apache/hadoop/hbase/security/AuthMethod;
      81: aastore
      82: putstatic     #1                  // Field $VALUES:[Lorg/apache/hadoop/hbase/security/AuthMethod;
      85: invokestatic  #11                 // Method values:()[Lorg/apache/hadoop/hbase/security/AuthMethod;
      88: iconst_0
      89: aaload
      90: getfield      #7                  // Field code:B
      93: putstatic     #10                 // Field FIRST_CODE:I
      96: return
}
