Compiled from "AuthenticationProtos.java"
public final class org.apache.hadoop.hbase.protobuf.generated.AuthenticationProtos$TokenIdentifier extends com.google.protobuf.GeneratedMessage implements org.apache.hadoop.hbase.protobuf.generated.AuthenticationProtos$TokenIdentifierOrBuilder {
  public static com.google.protobuf.Parser<org.apache.hadoop.hbase.protobuf.generated.AuthenticationProtos$TokenIdentifier> PARSER;

  public static final int KIND_FIELD_NUMBER;

  public static final int USERNAME_FIELD_NUMBER;

  public static final int KEY_ID_FIELD_NUMBER;

  public static final int ISSUE_DATE_FIELD_NUMBER;

  public static final int EXPIRATION_DATE_FIELD_NUMBER;

  public static final int SEQUENCE_NUMBER_FIELD_NUMBER;

  public static org.apache.hadoop.hbase.protobuf.generated.AuthenticationProtos$TokenIdentifier getDefaultInstance();
    Code:
       0: getstatic     #19                 // Field defaultInstance:Lorg/apache/hadoop/hbase/protobuf/generated/AuthenticationProtos$TokenIdentifier;
       3: areturn

  public org.apache.hadoop.hbase.protobuf.generated.AuthenticationProtos$TokenIdentifier getDefaultInstanceForType();
    Code:
       0: getstatic     #19                 // Field defaultInstance:Lorg/apache/hadoop/hbase/protobuf/generated/AuthenticationProtos$TokenIdentifier;
       3: areturn

  public final com.google.protobuf.UnknownFieldSet getUnknownFields();
    Code:
       0: aload_0
       1: getfield      #16                 // Field unknownFields:Lcom/google/protobuf/UnknownFieldSet;
       4: areturn

  public static final com.google.protobuf.Descriptors$Descriptor getDescriptor();
    Code:
       0: invokestatic  #37                 // Method org/apache/hadoop/hbase/protobuf/generated/AuthenticationProtos.access$1100:()Lcom/google/protobuf/Descriptors$Descriptor;
       3: areturn

  protected com.google.protobuf.GeneratedMessage$FieldAccessorTable internalGetFieldAccessorTable();
    Code:
       0: invokestatic  #38                 // Method org/apache/hadoop/hbase/protobuf/generated/AuthenticationProtos.access$1200:()Lcom/google/protobuf/GeneratedMessage$FieldAccessorTable;
       3: ldc           #39                 // class org/apache/hadoop/hbase/protobuf/generated/AuthenticationProtos$TokenIdentifier
       5: ldc           #40                 // class org/apache/hadoop/hbase/protobuf/generated/AuthenticationProtos$TokenIdentifier$Builder
       7: invokevirtual #41                 // Method com/google/protobuf/GeneratedMessage$FieldAccessorTable.ensureFieldAccessorsInitialized:(Ljava/lang/Class;Ljava/lang/Class;)Lcom/google/protobuf/GeneratedMessage$FieldAccessorTable;
      10: areturn

  public com.google.protobuf.Parser<org.apache.hadoop.hbase.protobuf.generated.AuthenticationProtos$TokenIdentifier> getParserForType();
    Code:
       0: getstatic     #42                 // Field PARSER:Lcom/google/protobuf/Parser;
       3: areturn

  public boolean hasKind();
    Code:
       0: aload_0
       1: getfield      #1                  // Field bitField0_:I
       4: iconst_1
       5: iand
       6: iconst_1
       7: if_icmpne     14
      10: iconst_1
      11: goto          15
      14: iconst_0
      15: ireturn

  public org.apache.hadoop.hbase.protobuf.generated.AuthenticationProtos$TokenIdentifier$Kind getKind();
    Code:
       0: aload_0
       1: getfield      #7                  // Field kind_:Lorg/apache/hadoop/hbase/protobuf/generated/AuthenticationProtos$TokenIdentifier$Kind;
       4: areturn

  public boolean hasUsername();
    Code:
       0: aload_0
       1: getfield      #1                  // Field bitField0_:I
       4: iconst_2
       5: iand
       6: iconst_2
       7: if_icmpne     14
      10: iconst_1
      11: goto          15
      14: iconst_0
      15: ireturn

  public com.google.protobuf.ByteString getUsername();
    Code:
       0: aload_0
       1: getfield      #6                  // Field username_:Lcom/google/protobuf/ByteString;
       4: areturn

  public boolean hasKeyId();
    Code:
       0: aload_0
       1: getfield      #1                  // Field bitField0_:I
       4: iconst_4
       5: iand
       6: iconst_4
       7: if_icmpne     14
      10: iconst_1
      11: goto          15
      14: iconst_0
      15: ireturn

  public int getKeyId();
    Code:
       0: aload_0
       1: getfield      #5                  // Field keyId_:I
       4: ireturn

  public boolean hasIssueDate();
    Code:
       0: aload_0
       1: getfield      #1                  // Field bitField0_:I
       4: bipush        8
       6: iand
       7: bipush        8
       9: if_icmpne     16
      12: iconst_1
      13: goto          17
      16: iconst_0
      17: ireturn

  public long getIssueDate();
    Code:
       0: aload_0
       1: getfield      #4                  // Field issueDate_:J
       4: lreturn

  public boolean hasExpirationDate();
    Code:
       0: aload_0
       1: getfield      #1                  // Field bitField0_:I
       4: bipush        16
       6: iand
       7: bipush        16
       9: if_icmpne     16
      12: iconst_1
      13: goto          17
      16: iconst_0
      17: ireturn

  public long getExpirationDate();
    Code:
       0: aload_0
       1: getfield      #3                  // Field expirationDate_:J
       4: lreturn

  public boolean hasSequenceNumber();
    Code:
       0: aload_0
       1: getfield      #1                  // Field bitField0_:I
       4: bipush        32
       6: iand
       7: bipush        32
       9: if_icmpne     16
      12: iconst_1
      13: goto          17
      16: iconst_0
      17: ireturn

  public long getSequenceNumber();
    Code:
       0: aload_0
       1: getfield      #2                  // Field sequenceNumber_:J
       4: lreturn

  public final boolean isInitialized();
    Code:
       0: aload_0
       1: getfield      #12                 // Field memoizedIsInitialized:B
       4: istore_1
       5: iload_1
       6: iconst_m1
       7: if_icmpeq     21
      10: iload_1
      11: iconst_1
      12: if_icmpne     19
      15: iconst_1
      16: goto          20
      19: iconst_0
      20: ireturn
      21: aload_0
      22: invokevirtual #45                 // Method hasKind:()Z
      25: ifne          35
      28: aload_0
      29: iconst_0
      30: putfield      #12                 // Field memoizedIsInitialized:B
      33: iconst_0
      34: ireturn
      35: aload_0
      36: invokevirtual #46                 // Method hasUsername:()Z
      39: ifne          49
      42: aload_0
      43: iconst_0
      44: putfield      #12                 // Field memoizedIsInitialized:B
      47: iconst_0
      48: ireturn
      49: aload_0
      50: invokevirtual #47                 // Method hasKeyId:()Z
      53: ifne          63
      56: aload_0
      57: iconst_0
      58: putfield      #12                 // Field memoizedIsInitialized:B
      61: iconst_0
      62: ireturn
      63: aload_0
      64: iconst_1
      65: putfield      #12                 // Field memoizedIsInitialized:B
      68: iconst_1
      69: ireturn

  public void writeTo(com.google.protobuf.CodedOutputStream) throws java.io.IOException;
    Code:
       0: aload_0
       1: invokevirtual #48                 // Method getSerializedSize:()I
       4: pop
       5: aload_0
       6: getfield      #1                  // Field bitField0_:I
       9: iconst_1
      10: iand
      11: iconst_1
      12: if_icmpne     27
      15: aload_1
      16: iconst_1
      17: aload_0
      18: getfield      #7                  // Field kind_:Lorg/apache/hadoop/hbase/protobuf/generated/AuthenticationProtos$TokenIdentifier$Kind;
      21: invokevirtual #49                 // Method org/apache/hadoop/hbase/protobuf/generated/AuthenticationProtos$TokenIdentifier$Kind.getNumber:()I
      24: invokevirtual #50                 // Method com/google/protobuf/CodedOutputStream.writeEnum:(II)V
      27: aload_0
      28: getfield      #1                  // Field bitField0_:I
      31: iconst_2
      32: iand
      33: iconst_2
      34: if_icmpne     46
      37: aload_1
      38: iconst_2
      39: aload_0
      40: getfield      #6                  // Field username_:Lcom/google/protobuf/ByteString;
      43: invokevirtual #51                 // Method com/google/protobuf/CodedOutputStream.writeBytes:(ILcom/google/protobuf/ByteString;)V
      46: aload_0
      47: getfield      #1                  // Field bitField0_:I
      50: iconst_4
      51: iand
      52: iconst_4
      53: if_icmpne     65
      56: aload_1
      57: iconst_3
      58: aload_0
      59: getfield      #5                  // Field keyId_:I
      62: invokevirtual #52                 // Method com/google/protobuf/CodedOutputStream.writeInt32:(II)V
      65: aload_0
      66: getfield      #1                  // Field bitField0_:I
      69: bipush        8
      71: iand
      72: bipush        8
      74: if_icmpne     86
      77: aload_1
      78: iconst_4
      79: aload_0
      80: getfield      #4                  // Field issueDate_:J
      83: invokevirtual #53                 // Method com/google/protobuf/CodedOutputStream.writeInt64:(IJ)V
      86: aload_0
      87: getfield      #1                  // Field bitField0_:I
      90: bipush        16
      92: iand
      93: bipush        16
      95: if_icmpne     107
      98: aload_1
      99: iconst_5
     100: aload_0
     101: getfield      #3                  // Field expirationDate_:J
     104: invokevirtual #53                 // Method com/google/protobuf/CodedOutputStream.writeInt64:(IJ)V
     107: aload_0
     108: getfield      #1                  // Field bitField0_:I
     111: bipush        32
     113: iand
     114: bipush        32
     116: if_icmpne     129
     119: aload_1
     120: bipush        6
     122: aload_0
     123: getfield      #2                  // Field sequenceNumber_:J
     126: invokevirtual #53                 // Method com/google/protobuf/CodedOutputStream.writeInt64:(IJ)V
     129: aload_0
     130: invokevirtual #54                 // Method getUnknownFields:()Lcom/google/protobuf/UnknownFieldSet;
     133: aload_1
     134: invokevirtual #55                 // Method com/google/protobuf/UnknownFieldSet.writeTo:(Lcom/google/protobuf/CodedOutputStream;)V
     137: return

  public int getSerializedSize();
    Code:
       0: aload_0
       1: getfield      #13                 // Field memoizedSerializedSize:I
       4: istore_1
       5: iload_1
       6: iconst_m1
       7: if_icmpeq     12
      10: iload_1
      11: ireturn
      12: iconst_0
      13: istore_1
      14: aload_0
      15: getfield      #1                  // Field bitField0_:I
      18: iconst_1
      19: iand
      20: iconst_1
      21: if_icmpne     38
      24: iload_1
      25: iconst_1
      26: aload_0
      27: getfield      #7                  // Field kind_:Lorg/apache/hadoop/hbase/protobuf/generated/AuthenticationProtos$TokenIdentifier$Kind;
      30: invokevirtual #49                 // Method org/apache/hadoop/hbase/protobuf/generated/AuthenticationProtos$TokenIdentifier$Kind.getNumber:()I
      33: invokestatic  #56                 // Method com/google/protobuf/CodedOutputStream.computeEnumSize:(II)I
      36: iadd
      37: istore_1
      38: aload_0
      39: getfield      #1                  // Field bitField0_:I
      42: iconst_2
      43: iand
      44: iconst_2
      45: if_icmpne     59
      48: iload_1
      49: iconst_2
      50: aload_0
      51: getfield      #6                  // Field username_:Lcom/google/protobuf/ByteString;
      54: invokestatic  #57                 // Method com/google/protobuf/CodedOutputStream.computeBytesSize:(ILcom/google/protobuf/ByteString;)I
      57: iadd
      58: istore_1
      59: aload_0
      60: getfield      #1                  // Field bitField0_:I
      63: iconst_4
      64: iand
      65: iconst_4
      66: if_icmpne     80
      69: iload_1
      70: iconst_3
      71: aload_0
      72: getfield      #5                  // Field keyId_:I
      75: invokestatic  #58                 // Method com/google/protobuf/CodedOutputStream.computeInt32Size:(II)I
      78: iadd
      79: istore_1
      80: aload_0
      81: getfield      #1                  // Field bitField0_:I
      84: bipush        8
      86: iand
      87: bipush        8
      89: if_icmpne     103
      92: iload_1
      93: iconst_4
      94: aload_0
      95: getfield      #4                  // Field issueDate_:J
      98: invokestatic  #59                 // Method com/google/protobuf/CodedOutputStream.computeInt64Size:(IJ)I
     101: iadd
     102: istore_1
     103: aload_0
     104: getfield      #1                  // Field bitField0_:I
     107: bipush        16
     109: iand
     110: bipush        16
     112: if_icmpne     126
     115: iload_1
     116: iconst_5
     117: aload_0
     118: getfield      #3                  // Field expirationDate_:J
     121: invokestatic  #59                 // Method com/google/protobuf/CodedOutputStream.computeInt64Size:(IJ)I
     124: iadd
     125: istore_1
     126: aload_0
     127: getfield      #1                  // Field bitField0_:I
     130: bipush        32
     132: iand
     133: bipush        32
     135: if_icmpne     150
     138: iload_1
     139: bipush        6
     141: aload_0
     142: getfield      #2                  // Field sequenceNumber_:J
     145: invokestatic  #59                 // Method com/google/protobuf/CodedOutputStream.computeInt64Size:(IJ)I
     148: iadd
     149: istore_1
     150: iload_1
     151: aload_0
     152: invokevirtual #54                 // Method getUnknownFields:()Lcom/google/protobuf/UnknownFieldSet;
     155: invokevirtual #60                 // Method com/google/protobuf/UnknownFieldSet.getSerializedSize:()I
     158: iadd
     159: istore_1
     160: aload_0
     161: iload_1
     162: putfield      #13                 // Field memoizedSerializedSize:I
     165: iload_1
     166: ireturn

  protected java.lang.Object writeReplace() throws java.io.ObjectStreamException;
    Code:
       0: aload_0
       1: invokespecial #61                 // Method com/google/protobuf/GeneratedMessage.writeReplace:()Ljava/lang/Object;
       4: areturn

  public boolean equals(java.lang.Object);
    Code:
       0: aload_1
       1: aload_0
       2: if_acmpne     7
       5: iconst_1
       6: ireturn
       7: aload_1
       8: instanceof    #39                 // class org/apache/hadoop/hbase/protobuf/generated/AuthenticationProtos$TokenIdentifier
      11: ifne          20
      14: aload_0
      15: aload_1
      16: invokespecial #62                 // Method com/google/protobuf/GeneratedMessage.equals:(Ljava/lang/Object;)Z
      19: ireturn
      20: aload_1
      21: checkcast     #39                 // class org/apache/hadoop/hbase/protobuf/generated/AuthenticationProtos$TokenIdentifier
      24: astore_2
      25: iconst_1
      26: istore_3
      27: iload_3
      28: ifeq          46
      31: aload_0
      32: invokevirtual #45                 // Method hasKind:()Z
      35: aload_2
      36: invokevirtual #45                 // Method hasKind:()Z
      39: if_icmpne     46
      42: iconst_1
      43: goto          47
      46: iconst_0
      47: istore_3
      48: aload_0
      49: invokevirtual #45                 // Method hasKind:()Z
      52: ifeq          76
      55: iload_3
      56: ifeq          74
      59: aload_0
      60: invokevirtual #63                 // Method getKind:()Lorg/apache/hadoop/hbase/protobuf/generated/AuthenticationProtos$TokenIdentifier$Kind;
      63: aload_2
      64: invokevirtual #63                 // Method getKind:()Lorg/apache/hadoop/hbase/protobuf/generated/AuthenticationProtos$TokenIdentifier$Kind;
      67: if_acmpne     74
      70: iconst_1
      71: goto          75
      74: iconst_0
      75: istore_3
      76: iload_3
      77: ifeq          95
      80: aload_0
      81: invokevirtual #46                 // Method hasUsername:()Z
      84: aload_2
      85: invokevirtual #46                 // Method hasUsername:()Z
      88: if_icmpne     95
      91: iconst_1
      92: goto          96
      95: iconst_0
      96: istore_3
      97: aload_0
      98: invokevirtual #46                 // Method hasUsername:()Z
     101: ifeq          128
     104: iload_3
     105: ifeq          126
     108: aload_0
     109: invokevirtual #64                 // Method getUsername:()Lcom/google/protobuf/ByteString;
     112: aload_2
     113: invokevirtual #64                 // Method getUsername:()Lcom/google/protobuf/ByteString;
     116: invokevirtual #65                 // Method com/google/protobuf/ByteString.equals:(Ljava/lang/Object;)Z
     119: ifeq          126
     122: iconst_1
     123: goto          127
     126: iconst_0
     127: istore_3
     128: iload_3
     129: ifeq          147
     132: aload_0
     133: invokevirtual #47                 // Method hasKeyId:()Z
     136: aload_2
     137: invokevirtual #47                 // Method hasKeyId:()Z
     140: if_icmpne     147
     143: iconst_1
     144: goto          148
     147: iconst_0
     148: istore_3
     149: aload_0
     150: invokevirtual #47                 // Method hasKeyId:()Z
     153: ifeq          177
     156: iload_3
     157: ifeq          175
     160: aload_0
     161: invokevirtual #66                 // Method getKeyId:()I
     164: aload_2
     165: invokevirtual #66                 // Method getKeyId:()I
     168: if_icmpne     175
     171: iconst_1
     172: goto          176
     175: iconst_0
     176: istore_3
     177: iload_3
     178: ifeq          196
     181: aload_0
     182: invokevirtual #67                 // Method hasIssueDate:()Z
     185: aload_2
     186: invokevirtual #67                 // Method hasIssueDate:()Z
     189: if_icmpne     196
     192: iconst_1
     193: goto          197
     196: iconst_0
     197: istore_3
     198: aload_0
     199: invokevirtual #67                 // Method hasIssueDate:()Z
     202: ifeq          227
     205: iload_3
     206: ifeq          225
     209: aload_0
     210: invokevirtual #68                 // Method getIssueDate:()J
     213: aload_2
     214: invokevirtual #68                 // Method getIssueDate:()J
     217: lcmp
     218: ifne          225
     221: iconst_1
     222: goto          226
     225: iconst_0
     226: istore_3
     227: iload_3
     228: ifeq          246
     231: aload_0
     232: invokevirtual #69                 // Method hasExpirationDate:()Z
     235: aload_2
     236: invokevirtual #69                 // Method hasExpirationDate:()Z
     239: if_icmpne     246
     242: iconst_1
     243: goto          247
     246: iconst_0
     247: istore_3
     248: aload_0
     249: invokevirtual #69                 // Method hasExpirationDate:()Z
     252: ifeq          277
     255: iload_3
     256: ifeq          275
     259: aload_0
     260: invokevirtual #70                 // Method getExpirationDate:()J
     263: aload_2
     264: invokevirtual #70                 // Method getExpirationDate:()J
     267: lcmp
     268: ifne          275
     271: iconst_1
     272: goto          276
     275: iconst_0
     276: istore_3
     277: iload_3
     278: ifeq          296
     281: aload_0
     282: invokevirtual #71                 // Method hasSequenceNumber:()Z
     285: aload_2
     286: invokevirtual #71                 // Method hasSequenceNumber:()Z
     289: if_icmpne     296
     292: iconst_1
     293: goto          297
     296: iconst_0
     297: istore_3
     298: aload_0
     299: invokevirtual #71                 // Method hasSequenceNumber:()Z
     302: ifeq          327
     305: iload_3
     306: ifeq          325
     309: aload_0
     310: invokevirtual #72                 // Method getSequenceNumber:()J
     313: aload_2
     314: invokevirtual #72                 // Method getSequenceNumber:()J
     317: lcmp
     318: ifne          325
     321: iconst_1
     322: goto          326
     325: iconst_0
     326: istore_3
     327: iload_3
     328: ifeq          349
     331: aload_0
     332: invokevirtual #54                 // Method getUnknownFields:()Lcom/google/protobuf/UnknownFieldSet;
     335: aload_2
     336: invokevirtual #54                 // Method getUnknownFields:()Lcom/google/protobuf/UnknownFieldSet;
     339: invokevirtual #73                 // Method com/google/protobuf/UnknownFieldSet.equals:(Ljava/lang/Object;)Z
     342: ifeq          349
     345: iconst_1
     346: goto          350
     349: iconst_0
     350: istore_3
     351: iload_3
     352: ireturn

  public int hashCode();
    Code:
       0: aload_0
       1: getfield      #14                 // Field memoizedHashCode:I
       4: ifeq          12
       7: aload_0
       8: getfield      #14                 // Field memoizedHashCode:I
      11: ireturn
      12: bipush        41
      14: istore_1
      15: bipush        19
      17: iload_1
      18: imul
      19: aload_0
      20: invokevirtual #74                 // Method getDescriptorForType:()Lcom/google/protobuf/Descriptors$Descriptor;
      23: invokevirtual #75                 // Method java/lang/Object.hashCode:()I
      26: iadd
      27: istore_1
      28: aload_0
      29: invokevirtual #45                 // Method hasKind:()Z
      32: ifeq          55
      35: bipush        37
      37: iload_1
      38: imul
      39: iconst_1
      40: iadd
      41: istore_1
      42: bipush        53
      44: iload_1
      45: imul
      46: aload_0
      47: invokevirtual #63                 // Method getKind:()Lorg/apache/hadoop/hbase/protobuf/generated/AuthenticationProtos$TokenIdentifier$Kind;
      50: invokestatic  #76                 // Method hashEnum:(Lcom/google/protobuf/Internal$EnumLite;)I
      53: iadd
      54: istore_1
      55: aload_0
      56: invokevirtual #46                 // Method hasUsername:()Z
      59: ifeq          82
      62: bipush        37
      64: iload_1
      65: imul
      66: iconst_2
      67: iadd
      68: istore_1
      69: bipush        53
      71: iload_1
      72: imul
      73: aload_0
      74: invokevirtual #64                 // Method getUsername:()Lcom/google/protobuf/ByteString;
      77: invokevirtual #77                 // Method com/google/protobuf/ByteString.hashCode:()I
      80: iadd
      81: istore_1
      82: aload_0
      83: invokevirtual #47                 // Method hasKeyId:()Z
      86: ifeq          106
      89: bipush        37
      91: iload_1
      92: imul
      93: iconst_3
      94: iadd
      95: istore_1
      96: bipush        53
      98: iload_1
      99: imul
     100: aload_0
     101: invokevirtual #66                 // Method getKeyId:()I
     104: iadd
     105: istore_1
     106: aload_0
     107: invokevirtual #67                 // Method hasIssueDate:()Z
     110: ifeq          133
     113: bipush        37
     115: iload_1
     116: imul
     117: iconst_4
     118: iadd
     119: istore_1
     120: bipush        53
     122: iload_1
     123: imul
     124: aload_0
     125: invokevirtual #68                 // Method getIssueDate:()J
     128: invokestatic  #78                 // Method hashLong:(J)I
     131: iadd
     132: istore_1
     133: aload_0
     134: invokevirtual #69                 // Method hasExpirationDate:()Z
     137: ifeq          160
     140: bipush        37
     142: iload_1
     143: imul
     144: iconst_5
     145: iadd
     146: istore_1
     147: bipush        53
     149: iload_1
     150: imul
     151: aload_0
     152: invokevirtual #70                 // Method getExpirationDate:()J
     155: invokestatic  #78                 // Method hashLong:(J)I
     158: iadd
     159: istore_1
     160: aload_0
     161: invokevirtual #71                 // Method hasSequenceNumber:()Z
     164: ifeq          188
     167: bipush        37
     169: iload_1
     170: imul
     171: bipush        6
     173: iadd
     174: istore_1
     175: bipush        53
     177: iload_1
     178: imul
     179: aload_0
     180: invokevirtual #72                 // Method getSequenceNumber:()J
     183: invokestatic  #78                 // Method hashLong:(J)I
     186: iadd
     187: istore_1
     188: bipush        29
     190: iload_1
     191: imul
     192: aload_0
     193: invokevirtual #54                 // Method getUnknownFields:()Lcom/google/protobuf/UnknownFieldSet;
     196: invokevirtual #79                 // Method com/google/protobuf/UnknownFieldSet.hashCode:()I
     199: iadd
     200: istore_1
     201: aload_0
     202: iload_1
     203: putfield      #14                 // Field memoizedHashCode:I
     206: iload_1
     207: ireturn

  public static org.apache.hadoop.hbase.protobuf.generated.AuthenticationProtos$TokenIdentifier parseFrom(com.google.protobuf.ByteString) throws com.google.protobuf.InvalidProtocolBufferException;
    Code:
       0: getstatic     #42                 // Field PARSER:Lcom/google/protobuf/Parser;
       3: aload_0
       4: invokeinterface #80,  2           // InterfaceMethod com/google/protobuf/Parser.parseFrom:(Lcom/google/protobuf/ByteString;)Ljava/lang/Object;
       9: checkcast     #39                 // class org/apache/hadoop/hbase/protobuf/generated/AuthenticationProtos$TokenIdentifier
      12: areturn

  public static org.apache.hadoop.hbase.protobuf.generated.AuthenticationProtos$TokenIdentifier parseFrom(com.google.protobuf.ByteString, com.google.protobuf.ExtensionRegistryLite) throws com.google.protobuf.InvalidProtocolBufferException;
    Code:
       0: getstatic     #42                 // Field PARSER:Lcom/google/protobuf/Parser;
       3: aload_0
       4: aload_1
       5: invokeinterface #81,  3           // InterfaceMethod com/google/protobuf/Parser.parseFrom:(Lcom/google/protobuf/ByteString;Lcom/google/protobuf/ExtensionRegistryLite;)Ljava/lang/Object;
      10: checkcast     #39                 // class org/apache/hadoop/hbase/protobuf/generated/AuthenticationProtos$TokenIdentifier
      13: areturn

  public static org.apache.hadoop.hbase.protobuf.generated.AuthenticationProtos$TokenIdentifier parseFrom(byte[]) throws com.google.protobuf.InvalidProtocolBufferException;
    Code:
       0: getstatic     #42                 // Field PARSER:Lcom/google/protobuf/Parser;
       3: aload_0
       4: invokeinterface #82,  2           // InterfaceMethod com/google/protobuf/Parser.parseFrom:([B)Ljava/lang/Object;
       9: checkcast     #39                 // class org/apache/hadoop/hbase/protobuf/generated/AuthenticationProtos$TokenIdentifier
      12: areturn

  public static org.apache.hadoop.hbase.protobuf.generated.AuthenticationProtos$TokenIdentifier parseFrom(byte[], com.google.protobuf.ExtensionRegistryLite) throws com.google.protobuf.InvalidProtocolBufferException;
    Code:
       0: getstatic     #42                 // Field PARSER:Lcom/google/protobuf/Parser;
       3: aload_0
       4: aload_1
       5: invokeinterface #83,  3           // InterfaceMethod com/google/protobuf/Parser.parseFrom:([BLcom/google/protobuf/ExtensionRegistryLite;)Ljava/lang/Object;
      10: checkcast     #39                 // class org/apache/hadoop/hbase/protobuf/generated/AuthenticationProtos$TokenIdentifier
      13: areturn

  public static org.apache.hadoop.hbase.protobuf.generated.AuthenticationProtos$TokenIdentifier parseFrom(java.io.InputStream) throws java.io.IOException;
    Code:
       0: getstatic     #42                 // Field PARSER:Lcom/google/protobuf/Parser;
       3: aload_0
       4: invokeinterface #84,  2           // InterfaceMethod com/google/protobuf/Parser.parseFrom:(Ljava/io/InputStream;)Ljava/lang/Object;
       9: checkcast     #39                 // class org/apache/hadoop/hbase/protobuf/generated/AuthenticationProtos$TokenIdentifier
      12: areturn

  public static org.apache.hadoop.hbase.protobuf.generated.AuthenticationProtos$TokenIdentifier parseFrom(java.io.InputStream, com.google.protobuf.ExtensionRegistryLite) throws java.io.IOException;
    Code:
       0: getstatic     #42                 // Field PARSER:Lcom/google/protobuf/Parser;
       3: aload_0
       4: aload_1
       5: invokeinterface #85,  3           // InterfaceMethod com/google/protobuf/Parser.parseFrom:(Ljava/io/InputStream;Lcom/google/protobuf/ExtensionRegistryLite;)Ljava/lang/Object;
      10: checkcast     #39                 // class org/apache/hadoop/hbase/protobuf/generated/AuthenticationProtos$TokenIdentifier
      13: areturn

  public static org.apache.hadoop.hbase.protobuf.generated.AuthenticationProtos$TokenIdentifier parseDelimitedFrom(java.io.InputStream) throws java.io.IOException;
    Code:
       0: getstatic     #42                 // Field PARSER:Lcom/google/protobuf/Parser;
       3: aload_0
       4: invokeinterface #86,  2           // InterfaceMethod com/google/protobuf/Parser.parseDelimitedFrom:(Ljava/io/InputStream;)Ljava/lang/Object;
       9: checkcast     #39                 // class org/apache/hadoop/hbase/protobuf/generated/AuthenticationProtos$TokenIdentifier
      12: areturn

  public static org.apache.hadoop.hbase.protobuf.generated.AuthenticationProtos$TokenIdentifier parseDelimitedFrom(java.io.InputStream, com.google.protobuf.ExtensionRegistryLite) throws java.io.IOException;
    Code:
       0: getstatic     #42                 // Field PARSER:Lcom/google/protobuf/Parser;
       3: aload_0
       4: aload_1
       5: invokeinterface #87,  3           // InterfaceMethod com/google/protobuf/Parser.parseDelimitedFrom:(Ljava/io/InputStream;Lcom/google/protobuf/ExtensionRegistryLite;)Ljava/lang/Object;
      10: checkcast     #39                 // class org/apache/hadoop/hbase/protobuf/generated/AuthenticationProtos$TokenIdentifier
      13: areturn

  public static org.apache.hadoop.hbase.protobuf.generated.AuthenticationProtos$TokenIdentifier parseFrom(com.google.protobuf.CodedInputStream) throws java.io.IOException;
    Code:
       0: getstatic     #42                 // Field PARSER:Lcom/google/protobuf/Parser;
       3: aload_0
       4: invokeinterface #88,  2           // InterfaceMethod com/google/protobuf/Parser.parseFrom:(Lcom/google/protobuf/CodedInputStream;)Ljava/lang/Object;
       9: checkcast     #39                 // class org/apache/hadoop/hbase/protobuf/generated/AuthenticationProtos$TokenIdentifier
      12: areturn

  public static org.apache.hadoop.hbase.protobuf.generated.AuthenticationProtos$TokenIdentifier parseFrom(com.google.protobuf.CodedInputStream, com.google.protobuf.ExtensionRegistryLite) throws java.io.IOException;
    Code:
       0: getstatic     #42                 // Field PARSER:Lcom/google/protobuf/Parser;
       3: aload_0
       4: aload_1
       5: invokeinterface #89,  3           // InterfaceMethod com/google/protobuf/Parser.parseFrom:(Lcom/google/protobuf/CodedInputStream;Lcom/google/protobuf/ExtensionRegistryLite;)Ljava/lang/Object;
      10: checkcast     #39                 // class org/apache/hadoop/hbase/protobuf/generated/AuthenticationProtos$TokenIdentifier
      13: areturn

  public static org.apache.hadoop.hbase.protobuf.generated.AuthenticationProtos$TokenIdentifier$Builder newBuilder();
    Code:
       0: invokestatic  #90                 // Method org/apache/hadoop/hbase/protobuf/generated/AuthenticationProtos$TokenIdentifier$Builder.access$1400:()Lorg/apache/hadoop/hbase/protobuf/generated/AuthenticationProtos$TokenIdentifier$Builder;
       3: areturn

  public org.apache.hadoop.hbase.protobuf.generated.AuthenticationProtos$TokenIdentifier$Builder newBuilderForType();
    Code:
       0: invokestatic  #91                 // Method newBuilder:()Lorg/apache/hadoop/hbase/protobuf/generated/AuthenticationProtos$TokenIdentifier$Builder;
       3: areturn

  public static org.apache.hadoop.hbase.protobuf.generated.AuthenticationProtos$TokenIdentifier$Builder newBuilder(org.apache.hadoop.hbase.protobuf.generated.AuthenticationProtos$TokenIdentifier);
    Code:
       0: invokestatic  #91                 // Method newBuilder:()Lorg/apache/hadoop/hbase/protobuf/generated/AuthenticationProtos$TokenIdentifier$Builder;
       3: aload_0
       4: invokevirtual #92                 // Method org/apache/hadoop/hbase/protobuf/generated/AuthenticationProtos$TokenIdentifier$Builder.mergeFrom:(Lorg/apache/hadoop/hbase/protobuf/generated/AuthenticationProtos$TokenIdentifier;)Lorg/apache/hadoop/hbase/protobuf/generated/AuthenticationProtos$TokenIdentifier$Builder;
       7: areturn

  public org.apache.hadoop.hbase.protobuf.generated.AuthenticationProtos$TokenIdentifier$Builder toBuilder();
    Code:
       0: aload_0
       1: invokestatic  #93                 // Method newBuilder:(Lorg/apache/hadoop/hbase/protobuf/generated/AuthenticationProtos$TokenIdentifier;)Lorg/apache/hadoop/hbase/protobuf/generated/AuthenticationProtos$TokenIdentifier$Builder;
       4: areturn

  protected org.apache.hadoop.hbase.protobuf.generated.AuthenticationProtos$TokenIdentifier$Builder newBuilderForType(com.google.protobuf.GeneratedMessage$BuilderParent);
    Code:
       0: new           #40                 // class org/apache/hadoop/hbase/protobuf/generated/AuthenticationProtos$TokenIdentifier$Builder
       3: dup
       4: aload_1
       5: aconst_null
       6: invokespecial #94                 // Method org/apache/hadoop/hbase/protobuf/generated/AuthenticationProtos$TokenIdentifier$Builder."<init>":(Lcom/google/protobuf/GeneratedMessage$BuilderParent;Lorg/apache/hadoop/hbase/protobuf/generated/AuthenticationProtos$1;)V
       9: astore_2
      10: aload_2
      11: areturn

  protected com.google.protobuf.Message$Builder newBuilderForType(com.google.protobuf.GeneratedMessage$BuilderParent);
    Code:
       0: aload_0
       1: aload_1
       2: invokevirtual #95                 // Method newBuilderForType:(Lcom/google/protobuf/GeneratedMessage$BuilderParent;)Lorg/apache/hadoop/hbase/protobuf/generated/AuthenticationProtos$TokenIdentifier$Builder;
       5: areturn

  public com.google.protobuf.Message$Builder toBuilder();
    Code:
       0: aload_0
       1: invokevirtual #96                 // Method toBuilder:()Lorg/apache/hadoop/hbase/protobuf/generated/AuthenticationProtos$TokenIdentifier$Builder;
       4: areturn

  public com.google.protobuf.Message$Builder newBuilderForType();
    Code:
       0: aload_0
       1: invokevirtual #97                 // Method newBuilderForType:()Lorg/apache/hadoop/hbase/protobuf/generated/AuthenticationProtos$TokenIdentifier$Builder;
       4: areturn

  public com.google.protobuf.MessageLite$Builder toBuilder();
    Code:
       0: aload_0
       1: invokevirtual #96                 // Method toBuilder:()Lorg/apache/hadoop/hbase/protobuf/generated/AuthenticationProtos$TokenIdentifier$Builder;
       4: areturn

  public com.google.protobuf.MessageLite$Builder newBuilderForType();
    Code:
       0: aload_0
       1: invokevirtual #97                 // Method newBuilderForType:()Lorg/apache/hadoop/hbase/protobuf/generated/AuthenticationProtos$TokenIdentifier$Builder;
       4: areturn

  public com.google.protobuf.MessageLite getDefaultInstanceForType();
    Code:
       0: aload_0
       1: invokevirtual #98                 // Method getDefaultInstanceForType:()Lorg/apache/hadoop/hbase/protobuf/generated/AuthenticationProtos$TokenIdentifier;
       4: areturn

  public com.google.protobuf.Message getDefaultInstanceForType();
    Code:
       0: aload_0
       1: invokevirtual #98                 // Method getDefaultInstanceForType:()Lorg/apache/hadoop/hbase/protobuf/generated/AuthenticationProtos$TokenIdentifier;
       4: areturn

  org.apache.hadoop.hbase.protobuf.generated.AuthenticationProtos$TokenIdentifier(com.google.protobuf.CodedInputStream, com.google.protobuf.ExtensionRegistryLite, org.apache.hadoop.hbase.protobuf.generated.AuthenticationProtos$1) throws com.google.protobuf.InvalidProtocolBufferException;
    Code:
       0: aload_0
       1: aload_1
       2: aload_2
       3: invokespecial #10                 // Method "<init>":(Lcom/google/protobuf/CodedInputStream;Lcom/google/protobuf/ExtensionRegistryLite;)V
       6: return

  static boolean access$1600();
    Code:
       0: getstatic     #9                  // Field alwaysUseFieldBuilders:Z
       3: ireturn

  org.apache.hadoop.hbase.protobuf.generated.AuthenticationProtos$TokenIdentifier(com.google.protobuf.GeneratedMessage$Builder, org.apache.hadoop.hbase.protobuf.generated.AuthenticationProtos$1);
    Code:
       0: aload_0
       1: aload_1
       2: invokespecial #8                  // Method "<init>":(Lcom/google/protobuf/GeneratedMessage$Builder;)V
       5: return

  static org.apache.hadoop.hbase.protobuf.generated.AuthenticationProtos$TokenIdentifier$Kind access$1802(org.apache.hadoop.hbase.protobuf.generated.AuthenticationProtos$TokenIdentifier, org.apache.hadoop.hbase.protobuf.generated.AuthenticationProtos$TokenIdentifier$Kind);
    Code:
       0: aload_0
       1: aload_1
       2: dup_x1
       3: putfield      #7                  // Field kind_:Lorg/apache/hadoop/hbase/protobuf/generated/AuthenticationProtos$TokenIdentifier$Kind;
       6: areturn

  static com.google.protobuf.ByteString access$1902(org.apache.hadoop.hbase.protobuf.generated.AuthenticationProtos$TokenIdentifier, com.google.protobuf.ByteString);
    Code:
       0: aload_0
       1: aload_1
       2: dup_x1
       3: putfield      #6                  // Field username_:Lcom/google/protobuf/ByteString;
       6: areturn

  static int access$2002(org.apache.hadoop.hbase.protobuf.generated.AuthenticationProtos$TokenIdentifier, int);
    Code:
       0: aload_0
       1: iload_1
       2: dup_x1
       3: putfield      #5                  // Field keyId_:I
       6: ireturn

  static long access$2102(org.apache.hadoop.hbase.protobuf.generated.AuthenticationProtos$TokenIdentifier, long);
    Code:
       0: aload_0
       1: lload_1
       2: dup2_x1
       3: putfield      #4                  // Field issueDate_:J
       6: lreturn

  static long access$2202(org.apache.hadoop.hbase.protobuf.generated.AuthenticationProtos$TokenIdentifier, long);
    Code:
       0: aload_0
       1: lload_1
       2: dup2_x1
       3: putfield      #3                  // Field expirationDate_:J
       6: lreturn

  static long access$2302(org.apache.hadoop.hbase.protobuf.generated.AuthenticationProtos$TokenIdentifier, long);
    Code:
       0: aload_0
       1: lload_1
       2: dup2_x1
       3: putfield      #2                  // Field sequenceNumber_:J
       6: lreturn

  static int access$2402(org.apache.hadoop.hbase.protobuf.generated.AuthenticationProtos$TokenIdentifier, int);
    Code:
       0: aload_0
       1: iload_1
       2: dup_x1
       3: putfield      #1                  // Field bitField0_:I
       6: ireturn

  static {};
    Code:
       0: new           #99                 // class org/apache/hadoop/hbase/protobuf/generated/AuthenticationProtos$TokenIdentifier$1
       3: dup
       4: invokespecial #100                // Method org/apache/hadoop/hbase/protobuf/generated/AuthenticationProtos$TokenIdentifier$1."<init>":()V
       7: putstatic     #42                 // Field PARSER:Lcom/google/protobuf/Parser;
      10: new           #39                 // class org/apache/hadoop/hbase/protobuf/generated/AuthenticationProtos$TokenIdentifier
      13: dup
      14: iconst_1
      15: invokespecial #101                // Method "<init>":(Z)V
      18: putstatic     #19                 // Field defaultInstance:Lorg/apache/hadoop/hbase/protobuf/generated/AuthenticationProtos$TokenIdentifier;
      21: getstatic     #19                 // Field defaultInstance:Lorg/apache/hadoop/hbase/protobuf/generated/AuthenticationProtos$TokenIdentifier;
      24: invokespecial #20                 // Method initFields:()V
      27: return
}
