Compiled from "Authorizations.java"
public class org.apache.hadoop.hbase.security.visibility.Authorizations {
  public org.apache.hadoop.hbase.security.visibility.Authorizations(java.lang.String...);
    Code:
       0: aload_0
       1: invokespecial #1                  // Method java/lang/Object."<init>":()V
       4: aload_0
       5: new           #2                  // class java/util/ArrayList
       8: dup
       9: aload_1
      10: arraylength
      11: invokespecial #3                  // Method java/util/ArrayList."<init>":(I)V
      14: putfield      #4                  // Field labels:Ljava/util/List;
      17: aload_0
      18: getfield      #4                  // Field labels:Ljava/util/List;
      21: aload_1
      22: invokestatic  #5                  // Method java/util/Collections.addAll:(Ljava/util/Collection;[Ljava/lang/Object;)Z
      25: pop
      26: return

  public org.apache.hadoop.hbase.security.visibility.Authorizations(java.util.List<java.lang.String>);
    Code:
       0: aload_0
       1: invokespecial #1                  // Method java/lang/Object."<init>":()V
       4: aload_0
       5: aload_1
       6: putfield      #4                  // Field labels:Ljava/util/List;
       9: return

  public java.util.List<java.lang.String> getLabels();
    Code:
       0: aload_0
       1: getfield      #4                  // Field labels:Ljava/util/List;
       4: invokestatic  #6                  // Method java/util/Collections.unmodifiableList:(Ljava/util/List;)Ljava/util/List;
       7: areturn

  public java.lang.String toString();
    Code:
       0: new           #7                  // class java/lang/StringBuilder
       3: dup
       4: invokespecial #8                  // Method java/lang/StringBuilder."<init>":()V
       7: astore_1
       8: aload_1
       9: ldc           #9                  // String [
      11: invokevirtual #10                 // Method java/lang/StringBuilder.append:(Ljava/lang/String;)Ljava/lang/StringBuilder;
      14: pop
      15: aload_0
      16: getfield      #4                  // Field labels:Ljava/util/List;
      19: invokeinterface #11,  1           // InterfaceMethod java/util/List.iterator:()Ljava/util/Iterator;
      24: astore_2
      25: aload_2
      26: invokeinterface #12,  1           // InterfaceMethod java/util/Iterator.hasNext:()Z
      31: ifeq          60
      34: aload_2
      35: invokeinterface #13,  1           // InterfaceMethod java/util/Iterator.next:()Ljava/lang/Object;
      40: checkcast     #14                 // class java/lang/String
      43: astore_3
      44: aload_1
      45: aload_3
      46: invokevirtual #10                 // Method java/lang/StringBuilder.append:(Ljava/lang/String;)Ljava/lang/StringBuilder;
      49: pop
      50: aload_1
      51: bipush        32
      53: invokevirtual #15                 // Method java/lang/StringBuilder.append:(C)Ljava/lang/StringBuilder;
      56: pop
      57: goto          25
      60: aload_1
      61: bipush        93
      63: invokevirtual #15                 // Method java/lang/StringBuilder.append:(C)Ljava/lang/StringBuilder;
      66: pop
      67: aload_1
      68: invokevirtual #16                 // Method java/lang/StringBuilder.toString:()Ljava/lang/String;
      71: areturn
}
