Compiled from "AuthUtil.java"
public final class org.apache.hadoop.hbase.AuthUtil {
  public static final java.lang.String HBASE_CLIENT_KEYTAB_FILE;

  public static final java.lang.String HBASE_CLIENT_KERBEROS_PRINCIPAL;

  public static org.apache.hadoop.hbase.security.User loginClient(org.apache.hadoop.conf.Configuration) throws java.io.IOException;
    Code:
       0: aload_0
       1: invokestatic  #3                  // Method org/apache/hadoop/hbase/security/UserProvider.instantiate:(Lorg/apache/hadoop/conf/Configuration;)Lorg/apache/hadoop/hbase/security/UserProvider;
       4: astore_1
       5: aload_1
       6: invokevirtual #4                  // Method org/apache/hadoop/hbase/security/UserProvider.getCurrent:()Lorg/apache/hadoop/hbase/security/User;
       9: astore_2
      10: aload_1
      11: invokevirtual #5                  // Method org/apache/hadoop/hbase/security/UserProvider.isHBaseSecurityEnabled:()Z
      14: ifeq          28
      17: aload_1
      18: invokevirtual #6                  // Method org/apache/hadoop/hbase/security/UserProvider.isHadoopSecurityEnabled:()Z
      21: ifeq          28
      24: iconst_1
      25: goto          29
      28: iconst_0
      29: istore_3
      30: iload_3
      31: ifeq          90
      34: aload_1
      35: invokevirtual #7                  // Method org/apache/hadoop/hbase/security/UserProvider.shouldLoginFromKeytab:()Z
      38: istore        4
      40: aload_2
      41: invokevirtual #8                  // Method org/apache/hadoop/hbase/security/User.getUGI:()Lorg/apache/hadoop/security/UserGroupInformation;
      44: invokevirtual #9                  // Method org/apache/hadoop/security/UserGroupInformation.hasKerberosCredentials:()Z
      47: ifeq          80
      50: iload         4
      52: ifeq          78
      55: aload_0
      56: aload_2
      57: invokevirtual #8                  // Method org/apache/hadoop/hbase/security/User.getUGI:()Lorg/apache/hadoop/security/UserGroupInformation;
      60: invokevirtual #10                 // Method org/apache/hadoop/security/UserGroupInformation.getUserName:()Ljava/lang/String;
      63: invokestatic  #11                 // Method checkPrincipalMatch:(Lorg/apache/hadoop/conf/Configuration;Ljava/lang/String;)Z
      66: ifeq          73
      69: aload_2
      70: goto          77
      73: aload_1
      74: invokestatic  #12                 // Method loginFromKeytabAndReturnUser:(Lorg/apache/hadoop/hbase/security/UserProvider;)Lorg/apache/hadoop/hbase/security/User;
      77: areturn
      78: aload_2
      79: areturn
      80: iload         4
      82: ifeq          90
      85: aload_1
      86: invokestatic  #12                 // Method loginFromKeytabAndReturnUser:(Lorg/apache/hadoop/hbase/security/UserProvider;)Lorg/apache/hadoop/hbase/security/User;
      89: areturn
      90: aload_2
      91: areturn

  public static org.apache.hadoop.hbase.ScheduledChore getAuthRenewalChore(org.apache.hadoop.security.UserGroupInformation);
    Code:
       0: aload_0
       1: invokevirtual #9                  // Method org/apache/hadoop/security/UserGroupInformation.hasKerberosCredentials:()Z
       4: ifne          9
       7: aconst_null
       8: areturn
       9: invokestatic  #42                 // Method createDummyStoppable:()Lorg/apache/hadoop/hbase/Stoppable;
      12: astore_1
      13: sipush        30000
      16: istore_2
      17: new           #43                 // class org/apache/hadoop/hbase/AuthUtil$1
      20: dup
      21: ldc           #44                 // String RefreshCredentials
      23: aload_1
      24: sipush        30000
      27: aload_0
      28: invokespecial #45                 // Method org/apache/hadoop/hbase/AuthUtil$1."<init>":(Ljava/lang/String;Lorg/apache/hadoop/hbase/Stoppable;ILorg/apache/hadoop/security/UserGroupInformation;)V
      31: areturn

  public static org.apache.hadoop.hbase.ScheduledChore getAuthChore(org.apache.hadoop.conf.Configuration) throws java.io.IOException;
    Code:
       0: aload_0
       1: invokestatic  #46                 // Method loginClientAsService:(Lorg/apache/hadoop/conf/Configuration;)Lorg/apache/hadoop/hbase/security/User;
       4: astore_1
       5: aload_1
       6: invokevirtual #8                  // Method org/apache/hadoop/hbase/security/User.getUGI:()Lorg/apache/hadoop/security/UserGroupInformation;
       9: invokestatic  #47                 // Method getAuthRenewalChore:(Lorg/apache/hadoop/security/UserGroupInformation;)Lorg/apache/hadoop/hbase/ScheduledChore;
      12: areturn

  public static boolean isGroupPrincipal(java.lang.String);
    Code:
       0: aload_0
       1: ifnull        17
       4: aload_0
       5: ldc           #50                 // String @
       7: invokevirtual #51                 // Method java/lang/String.startsWith:(Ljava/lang/String;)Z
      10: ifeq          17
      13: iconst_1
      14: goto          18
      17: iconst_0
      18: ireturn

  public static java.lang.String getGroupName(java.lang.String);
    Code:
       0: aload_0
       1: invokestatic  #52                 // Method isGroupPrincipal:(Ljava/lang/String;)Z
       4: ifne          9
       7: aload_0
       8: areturn
       9: aload_0
      10: ldc           #50                 // String @
      12: invokevirtual #53                 // Method java/lang/String.length:()I
      15: invokevirtual #54                 // Method java/lang/String.substring:(I)Ljava/lang/String;
      18: areturn

  public static java.lang.String toGroupEntry(java.lang.String);
    Code:
       0: new           #34                 // class java/lang/StringBuilder
       3: dup
       4: invokespecial #35                 // Method java/lang/StringBuilder."<init>":()V
       7: ldc           #50                 // String @
       9: invokevirtual #37                 // Method java/lang/StringBuilder.append:(Ljava/lang/String;)Ljava/lang/StringBuilder;
      12: aload_0
      13: invokevirtual #37                 // Method java/lang/StringBuilder.append:(Ljava/lang/String;)Ljava/lang/StringBuilder;
      16: invokevirtual #39                 // Method java/lang/StringBuilder.toString:()Ljava/lang/String;
      19: areturn

  static org.slf4j.Logger access$000();
    Code:
       0: getstatic     #1                  // Field LOG:Lorg/slf4j/Logger;
       3: areturn

  static {};
    Code:
       0: ldc           #13                 // class org/apache/hadoop/hbase/AuthUtil
       2: invokestatic  #55                 // Method org/slf4j/LoggerFactory.getLogger:(Ljava/lang/Class;)Lorg/slf4j/Logger;
       5: putstatic     #1                  // Field LOG:Lorg/slf4j/Logger;
       8: return
}
