Compiled from "AvlUtil.java"
public class org.apache.hadoop.hbase.util.AvlUtil$AvlTree {
  static final boolean $assertionsDisabled;

  public org.apache.hadoop.hbase.util.AvlUtil$AvlTree();
    Code:
       0: aload_0
       1: invokespecial #1                  // Method java/lang/Object."<init>":()V
       4: return

  public static <TNode extends org.apache.hadoop.hbase.util.AvlUtil$AvlNode> TNode get(TNode, java.lang.Object, org.apache.hadoop.hbase.util.AvlUtil$AvlKeyComparator<TNode>);
    Code:
       0: aload_0
       1: ifnull        42
       4: aload_2
       5: aload_0
       6: aload_1
       7: invokeinterface #2,  3            // InterfaceMethod org/apache/hadoop/hbase/util/AvlUtil$AvlKeyComparator.compareKey:(Lorg/apache/hadoop/hbase/util/AvlUtil$AvlNode;Ljava/lang/Object;)I
      12: istore_3
      13: iload_3
      14: ifle          25
      17: aload_0
      18: getfield      #3                  // Field org/apache/hadoop/hbase/util/AvlUtil$AvlNode.avlLeft:Lorg/apache/hadoop/hbase/util/AvlUtil$AvlNode;
      21: astore_0
      22: goto          39
      25: iload_3
      26: ifge          37
      29: aload_0
      30: getfield      #4                  // Field org/apache/hadoop/hbase/util/AvlUtil$AvlNode.avlRight:Lorg/apache/hadoop/hbase/util/AvlUtil$AvlNode;
      33: astore_0
      34: goto          39
      37: aload_0
      38: areturn
      39: goto          0
      42: aconst_null
      43: areturn

  public static <TNode extends org.apache.hadoop.hbase.util.AvlUtil$AvlNode> TNode getFirst(TNode);
    Code:
       0: aload_0
       1: ifnull        19
       4: aload_0
       5: getfield      #3                  // Field org/apache/hadoop/hbase/util/AvlUtil$AvlNode.avlLeft:Lorg/apache/hadoop/hbase/util/AvlUtil$AvlNode;
       8: ifnull        19
      11: aload_0
      12: getfield      #3                  // Field org/apache/hadoop/hbase/util/AvlUtil$AvlNode.avlLeft:Lorg/apache/hadoop/hbase/util/AvlUtil$AvlNode;
      15: astore_0
      16: goto          4
      19: aload_0
      20: areturn

  public static <TNode extends org.apache.hadoop.hbase.util.AvlUtil$AvlNode> TNode getLast(TNode);
    Code:
       0: aload_0
       1: ifnull        19
       4: aload_0
       5: getfield      #4                  // Field org/apache/hadoop/hbase/util/AvlUtil$AvlNode.avlRight:Lorg/apache/hadoop/hbase/util/AvlUtil$AvlNode;
       8: ifnull        19
      11: aload_0
      12: getfield      #4                  // Field org/apache/hadoop/hbase/util/AvlUtil$AvlNode.avlRight:Lorg/apache/hadoop/hbase/util/AvlUtil$AvlNode;
      15: astore_0
      16: goto          4
      19: aload_0
      20: areturn

  public static <TNode extends org.apache.hadoop.hbase.util.AvlUtil$AvlNode> TNode insert(TNode, TNode);
    Code:
       0: aload_0
       1: ifnonnull     6
       4: aload_1
       5: areturn
       6: aload_1
       7: aload_0
       8: invokevirtual #5                  // Method org/apache/hadoop/hbase/util/AvlUtil$AvlNode.compareTo:(Lorg/apache/hadoop/hbase/util/AvlUtil$AvlNode;)I
      11: istore_2
      12: getstatic     #6                  // Field $assertionsDisabled:Z
      15: ifne          49
      18: iload_2
      19: ifne          49
      22: new           #7                  // class java/lang/AssertionError
      25: dup
      26: new           #8                  // class java/lang/StringBuilder
      29: dup
      30: invokespecial #9                  // Method java/lang/StringBuilder."<init>":()V
      33: ldc           #10                 // String node already inserted:
      35: invokevirtual #11                 // Method java/lang/StringBuilder.append:(Ljava/lang/String;)Ljava/lang/StringBuilder;
      38: aload_0
      39: invokevirtual #12                 // Method java/lang/StringBuilder.append:(Ljava/lang/Object;)Ljava/lang/StringBuilder;
      42: invokevirtual #13                 // Method java/lang/StringBuilder.toString:()Ljava/lang/String;
      45: invokespecial #14                 // Method java/lang/AssertionError."<init>":(Ljava/lang/Object;)V
      48: athrow
      49: iload_2
      50: ifge          68
      53: aload_0
      54: aload_0
      55: getfield      #3                  // Field org/apache/hadoop/hbase/util/AvlUtil$AvlNode.avlLeft:Lorg/apache/hadoop/hbase/util/AvlUtil$AvlNode;
      58: aload_1
      59: invokestatic  #15                 // Method insert:(Lorg/apache/hadoop/hbase/util/AvlUtil$AvlNode;Lorg/apache/hadoop/hbase/util/AvlUtil$AvlNode;)Lorg/apache/hadoop/hbase/util/AvlUtil$AvlNode;
      62: putfield      #3                  // Field org/apache/hadoop/hbase/util/AvlUtil$AvlNode.avlLeft:Lorg/apache/hadoop/hbase/util/AvlUtil$AvlNode;
      65: goto          80
      68: aload_0
      69: aload_0
      70: getfield      #4                  // Field org/apache/hadoop/hbase/util/AvlUtil$AvlNode.avlRight:Lorg/apache/hadoop/hbase/util/AvlUtil$AvlNode;
      73: aload_1
      74: invokestatic  #15                 // Method insert:(Lorg/apache/hadoop/hbase/util/AvlUtil$AvlNode;Lorg/apache/hadoop/hbase/util/AvlUtil$AvlNode;)Lorg/apache/hadoop/hbase/util/AvlUtil$AvlNode;
      77: putfield      #4                  // Field org/apache/hadoop/hbase/util/AvlUtil$AvlNode.avlRight:Lorg/apache/hadoop/hbase/util/AvlUtil$AvlNode;
      80: aload_0
      81: invokestatic  #16                 // Method balance:(Lorg/apache/hadoop/hbase/util/AvlUtil$AvlNode;)Lorg/apache/hadoop/hbase/util/AvlUtil$AvlNode;
      84: areturn

  public static <TNode extends org.apache.hadoop.hbase.util.AvlUtil$AvlNode> TNode insert(TNode, java.lang.Object, org.apache.hadoop.hbase.util.AvlUtil$AvlKeyComparator<TNode>, org.apache.hadoop.hbase.util.AvlUtil$AvlInsertOrReplace<TNode>);
    Code:
       0: aload_0
       1: ifnonnull     12
       4: aload_3
       5: aload_1
       6: invokeinterface #17,  2           // InterfaceMethod org/apache/hadoop/hbase/util/AvlUtil$AvlInsertOrReplace.insert:(Ljava/lang/Object;)Lorg/apache/hadoop/hbase/util/AvlUtil$AvlNode;
      11: areturn
      12: aload_2
      13: aload_0
      14: aload_1
      15: invokeinterface #2,  3            // InterfaceMethod org/apache/hadoop/hbase/util/AvlUtil$AvlKeyComparator.compareKey:(Lorg/apache/hadoop/hbase/util/AvlUtil$AvlNode;Ljava/lang/Object;)I
      20: istore        4
      22: iload         4
      24: ifge          44
      27: aload_0
      28: aload_0
      29: getfield      #3                  // Field org/apache/hadoop/hbase/util/AvlUtil$AvlNode.avlLeft:Lorg/apache/hadoop/hbase/util/AvlUtil$AvlNode;
      32: aload_1
      33: aload_2
      34: aload_3
      35: invokestatic  #18                 // Method insert:(Lorg/apache/hadoop/hbase/util/AvlUtil$AvlNode;Ljava/lang/Object;Lorg/apache/hadoop/hbase/util/AvlUtil$AvlKeyComparator;Lorg/apache/hadoop/hbase/util/AvlUtil$AvlInsertOrReplace;)Lorg/apache/hadoop/hbase/util/AvlUtil$AvlNode;
      38: putfield      #3                  // Field org/apache/hadoop/hbase/util/AvlUtil$AvlNode.avlLeft:Lorg/apache/hadoop/hbase/util/AvlUtil$AvlNode;
      41: goto          101
      44: iload         4
      46: ifle          66
      49: aload_0
      50: aload_0
      51: getfield      #4                  // Field org/apache/hadoop/hbase/util/AvlUtil$AvlNode.avlRight:Lorg/apache/hadoop/hbase/util/AvlUtil$AvlNode;
      54: aload_1
      55: aload_2
      56: aload_3
      57: invokestatic  #18                 // Method insert:(Lorg/apache/hadoop/hbase/util/AvlUtil$AvlNode;Ljava/lang/Object;Lorg/apache/hadoop/hbase/util/AvlUtil$AvlKeyComparator;Lorg/apache/hadoop/hbase/util/AvlUtil$AvlInsertOrReplace;)Lorg/apache/hadoop/hbase/util/AvlUtil$AvlNode;
      60: putfield      #4                  // Field org/apache/hadoop/hbase/util/AvlUtil$AvlNode.avlRight:Lorg/apache/hadoop/hbase/util/AvlUtil$AvlNode;
      63: goto          101
      66: aload_0
      67: getfield      #3                  // Field org/apache/hadoop/hbase/util/AvlUtil$AvlNode.avlLeft:Lorg/apache/hadoop/hbase/util/AvlUtil$AvlNode;
      70: astore        5
      72: aload_0
      73: getfield      #4                  // Field org/apache/hadoop/hbase/util/AvlUtil$AvlNode.avlRight:Lorg/apache/hadoop/hbase/util/AvlUtil$AvlNode;
      76: astore        6
      78: aload_3
      79: aload_1
      80: aload_0
      81: invokeinterface #19,  3           // InterfaceMethod org/apache/hadoop/hbase/util/AvlUtil$AvlInsertOrReplace.replace:(Ljava/lang/Object;Lorg/apache/hadoop/hbase/util/AvlUtil$AvlNode;)Lorg/apache/hadoop/hbase/util/AvlUtil$AvlNode;
      86: astore_0
      87: aload_0
      88: aload         5
      90: putfield      #3                  // Field org/apache/hadoop/hbase/util/AvlUtil$AvlNode.avlLeft:Lorg/apache/hadoop/hbase/util/AvlUtil$AvlNode;
      93: aload_0
      94: aload         6
      96: putfield      #4                  // Field org/apache/hadoop/hbase/util/AvlUtil$AvlNode.avlRight:Lorg/apache/hadoop/hbase/util/AvlUtil$AvlNode;
      99: aload_0
     100: areturn
     101: aload_0
     102: invokestatic  #16                 // Method balance:(Lorg/apache/hadoop/hbase/util/AvlUtil$AvlNode;)Lorg/apache/hadoop/hbase/util/AvlUtil$AvlNode;
     105: areturn

  public static <TNode extends org.apache.hadoop.hbase.util.AvlUtil$AvlNode> TNode remove(TNode, java.lang.Object, org.apache.hadoop.hbase.util.AvlUtil$AvlKeyComparator<TNode>);
    Code:
       0: aload_0
       1: aload_1
       2: aload_2
       3: aconst_null
       4: invokestatic  #21                 // Method remove:(Lorg/apache/hadoop/hbase/util/AvlUtil$AvlNode;Ljava/lang/Object;Lorg/apache/hadoop/hbase/util/AvlUtil$AvlKeyComparator;Ljava/util/concurrent/atomic/AtomicBoolean;)Lorg/apache/hadoop/hbase/util/AvlUtil$AvlNode;
       7: areturn

  public static <TNode extends org.apache.hadoop.hbase.util.AvlUtil$AvlNode> TNode remove(TNode, java.lang.Object, org.apache.hadoop.hbase.util.AvlUtil$AvlKeyComparator<TNode>, java.util.concurrent.atomic.AtomicBoolean);
    Code:
       0: aload_0
       1: ifnonnull     6
       4: aconst_null
       5: areturn
       6: aload_2
       7: aload_0
       8: aload_1
       9: invokeinterface #2,  3            // InterfaceMethod org/apache/hadoop/hbase/util/AvlUtil$AvlKeyComparator.compareKey:(Lorg/apache/hadoop/hbase/util/AvlUtil$AvlNode;Ljava/lang/Object;)I
      14: istore        4
      16: iload         4
      18: ifne          80
      21: aload_3
      22: ifnull        30
      25: aload_3
      26: iconst_1
      27: invokevirtual #22                 // Method java/util/concurrent/atomic/AtomicBoolean.set:(Z)V
      30: aload_0
      31: getfield      #3                  // Field org/apache/hadoop/hbase/util/AvlUtil$AvlNode.avlLeft:Lorg/apache/hadoop/hbase/util/AvlUtil$AvlNode;
      34: astore        5
      36: aload_0
      37: getfield      #4                  // Field org/apache/hadoop/hbase/util/AvlUtil$AvlNode.avlRight:Lorg/apache/hadoop/hbase/util/AvlUtil$AvlNode;
      40: astore        6
      42: aload         6
      44: ifnonnull     50
      47: aload         5
      49: areturn
      50: aload         6
      52: invokestatic  #23                 // Method getFirst:(Lorg/apache/hadoop/hbase/util/AvlUtil$AvlNode;)Lorg/apache/hadoop/hbase/util/AvlUtil$AvlNode;
      55: astore        7
      57: aload         7
      59: aload         6
      61: invokestatic  #20                 // Method removeMin:(Lorg/apache/hadoop/hbase/util/AvlUtil$AvlNode;)Lorg/apache/hadoop/hbase/util/AvlUtil$AvlNode;
      64: putfield      #4                  // Field org/apache/hadoop/hbase/util/AvlUtil$AvlNode.avlRight:Lorg/apache/hadoop/hbase/util/AvlUtil$AvlNode;
      67: aload         7
      69: aload         5
      71: putfield      #3                  // Field org/apache/hadoop/hbase/util/AvlUtil$AvlNode.avlLeft:Lorg/apache/hadoop/hbase/util/AvlUtil$AvlNode;
      74: aload         7
      76: invokestatic  #16                 // Method balance:(Lorg/apache/hadoop/hbase/util/AvlUtil$AvlNode;)Lorg/apache/hadoop/hbase/util/AvlUtil$AvlNode;
      79: areturn
      80: iload         4
      82: ifle          101
      85: aload_0
      86: aload_0
      87: getfield      #3                  // Field org/apache/hadoop/hbase/util/AvlUtil$AvlNode.avlLeft:Lorg/apache/hadoop/hbase/util/AvlUtil$AvlNode;
      90: aload_1
      91: aload_2
      92: invokestatic  #24                 // Method remove:(Lorg/apache/hadoop/hbase/util/AvlUtil$AvlNode;Ljava/lang/Object;Lorg/apache/hadoop/hbase/util/AvlUtil$AvlKeyComparator;)Lorg/apache/hadoop/hbase/util/AvlUtil$AvlNode;
      95: putfield      #3                  // Field org/apache/hadoop/hbase/util/AvlUtil$AvlNode.avlLeft:Lorg/apache/hadoop/hbase/util/AvlUtil$AvlNode;
      98: goto          114
     101: aload_0
     102: aload_0
     103: getfield      #4                  // Field org/apache/hadoop/hbase/util/AvlUtil$AvlNode.avlRight:Lorg/apache/hadoop/hbase/util/AvlUtil$AvlNode;
     106: aload_1
     107: aload_2
     108: invokestatic  #24                 // Method remove:(Lorg/apache/hadoop/hbase/util/AvlUtil$AvlNode;Ljava/lang/Object;Lorg/apache/hadoop/hbase/util/AvlUtil$AvlKeyComparator;)Lorg/apache/hadoop/hbase/util/AvlUtil$AvlNode;
     111: putfield      #4                  // Field org/apache/hadoop/hbase/util/AvlUtil$AvlNode.avlRight:Lorg/apache/hadoop/hbase/util/AvlUtil$AvlNode;
     114: aload_0
     115: invokestatic  #16                 // Method balance:(Lorg/apache/hadoop/hbase/util/AvlUtil$AvlNode;)Lorg/apache/hadoop/hbase/util/AvlUtil$AvlNode;
     118: areturn

  public static <TNode extends org.apache.hadoop.hbase.util.AvlUtil$AvlNode> void visit(TNode, org.apache.hadoop.hbase.util.AvlUtil$AvlNodeVisitor<TNode>);
    Code:
       0: aload_0
       1: ifnonnull     5
       4: return
       5: new           #25                 // class org/apache/hadoop/hbase/util/AvlUtil$AvlTreeIterator
       8: dup
       9: aload_0
      10: invokespecial #26                 // Method org/apache/hadoop/hbase/util/AvlUtil$AvlTreeIterator."<init>":(Lorg/apache/hadoop/hbase/util/AvlUtil$AvlNode;)V
      13: astore_2
      14: iconst_1
      15: istore_3
      16: iload_3
      17: ifeq          41
      20: aload_2
      21: invokevirtual #27                 // Method org/apache/hadoop/hbase/util/AvlUtil$AvlTreeIterator.hasNext:()Z
      24: ifeq          41
      27: aload_1
      28: aload_2
      29: invokevirtual #28                 // Method org/apache/hadoop/hbase/util/AvlUtil$AvlTreeIterator.next:()Lorg/apache/hadoop/hbase/util/AvlUtil$AvlNode;
      32: invokeinterface #29,  2           // InterfaceMethod org/apache/hadoop/hbase/util/AvlUtil$AvlNodeVisitor.visitNode:(Lorg/apache/hadoop/hbase/util/AvlUtil$AvlNode;)Z
      37: istore_3
      38: goto          16
      41: return

  static {};
    Code:
       0: ldc           #37                 // class org/apache/hadoop/hbase/util/AvlUtil
       2: invokevirtual #38                 // Method java/lang/Class.desiredAssertionStatus:()Z
       5: ifne          12
       8: iconst_1
       9: goto          13
      12: iconst_0
      13: putstatic     #6                  // Field $assertionsDisabled:Z
      16: return
}
