Compiled from "BackupProtos.java"
public final class org.apache.hadoop.hbase.shaded.protobuf.generated.BackupProtos$BackupInfo extends org.apache.hbase.thirdparty.com.google.protobuf.GeneratedMessageV3 implements org.apache.hadoop.hbase.shaded.protobuf.generated.BackupProtos$BackupInfoOrBuilder {
  public static final int BACKUP_ID_FIELD_NUMBER;

  public static final int BACKUP_TYPE_FIELD_NUMBER;

  public static final int BACKUP_ROOT_DIR_FIELD_NUMBER;

  public static final int BACKUP_STATE_FIELD_NUMBER;

  public static final int BACKUP_PHASE_FIELD_NUMBER;

  public static final int FAILED_MESSAGE_FIELD_NUMBER;

  public static final int BACKUP_TABLE_INFO_FIELD_NUMBER;

  public static final int START_TS_FIELD_NUMBER;

  public static final int COMPLETE_TS_FIELD_NUMBER;

  public static final int PROGRESS_FIELD_NUMBER;

  public static final int WORKERS_NUMBER_FIELD_NUMBER;

  public static final int BANDWIDTH_FIELD_NUMBER;

  public static final org.apache.hbase.thirdparty.com.google.protobuf.Parser<org.apache.hadoop.hbase.shaded.protobuf.generated.BackupProtos$BackupInfo> PARSER;

  public final org.apache.hbase.thirdparty.com.google.protobuf.UnknownFieldSet getUnknownFields();
    Code:
       0: aload_0
       1: getfield      #2                  // Field unknownFields:Lorg/apache/hbase/thirdparty/com/google/protobuf/UnknownFieldSet;
       4: areturn

  public static final org.apache.hbase.thirdparty.com.google.protobuf.Descriptors$Descriptor getDescriptor();
    Code:
       0: invokestatic  #49                 // Method org/apache/hadoop/hbase/shaded/protobuf/generated/BackupProtos.access$5400:()Lorg/apache/hbase/thirdparty/com/google/protobuf/Descriptors$Descriptor;
       3: areturn

  protected org.apache.hbase.thirdparty.com.google.protobuf.GeneratedMessageV3$FieldAccessorTable internalGetFieldAccessorTable();
    Code:
       0: invokestatic  #50                 // Method org/apache/hadoop/hbase/shaded/protobuf/generated/BackupProtos.access$5500:()Lorg/apache/hbase/thirdparty/com/google/protobuf/GeneratedMessageV3$FieldAccessorTable;
       3: ldc           #51                 // class org/apache/hadoop/hbase/shaded/protobuf/generated/BackupProtos$BackupInfo
       5: ldc           #52                 // class org/apache/hadoop/hbase/shaded/protobuf/generated/BackupProtos$BackupInfo$Builder
       7: invokevirtual #53                 // Method org/apache/hbase/thirdparty/com/google/protobuf/GeneratedMessageV3$FieldAccessorTable.ensureFieldAccessorsInitialized:(Ljava/lang/Class;Ljava/lang/Class;)Lorg/apache/hbase/thirdparty/com/google/protobuf/GeneratedMessageV3$FieldAccessorTable;
      10: areturn

  public boolean hasBackupId();
    Code:
       0: aload_0
       1: getfield      #4                  // Field bitField0_:I
       4: iconst_1
       5: iand
       6: iconst_1
       7: if_icmpne     14
      10: iconst_1
      11: goto          15
      14: iconst_0
      15: ireturn

  public java.lang.String getBackupId();
    Code:
       0: aload_0
       1: getfield      #16                 // Field backupId_:Ljava/lang/Object;
       4: astore_1
       5: aload_1
       6: instanceof    #54                 // class java/lang/String
       9: ifeq          17
      12: aload_1
      13: checkcast     #54                 // class java/lang/String
      16: areturn
      17: aload_1
      18: checkcast     #55                 // class org/apache/hbase/thirdparty/com/google/protobuf/ByteString
      21: astore_2
      22: aload_2
      23: invokevirtual #56                 // Method org/apache/hbase/thirdparty/com/google/protobuf/ByteString.toStringUtf8:()Ljava/lang/String;
      26: astore_3
      27: aload_2
      28: invokevirtual #57                 // Method org/apache/hbase/thirdparty/com/google/protobuf/ByteString.isValidUtf8:()Z
      31: ifeq          39
      34: aload_0
      35: aload_3
      36: putfield      #16                 // Field backupId_:Ljava/lang/Object;
      39: aload_3
      40: areturn

  public org.apache.hbase.thirdparty.com.google.protobuf.ByteString getBackupIdBytes();
    Code:
       0: aload_0
       1: getfield      #16                 // Field backupId_:Ljava/lang/Object;
       4: astore_1
       5: aload_1
       6: instanceof    #54                 // class java/lang/String
       9: ifeq          27
      12: aload_1
      13: checkcast     #54                 // class java/lang/String
      16: invokestatic  #58                 // Method org/apache/hbase/thirdparty/com/google/protobuf/ByteString.copyFromUtf8:(Ljava/lang/String;)Lorg/apache/hbase/thirdparty/com/google/protobuf/ByteString;
      19: astore_2
      20: aload_0
      21: aload_2
      22: putfield      #16                 // Field backupId_:Ljava/lang/Object;
      25: aload_2
      26: areturn
      27: aload_1
      28: checkcast     #55                 // class org/apache/hbase/thirdparty/com/google/protobuf/ByteString
      31: areturn

  public boolean hasBackupType();
    Code:
       0: aload_0
       1: getfield      #4                  // Field bitField0_:I
       4: iconst_2
       5: iand
       6: iconst_2
       7: if_icmpne     14
      10: iconst_1
      11: goto          15
      14: iconst_0
      15: ireturn

  public org.apache.hadoop.hbase.shaded.protobuf.generated.BackupProtos$BackupType getBackupType();
    Code:
       0: aload_0
       1: getfield      #15                 // Field backupType_:I
       4: invokestatic  #31                 // Method org/apache/hadoop/hbase/shaded/protobuf/generated/BackupProtos$BackupType.valueOf:(I)Lorg/apache/hadoop/hbase/shaded/protobuf/generated/BackupProtos$BackupType;
       7: astore_1
       8: aload_1
       9: ifnonnull     18
      12: getstatic     #59                 // Field org/apache/hadoop/hbase/shaded/protobuf/generated/BackupProtos$BackupType.FULL:Lorg/apache/hadoop/hbase/shaded/protobuf/generated/BackupProtos$BackupType;
      15: goto          19
      18: aload_1
      19: areturn

  public boolean hasBackupRootDir();
    Code:
       0: aload_0
       1: getfield      #4                  // Field bitField0_:I
       4: iconst_4
       5: iand
       6: iconst_4
       7: if_icmpne     14
      10: iconst_1
      11: goto          15
      14: iconst_0
      15: ireturn

  public java.lang.String getBackupRootDir();
    Code:
       0: aload_0
       1: getfield      #14                 // Field backupRootDir_:Ljava/lang/Object;
       4: astore_1
       5: aload_1
       6: instanceof    #54                 // class java/lang/String
       9: ifeq          17
      12: aload_1
      13: checkcast     #54                 // class java/lang/String
      16: areturn
      17: aload_1
      18: checkcast     #55                 // class org/apache/hbase/thirdparty/com/google/protobuf/ByteString
      21: astore_2
      22: aload_2
      23: invokevirtual #56                 // Method org/apache/hbase/thirdparty/com/google/protobuf/ByteString.toStringUtf8:()Ljava/lang/String;
      26: astore_3
      27: aload_2
      28: invokevirtual #57                 // Method org/apache/hbase/thirdparty/com/google/protobuf/ByteString.isValidUtf8:()Z
      31: ifeq          39
      34: aload_0
      35: aload_3
      36: putfield      #14                 // Field backupRootDir_:Ljava/lang/Object;
      39: aload_3
      40: areturn

  public org.apache.hbase.thirdparty.com.google.protobuf.ByteString getBackupRootDirBytes();
    Code:
       0: aload_0
       1: getfield      #14                 // Field backupRootDir_:Ljava/lang/Object;
       4: astore_1
       5: aload_1
       6: instanceof    #54                 // class java/lang/String
       9: ifeq          27
      12: aload_1
      13: checkcast     #54                 // class java/lang/String
      16: invokestatic  #58                 // Method org/apache/hbase/thirdparty/com/google/protobuf/ByteString.copyFromUtf8:(Ljava/lang/String;)Lorg/apache/hbase/thirdparty/com/google/protobuf/ByteString;
      19: astore_2
      20: aload_0
      21: aload_2
      22: putfield      #14                 // Field backupRootDir_:Ljava/lang/Object;
      25: aload_2
      26: areturn
      27: aload_1
      28: checkcast     #55                 // class org/apache/hbase/thirdparty/com/google/protobuf/ByteString
      31: areturn

  public boolean hasBackupState();
    Code:
       0: aload_0
       1: getfield      #4                  // Field bitField0_:I
       4: bipush        8
       6: iand
       7: bipush        8
       9: if_icmpne     16
      12: iconst_1
      13: goto          17
      16: iconst_0
      17: ireturn

  public org.apache.hadoop.hbase.shaded.protobuf.generated.BackupProtos$BackupInfo$BackupState getBackupState();
    Code:
       0: aload_0
       1: getfield      #13                 // Field backupState_:I
       4: invokestatic  #33                 // Method org/apache/hadoop/hbase/shaded/protobuf/generated/BackupProtos$BackupInfo$BackupState.valueOf:(I)Lorg/apache/hadoop/hbase/shaded/protobuf/generated/BackupProtos$BackupInfo$BackupState;
       7: astore_1
       8: aload_1
       9: ifnonnull     18
      12: getstatic     #60                 // Field org/apache/hadoop/hbase/shaded/protobuf/generated/BackupProtos$BackupInfo$BackupState.RUNNING:Lorg/apache/hadoop/hbase/shaded/protobuf/generated/BackupProtos$BackupInfo$BackupState;
      15: goto          19
      18: aload_1
      19: areturn

  public boolean hasBackupPhase();
    Code:
       0: aload_0
       1: getfield      #4                  // Field bitField0_:I
       4: bipush        16
       6: iand
       7: bipush        16
       9: if_icmpne     16
      12: iconst_1
      13: goto          17
      16: iconst_0
      17: ireturn

  public org.apache.hadoop.hbase.shaded.protobuf.generated.BackupProtos$BackupInfo$BackupPhase getBackupPhase();
    Code:
       0: aload_0
       1: getfield      #12                 // Field backupPhase_:I
       4: invokestatic  #34                 // Method org/apache/hadoop/hbase/shaded/protobuf/generated/BackupProtos$BackupInfo$BackupPhase.valueOf:(I)Lorg/apache/hadoop/hbase/shaded/protobuf/generated/BackupProtos$BackupInfo$BackupPhase;
       7: astore_1
       8: aload_1
       9: ifnonnull     18
      12: getstatic     #61                 // Field org/apache/hadoop/hbase/shaded/protobuf/generated/BackupProtos$BackupInfo$BackupPhase.REQUEST:Lorg/apache/hadoop/hbase/shaded/protobuf/generated/BackupProtos$BackupInfo$BackupPhase;
      15: goto          19
      18: aload_1
      19: areturn

  public boolean hasFailedMessage();
    Code:
       0: aload_0
       1: getfield      #4                  // Field bitField0_:I
       4: bipush        32
       6: iand
       7: bipush        32
       9: if_icmpne     16
      12: iconst_1
      13: goto          17
      16: iconst_0
      17: ireturn

  public java.lang.String getFailedMessage();
    Code:
       0: aload_0
       1: getfield      #11                 // Field failedMessage_:Ljava/lang/Object;
       4: astore_1
       5: aload_1
       6: instanceof    #54                 // class java/lang/String
       9: ifeq          17
      12: aload_1
      13: checkcast     #54                 // class java/lang/String
      16: areturn
      17: aload_1
      18: checkcast     #55                 // class org/apache/hbase/thirdparty/com/google/protobuf/ByteString
      21: astore_2
      22: aload_2
      23: invokevirtual #56                 // Method org/apache/hbase/thirdparty/com/google/protobuf/ByteString.toStringUtf8:()Ljava/lang/String;
      26: astore_3
      27: aload_2
      28: invokevirtual #57                 // Method org/apache/hbase/thirdparty/com/google/protobuf/ByteString.isValidUtf8:()Z
      31: ifeq          39
      34: aload_0
      35: aload_3
      36: putfield      #11                 // Field failedMessage_:Ljava/lang/Object;
      39: aload_3
      40: areturn

  public org.apache.hbase.thirdparty.com.google.protobuf.ByteString getFailedMessageBytes();
    Code:
       0: aload_0
       1: getfield      #11                 // Field failedMessage_:Ljava/lang/Object;
       4: astore_1
       5: aload_1
       6: instanceof    #54                 // class java/lang/String
       9: ifeq          27
      12: aload_1
      13: checkcast     #54                 // class java/lang/String
      16: invokestatic  #58                 // Method org/apache/hbase/thirdparty/com/google/protobuf/ByteString.copyFromUtf8:(Ljava/lang/String;)Lorg/apache/hbase/thirdparty/com/google/protobuf/ByteString;
      19: astore_2
      20: aload_0
      21: aload_2
      22: putfield      #11                 // Field failedMessage_:Ljava/lang/Object;
      25: aload_2
      26: areturn
      27: aload_1
      28: checkcast     #55                 // class org/apache/hbase/thirdparty/com/google/protobuf/ByteString
      31: areturn

  public java.util.List<org.apache.hadoop.hbase.shaded.protobuf.generated.BackupProtos$BackupTableInfo> getBackupTableInfoList();
    Code:
       0: aload_0
       1: getfield      #10                 // Field backupTableInfo_:Ljava/util/List;
       4: areturn

  public java.util.List<? extends org.apache.hadoop.hbase.shaded.protobuf.generated.BackupProtos$BackupTableInfoOrBuilder> getBackupTableInfoOrBuilderList();
    Code:
       0: aload_0
       1: getfield      #10                 // Field backupTableInfo_:Ljava/util/List;
       4: areturn

  public int getBackupTableInfoCount();
    Code:
       0: aload_0
       1: getfield      #10                 // Field backupTableInfo_:Ljava/util/List;
       4: invokeinterface #62,  1           // InterfaceMethod java/util/List.size:()I
       9: ireturn

  public org.apache.hadoop.hbase.shaded.protobuf.generated.BackupProtos$BackupTableInfo getBackupTableInfo(int);
    Code:
       0: aload_0
       1: getfield      #10                 // Field backupTableInfo_:Ljava/util/List;
       4: iload_1
       5: invokeinterface #63,  2           // InterfaceMethod java/util/List.get:(I)Ljava/lang/Object;
      10: checkcast     #64                 // class org/apache/hadoop/hbase/shaded/protobuf/generated/BackupProtos$BackupTableInfo
      13: areturn

  public org.apache.hadoop.hbase.shaded.protobuf.generated.BackupProtos$BackupTableInfoOrBuilder getBackupTableInfoOrBuilder(int);
    Code:
       0: aload_0
       1: getfield      #10                 // Field backupTableInfo_:Ljava/util/List;
       4: iload_1
       5: invokeinterface #63,  2           // InterfaceMethod java/util/List.get:(I)Ljava/lang/Object;
      10: checkcast     #65                 // class org/apache/hadoop/hbase/shaded/protobuf/generated/BackupProtos$BackupTableInfoOrBuilder
      13: areturn

  public boolean hasStartTs();
    Code:
       0: aload_0
       1: getfield      #4                  // Field bitField0_:I
       4: bipush        64
       6: iand
       7: bipush        64
       9: if_icmpne     16
      12: iconst_1
      13: goto          17
      16: iconst_0
      17: ireturn

  public long getStartTs();
    Code:
       0: aload_0
       1: getfield      #9                  // Field startTs_:J
       4: lreturn

  public boolean hasCompleteTs();
    Code:
       0: aload_0
       1: getfield      #4                  // Field bitField0_:I
       4: sipush        128
       7: iand
       8: sipush        128
      11: if_icmpne     18
      14: iconst_1
      15: goto          19
      18: iconst_0
      19: ireturn

  public long getCompleteTs();
    Code:
       0: aload_0
       1: getfield      #8                  // Field completeTs_:J
       4: lreturn

  public boolean hasProgress();
    Code:
       0: aload_0
       1: getfield      #4                  // Field bitField0_:I
       4: sipush        256
       7: iand
       8: sipush        256
      11: if_icmpne     18
      14: iconst_1
      15: goto          19
      18: iconst_0
      19: ireturn

  public int getProgress();
    Code:
       0: aload_0
       1: getfield      #7                  // Field progress_:I
       4: ireturn

  public boolean hasWorkersNumber();
    Code:
       0: aload_0
       1: getfield      #4                  // Field bitField0_:I
       4: sipush        512
       7: iand
       8: sipush        512
      11: if_icmpne     18
      14: iconst_1
      15: goto          19
      18: iconst_0
      19: ireturn

  public int getWorkersNumber();
    Code:
       0: aload_0
       1: getfield      #6                  // Field workersNumber_:I
       4: ireturn

  public boolean hasBandwidth();
    Code:
       0: aload_0
       1: getfield      #4                  // Field bitField0_:I
       4: sipush        1024
       7: iand
       8: sipush        1024
      11: if_icmpne     18
      14: iconst_1
      15: goto          19
      18: iconst_0
      19: ireturn

  public long getBandwidth();
    Code:
       0: aload_0
       1: getfield      #5                  // Field bandwidth_:J
       4: lreturn

  public final boolean isInitialized();
    Code:
       0: aload_0
       1: getfield      #19                 // Field memoizedIsInitialized:B
       4: istore_1
       5: iload_1
       6: iconst_1
       7: if_icmpne     12
      10: iconst_1
      11: ireturn
      12: iload_1
      13: ifne          18
      16: iconst_0
      17: ireturn
      18: iconst_0
      19: istore_2
      20: iload_2
      21: aload_0
      22: invokevirtual #66                 // Method getBackupTableInfoCount:()I
      25: if_icmpge     52
      28: aload_0
      29: iload_2
      30: invokevirtual #67                 // Method getBackupTableInfo:(I)Lorg/apache/hadoop/hbase/shaded/protobuf/generated/BackupProtos$BackupTableInfo;
      33: invokevirtual #68                 // Method org/apache/hadoop/hbase/shaded/protobuf/generated/BackupProtos$BackupTableInfo.isInitialized:()Z
      36: ifne          46
      39: aload_0
      40: iconst_0
      41: putfield      #19                 // Field memoizedIsInitialized:B
      44: iconst_0
      45: ireturn
      46: iinc          2, 1
      49: goto          20
      52: aload_0
      53: iconst_1
      54: putfield      #19                 // Field memoizedIsInitialized:B
      57: iconst_1
      58: ireturn

  public void writeTo(org.apache.hbase.thirdparty.com.google.protobuf.CodedOutputStream) throws java.io.IOException;
    Code:
       0: aload_0
       1: getfield      #4                  // Field bitField0_:I
       4: iconst_1
       5: iand
       6: iconst_1
       7: if_icmpne     19
      10: aload_1
      11: iconst_1
      12: aload_0
      13: getfield      #16                 // Field backupId_:Ljava/lang/Object;
      16: invokestatic  #69                 // Method org/apache/hbase/thirdparty/com/google/protobuf/GeneratedMessageV3.writeString:(Lorg/apache/hbase/thirdparty/com/google/protobuf/CodedOutputStream;ILjava/lang/Object;)V
      19: aload_0
      20: getfield      #4                  // Field bitField0_:I
      23: iconst_2
      24: iand
      25: iconst_2
      26: if_icmpne     38
      29: aload_1
      30: iconst_2
      31: aload_0
      32: getfield      #15                 // Field backupType_:I
      35: invokevirtual #70                 // Method org/apache/hbase/thirdparty/com/google/protobuf/CodedOutputStream.writeEnum:(II)V
      38: aload_0
      39: getfield      #4                  // Field bitField0_:I
      42: iconst_4
      43: iand
      44: iconst_4
      45: if_icmpne     57
      48: aload_1
      49: iconst_3
      50: aload_0
      51: getfield      #14                 // Field backupRootDir_:Ljava/lang/Object;
      54: invokestatic  #69                 // Method org/apache/hbase/thirdparty/com/google/protobuf/GeneratedMessageV3.writeString:(Lorg/apache/hbase/thirdparty/com/google/protobuf/CodedOutputStream;ILjava/lang/Object;)V
      57: aload_0
      58: getfield      #4                  // Field bitField0_:I
      61: bipush        8
      63: iand
      64: bipush        8
      66: if_icmpne     78
      69: aload_1
      70: iconst_4
      71: aload_0
      72: getfield      #13                 // Field backupState_:I
      75: invokevirtual #70                 // Method org/apache/hbase/thirdparty/com/google/protobuf/CodedOutputStream.writeEnum:(II)V
      78: aload_0
      79: getfield      #4                  // Field bitField0_:I
      82: bipush        16
      84: iand
      85: bipush        16
      87: if_icmpne     99
      90: aload_1
      91: iconst_5
      92: aload_0
      93: getfield      #12                 // Field backupPhase_:I
      96: invokevirtual #70                 // Method org/apache/hbase/thirdparty/com/google/protobuf/CodedOutputStream.writeEnum:(II)V
      99: aload_0
     100: getfield      #4                  // Field bitField0_:I
     103: bipush        32
     105: iand
     106: bipush        32
     108: if_icmpne     121
     111: aload_1
     112: bipush        6
     114: aload_0
     115: getfield      #11                 // Field failedMessage_:Ljava/lang/Object;
     118: invokestatic  #69                 // Method org/apache/hbase/thirdparty/com/google/protobuf/GeneratedMessageV3.writeString:(Lorg/apache/hbase/thirdparty/com/google/protobuf/CodedOutputStream;ILjava/lang/Object;)V
     121: iconst_0
     122: istore_2
     123: iload_2
     124: aload_0
     125: getfield      #10                 // Field backupTableInfo_:Ljava/util/List;
     128: invokeinterface #62,  1           // InterfaceMethod java/util/List.size:()I
     133: if_icmpge     161
     136: aload_1
     137: bipush        7
     139: aload_0
     140: getfield      #10                 // Field backupTableInfo_:Ljava/util/List;
     143: iload_2
     144: invokeinterface #63,  2           // InterfaceMethod java/util/List.get:(I)Ljava/lang/Object;
     149: checkcast     #71                 // class org/apache/hbase/thirdparty/com/google/protobuf/MessageLite
     152: invokevirtual #72                 // Method org/apache/hbase/thirdparty/com/google/protobuf/CodedOutputStream.writeMessage:(ILorg/apache/hbase/thirdparty/com/google/protobuf/MessageLite;)V
     155: iinc          2, 1
     158: goto          123
     161: aload_0
     162: getfield      #4                  // Field bitField0_:I
     165: bipush        64
     167: iand
     168: bipush        64
     170: if_icmpne     183
     173: aload_1
     174: bipush        8
     176: aload_0
     177: getfield      #9                  // Field startTs_:J
     180: invokevirtual #73                 // Method org/apache/hbase/thirdparty/com/google/protobuf/CodedOutputStream.writeUInt64:(IJ)V
     183: aload_0
     184: getfield      #4                  // Field bitField0_:I
     187: sipush        128
     190: iand
     191: sipush        128
     194: if_icmpne     207
     197: aload_1
     198: bipush        9
     200: aload_0
     201: getfield      #8                  // Field completeTs_:J
     204: invokevirtual #73                 // Method org/apache/hbase/thirdparty/com/google/protobuf/CodedOutputStream.writeUInt64:(IJ)V
     207: aload_0
     208: getfield      #4                  // Field bitField0_:I
     211: sipush        256
     214: iand
     215: sipush        256
     218: if_icmpne     231
     221: aload_1
     222: bipush        10
     224: aload_0
     225: getfield      #7                  // Field progress_:I
     228: invokevirtual #74                 // Method org/apache/hbase/thirdparty/com/google/protobuf/CodedOutputStream.writeUInt32:(II)V
     231: aload_0
     232: getfield      #4                  // Field bitField0_:I
     235: sipush        512
     238: iand
     239: sipush        512
     242: if_icmpne     255
     245: aload_1
     246: bipush        11
     248: aload_0
     249: getfield      #6                  // Field workersNumber_:I
     252: invokevirtual #74                 // Method org/apache/hbase/thirdparty/com/google/protobuf/CodedOutputStream.writeUInt32:(II)V
     255: aload_0
     256: getfield      #4                  // Field bitField0_:I
     259: sipush        1024
     262: iand
     263: sipush        1024
     266: if_icmpne     279
     269: aload_1
     270: bipush        12
     272: aload_0
     273: getfield      #5                  // Field bandwidth_:J
     276: invokevirtual #73                 // Method org/apache/hbase/thirdparty/com/google/protobuf/CodedOutputStream.writeUInt64:(IJ)V
     279: aload_0
     280: getfield      #2                  // Field unknownFields:Lorg/apache/hbase/thirdparty/com/google/protobuf/UnknownFieldSet;
     283: aload_1
     284: invokevirtual #75                 // Method org/apache/hbase/thirdparty/com/google/protobuf/UnknownFieldSet.writeTo:(Lorg/apache/hbase/thirdparty/com/google/protobuf/CodedOutputStream;)V
     287: return

  public int getSerializedSize();
    Code:
       0: aload_0
       1: getfield      #76                 // Field memoizedSize:I
       4: istore_1
       5: iload_1
       6: iconst_m1
       7: if_icmpeq     12
      10: iload_1
      11: ireturn
      12: iconst_0
      13: istore_1
      14: aload_0
      15: getfield      #4                  // Field bitField0_:I
      18: iconst_1
      19: iand
      20: iconst_1
      21: if_icmpne     35
      24: iload_1
      25: iconst_1
      26: aload_0
      27: getfield      #16                 // Field backupId_:Ljava/lang/Object;
      30: invokestatic  #77                 // Method org/apache/hbase/thirdparty/com/google/protobuf/GeneratedMessageV3.computeStringSize:(ILjava/lang/Object;)I
      33: iadd
      34: istore_1
      35: aload_0
      36: getfield      #4                  // Field bitField0_:I
      39: iconst_2
      40: iand
      41: iconst_2
      42: if_icmpne     56
      45: iload_1
      46: iconst_2
      47: aload_0
      48: getfield      #15                 // Field backupType_:I
      51: invokestatic  #78                 // Method org/apache/hbase/thirdparty/com/google/protobuf/CodedOutputStream.computeEnumSize:(II)I
      54: iadd
      55: istore_1
      56: aload_0
      57: getfield      #4                  // Field bitField0_:I
      60: iconst_4
      61: iand
      62: iconst_4
      63: if_icmpne     77
      66: iload_1
      67: iconst_3
      68: aload_0
      69: getfield      #14                 // Field backupRootDir_:Ljava/lang/Object;
      72: invokestatic  #77                 // Method org/apache/hbase/thirdparty/com/google/protobuf/GeneratedMessageV3.computeStringSize:(ILjava/lang/Object;)I
      75: iadd
      76: istore_1
      77: aload_0
      78: getfield      #4                  // Field bitField0_:I
      81: bipush        8
      83: iand
      84: bipush        8
      86: if_icmpne     100
      89: iload_1
      90: iconst_4
      91: aload_0
      92: getfield      #13                 // Field backupState_:I
      95: invokestatic  #78                 // Method org/apache/hbase/thirdparty/com/google/protobuf/CodedOutputStream.computeEnumSize:(II)I
      98: iadd
      99: istore_1
     100: aload_0
     101: getfield      #4                  // Field bitField0_:I
     104: bipush        16
     106: iand
     107: bipush        16
     109: if_icmpne     123
     112: iload_1
     113: iconst_5
     114: aload_0
     115: getfield      #12                 // Field backupPhase_:I
     118: invokestatic  #78                 // Method org/apache/hbase/thirdparty/com/google/protobuf/CodedOutputStream.computeEnumSize:(II)I
     121: iadd
     122: istore_1
     123: aload_0
     124: getfield      #4                  // Field bitField0_:I
     127: bipush        32
     129: iand
     130: bipush        32
     132: if_icmpne     147
     135: iload_1
     136: bipush        6
     138: aload_0
     139: getfield      #11                 // Field failedMessage_:Ljava/lang/Object;
     142: invokestatic  #77                 // Method org/apache/hbase/thirdparty/com/google/protobuf/GeneratedMessageV3.computeStringSize:(ILjava/lang/Object;)I
     145: iadd
     146: istore_1
     147: iconst_0
     148: istore_2
     149: iload_2
     150: aload_0
     151: getfield      #10                 // Field backupTableInfo_:Ljava/util/List;
     154: invokeinterface #62,  1           // InterfaceMethod java/util/List.size:()I
     159: if_icmpge     189
     162: iload_1
     163: bipush        7
     165: aload_0
     166: getfield      #10                 // Field backupTableInfo_:Ljava/util/List;
     169: iload_2
     170: invokeinterface #63,  2           // InterfaceMethod java/util/List.get:(I)Ljava/lang/Object;
     175: checkcast     #71                 // class org/apache/hbase/thirdparty/com/google/protobuf/MessageLite
     178: invokestatic  #79                 // Method org/apache/hbase/thirdparty/com/google/protobuf/CodedOutputStream.computeMessageSize:(ILorg/apache/hbase/thirdparty/com/google/protobuf/MessageLite;)I
     181: iadd
     182: istore_1
     183: iinc          2, 1
     186: goto          149
     189: aload_0
     190: getfield      #4                  // Field bitField0_:I
     193: bipush        64
     195: iand
     196: bipush        64
     198: if_icmpne     213
     201: iload_1
     202: bipush        8
     204: aload_0
     205: getfield      #9                  // Field startTs_:J
     208: invokestatic  #80                 // Method org/apache/hbase/thirdparty/com/google/protobuf/CodedOutputStream.computeUInt64Size:(IJ)I
     211: iadd
     212: istore_1
     213: aload_0
     214: getfield      #4                  // Field bitField0_:I
     217: sipush        128
     220: iand
     221: sipush        128
     224: if_icmpne     239
     227: iload_1
     228: bipush        9
     230: aload_0
     231: getfield      #8                  // Field completeTs_:J
     234: invokestatic  #80                 // Method org/apache/hbase/thirdparty/com/google/protobuf/CodedOutputStream.computeUInt64Size:(IJ)I
     237: iadd
     238: istore_1
     239: aload_0
     240: getfield      #4                  // Field bitField0_:I
     243: sipush        256
     246: iand
     247: sipush        256
     250: if_icmpne     265
     253: iload_1
     254: bipush        10
     256: aload_0
     257: getfield      #7                  // Field progress_:I
     260: invokestatic  #81                 // Method org/apache/hbase/thirdparty/com/google/protobuf/CodedOutputStream.computeUInt32Size:(II)I
     263: iadd
     264: istore_1
     265: aload_0
     266: getfield      #4                  // Field bitField0_:I
     269: sipush        512
     272: iand
     273: sipush        512
     276: if_icmpne     291
     279: iload_1
     280: bipush        11
     282: aload_0
     283: getfield      #6                  // Field workersNumber_:I
     286: invokestatic  #81                 // Method org/apache/hbase/thirdparty/com/google/protobuf/CodedOutputStream.computeUInt32Size:(II)I
     289: iadd
     290: istore_1
     291: aload_0
     292: getfield      #4                  // Field bitField0_:I
     295: sipush        1024
     298: iand
     299: sipush        1024
     302: if_icmpne     317
     305: iload_1
     306: bipush        12
     308: aload_0
     309: getfield      #5                  // Field bandwidth_:J
     312: invokestatic  #80                 // Method org/apache/hbase/thirdparty/com/google/protobuf/CodedOutputStream.computeUInt64Size:(IJ)I
     315: iadd
     316: istore_1
     317: iload_1
     318: aload_0
     319: getfield      #2                  // Field unknownFields:Lorg/apache/hbase/thirdparty/com/google/protobuf/UnknownFieldSet;
     322: invokevirtual #82                 // Method org/apache/hbase/thirdparty/com/google/protobuf/UnknownFieldSet.getSerializedSize:()I
     325: iadd
     326: istore_1
     327: aload_0
     328: iload_1
     329: putfield      #76                 // Field memoizedSize:I
     332: iload_1
     333: ireturn

  public boolean equals(java.lang.Object);
    Code:
       0: aload_1
       1: aload_0
       2: if_acmpne     7
       5: iconst_1
       6: ireturn
       7: aload_1
       8: instanceof    #51                 // class org/apache/hadoop/hbase/shaded/protobuf/generated/BackupProtos$BackupInfo
      11: ifne          20
      14: aload_0
      15: aload_1
      16: invokespecial #83                 // Method org/apache/hbase/thirdparty/com/google/protobuf/GeneratedMessageV3.equals:(Ljava/lang/Object;)Z
      19: ireturn
      20: aload_1
      21: checkcast     #51                 // class org/apache/hadoop/hbase/shaded/protobuf/generated/BackupProtos$BackupInfo
      24: astore_2
      25: iconst_1
      26: istore_3
      27: iload_3
      28: ifeq          46
      31: aload_0
      32: invokevirtual #84                 // Method hasBackupId:()Z
      35: aload_2
      36: invokevirtual #84                 // Method hasBackupId:()Z
      39: if_icmpne     46
      42: iconst_1
      43: goto          47
      46: iconst_0
      47: istore_3
      48: aload_0
      49: invokevirtual #84                 // Method hasBackupId:()Z
      52: ifeq          79
      55: iload_3
      56: ifeq          77
      59: aload_0
      60: invokevirtual #85                 // Method getBackupId:()Ljava/lang/String;
      63: aload_2
      64: invokevirtual #85                 // Method getBackupId:()Ljava/lang/String;
      67: invokevirtual #86                 // Method java/lang/String.equals:(Ljava/lang/Object;)Z
      70: ifeq          77
      73: iconst_1
      74: goto          78
      77: iconst_0
      78: istore_3
      79: iload_3
      80: ifeq          98
      83: aload_0
      84: invokevirtual #87                 // Method hasBackupType:()Z
      87: aload_2
      88: invokevirtual #87                 // Method hasBackupType:()Z
      91: if_icmpne     98
      94: iconst_1
      95: goto          99
      98: iconst_0
      99: istore_3
     100: aload_0
     101: invokevirtual #87                 // Method hasBackupType:()Z
     104: ifeq          128
     107: iload_3
     108: ifeq          126
     111: aload_0
     112: getfield      #15                 // Field backupType_:I
     115: aload_2
     116: getfield      #15                 // Field backupType_:I
     119: if_icmpne     126
     122: iconst_1
     123: goto          127
     126: iconst_0
     127: istore_3
     128: iload_3
     129: ifeq          147
     132: aload_0
     133: invokevirtual #88                 // Method hasBackupRootDir:()Z
     136: aload_2
     137: invokevirtual #88                 // Method hasBackupRootDir:()Z
     140: if_icmpne     147
     143: iconst_1
     144: goto          148
     147: iconst_0
     148: istore_3
     149: aload_0
     150: invokevirtual #88                 // Method hasBackupRootDir:()Z
     153: ifeq          180
     156: iload_3
     157: ifeq          178
     160: aload_0
     161: invokevirtual #89                 // Method getBackupRootDir:()Ljava/lang/String;
     164: aload_2
     165: invokevirtual #89                 // Method getBackupRootDir:()Ljava/lang/String;
     168: invokevirtual #86                 // Method java/lang/String.equals:(Ljava/lang/Object;)Z
     171: ifeq          178
     174: iconst_1
     175: goto          179
     178: iconst_0
     179: istore_3
     180: iload_3
     181: ifeq          199
     184: aload_0
     185: invokevirtual #90                 // Method hasBackupState:()Z
     188: aload_2
     189: invokevirtual #90                 // Method hasBackupState:()Z
     192: if_icmpne     199
     195: iconst_1
     196: goto          200
     199: iconst_0
     200: istore_3
     201: aload_0
     202: invokevirtual #90                 // Method hasBackupState:()Z
     205: ifeq          229
     208: iload_3
     209: ifeq          227
     212: aload_0
     213: getfield      #13                 // Field backupState_:I
     216: aload_2
     217: getfield      #13                 // Field backupState_:I
     220: if_icmpne     227
     223: iconst_1
     224: goto          228
     227: iconst_0
     228: istore_3
     229: iload_3
     230: ifeq          248
     233: aload_0
     234: invokevirtual #91                 // Method hasBackupPhase:()Z
     237: aload_2
     238: invokevirtual #91                 // Method hasBackupPhase:()Z
     241: if_icmpne     248
     244: iconst_1
     245: goto          249
     248: iconst_0
     249: istore_3
     250: aload_0
     251: invokevirtual #91                 // Method hasBackupPhase:()Z
     254: ifeq          278
     257: iload_3
     258: ifeq          276
     261: aload_0
     262: getfield      #12                 // Field backupPhase_:I
     265: aload_2
     266: getfield      #12                 // Field backupPhase_:I
     269: if_icmpne     276
     272: iconst_1
     273: goto          277
     276: iconst_0
     277: istore_3
     278: iload_3
     279: ifeq          297
     282: aload_0
     283: invokevirtual #92                 // Method hasFailedMessage:()Z
     286: aload_2
     287: invokevirtual #92                 // Method hasFailedMessage:()Z
     290: if_icmpne     297
     293: iconst_1
     294: goto          298
     297: iconst_0
     298: istore_3
     299: aload_0
     300: invokevirtual #92                 // Method hasFailedMessage:()Z
     303: ifeq          330
     306: iload_3
     307: ifeq          328
     310: aload_0
     311: invokevirtual #93                 // Method getFailedMessage:()Ljava/lang/String;
     314: aload_2
     315: invokevirtual #93                 // Method getFailedMessage:()Ljava/lang/String;
     318: invokevirtual #86                 // Method java/lang/String.equals:(Ljava/lang/Object;)Z
     321: ifeq          328
     324: iconst_1
     325: goto          329
     328: iconst_0
     329: istore_3
     330: iload_3
     331: ifeq          354
     334: aload_0
     335: invokevirtual #94                 // Method getBackupTableInfoList:()Ljava/util/List;
     338: aload_2
     339: invokevirtual #94                 // Method getBackupTableInfoList:()Ljava/util/List;
     342: invokeinterface #95,  2           // InterfaceMethod java/util/List.equals:(Ljava/lang/Object;)Z
     347: ifeq          354
     350: iconst_1
     351: goto          355
     354: iconst_0
     355: istore_3
     356: iload_3
     357: ifeq          375
     360: aload_0
     361: invokevirtual #96                 // Method hasStartTs:()Z
     364: aload_2
     365: invokevirtual #96                 // Method hasStartTs:()Z
     368: if_icmpne     375
     371: iconst_1
     372: goto          376
     375: iconst_0
     376: istore_3
     377: aload_0
     378: invokevirtual #96                 // Method hasStartTs:()Z
     381: ifeq          406
     384: iload_3
     385: ifeq          404
     388: aload_0
     389: invokevirtual #97                 // Method getStartTs:()J
     392: aload_2
     393: invokevirtual #97                 // Method getStartTs:()J
     396: lcmp
     397: ifne          404
     400: iconst_1
     401: goto          405
     404: iconst_0
     405: istore_3
     406: iload_3
     407: ifeq          425
     410: aload_0
     411: invokevirtual #98                 // Method hasCompleteTs:()Z
     414: aload_2
     415: invokevirtual #98                 // Method hasCompleteTs:()Z
     418: if_icmpne     425
     421: iconst_1
     422: goto          426
     425: iconst_0
     426: istore_3
     427: aload_0
     428: invokevirtual #98                 // Method hasCompleteTs:()Z
     431: ifeq          456
     434: iload_3
     435: ifeq          454
     438: aload_0
     439: invokevirtual #99                 // Method getCompleteTs:()J
     442: aload_2
     443: invokevirtual #99                 // Method getCompleteTs:()J
     446: lcmp
     447: ifne          454
     450: iconst_1
     451: goto          455
     454: iconst_0
     455: istore_3
     456: iload_3
     457: ifeq          475
     460: aload_0
     461: invokevirtual #100                // Method hasProgress:()Z
     464: aload_2
     465: invokevirtual #100                // Method hasProgress:()Z
     468: if_icmpne     475
     471: iconst_1
     472: goto          476
     475: iconst_0
     476: istore_3
     477: aload_0
     478: invokevirtual #100                // Method hasProgress:()Z
     481: ifeq          505
     484: iload_3
     485: ifeq          503
     488: aload_0
     489: invokevirtual #101                // Method getProgress:()I
     492: aload_2
     493: invokevirtual #101                // Method getProgress:()I
     496: if_icmpne     503
     499: iconst_1
     500: goto          504
     503: iconst_0
     504: istore_3
     505: iload_3
     506: ifeq          524
     509: aload_0
     510: invokevirtual #102                // Method hasWorkersNumber:()Z
     513: aload_2
     514: invokevirtual #102                // Method hasWorkersNumber:()Z
     517: if_icmpne     524
     520: iconst_1
     521: goto          525
     524: iconst_0
     525: istore_3
     526: aload_0
     527: invokevirtual #102                // Method hasWorkersNumber:()Z
     530: ifeq          554
     533: iload_3
     534: ifeq          552
     537: aload_0
     538: invokevirtual #103                // Method getWorkersNumber:()I
     541: aload_2
     542: invokevirtual #103                // Method getWorkersNumber:()I
     545: if_icmpne     552
     548: iconst_1
     549: goto          553
     552: iconst_0
     553: istore_3
     554: iload_3
     555: ifeq          573
     558: aload_0
     559: invokevirtual #104                // Method hasBandwidth:()Z
     562: aload_2
     563: invokevirtual #104                // Method hasBandwidth:()Z
     566: if_icmpne     573
     569: iconst_1
     570: goto          574
     573: iconst_0
     574: istore_3
     575: aload_0
     576: invokevirtual #104                // Method hasBandwidth:()Z
     579: ifeq          604
     582: iload_3
     583: ifeq          602
     586: aload_0
     587: invokevirtual #105                // Method getBandwidth:()J
     590: aload_2
     591: invokevirtual #105                // Method getBandwidth:()J
     594: lcmp
     595: ifne          602
     598: iconst_1
     599: goto          603
     602: iconst_0
     603: istore_3
     604: iload_3
     605: ifeq          626
     608: aload_0
     609: getfield      #2                  // Field unknownFields:Lorg/apache/hbase/thirdparty/com/google/protobuf/UnknownFieldSet;
     612: aload_2
     613: getfield      #2                  // Field unknownFields:Lorg/apache/hbase/thirdparty/com/google/protobuf/UnknownFieldSet;
     616: invokevirtual #106                // Method org/apache/hbase/thirdparty/com/google/protobuf/UnknownFieldSet.equals:(Ljava/lang/Object;)Z
     619: ifeq          626
     622: iconst_1
     623: goto          627
     626: iconst_0
     627: istore_3
     628: iload_3
     629: ireturn

  public int hashCode();
    Code:
       0: aload_0
       1: getfield      #107                // Field memoizedHashCode:I
       4: ifeq          12
       7: aload_0
       8: getfield      #107                // Field memoizedHashCode:I
      11: ireturn
      12: bipush        41
      14: istore_1
      15: bipush        19
      17: iload_1
      18: imul
      19: invokestatic  #108                // Method getDescriptor:()Lorg/apache/hbase/thirdparty/com/google/protobuf/Descriptors$Descriptor;
      22: invokevirtual #109                // Method java/lang/Object.hashCode:()I
      25: iadd
      26: istore_1
      27: aload_0
      28: invokevirtual #84                 // Method hasBackupId:()Z
      31: ifeq          54
      34: bipush        37
      36: iload_1
      37: imul
      38: iconst_1
      39: iadd
      40: istore_1
      41: bipush        53
      43: iload_1
      44: imul
      45: aload_0
      46: invokevirtual #85                 // Method getBackupId:()Ljava/lang/String;
      49: invokevirtual #110                // Method java/lang/String.hashCode:()I
      52: iadd
      53: istore_1
      54: aload_0
      55: invokevirtual #87                 // Method hasBackupType:()Z
      58: ifeq          78
      61: bipush        37
      63: iload_1
      64: imul
      65: iconst_2
      66: iadd
      67: istore_1
      68: bipush        53
      70: iload_1
      71: imul
      72: aload_0
      73: getfield      #15                 // Field backupType_:I
      76: iadd
      77: istore_1
      78: aload_0
      79: invokevirtual #88                 // Method hasBackupRootDir:()Z
      82: ifeq          105
      85: bipush        37
      87: iload_1
      88: imul
      89: iconst_3
      90: iadd
      91: istore_1
      92: bipush        53
      94: iload_1
      95: imul
      96: aload_0
      97: invokevirtual #89                 // Method getBackupRootDir:()Ljava/lang/String;
     100: invokevirtual #110                // Method java/lang/String.hashCode:()I
     103: iadd
     104: istore_1
     105: aload_0
     106: invokevirtual #90                 // Method hasBackupState:()Z
     109: ifeq          129
     112: bipush        37
     114: iload_1
     115: imul
     116: iconst_4
     117: iadd
     118: istore_1
     119: bipush        53
     121: iload_1
     122: imul
     123: aload_0
     124: getfield      #13                 // Field backupState_:I
     127: iadd
     128: istore_1
     129: aload_0
     130: invokevirtual #91                 // Method hasBackupPhase:()Z
     133: ifeq          153
     136: bipush        37
     138: iload_1
     139: imul
     140: iconst_5
     141: iadd
     142: istore_1
     143: bipush        53
     145: iload_1
     146: imul
     147: aload_0
     148: getfield      #12                 // Field backupPhase_:I
     151: iadd
     152: istore_1
     153: aload_0
     154: invokevirtual #92                 // Method hasFailedMessage:()Z
     157: ifeq          181
     160: bipush        37
     162: iload_1
     163: imul
     164: bipush        6
     166: iadd
     167: istore_1
     168: bipush        53
     170: iload_1
     171: imul
     172: aload_0
     173: invokevirtual #93                 // Method getFailedMessage:()Ljava/lang/String;
     176: invokevirtual #110                // Method java/lang/String.hashCode:()I
     179: iadd
     180: istore_1
     181: aload_0
     182: invokevirtual #66                 // Method getBackupTableInfoCount:()I
     185: ifle          211
     188: bipush        37
     190: iload_1
     191: imul
     192: bipush        7
     194: iadd
     195: istore_1
     196: bipush        53
     198: iload_1
     199: imul
     200: aload_0
     201: invokevirtual #94                 // Method getBackupTableInfoList:()Ljava/util/List;
     204: invokeinterface #111,  1          // InterfaceMethod java/util/List.hashCode:()I
     209: iadd
     210: istore_1
     211: aload_0
     212: invokevirtual #96                 // Method hasStartTs:()Z
     215: ifeq          239
     218: bipush        37
     220: iload_1
     221: imul
     222: bipush        8
     224: iadd
     225: istore_1
     226: bipush        53
     228: iload_1
     229: imul
     230: aload_0
     231: invokevirtual #97                 // Method getStartTs:()J
     234: invokestatic  #112                // Method org/apache/hbase/thirdparty/com/google/protobuf/Internal.hashLong:(J)I
     237: iadd
     238: istore_1
     239: aload_0
     240: invokevirtual #98                 // Method hasCompleteTs:()Z
     243: ifeq          267
     246: bipush        37
     248: iload_1
     249: imul
     250: bipush        9
     252: iadd
     253: istore_1
     254: bipush        53
     256: iload_1
     257: imul
     258: aload_0
     259: invokevirtual #99                 // Method getCompleteTs:()J
     262: invokestatic  #112                // Method org/apache/hbase/thirdparty/com/google/protobuf/Internal.hashLong:(J)I
     265: iadd
     266: istore_1
     267: aload_0
     268: invokevirtual #100                // Method hasProgress:()Z
     271: ifeq          292
     274: bipush        37
     276: iload_1
     277: imul
     278: bipush        10
     280: iadd
     281: istore_1
     282: bipush        53
     284: iload_1
     285: imul
     286: aload_0
     287: invokevirtual #101                // Method getProgress:()I
     290: iadd
     291: istore_1
     292: aload_0
     293: invokevirtual #102                // Method hasWorkersNumber:()Z
     296: ifeq          317
     299: bipush        37
     301: iload_1
     302: imul
     303: bipush        11
     305: iadd
     306: istore_1
     307: bipush        53
     309: iload_1
     310: imul
     311: aload_0
     312: invokevirtual #103                // Method getWorkersNumber:()I
     315: iadd
     316: istore_1
     317: aload_0
     318: invokevirtual #104                // Method hasBandwidth:()Z
     321: ifeq          345
     324: bipush        37
     326: iload_1
     327: imul
     328: bipush        12
     330: iadd
     331: istore_1
     332: bipush        53
     334: iload_1
     335: imul
     336: aload_0
     337: invokevirtual #105                // Method getBandwidth:()J
     340: invokestatic  #112                // Method org/apache/hbase/thirdparty/com/google/protobuf/Internal.hashLong:(J)I
     343: iadd
     344: istore_1
     345: bipush        29
     347: iload_1
     348: imul
     349: aload_0
     350: getfield      #2                  // Field unknownFields:Lorg/apache/hbase/thirdparty/com/google/protobuf/UnknownFieldSet;
     353: invokevirtual #113                // Method org/apache/hbase/thirdparty/com/google/protobuf/UnknownFieldSet.hashCode:()I
     356: iadd
     357: istore_1
     358: aload_0
     359: iload_1
     360: putfield      #107                // Field memoizedHashCode:I
     363: iload_1
     364: ireturn

  public static org.apache.hadoop.hbase.shaded.protobuf.generated.BackupProtos$BackupInfo parseFrom(java.nio.ByteBuffer) throws org.apache.hbase.thirdparty.com.google.protobuf.InvalidProtocolBufferException;
    Code:
       0: getstatic     #114                // Field PARSER:Lorg/apache/hbase/thirdparty/com/google/protobuf/Parser;
       3: aload_0
       4: invokeinterface #115,  2          // InterfaceMethod org/apache/hbase/thirdparty/com/google/protobuf/Parser.parseFrom:(Ljava/nio/ByteBuffer;)Ljava/lang/Object;
       9: checkcast     #51                 // class org/apache/hadoop/hbase/shaded/protobuf/generated/BackupProtos$BackupInfo
      12: areturn

  public static org.apache.hadoop.hbase.shaded.protobuf.generated.BackupProtos$BackupInfo parseFrom(java.nio.ByteBuffer, org.apache.hbase.thirdparty.com.google.protobuf.ExtensionRegistryLite) throws org.apache.hbase.thirdparty.com.google.protobuf.InvalidProtocolBufferException;
    Code:
       0: getstatic     #114                // Field PARSER:Lorg/apache/hbase/thirdparty/com/google/protobuf/Parser;
       3: aload_0
       4: aload_1
       5: invokeinterface #116,  3          // InterfaceMethod org/apache/hbase/thirdparty/com/google/protobuf/Parser.parseFrom:(Ljava/nio/ByteBuffer;Lorg/apache/hbase/thirdparty/com/google/protobuf/ExtensionRegistryLite;)Ljava/lang/Object;
      10: checkcast     #51                 // class org/apache/hadoop/hbase/shaded/protobuf/generated/BackupProtos$BackupInfo
      13: areturn

  public static org.apache.hadoop.hbase.shaded.protobuf.generated.BackupProtos$BackupInfo parseFrom(org.apache.hbase.thirdparty.com.google.protobuf.ByteString) throws org.apache.hbase.thirdparty.com.google.protobuf.InvalidProtocolBufferException;
    Code:
       0: getstatic     #114                // Field PARSER:Lorg/apache/hbase/thirdparty/com/google/protobuf/Parser;
       3: aload_0
       4: invokeinterface #117,  2          // InterfaceMethod org/apache/hbase/thirdparty/com/google/protobuf/Parser.parseFrom:(Lorg/apache/hbase/thirdparty/com/google/protobuf/ByteString;)Ljava/lang/Object;
       9: checkcast     #51                 // class org/apache/hadoop/hbase/shaded/protobuf/generated/BackupProtos$BackupInfo
      12: areturn

  public static org.apache.hadoop.hbase.shaded.protobuf.generated.BackupProtos$BackupInfo parseFrom(org.apache.hbase.thirdparty.com.google.protobuf.ByteString, org.apache.hbase.thirdparty.com.google.protobuf.ExtensionRegistryLite) throws org.apache.hbase.thirdparty.com.google.protobuf.InvalidProtocolBufferException;
    Code:
       0: getstatic     #114                // Field PARSER:Lorg/apache/hbase/thirdparty/com/google/protobuf/Parser;
       3: aload_0
       4: aload_1
       5: invokeinterface #118,  3          // InterfaceMethod org/apache/hbase/thirdparty/com/google/protobuf/Parser.parseFrom:(Lorg/apache/hbase/thirdparty/com/google/protobuf/ByteString;Lorg/apache/hbase/thirdparty/com/google/protobuf/ExtensionRegistryLite;)Ljava/lang/Object;
      10: checkcast     #51                 // class org/apache/hadoop/hbase/shaded/protobuf/generated/BackupProtos$BackupInfo
      13: areturn

  public static org.apache.hadoop.hbase.shaded.protobuf.generated.BackupProtos$BackupInfo parseFrom(byte[]) throws org.apache.hbase.thirdparty.com.google.protobuf.InvalidProtocolBufferException;
    Code:
       0: getstatic     #114                // Field PARSER:Lorg/apache/hbase/thirdparty/com/google/protobuf/Parser;
       3: aload_0
       4: invokeinterface #119,  2          // InterfaceMethod org/apache/hbase/thirdparty/com/google/protobuf/Parser.parseFrom:([B)Ljava/lang/Object;
       9: checkcast     #51                 // class org/apache/hadoop/hbase/shaded/protobuf/generated/BackupProtos$BackupInfo
      12: areturn

  public static org.apache.hadoop.hbase.shaded.protobuf.generated.BackupProtos$BackupInfo parseFrom(byte[], org.apache.hbase.thirdparty.com.google.protobuf.ExtensionRegistryLite) throws org.apache.hbase.thirdparty.com.google.protobuf.InvalidProtocolBufferException;
    Code:
       0: getstatic     #114                // Field PARSER:Lorg/apache/hbase/thirdparty/com/google/protobuf/Parser;
       3: aload_0
       4: aload_1
       5: invokeinterface #120,  3          // InterfaceMethod org/apache/hbase/thirdparty/com/google/protobuf/Parser.parseFrom:([BLorg/apache/hbase/thirdparty/com/google/protobuf/ExtensionRegistryLite;)Ljava/lang/Object;
      10: checkcast     #51                 // class org/apache/hadoop/hbase/shaded/protobuf/generated/BackupProtos$BackupInfo
      13: areturn

  public static org.apache.hadoop.hbase.shaded.protobuf.generated.BackupProtos$BackupInfo parseFrom(java.io.InputStream) throws java.io.IOException;
    Code:
       0: getstatic     #114                // Field PARSER:Lorg/apache/hbase/thirdparty/com/google/protobuf/Parser;
       3: aload_0
       4: invokestatic  #121                // Method org/apache/hbase/thirdparty/com/google/protobuf/GeneratedMessageV3.parseWithIOException:(Lorg/apache/hbase/thirdparty/com/google/protobuf/Parser;Ljava/io/InputStream;)Lorg/apache/hbase/thirdparty/com/google/protobuf/Message;
       7: checkcast     #51                 // class org/apache/hadoop/hbase/shaded/protobuf/generated/BackupProtos$BackupInfo
      10: areturn

  public static org.apache.hadoop.hbase.shaded.protobuf.generated.BackupProtos$BackupInfo parseFrom(java.io.InputStream, org.apache.hbase.thirdparty.com.google.protobuf.ExtensionRegistryLite) throws java.io.IOException;
    Code:
       0: getstatic     #114                // Field PARSER:Lorg/apache/hbase/thirdparty/com/google/protobuf/Parser;
       3: aload_0
       4: aload_1
       5: invokestatic  #122                // Method org/apache/hbase/thirdparty/com/google/protobuf/GeneratedMessageV3.parseWithIOException:(Lorg/apache/hbase/thirdparty/com/google/protobuf/Parser;Ljava/io/InputStream;Lorg/apache/hbase/thirdparty/com/google/protobuf/ExtensionRegistryLite;)Lorg/apache/hbase/thirdparty/com/google/protobuf/Message;
       8: checkcast     #51                 // class org/apache/hadoop/hbase/shaded/protobuf/generated/BackupProtos$BackupInfo
      11: areturn

  public static org.apache.hadoop.hbase.shaded.protobuf.generated.BackupProtos$BackupInfo parseDelimitedFrom(java.io.InputStream) throws java.io.IOException;
    Code:
       0: getstatic     #114                // Field PARSER:Lorg/apache/hbase/thirdparty/com/google/protobuf/Parser;
       3: aload_0
       4: invokestatic  #123                // Method org/apache/hbase/thirdparty/com/google/protobuf/GeneratedMessageV3.parseDelimitedWithIOException:(Lorg/apache/hbase/thirdparty/com/google/protobuf/Parser;Ljava/io/InputStream;)Lorg/apache/hbase/thirdparty/com/google/protobuf/Message;
       7: checkcast     #51                 // class org/apache/hadoop/hbase/shaded/protobuf/generated/BackupProtos$BackupInfo
      10: areturn

  public static org.apache.hadoop.hbase.shaded.protobuf.generated.BackupProtos$BackupInfo parseDelimitedFrom(java.io.InputStream, org.apache.hbase.thirdparty.com.google.protobuf.ExtensionRegistryLite) throws java.io.IOException;
    Code:
       0: getstatic     #114                // Field PARSER:Lorg/apache/hbase/thirdparty/com/google/protobuf/Parser;
       3: aload_0
       4: aload_1
       5: invokestatic  #124                // Method org/apache/hbase/thirdparty/com/google/protobuf/GeneratedMessageV3.parseDelimitedWithIOException:(Lorg/apache/hbase/thirdparty/com/google/protobuf/Parser;Ljava/io/InputStream;Lorg/apache/hbase/thirdparty/com/google/protobuf/ExtensionRegistryLite;)Lorg/apache/hbase/thirdparty/com/google/protobuf/Message;
       8: checkcast     #51                 // class org/apache/hadoop/hbase/shaded/protobuf/generated/BackupProtos$BackupInfo
      11: areturn

  public static org.apache.hadoop.hbase.shaded.protobuf.generated.BackupProtos$BackupInfo parseFrom(org.apache.hbase.thirdparty.com.google.protobuf.CodedInputStream) throws java.io.IOException;
    Code:
       0: getstatic     #114                // Field PARSER:Lorg/apache/hbase/thirdparty/com/google/protobuf/Parser;
       3: aload_0
       4: invokestatic  #125                // Method org/apache/hbase/thirdparty/com/google/protobuf/GeneratedMessageV3.parseWithIOException:(Lorg/apache/hbase/thirdparty/com/google/protobuf/Parser;Lorg/apache/hbase/thirdparty/com/google/protobuf/CodedInputStream;)Lorg/apache/hbase/thirdparty/com/google/protobuf/Message;
       7: checkcast     #51                 // class org/apache/hadoop/hbase/shaded/protobuf/generated/BackupProtos$BackupInfo
      10: areturn

  public static org.apache.hadoop.hbase.shaded.protobuf.generated.BackupProtos$BackupInfo parseFrom(org.apache.hbase.thirdparty.com.google.protobuf.CodedInputStream, org.apache.hbase.thirdparty.com.google.protobuf.ExtensionRegistryLite) throws java.io.IOException;
    Code:
       0: getstatic     #114                // Field PARSER:Lorg/apache/hbase/thirdparty/com/google/protobuf/Parser;
       3: aload_0
       4: aload_1
       5: invokestatic  #126                // Method org/apache/hbase/thirdparty/com/google/protobuf/GeneratedMessageV3.parseWithIOException:(Lorg/apache/hbase/thirdparty/com/google/protobuf/Parser;Lorg/apache/hbase/thirdparty/com/google/protobuf/CodedInputStream;Lorg/apache/hbase/thirdparty/com/google/protobuf/ExtensionRegistryLite;)Lorg/apache/hbase/thirdparty/com/google/protobuf/Message;
       8: checkcast     #51                 // class org/apache/hadoop/hbase/shaded/protobuf/generated/BackupProtos$BackupInfo
      11: areturn

  public org.apache.hadoop.hbase.shaded.protobuf.generated.BackupProtos$BackupInfo$Builder newBuilderForType();
    Code:
       0: invokestatic  #127                // Method newBuilder:()Lorg/apache/hadoop/hbase/shaded/protobuf/generated/BackupProtos$BackupInfo$Builder;
       3: areturn

  public static org.apache.hadoop.hbase.shaded.protobuf.generated.BackupProtos$BackupInfo$Builder newBuilder();
    Code:
       0: getstatic     #128                // Field DEFAULT_INSTANCE:Lorg/apache/hadoop/hbase/shaded/protobuf/generated/BackupProtos$BackupInfo;
       3: invokevirtual #129                // Method toBuilder:()Lorg/apache/hadoop/hbase/shaded/protobuf/generated/BackupProtos$BackupInfo$Builder;
       6: areturn

  public static org.apache.hadoop.hbase.shaded.protobuf.generated.BackupProtos$BackupInfo$Builder newBuilder(org.apache.hadoop.hbase.shaded.protobuf.generated.BackupProtos$BackupInfo);
    Code:
       0: getstatic     #128                // Field DEFAULT_INSTANCE:Lorg/apache/hadoop/hbase/shaded/protobuf/generated/BackupProtos$BackupInfo;
       3: invokevirtual #129                // Method toBuilder:()Lorg/apache/hadoop/hbase/shaded/protobuf/generated/BackupProtos$BackupInfo$Builder;
       6: aload_0
       7: invokevirtual #130                // Method org/apache/hadoop/hbase/shaded/protobuf/generated/BackupProtos$BackupInfo$Builder.mergeFrom:(Lorg/apache/hadoop/hbase/shaded/protobuf/generated/BackupProtos$BackupInfo;)Lorg/apache/hadoop/hbase/shaded/protobuf/generated/BackupProtos$BackupInfo$Builder;
      10: areturn

  public org.apache.hadoop.hbase.shaded.protobuf.generated.BackupProtos$BackupInfo$Builder toBuilder();
    Code:
       0: aload_0
       1: getstatic     #128                // Field DEFAULT_INSTANCE:Lorg/apache/hadoop/hbase/shaded/protobuf/generated/BackupProtos$BackupInfo;
       4: if_acmpne     18
       7: new           #52                 // class org/apache/hadoop/hbase/shaded/protobuf/generated/BackupProtos$BackupInfo$Builder
      10: dup
      11: aconst_null
      12: invokespecial #131                // Method org/apache/hadoop/hbase/shaded/protobuf/generated/BackupProtos$BackupInfo$Builder."<init>":(Lorg/apache/hadoop/hbase/shaded/protobuf/generated/BackupProtos$1;)V
      15: goto          30
      18: new           #52                 // class org/apache/hadoop/hbase/shaded/protobuf/generated/BackupProtos$BackupInfo$Builder
      21: dup
      22: aconst_null
      23: invokespecial #131                // Method org/apache/hadoop/hbase/shaded/protobuf/generated/BackupProtos$BackupInfo$Builder."<init>":(Lorg/apache/hadoop/hbase/shaded/protobuf/generated/BackupProtos$1;)V
      26: aload_0
      27: invokevirtual #130                // Method org/apache/hadoop/hbase/shaded/protobuf/generated/BackupProtos$BackupInfo$Builder.mergeFrom:(Lorg/apache/hadoop/hbase/shaded/protobuf/generated/BackupProtos$BackupInfo;)Lorg/apache/hadoop/hbase/shaded/protobuf/generated/BackupProtos$BackupInfo$Builder;
      30: areturn

  protected org.apache.hadoop.hbase.shaded.protobuf.generated.BackupProtos$BackupInfo$Builder newBuilderForType(org.apache.hbase.thirdparty.com.google.protobuf.GeneratedMessageV3$BuilderParent);
    Code:
       0: new           #52                 // class org/apache/hadoop/hbase/shaded/protobuf/generated/BackupProtos$BackupInfo$Builder
       3: dup
       4: aload_1
       5: aconst_null
       6: invokespecial #132                // Method org/apache/hadoop/hbase/shaded/protobuf/generated/BackupProtos$BackupInfo$Builder."<init>":(Lorg/apache/hbase/thirdparty/com/google/protobuf/GeneratedMessageV3$BuilderParent;Lorg/apache/hadoop/hbase/shaded/protobuf/generated/BackupProtos$1;)V
       9: astore_2
      10: aload_2
      11: areturn

  public static org.apache.hadoop.hbase.shaded.protobuf.generated.BackupProtos$BackupInfo getDefaultInstance();
    Code:
       0: getstatic     #128                // Field DEFAULT_INSTANCE:Lorg/apache/hadoop/hbase/shaded/protobuf/generated/BackupProtos$BackupInfo;
       3: areturn

  public static org.apache.hbase.thirdparty.com.google.protobuf.Parser<org.apache.hadoop.hbase.shaded.protobuf.generated.BackupProtos$BackupInfo> parser();
    Code:
       0: getstatic     #114                // Field PARSER:Lorg/apache/hbase/thirdparty/com/google/protobuf/Parser;
       3: areturn

  public org.apache.hbase.thirdparty.com.google.protobuf.Parser<org.apache.hadoop.hbase.shaded.protobuf.generated.BackupProtos$BackupInfo> getParserForType();
    Code:
       0: getstatic     #114                // Field PARSER:Lorg/apache/hbase/thirdparty/com/google/protobuf/Parser;
       3: areturn

  public org.apache.hadoop.hbase.shaded.protobuf.generated.BackupProtos$BackupInfo getDefaultInstanceForType();
    Code:
       0: getstatic     #128                // Field DEFAULT_INSTANCE:Lorg/apache/hadoop/hbase/shaded/protobuf/generated/BackupProtos$BackupInfo;
       3: areturn

  protected org.apache.hbase.thirdparty.com.google.protobuf.Message$Builder newBuilderForType(org.apache.hbase.thirdparty.com.google.protobuf.GeneratedMessageV3$BuilderParent);
    Code:
       0: aload_0
       1: aload_1
       2: invokevirtual #133                // Method newBuilderForType:(Lorg/apache/hbase/thirdparty/com/google/protobuf/GeneratedMessageV3$BuilderParent;)Lorg/apache/hadoop/hbase/shaded/protobuf/generated/BackupProtos$BackupInfo$Builder;
       5: areturn

  public org.apache.hbase.thirdparty.com.google.protobuf.Message$Builder toBuilder();
    Code:
       0: aload_0
       1: invokevirtual #129                // Method toBuilder:()Lorg/apache/hadoop/hbase/shaded/protobuf/generated/BackupProtos$BackupInfo$Builder;
       4: areturn

  public org.apache.hbase.thirdparty.com.google.protobuf.Message$Builder newBuilderForType();
    Code:
       0: aload_0
       1: invokevirtual #134                // Method newBuilderForType:()Lorg/apache/hadoop/hbase/shaded/protobuf/generated/BackupProtos$BackupInfo$Builder;
       4: areturn

  public org.apache.hbase.thirdparty.com.google.protobuf.MessageLite$Builder toBuilder();
    Code:
       0: aload_0
       1: invokevirtual #129                // Method toBuilder:()Lorg/apache/hadoop/hbase/shaded/protobuf/generated/BackupProtos$BackupInfo$Builder;
       4: areturn

  public org.apache.hbase.thirdparty.com.google.protobuf.MessageLite$Builder newBuilderForType();
    Code:
       0: aload_0
       1: invokevirtual #134                // Method newBuilderForType:()Lorg/apache/hadoop/hbase/shaded/protobuf/generated/BackupProtos$BackupInfo$Builder;
       4: areturn

  public org.apache.hbase.thirdparty.com.google.protobuf.MessageLite getDefaultInstanceForType();
    Code:
       0: aload_0
       1: invokevirtual #135                // Method getDefaultInstanceForType:()Lorg/apache/hadoop/hbase/shaded/protobuf/generated/BackupProtos$BackupInfo;
       4: areturn

  public org.apache.hbase.thirdparty.com.google.protobuf.Message getDefaultInstanceForType();
    Code:
       0: aload_0
       1: invokevirtual #135                // Method getDefaultInstanceForType:()Lorg/apache/hadoop/hbase/shaded/protobuf/generated/BackupProtos$BackupInfo;
       4: areturn

  static boolean access$5800();
    Code:
       0: getstatic     #3                  // Field alwaysUseFieldBuilders:Z
       3: ireturn

  org.apache.hadoop.hbase.shaded.protobuf.generated.BackupProtos$BackupInfo(org.apache.hbase.thirdparty.com.google.protobuf.GeneratedMessageV3$Builder, org.apache.hadoop.hbase.shaded.protobuf.generated.BackupProtos$1);
    Code:
       0: aload_0
       1: aload_1
       2: invokespecial #17                 // Method "<init>":(Lorg/apache/hbase/thirdparty/com/google/protobuf/GeneratedMessageV3$Builder;)V
       5: return

  static java.lang.Object access$6002(org.apache.hadoop.hbase.shaded.protobuf.generated.BackupProtos$BackupInfo, java.lang.Object);
    Code:
       0: aload_0
       1: aload_1
       2: dup_x1
       3: putfield      #16                 // Field backupId_:Ljava/lang/Object;
       6: areturn

  static int access$6102(org.apache.hadoop.hbase.shaded.protobuf.generated.BackupProtos$BackupInfo, int);
    Code:
       0: aload_0
       1: iload_1
       2: dup_x1
       3: putfield      #15                 // Field backupType_:I
       6: ireturn

  static java.lang.Object access$6202(org.apache.hadoop.hbase.shaded.protobuf.generated.BackupProtos$BackupInfo, java.lang.Object);
    Code:
       0: aload_0
       1: aload_1
       2: dup_x1
       3: putfield      #14                 // Field backupRootDir_:Ljava/lang/Object;
       6: areturn

  static int access$6302(org.apache.hadoop.hbase.shaded.protobuf.generated.BackupProtos$BackupInfo, int);
    Code:
       0: aload_0
       1: iload_1
       2: dup_x1
       3: putfield      #13                 // Field backupState_:I
       6: ireturn

  static int access$6402(org.apache.hadoop.hbase.shaded.protobuf.generated.BackupProtos$BackupInfo, int);
    Code:
       0: aload_0
       1: iload_1
       2: dup_x1
       3: putfield      #12                 // Field backupPhase_:I
       6: ireturn

  static java.lang.Object access$6502(org.apache.hadoop.hbase.shaded.protobuf.generated.BackupProtos$BackupInfo, java.lang.Object);
    Code:
       0: aload_0
       1: aload_1
       2: dup_x1
       3: putfield      #11                 // Field failedMessage_:Ljava/lang/Object;
       6: areturn

  static java.util.List access$6602(org.apache.hadoop.hbase.shaded.protobuf.generated.BackupProtos$BackupInfo, java.util.List);
    Code:
       0: aload_0
       1: aload_1
       2: dup_x1
       3: putfield      #10                 // Field backupTableInfo_:Ljava/util/List;
       6: areturn

  static long access$6702(org.apache.hadoop.hbase.shaded.protobuf.generated.BackupProtos$BackupInfo, long);
    Code:
       0: aload_0
       1: lload_1
       2: dup2_x1
       3: putfield      #9                  // Field startTs_:J
       6: lreturn

  static long access$6802(org.apache.hadoop.hbase.shaded.protobuf.generated.BackupProtos$BackupInfo, long);
    Code:
       0: aload_0
       1: lload_1
       2: dup2_x1
       3: putfield      #8                  // Field completeTs_:J
       6: lreturn

  static int access$6902(org.apache.hadoop.hbase.shaded.protobuf.generated.BackupProtos$BackupInfo, int);
    Code:
       0: aload_0
       1: iload_1
       2: dup_x1
       3: putfield      #7                  // Field progress_:I
       6: ireturn

  static int access$7002(org.apache.hadoop.hbase.shaded.protobuf.generated.BackupProtos$BackupInfo, int);
    Code:
       0: aload_0
       1: iload_1
       2: dup_x1
       3: putfield      #6                  // Field workersNumber_:I
       6: ireturn

  static long access$7102(org.apache.hadoop.hbase.shaded.protobuf.generated.BackupProtos$BackupInfo, long);
    Code:
       0: aload_0
       1: lload_1
       2: dup2_x1
       3: putfield      #5                  // Field bandwidth_:J
       6: lreturn

  static int access$7202(org.apache.hadoop.hbase.shaded.protobuf.generated.BackupProtos$BackupInfo, int);
    Code:
       0: aload_0
       1: iload_1
       2: dup_x1
       3: putfield      #4                  // Field bitField0_:I
       6: ireturn

  static java.lang.Object access$6000(org.apache.hadoop.hbase.shaded.protobuf.generated.BackupProtos$BackupInfo);
    Code:
       0: aload_0
       1: getfield      #16                 // Field backupId_:Ljava/lang/Object;
       4: areturn

  static java.lang.Object access$6200(org.apache.hadoop.hbase.shaded.protobuf.generated.BackupProtos$BackupInfo);
    Code:
       0: aload_0
       1: getfield      #14                 // Field backupRootDir_:Ljava/lang/Object;
       4: areturn

  static java.lang.Object access$6500(org.apache.hadoop.hbase.shaded.protobuf.generated.BackupProtos$BackupInfo);
    Code:
       0: aload_0
       1: getfield      #11                 // Field failedMessage_:Ljava/lang/Object;
       4: areturn

  static java.util.List access$6600(org.apache.hadoop.hbase.shaded.protobuf.generated.BackupProtos$BackupInfo);
    Code:
       0: aload_0
       1: getfield      #10                 // Field backupTableInfo_:Ljava/util/List;
       4: areturn

  static boolean access$7300();
    Code:
       0: getstatic     #3                  // Field alwaysUseFieldBuilders:Z
       3: ireturn

  static org.apache.hbase.thirdparty.com.google.protobuf.UnknownFieldSet access$7400(org.apache.hadoop.hbase.shaded.protobuf.generated.BackupProtos$BackupInfo);
    Code:
       0: aload_0
       1: getfield      #2                  // Field unknownFields:Lorg/apache/hbase/thirdparty/com/google/protobuf/UnknownFieldSet;
       4: areturn

  org.apache.hadoop.hbase.shaded.protobuf.generated.BackupProtos$BackupInfo(org.apache.hbase.thirdparty.com.google.protobuf.CodedInputStream, org.apache.hbase.thirdparty.com.google.protobuf.ExtensionRegistryLite, org.apache.hadoop.hbase.shaded.protobuf.generated.BackupProtos$1) throws org.apache.hbase.thirdparty.com.google.protobuf.InvalidProtocolBufferException;
    Code:
       0: aload_0
       1: aload_1
       2: aload_2
       3: invokespecial #1                  // Method "<init>":(Lorg/apache/hbase/thirdparty/com/google/protobuf/CodedInputStream;Lorg/apache/hbase/thirdparty/com/google/protobuf/ExtensionRegistryLite;)V
       6: return

  static {};
    Code:
       0: new           #51                 // class org/apache/hadoop/hbase/shaded/protobuf/generated/BackupProtos$BackupInfo
       3: dup
       4: invokespecial #23                 // Method "<init>":()V
       7: putstatic     #128                // Field DEFAULT_INSTANCE:Lorg/apache/hadoop/hbase/shaded/protobuf/generated/BackupProtos$BackupInfo;
      10: new           #136                // class org/apache/hadoop/hbase/shaded/protobuf/generated/BackupProtos$BackupInfo$1
      13: dup
      14: invokespecial #137                // Method org/apache/hadoop/hbase/shaded/protobuf/generated/BackupProtos$BackupInfo$1."<init>":()V
      17: putstatic     #114                // Field PARSER:Lorg/apache/hbase/thirdparty/com/google/protobuf/Parser;
      20: return
}
