Compiled from "BalancerTestBase2.java"
public class org.apache.hadoop.hbase.master.balancer.BalancerTestBase2 extends org.apache.hadoop.hbase.master.balancer.BalancerTestBase {
  public org.apache.hadoop.hbase.master.balancer.BalancerTestBase2();
    Code:
       0: aload_0
       1: invokespecial #1                  // Method org/apache/hadoop/hbase/master/balancer/BalancerTestBase."<init>":()V
       4: return

  public void before();
    Code:
       0: getstatic     #2                  // Field conf:Lorg/apache/hadoop/conf/Configuration;
       3: ldc           #3                  // String hbase.master.balancer.stochastic.maxMovePercent
       5: fconst_1
       6: invokevirtual #4                  // Method org/apache/hadoop/conf/Configuration.setFloat:(Ljava/lang/String;F)V
       9: getstatic     #2                  // Field conf:Lorg/apache/hadoop/conf/Configuration;
      12: ldc           #6                  // String hbase.master.balancer.stochastic.maxSteps
      14: ldc2_w        #7                  // long 2000000l
      17: invokevirtual #9                  // Method org/apache/hadoop/conf/Configuration.setLong:(Ljava/lang/String;J)V
      20: getstatic     #2                  // Field conf:Lorg/apache/hadoop/conf/Configuration;
      23: ldc           #10                 // String hbase.master.balancer.stochastic.localityCost
      25: fconst_0
      26: invokevirtual #4                  // Method org/apache/hadoop/conf/Configuration.setFloat:(Ljava/lang/String;F)V
      29: getstatic     #2                  // Field conf:Lorg/apache/hadoop/conf/Configuration;
      32: ldc           #11                 // String hbase.master.balancer.stochastic.maxRunningTime
      34: ldc2_w        #12                 // long 90000l
      37: invokevirtual #9                  // Method org/apache/hadoop/conf/Configuration.setLong:(Ljava/lang/String;J)V
      40: getstatic     #2                  // Field conf:Lorg/apache/hadoop/conf/Configuration;
      43: ldc           #14                 // String hbase.master.balancer.stochastic.minCostNeedBalance
      45: ldc           #15                 // float 0.05f
      47: invokevirtual #4                  // Method org/apache/hadoop/conf/Configuration.setFloat:(Ljava/lang/String;F)V
      50: getstatic     #16                 // Field loadBalancer:Lorg/apache/hadoop/hbase/master/balancer/StochasticLoadBalancer;
      53: getstatic     #2                  // Field conf:Lorg/apache/hadoop/conf/Configuration;
      56: invokevirtual #17                 // Method org/apache/hadoop/hbase/master/balancer/StochasticLoadBalancer.setConf:(Lorg/apache/hadoop/conf/Configuration;)V
      59: return

  public void after();
    Code:
       0: getstatic     #16                 // Field loadBalancer:Lorg/apache/hadoop/hbase/master/balancer/StochasticLoadBalancer;
       3: getstatic     #2                  // Field conf:Lorg/apache/hadoop/conf/Configuration;
       6: invokevirtual #17                 // Method org/apache/hadoop/hbase/master/balancer/StochasticLoadBalancer.setConf:(Lorg/apache/hadoop/conf/Configuration;)V
       9: return
}
