Compiled from "BaseSource.java"
public interface org.apache.hadoop.hbase.metrics.BaseSource {
  public static final java.lang.String HBASE_METRICS_SYSTEM_NAME;

  public abstract void init();

  public abstract void setGauge(java.lang.String, long);

  public abstract void incGauge(java.lang.String, long);

  public abstract void decGauge(java.lang.String, long);

  public abstract void removeMetric(java.lang.String);

  public abstract void incCounters(java.lang.String, long);

  public abstract void updateHistogram(java.lang.String, long);

  public abstract java.lang.String getMetricsContext();

  public abstract java.lang.String getMetricsDescription();

  public abstract java.lang.String getMetricsJmxContext();

  public abstract java.lang.String getMetricsName();

  public org.apache.hadoop.hbase.metrics.MetricRegistryInfo getMetricRegistryInfo();
    Code:
       0: new           #1                  // class org/apache/hadoop/hbase/metrics/MetricRegistryInfo
       3: dup
       4: aload_0
       5: invokeinterface #2,  1            // InterfaceMethod getMetricsName:()Ljava/lang/String;
      10: aload_0
      11: invokeinterface #3,  1            // InterfaceMethod getMetricsDescription:()Ljava/lang/String;
      16: aload_0
      17: invokeinterface #4,  1            // InterfaceMethod getMetricsContext:()Ljava/lang/String;
      22: aload_0
      23: invokeinterface #5,  1            // InterfaceMethod getMetricsJmxContext:()Ljava/lang/String;
      28: iconst_1
      29: invokespecial #6                  // Method org/apache/hadoop/hbase/metrics/MetricRegistryInfo."<init>":(Ljava/lang/String;Ljava/lang/String;Ljava/lang/String;Ljava/lang/String;Z)V
      32: areturn
}
