Compiled from "BaseRowProcessor.java"
public abstract class org.apache.hadoop.hbase.regionserver.BaseRowProcessor<S extends com.google.protobuf.Message, T extends com.google.protobuf.Message> implements org.apache.hadoop.hbase.regionserver.RowProcessor<S, T> {
  public org.apache.hadoop.hbase.regionserver.BaseRowProcessor();
    Code:
       0: aload_0
       1: invokespecial #1                  // Method java/lang/Object."<init>":()V
       4: return

  public void preProcess(org.apache.hadoop.hbase.regionserver.HRegion, org.apache.hadoop.hbase.wal.WALEdit) throws java.io.IOException;
    Code:
       0: return

  public void preBatchMutate(org.apache.hadoop.hbase.regionserver.HRegion, org.apache.hadoop.hbase.wal.WALEdit) throws java.io.IOException;
    Code:
       0: return

  public void postBatchMutate(org.apache.hadoop.hbase.regionserver.HRegion) throws java.io.IOException;
    Code:
       0: return

  public void postProcess(org.apache.hadoop.hbase.regionserver.HRegion, org.apache.hadoop.hbase.wal.WALEdit, boolean) throws java.io.IOException;
    Code:
       0: return

  public java.util.List<java.util.UUID> getClusterIds();
    Code:
       0: invokestatic  #2                  // Method java/util/Collections.emptyList:()Ljava/util/List;
       3: areturn

  public java.lang.String getName();
    Code:
       0: aload_0
       1: invokevirtual #3                  // Method java/lang/Object.getClass:()Ljava/lang/Class;
       4: invokevirtual #4                  // Method java/lang/Class.getSimpleName:()Ljava/lang/String;
       7: getstatic     #5                  // Field java/util/Locale.ROOT:Ljava/util/Locale;
      10: invokevirtual #6                  // Method java/lang/String.toLowerCase:(Ljava/util/Locale;)Ljava/lang/String;
      13: areturn

  public org.apache.hadoop.hbase.client.Durability useDurability();
    Code:
       0: getstatic     #7                  // Field org/apache/hadoop/hbase/client/Durability.USE_DEFAULT:Lorg/apache/hadoop/hbase/client/Durability;
       3: areturn
}
