Compiled from "BaseLoadBalancer.java"
final class org.apache.hadoop.hbase.master.balancer.BaseLoadBalancer$Cluster$LocalityType extends java.lang.Enum<org.apache.hadoop.hbase.master.balancer.BaseLoadBalancer$Cluster$LocalityType> {
  public static final org.apache.hadoop.hbase.master.balancer.BaseLoadBalancer$Cluster$LocalityType SERVER;

  public static final org.apache.hadoop.hbase.master.balancer.BaseLoadBalancer$Cluster$LocalityType RACK;

  public static org.apache.hadoop.hbase.master.balancer.BaseLoadBalancer$Cluster$LocalityType[] values();
    Code:
       0: getstatic     #1                  // Field $VALUES:[Lorg/apache/hadoop/hbase/master/balancer/BaseLoadBalancer$Cluster$LocalityType;
       3: invokevirtual #2                  // Method "[Lorg/apache/hadoop/hbase/master/balancer/BaseLoadBalancer$Cluster$LocalityType;".clone:()Ljava/lang/Object;
       6: checkcast     #3                  // class "[Lorg/apache/hadoop/hbase/master/balancer/BaseLoadBalancer$Cluster$LocalityType;"
       9: areturn

  public static org.apache.hadoop.hbase.master.balancer.BaseLoadBalancer$Cluster$LocalityType valueOf(java.lang.String);
    Code:
       0: ldc           #4                  // class org/apache/hadoop/hbase/master/balancer/BaseLoadBalancer$Cluster$LocalityType
       2: aload_0
       3: invokestatic  #5                  // Method java/lang/Enum.valueOf:(Ljava/lang/Class;Ljava/lang/String;)Ljava/lang/Enum;
       6: checkcast     #4                  // class org/apache/hadoop/hbase/master/balancer/BaseLoadBalancer$Cluster$LocalityType
       9: areturn

  static {};
    Code:
       0: new           #4                  // class org/apache/hadoop/hbase/master/balancer/BaseLoadBalancer$Cluster$LocalityType
       3: dup
       4: ldc           #7                  // String SERVER
       6: iconst_0
       7: invokespecial #8                  // Method "<init>":(Ljava/lang/String;I)V
      10: putstatic     #9                  // Field SERVER:Lorg/apache/hadoop/hbase/master/balancer/BaseLoadBalancer$Cluster$LocalityType;
      13: new           #4                  // class org/apache/hadoop/hbase/master/balancer/BaseLoadBalancer$Cluster$LocalityType
      16: dup
      17: ldc           #10                 // String RACK
      19: iconst_1
      20: invokespecial #8                  // Method "<init>":(Ljava/lang/String;I)V
      23: putstatic     #11                 // Field RACK:Lorg/apache/hadoop/hbase/master/balancer/BaseLoadBalancer$Cluster$LocalityType;
      26: iconst_2
      27: anewarray     #4                  // class org/apache/hadoop/hbase/master/balancer/BaseLoadBalancer$Cluster$LocalityType
      30: dup
      31: iconst_0
      32: getstatic     #9                  // Field SERVER:Lorg/apache/hadoop/hbase/master/balancer/BaseLoadBalancer$Cluster$LocalityType;
      35: aastore
      36: dup
      37: iconst_1
      38: getstatic     #11                 // Field RACK:Lorg/apache/hadoop/hbase/master/balancer/BaseLoadBalancer$Cluster$LocalityType;
      41: aastore
      42: putstatic     #1                  // Field $VALUES:[Lorg/apache/hadoop/hbase/master/balancer/BaseLoadBalancer$Cluster$LocalityType;
      45: return
}
