Compiled from "BigDecimalComparator.java"
public class org.apache.hadoop.hbase.filter.BigDecimalComparator extends org.apache.hadoop.hbase.filter.ByteArrayComparable {
  public org.apache.hadoop.hbase.filter.BigDecimalComparator(java.math.BigDecimal);
    Code:
       0: aload_0
       1: aload_1
       2: invokestatic  #1                  // Method org/apache/hadoop/hbase/util/Bytes.toBytes:(Ljava/math/BigDecimal;)[B
       5: invokespecial #2                  // Method org/apache/hadoop/hbase/filter/ByteArrayComparable."<init>":([B)V
       8: aload_0
       9: aload_1
      10: putfield      #3                  // Field bigDecimal:Ljava/math/BigDecimal;
      13: return

  public boolean equals(java.lang.Object);
    Code:
       0: aload_1
       1: ifnull        11
       4: aload_1
       5: instanceof    #4                  // class org/apache/hadoop/hbase/filter/BigDecimalComparator
       8: ifne          13
      11: iconst_0
      12: ireturn
      13: aload_0
      14: aload_1
      15: if_acmpne     20
      18: iconst_1
      19: ireturn
      20: aload_1
      21: checkcast     #4                  // class org/apache/hadoop/hbase/filter/BigDecimalComparator
      24: astore_2
      25: aload_0
      26: getfield      #3                  // Field bigDecimal:Ljava/math/BigDecimal;
      29: aload_2
      30: getfield      #3                  // Field bigDecimal:Ljava/math/BigDecimal;
      33: invokevirtual #5                  // Method java/math/BigDecimal.equals:(Ljava/lang/Object;)Z
      36: ireturn

  public int hashCode();
    Code:
       0: iconst_1
       1: anewarray     #6                  // class java/lang/Object
       4: dup
       5: iconst_0
       6: aload_0
       7: getfield      #3                  // Field bigDecimal:Ljava/math/BigDecimal;
      10: aastore
      11: invokestatic  #7                  // Method java/util/Objects.hash:([Ljava/lang/Object;)I
      14: ireturn

  public int compareTo(byte[], int, int);
    Code:
       0: aload_1
       1: iload_2
       2: iload_3
       3: invokestatic  #8                  // Method org/apache/hadoop/hbase/util/Bytes.toBigDecimal:([BII)Ljava/math/BigDecimal;
       6: astore        4
       8: aload_0
       9: getfield      #3                  // Field bigDecimal:Ljava/math/BigDecimal;
      12: aload         4
      14: invokevirtual #9                  // Method java/math/BigDecimal.compareTo:(Ljava/math/BigDecimal;)I
      17: ireturn

  public int compareTo(java.nio.ByteBuffer, int, int);
    Code:
       0: aload_1
       1: iload_2
       2: iload_3
       3: invokestatic  #10                 // Method org/apache/hadoop/hbase/util/ByteBufferUtils.toBigDecimal:(Ljava/nio/ByteBuffer;II)Ljava/math/BigDecimal;
       6: astore        4
       8: aload_0
       9: getfield      #3                  // Field bigDecimal:Ljava/math/BigDecimal;
      12: aload         4
      14: invokevirtual #9                  // Method java/math/BigDecimal.compareTo:(Ljava/math/BigDecimal;)I
      17: ireturn

  public byte[] toByteArray();
    Code:
       0: invokestatic  #11                 // Method org/apache/hadoop/hbase/shaded/protobuf/generated/ComparatorProtos$BigDecimalComparator.newBuilder:()Lorg/apache/hadoop/hbase/shaded/protobuf/generated/ComparatorProtos$BigDecimalComparator$Builder;
       3: astore_1
       4: aload_1
       5: aload_0
       6: getfield      #12                 // Field value:[B
       9: invokestatic  #13                 // Method org/apache/hadoop/hbase/shaded/protobuf/ProtobufUtil.toByteArrayComparable:([B)Lorg/apache/hadoop/hbase/shaded/protobuf/generated/ComparatorProtos$ByteArrayComparable;
      12: invokevirtual #14                 // Method org/apache/hadoop/hbase/shaded/protobuf/generated/ComparatorProtos$BigDecimalComparator$Builder.setComparable:(Lorg/apache/hadoop/hbase/shaded/protobuf/generated/ComparatorProtos$ByteArrayComparable;)Lorg/apache/hadoop/hbase/shaded/protobuf/generated/ComparatorProtos$BigDecimalComparator$Builder;
      15: pop
      16: aload_1
      17: invokevirtual #15                 // Method org/apache/hadoop/hbase/shaded/protobuf/generated/ComparatorProtos$BigDecimalComparator$Builder.build:()Lorg/apache/hadoop/hbase/shaded/protobuf/generated/ComparatorProtos$BigDecimalComparator;
      20: invokevirtual #16                 // Method org/apache/hadoop/hbase/shaded/protobuf/generated/ComparatorProtos$BigDecimalComparator.toByteArray:()[B
      23: areturn

  public static org.apache.hadoop.hbase.filter.BigDecimalComparator parseFrom(byte[]) throws org.apache.hadoop.hbase.exceptions.DeserializationException;
    Code:
       0: aload_0
       1: invokestatic  #17                 // Method org/apache/hadoop/hbase/shaded/protobuf/generated/ComparatorProtos$BigDecimalComparator.parseFrom:([B)Lorg/apache/hadoop/hbase/shaded/protobuf/generated/ComparatorProtos$BigDecimalComparator;
       4: astore_1
       5: goto          18
       8: astore_2
       9: new           #19                 // class org/apache/hadoop/hbase/exceptions/DeserializationException
      12: dup
      13: aload_2
      14: invokespecial #20                 // Method org/apache/hadoop/hbase/exceptions/DeserializationException."<init>":(Ljava/lang/Throwable;)V
      17: athrow
      18: new           #4                  // class org/apache/hadoop/hbase/filter/BigDecimalComparator
      21: dup
      22: aload_1
      23: invokevirtual #21                 // Method org/apache/hadoop/hbase/shaded/protobuf/generated/ComparatorProtos$BigDecimalComparator.getComparable:()Lorg/apache/hadoop/hbase/shaded/protobuf/generated/ComparatorProtos$ByteArrayComparable;
      26: invokevirtual #22                 // Method org/apache/hadoop/hbase/shaded/protobuf/generated/ComparatorProtos$ByteArrayComparable.getValue:()Lorg/apache/hbase/thirdparty/com/google/protobuf/ByteString;
      29: invokevirtual #23                 // Method org/apache/hbase/thirdparty/com/google/protobuf/ByteString.toByteArray:()[B
      32: invokestatic  #24                 // Method org/apache/hadoop/hbase/util/Bytes.toBigDecimal:([B)Ljava/math/BigDecimal;
      35: invokespecial #25                 // Method "<init>":(Ljava/math/BigDecimal;)V
      38: areturn
    Exception table:
       from    to  target type
           0     5     8   Class org/apache/hbase/thirdparty/com/google/protobuf/InvalidProtocolBufferException

  boolean areSerializedFieldsEqual(org.apache.hadoop.hbase.filter.BigDecimalComparator);
    Code:
       0: aload_1
       1: aload_0
       2: if_acmpne     7
       5: iconst_1
       6: ireturn
       7: aload_0
       8: aload_1
       9: invokespecial #26                 // Method org/apache/hadoop/hbase/filter/ByteArrayComparable.areSerializedFieldsEqual:(Lorg/apache/hadoop/hbase/filter/ByteArrayComparable;)Z
      12: ireturn
}
