Compiled from "BitComparator.java"
public class org.apache.hadoop.hbase.filter.BitComparator extends org.apache.hadoop.hbase.filter.ByteArrayComparable {
  protected org.apache.hadoop.hbase.filter.BitComparator$BitwiseOp bitOperator;

  public org.apache.hadoop.hbase.filter.BitComparator(byte[], org.apache.hadoop.hbase.filter.BitComparator$BitwiseOp);
    Code:
       0: aload_0
       1: aload_1
       2: invokespecial #1                  // Method org/apache/hadoop/hbase/filter/ByteArrayComparable."<init>":([B)V
       5: aload_0
       6: aload_2
       7: putfield      #2                  // Field bitOperator:Lorg/apache/hadoop/hbase/filter/BitComparator$BitwiseOp;
      10: return

  public org.apache.hadoop.hbase.filter.BitComparator$BitwiseOp getOperator();
    Code:
       0: aload_0
       1: getfield      #2                  // Field bitOperator:Lorg/apache/hadoop/hbase/filter/BitComparator$BitwiseOp;
       4: areturn

  public byte[] toByteArray();
    Code:
       0: invokestatic  #3                  // Method org/apache/hadoop/hbase/shaded/protobuf/generated/ComparatorProtos$BitComparator.newBuilder:()Lorg/apache/hadoop/hbase/shaded/protobuf/generated/ComparatorProtos$BitComparator$Builder;
       3: astore_1
       4: aload_1
       5: aload_0
       6: getfield      #4                  // Field value:[B
       9: invokestatic  #5                  // Method org/apache/hadoop/hbase/shaded/protobuf/ProtobufUtil.toByteArrayComparable:([B)Lorg/apache/hadoop/hbase/shaded/protobuf/generated/ComparatorProtos$ByteArrayComparable;
      12: invokevirtual #6                  // Method org/apache/hadoop/hbase/shaded/protobuf/generated/ComparatorProtos$BitComparator$Builder.setComparable:(Lorg/apache/hadoop/hbase/shaded/protobuf/generated/ComparatorProtos$ByteArrayComparable;)Lorg/apache/hadoop/hbase/shaded/protobuf/generated/ComparatorProtos$BitComparator$Builder;
      15: pop
      16: aload_0
      17: getfield      #2                  // Field bitOperator:Lorg/apache/hadoop/hbase/filter/BitComparator$BitwiseOp;
      20: invokevirtual #7                  // Method org/apache/hadoop/hbase/filter/BitComparator$BitwiseOp.name:()Ljava/lang/String;
      23: invokestatic  #8                  // Method org/apache/hadoop/hbase/shaded/protobuf/generated/ComparatorProtos$BitComparator$BitwiseOp.valueOf:(Ljava/lang/String;)Lorg/apache/hadoop/hbase/shaded/protobuf/generated/ComparatorProtos$BitComparator$BitwiseOp;
      26: astore_2
      27: aload_1
      28: aload_2
      29: invokevirtual #9                  // Method org/apache/hadoop/hbase/shaded/protobuf/generated/ComparatorProtos$BitComparator$Builder.setBitwiseOp:(Lorg/apache/hadoop/hbase/shaded/protobuf/generated/ComparatorProtos$BitComparator$BitwiseOp;)Lorg/apache/hadoop/hbase/shaded/protobuf/generated/ComparatorProtos$BitComparator$Builder;
      32: pop
      33: aload_1
      34: invokevirtual #10                 // Method org/apache/hadoop/hbase/shaded/protobuf/generated/ComparatorProtos$BitComparator$Builder.build:()Lorg/apache/hadoop/hbase/shaded/protobuf/generated/ComparatorProtos$BitComparator;
      37: invokevirtual #11                 // Method org/apache/hadoop/hbase/shaded/protobuf/generated/ComparatorProtos$BitComparator.toByteArray:()[B
      40: areturn

  public static org.apache.hadoop.hbase.filter.BitComparator parseFrom(byte[]) throws org.apache.hadoop.hbase.exceptions.DeserializationException;
    Code:
       0: aload_0
       1: invokestatic  #12                 // Method org/apache/hadoop/hbase/shaded/protobuf/generated/ComparatorProtos$BitComparator.parseFrom:([B)Lorg/apache/hadoop/hbase/shaded/protobuf/generated/ComparatorProtos$BitComparator;
       4: astore_1
       5: goto          18
       8: astore_2
       9: new           #14                 // class org/apache/hadoop/hbase/exceptions/DeserializationException
      12: dup
      13: aload_2
      14: invokespecial #15                 // Method org/apache/hadoop/hbase/exceptions/DeserializationException."<init>":(Ljava/lang/Throwable;)V
      17: athrow
      18: aload_1
      19: invokevirtual #16                 // Method org/apache/hadoop/hbase/shaded/protobuf/generated/ComparatorProtos$BitComparator.getBitwiseOp:()Lorg/apache/hadoop/hbase/shaded/protobuf/generated/ComparatorProtos$BitComparator$BitwiseOp;
      22: invokevirtual #17                 // Method org/apache/hadoop/hbase/shaded/protobuf/generated/ComparatorProtos$BitComparator$BitwiseOp.name:()Ljava/lang/String;
      25: invokestatic  #18                 // Method org/apache/hadoop/hbase/filter/BitComparator$BitwiseOp.valueOf:(Ljava/lang/String;)Lorg/apache/hadoop/hbase/filter/BitComparator$BitwiseOp;
      28: astore_2
      29: new           #19                 // class org/apache/hadoop/hbase/filter/BitComparator
      32: dup
      33: aload_1
      34: invokevirtual #20                 // Method org/apache/hadoop/hbase/shaded/protobuf/generated/ComparatorProtos$BitComparator.getComparable:()Lorg/apache/hadoop/hbase/shaded/protobuf/generated/ComparatorProtos$ByteArrayComparable;
      37: invokevirtual #21                 // Method org/apache/hadoop/hbase/shaded/protobuf/generated/ComparatorProtos$ByteArrayComparable.getValue:()Lorg/apache/hbase/thirdparty/com/google/protobuf/ByteString;
      40: invokevirtual #22                 // Method org/apache/hbase/thirdparty/com/google/protobuf/ByteString.toByteArray:()[B
      43: aload_2
      44: invokespecial #23                 // Method "<init>":([BLorg/apache/hadoop/hbase/filter/BitComparator$BitwiseOp;)V
      47: areturn
    Exception table:
       from    to  target type
           0     5     8   Class org/apache/hbase/thirdparty/com/google/protobuf/InvalidProtocolBufferException

  boolean areSerializedFieldsEqual(org.apache.hadoop.hbase.filter.ByteArrayComparable);
    Code:
       0: aload_1
       1: aload_0
       2: if_acmpne     7
       5: iconst_1
       6: ireturn
       7: aload_1
       8: instanceof    #19                 // class org/apache/hadoop/hbase/filter/BitComparator
      11: ifne          16
      14: iconst_0
      15: ireturn
      16: aload_1
      17: checkcast     #19                 // class org/apache/hadoop/hbase/filter/BitComparator
      20: astore_2
      21: aload_0
      22: aload_1
      23: invokespecial #24                 // Method org/apache/hadoop/hbase/filter/ByteArrayComparable.areSerializedFieldsEqual:(Lorg/apache/hadoop/hbase/filter/ByteArrayComparable;)Z
      26: ifeq          47
      29: aload_0
      30: invokevirtual #25                 // Method getOperator:()Lorg/apache/hadoop/hbase/filter/BitComparator$BitwiseOp;
      33: aload_2
      34: invokevirtual #25                 // Method getOperator:()Lorg/apache/hadoop/hbase/filter/BitComparator$BitwiseOp;
      37: invokevirtual #26                 // Method org/apache/hadoop/hbase/filter/BitComparator$BitwiseOp.equals:(Ljava/lang/Object;)Z
      40: ifeq          47
      43: iconst_1
      44: goto          48
      47: iconst_0
      48: ireturn

  public int compareTo(byte[], int, int);
    Code:
       0: iload_3
       1: aload_0
       2: getfield      #4                  // Field value:[B
       5: arraylength
       6: if_icmpeq     11
       9: iconst_1
      10: ireturn
      11: iconst_0
      12: istore        4
      14: iload_3
      15: iconst_1
      16: isub
      17: istore        5
      19: iload         5
      21: iflt          140
      24: iload         4
      26: ifne          140
      29: getstatic     #27                 // Field org/apache/hadoop/hbase/filter/BitComparator$1.$SwitchMap$org$apache$hadoop$hbase$filter$BitComparator$BitwiseOp:[I
      32: aload_0
      33: getfield      #2                  // Field bitOperator:Lorg/apache/hadoop/hbase/filter/BitComparator$BitwiseOp;
      36: invokevirtual #28                 // Method org/apache/hadoop/hbase/filter/BitComparator$BitwiseOp.ordinal:()I
      39: iaload
      40: tableswitch   { // 1 to 3
                     1: 68
                     2: 91
                     3: 114
               default: 134
          }
      68: aload_0
      69: getfield      #4                  // Field value:[B
      72: iload         5
      74: baload
      75: aload_1
      76: iload         5
      78: iload_2
      79: iadd
      80: baload
      81: iand
      82: sipush        255
      85: iand
      86: istore        4
      88: goto          134
      91: aload_0
      92: getfield      #4                  // Field value:[B
      95: iload         5
      97: baload
      98: aload_1
      99: iload         5
     101: iload_2
     102: iadd
     103: baload
     104: ior
     105: sipush        255
     108: iand
     109: istore        4
     111: goto          134
     114: aload_0
     115: getfield      #4                  // Field value:[B
     118: iload         5
     120: baload
     121: aload_1
     122: iload         5
     124: iload_2
     125: iadd
     126: baload
     127: ixor
     128: sipush        255
     131: iand
     132: istore        4
     134: iinc          5, -1
     137: goto          19
     140: iload         4
     142: ifne          149
     145: iconst_1
     146: goto          150
     149: iconst_0
     150: ireturn

  public int compareTo(java.nio.ByteBuffer, int, int);
    Code:
       0: iload_3
       1: aload_0
       2: getfield      #4                  // Field value:[B
       5: arraylength
       6: if_icmpeq     11
       9: iconst_1
      10: ireturn
      11: iconst_0
      12: istore        4
      14: iload_3
      15: iconst_1
      16: isub
      17: istore        5
      19: iload         5
      21: iflt          146
      24: iload         4
      26: ifne          146
      29: getstatic     #27                 // Field org/apache/hadoop/hbase/filter/BitComparator$1.$SwitchMap$org$apache$hadoop$hbase$filter$BitComparator$BitwiseOp:[I
      32: aload_0
      33: getfield      #2                  // Field bitOperator:Lorg/apache/hadoop/hbase/filter/BitComparator$BitwiseOp;
      36: invokevirtual #28                 // Method org/apache/hadoop/hbase/filter/BitComparator$BitwiseOp.ordinal:()I
      39: iaload
      40: tableswitch   { // 1 to 3
                     1: 68
                     2: 93
                     3: 118
               default: 140
          }
      68: aload_0
      69: getfield      #4                  // Field value:[B
      72: iload         5
      74: baload
      75: aload_1
      76: iload         5
      78: iload_2
      79: iadd
      80: invokevirtual #29                 // Method java/nio/ByteBuffer.get:(I)B
      83: iand
      84: sipush        255
      87: iand
      88: istore        4
      90: goto          140
      93: aload_0
      94: getfield      #4                  // Field value:[B
      97: iload         5
      99: baload
     100: aload_1
     101: iload         5
     103: iload_2
     104: iadd
     105: invokevirtual #29                 // Method java/nio/ByteBuffer.get:(I)B
     108: ior
     109: sipush        255
     112: iand
     113: istore        4
     115: goto          140
     118: aload_0
     119: getfield      #4                  // Field value:[B
     122: iload         5
     124: baload
     125: aload_1
     126: iload         5
     128: iload_2
     129: iadd
     130: invokevirtual #29                 // Method java/nio/ByteBuffer.get:(I)B
     133: ixor
     134: sipush        255
     137: iand
     138: istore        4
     140: iinc          5, -1
     143: goto          19
     146: iload         4
     148: ifne          155
     151: iconst_1
     152: goto          156
     155: iconst_0
     156: ireturn
}
