Compiled from "BlockCacheTmpl.java"
class org.apache.hadoop.hbase.tmpl.regionserver.BlockCacheTmpl$1 extends org.jamon.AbstractRenderer {
  final org.apache.hadoop.hbase.io.hfile.CacheConfig val$cacheConfig;

  final org.apache.hadoop.conf.Configuration val$config;

  final org.apache.hadoop.hbase.io.hfile.BlockCache val$bc;

  final org.apache.hadoop.hbase.tmpl.regionserver.BlockCacheTmpl this$0;

  org.apache.hadoop.hbase.tmpl.regionserver.BlockCacheTmpl$1(org.apache.hadoop.hbase.tmpl.regionserver.BlockCacheTmpl, org.apache.hadoop.hbase.io.hfile.CacheConfig, org.apache.hadoop.conf.Configuration, org.apache.hadoop.hbase.io.hfile.BlockCache);
    Code:
       0: aload_0
       1: aload_1
       2: putfield      #1                  // Field this$0:Lorg/apache/hadoop/hbase/tmpl/regionserver/BlockCacheTmpl;
       5: aload_0
       6: aload_2
       7: putfield      #2                  // Field val$cacheConfig:Lorg/apache/hadoop/hbase/io/hfile/CacheConfig;
      10: aload_0
      11: aload_3
      12: putfield      #3                  // Field val$config:Lorg/apache/hadoop/conf/Configuration;
      15: aload_0
      16: aload         4
      18: putfield      #4                  // Field val$bc:Lorg/apache/hadoop/hbase/io/hfile/BlockCache;
      21: aload_0
      22: invokespecial #5                  // Method org/jamon/AbstractRenderer."<init>":()V
      25: return

  public void renderTo(java.io.Writer) throws java.io.IOException;
    Code:
       0: aload_0
       1: getfield      #1                  // Field this$0:Lorg/apache/hadoop/hbase/tmpl/regionserver/BlockCacheTmpl;
       4: aload_1
       5: aload_0
       6: getfield      #2                  // Field val$cacheConfig:Lorg/apache/hadoop/hbase/io/hfile/CacheConfig;
       9: aload_0
      10: getfield      #3                  // Field val$config:Lorg/apache/hadoop/conf/Configuration;
      13: aload_0
      14: getfield      #4                  // Field val$bc:Lorg/apache/hadoop/hbase/io/hfile/BlockCache;
      17: invokevirtual #6                  // Method org/apache/hadoop/hbase/tmpl/regionserver/BlockCacheTmpl.render:(Ljava/io/Writer;Lorg/apache/hadoop/hbase/io/hfile/CacheConfig;Lorg/apache/hadoop/conf/Configuration;Lorg/apache/hadoop/hbase/io/hfile/BlockCache;)V
      20: return
}
