Compiled from "BlockingRpcClient.java"
public class org.apache.hadoop.hbase.ipc.BlockingRpcClient extends org.apache.hadoop.hbase.ipc.AbstractRpcClient<org.apache.hadoop.hbase.ipc.BlockingRpcConnection> {
  protected final javax.net.SocketFactory socketFactory;

  org.apache.hadoop.hbase.ipc.BlockingRpcClient(org.apache.hadoop.conf.Configuration);
    Code:
       0: aload_0
       1: aload_1
       2: ldc           #2                  // String default-cluster
       4: aconst_null
       5: aconst_null
       6: invokespecial #3                  // Method "<init>":(Lorg/apache/hadoop/conf/Configuration;Ljava/lang/String;Ljava/net/SocketAddress;Lorg/apache/hadoop/hbase/client/MetricsConnection;)V
       9: return

  public org.apache.hadoop.hbase.ipc.BlockingRpcClient(org.apache.hadoop.conf.Configuration, java.lang.String, java.net.SocketAddress, org.apache.hadoop.hbase.client.MetricsConnection);
    Code:
       0: aload_0
       1: aload_1
       2: aload_2
       3: aload_3
       4: aload         4
       6: invokespecial #4                  // Method org/apache/hadoop/hbase/ipc/AbstractRpcClient."<init>":(Lorg/apache/hadoop/conf/Configuration;Ljava/lang/String;Ljava/net/SocketAddress;Lorg/apache/hadoop/hbase/client/MetricsConnection;)V
       9: aload_0
      10: aload_1
      11: invokestatic  #5                  // Method org/apache/hadoop/net/NetUtils.getDefaultSocketFactory:(Lorg/apache/hadoop/conf/Configuration;)Ljavax/net/SocketFactory;
      14: putfield      #6                  // Field socketFactory:Ljavax/net/SocketFactory;
      17: return

  protected org.apache.hadoop.hbase.ipc.BlockingRpcConnection createConnection(org.apache.hadoop.hbase.ipc.ConnectionId) throws java.io.IOException;
    Code:
       0: new           #7                  // class org/apache/hadoop/hbase/ipc/BlockingRpcConnection
       3: dup
       4: aload_0
       5: aload_1
       6: invokespecial #8                  // Method org/apache/hadoop/hbase/ipc/BlockingRpcConnection."<init>":(Lorg/apache/hadoop/hbase/ipc/BlockingRpcClient;Lorg/apache/hadoop/hbase/ipc/ConnectionId;)V
       9: areturn

  protected void closeInternal();
    Code:
       0: return

  protected org.apache.hadoop.hbase.ipc.RpcConnection createConnection(org.apache.hadoop.hbase.ipc.ConnectionId) throws java.io.IOException;
    Code:
       0: aload_0
       1: aload_1
       2: invokevirtual #9                  // Method createConnection:(Lorg/apache/hadoop/hbase/ipc/ConnectionId;)Lorg/apache/hadoop/hbase/ipc/BlockingRpcConnection;
       5: areturn
}
