Compiled from "BlockCacheTmpl.java"
public class org.apache.hadoop.hbase.tmpl.regionserver.BlockCacheTmpl$ImplData extends org.jamon.AbstractTemplateProxy$ImplData {
  public org.apache.hadoop.hbase.tmpl.regionserver.BlockCacheTmpl$ImplData();
    Code:
       0: aload_0
       1: invokespecial #1                  // Method org/jamon/AbstractTemplateProxy$ImplData."<init>":()V
       4: return

  public void setCacheConfig(org.apache.hadoop.hbase.io.hfile.CacheConfig);
    Code:
       0: aload_0
       1: aload_1
       2: putfield      #2                  // Field m_cacheConfig:Lorg/apache/hadoop/hbase/io/hfile/CacheConfig;
       5: return

  public org.apache.hadoop.hbase.io.hfile.CacheConfig getCacheConfig();
    Code:
       0: aload_0
       1: getfield      #2                  // Field m_cacheConfig:Lorg/apache/hadoop/hbase/io/hfile/CacheConfig;
       4: areturn

  public void setConfig(org.apache.hadoop.conf.Configuration);
    Code:
       0: aload_0
       1: aload_1
       2: putfield      #3                  // Field m_config:Lorg/apache/hadoop/conf/Configuration;
       5: return

  public org.apache.hadoop.conf.Configuration getConfig();
    Code:
       0: aload_0
       1: getfield      #3                  // Field m_config:Lorg/apache/hadoop/conf/Configuration;
       4: areturn

  public void setBc(org.apache.hadoop.hbase.io.hfile.BlockCache);
    Code:
       0: aload_0
       1: aload_1
       2: putfield      #4                  // Field m_bc:Lorg/apache/hadoop/hbase/io/hfile/BlockCache;
       5: return

  public org.apache.hadoop.hbase.io.hfile.BlockCache getBc();
    Code:
       0: aload_0
       1: getfield      #4                  // Field m_bc:Lorg/apache/hadoop/hbase/io/hfile/BlockCache;
       4: areturn
}
