Compiled from "BlockCacheUtil.java"
class org.apache.hadoop.hbase.io.hfile.BlockCacheUtil$CachedBlockCountsPerFile {
  org.apache.hadoop.hbase.io.hfile.BlockCacheUtil$CachedBlockCountsPerFile(java.lang.String);
    Code:
       0: aload_0
       1: invokespecial #5                  // Method java/lang/Object."<init>":()V
       4: aload_0
       5: iconst_0
       6: putfield      #4                  // Field count:I
       9: aload_0
      10: lconst_0
      11: putfield      #3                  // Field size:J
      14: aload_0
      15: iconst_0
      16: putfield      #2                  // Field countData:I
      19: aload_0
      20: lconst_0
      21: putfield      #1                  // Field sizeData:J
      24: aload_0
      25: aload_1
      26: putfield      #6                  // Field filename:Ljava/lang/String;
      29: return

  public int getCount();
    Code:
       0: aload_0
       1: getfield      #4                  // Field count:I
       4: ireturn

  public long getSize();
    Code:
       0: aload_0
       1: getfield      #3                  // Field size:J
       4: lreturn

  public int getCountData();
    Code:
       0: aload_0
       1: getfield      #2                  // Field countData:I
       4: ireturn

  public long getSizeData();
    Code:
       0: aload_0
       1: getfield      #1                  // Field sizeData:J
       4: lreturn

  public java.lang.String getFilename();
    Code:
       0: aload_0
       1: getfield      #6                  // Field filename:Ljava/lang/String;
       4: areturn

  static int access$008(org.apache.hadoop.hbase.io.hfile.BlockCacheUtil$CachedBlockCountsPerFile);
    Code:
       0: aload_0
       1: dup
       2: getfield      #4                  // Field count:I
       5: dup_x1
       6: iconst_1
       7: iadd
       8: putfield      #4                  // Field count:I
      11: ireturn

  static long access$100(org.apache.hadoop.hbase.io.hfile.BlockCacheUtil$CachedBlockCountsPerFile);
    Code:
       0: aload_0
       1: getfield      #3                  // Field size:J
       4: lreturn

  static long access$102(org.apache.hadoop.hbase.io.hfile.BlockCacheUtil$CachedBlockCountsPerFile, long);
    Code:
       0: aload_0
       1: lload_1
       2: dup2_x1
       3: putfield      #3                  // Field size:J
       6: lreturn

  static int access$208(org.apache.hadoop.hbase.io.hfile.BlockCacheUtil$CachedBlockCountsPerFile);
    Code:
       0: aload_0
       1: dup
       2: getfield      #2                  // Field countData:I
       5: dup_x1
       6: iconst_1
       7: iadd
       8: putfield      #2                  // Field countData:I
      11: ireturn

  static long access$300(org.apache.hadoop.hbase.io.hfile.BlockCacheUtil$CachedBlockCountsPerFile);
    Code:
       0: aload_0
       1: getfield      #1                  // Field sizeData:J
       4: lreturn

  static long access$302(org.apache.hadoop.hbase.io.hfile.BlockCacheUtil$CachedBlockCountsPerFile, long);
    Code:
       0: aload_0
       1: lload_1
       2: dup2_x1
       3: putfield      #1                  // Field sizeData:J
       6: lreturn
}
