Compiled from "BlockingRpcConnection.java"
class org.apache.hadoop.hbase.ipc.BlockingRpcConnection$2 implements java.security.PrivilegedExceptionAction<java.lang.Boolean> {
  final java.io.InputStream val$in2;

  final java.io.OutputStream val$out2;

  final org.apache.hadoop.hbase.ipc.BlockingRpcConnection this$0;

  org.apache.hadoop.hbase.ipc.BlockingRpcConnection$2(org.apache.hadoop.hbase.ipc.BlockingRpcConnection, java.io.InputStream, java.io.OutputStream);
    Code:
       0: aload_0
       1: aload_1
       2: putfield      #1                  // Field this$0:Lorg/apache/hadoop/hbase/ipc/BlockingRpcConnection;
       5: aload_0
       6: aload_2
       7: putfield      #2                  // Field val$in2:Ljava/io/InputStream;
      10: aload_0
      11: aload_3
      12: putfield      #3                  // Field val$out2:Ljava/io/OutputStream;
      15: aload_0
      16: invokespecial #4                  // Method java/lang/Object."<init>":()V
      19: return

  public java.lang.Boolean run() throws java.io.IOException;
    Code:
       0: aload_0
       1: getfield      #1                  // Field this$0:Lorg/apache/hadoop/hbase/ipc/BlockingRpcConnection;
       4: aload_0
       5: getfield      #2                  // Field val$in2:Ljava/io/InputStream;
       8: aload_0
       9: getfield      #3                  // Field val$out2:Ljava/io/OutputStream;
      12: invokestatic  #5                  // Method org/apache/hadoop/hbase/ipc/BlockingRpcConnection.access$600:(Lorg/apache/hadoop/hbase/ipc/BlockingRpcConnection;Ljava/io/InputStream;Ljava/io/OutputStream;)Z
      15: invokestatic  #6                  // Method java/lang/Boolean.valueOf:(Z)Ljava/lang/Boolean;
      18: areturn

  public java.lang.Object run() throws java.lang.Exception;
    Code:
       0: aload_0
       1: invokevirtual #7                  // Method run:()Ljava/lang/Boolean;
       4: areturn
}
