Compiled from "BlockType.java"
public class org.apache.hadoop.hbase.io.hfile.BlockType extends java.lang.Enum<org.apache.hadoop.hbase.io.hfile.BlockType> {
  public static final org.apache.hadoop.hbase.io.hfile.BlockType DATA;

  public static final org.apache.hadoop.hbase.io.hfile.BlockType ENCODED_DATA;

  public static final org.apache.hadoop.hbase.io.hfile.BlockType LEAF_INDEX;

  public static final org.apache.hadoop.hbase.io.hfile.BlockType BLOOM_CHUNK;

  public static final org.apache.hadoop.hbase.io.hfile.BlockType META;

  public static final org.apache.hadoop.hbase.io.hfile.BlockType INTERMEDIATE_INDEX;

  public static final org.apache.hadoop.hbase.io.hfile.BlockType ROOT_INDEX;

  public static final org.apache.hadoop.hbase.io.hfile.BlockType FILE_INFO;

  public static final org.apache.hadoop.hbase.io.hfile.BlockType GENERAL_BLOOM_META;

  public static final org.apache.hadoop.hbase.io.hfile.BlockType DELETE_FAMILY_BLOOM_META;

  public static final org.apache.hadoop.hbase.io.hfile.BlockType TRAILER;

  public static final org.apache.hadoop.hbase.io.hfile.BlockType INDEX_V1;

  public static final int MAGIC_LENGTH;

  static final boolean $assertionsDisabled;

  public static org.apache.hadoop.hbase.io.hfile.BlockType[] values();
    Code:
       0: getstatic     #2                  // Field $VALUES:[Lorg/apache/hadoop/hbase/io/hfile/BlockType;
       3: invokevirtual #3                  // Method "[Lorg/apache/hadoop/hbase/io/hfile/BlockType;".clone:()Ljava/lang/Object;
       6: checkcast     #4                  // class "[Lorg/apache/hadoop/hbase/io/hfile/BlockType;"
       9: areturn

  public static org.apache.hadoop.hbase.io.hfile.BlockType valueOf(java.lang.String);
    Code:
       0: ldc           #5                  // class org/apache/hadoop/hbase/io/hfile/BlockType
       2: aload_0
       3: invokestatic  #6                  // Method java/lang/Enum.valueOf:(Ljava/lang/Class;Ljava/lang/String;)Ljava/lang/Enum;
       6: checkcast     #5                  // class org/apache/hadoop/hbase/io/hfile/BlockType
       9: areturn

  public int getId();
    Code:
       0: aload_0
       1: invokevirtual #14                 // Method ordinal:()I
       4: ireturn

  public void writeToStream(java.io.OutputStream) throws java.io.IOException;
    Code:
       0: aload_1
       1: aload_0
       2: getfield      #9                  // Field magic:[B
       5: invokevirtual #15                 // Method java/io/OutputStream.write:([B)V
       8: return

  public void write(java.io.DataOutput) throws java.io.IOException;
    Code:
       0: aload_1
       1: aload_0
       2: getfield      #9                  // Field magic:[B
       5: invokeinterface #16,  2           // InterfaceMethod java/io/DataOutput.write:([B)V
      10: return

  public void write(java.nio.ByteBuffer);
    Code:
       0: aload_1
       1: aload_0
       2: getfield      #9                  // Field magic:[B
       5: invokevirtual #17                 // Method java/nio/ByteBuffer.put:([B)Ljava/nio/ByteBuffer;
       8: pop
       9: return

  public void write(org.apache.hadoop.hbase.nio.ByteBuff);
    Code:
       0: aload_1
       1: aload_0
       2: getfield      #9                  // Field magic:[B
       5: invokevirtual #18                 // Method org/apache/hadoop/hbase/nio/ByteBuff.put:([B)Lorg/apache/hadoop/hbase/nio/ByteBuff;
       8: pop
       9: return

  public org.apache.hadoop.hbase.io.hfile.BlockType$BlockCategory getCategory();
    Code:
       0: aload_0
       1: getfield      #10                 // Field metricCat:Lorg/apache/hadoop/hbase/io/hfile/BlockType$BlockCategory;
       4: areturn

  public static org.apache.hadoop.hbase.io.hfile.BlockType parse(byte[], int, int) throws java.io.IOException;
    Code:
       0: iload_2
       1: bipush        8
       3: if_icmpeq     38
       6: new           #19                 // class java/io/IOException
       9: dup
      10: new           #20                 // class java/lang/StringBuilder
      13: dup
      14: invokespecial #21                 // Method java/lang/StringBuilder."<init>":()V
      17: ldc           #22                 // String Magic record of invalid length:
      19: invokevirtual #23                 // Method java/lang/StringBuilder.append:(Ljava/lang/String;)Ljava/lang/StringBuilder;
      22: aload_0
      23: iload_1
      24: iload_2
      25: invokestatic  #24                 // Method org/apache/hadoop/hbase/util/Bytes.toStringBinary:([BII)Ljava/lang/String;
      28: invokevirtual #23                 // Method java/lang/StringBuilder.append:(Ljava/lang/String;)Ljava/lang/StringBuilder;
      31: invokevirtual #25                 // Method java/lang/StringBuilder.toString:()Ljava/lang/String;
      34: invokespecial #26                 // Method java/io/IOException."<init>":(Ljava/lang/String;)V
      37: athrow
      38: invokestatic  #27                 // Method values:()[Lorg/apache/hadoop/hbase/io/hfile/BlockType;
      41: astore_3
      42: aload_3
      43: arraylength
      44: istore        4
      46: iconst_0
      47: istore        5
      49: iload         5
      51: iload         4
      53: if_icmpge     89
      56: aload_3
      57: iload         5
      59: aaload
      60: astore        6
      62: aload         6
      64: getfield      #9                  // Field magic:[B
      67: iconst_0
      68: bipush        8
      70: aload_0
      71: iload_1
      72: bipush        8
      74: invokestatic  #28                 // Method org/apache/hadoop/hbase/util/Bytes.compareTo:([BII[BII)I
      77: ifne          83
      80: aload         6
      82: areturn
      83: iinc          5, 1
      86: goto          49
      89: new           #19                 // class java/io/IOException
      92: dup
      93: new           #20                 // class java/lang/StringBuilder
      96: dup
      97: invokespecial #21                 // Method java/lang/StringBuilder."<init>":()V
     100: ldc           #29                 // String Invalid HFile block magic:
     102: invokevirtual #23                 // Method java/lang/StringBuilder.append:(Ljava/lang/String;)Ljava/lang/StringBuilder;
     105: aload_0
     106: iload_1
     107: bipush        8
     109: invokestatic  #24                 // Method org/apache/hadoop/hbase/util/Bytes.toStringBinary:([BII)Ljava/lang/String;
     112: invokevirtual #23                 // Method java/lang/StringBuilder.append:(Ljava/lang/String;)Ljava/lang/StringBuilder;
     115: invokevirtual #25                 // Method java/lang/StringBuilder.toString:()Ljava/lang/String;
     118: invokespecial #26                 // Method java/io/IOException."<init>":(Ljava/lang/String;)V
     121: athrow

  public static org.apache.hadoop.hbase.io.hfile.BlockType read(java.io.DataInputStream) throws java.io.IOException;
    Code:
       0: bipush        8
       2: newarray       byte
       4: astore_1
       5: aload_0
       6: aload_1
       7: invokevirtual #30                 // Method java/io/DataInputStream.readFully:([B)V
      10: aload_1
      11: iconst_0
      12: aload_1
      13: arraylength
      14: invokestatic  #31                 // Method parse:([BII)Lorg/apache/hadoop/hbase/io/hfile/BlockType;
      17: areturn

  public static org.apache.hadoop.hbase.io.hfile.BlockType read(org.apache.hadoop.hbase.nio.ByteBuff) throws java.io.IOException;
    Code:
       0: aload_0
       1: invokevirtual #32                 // Method org/apache/hadoop/hbase/nio/ByteBuff.limit:()I
       4: aload_0
       5: invokevirtual #33                 // Method org/apache/hadoop/hbase/nio/ByteBuff.position:()I
       8: isub
       9: bipush        8
      11: invokestatic  #34                 // Method java/lang/Math.min:(II)I
      14: newarray       byte
      16: astore_1
      17: aload_0
      18: aload_1
      19: invokevirtual #35                 // Method org/apache/hadoop/hbase/nio/ByteBuff.get:([B)V
      22: aload_1
      23: iconst_0
      24: aload_1
      25: arraylength
      26: invokestatic  #31                 // Method parse:([BII)Lorg/apache/hadoop/hbase/io/hfile/BlockType;
      29: astore_2
      30: aload_2
      31: areturn

  public int put(byte[], int);
    Code:
       0: aload_0
       1: getfield      #9                  // Field magic:[B
       4: iconst_0
       5: aload_1
       6: iload_2
       7: bipush        8
       9: invokestatic  #36                 // Method java/lang/System.arraycopy:(Ljava/lang/Object;ILjava/lang/Object;II)V
      12: iload_2
      13: bipush        8
      15: iadd
      16: ireturn

  public void readAndCheck(java.io.DataInputStream) throws java.io.IOException;
    Code:
       0: bipush        8
       2: newarray       byte
       4: astore_2
       5: aload_1
       6: aload_2
       7: invokevirtual #30                 // Method java/io/DataInputStream.readFully:([B)V
      10: aload_2
      11: aload_0
      12: getfield      #9                  // Field magic:[B
      15: invokestatic  #37                 // Method org/apache/hadoop/hbase/util/Bytes.compareTo:([B[B)I
      18: ifeq          66
      21: new           #19                 // class java/io/IOException
      24: dup
      25: new           #20                 // class java/lang/StringBuilder
      28: dup
      29: invokespecial #21                 // Method java/lang/StringBuilder."<init>":()V
      32: ldc           #38                 // String Invalid magic: expected
      34: invokevirtual #23                 // Method java/lang/StringBuilder.append:(Ljava/lang/String;)Ljava/lang/StringBuilder;
      37: aload_0
      38: getfield      #9                  // Field magic:[B
      41: invokestatic  #39                 // Method org/apache/hadoop/hbase/util/Bytes.toStringBinary:([B)Ljava/lang/String;
      44: invokevirtual #23                 // Method java/lang/StringBuilder.append:(Ljava/lang/String;)Ljava/lang/StringBuilder;
      47: ldc           #40                 // String , got
      49: invokevirtual #23                 // Method java/lang/StringBuilder.append:(Ljava/lang/String;)Ljava/lang/StringBuilder;
      52: aload_2
      53: invokestatic  #39                 // Method org/apache/hadoop/hbase/util/Bytes.toStringBinary:([B)Ljava/lang/String;
      56: invokevirtual #23                 // Method java/lang/StringBuilder.append:(Ljava/lang/String;)Ljava/lang/StringBuilder;
      59: invokevirtual #25                 // Method java/lang/StringBuilder.toString:()Ljava/lang/String;
      62: invokespecial #26                 // Method java/io/IOException."<init>":(Ljava/lang/String;)V
      65: athrow
      66: return

  public void readAndCheck(java.nio.ByteBuffer) throws java.io.IOException;
    Code:
       0: bipush        8
       2: newarray       byte
       4: astore_2
       5: aload_1
       6: aload_2
       7: invokevirtual #41                 // Method java/nio/ByteBuffer.get:([B)Ljava/nio/ByteBuffer;
      10: pop
      11: aload_2
      12: aload_0
      13: getfield      #9                  // Field magic:[B
      16: invokestatic  #37                 // Method org/apache/hadoop/hbase/util/Bytes.compareTo:([B[B)I
      19: ifeq          67
      22: new           #19                 // class java/io/IOException
      25: dup
      26: new           #20                 // class java/lang/StringBuilder
      29: dup
      30: invokespecial #21                 // Method java/lang/StringBuilder."<init>":()V
      33: ldc           #38                 // String Invalid magic: expected
      35: invokevirtual #23                 // Method java/lang/StringBuilder.append:(Ljava/lang/String;)Ljava/lang/StringBuilder;
      38: aload_0
      39: getfield      #9                  // Field magic:[B
      42: invokestatic  #39                 // Method org/apache/hadoop/hbase/util/Bytes.toStringBinary:([B)Ljava/lang/String;
      45: invokevirtual #23                 // Method java/lang/StringBuilder.append:(Ljava/lang/String;)Ljava/lang/StringBuilder;
      48: ldc           #40                 // String , got
      50: invokevirtual #23                 // Method java/lang/StringBuilder.append:(Ljava/lang/String;)Ljava/lang/StringBuilder;
      53: aload_2
      54: invokestatic  #39                 // Method org/apache/hadoop/hbase/util/Bytes.toStringBinary:([B)Ljava/lang/String;
      57: invokevirtual #23                 // Method java/lang/StringBuilder.append:(Ljava/lang/String;)Ljava/lang/StringBuilder;
      60: invokevirtual #25                 // Method java/lang/StringBuilder.toString:()Ljava/lang/String;
      63: invokespecial #26                 // Method java/io/IOException."<init>":(Ljava/lang/String;)V
      66: athrow
      67: return

  public final boolean isData();
    Code:
       0: aload_0
       1: getstatic     #42                 // Field DATA:Lorg/apache/hadoop/hbase/io/hfile/BlockType;
       4: if_acmpeq     14
       7: aload_0
       8: getstatic     #43                 // Field ENCODED_DATA:Lorg/apache/hadoop/hbase/io/hfile/BlockType;
      11: if_acmpne     18
      14: iconst_1
      15: goto          19
      18: iconst_0
      19: ireturn

  org.apache.hadoop.hbase.io.hfile.BlockType(java.lang.String, int, java.lang.String, org.apache.hadoop.hbase.io.hfile.BlockType$BlockCategory, org.apache.hadoop.hbase.io.hfile.BlockType$1);
    Code:
       0: aload_0
       1: aload_1
       2: iload_2
       3: aload_3
       4: aload         4
       6: invokespecial #1                  // Method "<init>":(Ljava/lang/String;ILjava/lang/String;Lorg/apache/hadoop/hbase/io/hfile/BlockType$BlockCategory;)V
       9: return

  static {};
    Code:
       0: ldc           #5                  // class org/apache/hadoop/hbase/io/hfile/BlockType
       2: invokevirtual #44                 // Method java/lang/Class.desiredAssertionStatus:()Z
       5: ifne          12
       8: iconst_1
       9: goto          13
      12: iconst_0
      13: putstatic     #11                 // Field $assertionsDisabled:Z
      16: new           #5                  // class org/apache/hadoop/hbase/io/hfile/BlockType
      19: dup
      20: ldc           #45                 // String DATA
      22: iconst_0
      23: ldc           #46                 // String DATABLK*
      25: getstatic     #47                 // Field org/apache/hadoop/hbase/io/hfile/BlockType$BlockCategory.DATA:Lorg/apache/hadoop/hbase/io/hfile/BlockType$BlockCategory;
      28: invokespecial #1                  // Method "<init>":(Ljava/lang/String;ILjava/lang/String;Lorg/apache/hadoop/hbase/io/hfile/BlockType$BlockCategory;)V
      31: putstatic     #42                 // Field DATA:Lorg/apache/hadoop/hbase/io/hfile/BlockType;
      34: new           #48                 // class org/apache/hadoop/hbase/io/hfile/BlockType$1
      37: dup
      38: ldc           #49                 // String ENCODED_DATA
      40: iconst_1
      41: ldc           #50                 // String DATABLKE
      43: getstatic     #47                 // Field org/apache/hadoop/hbase/io/hfile/BlockType$BlockCategory.DATA:Lorg/apache/hadoop/hbase/io/hfile/BlockType$BlockCategory;
      46: invokespecial #51                 // Method org/apache/hadoop/hbase/io/hfile/BlockType$1."<init>":(Ljava/lang/String;ILjava/lang/String;Lorg/apache/hadoop/hbase/io/hfile/BlockType$BlockCategory;)V
      49: putstatic     #43                 // Field ENCODED_DATA:Lorg/apache/hadoop/hbase/io/hfile/BlockType;
      52: new           #5                  // class org/apache/hadoop/hbase/io/hfile/BlockType
      55: dup
      56: ldc           #52                 // String LEAF_INDEX
      58: iconst_2
      59: ldc           #53                 // String IDXLEAF2
      61: getstatic     #54                 // Field org/apache/hadoop/hbase/io/hfile/BlockType$BlockCategory.INDEX:Lorg/apache/hadoop/hbase/io/hfile/BlockType$BlockCategory;
      64: invokespecial #1                  // Method "<init>":(Ljava/lang/String;ILjava/lang/String;Lorg/apache/hadoop/hbase/io/hfile/BlockType$BlockCategory;)V
      67: putstatic     #55                 // Field LEAF_INDEX:Lorg/apache/hadoop/hbase/io/hfile/BlockType;
      70: new           #5                  // class org/apache/hadoop/hbase/io/hfile/BlockType
      73: dup
      74: ldc           #56                 // String BLOOM_CHUNK
      76: iconst_3
      77: ldc           #57                 // String BLMFBLK2
      79: getstatic     #58                 // Field org/apache/hadoop/hbase/io/hfile/BlockType$BlockCategory.BLOOM:Lorg/apache/hadoop/hbase/io/hfile/BlockType$BlockCategory;
      82: invokespecial #1                  // Method "<init>":(Ljava/lang/String;ILjava/lang/String;Lorg/apache/hadoop/hbase/io/hfile/BlockType$BlockCategory;)V
      85: putstatic     #59                 // Field BLOOM_CHUNK:Lorg/apache/hadoop/hbase/io/hfile/BlockType;
      88: new           #5                  // class org/apache/hadoop/hbase/io/hfile/BlockType
      91: dup
      92: ldc           #60                 // String META
      94: iconst_4
      95: ldc           #61                 // String METABLKc
      97: getstatic     #62                 // Field org/apache/hadoop/hbase/io/hfile/BlockType$BlockCategory.META:Lorg/apache/hadoop/hbase/io/hfile/BlockType$BlockCategory;
     100: invokespecial #1                  // Method "<init>":(Ljava/lang/String;ILjava/lang/String;Lorg/apache/hadoop/hbase/io/hfile/BlockType$BlockCategory;)V
     103: putstatic     #63                 // Field META:Lorg/apache/hadoop/hbase/io/hfile/BlockType;
     106: new           #5                  // class org/apache/hadoop/hbase/io/hfile/BlockType
     109: dup
     110: ldc           #64                 // String INTERMEDIATE_INDEX
     112: iconst_5
     113: ldc           #65                 // String IDXINTE2
     115: getstatic     #54                 // Field org/apache/hadoop/hbase/io/hfile/BlockType$BlockCategory.INDEX:Lorg/apache/hadoop/hbase/io/hfile/BlockType$BlockCategory;
     118: invokespecial #1                  // Method "<init>":(Ljava/lang/String;ILjava/lang/String;Lorg/apache/hadoop/hbase/io/hfile/BlockType$BlockCategory;)V
     121: putstatic     #66                 // Field INTERMEDIATE_INDEX:Lorg/apache/hadoop/hbase/io/hfile/BlockType;
     124: new           #5                  // class org/apache/hadoop/hbase/io/hfile/BlockType
     127: dup
     128: ldc           #67                 // String ROOT_INDEX
     130: bipush        6
     132: ldc           #68                 // String IDXROOT2
     134: getstatic     #54                 // Field org/apache/hadoop/hbase/io/hfile/BlockType$BlockCategory.INDEX:Lorg/apache/hadoop/hbase/io/hfile/BlockType$BlockCategory;
     137: invokespecial #1                  // Method "<init>":(Ljava/lang/String;ILjava/lang/String;Lorg/apache/hadoop/hbase/io/hfile/BlockType$BlockCategory;)V
     140: putstatic     #69                 // Field ROOT_INDEX:Lorg/apache/hadoop/hbase/io/hfile/BlockType;
     143: new           #5                  // class org/apache/hadoop/hbase/io/hfile/BlockType
     146: dup
     147: ldc           #70                 // String FILE_INFO
     149: bipush        7
     151: ldc           #71                 // String FILEINF2
     153: getstatic     #62                 // Field org/apache/hadoop/hbase/io/hfile/BlockType$BlockCategory.META:Lorg/apache/hadoop/hbase/io/hfile/BlockType$BlockCategory;
     156: invokespecial #1                  // Method "<init>":(Ljava/lang/String;ILjava/lang/String;Lorg/apache/hadoop/hbase/io/hfile/BlockType$BlockCategory;)V
     159: putstatic     #72                 // Field FILE_INFO:Lorg/apache/hadoop/hbase/io/hfile/BlockType;
     162: new           #5                  // class org/apache/hadoop/hbase/io/hfile/BlockType
     165: dup
     166: ldc           #73                 // String GENERAL_BLOOM_META
     168: bipush        8
     170: ldc           #74                 // String BLMFMET2
     172: getstatic     #58                 // Field org/apache/hadoop/hbase/io/hfile/BlockType$BlockCategory.BLOOM:Lorg/apache/hadoop/hbase/io/hfile/BlockType$BlockCategory;
     175: invokespecial #1                  // Method "<init>":(Ljava/lang/String;ILjava/lang/String;Lorg/apache/hadoop/hbase/io/hfile/BlockType$BlockCategory;)V
     178: putstatic     #75                 // Field GENERAL_BLOOM_META:Lorg/apache/hadoop/hbase/io/hfile/BlockType;
     181: new           #5                  // class org/apache/hadoop/hbase/io/hfile/BlockType
     184: dup
     185: ldc           #76                 // String DELETE_FAMILY_BLOOM_META
     187: bipush        9
     189: ldc           #77                 // String DFBLMET2
     191: getstatic     #58                 // Field org/apache/hadoop/hbase/io/hfile/BlockType$BlockCategory.BLOOM:Lorg/apache/hadoop/hbase/io/hfile/BlockType$BlockCategory;
     194: invokespecial #1                  // Method "<init>":(Ljava/lang/String;ILjava/lang/String;Lorg/apache/hadoop/hbase/io/hfile/BlockType$BlockCategory;)V
     197: putstatic     #78                 // Field DELETE_FAMILY_BLOOM_META:Lorg/apache/hadoop/hbase/io/hfile/BlockType;
     200: new           #5                  // class org/apache/hadoop/hbase/io/hfile/BlockType
     203: dup
     204: ldc           #79                 // String TRAILER
     206: bipush        10
     208: ldc           #80                 // String TRABLK\"$
     210: getstatic     #62                 // Field org/apache/hadoop/hbase/io/hfile/BlockType$BlockCategory.META:Lorg/apache/hadoop/hbase/io/hfile/BlockType$BlockCategory;
     213: invokespecial #1                  // Method "<init>":(Ljava/lang/String;ILjava/lang/String;Lorg/apache/hadoop/hbase/io/hfile/BlockType$BlockCategory;)V
     216: putstatic     #81                 // Field TRAILER:Lorg/apache/hadoop/hbase/io/hfile/BlockType;
     219: new           #5                  // class org/apache/hadoop/hbase/io/hfile/BlockType
     222: dup
     223: ldc           #82                 // String INDEX_V1
     225: bipush        11
     227: ldc           #83                 // String IDXBLK)+
     229: getstatic     #54                 // Field org/apache/hadoop/hbase/io/hfile/BlockType$BlockCategory.INDEX:Lorg/apache/hadoop/hbase/io/hfile/BlockType$BlockCategory;
     232: invokespecial #1                  // Method "<init>":(Ljava/lang/String;ILjava/lang/String;Lorg/apache/hadoop/hbase/io/hfile/BlockType$BlockCategory;)V
     235: putstatic     #84                 // Field INDEX_V1:Lorg/apache/hadoop/hbase/io/hfile/BlockType;
     238: bipush        12
     240: anewarray     #5                  // class org/apache/hadoop/hbase/io/hfile/BlockType
     243: dup
     244: iconst_0
     245: getstatic     #42                 // Field DATA:Lorg/apache/hadoop/hbase/io/hfile/BlockType;
     248: aastore
     249: dup
     250: iconst_1
     251: getstatic     #43                 // Field ENCODED_DATA:Lorg/apache/hadoop/hbase/io/hfile/BlockType;
     254: aastore
     255: dup
     256: iconst_2
     257: getstatic     #55                 // Field LEAF_INDEX:Lorg/apache/hadoop/hbase/io/hfile/BlockType;
     260: aastore
     261: dup
     262: iconst_3
     263: getstatic     #59                 // Field BLOOM_CHUNK:Lorg/apache/hadoop/hbase/io/hfile/BlockType;
     266: aastore
     267: dup
     268: iconst_4
     269: getstatic     #63                 // Field META:Lorg/apache/hadoop/hbase/io/hfile/BlockType;
     272: aastore
     273: dup
     274: iconst_5
     275: getstatic     #66                 // Field INTERMEDIATE_INDEX:Lorg/apache/hadoop/hbase/io/hfile/BlockType;
     278: aastore
     279: dup
     280: bipush        6
     282: getstatic     #69                 // Field ROOT_INDEX:Lorg/apache/hadoop/hbase/io/hfile/BlockType;
     285: aastore
     286: dup
     287: bipush        7
     289: getstatic     #72                 // Field FILE_INFO:Lorg/apache/hadoop/hbase/io/hfile/BlockType;
     292: aastore
     293: dup
     294: bipush        8
     296: getstatic     #75                 // Field GENERAL_BLOOM_META:Lorg/apache/hadoop/hbase/io/hfile/BlockType;
     299: aastore
     300: dup
     301: bipush        9
     303: getstatic     #78                 // Field DELETE_FAMILY_BLOOM_META:Lorg/apache/hadoop/hbase/io/hfile/BlockType;
     306: aastore
     307: dup
     308: bipush        10
     310: getstatic     #81                 // Field TRAILER:Lorg/apache/hadoop/hbase/io/hfile/BlockType;
     313: aastore
     314: dup
     315: bipush        11
     317: getstatic     #84                 // Field INDEX_V1:Lorg/apache/hadoop/hbase/io/hfile/BlockType;
     320: aastore
     321: putstatic     #2                  // Field $VALUES:[Lorg/apache/hadoop/hbase/io/hfile/BlockType;
     324: return
}
