Compiled from "BlockCacheViewTmpl.java"
class org.apache.hadoop.hbase.tmpl.regionserver.BlockCacheViewTmpl$1 extends org.jamon.AbstractRenderer {
  final org.apache.hadoop.hbase.io.hfile.CacheConfig val$cacheConfig;

  final org.apache.hadoop.conf.Configuration val$conf;

  final java.lang.String val$bcn;

  final java.lang.String val$bcv;

  final org.apache.hadoop.hbase.io.hfile.BlockCache val$blockCache;

  final org.apache.hadoop.hbase.tmpl.regionserver.BlockCacheViewTmpl this$0;

  org.apache.hadoop.hbase.tmpl.regionserver.BlockCacheViewTmpl$1(org.apache.hadoop.hbase.tmpl.regionserver.BlockCacheViewTmpl, org.apache.hadoop.hbase.io.hfile.CacheConfig, org.apache.hadoop.conf.Configuration, java.lang.String, java.lang.String, org.apache.hadoop.hbase.io.hfile.BlockCache);
    Code:
       0: aload_0
       1: aload_1
       2: putfield      #1                  // Field this$0:Lorg/apache/hadoop/hbase/tmpl/regionserver/BlockCacheViewTmpl;
       5: aload_0
       6: aload_2
       7: putfield      #2                  // Field val$cacheConfig:Lorg/apache/hadoop/hbase/io/hfile/CacheConfig;
      10: aload_0
      11: aload_3
      12: putfield      #3                  // Field val$conf:Lorg/apache/hadoop/conf/Configuration;
      15: aload_0
      16: aload         4
      18: putfield      #4                  // Field val$bcn:Ljava/lang/String;
      21: aload_0
      22: aload         5
      24: putfield      #5                  // Field val$bcv:Ljava/lang/String;
      27: aload_0
      28: aload         6
      30: putfield      #6                  // Field val$blockCache:Lorg/apache/hadoop/hbase/io/hfile/BlockCache;
      33: aload_0
      34: invokespecial #7                  // Method org/jamon/AbstractRenderer."<init>":()V
      37: return

  public void renderTo(java.io.Writer) throws java.io.IOException;
    Code:
       0: aload_0
       1: getfield      #1                  // Field this$0:Lorg/apache/hadoop/hbase/tmpl/regionserver/BlockCacheViewTmpl;
       4: aload_1
       5: aload_0
       6: getfield      #2                  // Field val$cacheConfig:Lorg/apache/hadoop/hbase/io/hfile/CacheConfig;
       9: aload_0
      10: getfield      #3                  // Field val$conf:Lorg/apache/hadoop/conf/Configuration;
      13: aload_0
      14: getfield      #4                  // Field val$bcn:Ljava/lang/String;
      17: aload_0
      18: getfield      #5                  // Field val$bcv:Ljava/lang/String;
      21: aload_0
      22: getfield      #6                  // Field val$blockCache:Lorg/apache/hadoop/hbase/io/hfile/BlockCache;
      25: invokevirtual #8                  // Method org/apache/hadoop/hbase/tmpl/regionserver/BlockCacheViewTmpl.render:(Ljava/io/Writer;Lorg/apache/hadoop/hbase/io/hfile/CacheConfig;Lorg/apache/hadoop/conf/Configuration;Ljava/lang/String;Ljava/lang/String;Lorg/apache/hadoop/hbase/io/hfile/BlockCache;)V
      28: return
}
