Compiled from "BlockCachesIterator.java"
class org.apache.hadoop.hbase.io.hfile.BlockCachesIterator implements java.util.Iterator<org.apache.hadoop.hbase.io.hfile.CachedBlock> {
  int index;

  final org.apache.hadoop.hbase.io.hfile.BlockCache[] bcs;

  java.util.Iterator<org.apache.hadoop.hbase.io.hfile.CachedBlock> current;

  org.apache.hadoop.hbase.io.hfile.BlockCachesIterator(org.apache.hadoop.hbase.io.hfile.BlockCache[]);
    Code:
       0: aload_0
       1: invokespecial #1                  // Method java/lang/Object."<init>":()V
       4: aload_0
       5: iconst_0
       6: putfield      #2                  // Field index:I
       9: aload_0
      10: aload_1
      11: putfield      #3                  // Field bcs:[Lorg/apache/hadoop/hbase/io/hfile/BlockCache;
      14: aload_0
      15: aload_0
      16: getfield      #3                  // Field bcs:[Lorg/apache/hadoop/hbase/io/hfile/BlockCache;
      19: aload_0
      20: getfield      #2                  // Field index:I
      23: aaload
      24: invokeinterface #4,  1            // InterfaceMethod org/apache/hadoop/hbase/io/hfile/BlockCache.iterator:()Ljava/util/Iterator;
      29: putfield      #5                  // Field current:Ljava/util/Iterator;
      32: return

  public boolean hasNext();
    Code:
       0: aload_0
       1: getfield      #5                  // Field current:Ljava/util/Iterator;
       4: invokeinterface #6,  1            // InterfaceMethod java/util/Iterator.hasNext:()Z
       9: ifeq          14
      12: iconst_1
      13: ireturn
      14: aload_0
      15: dup
      16: getfield      #2                  // Field index:I
      19: iconst_1
      20: iadd
      21: putfield      #2                  // Field index:I
      24: aload_0
      25: getfield      #2                  // Field index:I
      28: aload_0
      29: getfield      #3                  // Field bcs:[Lorg/apache/hadoop/hbase/io/hfile/BlockCache;
      32: arraylength
      33: if_icmplt     38
      36: iconst_0
      37: ireturn
      38: aload_0
      39: aload_0
      40: getfield      #3                  // Field bcs:[Lorg/apache/hadoop/hbase/io/hfile/BlockCache;
      43: aload_0
      44: getfield      #2                  // Field index:I
      47: aaload
      48: invokeinterface #4,  1            // InterfaceMethod org/apache/hadoop/hbase/io/hfile/BlockCache.iterator:()Ljava/util/Iterator;
      53: putfield      #5                  // Field current:Ljava/util/Iterator;
      56: aload_0
      57: invokevirtual #7                  // Method hasNext:()Z
      60: ireturn

  public org.apache.hadoop.hbase.io.hfile.CachedBlock next();
    Code:
       0: aload_0
       1: getfield      #5                  // Field current:Ljava/util/Iterator;
       4: invokeinterface #8,  1            // InterfaceMethod java/util/Iterator.next:()Ljava/lang/Object;
       9: checkcast     #9                  // class org/apache/hadoop/hbase/io/hfile/CachedBlock
      12: areturn

  public void remove();
    Code:
       0: new           #10                 // class java/lang/UnsupportedOperationException
       3: dup
       4: invokespecial #11                 // Method java/lang/UnsupportedOperationException."<init>":()V
       7: athrow

  public java.lang.Object next();
    Code:
       0: aload_0
       1: invokevirtual #12                 // Method next:()Lorg/apache/hadoop/hbase/io/hfile/CachedBlock;
       4: areturn
}
