Compiled from "BloomType.java"
public final class org.apache.hadoop.hbase.regionserver.BloomType extends java.lang.Enum<org.apache.hadoop.hbase.regionserver.BloomType> {
  public static final org.apache.hadoop.hbase.regionserver.BloomType NONE;

  public static final org.apache.hadoop.hbase.regionserver.BloomType ROW;

  public static final org.apache.hadoop.hbase.regionserver.BloomType ROWCOL;

  public static final org.apache.hadoop.hbase.regionserver.BloomType ROWPREFIX_FIXED_LENGTH;

  public static org.apache.hadoop.hbase.regionserver.BloomType[] values();
    Code:
       0: getstatic     #1                  // Field $VALUES:[Lorg/apache/hadoop/hbase/regionserver/BloomType;
       3: invokevirtual #2                  // Method "[Lorg/apache/hadoop/hbase/regionserver/BloomType;".clone:()Ljava/lang/Object;
       6: checkcast     #3                  // class "[Lorg/apache/hadoop/hbase/regionserver/BloomType;"
       9: areturn

  public static org.apache.hadoop.hbase.regionserver.BloomType valueOf(java.lang.String);
    Code:
       0: ldc           #4                  // class org/apache/hadoop/hbase/regionserver/BloomType
       2: aload_0
       3: invokestatic  #5                  // Method java/lang/Enum.valueOf:(Ljava/lang/Class;Ljava/lang/String;)Ljava/lang/Enum;
       6: checkcast     #4                  // class org/apache/hadoop/hbase/regionserver/BloomType
       9: areturn

  static {};
    Code:
       0: new           #4                  // class org/apache/hadoop/hbase/regionserver/BloomType
       3: dup
       4: ldc           #7                  // String NONE
       6: iconst_0
       7: invokespecial #8                  // Method "<init>":(Ljava/lang/String;I)V
      10: putstatic     #9                  // Field NONE:Lorg/apache/hadoop/hbase/regionserver/BloomType;
      13: new           #4                  // class org/apache/hadoop/hbase/regionserver/BloomType
      16: dup
      17: ldc           #10                 // String ROW
      19: iconst_1
      20: invokespecial #8                  // Method "<init>":(Ljava/lang/String;I)V
      23: putstatic     #11                 // Field ROW:Lorg/apache/hadoop/hbase/regionserver/BloomType;
      26: new           #4                  // class org/apache/hadoop/hbase/regionserver/BloomType
      29: dup
      30: ldc           #12                 // String ROWCOL
      32: iconst_2
      33: invokespecial #8                  // Method "<init>":(Ljava/lang/String;I)V
      36: putstatic     #13                 // Field ROWCOL:Lorg/apache/hadoop/hbase/regionserver/BloomType;
      39: new           #4                  // class org/apache/hadoop/hbase/regionserver/BloomType
      42: dup
      43: ldc           #14                 // String ROWPREFIX_FIXED_LENGTH
      45: iconst_3
      46: invokespecial #8                  // Method "<init>":(Ljava/lang/String;I)V
      49: putstatic     #15                 // Field ROWPREFIX_FIXED_LENGTH:Lorg/apache/hadoop/hbase/regionserver/BloomType;
      52: iconst_4
      53: anewarray     #4                  // class org/apache/hadoop/hbase/regionserver/BloomType
      56: dup
      57: iconst_0
      58: getstatic     #9                  // Field NONE:Lorg/apache/hadoop/hbase/regionserver/BloomType;
      61: aastore
      62: dup
      63: iconst_1
      64: getstatic     #11                 // Field ROW:Lorg/apache/hadoop/hbase/regionserver/BloomType;
      67: aastore
      68: dup
      69: iconst_2
      70: getstatic     #13                 // Field ROWCOL:Lorg/apache/hadoop/hbase/regionserver/BloomType;
      73: aastore
      74: dup
      75: iconst_3
      76: getstatic     #15                 // Field ROWPREFIX_FIXED_LENGTH:Lorg/apache/hadoop/hbase/regionserver/BloomType;
      79: aastore
      80: putstatic     #1                  // Field $VALUES:[Lorg/apache/hadoop/hbase/regionserver/BloomType;
      83: return
}
