Compiled from "BoundedPriorityBlockingQueue.java"
class org.apache.hadoop.hbase.util.BoundedPriorityBlockingQueue$PriorityQueue<E> {
  public org.apache.hadoop.hbase.util.BoundedPriorityBlockingQueue$PriorityQueue(int, java.util.Comparator<? super E>);
    Code:
       0: aload_0
       1: invokespecial #1                  // Method java/lang/Object."<init>":()V
       4: aload_0
       5: iconst_0
       6: putfield      #2                  // Field head:I
       9: aload_0
      10: iconst_0
      11: putfield      #3                  // Field tail:I
      14: aload_0
      15: iload_1
      16: anewarray     #4                  // class java/lang/Object
      19: checkcast     #5                  // class "[Ljava/lang/Object;"
      22: putfield      #6                  // Field objects:[Ljava/lang/Object;
      25: aload_0
      26: aload_2
      27: putfield      #7                  // Field comparator:Ljava/util/Comparator;
      30: return

  public void add(E);
    Code:
       0: aload_0
       1: getfield      #3                  // Field tail:I
       4: aload_0
       5: getfield      #6                  // Field objects:[Ljava/lang/Object;
       8: arraylength
       9: if_icmpne     50
      12: aload_0
      13: dup
      14: getfield      #3                  // Field tail:I
      17: aload_0
      18: getfield      #2                  // Field head:I
      21: isub
      22: putfield      #3                  // Field tail:I
      25: aload_0
      26: getfield      #6                  // Field objects:[Ljava/lang/Object;
      29: aload_0
      30: getfield      #2                  // Field head:I
      33: aload_0
      34: getfield      #6                  // Field objects:[Ljava/lang/Object;
      37: iconst_0
      38: aload_0
      39: getfield      #3                  // Field tail:I
      42: invokestatic  #8                  // Method java/lang/System.arraycopy:(Ljava/lang/Object;ILjava/lang/Object;II)V
      45: aload_0
      46: iconst_0
      47: putfield      #2                  // Field head:I
      50: aload_0
      51: getfield      #3                  // Field tail:I
      54: aload_0
      55: getfield      #2                  // Field head:I
      58: if_icmpeq     85
      61: aload_0
      62: getfield      #7                  // Field comparator:Ljava/util/Comparator;
      65: aload_0
      66: getfield      #6                  // Field objects:[Ljava/lang/Object;
      69: aload_0
      70: getfield      #3                  // Field tail:I
      73: iconst_1
      74: isub
      75: aaload
      76: aload_1
      77: invokeinterface #9,  3            // InterfaceMethod java/util/Comparator.compare:(Ljava/lang/Object;Ljava/lang/Object;)I
      82: ifgt          105
      85: aload_0
      86: getfield      #6                  // Field objects:[Ljava/lang/Object;
      89: aload_0
      90: dup
      91: getfield      #3                  // Field tail:I
      94: dup_x1
      95: iconst_1
      96: iadd
      97: putfield      #3                  // Field tail:I
     100: aload_1
     101: aastore
     102: goto          208
     105: aload_0
     106: getfield      #2                  // Field head:I
     109: ifle          154
     112: aload_0
     113: getfield      #7                  // Field comparator:Ljava/util/Comparator;
     116: aload_0
     117: getfield      #6                  // Field objects:[Ljava/lang/Object;
     120: aload_0
     121: getfield      #2                  // Field head:I
     124: aaload
     125: aload_1
     126: invokeinterface #9,  3            // InterfaceMethod java/util/Comparator.compare:(Ljava/lang/Object;Ljava/lang/Object;)I
     131: ifle          154
     134: aload_0
     135: getfield      #6                  // Field objects:[Ljava/lang/Object;
     138: aload_0
     139: dup
     140: getfield      #2                  // Field head:I
     143: iconst_1
     144: isub
     145: dup_x1
     146: putfield      #2                  // Field head:I
     149: aload_1
     150: aastore
     151: goto          208
     154: aload_0
     155: aload_0
     156: getfield      #2                  // Field head:I
     159: aload_0
     160: getfield      #3                  // Field tail:I
     163: iconst_1
     164: isub
     165: aload_1
     166: invokespecial #10                 // Method upperBound:(IILjava/lang/Object;)I
     169: istore_2
     170: aload_0
     171: getfield      #6                  // Field objects:[Ljava/lang/Object;
     174: iload_2
     175: aload_0
     176: getfield      #6                  // Field objects:[Ljava/lang/Object;
     179: iload_2
     180: iconst_1
     181: iadd
     182: aload_0
     183: getfield      #3                  // Field tail:I
     186: iload_2
     187: isub
     188: invokestatic  #8                  // Method java/lang/System.arraycopy:(Ljava/lang/Object;ILjava/lang/Object;II)V
     191: aload_0
     192: getfield      #6                  // Field objects:[Ljava/lang/Object;
     195: iload_2
     196: aload_1
     197: aastore
     198: aload_0
     199: dup
     200: getfield      #3                  // Field tail:I
     203: iconst_1
     204: iadd
     205: putfield      #3                  // Field tail:I
     208: return

  public E peek();
    Code:
       0: aload_0
       1: getfield      #2                  // Field head:I
       4: aload_0
       5: getfield      #3                  // Field tail:I
       8: if_icmpeq     23
      11: aload_0
      12: getfield      #6                  // Field objects:[Ljava/lang/Object;
      15: aload_0
      16: getfield      #2                  // Field head:I
      19: aaload
      20: goto          24
      23: aconst_null
      24: areturn

  public E poll();
    Code:
       0: aload_0
       1: getfield      #6                  // Field objects:[Ljava/lang/Object;
       4: aload_0
       5: getfield      #2                  // Field head:I
       8: aaload
       9: astore_1
      10: aload_0
      11: getfield      #6                  // Field objects:[Ljava/lang/Object;
      14: aload_0
      15: getfield      #2                  // Field head:I
      18: aconst_null
      19: aastore
      20: aload_0
      21: aload_0
      22: getfield      #2                  // Field head:I
      25: iconst_1
      26: iadd
      27: aload_0
      28: getfield      #6                  // Field objects:[Ljava/lang/Object;
      31: arraylength
      32: irem
      33: putfield      #2                  // Field head:I
      36: aload_0
      37: getfield      #2                  // Field head:I
      40: ifne          48
      43: aload_0
      44: iconst_0
      45: putfield      #3                  // Field tail:I
      48: aload_1
      49: areturn

  public int size();
    Code:
       0: aload_0
       1: getfield      #3                  // Field tail:I
       4: aload_0
       5: getfield      #2                  // Field head:I
       8: isub
       9: ireturn

  public java.util.Comparator<? super E> comparator();
    Code:
       0: aload_0
       1: getfield      #7                  // Field comparator:Ljava/util/Comparator;
       4: areturn

  public boolean contains(java.lang.Object);
    Code:
       0: aload_0
       1: getfield      #2                  // Field head:I
       4: istore_2
       5: iload_2
       6: aload_0
       7: getfield      #3                  // Field tail:I
      10: if_icmpge     31
      13: aload_0
      14: getfield      #6                  // Field objects:[Ljava/lang/Object;
      17: iload_2
      18: aaload
      19: aload_1
      20: if_acmpne     25
      23: iconst_1
      24: ireturn
      25: iinc          2, 1
      28: goto          5
      31: iconst_0
      32: ireturn

  public int remainingCapacity();
    Code:
       0: aload_0
       1: getfield      #6                  // Field objects:[Ljava/lang/Object;
       4: arraylength
       5: aload_0
       6: getfield      #3                  // Field tail:I
       9: aload_0
      10: getfield      #2                  // Field head:I
      13: isub
      14: isub
      15: ireturn
}
