Compiled from "BucketCache.java"
class org.apache.hadoop.hbase.io.hfile.bucket.BucketCache$WriterThread extends org.apache.hadoop.hbase.util.HasThread {
  final org.apache.hadoop.hbase.io.hfile.bucket.BucketCache this$0;

  org.apache.hadoop.hbase.io.hfile.bucket.BucketCache$WriterThread(java.util.concurrent.BlockingQueue<org.apache.hadoop.hbase.io.hfile.bucket.BucketCache$RAMQueueEntry>);
    Code:
       0: aload_0
       1: aload_1
       2: putfield      #1                  // Field this$0:Lorg/apache/hadoop/hbase/io/hfile/bucket/BucketCache;
       5: aload_0
       6: ldc           #2                  // String BucketCacheWriterThread
       8: invokespecial #3                  // Method org/apache/hadoop/hbase/util/HasThread."<init>":(Ljava/lang/String;)V
      11: aload_0
      12: iconst_1
      13: putfield      #4                  // Field writerEnabled:Z
      16: aload_0
      17: aload_2
      18: putfield      #5                  // Field inputQueue:Ljava/util/concurrent/BlockingQueue;
      21: return

  void disableWriter();
    Code:
       0: aload_0
       1: iconst_0
       2: putfield      #4                  // Field writerEnabled:Z
       5: return

  public void run();
    Code:
       0: new           #6                  // class java/util/ArrayList
       3: dup
       4: invokespecial #7                  // Method java/util/ArrayList."<init>":()V
       7: astore_1
       8: aload_0
       9: getfield      #1                  // Field this$0:Lorg/apache/hadoop/hbase/io/hfile/bucket/BucketCache;
      12: invokestatic  #8                  // Method org/apache/hadoop/hbase/io/hfile/bucket/BucketCache.access$000:(Lorg/apache/hadoop/hbase/io/hfile/bucket/BucketCache;)Z
      15: ifeq          74
      18: aload_0
      19: getfield      #4                  // Field writerEnabled:Z
      22: ifeq          74
      25: aload_0
      26: getfield      #5                  // Field inputQueue:Ljava/util/concurrent/BlockingQueue;
      29: aload_1
      30: invokestatic  #9                  // Method org/apache/hadoop/hbase/io/hfile/bucket/BucketCache.getRAMQueueEntries:(Ljava/util/concurrent/BlockingQueue;Ljava/util/List;)Ljava/util/List;
      33: astore_1
      34: goto          51
      37: astore_2
      38: aload_0
      39: getfield      #1                  // Field this$0:Lorg/apache/hadoop/hbase/io/hfile/bucket/BucketCache;
      42: invokestatic  #8                  // Method org/apache/hadoop/hbase/io/hfile/bucket/BucketCache.access$000:(Lorg/apache/hadoop/hbase/io/hfile/bucket/BucketCache;)Z
      45: ifne          51
      48: goto          74
      51: aload_0
      52: aload_1
      53: invokevirtual #11                 // Method doDrain:(Ljava/util/List;)V
      56: goto          8
      59: astore_2
      60: invokestatic  #13                 // Method org/apache/hadoop/hbase/io/hfile/bucket/BucketCache.access$100:()Lorg/slf4j/Logger;
      63: ldc           #14                 // String WriterThread encountered error
      65: aload_2
      66: invokeinterface #15,  3           // InterfaceMethod org/slf4j/Logger.error:(Ljava/lang/String;Ljava/lang/Throwable;)V
      71: goto          8
      74: goto          89
      77: astore_2
      78: invokestatic  #13                 // Method org/apache/hadoop/hbase/io/hfile/bucket/BucketCache.access$100:()Lorg/slf4j/Logger;
      81: ldc           #17                 // String Failed doing drain
      83: aload_2
      84: invokeinterface #18,  3           // InterfaceMethod org/slf4j/Logger.warn:(Ljava/lang/String;Ljava/lang/Throwable;)V
      89: invokestatic  #13                 // Method org/apache/hadoop/hbase/io/hfile/bucket/BucketCache.access$100:()Lorg/slf4j/Logger;
      92: new           #19                 // class java/lang/StringBuilder
      95: dup
      96: invokespecial #20                 // Method java/lang/StringBuilder."<init>":()V
      99: aload_0
     100: invokevirtual #21                 // Method getName:()Ljava/lang/String;
     103: invokevirtual #22                 // Method java/lang/StringBuilder.append:(Ljava/lang/String;)Ljava/lang/StringBuilder;
     106: ldc           #23                 // String  exiting, cacheEnabled=
     108: invokevirtual #22                 // Method java/lang/StringBuilder.append:(Ljava/lang/String;)Ljava/lang/StringBuilder;
     111: aload_0
     112: getfield      #1                  // Field this$0:Lorg/apache/hadoop/hbase/io/hfile/bucket/BucketCache;
     115: invokestatic  #8                  // Method org/apache/hadoop/hbase/io/hfile/bucket/BucketCache.access$000:(Lorg/apache/hadoop/hbase/io/hfile/bucket/BucketCache;)Z
     118: invokevirtual #24                 // Method java/lang/StringBuilder.append:(Z)Ljava/lang/StringBuilder;
     121: invokevirtual #25                 // Method java/lang/StringBuilder.toString:()Ljava/lang/String;
     124: invokeinterface #26,  2           // InterfaceMethod org/slf4j/Logger.info:(Ljava/lang/String;)V
     129: return
    Exception table:
       from    to  target type
          25    34    37   Class java/lang/InterruptedException
          25    48    59   Class java/lang/Exception
          51    56    59   Class java/lang/Exception
           8    74    77   Class java/lang/Throwable

  void doDrain(java.util.List<org.apache.hadoop.hbase.io.hfile.bucket.BucketCache$RAMQueueEntry>) throws java.lang.InterruptedException;
    Code:
       0: aload_1
       1: invokeinterface #38,  1           // InterfaceMethod java/util/List.isEmpty:()Z
       6: ifeq          10
       9: return
      10: aload_1
      11: invokeinterface #39,  1           // InterfaceMethod java/util/List.size:()I
      16: istore_2
      17: iload_2
      18: anewarray     #29                 // class org/apache/hadoop/hbase/io/hfile/bucket/BucketCache$BucketEntry
      21: astore_3
      22: iconst_0
      23: istore        4
      25: aload_0
      26: getfield      #1                  // Field this$0:Lorg/apache/hadoop/hbase/io/hfile/bucket/BucketCache;
      29: invokestatic  #8                  // Method org/apache/hadoop/hbase/io/hfile/bucket/BucketCache.access$000:(Lorg/apache/hadoop/hbase/io/hfile/bucket/BucketCache;)Z
      32: ifeq          262
      35: iload         4
      37: iload_2
      38: if_icmpge     262
      41: aconst_null
      42: astore        5
      44: aload_1
      45: iload         4
      47: invokeinterface #40,  2           // InterfaceMethod java/util/List.get:(I)Ljava/lang/Object;
      52: checkcast     #41                 // class org/apache/hadoop/hbase/io/hfile/bucket/BucketCache$RAMQueueEntry
      55: astore        5
      57: aload         5
      59: ifnonnull     78
      62: invokestatic  #13                 // Method org/apache/hadoop/hbase/io/hfile/bucket/BucketCache.access$100:()Lorg/slf4j/Logger;
      65: ldc           #42                 // String Couldn't get entry or changed on us; who else is messing with it?
      67: invokeinterface #43,  2           // InterfaceMethod org/slf4j/Logger.warn:(Ljava/lang/String;)V
      72: iinc          4, 1
      75: goto          25
      78: aload         5
      80: aload_0
      81: getfield      #1                  // Field this$0:Lorg/apache/hadoop/hbase/io/hfile/bucket/BucketCache;
      84: getfield      #44                 // Field org/apache/hadoop/hbase/io/hfile/bucket/BucketCache.ioEngine:Lorg/apache/hadoop/hbase/io/hfile/bucket/IOEngine;
      87: aload_0
      88: getfield      #1                  // Field this$0:Lorg/apache/hadoop/hbase/io/hfile/bucket/BucketCache;
      91: invokestatic  #45                 // Method org/apache/hadoop/hbase/io/hfile/bucket/BucketCache.access$200:(Lorg/apache/hadoop/hbase/io/hfile/bucket/BucketCache;)Lorg/apache/hadoop/hbase/io/hfile/bucket/BucketAllocator;
      94: aload_0
      95: getfield      #1                  // Field this$0:Lorg/apache/hadoop/hbase/io/hfile/bucket/BucketCache;
      98: invokestatic  #46                 // Method org/apache/hadoop/hbase/io/hfile/bucket/BucketCache.access$300:(Lorg/apache/hadoop/hbase/io/hfile/bucket/BucketCache;)Ljava/util/concurrent/atomic/LongAdder;
     101: invokevirtual #47                 // Method org/apache/hadoop/hbase/io/hfile/bucket/BucketCache$RAMQueueEntry.writeToCache:(Lorg/apache/hadoop/hbase/io/hfile/bucket/IOEngine;Lorg/apache/hadoop/hbase/io/hfile/bucket/BucketAllocator;Ljava/util/concurrent/atomic/LongAdder;)Lorg/apache/hadoop/hbase/io/hfile/bucket/BucketCache$BucketEntry;
     104: astore        6
     106: aload_3
     107: iload         4
     109: aload         6
     111: aastore
     112: aload_0
     113: getfield      #1                  // Field this$0:Lorg/apache/hadoop/hbase/io/hfile/bucket/BucketCache;
     116: invokestatic  #48                 // Method org/apache/hadoop/hbase/io/hfile/bucket/BucketCache.access$400:(Lorg/apache/hadoop/hbase/io/hfile/bucket/BucketCache;)J
     119: lconst_0
     120: lcmp
     121: ifle          135
     124: aload_0
     125: getfield      #1                  // Field this$0:Lorg/apache/hadoop/hbase/io/hfile/bucket/BucketCache;
     128: ldc2_w        #49                 // long -1l
     131: invokestatic  #51                 // Method org/apache/hadoop/hbase/io/hfile/bucket/BucketCache.access$402:(Lorg/apache/hadoop/hbase/io/hfile/bucket/BucketCache;J)J
     134: pop2
     135: iinc          4, 1
     138: goto          259
     141: astore        6
     143: invokestatic  #13                 // Method org/apache/hadoop/hbase/io/hfile/bucket/BucketCache.access$100:()Lorg/slf4j/Logger;
     146: new           #19                 // class java/lang/StringBuilder
     149: dup
     150: invokespecial #20                 // Method java/lang/StringBuilder."<init>":()V
     153: ldc           #53                 // String Failed allocation for
     155: invokevirtual #22                 // Method java/lang/StringBuilder.append:(Ljava/lang/String;)Ljava/lang/StringBuilder;
     158: aload         5
     160: ifnonnull     168
     163: ldc           #54                 // String
     165: goto          173
     168: aload         5
     170: invokevirtual #55                 // Method org/apache/hadoop/hbase/io/hfile/bucket/BucketCache$RAMQueueEntry.getKey:()Lorg/apache/hadoop/hbase/io/hfile/BlockCacheKey;
     173: invokevirtual #56                 // Method java/lang/StringBuilder.append:(Ljava/lang/Object;)Ljava/lang/StringBuilder;
     176: ldc           #57                 // String ;
     178: invokevirtual #22                 // Method java/lang/StringBuilder.append:(Ljava/lang/String;)Ljava/lang/StringBuilder;
     181: aload         6
     183: invokevirtual #56                 // Method java/lang/StringBuilder.append:(Ljava/lang/Object;)Ljava/lang/StringBuilder;
     186: invokevirtual #25                 // Method java/lang/StringBuilder.toString:()Ljava/lang/String;
     189: invokeinterface #43,  2           // InterfaceMethod org/slf4j/Logger.warn:(Ljava/lang/String;)V
     194: aload_3
     195: iload         4
     197: aconst_null
     198: aastore
     199: iinc          4, 1
     202: goto          259
     205: astore        6
     207: aload_0
     208: getfield      #1                  // Field this$0:Lorg/apache/hadoop/hbase/io/hfile/bucket/BucketCache;
     211: invokestatic  #59                 // Method org/apache/hadoop/hbase/io/hfile/bucket/BucketCache.access$500:(Lorg/apache/hadoop/hbase/io/hfile/bucket/BucketCache;)Z
     214: ifne          229
     217: aload_0
     218: getfield      #1                  // Field this$0:Lorg/apache/hadoop/hbase/io/hfile/bucket/BucketCache;
     221: ldc           #60                 // String Full!
     223: invokestatic  #61                 // Method org/apache/hadoop/hbase/io/hfile/bucket/BucketCache.access$600:(Lorg/apache/hadoop/hbase/io/hfile/bucket/BucketCache;Ljava/lang/String;)V
     226: goto          235
     229: ldc2_w        #62                 // long 50l
     232: invokestatic  #64                 // Method java/lang/Thread.sleep:(J)V
     235: goto          259
     238: astore        6
     240: invokestatic  #13                 // Method org/apache/hadoop/hbase/io/hfile/bucket/BucketCache.access$100:()Lorg/slf4j/Logger;
     243: ldc           #66                 // String Failed writing to bucket cache
     245: aload         6
     247: invokeinterface #15,  3           // InterfaceMethod org/slf4j/Logger.error:(Ljava/lang/String;Ljava/lang/Throwable;)V
     252: aload_0
     253: getfield      #1                  // Field this$0:Lorg/apache/hadoop/hbase/io/hfile/bucket/BucketCache;
     256: invokestatic  #67                 // Method org/apache/hadoop/hbase/io/hfile/bucket/BucketCache.access$700:(Lorg/apache/hadoop/hbase/io/hfile/bucket/BucketCache;)V
     259: goto          25
     262: aload_0
     263: getfield      #1                  // Field this$0:Lorg/apache/hadoop/hbase/io/hfile/bucket/BucketCache;
     266: getfield      #44                 // Field org/apache/hadoop/hbase/io/hfile/bucket/BucketCache.ioEngine:Lorg/apache/hadoop/hbase/io/hfile/bucket/IOEngine;
     269: invokeinterface #68,  1           // InterfaceMethod org/apache/hadoop/hbase/io/hfile/bucket/IOEngine.sync:()V
     274: goto          348
     277: astore        5
     279: invokestatic  #13                 // Method org/apache/hadoop/hbase/io/hfile/bucket/BucketCache.access$100:()Lorg/slf4j/Logger;
     282: ldc           #69                 // String Failed syncing IO engine
     284: aload         5
     286: invokeinterface #15,  3           // InterfaceMethod org/slf4j/Logger.error:(Ljava/lang/String;Ljava/lang/Throwable;)V
     291: aload_0
     292: getfield      #1                  // Field this$0:Lorg/apache/hadoop/hbase/io/hfile/bucket/BucketCache;
     295: invokestatic  #67                 // Method org/apache/hadoop/hbase/io/hfile/bucket/BucketCache.access$700:(Lorg/apache/hadoop/hbase/io/hfile/bucket/BucketCache;)V
     298: iconst_0
     299: istore        6
     301: iload         6
     303: aload_1
     304: invokeinterface #39,  1           // InterfaceMethod java/util/List.size:()I
     309: if_icmpge     348
     312: aload_3
     313: iload         6
     315: aaload
     316: ifnull        342
     319: aload_0
     320: getfield      #1                  // Field this$0:Lorg/apache/hadoop/hbase/io/hfile/bucket/BucketCache;
     323: invokestatic  #45                 // Method org/apache/hadoop/hbase/io/hfile/bucket/BucketCache.access$200:(Lorg/apache/hadoop/hbase/io/hfile/bucket/BucketCache;)Lorg/apache/hadoop/hbase/io/hfile/bucket/BucketAllocator;
     326: aload_3
     327: iload         6
     329: aaload
     330: invokevirtual #31                 // Method org/apache/hadoop/hbase/io/hfile/bucket/BucketCache$BucketEntry.offset:()J
     333: invokevirtual #70                 // Method org/apache/hadoop/hbase/io/hfile/bucket/BucketAllocator.freeBlock:(J)I
     336: pop
     337: aload_3
     338: iload         6
     340: aconst_null
     341: aastore
     342: iinc          6, 1
     345: goto          301
     348: iconst_0
     349: istore        5
     351: iload         5
     353: iload_2
     354: if_icmpge     586
     357: aload_1
     358: iload         5
     360: invokeinterface #40,  2           // InterfaceMethod java/util/List.get:(I)Ljava/lang/Object;
     365: checkcast     #41                 // class org/apache/hadoop/hbase/io/hfile/bucket/BucketCache$RAMQueueEntry
     368: invokevirtual #55                 // Method org/apache/hadoop/hbase/io/hfile/bucket/BucketCache$RAMQueueEntry.getKey:()Lorg/apache/hadoop/hbase/io/hfile/BlockCacheKey;
     371: astore        6
     373: aload_3
     374: iload         5
     376: aaload
     377: ifnull        390
     380: aload_0
     381: aload         6
     383: aload_3
     384: iload         5
     386: aaload
     387: invokespecial #71                 // Method putIntoBackingMap:(Lorg/apache/hadoop/hbase/io/hfile/BlockCacheKey;Lorg/apache/hadoop/hbase/io/hfile/bucket/BucketCache$BucketEntry;)V
     390: aload_0
     391: getfield      #1                  // Field this$0:Lorg/apache/hadoop/hbase/io/hfile/bucket/BucketCache;
     394: getfield      #72                 // Field org/apache/hadoop/hbase/io/hfile/bucket/BucketCache.ramCache:Ljava/util/concurrent/ConcurrentMap;
     397: aload         6
     399: invokeinterface #73,  2           // InterfaceMethod java/util/concurrent/ConcurrentMap.remove:(Ljava/lang/Object;)Ljava/lang/Object;
     404: checkcast     #41                 // class org/apache/hadoop/hbase/io/hfile/bucket/BucketCache$RAMQueueEntry
     407: astore        7
     409: aload         7
     411: ifnull        450
     414: aload_0
     415: getfield      #1                  // Field this$0:Lorg/apache/hadoop/hbase/io/hfile/bucket/BucketCache;
     418: invokestatic  #74                 // Method org/apache/hadoop/hbase/io/hfile/bucket/BucketCache.access$800:(Lorg/apache/hadoop/hbase/io/hfile/bucket/BucketCache;)Ljava/util/concurrent/atomic/LongAdder;
     421: ldc2_w        #49                 // long -1l
     424: aload_1
     425: iload         5
     427: invokeinterface #40,  2           // InterfaceMethod java/util/List.get:(I)Ljava/lang/Object;
     432: checkcast     #41                 // class org/apache/hadoop/hbase/io/hfile/bucket/BucketCache$RAMQueueEntry
     435: invokevirtual #75                 // Method org/apache/hadoop/hbase/io/hfile/bucket/BucketCache$RAMQueueEntry.getData:()Lorg/apache/hadoop/hbase/io/hfile/Cacheable;
     438: invokeinterface #76,  1           // InterfaceMethod org/apache/hadoop/hbase/io/hfile/Cacheable.heapSize:()J
     443: lmul
     444: invokevirtual #77                 // Method java/util/concurrent/atomic/LongAdder.add:(J)V
     447: goto          580
     450: aload_3
     451: iload         5
     453: aaload
     454: ifnull        580
     457: aload_0
     458: getfield      #1                  // Field this$0:Lorg/apache/hadoop/hbase/io/hfile/bucket/BucketCache;
     461: getfield      #30                 // Field org/apache/hadoop/hbase/io/hfile/bucket/BucketCache.offsetLock:Lorg/apache/hadoop/hbase/util/IdReadWriteLock;
     464: aload_3
     465: iload         5
     467: aaload
     468: invokevirtual #31                 // Method org/apache/hadoop/hbase/io/hfile/bucket/BucketCache$BucketEntry.offset:()J
     471: invokestatic  #32                 // Method java/lang/Long.valueOf:(J)Ljava/lang/Long;
     474: invokevirtual #33                 // Method org/apache/hadoop/hbase/util/IdReadWriteLock.getLock:(Ljava/lang/Object;)Ljava/util/concurrent/locks/ReentrantReadWriteLock;
     477: astore        8
     479: aload         8
     481: invokevirtual #34                 // Method java/util/concurrent/locks/ReentrantReadWriteLock.writeLock:()Ljava/util/concurrent/locks/ReentrantReadWriteLock$WriteLock;
     484: invokevirtual #35                 // Method java/util/concurrent/locks/ReentrantReadWriteLock$WriteLock.lock:()V
     487: aload_3
     488: iload         5
     490: aaload
     491: invokevirtual #78                 // Method org/apache/hadoop/hbase/io/hfile/bucket/BucketCache$BucketEntry.getRefCount:()I
     494: istore        9
     496: iload         9
     498: ifne          549
     501: aload_0
     502: getfield      #1                  // Field this$0:Lorg/apache/hadoop/hbase/io/hfile/bucket/BucketCache;
     505: getfield      #27                 // Field org/apache/hadoop/hbase/io/hfile/bucket/BucketCache.backingMap:Ljava/util/concurrent/ConcurrentMap;
     508: aload         6
     510: aload_3
     511: iload         5
     513: aaload
     514: invokeinterface #79,  3           // InterfaceMethod java/util/concurrent/ConcurrentMap.remove:(Ljava/lang/Object;Ljava/lang/Object;)Z
     519: ifeq          539
     522: aload_0
     523: getfield      #1                  // Field this$0:Lorg/apache/hadoop/hbase/io/hfile/bucket/BucketCache;
     526: aload         6
     528: aload_3
     529: iload         5
     531: aaload
     532: iconst_0
     533: invokevirtual #36                 // Method org/apache/hadoop/hbase/io/hfile/bucket/BucketCache.blockEvicted:(Lorg/apache/hadoop/hbase/io/hfile/BlockCacheKey;Lorg/apache/hadoop/hbase/io/hfile/bucket/BucketCache$BucketEntry;Z)V
     536: goto          556
     539: aload_3
     540: iload         5
     542: aaload
     543: invokevirtual #80                 // Method org/apache/hadoop/hbase/io/hfile/bucket/BucketCache$BucketEntry.markForEvict:()V
     546: goto          556
     549: aload_3
     550: iload         5
     552: aaload
     553: invokevirtual #80                 // Method org/apache/hadoop/hbase/io/hfile/bucket/BucketCache$BucketEntry.markForEvict:()V
     556: aload         8
     558: invokevirtual #34                 // Method java/util/concurrent/locks/ReentrantReadWriteLock.writeLock:()Ljava/util/concurrent/locks/ReentrantReadWriteLock$WriteLock;
     561: invokevirtual #37                 // Method java/util/concurrent/locks/ReentrantReadWriteLock$WriteLock.unlock:()V
     564: goto          580
     567: astore        10
     569: aload         8
     571: invokevirtual #34                 // Method java/util/concurrent/locks/ReentrantReadWriteLock.writeLock:()Ljava/util/concurrent/locks/ReentrantReadWriteLock$WriteLock;
     574: invokevirtual #37                 // Method java/util/concurrent/locks/ReentrantReadWriteLock$WriteLock.unlock:()V
     577: aload         10
     579: athrow
     580: iinc          5, 1
     583: goto          351
     586: aload_0
     587: getfield      #1                  // Field this$0:Lorg/apache/hadoop/hbase/io/hfile/bucket/BucketCache;
     590: invokestatic  #45                 // Method org/apache/hadoop/hbase/io/hfile/bucket/BucketCache.access$200:(Lorg/apache/hadoop/hbase/io/hfile/bucket/BucketCache;)Lorg/apache/hadoop/hbase/io/hfile/bucket/BucketAllocator;
     593: invokevirtual #81                 // Method org/apache/hadoop/hbase/io/hfile/bucket/BucketAllocator.getUsedSize:()J
     596: lstore        5
     598: lload         5
     600: aload_0
     601: getfield      #1                  // Field this$0:Lorg/apache/hadoop/hbase/io/hfile/bucket/BucketCache;
     604: invokevirtual #82                 // Method org/apache/hadoop/hbase/io/hfile/bucket/BucketCache.acceptableSize:()J
     607: lcmp
     608: ifle          653
     611: aload_0
     612: getfield      #1                  // Field this$0:Lorg/apache/hadoop/hbase/io/hfile/bucket/BucketCache;
     615: new           #19                 // class java/lang/StringBuilder
     618: dup
     619: invokespecial #20                 // Method java/lang/StringBuilder."<init>":()V
     622: ldc           #83                 // String Used=
     624: invokevirtual #22                 // Method java/lang/StringBuilder.append:(Ljava/lang/String;)Ljava/lang/StringBuilder;
     627: lload         5
     629: invokevirtual #84                 // Method java/lang/StringBuilder.append:(J)Ljava/lang/StringBuilder;
     632: ldc           #85                 // String  > acceptable=
     634: invokevirtual #22                 // Method java/lang/StringBuilder.append:(Ljava/lang/String;)Ljava/lang/StringBuilder;
     637: aload_0
     638: getfield      #1                  // Field this$0:Lorg/apache/hadoop/hbase/io/hfile/bucket/BucketCache;
     641: invokevirtual #82                 // Method org/apache/hadoop/hbase/io/hfile/bucket/BucketCache.acceptableSize:()J
     644: invokevirtual #84                 // Method java/lang/StringBuilder.append:(J)Ljava/lang/StringBuilder;
     647: invokevirtual #25                 // Method java/lang/StringBuilder.toString:()Ljava/lang/String;
     650: invokestatic  #61                 // Method org/apache/hadoop/hbase/io/hfile/bucket/BucketCache.access$600:(Lorg/apache/hadoop/hbase/io/hfile/bucket/BucketCache;Ljava/lang/String;)V
     653: return
    Exception table:
       from    to  target type
          44    75   141   Class org/apache/hadoop/hbase/io/hfile/bucket/BucketAllocatorException
          78   138   141   Class org/apache/hadoop/hbase/io/hfile/bucket/BucketAllocatorException
          44    75   205   Class org/apache/hadoop/hbase/io/hfile/bucket/CacheFullException
          78   138   205   Class org/apache/hadoop/hbase/io/hfile/bucket/CacheFullException
          44    75   238   Class java/io/IOException
          78   138   238   Class java/io/IOException
         262   274   277   Class java/io/IOException
         479   556   567   any
         567   569   567   any
}
