Compiled from "BucketCacheProtos.java"
public final class org.apache.hadoop.hbase.shaded.protobuf.generated.BucketCacheProtos$BucketCacheEntry extends org.apache.hbase.thirdparty.com.google.protobuf.GeneratedMessageV3 implements org.apache.hadoop.hbase.shaded.protobuf.generated.BucketCacheProtos$BucketCacheEntryOrBuilder {
  public static final int CACHE_CAPACITY_FIELD_NUMBER;

  public static final int IO_CLASS_FIELD_NUMBER;

  public static final int MAP_CLASS_FIELD_NUMBER;

  public static final int DESERIALIZERS_FIELD_NUMBER;

  public static final int BACKING_MAP_FIELD_NUMBER;

  public static final org.apache.hbase.thirdparty.com.google.protobuf.Parser<org.apache.hadoop.hbase.shaded.protobuf.generated.BucketCacheProtos$BucketCacheEntry> PARSER;

  public final org.apache.hbase.thirdparty.com.google.protobuf.UnknownFieldSet getUnknownFields();
    Code:
       0: aload_0
       1: getfield      #2                  // Field unknownFields:Lorg/apache/hbase/thirdparty/com/google/protobuf/UnknownFieldSet;
       4: areturn

  public static final org.apache.hbase.thirdparty.com.google.protobuf.Descriptors$Descriptor getDescriptor();
    Code:
       0: invokestatic  #44                 // Method org/apache/hadoop/hbase/shaded/protobuf/generated/BucketCacheProtos.access$000:()Lorg/apache/hbase/thirdparty/com/google/protobuf/Descriptors$Descriptor;
       3: areturn

  protected org.apache.hbase.thirdparty.com.google.protobuf.MapField internalGetMapField(int);
    Code:
       0: iload_1
       1: lookupswitch  { // 1
                     4: 20
               default: 25
          }
      20: aload_0
      21: invokespecial #3                  // Method internalGetDeserializers:()Lorg/apache/hbase/thirdparty/com/google/protobuf/MapField;
      24: areturn
      25: new           #45                 // class java/lang/RuntimeException
      28: dup
      29: new           #46                 // class java/lang/StringBuilder
      32: dup
      33: invokespecial #47                 // Method java/lang/StringBuilder."<init>":()V
      36: ldc           #48                 // String Invalid map field number:
      38: invokevirtual #49                 // Method java/lang/StringBuilder.append:(Ljava/lang/String;)Ljava/lang/StringBuilder;
      41: iload_1
      42: invokevirtual #50                 // Method java/lang/StringBuilder.append:(I)Ljava/lang/StringBuilder;
      45: invokevirtual #51                 // Method java/lang/StringBuilder.toString:()Ljava/lang/String;
      48: invokespecial #52                 // Method java/lang/RuntimeException."<init>":(Ljava/lang/String;)V
      51: athrow

  protected org.apache.hbase.thirdparty.com.google.protobuf.GeneratedMessageV3$FieldAccessorTable internalGetFieldAccessorTable();
    Code:
       0: invokestatic  #53                 // Method org/apache/hadoop/hbase/shaded/protobuf/generated/BucketCacheProtos.access$100:()Lorg/apache/hbase/thirdparty/com/google/protobuf/GeneratedMessageV3$FieldAccessorTable;
       3: ldc           #54                 // class org/apache/hadoop/hbase/shaded/protobuf/generated/BucketCacheProtos$BucketCacheEntry
       5: ldc           #55                 // class org/apache/hadoop/hbase/shaded/protobuf/generated/BucketCacheProtos$BucketCacheEntry$Builder
       7: invokevirtual #56                 // Method org/apache/hbase/thirdparty/com/google/protobuf/GeneratedMessageV3$FieldAccessorTable.ensureFieldAccessorsInitialized:(Ljava/lang/Class;Ljava/lang/Class;)Lorg/apache/hbase/thirdparty/com/google/protobuf/GeneratedMessageV3$FieldAccessorTable;
      10: areturn

  public boolean hasCacheCapacity();
    Code:
       0: aload_0
       1: getfield      #4                  // Field bitField0_:I
       4: iconst_1
       5: iand
       6: iconst_1
       7: if_icmpne     14
      10: iconst_1
      11: goto          15
      14: iconst_0
      15: ireturn

  public long getCacheCapacity();
    Code:
       0: aload_0
       1: getfield      #9                  // Field cacheCapacity_:J
       4: lreturn

  public boolean hasIoClass();
    Code:
       0: aload_0
       1: getfield      #4                  // Field bitField0_:I
       4: iconst_2
       5: iand
       6: iconst_2
       7: if_icmpne     14
      10: iconst_1
      11: goto          15
      14: iconst_0
      15: ireturn

  public java.lang.String getIoClass();
    Code:
       0: aload_0
       1: getfield      #8                  // Field ioClass_:Ljava/lang/Object;
       4: astore_1
       5: aload_1
       6: instanceof    #57                 // class java/lang/String
       9: ifeq          17
      12: aload_1
      13: checkcast     #57                 // class java/lang/String
      16: areturn
      17: aload_1
      18: checkcast     #58                 // class org/apache/hbase/thirdparty/com/google/protobuf/ByteString
      21: astore_2
      22: aload_2
      23: invokevirtual #59                 // Method org/apache/hbase/thirdparty/com/google/protobuf/ByteString.toStringUtf8:()Ljava/lang/String;
      26: astore_3
      27: aload_2
      28: invokevirtual #60                 // Method org/apache/hbase/thirdparty/com/google/protobuf/ByteString.isValidUtf8:()Z
      31: ifeq          39
      34: aload_0
      35: aload_3
      36: putfield      #8                  // Field ioClass_:Ljava/lang/Object;
      39: aload_3
      40: areturn

  public org.apache.hbase.thirdparty.com.google.protobuf.ByteString getIoClassBytes();
    Code:
       0: aload_0
       1: getfield      #8                  // Field ioClass_:Ljava/lang/Object;
       4: astore_1
       5: aload_1
       6: instanceof    #57                 // class java/lang/String
       9: ifeq          27
      12: aload_1
      13: checkcast     #57                 // class java/lang/String
      16: invokestatic  #61                 // Method org/apache/hbase/thirdparty/com/google/protobuf/ByteString.copyFromUtf8:(Ljava/lang/String;)Lorg/apache/hbase/thirdparty/com/google/protobuf/ByteString;
      19: astore_2
      20: aload_0
      21: aload_2
      22: putfield      #8                  // Field ioClass_:Ljava/lang/Object;
      25: aload_2
      26: areturn
      27: aload_1
      28: checkcast     #58                 // class org/apache/hbase/thirdparty/com/google/protobuf/ByteString
      31: areturn

  public boolean hasMapClass();
    Code:
       0: aload_0
       1: getfield      #4                  // Field bitField0_:I
       4: iconst_4
       5: iand
       6: iconst_4
       7: if_icmpne     14
      10: iconst_1
      11: goto          15
      14: iconst_0
      15: ireturn

  public java.lang.String getMapClass();
    Code:
       0: aload_0
       1: getfield      #7                  // Field mapClass_:Ljava/lang/Object;
       4: astore_1
       5: aload_1
       6: instanceof    #57                 // class java/lang/String
       9: ifeq          17
      12: aload_1
      13: checkcast     #57                 // class java/lang/String
      16: areturn
      17: aload_1
      18: checkcast     #58                 // class org/apache/hbase/thirdparty/com/google/protobuf/ByteString
      21: astore_2
      22: aload_2
      23: invokevirtual #59                 // Method org/apache/hbase/thirdparty/com/google/protobuf/ByteString.toStringUtf8:()Ljava/lang/String;
      26: astore_3
      27: aload_2
      28: invokevirtual #60                 // Method org/apache/hbase/thirdparty/com/google/protobuf/ByteString.isValidUtf8:()Z
      31: ifeq          39
      34: aload_0
      35: aload_3
      36: putfield      #7                  // Field mapClass_:Ljava/lang/Object;
      39: aload_3
      40: areturn

  public org.apache.hbase.thirdparty.com.google.protobuf.ByteString getMapClassBytes();
    Code:
       0: aload_0
       1: getfield      #7                  // Field mapClass_:Ljava/lang/Object;
       4: astore_1
       5: aload_1
       6: instanceof    #57                 // class java/lang/String
       9: ifeq          27
      12: aload_1
      13: checkcast     #57                 // class java/lang/String
      16: invokestatic  #61                 // Method org/apache/hbase/thirdparty/com/google/protobuf/ByteString.copyFromUtf8:(Ljava/lang/String;)Lorg/apache/hbase/thirdparty/com/google/protobuf/ByteString;
      19: astore_2
      20: aload_0
      21: aload_2
      22: putfield      #7                  // Field mapClass_:Ljava/lang/Object;
      25: aload_2
      26: areturn
      27: aload_1
      28: checkcast     #58                 // class org/apache/hbase/thirdparty/com/google/protobuf/ByteString
      31: areturn

  public int getDeserializersCount();
    Code:
       0: aload_0
       1: invokespecial #3                  // Method internalGetDeserializers:()Lorg/apache/hbase/thirdparty/com/google/protobuf/MapField;
       4: invokevirtual #63                 // Method org/apache/hbase/thirdparty/com/google/protobuf/MapField.getMap:()Ljava/util/Map;
       7: invokeinterface #64,  1           // InterfaceMethod java/util/Map.size:()I
      12: ireturn

  public boolean containsDeserializers(int);
    Code:
       0: aload_0
       1: invokespecial #3                  // Method internalGetDeserializers:()Lorg/apache/hbase/thirdparty/com/google/protobuf/MapField;
       4: invokevirtual #63                 // Method org/apache/hbase/thirdparty/com/google/protobuf/MapField.getMap:()Ljava/util/Map;
       7: iload_1
       8: invokestatic  #65                 // Method java/lang/Integer.valueOf:(I)Ljava/lang/Integer;
      11: invokeinterface #66,  2           // InterfaceMethod java/util/Map.containsKey:(Ljava/lang/Object;)Z
      16: ireturn

  public java.util.Map<java.lang.Integer, java.lang.String> getDeserializers();
    Code:
       0: aload_0
       1: invokevirtual #67                 // Method getDeserializersMap:()Ljava/util/Map;
       4: areturn

  public java.util.Map<java.lang.Integer, java.lang.String> getDeserializersMap();
    Code:
       0: aload_0
       1: invokespecial #3                  // Method internalGetDeserializers:()Lorg/apache/hbase/thirdparty/com/google/protobuf/MapField;
       4: invokevirtual #63                 // Method org/apache/hbase/thirdparty/com/google/protobuf/MapField.getMap:()Ljava/util/Map;
       7: areturn

  public java.lang.String getDeserializersOrDefault(int, java.lang.String);
    Code:
       0: aload_0
       1: invokespecial #3                  // Method internalGetDeserializers:()Lorg/apache/hbase/thirdparty/com/google/protobuf/MapField;
       4: invokevirtual #63                 // Method org/apache/hbase/thirdparty/com/google/protobuf/MapField.getMap:()Ljava/util/Map;
       7: astore_3
       8: aload_3
       9: iload_1
      10: invokestatic  #65                 // Method java/lang/Integer.valueOf:(I)Ljava/lang/Integer;
      13: invokeinterface #66,  2           // InterfaceMethod java/util/Map.containsKey:(Ljava/lang/Object;)Z
      18: ifeq          37
      21: aload_3
      22: iload_1
      23: invokestatic  #65                 // Method java/lang/Integer.valueOf:(I)Ljava/lang/Integer;
      26: invokeinterface #68,  2           // InterfaceMethod java/util/Map.get:(Ljava/lang/Object;)Ljava/lang/Object;
      31: checkcast     #57                 // class java/lang/String
      34: goto          38
      37: aload_2
      38: areturn

  public java.lang.String getDeserializersOrThrow(int);
    Code:
       0: aload_0
       1: invokespecial #3                  // Method internalGetDeserializers:()Lorg/apache/hbase/thirdparty/com/google/protobuf/MapField;
       4: invokevirtual #63                 // Method org/apache/hbase/thirdparty/com/google/protobuf/MapField.getMap:()Ljava/util/Map;
       7: astore_2
       8: aload_2
       9: iload_1
      10: invokestatic  #65                 // Method java/lang/Integer.valueOf:(I)Ljava/lang/Integer;
      13: invokeinterface #66,  2           // InterfaceMethod java/util/Map.containsKey:(Ljava/lang/Object;)Z
      18: ifne          29
      21: new           #69                 // class java/lang/IllegalArgumentException
      24: dup
      25: invokespecial #70                 // Method java/lang/IllegalArgumentException."<init>":()V
      28: athrow
      29: aload_2
      30: iload_1
      31: invokestatic  #65                 // Method java/lang/Integer.valueOf:(I)Ljava/lang/Integer;
      34: invokeinterface #68,  2           // InterfaceMethod java/util/Map.get:(Ljava/lang/Object;)Ljava/lang/Object;
      39: checkcast     #57                 // class java/lang/String
      42: areturn

  public boolean hasBackingMap();
    Code:
       0: aload_0
       1: getfield      #4                  // Field bitField0_:I
       4: bipush        8
       6: iand
       7: bipush        8
       9: if_icmpne     16
      12: iconst_1
      13: goto          17
      16: iconst_0
      17: ireturn

  public org.apache.hadoop.hbase.shaded.protobuf.generated.BucketCacheProtos$BackingMap getBackingMap();
    Code:
       0: aload_0
       1: getfield      #5                  // Field backingMap_:Lorg/apache/hadoop/hbase/shaded/protobuf/generated/BucketCacheProtos$BackingMap;
       4: ifnonnull     13
       7: invokestatic  #71                 // Method org/apache/hadoop/hbase/shaded/protobuf/generated/BucketCacheProtos$BackingMap.getDefaultInstance:()Lorg/apache/hadoop/hbase/shaded/protobuf/generated/BucketCacheProtos$BackingMap;
      10: goto          17
      13: aload_0
      14: getfield      #5                  // Field backingMap_:Lorg/apache/hadoop/hbase/shaded/protobuf/generated/BucketCacheProtos$BackingMap;
      17: areturn

  public org.apache.hadoop.hbase.shaded.protobuf.generated.BucketCacheProtos$BackingMapOrBuilder getBackingMapOrBuilder();
    Code:
       0: aload_0
       1: getfield      #5                  // Field backingMap_:Lorg/apache/hadoop/hbase/shaded/protobuf/generated/BucketCacheProtos$BackingMap;
       4: ifnonnull     13
       7: invokestatic  #71                 // Method org/apache/hadoop/hbase/shaded/protobuf/generated/BucketCacheProtos$BackingMap.getDefaultInstance:()Lorg/apache/hadoop/hbase/shaded/protobuf/generated/BucketCacheProtos$BackingMap;
      10: goto          17
      13: aload_0
      14: getfield      #5                  // Field backingMap_:Lorg/apache/hadoop/hbase/shaded/protobuf/generated/BucketCacheProtos$BackingMap;
      17: areturn

  public final boolean isInitialized();
    Code:
       0: aload_0
       1: getfield      #13                 // Field memoizedIsInitialized:B
       4: istore_1
       5: iload_1
       6: iconst_1
       7: if_icmpne     12
      10: iconst_1
      11: ireturn
      12: iload_1
      13: ifne          18
      16: iconst_0
      17: ireturn
      18: aload_0
      19: invokevirtual #72                 // Method hasCacheCapacity:()Z
      22: ifne          32
      25: aload_0
      26: iconst_0
      27: putfield      #13                 // Field memoizedIsInitialized:B
      30: iconst_0
      31: ireturn
      32: aload_0
      33: invokevirtual #73                 // Method hasIoClass:()Z
      36: ifne          46
      39: aload_0
      40: iconst_0
      41: putfield      #13                 // Field memoizedIsInitialized:B
      44: iconst_0
      45: ireturn
      46: aload_0
      47: invokevirtual #74                 // Method hasMapClass:()Z
      50: ifne          60
      53: aload_0
      54: iconst_0
      55: putfield      #13                 // Field memoizedIsInitialized:B
      58: iconst_0
      59: ireturn
      60: aload_0
      61: invokevirtual #75                 // Method hasBackingMap:()Z
      64: ifne          74
      67: aload_0
      68: iconst_0
      69: putfield      #13                 // Field memoizedIsInitialized:B
      72: iconst_0
      73: ireturn
      74: aload_0
      75: invokevirtual #76                 // Method getBackingMap:()Lorg/apache/hadoop/hbase/shaded/protobuf/generated/BucketCacheProtos$BackingMap;
      78: invokevirtual #77                 // Method org/apache/hadoop/hbase/shaded/protobuf/generated/BucketCacheProtos$BackingMap.isInitialized:()Z
      81: ifne          91
      84: aload_0
      85: iconst_0
      86: putfield      #13                 // Field memoizedIsInitialized:B
      89: iconst_0
      90: ireturn
      91: aload_0
      92: iconst_1
      93: putfield      #13                 // Field memoizedIsInitialized:B
      96: iconst_1
      97: ireturn

  public void writeTo(org.apache.hbase.thirdparty.com.google.protobuf.CodedOutputStream) throws java.io.IOException;
    Code:
       0: aload_0
       1: getfield      #4                  // Field bitField0_:I
       4: iconst_1
       5: iand
       6: iconst_1
       7: if_icmpne     19
      10: aload_1
      11: iconst_1
      12: aload_0
      13: getfield      #9                  // Field cacheCapacity_:J
      16: invokevirtual #78                 // Method org/apache/hbase/thirdparty/com/google/protobuf/CodedOutputStream.writeInt64:(IJ)V
      19: aload_0
      20: getfield      #4                  // Field bitField0_:I
      23: iconst_2
      24: iand
      25: iconst_2
      26: if_icmpne     38
      29: aload_1
      30: iconst_2
      31: aload_0
      32: getfield      #8                  // Field ioClass_:Ljava/lang/Object;
      35: invokestatic  #79                 // Method org/apache/hbase/thirdparty/com/google/protobuf/GeneratedMessageV3.writeString:(Lorg/apache/hbase/thirdparty/com/google/protobuf/CodedOutputStream;ILjava/lang/Object;)V
      38: aload_0
      39: getfield      #4                  // Field bitField0_:I
      42: iconst_4
      43: iand
      44: iconst_4
      45: if_icmpne     57
      48: aload_1
      49: iconst_3
      50: aload_0
      51: getfield      #7                  // Field mapClass_:Ljava/lang/Object;
      54: invokestatic  #79                 // Method org/apache/hbase/thirdparty/com/google/protobuf/GeneratedMessageV3.writeString:(Lorg/apache/hbase/thirdparty/com/google/protobuf/CodedOutputStream;ILjava/lang/Object;)V
      57: aload_1
      58: aload_0
      59: invokespecial #3                  // Method internalGetDeserializers:()Lorg/apache/hbase/thirdparty/com/google/protobuf/MapField;
      62: getstatic     #24                 // Field org/apache/hadoop/hbase/shaded/protobuf/generated/BucketCacheProtos$BucketCacheEntry$DeserializersDefaultEntryHolder.defaultEntry:Lorg/apache/hbase/thirdparty/com/google/protobuf/MapEntry;
      65: iconst_4
      66: invokestatic  #80                 // Method org/apache/hbase/thirdparty/com/google/protobuf/GeneratedMessageV3.serializeIntegerMapTo:(Lorg/apache/hbase/thirdparty/com/google/protobuf/CodedOutputStream;Lorg/apache/hbase/thirdparty/com/google/protobuf/MapField;Lorg/apache/hbase/thirdparty/com/google/protobuf/MapEntry;I)V
      69: aload_0
      70: getfield      #4                  // Field bitField0_:I
      73: bipush        8
      75: iand
      76: bipush        8
      78: if_icmpne     90
      81: aload_1
      82: iconst_5
      83: aload_0
      84: invokevirtual #76                 // Method getBackingMap:()Lorg/apache/hadoop/hbase/shaded/protobuf/generated/BucketCacheProtos$BackingMap;
      87: invokevirtual #81                 // Method org/apache/hbase/thirdparty/com/google/protobuf/CodedOutputStream.writeMessage:(ILorg/apache/hbase/thirdparty/com/google/protobuf/MessageLite;)V
      90: aload_0
      91: getfield      #2                  // Field unknownFields:Lorg/apache/hbase/thirdparty/com/google/protobuf/UnknownFieldSet;
      94: aload_1
      95: invokevirtual #82                 // Method org/apache/hbase/thirdparty/com/google/protobuf/UnknownFieldSet.writeTo:(Lorg/apache/hbase/thirdparty/com/google/protobuf/CodedOutputStream;)V
      98: return

  public int getSerializedSize();
    Code:
       0: aload_0
       1: getfield      #83                 // Field memoizedSize:I
       4: istore_1
       5: iload_1
       6: iconst_m1
       7: if_icmpeq     12
      10: iload_1
      11: ireturn
      12: iconst_0
      13: istore_1
      14: aload_0
      15: getfield      #4                  // Field bitField0_:I
      18: iconst_1
      19: iand
      20: iconst_1
      21: if_icmpne     35
      24: iload_1
      25: iconst_1
      26: aload_0
      27: getfield      #9                  // Field cacheCapacity_:J
      30: invokestatic  #84                 // Method org/apache/hbase/thirdparty/com/google/protobuf/CodedOutputStream.computeInt64Size:(IJ)I
      33: iadd
      34: istore_1
      35: aload_0
      36: getfield      #4                  // Field bitField0_:I
      39: iconst_2
      40: iand
      41: iconst_2
      42: if_icmpne     56
      45: iload_1
      46: iconst_2
      47: aload_0
      48: getfield      #8                  // Field ioClass_:Ljava/lang/Object;
      51: invokestatic  #85                 // Method org/apache/hbase/thirdparty/com/google/protobuf/GeneratedMessageV3.computeStringSize:(ILjava/lang/Object;)I
      54: iadd
      55: istore_1
      56: aload_0
      57: getfield      #4                  // Field bitField0_:I
      60: iconst_4
      61: iand
      62: iconst_4
      63: if_icmpne     77
      66: iload_1
      67: iconst_3
      68: aload_0
      69: getfield      #7                  // Field mapClass_:Ljava/lang/Object;
      72: invokestatic  #85                 // Method org/apache/hbase/thirdparty/com/google/protobuf/GeneratedMessageV3.computeStringSize:(ILjava/lang/Object;)I
      75: iadd
      76: istore_1
      77: aload_0
      78: invokespecial #3                  // Method internalGetDeserializers:()Lorg/apache/hbase/thirdparty/com/google/protobuf/MapField;
      81: invokevirtual #63                 // Method org/apache/hbase/thirdparty/com/google/protobuf/MapField.getMap:()Ljava/util/Map;
      84: invokeinterface #86,  1           // InterfaceMethod java/util/Map.entrySet:()Ljava/util/Set;
      89: invokeinterface #87,  1           // InterfaceMethod java/util/Set.iterator:()Ljava/util/Iterator;
      94: astore_2
      95: aload_2
      96: invokeinterface #88,  1           // InterfaceMethod java/util/Iterator.hasNext:()Z
     101: ifeq          155
     104: aload_2
     105: invokeinterface #89,  1           // InterfaceMethod java/util/Iterator.next:()Ljava/lang/Object;
     110: checkcast     #90                 // class java/util/Map$Entry
     113: astore_3
     114: getstatic     #24                 // Field org/apache/hadoop/hbase/shaded/protobuf/generated/BucketCacheProtos$BucketCacheEntry$DeserializersDefaultEntryHolder.defaultEntry:Lorg/apache/hbase/thirdparty/com/google/protobuf/MapEntry;
     117: invokevirtual #91                 // Method org/apache/hbase/thirdparty/com/google/protobuf/MapEntry.newBuilderForType:()Lorg/apache/hbase/thirdparty/com/google/protobuf/MapEntry$Builder;
     120: aload_3
     121: invokeinterface #92,  1           // InterfaceMethod java/util/Map$Entry.getKey:()Ljava/lang/Object;
     126: invokevirtual #93                 // Method org/apache/hbase/thirdparty/com/google/protobuf/MapEntry$Builder.setKey:(Ljava/lang/Object;)Lorg/apache/hbase/thirdparty/com/google/protobuf/MapEntry$Builder;
     129: aload_3
     130: invokeinterface #94,  1           // InterfaceMethod java/util/Map$Entry.getValue:()Ljava/lang/Object;
     135: invokevirtual #95                 // Method org/apache/hbase/thirdparty/com/google/protobuf/MapEntry$Builder.setValue:(Ljava/lang/Object;)Lorg/apache/hbase/thirdparty/com/google/protobuf/MapEntry$Builder;
     138: invokevirtual #96                 // Method org/apache/hbase/thirdparty/com/google/protobuf/MapEntry$Builder.build:()Lorg/apache/hbase/thirdparty/com/google/protobuf/MapEntry;
     141: astore        4
     143: iload_1
     144: iconst_4
     145: aload         4
     147: invokestatic  #97                 // Method org/apache/hbase/thirdparty/com/google/protobuf/CodedOutputStream.computeMessageSize:(ILorg/apache/hbase/thirdparty/com/google/protobuf/MessageLite;)I
     150: iadd
     151: istore_1
     152: goto          95
     155: aload_0
     156: getfield      #4                  // Field bitField0_:I
     159: bipush        8
     161: iand
     162: bipush        8
     164: if_icmpne     178
     167: iload_1
     168: iconst_5
     169: aload_0
     170: invokevirtual #76                 // Method getBackingMap:()Lorg/apache/hadoop/hbase/shaded/protobuf/generated/BucketCacheProtos$BackingMap;
     173: invokestatic  #97                 // Method org/apache/hbase/thirdparty/com/google/protobuf/CodedOutputStream.computeMessageSize:(ILorg/apache/hbase/thirdparty/com/google/protobuf/MessageLite;)I
     176: iadd
     177: istore_1
     178: iload_1
     179: aload_0
     180: getfield      #2                  // Field unknownFields:Lorg/apache/hbase/thirdparty/com/google/protobuf/UnknownFieldSet;
     183: invokevirtual #98                 // Method org/apache/hbase/thirdparty/com/google/protobuf/UnknownFieldSet.getSerializedSize:()I
     186: iadd
     187: istore_1
     188: aload_0
     189: iload_1
     190: putfield      #83                 // Field memoizedSize:I
     193: iload_1
     194: ireturn

  public boolean equals(java.lang.Object);
    Code:
       0: aload_1
       1: aload_0
       2: if_acmpne     7
       5: iconst_1
       6: ireturn
       7: aload_1
       8: instanceof    #54                 // class org/apache/hadoop/hbase/shaded/protobuf/generated/BucketCacheProtos$BucketCacheEntry
      11: ifne          20
      14: aload_0
      15: aload_1
      16: invokespecial #99                 // Method org/apache/hbase/thirdparty/com/google/protobuf/GeneratedMessageV3.equals:(Ljava/lang/Object;)Z
      19: ireturn
      20: aload_1
      21: checkcast     #54                 // class org/apache/hadoop/hbase/shaded/protobuf/generated/BucketCacheProtos$BucketCacheEntry
      24: astore_2
      25: iconst_1
      26: istore_3
      27: iload_3
      28: ifeq          46
      31: aload_0
      32: invokevirtual #72                 // Method hasCacheCapacity:()Z
      35: aload_2
      36: invokevirtual #72                 // Method hasCacheCapacity:()Z
      39: if_icmpne     46
      42: iconst_1
      43: goto          47
      46: iconst_0
      47: istore_3
      48: aload_0
      49: invokevirtual #72                 // Method hasCacheCapacity:()Z
      52: ifeq          77
      55: iload_3
      56: ifeq          75
      59: aload_0
      60: invokevirtual #100                // Method getCacheCapacity:()J
      63: aload_2
      64: invokevirtual #100                // Method getCacheCapacity:()J
      67: lcmp
      68: ifne          75
      71: iconst_1
      72: goto          76
      75: iconst_0
      76: istore_3
      77: iload_3
      78: ifeq          96
      81: aload_0
      82: invokevirtual #73                 // Method hasIoClass:()Z
      85: aload_2
      86: invokevirtual #73                 // Method hasIoClass:()Z
      89: if_icmpne     96
      92: iconst_1
      93: goto          97
      96: iconst_0
      97: istore_3
      98: aload_0
      99: invokevirtual #73                 // Method hasIoClass:()Z
     102: ifeq          129
     105: iload_3
     106: ifeq          127
     109: aload_0
     110: invokevirtual #101                // Method getIoClass:()Ljava/lang/String;
     113: aload_2
     114: invokevirtual #101                // Method getIoClass:()Ljava/lang/String;
     117: invokevirtual #102                // Method java/lang/String.equals:(Ljava/lang/Object;)Z
     120: ifeq          127
     123: iconst_1
     124: goto          128
     127: iconst_0
     128: istore_3
     129: iload_3
     130: ifeq          148
     133: aload_0
     134: invokevirtual #74                 // Method hasMapClass:()Z
     137: aload_2
     138: invokevirtual #74                 // Method hasMapClass:()Z
     141: if_icmpne     148
     144: iconst_1
     145: goto          149
     148: iconst_0
     149: istore_3
     150: aload_0
     151: invokevirtual #74                 // Method hasMapClass:()Z
     154: ifeq          181
     157: iload_3
     158: ifeq          179
     161: aload_0
     162: invokevirtual #103                // Method getMapClass:()Ljava/lang/String;
     165: aload_2
     166: invokevirtual #103                // Method getMapClass:()Ljava/lang/String;
     169: invokevirtual #102                // Method java/lang/String.equals:(Ljava/lang/Object;)Z
     172: ifeq          179
     175: iconst_1
     176: goto          180
     179: iconst_0
     180: istore_3
     181: iload_3
     182: ifeq          203
     185: aload_0
     186: invokespecial #3                  // Method internalGetDeserializers:()Lorg/apache/hbase/thirdparty/com/google/protobuf/MapField;
     189: aload_2
     190: invokespecial #3                  // Method internalGetDeserializers:()Lorg/apache/hbase/thirdparty/com/google/protobuf/MapField;
     193: invokevirtual #104                // Method org/apache/hbase/thirdparty/com/google/protobuf/MapField.equals:(Ljava/lang/Object;)Z
     196: ifeq          203
     199: iconst_1
     200: goto          204
     203: iconst_0
     204: istore_3
     205: iload_3
     206: ifeq          224
     209: aload_0
     210: invokevirtual #75                 // Method hasBackingMap:()Z
     213: aload_2
     214: invokevirtual #75                 // Method hasBackingMap:()Z
     217: if_icmpne     224
     220: iconst_1
     221: goto          225
     224: iconst_0
     225: istore_3
     226: aload_0
     227: invokevirtual #75                 // Method hasBackingMap:()Z
     230: ifeq          257
     233: iload_3
     234: ifeq          255
     237: aload_0
     238: invokevirtual #76                 // Method getBackingMap:()Lorg/apache/hadoop/hbase/shaded/protobuf/generated/BucketCacheProtos$BackingMap;
     241: aload_2
     242: invokevirtual #76                 // Method getBackingMap:()Lorg/apache/hadoop/hbase/shaded/protobuf/generated/BucketCacheProtos$BackingMap;
     245: invokevirtual #105                // Method org/apache/hadoop/hbase/shaded/protobuf/generated/BucketCacheProtos$BackingMap.equals:(Ljava/lang/Object;)Z
     248: ifeq          255
     251: iconst_1
     252: goto          256
     255: iconst_0
     256: istore_3
     257: iload_3
     258: ifeq          279
     261: aload_0
     262: getfield      #2                  // Field unknownFields:Lorg/apache/hbase/thirdparty/com/google/protobuf/UnknownFieldSet;
     265: aload_2
     266: getfield      #2                  // Field unknownFields:Lorg/apache/hbase/thirdparty/com/google/protobuf/UnknownFieldSet;
     269: invokevirtual #106                // Method org/apache/hbase/thirdparty/com/google/protobuf/UnknownFieldSet.equals:(Ljava/lang/Object;)Z
     272: ifeq          279
     275: iconst_1
     276: goto          280
     279: iconst_0
     280: istore_3
     281: iload_3
     282: ireturn

  public int hashCode();
    Code:
       0: aload_0
       1: getfield      #107                // Field memoizedHashCode:I
       4: ifeq          12
       7: aload_0
       8: getfield      #107                // Field memoizedHashCode:I
      11: ireturn
      12: bipush        41
      14: istore_1
      15: bipush        19
      17: iload_1
      18: imul
      19: invokestatic  #108                // Method getDescriptor:()Lorg/apache/hbase/thirdparty/com/google/protobuf/Descriptors$Descriptor;
      22: invokevirtual #109                // Method java/lang/Object.hashCode:()I
      25: iadd
      26: istore_1
      27: aload_0
      28: invokevirtual #72                 // Method hasCacheCapacity:()Z
      31: ifeq          54
      34: bipush        37
      36: iload_1
      37: imul
      38: iconst_1
      39: iadd
      40: istore_1
      41: bipush        53
      43: iload_1
      44: imul
      45: aload_0
      46: invokevirtual #100                // Method getCacheCapacity:()J
      49: invokestatic  #110                // Method org/apache/hbase/thirdparty/com/google/protobuf/Internal.hashLong:(J)I
      52: iadd
      53: istore_1
      54: aload_0
      55: invokevirtual #73                 // Method hasIoClass:()Z
      58: ifeq          81
      61: bipush        37
      63: iload_1
      64: imul
      65: iconst_2
      66: iadd
      67: istore_1
      68: bipush        53
      70: iload_1
      71: imul
      72: aload_0
      73: invokevirtual #101                // Method getIoClass:()Ljava/lang/String;
      76: invokevirtual #111                // Method java/lang/String.hashCode:()I
      79: iadd
      80: istore_1
      81: aload_0
      82: invokevirtual #74                 // Method hasMapClass:()Z
      85: ifeq          108
      88: bipush        37
      90: iload_1
      91: imul
      92: iconst_3
      93: iadd
      94: istore_1
      95: bipush        53
      97: iload_1
      98: imul
      99: aload_0
     100: invokevirtual #103                // Method getMapClass:()Ljava/lang/String;
     103: invokevirtual #111                // Method java/lang/String.hashCode:()I
     106: iadd
     107: istore_1
     108: aload_0
     109: invokespecial #3                  // Method internalGetDeserializers:()Lorg/apache/hbase/thirdparty/com/google/protobuf/MapField;
     112: invokevirtual #63                 // Method org/apache/hbase/thirdparty/com/google/protobuf/MapField.getMap:()Ljava/util/Map;
     115: invokeinterface #112,  1          // InterfaceMethod java/util/Map.isEmpty:()Z
     120: ifne          143
     123: bipush        37
     125: iload_1
     126: imul
     127: iconst_4
     128: iadd
     129: istore_1
     130: bipush        53
     132: iload_1
     133: imul
     134: aload_0
     135: invokespecial #3                  // Method internalGetDeserializers:()Lorg/apache/hbase/thirdparty/com/google/protobuf/MapField;
     138: invokevirtual #113                // Method org/apache/hbase/thirdparty/com/google/protobuf/MapField.hashCode:()I
     141: iadd
     142: istore_1
     143: aload_0
     144: invokevirtual #75                 // Method hasBackingMap:()Z
     147: ifeq          170
     150: bipush        37
     152: iload_1
     153: imul
     154: iconst_5
     155: iadd
     156: istore_1
     157: bipush        53
     159: iload_1
     160: imul
     161: aload_0
     162: invokevirtual #76                 // Method getBackingMap:()Lorg/apache/hadoop/hbase/shaded/protobuf/generated/BucketCacheProtos$BackingMap;
     165: invokevirtual #114                // Method org/apache/hadoop/hbase/shaded/protobuf/generated/BucketCacheProtos$BackingMap.hashCode:()I
     168: iadd
     169: istore_1
     170: bipush        29
     172: iload_1
     173: imul
     174: aload_0
     175: getfield      #2                  // Field unknownFields:Lorg/apache/hbase/thirdparty/com/google/protobuf/UnknownFieldSet;
     178: invokevirtual #115                // Method org/apache/hbase/thirdparty/com/google/protobuf/UnknownFieldSet.hashCode:()I
     181: iadd
     182: istore_1
     183: aload_0
     184: iload_1
     185: putfield      #107                // Field memoizedHashCode:I
     188: iload_1
     189: ireturn

  public static org.apache.hadoop.hbase.shaded.protobuf.generated.BucketCacheProtos$BucketCacheEntry parseFrom(java.nio.ByteBuffer) throws org.apache.hbase.thirdparty.com.google.protobuf.InvalidProtocolBufferException;
    Code:
       0: getstatic     #116                // Field PARSER:Lorg/apache/hbase/thirdparty/com/google/protobuf/Parser;
       3: aload_0
       4: invokeinterface #117,  2          // InterfaceMethod org/apache/hbase/thirdparty/com/google/protobuf/Parser.parseFrom:(Ljava/nio/ByteBuffer;)Ljava/lang/Object;
       9: checkcast     #54                 // class org/apache/hadoop/hbase/shaded/protobuf/generated/BucketCacheProtos$BucketCacheEntry
      12: areturn

  public static org.apache.hadoop.hbase.shaded.protobuf.generated.BucketCacheProtos$BucketCacheEntry parseFrom(java.nio.ByteBuffer, org.apache.hbase.thirdparty.com.google.protobuf.ExtensionRegistryLite) throws org.apache.hbase.thirdparty.com.google.protobuf.InvalidProtocolBufferException;
    Code:
       0: getstatic     #116                // Field PARSER:Lorg/apache/hbase/thirdparty/com/google/protobuf/Parser;
       3: aload_0
       4: aload_1
       5: invokeinterface #118,  3          // InterfaceMethod org/apache/hbase/thirdparty/com/google/protobuf/Parser.parseFrom:(Ljava/nio/ByteBuffer;Lorg/apache/hbase/thirdparty/com/google/protobuf/ExtensionRegistryLite;)Ljava/lang/Object;
      10: checkcast     #54                 // class org/apache/hadoop/hbase/shaded/protobuf/generated/BucketCacheProtos$BucketCacheEntry
      13: areturn

  public static org.apache.hadoop.hbase.shaded.protobuf.generated.BucketCacheProtos$BucketCacheEntry parseFrom(org.apache.hbase.thirdparty.com.google.protobuf.ByteString) throws org.apache.hbase.thirdparty.com.google.protobuf.InvalidProtocolBufferException;
    Code:
       0: getstatic     #116                // Field PARSER:Lorg/apache/hbase/thirdparty/com/google/protobuf/Parser;
       3: aload_0
       4: invokeinterface #119,  2          // InterfaceMethod org/apache/hbase/thirdparty/com/google/protobuf/Parser.parseFrom:(Lorg/apache/hbase/thirdparty/com/google/protobuf/ByteString;)Ljava/lang/Object;
       9: checkcast     #54                 // class org/apache/hadoop/hbase/shaded/protobuf/generated/BucketCacheProtos$BucketCacheEntry
      12: areturn

  public static org.apache.hadoop.hbase.shaded.protobuf.generated.BucketCacheProtos$BucketCacheEntry parseFrom(org.apache.hbase.thirdparty.com.google.protobuf.ByteString, org.apache.hbase.thirdparty.com.google.protobuf.ExtensionRegistryLite) throws org.apache.hbase.thirdparty.com.google.protobuf.InvalidProtocolBufferException;
    Code:
       0: getstatic     #116                // Field PARSER:Lorg/apache/hbase/thirdparty/com/google/protobuf/Parser;
       3: aload_0
       4: aload_1
       5: invokeinterface #120,  3          // InterfaceMethod org/apache/hbase/thirdparty/com/google/protobuf/Parser.parseFrom:(Lorg/apache/hbase/thirdparty/com/google/protobuf/ByteString;Lorg/apache/hbase/thirdparty/com/google/protobuf/ExtensionRegistryLite;)Ljava/lang/Object;
      10: checkcast     #54                 // class org/apache/hadoop/hbase/shaded/protobuf/generated/BucketCacheProtos$BucketCacheEntry
      13: areturn

  public static org.apache.hadoop.hbase.shaded.protobuf.generated.BucketCacheProtos$BucketCacheEntry parseFrom(byte[]) throws org.apache.hbase.thirdparty.com.google.protobuf.InvalidProtocolBufferException;
    Code:
       0: getstatic     #116                // Field PARSER:Lorg/apache/hbase/thirdparty/com/google/protobuf/Parser;
       3: aload_0
       4: invokeinterface #121,  2          // InterfaceMethod org/apache/hbase/thirdparty/com/google/protobuf/Parser.parseFrom:([B)Ljava/lang/Object;
       9: checkcast     #54                 // class org/apache/hadoop/hbase/shaded/protobuf/generated/BucketCacheProtos$BucketCacheEntry
      12: areturn

  public static org.apache.hadoop.hbase.shaded.protobuf.generated.BucketCacheProtos$BucketCacheEntry parseFrom(byte[], org.apache.hbase.thirdparty.com.google.protobuf.ExtensionRegistryLite) throws org.apache.hbase.thirdparty.com.google.protobuf.InvalidProtocolBufferException;
    Code:
       0: getstatic     #116                // Field PARSER:Lorg/apache/hbase/thirdparty/com/google/protobuf/Parser;
       3: aload_0
       4: aload_1
       5: invokeinterface #122,  3          // InterfaceMethod org/apache/hbase/thirdparty/com/google/protobuf/Parser.parseFrom:([BLorg/apache/hbase/thirdparty/com/google/protobuf/ExtensionRegistryLite;)Ljava/lang/Object;
      10: checkcast     #54                 // class org/apache/hadoop/hbase/shaded/protobuf/generated/BucketCacheProtos$BucketCacheEntry
      13: areturn

  public static org.apache.hadoop.hbase.shaded.protobuf.generated.BucketCacheProtos$BucketCacheEntry parseFrom(java.io.InputStream) throws java.io.IOException;
    Code:
       0: getstatic     #116                // Field PARSER:Lorg/apache/hbase/thirdparty/com/google/protobuf/Parser;
       3: aload_0
       4: invokestatic  #123                // Method org/apache/hbase/thirdparty/com/google/protobuf/GeneratedMessageV3.parseWithIOException:(Lorg/apache/hbase/thirdparty/com/google/protobuf/Parser;Ljava/io/InputStream;)Lorg/apache/hbase/thirdparty/com/google/protobuf/Message;
       7: checkcast     #54                 // class org/apache/hadoop/hbase/shaded/protobuf/generated/BucketCacheProtos$BucketCacheEntry
      10: areturn

  public static org.apache.hadoop.hbase.shaded.protobuf.generated.BucketCacheProtos$BucketCacheEntry parseFrom(java.io.InputStream, org.apache.hbase.thirdparty.com.google.protobuf.ExtensionRegistryLite) throws java.io.IOException;
    Code:
       0: getstatic     #116                // Field PARSER:Lorg/apache/hbase/thirdparty/com/google/protobuf/Parser;
       3: aload_0
       4: aload_1
       5: invokestatic  #124                // Method org/apache/hbase/thirdparty/com/google/protobuf/GeneratedMessageV3.parseWithIOException:(Lorg/apache/hbase/thirdparty/com/google/protobuf/Parser;Ljava/io/InputStream;Lorg/apache/hbase/thirdparty/com/google/protobuf/ExtensionRegistryLite;)Lorg/apache/hbase/thirdparty/com/google/protobuf/Message;
       8: checkcast     #54                 // class org/apache/hadoop/hbase/shaded/protobuf/generated/BucketCacheProtos$BucketCacheEntry
      11: areturn

  public static org.apache.hadoop.hbase.shaded.protobuf.generated.BucketCacheProtos$BucketCacheEntry parseDelimitedFrom(java.io.InputStream) throws java.io.IOException;
    Code:
       0: getstatic     #116                // Field PARSER:Lorg/apache/hbase/thirdparty/com/google/protobuf/Parser;
       3: aload_0
       4: invokestatic  #125                // Method org/apache/hbase/thirdparty/com/google/protobuf/GeneratedMessageV3.parseDelimitedWithIOException:(Lorg/apache/hbase/thirdparty/com/google/protobuf/Parser;Ljava/io/InputStream;)Lorg/apache/hbase/thirdparty/com/google/protobuf/Message;
       7: checkcast     #54                 // class org/apache/hadoop/hbase/shaded/protobuf/generated/BucketCacheProtos$BucketCacheEntry
      10: areturn

  public static org.apache.hadoop.hbase.shaded.protobuf.generated.BucketCacheProtos$BucketCacheEntry parseDelimitedFrom(java.io.InputStream, org.apache.hbase.thirdparty.com.google.protobuf.ExtensionRegistryLite) throws java.io.IOException;
    Code:
       0: getstatic     #116                // Field PARSER:Lorg/apache/hbase/thirdparty/com/google/protobuf/Parser;
       3: aload_0
       4: aload_1
       5: invokestatic  #126                // Method org/apache/hbase/thirdparty/com/google/protobuf/GeneratedMessageV3.parseDelimitedWithIOException:(Lorg/apache/hbase/thirdparty/com/google/protobuf/Parser;Ljava/io/InputStream;Lorg/apache/hbase/thirdparty/com/google/protobuf/ExtensionRegistryLite;)Lorg/apache/hbase/thirdparty/com/google/protobuf/Message;
       8: checkcast     #54                 // class org/apache/hadoop/hbase/shaded/protobuf/generated/BucketCacheProtos$BucketCacheEntry
      11: areturn

  public static org.apache.hadoop.hbase.shaded.protobuf.generated.BucketCacheProtos$BucketCacheEntry parseFrom(org.apache.hbase.thirdparty.com.google.protobuf.CodedInputStream) throws java.io.IOException;
    Code:
       0: getstatic     #116                // Field PARSER:Lorg/apache/hbase/thirdparty/com/google/protobuf/Parser;
       3: aload_0
       4: invokestatic  #127                // Method org/apache/hbase/thirdparty/com/google/protobuf/GeneratedMessageV3.parseWithIOException:(Lorg/apache/hbase/thirdparty/com/google/protobuf/Parser;Lorg/apache/hbase/thirdparty/com/google/protobuf/CodedInputStream;)Lorg/apache/hbase/thirdparty/com/google/protobuf/Message;
       7: checkcast     #54                 // class org/apache/hadoop/hbase/shaded/protobuf/generated/BucketCacheProtos$BucketCacheEntry
      10: areturn

  public static org.apache.hadoop.hbase.shaded.protobuf.generated.BucketCacheProtos$BucketCacheEntry parseFrom(org.apache.hbase.thirdparty.com.google.protobuf.CodedInputStream, org.apache.hbase.thirdparty.com.google.protobuf.ExtensionRegistryLite) throws java.io.IOException;
    Code:
       0: getstatic     #116                // Field PARSER:Lorg/apache/hbase/thirdparty/com/google/protobuf/Parser;
       3: aload_0
       4: aload_1
       5: invokestatic  #128                // Method org/apache/hbase/thirdparty/com/google/protobuf/GeneratedMessageV3.parseWithIOException:(Lorg/apache/hbase/thirdparty/com/google/protobuf/Parser;Lorg/apache/hbase/thirdparty/com/google/protobuf/CodedInputStream;Lorg/apache/hbase/thirdparty/com/google/protobuf/ExtensionRegistryLite;)Lorg/apache/hbase/thirdparty/com/google/protobuf/Message;
       8: checkcast     #54                 // class org/apache/hadoop/hbase/shaded/protobuf/generated/BucketCacheProtos$BucketCacheEntry
      11: areturn

  public org.apache.hadoop.hbase.shaded.protobuf.generated.BucketCacheProtos$BucketCacheEntry$Builder newBuilderForType();
    Code:
       0: invokestatic  #129                // Method newBuilder:()Lorg/apache/hadoop/hbase/shaded/protobuf/generated/BucketCacheProtos$BucketCacheEntry$Builder;
       3: areturn

  public static org.apache.hadoop.hbase.shaded.protobuf.generated.BucketCacheProtos$BucketCacheEntry$Builder newBuilder();
    Code:
       0: getstatic     #130                // Field DEFAULT_INSTANCE:Lorg/apache/hadoop/hbase/shaded/protobuf/generated/BucketCacheProtos$BucketCacheEntry;
       3: invokevirtual #131                // Method toBuilder:()Lorg/apache/hadoop/hbase/shaded/protobuf/generated/BucketCacheProtos$BucketCacheEntry$Builder;
       6: areturn

  public static org.apache.hadoop.hbase.shaded.protobuf.generated.BucketCacheProtos$BucketCacheEntry$Builder newBuilder(org.apache.hadoop.hbase.shaded.protobuf.generated.BucketCacheProtos$BucketCacheEntry);
    Code:
       0: getstatic     #130                // Field DEFAULT_INSTANCE:Lorg/apache/hadoop/hbase/shaded/protobuf/generated/BucketCacheProtos$BucketCacheEntry;
       3: invokevirtual #131                // Method toBuilder:()Lorg/apache/hadoop/hbase/shaded/protobuf/generated/BucketCacheProtos$BucketCacheEntry$Builder;
       6: aload_0
       7: invokevirtual #132                // Method org/apache/hadoop/hbase/shaded/protobuf/generated/BucketCacheProtos$BucketCacheEntry$Builder.mergeFrom:(Lorg/apache/hadoop/hbase/shaded/protobuf/generated/BucketCacheProtos$BucketCacheEntry;)Lorg/apache/hadoop/hbase/shaded/protobuf/generated/BucketCacheProtos$BucketCacheEntry$Builder;
      10: areturn

  public org.apache.hadoop.hbase.shaded.protobuf.generated.BucketCacheProtos$BucketCacheEntry$Builder toBuilder();
    Code:
       0: aload_0
       1: getstatic     #130                // Field DEFAULT_INSTANCE:Lorg/apache/hadoop/hbase/shaded/protobuf/generated/BucketCacheProtos$BucketCacheEntry;
       4: if_acmpne     18
       7: new           #55                 // class org/apache/hadoop/hbase/shaded/protobuf/generated/BucketCacheProtos$BucketCacheEntry$Builder
      10: dup
      11: aconst_null
      12: invokespecial #133                // Method org/apache/hadoop/hbase/shaded/protobuf/generated/BucketCacheProtos$BucketCacheEntry$Builder."<init>":(Lorg/apache/hadoop/hbase/shaded/protobuf/generated/BucketCacheProtos$1;)V
      15: goto          30
      18: new           #55                 // class org/apache/hadoop/hbase/shaded/protobuf/generated/BucketCacheProtos$BucketCacheEntry$Builder
      21: dup
      22: aconst_null
      23: invokespecial #133                // Method org/apache/hadoop/hbase/shaded/protobuf/generated/BucketCacheProtos$BucketCacheEntry$Builder."<init>":(Lorg/apache/hadoop/hbase/shaded/protobuf/generated/BucketCacheProtos$1;)V
      26: aload_0
      27: invokevirtual #132                // Method org/apache/hadoop/hbase/shaded/protobuf/generated/BucketCacheProtos$BucketCacheEntry$Builder.mergeFrom:(Lorg/apache/hadoop/hbase/shaded/protobuf/generated/BucketCacheProtos$BucketCacheEntry;)Lorg/apache/hadoop/hbase/shaded/protobuf/generated/BucketCacheProtos$BucketCacheEntry$Builder;
      30: areturn

  protected org.apache.hadoop.hbase.shaded.protobuf.generated.BucketCacheProtos$BucketCacheEntry$Builder newBuilderForType(org.apache.hbase.thirdparty.com.google.protobuf.GeneratedMessageV3$BuilderParent);
    Code:
       0: new           #55                 // class org/apache/hadoop/hbase/shaded/protobuf/generated/BucketCacheProtos$BucketCacheEntry$Builder
       3: dup
       4: aload_1
       5: aconst_null
       6: invokespecial #134                // Method org/apache/hadoop/hbase/shaded/protobuf/generated/BucketCacheProtos$BucketCacheEntry$Builder."<init>":(Lorg/apache/hbase/thirdparty/com/google/protobuf/GeneratedMessageV3$BuilderParent;Lorg/apache/hadoop/hbase/shaded/protobuf/generated/BucketCacheProtos$1;)V
       9: astore_2
      10: aload_2
      11: areturn

  public static org.apache.hadoop.hbase.shaded.protobuf.generated.BucketCacheProtos$BucketCacheEntry getDefaultInstance();
    Code:
       0: getstatic     #130                // Field DEFAULT_INSTANCE:Lorg/apache/hadoop/hbase/shaded/protobuf/generated/BucketCacheProtos$BucketCacheEntry;
       3: areturn

  public static org.apache.hbase.thirdparty.com.google.protobuf.Parser<org.apache.hadoop.hbase.shaded.protobuf.generated.BucketCacheProtos$BucketCacheEntry> parser();
    Code:
       0: getstatic     #116                // Field PARSER:Lorg/apache/hbase/thirdparty/com/google/protobuf/Parser;
       3: areturn

  public org.apache.hbase.thirdparty.com.google.protobuf.Parser<org.apache.hadoop.hbase.shaded.protobuf.generated.BucketCacheProtos$BucketCacheEntry> getParserForType();
    Code:
       0: getstatic     #116                // Field PARSER:Lorg/apache/hbase/thirdparty/com/google/protobuf/Parser;
       3: areturn

  public org.apache.hadoop.hbase.shaded.protobuf.generated.BucketCacheProtos$BucketCacheEntry getDefaultInstanceForType();
    Code:
       0: getstatic     #130                // Field DEFAULT_INSTANCE:Lorg/apache/hadoop/hbase/shaded/protobuf/generated/BucketCacheProtos$BucketCacheEntry;
       3: areturn

  protected org.apache.hbase.thirdparty.com.google.protobuf.Message$Builder newBuilderForType(org.apache.hbase.thirdparty.com.google.protobuf.GeneratedMessageV3$BuilderParent);
    Code:
       0: aload_0
       1: aload_1
       2: invokevirtual #135                // Method newBuilderForType:(Lorg/apache/hbase/thirdparty/com/google/protobuf/GeneratedMessageV3$BuilderParent;)Lorg/apache/hadoop/hbase/shaded/protobuf/generated/BucketCacheProtos$BucketCacheEntry$Builder;
       5: areturn

  public org.apache.hbase.thirdparty.com.google.protobuf.Message$Builder toBuilder();
    Code:
       0: aload_0
       1: invokevirtual #131                // Method toBuilder:()Lorg/apache/hadoop/hbase/shaded/protobuf/generated/BucketCacheProtos$BucketCacheEntry$Builder;
       4: areturn

  public org.apache.hbase.thirdparty.com.google.protobuf.Message$Builder newBuilderForType();
    Code:
       0: aload_0
       1: invokevirtual #136                // Method newBuilderForType:()Lorg/apache/hadoop/hbase/shaded/protobuf/generated/BucketCacheProtos$BucketCacheEntry$Builder;
       4: areturn

  public org.apache.hbase.thirdparty.com.google.protobuf.MessageLite$Builder toBuilder();
    Code:
       0: aload_0
       1: invokevirtual #131                // Method toBuilder:()Lorg/apache/hadoop/hbase/shaded/protobuf/generated/BucketCacheProtos$BucketCacheEntry$Builder;
       4: areturn

  public org.apache.hbase.thirdparty.com.google.protobuf.MessageLite$Builder newBuilderForType();
    Code:
       0: aload_0
       1: invokevirtual #136                // Method newBuilderForType:()Lorg/apache/hadoop/hbase/shaded/protobuf/generated/BucketCacheProtos$BucketCacheEntry$Builder;
       4: areturn

  public org.apache.hbase.thirdparty.com.google.protobuf.MessageLite getDefaultInstanceForType();
    Code:
       0: aload_0
       1: invokevirtual #137                // Method getDefaultInstanceForType:()Lorg/apache/hadoop/hbase/shaded/protobuf/generated/BucketCacheProtos$BucketCacheEntry;
       4: areturn

  public org.apache.hbase.thirdparty.com.google.protobuf.Message getDefaultInstanceForType();
    Code:
       0: aload_0
       1: invokevirtual #137                // Method getDefaultInstanceForType:()Lorg/apache/hadoop/hbase/shaded/protobuf/generated/BucketCacheProtos$BucketCacheEntry;
       4: areturn

  static boolean access$500();
    Code:
       0: getstatic     #11                 // Field alwaysUseFieldBuilders:Z
       3: ireturn

  org.apache.hadoop.hbase.shaded.protobuf.generated.BucketCacheProtos$BucketCacheEntry(org.apache.hbase.thirdparty.com.google.protobuf.GeneratedMessageV3$Builder, org.apache.hadoop.hbase.shaded.protobuf.generated.BucketCacheProtos$1);
    Code:
       0: aload_0
       1: aload_1
       2: invokespecial #10                 // Method "<init>":(Lorg/apache/hbase/thirdparty/com/google/protobuf/GeneratedMessageV3$Builder;)V
       5: return

  static long access$702(org.apache.hadoop.hbase.shaded.protobuf.generated.BucketCacheProtos$BucketCacheEntry, long);
    Code:
       0: aload_0
       1: lload_1
       2: dup2_x1
       3: putfield      #9                  // Field cacheCapacity_:J
       6: lreturn

  static java.lang.Object access$802(org.apache.hadoop.hbase.shaded.protobuf.generated.BucketCacheProtos$BucketCacheEntry, java.lang.Object);
    Code:
       0: aload_0
       1: aload_1
       2: dup_x1
       3: putfield      #8                  // Field ioClass_:Ljava/lang/Object;
       6: areturn

  static java.lang.Object access$902(org.apache.hadoop.hbase.shaded.protobuf.generated.BucketCacheProtos$BucketCacheEntry, java.lang.Object);
    Code:
       0: aload_0
       1: aload_1
       2: dup_x1
       3: putfield      #7                  // Field mapClass_:Ljava/lang/Object;
       6: areturn

  static org.apache.hbase.thirdparty.com.google.protobuf.MapField access$1002(org.apache.hadoop.hbase.shaded.protobuf.generated.BucketCacheProtos$BucketCacheEntry, org.apache.hbase.thirdparty.com.google.protobuf.MapField);
    Code:
       0: aload_0
       1: aload_1
       2: dup_x1
       3: putfield      #6                  // Field deserializers_:Lorg/apache/hbase/thirdparty/com/google/protobuf/MapField;
       6: areturn

  static org.apache.hbase.thirdparty.com.google.protobuf.MapField access$1000(org.apache.hadoop.hbase.shaded.protobuf.generated.BucketCacheProtos$BucketCacheEntry);
    Code:
       0: aload_0
       1: getfield      #6                  // Field deserializers_:Lorg/apache/hbase/thirdparty/com/google/protobuf/MapField;
       4: areturn

  static org.apache.hadoop.hbase.shaded.protobuf.generated.BucketCacheProtos$BackingMap access$1102(org.apache.hadoop.hbase.shaded.protobuf.generated.BucketCacheProtos$BucketCacheEntry, org.apache.hadoop.hbase.shaded.protobuf.generated.BucketCacheProtos$BackingMap);
    Code:
       0: aload_0
       1: aload_1
       2: dup_x1
       3: putfield      #5                  // Field backingMap_:Lorg/apache/hadoop/hbase/shaded/protobuf/generated/BucketCacheProtos$BackingMap;
       6: areturn

  static int access$1202(org.apache.hadoop.hbase.shaded.protobuf.generated.BucketCacheProtos$BucketCacheEntry, int);
    Code:
       0: aload_0
       1: iload_1
       2: dup_x1
       3: putfield      #4                  // Field bitField0_:I
       6: ireturn

  static java.lang.Object access$800(org.apache.hadoop.hbase.shaded.protobuf.generated.BucketCacheProtos$BucketCacheEntry);
    Code:
       0: aload_0
       1: getfield      #8                  // Field ioClass_:Ljava/lang/Object;
       4: areturn

  static java.lang.Object access$900(org.apache.hadoop.hbase.shaded.protobuf.generated.BucketCacheProtos$BucketCacheEntry);
    Code:
       0: aload_0
       1: getfield      #7                  // Field mapClass_:Ljava/lang/Object;
       4: areturn

  static org.apache.hbase.thirdparty.com.google.protobuf.MapField access$1300(org.apache.hadoop.hbase.shaded.protobuf.generated.BucketCacheProtos$BucketCacheEntry);
    Code:
       0: aload_0
       1: invokespecial #3                  // Method internalGetDeserializers:()Lorg/apache/hbase/thirdparty/com/google/protobuf/MapField;
       4: areturn

  static org.apache.hbase.thirdparty.com.google.protobuf.UnknownFieldSet access$1400(org.apache.hadoop.hbase.shaded.protobuf.generated.BucketCacheProtos$BucketCacheEntry);
    Code:
       0: aload_0
       1: getfield      #2                  // Field unknownFields:Lorg/apache/hbase/thirdparty/com/google/protobuf/UnknownFieldSet;
       4: areturn

  org.apache.hadoop.hbase.shaded.protobuf.generated.BucketCacheProtos$BucketCacheEntry(org.apache.hbase.thirdparty.com.google.protobuf.CodedInputStream, org.apache.hbase.thirdparty.com.google.protobuf.ExtensionRegistryLite, org.apache.hadoop.hbase.shaded.protobuf.generated.BucketCacheProtos$1) throws org.apache.hbase.thirdparty.com.google.protobuf.InvalidProtocolBufferException;
    Code:
       0: aload_0
       1: aload_1
       2: aload_2
       3: invokespecial #1                  // Method "<init>":(Lorg/apache/hbase/thirdparty/com/google/protobuf/CodedInputStream;Lorg/apache/hbase/thirdparty/com/google/protobuf/ExtensionRegistryLite;)V
       6: return

  static {};
    Code:
       0: new           #54                 // class org/apache/hadoop/hbase/shaded/protobuf/generated/BucketCacheProtos$BucketCacheEntry
       3: dup
       4: invokespecial #16                 // Method "<init>":()V
       7: putstatic     #130                // Field DEFAULT_INSTANCE:Lorg/apache/hadoop/hbase/shaded/protobuf/generated/BucketCacheProtos$BucketCacheEntry;
      10: new           #138                // class org/apache/hadoop/hbase/shaded/protobuf/generated/BucketCacheProtos$BucketCacheEntry$1
      13: dup
      14: invokespecial #139                // Method org/apache/hadoop/hbase/shaded/protobuf/generated/BucketCacheProtos$BucketCacheEntry$1."<init>":()V
      17: putstatic     #116                // Field PARSER:Lorg/apache/hbase/thirdparty/com/google/protobuf/Parser;
      20: return
}
