Compiled from "BucketCache.java"
class org.apache.hadoop.hbase.io.hfile.bucket.BucketCache$3$1 implements org.apache.hadoop.hbase.io.hfile.CachedBlock {
  final java.util.Map$Entry val$e;

  final org.apache.hadoop.hbase.io.hfile.bucket.BucketCache$3 this$1;

  org.apache.hadoop.hbase.io.hfile.bucket.BucketCache$3$1(org.apache.hadoop.hbase.io.hfile.bucket.BucketCache$3, java.util.Map$Entry);
    Code:
       0: aload_0
       1: aload_1
       2: putfield      #1                  // Field this$1:Lorg/apache/hadoop/hbase/io/hfile/bucket/BucketCache$3;
       5: aload_0
       6: aload_2
       7: putfield      #2                  // Field val$e:Ljava/util/Map$Entry;
      10: aload_0
      11: invokespecial #3                  // Method java/lang/Object."<init>":()V
      14: return

  public java.lang.String toString();
    Code:
       0: aload_0
       1: aload_0
       2: getfield      #1                  // Field this$1:Lorg/apache/hadoop/hbase/io/hfile/bucket/BucketCache$3;
       5: invokestatic  #4                  // Method org/apache/hadoop/hbase/io/hfile/bucket/BucketCache$3.access$900:(Lorg/apache/hadoop/hbase/io/hfile/bucket/BucketCache$3;)J
       8: invokestatic  #5                  // Method org/apache/hadoop/hbase/io/hfile/BlockCacheUtil.toString:(Lorg/apache/hadoop/hbase/io/hfile/CachedBlock;J)Ljava/lang/String;
      11: areturn

  public org.apache.hadoop.hbase.io.hfile.BlockPriority getBlockPriority();
    Code:
       0: aload_0
       1: getfield      #2                  // Field val$e:Ljava/util/Map$Entry;
       4: invokeinterface #6,  1            // InterfaceMethod java/util/Map$Entry.getValue:()Ljava/lang/Object;
       9: checkcast     #7                  // class org/apache/hadoop/hbase/io/hfile/bucket/BucketCache$BucketEntry
      12: invokevirtual #8                  // Method org/apache/hadoop/hbase/io/hfile/bucket/BucketCache$BucketEntry.getPriority:()Lorg/apache/hadoop/hbase/io/hfile/BlockPriority;
      15: areturn

  public org.apache.hadoop.hbase.io.hfile.BlockType getBlockType();
    Code:
       0: aconst_null
       1: areturn

  public long getOffset();
    Code:
       0: aload_0
       1: getfield      #2                  // Field val$e:Ljava/util/Map$Entry;
       4: invokeinterface #9,  1            // InterfaceMethod java/util/Map$Entry.getKey:()Ljava/lang/Object;
       9: checkcast     #10                 // class org/apache/hadoop/hbase/io/hfile/BlockCacheKey
      12: invokevirtual #11                 // Method org/apache/hadoop/hbase/io/hfile/BlockCacheKey.getOffset:()J
      15: lreturn

  public long getSize();
    Code:
       0: aload_0
       1: getfield      #2                  // Field val$e:Ljava/util/Map$Entry;
       4: invokeinterface #6,  1            // InterfaceMethod java/util/Map$Entry.getValue:()Ljava/lang/Object;
       9: checkcast     #7                  // class org/apache/hadoop/hbase/io/hfile/bucket/BucketCache$BucketEntry
      12: invokevirtual #12                 // Method org/apache/hadoop/hbase/io/hfile/bucket/BucketCache$BucketEntry.getLength:()I
      15: i2l
      16: lreturn

  public long getCachedTime();
    Code:
       0: aload_0
       1: getfield      #2                  // Field val$e:Ljava/util/Map$Entry;
       4: invokeinterface #6,  1            // InterfaceMethod java/util/Map$Entry.getValue:()Ljava/lang/Object;
       9: checkcast     #7                  // class org/apache/hadoop/hbase/io/hfile/bucket/BucketCache$BucketEntry
      12: invokevirtual #13                 // Method org/apache/hadoop/hbase/io/hfile/bucket/BucketCache$BucketEntry.getCachedTime:()J
      15: lreturn

  public java.lang.String getFilename();
    Code:
       0: aload_0
       1: getfield      #2                  // Field val$e:Ljava/util/Map$Entry;
       4: invokeinterface #9,  1            // InterfaceMethod java/util/Map$Entry.getKey:()Ljava/lang/Object;
       9: checkcast     #10                 // class org/apache/hadoop/hbase/io/hfile/BlockCacheKey
      12: invokevirtual #14                 // Method org/apache/hadoop/hbase/io/hfile/BlockCacheKey.getHfileName:()Ljava/lang/String;
      15: areturn

  public int compareTo(org.apache.hadoop.hbase.io.hfile.CachedBlock);
    Code:
       0: aload_0
       1: invokevirtual #15                 // Method getFilename:()Ljava/lang/String;
       4: aload_1
       5: invokeinterface #16,  1           // InterfaceMethod org/apache/hadoop/hbase/io/hfile/CachedBlock.getFilename:()Ljava/lang/String;
      10: invokevirtual #17                 // Method java/lang/String.compareTo:(Ljava/lang/String;)I
      13: istore_2
      14: iload_2
      15: ifeq          20
      18: iload_2
      19: ireturn
      20: aload_0
      21: invokevirtual #18                 // Method getOffset:()J
      24: aload_1
      25: invokeinterface #19,  1           // InterfaceMethod org/apache/hadoop/hbase/io/hfile/CachedBlock.getOffset:()J
      30: invokestatic  #20                 // Method java/lang/Long.compare:(JJ)I
      33: istore_2
      34: iload_2
      35: ifeq          40
      38: iload_2
      39: ireturn
      40: aload_1
      41: invokeinterface #21,  1           // InterfaceMethod org/apache/hadoop/hbase/io/hfile/CachedBlock.getCachedTime:()J
      46: lconst_0
      47: lcmp
      48: iflt          60
      51: aload_0
      52: invokevirtual #22                 // Method getCachedTime:()J
      55: lconst_0
      56: lcmp
      57: ifge          104
      60: new           #23                 // class java/lang/IllegalStateException
      63: dup
      64: new           #24                 // class java/lang/StringBuilder
      67: dup
      68: invokespecial #25                 // Method java/lang/StringBuilder."<init>":()V
      71: ldc           #26                 // String
      73: invokevirtual #27                 // Method java/lang/StringBuilder.append:(Ljava/lang/String;)Ljava/lang/StringBuilder;
      76: aload_0
      77: invokevirtual #22                 // Method getCachedTime:()J
      80: invokevirtual #28                 // Method java/lang/StringBuilder.append:(J)Ljava/lang/StringBuilder;
      83: ldc           #29                 // String ,
      85: invokevirtual #27                 // Method java/lang/StringBuilder.append:(Ljava/lang/String;)Ljava/lang/StringBuilder;
      88: aload_1
      89: invokeinterface #21,  1           // InterfaceMethod org/apache/hadoop/hbase/io/hfile/CachedBlock.getCachedTime:()J
      94: invokevirtual #28                 // Method java/lang/StringBuilder.append:(J)Ljava/lang/StringBuilder;
      97: invokevirtual #30                 // Method java/lang/StringBuilder.toString:()Ljava/lang/String;
     100: invokespecial #31                 // Method java/lang/IllegalStateException."<init>":(Ljava/lang/String;)V
     103: athrow
     104: aload_1
     105: invokeinterface #21,  1           // InterfaceMethod org/apache/hadoop/hbase/io/hfile/CachedBlock.getCachedTime:()J
     110: aload_0
     111: invokevirtual #22                 // Method getCachedTime:()J
     114: invokestatic  #20                 // Method java/lang/Long.compare:(JJ)I
     117: ireturn

  public int hashCode();
    Code:
       0: aload_0
       1: getfield      #2                  // Field val$e:Ljava/util/Map$Entry;
       4: invokeinterface #9,  1            // InterfaceMethod java/util/Map$Entry.getKey:()Ljava/lang/Object;
       9: checkcast     #10                 // class org/apache/hadoop/hbase/io/hfile/BlockCacheKey
      12: invokevirtual #32                 // Method org/apache/hadoop/hbase/io/hfile/BlockCacheKey.hashCode:()I
      15: ireturn

  public boolean equals(java.lang.Object);
    Code:
       0: aload_1
       1: instanceof    #33                 // class org/apache/hadoop/hbase/io/hfile/CachedBlock
       4: ifeq          26
       7: aload_1
       8: checkcast     #33                 // class org/apache/hadoop/hbase/io/hfile/CachedBlock
      11: astore_2
      12: aload_0
      13: aload_2
      14: invokevirtual #34                 // Method compareTo:(Lorg/apache/hadoop/hbase/io/hfile/CachedBlock;)I
      17: ifne          24
      20: iconst_1
      21: goto          25
      24: iconst_0
      25: ireturn
      26: iconst_0
      27: ireturn

  public int compareTo(java.lang.Object);
    Code:
       0: aload_0
       1: aload_1
       2: checkcast     #33                 // class org/apache/hadoop/hbase/io/hfile/CachedBlock
       5: invokevirtual #34                 // Method compareTo:(Lorg/apache/hadoop/hbase/io/hfile/CachedBlock;)I
       8: ireturn
}
