Compiled from "BucketCacheProtos.java"
public final class org.apache.hadoop.hbase.shaded.protobuf.generated.BucketCacheProtos$BucketCacheEntry$Builder extends org.apache.hbase.thirdparty.com.google.protobuf.GeneratedMessageV3$Builder<org.apache.hadoop.hbase.shaded.protobuf.generated.BucketCacheProtos$BucketCacheEntry$Builder> implements org.apache.hadoop.hbase.shaded.protobuf.generated.BucketCacheProtos$BucketCacheEntryOrBuilder {
  public static final org.apache.hbase.thirdparty.com.google.protobuf.Descriptors$Descriptor getDescriptor();
    Code:
       0: invokestatic  #3                  // Method org/apache/hadoop/hbase/shaded/protobuf/generated/BucketCacheProtos.access$000:()Lorg/apache/hbase/thirdparty/com/google/protobuf/Descriptors$Descriptor;
       3: areturn

  protected org.apache.hbase.thirdparty.com.google.protobuf.MapField internalGetMapField(int);
    Code:
       0: iload_1
       1: lookupswitch  { // 1
                     4: 20
               default: 25
          }
      20: aload_0
      21: invokespecial #4                  // Method internalGetDeserializers:()Lorg/apache/hbase/thirdparty/com/google/protobuf/MapField;
      24: areturn
      25: new           #5                  // class java/lang/RuntimeException
      28: dup
      29: new           #6                  // class java/lang/StringBuilder
      32: dup
      33: invokespecial #7                  // Method java/lang/StringBuilder."<init>":()V
      36: ldc           #8                  // String Invalid map field number:
      38: invokevirtual #9                  // Method java/lang/StringBuilder.append:(Ljava/lang/String;)Ljava/lang/StringBuilder;
      41: iload_1
      42: invokevirtual #10                 // Method java/lang/StringBuilder.append:(I)Ljava/lang/StringBuilder;
      45: invokevirtual #11                 // Method java/lang/StringBuilder.toString:()Ljava/lang/String;
      48: invokespecial #12                 // Method java/lang/RuntimeException."<init>":(Ljava/lang/String;)V
      51: athrow

  protected org.apache.hbase.thirdparty.com.google.protobuf.MapField internalGetMutableMapField(int);
    Code:
       0: iload_1
       1: lookupswitch  { // 1
                     4: 20
               default: 25
          }
      20: aload_0
      21: invokespecial #13                 // Method internalGetMutableDeserializers:()Lorg/apache/hbase/thirdparty/com/google/protobuf/MapField;
      24: areturn
      25: new           #5                  // class java/lang/RuntimeException
      28: dup
      29: new           #6                  // class java/lang/StringBuilder
      32: dup
      33: invokespecial #7                  // Method java/lang/StringBuilder."<init>":()V
      36: ldc           #8                  // String Invalid map field number:
      38: invokevirtual #9                  // Method java/lang/StringBuilder.append:(Ljava/lang/String;)Ljava/lang/StringBuilder;
      41: iload_1
      42: invokevirtual #10                 // Method java/lang/StringBuilder.append:(I)Ljava/lang/StringBuilder;
      45: invokevirtual #11                 // Method java/lang/StringBuilder.toString:()Ljava/lang/String;
      48: invokespecial #12                 // Method java/lang/RuntimeException."<init>":(Ljava/lang/String;)V
      51: athrow

  protected org.apache.hbase.thirdparty.com.google.protobuf.GeneratedMessageV3$FieldAccessorTable internalGetFieldAccessorTable();
    Code:
       0: invokestatic  #14                 // Method org/apache/hadoop/hbase/shaded/protobuf/generated/BucketCacheProtos.access$100:()Lorg/apache/hbase/thirdparty/com/google/protobuf/GeneratedMessageV3$FieldAccessorTable;
       3: ldc           #15                 // class org/apache/hadoop/hbase/shaded/protobuf/generated/BucketCacheProtos$BucketCacheEntry
       5: ldc           #16                 // class org/apache/hadoop/hbase/shaded/protobuf/generated/BucketCacheProtos$BucketCacheEntry$Builder
       7: invokevirtual #17                 // Method org/apache/hbase/thirdparty/com/google/protobuf/GeneratedMessageV3$FieldAccessorTable.ensureFieldAccessorsInitialized:(Ljava/lang/Class;Ljava/lang/Class;)Lorg/apache/hbase/thirdparty/com/google/protobuf/GeneratedMessageV3$FieldAccessorTable;
      10: areturn

  public org.apache.hadoop.hbase.shaded.protobuf.generated.BucketCacheProtos$BucketCacheEntry$Builder clear();
    Code:
       0: aload_0
       1: invokespecial #27                 // Method org/apache/hbase/thirdparty/com/google/protobuf/GeneratedMessageV3$Builder.clear:()Lorg/apache/hbase/thirdparty/com/google/protobuf/GeneratedMessageV3$Builder;
       4: pop
       5: aload_0
       6: lconst_0
       7: putfield      #28                 // Field cacheCapacity_:J
      10: aload_0
      11: aload_0
      12: getfield      #29                 // Field bitField0_:I
      15: bipush        -2
      17: iand
      18: putfield      #29                 // Field bitField0_:I
      21: aload_0
      22: ldc           #19                 // String
      24: putfield      #20                 // Field ioClass_:Ljava/lang/Object;
      27: aload_0
      28: aload_0
      29: getfield      #29                 // Field bitField0_:I
      32: bipush        -3
      34: iand
      35: putfield      #29                 // Field bitField0_:I
      38: aload_0
      39: ldc           #19                 // String
      41: putfield      #21                 // Field mapClass_:Ljava/lang/Object;
      44: aload_0
      45: aload_0
      46: getfield      #29                 // Field bitField0_:I
      49: bipush        -5
      51: iand
      52: putfield      #29                 // Field bitField0_:I
      55: aload_0
      56: invokespecial #13                 // Method internalGetMutableDeserializers:()Lorg/apache/hbase/thirdparty/com/google/protobuf/MapField;
      59: invokevirtual #30                 // Method org/apache/hbase/thirdparty/com/google/protobuf/MapField.clear:()V
      62: aload_0
      63: getfield      #31                 // Field backingMapBuilder_:Lorg/apache/hbase/thirdparty/com/google/protobuf/SingleFieldBuilderV3;
      66: ifnonnull     77
      69: aload_0
      70: aconst_null
      71: putfield      #22                 // Field backingMap_:Lorg/apache/hadoop/hbase/shaded/protobuf/generated/BucketCacheProtos$BackingMap;
      74: goto          85
      77: aload_0
      78: getfield      #31                 // Field backingMapBuilder_:Lorg/apache/hbase/thirdparty/com/google/protobuf/SingleFieldBuilderV3;
      81: invokevirtual #32                 // Method org/apache/hbase/thirdparty/com/google/protobuf/SingleFieldBuilderV3.clear:()Lorg/apache/hbase/thirdparty/com/google/protobuf/SingleFieldBuilderV3;
      84: pop
      85: aload_0
      86: aload_0
      87: getfield      #29                 // Field bitField0_:I
      90: bipush        -17
      92: iand
      93: putfield      #29                 // Field bitField0_:I
      96: aload_0
      97: areturn

  public org.apache.hbase.thirdparty.com.google.protobuf.Descriptors$Descriptor getDescriptorForType();
    Code:
       0: invokestatic  #3                  // Method org/apache/hadoop/hbase/shaded/protobuf/generated/BucketCacheProtos.access$000:()Lorg/apache/hbase/thirdparty/com/google/protobuf/Descriptors$Descriptor;
       3: areturn

  public org.apache.hadoop.hbase.shaded.protobuf.generated.BucketCacheProtos$BucketCacheEntry getDefaultInstanceForType();
    Code:
       0: invokestatic  #33                 // Method org/apache/hadoop/hbase/shaded/protobuf/generated/BucketCacheProtos$BucketCacheEntry.getDefaultInstance:()Lorg/apache/hadoop/hbase/shaded/protobuf/generated/BucketCacheProtos$BucketCacheEntry;
       3: areturn

  public org.apache.hadoop.hbase.shaded.protobuf.generated.BucketCacheProtos$BucketCacheEntry build();
    Code:
       0: aload_0
       1: invokevirtual #34                 // Method buildPartial:()Lorg/apache/hadoop/hbase/shaded/protobuf/generated/BucketCacheProtos$BucketCacheEntry;
       4: astore_1
       5: aload_1
       6: invokevirtual #35                 // Method org/apache/hadoop/hbase/shaded/protobuf/generated/BucketCacheProtos$BucketCacheEntry.isInitialized:()Z
       9: ifne          17
      12: aload_1
      13: invokestatic  #36                 // Method newUninitializedMessageException:(Lorg/apache/hbase/thirdparty/com/google/protobuf/Message;)Lorg/apache/hbase/thirdparty/com/google/protobuf/UninitializedMessageException;
      16: athrow
      17: aload_1
      18: areturn

  public org.apache.hadoop.hbase.shaded.protobuf.generated.BucketCacheProtos$BucketCacheEntry buildPartial();
    Code:
       0: new           #15                 // class org/apache/hadoop/hbase/shaded/protobuf/generated/BucketCacheProtos$BucketCacheEntry
       3: dup
       4: aload_0
       5: aconst_null
       6: invokespecial #37                 // Method org/apache/hadoop/hbase/shaded/protobuf/generated/BucketCacheProtos$BucketCacheEntry."<init>":(Lorg/apache/hbase/thirdparty/com/google/protobuf/GeneratedMessageV3$Builder;Lorg/apache/hadoop/hbase/shaded/protobuf/generated/BucketCacheProtos$1;)V
       9: astore_1
      10: aload_0
      11: getfield      #29                 // Field bitField0_:I
      14: istore_2
      15: iconst_0
      16: istore_3
      17: iload_2
      18: iconst_1
      19: iand
      20: iconst_1
      21: if_icmpne     28
      24: iload_3
      25: iconst_1
      26: ior
      27: istore_3
      28: aload_1
      29: aload_0
      30: getfield      #28                 // Field cacheCapacity_:J
      33: invokestatic  #38                 // Method org/apache/hadoop/hbase/shaded/protobuf/generated/BucketCacheProtos$BucketCacheEntry.access$702:(Lorg/apache/hadoop/hbase/shaded/protobuf/generated/BucketCacheProtos$BucketCacheEntry;J)J
      36: pop2
      37: iload_2
      38: iconst_2
      39: iand
      40: iconst_2
      41: if_icmpne     48
      44: iload_3
      45: iconst_2
      46: ior
      47: istore_3
      48: aload_1
      49: aload_0
      50: getfield      #20                 // Field ioClass_:Ljava/lang/Object;
      53: invokestatic  #39                 // Method org/apache/hadoop/hbase/shaded/protobuf/generated/BucketCacheProtos$BucketCacheEntry.access$802:(Lorg/apache/hadoop/hbase/shaded/protobuf/generated/BucketCacheProtos$BucketCacheEntry;Ljava/lang/Object;)Ljava/lang/Object;
      56: pop
      57: iload_2
      58: iconst_4
      59: iand
      60: iconst_4
      61: if_icmpne     68
      64: iload_3
      65: iconst_4
      66: ior
      67: istore_3
      68: aload_1
      69: aload_0
      70: getfield      #21                 // Field mapClass_:Ljava/lang/Object;
      73: invokestatic  #40                 // Method org/apache/hadoop/hbase/shaded/protobuf/generated/BucketCacheProtos$BucketCacheEntry.access$902:(Lorg/apache/hadoop/hbase/shaded/protobuf/generated/BucketCacheProtos$BucketCacheEntry;Ljava/lang/Object;)Ljava/lang/Object;
      76: pop
      77: aload_1
      78: aload_0
      79: invokespecial #4                  // Method internalGetDeserializers:()Lorg/apache/hbase/thirdparty/com/google/protobuf/MapField;
      82: invokestatic  #41                 // Method org/apache/hadoop/hbase/shaded/protobuf/generated/BucketCacheProtos$BucketCacheEntry.access$1002:(Lorg/apache/hadoop/hbase/shaded/protobuf/generated/BucketCacheProtos$BucketCacheEntry;Lorg/apache/hbase/thirdparty/com/google/protobuf/MapField;)Lorg/apache/hbase/thirdparty/com/google/protobuf/MapField;
      85: pop
      86: aload_1
      87: invokestatic  #42                 // Method org/apache/hadoop/hbase/shaded/protobuf/generated/BucketCacheProtos$BucketCacheEntry.access$1000:(Lorg/apache/hadoop/hbase/shaded/protobuf/generated/BucketCacheProtos$BucketCacheEntry;)Lorg/apache/hbase/thirdparty/com/google/protobuf/MapField;
      90: invokevirtual #43                 // Method org/apache/hbase/thirdparty/com/google/protobuf/MapField.makeImmutable:()V
      93: iload_2
      94: bipush        16
      96: iand
      97: bipush        16
      99: if_icmpne     107
     102: iload_3
     103: bipush        8
     105: ior
     106: istore_3
     107: aload_0
     108: getfield      #31                 // Field backingMapBuilder_:Lorg/apache/hbase/thirdparty/com/google/protobuf/SingleFieldBuilderV3;
     111: ifnonnull     126
     114: aload_1
     115: aload_0
     116: getfield      #22                 // Field backingMap_:Lorg/apache/hadoop/hbase/shaded/protobuf/generated/BucketCacheProtos$BackingMap;
     119: invokestatic  #44                 // Method org/apache/hadoop/hbase/shaded/protobuf/generated/BucketCacheProtos$BucketCacheEntry.access$1102:(Lorg/apache/hadoop/hbase/shaded/protobuf/generated/BucketCacheProtos$BucketCacheEntry;Lorg/apache/hadoop/hbase/shaded/protobuf/generated/BucketCacheProtos$BackingMap;)Lorg/apache/hadoop/hbase/shaded/protobuf/generated/BucketCacheProtos$BackingMap;
     122: pop
     123: goto          141
     126: aload_1
     127: aload_0
     128: getfield      #31                 // Field backingMapBuilder_:Lorg/apache/hbase/thirdparty/com/google/protobuf/SingleFieldBuilderV3;
     131: invokevirtual #45                 // Method org/apache/hbase/thirdparty/com/google/protobuf/SingleFieldBuilderV3.build:()Lorg/apache/hbase/thirdparty/com/google/protobuf/AbstractMessage;
     134: checkcast     #46                 // class org/apache/hadoop/hbase/shaded/protobuf/generated/BucketCacheProtos$BackingMap
     137: invokestatic  #44                 // Method org/apache/hadoop/hbase/shaded/protobuf/generated/BucketCacheProtos$BucketCacheEntry.access$1102:(Lorg/apache/hadoop/hbase/shaded/protobuf/generated/BucketCacheProtos$BucketCacheEntry;Lorg/apache/hadoop/hbase/shaded/protobuf/generated/BucketCacheProtos$BackingMap;)Lorg/apache/hadoop/hbase/shaded/protobuf/generated/BucketCacheProtos$BackingMap;
     140: pop
     141: aload_1
     142: iload_3
     143: invokestatic  #47                 // Method org/apache/hadoop/hbase/shaded/protobuf/generated/BucketCacheProtos$BucketCacheEntry.access$1202:(Lorg/apache/hadoop/hbase/shaded/protobuf/generated/BucketCacheProtos$BucketCacheEntry;I)I
     146: pop
     147: aload_0
     148: invokevirtual #48                 // Method onBuilt:()V
     151: aload_1
     152: areturn

  public org.apache.hadoop.hbase.shaded.protobuf.generated.BucketCacheProtos$BucketCacheEntry$Builder clone();
    Code:
       0: aload_0
       1: invokespecial #49                 // Method org/apache/hbase/thirdparty/com/google/protobuf/GeneratedMessageV3$Builder.clone:()Lorg/apache/hbase/thirdparty/com/google/protobuf/GeneratedMessageV3$Builder;
       4: checkcast     #16                 // class org/apache/hadoop/hbase/shaded/protobuf/generated/BucketCacheProtos$BucketCacheEntry$Builder
       7: areturn

  public org.apache.hadoop.hbase.shaded.protobuf.generated.BucketCacheProtos$BucketCacheEntry$Builder setField(org.apache.hbase.thirdparty.com.google.protobuf.Descriptors$FieldDescriptor, java.lang.Object);
    Code:
       0: aload_0
       1: aload_1
       2: aload_2
       3: invokespecial #50                 // Method org/apache/hbase/thirdparty/com/google/protobuf/GeneratedMessageV3$Builder.setField:(Lorg/apache/hbase/thirdparty/com/google/protobuf/Descriptors$FieldDescriptor;Ljava/lang/Object;)Lorg/apache/hbase/thirdparty/com/google/protobuf/GeneratedMessageV3$Builder;
       6: checkcast     #16                 // class org/apache/hadoop/hbase/shaded/protobuf/generated/BucketCacheProtos$BucketCacheEntry$Builder
       9: areturn

  public org.apache.hadoop.hbase.shaded.protobuf.generated.BucketCacheProtos$BucketCacheEntry$Builder clearField(org.apache.hbase.thirdparty.com.google.protobuf.Descriptors$FieldDescriptor);
    Code:
       0: aload_0
       1: aload_1
       2: invokespecial #51                 // Method org/apache/hbase/thirdparty/com/google/protobuf/GeneratedMessageV3$Builder.clearField:(Lorg/apache/hbase/thirdparty/com/google/protobuf/Descriptors$FieldDescriptor;)Lorg/apache/hbase/thirdparty/com/google/protobuf/GeneratedMessageV3$Builder;
       5: checkcast     #16                 // class org/apache/hadoop/hbase/shaded/protobuf/generated/BucketCacheProtos$BucketCacheEntry$Builder
       8: areturn

  public org.apache.hadoop.hbase.shaded.protobuf.generated.BucketCacheProtos$BucketCacheEntry$Builder clearOneof(org.apache.hbase.thirdparty.com.google.protobuf.Descriptors$OneofDescriptor);
    Code:
       0: aload_0
       1: aload_1
       2: invokespecial #52                 // Method org/apache/hbase/thirdparty/com/google/protobuf/GeneratedMessageV3$Builder.clearOneof:(Lorg/apache/hbase/thirdparty/com/google/protobuf/Descriptors$OneofDescriptor;)Lorg/apache/hbase/thirdparty/com/google/protobuf/GeneratedMessageV3$Builder;
       5: checkcast     #16                 // class org/apache/hadoop/hbase/shaded/protobuf/generated/BucketCacheProtos$BucketCacheEntry$Builder
       8: areturn

  public org.apache.hadoop.hbase.shaded.protobuf.generated.BucketCacheProtos$BucketCacheEntry$Builder setRepeatedField(org.apache.hbase.thirdparty.com.google.protobuf.Descriptors$FieldDescriptor, int, java.lang.Object);
    Code:
       0: aload_0
       1: aload_1
       2: iload_2
       3: aload_3
       4: invokespecial #53                 // Method org/apache/hbase/thirdparty/com/google/protobuf/GeneratedMessageV3$Builder.setRepeatedField:(Lorg/apache/hbase/thirdparty/com/google/protobuf/Descriptors$FieldDescriptor;ILjava/lang/Object;)Lorg/apache/hbase/thirdparty/com/google/protobuf/GeneratedMessageV3$Builder;
       7: checkcast     #16                 // class org/apache/hadoop/hbase/shaded/protobuf/generated/BucketCacheProtos$BucketCacheEntry$Builder
      10: areturn

  public org.apache.hadoop.hbase.shaded.protobuf.generated.BucketCacheProtos$BucketCacheEntry$Builder addRepeatedField(org.apache.hbase.thirdparty.com.google.protobuf.Descriptors$FieldDescriptor, java.lang.Object);
    Code:
       0: aload_0
       1: aload_1
       2: aload_2
       3: invokespecial #54                 // Method org/apache/hbase/thirdparty/com/google/protobuf/GeneratedMessageV3$Builder.addRepeatedField:(Lorg/apache/hbase/thirdparty/com/google/protobuf/Descriptors$FieldDescriptor;Ljava/lang/Object;)Lorg/apache/hbase/thirdparty/com/google/protobuf/GeneratedMessageV3$Builder;
       6: checkcast     #16                 // class org/apache/hadoop/hbase/shaded/protobuf/generated/BucketCacheProtos$BucketCacheEntry$Builder
       9: areturn

  public org.apache.hadoop.hbase.shaded.protobuf.generated.BucketCacheProtos$BucketCacheEntry$Builder mergeFrom(org.apache.hbase.thirdparty.com.google.protobuf.Message);
    Code:
       0: aload_1
       1: instanceof    #15                 // class org/apache/hadoop/hbase/shaded/protobuf/generated/BucketCacheProtos$BucketCacheEntry
       4: ifeq          16
       7: aload_0
       8: aload_1
       9: checkcast     #15                 // class org/apache/hadoop/hbase/shaded/protobuf/generated/BucketCacheProtos$BucketCacheEntry
      12: invokevirtual #55                 // Method mergeFrom:(Lorg/apache/hadoop/hbase/shaded/protobuf/generated/BucketCacheProtos$BucketCacheEntry;)Lorg/apache/hadoop/hbase/shaded/protobuf/generated/BucketCacheProtos$BucketCacheEntry$Builder;
      15: areturn
      16: aload_0
      17: aload_1
      18: invokespecial #56                 // Method org/apache/hbase/thirdparty/com/google/protobuf/GeneratedMessageV3$Builder.mergeFrom:(Lorg/apache/hbase/thirdparty/com/google/protobuf/Message;)Lorg/apache/hbase/thirdparty/com/google/protobuf/AbstractMessage$Builder;
      21: pop
      22: aload_0
      23: areturn

  public org.apache.hadoop.hbase.shaded.protobuf.generated.BucketCacheProtos$BucketCacheEntry$Builder mergeFrom(org.apache.hadoop.hbase.shaded.protobuf.generated.BucketCacheProtos$BucketCacheEntry);
    Code:
       0: aload_1
       1: invokestatic  #33                 // Method org/apache/hadoop/hbase/shaded/protobuf/generated/BucketCacheProtos$BucketCacheEntry.getDefaultInstance:()Lorg/apache/hadoop/hbase/shaded/protobuf/generated/BucketCacheProtos$BucketCacheEntry;
       4: if_acmpne     9
       7: aload_0
       8: areturn
       9: aload_1
      10: invokevirtual #57                 // Method org/apache/hadoop/hbase/shaded/protobuf/generated/BucketCacheProtos$BucketCacheEntry.hasCacheCapacity:()Z
      13: ifeq          25
      16: aload_0
      17: aload_1
      18: invokevirtual #58                 // Method org/apache/hadoop/hbase/shaded/protobuf/generated/BucketCacheProtos$BucketCacheEntry.getCacheCapacity:()J
      21: invokevirtual #59                 // Method setCacheCapacity:(J)Lorg/apache/hadoop/hbase/shaded/protobuf/generated/BucketCacheProtos$BucketCacheEntry$Builder;
      24: pop
      25: aload_1
      26: invokevirtual #60                 // Method org/apache/hadoop/hbase/shaded/protobuf/generated/BucketCacheProtos$BucketCacheEntry.hasIoClass:()Z
      29: ifeq          54
      32: aload_0
      33: dup
      34: getfield      #29                 // Field bitField0_:I
      37: iconst_2
      38: ior
      39: putfield      #29                 // Field bitField0_:I
      42: aload_0
      43: aload_1
      44: invokestatic  #61                 // Method org/apache/hadoop/hbase/shaded/protobuf/generated/BucketCacheProtos$BucketCacheEntry.access$800:(Lorg/apache/hadoop/hbase/shaded/protobuf/generated/BucketCacheProtos$BucketCacheEntry;)Ljava/lang/Object;
      47: putfield      #20                 // Field ioClass_:Ljava/lang/Object;
      50: aload_0
      51: invokevirtual #62                 // Method onChanged:()V
      54: aload_1
      55: invokevirtual #63                 // Method org/apache/hadoop/hbase/shaded/protobuf/generated/BucketCacheProtos$BucketCacheEntry.hasMapClass:()Z
      58: ifeq          83
      61: aload_0
      62: dup
      63: getfield      #29                 // Field bitField0_:I
      66: iconst_4
      67: ior
      68: putfield      #29                 // Field bitField0_:I
      71: aload_0
      72: aload_1
      73: invokestatic  #64                 // Method org/apache/hadoop/hbase/shaded/protobuf/generated/BucketCacheProtos$BucketCacheEntry.access$900:(Lorg/apache/hadoop/hbase/shaded/protobuf/generated/BucketCacheProtos$BucketCacheEntry;)Ljava/lang/Object;
      76: putfield      #21                 // Field mapClass_:Ljava/lang/Object;
      79: aload_0
      80: invokevirtual #62                 // Method onChanged:()V
      83: aload_0
      84: invokespecial #13                 // Method internalGetMutableDeserializers:()Lorg/apache/hbase/thirdparty/com/google/protobuf/MapField;
      87: aload_1
      88: invokestatic  #65                 // Method org/apache/hadoop/hbase/shaded/protobuf/generated/BucketCacheProtos$BucketCacheEntry.access$1300:(Lorg/apache/hadoop/hbase/shaded/protobuf/generated/BucketCacheProtos$BucketCacheEntry;)Lorg/apache/hbase/thirdparty/com/google/protobuf/MapField;
      91: invokevirtual #66                 // Method org/apache/hbase/thirdparty/com/google/protobuf/MapField.mergeFrom:(Lorg/apache/hbase/thirdparty/com/google/protobuf/MapField;)V
      94: aload_1
      95: invokevirtual #67                 // Method org/apache/hadoop/hbase/shaded/protobuf/generated/BucketCacheProtos$BucketCacheEntry.hasBackingMap:()Z
      98: ifeq          110
     101: aload_0
     102: aload_1
     103: invokevirtual #68                 // Method org/apache/hadoop/hbase/shaded/protobuf/generated/BucketCacheProtos$BucketCacheEntry.getBackingMap:()Lorg/apache/hadoop/hbase/shaded/protobuf/generated/BucketCacheProtos$BackingMap;
     106: invokevirtual #69                 // Method mergeBackingMap:(Lorg/apache/hadoop/hbase/shaded/protobuf/generated/BucketCacheProtos$BackingMap;)Lorg/apache/hadoop/hbase/shaded/protobuf/generated/BucketCacheProtos$BucketCacheEntry$Builder;
     109: pop
     110: aload_0
     111: aload_1
     112: invokestatic  #70                 // Method org/apache/hadoop/hbase/shaded/protobuf/generated/BucketCacheProtos$BucketCacheEntry.access$1400:(Lorg/apache/hadoop/hbase/shaded/protobuf/generated/BucketCacheProtos$BucketCacheEntry;)Lorg/apache/hbase/thirdparty/com/google/protobuf/UnknownFieldSet;
     115: invokevirtual #71                 // Method mergeUnknownFields:(Lorg/apache/hbase/thirdparty/com/google/protobuf/UnknownFieldSet;)Lorg/apache/hadoop/hbase/shaded/protobuf/generated/BucketCacheProtos$BucketCacheEntry$Builder;
     118: pop
     119: aload_0
     120: invokevirtual #62                 // Method onChanged:()V
     123: aload_0
     124: areturn

  public final boolean isInitialized();
    Code:
       0: aload_0
       1: invokevirtual #72                 // Method hasCacheCapacity:()Z
       4: ifne          9
       7: iconst_0
       8: ireturn
       9: aload_0
      10: invokevirtual #73                 // Method hasIoClass:()Z
      13: ifne          18
      16: iconst_0
      17: ireturn
      18: aload_0
      19: invokevirtual #74                 // Method hasMapClass:()Z
      22: ifne          27
      25: iconst_0
      26: ireturn
      27: aload_0
      28: invokevirtual #75                 // Method hasBackingMap:()Z
      31: ifne          36
      34: iconst_0
      35: ireturn
      36: aload_0
      37: invokevirtual #76                 // Method getBackingMap:()Lorg/apache/hadoop/hbase/shaded/protobuf/generated/BucketCacheProtos$BackingMap;
      40: invokevirtual #77                 // Method org/apache/hadoop/hbase/shaded/protobuf/generated/BucketCacheProtos$BackingMap.isInitialized:()Z
      43: ifne          48
      46: iconst_0
      47: ireturn
      48: iconst_1
      49: ireturn

  public org.apache.hadoop.hbase.shaded.protobuf.generated.BucketCacheProtos$BucketCacheEntry$Builder mergeFrom(org.apache.hbase.thirdparty.com.google.protobuf.CodedInputStream, org.apache.hbase.thirdparty.com.google.protobuf.ExtensionRegistryLite) throws java.io.IOException;
    Code:
       0: aconst_null
       1: astore_3
       2: getstatic     #78                 // Field org/apache/hadoop/hbase/shaded/protobuf/generated/BucketCacheProtos$BucketCacheEntry.PARSER:Lorg/apache/hbase/thirdparty/com/google/protobuf/Parser;
       5: aload_1
       6: aload_2
       7: invokeinterface #79,  3           // InterfaceMethod org/apache/hbase/thirdparty/com/google/protobuf/Parser.parsePartialFrom:(Lorg/apache/hbase/thirdparty/com/google/protobuf/CodedInputStream;Lorg/apache/hbase/thirdparty/com/google/protobuf/ExtensionRegistryLite;)Ljava/lang/Object;
      12: checkcast     #15                 // class org/apache/hadoop/hbase/shaded/protobuf/generated/BucketCacheProtos$BucketCacheEntry
      15: astore_3
      16: aload_3
      17: ifnull        61
      20: aload_0
      21: aload_3
      22: invokevirtual #55                 // Method mergeFrom:(Lorg/apache/hadoop/hbase/shaded/protobuf/generated/BucketCacheProtos$BucketCacheEntry;)Lorg/apache/hadoop/hbase/shaded/protobuf/generated/BucketCacheProtos$BucketCacheEntry$Builder;
      25: pop
      26: goto          61
      29: astore        4
      31: aload         4
      33: invokevirtual #81                 // Method org/apache/hbase/thirdparty/com/google/protobuf/InvalidProtocolBufferException.getUnfinishedMessage:()Lorg/apache/hbase/thirdparty/com/google/protobuf/MessageLite;
      36: checkcast     #15                 // class org/apache/hadoop/hbase/shaded/protobuf/generated/BucketCacheProtos$BucketCacheEntry
      39: astore_3
      40: aload         4
      42: invokevirtual #82                 // Method org/apache/hbase/thirdparty/com/google/protobuf/InvalidProtocolBufferException.unwrapIOException:()Ljava/io/IOException;
      45: athrow
      46: astore        5
      48: aload_3
      49: ifnull        58
      52: aload_0
      53: aload_3
      54: invokevirtual #55                 // Method mergeFrom:(Lorg/apache/hadoop/hbase/shaded/protobuf/generated/BucketCacheProtos$BucketCacheEntry;)Lorg/apache/hadoop/hbase/shaded/protobuf/generated/BucketCacheProtos$BucketCacheEntry$Builder;
      57: pop
      58: aload         5
      60: athrow
      61: aload_0
      62: areturn
    Exception table:
       from    to  target type
           2    16    29   Class org/apache/hbase/thirdparty/com/google/protobuf/InvalidProtocolBufferException
           2    16    46   any
          29    48    46   any

  public boolean hasCacheCapacity();
    Code:
       0: aload_0
       1: getfield      #29                 // Field bitField0_:I
       4: iconst_1
       5: iand
       6: iconst_1
       7: if_icmpne     14
      10: iconst_1
      11: goto          15
      14: iconst_0
      15: ireturn

  public long getCacheCapacity();
    Code:
       0: aload_0
       1: getfield      #28                 // Field cacheCapacity_:J
       4: lreturn

  public org.apache.hadoop.hbase.shaded.protobuf.generated.BucketCacheProtos$BucketCacheEntry$Builder setCacheCapacity(long);
    Code:
       0: aload_0
       1: dup
       2: getfield      #29                 // Field bitField0_:I
       5: iconst_1
       6: ior
       7: putfield      #29                 // Field bitField0_:I
      10: aload_0
      11: lload_1
      12: putfield      #28                 // Field cacheCapacity_:J
      15: aload_0
      16: invokevirtual #62                 // Method onChanged:()V
      19: aload_0
      20: areturn

  public org.apache.hadoop.hbase.shaded.protobuf.generated.BucketCacheProtos$BucketCacheEntry$Builder clearCacheCapacity();
    Code:
       0: aload_0
       1: aload_0
       2: getfield      #29                 // Field bitField0_:I
       5: bipush        -2
       7: iand
       8: putfield      #29                 // Field bitField0_:I
      11: aload_0
      12: lconst_0
      13: putfield      #28                 // Field cacheCapacity_:J
      16: aload_0
      17: invokevirtual #62                 // Method onChanged:()V
      20: aload_0
      21: areturn

  public boolean hasIoClass();
    Code:
       0: aload_0
       1: getfield      #29                 // Field bitField0_:I
       4: iconst_2
       5: iand
       6: iconst_2
       7: if_icmpne     14
      10: iconst_1
      11: goto          15
      14: iconst_0
      15: ireturn

  public java.lang.String getIoClass();
    Code:
       0: aload_0
       1: getfield      #20                 // Field ioClass_:Ljava/lang/Object;
       4: astore_1
       5: aload_1
       6: instanceof    #83                 // class java/lang/String
       9: ifne          36
      12: aload_1
      13: checkcast     #84                 // class org/apache/hbase/thirdparty/com/google/protobuf/ByteString
      16: astore_2
      17: aload_2
      18: invokevirtual #85                 // Method org/apache/hbase/thirdparty/com/google/protobuf/ByteString.toStringUtf8:()Ljava/lang/String;
      21: astore_3
      22: aload_2
      23: invokevirtual #86                 // Method org/apache/hbase/thirdparty/com/google/protobuf/ByteString.isValidUtf8:()Z
      26: ifeq          34
      29: aload_0
      30: aload_3
      31: putfield      #20                 // Field ioClass_:Ljava/lang/Object;
      34: aload_3
      35: areturn
      36: aload_1
      37: checkcast     #83                 // class java/lang/String
      40: areturn

  public org.apache.hbase.thirdparty.com.google.protobuf.ByteString getIoClassBytes();
    Code:
       0: aload_0
       1: getfield      #20                 // Field ioClass_:Ljava/lang/Object;
       4: astore_1
       5: aload_1
       6: instanceof    #83                 // class java/lang/String
       9: ifeq          27
      12: aload_1
      13: checkcast     #83                 // class java/lang/String
      16: invokestatic  #87                 // Method org/apache/hbase/thirdparty/com/google/protobuf/ByteString.copyFromUtf8:(Ljava/lang/String;)Lorg/apache/hbase/thirdparty/com/google/protobuf/ByteString;
      19: astore_2
      20: aload_0
      21: aload_2
      22: putfield      #20                 // Field ioClass_:Ljava/lang/Object;
      25: aload_2
      26: areturn
      27: aload_1
      28: checkcast     #84                 // class org/apache/hbase/thirdparty/com/google/protobuf/ByteString
      31: areturn

  public org.apache.hadoop.hbase.shaded.protobuf.generated.BucketCacheProtos$BucketCacheEntry$Builder setIoClass(java.lang.String);
    Code:
       0: aload_1
       1: ifnonnull     12
       4: new           #88                 // class java/lang/NullPointerException
       7: dup
       8: invokespecial #89                 // Method java/lang/NullPointerException."<init>":()V
      11: athrow
      12: aload_0
      13: dup
      14: getfield      #29                 // Field bitField0_:I
      17: iconst_2
      18: ior
      19: putfield      #29                 // Field bitField0_:I
      22: aload_0
      23: aload_1
      24: putfield      #20                 // Field ioClass_:Ljava/lang/Object;
      27: aload_0
      28: invokevirtual #62                 // Method onChanged:()V
      31: aload_0
      32: areturn

  public org.apache.hadoop.hbase.shaded.protobuf.generated.BucketCacheProtos$BucketCacheEntry$Builder clearIoClass();
    Code:
       0: aload_0
       1: aload_0
       2: getfield      #29                 // Field bitField0_:I
       5: bipush        -3
       7: iand
       8: putfield      #29                 // Field bitField0_:I
      11: aload_0
      12: invokestatic  #33                 // Method org/apache/hadoop/hbase/shaded/protobuf/generated/BucketCacheProtos$BucketCacheEntry.getDefaultInstance:()Lorg/apache/hadoop/hbase/shaded/protobuf/generated/BucketCacheProtos$BucketCacheEntry;
      15: invokevirtual #90                 // Method org/apache/hadoop/hbase/shaded/protobuf/generated/BucketCacheProtos$BucketCacheEntry.getIoClass:()Ljava/lang/String;
      18: putfield      #20                 // Field ioClass_:Ljava/lang/Object;
      21: aload_0
      22: invokevirtual #62                 // Method onChanged:()V
      25: aload_0
      26: areturn

  public org.apache.hadoop.hbase.shaded.protobuf.generated.BucketCacheProtos$BucketCacheEntry$Builder setIoClassBytes(org.apache.hbase.thirdparty.com.google.protobuf.ByteString);
    Code:
       0: aload_1
       1: ifnonnull     12
       4: new           #88                 // class java/lang/NullPointerException
       7: dup
       8: invokespecial #89                 // Method java/lang/NullPointerException."<init>":()V
      11: athrow
      12: aload_0
      13: dup
      14: getfield      #29                 // Field bitField0_:I
      17: iconst_2
      18: ior
      19: putfield      #29                 // Field bitField0_:I
      22: aload_0
      23: aload_1
      24: putfield      #20                 // Field ioClass_:Ljava/lang/Object;
      27: aload_0
      28: invokevirtual #62                 // Method onChanged:()V
      31: aload_0
      32: areturn

  public boolean hasMapClass();
    Code:
       0: aload_0
       1: getfield      #29                 // Field bitField0_:I
       4: iconst_4
       5: iand
       6: iconst_4
       7: if_icmpne     14
      10: iconst_1
      11: goto          15
      14: iconst_0
      15: ireturn

  public java.lang.String getMapClass();
    Code:
       0: aload_0
       1: getfield      #21                 // Field mapClass_:Ljava/lang/Object;
       4: astore_1
       5: aload_1
       6: instanceof    #83                 // class java/lang/String
       9: ifne          36
      12: aload_1
      13: checkcast     #84                 // class org/apache/hbase/thirdparty/com/google/protobuf/ByteString
      16: astore_2
      17: aload_2
      18: invokevirtual #85                 // Method org/apache/hbase/thirdparty/com/google/protobuf/ByteString.toStringUtf8:()Ljava/lang/String;
      21: astore_3
      22: aload_2
      23: invokevirtual #86                 // Method org/apache/hbase/thirdparty/com/google/protobuf/ByteString.isValidUtf8:()Z
      26: ifeq          34
      29: aload_0
      30: aload_3
      31: putfield      #21                 // Field mapClass_:Ljava/lang/Object;
      34: aload_3
      35: areturn
      36: aload_1
      37: checkcast     #83                 // class java/lang/String
      40: areturn

  public org.apache.hbase.thirdparty.com.google.protobuf.ByteString getMapClassBytes();
    Code:
       0: aload_0
       1: getfield      #21                 // Field mapClass_:Ljava/lang/Object;
       4: astore_1
       5: aload_1
       6: instanceof    #83                 // class java/lang/String
       9: ifeq          27
      12: aload_1
      13: checkcast     #83                 // class java/lang/String
      16: invokestatic  #87                 // Method org/apache/hbase/thirdparty/com/google/protobuf/ByteString.copyFromUtf8:(Ljava/lang/String;)Lorg/apache/hbase/thirdparty/com/google/protobuf/ByteString;
      19: astore_2
      20: aload_0
      21: aload_2
      22: putfield      #21                 // Field mapClass_:Ljava/lang/Object;
      25: aload_2
      26: areturn
      27: aload_1
      28: checkcast     #84                 // class org/apache/hbase/thirdparty/com/google/protobuf/ByteString
      31: areturn

  public org.apache.hadoop.hbase.shaded.protobuf.generated.BucketCacheProtos$BucketCacheEntry$Builder setMapClass(java.lang.String);
    Code:
       0: aload_1
       1: ifnonnull     12
       4: new           #88                 // class java/lang/NullPointerException
       7: dup
       8: invokespecial #89                 // Method java/lang/NullPointerException."<init>":()V
      11: athrow
      12: aload_0
      13: dup
      14: getfield      #29                 // Field bitField0_:I
      17: iconst_4
      18: ior
      19: putfield      #29                 // Field bitField0_:I
      22: aload_0
      23: aload_1
      24: putfield      #21                 // Field mapClass_:Ljava/lang/Object;
      27: aload_0
      28: invokevirtual #62                 // Method onChanged:()V
      31: aload_0
      32: areturn

  public org.apache.hadoop.hbase.shaded.protobuf.generated.BucketCacheProtos$BucketCacheEntry$Builder clearMapClass();
    Code:
       0: aload_0
       1: aload_0
       2: getfield      #29                 // Field bitField0_:I
       5: bipush        -5
       7: iand
       8: putfield      #29                 // Field bitField0_:I
      11: aload_0
      12: invokestatic  #33                 // Method org/apache/hadoop/hbase/shaded/protobuf/generated/BucketCacheProtos$BucketCacheEntry.getDefaultInstance:()Lorg/apache/hadoop/hbase/shaded/protobuf/generated/BucketCacheProtos$BucketCacheEntry;
      15: invokevirtual #91                 // Method org/apache/hadoop/hbase/shaded/protobuf/generated/BucketCacheProtos$BucketCacheEntry.getMapClass:()Ljava/lang/String;
      18: putfield      #21                 // Field mapClass_:Ljava/lang/Object;
      21: aload_0
      22: invokevirtual #62                 // Method onChanged:()V
      25: aload_0
      26: areturn

  public org.apache.hadoop.hbase.shaded.protobuf.generated.BucketCacheProtos$BucketCacheEntry$Builder setMapClassBytes(org.apache.hbase.thirdparty.com.google.protobuf.ByteString);
    Code:
       0: aload_1
       1: ifnonnull     12
       4: new           #88                 // class java/lang/NullPointerException
       7: dup
       8: invokespecial #89                 // Method java/lang/NullPointerException."<init>":()V
      11: athrow
      12: aload_0
      13: dup
      14: getfield      #29                 // Field bitField0_:I
      17: iconst_4
      18: ior
      19: putfield      #29                 // Field bitField0_:I
      22: aload_0
      23: aload_1
      24: putfield      #21                 // Field mapClass_:Ljava/lang/Object;
      27: aload_0
      28: invokevirtual #62                 // Method onChanged:()V
      31: aload_0
      32: areturn

  public int getDeserializersCount();
    Code:
       0: aload_0
       1: invokespecial #4                  // Method internalGetDeserializers:()Lorg/apache/hbase/thirdparty/com/google/protobuf/MapField;
       4: invokevirtual #98                 // Method org/apache/hbase/thirdparty/com/google/protobuf/MapField.getMap:()Ljava/util/Map;
       7: invokeinterface #99,  1           // InterfaceMethod java/util/Map.size:()I
      12: ireturn

  public boolean containsDeserializers(int);
    Code:
       0: aload_0
       1: invokespecial #4                  // Method internalGetDeserializers:()Lorg/apache/hbase/thirdparty/com/google/protobuf/MapField;
       4: invokevirtual #98                 // Method org/apache/hbase/thirdparty/com/google/protobuf/MapField.getMap:()Ljava/util/Map;
       7: iload_1
       8: invokestatic  #100                // Method java/lang/Integer.valueOf:(I)Ljava/lang/Integer;
      11: invokeinterface #101,  2          // InterfaceMethod java/util/Map.containsKey:(Ljava/lang/Object;)Z
      16: ireturn

  public java.util.Map<java.lang.Integer, java.lang.String> getDeserializers();
    Code:
       0: aload_0
       1: invokevirtual #102                // Method getDeserializersMap:()Ljava/util/Map;
       4: areturn

  public java.util.Map<java.lang.Integer, java.lang.String> getDeserializersMap();
    Code:
       0: aload_0
       1: invokespecial #4                  // Method internalGetDeserializers:()Lorg/apache/hbase/thirdparty/com/google/protobuf/MapField;
       4: invokevirtual #98                 // Method org/apache/hbase/thirdparty/com/google/protobuf/MapField.getMap:()Ljava/util/Map;
       7: areturn

  public java.lang.String getDeserializersOrDefault(int, java.lang.String);
    Code:
       0: aload_0
       1: invokespecial #4                  // Method internalGetDeserializers:()Lorg/apache/hbase/thirdparty/com/google/protobuf/MapField;
       4: invokevirtual #98                 // Method org/apache/hbase/thirdparty/com/google/protobuf/MapField.getMap:()Ljava/util/Map;
       7: astore_3
       8: aload_3
       9: iload_1
      10: invokestatic  #100                // Method java/lang/Integer.valueOf:(I)Ljava/lang/Integer;
      13: invokeinterface #101,  2          // InterfaceMethod java/util/Map.containsKey:(Ljava/lang/Object;)Z
      18: ifeq          37
      21: aload_3
      22: iload_1
      23: invokestatic  #100                // Method java/lang/Integer.valueOf:(I)Ljava/lang/Integer;
      26: invokeinterface #103,  2          // InterfaceMethod java/util/Map.get:(Ljava/lang/Object;)Ljava/lang/Object;
      31: checkcast     #83                 // class java/lang/String
      34: goto          38
      37: aload_2
      38: areturn

  public java.lang.String getDeserializersOrThrow(int);
    Code:
       0: aload_0
       1: invokespecial #4                  // Method internalGetDeserializers:()Lorg/apache/hbase/thirdparty/com/google/protobuf/MapField;
       4: invokevirtual #98                 // Method org/apache/hbase/thirdparty/com/google/protobuf/MapField.getMap:()Ljava/util/Map;
       7: astore_2
       8: aload_2
       9: iload_1
      10: invokestatic  #100                // Method java/lang/Integer.valueOf:(I)Ljava/lang/Integer;
      13: invokeinterface #101,  2          // InterfaceMethod java/util/Map.containsKey:(Ljava/lang/Object;)Z
      18: ifne          29
      21: new           #104                // class java/lang/IllegalArgumentException
      24: dup
      25: invokespecial #105                // Method java/lang/IllegalArgumentException."<init>":()V
      28: athrow
      29: aload_2
      30: iload_1
      31: invokestatic  #100                // Method java/lang/Integer.valueOf:(I)Ljava/lang/Integer;
      34: invokeinterface #103,  2          // InterfaceMethod java/util/Map.get:(Ljava/lang/Object;)Ljava/lang/Object;
      39: checkcast     #83                 // class java/lang/String
      42: areturn

  public org.apache.hadoop.hbase.shaded.protobuf.generated.BucketCacheProtos$BucketCacheEntry$Builder clearDeserializers();
    Code:
       0: aload_0
       1: invokespecial #13                 // Method internalGetMutableDeserializers:()Lorg/apache/hbase/thirdparty/com/google/protobuf/MapField;
       4: invokevirtual #106                // Method org/apache/hbase/thirdparty/com/google/protobuf/MapField.getMutableMap:()Ljava/util/Map;
       7: invokeinterface #107,  1          // InterfaceMethod java/util/Map.clear:()V
      12: aload_0
      13: areturn

  public org.apache.hadoop.hbase.shaded.protobuf.generated.BucketCacheProtos$BucketCacheEntry$Builder removeDeserializers(int);
    Code:
       0: aload_0
       1: invokespecial #13                 // Method internalGetMutableDeserializers:()Lorg/apache/hbase/thirdparty/com/google/protobuf/MapField;
       4: invokevirtual #106                // Method org/apache/hbase/thirdparty/com/google/protobuf/MapField.getMutableMap:()Ljava/util/Map;
       7: iload_1
       8: invokestatic  #100                // Method java/lang/Integer.valueOf:(I)Ljava/lang/Integer;
      11: invokeinterface #108,  2          // InterfaceMethod java/util/Map.remove:(Ljava/lang/Object;)Ljava/lang/Object;
      16: pop
      17: aload_0
      18: areturn

  public java.util.Map<java.lang.Integer, java.lang.String> getMutableDeserializers();
    Code:
       0: aload_0
       1: invokespecial #13                 // Method internalGetMutableDeserializers:()Lorg/apache/hbase/thirdparty/com/google/protobuf/MapField;
       4: invokevirtual #106                // Method org/apache/hbase/thirdparty/com/google/protobuf/MapField.getMutableMap:()Ljava/util/Map;
       7: areturn

  public org.apache.hadoop.hbase.shaded.protobuf.generated.BucketCacheProtos$BucketCacheEntry$Builder putDeserializers(int, java.lang.String);
    Code:
       0: aload_2
       1: ifnonnull     12
       4: new           #88                 // class java/lang/NullPointerException
       7: dup
       8: invokespecial #89                 // Method java/lang/NullPointerException."<init>":()V
      11: athrow
      12: aload_0
      13: invokespecial #13                 // Method internalGetMutableDeserializers:()Lorg/apache/hbase/thirdparty/com/google/protobuf/MapField;
      16: invokevirtual #106                // Method org/apache/hbase/thirdparty/com/google/protobuf/MapField.getMutableMap:()Ljava/util/Map;
      19: iload_1
      20: invokestatic  #100                // Method java/lang/Integer.valueOf:(I)Ljava/lang/Integer;
      23: aload_2
      24: invokeinterface #109,  3          // InterfaceMethod java/util/Map.put:(Ljava/lang/Object;Ljava/lang/Object;)Ljava/lang/Object;
      29: pop
      30: aload_0
      31: areturn

  public org.apache.hadoop.hbase.shaded.protobuf.generated.BucketCacheProtos$BucketCacheEntry$Builder putAllDeserializers(java.util.Map<java.lang.Integer, java.lang.String>);
    Code:
       0: aload_0
       1: invokespecial #13                 // Method internalGetMutableDeserializers:()Lorg/apache/hbase/thirdparty/com/google/protobuf/MapField;
       4: invokevirtual #106                // Method org/apache/hbase/thirdparty/com/google/protobuf/MapField.getMutableMap:()Ljava/util/Map;
       7: aload_1
       8: invokeinterface #110,  2          // InterfaceMethod java/util/Map.putAll:(Ljava/util/Map;)V
      13: aload_0
      14: areturn

  public boolean hasBackingMap();
    Code:
       0: aload_0
       1: getfield      #29                 // Field bitField0_:I
       4: bipush        16
       6: iand
       7: bipush        16
       9: if_icmpne     16
      12: iconst_1
      13: goto          17
      16: iconst_0
      17: ireturn

  public org.apache.hadoop.hbase.shaded.protobuf.generated.BucketCacheProtos$BackingMap getBackingMap();
    Code:
       0: aload_0
       1: getfield      #31                 // Field backingMapBuilder_:Lorg/apache/hbase/thirdparty/com/google/protobuf/SingleFieldBuilderV3;
       4: ifnonnull     25
       7: aload_0
       8: getfield      #22                 // Field backingMap_:Lorg/apache/hadoop/hbase/shaded/protobuf/generated/BucketCacheProtos$BackingMap;
      11: ifnonnull     20
      14: invokestatic  #111                // Method org/apache/hadoop/hbase/shaded/protobuf/generated/BucketCacheProtos$BackingMap.getDefaultInstance:()Lorg/apache/hadoop/hbase/shaded/protobuf/generated/BucketCacheProtos$BackingMap;
      17: goto          24
      20: aload_0
      21: getfield      #22                 // Field backingMap_:Lorg/apache/hadoop/hbase/shaded/protobuf/generated/BucketCacheProtos$BackingMap;
      24: areturn
      25: aload_0
      26: getfield      #31                 // Field backingMapBuilder_:Lorg/apache/hbase/thirdparty/com/google/protobuf/SingleFieldBuilderV3;
      29: invokevirtual #112                // Method org/apache/hbase/thirdparty/com/google/protobuf/SingleFieldBuilderV3.getMessage:()Lorg/apache/hbase/thirdparty/com/google/protobuf/AbstractMessage;
      32: checkcast     #46                 // class org/apache/hadoop/hbase/shaded/protobuf/generated/BucketCacheProtos$BackingMap
      35: areturn

  public org.apache.hadoop.hbase.shaded.protobuf.generated.BucketCacheProtos$BucketCacheEntry$Builder setBackingMap(org.apache.hadoop.hbase.shaded.protobuf.generated.BucketCacheProtos$BackingMap);
    Code:
       0: aload_0
       1: getfield      #31                 // Field backingMapBuilder_:Lorg/apache/hbase/thirdparty/com/google/protobuf/SingleFieldBuilderV3;
       4: ifnonnull     31
       7: aload_1
       8: ifnonnull     19
      11: new           #88                 // class java/lang/NullPointerException
      14: dup
      15: invokespecial #89                 // Method java/lang/NullPointerException."<init>":()V
      18: athrow
      19: aload_0
      20: aload_1
      21: putfield      #22                 // Field backingMap_:Lorg/apache/hadoop/hbase/shaded/protobuf/generated/BucketCacheProtos$BackingMap;
      24: aload_0
      25: invokevirtual #62                 // Method onChanged:()V
      28: goto          40
      31: aload_0
      32: getfield      #31                 // Field backingMapBuilder_:Lorg/apache/hbase/thirdparty/com/google/protobuf/SingleFieldBuilderV3;
      35: aload_1
      36: invokevirtual #113                // Method org/apache/hbase/thirdparty/com/google/protobuf/SingleFieldBuilderV3.setMessage:(Lorg/apache/hbase/thirdparty/com/google/protobuf/AbstractMessage;)Lorg/apache/hbase/thirdparty/com/google/protobuf/SingleFieldBuilderV3;
      39: pop
      40: aload_0
      41: dup
      42: getfield      #29                 // Field bitField0_:I
      45: bipush        16
      47: ior
      48: putfield      #29                 // Field bitField0_:I
      51: aload_0
      52: areturn

  public org.apache.hadoop.hbase.shaded.protobuf.generated.BucketCacheProtos$BucketCacheEntry$Builder setBackingMap(org.apache.hadoop.hbase.shaded.protobuf.generated.BucketCacheProtos$BackingMap$Builder);
    Code:
       0: aload_0
       1: getfield      #31                 // Field backingMapBuilder_:Lorg/apache/hbase/thirdparty/com/google/protobuf/SingleFieldBuilderV3;
       4: ifnonnull     22
       7: aload_0
       8: aload_1
       9: invokevirtual #114                // Method org/apache/hadoop/hbase/shaded/protobuf/generated/BucketCacheProtos$BackingMap$Builder.build:()Lorg/apache/hadoop/hbase/shaded/protobuf/generated/BucketCacheProtos$BackingMap;
      12: putfield      #22                 // Field backingMap_:Lorg/apache/hadoop/hbase/shaded/protobuf/generated/BucketCacheProtos$BackingMap;
      15: aload_0
      16: invokevirtual #62                 // Method onChanged:()V
      19: goto          34
      22: aload_0
      23: getfield      #31                 // Field backingMapBuilder_:Lorg/apache/hbase/thirdparty/com/google/protobuf/SingleFieldBuilderV3;
      26: aload_1
      27: invokevirtual #114                // Method org/apache/hadoop/hbase/shaded/protobuf/generated/BucketCacheProtos$BackingMap$Builder.build:()Lorg/apache/hadoop/hbase/shaded/protobuf/generated/BucketCacheProtos$BackingMap;
      30: invokevirtual #113                // Method org/apache/hbase/thirdparty/com/google/protobuf/SingleFieldBuilderV3.setMessage:(Lorg/apache/hbase/thirdparty/com/google/protobuf/AbstractMessage;)Lorg/apache/hbase/thirdparty/com/google/protobuf/SingleFieldBuilderV3;
      33: pop
      34: aload_0
      35: dup
      36: getfield      #29                 // Field bitField0_:I
      39: bipush        16
      41: ior
      42: putfield      #29                 // Field bitField0_:I
      45: aload_0
      46: areturn

  public org.apache.hadoop.hbase.shaded.protobuf.generated.BucketCacheProtos$BucketCacheEntry$Builder mergeBackingMap(org.apache.hadoop.hbase.shaded.protobuf.generated.BucketCacheProtos$BackingMap);
    Code:
       0: aload_0
       1: getfield      #31                 // Field backingMapBuilder_:Lorg/apache/hbase/thirdparty/com/google/protobuf/SingleFieldBuilderV3;
       4: ifnonnull     69
       7: aload_0
       8: getfield      #29                 // Field bitField0_:I
      11: bipush        16
      13: iand
      14: bipush        16
      16: if_icmpne     57
      19: aload_0
      20: getfield      #22                 // Field backingMap_:Lorg/apache/hadoop/hbase/shaded/protobuf/generated/BucketCacheProtos$BackingMap;
      23: ifnull        57
      26: aload_0
      27: getfield      #22                 // Field backingMap_:Lorg/apache/hadoop/hbase/shaded/protobuf/generated/BucketCacheProtos$BackingMap;
      30: invokestatic  #111                // Method org/apache/hadoop/hbase/shaded/protobuf/generated/BucketCacheProtos$BackingMap.getDefaultInstance:()Lorg/apache/hadoop/hbase/shaded/protobuf/generated/BucketCacheProtos$BackingMap;
      33: if_acmpeq     57
      36: aload_0
      37: aload_0
      38: getfield      #22                 // Field backingMap_:Lorg/apache/hadoop/hbase/shaded/protobuf/generated/BucketCacheProtos$BackingMap;
      41: invokestatic  #115                // Method org/apache/hadoop/hbase/shaded/protobuf/generated/BucketCacheProtos$BackingMap.newBuilder:(Lorg/apache/hadoop/hbase/shaded/protobuf/generated/BucketCacheProtos$BackingMap;)Lorg/apache/hadoop/hbase/shaded/protobuf/generated/BucketCacheProtos$BackingMap$Builder;
      44: aload_1
      45: invokevirtual #116                // Method org/apache/hadoop/hbase/shaded/protobuf/generated/BucketCacheProtos$BackingMap$Builder.mergeFrom:(Lorg/apache/hadoop/hbase/shaded/protobuf/generated/BucketCacheProtos$BackingMap;)Lorg/apache/hadoop/hbase/shaded/protobuf/generated/BucketCacheProtos$BackingMap$Builder;
      48: invokevirtual #117                // Method org/apache/hadoop/hbase/shaded/protobuf/generated/BucketCacheProtos$BackingMap$Builder.buildPartial:()Lorg/apache/hadoop/hbase/shaded/protobuf/generated/BucketCacheProtos$BackingMap;
      51: putfield      #22                 // Field backingMap_:Lorg/apache/hadoop/hbase/shaded/protobuf/generated/BucketCacheProtos$BackingMap;
      54: goto          62
      57: aload_0
      58: aload_1
      59: putfield      #22                 // Field backingMap_:Lorg/apache/hadoop/hbase/shaded/protobuf/generated/BucketCacheProtos$BackingMap;
      62: aload_0
      63: invokevirtual #62                 // Method onChanged:()V
      66: goto          78
      69: aload_0
      70: getfield      #31                 // Field backingMapBuilder_:Lorg/apache/hbase/thirdparty/com/google/protobuf/SingleFieldBuilderV3;
      73: aload_1
      74: invokevirtual #118                // Method org/apache/hbase/thirdparty/com/google/protobuf/SingleFieldBuilderV3.mergeFrom:(Lorg/apache/hbase/thirdparty/com/google/protobuf/AbstractMessage;)Lorg/apache/hbase/thirdparty/com/google/protobuf/SingleFieldBuilderV3;
      77: pop
      78: aload_0
      79: dup
      80: getfield      #29                 // Field bitField0_:I
      83: bipush        16
      85: ior
      86: putfield      #29                 // Field bitField0_:I
      89: aload_0
      90: areturn

  public org.apache.hadoop.hbase.shaded.protobuf.generated.BucketCacheProtos$BucketCacheEntry$Builder clearBackingMap();
    Code:
       0: aload_0
       1: getfield      #31                 // Field backingMapBuilder_:Lorg/apache/hbase/thirdparty/com/google/protobuf/SingleFieldBuilderV3;
       4: ifnonnull     19
       7: aload_0
       8: aconst_null
       9: putfield      #22                 // Field backingMap_:Lorg/apache/hadoop/hbase/shaded/protobuf/generated/BucketCacheProtos$BackingMap;
      12: aload_0
      13: invokevirtual #62                 // Method onChanged:()V
      16: goto          27
      19: aload_0
      20: getfield      #31                 // Field backingMapBuilder_:Lorg/apache/hbase/thirdparty/com/google/protobuf/SingleFieldBuilderV3;
      23: invokevirtual #32                 // Method org/apache/hbase/thirdparty/com/google/protobuf/SingleFieldBuilderV3.clear:()Lorg/apache/hbase/thirdparty/com/google/protobuf/SingleFieldBuilderV3;
      26: pop
      27: aload_0
      28: aload_0
      29: getfield      #29                 // Field bitField0_:I
      32: bipush        -17
      34: iand
      35: putfield      #29                 // Field bitField0_:I
      38: aload_0
      39: areturn

  public org.apache.hadoop.hbase.shaded.protobuf.generated.BucketCacheProtos$BackingMap$Builder getBackingMapBuilder();
    Code:
       0: aload_0
       1: dup
       2: getfield      #29                 // Field bitField0_:I
       5: bipush        16
       7: ior
       8: putfield      #29                 // Field bitField0_:I
      11: aload_0
      12: invokevirtual #62                 // Method onChanged:()V
      15: aload_0
      16: invokespecial #26                 // Method getBackingMapFieldBuilder:()Lorg/apache/hbase/thirdparty/com/google/protobuf/SingleFieldBuilderV3;
      19: invokevirtual #119                // Method org/apache/hbase/thirdparty/com/google/protobuf/SingleFieldBuilderV3.getBuilder:()Lorg/apache/hbase/thirdparty/com/google/protobuf/AbstractMessage$Builder;
      22: checkcast     #120                // class org/apache/hadoop/hbase/shaded/protobuf/generated/BucketCacheProtos$BackingMap$Builder
      25: areturn

  public org.apache.hadoop.hbase.shaded.protobuf.generated.BucketCacheProtos$BackingMapOrBuilder getBackingMapOrBuilder();
    Code:
       0: aload_0
       1: getfield      #31                 // Field backingMapBuilder_:Lorg/apache/hbase/thirdparty/com/google/protobuf/SingleFieldBuilderV3;
       4: ifnull        18
       7: aload_0
       8: getfield      #31                 // Field backingMapBuilder_:Lorg/apache/hbase/thirdparty/com/google/protobuf/SingleFieldBuilderV3;
      11: invokevirtual #121                // Method org/apache/hbase/thirdparty/com/google/protobuf/SingleFieldBuilderV3.getMessageOrBuilder:()Lorg/apache/hbase/thirdparty/com/google/protobuf/MessageOrBuilder;
      14: checkcast     #122                // class org/apache/hadoop/hbase/shaded/protobuf/generated/BucketCacheProtos$BackingMapOrBuilder
      17: areturn
      18: aload_0
      19: getfield      #22                 // Field backingMap_:Lorg/apache/hadoop/hbase/shaded/protobuf/generated/BucketCacheProtos$BackingMap;
      22: ifnonnull     31
      25: invokestatic  #111                // Method org/apache/hadoop/hbase/shaded/protobuf/generated/BucketCacheProtos$BackingMap.getDefaultInstance:()Lorg/apache/hadoop/hbase/shaded/protobuf/generated/BucketCacheProtos$BackingMap;
      28: goto          35
      31: aload_0
      32: getfield      #22                 // Field backingMap_:Lorg/apache/hadoop/hbase/shaded/protobuf/generated/BucketCacheProtos$BackingMap;
      35: areturn

  public final org.apache.hadoop.hbase.shaded.protobuf.generated.BucketCacheProtos$BucketCacheEntry$Builder setUnknownFields(org.apache.hbase.thirdparty.com.google.protobuf.UnknownFieldSet);
    Code:
       0: aload_0
       1: aload_1
       2: invokespecial #127                // Method org/apache/hbase/thirdparty/com/google/protobuf/GeneratedMessageV3$Builder.setUnknownFields:(Lorg/apache/hbase/thirdparty/com/google/protobuf/UnknownFieldSet;)Lorg/apache/hbase/thirdparty/com/google/protobuf/GeneratedMessageV3$Builder;
       5: checkcast     #16                 // class org/apache/hadoop/hbase/shaded/protobuf/generated/BucketCacheProtos$BucketCacheEntry$Builder
       8: areturn

  public final org.apache.hadoop.hbase.shaded.protobuf.generated.BucketCacheProtos$BucketCacheEntry$Builder mergeUnknownFields(org.apache.hbase.thirdparty.com.google.protobuf.UnknownFieldSet);
    Code:
       0: aload_0
       1: aload_1
       2: invokespecial #128                // Method org/apache/hbase/thirdparty/com/google/protobuf/GeneratedMessageV3$Builder.mergeUnknownFields:(Lorg/apache/hbase/thirdparty/com/google/protobuf/UnknownFieldSet;)Lorg/apache/hbase/thirdparty/com/google/protobuf/GeneratedMessageV3$Builder;
       5: checkcast     #16                 // class org/apache/hadoop/hbase/shaded/protobuf/generated/BucketCacheProtos$BucketCacheEntry$Builder
       8: areturn

  public org.apache.hbase.thirdparty.com.google.protobuf.GeneratedMessageV3$Builder mergeUnknownFields(org.apache.hbase.thirdparty.com.google.protobuf.UnknownFieldSet);
    Code:
       0: aload_0
       1: aload_1
       2: invokevirtual #71                 // Method mergeUnknownFields:(Lorg/apache/hbase/thirdparty/com/google/protobuf/UnknownFieldSet;)Lorg/apache/hadoop/hbase/shaded/protobuf/generated/BucketCacheProtos$BucketCacheEntry$Builder;
       5: areturn

  public org.apache.hbase.thirdparty.com.google.protobuf.GeneratedMessageV3$Builder setUnknownFields(org.apache.hbase.thirdparty.com.google.protobuf.UnknownFieldSet);
    Code:
       0: aload_0
       1: aload_1
       2: invokevirtual #129                // Method setUnknownFields:(Lorg/apache/hbase/thirdparty/com/google/protobuf/UnknownFieldSet;)Lorg/apache/hadoop/hbase/shaded/protobuf/generated/BucketCacheProtos$BucketCacheEntry$Builder;
       5: areturn

  public org.apache.hbase.thirdparty.com.google.protobuf.GeneratedMessageV3$Builder addRepeatedField(org.apache.hbase.thirdparty.com.google.protobuf.Descriptors$FieldDescriptor, java.lang.Object);
    Code:
       0: aload_0
       1: aload_1
       2: aload_2
       3: invokevirtual #130                // Method addRepeatedField:(Lorg/apache/hbase/thirdparty/com/google/protobuf/Descriptors$FieldDescriptor;Ljava/lang/Object;)Lorg/apache/hadoop/hbase/shaded/protobuf/generated/BucketCacheProtos$BucketCacheEntry$Builder;
       6: areturn

  public org.apache.hbase.thirdparty.com.google.protobuf.GeneratedMessageV3$Builder setRepeatedField(org.apache.hbase.thirdparty.com.google.protobuf.Descriptors$FieldDescriptor, int, java.lang.Object);
    Code:
       0: aload_0
       1: aload_1
       2: iload_2
       3: aload_3
       4: invokevirtual #131                // Method setRepeatedField:(Lorg/apache/hbase/thirdparty/com/google/protobuf/Descriptors$FieldDescriptor;ILjava/lang/Object;)Lorg/apache/hadoop/hbase/shaded/protobuf/generated/BucketCacheProtos$BucketCacheEntry$Builder;
       7: areturn

  public org.apache.hbase.thirdparty.com.google.protobuf.GeneratedMessageV3$Builder clearOneof(org.apache.hbase.thirdparty.com.google.protobuf.Descriptors$OneofDescriptor);
    Code:
       0: aload_0
       1: aload_1
       2: invokevirtual #132                // Method clearOneof:(Lorg/apache/hbase/thirdparty/com/google/protobuf/Descriptors$OneofDescriptor;)Lorg/apache/hadoop/hbase/shaded/protobuf/generated/BucketCacheProtos$BucketCacheEntry$Builder;
       5: areturn

  public org.apache.hbase.thirdparty.com.google.protobuf.GeneratedMessageV3$Builder clearField(org.apache.hbase.thirdparty.com.google.protobuf.Descriptors$FieldDescriptor);
    Code:
       0: aload_0
       1: aload_1
       2: invokevirtual #133                // Method clearField:(Lorg/apache/hbase/thirdparty/com/google/protobuf/Descriptors$FieldDescriptor;)Lorg/apache/hadoop/hbase/shaded/protobuf/generated/BucketCacheProtos$BucketCacheEntry$Builder;
       5: areturn

  public org.apache.hbase.thirdparty.com.google.protobuf.GeneratedMessageV3$Builder setField(org.apache.hbase.thirdparty.com.google.protobuf.Descriptors$FieldDescriptor, java.lang.Object);
    Code:
       0: aload_0
       1: aload_1
       2: aload_2
       3: invokevirtual #134                // Method setField:(Lorg/apache/hbase/thirdparty/com/google/protobuf/Descriptors$FieldDescriptor;Ljava/lang/Object;)Lorg/apache/hadoop/hbase/shaded/protobuf/generated/BucketCacheProtos$BucketCacheEntry$Builder;
       6: areturn

  public org.apache.hbase.thirdparty.com.google.protobuf.GeneratedMessageV3$Builder clear();
    Code:
       0: aload_0
       1: invokevirtual #135                // Method clear:()Lorg/apache/hadoop/hbase/shaded/protobuf/generated/BucketCacheProtos$BucketCacheEntry$Builder;
       4: areturn

  public org.apache.hbase.thirdparty.com.google.protobuf.GeneratedMessageV3$Builder clone();
    Code:
       0: aload_0
       1: invokevirtual #136                // Method clone:()Lorg/apache/hadoop/hbase/shaded/protobuf/generated/BucketCacheProtos$BucketCacheEntry$Builder;
       4: areturn

  public org.apache.hbase.thirdparty.com.google.protobuf.AbstractMessage$Builder mergeUnknownFields(org.apache.hbase.thirdparty.com.google.protobuf.UnknownFieldSet);
    Code:
       0: aload_0
       1: aload_1
       2: invokevirtual #71                 // Method mergeUnknownFields:(Lorg/apache/hbase/thirdparty/com/google/protobuf/UnknownFieldSet;)Lorg/apache/hadoop/hbase/shaded/protobuf/generated/BucketCacheProtos$BucketCacheEntry$Builder;
       5: areturn

  public org.apache.hbase.thirdparty.com.google.protobuf.AbstractMessage$Builder mergeFrom(org.apache.hbase.thirdparty.com.google.protobuf.CodedInputStream, org.apache.hbase.thirdparty.com.google.protobuf.ExtensionRegistryLite) throws java.io.IOException;
    Code:
       0: aload_0
       1: aload_1
       2: aload_2
       3: invokevirtual #137                // Method mergeFrom:(Lorg/apache/hbase/thirdparty/com/google/protobuf/CodedInputStream;Lorg/apache/hbase/thirdparty/com/google/protobuf/ExtensionRegistryLite;)Lorg/apache/hadoop/hbase/shaded/protobuf/generated/BucketCacheProtos$BucketCacheEntry$Builder;
       6: areturn

  public org.apache.hbase.thirdparty.com.google.protobuf.AbstractMessage$Builder mergeFrom(org.apache.hbase.thirdparty.com.google.protobuf.Message);
    Code:
       0: aload_0
       1: aload_1
       2: invokevirtual #138                // Method mergeFrom:(Lorg/apache/hbase/thirdparty/com/google/protobuf/Message;)Lorg/apache/hadoop/hbase/shaded/protobuf/generated/BucketCacheProtos$BucketCacheEntry$Builder;
       5: areturn

  public org.apache.hbase.thirdparty.com.google.protobuf.AbstractMessage$Builder clear();
    Code:
       0: aload_0
       1: invokevirtual #135                // Method clear:()Lorg/apache/hadoop/hbase/shaded/protobuf/generated/BucketCacheProtos$BucketCacheEntry$Builder;
       4: areturn

  public org.apache.hbase.thirdparty.com.google.protobuf.AbstractMessage$Builder clearOneof(org.apache.hbase.thirdparty.com.google.protobuf.Descriptors$OneofDescriptor);
    Code:
       0: aload_0
       1: aload_1
       2: invokevirtual #132                // Method clearOneof:(Lorg/apache/hbase/thirdparty/com/google/protobuf/Descriptors$OneofDescriptor;)Lorg/apache/hadoop/hbase/shaded/protobuf/generated/BucketCacheProtos$BucketCacheEntry$Builder;
       5: areturn

  public org.apache.hbase.thirdparty.com.google.protobuf.AbstractMessage$Builder clone();
    Code:
       0: aload_0
       1: invokevirtual #136                // Method clone:()Lorg/apache/hadoop/hbase/shaded/protobuf/generated/BucketCacheProtos$BucketCacheEntry$Builder;
       4: areturn

  public org.apache.hbase.thirdparty.com.google.protobuf.Message$Builder mergeUnknownFields(org.apache.hbase.thirdparty.com.google.protobuf.UnknownFieldSet);
    Code:
       0: aload_0
       1: aload_1
       2: invokevirtual #71                 // Method mergeUnknownFields:(Lorg/apache/hbase/thirdparty/com/google/protobuf/UnknownFieldSet;)Lorg/apache/hadoop/hbase/shaded/protobuf/generated/BucketCacheProtos$BucketCacheEntry$Builder;
       5: areturn

  public org.apache.hbase.thirdparty.com.google.protobuf.Message$Builder setUnknownFields(org.apache.hbase.thirdparty.com.google.protobuf.UnknownFieldSet);
    Code:
       0: aload_0
       1: aload_1
       2: invokevirtual #129                // Method setUnknownFields:(Lorg/apache/hbase/thirdparty/com/google/protobuf/UnknownFieldSet;)Lorg/apache/hadoop/hbase/shaded/protobuf/generated/BucketCacheProtos$BucketCacheEntry$Builder;
       5: areturn

  public org.apache.hbase.thirdparty.com.google.protobuf.Message$Builder addRepeatedField(org.apache.hbase.thirdparty.com.google.protobuf.Descriptors$FieldDescriptor, java.lang.Object);
    Code:
       0: aload_0
       1: aload_1
       2: aload_2
       3: invokevirtual #130                // Method addRepeatedField:(Lorg/apache/hbase/thirdparty/com/google/protobuf/Descriptors$FieldDescriptor;Ljava/lang/Object;)Lorg/apache/hadoop/hbase/shaded/protobuf/generated/BucketCacheProtos$BucketCacheEntry$Builder;
       6: areturn

  public org.apache.hbase.thirdparty.com.google.protobuf.Message$Builder setRepeatedField(org.apache.hbase.thirdparty.com.google.protobuf.Descriptors$FieldDescriptor, int, java.lang.Object);
    Code:
       0: aload_0
       1: aload_1
       2: iload_2
       3: aload_3
       4: invokevirtual #131                // Method setRepeatedField:(Lorg/apache/hbase/thirdparty/com/google/protobuf/Descriptors$FieldDescriptor;ILjava/lang/Object;)Lorg/apache/hadoop/hbase/shaded/protobuf/generated/BucketCacheProtos$BucketCacheEntry$Builder;
       7: areturn

  public org.apache.hbase.thirdparty.com.google.protobuf.Message$Builder clearOneof(org.apache.hbase.thirdparty.com.google.protobuf.Descriptors$OneofDescriptor);
    Code:
       0: aload_0
       1: aload_1
       2: invokevirtual #132                // Method clearOneof:(Lorg/apache/hbase/thirdparty/com/google/protobuf/Descriptors$OneofDescriptor;)Lorg/apache/hadoop/hbase/shaded/protobuf/generated/BucketCacheProtos$BucketCacheEntry$Builder;
       5: areturn

  public org.apache.hbase.thirdparty.com.google.protobuf.Message$Builder clearField(org.apache.hbase.thirdparty.com.google.protobuf.Descriptors$FieldDescriptor);
    Code:
       0: aload_0
       1: aload_1
       2: invokevirtual #133                // Method clearField:(Lorg/apache/hbase/thirdparty/com/google/protobuf/Descriptors$FieldDescriptor;)Lorg/apache/hadoop/hbase/shaded/protobuf/generated/BucketCacheProtos$BucketCacheEntry$Builder;
       5: areturn

  public org.apache.hbase.thirdparty.com.google.protobuf.Message$Builder setField(org.apache.hbase.thirdparty.com.google.protobuf.Descriptors$FieldDescriptor, java.lang.Object);
    Code:
       0: aload_0
       1: aload_1
       2: aload_2
       3: invokevirtual #134                // Method setField:(Lorg/apache/hbase/thirdparty/com/google/protobuf/Descriptors$FieldDescriptor;Ljava/lang/Object;)Lorg/apache/hadoop/hbase/shaded/protobuf/generated/BucketCacheProtos$BucketCacheEntry$Builder;
       6: areturn

  public org.apache.hbase.thirdparty.com.google.protobuf.Message$Builder mergeFrom(org.apache.hbase.thirdparty.com.google.protobuf.CodedInputStream, org.apache.hbase.thirdparty.com.google.protobuf.ExtensionRegistryLite) throws java.io.IOException;
    Code:
       0: aload_0
       1: aload_1
       2: aload_2
       3: invokevirtual #137                // Method mergeFrom:(Lorg/apache/hbase/thirdparty/com/google/protobuf/CodedInputStream;Lorg/apache/hbase/thirdparty/com/google/protobuf/ExtensionRegistryLite;)Lorg/apache/hadoop/hbase/shaded/protobuf/generated/BucketCacheProtos$BucketCacheEntry$Builder;
       6: areturn

  public org.apache.hbase.thirdparty.com.google.protobuf.Message$Builder clone();
    Code:
       0: aload_0
       1: invokevirtual #136                // Method clone:()Lorg/apache/hadoop/hbase/shaded/protobuf/generated/BucketCacheProtos$BucketCacheEntry$Builder;
       4: areturn

  public org.apache.hbase.thirdparty.com.google.protobuf.Message buildPartial();
    Code:
       0: aload_0
       1: invokevirtual #34                 // Method buildPartial:()Lorg/apache/hadoop/hbase/shaded/protobuf/generated/BucketCacheProtos$BucketCacheEntry;
       4: areturn

  public org.apache.hbase.thirdparty.com.google.protobuf.Message build();
    Code:
       0: aload_0
       1: invokevirtual #139                // Method build:()Lorg/apache/hadoop/hbase/shaded/protobuf/generated/BucketCacheProtos$BucketCacheEntry;
       4: areturn

  public org.apache.hbase.thirdparty.com.google.protobuf.Message$Builder mergeFrom(org.apache.hbase.thirdparty.com.google.protobuf.Message);
    Code:
       0: aload_0
       1: aload_1
       2: invokevirtual #138                // Method mergeFrom:(Lorg/apache/hbase/thirdparty/com/google/protobuf/Message;)Lorg/apache/hadoop/hbase/shaded/protobuf/generated/BucketCacheProtos$BucketCacheEntry$Builder;
       5: areturn

  public org.apache.hbase.thirdparty.com.google.protobuf.Message$Builder clear();
    Code:
       0: aload_0
       1: invokevirtual #135                // Method clear:()Lorg/apache/hadoop/hbase/shaded/protobuf/generated/BucketCacheProtos$BucketCacheEntry$Builder;
       4: areturn

  public org.apache.hbase.thirdparty.com.google.protobuf.MessageLite$Builder mergeFrom(org.apache.hbase.thirdparty.com.google.protobuf.CodedInputStream, org.apache.hbase.thirdparty.com.google.protobuf.ExtensionRegistryLite) throws java.io.IOException;
    Code:
       0: aload_0
       1: aload_1
       2: aload_2
       3: invokevirtual #137                // Method mergeFrom:(Lorg/apache/hbase/thirdparty/com/google/protobuf/CodedInputStream;Lorg/apache/hbase/thirdparty/com/google/protobuf/ExtensionRegistryLite;)Lorg/apache/hadoop/hbase/shaded/protobuf/generated/BucketCacheProtos$BucketCacheEntry$Builder;
       6: areturn

  public org.apache.hbase.thirdparty.com.google.protobuf.MessageLite$Builder clone();
    Code:
       0: aload_0
       1: invokevirtual #136                // Method clone:()Lorg/apache/hadoop/hbase/shaded/protobuf/generated/BucketCacheProtos$BucketCacheEntry$Builder;
       4: areturn

  public org.apache.hbase.thirdparty.com.google.protobuf.MessageLite buildPartial();
    Code:
       0: aload_0
       1: invokevirtual #34                 // Method buildPartial:()Lorg/apache/hadoop/hbase/shaded/protobuf/generated/BucketCacheProtos$BucketCacheEntry;
       4: areturn

  public org.apache.hbase.thirdparty.com.google.protobuf.MessageLite build();
    Code:
       0: aload_0
       1: invokevirtual #139                // Method build:()Lorg/apache/hadoop/hbase/shaded/protobuf/generated/BucketCacheProtos$BucketCacheEntry;
       4: areturn

  public org.apache.hbase.thirdparty.com.google.protobuf.MessageLite$Builder clear();
    Code:
       0: aload_0
       1: invokevirtual #135                // Method clear:()Lorg/apache/hadoop/hbase/shaded/protobuf/generated/BucketCacheProtos$BucketCacheEntry$Builder;
       4: areturn

  public org.apache.hbase.thirdparty.com.google.protobuf.MessageLite getDefaultInstanceForType();
    Code:
       0: aload_0
       1: invokevirtual #140                // Method getDefaultInstanceForType:()Lorg/apache/hadoop/hbase/shaded/protobuf/generated/BucketCacheProtos$BucketCacheEntry;
       4: areturn

  public org.apache.hbase.thirdparty.com.google.protobuf.Message getDefaultInstanceForType();
    Code:
       0: aload_0
       1: invokevirtual #140                // Method getDefaultInstanceForType:()Lorg/apache/hadoop/hbase/shaded/protobuf/generated/BucketCacheProtos$BucketCacheEntry;
       4: areturn

  public org.apache.hbase.thirdparty.com.google.protobuf.AbstractMessageLite$Builder mergeFrom(org.apache.hbase.thirdparty.com.google.protobuf.CodedInputStream, org.apache.hbase.thirdparty.com.google.protobuf.ExtensionRegistryLite) throws java.io.IOException;
    Code:
       0: aload_0
       1: aload_1
       2: aload_2
       3: invokevirtual #137                // Method mergeFrom:(Lorg/apache/hbase/thirdparty/com/google/protobuf/CodedInputStream;Lorg/apache/hbase/thirdparty/com/google/protobuf/ExtensionRegistryLite;)Lorg/apache/hadoop/hbase/shaded/protobuf/generated/BucketCacheProtos$BucketCacheEntry$Builder;
       6: areturn

  public org.apache.hbase.thirdparty.com.google.protobuf.AbstractMessageLite$Builder clone();
    Code:
       0: aload_0
       1: invokevirtual #136                // Method clone:()Lorg/apache/hadoop/hbase/shaded/protobuf/generated/BucketCacheProtos$BucketCacheEntry$Builder;
       4: areturn

  public java.lang.Object clone() throws java.lang.CloneNotSupportedException;
    Code:
       0: aload_0
       1: invokevirtual #136                // Method clone:()Lorg/apache/hadoop/hbase/shaded/protobuf/generated/BucketCacheProtos$BucketCacheEntry$Builder;
       4: areturn

  org.apache.hadoop.hbase.shaded.protobuf.generated.BucketCacheProtos$BucketCacheEntry$Builder(org.apache.hadoop.hbase.shaded.protobuf.generated.BucketCacheProtos$1);
    Code:
       0: aload_0
       1: invokespecial #2                  // Method "<init>":()V
       4: return

  org.apache.hadoop.hbase.shaded.protobuf.generated.BucketCacheProtos$BucketCacheEntry$Builder(org.apache.hbase.thirdparty.com.google.protobuf.GeneratedMessageV3$BuilderParent, org.apache.hadoop.hbase.shaded.protobuf.generated.BucketCacheProtos$1);
    Code:
       0: aload_0
       1: aload_1
       2: invokespecial #1                  // Method "<init>":(Lorg/apache/hbase/thirdparty/com/google/protobuf/GeneratedMessageV3$BuilderParent;)V
       5: return
}
