Compiled from "BucketCacheProtos.java"
public final class org.apache.hadoop.hbase.shaded.protobuf.generated.BucketCacheProtos$BucketEntry$Builder extends org.apache.hbase.thirdparty.com.google.protobuf.GeneratedMessageV3$Builder<org.apache.hadoop.hbase.shaded.protobuf.generated.BucketCacheProtos$BucketEntry$Builder> implements org.apache.hadoop.hbase.shaded.protobuf.generated.BucketCacheProtos$BucketEntryOrBuilder {
  public static final org.apache.hbase.thirdparty.com.google.protobuf.Descriptors$Descriptor getDescriptor();
    Code:
       0: invokestatic  #3                  // Method org/apache/hadoop/hbase/shaded/protobuf/generated/BucketCacheProtos.access$5000:()Lorg/apache/hbase/thirdparty/com/google/protobuf/Descriptors$Descriptor;
       3: areturn

  protected org.apache.hbase.thirdparty.com.google.protobuf.GeneratedMessageV3$FieldAccessorTable internalGetFieldAccessorTable();
    Code:
       0: invokestatic  #4                  // Method org/apache/hadoop/hbase/shaded/protobuf/generated/BucketCacheProtos.access$5100:()Lorg/apache/hbase/thirdparty/com/google/protobuf/GeneratedMessageV3$FieldAccessorTable;
       3: ldc           #5                  // class org/apache/hadoop/hbase/shaded/protobuf/generated/BucketCacheProtos$BucketEntry
       5: ldc           #6                  // class org/apache/hadoop/hbase/shaded/protobuf/generated/BucketCacheProtos$BucketEntry$Builder
       7: invokevirtual #7                  // Method org/apache/hbase/thirdparty/com/google/protobuf/GeneratedMessageV3$FieldAccessorTable.ensureFieldAccessorsInitialized:(Ljava/lang/Class;Ljava/lang/Class;)Lorg/apache/hbase/thirdparty/com/google/protobuf/GeneratedMessageV3$FieldAccessorTable;
      10: areturn

  public org.apache.hadoop.hbase.shaded.protobuf.generated.BucketCacheProtos$BucketEntry$Builder clear();
    Code:
       0: aload_0
       1: invokespecial #13                 // Method org/apache/hbase/thirdparty/com/google/protobuf/GeneratedMessageV3$Builder.clear:()Lorg/apache/hbase/thirdparty/com/google/protobuf/GeneratedMessageV3$Builder;
       4: pop
       5: aload_0
       6: lconst_0
       7: putfield      #14                 // Field offset_:J
      10: aload_0
      11: aload_0
      12: getfield      #15                 // Field bitField0_:I
      15: bipush        -2
      17: iand
      18: putfield      #15                 // Field bitField0_:I
      21: aload_0
      22: iconst_0
      23: putfield      #16                 // Field length_:I
      26: aload_0
      27: aload_0
      28: getfield      #15                 // Field bitField0_:I
      31: bipush        -3
      33: iand
      34: putfield      #15                 // Field bitField0_:I
      37: aload_0
      38: lconst_0
      39: putfield      #17                 // Field accessCounter_:J
      42: aload_0
      43: aload_0
      44: getfield      #15                 // Field bitField0_:I
      47: bipush        -5
      49: iand
      50: putfield      #15                 // Field bitField0_:I
      53: aload_0
      54: iconst_0
      55: putfield      #18                 // Field deserialiserIndex_:I
      58: aload_0
      59: aload_0
      60: getfield      #15                 // Field bitField0_:I
      63: bipush        -9
      65: iand
      66: putfield      #15                 // Field bitField0_:I
      69: aload_0
      70: iconst_0
      71: putfield      #9                  // Field priority_:I
      74: aload_0
      75: aload_0
      76: getfield      #15                 // Field bitField0_:I
      79: bipush        -17
      81: iand
      82: putfield      #15                 // Field bitField0_:I
      85: aload_0
      86: areturn

  public org.apache.hbase.thirdparty.com.google.protobuf.Descriptors$Descriptor getDescriptorForType();
    Code:
       0: invokestatic  #3                  // Method org/apache/hadoop/hbase/shaded/protobuf/generated/BucketCacheProtos.access$5000:()Lorg/apache/hbase/thirdparty/com/google/protobuf/Descriptors$Descriptor;
       3: areturn

  public org.apache.hadoop.hbase.shaded.protobuf.generated.BucketCacheProtos$BucketEntry getDefaultInstanceForType();
    Code:
       0: invokestatic  #19                 // Method org/apache/hadoop/hbase/shaded/protobuf/generated/BucketCacheProtos$BucketEntry.getDefaultInstance:()Lorg/apache/hadoop/hbase/shaded/protobuf/generated/BucketCacheProtos$BucketEntry;
       3: areturn

  public org.apache.hadoop.hbase.shaded.protobuf.generated.BucketCacheProtos$BucketEntry build();
    Code:
       0: aload_0
       1: invokevirtual #20                 // Method buildPartial:()Lorg/apache/hadoop/hbase/shaded/protobuf/generated/BucketCacheProtos$BucketEntry;
       4: astore_1
       5: aload_1
       6: invokevirtual #21                 // Method org/apache/hadoop/hbase/shaded/protobuf/generated/BucketCacheProtos$BucketEntry.isInitialized:()Z
       9: ifne          17
      12: aload_1
      13: invokestatic  #22                 // Method newUninitializedMessageException:(Lorg/apache/hbase/thirdparty/com/google/protobuf/Message;)Lorg/apache/hbase/thirdparty/com/google/protobuf/UninitializedMessageException;
      16: athrow
      17: aload_1
      18: areturn

  public org.apache.hadoop.hbase.shaded.protobuf.generated.BucketCacheProtos$BucketEntry buildPartial();
    Code:
       0: new           #5                  // class org/apache/hadoop/hbase/shaded/protobuf/generated/BucketCacheProtos$BucketEntry
       3: dup
       4: aload_0
       5: aconst_null
       6: invokespecial #23                 // Method org/apache/hadoop/hbase/shaded/protobuf/generated/BucketCacheProtos$BucketEntry."<init>":(Lorg/apache/hbase/thirdparty/com/google/protobuf/GeneratedMessageV3$Builder;Lorg/apache/hadoop/hbase/shaded/protobuf/generated/BucketCacheProtos$1;)V
       9: astore_1
      10: aload_0
      11: getfield      #15                 // Field bitField0_:I
      14: istore_2
      15: iconst_0
      16: istore_3
      17: iload_2
      18: iconst_1
      19: iand
      20: iconst_1
      21: if_icmpne     28
      24: iload_3
      25: iconst_1
      26: ior
      27: istore_3
      28: aload_1
      29: aload_0
      30: getfield      #14                 // Field offset_:J
      33: invokestatic  #24                 // Method org/apache/hadoop/hbase/shaded/protobuf/generated/BucketCacheProtos$BucketEntry.access$5602:(Lorg/apache/hadoop/hbase/shaded/protobuf/generated/BucketCacheProtos$BucketEntry;J)J
      36: pop2
      37: iload_2
      38: iconst_2
      39: iand
      40: iconst_2
      41: if_icmpne     48
      44: iload_3
      45: iconst_2
      46: ior
      47: istore_3
      48: aload_1
      49: aload_0
      50: getfield      #16                 // Field length_:I
      53: invokestatic  #25                 // Method org/apache/hadoop/hbase/shaded/protobuf/generated/BucketCacheProtos$BucketEntry.access$5702:(Lorg/apache/hadoop/hbase/shaded/protobuf/generated/BucketCacheProtos$BucketEntry;I)I
      56: pop
      57: iload_2
      58: iconst_4
      59: iand
      60: iconst_4
      61: if_icmpne     68
      64: iload_3
      65: iconst_4
      66: ior
      67: istore_3
      68: aload_1
      69: aload_0
      70: getfield      #17                 // Field accessCounter_:J
      73: invokestatic  #26                 // Method org/apache/hadoop/hbase/shaded/protobuf/generated/BucketCacheProtos$BucketEntry.access$5802:(Lorg/apache/hadoop/hbase/shaded/protobuf/generated/BucketCacheProtos$BucketEntry;J)J
      76: pop2
      77: iload_2
      78: bipush        8
      80: iand
      81: bipush        8
      83: if_icmpne     91
      86: iload_3
      87: bipush        8
      89: ior
      90: istore_3
      91: aload_1
      92: aload_0
      93: getfield      #18                 // Field deserialiserIndex_:I
      96: invokestatic  #27                 // Method org/apache/hadoop/hbase/shaded/protobuf/generated/BucketCacheProtos$BucketEntry.access$5902:(Lorg/apache/hadoop/hbase/shaded/protobuf/generated/BucketCacheProtos$BucketEntry;I)I
      99: pop
     100: iload_2
     101: bipush        16
     103: iand
     104: bipush        16
     106: if_icmpne     114
     109: iload_3
     110: bipush        16
     112: ior
     113: istore_3
     114: aload_1
     115: aload_0
     116: getfield      #9                  // Field priority_:I
     119: invokestatic  #28                 // Method org/apache/hadoop/hbase/shaded/protobuf/generated/BucketCacheProtos$BucketEntry.access$6002:(Lorg/apache/hadoop/hbase/shaded/protobuf/generated/BucketCacheProtos$BucketEntry;I)I
     122: pop
     123: aload_1
     124: iload_3
     125: invokestatic  #29                 // Method org/apache/hadoop/hbase/shaded/protobuf/generated/BucketCacheProtos$BucketEntry.access$6102:(Lorg/apache/hadoop/hbase/shaded/protobuf/generated/BucketCacheProtos$BucketEntry;I)I
     128: pop
     129: aload_0
     130: invokevirtual #30                 // Method onBuilt:()V
     133: aload_1
     134: areturn

  public org.apache.hadoop.hbase.shaded.protobuf.generated.BucketCacheProtos$BucketEntry$Builder clone();
    Code:
       0: aload_0
       1: invokespecial #31                 // Method org/apache/hbase/thirdparty/com/google/protobuf/GeneratedMessageV3$Builder.clone:()Lorg/apache/hbase/thirdparty/com/google/protobuf/GeneratedMessageV3$Builder;
       4: checkcast     #6                  // class org/apache/hadoop/hbase/shaded/protobuf/generated/BucketCacheProtos$BucketEntry$Builder
       7: areturn

  public org.apache.hadoop.hbase.shaded.protobuf.generated.BucketCacheProtos$BucketEntry$Builder setField(org.apache.hbase.thirdparty.com.google.protobuf.Descriptors$FieldDescriptor, java.lang.Object);
    Code:
       0: aload_0
       1: aload_1
       2: aload_2
       3: invokespecial #32                 // Method org/apache/hbase/thirdparty/com/google/protobuf/GeneratedMessageV3$Builder.setField:(Lorg/apache/hbase/thirdparty/com/google/protobuf/Descriptors$FieldDescriptor;Ljava/lang/Object;)Lorg/apache/hbase/thirdparty/com/google/protobuf/GeneratedMessageV3$Builder;
       6: checkcast     #6                  // class org/apache/hadoop/hbase/shaded/protobuf/generated/BucketCacheProtos$BucketEntry$Builder
       9: areturn

  public org.apache.hadoop.hbase.shaded.protobuf.generated.BucketCacheProtos$BucketEntry$Builder clearField(org.apache.hbase.thirdparty.com.google.protobuf.Descriptors$FieldDescriptor);
    Code:
       0: aload_0
       1: aload_1
       2: invokespecial #33                 // Method org/apache/hbase/thirdparty/com/google/protobuf/GeneratedMessageV3$Builder.clearField:(Lorg/apache/hbase/thirdparty/com/google/protobuf/Descriptors$FieldDescriptor;)Lorg/apache/hbase/thirdparty/com/google/protobuf/GeneratedMessageV3$Builder;
       5: checkcast     #6                  // class org/apache/hadoop/hbase/shaded/protobuf/generated/BucketCacheProtos$BucketEntry$Builder
       8: areturn

  public org.apache.hadoop.hbase.shaded.protobuf.generated.BucketCacheProtos$BucketEntry$Builder clearOneof(org.apache.hbase.thirdparty.com.google.protobuf.Descriptors$OneofDescriptor);
    Code:
       0: aload_0
       1: aload_1
       2: invokespecial #34                 // Method org/apache/hbase/thirdparty/com/google/protobuf/GeneratedMessageV3$Builder.clearOneof:(Lorg/apache/hbase/thirdparty/com/google/protobuf/Descriptors$OneofDescriptor;)Lorg/apache/hbase/thirdparty/com/google/protobuf/GeneratedMessageV3$Builder;
       5: checkcast     #6                  // class org/apache/hadoop/hbase/shaded/protobuf/generated/BucketCacheProtos$BucketEntry$Builder
       8: areturn

  public org.apache.hadoop.hbase.shaded.protobuf.generated.BucketCacheProtos$BucketEntry$Builder setRepeatedField(org.apache.hbase.thirdparty.com.google.protobuf.Descriptors$FieldDescriptor, int, java.lang.Object);
    Code:
       0: aload_0
       1: aload_1
       2: iload_2
       3: aload_3
       4: invokespecial #35                 // Method org/apache/hbase/thirdparty/com/google/protobuf/GeneratedMessageV3$Builder.setRepeatedField:(Lorg/apache/hbase/thirdparty/com/google/protobuf/Descriptors$FieldDescriptor;ILjava/lang/Object;)Lorg/apache/hbase/thirdparty/com/google/protobuf/GeneratedMessageV3$Builder;
       7: checkcast     #6                  // class org/apache/hadoop/hbase/shaded/protobuf/generated/BucketCacheProtos$BucketEntry$Builder
      10: areturn

  public org.apache.hadoop.hbase.shaded.protobuf.generated.BucketCacheProtos$BucketEntry$Builder addRepeatedField(org.apache.hbase.thirdparty.com.google.protobuf.Descriptors$FieldDescriptor, java.lang.Object);
    Code:
       0: aload_0
       1: aload_1
       2: aload_2
       3: invokespecial #36                 // Method org/apache/hbase/thirdparty/com/google/protobuf/GeneratedMessageV3$Builder.addRepeatedField:(Lorg/apache/hbase/thirdparty/com/google/protobuf/Descriptors$FieldDescriptor;Ljava/lang/Object;)Lorg/apache/hbase/thirdparty/com/google/protobuf/GeneratedMessageV3$Builder;
       6: checkcast     #6                  // class org/apache/hadoop/hbase/shaded/protobuf/generated/BucketCacheProtos$BucketEntry$Builder
       9: areturn

  public org.apache.hadoop.hbase.shaded.protobuf.generated.BucketCacheProtos$BucketEntry$Builder mergeFrom(org.apache.hbase.thirdparty.com.google.protobuf.Message);
    Code:
       0: aload_1
       1: instanceof    #5                  // class org/apache/hadoop/hbase/shaded/protobuf/generated/BucketCacheProtos$BucketEntry
       4: ifeq          16
       7: aload_0
       8: aload_1
       9: checkcast     #5                  // class org/apache/hadoop/hbase/shaded/protobuf/generated/BucketCacheProtos$BucketEntry
      12: invokevirtual #37                 // Method mergeFrom:(Lorg/apache/hadoop/hbase/shaded/protobuf/generated/BucketCacheProtos$BucketEntry;)Lorg/apache/hadoop/hbase/shaded/protobuf/generated/BucketCacheProtos$BucketEntry$Builder;
      15: areturn
      16: aload_0
      17: aload_1
      18: invokespecial #38                 // Method org/apache/hbase/thirdparty/com/google/protobuf/GeneratedMessageV3$Builder.mergeFrom:(Lorg/apache/hbase/thirdparty/com/google/protobuf/Message;)Lorg/apache/hbase/thirdparty/com/google/protobuf/AbstractMessage$Builder;
      21: pop
      22: aload_0
      23: areturn

  public org.apache.hadoop.hbase.shaded.protobuf.generated.BucketCacheProtos$BucketEntry$Builder mergeFrom(org.apache.hadoop.hbase.shaded.protobuf.generated.BucketCacheProtos$BucketEntry);
    Code:
       0: aload_1
       1: invokestatic  #19                 // Method org/apache/hadoop/hbase/shaded/protobuf/generated/BucketCacheProtos$BucketEntry.getDefaultInstance:()Lorg/apache/hadoop/hbase/shaded/protobuf/generated/BucketCacheProtos$BucketEntry;
       4: if_acmpne     9
       7: aload_0
       8: areturn
       9: aload_1
      10: invokevirtual #39                 // Method org/apache/hadoop/hbase/shaded/protobuf/generated/BucketCacheProtos$BucketEntry.hasOffset:()Z
      13: ifeq          25
      16: aload_0
      17: aload_1
      18: invokevirtual #40                 // Method org/apache/hadoop/hbase/shaded/protobuf/generated/BucketCacheProtos$BucketEntry.getOffset:()J
      21: invokevirtual #41                 // Method setOffset:(J)Lorg/apache/hadoop/hbase/shaded/protobuf/generated/BucketCacheProtos$BucketEntry$Builder;
      24: pop
      25: aload_1
      26: invokevirtual #42                 // Method org/apache/hadoop/hbase/shaded/protobuf/generated/BucketCacheProtos$BucketEntry.hasLength:()Z
      29: ifeq          41
      32: aload_0
      33: aload_1
      34: invokevirtual #43                 // Method org/apache/hadoop/hbase/shaded/protobuf/generated/BucketCacheProtos$BucketEntry.getLength:()I
      37: invokevirtual #44                 // Method setLength:(I)Lorg/apache/hadoop/hbase/shaded/protobuf/generated/BucketCacheProtos$BucketEntry$Builder;
      40: pop
      41: aload_1
      42: invokevirtual #45                 // Method org/apache/hadoop/hbase/shaded/protobuf/generated/BucketCacheProtos$BucketEntry.hasAccessCounter:()Z
      45: ifeq          57
      48: aload_0
      49: aload_1
      50: invokevirtual #46                 // Method org/apache/hadoop/hbase/shaded/protobuf/generated/BucketCacheProtos$BucketEntry.getAccessCounter:()J
      53: invokevirtual #47                 // Method setAccessCounter:(J)Lorg/apache/hadoop/hbase/shaded/protobuf/generated/BucketCacheProtos$BucketEntry$Builder;
      56: pop
      57: aload_1
      58: invokevirtual #48                 // Method org/apache/hadoop/hbase/shaded/protobuf/generated/BucketCacheProtos$BucketEntry.hasDeserialiserIndex:()Z
      61: ifeq          73
      64: aload_0
      65: aload_1
      66: invokevirtual #49                 // Method org/apache/hadoop/hbase/shaded/protobuf/generated/BucketCacheProtos$BucketEntry.getDeserialiserIndex:()I
      69: invokevirtual #50                 // Method setDeserialiserIndex:(I)Lorg/apache/hadoop/hbase/shaded/protobuf/generated/BucketCacheProtos$BucketEntry$Builder;
      72: pop
      73: aload_1
      74: invokevirtual #51                 // Method org/apache/hadoop/hbase/shaded/protobuf/generated/BucketCacheProtos$BucketEntry.hasPriority:()Z
      77: ifeq          89
      80: aload_0
      81: aload_1
      82: invokevirtual #52                 // Method org/apache/hadoop/hbase/shaded/protobuf/generated/BucketCacheProtos$BucketEntry.getPriority:()Lorg/apache/hadoop/hbase/shaded/protobuf/generated/BucketCacheProtos$BlockPriority;
      85: invokevirtual #53                 // Method setPriority:(Lorg/apache/hadoop/hbase/shaded/protobuf/generated/BucketCacheProtos$BlockPriority;)Lorg/apache/hadoop/hbase/shaded/protobuf/generated/BucketCacheProtos$BucketEntry$Builder;
      88: pop
      89: aload_0
      90: aload_1
      91: invokestatic  #54                 // Method org/apache/hadoop/hbase/shaded/protobuf/generated/BucketCacheProtos$BucketEntry.access$6200:(Lorg/apache/hadoop/hbase/shaded/protobuf/generated/BucketCacheProtos$BucketEntry;)Lorg/apache/hbase/thirdparty/com/google/protobuf/UnknownFieldSet;
      94: invokevirtual #55                 // Method mergeUnknownFields:(Lorg/apache/hbase/thirdparty/com/google/protobuf/UnknownFieldSet;)Lorg/apache/hadoop/hbase/shaded/protobuf/generated/BucketCacheProtos$BucketEntry$Builder;
      97: pop
      98: aload_0
      99: invokevirtual #56                 // Method onChanged:()V
     102: aload_0
     103: areturn

  public final boolean isInitialized();
    Code:
       0: aload_0
       1: invokevirtual #57                 // Method hasOffset:()Z
       4: ifne          9
       7: iconst_0
       8: ireturn
       9: aload_0
      10: invokevirtual #58                 // Method hasLength:()Z
      13: ifne          18
      16: iconst_0
      17: ireturn
      18: aload_0
      19: invokevirtual #59                 // Method hasAccessCounter:()Z
      22: ifne          27
      25: iconst_0
      26: ireturn
      27: aload_0
      28: invokevirtual #60                 // Method hasDeserialiserIndex:()Z
      31: ifne          36
      34: iconst_0
      35: ireturn
      36: aload_0
      37: invokevirtual #61                 // Method hasPriority:()Z
      40: ifne          45
      43: iconst_0
      44: ireturn
      45: iconst_1
      46: ireturn

  public org.apache.hadoop.hbase.shaded.protobuf.generated.BucketCacheProtos$BucketEntry$Builder mergeFrom(org.apache.hbase.thirdparty.com.google.protobuf.CodedInputStream, org.apache.hbase.thirdparty.com.google.protobuf.ExtensionRegistryLite) throws java.io.IOException;
    Code:
       0: aconst_null
       1: astore_3
       2: getstatic     #62                 // Field org/apache/hadoop/hbase/shaded/protobuf/generated/BucketCacheProtos$BucketEntry.PARSER:Lorg/apache/hbase/thirdparty/com/google/protobuf/Parser;
       5: aload_1
       6: aload_2
       7: invokeinterface #63,  3           // InterfaceMethod org/apache/hbase/thirdparty/com/google/protobuf/Parser.parsePartialFrom:(Lorg/apache/hbase/thirdparty/com/google/protobuf/CodedInputStream;Lorg/apache/hbase/thirdparty/com/google/protobuf/ExtensionRegistryLite;)Ljava/lang/Object;
      12: checkcast     #5                  // class org/apache/hadoop/hbase/shaded/protobuf/generated/BucketCacheProtos$BucketEntry
      15: astore_3
      16: aload_3
      17: ifnull        61
      20: aload_0
      21: aload_3
      22: invokevirtual #37                 // Method mergeFrom:(Lorg/apache/hadoop/hbase/shaded/protobuf/generated/BucketCacheProtos$BucketEntry;)Lorg/apache/hadoop/hbase/shaded/protobuf/generated/BucketCacheProtos$BucketEntry$Builder;
      25: pop
      26: goto          61
      29: astore        4
      31: aload         4
      33: invokevirtual #65                 // Method org/apache/hbase/thirdparty/com/google/protobuf/InvalidProtocolBufferException.getUnfinishedMessage:()Lorg/apache/hbase/thirdparty/com/google/protobuf/MessageLite;
      36: checkcast     #5                  // class org/apache/hadoop/hbase/shaded/protobuf/generated/BucketCacheProtos$BucketEntry
      39: astore_3
      40: aload         4
      42: invokevirtual #66                 // Method org/apache/hbase/thirdparty/com/google/protobuf/InvalidProtocolBufferException.unwrapIOException:()Ljava/io/IOException;
      45: athrow
      46: astore        5
      48: aload_3
      49: ifnull        58
      52: aload_0
      53: aload_3
      54: invokevirtual #37                 // Method mergeFrom:(Lorg/apache/hadoop/hbase/shaded/protobuf/generated/BucketCacheProtos$BucketEntry;)Lorg/apache/hadoop/hbase/shaded/protobuf/generated/BucketCacheProtos$BucketEntry$Builder;
      57: pop
      58: aload         5
      60: athrow
      61: aload_0
      62: areturn
    Exception table:
       from    to  target type
           2    16    29   Class org/apache/hbase/thirdparty/com/google/protobuf/InvalidProtocolBufferException
           2    16    46   any
          29    48    46   any

  public boolean hasOffset();
    Code:
       0: aload_0
       1: getfield      #15                 // Field bitField0_:I
       4: iconst_1
       5: iand
       6: iconst_1
       7: if_icmpne     14
      10: iconst_1
      11: goto          15
      14: iconst_0
      15: ireturn

  public long getOffset();
    Code:
       0: aload_0
       1: getfield      #14                 // Field offset_:J
       4: lreturn

  public org.apache.hadoop.hbase.shaded.protobuf.generated.BucketCacheProtos$BucketEntry$Builder setOffset(long);
    Code:
       0: aload_0
       1: dup
       2: getfield      #15                 // Field bitField0_:I
       5: iconst_1
       6: ior
       7: putfield      #15                 // Field bitField0_:I
      10: aload_0
      11: lload_1
      12: putfield      #14                 // Field offset_:J
      15: aload_0
      16: invokevirtual #56                 // Method onChanged:()V
      19: aload_0
      20: areturn

  public org.apache.hadoop.hbase.shaded.protobuf.generated.BucketCacheProtos$BucketEntry$Builder clearOffset();
    Code:
       0: aload_0
       1: aload_0
       2: getfield      #15                 // Field bitField0_:I
       5: bipush        -2
       7: iand
       8: putfield      #15                 // Field bitField0_:I
      11: aload_0
      12: lconst_0
      13: putfield      #14                 // Field offset_:J
      16: aload_0
      17: invokevirtual #56                 // Method onChanged:()V
      20: aload_0
      21: areturn

  public boolean hasLength();
    Code:
       0: aload_0
       1: getfield      #15                 // Field bitField0_:I
       4: iconst_2
       5: iand
       6: iconst_2
       7: if_icmpne     14
      10: iconst_1
      11: goto          15
      14: iconst_0
      15: ireturn

  public int getLength();
    Code:
       0: aload_0
       1: getfield      #16                 // Field length_:I
       4: ireturn

  public org.apache.hadoop.hbase.shaded.protobuf.generated.BucketCacheProtos$BucketEntry$Builder setLength(int);
    Code:
       0: aload_0
       1: dup
       2: getfield      #15                 // Field bitField0_:I
       5: iconst_2
       6: ior
       7: putfield      #15                 // Field bitField0_:I
      10: aload_0
      11: iload_1
      12: putfield      #16                 // Field length_:I
      15: aload_0
      16: invokevirtual #56                 // Method onChanged:()V
      19: aload_0
      20: areturn

  public org.apache.hadoop.hbase.shaded.protobuf.generated.BucketCacheProtos$BucketEntry$Builder clearLength();
    Code:
       0: aload_0
       1: aload_0
       2: getfield      #15                 // Field bitField0_:I
       5: bipush        -3
       7: iand
       8: putfield      #15                 // Field bitField0_:I
      11: aload_0
      12: iconst_0
      13: putfield      #16                 // Field length_:I
      16: aload_0
      17: invokevirtual #56                 // Method onChanged:()V
      20: aload_0
      21: areturn

  public boolean hasAccessCounter();
    Code:
       0: aload_0
       1: getfield      #15                 // Field bitField0_:I
       4: iconst_4
       5: iand
       6: iconst_4
       7: if_icmpne     14
      10: iconst_1
      11: goto          15
      14: iconst_0
      15: ireturn

  public long getAccessCounter();
    Code:
       0: aload_0
       1: getfield      #17                 // Field accessCounter_:J
       4: lreturn

  public org.apache.hadoop.hbase.shaded.protobuf.generated.BucketCacheProtos$BucketEntry$Builder setAccessCounter(long);
    Code:
       0: aload_0
       1: dup
       2: getfield      #15                 // Field bitField0_:I
       5: iconst_4
       6: ior
       7: putfield      #15                 // Field bitField0_:I
      10: aload_0
      11: lload_1
      12: putfield      #17                 // Field accessCounter_:J
      15: aload_0
      16: invokevirtual #56                 // Method onChanged:()V
      19: aload_0
      20: areturn

  public org.apache.hadoop.hbase.shaded.protobuf.generated.BucketCacheProtos$BucketEntry$Builder clearAccessCounter();
    Code:
       0: aload_0
       1: aload_0
       2: getfield      #15                 // Field bitField0_:I
       5: bipush        -5
       7: iand
       8: putfield      #15                 // Field bitField0_:I
      11: aload_0
      12: lconst_0
      13: putfield      #17                 // Field accessCounter_:J
      16: aload_0
      17: invokevirtual #56                 // Method onChanged:()V
      20: aload_0
      21: areturn

  public boolean hasDeserialiserIndex();
    Code:
       0: aload_0
       1: getfield      #15                 // Field bitField0_:I
       4: bipush        8
       6: iand
       7: bipush        8
       9: if_icmpne     16
      12: iconst_1
      13: goto          17
      16: iconst_0
      17: ireturn

  public int getDeserialiserIndex();
    Code:
       0: aload_0
       1: getfield      #18                 // Field deserialiserIndex_:I
       4: ireturn

  public org.apache.hadoop.hbase.shaded.protobuf.generated.BucketCacheProtos$BucketEntry$Builder setDeserialiserIndex(int);
    Code:
       0: aload_0
       1: dup
       2: getfield      #15                 // Field bitField0_:I
       5: bipush        8
       7: ior
       8: putfield      #15                 // Field bitField0_:I
      11: aload_0
      12: iload_1
      13: putfield      #18                 // Field deserialiserIndex_:I
      16: aload_0
      17: invokevirtual #56                 // Method onChanged:()V
      20: aload_0
      21: areturn

  public org.apache.hadoop.hbase.shaded.protobuf.generated.BucketCacheProtos$BucketEntry$Builder clearDeserialiserIndex();
    Code:
       0: aload_0
       1: aload_0
       2: getfield      #15                 // Field bitField0_:I
       5: bipush        -9
       7: iand
       8: putfield      #15                 // Field bitField0_:I
      11: aload_0
      12: iconst_0
      13: putfield      #18                 // Field deserialiserIndex_:I
      16: aload_0
      17: invokevirtual #56                 // Method onChanged:()V
      20: aload_0
      21: areturn

  public boolean hasPriority();
    Code:
       0: aload_0
       1: getfield      #15                 // Field bitField0_:I
       4: bipush        16
       6: iand
       7: bipush        16
       9: if_icmpne     16
      12: iconst_1
      13: goto          17
      16: iconst_0
      17: ireturn

  public org.apache.hadoop.hbase.shaded.protobuf.generated.BucketCacheProtos$BlockPriority getPriority();
    Code:
       0: aload_0
       1: getfield      #9                  // Field priority_:I
       4: invokestatic  #67                 // Method org/apache/hadoop/hbase/shaded/protobuf/generated/BucketCacheProtos$BlockPriority.valueOf:(I)Lorg/apache/hadoop/hbase/shaded/protobuf/generated/BucketCacheProtos$BlockPriority;
       7: astore_1
       8: aload_1
       9: ifnonnull     18
      12: getstatic     #68                 // Field org/apache/hadoop/hbase/shaded/protobuf/generated/BucketCacheProtos$BlockPriority.single:Lorg/apache/hadoop/hbase/shaded/protobuf/generated/BucketCacheProtos$BlockPriority;
      15: goto          19
      18: aload_1
      19: areturn

  public org.apache.hadoop.hbase.shaded.protobuf.generated.BucketCacheProtos$BucketEntry$Builder setPriority(org.apache.hadoop.hbase.shaded.protobuf.generated.BucketCacheProtos$BlockPriority);
    Code:
       0: aload_1
       1: ifnonnull     12
       4: new           #69                 // class java/lang/NullPointerException
       7: dup
       8: invokespecial #70                 // Method java/lang/NullPointerException."<init>":()V
      11: athrow
      12: aload_0
      13: dup
      14: getfield      #15                 // Field bitField0_:I
      17: bipush        16
      19: ior
      20: putfield      #15                 // Field bitField0_:I
      23: aload_0
      24: aload_1
      25: invokevirtual #71                 // Method org/apache/hadoop/hbase/shaded/protobuf/generated/BucketCacheProtos$BlockPriority.getNumber:()I
      28: putfield      #9                  // Field priority_:I
      31: aload_0
      32: invokevirtual #56                 // Method onChanged:()V
      35: aload_0
      36: areturn

  public org.apache.hadoop.hbase.shaded.protobuf.generated.BucketCacheProtos$BucketEntry$Builder clearPriority();
    Code:
       0: aload_0
       1: aload_0
       2: getfield      #15                 // Field bitField0_:I
       5: bipush        -17
       7: iand
       8: putfield      #15                 // Field bitField0_:I
      11: aload_0
      12: iconst_0
      13: putfield      #9                  // Field priority_:I
      16: aload_0
      17: invokevirtual #56                 // Method onChanged:()V
      20: aload_0
      21: areturn

  public final org.apache.hadoop.hbase.shaded.protobuf.generated.BucketCacheProtos$BucketEntry$Builder setUnknownFields(org.apache.hbase.thirdparty.com.google.protobuf.UnknownFieldSet);
    Code:
       0: aload_0
       1: aload_1
       2: invokespecial #72                 // Method org/apache/hbase/thirdparty/com/google/protobuf/GeneratedMessageV3$Builder.setUnknownFields:(Lorg/apache/hbase/thirdparty/com/google/protobuf/UnknownFieldSet;)Lorg/apache/hbase/thirdparty/com/google/protobuf/GeneratedMessageV3$Builder;
       5: checkcast     #6                  // class org/apache/hadoop/hbase/shaded/protobuf/generated/BucketCacheProtos$BucketEntry$Builder
       8: areturn

  public final org.apache.hadoop.hbase.shaded.protobuf.generated.BucketCacheProtos$BucketEntry$Builder mergeUnknownFields(org.apache.hbase.thirdparty.com.google.protobuf.UnknownFieldSet);
    Code:
       0: aload_0
       1: aload_1
       2: invokespecial #73                 // Method org/apache/hbase/thirdparty/com/google/protobuf/GeneratedMessageV3$Builder.mergeUnknownFields:(Lorg/apache/hbase/thirdparty/com/google/protobuf/UnknownFieldSet;)Lorg/apache/hbase/thirdparty/com/google/protobuf/GeneratedMessageV3$Builder;
       5: checkcast     #6                  // class org/apache/hadoop/hbase/shaded/protobuf/generated/BucketCacheProtos$BucketEntry$Builder
       8: areturn

  public org.apache.hbase.thirdparty.com.google.protobuf.GeneratedMessageV3$Builder mergeUnknownFields(org.apache.hbase.thirdparty.com.google.protobuf.UnknownFieldSet);
    Code:
       0: aload_0
       1: aload_1
       2: invokevirtual #55                 // Method mergeUnknownFields:(Lorg/apache/hbase/thirdparty/com/google/protobuf/UnknownFieldSet;)Lorg/apache/hadoop/hbase/shaded/protobuf/generated/BucketCacheProtos$BucketEntry$Builder;
       5: areturn

  public org.apache.hbase.thirdparty.com.google.protobuf.GeneratedMessageV3$Builder setUnknownFields(org.apache.hbase.thirdparty.com.google.protobuf.UnknownFieldSet);
    Code:
       0: aload_0
       1: aload_1
       2: invokevirtual #74                 // Method setUnknownFields:(Lorg/apache/hbase/thirdparty/com/google/protobuf/UnknownFieldSet;)Lorg/apache/hadoop/hbase/shaded/protobuf/generated/BucketCacheProtos$BucketEntry$Builder;
       5: areturn

  public org.apache.hbase.thirdparty.com.google.protobuf.GeneratedMessageV3$Builder addRepeatedField(org.apache.hbase.thirdparty.com.google.protobuf.Descriptors$FieldDescriptor, java.lang.Object);
    Code:
       0: aload_0
       1: aload_1
       2: aload_2
       3: invokevirtual #75                 // Method addRepeatedField:(Lorg/apache/hbase/thirdparty/com/google/protobuf/Descriptors$FieldDescriptor;Ljava/lang/Object;)Lorg/apache/hadoop/hbase/shaded/protobuf/generated/BucketCacheProtos$BucketEntry$Builder;
       6: areturn

  public org.apache.hbase.thirdparty.com.google.protobuf.GeneratedMessageV3$Builder setRepeatedField(org.apache.hbase.thirdparty.com.google.protobuf.Descriptors$FieldDescriptor, int, java.lang.Object);
    Code:
       0: aload_0
       1: aload_1
       2: iload_2
       3: aload_3
       4: invokevirtual #76                 // Method setRepeatedField:(Lorg/apache/hbase/thirdparty/com/google/protobuf/Descriptors$FieldDescriptor;ILjava/lang/Object;)Lorg/apache/hadoop/hbase/shaded/protobuf/generated/BucketCacheProtos$BucketEntry$Builder;
       7: areturn

  public org.apache.hbase.thirdparty.com.google.protobuf.GeneratedMessageV3$Builder clearOneof(org.apache.hbase.thirdparty.com.google.protobuf.Descriptors$OneofDescriptor);
    Code:
       0: aload_0
       1: aload_1
       2: invokevirtual #77                 // Method clearOneof:(Lorg/apache/hbase/thirdparty/com/google/protobuf/Descriptors$OneofDescriptor;)Lorg/apache/hadoop/hbase/shaded/protobuf/generated/BucketCacheProtos$BucketEntry$Builder;
       5: areturn

  public org.apache.hbase.thirdparty.com.google.protobuf.GeneratedMessageV3$Builder clearField(org.apache.hbase.thirdparty.com.google.protobuf.Descriptors$FieldDescriptor);
    Code:
       0: aload_0
       1: aload_1
       2: invokevirtual #78                 // Method clearField:(Lorg/apache/hbase/thirdparty/com/google/protobuf/Descriptors$FieldDescriptor;)Lorg/apache/hadoop/hbase/shaded/protobuf/generated/BucketCacheProtos$BucketEntry$Builder;
       5: areturn

  public org.apache.hbase.thirdparty.com.google.protobuf.GeneratedMessageV3$Builder setField(org.apache.hbase.thirdparty.com.google.protobuf.Descriptors$FieldDescriptor, java.lang.Object);
    Code:
       0: aload_0
       1: aload_1
       2: aload_2
       3: invokevirtual #79                 // Method setField:(Lorg/apache/hbase/thirdparty/com/google/protobuf/Descriptors$FieldDescriptor;Ljava/lang/Object;)Lorg/apache/hadoop/hbase/shaded/protobuf/generated/BucketCacheProtos$BucketEntry$Builder;
       6: areturn

  public org.apache.hbase.thirdparty.com.google.protobuf.GeneratedMessageV3$Builder clear();
    Code:
       0: aload_0
       1: invokevirtual #80                 // Method clear:()Lorg/apache/hadoop/hbase/shaded/protobuf/generated/BucketCacheProtos$BucketEntry$Builder;
       4: areturn

  public org.apache.hbase.thirdparty.com.google.protobuf.GeneratedMessageV3$Builder clone();
    Code:
       0: aload_0
       1: invokevirtual #81                 // Method clone:()Lorg/apache/hadoop/hbase/shaded/protobuf/generated/BucketCacheProtos$BucketEntry$Builder;
       4: areturn

  public org.apache.hbase.thirdparty.com.google.protobuf.AbstractMessage$Builder mergeUnknownFields(org.apache.hbase.thirdparty.com.google.protobuf.UnknownFieldSet);
    Code:
       0: aload_0
       1: aload_1
       2: invokevirtual #55                 // Method mergeUnknownFields:(Lorg/apache/hbase/thirdparty/com/google/protobuf/UnknownFieldSet;)Lorg/apache/hadoop/hbase/shaded/protobuf/generated/BucketCacheProtos$BucketEntry$Builder;
       5: areturn

  public org.apache.hbase.thirdparty.com.google.protobuf.AbstractMessage$Builder mergeFrom(org.apache.hbase.thirdparty.com.google.protobuf.CodedInputStream, org.apache.hbase.thirdparty.com.google.protobuf.ExtensionRegistryLite) throws java.io.IOException;
    Code:
       0: aload_0
       1: aload_1
       2: aload_2
       3: invokevirtual #82                 // Method mergeFrom:(Lorg/apache/hbase/thirdparty/com/google/protobuf/CodedInputStream;Lorg/apache/hbase/thirdparty/com/google/protobuf/ExtensionRegistryLite;)Lorg/apache/hadoop/hbase/shaded/protobuf/generated/BucketCacheProtos$BucketEntry$Builder;
       6: areturn

  public org.apache.hbase.thirdparty.com.google.protobuf.AbstractMessage$Builder mergeFrom(org.apache.hbase.thirdparty.com.google.protobuf.Message);
    Code:
       0: aload_0
       1: aload_1
       2: invokevirtual #83                 // Method mergeFrom:(Lorg/apache/hbase/thirdparty/com/google/protobuf/Message;)Lorg/apache/hadoop/hbase/shaded/protobuf/generated/BucketCacheProtos$BucketEntry$Builder;
       5: areturn

  public org.apache.hbase.thirdparty.com.google.protobuf.AbstractMessage$Builder clear();
    Code:
       0: aload_0
       1: invokevirtual #80                 // Method clear:()Lorg/apache/hadoop/hbase/shaded/protobuf/generated/BucketCacheProtos$BucketEntry$Builder;
       4: areturn

  public org.apache.hbase.thirdparty.com.google.protobuf.AbstractMessage$Builder clearOneof(org.apache.hbase.thirdparty.com.google.protobuf.Descriptors$OneofDescriptor);
    Code:
       0: aload_0
       1: aload_1
       2: invokevirtual #77                 // Method clearOneof:(Lorg/apache/hbase/thirdparty/com/google/protobuf/Descriptors$OneofDescriptor;)Lorg/apache/hadoop/hbase/shaded/protobuf/generated/BucketCacheProtos$BucketEntry$Builder;
       5: areturn

  public org.apache.hbase.thirdparty.com.google.protobuf.AbstractMessage$Builder clone();
    Code:
       0: aload_0
       1: invokevirtual #81                 // Method clone:()Lorg/apache/hadoop/hbase/shaded/protobuf/generated/BucketCacheProtos$BucketEntry$Builder;
       4: areturn

  public org.apache.hbase.thirdparty.com.google.protobuf.Message$Builder mergeUnknownFields(org.apache.hbase.thirdparty.com.google.protobuf.UnknownFieldSet);
    Code:
       0: aload_0
       1: aload_1
       2: invokevirtual #55                 // Method mergeUnknownFields:(Lorg/apache/hbase/thirdparty/com/google/protobuf/UnknownFieldSet;)Lorg/apache/hadoop/hbase/shaded/protobuf/generated/BucketCacheProtos$BucketEntry$Builder;
       5: areturn

  public org.apache.hbase.thirdparty.com.google.protobuf.Message$Builder setUnknownFields(org.apache.hbase.thirdparty.com.google.protobuf.UnknownFieldSet);
    Code:
       0: aload_0
       1: aload_1
       2: invokevirtual #74                 // Method setUnknownFields:(Lorg/apache/hbase/thirdparty/com/google/protobuf/UnknownFieldSet;)Lorg/apache/hadoop/hbase/shaded/protobuf/generated/BucketCacheProtos$BucketEntry$Builder;
       5: areturn

  public org.apache.hbase.thirdparty.com.google.protobuf.Message$Builder addRepeatedField(org.apache.hbase.thirdparty.com.google.protobuf.Descriptors$FieldDescriptor, java.lang.Object);
    Code:
       0: aload_0
       1: aload_1
       2: aload_2
       3: invokevirtual #75                 // Method addRepeatedField:(Lorg/apache/hbase/thirdparty/com/google/protobuf/Descriptors$FieldDescriptor;Ljava/lang/Object;)Lorg/apache/hadoop/hbase/shaded/protobuf/generated/BucketCacheProtos$BucketEntry$Builder;
       6: areturn

  public org.apache.hbase.thirdparty.com.google.protobuf.Message$Builder setRepeatedField(org.apache.hbase.thirdparty.com.google.protobuf.Descriptors$FieldDescriptor, int, java.lang.Object);
    Code:
       0: aload_0
       1: aload_1
       2: iload_2
       3: aload_3
       4: invokevirtual #76                 // Method setRepeatedField:(Lorg/apache/hbase/thirdparty/com/google/protobuf/Descriptors$FieldDescriptor;ILjava/lang/Object;)Lorg/apache/hadoop/hbase/shaded/protobuf/generated/BucketCacheProtos$BucketEntry$Builder;
       7: areturn

  public org.apache.hbase.thirdparty.com.google.protobuf.Message$Builder clearOneof(org.apache.hbase.thirdparty.com.google.protobuf.Descriptors$OneofDescriptor);
    Code:
       0: aload_0
       1: aload_1
       2: invokevirtual #77                 // Method clearOneof:(Lorg/apache/hbase/thirdparty/com/google/protobuf/Descriptors$OneofDescriptor;)Lorg/apache/hadoop/hbase/shaded/protobuf/generated/BucketCacheProtos$BucketEntry$Builder;
       5: areturn

  public org.apache.hbase.thirdparty.com.google.protobuf.Message$Builder clearField(org.apache.hbase.thirdparty.com.google.protobuf.Descriptors$FieldDescriptor);
    Code:
       0: aload_0
       1: aload_1
       2: invokevirtual #78                 // Method clearField:(Lorg/apache/hbase/thirdparty/com/google/protobuf/Descriptors$FieldDescriptor;)Lorg/apache/hadoop/hbase/shaded/protobuf/generated/BucketCacheProtos$BucketEntry$Builder;
       5: areturn

  public org.apache.hbase.thirdparty.com.google.protobuf.Message$Builder setField(org.apache.hbase.thirdparty.com.google.protobuf.Descriptors$FieldDescriptor, java.lang.Object);
    Code:
       0: aload_0
       1: aload_1
       2: aload_2
       3: invokevirtual #79                 // Method setField:(Lorg/apache/hbase/thirdparty/com/google/protobuf/Descriptors$FieldDescriptor;Ljava/lang/Object;)Lorg/apache/hadoop/hbase/shaded/protobuf/generated/BucketCacheProtos$BucketEntry$Builder;
       6: areturn

  public org.apache.hbase.thirdparty.com.google.protobuf.Message$Builder mergeFrom(org.apache.hbase.thirdparty.com.google.protobuf.CodedInputStream, org.apache.hbase.thirdparty.com.google.protobuf.ExtensionRegistryLite) throws java.io.IOException;
    Code:
       0: aload_0
       1: aload_1
       2: aload_2
       3: invokevirtual #82                 // Method mergeFrom:(Lorg/apache/hbase/thirdparty/com/google/protobuf/CodedInputStream;Lorg/apache/hbase/thirdparty/com/google/protobuf/ExtensionRegistryLite;)Lorg/apache/hadoop/hbase/shaded/protobuf/generated/BucketCacheProtos$BucketEntry$Builder;
       6: areturn

  public org.apache.hbase.thirdparty.com.google.protobuf.Message$Builder clone();
    Code:
       0: aload_0
       1: invokevirtual #81                 // Method clone:()Lorg/apache/hadoop/hbase/shaded/protobuf/generated/BucketCacheProtos$BucketEntry$Builder;
       4: areturn

  public org.apache.hbase.thirdparty.com.google.protobuf.Message buildPartial();
    Code:
       0: aload_0
       1: invokevirtual #20                 // Method buildPartial:()Lorg/apache/hadoop/hbase/shaded/protobuf/generated/BucketCacheProtos$BucketEntry;
       4: areturn

  public org.apache.hbase.thirdparty.com.google.protobuf.Message build();
    Code:
       0: aload_0
       1: invokevirtual #84                 // Method build:()Lorg/apache/hadoop/hbase/shaded/protobuf/generated/BucketCacheProtos$BucketEntry;
       4: areturn

  public org.apache.hbase.thirdparty.com.google.protobuf.Message$Builder mergeFrom(org.apache.hbase.thirdparty.com.google.protobuf.Message);
    Code:
       0: aload_0
       1: aload_1
       2: invokevirtual #83                 // Method mergeFrom:(Lorg/apache/hbase/thirdparty/com/google/protobuf/Message;)Lorg/apache/hadoop/hbase/shaded/protobuf/generated/BucketCacheProtos$BucketEntry$Builder;
       5: areturn

  public org.apache.hbase.thirdparty.com.google.protobuf.Message$Builder clear();
    Code:
       0: aload_0
       1: invokevirtual #80                 // Method clear:()Lorg/apache/hadoop/hbase/shaded/protobuf/generated/BucketCacheProtos$BucketEntry$Builder;
       4: areturn

  public org.apache.hbase.thirdparty.com.google.protobuf.MessageLite$Builder mergeFrom(org.apache.hbase.thirdparty.com.google.protobuf.CodedInputStream, org.apache.hbase.thirdparty.com.google.protobuf.ExtensionRegistryLite) throws java.io.IOException;
    Code:
       0: aload_0
       1: aload_1
       2: aload_2
       3: invokevirtual #82                 // Method mergeFrom:(Lorg/apache/hbase/thirdparty/com/google/protobuf/CodedInputStream;Lorg/apache/hbase/thirdparty/com/google/protobuf/ExtensionRegistryLite;)Lorg/apache/hadoop/hbase/shaded/protobuf/generated/BucketCacheProtos$BucketEntry$Builder;
       6: areturn

  public org.apache.hbase.thirdparty.com.google.protobuf.MessageLite$Builder clone();
    Code:
       0: aload_0
       1: invokevirtual #81                 // Method clone:()Lorg/apache/hadoop/hbase/shaded/protobuf/generated/BucketCacheProtos$BucketEntry$Builder;
       4: areturn

  public org.apache.hbase.thirdparty.com.google.protobuf.MessageLite buildPartial();
    Code:
       0: aload_0
       1: invokevirtual #20                 // Method buildPartial:()Lorg/apache/hadoop/hbase/shaded/protobuf/generated/BucketCacheProtos$BucketEntry;
       4: areturn

  public org.apache.hbase.thirdparty.com.google.protobuf.MessageLite build();
    Code:
       0: aload_0
       1: invokevirtual #84                 // Method build:()Lorg/apache/hadoop/hbase/shaded/protobuf/generated/BucketCacheProtos$BucketEntry;
       4: areturn

  public org.apache.hbase.thirdparty.com.google.protobuf.MessageLite$Builder clear();
    Code:
       0: aload_0
       1: invokevirtual #80                 // Method clear:()Lorg/apache/hadoop/hbase/shaded/protobuf/generated/BucketCacheProtos$BucketEntry$Builder;
       4: areturn

  public org.apache.hbase.thirdparty.com.google.protobuf.MessageLite getDefaultInstanceForType();
    Code:
       0: aload_0
       1: invokevirtual #85                 // Method getDefaultInstanceForType:()Lorg/apache/hadoop/hbase/shaded/protobuf/generated/BucketCacheProtos$BucketEntry;
       4: areturn

  public org.apache.hbase.thirdparty.com.google.protobuf.Message getDefaultInstanceForType();
    Code:
       0: aload_0
       1: invokevirtual #85                 // Method getDefaultInstanceForType:()Lorg/apache/hadoop/hbase/shaded/protobuf/generated/BucketCacheProtos$BucketEntry;
       4: areturn

  public org.apache.hbase.thirdparty.com.google.protobuf.AbstractMessageLite$Builder mergeFrom(org.apache.hbase.thirdparty.com.google.protobuf.CodedInputStream, org.apache.hbase.thirdparty.com.google.protobuf.ExtensionRegistryLite) throws java.io.IOException;
    Code:
       0: aload_0
       1: aload_1
       2: aload_2
       3: invokevirtual #82                 // Method mergeFrom:(Lorg/apache/hbase/thirdparty/com/google/protobuf/CodedInputStream;Lorg/apache/hbase/thirdparty/com/google/protobuf/ExtensionRegistryLite;)Lorg/apache/hadoop/hbase/shaded/protobuf/generated/BucketCacheProtos$BucketEntry$Builder;
       6: areturn

  public org.apache.hbase.thirdparty.com.google.protobuf.AbstractMessageLite$Builder clone();
    Code:
       0: aload_0
       1: invokevirtual #81                 // Method clone:()Lorg/apache/hadoop/hbase/shaded/protobuf/generated/BucketCacheProtos$BucketEntry$Builder;
       4: areturn

  public java.lang.Object clone() throws java.lang.CloneNotSupportedException;
    Code:
       0: aload_0
       1: invokevirtual #81                 // Method clone:()Lorg/apache/hadoop/hbase/shaded/protobuf/generated/BucketCacheProtos$BucketEntry$Builder;
       4: areturn

  org.apache.hadoop.hbase.shaded.protobuf.generated.BucketCacheProtos$BucketEntry$Builder(org.apache.hadoop.hbase.shaded.protobuf.generated.BucketCacheProtos$1);
    Code:
       0: aload_0
       1: invokespecial #2                  // Method "<init>":()V
       4: return

  org.apache.hadoop.hbase.shaded.protobuf.generated.BucketCacheProtos$BucketEntry$Builder(org.apache.hbase.thirdparty.com.google.protobuf.GeneratedMessageV3$BuilderParent, org.apache.hadoop.hbase.shaded.protobuf.generated.BucketCacheProtos$1);
    Code:
       0: aload_0
       1: aload_1
       2: invokespecial #1                  // Method "<init>":(Lorg/apache/hbase/thirdparty/com/google/protobuf/GeneratedMessageV3$BuilderParent;)V
       5: return
}
