Compiled from "BucketProtoUtils.java"
class org.apache.hadoop.hbase.io.hfile.bucket.BucketProtoUtils$1 {
  static final int[] $SwitchMap$org$apache$hadoop$hbase$io$hfile$BlockType;

  static final int[] $SwitchMap$org$apache$hadoop$hbase$io$hfile$BlockPriority;

  static final int[] $SwitchMap$org$apache$hadoop$hbase$shaded$protobuf$generated$BucketCacheProtos$BlockType;

  static {};
    Code:
       0: invokestatic  #1                  // Method org/apache/hadoop/hbase/shaded/protobuf/generated/BucketCacheProtos$BlockType.values:()[Lorg/apache/hadoop/hbase/shaded/protobuf/generated/BucketCacheProtos$BlockType;
       3: arraylength
       4: newarray       int
       6: putstatic     #2                  // Field $SwitchMap$org$apache$hadoop$hbase$shaded$protobuf$generated$BucketCacheProtos$BlockType:[I
       9: getstatic     #2                  // Field $SwitchMap$org$apache$hadoop$hbase$shaded$protobuf$generated$BucketCacheProtos$BlockType:[I
      12: getstatic     #3                  // Field org/apache/hadoop/hbase/shaded/protobuf/generated/BucketCacheProtos$BlockType.data:Lorg/apache/hadoop/hbase/shaded/protobuf/generated/BucketCacheProtos$BlockType;
      15: invokevirtual #4                  // Method org/apache/hadoop/hbase/shaded/protobuf/generated/BucketCacheProtos$BlockType.ordinal:()I
      18: iconst_1
      19: iastore
      20: goto          24
      23: astore_0
      24: getstatic     #2                  // Field $SwitchMap$org$apache$hadoop$hbase$shaded$protobuf$generated$BucketCacheProtos$BlockType:[I
      27: getstatic     #6                  // Field org/apache/hadoop/hbase/shaded/protobuf/generated/BucketCacheProtos$BlockType.meta:Lorg/apache/hadoop/hbase/shaded/protobuf/generated/BucketCacheProtos$BlockType;
      30: invokevirtual #4                  // Method org/apache/hadoop/hbase/shaded/protobuf/generated/BucketCacheProtos$BlockType.ordinal:()I
      33: iconst_2
      34: iastore
      35: goto          39
      38: astore_0
      39: getstatic     #2                  // Field $SwitchMap$org$apache$hadoop$hbase$shaded$protobuf$generated$BucketCacheProtos$BlockType:[I
      42: getstatic     #7                  // Field org/apache/hadoop/hbase/shaded/protobuf/generated/BucketCacheProtos$BlockType.trailer:Lorg/apache/hadoop/hbase/shaded/protobuf/generated/BucketCacheProtos$BlockType;
      45: invokevirtual #4                  // Method org/apache/hadoop/hbase/shaded/protobuf/generated/BucketCacheProtos$BlockType.ordinal:()I
      48: iconst_3
      49: iastore
      50: goto          54
      53: astore_0
      54: getstatic     #2                  // Field $SwitchMap$org$apache$hadoop$hbase$shaded$protobuf$generated$BucketCacheProtos$BlockType:[I
      57: getstatic     #8                  // Field org/apache/hadoop/hbase/shaded/protobuf/generated/BucketCacheProtos$BlockType.index_v1:Lorg/apache/hadoop/hbase/shaded/protobuf/generated/BucketCacheProtos$BlockType;
      60: invokevirtual #4                  // Method org/apache/hadoop/hbase/shaded/protobuf/generated/BucketCacheProtos$BlockType.ordinal:()I
      63: iconst_4
      64: iastore
      65: goto          69
      68: astore_0
      69: getstatic     #2                  // Field $SwitchMap$org$apache$hadoop$hbase$shaded$protobuf$generated$BucketCacheProtos$BlockType:[I
      72: getstatic     #9                  // Field org/apache/hadoop/hbase/shaded/protobuf/generated/BucketCacheProtos$BlockType.file_info:Lorg/apache/hadoop/hbase/shaded/protobuf/generated/BucketCacheProtos$BlockType;
      75: invokevirtual #4                  // Method org/apache/hadoop/hbase/shaded/protobuf/generated/BucketCacheProtos$BlockType.ordinal:()I
      78: iconst_5
      79: iastore
      80: goto          84
      83: astore_0
      84: getstatic     #2                  // Field $SwitchMap$org$apache$hadoop$hbase$shaded$protobuf$generated$BucketCacheProtos$BlockType:[I
      87: getstatic     #10                 // Field org/apache/hadoop/hbase/shaded/protobuf/generated/BucketCacheProtos$BlockType.leaf_index:Lorg/apache/hadoop/hbase/shaded/protobuf/generated/BucketCacheProtos$BlockType;
      90: invokevirtual #4                  // Method org/apache/hadoop/hbase/shaded/protobuf/generated/BucketCacheProtos$BlockType.ordinal:()I
      93: bipush        6
      95: iastore
      96: goto          100
      99: astore_0
     100: getstatic     #2                  // Field $SwitchMap$org$apache$hadoop$hbase$shaded$protobuf$generated$BucketCacheProtos$BlockType:[I
     103: getstatic     #11                 // Field org/apache/hadoop/hbase/shaded/protobuf/generated/BucketCacheProtos$BlockType.root_index:Lorg/apache/hadoop/hbase/shaded/protobuf/generated/BucketCacheProtos$BlockType;
     106: invokevirtual #4                  // Method org/apache/hadoop/hbase/shaded/protobuf/generated/BucketCacheProtos$BlockType.ordinal:()I
     109: bipush        7
     111: iastore
     112: goto          116
     115: astore_0
     116: getstatic     #2                  // Field $SwitchMap$org$apache$hadoop$hbase$shaded$protobuf$generated$BucketCacheProtos$BlockType:[I
     119: getstatic     #12                 // Field org/apache/hadoop/hbase/shaded/protobuf/generated/BucketCacheProtos$BlockType.bloom_chunk:Lorg/apache/hadoop/hbase/shaded/protobuf/generated/BucketCacheProtos$BlockType;
     122: invokevirtual #4                  // Method org/apache/hadoop/hbase/shaded/protobuf/generated/BucketCacheProtos$BlockType.ordinal:()I
     125: bipush        8
     127: iastore
     128: goto          132
     131: astore_0
     132: getstatic     #2                  // Field $SwitchMap$org$apache$hadoop$hbase$shaded$protobuf$generated$BucketCacheProtos$BlockType:[I
     135: getstatic     #13                 // Field org/apache/hadoop/hbase/shaded/protobuf/generated/BucketCacheProtos$BlockType.encoded_data:Lorg/apache/hadoop/hbase/shaded/protobuf/generated/BucketCacheProtos$BlockType;
     138: invokevirtual #4                  // Method org/apache/hadoop/hbase/shaded/protobuf/generated/BucketCacheProtos$BlockType.ordinal:()I
     141: bipush        9
     143: iastore
     144: goto          148
     147: astore_0
     148: getstatic     #2                  // Field $SwitchMap$org$apache$hadoop$hbase$shaded$protobuf$generated$BucketCacheProtos$BlockType:[I
     151: getstatic     #14                 // Field org/apache/hadoop/hbase/shaded/protobuf/generated/BucketCacheProtos$BlockType.general_bloom_meta:Lorg/apache/hadoop/hbase/shaded/protobuf/generated/BucketCacheProtos$BlockType;
     154: invokevirtual #4                  // Method org/apache/hadoop/hbase/shaded/protobuf/generated/BucketCacheProtos$BlockType.ordinal:()I
     157: bipush        10
     159: iastore
     160: goto          164
     163: astore_0
     164: getstatic     #2                  // Field $SwitchMap$org$apache$hadoop$hbase$shaded$protobuf$generated$BucketCacheProtos$BlockType:[I
     167: getstatic     #15                 // Field org/apache/hadoop/hbase/shaded/protobuf/generated/BucketCacheProtos$BlockType.intermediate_index:Lorg/apache/hadoop/hbase/shaded/protobuf/generated/BucketCacheProtos$BlockType;
     170: invokevirtual #4                  // Method org/apache/hadoop/hbase/shaded/protobuf/generated/BucketCacheProtos$BlockType.ordinal:()I
     173: bipush        11
     175: iastore
     176: goto          180
     179: astore_0
     180: getstatic     #2                  // Field $SwitchMap$org$apache$hadoop$hbase$shaded$protobuf$generated$BucketCacheProtos$BlockType:[I
     183: getstatic     #16                 // Field org/apache/hadoop/hbase/shaded/protobuf/generated/BucketCacheProtos$BlockType.delete_family_bloom_meta:Lorg/apache/hadoop/hbase/shaded/protobuf/generated/BucketCacheProtos$BlockType;
     186: invokevirtual #4                  // Method org/apache/hadoop/hbase/shaded/protobuf/generated/BucketCacheProtos$BlockType.ordinal:()I
     189: bipush        12
     191: iastore
     192: goto          196
     195: astore_0
     196: invokestatic  #17                 // Method org/apache/hadoop/hbase/io/hfile/BlockPriority.values:()[Lorg/apache/hadoop/hbase/io/hfile/BlockPriority;
     199: arraylength
     200: newarray       int
     202: putstatic     #18                 // Field $SwitchMap$org$apache$hadoop$hbase$io$hfile$BlockPriority:[I
     205: getstatic     #18                 // Field $SwitchMap$org$apache$hadoop$hbase$io$hfile$BlockPriority:[I
     208: getstatic     #19                 // Field org/apache/hadoop/hbase/io/hfile/BlockPriority.MULTI:Lorg/apache/hadoop/hbase/io/hfile/BlockPriority;
     211: invokevirtual #20                 // Method org/apache/hadoop/hbase/io/hfile/BlockPriority.ordinal:()I
     214: iconst_1
     215: iastore
     216: goto          220
     219: astore_0
     220: getstatic     #18                 // Field $SwitchMap$org$apache$hadoop$hbase$io$hfile$BlockPriority:[I
     223: getstatic     #21                 // Field org/apache/hadoop/hbase/io/hfile/BlockPriority.MEMORY:Lorg/apache/hadoop/hbase/io/hfile/BlockPriority;
     226: invokevirtual #20                 // Method org/apache/hadoop/hbase/io/hfile/BlockPriority.ordinal:()I
     229: iconst_2
     230: iastore
     231: goto          235
     234: astore_0
     235: getstatic     #18                 // Field $SwitchMap$org$apache$hadoop$hbase$io$hfile$BlockPriority:[I
     238: getstatic     #22                 // Field org/apache/hadoop/hbase/io/hfile/BlockPriority.SINGLE:Lorg/apache/hadoop/hbase/io/hfile/BlockPriority;
     241: invokevirtual #20                 // Method org/apache/hadoop/hbase/io/hfile/BlockPriority.ordinal:()I
     244: iconst_3
     245: iastore
     246: goto          250
     249: astore_0
     250: invokestatic  #23                 // Method org/apache/hadoop/hbase/io/hfile/BlockType.values:()[Lorg/apache/hadoop/hbase/io/hfile/BlockType;
     253: arraylength
     254: newarray       int
     256: putstatic     #24                 // Field $SwitchMap$org$apache$hadoop$hbase$io$hfile$BlockType:[I
     259: getstatic     #24                 // Field $SwitchMap$org$apache$hadoop$hbase$io$hfile$BlockType:[I
     262: getstatic     #25                 // Field org/apache/hadoop/hbase/io/hfile/BlockType.DATA:Lorg/apache/hadoop/hbase/io/hfile/BlockType;
     265: invokevirtual #26                 // Method org/apache/hadoop/hbase/io/hfile/BlockType.ordinal:()I
     268: iconst_1
     269: iastore
     270: goto          274
     273: astore_0
     274: getstatic     #24                 // Field $SwitchMap$org$apache$hadoop$hbase$io$hfile$BlockType:[I
     277: getstatic     #27                 // Field org/apache/hadoop/hbase/io/hfile/BlockType.META:Lorg/apache/hadoop/hbase/io/hfile/BlockType;
     280: invokevirtual #26                 // Method org/apache/hadoop/hbase/io/hfile/BlockType.ordinal:()I
     283: iconst_2
     284: iastore
     285: goto          289
     288: astore_0
     289: getstatic     #24                 // Field $SwitchMap$org$apache$hadoop$hbase$io$hfile$BlockType:[I
     292: getstatic     #28                 // Field org/apache/hadoop/hbase/io/hfile/BlockType.TRAILER:Lorg/apache/hadoop/hbase/io/hfile/BlockType;
     295: invokevirtual #26                 // Method org/apache/hadoop/hbase/io/hfile/BlockType.ordinal:()I
     298: iconst_3
     299: iastore
     300: goto          304
     303: astore_0
     304: getstatic     #24                 // Field $SwitchMap$org$apache$hadoop$hbase$io$hfile$BlockType:[I
     307: getstatic     #29                 // Field org/apache/hadoop/hbase/io/hfile/BlockType.INDEX_V1:Lorg/apache/hadoop/hbase/io/hfile/BlockType;
     310: invokevirtual #26                 // Method org/apache/hadoop/hbase/io/hfile/BlockType.ordinal:()I
     313: iconst_4
     314: iastore
     315: goto          319
     318: astore_0
     319: getstatic     #24                 // Field $SwitchMap$org$apache$hadoop$hbase$io$hfile$BlockType:[I
     322: getstatic     #30                 // Field org/apache/hadoop/hbase/io/hfile/BlockType.FILE_INFO:Lorg/apache/hadoop/hbase/io/hfile/BlockType;
     325: invokevirtual #26                 // Method org/apache/hadoop/hbase/io/hfile/BlockType.ordinal:()I
     328: iconst_5
     329: iastore
     330: goto          334
     333: astore_0
     334: getstatic     #24                 // Field $SwitchMap$org$apache$hadoop$hbase$io$hfile$BlockType:[I
     337: getstatic     #31                 // Field org/apache/hadoop/hbase/io/hfile/BlockType.LEAF_INDEX:Lorg/apache/hadoop/hbase/io/hfile/BlockType;
     340: invokevirtual #26                 // Method org/apache/hadoop/hbase/io/hfile/BlockType.ordinal:()I
     343: bipush        6
     345: iastore
     346: goto          350
     349: astore_0
     350: getstatic     #24                 // Field $SwitchMap$org$apache$hadoop$hbase$io$hfile$BlockType:[I
     353: getstatic     #32                 // Field org/apache/hadoop/hbase/io/hfile/BlockType.ROOT_INDEX:Lorg/apache/hadoop/hbase/io/hfile/BlockType;
     356: invokevirtual #26                 // Method org/apache/hadoop/hbase/io/hfile/BlockType.ordinal:()I
     359: bipush        7
     361: iastore
     362: goto          366
     365: astore_0
     366: getstatic     #24                 // Field $SwitchMap$org$apache$hadoop$hbase$io$hfile$BlockType:[I
     369: getstatic     #33                 // Field org/apache/hadoop/hbase/io/hfile/BlockType.BLOOM_CHUNK:Lorg/apache/hadoop/hbase/io/hfile/BlockType;
     372: invokevirtual #26                 // Method org/apache/hadoop/hbase/io/hfile/BlockType.ordinal:()I
     375: bipush        8
     377: iastore
     378: goto          382
     381: astore_0
     382: getstatic     #24                 // Field $SwitchMap$org$apache$hadoop$hbase$io$hfile$BlockType:[I
     385: getstatic     #34                 // Field org/apache/hadoop/hbase/io/hfile/BlockType.ENCODED_DATA:Lorg/apache/hadoop/hbase/io/hfile/BlockType;
     388: invokevirtual #26                 // Method org/apache/hadoop/hbase/io/hfile/BlockType.ordinal:()I
     391: bipush        9
     393: iastore
     394: goto          398
     397: astore_0
     398: getstatic     #24                 // Field $SwitchMap$org$apache$hadoop$hbase$io$hfile$BlockType:[I
     401: getstatic     #35                 // Field org/apache/hadoop/hbase/io/hfile/BlockType.GENERAL_BLOOM_META:Lorg/apache/hadoop/hbase/io/hfile/BlockType;
     404: invokevirtual #26                 // Method org/apache/hadoop/hbase/io/hfile/BlockType.ordinal:()I
     407: bipush        10
     409: iastore
     410: goto          414
     413: astore_0
     414: getstatic     #24                 // Field $SwitchMap$org$apache$hadoop$hbase$io$hfile$BlockType:[I
     417: getstatic     #36                 // Field org/apache/hadoop/hbase/io/hfile/BlockType.INTERMEDIATE_INDEX:Lorg/apache/hadoop/hbase/io/hfile/BlockType;
     420: invokevirtual #26                 // Method org/apache/hadoop/hbase/io/hfile/BlockType.ordinal:()I
     423: bipush        11
     425: iastore
     426: goto          430
     429: astore_0
     430: getstatic     #24                 // Field $SwitchMap$org$apache$hadoop$hbase$io$hfile$BlockType:[I
     433: getstatic     #37                 // Field org/apache/hadoop/hbase/io/hfile/BlockType.DELETE_FAMILY_BLOOM_META:Lorg/apache/hadoop/hbase/io/hfile/BlockType;
     436: invokevirtual #26                 // Method org/apache/hadoop/hbase/io/hfile/BlockType.ordinal:()I
     439: bipush        12
     441: iastore
     442: goto          446
     445: astore_0
     446: return
    Exception table:
       from    to  target type
           9    20    23   Class java/lang/NoSuchFieldError
          24    35    38   Class java/lang/NoSuchFieldError
          39    50    53   Class java/lang/NoSuchFieldError
          54    65    68   Class java/lang/NoSuchFieldError
          69    80    83   Class java/lang/NoSuchFieldError
          84    96    99   Class java/lang/NoSuchFieldError
         100   112   115   Class java/lang/NoSuchFieldError
         116   128   131   Class java/lang/NoSuchFieldError
         132   144   147   Class java/lang/NoSuchFieldError
         148   160   163   Class java/lang/NoSuchFieldError
         164   176   179   Class java/lang/NoSuchFieldError
         180   192   195   Class java/lang/NoSuchFieldError
         205   216   219   Class java/lang/NoSuchFieldError
         220   231   234   Class java/lang/NoSuchFieldError
         235   246   249   Class java/lang/NoSuchFieldError
         259   270   273   Class java/lang/NoSuchFieldError
         274   285   288   Class java/lang/NoSuchFieldError
         289   300   303   Class java/lang/NoSuchFieldError
         304   315   318   Class java/lang/NoSuchFieldError
         319   330   333   Class java/lang/NoSuchFieldError
         334   346   349   Class java/lang/NoSuchFieldError
         350   362   365   Class java/lang/NoSuchFieldError
         366   378   381   Class java/lang/NoSuchFieldError
         382   394   397   Class java/lang/NoSuchFieldError
         398   410   413   Class java/lang/NoSuchFieldError
         414   426   429   Class java/lang/NoSuchFieldError
         430   442   445   Class java/lang/NoSuchFieldError
}
