Compiled from "BufferedMutatorParams.java"
public class org.apache.hadoop.hbase.client.BufferedMutatorParams implements java.lang.Cloneable {
  static final int UNSET;

  public org.apache.hadoop.hbase.client.BufferedMutatorParams(org.apache.hadoop.hbase.TableName);
    Code:
       0: aload_0
       1: invokespecial #1                  // Method java/lang/Object."<init>":()V
       4: aload_0
       5: ldc2_w        #3                  // long -1l
       8: putfield      #5                  // Field writeBufferSize:J
      11: aload_0
      12: ldc2_w        #3                  // long -1l
      15: putfield      #6                  // Field writeBufferPeriodicFlushTimeoutMs:J
      18: aload_0
      19: ldc2_w        #3                  // long -1l
      22: putfield      #7                  // Field writeBufferPeriodicFlushTimerTickMs:J
      25: aload_0
      26: iconst_m1
      27: putfield      #8                  // Field maxKeyValueSize:I
      30: aload_0
      31: aconst_null
      32: putfield      #9                  // Field pool:Ljava/util/concurrent/ExecutorService;
      35: aload_0
      36: aconst_null
      37: putfield      #10                 // Field implementationClassName:Ljava/lang/String;
      40: aload_0
      41: iconst_m1
      42: putfield      #11                 // Field rpcTimeout:I
      45: aload_0
      46: iconst_m1
      47: putfield      #12                 // Field operationTimeout:I
      50: aload_0
      51: new           #13                 // class org/apache/hadoop/hbase/client/BufferedMutatorParams$1
      54: dup
      55: aload_0
      56: invokespecial #14                 // Method org/apache/hadoop/hbase/client/BufferedMutatorParams$1."<init>":(Lorg/apache/hadoop/hbase/client/BufferedMutatorParams;)V
      59: putfield      #15                 // Field listener:Lorg/apache/hadoop/hbase/client/BufferedMutator$ExceptionListener;
      62: aload_0
      63: aload_1
      64: putfield      #16                 // Field tableName:Lorg/apache/hadoop/hbase/TableName;
      67: return

  public org.apache.hadoop.hbase.TableName getTableName();
    Code:
       0: aload_0
       1: getfield      #16                 // Field tableName:Lorg/apache/hadoop/hbase/TableName;
       4: areturn

  public long getWriteBufferSize();
    Code:
       0: aload_0
       1: getfield      #5                  // Field writeBufferSize:J
       4: lreturn

  public org.apache.hadoop.hbase.client.BufferedMutatorParams rpcTimeout(int);
    Code:
       0: aload_0
       1: iload_1
       2: putfield      #11                 // Field rpcTimeout:I
       5: aload_0
       6: areturn

  public int getRpcTimeout();
    Code:
       0: aload_0
       1: getfield      #11                 // Field rpcTimeout:I
       4: ireturn

  public org.apache.hadoop.hbase.client.BufferedMutatorParams opertationTimeout(int);
    Code:
       0: aload_0
       1: iload_1
       2: putfield      #12                 // Field operationTimeout:I
       5: aload_0
       6: areturn

  public int getOperationTimeout();
    Code:
       0: aload_0
       1: getfield      #12                 // Field operationTimeout:I
       4: ireturn

  public org.apache.hadoop.hbase.client.BufferedMutatorParams writeBufferSize(long);
    Code:
       0: aload_0
       1: lload_1
       2: putfield      #5                  // Field writeBufferSize:J
       5: aload_0
       6: areturn

  public long getWriteBufferPeriodicFlushTimeoutMs();
    Code:
       0: aload_0
       1: getfield      #6                  // Field writeBufferPeriodicFlushTimeoutMs:J
       4: lreturn

  public org.apache.hadoop.hbase.client.BufferedMutatorParams setWriteBufferPeriodicFlushTimeoutMs(long);
    Code:
       0: aload_0
       1: lload_1
       2: putfield      #6                  // Field writeBufferPeriodicFlushTimeoutMs:J
       5: aload_0
       6: areturn

  public long getWriteBufferPeriodicFlushTimerTickMs();
    Code:
       0: aload_0
       1: getfield      #7                  // Field writeBufferPeriodicFlushTimerTickMs:J
       4: lreturn

  public org.apache.hadoop.hbase.client.BufferedMutatorParams setWriteBufferPeriodicFlushTimerTickMs(long);
    Code:
       0: aload_0
       1: lload_1
       2: putfield      #7                  // Field writeBufferPeriodicFlushTimerTickMs:J
       5: aload_0
       6: areturn

  public int getMaxKeyValueSize();
    Code:
       0: aload_0
       1: getfield      #8                  // Field maxKeyValueSize:I
       4: ireturn

  public org.apache.hadoop.hbase.client.BufferedMutatorParams maxKeyValueSize(int);
    Code:
       0: aload_0
       1: iload_1
       2: putfield      #8                  // Field maxKeyValueSize:I
       5: aload_0
       6: areturn

  public java.util.concurrent.ExecutorService getPool();
    Code:
       0: aload_0
       1: getfield      #9                  // Field pool:Ljava/util/concurrent/ExecutorService;
       4: areturn

  public org.apache.hadoop.hbase.client.BufferedMutatorParams pool(java.util.concurrent.ExecutorService);
    Code:
       0: aload_0
       1: aload_1
       2: putfield      #9                  // Field pool:Ljava/util/concurrent/ExecutorService;
       5: aload_0
       6: areturn

  public java.lang.String getImplementationClassName();
    Code:
       0: aload_0
       1: getfield      #10                 // Field implementationClassName:Ljava/lang/String;
       4: areturn

  public org.apache.hadoop.hbase.client.BufferedMutatorParams implementationClassName(java.lang.String);
    Code:
       0: aload_0
       1: aload_1
       2: putfield      #10                 // Field implementationClassName:Ljava/lang/String;
       5: aload_0
       6: areturn

  public org.apache.hadoop.hbase.client.BufferedMutator$ExceptionListener getListener();
    Code:
       0: aload_0
       1: getfield      #15                 // Field listener:Lorg/apache/hadoop/hbase/client/BufferedMutator$ExceptionListener;
       4: areturn

  public org.apache.hadoop.hbase.client.BufferedMutatorParams listener(org.apache.hadoop.hbase.client.BufferedMutator$ExceptionListener);
    Code:
       0: aload_0
       1: aload_1
       2: putfield      #15                 // Field listener:Lorg/apache/hadoop/hbase/client/BufferedMutator$ExceptionListener;
       5: aload_0
       6: areturn

  public org.apache.hadoop.hbase.client.BufferedMutatorParams clone();
    Code:
       0: new           #2                  // class org/apache/hadoop/hbase/client/BufferedMutatorParams
       3: dup
       4: aload_0
       5: getfield      #16                 // Field tableName:Lorg/apache/hadoop/hbase/TableName;
       8: invokespecial #17                 // Method "<init>":(Lorg/apache/hadoop/hbase/TableName;)V
      11: astore_1
      12: aload_1
      13: aload_0
      14: getfield      #5                  // Field writeBufferSize:J
      17: putfield      #5                  // Field writeBufferSize:J
      20: aload_1
      21: aload_0
      22: getfield      #6                  // Field writeBufferPeriodicFlushTimeoutMs:J
      25: putfield      #6                  // Field writeBufferPeriodicFlushTimeoutMs:J
      28: aload_1
      29: aload_0
      30: getfield      #7                  // Field writeBufferPeriodicFlushTimerTickMs:J
      33: putfield      #7                  // Field writeBufferPeriodicFlushTimerTickMs:J
      36: aload_1
      37: aload_0
      38: getfield      #8                  // Field maxKeyValueSize:I
      41: putfield      #8                  // Field maxKeyValueSize:I
      44: aload_1
      45: aload_0
      46: getfield      #9                  // Field pool:Ljava/util/concurrent/ExecutorService;
      49: putfield      #9                  // Field pool:Ljava/util/concurrent/ExecutorService;
      52: aload_1
      53: aload_0
      54: getfield      #15                 // Field listener:Lorg/apache/hadoop/hbase/client/BufferedMutator$ExceptionListener;
      57: putfield      #15                 // Field listener:Lorg/apache/hadoop/hbase/client/BufferedMutator$ExceptionListener;
      60: aload_1
      61: aload_0
      62: getfield      #10                 // Field implementationClassName:Ljava/lang/String;
      65: putfield      #10                 // Field implementationClassName:Ljava/lang/String;
      68: aload_1
      69: areturn

  public java.lang.Object clone() throws java.lang.CloneNotSupportedException;
    Code:
       0: aload_0
       1: invokevirtual #18                 // Method clone:()Lorg/apache/hadoop/hbase/client/BufferedMutatorParams;
       4: areturn
}
