Compiled from "BufferedMutatorImpl.java"
class org.apache.hadoop.hbase.client.BufferedMutatorImpl$2 extends java.util.TimerTask {
  final org.apache.hadoop.hbase.client.BufferedMutatorImpl this$0;

  org.apache.hadoop.hbase.client.BufferedMutatorImpl$2(org.apache.hadoop.hbase.client.BufferedMutatorImpl);
    Code:
       0: aload_0
       1: aload_1
       2: putfield      #1                  // Field this$0:Lorg/apache/hadoop/hbase/client/BufferedMutatorImpl;
       5: aload_0
       6: invokespecial #2                  // Method java/util/TimerTask."<init>":()V
       9: return

  public void run();
    Code:
       0: aload_0
       1: getfield      #1                  // Field this$0:Lorg/apache/hadoop/hbase/client/BufferedMutatorImpl;
       4: invokestatic  #3                  // Method org/apache/hadoop/hbase/client/BufferedMutatorImpl.access$200:(Lorg/apache/hadoop/hbase/client/BufferedMutatorImpl;)V
       7: return
}
