Compiled from "BufferedMutatorImpl.java"
class org.apache.hadoop.hbase.client.BufferedMutatorImpl$QueueRowAccess$1 implements java.util.Iterator<org.apache.hadoop.hbase.client.Row> {
  final org.apache.hadoop.hbase.client.BufferedMutatorImpl$QueueRowAccess this$1;

  org.apache.hadoop.hbase.client.BufferedMutatorImpl$QueueRowAccess$1(org.apache.hadoop.hbase.client.BufferedMutatorImpl$QueueRowAccess);
    Code:
       0: aload_0
       1: aload_1
       2: putfield      #1                  // Field this$1:Lorg/apache/hadoop/hbase/client/BufferedMutatorImpl$QueueRowAccess;
       5: aload_0
       6: invokespecial #2                  // Method java/lang/Object."<init>":()V
       9: aload_0
      10: aload_0
      11: getfield      #1                  // Field this$1:Lorg/apache/hadoop/hbase/client/BufferedMutatorImpl$QueueRowAccess;
      14: invokestatic  #3                  // Method org/apache/hadoop/hbase/client/BufferedMutatorImpl$QueueRowAccess.access$600:(Lorg/apache/hadoop/hbase/client/BufferedMutatorImpl$QueueRowAccess;)I
      17: putfield      #4                  // Field countDown:I
      20: return

  public boolean hasNext();
    Code:
       0: aload_0
       1: getfield      #4                  // Field countDown:I
       4: ifle          11
       7: iconst_1
       8: goto          12
      11: iconst_0
      12: ireturn

  public org.apache.hadoop.hbase.client.Row next();
    Code:
       0: aload_0
       1: getfield      #1                  // Field this$1:Lorg/apache/hadoop/hbase/client/BufferedMutatorImpl$QueueRowAccess;
       4: invokestatic  #5                  // Method org/apache/hadoop/hbase/client/BufferedMutatorImpl$QueueRowAccess.access$700:(Lorg/apache/hadoop/hbase/client/BufferedMutatorImpl$QueueRowAccess;)V
       7: aload_0
       8: invokevirtual #6                  // Method hasNext:()Z
      11: ifne          22
      14: new           #7                  // class java/util/NoSuchElementException
      17: dup
      18: invokespecial #8                  // Method java/util/NoSuchElementException."<init>":()V
      21: athrow
      22: aload_0
      23: getfield      #1                  // Field this$1:Lorg/apache/hadoop/hbase/client/BufferedMutatorImpl$QueueRowAccess;
      26: aload_0
      27: getfield      #1                  // Field this$1:Lorg/apache/hadoop/hbase/client/BufferedMutatorImpl$QueueRowAccess;
      30: getfield      #9                  // Field org/apache/hadoop/hbase/client/BufferedMutatorImpl$QueueRowAccess.this$0:Lorg/apache/hadoop/hbase/client/BufferedMutatorImpl;
      33: invokestatic  #10                 // Method org/apache/hadoop/hbase/client/BufferedMutatorImpl.access$400:(Lorg/apache/hadoop/hbase/client/BufferedMutatorImpl;)Ljava/util/concurrent/ConcurrentLinkedQueue;
      36: invokevirtual #11                 // Method java/util/concurrent/ConcurrentLinkedQueue.poll:()Ljava/lang/Object;
      39: checkcast     #12                 // class org/apache/hadoop/hbase/client/Mutation
      42: invokestatic  #13                 // Method org/apache/hadoop/hbase/client/BufferedMutatorImpl$QueueRowAccess.access$802:(Lorg/apache/hadoop/hbase/client/BufferedMutatorImpl$QueueRowAccess;Lorg/apache/hadoop/hbase/client/Mutation;)Lorg/apache/hadoop/hbase/client/Mutation;
      45: pop
      46: aload_0
      47: getfield      #1                  // Field this$1:Lorg/apache/hadoop/hbase/client/BufferedMutatorImpl$QueueRowAccess;
      50: invokestatic  #14                 // Method org/apache/hadoop/hbase/client/BufferedMutatorImpl$QueueRowAccess.access$800:(Lorg/apache/hadoop/hbase/client/BufferedMutatorImpl$QueueRowAccess;)Lorg/apache/hadoop/hbase/client/Mutation;
      53: ifnonnull     64
      56: new           #7                  // class java/util/NoSuchElementException
      59: dup
      60: invokespecial #8                  // Method java/util/NoSuchElementException."<init>":()V
      63: athrow
      64: aload_0
      65: getfield      #1                  // Field this$1:Lorg/apache/hadoop/hbase/client/BufferedMutatorImpl$QueueRowAccess;
      68: getfield      #9                  // Field org/apache/hadoop/hbase/client/BufferedMutatorImpl$QueueRowAccess.this$0:Lorg/apache/hadoop/hbase/client/BufferedMutatorImpl;
      71: invokestatic  #15                 // Method org/apache/hadoop/hbase/client/BufferedMutatorImpl.access$500:(Lorg/apache/hadoop/hbase/client/BufferedMutatorImpl;)Ljava/util/concurrent/atomic/AtomicLong;
      74: aload_0
      75: getfield      #1                  // Field this$1:Lorg/apache/hadoop/hbase/client/BufferedMutatorImpl$QueueRowAccess;
      78: invokestatic  #14                 // Method org/apache/hadoop/hbase/client/BufferedMutatorImpl$QueueRowAccess.access$800:(Lorg/apache/hadoop/hbase/client/BufferedMutatorImpl$QueueRowAccess;)Lorg/apache/hadoop/hbase/client/Mutation;
      81: invokevirtual #16                 // Method org/apache/hadoop/hbase/client/Mutation.heapSize:()J
      84: lneg
      85: invokevirtual #17                 // Method java/util/concurrent/atomic/AtomicLong.addAndGet:(J)J
      88: pop2
      89: aload_0
      90: dup
      91: getfield      #4                  // Field countDown:I
      94: iconst_1
      95: isub
      96: putfield      #4                  // Field countDown:I
      99: aload_0
     100: getfield      #1                  // Field this$1:Lorg/apache/hadoop/hbase/client/BufferedMutatorImpl$QueueRowAccess;
     103: invokestatic  #14                 // Method org/apache/hadoop/hbase/client/BufferedMutatorImpl$QueueRowAccess.access$800:(Lorg/apache/hadoop/hbase/client/BufferedMutatorImpl$QueueRowAccess;)Lorg/apache/hadoop/hbase/client/Mutation;
     106: areturn

  public void remove();
    Code:
       0: aload_0
       1: getfield      #1                  // Field this$1:Lorg/apache/hadoop/hbase/client/BufferedMutatorImpl$QueueRowAccess;
       4: invokestatic  #14                 // Method org/apache/hadoop/hbase/client/BufferedMutatorImpl$QueueRowAccess.access$800:(Lorg/apache/hadoop/hbase/client/BufferedMutatorImpl$QueueRowAccess;)Lorg/apache/hadoop/hbase/client/Mutation;
       7: ifnonnull     18
      10: new           #18                 // class java/lang/IllegalStateException
      13: dup
      14: invokespecial #19                 // Method java/lang/IllegalStateException."<init>":()V
      17: athrow
      18: aload_0
      19: getfield      #1                  // Field this$1:Lorg/apache/hadoop/hbase/client/BufferedMutatorImpl$QueueRowAccess;
      22: invokestatic  #20                 // Method org/apache/hadoop/hbase/client/BufferedMutatorImpl$QueueRowAccess.access$606:(Lorg/apache/hadoop/hbase/client/BufferedMutatorImpl$QueueRowAccess;)I
      25: pop
      26: aload_0
      27: getfield      #1                  // Field this$1:Lorg/apache/hadoop/hbase/client/BufferedMutatorImpl$QueueRowAccess;
      30: aconst_null
      31: invokestatic  #13                 // Method org/apache/hadoop/hbase/client/BufferedMutatorImpl$QueueRowAccess.access$802:(Lorg/apache/hadoop/hbase/client/BufferedMutatorImpl$QueueRowAccess;Lorg/apache/hadoop/hbase/client/Mutation;)Lorg/apache/hadoop/hbase/client/Mutation;
      34: pop
      35: return

  public java.lang.Object next();
    Code:
       0: aload_0
       1: invokevirtual #21                 // Method next:()Lorg/apache/hadoop/hbase/client/Row;
       4: areturn
}
