Compiled from "BufferCallBeforeInitHandler.java"
class org.apache.hadoop.hbase.ipc.BufferCallBeforeInitHandler extends org.apache.hbase.thirdparty.io.netty.channel.ChannelDuplexHandler {
  org.apache.hadoop.hbase.ipc.BufferCallBeforeInitHandler();
    Code:
       0: aload_0
       1: invokespecial #2                  // Method org/apache/hbase/thirdparty/io/netty/channel/ChannelDuplexHandler."<init>":()V
       4: aload_0
       5: new           #3                  // class java/util/HashMap
       8: dup
       9: invokespecial #4                  // Method java/util/HashMap."<init>":()V
      12: putfield      #5                  // Field id2Call:Ljava/util/Map;
      15: return

  public void write(org.apache.hbase.thirdparty.io.netty.channel.ChannelHandlerContext, java.lang.Object, org.apache.hbase.thirdparty.io.netty.channel.ChannelPromise);
    Code:
       0: aload_2
       1: instanceof    #6                  // class org/apache/hadoop/hbase/ipc/Call
       4: ifeq          43
       7: aload_2
       8: checkcast     #6                  // class org/apache/hadoop/hbase/ipc/Call
      11: astore        4
      13: aload_0
      14: getfield      #5                  // Field id2Call:Ljava/util/Map;
      17: aload         4
      19: getfield      #7                  // Field org/apache/hadoop/hbase/ipc/Call.id:I
      22: invokestatic  #8                  // Method java/lang/Integer.valueOf:(I)Ljava/lang/Integer;
      25: aload         4
      27: invokeinterface #9,  3            // InterfaceMethod java/util/Map.put:(Ljava/lang/Object;Ljava/lang/Object;)Ljava/lang/Object;
      32: pop
      33: aload_3
      34: invokeinterface #10,  1           // InterfaceMethod org/apache/hbase/thirdparty/io/netty/channel/ChannelPromise.trySuccess:()Z
      39: pop
      40: goto          52
      43: aload_1
      44: aload_2
      45: aload_3
      46: invokeinterface #11,  3           // InterfaceMethod org/apache/hbase/thirdparty/io/netty/channel/ChannelHandlerContext.write:(Ljava/lang/Object;Lorg/apache/hbase/thirdparty/io/netty/channel/ChannelPromise;)Lorg/apache/hbase/thirdparty/io/netty/channel/ChannelFuture;
      51: pop
      52: return

  public void userEventTriggered(org.apache.hbase.thirdparty.io.netty.channel.ChannelHandlerContext, java.lang.Object) throws java.lang.Exception;
    Code:
       0: aload_2
       1: instanceof    #12                 // class org/apache/hadoop/hbase/ipc/BufferCallBeforeInitHandler$BufferCallEvent
       4: ifeq          174
       7: aload_2
       8: checkcast     #12                 // class org/apache/hadoop/hbase/ipc/BufferCallBeforeInitHandler$BufferCallEvent
      11: astore_3
      12: getstatic     #13                 // Field org/apache/hadoop/hbase/ipc/BufferCallBeforeInitHandler$1.$SwitchMap$org$apache$hadoop$hbase$ipc$BufferCallBeforeInitHandler$BufferCallAction:[I
      15: aload_3
      16: getfield      #14                 // Field org/apache/hadoop/hbase/ipc/BufferCallBeforeInitHandler$BufferCallEvent.action:Lorg/apache/hadoop/hbase/ipc/BufferCallBeforeInitHandler$BufferCallAction;
      19: invokevirtual #15                 // Method org/apache/hadoop/hbase/ipc/BufferCallBeforeInitHandler$BufferCallAction.ordinal:()I
      22: iaload
      23: lookupswitch  { // 2
                     1: 48
                     2: 101
               default: 151
          }
      48: aload_0
      49: getfield      #5                  // Field id2Call:Ljava/util/Map;
      52: invokeinterface #16,  1           // InterfaceMethod java/util/Map.values:()Ljava/util/Collection;
      57: invokeinterface #17,  1           // InterfaceMethod java/util/Collection.iterator:()Ljava/util/Iterator;
      62: astore        4
      64: aload         4
      66: invokeinterface #18,  1           // InterfaceMethod java/util/Iterator.hasNext:()Z
      71: ifeq          98
      74: aload         4
      76: invokeinterface #19,  1           // InterfaceMethod java/util/Iterator.next:()Ljava/lang/Object;
      81: checkcast     #6                  // class org/apache/hadoop/hbase/ipc/Call
      84: astore        5
      86: aload_1
      87: aload         5
      89: invokeinterface #20,  2           // InterfaceMethod org/apache/hbase/thirdparty/io/netty/channel/ChannelHandlerContext.write:(Ljava/lang/Object;)Lorg/apache/hbase/thirdparty/io/netty/channel/ChannelFuture;
      94: pop
      95: goto          64
      98: goto          151
     101: aload_0
     102: getfield      #5                  // Field id2Call:Ljava/util/Map;
     105: invokeinterface #16,  1           // InterfaceMethod java/util/Map.values:()Ljava/util/Collection;
     110: invokeinterface #17,  1           // InterfaceMethod java/util/Collection.iterator:()Ljava/util/Iterator;
     115: astore        4
     117: aload         4
     119: invokeinterface #18,  1           // InterfaceMethod java/util/Iterator.hasNext:()Z
     124: ifeq          151
     127: aload         4
     129: invokeinterface #19,  1           // InterfaceMethod java/util/Iterator.next:()Ljava/lang/Object;
     134: checkcast     #6                  // class org/apache/hadoop/hbase/ipc/Call
     137: astore        5
     139: aload         5
     141: aload_3
     142: getfield      #21                 // Field org/apache/hadoop/hbase/ipc/BufferCallBeforeInitHandler$BufferCallEvent.error:Ljava/io/IOException;
     145: invokevirtual #22                 // Method org/apache/hadoop/hbase/ipc/Call.setException:(Ljava/io/IOException;)V
     148: goto          117
     151: aload_1
     152: invokeinterface #23,  1           // InterfaceMethod org/apache/hbase/thirdparty/io/netty/channel/ChannelHandlerContext.flush:()Lorg/apache/hbase/thirdparty/io/netty/channel/ChannelHandlerContext;
     157: pop
     158: aload_1
     159: invokeinterface #24,  1           // InterfaceMethod org/apache/hbase/thirdparty/io/netty/channel/ChannelHandlerContext.pipeline:()Lorg/apache/hbase/thirdparty/io/netty/channel/ChannelPipeline;
     164: aload_0
     165: invokeinterface #25,  2           // InterfaceMethod org/apache/hbase/thirdparty/io/netty/channel/ChannelPipeline.remove:(Lorg/apache/hbase/thirdparty/io/netty/channel/ChannelHandler;)Lorg/apache/hbase/thirdparty/io/netty/channel/ChannelPipeline;
     170: pop
     171: goto          215
     174: aload_2
     175: instanceof    #26                 // class org/apache/hadoop/hbase/ipc/CallEvent
     178: ifeq          207
     181: aload_0
     182: getfield      #5                  // Field id2Call:Ljava/util/Map;
     185: aload_2
     186: checkcast     #26                 // class org/apache/hadoop/hbase/ipc/CallEvent
     189: getfield      #27                 // Field org/apache/hadoop/hbase/ipc/CallEvent.call:Lorg/apache/hadoop/hbase/ipc/Call;
     192: getfield      #7                  // Field org/apache/hadoop/hbase/ipc/Call.id:I
     195: invokestatic  #8                  // Method java/lang/Integer.valueOf:(I)Ljava/lang/Integer;
     198: invokeinterface #28,  2           // InterfaceMethod java/util/Map.remove:(Ljava/lang/Object;)Ljava/lang/Object;
     203: pop
     204: goto          215
     207: aload_1
     208: aload_2
     209: invokeinterface #29,  2           // InterfaceMethod org/apache/hbase/thirdparty/io/netty/channel/ChannelHandlerContext.fireUserEventTriggered:(Ljava/lang/Object;)Lorg/apache/hbase/thirdparty/io/netty/channel/ChannelHandlerContext;
     214: pop
     215: return

  static org.apache.hadoop.hbase.ipc.BufferCallBeforeInitHandler$BufferCallEvent access$000();
    Code:
       0: getstatic     #1                  // Field SUCCESS_EVENT:Lorg/apache/hadoop/hbase/ipc/BufferCallBeforeInitHandler$BufferCallEvent;
       3: areturn

  static {};
    Code:
       0: new           #12                 // class org/apache/hadoop/hbase/ipc/BufferCallBeforeInitHandler$BufferCallEvent
       3: dup
       4: getstatic     #30                 // Field org/apache/hadoop/hbase/ipc/BufferCallBeforeInitHandler$BufferCallAction.FLUSH:Lorg/apache/hadoop/hbase/ipc/BufferCallBeforeInitHandler$BufferCallAction;
       7: aconst_null
       8: aconst_null
       9: invokespecial #31                 // Method org/apache/hadoop/hbase/ipc/BufferCallBeforeInitHandler$BufferCallEvent."<init>":(Lorg/apache/hadoop/hbase/ipc/BufferCallBeforeInitHandler$BufferCallAction;Ljava/io/IOException;Lorg/apache/hadoop/hbase/ipc/BufferCallBeforeInitHandler$1;)V
      12: putstatic     #1                  // Field SUCCESS_EVENT:Lorg/apache/hadoop/hbase/ipc/BufferCallBeforeInitHandler$BufferCallEvent;
      15: return
}
