Compiled from "BufferedDataBlockEncoder.java"
abstract class org.apache.hadoop.hbase.io.encoding.BufferedDataBlockEncoder extends org.apache.hadoop.hbase.io.encoding.AbstractDataBlockEncoder {
  org.apache.hadoop.hbase.io.encoding.BufferedDataBlockEncoder();
    Code:
       0: aload_0
       1: invokespecial #2                  // Method org/apache/hadoop/hbase/io/encoding/AbstractDataBlockEncoder."<init>":()V
       4: return

  public java.nio.ByteBuffer decodeKeyValues(java.io.DataInputStream, org.apache.hadoop.hbase.io.encoding.HFileBlockDecodingContext) throws java.io.IOException;
    Code:
       0: aload_2
       1: invokevirtual #3                  // Method java/lang/Object.getClass:()Ljava/lang/Class;
       4: ldc           #4                  // class org/apache/hadoop/hbase/io/encoding/HFileBlockDefaultDecodingContext
       6: if_acmpeq     55
       9: new           #5                  // class java/io/IOException
      12: dup
      13: new           #6                  // class java/lang/StringBuilder
      16: dup
      17: invokespecial #7                  // Method java/lang/StringBuilder."<init>":()V
      20: aload_0
      21: invokevirtual #3                  // Method java/lang/Object.getClass:()Ljava/lang/Class;
      24: invokevirtual #8                  // Method java/lang/Class.getName:()Ljava/lang/String;
      27: invokevirtual #9                  // Method java/lang/StringBuilder.append:(Ljava/lang/String;)Ljava/lang/StringBuilder;
      30: ldc           #10                 // String  only accepts
      32: invokevirtual #9                  // Method java/lang/StringBuilder.append:(Ljava/lang/String;)Ljava/lang/StringBuilder;
      35: ldc           #4                  // class org/apache/hadoop/hbase/io/encoding/HFileBlockDefaultDecodingContext
      37: invokevirtual #8                  // Method java/lang/Class.getName:()Ljava/lang/String;
      40: invokevirtual #9                  // Method java/lang/StringBuilder.append:(Ljava/lang/String;)Ljava/lang/StringBuilder;
      43: ldc           #11                 // String  as the decoding context.
      45: invokevirtual #9                  // Method java/lang/StringBuilder.append:(Ljava/lang/String;)Ljava/lang/StringBuilder;
      48: invokevirtual #12                 // Method java/lang/StringBuilder.toString:()Ljava/lang/String;
      51: invokespecial #13                 // Method java/io/IOException."<init>":(Ljava/lang/String;)V
      54: athrow
      55: aload_2
      56: checkcast     #4                  // class org/apache/hadoop/hbase/io/encoding/HFileBlockDefaultDecodingContext
      59: astore_3
      60: aload_3
      61: invokevirtual #14                 // Method org/apache/hadoop/hbase/io/encoding/HFileBlockDefaultDecodingContext.getHFileContext:()Lorg/apache/hadoop/hbase/io/hfile/HFileContext;
      64: invokevirtual #15                 // Method org/apache/hadoop/hbase/io/hfile/HFileContext.isIncludesTags:()Z
      67: ifeq          133
      70: aload_3
      71: invokevirtual #14                 // Method org/apache/hadoop/hbase/io/encoding/HFileBlockDefaultDecodingContext.getHFileContext:()Lorg/apache/hadoop/hbase/io/hfile/HFileContext;
      74: invokevirtual #16                 // Method org/apache/hadoop/hbase/io/hfile/HFileContext.isCompressTags:()Z
      77: ifeq          133
      80: aload_3
      81: invokevirtual #17                 // Method org/apache/hadoop/hbase/io/encoding/HFileBlockDefaultDecodingContext.getTagCompressionContext:()Lorg/apache/hadoop/hbase/io/TagCompressionContext;
      84: ifnull        97
      87: aload_3
      88: invokevirtual #17                 // Method org/apache/hadoop/hbase/io/encoding/HFileBlockDefaultDecodingContext.getTagCompressionContext:()Lorg/apache/hadoop/hbase/io/TagCompressionContext;
      91: invokevirtual #18                 // Method org/apache/hadoop/hbase/io/TagCompressionContext.clear:()V
      94: goto          133
      97: new           #19                 // class org/apache/hadoop/hbase/io/TagCompressionContext
     100: dup
     101: ldc           #20                 // class org/apache/hadoop/hbase/io/util/LRUDictionary
     103: bipush        127
     105: invokespecial #22                 // Method org/apache/hadoop/hbase/io/TagCompressionContext."<init>":(Ljava/lang/Class;I)V
     108: astore        4
     110: aload_3
     111: aload         4
     113: invokevirtual #23                 // Method org/apache/hadoop/hbase/io/encoding/HFileBlockDefaultDecodingContext.setTagCompressionContext:(Lorg/apache/hadoop/hbase/io/TagCompressionContext;)V
     116: goto          133
     119: astore        4
     121: new           #5                  // class java/io/IOException
     124: dup
     125: ldc           #25                 // String Failed to initialize TagCompressionContext
     127: aload         4
     129: invokespecial #26                 // Method java/io/IOException."<init>":(Ljava/lang/String;Ljava/lang/Throwable;)V
     132: athrow
     133: aload_0
     134: aload_1
     135: iconst_0
     136: iconst_0
     137: aload_3
     138: invokevirtual #27                 // Method internalDecodeKeyValues:(Ljava/io/DataInputStream;IILorg/apache/hadoop/hbase/io/encoding/HFileBlockDefaultDecodingContext;)Ljava/nio/ByteBuffer;
     141: areturn
    Exception table:
       from    to  target type
          97   116   119   Class java/lang/Exception

  public static int compareCommonRowPrefix(org.apache.hadoop.hbase.Cell, org.apache.hadoop.hbase.Cell, int);
    Code:
       0: aload_0
       1: invokeinterface #28,  1           // InterfaceMethod org/apache/hadoop/hbase/Cell.getRowArray:()[B
       6: aload_0
       7: invokeinterface #29,  1           // InterfaceMethod org/apache/hadoop/hbase/Cell.getRowOffset:()I
      12: iload_2
      13: iadd
      14: aload_0
      15: invokeinterface #30,  1           // InterfaceMethod org/apache/hadoop/hbase/Cell.getRowLength:()S
      20: iload_2
      21: isub
      22: aload_1
      23: invokeinterface #28,  1           // InterfaceMethod org/apache/hadoop/hbase/Cell.getRowArray:()[B
      28: aload_1
      29: invokeinterface #29,  1           // InterfaceMethod org/apache/hadoop/hbase/Cell.getRowOffset:()I
      34: iload_2
      35: iadd
      36: aload_1
      37: invokeinterface #30,  1           // InterfaceMethod org/apache/hadoop/hbase/Cell.getRowLength:()S
      42: iload_2
      43: isub
      44: invokestatic  #31                 // Method org/apache/hadoop/hbase/util/Bytes.compareTo:([BII[BII)I
      47: ireturn

  public static int compareCommonFamilyPrefix(org.apache.hadoop.hbase.Cell, org.apache.hadoop.hbase.Cell, int);
    Code:
       0: aload_0
       1: invokeinterface #32,  1           // InterfaceMethod org/apache/hadoop/hbase/Cell.getFamilyArray:()[B
       6: aload_0
       7: invokeinterface #33,  1           // InterfaceMethod org/apache/hadoop/hbase/Cell.getFamilyOffset:()I
      12: iload_2
      13: iadd
      14: aload_0
      15: invokeinterface #34,  1           // InterfaceMethod org/apache/hadoop/hbase/Cell.getFamilyLength:()B
      20: iload_2
      21: isub
      22: aload_1
      23: invokeinterface #32,  1           // InterfaceMethod org/apache/hadoop/hbase/Cell.getFamilyArray:()[B
      28: aload_1
      29: invokeinterface #33,  1           // InterfaceMethod org/apache/hadoop/hbase/Cell.getFamilyOffset:()I
      34: iload_2
      35: iadd
      36: aload_1
      37: invokeinterface #34,  1           // InterfaceMethod org/apache/hadoop/hbase/Cell.getFamilyLength:()B
      42: iload_2
      43: isub
      44: invokestatic  #31                 // Method org/apache/hadoop/hbase/util/Bytes.compareTo:([BII[BII)I
      47: ireturn

  public static int compareCommonQualifierPrefix(org.apache.hadoop.hbase.Cell, org.apache.hadoop.hbase.Cell, int);
    Code:
       0: aload_0
       1: invokeinterface #35,  1           // InterfaceMethod org/apache/hadoop/hbase/Cell.getQualifierArray:()[B
       6: aload_0
       7: invokeinterface #36,  1           // InterfaceMethod org/apache/hadoop/hbase/Cell.getQualifierOffset:()I
      12: iload_2
      13: iadd
      14: aload_0
      15: invokeinterface #37,  1           // InterfaceMethod org/apache/hadoop/hbase/Cell.getQualifierLength:()I
      20: iload_2
      21: isub
      22: aload_1
      23: invokeinterface #35,  1           // InterfaceMethod org/apache/hadoop/hbase/Cell.getQualifierArray:()[B
      28: aload_1
      29: invokeinterface #36,  1           // InterfaceMethod org/apache/hadoop/hbase/Cell.getQualifierOffset:()I
      34: iload_2
      35: iadd
      36: aload_1
      37: invokeinterface #37,  1           // InterfaceMethod org/apache/hadoop/hbase/Cell.getQualifierLength:()I
      42: iload_2
      43: isub
      44: invokestatic  #31                 // Method org/apache/hadoop/hbase/util/Bytes.compareTo:([BII[BII)I
      47: ireturn

  protected final int afterEncodingKeyValue(org.apache.hadoop.hbase.Cell, java.io.DataOutputStream, org.apache.hadoop.hbase.io.encoding.HFileBlockDefaultEncodingContext) throws java.io.IOException;
    Code:
       0: iconst_0
       1: istore        4
       3: aload_3
       4: invokevirtual #38                 // Method org/apache/hadoop/hbase/io/encoding/HFileBlockDefaultEncodingContext.getHFileContext:()Lorg/apache/hadoop/hbase/io/hfile/HFileContext;
       7: invokevirtual #15                 // Method org/apache/hadoop/hbase/io/hfile/HFileContext.isIncludesTags:()Z
      10: ifeq          70
      13: aload_1
      14: invokeinterface #39,  1           // InterfaceMethod org/apache/hadoop/hbase/Cell.getTagsLength:()I
      19: istore        5
      21: aload_2
      22: iload         5
      24: invokestatic  #40                 // Method org/apache/hadoop/hbase/util/ByteBufferUtils.putCompressedInt:(Ljava/io/OutputStream;I)I
      27: pop
      28: iload         5
      30: ifle          61
      33: aload_3
      34: invokevirtual #41                 // Method org/apache/hadoop/hbase/io/encoding/HFileBlockDefaultEncodingContext.getTagCompressionContext:()Lorg/apache/hadoop/hbase/io/TagCompressionContext;
      37: astore        6
      39: aload         6
      41: ifnull        54
      44: aload_2
      45: aload_1
      46: aload         6
      48: invokestatic  #42                 // Method org/apache/hadoop/hbase/PrivateCellUtil.compressTags:(Ljava/io/OutputStream;Lorg/apache/hadoop/hbase/Cell;Lorg/apache/hadoop/hbase/io/TagCompressionContext;)V
      51: goto          61
      54: aload_2
      55: aload_1
      56: iload         5
      58: invokestatic  #43                 // Method org/apache/hadoop/hbase/PrivateCellUtil.writeTags:(Ljava/io/OutputStream;Lorg/apache/hadoop/hbase/Cell;I)V
      61: iload         4
      63: iload         5
      65: iconst_2
      66: iadd
      67: iadd
      68: istore        4
      70: aload_3
      71: invokevirtual #38                 // Method org/apache/hadoop/hbase/io/encoding/HFileBlockDefaultEncodingContext.getHFileContext:()Lorg/apache/hadoop/hbase/io/hfile/HFileContext;
      74: invokevirtual #45                 // Method org/apache/hadoop/hbase/io/hfile/HFileContext.isIncludesMvcc:()Z
      77: ifeq          104
      80: aload_1
      81: invokeinterface #46,  1           // InterfaceMethod org/apache/hadoop/hbase/Cell.getSequenceId:()J
      86: lstore        5
      88: aload_2
      89: lload         5
      91: invokestatic  #47                 // Method org/apache/hadoop/io/WritableUtils.writeVLong:(Ljava/io/DataOutput;J)V
      94: iload         4
      96: lload         5
      98: invokestatic  #48                 // Method org/apache/hadoop/io/WritableUtils.getVIntSize:(J)I
     101: iadd
     102: istore        4
     104: iload         4
     106: ireturn

  protected final void afterDecodingKeyValue(java.io.DataInputStream, java.nio.ByteBuffer, org.apache.hadoop.hbase.io.encoding.HFileBlockDefaultDecodingContext) throws java.io.IOException;
    Code:
       0: aload_3
       1: invokevirtual #14                 // Method org/apache/hadoop/hbase/io/encoding/HFileBlockDefaultDecodingContext.getHFileContext:()Lorg/apache/hadoop/hbase/io/hfile/HFileContext;
       4: invokevirtual #15                 // Method org/apache/hadoop/hbase/io/hfile/HFileContext.isIncludesTags:()Z
       7: ifeq          78
      10: aload_1
      11: invokestatic  #49                 // Method org/apache/hadoop/hbase/util/ByteBufferUtils.readCompressedInt:(Ljava/io/InputStream;)I
      14: istore        4
      16: aload_2
      17: iload         4
      19: bipush        8
      21: ishr
      22: sipush        255
      25: iand
      26: i2b
      27: invokevirtual #50                 // Method java/nio/ByteBuffer.put:(B)Ljava/nio/ByteBuffer;
      30: pop
      31: aload_2
      32: iload         4
      34: sipush        255
      37: iand
      38: i2b
      39: invokevirtual #50                 // Method java/nio/ByteBuffer.put:(B)Ljava/nio/ByteBuffer;
      42: pop
      43: iload         4
      45: ifle          78
      48: aload_3
      49: invokevirtual #17                 // Method org/apache/hadoop/hbase/io/encoding/HFileBlockDefaultDecodingContext.getTagCompressionContext:()Lorg/apache/hadoop/hbase/io/TagCompressionContext;
      52: astore        5
      54: aload         5
      56: ifnull        71
      59: aload         5
      61: aload_1
      62: aload_2
      63: iload         4
      65: invokevirtual #51                 // Method org/apache/hadoop/hbase/io/TagCompressionContext.uncompressTags:(Ljava/io/InputStream;Ljava/nio/ByteBuffer;I)V
      68: goto          78
      71: aload_2
      72: aload_1
      73: iload         4
      75: invokestatic  #52                 // Method org/apache/hadoop/hbase/util/ByteBufferUtils.copyFromStreamToBuffer:(Ljava/nio/ByteBuffer;Ljava/io/DataInputStream;I)V
      78: aload_3
      79: invokevirtual #14                 // Method org/apache/hadoop/hbase/io/encoding/HFileBlockDefaultDecodingContext.getHFileContext:()Lorg/apache/hadoop/hbase/io/hfile/HFileContext;
      82: invokevirtual #45                 // Method org/apache/hadoop/hbase/io/hfile/HFileContext.isIncludesMvcc:()Z
      85: ifeq          143
      88: ldc2_w        #53                 // long -1l
      91: lstore        4
      93: aload_1
      94: invokestatic  #55                 // Method org/apache/hadoop/io/WritableUtils.readVLong:(Ljava/io/DataInput;)J
      97: lstore        4
      99: aload_2
     100: lload         4
     102: invokestatic  #56                 // Method org/apache/hadoop/hbase/util/ByteBufferUtils.writeVLong:(Ljava/nio/ByteBuffer;J)V
     105: goto          143
     108: astore        6
     110: new           #57                 // class java/lang/RuntimeException
     113: dup
     114: new           #6                  // class java/lang/StringBuilder
     117: dup
     118: invokespecial #7                  // Method java/lang/StringBuilder."<init>":()V
     121: ldc           #58                 // String Unable to copy memstore timestamp
     123: invokevirtual #9                  // Method java/lang/StringBuilder.append:(Ljava/lang/String;)Ljava/lang/StringBuilder;
     126: lload         4
     128: invokevirtual #59                 // Method java/lang/StringBuilder.append:(J)Ljava/lang/StringBuilder;
     131: ldc           #60                 // String  after decoding a key/value
     133: invokevirtual #9                  // Method java/lang/StringBuilder.append:(Ljava/lang/String;)Ljava/lang/StringBuilder;
     136: invokevirtual #12                 // Method java/lang/StringBuilder.toString:()Ljava/lang/String;
     139: invokespecial #61                 // Method java/lang/RuntimeException."<init>":(Ljava/lang/String;)V
     142: athrow
     143: return
    Exception table:
       from    to  target type
          93   105   108   Class java/io/IOException

  protected abstract java.nio.ByteBuffer internalDecodeKeyValues(java.io.DataInputStream, int, int, org.apache.hadoop.hbase.io.encoding.HFileBlockDefaultDecodingContext) throws java.io.IOException;

  protected static void ensureSpace(java.nio.ByteBuffer, int) throws org.apache.hadoop.hbase.io.encoding.EncoderBufferTooSmallException;
    Code:
       0: aload_0
       1: invokevirtual #62                 // Method java/nio/ByteBuffer.position:()I
       4: iload_1
       5: iadd
       6: aload_0
       7: invokevirtual #63                 // Method java/nio/ByteBuffer.limit:()I
      10: if_icmple     64
      13: new           #64                 // class org/apache/hadoop/hbase/io/encoding/EncoderBufferTooSmallException
      16: dup
      17: new           #6                  // class java/lang/StringBuilder
      20: dup
      21: invokespecial #7                  // Method java/lang/StringBuilder."<init>":()V
      24: ldc           #65                 // String Buffer position=
      26: invokevirtual #9                  // Method java/lang/StringBuilder.append:(Ljava/lang/String;)Ljava/lang/StringBuilder;
      29: aload_0
      30: invokevirtual #62                 // Method java/nio/ByteBuffer.position:()I
      33: invokevirtual #66                 // Method java/lang/StringBuilder.append:(I)Ljava/lang/StringBuilder;
      36: ldc           #67                 // String , buffer limit=
      38: invokevirtual #9                  // Method java/lang/StringBuilder.append:(Ljava/lang/String;)Ljava/lang/StringBuilder;
      41: aload_0
      42: invokevirtual #63                 // Method java/nio/ByteBuffer.limit:()I
      45: invokevirtual #66                 // Method java/lang/StringBuilder.append:(I)Ljava/lang/StringBuilder;
      48: ldc           #68                 // String , length to be written=
      50: invokevirtual #9                  // Method java/lang/StringBuilder.append:(Ljava/lang/String;)Ljava/lang/StringBuilder;
      53: iload_1
      54: invokevirtual #66                 // Method java/lang/StringBuilder.append:(I)Ljava/lang/StringBuilder;
      57: invokevirtual #12                 // Method java/lang/StringBuilder.toString:()Ljava/lang/String;
      60: invokespecial #69                 // Method org/apache/hadoop/hbase/io/encoding/EncoderBufferTooSmallException."<init>":(Ljava/lang/String;)V
      63: athrow
      64: return

  public void startBlockEncoding(org.apache.hadoop.hbase.io.encoding.HFileBlockEncodingContext, java.io.DataOutputStream) throws java.io.IOException;
    Code:
       0: aload_1
       1: invokevirtual #3                  // Method java/lang/Object.getClass:()Ljava/lang/Class;
       4: ldc           #70                 // class org/apache/hadoop/hbase/io/encoding/HFileBlockDefaultEncodingContext
       6: if_acmpeq     55
       9: new           #5                  // class java/io/IOException
      12: dup
      13: new           #6                  // class java/lang/StringBuilder
      16: dup
      17: invokespecial #7                  // Method java/lang/StringBuilder."<init>":()V
      20: aload_0
      21: invokevirtual #3                  // Method java/lang/Object.getClass:()Ljava/lang/Class;
      24: invokevirtual #8                  // Method java/lang/Class.getName:()Ljava/lang/String;
      27: invokevirtual #9                  // Method java/lang/StringBuilder.append:(Ljava/lang/String;)Ljava/lang/StringBuilder;
      30: ldc           #10                 // String  only accepts
      32: invokevirtual #9                  // Method java/lang/StringBuilder.append:(Ljava/lang/String;)Ljava/lang/StringBuilder;
      35: ldc           #70                 // class org/apache/hadoop/hbase/io/encoding/HFileBlockDefaultEncodingContext
      37: invokevirtual #8                  // Method java/lang/Class.getName:()Ljava/lang/String;
      40: invokevirtual #9                  // Method java/lang/StringBuilder.append:(Ljava/lang/String;)Ljava/lang/StringBuilder;
      43: ldc           #71                 // String  as the encoding context.
      45: invokevirtual #9                  // Method java/lang/StringBuilder.append:(Ljava/lang/String;)Ljava/lang/StringBuilder;
      48: invokevirtual #12                 // Method java/lang/StringBuilder.toString:()Ljava/lang/String;
      51: invokespecial #13                 // Method java/io/IOException."<init>":(Ljava/lang/String;)V
      54: athrow
      55: aload_1
      56: checkcast     #70                 // class org/apache/hadoop/hbase/io/encoding/HFileBlockDefaultEncodingContext
      59: astore_3
      60: aload_3
      61: aload_2
      62: invokevirtual #72                 // Method org/apache/hadoop/hbase/io/encoding/HFileBlockDefaultEncodingContext.prepareEncoding:(Ljava/io/DataOutputStream;)V
      65: aload_3
      66: invokevirtual #38                 // Method org/apache/hadoop/hbase/io/encoding/HFileBlockDefaultEncodingContext.getHFileContext:()Lorg/apache/hadoop/hbase/io/hfile/HFileContext;
      69: invokevirtual #15                 // Method org/apache/hadoop/hbase/io/hfile/HFileContext.isIncludesTags:()Z
      72: ifeq          138
      75: aload_3
      76: invokevirtual #38                 // Method org/apache/hadoop/hbase/io/encoding/HFileBlockDefaultEncodingContext.getHFileContext:()Lorg/apache/hadoop/hbase/io/hfile/HFileContext;
      79: invokevirtual #16                 // Method org/apache/hadoop/hbase/io/hfile/HFileContext.isCompressTags:()Z
      82: ifeq          138
      85: aload_3
      86: invokevirtual #41                 // Method org/apache/hadoop/hbase/io/encoding/HFileBlockDefaultEncodingContext.getTagCompressionContext:()Lorg/apache/hadoop/hbase/io/TagCompressionContext;
      89: ifnull        102
      92: aload_3
      93: invokevirtual #41                 // Method org/apache/hadoop/hbase/io/encoding/HFileBlockDefaultEncodingContext.getTagCompressionContext:()Lorg/apache/hadoop/hbase/io/TagCompressionContext;
      96: invokevirtual #18                 // Method org/apache/hadoop/hbase/io/TagCompressionContext.clear:()V
      99: goto          138
     102: new           #19                 // class org/apache/hadoop/hbase/io/TagCompressionContext
     105: dup
     106: ldc           #20                 // class org/apache/hadoop/hbase/io/util/LRUDictionary
     108: bipush        127
     110: invokespecial #22                 // Method org/apache/hadoop/hbase/io/TagCompressionContext."<init>":(Ljava/lang/Class;I)V
     113: astore        4
     115: aload_3
     116: aload         4
     118: invokevirtual #73                 // Method org/apache/hadoop/hbase/io/encoding/HFileBlockDefaultEncodingContext.setTagCompressionContext:(Lorg/apache/hadoop/hbase/io/TagCompressionContext;)V
     121: goto          138
     124: astore        4
     126: new           #5                  // class java/io/IOException
     129: dup
     130: ldc           #25                 // String Failed to initialize TagCompressionContext
     132: aload         4
     134: invokespecial #26                 // Method java/io/IOException."<init>":(Ljava/lang/String;Ljava/lang/Throwable;)V
     137: athrow
     138: aload_2
     139: iconst_0
     140: invokestatic  #74                 // Method org/apache/hadoop/hbase/io/util/StreamUtils.writeInt:(Ljava/io/OutputStream;I)V
     143: aload_1
     144: new           #75                 // class org/apache/hadoop/hbase/io/encoding/BufferedDataBlockEncoder$BufferedDataBlockEncodingState
     147: dup
     148: aconst_null
     149: invokespecial #76                 // Method org/apache/hadoop/hbase/io/encoding/BufferedDataBlockEncoder$BufferedDataBlockEncodingState."<init>":(Lorg/apache/hadoop/hbase/io/encoding/BufferedDataBlockEncoder$1;)V
     152: invokeinterface #77,  2           // InterfaceMethod org/apache/hadoop/hbase/io/encoding/HFileBlockEncodingContext.setEncodingState:(Lorg/apache/hadoop/hbase/io/encoding/EncodingState;)V
     157: return
    Exception table:
       from    to  target type
         102   121   124   Class java/lang/Exception

  public int encode(org.apache.hadoop.hbase.Cell, org.apache.hadoop.hbase.io.encoding.HFileBlockEncodingContext, java.io.DataOutputStream) throws java.io.IOException;
    Code:
       0: aload_2
       1: invokeinterface #78,  1           // InterfaceMethod org/apache/hadoop/hbase/io/encoding/HFileBlockEncodingContext.getEncodingState:()Lorg/apache/hadoop/hbase/io/encoding/EncodingState;
       6: checkcast     #75                 // class org/apache/hadoop/hbase/io/encoding/BufferedDataBlockEncoder$BufferedDataBlockEncodingState
       9: astore        4
      11: aload_0
      12: aload_1
      13: aload_2
      14: checkcast     #70                 // class org/apache/hadoop/hbase/io/encoding/HFileBlockDefaultEncodingContext
      17: aload_3
      18: invokevirtual #79                 // Method internalEncode:(Lorg/apache/hadoop/hbase/Cell;Lorg/apache/hadoop/hbase/io/encoding/HFileBlockDefaultEncodingContext;Ljava/io/DataOutputStream;)I
      21: istore        5
      23: aload         4
      25: dup
      26: getfield      #80                 // Field org/apache/hadoop/hbase/io/encoding/BufferedDataBlockEncoder$BufferedDataBlockEncodingState.unencodedDataSizeWritten:I
      29: iload         5
      31: iadd
      32: putfield      #80                 // Field org/apache/hadoop/hbase/io/encoding/BufferedDataBlockEncoder$BufferedDataBlockEncodingState.unencodedDataSizeWritten:I
      35: iload         5
      37: ireturn

  public abstract int internalEncode(org.apache.hadoop.hbase.Cell, org.apache.hadoop.hbase.io.encoding.HFileBlockDefaultEncodingContext, java.io.DataOutputStream) throws java.io.IOException;

  public void endBlockEncoding(org.apache.hadoop.hbase.io.encoding.HFileBlockEncodingContext, java.io.DataOutputStream, byte[]) throws java.io.IOException;
    Code:
       0: aload_1
       1: invokeinterface #78,  1           // InterfaceMethod org/apache/hadoop/hbase/io/encoding/HFileBlockEncodingContext.getEncodingState:()Lorg/apache/hadoop/hbase/io/encoding/EncodingState;
       6: checkcast     #75                 // class org/apache/hadoop/hbase/io/encoding/BufferedDataBlockEncoder$BufferedDataBlockEncodingState
       9: astore        4
      11: aload_3
      12: bipush        35
      14: aload         4
      16: getfield      #80                 // Field org/apache/hadoop/hbase/io/encoding/BufferedDataBlockEncoder$BufferedDataBlockEncodingState.unencodedDataSizeWritten:I
      19: invokestatic  #83                 // Method org/apache/hadoop/hbase/util/Bytes.putInt:([BII)I
      22: pop
      23: aload_0
      24: aload_1
      25: invokevirtual #84                 // Method postEncoding:(Lorg/apache/hadoop/hbase/io/encoding/HFileBlockEncodingContext;)V
      28: return

  static int access$000();
    Code:
       0: getstatic     #1                  // Field INITIAL_KEY_BUFFER_SIZE:I
       3: ireturn

  static {};
    Code:
       0: sipush        512
       3: putstatic     #1                  // Field INITIAL_KEY_BUFFER_SIZE:I
       6: return
}
