Compiled from "BufferCallBeforeInitHandler.java"
public final class org.apache.hadoop.hbase.ipc.BufferCallBeforeInitHandler$BufferCallEvent {
  public final org.apache.hadoop.hbase.ipc.BufferCallBeforeInitHandler$BufferCallAction action;

  public final java.io.IOException error;

  public static org.apache.hadoop.hbase.ipc.BufferCallBeforeInitHandler$BufferCallEvent success();
    Code:
       0: invokestatic  #5                  // Method org/apache/hadoop/hbase/ipc/BufferCallBeforeInitHandler.access$000:()Lorg/apache/hadoop/hbase/ipc/BufferCallBeforeInitHandler$BufferCallEvent;
       3: areturn

  public static org.apache.hadoop.hbase.ipc.BufferCallBeforeInitHandler$BufferCallEvent fail(java.io.IOException);
    Code:
       0: new           #6                  // class org/apache/hadoop/hbase/ipc/BufferCallBeforeInitHandler$BufferCallEvent
       3: dup
       4: getstatic     #7                  // Field org/apache/hadoop/hbase/ipc/BufferCallBeforeInitHandler$BufferCallAction.FAIL:Lorg/apache/hadoop/hbase/ipc/BufferCallBeforeInitHandler$BufferCallAction;
       7: aload_0
       8: invokespecial #1                  // Method "<init>":(Lorg/apache/hadoop/hbase/ipc/BufferCallBeforeInitHandler$BufferCallAction;Ljava/io/IOException;)V
      11: areturn

  org.apache.hadoop.hbase.ipc.BufferCallBeforeInitHandler$BufferCallEvent(org.apache.hadoop.hbase.ipc.BufferCallBeforeInitHandler$BufferCallAction, java.io.IOException, org.apache.hadoop.hbase.ipc.BufferCallBeforeInitHandler$1);
    Code:
       0: aload_0
       1: aload_1
       2: aload_2
       3: invokespecial #1                  // Method "<init>":(Lorg/apache/hadoop/hbase/ipc/BufferCallBeforeInitHandler$BufferCallAction;Ljava/io/IOException;)V
       6: return
}
