Compiled from "BulkLoadHFiles.java"
public class org.apache.hadoop.hbase.tool.BulkLoadHFiles$LoadQueueItem {
  public org.apache.hadoop.hbase.tool.BulkLoadHFiles$LoadQueueItem(byte[], org.apache.hadoop.fs.Path);
    Code:
       0: aload_0
       1: invokespecial #1                  // Method java/lang/Object."<init>":()V
       4: aload_0
       5: aload_1
       6: putfield      #2                  // Field family:[B
       9: aload_0
      10: aload_2
      11: putfield      #3                  // Field hfilePath:Lorg/apache/hadoop/fs/Path;
      14: return

  public java.lang.String toString();
    Code:
       0: new           #4                  // class java/lang/StringBuilder
       3: dup
       4: invokespecial #5                  // Method java/lang/StringBuilder."<init>":()V
       7: ldc           #6                  // String family:
       9: invokevirtual #7                  // Method java/lang/StringBuilder.append:(Ljava/lang/String;)Ljava/lang/StringBuilder;
      12: aload_0
      13: getfield      #2                  // Field family:[B
      16: invokestatic  #8                  // Method org/apache/hadoop/hbase/util/Bytes.toString:([B)Ljava/lang/String;
      19: invokevirtual #7                  // Method java/lang/StringBuilder.append:(Ljava/lang/String;)Ljava/lang/StringBuilder;
      22: ldc           #9                  // String  path:
      24: invokevirtual #7                  // Method java/lang/StringBuilder.append:(Ljava/lang/String;)Ljava/lang/StringBuilder;
      27: aload_0
      28: getfield      #3                  // Field hfilePath:Lorg/apache/hadoop/fs/Path;
      31: invokevirtual #10                 // Method org/apache/hadoop/fs/Path.toString:()Ljava/lang/String;
      34: invokevirtual #7                  // Method java/lang/StringBuilder.append:(Ljava/lang/String;)Ljava/lang/StringBuilder;
      37: invokevirtual #11                 // Method java/lang/StringBuilder.toString:()Ljava/lang/String;
      40: areturn

  public byte[] getFamily();
    Code:
       0: aload_0
       1: getfield      #2                  // Field family:[B
       4: areturn

  public org.apache.hadoop.fs.Path getFilePath();
    Code:
       0: aload_0
       1: getfield      #3                  // Field hfilePath:Lorg/apache/hadoop/fs/Path;
       4: areturn
}
