Compiled from "ByteBufferUtils.java"
final class org.apache.hadoop.hbase.util.ByteBufferUtils$ConverterHolder$UnsafeConverter extends org.apache.hadoop.hbase.util.ByteBufferUtils$Converter {
  public org.apache.hadoop.hbase.util.ByteBufferUtils$ConverterHolder$UnsafeConverter();
    Code:
       0: aload_0
       1: invokespecial #1                  // Method org/apache/hadoop/hbase/util/ByteBufferUtils$Converter."<init>":()V
       4: return

  short toShort(java.nio.ByteBuffer, int);
    Code:
       0: aload_1
       1: iload_2
       2: invokestatic  #2                  // Method org/apache/hadoop/hbase/util/UnsafeAccess.toShort:(Ljava/nio/ByteBuffer;I)S
       5: ireturn

  int toInt(java.nio.ByteBuffer);
    Code:
       0: aload_1
       1: aload_1
       2: invokevirtual #3                  // Method java/nio/ByteBuffer.position:()I
       5: invokestatic  #4                  // Method org/apache/hadoop/hbase/util/UnsafeAccess.toInt:(Ljava/nio/ByteBuffer;I)I
       8: istore_2
       9: aload_1
      10: aload_1
      11: invokevirtual #3                  // Method java/nio/ByteBuffer.position:()I
      14: iconst_4
      15: iadd
      16: invokevirtual #6                  // Method java/nio/ByteBuffer.position:(I)Ljava/nio/Buffer;
      19: pop
      20: iload_2
      21: ireturn

  int toInt(java.nio.ByteBuffer, int);
    Code:
       0: aload_1
       1: iload_2
       2: invokestatic  #4                  // Method org/apache/hadoop/hbase/util/UnsafeAccess.toInt:(Ljava/nio/ByteBuffer;I)I
       5: ireturn

  long toLong(java.nio.ByteBuffer, int);
    Code:
       0: aload_1
       1: iload_2
       2: invokestatic  #7                  // Method org/apache/hadoop/hbase/util/UnsafeAccess.toLong:(Ljava/nio/ByteBuffer;I)J
       5: lreturn

  void putInt(java.nio.ByteBuffer, int);
    Code:
       0: aload_1
       1: aload_1
       2: invokevirtual #3                  // Method java/nio/ByteBuffer.position:()I
       5: iload_2
       6: invokestatic  #8                  // Method org/apache/hadoop/hbase/util/UnsafeAccess.putInt:(Ljava/nio/ByteBuffer;II)I
       9: istore_3
      10: aload_1
      11: iload_3
      12: invokevirtual #6                  // Method java/nio/ByteBuffer.position:(I)Ljava/nio/Buffer;
      15: pop
      16: return

  int putInt(java.nio.ByteBuffer, int, int);
    Code:
       0: aload_1
       1: iload_2
       2: iload_3
       3: invokestatic  #8                  // Method org/apache/hadoop/hbase/util/UnsafeAccess.putInt:(Ljava/nio/ByteBuffer;II)I
       6: ireturn

  void putShort(java.nio.ByteBuffer, short);
    Code:
       0: aload_1
       1: aload_1
       2: invokevirtual #3                  // Method java/nio/ByteBuffer.position:()I
       5: iload_2
       6: invokestatic  #9                  // Method org/apache/hadoop/hbase/util/UnsafeAccess.putShort:(Ljava/nio/ByteBuffer;IS)I
       9: istore_3
      10: aload_1
      11: iload_3
      12: invokevirtual #6                  // Method java/nio/ByteBuffer.position:(I)Ljava/nio/Buffer;
      15: pop
      16: return

  int putShort(java.nio.ByteBuffer, int, short);
    Code:
       0: aload_1
       1: iload_2
       2: iload_3
       3: invokestatic  #9                  // Method org/apache/hadoop/hbase/util/UnsafeAccess.putShort:(Ljava/nio/ByteBuffer;IS)I
       6: ireturn

  void putLong(java.nio.ByteBuffer, long);
    Code:
       0: aload_1
       1: aload_1
       2: invokevirtual #3                  // Method java/nio/ByteBuffer.position:()I
       5: lload_2
       6: invokestatic  #10                 // Method org/apache/hadoop/hbase/util/UnsafeAccess.putLong:(Ljava/nio/ByteBuffer;IJ)I
       9: istore        4
      11: aload_1
      12: iload         4
      14: invokevirtual #6                  // Method java/nio/ByteBuffer.position:(I)Ljava/nio/Buffer;
      17: pop
      18: return

  int putLong(java.nio.ByteBuffer, int, long);
    Code:
       0: aload_1
       1: iload_2
       2: lload_3
       3: invokestatic  #10                 // Method org/apache/hadoop/hbase/util/UnsafeAccess.putLong:(Ljava/nio/ByteBuffer;IJ)I
       6: ireturn

  static {};
    Code:
       0: getstatic     #11                 // Field org/apache/hadoop/hbase/util/ByteBufferUtils.UNSAFE_UNALIGNED:Z
       3: ifne          14
       6: new           #12                 // class java/lang/Error
       9: dup
      10: invokespecial #13                 // Method java/lang/Error."<init>":()V
      13: athrow
      14: return
}
