Compiled from "ByteBufferArray.java"
final class org.apache.hadoop.hbase.util.ByteBufferArray$1 implements org.apache.hadoop.hbase.util.ByteBufferArray$Visitor {
  org.apache.hadoop.hbase.util.ByteBufferArray$1();
    Code:
       0: aload_0
       1: invokespecial #1                  // Method java/lang/Object."<init>":()V
       4: return

  public void visit(java.nio.ByteBuffer, int, byte[], int, int);
    Code:
       0: aload_3
       1: aload_1
       2: iload_2
       3: iload         4
       5: iload         5
       7: invokestatic  #2                  // Method org/apache/hadoop/hbase/util/ByteBufferUtils.copyFromBufferToArray:([BLjava/nio/ByteBuffer;III)V
      10: return
}
