Compiled from "ByteArrayOutputStream.java"
public class org.apache.hadoop.hbase.io.ByteArrayOutputStream extends java.io.OutputStream implements org.apache.hadoop.hbase.io.ByteBufferWriter {
  public org.apache.hadoop.hbase.io.ByteArrayOutputStream();
    Code:
       0: aload_0
       1: bipush        32
       3: invokespecial #2                  // Method "<init>":(I)V
       6: return

  public org.apache.hadoop.hbase.io.ByteArrayOutputStream(int);
    Code:
       0: aload_0
       1: invokespecial #3                  // Method java/io/OutputStream."<init>":()V
       4: aload_0
       5: iconst_0
       6: putfield      #4                  // Field pos:I
       9: aload_0
      10: iload_1
      11: newarray       byte
      13: putfield      #5                  // Field buf:[B
      16: return

  public void write(java.nio.ByteBuffer, int, int);
    Code:
       0: aload_0
       1: iload_3
       2: invokespecial #6                  // Method checkSizeAndGrow:(I)V
       5: aload_0
       6: getfield      #5                  // Field buf:[B
       9: aload_1
      10: iload_2
      11: aload_0
      12: getfield      #4                  // Field pos:I
      15: iload_3
      16: invokestatic  #7                  // Method org/apache/hadoop/hbase/util/ByteBufferUtils.copyFromBufferToArray:([BLjava/nio/ByteBuffer;III)V
      19: aload_0
      20: dup
      21: getfield      #4                  // Field pos:I
      24: iload_3
      25: iadd
      26: putfield      #4                  // Field pos:I
      29: return

  public void writeInt(int);
    Code:
       0: aload_0
       1: iconst_4
       2: invokespecial #6                  // Method checkSizeAndGrow:(I)V
       5: aload_0
       6: getfield      #5                  // Field buf:[B
       9: aload_0
      10: getfield      #4                  // Field pos:I
      13: iload_1
      14: invokestatic  #9                  // Method org/apache/hadoop/hbase/util/Bytes.putInt:([BII)I
      17: pop
      18: aload_0
      19: dup
      20: getfield      #4                  // Field pos:I
      23: iconst_4
      24: iadd
      25: putfield      #4                  // Field pos:I
      28: return

  public void write(int);
    Code:
       0: aload_0
       1: iconst_1
       2: invokespecial #6                  // Method checkSizeAndGrow:(I)V
       5: aload_0
       6: getfield      #5                  // Field buf:[B
       9: aload_0
      10: getfield      #4                  // Field pos:I
      13: iload_1
      14: i2b
      15: bastore
      16: aload_0
      17: dup
      18: getfield      #4                  // Field pos:I
      21: iconst_1
      22: iadd
      23: putfield      #4                  // Field pos:I
      26: return

  public void write(byte[], int, int);
    Code:
       0: aload_0
       1: iload_3
       2: invokespecial #6                  // Method checkSizeAndGrow:(I)V
       5: aload_1
       6: iload_2
       7: aload_0
       8: getfield      #5                  // Field buf:[B
      11: aload_0
      12: getfield      #4                  // Field pos:I
      15: iload_3
      16: invokestatic  #10                 // Method java/lang/System.arraycopy:(Ljava/lang/Object;ILjava/lang/Object;II)V
      19: aload_0
      20: dup
      21: getfield      #4                  // Field pos:I
      24: iload_3
      25: iadd
      26: putfield      #4                  // Field pos:I
      29: return

  public void reset();
    Code:
       0: aload_0
       1: iconst_0
       2: putfield      #4                  // Field pos:I
       5: return

  public byte[] toByteArray();
    Code:
       0: aload_0
       1: getfield      #5                  // Field buf:[B
       4: aload_0
       5: getfield      #4                  // Field pos:I
       8: invokestatic  #19                 // Method java/util/Arrays.copyOf:([BI)[B
      11: areturn

  public byte[] getBuffer();
    Code:
       0: aload_0
       1: getfield      #5                  // Field buf:[B
       4: areturn

  public int size();
    Code:
       0: aload_0
       1: getfield      #4                  // Field pos:I
       4: ireturn
}
