Compiled from "ByteBufferArray.java"
public class org.apache.hadoop.hbase.util.ByteBufferArray {
  public static final int DEFAULT_BUFFER_SIZE;

  java.nio.ByteBuffer[] buffers;

  int bufferCount;

  static final boolean $assertionsDisabled;

  public org.apache.hadoop.hbase.util.ByteBufferArray(long, org.apache.hadoop.hbase.util.ByteBufferAllocator) throws java.io.IOException;
    Code:
       0: aload_0
       1: invokespecial #1                  // Method java/lang/Object."<init>":()V
       4: aload_0
       5: ldc           #3                  // int 4194304
       7: putfield      #4                  // Field bufferSize:I
      10: aload_0
      11: getfield      #4                  // Field bufferSize:I
      14: i2l
      15: lload_1
      16: ldc2_w        #5                  // long 16l
      19: ldiv
      20: lcmp
      21: ifle          41
      24: aload_0
      25: aload_0
      26: lload_1
      27: ldc2_w        #5                  // long 16l
      30: ldiv
      31: ldc2_w        #7                  // long 32768l
      34: invokespecial #9                  // Method roundUp:(JJ)J
      37: l2i
      38: putfield      #4                  // Field bufferSize:I
      41: aload_0
      42: aload_0
      43: lload_1
      44: aload_0
      45: getfield      #4                  // Field bufferSize:I
      48: i2l
      49: invokespecial #9                  // Method roundUp:(JJ)J
      52: aload_0
      53: getfield      #4                  // Field bufferSize:I
      56: i2l
      57: ldiv
      58: l2i
      59: putfield      #10                 // Field bufferCount:I
      62: getstatic     #11                 // Field LOG:Lorg/slf4j/Logger;
      65: new           #12                 // class java/lang/StringBuilder
      68: dup
      69: invokespecial #13                 // Method java/lang/StringBuilder."<init>":()V
      72: ldc           #14                 // String Allocating buffers total=
      74: invokevirtual #15                 // Method java/lang/StringBuilder.append:(Ljava/lang/String;)Ljava/lang/StringBuilder;
      77: lload_1
      78: invokestatic  #16                 // Method org/apache/hadoop/util/StringUtils.byteDesc:(J)Ljava/lang/String;
      81: invokevirtual #15                 // Method java/lang/StringBuilder.append:(Ljava/lang/String;)Ljava/lang/StringBuilder;
      84: ldc           #17                 // String , sizePerBuffer=
      86: invokevirtual #15                 // Method java/lang/StringBuilder.append:(Ljava/lang/String;)Ljava/lang/StringBuilder;
      89: aload_0
      90: getfield      #4                  // Field bufferSize:I
      93: i2l
      94: invokestatic  #16                 // Method org/apache/hadoop/util/StringUtils.byteDesc:(J)Ljava/lang/String;
      97: invokevirtual #15                 // Method java/lang/StringBuilder.append:(Ljava/lang/String;)Ljava/lang/StringBuilder;
     100: ldc           #18                 // String , count=
     102: invokevirtual #15                 // Method java/lang/StringBuilder.append:(Ljava/lang/String;)Ljava/lang/StringBuilder;
     105: aload_0
     106: getfield      #10                 // Field bufferCount:I
     109: invokevirtual #19                 // Method java/lang/StringBuilder.append:(I)Ljava/lang/StringBuilder;
     112: invokevirtual #20                 // Method java/lang/StringBuilder.toString:()Ljava/lang/String;
     115: invokeinterface #21,  2           // InterfaceMethod org/slf4j/Logger.info:(Ljava/lang/String;)V
     120: aload_0
     121: aload_0
     122: getfield      #10                 // Field bufferCount:I
     125: iconst_1
     126: iadd
     127: anewarray     #22                 // class java/nio/ByteBuffer
     130: putfield      #23                 // Field buffers:[Ljava/nio/ByteBuffer;
     133: aload_0
     134: aload_3
     135: invokevirtual #24                 // Method createBuffers:(Lorg/apache/hadoop/hbase/util/ByteBufferAllocator;)V
     138: return

  void createBuffers(org.apache.hadoop.hbase.util.ByteBufferAllocator) throws java.io.IOException;
    Code:
       0: aload_0
       1: invokevirtual #25                 // Method getThreadCount:()I
       4: istore_2
       5: new           #26                 // class java/util/concurrent/ThreadPoolExecutor
       8: dup
       9: iload_2
      10: iload_2
      11: lconst_0
      12: getstatic     #27                 // Field java/util/concurrent/TimeUnit.MILLISECONDS:Ljava/util/concurrent/TimeUnit;
      15: new           #28                 // class java/util/concurrent/LinkedBlockingQueue
      18: dup
      19: invokespecial #29                 // Method java/util/concurrent/LinkedBlockingQueue."<init>":()V
      22: invokespecial #30                 // Method java/util/concurrent/ThreadPoolExecutor."<init>":(IIJLjava/util/concurrent/TimeUnit;Ljava/util/concurrent/BlockingQueue;)V
      25: astore_3
      26: aload_0
      27: getfield      #10                 // Field bufferCount:I
      30: i2d
      31: iload_2
      32: i2d
      33: ddiv
      34: invokestatic  #31                 // Method java/lang/Math.floor:(D)D
      37: d2i
      38: istore        4
      40: aload_0
      41: getfield      #10                 // Field bufferCount:I
      44: iload         4
      46: iload_2
      47: iconst_1
      48: isub
      49: imul
      50: isub
      51: istore        5
      53: iload_2
      54: anewarray     #32                 // class java/util/concurrent/Future
      57: astore        6
      59: iconst_0
      60: istore        7
      62: iload         7
      64: iload_2
      65: if_icmpge     116
      68: iload         7
      70: iload_2
      71: iconst_1
      72: isub
      73: if_icmpne     81
      76: iload         5
      78: goto          83
      81: iload         4
      83: istore        8
      85: aload         6
      87: iload         7
      89: aload_3
      90: new           #33                 // class org/apache/hadoop/hbase/util/ByteBufferArray$BufferCreatorCallable
      93: dup
      94: aload_0
      95: getfield      #4                  // Field bufferSize:I
      98: iload         8
     100: aload_1
     101: invokespecial #34                 // Method org/apache/hadoop/hbase/util/ByteBufferArray$BufferCreatorCallable."<init>":(IILorg/apache/hadoop/hbase/util/ByteBufferAllocator;)V
     104: invokeinterface #35,  2           // InterfaceMethod java/util/concurrent/ExecutorService.submit:(Ljava/util/concurrent/Callable;)Ljava/util/concurrent/Future;
     109: aastore
     110: iinc          7, 1
     113: goto          62
     116: iconst_0
     117: istore        7
     119: aload         6
     121: astore        8
     123: aload         8
     125: arraylength
     126: istore        9
     128: iconst_0
     129: istore        10
     131: iload         10
     133: iload         9
     135: if_icmpge     234
     138: aload         8
     140: iload         10
     142: aaload
     143: astore        11
     145: aload         11
     147: invokeinterface #36,  1           // InterfaceMethod java/util/concurrent/Future.get:()Ljava/lang/Object;
     152: checkcast     #37                 // class "[Ljava/nio/ByteBuffer;"
     155: astore        12
     157: aload         12
     159: astore        13
     161: aload         13
     163: arraylength
     164: istore        14
     166: iconst_0
     167: istore        15
     169: iload         15
     171: iload         14
     173: if_icmpge     201
     176: aload         13
     178: iload         15
     180: aaload
     181: astore        16
     183: aload_0
     184: getfield      #23                 // Field buffers:[Ljava/nio/ByteBuffer;
     187: iload         7
     189: iinc          7, 1
     192: aload         16
     194: aastore
     195: iinc          15, 1
     198: goto          169
     201: goto          228
     204: astore        12
     206: getstatic     #11                 // Field LOG:Lorg/slf4j/Logger;
     209: ldc           #40                 // String Buffer creation interrupted
     211: aload         12
     213: invokeinterface #41,  3           // InterfaceMethod org/slf4j/Logger.error:(Ljava/lang/String;Ljava/lang/Throwable;)V
     218: new           #42                 // class java/io/IOException
     221: dup
     222: aload         12
     224: invokespecial #43                 // Method java/io/IOException."<init>":(Ljava/lang/Throwable;)V
     227: athrow
     228: iinc          10, 1
     231: goto          131
     234: aload_3
     235: invokeinterface #44,  1           // InterfaceMethod java/util/concurrent/ExecutorService.shutdownNow:()Ljava/util/List;
     240: pop
     241: goto          256
     244: astore        17
     246: aload_3
     247: invokeinterface #44,  1           // InterfaceMethod java/util/concurrent/ExecutorService.shutdownNow:()Ljava/util/List;
     252: pop
     253: aload         17
     255: athrow
     256: aload_0
     257: getfield      #23                 // Field buffers:[Ljava/nio/ByteBuffer;
     260: aload_0
     261: getfield      #10                 // Field bufferCount:I
     264: iconst_0
     265: invokestatic  #45                 // Method java/nio/ByteBuffer.allocate:(I)Ljava/nio/ByteBuffer;
     268: aastore
     269: return
    Exception table:
       from    to  target type
         145   201   204   Class java/lang/InterruptedException
         145   201   204   Class java/util/concurrent/ExecutionException
          59   234   244   any
         244   246   244   any

  int getThreadCount();
    Code:
       0: invokestatic  #46                 // Method java/lang/Runtime.getRuntime:()Ljava/lang/Runtime;
       3: invokevirtual #47                 // Method java/lang/Runtime.availableProcessors:()I
       6: ireturn

  public int getMultiple(long, int, byte[]);
    Code:
       0: aload_0
       1: lload_1
       2: iload_3
       3: aload         4
       5: iconst_0
       6: invokevirtual #48                 // Method getMultiple:(JI[BI)I
       9: ireturn

  public int getMultiple(long, int, byte[], int);
    Code:
       0: aload_0
       1: lload_1
       2: iload_3
       3: aload         4
       5: iload         5
       7: getstatic     #49                 // Field GET_MULTIPLE_VISTOR:Lorg/apache/hadoop/hbase/util/ByteBufferArray$Visitor;
      10: invokevirtual #50                 // Method multiple:(JI[BILorg/apache/hadoop/hbase/util/ByteBufferArray$Visitor;)V
      13: iload_3
      14: ireturn

  public void putMultiple(long, int, byte[]);
    Code:
       0: aload_0
       1: lload_1
       2: iload_3
       3: aload         4
       5: iconst_0
       6: invokevirtual #51                 // Method putMultiple:(JI[BI)V
       9: return

  public void putMultiple(long, int, byte[], int);
    Code:
       0: aload_0
       1: lload_1
       2: iload_3
       3: aload         4
       5: iload         5
       7: getstatic     #52                 // Field PUT_MULTIPLE_VISITOR:Lorg/apache/hadoop/hbase/util/ByteBufferArray$Visitor;
      10: invokevirtual #50                 // Method multiple:(JI[BILorg/apache/hadoop/hbase/util/ByteBufferArray$Visitor;)V
      13: return

  void multiple(long, int, byte[], int, org.apache.hadoop.hbase.util.ByteBufferArray$Visitor);
    Code:
       0: getstatic     #53                 // Field $assertionsDisabled:Z
       3: ifne          18
       6: iload_3
       7: ifge          18
      10: new           #54                 // class java/lang/AssertionError
      13: dup
      14: invokespecial #55                 // Method java/lang/AssertionError."<init>":()V
      17: athrow
      18: lload_1
      19: iload_3
      20: i2l
      21: ladd
      22: lstore        7
      24: lload_1
      25: aload_0
      26: getfield      #4                  // Field bufferSize:I
      29: i2l
      30: ldiv
      31: l2i
      32: istore        9
      34: lload_1
      35: aload_0
      36: getfield      #4                  // Field bufferSize:I
      39: i2l
      40: lrem
      41: l2i
      42: istore        10
      44: lload         7
      46: aload_0
      47: getfield      #4                  // Field bufferSize:I
      50: i2l
      51: ldiv
      52: l2i
      53: istore        11
      55: lload         7
      57: aload_0
      58: getfield      #4                  // Field bufferSize:I
      61: i2l
      62: lrem
      63: l2i
      64: istore        12
      66: getstatic     #53                 // Field $assertionsDisabled:Z
      69: ifne          90
      72: aload         4
      74: arraylength
      75: iload_3
      76: iload         5
      78: iadd
      79: if_icmpge     90
      82: new           #54                 // class java/lang/AssertionError
      85: dup
      86: invokespecial #55                 // Method java/lang/AssertionError."<init>":()V
      89: athrow
      90: getstatic     #53                 // Field $assertionsDisabled:Z
      93: ifne          118
      96: iload         9
      98: iflt          110
     101: iload         9
     103: aload_0
     104: getfield      #10                 // Field bufferCount:I
     107: if_icmplt     118
     110: new           #54                 // class java/lang/AssertionError
     113: dup
     114: invokespecial #55                 // Method java/lang/AssertionError."<init>":()V
     117: athrow
     118: getstatic     #53                 // Field $assertionsDisabled:Z
     121: ifne          160
     124: iload         11
     126: iflt          138
     129: iload         11
     131: aload_0
     132: getfield      #10                 // Field bufferCount:I
     135: if_icmplt     160
     138: iload         11
     140: aload_0
     141: getfield      #10                 // Field bufferCount:I
     144: if_icmpne     152
     147: iload         12
     149: ifeq          160
     152: new           #54                 // class java/lang/AssertionError
     155: dup
     156: invokespecial #55                 // Method java/lang/AssertionError."<init>":()V
     159: athrow
     160: iload         9
     162: aload_0
     163: getfield      #23                 // Field buffers:[Ljava/nio/ByteBuffer;
     166: arraylength
     167: if_icmpge     175
     170: iload         9
     172: ifge          238
     175: new           #12                 // class java/lang/StringBuilder
     178: dup
     179: invokespecial #13                 // Method java/lang/StringBuilder."<init>":()V
     182: ldc           #56                 // String Failed multiple, start=
     184: invokevirtual #15                 // Method java/lang/StringBuilder.append:(Ljava/lang/String;)Ljava/lang/StringBuilder;
     187: lload_1
     188: invokevirtual #57                 // Method java/lang/StringBuilder.append:(J)Ljava/lang/StringBuilder;
     191: ldc           #58                 // String ,startBuffer=
     193: invokevirtual #15                 // Method java/lang/StringBuilder.append:(Ljava/lang/String;)Ljava/lang/StringBuilder;
     196: iload         9
     198: invokevirtual #19                 // Method java/lang/StringBuilder.append:(I)Ljava/lang/StringBuilder;
     201: ldc           #59                 // String ,bufferSize=
     203: invokevirtual #15                 // Method java/lang/StringBuilder.append:(Ljava/lang/String;)Ljava/lang/StringBuilder;
     206: aload_0
     207: getfield      #4                  // Field bufferSize:I
     210: invokevirtual #19                 // Method java/lang/StringBuilder.append:(I)Ljava/lang/StringBuilder;
     213: invokevirtual #20                 // Method java/lang/StringBuilder.toString:()Ljava/lang/String;
     216: astore        13
     218: getstatic     #11                 // Field LOG:Lorg/slf4j/Logger;
     221: aload         13
     223: invokeinterface #60,  2           // InterfaceMethod org/slf4j/Logger.error:(Ljava/lang/String;)V
     228: new           #61                 // class java/lang/RuntimeException
     231: dup
     232: aload         13
     234: invokespecial #62                 // Method java/lang/RuntimeException."<init>":(Ljava/lang/String;)V
     237: athrow
     238: iconst_0
     239: istore        13
     241: iconst_m1
     242: istore        14
     244: iload         9
     246: istore        15
     248: iload         15
     250: iload         11
     252: if_icmpgt     355
     255: aload_0
     256: getfield      #23                 // Field buffers:[Ljava/nio/ByteBuffer;
     259: iload         15
     261: aaload
     262: invokevirtual #63                 // Method java/nio/ByteBuffer.duplicate:()Ljava/nio/ByteBuffer;
     265: astore        16
     267: iconst_0
     268: istore        17
     270: iload         15
     272: iload         9
     274: if_icmpne     302
     277: aload_0
     278: getfield      #4                  // Field bufferSize:I
     281: iload         10
     283: isub
     284: istore        14
     286: iload         14
     288: iload_3
     289: if_icmple     295
     292: iload_3
     293: istore        14
     295: iload         10
     297: istore        17
     299: goto          322
     302: iload         15
     304: iload         11
     306: if_icmpne     316
     309: iload         12
     311: istore        14
     313: goto          322
     316: aload_0
     317: getfield      #4                  // Field bufferSize:I
     320: istore        14
     322: aload         6
     324: aload         16
     326: iload         17
     328: aload         4
     330: iload         13
     332: iload         5
     334: iadd
     335: iload         14
     337: invokeinterface #64,  6           // InterfaceMethod org/apache/hadoop/hbase/util/ByteBufferArray$Visitor.visit:(Ljava/nio/ByteBuffer;I[BII)V
     342: iload         13
     344: iload         14
     346: iadd
     347: istore        13
     349: iinc          15, 1
     352: goto          248
     355: getstatic     #53                 // Field $assertionsDisabled:Z
     358: ifne          375
     361: iload         13
     363: iload_3
     364: if_icmpeq     375
     367: new           #54                 // class java/lang/AssertionError
     370: dup
     371: invokespecial #55                 // Method java/lang/AssertionError."<init>":()V
     374: athrow
     375: return

  public org.apache.hadoop.hbase.nio.ByteBuff asSubByteBuff(long, int);
    Code:
       0: getstatic     #53                 // Field $assertionsDisabled:Z
       3: ifne          18
       6: iload_3
       7: ifge          18
      10: new           #54                 // class java/lang/AssertionError
      13: dup
      14: invokespecial #55                 // Method java/lang/AssertionError."<init>":()V
      17: athrow
      18: lload_1
      19: iload_3
      20: i2l
      21: ladd
      22: lstore        4
      24: lload_1
      25: aload_0
      26: getfield      #4                  // Field bufferSize:I
      29: i2l
      30: ldiv
      31: l2i
      32: istore        6
      34: lload_1
      35: aload_0
      36: getfield      #4                  // Field bufferSize:I
      39: i2l
      40: lrem
      41: l2i
      42: istore        7
      44: lload         4
      46: aload_0
      47: getfield      #4                  // Field bufferSize:I
      50: i2l
      51: ldiv
      52: l2i
      53: istore        8
      55: lload         4
      57: aload_0
      58: getfield      #4                  // Field bufferSize:I
      61: i2l
      62: lrem
      63: l2i
      64: istore        9
      66: iload         8
      68: aload_0
      69: getfield      #10                 // Field bufferCount:I
      72: if_icmpne     84
      75: iinc          8, -1
      78: aload_0
      79: getfield      #4                  // Field bufferSize:I
      82: istore        9
      84: getstatic     #53                 // Field $assertionsDisabled:Z
      87: ifne          112
      90: iload         6
      92: iflt          104
      95: iload         6
      97: aload_0
      98: getfield      #10                 // Field bufferCount:I
     101: if_icmplt     112
     104: new           #54                 // class java/lang/AssertionError
     107: dup
     108: invokespecial #55                 // Method java/lang/AssertionError."<init>":()V
     111: athrow
     112: getstatic     #53                 // Field $assertionsDisabled:Z
     115: ifne          154
     118: iload         8
     120: iflt          132
     123: iload         8
     125: aload_0
     126: getfield      #10                 // Field bufferCount:I
     129: if_icmplt     154
     132: iload         8
     134: aload_0
     135: getfield      #10                 // Field bufferCount:I
     138: if_icmpne     146
     141: iload         9
     143: ifeq          154
     146: new           #54                 // class java/lang/AssertionError
     149: dup
     150: invokespecial #55                 // Method java/lang/AssertionError."<init>":()V
     153: athrow
     154: iload         6
     156: aload_0
     157: getfield      #23                 // Field buffers:[Ljava/nio/ByteBuffer;
     160: arraylength
     161: if_icmpge     169
     164: iload         6
     166: ifge          232
     169: new           #12                 // class java/lang/StringBuilder
     172: dup
     173: invokespecial #13                 // Method java/lang/StringBuilder."<init>":()V
     176: ldc           #65                 // String Failed subArray, start=
     178: invokevirtual #15                 // Method java/lang/StringBuilder.append:(Ljava/lang/String;)Ljava/lang/StringBuilder;
     181: lload_1
     182: invokevirtual #57                 // Method java/lang/StringBuilder.append:(J)Ljava/lang/StringBuilder;
     185: ldc           #58                 // String ,startBuffer=
     187: invokevirtual #15                 // Method java/lang/StringBuilder.append:(Ljava/lang/String;)Ljava/lang/StringBuilder;
     190: iload         6
     192: invokevirtual #19                 // Method java/lang/StringBuilder.append:(I)Ljava/lang/StringBuilder;
     195: ldc           #59                 // String ,bufferSize=
     197: invokevirtual #15                 // Method java/lang/StringBuilder.append:(Ljava/lang/String;)Ljava/lang/StringBuilder;
     200: aload_0
     201: getfield      #4                  // Field bufferSize:I
     204: invokevirtual #19                 // Method java/lang/StringBuilder.append:(I)Ljava/lang/StringBuilder;
     207: invokevirtual #20                 // Method java/lang/StringBuilder.toString:()Ljava/lang/String;
     210: astore        10
     212: getstatic     #11                 // Field LOG:Lorg/slf4j/Logger;
     215: aload         10
     217: invokeinterface #60,  2           // InterfaceMethod org/slf4j/Logger.error:(Ljava/lang/String;)V
     222: new           #61                 // class java/lang/RuntimeException
     225: dup
     226: aload         10
     228: invokespecial #62                 // Method java/lang/RuntimeException."<init>":(Ljava/lang/String;)V
     231: athrow
     232: iconst_0
     233: istore        10
     235: iconst_m1
     236: istore        11
     238: iload         8
     240: iload         6
     242: isub
     243: iconst_1
     244: iadd
     245: anewarray     #22                 // class java/nio/ByteBuffer
     248: astore        12
     250: iload         6
     252: istore        13
     254: iconst_0
     255: istore        14
     257: iload         13
     259: iload         8
     261: if_icmpgt     390
     264: aload_0
     265: getfield      #23                 // Field buffers:[Ljava/nio/ByteBuffer;
     268: iload         13
     270: aaload
     271: invokevirtual #63                 // Method java/nio/ByteBuffer.duplicate:()Ljava/nio/ByteBuffer;
     274: astore        15
     276: iload         13
     278: iload         6
     280: if_icmpne     320
     283: aload_0
     284: getfield      #4                  // Field bufferSize:I
     287: iload         7
     289: isub
     290: istore        11
     292: iload         11
     294: iload_3
     295: if_icmple     301
     298: iload_3
     299: istore        11
     301: aload         15
     303: iload         7
     305: iload         11
     307: iadd
     308: invokevirtual #66                 // Method java/nio/ByteBuffer.limit:(I)Ljava/nio/Buffer;
     311: iload         7
     313: invokevirtual #67                 // Method java/nio/Buffer.position:(I)Ljava/nio/Buffer;
     316: pop
     317: goto          364
     320: iload         13
     322: iload         8
     324: if_icmpne     346
     327: iload         9
     329: istore        11
     331: aload         15
     333: iconst_0
     334: invokevirtual #68                 // Method java/nio/ByteBuffer.position:(I)Ljava/nio/Buffer;
     337: iload         11
     339: invokevirtual #69                 // Method java/nio/Buffer.limit:(I)Ljava/nio/Buffer;
     342: pop
     343: goto          364
     346: aload_0
     347: getfield      #4                  // Field bufferSize:I
     350: istore        11
     352: aload         15
     354: iconst_0
     355: invokevirtual #68                 // Method java/nio/ByteBuffer.position:(I)Ljava/nio/Buffer;
     358: iload         11
     360: invokevirtual #69                 // Method java/nio/Buffer.limit:(I)Ljava/nio/Buffer;
     363: pop
     364: aload         12
     366: iload         14
     368: aload         15
     370: invokevirtual #70                 // Method java/nio/ByteBuffer.slice:()Ljava/nio/ByteBuffer;
     373: aastore
     374: iload         10
     376: iload         11
     378: iadd
     379: istore        10
     381: iinc          13, 1
     384: iinc          14, 1
     387: goto          257
     390: getstatic     #53                 // Field $assertionsDisabled:Z
     393: ifne          410
     396: iload         10
     398: iload_3
     399: if_icmpeq     410
     402: new           #54                 // class java/lang/AssertionError
     405: dup
     406: invokespecial #55                 // Method java/lang/AssertionError."<init>":()V
     409: athrow
     410: aload         12
     412: arraylength
     413: iconst_1
     414: if_icmple     427
     417: new           #71                 // class org/apache/hadoop/hbase/nio/MultiByteBuff
     420: dup
     421: aload         12
     423: invokespecial #72                 // Method org/apache/hadoop/hbase/nio/MultiByteBuff."<init>":([Ljava/nio/ByteBuffer;)V
     426: areturn
     427: new           #73                 // class org/apache/hadoop/hbase/nio/SingleByteBuff
     430: dup
     431: aload         12
     433: iconst_0
     434: aaload
     435: invokespecial #74                 // Method org/apache/hadoop/hbase/nio/SingleByteBuff."<init>":(Ljava/nio/ByteBuffer;)V
     438: areturn

  static {};
    Code:
       0: ldc           #2                  // class org/apache/hadoop/hbase/util/ByteBufferArray
       2: invokevirtual #75                 // Method java/lang/Class.desiredAssertionStatus:()Z
       5: ifne          12
       8: iconst_1
       9: goto          13
      12: iconst_0
      13: putstatic     #53                 // Field $assertionsDisabled:Z
      16: ldc           #2                  // class org/apache/hadoop/hbase/util/ByteBufferArray
      18: invokestatic  #76                 // Method org/slf4j/LoggerFactory.getLogger:(Ljava/lang/Class;)Lorg/slf4j/Logger;
      21: putstatic     #11                 // Field LOG:Lorg/slf4j/Logger;
      24: new           #77                 // class org/apache/hadoop/hbase/util/ByteBufferArray$1
      27: dup
      28: invokespecial #78                 // Method org/apache/hadoop/hbase/util/ByteBufferArray$1."<init>":()V
      31: putstatic     #49                 // Field GET_MULTIPLE_VISTOR:Lorg/apache/hadoop/hbase/util/ByteBufferArray$Visitor;
      34: new           #79                 // class org/apache/hadoop/hbase/util/ByteBufferArray$2
      37: dup
      38: invokespecial #80                 // Method org/apache/hadoop/hbase/util/ByteBufferArray$2."<init>":()V
      41: putstatic     #52                 // Field PUT_MULTIPLE_VISITOR:Lorg/apache/hadoop/hbase/util/ByteBufferArray$Visitor;
      44: return
}
