Compiled from "Bytes.java"
class org.apache.hadoop.hbase.util.Bytes$LexicographicalComparerHolder {
  static final java.lang.String UNSAFE_COMPARER_NAME;

  static final org.apache.hadoop.hbase.util.Bytes$Comparer<byte[]> BEST_COMPARER;

  org.apache.hadoop.hbase.util.Bytes$LexicographicalComparerHolder();
    Code:
       0: aload_0
       1: invokespecial #1                  // Method java/lang/Object."<init>":()V
       4: return

  static org.apache.hadoop.hbase.util.Bytes$Comparer<byte[]> getBestComparer();
    Code:
       0: getstatic     #2                  // Field UNSAFE_COMPARER_NAME:Ljava/lang/String;
       3: invokestatic  #3                  // Method java/lang/Class.forName:(Ljava/lang/String;)Ljava/lang/Class;
       6: astore_0
       7: aload_0
       8: invokevirtual #4                  // Method java/lang/Class.getEnumConstants:()[Ljava/lang/Object;
      11: iconst_0
      12: aaload
      13: checkcast     #5                  // class org/apache/hadoop/hbase/util/Bytes$Comparer
      16: astore_1
      17: aload_1
      18: areturn
      19: astore_0
      20: invokestatic  #7                  // Method org/apache/hadoop/hbase/util/Bytes.lexicographicalComparerJavaImpl:()Lorg/apache/hadoop/hbase/util/Bytes$Comparer;
      23: areturn
    Exception table:
       from    to  target type
           0    18    19   Class java/lang/Throwable

  static {};
    Code:
       0: new           #8                  // class java/lang/StringBuilder
       3: dup
       4: invokespecial #9                  // Method java/lang/StringBuilder."<init>":()V
       7: ldc           #10                 // class org/apache/hadoop/hbase/util/Bytes$LexicographicalComparerHolder
       9: invokevirtual #11                 // Method java/lang/Class.getName:()Ljava/lang/String;
      12: invokevirtual #12                 // Method java/lang/StringBuilder.append:(Ljava/lang/String;)Ljava/lang/StringBuilder;
      15: ldc           #13                 // String $UnsafeComparer
      17: invokevirtual #12                 // Method java/lang/StringBuilder.append:(Ljava/lang/String;)Ljava/lang/StringBuilder;
      20: invokevirtual #14                 // Method java/lang/StringBuilder.toString:()Ljava/lang/String;
      23: putstatic     #2                  // Field UNSAFE_COMPARER_NAME:Ljava/lang/String;
      26: invokestatic  #15                 // Method getBestComparer:()Lorg/apache/hadoop/hbase/util/Bytes$Comparer;
      29: putstatic     #16                 // Field BEST_COMPARER:Lorg/apache/hadoop/hbase/util/Bytes$Comparer;
      32: return
}
