Compiled from "ByteStringer.java"
public final class org.apache.hadoop.hbase.util.ByteStringer {
  public static com.google.protobuf.ByteString wrap(byte[]);
    Code:
       0: getstatic     #2                  // Field USE_ZEROCOPYBYTESTRING:Z
       3: ifeq          13
       6: aload_0
       7: invokestatic  #3                  // Method com/google/protobuf/HBaseZeroCopyByteString.wrap:([B)Lcom/google/protobuf/ByteString;
      10: goto          17
      13: aload_0
      14: invokestatic  #4                  // Method com/google/protobuf/ByteString.copyFrom:([B)Lcom/google/protobuf/ByteString;
      17: areturn

  public static com.google.protobuf.ByteString wrap(byte[], int, int);
    Code:
       0: getstatic     #2                  // Field USE_ZEROCOPYBYTESTRING:Z
       3: ifeq          15
       6: aload_0
       7: iload_1
       8: iload_2
       9: invokestatic  #5                  // Method com/google/protobuf/HBaseZeroCopyByteString.wrap:([BII)Lcom/google/protobuf/ByteString;
      12: goto          21
      15: aload_0
      16: iload_1
      17: iload_2
      18: invokestatic  #6                  // Method com/google/protobuf/ByteString.copyFrom:([BII)Lcom/google/protobuf/ByteString;
      21: areturn

  static {};
    Code:
       0: ldc           #7                  // class org/apache/hadoop/hbase/util/ByteStringer
       2: invokestatic  #8                  // Method org/slf4j/LoggerFactory.getLogger:(Ljava/lang/Class;)Lorg/slf4j/Logger;
       5: putstatic     #9                  // Field LOG:Lorg/slf4j/Logger;
       8: iconst_1
       9: putstatic     #2                  // Field USE_ZEROCOPYBYTESTRING:Z
      12: iconst_0
      13: newarray       byte
      15: invokestatic  #3                  // Method com/google/protobuf/HBaseZeroCopyByteString.wrap:([B)Lcom/google/protobuf/ByteString;
      18: pop
      19: goto          57
      22: astore_0
      23: iconst_0
      24: putstatic     #2                  // Field USE_ZEROCOPYBYTESTRING:Z
      27: getstatic     #9                  // Field LOG:Lorg/slf4j/Logger;
      30: new           #11                 // class java/lang/StringBuilder
      33: dup
      34: invokespecial #12                 // Method java/lang/StringBuilder."<init>":()V
      37: ldc           #13                 // String Failed to classload HBaseZeroCopyByteString:
      39: invokevirtual #14                 // Method java/lang/StringBuilder.append:(Ljava/lang/String;)Ljava/lang/StringBuilder;
      42: aload_0
      43: invokevirtual #15                 // Method java/lang/IllegalAccessError.toString:()Ljava/lang/String;
      46: invokevirtual #14                 // Method java/lang/StringBuilder.append:(Ljava/lang/String;)Ljava/lang/StringBuilder;
      49: invokevirtual #16                 // Method java/lang/StringBuilder.toString:()Ljava/lang/String;
      52: invokeinterface #17,  2           // InterfaceMethod org/slf4j/Logger.debug:(Ljava/lang/String;)V
      57: return
    Exception table:
       from    to  target type
          12    19    22   Class java/lang/IllegalAccessError
}
