Compiled from "CacheTestUtils.java"
final class org.apache.hadoop.hbase.io.hfile.CacheTestUtils$3 extends org.apache.hadoop.hbase.MultithreadedTestUtil$RepeatingTestThread {
  final org.apache.hadoop.hbase.io.hfile.BlockCache val$toBeTested;

  final org.apache.hadoop.hbase.io.hfile.BlockCacheKey val$key;

  final org.apache.hadoop.hbase.io.hfile.CacheTestUtils$ByteArrayCacheable val$bac;

  org.apache.hadoop.hbase.io.hfile.CacheTestUtils$3(org.apache.hadoop.hbase.MultithreadedTestUtil$TestContext, org.apache.hadoop.hbase.io.hfile.BlockCache, org.apache.hadoop.hbase.io.hfile.BlockCacheKey, org.apache.hadoop.hbase.io.hfile.CacheTestUtils$ByteArrayCacheable);
    Code:
       0: aload_0
       1: aload_2
       2: putfield      #1                  // Field val$toBeTested:Lorg/apache/hadoop/hbase/io/hfile/BlockCache;
       5: aload_0
       6: aload_3
       7: putfield      #2                  // Field val$key:Lorg/apache/hadoop/hbase/io/hfile/BlockCacheKey;
      10: aload_0
      11: aload         4
      13: putfield      #3                  // Field val$bac:Lorg/apache/hadoop/hbase/io/hfile/CacheTestUtils$ByteArrayCacheable;
      16: aload_0
      17: aload_1
      18: invokespecial #4                  // Method org/apache/hadoop/hbase/MultithreadedTestUtil$RepeatingTestThread."<init>":(Lorg/apache/hadoop/hbase/MultithreadedTestUtil$TestContext;)V
      21: return

  public void doAnAction() throws java.lang.Exception;
    Code:
       0: aload_0
       1: getfield      #1                  // Field val$toBeTested:Lorg/apache/hadoop/hbase/io/hfile/BlockCache;
       4: aload_0
       5: getfield      #2                  // Field val$key:Lorg/apache/hadoop/hbase/io/hfile/BlockCacheKey;
       8: invokeinterface #5,  2            // InterfaceMethod org/apache/hadoop/hbase/io/hfile/BlockCache.evictBlock:(Lorg/apache/hadoop/hbase/io/hfile/BlockCacheKey;)Z
      13: pop
      14: aload_0
      15: getfield      #1                  // Field val$toBeTested:Lorg/apache/hadoop/hbase/io/hfile/BlockCache;
      18: aload_0
      19: getfield      #2                  // Field val$key:Lorg/apache/hadoop/hbase/io/hfile/BlockCacheKey;
      22: aload_0
      23: getfield      #3                  // Field val$bac:Lorg/apache/hadoop/hbase/io/hfile/CacheTestUtils$ByteArrayCacheable;
      26: invokeinterface #6,  3            // InterfaceMethod org/apache/hadoop/hbase/io/hfile/BlockCache.cacheBlock:(Lorg/apache/hadoop/hbase/io/hfile/BlockCacheKey;Lorg/apache/hadoop/hbase/io/hfile/Cacheable;)V
      31: ldc2_w        #7                  // long 50l
      34: invokestatic  #9                  // Method java/lang/Thread.sleep:(J)V
      37: return
}
