Compiled from "CacheEvictionStats.java"
public final class org.apache.hadoop.hbase.CacheEvictionStats {
  org.apache.hadoop.hbase.CacheEvictionStats(org.apache.hadoop.hbase.CacheEvictionStatsBuilder);
    Code:
       0: aload_0
       1: invokespecial #1                  // Method java/lang/Object."<init>":()V
       4: aload_0
       5: aload_1
       6: getfield      #2                  // Field org/apache/hadoop/hbase/CacheEvictionStatsBuilder.evictedBlocks:J
       9: putfield      #3                  // Field evictedBlocks:J
      12: aload_0
      13: aload_1
      14: getfield      #4                  // Field org/apache/hadoop/hbase/CacheEvictionStatsBuilder.maxCacheSize:J
      17: putfield      #5                  // Field maxCacheSize:J
      20: aload_0
      21: aload_1
      22: getfield      #6                  // Field org/apache/hadoop/hbase/CacheEvictionStatsBuilder.exceptions:Ljava/util/Map;
      25: putfield      #7                  // Field exceptions:Ljava/util/Map;
      28: return

  public long getEvictedBlocks();
    Code:
       0: aload_0
       1: getfield      #3                  // Field evictedBlocks:J
       4: lreturn

  public long getMaxCacheSize();
    Code:
       0: aload_0
       1: getfield      #5                  // Field maxCacheSize:J
       4: lreturn

  public java.util.Map<byte[], java.lang.Throwable> getExceptions();
    Code:
       0: aload_0
       1: getfield      #7                  // Field exceptions:Ljava/util/Map;
       4: invokestatic  #8                  // Method java/util/Collections.unmodifiableMap:(Ljava/util/Map;)Ljava/util/Map;
       7: areturn

  public int getExceptionCount();
    Code:
       0: aload_0
       1: getfield      #7                  // Field exceptions:Ljava/util/Map;
       4: invokeinterface #9,  1            // InterfaceMethod java/util/Map.size:()I
       9: ireturn

  public static org.apache.hadoop.hbase.CacheEvictionStatsBuilder builder();
    Code:
       0: new           #18                 // class org/apache/hadoop/hbase/CacheEvictionStatsBuilder
       3: dup
       4: invokespecial #19                 // Method org/apache/hadoop/hbase/CacheEvictionStatsBuilder."<init>":()V
       7: areturn

  public java.lang.String toString();
    Code:
       0: new           #20                 // class java/lang/StringBuilder
       3: dup
       4: invokespecial #21                 // Method java/lang/StringBuilder."<init>":()V
       7: ldc           #22                 // String CacheEvictionStats{evictedBlocks=
       9: invokevirtual #23                 // Method java/lang/StringBuilder.append:(Ljava/lang/String;)Ljava/lang/StringBuilder;
      12: aload_0
      13: getfield      #3                  // Field evictedBlocks:J
      16: invokevirtual #24                 // Method java/lang/StringBuilder.append:(J)Ljava/lang/StringBuilder;
      19: ldc           #25                 // String , maxCacheSize=
      21: invokevirtual #23                 // Method java/lang/StringBuilder.append:(Ljava/lang/String;)Ljava/lang/StringBuilder;
      24: aload_0
      25: getfield      #5                  // Field maxCacheSize:J
      28: invokevirtual #24                 // Method java/lang/StringBuilder.append:(J)Ljava/lang/StringBuilder;
      31: ldc           #26                 // String , failedRegionsSize=
      33: invokevirtual #23                 // Method java/lang/StringBuilder.append:(Ljava/lang/String;)Ljava/lang/StringBuilder;
      36: aload_0
      37: invokevirtual #27                 // Method getExceptionCount:()I
      40: invokevirtual #28                 // Method java/lang/StringBuilder.append:(I)Ljava/lang/StringBuilder;
      43: ldc           #29                 // String , failedRegions=
      45: invokevirtual #23                 // Method java/lang/StringBuilder.append:(Ljava/lang/String;)Ljava/lang/StringBuilder;
      48: aload_0
      49: invokespecial #30                 // Method getFailedRegions:()Ljava/lang/String;
      52: invokevirtual #23                 // Method java/lang/StringBuilder.append:(Ljava/lang/String;)Ljava/lang/StringBuilder;
      55: bipush        125
      57: invokevirtual #31                 // Method java/lang/StringBuilder.append:(C)Ljava/lang/StringBuilder;
      60: invokevirtual #32                 // Method java/lang/StringBuilder.toString:()Ljava/lang/String;
      63: areturn
}
