Compiled from "CallQueueInfo.java"
public class org.apache.hadoop.hbase.ipc.CallQueueInfo {
  org.apache.hadoop.hbase.ipc.CallQueueInfo();
    Code:
       0: aload_0
       1: invokespecial #1                  // Method java/lang/Object."<init>":()V
       4: aload_0
       5: new           #2                  // class java/util/HashMap
       8: dup
       9: invokespecial #3                  // Method java/util/HashMap."<init>":()V
      12: putfield      #4                  // Field callQueueMethodCountsSummary:Ljava/util/Map;
      15: aload_0
      16: new           #2                  // class java/util/HashMap
      19: dup
      20: invokespecial #3                  // Method java/util/HashMap."<init>":()V
      23: putfield      #5                  // Field callQueueMethodSizeSummary:Ljava/util/Map;
      26: return

  public java.util.Set<java.lang.String> getCallQueueNames();
    Code:
       0: aload_0
       1: getfield      #4                  // Field callQueueMethodCountsSummary:Ljava/util/Map;
       4: invokeinterface #6,  1            // InterfaceMethod java/util/Map.keySet:()Ljava/util/Set;
       9: areturn

  public java.util.Set<java.lang.String> getCalledMethodNames(java.lang.String);
    Code:
       0: aload_0
       1: getfield      #4                  // Field callQueueMethodCountsSummary:Ljava/util/Map;
       4: aload_1
       5: invokeinterface #7,  2            // InterfaceMethod java/util/Map.get:(Ljava/lang/Object;)Ljava/lang/Object;
      10: checkcast     #8                  // class java/util/Map
      13: invokeinterface #6,  1            // InterfaceMethod java/util/Map.keySet:()Ljava/util/Set;
      18: areturn

  public long getCallMethodCount(java.lang.String, java.lang.String);
    Code:
       0: aload_0
       1: getfield      #4                  // Field callQueueMethodCountsSummary:Ljava/util/Map;
       4: aload_1
       5: aconst_null
       6: invokeinterface #9,  3            // InterfaceMethod java/util/Map.getOrDefault:(Ljava/lang/Object;Ljava/lang/Object;)Ljava/lang/Object;
      11: checkcast     #8                  // class java/util/Map
      14: astore        5
      16: aconst_null
      17: aload         5
      19: if_acmpeq     44
      22: aload         5
      24: aload_2
      25: lconst_0
      26: invokestatic  #10                 // Method java/lang/Long.valueOf:(J)Ljava/lang/Long;
      29: invokeinterface #9,  3            // InterfaceMethod java/util/Map.getOrDefault:(Ljava/lang/Object;Ljava/lang/Object;)Ljava/lang/Object;
      34: checkcast     #11                 // class java/lang/Long
      37: invokevirtual #12                 // Method java/lang/Long.longValue:()J
      40: lstore_3
      41: goto          46
      44: lconst_0
      45: lstore_3
      46: lload_3
      47: lreturn

  void setCallMethodCount(java.lang.String, java.util.Map<java.lang.String, java.lang.Long>);
    Code:
       0: aload_0
       1: getfield      #4                  // Field callQueueMethodCountsSummary:Ljava/util/Map;
       4: aload_1
       5: aload_2
       6: invokeinterface #13,  3           // InterfaceMethod java/util/Map.put:(Ljava/lang/Object;Ljava/lang/Object;)Ljava/lang/Object;
      11: pop
      12: return

  public long getCallMethodSize(java.lang.String, java.lang.String);
    Code:
       0: aload_0
       1: getfield      #5                  // Field callQueueMethodSizeSummary:Ljava/util/Map;
       4: aload_1
       5: aconst_null
       6: invokeinterface #9,  3            // InterfaceMethod java/util/Map.getOrDefault:(Ljava/lang/Object;Ljava/lang/Object;)Ljava/lang/Object;
      11: checkcast     #8                  // class java/util/Map
      14: astore        5
      16: aconst_null
      17: aload         5
      19: if_acmpeq     44
      22: aload         5
      24: aload_2
      25: lconst_0
      26: invokestatic  #10                 // Method java/lang/Long.valueOf:(J)Ljava/lang/Long;
      29: invokeinterface #9,  3            // InterfaceMethod java/util/Map.getOrDefault:(Ljava/lang/Object;Ljava/lang/Object;)Ljava/lang/Object;
      34: checkcast     #11                 // class java/lang/Long
      37: invokevirtual #12                 // Method java/lang/Long.longValue:()J
      40: lstore_3
      41: goto          46
      44: lconst_0
      45: lstore_3
      46: lload_3
      47: lreturn

  void setCallMethodSize(java.lang.String, java.util.Map<java.lang.String, java.lang.Long>);
    Code:
       0: aload_0
       1: getfield      #5                  // Field callQueueMethodSizeSummary:Ljava/util/Map;
       4: aload_1
       5: aload_2
       6: invokeinterface #13,  3           // InterfaceMethod java/util/Map.put:(Ljava/lang/Object;Ljava/lang/Object;)Ljava/lang/Object;
      11: pop
      12: return
}
