Compiled from "CellArrayImmutableSegment.java"
public class org.apache.hadoop.hbase.regionserver.CellArrayImmutableSegment extends org.apache.hadoop.hbase.regionserver.ImmutableSegment {
  public static final long DEEP_OVERHEAD_CAM;

  protected org.apache.hadoop.hbase.regionserver.CellArrayImmutableSegment(org.apache.hadoop.hbase.CellComparator, org.apache.hadoop.hbase.regionserver.MemStoreSegmentsIterator, org.apache.hadoop.hbase.regionserver.MemStoreLAB, int, org.apache.hadoop.hbase.regionserver.MemStoreCompactionStrategy$Action);
    Code:
       0: aload_0
       1: aconst_null
       2: aload_1
       3: aload_3
       4: invokespecial #1                  // Method org/apache/hadoop/hbase/regionserver/ImmutableSegment."<init>":(Lorg/apache/hadoop/hbase/regionserver/CellSet;Lorg/apache/hadoop/hbase/CellComparator;Lorg/apache/hadoop/hbase/regionserver/MemStoreLAB;)V
       7: aload_0
       8: lconst_0
       9: getstatic     #2                  // Field DEEP_OVERHEAD_CAM:J
      12: lconst_0
      13: iconst_0
      14: invokevirtual #3                  // Method incMemStoreSize:(JJJI)J
      17: pop2
      18: aload_0
      19: iload         4
      21: aload_2
      22: aload         5
      24: invokespecial #4                  // Method initializeCellSet:(ILorg/apache/hadoop/hbase/regionserver/MemStoreSegmentsIterator;Lorg/apache/hadoop/hbase/regionserver/MemStoreCompactionStrategy$Action;)V
      27: return

  protected org.apache.hadoop.hbase.regionserver.CellArrayImmutableSegment(org.apache.hadoop.hbase.regionserver.CSLMImmutableSegment, org.apache.hadoop.hbase.regionserver.MemStoreSizing, org.apache.hadoop.hbase.regionserver.MemStoreCompactionStrategy$Action);
    Code:
       0: aload_0
       1: aload_1
       2: invokespecial #5                  // Method org/apache/hadoop/hbase/regionserver/ImmutableSegment."<init>":(Lorg/apache/hadoop/hbase/regionserver/Segment;)V
       5: getstatic     #2                  // Field DEEP_OVERHEAD_CAM:J
       8: getstatic     #6                  // Field org/apache/hadoop/hbase/regionserver/CSLMImmutableSegment.DEEP_OVERHEAD_CSLM:J
      11: lsub
      12: lstore        4
      14: aload_0
      15: lconst_0
      16: lload         4
      18: lconst_0
      19: iconst_0
      20: invokevirtual #3                  // Method incMemStoreSize:(JJJI)J
      23: pop2
      24: aload_2
      25: lconst_0
      26: lload         4
      28: lconst_0
      29: iconst_0
      30: invokeinterface #7,  8            // InterfaceMethod org/apache/hadoop/hbase/regionserver/MemStoreSizing.incMemStoreSize:(JJJI)J
      35: pop2
      36: aload_1
      37: invokevirtual #8                  // Method org/apache/hadoop/hbase/regionserver/CSLMImmutableSegment.getCellsCount:()I
      40: istore        6
      42: aload_0
      43: iload         6
      45: aload_1
      46: ldc2_w        #10                 // long 9223372036854775807l
      49: invokevirtual #12                 // Method org/apache/hadoop/hbase/regionserver/CSLMImmutableSegment.getScanner:(J)Lorg/apache/hadoop/hbase/regionserver/KeyValueScanner;
      52: aload_1
      53: invokevirtual #13                 // Method org/apache/hadoop/hbase/regionserver/CSLMImmutableSegment.getCellSet:()Lorg/apache/hadoop/hbase/regionserver/CellSet;
      56: aload_3
      57: invokespecial #14                 // Method reinitializeCellSet:(ILorg/apache/hadoop/hbase/regionserver/KeyValueScanner;Lorg/apache/hadoop/hbase/regionserver/CellSet;Lorg/apache/hadoop/hbase/regionserver/MemStoreCompactionStrategy$Action;)V
      60: iload         6
      62: i2l
      63: aload_0
      64: invokevirtual #15                 // Method indexEntrySize:()J
      67: getstatic     #16                 // Field org/apache/hadoop/hbase/util/ClassSize.CONCURRENT_SKIPLISTMAP_ENTRY:I
      70: i2l
      71: lsub
      72: lmul
      73: lstore        7
      75: aload_0
      76: lconst_0
      77: lload         7
      79: lconst_0
      80: iconst_0
      81: invokevirtual #3                  // Method incMemStoreSize:(JJJI)J
      84: pop2
      85: aload_2
      86: lconst_0
      87: lload         7
      89: lconst_0
      90: iconst_0
      91: invokeinterface #7,  8            // InterfaceMethod org/apache/hadoop/hbase/regionserver/MemStoreSizing.incMemStoreSize:(JJJI)J
      96: pop2
      97: return

  protected long indexEntrySize();
    Code:
       0: getstatic     #17                 // Field org/apache/hadoop/hbase/util/ClassSize.CELL_ARRAY_MAP_ENTRY:I
       3: i2l
       4: lreturn

  protected boolean canBeFlattened();
    Code:
       0: iconst_0
       1: ireturn

  static {};
    Code:
       0: getstatic     #40                 // Field DEEP_OVERHEAD:J
       3: getstatic     #41                 // Field org/apache/hadoop/hbase/util/ClassSize.CELL_ARRAY_MAP:I
       6: i2l
       7: ladd
       8: putstatic     #2                  // Field DEEP_OVERHEAD_CAM:J
      11: return
}
