Compiled from "CellArrayMap.java"
public class org.apache.hadoop.hbase.regionserver.CellArrayMap extends org.apache.hadoop.hbase.regionserver.CellFlatMap {
  public org.apache.hadoop.hbase.regionserver.CellArrayMap(java.util.Comparator<? super org.apache.hadoop.hbase.Cell>, org.apache.hadoop.hbase.Cell[], int, int, boolean);
    Code:
       0: aload_0
       1: aload_1
       2: iload_3
       3: iload         4
       5: iload         5
       7: invokespecial #1                  // Method org/apache/hadoop/hbase/regionserver/CellFlatMap."<init>":(Ljava/util/Comparator;IIZ)V
      10: aload_0
      11: aload_2
      12: putfield      #2                  // Field block:[Lorg/apache/hadoop/hbase/Cell;
      15: return

  protected org.apache.hadoop.hbase.regionserver.CellFlatMap createSubCellFlatMap(int, int, boolean);
    Code:
       0: new           #3                  // class org/apache/hadoop/hbase/regionserver/CellArrayMap
       3: dup
       4: aload_0
       5: invokevirtual #4                  // Method comparator:()Ljava/util/Comparator;
       8: aload_0
       9: getfield      #2                  // Field block:[Lorg/apache/hadoop/hbase/Cell;
      12: iload_1
      13: iload_2
      14: iload_3
      15: invokespecial #5                  // Method "<init>":(Ljava/util/Comparator;[Lorg/apache/hadoop/hbase/Cell;IIZ)V
      18: areturn

  protected org.apache.hadoop.hbase.Cell getCell(int);
    Code:
       0: iload_1
       1: aload_0
       2: getfield      #6                  // Field minCellIdx:I
       5: if_icmplt     16
       8: iload_1
       9: aload_0
      10: getfield      #7                  // Field maxCellIdx:I
      13: if_icmplt     18
      16: aconst_null
      17: areturn
      18: aload_0
      19: getfield      #2                  // Field block:[Lorg/apache/hadoop/hbase/Cell;
      22: iload_1
      23: aaload
      24: areturn
}
