Compiled from "CellComparator.java"
public interface org.apache.hadoop.hbase.CellComparator extends java.util.Comparator<org.apache.hadoop.hbase.Cell> {
  public static org.apache.hadoop.hbase.CellComparator getInstance();
    Code:
       0: getstatic     #1                  // Field org/apache/hadoop/hbase/CellComparatorImpl.COMPARATOR:Lorg/apache/hadoop/hbase/CellComparatorImpl;
       3: areturn

  public abstract int compare(org.apache.hadoop.hbase.Cell, org.apache.hadoop.hbase.Cell);

  public abstract int compare(org.apache.hadoop.hbase.Cell, org.apache.hadoop.hbase.Cell, boolean);

  public abstract int compareRows(org.apache.hadoop.hbase.Cell, org.apache.hadoop.hbase.Cell);

  public abstract int compareRows(org.apache.hadoop.hbase.Cell, byte[], int, int);

  public abstract int compareWithoutRow(org.apache.hadoop.hbase.Cell, org.apache.hadoop.hbase.Cell);

  public abstract int compareFamilies(org.apache.hadoop.hbase.Cell, org.apache.hadoop.hbase.Cell);

  public abstract int compareQualifiers(org.apache.hadoop.hbase.Cell, org.apache.hadoop.hbase.Cell);

  public abstract int compareTimestamps(org.apache.hadoop.hbase.Cell, org.apache.hadoop.hbase.Cell);

  public abstract int compareTimestamps(long, long);

  public abstract java.util.Comparator getSimpleComparator();

  public int compare(java.lang.Object, java.lang.Object);
    Code:
       0: aload_0
       1: aload_1
       2: checkcast     #2                  // class org/apache/hadoop/hbase/Cell
       5: aload_2
       6: checkcast     #2                  // class org/apache/hadoop/hbase/Cell
       9: invokeinterface #3,  3            // InterfaceMethod compare:(Lorg/apache/hadoop/hbase/Cell;Lorg/apache/hadoop/hbase/Cell;)I
      14: ireturn
}
