Compiled from "CellProtos.java"
public final class org.apache.hadoop.hbase.protobuf.generated.CellProtos$CellType extends java.lang.Enum<org.apache.hadoop.hbase.protobuf.generated.CellProtos$CellType> implements com.google.protobuf.ProtocolMessageEnum {
  public static final org.apache.hadoop.hbase.protobuf.generated.CellProtos$CellType MINIMUM;

  public static final org.apache.hadoop.hbase.protobuf.generated.CellProtos$CellType PUT;

  public static final org.apache.hadoop.hbase.protobuf.generated.CellProtos$CellType DELETE;

  public static final org.apache.hadoop.hbase.protobuf.generated.CellProtos$CellType DELETE_FAMILY_VERSION;

  public static final org.apache.hadoop.hbase.protobuf.generated.CellProtos$CellType DELETE_COLUMN;

  public static final org.apache.hadoop.hbase.protobuf.generated.CellProtos$CellType DELETE_FAMILY;

  public static final org.apache.hadoop.hbase.protobuf.generated.CellProtos$CellType MAXIMUM;

  public static final int MINIMUM_VALUE;

  public static final int PUT_VALUE;

  public static final int DELETE_VALUE;

  public static final int DELETE_FAMILY_VERSION_VALUE;

  public static final int DELETE_COLUMN_VALUE;

  public static final int DELETE_FAMILY_VALUE;

  public static final int MAXIMUM_VALUE;

  public static org.apache.hadoop.hbase.protobuf.generated.CellProtos$CellType[] values();
    Code:
       0: getstatic     #1                  // Field $VALUES:[Lorg/apache/hadoop/hbase/protobuf/generated/CellProtos$CellType;
       3: invokevirtual #2                  // Method "[Lorg/apache/hadoop/hbase/protobuf/generated/CellProtos$CellType;".clone:()Ljava/lang/Object;
       6: checkcast     #3                  // class "[Lorg/apache/hadoop/hbase/protobuf/generated/CellProtos$CellType;"
       9: areturn

  public static org.apache.hadoop.hbase.protobuf.generated.CellProtos$CellType valueOf(java.lang.String);
    Code:
       0: ldc           #4                  // class org/apache/hadoop/hbase/protobuf/generated/CellProtos$CellType
       2: aload_0
       3: invokestatic  #5                  // Method java/lang/Enum.valueOf:(Ljava/lang/Class;Ljava/lang/String;)Ljava/lang/Enum;
       6: checkcast     #4                  // class org/apache/hadoop/hbase/protobuf/generated/CellProtos$CellType
       9: areturn

  public final int getNumber();
    Code:
       0: aload_0
       1: getfield      #6                  // Field value:I
       4: ireturn

  public static org.apache.hadoop.hbase.protobuf.generated.CellProtos$CellType valueOf(int);
    Code:
       0: iload_0
       1: lookupswitch  { // 7
                     0: 68
                     4: 72
                     8: 76
                    10: 80
                    12: 84
                    14: 88
                   255: 92
               default: 96
          }
      68: getstatic     #7                  // Field MINIMUM:Lorg/apache/hadoop/hbase/protobuf/generated/CellProtos$CellType;
      71: areturn
      72: getstatic     #8                  // Field PUT:Lorg/apache/hadoop/hbase/protobuf/generated/CellProtos$CellType;
      75: areturn
      76: getstatic     #9                  // Field DELETE:Lorg/apache/hadoop/hbase/protobuf/generated/CellProtos$CellType;
      79: areturn
      80: getstatic     #10                 // Field DELETE_FAMILY_VERSION:Lorg/apache/hadoop/hbase/protobuf/generated/CellProtos$CellType;
      83: areturn
      84: getstatic     #11                 // Field DELETE_COLUMN:Lorg/apache/hadoop/hbase/protobuf/generated/CellProtos$CellType;
      87: areturn
      88: getstatic     #12                 // Field DELETE_FAMILY:Lorg/apache/hadoop/hbase/protobuf/generated/CellProtos$CellType;
      91: areturn
      92: getstatic     #13                 // Field MAXIMUM:Lorg/apache/hadoop/hbase/protobuf/generated/CellProtos$CellType;
      95: areturn
      96: aconst_null
      97: areturn

  public static com.google.protobuf.Internal$EnumLiteMap<org.apache.hadoop.hbase.protobuf.generated.CellProtos$CellType> internalGetValueMap();
    Code:
       0: getstatic     #14                 // Field internalValueMap:Lcom/google/protobuf/Internal$EnumLiteMap;
       3: areturn

  public final com.google.protobuf.Descriptors$EnumValueDescriptor getValueDescriptor();
    Code:
       0: invokestatic  #15                 // Method getDescriptor:()Lcom/google/protobuf/Descriptors$EnumDescriptor;
       3: invokevirtual #16                 // Method com/google/protobuf/Descriptors$EnumDescriptor.getValues:()Ljava/util/List;
       6: aload_0
       7: getfield      #17                 // Field index:I
      10: invokeinterface #18,  2           // InterfaceMethod java/util/List.get:(I)Ljava/lang/Object;
      15: checkcast     #19                 // class com/google/protobuf/Descriptors$EnumValueDescriptor
      18: areturn

  public final com.google.protobuf.Descriptors$EnumDescriptor getDescriptorForType();
    Code:
       0: invokestatic  #15                 // Method getDescriptor:()Lcom/google/protobuf/Descriptors$EnumDescriptor;
       3: areturn

  public static final com.google.protobuf.Descriptors$EnumDescriptor getDescriptor();
    Code:
       0: invokestatic  #20                 // Method org/apache/hadoop/hbase/protobuf/generated/CellProtos.getDescriptor:()Lcom/google/protobuf/Descriptors$FileDescriptor;
       3: invokevirtual #21                 // Method com/google/protobuf/Descriptors$FileDescriptor.getEnumTypes:()Ljava/util/List;
       6: iconst_0
       7: invokeinterface #18,  2           // InterfaceMethod java/util/List.get:(I)Ljava/lang/Object;
      12: checkcast     #22                 // class com/google/protobuf/Descriptors$EnumDescriptor
      15: areturn

  public static org.apache.hadoop.hbase.protobuf.generated.CellProtos$CellType valueOf(com.google.protobuf.Descriptors$EnumValueDescriptor);
    Code:
       0: aload_0
       1: invokevirtual #23                 // Method com/google/protobuf/Descriptors$EnumValueDescriptor.getType:()Lcom/google/protobuf/Descriptors$EnumDescriptor;
       4: invokestatic  #15                 // Method getDescriptor:()Lcom/google/protobuf/Descriptors$EnumDescriptor;
       7: if_acmpeq     20
      10: new           #24                 // class java/lang/IllegalArgumentException
      13: dup
      14: ldc           #25                 // String EnumValueDescriptor is not for this type.
      16: invokespecial #26                 // Method java/lang/IllegalArgumentException."<init>":(Ljava/lang/String;)V
      19: athrow
      20: getstatic     #27                 // Field VALUES:[Lorg/apache/hadoop/hbase/protobuf/generated/CellProtos$CellType;
      23: aload_0
      24: invokevirtual #28                 // Method com/google/protobuf/Descriptors$EnumValueDescriptor.getIndex:()I
      27: aaload
      28: areturn

  static {};
    Code:
       0: new           #4                  // class org/apache/hadoop/hbase/protobuf/generated/CellProtos$CellType
       3: dup
       4: ldc           #30                 // String MINIMUM
       6: iconst_0
       7: iconst_0
       8: iconst_0
       9: invokespecial #31                 // Method "<init>":(Ljava/lang/String;III)V
      12: putstatic     #7                  // Field MINIMUM:Lorg/apache/hadoop/hbase/protobuf/generated/CellProtos$CellType;
      15: new           #4                  // class org/apache/hadoop/hbase/protobuf/generated/CellProtos$CellType
      18: dup
      19: ldc           #32                 // String PUT
      21: iconst_1
      22: iconst_1
      23: iconst_4
      24: invokespecial #31                 // Method "<init>":(Ljava/lang/String;III)V
      27: putstatic     #8                  // Field PUT:Lorg/apache/hadoop/hbase/protobuf/generated/CellProtos$CellType;
      30: new           #4                  // class org/apache/hadoop/hbase/protobuf/generated/CellProtos$CellType
      33: dup
      34: ldc           #33                 // String DELETE
      36: iconst_2
      37: iconst_2
      38: bipush        8
      40: invokespecial #31                 // Method "<init>":(Ljava/lang/String;III)V
      43: putstatic     #9                  // Field DELETE:Lorg/apache/hadoop/hbase/protobuf/generated/CellProtos$CellType;
      46: new           #4                  // class org/apache/hadoop/hbase/protobuf/generated/CellProtos$CellType
      49: dup
      50: ldc           #34                 // String DELETE_FAMILY_VERSION
      52: iconst_3
      53: iconst_3
      54: bipush        10
      56: invokespecial #31                 // Method "<init>":(Ljava/lang/String;III)V
      59: putstatic     #10                 // Field DELETE_FAMILY_VERSION:Lorg/apache/hadoop/hbase/protobuf/generated/CellProtos$CellType;
      62: new           #4                  // class org/apache/hadoop/hbase/protobuf/generated/CellProtos$CellType
      65: dup
      66: ldc           #35                 // String DELETE_COLUMN
      68: iconst_4
      69: iconst_4
      70: bipush        12
      72: invokespecial #31                 // Method "<init>":(Ljava/lang/String;III)V
      75: putstatic     #11                 // Field DELETE_COLUMN:Lorg/apache/hadoop/hbase/protobuf/generated/CellProtos$CellType;
      78: new           #4                  // class org/apache/hadoop/hbase/protobuf/generated/CellProtos$CellType
      81: dup
      82: ldc           #36                 // String DELETE_FAMILY
      84: iconst_5
      85: iconst_5
      86: bipush        14
      88: invokespecial #31                 // Method "<init>":(Ljava/lang/String;III)V
      91: putstatic     #12                 // Field DELETE_FAMILY:Lorg/apache/hadoop/hbase/protobuf/generated/CellProtos$CellType;
      94: new           #4                  // class org/apache/hadoop/hbase/protobuf/generated/CellProtos$CellType
      97: dup
      98: ldc           #37                 // String MAXIMUM
     100: bipush        6
     102: bipush        6
     104: sipush        255
     107: invokespecial #31                 // Method "<init>":(Ljava/lang/String;III)V
     110: putstatic     #13                 // Field MAXIMUM:Lorg/apache/hadoop/hbase/protobuf/generated/CellProtos$CellType;
     113: bipush        7
     115: anewarray     #4                  // class org/apache/hadoop/hbase/protobuf/generated/CellProtos$CellType
     118: dup
     119: iconst_0
     120: getstatic     #7                  // Field MINIMUM:Lorg/apache/hadoop/hbase/protobuf/generated/CellProtos$CellType;
     123: aastore
     124: dup
     125: iconst_1
     126: getstatic     #8                  // Field PUT:Lorg/apache/hadoop/hbase/protobuf/generated/CellProtos$CellType;
     129: aastore
     130: dup
     131: iconst_2
     132: getstatic     #9                  // Field DELETE:Lorg/apache/hadoop/hbase/protobuf/generated/CellProtos$CellType;
     135: aastore
     136: dup
     137: iconst_3
     138: getstatic     #10                 // Field DELETE_FAMILY_VERSION:Lorg/apache/hadoop/hbase/protobuf/generated/CellProtos$CellType;
     141: aastore
     142: dup
     143: iconst_4
     144: getstatic     #11                 // Field DELETE_COLUMN:Lorg/apache/hadoop/hbase/protobuf/generated/CellProtos$CellType;
     147: aastore
     148: dup
     149: iconst_5
     150: getstatic     #12                 // Field DELETE_FAMILY:Lorg/apache/hadoop/hbase/protobuf/generated/CellProtos$CellType;
     153: aastore
     154: dup
     155: bipush        6
     157: getstatic     #13                 // Field MAXIMUM:Lorg/apache/hadoop/hbase/protobuf/generated/CellProtos$CellType;
     160: aastore
     161: putstatic     #1                  // Field $VALUES:[Lorg/apache/hadoop/hbase/protobuf/generated/CellProtos$CellType;
     164: new           #38                 // class org/apache/hadoop/hbase/protobuf/generated/CellProtos$CellType$1
     167: dup
     168: invokespecial #39                 // Method org/apache/hadoop/hbase/protobuf/generated/CellProtos$CellType$1."<init>":()V
     171: putstatic     #14                 // Field internalValueMap:Lcom/google/protobuf/Internal$EnumLiteMap;
     174: invokestatic  #40                 // Method values:()[Lorg/apache/hadoop/hbase/protobuf/generated/CellProtos$CellType;
     177: putstatic     #27                 // Field VALUES:[Lorg/apache/hadoop/hbase/protobuf/generated/CellProtos$CellType;
     180: return
}
