Compiled from "CellUtil.java"
public final class org.apache.hadoop.hbase.CellUtil {
  public static org.apache.hadoop.hbase.util.ByteRange fillRowRange(org.apache.hadoop.hbase.Cell, org.apache.hadoop.hbase.util.ByteRange);
    Code:
       0: aload_0
       1: aload_1
       2: invokestatic  #3                  // Method org/apache/hadoop/hbase/PrivateCellUtil.fillRowRange:(Lorg/apache/hadoop/hbase/Cell;Lorg/apache/hadoop/hbase/util/ByteRange;)Lorg/apache/hadoop/hbase/util/ByteRange;
       5: areturn

  public static org.apache.hadoop.hbase.util.ByteRange fillFamilyRange(org.apache.hadoop.hbase.Cell, org.apache.hadoop.hbase.util.ByteRange);
    Code:
       0: aload_0
       1: aload_1
       2: invokestatic  #4                  // Method org/apache/hadoop/hbase/PrivateCellUtil.fillFamilyRange:(Lorg/apache/hadoop/hbase/Cell;Lorg/apache/hadoop/hbase/util/ByteRange;)Lorg/apache/hadoop/hbase/util/ByteRange;
       5: areturn

  public static org.apache.hadoop.hbase.util.ByteRange fillQualifierRange(org.apache.hadoop.hbase.Cell, org.apache.hadoop.hbase.util.ByteRange);
    Code:
       0: aload_0
       1: aload_1
       2: invokestatic  #5                  // Method org/apache/hadoop/hbase/PrivateCellUtil.fillQualifierRange:(Lorg/apache/hadoop/hbase/Cell;Lorg/apache/hadoop/hbase/util/ByteRange;)Lorg/apache/hadoop/hbase/util/ByteRange;
       5: areturn

  public static org.apache.hadoop.hbase.util.ByteRange fillValueRange(org.apache.hadoop.hbase.Cell, org.apache.hadoop.hbase.util.ByteRange);
    Code:
       0: aload_0
       1: aload_1
       2: invokestatic  #6                  // Method org/apache/hadoop/hbase/PrivateCellUtil.fillValueRange:(Lorg/apache/hadoop/hbase/Cell;Lorg/apache/hadoop/hbase/util/ByteRange;)Lorg/apache/hadoop/hbase/util/ByteRange;
       5: areturn

  public static org.apache.hadoop.hbase.util.ByteRange fillTagRange(org.apache.hadoop.hbase.Cell, org.apache.hadoop.hbase.util.ByteRange);
    Code:
       0: aload_0
       1: aload_1
       2: invokestatic  #7                  // Method org/apache/hadoop/hbase/PrivateCellUtil.fillTagRange:(Lorg/apache/hadoop/hbase/Cell;Lorg/apache/hadoop/hbase/util/ByteRange;)Lorg/apache/hadoop/hbase/util/ByteRange;
       5: areturn

  public static byte[] cloneRow(org.apache.hadoop.hbase.Cell);
    Code:
       0: aload_0
       1: invokeinterface #8,  1            // InterfaceMethod org/apache/hadoop/hbase/Cell.getRowLength:()S
       6: newarray       byte
       8: astore_1
       9: aload_0
      10: aload_1
      11: iconst_0
      12: invokestatic  #9                  // Method copyRowTo:(Lorg/apache/hadoop/hbase/Cell;[BI)I
      15: pop
      16: aload_1
      17: areturn

  public static byte[] cloneFamily(org.apache.hadoop.hbase.Cell);
    Code:
       0: aload_0
       1: invokeinterface #10,  1           // InterfaceMethod org/apache/hadoop/hbase/Cell.getFamilyLength:()B
       6: newarray       byte
       8: astore_1
       9: aload_0
      10: aload_1
      11: iconst_0
      12: invokestatic  #11                 // Method copyFamilyTo:(Lorg/apache/hadoop/hbase/Cell;[BI)I
      15: pop
      16: aload_1
      17: areturn

  public static byte[] cloneQualifier(org.apache.hadoop.hbase.Cell);
    Code:
       0: aload_0
       1: invokeinterface #12,  1           // InterfaceMethod org/apache/hadoop/hbase/Cell.getQualifierLength:()I
       6: newarray       byte
       8: astore_1
       9: aload_0
      10: aload_1
      11: iconst_0
      12: invokestatic  #13                 // Method copyQualifierTo:(Lorg/apache/hadoop/hbase/Cell;[BI)I
      15: pop
      16: aload_1
      17: areturn

  public static byte[] cloneValue(org.apache.hadoop.hbase.Cell);
    Code:
       0: aload_0
       1: invokeinterface #14,  1           // InterfaceMethod org/apache/hadoop/hbase/Cell.getValueLength:()I
       6: newarray       byte
       8: astore_1
       9: aload_0
      10: aload_1
      11: iconst_0
      12: invokestatic  #15                 // Method copyValueTo:(Lorg/apache/hadoop/hbase/Cell;[BI)I
      15: pop
      16: aload_1
      17: areturn

  public static byte[] cloneTags(org.apache.hadoop.hbase.Cell);
    Code:
       0: aload_0
       1: invokestatic  #16                 // Method org/apache/hadoop/hbase/PrivateCellUtil.cloneTags:(Lorg/apache/hadoop/hbase/Cell;)[B
       4: areturn

  public static byte[] getTagArray(org.apache.hadoop.hbase.Cell);
    Code:
       0: aload_0
       1: invokestatic  #16                 // Method org/apache/hadoop/hbase/PrivateCellUtil.cloneTags:(Lorg/apache/hadoop/hbase/Cell;)[B
       4: areturn

  public static byte[] makeColumn(byte[], byte[]);
    Code:
       0: aload_0
       1: getstatic     #17                 // Field org/apache/hadoop/hbase/KeyValue.COLUMN_FAMILY_DELIM_ARRAY:[B
       4: aload_1
       5: invokestatic  #18                 // Method org/apache/hadoop/hbase/util/Bytes.add:([B[B[B)[B
       8: areturn

  public static byte[][] parseColumn(byte[]);
    Code:
       0: aload_0
       1: iconst_0
       2: aload_0
       3: arraylength
       4: bipush        58
       6: invokestatic  #19                 // Method org/apache/hadoop/hbase/KeyValue.getDelimiter:([BIII)I
       9: istore_1
      10: iload_1
      11: iconst_m1
      12: if_icmpne     24
      15: iconst_1
      16: anewarray     #20                 // class "[B"
      19: dup
      20: iconst_0
      21: aload_0
      22: aastore
      23: areturn
      24: iload_1
      25: aload_0
      26: arraylength
      27: iconst_1
      28: isub
      29: if_icmpne     63
      32: aload_0
      33: arraylength
      34: iconst_1
      35: isub
      36: newarray       byte
      38: astore_2
      39: aload_0
      40: iconst_0
      41: aload_2
      42: iconst_0
      43: aload_2
      44: arraylength
      45: invokestatic  #21                 // Method java/lang/System.arraycopy:(Ljava/lang/Object;ILjava/lang/Object;II)V
      48: iconst_2
      49: anewarray     #20                 // class "[B"
      52: dup
      53: iconst_0
      54: aload_2
      55: aastore
      56: dup
      57: iconst_1
      58: getstatic     #22                 // Field org/apache/hadoop/hbase/HConstants.EMPTY_BYTE_ARRAY:[B
      61: aastore
      62: areturn
      63: iconst_2
      64: anewarray     #20                 // class "[B"
      67: astore_2
      68: aload_2
      69: iconst_0
      70: iload_1
      71: newarray       byte
      73: aastore
      74: aload_0
      75: iconst_0
      76: aload_2
      77: iconst_0
      78: aaload
      79: iconst_0
      80: iload_1
      81: invokestatic  #21                 // Method java/lang/System.arraycopy:(Ljava/lang/Object;ILjava/lang/Object;II)V
      84: aload_0
      85: arraylength
      86: iload_1
      87: iconst_1
      88: iadd
      89: isub
      90: istore_3
      91: aload_2
      92: iconst_1
      93: iload_3
      94: newarray       byte
      96: aastore
      97: aload_0
      98: iload_1
      99: iconst_1
     100: iadd
     101: aload_2
     102: iconst_1
     103: aaload
     104: iconst_0
     105: iload_3
     106: invokestatic  #21                 // Method java/lang/System.arraycopy:(Ljava/lang/Object;ILjava/lang/Object;II)V
     109: aload_2
     110: areturn

  public static int copyRowTo(org.apache.hadoop.hbase.Cell, byte[], int);
    Code:
       0: aload_0
       1: invokeinterface #8,  1            // InterfaceMethod org/apache/hadoop/hbase/Cell.getRowLength:()S
       6: istore_3
       7: aload_0
       8: instanceof    #23                 // class org/apache/hadoop/hbase/ByteBufferExtendedCell
      11: ifeq          37
      14: aload_1
      15: aload_0
      16: checkcast     #23                 // class org/apache/hadoop/hbase/ByteBufferExtendedCell
      19: invokevirtual #24                 // Method org/apache/hadoop/hbase/ByteBufferExtendedCell.getRowByteBuffer:()Ljava/nio/ByteBuffer;
      22: aload_0
      23: checkcast     #23                 // class org/apache/hadoop/hbase/ByteBufferExtendedCell
      26: invokevirtual #25                 // Method org/apache/hadoop/hbase/ByteBufferExtendedCell.getRowPosition:()I
      29: iload_2
      30: iload_3
      31: invokestatic  #26                 // Method org/apache/hadoop/hbase/util/ByteBufferUtils.copyFromBufferToArray:([BLjava/nio/ByteBuffer;III)V
      34: goto          55
      37: aload_0
      38: invokeinterface #27,  1           // InterfaceMethod org/apache/hadoop/hbase/Cell.getRowArray:()[B
      43: aload_0
      44: invokeinterface #28,  1           // InterfaceMethod org/apache/hadoop/hbase/Cell.getRowOffset:()I
      49: aload_1
      50: iload_2
      51: iload_3
      52: invokestatic  #21                 // Method java/lang/System.arraycopy:(Ljava/lang/Object;ILjava/lang/Object;II)V
      55: iload_2
      56: iload_3
      57: iadd
      58: ireturn

  public static int copyRowTo(org.apache.hadoop.hbase.Cell, java.nio.ByteBuffer, int);
    Code:
       0: aload_0
       1: invokeinterface #8,  1            // InterfaceMethod org/apache/hadoop/hbase/Cell.getRowLength:()S
       6: istore_3
       7: aload_0
       8: instanceof    #23                 // class org/apache/hadoop/hbase/ByteBufferExtendedCell
      11: ifeq          37
      14: aload_0
      15: checkcast     #23                 // class org/apache/hadoop/hbase/ByteBufferExtendedCell
      18: invokevirtual #24                 // Method org/apache/hadoop/hbase/ByteBufferExtendedCell.getRowByteBuffer:()Ljava/nio/ByteBuffer;
      21: aload_1
      22: aload_0
      23: checkcast     #23                 // class org/apache/hadoop/hbase/ByteBufferExtendedCell
      26: invokevirtual #25                 // Method org/apache/hadoop/hbase/ByteBufferExtendedCell.getRowPosition:()I
      29: iload_2
      30: iload_3
      31: invokestatic  #29                 // Method org/apache/hadoop/hbase/util/ByteBufferUtils.copyFromBufferToBuffer:(Ljava/nio/ByteBuffer;Ljava/nio/ByteBuffer;III)V
      34: goto          55
      37: aload_1
      38: iload_2
      39: aload_0
      40: invokeinterface #27,  1           // InterfaceMethod org/apache/hadoop/hbase/Cell.getRowArray:()[B
      45: aload_0
      46: invokeinterface #28,  1           // InterfaceMethod org/apache/hadoop/hbase/Cell.getRowOffset:()I
      51: iload_3
      52: invokestatic  #30                 // Method org/apache/hadoop/hbase/util/ByteBufferUtils.copyFromArrayToBuffer:(Ljava/nio/ByteBuffer;I[BII)V
      55: iload_2
      56: iload_3
      57: iadd
      58: ireturn

  public static byte[] copyRow(org.apache.hadoop.hbase.Cell);
    Code:
       0: aload_0
       1: instanceof    #23                 // class org/apache/hadoop/hbase/ByteBufferExtendedCell
       4: ifeq          39
       7: aload_0
       8: checkcast     #23                 // class org/apache/hadoop/hbase/ByteBufferExtendedCell
      11: invokevirtual #24                 // Method org/apache/hadoop/hbase/ByteBufferExtendedCell.getRowByteBuffer:()Ljava/nio/ByteBuffer;
      14: aload_0
      15: checkcast     #23                 // class org/apache/hadoop/hbase/ByteBufferExtendedCell
      18: invokevirtual #25                 // Method org/apache/hadoop/hbase/ByteBufferExtendedCell.getRowPosition:()I
      21: aload_0
      22: checkcast     #23                 // class org/apache/hadoop/hbase/ByteBufferExtendedCell
      25: invokevirtual #25                 // Method org/apache/hadoop/hbase/ByteBufferExtendedCell.getRowPosition:()I
      28: aload_0
      29: invokeinterface #8,  1            // InterfaceMethod org/apache/hadoop/hbase/Cell.getRowLength:()S
      34: iadd
      35: invokestatic  #31                 // Method org/apache/hadoop/hbase/util/ByteBufferUtils.copyOfRange:(Ljava/nio/ByteBuffer;II)[B
      38: areturn
      39: aload_0
      40: invokeinterface #27,  1           // InterfaceMethod org/apache/hadoop/hbase/Cell.getRowArray:()[B
      45: aload_0
      46: invokeinterface #28,  1           // InterfaceMethod org/apache/hadoop/hbase/Cell.getRowOffset:()I
      51: aload_0
      52: invokeinterface #28,  1           // InterfaceMethod org/apache/hadoop/hbase/Cell.getRowOffset:()I
      57: aload_0
      58: invokeinterface #8,  1            // InterfaceMethod org/apache/hadoop/hbase/Cell.getRowLength:()S
      63: iadd
      64: invokestatic  #32                 // Method java/util/Arrays.copyOfRange:([BII)[B
      67: areturn

  public static int copyFamilyTo(org.apache.hadoop.hbase.Cell, byte[], int);
    Code:
       0: aload_0
       1: invokeinterface #10,  1           // InterfaceMethod org/apache/hadoop/hbase/Cell.getFamilyLength:()B
       6: istore_3
       7: aload_0
       8: instanceof    #23                 // class org/apache/hadoop/hbase/ByteBufferExtendedCell
      11: ifeq          37
      14: aload_1
      15: aload_0
      16: checkcast     #23                 // class org/apache/hadoop/hbase/ByteBufferExtendedCell
      19: invokevirtual #33                 // Method org/apache/hadoop/hbase/ByteBufferExtendedCell.getFamilyByteBuffer:()Ljava/nio/ByteBuffer;
      22: aload_0
      23: checkcast     #23                 // class org/apache/hadoop/hbase/ByteBufferExtendedCell
      26: invokevirtual #34                 // Method org/apache/hadoop/hbase/ByteBufferExtendedCell.getFamilyPosition:()I
      29: iload_2
      30: iload_3
      31: invokestatic  #26                 // Method org/apache/hadoop/hbase/util/ByteBufferUtils.copyFromBufferToArray:([BLjava/nio/ByteBuffer;III)V
      34: goto          55
      37: aload_0
      38: invokeinterface #35,  1           // InterfaceMethod org/apache/hadoop/hbase/Cell.getFamilyArray:()[B
      43: aload_0
      44: invokeinterface #36,  1           // InterfaceMethod org/apache/hadoop/hbase/Cell.getFamilyOffset:()I
      49: aload_1
      50: iload_2
      51: iload_3
      52: invokestatic  #21                 // Method java/lang/System.arraycopy:(Ljava/lang/Object;ILjava/lang/Object;II)V
      55: iload_2
      56: iload_3
      57: iadd
      58: ireturn

  public static int copyFamilyTo(org.apache.hadoop.hbase.Cell, java.nio.ByteBuffer, int);
    Code:
       0: aload_0
       1: invokeinterface #10,  1           // InterfaceMethod org/apache/hadoop/hbase/Cell.getFamilyLength:()B
       6: istore_3
       7: aload_0
       8: instanceof    #23                 // class org/apache/hadoop/hbase/ByteBufferExtendedCell
      11: ifeq          37
      14: aload_0
      15: checkcast     #23                 // class org/apache/hadoop/hbase/ByteBufferExtendedCell
      18: invokevirtual #33                 // Method org/apache/hadoop/hbase/ByteBufferExtendedCell.getFamilyByteBuffer:()Ljava/nio/ByteBuffer;
      21: aload_1
      22: aload_0
      23: checkcast     #23                 // class org/apache/hadoop/hbase/ByteBufferExtendedCell
      26: invokevirtual #34                 // Method org/apache/hadoop/hbase/ByteBufferExtendedCell.getFamilyPosition:()I
      29: iload_2
      30: iload_3
      31: invokestatic  #29                 // Method org/apache/hadoop/hbase/util/ByteBufferUtils.copyFromBufferToBuffer:(Ljava/nio/ByteBuffer;Ljava/nio/ByteBuffer;III)V
      34: goto          55
      37: aload_1
      38: iload_2
      39: aload_0
      40: invokeinterface #35,  1           // InterfaceMethod org/apache/hadoop/hbase/Cell.getFamilyArray:()[B
      45: aload_0
      46: invokeinterface #36,  1           // InterfaceMethod org/apache/hadoop/hbase/Cell.getFamilyOffset:()I
      51: iload_3
      52: invokestatic  #30                 // Method org/apache/hadoop/hbase/util/ByteBufferUtils.copyFromArrayToBuffer:(Ljava/nio/ByteBuffer;I[BII)V
      55: iload_2
      56: iload_3
      57: iadd
      58: ireturn

  public static int copyQualifierTo(org.apache.hadoop.hbase.Cell, byte[], int);
    Code:
       0: aload_0
       1: invokeinterface #12,  1           // InterfaceMethod org/apache/hadoop/hbase/Cell.getQualifierLength:()I
       6: istore_3
       7: aload_0
       8: instanceof    #23                 // class org/apache/hadoop/hbase/ByteBufferExtendedCell
      11: ifeq          37
      14: aload_1
      15: aload_0
      16: checkcast     #23                 // class org/apache/hadoop/hbase/ByteBufferExtendedCell
      19: invokevirtual #37                 // Method org/apache/hadoop/hbase/ByteBufferExtendedCell.getQualifierByteBuffer:()Ljava/nio/ByteBuffer;
      22: aload_0
      23: checkcast     #23                 // class org/apache/hadoop/hbase/ByteBufferExtendedCell
      26: invokevirtual #38                 // Method org/apache/hadoop/hbase/ByteBufferExtendedCell.getQualifierPosition:()I
      29: iload_2
      30: iload_3
      31: invokestatic  #26                 // Method org/apache/hadoop/hbase/util/ByteBufferUtils.copyFromBufferToArray:([BLjava/nio/ByteBuffer;III)V
      34: goto          55
      37: aload_0
      38: invokeinterface #39,  1           // InterfaceMethod org/apache/hadoop/hbase/Cell.getQualifierArray:()[B
      43: aload_0
      44: invokeinterface #40,  1           // InterfaceMethod org/apache/hadoop/hbase/Cell.getQualifierOffset:()I
      49: aload_1
      50: iload_2
      51: iload_3
      52: invokestatic  #21                 // Method java/lang/System.arraycopy:(Ljava/lang/Object;ILjava/lang/Object;II)V
      55: iload_2
      56: iload_3
      57: iadd
      58: ireturn

  public static int copyQualifierTo(org.apache.hadoop.hbase.Cell, java.nio.ByteBuffer, int);
    Code:
       0: aload_0
       1: invokeinterface #12,  1           // InterfaceMethod org/apache/hadoop/hbase/Cell.getQualifierLength:()I
       6: istore_3
       7: aload_0
       8: instanceof    #23                 // class org/apache/hadoop/hbase/ByteBufferExtendedCell
      11: ifeq          37
      14: aload_0
      15: checkcast     #23                 // class org/apache/hadoop/hbase/ByteBufferExtendedCell
      18: invokevirtual #37                 // Method org/apache/hadoop/hbase/ByteBufferExtendedCell.getQualifierByteBuffer:()Ljava/nio/ByteBuffer;
      21: aload_1
      22: aload_0
      23: checkcast     #23                 // class org/apache/hadoop/hbase/ByteBufferExtendedCell
      26: invokevirtual #38                 // Method org/apache/hadoop/hbase/ByteBufferExtendedCell.getQualifierPosition:()I
      29: iload_2
      30: iload_3
      31: invokestatic  #29                 // Method org/apache/hadoop/hbase/util/ByteBufferUtils.copyFromBufferToBuffer:(Ljava/nio/ByteBuffer;Ljava/nio/ByteBuffer;III)V
      34: goto          55
      37: aload_1
      38: iload_2
      39: aload_0
      40: invokeinterface #39,  1           // InterfaceMethod org/apache/hadoop/hbase/Cell.getQualifierArray:()[B
      45: aload_0
      46: invokeinterface #40,  1           // InterfaceMethod org/apache/hadoop/hbase/Cell.getQualifierOffset:()I
      51: iload_3
      52: invokestatic  #30                 // Method org/apache/hadoop/hbase/util/ByteBufferUtils.copyFromArrayToBuffer:(Ljava/nio/ByteBuffer;I[BII)V
      55: iload_2
      56: iload_3
      57: iadd
      58: ireturn

  public static int copyValueTo(org.apache.hadoop.hbase.Cell, byte[], int);
    Code:
       0: aload_0
       1: invokeinterface #14,  1           // InterfaceMethod org/apache/hadoop/hbase/Cell.getValueLength:()I
       6: istore_3
       7: aload_0
       8: instanceof    #23                 // class org/apache/hadoop/hbase/ByteBufferExtendedCell
      11: ifeq          37
      14: aload_1
      15: aload_0
      16: checkcast     #23                 // class org/apache/hadoop/hbase/ByteBufferExtendedCell
      19: invokevirtual #41                 // Method org/apache/hadoop/hbase/ByteBufferExtendedCell.getValueByteBuffer:()Ljava/nio/ByteBuffer;
      22: aload_0
      23: checkcast     #23                 // class org/apache/hadoop/hbase/ByteBufferExtendedCell
      26: invokevirtual #42                 // Method org/apache/hadoop/hbase/ByteBufferExtendedCell.getValuePosition:()I
      29: iload_2
      30: iload_3
      31: invokestatic  #26                 // Method org/apache/hadoop/hbase/util/ByteBufferUtils.copyFromBufferToArray:([BLjava/nio/ByteBuffer;III)V
      34: goto          55
      37: aload_0
      38: invokeinterface #43,  1           // InterfaceMethod org/apache/hadoop/hbase/Cell.getValueArray:()[B
      43: aload_0
      44: invokeinterface #44,  1           // InterfaceMethod org/apache/hadoop/hbase/Cell.getValueOffset:()I
      49: aload_1
      50: iload_2
      51: iload_3
      52: invokestatic  #21                 // Method java/lang/System.arraycopy:(Ljava/lang/Object;ILjava/lang/Object;II)V
      55: iload_2
      56: iload_3
      57: iadd
      58: ireturn

  public static int copyValueTo(org.apache.hadoop.hbase.Cell, java.nio.ByteBuffer, int);
    Code:
       0: aload_0
       1: invokeinterface #14,  1           // InterfaceMethod org/apache/hadoop/hbase/Cell.getValueLength:()I
       6: istore_3
       7: aload_0
       8: instanceof    #23                 // class org/apache/hadoop/hbase/ByteBufferExtendedCell
      11: ifeq          37
      14: aload_0
      15: checkcast     #23                 // class org/apache/hadoop/hbase/ByteBufferExtendedCell
      18: invokevirtual #41                 // Method org/apache/hadoop/hbase/ByteBufferExtendedCell.getValueByteBuffer:()Ljava/nio/ByteBuffer;
      21: aload_1
      22: aload_0
      23: checkcast     #23                 // class org/apache/hadoop/hbase/ByteBufferExtendedCell
      26: invokevirtual #42                 // Method org/apache/hadoop/hbase/ByteBufferExtendedCell.getValuePosition:()I
      29: iload_2
      30: iload_3
      31: invokestatic  #29                 // Method org/apache/hadoop/hbase/util/ByteBufferUtils.copyFromBufferToBuffer:(Ljava/nio/ByteBuffer;Ljava/nio/ByteBuffer;III)V
      34: goto          55
      37: aload_1
      38: iload_2
      39: aload_0
      40: invokeinterface #43,  1           // InterfaceMethod org/apache/hadoop/hbase/Cell.getValueArray:()[B
      45: aload_0
      46: invokeinterface #44,  1           // InterfaceMethod org/apache/hadoop/hbase/Cell.getValueOffset:()I
      51: iload_3
      52: invokestatic  #30                 // Method org/apache/hadoop/hbase/util/ByteBufferUtils.copyFromArrayToBuffer:(Ljava/nio/ByteBuffer;I[BII)V
      55: iload_2
      56: iload_3
      57: iadd
      58: ireturn

  public static int copyTagTo(org.apache.hadoop.hbase.Cell, byte[], int);
    Code:
       0: aload_0
       1: aload_1
       2: iload_2
       3: invokestatic  #45                 // Method org/apache/hadoop/hbase/PrivateCellUtil.copyTagsTo:(Lorg/apache/hadoop/hbase/Cell;[BI)I
       6: ireturn

  public static int copyTagTo(org.apache.hadoop.hbase.Cell, java.nio.ByteBuffer, int);
    Code:
       0: aload_0
       1: aload_1
       2: iload_2
       3: invokestatic  #46                 // Method org/apache/hadoop/hbase/PrivateCellUtil.copyTagsTo:(Lorg/apache/hadoop/hbase/Cell;Ljava/nio/ByteBuffer;I)I
       6: ireturn

  public static byte getRowByte(org.apache.hadoop.hbase.Cell, int);
    Code:
       0: aload_0
       1: iload_1
       2: invokestatic  #47                 // Method org/apache/hadoop/hbase/PrivateCellUtil.getRowByte:(Lorg/apache/hadoop/hbase/Cell;I)B
       5: ireturn

  public static java.nio.ByteBuffer getValueBufferShallowCopy(org.apache.hadoop.hbase.Cell);
    Code:
       0: aload_0
       1: invokestatic  #48                 // Method org/apache/hadoop/hbase/PrivateCellUtil.getValueBufferShallowCopy:(Lorg/apache/hadoop/hbase/Cell;)Ljava/nio/ByteBuffer;
       4: areturn

  public static java.nio.ByteBuffer getQualifierBufferShallowCopy(org.apache.hadoop.hbase.Cell);
    Code:
       0: aload_0
       1: invokeinterface #39,  1           // InterfaceMethod org/apache/hadoop/hbase/Cell.getQualifierArray:()[B
       6: aload_0
       7: invokeinterface #40,  1           // InterfaceMethod org/apache/hadoop/hbase/Cell.getQualifierOffset:()I
      12: aload_0
      13: invokeinterface #12,  1           // InterfaceMethod org/apache/hadoop/hbase/Cell.getQualifierLength:()I
      18: invokestatic  #49                 // Method java/nio/ByteBuffer.wrap:([BII)Ljava/nio/ByteBuffer;
      21: astore_1
      22: aload_1
      23: areturn

  public static org.apache.hadoop.hbase.Cell createCell(byte[], byte[], byte[], long, byte, byte[]);
    Code:
       0: getstatic     #50                 // Field org/apache/hadoop/hbase/CellBuilderType.DEEP_COPY:Lorg/apache/hadoop/hbase/CellBuilderType;
       3: invokestatic  #51                 // Method org/apache/hadoop/hbase/ExtendedCellBuilderFactory.create:(Lorg/apache/hadoop/hbase/CellBuilderType;)Lorg/apache/hadoop/hbase/ExtendedCellBuilder;
       6: aload_0
       7: invokeinterface #52,  2           // InterfaceMethod org/apache/hadoop/hbase/ExtendedCellBuilder.setRow:([B)Lorg/apache/hadoop/hbase/ExtendedCellBuilder;
      12: aload_1
      13: invokeinterface #53,  2           // InterfaceMethod org/apache/hadoop/hbase/ExtendedCellBuilder.setFamily:([B)Lorg/apache/hadoop/hbase/ExtendedCellBuilder;
      18: aload_2
      19: invokeinterface #54,  2           // InterfaceMethod org/apache/hadoop/hbase/ExtendedCellBuilder.setQualifier:([B)Lorg/apache/hadoop/hbase/ExtendedCellBuilder;
      24: lload_3
      25: invokeinterface #55,  3           // InterfaceMethod org/apache/hadoop/hbase/ExtendedCellBuilder.setTimestamp:(J)Lorg/apache/hadoop/hbase/ExtendedCellBuilder;
      30: iload         5
      32: invokeinterface #56,  2           // InterfaceMethod org/apache/hadoop/hbase/ExtendedCellBuilder.setType:(B)Lorg/apache/hadoop/hbase/ExtendedCellBuilder;
      37: aload         6
      39: invokeinterface #57,  2           // InterfaceMethod org/apache/hadoop/hbase/ExtendedCellBuilder.setValue:([B)Lorg/apache/hadoop/hbase/ExtendedCellBuilder;
      44: invokeinterface #58,  1           // InterfaceMethod org/apache/hadoop/hbase/ExtendedCellBuilder.build:()Lorg/apache/hadoop/hbase/ExtendedCell;
      49: areturn

  public static org.apache.hadoop.hbase.Cell createCell(byte[], int, int, byte[], int, int, byte[], int, int);
    Code:
       0: getstatic     #50                 // Field org/apache/hadoop/hbase/CellBuilderType.DEEP_COPY:Lorg/apache/hadoop/hbase/CellBuilderType;
       3: invokestatic  #51                 // Method org/apache/hadoop/hbase/ExtendedCellBuilderFactory.create:(Lorg/apache/hadoop/hbase/CellBuilderType;)Lorg/apache/hadoop/hbase/ExtendedCellBuilder;
       6: aload_0
       7: iload_1
       8: iload_2
       9: invokeinterface #59,  4           // InterfaceMethod org/apache/hadoop/hbase/ExtendedCellBuilder.setRow:([BII)Lorg/apache/hadoop/hbase/ExtendedCellBuilder;
      14: aload_3
      15: iload         4
      17: iload         5
      19: invokeinterface #60,  4           // InterfaceMethod org/apache/hadoop/hbase/ExtendedCellBuilder.setFamily:([BII)Lorg/apache/hadoop/hbase/ExtendedCellBuilder;
      24: aload         6
      26: iload         7
      28: iload         8
      30: invokeinterface #61,  4           // InterfaceMethod org/apache/hadoop/hbase/ExtendedCellBuilder.setQualifier:([BII)Lorg/apache/hadoop/hbase/ExtendedCellBuilder;
      35: ldc2_w        #63                 // long 9223372036854775807l
      38: invokeinterface #55,  3           // InterfaceMethod org/apache/hadoop/hbase/ExtendedCellBuilder.setTimestamp:(J)Lorg/apache/hadoop/hbase/ExtendedCellBuilder;
      43: getstatic     #65                 // Field org/apache/hadoop/hbase/KeyValue$Type.Maximum:Lorg/apache/hadoop/hbase/KeyValue$Type;
      46: invokevirtual #66                 // Method org/apache/hadoop/hbase/KeyValue$Type.getCode:()B
      49: invokeinterface #56,  2           // InterfaceMethod org/apache/hadoop/hbase/ExtendedCellBuilder.setType:(B)Lorg/apache/hadoop/hbase/ExtendedCellBuilder;
      54: getstatic     #22                 // Field org/apache/hadoop/hbase/HConstants.EMPTY_BYTE_ARRAY:[B
      57: iconst_0
      58: getstatic     #22                 // Field org/apache/hadoop/hbase/HConstants.EMPTY_BYTE_ARRAY:[B
      61: arraylength
      62: invokeinterface #67,  4           // InterfaceMethod org/apache/hadoop/hbase/ExtendedCellBuilder.setValue:([BII)Lorg/apache/hadoop/hbase/ExtendedCellBuilder;
      67: invokeinterface #58,  1           // InterfaceMethod org/apache/hadoop/hbase/ExtendedCellBuilder.build:()Lorg/apache/hadoop/hbase/ExtendedCell;
      72: areturn

  public static org.apache.hadoop.hbase.Cell createCell(byte[], byte[], byte[], long, byte, byte[], long);
    Code:
       0: aload_0
       1: aload_1
       2: aload_2
       3: lload_3
       4: iload         5
       6: aload         6
       8: aconst_null
       9: lload         7
      11: invokestatic  #68                 // Method createCell:([B[B[BJB[B[BJ)Lorg/apache/hadoop/hbase/Cell;
      14: areturn

  public static org.apache.hadoop.hbase.Cell createCell(byte[], byte[], byte[], long, byte, byte[], byte[], long);
    Code:
       0: getstatic     #50                 // Field org/apache/hadoop/hbase/CellBuilderType.DEEP_COPY:Lorg/apache/hadoop/hbase/CellBuilderType;
       3: invokestatic  #51                 // Method org/apache/hadoop/hbase/ExtendedCellBuilderFactory.create:(Lorg/apache/hadoop/hbase/CellBuilderType;)Lorg/apache/hadoop/hbase/ExtendedCellBuilder;
       6: aload_0
       7: invokeinterface #52,  2           // InterfaceMethod org/apache/hadoop/hbase/ExtendedCellBuilder.setRow:([B)Lorg/apache/hadoop/hbase/ExtendedCellBuilder;
      12: aload_1
      13: invokeinterface #53,  2           // InterfaceMethod org/apache/hadoop/hbase/ExtendedCellBuilder.setFamily:([B)Lorg/apache/hadoop/hbase/ExtendedCellBuilder;
      18: aload_2
      19: invokeinterface #54,  2           // InterfaceMethod org/apache/hadoop/hbase/ExtendedCellBuilder.setQualifier:([B)Lorg/apache/hadoop/hbase/ExtendedCellBuilder;
      24: lload_3
      25: invokeinterface #55,  3           // InterfaceMethod org/apache/hadoop/hbase/ExtendedCellBuilder.setTimestamp:(J)Lorg/apache/hadoop/hbase/ExtendedCellBuilder;
      30: iload         5
      32: invokeinterface #56,  2           // InterfaceMethod org/apache/hadoop/hbase/ExtendedCellBuilder.setType:(B)Lorg/apache/hadoop/hbase/ExtendedCellBuilder;
      37: aload         6
      39: invokeinterface #57,  2           // InterfaceMethod org/apache/hadoop/hbase/ExtendedCellBuilder.setValue:([B)Lorg/apache/hadoop/hbase/ExtendedCellBuilder;
      44: aload         7
      46: invokeinterface #69,  2           // InterfaceMethod org/apache/hadoop/hbase/ExtendedCellBuilder.setTags:([B)Lorg/apache/hadoop/hbase/ExtendedCellBuilder;
      51: lload         8
      53: invokeinterface #70,  3           // InterfaceMethod org/apache/hadoop/hbase/ExtendedCellBuilder.setSequenceId:(J)Lorg/apache/hadoop/hbase/ExtendedCellBuilder;
      58: invokeinterface #58,  1           // InterfaceMethod org/apache/hadoop/hbase/ExtendedCellBuilder.build:()Lorg/apache/hadoop/hbase/ExtendedCell;
      63: areturn

  public static org.apache.hadoop.hbase.Cell createCell(byte[], byte[], byte[], long, org.apache.hadoop.hbase.KeyValue$Type, byte[], byte[]);
    Code:
       0: aload_0
       1: aload_1
       2: aload_2
       3: lload_3
       4: aload         5
       6: invokevirtual #66                 // Method org/apache/hadoop/hbase/KeyValue$Type.getCode:()B
       9: aload         6
      11: aload         7
      13: lconst_0
      14: invokestatic  #68                 // Method createCell:([B[B[BJB[B[BJ)Lorg/apache/hadoop/hbase/Cell;
      17: areturn

  public static org.apache.hadoop.hbase.Cell createCell(byte[]);
    Code:
       0: aload_0
       1: getstatic     #22                 // Field org/apache/hadoop/hbase/HConstants.EMPTY_BYTE_ARRAY:[B
       4: invokestatic  #71                 // Method createCell:([B[B)Lorg/apache/hadoop/hbase/Cell;
       7: areturn

  public static org.apache.hadoop.hbase.Cell createCell(byte[], byte[]);
    Code:
       0: aload_0
       1: getstatic     #22                 // Field org/apache/hadoop/hbase/HConstants.EMPTY_BYTE_ARRAY:[B
       4: getstatic     #22                 // Field org/apache/hadoop/hbase/HConstants.EMPTY_BYTE_ARRAY:[B
       7: ldc2_w        #63                 // long 9223372036854775807l
      10: getstatic     #65                 // Field org/apache/hadoop/hbase/KeyValue$Type.Maximum:Lorg/apache/hadoop/hbase/KeyValue$Type;
      13: invokevirtual #66                 // Method org/apache/hadoop/hbase/KeyValue$Type.getCode:()B
      16: aload_1
      17: invokestatic  #72                 // Method createCell:([B[B[BJB[B)Lorg/apache/hadoop/hbase/Cell;
      20: areturn

  public static org.apache.hadoop.hbase.Cell createCell(byte[], byte[], byte[]);
    Code:
       0: aload_0
       1: aload_1
       2: aload_2
       3: ldc2_w        #63                 // long 9223372036854775807l
       6: getstatic     #65                 // Field org/apache/hadoop/hbase/KeyValue$Type.Maximum:Lorg/apache/hadoop/hbase/KeyValue$Type;
       9: invokevirtual #66                 // Method org/apache/hadoop/hbase/KeyValue$Type.getCode:()B
      12: getstatic     #22                 // Field org/apache/hadoop/hbase/HConstants.EMPTY_BYTE_ARRAY:[B
      15: invokestatic  #72                 // Method createCell:([B[B[BJB[B)Lorg/apache/hadoop/hbase/Cell;
      18: areturn

  public static org.apache.hadoop.hbase.Cell createCell(org.apache.hadoop.hbase.Cell, java.util.List<org.apache.hadoop.hbase.Tag>);
    Code:
       0: aload_0
       1: aload_1
       2: invokestatic  #73                 // Method org/apache/hadoop/hbase/PrivateCellUtil.createCell:(Lorg/apache/hadoop/hbase/Cell;Ljava/util/List;)Lorg/apache/hadoop/hbase/Cell;
       5: areturn

  public static org.apache.hadoop.hbase.Cell createCell(org.apache.hadoop.hbase.Cell, byte[]);
    Code:
       0: aload_0
       1: aload_1
       2: invokestatic  #74                 // Method org/apache/hadoop/hbase/PrivateCellUtil.createCell:(Lorg/apache/hadoop/hbase/Cell;[B)Lorg/apache/hadoop/hbase/Cell;
       5: areturn

  public static org.apache.hadoop.hbase.Cell createCell(org.apache.hadoop.hbase.Cell, byte[], byte[]);
    Code:
       0: aload_0
       1: aload_1
       2: aload_2
       3: invokestatic  #75                 // Method org/apache/hadoop/hbase/PrivateCellUtil.createCell:(Lorg/apache/hadoop/hbase/Cell;[B[B)Lorg/apache/hadoop/hbase/Cell;
       6: areturn

  public static org.apache.hadoop.hbase.CellScanner createCellScanner(java.util.List<? extends org.apache.hadoop.hbase.CellScannable>);
    Code:
       0: new           #76                 // class org/apache/hadoop/hbase/CellUtil$1
       3: dup
       4: aload_0
       5: invokespecial #77                 // Method org/apache/hadoop/hbase/CellUtil$1."<init>":(Ljava/util/List;)V
       8: areturn

  public static org.apache.hadoop.hbase.CellScanner createCellScanner(java.lang.Iterable<org.apache.hadoop.hbase.Cell>);
    Code:
       0: aload_0
       1: ifnonnull     6
       4: aconst_null
       5: areturn
       6: aload_0
       7: invokeinterface #78,  1           // InterfaceMethod java/lang/Iterable.iterator:()Ljava/util/Iterator;
      12: invokestatic  #79                 // Method createCellScanner:(Ljava/util/Iterator;)Lorg/apache/hadoop/hbase/CellScanner;
      15: areturn

  public static org.apache.hadoop.hbase.CellScanner createCellScanner(java.util.Iterator<org.apache.hadoop.hbase.Cell>);
    Code:
       0: aload_0
       1: ifnonnull     6
       4: aconst_null
       5: areturn
       6: new           #80                 // class org/apache/hadoop/hbase/CellUtil$2
       9: dup
      10: aload_0
      11: invokespecial #81                 // Method org/apache/hadoop/hbase/CellUtil$2."<init>":(Ljava/util/Iterator;)V
      14: areturn

  public static org.apache.hadoop.hbase.CellScanner createCellScanner(org.apache.hadoop.hbase.Cell[]);
    Code:
       0: new           #82                 // class org/apache/hadoop/hbase/CellUtil$3
       3: dup
       4: aload_0
       5: invokespecial #83                 // Method org/apache/hadoop/hbase/CellUtil$3."<init>":([Lorg/apache/hadoop/hbase/Cell;)V
       8: areturn

  public static org.apache.hadoop.hbase.CellScanner createCellScanner(java.util.NavigableMap<byte[], java.util.List<org.apache.hadoop.hbase.Cell>>);
    Code:
       0: new           #84                 // class org/apache/hadoop/hbase/CellUtil$4
       3: dup
       4: aload_0
       5: invokespecial #85                 // Method org/apache/hadoop/hbase/CellUtil$4."<init>":(Ljava/util/NavigableMap;)V
       8: areturn

  public static boolean matchingRow(org.apache.hadoop.hbase.Cell, org.apache.hadoop.hbase.Cell);
    Code:
       0: aload_0
       1: aload_1
       2: invokestatic  #86                 // Method matchingRows:(Lorg/apache/hadoop/hbase/Cell;Lorg/apache/hadoop/hbase/Cell;)Z
       5: ireturn

  public static boolean matchingRow(org.apache.hadoop.hbase.Cell, byte[]);
    Code:
       0: aload_0
       1: aload_1
       2: invokestatic  #87                 // Method matchingRows:(Lorg/apache/hadoop/hbase/Cell;[B)Z
       5: ireturn

  public static boolean matchingRows(org.apache.hadoop.hbase.Cell, byte[]);
    Code:
       0: aload_1
       1: ifnonnull     19
       4: aload_0
       5: invokeinterface #8,  1            // InterfaceMethod org/apache/hadoop/hbase/Cell.getRowLength:()S
      10: ifne          17
      13: iconst_1
      14: goto          18
      17: iconst_0
      18: ireturn
      19: aload_0
      20: aload_1
      21: iconst_0
      22: aload_1
      23: arraylength
      24: invokestatic  #88                 // Method org/apache/hadoop/hbase/PrivateCellUtil.matchingRows:(Lorg/apache/hadoop/hbase/Cell;[BII)Z
      27: ireturn

  public static boolean matchingRow(org.apache.hadoop.hbase.Cell, byte[], int, int);
    Code:
       0: aload_0
       1: aload_1
       2: iload_2
       3: iload_3
       4: invokestatic  #88                 // Method org/apache/hadoop/hbase/PrivateCellUtil.matchingRows:(Lorg/apache/hadoop/hbase/Cell;[BII)Z
       7: ireturn

  public static boolean matchingFamily(org.apache.hadoop.hbase.Cell, org.apache.hadoop.hbase.Cell);
    Code:
       0: aload_0
       1: invokeinterface #10,  1           // InterfaceMethod org/apache/hadoop/hbase/Cell.getFamilyLength:()B
       6: istore_2
       7: aload_1
       8: invokeinterface #10,  1           // InterfaceMethod org/apache/hadoop/hbase/Cell.getFamilyLength:()B
      13: istore_3
      14: aload_0
      15: instanceof    #23                 // class org/apache/hadoop/hbase/ByteBufferExtendedCell
      18: ifeq          62
      21: aload_1
      22: instanceof    #23                 // class org/apache/hadoop/hbase/ByteBufferExtendedCell
      25: ifeq          62
      28: aload_0
      29: checkcast     #23                 // class org/apache/hadoop/hbase/ByteBufferExtendedCell
      32: invokevirtual #33                 // Method org/apache/hadoop/hbase/ByteBufferExtendedCell.getFamilyByteBuffer:()Ljava/nio/ByteBuffer;
      35: aload_0
      36: checkcast     #23                 // class org/apache/hadoop/hbase/ByteBufferExtendedCell
      39: invokevirtual #34                 // Method org/apache/hadoop/hbase/ByteBufferExtendedCell.getFamilyPosition:()I
      42: iload_2
      43: aload_1
      44: checkcast     #23                 // class org/apache/hadoop/hbase/ByteBufferExtendedCell
      47: invokevirtual #33                 // Method org/apache/hadoop/hbase/ByteBufferExtendedCell.getFamilyByteBuffer:()Ljava/nio/ByteBuffer;
      50: aload_1
      51: checkcast     #23                 // class org/apache/hadoop/hbase/ByteBufferExtendedCell
      54: invokevirtual #34                 // Method org/apache/hadoop/hbase/ByteBufferExtendedCell.getFamilyPosition:()I
      57: iload_3
      58: invokestatic  #89                 // Method org/apache/hadoop/hbase/util/ByteBufferUtils.equals:(Ljava/nio/ByteBuffer;IILjava/nio/ByteBuffer;II)Z
      61: ireturn
      62: aload_0
      63: instanceof    #23                 // class org/apache/hadoop/hbase/ByteBufferExtendedCell
      66: ifeq          101
      69: aload_0
      70: checkcast     #23                 // class org/apache/hadoop/hbase/ByteBufferExtendedCell
      73: invokevirtual #33                 // Method org/apache/hadoop/hbase/ByteBufferExtendedCell.getFamilyByteBuffer:()Ljava/nio/ByteBuffer;
      76: aload_0
      77: checkcast     #23                 // class org/apache/hadoop/hbase/ByteBufferExtendedCell
      80: invokevirtual #34                 // Method org/apache/hadoop/hbase/ByteBufferExtendedCell.getFamilyPosition:()I
      83: iload_2
      84: aload_1
      85: invokeinterface #35,  1           // InterfaceMethod org/apache/hadoop/hbase/Cell.getFamilyArray:()[B
      90: aload_1
      91: invokeinterface #36,  1           // InterfaceMethod org/apache/hadoop/hbase/Cell.getFamilyOffset:()I
      96: iload_3
      97: invokestatic  #90                 // Method org/apache/hadoop/hbase/util/ByteBufferUtils.equals:(Ljava/nio/ByteBuffer;II[BII)Z
     100: ireturn
     101: aload_1
     102: instanceof    #23                 // class org/apache/hadoop/hbase/ByteBufferExtendedCell
     105: ifeq          140
     108: aload_1
     109: checkcast     #23                 // class org/apache/hadoop/hbase/ByteBufferExtendedCell
     112: invokevirtual #33                 // Method org/apache/hadoop/hbase/ByteBufferExtendedCell.getFamilyByteBuffer:()Ljava/nio/ByteBuffer;
     115: aload_1
     116: checkcast     #23                 // class org/apache/hadoop/hbase/ByteBufferExtendedCell
     119: invokevirtual #34                 // Method org/apache/hadoop/hbase/ByteBufferExtendedCell.getFamilyPosition:()I
     122: iload_3
     123: aload_0
     124: invokeinterface #35,  1           // InterfaceMethod org/apache/hadoop/hbase/Cell.getFamilyArray:()[B
     129: aload_0
     130: invokeinterface #36,  1           // InterfaceMethod org/apache/hadoop/hbase/Cell.getFamilyOffset:()I
     135: iload_2
     136: invokestatic  #90                 // Method org/apache/hadoop/hbase/util/ByteBufferUtils.equals:(Ljava/nio/ByteBuffer;II[BII)Z
     139: ireturn
     140: aload_0
     141: invokeinterface #35,  1           // InterfaceMethod org/apache/hadoop/hbase/Cell.getFamilyArray:()[B
     146: aload_0
     147: invokeinterface #36,  1           // InterfaceMethod org/apache/hadoop/hbase/Cell.getFamilyOffset:()I
     152: iload_2
     153: aload_1
     154: invokeinterface #35,  1           // InterfaceMethod org/apache/hadoop/hbase/Cell.getFamilyArray:()[B
     159: aload_1
     160: invokeinterface #36,  1           // InterfaceMethod org/apache/hadoop/hbase/Cell.getFamilyOffset:()I
     165: iload_3
     166: invokestatic  #91                 // Method org/apache/hadoop/hbase/util/Bytes.equals:([BII[BII)Z
     169: ireturn

  public static boolean matchingFamily(org.apache.hadoop.hbase.Cell, byte[]);
    Code:
       0: aload_1
       1: ifnonnull     19
       4: aload_0
       5: invokeinterface #10,  1           // InterfaceMethod org/apache/hadoop/hbase/Cell.getFamilyLength:()B
      10: ifne          17
      13: iconst_1
      14: goto          18
      17: iconst_0
      18: ireturn
      19: aload_0
      20: aload_1
      21: iconst_0
      22: aload_1
      23: arraylength
      24: invokestatic  #92                 // Method matchingFamily:(Lorg/apache/hadoop/hbase/Cell;[BII)Z
      27: ireturn

  public static boolean matchingFamily(org.apache.hadoop.hbase.Cell, byte[], int, int);
    Code:
       0: aload_0
       1: aload_1
       2: iload_2
       3: iload_3
       4: invokestatic  #93                 // Method org/apache/hadoop/hbase/PrivateCellUtil.matchingFamily:(Lorg/apache/hadoop/hbase/Cell;[BII)Z
       7: ireturn

  public static boolean matchingQualifier(org.apache.hadoop.hbase.Cell, org.apache.hadoop.hbase.Cell);
    Code:
       0: aload_0
       1: invokeinterface #12,  1           // InterfaceMethod org/apache/hadoop/hbase/Cell.getQualifierLength:()I
       6: istore_2
       7: aload_1
       8: invokeinterface #12,  1           // InterfaceMethod org/apache/hadoop/hbase/Cell.getQualifierLength:()I
      13: istore_3
      14: aload_0
      15: instanceof    #23                 // class org/apache/hadoop/hbase/ByteBufferExtendedCell
      18: ifeq          62
      21: aload_1
      22: instanceof    #23                 // class org/apache/hadoop/hbase/ByteBufferExtendedCell
      25: ifeq          62
      28: aload_0
      29: checkcast     #23                 // class org/apache/hadoop/hbase/ByteBufferExtendedCell
      32: invokevirtual #37                 // Method org/apache/hadoop/hbase/ByteBufferExtendedCell.getQualifierByteBuffer:()Ljava/nio/ByteBuffer;
      35: aload_0
      36: checkcast     #23                 // class org/apache/hadoop/hbase/ByteBufferExtendedCell
      39: invokevirtual #38                 // Method org/apache/hadoop/hbase/ByteBufferExtendedCell.getQualifierPosition:()I
      42: iload_2
      43: aload_1
      44: checkcast     #23                 // class org/apache/hadoop/hbase/ByteBufferExtendedCell
      47: invokevirtual #37                 // Method org/apache/hadoop/hbase/ByteBufferExtendedCell.getQualifierByteBuffer:()Ljava/nio/ByteBuffer;
      50: aload_1
      51: checkcast     #23                 // class org/apache/hadoop/hbase/ByteBufferExtendedCell
      54: invokevirtual #38                 // Method org/apache/hadoop/hbase/ByteBufferExtendedCell.getQualifierPosition:()I
      57: iload_3
      58: invokestatic  #89                 // Method org/apache/hadoop/hbase/util/ByteBufferUtils.equals:(Ljava/nio/ByteBuffer;IILjava/nio/ByteBuffer;II)Z
      61: ireturn
      62: aload_0
      63: instanceof    #23                 // class org/apache/hadoop/hbase/ByteBufferExtendedCell
      66: ifeq          101
      69: aload_0
      70: checkcast     #23                 // class org/apache/hadoop/hbase/ByteBufferExtendedCell
      73: invokevirtual #37                 // Method org/apache/hadoop/hbase/ByteBufferExtendedCell.getQualifierByteBuffer:()Ljava/nio/ByteBuffer;
      76: aload_0
      77: checkcast     #23                 // class org/apache/hadoop/hbase/ByteBufferExtendedCell
      80: invokevirtual #38                 // Method org/apache/hadoop/hbase/ByteBufferExtendedCell.getQualifierPosition:()I
      83: iload_2
      84: aload_1
      85: invokeinterface #39,  1           // InterfaceMethod org/apache/hadoop/hbase/Cell.getQualifierArray:()[B
      90: aload_1
      91: invokeinterface #40,  1           // InterfaceMethod org/apache/hadoop/hbase/Cell.getQualifierOffset:()I
      96: iload_3
      97: invokestatic  #90                 // Method org/apache/hadoop/hbase/util/ByteBufferUtils.equals:(Ljava/nio/ByteBuffer;II[BII)Z
     100: ireturn
     101: aload_1
     102: instanceof    #23                 // class org/apache/hadoop/hbase/ByteBufferExtendedCell
     105: ifeq          140
     108: aload_1
     109: checkcast     #23                 // class org/apache/hadoop/hbase/ByteBufferExtendedCell
     112: invokevirtual #37                 // Method org/apache/hadoop/hbase/ByteBufferExtendedCell.getQualifierByteBuffer:()Ljava/nio/ByteBuffer;
     115: aload_1
     116: checkcast     #23                 // class org/apache/hadoop/hbase/ByteBufferExtendedCell
     119: invokevirtual #38                 // Method org/apache/hadoop/hbase/ByteBufferExtendedCell.getQualifierPosition:()I
     122: iload_3
     123: aload_0
     124: invokeinterface #39,  1           // InterfaceMethod org/apache/hadoop/hbase/Cell.getQualifierArray:()[B
     129: aload_0
     130: invokeinterface #40,  1           // InterfaceMethod org/apache/hadoop/hbase/Cell.getQualifierOffset:()I
     135: iload_2
     136: invokestatic  #90                 // Method org/apache/hadoop/hbase/util/ByteBufferUtils.equals:(Ljava/nio/ByteBuffer;II[BII)Z
     139: ireturn
     140: aload_0
     141: invokeinterface #39,  1           // InterfaceMethod org/apache/hadoop/hbase/Cell.getQualifierArray:()[B
     146: aload_0
     147: invokeinterface #40,  1           // InterfaceMethod org/apache/hadoop/hbase/Cell.getQualifierOffset:()I
     152: iload_2
     153: aload_1
     154: invokeinterface #39,  1           // InterfaceMethod org/apache/hadoop/hbase/Cell.getQualifierArray:()[B
     159: aload_1
     160: invokeinterface #40,  1           // InterfaceMethod org/apache/hadoop/hbase/Cell.getQualifierOffset:()I
     165: iload_3
     166: invokestatic  #91                 // Method org/apache/hadoop/hbase/util/Bytes.equals:([BII[BII)Z
     169: ireturn

  public static boolean matchingQualifier(org.apache.hadoop.hbase.Cell, byte[]);
    Code:
       0: aload_1
       1: ifnonnull     19
       4: aload_0
       5: invokeinterface #12,  1           // InterfaceMethod org/apache/hadoop/hbase/Cell.getQualifierLength:()I
      10: ifne          17
      13: iconst_1
      14: goto          18
      17: iconst_0
      18: ireturn
      19: aload_0
      20: aload_1
      21: iconst_0
      22: aload_1
      23: arraylength
      24: invokestatic  #94                 // Method matchingQualifier:(Lorg/apache/hadoop/hbase/Cell;[BII)Z
      27: ireturn

  public static boolean matchingQualifier(org.apache.hadoop.hbase.Cell, byte[], int, int);
    Code:
       0: aload_0
       1: aload_1
       2: iload_2
       3: iload_3
       4: invokestatic  #95                 // Method org/apache/hadoop/hbase/PrivateCellUtil.matchingQualifier:(Lorg/apache/hadoop/hbase/Cell;[BII)Z
       7: ireturn

  public static boolean matchingColumn(org.apache.hadoop.hbase.Cell, byte[], byte[]);
    Code:
       0: aload_0
       1: aload_1
       2: invokestatic  #96                 // Method matchingFamily:(Lorg/apache/hadoop/hbase/Cell;[B)Z
       5: ifne          10
       8: iconst_0
       9: ireturn
      10: aload_0
      11: aload_2
      12: invokestatic  #97                 // Method matchingQualifier:(Lorg/apache/hadoop/hbase/Cell;[B)Z
      15: ireturn

  public static boolean matchingColumn(org.apache.hadoop.hbase.Cell, byte[], int, int, byte[], int, int);
    Code:
       0: aload_0
       1: aload_1
       2: iload_2
       3: iload_3
       4: aload         4
       6: iload         5
       8: iload         6
      10: invokestatic  #98                 // Method org/apache/hadoop/hbase/PrivateCellUtil.matchingColumn:(Lorg/apache/hadoop/hbase/Cell;[BII[BII)Z
      13: ireturn

  public static boolean matchingColumn(org.apache.hadoop.hbase.Cell, org.apache.hadoop.hbase.Cell);
    Code:
       0: aload_0
       1: aload_1
       2: invokestatic  #99                 // Method matchingFamily:(Lorg/apache/hadoop/hbase/Cell;Lorg/apache/hadoop/hbase/Cell;)Z
       5: ifne          10
       8: iconst_0
       9: ireturn
      10: aload_0
      11: aload_1
      12: invokestatic  #100                // Method matchingQualifier:(Lorg/apache/hadoop/hbase/Cell;Lorg/apache/hadoop/hbase/Cell;)Z
      15: ireturn

  public static boolean matchingValue(org.apache.hadoop.hbase.Cell, org.apache.hadoop.hbase.Cell);
    Code:
       0: aload_0
       1: aload_1
       2: aload_0
       3: invokeinterface #14,  1           // InterfaceMethod org/apache/hadoop/hbase/Cell.getValueLength:()I
       8: aload_1
       9: invokeinterface #14,  1           // InterfaceMethod org/apache/hadoop/hbase/Cell.getValueLength:()I
      14: invokestatic  #101                // Method matchingValue:(Lorg/apache/hadoop/hbase/Cell;Lorg/apache/hadoop/hbase/Cell;II)Z
      17: ireturn

  public static boolean matchingValue(org.apache.hadoop.hbase.Cell, org.apache.hadoop.hbase.Cell, int, int);
    Code:
       0: aload_0
       1: instanceof    #23                 // class org/apache/hadoop/hbase/ByteBufferExtendedCell
       4: ifeq          48
       7: aload_1
       8: instanceof    #23                 // class org/apache/hadoop/hbase/ByteBufferExtendedCell
      11: ifeq          48
      14: aload_0
      15: checkcast     #23                 // class org/apache/hadoop/hbase/ByteBufferExtendedCell
      18: invokevirtual #41                 // Method org/apache/hadoop/hbase/ByteBufferExtendedCell.getValueByteBuffer:()Ljava/nio/ByteBuffer;
      21: aload_0
      22: checkcast     #23                 // class org/apache/hadoop/hbase/ByteBufferExtendedCell
      25: invokevirtual #42                 // Method org/apache/hadoop/hbase/ByteBufferExtendedCell.getValuePosition:()I
      28: iload_2
      29: aload_1
      30: checkcast     #23                 // class org/apache/hadoop/hbase/ByteBufferExtendedCell
      33: invokevirtual #41                 // Method org/apache/hadoop/hbase/ByteBufferExtendedCell.getValueByteBuffer:()Ljava/nio/ByteBuffer;
      36: aload_1
      37: checkcast     #23                 // class org/apache/hadoop/hbase/ByteBufferExtendedCell
      40: invokevirtual #42                 // Method org/apache/hadoop/hbase/ByteBufferExtendedCell.getValuePosition:()I
      43: iload_3
      44: invokestatic  #89                 // Method org/apache/hadoop/hbase/util/ByteBufferUtils.equals:(Ljava/nio/ByteBuffer;IILjava/nio/ByteBuffer;II)Z
      47: ireturn
      48: aload_0
      49: instanceof    #23                 // class org/apache/hadoop/hbase/ByteBufferExtendedCell
      52: ifeq          87
      55: aload_0
      56: checkcast     #23                 // class org/apache/hadoop/hbase/ByteBufferExtendedCell
      59: invokevirtual #41                 // Method org/apache/hadoop/hbase/ByteBufferExtendedCell.getValueByteBuffer:()Ljava/nio/ByteBuffer;
      62: aload_0
      63: checkcast     #23                 // class org/apache/hadoop/hbase/ByteBufferExtendedCell
      66: invokevirtual #42                 // Method org/apache/hadoop/hbase/ByteBufferExtendedCell.getValuePosition:()I
      69: iload_2
      70: aload_1
      71: invokeinterface #43,  1           // InterfaceMethod org/apache/hadoop/hbase/Cell.getValueArray:()[B
      76: aload_1
      77: invokeinterface #44,  1           // InterfaceMethod org/apache/hadoop/hbase/Cell.getValueOffset:()I
      82: iload_3
      83: invokestatic  #90                 // Method org/apache/hadoop/hbase/util/ByteBufferUtils.equals:(Ljava/nio/ByteBuffer;II[BII)Z
      86: ireturn
      87: aload_1
      88: instanceof    #23                 // class org/apache/hadoop/hbase/ByteBufferExtendedCell
      91: ifeq          126
      94: aload_1
      95: checkcast     #23                 // class org/apache/hadoop/hbase/ByteBufferExtendedCell
      98: invokevirtual #41                 // Method org/apache/hadoop/hbase/ByteBufferExtendedCell.getValueByteBuffer:()Ljava/nio/ByteBuffer;
     101: aload_1
     102: checkcast     #23                 // class org/apache/hadoop/hbase/ByteBufferExtendedCell
     105: invokevirtual #42                 // Method org/apache/hadoop/hbase/ByteBufferExtendedCell.getValuePosition:()I
     108: iload_3
     109: aload_0
     110: invokeinterface #43,  1           // InterfaceMethod org/apache/hadoop/hbase/Cell.getValueArray:()[B
     115: aload_0
     116: invokeinterface #44,  1           // InterfaceMethod org/apache/hadoop/hbase/Cell.getValueOffset:()I
     121: iload_2
     122: invokestatic  #90                 // Method org/apache/hadoop/hbase/util/ByteBufferUtils.equals:(Ljava/nio/ByteBuffer;II[BII)Z
     125: ireturn
     126: aload_0
     127: invokeinterface #43,  1           // InterfaceMethod org/apache/hadoop/hbase/Cell.getValueArray:()[B
     132: aload_0
     133: invokeinterface #44,  1           // InterfaceMethod org/apache/hadoop/hbase/Cell.getValueOffset:()I
     138: iload_2
     139: aload_1
     140: invokeinterface #43,  1           // InterfaceMethod org/apache/hadoop/hbase/Cell.getValueArray:()[B
     145: aload_1
     146: invokeinterface #44,  1           // InterfaceMethod org/apache/hadoop/hbase/Cell.getValueOffset:()I
     151: iload_3
     152: invokestatic  #91                 // Method org/apache/hadoop/hbase/util/Bytes.equals:([BII[BII)Z
     155: ireturn

  public static boolean matchingValue(org.apache.hadoop.hbase.Cell, byte[]);
    Code:
       0: aload_0
       1: instanceof    #23                 // class org/apache/hadoop/hbase/ByteBufferExtendedCell
       4: ifeq          43
       7: aload_0
       8: checkcast     #23                 // class org/apache/hadoop/hbase/ByteBufferExtendedCell
      11: invokevirtual #41                 // Method org/apache/hadoop/hbase/ByteBufferExtendedCell.getValueByteBuffer:()Ljava/nio/ByteBuffer;
      14: aload_0
      15: checkcast     #23                 // class org/apache/hadoop/hbase/ByteBufferExtendedCell
      18: invokevirtual #42                 // Method org/apache/hadoop/hbase/ByteBufferExtendedCell.getValuePosition:()I
      21: aload_0
      22: invokeinterface #14,  1           // InterfaceMethod org/apache/hadoop/hbase/Cell.getValueLength:()I
      27: aload_1
      28: iconst_0
      29: aload_1
      30: arraylength
      31: invokestatic  #102                // Method org/apache/hadoop/hbase/util/ByteBufferUtils.compareTo:(Ljava/nio/ByteBuffer;II[BII)I
      34: ifne          41
      37: iconst_1
      38: goto          42
      41: iconst_0
      42: ireturn
      43: aload_0
      44: invokeinterface #43,  1           // InterfaceMethod org/apache/hadoop/hbase/Cell.getValueArray:()[B
      49: aload_0
      50: invokeinterface #44,  1           // InterfaceMethod org/apache/hadoop/hbase/Cell.getValueOffset:()I
      55: aload_0
      56: invokeinterface #14,  1           // InterfaceMethod org/apache/hadoop/hbase/Cell.getValueLength:()I
      61: aload_1
      62: iconst_0
      63: aload_1
      64: arraylength
      65: invokestatic  #91                 // Method org/apache/hadoop/hbase/util/Bytes.equals:([BII[BII)Z
      68: ireturn

  public static boolean isDelete(org.apache.hadoop.hbase.Cell);
    Code:
       0: aload_0
       1: invokeinterface #103,  1          // InterfaceMethod org/apache/hadoop/hbase/Cell.getTypeByte:()B
       6: invokestatic  #104                // Method org/apache/hadoop/hbase/PrivateCellUtil.isDelete:(B)Z
       9: ireturn

  public static boolean isDelete(byte);
    Code:
       0: getstatic     #105                // Field org/apache/hadoop/hbase/KeyValue$Type.Delete:Lorg/apache/hadoop/hbase/KeyValue$Type;
       3: invokevirtual #66                 // Method org/apache/hadoop/hbase/KeyValue$Type.getCode:()B
       6: iload_0
       7: if_icmpgt     24
      10: iload_0
      11: getstatic     #106                // Field org/apache/hadoop/hbase/KeyValue$Type.DeleteFamily:Lorg/apache/hadoop/hbase/KeyValue$Type;
      14: invokevirtual #66                 // Method org/apache/hadoop/hbase/KeyValue$Type.getCode:()B
      17: if_icmpgt     24
      20: iconst_1
      21: goto          25
      24: iconst_0
      25: ireturn

  public static boolean isDeleteType(org.apache.hadoop.hbase.Cell);
    Code:
       0: aload_0
       1: invokeinterface #103,  1          // InterfaceMethod org/apache/hadoop/hbase/Cell.getTypeByte:()B
       6: getstatic     #105                // Field org/apache/hadoop/hbase/KeyValue$Type.Delete:Lorg/apache/hadoop/hbase/KeyValue$Type;
       9: invokevirtual #66                 // Method org/apache/hadoop/hbase/KeyValue$Type.getCode:()B
      12: if_icmpne     19
      15: iconst_1
      16: goto          20
      19: iconst_0
      20: ireturn

  public static boolean isDeleteFamily(org.apache.hadoop.hbase.Cell);
    Code:
       0: aload_0
       1: invokeinterface #103,  1          // InterfaceMethod org/apache/hadoop/hbase/Cell.getTypeByte:()B
       6: getstatic     #106                // Field org/apache/hadoop/hbase/KeyValue$Type.DeleteFamily:Lorg/apache/hadoop/hbase/KeyValue$Type;
       9: invokevirtual #66                 // Method org/apache/hadoop/hbase/KeyValue$Type.getCode:()B
      12: if_icmpne     19
      15: iconst_1
      16: goto          20
      19: iconst_0
      20: ireturn

  public static boolean isDeleteFamilyVersion(org.apache.hadoop.hbase.Cell);
    Code:
       0: aload_0
       1: invokeinterface #103,  1          // InterfaceMethod org/apache/hadoop/hbase/Cell.getTypeByte:()B
       6: getstatic     #107                // Field org/apache/hadoop/hbase/KeyValue$Type.DeleteFamilyVersion:Lorg/apache/hadoop/hbase/KeyValue$Type;
       9: invokevirtual #66                 // Method org/apache/hadoop/hbase/KeyValue$Type.getCode:()B
      12: if_icmpne     19
      15: iconst_1
      16: goto          20
      19: iconst_0
      20: ireturn

  public static boolean isDeleteColumns(org.apache.hadoop.hbase.Cell);
    Code:
       0: aload_0
       1: invokeinterface #103,  1          // InterfaceMethod org/apache/hadoop/hbase/Cell.getTypeByte:()B
       6: getstatic     #108                // Field org/apache/hadoop/hbase/KeyValue$Type.DeleteColumn:Lorg/apache/hadoop/hbase/KeyValue$Type;
       9: invokevirtual #66                 // Method org/apache/hadoop/hbase/KeyValue$Type.getCode:()B
      12: if_icmpne     19
      15: iconst_1
      16: goto          20
      19: iconst_0
      20: ireturn

  public static boolean isDeleteColumnVersion(org.apache.hadoop.hbase.Cell);
    Code:
       0: aload_0
       1: invokeinterface #103,  1          // InterfaceMethod org/apache/hadoop/hbase/Cell.getTypeByte:()B
       6: getstatic     #105                // Field org/apache/hadoop/hbase/KeyValue$Type.Delete:Lorg/apache/hadoop/hbase/KeyValue$Type;
       9: invokevirtual #66                 // Method org/apache/hadoop/hbase/KeyValue$Type.getCode:()B
      12: if_icmpne     19
      15: iconst_1
      16: goto          20
      19: iconst_0
      20: ireturn

  public static boolean isDeleteColumnOrFamily(org.apache.hadoop.hbase.Cell);
    Code:
       0: aload_0
       1: invokeinterface #103,  1          // InterfaceMethod org/apache/hadoop/hbase/Cell.getTypeByte:()B
       6: istore_1
       7: iload_1
       8: getstatic     #108                // Field org/apache/hadoop/hbase/KeyValue$Type.DeleteColumn:Lorg/apache/hadoop/hbase/KeyValue$Type;
      11: invokevirtual #66                 // Method org/apache/hadoop/hbase/KeyValue$Type.getCode:()B
      14: if_icmpeq     27
      17: iload_1
      18: getstatic     #106                // Field org/apache/hadoop/hbase/KeyValue$Type.DeleteFamily:Lorg/apache/hadoop/hbase/KeyValue$Type;
      21: invokevirtual #66                 // Method org/apache/hadoop/hbase/KeyValue$Type.getCode:()B
      24: if_icmpne     31
      27: iconst_1
      28: goto          32
      31: iconst_0
      32: ireturn

  public static boolean isPut(org.apache.hadoop.hbase.Cell);
    Code:
       0: aload_0
       1: invokeinterface #103,  1          // InterfaceMethod org/apache/hadoop/hbase/Cell.getTypeByte:()B
       6: getstatic     #109                // Field org/apache/hadoop/hbase/KeyValue$Type.Put:Lorg/apache/hadoop/hbase/KeyValue$Type;
       9: invokevirtual #66                 // Method org/apache/hadoop/hbase/KeyValue$Type.getCode:()B
      12: if_icmpne     19
      15: iconst_1
      16: goto          20
      19: iconst_0
      20: ireturn

  public static int estimatedSerializedSizeOf(org.apache.hadoop.hbase.Cell);
    Code:
       0: aload_0
       1: invokestatic  #110                // Method org/apache/hadoop/hbase/PrivateCellUtil.estimatedSerializedSizeOf:(Lorg/apache/hadoop/hbase/Cell;)I
       4: ireturn

  public static int estimatedSerializedSizeOfKey(org.apache.hadoop.hbase.Cell);
    Code:
       0: aload_0
       1: invokestatic  #111                // Method org/apache/hadoop/hbase/PrivateCellUtil.estimatedSerializedSizeOfKey:(Lorg/apache/hadoop/hbase/Cell;)I
       4: ireturn

  public static long estimatedHeapSizeOf(org.apache.hadoop.hbase.Cell);
    Code:
       0: aload_0
       1: invokeinterface #112,  1          // InterfaceMethod org/apache/hadoop/hbase/Cell.heapSize:()J
       6: lreturn

  public static java.util.Iterator<org.apache.hadoop.hbase.Tag> tagsIterator(byte[], int, int);
    Code:
       0: new           #113                // class org/apache/hadoop/hbase/CellUtil$5
       3: dup
       4: iload_1
       5: iload_2
       6: aload_0
       7: invokespecial #114                // Method org/apache/hadoop/hbase/CellUtil$5."<init>":(II[B)V
      10: areturn

  public static java.util.List<org.apache.hadoop.hbase.Tag> getTags(org.apache.hadoop.hbase.Cell);
    Code:
       0: aload_0
       1: invokestatic  #115                // Method org/apache/hadoop/hbase/PrivateCellUtil.getTags:(Lorg/apache/hadoop/hbase/Cell;)Ljava/util/List;
       4: areturn

  public static org.apache.hadoop.hbase.Tag getTag(org.apache.hadoop.hbase.Cell, byte);
    Code:
       0: aload_0
       1: iload_1
       2: invokestatic  #116                // Method org/apache/hadoop/hbase/PrivateCellUtil.getTag:(Lorg/apache/hadoop/hbase/Cell;B)Ljava/util/Optional;
       5: astore_2
       6: aload_2
       7: invokevirtual #117                // Method java/util/Optional.isPresent:()Z
      10: ifeq          21
      13: aload_2
      14: invokevirtual #118                // Method java/util/Optional.get:()Ljava/lang/Object;
      17: checkcast     #119                // class org/apache/hadoop/hbase/Tag
      20: areturn
      21: aconst_null
      22: areturn

  public static boolean overlappingKeys(byte[], byte[], byte[], byte[]);
    Code:
       0: aload_0
       1: aload_1
       2: aload_2
       3: aload_3
       4: invokestatic  #120                // Method org/apache/hadoop/hbase/PrivateCellUtil.overlappingKeys:([B[B[B[B)Z
       7: ireturn

  public static void setSequenceId(org.apache.hadoop.hbase.Cell, long) throws java.io.IOException;
    Code:
       0: aload_0
       1: lload_1
       2: invokestatic  #121                // Method org/apache/hadoop/hbase/PrivateCellUtil.setSequenceId:(Lorg/apache/hadoop/hbase/Cell;J)V
       5: return

  public static void setTimestamp(org.apache.hadoop.hbase.Cell, long) throws java.io.IOException;
    Code:
       0: aload_0
       1: lload_1
       2: invokestatic  #122                // Method org/apache/hadoop/hbase/PrivateCellUtil.setTimestamp:(Lorg/apache/hadoop/hbase/Cell;J)V
       5: return

  public static void setTimestamp(org.apache.hadoop.hbase.Cell, byte[], int) throws java.io.IOException;
    Code:
       0: aload_0
       1: aload_1
       2: iload_2
       3: invokestatic  #123                // Method org/apache/hadoop/hbase/util/Bytes.toLong:([BI)J
       6: invokestatic  #122                // Method org/apache/hadoop/hbase/PrivateCellUtil.setTimestamp:(Lorg/apache/hadoop/hbase/Cell;J)V
       9: return

  public static boolean updateLatestStamp(org.apache.hadoop.hbase.Cell, long) throws java.io.IOException;
    Code:
       0: aload_0
       1: lload_1
       2: invokestatic  #124                // Method org/apache/hadoop/hbase/PrivateCellUtil.updateLatestStamp:(Lorg/apache/hadoop/hbase/Cell;J)Z
       5: ireturn

  public static boolean updateLatestStamp(org.apache.hadoop.hbase.Cell, byte[], int) throws java.io.IOException;
    Code:
       0: aload_0
       1: aload_1
       2: iload_2
       3: invokestatic  #123                // Method org/apache/hadoop/hbase/util/Bytes.toLong:([BI)J
       6: invokestatic  #124                // Method org/apache/hadoop/hbase/PrivateCellUtil.updateLatestStamp:(Lorg/apache/hadoop/hbase/Cell;J)Z
       9: ireturn

  public static int writeFlatKey(org.apache.hadoop.hbase.Cell, java.io.OutputStream) throws java.io.IOException;
    Code:
       0: aload_0
       1: aload_1
       2: invokestatic  #125                // Method org/apache/hadoop/hbase/PrivateCellUtil.writeFlatKey:(Lorg/apache/hadoop/hbase/Cell;Ljava/io/OutputStream;)I
       5: ireturn

  public static void writeRowSkippingBytes(java.io.DataOutputStream, org.apache.hadoop.hbase.Cell, short, int) throws java.io.IOException;
    Code:
       0: aload_0
       1: aload_1
       2: iload_2
       3: iload_3
       4: invokestatic  #126                // Method org/apache/hadoop/hbase/PrivateCellUtil.writeRowSkippingBytes:(Ljava/io/DataOutputStream;Lorg/apache/hadoop/hbase/Cell;SI)V
       7: return

  public static void writeQualifierSkippingBytes(java.io.DataOutputStream, org.apache.hadoop.hbase.Cell, int, int) throws java.io.IOException;
    Code:
       0: aload_1
       1: instanceof    #23                 // class org/apache/hadoop/hbase/ByteBufferExtendedCell
       4: ifeq          33
       7: aload_0
       8: aload_1
       9: checkcast     #23                 // class org/apache/hadoop/hbase/ByteBufferExtendedCell
      12: invokevirtual #37                 // Method org/apache/hadoop/hbase/ByteBufferExtendedCell.getQualifierByteBuffer:()Ljava/nio/ByteBuffer;
      15: aload_1
      16: checkcast     #23                 // class org/apache/hadoop/hbase/ByteBufferExtendedCell
      19: invokevirtual #38                 // Method org/apache/hadoop/hbase/ByteBufferExtendedCell.getQualifierPosition:()I
      22: iload_3
      23: iadd
      24: iload_2
      25: iload_3
      26: isub
      27: invokestatic  #127                // Method org/apache/hadoop/hbase/util/ByteBufferUtils.copyBufferToStream:(Ljava/io/DataOutput;Ljava/nio/ByteBuffer;II)V
      30: goto          54
      33: aload_0
      34: aload_1
      35: invokeinterface #39,  1           // InterfaceMethod org/apache/hadoop/hbase/Cell.getQualifierArray:()[B
      40: aload_1
      41: invokeinterface #40,  1           // InterfaceMethod org/apache/hadoop/hbase/Cell.getQualifierOffset:()I
      46: iload_3
      47: iadd
      48: iload_2
      49: iload_3
      50: isub
      51: invokevirtual #128                // Method java/io/DataOutputStream.write:([BII)V
      54: return

  public static java.lang.String getCellKeyAsString(org.apache.hadoop.hbase.Cell);
    Code:
       0: new           #129                // class java/lang/StringBuilder
       3: dup
       4: aload_0
       5: invokeinterface #27,  1           // InterfaceMethod org/apache/hadoop/hbase/Cell.getRowArray:()[B
      10: aload_0
      11: invokeinterface #28,  1           // InterfaceMethod org/apache/hadoop/hbase/Cell.getRowOffset:()I
      16: aload_0
      17: invokeinterface #8,  1            // InterfaceMethod org/apache/hadoop/hbase/Cell.getRowLength:()S
      22: invokestatic  #130                // Method org/apache/hadoop/hbase/util/Bytes.toStringBinary:([BII)Ljava/lang/String;
      25: invokespecial #131                // Method java/lang/StringBuilder."<init>":(Ljava/lang/String;)V
      28: astore_1
      29: aload_1
      30: bipush        47
      32: invokevirtual #132                // Method java/lang/StringBuilder.append:(C)Ljava/lang/StringBuilder;
      35: pop
      36: aload_1
      37: aload_0
      38: invokeinterface #10,  1           // InterfaceMethod org/apache/hadoop/hbase/Cell.getFamilyLength:()B
      43: ifne          51
      46: ldc           #133                // String
      48: goto          72
      51: aload_0
      52: invokeinterface #35,  1           // InterfaceMethod org/apache/hadoop/hbase/Cell.getFamilyArray:()[B
      57: aload_0
      58: invokeinterface #36,  1           // InterfaceMethod org/apache/hadoop/hbase/Cell.getFamilyOffset:()I
      63: aload_0
      64: invokeinterface #10,  1           // InterfaceMethod org/apache/hadoop/hbase/Cell.getFamilyLength:()B
      69: invokestatic  #130                // Method org/apache/hadoop/hbase/util/Bytes.toStringBinary:([BII)Ljava/lang/String;
      72: invokevirtual #134                // Method java/lang/StringBuilder.append:(Ljava/lang/String;)Ljava/lang/StringBuilder;
      75: pop
      76: aload_0
      77: invokeinterface #10,  1           // InterfaceMethod org/apache/hadoop/hbase/Cell.getFamilyLength:()B
      82: ifle          92
      85: aload_1
      86: bipush        58
      88: invokevirtual #132                // Method java/lang/StringBuilder.append:(C)Ljava/lang/StringBuilder;
      91: pop
      92: aload_1
      93: aload_0
      94: invokeinterface #12,  1           // InterfaceMethod org/apache/hadoop/hbase/Cell.getQualifierLength:()I
      99: ifne          107
     102: ldc           #133                // String
     104: goto          128
     107: aload_0
     108: invokeinterface #39,  1           // InterfaceMethod org/apache/hadoop/hbase/Cell.getQualifierArray:()[B
     113: aload_0
     114: invokeinterface #40,  1           // InterfaceMethod org/apache/hadoop/hbase/Cell.getQualifierOffset:()I
     119: aload_0
     120: invokeinterface #12,  1           // InterfaceMethod org/apache/hadoop/hbase/Cell.getQualifierLength:()I
     125: invokestatic  #130                // Method org/apache/hadoop/hbase/util/Bytes.toStringBinary:([BII)Ljava/lang/String;
     128: invokevirtual #134                // Method java/lang/StringBuilder.append:(Ljava/lang/String;)Ljava/lang/StringBuilder;
     131: pop
     132: aload_1
     133: bipush        47
     135: invokevirtual #132                // Method java/lang/StringBuilder.append:(C)Ljava/lang/StringBuilder;
     138: pop
     139: aload_1
     140: aload_0
     141: invokeinterface #135,  1          // InterfaceMethod org/apache/hadoop/hbase/Cell.getTimestamp:()J
     146: invokestatic  #136                // Method org/apache/hadoop/hbase/KeyValue.humanReadableTimestamp:(J)Ljava/lang/String;
     149: invokevirtual #134                // Method java/lang/StringBuilder.append:(Ljava/lang/String;)Ljava/lang/StringBuilder;
     152: pop
     153: aload_1
     154: bipush        47
     156: invokevirtual #132                // Method java/lang/StringBuilder.append:(C)Ljava/lang/StringBuilder;
     159: pop
     160: aload_1
     161: aload_0
     162: invokeinterface #103,  1          // InterfaceMethod org/apache/hadoop/hbase/Cell.getTypeByte:()B
     167: invokestatic  #137                // Method org/apache/hadoop/hbase/KeyValue$Type.codeToType:(B)Lorg/apache/hadoop/hbase/KeyValue$Type;
     170: invokevirtual #138                // Method java/lang/StringBuilder.append:(Ljava/lang/Object;)Ljava/lang/StringBuilder;
     173: pop
     174: aload_0
     175: instanceof    #139                // class org/apache/hadoop/hbase/KeyValue$KeyOnlyKeyValue
     178: ifne          199
     181: aload_1
     182: ldc           #140                // String /vlen=
     184: invokevirtual #134                // Method java/lang/StringBuilder.append:(Ljava/lang/String;)Ljava/lang/StringBuilder;
     187: pop
     188: aload_1
     189: aload_0
     190: invokeinterface #14,  1           // InterfaceMethod org/apache/hadoop/hbase/Cell.getValueLength:()I
     195: invokevirtual #141                // Method java/lang/StringBuilder.append:(I)Ljava/lang/StringBuilder;
     198: pop
     199: aload_1
     200: ldc           #142                // String /seqid=
     202: invokevirtual #134                // Method java/lang/StringBuilder.append:(Ljava/lang/String;)Ljava/lang/StringBuilder;
     205: pop
     206: aload_1
     207: aload_0
     208: invokeinterface #143,  1          // InterfaceMethod org/apache/hadoop/hbase/Cell.getSequenceId:()J
     213: invokevirtual #144                // Method java/lang/StringBuilder.append:(J)Ljava/lang/StringBuilder;
     216: pop
     217: aload_1
     218: invokevirtual #145                // Method java/lang/StringBuilder.toString:()Ljava/lang/String;
     221: areturn

  public static byte[] getCellKeySerializedAsKeyValueKey(org.apache.hadoop.hbase.Cell);
    Code:
       0: aload_0
       1: invokestatic  #146                // Method org/apache/hadoop/hbase/PrivateCellUtil.getCellKeySerializedAsKeyValueKey:(Lorg/apache/hadoop/hbase/Cell;)[B
       4: areturn

  public static void writeRowKeyExcludingCommon(org.apache.hadoop.hbase.Cell, short, int, java.io.DataOutputStream) throws java.io.IOException;
    Code:
       0: aload_0
       1: iload_1
       2: iload_2
       3: aload_3
       4: invokestatic  #147                // Method org/apache/hadoop/hbase/PrivateCellUtil.writeRowKeyExcludingCommon:(Lorg/apache/hadoop/hbase/Cell;SILjava/io/DataOutputStream;)V
       7: return

  public static int findCommonPrefixInFlatKey(org.apache.hadoop.hbase.Cell, org.apache.hadoop.hbase.Cell, boolean, boolean);
    Code:
       0: aload_0
       1: aload_1
       2: iload_2
       3: iload_3
       4: invokestatic  #148                // Method org/apache/hadoop/hbase/PrivateCellUtil.findCommonPrefixInFlatKey:(Lorg/apache/hadoop/hbase/Cell;Lorg/apache/hadoop/hbase/Cell;ZZ)I
       7: ireturn

  public static java.lang.String toString(org.apache.hadoop.hbase.Cell, boolean);
    Code:
       0: aload_0
       1: ifnonnull     7
       4: ldc           #133                // String
       6: areturn
       7: new           #129                // class java/lang/StringBuilder
      10: dup
      11: invokespecial #149                // Method java/lang/StringBuilder."<init>":()V
      14: astore_2
      15: aload_0
      16: invokestatic  #150                // Method getCellKeyAsString:(Lorg/apache/hadoop/hbase/Cell;)Ljava/lang/String;
      19: astore_3
      20: aconst_null
      21: astore        4
      23: aconst_null
      24: astore        5
      26: iload_1
      27: ifeq          92
      30: aload_0
      31: invokeinterface #151,  1          // InterfaceMethod org/apache/hadoop/hbase/Cell.getTagsLength:()I
      36: ifle          62
      39: aload_0
      40: invokeinterface #152,  1          // InterfaceMethod org/apache/hadoop/hbase/Cell.getTagsArray:()[B
      45: aload_0
      46: invokeinterface #153,  1          // InterfaceMethod org/apache/hadoop/hbase/Cell.getTagsOffset:()I
      51: aload_0
      52: invokeinterface #151,  1          // InterfaceMethod org/apache/hadoop/hbase/Cell.getTagsLength:()I
      57: invokestatic  #130                // Method org/apache/hadoop/hbase/util/Bytes.toStringBinary:([BII)Ljava/lang/String;
      60: astore        4
      62: aload_0
      63: instanceof    #139                // class org/apache/hadoop/hbase/KeyValue$KeyOnlyKeyValue
      66: ifne          92
      69: aload_0
      70: invokeinterface #43,  1           // InterfaceMethod org/apache/hadoop/hbase/Cell.getValueArray:()[B
      75: aload_0
      76: invokeinterface #44,  1           // InterfaceMethod org/apache/hadoop/hbase/Cell.getValueOffset:()I
      81: aload_0
      82: invokeinterface #14,  1           // InterfaceMethod org/apache/hadoop/hbase/Cell.getValueLength:()I
      87: invokestatic  #130                // Method org/apache/hadoop/hbase/util/Bytes.toStringBinary:([BII)Ljava/lang/String;
      90: astore        5
      92: aload_2
      93: aload_3
      94: invokevirtual #134                // Method java/lang/StringBuilder.append:(Ljava/lang/String;)Ljava/lang/StringBuilder;
      97: pop
      98: aload         4
     100: ifnull        123
     103: aload         4
     105: invokevirtual #154                // Method java/lang/String.isEmpty:()Z
     108: ifne          123
     111: aload_2
     112: ldc           #155                // String /
     114: invokevirtual #134                // Method java/lang/StringBuilder.append:(Ljava/lang/String;)Ljava/lang/StringBuilder;
     117: aload         4
     119: invokevirtual #134                // Method java/lang/StringBuilder.append:(Ljava/lang/String;)Ljava/lang/StringBuilder;
     122: pop
     123: aload         5
     125: ifnull        140
     128: aload_2
     129: ldc           #155                // String /
     131: invokevirtual #134                // Method java/lang/StringBuilder.append:(Ljava/lang/String;)Ljava/lang/StringBuilder;
     134: aload         5
     136: invokevirtual #134                // Method java/lang/StringBuilder.append:(Ljava/lang/String;)Ljava/lang/StringBuilder;
     139: pop
     140: aload_2
     141: invokevirtual #145                // Method java/lang/StringBuilder.toString:()Ljava/lang/String;
     144: areturn

  public static boolean equalsIgnoreMvccVersion(org.apache.hadoop.hbase.Cell, org.apache.hadoop.hbase.Cell);
    Code:
       0: aload_0
       1: aload_1
       2: invokestatic  #156                // Method org/apache/hadoop/hbase/PrivateCellUtil.equalsIgnoreMvccVersion:(Lorg/apache/hadoop/hbase/Cell;Lorg/apache/hadoop/hbase/Cell;)Z
       5: ireturn

  public static boolean equals(org.apache.hadoop.hbase.Cell, org.apache.hadoop.hbase.Cell);
    Code:
       0: aload_0
       1: aload_1
       2: invokestatic  #86                 // Method matchingRows:(Lorg/apache/hadoop/hbase/Cell;Lorg/apache/hadoop/hbase/Cell;)Z
       5: ifeq          44
       8: aload_0
       9: aload_1
      10: invokestatic  #99                 // Method matchingFamily:(Lorg/apache/hadoop/hbase/Cell;Lorg/apache/hadoop/hbase/Cell;)Z
      13: ifeq          44
      16: aload_0
      17: aload_1
      18: invokestatic  #100                // Method matchingQualifier:(Lorg/apache/hadoop/hbase/Cell;Lorg/apache/hadoop/hbase/Cell;)Z
      21: ifeq          44
      24: aload_0
      25: aload_1
      26: invokestatic  #157                // Method matchingTimestamp:(Lorg/apache/hadoop/hbase/Cell;Lorg/apache/hadoop/hbase/Cell;)Z
      29: ifeq          44
      32: aload_0
      33: aload_1
      34: invokestatic  #158                // Method org/apache/hadoop/hbase/PrivateCellUtil.matchingType:(Lorg/apache/hadoop/hbase/Cell;Lorg/apache/hadoop/hbase/Cell;)Z
      37: ifeq          44
      40: iconst_1
      41: goto          45
      44: iconst_0
      45: ireturn

  public static boolean matchingTimestamp(org.apache.hadoop.hbase.Cell, org.apache.hadoop.hbase.Cell);
    Code:
       0: invokestatic  #159                // InterfaceMethod org/apache/hadoop/hbase/CellComparator.getInstance:()Lorg/apache/hadoop/hbase/CellComparator;
       3: aload_0
       4: invokeinterface #135,  1          // InterfaceMethod org/apache/hadoop/hbase/Cell.getTimestamp:()J
       9: aload_1
      10: invokeinterface #135,  1          // InterfaceMethod org/apache/hadoop/hbase/Cell.getTimestamp:()J
      15: invokeinterface #160,  5          // InterfaceMethod org/apache/hadoop/hbase/CellComparator.compareTimestamps:(JJ)I
      20: ifne          27
      23: iconst_1
      24: goto          28
      27: iconst_0
      28: ireturn

  public static boolean matchingType(org.apache.hadoop.hbase.Cell, org.apache.hadoop.hbase.Cell);
    Code:
       0: aload_0
       1: aload_1
       2: invokestatic  #158                // Method org/apache/hadoop/hbase/PrivateCellUtil.matchingType:(Lorg/apache/hadoop/hbase/Cell;Lorg/apache/hadoop/hbase/Cell;)Z
       5: ireturn

  public static boolean matchingRows(org.apache.hadoop.hbase.Cell, org.apache.hadoop.hbase.Cell);
    Code:
       0: aload_0
       1: invokeinterface #8,  1            // InterfaceMethod org/apache/hadoop/hbase/Cell.getRowLength:()S
       6: istore_2
       7: aload_1
       8: invokeinterface #8,  1            // InterfaceMethod org/apache/hadoop/hbase/Cell.getRowLength:()S
      13: istore_3
      14: iload_2
      15: iload_3
      16: if_icmpeq     21
      19: iconst_0
      20: ireturn
      21: aload_0
      22: instanceof    #23                 // class org/apache/hadoop/hbase/ByteBufferExtendedCell
      25: ifeq          69
      28: aload_1
      29: instanceof    #23                 // class org/apache/hadoop/hbase/ByteBufferExtendedCell
      32: ifeq          69
      35: aload_0
      36: checkcast     #23                 // class org/apache/hadoop/hbase/ByteBufferExtendedCell
      39: invokevirtual #24                 // Method org/apache/hadoop/hbase/ByteBufferExtendedCell.getRowByteBuffer:()Ljava/nio/ByteBuffer;
      42: aload_0
      43: checkcast     #23                 // class org/apache/hadoop/hbase/ByteBufferExtendedCell
      46: invokevirtual #25                 // Method org/apache/hadoop/hbase/ByteBufferExtendedCell.getRowPosition:()I
      49: iload_2
      50: aload_1
      51: checkcast     #23                 // class org/apache/hadoop/hbase/ByteBufferExtendedCell
      54: invokevirtual #24                 // Method org/apache/hadoop/hbase/ByteBufferExtendedCell.getRowByteBuffer:()Ljava/nio/ByteBuffer;
      57: aload_1
      58: checkcast     #23                 // class org/apache/hadoop/hbase/ByteBufferExtendedCell
      61: invokevirtual #25                 // Method org/apache/hadoop/hbase/ByteBufferExtendedCell.getRowPosition:()I
      64: iload_3
      65: invokestatic  #89                 // Method org/apache/hadoop/hbase/util/ByteBufferUtils.equals:(Ljava/nio/ByteBuffer;IILjava/nio/ByteBuffer;II)Z
      68: ireturn
      69: aload_0
      70: instanceof    #23                 // class org/apache/hadoop/hbase/ByteBufferExtendedCell
      73: ifeq          108
      76: aload_0
      77: checkcast     #23                 // class org/apache/hadoop/hbase/ByteBufferExtendedCell
      80: invokevirtual #24                 // Method org/apache/hadoop/hbase/ByteBufferExtendedCell.getRowByteBuffer:()Ljava/nio/ByteBuffer;
      83: aload_0
      84: checkcast     #23                 // class org/apache/hadoop/hbase/ByteBufferExtendedCell
      87: invokevirtual #25                 // Method org/apache/hadoop/hbase/ByteBufferExtendedCell.getRowPosition:()I
      90: iload_2
      91: aload_1
      92: invokeinterface #27,  1           // InterfaceMethod org/apache/hadoop/hbase/Cell.getRowArray:()[B
      97: aload_1
      98: invokeinterface #28,  1           // InterfaceMethod org/apache/hadoop/hbase/Cell.getRowOffset:()I
     103: iload_3
     104: invokestatic  #90                 // Method org/apache/hadoop/hbase/util/ByteBufferUtils.equals:(Ljava/nio/ByteBuffer;II[BII)Z
     107: ireturn
     108: aload_1
     109: instanceof    #23                 // class org/apache/hadoop/hbase/ByteBufferExtendedCell
     112: ifeq          147
     115: aload_1
     116: checkcast     #23                 // class org/apache/hadoop/hbase/ByteBufferExtendedCell
     119: invokevirtual #24                 // Method org/apache/hadoop/hbase/ByteBufferExtendedCell.getRowByteBuffer:()Ljava/nio/ByteBuffer;
     122: aload_1
     123: checkcast     #23                 // class org/apache/hadoop/hbase/ByteBufferExtendedCell
     126: invokevirtual #25                 // Method org/apache/hadoop/hbase/ByteBufferExtendedCell.getRowPosition:()I
     129: iload_3
     130: aload_0
     131: invokeinterface #27,  1           // InterfaceMethod org/apache/hadoop/hbase/Cell.getRowArray:()[B
     136: aload_0
     137: invokeinterface #28,  1           // InterfaceMethod org/apache/hadoop/hbase/Cell.getRowOffset:()I
     142: iload_2
     143: invokestatic  #90                 // Method org/apache/hadoop/hbase/util/ByteBufferUtils.equals:(Ljava/nio/ByteBuffer;II[BII)Z
     146: ireturn
     147: aload_0
     148: invokeinterface #27,  1           // InterfaceMethod org/apache/hadoop/hbase/Cell.getRowArray:()[B
     153: aload_0
     154: invokeinterface #28,  1           // InterfaceMethod org/apache/hadoop/hbase/Cell.getRowOffset:()I
     159: iload_2
     160: aload_1
     161: invokeinterface #27,  1           // InterfaceMethod org/apache/hadoop/hbase/Cell.getRowArray:()[B
     166: aload_1
     167: invokeinterface #28,  1           // InterfaceMethod org/apache/hadoop/hbase/Cell.getRowOffset:()I
     172: iload_3
     173: invokestatic  #91                 // Method org/apache/hadoop/hbase/util/Bytes.equals:([BII[BII)Z
     176: ireturn

  public static boolean matchingRowColumn(org.apache.hadoop.hbase.Cell, org.apache.hadoop.hbase.Cell);
    Code:
       0: aload_0
       1: invokeinterface #8,  1            // InterfaceMethod org/apache/hadoop/hbase/Cell.getRowLength:()S
       6: aload_0
       7: invokeinterface #10,  1           // InterfaceMethod org/apache/hadoop/hbase/Cell.getFamilyLength:()B
      12: iadd
      13: aload_0
      14: invokeinterface #12,  1           // InterfaceMethod org/apache/hadoop/hbase/Cell.getQualifierLength:()I
      19: iadd
      20: aload_1
      21: invokeinterface #8,  1            // InterfaceMethod org/apache/hadoop/hbase/Cell.getRowLength:()S
      26: aload_1
      27: invokeinterface #10,  1           // InterfaceMethod org/apache/hadoop/hbase/Cell.getFamilyLength:()B
      32: iadd
      33: aload_1
      34: invokeinterface #12,  1           // InterfaceMethod org/apache/hadoop/hbase/Cell.getQualifierLength:()I
      39: iadd
      40: if_icmpeq     45
      43: iconst_0
      44: ireturn
      45: aload_0
      46: aload_1
      47: invokestatic  #86                 // Method matchingRows:(Lorg/apache/hadoop/hbase/Cell;Lorg/apache/hadoop/hbase/Cell;)Z
      50: ifne          55
      53: iconst_0
      54: ireturn
      55: aload_0
      56: aload_1
      57: invokestatic  #161                // Method matchingColumn:(Lorg/apache/hadoop/hbase/Cell;Lorg/apache/hadoop/hbase/Cell;)Z
      60: ireturn

  public static boolean matchingRowColumnBytes(org.apache.hadoop.hbase.Cell, org.apache.hadoop.hbase.Cell);
    Code:
       0: aload_0
       1: invokeinterface #8,  1            // InterfaceMethod org/apache/hadoop/hbase/Cell.getRowLength:()S
       6: istore_2
       7: aload_1
       8: invokeinterface #8,  1            // InterfaceMethod org/apache/hadoop/hbase/Cell.getRowLength:()S
      13: istore_3
      14: aload_0
      15: invokeinterface #10,  1           // InterfaceMethod org/apache/hadoop/hbase/Cell.getFamilyLength:()B
      20: istore        4
      22: aload_1
      23: invokeinterface #10,  1           // InterfaceMethod org/apache/hadoop/hbase/Cell.getFamilyLength:()B
      28: istore        5
      30: aload_0
      31: invokeinterface #12,  1           // InterfaceMethod org/apache/hadoop/hbase/Cell.getQualifierLength:()I
      36: istore        6
      38: aload_1
      39: invokeinterface #12,  1           // InterfaceMethod org/apache/hadoop/hbase/Cell.getQualifierLength:()I
      44: istore        7
      46: iload_2
      47: iload         4
      49: iadd
      50: iload         6
      52: iadd
      53: iload_3
      54: iload         5
      56: iadd
      57: iload         7
      59: iadd
      60: if_icmpeq     65
      63: iconst_0
      64: ireturn
      65: aload_0
      66: invokeinterface #27,  1           // InterfaceMethod org/apache/hadoop/hbase/Cell.getRowArray:()[B
      71: aload_0
      72: invokeinterface #28,  1           // InterfaceMethod org/apache/hadoop/hbase/Cell.getRowOffset:()I
      77: iload_2
      78: aload_1
      79: invokeinterface #27,  1           // InterfaceMethod org/apache/hadoop/hbase/Cell.getRowArray:()[B
      84: aload_1
      85: invokeinterface #28,  1           // InterfaceMethod org/apache/hadoop/hbase/Cell.getRowOffset:()I
      90: iload_3
      91: invokestatic  #91                 // Method org/apache/hadoop/hbase/util/Bytes.equals:([BII[BII)Z
      94: ifne          99
      97: iconst_0
      98: ireturn
      99: aload_0
     100: invokeinterface #35,  1           // InterfaceMethod org/apache/hadoop/hbase/Cell.getFamilyArray:()[B
     105: aload_0
     106: invokeinterface #36,  1           // InterfaceMethod org/apache/hadoop/hbase/Cell.getFamilyOffset:()I
     111: iload         4
     113: aload_1
     114: invokeinterface #35,  1           // InterfaceMethod org/apache/hadoop/hbase/Cell.getFamilyArray:()[B
     119: aload_1
     120: invokeinterface #36,  1           // InterfaceMethod org/apache/hadoop/hbase/Cell.getFamilyOffset:()I
     125: iload         5
     127: invokestatic  #91                 // Method org/apache/hadoop/hbase/util/Bytes.equals:([BII[BII)Z
     130: ifne          135
     133: iconst_0
     134: ireturn
     135: aload_0
     136: invokeinterface #39,  1           // InterfaceMethod org/apache/hadoop/hbase/Cell.getQualifierArray:()[B
     141: aload_0
     142: invokeinterface #40,  1           // InterfaceMethod org/apache/hadoop/hbase/Cell.getQualifierOffset:()I
     147: iload         6
     149: aload_1
     150: invokeinterface #39,  1           // InterfaceMethod org/apache/hadoop/hbase/Cell.getQualifierArray:()[B
     155: aload_1
     156: invokeinterface #40,  1           // InterfaceMethod org/apache/hadoop/hbase/Cell.getQualifierOffset:()I
     161: iload         7
     163: invokestatic  #91                 // Method org/apache/hadoop/hbase/util/Bytes.equals:([BII[BII)Z
     166: ireturn

  public static final int compareQualifiers(org.apache.hadoop.hbase.Cell, byte[], int, int);
    Code:
       0: aload_0
       1: instanceof    #23                 // class org/apache/hadoop/hbase/ByteBufferExtendedCell
       4: ifeq          34
       7: aload_0
       8: checkcast     #23                 // class org/apache/hadoop/hbase/ByteBufferExtendedCell
      11: invokevirtual #37                 // Method org/apache/hadoop/hbase/ByteBufferExtendedCell.getQualifierByteBuffer:()Ljava/nio/ByteBuffer;
      14: aload_0
      15: checkcast     #23                 // class org/apache/hadoop/hbase/ByteBufferExtendedCell
      18: invokevirtual #38                 // Method org/apache/hadoop/hbase/ByteBufferExtendedCell.getQualifierPosition:()I
      21: aload_0
      22: invokeinterface #12,  1           // InterfaceMethod org/apache/hadoop/hbase/Cell.getQualifierLength:()I
      27: aload_1
      28: iload_2
      29: iload_3
      30: invokestatic  #102                // Method org/apache/hadoop/hbase/util/ByteBufferUtils.compareTo:(Ljava/nio/ByteBuffer;II[BII)I
      33: ireturn
      34: aload_0
      35: invokeinterface #39,  1           // InterfaceMethod org/apache/hadoop/hbase/Cell.getQualifierArray:()[B
      40: aload_0
      41: invokeinterface #40,  1           // InterfaceMethod org/apache/hadoop/hbase/Cell.getQualifierOffset:()I
      46: aload_0
      47: invokeinterface #12,  1           // InterfaceMethod org/apache/hadoop/hbase/Cell.getQualifierLength:()I
      52: aload_1
      53: iload_2
      54: iload_3
      55: invokestatic  #162                // Method org/apache/hadoop/hbase/util/Bytes.compareTo:([BII[BII)I
      58: ireturn

  public static final int compare(org.apache.hadoop.hbase.CellComparator, org.apache.hadoop.hbase.Cell, byte[], int, int);
    Code:
       0: aload_2
       1: iload_3
       2: invokestatic  #163                // Method org/apache/hadoop/hbase/util/Bytes.toShort:([BI)S
       5: istore        5
       7: aload_0
       8: aload_1
       9: aload_2
      10: iload_3
      11: iconst_2
      12: iadd
      13: iload         5
      15: invokeinterface #165,  5          // InterfaceMethod org/apache/hadoop/hbase/CellComparator.compareRows:(Lorg/apache/hadoop/hbase/Cell;[BII)I
      20: istore        6
      22: iload         6
      24: ifeq          30
      27: iload         6
      29: ireturn
      30: aload_0
      31: aload_1
      32: aload_2
      33: iload_3
      34: iload         4
      36: iload         5
      38: invokestatic  #166                // Method org/apache/hadoop/hbase/PrivateCellUtil.compareWithoutRow:(Lorg/apache/hadoop/hbase/CellComparator;Lorg/apache/hadoop/hbase/Cell;[BIIS)I
      41: ireturn

  public static final int compareFamilies(org.apache.hadoop.hbase.Cell, byte[], int, int);
    Code:
       0: aload_0
       1: instanceof    #23                 // class org/apache/hadoop/hbase/ByteBufferExtendedCell
       4: ifeq          34
       7: aload_0
       8: checkcast     #23                 // class org/apache/hadoop/hbase/ByteBufferExtendedCell
      11: invokevirtual #33                 // Method org/apache/hadoop/hbase/ByteBufferExtendedCell.getFamilyByteBuffer:()Ljava/nio/ByteBuffer;
      14: aload_0
      15: checkcast     #23                 // class org/apache/hadoop/hbase/ByteBufferExtendedCell
      18: invokevirtual #34                 // Method org/apache/hadoop/hbase/ByteBufferExtendedCell.getFamilyPosition:()I
      21: aload_0
      22: invokeinterface #10,  1           // InterfaceMethod org/apache/hadoop/hbase/Cell.getFamilyLength:()B
      27: aload_1
      28: iload_2
      29: iload_3
      30: invokestatic  #102                // Method org/apache/hadoop/hbase/util/ByteBufferUtils.compareTo:(Ljava/nio/ByteBuffer;II[BII)I
      33: ireturn
      34: aload_0
      35: invokeinterface #35,  1           // InterfaceMethod org/apache/hadoop/hbase/Cell.getFamilyArray:()[B
      40: aload_0
      41: invokeinterface #36,  1           // InterfaceMethod org/apache/hadoop/hbase/Cell.getFamilyOffset:()I
      46: aload_0
      47: invokeinterface #10,  1           // InterfaceMethod org/apache/hadoop/hbase/Cell.getFamilyLength:()B
      52: aload_1
      53: iload_2
      54: iload_3
      55: invokestatic  #162                // Method org/apache/hadoop/hbase/util/Bytes.compareTo:([BII[BII)I
      58: ireturn

  public static final int compareColumns(org.apache.hadoop.hbase.Cell, byte[], int, int, int, int);
    Code:
       0: aload_0
       1: aload_1
       2: iload_2
       3: iload_3
       4: invokestatic  #167                // Method compareFamilies:(Lorg/apache/hadoop/hbase/Cell;[BII)I
       7: istore        6
       9: iload         6
      11: ifeq          17
      14: iload         6
      16: ireturn
      17: aload_0
      18: aload_1
      19: iload         4
      21: iload         5
      23: invokestatic  #168                // Method compareQualifiers:(Lorg/apache/hadoop/hbase/Cell;[BII)I
      26: ireturn
}
