Compiled from "CellBlockBuilder.java"
final class org.apache.hadoop.hbase.ipc.CellBlockBuilder$ByteBufOutputStreamSupplier implements org.apache.hadoop.hbase.ipc.CellBlockBuilder$OutputStreamSupplier {
  public org.apache.hadoop.hbase.ipc.CellBlockBuilder$ByteBufOutputStreamSupplier(org.apache.hbase.thirdparty.io.netty.buffer.ByteBufAllocator);
    Code:
       0: aload_0
       1: invokespecial #2                  // Method java/lang/Object."<init>":()V
       4: aload_0
       5: aload_1
       6: putfield      #3                  // Field alloc:Lorg/apache/hbase/thirdparty/io/netty/buffer/ByteBufAllocator;
       9: return

  public java.io.OutputStream get(int);
    Code:
       0: aload_0
       1: aload_0
       2: getfield      #3                  // Field alloc:Lorg/apache/hbase/thirdparty/io/netty/buffer/ByteBufAllocator;
       5: iload_1
       6: invokeinterface #4,  2            // InterfaceMethod org/apache/hbase/thirdparty/io/netty/buffer/ByteBufAllocator.buffer:(I)Lorg/apache/hbase/thirdparty/io/netty/buffer/ByteBuf;
      11: putfield      #1                  // Field buf:Lorg/apache/hbase/thirdparty/io/netty/buffer/ByteBuf;
      14: new           #5                  // class org/apache/hbase/thirdparty/io/netty/buffer/ByteBufOutputStream
      17: dup
      18: aload_0
      19: getfield      #1                  // Field buf:Lorg/apache/hbase/thirdparty/io/netty/buffer/ByteBuf;
      22: invokespecial #6                  // Method org/apache/hbase/thirdparty/io/netty/buffer/ByteBufOutputStream."<init>":(Lorg/apache/hbase/thirdparty/io/netty/buffer/ByteBuf;)V
      25: areturn

  public int size();
    Code:
       0: aload_0
       1: getfield      #1                  // Field buf:Lorg/apache/hbase/thirdparty/io/netty/buffer/ByteBuf;
       4: invokevirtual #7                  // Method org/apache/hbase/thirdparty/io/netty/buffer/ByteBuf.writerIndex:()I
       7: ireturn

  static org.apache.hbase.thirdparty.io.netty.buffer.ByteBuf access$200(org.apache.hadoop.hbase.ipc.CellBlockBuilder$ByteBufOutputStreamSupplier);
    Code:
       0: aload_0
       1: getfield      #1                  // Field buf:Lorg/apache/hbase/thirdparty/io/netty/buffer/ByteBuf;
       4: areturn
}
