Compiled from "ChunkCreator.java"
class org.apache.hadoop.hbase.regionserver.ChunkCreator$MemStoreChunkPool$StatisticsThread extends java.lang.Thread {
  final org.apache.hadoop.hbase.regionserver.ChunkCreator$MemStoreChunkPool this$1;

  org.apache.hadoop.hbase.regionserver.ChunkCreator$MemStoreChunkPool$StatisticsThread(org.apache.hadoop.hbase.regionserver.ChunkCreator$MemStoreChunkPool);
    Code:
       0: aload_0
       1: aload_1
       2: putfield      #1                  // Field this$1:Lorg/apache/hadoop/hbase/regionserver/ChunkCreator$MemStoreChunkPool;
       5: aload_0
       6: ldc           #2                  // String MemStoreChunkPool.StatisticsThread
       8: invokespecial #3                  // Method java/lang/Thread."<init>":(Ljava/lang/String;)V
      11: aload_0
      12: iconst_1
      13: invokevirtual #4                  // Method setDaemon:(Z)V
      16: return

  public void run();
    Code:
       0: aload_0
       1: invokespecial #5                  // Method logStats:()V
       4: return
}
