Compiled from "ClassFinder.java"
class org.apache.hadoop.hbase.ClassFinder$FileFilterWithName implements java.io.FileFilter {
  public org.apache.hadoop.hbase.ClassFinder$FileFilterWithName(org.apache.hadoop.hbase.ClassFinder$FileNameFilter);
    Code:
       0: aload_0
       1: invokespecial #1                  // Method java/lang/Object."<init>":()V
       4: aload_0
       5: aload_1
       6: putfield      #2                  // Field nameFilter:Lorg/apache/hadoop/hbase/ClassFinder$FileNameFilter;
       9: return

  public boolean accept(java.io.File);
    Code:
       0: aload_1
       1: invokevirtual #3                  // Method java/io/File.isDirectory:()Z
       4: ifne          48
       7: aload_1
       8: invokevirtual #4                  // Method java/io/File.getName:()Ljava/lang/String;
      11: invokestatic  #5                  // Method org/apache/hadoop/hbase/ClassFinder.access$000:()Ljava/lang/String;
      14: invokevirtual #6                  // Method java/lang/String.endsWith:(Ljava/lang/String;)Z
      17: ifeq          52
      20: aconst_null
      21: aload_0
      22: getfield      #2                  // Field nameFilter:Lorg/apache/hadoop/hbase/ClassFinder$FileNameFilter;
      25: if_acmpeq     48
      28: aload_0
      29: getfield      #2                  // Field nameFilter:Lorg/apache/hadoop/hbase/ClassFinder$FileNameFilter;
      32: aload_1
      33: invokevirtual #4                  // Method java/io/File.getName:()Ljava/lang/String;
      36: aload_1
      37: invokevirtual #7                  // Method java/io/File.getAbsolutePath:()Ljava/lang/String;
      40: invokeinterface #8,  3            // InterfaceMethod org/apache/hadoop/hbase/ClassFinder$FileNameFilter.isCandidateFile:(Ljava/lang/String;Ljava/lang/String;)Z
      45: ifeq          52
      48: iconst_1
      49: goto          53
      52: iconst_0
      53: ireturn
}
