Compiled from "ClassLoaderBase.java"
public class org.apache.hadoop.hbase.util.ClassLoaderBase extends java.net.URLClassLoader {
  protected static final java.lang.String DEFAULT_LOCAL_DIR;

  protected static final java.lang.String LOCAL_DIR_KEY;

  protected final java.lang.ClassLoader parent;

  public org.apache.hadoop.hbase.util.ClassLoaderBase(java.lang.ClassLoader);
    Code:
       0: aload_0
       1: iconst_0
       2: anewarray     #1                  // class java/net/URL
       5: aload_1
       6: invokespecial #2                  // Method java/net/URLClassLoader."<init>":([Ljava/net/URL;Ljava/lang/ClassLoader;)V
       9: aload_1
      10: ldc           #3                  // String No parent classloader!
      12: invokestatic  #4                  // Method org/apache/hbase/thirdparty/com/google/common/base/Preconditions.checkNotNull:(Ljava/lang/Object;Ljava/lang/Object;)Ljava/lang/Object;
      15: pop
      16: aload_0
      17: aload_1
      18: putfield      #5                  // Field parent:Ljava/lang/ClassLoader;
      21: return
}
