Compiled from "ClassTestFinder.java"
public class org.apache.hadoop.hbase.ClassTestFinder$TestClassFilter implements org.apache.hadoop.hbase.ClassFinder$ClassFilter {
  public org.apache.hadoop.hbase.ClassTestFinder$TestClassFilter(java.lang.Class<?>);
    Code:
       0: aload_0
       1: invokespecial #1                  // Method java/lang/Object."<init>":()V
       4: aload_0
       5: aconst_null
       6: putfield      #2                  // Field categoryAnnotation:Ljava/lang/Class;
       9: aload_0
      10: aload_1
      11: putfield      #2                  // Field categoryAnnotation:Ljava/lang/Class;
      14: return

  public org.apache.hadoop.hbase.ClassTestFinder$TestClassFilter();
    Code:
       0: aload_0
       1: aconst_null
       2: invokespecial #3                  // Method "<init>":(Ljava/lang/Class;)V
       5: return

  public boolean isCandidateClass(java.lang.Class<?>);
    Code:
       0: aload_0
       1: aload_1
       2: invokespecial #4                  // Method isTestClass:(Ljava/lang/Class;)Z
       5: ifeq          20
       8: aload_0
       9: aload_1
      10: invokespecial #5                  // Method isCategorizedClass:(Ljava/lang/Class;)Z
      13: ifeq          20
      16: iconst_1
      17: goto          21
      20: iconst_0
      21: ireturn
}
