Compiled from "ClickjackingPreventionFilter.java"
public class org.apache.hadoop.hbase.http.ClickjackingPreventionFilter implements javax.servlet.Filter {
  public org.apache.hadoop.hbase.http.ClickjackingPreventionFilter();
    Code:
       0: aload_0
       1: invokespecial #1                  // Method java/lang/Object."<init>":()V
       4: return

  public void init(javax.servlet.FilterConfig) throws javax.servlet.ServletException;
    Code:
       0: aload_0
       1: aload_1
       2: putfield      #2                  // Field filterConfig:Ljavax/servlet/FilterConfig;
       5: return

  public void doFilter(javax.servlet.ServletRequest, javax.servlet.ServletResponse, javax.servlet.FilterChain) throws java.io.IOException, javax.servlet.ServletException;
    Code:
       0: aload_2
       1: checkcast     #3                  // class javax/servlet/http/HttpServletResponse
       4: astore        4
       6: aload         4
       8: ldc           #4                  // String X-Frame-Options
      10: aload_0
      11: getfield      #2                  // Field filterConfig:Ljavax/servlet/FilterConfig;
      14: ldc           #5                  // String xframeoptions
      16: invokeinterface #6,  2            // InterfaceMethod javax/servlet/FilterConfig.getInitParameter:(Ljava/lang/String;)Ljava/lang/String;
      21: invokeinterface #7,  3            // InterfaceMethod javax/servlet/http/HttpServletResponse.addHeader:(Ljava/lang/String;Ljava/lang/String;)V
      26: aload_3
      27: aload_1
      28: aload_2
      29: invokeinterface #8,  3            // InterfaceMethod javax/servlet/FilterChain.doFilter:(Ljavax/servlet/ServletRequest;Ljavax/servlet/ServletResponse;)V
      34: return

  public void destroy();
    Code:
       0: return
}
