Compiled from "ClientAsyncPrefetchScanner.java"
class org.apache.hadoop.hbase.client.ClientAsyncPrefetchScanner$PrefetchRunnable implements java.lang.Runnable {
  final org.apache.hadoop.hbase.client.ClientAsyncPrefetchScanner this$0;

  public void run();
    Code:
       0: aload_0
       1: getfield      #2                  // Field this$0:Lorg/apache/hadoop/hbase/client/ClientAsyncPrefetchScanner;
       4: getfield      #4                  // Field org/apache/hadoop/hbase/client/ClientAsyncPrefetchScanner.closed:Z
       7: ifne          235
      10: iconst_0
      11: istore_1
      12: aload_0
      13: getfield      #2                  // Field this$0:Lorg/apache/hadoop/hbase/client/ClientAsyncPrefetchScanner;
      16: invokestatic  #5                  // Method org/apache/hadoop/hbase/client/ClientAsyncPrefetchScanner.access$100:(Lorg/apache/hadoop/hbase/client/ClientAsyncPrefetchScanner;)Ljava/util/concurrent/locks/Lock;
      19: invokeinterface #6,  1            // InterfaceMethod java/util/concurrent/locks/Lock.lock:()V
      24: aload_0
      25: getfield      #2                  // Field this$0:Lorg/apache/hadoop/hbase/client/ClientAsyncPrefetchScanner;
      28: invokestatic  #7                  // Method org/apache/hadoop/hbase/client/ClientAsyncPrefetchScanner.access$200:(Lorg/apache/hadoop/hbase/client/ClientAsyncPrefetchScanner;)Z
      31: ifne          49
      34: aload_0
      35: getfield      #2                  // Field this$0:Lorg/apache/hadoop/hbase/client/ClientAsyncPrefetchScanner;
      38: invokestatic  #8                  // Method org/apache/hadoop/hbase/client/ClientAsyncPrefetchScanner.access$300:(Lorg/apache/hadoop/hbase/client/ClientAsyncPrefetchScanner;)Ljava/util/concurrent/locks/Condition;
      41: invokeinterface #9,  1            // InterfaceMethod java/util/concurrent/locks/Condition.await:()V
      46: goto          24
      49: aload_0
      50: getfield      #2                  // Field this$0:Lorg/apache/hadoop/hbase/client/ClientAsyncPrefetchScanner;
      53: invokevirtual #10                 // Method org/apache/hadoop/hbase/client/ClientAsyncPrefetchScanner.loadCache:()V
      56: iconst_1
      57: istore_1
      58: aload_0
      59: getfield      #2                  // Field this$0:Lorg/apache/hadoop/hbase/client/ClientAsyncPrefetchScanner;
      62: invokestatic  #11                 // Method org/apache/hadoop/hbase/client/ClientAsyncPrefetchScanner.access$500:(Lorg/apache/hadoop/hbase/client/ClientAsyncPrefetchScanner;)Ljava/util/concurrent/locks/Condition;
      65: invokeinterface #12,  1           // InterfaceMethod java/util/concurrent/locks/Condition.signalAll:()V
      70: aload_0
      71: getfield      #2                  // Field this$0:Lorg/apache/hadoop/hbase/client/ClientAsyncPrefetchScanner;
      74: invokestatic  #5                  // Method org/apache/hadoop/hbase/client/ClientAsyncPrefetchScanner.access$100:(Lorg/apache/hadoop/hbase/client/ClientAsyncPrefetchScanner;)Ljava/util/concurrent/locks/Lock;
      77: invokeinterface #13,  1           // InterfaceMethod java/util/concurrent/locks/Lock.unlock:()V
      82: aload_0
      83: getfield      #2                  // Field this$0:Lorg/apache/hadoop/hbase/client/ClientAsyncPrefetchScanner;
      86: invokestatic  #14                 // Method org/apache/hadoop/hbase/client/ClientAsyncPrefetchScanner.access$600:(Lorg/apache/hadoop/hbase/client/ClientAsyncPrefetchScanner;)Ljava/util/function/Consumer;
      89: ifnull        232
      92: aload_0
      93: getfield      #2                  // Field this$0:Lorg/apache/hadoop/hbase/client/ClientAsyncPrefetchScanner;
      96: invokestatic  #14                 // Method org/apache/hadoop/hbase/client/ClientAsyncPrefetchScanner.access$600:(Lorg/apache/hadoop/hbase/client/ClientAsyncPrefetchScanner;)Ljava/util/function/Consumer;
      99: iload_1
     100: invokestatic  #15                 // Method java/lang/Boolean.valueOf:(Z)Ljava/lang/Boolean;
     103: invokeinterface #16,  2           // InterfaceMethod java/util/function/Consumer.accept:(Ljava/lang/Object;)V
     108: goto          232
     111: astore_2
     112: aload_0
     113: getfield      #2                  // Field this$0:Lorg/apache/hadoop/hbase/client/ClientAsyncPrefetchScanner;
     116: invokestatic  #18                 // Method org/apache/hadoop/hbase/client/ClientAsyncPrefetchScanner.access$400:(Lorg/apache/hadoop/hbase/client/ClientAsyncPrefetchScanner;)Ljava/util/Queue;
     119: aload_2
     120: invokeinterface #19,  2           // InterfaceMethod java/util/Queue.add:(Ljava/lang/Object;)Z
     125: pop
     126: aload_0
     127: getfield      #2                  // Field this$0:Lorg/apache/hadoop/hbase/client/ClientAsyncPrefetchScanner;
     130: invokestatic  #11                 // Method org/apache/hadoop/hbase/client/ClientAsyncPrefetchScanner.access$500:(Lorg/apache/hadoop/hbase/client/ClientAsyncPrefetchScanner;)Ljava/util/concurrent/locks/Condition;
     133: invokeinterface #12,  1           // InterfaceMethod java/util/concurrent/locks/Condition.signalAll:()V
     138: aload_0
     139: getfield      #2                  // Field this$0:Lorg/apache/hadoop/hbase/client/ClientAsyncPrefetchScanner;
     142: invokestatic  #5                  // Method org/apache/hadoop/hbase/client/ClientAsyncPrefetchScanner.access$100:(Lorg/apache/hadoop/hbase/client/ClientAsyncPrefetchScanner;)Ljava/util/concurrent/locks/Lock;
     145: invokeinterface #13,  1           // InterfaceMethod java/util/concurrent/locks/Lock.unlock:()V
     150: aload_0
     151: getfield      #2                  // Field this$0:Lorg/apache/hadoop/hbase/client/ClientAsyncPrefetchScanner;
     154: invokestatic  #14                 // Method org/apache/hadoop/hbase/client/ClientAsyncPrefetchScanner.access$600:(Lorg/apache/hadoop/hbase/client/ClientAsyncPrefetchScanner;)Ljava/util/function/Consumer;
     157: ifnull        232
     160: aload_0
     161: getfield      #2                  // Field this$0:Lorg/apache/hadoop/hbase/client/ClientAsyncPrefetchScanner;
     164: invokestatic  #14                 // Method org/apache/hadoop/hbase/client/ClientAsyncPrefetchScanner.access$600:(Lorg/apache/hadoop/hbase/client/ClientAsyncPrefetchScanner;)Ljava/util/function/Consumer;
     167: iload_1
     168: invokestatic  #15                 // Method java/lang/Boolean.valueOf:(Z)Ljava/lang/Boolean;
     171: invokeinterface #16,  2           // InterfaceMethod java/util/function/Consumer.accept:(Ljava/lang/Object;)V
     176: goto          232
     179: astore_3
     180: aload_0
     181: getfield      #2                  // Field this$0:Lorg/apache/hadoop/hbase/client/ClientAsyncPrefetchScanner;
     184: invokestatic  #11                 // Method org/apache/hadoop/hbase/client/ClientAsyncPrefetchScanner.access$500:(Lorg/apache/hadoop/hbase/client/ClientAsyncPrefetchScanner;)Ljava/util/concurrent/locks/Condition;
     187: invokeinterface #12,  1           // InterfaceMethod java/util/concurrent/locks/Condition.signalAll:()V
     192: aload_0
     193: getfield      #2                  // Field this$0:Lorg/apache/hadoop/hbase/client/ClientAsyncPrefetchScanner;
     196: invokestatic  #5                  // Method org/apache/hadoop/hbase/client/ClientAsyncPrefetchScanner.access$100:(Lorg/apache/hadoop/hbase/client/ClientAsyncPrefetchScanner;)Ljava/util/concurrent/locks/Lock;
     199: invokeinterface #13,  1           // InterfaceMethod java/util/concurrent/locks/Lock.unlock:()V
     204: aload_0
     205: getfield      #2                  // Field this$0:Lorg/apache/hadoop/hbase/client/ClientAsyncPrefetchScanner;
     208: invokestatic  #14                 // Method org/apache/hadoop/hbase/client/ClientAsyncPrefetchScanner.access$600:(Lorg/apache/hadoop/hbase/client/ClientAsyncPrefetchScanner;)Ljava/util/function/Consumer;
     211: ifnull        230
     214: aload_0
     215: getfield      #2                  // Field this$0:Lorg/apache/hadoop/hbase/client/ClientAsyncPrefetchScanner;
     218: invokestatic  #14                 // Method org/apache/hadoop/hbase/client/ClientAsyncPrefetchScanner.access$600:(Lorg/apache/hadoop/hbase/client/ClientAsyncPrefetchScanner;)Ljava/util/function/Consumer;
     221: iload_1
     222: invokestatic  #15                 // Method java/lang/Boolean.valueOf:(Z)Ljava/lang/Boolean;
     225: invokeinterface #16,  2           // InterfaceMethod java/util/function/Consumer.accept:(Ljava/lang/Object;)V
     230: aload_3
     231: athrow
     232: goto          0
     235: return
    Exception table:
       from    to  target type
          12    58   111   Class java/lang/Exception
          12    58   179   any
         111   126   179   any

  org.apache.hadoop.hbase.client.ClientAsyncPrefetchScanner$PrefetchRunnable(org.apache.hadoop.hbase.client.ClientAsyncPrefetchScanner, org.apache.hadoop.hbase.client.ClientAsyncPrefetchScanner$1);
    Code:
       0: aload_0
       1: aload_1
       2: invokespecial #1                  // Method "<init>":(Lorg/apache/hadoop/hbase/client/ClientAsyncPrefetchScanner;)V
       5: return
}
