Compiled from "ClientProtos.java"
public final class org.apache.hadoop.hbase.protobuf.generated.ClientProtos$MultiRequest$Builder extends com.google.protobuf.GeneratedMessage$Builder<org.apache.hadoop.hbase.protobuf.generated.ClientProtos$MultiRequest$Builder> implements org.apache.hadoop.hbase.protobuf.generated.ClientProtos$MultiRequestOrBuilder {
  public static final com.google.protobuf.Descriptors$Descriptor getDescriptor();
    Code:
       0: invokestatic  #3                  // Method org/apache/hadoop/hbase/protobuf/generated/ClientProtos.access$44100:()Lcom/google/protobuf/Descriptors$Descriptor;
       3: areturn

  protected com.google.protobuf.GeneratedMessage$FieldAccessorTable internalGetFieldAccessorTable();
    Code:
       0: invokestatic  #4                  // Method org/apache/hadoop/hbase/protobuf/generated/ClientProtos.access$44200:()Lcom/google/protobuf/GeneratedMessage$FieldAccessorTable;
       3: ldc           #5                  // class org/apache/hadoop/hbase/protobuf/generated/ClientProtos$MultiRequest
       5: ldc           #6                  // class org/apache/hadoop/hbase/protobuf/generated/ClientProtos$MultiRequest$Builder
       7: invokevirtual #7                  // Method com/google/protobuf/GeneratedMessage$FieldAccessorTable.ensureFieldAccessorsInitialized:(Ljava/lang/Class;Ljava/lang/Class;)Lcom/google/protobuf/GeneratedMessage$FieldAccessorTable;
      10: areturn

  public org.apache.hadoop.hbase.protobuf.generated.ClientProtos$MultiRequest$Builder clear();
    Code:
       0: aload_0
       1: invokespecial #19                 // Method com/google/protobuf/GeneratedMessage$Builder.clear:()Lcom/google/protobuf/GeneratedMessage$Builder;
       4: pop
       5: aload_0
       6: getfield      #20                 // Field regionActionBuilder_:Lcom/google/protobuf/RepeatedFieldBuilder;
       9: ifnonnull     33
      12: aload_0
      13: invokestatic  #9                  // Method java/util/Collections.emptyList:()Ljava/util/List;
      16: putfield      #10                 // Field regionAction_:Ljava/util/List;
      19: aload_0
      20: aload_0
      21: getfield      #21                 // Field bitField0_:I
      24: bipush        -2
      26: iand
      27: putfield      #21                 // Field bitField0_:I
      30: goto          40
      33: aload_0
      34: getfield      #20                 // Field regionActionBuilder_:Lcom/google/protobuf/RepeatedFieldBuilder;
      37: invokevirtual #22                 // Method com/google/protobuf/RepeatedFieldBuilder.clear:()V
      40: aload_0
      41: lconst_0
      42: putfield      #23                 // Field nonceGroup_:J
      45: aload_0
      46: aload_0
      47: getfield      #21                 // Field bitField0_:I
      50: bipush        -3
      52: iand
      53: putfield      #21                 // Field bitField0_:I
      56: aload_0
      57: getfield      #24                 // Field conditionBuilder_:Lcom/google/protobuf/SingleFieldBuilder;
      60: ifnonnull     73
      63: aload_0
      64: invokestatic  #11                 // Method org/apache/hadoop/hbase/protobuf/generated/ClientProtos$Condition.getDefaultInstance:()Lorg/apache/hadoop/hbase/protobuf/generated/ClientProtos$Condition;
      67: putfield      #12                 // Field condition_:Lorg/apache/hadoop/hbase/protobuf/generated/ClientProtos$Condition;
      70: goto          81
      73: aload_0
      74: getfield      #24                 // Field conditionBuilder_:Lcom/google/protobuf/SingleFieldBuilder;
      77: invokevirtual #25                 // Method com/google/protobuf/SingleFieldBuilder.clear:()Lcom/google/protobuf/SingleFieldBuilder;
      80: pop
      81: aload_0
      82: aload_0
      83: getfield      #21                 // Field bitField0_:I
      86: bipush        -5
      88: iand
      89: putfield      #21                 // Field bitField0_:I
      92: aload_0
      93: areturn

  public org.apache.hadoop.hbase.protobuf.generated.ClientProtos$MultiRequest$Builder clone();
    Code:
       0: invokestatic  #2                  // Method create:()Lorg/apache/hadoop/hbase/protobuf/generated/ClientProtos$MultiRequest$Builder;
       3: aload_0
       4: invokevirtual #26                 // Method buildPartial:()Lorg/apache/hadoop/hbase/protobuf/generated/ClientProtos$MultiRequest;
       7: invokevirtual #27                 // Method mergeFrom:(Lorg/apache/hadoop/hbase/protobuf/generated/ClientProtos$MultiRequest;)Lorg/apache/hadoop/hbase/protobuf/generated/ClientProtos$MultiRequest$Builder;
      10: areturn

  public com.google.protobuf.Descriptors$Descriptor getDescriptorForType();
    Code:
       0: invokestatic  #3                  // Method org/apache/hadoop/hbase/protobuf/generated/ClientProtos.access$44100:()Lcom/google/protobuf/Descriptors$Descriptor;
       3: areturn

  public org.apache.hadoop.hbase.protobuf.generated.ClientProtos$MultiRequest getDefaultInstanceForType();
    Code:
       0: invokestatic  #28                 // Method org/apache/hadoop/hbase/protobuf/generated/ClientProtos$MultiRequest.getDefaultInstance:()Lorg/apache/hadoop/hbase/protobuf/generated/ClientProtos$MultiRequest;
       3: areturn

  public org.apache.hadoop.hbase.protobuf.generated.ClientProtos$MultiRequest build();
    Code:
       0: aload_0
       1: invokevirtual #26                 // Method buildPartial:()Lorg/apache/hadoop/hbase/protobuf/generated/ClientProtos$MultiRequest;
       4: astore_1
       5: aload_1
       6: invokevirtual #29                 // Method org/apache/hadoop/hbase/protobuf/generated/ClientProtos$MultiRequest.isInitialized:()Z
       9: ifne          17
      12: aload_1
      13: invokestatic  #30                 // Method newUninitializedMessageException:(Lcom/google/protobuf/Message;)Lcom/google/protobuf/UninitializedMessageException;
      16: athrow
      17: aload_1
      18: areturn

  public org.apache.hadoop.hbase.protobuf.generated.ClientProtos$MultiRequest buildPartial();
    Code:
       0: new           #5                  // class org/apache/hadoop/hbase/protobuf/generated/ClientProtos$MultiRequest
       3: dup
       4: aload_0
       5: aconst_null
       6: invokespecial #31                 // Method org/apache/hadoop/hbase/protobuf/generated/ClientProtos$MultiRequest."<init>":(Lcom/google/protobuf/GeneratedMessage$Builder;Lorg/apache/hadoop/hbase/protobuf/generated/ClientProtos$1;)V
       9: astore_1
      10: aload_0
      11: getfield      #21                 // Field bitField0_:I
      14: istore_2
      15: iconst_0
      16: istore_3
      17: aload_0
      18: getfield      #20                 // Field regionActionBuilder_:Lcom/google/protobuf/RepeatedFieldBuilder;
      21: ifnonnull     68
      24: aload_0
      25: getfield      #21                 // Field bitField0_:I
      28: iconst_1
      29: iand
      30: iconst_1
      31: if_icmpne     56
      34: aload_0
      35: aload_0
      36: getfield      #10                 // Field regionAction_:Ljava/util/List;
      39: invokestatic  #32                 // Method java/util/Collections.unmodifiableList:(Ljava/util/List;)Ljava/util/List;
      42: putfield      #10                 // Field regionAction_:Ljava/util/List;
      45: aload_0
      46: aload_0
      47: getfield      #21                 // Field bitField0_:I
      50: bipush        -2
      52: iand
      53: putfield      #21                 // Field bitField0_:I
      56: aload_1
      57: aload_0
      58: getfield      #10                 // Field regionAction_:Ljava/util/List;
      61: invokestatic  #33                 // Method org/apache/hadoop/hbase/protobuf/generated/ClientProtos$MultiRequest.access$44802:(Lorg/apache/hadoop/hbase/protobuf/generated/ClientProtos$MultiRequest;Ljava/util/List;)Ljava/util/List;
      64: pop
      65: goto          80
      68: aload_1
      69: aload_0
      70: getfield      #20                 // Field regionActionBuilder_:Lcom/google/protobuf/RepeatedFieldBuilder;
      73: invokevirtual #34                 // Method com/google/protobuf/RepeatedFieldBuilder.build:()Ljava/util/List;
      76: invokestatic  #33                 // Method org/apache/hadoop/hbase/protobuf/generated/ClientProtos$MultiRequest.access$44802:(Lorg/apache/hadoop/hbase/protobuf/generated/ClientProtos$MultiRequest;Ljava/util/List;)Ljava/util/List;
      79: pop
      80: iload_2
      81: iconst_2
      82: iand
      83: iconst_2
      84: if_icmpne     91
      87: iload_3
      88: iconst_1
      89: ior
      90: istore_3
      91: aload_1
      92: aload_0
      93: getfield      #23                 // Field nonceGroup_:J
      96: invokestatic  #35                 // Method org/apache/hadoop/hbase/protobuf/generated/ClientProtos$MultiRequest.access$44902:(Lorg/apache/hadoop/hbase/protobuf/generated/ClientProtos$MultiRequest;J)J
      99: pop2
     100: iload_2
     101: iconst_4
     102: iand
     103: iconst_4
     104: if_icmpne     111
     107: iload_3
     108: iconst_2
     109: ior
     110: istore_3
     111: aload_0
     112: getfield      #24                 // Field conditionBuilder_:Lcom/google/protobuf/SingleFieldBuilder;
     115: ifnonnull     130
     118: aload_1
     119: aload_0
     120: getfield      #12                 // Field condition_:Lorg/apache/hadoop/hbase/protobuf/generated/ClientProtos$Condition;
     123: invokestatic  #36                 // Method org/apache/hadoop/hbase/protobuf/generated/ClientProtos$MultiRequest.access$45002:(Lorg/apache/hadoop/hbase/protobuf/generated/ClientProtos$MultiRequest;Lorg/apache/hadoop/hbase/protobuf/generated/ClientProtos$Condition;)Lorg/apache/hadoop/hbase/protobuf/generated/ClientProtos$Condition;
     126: pop
     127: goto          145
     130: aload_1
     131: aload_0
     132: getfield      #24                 // Field conditionBuilder_:Lcom/google/protobuf/SingleFieldBuilder;
     135: invokevirtual #37                 // Method com/google/protobuf/SingleFieldBuilder.build:()Lcom/google/protobuf/GeneratedMessage;
     138: checkcast     #38                 // class org/apache/hadoop/hbase/protobuf/generated/ClientProtos$Condition
     141: invokestatic  #36                 // Method org/apache/hadoop/hbase/protobuf/generated/ClientProtos$MultiRequest.access$45002:(Lorg/apache/hadoop/hbase/protobuf/generated/ClientProtos$MultiRequest;Lorg/apache/hadoop/hbase/protobuf/generated/ClientProtos$Condition;)Lorg/apache/hadoop/hbase/protobuf/generated/ClientProtos$Condition;
     144: pop
     145: aload_1
     146: iload_3
     147: invokestatic  #39                 // Method org/apache/hadoop/hbase/protobuf/generated/ClientProtos$MultiRequest.access$45102:(Lorg/apache/hadoop/hbase/protobuf/generated/ClientProtos$MultiRequest;I)I
     150: pop
     151: aload_0
     152: invokevirtual #40                 // Method onBuilt:()V
     155: aload_1
     156: areturn

  public org.apache.hadoop.hbase.protobuf.generated.ClientProtos$MultiRequest$Builder mergeFrom(com.google.protobuf.Message);
    Code:
       0: aload_1
       1: instanceof    #5                  // class org/apache/hadoop/hbase/protobuf/generated/ClientProtos$MultiRequest
       4: ifeq          16
       7: aload_0
       8: aload_1
       9: checkcast     #5                  // class org/apache/hadoop/hbase/protobuf/generated/ClientProtos$MultiRequest
      12: invokevirtual #27                 // Method mergeFrom:(Lorg/apache/hadoop/hbase/protobuf/generated/ClientProtos$MultiRequest;)Lorg/apache/hadoop/hbase/protobuf/generated/ClientProtos$MultiRequest$Builder;
      15: areturn
      16: aload_0
      17: aload_1
      18: invokespecial #41                 // Method com/google/protobuf/GeneratedMessage$Builder.mergeFrom:(Lcom/google/protobuf/Message;)Lcom/google/protobuf/AbstractMessage$Builder;
      21: pop
      22: aload_0
      23: areturn

  public org.apache.hadoop.hbase.protobuf.generated.ClientProtos$MultiRequest$Builder mergeFrom(org.apache.hadoop.hbase.protobuf.generated.ClientProtos$MultiRequest);
    Code:
       0: aload_1
       1: invokestatic  #28                 // Method org/apache/hadoop/hbase/protobuf/generated/ClientProtos$MultiRequest.getDefaultInstance:()Lorg/apache/hadoop/hbase/protobuf/generated/ClientProtos$MultiRequest;
       4: if_acmpne     9
       7: aload_0
       8: areturn
       9: aload_0
      10: getfield      #20                 // Field regionActionBuilder_:Lcom/google/protobuf/RepeatedFieldBuilder;
      13: ifnonnull     87
      16: aload_1
      17: invokestatic  #42                 // Method org/apache/hadoop/hbase/protobuf/generated/ClientProtos$MultiRequest.access$44800:(Lorg/apache/hadoop/hbase/protobuf/generated/ClientProtos$MultiRequest;)Ljava/util/List;
      20: invokeinterface #43,  1           // InterfaceMethod java/util/List.isEmpty:()Z
      25: ifne          173
      28: aload_0
      29: getfield      #10                 // Field regionAction_:Ljava/util/List;
      32: invokeinterface #43,  1           // InterfaceMethod java/util/List.isEmpty:()Z
      37: ifeq          62
      40: aload_0
      41: aload_1
      42: invokestatic  #42                 // Method org/apache/hadoop/hbase/protobuf/generated/ClientProtos$MultiRequest.access$44800:(Lorg/apache/hadoop/hbase/protobuf/generated/ClientProtos$MultiRequest;)Ljava/util/List;
      45: putfield      #10                 // Field regionAction_:Ljava/util/List;
      48: aload_0
      49: aload_0
      50: getfield      #21                 // Field bitField0_:I
      53: bipush        -2
      55: iand
      56: putfield      #21                 // Field bitField0_:I
      59: goto          80
      62: aload_0
      63: invokespecial #44                 // Method ensureRegionActionIsMutable:()V
      66: aload_0
      67: getfield      #10                 // Field regionAction_:Ljava/util/List;
      70: aload_1
      71: invokestatic  #42                 // Method org/apache/hadoop/hbase/protobuf/generated/ClientProtos$MultiRequest.access$44800:(Lorg/apache/hadoop/hbase/protobuf/generated/ClientProtos$MultiRequest;)Ljava/util/List;
      74: invokeinterface #45,  2           // InterfaceMethod java/util/List.addAll:(Ljava/util/Collection;)Z
      79: pop
      80: aload_0
      81: invokevirtual #46                 // Method onChanged:()V
      84: goto          173
      87: aload_1
      88: invokestatic  #42                 // Method org/apache/hadoop/hbase/protobuf/generated/ClientProtos$MultiRequest.access$44800:(Lorg/apache/hadoop/hbase/protobuf/generated/ClientProtos$MultiRequest;)Ljava/util/List;
      91: invokeinterface #43,  1           // InterfaceMethod java/util/List.isEmpty:()Z
      96: ifne          173
      99: aload_0
     100: getfield      #20                 // Field regionActionBuilder_:Lcom/google/protobuf/RepeatedFieldBuilder;
     103: invokevirtual #47                 // Method com/google/protobuf/RepeatedFieldBuilder.isEmpty:()Z
     106: ifeq          161
     109: aload_0
     110: getfield      #20                 // Field regionActionBuilder_:Lcom/google/protobuf/RepeatedFieldBuilder;
     113: invokevirtual #48                 // Method com/google/protobuf/RepeatedFieldBuilder.dispose:()V
     116: aload_0
     117: aconst_null
     118: putfield      #20                 // Field regionActionBuilder_:Lcom/google/protobuf/RepeatedFieldBuilder;
     121: aload_0
     122: aload_1
     123: invokestatic  #42                 // Method org/apache/hadoop/hbase/protobuf/generated/ClientProtos$MultiRequest.access$44800:(Lorg/apache/hadoop/hbase/protobuf/generated/ClientProtos$MultiRequest;)Ljava/util/List;
     126: putfield      #10                 // Field regionAction_:Ljava/util/List;
     129: aload_0
     130: aload_0
     131: getfield      #21                 // Field bitField0_:I
     134: bipush        -2
     136: iand
     137: putfield      #21                 // Field bitField0_:I
     140: aload_0
     141: invokestatic  #49                 // Method org/apache/hadoop/hbase/protobuf/generated/ClientProtos$MultiRequest.access$45200:()Z
     144: ifeq          154
     147: aload_0
     148: invokespecial #16                 // Method getRegionActionFieldBuilder:()Lcom/google/protobuf/RepeatedFieldBuilder;
     151: goto          155
     154: aconst_null
     155: putfield      #20                 // Field regionActionBuilder_:Lcom/google/protobuf/RepeatedFieldBuilder;
     158: goto          173
     161: aload_0
     162: getfield      #20                 // Field regionActionBuilder_:Lcom/google/protobuf/RepeatedFieldBuilder;
     165: aload_1
     166: invokestatic  #42                 // Method org/apache/hadoop/hbase/protobuf/generated/ClientProtos$MultiRequest.access$44800:(Lorg/apache/hadoop/hbase/protobuf/generated/ClientProtos$MultiRequest;)Ljava/util/List;
     169: invokevirtual #50                 // Method com/google/protobuf/RepeatedFieldBuilder.addAllMessages:(Ljava/lang/Iterable;)Lcom/google/protobuf/RepeatedFieldBuilder;
     172: pop
     173: aload_1
     174: invokevirtual #51                 // Method org/apache/hadoop/hbase/protobuf/generated/ClientProtos$MultiRequest.hasNonceGroup:()Z
     177: ifeq          189
     180: aload_0
     181: aload_1
     182: invokevirtual #52                 // Method org/apache/hadoop/hbase/protobuf/generated/ClientProtos$MultiRequest.getNonceGroup:()J
     185: invokevirtual #53                 // Method setNonceGroup:(J)Lorg/apache/hadoop/hbase/protobuf/generated/ClientProtos$MultiRequest$Builder;
     188: pop
     189: aload_1
     190: invokevirtual #54                 // Method org/apache/hadoop/hbase/protobuf/generated/ClientProtos$MultiRequest.hasCondition:()Z
     193: ifeq          205
     196: aload_0
     197: aload_1
     198: invokevirtual #55                 // Method org/apache/hadoop/hbase/protobuf/generated/ClientProtos$MultiRequest.getCondition:()Lorg/apache/hadoop/hbase/protobuf/generated/ClientProtos$Condition;
     201: invokevirtual #56                 // Method mergeCondition:(Lorg/apache/hadoop/hbase/protobuf/generated/ClientProtos$Condition;)Lorg/apache/hadoop/hbase/protobuf/generated/ClientProtos$MultiRequest$Builder;
     204: pop
     205: aload_0
     206: aload_1
     207: invokevirtual #57                 // Method org/apache/hadoop/hbase/protobuf/generated/ClientProtos$MultiRequest.getUnknownFields:()Lcom/google/protobuf/UnknownFieldSet;
     210: invokevirtual #58                 // Method mergeUnknownFields:(Lcom/google/protobuf/UnknownFieldSet;)Lcom/google/protobuf/GeneratedMessage$Builder;
     213: pop
     214: aload_0
     215: areturn

  public final boolean isInitialized();
    Code:
       0: iconst_0
       1: istore_1
       2: iload_1
       3: aload_0
       4: invokevirtual #59                 // Method getRegionActionCount:()I
       7: if_icmpge     29
      10: aload_0
      11: iload_1
      12: invokevirtual #60                 // Method getRegionAction:(I)Lorg/apache/hadoop/hbase/protobuf/generated/ClientProtos$RegionAction;
      15: invokevirtual #61                 // Method org/apache/hadoop/hbase/protobuf/generated/ClientProtos$RegionAction.isInitialized:()Z
      18: ifne          23
      21: iconst_0
      22: ireturn
      23: iinc          1, 1
      26: goto          2
      29: aload_0
      30: invokevirtual #62                 // Method hasCondition:()Z
      33: ifeq          48
      36: aload_0
      37: invokevirtual #63                 // Method getCondition:()Lorg/apache/hadoop/hbase/protobuf/generated/ClientProtos$Condition;
      40: invokevirtual #64                 // Method org/apache/hadoop/hbase/protobuf/generated/ClientProtos$Condition.isInitialized:()Z
      43: ifne          48
      46: iconst_0
      47: ireturn
      48: iconst_1
      49: ireturn

  public org.apache.hadoop.hbase.protobuf.generated.ClientProtos$MultiRequest$Builder mergeFrom(com.google.protobuf.CodedInputStream, com.google.protobuf.ExtensionRegistryLite) throws java.io.IOException;
    Code:
       0: aconst_null
       1: astore_3
       2: getstatic     #65                 // Field org/apache/hadoop/hbase/protobuf/generated/ClientProtos$MultiRequest.PARSER:Lcom/google/protobuf/Parser;
       5: aload_1
       6: aload_2
       7: invokeinterface #66,  3           // InterfaceMethod com/google/protobuf/Parser.parsePartialFrom:(Lcom/google/protobuf/CodedInputStream;Lcom/google/protobuf/ExtensionRegistryLite;)Ljava/lang/Object;
      12: checkcast     #5                  // class org/apache/hadoop/hbase/protobuf/generated/ClientProtos$MultiRequest
      15: astore_3
      16: aload_3
      17: ifnull        58
      20: aload_0
      21: aload_3
      22: invokevirtual #27                 // Method mergeFrom:(Lorg/apache/hadoop/hbase/protobuf/generated/ClientProtos$MultiRequest;)Lorg/apache/hadoop/hbase/protobuf/generated/ClientProtos$MultiRequest$Builder;
      25: pop
      26: goto          58
      29: astore        4
      31: aload         4
      33: invokevirtual #68                 // Method com/google/protobuf/InvalidProtocolBufferException.getUnfinishedMessage:()Lcom/google/protobuf/MessageLite;
      36: checkcast     #5                  // class org/apache/hadoop/hbase/protobuf/generated/ClientProtos$MultiRequest
      39: astore_3
      40: aload         4
      42: athrow
      43: astore        5
      45: aload_3
      46: ifnull        55
      49: aload_0
      50: aload_3
      51: invokevirtual #27                 // Method mergeFrom:(Lorg/apache/hadoop/hbase/protobuf/generated/ClientProtos$MultiRequest;)Lorg/apache/hadoop/hbase/protobuf/generated/ClientProtos$MultiRequest$Builder;
      54: pop
      55: aload         5
      57: athrow
      58: aload_0
      59: areturn
    Exception table:
       from    to  target type
           2    16    29   Class com/google/protobuf/InvalidProtocolBufferException
           2    16    43   any
          29    45    43   any

  public java.util.List<org.apache.hadoop.hbase.protobuf.generated.ClientProtos$RegionAction> getRegionActionList();
    Code:
       0: aload_0
       1: getfield      #20                 // Field regionActionBuilder_:Lcom/google/protobuf/RepeatedFieldBuilder;
       4: ifnonnull     15
       7: aload_0
       8: getfield      #10                 // Field regionAction_:Ljava/util/List;
      11: invokestatic  #32                 // Method java/util/Collections.unmodifiableList:(Ljava/util/List;)Ljava/util/List;
      14: areturn
      15: aload_0
      16: getfield      #20                 // Field regionActionBuilder_:Lcom/google/protobuf/RepeatedFieldBuilder;
      19: invokevirtual #71                 // Method com/google/protobuf/RepeatedFieldBuilder.getMessageList:()Ljava/util/List;
      22: areturn

  public int getRegionActionCount();
    Code:
       0: aload_0
       1: getfield      #20                 // Field regionActionBuilder_:Lcom/google/protobuf/RepeatedFieldBuilder;
       4: ifnonnull     17
       7: aload_0
       8: getfield      #10                 // Field regionAction_:Ljava/util/List;
      11: invokeinterface #72,  1           // InterfaceMethod java/util/List.size:()I
      16: ireturn
      17: aload_0
      18: getfield      #20                 // Field regionActionBuilder_:Lcom/google/protobuf/RepeatedFieldBuilder;
      21: invokevirtual #73                 // Method com/google/protobuf/RepeatedFieldBuilder.getCount:()I
      24: ireturn

  public org.apache.hadoop.hbase.protobuf.generated.ClientProtos$RegionAction getRegionAction(int);
    Code:
       0: aload_0
       1: getfield      #20                 // Field regionActionBuilder_:Lcom/google/protobuf/RepeatedFieldBuilder;
       4: ifnonnull     21
       7: aload_0
       8: getfield      #10                 // Field regionAction_:Ljava/util/List;
      11: iload_1
      12: invokeinterface #74,  2           // InterfaceMethod java/util/List.get:(I)Ljava/lang/Object;
      17: checkcast     #75                 // class org/apache/hadoop/hbase/protobuf/generated/ClientProtos$RegionAction
      20: areturn
      21: aload_0
      22: getfield      #20                 // Field regionActionBuilder_:Lcom/google/protobuf/RepeatedFieldBuilder;
      25: iload_1
      26: invokevirtual #76                 // Method com/google/protobuf/RepeatedFieldBuilder.getMessage:(I)Lcom/google/protobuf/GeneratedMessage;
      29: checkcast     #75                 // class org/apache/hadoop/hbase/protobuf/generated/ClientProtos$RegionAction
      32: areturn

  public org.apache.hadoop.hbase.protobuf.generated.ClientProtos$MultiRequest$Builder setRegionAction(int, org.apache.hadoop.hbase.protobuf.generated.ClientProtos$RegionAction);
    Code:
       0: aload_0
       1: getfield      #20                 // Field regionActionBuilder_:Lcom/google/protobuf/RepeatedFieldBuilder;
       4: ifnonnull     42
       7: aload_2
       8: ifnonnull     19
      11: new           #77                 // class java/lang/NullPointerException
      14: dup
      15: invokespecial #78                 // Method java/lang/NullPointerException."<init>":()V
      18: athrow
      19: aload_0
      20: invokespecial #44                 // Method ensureRegionActionIsMutable:()V
      23: aload_0
      24: getfield      #10                 // Field regionAction_:Ljava/util/List;
      27: iload_1
      28: aload_2
      29: invokeinterface #79,  3           // InterfaceMethod java/util/List.set:(ILjava/lang/Object;)Ljava/lang/Object;
      34: pop
      35: aload_0
      36: invokevirtual #46                 // Method onChanged:()V
      39: goto          52
      42: aload_0
      43: getfield      #20                 // Field regionActionBuilder_:Lcom/google/protobuf/RepeatedFieldBuilder;
      46: iload_1
      47: aload_2
      48: invokevirtual #80                 // Method com/google/protobuf/RepeatedFieldBuilder.setMessage:(ILcom/google/protobuf/GeneratedMessage;)Lcom/google/protobuf/RepeatedFieldBuilder;
      51: pop
      52: aload_0
      53: areturn

  public org.apache.hadoop.hbase.protobuf.generated.ClientProtos$MultiRequest$Builder setRegionAction(int, org.apache.hadoop.hbase.protobuf.generated.ClientProtos$RegionAction$Builder);
    Code:
       0: aload_0
       1: getfield      #20                 // Field regionActionBuilder_:Lcom/google/protobuf/RepeatedFieldBuilder;
       4: ifnonnull     33
       7: aload_0
       8: invokespecial #44                 // Method ensureRegionActionIsMutable:()V
      11: aload_0
      12: getfield      #10                 // Field regionAction_:Ljava/util/List;
      15: iload_1
      16: aload_2
      17: invokevirtual #81                 // Method org/apache/hadoop/hbase/protobuf/generated/ClientProtos$RegionAction$Builder.build:()Lorg/apache/hadoop/hbase/protobuf/generated/ClientProtos$RegionAction;
      20: invokeinterface #79,  3           // InterfaceMethod java/util/List.set:(ILjava/lang/Object;)Ljava/lang/Object;
      25: pop
      26: aload_0
      27: invokevirtual #46                 // Method onChanged:()V
      30: goto          46
      33: aload_0
      34: getfield      #20                 // Field regionActionBuilder_:Lcom/google/protobuf/RepeatedFieldBuilder;
      37: iload_1
      38: aload_2
      39: invokevirtual #81                 // Method org/apache/hadoop/hbase/protobuf/generated/ClientProtos$RegionAction$Builder.build:()Lorg/apache/hadoop/hbase/protobuf/generated/ClientProtos$RegionAction;
      42: invokevirtual #80                 // Method com/google/protobuf/RepeatedFieldBuilder.setMessage:(ILcom/google/protobuf/GeneratedMessage;)Lcom/google/protobuf/RepeatedFieldBuilder;
      45: pop
      46: aload_0
      47: areturn

  public org.apache.hadoop.hbase.protobuf.generated.ClientProtos$MultiRequest$Builder addRegionAction(org.apache.hadoop.hbase.protobuf.generated.ClientProtos$RegionAction);
    Code:
       0: aload_0
       1: getfield      #20                 // Field regionActionBuilder_:Lcom/google/protobuf/RepeatedFieldBuilder;
       4: ifnonnull     41
       7: aload_1
       8: ifnonnull     19
      11: new           #77                 // class java/lang/NullPointerException
      14: dup
      15: invokespecial #78                 // Method java/lang/NullPointerException."<init>":()V
      18: athrow
      19: aload_0
      20: invokespecial #44                 // Method ensureRegionActionIsMutable:()V
      23: aload_0
      24: getfield      #10                 // Field regionAction_:Ljava/util/List;
      27: aload_1
      28: invokeinterface #82,  2           // InterfaceMethod java/util/List.add:(Ljava/lang/Object;)Z
      33: pop
      34: aload_0
      35: invokevirtual #46                 // Method onChanged:()V
      38: goto          50
      41: aload_0
      42: getfield      #20                 // Field regionActionBuilder_:Lcom/google/protobuf/RepeatedFieldBuilder;
      45: aload_1
      46: invokevirtual #83                 // Method com/google/protobuf/RepeatedFieldBuilder.addMessage:(Lcom/google/protobuf/GeneratedMessage;)Lcom/google/protobuf/RepeatedFieldBuilder;
      49: pop
      50: aload_0
      51: areturn

  public org.apache.hadoop.hbase.protobuf.generated.ClientProtos$MultiRequest$Builder addRegionAction(int, org.apache.hadoop.hbase.protobuf.generated.ClientProtos$RegionAction);
    Code:
       0: aload_0
       1: getfield      #20                 // Field regionActionBuilder_:Lcom/google/protobuf/RepeatedFieldBuilder;
       4: ifnonnull     41
       7: aload_2
       8: ifnonnull     19
      11: new           #77                 // class java/lang/NullPointerException
      14: dup
      15: invokespecial #78                 // Method java/lang/NullPointerException."<init>":()V
      18: athrow
      19: aload_0
      20: invokespecial #44                 // Method ensureRegionActionIsMutable:()V
      23: aload_0
      24: getfield      #10                 // Field regionAction_:Ljava/util/List;
      27: iload_1
      28: aload_2
      29: invokeinterface #84,  3           // InterfaceMethod java/util/List.add:(ILjava/lang/Object;)V
      34: aload_0
      35: invokevirtual #46                 // Method onChanged:()V
      38: goto          51
      41: aload_0
      42: getfield      #20                 // Field regionActionBuilder_:Lcom/google/protobuf/RepeatedFieldBuilder;
      45: iload_1
      46: aload_2
      47: invokevirtual #85                 // Method com/google/protobuf/RepeatedFieldBuilder.addMessage:(ILcom/google/protobuf/GeneratedMessage;)Lcom/google/protobuf/RepeatedFieldBuilder;
      50: pop
      51: aload_0
      52: areturn

  public org.apache.hadoop.hbase.protobuf.generated.ClientProtos$MultiRequest$Builder addRegionAction(org.apache.hadoop.hbase.protobuf.generated.ClientProtos$RegionAction$Builder);
    Code:
       0: aload_0
       1: getfield      #20                 // Field regionActionBuilder_:Lcom/google/protobuf/RepeatedFieldBuilder;
       4: ifnonnull     32
       7: aload_0
       8: invokespecial #44                 // Method ensureRegionActionIsMutable:()V
      11: aload_0
      12: getfield      #10                 // Field regionAction_:Ljava/util/List;
      15: aload_1
      16: invokevirtual #81                 // Method org/apache/hadoop/hbase/protobuf/generated/ClientProtos$RegionAction$Builder.build:()Lorg/apache/hadoop/hbase/protobuf/generated/ClientProtos$RegionAction;
      19: invokeinterface #82,  2           // InterfaceMethod java/util/List.add:(Ljava/lang/Object;)Z
      24: pop
      25: aload_0
      26: invokevirtual #46                 // Method onChanged:()V
      29: goto          44
      32: aload_0
      33: getfield      #20                 // Field regionActionBuilder_:Lcom/google/protobuf/RepeatedFieldBuilder;
      36: aload_1
      37: invokevirtual #81                 // Method org/apache/hadoop/hbase/protobuf/generated/ClientProtos$RegionAction$Builder.build:()Lorg/apache/hadoop/hbase/protobuf/generated/ClientProtos$RegionAction;
      40: invokevirtual #83                 // Method com/google/protobuf/RepeatedFieldBuilder.addMessage:(Lcom/google/protobuf/GeneratedMessage;)Lcom/google/protobuf/RepeatedFieldBuilder;
      43: pop
      44: aload_0
      45: areturn

  public org.apache.hadoop.hbase.protobuf.generated.ClientProtos$MultiRequest$Builder addRegionAction(int, org.apache.hadoop.hbase.protobuf.generated.ClientProtos$RegionAction$Builder);
    Code:
       0: aload_0
       1: getfield      #20                 // Field regionActionBuilder_:Lcom/google/protobuf/RepeatedFieldBuilder;
       4: ifnonnull     32
       7: aload_0
       8: invokespecial #44                 // Method ensureRegionActionIsMutable:()V
      11: aload_0
      12: getfield      #10                 // Field regionAction_:Ljava/util/List;
      15: iload_1
      16: aload_2
      17: invokevirtual #81                 // Method org/apache/hadoop/hbase/protobuf/generated/ClientProtos$RegionAction$Builder.build:()Lorg/apache/hadoop/hbase/protobuf/generated/ClientProtos$RegionAction;
      20: invokeinterface #84,  3           // InterfaceMethod java/util/List.add:(ILjava/lang/Object;)V
      25: aload_0
      26: invokevirtual #46                 // Method onChanged:()V
      29: goto          45
      32: aload_0
      33: getfield      #20                 // Field regionActionBuilder_:Lcom/google/protobuf/RepeatedFieldBuilder;
      36: iload_1
      37: aload_2
      38: invokevirtual #81                 // Method org/apache/hadoop/hbase/protobuf/generated/ClientProtos$RegionAction$Builder.build:()Lorg/apache/hadoop/hbase/protobuf/generated/ClientProtos$RegionAction;
      41: invokevirtual #85                 // Method com/google/protobuf/RepeatedFieldBuilder.addMessage:(ILcom/google/protobuf/GeneratedMessage;)Lcom/google/protobuf/RepeatedFieldBuilder;
      44: pop
      45: aload_0
      46: areturn

  public org.apache.hadoop.hbase.protobuf.generated.ClientProtos$MultiRequest$Builder addAllRegionAction(java.lang.Iterable<? extends org.apache.hadoop.hbase.protobuf.generated.ClientProtos$RegionAction>);
    Code:
       0: aload_0
       1: getfield      #20                 // Field regionActionBuilder_:Lcom/google/protobuf/RepeatedFieldBuilder;
       4: ifnonnull     26
       7: aload_0
       8: invokespecial #44                 // Method ensureRegionActionIsMutable:()V
      11: aload_1
      12: aload_0
      13: getfield      #10                 // Field regionAction_:Ljava/util/List;
      16: invokestatic  #86                 // Method com/google/protobuf/GeneratedMessage$Builder.addAll:(Ljava/lang/Iterable;Ljava/util/Collection;)V
      19: aload_0
      20: invokevirtual #46                 // Method onChanged:()V
      23: goto          35
      26: aload_0
      27: getfield      #20                 // Field regionActionBuilder_:Lcom/google/protobuf/RepeatedFieldBuilder;
      30: aload_1
      31: invokevirtual #50                 // Method com/google/protobuf/RepeatedFieldBuilder.addAllMessages:(Ljava/lang/Iterable;)Lcom/google/protobuf/RepeatedFieldBuilder;
      34: pop
      35: aload_0
      36: areturn

  public org.apache.hadoop.hbase.protobuf.generated.ClientProtos$MultiRequest$Builder clearRegionAction();
    Code:
       0: aload_0
       1: getfield      #20                 // Field regionActionBuilder_:Lcom/google/protobuf/RepeatedFieldBuilder;
       4: ifnonnull     32
       7: aload_0
       8: invokestatic  #9                  // Method java/util/Collections.emptyList:()Ljava/util/List;
      11: putfield      #10                 // Field regionAction_:Ljava/util/List;
      14: aload_0
      15: aload_0
      16: getfield      #21                 // Field bitField0_:I
      19: bipush        -2
      21: iand
      22: putfield      #21                 // Field bitField0_:I
      25: aload_0
      26: invokevirtual #46                 // Method onChanged:()V
      29: goto          39
      32: aload_0
      33: getfield      #20                 // Field regionActionBuilder_:Lcom/google/protobuf/RepeatedFieldBuilder;
      36: invokevirtual #22                 // Method com/google/protobuf/RepeatedFieldBuilder.clear:()V
      39: aload_0
      40: areturn

  public org.apache.hadoop.hbase.protobuf.generated.ClientProtos$MultiRequest$Builder removeRegionAction(int);
    Code:
       0: aload_0
       1: getfield      #20                 // Field regionActionBuilder_:Lcom/google/protobuf/RepeatedFieldBuilder;
       4: ifnonnull     29
       7: aload_0
       8: invokespecial #44                 // Method ensureRegionActionIsMutable:()V
      11: aload_0
      12: getfield      #10                 // Field regionAction_:Ljava/util/List;
      15: iload_1
      16: invokeinterface #87,  2           // InterfaceMethod java/util/List.remove:(I)Ljava/lang/Object;
      21: pop
      22: aload_0
      23: invokevirtual #46                 // Method onChanged:()V
      26: goto          37
      29: aload_0
      30: getfield      #20                 // Field regionActionBuilder_:Lcom/google/protobuf/RepeatedFieldBuilder;
      33: iload_1
      34: invokevirtual #88                 // Method com/google/protobuf/RepeatedFieldBuilder.remove:(I)V
      37: aload_0
      38: areturn

  public org.apache.hadoop.hbase.protobuf.generated.ClientProtos$RegionAction$Builder getRegionActionBuilder(int);
    Code:
       0: aload_0
       1: invokespecial #16                 // Method getRegionActionFieldBuilder:()Lcom/google/protobuf/RepeatedFieldBuilder;
       4: iload_1
       5: invokevirtual #89                 // Method com/google/protobuf/RepeatedFieldBuilder.getBuilder:(I)Lcom/google/protobuf/GeneratedMessage$Builder;
       8: checkcast     #90                 // class org/apache/hadoop/hbase/protobuf/generated/ClientProtos$RegionAction$Builder
      11: areturn

  public org.apache.hadoop.hbase.protobuf.generated.ClientProtos$RegionActionOrBuilder getRegionActionOrBuilder(int);
    Code:
       0: aload_0
       1: getfield      #20                 // Field regionActionBuilder_:Lcom/google/protobuf/RepeatedFieldBuilder;
       4: ifnonnull     21
       7: aload_0
       8: getfield      #10                 // Field regionAction_:Ljava/util/List;
      11: iload_1
      12: invokeinterface #74,  2           // InterfaceMethod java/util/List.get:(I)Ljava/lang/Object;
      17: checkcast     #91                 // class org/apache/hadoop/hbase/protobuf/generated/ClientProtos$RegionActionOrBuilder
      20: areturn
      21: aload_0
      22: getfield      #20                 // Field regionActionBuilder_:Lcom/google/protobuf/RepeatedFieldBuilder;
      25: iload_1
      26: invokevirtual #92                 // Method com/google/protobuf/RepeatedFieldBuilder.getMessageOrBuilder:(I)Lcom/google/protobuf/MessageOrBuilder;
      29: checkcast     #91                 // class org/apache/hadoop/hbase/protobuf/generated/ClientProtos$RegionActionOrBuilder
      32: areturn

  public java.util.List<? extends org.apache.hadoop.hbase.protobuf.generated.ClientProtos$RegionActionOrBuilder> getRegionActionOrBuilderList();
    Code:
       0: aload_0
       1: getfield      #20                 // Field regionActionBuilder_:Lcom/google/protobuf/RepeatedFieldBuilder;
       4: ifnull        15
       7: aload_0
       8: getfield      #20                 // Field regionActionBuilder_:Lcom/google/protobuf/RepeatedFieldBuilder;
      11: invokevirtual #93                 // Method com/google/protobuf/RepeatedFieldBuilder.getMessageOrBuilderList:()Ljava/util/List;
      14: areturn
      15: aload_0
      16: getfield      #10                 // Field regionAction_:Ljava/util/List;
      19: invokestatic  #32                 // Method java/util/Collections.unmodifiableList:(Ljava/util/List;)Ljava/util/List;
      22: areturn

  public org.apache.hadoop.hbase.protobuf.generated.ClientProtos$RegionAction$Builder addRegionActionBuilder();
    Code:
       0: aload_0
       1: invokespecial #16                 // Method getRegionActionFieldBuilder:()Lcom/google/protobuf/RepeatedFieldBuilder;
       4: invokestatic  #94                 // Method org/apache/hadoop/hbase/protobuf/generated/ClientProtos$RegionAction.getDefaultInstance:()Lorg/apache/hadoop/hbase/protobuf/generated/ClientProtos$RegionAction;
       7: invokevirtual #95                 // Method com/google/protobuf/RepeatedFieldBuilder.addBuilder:(Lcom/google/protobuf/GeneratedMessage;)Lcom/google/protobuf/GeneratedMessage$Builder;
      10: checkcast     #90                 // class org/apache/hadoop/hbase/protobuf/generated/ClientProtos$RegionAction$Builder
      13: areturn

  public org.apache.hadoop.hbase.protobuf.generated.ClientProtos$RegionAction$Builder addRegionActionBuilder(int);
    Code:
       0: aload_0
       1: invokespecial #16                 // Method getRegionActionFieldBuilder:()Lcom/google/protobuf/RepeatedFieldBuilder;
       4: iload_1
       5: invokestatic  #94                 // Method org/apache/hadoop/hbase/protobuf/generated/ClientProtos$RegionAction.getDefaultInstance:()Lorg/apache/hadoop/hbase/protobuf/generated/ClientProtos$RegionAction;
       8: invokevirtual #96                 // Method com/google/protobuf/RepeatedFieldBuilder.addBuilder:(ILcom/google/protobuf/GeneratedMessage;)Lcom/google/protobuf/GeneratedMessage$Builder;
      11: checkcast     #90                 // class org/apache/hadoop/hbase/protobuf/generated/ClientProtos$RegionAction$Builder
      14: areturn

  public java.util.List<org.apache.hadoop.hbase.protobuf.generated.ClientProtos$RegionAction$Builder> getRegionActionBuilderList();
    Code:
       0: aload_0
       1: invokespecial #16                 // Method getRegionActionFieldBuilder:()Lcom/google/protobuf/RepeatedFieldBuilder;
       4: invokevirtual #97                 // Method com/google/protobuf/RepeatedFieldBuilder.getBuilderList:()Ljava/util/List;
       7: areturn

  public boolean hasNonceGroup();
    Code:
       0: aload_0
       1: getfield      #21                 // Field bitField0_:I
       4: iconst_2
       5: iand
       6: iconst_2
       7: if_icmpne     14
      10: iconst_1
      11: goto          15
      14: iconst_0
      15: ireturn

  public long getNonceGroup();
    Code:
       0: aload_0
       1: getfield      #23                 // Field nonceGroup_:J
       4: lreturn

  public org.apache.hadoop.hbase.protobuf.generated.ClientProtos$MultiRequest$Builder setNonceGroup(long);
    Code:
       0: aload_0
       1: dup
       2: getfield      #21                 // Field bitField0_:I
       5: iconst_2
       6: ior
       7: putfield      #21                 // Field bitField0_:I
      10: aload_0
      11: lload_1
      12: putfield      #23                 // Field nonceGroup_:J
      15: aload_0
      16: invokevirtual #46                 // Method onChanged:()V
      19: aload_0
      20: areturn

  public org.apache.hadoop.hbase.protobuf.generated.ClientProtos$MultiRequest$Builder clearNonceGroup();
    Code:
       0: aload_0
       1: aload_0
       2: getfield      #21                 // Field bitField0_:I
       5: bipush        -3
       7: iand
       8: putfield      #21                 // Field bitField0_:I
      11: aload_0
      12: lconst_0
      13: putfield      #23                 // Field nonceGroup_:J
      16: aload_0
      17: invokevirtual #46                 // Method onChanged:()V
      20: aload_0
      21: areturn

  public boolean hasCondition();
    Code:
       0: aload_0
       1: getfield      #21                 // Field bitField0_:I
       4: iconst_4
       5: iand
       6: iconst_4
       7: if_icmpne     14
      10: iconst_1
      11: goto          15
      14: iconst_0
      15: ireturn

  public org.apache.hadoop.hbase.protobuf.generated.ClientProtos$Condition getCondition();
    Code:
       0: aload_0
       1: getfield      #24                 // Field conditionBuilder_:Lcom/google/protobuf/SingleFieldBuilder;
       4: ifnonnull     12
       7: aload_0
       8: getfield      #12                 // Field condition_:Lorg/apache/hadoop/hbase/protobuf/generated/ClientProtos$Condition;
      11: areturn
      12: aload_0
      13: getfield      #24                 // Field conditionBuilder_:Lcom/google/protobuf/SingleFieldBuilder;
      16: invokevirtual #102                // Method com/google/protobuf/SingleFieldBuilder.getMessage:()Lcom/google/protobuf/GeneratedMessage;
      19: checkcast     #38                 // class org/apache/hadoop/hbase/protobuf/generated/ClientProtos$Condition
      22: areturn

  public org.apache.hadoop.hbase.protobuf.generated.ClientProtos$MultiRequest$Builder setCondition(org.apache.hadoop.hbase.protobuf.generated.ClientProtos$Condition);
    Code:
       0: aload_0
       1: getfield      #24                 // Field conditionBuilder_:Lcom/google/protobuf/SingleFieldBuilder;
       4: ifnonnull     31
       7: aload_1
       8: ifnonnull     19
      11: new           #77                 // class java/lang/NullPointerException
      14: dup
      15: invokespecial #78                 // Method java/lang/NullPointerException."<init>":()V
      18: athrow
      19: aload_0
      20: aload_1
      21: putfield      #12                 // Field condition_:Lorg/apache/hadoop/hbase/protobuf/generated/ClientProtos$Condition;
      24: aload_0
      25: invokevirtual #46                 // Method onChanged:()V
      28: goto          40
      31: aload_0
      32: getfield      #24                 // Field conditionBuilder_:Lcom/google/protobuf/SingleFieldBuilder;
      35: aload_1
      36: invokevirtual #103                // Method com/google/protobuf/SingleFieldBuilder.setMessage:(Lcom/google/protobuf/GeneratedMessage;)Lcom/google/protobuf/SingleFieldBuilder;
      39: pop
      40: aload_0
      41: dup
      42: getfield      #21                 // Field bitField0_:I
      45: iconst_4
      46: ior
      47: putfield      #21                 // Field bitField0_:I
      50: aload_0
      51: areturn

  public org.apache.hadoop.hbase.protobuf.generated.ClientProtos$MultiRequest$Builder setCondition(org.apache.hadoop.hbase.protobuf.generated.ClientProtos$Condition$Builder);
    Code:
       0: aload_0
       1: getfield      #24                 // Field conditionBuilder_:Lcom/google/protobuf/SingleFieldBuilder;
       4: ifnonnull     22
       7: aload_0
       8: aload_1
       9: invokevirtual #104                // Method org/apache/hadoop/hbase/protobuf/generated/ClientProtos$Condition$Builder.build:()Lorg/apache/hadoop/hbase/protobuf/generated/ClientProtos$Condition;
      12: putfield      #12                 // Field condition_:Lorg/apache/hadoop/hbase/protobuf/generated/ClientProtos$Condition;
      15: aload_0
      16: invokevirtual #46                 // Method onChanged:()V
      19: goto          34
      22: aload_0
      23: getfield      #24                 // Field conditionBuilder_:Lcom/google/protobuf/SingleFieldBuilder;
      26: aload_1
      27: invokevirtual #104                // Method org/apache/hadoop/hbase/protobuf/generated/ClientProtos$Condition$Builder.build:()Lorg/apache/hadoop/hbase/protobuf/generated/ClientProtos$Condition;
      30: invokevirtual #103                // Method com/google/protobuf/SingleFieldBuilder.setMessage:(Lcom/google/protobuf/GeneratedMessage;)Lcom/google/protobuf/SingleFieldBuilder;
      33: pop
      34: aload_0
      35: dup
      36: getfield      #21                 // Field bitField0_:I
      39: iconst_4
      40: ior
      41: putfield      #21                 // Field bitField0_:I
      44: aload_0
      45: areturn

  public org.apache.hadoop.hbase.protobuf.generated.ClientProtos$MultiRequest$Builder mergeCondition(org.apache.hadoop.hbase.protobuf.generated.ClientProtos$Condition);
    Code:
       0: aload_0
       1: getfield      #24                 // Field conditionBuilder_:Lcom/google/protobuf/SingleFieldBuilder;
       4: ifnonnull     60
       7: aload_0
       8: getfield      #21                 // Field bitField0_:I
      11: iconst_4
      12: iand
      13: iconst_4
      14: if_icmpne     48
      17: aload_0
      18: getfield      #12                 // Field condition_:Lorg/apache/hadoop/hbase/protobuf/generated/ClientProtos$Condition;
      21: invokestatic  #11                 // Method org/apache/hadoop/hbase/protobuf/generated/ClientProtos$Condition.getDefaultInstance:()Lorg/apache/hadoop/hbase/protobuf/generated/ClientProtos$Condition;
      24: if_acmpeq     48
      27: aload_0
      28: aload_0
      29: getfield      #12                 // Field condition_:Lorg/apache/hadoop/hbase/protobuf/generated/ClientProtos$Condition;
      32: invokestatic  #105                // Method org/apache/hadoop/hbase/protobuf/generated/ClientProtos$Condition.newBuilder:(Lorg/apache/hadoop/hbase/protobuf/generated/ClientProtos$Condition;)Lorg/apache/hadoop/hbase/protobuf/generated/ClientProtos$Condition$Builder;
      35: aload_1
      36: invokevirtual #106                // Method org/apache/hadoop/hbase/protobuf/generated/ClientProtos$Condition$Builder.mergeFrom:(Lorg/apache/hadoop/hbase/protobuf/generated/ClientProtos$Condition;)Lorg/apache/hadoop/hbase/protobuf/generated/ClientProtos$Condition$Builder;
      39: invokevirtual #107                // Method org/apache/hadoop/hbase/protobuf/generated/ClientProtos$Condition$Builder.buildPartial:()Lorg/apache/hadoop/hbase/protobuf/generated/ClientProtos$Condition;
      42: putfield      #12                 // Field condition_:Lorg/apache/hadoop/hbase/protobuf/generated/ClientProtos$Condition;
      45: goto          53
      48: aload_0
      49: aload_1
      50: putfield      #12                 // Field condition_:Lorg/apache/hadoop/hbase/protobuf/generated/ClientProtos$Condition;
      53: aload_0
      54: invokevirtual #46                 // Method onChanged:()V
      57: goto          69
      60: aload_0
      61: getfield      #24                 // Field conditionBuilder_:Lcom/google/protobuf/SingleFieldBuilder;
      64: aload_1
      65: invokevirtual #108                // Method com/google/protobuf/SingleFieldBuilder.mergeFrom:(Lcom/google/protobuf/GeneratedMessage;)Lcom/google/protobuf/SingleFieldBuilder;
      68: pop
      69: aload_0
      70: dup
      71: getfield      #21                 // Field bitField0_:I
      74: iconst_4
      75: ior
      76: putfield      #21                 // Field bitField0_:I
      79: aload_0
      80: areturn

  public org.apache.hadoop.hbase.protobuf.generated.ClientProtos$MultiRequest$Builder clearCondition();
    Code:
       0: aload_0
       1: getfield      #24                 // Field conditionBuilder_:Lcom/google/protobuf/SingleFieldBuilder;
       4: ifnonnull     21
       7: aload_0
       8: invokestatic  #11                 // Method org/apache/hadoop/hbase/protobuf/generated/ClientProtos$Condition.getDefaultInstance:()Lorg/apache/hadoop/hbase/protobuf/generated/ClientProtos$Condition;
      11: putfield      #12                 // Field condition_:Lorg/apache/hadoop/hbase/protobuf/generated/ClientProtos$Condition;
      14: aload_0
      15: invokevirtual #46                 // Method onChanged:()V
      18: goto          29
      21: aload_0
      22: getfield      #24                 // Field conditionBuilder_:Lcom/google/protobuf/SingleFieldBuilder;
      25: invokevirtual #25                 // Method com/google/protobuf/SingleFieldBuilder.clear:()Lcom/google/protobuf/SingleFieldBuilder;
      28: pop
      29: aload_0
      30: aload_0
      31: getfield      #21                 // Field bitField0_:I
      34: bipush        -5
      36: iand
      37: putfield      #21                 // Field bitField0_:I
      40: aload_0
      41: areturn

  public org.apache.hadoop.hbase.protobuf.generated.ClientProtos$Condition$Builder getConditionBuilder();
    Code:
       0: aload_0
       1: dup
       2: getfield      #21                 // Field bitField0_:I
       5: iconst_4
       6: ior
       7: putfield      #21                 // Field bitField0_:I
      10: aload_0
      11: invokevirtual #46                 // Method onChanged:()V
      14: aload_0
      15: invokespecial #17                 // Method getConditionFieldBuilder:()Lcom/google/protobuf/SingleFieldBuilder;
      18: invokevirtual #109                // Method com/google/protobuf/SingleFieldBuilder.getBuilder:()Lcom/google/protobuf/GeneratedMessage$Builder;
      21: checkcast     #110                // class org/apache/hadoop/hbase/protobuf/generated/ClientProtos$Condition$Builder
      24: areturn

  public org.apache.hadoop.hbase.protobuf.generated.ClientProtos$ConditionOrBuilder getConditionOrBuilder();
    Code:
       0: aload_0
       1: getfield      #24                 // Field conditionBuilder_:Lcom/google/protobuf/SingleFieldBuilder;
       4: ifnull        18
       7: aload_0
       8: getfield      #24                 // Field conditionBuilder_:Lcom/google/protobuf/SingleFieldBuilder;
      11: invokevirtual #111                // Method com/google/protobuf/SingleFieldBuilder.getMessageOrBuilder:()Lcom/google/protobuf/MessageOrBuilder;
      14: checkcast     #112                // class org/apache/hadoop/hbase/protobuf/generated/ClientProtos$ConditionOrBuilder
      17: areturn
      18: aload_0
      19: getfield      #12                 // Field condition_:Lorg/apache/hadoop/hbase/protobuf/generated/ClientProtos$Condition;
      22: areturn

  public com.google.protobuf.GeneratedMessage$Builder clear();
    Code:
       0: aload_0
       1: invokevirtual #115                // Method clear:()Lorg/apache/hadoop/hbase/protobuf/generated/ClientProtos$MultiRequest$Builder;
       4: areturn

  public com.google.protobuf.GeneratedMessage$Builder clone();
    Code:
       0: aload_0
       1: invokevirtual #116                // Method clone:()Lorg/apache/hadoop/hbase/protobuf/generated/ClientProtos$MultiRequest$Builder;
       4: areturn

  public com.google.protobuf.AbstractMessage$Builder mergeFrom(com.google.protobuf.CodedInputStream, com.google.protobuf.ExtensionRegistryLite) throws java.io.IOException;
    Code:
       0: aload_0
       1: aload_1
       2: aload_2
       3: invokevirtual #117                // Method mergeFrom:(Lcom/google/protobuf/CodedInputStream;Lcom/google/protobuf/ExtensionRegistryLite;)Lorg/apache/hadoop/hbase/protobuf/generated/ClientProtos$MultiRequest$Builder;
       6: areturn

  public com.google.protobuf.AbstractMessage$Builder mergeFrom(com.google.protobuf.Message);
    Code:
       0: aload_0
       1: aload_1
       2: invokevirtual #118                // Method mergeFrom:(Lcom/google/protobuf/Message;)Lorg/apache/hadoop/hbase/protobuf/generated/ClientProtos$MultiRequest$Builder;
       5: areturn

  public com.google.protobuf.AbstractMessage$Builder clear();
    Code:
       0: aload_0
       1: invokevirtual #115                // Method clear:()Lorg/apache/hadoop/hbase/protobuf/generated/ClientProtos$MultiRequest$Builder;
       4: areturn

  public com.google.protobuf.AbstractMessage$Builder clone();
    Code:
       0: aload_0
       1: invokevirtual #116                // Method clone:()Lorg/apache/hadoop/hbase/protobuf/generated/ClientProtos$MultiRequest$Builder;
       4: areturn

  public com.google.protobuf.Message$Builder mergeFrom(com.google.protobuf.CodedInputStream, com.google.protobuf.ExtensionRegistryLite) throws java.io.IOException;
    Code:
       0: aload_0
       1: aload_1
       2: aload_2
       3: invokevirtual #117                // Method mergeFrom:(Lcom/google/protobuf/CodedInputStream;Lcom/google/protobuf/ExtensionRegistryLite;)Lorg/apache/hadoop/hbase/protobuf/generated/ClientProtos$MultiRequest$Builder;
       6: areturn

  public com.google.protobuf.Message$Builder clone();
    Code:
       0: aload_0
       1: invokevirtual #116                // Method clone:()Lorg/apache/hadoop/hbase/protobuf/generated/ClientProtos$MultiRequest$Builder;
       4: areturn

  public com.google.protobuf.Message buildPartial();
    Code:
       0: aload_0
       1: invokevirtual #26                 // Method buildPartial:()Lorg/apache/hadoop/hbase/protobuf/generated/ClientProtos$MultiRequest;
       4: areturn

  public com.google.protobuf.Message build();
    Code:
       0: aload_0
       1: invokevirtual #119                // Method build:()Lorg/apache/hadoop/hbase/protobuf/generated/ClientProtos$MultiRequest;
       4: areturn

  public com.google.protobuf.Message$Builder mergeFrom(com.google.protobuf.Message);
    Code:
       0: aload_0
       1: aload_1
       2: invokevirtual #118                // Method mergeFrom:(Lcom/google/protobuf/Message;)Lorg/apache/hadoop/hbase/protobuf/generated/ClientProtos$MultiRequest$Builder;
       5: areturn

  public com.google.protobuf.Message$Builder clear();
    Code:
       0: aload_0
       1: invokevirtual #115                // Method clear:()Lorg/apache/hadoop/hbase/protobuf/generated/ClientProtos$MultiRequest$Builder;
       4: areturn

  public com.google.protobuf.MessageLite$Builder mergeFrom(com.google.protobuf.CodedInputStream, com.google.protobuf.ExtensionRegistryLite) throws java.io.IOException;
    Code:
       0: aload_0
       1: aload_1
       2: aload_2
       3: invokevirtual #117                // Method mergeFrom:(Lcom/google/protobuf/CodedInputStream;Lcom/google/protobuf/ExtensionRegistryLite;)Lorg/apache/hadoop/hbase/protobuf/generated/ClientProtos$MultiRequest$Builder;
       6: areturn

  public com.google.protobuf.MessageLite$Builder clone();
    Code:
       0: aload_0
       1: invokevirtual #116                // Method clone:()Lorg/apache/hadoop/hbase/protobuf/generated/ClientProtos$MultiRequest$Builder;
       4: areturn

  public com.google.protobuf.MessageLite buildPartial();
    Code:
       0: aload_0
       1: invokevirtual #26                 // Method buildPartial:()Lorg/apache/hadoop/hbase/protobuf/generated/ClientProtos$MultiRequest;
       4: areturn

  public com.google.protobuf.MessageLite build();
    Code:
       0: aload_0
       1: invokevirtual #119                // Method build:()Lorg/apache/hadoop/hbase/protobuf/generated/ClientProtos$MultiRequest;
       4: areturn

  public com.google.protobuf.MessageLite$Builder clear();
    Code:
       0: aload_0
       1: invokevirtual #115                // Method clear:()Lorg/apache/hadoop/hbase/protobuf/generated/ClientProtos$MultiRequest$Builder;
       4: areturn

  public com.google.protobuf.MessageLite getDefaultInstanceForType();
    Code:
       0: aload_0
       1: invokevirtual #120                // Method getDefaultInstanceForType:()Lorg/apache/hadoop/hbase/protobuf/generated/ClientProtos$MultiRequest;
       4: areturn

  public com.google.protobuf.Message getDefaultInstanceForType();
    Code:
       0: aload_0
       1: invokevirtual #120                // Method getDefaultInstanceForType:()Lorg/apache/hadoop/hbase/protobuf/generated/ClientProtos$MultiRequest;
       4: areturn

  public com.google.protobuf.AbstractMessageLite$Builder mergeFrom(com.google.protobuf.CodedInputStream, com.google.protobuf.ExtensionRegistryLite) throws java.io.IOException;
    Code:
       0: aload_0
       1: aload_1
       2: aload_2
       3: invokevirtual #117                // Method mergeFrom:(Lcom/google/protobuf/CodedInputStream;Lcom/google/protobuf/ExtensionRegistryLite;)Lorg/apache/hadoop/hbase/protobuf/generated/ClientProtos$MultiRequest$Builder;
       6: areturn

  public com.google.protobuf.AbstractMessageLite$Builder clone();
    Code:
       0: aload_0
       1: invokevirtual #116                // Method clone:()Lorg/apache/hadoop/hbase/protobuf/generated/ClientProtos$MultiRequest$Builder;
       4: areturn

  public java.lang.Object clone() throws java.lang.CloneNotSupportedException;
    Code:
       0: aload_0
       1: invokevirtual #116                // Method clone:()Lorg/apache/hadoop/hbase/protobuf/generated/ClientProtos$MultiRequest$Builder;
       4: areturn

  static org.apache.hadoop.hbase.protobuf.generated.ClientProtos$MultiRequest$Builder access$44400();
    Code:
       0: invokestatic  #2                  // Method create:()Lorg/apache/hadoop/hbase/protobuf/generated/ClientProtos$MultiRequest$Builder;
       3: areturn

  org.apache.hadoop.hbase.protobuf.generated.ClientProtos$MultiRequest$Builder(com.google.protobuf.GeneratedMessage$BuilderParent, org.apache.hadoop.hbase.protobuf.generated.ClientProtos$1);
    Code:
       0: aload_0
       1: aload_1
       2: invokespecial #1                  // Method "<init>":(Lcom/google/protobuf/GeneratedMessage$BuilderParent;)V
       5: return
}
