Compiled from "ClientProtos.java"
public final class org.apache.hadoop.hbase.protobuf.generated.ClientProtos$ClientService$Stub extends org.apache.hadoop.hbase.protobuf.generated.ClientProtos$ClientService implements org.apache.hadoop.hbase.protobuf.generated.ClientProtos$ClientService$Interface {
  public com.google.protobuf.RpcChannel getChannel();
    Code:
       0: aload_0
       1: getfield      #3                  // Field channel:Lcom/google/protobuf/RpcChannel;
       4: areturn

  public void get(com.google.protobuf.RpcController, org.apache.hadoop.hbase.protobuf.generated.ClientProtos$GetRequest, com.google.protobuf.RpcCallback<org.apache.hadoop.hbase.protobuf.generated.ClientProtos$GetResponse>);
    Code:
       0: aload_0
       1: getfield      #3                  // Field channel:Lcom/google/protobuf/RpcChannel;
       4: invokestatic  #4                  // Method getDescriptor:()Lcom/google/protobuf/Descriptors$ServiceDescriptor;
       7: invokevirtual #5                  // Method com/google/protobuf/Descriptors$ServiceDescriptor.getMethods:()Ljava/util/List;
      10: iconst_0
      11: invokeinterface #6,  2            // InterfaceMethod java/util/List.get:(I)Ljava/lang/Object;
      16: checkcast     #7                  // class com/google/protobuf/Descriptors$MethodDescriptor
      19: aload_1
      20: aload_2
      21: invokestatic  #8                  // Method org/apache/hadoop/hbase/protobuf/generated/ClientProtos$GetResponse.getDefaultInstance:()Lorg/apache/hadoop/hbase/protobuf/generated/ClientProtos$GetResponse;
      24: aload_3
      25: ldc           #9                  // class org/apache/hadoop/hbase/protobuf/generated/ClientProtos$GetResponse
      27: invokestatic  #8                  // Method org/apache/hadoop/hbase/protobuf/generated/ClientProtos$GetResponse.getDefaultInstance:()Lorg/apache/hadoop/hbase/protobuf/generated/ClientProtos$GetResponse;
      30: invokestatic  #10                 // Method com/google/protobuf/RpcUtil.generalizeCallback:(Lcom/google/protobuf/RpcCallback;Ljava/lang/Class;Lcom/google/protobuf/Message;)Lcom/google/protobuf/RpcCallback;
      33: invokeinterface #11,  6           // InterfaceMethod com/google/protobuf/RpcChannel.callMethod:(Lcom/google/protobuf/Descriptors$MethodDescriptor;Lcom/google/protobuf/RpcController;Lcom/google/protobuf/Message;Lcom/google/protobuf/Message;Lcom/google/protobuf/RpcCallback;)V
      38: return

  public void mutate(com.google.protobuf.RpcController, org.apache.hadoop.hbase.protobuf.generated.ClientProtos$MutateRequest, com.google.protobuf.RpcCallback<org.apache.hadoop.hbase.protobuf.generated.ClientProtos$MutateResponse>);
    Code:
       0: aload_0
       1: getfield      #3                  // Field channel:Lcom/google/protobuf/RpcChannel;
       4: invokestatic  #4                  // Method getDescriptor:()Lcom/google/protobuf/Descriptors$ServiceDescriptor;
       7: invokevirtual #5                  // Method com/google/protobuf/Descriptors$ServiceDescriptor.getMethods:()Ljava/util/List;
      10: iconst_1
      11: invokeinterface #6,  2            // InterfaceMethod java/util/List.get:(I)Ljava/lang/Object;
      16: checkcast     #7                  // class com/google/protobuf/Descriptors$MethodDescriptor
      19: aload_1
      20: aload_2
      21: invokestatic  #12                 // Method org/apache/hadoop/hbase/protobuf/generated/ClientProtos$MutateResponse.getDefaultInstance:()Lorg/apache/hadoop/hbase/protobuf/generated/ClientProtos$MutateResponse;
      24: aload_3
      25: ldc           #13                 // class org/apache/hadoop/hbase/protobuf/generated/ClientProtos$MutateResponse
      27: invokestatic  #12                 // Method org/apache/hadoop/hbase/protobuf/generated/ClientProtos$MutateResponse.getDefaultInstance:()Lorg/apache/hadoop/hbase/protobuf/generated/ClientProtos$MutateResponse;
      30: invokestatic  #10                 // Method com/google/protobuf/RpcUtil.generalizeCallback:(Lcom/google/protobuf/RpcCallback;Ljava/lang/Class;Lcom/google/protobuf/Message;)Lcom/google/protobuf/RpcCallback;
      33: invokeinterface #11,  6           // InterfaceMethod com/google/protobuf/RpcChannel.callMethod:(Lcom/google/protobuf/Descriptors$MethodDescriptor;Lcom/google/protobuf/RpcController;Lcom/google/protobuf/Message;Lcom/google/protobuf/Message;Lcom/google/protobuf/RpcCallback;)V
      38: return

  public void scan(com.google.protobuf.RpcController, org.apache.hadoop.hbase.protobuf.generated.ClientProtos$ScanRequest, com.google.protobuf.RpcCallback<org.apache.hadoop.hbase.protobuf.generated.ClientProtos$ScanResponse>);
    Code:
       0: aload_0
       1: getfield      #3                  // Field channel:Lcom/google/protobuf/RpcChannel;
       4: invokestatic  #4                  // Method getDescriptor:()Lcom/google/protobuf/Descriptors$ServiceDescriptor;
       7: invokevirtual #5                  // Method com/google/protobuf/Descriptors$ServiceDescriptor.getMethods:()Ljava/util/List;
      10: iconst_2
      11: invokeinterface #6,  2            // InterfaceMethod java/util/List.get:(I)Ljava/lang/Object;
      16: checkcast     #7                  // class com/google/protobuf/Descriptors$MethodDescriptor
      19: aload_1
      20: aload_2
      21: invokestatic  #14                 // Method org/apache/hadoop/hbase/protobuf/generated/ClientProtos$ScanResponse.getDefaultInstance:()Lorg/apache/hadoop/hbase/protobuf/generated/ClientProtos$ScanResponse;
      24: aload_3
      25: ldc           #15                 // class org/apache/hadoop/hbase/protobuf/generated/ClientProtos$ScanResponse
      27: invokestatic  #14                 // Method org/apache/hadoop/hbase/protobuf/generated/ClientProtos$ScanResponse.getDefaultInstance:()Lorg/apache/hadoop/hbase/protobuf/generated/ClientProtos$ScanResponse;
      30: invokestatic  #10                 // Method com/google/protobuf/RpcUtil.generalizeCallback:(Lcom/google/protobuf/RpcCallback;Ljava/lang/Class;Lcom/google/protobuf/Message;)Lcom/google/protobuf/RpcCallback;
      33: invokeinterface #11,  6           // InterfaceMethod com/google/protobuf/RpcChannel.callMethod:(Lcom/google/protobuf/Descriptors$MethodDescriptor;Lcom/google/protobuf/RpcController;Lcom/google/protobuf/Message;Lcom/google/protobuf/Message;Lcom/google/protobuf/RpcCallback;)V
      38: return

  public void bulkLoadHFile(com.google.protobuf.RpcController, org.apache.hadoop.hbase.protobuf.generated.ClientProtos$BulkLoadHFileRequest, com.google.protobuf.RpcCallback<org.apache.hadoop.hbase.protobuf.generated.ClientProtos$BulkLoadHFileResponse>);
    Code:
       0: aload_0
       1: getfield      #3                  // Field channel:Lcom/google/protobuf/RpcChannel;
       4: invokestatic  #4                  // Method getDescriptor:()Lcom/google/protobuf/Descriptors$ServiceDescriptor;
       7: invokevirtual #5                  // Method com/google/protobuf/Descriptors$ServiceDescriptor.getMethods:()Ljava/util/List;
      10: iconst_3
      11: invokeinterface #6,  2            // InterfaceMethod java/util/List.get:(I)Ljava/lang/Object;
      16: checkcast     #7                  // class com/google/protobuf/Descriptors$MethodDescriptor
      19: aload_1
      20: aload_2
      21: invokestatic  #16                 // Method org/apache/hadoop/hbase/protobuf/generated/ClientProtos$BulkLoadHFileResponse.getDefaultInstance:()Lorg/apache/hadoop/hbase/protobuf/generated/ClientProtos$BulkLoadHFileResponse;
      24: aload_3
      25: ldc           #17                 // class org/apache/hadoop/hbase/protobuf/generated/ClientProtos$BulkLoadHFileResponse
      27: invokestatic  #16                 // Method org/apache/hadoop/hbase/protobuf/generated/ClientProtos$BulkLoadHFileResponse.getDefaultInstance:()Lorg/apache/hadoop/hbase/protobuf/generated/ClientProtos$BulkLoadHFileResponse;
      30: invokestatic  #10                 // Method com/google/protobuf/RpcUtil.generalizeCallback:(Lcom/google/protobuf/RpcCallback;Ljava/lang/Class;Lcom/google/protobuf/Message;)Lcom/google/protobuf/RpcCallback;
      33: invokeinterface #11,  6           // InterfaceMethod com/google/protobuf/RpcChannel.callMethod:(Lcom/google/protobuf/Descriptors$MethodDescriptor;Lcom/google/protobuf/RpcController;Lcom/google/protobuf/Message;Lcom/google/protobuf/Message;Lcom/google/protobuf/RpcCallback;)V
      38: return

  public void prepareBulkLoad(com.google.protobuf.RpcController, org.apache.hadoop.hbase.protobuf.generated.ClientProtos$PrepareBulkLoadRequest, com.google.protobuf.RpcCallback<org.apache.hadoop.hbase.protobuf.generated.ClientProtos$PrepareBulkLoadResponse>);
    Code:
       0: aload_0
       1: getfield      #3                  // Field channel:Lcom/google/protobuf/RpcChannel;
       4: invokestatic  #4                  // Method getDescriptor:()Lcom/google/protobuf/Descriptors$ServiceDescriptor;
       7: invokevirtual #5                  // Method com/google/protobuf/Descriptors$ServiceDescriptor.getMethods:()Ljava/util/List;
      10: iconst_4
      11: invokeinterface #6,  2            // InterfaceMethod java/util/List.get:(I)Ljava/lang/Object;
      16: checkcast     #7                  // class com/google/protobuf/Descriptors$MethodDescriptor
      19: aload_1
      20: aload_2
      21: invokestatic  #18                 // Method org/apache/hadoop/hbase/protobuf/generated/ClientProtos$PrepareBulkLoadResponse.getDefaultInstance:()Lorg/apache/hadoop/hbase/protobuf/generated/ClientProtos$PrepareBulkLoadResponse;
      24: aload_3
      25: ldc           #19                 // class org/apache/hadoop/hbase/protobuf/generated/ClientProtos$PrepareBulkLoadResponse
      27: invokestatic  #18                 // Method org/apache/hadoop/hbase/protobuf/generated/ClientProtos$PrepareBulkLoadResponse.getDefaultInstance:()Lorg/apache/hadoop/hbase/protobuf/generated/ClientProtos$PrepareBulkLoadResponse;
      30: invokestatic  #10                 // Method com/google/protobuf/RpcUtil.generalizeCallback:(Lcom/google/protobuf/RpcCallback;Ljava/lang/Class;Lcom/google/protobuf/Message;)Lcom/google/protobuf/RpcCallback;
      33: invokeinterface #11,  6           // InterfaceMethod com/google/protobuf/RpcChannel.callMethod:(Lcom/google/protobuf/Descriptors$MethodDescriptor;Lcom/google/protobuf/RpcController;Lcom/google/protobuf/Message;Lcom/google/protobuf/Message;Lcom/google/protobuf/RpcCallback;)V
      38: return

  public void cleanupBulkLoad(com.google.protobuf.RpcController, org.apache.hadoop.hbase.protobuf.generated.ClientProtos$CleanupBulkLoadRequest, com.google.protobuf.RpcCallback<org.apache.hadoop.hbase.protobuf.generated.ClientProtos$CleanupBulkLoadResponse>);
    Code:
       0: aload_0
       1: getfield      #3                  // Field channel:Lcom/google/protobuf/RpcChannel;
       4: invokestatic  #4                  // Method getDescriptor:()Lcom/google/protobuf/Descriptors$ServiceDescriptor;
       7: invokevirtual #5                  // Method com/google/protobuf/Descriptors$ServiceDescriptor.getMethods:()Ljava/util/List;
      10: iconst_5
      11: invokeinterface #6,  2            // InterfaceMethod java/util/List.get:(I)Ljava/lang/Object;
      16: checkcast     #7                  // class com/google/protobuf/Descriptors$MethodDescriptor
      19: aload_1
      20: aload_2
      21: invokestatic  #20                 // Method org/apache/hadoop/hbase/protobuf/generated/ClientProtos$CleanupBulkLoadResponse.getDefaultInstance:()Lorg/apache/hadoop/hbase/protobuf/generated/ClientProtos$CleanupBulkLoadResponse;
      24: aload_3
      25: ldc           #21                 // class org/apache/hadoop/hbase/protobuf/generated/ClientProtos$CleanupBulkLoadResponse
      27: invokestatic  #20                 // Method org/apache/hadoop/hbase/protobuf/generated/ClientProtos$CleanupBulkLoadResponse.getDefaultInstance:()Lorg/apache/hadoop/hbase/protobuf/generated/ClientProtos$CleanupBulkLoadResponse;
      30: invokestatic  #10                 // Method com/google/protobuf/RpcUtil.generalizeCallback:(Lcom/google/protobuf/RpcCallback;Ljava/lang/Class;Lcom/google/protobuf/Message;)Lcom/google/protobuf/RpcCallback;
      33: invokeinterface #11,  6           // InterfaceMethod com/google/protobuf/RpcChannel.callMethod:(Lcom/google/protobuf/Descriptors$MethodDescriptor;Lcom/google/protobuf/RpcController;Lcom/google/protobuf/Message;Lcom/google/protobuf/Message;Lcom/google/protobuf/RpcCallback;)V
      38: return

  public void execService(com.google.protobuf.RpcController, org.apache.hadoop.hbase.protobuf.generated.ClientProtos$CoprocessorServiceRequest, com.google.protobuf.RpcCallback<org.apache.hadoop.hbase.protobuf.generated.ClientProtos$CoprocessorServiceResponse>);
    Code:
       0: aload_0
       1: getfield      #3                  // Field channel:Lcom/google/protobuf/RpcChannel;
       4: invokestatic  #4                  // Method getDescriptor:()Lcom/google/protobuf/Descriptors$ServiceDescriptor;
       7: invokevirtual #5                  // Method com/google/protobuf/Descriptors$ServiceDescriptor.getMethods:()Ljava/util/List;
      10: bipush        6
      12: invokeinterface #6,  2            // InterfaceMethod java/util/List.get:(I)Ljava/lang/Object;
      17: checkcast     #7                  // class com/google/protobuf/Descriptors$MethodDescriptor
      20: aload_1
      21: aload_2
      22: invokestatic  #22                 // Method org/apache/hadoop/hbase/protobuf/generated/ClientProtos$CoprocessorServiceResponse.getDefaultInstance:()Lorg/apache/hadoop/hbase/protobuf/generated/ClientProtos$CoprocessorServiceResponse;
      25: aload_3
      26: ldc           #23                 // class org/apache/hadoop/hbase/protobuf/generated/ClientProtos$CoprocessorServiceResponse
      28: invokestatic  #22                 // Method org/apache/hadoop/hbase/protobuf/generated/ClientProtos$CoprocessorServiceResponse.getDefaultInstance:()Lorg/apache/hadoop/hbase/protobuf/generated/ClientProtos$CoprocessorServiceResponse;
      31: invokestatic  #10                 // Method com/google/protobuf/RpcUtil.generalizeCallback:(Lcom/google/protobuf/RpcCallback;Ljava/lang/Class;Lcom/google/protobuf/Message;)Lcom/google/protobuf/RpcCallback;
      34: invokeinterface #11,  6           // InterfaceMethod com/google/protobuf/RpcChannel.callMethod:(Lcom/google/protobuf/Descriptors$MethodDescriptor;Lcom/google/protobuf/RpcController;Lcom/google/protobuf/Message;Lcom/google/protobuf/Message;Lcom/google/protobuf/RpcCallback;)V
      39: return

  public void execRegionServerService(com.google.protobuf.RpcController, org.apache.hadoop.hbase.protobuf.generated.ClientProtos$CoprocessorServiceRequest, com.google.protobuf.RpcCallback<org.apache.hadoop.hbase.protobuf.generated.ClientProtos$CoprocessorServiceResponse>);
    Code:
       0: aload_0
       1: getfield      #3                  // Field channel:Lcom/google/protobuf/RpcChannel;
       4: invokestatic  #4                  // Method getDescriptor:()Lcom/google/protobuf/Descriptors$ServiceDescriptor;
       7: invokevirtual #5                  // Method com/google/protobuf/Descriptors$ServiceDescriptor.getMethods:()Ljava/util/List;
      10: bipush        7
      12: invokeinterface #6,  2            // InterfaceMethod java/util/List.get:(I)Ljava/lang/Object;
      17: checkcast     #7                  // class com/google/protobuf/Descriptors$MethodDescriptor
      20: aload_1
      21: aload_2
      22: invokestatic  #22                 // Method org/apache/hadoop/hbase/protobuf/generated/ClientProtos$CoprocessorServiceResponse.getDefaultInstance:()Lorg/apache/hadoop/hbase/protobuf/generated/ClientProtos$CoprocessorServiceResponse;
      25: aload_3
      26: ldc           #23                 // class org/apache/hadoop/hbase/protobuf/generated/ClientProtos$CoprocessorServiceResponse
      28: invokestatic  #22                 // Method org/apache/hadoop/hbase/protobuf/generated/ClientProtos$CoprocessorServiceResponse.getDefaultInstance:()Lorg/apache/hadoop/hbase/protobuf/generated/ClientProtos$CoprocessorServiceResponse;
      31: invokestatic  #10                 // Method com/google/protobuf/RpcUtil.generalizeCallback:(Lcom/google/protobuf/RpcCallback;Ljava/lang/Class;Lcom/google/protobuf/Message;)Lcom/google/protobuf/RpcCallback;
      34: invokeinterface #11,  6           // InterfaceMethod com/google/protobuf/RpcChannel.callMethod:(Lcom/google/protobuf/Descriptors$MethodDescriptor;Lcom/google/protobuf/RpcController;Lcom/google/protobuf/Message;Lcom/google/protobuf/Message;Lcom/google/protobuf/RpcCallback;)V
      39: return

  public void multi(com.google.protobuf.RpcController, org.apache.hadoop.hbase.protobuf.generated.ClientProtos$MultiRequest, com.google.protobuf.RpcCallback<org.apache.hadoop.hbase.protobuf.generated.ClientProtos$MultiResponse>);
    Code:
       0: aload_0
       1: getfield      #3                  // Field channel:Lcom/google/protobuf/RpcChannel;
       4: invokestatic  #4                  // Method getDescriptor:()Lcom/google/protobuf/Descriptors$ServiceDescriptor;
       7: invokevirtual #5                  // Method com/google/protobuf/Descriptors$ServiceDescriptor.getMethods:()Ljava/util/List;
      10: bipush        8
      12: invokeinterface #6,  2            // InterfaceMethod java/util/List.get:(I)Ljava/lang/Object;
      17: checkcast     #7                  // class com/google/protobuf/Descriptors$MethodDescriptor
      20: aload_1
      21: aload_2
      22: invokestatic  #24                 // Method org/apache/hadoop/hbase/protobuf/generated/ClientProtos$MultiResponse.getDefaultInstance:()Lorg/apache/hadoop/hbase/protobuf/generated/ClientProtos$MultiResponse;
      25: aload_3
      26: ldc           #25                 // class org/apache/hadoop/hbase/protobuf/generated/ClientProtos$MultiResponse
      28: invokestatic  #24                 // Method org/apache/hadoop/hbase/protobuf/generated/ClientProtos$MultiResponse.getDefaultInstance:()Lorg/apache/hadoop/hbase/protobuf/generated/ClientProtos$MultiResponse;
      31: invokestatic  #10                 // Method com/google/protobuf/RpcUtil.generalizeCallback:(Lcom/google/protobuf/RpcCallback;Ljava/lang/Class;Lcom/google/protobuf/Message;)Lcom/google/protobuf/RpcCallback;
      34: invokeinterface #11,  6           // InterfaceMethod com/google/protobuf/RpcChannel.callMethod:(Lcom/google/protobuf/Descriptors$MethodDescriptor;Lcom/google/protobuf/RpcController;Lcom/google/protobuf/Message;Lcom/google/protobuf/Message;Lcom/google/protobuf/RpcCallback;)V
      39: return

  org.apache.hadoop.hbase.protobuf.generated.ClientProtos$ClientService$Stub(com.google.protobuf.RpcChannel, org.apache.hadoop.hbase.protobuf.generated.ClientProtos$1);
    Code:
       0: aload_0
       1: aload_1
       2: invokespecial #1                  // Method "<init>":(Lcom/google/protobuf/RpcChannel;)V
       5: return
}
