Compiled from "ClientProtos.java"
public final class org.apache.hadoop.hbase.protobuf.generated.ClientProtos$ScanResponse extends com.google.protobuf.GeneratedMessage implements org.apache.hadoop.hbase.protobuf.generated.ClientProtos$ScanResponseOrBuilder {
  public static com.google.protobuf.Parser<org.apache.hadoop.hbase.protobuf.generated.ClientProtos$ScanResponse> PARSER;

  public static final int CELLS_PER_RESULT_FIELD_NUMBER;

  public static final int SCANNER_ID_FIELD_NUMBER;

  public static final int MORE_RESULTS_FIELD_NUMBER;

  public static final int TTL_FIELD_NUMBER;

  public static final int RESULTS_FIELD_NUMBER;

  public static final int STALE_FIELD_NUMBER;

  public static final int PARTIAL_FLAG_PER_RESULT_FIELD_NUMBER;

  public static final int MORE_RESULTS_IN_REGION_FIELD_NUMBER;

  public static final int HEARTBEAT_MESSAGE_FIELD_NUMBER;

  public static final int SCAN_METRICS_FIELD_NUMBER;

  public static final int MVCC_READ_POINT_FIELD_NUMBER;

  public static final int CURSOR_FIELD_NUMBER;

  public static org.apache.hadoop.hbase.protobuf.generated.ClientProtos$ScanResponse getDefaultInstance();
    Code:
       0: getstatic     #25                 // Field defaultInstance:Lorg/apache/hadoop/hbase/protobuf/generated/ClientProtos$ScanResponse;
       3: areturn

  public org.apache.hadoop.hbase.protobuf.generated.ClientProtos$ScanResponse getDefaultInstanceForType();
    Code:
       0: getstatic     #25                 // Field defaultInstance:Lorg/apache/hadoop/hbase/protobuf/generated/ClientProtos$ScanResponse;
       3: areturn

  public final com.google.protobuf.UnknownFieldSet getUnknownFields();
    Code:
       0: aload_0
       1: getfield      #22                 // Field unknownFields:Lcom/google/protobuf/UnknownFieldSet;
       4: areturn

  public static final com.google.protobuf.Descriptors$Descriptor getDescriptor();
    Code:
       0: invokestatic  #62                 // Method org/apache/hadoop/hbase/protobuf/generated/ClientProtos.access$22700:()Lcom/google/protobuf/Descriptors$Descriptor;
       3: areturn

  protected com.google.protobuf.GeneratedMessage$FieldAccessorTable internalGetFieldAccessorTable();
    Code:
       0: invokestatic  #63                 // Method org/apache/hadoop/hbase/protobuf/generated/ClientProtos.access$22800:()Lcom/google/protobuf/GeneratedMessage$FieldAccessorTable;
       3: ldc           #64                 // class org/apache/hadoop/hbase/protobuf/generated/ClientProtos$ScanResponse
       5: ldc           #65                 // class org/apache/hadoop/hbase/protobuf/generated/ClientProtos$ScanResponse$Builder
       7: invokevirtual #66                 // Method com/google/protobuf/GeneratedMessage$FieldAccessorTable.ensureFieldAccessorsInitialized:(Ljava/lang/Class;Ljava/lang/Class;)Lcom/google/protobuf/GeneratedMessage$FieldAccessorTable;
      10: areturn

  public com.google.protobuf.Parser<org.apache.hadoop.hbase.protobuf.generated.ClientProtos$ScanResponse> getParserForType();
    Code:
       0: getstatic     #67                 // Field PARSER:Lcom/google/protobuf/Parser;
       3: areturn

  public java.util.List<java.lang.Integer> getCellsPerResultList();
    Code:
       0: aload_0
       1: getfield      #14                 // Field cellsPerResult_:Ljava/util/List;
       4: areturn

  public int getCellsPerResultCount();
    Code:
       0: aload_0
       1: getfield      #14                 // Field cellsPerResult_:Ljava/util/List;
       4: invokeinterface #68,  1           // InterfaceMethod java/util/List.size:()I
       9: ireturn

  public int getCellsPerResult(int);
    Code:
       0: aload_0
       1: getfield      #14                 // Field cellsPerResult_:Ljava/util/List;
       4: iload_1
       5: invokeinterface #69,  2           // InterfaceMethod java/util/List.get:(I)Ljava/lang/Object;
      10: checkcast     #70                 // class java/lang/Integer
      13: invokevirtual #71                 // Method java/lang/Integer.intValue:()I
      16: ireturn

  public boolean hasScannerId();
    Code:
       0: aload_0
       1: getfield      #2                  // Field bitField0_:I
       4: iconst_1
       5: iand
       6: iconst_1
       7: if_icmpne     14
      10: iconst_1
      11: goto          15
      14: iconst_0
      15: ireturn

  public long getScannerId();
    Code:
       0: aload_0
       1: getfield      #13                 // Field scannerId_:J
       4: lreturn

  public boolean hasMoreResults();
    Code:
       0: aload_0
       1: getfield      #2                  // Field bitField0_:I
       4: iconst_2
       5: iand
       6: iconst_2
       7: if_icmpne     14
      10: iconst_1
      11: goto          15
      14: iconst_0
      15: ireturn

  public boolean getMoreResults();
    Code:
       0: aload_0
       1: getfield      #12                 // Field moreResults_:Z
       4: ireturn

  public boolean hasTtl();
    Code:
       0: aload_0
       1: getfield      #2                  // Field bitField0_:I
       4: iconst_4
       5: iand
       6: iconst_4
       7: if_icmpne     14
      10: iconst_1
      11: goto          15
      14: iconst_0
      15: ireturn

  public int getTtl();
    Code:
       0: aload_0
       1: getfield      #11                 // Field ttl_:I
       4: ireturn

  public java.util.List<org.apache.hadoop.hbase.protobuf.generated.ClientProtos$Result> getResultsList();
    Code:
       0: aload_0
       1: getfield      #10                 // Field results_:Ljava/util/List;
       4: areturn

  public java.util.List<? extends org.apache.hadoop.hbase.protobuf.generated.ClientProtos$ResultOrBuilder> getResultsOrBuilderList();
    Code:
       0: aload_0
       1: getfield      #10                 // Field results_:Ljava/util/List;
       4: areturn

  public int getResultsCount();
    Code:
       0: aload_0
       1: getfield      #10                 // Field results_:Ljava/util/List;
       4: invokeinterface #68,  1           // InterfaceMethod java/util/List.size:()I
       9: ireturn

  public org.apache.hadoop.hbase.protobuf.generated.ClientProtos$Result getResults(int);
    Code:
       0: aload_0
       1: getfield      #10                 // Field results_:Ljava/util/List;
       4: iload_1
       5: invokeinterface #69,  2           // InterfaceMethod java/util/List.get:(I)Ljava/lang/Object;
      10: checkcast     #72                 // class org/apache/hadoop/hbase/protobuf/generated/ClientProtos$Result
      13: areturn

  public org.apache.hadoop.hbase.protobuf.generated.ClientProtos$ResultOrBuilder getResultsOrBuilder(int);
    Code:
       0: aload_0
       1: getfield      #10                 // Field results_:Ljava/util/List;
       4: iload_1
       5: invokeinterface #69,  2           // InterfaceMethod java/util/List.get:(I)Ljava/lang/Object;
      10: checkcast     #73                 // class org/apache/hadoop/hbase/protobuf/generated/ClientProtos$ResultOrBuilder
      13: areturn

  public boolean hasStale();
    Code:
       0: aload_0
       1: getfield      #2                  // Field bitField0_:I
       4: bipush        8
       6: iand
       7: bipush        8
       9: if_icmpne     16
      12: iconst_1
      13: goto          17
      16: iconst_0
      17: ireturn

  public boolean getStale();
    Code:
       0: aload_0
       1: getfield      #9                  // Field stale_:Z
       4: ireturn

  public java.util.List<java.lang.Boolean> getPartialFlagPerResultList();
    Code:
       0: aload_0
       1: getfield      #8                  // Field partialFlagPerResult_:Ljava/util/List;
       4: areturn

  public int getPartialFlagPerResultCount();
    Code:
       0: aload_0
       1: getfield      #8                  // Field partialFlagPerResult_:Ljava/util/List;
       4: invokeinterface #68,  1           // InterfaceMethod java/util/List.size:()I
       9: ireturn

  public boolean getPartialFlagPerResult(int);
    Code:
       0: aload_0
       1: getfield      #8                  // Field partialFlagPerResult_:Ljava/util/List;
       4: iload_1
       5: invokeinterface #69,  2           // InterfaceMethod java/util/List.get:(I)Ljava/lang/Object;
      10: checkcast     #74                 // class java/lang/Boolean
      13: invokevirtual #75                 // Method java/lang/Boolean.booleanValue:()Z
      16: ireturn

  public boolean hasMoreResultsInRegion();
    Code:
       0: aload_0
       1: getfield      #2                  // Field bitField0_:I
       4: bipush        16
       6: iand
       7: bipush        16
       9: if_icmpne     16
      12: iconst_1
      13: goto          17
      16: iconst_0
      17: ireturn

  public boolean getMoreResultsInRegion();
    Code:
       0: aload_0
       1: getfield      #7                  // Field moreResultsInRegion_:Z
       4: ireturn

  public boolean hasHeartbeatMessage();
    Code:
       0: aload_0
       1: getfield      #2                  // Field bitField0_:I
       4: bipush        32
       6: iand
       7: bipush        32
       9: if_icmpne     16
      12: iconst_1
      13: goto          17
      16: iconst_0
      17: ireturn

  public boolean getHeartbeatMessage();
    Code:
       0: aload_0
       1: getfield      #6                  // Field heartbeatMessage_:Z
       4: ireturn

  public boolean hasScanMetrics();
    Code:
       0: aload_0
       1: getfield      #2                  // Field bitField0_:I
       4: bipush        64
       6: iand
       7: bipush        64
       9: if_icmpne     16
      12: iconst_1
      13: goto          17
      16: iconst_0
      17: ireturn

  public org.apache.hadoop.hbase.protobuf.generated.MapReduceProtos$ScanMetrics getScanMetrics();
    Code:
       0: aload_0
       1: getfield      #5                  // Field scanMetrics_:Lorg/apache/hadoop/hbase/protobuf/generated/MapReduceProtos$ScanMetrics;
       4: areturn

  public org.apache.hadoop.hbase.protobuf.generated.MapReduceProtos$ScanMetricsOrBuilder getScanMetricsOrBuilder();
    Code:
       0: aload_0
       1: getfield      #5                  // Field scanMetrics_:Lorg/apache/hadoop/hbase/protobuf/generated/MapReduceProtos$ScanMetrics;
       4: areturn

  public boolean hasMvccReadPoint();
    Code:
       0: aload_0
       1: getfield      #2                  // Field bitField0_:I
       4: sipush        128
       7: iand
       8: sipush        128
      11: if_icmpne     18
      14: iconst_1
      15: goto          19
      18: iconst_0
      19: ireturn

  public long getMvccReadPoint();
    Code:
       0: aload_0
       1: getfield      #4                  // Field mvccReadPoint_:J
       4: lreturn

  public boolean hasCursor();
    Code:
       0: aload_0
       1: getfield      #2                  // Field bitField0_:I
       4: sipush        256
       7: iand
       8: sipush        256
      11: if_icmpne     18
      14: iconst_1
      15: goto          19
      18: iconst_0
      19: ireturn

  public org.apache.hadoop.hbase.protobuf.generated.ClientProtos$Cursor getCursor();
    Code:
       0: aload_0
       1: getfield      #3                  // Field cursor_:Lorg/apache/hadoop/hbase/protobuf/generated/ClientProtos$Cursor;
       4: areturn

  public org.apache.hadoop.hbase.protobuf.generated.ClientProtos$CursorOrBuilder getCursorOrBuilder();
    Code:
       0: aload_0
       1: getfield      #3                  // Field cursor_:Lorg/apache/hadoop/hbase/protobuf/generated/ClientProtos$Cursor;
       4: areturn

  public final boolean isInitialized();
    Code:
       0: aload_0
       1: getfield      #18                 // Field memoizedIsInitialized:B
       4: istore_1
       5: iload_1
       6: iconst_m1
       7: if_icmpeq     21
      10: iload_1
      11: iconst_1
      12: if_icmpne     19
      15: iconst_1
      16: goto          20
      19: iconst_0
      20: ireturn
      21: aload_0
      22: iconst_1
      23: putfield      #18                 // Field memoizedIsInitialized:B
      26: iconst_1
      27: ireturn

  public void writeTo(com.google.protobuf.CodedOutputStream) throws java.io.IOException;
    Code:
       0: aload_0
       1: invokevirtual #79                 // Method getSerializedSize:()I
       4: pop
       5: iconst_0
       6: istore_2
       7: iload_2
       8: aload_0
       9: getfield      #14                 // Field cellsPerResult_:Ljava/util/List;
      12: invokeinterface #68,  1           // InterfaceMethod java/util/List.size:()I
      17: if_icmpge     47
      20: aload_1
      21: iconst_1
      22: aload_0
      23: getfield      #14                 // Field cellsPerResult_:Ljava/util/List;
      26: iload_2
      27: invokeinterface #69,  2           // InterfaceMethod java/util/List.get:(I)Ljava/lang/Object;
      32: checkcast     #70                 // class java/lang/Integer
      35: invokevirtual #71                 // Method java/lang/Integer.intValue:()I
      38: invokevirtual #80                 // Method com/google/protobuf/CodedOutputStream.writeUInt32:(II)V
      41: iinc          2, 1
      44: goto          7
      47: aload_0
      48: getfield      #2                  // Field bitField0_:I
      51: iconst_1
      52: iand
      53: iconst_1
      54: if_icmpne     66
      57: aload_1
      58: iconst_2
      59: aload_0
      60: getfield      #13                 // Field scannerId_:J
      63: invokevirtual #81                 // Method com/google/protobuf/CodedOutputStream.writeUInt64:(IJ)V
      66: aload_0
      67: getfield      #2                  // Field bitField0_:I
      70: iconst_2
      71: iand
      72: iconst_2
      73: if_icmpne     85
      76: aload_1
      77: iconst_3
      78: aload_0
      79: getfield      #12                 // Field moreResults_:Z
      82: invokevirtual #82                 // Method com/google/protobuf/CodedOutputStream.writeBool:(IZ)V
      85: aload_0
      86: getfield      #2                  // Field bitField0_:I
      89: iconst_4
      90: iand
      91: iconst_4
      92: if_icmpne     104
      95: aload_1
      96: iconst_4
      97: aload_0
      98: getfield      #11                 // Field ttl_:I
     101: invokevirtual #80                 // Method com/google/protobuf/CodedOutputStream.writeUInt32:(II)V
     104: iconst_0
     105: istore_2
     106: iload_2
     107: aload_0
     108: getfield      #10                 // Field results_:Ljava/util/List;
     111: invokeinterface #68,  1           // InterfaceMethod java/util/List.size:()I
     116: if_icmpge     143
     119: aload_1
     120: iconst_5
     121: aload_0
     122: getfield      #10                 // Field results_:Ljava/util/List;
     125: iload_2
     126: invokeinterface #69,  2           // InterfaceMethod java/util/List.get:(I)Ljava/lang/Object;
     131: checkcast     #83                 // class com/google/protobuf/MessageLite
     134: invokevirtual #84                 // Method com/google/protobuf/CodedOutputStream.writeMessage:(ILcom/google/protobuf/MessageLite;)V
     137: iinc          2, 1
     140: goto          106
     143: aload_0
     144: getfield      #2                  // Field bitField0_:I
     147: bipush        8
     149: iand
     150: bipush        8
     152: if_icmpne     165
     155: aload_1
     156: bipush        6
     158: aload_0
     159: getfield      #9                  // Field stale_:Z
     162: invokevirtual #82                 // Method com/google/protobuf/CodedOutputStream.writeBool:(IZ)V
     165: iconst_0
     166: istore_2
     167: iload_2
     168: aload_0
     169: getfield      #8                  // Field partialFlagPerResult_:Ljava/util/List;
     172: invokeinterface #68,  1           // InterfaceMethod java/util/List.size:()I
     177: if_icmpge     208
     180: aload_1
     181: bipush        7
     183: aload_0
     184: getfield      #8                  // Field partialFlagPerResult_:Ljava/util/List;
     187: iload_2
     188: invokeinterface #69,  2           // InterfaceMethod java/util/List.get:(I)Ljava/lang/Object;
     193: checkcast     #74                 // class java/lang/Boolean
     196: invokevirtual #75                 // Method java/lang/Boolean.booleanValue:()Z
     199: invokevirtual #82                 // Method com/google/protobuf/CodedOutputStream.writeBool:(IZ)V
     202: iinc          2, 1
     205: goto          167
     208: aload_0
     209: getfield      #2                  // Field bitField0_:I
     212: bipush        16
     214: iand
     215: bipush        16
     217: if_icmpne     230
     220: aload_1
     221: bipush        8
     223: aload_0
     224: getfield      #7                  // Field moreResultsInRegion_:Z
     227: invokevirtual #82                 // Method com/google/protobuf/CodedOutputStream.writeBool:(IZ)V
     230: aload_0
     231: getfield      #2                  // Field bitField0_:I
     234: bipush        32
     236: iand
     237: bipush        32
     239: if_icmpne     252
     242: aload_1
     243: bipush        9
     245: aload_0
     246: getfield      #6                  // Field heartbeatMessage_:Z
     249: invokevirtual #82                 // Method com/google/protobuf/CodedOutputStream.writeBool:(IZ)V
     252: aload_0
     253: getfield      #2                  // Field bitField0_:I
     256: bipush        64
     258: iand
     259: bipush        64
     261: if_icmpne     274
     264: aload_1
     265: bipush        10
     267: aload_0
     268: getfield      #5                  // Field scanMetrics_:Lorg/apache/hadoop/hbase/protobuf/generated/MapReduceProtos$ScanMetrics;
     271: invokevirtual #84                 // Method com/google/protobuf/CodedOutputStream.writeMessage:(ILcom/google/protobuf/MessageLite;)V
     274: aload_0
     275: getfield      #2                  // Field bitField0_:I
     278: sipush        128
     281: iand
     282: sipush        128
     285: if_icmpne     298
     288: aload_1
     289: bipush        11
     291: aload_0
     292: getfield      #4                  // Field mvccReadPoint_:J
     295: invokevirtual #81                 // Method com/google/protobuf/CodedOutputStream.writeUInt64:(IJ)V
     298: aload_0
     299: getfield      #2                  // Field bitField0_:I
     302: sipush        256
     305: iand
     306: sipush        256
     309: if_icmpne     322
     312: aload_1
     313: bipush        12
     315: aload_0
     316: getfield      #3                  // Field cursor_:Lorg/apache/hadoop/hbase/protobuf/generated/ClientProtos$Cursor;
     319: invokevirtual #84                 // Method com/google/protobuf/CodedOutputStream.writeMessage:(ILcom/google/protobuf/MessageLite;)V
     322: aload_0
     323: invokevirtual #85                 // Method getUnknownFields:()Lcom/google/protobuf/UnknownFieldSet;
     326: aload_1
     327: invokevirtual #86                 // Method com/google/protobuf/UnknownFieldSet.writeTo:(Lcom/google/protobuf/CodedOutputStream;)V
     330: return

  public int getSerializedSize();
    Code:
       0: aload_0
       1: getfield      #19                 // Field memoizedSerializedSize:I
       4: istore_1
       5: iload_1
       6: iconst_m1
       7: if_icmpeq     12
      10: iload_1
      11: ireturn
      12: iconst_0
      13: istore_1
      14: iconst_0
      15: istore_2
      16: iconst_0
      17: istore_3
      18: iload_3
      19: aload_0
      20: getfield      #14                 // Field cellsPerResult_:Ljava/util/List;
      23: invokeinterface #68,  1           // InterfaceMethod java/util/List.size:()I
      28: if_icmpge     59
      31: iload_2
      32: aload_0
      33: getfield      #14                 // Field cellsPerResult_:Ljava/util/List;
      36: iload_3
      37: invokeinterface #69,  2           // InterfaceMethod java/util/List.get:(I)Ljava/lang/Object;
      42: checkcast     #70                 // class java/lang/Integer
      45: invokevirtual #71                 // Method java/lang/Integer.intValue:()I
      48: invokestatic  #87                 // Method com/google/protobuf/CodedOutputStream.computeUInt32SizeNoTag:(I)I
      51: iadd
      52: istore_2
      53: iinc          3, 1
      56: goto          18
      59: iload_1
      60: iload_2
      61: iadd
      62: istore_1
      63: iload_1
      64: iconst_1
      65: aload_0
      66: invokevirtual #88                 // Method getCellsPerResultList:()Ljava/util/List;
      69: invokeinterface #68,  1           // InterfaceMethod java/util/List.size:()I
      74: imul
      75: iadd
      76: istore_1
      77: aload_0
      78: getfield      #2                  // Field bitField0_:I
      81: iconst_1
      82: iand
      83: iconst_1
      84: if_icmpne     98
      87: iload_1
      88: iconst_2
      89: aload_0
      90: getfield      #13                 // Field scannerId_:J
      93: invokestatic  #89                 // Method com/google/protobuf/CodedOutputStream.computeUInt64Size:(IJ)I
      96: iadd
      97: istore_1
      98: aload_0
      99: getfield      #2                  // Field bitField0_:I
     102: iconst_2
     103: iand
     104: iconst_2
     105: if_icmpne     119
     108: iload_1
     109: iconst_3
     110: aload_0
     111: getfield      #12                 // Field moreResults_:Z
     114: invokestatic  #90                 // Method com/google/protobuf/CodedOutputStream.computeBoolSize:(IZ)I
     117: iadd
     118: istore_1
     119: aload_0
     120: getfield      #2                  // Field bitField0_:I
     123: iconst_4
     124: iand
     125: iconst_4
     126: if_icmpne     140
     129: iload_1
     130: iconst_4
     131: aload_0
     132: getfield      #11                 // Field ttl_:I
     135: invokestatic  #91                 // Method com/google/protobuf/CodedOutputStream.computeUInt32Size:(II)I
     138: iadd
     139: istore_1
     140: iconst_0
     141: istore_2
     142: iload_2
     143: aload_0
     144: getfield      #10                 // Field results_:Ljava/util/List;
     147: invokeinterface #68,  1           // InterfaceMethod java/util/List.size:()I
     152: if_icmpge     181
     155: iload_1
     156: iconst_5
     157: aload_0
     158: getfield      #10                 // Field results_:Ljava/util/List;
     161: iload_2
     162: invokeinterface #69,  2           // InterfaceMethod java/util/List.get:(I)Ljava/lang/Object;
     167: checkcast     #83                 // class com/google/protobuf/MessageLite
     170: invokestatic  #92                 // Method com/google/protobuf/CodedOutputStream.computeMessageSize:(ILcom/google/protobuf/MessageLite;)I
     173: iadd
     174: istore_1
     175: iinc          2, 1
     178: goto          142
     181: aload_0
     182: getfield      #2                  // Field bitField0_:I
     185: bipush        8
     187: iand
     188: bipush        8
     190: if_icmpne     205
     193: iload_1
     194: bipush        6
     196: aload_0
     197: getfield      #9                  // Field stale_:Z
     200: invokestatic  #90                 // Method com/google/protobuf/CodedOutputStream.computeBoolSize:(IZ)I
     203: iadd
     204: istore_1
     205: iconst_0
     206: istore_2
     207: iconst_1
     208: aload_0
     209: invokevirtual #93                 // Method getPartialFlagPerResultList:()Ljava/util/List;
     212: invokeinterface #68,  1           // InterfaceMethod java/util/List.size:()I
     217: imul
     218: istore_2
     219: iload_1
     220: iload_2
     221: iadd
     222: istore_1
     223: iload_1
     224: iconst_1
     225: aload_0
     226: invokevirtual #93                 // Method getPartialFlagPerResultList:()Ljava/util/List;
     229: invokeinterface #68,  1           // InterfaceMethod java/util/List.size:()I
     234: imul
     235: iadd
     236: istore_1
     237: aload_0
     238: getfield      #2                  // Field bitField0_:I
     241: bipush        16
     243: iand
     244: bipush        16
     246: if_icmpne     261
     249: iload_1
     250: bipush        8
     252: aload_0
     253: getfield      #7                  // Field moreResultsInRegion_:Z
     256: invokestatic  #90                 // Method com/google/protobuf/CodedOutputStream.computeBoolSize:(IZ)I
     259: iadd
     260: istore_1
     261: aload_0
     262: getfield      #2                  // Field bitField0_:I
     265: bipush        32
     267: iand
     268: bipush        32
     270: if_icmpne     285
     273: iload_1
     274: bipush        9
     276: aload_0
     277: getfield      #6                  // Field heartbeatMessage_:Z
     280: invokestatic  #90                 // Method com/google/protobuf/CodedOutputStream.computeBoolSize:(IZ)I
     283: iadd
     284: istore_1
     285: aload_0
     286: getfield      #2                  // Field bitField0_:I
     289: bipush        64
     291: iand
     292: bipush        64
     294: if_icmpne     309
     297: iload_1
     298: bipush        10
     300: aload_0
     301: getfield      #5                  // Field scanMetrics_:Lorg/apache/hadoop/hbase/protobuf/generated/MapReduceProtos$ScanMetrics;
     304: invokestatic  #92                 // Method com/google/protobuf/CodedOutputStream.computeMessageSize:(ILcom/google/protobuf/MessageLite;)I
     307: iadd
     308: istore_1
     309: aload_0
     310: getfield      #2                  // Field bitField0_:I
     313: sipush        128
     316: iand
     317: sipush        128
     320: if_icmpne     335
     323: iload_1
     324: bipush        11
     326: aload_0
     327: getfield      #4                  // Field mvccReadPoint_:J
     330: invokestatic  #89                 // Method com/google/protobuf/CodedOutputStream.computeUInt64Size:(IJ)I
     333: iadd
     334: istore_1
     335: aload_0
     336: getfield      #2                  // Field bitField0_:I
     339: sipush        256
     342: iand
     343: sipush        256
     346: if_icmpne     361
     349: iload_1
     350: bipush        12
     352: aload_0
     353: getfield      #3                  // Field cursor_:Lorg/apache/hadoop/hbase/protobuf/generated/ClientProtos$Cursor;
     356: invokestatic  #92                 // Method com/google/protobuf/CodedOutputStream.computeMessageSize:(ILcom/google/protobuf/MessageLite;)I
     359: iadd
     360: istore_1
     361: iload_1
     362: aload_0
     363: invokevirtual #85                 // Method getUnknownFields:()Lcom/google/protobuf/UnknownFieldSet;
     366: invokevirtual #94                 // Method com/google/protobuf/UnknownFieldSet.getSerializedSize:()I
     369: iadd
     370: istore_1
     371: aload_0
     372: iload_1
     373: putfield      #19                 // Field memoizedSerializedSize:I
     376: iload_1
     377: ireturn

  protected java.lang.Object writeReplace() throws java.io.ObjectStreamException;
    Code:
       0: aload_0
       1: invokespecial #95                 // Method com/google/protobuf/GeneratedMessage.writeReplace:()Ljava/lang/Object;
       4: areturn

  public boolean equals(java.lang.Object);
    Code:
       0: aload_1
       1: aload_0
       2: if_acmpne     7
       5: iconst_1
       6: ireturn
       7: aload_1
       8: instanceof    #64                 // class org/apache/hadoop/hbase/protobuf/generated/ClientProtos$ScanResponse
      11: ifne          20
      14: aload_0
      15: aload_1
      16: invokespecial #96                 // Method com/google/protobuf/GeneratedMessage.equals:(Ljava/lang/Object;)Z
      19: ireturn
      20: aload_1
      21: checkcast     #64                 // class org/apache/hadoop/hbase/protobuf/generated/ClientProtos$ScanResponse
      24: astore_2
      25: iconst_1
      26: istore_3
      27: iload_3
      28: ifeq          51
      31: aload_0
      32: invokevirtual #88                 // Method getCellsPerResultList:()Ljava/util/List;
      35: aload_2
      36: invokevirtual #88                 // Method getCellsPerResultList:()Ljava/util/List;
      39: invokeinterface #97,  2           // InterfaceMethod java/util/List.equals:(Ljava/lang/Object;)Z
      44: ifeq          51
      47: iconst_1
      48: goto          52
      51: iconst_0
      52: istore_3
      53: iload_3
      54: ifeq          72
      57: aload_0
      58: invokevirtual #98                 // Method hasScannerId:()Z
      61: aload_2
      62: invokevirtual #98                 // Method hasScannerId:()Z
      65: if_icmpne     72
      68: iconst_1
      69: goto          73
      72: iconst_0
      73: istore_3
      74: aload_0
      75: invokevirtual #98                 // Method hasScannerId:()Z
      78: ifeq          103
      81: iload_3
      82: ifeq          101
      85: aload_0
      86: invokevirtual #99                 // Method getScannerId:()J
      89: aload_2
      90: invokevirtual #99                 // Method getScannerId:()J
      93: lcmp
      94: ifne          101
      97: iconst_1
      98: goto          102
     101: iconst_0
     102: istore_3
     103: iload_3
     104: ifeq          122
     107: aload_0
     108: invokevirtual #100                // Method hasMoreResults:()Z
     111: aload_2
     112: invokevirtual #100                // Method hasMoreResults:()Z
     115: if_icmpne     122
     118: iconst_1
     119: goto          123
     122: iconst_0
     123: istore_3
     124: aload_0
     125: invokevirtual #100                // Method hasMoreResults:()Z
     128: ifeq          152
     131: iload_3
     132: ifeq          150
     135: aload_0
     136: invokevirtual #101                // Method getMoreResults:()Z
     139: aload_2
     140: invokevirtual #101                // Method getMoreResults:()Z
     143: if_icmpne     150
     146: iconst_1
     147: goto          151
     150: iconst_0
     151: istore_3
     152: iload_3
     153: ifeq          171
     156: aload_0
     157: invokevirtual #102                // Method hasTtl:()Z
     160: aload_2
     161: invokevirtual #102                // Method hasTtl:()Z
     164: if_icmpne     171
     167: iconst_1
     168: goto          172
     171: iconst_0
     172: istore_3
     173: aload_0
     174: invokevirtual #102                // Method hasTtl:()Z
     177: ifeq          201
     180: iload_3
     181: ifeq          199
     184: aload_0
     185: invokevirtual #103                // Method getTtl:()I
     188: aload_2
     189: invokevirtual #103                // Method getTtl:()I
     192: if_icmpne     199
     195: iconst_1
     196: goto          200
     199: iconst_0
     200: istore_3
     201: iload_3
     202: ifeq          225
     205: aload_0
     206: invokevirtual #104                // Method getResultsList:()Ljava/util/List;
     209: aload_2
     210: invokevirtual #104                // Method getResultsList:()Ljava/util/List;
     213: invokeinterface #97,  2           // InterfaceMethod java/util/List.equals:(Ljava/lang/Object;)Z
     218: ifeq          225
     221: iconst_1
     222: goto          226
     225: iconst_0
     226: istore_3
     227: iload_3
     228: ifeq          246
     231: aload_0
     232: invokevirtual #105                // Method hasStale:()Z
     235: aload_2
     236: invokevirtual #105                // Method hasStale:()Z
     239: if_icmpne     246
     242: iconst_1
     243: goto          247
     246: iconst_0
     247: istore_3
     248: aload_0
     249: invokevirtual #105                // Method hasStale:()Z
     252: ifeq          276
     255: iload_3
     256: ifeq          274
     259: aload_0
     260: invokevirtual #106                // Method getStale:()Z
     263: aload_2
     264: invokevirtual #106                // Method getStale:()Z
     267: if_icmpne     274
     270: iconst_1
     271: goto          275
     274: iconst_0
     275: istore_3
     276: iload_3
     277: ifeq          300
     280: aload_0
     281: invokevirtual #93                 // Method getPartialFlagPerResultList:()Ljava/util/List;
     284: aload_2
     285: invokevirtual #93                 // Method getPartialFlagPerResultList:()Ljava/util/List;
     288: invokeinterface #97,  2           // InterfaceMethod java/util/List.equals:(Ljava/lang/Object;)Z
     293: ifeq          300
     296: iconst_1
     297: goto          301
     300: iconst_0
     301: istore_3
     302: iload_3
     303: ifeq          321
     306: aload_0
     307: invokevirtual #107                // Method hasMoreResultsInRegion:()Z
     310: aload_2
     311: invokevirtual #107                // Method hasMoreResultsInRegion:()Z
     314: if_icmpne     321
     317: iconst_1
     318: goto          322
     321: iconst_0
     322: istore_3
     323: aload_0
     324: invokevirtual #107                // Method hasMoreResultsInRegion:()Z
     327: ifeq          351
     330: iload_3
     331: ifeq          349
     334: aload_0
     335: invokevirtual #108                // Method getMoreResultsInRegion:()Z
     338: aload_2
     339: invokevirtual #108                // Method getMoreResultsInRegion:()Z
     342: if_icmpne     349
     345: iconst_1
     346: goto          350
     349: iconst_0
     350: istore_3
     351: iload_3
     352: ifeq          370
     355: aload_0
     356: invokevirtual #109                // Method hasHeartbeatMessage:()Z
     359: aload_2
     360: invokevirtual #109                // Method hasHeartbeatMessage:()Z
     363: if_icmpne     370
     366: iconst_1
     367: goto          371
     370: iconst_0
     371: istore_3
     372: aload_0
     373: invokevirtual #109                // Method hasHeartbeatMessage:()Z
     376: ifeq          400
     379: iload_3
     380: ifeq          398
     383: aload_0
     384: invokevirtual #110                // Method getHeartbeatMessage:()Z
     387: aload_2
     388: invokevirtual #110                // Method getHeartbeatMessage:()Z
     391: if_icmpne     398
     394: iconst_1
     395: goto          399
     398: iconst_0
     399: istore_3
     400: iload_3
     401: ifeq          419
     404: aload_0
     405: invokevirtual #111                // Method hasScanMetrics:()Z
     408: aload_2
     409: invokevirtual #111                // Method hasScanMetrics:()Z
     412: if_icmpne     419
     415: iconst_1
     416: goto          420
     419: iconst_0
     420: istore_3
     421: aload_0
     422: invokevirtual #111                // Method hasScanMetrics:()Z
     425: ifeq          452
     428: iload_3
     429: ifeq          450
     432: aload_0
     433: invokevirtual #112                // Method getScanMetrics:()Lorg/apache/hadoop/hbase/protobuf/generated/MapReduceProtos$ScanMetrics;
     436: aload_2
     437: invokevirtual #112                // Method getScanMetrics:()Lorg/apache/hadoop/hbase/protobuf/generated/MapReduceProtos$ScanMetrics;
     440: invokevirtual #113                // Method org/apache/hadoop/hbase/protobuf/generated/MapReduceProtos$ScanMetrics.equals:(Ljava/lang/Object;)Z
     443: ifeq          450
     446: iconst_1
     447: goto          451
     450: iconst_0
     451: istore_3
     452: iload_3
     453: ifeq          471
     456: aload_0
     457: invokevirtual #114                // Method hasMvccReadPoint:()Z
     460: aload_2
     461: invokevirtual #114                // Method hasMvccReadPoint:()Z
     464: if_icmpne     471
     467: iconst_1
     468: goto          472
     471: iconst_0
     472: istore_3
     473: aload_0
     474: invokevirtual #114                // Method hasMvccReadPoint:()Z
     477: ifeq          502
     480: iload_3
     481: ifeq          500
     484: aload_0
     485: invokevirtual #115                // Method getMvccReadPoint:()J
     488: aload_2
     489: invokevirtual #115                // Method getMvccReadPoint:()J
     492: lcmp
     493: ifne          500
     496: iconst_1
     497: goto          501
     500: iconst_0
     501: istore_3
     502: iload_3
     503: ifeq          521
     506: aload_0
     507: invokevirtual #116                // Method hasCursor:()Z
     510: aload_2
     511: invokevirtual #116                // Method hasCursor:()Z
     514: if_icmpne     521
     517: iconst_1
     518: goto          522
     521: iconst_0
     522: istore_3
     523: aload_0
     524: invokevirtual #116                // Method hasCursor:()Z
     527: ifeq          554
     530: iload_3
     531: ifeq          552
     534: aload_0
     535: invokevirtual #117                // Method getCursor:()Lorg/apache/hadoop/hbase/protobuf/generated/ClientProtos$Cursor;
     538: aload_2
     539: invokevirtual #117                // Method getCursor:()Lorg/apache/hadoop/hbase/protobuf/generated/ClientProtos$Cursor;
     542: invokevirtual #118                // Method org/apache/hadoop/hbase/protobuf/generated/ClientProtos$Cursor.equals:(Ljava/lang/Object;)Z
     545: ifeq          552
     548: iconst_1
     549: goto          553
     552: iconst_0
     553: istore_3
     554: iload_3
     555: ifeq          576
     558: aload_0
     559: invokevirtual #85                 // Method getUnknownFields:()Lcom/google/protobuf/UnknownFieldSet;
     562: aload_2
     563: invokevirtual #85                 // Method getUnknownFields:()Lcom/google/protobuf/UnknownFieldSet;
     566: invokevirtual #119                // Method com/google/protobuf/UnknownFieldSet.equals:(Ljava/lang/Object;)Z
     569: ifeq          576
     572: iconst_1
     573: goto          577
     576: iconst_0
     577: istore_3
     578: iload_3
     579: ireturn

  public int hashCode();
    Code:
       0: aload_0
       1: getfield      #20                 // Field memoizedHashCode:I
       4: ifeq          12
       7: aload_0
       8: getfield      #20                 // Field memoizedHashCode:I
      11: ireturn
      12: bipush        41
      14: istore_1
      15: bipush        19
      17: iload_1
      18: imul
      19: aload_0
      20: invokevirtual #120                // Method getDescriptorForType:()Lcom/google/protobuf/Descriptors$Descriptor;
      23: invokevirtual #121                // Method java/lang/Object.hashCode:()I
      26: iadd
      27: istore_1
      28: aload_0
      29: invokevirtual #122                // Method getCellsPerResultCount:()I
      32: ifle          57
      35: bipush        37
      37: iload_1
      38: imul
      39: iconst_1
      40: iadd
      41: istore_1
      42: bipush        53
      44: iload_1
      45: imul
      46: aload_0
      47: invokevirtual #88                 // Method getCellsPerResultList:()Ljava/util/List;
      50: invokeinterface #123,  1          // InterfaceMethod java/util/List.hashCode:()I
      55: iadd
      56: istore_1
      57: aload_0
      58: invokevirtual #98                 // Method hasScannerId:()Z
      61: ifeq          84
      64: bipush        37
      66: iload_1
      67: imul
      68: iconst_2
      69: iadd
      70: istore_1
      71: bipush        53
      73: iload_1
      74: imul
      75: aload_0
      76: invokevirtual #99                 // Method getScannerId:()J
      79: invokestatic  #124                // Method hashLong:(J)I
      82: iadd
      83: istore_1
      84: aload_0
      85: invokevirtual #100                // Method hasMoreResults:()Z
      88: ifeq          111
      91: bipush        37
      93: iload_1
      94: imul
      95: iconst_3
      96: iadd
      97: istore_1
      98: bipush        53
     100: iload_1
     101: imul
     102: aload_0
     103: invokevirtual #101                // Method getMoreResults:()Z
     106: invokestatic  #125                // Method hashBoolean:(Z)I
     109: iadd
     110: istore_1
     111: aload_0
     112: invokevirtual #102                // Method hasTtl:()Z
     115: ifeq          135
     118: bipush        37
     120: iload_1
     121: imul
     122: iconst_4
     123: iadd
     124: istore_1
     125: bipush        53
     127: iload_1
     128: imul
     129: aload_0
     130: invokevirtual #103                // Method getTtl:()I
     133: iadd
     134: istore_1
     135: aload_0
     136: invokevirtual #126                // Method getResultsCount:()I
     139: ifle          164
     142: bipush        37
     144: iload_1
     145: imul
     146: iconst_5
     147: iadd
     148: istore_1
     149: bipush        53
     151: iload_1
     152: imul
     153: aload_0
     154: invokevirtual #104                // Method getResultsList:()Ljava/util/List;
     157: invokeinterface #123,  1          // InterfaceMethod java/util/List.hashCode:()I
     162: iadd
     163: istore_1
     164: aload_0
     165: invokevirtual #105                // Method hasStale:()Z
     168: ifeq          192
     171: bipush        37
     173: iload_1
     174: imul
     175: bipush        6
     177: iadd
     178: istore_1
     179: bipush        53
     181: iload_1
     182: imul
     183: aload_0
     184: invokevirtual #106                // Method getStale:()Z
     187: invokestatic  #125                // Method hashBoolean:(Z)I
     190: iadd
     191: istore_1
     192: aload_0
     193: invokevirtual #127                // Method getPartialFlagPerResultCount:()I
     196: ifle          222
     199: bipush        37
     201: iload_1
     202: imul
     203: bipush        7
     205: iadd
     206: istore_1
     207: bipush        53
     209: iload_1
     210: imul
     211: aload_0
     212: invokevirtual #93                 // Method getPartialFlagPerResultList:()Ljava/util/List;
     215: invokeinterface #123,  1          // InterfaceMethod java/util/List.hashCode:()I
     220: iadd
     221: istore_1
     222: aload_0
     223: invokevirtual #107                // Method hasMoreResultsInRegion:()Z
     226: ifeq          250
     229: bipush        37
     231: iload_1
     232: imul
     233: bipush        8
     235: iadd
     236: istore_1
     237: bipush        53
     239: iload_1
     240: imul
     241: aload_0
     242: invokevirtual #108                // Method getMoreResultsInRegion:()Z
     245: invokestatic  #125                // Method hashBoolean:(Z)I
     248: iadd
     249: istore_1
     250: aload_0
     251: invokevirtual #109                // Method hasHeartbeatMessage:()Z
     254: ifeq          278
     257: bipush        37
     259: iload_1
     260: imul
     261: bipush        9
     263: iadd
     264: istore_1
     265: bipush        53
     267: iload_1
     268: imul
     269: aload_0
     270: invokevirtual #110                // Method getHeartbeatMessage:()Z
     273: invokestatic  #125                // Method hashBoolean:(Z)I
     276: iadd
     277: istore_1
     278: aload_0
     279: invokevirtual #111                // Method hasScanMetrics:()Z
     282: ifeq          306
     285: bipush        37
     287: iload_1
     288: imul
     289: bipush        10
     291: iadd
     292: istore_1
     293: bipush        53
     295: iload_1
     296: imul
     297: aload_0
     298: invokevirtual #112                // Method getScanMetrics:()Lorg/apache/hadoop/hbase/protobuf/generated/MapReduceProtos$ScanMetrics;
     301: invokevirtual #128                // Method org/apache/hadoop/hbase/protobuf/generated/MapReduceProtos$ScanMetrics.hashCode:()I
     304: iadd
     305: istore_1
     306: aload_0
     307: invokevirtual #114                // Method hasMvccReadPoint:()Z
     310: ifeq          334
     313: bipush        37
     315: iload_1
     316: imul
     317: bipush        11
     319: iadd
     320: istore_1
     321: bipush        53
     323: iload_1
     324: imul
     325: aload_0
     326: invokevirtual #115                // Method getMvccReadPoint:()J
     329: invokestatic  #124                // Method hashLong:(J)I
     332: iadd
     333: istore_1
     334: aload_0
     335: invokevirtual #116                // Method hasCursor:()Z
     338: ifeq          362
     341: bipush        37
     343: iload_1
     344: imul
     345: bipush        12
     347: iadd
     348: istore_1
     349: bipush        53
     351: iload_1
     352: imul
     353: aload_0
     354: invokevirtual #117                // Method getCursor:()Lorg/apache/hadoop/hbase/protobuf/generated/ClientProtos$Cursor;
     357: invokevirtual #129                // Method org/apache/hadoop/hbase/protobuf/generated/ClientProtos$Cursor.hashCode:()I
     360: iadd
     361: istore_1
     362: bipush        29
     364: iload_1
     365: imul
     366: aload_0
     367: invokevirtual #85                 // Method getUnknownFields:()Lcom/google/protobuf/UnknownFieldSet;
     370: invokevirtual #130                // Method com/google/protobuf/UnknownFieldSet.hashCode:()I
     373: iadd
     374: istore_1
     375: aload_0
     376: iload_1
     377: putfield      #20                 // Field memoizedHashCode:I
     380: iload_1
     381: ireturn

  public static org.apache.hadoop.hbase.protobuf.generated.ClientProtos$ScanResponse parseFrom(com.google.protobuf.ByteString) throws com.google.protobuf.InvalidProtocolBufferException;
    Code:
       0: getstatic     #67                 // Field PARSER:Lcom/google/protobuf/Parser;
       3: aload_0
       4: invokeinterface #131,  2          // InterfaceMethod com/google/protobuf/Parser.parseFrom:(Lcom/google/protobuf/ByteString;)Ljava/lang/Object;
       9: checkcast     #64                 // class org/apache/hadoop/hbase/protobuf/generated/ClientProtos$ScanResponse
      12: areturn

  public static org.apache.hadoop.hbase.protobuf.generated.ClientProtos$ScanResponse parseFrom(com.google.protobuf.ByteString, com.google.protobuf.ExtensionRegistryLite) throws com.google.protobuf.InvalidProtocolBufferException;
    Code:
       0: getstatic     #67                 // Field PARSER:Lcom/google/protobuf/Parser;
       3: aload_0
       4: aload_1
       5: invokeinterface #132,  3          // InterfaceMethod com/google/protobuf/Parser.parseFrom:(Lcom/google/protobuf/ByteString;Lcom/google/protobuf/ExtensionRegistryLite;)Ljava/lang/Object;
      10: checkcast     #64                 // class org/apache/hadoop/hbase/protobuf/generated/ClientProtos$ScanResponse
      13: areturn

  public static org.apache.hadoop.hbase.protobuf.generated.ClientProtos$ScanResponse parseFrom(byte[]) throws com.google.protobuf.InvalidProtocolBufferException;
    Code:
       0: getstatic     #67                 // Field PARSER:Lcom/google/protobuf/Parser;
       3: aload_0
       4: invokeinterface #133,  2          // InterfaceMethod com/google/protobuf/Parser.parseFrom:([B)Ljava/lang/Object;
       9: checkcast     #64                 // class org/apache/hadoop/hbase/protobuf/generated/ClientProtos$ScanResponse
      12: areturn

  public static org.apache.hadoop.hbase.protobuf.generated.ClientProtos$ScanResponse parseFrom(byte[], com.google.protobuf.ExtensionRegistryLite) throws com.google.protobuf.InvalidProtocolBufferException;
    Code:
       0: getstatic     #67                 // Field PARSER:Lcom/google/protobuf/Parser;
       3: aload_0
       4: aload_1
       5: invokeinterface #134,  3          // InterfaceMethod com/google/protobuf/Parser.parseFrom:([BLcom/google/protobuf/ExtensionRegistryLite;)Ljava/lang/Object;
      10: checkcast     #64                 // class org/apache/hadoop/hbase/protobuf/generated/ClientProtos$ScanResponse
      13: areturn

  public static org.apache.hadoop.hbase.protobuf.generated.ClientProtos$ScanResponse parseFrom(java.io.InputStream) throws java.io.IOException;
    Code:
       0: getstatic     #67                 // Field PARSER:Lcom/google/protobuf/Parser;
       3: aload_0
       4: invokeinterface #135,  2          // InterfaceMethod com/google/protobuf/Parser.parseFrom:(Ljava/io/InputStream;)Ljava/lang/Object;
       9: checkcast     #64                 // class org/apache/hadoop/hbase/protobuf/generated/ClientProtos$ScanResponse
      12: areturn

  public static org.apache.hadoop.hbase.protobuf.generated.ClientProtos$ScanResponse parseFrom(java.io.InputStream, com.google.protobuf.ExtensionRegistryLite) throws java.io.IOException;
    Code:
       0: getstatic     #67                 // Field PARSER:Lcom/google/protobuf/Parser;
       3: aload_0
       4: aload_1
       5: invokeinterface #136,  3          // InterfaceMethod com/google/protobuf/Parser.parseFrom:(Ljava/io/InputStream;Lcom/google/protobuf/ExtensionRegistryLite;)Ljava/lang/Object;
      10: checkcast     #64                 // class org/apache/hadoop/hbase/protobuf/generated/ClientProtos$ScanResponse
      13: areturn

  public static org.apache.hadoop.hbase.protobuf.generated.ClientProtos$ScanResponse parseDelimitedFrom(java.io.InputStream) throws java.io.IOException;
    Code:
       0: getstatic     #67                 // Field PARSER:Lcom/google/protobuf/Parser;
       3: aload_0
       4: invokeinterface #137,  2          // InterfaceMethod com/google/protobuf/Parser.parseDelimitedFrom:(Ljava/io/InputStream;)Ljava/lang/Object;
       9: checkcast     #64                 // class org/apache/hadoop/hbase/protobuf/generated/ClientProtos$ScanResponse
      12: areturn

  public static org.apache.hadoop.hbase.protobuf.generated.ClientProtos$ScanResponse parseDelimitedFrom(java.io.InputStream, com.google.protobuf.ExtensionRegistryLite) throws java.io.IOException;
    Code:
       0: getstatic     #67                 // Field PARSER:Lcom/google/protobuf/Parser;
       3: aload_0
       4: aload_1
       5: invokeinterface #138,  3          // InterfaceMethod com/google/protobuf/Parser.parseDelimitedFrom:(Ljava/io/InputStream;Lcom/google/protobuf/ExtensionRegistryLite;)Ljava/lang/Object;
      10: checkcast     #64                 // class org/apache/hadoop/hbase/protobuf/generated/ClientProtos$ScanResponse
      13: areturn

  public static org.apache.hadoop.hbase.protobuf.generated.ClientProtos$ScanResponse parseFrom(com.google.protobuf.CodedInputStream) throws java.io.IOException;
    Code:
       0: getstatic     #67                 // Field PARSER:Lcom/google/protobuf/Parser;
       3: aload_0
       4: invokeinterface #139,  2          // InterfaceMethod com/google/protobuf/Parser.parseFrom:(Lcom/google/protobuf/CodedInputStream;)Ljava/lang/Object;
       9: checkcast     #64                 // class org/apache/hadoop/hbase/protobuf/generated/ClientProtos$ScanResponse
      12: areturn

  public static org.apache.hadoop.hbase.protobuf.generated.ClientProtos$ScanResponse parseFrom(com.google.protobuf.CodedInputStream, com.google.protobuf.ExtensionRegistryLite) throws java.io.IOException;
    Code:
       0: getstatic     #67                 // Field PARSER:Lcom/google/protobuf/Parser;
       3: aload_0
       4: aload_1
       5: invokeinterface #140,  3          // InterfaceMethod com/google/protobuf/Parser.parseFrom:(Lcom/google/protobuf/CodedInputStream;Lcom/google/protobuf/ExtensionRegistryLite;)Ljava/lang/Object;
      10: checkcast     #64                 // class org/apache/hadoop/hbase/protobuf/generated/ClientProtos$ScanResponse
      13: areturn

  public static org.apache.hadoop.hbase.protobuf.generated.ClientProtos$ScanResponse$Builder newBuilder();
    Code:
       0: invokestatic  #141                // Method org/apache/hadoop/hbase/protobuf/generated/ClientProtos$ScanResponse$Builder.access$23000:()Lorg/apache/hadoop/hbase/protobuf/generated/ClientProtos$ScanResponse$Builder;
       3: areturn

  public org.apache.hadoop.hbase.protobuf.generated.ClientProtos$ScanResponse$Builder newBuilderForType();
    Code:
       0: invokestatic  #142                // Method newBuilder:()Lorg/apache/hadoop/hbase/protobuf/generated/ClientProtos$ScanResponse$Builder;
       3: areturn

  public static org.apache.hadoop.hbase.protobuf.generated.ClientProtos$ScanResponse$Builder newBuilder(org.apache.hadoop.hbase.protobuf.generated.ClientProtos$ScanResponse);
    Code:
       0: invokestatic  #142                // Method newBuilder:()Lorg/apache/hadoop/hbase/protobuf/generated/ClientProtos$ScanResponse$Builder;
       3: aload_0
       4: invokevirtual #143                // Method org/apache/hadoop/hbase/protobuf/generated/ClientProtos$ScanResponse$Builder.mergeFrom:(Lorg/apache/hadoop/hbase/protobuf/generated/ClientProtos$ScanResponse;)Lorg/apache/hadoop/hbase/protobuf/generated/ClientProtos$ScanResponse$Builder;
       7: areturn

  public org.apache.hadoop.hbase.protobuf.generated.ClientProtos$ScanResponse$Builder toBuilder();
    Code:
       0: aload_0
       1: invokestatic  #144                // Method newBuilder:(Lorg/apache/hadoop/hbase/protobuf/generated/ClientProtos$ScanResponse;)Lorg/apache/hadoop/hbase/protobuf/generated/ClientProtos$ScanResponse$Builder;
       4: areturn

  protected org.apache.hadoop.hbase.protobuf.generated.ClientProtos$ScanResponse$Builder newBuilderForType(com.google.protobuf.GeneratedMessage$BuilderParent);
    Code:
       0: new           #65                 // class org/apache/hadoop/hbase/protobuf/generated/ClientProtos$ScanResponse$Builder
       3: dup
       4: aload_1
       5: aconst_null
       6: invokespecial #145                // Method org/apache/hadoop/hbase/protobuf/generated/ClientProtos$ScanResponse$Builder."<init>":(Lcom/google/protobuf/GeneratedMessage$BuilderParent;Lorg/apache/hadoop/hbase/protobuf/generated/ClientProtos$1;)V
       9: astore_2
      10: aload_2
      11: areturn

  protected com.google.protobuf.Message$Builder newBuilderForType(com.google.protobuf.GeneratedMessage$BuilderParent);
    Code:
       0: aload_0
       1: aload_1
       2: invokevirtual #146                // Method newBuilderForType:(Lcom/google/protobuf/GeneratedMessage$BuilderParent;)Lorg/apache/hadoop/hbase/protobuf/generated/ClientProtos$ScanResponse$Builder;
       5: areturn

  public com.google.protobuf.Message$Builder toBuilder();
    Code:
       0: aload_0
       1: invokevirtual #147                // Method toBuilder:()Lorg/apache/hadoop/hbase/protobuf/generated/ClientProtos$ScanResponse$Builder;
       4: areturn

  public com.google.protobuf.Message$Builder newBuilderForType();
    Code:
       0: aload_0
       1: invokevirtual #148                // Method newBuilderForType:()Lorg/apache/hadoop/hbase/protobuf/generated/ClientProtos$ScanResponse$Builder;
       4: areturn

  public com.google.protobuf.MessageLite$Builder toBuilder();
    Code:
       0: aload_0
       1: invokevirtual #147                // Method toBuilder:()Lorg/apache/hadoop/hbase/protobuf/generated/ClientProtos$ScanResponse$Builder;
       4: areturn

  public com.google.protobuf.MessageLite$Builder newBuilderForType();
    Code:
       0: aload_0
       1: invokevirtual #148                // Method newBuilderForType:()Lorg/apache/hadoop/hbase/protobuf/generated/ClientProtos$ScanResponse$Builder;
       4: areturn

  public com.google.protobuf.MessageLite getDefaultInstanceForType();
    Code:
       0: aload_0
       1: invokevirtual #149                // Method getDefaultInstanceForType:()Lorg/apache/hadoop/hbase/protobuf/generated/ClientProtos$ScanResponse;
       4: areturn

  public com.google.protobuf.Message getDefaultInstanceForType();
    Code:
       0: aload_0
       1: invokevirtual #149                // Method getDefaultInstanceForType:()Lorg/apache/hadoop/hbase/protobuf/generated/ClientProtos$ScanResponse;
       4: areturn

  org.apache.hadoop.hbase.protobuf.generated.ClientProtos$ScanResponse(com.google.protobuf.CodedInputStream, com.google.protobuf.ExtensionRegistryLite, org.apache.hadoop.hbase.protobuf.generated.ClientProtos$1) throws com.google.protobuf.InvalidProtocolBufferException;
    Code:
       0: aload_0
       1: aload_1
       2: aload_2
       3: invokespecial #16                 // Method "<init>":(Lcom/google/protobuf/CodedInputStream;Lcom/google/protobuf/ExtensionRegistryLite;)V
       6: return

  static boolean access$23200();
    Code:
       0: getstatic     #1                  // Field alwaysUseFieldBuilders:Z
       3: ireturn

  org.apache.hadoop.hbase.protobuf.generated.ClientProtos$ScanResponse(com.google.protobuf.GeneratedMessage$Builder, org.apache.hadoop.hbase.protobuf.generated.ClientProtos$1);
    Code:
       0: aload_0
       1: aload_1
       2: invokespecial #15                 // Method "<init>":(Lcom/google/protobuf/GeneratedMessage$Builder;)V
       5: return

  static java.util.List access$23402(org.apache.hadoop.hbase.protobuf.generated.ClientProtos$ScanResponse, java.util.List);
    Code:
       0: aload_0
       1: aload_1
       2: dup_x1
       3: putfield      #14                 // Field cellsPerResult_:Ljava/util/List;
       6: areturn

  static long access$23502(org.apache.hadoop.hbase.protobuf.generated.ClientProtos$ScanResponse, long);
    Code:
       0: aload_0
       1: lload_1
       2: dup2_x1
       3: putfield      #13                 // Field scannerId_:J
       6: lreturn

  static boolean access$23602(org.apache.hadoop.hbase.protobuf.generated.ClientProtos$ScanResponse, boolean);
    Code:
       0: aload_0
       1: iload_1
       2: dup_x1
       3: putfield      #12                 // Field moreResults_:Z
       6: ireturn

  static int access$23702(org.apache.hadoop.hbase.protobuf.generated.ClientProtos$ScanResponse, int);
    Code:
       0: aload_0
       1: iload_1
       2: dup_x1
       3: putfield      #11                 // Field ttl_:I
       6: ireturn

  static java.util.List access$23802(org.apache.hadoop.hbase.protobuf.generated.ClientProtos$ScanResponse, java.util.List);
    Code:
       0: aload_0
       1: aload_1
       2: dup_x1
       3: putfield      #10                 // Field results_:Ljava/util/List;
       6: areturn

  static boolean access$23902(org.apache.hadoop.hbase.protobuf.generated.ClientProtos$ScanResponse, boolean);
    Code:
       0: aload_0
       1: iload_1
       2: dup_x1
       3: putfield      #9                  // Field stale_:Z
       6: ireturn

  static java.util.List access$24002(org.apache.hadoop.hbase.protobuf.generated.ClientProtos$ScanResponse, java.util.List);
    Code:
       0: aload_0
       1: aload_1
       2: dup_x1
       3: putfield      #8                  // Field partialFlagPerResult_:Ljava/util/List;
       6: areturn

  static boolean access$24102(org.apache.hadoop.hbase.protobuf.generated.ClientProtos$ScanResponse, boolean);
    Code:
       0: aload_0
       1: iload_1
       2: dup_x1
       3: putfield      #7                  // Field moreResultsInRegion_:Z
       6: ireturn

  static boolean access$24202(org.apache.hadoop.hbase.protobuf.generated.ClientProtos$ScanResponse, boolean);
    Code:
       0: aload_0
       1: iload_1
       2: dup_x1
       3: putfield      #6                  // Field heartbeatMessage_:Z
       6: ireturn

  static org.apache.hadoop.hbase.protobuf.generated.MapReduceProtos$ScanMetrics access$24302(org.apache.hadoop.hbase.protobuf.generated.ClientProtos$ScanResponse, org.apache.hadoop.hbase.protobuf.generated.MapReduceProtos$ScanMetrics);
    Code:
       0: aload_0
       1: aload_1
       2: dup_x1
       3: putfield      #5                  // Field scanMetrics_:Lorg/apache/hadoop/hbase/protobuf/generated/MapReduceProtos$ScanMetrics;
       6: areturn

  static long access$24402(org.apache.hadoop.hbase.protobuf.generated.ClientProtos$ScanResponse, long);
    Code:
       0: aload_0
       1: lload_1
       2: dup2_x1
       3: putfield      #4                  // Field mvccReadPoint_:J
       6: lreturn

  static org.apache.hadoop.hbase.protobuf.generated.ClientProtos$Cursor access$24502(org.apache.hadoop.hbase.protobuf.generated.ClientProtos$ScanResponse, org.apache.hadoop.hbase.protobuf.generated.ClientProtos$Cursor);
    Code:
       0: aload_0
       1: aload_1
       2: dup_x1
       3: putfield      #3                  // Field cursor_:Lorg/apache/hadoop/hbase/protobuf/generated/ClientProtos$Cursor;
       6: areturn

  static int access$24602(org.apache.hadoop.hbase.protobuf.generated.ClientProtos$ScanResponse, int);
    Code:
       0: aload_0
       1: iload_1
       2: dup_x1
       3: putfield      #2                  // Field bitField0_:I
       6: ireturn

  static java.util.List access$23400(org.apache.hadoop.hbase.protobuf.generated.ClientProtos$ScanResponse);
    Code:
       0: aload_0
       1: getfield      #14                 // Field cellsPerResult_:Ljava/util/List;
       4: areturn

  static java.util.List access$23800(org.apache.hadoop.hbase.protobuf.generated.ClientProtos$ScanResponse);
    Code:
       0: aload_0
       1: getfield      #10                 // Field results_:Ljava/util/List;
       4: areturn

  static boolean access$24700();
    Code:
       0: getstatic     #1                  // Field alwaysUseFieldBuilders:Z
       3: ireturn

  static java.util.List access$24000(org.apache.hadoop.hbase.protobuf.generated.ClientProtos$ScanResponse);
    Code:
       0: aload_0
       1: getfield      #8                  // Field partialFlagPerResult_:Ljava/util/List;
       4: areturn

  static {};
    Code:
       0: new           #150                // class org/apache/hadoop/hbase/protobuf/generated/ClientProtos$ScanResponse$1
       3: dup
       4: invokespecial #151                // Method org/apache/hadoop/hbase/protobuf/generated/ClientProtos$ScanResponse$1."<init>":()V
       7: putstatic     #67                 // Field PARSER:Lcom/google/protobuf/Parser;
      10: new           #64                 // class org/apache/hadoop/hbase/protobuf/generated/ClientProtos$ScanResponse
      13: dup
      14: iconst_1
      15: invokespecial #152                // Method "<init>":(Z)V
      18: putstatic     #25                 // Field defaultInstance:Lorg/apache/hadoop/hbase/protobuf/generated/ClientProtos$ScanResponse;
      21: getstatic     #25                 // Field defaultInstance:Lorg/apache/hadoop/hbase/protobuf/generated/ClientProtos$ScanResponse;
      24: invokespecial #26                 // Method initFields:()V
      27: return
}
