Compiled from "CloneSnapshotFromClientAfterSplittingRegionTestBase.java"
public class org.apache.hadoop.hbase.client.CloneSnapshotFromClientAfterSplittingRegionTestBase extends org.apache.hadoop.hbase.client.CloneSnapshotFromClientTestBase {
  public org.apache.hadoop.hbase.client.CloneSnapshotFromClientAfterSplittingRegionTestBase();
    Code:
       0: aload_0
       1: invokespecial #1                  // Method org/apache/hadoop/hbase/client/CloneSnapshotFromClientTestBase."<init>":()V
       4: return

  public void testCloneSnapshotAfterSplittingRegion() throws java.io.IOException, java.lang.InterruptedException;
    Code:
       0: aload_0
       1: getfield      #5                  // Field admin:Lorg/apache/hadoop/hbase/client/Admin;
       4: iconst_0
       5: invokeinterface #8,  2            // InterfaceMethod org/apache/hadoop/hbase/client/Admin.catalogJanitorSwitch:(Z)Z
      10: pop
      11: aload_0
      12: getfield      #5                  // Field admin:Lorg/apache/hadoop/hbase/client/Admin;
      15: aload_0
      16: getfield      #9                  // Field tableName:Lorg/apache/hadoop/hbase/TableName;
      19: invokeinterface #10,  2           // InterfaceMethod org/apache/hadoop/hbase/client/Admin.getRegions:(Lorg/apache/hadoop/hbase/TableName;)Ljava/util/List;
      24: astore_1
      25: aload_1
      26: invokestatic  #11                 // Method org/apache/hadoop/hbase/client/RegionReplicaUtil.removeNonDefaultRegions:(Ljava/util/Collection;)V
      29: aload_0
      30: aload_1
      31: iconst_0
      32: invokeinterface #12,  2           // InterfaceMethod java/util/List.get:(I)Ljava/lang/Object;
      37: checkcast     #13                 // class org/apache/hadoop/hbase/client/RegionInfo
      40: invokespecial #14                 // Method splitRegion:(Lorg/apache/hadoop/hbase/client/RegionInfo;)V
      43: aload_0
      44: getfield      #5                  // Field admin:Lorg/apache/hadoop/hbase/client/Admin;
      47: aload_0
      48: getfield      #15                 // Field snapshotName2:Ljava/lang/String;
      51: aload_0
      52: getfield      #9                  // Field tableName:Lorg/apache/hadoop/hbase/TableName;
      55: invokeinterface #16,  3           // InterfaceMethod org/apache/hadoop/hbase/client/Admin.snapshot:(Ljava/lang/String;Lorg/apache/hadoop/hbase/TableName;)V
      60: new           #17                 // class java/lang/StringBuilder
      63: dup
      64: invokespecial #18                 // Method java/lang/StringBuilder."<init>":()V
      67: aload_0
      68: invokevirtual #19                 // Method getValidMethodName:()Ljava/lang/String;
      71: invokevirtual #20                 // Method java/lang/StringBuilder.append:(Ljava/lang/String;)Ljava/lang/StringBuilder;
      74: ldc           #21                 // String -
      76: invokevirtual #20                 // Method java/lang/StringBuilder.append:(Ljava/lang/String;)Ljava/lang/StringBuilder;
      79: invokestatic  #22                 // Method java/lang/System.currentTimeMillis:()J
      82: invokevirtual #23                 // Method java/lang/StringBuilder.append:(J)Ljava/lang/StringBuilder;
      85: invokevirtual #24                 // Method java/lang/StringBuilder.toString:()Ljava/lang/String;
      88: invokestatic  #25                 // Method org/apache/hadoop/hbase/TableName.valueOf:(Ljava/lang/String;)Lorg/apache/hadoop/hbase/TableName;
      91: astore_2
      92: aload_0
      93: getfield      #5                  // Field admin:Lorg/apache/hadoop/hbase/client/Admin;
      96: aload_0
      97: getfield      #15                 // Field snapshotName2:Ljava/lang/String;
     100: aload_2
     101: invokeinterface #26,  3           // InterfaceMethod org/apache/hadoop/hbase/client/Admin.cloneSnapshot:(Ljava/lang/String;Lorg/apache/hadoop/hbase/TableName;)V
     106: getstatic     #27                 // Field TEST_UTIL:Lorg/apache/hadoop/hbase/HBaseTestingUtility;
     109: aload_2
     110: invokestatic  #28                 // Method org/apache/hadoop/hbase/snapshot/SnapshotTestingUtils.waitForTableToBeOnline:(Lorg/apache/hadoop/hbase/HBaseTestingUtility;Lorg/apache/hadoop/hbase/TableName;)V
     113: aload_0
     114: getstatic     #27                 // Field TEST_UTIL:Lorg/apache/hadoop/hbase/HBaseTestingUtility;
     117: aload_2
     118: aload_0
     119: getfield      #29                 // Field snapshot1Rows:I
     122: i2l
     123: invokevirtual #30                 // Method verifyRowCount:(Lorg/apache/hadoop/hbase/HBaseTestingUtility;Lorg/apache/hadoop/hbase/TableName;J)V
     126: getstatic     #27                 // Field TEST_UTIL:Lorg/apache/hadoop/hbase/HBaseTestingUtility;
     129: invokevirtual #31                 // Method org/apache/hadoop/hbase/HBaseTestingUtility.getHBaseCluster:()Lorg/apache/hadoop/hbase/MiniHBaseCluster;
     132: invokevirtual #32                 // Method org/apache/hadoop/hbase/MiniHBaseCluster.getMaster:()Lorg/apache/hadoop/hbase/master/HMaster;
     135: invokevirtual #33                 // Method org/apache/hadoop/hbase/master/HMaster.getAssignmentManager:()Lorg/apache/hadoop/hbase/master/assignment/AssignmentManager;
     138: invokevirtual #34                 // Method org/apache/hadoop/hbase/master/assignment/AssignmentManager.getRegionStates:()Lorg/apache/hadoop/hbase/master/assignment/RegionStates;
     141: astore_3
     142: aload_3
     143: aload_0
     144: getfield      #9                  // Field tableName:Lorg/apache/hadoop/hbase/TableName;
     147: invokevirtual #35                 // Method org/apache/hadoop/hbase/master/assignment/RegionStates.getRegionByStateOfTable:(Lorg/apache/hadoop/hbase/TableName;)Ljava/util/Map;
     150: getstatic     #36                 // Field org/apache/hadoop/hbase/master/RegionState$State.OPEN:Lorg/apache/hadoop/hbase/master/RegionState$State;
     153: invokeinterface #37,  2           // InterfaceMethod java/util/Map.get:(Ljava/lang/Object;)Ljava/lang/Object;
     158: checkcast     #38                 // class java/util/List
     161: invokeinterface #39,  1           // InterfaceMethod java/util/List.size:()I
     166: istore        4
     168: aload_3
     169: aload_2
     170: invokevirtual #35                 // Method org/apache/hadoop/hbase/master/assignment/RegionStates.getRegionByStateOfTable:(Lorg/apache/hadoop/hbase/TableName;)Ljava/util/Map;
     173: getstatic     #36                 // Field org/apache/hadoop/hbase/master/RegionState$State.OPEN:Lorg/apache/hadoop/hbase/master/RegionState$State;
     176: invokeinterface #37,  2           // InterfaceMethod java/util/Map.get:(Ljava/lang/Object;)Ljava/lang/Object;
     181: checkcast     #38                 // class java/util/List
     184: invokeinterface #39,  1           // InterfaceMethod java/util/List.size:()I
     189: istore        5
     191: iload         4
     193: i2l
     194: iload         5
     196: i2l
     197: invokestatic  #40                 // Method org/junit/Assert.assertEquals:(JJ)V
     200: aload_3
     201: aload_0
     202: getfield      #9                  // Field tableName:Lorg/apache/hadoop/hbase/TableName;
     205: invokevirtual #35                 // Method org/apache/hadoop/hbase/master/assignment/RegionStates.getRegionByStateOfTable:(Lorg/apache/hadoop/hbase/TableName;)Ljava/util/Map;
     208: getstatic     #41                 // Field org/apache/hadoop/hbase/master/RegionState$State.SPLIT:Lorg/apache/hadoop/hbase/master/RegionState$State;
     211: invokeinterface #37,  2           // InterfaceMethod java/util/Map.get:(Ljava/lang/Object;)Ljava/lang/Object;
     216: checkcast     #38                 // class java/util/List
     219: invokeinterface #39,  1           // InterfaceMethod java/util/List.size:()I
     224: istore        6
     226: aload_3
     227: aload_2
     228: invokevirtual #35                 // Method org/apache/hadoop/hbase/master/assignment/RegionStates.getRegionByStateOfTable:(Lorg/apache/hadoop/hbase/TableName;)Ljava/util/Map;
     231: getstatic     #41                 // Field org/apache/hadoop/hbase/master/RegionState$State.SPLIT:Lorg/apache/hadoop/hbase/master/RegionState$State;
     234: invokeinterface #37,  2           // InterfaceMethod java/util/Map.get:(Ljava/lang/Object;)Ljava/lang/Object;
     239: checkcast     #38                 // class java/util/List
     242: invokeinterface #39,  1           // InterfaceMethod java/util/List.size:()I
     247: istore        7
     249: iload         6
     251: i2l
     252: iload         7
     254: i2l
     255: invokestatic  #40                 // Method org/junit/Assert.assertEquals:(JJ)V
     258: getstatic     #27                 // Field TEST_UTIL:Lorg/apache/hadoop/hbase/HBaseTestingUtility;
     261: aload_2
     262: invokevirtual #42                 // Method org/apache/hadoop/hbase/HBaseTestingUtility.deleteTable:(Lorg/apache/hadoop/hbase/TableName;)V
     265: aload_0
     266: getfield      #5                  // Field admin:Lorg/apache/hadoop/hbase/client/Admin;
     269: iconst_1
     270: invokeinterface #8,  2            // InterfaceMethod org/apache/hadoop/hbase/client/Admin.catalogJanitorSwitch:(Z)Z
     275: pop
     276: goto          295
     279: astore        8
     281: aload_0
     282: getfield      #5                  // Field admin:Lorg/apache/hadoop/hbase/client/Admin;
     285: iconst_1
     286: invokeinterface #8,  2            // InterfaceMethod org/apache/hadoop/hbase/client/Admin.catalogJanitorSwitch:(Z)Z
     291: pop
     292: aload         8
     294: athrow
     295: return
    Exception table:
       from    to  target type
          11   265   279   any
         279   281   279   any
}
