Compiled from "ClusterStatus.java"
public class org.apache.hadoop.hbase.ClusterStatus implements org.apache.hadoop.hbase.ClusterMetrics {
  public org.apache.hadoop.hbase.ClusterStatus(java.lang.String, java.lang.String, java.util.Map<org.apache.hadoop.hbase.ServerName, org.apache.hadoop.hbase.ServerLoad>, java.util.Collection<org.apache.hadoop.hbase.ServerName>, org.apache.hadoop.hbase.ServerName, java.util.Collection<org.apache.hadoop.hbase.ServerName>, java.util.List<org.apache.hadoop.hbase.master.RegionState>, java.lang.String[], java.lang.Boolean, int);
    Code:
       0: aload_0
       1: invokestatic  #1                  // Method org/apache/hadoop/hbase/ClusterMetricsBuilder.newBuilder:()Lorg/apache/hadoop/hbase/ClusterMetricsBuilder;
       4: aload_1
       5: invokevirtual #2                  // Method org/apache/hadoop/hbase/ClusterMetricsBuilder.setHBaseVersion:(Ljava/lang/String;)Lorg/apache/hadoop/hbase/ClusterMetricsBuilder;
       8: new           #3                  // class java/util/ArrayList
      11: dup
      12: aload         4
      14: invokespecial #4                  // Method java/util/ArrayList."<init>":(Ljava/util/Collection;)V
      17: invokevirtual #5                  // Method org/apache/hadoop/hbase/ClusterMetricsBuilder.setDeadServerNames:(Ljava/util/List;)Lorg/apache/hadoop/hbase/ClusterMetricsBuilder;
      20: aload_3
      21: invokeinterface #6,  1            // InterfaceMethod java/util/Map.entrySet:()Ljava/util/Set;
      26: invokeinterface #7,  1            // InterfaceMethod java/util/Set.stream:()Ljava/util/stream/Stream;
      31: invokedynamic #8,  0              // InvokeDynamic #0:apply:()Ljava/util/function/Function;
      36: invokedynamic #9,  0              // InvokeDynamic #1:apply:()Ljava/util/function/Function;
      41: invokestatic  #10                 // Method java/util/stream/Collectors.toMap:(Ljava/util/function/Function;Ljava/util/function/Function;)Ljava/util/stream/Collector;
      44: invokeinterface #11,  2           // InterfaceMethod java/util/stream/Stream.collect:(Ljava/util/stream/Collector;)Ljava/lang/Object;
      49: checkcast     #12                 // class java/util/Map
      52: invokevirtual #13                 // Method org/apache/hadoop/hbase/ClusterMetricsBuilder.setLiveServerMetrics:(Ljava/util/Map;)Lorg/apache/hadoop/hbase/ClusterMetricsBuilder;
      55: new           #3                  // class java/util/ArrayList
      58: dup
      59: aload         6
      61: invokespecial #4                  // Method java/util/ArrayList."<init>":(Ljava/util/Collection;)V
      64: invokevirtual #14                 // Method org/apache/hadoop/hbase/ClusterMetricsBuilder.setBackerMasterNames:(Ljava/util/List;)Lorg/apache/hadoop/hbase/ClusterMetricsBuilder;
      67: aload         9
      69: invokevirtual #15                 // Method org/apache/hadoop/hbase/ClusterMetricsBuilder.setBalancerOn:(Ljava/lang/Boolean;)Lorg/apache/hadoop/hbase/ClusterMetricsBuilder;
      72: aload_2
      73: invokevirtual #16                 // Method org/apache/hadoop/hbase/ClusterMetricsBuilder.setClusterId:(Ljava/lang/String;)Lorg/apache/hadoop/hbase/ClusterMetricsBuilder;
      76: aload         8
      78: invokestatic  #17                 // Method java/util/Arrays.asList:([Ljava/lang/Object;)Ljava/util/List;
      81: invokevirtual #18                 // Method org/apache/hadoop/hbase/ClusterMetricsBuilder.setMasterCoprocessorNames:(Ljava/util/List;)Lorg/apache/hadoop/hbase/ClusterMetricsBuilder;
      84: aload         5
      86: invokevirtual #19                 // Method org/apache/hadoop/hbase/ClusterMetricsBuilder.setMasterName:(Lorg/apache/hadoop/hbase/ServerName;)Lorg/apache/hadoop/hbase/ClusterMetricsBuilder;
      89: iload         10
      91: invokevirtual #20                 // Method org/apache/hadoop/hbase/ClusterMetricsBuilder.setMasterInfoPort:(I)Lorg/apache/hadoop/hbase/ClusterMetricsBuilder;
      94: aload         7
      96: invokevirtual #21                 // Method org/apache/hadoop/hbase/ClusterMetricsBuilder.setRegionsInTransition:(Ljava/util/List;)Lorg/apache/hadoop/hbase/ClusterMetricsBuilder;
      99: invokevirtual #22                 // Method org/apache/hadoop/hbase/ClusterMetricsBuilder.build:()Lorg/apache/hadoop/hbase/ClusterMetrics;
     102: invokespecial #23                 // Method "<init>":(Lorg/apache/hadoop/hbase/ClusterMetrics;)V
     105: return

  public org.apache.hadoop.hbase.ClusterStatus(org.apache.hadoop.hbase.ClusterMetrics);
    Code:
       0: aload_0
       1: invokespecial #24                 // Method java/lang/Object."<init>":()V
       4: aload_0
       5: aload_1
       6: putfield      #25                 // Field metrics:Lorg/apache/hadoop/hbase/ClusterMetrics;
       9: return

  public java.util.List<org.apache.hadoop.hbase.ServerName> getDeadServerNames();
    Code:
       0: aload_0
       1: getfield      #25                 // Field metrics:Lorg/apache/hadoop/hbase/ClusterMetrics;
       4: invokeinterface #26,  1           // InterfaceMethod org/apache/hadoop/hbase/ClusterMetrics.getDeadServerNames:()Ljava/util/List;
       9: areturn

  public java.util.Map<org.apache.hadoop.hbase.ServerName, org.apache.hadoop.hbase.ServerMetrics> getLiveServerMetrics();
    Code:
       0: aload_0
       1: getfield      #25                 // Field metrics:Lorg/apache/hadoop/hbase/ClusterMetrics;
       4: invokeinterface #27,  1           // InterfaceMethod org/apache/hadoop/hbase/ClusterMetrics.getLiveServerMetrics:()Ljava/util/Map;
       9: areturn

  public int getServersSize();
    Code:
       0: aload_0
       1: getfield      #25                 // Field metrics:Lorg/apache/hadoop/hbase/ClusterMetrics;
       4: invokeinterface #27,  1           // InterfaceMethod org/apache/hadoop/hbase/ClusterMetrics.getLiveServerMetrics:()Ljava/util/Map;
       9: invokeinterface #28,  1           // InterfaceMethod java/util/Map.size:()I
      14: ireturn

  public int getDeadServers();
    Code:
       0: aload_0
       1: invokevirtual #29                 // Method getDeadServersSize:()I
       4: ireturn

  public int getDeadServersSize();
    Code:
       0: aload_0
       1: getfield      #25                 // Field metrics:Lorg/apache/hadoop/hbase/ClusterMetrics;
       4: invokeinterface #26,  1           // InterfaceMethod org/apache/hadoop/hbase/ClusterMetrics.getDeadServerNames:()Ljava/util/List;
       9: invokeinterface #30,  1           // InterfaceMethod java/util/List.size:()I
      14: ireturn

  public int getRegionsCount();
    Code:
       0: aload_0
       1: invokevirtual #31                 // Method getRegionCount:()I
       4: ireturn

  public int getRequestsCount();
    Code:
       0: aload_0
       1: invokevirtual #32                 // Method getRequestCount:()J
       4: l2i
       5: ireturn

  public org.apache.hadoop.hbase.ServerName getMasterName();
    Code:
       0: aload_0
       1: getfield      #25                 // Field metrics:Lorg/apache/hadoop/hbase/ClusterMetrics;
       4: invokeinterface #33,  1           // InterfaceMethod org/apache/hadoop/hbase/ClusterMetrics.getMasterName:()Lorg/apache/hadoop/hbase/ServerName;
       9: areturn

  public java.util.List<org.apache.hadoop.hbase.ServerName> getBackupMasterNames();
    Code:
       0: aload_0
       1: getfield      #25                 // Field metrics:Lorg/apache/hadoop/hbase/ClusterMetrics;
       4: invokeinterface #34,  1           // InterfaceMethod org/apache/hadoop/hbase/ClusterMetrics.getBackupMasterNames:()Ljava/util/List;
       9: areturn

  public java.util.List<org.apache.hadoop.hbase.master.RegionState> getRegionStatesInTransition();
    Code:
       0: aload_0
       1: getfield      #25                 // Field metrics:Lorg/apache/hadoop/hbase/ClusterMetrics;
       4: invokeinterface #35,  1           // InterfaceMethod org/apache/hadoop/hbase/ClusterMetrics.getRegionStatesInTransition:()Ljava/util/List;
       9: areturn

  public java.lang.String getHBaseVersion();
    Code:
       0: aload_0
       1: getfield      #25                 // Field metrics:Lorg/apache/hadoop/hbase/ClusterMetrics;
       4: invokeinterface #36,  1           // InterfaceMethod org/apache/hadoop/hbase/ClusterMetrics.getHBaseVersion:()Ljava/lang/String;
       9: areturn

  public boolean equals(java.lang.Object);
    Code:
       0: aload_0
       1: aload_1
       2: if_acmpne     7
       5: iconst_1
       6: ireturn
       7: aload_1
       8: instanceof    #39                 // class org/apache/hadoop/hbase/ClusterStatus
      11: ifne          16
      14: iconst_0
      15: ireturn
      16: aload_1
      17: checkcast     #39                 // class org/apache/hadoop/hbase/ClusterStatus
      20: astore_2
      21: aload_0
      22: invokevirtual #40                 // Method getHBaseVersion:()Ljava/lang/String;
      25: aload_2
      26: invokevirtual #40                 // Method getHBaseVersion:()Ljava/lang/String;
      29: invokestatic  #41                 // Method org/apache/hbase/thirdparty/com/google/common/base/Objects.equal:(Ljava/lang/Object;Ljava/lang/Object;)Z
      32: ifeq          138
      35: aload_0
      36: invokespecial #42                 // Method getLiveServerLoads:()Ljava/util/Map;
      39: aload_2
      40: invokespecial #42                 // Method getLiveServerLoads:()Ljava/util/Map;
      43: invokestatic  #41                 // Method org/apache/hbase/thirdparty/com/google/common/base/Objects.equal:(Ljava/lang/Object;Ljava/lang/Object;)Z
      46: ifeq          138
      49: aload_0
      50: invokevirtual #43                 // Method getDeadServerNames:()Ljava/util/List;
      53: aload_2
      54: invokevirtual #43                 // Method getDeadServerNames:()Ljava/util/List;
      57: invokeinterface #44,  2           // InterfaceMethod java/util/List.containsAll:(Ljava/util/Collection;)Z
      62: ifeq          138
      65: aload_0
      66: invokevirtual #45                 // Method getMasterCoprocessors:()[Ljava/lang/String;
      69: aload_2
      70: invokevirtual #45                 // Method getMasterCoprocessors:()[Ljava/lang/String;
      73: invokestatic  #46                 // Method java/util/Arrays.equals:([Ljava/lang/Object;[Ljava/lang/Object;)Z
      76: ifeq          138
      79: aload_0
      80: invokevirtual #47                 // Method getMaster:()Lorg/apache/hadoop/hbase/ServerName;
      83: aload_2
      84: invokevirtual #47                 // Method getMaster:()Lorg/apache/hadoop/hbase/ServerName;
      87: invokestatic  #41                 // Method org/apache/hbase/thirdparty/com/google/common/base/Objects.equal:(Ljava/lang/Object;Ljava/lang/Object;)Z
      90: ifeq          138
      93: aload_0
      94: invokevirtual #48                 // Method getBackupMasters:()Ljava/util/List;
      97: aload_2
      98: invokevirtual #48                 // Method getBackupMasters:()Ljava/util/List;
     101: invokeinterface #44,  2           // InterfaceMethod java/util/List.containsAll:(Ljava/util/Collection;)Z
     106: ifeq          138
     109: aload_0
     110: invokevirtual #49                 // Method getClusterId:()Ljava/lang/String;
     113: aload_2
     114: invokevirtual #49                 // Method getClusterId:()Ljava/lang/String;
     117: invokestatic  #41                 // Method org/apache/hbase/thirdparty/com/google/common/base/Objects.equal:(Ljava/lang/Object;Ljava/lang/Object;)Z
     120: ifeq          138
     123: aload_0
     124: invokevirtual #50                 // Method getMasterInfoPort:()I
     127: aload_2
     128: invokevirtual #50                 // Method getMasterInfoPort:()I
     131: if_icmpne     138
     134: iconst_1
     135: goto          139
     138: iconst_0
     139: ireturn

  public int hashCode();
    Code:
       0: aload_0
       1: getfield      #25                 // Field metrics:Lorg/apache/hadoop/hbase/ClusterMetrics;
       4: invokevirtual #51                 // Method java/lang/Object.hashCode:()I
       7: ireturn

  public byte getVersion();
    Code:
       0: iconst_2
       1: ireturn

  public java.util.Collection<org.apache.hadoop.hbase.ServerName> getServers();
    Code:
       0: aload_0
       1: getfield      #25                 // Field metrics:Lorg/apache/hadoop/hbase/ClusterMetrics;
       4: invokeinterface #27,  1           // InterfaceMethod org/apache/hadoop/hbase/ClusterMetrics.getLiveServerMetrics:()Ljava/util/Map;
       9: invokeinterface #52,  1           // InterfaceMethod java/util/Map.keySet:()Ljava/util/Set;
      14: areturn

  public org.apache.hadoop.hbase.ServerName getMaster();
    Code:
       0: aload_0
       1: getfield      #25                 // Field metrics:Lorg/apache/hadoop/hbase/ClusterMetrics;
       4: invokeinterface #33,  1           // InterfaceMethod org/apache/hadoop/hbase/ClusterMetrics.getMasterName:()Lorg/apache/hadoop/hbase/ServerName;
       9: areturn

  public int getBackupMastersSize();
    Code:
       0: aload_0
       1: getfield      #25                 // Field metrics:Lorg/apache/hadoop/hbase/ClusterMetrics;
       4: invokeinterface #34,  1           // InterfaceMethod org/apache/hadoop/hbase/ClusterMetrics.getBackupMasterNames:()Ljava/util/List;
       9: invokeinterface #30,  1           // InterfaceMethod java/util/List.size:()I
      14: ireturn

  public java.util.List<org.apache.hadoop.hbase.ServerName> getBackupMasters();
    Code:
       0: aload_0
       1: getfield      #25                 // Field metrics:Lorg/apache/hadoop/hbase/ClusterMetrics;
       4: invokeinterface #34,  1           // InterfaceMethod org/apache/hadoop/hbase/ClusterMetrics.getBackupMasterNames:()Ljava/util/List;
       9: areturn

  public org.apache.hadoop.hbase.ServerLoad getLoad(org.apache.hadoop.hbase.ServerName);
    Code:
       0: aload_0
       1: getfield      #25                 // Field metrics:Lorg/apache/hadoop/hbase/ClusterMetrics;
       4: invokeinterface #27,  1           // InterfaceMethod org/apache/hadoop/hbase/ClusterMetrics.getLiveServerMetrics:()Ljava/util/Map;
       9: aload_1
      10: invokeinterface #53,  2           // InterfaceMethod java/util/Map.get:(Ljava/lang/Object;)Ljava/lang/Object;
      15: checkcast     #54                 // class org/apache/hadoop/hbase/ServerMetrics
      18: astore_2
      19: aload_2
      20: ifnonnull     27
      23: aconst_null
      24: goto          35
      27: new           #55                 // class org/apache/hadoop/hbase/ServerLoad
      30: dup
      31: aload_2
      32: invokespecial #56                 // Method org/apache/hadoop/hbase/ServerLoad."<init>":(Lorg/apache/hadoop/hbase/ServerMetrics;)V
      35: areturn

  public java.lang.String getClusterId();
    Code:
       0: aload_0
       1: getfield      #25                 // Field metrics:Lorg/apache/hadoop/hbase/ClusterMetrics;
       4: invokeinterface #57,  1           // InterfaceMethod org/apache/hadoop/hbase/ClusterMetrics.getClusterId:()Ljava/lang/String;
       9: areturn

  public java.util.List<java.lang.String> getMasterCoprocessorNames();
    Code:
       0: aload_0
       1: getfield      #25                 // Field metrics:Lorg/apache/hadoop/hbase/ClusterMetrics;
       4: invokeinterface #58,  1           // InterfaceMethod org/apache/hadoop/hbase/ClusterMetrics.getMasterCoprocessorNames:()Ljava/util/List;
       9: areturn

  public java.lang.String[] getMasterCoprocessors();
    Code:
       0: aload_0
       1: getfield      #25                 // Field metrics:Lorg/apache/hadoop/hbase/ClusterMetrics;
       4: invokeinterface #58,  1           // InterfaceMethod org/apache/hadoop/hbase/ClusterMetrics.getMasterCoprocessorNames:()Ljava/util/List;
       9: astore_1
      10: aload_1
      11: aload_1
      12: invokeinterface #30,  1           // InterfaceMethod java/util/List.size:()I
      17: anewarray     #59                 // class java/lang/String
      20: invokeinterface #60,  2           // InterfaceMethod java/util/List.toArray:([Ljava/lang/Object;)[Ljava/lang/Object;
      25: checkcast     #61                 // class "[Ljava/lang/String;"
      28: areturn

  public long getLastMajorCompactionTsForTable(org.apache.hadoop.hbase.TableName);
    Code:
       0: aload_0
       1: getfield      #25                 // Field metrics:Lorg/apache/hadoop/hbase/ClusterMetrics;
       4: aload_1
       5: invokeinterface #62,  2           // InterfaceMethod org/apache/hadoop/hbase/ClusterMetrics.getLastMajorCompactionTimestamp:(Lorg/apache/hadoop/hbase/TableName;)J
      10: lreturn

  public long getLastMajorCompactionTsForRegion(byte[]);
    Code:
       0: aload_0
       1: getfield      #25                 // Field metrics:Lorg/apache/hadoop/hbase/ClusterMetrics;
       4: aload_1
       5: invokeinterface #63,  2           // InterfaceMethod org/apache/hadoop/hbase/ClusterMetrics.getLastMajorCompactionTimestamp:([B)J
      10: lreturn

  public boolean isBalancerOn();
    Code:
       0: aload_0
       1: getfield      #25                 // Field metrics:Lorg/apache/hadoop/hbase/ClusterMetrics;
       4: invokeinterface #64,  1           // InterfaceMethod org/apache/hadoop/hbase/ClusterMetrics.getBalancerOn:()Ljava/lang/Boolean;
       9: ifnull        31
      12: aload_0
      13: getfield      #25                 // Field metrics:Lorg/apache/hadoop/hbase/ClusterMetrics;
      16: invokeinterface #64,  1           // InterfaceMethod org/apache/hadoop/hbase/ClusterMetrics.getBalancerOn:()Ljava/lang/Boolean;
      21: invokevirtual #65                 // Method java/lang/Boolean.booleanValue:()Z
      24: ifeq          31
      27: iconst_1
      28: goto          32
      31: iconst_0
      32: ireturn

  public java.lang.Boolean getBalancerOn();
    Code:
       0: aload_0
       1: getfield      #25                 // Field metrics:Lorg/apache/hadoop/hbase/ClusterMetrics;
       4: invokeinterface #64,  1           // InterfaceMethod org/apache/hadoop/hbase/ClusterMetrics.getBalancerOn:()Ljava/lang/Boolean;
       9: areturn

  public int getMasterInfoPort();
    Code:
       0: aload_0
       1: getfield      #25                 // Field metrics:Lorg/apache/hadoop/hbase/ClusterMetrics;
       4: invokeinterface #66,  1           // InterfaceMethod org/apache/hadoop/hbase/ClusterMetrics.getMasterInfoPort:()I
       9: ireturn

  public java.util.List<org.apache.hadoop.hbase.ServerName> getServersName();
    Code:
       0: aload_0
       1: getfield      #25                 // Field metrics:Lorg/apache/hadoop/hbase/ClusterMetrics;
       4: invokeinterface #67,  1           // InterfaceMethod org/apache/hadoop/hbase/ClusterMetrics.getServersName:()Ljava/util/List;
       9: areturn

  public java.lang.String toString();
    Code:
       0: new           #68                 // class java/lang/StringBuilder
       3: dup
       4: sipush        1024
       7: invokespecial #69                 // Method java/lang/StringBuilder."<init>":(I)V
      10: astore_1
      11: aload_1
      12: new           #68                 // class java/lang/StringBuilder
      15: dup
      16: invokespecial #70                 // Method java/lang/StringBuilder."<init>":()V
      19: ldc           #71                 // String Master:
      21: invokevirtual #72                 // Method java/lang/StringBuilder.append:(Ljava/lang/String;)Ljava/lang/StringBuilder;
      24: aload_0
      25: getfield      #25                 // Field metrics:Lorg/apache/hadoop/hbase/ClusterMetrics;
      28: invokeinterface #33,  1           // InterfaceMethod org/apache/hadoop/hbase/ClusterMetrics.getMasterName:()Lorg/apache/hadoop/hbase/ServerName;
      33: invokevirtual #73                 // Method java/lang/StringBuilder.append:(Ljava/lang/Object;)Ljava/lang/StringBuilder;
      36: invokevirtual #74                 // Method java/lang/StringBuilder.toString:()Ljava/lang/String;
      39: invokevirtual #72                 // Method java/lang/StringBuilder.append:(Ljava/lang/String;)Ljava/lang/StringBuilder;
      42: pop
      43: aload_0
      44: invokevirtual #75                 // Method getBackupMastersSize:()I
      47: istore_2
      48: aload_1
      49: new           #68                 // class java/lang/StringBuilder
      52: dup
      53: invokespecial #70                 // Method java/lang/StringBuilder."<init>":()V
      56: ldc           #76                 // String \nNumber of backup masters:
      58: invokevirtual #72                 // Method java/lang/StringBuilder.append:(Ljava/lang/String;)Ljava/lang/StringBuilder;
      61: iload_2
      62: invokevirtual #77                 // Method java/lang/StringBuilder.append:(I)Ljava/lang/StringBuilder;
      65: invokevirtual #74                 // Method java/lang/StringBuilder.toString:()Ljava/lang/String;
      68: invokevirtual #72                 // Method java/lang/StringBuilder.append:(Ljava/lang/String;)Ljava/lang/StringBuilder;
      71: pop
      72: iload_2
      73: ifle          139
      76: aload_0
      77: getfield      #25                 // Field metrics:Lorg/apache/hadoop/hbase/ClusterMetrics;
      80: invokeinterface #34,  1           // InterfaceMethod org/apache/hadoop/hbase/ClusterMetrics.getBackupMasterNames:()Ljava/util/List;
      85: invokeinterface #78,  1           // InterfaceMethod java/util/List.iterator:()Ljava/util/Iterator;
      90: astore_3
      91: aload_3
      92: invokeinterface #79,  1           // InterfaceMethod java/util/Iterator.hasNext:()Z
      97: ifeq          139
     100: aload_3
     101: invokeinterface #80,  1           // InterfaceMethod java/util/Iterator.next:()Ljava/lang/Object;
     106: checkcast     #81                 // class org/apache/hadoop/hbase/ServerName
     109: astore        4
     111: aload_1
     112: new           #68                 // class java/lang/StringBuilder
     115: dup
     116: invokespecial #70                 // Method java/lang/StringBuilder."<init>":()V
     119: ldc           #82                 // String \n
     121: invokevirtual #72                 // Method java/lang/StringBuilder.append:(Ljava/lang/String;)Ljava/lang/StringBuilder;
     124: aload         4
     126: invokevirtual #73                 // Method java/lang/StringBuilder.append:(Ljava/lang/Object;)Ljava/lang/StringBuilder;
     129: invokevirtual #74                 // Method java/lang/StringBuilder.toString:()Ljava/lang/String;
     132: invokevirtual #72                 // Method java/lang/StringBuilder.append:(Ljava/lang/String;)Ljava/lang/StringBuilder;
     135: pop
     136: goto          91
     139: aload_0
     140: invokevirtual #83                 // Method getServersSize:()I
     143: istore_3
     144: aload_0
     145: invokevirtual #84                 // Method getServersName:()Ljava/util/List;
     148: invokeinterface #30,  1           // InterfaceMethod java/util/List.size:()I
     153: istore        4
     155: aload_1
     156: new           #68                 // class java/lang/StringBuilder
     159: dup
     160: invokespecial #70                 // Method java/lang/StringBuilder."<init>":()V
     163: ldc           #85                 // String \nNumber of live region servers:
     165: invokevirtual #72                 // Method java/lang/StringBuilder.append:(Ljava/lang/String;)Ljava/lang/StringBuilder;
     168: iload_3
     169: ifle          176
     172: iload_3
     173: goto          178
     176: iload         4
     178: invokevirtual #77                 // Method java/lang/StringBuilder.append:(I)Ljava/lang/StringBuilder;
     181: invokevirtual #74                 // Method java/lang/StringBuilder.toString:()Ljava/lang/String;
     184: invokevirtual #72                 // Method java/lang/StringBuilder.append:(Ljava/lang/String;)Ljava/lang/StringBuilder;
     187: pop
     188: iload_3
     189: ifle          269
     192: aload_0
     193: getfield      #25                 // Field metrics:Lorg/apache/hadoop/hbase/ClusterMetrics;
     196: invokeinterface #27,  1           // InterfaceMethod org/apache/hadoop/hbase/ClusterMetrics.getLiveServerMetrics:()Ljava/util/Map;
     201: invokeinterface #52,  1           // InterfaceMethod java/util/Map.keySet:()Ljava/util/Set;
     206: invokeinterface #86,  1           // InterfaceMethod java/util/Set.iterator:()Ljava/util/Iterator;
     211: astore        5
     213: aload         5
     215: invokeinterface #79,  1           // InterfaceMethod java/util/Iterator.hasNext:()Z
     220: ifeq          266
     223: aload         5
     225: invokeinterface #80,  1           // InterfaceMethod java/util/Iterator.next:()Ljava/lang/Object;
     230: checkcast     #81                 // class org/apache/hadoop/hbase/ServerName
     233: astore        6
     235: aload_1
     236: new           #68                 // class java/lang/StringBuilder
     239: dup
     240: invokespecial #70                 // Method java/lang/StringBuilder."<init>":()V
     243: ldc           #82                 // String \n
     245: invokevirtual #72                 // Method java/lang/StringBuilder.append:(Ljava/lang/String;)Ljava/lang/StringBuilder;
     248: aload         6
     250: invokevirtual #87                 // Method org/apache/hadoop/hbase/ServerName.getServerName:()Ljava/lang/String;
     253: invokevirtual #72                 // Method java/lang/StringBuilder.append:(Ljava/lang/String;)Ljava/lang/StringBuilder;
     256: invokevirtual #74                 // Method java/lang/StringBuilder.toString:()Ljava/lang/String;
     259: invokevirtual #72                 // Method java/lang/StringBuilder.append:(Ljava/lang/String;)Ljava/lang/StringBuilder;
     262: pop
     263: goto          213
     266: goto          338
     269: iload         4
     271: ifle          338
     274: aload_0
     275: invokevirtual #84                 // Method getServersName:()Ljava/util/List;
     278: invokeinterface #78,  1           // InterfaceMethod java/util/List.iterator:()Ljava/util/Iterator;
     283: astore        5
     285: aload         5
     287: invokeinterface #79,  1           // InterfaceMethod java/util/Iterator.hasNext:()Z
     292: ifeq          338
     295: aload         5
     297: invokeinterface #80,  1           // InterfaceMethod java/util/Iterator.next:()Ljava/lang/Object;
     302: checkcast     #81                 // class org/apache/hadoop/hbase/ServerName
     305: astore        6
     307: aload_1
     308: new           #68                 // class java/lang/StringBuilder
     311: dup
     312: invokespecial #70                 // Method java/lang/StringBuilder."<init>":()V
     315: ldc           #82                 // String \n
     317: invokevirtual #72                 // Method java/lang/StringBuilder.append:(Ljava/lang/String;)Ljava/lang/StringBuilder;
     320: aload         6
     322: invokevirtual #87                 // Method org/apache/hadoop/hbase/ServerName.getServerName:()Ljava/lang/String;
     325: invokevirtual #72                 // Method java/lang/StringBuilder.append:(Ljava/lang/String;)Ljava/lang/StringBuilder;
     328: invokevirtual #74                 // Method java/lang/StringBuilder.toString:()Ljava/lang/String;
     331: invokevirtual #72                 // Method java/lang/StringBuilder.append:(Ljava/lang/String;)Ljava/lang/StringBuilder;
     334: pop
     335: goto          285
     338: aload_0
     339: getfield      #25                 // Field metrics:Lorg/apache/hadoop/hbase/ClusterMetrics;
     342: invokeinterface #26,  1           // InterfaceMethod org/apache/hadoop/hbase/ClusterMetrics.getDeadServerNames:()Ljava/util/List;
     347: invokeinterface #30,  1           // InterfaceMethod java/util/List.size:()I
     352: istore        5
     354: aload_1
     355: new           #68                 // class java/lang/StringBuilder
     358: dup
     359: invokespecial #70                 // Method java/lang/StringBuilder."<init>":()V
     362: ldc           #88                 // String \nNumber of dead region servers:
     364: invokevirtual #72                 // Method java/lang/StringBuilder.append:(Ljava/lang/String;)Ljava/lang/StringBuilder;
     367: iload         5
     369: invokevirtual #77                 // Method java/lang/StringBuilder.append:(I)Ljava/lang/StringBuilder;
     372: invokevirtual #74                 // Method java/lang/StringBuilder.toString:()Ljava/lang/String;
     375: invokevirtual #72                 // Method java/lang/StringBuilder.append:(Ljava/lang/String;)Ljava/lang/StringBuilder;
     378: pop
     379: iload         5
     381: ifle          450
     384: aload_0
     385: getfield      #25                 // Field metrics:Lorg/apache/hadoop/hbase/ClusterMetrics;
     388: invokeinterface #26,  1           // InterfaceMethod org/apache/hadoop/hbase/ClusterMetrics.getDeadServerNames:()Ljava/util/List;
     393: invokeinterface #78,  1           // InterfaceMethod java/util/List.iterator:()Ljava/util/Iterator;
     398: astore        6
     400: aload         6
     402: invokeinterface #79,  1           // InterfaceMethod java/util/Iterator.hasNext:()Z
     407: ifeq          450
     410: aload         6
     412: invokeinterface #80,  1           // InterfaceMethod java/util/Iterator.next:()Ljava/lang/Object;
     417: checkcast     #81                 // class org/apache/hadoop/hbase/ServerName
     420: astore        7
     422: aload_1
     423: new           #68                 // class java/lang/StringBuilder
     426: dup
     427: invokespecial #70                 // Method java/lang/StringBuilder."<init>":()V
     430: ldc           #82                 // String \n
     432: invokevirtual #72                 // Method java/lang/StringBuilder.append:(Ljava/lang/String;)Ljava/lang/StringBuilder;
     435: aload         7
     437: invokevirtual #73                 // Method java/lang/StringBuilder.append:(Ljava/lang/Object;)Ljava/lang/StringBuilder;
     440: invokevirtual #74                 // Method java/lang/StringBuilder.toString:()Ljava/lang/String;
     443: invokevirtual #72                 // Method java/lang/StringBuilder.append:(Ljava/lang/String;)Ljava/lang/StringBuilder;
     446: pop
     447: goto          400
     450: aload_1
     451: new           #68                 // class java/lang/StringBuilder
     454: dup
     455: invokespecial #70                 // Method java/lang/StringBuilder."<init>":()V
     458: ldc           #89                 // String \nAverage load:
     460: invokevirtual #72                 // Method java/lang/StringBuilder.append:(Ljava/lang/String;)Ljava/lang/StringBuilder;
     463: aload_0
     464: invokevirtual #90                 // Method getAverageLoad:()D
     467: invokevirtual #91                 // Method java/lang/StringBuilder.append:(D)Ljava/lang/StringBuilder;
     470: invokevirtual #74                 // Method java/lang/StringBuilder.toString:()Ljava/lang/String;
     473: invokevirtual #72                 // Method java/lang/StringBuilder.append:(Ljava/lang/String;)Ljava/lang/StringBuilder;
     476: pop
     477: aload_1
     478: new           #68                 // class java/lang/StringBuilder
     481: dup
     482: invokespecial #70                 // Method java/lang/StringBuilder."<init>":()V
     485: ldc           #92                 // String \nNumber of requests:
     487: invokevirtual #72                 // Method java/lang/StringBuilder.append:(Ljava/lang/String;)Ljava/lang/StringBuilder;
     490: aload_0
     491: invokevirtual #32                 // Method getRequestCount:()J
     494: invokevirtual #93                 // Method java/lang/StringBuilder.append:(J)Ljava/lang/StringBuilder;
     497: invokevirtual #74                 // Method java/lang/StringBuilder.toString:()Ljava/lang/String;
     500: invokevirtual #72                 // Method java/lang/StringBuilder.append:(Ljava/lang/String;)Ljava/lang/StringBuilder;
     503: pop
     504: aload_1
     505: new           #68                 // class java/lang/StringBuilder
     508: dup
     509: invokespecial #70                 // Method java/lang/StringBuilder."<init>":()V
     512: ldc           #94                 // String \nNumber of regions:
     514: invokevirtual #72                 // Method java/lang/StringBuilder.append:(Ljava/lang/String;)Ljava/lang/StringBuilder;
     517: aload_0
     518: invokevirtual #95                 // Method getRegionsCount:()I
     521: invokevirtual #77                 // Method java/lang/StringBuilder.append:(I)Ljava/lang/StringBuilder;
     524: invokevirtual #74                 // Method java/lang/StringBuilder.toString:()Ljava/lang/String;
     527: invokevirtual #72                 // Method java/lang/StringBuilder.append:(Ljava/lang/String;)Ljava/lang/StringBuilder;
     530: pop
     531: aload_0
     532: getfield      #25                 // Field metrics:Lorg/apache/hadoop/hbase/ClusterMetrics;
     535: invokeinterface #35,  1           // InterfaceMethod org/apache/hadoop/hbase/ClusterMetrics.getRegionStatesInTransition:()Ljava/util/List;
     540: invokeinterface #30,  1           // InterfaceMethod java/util/List.size:()I
     545: istore        6
     547: aload_1
     548: new           #68                 // class java/lang/StringBuilder
     551: dup
     552: invokespecial #70                 // Method java/lang/StringBuilder."<init>":()V
     555: ldc           #96                 // String \nNumber of regions in transition:
     557: invokevirtual #72                 // Method java/lang/StringBuilder.append:(Ljava/lang/String;)Ljava/lang/StringBuilder;
     560: iload         6
     562: invokevirtual #77                 // Method java/lang/StringBuilder.append:(I)Ljava/lang/StringBuilder;
     565: invokevirtual #74                 // Method java/lang/StringBuilder.toString:()Ljava/lang/String;
     568: invokevirtual #72                 // Method java/lang/StringBuilder.append:(Ljava/lang/String;)Ljava/lang/StringBuilder;
     571: pop
     572: iload         6
     574: ifle          646
     577: aload_0
     578: getfield      #25                 // Field metrics:Lorg/apache/hadoop/hbase/ClusterMetrics;
     581: invokeinterface #35,  1           // InterfaceMethod org/apache/hadoop/hbase/ClusterMetrics.getRegionStatesInTransition:()Ljava/util/List;
     586: invokeinterface #78,  1           // InterfaceMethod java/util/List.iterator:()Ljava/util/Iterator;
     591: astore        7
     593: aload         7
     595: invokeinterface #79,  1           // InterfaceMethod java/util/Iterator.hasNext:()Z
     600: ifeq          646
     603: aload         7
     605: invokeinterface #80,  1           // InterfaceMethod java/util/Iterator.next:()Ljava/lang/Object;
     610: checkcast     #97                 // class org/apache/hadoop/hbase/master/RegionState
     613: astore        8
     615: aload_1
     616: new           #68                 // class java/lang/StringBuilder
     619: dup
     620: invokespecial #70                 // Method java/lang/StringBuilder."<init>":()V
     623: ldc           #82                 // String \n
     625: invokevirtual #72                 // Method java/lang/StringBuilder.append:(Ljava/lang/String;)Ljava/lang/StringBuilder;
     628: aload         8
     630: invokevirtual #98                 // Method org/apache/hadoop/hbase/master/RegionState.toDescriptiveString:()Ljava/lang/String;
     633: invokevirtual #72                 // Method java/lang/StringBuilder.append:(Ljava/lang/String;)Ljava/lang/StringBuilder;
     636: invokevirtual #74                 // Method java/lang/StringBuilder.toString:()Ljava/lang/String;
     639: invokevirtual #72                 // Method java/lang/StringBuilder.append:(Ljava/lang/String;)Ljava/lang/StringBuilder;
     642: pop
     643: goto          593
     646: aload_1
     647: invokevirtual #74                 // Method java/lang/StringBuilder.toString:()Ljava/lang/String;
     650: areturn
}
