Compiled from "ClusterStatusProtos.java"
public final class org.apache.hadoop.hbase.protobuf.generated.ClusterStatusProtos$ClusterStatus extends com.google.protobuf.GeneratedMessage implements org.apache.hadoop.hbase.protobuf.generated.ClusterStatusProtos$ClusterStatusOrBuilder {
  public static com.google.protobuf.Parser<org.apache.hadoop.hbase.protobuf.generated.ClusterStatusProtos$ClusterStatus> PARSER;

  public static final int HBASE_VERSION_FIELD_NUMBER;

  public static final int LIVE_SERVERS_FIELD_NUMBER;

  public static final int DEAD_SERVERS_FIELD_NUMBER;

  public static final int REGIONS_IN_TRANSITION_FIELD_NUMBER;

  public static final int CLUSTER_ID_FIELD_NUMBER;

  public static final int MASTER_COPROCESSORS_FIELD_NUMBER;

  public static final int MASTER_FIELD_NUMBER;

  public static final int BACKUP_MASTERS_FIELD_NUMBER;

  public static final int BALANCER_ON_FIELD_NUMBER;

  public static org.apache.hadoop.hbase.protobuf.generated.ClusterStatusProtos$ClusterStatus getDefaultInstance();
    Code:
       0: getstatic     #22                 // Field defaultInstance:Lorg/apache/hadoop/hbase/protobuf/generated/ClusterStatusProtos$ClusterStatus;
       3: areturn

  public org.apache.hadoop.hbase.protobuf.generated.ClusterStatusProtos$ClusterStatus getDefaultInstanceForType();
    Code:
       0: getstatic     #22                 // Field defaultInstance:Lorg/apache/hadoop/hbase/protobuf/generated/ClusterStatusProtos$ClusterStatus;
       3: areturn

  public final com.google.protobuf.UnknownFieldSet getUnknownFields();
    Code:
       0: aload_0
       1: getfield      #19                 // Field unknownFields:Lcom/google/protobuf/UnknownFieldSet;
       4: areturn

  public static final com.google.protobuf.Descriptors$Descriptor getDescriptor();
    Code:
       0: invokestatic  #58                 // Method org/apache/hadoop/hbase/protobuf/generated/ClusterStatusProtos.access$12700:()Lcom/google/protobuf/Descriptors$Descriptor;
       3: areturn

  protected com.google.protobuf.GeneratedMessage$FieldAccessorTable internalGetFieldAccessorTable();
    Code:
       0: invokestatic  #59                 // Method org/apache/hadoop/hbase/protobuf/generated/ClusterStatusProtos.access$12800:()Lcom/google/protobuf/GeneratedMessage$FieldAccessorTable;
       3: ldc           #60                 // class org/apache/hadoop/hbase/protobuf/generated/ClusterStatusProtos$ClusterStatus
       5: ldc           #61                 // class org/apache/hadoop/hbase/protobuf/generated/ClusterStatusProtos$ClusterStatus$Builder
       7: invokevirtual #62                 // Method com/google/protobuf/GeneratedMessage$FieldAccessorTable.ensureFieldAccessorsInitialized:(Ljava/lang/Class;Ljava/lang/Class;)Lcom/google/protobuf/GeneratedMessage$FieldAccessorTable;
      10: areturn

  public com.google.protobuf.Parser<org.apache.hadoop.hbase.protobuf.generated.ClusterStatusProtos$ClusterStatus> getParserForType();
    Code:
       0: getstatic     #63                 // Field PARSER:Lcom/google/protobuf/Parser;
       3: areturn

  public boolean hasHbaseVersion();
    Code:
       0: aload_0
       1: getfield      #2                  // Field bitField0_:I
       4: iconst_1
       5: iand
       6: iconst_1
       7: if_icmpne     14
      10: iconst_1
      11: goto          15
      14: iconst_0
      15: ireturn

  public org.apache.hadoop.hbase.protobuf.generated.FSProtos$HBaseVersionFileContent getHbaseVersion();
    Code:
       0: aload_0
       1: getfield      #11                 // Field hbaseVersion_:Lorg/apache/hadoop/hbase/protobuf/generated/FSProtos$HBaseVersionFileContent;
       4: areturn

  public org.apache.hadoop.hbase.protobuf.generated.FSProtos$HBaseVersionFileContentOrBuilder getHbaseVersionOrBuilder();
    Code:
       0: aload_0
       1: getfield      #11                 // Field hbaseVersion_:Lorg/apache/hadoop/hbase/protobuf/generated/FSProtos$HBaseVersionFileContent;
       4: areturn

  public java.util.List<org.apache.hadoop.hbase.protobuf.generated.ClusterStatusProtos$LiveServerInfo> getLiveServersList();
    Code:
       0: aload_0
       1: getfield      #10                 // Field liveServers_:Ljava/util/List;
       4: areturn

  public java.util.List<? extends org.apache.hadoop.hbase.protobuf.generated.ClusterStatusProtos$LiveServerInfoOrBuilder> getLiveServersOrBuilderList();
    Code:
       0: aload_0
       1: getfield      #10                 // Field liveServers_:Ljava/util/List;
       4: areturn

  public int getLiveServersCount();
    Code:
       0: aload_0
       1: getfield      #10                 // Field liveServers_:Ljava/util/List;
       4: invokeinterface #64,  1           // InterfaceMethod java/util/List.size:()I
       9: ireturn

  public org.apache.hadoop.hbase.protobuf.generated.ClusterStatusProtos$LiveServerInfo getLiveServers(int);
    Code:
       0: aload_0
       1: getfield      #10                 // Field liveServers_:Ljava/util/List;
       4: iload_1
       5: invokeinterface #65,  2           // InterfaceMethod java/util/List.get:(I)Ljava/lang/Object;
      10: checkcast     #66                 // class org/apache/hadoop/hbase/protobuf/generated/ClusterStatusProtos$LiveServerInfo
      13: areturn

  public org.apache.hadoop.hbase.protobuf.generated.ClusterStatusProtos$LiveServerInfoOrBuilder getLiveServersOrBuilder(int);
    Code:
       0: aload_0
       1: getfield      #10                 // Field liveServers_:Ljava/util/List;
       4: iload_1
       5: invokeinterface #65,  2           // InterfaceMethod java/util/List.get:(I)Ljava/lang/Object;
      10: checkcast     #67                 // class org/apache/hadoop/hbase/protobuf/generated/ClusterStatusProtos$LiveServerInfoOrBuilder
      13: areturn

  public java.util.List<org.apache.hadoop.hbase.protobuf.generated.HBaseProtos$ServerName> getDeadServersList();
    Code:
       0: aload_0
       1: getfield      #9                  // Field deadServers_:Ljava/util/List;
       4: areturn

  public java.util.List<? extends org.apache.hadoop.hbase.protobuf.generated.HBaseProtos$ServerNameOrBuilder> getDeadServersOrBuilderList();
    Code:
       0: aload_0
       1: getfield      #9                  // Field deadServers_:Ljava/util/List;
       4: areturn

  public int getDeadServersCount();
    Code:
       0: aload_0
       1: getfield      #9                  // Field deadServers_:Ljava/util/List;
       4: invokeinterface #64,  1           // InterfaceMethod java/util/List.size:()I
       9: ireturn

  public org.apache.hadoop.hbase.protobuf.generated.HBaseProtos$ServerName getDeadServers(int);
    Code:
       0: aload_0
       1: getfield      #9                  // Field deadServers_:Ljava/util/List;
       4: iload_1
       5: invokeinterface #65,  2           // InterfaceMethod java/util/List.get:(I)Ljava/lang/Object;
      10: checkcast     #46                 // class org/apache/hadoop/hbase/protobuf/generated/HBaseProtos$ServerName
      13: areturn

  public org.apache.hadoop.hbase.protobuf.generated.HBaseProtos$ServerNameOrBuilder getDeadServersOrBuilder(int);
    Code:
       0: aload_0
       1: getfield      #9                  // Field deadServers_:Ljava/util/List;
       4: iload_1
       5: invokeinterface #65,  2           // InterfaceMethod java/util/List.get:(I)Ljava/lang/Object;
      10: checkcast     #68                 // class org/apache/hadoop/hbase/protobuf/generated/HBaseProtos$ServerNameOrBuilder
      13: areturn

  public java.util.List<org.apache.hadoop.hbase.protobuf.generated.ClusterStatusProtos$RegionInTransition> getRegionsInTransitionList();
    Code:
       0: aload_0
       1: getfield      #8                  // Field regionsInTransition_:Ljava/util/List;
       4: areturn

  public java.util.List<? extends org.apache.hadoop.hbase.protobuf.generated.ClusterStatusProtos$RegionInTransitionOrBuilder> getRegionsInTransitionOrBuilderList();
    Code:
       0: aload_0
       1: getfield      #8                  // Field regionsInTransition_:Ljava/util/List;
       4: areturn

  public int getRegionsInTransitionCount();
    Code:
       0: aload_0
       1: getfield      #8                  // Field regionsInTransition_:Ljava/util/List;
       4: invokeinterface #64,  1           // InterfaceMethod java/util/List.size:()I
       9: ireturn

  public org.apache.hadoop.hbase.protobuf.generated.ClusterStatusProtos$RegionInTransition getRegionsInTransition(int);
    Code:
       0: aload_0
       1: getfield      #8                  // Field regionsInTransition_:Ljava/util/List;
       4: iload_1
       5: invokeinterface #65,  2           // InterfaceMethod java/util/List.get:(I)Ljava/lang/Object;
      10: checkcast     #69                 // class org/apache/hadoop/hbase/protobuf/generated/ClusterStatusProtos$RegionInTransition
      13: areturn

  public org.apache.hadoop.hbase.protobuf.generated.ClusterStatusProtos$RegionInTransitionOrBuilder getRegionsInTransitionOrBuilder(int);
    Code:
       0: aload_0
       1: getfield      #8                  // Field regionsInTransition_:Ljava/util/List;
       4: iload_1
       5: invokeinterface #65,  2           // InterfaceMethod java/util/List.get:(I)Ljava/lang/Object;
      10: checkcast     #70                 // class org/apache/hadoop/hbase/protobuf/generated/ClusterStatusProtos$RegionInTransitionOrBuilder
      13: areturn

  public boolean hasClusterId();
    Code:
       0: aload_0
       1: getfield      #2                  // Field bitField0_:I
       4: iconst_2
       5: iand
       6: iconst_2
       7: if_icmpne     14
      10: iconst_1
      11: goto          15
      14: iconst_0
      15: ireturn

  public org.apache.hadoop.hbase.protobuf.generated.ClusterIdProtos$ClusterId getClusterId();
    Code:
       0: aload_0
       1: getfield      #7                  // Field clusterId_:Lorg/apache/hadoop/hbase/protobuf/generated/ClusterIdProtos$ClusterId;
       4: areturn

  public org.apache.hadoop.hbase.protobuf.generated.ClusterIdProtos$ClusterIdOrBuilder getClusterIdOrBuilder();
    Code:
       0: aload_0
       1: getfield      #7                  // Field clusterId_:Lorg/apache/hadoop/hbase/protobuf/generated/ClusterIdProtos$ClusterId;
       4: areturn

  public java.util.List<org.apache.hadoop.hbase.protobuf.generated.HBaseProtos$Coprocessor> getMasterCoprocessorsList();
    Code:
       0: aload_0
       1: getfield      #6                  // Field masterCoprocessors_:Ljava/util/List;
       4: areturn

  public java.util.List<? extends org.apache.hadoop.hbase.protobuf.generated.HBaseProtos$CoprocessorOrBuilder> getMasterCoprocessorsOrBuilderList();
    Code:
       0: aload_0
       1: getfield      #6                  // Field masterCoprocessors_:Ljava/util/List;
       4: areturn

  public int getMasterCoprocessorsCount();
    Code:
       0: aload_0
       1: getfield      #6                  // Field masterCoprocessors_:Ljava/util/List;
       4: invokeinterface #64,  1           // InterfaceMethod java/util/List.size:()I
       9: ireturn

  public org.apache.hadoop.hbase.protobuf.generated.HBaseProtos$Coprocessor getMasterCoprocessors(int);
    Code:
       0: aload_0
       1: getfield      #6                  // Field masterCoprocessors_:Ljava/util/List;
       4: iload_1
       5: invokeinterface #65,  2           // InterfaceMethod java/util/List.get:(I)Ljava/lang/Object;
      10: checkcast     #71                 // class org/apache/hadoop/hbase/protobuf/generated/HBaseProtos$Coprocessor
      13: areturn

  public org.apache.hadoop.hbase.protobuf.generated.HBaseProtos$CoprocessorOrBuilder getMasterCoprocessorsOrBuilder(int);
    Code:
       0: aload_0
       1: getfield      #6                  // Field masterCoprocessors_:Ljava/util/List;
       4: iload_1
       5: invokeinterface #65,  2           // InterfaceMethod java/util/List.get:(I)Ljava/lang/Object;
      10: checkcast     #72                 // class org/apache/hadoop/hbase/protobuf/generated/HBaseProtos$CoprocessorOrBuilder
      13: areturn

  public boolean hasMaster();
    Code:
       0: aload_0
       1: getfield      #2                  // Field bitField0_:I
       4: iconst_4
       5: iand
       6: iconst_4
       7: if_icmpne     14
      10: iconst_1
      11: goto          15
      14: iconst_0
      15: ireturn

  public org.apache.hadoop.hbase.protobuf.generated.HBaseProtos$ServerName getMaster();
    Code:
       0: aload_0
       1: getfield      #5                  // Field master_:Lorg/apache/hadoop/hbase/protobuf/generated/HBaseProtos$ServerName;
       4: areturn

  public org.apache.hadoop.hbase.protobuf.generated.HBaseProtos$ServerNameOrBuilder getMasterOrBuilder();
    Code:
       0: aload_0
       1: getfield      #5                  // Field master_:Lorg/apache/hadoop/hbase/protobuf/generated/HBaseProtos$ServerName;
       4: areturn

  public java.util.List<org.apache.hadoop.hbase.protobuf.generated.HBaseProtos$ServerName> getBackupMastersList();
    Code:
       0: aload_0
       1: getfield      #4                  // Field backupMasters_:Ljava/util/List;
       4: areturn

  public java.util.List<? extends org.apache.hadoop.hbase.protobuf.generated.HBaseProtos$ServerNameOrBuilder> getBackupMastersOrBuilderList();
    Code:
       0: aload_0
       1: getfield      #4                  // Field backupMasters_:Ljava/util/List;
       4: areturn

  public int getBackupMastersCount();
    Code:
       0: aload_0
       1: getfield      #4                  // Field backupMasters_:Ljava/util/List;
       4: invokeinterface #64,  1           // InterfaceMethod java/util/List.size:()I
       9: ireturn

  public org.apache.hadoop.hbase.protobuf.generated.HBaseProtos$ServerName getBackupMasters(int);
    Code:
       0: aload_0
       1: getfield      #4                  // Field backupMasters_:Ljava/util/List;
       4: iload_1
       5: invokeinterface #65,  2           // InterfaceMethod java/util/List.get:(I)Ljava/lang/Object;
      10: checkcast     #46                 // class org/apache/hadoop/hbase/protobuf/generated/HBaseProtos$ServerName
      13: areturn

  public org.apache.hadoop.hbase.protobuf.generated.HBaseProtos$ServerNameOrBuilder getBackupMastersOrBuilder(int);
    Code:
       0: aload_0
       1: getfield      #4                  // Field backupMasters_:Ljava/util/List;
       4: iload_1
       5: invokeinterface #65,  2           // InterfaceMethod java/util/List.get:(I)Ljava/lang/Object;
      10: checkcast     #68                 // class org/apache/hadoop/hbase/protobuf/generated/HBaseProtos$ServerNameOrBuilder
      13: areturn

  public boolean hasBalancerOn();
    Code:
       0: aload_0
       1: getfield      #2                  // Field bitField0_:I
       4: bipush        8
       6: iand
       7: bipush        8
       9: if_icmpne     16
      12: iconst_1
      13: goto          17
      16: iconst_0
      17: ireturn

  public boolean getBalancerOn();
    Code:
       0: aload_0
       1: getfield      #3                  // Field balancerOn_:Z
       4: ireturn

  public final boolean isInitialized();
    Code:
       0: aload_0
       1: getfield      #15                 // Field memoizedIsInitialized:B
       4: istore_1
       5: iload_1
       6: iconst_m1
       7: if_icmpeq     21
      10: iload_1
      11: iconst_1
      12: if_icmpne     19
      15: iconst_1
      16: goto          20
      19: iconst_0
      20: ireturn
      21: aload_0
      22: invokevirtual #77                 // Method hasHbaseVersion:()Z
      25: ifeq          45
      28: aload_0
      29: invokevirtual #78                 // Method getHbaseVersion:()Lorg/apache/hadoop/hbase/protobuf/generated/FSProtos$HBaseVersionFileContent;
      32: invokevirtual #79                 // Method org/apache/hadoop/hbase/protobuf/generated/FSProtos$HBaseVersionFileContent.isInitialized:()Z
      35: ifne          45
      38: aload_0
      39: iconst_0
      40: putfield      #15                 // Field memoizedIsInitialized:B
      43: iconst_0
      44: ireturn
      45: iconst_0
      46: istore_2
      47: iload_2
      48: aload_0
      49: invokevirtual #80                 // Method getLiveServersCount:()I
      52: if_icmpge     79
      55: aload_0
      56: iload_2
      57: invokevirtual #81                 // Method getLiveServers:(I)Lorg/apache/hadoop/hbase/protobuf/generated/ClusterStatusProtos$LiveServerInfo;
      60: invokevirtual #82                 // Method org/apache/hadoop/hbase/protobuf/generated/ClusterStatusProtos$LiveServerInfo.isInitialized:()Z
      63: ifne          73
      66: aload_0
      67: iconst_0
      68: putfield      #15                 // Field memoizedIsInitialized:B
      71: iconst_0
      72: ireturn
      73: iinc          2, 1
      76: goto          47
      79: iconst_0
      80: istore_2
      81: iload_2
      82: aload_0
      83: invokevirtual #83                 // Method getDeadServersCount:()I
      86: if_icmpge     113
      89: aload_0
      90: iload_2
      91: invokevirtual #84                 // Method getDeadServers:(I)Lorg/apache/hadoop/hbase/protobuf/generated/HBaseProtos$ServerName;
      94: invokevirtual #85                 // Method org/apache/hadoop/hbase/protobuf/generated/HBaseProtos$ServerName.isInitialized:()Z
      97: ifne          107
     100: aload_0
     101: iconst_0
     102: putfield      #15                 // Field memoizedIsInitialized:B
     105: iconst_0
     106: ireturn
     107: iinc          2, 1
     110: goto          81
     113: iconst_0
     114: istore_2
     115: iload_2
     116: aload_0
     117: invokevirtual #86                 // Method getRegionsInTransitionCount:()I
     120: if_icmpge     147
     123: aload_0
     124: iload_2
     125: invokevirtual #87                 // Method getRegionsInTransition:(I)Lorg/apache/hadoop/hbase/protobuf/generated/ClusterStatusProtos$RegionInTransition;
     128: invokevirtual #88                 // Method org/apache/hadoop/hbase/protobuf/generated/ClusterStatusProtos$RegionInTransition.isInitialized:()Z
     131: ifne          141
     134: aload_0
     135: iconst_0
     136: putfield      #15                 // Field memoizedIsInitialized:B
     139: iconst_0
     140: ireturn
     141: iinc          2, 1
     144: goto          115
     147: aload_0
     148: invokevirtual #89                 // Method hasClusterId:()Z
     151: ifeq          171
     154: aload_0
     155: invokevirtual #90                 // Method getClusterId:()Lorg/apache/hadoop/hbase/protobuf/generated/ClusterIdProtos$ClusterId;
     158: invokevirtual #91                 // Method org/apache/hadoop/hbase/protobuf/generated/ClusterIdProtos$ClusterId.isInitialized:()Z
     161: ifne          171
     164: aload_0
     165: iconst_0
     166: putfield      #15                 // Field memoizedIsInitialized:B
     169: iconst_0
     170: ireturn
     171: iconst_0
     172: istore_2
     173: iload_2
     174: aload_0
     175: invokevirtual #92                 // Method getMasterCoprocessorsCount:()I
     178: if_icmpge     205
     181: aload_0
     182: iload_2
     183: invokevirtual #93                 // Method getMasterCoprocessors:(I)Lorg/apache/hadoop/hbase/protobuf/generated/HBaseProtos$Coprocessor;
     186: invokevirtual #94                 // Method org/apache/hadoop/hbase/protobuf/generated/HBaseProtos$Coprocessor.isInitialized:()Z
     189: ifne          199
     192: aload_0
     193: iconst_0
     194: putfield      #15                 // Field memoizedIsInitialized:B
     197: iconst_0
     198: ireturn
     199: iinc          2, 1
     202: goto          173
     205: aload_0
     206: invokevirtual #95                 // Method hasMaster:()Z
     209: ifeq          229
     212: aload_0
     213: invokevirtual #96                 // Method getMaster:()Lorg/apache/hadoop/hbase/protobuf/generated/HBaseProtos$ServerName;
     216: invokevirtual #85                 // Method org/apache/hadoop/hbase/protobuf/generated/HBaseProtos$ServerName.isInitialized:()Z
     219: ifne          229
     222: aload_0
     223: iconst_0
     224: putfield      #15                 // Field memoizedIsInitialized:B
     227: iconst_0
     228: ireturn
     229: iconst_0
     230: istore_2
     231: iload_2
     232: aload_0
     233: invokevirtual #97                 // Method getBackupMastersCount:()I
     236: if_icmpge     263
     239: aload_0
     240: iload_2
     241: invokevirtual #98                 // Method getBackupMasters:(I)Lorg/apache/hadoop/hbase/protobuf/generated/HBaseProtos$ServerName;
     244: invokevirtual #85                 // Method org/apache/hadoop/hbase/protobuf/generated/HBaseProtos$ServerName.isInitialized:()Z
     247: ifne          257
     250: aload_0
     251: iconst_0
     252: putfield      #15                 // Field memoizedIsInitialized:B
     255: iconst_0
     256: ireturn
     257: iinc          2, 1
     260: goto          231
     263: aload_0
     264: iconst_1
     265: putfield      #15                 // Field memoizedIsInitialized:B
     268: iconst_1
     269: ireturn

  public void writeTo(com.google.protobuf.CodedOutputStream) throws java.io.IOException;
    Code:
       0: aload_0
       1: invokevirtual #99                 // Method getSerializedSize:()I
       4: pop
       5: aload_0
       6: getfield      #2                  // Field bitField0_:I
       9: iconst_1
      10: iand
      11: iconst_1
      12: if_icmpne     24
      15: aload_1
      16: iconst_1
      17: aload_0
      18: getfield      #11                 // Field hbaseVersion_:Lorg/apache/hadoop/hbase/protobuf/generated/FSProtos$HBaseVersionFileContent;
      21: invokevirtual #100                // Method com/google/protobuf/CodedOutputStream.writeMessage:(ILcom/google/protobuf/MessageLite;)V
      24: iconst_0
      25: istore_2
      26: iload_2
      27: aload_0
      28: getfield      #10                 // Field liveServers_:Ljava/util/List;
      31: invokeinterface #64,  1           // InterfaceMethod java/util/List.size:()I
      36: if_icmpge     63
      39: aload_1
      40: iconst_2
      41: aload_0
      42: getfield      #10                 // Field liveServers_:Ljava/util/List;
      45: iload_2
      46: invokeinterface #65,  2           // InterfaceMethod java/util/List.get:(I)Ljava/lang/Object;
      51: checkcast     #101                // class com/google/protobuf/MessageLite
      54: invokevirtual #100                // Method com/google/protobuf/CodedOutputStream.writeMessage:(ILcom/google/protobuf/MessageLite;)V
      57: iinc          2, 1
      60: goto          26
      63: iconst_0
      64: istore_2
      65: iload_2
      66: aload_0
      67: getfield      #9                  // Field deadServers_:Ljava/util/List;
      70: invokeinterface #64,  1           // InterfaceMethod java/util/List.size:()I
      75: if_icmpge     102
      78: aload_1
      79: iconst_3
      80: aload_0
      81: getfield      #9                  // Field deadServers_:Ljava/util/List;
      84: iload_2
      85: invokeinterface #65,  2           // InterfaceMethod java/util/List.get:(I)Ljava/lang/Object;
      90: checkcast     #101                // class com/google/protobuf/MessageLite
      93: invokevirtual #100                // Method com/google/protobuf/CodedOutputStream.writeMessage:(ILcom/google/protobuf/MessageLite;)V
      96: iinc          2, 1
      99: goto          65
     102: iconst_0
     103: istore_2
     104: iload_2
     105: aload_0
     106: getfield      #8                  // Field regionsInTransition_:Ljava/util/List;
     109: invokeinterface #64,  1           // InterfaceMethod java/util/List.size:()I
     114: if_icmpge     141
     117: aload_1
     118: iconst_4
     119: aload_0
     120: getfield      #8                  // Field regionsInTransition_:Ljava/util/List;
     123: iload_2
     124: invokeinterface #65,  2           // InterfaceMethod java/util/List.get:(I)Ljava/lang/Object;
     129: checkcast     #101                // class com/google/protobuf/MessageLite
     132: invokevirtual #100                // Method com/google/protobuf/CodedOutputStream.writeMessage:(ILcom/google/protobuf/MessageLite;)V
     135: iinc          2, 1
     138: goto          104
     141: aload_0
     142: getfield      #2                  // Field bitField0_:I
     145: iconst_2
     146: iand
     147: iconst_2
     148: if_icmpne     160
     151: aload_1
     152: iconst_5
     153: aload_0
     154: getfield      #7                  // Field clusterId_:Lorg/apache/hadoop/hbase/protobuf/generated/ClusterIdProtos$ClusterId;
     157: invokevirtual #100                // Method com/google/protobuf/CodedOutputStream.writeMessage:(ILcom/google/protobuf/MessageLite;)V
     160: iconst_0
     161: istore_2
     162: iload_2
     163: aload_0
     164: getfield      #6                  // Field masterCoprocessors_:Ljava/util/List;
     167: invokeinterface #64,  1           // InterfaceMethod java/util/List.size:()I
     172: if_icmpge     200
     175: aload_1
     176: bipush        6
     178: aload_0
     179: getfield      #6                  // Field masterCoprocessors_:Ljava/util/List;
     182: iload_2
     183: invokeinterface #65,  2           // InterfaceMethod java/util/List.get:(I)Ljava/lang/Object;
     188: checkcast     #101                // class com/google/protobuf/MessageLite
     191: invokevirtual #100                // Method com/google/protobuf/CodedOutputStream.writeMessage:(ILcom/google/protobuf/MessageLite;)V
     194: iinc          2, 1
     197: goto          162
     200: aload_0
     201: getfield      #2                  // Field bitField0_:I
     204: iconst_4
     205: iand
     206: iconst_4
     207: if_icmpne     220
     210: aload_1
     211: bipush        7
     213: aload_0
     214: getfield      #5                  // Field master_:Lorg/apache/hadoop/hbase/protobuf/generated/HBaseProtos$ServerName;
     217: invokevirtual #100                // Method com/google/protobuf/CodedOutputStream.writeMessage:(ILcom/google/protobuf/MessageLite;)V
     220: iconst_0
     221: istore_2
     222: iload_2
     223: aload_0
     224: getfield      #4                  // Field backupMasters_:Ljava/util/List;
     227: invokeinterface #64,  1           // InterfaceMethod java/util/List.size:()I
     232: if_icmpge     260
     235: aload_1
     236: bipush        8
     238: aload_0
     239: getfield      #4                  // Field backupMasters_:Ljava/util/List;
     242: iload_2
     243: invokeinterface #65,  2           // InterfaceMethod java/util/List.get:(I)Ljava/lang/Object;
     248: checkcast     #101                // class com/google/protobuf/MessageLite
     251: invokevirtual #100                // Method com/google/protobuf/CodedOutputStream.writeMessage:(ILcom/google/protobuf/MessageLite;)V
     254: iinc          2, 1
     257: goto          222
     260: aload_0
     261: getfield      #2                  // Field bitField0_:I
     264: bipush        8
     266: iand
     267: bipush        8
     269: if_icmpne     282
     272: aload_1
     273: bipush        9
     275: aload_0
     276: getfield      #3                  // Field balancerOn_:Z
     279: invokevirtual #102                // Method com/google/protobuf/CodedOutputStream.writeBool:(IZ)V
     282: aload_0
     283: invokevirtual #103                // Method getUnknownFields:()Lcom/google/protobuf/UnknownFieldSet;
     286: aload_1
     287: invokevirtual #104                // Method com/google/protobuf/UnknownFieldSet.writeTo:(Lcom/google/protobuf/CodedOutputStream;)V
     290: return

  public int getSerializedSize();
    Code:
       0: aload_0
       1: getfield      #16                 // Field memoizedSerializedSize:I
       4: istore_1
       5: iload_1
       6: iconst_m1
       7: if_icmpeq     12
      10: iload_1
      11: ireturn
      12: iconst_0
      13: istore_1
      14: aload_0
      15: getfield      #2                  // Field bitField0_:I
      18: iconst_1
      19: iand
      20: iconst_1
      21: if_icmpne     35
      24: iload_1
      25: iconst_1
      26: aload_0
      27: getfield      #11                 // Field hbaseVersion_:Lorg/apache/hadoop/hbase/protobuf/generated/FSProtos$HBaseVersionFileContent;
      30: invokestatic  #105                // Method com/google/protobuf/CodedOutputStream.computeMessageSize:(ILcom/google/protobuf/MessageLite;)I
      33: iadd
      34: istore_1
      35: iconst_0
      36: istore_2
      37: iload_2
      38: aload_0
      39: getfield      #10                 // Field liveServers_:Ljava/util/List;
      42: invokeinterface #64,  1           // InterfaceMethod java/util/List.size:()I
      47: if_icmpge     76
      50: iload_1
      51: iconst_2
      52: aload_0
      53: getfield      #10                 // Field liveServers_:Ljava/util/List;
      56: iload_2
      57: invokeinterface #65,  2           // InterfaceMethod java/util/List.get:(I)Ljava/lang/Object;
      62: checkcast     #101                // class com/google/protobuf/MessageLite
      65: invokestatic  #105                // Method com/google/protobuf/CodedOutputStream.computeMessageSize:(ILcom/google/protobuf/MessageLite;)I
      68: iadd
      69: istore_1
      70: iinc          2, 1
      73: goto          37
      76: iconst_0
      77: istore_2
      78: iload_2
      79: aload_0
      80: getfield      #9                  // Field deadServers_:Ljava/util/List;
      83: invokeinterface #64,  1           // InterfaceMethod java/util/List.size:()I
      88: if_icmpge     117
      91: iload_1
      92: iconst_3
      93: aload_0
      94: getfield      #9                  // Field deadServers_:Ljava/util/List;
      97: iload_2
      98: invokeinterface #65,  2           // InterfaceMethod java/util/List.get:(I)Ljava/lang/Object;
     103: checkcast     #101                // class com/google/protobuf/MessageLite
     106: invokestatic  #105                // Method com/google/protobuf/CodedOutputStream.computeMessageSize:(ILcom/google/protobuf/MessageLite;)I
     109: iadd
     110: istore_1
     111: iinc          2, 1
     114: goto          78
     117: iconst_0
     118: istore_2
     119: iload_2
     120: aload_0
     121: getfield      #8                  // Field regionsInTransition_:Ljava/util/List;
     124: invokeinterface #64,  1           // InterfaceMethod java/util/List.size:()I
     129: if_icmpge     158
     132: iload_1
     133: iconst_4
     134: aload_0
     135: getfield      #8                  // Field regionsInTransition_:Ljava/util/List;
     138: iload_2
     139: invokeinterface #65,  2           // InterfaceMethod java/util/List.get:(I)Ljava/lang/Object;
     144: checkcast     #101                // class com/google/protobuf/MessageLite
     147: invokestatic  #105                // Method com/google/protobuf/CodedOutputStream.computeMessageSize:(ILcom/google/protobuf/MessageLite;)I
     150: iadd
     151: istore_1
     152: iinc          2, 1
     155: goto          119
     158: aload_0
     159: getfield      #2                  // Field bitField0_:I
     162: iconst_2
     163: iand
     164: iconst_2
     165: if_icmpne     179
     168: iload_1
     169: iconst_5
     170: aload_0
     171: getfield      #7                  // Field clusterId_:Lorg/apache/hadoop/hbase/protobuf/generated/ClusterIdProtos$ClusterId;
     174: invokestatic  #105                // Method com/google/protobuf/CodedOutputStream.computeMessageSize:(ILcom/google/protobuf/MessageLite;)I
     177: iadd
     178: istore_1
     179: iconst_0
     180: istore_2
     181: iload_2
     182: aload_0
     183: getfield      #6                  // Field masterCoprocessors_:Ljava/util/List;
     186: invokeinterface #64,  1           // InterfaceMethod java/util/List.size:()I
     191: if_icmpge     221
     194: iload_1
     195: bipush        6
     197: aload_0
     198: getfield      #6                  // Field masterCoprocessors_:Ljava/util/List;
     201: iload_2
     202: invokeinterface #65,  2           // InterfaceMethod java/util/List.get:(I)Ljava/lang/Object;
     207: checkcast     #101                // class com/google/protobuf/MessageLite
     210: invokestatic  #105                // Method com/google/protobuf/CodedOutputStream.computeMessageSize:(ILcom/google/protobuf/MessageLite;)I
     213: iadd
     214: istore_1
     215: iinc          2, 1
     218: goto          181
     221: aload_0
     222: getfield      #2                  // Field bitField0_:I
     225: iconst_4
     226: iand
     227: iconst_4
     228: if_icmpne     243
     231: iload_1
     232: bipush        7
     234: aload_0
     235: getfield      #5                  // Field master_:Lorg/apache/hadoop/hbase/protobuf/generated/HBaseProtos$ServerName;
     238: invokestatic  #105                // Method com/google/protobuf/CodedOutputStream.computeMessageSize:(ILcom/google/protobuf/MessageLite;)I
     241: iadd
     242: istore_1
     243: iconst_0
     244: istore_2
     245: iload_2
     246: aload_0
     247: getfield      #4                  // Field backupMasters_:Ljava/util/List;
     250: invokeinterface #64,  1           // InterfaceMethod java/util/List.size:()I
     255: if_icmpge     285
     258: iload_1
     259: bipush        8
     261: aload_0
     262: getfield      #4                  // Field backupMasters_:Ljava/util/List;
     265: iload_2
     266: invokeinterface #65,  2           // InterfaceMethod java/util/List.get:(I)Ljava/lang/Object;
     271: checkcast     #101                // class com/google/protobuf/MessageLite
     274: invokestatic  #105                // Method com/google/protobuf/CodedOutputStream.computeMessageSize:(ILcom/google/protobuf/MessageLite;)I
     277: iadd
     278: istore_1
     279: iinc          2, 1
     282: goto          245
     285: aload_0
     286: getfield      #2                  // Field bitField0_:I
     289: bipush        8
     291: iand
     292: bipush        8
     294: if_icmpne     309
     297: iload_1
     298: bipush        9
     300: aload_0
     301: getfield      #3                  // Field balancerOn_:Z
     304: invokestatic  #106                // Method com/google/protobuf/CodedOutputStream.computeBoolSize:(IZ)I
     307: iadd
     308: istore_1
     309: iload_1
     310: aload_0
     311: invokevirtual #103                // Method getUnknownFields:()Lcom/google/protobuf/UnknownFieldSet;
     314: invokevirtual #107                // Method com/google/protobuf/UnknownFieldSet.getSerializedSize:()I
     317: iadd
     318: istore_1
     319: aload_0
     320: iload_1
     321: putfield      #16                 // Field memoizedSerializedSize:I
     324: iload_1
     325: ireturn

  protected java.lang.Object writeReplace() throws java.io.ObjectStreamException;
    Code:
       0: aload_0
       1: invokespecial #108                // Method com/google/protobuf/GeneratedMessage.writeReplace:()Ljava/lang/Object;
       4: areturn

  public boolean equals(java.lang.Object);
    Code:
       0: aload_1
       1: aload_0
       2: if_acmpne     7
       5: iconst_1
       6: ireturn
       7: aload_1
       8: instanceof    #60                 // class org/apache/hadoop/hbase/protobuf/generated/ClusterStatusProtos$ClusterStatus
      11: ifne          20
      14: aload_0
      15: aload_1
      16: invokespecial #109                // Method com/google/protobuf/GeneratedMessage.equals:(Ljava/lang/Object;)Z
      19: ireturn
      20: aload_1
      21: checkcast     #60                 // class org/apache/hadoop/hbase/protobuf/generated/ClusterStatusProtos$ClusterStatus
      24: astore_2
      25: iconst_1
      26: istore_3
      27: iload_3
      28: ifeq          46
      31: aload_0
      32: invokevirtual #77                 // Method hasHbaseVersion:()Z
      35: aload_2
      36: invokevirtual #77                 // Method hasHbaseVersion:()Z
      39: if_icmpne     46
      42: iconst_1
      43: goto          47
      46: iconst_0
      47: istore_3
      48: aload_0
      49: invokevirtual #77                 // Method hasHbaseVersion:()Z
      52: ifeq          79
      55: iload_3
      56: ifeq          77
      59: aload_0
      60: invokevirtual #78                 // Method getHbaseVersion:()Lorg/apache/hadoop/hbase/protobuf/generated/FSProtos$HBaseVersionFileContent;
      63: aload_2
      64: invokevirtual #78                 // Method getHbaseVersion:()Lorg/apache/hadoop/hbase/protobuf/generated/FSProtos$HBaseVersionFileContent;
      67: invokevirtual #110                // Method org/apache/hadoop/hbase/protobuf/generated/FSProtos$HBaseVersionFileContent.equals:(Ljava/lang/Object;)Z
      70: ifeq          77
      73: iconst_1
      74: goto          78
      77: iconst_0
      78: istore_3
      79: iload_3
      80: ifeq          103
      83: aload_0
      84: invokevirtual #111                // Method getLiveServersList:()Ljava/util/List;
      87: aload_2
      88: invokevirtual #111                // Method getLiveServersList:()Ljava/util/List;
      91: invokeinterface #112,  2          // InterfaceMethod java/util/List.equals:(Ljava/lang/Object;)Z
      96: ifeq          103
      99: iconst_1
     100: goto          104
     103: iconst_0
     104: istore_3
     105: iload_3
     106: ifeq          129
     109: aload_0
     110: invokevirtual #113                // Method getDeadServersList:()Ljava/util/List;
     113: aload_2
     114: invokevirtual #113                // Method getDeadServersList:()Ljava/util/List;
     117: invokeinterface #112,  2          // InterfaceMethod java/util/List.equals:(Ljava/lang/Object;)Z
     122: ifeq          129
     125: iconst_1
     126: goto          130
     129: iconst_0
     130: istore_3
     131: iload_3
     132: ifeq          155
     135: aload_0
     136: invokevirtual #114                // Method getRegionsInTransitionList:()Ljava/util/List;
     139: aload_2
     140: invokevirtual #114                // Method getRegionsInTransitionList:()Ljava/util/List;
     143: invokeinterface #112,  2          // InterfaceMethod java/util/List.equals:(Ljava/lang/Object;)Z
     148: ifeq          155
     151: iconst_1
     152: goto          156
     155: iconst_0
     156: istore_3
     157: iload_3
     158: ifeq          176
     161: aload_0
     162: invokevirtual #89                 // Method hasClusterId:()Z
     165: aload_2
     166: invokevirtual #89                 // Method hasClusterId:()Z
     169: if_icmpne     176
     172: iconst_1
     173: goto          177
     176: iconst_0
     177: istore_3
     178: aload_0
     179: invokevirtual #89                 // Method hasClusterId:()Z
     182: ifeq          209
     185: iload_3
     186: ifeq          207
     189: aload_0
     190: invokevirtual #90                 // Method getClusterId:()Lorg/apache/hadoop/hbase/protobuf/generated/ClusterIdProtos$ClusterId;
     193: aload_2
     194: invokevirtual #90                 // Method getClusterId:()Lorg/apache/hadoop/hbase/protobuf/generated/ClusterIdProtos$ClusterId;
     197: invokevirtual #115                // Method org/apache/hadoop/hbase/protobuf/generated/ClusterIdProtos$ClusterId.equals:(Ljava/lang/Object;)Z
     200: ifeq          207
     203: iconst_1
     204: goto          208
     207: iconst_0
     208: istore_3
     209: iload_3
     210: ifeq          233
     213: aload_0
     214: invokevirtual #116                // Method getMasterCoprocessorsList:()Ljava/util/List;
     217: aload_2
     218: invokevirtual #116                // Method getMasterCoprocessorsList:()Ljava/util/List;
     221: invokeinterface #112,  2          // InterfaceMethod java/util/List.equals:(Ljava/lang/Object;)Z
     226: ifeq          233
     229: iconst_1
     230: goto          234
     233: iconst_0
     234: istore_3
     235: iload_3
     236: ifeq          254
     239: aload_0
     240: invokevirtual #95                 // Method hasMaster:()Z
     243: aload_2
     244: invokevirtual #95                 // Method hasMaster:()Z
     247: if_icmpne     254
     250: iconst_1
     251: goto          255
     254: iconst_0
     255: istore_3
     256: aload_0
     257: invokevirtual #95                 // Method hasMaster:()Z
     260: ifeq          287
     263: iload_3
     264: ifeq          285
     267: aload_0
     268: invokevirtual #96                 // Method getMaster:()Lorg/apache/hadoop/hbase/protobuf/generated/HBaseProtos$ServerName;
     271: aload_2
     272: invokevirtual #96                 // Method getMaster:()Lorg/apache/hadoop/hbase/protobuf/generated/HBaseProtos$ServerName;
     275: invokevirtual #117                // Method org/apache/hadoop/hbase/protobuf/generated/HBaseProtos$ServerName.equals:(Ljava/lang/Object;)Z
     278: ifeq          285
     281: iconst_1
     282: goto          286
     285: iconst_0
     286: istore_3
     287: iload_3
     288: ifeq          311
     291: aload_0
     292: invokevirtual #118                // Method getBackupMastersList:()Ljava/util/List;
     295: aload_2
     296: invokevirtual #118                // Method getBackupMastersList:()Ljava/util/List;
     299: invokeinterface #112,  2          // InterfaceMethod java/util/List.equals:(Ljava/lang/Object;)Z
     304: ifeq          311
     307: iconst_1
     308: goto          312
     311: iconst_0
     312: istore_3
     313: iload_3
     314: ifeq          332
     317: aload_0
     318: invokevirtual #119                // Method hasBalancerOn:()Z
     321: aload_2
     322: invokevirtual #119                // Method hasBalancerOn:()Z
     325: if_icmpne     332
     328: iconst_1
     329: goto          333
     332: iconst_0
     333: istore_3
     334: aload_0
     335: invokevirtual #119                // Method hasBalancerOn:()Z
     338: ifeq          362
     341: iload_3
     342: ifeq          360
     345: aload_0
     346: invokevirtual #120                // Method getBalancerOn:()Z
     349: aload_2
     350: invokevirtual #120                // Method getBalancerOn:()Z
     353: if_icmpne     360
     356: iconst_1
     357: goto          361
     360: iconst_0
     361: istore_3
     362: iload_3
     363: ifeq          384
     366: aload_0
     367: invokevirtual #103                // Method getUnknownFields:()Lcom/google/protobuf/UnknownFieldSet;
     370: aload_2
     371: invokevirtual #103                // Method getUnknownFields:()Lcom/google/protobuf/UnknownFieldSet;
     374: invokevirtual #121                // Method com/google/protobuf/UnknownFieldSet.equals:(Ljava/lang/Object;)Z
     377: ifeq          384
     380: iconst_1
     381: goto          385
     384: iconst_0
     385: istore_3
     386: iload_3
     387: ireturn

  public int hashCode();
    Code:
       0: aload_0
       1: getfield      #17                 // Field memoizedHashCode:I
       4: ifeq          12
       7: aload_0
       8: getfield      #17                 // Field memoizedHashCode:I
      11: ireturn
      12: bipush        41
      14: istore_1
      15: bipush        19
      17: iload_1
      18: imul
      19: aload_0
      20: invokevirtual #122                // Method getDescriptorForType:()Lcom/google/protobuf/Descriptors$Descriptor;
      23: invokevirtual #123                // Method java/lang/Object.hashCode:()I
      26: iadd
      27: istore_1
      28: aload_0
      29: invokevirtual #77                 // Method hasHbaseVersion:()Z
      32: ifeq          55
      35: bipush        37
      37: iload_1
      38: imul
      39: iconst_1
      40: iadd
      41: istore_1
      42: bipush        53
      44: iload_1
      45: imul
      46: aload_0
      47: invokevirtual #78                 // Method getHbaseVersion:()Lorg/apache/hadoop/hbase/protobuf/generated/FSProtos$HBaseVersionFileContent;
      50: invokevirtual #124                // Method org/apache/hadoop/hbase/protobuf/generated/FSProtos$HBaseVersionFileContent.hashCode:()I
      53: iadd
      54: istore_1
      55: aload_0
      56: invokevirtual #80                 // Method getLiveServersCount:()I
      59: ifle          84
      62: bipush        37
      64: iload_1
      65: imul
      66: iconst_2
      67: iadd
      68: istore_1
      69: bipush        53
      71: iload_1
      72: imul
      73: aload_0
      74: invokevirtual #111                // Method getLiveServersList:()Ljava/util/List;
      77: invokeinterface #125,  1          // InterfaceMethod java/util/List.hashCode:()I
      82: iadd
      83: istore_1
      84: aload_0
      85: invokevirtual #83                 // Method getDeadServersCount:()I
      88: ifle          113
      91: bipush        37
      93: iload_1
      94: imul
      95: iconst_3
      96: iadd
      97: istore_1
      98: bipush        53
     100: iload_1
     101: imul
     102: aload_0
     103: invokevirtual #113                // Method getDeadServersList:()Ljava/util/List;
     106: invokeinterface #125,  1          // InterfaceMethod java/util/List.hashCode:()I
     111: iadd
     112: istore_1
     113: aload_0
     114: invokevirtual #86                 // Method getRegionsInTransitionCount:()I
     117: ifle          142
     120: bipush        37
     122: iload_1
     123: imul
     124: iconst_4
     125: iadd
     126: istore_1
     127: bipush        53
     129: iload_1
     130: imul
     131: aload_0
     132: invokevirtual #114                // Method getRegionsInTransitionList:()Ljava/util/List;
     135: invokeinterface #125,  1          // InterfaceMethod java/util/List.hashCode:()I
     140: iadd
     141: istore_1
     142: aload_0
     143: invokevirtual #89                 // Method hasClusterId:()Z
     146: ifeq          169
     149: bipush        37
     151: iload_1
     152: imul
     153: iconst_5
     154: iadd
     155: istore_1
     156: bipush        53
     158: iload_1
     159: imul
     160: aload_0
     161: invokevirtual #90                 // Method getClusterId:()Lorg/apache/hadoop/hbase/protobuf/generated/ClusterIdProtos$ClusterId;
     164: invokevirtual #126                // Method org/apache/hadoop/hbase/protobuf/generated/ClusterIdProtos$ClusterId.hashCode:()I
     167: iadd
     168: istore_1
     169: aload_0
     170: invokevirtual #92                 // Method getMasterCoprocessorsCount:()I
     173: ifle          199
     176: bipush        37
     178: iload_1
     179: imul
     180: bipush        6
     182: iadd
     183: istore_1
     184: bipush        53
     186: iload_1
     187: imul
     188: aload_0
     189: invokevirtual #116                // Method getMasterCoprocessorsList:()Ljava/util/List;
     192: invokeinterface #125,  1          // InterfaceMethod java/util/List.hashCode:()I
     197: iadd
     198: istore_1
     199: aload_0
     200: invokevirtual #95                 // Method hasMaster:()Z
     203: ifeq          227
     206: bipush        37
     208: iload_1
     209: imul
     210: bipush        7
     212: iadd
     213: istore_1
     214: bipush        53
     216: iload_1
     217: imul
     218: aload_0
     219: invokevirtual #96                 // Method getMaster:()Lorg/apache/hadoop/hbase/protobuf/generated/HBaseProtos$ServerName;
     222: invokevirtual #127                // Method org/apache/hadoop/hbase/protobuf/generated/HBaseProtos$ServerName.hashCode:()I
     225: iadd
     226: istore_1
     227: aload_0
     228: invokevirtual #97                 // Method getBackupMastersCount:()I
     231: ifle          257
     234: bipush        37
     236: iload_1
     237: imul
     238: bipush        8
     240: iadd
     241: istore_1
     242: bipush        53
     244: iload_1
     245: imul
     246: aload_0
     247: invokevirtual #118                // Method getBackupMastersList:()Ljava/util/List;
     250: invokeinterface #125,  1          // InterfaceMethod java/util/List.hashCode:()I
     255: iadd
     256: istore_1
     257: aload_0
     258: invokevirtual #119                // Method hasBalancerOn:()Z
     261: ifeq          285
     264: bipush        37
     266: iload_1
     267: imul
     268: bipush        9
     270: iadd
     271: istore_1
     272: bipush        53
     274: iload_1
     275: imul
     276: aload_0
     277: invokevirtual #120                // Method getBalancerOn:()Z
     280: invokestatic  #128                // Method hashBoolean:(Z)I
     283: iadd
     284: istore_1
     285: bipush        29
     287: iload_1
     288: imul
     289: aload_0
     290: invokevirtual #103                // Method getUnknownFields:()Lcom/google/protobuf/UnknownFieldSet;
     293: invokevirtual #129                // Method com/google/protobuf/UnknownFieldSet.hashCode:()I
     296: iadd
     297: istore_1
     298: aload_0
     299: iload_1
     300: putfield      #17                 // Field memoizedHashCode:I
     303: iload_1
     304: ireturn

  public static org.apache.hadoop.hbase.protobuf.generated.ClusterStatusProtos$ClusterStatus parseFrom(com.google.protobuf.ByteString) throws com.google.protobuf.InvalidProtocolBufferException;
    Code:
       0: getstatic     #63                 // Field PARSER:Lcom/google/protobuf/Parser;
       3: aload_0
       4: invokeinterface #130,  2          // InterfaceMethod com/google/protobuf/Parser.parseFrom:(Lcom/google/protobuf/ByteString;)Ljava/lang/Object;
       9: checkcast     #60                 // class org/apache/hadoop/hbase/protobuf/generated/ClusterStatusProtos$ClusterStatus
      12: areturn

  public static org.apache.hadoop.hbase.protobuf.generated.ClusterStatusProtos$ClusterStatus parseFrom(com.google.protobuf.ByteString, com.google.protobuf.ExtensionRegistryLite) throws com.google.protobuf.InvalidProtocolBufferException;
    Code:
       0: getstatic     #63                 // Field PARSER:Lcom/google/protobuf/Parser;
       3: aload_0
       4: aload_1
       5: invokeinterface #131,  3          // InterfaceMethod com/google/protobuf/Parser.parseFrom:(Lcom/google/protobuf/ByteString;Lcom/google/protobuf/ExtensionRegistryLite;)Ljava/lang/Object;
      10: checkcast     #60                 // class org/apache/hadoop/hbase/protobuf/generated/ClusterStatusProtos$ClusterStatus
      13: areturn

  public static org.apache.hadoop.hbase.protobuf.generated.ClusterStatusProtos$ClusterStatus parseFrom(byte[]) throws com.google.protobuf.InvalidProtocolBufferException;
    Code:
       0: getstatic     #63                 // Field PARSER:Lcom/google/protobuf/Parser;
       3: aload_0
       4: invokeinterface #132,  2          // InterfaceMethod com/google/protobuf/Parser.parseFrom:([B)Ljava/lang/Object;
       9: checkcast     #60                 // class org/apache/hadoop/hbase/protobuf/generated/ClusterStatusProtos$ClusterStatus
      12: areturn

  public static org.apache.hadoop.hbase.protobuf.generated.ClusterStatusProtos$ClusterStatus parseFrom(byte[], com.google.protobuf.ExtensionRegistryLite) throws com.google.protobuf.InvalidProtocolBufferException;
    Code:
       0: getstatic     #63                 // Field PARSER:Lcom/google/protobuf/Parser;
       3: aload_0
       4: aload_1
       5: invokeinterface #133,  3          // InterfaceMethod com/google/protobuf/Parser.parseFrom:([BLcom/google/protobuf/ExtensionRegistryLite;)Ljava/lang/Object;
      10: checkcast     #60                 // class org/apache/hadoop/hbase/protobuf/generated/ClusterStatusProtos$ClusterStatus
      13: areturn

  public static org.apache.hadoop.hbase.protobuf.generated.ClusterStatusProtos$ClusterStatus parseFrom(java.io.InputStream) throws java.io.IOException;
    Code:
       0: getstatic     #63                 // Field PARSER:Lcom/google/protobuf/Parser;
       3: aload_0
       4: invokeinterface #134,  2          // InterfaceMethod com/google/protobuf/Parser.parseFrom:(Ljava/io/InputStream;)Ljava/lang/Object;
       9: checkcast     #60                 // class org/apache/hadoop/hbase/protobuf/generated/ClusterStatusProtos$ClusterStatus
      12: areturn

  public static org.apache.hadoop.hbase.protobuf.generated.ClusterStatusProtos$ClusterStatus parseFrom(java.io.InputStream, com.google.protobuf.ExtensionRegistryLite) throws java.io.IOException;
    Code:
       0: getstatic     #63                 // Field PARSER:Lcom/google/protobuf/Parser;
       3: aload_0
       4: aload_1
       5: invokeinterface #135,  3          // InterfaceMethod com/google/protobuf/Parser.parseFrom:(Ljava/io/InputStream;Lcom/google/protobuf/ExtensionRegistryLite;)Ljava/lang/Object;
      10: checkcast     #60                 // class org/apache/hadoop/hbase/protobuf/generated/ClusterStatusProtos$ClusterStatus
      13: areturn

  public static org.apache.hadoop.hbase.protobuf.generated.ClusterStatusProtos$ClusterStatus parseDelimitedFrom(java.io.InputStream) throws java.io.IOException;
    Code:
       0: getstatic     #63                 // Field PARSER:Lcom/google/protobuf/Parser;
       3: aload_0
       4: invokeinterface #136,  2          // InterfaceMethod com/google/protobuf/Parser.parseDelimitedFrom:(Ljava/io/InputStream;)Ljava/lang/Object;
       9: checkcast     #60                 // class org/apache/hadoop/hbase/protobuf/generated/ClusterStatusProtos$ClusterStatus
      12: areturn

  public static org.apache.hadoop.hbase.protobuf.generated.ClusterStatusProtos$ClusterStatus parseDelimitedFrom(java.io.InputStream, com.google.protobuf.ExtensionRegistryLite) throws java.io.IOException;
    Code:
       0: getstatic     #63                 // Field PARSER:Lcom/google/protobuf/Parser;
       3: aload_0
       4: aload_1
       5: invokeinterface #137,  3          // InterfaceMethod com/google/protobuf/Parser.parseDelimitedFrom:(Ljava/io/InputStream;Lcom/google/protobuf/ExtensionRegistryLite;)Ljava/lang/Object;
      10: checkcast     #60                 // class org/apache/hadoop/hbase/protobuf/generated/ClusterStatusProtos$ClusterStatus
      13: areturn

  public static org.apache.hadoop.hbase.protobuf.generated.ClusterStatusProtos$ClusterStatus parseFrom(com.google.protobuf.CodedInputStream) throws java.io.IOException;
    Code:
       0: getstatic     #63                 // Field PARSER:Lcom/google/protobuf/Parser;
       3: aload_0
       4: invokeinterface #138,  2          // InterfaceMethod com/google/protobuf/Parser.parseFrom:(Lcom/google/protobuf/CodedInputStream;)Ljava/lang/Object;
       9: checkcast     #60                 // class org/apache/hadoop/hbase/protobuf/generated/ClusterStatusProtos$ClusterStatus
      12: areturn

  public static org.apache.hadoop.hbase.protobuf.generated.ClusterStatusProtos$ClusterStatus parseFrom(com.google.protobuf.CodedInputStream, com.google.protobuf.ExtensionRegistryLite) throws java.io.IOException;
    Code:
       0: getstatic     #63                 // Field PARSER:Lcom/google/protobuf/Parser;
       3: aload_0
       4: aload_1
       5: invokeinterface #139,  3          // InterfaceMethod com/google/protobuf/Parser.parseFrom:(Lcom/google/protobuf/CodedInputStream;Lcom/google/protobuf/ExtensionRegistryLite;)Ljava/lang/Object;
      10: checkcast     #60                 // class org/apache/hadoop/hbase/protobuf/generated/ClusterStatusProtos$ClusterStatus
      13: areturn

  public static org.apache.hadoop.hbase.protobuf.generated.ClusterStatusProtos$ClusterStatus$Builder newBuilder();
    Code:
       0: invokestatic  #140                // Method org/apache/hadoop/hbase/protobuf/generated/ClusterStatusProtos$ClusterStatus$Builder.access$13000:()Lorg/apache/hadoop/hbase/protobuf/generated/ClusterStatusProtos$ClusterStatus$Builder;
       3: areturn

  public org.apache.hadoop.hbase.protobuf.generated.ClusterStatusProtos$ClusterStatus$Builder newBuilderForType();
    Code:
       0: invokestatic  #141                // Method newBuilder:()Lorg/apache/hadoop/hbase/protobuf/generated/ClusterStatusProtos$ClusterStatus$Builder;
       3: areturn

  public static org.apache.hadoop.hbase.protobuf.generated.ClusterStatusProtos$ClusterStatus$Builder newBuilder(org.apache.hadoop.hbase.protobuf.generated.ClusterStatusProtos$ClusterStatus);
    Code:
       0: invokestatic  #141                // Method newBuilder:()Lorg/apache/hadoop/hbase/protobuf/generated/ClusterStatusProtos$ClusterStatus$Builder;
       3: aload_0
       4: invokevirtual #142                // Method org/apache/hadoop/hbase/protobuf/generated/ClusterStatusProtos$ClusterStatus$Builder.mergeFrom:(Lorg/apache/hadoop/hbase/protobuf/generated/ClusterStatusProtos$ClusterStatus;)Lorg/apache/hadoop/hbase/protobuf/generated/ClusterStatusProtos$ClusterStatus$Builder;
       7: areturn

  public org.apache.hadoop.hbase.protobuf.generated.ClusterStatusProtos$ClusterStatus$Builder toBuilder();
    Code:
       0: aload_0
       1: invokestatic  #143                // Method newBuilder:(Lorg/apache/hadoop/hbase/protobuf/generated/ClusterStatusProtos$ClusterStatus;)Lorg/apache/hadoop/hbase/protobuf/generated/ClusterStatusProtos$ClusterStatus$Builder;
       4: areturn

  protected org.apache.hadoop.hbase.protobuf.generated.ClusterStatusProtos$ClusterStatus$Builder newBuilderForType(com.google.protobuf.GeneratedMessage$BuilderParent);
    Code:
       0: new           #61                 // class org/apache/hadoop/hbase/protobuf/generated/ClusterStatusProtos$ClusterStatus$Builder
       3: dup
       4: aload_1
       5: aconst_null
       6: invokespecial #144                // Method org/apache/hadoop/hbase/protobuf/generated/ClusterStatusProtos$ClusterStatus$Builder."<init>":(Lcom/google/protobuf/GeneratedMessage$BuilderParent;Lorg/apache/hadoop/hbase/protobuf/generated/ClusterStatusProtos$1;)V
       9: astore_2
      10: aload_2
      11: areturn

  protected com.google.protobuf.Message$Builder newBuilderForType(com.google.protobuf.GeneratedMessage$BuilderParent);
    Code:
       0: aload_0
       1: aload_1
       2: invokevirtual #145                // Method newBuilderForType:(Lcom/google/protobuf/GeneratedMessage$BuilderParent;)Lorg/apache/hadoop/hbase/protobuf/generated/ClusterStatusProtos$ClusterStatus$Builder;
       5: areturn

  public com.google.protobuf.Message$Builder toBuilder();
    Code:
       0: aload_0
       1: invokevirtual #146                // Method toBuilder:()Lorg/apache/hadoop/hbase/protobuf/generated/ClusterStatusProtos$ClusterStatus$Builder;
       4: areturn

  public com.google.protobuf.Message$Builder newBuilderForType();
    Code:
       0: aload_0
       1: invokevirtual #147                // Method newBuilderForType:()Lorg/apache/hadoop/hbase/protobuf/generated/ClusterStatusProtos$ClusterStatus$Builder;
       4: areturn

  public com.google.protobuf.MessageLite$Builder toBuilder();
    Code:
       0: aload_0
       1: invokevirtual #146                // Method toBuilder:()Lorg/apache/hadoop/hbase/protobuf/generated/ClusterStatusProtos$ClusterStatus$Builder;
       4: areturn

  public com.google.protobuf.MessageLite$Builder newBuilderForType();
    Code:
       0: aload_0
       1: invokevirtual #147                // Method newBuilderForType:()Lorg/apache/hadoop/hbase/protobuf/generated/ClusterStatusProtos$ClusterStatus$Builder;
       4: areturn

  public com.google.protobuf.MessageLite getDefaultInstanceForType();
    Code:
       0: aload_0
       1: invokevirtual #148                // Method getDefaultInstanceForType:()Lorg/apache/hadoop/hbase/protobuf/generated/ClusterStatusProtos$ClusterStatus;
       4: areturn

  public com.google.protobuf.Message getDefaultInstanceForType();
    Code:
       0: aload_0
       1: invokevirtual #148                // Method getDefaultInstanceForType:()Lorg/apache/hadoop/hbase/protobuf/generated/ClusterStatusProtos$ClusterStatus;
       4: areturn

  org.apache.hadoop.hbase.protobuf.generated.ClusterStatusProtos$ClusterStatus(com.google.protobuf.CodedInputStream, com.google.protobuf.ExtensionRegistryLite, org.apache.hadoop.hbase.protobuf.generated.ClusterStatusProtos$1) throws com.google.protobuf.InvalidProtocolBufferException;
    Code:
       0: aload_0
       1: aload_1
       2: aload_2
       3: invokespecial #13                 // Method "<init>":(Lcom/google/protobuf/CodedInputStream;Lcom/google/protobuf/ExtensionRegistryLite;)V
       6: return

  static boolean access$13200();
    Code:
       0: getstatic     #1                  // Field alwaysUseFieldBuilders:Z
       3: ireturn

  org.apache.hadoop.hbase.protobuf.generated.ClusterStatusProtos$ClusterStatus(com.google.protobuf.GeneratedMessage$Builder, org.apache.hadoop.hbase.protobuf.generated.ClusterStatusProtos$1);
    Code:
       0: aload_0
       1: aload_1
       2: invokespecial #12                 // Method "<init>":(Lcom/google/protobuf/GeneratedMessage$Builder;)V
       5: return

  static org.apache.hadoop.hbase.protobuf.generated.FSProtos$HBaseVersionFileContent access$13402(org.apache.hadoop.hbase.protobuf.generated.ClusterStatusProtos$ClusterStatus, org.apache.hadoop.hbase.protobuf.generated.FSProtos$HBaseVersionFileContent);
    Code:
       0: aload_0
       1: aload_1
       2: dup_x1
       3: putfield      #11                 // Field hbaseVersion_:Lorg/apache/hadoop/hbase/protobuf/generated/FSProtos$HBaseVersionFileContent;
       6: areturn

  static java.util.List access$13502(org.apache.hadoop.hbase.protobuf.generated.ClusterStatusProtos$ClusterStatus, java.util.List);
    Code:
       0: aload_0
       1: aload_1
       2: dup_x1
       3: putfield      #10                 // Field liveServers_:Ljava/util/List;
       6: areturn

  static java.util.List access$13602(org.apache.hadoop.hbase.protobuf.generated.ClusterStatusProtos$ClusterStatus, java.util.List);
    Code:
       0: aload_0
       1: aload_1
       2: dup_x1
       3: putfield      #9                  // Field deadServers_:Ljava/util/List;
       6: areturn

  static java.util.List access$13702(org.apache.hadoop.hbase.protobuf.generated.ClusterStatusProtos$ClusterStatus, java.util.List);
    Code:
       0: aload_0
       1: aload_1
       2: dup_x1
       3: putfield      #8                  // Field regionsInTransition_:Ljava/util/List;
       6: areturn

  static org.apache.hadoop.hbase.protobuf.generated.ClusterIdProtos$ClusterId access$13802(org.apache.hadoop.hbase.protobuf.generated.ClusterStatusProtos$ClusterStatus, org.apache.hadoop.hbase.protobuf.generated.ClusterIdProtos$ClusterId);
    Code:
       0: aload_0
       1: aload_1
       2: dup_x1
       3: putfield      #7                  // Field clusterId_:Lorg/apache/hadoop/hbase/protobuf/generated/ClusterIdProtos$ClusterId;
       6: areturn

  static java.util.List access$13902(org.apache.hadoop.hbase.protobuf.generated.ClusterStatusProtos$ClusterStatus, java.util.List);
    Code:
       0: aload_0
       1: aload_1
       2: dup_x1
       3: putfield      #6                  // Field masterCoprocessors_:Ljava/util/List;
       6: areturn

  static org.apache.hadoop.hbase.protobuf.generated.HBaseProtos$ServerName access$14002(org.apache.hadoop.hbase.protobuf.generated.ClusterStatusProtos$ClusterStatus, org.apache.hadoop.hbase.protobuf.generated.HBaseProtos$ServerName);
    Code:
       0: aload_0
       1: aload_1
       2: dup_x1
       3: putfield      #5                  // Field master_:Lorg/apache/hadoop/hbase/protobuf/generated/HBaseProtos$ServerName;
       6: areturn

  static java.util.List access$14102(org.apache.hadoop.hbase.protobuf.generated.ClusterStatusProtos$ClusterStatus, java.util.List);
    Code:
       0: aload_0
       1: aload_1
       2: dup_x1
       3: putfield      #4                  // Field backupMasters_:Ljava/util/List;
       6: areturn

  static boolean access$14202(org.apache.hadoop.hbase.protobuf.generated.ClusterStatusProtos$ClusterStatus, boolean);
    Code:
       0: aload_0
       1: iload_1
       2: dup_x1
       3: putfield      #3                  // Field balancerOn_:Z
       6: ireturn

  static int access$14302(org.apache.hadoop.hbase.protobuf.generated.ClusterStatusProtos$ClusterStatus, int);
    Code:
       0: aload_0
       1: iload_1
       2: dup_x1
       3: putfield      #2                  // Field bitField0_:I
       6: ireturn

  static java.util.List access$13500(org.apache.hadoop.hbase.protobuf.generated.ClusterStatusProtos$ClusterStatus);
    Code:
       0: aload_0
       1: getfield      #10                 // Field liveServers_:Ljava/util/List;
       4: areturn

  static boolean access$14400();
    Code:
       0: getstatic     #1                  // Field alwaysUseFieldBuilders:Z
       3: ireturn

  static java.util.List access$13600(org.apache.hadoop.hbase.protobuf.generated.ClusterStatusProtos$ClusterStatus);
    Code:
       0: aload_0
       1: getfield      #9                  // Field deadServers_:Ljava/util/List;
       4: areturn

  static boolean access$14500();
    Code:
       0: getstatic     #1                  // Field alwaysUseFieldBuilders:Z
       3: ireturn

  static java.util.List access$13700(org.apache.hadoop.hbase.protobuf.generated.ClusterStatusProtos$ClusterStatus);
    Code:
       0: aload_0
       1: getfield      #8                  // Field regionsInTransition_:Ljava/util/List;
       4: areturn

  static boolean access$14600();
    Code:
       0: getstatic     #1                  // Field alwaysUseFieldBuilders:Z
       3: ireturn

  static java.util.List access$13900(org.apache.hadoop.hbase.protobuf.generated.ClusterStatusProtos$ClusterStatus);
    Code:
       0: aload_0
       1: getfield      #6                  // Field masterCoprocessors_:Ljava/util/List;
       4: areturn

  static boolean access$14700();
    Code:
       0: getstatic     #1                  // Field alwaysUseFieldBuilders:Z
       3: ireturn

  static java.util.List access$14100(org.apache.hadoop.hbase.protobuf.generated.ClusterStatusProtos$ClusterStatus);
    Code:
       0: aload_0
       1: getfield      #4                  // Field backupMasters_:Ljava/util/List;
       4: areturn

  static boolean access$14800();
    Code:
       0: getstatic     #1                  // Field alwaysUseFieldBuilders:Z
       3: ireturn

  static {};
    Code:
       0: new           #149                // class org/apache/hadoop/hbase/protobuf/generated/ClusterStatusProtos$ClusterStatus$1
       3: dup
       4: invokespecial #150                // Method org/apache/hadoop/hbase/protobuf/generated/ClusterStatusProtos$ClusterStatus$1."<init>":()V
       7: putstatic     #63                 // Field PARSER:Lcom/google/protobuf/Parser;
      10: new           #60                 // class org/apache/hadoop/hbase/protobuf/generated/ClusterStatusProtos$ClusterStatus
      13: dup
      14: iconst_1
      15: invokespecial #151                // Method "<init>":(Z)V
      18: putstatic     #22                 // Field defaultInstance:Lorg/apache/hadoop/hbase/protobuf/generated/ClusterStatusProtos$ClusterStatus;
      21: getstatic     #22                 // Field defaultInstance:Lorg/apache/hadoop/hbase/protobuf/generated/ClusterStatusProtos$ClusterStatus;
      24: invokespecial #23                 // Method initFields:()V
      27: return
}
