Compiled from "ClusterStatusTracker.java"
public class org.apache.hadoop.hbase.zookeeper.ClusterStatusTracker extends org.apache.hadoop.hbase.zookeeper.ZKNodeTracker {
  public org.apache.hadoop.hbase.zookeeper.ClusterStatusTracker(org.apache.hadoop.hbase.zookeeper.ZKWatcher, org.apache.hadoop.hbase.Abortable);
    Code:
       0: aload_0
       1: aload_1
       2: aload_1
       3: invokevirtual #1                  // Method org/apache/hadoop/hbase/zookeeper/ZKWatcher.getZNodePaths:()Lorg/apache/hadoop/hbase/zookeeper/ZNodePaths;
       6: getfield      #2                  // Field org/apache/hadoop/hbase/zookeeper/ZNodePaths.clusterStateZNode:Ljava/lang/String;
       9: aload_2
      10: invokespecial #3                  // Method org/apache/hadoop/hbase/zookeeper/ZKNodeTracker."<init>":(Lorg/apache/hadoop/hbase/zookeeper/ZKWatcher;Ljava/lang/String;Lorg/apache/hadoop/hbase/Abortable;)V
      13: return

  public boolean isClusterUp();
    Code:
       0: aload_0
       1: iconst_0
       2: invokespecial #4                  // Method org/apache/hadoop/hbase/zookeeper/ZKNodeTracker.getData:(Z)[B
       5: ifnull        12
       8: iconst_1
       9: goto          13
      12: iconst_0
      13: ireturn

  public void setClusterUp() throws org.apache.zookeeper.KeeperException;
    Code:
       0: invokestatic  #5                  // Method toByteArray:()[B
       3: astore_1
       4: aload_0
       5: getfield      #6                  // Field watcher:Lorg/apache/hadoop/hbase/zookeeper/ZKWatcher;
       8: aload_0
       9: getfield      #6                  // Field watcher:Lorg/apache/hadoop/hbase/zookeeper/ZKWatcher;
      12: invokevirtual #1                  // Method org/apache/hadoop/hbase/zookeeper/ZKWatcher.getZNodePaths:()Lorg/apache/hadoop/hbase/zookeeper/ZNodePaths;
      15: getfield      #2                  // Field org/apache/hadoop/hbase/zookeeper/ZNodePaths.clusterStateZNode:Ljava/lang/String;
      18: aload_1
      19: invokestatic  #7                  // Method org/apache/hadoop/hbase/zookeeper/ZKUtil.createAndWatch:(Lorg/apache/hadoop/hbase/zookeeper/ZKWatcher;Ljava/lang/String;[B)I
      22: pop
      23: goto          45
      26: astore_2
      27: aload_0
      28: getfield      #6                  // Field watcher:Lorg/apache/hadoop/hbase/zookeeper/ZKWatcher;
      31: aload_0
      32: getfield      #6                  // Field watcher:Lorg/apache/hadoop/hbase/zookeeper/ZKWatcher;
      35: invokevirtual #1                  // Method org/apache/hadoop/hbase/zookeeper/ZKWatcher.getZNodePaths:()Lorg/apache/hadoop/hbase/zookeeper/ZNodePaths;
      38: getfield      #2                  // Field org/apache/hadoop/hbase/zookeeper/ZNodePaths.clusterStateZNode:Ljava/lang/String;
      41: aload_1
      42: invokestatic  #9                  // Method org/apache/hadoop/hbase/zookeeper/ZKUtil.setData:(Lorg/apache/hadoop/hbase/zookeeper/ZKWatcher;Ljava/lang/String;[B)V
      45: return
    Exception table:
       from    to  target type
           4    23    26   Class org/apache/zookeeper/KeeperException$NodeExistsException

  public void setClusterDown() throws org.apache.zookeeper.KeeperException;
    Code:
       0: aload_0
       1: getfield      #6                  // Field watcher:Lorg/apache/hadoop/hbase/zookeeper/ZKWatcher;
       4: aload_0
       5: getfield      #6                  // Field watcher:Lorg/apache/hadoop/hbase/zookeeper/ZKWatcher;
       8: invokevirtual #1                  // Method org/apache/hadoop/hbase/zookeeper/ZKWatcher.getZNodePaths:()Lorg/apache/hadoop/hbase/zookeeper/ZNodePaths;
      11: getfield      #2                  // Field org/apache/hadoop/hbase/zookeeper/ZNodePaths.clusterStateZNode:Ljava/lang/String;
      14: invokestatic  #10                 // Method org/apache/hadoop/hbase/zookeeper/ZKUtil.deleteNode:(Lorg/apache/hadoop/hbase/zookeeper/ZKWatcher;Ljava/lang/String;)V
      17: goto          62
      20: astore_1
      21: getstatic     #12                 // Field LOG:Lorg/slf4j/Logger;
      24: new           #13                 // class java/lang/StringBuilder
      27: dup
      28: invokespecial #14                 // Method java/lang/StringBuilder."<init>":()V
      31: ldc           #15                 // String Attempted to set cluster as down but already down, cluster state node (
      33: invokevirtual #16                 // Method java/lang/StringBuilder.append:(Ljava/lang/String;)Ljava/lang/StringBuilder;
      36: aload_0
      37: getfield      #6                  // Field watcher:Lorg/apache/hadoop/hbase/zookeeper/ZKWatcher;
      40: invokevirtual #1                  // Method org/apache/hadoop/hbase/zookeeper/ZKWatcher.getZNodePaths:()Lorg/apache/hadoop/hbase/zookeeper/ZNodePaths;
      43: getfield      #2                  // Field org/apache/hadoop/hbase/zookeeper/ZNodePaths.clusterStateZNode:Ljava/lang/String;
      46: invokevirtual #16                 // Method java/lang/StringBuilder.append:(Ljava/lang/String;)Ljava/lang/StringBuilder;
      49: ldc           #17                 // String ) not found
      51: invokevirtual #16                 // Method java/lang/StringBuilder.append:(Ljava/lang/String;)Ljava/lang/StringBuilder;
      54: invokevirtual #18                 // Method java/lang/StringBuilder.toString:()Ljava/lang/String;
      57: invokeinterface #19,  2           // InterfaceMethod org/slf4j/Logger.warn:(Ljava/lang/String;)V
      62: return
    Exception table:
       from    to  target type
           0    17    20   Class org/apache/zookeeper/KeeperException$NoNodeException

  static byte[] toByteArray();
    Code:
       0: invokestatic  #20                 // Method org/apache/hadoop/hbase/shaded/protobuf/generated/ZooKeeperProtos$ClusterUp.newBuilder:()Lorg/apache/hadoop/hbase/shaded/protobuf/generated/ZooKeeperProtos$ClusterUp$Builder;
       3: astore_0
       4: aload_0
       5: new           #21                 // class java/util/Date
       8: dup
       9: invokespecial #22                 // Method java/util/Date."<init>":()V
      12: invokevirtual #23                 // Method java/util/Date.toString:()Ljava/lang/String;
      15: invokevirtual #24                 // Method org/apache/hadoop/hbase/shaded/protobuf/generated/ZooKeeperProtos$ClusterUp$Builder.setStartDate:(Ljava/lang/String;)Lorg/apache/hadoop/hbase/shaded/protobuf/generated/ZooKeeperProtos$ClusterUp$Builder;
      18: pop
      19: aload_0
      20: invokevirtual #25                 // Method org/apache/hadoop/hbase/shaded/protobuf/generated/ZooKeeperProtos$ClusterUp$Builder.build:()Lorg/apache/hadoop/hbase/shaded/protobuf/generated/ZooKeeperProtos$ClusterUp;
      23: invokevirtual #26                 // Method org/apache/hadoop/hbase/shaded/protobuf/generated/ZooKeeperProtos$ClusterUp.toByteArray:()[B
      26: invokestatic  #27                 // Method org/apache/hadoop/hbase/shaded/protobuf/ProtobufUtil.prependPBMagic:([B)[B
      29: areturn

  static {};
    Code:
       0: ldc           #28                 // class org/apache/hadoop/hbase/zookeeper/ClusterStatusTracker
       2: invokestatic  #29                 // Method org/slf4j/LoggerFactory.getLogger:(Ljava/lang/Class;)Lorg/slf4j/Logger;
       5: putstatic     #12                 // Field LOG:Lorg/slf4j/Logger;
       8: return
}
