Compiled from "ClusterStatusPublisher.java"
public class org.apache.hadoop.hbase.master.ClusterStatusPublisher extends org.apache.hadoop.hbase.ScheduledChore {
  public static final java.lang.String STATUS_PUBLISHER_CLASS;

  public static final java.lang.Class<? extends org.apache.hadoop.hbase.master.ClusterStatusPublisher$Publisher> DEFAULT_STATUS_PUBLISHER_CLASS;

  public static final java.lang.String STATUS_PUBLISH_PERIOD;

  public static final int DEFAULT_STATUS_PUBLISH_PERIOD;

  public static final int MAX_SERVER_PER_MESSAGE;

  public static final int NB_SEND;

  public org.apache.hadoop.hbase.master.ClusterStatusPublisher(org.apache.hadoop.hbase.master.HMaster, org.apache.hadoop.conf.Configuration, java.lang.Class<? extends org.apache.hadoop.hbase.master.ClusterStatusPublisher$Publisher>) throws java.io.IOException;
    Code:
       0: aload_0
       1: new           #1                  // class java/lang/StringBuilder
       4: dup
       5: invokespecial #2                  // Method java/lang/StringBuilder."<init>":()V
       8: ldc           #3                  // String HBase clusterStatusPublisher for
      10: invokevirtual #4                  // Method java/lang/StringBuilder.append:(Ljava/lang/String;)Ljava/lang/StringBuilder;
      13: aload_1
      14: invokevirtual #5                  // Method org/apache/hadoop/hbase/master/HMaster.getName:()Ljava/lang/String;
      17: invokevirtual #4                  // Method java/lang/StringBuilder.append:(Ljava/lang/String;)Ljava/lang/StringBuilder;
      20: invokevirtual #6                  // Method java/lang/StringBuilder.toString:()Ljava/lang/String;
      23: aload_1
      24: aload_2
      25: ldc           #8                  // String hbase.status.publish.period
      27: sipush        10000
      30: invokevirtual #9                  // Method org/apache/hadoop/conf/Configuration.getInt:(Ljava/lang/String;I)I
      33: invokespecial #10                 // Method org/apache/hadoop/hbase/ScheduledChore."<init>":(Ljava/lang/String;Lorg/apache/hadoop/hbase/Stoppable;I)V
      36: aload_0
      37: lconst_0
      38: putfield      #11                 // Field lastMessageTime:J
      41: aload_0
      42: new           #12                 // class java/util/concurrent/ConcurrentHashMap
      45: dup
      46: invokespecial #13                 // Method java/util/concurrent/ConcurrentHashMap."<init>":()V
      49: putfield      #14                 // Field lastSent:Ljava/util/concurrent/ConcurrentMap;
      52: aload_0
      53: iconst_0
      54: putfield      #15                 // Field connected:Z
      57: aload_0
      58: aload_1
      59: putfield      #16                 // Field master:Lorg/apache/hadoop/hbase/master/HMaster;
      62: aload_0
      63: aload_2
      64: ldc           #8                  // String hbase.status.publish.period
      66: sipush        10000
      69: invokevirtual #9                  // Method org/apache/hadoop/conf/Configuration.getInt:(Ljava/lang/String;I)I
      72: putfield      #17                 // Field messagePeriod:I
      75: aload_0
      76: aload_3
      77: iconst_0
      78: anewarray     #18                 // class java/lang/Class
      81: invokevirtual #19                 // Method java/lang/Class.getDeclaredConstructor:([Ljava/lang/Class;)Ljava/lang/reflect/Constructor;
      84: iconst_0
      85: anewarray     #20                 // class java/lang/Object
      88: invokevirtual #21                 // Method java/lang/reflect/Constructor.newInstance:([Ljava/lang/Object;)Ljava/lang/Object;
      91: checkcast     #22                 // class org/apache/hadoop/hbase/master/ClusterStatusPublisher$Publisher
      94: putfield      #23                 // Field publisher:Lorg/apache/hadoop/hbase/master/ClusterStatusPublisher$Publisher;
      97: goto          134
     100: astore        4
     102: new           #25                 // class java/io/IOException
     105: dup
     106: new           #1                  // class java/lang/StringBuilder
     109: dup
     110: invokespecial #2                  // Method java/lang/StringBuilder."<init>":()V
     113: ldc           #26                 // String Can't create publisher
     115: invokevirtual #4                  // Method java/lang/StringBuilder.append:(Ljava/lang/String;)Ljava/lang/StringBuilder;
     118: aload_3
     119: invokevirtual #27                 // Method java/lang/Class.getName:()Ljava/lang/String;
     122: invokevirtual #4                  // Method java/lang/StringBuilder.append:(Ljava/lang/String;)Ljava/lang/StringBuilder;
     125: invokevirtual #6                  // Method java/lang/StringBuilder.toString:()Ljava/lang/String;
     128: aload         4
     130: invokespecial #28                 // Method java/io/IOException."<init>":(Ljava/lang/String;Ljava/lang/Throwable;)V
     133: athrow
     134: aload_0
     135: getfield      #23                 // Field publisher:Lorg/apache/hadoop/hbase/master/ClusterStatusPublisher$Publisher;
     138: aload_2
     139: invokeinterface #29,  2           // InterfaceMethod org/apache/hadoop/hbase/master/ClusterStatusPublisher$Publisher.connect:(Lorg/apache/hadoop/conf/Configuration;)V
     144: aload_0
     145: iconst_1
     146: putfield      #15                 // Field connected:Z
     149: return
    Exception table:
       from    to  target type
          75    97   100   Class java/lang/Exception

  protected org.apache.hadoop.hbase.master.ClusterStatusPublisher();
    Code:
       0: aload_0
       1: invokespecial #30                 // Method org/apache/hadoop/hbase/ScheduledChore."<init>":()V
       4: aload_0
       5: lconst_0
       6: putfield      #11                 // Field lastMessageTime:J
       9: aload_0
      10: new           #12                 // class java/util/concurrent/ConcurrentHashMap
      13: dup
      14: invokespecial #13                 // Method java/util/concurrent/ConcurrentHashMap."<init>":()V
      17: putfield      #14                 // Field lastSent:Ljava/util/concurrent/ConcurrentMap;
      20: aload_0
      21: iconst_0
      22: putfield      #15                 // Field connected:Z
      25: aload_0
      26: aconst_null
      27: putfield      #16                 // Field master:Lorg/apache/hadoop/hbase/master/HMaster;
      30: aload_0
      31: iconst_0
      32: putfield      #17                 // Field messagePeriod:I
      35: return

  protected void chore();
    Code:
       0: aload_0
       1: invokespecial #31                 // Method isConnected:()Z
       4: ifne          8
       7: return
       8: aload_0
       9: invokevirtual #32                 // Method generateDeadServersListToSend:()Ljava/util/List;
      12: astore_1
      13: aload_1
      14: invokeinterface #33,  1           // InterfaceMethod java/util/List.isEmpty:()Z
      19: ifeq          23
      22: return
      23: invokestatic  #34                 // Method org/apache/hadoop/hbase/util/EnvironmentEdgeManager.currentTime:()J
      26: lstore_2
      27: aload_0
      28: getfield      #11                 // Field lastMessageTime:J
      31: lload_2
      32: aload_0
      33: getfield      #17                 // Field messagePeriod:I
      36: i2l
      37: lsub
      38: lcmp
      39: ifle          43
      42: return
      43: aload_0
      44: lload_2
      45: putfield      #11                 // Field lastMessageTime:J
      48: aload_0
      49: getfield      #23                 // Field publisher:Lorg/apache/hadoop/hbase/master/ClusterStatusPublisher$Publisher;
      52: invokestatic  #35                 // Method org/apache/hadoop/hbase/ClusterMetricsBuilder.newBuilder:()Lorg/apache/hadoop/hbase/ClusterMetricsBuilder;
      55: invokestatic  #36                 // Method org/apache/hadoop/hbase/util/VersionInfo.getVersion:()Ljava/lang/String;
      58: invokevirtual #37                 // Method org/apache/hadoop/hbase/ClusterMetricsBuilder.setHBaseVersion:(Ljava/lang/String;)Lorg/apache/hadoop/hbase/ClusterMetricsBuilder;
      61: aload_0
      62: getfield      #16                 // Field master:Lorg/apache/hadoop/hbase/master/HMaster;
      65: invokevirtual #38                 // Method org/apache/hadoop/hbase/master/HMaster.getMasterFileSystem:()Lorg/apache/hadoop/hbase/master/MasterFileSystem;
      68: invokevirtual #39                 // Method org/apache/hadoop/hbase/master/MasterFileSystem.getClusterId:()Lorg/apache/hadoop/hbase/ClusterId;
      71: invokevirtual #40                 // Method org/apache/hadoop/hbase/ClusterId.toString:()Ljava/lang/String;
      74: invokevirtual #41                 // Method org/apache/hadoop/hbase/ClusterMetricsBuilder.setClusterId:(Ljava/lang/String;)Lorg/apache/hadoop/hbase/ClusterMetricsBuilder;
      77: aload_0
      78: getfield      #16                 // Field master:Lorg/apache/hadoop/hbase/master/HMaster;
      81: invokevirtual #42                 // Method org/apache/hadoop/hbase/master/HMaster.getServerName:()Lorg/apache/hadoop/hbase/ServerName;
      84: invokevirtual #43                 // Method org/apache/hadoop/hbase/ClusterMetricsBuilder.setMasterName:(Lorg/apache/hadoop/hbase/ServerName;)Lorg/apache/hadoop/hbase/ClusterMetricsBuilder;
      87: aload_1
      88: invokevirtual #44                 // Method org/apache/hadoop/hbase/ClusterMetricsBuilder.setDeadServerNames:(Ljava/util/List;)Lorg/apache/hadoop/hbase/ClusterMetricsBuilder;
      91: invokevirtual #45                 // Method org/apache/hadoop/hbase/ClusterMetricsBuilder.build:()Lorg/apache/hadoop/hbase/ClusterMetrics;
      94: invokeinterface #46,  2           // InterfaceMethod org/apache/hadoop/hbase/master/ClusterStatusPublisher$Publisher.publish:(Lorg/apache/hadoop/hbase/ClusterMetrics;)V
      99: return

  protected synchronized void cleanup();
    Code:
       0: aload_0
       1: iconst_0
       2: putfield      #15                 // Field connected:Z
       5: aload_0
       6: getfield      #23                 // Field publisher:Lorg/apache/hadoop/hbase/master/ClusterStatusPublisher$Publisher;
       9: invokeinterface #47,  1           // InterfaceMethod org/apache/hadoop/hbase/master/ClusterStatusPublisher$Publisher.close:()V
      14: return

  protected java.util.List<org.apache.hadoop.hbase.ServerName> generateDeadServersListToSend();
    Code:
       0: invokestatic  #34                 // Method org/apache/hadoop/hbase/util/EnvironmentEdgeManager.currentTime:()J
       3: aload_0
       4: getfield      #17                 // Field messagePeriod:I
       7: iconst_2
       8: imul
       9: i2l
      10: lsub
      11: lstore_1
      12: aload_0
      13: lload_1
      14: invokevirtual #48                 // Method getDeadServers:(J)Ljava/util/List;
      17: invokeinterface #49,  1           // InterfaceMethod java/util/List.iterator:()Ljava/util/Iterator;
      22: astore_3
      23: aload_3
      24: invokeinterface #50,  1           // InterfaceMethod java/util/Iterator.hasNext:()Z
      29: ifeq          65
      32: aload_3
      33: invokeinterface #51,  1           // InterfaceMethod java/util/Iterator.next:()Ljava/lang/Object;
      38: checkcast     #52                 // class org/apache/hadoop/hbase/util/Pair
      41: astore        4
      43: aload_0
      44: getfield      #14                 // Field lastSent:Ljava/util/concurrent/ConcurrentMap;
      47: aload         4
      49: invokevirtual #53                 // Method org/apache/hadoop/hbase/util/Pair.getFirst:()Ljava/lang/Object;
      52: iconst_0
      53: invokestatic  #54                 // Method java/lang/Integer.valueOf:(I)Ljava/lang/Integer;
      56: invokeinterface #55,  3           // InterfaceMethod java/util/concurrent/ConcurrentMap.putIfAbsent:(Ljava/lang/Object;Ljava/lang/Object;)Ljava/lang/Object;
      61: pop
      62: goto          23
      65: new           #56                 // class java/util/ArrayList
      68: dup
      69: aload_0
      70: getfield      #14                 // Field lastSent:Ljava/util/concurrent/ConcurrentMap;
      73: invokeinterface #57,  1           // InterfaceMethod java/util/concurrent/ConcurrentMap.entrySet:()Ljava/util/Set;
      78: invokespecial #58                 // Method java/util/ArrayList."<init>":(Ljava/util/Collection;)V
      81: astore_3
      82: aload_3
      83: new           #59                 // class org/apache/hadoop/hbase/master/ClusterStatusPublisher$1
      86: dup
      87: aload_0
      88: invokespecial #60                 // Method org/apache/hadoop/hbase/master/ClusterStatusPublisher$1."<init>":(Lorg/apache/hadoop/hbase/master/ClusterStatusPublisher;)V
      91: invokestatic  #61                 // Method java/util/Collections.sort:(Ljava/util/List;Ljava/util/Comparator;)V
      94: aload_3
      95: invokeinterface #62,  1           // InterfaceMethod java/util/List.size:()I
     100: bipush        10
     102: if_icmple     110
     105: bipush        10
     107: goto          116
     110: aload_3
     111: invokeinterface #62,  1           // InterfaceMethod java/util/List.size:()I
     116: istore        4
     118: new           #56                 // class java/util/ArrayList
     121: dup
     122: iload         4
     124: invokespecial #63                 // Method java/util/ArrayList."<init>":(I)V
     127: astore        5
     129: iconst_0
     130: istore        6
     132: iload         6
     134: iload         4
     136: if_icmpge     252
     139: aload_3
     140: iload         6
     142: invokeinterface #64,  2           // InterfaceMethod java/util/List.get:(I)Ljava/lang/Object;
     147: checkcast     #65                 // class java/util/Map$Entry
     150: astore        7
     152: aload         7
     154: invokeinterface #66,  1           // InterfaceMethod java/util/Map$Entry.getValue:()Ljava/lang/Object;
     159: checkcast     #67                 // class java/lang/Integer
     162: invokevirtual #68                 // Method java/lang/Integer.intValue:()I
     165: iconst_4
     166: if_icmplt     189
     169: aload_0
     170: getfield      #14                 // Field lastSent:Ljava/util/concurrent/ConcurrentMap;
     173: aload         7
     175: invokeinterface #69,  1           // InterfaceMethod java/util/Map$Entry.getKey:()Ljava/lang/Object;
     180: invokeinterface #70,  2           // InterfaceMethod java/util/concurrent/ConcurrentMap.remove:(Ljava/lang/Object;)Ljava/lang/Object;
     185: pop
     186: goto          231
     189: aload_0
     190: getfield      #14                 // Field lastSent:Ljava/util/concurrent/ConcurrentMap;
     193: aload         7
     195: invokeinterface #69,  1           // InterfaceMethod java/util/Map$Entry.getKey:()Ljava/lang/Object;
     200: aload         7
     202: invokeinterface #66,  1           // InterfaceMethod java/util/Map$Entry.getValue:()Ljava/lang/Object;
     207: aload         7
     209: invokeinterface #66,  1           // InterfaceMethod java/util/Map$Entry.getValue:()Ljava/lang/Object;
     214: checkcast     #67                 // class java/lang/Integer
     217: invokevirtual #68                 // Method java/lang/Integer.intValue:()I
     220: iconst_1
     221: iadd
     222: invokestatic  #54                 // Method java/lang/Integer.valueOf:(I)Ljava/lang/Integer;
     225: invokeinterface #71,  4           // InterfaceMethod java/util/concurrent/ConcurrentMap.replace:(Ljava/lang/Object;Ljava/lang/Object;Ljava/lang/Object;)Z
     230: pop
     231: aload         5
     233: aload         7
     235: invokeinterface #69,  1           // InterfaceMethod java/util/Map$Entry.getKey:()Ljava/lang/Object;
     240: invokeinterface #72,  2           // InterfaceMethod java/util/List.add:(Ljava/lang/Object;)Z
     245: pop
     246: iinc          6, 1
     249: goto          132
     252: aload         5
     254: areturn

  protected java.util.List<org.apache.hadoop.hbase.util.Pair<org.apache.hadoop.hbase.ServerName, java.lang.Long>> getDeadServers(long);
    Code:
       0: aload_0
       1: getfield      #16                 // Field master:Lorg/apache/hadoop/hbase/master/HMaster;
       4: invokevirtual #73                 // Method org/apache/hadoop/hbase/master/HMaster.getServerManager:()Lorg/apache/hadoop/hbase/master/ServerManager;
       7: ifnonnull     14
      10: invokestatic  #74                 // Method java/util/Collections.emptyList:()Ljava/util/List;
      13: areturn
      14: aload_0
      15: getfield      #16                 // Field master:Lorg/apache/hadoop/hbase/master/HMaster;
      18: invokevirtual #73                 // Method org/apache/hadoop/hbase/master/HMaster.getServerManager:()Lorg/apache/hadoop/hbase/master/ServerManager;
      21: invokevirtual #75                 // Method org/apache/hadoop/hbase/master/ServerManager.getDeadServers:()Lorg/apache/hadoop/hbase/master/DeadServer;
      24: lload_1
      25: invokevirtual #76                 // Method org/apache/hadoop/hbase/master/DeadServer.copyDeadServersSince:(J)Ljava/util/List;
      28: areturn

  static {};
    Code:
       0: ldc           #77                 // class org/apache/hadoop/hbase/master/ClusterStatusPublisher$MulticastPublisher
       2: putstatic     #78                 // Field DEFAULT_STATUS_PUBLISHER_CLASS:Ljava/lang/Class;
       5: return
}
