Compiled from "CombinedBlockCache.java"
public class org.apache.hadoop.hbase.io.hfile.CombinedBlockCache implements org.apache.hadoop.hbase.io.hfile.ResizableBlockCache,org.apache.hadoop.hbase.io.HeapSize {
  protected final org.apache.hadoop.hbase.io.hfile.FirstLevelBlockCache l1Cache;

  protected final org.apache.hadoop.hbase.io.hfile.BlockCache l2Cache;

  protected final org.apache.hadoop.hbase.io.hfile.CombinedBlockCache$CombinedCacheStats combinedCacheStats;

  public org.apache.hadoop.hbase.io.hfile.CombinedBlockCache(org.apache.hadoop.hbase.io.hfile.FirstLevelBlockCache, org.apache.hadoop.hbase.io.hfile.BlockCache);
    Code:
       0: aload_0
       1: invokespecial #1                  // Method java/lang/Object."<init>":()V
       4: aload_0
       5: aload_1
       6: putfield      #2                  // Field l1Cache:Lorg/apache/hadoop/hbase/io/hfile/FirstLevelBlockCache;
       9: aload_0
      10: aload_2
      11: putfield      #3                  // Field l2Cache:Lorg/apache/hadoop/hbase/io/hfile/BlockCache;
      14: aload_0
      15: new           #4                  // class org/apache/hadoop/hbase/io/hfile/CombinedBlockCache$CombinedCacheStats
      18: dup
      19: aload_1
      20: invokeinterface #5,  1            // InterfaceMethod org/apache/hadoop/hbase/io/hfile/FirstLevelBlockCache.getStats:()Lorg/apache/hadoop/hbase/io/hfile/CacheStats;
      25: aload_2
      26: invokeinterface #6,  1            // InterfaceMethod org/apache/hadoop/hbase/io/hfile/BlockCache.getStats:()Lorg/apache/hadoop/hbase/io/hfile/CacheStats;
      31: invokespecial #7                  // Method org/apache/hadoop/hbase/io/hfile/CombinedBlockCache$CombinedCacheStats."<init>":(Lorg/apache/hadoop/hbase/io/hfile/CacheStats;Lorg/apache/hadoop/hbase/io/hfile/CacheStats;)V
      34: putfield      #8                  // Field combinedCacheStats:Lorg/apache/hadoop/hbase/io/hfile/CombinedBlockCache$CombinedCacheStats;
      37: return

  public long heapSize();
    Code:
       0: lconst_0
       1: lstore_1
       2: aload_0
       3: getfield      #3                  // Field l2Cache:Lorg/apache/hadoop/hbase/io/hfile/BlockCache;
       6: instanceof    #9                  // class org/apache/hadoop/hbase/io/HeapSize
       9: ifeq          25
      12: aload_0
      13: getfield      #3                  // Field l2Cache:Lorg/apache/hadoop/hbase/io/hfile/BlockCache;
      16: checkcast     #9                  // class org/apache/hadoop/hbase/io/HeapSize
      19: invokeinterface #10,  1           // InterfaceMethod org/apache/hadoop/hbase/io/HeapSize.heapSize:()J
      24: lstore_1
      25: aload_0
      26: getfield      #2                  // Field l1Cache:Lorg/apache/hadoop/hbase/io/hfile/FirstLevelBlockCache;
      29: invokeinterface #11,  1           // InterfaceMethod org/apache/hadoop/hbase/io/hfile/FirstLevelBlockCache.heapSize:()J
      34: lload_1
      35: ladd
      36: lreturn

  public void cacheBlock(org.apache.hadoop.hbase.io.hfile.BlockCacheKey, org.apache.hadoop.hbase.io.hfile.Cacheable, boolean);
    Code:
       0: aload_2
       1: invokeinterface #12,  1           // InterfaceMethod org/apache/hadoop/hbase/io/hfile/Cacheable.getBlockType:()Lorg/apache/hadoop/hbase/io/hfile/BlockType;
       6: invokevirtual #13                 // Method org/apache/hadoop/hbase/io/hfile/BlockType.getCategory:()Lorg/apache/hadoop/hbase/io/hfile/BlockType$BlockCategory;
       9: getstatic     #14                 // Field org/apache/hadoop/hbase/io/hfile/BlockType$BlockCategory.DATA:Lorg/apache/hadoop/hbase/io/hfile/BlockType$BlockCategory;
      12: if_acmpeq     19
      15: iconst_1
      16: goto          20
      19: iconst_0
      20: istore        4
      22: iload         4
      24: ifeq          42
      27: aload_0
      28: getfield      #2                  // Field l1Cache:Lorg/apache/hadoop/hbase/io/hfile/FirstLevelBlockCache;
      31: aload_1
      32: aload_2
      33: iload_3
      34: invokeinterface #15,  4           // InterfaceMethod org/apache/hadoop/hbase/io/hfile/FirstLevelBlockCache.cacheBlock:(Lorg/apache/hadoop/hbase/io/hfile/BlockCacheKey;Lorg/apache/hadoop/hbase/io/hfile/Cacheable;Z)V
      39: goto          54
      42: aload_0
      43: getfield      #3                  // Field l2Cache:Lorg/apache/hadoop/hbase/io/hfile/BlockCache;
      46: aload_1
      47: aload_2
      48: iload_3
      49: invokeinterface #16,  4           // InterfaceMethod org/apache/hadoop/hbase/io/hfile/BlockCache.cacheBlock:(Lorg/apache/hadoop/hbase/io/hfile/BlockCacheKey;Lorg/apache/hadoop/hbase/io/hfile/Cacheable;Z)V
      54: return

  public void cacheBlock(org.apache.hadoop.hbase.io.hfile.BlockCacheKey, org.apache.hadoop.hbase.io.hfile.Cacheable);
    Code:
       0: aload_0
       1: aload_1
       2: aload_2
       3: iconst_0
       4: invokevirtual #17                 // Method cacheBlock:(Lorg/apache/hadoop/hbase/io/hfile/BlockCacheKey;Lorg/apache/hadoop/hbase/io/hfile/Cacheable;Z)V
       7: return

  public org.apache.hadoop.hbase.io.hfile.Cacheable getBlock(org.apache.hadoop.hbase.io.hfile.BlockCacheKey, boolean, boolean, boolean);
    Code:
       0: aload_0
       1: getfield      #2                  // Field l1Cache:Lorg/apache/hadoop/hbase/io/hfile/FirstLevelBlockCache;
       4: aload_1
       5: invokeinterface #18,  2           // InterfaceMethod org/apache/hadoop/hbase/io/hfile/FirstLevelBlockCache.containsBlock:(Lorg/apache/hadoop/hbase/io/hfile/BlockCacheKey;)Z
      10: ifeq          30
      13: aload_0
      14: getfield      #2                  // Field l1Cache:Lorg/apache/hadoop/hbase/io/hfile/FirstLevelBlockCache;
      17: aload_1
      18: iload_2
      19: iload_3
      20: iload         4
      22: invokeinterface #19,  5           // InterfaceMethod org/apache/hadoop/hbase/io/hfile/FirstLevelBlockCache.getBlock:(Lorg/apache/hadoop/hbase/io/hfile/BlockCacheKey;ZZZ)Lorg/apache/hadoop/hbase/io/hfile/Cacheable;
      27: goto          44
      30: aload_0
      31: getfield      #3                  // Field l2Cache:Lorg/apache/hadoop/hbase/io/hfile/BlockCache;
      34: aload_1
      35: iload_2
      36: iload_3
      37: iload         4
      39: invokeinterface #20,  5           // InterfaceMethod org/apache/hadoop/hbase/io/hfile/BlockCache.getBlock:(Lorg/apache/hadoop/hbase/io/hfile/BlockCacheKey;ZZZ)Lorg/apache/hadoop/hbase/io/hfile/Cacheable;
      44: areturn

  public boolean evictBlock(org.apache.hadoop.hbase.io.hfile.BlockCacheKey);
    Code:
       0: aload_0
       1: getfield      #2                  // Field l1Cache:Lorg/apache/hadoop/hbase/io/hfile/FirstLevelBlockCache;
       4: aload_1
       5: invokeinterface #21,  2           // InterfaceMethod org/apache/hadoop/hbase/io/hfile/FirstLevelBlockCache.evictBlock:(Lorg/apache/hadoop/hbase/io/hfile/BlockCacheKey;)Z
      10: ifne          26
      13: aload_0
      14: getfield      #3                  // Field l2Cache:Lorg/apache/hadoop/hbase/io/hfile/BlockCache;
      17: aload_1
      18: invokeinterface #22,  2           // InterfaceMethod org/apache/hadoop/hbase/io/hfile/BlockCache.evictBlock:(Lorg/apache/hadoop/hbase/io/hfile/BlockCacheKey;)Z
      23: ifeq          30
      26: iconst_1
      27: goto          31
      30: iconst_0
      31: ireturn

  public int evictBlocksByHfileName(java.lang.String);
    Code:
       0: aload_0
       1: getfield      #2                  // Field l1Cache:Lorg/apache/hadoop/hbase/io/hfile/FirstLevelBlockCache;
       4: aload_1
       5: invokeinterface #23,  2           // InterfaceMethod org/apache/hadoop/hbase/io/hfile/FirstLevelBlockCache.evictBlocksByHfileName:(Ljava/lang/String;)I
      10: aload_0
      11: getfield      #3                  // Field l2Cache:Lorg/apache/hadoop/hbase/io/hfile/BlockCache;
      14: aload_1
      15: invokeinterface #24,  2           // InterfaceMethod org/apache/hadoop/hbase/io/hfile/BlockCache.evictBlocksByHfileName:(Ljava/lang/String;)I
      20: iadd
      21: ireturn

  public org.apache.hadoop.hbase.io.hfile.CacheStats getStats();
    Code:
       0: aload_0
       1: getfield      #8                  // Field combinedCacheStats:Lorg/apache/hadoop/hbase/io/hfile/CombinedBlockCache$CombinedCacheStats;
       4: areturn

  public void shutdown();
    Code:
       0: aload_0
       1: getfield      #2                  // Field l1Cache:Lorg/apache/hadoop/hbase/io/hfile/FirstLevelBlockCache;
       4: invokeinterface #25,  1           // InterfaceMethod org/apache/hadoop/hbase/io/hfile/FirstLevelBlockCache.shutdown:()V
       9: aload_0
      10: getfield      #3                  // Field l2Cache:Lorg/apache/hadoop/hbase/io/hfile/BlockCache;
      13: invokeinterface #26,  1           // InterfaceMethod org/apache/hadoop/hbase/io/hfile/BlockCache.shutdown:()V
      18: return

  public long size();
    Code:
       0: aload_0
       1: getfield      #2                  // Field l1Cache:Lorg/apache/hadoop/hbase/io/hfile/FirstLevelBlockCache;
       4: invokeinterface #27,  1           // InterfaceMethod org/apache/hadoop/hbase/io/hfile/FirstLevelBlockCache.size:()J
       9: aload_0
      10: getfield      #3                  // Field l2Cache:Lorg/apache/hadoop/hbase/io/hfile/BlockCache;
      13: invokeinterface #28,  1           // InterfaceMethod org/apache/hadoop/hbase/io/hfile/BlockCache.size:()J
      18: ladd
      19: lreturn

  public long getMaxSize();
    Code:
       0: aload_0
       1: getfield      #2                  // Field l1Cache:Lorg/apache/hadoop/hbase/io/hfile/FirstLevelBlockCache;
       4: invokeinterface #29,  1           // InterfaceMethod org/apache/hadoop/hbase/io/hfile/FirstLevelBlockCache.getMaxSize:()J
       9: aload_0
      10: getfield      #3                  // Field l2Cache:Lorg/apache/hadoop/hbase/io/hfile/BlockCache;
      13: invokeinterface #30,  1           // InterfaceMethod org/apache/hadoop/hbase/io/hfile/BlockCache.getMaxSize:()J
      18: ladd
      19: lreturn

  public long getCurrentDataSize();
    Code:
       0: aload_0
       1: getfield      #2                  // Field l1Cache:Lorg/apache/hadoop/hbase/io/hfile/FirstLevelBlockCache;
       4: invokeinterface #31,  1           // InterfaceMethod org/apache/hadoop/hbase/io/hfile/FirstLevelBlockCache.getCurrentDataSize:()J
       9: aload_0
      10: getfield      #3                  // Field l2Cache:Lorg/apache/hadoop/hbase/io/hfile/BlockCache;
      13: invokeinterface #32,  1           // InterfaceMethod org/apache/hadoop/hbase/io/hfile/BlockCache.getCurrentDataSize:()J
      18: ladd
      19: lreturn

  public long getFreeSize();
    Code:
       0: aload_0
       1: getfield      #2                  // Field l1Cache:Lorg/apache/hadoop/hbase/io/hfile/FirstLevelBlockCache;
       4: invokeinterface #33,  1           // InterfaceMethod org/apache/hadoop/hbase/io/hfile/FirstLevelBlockCache.getFreeSize:()J
       9: aload_0
      10: getfield      #3                  // Field l2Cache:Lorg/apache/hadoop/hbase/io/hfile/BlockCache;
      13: invokeinterface #34,  1           // InterfaceMethod org/apache/hadoop/hbase/io/hfile/BlockCache.getFreeSize:()J
      18: ladd
      19: lreturn

  public long getCurrentSize();
    Code:
       0: aload_0
       1: getfield      #2                  // Field l1Cache:Lorg/apache/hadoop/hbase/io/hfile/FirstLevelBlockCache;
       4: invokeinterface #35,  1           // InterfaceMethod org/apache/hadoop/hbase/io/hfile/FirstLevelBlockCache.getCurrentSize:()J
       9: aload_0
      10: getfield      #3                  // Field l2Cache:Lorg/apache/hadoop/hbase/io/hfile/BlockCache;
      13: invokeinterface #36,  1           // InterfaceMethod org/apache/hadoop/hbase/io/hfile/BlockCache.getCurrentSize:()J
      18: ladd
      19: lreturn

  public long getBlockCount();
    Code:
       0: aload_0
       1: getfield      #2                  // Field l1Cache:Lorg/apache/hadoop/hbase/io/hfile/FirstLevelBlockCache;
       4: invokeinterface #37,  1           // InterfaceMethod org/apache/hadoop/hbase/io/hfile/FirstLevelBlockCache.getBlockCount:()J
       9: aload_0
      10: getfield      #3                  // Field l2Cache:Lorg/apache/hadoop/hbase/io/hfile/BlockCache;
      13: invokeinterface #38,  1           // InterfaceMethod org/apache/hadoop/hbase/io/hfile/BlockCache.getBlockCount:()J
      18: ladd
      19: lreturn

  public long getDataBlockCount();
    Code:
       0: aload_0
       1: getfield      #2                  // Field l1Cache:Lorg/apache/hadoop/hbase/io/hfile/FirstLevelBlockCache;
       4: invokeinterface #39,  1           // InterfaceMethod org/apache/hadoop/hbase/io/hfile/FirstLevelBlockCache.getDataBlockCount:()J
       9: aload_0
      10: getfield      #3                  // Field l2Cache:Lorg/apache/hadoop/hbase/io/hfile/BlockCache;
      13: invokeinterface #40,  1           // InterfaceMethod org/apache/hadoop/hbase/io/hfile/BlockCache.getDataBlockCount:()J
      18: ladd
      19: lreturn

  public java.util.Iterator<org.apache.hadoop.hbase.io.hfile.CachedBlock> iterator();
    Code:
       0: new           #41                 // class org/apache/hadoop/hbase/io/hfile/BlockCachesIterator
       3: dup
       4: aload_0
       5: invokevirtual #42                 // Method getBlockCaches:()[Lorg/apache/hadoop/hbase/io/hfile/BlockCache;
       8: invokespecial #43                 // Method org/apache/hadoop/hbase/io/hfile/BlockCachesIterator."<init>":([Lorg/apache/hadoop/hbase/io/hfile/BlockCache;)V
      11: areturn

  public org.apache.hadoop.hbase.io.hfile.BlockCache[] getBlockCaches();
    Code:
       0: iconst_2
       1: anewarray     #44                 // class org/apache/hadoop/hbase/io/hfile/BlockCache
       4: dup
       5: iconst_0
       6: aload_0
       7: getfield      #2                  // Field l1Cache:Lorg/apache/hadoop/hbase/io/hfile/FirstLevelBlockCache;
      10: aastore
      11: dup
      12: iconst_1
      13: aload_0
      14: getfield      #3                  // Field l2Cache:Lorg/apache/hadoop/hbase/io/hfile/BlockCache;
      17: aastore
      18: areturn

  public void setMaxSize(long);
    Code:
       0: aload_0
       1: getfield      #2                  // Field l1Cache:Lorg/apache/hadoop/hbase/io/hfile/FirstLevelBlockCache;
       4: lload_1
       5: invokeinterface #45,  3           // InterfaceMethod org/apache/hadoop/hbase/io/hfile/FirstLevelBlockCache.setMaxSize:(J)V
      10: return

  public void returnBlock(org.apache.hadoop.hbase.io.hfile.BlockCacheKey, org.apache.hadoop.hbase.io.hfile.Cacheable);
    Code:
       0: aload_0
       1: getfield      #3                  // Field l2Cache:Lorg/apache/hadoop/hbase/io/hfile/BlockCache;
       4: aload_1
       5: aload_2
       6: invokeinterface #46,  3           // InterfaceMethod org/apache/hadoop/hbase/io/hfile/BlockCache.returnBlock:(Lorg/apache/hadoop/hbase/io/hfile/BlockCacheKey;Lorg/apache/hadoop/hbase/io/hfile/Cacheable;)V
      11: return

  public int getRefCount(org.apache.hadoop.hbase.io.hfile.BlockCacheKey);
    Code:
       0: aload_0
       1: getfield      #3                  // Field l2Cache:Lorg/apache/hadoop/hbase/io/hfile/BlockCache;
       4: instanceof    #47                 // class org/apache/hadoop/hbase/io/hfile/bucket/BucketCache
       7: ifeq          24
      10: aload_0
      11: getfield      #3                  // Field l2Cache:Lorg/apache/hadoop/hbase/io/hfile/BlockCache;
      14: checkcast     #47                 // class org/apache/hadoop/hbase/io/hfile/bucket/BucketCache
      17: aload_1
      18: invokevirtual #48                 // Method org/apache/hadoop/hbase/io/hfile/bucket/BucketCache.getRefCount:(Lorg/apache/hadoop/hbase/io/hfile/BlockCacheKey;)I
      21: goto          25
      24: iconst_0
      25: ireturn

  public org.apache.hadoop.hbase.io.hfile.FirstLevelBlockCache getFirstLevelCache();
    Code:
       0: aload_0
       1: getfield      #2                  // Field l1Cache:Lorg/apache/hadoop/hbase/io/hfile/FirstLevelBlockCache;
       4: areturn
}
