Compiled from "CompatibilitySingletonFactory.java"
public class org.apache.hadoop.hbase.CompatibilitySingletonFactory extends org.apache.hadoop.hbase.CompatibilityFactory {
  protected org.apache.hadoop.hbase.CompatibilitySingletonFactory();
    Code:
       0: aload_0
       1: invokespecial #1                  // Method org/apache/hadoop/hbase/CompatibilityFactory."<init>":()V
       4: return

  public static <T> T getInstance(java.lang.Class<T>);
    Code:
       0: getstatic     #2                  // Field org/apache/hadoop/hbase/CompatibilitySingletonFactory$SingletonStorage.INSTANCE:Lorg/apache/hadoop/hbase/CompatibilitySingletonFactory$SingletonStorage;
       3: invokestatic  #3                  // Method org/apache/hadoop/hbase/CompatibilitySingletonFactory$SingletonStorage.access$000:(Lorg/apache/hadoop/hbase/CompatibilitySingletonFactory$SingletonStorage;)Ljava/lang/Object;
       6: dup
       7: astore_1
       8: monitorenter
       9: getstatic     #2                  // Field org/apache/hadoop/hbase/CompatibilitySingletonFactory$SingletonStorage.INSTANCE:Lorg/apache/hadoop/hbase/CompatibilitySingletonFactory$SingletonStorage;
      12: invokestatic  #4                  // Method org/apache/hadoop/hbase/CompatibilitySingletonFactory$SingletonStorage.access$100:(Lorg/apache/hadoop/hbase/CompatibilitySingletonFactory$SingletonStorage;)Ljava/util/Map;
      15: aload_0
      16: invokeinterface #5,  2            // InterfaceMethod java/util/Map.get:(Ljava/lang/Object;)Ljava/lang/Object;
      21: astore_2
      22: aload_2
      23: ifnonnull     206
      26: aload_0
      27: invokestatic  #6                  // Method java/util/ServiceLoader.load:(Ljava/lang/Class;)Ljava/util/ServiceLoader;
      30: astore_3
      31: aload_3
      32: invokevirtual #7                  // Method java/util/ServiceLoader.iterator:()Ljava/util/Iterator;
      35: astore        4
      37: aload         4
      39: invokeinterface #8,  1            // InterfaceMethod java/util/Iterator.next:()Ljava/lang/Object;
      44: astore_2
      45: aload         4
      47: invokeinterface #9,  1            // InterfaceMethod java/util/Iterator.hasNext:()Z
      52: ifeq          145
      55: new           #10                 // class java/lang/StringBuilder
      58: dup
      59: invokespecial #11                 // Method java/lang/StringBuilder."<init>":()V
      62: astore        5
      64: aload         5
      66: ldc           #12                 // String ServiceLoader provided more than one implementation for class:
      68: invokevirtual #13                 // Method java/lang/StringBuilder.append:(Ljava/lang/String;)Ljava/lang/StringBuilder;
      71: aload_0
      72: invokevirtual #14                 // Method java/lang/StringBuilder.append:(Ljava/lang/Object;)Ljava/lang/StringBuilder;
      75: ldc           #15                 // String , using implementation:
      77: invokevirtual #13                 // Method java/lang/StringBuilder.append:(Ljava/lang/String;)Ljava/lang/StringBuilder;
      80: aload_2
      81: invokevirtual #16                 // Method java/lang/Object.getClass:()Ljava/lang/Class;
      84: invokevirtual #14                 // Method java/lang/StringBuilder.append:(Ljava/lang/Object;)Ljava/lang/StringBuilder;
      87: ldc           #17                 // String , other implementations: {
      89: invokevirtual #13                 // Method java/lang/StringBuilder.append:(Ljava/lang/String;)Ljava/lang/StringBuilder;
      92: pop
      93: aload         4
      95: invokeinterface #9,  1            // InterfaceMethod java/util/Iterator.hasNext:()Z
     100: ifeq          124
     103: aload         5
     105: aload         4
     107: invokeinterface #8,  1            // InterfaceMethod java/util/Iterator.next:()Ljava/lang/Object;
     112: invokevirtual #14                 // Method java/lang/StringBuilder.append:(Ljava/lang/Object;)Ljava/lang/StringBuilder;
     115: ldc           #18                 // String
     117: invokevirtual #13                 // Method java/lang/StringBuilder.append:(Ljava/lang/String;)Ljava/lang/StringBuilder;
     120: pop
     121: goto          93
     124: aload         5
     126: ldc           #19                 // String }
     128: invokevirtual #13                 // Method java/lang/StringBuilder.append:(Ljava/lang/String;)Ljava/lang/StringBuilder;
     131: pop
     132: getstatic     #20                 // Field LOG:Lorg/slf4j/Logger;
     135: aload         5
     137: invokevirtual #21                 // Method java/lang/StringBuilder.toString:()Ljava/lang/String;
     140: invokeinterface #22,  2           // InterfaceMethod org/slf4j/Logger.warn:(Ljava/lang/String;)V
     145: goto          176
     148: astore_3
     149: new           #24                 // class java/lang/RuntimeException
     152: dup
     153: aload_0
     154: invokestatic  #25                 // Method createExceptionString:(Ljava/lang/Class;)Ljava/lang/String;
     157: aload_3
     158: invokespecial #26                 // Method java/lang/RuntimeException."<init>":(Ljava/lang/String;Ljava/lang/Throwable;)V
     161: athrow
     162: astore_3
     163: new           #24                 // class java/lang/RuntimeException
     166: dup
     167: aload_0
     168: invokestatic  #25                 // Method createExceptionString:(Ljava/lang/Class;)Ljava/lang/String;
     171: aload_3
     172: invokespecial #26                 // Method java/lang/RuntimeException."<init>":(Ljava/lang/String;Ljava/lang/Throwable;)V
     175: athrow
     176: aload_2
     177: ifnonnull     192
     180: new           #24                 // class java/lang/RuntimeException
     183: dup
     184: aload_0
     185: invokestatic  #25                 // Method createExceptionString:(Ljava/lang/Class;)Ljava/lang/String;
     188: invokespecial #28                 // Method java/lang/RuntimeException."<init>":(Ljava/lang/String;)V
     191: athrow
     192: getstatic     #2                  // Field org/apache/hadoop/hbase/CompatibilitySingletonFactory$SingletonStorage.INSTANCE:Lorg/apache/hadoop/hbase/CompatibilitySingletonFactory$SingletonStorage;
     195: invokestatic  #4                  // Method org/apache/hadoop/hbase/CompatibilitySingletonFactory$SingletonStorage.access$100:(Lorg/apache/hadoop/hbase/CompatibilitySingletonFactory$SingletonStorage;)Ljava/util/Map;
     198: aload_0
     199: aload_2
     200: invokeinterface #29,  3           // InterfaceMethod java/util/Map.put:(Ljava/lang/Object;Ljava/lang/Object;)Ljava/lang/Object;
     205: pop
     206: aload_2
     207: aload_1
     208: monitorexit
     209: areturn
     210: astore        6
     212: aload_1
     213: monitorexit
     214: aload         6
     216: athrow
    Exception table:
       from    to  target type
          26   145   148   Class java/lang/Exception
          26   145   162   Class java/lang/Error
           9   209   210   any
         210   214   210   any

  static {};
    Code:
       0: ldc           #30                 // class org/apache/hadoop/hbase/CompatibilitySingletonFactory
       2: invokestatic  #31                 // Method org/slf4j/LoggerFactory.getLogger:(Ljava/lang/Class;)Lorg/slf4j/Logger;
       5: putstatic     #20                 // Field LOG:Lorg/slf4j/Logger;
       8: return
}
