Compiled from "CompressionTest.java"
public class org.apache.hadoop.hbase.util.CompressionTest {
  protected static org.apache.hadoop.fs.Path path;

  public org.apache.hadoop.hbase.util.CompressionTest();
    Code:
       0: aload_0
       1: invokespecial #1                  // Method java/lang/Object."<init>":()V
       4: return

  public static boolean testCompression(java.lang.String);
    Code:
       0: aload_0
       1: getstatic     #2                  // Field java/util/Locale.ROOT:Ljava/util/Locale;
       4: invokevirtual #3                  // Method java/lang/String.toLowerCase:(Ljava/util/Locale;)Ljava/lang/String;
       7: astore_0
       8: aload_0
       9: invokestatic  #4                  // Method org/apache/hadoop/hbase/io/compress/Compression.getCompressionAlgorithmByName:(Ljava/lang/String;)Lorg/apache/hadoop/hbase/io/compress/Compression$Algorithm;
      12: astore_1
      13: goto          51
      16: astore_2
      17: getstatic     #6                  // Field LOG:Lorg/slf4j/Logger;
      20: new           #7                  // class java/lang/StringBuilder
      23: dup
      24: invokespecial #8                  // Method java/lang/StringBuilder."<init>":()V
      27: ldc           #9                  // String Codec type:
      29: invokevirtual #10                 // Method java/lang/StringBuilder.append:(Ljava/lang/String;)Ljava/lang/StringBuilder;
      32: aload_0
      33: invokevirtual #10                 // Method java/lang/StringBuilder.append:(Ljava/lang/String;)Ljava/lang/StringBuilder;
      36: ldc           #11                 // String  is not known
      38: invokevirtual #10                 // Method java/lang/StringBuilder.append:(Ljava/lang/String;)Ljava/lang/StringBuilder;
      41: invokevirtual #12                 // Method java/lang/StringBuilder.toString:()Ljava/lang/String;
      44: invokeinterface #13,  2           // InterfaceMethod org/slf4j/Logger.warn:(Ljava/lang/String;)V
      49: iconst_0
      50: ireturn
      51: aload_1
      52: invokestatic  #14                 // Method testCompression:(Lorg/apache/hadoop/hbase/io/compress/Compression$Algorithm;)V
      55: iconst_1
      56: ireturn
      57: astore_2
      58: getstatic     #6                  // Field LOG:Lorg/slf4j/Logger;
      61: new           #7                  // class java/lang/StringBuilder
      64: dup
      65: invokespecial #8                  // Method java/lang/StringBuilder."<init>":()V
      68: ldc           #16                 // String Can't instantiate codec:
      70: invokevirtual #10                 // Method java/lang/StringBuilder.append:(Ljava/lang/String;)Ljava/lang/StringBuilder;
      73: aload_0
      74: invokevirtual #10                 // Method java/lang/StringBuilder.append:(Ljava/lang/String;)Ljava/lang/StringBuilder;
      77: invokevirtual #12                 // Method java/lang/StringBuilder.toString:()Ljava/lang/String;
      80: aload_2
      81: invokeinterface #17,  3           // InterfaceMethod org/slf4j/Logger.warn:(Ljava/lang/String;Ljava/lang/Throwable;)V
      86: iconst_0
      87: ireturn
    Exception table:
       from    to  target type
           8    13    16   Class java/lang/IllegalArgumentException
          51    56    57   Class java/io/IOException

  public static void testCompression(org.apache.hadoop.hbase.io.compress.Compression$Algorithm) throws java.io.IOException;
    Code:
       0: getstatic     #18                 // Field compressionTestResults:[Ljava/lang/Boolean;
       3: aload_0
       4: invokevirtual #19                 // Method org/apache/hadoop/hbase/io/compress/Compression$Algorithm.ordinal:()I
       7: aaload
       8: ifnull        61
      11: getstatic     #18                 // Field compressionTestResults:[Ljava/lang/Boolean;
      14: aload_0
      15: invokevirtual #19                 // Method org/apache/hadoop/hbase/io/compress/Compression$Algorithm.ordinal:()I
      18: aaload
      19: invokevirtual #20                 // Method java/lang/Boolean.booleanValue:()Z
      22: ifeq          26
      25: return
      26: new           #21                 // class org/apache/hadoop/hbase/DoNotRetryIOException
      29: dup
      30: new           #7                  // class java/lang/StringBuilder
      33: dup
      34: invokespecial #8                  // Method java/lang/StringBuilder."<init>":()V
      37: ldc           #22                 // String Compression algorithm '
      39: invokevirtual #10                 // Method java/lang/StringBuilder.append:(Ljava/lang/String;)Ljava/lang/StringBuilder;
      42: aload_0
      43: invokevirtual #23                 // Method org/apache/hadoop/hbase/io/compress/Compression$Algorithm.getName:()Ljava/lang/String;
      46: invokevirtual #10                 // Method java/lang/StringBuilder.append:(Ljava/lang/String;)Ljava/lang/StringBuilder;
      49: ldc           #24                 // String ' previously failed test.
      51: invokevirtual #10                 // Method java/lang/StringBuilder.append:(Ljava/lang/String;)Ljava/lang/StringBuilder;
      54: invokevirtual #12                 // Method java/lang/StringBuilder.toString:()Ljava/lang/String;
      57: invokespecial #25                 // Method org/apache/hadoop/hbase/DoNotRetryIOException."<init>":(Ljava/lang/String;)V
      60: athrow
      61: aload_0
      62: invokevirtual #26                 // Method org/apache/hadoop/hbase/io/compress/Compression$Algorithm.getCompressor:()Lorg/apache/hadoop/io/compress/Compressor;
      65: astore_1
      66: aload_0
      67: aload_1
      68: invokevirtual #27                 // Method org/apache/hadoop/hbase/io/compress/Compression$Algorithm.returnCompressor:(Lorg/apache/hadoop/io/compress/Compressor;)V
      71: getstatic     #18                 // Field compressionTestResults:[Ljava/lang/Boolean;
      74: aload_0
      75: invokevirtual #19                 // Method org/apache/hadoop/hbase/io/compress/Compression$Algorithm.ordinal:()I
      78: iconst_1
      79: invokestatic  #28                 // Method java/lang/Boolean.valueOf:(Z)Ljava/lang/Boolean;
      82: aastore
      83: goto          108
      86: astore_1
      87: getstatic     #18                 // Field compressionTestResults:[Ljava/lang/Boolean;
      90: aload_0
      91: invokevirtual #19                 // Method org/apache/hadoop/hbase/io/compress/Compression$Algorithm.ordinal:()I
      94: iconst_0
      95: invokestatic  #28                 // Method java/lang/Boolean.valueOf:(Z)Ljava/lang/Boolean;
      98: aastore
      99: new           #21                 // class org/apache/hadoop/hbase/DoNotRetryIOException
     102: dup
     103: aload_1
     104: invokespecial #30                 // Method org/apache/hadoop/hbase/DoNotRetryIOException."<init>":(Ljava/lang/Throwable;)V
     107: athrow
     108: return
    Exception table:
       from    to  target type
          61    83    86   Class java/lang/Throwable

  public static void usage();
    Code:
       0: getstatic     #31                 // Field java/lang/System.err:Ljava/io/PrintStream;
       3: new           #7                  // class java/lang/StringBuilder
       6: dup
       7: invokespecial #8                  // Method java/lang/StringBuilder."<init>":()V
      10: ldc           #32                 // String Usage: CompressionTest <path>
      12: invokevirtual #10                 // Method java/lang/StringBuilder.append:(Ljava/lang/String;)Ljava/lang/StringBuilder;
      15: invokestatic  #33                 // Method org/apache/hadoop/hbase/io/compress/Compression$Algorithm.values:()[Lorg/apache/hadoop/hbase/io/compress/Compression$Algorithm;
      18: ldc           #34                 // String |
      20: invokestatic  #35                 // Method org/apache/commons/lang3/StringUtils.join:([Ljava/lang/Object;Ljava/lang/String;)Ljava/lang/String;
      23: getstatic     #2                  // Field java/util/Locale.ROOT:Ljava/util/Locale;
      26: invokevirtual #3                  // Method java/lang/String.toLowerCase:(Ljava/util/Locale;)Ljava/lang/String;
      29: invokevirtual #10                 // Method java/lang/StringBuilder.append:(Ljava/lang/String;)Ljava/lang/StringBuilder;
      32: ldc           #36                 // String \nFor example:\n  hbase
      34: invokevirtual #10                 // Method java/lang/StringBuilder.append:(Ljava/lang/String;)Ljava/lang/StringBuilder;
      37: ldc           #37                 // class org/apache/hadoop/hbase/util/CompressionTest
      39: invokevirtual #38                 // Method java/lang/StringBuilder.append:(Ljava/lang/Object;)Ljava/lang/StringBuilder;
      42: ldc           #39                 // String  file:///tmp/testfile gz\n
      44: invokevirtual #10                 // Method java/lang/StringBuilder.append:(Ljava/lang/String;)Ljava/lang/StringBuilder;
      47: invokevirtual #12                 // Method java/lang/StringBuilder.toString:()Ljava/lang/String;
      50: invokevirtual #40                 // Method java/io/PrintStream.println:(Ljava/lang/String;)V
      53: iconst_1
      54: invokestatic  #41                 // Method java/lang/System.exit:(I)V
      57: return

  public static void doSmokeTest(org.apache.hadoop.fs.FileSystem, org.apache.hadoop.fs.Path, java.lang.String) throws java.lang.Exception;
    Code:
       0: invokestatic  #42                 // Method org/apache/hadoop/hbase/HBaseConfiguration.create:()Lorg/apache/hadoop/conf/Configuration;
       3: astore_3
       4: new           #43                 // class org/apache/hadoop/hbase/io/hfile/HFileContextBuilder
       7: dup
       8: invokespecial #44                 // Method org/apache/hadoop/hbase/io/hfile/HFileContextBuilder."<init>":()V
      11: aload_2
      12: invokestatic  #45                 // Method org/apache/hadoop/hbase/io/hfile/HFileWriterImpl.compressionByName:(Ljava/lang/String;)Lorg/apache/hadoop/hbase/io/compress/Compression$Algorithm;
      15: invokevirtual #46                 // Method org/apache/hadoop/hbase/io/hfile/HFileContextBuilder.withCompression:(Lorg/apache/hadoop/hbase/io/compress/Compression$Algorithm;)Lorg/apache/hadoop/hbase/io/hfile/HFileContextBuilder;
      18: invokevirtual #47                 // Method org/apache/hadoop/hbase/io/hfile/HFileContextBuilder.build:()Lorg/apache/hadoop/hbase/io/hfile/HFileContext;
      21: astore        4
      23: aload_3
      24: invokestatic  #48                 // Method org/apache/hadoop/hbase/io/hfile/HFile.getWriterFactoryNoCache:(Lorg/apache/hadoop/conf/Configuration;)Lorg/apache/hadoop/hbase/io/hfile/HFile$WriterFactory;
      27: aload_0
      28: aload_1
      29: invokevirtual #49                 // Method org/apache/hadoop/hbase/io/hfile/HFile$WriterFactory.withPath:(Lorg/apache/hadoop/fs/FileSystem;Lorg/apache/hadoop/fs/Path;)Lorg/apache/hadoop/hbase/io/hfile/HFile$WriterFactory;
      32: aload         4
      34: invokevirtual #50                 // Method org/apache/hadoop/hbase/io/hfile/HFile$WriterFactory.withFileContext:(Lorg/apache/hadoop/hbase/io/hfile/HFileContext;)Lorg/apache/hadoop/hbase/io/hfile/HFile$WriterFactory;
      37: invokevirtual #51                 // Method org/apache/hadoop/hbase/io/hfile/HFile$WriterFactory.create:()Lorg/apache/hadoop/hbase/io/hfile/HFile$Writer;
      40: astore        5
      42: ldc           #52                 // String compressiontestkey
      44: invokestatic  #53                 // Method org/apache/hadoop/hbase/util/Bytes.toBytes:(Ljava/lang/String;)[B
      47: astore        6
      49: aload         6
      51: ldc           #54                 // String compressiontestval
      53: invokestatic  #53                 // Method org/apache/hadoop/hbase/util/Bytes.toBytes:(Ljava/lang/String;)[B
      56: invokestatic  #55                 // Method org/apache/hadoop/hbase/CellUtil.createCell:([B[B)Lorg/apache/hadoop/hbase/Cell;
      59: astore        7
      61: aload         5
      63: aload         7
      65: invokeinterface #56,  2           // InterfaceMethod org/apache/hadoop/hbase/io/hfile/HFile$Writer.append:(Lorg/apache/hadoop/hbase/Cell;)V
      70: aload         5
      72: ldc           #57                 // String compressioninfokey
      74: invokestatic  #53                 // Method org/apache/hadoop/hbase/util/Bytes.toBytes:(Ljava/lang/String;)[B
      77: ldc           #58                 // String compressioninfoval
      79: invokestatic  #53                 // Method org/apache/hadoop/hbase/util/Bytes.toBytes:(Ljava/lang/String;)[B
      82: invokeinterface #59,  3           // InterfaceMethod org/apache/hadoop/hbase/io/hfile/HFile$Writer.appendFileInfo:([B[B)V
      87: aload         5
      89: invokeinterface #60,  1           // InterfaceMethod org/apache/hadoop/hbase/io/hfile/HFile$Writer.close:()V
      94: aconst_null
      95: astore        8
      97: aload_0
      98: aload_1
      99: getstatic     #61                 // Field org/apache/hadoop/hbase/io/hfile/CacheConfig.DISABLED:Lorg/apache/hadoop/hbase/io/hfile/CacheConfig;
     102: iconst_1
     103: aload_3
     104: invokestatic  #62                 // Method org/apache/hadoop/hbase/io/hfile/HFile.createReader:(Lorg/apache/hadoop/fs/FileSystem;Lorg/apache/hadoop/fs/Path;Lorg/apache/hadoop/hbase/io/hfile/CacheConfig;ZLorg/apache/hadoop/conf/Configuration;)Lorg/apache/hadoop/hbase/io/hfile/HFile$Reader;
     107: astore        9
     109: aload         9
     111: invokeinterface #63,  1           // InterfaceMethod org/apache/hadoop/hbase/io/hfile/HFile$Reader.loadFileInfo:()Ljava/util/Map;
     116: pop
     117: aload         9
     119: iconst_0
     120: iconst_1
     121: invokeinterface #64,  3           // InterfaceMethod org/apache/hadoop/hbase/io/hfile/HFile$Reader.getScanner:(ZZ)Lorg/apache/hadoop/hbase/io/hfile/HFileScanner;
     126: astore        10
     128: aload         10
     130: invokeinterface #65,  1           // InterfaceMethod org/apache/hadoop/hbase/io/hfile/HFileScanner.seekTo:()Z
     135: pop
     136: aload         10
     138: invokeinterface #66,  1           // InterfaceMethod org/apache/hadoop/hbase/io/hfile/HFileScanner.getCell:()Lorg/apache/hadoop/hbase/Cell;
     143: astore        8
     145: invokestatic  #67                 // InterfaceMethod org/apache/hadoop/hbase/CellComparator.getInstance:()Lorg/apache/hadoop/hbase/CellComparator;
     148: aload         7
     150: aload         8
     152: invokeinterface #68,  3           // InterfaceMethod org/apache/hadoop/hbase/CellComparator.compareRows:(Lorg/apache/hadoop/hbase/Cell;Lorg/apache/hadoop/hbase/Cell;)I
     157: ifeq          204
     160: new           #69                 // class java/lang/Exception
     163: dup
     164: new           #7                  // class java/lang/StringBuilder
     167: dup
     168: invokespecial #8                  // Method java/lang/StringBuilder."<init>":()V
     171: ldc           #70                 // String Read back incorrect result:
     173: invokevirtual #10                 // Method java/lang/StringBuilder.append:(Ljava/lang/String;)Ljava/lang/StringBuilder;
     176: aload         7
     178: invokevirtual #71                 // Method java/lang/Object.toString:()Ljava/lang/String;
     181: invokevirtual #10                 // Method java/lang/StringBuilder.append:(Ljava/lang/String;)Ljava/lang/StringBuilder;
     184: ldc           #72                 // String  vs
     186: invokevirtual #10                 // Method java/lang/StringBuilder.append:(Ljava/lang/String;)Ljava/lang/StringBuilder;
     189: aload         8
     191: invokevirtual #71                 // Method java/lang/Object.toString:()Ljava/lang/String;
     194: invokevirtual #10                 // Method java/lang/StringBuilder.append:(Ljava/lang/String;)Ljava/lang/StringBuilder;
     197: invokevirtual #12                 // Method java/lang/StringBuilder.toString:()Ljava/lang/String;
     200: invokespecial #73                 // Method java/lang/Exception."<init>":(Ljava/lang/String;)V
     203: athrow
     204: aload         9
     206: invokeinterface #74,  1           // InterfaceMethod org/apache/hadoop/hbase/io/hfile/HFile$Reader.close:()V
     211: goto          226
     214: astore        11
     216: aload         9
     218: invokeinterface #74,  1           // InterfaceMethod org/apache/hadoop/hbase/io/hfile/HFile$Reader.close:()V
     223: aload         11
     225: athrow
     226: return
    Exception table:
       from    to  target type
         109   204   214   any
         214   216   214   any

  public static void main(java.lang.String[]) throws java.lang.Exception;
    Code:
       0: aload_0
       1: arraylength
       2: iconst_2
       3: if_icmpeq     13
       6: invokestatic  #75                 // Method usage:()V
       9: iconst_1
      10: invokestatic  #41                 // Method java/lang/System.exit:(I)V
      13: new           #76                 // class org/apache/hadoop/conf/Configuration
      16: dup
      17: invokespecial #77                 // Method org/apache/hadoop/conf/Configuration."<init>":()V
      20: astore_1
      21: new           #78                 // class org/apache/hadoop/fs/Path
      24: dup
      25: aload_0
      26: iconst_0
      27: aaload
      28: invokespecial #79                 // Method org/apache/hadoop/fs/Path."<init>":(Ljava/lang/String;)V
      31: astore_2
      32: aload_2
      33: aload_1
      34: invokevirtual #80                 // Method org/apache/hadoop/fs/Path.getFileSystem:(Lorg/apache/hadoop/conf/Configuration;)Lorg/apache/hadoop/fs/FileSystem;
      37: astore_3
      38: aload_3
      39: aload_2
      40: invokevirtual #81                 // Method org/apache/hadoop/fs/FileSystem.exists:(Lorg/apache/hadoop/fs/Path;)Z
      43: ifeq          58
      46: getstatic     #31                 // Field java/lang/System.err:Ljava/io/PrintStream;
      49: ldc           #82                 // String The specified path exists, aborting!
      51: invokevirtual #40                 // Method java/io/PrintStream.println:(Ljava/lang/String;)V
      54: iconst_1
      55: invokestatic  #41                 // Method java/lang/System.exit:(I)V
      58: aload_3
      59: aload_2
      60: aload_0
      61: iconst_1
      62: aaload
      63: invokestatic  #83                 // Method doSmokeTest:(Lorg/apache/hadoop/fs/FileSystem;Lorg/apache/hadoop/fs/Path;Ljava/lang/String;)V
      66: aload_3
      67: aload_2
      68: iconst_0
      69: invokevirtual #84                 // Method org/apache/hadoop/fs/FileSystem.delete:(Lorg/apache/hadoop/fs/Path;Z)Z
      72: pop
      73: goto          88
      76: astore        4
      78: aload_3
      79: aload_2
      80: iconst_0
      81: invokevirtual #84                 // Method org/apache/hadoop/fs/FileSystem.delete:(Lorg/apache/hadoop/fs/Path;Z)Z
      84: pop
      85: aload         4
      87: athrow
      88: getstatic     #85                 // Field java/lang/System.out:Ljava/io/PrintStream;
      91: ldc           #86                 // String SUCCESS
      93: invokevirtual #40                 // Method java/io/PrintStream.println:(Ljava/lang/String;)V
      96: return
    Exception table:
       from    to  target type
          58    66    76   any
          76    78    76   any

  static {};
    Code:
       0: ldc           #37                 // class org/apache/hadoop/hbase/util/CompressionTest
       2: invokestatic  #87                 // Method org/slf4j/LoggerFactory.getLogger:(Ljava/lang/Class;)Lorg/slf4j/Logger;
       5: putstatic     #6                  // Field LOG:Lorg/slf4j/Logger;
       8: invokestatic  #33                 // Method org/apache/hadoop/hbase/io/compress/Compression$Algorithm.values:()[Lorg/apache/hadoop/hbase/io/compress/Compression$Algorithm;
      11: arraylength
      12: anewarray     #88                 // class java/lang/Boolean
      15: putstatic     #18                 // Field compressionTestResults:[Ljava/lang/Boolean;
      18: iconst_0
      19: istore_0
      20: iload_0
      21: getstatic     #18                 // Field compressionTestResults:[Ljava/lang/Boolean;
      24: arraylength
      25: if_icmpge     40
      28: getstatic     #18                 // Field compressionTestResults:[Ljava/lang/Boolean;
      31: iload_0
      32: aconst_null
      33: aastore
      34: iinc          0, 1
      37: goto          20
      40: new           #78                 // class org/apache/hadoop/fs/Path
      43: dup
      44: ldc           #89                 // String .hfile-comp-test
      46: invokespecial #79                 // Method org/apache/hadoop/fs/Path."<init>":(Ljava/lang/String;)V
      49: putstatic     #90                 // Field path:Lorg/apache/hadoop/fs/Path;
      52: return
}
