Compiled from "CompactingMemStore.java"
public class org.apache.hadoop.hbase.regionserver.CompactingMemStore extends org.apache.hadoop.hbase.regionserver.AbstractMemStore {
  public static final java.lang.String COMPACTING_MEMSTORE_TYPE_KEY;

  public static final java.lang.String COMPACTING_MEMSTORE_TYPE_DEFAULT;

  public static final java.lang.String IN_MEMORY_FLUSH_THRESHOLD_FACTOR_KEY;

  public static final java.lang.String IN_MEMORY_CONPACTION_POOL_SIZE_KEY;

  public static final int IN_MEMORY_CONPACTION_POOL_SIZE_DEFAULT;

  protected org.apache.hadoop.hbase.regionserver.MemStoreCompactor compactor;

  protected final java.util.concurrent.atomic.AtomicBoolean allowCompaction;

  public static final long DEEP_OVERHEAD;

  public org.apache.hadoop.hbase.regionserver.CompactingMemStore(org.apache.hadoop.conf.Configuration, org.apache.hadoop.hbase.CellComparator, org.apache.hadoop.hbase.regionserver.HStore, org.apache.hadoop.hbase.regionserver.RegionServicesForStores, org.apache.hadoop.hbase.MemoryCompactionPolicy) throws java.io.IOException;
    Code:
       0: aload_0
       1: aload_1
       2: aload_2
       3: aload         4
       5: invokespecial #1                  // Method org/apache/hadoop/hbase/regionserver/AbstractMemStore."<init>":(Lorg/apache/hadoop/conf/Configuration;Lorg/apache/hadoop/hbase/CellComparator;Lorg/apache/hadoop/hbase/regionserver/RegionServicesForStores;)V
       8: aload_0
       9: new           #2                  // class java/util/concurrent/atomic/AtomicBoolean
      12: dup
      13: iconst_0
      14: invokespecial #3                  // Method java/util/concurrent/atomic/AtomicBoolean."<init>":(Z)V
      17: putfield      #4                  // Field inMemoryCompactionInProgress:Ljava/util/concurrent/atomic/AtomicBoolean;
      20: aload_0
      21: iconst_0
      22: putfield      #5                  // Field inWalReplay:Z
      25: aload_0
      26: new           #2                  // class java/util/concurrent/atomic/AtomicBoolean
      29: dup
      30: iconst_1
      31: invokespecial #3                  // Method java/util/concurrent/atomic/AtomicBoolean."<init>":(Z)V
      34: putfield      #6                  // Field allowCompaction:Ljava/util/concurrent/atomic/AtomicBoolean;
      37: aload_0
      38: iconst_1
      39: putfield      #7                  // Field compositeSnapshot:Z
      42: aload_0
      43: getstatic     #8                  // Field org/apache/hadoop/hbase/regionserver/CompactingMemStore$IndexType.ARRAY_MAP:Lorg/apache/hadoop/hbase/regionserver/CompactingMemStore$IndexType;
      46: putfield      #9                  // Field indexType:Lorg/apache/hadoop/hbase/regionserver/CompactingMemStore$IndexType;
      49: aload_0
      50: aload_3
      51: putfield      #10                 // Field store:Lorg/apache/hadoop/hbase/regionserver/HStore;
      54: aload_0
      55: aload         4
      57: putfield      #11                 // Field regionServices:Lorg/apache/hadoop/hbase/regionserver/RegionServicesForStores;
      60: aload_0
      61: new           #12                 // class org/apache/hadoop/hbase/regionserver/CompactionPipeline
      64: dup
      65: aload_0
      66: invokespecial #13                 // Method getRegionServices:()Lorg/apache/hadoop/hbase/regionserver/RegionServicesForStores;
      69: invokespecial #14                 // Method org/apache/hadoop/hbase/regionserver/CompactionPipeline."<init>":(Lorg/apache/hadoop/hbase/regionserver/RegionServicesForStores;)V
      72: putfield      #15                 // Field pipeline:Lorg/apache/hadoop/hbase/regionserver/CompactionPipeline;
      75: aload_0
      76: aload_0
      77: aload         5
      79: invokevirtual #16                 // Method createMemStoreCompactor:(Lorg/apache/hadoop/hbase/MemoryCompactionPolicy;)Lorg/apache/hadoop/hbase/regionserver/MemStoreCompactor;
      82: putfield      #17                 // Field compactor:Lorg/apache/hadoop/hbase/regionserver/MemStoreCompactor;
      85: aload_1
      86: ldc           #19                 // String hbase.hregion.memstore.mslab.enabled
      88: iconst_1
      89: invokevirtual #20                 // Method org/apache/hadoop/conf/Configuration.getBoolean:(Ljava/lang/String;Z)Z
      92: ifeq          105
      95: aload_0
      96: getstatic     #21                 // Field org/apache/hadoop/hbase/regionserver/CompactingMemStore$IndexType.CHUNK_MAP:Lorg/apache/hadoop/hbase/regionserver/CompactingMemStore$IndexType;
      99: putfield      #9                  // Field indexType:Lorg/apache/hadoop/hbase/regionserver/CompactingMemStore$IndexType;
     102: goto          112
     105: aload_0
     106: getstatic     #8                  // Field org/apache/hadoop/hbase/regionserver/CompactingMemStore$IndexType.ARRAY_MAP:Lorg/apache/hadoop/hbase/regionserver/CompactingMemStore$IndexType;
     109: putfield      #9                  // Field indexType:Lorg/apache/hadoop/hbase/regionserver/CompactingMemStore$IndexType;
     112: aload_0
     113: aload_1
     114: invokespecial #22                 // Method initInmemoryFlushSize:(Lorg/apache/hadoop/conf/Configuration;)V
     117: getstatic     #23                 // Field LOG:Lorg/slf4j/Logger;
     120: ldc           #24                 // String Store={}, in-memory flush size threshold={}, immutable segments index type={}, compactor={}
     122: iconst_4
     123: anewarray     #25                 // class java/lang/Object
     126: dup
     127: iconst_0
     128: aload_0
     129: getfield      #10                 // Field store:Lorg/apache/hadoop/hbase/regionserver/HStore;
     132: invokevirtual #26                 // Method org/apache/hadoop/hbase/regionserver/HStore.getColumnFamilyName:()Ljava/lang/String;
     135: aastore
     136: dup
     137: iconst_1
     138: aload_0
     139: getfield      #27                 // Field inmemoryFlushSize:J
     142: invokestatic  #28                 // Method org/apache/hadoop/util/StringUtils.byteDesc:(J)Ljava/lang/String;
     145: aastore
     146: dup
     147: iconst_2
     148: aload_0
     149: getfield      #9                  // Field indexType:Lorg/apache/hadoop/hbase/regionserver/CompactingMemStore$IndexType;
     152: aastore
     153: dup
     154: iconst_3
     155: aload_0
     156: getfield      #17                 // Field compactor:Lorg/apache/hadoop/hbase/regionserver/MemStoreCompactor;
     159: ifnonnull     167
     162: ldc           #29                 // String NULL
     164: goto          174
     167: aload_0
     168: getfield      #17                 // Field compactor:Lorg/apache/hadoop/hbase/regionserver/MemStoreCompactor;
     171: invokevirtual #30                 // Method org/apache/hadoop/hbase/regionserver/MemStoreCompactor.toString:()Ljava/lang/String;
     174: aastore
     175: invokeinterface #31,  3           // InterfaceMethod org/slf4j/Logger.info:(Ljava/lang/String;[Ljava/lang/Object;)V
     180: return

  protected org.apache.hadoop.hbase.regionserver.MemStoreCompactor createMemStoreCompactor(org.apache.hadoop.hbase.MemoryCompactionPolicy) throws org.apache.hadoop.hbase.exceptions.IllegalArgumentIOException;
    Code:
       0: new           #32                 // class org/apache/hadoop/hbase/regionserver/MemStoreCompactor
       3: dup
       4: aload_0
       5: aload_1
       6: invokespecial #33                 // Method org/apache/hadoop/hbase/regionserver/MemStoreCompactor."<init>":(Lorg/apache/hadoop/hbase/regionserver/CompactingMemStore;Lorg/apache/hadoop/hbase/MemoryCompactionPolicy;)V
       9: areturn

  public org.apache.hadoop.hbase.regionserver.MemStoreSize size();
    Code:
       0: new           #46                 // class org/apache/hadoop/hbase/regionserver/NonThreadSafeMemStoreSizing
       3: dup
       4: invokespecial #47                 // Method org/apache/hadoop/hbase/regionserver/NonThreadSafeMemStoreSizing."<init>":()V
       7: astore_1
       8: aload_1
       9: aload_0
      10: invokevirtual #48                 // Method getActive:()Lorg/apache/hadoop/hbase/regionserver/MutableSegment;
      13: invokevirtual #49                 // Method org/apache/hadoop/hbase/regionserver/MutableSegment.getMemStoreSize:()Lorg/apache/hadoop/hbase/regionserver/MemStoreSize;
      16: invokeinterface #50,  2           // InterfaceMethod org/apache/hadoop/hbase/regionserver/MemStoreSizing.incMemStoreSize:(Lorg/apache/hadoop/hbase/regionserver/MemStoreSize;)J
      21: pop2
      22: aload_0
      23: getfield      #15                 // Field pipeline:Lorg/apache/hadoop/hbase/regionserver/CompactionPipeline;
      26: invokevirtual #51                 // Method org/apache/hadoop/hbase/regionserver/CompactionPipeline.getSegments:()Ljava/util/List;
      29: invokeinterface #52,  1           // InterfaceMethod java/util/List.iterator:()Ljava/util/Iterator;
      34: astore_2
      35: aload_2
      36: invokeinterface #53,  1           // InterfaceMethod java/util/Iterator.hasNext:()Z
      41: ifeq          68
      44: aload_2
      45: invokeinterface #54,  1           // InterfaceMethod java/util/Iterator.next:()Ljava/lang/Object;
      50: checkcast     #55                 // class org/apache/hadoop/hbase/regionserver/Segment
      53: astore_3
      54: aload_1
      55: aload_3
      56: invokevirtual #56                 // Method org/apache/hadoop/hbase/regionserver/Segment.getMemStoreSize:()Lorg/apache/hadoop/hbase/regionserver/MemStoreSize;
      59: invokeinterface #50,  2           // InterfaceMethod org/apache/hadoop/hbase/regionserver/MemStoreSizing.incMemStoreSize:(Lorg/apache/hadoop/hbase/regionserver/MemStoreSize;)J
      64: pop2
      65: goto          35
      68: aload_1
      69: invokeinterface #57,  1           // InterfaceMethod org/apache/hadoop/hbase/regionserver/MemStoreSizing.getMemStoreSize:()Lorg/apache/hadoop/hbase/regionserver/MemStoreSize;
      74: areturn

  public long preFlushSeqIDEstimation();
    Code:
       0: aload_0
       1: getfield      #7                  // Field compositeSnapshot:Z
       4: ifeq          11
       7: ldc2_w        #59                 // long -1l
      10: lreturn
      11: aload_0
      12: invokespecial #61                 // Method getLastSegment:()Lorg/apache/hadoop/hbase/regionserver/Segment;
      15: astore_1
      16: aload_1
      17: ifnonnull     24
      20: ldc2_w        #59                 // long -1l
      23: lreturn
      24: aload_1
      25: invokevirtual #62                 // Method org/apache/hadoop/hbase/regionserver/Segment.getMinSequenceId:()J
      28: lreturn

  public boolean isSloppy();
    Code:
       0: iconst_1
       1: ireturn

  public org.apache.hadoop.hbase.regionserver.MemStoreSnapshot snapshot();
    Code:
       0: aload_0
       1: getfield      #63                 // Field snapshot:Lorg/apache/hadoop/hbase/regionserver/ImmutableSegment;
       4: invokevirtual #64                 // Method org/apache/hadoop/hbase/regionserver/ImmutableSegment.isEmpty:()Z
       7: ifne          23
      10: getstatic     #23                 // Field LOG:Lorg/slf4j/Logger;
      13: ldc           #65                 // String Snapshot called again without clearing previous. Doing nothing. Another ongoing flush or did we fail last attempt?
      15: invokeinterface #66,  2           // InterfaceMethod org/slf4j/Logger.warn:(Ljava/lang/String;)V
      20: goto          93
      23: getstatic     #23                 // Field LOG:Lorg/slf4j/Logger;
      26: ldc           #67                 // String FLUSHING TO DISK {}, store={}
      28: aload_0
      29: invokespecial #13                 // Method getRegionServices:()Lorg/apache/hadoop/hbase/regionserver/RegionServicesForStores;
      32: invokevirtual #68                 // Method org/apache/hadoop/hbase/regionserver/RegionServicesForStores.getRegionInfo:()Lorg/apache/hadoop/hbase/client/RegionInfo;
      35: invokeinterface #69,  1           // InterfaceMethod org/apache/hadoop/hbase/client/RegionInfo.getEncodedName:()Ljava/lang/String;
      40: aload_0
      41: invokevirtual #70                 // Method getFamilyName:()Ljava/lang/String;
      44: invokeinterface #71,  4           // InterfaceMethod org/slf4j/Logger.debug:(Ljava/lang/String;Ljava/lang/Object;Ljava/lang/Object;)V
      49: aload_0
      50: invokespecial #72                 // Method stopCompaction:()V
      53: aload_0
      54: aload_0
      55: invokevirtual #48                 // Method getActive:()Lorg/apache/hadoop/hbase/regionserver/MutableSegment;
      58: invokevirtual #73                 // Method pushActiveToPipeline:(Lorg/apache/hadoop/hbase/regionserver/MutableSegment;)V
      61: aload_0
      62: invokestatic  #74                 // Method org/apache/hadoop/hbase/util/EnvironmentEdgeManager.currentTime:()J
      65: putfield      #75                 // Field snapshotId:J
      68: aload_0
      69: getfield      #7                  // Field compositeSnapshot:Z
      72: ifeq          82
      75: aload_0
      76: invokespecial #76                 // Method pushPipelineToSnapshot:()V
      79: goto          86
      82: aload_0
      83: invokespecial #77                 // Method pushTailToSnapshot:()V
      86: aload_0
      87: getfield      #17                 // Field compactor:Lorg/apache/hadoop/hbase/regionserver/MemStoreCompactor;
      90: invokevirtual #78                 // Method org/apache/hadoop/hbase/regionserver/MemStoreCompactor.resetStats:()V
      93: new           #79                 // class org/apache/hadoop/hbase/regionserver/MemStoreSnapshot
      96: dup
      97: aload_0
      98: getfield      #75                 // Field snapshotId:J
     101: aload_0
     102: getfield      #63                 // Field snapshot:Lorg/apache/hadoop/hbase/regionserver/ImmutableSegment;
     105: invokespecial #80                 // Method org/apache/hadoop/hbase/regionserver/MemStoreSnapshot."<init>":(JLorg/apache/hadoop/hbase/regionserver/ImmutableSegment;)V
     108: areturn

  public org.apache.hadoop.hbase.regionserver.MemStoreSize getFlushableSize();
    Code:
       0: aload_0
       1: invokevirtual #81                 // Method getSnapshotSize:()Lorg/apache/hadoop/hbase/regionserver/MemStoreSize;
       4: astore_1
       5: aload_1
       6: invokevirtual #82                 // Method org/apache/hadoop/hbase/regionserver/MemStoreSize.getDataSize:()J
       9: lconst_0
      10: lcmp
      11: ifne          77
      14: aload_0
      15: getfield      #7                  // Field compositeSnapshot:Z
      18: ifeq          69
      21: new           #46                 // class org/apache/hadoop/hbase/regionserver/NonThreadSafeMemStoreSizing
      24: dup
      25: aload_0
      26: getfield      #15                 // Field pipeline:Lorg/apache/hadoop/hbase/regionserver/CompactionPipeline;
      29: invokevirtual #83                 // Method org/apache/hadoop/hbase/regionserver/CompactionPipeline.getPipelineSize:()Lorg/apache/hadoop/hbase/regionserver/MemStoreSize;
      32: invokespecial #84                 // Method org/apache/hadoop/hbase/regionserver/NonThreadSafeMemStoreSizing."<init>":(Lorg/apache/hadoop/hbase/regionserver/MemStoreSize;)V
      35: astore_2
      36: aload_0
      37: invokevirtual #48                 // Method getActive:()Lorg/apache/hadoop/hbase/regionserver/MutableSegment;
      40: astore_3
      41: aload_3
      42: invokevirtual #85                 // Method org/apache/hadoop/hbase/regionserver/MutableSegment.isEmpty:()Z
      45: ifne          59
      48: aload_2
      49: aload_3
      50: invokevirtual #49                 // Method org/apache/hadoop/hbase/regionserver/MutableSegment.getMemStoreSize:()Lorg/apache/hadoop/hbase/regionserver/MemStoreSize;
      53: invokeinterface #50,  2           // InterfaceMethod org/apache/hadoop/hbase/regionserver/MemStoreSizing.incMemStoreSize:(Lorg/apache/hadoop/hbase/regionserver/MemStoreSize;)J
      58: pop2
      59: aload_2
      60: invokeinterface #57,  1           // InterfaceMethod org/apache/hadoop/hbase/regionserver/MemStoreSizing.getMemStoreSize:()Lorg/apache/hadoop/hbase/regionserver/MemStoreSize;
      65: astore_1
      66: goto          77
      69: aload_0
      70: getfield      #15                 // Field pipeline:Lorg/apache/hadoop/hbase/regionserver/CompactionPipeline;
      73: invokevirtual #86                 // Method org/apache/hadoop/hbase/regionserver/CompactionPipeline.getTailSize:()Lorg/apache/hadoop/hbase/regionserver/MemStoreSize;
      76: astore_1
      77: aload_1
      78: invokevirtual #82                 // Method org/apache/hadoop/hbase/regionserver/MemStoreSize.getDataSize:()J
      81: lconst_0
      82: lcmp
      83: ifle          90
      86: aload_1
      87: goto          97
      90: aload_0
      91: invokevirtual #48                 // Method getActive:()Lorg/apache/hadoop/hbase/regionserver/MutableSegment;
      94: invokevirtual #49                 // Method org/apache/hadoop/hbase/regionserver/MutableSegment.getMemStoreSize:()Lorg/apache/hadoop/hbase/regionserver/MemStoreSize;
      97: areturn

  public void setInMemoryCompactionCompleted();
    Code:
       0: aload_0
       1: getfield      #4                  // Field inMemoryCompactionInProgress:Ljava/util/concurrent/atomic/AtomicBoolean;
       4: iconst_0
       5: invokevirtual #87                 // Method java/util/concurrent/atomic/AtomicBoolean.set:(Z)V
       8: return

  protected boolean setInMemoryCompactionFlag();
    Code:
       0: aload_0
       1: getfield      #4                  // Field inMemoryCompactionInProgress:Ljava/util/concurrent/atomic/AtomicBoolean;
       4: iconst_0
       5: iconst_1
       6: invokevirtual #88                 // Method java/util/concurrent/atomic/AtomicBoolean.compareAndSet:(ZZ)Z
       9: ireturn

  protected long keySize();
    Code:
       0: aload_0
       1: invokevirtual #48                 // Method getActive:()Lorg/apache/hadoop/hbase/regionserver/MutableSegment;
       4: invokevirtual #89                 // Method org/apache/hadoop/hbase/regionserver/MutableSegment.getDataSize:()J
       7: lstore_1
       8: aload_0
       9: getfield      #15                 // Field pipeline:Lorg/apache/hadoop/hbase/regionserver/CompactionPipeline;
      12: invokevirtual #51                 // Method org/apache/hadoop/hbase/regionserver/CompactionPipeline.getSegments:()Ljava/util/List;
      15: invokeinterface #52,  1           // InterfaceMethod java/util/List.iterator:()Ljava/util/Iterator;
      20: astore_3
      21: aload_3
      22: invokeinterface #53,  1           // InterfaceMethod java/util/Iterator.hasNext:()Z
      27: ifeq          52
      30: aload_3
      31: invokeinterface #54,  1           // InterfaceMethod java/util/Iterator.next:()Ljava/lang/Object;
      36: checkcast     #55                 // class org/apache/hadoop/hbase/regionserver/Segment
      39: astore        4
      41: lload_1
      42: aload         4
      44: invokevirtual #90                 // Method org/apache/hadoop/hbase/regionserver/Segment.getDataSize:()J
      47: ladd
      48: lstore_1
      49: goto          21
      52: lload_1
      53: lreturn

  protected long heapSize();
    Code:
       0: aload_0
       1: invokevirtual #48                 // Method getActive:()Lorg/apache/hadoop/hbase/regionserver/MutableSegment;
       4: invokevirtual #91                 // Method org/apache/hadoop/hbase/regionserver/MutableSegment.getHeapSize:()J
       7: lstore_1
       8: aload_0
       9: getfield      #15                 // Field pipeline:Lorg/apache/hadoop/hbase/regionserver/CompactionPipeline;
      12: invokevirtual #51                 // Method org/apache/hadoop/hbase/regionserver/CompactionPipeline.getSegments:()Ljava/util/List;
      15: invokeinterface #52,  1           // InterfaceMethod java/util/List.iterator:()Ljava/util/Iterator;
      20: astore_3
      21: aload_3
      22: invokeinterface #53,  1           // InterfaceMethod java/util/Iterator.hasNext:()Z
      27: ifeq          52
      30: aload_3
      31: invokeinterface #54,  1           // InterfaceMethod java/util/Iterator.next:()Ljava/lang/Object;
      36: checkcast     #55                 // class org/apache/hadoop/hbase/regionserver/Segment
      39: astore        4
      41: lload_1
      42: aload         4
      44: invokevirtual #92                 // Method org/apache/hadoop/hbase/regionserver/Segment.getHeapSize:()J
      47: ladd
      48: lstore_1
      49: goto          21
      52: lload_1
      53: lreturn

  public void updateLowestUnflushedSequenceIdInWAL(boolean);
    Code:
       0: aload_0
       1: getfield      #15                 // Field pipeline:Lorg/apache/hadoop/hbase/regionserver/CompactionPipeline;
       4: invokevirtual #93                 // Method org/apache/hadoop/hbase/regionserver/CompactionPipeline.getMinSequenceId:()J
       7: lstore_2
       8: lload_2
       9: ldc2_w        #95                 // long 9223372036854775807l
      12: lcmp
      13: ifeq          66
      16: aload_0
      17: invokespecial #13                 // Method getRegionServices:()Lorg/apache/hadoop/hbase/regionserver/RegionServicesForStores;
      20: invokevirtual #68                 // Method org/apache/hadoop/hbase/regionserver/RegionServicesForStores.getRegionInfo:()Lorg/apache/hadoop/hbase/client/RegionInfo;
      23: invokeinterface #97,  1           // InterfaceMethod org/apache/hadoop/hbase/client/RegionInfo.getEncodedNameAsBytes:()[B
      28: astore        4
      30: aload_0
      31: invokespecial #98                 // Method getFamilyNameInBytes:()[B
      34: astore        5
      36: aload_0
      37: invokespecial #13                 // Method getRegionServices:()Lorg/apache/hadoop/hbase/regionserver/RegionServicesForStores;
      40: invokevirtual #99                 // Method org/apache/hadoop/hbase/regionserver/RegionServicesForStores.getWAL:()Lorg/apache/hadoop/hbase/wal/WAL;
      43: astore        6
      45: aload         6
      47: ifnull        66
      50: aload         6
      52: aload         4
      54: aload         5
      56: lload_2
      57: invokestatic  #100                // Method java/lang/Long.valueOf:(J)Ljava/lang/Long;
      60: iload_1
      61: invokeinterface #101,  5          // InterfaceMethod org/apache/hadoop/hbase/wal/WAL.updateStore:([B[BLjava/lang/Long;Z)V
      66: return

  public void startReplayingFromWAL();
    Code:
       0: aload_0
       1: iconst_1
       2: putfield      #5                  // Field inWalReplay:Z
       5: return

  public void stopReplayingFromWAL();
    Code:
       0: aload_0
       1: iconst_0
       2: putfield      #5                  // Field inWalReplay:Z
       5: return

  protected boolean preUpdate(org.apache.hadoop.hbase.regionserver.MutableSegment, org.apache.hadoop.hbase.Cell, org.apache.hadoop.hbase.regionserver.MemStoreSizing);
    Code:
       0: aload_1
       1: invokevirtual #102                // Method org/apache/hadoop/hbase/regionserver/MutableSegment.sharedLock:()Z
       4: ifeq          23
       7: aload_0
       8: aload_1
       9: aload_2
      10: aload_3
      11: invokespecial #103                // Method checkAndAddToActiveSize:(Lorg/apache/hadoop/hbase/regionserver/MutableSegment;Lorg/apache/hadoop/hbase/Cell;Lorg/apache/hadoop/hbase/regionserver/MemStoreSizing;)Z
      14: ifeq          19
      17: iconst_1
      18: ireturn
      19: aload_1
      20: invokevirtual #104                // Method org/apache/hadoop/hbase/regionserver/MutableSegment.sharedUnlock:()V
      23: iconst_0
      24: ireturn

  protected void postUpdate(org.apache.hadoop.hbase.regionserver.MutableSegment);
    Code:
       0: aload_1
       1: invokevirtual #104                // Method org/apache/hadoop/hbase/regionserver/MutableSegment.sharedUnlock:()V
       4: return

  protected boolean sizeAddedPreOperation();
    Code:
       0: iconst_1
       1: ireturn

  protected java.util.List<org.apache.hadoop.hbase.regionserver.Segment> getSegments();
    Code:
       0: aload_0
       1: getfield      #15                 // Field pipeline:Lorg/apache/hadoop/hbase/regionserver/CompactionPipeline;
       4: invokevirtual #51                 // Method org/apache/hadoop/hbase/regionserver/CompactionPipeline.getSegments:()Ljava/util/List;
       7: astore_1
       8: new           #105                // class java/util/ArrayList
      11: dup
      12: aload_1
      13: invokeinterface #106,  1          // InterfaceMethod java/util/List.size:()I
      18: iconst_2
      19: iadd
      20: invokespecial #107                // Method java/util/ArrayList."<init>":(I)V
      23: astore_2
      24: aload_2
      25: aload_0
      26: invokevirtual #48                 // Method getActive:()Lorg/apache/hadoop/hbase/regionserver/MutableSegment;
      29: invokeinterface #108,  2          // InterfaceMethod java/util/List.add:(Ljava/lang/Object;)Z
      34: pop
      35: aload_2
      36: aload_1
      37: invokeinterface #109,  2          // InterfaceMethod java/util/List.addAll:(Ljava/util/Collection;)Z
      42: pop
      43: aload_2
      44: aload_0
      45: getfield      #63                 // Field snapshot:Lorg/apache/hadoop/hbase/regionserver/ImmutableSegment;
      48: invokevirtual #110                // Method org/apache/hadoop/hbase/regionserver/ImmutableSegment.getAllSegments:()Ljava/util/List;
      51: invokeinterface #109,  2          // InterfaceMethod java/util/List.addAll:(Ljava/util/Collection;)Z
      56: pop
      57: aload_2
      58: areturn

  public void setCompositeSnapshot(boolean);
    Code:
       0: aload_0
       1: iload_1
       2: putfield      #7                  // Field compositeSnapshot:Z
       5: return

  public boolean swapCompactedSegments(org.apache.hadoop.hbase.regionserver.VersionedSegmentsList, org.apache.hadoop.hbase.regionserver.ImmutableSegment, boolean);
    Code:
       0: aload_0
       1: getfield      #15                 // Field pipeline:Lorg/apache/hadoop/hbase/regionserver/CompactionPipeline;
       4: aload_1
       5: aload_2
       6: iload_3
       7: ifne          14
      10: iconst_1
      11: goto          15
      14: iconst_0
      15: iconst_1
      16: invokevirtual #111                // Method org/apache/hadoop/hbase/regionserver/CompactionPipeline.swap:(Lorg/apache/hadoop/hbase/regionserver/VersionedSegmentsList;Lorg/apache/hadoop/hbase/regionserver/ImmutableSegment;ZZ)Z
      19: ireturn

  public void flattenOneSegment(long, org.apache.hadoop.hbase.regionserver.MemStoreCompactionStrategy$Action);
    Code:
       0: aload_0
       1: getfield      #15                 // Field pipeline:Lorg/apache/hadoop/hbase/regionserver/CompactionPipeline;
       4: lload_1
       5: aload_0
       6: getfield      #9                  // Field indexType:Lorg/apache/hadoop/hbase/regionserver/CompactingMemStore$IndexType;
       9: aload_3
      10: invokevirtual #112                // Method org/apache/hadoop/hbase/regionserver/CompactionPipeline.flattenOneSegment:(JLorg/apache/hadoop/hbase/regionserver/CompactingMemStore$IndexType;Lorg/apache/hadoop/hbase/regionserver/MemStoreCompactionStrategy$Action;)Z
      13: pop
      14: return

  void setIndexType(org.apache.hadoop.hbase.regionserver.CompactingMemStore$IndexType);
    Code:
       0: aload_0
       1: aload_1
       2: putfield      #9                  // Field indexType:Lorg/apache/hadoop/hbase/regionserver/CompactingMemStore$IndexType;
       5: return

  public org.apache.hadoop.hbase.regionserver.CompactingMemStore$IndexType getIndexType();
    Code:
       0: aload_0
       1: getfield      #9                  // Field indexType:Lorg/apache/hadoop/hbase/regionserver/CompactingMemStore$IndexType;
       4: areturn

  public boolean hasImmutableSegments();
    Code:
       0: aload_0
       1: getfield      #15                 // Field pipeline:Lorg/apache/hadoop/hbase/regionserver/CompactionPipeline;
       4: invokevirtual #113                // Method org/apache/hadoop/hbase/regionserver/CompactionPipeline.isEmpty:()Z
       7: ifne          14
      10: iconst_1
      11: goto          15
      14: iconst_0
      15: ireturn

  public org.apache.hadoop.hbase.regionserver.VersionedSegmentsList getImmutableSegments();
    Code:
       0: aload_0
       1: getfield      #15                 // Field pipeline:Lorg/apache/hadoop/hbase/regionserver/CompactionPipeline;
       4: invokevirtual #114                // Method org/apache/hadoop/hbase/regionserver/CompactionPipeline.getVersionedList:()Lorg/apache/hadoop/hbase/regionserver/VersionedSegmentsList;
       7: areturn

  public long getSmallestReadPoint();
    Code:
       0: aload_0
       1: getfield      #10                 // Field store:Lorg/apache/hadoop/hbase/regionserver/HStore;
       4: invokevirtual #115                // Method org/apache/hadoop/hbase/regionserver/HStore.getSmallestReadPoint:()J
       7: lreturn

  public org.apache.hadoop.hbase.regionserver.HStore getStore();
    Code:
       0: aload_0
       1: getfield      #10                 // Field store:Lorg/apache/hadoop/hbase/regionserver/HStore;
       4: areturn

  public java.lang.String getFamilyName();
    Code:
       0: aload_0
       1: invokespecial #98                 // Method getFamilyNameInBytes:()[B
       4: invokestatic  #116                // Method org/apache/hadoop/hbase/util/Bytes.toString:([B)Ljava/lang/String;
       7: areturn

  public java.util.List<org.apache.hadoop.hbase.regionserver.KeyValueScanner> getScanners(long) throws java.io.IOException;
    Code:
       0: aload_0
       1: invokevirtual #48                 // Method getActive:()Lorg/apache/hadoop/hbase/regionserver/MutableSegment;
       4: astore_3
       5: aload_0
       6: getfield      #15                 // Field pipeline:Lorg/apache/hadoop/hbase/regionserver/CompactionPipeline;
       9: invokevirtual #51                 // Method org/apache/hadoop/hbase/regionserver/CompactionPipeline.getSegments:()Ljava/util/List;
      12: astore        4
      14: aload_0
      15: getfield      #63                 // Field snapshot:Lorg/apache/hadoop/hbase/regionserver/ImmutableSegment;
      18: invokevirtual #110                // Method org/apache/hadoop/hbase/regionserver/ImmutableSegment.getAllSegments:()Ljava/util/List;
      21: astore        5
      23: lconst_1
      24: aload         4
      26: invokeinterface #106,  1          // InterfaceMethod java/util/List.size:()I
      31: i2l
      32: ladd
      33: aload         5
      35: invokeinterface #106,  1          // InterfaceMethod java/util/List.size:()I
      40: i2l
      41: ladd
      42: lstore        6
      44: aload_0
      45: lload         6
      47: l2i
      48: invokevirtual #117                // Method createList:(I)Ljava/util/List;
      51: astore        8
      53: aload_3
      54: lload_1
      55: aload         8
      57: invokestatic  #118                // Method addToScanners:(Lorg/apache/hadoop/hbase/regionserver/Segment;JLjava/util/List;)V
      60: aload         4
      62: lload_1
      63: aload         8
      65: invokestatic  #119                // Method addToScanners:(Ljava/util/List;JLjava/util/List;)V
      68: aload         5
      70: lload_1
      71: aload         8
      73: invokestatic  #119                // Method addToScanners:(Ljava/util/List;JLjava/util/List;)V
      76: aload         8
      78: areturn

  protected java.util.List<org.apache.hadoop.hbase.regionserver.KeyValueScanner> createList(int);
    Code:
       0: new           #105                // class java/util/ArrayList
       3: dup
       4: iload_1
       5: invokespecial #107                // Method java/util/ArrayList."<init>":(I)V
       8: areturn

  void flushInMemory();
    Code:
       0: aload_0
       1: invokevirtual #48                 // Method getActive:()Lorg/apache/hadoop/hbase/regionserver/MutableSegment;
       4: astore_1
       5: aload_1
       6: invokevirtual #121                // Method org/apache/hadoop/hbase/regionserver/MutableSegment.setInMemoryFlushed:()Z
       9: ifeq          17
      12: aload_0
      13: aload_1
      14: invokespecial #122                // Method flushInMemory:(Lorg/apache/hadoop/hbase/regionserver/MutableSegment;)V
      17: aload_0
      18: invokevirtual #135                // Method inMemoryCompaction:()V
      21: return

  void inMemoryCompaction();
    Code:
       0: aload_0
       1: getfield      #4                  // Field inMemoryCompactionInProgress:Ljava/util/concurrent/atomic/AtomicBoolean;
       4: iconst_1
       5: invokevirtual #87                 // Method java/util/concurrent/atomic/AtomicBoolean.set:(Z)V
       8: aload_0
       9: getfield      #6                  // Field allowCompaction:Ljava/util/concurrent/atomic/AtomicBoolean;
      12: invokevirtual #137                // Method java/util/concurrent/atomic/AtomicBoolean.get:()Z
      15: ifne          19
      18: return
      19: aload_0
      20: getfield      #17                 // Field compactor:Lorg/apache/hadoop/hbase/regionserver/MemStoreCompactor;
      23: invokevirtual #138                // Method org/apache/hadoop/hbase/regionserver/MemStoreCompactor.start:()Z
      26: ifne          33
      29: aload_0
      30: invokevirtual #139                // Method setInMemoryCompactionCompleted:()V
      33: goto          77
      36: astore_1
      37: getstatic     #23                 // Field LOG:Lorg/slf4j/Logger;
      40: ldc           #141                // String Unable to run in-memory compaction on {}/{}; exception={}
      42: iconst_3
      43: anewarray     #25                 // class java/lang/Object
      46: dup
      47: iconst_0
      48: aload_0
      49: invokespecial #13                 // Method getRegionServices:()Lorg/apache/hadoop/hbase/regionserver/RegionServicesForStores;
      52: invokevirtual #68                 // Method org/apache/hadoop/hbase/regionserver/RegionServicesForStores.getRegionInfo:()Lorg/apache/hadoop/hbase/client/RegionInfo;
      55: invokeinterface #69,  1           // InterfaceMethod org/apache/hadoop/hbase/client/RegionInfo.getEncodedName:()Ljava/lang/String;
      60: aastore
      61: dup
      62: iconst_1
      63: aload_0
      64: invokevirtual #70                 // Method getFamilyName:()Ljava/lang/String;
      67: aastore
      68: dup
      69: iconst_2
      70: aload_1
      71: aastore
      72: invokeinterface #142,  3          // InterfaceMethod org/slf4j/Logger.warn:(Ljava/lang/String;[Ljava/lang/Object;)V
      77: return
    Exception table:
       from    to  target type
          19    33    36   Class java/io/IOException

  protected boolean shouldFlushInMemory(org.apache.hadoop.hbase.regionserver.MutableSegment, org.apache.hadoop.hbase.Cell, org.apache.hadoop.hbase.regionserver.MemStoreSizing);
    Code:
       0: aload_1
       1: pop
       2: aload_2
       3: invokestatic  #147                // Method org/apache/hadoop/hbase/regionserver/MutableSegment.getCellLength:(Lorg/apache/hadoop/hbase/Cell;)I
       6: i2l
       7: lstore        4
       9: aload_1
      10: invokevirtual #89                 // Method org/apache/hadoop/hbase/regionserver/MutableSegment.getDataSize:()J
      13: lstore        6
      15: lload         6
      17: lload         4
      19: ladd
      20: aload_0
      21: getfield      #27                 // Field inmemoryFlushSize:J
      24: lcmp
      25: iflt          35
      28: aload_0
      29: getfield      #5                  // Field inWalReplay:Z
      32: ifeq          76
      35: aload_1
      36: lload         6
      38: lload         6
      40: lload         4
      42: ladd
      43: invokevirtual #148                // Method org/apache/hadoop/hbase/regionserver/MutableSegment.compareAndSetDataSize:(JJ)Z
      46: ifeq          67
      49: aload_3
      50: ifnull        65
      53: aload_3
      54: lload         4
      56: lconst_0
      57: lconst_0
      58: iconst_0
      59: invokeinterface #149,  8          // InterfaceMethod org/apache/hadoop/hbase/regionserver/MemStoreSizing.incMemStoreSize:(JJJI)J
      64: pop2
      65: iconst_0
      66: ireturn
      67: aload_1
      68: invokevirtual #89                 // Method org/apache/hadoop/hbase/regionserver/MutableSegment.getDataSize:()J
      71: lstore        6
      73: goto          15
      76: iconst_1
      77: ireturn

  protected void pushActiveToPipeline(org.apache.hadoop.hbase.regionserver.MutableSegment);
    Code:
       0: aload_1
       1: invokevirtual #85                 // Method org/apache/hadoop/hbase/regionserver/MutableSegment.isEmpty:()Z
       4: ifne          20
       7: aload_0
       8: getfield      #15                 // Field pipeline:Lorg/apache/hadoop/hbase/regionserver/CompactionPipeline;
      11: aload_1
      12: invokevirtual #151                // Method org/apache/hadoop/hbase/regionserver/CompactionPipeline.pushHead:(Lorg/apache/hadoop/hbase/regionserver/MutableSegment;)Z
      15: pop
      16: aload_0
      17: invokevirtual #152                // Method resetActive:()V
      20: return

  boolean isMemStoreFlushingInMemory();
    Code:
       0: aload_0
       1: getfield      #4                  // Field inMemoryCompactionInProgress:Ljava/util/concurrent/atomic/AtomicBoolean;
       4: invokevirtual #137                // Method java/util/concurrent/atomic/AtomicBoolean.get:()Z
       7: ireturn

  org.apache.hadoop.hbase.Cell getNextRow(org.apache.hadoop.hbase.Cell);
    Code:
       0: aconst_null
       1: astore_2
       2: aload_0
       3: invokevirtual #164                // Method getSegments:()Ljava/util/List;
       6: astore_3
       7: aload_3
       8: invokeinterface #52,  1           // InterfaceMethod java/util/List.iterator:()Ljava/util/Iterator;
      13: astore        4
      15: aload         4
      17: invokeinterface #53,  1           // InterfaceMethod java/util/Iterator.hasNext:()Z
      22: ifeq          74
      25: aload         4
      27: invokeinterface #54,  1           // InterfaceMethod java/util/Iterator.next:()Ljava/lang/Object;
      32: checkcast     #55                 // class org/apache/hadoop/hbase/regionserver/Segment
      35: astore        5
      37: aload_2
      38: ifnonnull     55
      41: aload_0
      42: aload_1
      43: aload         5
      45: invokevirtual #165                // Method org/apache/hadoop/hbase/regionserver/Segment.getCellSet:()Lorg/apache/hadoop/hbase/regionserver/CellSet;
      48: invokevirtual #166                // Method getNextRow:(Lorg/apache/hadoop/hbase/Cell;Ljava/util/NavigableSet;)Lorg/apache/hadoop/hbase/Cell;
      51: astore_2
      52: goto          71
      55: aload_0
      56: aload_2
      57: aload_0
      58: aload_1
      59: aload         5
      61: invokevirtual #165                // Method org/apache/hadoop/hbase/regionserver/Segment.getCellSet:()Lorg/apache/hadoop/hbase/regionserver/CellSet;
      64: invokevirtual #166                // Method getNextRow:(Lorg/apache/hadoop/hbase/Cell;Ljava/util/NavigableSet;)Lorg/apache/hadoop/hbase/Cell;
      67: invokevirtual #167                // Method getLowest:(Lorg/apache/hadoop/hbase/Cell;Lorg/apache/hadoop/hbase/Cell;)Lorg/apache/hadoop/hbase/Cell;
      70: astore_2
      71: goto          15
      74: aload_2
      75: areturn

  long getInmemoryFlushSize();
    Code:
       0: aload_0
       1: getfield      #27                 // Field inmemoryFlushSize:J
       4: lreturn

  public void debug();
    Code:
       0: new           #127                // class java/lang/StringBuilder
       3: dup
       4: invokespecial #128                // Method java/lang/StringBuilder."<init>":()V
       7: ldc           #168                // String active size=
       9: invokevirtual #130                // Method java/lang/StringBuilder.append:(Ljava/lang/String;)Ljava/lang/StringBuilder;
      12: aload_0
      13: invokevirtual #48                 // Method getActive:()Lorg/apache/hadoop/hbase/regionserver/MutableSegment;
      16: invokevirtual #89                 // Method org/apache/hadoop/hbase/regionserver/MutableSegment.getDataSize:()J
      19: invokevirtual #169                // Method java/lang/StringBuilder.append:(J)Ljava/lang/StringBuilder;
      22: invokevirtual #131                // Method java/lang/StringBuilder.toString:()Ljava/lang/String;
      25: astore_1
      26: new           #127                // class java/lang/StringBuilder
      29: dup
      30: invokespecial #128                // Method java/lang/StringBuilder."<init>":()V
      33: aload_1
      34: invokevirtual #130                // Method java/lang/StringBuilder.append:(Ljava/lang/String;)Ljava/lang/StringBuilder;
      37: ldc           #170                // String  allow compaction is
      39: invokevirtual #130                // Method java/lang/StringBuilder.append:(Ljava/lang/String;)Ljava/lang/StringBuilder;
      42: aload_0
      43: getfield      #6                  // Field allowCompaction:Ljava/util/concurrent/atomic/AtomicBoolean;
      46: invokevirtual #137                // Method java/util/concurrent/atomic/AtomicBoolean.get:()Z
      49: ifeq          57
      52: ldc           #171                // String true
      54: goto          59
      57: ldc           #172                // String false
      59: invokevirtual #130                // Method java/lang/StringBuilder.append:(Ljava/lang/String;)Ljava/lang/StringBuilder;
      62: invokevirtual #131                // Method java/lang/StringBuilder.toString:()Ljava/lang/String;
      65: astore_1
      66: new           #127                // class java/lang/StringBuilder
      69: dup
      70: invokespecial #128                // Method java/lang/StringBuilder."<init>":()V
      73: aload_1
      74: invokevirtual #130                // Method java/lang/StringBuilder.append:(Ljava/lang/String;)Ljava/lang/StringBuilder;
      77: ldc           #173                // String  inMemoryCompactionInProgress is
      79: invokevirtual #130                // Method java/lang/StringBuilder.append:(Ljava/lang/String;)Ljava/lang/StringBuilder;
      82: aload_0
      83: getfield      #4                  // Field inMemoryCompactionInProgress:Ljava/util/concurrent/atomic/AtomicBoolean;
      86: invokevirtual #137                // Method java/util/concurrent/atomic/AtomicBoolean.get:()Z
      89: ifeq          97
      92: ldc           #171                // String true
      94: goto          99
      97: ldc           #172                // String false
      99: invokevirtual #130                // Method java/lang/StringBuilder.append:(Ljava/lang/String;)Ljava/lang/StringBuilder;
     102: invokevirtual #131                // Method java/lang/StringBuilder.toString:()Ljava/lang/String;
     105: astore_1
     106: getstatic     #23                 // Field LOG:Lorg/slf4j/Logger;
     109: aload_1
     110: invokeinterface #174,  2          // InterfaceMethod org/slf4j/Logger.debug:(Ljava/lang/String;)V
     115: return

  static {};
    Code:
       0: getstatic     #175                // Field org/apache/hadoop/hbase/MemoryCompactionPolicy.NONE:Lorg/apache/hadoop/hbase/MemoryCompactionPolicy;
       3: invokestatic  #176                // Method java/lang/String.valueOf:(Ljava/lang/Object;)Ljava/lang/String;
       6: putstatic     #177                // Field COMPACTING_MEMSTORE_TYPE_DEFAULT:Ljava/lang/String;
       9: ldc           #36                 // class org/apache/hadoop/hbase/regionserver/CompactingMemStore
      11: invokestatic  #178                // Method org/slf4j/LoggerFactory.getLogger:(Ljava/lang/Class;)Lorg/slf4j/Logger;
      14: putstatic     #23                 // Field LOG:Lorg/slf4j/Logger;
      17: getstatic     #179                // Field org/apache/hadoop/hbase/regionserver/AbstractMemStore.DEEP_OVERHEAD:J
      20: bipush        6
      22: getstatic     #180                // Field org/apache/hadoop/hbase/util/ClassSize.REFERENCE:I
      25: imul
      26: i2l
      27: ladd
      28: ldc2_w        #182                // long 8l
      31: ladd
      32: ldc2_w        #184                // long 2l
      35: ladd
      36: iconst_2
      37: getstatic     #186                // Field org/apache/hadoop/hbase/util/ClassSize.ATOMIC_BOOLEAN:I
      40: imul
      41: i2l
      42: ladd
      43: getstatic     #187                // Field org/apache/hadoop/hbase/regionserver/CompactionPipeline.DEEP_OVERHEAD:J
      46: ladd
      47: getstatic     #188                // Field org/apache/hadoop/hbase/regionserver/MemStoreCompactor.DEEP_OVERHEAD:J
      50: ladd
      51: invokestatic  #189                // Method org/apache/hadoop/hbase/util/ClassSize.align:(J)J
      54: putstatic     #190                // Field DEEP_OVERHEAD:J
      57: return
}
