Compiled from "CompactionScanQueryMatcher.java"
public abstract class org.apache.hadoop.hbase.regionserver.querymatcher.CompactionScanQueryMatcher extends org.apache.hadoop.hbase.regionserver.querymatcher.ScanQueryMatcher {
  protected final long maxReadPointToTrackVersions;

  protected final org.apache.hadoop.hbase.regionserver.querymatcher.DeleteTracker deletes;

  protected final org.apache.hadoop.hbase.KeepDeletedCells keepDeletedCells;

  protected org.apache.hadoop.hbase.regionserver.querymatcher.CompactionScanQueryMatcher(org.apache.hadoop.hbase.regionserver.ScanInfo, org.apache.hadoop.hbase.regionserver.querymatcher.DeleteTracker, org.apache.hadoop.hbase.regionserver.querymatcher.ColumnTracker, long, long, long);
    Code:
       0: aload_0
       1: getstatic     #1                  // Field org/apache/hadoop/hbase/HConstants.EMPTY_START_ROW:[B
       4: aload_1
       5: invokestatic  #2                  // Method createStartKeyFromRow:([BLorg/apache/hadoop/hbase/regionserver/ScanInfo;)Lorg/apache/hadoop/hbase/Cell;
       8: aload_1
       9: aload_3
      10: lload         6
      12: lload         8
      14: invokespecial #3                  // Method org/apache/hadoop/hbase/regionserver/querymatcher/ScanQueryMatcher."<init>":(Lorg/apache/hadoop/hbase/Cell;Lorg/apache/hadoop/hbase/regionserver/ScanInfo;Lorg/apache/hadoop/hbase/regionserver/querymatcher/ColumnTracker;JJ)V
      17: aload_0
      18: lload         4
      20: putfield      #4                  // Field maxReadPointToTrackVersions:J
      23: aload_0
      24: aload_2
      25: putfield      #5                  // Field deletes:Lorg/apache/hadoop/hbase/regionserver/querymatcher/DeleteTracker;
      28: aload_0
      29: aload_1
      30: invokevirtual #6                  // Method org/apache/hadoop/hbase/regionserver/ScanInfo.getKeepDeletedCells:()Lorg/apache/hadoop/hbase/KeepDeletedCells;
      33: putfield      #7                  // Field keepDeletedCells:Lorg/apache/hadoop/hbase/KeepDeletedCells;
      36: return

  public void beforeShipped() throws java.io.IOException;
    Code:
       0: aload_0
       1: invokespecial #8                  // Method org/apache/hadoop/hbase/regionserver/querymatcher/ScanQueryMatcher.beforeShipped:()V
       4: aload_0
       5: getfield      #5                  // Field deletes:Lorg/apache/hadoop/hbase/regionserver/querymatcher/DeleteTracker;
       8: invokeinterface #9,  1            // InterfaceMethod org/apache/hadoop/hbase/regionserver/querymatcher/DeleteTracker.beforeShipped:()V
      13: return

  public boolean hasNullColumnInQuery();
    Code:
       0: iconst_1
       1: ireturn

  public boolean isUserScan();
    Code:
       0: iconst_0
       1: ireturn

  public boolean moreRowsMayExistAfter(org.apache.hadoop.hbase.Cell);
    Code:
       0: iconst_1
       1: ireturn

  public org.apache.hadoop.hbase.filter.Filter getFilter();
    Code:
       0: aconst_null
       1: areturn

  public org.apache.hadoop.hbase.Cell getNextKeyHint(org.apache.hadoop.hbase.Cell) throws java.io.IOException;
    Code:
       0: aconst_null
       1: areturn

  protected void reset();
    Code:
       0: aload_0
       1: getfield      #5                  // Field deletes:Lorg/apache/hadoop/hbase/regionserver/querymatcher/DeleteTracker;
       4: invokeinterface #10,  1           // InterfaceMethod org/apache/hadoop/hbase/regionserver/querymatcher/DeleteTracker.reset:()V
       9: return

  protected final void trackDelete(org.apache.hadoop.hbase.Cell);
    Code:
       0: aload_0
       1: getfield      #7                  // Field keepDeletedCells:Lorg/apache/hadoop/hbase/KeepDeletedCells;
       4: getstatic     #11                 // Field org/apache/hadoop/hbase/KeepDeletedCells.FALSE:Lorg/apache/hadoop/hbase/KeepDeletedCells;
       7: if_acmpeq     34
      10: aload_0
      11: getfield      #7                  // Field keepDeletedCells:Lorg/apache/hadoop/hbase/KeepDeletedCells;
      14: getstatic     #12                 // Field org/apache/hadoop/hbase/KeepDeletedCells.TTL:Lorg/apache/hadoop/hbase/KeepDeletedCells;
      17: if_acmpne     44
      20: aload_1
      21: invokeinterface #13,  1           // InterfaceMethod org/apache/hadoop/hbase/Cell.getTimestamp:()J
      26: aload_0
      27: getfield      #14                 // Field oldestUnexpiredTS:J
      30: lcmp
      31: ifge          44
      34: aload_0
      35: getfield      #5                  // Field deletes:Lorg/apache/hadoop/hbase/regionserver/querymatcher/DeleteTracker;
      38: aload_1
      39: invokeinterface #15,  2           // InterfaceMethod org/apache/hadoop/hbase/regionserver/querymatcher/DeleteTracker.add:(Lorg/apache/hadoop/hbase/Cell;)V
      44: return

  public static org.apache.hadoop.hbase.regionserver.querymatcher.CompactionScanQueryMatcher create(org.apache.hadoop.hbase.regionserver.ScanInfo, org.apache.hadoop.hbase.regionserver.ScanType, long, long, long, long, byte[], byte[], org.apache.hadoop.hbase.regionserver.RegionCoprocessorHost) throws java.io.IOException;
    Code:
       0: aload         12
       2: aconst_null
       3: aload_0
       4: lload         6
       6: aconst_null
       7: invokestatic  #16                 // Method getTrackers:(Lorg/apache/hadoop/hbase/regionserver/RegionCoprocessorHost;Ljava/util/NavigableSet;Lorg/apache/hadoop/hbase/regionserver/ScanInfo;JLorg/apache/hadoop/hbase/client/Scan;)Lorg/apache/hadoop/hbase/util/Pair;
      10: astore        13
      12: aload         13
      14: invokevirtual #17                 // Method org/apache/hadoop/hbase/util/Pair.getFirst:()Ljava/lang/Object;
      17: checkcast     #18                 // class org/apache/hadoop/hbase/regionserver/querymatcher/DeleteTracker
      20: astore        14
      22: aload         13
      24: invokevirtual #19                 // Method org/apache/hadoop/hbase/util/Pair.getSecond:()Ljava/lang/Object;
      27: checkcast     #20                 // class org/apache/hadoop/hbase/regionserver/querymatcher/ColumnTracker
      30: astore        15
      32: aload         10
      34: ifnonnull     107
      37: aload_1
      38: getstatic     #21                 // Field org/apache/hadoop/hbase/regionserver/ScanType.COMPACT_RETAIN_DELETES:Lorg/apache/hadoop/hbase/regionserver/ScanType;
      41: if_acmpne     87
      44: aload_0
      45: invokevirtual #22                 // Method org/apache/hadoop/hbase/regionserver/ScanInfo.isNewVersionBehavior:()Z
      48: ifeq          69
      51: new           #23                 // class org/apache/hadoop/hbase/regionserver/querymatcher/IncludeAllCompactionQueryMatcher
      54: dup
      55: aload_0
      56: aload         14
      58: aload         15
      60: lload_2
      61: lload         6
      63: lload         8
      65: invokespecial #24                 // Method org/apache/hadoop/hbase/regionserver/querymatcher/IncludeAllCompactionQueryMatcher."<init>":(Lorg/apache/hadoop/hbase/regionserver/ScanInfo;Lorg/apache/hadoop/hbase/regionserver/querymatcher/DeleteTracker;Lorg/apache/hadoop/hbase/regionserver/querymatcher/ColumnTracker;JJJ)V
      68: areturn
      69: new           #25                 // class org/apache/hadoop/hbase/regionserver/querymatcher/MinorCompactionScanQueryMatcher
      72: dup
      73: aload_0
      74: aload         14
      76: aload         15
      78: lload_2
      79: lload         6
      81: lload         8
      83: invokespecial #26                 // Method org/apache/hadoop/hbase/regionserver/querymatcher/MinorCompactionScanQueryMatcher."<init>":(Lorg/apache/hadoop/hbase/regionserver/ScanInfo;Lorg/apache/hadoop/hbase/regionserver/querymatcher/DeleteTracker;Lorg/apache/hadoop/hbase/regionserver/querymatcher/ColumnTracker;JJJ)V
      86: areturn
      87: new           #27                 // class org/apache/hadoop/hbase/regionserver/querymatcher/MajorCompactionScanQueryMatcher
      90: dup
      91: aload_0
      92: aload         14
      94: aload         15
      96: lload_2
      97: lload         4
      99: lload         6
     101: lload         8
     103: invokespecial #28                 // Method org/apache/hadoop/hbase/regionserver/querymatcher/MajorCompactionScanQueryMatcher."<init>":(Lorg/apache/hadoop/hbase/regionserver/ScanInfo;Lorg/apache/hadoop/hbase/regionserver/querymatcher/DeleteTracker;Lorg/apache/hadoop/hbase/regionserver/querymatcher/ColumnTracker;JJJJ)V
     106: areturn
     107: new           #29                 // class org/apache/hadoop/hbase/regionserver/querymatcher/StripeCompactionScanQueryMatcher
     110: dup
     111: aload_0
     112: aload         14
     114: aload         15
     116: lload_2
     117: lload         4
     119: lload         6
     121: lload         8
     123: aload         10
     125: aload         11
     127: invokespecial #30                 // Method org/apache/hadoop/hbase/regionserver/querymatcher/StripeCompactionScanQueryMatcher."<init>":(Lorg/apache/hadoop/hbase/regionserver/ScanInfo;Lorg/apache/hadoop/hbase/regionserver/querymatcher/DeleteTracker;Lorg/apache/hadoop/hbase/regionserver/querymatcher/ColumnTracker;JJJJ[B[B)V
     130: areturn
}
