Compiled from "ConnectionFactory.java"
public class org.apache.hadoop.hbase.client.ConnectionFactory {
  public static final java.lang.String HBASE_CLIENT_ASYNC_CONNECTION_IMPL;

  protected org.apache.hadoop.hbase.client.ConnectionFactory();
    Code:
       0: aload_0
       1: invokespecial #1                  // Method java/lang/Object."<init>":()V
       4: return

  public static org.apache.hadoop.hbase.client.Connection createConnection() throws java.io.IOException;
    Code:
       0: invokestatic  #2                  // Method org/apache/hadoop/hbase/HBaseConfiguration.create:()Lorg/apache/hadoop/conf/Configuration;
       3: astore_0
       4: aload_0
       5: aconst_null
       6: aload_0
       7: invokestatic  #3                  // Method org/apache/hadoop/hbase/AuthUtil.loginClient:(Lorg/apache/hadoop/conf/Configuration;)Lorg/apache/hadoop/hbase/security/User;
      10: invokestatic  #4                  // Method createConnection:(Lorg/apache/hadoop/conf/Configuration;Ljava/util/concurrent/ExecutorService;Lorg/apache/hadoop/hbase/security/User;)Lorg/apache/hadoop/hbase/client/Connection;
      13: areturn

  public static org.apache.hadoop.hbase.client.Connection createConnection(org.apache.hadoop.conf.Configuration) throws java.io.IOException;
    Code:
       0: aload_0
       1: aconst_null
       2: aload_0
       3: invokestatic  #3                  // Method org/apache/hadoop/hbase/AuthUtil.loginClient:(Lorg/apache/hadoop/conf/Configuration;)Lorg/apache/hadoop/hbase/security/User;
       6: invokestatic  #4                  // Method createConnection:(Lorg/apache/hadoop/conf/Configuration;Ljava/util/concurrent/ExecutorService;Lorg/apache/hadoop/hbase/security/User;)Lorg/apache/hadoop/hbase/client/Connection;
       9: areturn

  public static org.apache.hadoop.hbase.client.Connection createConnection(org.apache.hadoop.conf.Configuration, java.util.concurrent.ExecutorService) throws java.io.IOException;
    Code:
       0: aload_0
       1: aload_1
       2: aload_0
       3: invokestatic  #3                  // Method org/apache/hadoop/hbase/AuthUtil.loginClient:(Lorg/apache/hadoop/conf/Configuration;)Lorg/apache/hadoop/hbase/security/User;
       6: invokestatic  #4                  // Method createConnection:(Lorg/apache/hadoop/conf/Configuration;Ljava/util/concurrent/ExecutorService;Lorg/apache/hadoop/hbase/security/User;)Lorg/apache/hadoop/hbase/client/Connection;
       9: areturn

  public static org.apache.hadoop.hbase.client.Connection createConnection(org.apache.hadoop.conf.Configuration, org.apache.hadoop.hbase.security.User) throws java.io.IOException;
    Code:
       0: aload_0
       1: aconst_null
       2: aload_1
       3: invokestatic  #4                  // Method createConnection:(Lorg/apache/hadoop/conf/Configuration;Ljava/util/concurrent/ExecutorService;Lorg/apache/hadoop/hbase/security/User;)Lorg/apache/hadoop/hbase/client/Connection;
       6: areturn

  public static org.apache.hadoop.hbase.client.Connection createConnection(org.apache.hadoop.conf.Configuration, java.util.concurrent.ExecutorService, org.apache.hadoop.hbase.security.User) throws java.io.IOException;
    Code:
       0: aload_0
       1: ldc           #6                  // String hbase.client.connection.impl
       3: ldc           #7                  // class org/apache/hadoop/hbase/client/ConnectionImplementation
       5: invokevirtual #8                  // Method java/lang/Class.getName:()Ljava/lang/String;
       8: invokevirtual #9                  // Method org/apache/hadoop/conf/Configuration.get:(Ljava/lang/String;Ljava/lang/String;)Ljava/lang/String;
      11: astore_3
      12: aload_3
      13: invokestatic  #10                 // Method java/lang/Class.forName:(Ljava/lang/String;)Ljava/lang/Class;
      16: astore        4
      18: goto          33
      21: astore        5
      23: new           #12                 // class java/io/IOException
      26: dup
      27: aload         5
      29: invokespecial #13                 // Method java/io/IOException."<init>":(Ljava/lang/Throwable;)V
      32: athrow
      33: aload         4
      35: iconst_3
      36: anewarray     #14                 // class java/lang/Class
      39: dup
      40: iconst_0
      41: ldc           #15                 // class org/apache/hadoop/conf/Configuration
      43: aastore
      44: dup
      45: iconst_1
      46: ldc           #16                 // class java/util/concurrent/ExecutorService
      48: aastore
      49: dup
      50: iconst_2
      51: ldc           #17                 // class org/apache/hadoop/hbase/security/User
      53: aastore
      54: invokevirtual #18                 // Method java/lang/Class.getDeclaredConstructor:([Ljava/lang/Class;)Ljava/lang/reflect/Constructor;
      57: astore        5
      59: aload         5
      61: iconst_1
      62: invokevirtual #19                 // Method java/lang/reflect/Constructor.setAccessible:(Z)V
      65: aload_2
      66: aload         5
      68: aload_0
      69: aload_1
      70: aload_2
      71: invokedynamic #20,  0             // InvokeDynamic #0:run:(Ljava/lang/reflect/Constructor;Lorg/apache/hadoop/conf/Configuration;Ljava/util/concurrent/ExecutorService;Lorg/apache/hadoop/hbase/security/User;)Ljava/security/PrivilegedExceptionAction;
      76: invokevirtual #21                 // Method org/apache/hadoop/hbase/security/User.runAs:(Ljava/security/PrivilegedExceptionAction;)Ljava/lang/Object;
      79: checkcast     #22                 // class org/apache/hadoop/hbase/client/Connection
      82: areturn
      83: astore        5
      85: new           #12                 // class java/io/IOException
      88: dup
      89: aload         5
      91: invokespecial #13                 // Method java/io/IOException."<init>":(Ljava/lang/Throwable;)V
      94: athrow
    Exception table:
       from    to  target type
          12    18    21   Class java/lang/ClassNotFoundException
          33    82    83   Class java/lang/Exception

  public static java.util.concurrent.CompletableFuture<org.apache.hadoop.hbase.client.AsyncConnection> createAsyncConnection();
    Code:
       0: invokestatic  #2                  // Method org/apache/hadoop/hbase/HBaseConfiguration.create:()Lorg/apache/hadoop/conf/Configuration;
       3: invokestatic  #24                 // Method createAsyncConnection:(Lorg/apache/hadoop/conf/Configuration;)Ljava/util/concurrent/CompletableFuture;
       6: areturn

  public static java.util.concurrent.CompletableFuture<org.apache.hadoop.hbase.client.AsyncConnection> createAsyncConnection(org.apache.hadoop.conf.Configuration);
    Code:
       0: aload_0
       1: invokestatic  #3                  // Method org/apache/hadoop/hbase/AuthUtil.loginClient:(Lorg/apache/hadoop/conf/Configuration;)Lorg/apache/hadoop/hbase/security/User;
       4: astore_1
       5: goto          25
       8: astore_2
       9: new           #25                 // class java/util/concurrent/CompletableFuture
      12: dup
      13: invokespecial #26                 // Method java/util/concurrent/CompletableFuture."<init>":()V
      16: astore_3
      17: aload_3
      18: aload_2
      19: invokevirtual #27                 // Method java/util/concurrent/CompletableFuture.completeExceptionally:(Ljava/lang/Throwable;)Z
      22: pop
      23: aload_3
      24: areturn
      25: aload_0
      26: aload_1
      27: invokestatic  #28                 // Method createAsyncConnection:(Lorg/apache/hadoop/conf/Configuration;Lorg/apache/hadoop/hbase/security/User;)Ljava/util/concurrent/CompletableFuture;
      30: areturn
    Exception table:
       from    to  target type
           0     5     8   Class java/io/IOException

  public static java.util.concurrent.CompletableFuture<org.apache.hadoop.hbase.client.AsyncConnection> createAsyncConnection(org.apache.hadoop.conf.Configuration, org.apache.hadoop.hbase.security.User);
    Code:
       0: new           #25                 // class java/util/concurrent/CompletableFuture
       3: dup
       4: invokespecial #26                 // Method java/util/concurrent/CompletableFuture."<init>":()V
       7: astore_2
       8: aload_0
       9: invokestatic  #29                 // Method org/apache/hadoop/hbase/client/AsyncRegistryFactory.getRegistry:(Lorg/apache/hadoop/conf/Configuration;)Lorg/apache/hadoop/hbase/client/AsyncRegistry;
      12: astore_3
      13: aload_3
      14: invokeinterface #30,  1           // InterfaceMethod org/apache/hadoop/hbase/client/AsyncRegistry.getClusterId:()Ljava/util/concurrent/CompletableFuture;
      19: aload_3
      20: aload_2
      21: aload_0
      22: aload_1
      23: invokedynamic #31,  0             // InvokeDynamic #1:accept:(Lorg/apache/hadoop/hbase/client/AsyncRegistry;Ljava/util/concurrent/CompletableFuture;Lorg/apache/hadoop/conf/Configuration;Lorg/apache/hadoop/hbase/security/User;)Ljava/util/function/BiConsumer;
      28: invokestatic  #32                 // Method org/apache/hadoop/hbase/util/FutureUtils.addListener:(Ljava/util/concurrent/CompletableFuture;Ljava/util/function/BiConsumer;)V
      31: aload_2
      32: areturn
}
