Compiled from "CoprocessorValidatorTest.java"
class org.apache.hadoop.hbase.tool.coprocessor.CoprocessorValidatorTest$MissingClassClassLoader extends java.lang.ClassLoader {
  public org.apache.hadoop.hbase.tool.coprocessor.CoprocessorValidatorTest$MissingClassClassLoader();
    Code:
       0: aload_0
       1: invokestatic  #1                  // Method org/apache/hadoop/hbase/tool/coprocessor/CoprocessorValidatorTest.access$000:()Ljava/lang/ClassLoader;
       4: invokespecial #2                  // Method java/lang/ClassLoader."<init>":(Ljava/lang/ClassLoader;)V
       7: return

  public java.lang.Class<?> loadClass(java.lang.String) throws java.lang.ClassNotFoundException;
    Code:
       0: aload_1
       1: ldc           #3                  // String MissingClass
       3: invokestatic  #4                  // Method org/apache/hadoop/hbase/tool/coprocessor/CoprocessorValidatorTest.access$100:(Ljava/lang/String;)Ljava/lang/String;
       6: invokevirtual #5                  // Method java/lang/String.equals:(Ljava/lang/Object;)Z
       9: ifeq          21
      12: new           #6                  // class java/lang/ClassNotFoundException
      15: dup
      16: aload_1
      17: invokespecial #7                  // Method java/lang/ClassNotFoundException."<init>":(Ljava/lang/String;)V
      20: athrow
      21: aload_0
      22: aload_1
      23: invokespecial #8                  // Method java/lang/ClassLoader.findClass:(Ljava/lang/String;)Ljava/lang/Class;
      26: areturn
}
