Compiled from "Coprocessor.java"
public final class org.apache.hadoop.hbase.Coprocessor$State extends java.lang.Enum<org.apache.hadoop.hbase.Coprocessor$State> {
  public static final org.apache.hadoop.hbase.Coprocessor$State UNINSTALLED;

  public static final org.apache.hadoop.hbase.Coprocessor$State INSTALLED;

  public static final org.apache.hadoop.hbase.Coprocessor$State STARTING;

  public static final org.apache.hadoop.hbase.Coprocessor$State ACTIVE;

  public static final org.apache.hadoop.hbase.Coprocessor$State STOPPING;

  public static final org.apache.hadoop.hbase.Coprocessor$State STOPPED;

  public static org.apache.hadoop.hbase.Coprocessor$State[] values();
    Code:
       0: getstatic     #1                  // Field $VALUES:[Lorg/apache/hadoop/hbase/Coprocessor$State;
       3: invokevirtual #2                  // Method "[Lorg/apache/hadoop/hbase/Coprocessor$State;".clone:()Ljava/lang/Object;
       6: checkcast     #3                  // class "[Lorg/apache/hadoop/hbase/Coprocessor$State;"
       9: areturn

  public static org.apache.hadoop.hbase.Coprocessor$State valueOf(java.lang.String);
    Code:
       0: ldc           #4                  // class org/apache/hadoop/hbase/Coprocessor$State
       2: aload_0
       3: invokestatic  #5                  // Method java/lang/Enum.valueOf:(Ljava/lang/Class;Ljava/lang/String;)Ljava/lang/Enum;
       6: checkcast     #4                  // class org/apache/hadoop/hbase/Coprocessor$State
       9: areturn

  static {};
    Code:
       0: new           #4                  // class org/apache/hadoop/hbase/Coprocessor$State
       3: dup
       4: ldc           #7                  // String UNINSTALLED
       6: iconst_0
       7: invokespecial #8                  // Method "<init>":(Ljava/lang/String;I)V
      10: putstatic     #9                  // Field UNINSTALLED:Lorg/apache/hadoop/hbase/Coprocessor$State;
      13: new           #4                  // class org/apache/hadoop/hbase/Coprocessor$State
      16: dup
      17: ldc           #10                 // String INSTALLED
      19: iconst_1
      20: invokespecial #8                  // Method "<init>":(Ljava/lang/String;I)V
      23: putstatic     #11                 // Field INSTALLED:Lorg/apache/hadoop/hbase/Coprocessor$State;
      26: new           #4                  // class org/apache/hadoop/hbase/Coprocessor$State
      29: dup
      30: ldc           #12                 // String STARTING
      32: iconst_2
      33: invokespecial #8                  // Method "<init>":(Ljava/lang/String;I)V
      36: putstatic     #13                 // Field STARTING:Lorg/apache/hadoop/hbase/Coprocessor$State;
      39: new           #4                  // class org/apache/hadoop/hbase/Coprocessor$State
      42: dup
      43: ldc           #14                 // String ACTIVE
      45: iconst_3
      46: invokespecial #8                  // Method "<init>":(Ljava/lang/String;I)V
      49: putstatic     #15                 // Field ACTIVE:Lorg/apache/hadoop/hbase/Coprocessor$State;
      52: new           #4                  // class org/apache/hadoop/hbase/Coprocessor$State
      55: dup
      56: ldc           #16                 // String STOPPING
      58: iconst_4
      59: invokespecial #8                  // Method "<init>":(Ljava/lang/String;I)V
      62: putstatic     #17                 // Field STOPPING:Lorg/apache/hadoop/hbase/Coprocessor$State;
      65: new           #4                  // class org/apache/hadoop/hbase/Coprocessor$State
      68: dup
      69: ldc           #18                 // String STOPPED
      71: iconst_5
      72: invokespecial #8                  // Method "<init>":(Ljava/lang/String;I)V
      75: putstatic     #19                 // Field STOPPED:Lorg/apache/hadoop/hbase/Coprocessor$State;
      78: bipush        6
      80: anewarray     #4                  // class org/apache/hadoop/hbase/Coprocessor$State
      83: dup
      84: iconst_0
      85: getstatic     #9                  // Field UNINSTALLED:Lorg/apache/hadoop/hbase/Coprocessor$State;
      88: aastore
      89: dup
      90: iconst_1
      91: getstatic     #11                 // Field INSTALLED:Lorg/apache/hadoop/hbase/Coprocessor$State;
      94: aastore
      95: dup
      96: iconst_2
      97: getstatic     #13                 // Field STARTING:Lorg/apache/hadoop/hbase/Coprocessor$State;
     100: aastore
     101: dup
     102: iconst_3
     103: getstatic     #15                 // Field ACTIVE:Lorg/apache/hadoop/hbase/Coprocessor$State;
     106: aastore
     107: dup
     108: iconst_4
     109: getstatic     #17                 // Field STOPPING:Lorg/apache/hadoop/hbase/Coprocessor$State;
     112: aastore
     113: dup
     114: iconst_5
     115: getstatic     #19                 // Field STOPPED:Lorg/apache/hadoop/hbase/Coprocessor$State;
     118: aastore
     119: putstatic     #1                  // Field $VALUES:[Lorg/apache/hadoop/hbase/Coprocessor$State;
     122: return
}
