Compiled from "CoprocessorHost.java"
public abstract class org.apache.hadoop.hbase.coprocessor.CoprocessorHost$ObserverOperationWithResult<O, R> extends org.apache.hadoop.hbase.coprocessor.CoprocessorHost<C, E>.ObserverOperation<O> {
  final org.apache.hadoop.hbase.coprocessor.CoprocessorHost this$0;

  protected abstract R call(O) throws java.io.IOException;

  public org.apache.hadoop.hbase.coprocessor.CoprocessorHost$ObserverOperationWithResult(org.apache.hadoop.hbase.coprocessor.CoprocessorHost$ObserverGetter<C, O>, R);
    Code:
       0: aload_0
       1: aload_1
       2: aload_2
       3: aload_3
       4: iconst_0
       5: invokespecial #1                  // Method "<init>":(Lorg/apache/hadoop/hbase/coprocessor/CoprocessorHost;Lorg/apache/hadoop/hbase/coprocessor/CoprocessorHost$ObserverGetter;Ljava/lang/Object;Z)V
       8: return

  public org.apache.hadoop.hbase.coprocessor.CoprocessorHost$ObserverOperationWithResult(org.apache.hadoop.hbase.coprocessor.CoprocessorHost$ObserverGetter<C, O>, R, boolean);
    Code:
       0: aload_0
       1: aload_1
       2: aload_2
       3: aload_3
       4: aconst_null
       5: iload         4
       7: invokespecial #2                  // Method "<init>":(Lorg/apache/hadoop/hbase/coprocessor/CoprocessorHost;Lorg/apache/hadoop/hbase/coprocessor/CoprocessorHost$ObserverGetter;Ljava/lang/Object;Lorg/apache/hadoop/hbase/security/User;Z)V
      10: return

  public org.apache.hadoop.hbase.coprocessor.CoprocessorHost$ObserverOperationWithResult(org.apache.hadoop.hbase.coprocessor.CoprocessorHost$ObserverGetter<C, O>, R, org.apache.hadoop.hbase.security.User);
    Code:
       0: aload_0
       1: aload_1
       2: aload_2
       3: aload_3
       4: aload         4
       6: iconst_0
       7: invokespecial #2                  // Method "<init>":(Lorg/apache/hadoop/hbase/coprocessor/CoprocessorHost;Lorg/apache/hadoop/hbase/coprocessor/CoprocessorHost$ObserverGetter;Ljava/lang/Object;Lorg/apache/hadoop/hbase/security/User;Z)V
      10: return

  protected R getResult();
    Code:
       0: aload_0
       1: getfield      #5                  // Field result:Ljava/lang/Object;
       4: areturn

  void callObserver() throws java.io.IOException;
    Code:
       0: aload_0
       1: getfield      #6                  // Field observerGetter:Lorg/apache/hadoop/hbase/coprocessor/CoprocessorHost$ObserverGetter;
       4: aload_0
       5: invokevirtual #7                  // Method getEnvironment:()Lorg/apache/hadoop/hbase/CoprocessorEnvironment;
       8: invokeinterface #8,  1            // InterfaceMethod org/apache/hadoop/hbase/CoprocessorEnvironment.getInstance:()Lorg/apache/hadoop/hbase/Coprocessor;
      13: invokeinterface #9,  2            // InterfaceMethod org/apache/hadoop/hbase/coprocessor/CoprocessorHost$ObserverGetter.apply:(Ljava/lang/Object;)Ljava/lang/Object;
      18: checkcast     #10                 // class java/util/Optional
      21: astore_1
      22: aload_1
      23: invokevirtual #11                 // Method java/util/Optional.isPresent:()Z
      26: ifeq          41
      29: aload_0
      30: aload_0
      31: aload_1
      32: invokevirtual #12                 // Method java/util/Optional.get:()Ljava/lang/Object;
      35: invokevirtual #13                 // Method call:(Ljava/lang/Object;)Ljava/lang/Object;
      38: putfield      #5                  // Field result:Ljava/lang/Object;
      41: return
}
