Compiled from "CoprocessorHost.java"
class org.apache.hadoop.hbase.coprocessor.CoprocessorHost$EnvironmentPriorityComparator implements java.util.Comparator<org.apache.hadoop.hbase.CoprocessorEnvironment> {
  org.apache.hadoop.hbase.coprocessor.CoprocessorHost$EnvironmentPriorityComparator();
    Code:
       0: aload_0
       1: invokespecial #1                  // Method java/lang/Object."<init>":()V
       4: return

  public int compare(org.apache.hadoop.hbase.CoprocessorEnvironment, org.apache.hadoop.hbase.CoprocessorEnvironment);
    Code:
       0: aload_1
       1: invokeinterface #2,  1            // InterfaceMethod org/apache/hadoop/hbase/CoprocessorEnvironment.getPriority:()I
       6: aload_2
       7: invokeinterface #2,  1            // InterfaceMethod org/apache/hadoop/hbase/CoprocessorEnvironment.getPriority:()I
      12: if_icmpge     17
      15: iconst_m1
      16: ireturn
      17: aload_1
      18: invokeinterface #2,  1            // InterfaceMethod org/apache/hadoop/hbase/CoprocessorEnvironment.getPriority:()I
      23: aload_2
      24: invokeinterface #2,  1            // InterfaceMethod org/apache/hadoop/hbase/CoprocessorEnvironment.getPriority:()I
      29: if_icmple     34
      32: iconst_1
      33: ireturn
      34: aload_1
      35: invokeinterface #3,  1            // InterfaceMethod org/apache/hadoop/hbase/CoprocessorEnvironment.getLoadSequence:()I
      40: aload_2
      41: invokeinterface #3,  1            // InterfaceMethod org/apache/hadoop/hbase/CoprocessorEnvironment.getLoadSequence:()I
      46: if_icmpge     51
      49: iconst_m1
      50: ireturn
      51: aload_1
      52: invokeinterface #3,  1            // InterfaceMethod org/apache/hadoop/hbase/CoprocessorEnvironment.getLoadSequence:()I
      57: aload_2
      58: invokeinterface #3,  1            // InterfaceMethod org/apache/hadoop/hbase/CoprocessorEnvironment.getLoadSequence:()I
      63: if_icmple     68
      66: iconst_1
      67: ireturn
      68: iconst_0
      69: ireturn

  public int compare(java.lang.Object, java.lang.Object);
    Code:
       0: aload_0
       1: aload_1
       2: checkcast     #4                  // class org/apache/hadoop/hbase/CoprocessorEnvironment
       5: aload_2
       6: checkcast     #4                  // class org/apache/hadoop/hbase/CoprocessorEnvironment
       9: invokevirtual #5                  // Method compare:(Lorg/apache/hadoop/hbase/CoprocessorEnvironment;Lorg/apache/hadoop/hbase/CoprocessorEnvironment;)I
      12: ireturn
}
