Compiled from "CoprocessorRpcUtils.java"
public final class org.apache.hadoop.hbase.ipc.CoprocessorRpcUtils {
  public static java.lang.String getServiceName(com.google.protobuf.Descriptors$ServiceDescriptor);
    Code:
       0: aload_0
       1: invokevirtual #2                  // Method com/google/protobuf/Descriptors$ServiceDescriptor.getFullName:()Ljava/lang/String;
       4: getstatic     #3                  // Field hbaseServicePackage:Ljava/lang/String;
       7: invokevirtual #4                  // Method java/lang/String.startsWith:(Ljava/lang/String;)Z
      10: ifeq          18
      13: aload_0
      14: invokevirtual #5                  // Method com/google/protobuf/Descriptors$ServiceDescriptor.getName:()Ljava/lang/String;
      17: areturn
      18: aload_0
      19: invokevirtual #2                  // Method com/google/protobuf/Descriptors$ServiceDescriptor.getFullName:()Ljava/lang/String;
      22: areturn

  public static org.apache.hadoop.hbase.shaded.protobuf.generated.ClientProtos$CoprocessorServiceRequest getCoprocessorServiceRequest(com.google.protobuf.Descriptors$MethodDescriptor, com.google.protobuf.Message);
    Code:
       0: aload_0
       1: aload_1
       2: getstatic     #6                  // Field org/apache/hadoop/hbase/HConstants.EMPTY_BYTE_ARRAY:[B
       5: getstatic     #6                  // Field org/apache/hadoop/hbase/HConstants.EMPTY_BYTE_ARRAY:[B
       8: invokestatic  #7                  // Method getCoprocessorServiceRequest:(Lcom/google/protobuf/Descriptors$MethodDescriptor;Lcom/google/protobuf/Message;[B[B)Lorg/apache/hadoop/hbase/shaded/protobuf/generated/ClientProtos$CoprocessorServiceRequest;
      11: areturn

  public static org.apache.hadoop.hbase.shaded.protobuf.generated.ClientProtos$CoprocessorServiceRequest getCoprocessorServiceRequest(com.google.protobuf.Descriptors$MethodDescriptor, com.google.protobuf.Message, byte[], byte[]);
    Code:
       0: invokestatic  #8                  // Method org/apache/hadoop/hbase/shaded/protobuf/generated/ClientProtos$CoprocessorServiceRequest.newBuilder:()Lorg/apache/hadoop/hbase/shaded/protobuf/generated/ClientProtos$CoprocessorServiceRequest$Builder;
       3: aload_0
       4: aload_1
       5: aload_2
       6: invokestatic  #9                  // Method getCoprocessorServiceCall:(Lcom/google/protobuf/Descriptors$MethodDescriptor;Lcom/google/protobuf/Message;[B)Lorg/apache/hadoop/hbase/shaded/protobuf/generated/ClientProtos$CoprocessorServiceCall;
       9: invokevirtual #10                 // Method org/apache/hadoop/hbase/shaded/protobuf/generated/ClientProtos$CoprocessorServiceRequest$Builder.setCall:(Lorg/apache/hadoop/hbase/shaded/protobuf/generated/ClientProtos$CoprocessorServiceCall;)Lorg/apache/hadoop/hbase/shaded/protobuf/generated/ClientProtos$CoprocessorServiceRequest$Builder;
      12: getstatic     #11                 // Field org/apache/hadoop/hbase/shaded/protobuf/generated/HBaseProtos$RegionSpecifier$RegionSpecifierType.REGION_NAME:Lorg/apache/hadoop/hbase/shaded/protobuf/generated/HBaseProtos$RegionSpecifier$RegionSpecifierType;
      15: aload_3
      16: invokestatic  #12                 // Method org/apache/hadoop/hbase/shaded/protobuf/RequestConverter.buildRegionSpecifier:(Lorg/apache/hadoop/hbase/shaded/protobuf/generated/HBaseProtos$RegionSpecifier$RegionSpecifierType;[B)Lorg/apache/hadoop/hbase/shaded/protobuf/generated/HBaseProtos$RegionSpecifier;
      19: invokevirtual #13                 // Method org/apache/hadoop/hbase/shaded/protobuf/generated/ClientProtos$CoprocessorServiceRequest$Builder.setRegion:(Lorg/apache/hadoop/hbase/shaded/protobuf/generated/HBaseProtos$RegionSpecifier;)Lorg/apache/hadoop/hbase/shaded/protobuf/generated/ClientProtos$CoprocessorServiceRequest$Builder;
      22: invokevirtual #14                 // Method org/apache/hadoop/hbase/shaded/protobuf/generated/ClientProtos$CoprocessorServiceRequest$Builder.build:()Lorg/apache/hadoop/hbase/shaded/protobuf/generated/ClientProtos$CoprocessorServiceRequest;
      25: areturn

  public static com.google.protobuf.Descriptors$MethodDescriptor getMethodDescriptor(java.lang.String, com.google.protobuf.Descriptors$ServiceDescriptor) throws org.apache.hadoop.hbase.exceptions.UnknownProtocolException;
    Code:
       0: aload_1
       1: aload_0
       2: invokevirtual #26                 // Method com/google/protobuf/Descriptors$ServiceDescriptor.findMethodByName:(Ljava/lang/String;)Lcom/google/protobuf/Descriptors$MethodDescriptor;
       5: astore_2
       6: aload_2
       7: ifnonnull     49
      10: new           #27                 // class org/apache/hadoop/hbase/exceptions/UnknownProtocolException
      13: dup
      14: new           #28                 // class java/lang/StringBuilder
      17: dup
      18: invokespecial #29                 // Method java/lang/StringBuilder."<init>":()V
      21: ldc           #30                 // String Unknown method
      23: invokevirtual #31                 // Method java/lang/StringBuilder.append:(Ljava/lang/String;)Ljava/lang/StringBuilder;
      26: aload_0
      27: invokevirtual #31                 // Method java/lang/StringBuilder.append:(Ljava/lang/String;)Ljava/lang/StringBuilder;
      30: ldc           #32                 // String  called on service
      32: invokevirtual #31                 // Method java/lang/StringBuilder.append:(Ljava/lang/String;)Ljava/lang/StringBuilder;
      35: aload_1
      36: invokevirtual #2                  // Method com/google/protobuf/Descriptors$ServiceDescriptor.getFullName:()Ljava/lang/String;
      39: invokevirtual #31                 // Method java/lang/StringBuilder.append:(Ljava/lang/String;)Ljava/lang/StringBuilder;
      42: invokevirtual #33                 // Method java/lang/StringBuilder.toString:()Ljava/lang/String;
      45: invokespecial #34                 // Method org/apache/hadoop/hbase/exceptions/UnknownProtocolException."<init>":(Ljava/lang/String;)V
      48: athrow
      49: aload_2
      50: areturn

  public static com.google.protobuf.Message getRequest(com.google.protobuf.Service, com.google.protobuf.Descriptors$MethodDescriptor, org.apache.hbase.thirdparty.com.google.protobuf.ByteString) throws java.io.IOException;
    Code:
       0: aload_0
       1: aload_1
       2: invokeinterface #35,  2           // InterfaceMethod com/google/protobuf/Service.getRequestPrototype:(Lcom/google/protobuf/Descriptors$MethodDescriptor;)Lcom/google/protobuf/Message;
       7: invokeinterface #36,  1           // InterfaceMethod com/google/protobuf/Message.newBuilderForType:()Lcom/google/protobuf/Message$Builder;
      12: astore_3
      13: aload_3
      14: aload_2
      15: invokevirtual #37                 // Method org/apache/hbase/thirdparty/com/google/protobuf/ByteString.toByteArray:()[B
      18: invokestatic  #38                 // Method org/apache/hadoop/hbase/protobuf/ProtobufUtil.mergeFrom:(Lcom/google/protobuf/Message$Builder;[B)V
      21: aload_3
      22: invokeinterface #39,  1           // InterfaceMethod com/google/protobuf/Message$Builder.build:()Lcom/google/protobuf/Message;
      27: areturn

  public static com.google.protobuf.Message getResponse(org.apache.hadoop.hbase.shaded.protobuf.generated.ClientProtos$CoprocessorServiceResponse, com.google.protobuf.Message) throws java.io.IOException;
    Code:
       0: aload_0
       1: invokevirtual #40                 // Method org/apache/hadoop/hbase/shaded/protobuf/generated/ClientProtos$CoprocessorServiceResponse.getValue:()Lorg/apache/hadoop/hbase/shaded/protobuf/generated/HBaseProtos$NameBytesPair;
       4: invokevirtual #41                 // Method org/apache/hadoop/hbase/shaded/protobuf/generated/HBaseProtos$NameBytesPair.hasValue:()Z
       7: ifeq          44
      10: aload_1
      11: invokeinterface #36,  1           // InterfaceMethod com/google/protobuf/Message.newBuilderForType:()Lcom/google/protobuf/Message$Builder;
      16: astore_3
      17: aload_3
      18: aload_0
      19: invokevirtual #40                 // Method org/apache/hadoop/hbase/shaded/protobuf/generated/ClientProtos$CoprocessorServiceResponse.getValue:()Lorg/apache/hadoop/hbase/shaded/protobuf/generated/HBaseProtos$NameBytesPair;
      22: invokevirtual #42                 // Method org/apache/hadoop/hbase/shaded/protobuf/generated/HBaseProtos$NameBytesPair.getValue:()Lorg/apache/hbase/thirdparty/com/google/protobuf/ByteString;
      25: invokevirtual #43                 // Method org/apache/hbase/thirdparty/com/google/protobuf/ByteString.newInput:()Ljava/io/InputStream;
      28: invokeinterface #44,  2           // InterfaceMethod com/google/protobuf/Message$Builder.mergeFrom:(Ljava/io/InputStream;)Lcom/google/protobuf/Message$Builder;
      33: pop
      34: aload_3
      35: invokeinterface #39,  1           // InterfaceMethod com/google/protobuf/Message$Builder.build:()Lcom/google/protobuf/Message;
      40: astore_2
      41: goto          51
      44: aload_1
      45: invokeinterface #45,  1           // InterfaceMethod com/google/protobuf/Message.getDefaultInstanceForType:()Lcom/google/protobuf/Message;
      50: astore_2
      51: getstatic     #46                 // Field LOG:Lorg/slf4j/Logger;
      54: invokeinterface #47,  1           // InterfaceMethod org/slf4j/Logger.isTraceEnabled:()Z
      59: ifeq          89
      62: getstatic     #46                 // Field LOG:Lorg/slf4j/Logger;
      65: new           #28                 // class java/lang/StringBuilder
      68: dup
      69: invokespecial #29                 // Method java/lang/StringBuilder."<init>":()V
      72: ldc           #48                 // String Master Result is value=
      74: invokevirtual #31                 // Method java/lang/StringBuilder.append:(Ljava/lang/String;)Ljava/lang/StringBuilder;
      77: aload_2
      78: invokevirtual #49                 // Method java/lang/StringBuilder.append:(Ljava/lang/Object;)Ljava/lang/StringBuilder;
      81: invokevirtual #33                 // Method java/lang/StringBuilder.toString:()Ljava/lang/String;
      84: invokeinterface #50,  2           // InterfaceMethod org/slf4j/Logger.trace:(Ljava/lang/String;)V
      89: aload_2
      90: areturn

  public static org.apache.hadoop.hbase.shaded.protobuf.generated.ClientProtos$CoprocessorServiceResponse getResponse(com.google.protobuf.Message, byte[]);
    Code:
       0: invokestatic  #51                 // Method org/apache/hadoop/hbase/shaded/protobuf/generated/ClientProtos$CoprocessorServiceResponse.newBuilder:()Lorg/apache/hadoop/hbase/shaded/protobuf/generated/ClientProtos$CoprocessorServiceResponse$Builder;
       3: astore_2
       4: aload_2
       5: getstatic     #11                 // Field org/apache/hadoop/hbase/shaded/protobuf/generated/HBaseProtos$RegionSpecifier$RegionSpecifierType.REGION_NAME:Lorg/apache/hadoop/hbase/shaded/protobuf/generated/HBaseProtos$RegionSpecifier$RegionSpecifierType;
       8: aload_1
       9: invokestatic  #12                 // Method org/apache/hadoop/hbase/shaded/protobuf/RequestConverter.buildRegionSpecifier:(Lorg/apache/hadoop/hbase/shaded/protobuf/generated/HBaseProtos$RegionSpecifier$RegionSpecifierType;[B)Lorg/apache/hadoop/hbase/shaded/protobuf/generated/HBaseProtos$RegionSpecifier;
      12: invokevirtual #52                 // Method org/apache/hadoop/hbase/shaded/protobuf/generated/ClientProtos$CoprocessorServiceResponse$Builder.setRegion:(Lorg/apache/hadoop/hbase/shaded/protobuf/generated/HBaseProtos$RegionSpecifier;)Lorg/apache/hadoop/hbase/shaded/protobuf/generated/ClientProtos$CoprocessorServiceResponse$Builder;
      15: pop
      16: aload_2
      17: aload_2
      18: invokevirtual #53                 // Method org/apache/hadoop/hbase/shaded/protobuf/generated/ClientProtos$CoprocessorServiceResponse$Builder.getValueBuilder:()Lorg/apache/hadoop/hbase/shaded/protobuf/generated/HBaseProtos$NameBytesPair$Builder;
      21: aload_0
      22: invokevirtual #54                 // Method java/lang/Object.getClass:()Ljava/lang/Class;
      25: invokevirtual #55                 // Method java/lang/Class.getName:()Ljava/lang/String;
      28: invokevirtual #56                 // Method org/apache/hadoop/hbase/shaded/protobuf/generated/HBaseProtos$NameBytesPair$Builder.setName:(Ljava/lang/String;)Lorg/apache/hadoop/hbase/shaded/protobuf/generated/HBaseProtos$NameBytesPair$Builder;
      31: aload_0
      32: invokeinterface #23,  1           // InterfaceMethod com/google/protobuf/Message.toByteArray:()[B
      37: invokestatic  #57                 // Method org/apache/hbase/thirdparty/com/google/protobuf/ByteString.copyFrom:([B)Lorg/apache/hbase/thirdparty/com/google/protobuf/ByteString;
      40: invokevirtual #58                 // Method org/apache/hadoop/hbase/shaded/protobuf/generated/HBaseProtos$NameBytesPair$Builder.setValue:(Lorg/apache/hbase/thirdparty/com/google/protobuf/ByteString;)Lorg/apache/hadoop/hbase/shaded/protobuf/generated/HBaseProtos$NameBytesPair$Builder;
      43: invokevirtual #59                 // Method org/apache/hadoop/hbase/shaded/protobuf/generated/ClientProtos$CoprocessorServiceResponse$Builder.setValue:(Lorg/apache/hadoop/hbase/shaded/protobuf/generated/HBaseProtos$NameBytesPair$Builder;)Lorg/apache/hadoop/hbase/shaded/protobuf/generated/ClientProtos$CoprocessorServiceResponse$Builder;
      46: pop
      47: aload_2
      48: invokevirtual #60                 // Method org/apache/hadoop/hbase/shaded/protobuf/generated/ClientProtos$CoprocessorServiceResponse$Builder.build:()Lorg/apache/hadoop/hbase/shaded/protobuf/generated/ClientProtos$CoprocessorServiceResponse;
      51: areturn

  public static void setControllerException(com.google.protobuf.RpcController, java.io.IOException);
    Code:
       0: aload_0
       1: ifnonnull     5
       4: return
       5: aload_0
       6: instanceof    #61                 // class org/apache/hadoop/hbase/ipc/ServerRpcController
       9: ifeq          23
      12: aload_0
      13: checkcast     #61                 // class org/apache/hadoop/hbase/ipc/ServerRpcController
      16: aload_1
      17: invokevirtual #62                 // Method org/apache/hadoop/hbase/ipc/ServerRpcController.setFailedOn:(Ljava/io/IOException;)V
      20: goto          33
      23: aload_0
      24: aload_1
      25: invokestatic  #63                 // Method org/apache/hadoop/util/StringUtils.stringifyException:(Ljava/lang/Throwable;)Ljava/lang/String;
      28: invokeinterface #64,  2           // InterfaceMethod com/google/protobuf/RpcController.setFailed:(Ljava/lang/String;)V
      33: return

  public static java.io.IOException getControllerException(com.google.protobuf.RpcController) throws java.io.IOException;
    Code:
       0: aload_0
       1: ifnull        13
       4: aload_0
       5: invokeinterface #65,  1           // InterfaceMethod com/google/protobuf/RpcController.failed:()Z
      10: ifne          15
      13: aconst_null
      14: areturn
      15: aload_0
      16: instanceof    #61                 // class org/apache/hadoop/hbase/ipc/ServerRpcController
      19: ifeq          30
      22: aload_0
      23: checkcast     #61                 // class org/apache/hadoop/hbase/ipc/ServerRpcController
      26: invokevirtual #66                 // Method org/apache/hadoop/hbase/ipc/ServerRpcController.getFailedOn:()Ljava/io/IOException;
      29: areturn
      30: new           #67                 // class org/apache/hadoop/hbase/DoNotRetryIOException
      33: dup
      34: aload_0
      35: invokeinterface #68,  1           // InterfaceMethod com/google/protobuf/RpcController.errorText:()Ljava/lang/String;
      40: invokespecial #69                 // Method org/apache/hadoop/hbase/DoNotRetryIOException."<init>":(Ljava/lang/String;)V
      43: areturn

  static {};
    Code:
       0: ldc           #70                 // class org/apache/hadoop/hbase/ipc/CoprocessorRpcUtils
       2: invokestatic  #71                 // Method org/slf4j/LoggerFactory.getLogger:(Ljava/lang/Class;)Lorg/slf4j/Logger;
       5: putstatic     #46                 // Field LOG:Lorg/slf4j/Logger;
       8: invokestatic  #72                 // Method org/apache/hadoop/hbase/protobuf/generated/ClientProtos$ClientService.getDescriptor:()Lcom/google/protobuf/Descriptors$ServiceDescriptor;
      11: astore_0
      12: aload_0
      13: invokevirtual #2                  // Method com/google/protobuf/Descriptors$ServiceDescriptor.getFullName:()Ljava/lang/String;
      16: iconst_0
      17: aload_0
      18: invokevirtual #2                  // Method com/google/protobuf/Descriptors$ServiceDescriptor.getFullName:()Ljava/lang/String;
      21: aload_0
      22: invokevirtual #5                  // Method com/google/protobuf/Descriptors$ServiceDescriptor.getName:()Ljava/lang/String;
      25: invokevirtual #73                 // Method java/lang/String.lastIndexOf:(Ljava/lang/String;)I
      28: invokevirtual #74                 // Method java/lang/String.substring:(II)Ljava/lang/String;
      31: putstatic     #3                  // Field hbaseServicePackage:Ljava/lang/String;
      34: return
}
