Compiled from "CorruptedSnapshotException.java"
public class org.apache.hadoop.hbase.snapshot.CorruptedSnapshotException extends org.apache.hadoop.hbase.snapshot.HBaseSnapshotException {
  public org.apache.hadoop.hbase.snapshot.CorruptedSnapshotException(java.lang.String, java.lang.Exception);
    Code:
       0: aload_0
       1: aload_1
       2: aload_2
       3: invokespecial #1                  // Method org/apache/hadoop/hbase/snapshot/HBaseSnapshotException."<init>":(Ljava/lang/String;Ljava/lang/Throwable;)V
       6: return

  public org.apache.hadoop.hbase.snapshot.CorruptedSnapshotException(java.lang.String, org.apache.hadoop.hbase.client.SnapshotDescription);
    Code:
       0: aload_0
       1: aload_1
       2: aload_2
       3: invokespecial #2                  // Method org/apache/hadoop/hbase/snapshot/HBaseSnapshotException."<init>":(Ljava/lang/String;Lorg/apache/hadoop/hbase/client/SnapshotDescription;)V
       6: return

  public org.apache.hadoop.hbase.snapshot.CorruptedSnapshotException(java.lang.String);
    Code:
       0: aload_0
       1: aload_1
       2: aconst_null
       3: checkcast     #3                  // class org/apache/hadoop/hbase/client/SnapshotDescription
       6: invokespecial #2                  // Method org/apache/hadoop/hbase/snapshot/HBaseSnapshotException."<init>":(Ljava/lang/String;Lorg/apache/hadoop/hbase/client/SnapshotDescription;)V
       9: return
}
