Compiled from "CSLMImmutableSegment.java"
public class org.apache.hadoop.hbase.regionserver.CSLMImmutableSegment extends org.apache.hadoop.hbase.regionserver.ImmutableSegment {
  public static final long DEEP_OVERHEAD_CSLM;

  protected org.apache.hadoop.hbase.regionserver.CSLMImmutableSegment(org.apache.hadoop.hbase.regionserver.Segment, org.apache.hadoop.hbase.regionserver.MemStoreSizing);
    Code:
       0: aload_0
       1: aload_1
       2: invokespecial #1                  // Method org/apache/hadoop/hbase/regionserver/ImmutableSegment."<init>":(Lorg/apache/hadoop/hbase/regionserver/Segment;)V
       5: getstatic     #2                  // Field org/apache/hadoop/hbase/regionserver/MutableSegment.DEEP_OVERHEAD:J
       8: lneg
       9: getstatic     #3                  // Field DEEP_OVERHEAD_CSLM:J
      12: ladd
      13: lstore_3
      14: aload_0
      15: lconst_0
      16: lload_3
      17: lconst_0
      18: iconst_0
      19: invokevirtual #4                  // Method incMemStoreSize:(JJJI)J
      22: pop2
      23: aload_2
      24: ifnull        38
      27: aload_2
      28: lconst_0
      29: lload_3
      30: lconst_0
      31: iconst_0
      32: invokeinterface #5,  8            // InterfaceMethod org/apache/hadoop/hbase/regionserver/MemStoreSizing.incMemStoreSize:(JJJI)J
      37: pop2
      38: return

  protected long indexEntrySize();
    Code:
       0: getstatic     #6                  // Field org/apache/hadoop/hbase/util/ClassSize.CONCURRENT_SKIPLISTMAP_ENTRY:I
       3: i2l
       4: lreturn

  protected boolean canBeFlattened();
    Code:
       0: iconst_1
       1: ireturn

  static {};
    Code:
       0: getstatic     #7                  // Field org/apache/hadoop/hbase/regionserver/ImmutableSegment.DEEP_OVERHEAD:J
       3: getstatic     #8                  // Field org/apache/hadoop/hbase/util/ClassSize.CONCURRENT_SKIPLISTMAP:I
       6: i2l
       7: ladd
       8: putstatic     #3                  // Field DEEP_OVERHEAD_CSLM:J
      11: return
}
