Compiled from "CurrentHourProvider.java"
final class org.apache.hadoop.hbase.regionserver.compactions.CurrentHourProvider$Tick {
  final int currentHour;

  final long expirationTimeInMillis;

  org.apache.hadoop.hbase.regionserver.compactions.CurrentHourProvider$Tick(int, long);
    Code:
       0: aload_0
       1: invokespecial #1                  // Method java/lang/Object."<init>":()V
       4: aload_0
       5: iload_1
       6: putfield      #2                  // Field currentHour:I
       9: aload_0
      10: lload_2
      11: putfield      #3                  // Field expirationTimeInMillis:J
      14: return
}
