Compiled from "DateTieredStoreEngine.java"
final class org.apache.hadoop.hbase.regionserver.DateTieredStoreEngine$DateTieredCompactionContext extends org.apache.hadoop.hbase.regionserver.compactions.CompactionContext {
  final org.apache.hadoop.hbase.regionserver.DateTieredStoreEngine this$0;

  public java.util.List<org.apache.hadoop.hbase.regionserver.HStoreFile> preSelect(java.util.List<org.apache.hadoop.hbase.regionserver.HStoreFile>);
    Code:
       0: aload_0
       1: getfield      #2                  // Field this$0:Lorg/apache/hadoop/hbase/regionserver/DateTieredStoreEngine;
       4: getfield      #4                  // Field org/apache/hadoop/hbase/regionserver/DateTieredStoreEngine.compactionPolicy:Lorg/apache/hadoop/hbase/regionserver/compactions/CompactionPolicy;
       7: checkcast     #5                  // class org/apache/hadoop/hbase/regionserver/compactions/DateTieredCompactionPolicy
      10: aload_0
      11: getfield      #2                  // Field this$0:Lorg/apache/hadoop/hbase/regionserver/DateTieredStoreEngine;
      14: getfield      #6                  // Field org/apache/hadoop/hbase/regionserver/DateTieredStoreEngine.storeFileManager:Lorg/apache/hadoop/hbase/regionserver/StoreFileManager;
      17: checkcast     #7                  // class org/apache/hadoop/hbase/regionserver/DefaultStoreFileManager
      20: invokevirtual #8                  // Method org/apache/hadoop/hbase/regionserver/DefaultStoreFileManager.getStorefiles:()Ljava/util/Collection;
      23: aload_1
      24: invokevirtual #9                  // Method org/apache/hadoop/hbase/regionserver/compactions/DateTieredCompactionPolicy.preSelectCompactionForCoprocessor:(Ljava/util/Collection;Ljava/util/List;)Ljava/util/List;
      27: areturn

  public boolean select(java.util.List<org.apache.hadoop.hbase.regionserver.HStoreFile>, boolean, boolean, boolean) throws java.io.IOException;
    Code:
       0: aload_0
       1: aload_0
       2: getfield      #2                  // Field this$0:Lorg/apache/hadoop/hbase/regionserver/DateTieredStoreEngine;
       5: getfield      #4                  // Field org/apache/hadoop/hbase/regionserver/DateTieredStoreEngine.compactionPolicy:Lorg/apache/hadoop/hbase/regionserver/compactions/CompactionPolicy;
       8: checkcast     #5                  // class org/apache/hadoop/hbase/regionserver/compactions/DateTieredCompactionPolicy
      11: aload_0
      12: getfield      #2                  // Field this$0:Lorg/apache/hadoop/hbase/regionserver/DateTieredStoreEngine;
      15: getfield      #6                  // Field org/apache/hadoop/hbase/regionserver/DateTieredStoreEngine.storeFileManager:Lorg/apache/hadoop/hbase/regionserver/StoreFileManager;
      18: checkcast     #7                  // class org/apache/hadoop/hbase/regionserver/DefaultStoreFileManager
      21: invokevirtual #8                  // Method org/apache/hadoop/hbase/regionserver/DefaultStoreFileManager.getStorefiles:()Ljava/util/Collection;
      24: aload_1
      25: iload_2
      26: iload_3
      27: iload         4
      29: invokevirtual #10                 // Method org/apache/hadoop/hbase/regionserver/compactions/DateTieredCompactionPolicy.selectCompaction:(Ljava/util/Collection;Ljava/util/List;ZZZ)Lorg/apache/hadoop/hbase/regionserver/compactions/CompactionRequestImpl;
      32: putfield      #11                 // Field request:Lorg/apache/hadoop/hbase/regionserver/compactions/CompactionRequestImpl;
      35: aload_0
      36: getfield      #11                 // Field request:Lorg/apache/hadoop/hbase/regionserver/compactions/CompactionRequestImpl;
      39: ifnull        46
      42: iconst_1
      43: goto          47
      46: iconst_0
      47: ireturn

  public void forceSelect(org.apache.hadoop.hbase.regionserver.compactions.CompactionRequestImpl);
    Code:
       0: aload_1
       1: instanceof    #12                 // class org/apache/hadoop/hbase/regionserver/compactions/DateTieredCompactionRequest
       4: ifne          40
       7: new           #13                 // class java/lang/IllegalArgumentException
      10: dup
      11: new           #14                 // class java/lang/StringBuilder
      14: dup
      15: invokespecial #15                 // Method java/lang/StringBuilder."<init>":()V
      18: ldc           #16                 // String DateTieredCompactionRequest is expected. Actual:
      20: invokevirtual #17                 // Method java/lang/StringBuilder.append:(Ljava/lang/String;)Ljava/lang/StringBuilder;
      23: aload_1
      24: invokevirtual #18                 // Method java/lang/Object.getClass:()Ljava/lang/Class;
      27: invokevirtual #19                 // Method java/lang/Class.getCanonicalName:()Ljava/lang/String;
      30: invokevirtual #17                 // Method java/lang/StringBuilder.append:(Ljava/lang/String;)Ljava/lang/StringBuilder;
      33: invokevirtual #20                 // Method java/lang/StringBuilder.toString:()Ljava/lang/String;
      36: invokespecial #21                 // Method java/lang/IllegalArgumentException."<init>":(Ljava/lang/String;)V
      39: athrow
      40: aload_0
      41: aload_1
      42: invokespecial #22                 // Method org/apache/hadoop/hbase/regionserver/compactions/CompactionContext.forceSelect:(Lorg/apache/hadoop/hbase/regionserver/compactions/CompactionRequestImpl;)V
      45: return

  public java.util.List<org.apache.hadoop.fs.Path> compact(org.apache.hadoop.hbase.regionserver.throttle.ThroughputController, org.apache.hadoop.hbase.security.User) throws java.io.IOException;
    Code:
       0: aload_0
       1: getfield      #11                 // Field request:Lorg/apache/hadoop/hbase/regionserver/compactions/CompactionRequestImpl;
       4: instanceof    #12                 // class org/apache/hadoop/hbase/regionserver/compactions/DateTieredCompactionRequest
       7: ifeq          40
      10: aload_0
      11: getfield      #2                  // Field this$0:Lorg/apache/hadoop/hbase/regionserver/DateTieredStoreEngine;
      14: getfield      #23                 // Field org/apache/hadoop/hbase/regionserver/DateTieredStoreEngine.compactor:Lorg/apache/hadoop/hbase/regionserver/compactions/Compactor;
      17: checkcast     #24                 // class org/apache/hadoop/hbase/regionserver/compactions/DateTieredCompactor
      20: aload_0
      21: getfield      #11                 // Field request:Lorg/apache/hadoop/hbase/regionserver/compactions/CompactionRequestImpl;
      24: aload_0
      25: getfield      #11                 // Field request:Lorg/apache/hadoop/hbase/regionserver/compactions/CompactionRequestImpl;
      28: checkcast     #12                 // class org/apache/hadoop/hbase/regionserver/compactions/DateTieredCompactionRequest
      31: invokevirtual #25                 // Method org/apache/hadoop/hbase/regionserver/compactions/DateTieredCompactionRequest.getBoundaries:()Ljava/util/List;
      34: aload_1
      35: aload_2
      36: invokevirtual #26                 // Method org/apache/hadoop/hbase/regionserver/compactions/DateTieredCompactor.compact:(Lorg/apache/hadoop/hbase/regionserver/compactions/CompactionRequestImpl;Ljava/util/List;Lorg/apache/hadoop/hbase/regionserver/throttle/ThroughputController;Lorg/apache/hadoop/hbase/security/User;)Ljava/util/List;
      39: areturn
      40: new           #13                 // class java/lang/IllegalArgumentException
      43: dup
      44: new           #14                 // class java/lang/StringBuilder
      47: dup
      48: invokespecial #15                 // Method java/lang/StringBuilder."<init>":()V
      51: ldc           #16                 // String DateTieredCompactionRequest is expected. Actual:
      53: invokevirtual #17                 // Method java/lang/StringBuilder.append:(Ljava/lang/String;)Ljava/lang/StringBuilder;
      56: aload_0
      57: getfield      #11                 // Field request:Lorg/apache/hadoop/hbase/regionserver/compactions/CompactionRequestImpl;
      60: invokevirtual #18                 // Method java/lang/Object.getClass:()Ljava/lang/Class;
      63: invokevirtual #19                 // Method java/lang/Class.getCanonicalName:()Ljava/lang/String;
      66: invokevirtual #17                 // Method java/lang/StringBuilder.append:(Ljava/lang/String;)Ljava/lang/StringBuilder;
      69: invokevirtual #20                 // Method java/lang/StringBuilder.toString:()Ljava/lang/String;
      72: invokespecial #21                 // Method java/lang/IllegalArgumentException."<init>":(Ljava/lang/String;)V
      75: athrow

  org.apache.hadoop.hbase.regionserver.DateTieredStoreEngine$DateTieredCompactionContext(org.apache.hadoop.hbase.regionserver.DateTieredStoreEngine, org.apache.hadoop.hbase.regionserver.DateTieredStoreEngine$1);
    Code:
       0: aload_0
       1: aload_1
       2: invokespecial #1                  // Method "<init>":(Lorg/apache/hadoop/hbase/regionserver/DateTieredStoreEngine;)V
       5: return
}
