Compiled from "DateTieredCompactor.java"
class org.apache.hadoop.hbase.regionserver.compactions.DateTieredCompactor$1 implements org.apache.hadoop.hbase.regionserver.compactions.Compactor$CellSinkFactory<org.apache.hadoop.hbase.regionserver.DateTieredMultiFileWriter> {
  final java.util.List val$lowerBoundaries;

  final org.apache.hadoop.hbase.regionserver.compactions.CompactionRequestImpl val$request;

  final org.apache.hadoop.hbase.regionserver.compactions.DateTieredCompactor this$0;

  org.apache.hadoop.hbase.regionserver.compactions.DateTieredCompactor$1(org.apache.hadoop.hbase.regionserver.compactions.DateTieredCompactor, java.util.List, org.apache.hadoop.hbase.regionserver.compactions.CompactionRequestImpl);
    Code:
       0: aload_0
       1: aload_1
       2: putfield      #1                  // Field this$0:Lorg/apache/hadoop/hbase/regionserver/compactions/DateTieredCompactor;
       5: aload_0
       6: aload_2
       7: putfield      #2                  // Field val$lowerBoundaries:Ljava/util/List;
      10: aload_0
      11: aload_3
      12: putfield      #3                  // Field val$request:Lorg/apache/hadoop/hbase/regionserver/compactions/CompactionRequestImpl;
      15: aload_0
      16: invokespecial #4                  // Method java/lang/Object."<init>":()V
      19: return

  public org.apache.hadoop.hbase.regionserver.DateTieredMultiFileWriter createWriter(org.apache.hadoop.hbase.regionserver.InternalScanner, org.apache.hadoop.hbase.regionserver.compactions.Compactor$FileDetails, boolean) throws java.io.IOException;
    Code:
       0: new           #5                  // class org/apache/hadoop/hbase/regionserver/DateTieredMultiFileWriter
       3: dup
       4: aload_0
       5: getfield      #2                  // Field val$lowerBoundaries:Ljava/util/List;
       8: aload_0
       9: getfield      #1                  // Field this$0:Lorg/apache/hadoop/hbase/regionserver/compactions/DateTieredCompactor;
      12: aload_0
      13: getfield      #3                  // Field val$request:Lorg/apache/hadoop/hbase/regionserver/compactions/CompactionRequestImpl;
      16: invokestatic  #6                  // Method org/apache/hadoop/hbase/regionserver/compactions/DateTieredCompactor.access$000:(Lorg/apache/hadoop/hbase/regionserver/compactions/DateTieredCompactor;Lorg/apache/hadoop/hbase/regionserver/compactions/CompactionRequestImpl;)Z
      19: invokespecial #7                  // Method org/apache/hadoop/hbase/regionserver/DateTieredMultiFileWriter."<init>":(Ljava/util/List;Z)V
      22: astore        4
      24: aload_0
      25: getfield      #1                  // Field this$0:Lorg/apache/hadoop/hbase/regionserver/compactions/DateTieredCompactor;
      28: aload         4
      30: aload_1
      31: aload_2
      32: iload_3
      33: invokevirtual #8                  // Method org/apache/hadoop/hbase/regionserver/compactions/DateTieredCompactor.initMultiWriter:(Lorg/apache/hadoop/hbase/regionserver/AbstractMultiFileWriter;Lorg/apache/hadoop/hbase/regionserver/InternalScanner;Lorg/apache/hadoop/hbase/regionserver/compactions/Compactor$FileDetails;Z)V
      36: aload         4
      38: areturn

  public java.lang.Object createWriter(org.apache.hadoop.hbase.regionserver.InternalScanner, org.apache.hadoop.hbase.regionserver.compactions.Compactor$FileDetails, boolean) throws java.io.IOException;
    Code:
       0: aload_0
       1: aload_1
       2: aload_2
       3: iload_3
       4: invokevirtual #9                  // Method createWriter:(Lorg/apache/hadoop/hbase/regionserver/InternalScanner;Lorg/apache/hadoop/hbase/regionserver/compactions/Compactor$FileDetails;Z)Lorg/apache/hadoop/hbase/regionserver/DateTieredMultiFileWriter;
       7: areturn
}
