Compiled from "DateTieredCompactionRequest.java"
public class org.apache.hadoop.hbase.regionserver.compactions.DateTieredCompactionRequest extends org.apache.hadoop.hbase.regionserver.compactions.CompactionRequestImpl {
  public org.apache.hadoop.hbase.regionserver.compactions.DateTieredCompactionRequest(java.util.Collection<org.apache.hadoop.hbase.regionserver.HStoreFile>, java.util.List<java.lang.Long>);
    Code:
       0: aload_0
       1: aload_1
       2: invokespecial #1                  // Method org/apache/hadoop/hbase/regionserver/compactions/CompactionRequestImpl."<init>":(Ljava/util/Collection;)V
       5: aload_0
       6: aload_2
       7: putfield      #2                  // Field boundaries:Ljava/util/List;
      10: return

  public java.util.List<java.lang.Long> getBoundaries();
    Code:
       0: aload_0
       1: getfield      #2                  // Field boundaries:Ljava/util/List;
       4: areturn

  public java.lang.String toString();
    Code:
       0: new           #3                  // class java/lang/StringBuilder
       3: dup
       4: invokespecial #4                  // Method java/lang/StringBuilder."<init>":()V
       7: aload_0
       8: invokespecial #5                  // Method org/apache/hadoop/hbase/regionserver/compactions/CompactionRequestImpl.toString:()Ljava/lang/String;
      11: invokevirtual #6                  // Method java/lang/StringBuilder.append:(Ljava/lang/String;)Ljava/lang/StringBuilder;
      14: ldc           #7                  // String  boundaries=
      16: invokevirtual #6                  // Method java/lang/StringBuilder.append:(Ljava/lang/String;)Ljava/lang/StringBuilder;
      19: aload_0
      20: getfield      #2                  // Field boundaries:Ljava/util/List;
      23: invokeinterface #8,  1            // InterfaceMethod java/util/List.toArray:()[Ljava/lang/Object;
      28: invokestatic  #9                  // Method java/util/Arrays.toString:([Ljava/lang/Object;)Ljava/lang/String;
      31: invokevirtual #6                  // Method java/lang/StringBuilder.append:(Ljava/lang/String;)Ljava/lang/StringBuilder;
      34: invokevirtual #10                 // Method java/lang/StringBuilder.toString:()Ljava/lang/String;
      37: areturn
}
