Compiled from "DefaultNettyEventLoopConfig.java"
class org.apache.hadoop.hbase.ipc.DefaultNettyEventLoopConfig {
  public static final org.apache.hadoop.hbase.util.Pair<org.apache.hbase.thirdparty.io.netty.channel.EventLoopGroup, java.lang.Class<? extends org.apache.hbase.thirdparty.io.netty.channel.Channel>> GROUP_AND_CHANNEL_CLASS;

  org.apache.hadoop.hbase.ipc.DefaultNettyEventLoopConfig();
    Code:
       0: aload_0
       1: invokespecial #1                  // Method java/lang/Object."<init>":()V
       4: return

  static {};
    Code:
       0: new           #2                  // class org/apache/hbase/thirdparty/io/netty/channel/nio/NioEventLoopGroup
       3: dup
       4: iconst_0
       5: new           #3                  // class org/apache/hbase/thirdparty/io/netty/util/concurrent/DefaultThreadFactory
       8: dup
       9: ldc           #4                  // String Default-IPC-NioEventLoopGroup
      11: iconst_1
      12: bipush        10
      14: invokespecial #6                  // Method org/apache/hbase/thirdparty/io/netty/util/concurrent/DefaultThreadFactory."<init>":(Ljava/lang/String;ZI)V
      17: invokespecial #7                  // Method org/apache/hbase/thirdparty/io/netty/channel/nio/NioEventLoopGroup."<init>":(ILjava/util/concurrent/ThreadFactory;)V
      20: ldc           #8                  // class org/apache/hbase/thirdparty/io/netty/channel/socket/nio/NioSocketChannel
      22: invokestatic  #9                  // Method org/apache/hadoop/hbase/util/Pair.newPair:(Ljava/lang/Object;Ljava/lang/Object;)Lorg/apache/hadoop/hbase/util/Pair;
      25: putstatic     #10                 // Field GROUP_AND_CHANNEL_CLASS:Lorg/apache/hadoop/hbase/util/Pair;
      28: return
}
