Compiled from "DefaultSourceFSConfigurationProvider.java"
public class org.apache.hadoop.hbase.replication.regionserver.DefaultSourceFSConfigurationProvider implements org.apache.hadoop.hbase.replication.regionserver.SourceFSConfigurationProvider {
  public org.apache.hadoop.hbase.replication.regionserver.DefaultSourceFSConfigurationProvider();
    Code:
       0: aload_0
       1: invokespecial #1                  // Method java/lang/Object."<init>":()V
       4: aload_0
       5: new           #2                  // class java/util/HashMap
       8: dup
       9: invokespecial #3                  // Method java/util/HashMap."<init>":()V
      12: putfield      #4                  // Field sourceClustersConfs:Ljava/util/Map;
      15: return

  public org.apache.hadoop.conf.Configuration getConf(org.apache.hadoop.conf.Configuration, java.lang.String) throws java.io.IOException;
    Code:
       0: aload_0
       1: getfield      #4                  // Field sourceClustersConfs:Ljava/util/Map;
       4: aload_2
       5: invokeinterface #5,  2            // InterfaceMethod java/util/Map.get:(Ljava/lang/Object;)Ljava/lang/Object;
      10: ifnonnull     301
      13: aload_0
      14: getfield      #4                  // Field sourceClustersConfs:Ljava/util/Map;
      17: dup
      18: astore_3
      19: monitorenter
      20: aload_0
      21: getfield      #4                  // Field sourceClustersConfs:Ljava/util/Map;
      24: aload_2
      25: invokeinterface #5,  2            // InterfaceMethod java/util/Map.get:(Ljava/lang/Object;)Ljava/lang/Object;
      30: ifnonnull     289
      33: getstatic     #6                  // Field LOG:Lorg/slf4j/Logger;
      36: new           #7                  // class java/lang/StringBuilder
      39: dup
      40: invokespecial #8                  // Method java/lang/StringBuilder."<init>":()V
      43: ldc           #9                  // String Loading source cluster FS client conf for cluster
      45: invokevirtual #10                 // Method java/lang/StringBuilder.append:(Ljava/lang/String;)Ljava/lang/StringBuilder;
      48: aload_2
      49: invokevirtual #10                 // Method java/lang/StringBuilder.append:(Ljava/lang/String;)Ljava/lang/StringBuilder;
      52: invokevirtual #11                 // Method java/lang/StringBuilder.toString:()Ljava/lang/String;
      55: invokeinterface #12,  2           // InterfaceMethod org/slf4j/Logger.info:(Ljava/lang/String;)V
      60: new           #13                 // class org/apache/hadoop/conf/Configuration
      63: dup
      64: iconst_0
      65: invokespecial #14                 // Method org/apache/hadoop/conf/Configuration."<init>":(Z)V
      68: astore        4
      70: aload_1
      71: ldc           #16                 // String hbase.replication.conf.dir
      73: invokevirtual #17                 // Method org/apache/hadoop/conf/Configuration.get:(Ljava/lang/String;)Ljava/lang/String;
      76: astore        5
      78: aload         5
      80: ifnonnull     142
      83: getstatic     #6                  // Field LOG:Lorg/slf4j/Logger;
      86: ldc           #18                 // String hbase.replication.conf.dir is not configured.
      88: invokeinterface #19,  2           // InterfaceMethod org/slf4j/Logger.debug:(Ljava/lang/String;)V
      93: ldc           #20                 // class org/apache/hadoop/hbase/HBaseConfiguration
      95: invokevirtual #21                 // Method java/lang/Class.getClassLoader:()Ljava/lang/ClassLoader;
      98: ldc           #22                 // String hbase-site.xml
     100: invokevirtual #23                 // Method java/lang/ClassLoader.getResource:(Ljava/lang/String;)Ljava/net/URL;
     103: astore        6
     105: aload         6
     107: ifnull        135
     110: aload         6
     112: invokevirtual #24                 // Method java/net/URL.getPath:()Ljava/lang/String;
     115: astore        7
     117: aload         7
     119: iconst_0
     120: aload         7
     122: ldc           #25                 // String /
     124: invokevirtual #26                 // Method java/lang/String.lastIndexOf:(Ljava/lang/String;)I
     127: invokevirtual #27                 // Method java/lang/String.substring:(II)Ljava/lang/String;
     130: astore        5
     132: goto          142
     135: ldc           #28                 // String HBASE_CONF_DIR
     137: invokestatic  #29                 // Method java/lang/System.getenv:(Ljava/lang/String;)Ljava/lang/String;
     140: astore        5
     142: new           #30                 // class java/io/File
     145: dup
     146: aload         5
     148: aload_2
     149: invokespecial #31                 // Method java/io/File."<init>":(Ljava/lang/String;Ljava/lang/String;)V
     152: astore        6
     154: getstatic     #6                  // Field LOG:Lorg/slf4j/Logger;
     157: new           #7                  // class java/lang/StringBuilder
     160: dup
     161: invokespecial #8                  // Method java/lang/StringBuilder."<init>":()V
     164: ldc           #32                 // String Loading source cluster
     166: invokevirtual #10                 // Method java/lang/StringBuilder.append:(Ljava/lang/String;)Ljava/lang/StringBuilder;
     169: aload_2
     170: invokevirtual #10                 // Method java/lang/StringBuilder.append:(Ljava/lang/String;)Ljava/lang/StringBuilder;
     173: ldc           #33                 // String  file system configurations from xml files under directory
     175: invokevirtual #10                 // Method java/lang/StringBuilder.append:(Ljava/lang/String;)Ljava/lang/StringBuilder;
     178: aload         6
     180: invokevirtual #34                 // Method java/lang/StringBuilder.append:(Ljava/lang/Object;)Ljava/lang/StringBuilder;
     183: invokevirtual #11                 // Method java/lang/StringBuilder.toString:()Ljava/lang/String;
     186: invokeinterface #12,  2           // InterfaceMethod org/slf4j/Logger.info:(Ljava/lang/String;)V
     191: aload         6
     193: invokestatic  #35                 // Method org/apache/hadoop/fs/FileUtil.list:(Ljava/io/File;)[Ljava/lang/String;
     196: astore        7
     198: aload         7
     200: astore        8
     202: aload         8
     204: arraylength
     205: istore        9
     207: iconst_0
     208: istore        10
     210: iload         10
     212: iload         9
     214: if_icmpge     276
     217: aload         8
     219: iload         10
     221: aaload
     222: astore        11
     224: new           #30                 // class java/io/File
     227: dup
     228: aload         6
     230: aload         11
     232: invokespecial #36                 // Method java/io/File."<init>":(Ljava/io/File;Ljava/lang/String;)V
     235: invokevirtual #37                 // Method java/io/File.isFile:()Z
     238: ifeq          270
     241: aload         11
     243: ldc           #39                 // String .xml
     245: invokevirtual #40                 // Method java/lang/String.endsWith:(Ljava/lang/String;)Z
     248: ifeq          270
     251: aload         4
     253: new           #41                 // class org/apache/hadoop/fs/Path
     256: dup
     257: aload         6
     259: invokevirtual #42                 // Method java/io/File.getPath:()Ljava/lang/String;
     262: aload         11
     264: invokespecial #43                 // Method org/apache/hadoop/fs/Path."<init>":(Ljava/lang/String;Ljava/lang/String;)V
     267: invokevirtual #44                 // Method org/apache/hadoop/conf/Configuration.addResource:(Lorg/apache/hadoop/fs/Path;)V
     270: iinc          10, 1
     273: goto          210
     276: aload_0
     277: getfield      #4                  // Field sourceClustersConfs:Ljava/util/Map;
     280: aload_2
     281: aload         4
     283: invokeinterface #45,  3           // InterfaceMethod java/util/Map.put:(Ljava/lang/Object;Ljava/lang/Object;)Ljava/lang/Object;
     288: pop
     289: aload_3
     290: monitorexit
     291: goto          301
     294: astore        12
     296: aload_3
     297: monitorexit
     298: aload         12
     300: athrow
     301: aload_0
     302: getfield      #4                  // Field sourceClustersConfs:Ljava/util/Map;
     305: aload_2
     306: invokeinterface #5,  2            // InterfaceMethod java/util/Map.get:(Ljava/lang/Object;)Ljava/lang/Object;
     311: checkcast     #13                 // class org/apache/hadoop/conf/Configuration
     314: areturn
    Exception table:
       from    to  target type
          20   291   294   any
         294   298   294   any

  static {};
    Code:
       0: ldc           #38                 // class org/apache/hadoop/hbase/replication/regionserver/DefaultSourceFSConfigurationProvider
       2: invokestatic  #46                 // Method org/slf4j/LoggerFactory.getLogger:(Ljava/lang/Class;)Lorg/slf4j/Logger;
       5: putstatic     #6                  // Field LOG:Lorg/slf4j/Logger;
       8: return
}
