Compiled from "DefaultStoreFileManager.java"
class org.apache.hadoop.hbase.regionserver.DefaultStoreFileManager implements org.apache.hadoop.hbase.regionserver.StoreFileManager {
  public org.apache.hadoop.hbase.regionserver.DefaultStoreFileManager(org.apache.hadoop.hbase.CellComparator, java.util.Comparator<org.apache.hadoop.hbase.regionserver.HStoreFile>, org.apache.hadoop.conf.Configuration, org.apache.hadoop.hbase.regionserver.compactions.CompactionConfiguration);
    Code:
       0: aload_0
       1: invokespecial #1                  // Method java/lang/Object."<init>":()V
       4: aload_0
       5: invokestatic  #2                  // Method org/apache/hbase/thirdparty/com/google/common/collect/ImmutableList.of:()Lorg/apache/hbase/thirdparty/com/google/common/collect/ImmutableList;
       8: putfield      #3                  // Field storefiles:Lorg/apache/hbase/thirdparty/com/google/common/collect/ImmutableList;
      11: aload_0
      12: invokestatic  #2                  // Method org/apache/hbase/thirdparty/com/google/common/collect/ImmutableList.of:()Lorg/apache/hbase/thirdparty/com/google/common/collect/ImmutableList;
      15: putfield      #4                  // Field compactedfiles:Lorg/apache/hbase/thirdparty/com/google/common/collect/ImmutableList;
      18: aload_0
      19: aload_1
      20: putfield      #5                  // Field cellComparator:Lorg/apache/hadoop/hbase/CellComparator;
      23: aload_0
      24: aload_2
      25: putfield      #6                  // Field storeFileComparator:Ljava/util/Comparator;
      28: aload_0
      29: aload         4
      31: putfield      #7                  // Field comConf:Lorg/apache/hadoop/hbase/regionserver/compactions/CompactionConfiguration;
      34: aload_0
      35: aload_3
      36: ldc           #9                  // String hbase.hstore.blockingStoreFiles
      38: bipush        16
      40: invokevirtual #10                 // Method org/apache/hadoop/conf/Configuration.getInt:(Ljava/lang/String;I)I
      43: putfield      #11                 // Field blockingFileCount:I
      46: return

  public void loadFiles(java.util.List<org.apache.hadoop.hbase.regionserver.HStoreFile>);
    Code:
       0: aload_0
       1: aload_0
       2: getfield      #6                  // Field storeFileComparator:Ljava/util/Comparator;
       5: aload_1
       6: invokestatic  #12                 // Method org/apache/hbase/thirdparty/com/google/common/collect/ImmutableList.sortedCopyOf:(Ljava/util/Comparator;Ljava/lang/Iterable;)Lorg/apache/hbase/thirdparty/com/google/common/collect/ImmutableList;
       9: putfield      #3                  // Field storefiles:Lorg/apache/hbase/thirdparty/com/google/common/collect/ImmutableList;
      12: return

  public final java.util.Collection<org.apache.hadoop.hbase.regionserver.HStoreFile> getStorefiles();
    Code:
       0: aload_0
       1: getfield      #3                  // Field storefiles:Lorg/apache/hbase/thirdparty/com/google/common/collect/ImmutableList;
       4: areturn

  public java.util.Collection<org.apache.hadoop.hbase.regionserver.HStoreFile> getCompactedfiles();
    Code:
       0: aload_0
       1: getfield      #4                  // Field compactedfiles:Lorg/apache/hbase/thirdparty/com/google/common/collect/ImmutableList;
       4: areturn

  public void insertNewFiles(java.util.Collection<org.apache.hadoop.hbase.regionserver.HStoreFile>) throws java.io.IOException;
    Code:
       0: aload_0
       1: aload_0
       2: getfield      #6                  // Field storeFileComparator:Ljava/util/Comparator;
       5: aload_0
       6: getfield      #3                  // Field storefiles:Lorg/apache/hbase/thirdparty/com/google/common/collect/ImmutableList;
       9: aload_1
      10: invokestatic  #13                 // Method org/apache/hbase/thirdparty/com/google/common/collect/Iterables.concat:(Ljava/lang/Iterable;Ljava/lang/Iterable;)Ljava/lang/Iterable;
      13: invokestatic  #12                 // Method org/apache/hbase/thirdparty/com/google/common/collect/ImmutableList.sortedCopyOf:(Ljava/util/Comparator;Ljava/lang/Iterable;)Lorg/apache/hbase/thirdparty/com/google/common/collect/ImmutableList;
      16: putfield      #3                  // Field storefiles:Lorg/apache/hbase/thirdparty/com/google/common/collect/ImmutableList;
      19: return

  public org.apache.hbase.thirdparty.com.google.common.collect.ImmutableCollection<org.apache.hadoop.hbase.regionserver.HStoreFile> clearFiles();
    Code:
       0: aload_0
       1: getfield      #3                  // Field storefiles:Lorg/apache/hbase/thirdparty/com/google/common/collect/ImmutableList;
       4: astore_1
       5: aload_0
       6: invokestatic  #2                  // Method org/apache/hbase/thirdparty/com/google/common/collect/ImmutableList.of:()Lorg/apache/hbase/thirdparty/com/google/common/collect/ImmutableList;
       9: putfield      #3                  // Field storefiles:Lorg/apache/hbase/thirdparty/com/google/common/collect/ImmutableList;
      12: aload_1
      13: areturn

  public java.util.Collection<org.apache.hadoop.hbase.regionserver.HStoreFile> clearCompactedFiles();
    Code:
       0: aload_0
       1: getfield      #4                  // Field compactedfiles:Lorg/apache/hbase/thirdparty/com/google/common/collect/ImmutableList;
       4: astore_1
       5: aload_0
       6: invokestatic  #2                  // Method org/apache/hbase/thirdparty/com/google/common/collect/ImmutableList.of:()Lorg/apache/hbase/thirdparty/com/google/common/collect/ImmutableList;
       9: putfield      #4                  // Field compactedfiles:Lorg/apache/hbase/thirdparty/com/google/common/collect/ImmutableList;
      12: aload_1
      13: areturn

  public final int getStorefileCount();
    Code:
       0: aload_0
       1: getfield      #3                  // Field storefiles:Lorg/apache/hbase/thirdparty/com/google/common/collect/ImmutableList;
       4: invokevirtual #14                 // Method org/apache/hbase/thirdparty/com/google/common/collect/ImmutableList.size:()I
       7: ireturn

  public final int getCompactedFilesCount();
    Code:
       0: aload_0
       1: getfield      #4                  // Field compactedfiles:Lorg/apache/hbase/thirdparty/com/google/common/collect/ImmutableList;
       4: invokevirtual #14                 // Method org/apache/hbase/thirdparty/com/google/common/collect/ImmutableList.size:()I
       7: ireturn

  public void addCompactionResults(java.util.Collection<org.apache.hadoop.hbase.regionserver.HStoreFile>, java.util.Collection<org.apache.hadoop.hbase.regionserver.HStoreFile>);
    Code:
       0: aload_0
       1: aload_0
       2: getfield      #6                  // Field storeFileComparator:Ljava/util/Comparator;
       5: aload_0
       6: getfield      #3                  // Field storefiles:Lorg/apache/hbase/thirdparty/com/google/common/collect/ImmutableList;
       9: aload_1
      10: invokedynamic #15,  0             // InvokeDynamic #0:apply:(Ljava/util/Collection;)Lorg/apache/hbase/thirdparty/com/google/common/base/Predicate;
      15: invokestatic  #16                 // Method org/apache/hbase/thirdparty/com/google/common/collect/Iterables.filter:(Ljava/lang/Iterable;Lorg/apache/hbase/thirdparty/com/google/common/base/Predicate;)Ljava/lang/Iterable;
      18: aload_2
      19: invokestatic  #13                 // Method org/apache/hbase/thirdparty/com/google/common/collect/Iterables.concat:(Ljava/lang/Iterable;Ljava/lang/Iterable;)Ljava/lang/Iterable;
      22: invokestatic  #12                 // Method org/apache/hbase/thirdparty/com/google/common/collect/ImmutableList.sortedCopyOf:(Ljava/util/Comparator;Ljava/lang/Iterable;)Lorg/apache/hbase/thirdparty/com/google/common/collect/ImmutableList;
      25: putfield      #3                  // Field storefiles:Lorg/apache/hbase/thirdparty/com/google/common/collect/ImmutableList;
      28: aload_1
      29: invokedynamic #17,  0             // InvokeDynamic #1:accept:()Ljava/util/function/Consumer;
      34: invokeinterface #18,  2           // InterfaceMethod java/util/Collection.forEach:(Ljava/util/function/Consumer;)V
      39: aload_0
      40: aload_0
      41: getfield      #6                  // Field storeFileComparator:Ljava/util/Comparator;
      44: aload_0
      45: getfield      #4                  // Field compactedfiles:Lorg/apache/hbase/thirdparty/com/google/common/collect/ImmutableList;
      48: aload_1
      49: invokestatic  #13                 // Method org/apache/hbase/thirdparty/com/google/common/collect/Iterables.concat:(Ljava/lang/Iterable;Ljava/lang/Iterable;)Ljava/lang/Iterable;
      52: invokestatic  #12                 // Method org/apache/hbase/thirdparty/com/google/common/collect/ImmutableList.sortedCopyOf:(Ljava/util/Comparator;Ljava/lang/Iterable;)Lorg/apache/hbase/thirdparty/com/google/common/collect/ImmutableList;
      55: putfield      #4                  // Field compactedfiles:Lorg/apache/hbase/thirdparty/com/google/common/collect/ImmutableList;
      58: return

  public void removeCompactedFiles(java.util.Collection<org.apache.hadoop.hbase.regionserver.HStoreFile>) throws java.io.IOException;
    Code:
       0: aload_0
       1: aload_0
       2: getfield      #4                  // Field compactedfiles:Lorg/apache/hbase/thirdparty/com/google/common/collect/ImmutableList;
       5: invokevirtual #19                 // Method org/apache/hbase/thirdparty/com/google/common/collect/ImmutableList.stream:()Ljava/util/stream/Stream;
       8: aload_1
       9: invokedynamic #20,  0             // InvokeDynamic #2:test:(Ljava/util/Collection;)Ljava/util/function/Predicate;
      14: invokeinterface #21,  2           // InterfaceMethod java/util/stream/Stream.filter:(Ljava/util/function/Predicate;)Ljava/util/stream/Stream;
      19: aload_0
      20: getfield      #6                  // Field storeFileComparator:Ljava/util/Comparator;
      23: invokeinterface #22,  2           // InterfaceMethod java/util/stream/Stream.sorted:(Ljava/util/Comparator;)Ljava/util/stream/Stream;
      28: invokestatic  #23                 // Method org/apache/hbase/thirdparty/com/google/common/collect/ImmutableList.toImmutableList:()Ljava/util/stream/Collector;
      31: invokeinterface #24,  2           // InterfaceMethod java/util/stream/Stream.collect:(Ljava/util/stream/Collector;)Ljava/lang/Object;
      36: checkcast     #25                 // class org/apache/hbase/thirdparty/com/google/common/collect/ImmutableList
      39: putfield      #4                  // Field compactedfiles:Lorg/apache/hbase/thirdparty/com/google/common/collect/ImmutableList;
      42: return

  public final java.util.Iterator<org.apache.hadoop.hbase.regionserver.HStoreFile> getCandidateFilesForRowKeyBefore(org.apache.hadoop.hbase.KeyValue);
    Code:
       0: aload_0
       1: getfield      #3                  // Field storefiles:Lorg/apache/hbase/thirdparty/com/google/common/collect/ImmutableList;
       4: invokevirtual #26                 // Method org/apache/hbase/thirdparty/com/google/common/collect/ImmutableList.reverse:()Lorg/apache/hbase/thirdparty/com/google/common/collect/ImmutableList;
       7: invokevirtual #27                 // Method org/apache/hbase/thirdparty/com/google/common/collect/ImmutableList.iterator:()Lorg/apache/hbase/thirdparty/com/google/common/collect/UnmodifiableIterator;
      10: areturn

  public java.util.Iterator<org.apache.hadoop.hbase.regionserver.HStoreFile> updateCandidateFilesForRowKeyBefore(java.util.Iterator<org.apache.hadoop.hbase.regionserver.HStoreFile>, org.apache.hadoop.hbase.KeyValue, org.apache.hadoop.hbase.Cell);
    Code:
       0: aload_1
       1: areturn

  public final java.util.Optional<byte[]> getSplitPoint() throws java.io.IOException;
    Code:
       0: aload_0
       1: getfield      #3                  // Field storefiles:Lorg/apache/hbase/thirdparty/com/google/common/collect/ImmutableList;
       4: aload_0
       5: getfield      #5                  // Field cellComparator:Lorg/apache/hadoop/hbase/CellComparator;
       8: invokestatic  #28                 // Method org/apache/hadoop/hbase/regionserver/StoreUtils.getSplitPoint:(Ljava/util/Collection;Lorg/apache/hadoop/hbase/CellComparator;)Ljava/util/Optional;
      11: areturn

  public final java.util.Collection<org.apache.hadoop.hbase.regionserver.HStoreFile> getFilesForScan(byte[], boolean, byte[], boolean);
    Code:
       0: aload_0
       1: invokevirtual #29                 // Method getStorefiles:()Ljava/util/Collection;
       4: areturn

  public int getStoreCompactionPriority();
    Code:
       0: aload_0
       1: getfield      #11                 // Field blockingFileCount:I
       4: aload_0
       5: getfield      #3                  // Field storefiles:Lorg/apache/hbase/thirdparty/com/google/common/collect/ImmutableList;
       8: invokevirtual #14                 // Method org/apache/hbase/thirdparty/com/google/common/collect/ImmutableList.size:()I
      11: isub
      12: istore_1
      13: iload_1
      14: iconst_1
      15: if_icmpne     24
      18: iload_1
      19: iconst_1
      20: iadd
      21: goto          25
      24: iload_1
      25: ireturn

  public java.util.Collection<org.apache.hadoop.hbase.regionserver.HStoreFile> getUnneededFiles(long, java.util.List<org.apache.hadoop.hbase.regionserver.HStoreFile>);
    Code:
       0: aload_0
       1: getfield      #3                  // Field storefiles:Lorg/apache/hbase/thirdparty/com/google/common/collect/ImmutableList;
       4: astore        4
       6: aload         4
       8: invokevirtual #19                 // Method org/apache/hbase/thirdparty/com/google/common/collect/ImmutableList.stream:()Ljava/util/stream/Stream;
      11: iconst_0
      12: aload         4
      14: invokevirtual #14                 // Method org/apache/hbase/thirdparty/com/google/common/collect/ImmutableList.size:()I
      17: iconst_1
      18: isub
      19: invokestatic  #30                 // Method java/lang/Math.max:(II)I
      22: i2l
      23: invokeinterface #31,  3           // InterfaceMethod java/util/stream/Stream.limit:(J)Ljava/util/stream/Stream;
      28: lload_1
      29: aload_3
      30: invokedynamic #32,  0             // InvokeDynamic #3:test:(JLjava/util/List;)Ljava/util/function/Predicate;
      35: invokeinterface #21,  2           // InterfaceMethod java/util/stream/Stream.filter:(Ljava/util/function/Predicate;)Ljava/util/stream/Stream;
      40: invokestatic  #33                 // Method java/util/stream/Collectors.toList:()Ljava/util/stream/Collector;
      43: invokeinterface #24,  2           // InterfaceMethod java/util/stream/Stream.collect:(Ljava/util/stream/Collector;)Ljava/lang/Object;
      48: checkcast     #34                 // class java/util/Collection
      51: areturn

  public double getCompactionPressure();
    Code:
       0: aload_0
       1: invokevirtual #35                 // Method getStorefileCount:()I
       4: istore_1
       5: aload_0
       6: getfield      #7                  // Field comConf:Lorg/apache/hadoop/hbase/regionserver/compactions/CompactionConfiguration;
       9: invokevirtual #36                 // Method org/apache/hadoop/hbase/regionserver/compactions/CompactionConfiguration.getMinFilesToCompact:()I
      12: istore_2
      13: iload_1
      14: iload_2
      15: if_icmpgt     20
      18: dconst_0
      19: dreturn
      20: iload_1
      21: iload_2
      22: isub
      23: i2d
      24: aload_0
      25: getfield      #11                 // Field blockingFileCount:I
      28: iload_2
      29: isub
      30: i2d
      31: ddiv
      32: dreturn

  public java.util.Comparator<org.apache.hadoop.hbase.regionserver.HStoreFile> getStoreFileComparator();
    Code:
       0: aload_0
       1: getfield      #6                  // Field storeFileComparator:Ljava/util/Comparator;
       4: areturn

  static {};
    Code:
       0: ldc           #47                 // class org/apache/hadoop/hbase/regionserver/DefaultStoreFileManager
       2: invokestatic  #48                 // Method org/slf4j/LoggerFactory.getLogger:(Ljava/lang/Class;)Lorg/slf4j/Logger;
       5: putstatic     #40                 // Field LOG:Lorg/slf4j/Logger;
       8: return
}
