Compiled from "DefaultVisibilityLabelServiceImpl.java"
public class org.apache.hadoop.hbase.security.visibility.DefaultVisibilityLabelServiceImpl implements org.apache.hadoop.hbase.security.visibility.VisibilityLabelService {
  static final boolean $assertionsDisabled;

  public org.apache.hadoop.hbase.security.visibility.DefaultVisibilityLabelServiceImpl();
    Code:
       0: aload_0
       1: invokespecial #4                  // Method java/lang/Object."<init>":()V
       4: aload_0
       5: new           #5                  // class java/util/concurrent/atomic/AtomicInteger
       8: dup
       9: iconst_m1
      10: invokespecial #6                  // Method java/util/concurrent/atomic/AtomicInteger."<init>":(I)V
      13: putfield      #7                  // Field ordinalCounter:Ljava/util/concurrent/atomic/AtomicInteger;
      16: return

  public void setConf(org.apache.hadoop.conf.Configuration);
    Code:
       0: aload_0
       1: aload_1
       2: putfield      #8                  // Field conf:Lorg/apache/hadoop/conf/Configuration;
       5: return

  public org.apache.hadoop.conf.Configuration getConf();
    Code:
       0: aload_0
       1: getfield      #8                  // Field conf:Lorg/apache/hadoop/conf/Configuration;
       4: areturn

  public void init(org.apache.hadoop.hbase.coprocessor.RegionCoprocessorEnvironment) throws java.io.IOException;
    Code:
       0: aload_1
       1: checkcast     #9                  // class org/apache/hadoop/hbase/coprocessor/HasRegionServerServices
       4: invokeinterface #10,  1           // InterfaceMethod org/apache/hadoop/hbase/coprocessor/HasRegionServerServices.getRegionServerServices:()Lorg/apache/hadoop/hbase/regionserver/RegionServerServices;
       9: invokeinterface #11,  1           // InterfaceMethod org/apache/hadoop/hbase/regionserver/RegionServerServices.getZooKeeper:()Lorg/apache/hadoop/hbase/zookeeper/ZKWatcher;
      14: astore_2
      15: aload_0
      16: aload_2
      17: aload_0
      18: getfield      #8                  // Field conf:Lorg/apache/hadoop/conf/Configuration;
      21: invokestatic  #12                 // Method org/apache/hadoop/hbase/security/visibility/VisibilityLabelsCache.createAndGet:(Lorg/apache/hadoop/hbase/zookeeper/ZKWatcher;Lorg/apache/hadoop/conf/Configuration;)Lorg/apache/hadoop/hbase/security/visibility/VisibilityLabelsCache;
      24: putfield      #13                 // Field labelsCache:Lorg/apache/hadoop/hbase/security/visibility/VisibilityLabelsCache;
      27: goto          44
      30: astore_3
      31: getstatic     #15                 // Field LOG:Lorg/slf4j/Logger;
      34: ldc           #16                 // String Error creating VisibilityLabelsCache
      36: aload_3
      37: invokeinterface #17,  3           // InterfaceMethod org/slf4j/Logger.error:(Ljava/lang/String;Ljava/lang/Throwable;)V
      42: aload_3
      43: athrow
      44: aload_0
      45: aload_0
      46: getfield      #8                  // Field conf:Lorg/apache/hadoop/conf/Configuration;
      49: invokestatic  #18                 // Method org/apache/hadoop/hbase/security/visibility/VisibilityUtils.getScanLabelGenerators:(Lorg/apache/hadoop/conf/Configuration;)Ljava/util/List;
      52: putfield      #19                 // Field scanLabelGenerators:Ljava/util/List;
      55: aload_1
      56: invokeinterface #20,  1           // InterfaceMethod org/apache/hadoop/hbase/coprocessor/RegionCoprocessorEnvironment.getRegion:()Lorg/apache/hadoop/hbase/regionserver/Region;
      61: invokeinterface #21,  1           // InterfaceMethod org/apache/hadoop/hbase/regionserver/Region.getRegionInfo:()Lorg/apache/hadoop/hbase/client/RegionInfo;
      66: invokeinterface #22,  1           // InterfaceMethod org/apache/hadoop/hbase/client/RegionInfo.getTable:()Lorg/apache/hadoop/hbase/TableName;
      71: getstatic     #23                 // Field org/apache/hadoop/hbase/security/visibility/VisibilityConstants.LABELS_TABLE_NAME:Lorg/apache/hadoop/hbase/TableName;
      74: invokevirtual #24                 // Method org/apache/hadoop/hbase/TableName.equals:(Ljava/lang/Object;)Z
      77: ifeq          271
      80: aload_0
      81: aload_1
      82: invokeinterface #20,  1           // InterfaceMethod org/apache/hadoop/hbase/coprocessor/RegionCoprocessorEnvironment.getRegion:()Lorg/apache/hadoop/hbase/regionserver/Region;
      87: putfield      #25                 // Field labelsRegion:Lorg/apache/hadoop/hbase/regionserver/Region;
      90: aload_0
      91: aload_0
      92: invokevirtual #26                 // Method getExistingLabelsWithAuths:()Ljava/util/List;
      95: invokevirtual #27                 // Method extractLabelsAndAuths:(Ljava/util/List;)Lorg/apache/hadoop/hbase/util/Pair;
      98: astore_3
      99: aload_3
     100: invokevirtual #28                 // Method org/apache/hadoop/hbase/util/Pair.getFirst:()Ljava/lang/Object;
     103: checkcast     #29                 // class java/util/Map
     106: astore        4
     108: aload_3
     109: invokevirtual #30                 // Method org/apache/hadoop/hbase/util/Pair.getSecond:()Ljava/lang/Object;
     112: checkcast     #29                 // class java/util/Map
     115: astore        5
     117: aload_0
     118: aload_0
     119: getfield      #25                 // Field labelsRegion:Lorg/apache/hadoop/hbase/regionserver/Region;
     122: aload         4
     124: aload         5
     126: invokevirtual #31                 // Method addSystemLabel:(Lorg/apache/hadoop/hbase/regionserver/Region;Ljava/util/Map;Ljava/util/Map;)V
     129: iconst_1
     130: istore        6
     132: aload         4
     134: invokeinterface #33,  1           // InterfaceMethod java/util/Map.values:()Ljava/util/Collection;
     139: invokeinterface #34,  1           // InterfaceMethod java/util/Collection.iterator:()Ljava/util/Iterator;
     144: astore        7
     146: aload         7
     148: invokeinterface #35,  1           // InterfaceMethod java/util/Iterator.hasNext:()Z
     153: ifeq          188
     156: aload         7
     158: invokeinterface #36,  1           // InterfaceMethod java/util/Iterator.next:()Ljava/lang/Object;
     163: checkcast     #37                 // class java/lang/Integer
     166: astore        8
     168: aload         8
     170: invokevirtual #38                 // Method java/lang/Integer.intValue:()I
     173: iload         6
     175: if_icmple     185
     178: aload         8
     180: invokevirtual #38                 // Method java/lang/Integer.intValue:()I
     183: istore        6
     185: goto          146
     188: aload_0
     189: getfield      #7                  // Field ordinalCounter:Ljava/util/concurrent/atomic/AtomicInteger;
     192: iload         6
     194: iconst_1
     195: iadd
     196: invokevirtual #39                 // Method java/util/concurrent/atomic/AtomicInteger.set:(I)V
     199: aload         4
     201: invokeinterface #40,  1           // InterfaceMethod java/util/Map.size:()I
     206: ifle          235
     209: aload         4
     211: invokestatic  #41                 // Method org/apache/hadoop/hbase/security/visibility/VisibilityUtils.getDataToWriteToZooKeeper:(Ljava/util/Map;)[B
     214: astore        7
     216: aload_0
     217: getfield      #13                 // Field labelsCache:Lorg/apache/hadoop/hbase/security/visibility/VisibilityLabelsCache;
     220: aload         7
     222: iconst_1
     223: invokevirtual #42                 // Method org/apache/hadoop/hbase/security/visibility/VisibilityLabelsCache.writeToZookeeper:([BZ)V
     226: aload_0
     227: getfield      #13                 // Field labelsCache:Lorg/apache/hadoop/hbase/security/visibility/VisibilityLabelsCache;
     230: aload         7
     232: invokevirtual #43                 // Method org/apache/hadoop/hbase/security/visibility/VisibilityLabelsCache.refreshLabelsCache:([B)V
     235: aload         5
     237: invokeinterface #40,  1           // InterfaceMethod java/util/Map.size:()I
     242: ifle          271
     245: aload         5
     247: invokestatic  #44                 // Method org/apache/hadoop/hbase/security/visibility/VisibilityUtils.getUserAuthsDataToWriteToZooKeeper:(Ljava/util/Map;)[B
     250: astore        7
     252: aload_0
     253: getfield      #13                 // Field labelsCache:Lorg/apache/hadoop/hbase/security/visibility/VisibilityLabelsCache;
     256: aload         7
     258: iconst_0
     259: invokevirtual #42                 // Method org/apache/hadoop/hbase/security/visibility/VisibilityLabelsCache.writeToZookeeper:([BZ)V
     262: aload_0
     263: getfield      #13                 // Field labelsCache:Lorg/apache/hadoop/hbase/security/visibility/VisibilityLabelsCache;
     266: aload         7
     268: invokevirtual #45                 // Method org/apache/hadoop/hbase/security/visibility/VisibilityLabelsCache.refreshUserAuthsCache:([B)V
     271: return
    Exception table:
       from    to  target type
          15    27    30   Class java/io/IOException

  protected java.util.List<java.util.List<org.apache.hadoop.hbase.Cell>> getExistingLabelsWithAuths() throws java.io.IOException;
    Code:
       0: new           #46                 // class org/apache/hadoop/hbase/client/Scan
       3: dup
       4: invokespecial #47                 // Method org/apache/hadoop/hbase/client/Scan."<init>":()V
       7: astore_1
       8: aload_0
       9: getfield      #25                 // Field labelsRegion:Lorg/apache/hadoop/hbase/regionserver/Region;
      12: aload_1
      13: invokeinterface #48,  2           // InterfaceMethod org/apache/hadoop/hbase/regionserver/Region.getScanner:(Lorg/apache/hadoop/hbase/client/Scan;)Lorg/apache/hadoop/hbase/regionserver/RegionScanner;
      18: astore_2
      19: new           #49                 // class java/util/ArrayList
      22: dup
      23: invokespecial #50                 // Method java/util/ArrayList."<init>":()V
      26: astore_3
      27: new           #49                 // class java/util/ArrayList
      30: dup
      31: invokespecial #50                 // Method java/util/ArrayList."<init>":()V
      34: astore        4
      36: aload_2
      37: aload         4
      39: invokeinterface #51,  2           // InterfaceMethod org/apache/hadoop/hbase/regionserver/RegionScanner.next:(Ljava/util/List;)Z
      44: pop
      45: aload         4
      47: invokeinterface #52,  1           // InterfaceMethod java/util/List.isEmpty:()Z
      52: ifeq          58
      55: goto          70
      58: aload_3
      59: aload         4
      61: invokeinterface #53,  2           // InterfaceMethod java/util/List.add:(Ljava/lang/Object;)Z
      66: pop
      67: goto          27
      70: aload_2
      71: invokeinterface #54,  1           // InterfaceMethod org/apache/hadoop/hbase/regionserver/RegionScanner.close:()V
      76: goto          90
      79: astore        5
      81: aload_2
      82: invokeinterface #54,  1           // InterfaceMethod org/apache/hadoop/hbase/regionserver/RegionScanner.close:()V
      87: aload         5
      89: athrow
      90: aload_3
      91: areturn
    Exception table:
       from    to  target type
          27    70    79   any
          79    81    79   any

  protected org.apache.hadoop.hbase.util.Pair<java.util.Map<java.lang.String, java.lang.Integer>, java.util.Map<java.lang.String, java.util.List<java.lang.Integer>>> extractLabelsAndAuths(java.util.List<java.util.List<org.apache.hadoop.hbase.Cell>>);
    Code:
       0: new           #55                 // class java/util/HashMap
       3: dup
       4: invokespecial #56                 // Method java/util/HashMap."<init>":()V
       7: astore_2
       8: new           #55                 // class java/util/HashMap
      11: dup
      12: invokespecial #56                 // Method java/util/HashMap."<init>":()V
      15: astore_3
      16: aload_1
      17: invokeinterface #57,  1           // InterfaceMethod java/util/List.iterator:()Ljava/util/Iterator;
      22: astore        4
      24: aload         4
      26: invokeinterface #35,  1           // InterfaceMethod java/util/Iterator.hasNext:()Z
      31: ifeq          216
      34: aload         4
      36: invokeinterface #36,  1           // InterfaceMethod java/util/Iterator.next:()Ljava/lang/Object;
      41: checkcast     #58                 // class java/util/List
      44: astore        5
      46: aload         5
      48: invokeinterface #57,  1           // InterfaceMethod java/util/List.iterator:()Ljava/util/Iterator;
      53: astore        6
      55: aload         6
      57: invokeinterface #35,  1           // InterfaceMethod java/util/Iterator.hasNext:()Z
      62: ifeq          213
      65: aload         6
      67: invokeinterface #36,  1           // InterfaceMethod java/util/Iterator.next:()Ljava/lang/Object;
      72: checkcast     #59                 // class org/apache/hadoop/hbase/Cell
      75: astore        7
      77: aload         7
      79: getstatic     #60                 // Field org/apache/hadoop/hbase/security/visibility/VisibilityConstants.LABEL_QUALIFIER:[B
      82: invokestatic  #61                 // Method org/apache/hadoop/hbase/CellUtil.matchingQualifier:(Lorg/apache/hadoop/hbase/Cell;[B)Z
      85: ifeq          130
      88: aload_2
      89: aload         7
      91: invokeinterface #62,  1           // InterfaceMethod org/apache/hadoop/hbase/Cell.getValueArray:()[B
      96: aload         7
      98: invokeinterface #63,  1           // InterfaceMethod org/apache/hadoop/hbase/Cell.getValueOffset:()I
     103: aload         7
     105: invokeinterface #64,  1           // InterfaceMethod org/apache/hadoop/hbase/Cell.getValueLength:()I
     110: invokestatic  #65                 // Method org/apache/hadoop/hbase/util/Bytes.toString:([BII)Ljava/lang/String;
     113: aload         7
     115: invokestatic  #66                 // Method org/apache/hadoop/hbase/PrivateCellUtil.getRowAsInt:(Lorg/apache/hadoop/hbase/Cell;)I
     118: invokestatic  #67                 // Method java/lang/Integer.valueOf:(I)Ljava/lang/Integer;
     121: invokeinterface #68,  3           // InterfaceMethod java/util/Map.put:(Ljava/lang/Object;Ljava/lang/Object;)Ljava/lang/Object;
     126: pop
     127: goto          210
     130: aload         7
     132: invokeinterface #69,  1           // InterfaceMethod org/apache/hadoop/hbase/Cell.getQualifierArray:()[B
     137: aload         7
     139: invokeinterface #70,  1           // InterfaceMethod org/apache/hadoop/hbase/Cell.getQualifierOffset:()I
     144: aload         7
     146: invokeinterface #71,  1           // InterfaceMethod org/apache/hadoop/hbase/Cell.getQualifierLength:()I
     151: invokestatic  #65                 // Method org/apache/hadoop/hbase/util/Bytes.toString:([BII)Ljava/lang/String;
     154: astore        8
     156: aload_3
     157: aload         8
     159: invokeinterface #72,  2           // InterfaceMethod java/util/Map.get:(Ljava/lang/Object;)Ljava/lang/Object;
     164: checkcast     #58                 // class java/util/List
     167: astore        9
     169: aload         9
     171: ifnonnull     194
     174: new           #49                 // class java/util/ArrayList
     177: dup
     178: invokespecial #50                 // Method java/util/ArrayList."<init>":()V
     181: astore        9
     183: aload_3
     184: aload         8
     186: aload         9
     188: invokeinterface #68,  3           // InterfaceMethod java/util/Map.put:(Ljava/lang/Object;Ljava/lang/Object;)Ljava/lang/Object;
     193: pop
     194: aload         9
     196: aload         7
     198: invokestatic  #66                 // Method org/apache/hadoop/hbase/PrivateCellUtil.getRowAsInt:(Lorg/apache/hadoop/hbase/Cell;)I
     201: invokestatic  #67                 // Method java/lang/Integer.valueOf:(I)Ljava/lang/Integer;
     204: invokeinterface #53,  2           // InterfaceMethod java/util/List.add:(Ljava/lang/Object;)Z
     209: pop
     210: goto          55
     213: goto          24
     216: new           #73                 // class org/apache/hadoop/hbase/util/Pair
     219: dup
     220: aload_2
     221: aload_3
     222: invokespecial #74                 // Method org/apache/hadoop/hbase/util/Pair."<init>":(Ljava/lang/Object;Ljava/lang/Object;)V
     225: areturn

  protected void addSystemLabel(org.apache.hadoop.hbase.regionserver.Region, java.util.Map<java.lang.String, java.lang.Integer>, java.util.Map<java.lang.String, java.util.List<java.lang.Integer>>) throws java.io.IOException;
    Code:
       0: aload_2
       1: ldc           #75                 // String system
       3: invokeinterface #76,  2           // InterfaceMethod java/util/Map.containsKey:(Ljava/lang/Object;)Z
       8: ifne          117
      11: iconst_1
      12: invokestatic  #77                 // Method org/apache/hadoop/hbase/util/Bytes.toBytes:(I)[B
      15: astore        4
      17: new           #78                 // class org/apache/hadoop/hbase/client/Put
      20: dup
      21: aload         4
      23: invokespecial #79                 // Method org/apache/hadoop/hbase/client/Put."<init>":([B)V
      26: astore        5
      28: aload         5
      30: getstatic     #80                 // Field org/apache/hadoop/hbase/CellBuilderType.SHALLOW_COPY:Lorg/apache/hadoop/hbase/CellBuilderType;
      33: invokestatic  #81                 // Method org/apache/hadoop/hbase/CellBuilderFactory.create:(Lorg/apache/hadoop/hbase/CellBuilderType;)Lorg/apache/hadoop/hbase/CellBuilder;
      36: aload         4
      38: invokeinterface #82,  2           // InterfaceMethod org/apache/hadoop/hbase/CellBuilder.setRow:([B)Lorg/apache/hadoop/hbase/CellBuilder;
      43: getstatic     #83                 // Field org/apache/hadoop/hbase/security/visibility/VisibilityConstants.LABELS_TABLE_FAMILY:[B
      46: invokeinterface #84,  2           // InterfaceMethod org/apache/hadoop/hbase/CellBuilder.setFamily:([B)Lorg/apache/hadoop/hbase/CellBuilder;
      51: getstatic     #60                 // Field org/apache/hadoop/hbase/security/visibility/VisibilityConstants.LABEL_QUALIFIER:[B
      54: invokeinterface #85,  2           // InterfaceMethod org/apache/hadoop/hbase/CellBuilder.setQualifier:([B)Lorg/apache/hadoop/hbase/CellBuilder;
      59: aload         5
      61: invokevirtual #86                 // Method org/apache/hadoop/hbase/client/Put.getTimestamp:()J
      64: invokeinterface #87,  3           // InterfaceMethod org/apache/hadoop/hbase/CellBuilder.setTimestamp:(J)Lorg/apache/hadoop/hbase/CellBuilder;
      69: getstatic     #88                 // Field org/apache/hadoop/hbase/Cell$Type.Put:Lorg/apache/hadoop/hbase/Cell$Type;
      72: invokeinterface #89,  2           // InterfaceMethod org/apache/hadoop/hbase/CellBuilder.setType:(Lorg/apache/hadoop/hbase/Cell$Type;)Lorg/apache/hadoop/hbase/CellBuilder;
      77: ldc           #75                 // String system
      79: invokestatic  #90                 // Method org/apache/hadoop/hbase/util/Bytes.toBytes:(Ljava/lang/String;)[B
      82: invokeinterface #91,  2           // InterfaceMethod org/apache/hadoop/hbase/CellBuilder.setValue:([B)Lorg/apache/hadoop/hbase/CellBuilder;
      87: invokeinterface #92,  1           // InterfaceMethod org/apache/hadoop/hbase/CellBuilder.build:()Lorg/apache/hadoop/hbase/Cell;
      92: invokevirtual #93                 // Method org/apache/hadoop/hbase/client/Put.add:(Lorg/apache/hadoop/hbase/Cell;)Lorg/apache/hadoop/hbase/client/Put;
      95: pop
      96: aload_1
      97: aload         5
      99: invokeinterface #94,  2           // InterfaceMethod org/apache/hadoop/hbase/regionserver/Region.put:(Lorg/apache/hadoop/hbase/client/Put;)V
     104: aload_2
     105: ldc           #75                 // String system
     107: iconst_1
     108: invokestatic  #67                 // Method java/lang/Integer.valueOf:(I)Ljava/lang/Integer;
     111: invokeinterface #68,  3           // InterfaceMethod java/util/Map.put:(Ljava/lang/Object;Ljava/lang/Object;)Ljava/lang/Object;
     116: pop
     117: return

  public org.apache.hadoop.hbase.regionserver.OperationStatus[] addLabels(java.util.List<byte[]>) throws java.io.IOException;
    Code:
       0: getstatic     #95                 // Field $assertionsDisabled:Z
       3: ifne          21
       6: aload_0
       7: getfield      #25                 // Field labelsRegion:Lorg/apache/hadoop/hbase/regionserver/Region;
      10: ifnonnull     21
      13: new           #96                 // class java/lang/AssertionError
      16: dup
      17: invokespecial #97                 // Method java/lang/AssertionError."<init>":()V
      20: athrow
      21: aload_1
      22: invokeinterface #98,  1           // InterfaceMethod java/util/List.size:()I
      27: anewarray     #99                 // class org/apache/hadoop/hbase/regionserver/OperationStatus
      30: astore_2
      31: new           #49                 // class java/util/ArrayList
      34: dup
      35: aload_1
      36: invokeinterface #98,  1           // InterfaceMethod java/util/List.size:()I
      41: invokespecial #100                // Method java/util/ArrayList."<init>":(I)V
      44: astore_3
      45: iconst_0
      46: istore        4
      48: getstatic     #80                 // Field org/apache/hadoop/hbase/CellBuilderType.SHALLOW_COPY:Lorg/apache/hadoop/hbase/CellBuilderType;
      51: invokestatic  #101                // Method org/apache/hadoop/hbase/ExtendedCellBuilderFactory.create:(Lorg/apache/hadoop/hbase/CellBuilderType;)Lorg/apache/hadoop/hbase/ExtendedCellBuilder;
      54: astore        5
      56: aload_1
      57: invokeinterface #57,  1           // InterfaceMethod java/util/List.iterator:()Ljava/util/Iterator;
      62: astore        6
      64: aload         6
      66: invokeinterface #35,  1           // InterfaceMethod java/util/Iterator.hasNext:()Z
      71: ifeq          319
      74: aload         6
      76: invokeinterface #36,  1           // InterfaceMethod java/util/Iterator.next:()Ljava/lang/Object;
      81: checkcast     #102                // class "[B"
      84: astore        7
      86: aload         7
      88: invokestatic  #103                // Method org/apache/hadoop/hbase/util/Bytes.toString:([B)Ljava/lang/String;
      91: astore        8
      93: aload_0
      94: getfield      #13                 // Field labelsCache:Lorg/apache/hadoop/hbase/security/visibility/VisibilityLabelsCache;
      97: aload         8
      99: invokevirtual #104                // Method org/apache/hadoop/hbase/security/visibility/VisibilityLabelsCache.getLabelOrdinal:(Ljava/lang/String;)I
     102: ifle          154
     105: aload_2
     106: iload         4
     108: new           #99                 // class org/apache/hadoop/hbase/regionserver/OperationStatus
     111: dup
     112: getstatic     #105                // Field org/apache/hadoop/hbase/HConstants$OperationStatusCode.FAILURE:Lorg/apache/hadoop/hbase/HConstants$OperationStatusCode;
     115: new           #106                // class org/apache/hadoop/hbase/security/visibility/LabelAlreadyExistsException
     118: dup
     119: new           #107                // class java/lang/StringBuilder
     122: dup
     123: invokespecial #108                // Method java/lang/StringBuilder."<init>":()V
     126: ldc           #109                // String Label '
     128: invokevirtual #110                // Method java/lang/StringBuilder.append:(Ljava/lang/String;)Ljava/lang/StringBuilder;
     131: aload         8
     133: invokevirtual #110                // Method java/lang/StringBuilder.append:(Ljava/lang/String;)Ljava/lang/StringBuilder;
     136: ldc           #111                // String ' already exists
     138: invokevirtual #110                // Method java/lang/StringBuilder.append:(Ljava/lang/String;)Ljava/lang/StringBuilder;
     141: invokevirtual #112                // Method java/lang/StringBuilder.toString:()Ljava/lang/String;
     144: invokespecial #113                // Method org/apache/hadoop/hbase/security/visibility/LabelAlreadyExistsException."<init>":(Ljava/lang/String;)V
     147: invokespecial #114                // Method org/apache/hadoop/hbase/regionserver/OperationStatus."<init>":(Lorg/apache/hadoop/hbase/HConstants$OperationStatusCode;Ljava/lang/Exception;)V
     150: aastore
     151: goto          313
     154: aload_0
     155: getfield      #7                  // Field ordinalCounter:Ljava/util/concurrent/atomic/AtomicInteger;
     158: invokevirtual #115                // Method java/util/concurrent/atomic/AtomicInteger.get:()I
     161: invokestatic  #77                 // Method org/apache/hadoop/hbase/util/Bytes.toBytes:(I)[B
     164: astore        9
     166: new           #78                 // class org/apache/hadoop/hbase/client/Put
     169: dup
     170: aload         9
     172: invokespecial #79                 // Method org/apache/hadoop/hbase/client/Put."<init>":([B)V
     175: astore        10
     177: aload         10
     179: aload         5
     181: invokeinterface #116,  1          // InterfaceMethod org/apache/hadoop/hbase/ExtendedCellBuilder.clear:()Lorg/apache/hadoop/hbase/ExtendedCellBuilder;
     186: aload         9
     188: invokeinterface #117,  2          // InterfaceMethod org/apache/hadoop/hbase/ExtendedCellBuilder.setRow:([B)Lorg/apache/hadoop/hbase/ExtendedCellBuilder;
     193: getstatic     #83                 // Field org/apache/hadoop/hbase/security/visibility/VisibilityConstants.LABELS_TABLE_FAMILY:[B
     196: invokeinterface #118,  2          // InterfaceMethod org/apache/hadoop/hbase/ExtendedCellBuilder.setFamily:([B)Lorg/apache/hadoop/hbase/ExtendedCellBuilder;
     201: getstatic     #60                 // Field org/apache/hadoop/hbase/security/visibility/VisibilityConstants.LABEL_QUALIFIER:[B
     204: invokeinterface #119,  2          // InterfaceMethod org/apache/hadoop/hbase/ExtendedCellBuilder.setQualifier:([B)Lorg/apache/hadoop/hbase/ExtendedCellBuilder;
     209: aload         10
     211: invokevirtual #86                 // Method org/apache/hadoop/hbase/client/Put.getTimestamp:()J
     214: invokeinterface #120,  3          // InterfaceMethod org/apache/hadoop/hbase/ExtendedCellBuilder.setTimestamp:(J)Lorg/apache/hadoop/hbase/ExtendedCellBuilder;
     219: getstatic     #88                 // Field org/apache/hadoop/hbase/Cell$Type.Put:Lorg/apache/hadoop/hbase/Cell$Type;
     222: invokeinterface #121,  2          // InterfaceMethod org/apache/hadoop/hbase/ExtendedCellBuilder.setType:(Lorg/apache/hadoop/hbase/Cell$Type;)Lorg/apache/hadoop/hbase/ExtendedCellBuilder;
     227: aload         7
     229: invokeinterface #122,  2          // InterfaceMethod org/apache/hadoop/hbase/ExtendedCellBuilder.setValue:([B)Lorg/apache/hadoop/hbase/ExtendedCellBuilder;
     234: getstatic     #123                // Field LABELS_TABLE_TAGS:[Lorg/apache/hadoop/hbase/Tag;
     237: invokestatic  #124                // Method java/util/Arrays.asList:([Ljava/lang/Object;)Ljava/util/List;
     240: invokestatic  #125                // Method org/apache/hadoop/hbase/TagUtil.fromList:(Ljava/util/List;)[B
     243: invokeinterface #126,  2          // InterfaceMethod org/apache/hadoop/hbase/ExtendedCellBuilder.setTags:([B)Lorg/apache/hadoop/hbase/ExtendedCellBuilder;
     248: invokeinterface #127,  1          // InterfaceMethod org/apache/hadoop/hbase/ExtendedCellBuilder.build:()Lorg/apache/hadoop/hbase/ExtendedCell;
     253: invokevirtual #93                 // Method org/apache/hadoop/hbase/client/Put.add:(Lorg/apache/hadoop/hbase/Cell;)Lorg/apache/hadoop/hbase/client/Put;
     256: pop
     257: getstatic     #15                 // Field LOG:Lorg/slf4j/Logger;
     260: invokeinterface #128,  1          // InterfaceMethod org/slf4j/Logger.isDebugEnabled:()Z
     265: ifeq          296
     268: getstatic     #15                 // Field LOG:Lorg/slf4j/Logger;
     271: new           #107                // class java/lang/StringBuilder
     274: dup
     275: invokespecial #108                // Method java/lang/StringBuilder."<init>":()V
     278: ldc           #129                // String Adding the label
     280: invokevirtual #110                // Method java/lang/StringBuilder.append:(Ljava/lang/String;)Ljava/lang/StringBuilder;
     283: aload         8
     285: invokevirtual #110                // Method java/lang/StringBuilder.append:(Ljava/lang/String;)Ljava/lang/StringBuilder;
     288: invokevirtual #112                // Method java/lang/StringBuilder.toString:()Ljava/lang/String;
     291: invokeinterface #130,  2          // InterfaceMethod org/slf4j/Logger.debug:(Ljava/lang/String;)V
     296: aload_3
     297: aload         10
     299: invokeinterface #53,  2           // InterfaceMethod java/util/List.add:(Ljava/lang/Object;)Z
     304: pop
     305: aload_0
     306: getfield      #7                  // Field ordinalCounter:Ljava/util/concurrent/atomic/AtomicInteger;
     309: invokevirtual #131                // Method java/util/concurrent/atomic/AtomicInteger.incrementAndGet:()I
     312: pop
     313: iinc          4, 1
     316: goto          64
     319: aload_0
     320: aload_3
     321: aload_2
     322: invokespecial #132                // Method mutateLabelsRegion:(Ljava/util/List;[Lorg/apache/hadoop/hbase/regionserver/OperationStatus;)Z
     325: ifeq          333
     328: aload_0
     329: iconst_1
     330: invokevirtual #133                // Method updateZk:(Z)V
     333: aload_2
     334: areturn

  public org.apache.hadoop.hbase.regionserver.OperationStatus[] setAuths(byte[], java.util.List<byte[]>) throws java.io.IOException;
    Code:
       0: getstatic     #95                 // Field $assertionsDisabled:Z
       3: ifne          21
       6: aload_0
       7: getfield      #25                 // Field labelsRegion:Lorg/apache/hadoop/hbase/regionserver/Region;
      10: ifnonnull     21
      13: new           #96                 // class java/lang/AssertionError
      16: dup
      17: invokespecial #97                 // Method java/lang/AssertionError."<init>":()V
      20: athrow
      21: aload_2
      22: invokeinterface #98,  1           // InterfaceMethod java/util/List.size:()I
      27: anewarray     #99                 // class org/apache/hadoop/hbase/regionserver/OperationStatus
      30: astore_3
      31: new           #49                 // class java/util/ArrayList
      34: dup
      35: aload_2
      36: invokeinterface #98,  1           // InterfaceMethod java/util/List.size:()I
      41: invokespecial #100                // Method java/util/ArrayList."<init>":(I)V
      44: astore        4
      46: iconst_0
      47: istore        5
      49: getstatic     #80                 // Field org/apache/hadoop/hbase/CellBuilderType.SHALLOW_COPY:Lorg/apache/hadoop/hbase/CellBuilderType;
      52: invokestatic  #101                // Method org/apache/hadoop/hbase/ExtendedCellBuilderFactory.create:(Lorg/apache/hadoop/hbase/CellBuilderType;)Lorg/apache/hadoop/hbase/ExtendedCellBuilder;
      55: astore        6
      57: aload_2
      58: invokeinterface #57,  1           // InterfaceMethod java/util/List.iterator:()Ljava/util/Iterator;
      63: astore        7
      65: aload         7
      67: invokeinterface #35,  1           // InterfaceMethod java/util/Iterator.hasNext:()Z
      72: ifeq          272
      75: aload         7
      77: invokeinterface #36,  1           // InterfaceMethod java/util/Iterator.next:()Ljava/lang/Object;
      82: checkcast     #102                // class "[B"
      85: astore        8
      87: aload         8
      89: invokestatic  #103                // Method org/apache/hadoop/hbase/util/Bytes.toString:([B)Ljava/lang/String;
      92: astore        9
      94: aload_0
      95: getfield      #13                 // Field labelsCache:Lorg/apache/hadoop/hbase/security/visibility/VisibilityLabelsCache;
      98: aload         9
     100: invokevirtual #104                // Method org/apache/hadoop/hbase/security/visibility/VisibilityLabelsCache.getLabelOrdinal:(Ljava/lang/String;)I
     103: istore        10
     105: iload         10
     107: ifne          159
     110: aload_3
     111: iload         5
     113: new           #99                 // class org/apache/hadoop/hbase/regionserver/OperationStatus
     116: dup
     117: getstatic     #105                // Field org/apache/hadoop/hbase/HConstants$OperationStatusCode.FAILURE:Lorg/apache/hadoop/hbase/HConstants$OperationStatusCode;
     120: new           #134                // class org/apache/hadoop/hbase/security/visibility/InvalidLabelException
     123: dup
     124: new           #107                // class java/lang/StringBuilder
     127: dup
     128: invokespecial #108                // Method java/lang/StringBuilder."<init>":()V
     131: ldc           #109                // String Label '
     133: invokevirtual #110                // Method java/lang/StringBuilder.append:(Ljava/lang/String;)Ljava/lang/StringBuilder;
     136: aload         9
     138: invokevirtual #110                // Method java/lang/StringBuilder.append:(Ljava/lang/String;)Ljava/lang/StringBuilder;
     141: ldc           #135                // String ' doesn't exists
     143: invokevirtual #110                // Method java/lang/StringBuilder.append:(Ljava/lang/String;)Ljava/lang/StringBuilder;
     146: invokevirtual #112                // Method java/lang/StringBuilder.toString:()Ljava/lang/String;
     149: invokespecial #136                // Method org/apache/hadoop/hbase/security/visibility/InvalidLabelException."<init>":(Ljava/lang/String;)V
     152: invokespecial #114                // Method org/apache/hadoop/hbase/regionserver/OperationStatus."<init>":(Lorg/apache/hadoop/hbase/HConstants$OperationStatusCode;Ljava/lang/Exception;)V
     155: aastore
     156: goto          266
     159: iload         10
     161: invokestatic  #77                 // Method org/apache/hadoop/hbase/util/Bytes.toBytes:(I)[B
     164: astore        11
     166: new           #78                 // class org/apache/hadoop/hbase/client/Put
     169: dup
     170: aload         11
     172: invokespecial #79                 // Method org/apache/hadoop/hbase/client/Put."<init>":([B)V
     175: astore        12
     177: aload         12
     179: aload         6
     181: invokeinterface #116,  1          // InterfaceMethod org/apache/hadoop/hbase/ExtendedCellBuilder.clear:()Lorg/apache/hadoop/hbase/ExtendedCellBuilder;
     186: aload         11
     188: invokeinterface #117,  2          // InterfaceMethod org/apache/hadoop/hbase/ExtendedCellBuilder.setRow:([B)Lorg/apache/hadoop/hbase/ExtendedCellBuilder;
     193: getstatic     #83                 // Field org/apache/hadoop/hbase/security/visibility/VisibilityConstants.LABELS_TABLE_FAMILY:[B
     196: invokeinterface #118,  2          // InterfaceMethod org/apache/hadoop/hbase/ExtendedCellBuilder.setFamily:([B)Lorg/apache/hadoop/hbase/ExtendedCellBuilder;
     201: aload_1
     202: invokeinterface #119,  2          // InterfaceMethod org/apache/hadoop/hbase/ExtendedCellBuilder.setQualifier:([B)Lorg/apache/hadoop/hbase/ExtendedCellBuilder;
     207: aload         12
     209: invokevirtual #86                 // Method org/apache/hadoop/hbase/client/Put.getTimestamp:()J
     212: invokeinterface #120,  3          // InterfaceMethod org/apache/hadoop/hbase/ExtendedCellBuilder.setTimestamp:(J)Lorg/apache/hadoop/hbase/ExtendedCellBuilder;
     217: getstatic     #88                 // Field org/apache/hadoop/hbase/Cell$Type.Put:Lorg/apache/hadoop/hbase/Cell$Type;
     220: invokeinterface #121,  2          // InterfaceMethod org/apache/hadoop/hbase/ExtendedCellBuilder.setType:(Lorg/apache/hadoop/hbase/Cell$Type;)Lorg/apache/hadoop/hbase/ExtendedCellBuilder;
     225: getstatic     #137                // Field DUMMY_VALUE:[B
     228: invokeinterface #122,  2          // InterfaceMethod org/apache/hadoop/hbase/ExtendedCellBuilder.setValue:([B)Lorg/apache/hadoop/hbase/ExtendedCellBuilder;
     233: getstatic     #123                // Field LABELS_TABLE_TAGS:[Lorg/apache/hadoop/hbase/Tag;
     236: invokestatic  #124                // Method java/util/Arrays.asList:([Ljava/lang/Object;)Ljava/util/List;
     239: invokestatic  #125                // Method org/apache/hadoop/hbase/TagUtil.fromList:(Ljava/util/List;)[B
     242: invokeinterface #126,  2          // InterfaceMethod org/apache/hadoop/hbase/ExtendedCellBuilder.setTags:([B)Lorg/apache/hadoop/hbase/ExtendedCellBuilder;
     247: invokeinterface #127,  1          // InterfaceMethod org/apache/hadoop/hbase/ExtendedCellBuilder.build:()Lorg/apache/hadoop/hbase/ExtendedCell;
     252: invokevirtual #93                 // Method org/apache/hadoop/hbase/client/Put.add:(Lorg/apache/hadoop/hbase/Cell;)Lorg/apache/hadoop/hbase/client/Put;
     255: pop
     256: aload         4
     258: aload         12
     260: invokeinterface #53,  2           // InterfaceMethod java/util/List.add:(Ljava/lang/Object;)Z
     265: pop
     266: iinc          5, 1
     269: goto          65
     272: aload_0
     273: aload         4
     275: aload_3
     276: invokespecial #132                // Method mutateLabelsRegion:(Ljava/util/List;[Lorg/apache/hadoop/hbase/regionserver/OperationStatus;)Z
     279: ifeq          287
     282: aload_0
     283: iconst_0
     284: invokevirtual #133                // Method updateZk:(Z)V
     287: aload_3
     288: areturn

  public org.apache.hadoop.hbase.regionserver.OperationStatus[] clearAuths(byte[], java.util.List<byte[]>) throws java.io.IOException;
    Code:
       0: getstatic     #95                 // Field $assertionsDisabled:Z
       3: ifne          21
       6: aload_0
       7: getfield      #25                 // Field labelsRegion:Lorg/apache/hadoop/hbase/regionserver/Region;
      10: ifnonnull     21
      13: new           #96                 // class java/lang/AssertionError
      16: dup
      17: invokespecial #97                 // Method java/lang/AssertionError."<init>":()V
      20: athrow
      21: aload_2
      22: invokeinterface #98,  1           // InterfaceMethod java/util/List.size:()I
      27: anewarray     #99                 // class org/apache/hadoop/hbase/regionserver/OperationStatus
      30: astore_3
      31: aload_1
      32: invokestatic  #103                // Method org/apache/hadoop/hbase/util/Bytes.toString:([B)Ljava/lang/String;
      35: invokestatic  #138                // Method org/apache/hadoop/hbase/AuthUtil.isGroupPrincipal:(Ljava/lang/String;)Z
      38: ifeq          69
      41: aload_1
      42: invokestatic  #103                // Method org/apache/hadoop/hbase/util/Bytes.toString:([B)Ljava/lang/String;
      45: invokestatic  #139                // Method org/apache/hadoop/hbase/AuthUtil.getGroupName:(Ljava/lang/String;)Ljava/lang/String;
      48: astore        5
      50: aload_0
      51: iconst_1
      52: anewarray     #140                // class java/lang/String
      55: dup
      56: iconst_0
      57: aload         5
      59: aastore
      60: iconst_1
      61: invokevirtual #141                // Method getGroupAuths:([Ljava/lang/String;Z)Ljava/util/List;
      64: astore        4
      66: goto          77
      69: aload_0
      70: aload_1
      71: iconst_1
      72: invokevirtual #142                // Method getUserAuths:([BZ)Ljava/util/List;
      75: astore        4
      77: new           #49                 // class java/util/ArrayList
      80: dup
      81: aload_2
      82: invokeinterface #98,  1           // InterfaceMethod java/util/List.size:()I
      87: invokespecial #100                // Method java/util/ArrayList."<init>":(I)V
      90: astore        5
      92: iconst_0
      93: istore        6
      95: aload_2
      96: invokeinterface #57,  1           // InterfaceMethod java/util/List.iterator:()Ljava/util/Iterator;
     101: astore        7
     103: aload         7
     105: invokeinterface #35,  1           // InterfaceMethod java/util/Iterator.hasNext:()Z
     110: ifeq          270
     113: aload         7
     115: invokeinterface #36,  1           // InterfaceMethod java/util/Iterator.next:()Ljava/lang/Object;
     120: checkcast     #102                // class "[B"
     123: astore        8
     125: aload         8
     127: invokestatic  #103                // Method org/apache/hadoop/hbase/util/Bytes.toString:([B)Ljava/lang/String;
     130: astore        9
     132: aload         4
     134: aload         9
     136: invokeinterface #143,  2          // InterfaceMethod java/util/List.contains:(Ljava/lang/Object;)Z
     141: ifeq          211
     144: aload_0
     145: getfield      #13                 // Field labelsCache:Lorg/apache/hadoop/hbase/security/visibility/VisibilityLabelsCache;
     148: aload         9
     150: invokevirtual #104                // Method org/apache/hadoop/hbase/security/visibility/VisibilityLabelsCache.getLabelOrdinal:(Ljava/lang/String;)I
     153: istore        10
     155: getstatic     #95                 // Field $assertionsDisabled:Z
     158: ifne          174
     161: iload         10
     163: ifgt          174
     166: new           #96                 // class java/lang/AssertionError
     169: dup
     170: invokespecial #97                 // Method java/lang/AssertionError."<init>":()V
     173: athrow
     174: new           #144                // class org/apache/hadoop/hbase/client/Delete
     177: dup
     178: iload         10
     180: invokestatic  #77                 // Method org/apache/hadoop/hbase/util/Bytes.toBytes:(I)[B
     183: invokespecial #145                // Method org/apache/hadoop/hbase/client/Delete."<init>":([B)V
     186: astore        11
     188: aload         11
     190: getstatic     #83                 // Field org/apache/hadoop/hbase/security/visibility/VisibilityConstants.LABELS_TABLE_FAMILY:[B
     193: aload_1
     194: invokevirtual #146                // Method org/apache/hadoop/hbase/client/Delete.addColumns:([B[B)Lorg/apache/hadoop/hbase/client/Delete;
     197: pop
     198: aload         5
     200: aload         11
     202: invokeinterface #53,  2           // InterfaceMethod java/util/List.add:(Ljava/lang/Object;)Z
     207: pop
     208: goto          264
     211: aload_3
     212: iload         6
     214: new           #99                 // class org/apache/hadoop/hbase/regionserver/OperationStatus
     217: dup
     218: getstatic     #105                // Field org/apache/hadoop/hbase/HConstants$OperationStatusCode.FAILURE:Lorg/apache/hadoop/hbase/HConstants$OperationStatusCode;
     221: new           #134                // class org/apache/hadoop/hbase/security/visibility/InvalidLabelException
     224: dup
     225: new           #107                // class java/lang/StringBuilder
     228: dup
     229: invokespecial #108                // Method java/lang/StringBuilder."<init>":()V
     232: ldc           #109                // String Label '
     234: invokevirtual #110                // Method java/lang/StringBuilder.append:(Ljava/lang/String;)Ljava/lang/StringBuilder;
     237: aload         9
     239: invokevirtual #110                // Method java/lang/StringBuilder.append:(Ljava/lang/String;)Ljava/lang/StringBuilder;
     242: ldc           #147                // String ' is not set for the user
     244: invokevirtual #110                // Method java/lang/StringBuilder.append:(Ljava/lang/String;)Ljava/lang/StringBuilder;
     247: aload_1
     248: invokestatic  #103                // Method org/apache/hadoop/hbase/util/Bytes.toString:([B)Ljava/lang/String;
     251: invokevirtual #110                // Method java/lang/StringBuilder.append:(Ljava/lang/String;)Ljava/lang/StringBuilder;
     254: invokevirtual #112                // Method java/lang/StringBuilder.toString:()Ljava/lang/String;
     257: invokespecial #136                // Method org/apache/hadoop/hbase/security/visibility/InvalidLabelException."<init>":(Ljava/lang/String;)V
     260: invokespecial #114                // Method org/apache/hadoop/hbase/regionserver/OperationStatus."<init>":(Lorg/apache/hadoop/hbase/HConstants$OperationStatusCode;Ljava/lang/Exception;)V
     263: aastore
     264: iinc          6, 1
     267: goto          103
     270: aload_0
     271: aload         5
     273: aload_3
     274: invokespecial #132                // Method mutateLabelsRegion:(Ljava/util/List;[Lorg/apache/hadoop/hbase/regionserver/OperationStatus;)Z
     277: ifeq          285
     280: aload_0
     281: iconst_0
     282: invokevirtual #133                // Method updateZk:(Z)V
     285: aload_3
     286: areturn

  public java.util.List<java.lang.String> getUserAuths(byte[], boolean) throws java.io.IOException;
    Code:
       0: getstatic     #95                 // Field $assertionsDisabled:Z
       3: ifne          25
       6: aload_0
       7: getfield      #25                 // Field labelsRegion:Lorg/apache/hadoop/hbase/regionserver/Region;
      10: ifnonnull     25
      13: iload_2
      14: ifne          25
      17: new           #96                 // class java/lang/AssertionError
      20: dup
      21: invokespecial #97                 // Method java/lang/AssertionError."<init>":()V
      24: athrow
      25: iload_2
      26: ifne          36
      29: aload_0
      30: getfield      #25                 // Field labelsRegion:Lorg/apache/hadoop/hbase/regionserver/Region;
      33: ifnonnull     48
      36: aload_0
      37: getfield      #13                 // Field labelsCache:Lorg/apache/hadoop/hbase/security/visibility/VisibilityLabelsCache;
      40: aload_1
      41: invokestatic  #103                // Method org/apache/hadoop/hbase/util/Bytes.toString:([B)Ljava/lang/String;
      44: invokevirtual #154                // Method org/apache/hadoop/hbase/security/visibility/VisibilityLabelsCache.getUserAuths:(Ljava/lang/String;)Ljava/util/List;
      47: areturn
      48: new           #46                 // class org/apache/hadoop/hbase/client/Scan
      51: dup
      52: invokespecial #47                 // Method org/apache/hadoop/hbase/client/Scan."<init>":()V
      55: astore_3
      56: aload_1
      57: ifnull        74
      60: aload_1
      61: arraylength
      62: ifle          74
      65: aload_3
      66: getstatic     #83                 // Field org/apache/hadoop/hbase/security/visibility/VisibilityConstants.LABELS_TABLE_FAMILY:[B
      69: aload_1
      70: invokevirtual #155                // Method org/apache/hadoop/hbase/client/Scan.addColumn:([B[B)Lorg/apache/hadoop/hbase/client/Scan;
      73: pop
      74: aload_0
      75: getfield      #25                 // Field labelsRegion:Lorg/apache/hadoop/hbase/regionserver/Region;
      78: new           #156                // class org/apache/hadoop/hbase/security/visibility/Authorizations
      81: dup
      82: iconst_1
      83: anewarray     #140                // class java/lang/String
      86: dup
      87: iconst_0
      88: ldc           #75                 // String system
      90: aastore
      91: invokespecial #157                // Method org/apache/hadoop/hbase/security/visibility/Authorizations."<init>":([Ljava/lang/String;)V
      94: invokestatic  #158                // Method org/apache/hadoop/hbase/security/visibility/VisibilityUtils.createVisibilityLabelFilter:(Lorg/apache/hadoop/hbase/regionserver/Region;Lorg/apache/hadoop/hbase/security/visibility/Authorizations;)Lorg/apache/hadoop/hbase/filter/Filter;
      97: astore        4
      99: aload_3
     100: aload         4
     102: invokevirtual #159                // Method org/apache/hadoop/hbase/client/Scan.setFilter:(Lorg/apache/hadoop/hbase/filter/Filter;)Lorg/apache/hadoop/hbase/client/Scan;
     105: pop
     106: new           #49                 // class java/util/ArrayList
     109: dup
     110: invokespecial #50                 // Method java/util/ArrayList."<init>":()V
     113: astore        5
     115: aload_0
     116: getfield      #25                 // Field labelsRegion:Lorg/apache/hadoop/hbase/regionserver/Region;
     119: aload_3
     120: invokeinterface #48,  2           // InterfaceMethod org/apache/hadoop/hbase/regionserver/Region.getScanner:(Lorg/apache/hadoop/hbase/client/Scan;)Lorg/apache/hadoop/hbase/regionserver/RegionScanner;
     125: astore        6
     127: new           #49                 // class java/util/ArrayList
     130: dup
     131: iconst_1
     132: invokespecial #100                // Method java/util/ArrayList."<init>":(I)V
     135: astore        7
     137: aload         6
     139: aload         7
     141: invokeinterface #51,  2           // InterfaceMethod org/apache/hadoop/hbase/regionserver/RegionScanner.next:(Ljava/util/List;)Z
     146: pop
     147: aload         7
     149: invokeinterface #52,  1           // InterfaceMethod java/util/List.isEmpty:()Z
     154: ifeq          160
     157: goto          214
     160: aload         7
     162: iconst_0
     163: invokeinterface #160,  2          // InterfaceMethod java/util/List.get:(I)Ljava/lang/Object;
     168: checkcast     #59                 // class org/apache/hadoop/hbase/Cell
     171: astore        8
     173: aload         8
     175: invokestatic  #66                 // Method org/apache/hadoop/hbase/PrivateCellUtil.getRowAsInt:(Lorg/apache/hadoop/hbase/Cell;)I
     178: istore        9
     180: aload_0
     181: getfield      #13                 // Field labelsCache:Lorg/apache/hadoop/hbase/security/visibility/VisibilityLabelsCache;
     184: iload         9
     186: invokevirtual #161                // Method org/apache/hadoop/hbase/security/visibility/VisibilityLabelsCache.getLabel:(I)Ljava/lang/String;
     189: astore        10
     191: aload         10
     193: ifnull        204
     196: aload         5
     198: aload         10
     200: invokevirtual #162                // Method java/util/ArrayList.add:(Ljava/lang/Object;)Z
     203: pop
     204: aload         7
     206: invokeinterface #163,  1          // InterfaceMethod java/util/List.clear:()V
     211: goto          137
     214: aload         6
     216: invokeinterface #54,  1           // InterfaceMethod org/apache/hadoop/hbase/regionserver/RegionScanner.close:()V
     221: goto          236
     224: astore        11
     226: aload         6
     228: invokeinterface #54,  1           // InterfaceMethod org/apache/hadoop/hbase/regionserver/RegionScanner.close:()V
     233: aload         11
     235: athrow
     236: aload         5
     238: areturn
    Exception table:
       from    to  target type
         127   214   224   any
         224   226   224   any

  public java.util.List<java.lang.String> getGroupAuths(java.lang.String[], boolean) throws java.io.IOException;
    Code:
       0: getstatic     #95                 // Field $assertionsDisabled:Z
       3: ifne          25
       6: aload_0
       7: getfield      #25                 // Field labelsRegion:Lorg/apache/hadoop/hbase/regionserver/Region;
      10: ifnonnull     25
      13: iload_2
      14: ifne          25
      17: new           #96                 // class java/lang/AssertionError
      20: dup
      21: invokespecial #97                 // Method java/lang/AssertionError."<init>":()V
      24: athrow
      25: iload_2
      26: ifne          36
      29: aload_0
      30: getfield      #25                 // Field labelsRegion:Lorg/apache/hadoop/hbase/regionserver/Region;
      33: ifnonnull     45
      36: aload_0
      37: getfield      #13                 // Field labelsCache:Lorg/apache/hadoop/hbase/security/visibility/VisibilityLabelsCache;
      40: aload_1
      41: invokevirtual #164                // Method org/apache/hadoop/hbase/security/visibility/VisibilityLabelsCache.getGroupAuths:([Ljava/lang/String;)Ljava/util/List;
      44: areturn
      45: new           #46                 // class org/apache/hadoop/hbase/client/Scan
      48: dup
      49: invokespecial #47                 // Method org/apache/hadoop/hbase/client/Scan."<init>":()V
      52: astore_3
      53: aload_1
      54: ifnull        109
      57: aload_1
      58: arraylength
      59: ifle          109
      62: aload_1
      63: astore        4
      65: aload         4
      67: arraylength
      68: istore        5
      70: iconst_0
      71: istore        6
      73: iload         6
      75: iload         5
      77: if_icmpge     109
      80: aload         4
      82: iload         6
      84: aaload
      85: astore        7
      87: aload_3
      88: getstatic     #83                 // Field org/apache/hadoop/hbase/security/visibility/VisibilityConstants.LABELS_TABLE_FAMILY:[B
      91: aload         7
      93: invokestatic  #165                // Method org/apache/hadoop/hbase/AuthUtil.toGroupEntry:(Ljava/lang/String;)Ljava/lang/String;
      96: invokestatic  #90                 // Method org/apache/hadoop/hbase/util/Bytes.toBytes:(Ljava/lang/String;)[B
      99: invokevirtual #155                // Method org/apache/hadoop/hbase/client/Scan.addColumn:([B[B)Lorg/apache/hadoop/hbase/client/Scan;
     102: pop
     103: iinc          6, 1
     106: goto          73
     109: aload_0
     110: getfield      #25                 // Field labelsRegion:Lorg/apache/hadoop/hbase/regionserver/Region;
     113: new           #156                // class org/apache/hadoop/hbase/security/visibility/Authorizations
     116: dup
     117: iconst_1
     118: anewarray     #140                // class java/lang/String
     121: dup
     122: iconst_0
     123: ldc           #75                 // String system
     125: aastore
     126: invokespecial #157                // Method org/apache/hadoop/hbase/security/visibility/Authorizations."<init>":([Ljava/lang/String;)V
     129: invokestatic  #158                // Method org/apache/hadoop/hbase/security/visibility/VisibilityUtils.createVisibilityLabelFilter:(Lorg/apache/hadoop/hbase/regionserver/Region;Lorg/apache/hadoop/hbase/security/visibility/Authorizations;)Lorg/apache/hadoop/hbase/filter/Filter;
     132: astore        4
     134: aload_3
     135: aload         4
     137: invokevirtual #159                // Method org/apache/hadoop/hbase/client/Scan.setFilter:(Lorg/apache/hadoop/hbase/filter/Filter;)Lorg/apache/hadoop/hbase/client/Scan;
     140: pop
     141: new           #166                // class java/util/HashSet
     144: dup
     145: invokespecial #167                // Method java/util/HashSet."<init>":()V
     148: astore        5
     150: aload_0
     151: getfield      #25                 // Field labelsRegion:Lorg/apache/hadoop/hbase/regionserver/Region;
     154: aload_3
     155: invokeinterface #48,  2           // InterfaceMethod org/apache/hadoop/hbase/regionserver/Region.getScanner:(Lorg/apache/hadoop/hbase/client/Scan;)Lorg/apache/hadoop/hbase/regionserver/RegionScanner;
     160: astore        6
     162: new           #49                 // class java/util/ArrayList
     165: dup
     166: iconst_1
     167: invokespecial #100                // Method java/util/ArrayList."<init>":(I)V
     170: astore        7
     172: aload         6
     174: aload         7
     176: invokeinterface #51,  2           // InterfaceMethod org/apache/hadoop/hbase/regionserver/RegionScanner.next:(Ljava/util/List;)Z
     181: pop
     182: aload         7
     184: invokeinterface #52,  1           // InterfaceMethod java/util/List.isEmpty:()Z
     189: ifeq          195
     192: goto          251
     195: aload         7
     197: iconst_0
     198: invokeinterface #160,  2          // InterfaceMethod java/util/List.get:(I)Ljava/lang/Object;
     203: checkcast     #59                 // class org/apache/hadoop/hbase/Cell
     206: astore        8
     208: aload         8
     210: invokestatic  #66                 // Method org/apache/hadoop/hbase/PrivateCellUtil.getRowAsInt:(Lorg/apache/hadoop/hbase/Cell;)I
     213: istore        9
     215: aload_0
     216: getfield      #13                 // Field labelsCache:Lorg/apache/hadoop/hbase/security/visibility/VisibilityLabelsCache;
     219: iload         9
     221: invokevirtual #161                // Method org/apache/hadoop/hbase/security/visibility/VisibilityLabelsCache.getLabel:(I)Ljava/lang/String;
     224: astore        10
     226: aload         10
     228: ifnull        241
     231: aload         5
     233: aload         10
     235: invokeinterface #168,  2          // InterfaceMethod java/util/Set.add:(Ljava/lang/Object;)Z
     240: pop
     241: aload         7
     243: invokeinterface #163,  1          // InterfaceMethod java/util/List.clear:()V
     248: goto          172
     251: aload         6
     253: invokeinterface #54,  1           // InterfaceMethod org/apache/hadoop/hbase/regionserver/RegionScanner.close:()V
     258: goto          273
     261: astore        11
     263: aload         6
     265: invokeinterface #54,  1           // InterfaceMethod org/apache/hadoop/hbase/regionserver/RegionScanner.close:()V
     270: aload         11
     272: athrow
     273: new           #49                 // class java/util/ArrayList
     276: dup
     277: aload         5
     279: invokespecial #169                // Method java/util/ArrayList."<init>":(Ljava/util/Collection;)V
     282: areturn
    Exception table:
       from    to  target type
         162   251   261   any
         261   263   261   any

  public java.util.List<java.lang.String> listLabels(java.lang.String) throws java.io.IOException;
    Code:
       0: getstatic     #95                 // Field $assertionsDisabled:Z
       3: ifne          21
       6: aload_0
       7: getfield      #25                 // Field labelsRegion:Lorg/apache/hadoop/hbase/regionserver/Region;
      10: ifnonnull     21
      13: new           #96                 // class java/lang/AssertionError
      16: dup
      17: invokespecial #97                 // Method java/lang/AssertionError."<init>":()V
      20: athrow
      21: aload_0
      22: aload_0
      23: invokevirtual #26                 // Method getExistingLabelsWithAuths:()Ljava/util/List;
      26: invokevirtual #27                 // Method extractLabelsAndAuths:(Ljava/util/List;)Lorg/apache/hadoop/hbase/util/Pair;
      29: astore_2
      30: aload_2
      31: invokevirtual #28                 // Method org/apache/hadoop/hbase/util/Pair.getFirst:()Ljava/lang/Object;
      34: checkcast     #29                 // class java/util/Map
      37: astore_3
      38: aload_3
      39: ldc           #75                 // String system
      41: invokeinterface #170,  2          // InterfaceMethod java/util/Map.remove:(Ljava/lang/Object;)Ljava/lang/Object;
      46: pop
      47: aload_1
      48: ifnull        128
      51: aload_1
      52: invokestatic  #171                // Method java/util/regex/Pattern.compile:(Ljava/lang/String;)Ljava/util/regex/Pattern;
      55: astore        4
      57: new           #49                 // class java/util/ArrayList
      60: dup
      61: invokespecial #50                 // Method java/util/ArrayList."<init>":()V
      64: astore        5
      66: aload_3
      67: invokeinterface #172,  1          // InterfaceMethod java/util/Map.keySet:()Ljava/util/Set;
      72: invokeinterface #173,  1          // InterfaceMethod java/util/Set.iterator:()Ljava/util/Iterator;
      77: astore        6
      79: aload         6
      81: invokeinterface #35,  1           // InterfaceMethod java/util/Iterator.hasNext:()Z
      86: ifeq          125
      89: aload         6
      91: invokeinterface #36,  1           // InterfaceMethod java/util/Iterator.next:()Ljava/lang/Object;
      96: checkcast     #140                // class java/lang/String
      99: astore        7
     101: aload         4
     103: aload         7
     105: invokevirtual #174                // Method java/util/regex/Pattern.matcher:(Ljava/lang/CharSequence;)Ljava/util/regex/Matcher;
     108: invokevirtual #175                // Method java/util/regex/Matcher.matches:()Z
     111: ifeq          122
     114: aload         5
     116: aload         7
     118: invokevirtual #162                // Method java/util/ArrayList.add:(Ljava/lang/Object;)Z
     121: pop
     122: goto          79
     125: aload         5
     127: areturn
     128: new           #49                 // class java/util/ArrayList
     131: dup
     132: aload_3
     133: invokeinterface #172,  1          // InterfaceMethod java/util/Map.keySet:()Ljava/util/Set;
     138: invokespecial #169                // Method java/util/ArrayList."<init>":(Ljava/util/Collection;)V
     141: areturn

  public java.util.List<org.apache.hadoop.hbase.Tag> createVisibilityExpTags(java.lang.String, boolean, boolean) throws java.io.IOException;
    Code:
       0: new           #166                // class java/util/HashSet
       3: dup
       4: invokespecial #167                // Method java/util/HashSet."<init>":()V
       7: astore        4
       9: iload_3
      10: ifeq          58
      13: invokestatic  #176                // Method org/apache/hadoop/hbase/security/visibility/VisibilityUtils.getActiveUser:()Lorg/apache/hadoop/hbase/security/User;
      16: astore        5
      18: aload         4
      20: aload_0
      21: getfield      #13                 // Field labelsCache:Lorg/apache/hadoop/hbase/security/visibility/VisibilityLabelsCache;
      24: aload         5
      26: invokevirtual #177                // Method org/apache/hadoop/hbase/security/User.getShortName:()Ljava/lang/String;
      29: invokevirtual #178                // Method org/apache/hadoop/hbase/security/visibility/VisibilityLabelsCache.getUserAuthsAsOrdinals:(Ljava/lang/String;)Ljava/util/Set;
      32: invokeinterface #179,  2          // InterfaceMethod java/util/Set.addAll:(Ljava/util/Collection;)Z
      37: pop
      38: aload         4
      40: aload_0
      41: getfield      #13                 // Field labelsCache:Lorg/apache/hadoop/hbase/security/visibility/VisibilityLabelsCache;
      44: aload         5
      46: invokevirtual #180                // Method org/apache/hadoop/hbase/security/User.getGroupNames:()[Ljava/lang/String;
      49: invokevirtual #181                // Method org/apache/hadoop/hbase/security/visibility/VisibilityLabelsCache.getGroupAuthsAsOrdinals:([Ljava/lang/String;)Ljava/util/Set;
      52: invokeinterface #179,  2          // InterfaceMethod java/util/Set.addAll:(Ljava/util/Collection;)Z
      57: pop
      58: aload_1
      59: iload_2
      60: iload_3
      61: aload         4
      63: aload_0
      64: getfield      #13                 // Field labelsCache:Lorg/apache/hadoop/hbase/security/visibility/VisibilityLabelsCache;
      67: invokestatic  #182                // Method org/apache/hadoop/hbase/security/visibility/VisibilityUtils.createVisibilityExpTags:(Ljava/lang/String;ZZLjava/util/Set;Lorg/apache/hadoop/hbase/security/visibility/VisibilityLabelOrdinalProvider;)Ljava/util/List;
      70: areturn

  protected void updateZk(boolean) throws java.io.IOException;
    Code:
       0: aload_0
       1: aload_0
       2: invokevirtual #26                 // Method getExistingLabelsWithAuths:()Ljava/util/List;
       5: invokevirtual #27                 // Method extractLabelsAndAuths:(Ljava/util/List;)Lorg/apache/hadoop/hbase/util/Pair;
       8: astore_2
       9: aload_2
      10: invokevirtual #28                 // Method org/apache/hadoop/hbase/util/Pair.getFirst:()Ljava/lang/Object;
      13: checkcast     #29                 // class java/util/Map
      16: astore_3
      17: aload_2
      18: invokevirtual #30                 // Method org/apache/hadoop/hbase/util/Pair.getSecond:()Ljava/lang/Object;
      21: checkcast     #29                 // class java/util/Map
      24: astore        4
      26: iload_1
      27: ifeq          49
      30: aload_3
      31: invokestatic  #41                 // Method org/apache/hadoop/hbase/security/visibility/VisibilityUtils.getDataToWriteToZooKeeper:(Ljava/util/Map;)[B
      34: astore        5
      36: aload_0
      37: getfield      #13                 // Field labelsCache:Lorg/apache/hadoop/hbase/security/visibility/VisibilityLabelsCache;
      40: aload         5
      42: iconst_1
      43: invokevirtual #42                 // Method org/apache/hadoop/hbase/security/visibility/VisibilityLabelsCache.writeToZookeeper:([BZ)V
      46: goto          66
      49: aload         4
      51: invokestatic  #44                 // Method org/apache/hadoop/hbase/security/visibility/VisibilityUtils.getUserAuthsDataToWriteToZooKeeper:(Ljava/util/Map;)[B
      54: astore        5
      56: aload_0
      57: getfield      #13                 // Field labelsCache:Lorg/apache/hadoop/hbase/security/visibility/VisibilityLabelsCache;
      60: aload         5
      62: iconst_0
      63: invokevirtual #42                 // Method org/apache/hadoop/hbase/security/visibility/VisibilityLabelsCache.writeToZookeeper:([BZ)V
      66: return

  public org.apache.hadoop.hbase.security.visibility.VisibilityExpEvaluator getVisibilityExpEvaluator(org.apache.hadoop.hbase.security.visibility.Authorizations) throws java.io.IOException;
    Code:
       0: aload_0
       1: invokevirtual #183                // Method isReadFromSystemAuthUser:()Z
       4: ifeq          16
       7: new           #184                // class org/apache/hadoop/hbase/security/visibility/DefaultVisibilityLabelServiceImpl$1
      10: dup
      11: aload_0
      12: invokespecial #185                // Method org/apache/hadoop/hbase/security/visibility/DefaultVisibilityLabelServiceImpl$1."<init>":(Lorg/apache/hadoop/hbase/security/visibility/DefaultVisibilityLabelServiceImpl;)V
      15: areturn
      16: aconst_null
      17: astore_2
      18: aload_0
      19: getfield      #19                 // Field scanLabelGenerators:Ljava/util/List;
      22: invokeinterface #57,  1           // InterfaceMethod java/util/List.iterator:()Ljava/util/Iterator;
      27: astore_3
      28: aload_3
      29: invokeinterface #35,  1           // InterfaceMethod java/util/Iterator.hasNext:()Z
      34: ifeq          118
      37: aload_3
      38: invokeinterface #36,  1           // InterfaceMethod java/util/Iterator.next:()Ljava/lang/Object;
      43: checkcast     #186                // class org/apache/hadoop/hbase/security/visibility/ScanLabelGenerator
      46: astore        4
      48: aload         4
      50: invokestatic  #176                // Method org/apache/hadoop/hbase/security/visibility/VisibilityUtils.getActiveUser:()Lorg/apache/hadoop/hbase/security/User;
      53: aload_1
      54: invokeinterface #187,  3          // InterfaceMethod org/apache/hadoop/hbase/security/visibility/ScanLabelGenerator.getLabels:(Lorg/apache/hadoop/hbase/security/User;Lorg/apache/hadoop/hbase/security/visibility/Authorizations;)Ljava/util/List;
      59: astore_2
      60: aload_2
      61: ifnonnull     74
      64: new           #49                 // class java/util/ArrayList
      67: dup
      68: invokespecial #50                 // Method java/util/ArrayList."<init>":()V
      71: goto          75
      74: aload_2
      75: astore_2
      76: new           #156                // class org/apache/hadoop/hbase/security/visibility/Authorizations
      79: dup
      80: aload_2
      81: invokespecial #188                // Method org/apache/hadoop/hbase/security/visibility/Authorizations."<init>":(Ljava/util/List;)V
      84: astore_1
      85: goto          115
      88: astore        5
      90: getstatic     #15                 // Field LOG:Lorg/slf4j/Logger;
      93: aload         5
      95: invokevirtual #190                // Method java/lang/Throwable.toString:()Ljava/lang/String;
      98: aload         5
     100: invokeinterface #17,  3           // InterfaceMethod org/slf4j/Logger.error:(Ljava/lang/String;Ljava/lang/Throwable;)V
     105: new           #14                 // class java/io/IOException
     108: dup
     109: aload         5
     111: invokespecial #191                // Method java/io/IOException."<init>":(Ljava/lang/Throwable;)V
     114: athrow
     115: goto          28
     118: aload_0
     119: getfield      #13                 // Field labelsCache:Lorg/apache/hadoop/hbase/security/visibility/VisibilityLabelsCache;
     122: invokevirtual #192                // Method org/apache/hadoop/hbase/security/visibility/VisibilityLabelsCache.getLabelsCount:()I
     125: istore_3
     126: new           #193                // class java/util/BitSet
     129: dup
     130: iload_3
     131: iconst_1
     132: iadd
     133: invokespecial #194                // Method java/util/BitSet."<init>":(I)V
     136: astore        4
     138: aload_2
     139: ifnull        198
     142: aload_2
     143: invokeinterface #57,  1           // InterfaceMethod java/util/List.iterator:()Ljava/util/Iterator;
     148: astore        5
     150: aload         5
     152: invokeinterface #35,  1           // InterfaceMethod java/util/Iterator.hasNext:()Z
     157: ifeq          198
     160: aload         5
     162: invokeinterface #36,  1           // InterfaceMethod java/util/Iterator.next:()Ljava/lang/Object;
     167: checkcast     #140                // class java/lang/String
     170: astore        6
     172: aload_0
     173: getfield      #13                 // Field labelsCache:Lorg/apache/hadoop/hbase/security/visibility/VisibilityLabelsCache;
     176: aload         6
     178: invokevirtual #104                // Method org/apache/hadoop/hbase/security/visibility/VisibilityLabelsCache.getLabelOrdinal:(Ljava/lang/String;)I
     181: istore        7
     183: iload         7
     185: ifeq          195
     188: aload         4
     190: iload         7
     192: invokevirtual #195                // Method java/util/BitSet.set:(I)V
     195: goto          150
     198: new           #196                // class org/apache/hadoop/hbase/security/visibility/DefaultVisibilityLabelServiceImpl$2
     201: dup
     202: aload_0
     203: aload         4
     205: invokespecial #197                // Method org/apache/hadoop/hbase/security/visibility/DefaultVisibilityLabelServiceImpl$2."<init>":(Lorg/apache/hadoop/hbase/security/visibility/DefaultVisibilityLabelServiceImpl;Ljava/util/BitSet;)V
     208: areturn
    Exception table:
       from    to  target type
          48    85    88   Class java/lang/Throwable

  protected boolean isReadFromSystemAuthUser() throws java.io.IOException;
    Code:
       0: invokestatic  #176                // Method org/apache/hadoop/hbase/security/visibility/VisibilityUtils.getActiveUser:()Lorg/apache/hadoop/hbase/security/User;
       3: astore_1
       4: aload_0
       5: aload_1
       6: invokevirtual #198                // Method havingSystemAuth:(Lorg/apache/hadoop/hbase/security/User;)Z
       9: ireturn

  public boolean havingSystemAuth(org.apache.hadoop.hbase.security.User) throws java.io.IOException;
    Code:
       0: aload_1
       1: invokestatic  #199                // Method org/apache/hadoop/hbase/security/Superusers.isSuperUser:(Lorg/apache/hadoop/hbase/security/User;)Z
       4: ifeq          9
       7: iconst_1
       8: ireturn
       9: aload_0
      10: aload_1
      11: invokevirtual #177                // Method org/apache/hadoop/hbase/security/User.getShortName:()Ljava/lang/String;
      14: invokestatic  #90                 // Method org/apache/hadoop/hbase/util/Bytes.toBytes:(Ljava/lang/String;)[B
      17: iconst_1
      18: invokevirtual #142                // Method getUserAuths:([BZ)Ljava/util/List;
      21: astore_2
      22: getstatic     #15                 // Field LOG:Lorg/slf4j/Logger;
      25: invokeinterface #200,  1          // InterfaceMethod org/slf4j/Logger.isTraceEnabled:()Z
      30: ifeq          72
      33: getstatic     #15                 // Field LOG:Lorg/slf4j/Logger;
      36: new           #107                // class java/lang/StringBuilder
      39: dup
      40: invokespecial #108                // Method java/lang/StringBuilder."<init>":()V
      43: ldc           #201                // String The auths for user
      45: invokevirtual #110                // Method java/lang/StringBuilder.append:(Ljava/lang/String;)Ljava/lang/StringBuilder;
      48: aload_1
      49: invokevirtual #177                // Method org/apache/hadoop/hbase/security/User.getShortName:()Ljava/lang/String;
      52: invokevirtual #110                // Method java/lang/StringBuilder.append:(Ljava/lang/String;)Ljava/lang/StringBuilder;
      55: ldc           #202                // String  are
      57: invokevirtual #110                // Method java/lang/StringBuilder.append:(Ljava/lang/String;)Ljava/lang/StringBuilder;
      60: aload_2
      61: invokevirtual #203                // Method java/lang/StringBuilder.append:(Ljava/lang/Object;)Ljava/lang/StringBuilder;
      64: invokevirtual #112                // Method java/lang/StringBuilder.toString:()Ljava/lang/String;
      67: invokeinterface #204,  2          // InterfaceMethod org/slf4j/Logger.trace:(Ljava/lang/String;)V
      72: aload_2
      73: ldc           #75                 // String system
      75: invokeinterface #143,  2          // InterfaceMethod java/util/List.contains:(Ljava/lang/Object;)Z
      80: ifeq          85
      83: iconst_1
      84: ireturn
      85: aload_0
      86: aload_1
      87: invokevirtual #180                // Method org/apache/hadoop/hbase/security/User.getGroupNames:()[Ljava/lang/String;
      90: iconst_1
      91: invokevirtual #141                // Method getGroupAuths:([Ljava/lang/String;Z)Ljava/util/List;
      94: astore_2
      95: getstatic     #15                 // Field LOG:Lorg/slf4j/Logger;
      98: invokeinterface #200,  1          // InterfaceMethod org/slf4j/Logger.isTraceEnabled:()Z
     103: ifeq          145
     106: getstatic     #15                 // Field LOG:Lorg/slf4j/Logger;
     109: new           #107                // class java/lang/StringBuilder
     112: dup
     113: invokespecial #108                // Method java/lang/StringBuilder."<init>":()V
     116: ldc           #205                // String The auths for groups of user
     118: invokevirtual #110                // Method java/lang/StringBuilder.append:(Ljava/lang/String;)Ljava/lang/StringBuilder;
     121: aload_1
     122: invokevirtual #177                // Method org/apache/hadoop/hbase/security/User.getShortName:()Ljava/lang/String;
     125: invokevirtual #110                // Method java/lang/StringBuilder.append:(Ljava/lang/String;)Ljava/lang/StringBuilder;
     128: ldc           #202                // String  are
     130: invokevirtual #110                // Method java/lang/StringBuilder.append:(Ljava/lang/String;)Ljava/lang/StringBuilder;
     133: aload_2
     134: invokevirtual #203                // Method java/lang/StringBuilder.append:(Ljava/lang/Object;)Ljava/lang/StringBuilder;
     137: invokevirtual #112                // Method java/lang/StringBuilder.toString:()Ljava/lang/String;
     140: invokeinterface #204,  2          // InterfaceMethod org/slf4j/Logger.trace:(Ljava/lang/String;)V
     145: aload_2
     146: ldc           #75                 // String system
     148: invokeinterface #143,  2          // InterfaceMethod java/util/List.contains:(Ljava/lang/Object;)Z
     153: ireturn

  public boolean matchVisibility(java.util.List<org.apache.hadoop.hbase.Tag>, java.lang.Byte, java.util.List<org.apache.hadoop.hbase.Tag>, java.lang.Byte) throws java.io.IOException;
    Code:
       0: aload_1
       1: invokeinterface #52,  1           // InterfaceMethod java/util/List.isEmpty:()Z
       6: ifeq          20
       9: aload_3
      10: invokeinterface #52,  1           // InterfaceMethod java/util/List.isEmpty:()Z
      15: ifeq          20
      18: iconst_1
      19: ireturn
      20: aload_1
      21: invokeinterface #52,  1           // InterfaceMethod java/util/List.isEmpty:()Z
      26: aload_3
      27: invokeinterface #52,  1           // InterfaceMethod java/util/List.isEmpty:()Z
      32: ixor
      33: ifeq          38
      36: iconst_0
      37: ireturn
      38: aload         4
      40: ifnull        80
      43: aload         4
      45: invokevirtual #206                // Method java/lang/Byte.byteValue:()B
      48: iconst_1
      49: if_icmpne     80
      52: aload_2
      53: ifnull        64
      56: aload_2
      57: invokevirtual #206                // Method java/lang/Byte.byteValue:()B
      60: iconst_1
      61: if_icmpne     80
      64: aload_2
      65: ifnonnull     74
      68: aload_1
      69: aload_3
      70: invokestatic  #207                // Method matchUnSortedVisibilityTags:(Ljava/util/List;Ljava/util/List;)Z
      73: ireturn
      74: aload_1
      75: aload_3
      76: invokestatic  #208                // Method matchOrdinalSortedVisibilityTags:(Ljava/util/List;Ljava/util/List;)Z
      79: ireturn
      80: new           #14                 // class java/io/IOException
      83: dup
      84: new           #107                // class java/lang/StringBuilder
      87: dup
      88: invokespecial #108                // Method java/lang/StringBuilder."<init>":()V
      91: ldc           #209                // String Unexpected tag format passed for comparison, deleteTagsFormat :
      93: invokevirtual #110                // Method java/lang/StringBuilder.append:(Ljava/lang/String;)Ljava/lang/StringBuilder;
      96: aload         4
      98: invokevirtual #203                // Method java/lang/StringBuilder.append:(Ljava/lang/Object;)Ljava/lang/StringBuilder;
     101: ldc           #210                // String , putTagsFormat :
     103: invokevirtual #110                // Method java/lang/StringBuilder.append:(Ljava/lang/String;)Ljava/lang/StringBuilder;
     106: aload_2
     107: invokevirtual #203                // Method java/lang/StringBuilder.append:(Ljava/lang/Object;)Ljava/lang/StringBuilder;
     110: invokevirtual #112                // Method java/lang/StringBuilder.toString:()Ljava/lang/String;
     113: invokespecial #211                // Method java/io/IOException."<init>":(Ljava/lang/String;)V
     116: athrow

  public byte[] encodeVisibilityForReplication(java.util.List<org.apache.hadoop.hbase.Tag>, java.lang.Byte) throws java.io.IOException;
    Code:
       0: aload_1
       1: invokeinterface #98,  1           // InterfaceMethod java/util/List.size:()I
       6: ifle          27
       9: aload_2
      10: ifnull        21
      13: aload_2
      14: invokevirtual #206                // Method java/lang/Byte.byteValue:()B
      17: iconst_1
      18: if_icmpne     27
      21: aload_0
      22: aload_1
      23: invokespecial #223                // Method createModifiedVisExpression:(Ljava/util/List;)[B
      26: areturn
      27: aconst_null
      28: areturn

  static {};
    Code:
       0: ldc           #32                 // class org/apache/hadoop/hbase/security/visibility/DefaultVisibilityLabelServiceImpl
       2: invokevirtual #231                // Method java/lang/Class.desiredAssertionStatus:()Z
       5: ifne          12
       8: iconst_1
       9: goto          13
      12: iconst_0
      13: putstatic     #95                 // Field $assertionsDisabled:Z
      16: ldc           #32                 // class org/apache/hadoop/hbase/security/visibility/DefaultVisibilityLabelServiceImpl
      18: invokestatic  #232                // Method org/slf4j/LoggerFactory.getLogger:(Ljava/lang/Class;)Lorg/slf4j/Logger;
      21: putstatic     #15                 // Field LOG:Lorg/slf4j/Logger;
      24: iconst_1
      25: anewarray     #214                // class org/apache/hadoop/hbase/Tag
      28: putstatic     #123                // Field LABELS_TABLE_TAGS:[Lorg/apache/hadoop/hbase/Tag;
      31: iconst_0
      32: newarray       byte
      34: putstatic     #137                // Field DUMMY_VALUE:[B
      37: new           #233                // class java/io/ByteArrayOutputStream
      40: dup
      41: invokespecial #234                // Method java/io/ByteArrayOutputStream."<init>":()V
      44: astore_0
      45: new           #235                // class java/io/DataOutputStream
      48: dup
      49: aload_0
      50: invokespecial #236                // Method java/io/DataOutputStream."<init>":(Ljava/io/OutputStream;)V
      53: astore_1
      54: aload_1
      55: iconst_1
      56: invokestatic  #237                // Method org/apache/hadoop/hbase/io/util/StreamUtils.writeRawVInt32:(Ljava/io/OutputStream;I)V
      59: goto          63
      62: astore_2
      63: getstatic     #123                // Field LABELS_TABLE_TAGS:[Lorg/apache/hadoop/hbase/Tag;
      66: iconst_0
      67: new           #238                // class org/apache/hadoop/hbase/ArrayBackedTag
      70: dup
      71: iconst_2
      72: aload_0
      73: invokevirtual #239                // Method java/io/ByteArrayOutputStream.toByteArray:()[B
      76: invokespecial #240                // Method org/apache/hadoop/hbase/ArrayBackedTag."<init>":(B[B)V
      79: aastore
      80: return
    Exception table:
       from    to  target type
          54    59    62   Class java/io/IOException
}
