Compiled from "DefaultHeapMemoryTuner.java"
class org.apache.hadoop.hbase.regionserver.DefaultHeapMemoryTuner implements org.apache.hadoop.hbase.regionserver.HeapMemoryTuner {
  public static final java.lang.String MAX_STEP_KEY;

  public static final java.lang.String MIN_STEP_KEY;

  public static final java.lang.String SUFFICIENT_MEMORY_LEVEL_KEY;

  public static final java.lang.String LOOKUP_PERIODS_KEY;

  public static final java.lang.String NUM_PERIODS_TO_IGNORE;

  public static final float DEFAULT_MAX_STEP_VALUE;

  public static final float DEFAULT_MIN_STEP_VALUE;

  public static final float DEFAULT_SUFFICIENT_MEMORY_LEVEL_VALUE;

  public static final int DEFAULT_LOOKUP_PERIODS;

  public static final int DEFAULT_NUM_PERIODS_IGNORED;

  org.apache.hadoop.hbase.regionserver.DefaultHeapMemoryTuner();
    Code:
       0: aload_0
       1: invokespecial #3                  // Method java/lang/Object."<init>":()V
       4: aload_0
       5: ldc           #4                  // class org/apache/hadoop/hbase/regionserver/DefaultHeapMemoryTuner
       7: invokestatic  #5                  // Method org/slf4j/LoggerFactory.getLogger:(Ljava/lang/Class;)Lorg/slf4j/Logger;
      10: putfield      #6                  // Field LOG:Lorg/slf4j/Logger;
      13: aload_0
      14: new           #7                  // class org/apache/hadoop/hbase/regionserver/HeapMemoryManager$TunerResult
      17: dup
      18: iconst_1
      19: invokespecial #8                  // Method org/apache/hadoop/hbase/regionserver/HeapMemoryManager$TunerResult."<init>":(Z)V
      22: putfield      #9                  // Field TUNER_RESULT:Lorg/apache/hadoop/hbase/regionserver/HeapMemoryManager$TunerResult;
      25: aload_0
      26: ldc           #10                 // float 0.5f
      28: putfield      #11                 // Field sufficientMemoryLevel:F
      31: aload_0
      32: ldc           #12                 // float 0.04f
      34: putfield      #13                 // Field maximumStepSize:F
      37: aload_0
      38: ldc           #14                 // float 0.00125f
      40: putfield      #15                 // Field minimumStepSize:F
      43: aload_0
      44: bipush        60
      46: putfield      #16                 // Field tunerLookupPeriods:I
      49: aload_0
      50: bipush        60
      52: putfield      #17                 // Field numPeriodsToIgnore:I
      55: aload_0
      56: iconst_0
      57: putfield      #18                 // Field ignoreInitialPeriods:I
      60: aload_0
      61: ldc           #12                 // float 0.04f
      63: putfield      #19                 // Field step:F
      66: aload_0
      67: getstatic     #20                 // Field org/apache/hadoop/hbase/regionserver/DefaultHeapMemoryTuner$StepDirection.NEUTRAL:Lorg/apache/hadoop/hbase/regionserver/DefaultHeapMemoryTuner$StepDirection;
      70: putfield      #21                 // Field prevTuneDirection:Lorg/apache/hadoop/hbase/regionserver/DefaultHeapMemoryTuner$StepDirection;
      73: aload_0
      74: dconst_0
      75: putfield      #22                 // Field decayingTunerStepSizeSum:D
      78: return

  public org.apache.hadoop.hbase.regionserver.HeapMemoryManager$TunerResult tune(org.apache.hadoop.hbase.regionserver.HeapMemoryManager$TunerContext);
    Code:
       0: aload_1
       1: invokevirtual #23                 // Method org/apache/hadoop/hbase/regionserver/HeapMemoryManager$TunerContext.getCurMemStoreSize:()F
       4: fstore_2
       5: aload_1
       6: invokevirtual #24                 // Method org/apache/hadoop/hbase/regionserver/HeapMemoryManager$TunerContext.getCurBlockCacheSize:()F
       9: fstore_3
      10: aload_0
      11: aload_1
      12: invokespecial #25                 // Method addToRollingStats:(Lorg/apache/hadoop/hbase/regionserver/HeapMemoryManager$TunerContext;)V
      15: aload_0
      16: getfield      #18                 // Field ignoreInitialPeriods:I
      19: aload_0
      20: getfield      #17                 // Field numPeriodsToIgnore:I
      23: if_icmpge     48
      26: aload_0
      27: dup
      28: getfield      #18                 // Field ignoreInitialPeriods:I
      31: iconst_1
      32: iadd
      33: putfield      #18                 // Field ignoreInitialPeriods:I
      36: aload_0
      37: getfield      #26                 // Field rollingStatsForTunerSteps:Lorg/apache/hadoop/hbase/util/RollingStatCalculator;
      40: lconst_0
      41: invokevirtual #27                 // Method org/apache/hadoop/hbase/util/RollingStatCalculator.insertDataValue:(J)V
      44: getstatic     #28                 // Field NO_OP_TUNER_RESULT:Lorg/apache/hadoop/hbase/regionserver/HeapMemoryManager$TunerResult;
      47: areturn
      48: aload_0
      49: aload_1
      50: invokespecial #29                 // Method getTuneDirection:(Lorg/apache/hadoop/hbase/regionserver/HeapMemoryManager$TunerContext;)Lorg/apache/hadoop/hbase/regionserver/DefaultHeapMemoryTuner$StepDirection;
      53: astore        4
      55: aload_1
      56: invokevirtual #30                 // Method org/apache/hadoop/hbase/regionserver/HeapMemoryManager$TunerContext.getBlockedFlushCount:()J
      59: lstore        5
      61: aload_1
      62: invokevirtual #31                 // Method org/apache/hadoop/hbase/regionserver/HeapMemoryManager$TunerContext.getUnblockedFlushCount:()J
      65: lstore        7
      67: lload         5
      69: lload         7
      71: ladd
      72: lstore        9
      74: aload_1
      75: invokevirtual #32                 // Method org/apache/hadoop/hbase/regionserver/HeapMemoryManager$TunerContext.isOffheapMemStore:()Z
      78: istore        11
      80: aload_0
      81: getfield      #21                 // Field prevTuneDirection:Lorg/apache/hadoop/hbase/regionserver/DefaultHeapMemoryTuner$StepDirection;
      84: getstatic     #20                 // Field org/apache/hadoop/hbase/regionserver/DefaultHeapMemoryTuner$StepDirection.NEUTRAL:Lorg/apache/hadoop/hbase/regionserver/DefaultHeapMemoryTuner$StepDirection;
      87: if_acmpne     123
      90: aload         4
      92: getstatic     #20                 // Field org/apache/hadoop/hbase/regionserver/DefaultHeapMemoryTuner$StepDirection.NEUTRAL:Lorg/apache/hadoop/hbase/regionserver/DefaultHeapMemoryTuner$StepDirection;
      95: if_acmpeq     123
      98: aload_0
      99: getfield      #26                 // Field rollingStatsForTunerSteps:Lorg/apache/hadoop/hbase/util/RollingStatCalculator;
     102: invokevirtual #33                 // Method org/apache/hadoop/hbase/util/RollingStatCalculator.getDeviation:()D
     105: ldc2_w        #34                 // double 1.0E-6d
     108: dcmpg
     109: ifge          123
     112: aload_0
     113: aload_0
     114: getfield      #13                 // Field maximumStepSize:F
     117: putfield      #19                 // Field step:F
     120: goto          184
     123: aload         4
     125: getstatic     #36                 // Field org/apache/hadoop/hbase/regionserver/DefaultHeapMemoryTuner$StepDirection.INCREASE_MEMSTORE_SIZE:Lorg/apache/hadoop/hbase/regionserver/DefaultHeapMemoryTuner$StepDirection;
     128: if_acmpne     140
     131: aload_0
     132: getfield      #22                 // Field decayingTunerStepSizeSum:D
     135: dconst_0
     136: dcmpg
     137: iflt          157
     140: aload         4
     142: getstatic     #37                 // Field org/apache/hadoop/hbase/regionserver/DefaultHeapMemoryTuner$StepDirection.INCREASE_BLOCK_CACHE_SIZE:Lorg/apache/hadoop/hbase/regionserver/DefaultHeapMemoryTuner$StepDirection;
     145: if_acmpne     184
     148: aload_0
     149: getfield      #22                 // Field decayingTunerStepSizeSum:D
     152: dconst_0
     153: dcmpl
     154: ifle          184
     157: iload         11
     159: ifne          184
     162: aload_0
     163: getfield      #19                 // Field step:F
     166: aload_0
     167: getfield      #15                 // Field minimumStepSize:F
     170: fcmpl
     171: ifeq          184
     174: aload_0
     175: aload_0
     176: getfield      #19                 // Field step:F
     179: fconst_2
     180: fdiv
     181: putfield      #19                 // Field step:F
     184: aload_0
     185: getfield      #19                 // Field step:F
     188: aload_0
     189: getfield      #15                 // Field minimumStepSize:F
     192: fcmpg
     193: ifge          217
     196: aload_0
     197: getfield      #6                  // Field LOG:Lorg/slf4j/Logger;
     200: ldc           #38                 // String Tuner step size is too low; we will not perform any tuning this time.
     202: invokeinterface #39,  2           // InterfaceMethod org/slf4j/Logger.debug:(Ljava/lang/String;)V
     207: aload_0
     208: fconst_0
     209: putfield      #19                 // Field step:F
     212: getstatic     #20                 // Field org/apache/hadoop/hbase/regionserver/DefaultHeapMemoryTuner$StepDirection.NEUTRAL:Lorg/apache/hadoop/hbase/regionserver/DefaultHeapMemoryTuner$StepDirection;
     215: astore        4
     217: lload         9
     219: lconst_0
     220: lcmp
     221: ifne          245
     224: iload         11
     226: ifeq          245
     229: aload         4
     231: getstatic     #37                 // Field org/apache/hadoop/hbase/regionserver/DefaultHeapMemoryTuner$StepDirection.INCREASE_BLOCK_CACHE_SIZE:Lorg/apache/hadoop/hbase/regionserver/DefaultHeapMemoryTuner$StepDirection;
     234: if_acmpne     245
     237: aload_0
     238: aload_0
     239: getfield      #15                 // Field minimumStepSize:F
     242: putfield      #19                 // Field step:F
     245: aload_0
     246: getfield      #40                 // Field globalMemStoreLimitLowMarkPercent:F
     249: fconst_1
     250: fadd
     251: fload_2
     252: fmul
     253: fconst_2
     254: fdiv
     255: fstore        14
     257: getstatic     #41                 // Field org/apache/hadoop/hbase/regionserver/DefaultHeapMemoryTuner$1.$SwitchMap$org$apache$hadoop$hbase$regionserver$DefaultHeapMemoryTuner$StepDirection:[I
     260: aload         4
     262: invokevirtual #42                 // Method org/apache/hadoop/hbase/regionserver/DefaultHeapMemoryTuner$StepDirection.ordinal:()I
     265: iaload
     266: lookupswitch  { // 2
                     1: 292
                     2: 366
               default: 419
          }
     292: fload_2
     293: aload_0
     294: getfield      #19                 // Field step:F
     297: fsub
     298: fload         14
     300: fcmpg
     301: ifge          312
     304: aload_0
     305: fload_2
     306: fload         14
     308: fsub
     309: putfield      #19                 // Field step:F
     312: fload_2
     313: aload_0
     314: getfield      #19                 // Field step:F
     317: fsub
     318: fstore        12
     320: fload_3
     321: aload_0
     322: getfield      #19                 // Field step:F
     325: fadd
     326: fstore        13
     328: aload_0
     329: getfield      #26                 // Field rollingStatsForTunerSteps:Lorg/apache/hadoop/hbase/util/RollingStatCalculator;
     332: aload_0
     333: getfield      #19                 // Field step:F
     336: ldc           #43                 // float 100000.0f
     338: fmul
     339: f2i
     340: ineg
     341: i2l
     342: invokevirtual #27                 // Method org/apache/hadoop/hbase/util/RollingStatCalculator.insertDataValue:(J)V
     345: aload_0
     346: aload_0
     347: getfield      #22                 // Field decayingTunerStepSizeSum:D
     350: aload_0
     351: getfield      #19                 // Field step:F
     354: f2d
     355: dsub
     356: ldc2_w        #44                 // double 2.0d
     359: ddiv
     360: putfield      #22                 // Field decayingTunerStepSizeSum:D
     363: goto          450
     366: fload_3
     367: aload_0
     368: getfield      #19                 // Field step:F
     371: fsub
     372: fstore        13
     374: fload_2
     375: aload_0
     376: getfield      #19                 // Field step:F
     379: fadd
     380: fstore        12
     382: aload_0
     383: getfield      #26                 // Field rollingStatsForTunerSteps:Lorg/apache/hadoop/hbase/util/RollingStatCalculator;
     386: aload_0
     387: getfield      #19                 // Field step:F
     390: ldc           #43                 // float 100000.0f
     392: fmul
     393: f2i
     394: i2l
     395: invokevirtual #27                 // Method org/apache/hadoop/hbase/util/RollingStatCalculator.insertDataValue:(J)V
     398: aload_0
     399: aload_0
     400: getfield      #22                 // Field decayingTunerStepSizeSum:D
     403: aload_0
     404: getfield      #19                 // Field step:F
     407: f2d
     408: dadd
     409: ldc2_w        #44                 // double 2.0d
     412: ddiv
     413: putfield      #22                 // Field decayingTunerStepSizeSum:D
     416: goto          450
     419: aload_0
     420: getstatic     #20                 // Field org/apache/hadoop/hbase/regionserver/DefaultHeapMemoryTuner$StepDirection.NEUTRAL:Lorg/apache/hadoop/hbase/regionserver/DefaultHeapMemoryTuner$StepDirection;
     423: putfield      #21                 // Field prevTuneDirection:Lorg/apache/hadoop/hbase/regionserver/DefaultHeapMemoryTuner$StepDirection;
     426: aload_0
     427: getfield      #26                 // Field rollingStatsForTunerSteps:Lorg/apache/hadoop/hbase/util/RollingStatCalculator;
     430: lconst_0
     431: invokevirtual #27                 // Method org/apache/hadoop/hbase/util/RollingStatCalculator.insertDataValue:(J)V
     434: aload_0
     435: aload_0
     436: getfield      #22                 // Field decayingTunerStepSizeSum:D
     439: ldc2_w        #44                 // double 2.0d
     442: ddiv
     443: putfield      #22                 // Field decayingTunerStepSizeSum:D
     446: getstatic     #28                 // Field NO_OP_TUNER_RESULT:Lorg/apache/hadoop/hbase/regionserver/HeapMemoryManager$TunerResult;
     449: areturn
     450: fload         12
     452: aload_0
     453: getfield      #46                 // Field globalMemStorePercentMaxRange:F
     456: fcmpl
     457: ifle          469
     460: aload_0
     461: getfield      #46                 // Field globalMemStorePercentMaxRange:F
     464: fstore        12
     466: goto          485
     469: fload         12
     471: aload_0
     472: getfield      #47                 // Field globalMemStorePercentMinRange:F
     475: fcmpg
     476: ifge          485
     479: aload_0
     480: getfield      #47                 // Field globalMemStorePercentMinRange:F
     483: fstore        12
     485: fload         13
     487: aload_0
     488: getfield      #48                 // Field blockCachePercentMaxRange:F
     491: fcmpl
     492: ifle          504
     495: aload_0
     496: getfield      #48                 // Field blockCachePercentMaxRange:F
     499: fstore        13
     501: goto          520
     504: fload         13
     506: aload_0
     507: getfield      #49                 // Field blockCachePercentMinRange:F
     510: fcmpg
     511: ifge          520
     514: aload_0
     515: getfield      #49                 // Field blockCachePercentMinRange:F
     518: fstore        13
     520: aload_0
     521: getfield      #9                  // Field TUNER_RESULT:Lorg/apache/hadoop/hbase/regionserver/HeapMemoryManager$TunerResult;
     524: fload         13
     526: invokevirtual #50                 // Method org/apache/hadoop/hbase/regionserver/HeapMemoryManager$TunerResult.setBlockCacheSize:(F)V
     529: aload_0
     530: getfield      #9                  // Field TUNER_RESULT:Lorg/apache/hadoop/hbase/regionserver/HeapMemoryManager$TunerResult;
     533: fload         12
     535: invokevirtual #51                 // Method org/apache/hadoop/hbase/regionserver/HeapMemoryManager$TunerResult.setMemStoreSize:(F)V
     538: aload_0
     539: aload         4
     541: putfield      #21                 // Field prevTuneDirection:Lorg/apache/hadoop/hbase/regionserver/DefaultHeapMemoryTuner$StepDirection;
     544: aload_0
     545: getfield      #9                  // Field TUNER_RESULT:Lorg/apache/hadoop/hbase/regionserver/HeapMemoryManager$TunerResult;
     548: areturn

  public org.apache.hadoop.conf.Configuration getConf();
    Code:
       0: aload_0
       1: getfield      #78                 // Field conf:Lorg/apache/hadoop/conf/Configuration;
       4: areturn

  public void setConf(org.apache.hadoop.conf.Configuration);
    Code:
       0: aload_0
       1: aload_1
       2: putfield      #78                 // Field conf:Lorg/apache/hadoop/conf/Configuration;
       5: aload_0
       6: aload_1
       7: ldc           #79                 // String hbase.regionserver.heapmemory.autotuner.step.max
       9: ldc           #12                 // float 0.04f
      11: invokevirtual #80                 // Method org/apache/hadoop/conf/Configuration.getFloat:(Ljava/lang/String;F)F
      14: putfield      #13                 // Field maximumStepSize:F
      17: aload_0
      18: aload_1
      19: ldc           #81                 // String hbase.regionserver.heapmemory.autotuner.step.min
      21: ldc           #14                 // float 0.00125f
      23: invokevirtual #80                 // Method org/apache/hadoop/conf/Configuration.getFloat:(Ljava/lang/String;F)F
      26: putfield      #15                 // Field minimumStepSize:F
      29: aload_0
      30: aload_0
      31: getfield      #13                 // Field maximumStepSize:F
      34: putfield      #19                 // Field step:F
      37: aload_0
      38: aload_1
      39: ldc           #82                 // String hbase.regionserver.heapmemory.autotuner.sufficient.memory.level
      41: ldc           #10                 // float 0.5f
      43: invokevirtual #80                 // Method org/apache/hadoop/conf/Configuration.getFloat:(Ljava/lang/String;F)F
      46: putfield      #11                 // Field sufficientMemoryLevel:F
      49: aload_0
      50: aload_1
      51: ldc           #83                 // String hbase.regionserver.heapmemory.autotuner.lookup.periods
      53: bipush        60
      55: invokevirtual #84                 // Method org/apache/hadoop/conf/Configuration.getInt:(Ljava/lang/String;I)I
      58: putfield      #16                 // Field tunerLookupPeriods:I
      61: aload_0
      62: aload_1
      63: ldc           #85                 // String hfile.block.cache.size.min.range
      65: aload_1
      66: ldc           #86                 // String hfile.block.cache.size
      68: ldc           #87                 // float 0.4f
      70: invokevirtual #80                 // Method org/apache/hadoop/conf/Configuration.getFloat:(Ljava/lang/String;F)F
      73: invokevirtual #80                 // Method org/apache/hadoop/conf/Configuration.getFloat:(Ljava/lang/String;F)F
      76: putfield      #49                 // Field blockCachePercentMinRange:F
      79: aload_0
      80: aload_1
      81: ldc           #88                 // String hfile.block.cache.size.max.range
      83: aload_1
      84: ldc           #86                 // String hfile.block.cache.size
      86: ldc           #87                 // float 0.4f
      88: invokevirtual #80                 // Method org/apache/hadoop/conf/Configuration.getFloat:(Ljava/lang/String;F)F
      91: invokevirtual #80                 // Method org/apache/hadoop/conf/Configuration.getFloat:(Ljava/lang/String;F)F
      94: putfield      #48                 // Field blockCachePercentMaxRange:F
      97: aload_0
      98: aload_1
      99: ldc           #89                 // String hbase.regionserver.global.memstore.size.min.range
     101: aload_1
     102: iconst_0
     103: invokestatic  #90                 // Method org/apache/hadoop/hbase/io/util/MemorySizeUtil.getGlobalMemStoreHeapPercent:(Lorg/apache/hadoop/conf/Configuration;Z)F
     106: invokevirtual #80                 // Method org/apache/hadoop/conf/Configuration.getFloat:(Ljava/lang/String;F)F
     109: putfield      #47                 // Field globalMemStorePercentMinRange:F
     112: aload_0
     113: aload_1
     114: ldc           #91                 // String hbase.regionserver.global.memstore.size.max.range
     116: aload_1
     117: iconst_0
     118: invokestatic  #90                 // Method org/apache/hadoop/hbase/io/util/MemorySizeUtil.getGlobalMemStoreHeapPercent:(Lorg/apache/hadoop/conf/Configuration;Z)F
     121: invokevirtual #80                 // Method org/apache/hadoop/conf/Configuration.getFloat:(Ljava/lang/String;F)F
     124: putfield      #46                 // Field globalMemStorePercentMaxRange:F
     127: aload_0
     128: aload_1
     129: iconst_1
     130: invokestatic  #92                 // Method org/apache/hadoop/hbase/io/util/MemorySizeUtil.getGlobalMemStoreHeapLowerMark:(Lorg/apache/hadoop/conf/Configuration;Z)F
     133: putfield      #40                 // Field globalMemStoreLimitLowMarkPercent:F
     136: aload_0
     137: aload_1
     138: ldc           #93                 // String hbase.regionserver.heapmemory.autotuner.ignored.periods
     140: aload_0
     141: getfield      #16                 // Field tunerLookupPeriods:I
     144: invokevirtual #84                 // Method org/apache/hadoop/conf/Configuration.getInt:(Ljava/lang/String;I)I
     147: putfield      #17                 // Field numPeriodsToIgnore:I
     150: aload_0
     151: new           #94                 // class org/apache/hadoop/hbase/util/RollingStatCalculator
     154: dup
     155: aload_0
     156: getfield      #16                 // Field tunerLookupPeriods:I
     159: invokespecial #95                 // Method org/apache/hadoop/hbase/util/RollingStatCalculator."<init>":(I)V
     162: putfield      #67                 // Field rollingStatsForCacheMisses:Lorg/apache/hadoop/hbase/util/RollingStatCalculator;
     165: aload_0
     166: new           #94                 // class org/apache/hadoop/hbase/util/RollingStatCalculator
     169: dup
     170: aload_0
     171: getfield      #16                 // Field tunerLookupPeriods:I
     174: invokespecial #95                 // Method org/apache/hadoop/hbase/util/RollingStatCalculator."<init>":(I)V
     177: putfield      #60                 // Field rollingStatsForFlushes:Lorg/apache/hadoop/hbase/util/RollingStatCalculator;
     180: aload_0
     181: new           #94                 // class org/apache/hadoop/hbase/util/RollingStatCalculator
     184: dup
     185: aload_0
     186: getfield      #16                 // Field tunerLookupPeriods:I
     189: invokespecial #95                 // Method org/apache/hadoop/hbase/util/RollingStatCalculator."<init>":(I)V
     192: putfield      #58                 // Field rollingStatsForEvictions:Lorg/apache/hadoop/hbase/util/RollingStatCalculator;
     195: aload_0
     196: new           #94                 // class org/apache/hadoop/hbase/util/RollingStatCalculator
     199: dup
     200: aload_0
     201: getfield      #16                 // Field tunerLookupPeriods:I
     204: invokespecial #95                 // Method org/apache/hadoop/hbase/util/RollingStatCalculator."<init>":(I)V
     207: putfield      #26                 // Field rollingStatsForTunerSteps:Lorg/apache/hadoop/hbase/util/RollingStatCalculator;
     210: return

  static {};
    Code:
       0: new           #7                  // class org/apache/hadoop/hbase/regionserver/HeapMemoryManager$TunerResult
       3: dup
       4: iconst_0
       5: invokespecial #8                  // Method org/apache/hadoop/hbase/regionserver/HeapMemoryManager$TunerResult."<init>":(Z)V
       8: putstatic     #28                 // Field NO_OP_TUNER_RESULT:Lorg/apache/hadoop/hbase/regionserver/HeapMemoryManager$TunerResult;
      11: return
}
