Compiled from "DefaultViolationPolicyEnforcement.java"
public class org.apache.hadoop.hbase.quotas.policies.DefaultViolationPolicyEnforcement extends org.apache.hadoop.hbase.quotas.policies.AbstractViolationPolicyEnforcement {
  public org.apache.hadoop.hbase.quotas.policies.DefaultViolationPolicyEnforcement();
    Code:
       0: aload_0
       1: invokespecial #1                  // Method org/apache/hadoop/hbase/quotas/policies/AbstractViolationPolicyEnforcement."<init>":()V
       4: return

  public void enable() throws java.io.IOException;
    Code:
       0: return

  public void disable() throws java.io.IOException;
    Code:
       0: return

  public java.lang.String getPolicyName();
    Code:
       0: ldc           #2                  // String BulkLoadVerifying
       2: areturn

  public void check(org.apache.hadoop.hbase.client.Mutation) throws org.apache.hadoop.hbase.quotas.SpaceLimitingException;
    Code:
       0: return

  public boolean shouldCheckBulkLoads();
    Code:
       0: invokestatic  #3                  // Method org/apache/hadoop/hbase/quotas/SpaceQuotaSnapshot.getNoSuchSnapshot:()Lorg/apache/hadoop/hbase/quotas/SpaceQuotaSnapshot;
       3: aload_0
       4: getfield      #4                  // Field quotaSnapshot:Lorg/apache/hadoop/hbase/quotas/SpaceQuotaSnapshot;
       7: if_acmpeq     14
      10: iconst_1
      11: goto          15
      14: iconst_0
      15: ireturn

  public long computeBulkLoadSize(org.apache.hadoop.fs.FileSystem, java.util.List<java.lang.String>) throws org.apache.hadoop.hbase.quotas.SpaceLimitingException;
    Code:
       0: aload_0
       1: getfield      #4                  // Field quotaSnapshot:Lorg/apache/hadoop/hbase/quotas/SpaceQuotaSnapshot;
       4: invokevirtual #5                  // Method org/apache/hadoop/hbase/quotas/SpaceQuotaSnapshot.getLimit:()J
       7: aload_0
       8: getfield      #4                  // Field quotaSnapshot:Lorg/apache/hadoop/hbase/quotas/SpaceQuotaSnapshot;
      11: invokevirtual #6                  // Method org/apache/hadoop/hbase/quotas/SpaceQuotaSnapshot.getUsage:()J
      14: lsub
      15: lstore_3
      16: lconst_0
      17: lstore        5
      19: aload_2
      20: invokeinterface #7,  1            // InterfaceMethod java/util/List.iterator:()Ljava/util/Iterator;
      25: astore        7
      27: aload         7
      29: invokeinterface #8,  1            // InterfaceMethod java/util/Iterator.hasNext:()Z
      34: ifeq          146
      37: aload         7
      39: invokeinterface #9,  1            // InterfaceMethod java/util/Iterator.next:()Ljava/lang/Object;
      44: checkcast     #10                 // class java/lang/String
      47: astore        8
      49: lload         5
      51: aload_0
      52: aload_1
      53: aload         8
      55: invokevirtual #11                 // Method getFileSize:(Lorg/apache/hadoop/fs/FileSystem;Ljava/lang/String;)J
      58: ladd
      59: lstore        5
      61: goto          100
      64: astore        9
      66: new           #13                 // class org/apache/hadoop/hbase/quotas/SpaceLimitingException
      69: dup
      70: aload_0
      71: invokevirtual #14                 // Method getPolicyName:()Ljava/lang/String;
      74: new           #15                 // class java/lang/StringBuilder
      77: dup
      78: invokespecial #16                 // Method java/lang/StringBuilder."<init>":()V
      81: ldc           #17                 // String Colud not verify length of file to bulk load:
      83: invokevirtual #18                 // Method java/lang/StringBuilder.append:(Ljava/lang/String;)Ljava/lang/StringBuilder;
      86: aload         8
      88: invokevirtual #18                 // Method java/lang/StringBuilder.append:(Ljava/lang/String;)Ljava/lang/StringBuilder;
      91: invokevirtual #19                 // Method java/lang/StringBuilder.toString:()Ljava/lang/String;
      94: aload         9
      96: invokespecial #20                 // Method org/apache/hadoop/hbase/quotas/SpaceLimitingException."<init>":(Ljava/lang/String;Ljava/lang/String;Ljava/lang/Throwable;)V
      99: athrow
     100: lload         5
     102: lload_3
     103: lcmp
     104: ifle          143
     107: new           #13                 // class org/apache/hadoop/hbase/quotas/SpaceLimitingException
     110: dup
     111: aload_0
     112: invokevirtual #14                 // Method getPolicyName:()Ljava/lang/String;
     115: new           #15                 // class java/lang/StringBuilder
     118: dup
     119: invokespecial #16                 // Method java/lang/StringBuilder."<init>":()V
     122: ldc           #21                 // String Bulk load of
     124: invokevirtual #18                 // Method java/lang/StringBuilder.append:(Ljava/lang/String;)Ljava/lang/StringBuilder;
     127: aload_2
     128: invokevirtual #22                 // Method java/lang/StringBuilder.append:(Ljava/lang/Object;)Ljava/lang/StringBuilder;
     131: ldc           #23                 // String  is disallowed because the file(s) exceed the limits of a space quota.
     133: invokevirtual #18                 // Method java/lang/StringBuilder.append:(Ljava/lang/String;)Ljava/lang/StringBuilder;
     136: invokevirtual #19                 // Method java/lang/StringBuilder.toString:()Ljava/lang/String;
     139: invokespecial #24                 // Method org/apache/hadoop/hbase/quotas/SpaceLimitingException."<init>":(Ljava/lang/String;Ljava/lang/String;)V
     142: athrow
     143: goto          27
     146: lload         5
     148: lreturn
    Exception table:
       from    to  target type
          49    61    64   Class java/io/IOException
}
