Compiled from "DelayedUtil.java"
public abstract class org.apache.hadoop.hbase.procedure2.util.DelayedUtil$DelayedObject implements org.apache.hadoop.hbase.procedure2.util.DelayedUtil$DelayedWithTimeout {
  public org.apache.hadoop.hbase.procedure2.util.DelayedUtil$DelayedObject();
    Code:
       0: aload_0
       1: invokespecial #1                  // Method java/lang/Object."<init>":()V
       4: return

  public long getDelay(java.util.concurrent.TimeUnit);
    Code:
       0: aload_1
       1: aload_0
       2: invokevirtual #2                  // Method getTimeout:()J
       5: invokestatic  #3                  // Method org/apache/hadoop/hbase/procedure2/util/DelayedUtil.getRemainingTime:(Ljava/util/concurrent/TimeUnit;J)J
       8: lreturn

  public int compareTo(java.util.concurrent.Delayed);
    Code:
       0: aload_0
       1: aload_1
       2: invokestatic  #4                  // Method org/apache/hadoop/hbase/procedure2/util/DelayedUtil.compareDelayed:(Ljava/util/concurrent/Delayed;Ljava/util/concurrent/Delayed;)I
       5: ireturn

  public java.lang.String toString();
    Code:
       0: aload_0
       1: invokevirtual #2                  // Method getTimeout:()J
       4: lstore_1
       5: new           #5                  // class java/lang/StringBuilder
       8: dup
       9: invokespecial #6                  // Method java/lang/StringBuilder."<init>":()V
      12: ldc           #7                  // String timeout=
      14: invokevirtual #8                  // Method java/lang/StringBuilder.append:(Ljava/lang/String;)Ljava/lang/StringBuilder;
      17: lload_1
      18: invokevirtual #9                  // Method java/lang/StringBuilder.append:(J)Ljava/lang/StringBuilder;
      21: ldc           #10                 // String , delay=
      23: invokevirtual #8                  // Method java/lang/StringBuilder.append:(Ljava/lang/String;)Ljava/lang/StringBuilder;
      26: aload_0
      27: getstatic     #11                 // Field java/util/concurrent/TimeUnit.MILLISECONDS:Ljava/util/concurrent/TimeUnit;
      30: invokevirtual #12                 // Method getDelay:(Ljava/util/concurrent/TimeUnit;)J
      33: invokevirtual #9                  // Method java/lang/StringBuilder.append:(J)Ljava/lang/StringBuilder;
      36: invokevirtual #13                 // Method java/lang/StringBuilder.toString:()Ljava/lang/String;
      39: areturn

  public int compareTo(java.lang.Object);
    Code:
       0: aload_0
       1: aload_1
       2: checkcast     #14                 // class java/util/concurrent/Delayed
       5: invokevirtual #15                 // Method compareTo:(Ljava/util/concurrent/Delayed;)I
       8: ireturn
}
