Compiled from "DelayedUtil.java"
final class org.apache.hadoop.hbase.procedure2.util.DelayedUtil$1 implements org.apache.hadoop.hbase.procedure2.util.DelayedUtil$DelayedWithTimeout {
  org.apache.hadoop.hbase.procedure2.util.DelayedUtil$1();
    Code:
       0: aload_0
       1: invokespecial #1                  // Method java/lang/Object."<init>":()V
       4: return

  public long getTimeout();
    Code:
       0: lconst_0
       1: lreturn

  public long getDelay(java.util.concurrent.TimeUnit);
    Code:
       0: lconst_0
       1: lreturn

  public int compareTo(java.util.concurrent.Delayed);
    Code:
       0: lconst_0
       1: aload_1
       2: invokestatic  #2                  // Method org/apache/hadoop/hbase/procedure2/util/DelayedUtil.access$000:(Ljava/util/concurrent/Delayed;)J
       5: invokestatic  #3                  // Method java/lang/Long.compare:(JJ)I
       8: ireturn

  public boolean equals(java.lang.Object);
    Code:
       0: aload_0
       1: aload_1
       2: if_acmpne     9
       5: iconst_1
       6: goto          10
       9: iconst_0
      10: ireturn

  public int hashCode();
    Code:
       0: iconst_1
       1: anewarray     #4                  // class java/lang/Object
       4: dup
       5: iconst_0
       6: aload_0
       7: aastore
       8: invokestatic  #5                  // Method java/util/Objects.hash:([Ljava/lang/Object;)I
      11: ireturn

  public java.lang.String toString();
    Code:
       0: new           #6                  // class java/lang/StringBuilder
       3: dup
       4: invokespecial #7                  // Method java/lang/StringBuilder."<init>":()V
       7: aload_0
       8: invokevirtual #8                  // Method java/lang/Object.getClass:()Ljava/lang/Class;
      11: invokevirtual #9                  // Method java/lang/Class.getSimpleName:()Ljava/lang/String;
      14: invokevirtual #10                 // Method java/lang/StringBuilder.append:(Ljava/lang/String;)Ljava/lang/StringBuilder;
      17: ldc           #11                 // String (POISON)
      19: invokevirtual #10                 // Method java/lang/StringBuilder.append:(Ljava/lang/String;)Ljava/lang/StringBuilder;
      22: invokevirtual #12                 // Method java/lang/StringBuilder.toString:()Ljava/lang/String;
      25: areturn

  public int compareTo(java.lang.Object);
    Code:
       0: aload_0
       1: aload_1
       2: checkcast     #13                 // class java/util/concurrent/Delayed
       5: invokevirtual #14                 // Method compareTo:(Ljava/util/concurrent/Delayed;)I
       8: ireturn
}
