Compiled from "DelayingRunner.java"
public class org.apache.hadoop.hbase.client.DelayingRunner implements java.lang.Runnable {
  public org.apache.hadoop.hbase.client.DelayingRunner(long, java.util.Map$Entry<byte[], java.util.List<org.apache.hadoop.hbase.client.Action>>);
    Code:
       0: aload_0
       1: invokespecial #1                  // Method java/lang/Object."<init>":()V
       4: aload_0
       5: new           #2                  // class java/lang/Object
       8: dup
       9: invokespecial #1                  // Method java/lang/Object."<init>":()V
      12: putfield      #3                  // Field sleepLock:Ljava/lang/Object;
      15: aload_0
      16: iconst_0
      17: putfield      #4                  // Field triggerWake:Z
      20: aload_0
      21: new           #5                  // class org/apache/hadoop/hbase/client/MultiAction
      24: dup
      25: invokespecial #6                  // Method org/apache/hadoop/hbase/client/MultiAction."<init>":()V
      28: putfield      #7                  // Field actions:Lorg/apache/hadoop/hbase/client/MultiAction;
      31: aload_0
      32: lload_1
      33: putfield      #8                  // Field sleepTime:J
      36: aload_0
      37: aload_3
      38: invokevirtual #9                  // Method add:(Ljava/util/Map$Entry;)V
      41: return

  public void setRunner(java.lang.Runnable);
    Code:
       0: aload_0
       1: aload_1
       2: putfield      #10                 // Field runnable:Ljava/lang/Runnable;
       5: return

  public void run();
    Code:
       0: aload_0
       1: invokespecial #11                 // Method sleep:()Z
       4: ifne          42
       7: getstatic     #12                 // Field LOG:Lorg/slf4j/Logger;
      10: new           #13                 // class java/lang/StringBuilder
      13: dup
      14: invokespecial #14                 // Method java/lang/StringBuilder."<init>":()V
      17: ldc           #15                 // String Interrupted while sleeping for expected sleep time
      19: invokevirtual #16                 // Method java/lang/StringBuilder.append:(Ljava/lang/String;)Ljava/lang/StringBuilder;
      22: aload_0
      23: getfield      #8                  // Field sleepTime:J
      26: invokevirtual #17                 // Method java/lang/StringBuilder.append:(J)Ljava/lang/StringBuilder;
      29: ldc           #18                 // String  ms
      31: invokevirtual #16                 // Method java/lang/StringBuilder.append:(Ljava/lang/String;)Ljava/lang/StringBuilder;
      34: invokevirtual #19                 // Method java/lang/StringBuilder.toString:()Ljava/lang/String;
      37: invokeinterface #20,  2           // InterfaceMethod org/slf4j/Logger.warn:(Ljava/lang/String;)V
      42: aload_0
      43: getfield      #10                 // Field runnable:Ljava/lang/Runnable;
      46: invokeinterface #21,  1           // InterfaceMethod java/lang/Runnable.run:()V
      51: return

  public void add(java.util.Map$Entry<byte[], java.util.List<org.apache.hadoop.hbase.client.Action>>);
    Code:
       0: aload_0
       1: getfield      #7                  // Field actions:Lorg/apache/hadoop/hbase/client/MultiAction;
       4: aload_1
       5: invokeinterface #27,  1           // InterfaceMethod java/util/Map$Entry.getKey:()Ljava/lang/Object;
      10: checkcast     #28                 // class "[B"
      13: aload_1
      14: invokeinterface #29,  1           // InterfaceMethod java/util/Map$Entry.getValue:()Ljava/lang/Object;
      19: checkcast     #30                 // class java/util/List
      22: invokevirtual #31                 // Method org/apache/hadoop/hbase/client/MultiAction.add:([BLjava/util/List;)V
      25: return

  public org.apache.hadoop.hbase.client.MultiAction getActions();
    Code:
       0: aload_0
       1: getfield      #7                  // Field actions:Lorg/apache/hadoop/hbase/client/MultiAction;
       4: areturn

  public long getSleepTime();
    Code:
       0: aload_0
       1: getfield      #8                  // Field sleepTime:J
       4: lreturn

  static {};
    Code:
       0: ldc           #32                 // class org/apache/hadoop/hbase/client/DelayingRunner
       2: invokestatic  #33                 // Method org/slf4j/LoggerFactory.getLogger:(Ljava/lang/Class;)Lorg/slf4j/Logger;
       5: putstatic     #12                 // Field LOG:Lorg/slf4j/Logger;
       8: return
}
