Compiled from "DelayedUtil.java"
public class org.apache.hadoop.hbase.procedure2.util.DelayedUtil$DelayedContainerWithTimestamp<T> extends org.apache.hadoop.hbase.procedure2.util.DelayedUtil$DelayedContainer<T> {
  public org.apache.hadoop.hbase.procedure2.util.DelayedUtil$DelayedContainerWithTimestamp(T, long);
    Code:
       0: aload_0
       1: aload_1
       2: invokespecial #1                  // Method org/apache/hadoop/hbase/procedure2/util/DelayedUtil$DelayedContainer."<init>":(Ljava/lang/Object;)V
       5: aload_0
       6: lload_2
       7: invokevirtual #2                  // Method setTimeout:(J)V
      10: return

  public long getTimeout();
    Code:
       0: aload_0
       1: getfield      #3                  // Field timeout:J
       4: lreturn

  public void setTimeout(long);
    Code:
       0: aload_0
       1: lload_1
       2: putfield      #3                  // Field timeout:J
       5: return
}
