Compiled from "DeleteTracker.java"
public final class org.apache.hadoop.hbase.regionserver.querymatcher.DeleteTracker$DeleteResult extends java.lang.Enum<org.apache.hadoop.hbase.regionserver.querymatcher.DeleteTracker$DeleteResult> {
  public static final org.apache.hadoop.hbase.regionserver.querymatcher.DeleteTracker$DeleteResult FAMILY_DELETED;

  public static final org.apache.hadoop.hbase.regionserver.querymatcher.DeleteTracker$DeleteResult FAMILY_VERSION_DELETED;

  public static final org.apache.hadoop.hbase.regionserver.querymatcher.DeleteTracker$DeleteResult COLUMN_DELETED;

  public static final org.apache.hadoop.hbase.regionserver.querymatcher.DeleteTracker$DeleteResult VERSION_DELETED;

  public static final org.apache.hadoop.hbase.regionserver.querymatcher.DeleteTracker$DeleteResult NOT_DELETED;

  public static final org.apache.hadoop.hbase.regionserver.querymatcher.DeleteTracker$DeleteResult VERSION_MASKED;

  public static org.apache.hadoop.hbase.regionserver.querymatcher.DeleteTracker$DeleteResult[] values();
    Code:
       0: getstatic     #1                  // Field $VALUES:[Lorg/apache/hadoop/hbase/regionserver/querymatcher/DeleteTracker$DeleteResult;
       3: invokevirtual #2                  // Method "[Lorg/apache/hadoop/hbase/regionserver/querymatcher/DeleteTracker$DeleteResult;".clone:()Ljava/lang/Object;
       6: checkcast     #3                  // class "[Lorg/apache/hadoop/hbase/regionserver/querymatcher/DeleteTracker$DeleteResult;"
       9: areturn

  public static org.apache.hadoop.hbase.regionserver.querymatcher.DeleteTracker$DeleteResult valueOf(java.lang.String);
    Code:
       0: ldc           #4                  // class org/apache/hadoop/hbase/regionserver/querymatcher/DeleteTracker$DeleteResult
       2: aload_0
       3: invokestatic  #5                  // Method java/lang/Enum.valueOf:(Ljava/lang/Class;Ljava/lang/String;)Ljava/lang/Enum;
       6: checkcast     #4                  // class org/apache/hadoop/hbase/regionserver/querymatcher/DeleteTracker$DeleteResult
       9: areturn

  static {};
    Code:
       0: new           #4                  // class org/apache/hadoop/hbase/regionserver/querymatcher/DeleteTracker$DeleteResult
       3: dup
       4: ldc           #7                  // String FAMILY_DELETED
       6: iconst_0
       7: invokespecial #8                  // Method "<init>":(Ljava/lang/String;I)V
      10: putstatic     #9                  // Field FAMILY_DELETED:Lorg/apache/hadoop/hbase/regionserver/querymatcher/DeleteTracker$DeleteResult;
      13: new           #4                  // class org/apache/hadoop/hbase/regionserver/querymatcher/DeleteTracker$DeleteResult
      16: dup
      17: ldc           #10                 // String FAMILY_VERSION_DELETED
      19: iconst_1
      20: invokespecial #8                  // Method "<init>":(Ljava/lang/String;I)V
      23: putstatic     #11                 // Field FAMILY_VERSION_DELETED:Lorg/apache/hadoop/hbase/regionserver/querymatcher/DeleteTracker$DeleteResult;
      26: new           #4                  // class org/apache/hadoop/hbase/regionserver/querymatcher/DeleteTracker$DeleteResult
      29: dup
      30: ldc           #12                 // String COLUMN_DELETED
      32: iconst_2
      33: invokespecial #8                  // Method "<init>":(Ljava/lang/String;I)V
      36: putstatic     #13                 // Field COLUMN_DELETED:Lorg/apache/hadoop/hbase/regionserver/querymatcher/DeleteTracker$DeleteResult;
      39: new           #4                  // class org/apache/hadoop/hbase/regionserver/querymatcher/DeleteTracker$DeleteResult
      42: dup
      43: ldc           #14                 // String VERSION_DELETED
      45: iconst_3
      46: invokespecial #8                  // Method "<init>":(Ljava/lang/String;I)V
      49: putstatic     #15                 // Field VERSION_DELETED:Lorg/apache/hadoop/hbase/regionserver/querymatcher/DeleteTracker$DeleteResult;
      52: new           #4                  // class org/apache/hadoop/hbase/regionserver/querymatcher/DeleteTracker$DeleteResult
      55: dup
      56: ldc           #16                 // String NOT_DELETED
      58: iconst_4
      59: invokespecial #8                  // Method "<init>":(Ljava/lang/String;I)V
      62: putstatic     #17                 // Field NOT_DELETED:Lorg/apache/hadoop/hbase/regionserver/querymatcher/DeleteTracker$DeleteResult;
      65: new           #4                  // class org/apache/hadoop/hbase/regionserver/querymatcher/DeleteTracker$DeleteResult
      68: dup
      69: ldc           #18                 // String VERSION_MASKED
      71: iconst_5
      72: invokespecial #8                  // Method "<init>":(Ljava/lang/String;I)V
      75: putstatic     #19                 // Field VERSION_MASKED:Lorg/apache/hadoop/hbase/regionserver/querymatcher/DeleteTracker$DeleteResult;
      78: bipush        6
      80: anewarray     #4                  // class org/apache/hadoop/hbase/regionserver/querymatcher/DeleteTracker$DeleteResult
      83: dup
      84: iconst_0
      85: getstatic     #9                  // Field FAMILY_DELETED:Lorg/apache/hadoop/hbase/regionserver/querymatcher/DeleteTracker$DeleteResult;
      88: aastore
      89: dup
      90: iconst_1
      91: getstatic     #11                 // Field FAMILY_VERSION_DELETED:Lorg/apache/hadoop/hbase/regionserver/querymatcher/DeleteTracker$DeleteResult;
      94: aastore
      95: dup
      96: iconst_2
      97: getstatic     #13                 // Field COLUMN_DELETED:Lorg/apache/hadoop/hbase/regionserver/querymatcher/DeleteTracker$DeleteResult;
     100: aastore
     101: dup
     102: iconst_3
     103: getstatic     #15                 // Field VERSION_DELETED:Lorg/apache/hadoop/hbase/regionserver/querymatcher/DeleteTracker$DeleteResult;
     106: aastore
     107: dup
     108: iconst_4
     109: getstatic     #17                 // Field NOT_DELETED:Lorg/apache/hadoop/hbase/regionserver/querymatcher/DeleteTracker$DeleteResult;
     112: aastore
     113: dup
     114: iconst_5
     115: getstatic     #19                 // Field VERSION_MASKED:Lorg/apache/hadoop/hbase/regionserver/querymatcher/DeleteTracker$DeleteResult;
     118: aastore
     119: putstatic     #1                  // Field $VALUES:[Lorg/apache/hadoop/hbase/regionserver/querymatcher/DeleteTracker$DeleteResult;
     122: return
}
