Compiled from "DelegatingHBaseRpcController.java"
public class org.apache.hadoop.hbase.ipc.DelegatingHBaseRpcController implements org.apache.hadoop.hbase.ipc.HBaseRpcController {
  public org.apache.hadoop.hbase.ipc.DelegatingHBaseRpcController(org.apache.hadoop.hbase.ipc.HBaseRpcController);
    Code:
       0: aload_0
       1: invokespecial #1                  // Method java/lang/Object."<init>":()V
       4: aload_0
       5: aload_1
       6: putfield      #2                  // Field delegate:Lorg/apache/hadoop/hbase/ipc/HBaseRpcController;
       9: return

  public void reset();
    Code:
       0: aload_0
       1: getfield      #2                  // Field delegate:Lorg/apache/hadoop/hbase/ipc/HBaseRpcController;
       4: invokeinterface #3,  1            // InterfaceMethod org/apache/hadoop/hbase/ipc/HBaseRpcController.reset:()V
       9: return

  public boolean failed();
    Code:
       0: aload_0
       1: getfield      #2                  // Field delegate:Lorg/apache/hadoop/hbase/ipc/HBaseRpcController;
       4: invokeinterface #4,  1            // InterfaceMethod org/apache/hadoop/hbase/ipc/HBaseRpcController.failed:()Z
       9: ireturn

  public java.lang.String errorText();
    Code:
       0: aload_0
       1: getfield      #2                  // Field delegate:Lorg/apache/hadoop/hbase/ipc/HBaseRpcController;
       4: invokeinterface #5,  1            // InterfaceMethod org/apache/hadoop/hbase/ipc/HBaseRpcController.errorText:()Ljava/lang/String;
       9: areturn

  public void startCancel();
    Code:
       0: aload_0
       1: getfield      #2                  // Field delegate:Lorg/apache/hadoop/hbase/ipc/HBaseRpcController;
       4: invokeinterface #6,  1            // InterfaceMethod org/apache/hadoop/hbase/ipc/HBaseRpcController.startCancel:()V
       9: return

  public void setFailed(java.lang.String);
    Code:
       0: aload_0
       1: getfield      #2                  // Field delegate:Lorg/apache/hadoop/hbase/ipc/HBaseRpcController;
       4: aload_1
       5: invokeinterface #7,  2            // InterfaceMethod org/apache/hadoop/hbase/ipc/HBaseRpcController.setFailed:(Ljava/lang/String;)V
      10: return

  public boolean isCanceled();
    Code:
       0: aload_0
       1: getfield      #2                  // Field delegate:Lorg/apache/hadoop/hbase/ipc/HBaseRpcController;
       4: invokeinterface #8,  1            // InterfaceMethod org/apache/hadoop/hbase/ipc/HBaseRpcController.isCanceled:()Z
       9: ireturn

  public void notifyOnCancel(org.apache.hbase.thirdparty.com.google.protobuf.RpcCallback<java.lang.Object>);
    Code:
       0: aload_0
       1: getfield      #2                  // Field delegate:Lorg/apache/hadoop/hbase/ipc/HBaseRpcController;
       4: aload_1
       5: invokeinterface #9,  2            // InterfaceMethod org/apache/hadoop/hbase/ipc/HBaseRpcController.notifyOnCancel:(Lorg/apache/hbase/thirdparty/com/google/protobuf/RpcCallback;)V
      10: return

  public org.apache.hadoop.hbase.CellScanner cellScanner();
    Code:
       0: aload_0
       1: getfield      #2                  // Field delegate:Lorg/apache/hadoop/hbase/ipc/HBaseRpcController;
       4: invokeinterface #10,  1           // InterfaceMethod org/apache/hadoop/hbase/ipc/HBaseRpcController.cellScanner:()Lorg/apache/hadoop/hbase/CellScanner;
       9: areturn

  public void setCellScanner(org.apache.hadoop.hbase.CellScanner);
    Code:
       0: aload_0
       1: getfield      #2                  // Field delegate:Lorg/apache/hadoop/hbase/ipc/HBaseRpcController;
       4: aload_1
       5: invokeinterface #11,  2           // InterfaceMethod org/apache/hadoop/hbase/ipc/HBaseRpcController.setCellScanner:(Lorg/apache/hadoop/hbase/CellScanner;)V
      10: return

  public void setPriority(int);
    Code:
       0: aload_0
       1: getfield      #2                  // Field delegate:Lorg/apache/hadoop/hbase/ipc/HBaseRpcController;
       4: iload_1
       5: invokeinterface #12,  2           // InterfaceMethod org/apache/hadoop/hbase/ipc/HBaseRpcController.setPriority:(I)V
      10: return

  public void setPriority(org.apache.hadoop.hbase.TableName);
    Code:
       0: aload_0
       1: getfield      #2                  // Field delegate:Lorg/apache/hadoop/hbase/ipc/HBaseRpcController;
       4: aload_1
       5: invokeinterface #13,  2           // InterfaceMethod org/apache/hadoop/hbase/ipc/HBaseRpcController.setPriority:(Lorg/apache/hadoop/hbase/TableName;)V
      10: return

  public int getPriority();
    Code:
       0: aload_0
       1: getfield      #2                  // Field delegate:Lorg/apache/hadoop/hbase/ipc/HBaseRpcController;
       4: invokeinterface #14,  1           // InterfaceMethod org/apache/hadoop/hbase/ipc/HBaseRpcController.getPriority:()I
       9: ireturn

  public int getCallTimeout();
    Code:
       0: aload_0
       1: getfield      #2                  // Field delegate:Lorg/apache/hadoop/hbase/ipc/HBaseRpcController;
       4: invokeinterface #15,  1           // InterfaceMethod org/apache/hadoop/hbase/ipc/HBaseRpcController.getCallTimeout:()I
       9: ireturn

  public void setCallTimeout(int);
    Code:
       0: aload_0
       1: getfield      #2                  // Field delegate:Lorg/apache/hadoop/hbase/ipc/HBaseRpcController;
       4: iload_1
       5: invokeinterface #16,  2           // InterfaceMethod org/apache/hadoop/hbase/ipc/HBaseRpcController.setCallTimeout:(I)V
      10: return

  public boolean hasCallTimeout();
    Code:
       0: aload_0
       1: getfield      #2                  // Field delegate:Lorg/apache/hadoop/hbase/ipc/HBaseRpcController;
       4: invokeinterface #17,  1           // InterfaceMethod org/apache/hadoop/hbase/ipc/HBaseRpcController.hasCallTimeout:()Z
       9: ireturn

  public void setFailed(java.io.IOException);
    Code:
       0: aload_0
       1: getfield      #2                  // Field delegate:Lorg/apache/hadoop/hbase/ipc/HBaseRpcController;
       4: aload_1
       5: invokeinterface #18,  2           // InterfaceMethod org/apache/hadoop/hbase/ipc/HBaseRpcController.setFailed:(Ljava/io/IOException;)V
      10: return

  public java.io.IOException getFailed();
    Code:
       0: aload_0
       1: getfield      #2                  // Field delegate:Lorg/apache/hadoop/hbase/ipc/HBaseRpcController;
       4: invokeinterface #19,  1           // InterfaceMethod org/apache/hadoop/hbase/ipc/HBaseRpcController.getFailed:()Ljava/io/IOException;
       9: areturn

  public void setDone(org.apache.hadoop.hbase.CellScanner);
    Code:
       0: aload_0
       1: getfield      #2                  // Field delegate:Lorg/apache/hadoop/hbase/ipc/HBaseRpcController;
       4: aload_1
       5: invokeinterface #20,  2           // InterfaceMethod org/apache/hadoop/hbase/ipc/HBaseRpcController.setDone:(Lorg/apache/hadoop/hbase/CellScanner;)V
      10: return

  public void notifyOnCancel(org.apache.hbase.thirdparty.com.google.protobuf.RpcCallback<java.lang.Object>, org.apache.hadoop.hbase.ipc.HBaseRpcController$CancellationCallback) throws java.io.IOException;
    Code:
       0: aload_0
       1: getfield      #2                  // Field delegate:Lorg/apache/hadoop/hbase/ipc/HBaseRpcController;
       4: aload_1
       5: aload_2
       6: invokeinterface #21,  3           // InterfaceMethod org/apache/hadoop/hbase/ipc/HBaseRpcController.notifyOnCancel:(Lorg/apache/hbase/thirdparty/com/google/protobuf/RpcCallback;Lorg/apache/hadoop/hbase/ipc/HBaseRpcController$CancellationCallback;)V
      11: return
}
