Compiled from "DelegatingInternalScanner.java"
public class org.apache.hadoop.hbase.regionserver.DelegatingInternalScanner implements org.apache.hadoop.hbase.regionserver.InternalScanner {
  protected final org.apache.hadoop.hbase.regionserver.InternalScanner scanner;

  public org.apache.hadoop.hbase.regionserver.DelegatingInternalScanner(org.apache.hadoop.hbase.regionserver.InternalScanner);
    Code:
       0: aload_0
       1: invokespecial #1                  // Method java/lang/Object."<init>":()V
       4: aload_0
       5: aload_1
       6: putfield      #2                  // Field scanner:Lorg/apache/hadoop/hbase/regionserver/InternalScanner;
       9: return

  public boolean next(java.util.List<org.apache.hadoop.hbase.Cell>, org.apache.hadoop.hbase.regionserver.ScannerContext) throws java.io.IOException;
    Code:
       0: aload_0
       1: getfield      #2                  // Field scanner:Lorg/apache/hadoop/hbase/regionserver/InternalScanner;
       4: aload_1
       5: aload_2
       6: invokeinterface #3,  3            // InterfaceMethod org/apache/hadoop/hbase/regionserver/InternalScanner.next:(Ljava/util/List;Lorg/apache/hadoop/hbase/regionserver/ScannerContext;)Z
      11: ireturn

  public void close() throws java.io.IOException;
    Code:
       0: aload_0
       1: getfield      #2                  // Field scanner:Lorg/apache/hadoop/hbase/regionserver/InternalScanner;
       4: invokeinterface #4,  1            // InterfaceMethod org/apache/hadoop/hbase/regionserver/InternalScanner.close:()V
       9: return
}
