Compiled from "Dictionary.java"
public interface org.apache.hadoop.hbase.io.util.Dictionary {
  public static final byte NOT_IN_DICTIONARY;

  public abstract void init(int);

  public abstract byte[] getEntry(short);

  public abstract short findEntry(byte[], int, int);

  public abstract short findEntry(java.nio.ByteBuffer, int, int);

  public abstract short addEntry(byte[], int, int);

  public abstract void clear();

  public static void write(java.io.OutputStream, byte[], int, int, org.apache.hadoop.hbase.io.util.Dictionary) throws java.io.IOException;
    Code:
       0: iconst_m1
       1: istore        5
       3: aload         4
       5: ifnull        20
       8: aload         4
      10: aload_1
      11: iload_2
      12: iload_3
      13: invokeinterface #2,  4            // InterfaceMethod findEntry:([BII)S
      18: istore        5
      20: iload         5
      22: iconst_m1
      23: if_icmpne     46
      26: aload_0
      27: iconst_m1
      28: invokevirtual #3                  // Method java/io/OutputStream.write:(I)V
      31: aload_0
      32: iload_3
      33: invokestatic  #4                  // Method org/apache/hadoop/hbase/io/util/StreamUtils.writeRawVInt32:(Ljava/io/OutputStream;I)V
      36: aload_0
      37: aload_1
      38: iload_2
      39: iload_3
      40: invokevirtual #5                  // Method java/io/OutputStream.write:([BII)V
      43: goto          52
      46: aload_0
      47: iload         5
      49: invokestatic  #6                  // Method org/apache/hadoop/hbase/io/util/StreamUtils.writeShort:(Ljava/io/OutputStream;S)V
      52: return

  public static void write(java.io.OutputStream, java.nio.ByteBuffer, int, int, org.apache.hadoop.hbase.io.util.Dictionary) throws java.io.IOException;
    Code:
       0: iconst_m1
       1: istore        5
       3: aload         4
       5: ifnull        20
       8: aload         4
      10: aload_1
      11: iload_2
      12: iload_3
      13: invokeinterface #7,  4            // InterfaceMethod findEntry:(Ljava/nio/ByteBuffer;II)S
      18: istore        5
      20: iload         5
      22: iconst_m1
      23: if_icmpne     46
      26: aload_0
      27: iconst_m1
      28: invokevirtual #3                  // Method java/io/OutputStream.write:(I)V
      31: aload_0
      32: iload_3
      33: invokestatic  #4                  // Method org/apache/hadoop/hbase/io/util/StreamUtils.writeRawVInt32:(Ljava/io/OutputStream;I)V
      36: aload_0
      37: aload_1
      38: iload_2
      39: iload_3
      40: invokestatic  #8                  // Method org/apache/hadoop/hbase/util/ByteBufferUtils.copyBufferToStream:(Ljava/io/OutputStream;Ljava/nio/ByteBuffer;II)V
      43: goto          52
      46: aload_0
      47: iload         5
      49: invokestatic  #6                  // Method org/apache/hadoop/hbase/io/util/StreamUtils.writeShort:(Ljava/io/OutputStream;S)V
      52: return
}
