Compiled from "DiffKeyDeltaEncoder.java"
public class org.apache.hadoop.hbase.io.encoding.DiffKeyDeltaEncoder$DiffCompressionState extends org.apache.hadoop.hbase.io.encoding.CompressionState {
  long timestamp;

  byte[] familyNameWithSize;

  protected org.apache.hadoop.hbase.io.encoding.DiffKeyDeltaEncoder$DiffCompressionState();
    Code:
       0: aload_0
       1: invokespecial #1                  // Method org/apache/hadoop/hbase/io/encoding/CompressionState."<init>":()V
       4: return

  protected void readTimestamp(java.nio.ByteBuffer);
    Code:
       0: aload_0
       1: aload_1
       2: invokevirtual #2                  // Method java/nio/ByteBuffer.getLong:()J
       5: putfield      #3                  // Field timestamp:J
       8: return

  void copyFrom(org.apache.hadoop.hbase.io.encoding.CompressionState);
    Code:
       0: aload_0
       1: aload_1
       2: invokespecial #4                  // Method org/apache/hadoop/hbase/io/encoding/CompressionState.copyFrom:(Lorg/apache/hadoop/hbase/io/encoding/CompressionState;)V
       5: aload_1
       6: checkcast     #5                  // class org/apache/hadoop/hbase/io/encoding/DiffKeyDeltaEncoder$DiffCompressionState
       9: astore_2
      10: aload_0
      11: aload_2
      12: getfield      #3                  // Field timestamp:J
      15: putfield      #3                  // Field timestamp:J
      18: return
}
