Compiled from "DirectMemoryUtils.java"
public class org.apache.hadoop.hbase.util.DirectMemoryUtils {
  public org.apache.hadoop.hbase.util.DirectMemoryUtils();
    Code:
       0: aload_0
       1: invokespecial #1                  // Method java/lang/Object."<init>":()V
       4: return

  public static long getDirectMemorySize();
    Code:
       0: invokestatic  #2                  // Method java/lang/management/ManagementFactory.getRuntimeMXBean:()Ljava/lang/management/RuntimeMXBean;
       3: astore_0
       4: aload_0
       5: invokeinterface #3,  1            // InterfaceMethod java/lang/management/RuntimeMXBean.getInputArguments:()Ljava/util/List;
      10: astore_1
      11: lconst_1
      12: lstore_2
      13: aload_1
      14: invokeinterface #4,  1            // InterfaceMethod java/util/List.iterator:()Ljava/util/Iterator;
      19: astore        4
      21: aload         4
      23: invokeinterface #5,  1            // InterfaceMethod java/util/Iterator.hasNext:()Z
      28: ifeq          147
      31: aload         4
      33: invokeinterface #6,  1            // InterfaceMethod java/util/Iterator.next:()Ljava/lang/Object;
      38: checkcast     #7                  // class java/lang/String
      41: astore        5
      43: aload         5
      45: ldc           #8                  // String -XX:MaxDirectMemorySize=
      47: invokevirtual #9                  // Method java/lang/String.contains:(Ljava/lang/CharSequence;)Z
      50: ifeq          144
      53: aload         5
      55: getstatic     #10                 // Field java/util/Locale.ROOT:Ljava/util/Locale;
      58: invokevirtual #11                 // Method java/lang/String.toLowerCase:(Ljava/util/Locale;)Ljava/lang/String;
      61: ldc           #12                 // String -xx:maxdirectmemorysize=
      63: ldc           #13                 // String
      65: invokevirtual #14                 // Method java/lang/String.replace:(Ljava/lang/CharSequence;Ljava/lang/CharSequence;)Ljava/lang/String;
      68: invokevirtual #15                 // Method java/lang/String.trim:()Ljava/lang/String;
      71: astore        6
      73: aload         6
      75: ldc           #16                 // String k
      77: invokevirtual #9                  // Method java/lang/String.contains:(Ljava/lang/CharSequence;)Z
      80: ifeq          90
      83: ldc2_w        #17                 // long 1024l
      86: lstore_2
      87: goto          121
      90: aload         6
      92: ldc           #19                 // String m
      94: invokevirtual #9                  // Method java/lang/String.contains:(Ljava/lang/CharSequence;)Z
      97: ifeq          107
     100: ldc2_w        #20                 // long 1048576l
     103: lstore_2
     104: goto          121
     107: aload         6
     109: ldc           #22                 // String g
     111: invokevirtual #9                  // Method java/lang/String.contains:(Ljava/lang/CharSequence;)Z
     114: ifeq          121
     117: ldc2_w        #23                 // long 1073741824l
     120: lstore_2
     121: aload         6
     123: ldc           #25                 // String [^\d]
     125: ldc           #13                 // String
     127: invokevirtual #26                 // Method java/lang/String.replaceAll:(Ljava/lang/String;Ljava/lang/String;)Ljava/lang/String;
     130: astore        6
     132: aload         6
     134: invokestatic  #27                 // Method java/lang/Long.parseLong:(Ljava/lang/String;)J
     137: lstore        7
     139: lload         7
     141: lload_2
     142: lmul
     143: lreturn
     144: goto          21
     147: lconst_0
     148: lreturn

  public static long getDirectMemoryUsage();
    Code:
       0: getstatic     #28                 // Field BEAN_SERVER:Ljavax/management/MBeanServer;
       3: ifnull        18
       6: getstatic     #29                 // Field NIO_DIRECT_POOL:Ljavax/management/ObjectName;
       9: ifnull        18
      12: getstatic     #30                 // Field HAS_MEMORY_USED_ATTRIBUTE:Z
      15: ifne          20
      18: lconst_0
      19: lreturn
      20: getstatic     #28                 // Field BEAN_SERVER:Ljavax/management/MBeanServer;
      23: getstatic     #29                 // Field NIO_DIRECT_POOL:Ljavax/management/ObjectName;
      26: ldc           #32                 // String MemoryUsed
      28: invokeinterface #33,  3           // InterfaceMethod javax/management/MBeanServer.getAttribute:(Ljavax/management/ObjectName;Ljava/lang/String;)Ljava/lang/Object;
      33: checkcast     #34                 // class java/lang/Long
      36: astore_0
      37: aload_0
      38: ifnonnull     45
      41: lconst_0
      42: goto          49
      45: aload_0
      46: invokevirtual #35                 // Method java/lang/Long.longValue:()J
      49: lreturn
      50: astore_0
      51: lconst_0
      52: lreturn
    Exception table:
       from    to  target type
          20    49    50   Class javax/management/JMException

  public static long getNettyDirectMemoryUsage();
    Code:
       0: getstatic     #37                 // Field org/apache/hbase/thirdparty/io/netty/buffer/PooledByteBufAllocator.DEFAULT:Lorg/apache/hbase/thirdparty/io/netty/buffer/PooledByteBufAllocator;
       3: invokeinterface #38,  1           // InterfaceMethod org/apache/hbase/thirdparty/io/netty/buffer/ByteBufAllocatorMetricProvider.metric:()Lorg/apache/hbase/thirdparty/io/netty/buffer/ByteBufAllocatorMetric;
       8: astore_0
       9: aload_0
      10: invokeinterface #39,  1           // InterfaceMethod org/apache/hbase/thirdparty/io/netty/buffer/ByteBufAllocatorMetric.usedDirectMemory:()J
      15: lreturn

  public static void destroyDirectByteBuffer(java.nio.ByteBuffer) throws java.lang.IllegalArgumentException, java.lang.IllegalAccessException, java.lang.reflect.InvocationTargetException, java.lang.SecurityException, java.lang.NoSuchMethodException;
    Code:
       0: aload_0
       1: invokevirtual #40                 // Method java/nio/ByteBuffer.isDirect:()Z
       4: ldc           #41                 // String toBeDestroyed isn't direct!
       6: invokestatic  #42                 // Method org/apache/hbase/thirdparty/com/google/common/base/Preconditions.checkArgument:(ZLjava/lang/Object;)V
       9: aload_0
      10: invokevirtual #43                 // Method java/lang/Object.getClass:()Ljava/lang/Class;
      13: ldc           #44                 // String cleaner
      15: iconst_0
      16: anewarray     #45                 // class java/lang/Class
      19: invokevirtual #46                 // Method java/lang/Class.getMethod:(Ljava/lang/String;[Ljava/lang/Class;)Ljava/lang/reflect/Method;
      22: astore_1
      23: aload_1
      24: iconst_1
      25: invokevirtual #47                 // Method java/lang/reflect/Method.setAccessible:(Z)V
      28: aload_1
      29: aload_0
      30: iconst_0
      31: anewarray     #48                 // class java/lang/Object
      34: invokevirtual #49                 // Method java/lang/reflect/Method.invoke:(Ljava/lang/Object;[Ljava/lang/Object;)Ljava/lang/Object;
      37: astore_2
      38: aload_2
      39: invokevirtual #43                 // Method java/lang/Object.getClass:()Ljava/lang/Class;
      42: ldc           #50                 // String clean
      44: iconst_0
      45: anewarray     #45                 // class java/lang/Class
      48: invokevirtual #46                 // Method java/lang/Class.getMethod:(Ljava/lang/String;[Ljava/lang/Class;)Ljava/lang/reflect/Method;
      51: astore_3
      52: aload_3
      53: iconst_1
      54: invokevirtual #47                 // Method java/lang/reflect/Method.setAccessible:(Z)V
      57: aload_3
      58: aload_2
      59: iconst_0
      60: anewarray     #48                 // class java/lang/Object
      63: invokevirtual #49                 // Method java/lang/reflect/Method.invoke:(Ljava/lang/Object;[Ljava/lang/Object;)Ljava/lang/Object;
      66: pop
      67: return

  static {};
    Code:
       0: ldc           #31                 // class org/apache/hadoop/hbase/util/DirectMemoryUtils
       2: invokestatic  #51                 // Method org/slf4j/LoggerFactory.getLogger:(Ljava/lang/Class;)Lorg/slf4j/Logger;
       5: putstatic     #52                 // Field LOG:Lorg/slf4j/Logger;
       8: aconst_null
       9: astore_0
      10: aconst_null
      11: astore_1
      12: aconst_null
      13: astore_2
      14: new           #53                 // class javax/management/ObjectName
      17: dup
      18: ldc           #54                 // String java.nio:type=BufferPool,name=direct
      20: invokespecial #55                 // Method javax/management/ObjectName."<init>":(Ljava/lang/String;)V
      23: astore_0
      24: aload_0
      25: putstatic     #29                 // Field NIO_DIRECT_POOL:Ljavax/management/ObjectName;
      28: goto          58
      31: astore_3
      32: getstatic     #52                 // Field LOG:Lorg/slf4j/Logger;
      35: ldc           #57                 // String Unable to initialize ObjectName for DirectByteBuffer allocations.
      37: invokeinterface #58,  2           // InterfaceMethod org/slf4j/Logger.warn:(Ljava/lang/String;)V
      42: aload_0
      43: putstatic     #29                 // Field NIO_DIRECT_POOL:Ljavax/management/ObjectName;
      46: goto          58
      49: astore        4
      51: aload_0
      52: putstatic     #29                 // Field NIO_DIRECT_POOL:Ljavax/management/ObjectName;
      55: aload         4
      57: athrow
      58: getstatic     #29                 // Field NIO_DIRECT_POOL:Ljavax/management/ObjectName;
      61: ifnull        68
      64: invokestatic  #59                 // Method java/lang/management/ManagementFactory.getPlatformMBeanServer:()Ljavax/management/MBeanServer;
      67: astore_1
      68: aload_1
      69: putstatic     #28                 // Field BEAN_SERVER:Ljavax/management/MBeanServer;
      72: getstatic     #28                 // Field BEAN_SERVER:Ljavax/management/MBeanServer;
      75: ifnull        123
      78: getstatic     #28                 // Field BEAN_SERVER:Ljavax/management/MBeanServer;
      81: getstatic     #29                 // Field NIO_DIRECT_POOL:Ljavax/management/ObjectName;
      84: ldc           #32                 // String MemoryUsed
      86: invokeinterface #33,  3           // InterfaceMethod javax/management/MBeanServer.getAttribute:(Ljavax/management/ObjectName;Ljava/lang/String;)Ljava/lang/Object;
      91: astore_2
      92: goto          123
      95: astore_3
      96: getstatic     #52                 // Field LOG:Lorg/slf4j/Logger;
      99: new           #60                 // class java/lang/StringBuilder
     102: dup
     103: invokespecial #61                 // Method java/lang/StringBuilder."<init>":()V
     106: ldc           #62                 // String Failed to retrieve nio.BufferPool direct MemoryUsed attribute:
     108: invokevirtual #63                 // Method java/lang/StringBuilder.append:(Ljava/lang/String;)Ljava/lang/StringBuilder;
     111: aload_3
     112: invokevirtual #64                 // Method java/lang/StringBuilder.append:(Ljava/lang/Object;)Ljava/lang/StringBuilder;
     115: invokevirtual #65                 // Method java/lang/StringBuilder.toString:()Ljava/lang/String;
     118: invokeinterface #66,  2           // InterfaceMethod org/slf4j/Logger.debug:(Ljava/lang/String;)V
     123: aload_2
     124: ifnull        131
     127: iconst_1
     128: goto          132
     131: iconst_0
     132: putstatic     #30                 // Field HAS_MEMORY_USED_ATTRIBUTE:Z
     135: return
    Exception table:
       from    to  target type
          14    24    31   Class javax/management/MalformedObjectNameException
          14    24    49   any
          31    42    49   any
          49    51    49   any
          78    92    95   Class javax/management/JMException
}
