Compiled from "DisabledWALProvider.java"
class org.apache.hadoop.hbase.wal.DisabledWALProvider implements org.apache.hadoop.hbase.wal.WALProvider {
  org.apache.hadoop.hbase.wal.WAL disabled;

  org.apache.hadoop.hbase.wal.DisabledWALProvider();
    Code:
       0: aload_0
       1: invokespecial #2                  // Method java/lang/Object."<init>":()V
       4: return

  public void init(org.apache.hadoop.hbase.wal.WALFactory, org.apache.hadoop.conf.Configuration, java.lang.String) throws java.io.IOException;
    Code:
       0: aconst_null
       1: aload_0
       2: getfield      #3                  // Field disabled:Lorg/apache/hadoop/hbase/wal/WAL;
       5: if_acmpeq     18
       8: new           #4                  // class java/lang/IllegalStateException
      11: dup
      12: ldc           #5                  // String WALProvider.init should only be called once.
      14: invokespecial #6                  // Method java/lang/IllegalStateException."<init>":(Ljava/lang/String;)V
      17: athrow
      18: aconst_null
      19: aload_3
      20: if_acmpne     26
      23: ldc           #7                  // String defaultDisabled
      25: astore_3
      26: aload_0
      27: new           #8                  // class org/apache/hadoop/hbase/wal/DisabledWALProvider$DisabledWAL
      30: dup
      31: new           #9                  // class org/apache/hadoop/fs/Path
      34: dup
      35: aload_2
      36: invokestatic  #10                 // Method org/apache/hadoop/hbase/util/FSUtils.getWALRootDir:(Lorg/apache/hadoop/conf/Configuration;)Lorg/apache/hadoop/fs/Path;
      39: aload_3
      40: invokespecial #11                 // Method org/apache/hadoop/fs/Path."<init>":(Lorg/apache/hadoop/fs/Path;Ljava/lang/String;)V
      43: aload_2
      44: aconst_null
      45: invokespecial #12                 // Method org/apache/hadoop/hbase/wal/DisabledWALProvider$DisabledWAL."<init>":(Lorg/apache/hadoop/fs/Path;Lorg/apache/hadoop/conf/Configuration;Ljava/util/List;)V
      48: putfield      #3                  // Field disabled:Lorg/apache/hadoop/hbase/wal/WAL;
      51: return

  public java.util.List<org.apache.hadoop.hbase.wal.WAL> getWALs();
    Code:
       0: new           #13                 // class java/util/ArrayList
       3: dup
       4: iconst_1
       5: invokespecial #14                 // Method java/util/ArrayList."<init>":(I)V
       8: astore_1
       9: aload_1
      10: aload_0
      11: getfield      #3                  // Field disabled:Lorg/apache/hadoop/hbase/wal/WAL;
      14: invokeinterface #15,  2           // InterfaceMethod java/util/List.add:(Ljava/lang/Object;)Z
      19: pop
      20: aload_1
      21: areturn

  public org.apache.hadoop.hbase.wal.WAL getWAL(org.apache.hadoop.hbase.client.RegionInfo) throws java.io.IOException;
    Code:
       0: aload_0
       1: getfield      #3                  // Field disabled:Lorg/apache/hadoop/hbase/wal/WAL;
       4: areturn

  public void close() throws java.io.IOException;
    Code:
       0: aload_0
       1: getfield      #3                  // Field disabled:Lorg/apache/hadoop/hbase/wal/WAL;
       4: invokeinterface #16,  1           // InterfaceMethod org/apache/hadoop/hbase/wal/WAL.close:()V
       9: return

  public void shutdown() throws java.io.IOException;
    Code:
       0: aload_0
       1: getfield      #3                  // Field disabled:Lorg/apache/hadoop/hbase/wal/WAL;
       4: invokeinterface #17,  1           // InterfaceMethod org/apache/hadoop/hbase/wal/WAL.shutdown:()V
       9: return

  public long getNumLogFiles();
    Code:
       0: lconst_0
       1: lreturn

  public long getLogFileSize();
    Code:
       0: lconst_0
       1: lreturn

  public void addWALActionsListener(org.apache.hadoop.hbase.regionserver.wal.WALActionsListener);
    Code:
       0: aload_0
       1: getfield      #3                  // Field disabled:Lorg/apache/hadoop/hbase/wal/WAL;
       4: aload_1
       5: invokeinterface #18,  2           // InterfaceMethod org/apache/hadoop/hbase/wal/WAL.registerWALActionsListener:(Lorg/apache/hadoop/hbase/regionserver/wal/WALActionsListener;)V
      10: return

  static org.slf4j.Logger access$000();
    Code:
       0: getstatic     #1                  // Field LOG:Lorg/slf4j/Logger;
       3: areturn

  static {};
    Code:
       0: ldc           #19                 // class org/apache/hadoop/hbase/wal/DisabledWALProvider
       2: invokestatic  #20                 // Method org/slf4j/LoggerFactory.getLogger:(Ljava/lang/Class;)Lorg/slf4j/Logger;
       5: putstatic     #1                  // Field LOG:Lorg/slf4j/Logger;
       8: return
}
