Compiled from "DoubleColumnInterpreter.java"
public class org.apache.hadoop.hbase.client.coprocessor.DoubleColumnInterpreter extends org.apache.hadoop.hbase.coprocessor.ColumnInterpreter<java.lang.Double, java.lang.Double, org.apache.hadoop.hbase.protobuf.generated.HBaseProtos$EmptyMsg, org.apache.hadoop.hbase.protobuf.generated.HBaseProtos$DoubleMsg, org.apache.hadoop.hbase.protobuf.generated.HBaseProtos$DoubleMsg> {
  public org.apache.hadoop.hbase.client.coprocessor.DoubleColumnInterpreter();
    Code:
       0: aload_0
       1: invokespecial #1                  // Method org/apache/hadoop/hbase/coprocessor/ColumnInterpreter."<init>":()V
       4: return

  public java.lang.Double getValue(byte[], byte[], org.apache.hadoop.hbase.Cell) throws java.io.IOException;
    Code:
       0: aload_3
       1: ifnull        15
       4: aload_3
       5: invokeinterface #2,  1            // InterfaceMethod org/apache/hadoop/hbase/Cell.getValueLength:()I
      10: bipush        8
      12: if_icmpeq     17
      15: aconst_null
      16: areturn
      17: aload_3
      18: invokestatic  #4                  // Method org/apache/hadoop/hbase/PrivateCellUtil.getValueAsDouble:(Lorg/apache/hadoop/hbase/Cell;)D
      21: invokestatic  #5                  // Method java/lang/Double.valueOf:(D)Ljava/lang/Double;
      24: areturn

  public java.lang.Double add(java.lang.Double, java.lang.Double);
    Code:
       0: aload_1
       1: ifnull        8
       4: aload_2
       5: ifnonnull     18
       8: aload_1
       9: ifnonnull     16
      12: aload_2
      13: goto          17
      16: aload_1
      17: areturn
      18: aload_1
      19: invokevirtual #6                  // Method java/lang/Double.doubleValue:()D
      22: aload_2
      23: invokevirtual #6                  // Method java/lang/Double.doubleValue:()D
      26: dadd
      27: invokestatic  #5                  // Method java/lang/Double.valueOf:(D)Ljava/lang/Double;
      30: areturn

  public int compare(java.lang.Double, java.lang.Double);
    Code:
       0: aload_1
       1: ifnonnull     8
       4: iconst_1
       5: goto          9
       8: iconst_0
       9: aload_2
      10: ifnonnull     17
      13: iconst_1
      14: goto          18
      17: iconst_0
      18: ixor
      19: ifeq          32
      22: aload_1
      23: ifnonnull     30
      26: iconst_m1
      27: goto          31
      30: iconst_1
      31: ireturn
      32: aload_1
      33: ifnonnull     38
      36: iconst_0
      37: ireturn
      38: aload_1
      39: aload_2
      40: invokevirtual #7                  // Method java/lang/Double.compareTo:(Ljava/lang/Double;)I
      43: ireturn

  public java.lang.Double getMaxValue();
    Code:
       0: ldc2_w        #9                  // double 1.7976931348623157E308d
       3: invokestatic  #5                  // Method java/lang/Double.valueOf:(D)Ljava/lang/Double;
       6: areturn

  public java.lang.Double increment(java.lang.Double);
    Code:
       0: aload_1
       1: ifnonnull     8
       4: aconst_null
       5: goto          17
       8: aload_1
       9: invokevirtual #6                  // Method java/lang/Double.doubleValue:()D
      12: dconst_1
      13: dadd
      14: invokestatic  #5                  // Method java/lang/Double.valueOf:(D)Ljava/lang/Double;
      17: areturn

  public java.lang.Double multiply(java.lang.Double, java.lang.Double);
    Code:
       0: aload_1
       1: ifnull        8
       4: aload_2
       5: ifnonnull     12
       8: aconst_null
       9: goto          24
      12: aload_1
      13: invokevirtual #6                  // Method java/lang/Double.doubleValue:()D
      16: aload_2
      17: invokevirtual #6                  // Method java/lang/Double.doubleValue:()D
      20: dmul
      21: invokestatic  #5                  // Method java/lang/Double.valueOf:(D)Ljava/lang/Double;
      24: areturn

  public java.lang.Double getMinValue();
    Code:
       0: ldc2_w        #11                 // double 4.9E-324d
       3: invokestatic  #5                  // Method java/lang/Double.valueOf:(D)Ljava/lang/Double;
       6: areturn

  public double divideForAvg(java.lang.Double, java.lang.Long);
    Code:
       0: aload_2
       1: ifnull        8
       4: aload_1
       5: ifnonnull     14
       8: ldc2_w        #13                 // double NaNd
      11: goto          23
      14: aload_1
      15: invokevirtual #6                  // Method java/lang/Double.doubleValue:()D
      18: aload_2
      19: invokevirtual #15                 // Method java/lang/Long.doubleValue:()D
      22: ddiv
      23: dreturn

  public java.lang.Double castToReturnType(java.lang.Double);
    Code:
       0: aload_1
       1: areturn

  public java.lang.Double castToCellType(java.lang.Double);
    Code:
       0: aload_1
       1: areturn

  public org.apache.hadoop.hbase.protobuf.generated.HBaseProtos$EmptyMsg getRequestData();
    Code:
       0: invokestatic  #16                 // Method org/apache/hadoop/hbase/protobuf/generated/HBaseProtos$EmptyMsg.getDefaultInstance:()Lorg/apache/hadoop/hbase/protobuf/generated/HBaseProtos$EmptyMsg;
       3: areturn

  public void initialize(org.apache.hadoop.hbase.protobuf.generated.HBaseProtos$EmptyMsg);
    Code:
       0: return

  public org.apache.hadoop.hbase.protobuf.generated.HBaseProtos$DoubleMsg getProtoForCellType(java.lang.Double);
    Code:
       0: invokestatic  #17                 // Method org/apache/hadoop/hbase/protobuf/generated/HBaseProtos$DoubleMsg.newBuilder:()Lorg/apache/hadoop/hbase/protobuf/generated/HBaseProtos$DoubleMsg$Builder;
       3: astore_2
       4: aload_2
       5: aload_1
       6: invokevirtual #6                  // Method java/lang/Double.doubleValue:()D
       9: invokevirtual #18                 // Method org/apache/hadoop/hbase/protobuf/generated/HBaseProtos$DoubleMsg$Builder.setDoubleMsg:(D)Lorg/apache/hadoop/hbase/protobuf/generated/HBaseProtos$DoubleMsg$Builder;
      12: invokevirtual #19                 // Method org/apache/hadoop/hbase/protobuf/generated/HBaseProtos$DoubleMsg$Builder.build:()Lorg/apache/hadoop/hbase/protobuf/generated/HBaseProtos$DoubleMsg;
      15: areturn

  public org.apache.hadoop.hbase.protobuf.generated.HBaseProtos$DoubleMsg getProtoForPromotedType(java.lang.Double);
    Code:
       0: invokestatic  #17                 // Method org/apache/hadoop/hbase/protobuf/generated/HBaseProtos$DoubleMsg.newBuilder:()Lorg/apache/hadoop/hbase/protobuf/generated/HBaseProtos$DoubleMsg$Builder;
       3: astore_2
       4: aload_2
       5: aload_1
       6: invokevirtual #6                  // Method java/lang/Double.doubleValue:()D
       9: invokevirtual #18                 // Method org/apache/hadoop/hbase/protobuf/generated/HBaseProtos$DoubleMsg$Builder.setDoubleMsg:(D)Lorg/apache/hadoop/hbase/protobuf/generated/HBaseProtos$DoubleMsg$Builder;
      12: invokevirtual #19                 // Method org/apache/hadoop/hbase/protobuf/generated/HBaseProtos$DoubleMsg$Builder.build:()Lorg/apache/hadoop/hbase/protobuf/generated/HBaseProtos$DoubleMsg;
      15: areturn

  public java.lang.Double getPromotedValueFromProto(org.apache.hadoop.hbase.protobuf.generated.HBaseProtos$DoubleMsg);
    Code:
       0: aload_1
       1: invokevirtual #20                 // Method org/apache/hadoop/hbase/protobuf/generated/HBaseProtos$DoubleMsg.getDoubleMsg:()D
       4: invokestatic  #5                  // Method java/lang/Double.valueOf:(D)Ljava/lang/Double;
       7: areturn

  public java.lang.Double getCellValueFromProto(org.apache.hadoop.hbase.protobuf.generated.HBaseProtos$DoubleMsg);
    Code:
       0: aload_1
       1: invokevirtual #20                 // Method org/apache/hadoop/hbase/protobuf/generated/HBaseProtos$DoubleMsg.getDoubleMsg:()D
       4: invokestatic  #5                  // Method java/lang/Double.valueOf:(D)Ljava/lang/Double;
       7: areturn

  public java.lang.Object castToCellType(java.lang.Object);
    Code:
       0: aload_0
       1: aload_1
       2: checkcast     #8                  // class java/lang/Double
       5: invokevirtual #21                 // Method castToCellType:(Ljava/lang/Double;)Ljava/lang/Double;
       8: areturn

  public java.lang.Object getPromotedValueFromProto(com.google.protobuf.Message);
    Code:
       0: aload_0
       1: aload_1
       2: checkcast     #22                 // class org/apache/hadoop/hbase/protobuf/generated/HBaseProtos$DoubleMsg
       5: invokevirtual #23                 // Method getPromotedValueFromProto:(Lorg/apache/hadoop/hbase/protobuf/generated/HBaseProtos$DoubleMsg;)Ljava/lang/Double;
       8: areturn

  public com.google.protobuf.Message getProtoForPromotedType(java.lang.Object);
    Code:
       0: aload_0
       1: aload_1
       2: checkcast     #8                  // class java/lang/Double
       5: invokevirtual #24                 // Method getProtoForPromotedType:(Ljava/lang/Double;)Lorg/apache/hadoop/hbase/protobuf/generated/HBaseProtos$DoubleMsg;
       8: areturn

  public java.lang.Object getCellValueFromProto(com.google.protobuf.Message);
    Code:
       0: aload_0
       1: aload_1
       2: checkcast     #22                 // class org/apache/hadoop/hbase/protobuf/generated/HBaseProtos$DoubleMsg
       5: invokevirtual #25                 // Method getCellValueFromProto:(Lorg/apache/hadoop/hbase/protobuf/generated/HBaseProtos$DoubleMsg;)Ljava/lang/Double;
       8: areturn

  public com.google.protobuf.Message getProtoForCellType(java.lang.Object);
    Code:
       0: aload_0
       1: aload_1
       2: checkcast     #8                  // class java/lang/Double
       5: invokevirtual #26                 // Method getProtoForCellType:(Ljava/lang/Double;)Lorg/apache/hadoop/hbase/protobuf/generated/HBaseProtos$DoubleMsg;
       8: areturn

  public void initialize(com.google.protobuf.Message);
    Code:
       0: aload_0
       1: aload_1
       2: checkcast     #27                 // class org/apache/hadoop/hbase/protobuf/generated/HBaseProtos$EmptyMsg
       5: invokevirtual #28                 // Method initialize:(Lorg/apache/hadoop/hbase/protobuf/generated/HBaseProtos$EmptyMsg;)V
       8: return

  public com.google.protobuf.Message getRequestData();
    Code:
       0: aload_0
       1: invokevirtual #29                 // Method getRequestData:()Lorg/apache/hadoop/hbase/protobuf/generated/HBaseProtos$EmptyMsg;
       4: areturn

  public double divideForAvg(java.lang.Object, java.lang.Long);
    Code:
       0: aload_0
       1: aload_1
       2: checkcast     #8                  // class java/lang/Double
       5: aload_2
       6: invokevirtual #30                 // Method divideForAvg:(Ljava/lang/Double;Ljava/lang/Long;)D
       9: dreturn

  public int compare(java.lang.Object, java.lang.Object);
    Code:
       0: aload_0
       1: aload_1
       2: checkcast     #8                  // class java/lang/Double
       5: aload_2
       6: checkcast     #8                  // class java/lang/Double
       9: invokevirtual #31                 // Method compare:(Ljava/lang/Double;Ljava/lang/Double;)I
      12: ireturn

  public java.lang.Object castToReturnType(java.lang.Object);
    Code:
       0: aload_0
       1: aload_1
       2: checkcast     #8                  // class java/lang/Double
       5: invokevirtual #32                 // Method castToReturnType:(Ljava/lang/Double;)Ljava/lang/Double;
       8: areturn

  public java.lang.Object increment(java.lang.Object);
    Code:
       0: aload_0
       1: aload_1
       2: checkcast     #8                  // class java/lang/Double
       5: invokevirtual #33                 // Method increment:(Ljava/lang/Double;)Ljava/lang/Double;
       8: areturn

  public java.lang.Object multiply(java.lang.Object, java.lang.Object);
    Code:
       0: aload_0
       1: aload_1
       2: checkcast     #8                  // class java/lang/Double
       5: aload_2
       6: checkcast     #8                  // class java/lang/Double
       9: invokevirtual #34                 // Method multiply:(Ljava/lang/Double;Ljava/lang/Double;)Ljava/lang/Double;
      12: areturn

  public java.lang.Object getMinValue();
    Code:
       0: aload_0
       1: invokevirtual #35                 // Method getMinValue:()Ljava/lang/Double;
       4: areturn

  public java.lang.Object getMaxValue();
    Code:
       0: aload_0
       1: invokevirtual #36                 // Method getMaxValue:()Ljava/lang/Double;
       4: areturn

  public java.lang.Object add(java.lang.Object, java.lang.Object);
    Code:
       0: aload_0
       1: aload_1
       2: checkcast     #8                  // class java/lang/Double
       5: aload_2
       6: checkcast     #8                  // class java/lang/Double
       9: invokevirtual #37                 // Method add:(Ljava/lang/Double;Ljava/lang/Double;)Ljava/lang/Double;
      12: areturn

  public java.lang.Object getValue(byte[], byte[], org.apache.hadoop.hbase.Cell) throws java.io.IOException;
    Code:
       0: aload_0
       1: aload_1
       2: aload_2
       3: aload_3
       4: invokevirtual #38                 // Method getValue:([B[BLorg/apache/hadoop/hbase/Cell;)Ljava/lang/Double;
       7: areturn
}
