Compiled from "DropwizardMeter.java"
public class org.apache.hadoop.hbase.metrics.impl.DropwizardMeter implements org.apache.hadoop.hbase.metrics.Meter {
  public org.apache.hadoop.hbase.metrics.impl.DropwizardMeter();
    Code:
       0: aload_0
       1: invokespecial #1                  // Method java/lang/Object."<init>":()V
       4: aload_0
       5: new           #2                  // class com/codahale/metrics/Meter
       8: dup
       9: invokespecial #3                  // Method com/codahale/metrics/Meter."<init>":()V
      12: putfield      #4                  // Field meter:Lcom/codahale/metrics/Meter;
      15: return

  public org.apache.hadoop.hbase.metrics.impl.DropwizardMeter(com.codahale.metrics.Meter);
    Code:
       0: aload_0
       1: invokespecial #1                  // Method java/lang/Object."<init>":()V
       4: aload_0
       5: aload_1
       6: invokestatic  #5                  // Method java/util/Objects.requireNonNull:(Ljava/lang/Object;)Ljava/lang/Object;
       9: checkcast     #2                  // class com/codahale/metrics/Meter
      12: putfield      #4                  // Field meter:Lcom/codahale/metrics/Meter;
      15: return

  public void mark();
    Code:
       0: aload_0
       1: getfield      #4                  // Field meter:Lcom/codahale/metrics/Meter;
       4: invokevirtual #6                  // Method com/codahale/metrics/Meter.mark:()V
       7: return

  public void mark(long);
    Code:
       0: aload_0
       1: getfield      #4                  // Field meter:Lcom/codahale/metrics/Meter;
       4: lload_1
       5: invokevirtual #7                  // Method com/codahale/metrics/Meter.mark:(J)V
       8: return

  public long getCount();
    Code:
       0: aload_0
       1: getfield      #4                  // Field meter:Lcom/codahale/metrics/Meter;
       4: invokevirtual #8                  // Method com/codahale/metrics/Meter.getCount:()J
       7: lreturn

  public double getMeanRate();
    Code:
       0: aload_0
       1: getfield      #4                  // Field meter:Lcom/codahale/metrics/Meter;
       4: invokevirtual #9                  // Method com/codahale/metrics/Meter.getMeanRate:()D
       7: dreturn

  public double getOneMinuteRate();
    Code:
       0: aload_0
       1: getfield      #4                  // Field meter:Lcom/codahale/metrics/Meter;
       4: invokevirtual #10                 // Method com/codahale/metrics/Meter.getOneMinuteRate:()D
       7: dreturn

  public double getFiveMinuteRate();
    Code:
       0: aload_0
       1: getfield      #4                  // Field meter:Lcom/codahale/metrics/Meter;
       4: invokevirtual #11                 // Method com/codahale/metrics/Meter.getFiveMinuteRate:()D
       7: dreturn

  public double getFifteenMinuteRate();
    Code:
       0: aload_0
       1: getfield      #4                  // Field meter:Lcom/codahale/metrics/Meter;
       4: invokevirtual #12                 // Method com/codahale/metrics/Meter.getFifteenMinuteRate:()D
       7: dreturn
}
