Compiled from "DumpReplicationQueues.java"
class org.apache.hadoop.hbase.replication.regionserver.DumpReplicationQueues$WarnOnlyStoppable implements org.apache.hadoop.hbase.Stoppable {
  public void stop(java.lang.String);
    Code:
       0: invokestatic  #3                  // Method org/apache/hadoop/hbase/replication/regionserver/DumpReplicationQueues.access$200:()Lorg/slf4j/Logger;
       3: new           #4                  // class java/lang/StringBuilder
       6: dup
       7: invokespecial #5                  // Method java/lang/StringBuilder."<init>":()V
      10: ldc           #6                  // String DumpReplicationQueue received stop, ignoring.  Reason:
      12: invokevirtual #7                  // Method java/lang/StringBuilder.append:(Ljava/lang/String;)Ljava/lang/StringBuilder;
      15: aload_1
      16: invokevirtual #7                  // Method java/lang/StringBuilder.append:(Ljava/lang/String;)Ljava/lang/StringBuilder;
      19: invokevirtual #8                  // Method java/lang/StringBuilder.toString:()Ljava/lang/String;
      22: invokeinterface #9,  2            // InterfaceMethod org/slf4j/Logger.warn:(Ljava/lang/String;)V
      27: return

  public boolean isStopped();
    Code:
       0: iconst_0
       1: ireturn

  org.apache.hadoop.hbase.replication.regionserver.DumpReplicationQueues$WarnOnlyStoppable(org.apache.hadoop.hbase.replication.regionserver.DumpReplicationQueues$1);
    Code:
       0: aload_0
       1: invokespecial #1                  // Method "<init>":()V
       4: return
}
