Compiled from "EncodedDataBlock.java"
public class org.apache.hadoop.hbase.io.encoding.EncodedDataBlock {
  public org.apache.hadoop.hbase.io.encoding.EncodedDataBlock(org.apache.hadoop.hbase.io.encoding.DataBlockEncoder, org.apache.hadoop.hbase.io.encoding.DataBlockEncoding, byte[], org.apache.hadoop.hbase.io.hfile.HFileContext);
    Code:
       0: aload_0
       1: invokespecial #5                  // Method java/lang/Object."<init>":()V
       4: aload_0
       5: new           #6                  // class java/util/ArrayList
       8: dup
       9: invokespecial #7                  // Method java/util/ArrayList."<init>":()V
      12: putfield      #4                  // Field isTagsLenZero:Ljava/util/List;
      15: aload_2
      16: ldc           #8                  // String Cannot create encoded data block with null encoder
      18: invokestatic  #9                  // Method org/apache/hbase/thirdparty/com/google/common/base/Preconditions.checkNotNull:(Ljava/lang/Object;Ljava/lang/Object;)Ljava/lang/Object;
      21: pop
      22: aload_0
      23: aload_1
      24: putfield      #2                  // Field dataBlockEncoder:Lorg/apache/hadoop/hbase/io/encoding/DataBlockEncoder;
      27: aload_0
      28: aload_2
      29: putfield      #1                  // Field encoding:Lorg/apache/hadoop/hbase/io/encoding/DataBlockEncoding;
      32: aload_0
      33: aload_1
      34: aload_2
      35: getstatic     #10                 // Field org/apache/hadoop/hbase/HConstants.HFILEBLOCK_DUMMY_HEADER:[B
      38: aload         4
      40: invokeinterface #11,  4           // InterfaceMethod org/apache/hadoop/hbase/io/encoding/DataBlockEncoder.newDataBlockEncodingContext:(Lorg/apache/hadoop/hbase/io/encoding/DataBlockEncoding;[BLorg/apache/hadoop/hbase/io/hfile/HFileContext;)Lorg/apache/hadoop/hbase/io/encoding/HFileBlockEncodingContext;
      45: putfield      #12                 // Field encodingCtx:Lorg/apache/hadoop/hbase/io/encoding/HFileBlockEncodingContext;
      48: aload_0
      49: aload_3
      50: putfield      #13                 // Field rawKVs:[B
      53: aload_0
      54: aload         4
      56: putfield      #3                  // Field meta:Lorg/apache/hadoop/hbase/io/hfile/HFileContext;
      59: return

  public java.util.Iterator<org.apache.hadoop.hbase.Cell> getIterator(int);
    Code:
       0: aload_0
       1: getfield      #13                 // Field rawKVs:[B
       4: arraylength
       5: istore_2
       6: aload_0
       7: invokespecial #14                 // Method getEncodedData:()[B
      10: astore_3
      11: iload_1
      12: iconst_2
      13: iadd
      14: istore        4
      16: new           #16                 // class java/io/ByteArrayInputStream
      19: dup
      20: aload_3
      21: iload         4
      23: aload_3
      24: arraylength
      25: iload         4
      27: isub
      28: invokespecial #17                 // Method java/io/ByteArrayInputStream."<init>":([BII)V
      31: astore        5
      33: new           #18                 // class java/io/DataInputStream
      36: dup
      37: aload         5
      39: invokespecial #19                 // Method java/io/DataInputStream."<init>":(Ljava/io/InputStream;)V
      42: astore        6
      44: new           #20                 // class org/apache/hadoop/hbase/io/encoding/EncodedDataBlock$1
      47: dup
      48: aload_0
      49: iload_2
      50: aload         6
      52: invokespecial #21                 // Method org/apache/hadoop/hbase/io/encoding/EncodedDataBlock$1."<init>":(Lorg/apache/hadoop/hbase/io/encoding/EncodedDataBlock;ILjava/io/DataInputStream;)V
      55: areturn

  public int getSize();
    Code:
       0: aload_0
       1: invokespecial #14                 // Method getEncodedData:()[B
       4: arraylength
       5: ireturn

  public static int getCompressedSize(org.apache.hadoop.hbase.io.compress.Compression$Algorithm, org.apache.hadoop.io.compress.Compressor, byte[], int, int) throws java.io.IOException;
    Code:
       0: new           #22                 // class org/apache/hadoop/io/IOUtils$NullOutputStream
       3: dup
       4: invokespecial #23                 // Method org/apache/hadoop/io/IOUtils$NullOutputStream."<init>":()V
       7: astore        5
       9: new           #24                 // class java/io/DataOutputStream
      12: dup
      13: aload         5
      15: invokespecial #25                 // Method java/io/DataOutputStream."<init>":(Ljava/io/OutputStream;)V
      18: astore        6
      20: aconst_null
      21: astore        7
      23: aload_1
      24: ifnull        33
      27: aload_1
      28: invokeinterface #26,  1           // InterfaceMethod org/apache/hadoop/io/compress/Compressor.reset:()V
      33: aload_0
      34: aload         6
      36: aload_1
      37: iconst_0
      38: invokevirtual #27                 // Method org/apache/hadoop/hbase/io/compress/Compression$Algorithm.createCompressionStream:(Ljava/io/OutputStream;Lorg/apache/hadoop/io/compress/Compressor;I)Ljava/io/OutputStream;
      41: astore        7
      43: aload         7
      45: aload_2
      46: iload_3
      47: iload         4
      49: invokevirtual #28                 // Method java/io/OutputStream.write:([BII)V
      52: aload         7
      54: invokevirtual #29                 // Method java/io/OutputStream.flush:()V
      57: aload         6
      59: invokevirtual #30                 // Method java/io/DataOutputStream.size:()I
      62: istore        8
      64: aload         5
      66: invokevirtual #31                 // Method org/apache/hadoop/io/IOUtils$NullOutputStream.close:()V
      69: aload         6
      71: invokevirtual #32                 // Method java/io/DataOutputStream.close:()V
      74: aload         7
      76: invokevirtual #33                 // Method java/io/OutputStream.close:()V
      79: iload         8
      81: ireturn
      82: astore        9
      84: aload         5
      86: invokevirtual #31                 // Method org/apache/hadoop/io/IOUtils$NullOutputStream.close:()V
      89: aload         6
      91: invokevirtual #32                 // Method java/io/DataOutputStream.close:()V
      94: aload         7
      96: invokevirtual #33                 // Method java/io/OutputStream.close:()V
      99: aload         9
     101: athrow
    Exception table:
       from    to  target type
          23    64    82   any
          82    84    82   any

  public int getEncodedCompressedSize(org.apache.hadoop.hbase.io.compress.Compression$Algorithm, org.apache.hadoop.io.compress.Compressor) throws java.io.IOException;
    Code:
       0: aload_0
       1: invokespecial #14                 // Method getEncodedData:()[B
       4: astore_3
       5: aload_1
       6: aload_2
       7: aload_3
       8: iconst_0
       9: aload_3
      10: arraylength
      11: invokestatic  #34                 // Method getCompressedSize:(Lorg/apache/hadoop/hbase/io/compress/Compression$Algorithm;Lorg/apache/hadoop/io/compress/Compressor;[BII)I
      14: ireturn

  public byte[] encodeData();
    Code:
       0: new           #40                 // class java/io/ByteArrayOutputStream
       3: dup
       4: invokespecial #41                 // Method java/io/ByteArrayOutputStream."<init>":()V
       7: astore_1
       8: aconst_null
       9: astore_2
      10: aload_1
      11: getstatic     #10                 // Field org/apache/hadoop/hbase/HConstants.HFILEBLOCK_DUMMY_HEADER:[B
      14: invokevirtual #42                 // Method java/io/ByteArrayOutputStream.write:([B)V
      17: new           #24                 // class java/io/DataOutputStream
      20: dup
      21: aload_1
      22: invokespecial #25                 // Method java/io/DataOutputStream."<init>":(Ljava/io/OutputStream;)V
      25: astore_3
      26: aload_0
      27: getfield      #2                  // Field dataBlockEncoder:Lorg/apache/hadoop/hbase/io/encoding/DataBlockEncoder;
      30: aload_0
      31: getfield      #12                 // Field encodingCtx:Lorg/apache/hadoop/hbase/io/encoding/HFileBlockEncodingContext;
      34: aload_3
      35: invokeinterface #43,  3           // InterfaceMethod org/apache/hadoop/hbase/io/encoding/DataBlockEncoder.startBlockEncoding:(Lorg/apache/hadoop/hbase/io/encoding/HFileBlockEncodingContext;Ljava/io/DataOutputStream;)V
      40: aload_0
      41: invokespecial #44                 // Method getUncompressedBuffer:()Ljava/nio/ByteBuffer;
      44: astore        4
      46: aload         4
      48: invokevirtual #45                 // Method java/nio/ByteBuffer.rewind:()Ljava/nio/Buffer;
      51: pop
      52: iconst_0
      53: istore        7
      55: lconst_0
      56: lstore        8
      58: aconst_null
      59: astore        10
      61: aload         4
      63: invokevirtual #46                 // Method java/nio/ByteBuffer.hasRemaining:()Z
      66: ifeq          234
      69: aload         4
      71: invokevirtual #47                 // Method java/nio/ByteBuffer.position:()I
      74: istore        11
      76: aload         4
      78: invokevirtual #48                 // Method java/nio/ByteBuffer.getInt:()I
      81: istore        5
      83: aload         4
      85: invokevirtual #48                 // Method java/nio/ByteBuffer.getInt:()I
      88: istore        6
      90: aload         4
      92: iload         5
      94: iload         6
      96: iadd
      97: invokestatic  #49                 // Method org/apache/hadoop/hbase/util/ByteBufferUtils.skip:(Ljava/nio/ByteBuffer;I)V
     100: aload_0
     101: getfield      #3                  // Field meta:Lorg/apache/hadoop/hbase/io/hfile/HFileContext;
     104: invokevirtual #50                 // Method org/apache/hadoop/hbase/io/hfile/HFileContext.isIncludesTags:()Z
     107: ifeq          164
     110: aload         4
     112: invokevirtual #51                 // Method java/nio/ByteBuffer.get:()B
     115: sipush        255
     118: iand
     119: bipush        8
     121: ishl
     122: aload         4
     124: invokevirtual #51                 // Method java/nio/ByteBuffer.get:()B
     127: sipush        255
     130: iand
     131: ixor
     132: istore        7
     134: aload         4
     136: iload         7
     138: invokestatic  #49                 // Method org/apache/hadoop/hbase/util/ByteBufferUtils.skip:(Ljava/nio/ByteBuffer;I)V
     141: aload_0
     142: getfield      #4                  // Field isTagsLenZero:Ljava/util/List;
     145: iload         7
     147: ifne          154
     150: iconst_1
     151: goto          155
     154: iconst_0
     155: invokestatic  #52                 // Method java/lang/Boolean.valueOf:(Z)Ljava/lang/Boolean;
     158: invokeinterface #53,  2           // InterfaceMethod java/util/List.add:(Ljava/lang/Object;)Z
     163: pop
     164: aload_0
     165: getfield      #3                  // Field meta:Lorg/apache/hadoop/hbase/io/hfile/HFileContext;
     168: invokevirtual #54                 // Method org/apache/hadoop/hbase/io/hfile/HFileContext.isIncludesMvcc:()Z
     171: ifeq          181
     174: aload         4
     176: invokestatic  #55                 // Method org/apache/hadoop/hbase/util/ByteBufferUtils.readVLong:(Ljava/nio/ByteBuffer;)J
     179: lstore        8
     181: new           #56                 // class org/apache/hadoop/hbase/KeyValue
     184: dup
     185: aload         4
     187: invokevirtual #57                 // Method java/nio/ByteBuffer.array:()[B
     190: iload         11
     192: iload         5
     194: iload         6
     196: iload         7
     198: invokestatic  #58                 // Method org/apache/hadoop/hbase/KeyValue.getKeyValueDataStructureSize:(III)J
     201: l2i
     202: invokespecial #59                 // Method org/apache/hadoop/hbase/KeyValue."<init>":([BII)V
     205: astore        10
     207: aload         10
     209: lload         8
     211: invokevirtual #60                 // Method org/apache/hadoop/hbase/KeyValue.setSequenceId:(J)V
     214: aload_0
     215: getfield      #2                  // Field dataBlockEncoder:Lorg/apache/hadoop/hbase/io/encoding/DataBlockEncoder;
     218: aload         10
     220: aload_0
     221: getfield      #12                 // Field encodingCtx:Lorg/apache/hadoop/hbase/io/encoding/HFileBlockEncodingContext;
     224: aload_3
     225: invokeinterface #61,  4           // InterfaceMethod org/apache/hadoop/hbase/io/encoding/DataBlockEncoder.encode:(Lorg/apache/hadoop/hbase/Cell;Lorg/apache/hadoop/hbase/io/encoding/HFileBlockEncodingContext;Ljava/io/DataOutputStream;)I
     230: pop
     231: goto          61
     234: aload_1
     235: invokevirtual #62                 // Method java/io/ByteArrayOutputStream.flush:()V
     238: aload_1
     239: invokevirtual #63                 // Method java/io/ByteArrayOutputStream.toByteArray:()[B
     242: astore_2
     243: aload_0
     244: getfield      #2                  // Field dataBlockEncoder:Lorg/apache/hadoop/hbase/io/encoding/DataBlockEncoder;
     247: aload_0
     248: getfield      #12                 // Field encodingCtx:Lorg/apache/hadoop/hbase/io/encoding/HFileBlockEncodingContext;
     251: aload_3
     252: aload_2
     253: invokeinterface #64,  4           // InterfaceMethod org/apache/hadoop/hbase/io/encoding/DataBlockEncoder.endBlockEncoding:(Lorg/apache/hadoop/hbase/io/encoding/HFileBlockEncodingContext;Ljava/io/DataOutputStream;[B)V
     258: aload_0
     259: getfield      #1                  // Field encoding:Lorg/apache/hadoop/hbase/io/encoding/DataBlockEncoding;
     262: getstatic     #65                 // Field org/apache/hadoop/hbase/io/encoding/DataBlockEncoding.ROW_INDEX_V1:Lorg/apache/hadoop/hbase/io/encoding/DataBlockEncoding;
     265: invokevirtual #66                 // Method org/apache/hadoop/hbase/io/encoding/DataBlockEncoding.equals:(Ljava/lang/Object;)Z
     268: ifeq          276
     271: aload_1
     272: invokevirtual #63                 // Method java/io/ByteArrayOutputStream.toByteArray:()[B
     275: astore_2
     276: goto          305
     279: astore_3
     280: new           #68                 // class java/lang/RuntimeException
     283: dup
     284: ldc           #69                 // String Bug in encoding part of algorithm %s. Probably it requested more bytes than are available.
     286: iconst_1
     287: anewarray     #70                 // class java/lang/Object
     290: dup
     291: iconst_0
     292: aload_0
     293: invokevirtual #71                 // Method toString:()Ljava/lang/String;
     296: aastore
     297: invokestatic  #72                 // Method java/lang/String.format:(Ljava/lang/String;[Ljava/lang/Object;)Ljava/lang/String;
     300: aload_3
     301: invokespecial #73                 // Method java/lang/RuntimeException."<init>":(Ljava/lang/String;Ljava/lang/Throwable;)V
     304: athrow
     305: aload_2
     306: areturn
    Exception table:
       from    to  target type
          10   276   279   Class java/io/IOException

  public java.lang.String toString();
    Code:
       0: aload_0
       1: getfield      #1                  // Field encoding:Lorg/apache/hadoop/hbase/io/encoding/DataBlockEncoding;
       4: invokevirtual #74                 // Method org/apache/hadoop/hbase/io/encoding/DataBlockEncoding.name:()Ljava/lang/String;
       7: areturn

  static java.util.List access$000(org.apache.hadoop.hbase.io.encoding.EncodedDataBlock);
    Code:
       0: aload_0
       1: getfield      #4                  // Field isTagsLenZero:Ljava/util/List;
       4: areturn

  static org.apache.hadoop.hbase.io.hfile.HFileContext access$100(org.apache.hadoop.hbase.io.encoding.EncodedDataBlock);
    Code:
       0: aload_0
       1: getfield      #3                  // Field meta:Lorg/apache/hadoop/hbase/io/hfile/HFileContext;
       4: areturn

  static org.apache.hadoop.hbase.io.encoding.DataBlockEncoder access$200(org.apache.hadoop.hbase.io.encoding.EncodedDataBlock);
    Code:
       0: aload_0
       1: getfield      #2                  // Field dataBlockEncoder:Lorg/apache/hadoop/hbase/io/encoding/DataBlockEncoder;
       4: areturn

  static org.apache.hadoop.hbase.io.encoding.DataBlockEncoding access$300(org.apache.hadoop.hbase.io.encoding.EncodedDataBlock);
    Code:
       0: aload_0
       1: getfield      #1                  // Field encoding:Lorg/apache/hadoop/hbase/io/encoding/DataBlockEncoding;
       4: areturn
}
