Compiled from "EncryptionTest.java"
public class org.apache.hadoop.hbase.util.EncryptionTest {
  static final java.util.Map<java.lang.String, java.lang.Boolean> keyProviderResults;

  static final java.util.Map<java.lang.String, java.lang.Boolean> cipherProviderResults;

  static final java.util.Map<java.lang.String, java.lang.Boolean> cipherResults;

  public static void testKeyProvider(org.apache.hadoop.conf.Configuration) throws java.io.IOException;
    Code:
       0: aload_0
       1: ldc           #3                  // String hbase.crypto.keyprovider
       3: ldc           #4                  // class org/apache/hadoop/hbase/io/crypto/KeyStoreKeyProvider
       5: invokevirtual #5                  // Method java/lang/Class.getName:()Ljava/lang/String;
       8: invokevirtual #6                  // Method org/apache/hadoop/conf/Configuration.get:(Ljava/lang/String;Ljava/lang/String;)Ljava/lang/String;
      11: astore_1
      12: getstatic     #7                  // Field keyProviderResults:Ljava/util/Map;
      15: aload_1
      16: invokeinterface #8,  2            // InterfaceMethod java/util/Map.get:(Ljava/lang/Object;)Ljava/lang/Object;
      21: checkcast     #9                  // class java/lang/Boolean
      24: astore_2
      25: aload_2
      26: ifnonnull     106
      29: aload_0
      30: invokestatic  #10                 // Method org/apache/hadoop/hbase/io/crypto/Encryption.getKeyProvider:(Lorg/apache/hadoop/conf/Configuration;)Lorg/apache/hadoop/hbase/io/crypto/KeyProvider;
      33: pop
      34: getstatic     #7                  // Field keyProviderResults:Ljava/util/Map;
      37: aload_1
      38: iconst_1
      39: invokestatic  #11                 // Method java/lang/Boolean.valueOf:(Z)Ljava/lang/Boolean;
      42: invokeinterface #12,  3           // InterfaceMethod java/util/Map.put:(Ljava/lang/Object;Ljava/lang/Object;)Ljava/lang/Object;
      47: pop
      48: goto          145
      51: astore_3
      52: getstatic     #7                  // Field keyProviderResults:Ljava/util/Map;
      55: aload_1
      56: iconst_0
      57: invokestatic  #11                 // Method java/lang/Boolean.valueOf:(Z)Ljava/lang/Boolean;
      60: invokeinterface #12,  3           // InterfaceMethod java/util/Map.put:(Ljava/lang/Object;Ljava/lang/Object;)Ljava/lang/Object;
      65: pop
      66: new           #14                 // class java/io/IOException
      69: dup
      70: new           #15                 // class java/lang/StringBuilder
      73: dup
      74: invokespecial #16                 // Method java/lang/StringBuilder."<init>":()V
      77: ldc           #17                 // String Key provider
      79: invokevirtual #18                 // Method java/lang/StringBuilder.append:(Ljava/lang/String;)Ljava/lang/StringBuilder;
      82: aload_1
      83: invokevirtual #18                 // Method java/lang/StringBuilder.append:(Ljava/lang/String;)Ljava/lang/StringBuilder;
      86: ldc           #19                 // String  failed test:
      88: invokevirtual #18                 // Method java/lang/StringBuilder.append:(Ljava/lang/String;)Ljava/lang/StringBuilder;
      91: aload_3
      92: invokevirtual #20                 // Method java/lang/Exception.getMessage:()Ljava/lang/String;
      95: invokevirtual #18                 // Method java/lang/StringBuilder.append:(Ljava/lang/String;)Ljava/lang/StringBuilder;
      98: invokevirtual #21                 // Method java/lang/StringBuilder.toString:()Ljava/lang/String;
     101: aload_3
     102: invokespecial #22                 // Method java/io/IOException."<init>":(Ljava/lang/String;Ljava/lang/Throwable;)V
     105: athrow
     106: aload_2
     107: invokevirtual #23                 // Method java/lang/Boolean.booleanValue:()Z
     110: ifne          145
     113: new           #14                 // class java/io/IOException
     116: dup
     117: new           #15                 // class java/lang/StringBuilder
     120: dup
     121: invokespecial #16                 // Method java/lang/StringBuilder."<init>":()V
     124: ldc           #17                 // String Key provider
     126: invokevirtual #18                 // Method java/lang/StringBuilder.append:(Ljava/lang/String;)Ljava/lang/StringBuilder;
     129: aload_1
     130: invokevirtual #18                 // Method java/lang/StringBuilder.append:(Ljava/lang/String;)Ljava/lang/StringBuilder;
     133: ldc           #24                 // String  previously failed test
     135: invokevirtual #18                 // Method java/lang/StringBuilder.append:(Ljava/lang/String;)Ljava/lang/StringBuilder;
     138: invokevirtual #21                 // Method java/lang/StringBuilder.toString:()Ljava/lang/String;
     141: invokespecial #25                 // Method java/io/IOException."<init>":(Ljava/lang/String;)V
     144: athrow
     145: return
    Exception table:
       from    to  target type
          29    48    51   Class java/lang/Exception

  public static void testCipherProvider(org.apache.hadoop.conf.Configuration) throws java.io.IOException;
    Code:
       0: aload_0
       1: ldc           #26                 // String hbase.crypto.cipherprovider
       3: ldc           #27                 // class org/apache/hadoop/hbase/io/crypto/DefaultCipherProvider
       5: invokevirtual #5                  // Method java/lang/Class.getName:()Ljava/lang/String;
       8: invokevirtual #6                  // Method org/apache/hadoop/conf/Configuration.get:(Ljava/lang/String;Ljava/lang/String;)Ljava/lang/String;
      11: astore_1
      12: getstatic     #28                 // Field cipherProviderResults:Ljava/util/Map;
      15: aload_1
      16: invokeinterface #8,  2            // InterfaceMethod java/util/Map.get:(Ljava/lang/Object;)Ljava/lang/Object;
      21: checkcast     #9                  // class java/lang/Boolean
      24: astore_2
      25: aload_2
      26: ifnonnull     106
      29: aload_0
      30: invokestatic  #29                 // Method org/apache/hadoop/hbase/io/crypto/Encryption.getCipherProvider:(Lorg/apache/hadoop/conf/Configuration;)Lorg/apache/hadoop/hbase/io/crypto/CipherProvider;
      33: pop
      34: getstatic     #28                 // Field cipherProviderResults:Ljava/util/Map;
      37: aload_1
      38: iconst_1
      39: invokestatic  #11                 // Method java/lang/Boolean.valueOf:(Z)Ljava/lang/Boolean;
      42: invokeinterface #12,  3           // InterfaceMethod java/util/Map.put:(Ljava/lang/Object;Ljava/lang/Object;)Ljava/lang/Object;
      47: pop
      48: goto          145
      51: astore_3
      52: getstatic     #28                 // Field cipherProviderResults:Ljava/util/Map;
      55: aload_1
      56: iconst_0
      57: invokestatic  #11                 // Method java/lang/Boolean.valueOf:(Z)Ljava/lang/Boolean;
      60: invokeinterface #12,  3           // InterfaceMethod java/util/Map.put:(Ljava/lang/Object;Ljava/lang/Object;)Ljava/lang/Object;
      65: pop
      66: new           #14                 // class java/io/IOException
      69: dup
      70: new           #15                 // class java/lang/StringBuilder
      73: dup
      74: invokespecial #16                 // Method java/lang/StringBuilder."<init>":()V
      77: ldc           #30                 // String Cipher provider
      79: invokevirtual #18                 // Method java/lang/StringBuilder.append:(Ljava/lang/String;)Ljava/lang/StringBuilder;
      82: aload_1
      83: invokevirtual #18                 // Method java/lang/StringBuilder.append:(Ljava/lang/String;)Ljava/lang/StringBuilder;
      86: ldc           #19                 // String  failed test:
      88: invokevirtual #18                 // Method java/lang/StringBuilder.append:(Ljava/lang/String;)Ljava/lang/StringBuilder;
      91: aload_3
      92: invokevirtual #20                 // Method java/lang/Exception.getMessage:()Ljava/lang/String;
      95: invokevirtual #18                 // Method java/lang/StringBuilder.append:(Ljava/lang/String;)Ljava/lang/StringBuilder;
      98: invokevirtual #21                 // Method java/lang/StringBuilder.toString:()Ljava/lang/String;
     101: aload_3
     102: invokespecial #22                 // Method java/io/IOException."<init>":(Ljava/lang/String;Ljava/lang/Throwable;)V
     105: athrow
     106: aload_2
     107: invokevirtual #23                 // Method java/lang/Boolean.booleanValue:()Z
     110: ifne          145
     113: new           #14                 // class java/io/IOException
     116: dup
     117: new           #15                 // class java/lang/StringBuilder
     120: dup
     121: invokespecial #16                 // Method java/lang/StringBuilder."<init>":()V
     124: ldc           #30                 // String Cipher provider
     126: invokevirtual #18                 // Method java/lang/StringBuilder.append:(Ljava/lang/String;)Ljava/lang/StringBuilder;
     129: aload_1
     130: invokevirtual #18                 // Method java/lang/StringBuilder.append:(Ljava/lang/String;)Ljava/lang/StringBuilder;
     133: ldc           #24                 // String  previously failed test
     135: invokevirtual #18                 // Method java/lang/StringBuilder.append:(Ljava/lang/String;)Ljava/lang/StringBuilder;
     138: invokevirtual #21                 // Method java/lang/StringBuilder.toString:()Ljava/lang/String;
     141: invokespecial #25                 // Method java/io/IOException."<init>":(Ljava/lang/String;)V
     144: athrow
     145: return
    Exception table:
       from    to  target type
          29    48    51   Class java/lang/Exception

  public static void testEncryption(org.apache.hadoop.conf.Configuration, java.lang.String, byte[]) throws java.io.IOException;
    Code:
       0: aload_1
       1: ifnonnull     5
       4: return
       5: aload_0
       6: invokestatic  #31                 // Method testKeyProvider:(Lorg/apache/hadoop/conf/Configuration;)V
       9: aload_0
      10: invokestatic  #32                 // Method testCipherProvider:(Lorg/apache/hadoop/conf/Configuration;)V
      13: getstatic     #33                 // Field cipherResults:Ljava/util/Map;
      16: aload_1
      17: invokeinterface #8,  2            // InterfaceMethod java/util/Map.get:(Ljava/lang/Object;)Ljava/lang/Object;
      22: checkcast     #9                  // class java/lang/Boolean
      25: astore_3
      26: aload_3
      27: ifnonnull     292
      30: aload_0
      31: invokestatic  #34                 // Method org/apache/hadoop/hbase/io/crypto/Encryption.newContext:(Lorg/apache/hadoop/conf/Configuration;)Lorg/apache/hadoop/hbase/io/crypto/Encryption$Context;
      34: astore        4
      36: aload         4
      38: aload_0
      39: aload_1
      40: invokestatic  #35                 // Method org/apache/hadoop/hbase/io/crypto/Encryption.getCipher:(Lorg/apache/hadoop/conf/Configuration;Ljava/lang/String;)Lorg/apache/hadoop/hbase/io/crypto/Cipher;
      43: invokevirtual #36                 // Method org/apache/hadoop/hbase/io/crypto/Encryption$Context.setCipher:(Lorg/apache/hadoop/hbase/io/crypto/Cipher;)Lorg/apache/hadoop/hbase/io/crypto/Encryption$Context;
      46: pop
      47: aload_2
      48: ifnonnull     68
      51: aload         4
      53: aload         4
      55: invokevirtual #37                 // Method org/apache/hadoop/hbase/io/crypto/Encryption$Context.getCipher:()Lorg/apache/hadoop/hbase/io/crypto/Cipher;
      58: invokevirtual #38                 // Method org/apache/hadoop/hbase/io/crypto/Cipher.getRandomKey:()Ljava/security/Key;
      61: invokevirtual #39                 // Method org/apache/hadoop/hbase/io/crypto/Encryption$Context.setKey:(Ljava/security/Key;)Lorg/apache/hadoop/hbase/io/crypto/Encryption$Context;
      64: pop
      65: goto          87
      68: aload         4
      70: aload_0
      71: aload_0
      72: ldc           #40                 // String hbase.crypto.master.key.name
      74: ldc           #41                 // String hbase
      76: invokevirtual #6                  // Method org/apache/hadoop/conf/Configuration.get:(Ljava/lang/String;Ljava/lang/String;)Ljava/lang/String;
      79: aload_2
      80: invokestatic  #42                 // Method org/apache/hadoop/hbase/security/EncryptionUtil.unwrapKey:(Lorg/apache/hadoop/conf/Configuration;Ljava/lang/String;[B)Ljava/security/Key;
      83: invokevirtual #39                 // Method org/apache/hadoop/hbase/io/crypto/Encryption$Context.setKey:(Ljava/security/Key;)Lorg/apache/hadoop/hbase/io/crypto/Encryption$Context;
      86: pop
      87: aconst_null
      88: astore        5
      90: aload         4
      92: invokevirtual #37                 // Method org/apache/hadoop/hbase/io/crypto/Encryption$Context.getCipher:()Lorg/apache/hadoop/hbase/io/crypto/Cipher;
      95: invokevirtual #43                 // Method org/apache/hadoop/hbase/io/crypto/Cipher.getIvLength:()I
      98: ifle          118
     101: aload         4
     103: invokevirtual #37                 // Method org/apache/hadoop/hbase/io/crypto/Encryption$Context.getCipher:()Lorg/apache/hadoop/hbase/io/crypto/Cipher;
     106: invokevirtual #43                 // Method org/apache/hadoop/hbase/io/crypto/Cipher.getIvLength:()I
     109: newarray       byte
     111: astore        5
     113: aload         5
     115: invokestatic  #44                 // Method org/apache/hadoop/hbase/util/Bytes.random:([B)V
     118: sipush        1024
     121: newarray       byte
     123: astore        6
     125: aload         6
     127: invokestatic  #44                 // Method org/apache/hadoop/hbase/util/Bytes.random:([B)V
     130: new           #45                 // class java/io/ByteArrayOutputStream
     133: dup
     134: invokespecial #46                 // Method java/io/ByteArrayOutputStream."<init>":()V
     137: astore        7
     139: aload         7
     141: new           #47                 // class java/io/ByteArrayInputStream
     144: dup
     145: aload         6
     147: invokespecial #48                 // Method java/io/ByteArrayInputStream."<init>":([B)V
     150: aload         4
     152: aload         5
     154: invokestatic  #49                 // Method org/apache/hadoop/hbase/io/crypto/Encryption.encrypt:(Ljava/io/OutputStream;Ljava/io/InputStream;Lorg/apache/hadoop/hbase/io/crypto/Encryption$Context;[B)V
     157: aload         7
     159: invokevirtual #50                 // Method java/io/ByteArrayOutputStream.toByteArray:()[B
     162: astore        8
     164: aload         7
     166: invokevirtual #51                 // Method java/io/ByteArrayOutputStream.reset:()V
     169: aload         7
     171: new           #47                 // class java/io/ByteArrayInputStream
     174: dup
     175: aload         8
     177: invokespecial #48                 // Method java/io/ByteArrayInputStream."<init>":([B)V
     180: aload         6
     182: arraylength
     183: aload         4
     185: aload         5
     187: invokestatic  #52                 // Method org/apache/hadoop/hbase/io/crypto/Encryption.decrypt:(Ljava/io/OutputStream;Ljava/io/InputStream;ILorg/apache/hadoop/hbase/io/crypto/Encryption$Context;[B)V
     190: aload         7
     192: invokevirtual #50                 // Method java/io/ByteArrayOutputStream.toByteArray:()[B
     195: astore        9
     197: aload         6
     199: aload         9
     201: invokestatic  #53                 // Method org/apache/hadoop/hbase/util/Bytes.equals:([B[B)Z
     204: ifne          217
     207: new           #14                 // class java/io/IOException
     210: dup
     211: ldc           #54                 // String Did not pass encrypt/decrypt test
     213: invokespecial #25                 // Method java/io/IOException."<init>":(Ljava/lang/String;)V
     216: athrow
     217: getstatic     #33                 // Field cipherResults:Ljava/util/Map;
     220: aload_1
     221: iconst_1
     222: invokestatic  #11                 // Method java/lang/Boolean.valueOf:(Z)Ljava/lang/Boolean;
     225: invokeinterface #12,  3           // InterfaceMethod java/util/Map.put:(Ljava/lang/Object;Ljava/lang/Object;)Ljava/lang/Object;
     230: pop
     231: goto          331
     234: astore        4
     236: getstatic     #33                 // Field cipherResults:Ljava/util/Map;
     239: aload_1
     240: iconst_0
     241: invokestatic  #11                 // Method java/lang/Boolean.valueOf:(Z)Ljava/lang/Boolean;
     244: invokeinterface #12,  3           // InterfaceMethod java/util/Map.put:(Ljava/lang/Object;Ljava/lang/Object;)Ljava/lang/Object;
     249: pop
     250: new           #14                 // class java/io/IOException
     253: dup
     254: new           #15                 // class java/lang/StringBuilder
     257: dup
     258: invokespecial #16                 // Method java/lang/StringBuilder."<init>":()V
     261: ldc           #55                 // String Cipher
     263: invokevirtual #18                 // Method java/lang/StringBuilder.append:(Ljava/lang/String;)Ljava/lang/StringBuilder;
     266: aload_1
     267: invokevirtual #18                 // Method java/lang/StringBuilder.append:(Ljava/lang/String;)Ljava/lang/StringBuilder;
     270: ldc           #19                 // String  failed test:
     272: invokevirtual #18                 // Method java/lang/StringBuilder.append:(Ljava/lang/String;)Ljava/lang/StringBuilder;
     275: aload         4
     277: invokevirtual #20                 // Method java/lang/Exception.getMessage:()Ljava/lang/String;
     280: invokevirtual #18                 // Method java/lang/StringBuilder.append:(Ljava/lang/String;)Ljava/lang/StringBuilder;
     283: invokevirtual #21                 // Method java/lang/StringBuilder.toString:()Ljava/lang/String;
     286: aload         4
     288: invokespecial #22                 // Method java/io/IOException."<init>":(Ljava/lang/String;Ljava/lang/Throwable;)V
     291: athrow
     292: aload_3
     293: invokevirtual #23                 // Method java/lang/Boolean.booleanValue:()Z
     296: ifne          331
     299: new           #14                 // class java/io/IOException
     302: dup
     303: new           #15                 // class java/lang/StringBuilder
     306: dup
     307: invokespecial #16                 // Method java/lang/StringBuilder."<init>":()V
     310: ldc           #55                 // String Cipher
     312: invokevirtual #18                 // Method java/lang/StringBuilder.append:(Ljava/lang/String;)Ljava/lang/StringBuilder;
     315: aload_1
     316: invokevirtual #18                 // Method java/lang/StringBuilder.append:(Ljava/lang/String;)Ljava/lang/StringBuilder;
     319: ldc           #24                 // String  previously failed test
     321: invokevirtual #18                 // Method java/lang/StringBuilder.append:(Ljava/lang/String;)Ljava/lang/StringBuilder;
     324: invokevirtual #21                 // Method java/lang/StringBuilder.toString:()Ljava/lang/String;
     327: invokespecial #25                 // Method java/io/IOException."<init>":(Ljava/lang/String;)V
     330: athrow
     331: return
    Exception table:
       from    to  target type
          30   231   234   Class java/lang/Exception

  static {};
    Code:
       0: ldc           #56                 // class org/apache/hadoop/hbase/util/EncryptionTest
       2: invokestatic  #57                 // Method org/slf4j/LoggerFactory.getLogger:(Ljava/lang/Class;)Lorg/slf4j/Logger;
       5: putstatic     #58                 // Field LOG:Lorg/slf4j/Logger;
       8: new           #59                 // class java/util/concurrent/ConcurrentHashMap
      11: dup
      12: invokespecial #60                 // Method java/util/concurrent/ConcurrentHashMap."<init>":()V
      15: putstatic     #7                  // Field keyProviderResults:Ljava/util/Map;
      18: new           #59                 // class java/util/concurrent/ConcurrentHashMap
      21: dup
      22: invokespecial #60                 // Method java/util/concurrent/ConcurrentHashMap."<init>":()V
      25: putstatic     #28                 // Field cipherProviderResults:Ljava/util/Map;
      28: new           #59                 // class java/util/concurrent/ConcurrentHashMap
      31: dup
      32: invokespecial #60                 // Method java/util/concurrent/ConcurrentHashMap."<init>":()V
      35: putstatic     #33                 // Field cipherResults:Ljava/util/Map;
      38: return
}
