Compiled from "Encryption.java"
public class org.apache.hadoop.hbase.io.crypto.Encryption$Context extends org.apache.hadoop.hbase.io.crypto.Context {
  public static final org.apache.hadoop.hbase.io.crypto.Encryption$Context NONE;

  public org.apache.hadoop.hbase.io.crypto.Encryption$Context setCipher(org.apache.hadoop.hbase.io.crypto.Cipher);
    Code:
       0: aload_0
       1: aload_1
       2: invokespecial #5                  // Method org/apache/hadoop/hbase/io/crypto/Context.setCipher:(Lorg/apache/hadoop/hbase/io/crypto/Cipher;)Lorg/apache/hadoop/hbase/io/crypto/Context;
       5: pop
       6: aload_0
       7: areturn

  public org.apache.hadoop.hbase.io.crypto.Encryption$Context setKey(java.security.Key);
    Code:
       0: aload_0
       1: aload_1
       2: invokespecial #6                  // Method org/apache/hadoop/hbase/io/crypto/Context.setKey:(Ljava/security/Key;)Lorg/apache/hadoop/hbase/io/crypto/Context;
       5: pop
       6: aload_0
       7: areturn

  public org.apache.hadoop.hbase.io.crypto.Encryption$Context setKey(byte[]);
    Code:
       0: aload_0
       1: new           #7                  // class javax/crypto/spec/SecretKeySpec
       4: dup
       5: aload_1
       6: aload_0
       7: invokevirtual #8                  // Method getCipher:()Lorg/apache/hadoop/hbase/io/crypto/Cipher;
      10: invokevirtual #9                  // Method org/apache/hadoop/hbase/io/crypto/Cipher.getName:()Ljava/lang/String;
      13: invokespecial #10                 // Method javax/crypto/spec/SecretKeySpec."<init>":([BLjava/lang/String;)V
      16: invokespecial #6                  // Method org/apache/hadoop/hbase/io/crypto/Context.setKey:(Ljava/security/Key;)Lorg/apache/hadoop/hbase/io/crypto/Context;
      19: pop
      20: aload_0
      21: areturn

  public org.apache.hadoop.hbase.io.crypto.Context setKey(java.security.Key);
    Code:
       0: aload_0
       1: aload_1
       2: invokevirtual #11                 // Method setKey:(Ljava/security/Key;)Lorg/apache/hadoop/hbase/io/crypto/Encryption$Context;
       5: areturn

  public org.apache.hadoop.hbase.io.crypto.Context setCipher(org.apache.hadoop.hbase.io.crypto.Cipher);
    Code:
       0: aload_0
       1: aload_1
       2: invokevirtual #12                 // Method setCipher:(Lorg/apache/hadoop/hbase/io/crypto/Cipher;)Lorg/apache/hadoop/hbase/io/crypto/Encryption$Context;
       5: areturn

  org.apache.hadoop.hbase.io.crypto.Encryption$Context(org.apache.hadoop.hbase.io.crypto.Encryption$1);
    Code:
       0: aload_0
       1: invokespecial #2                  // Method "<init>":()V
       4: return

  org.apache.hadoop.hbase.io.crypto.Encryption$Context(org.apache.hadoop.conf.Configuration, org.apache.hadoop.hbase.io.crypto.Encryption$1);
    Code:
       0: aload_0
       1: aload_1
       2: invokespecial #1                  // Method "<init>":(Lorg/apache/hadoop/conf/Configuration;)V
       5: return

  static {};
    Code:
       0: new           #13                 // class org/apache/hadoop/hbase/io/crypto/Encryption$Context
       3: dup
       4: invokespecial #2                  // Method "<init>":()V
       7: putstatic     #14                 // Field NONE:Lorg/apache/hadoop/hbase/io/crypto/Encryption$Context;
      10: return
}
