Compiled from "Encryption.java"
public final class org.apache.hadoop.hbase.io.crypto.Encryption {
  static final java.util.Map<org.apache.hadoop.hbase.util.Pair<java.lang.String, java.lang.String>, org.apache.hadoop.hbase.io.crypto.KeyProvider> keyProviderCache;

  public static org.apache.hadoop.hbase.io.crypto.Encryption$Context newContext();
    Code:
       0: new           #1                  // class org/apache/hadoop/hbase/io/crypto/Encryption$Context
       3: dup
       4: aconst_null
       5: invokespecial #2                  // Method org/apache/hadoop/hbase/io/crypto/Encryption$Context."<init>":(Lorg/apache/hadoop/hbase/io/crypto/Encryption$1;)V
       8: areturn

  public static org.apache.hadoop.hbase.io.crypto.Encryption$Context newContext(org.apache.hadoop.conf.Configuration);
    Code:
       0: new           #1                  // class org/apache/hadoop/hbase/io/crypto/Encryption$Context
       3: dup
       4: aload_0
       5: aconst_null
       6: invokespecial #3                  // Method org/apache/hadoop/hbase/io/crypto/Encryption$Context."<init>":(Lorg/apache/hadoop/conf/Configuration;Lorg/apache/hadoop/hbase/io/crypto/Encryption$1;)V
       9: areturn

  public static org.apache.hadoop.hbase.io.crypto.Cipher getCipher(org.apache.hadoop.conf.Configuration, java.lang.String);
    Code:
       0: aload_0
       1: invokestatic  #5                  // Method getCipherProvider:(Lorg/apache/hadoop/conf/Configuration;)Lorg/apache/hadoop/hbase/io/crypto/CipherProvider;
       4: aload_1
       5: invokeinterface #6,  2            // InterfaceMethod org/apache/hadoop/hbase/io/crypto/CipherProvider.getCipher:(Ljava/lang/String;)Lorg/apache/hadoop/hbase/io/crypto/Cipher;
      10: areturn

  public static java.lang.String[] getSupportedCiphers();
    Code:
       0: invokestatic  #7                  // Method org/apache/hadoop/hbase/HBaseConfiguration.create:()Lorg/apache/hadoop/conf/Configuration;
       3: invokestatic  #8                  // Method getSupportedCiphers:(Lorg/apache/hadoop/conf/Configuration;)[Ljava/lang/String;
       6: areturn

  public static java.lang.String[] getSupportedCiphers(org.apache.hadoop.conf.Configuration);
    Code:
       0: aload_0
       1: invokestatic  #5                  // Method getCipherProvider:(Lorg/apache/hadoop/conf/Configuration;)Lorg/apache/hadoop/hbase/io/crypto/CipherProvider;
       4: invokeinterface #9,  1            // InterfaceMethod org/apache/hadoop/hbase/io/crypto/CipherProvider.getSupportedCiphers:()[Ljava/lang/String;
       9: areturn

  public static byte[] hash128(java.lang.String...);
    Code:
       0: bipush        16
       2: newarray       byte
       4: astore_1
       5: ldc           #10                 // String MD5
       7: invokestatic  #11                 // Method java/security/MessageDigest.getInstance:(Ljava/lang/String;)Ljava/security/MessageDigest;
      10: astore_2
      11: aload_0
      12: astore_3
      13: aload_3
      14: arraylength
      15: istore        4
      17: iconst_0
      18: istore        5
      20: iload         5
      22: iload         4
      24: if_icmpge     48
      27: aload_3
      28: iload         5
      30: aaload
      31: astore        6
      33: aload_2
      34: aload         6
      36: invokestatic  #12                 // Method org/apache/hadoop/hbase/util/Bytes.toBytes:(Ljava/lang/String;)[B
      39: invokevirtual #13                 // Method java/security/MessageDigest.update:([B)V
      42: iinc          5, 1
      45: goto          20
      48: aload_2
      49: aload_1
      50: iconst_0
      51: aload_1
      52: arraylength
      53: invokevirtual #14                 // Method java/security/MessageDigest.digest:([BII)I
      56: pop
      57: aload_1
      58: areturn
      59: astore_2
      60: new           #16                 // class java/lang/RuntimeException
      63: dup
      64: aload_2
      65: invokespecial #17                 // Method java/lang/RuntimeException."<init>":(Ljava/lang/Throwable;)V
      68: athrow
      69: astore_2
      70: new           #16                 // class java/lang/RuntimeException
      73: dup
      74: aload_2
      75: invokespecial #17                 // Method java/lang/RuntimeException."<init>":(Ljava/lang/Throwable;)V
      78: athrow
    Exception table:
       from    to  target type
           5    58    59   Class java/security/NoSuchAlgorithmException
           5    58    69   Class java/security/DigestException

  public static byte[] hash128(byte[]...);
    Code:
       0: bipush        16
       2: newarray       byte
       4: astore_1
       5: ldc           #10                 // String MD5
       7: invokestatic  #11                 // Method java/security/MessageDigest.getInstance:(Ljava/lang/String;)Ljava/security/MessageDigest;
      10: astore_2
      11: aload_0
      12: astore_3
      13: aload_3
      14: arraylength
      15: istore        4
      17: iconst_0
      18: istore        5
      20: iload         5
      22: iload         4
      24: if_icmpge     45
      27: aload_3
      28: iload         5
      30: aaload
      31: astore        6
      33: aload_2
      34: aload         6
      36: invokevirtual #13                 // Method java/security/MessageDigest.update:([B)V
      39: iinc          5, 1
      42: goto          20
      45: aload_2
      46: aload_1
      47: iconst_0
      48: aload_1
      49: arraylength
      50: invokevirtual #14                 // Method java/security/MessageDigest.digest:([BII)I
      53: pop
      54: aload_1
      55: areturn
      56: astore_2
      57: new           #16                 // class java/lang/RuntimeException
      60: dup
      61: aload_2
      62: invokespecial #17                 // Method java/lang/RuntimeException."<init>":(Ljava/lang/Throwable;)V
      65: athrow
      66: astore_2
      67: new           #16                 // class java/lang/RuntimeException
      70: dup
      71: aload_2
      72: invokespecial #17                 // Method java/lang/RuntimeException."<init>":(Ljava/lang/Throwable;)V
      75: athrow
    Exception table:
       from    to  target type
           5    55    56   Class java/security/NoSuchAlgorithmException
           5    55    66   Class java/security/DigestException

  public static byte[] hash256(java.lang.String...);
    Code:
       0: bipush        32
       2: newarray       byte
       4: astore_1
       5: ldc           #19                 // String SHA-256
       7: invokestatic  #11                 // Method java/security/MessageDigest.getInstance:(Ljava/lang/String;)Ljava/security/MessageDigest;
      10: astore_2
      11: aload_0
      12: astore_3
      13: aload_3
      14: arraylength
      15: istore        4
      17: iconst_0
      18: istore        5
      20: iload         5
      22: iload         4
      24: if_icmpge     48
      27: aload_3
      28: iload         5
      30: aaload
      31: astore        6
      33: aload_2
      34: aload         6
      36: invokestatic  #12                 // Method org/apache/hadoop/hbase/util/Bytes.toBytes:(Ljava/lang/String;)[B
      39: invokevirtual #13                 // Method java/security/MessageDigest.update:([B)V
      42: iinc          5, 1
      45: goto          20
      48: aload_2
      49: aload_1
      50: iconst_0
      51: aload_1
      52: arraylength
      53: invokevirtual #14                 // Method java/security/MessageDigest.digest:([BII)I
      56: pop
      57: aload_1
      58: areturn
      59: astore_2
      60: new           #16                 // class java/lang/RuntimeException
      63: dup
      64: aload_2
      65: invokespecial #17                 // Method java/lang/RuntimeException."<init>":(Ljava/lang/Throwable;)V
      68: athrow
      69: astore_2
      70: new           #16                 // class java/lang/RuntimeException
      73: dup
      74: aload_2
      75: invokespecial #17                 // Method java/lang/RuntimeException."<init>":(Ljava/lang/Throwable;)V
      78: athrow
    Exception table:
       from    to  target type
           5    58    59   Class java/security/NoSuchAlgorithmException
           5    58    69   Class java/security/DigestException

  public static byte[] hash256(byte[]...);
    Code:
       0: bipush        32
       2: newarray       byte
       4: astore_1
       5: ldc           #19                 // String SHA-256
       7: invokestatic  #11                 // Method java/security/MessageDigest.getInstance:(Ljava/lang/String;)Ljava/security/MessageDigest;
      10: astore_2
      11: aload_0
      12: astore_3
      13: aload_3
      14: arraylength
      15: istore        4
      17: iconst_0
      18: istore        5
      20: iload         5
      22: iload         4
      24: if_icmpge     45
      27: aload_3
      28: iload         5
      30: aaload
      31: astore        6
      33: aload_2
      34: aload         6
      36: invokevirtual #13                 // Method java/security/MessageDigest.update:([B)V
      39: iinc          5, 1
      42: goto          20
      45: aload_2
      46: aload_1
      47: iconst_0
      48: aload_1
      49: arraylength
      50: invokevirtual #14                 // Method java/security/MessageDigest.digest:([BII)I
      53: pop
      54: aload_1
      55: areturn
      56: astore_2
      57: new           #16                 // class java/lang/RuntimeException
      60: dup
      61: aload_2
      62: invokespecial #17                 // Method java/lang/RuntimeException."<init>":(Ljava/lang/Throwable;)V
      65: athrow
      66: astore_2
      67: new           #16                 // class java/lang/RuntimeException
      70: dup
      71: aload_2
      72: invokespecial #17                 // Method java/lang/RuntimeException."<init>":(Ljava/lang/Throwable;)V
      75: athrow
    Exception table:
       from    to  target type
           5    55    56   Class java/security/NoSuchAlgorithmException
           5    55    66   Class java/security/DigestException

  public static byte[] pbkdf128(java.lang.String...);
    Code:
       0: sipush        128
       3: newarray       byte
       5: astore_1
       6: aload_1
       7: invokestatic  #20                 // Method org/apache/hadoop/hbase/util/Bytes.random:([B)V
      10: new           #21                 // class java/lang/StringBuilder
      13: dup
      14: invokespecial #22                 // Method java/lang/StringBuilder."<init>":()V
      17: astore_2
      18: aload_0
      19: astore_3
      20: aload_3
      21: arraylength
      22: istore        4
      24: iconst_0
      25: istore        5
      27: iload         5
      29: iload         4
      31: if_icmpge     53
      34: aload_3
      35: iload         5
      37: aaload
      38: astore        6
      40: aload_2
      41: aload         6
      43: invokevirtual #23                 // Method java/lang/StringBuilder.append:(Ljava/lang/String;)Ljava/lang/StringBuilder;
      46: pop
      47: iinc          5, 1
      50: goto          27
      53: new           #24                 // class javax/crypto/spec/PBEKeySpec
      56: dup
      57: aload_2
      58: invokevirtual #25                 // Method java/lang/StringBuilder.toString:()Ljava/lang/String;
      61: invokevirtual #26                 // Method java/lang/String.toCharArray:()[C
      64: aload_1
      65: sipush        10000
      68: sipush        128
      71: invokespecial #27                 // Method javax/crypto/spec/PBEKeySpec."<init>":([C[BII)V
      74: astore_3
      75: ldc           #28                 // String PBKDF2WithHmacSHA1
      77: invokestatic  #29                 // Method javax/crypto/SecretKeyFactory.getInstance:(Ljava/lang/String;)Ljavax/crypto/SecretKeyFactory;
      80: aload_3
      81: invokevirtual #30                 // Method javax/crypto/SecretKeyFactory.generateSecret:(Ljava/security/spec/KeySpec;)Ljavax/crypto/SecretKey;
      84: invokeinterface #31,  1           // InterfaceMethod javax/crypto/SecretKey.getEncoded:()[B
      89: areturn
      90: astore        4
      92: new           #16                 // class java/lang/RuntimeException
      95: dup
      96: aload         4
      98: invokespecial #17                 // Method java/lang/RuntimeException."<init>":(Ljava/lang/Throwable;)V
     101: athrow
     102: astore        4
     104: new           #16                 // class java/lang/RuntimeException
     107: dup
     108: aload         4
     110: invokespecial #17                 // Method java/lang/RuntimeException."<init>":(Ljava/lang/Throwable;)V
     113: athrow
    Exception table:
       from    to  target type
          75    89    90   Class java/security/NoSuchAlgorithmException
          75    89   102   Class java/security/spec/InvalidKeySpecException

  public static byte[] pbkdf128(byte[]...);
    Code:
       0: sipush        128
       3: newarray       byte
       5: astore_1
       6: aload_1
       7: invokestatic  #20                 // Method org/apache/hadoop/hbase/util/Bytes.random:([B)V
      10: new           #21                 // class java/lang/StringBuilder
      13: dup
      14: invokespecial #22                 // Method java/lang/StringBuilder."<init>":()V
      17: astore_2
      18: aload_0
      19: astore_3
      20: aload_3
      21: arraylength
      22: istore        4
      24: iconst_0
      25: istore        5
      27: iload         5
      29: iload         4
      31: if_icmpge     56
      34: aload_3
      35: iload         5
      37: aaload
      38: astore        6
      40: aload_2
      41: aload         6
      43: invokestatic  #33                 // Method java/util/Arrays.toString:([B)Ljava/lang/String;
      46: invokevirtual #23                 // Method java/lang/StringBuilder.append:(Ljava/lang/String;)Ljava/lang/StringBuilder;
      49: pop
      50: iinc          5, 1
      53: goto          27
      56: new           #24                 // class javax/crypto/spec/PBEKeySpec
      59: dup
      60: aload_2
      61: invokevirtual #25                 // Method java/lang/StringBuilder.toString:()Ljava/lang/String;
      64: invokevirtual #26                 // Method java/lang/String.toCharArray:()[C
      67: aload_1
      68: sipush        10000
      71: sipush        128
      74: invokespecial #27                 // Method javax/crypto/spec/PBEKeySpec."<init>":([C[BII)V
      77: astore_3
      78: ldc           #28                 // String PBKDF2WithHmacSHA1
      80: invokestatic  #29                 // Method javax/crypto/SecretKeyFactory.getInstance:(Ljava/lang/String;)Ljavax/crypto/SecretKeyFactory;
      83: aload_3
      84: invokevirtual #30                 // Method javax/crypto/SecretKeyFactory.generateSecret:(Ljava/security/spec/KeySpec;)Ljavax/crypto/SecretKey;
      87: invokeinterface #31,  1           // InterfaceMethod javax/crypto/SecretKey.getEncoded:()[B
      92: areturn
      93: astore        4
      95: new           #16                 // class java/lang/RuntimeException
      98: dup
      99: aload         4
     101: invokespecial #17                 // Method java/lang/RuntimeException."<init>":(Ljava/lang/Throwable;)V
     104: athrow
     105: astore        4
     107: new           #16                 // class java/lang/RuntimeException
     110: dup
     111: aload         4
     113: invokespecial #17                 // Method java/lang/RuntimeException."<init>":(Ljava/lang/Throwable;)V
     116: athrow
    Exception table:
       from    to  target type
          78    92    93   Class java/security/NoSuchAlgorithmException
          78    92   105   Class java/security/spec/InvalidKeySpecException

  public static void encrypt(java.io.OutputStream, byte[], int, int, org.apache.hadoop.hbase.io.crypto.Encryptor) throws java.io.IOException;
    Code:
       0: aload         4
       2: aload_0
       3: invokeinterface #34,  2           // InterfaceMethod org/apache/hadoop/hbase/io/crypto/Encryptor.createEncryptionStream:(Ljava/io/OutputStream;)Ljava/io/OutputStream;
       8: astore        5
      10: aload         5
      12: aload_1
      13: iload_2
      14: iload_3
      15: invokevirtual #35                 // Method java/io/OutputStream.write:([BII)V
      18: aload         5
      20: invokevirtual #36                 // Method java/io/OutputStream.close:()V
      23: goto          36
      26: astore        6
      28: aload         5
      30: invokevirtual #36                 // Method java/io/OutputStream.close:()V
      33: aload         6
      35: athrow
      36: return
    Exception table:
       from    to  target type
          10    18    26   any
          26    28    26   any

  public static void encrypt(java.io.OutputStream, byte[], int, int, org.apache.hadoop.hbase.io.crypto.Encryption$Context, byte[]) throws java.io.IOException;
    Code:
       0: aload         4
       2: invokevirtual #37                 // Method org/apache/hadoop/hbase/io/crypto/Encryption$Context.getCipher:()Lorg/apache/hadoop/hbase/io/crypto/Cipher;
       5: invokevirtual #38                 // Method org/apache/hadoop/hbase/io/crypto/Cipher.getEncryptor:()Lorg/apache/hadoop/hbase/io/crypto/Encryptor;
       8: astore        6
      10: aload         6
      12: aload         4
      14: invokevirtual #39                 // Method org/apache/hadoop/hbase/io/crypto/Encryption$Context.getKey:()Ljava/security/Key;
      17: invokeinterface #40,  2           // InterfaceMethod org/apache/hadoop/hbase/io/crypto/Encryptor.setKey:(Ljava/security/Key;)V
      22: aload         6
      24: aload         5
      26: invokeinterface #41,  2           // InterfaceMethod org/apache/hadoop/hbase/io/crypto/Encryptor.setIv:([B)V
      31: aload         6
      33: invokeinterface #42,  1           // InterfaceMethod org/apache/hadoop/hbase/io/crypto/Encryptor.reset:()V
      38: aload_0
      39: aload_1
      40: iload_2
      41: iload_3
      42: aload         6
      44: invokestatic  #43                 // Method encrypt:(Ljava/io/OutputStream;[BIILorg/apache/hadoop/hbase/io/crypto/Encryptor;)V
      47: return

  public static void encrypt(java.io.OutputStream, java.io.InputStream, org.apache.hadoop.hbase.io.crypto.Encryptor) throws java.io.IOException;
    Code:
       0: aload_2
       1: aload_0
       2: invokeinterface #34,  2           // InterfaceMethod org/apache/hadoop/hbase/io/crypto/Encryptor.createEncryptionStream:(Ljava/io/OutputStream;)Ljava/io/OutputStream;
       7: astore_3
       8: aload_1
       9: aload_3
      10: invokestatic  #44                 // Method org/apache/commons/io/IOUtils.copy:(Ljava/io/InputStream;Ljava/io/OutputStream;)I
      13: pop
      14: aload_3
      15: invokevirtual #36                 // Method java/io/OutputStream.close:()V
      18: goto          30
      21: astore        4
      23: aload_3
      24: invokevirtual #36                 // Method java/io/OutputStream.close:()V
      27: aload         4
      29: athrow
      30: return
    Exception table:
       from    to  target type
           8    14    21   any
          21    23    21   any

  public static void encrypt(java.io.OutputStream, java.io.InputStream, org.apache.hadoop.hbase.io.crypto.Encryption$Context, byte[]) throws java.io.IOException;
    Code:
       0: aload_2
       1: invokevirtual #37                 // Method org/apache/hadoop/hbase/io/crypto/Encryption$Context.getCipher:()Lorg/apache/hadoop/hbase/io/crypto/Cipher;
       4: invokevirtual #38                 // Method org/apache/hadoop/hbase/io/crypto/Cipher.getEncryptor:()Lorg/apache/hadoop/hbase/io/crypto/Encryptor;
       7: astore        4
       9: aload         4
      11: aload_2
      12: invokevirtual #39                 // Method org/apache/hadoop/hbase/io/crypto/Encryption$Context.getKey:()Ljava/security/Key;
      15: invokeinterface #40,  2           // InterfaceMethod org/apache/hadoop/hbase/io/crypto/Encryptor.setKey:(Ljava/security/Key;)V
      20: aload         4
      22: aload_3
      23: invokeinterface #41,  2           // InterfaceMethod org/apache/hadoop/hbase/io/crypto/Encryptor.setIv:([B)V
      28: aload         4
      30: invokeinterface #42,  1           // InterfaceMethod org/apache/hadoop/hbase/io/crypto/Encryptor.reset:()V
      35: aload_0
      36: aload_1
      37: aload         4
      39: invokestatic  #45                 // Method encrypt:(Ljava/io/OutputStream;Ljava/io/InputStream;Lorg/apache/hadoop/hbase/io/crypto/Encryptor;)V
      42: return

  public static void decrypt(byte[], int, java.io.InputStream, int, org.apache.hadoop.hbase.io.crypto.Decryptor) throws java.io.IOException;
    Code:
       0: aload         4
       2: aload_2
       3: invokeinterface #46,  2           // InterfaceMethod org/apache/hadoop/hbase/io/crypto/Decryptor.createDecryptionStream:(Ljava/io/InputStream;)Ljava/io/InputStream;
       8: astore        5
      10: aload         5
      12: aload_0
      13: iload_1
      14: iload_3
      15: invokestatic  #47                 // Method org/apache/commons/io/IOUtils.readFully:(Ljava/io/InputStream;[BII)V
      18: aload         5
      20: invokevirtual #48                 // Method java/io/InputStream.close:()V
      23: goto          36
      26: astore        6
      28: aload         5
      30: invokevirtual #48                 // Method java/io/InputStream.close:()V
      33: aload         6
      35: athrow
      36: return
    Exception table:
       from    to  target type
          10    18    26   any
          26    28    26   any

  public static void decrypt(byte[], int, java.io.InputStream, int, org.apache.hadoop.hbase.io.crypto.Encryption$Context, byte[]) throws java.io.IOException;
    Code:
       0: aload         4
       2: invokevirtual #37                 // Method org/apache/hadoop/hbase/io/crypto/Encryption$Context.getCipher:()Lorg/apache/hadoop/hbase/io/crypto/Cipher;
       5: invokevirtual #49                 // Method org/apache/hadoop/hbase/io/crypto/Cipher.getDecryptor:()Lorg/apache/hadoop/hbase/io/crypto/Decryptor;
       8: astore        6
      10: aload         6
      12: aload         4
      14: invokevirtual #39                 // Method org/apache/hadoop/hbase/io/crypto/Encryption$Context.getKey:()Ljava/security/Key;
      17: invokeinterface #50,  2           // InterfaceMethod org/apache/hadoop/hbase/io/crypto/Decryptor.setKey:(Ljava/security/Key;)V
      22: aload         6
      24: aload         5
      26: invokeinterface #51,  2           // InterfaceMethod org/apache/hadoop/hbase/io/crypto/Decryptor.setIv:([B)V
      31: aload_0
      32: iload_1
      33: aload_2
      34: iload_3
      35: aload         6
      37: invokestatic  #52                 // Method decrypt:([BILjava/io/InputStream;ILorg/apache/hadoop/hbase/io/crypto/Decryptor;)V
      40: return

  public static void decrypt(java.io.OutputStream, java.io.InputStream, int, org.apache.hadoop.hbase.io.crypto.Decryptor) throws java.io.IOException;
    Code:
       0: aload_3
       1: aload_1
       2: invokeinterface #46,  2           // InterfaceMethod org/apache/hadoop/hbase/io/crypto/Decryptor.createDecryptionStream:(Ljava/io/InputStream;)Ljava/io/InputStream;
       7: astore        4
       9: sipush        8192
      12: newarray       byte
      14: astore        5
      16: iload_2
      17: i2l
      18: lstore        6
      20: lload         6
      22: lconst_0
      23: lcmp
      24: ifle          89
      27: lload         6
      29: aload         5
      31: arraylength
      32: i2l
      33: lcmp
      34: ifge          42
      37: lload         6
      39: goto          46
      42: aload         5
      44: arraylength
      45: i2l
      46: l2i
      47: istore        8
      49: aload         4
      51: aload         5
      53: iconst_0
      54: iload         8
      56: invokevirtual #53                 // Method java/io/InputStream.read:([BII)I
      59: istore        9
      61: iload         9
      63: ifge          69
      66: goto          89
      69: aload_0
      70: aload         5
      72: iconst_0
      73: iload         9
      75: invokevirtual #35                 // Method java/io/OutputStream.write:([BII)V
      78: lload         6
      80: iload         9
      82: i2l
      83: lsub
      84: lstore        6
      86: goto          20
      89: aload         4
      91: invokevirtual #48                 // Method java/io/InputStream.close:()V
      94: goto          107
      97: astore        10
      99: aload         4
     101: invokevirtual #48                 // Method java/io/InputStream.close:()V
     104: aload         10
     106: athrow
     107: return
    Exception table:
       from    to  target type
          20    89    97   any
          97    99    97   any

  public static void decrypt(java.io.OutputStream, java.io.InputStream, int, org.apache.hadoop.hbase.io.crypto.Encryption$Context, byte[]) throws java.io.IOException;
    Code:
       0: aload_3
       1: invokevirtual #37                 // Method org/apache/hadoop/hbase/io/crypto/Encryption$Context.getCipher:()Lorg/apache/hadoop/hbase/io/crypto/Cipher;
       4: invokevirtual #49                 // Method org/apache/hadoop/hbase/io/crypto/Cipher.getDecryptor:()Lorg/apache/hadoop/hbase/io/crypto/Decryptor;
       7: astore        5
       9: aload         5
      11: aload_3
      12: invokevirtual #39                 // Method org/apache/hadoop/hbase/io/crypto/Encryption$Context.getKey:()Ljava/security/Key;
      15: invokeinterface #50,  2           // InterfaceMethod org/apache/hadoop/hbase/io/crypto/Decryptor.setKey:(Ljava/security/Key;)V
      20: aload         5
      22: aload         4
      24: invokeinterface #51,  2           // InterfaceMethod org/apache/hadoop/hbase/io/crypto/Decryptor.setIv:([B)V
      29: aload_0
      30: aload_1
      31: iload_2
      32: aload         5
      34: invokestatic  #54                 // Method decrypt:(Ljava/io/OutputStream;Ljava/io/InputStream;ILorg/apache/hadoop/hbase/io/crypto/Decryptor;)V
      37: return

  public static java.security.Key getSecretKeyForSubject(java.lang.String, org.apache.hadoop.conf.Configuration) throws java.io.IOException;
    Code:
       0: aload_1
       1: invokestatic  #55                 // Method getKeyProvider:(Lorg/apache/hadoop/conf/Configuration;)Lorg/apache/hadoop/hbase/io/crypto/KeyProvider;
       4: astore_2
       5: aload_2
       6: ifnull        50
       9: aload_2
      10: iconst_1
      11: anewarray     #56                 // class java/lang/String
      14: dup
      15: iconst_0
      16: aload_0
      17: aastore
      18: invokeinterface #57,  2           // InterfaceMethod org/apache/hadoop/hbase/io/crypto/KeyProvider.getKeys:([Ljava/lang/String;)[Ljava/security/Key;
      23: astore_3
      24: aload_3
      25: ifnull        37
      28: aload_3
      29: arraylength
      30: ifle          37
      33: aload_3
      34: iconst_0
      35: aaload
      36: areturn
      37: goto          50
      40: astore_3
      41: new           #59                 // class java/io/IOException
      44: dup
      45: aload_3
      46: invokespecial #60                 // Method java/io/IOException."<init>":(Ljava/lang/Throwable;)V
      49: athrow
      50: new           #59                 // class java/io/IOException
      53: dup
      54: new           #21                 // class java/lang/StringBuilder
      57: dup
      58: invokespecial #22                 // Method java/lang/StringBuilder."<init>":()V
      61: ldc           #61                 // String No key found for subject '
      63: invokevirtual #23                 // Method java/lang/StringBuilder.append:(Ljava/lang/String;)Ljava/lang/StringBuilder;
      66: aload_0
      67: invokevirtual #23                 // Method java/lang/StringBuilder.append:(Ljava/lang/String;)Ljava/lang/StringBuilder;
      70: ldc           #62                 // String '
      72: invokevirtual #23                 // Method java/lang/StringBuilder.append:(Ljava/lang/String;)Ljava/lang/StringBuilder;
      75: invokevirtual #25                 // Method java/lang/StringBuilder.toString:()Ljava/lang/String;
      78: invokespecial #63                 // Method java/io/IOException."<init>":(Ljava/lang/String;)V
      81: athrow
    Exception table:
       from    to  target type
           9    36    40   Class java/lang/Exception

  public static void encryptWithSubjectKey(java.io.OutputStream, java.io.InputStream, java.lang.String, org.apache.hadoop.conf.Configuration, org.apache.hadoop.hbase.io.crypto.Cipher, byte[]) throws java.io.IOException;
    Code:
       0: aload_2
       1: aload_3
       2: invokestatic  #64                 // Method getSecretKeyForSubject:(Ljava/lang/String;Lorg/apache/hadoop/conf/Configuration;)Ljava/security/Key;
       5: astore        6
       7: aload         6
       9: ifnonnull     44
      12: new           #59                 // class java/io/IOException
      15: dup
      16: new           #21                 // class java/lang/StringBuilder
      19: dup
      20: invokespecial #22                 // Method java/lang/StringBuilder."<init>":()V
      23: ldc           #61                 // String No key found for subject '
      25: invokevirtual #23                 // Method java/lang/StringBuilder.append:(Ljava/lang/String;)Ljava/lang/StringBuilder;
      28: aload_2
      29: invokevirtual #23                 // Method java/lang/StringBuilder.append:(Ljava/lang/String;)Ljava/lang/StringBuilder;
      32: ldc           #62                 // String '
      34: invokevirtual #23                 // Method java/lang/StringBuilder.append:(Ljava/lang/String;)Ljava/lang/StringBuilder;
      37: invokevirtual #25                 // Method java/lang/StringBuilder.toString:()Ljava/lang/String;
      40: invokespecial #63                 // Method java/io/IOException."<init>":(Ljava/lang/String;)V
      43: athrow
      44: aload         4
      46: invokevirtual #38                 // Method org/apache/hadoop/hbase/io/crypto/Cipher.getEncryptor:()Lorg/apache/hadoop/hbase/io/crypto/Encryptor;
      49: astore        7
      51: aload         7
      53: aload         6
      55: invokeinterface #40,  2           // InterfaceMethod org/apache/hadoop/hbase/io/crypto/Encryptor.setKey:(Ljava/security/Key;)V
      60: aload         7
      62: aload         5
      64: invokeinterface #41,  2           // InterfaceMethod org/apache/hadoop/hbase/io/crypto/Encryptor.setIv:([B)V
      69: aload_0
      70: aload_1
      71: aload         7
      73: invokestatic  #45                 // Method encrypt:(Ljava/io/OutputStream;Ljava/io/InputStream;Lorg/apache/hadoop/hbase/io/crypto/Encryptor;)V
      76: return

  public static void decryptWithSubjectKey(java.io.OutputStream, java.io.InputStream, int, java.lang.String, org.apache.hadoop.conf.Configuration, org.apache.hadoop.hbase.io.crypto.Cipher, byte[]) throws java.io.IOException;
    Code:
       0: aload_3
       1: aload         4
       3: invokestatic  #64                 // Method getSecretKeyForSubject:(Ljava/lang/String;Lorg/apache/hadoop/conf/Configuration;)Ljava/security/Key;
       6: astore        7
       8: aload         7
      10: ifnonnull     45
      13: new           #59                 // class java/io/IOException
      16: dup
      17: new           #21                 // class java/lang/StringBuilder
      20: dup
      21: invokespecial #22                 // Method java/lang/StringBuilder."<init>":()V
      24: ldc           #61                 // String No key found for subject '
      26: invokevirtual #23                 // Method java/lang/StringBuilder.append:(Ljava/lang/String;)Ljava/lang/StringBuilder;
      29: aload_3
      30: invokevirtual #23                 // Method java/lang/StringBuilder.append:(Ljava/lang/String;)Ljava/lang/StringBuilder;
      33: ldc           #62                 // String '
      35: invokevirtual #23                 // Method java/lang/StringBuilder.append:(Ljava/lang/String;)Ljava/lang/StringBuilder;
      38: invokevirtual #25                 // Method java/lang/StringBuilder.toString:()Ljava/lang/String;
      41: invokespecial #63                 // Method java/io/IOException."<init>":(Ljava/lang/String;)V
      44: athrow
      45: aload         5
      47: invokevirtual #49                 // Method org/apache/hadoop/hbase/io/crypto/Cipher.getDecryptor:()Lorg/apache/hadoop/hbase/io/crypto/Decryptor;
      50: astore        8
      52: aload         8
      54: aload         7
      56: invokeinterface #50,  2           // InterfaceMethod org/apache/hadoop/hbase/io/crypto/Decryptor.setKey:(Ljava/security/Key;)V
      61: aload         8
      63: aload         6
      65: invokeinterface #51,  2           // InterfaceMethod org/apache/hadoop/hbase/io/crypto/Decryptor.setIv:([B)V
      70: aload_0
      71: aload_1
      72: iload_2
      73: aload         8
      75: invokestatic  #54                 // Method decrypt:(Ljava/io/OutputStream;Ljava/io/InputStream;ILorg/apache/hadoop/hbase/io/crypto/Decryptor;)V
      78: goto          251
      81: astore        9
      83: aload         4
      85: ldc           #66                 // String hbase.crypto.alternate.key.algorithm
      87: invokevirtual #67                 // Method org/apache/hadoop/conf/Configuration.get:(Ljava/lang/String;)Ljava/lang/String;
      90: astore        10
      92: aload         10
      94: ifnull        241
      97: getstatic     #68                 // Field LOG:Lorg/slf4j/Logger;
     100: invokeinterface #69,  1           // InterfaceMethod org/slf4j/Logger.isDebugEnabled:()Z
     105: ifeq          158
     108: getstatic     #68                 // Field LOG:Lorg/slf4j/Logger;
     111: new           #21                 // class java/lang/StringBuilder
     114: dup
     115: invokespecial #22                 // Method java/lang/StringBuilder."<init>":()V
     118: ldc           #70                 // String Unable to decrypt data with current cipher algorithm '
     120: invokevirtual #23                 // Method java/lang/StringBuilder.append:(Ljava/lang/String;)Ljava/lang/StringBuilder;
     123: aload         4
     125: ldc           #71                 // String hbase.crypto.key.algorithm
     127: ldc           #72                 // String AES
     129: invokevirtual #73                 // Method org/apache/hadoop/conf/Configuration.get:(Ljava/lang/String;Ljava/lang/String;)Ljava/lang/String;
     132: invokevirtual #23                 // Method java/lang/StringBuilder.append:(Ljava/lang/String;)Ljava/lang/StringBuilder;
     135: ldc           #74                 // String '. Trying with the alternate cipher algorithm '
     137: invokevirtual #23                 // Method java/lang/StringBuilder.append:(Ljava/lang/String;)Ljava/lang/StringBuilder;
     140: aload         10
     142: invokevirtual #23                 // Method java/lang/StringBuilder.append:(Ljava/lang/String;)Ljava/lang/StringBuilder;
     145: ldc           #75                 // String ' configured.
     147: invokevirtual #23                 // Method java/lang/StringBuilder.append:(Ljava/lang/String;)Ljava/lang/StringBuilder;
     150: invokevirtual #25                 // Method java/lang/StringBuilder.toString:()Ljava/lang/String;
     153: invokeinterface #76,  2           // InterfaceMethod org/slf4j/Logger.debug:(Ljava/lang/String;)V
     158: aload         4
     160: aload         10
     162: invokestatic  #77                 // Method getCipher:(Lorg/apache/hadoop/conf/Configuration;Ljava/lang/String;)Lorg/apache/hadoop/hbase/io/crypto/Cipher;
     165: astore        11
     167: aload         11
     169: ifnonnull     205
     172: new           #16                 // class java/lang/RuntimeException
     175: dup
     176: new           #21                 // class java/lang/StringBuilder
     179: dup
     180: invokespecial #22                 // Method java/lang/StringBuilder."<init>":()V
     183: ldc           #78                 // String Cipher '
     185: invokevirtual #23                 // Method java/lang/StringBuilder.append:(Ljava/lang/String;)Ljava/lang/StringBuilder;
     188: aload         10
     190: invokevirtual #23                 // Method java/lang/StringBuilder.append:(Ljava/lang/String;)Ljava/lang/StringBuilder;
     193: ldc           #79                 // String ' not available
     195: invokevirtual #23                 // Method java/lang/StringBuilder.append:(Ljava/lang/String;)Ljava/lang/StringBuilder;
     198: invokevirtual #25                 // Method java/lang/StringBuilder.toString:()Ljava/lang/String;
     201: invokespecial #80                 // Method java/lang/RuntimeException."<init>":(Ljava/lang/String;)V
     204: athrow
     205: aload         11
     207: invokevirtual #49                 // Method org/apache/hadoop/hbase/io/crypto/Cipher.getDecryptor:()Lorg/apache/hadoop/hbase/io/crypto/Decryptor;
     210: astore        8
     212: aload         8
     214: aload         7
     216: invokeinterface #50,  2           // InterfaceMethod org/apache/hadoop/hbase/io/crypto/Decryptor.setKey:(Ljava/security/Key;)V
     221: aload         8
     223: aload         6
     225: invokeinterface #51,  2           // InterfaceMethod org/apache/hadoop/hbase/io/crypto/Decryptor.setIv:([B)V
     230: aload_0
     231: aload_1
     232: iload_2
     233: aload         8
     235: invokestatic  #54                 // Method decrypt:(Ljava/io/OutputStream;Ljava/io/InputStream;ILorg/apache/hadoop/hbase/io/crypto/Decryptor;)V
     238: goto          251
     241: new           #59                 // class java/io/IOException
     244: dup
     245: aload         9
     247: invokespecial #60                 // Method java/io/IOException."<init>":(Ljava/lang/Throwable;)V
     250: athrow
     251: return
    Exception table:
       from    to  target type
          70    78    81   Class java/io/IOException

  public static org.apache.hadoop.hbase.io.crypto.CipherProvider getCipherProvider(org.apache.hadoop.conf.Configuration);
    Code:
       0: aload_0
       1: ldc           #86                 // String hbase.crypto.cipherprovider
       3: ldc           #87                 // class org/apache/hadoop/hbase/io/crypto/DefaultCipherProvider
       5: invokevirtual #88                 // Method java/lang/Class.getName:()Ljava/lang/String;
       8: invokevirtual #73                 // Method org/apache/hadoop/conf/Configuration.get:(Ljava/lang/String;Ljava/lang/String;)Ljava/lang/String;
      11: astore_1
      12: ldc           #89                 // class org/apache/hadoop/hbase/io/crypto/CipherProvider
      14: invokestatic  #90                 // Method getClassLoaderForClass:(Ljava/lang/Class;)Ljava/lang/ClassLoader;
      17: aload_1
      18: invokevirtual #91                 // Method java/lang/ClassLoader.loadClass:(Ljava/lang/String;)Ljava/lang/Class;
      21: aload_0
      22: invokestatic  #92                 // Method org/apache/hadoop/util/ReflectionUtils.newInstance:(Ljava/lang/Class;Lorg/apache/hadoop/conf/Configuration;)Ljava/lang/Object;
      25: checkcast     #89                 // class org/apache/hadoop/hbase/io/crypto/CipherProvider
      28: astore_2
      29: aload_2
      30: areturn
      31: astore_2
      32: new           #16                 // class java/lang/RuntimeException
      35: dup
      36: aload_2
      37: invokespecial #17                 // Method java/lang/RuntimeException."<init>":(Ljava/lang/Throwable;)V
      40: athrow
    Exception table:
       from    to  target type
          12    30    31   Class java/lang/Exception

  public static org.apache.hadoop.hbase.io.crypto.KeyProvider getKeyProvider(org.apache.hadoop.conf.Configuration);
    Code:
       0: aload_0
       1: ldc           #93                 // String hbase.crypto.keyprovider
       3: ldc           #94                 // class org/apache/hadoop/hbase/io/crypto/KeyStoreKeyProvider
       5: invokevirtual #88                 // Method java/lang/Class.getName:()Ljava/lang/String;
       8: invokevirtual #73                 // Method org/apache/hadoop/conf/Configuration.get:(Ljava/lang/String;Ljava/lang/String;)Ljava/lang/String;
      11: astore_1
      12: aload_0
      13: ldc           #95                 // String hbase.crypto.keyprovider.parameters
      15: ldc           #96                 // String
      17: invokevirtual #73                 // Method org/apache/hadoop/conf/Configuration.get:(Ljava/lang/String;Ljava/lang/String;)Ljava/lang/String;
      20: astore_2
      21: new           #97                 // class org/apache/hadoop/hbase/util/Pair
      24: dup
      25: aload_1
      26: aload_2
      27: invokespecial #98                 // Method org/apache/hadoop/hbase/util/Pair."<init>":(Ljava/lang/Object;Ljava/lang/Object;)V
      30: astore_3
      31: getstatic     #99                 // Field keyProviderCache:Ljava/util/Map;
      34: aload_3
      35: invokeinterface #100,  2          // InterfaceMethod java/util/Map.get:(Ljava/lang/Object;)Ljava/lang/Object;
      40: checkcast     #101                // class org/apache/hadoop/hbase/io/crypto/KeyProvider
      43: astore        4
      45: aload         4
      47: ifnull        53
      50: aload         4
      52: areturn
      53: ldc           #101                // class org/apache/hadoop/hbase/io/crypto/KeyProvider
      55: invokestatic  #90                 // Method getClassLoaderForClass:(Ljava/lang/Class;)Ljava/lang/ClassLoader;
      58: aload_1
      59: invokevirtual #91                 // Method java/lang/ClassLoader.loadClass:(Ljava/lang/String;)Ljava/lang/Class;
      62: aload_0
      63: invokestatic  #92                 // Method org/apache/hadoop/util/ReflectionUtils.newInstance:(Ljava/lang/Class;Lorg/apache/hadoop/conf/Configuration;)Ljava/lang/Object;
      66: checkcast     #101                // class org/apache/hadoop/hbase/io/crypto/KeyProvider
      69: astore        4
      71: aload         4
      73: aload_2
      74: invokeinterface #102,  2          // InterfaceMethod org/apache/hadoop/hbase/io/crypto/KeyProvider.init:(Ljava/lang/String;)V
      79: getstatic     #68                 // Field LOG:Lorg/slf4j/Logger;
      82: invokeinterface #69,  1           // InterfaceMethod org/slf4j/Logger.isDebugEnabled:()Z
      87: ifeq          122
      90: getstatic     #68                 // Field LOG:Lorg/slf4j/Logger;
      93: new           #21                 // class java/lang/StringBuilder
      96: dup
      97: invokespecial #22                 // Method java/lang/StringBuilder."<init>":()V
     100: ldc           #103                // String Installed
     102: invokevirtual #23                 // Method java/lang/StringBuilder.append:(Ljava/lang/String;)Ljava/lang/StringBuilder;
     105: aload_1
     106: invokevirtual #23                 // Method java/lang/StringBuilder.append:(Ljava/lang/String;)Ljava/lang/StringBuilder;
     109: ldc           #104                // String  into key provider cache
     111: invokevirtual #23                 // Method java/lang/StringBuilder.append:(Ljava/lang/String;)Ljava/lang/StringBuilder;
     114: invokevirtual #25                 // Method java/lang/StringBuilder.toString:()Ljava/lang/String;
     117: invokeinterface #76,  2           // InterfaceMethod org/slf4j/Logger.debug:(Ljava/lang/String;)V
     122: getstatic     #99                 // Field keyProviderCache:Ljava/util/Map;
     125: aload_3
     126: aload         4
     128: invokeinterface #105,  3          // InterfaceMethod java/util/Map.put:(Ljava/lang/Object;Ljava/lang/Object;)Ljava/lang/Object;
     133: pop
     134: aload         4
     136: areturn
     137: astore_3
     138: new           #16                 // class java/lang/RuntimeException
     141: dup
     142: aload_3
     143: invokespecial #17                 // Method java/lang/RuntimeException."<init>":(Ljava/lang/Throwable;)V
     146: athrow
    Exception table:
       from    to  target type
          21    52   137   Class java/lang/Exception
          53   136   137   Class java/lang/Exception

  public static void incrementIv(byte[]);
    Code:
       0: aload_0
       1: iconst_1
       2: invokestatic  #106                // Method incrementIv:([BI)V
       5: return

  public static void incrementIv(byte[], int);
    Code:
       0: aload_0
       1: arraylength
       2: istore_2
       3: iconst_1
       4: istore_3
       5: iconst_0
       6: istore        4
       8: iload         4
      10: iload_2
      11: if_icmpge     53
      14: iload_3
      15: ifeq          53
      18: aload_0
      19: iload         4
      21: aload_0
      22: iload         4
      24: baload
      25: iconst_1
      26: iadd
      27: sipush        255
      30: iand
      31: i2b
      32: bastore
      33: iconst_0
      34: aload_0
      35: iload         4
      37: baload
      38: if_icmpne     45
      41: iconst_1
      42: goto          46
      45: iconst_0
      46: istore_3
      47: iinc          4, 1
      50: goto          8
      53: iinc          1, -1
      56: iload_1
      57: ifgt          5
      60: return

  static {};
    Code:
       0: ldc           #107                // class org/apache/hadoop/hbase/io/crypto/Encryption
       2: invokestatic  #108                // Method org/slf4j/LoggerFactory.getLogger:(Ljava/lang/Class;)Lorg/slf4j/Logger;
       5: putstatic     #68                 // Field LOG:Lorg/slf4j/Logger;
       8: new           #109                // class java/util/concurrent/ConcurrentHashMap
      11: dup
      12: invokespecial #110                // Method java/util/concurrent/ConcurrentHashMap."<init>":()V
      15: putstatic     #99                 // Field keyProviderCache:Ljava/util/Map;
      18: return
}
