Compiled from "EnforcingScanLabelGenerator.java"
public class org.apache.hadoop.hbase.security.visibility.EnforcingScanLabelGenerator implements org.apache.hadoop.hbase.security.visibility.ScanLabelGenerator {
  public org.apache.hadoop.hbase.security.visibility.EnforcingScanLabelGenerator();
    Code:
       0: aload_0
       1: invokespecial #1                  // Method java/lang/Object."<init>":()V
       4: aload_0
       5: invokestatic  #2                  // Method org/apache/hadoop/hbase/security/visibility/VisibilityLabelsCache.get:()Lorg/apache/hadoop/hbase/security/visibility/VisibilityLabelsCache;
       8: putfield      #3                  // Field labelsCache:Lorg/apache/hadoop/hbase/security/visibility/VisibilityLabelsCache;
      11: return

  public void setConf(org.apache.hadoop.conf.Configuration);
    Code:
       0: aload_0
       1: aload_1
       2: putfield      #4                  // Field conf:Lorg/apache/hadoop/conf/Configuration;
       5: return

  public org.apache.hadoop.conf.Configuration getConf();
    Code:
       0: aload_0
       1: getfield      #4                  // Field conf:Lorg/apache/hadoop/conf/Configuration;
       4: areturn

  public java.util.List<java.lang.String> getLabels(org.apache.hadoop.hbase.security.User, org.apache.hadoop.hbase.security.visibility.Authorizations);
    Code:
       0: aload_1
       1: invokevirtual #5                  // Method org/apache/hadoop/hbase/security/User.getShortName:()Ljava/lang/String;
       4: astore_3
       5: aload_2
       6: ifnull        45
       9: getstatic     #6                  // Field LOG:Lorg/slf4j/Logger;
      12: new           #7                  // class java/lang/StringBuilder
      15: dup
      16: invokespecial #8                  // Method java/lang/StringBuilder."<init>":()V
      19: ldc           #9                  // String Dropping authorizations requested by user
      21: invokevirtual #10                 // Method java/lang/StringBuilder.append:(Ljava/lang/String;)Ljava/lang/StringBuilder;
      24: aload_3
      25: invokevirtual #10                 // Method java/lang/StringBuilder.append:(Ljava/lang/String;)Ljava/lang/StringBuilder;
      28: ldc           #11                 // String :
      30: invokevirtual #10                 // Method java/lang/StringBuilder.append:(Ljava/lang/String;)Ljava/lang/StringBuilder;
      33: aload_2
      34: invokevirtual #12                 // Method java/lang/StringBuilder.append:(Ljava/lang/Object;)Ljava/lang/StringBuilder;
      37: invokevirtual #13                 // Method java/lang/StringBuilder.toString:()Ljava/lang/String;
      40: invokeinterface #14,  2           // InterfaceMethod org/slf4j/Logger.warn:(Ljava/lang/String;)V
      45: new           #15                 // class java/util/HashSet
      48: dup
      49: invokespecial #16                 // Method java/util/HashSet."<init>":()V
      52: astore        4
      54: aload         4
      56: aload_0
      57: getfield      #3                  // Field labelsCache:Lorg/apache/hadoop/hbase/security/visibility/VisibilityLabelsCache;
      60: aload_3
      61: invokevirtual #17                 // Method org/apache/hadoop/hbase/security/visibility/VisibilityLabelsCache.getUserAuths:(Ljava/lang/String;)Ljava/util/List;
      64: invokeinterface #18,  2           // InterfaceMethod java/util/Set.addAll:(Ljava/util/Collection;)Z
      69: pop
      70: aload         4
      72: aload_0
      73: getfield      #3                  // Field labelsCache:Lorg/apache/hadoop/hbase/security/visibility/VisibilityLabelsCache;
      76: aload_1
      77: invokevirtual #19                 // Method org/apache/hadoop/hbase/security/User.getGroupNames:()[Ljava/lang/String;
      80: invokevirtual #20                 // Method org/apache/hadoop/hbase/security/visibility/VisibilityLabelsCache.getGroupAuths:([Ljava/lang/String;)Ljava/util/List;
      83: invokeinterface #18,  2           // InterfaceMethod java/util/Set.addAll:(Ljava/util/Collection;)Z
      88: pop
      89: new           #21                 // class java/util/ArrayList
      92: dup
      93: aload         4
      95: invokespecial #22                 // Method java/util/ArrayList."<init>":(Ljava/util/Collection;)V
      98: areturn

  static {};
    Code:
       0: ldc           #23                 // class org/apache/hadoop/hbase/security/visibility/EnforcingScanLabelGenerator
       2: invokestatic  #24                 // Method org/slf4j/LoggerFactory.getLogger:(Ljava/lang/Class;)Lorg/slf4j/Logger;
       5: putstatic     #6                  // Field LOG:Lorg/slf4j/Logger;
       8: return
}
