Compiled from "ErrorHandlingProtos.java"
public final class org.apache.hadoop.hbase.protobuf.generated.ErrorHandlingProtos$GenericExceptionMessage extends com.google.protobuf.GeneratedMessage implements org.apache.hadoop.hbase.protobuf.generated.ErrorHandlingProtos$GenericExceptionMessageOrBuilder {
  public static com.google.protobuf.Parser<org.apache.hadoop.hbase.protobuf.generated.ErrorHandlingProtos$GenericExceptionMessage> PARSER;

  public static final int CLASS_NAME_FIELD_NUMBER;

  public static final int MESSAGE_FIELD_NUMBER;

  public static final int ERROR_INFO_FIELD_NUMBER;

  public static final int TRACE_FIELD_NUMBER;

  public static org.apache.hadoop.hbase.protobuf.generated.ErrorHandlingProtos$GenericExceptionMessage getDefaultInstance();
    Code:
       0: getstatic     #17                 // Field defaultInstance:Lorg/apache/hadoop/hbase/protobuf/generated/ErrorHandlingProtos$GenericExceptionMessage;
       3: areturn

  public org.apache.hadoop.hbase.protobuf.generated.ErrorHandlingProtos$GenericExceptionMessage getDefaultInstanceForType();
    Code:
       0: getstatic     #17                 // Field defaultInstance:Lorg/apache/hadoop/hbase/protobuf/generated/ErrorHandlingProtos$GenericExceptionMessage;
       3: areturn

  public final com.google.protobuf.UnknownFieldSet getUnknownFields();
    Code:
       0: aload_0
       1: getfield      #14                 // Field unknownFields:Lcom/google/protobuf/UnknownFieldSet;
       4: areturn

  public static final com.google.protobuf.Descriptors$Descriptor getDescriptor();
    Code:
       0: invokestatic  #36                 // Method org/apache/hadoop/hbase/protobuf/generated/ErrorHandlingProtos.access$1200:()Lcom/google/protobuf/Descriptors$Descriptor;
       3: areturn

  protected com.google.protobuf.GeneratedMessage$FieldAccessorTable internalGetFieldAccessorTable();
    Code:
       0: invokestatic  #37                 // Method org/apache/hadoop/hbase/protobuf/generated/ErrorHandlingProtos.access$1300:()Lcom/google/protobuf/GeneratedMessage$FieldAccessorTable;
       3: ldc           #38                 // class org/apache/hadoop/hbase/protobuf/generated/ErrorHandlingProtos$GenericExceptionMessage
       5: ldc           #39                 // class org/apache/hadoop/hbase/protobuf/generated/ErrorHandlingProtos$GenericExceptionMessage$Builder
       7: invokevirtual #40                 // Method com/google/protobuf/GeneratedMessage$FieldAccessorTable.ensureFieldAccessorsInitialized:(Ljava/lang/Class;Ljava/lang/Class;)Lcom/google/protobuf/GeneratedMessage$FieldAccessorTable;
      10: areturn

  public com.google.protobuf.Parser<org.apache.hadoop.hbase.protobuf.generated.ErrorHandlingProtos$GenericExceptionMessage> getParserForType();
    Code:
       0: getstatic     #41                 // Field PARSER:Lcom/google/protobuf/Parser;
       3: areturn

  public boolean hasClassName();
    Code:
       0: aload_0
       1: getfield      #2                  // Field bitField0_:I
       4: iconst_1
       5: iand
       6: iconst_1
       7: if_icmpne     14
      10: iconst_1
      11: goto          15
      14: iconst_0
      15: ireturn

  public java.lang.String getClassName();
    Code:
       0: aload_0
       1: getfield      #6                  // Field className_:Ljava/lang/Object;
       4: astore_1
       5: aload_1
       6: instanceof    #42                 // class java/lang/String
       9: ifeq          17
      12: aload_1
      13: checkcast     #42                 // class java/lang/String
      16: areturn
      17: aload_1
      18: checkcast     #43                 // class com/google/protobuf/ByteString
      21: astore_2
      22: aload_2
      23: invokevirtual #44                 // Method com/google/protobuf/ByteString.toStringUtf8:()Ljava/lang/String;
      26: astore_3
      27: aload_2
      28: invokevirtual #45                 // Method com/google/protobuf/ByteString.isValidUtf8:()Z
      31: ifeq          39
      34: aload_0
      35: aload_3
      36: putfield      #6                  // Field className_:Ljava/lang/Object;
      39: aload_3
      40: areturn

  public com.google.protobuf.ByteString getClassNameBytes();
    Code:
       0: aload_0
       1: getfield      #6                  // Field className_:Ljava/lang/Object;
       4: astore_1
       5: aload_1
       6: instanceof    #42                 // class java/lang/String
       9: ifeq          27
      12: aload_1
      13: checkcast     #42                 // class java/lang/String
      16: invokestatic  #46                 // Method com/google/protobuf/ByteString.copyFromUtf8:(Ljava/lang/String;)Lcom/google/protobuf/ByteString;
      19: astore_2
      20: aload_0
      21: aload_2
      22: putfield      #6                  // Field className_:Ljava/lang/Object;
      25: aload_2
      26: areturn
      27: aload_1
      28: checkcast     #43                 // class com/google/protobuf/ByteString
      31: areturn

  public boolean hasMessage();
    Code:
       0: aload_0
       1: getfield      #2                  // Field bitField0_:I
       4: iconst_2
       5: iand
       6: iconst_2
       7: if_icmpne     14
      10: iconst_1
      11: goto          15
      14: iconst_0
      15: ireturn

  public java.lang.String getMessage();
    Code:
       0: aload_0
       1: getfield      #5                  // Field message_:Ljava/lang/Object;
       4: astore_1
       5: aload_1
       6: instanceof    #42                 // class java/lang/String
       9: ifeq          17
      12: aload_1
      13: checkcast     #42                 // class java/lang/String
      16: areturn
      17: aload_1
      18: checkcast     #43                 // class com/google/protobuf/ByteString
      21: astore_2
      22: aload_2
      23: invokevirtual #44                 // Method com/google/protobuf/ByteString.toStringUtf8:()Ljava/lang/String;
      26: astore_3
      27: aload_2
      28: invokevirtual #45                 // Method com/google/protobuf/ByteString.isValidUtf8:()Z
      31: ifeq          39
      34: aload_0
      35: aload_3
      36: putfield      #5                  // Field message_:Ljava/lang/Object;
      39: aload_3
      40: areturn

  public com.google.protobuf.ByteString getMessageBytes();
    Code:
       0: aload_0
       1: getfield      #5                  // Field message_:Ljava/lang/Object;
       4: astore_1
       5: aload_1
       6: instanceof    #42                 // class java/lang/String
       9: ifeq          27
      12: aload_1
      13: checkcast     #42                 // class java/lang/String
      16: invokestatic  #46                 // Method com/google/protobuf/ByteString.copyFromUtf8:(Ljava/lang/String;)Lcom/google/protobuf/ByteString;
      19: astore_2
      20: aload_0
      21: aload_2
      22: putfield      #5                  // Field message_:Ljava/lang/Object;
      25: aload_2
      26: areturn
      27: aload_1
      28: checkcast     #43                 // class com/google/protobuf/ByteString
      31: areturn

  public boolean hasErrorInfo();
    Code:
       0: aload_0
       1: getfield      #2                  // Field bitField0_:I
       4: iconst_4
       5: iand
       6: iconst_4
       7: if_icmpne     14
      10: iconst_1
      11: goto          15
      14: iconst_0
      15: ireturn

  public com.google.protobuf.ByteString getErrorInfo();
    Code:
       0: aload_0
       1: getfield      #4                  // Field errorInfo_:Lcom/google/protobuf/ByteString;
       4: areturn

  public java.util.List<org.apache.hadoop.hbase.protobuf.generated.ErrorHandlingProtos$StackTraceElementMessage> getTraceList();
    Code:
       0: aload_0
       1: getfield      #3                  // Field trace_:Ljava/util/List;
       4: areturn

  public java.util.List<? extends org.apache.hadoop.hbase.protobuf.generated.ErrorHandlingProtos$StackTraceElementMessageOrBuilder> getTraceOrBuilderList();
    Code:
       0: aload_0
       1: getfield      #3                  // Field trace_:Ljava/util/List;
       4: areturn

  public int getTraceCount();
    Code:
       0: aload_0
       1: getfield      #3                  // Field trace_:Ljava/util/List;
       4: invokeinterface #47,  1           // InterfaceMethod java/util/List.size:()I
       9: ireturn

  public org.apache.hadoop.hbase.protobuf.generated.ErrorHandlingProtos$StackTraceElementMessage getTrace(int);
    Code:
       0: aload_0
       1: getfield      #3                  // Field trace_:Ljava/util/List;
       4: iload_1
       5: invokeinterface #48,  2           // InterfaceMethod java/util/List.get:(I)Ljava/lang/Object;
      10: checkcast     #49                 // class org/apache/hadoop/hbase/protobuf/generated/ErrorHandlingProtos$StackTraceElementMessage
      13: areturn

  public org.apache.hadoop.hbase.protobuf.generated.ErrorHandlingProtos$StackTraceElementMessageOrBuilder getTraceOrBuilder(int);
    Code:
       0: aload_0
       1: getfield      #3                  // Field trace_:Ljava/util/List;
       4: iload_1
       5: invokeinterface #48,  2           // InterfaceMethod java/util/List.get:(I)Ljava/lang/Object;
      10: checkcast     #50                 // class org/apache/hadoop/hbase/protobuf/generated/ErrorHandlingProtos$StackTraceElementMessageOrBuilder
      13: areturn

  public final boolean isInitialized();
    Code:
       0: aload_0
       1: getfield      #10                 // Field memoizedIsInitialized:B
       4: istore_1
       5: iload_1
       6: iconst_m1
       7: if_icmpeq     21
      10: iload_1
      11: iconst_1
      12: if_icmpne     19
      15: iconst_1
      16: goto          20
      19: iconst_0
      20: ireturn
      21: aload_0
      22: iconst_1
      23: putfield      #10                 // Field memoizedIsInitialized:B
      26: iconst_1
      27: ireturn

  public void writeTo(com.google.protobuf.CodedOutputStream) throws java.io.IOException;
    Code:
       0: aload_0
       1: invokevirtual #54                 // Method getSerializedSize:()I
       4: pop
       5: aload_0
       6: getfield      #2                  // Field bitField0_:I
       9: iconst_1
      10: iand
      11: iconst_1
      12: if_icmpne     24
      15: aload_1
      16: iconst_1
      17: aload_0
      18: invokevirtual #55                 // Method getClassNameBytes:()Lcom/google/protobuf/ByteString;
      21: invokevirtual #56                 // Method com/google/protobuf/CodedOutputStream.writeBytes:(ILcom/google/protobuf/ByteString;)V
      24: aload_0
      25: getfield      #2                  // Field bitField0_:I
      28: iconst_2
      29: iand
      30: iconst_2
      31: if_icmpne     43
      34: aload_1
      35: iconst_2
      36: aload_0
      37: invokevirtual #57                 // Method getMessageBytes:()Lcom/google/protobuf/ByteString;
      40: invokevirtual #56                 // Method com/google/protobuf/CodedOutputStream.writeBytes:(ILcom/google/protobuf/ByteString;)V
      43: aload_0
      44: getfield      #2                  // Field bitField0_:I
      47: iconst_4
      48: iand
      49: iconst_4
      50: if_icmpne     62
      53: aload_1
      54: iconst_3
      55: aload_0
      56: getfield      #4                  // Field errorInfo_:Lcom/google/protobuf/ByteString;
      59: invokevirtual #56                 // Method com/google/protobuf/CodedOutputStream.writeBytes:(ILcom/google/protobuf/ByteString;)V
      62: iconst_0
      63: istore_2
      64: iload_2
      65: aload_0
      66: getfield      #3                  // Field trace_:Ljava/util/List;
      69: invokeinterface #47,  1           // InterfaceMethod java/util/List.size:()I
      74: if_icmpge     101
      77: aload_1
      78: iconst_4
      79: aload_0
      80: getfield      #3                  // Field trace_:Ljava/util/List;
      83: iload_2
      84: invokeinterface #48,  2           // InterfaceMethod java/util/List.get:(I)Ljava/lang/Object;
      89: checkcast     #58                 // class com/google/protobuf/MessageLite
      92: invokevirtual #59                 // Method com/google/protobuf/CodedOutputStream.writeMessage:(ILcom/google/protobuf/MessageLite;)V
      95: iinc          2, 1
      98: goto          64
     101: aload_0
     102: invokevirtual #60                 // Method getUnknownFields:()Lcom/google/protobuf/UnknownFieldSet;
     105: aload_1
     106: invokevirtual #61                 // Method com/google/protobuf/UnknownFieldSet.writeTo:(Lcom/google/protobuf/CodedOutputStream;)V
     109: return

  public int getSerializedSize();
    Code:
       0: aload_0
       1: getfield      #11                 // Field memoizedSerializedSize:I
       4: istore_1
       5: iload_1
       6: iconst_m1
       7: if_icmpeq     12
      10: iload_1
      11: ireturn
      12: iconst_0
      13: istore_1
      14: aload_0
      15: getfield      #2                  // Field bitField0_:I
      18: iconst_1
      19: iand
      20: iconst_1
      21: if_icmpne     35
      24: iload_1
      25: iconst_1
      26: aload_0
      27: invokevirtual #55                 // Method getClassNameBytes:()Lcom/google/protobuf/ByteString;
      30: invokestatic  #62                 // Method com/google/protobuf/CodedOutputStream.computeBytesSize:(ILcom/google/protobuf/ByteString;)I
      33: iadd
      34: istore_1
      35: aload_0
      36: getfield      #2                  // Field bitField0_:I
      39: iconst_2
      40: iand
      41: iconst_2
      42: if_icmpne     56
      45: iload_1
      46: iconst_2
      47: aload_0
      48: invokevirtual #57                 // Method getMessageBytes:()Lcom/google/protobuf/ByteString;
      51: invokestatic  #62                 // Method com/google/protobuf/CodedOutputStream.computeBytesSize:(ILcom/google/protobuf/ByteString;)I
      54: iadd
      55: istore_1
      56: aload_0
      57: getfield      #2                  // Field bitField0_:I
      60: iconst_4
      61: iand
      62: iconst_4
      63: if_icmpne     77
      66: iload_1
      67: iconst_3
      68: aload_0
      69: getfield      #4                  // Field errorInfo_:Lcom/google/protobuf/ByteString;
      72: invokestatic  #62                 // Method com/google/protobuf/CodedOutputStream.computeBytesSize:(ILcom/google/protobuf/ByteString;)I
      75: iadd
      76: istore_1
      77: iconst_0
      78: istore_2
      79: iload_2
      80: aload_0
      81: getfield      #3                  // Field trace_:Ljava/util/List;
      84: invokeinterface #47,  1           // InterfaceMethod java/util/List.size:()I
      89: if_icmpge     118
      92: iload_1
      93: iconst_4
      94: aload_0
      95: getfield      #3                  // Field trace_:Ljava/util/List;
      98: iload_2
      99: invokeinterface #48,  2           // InterfaceMethod java/util/List.get:(I)Ljava/lang/Object;
     104: checkcast     #58                 // class com/google/protobuf/MessageLite
     107: invokestatic  #63                 // Method com/google/protobuf/CodedOutputStream.computeMessageSize:(ILcom/google/protobuf/MessageLite;)I
     110: iadd
     111: istore_1
     112: iinc          2, 1
     115: goto          79
     118: iload_1
     119: aload_0
     120: invokevirtual #60                 // Method getUnknownFields:()Lcom/google/protobuf/UnknownFieldSet;
     123: invokevirtual #64                 // Method com/google/protobuf/UnknownFieldSet.getSerializedSize:()I
     126: iadd
     127: istore_1
     128: aload_0
     129: iload_1
     130: putfield      #11                 // Field memoizedSerializedSize:I
     133: iload_1
     134: ireturn

  protected java.lang.Object writeReplace() throws java.io.ObjectStreamException;
    Code:
       0: aload_0
       1: invokespecial #65                 // Method com/google/protobuf/GeneratedMessage.writeReplace:()Ljava/lang/Object;
       4: areturn

  public boolean equals(java.lang.Object);
    Code:
       0: aload_1
       1: aload_0
       2: if_acmpne     7
       5: iconst_1
       6: ireturn
       7: aload_1
       8: instanceof    #38                 // class org/apache/hadoop/hbase/protobuf/generated/ErrorHandlingProtos$GenericExceptionMessage
      11: ifne          20
      14: aload_0
      15: aload_1
      16: invokespecial #66                 // Method com/google/protobuf/GeneratedMessage.equals:(Ljava/lang/Object;)Z
      19: ireturn
      20: aload_1
      21: checkcast     #38                 // class org/apache/hadoop/hbase/protobuf/generated/ErrorHandlingProtos$GenericExceptionMessage
      24: astore_2
      25: iconst_1
      26: istore_3
      27: iload_3
      28: ifeq          46
      31: aload_0
      32: invokevirtual #67                 // Method hasClassName:()Z
      35: aload_2
      36: invokevirtual #67                 // Method hasClassName:()Z
      39: if_icmpne     46
      42: iconst_1
      43: goto          47
      46: iconst_0
      47: istore_3
      48: aload_0
      49: invokevirtual #67                 // Method hasClassName:()Z
      52: ifeq          79
      55: iload_3
      56: ifeq          77
      59: aload_0
      60: invokevirtual #68                 // Method getClassName:()Ljava/lang/String;
      63: aload_2
      64: invokevirtual #68                 // Method getClassName:()Ljava/lang/String;
      67: invokevirtual #69                 // Method java/lang/String.equals:(Ljava/lang/Object;)Z
      70: ifeq          77
      73: iconst_1
      74: goto          78
      77: iconst_0
      78: istore_3
      79: iload_3
      80: ifeq          98
      83: aload_0
      84: invokevirtual #70                 // Method hasMessage:()Z
      87: aload_2
      88: invokevirtual #70                 // Method hasMessage:()Z
      91: if_icmpne     98
      94: iconst_1
      95: goto          99
      98: iconst_0
      99: istore_3
     100: aload_0
     101: invokevirtual #70                 // Method hasMessage:()Z
     104: ifeq          131
     107: iload_3
     108: ifeq          129
     111: aload_0
     112: invokevirtual #71                 // Method getMessage:()Ljava/lang/String;
     115: aload_2
     116: invokevirtual #71                 // Method getMessage:()Ljava/lang/String;
     119: invokevirtual #69                 // Method java/lang/String.equals:(Ljava/lang/Object;)Z
     122: ifeq          129
     125: iconst_1
     126: goto          130
     129: iconst_0
     130: istore_3
     131: iload_3
     132: ifeq          150
     135: aload_0
     136: invokevirtual #72                 // Method hasErrorInfo:()Z
     139: aload_2
     140: invokevirtual #72                 // Method hasErrorInfo:()Z
     143: if_icmpne     150
     146: iconst_1
     147: goto          151
     150: iconst_0
     151: istore_3
     152: aload_0
     153: invokevirtual #72                 // Method hasErrorInfo:()Z
     156: ifeq          183
     159: iload_3
     160: ifeq          181
     163: aload_0
     164: invokevirtual #73                 // Method getErrorInfo:()Lcom/google/protobuf/ByteString;
     167: aload_2
     168: invokevirtual #73                 // Method getErrorInfo:()Lcom/google/protobuf/ByteString;
     171: invokevirtual #74                 // Method com/google/protobuf/ByteString.equals:(Ljava/lang/Object;)Z
     174: ifeq          181
     177: iconst_1
     178: goto          182
     181: iconst_0
     182: istore_3
     183: iload_3
     184: ifeq          207
     187: aload_0
     188: invokevirtual #75                 // Method getTraceList:()Ljava/util/List;
     191: aload_2
     192: invokevirtual #75                 // Method getTraceList:()Ljava/util/List;
     195: invokeinterface #76,  2           // InterfaceMethod java/util/List.equals:(Ljava/lang/Object;)Z
     200: ifeq          207
     203: iconst_1
     204: goto          208
     207: iconst_0
     208: istore_3
     209: iload_3
     210: ifeq          231
     213: aload_0
     214: invokevirtual #60                 // Method getUnknownFields:()Lcom/google/protobuf/UnknownFieldSet;
     217: aload_2
     218: invokevirtual #60                 // Method getUnknownFields:()Lcom/google/protobuf/UnknownFieldSet;
     221: invokevirtual #77                 // Method com/google/protobuf/UnknownFieldSet.equals:(Ljava/lang/Object;)Z
     224: ifeq          231
     227: iconst_1
     228: goto          232
     231: iconst_0
     232: istore_3
     233: iload_3
     234: ireturn

  public int hashCode();
    Code:
       0: aload_0
       1: getfield      #12                 // Field memoizedHashCode:I
       4: ifeq          12
       7: aload_0
       8: getfield      #12                 // Field memoizedHashCode:I
      11: ireturn
      12: bipush        41
      14: istore_1
      15: bipush        19
      17: iload_1
      18: imul
      19: aload_0
      20: invokevirtual #78                 // Method getDescriptorForType:()Lcom/google/protobuf/Descriptors$Descriptor;
      23: invokevirtual #79                 // Method java/lang/Object.hashCode:()I
      26: iadd
      27: istore_1
      28: aload_0
      29: invokevirtual #67                 // Method hasClassName:()Z
      32: ifeq          55
      35: bipush        37
      37: iload_1
      38: imul
      39: iconst_1
      40: iadd
      41: istore_1
      42: bipush        53
      44: iload_1
      45: imul
      46: aload_0
      47: invokevirtual #68                 // Method getClassName:()Ljava/lang/String;
      50: invokevirtual #80                 // Method java/lang/String.hashCode:()I
      53: iadd
      54: istore_1
      55: aload_0
      56: invokevirtual #70                 // Method hasMessage:()Z
      59: ifeq          82
      62: bipush        37
      64: iload_1
      65: imul
      66: iconst_2
      67: iadd
      68: istore_1
      69: bipush        53
      71: iload_1
      72: imul
      73: aload_0
      74: invokevirtual #71                 // Method getMessage:()Ljava/lang/String;
      77: invokevirtual #80                 // Method java/lang/String.hashCode:()I
      80: iadd
      81: istore_1
      82: aload_0
      83: invokevirtual #72                 // Method hasErrorInfo:()Z
      86: ifeq          109
      89: bipush        37
      91: iload_1
      92: imul
      93: iconst_3
      94: iadd
      95: istore_1
      96: bipush        53
      98: iload_1
      99: imul
     100: aload_0
     101: invokevirtual #73                 // Method getErrorInfo:()Lcom/google/protobuf/ByteString;
     104: invokevirtual #81                 // Method com/google/protobuf/ByteString.hashCode:()I
     107: iadd
     108: istore_1
     109: aload_0
     110: invokevirtual #82                 // Method getTraceCount:()I
     113: ifle          138
     116: bipush        37
     118: iload_1
     119: imul
     120: iconst_4
     121: iadd
     122: istore_1
     123: bipush        53
     125: iload_1
     126: imul
     127: aload_0
     128: invokevirtual #75                 // Method getTraceList:()Ljava/util/List;
     131: invokeinterface #83,  1           // InterfaceMethod java/util/List.hashCode:()I
     136: iadd
     137: istore_1
     138: bipush        29
     140: iload_1
     141: imul
     142: aload_0
     143: invokevirtual #60                 // Method getUnknownFields:()Lcom/google/protobuf/UnknownFieldSet;
     146: invokevirtual #84                 // Method com/google/protobuf/UnknownFieldSet.hashCode:()I
     149: iadd
     150: istore_1
     151: aload_0
     152: iload_1
     153: putfield      #12                 // Field memoizedHashCode:I
     156: iload_1
     157: ireturn

  public static org.apache.hadoop.hbase.protobuf.generated.ErrorHandlingProtos$GenericExceptionMessage parseFrom(com.google.protobuf.ByteString) throws com.google.protobuf.InvalidProtocolBufferException;
    Code:
       0: getstatic     #41                 // Field PARSER:Lcom/google/protobuf/Parser;
       3: aload_0
       4: invokeinterface #85,  2           // InterfaceMethod com/google/protobuf/Parser.parseFrom:(Lcom/google/protobuf/ByteString;)Ljava/lang/Object;
       9: checkcast     #38                 // class org/apache/hadoop/hbase/protobuf/generated/ErrorHandlingProtos$GenericExceptionMessage
      12: areturn

  public static org.apache.hadoop.hbase.protobuf.generated.ErrorHandlingProtos$GenericExceptionMessage parseFrom(com.google.protobuf.ByteString, com.google.protobuf.ExtensionRegistryLite) throws com.google.protobuf.InvalidProtocolBufferException;
    Code:
       0: getstatic     #41                 // Field PARSER:Lcom/google/protobuf/Parser;
       3: aload_0
       4: aload_1
       5: invokeinterface #86,  3           // InterfaceMethod com/google/protobuf/Parser.parseFrom:(Lcom/google/protobuf/ByteString;Lcom/google/protobuf/ExtensionRegistryLite;)Ljava/lang/Object;
      10: checkcast     #38                 // class org/apache/hadoop/hbase/protobuf/generated/ErrorHandlingProtos$GenericExceptionMessage
      13: areturn

  public static org.apache.hadoop.hbase.protobuf.generated.ErrorHandlingProtos$GenericExceptionMessage parseFrom(byte[]) throws com.google.protobuf.InvalidProtocolBufferException;
    Code:
       0: getstatic     #41                 // Field PARSER:Lcom/google/protobuf/Parser;
       3: aload_0
       4: invokeinterface #87,  2           // InterfaceMethod com/google/protobuf/Parser.parseFrom:([B)Ljava/lang/Object;
       9: checkcast     #38                 // class org/apache/hadoop/hbase/protobuf/generated/ErrorHandlingProtos$GenericExceptionMessage
      12: areturn

  public static org.apache.hadoop.hbase.protobuf.generated.ErrorHandlingProtos$GenericExceptionMessage parseFrom(byte[], com.google.protobuf.ExtensionRegistryLite) throws com.google.protobuf.InvalidProtocolBufferException;
    Code:
       0: getstatic     #41                 // Field PARSER:Lcom/google/protobuf/Parser;
       3: aload_0
       4: aload_1
       5: invokeinterface #88,  3           // InterfaceMethod com/google/protobuf/Parser.parseFrom:([BLcom/google/protobuf/ExtensionRegistryLite;)Ljava/lang/Object;
      10: checkcast     #38                 // class org/apache/hadoop/hbase/protobuf/generated/ErrorHandlingProtos$GenericExceptionMessage
      13: areturn

  public static org.apache.hadoop.hbase.protobuf.generated.ErrorHandlingProtos$GenericExceptionMessage parseFrom(java.io.InputStream) throws java.io.IOException;
    Code:
       0: getstatic     #41                 // Field PARSER:Lcom/google/protobuf/Parser;
       3: aload_0
       4: invokeinterface #89,  2           // InterfaceMethod com/google/protobuf/Parser.parseFrom:(Ljava/io/InputStream;)Ljava/lang/Object;
       9: checkcast     #38                 // class org/apache/hadoop/hbase/protobuf/generated/ErrorHandlingProtos$GenericExceptionMessage
      12: areturn

  public static org.apache.hadoop.hbase.protobuf.generated.ErrorHandlingProtos$GenericExceptionMessage parseFrom(java.io.InputStream, com.google.protobuf.ExtensionRegistryLite) throws java.io.IOException;
    Code:
       0: getstatic     #41                 // Field PARSER:Lcom/google/protobuf/Parser;
       3: aload_0
       4: aload_1
       5: invokeinterface #90,  3           // InterfaceMethod com/google/protobuf/Parser.parseFrom:(Ljava/io/InputStream;Lcom/google/protobuf/ExtensionRegistryLite;)Ljava/lang/Object;
      10: checkcast     #38                 // class org/apache/hadoop/hbase/protobuf/generated/ErrorHandlingProtos$GenericExceptionMessage
      13: areturn

  public static org.apache.hadoop.hbase.protobuf.generated.ErrorHandlingProtos$GenericExceptionMessage parseDelimitedFrom(java.io.InputStream) throws java.io.IOException;
    Code:
       0: getstatic     #41                 // Field PARSER:Lcom/google/protobuf/Parser;
       3: aload_0
       4: invokeinterface #91,  2           // InterfaceMethod com/google/protobuf/Parser.parseDelimitedFrom:(Ljava/io/InputStream;)Ljava/lang/Object;
       9: checkcast     #38                 // class org/apache/hadoop/hbase/protobuf/generated/ErrorHandlingProtos$GenericExceptionMessage
      12: areturn

  public static org.apache.hadoop.hbase.protobuf.generated.ErrorHandlingProtos$GenericExceptionMessage parseDelimitedFrom(java.io.InputStream, com.google.protobuf.ExtensionRegistryLite) throws java.io.IOException;
    Code:
       0: getstatic     #41                 // Field PARSER:Lcom/google/protobuf/Parser;
       3: aload_0
       4: aload_1
       5: invokeinterface #92,  3           // InterfaceMethod com/google/protobuf/Parser.parseDelimitedFrom:(Ljava/io/InputStream;Lcom/google/protobuf/ExtensionRegistryLite;)Ljava/lang/Object;
      10: checkcast     #38                 // class org/apache/hadoop/hbase/protobuf/generated/ErrorHandlingProtos$GenericExceptionMessage
      13: areturn

  public static org.apache.hadoop.hbase.protobuf.generated.ErrorHandlingProtos$GenericExceptionMessage parseFrom(com.google.protobuf.CodedInputStream) throws java.io.IOException;
    Code:
       0: getstatic     #41                 // Field PARSER:Lcom/google/protobuf/Parser;
       3: aload_0
       4: invokeinterface #93,  2           // InterfaceMethod com/google/protobuf/Parser.parseFrom:(Lcom/google/protobuf/CodedInputStream;)Ljava/lang/Object;
       9: checkcast     #38                 // class org/apache/hadoop/hbase/protobuf/generated/ErrorHandlingProtos$GenericExceptionMessage
      12: areturn

  public static org.apache.hadoop.hbase.protobuf.generated.ErrorHandlingProtos$GenericExceptionMessage parseFrom(com.google.protobuf.CodedInputStream, com.google.protobuf.ExtensionRegistryLite) throws java.io.IOException;
    Code:
       0: getstatic     #41                 // Field PARSER:Lcom/google/protobuf/Parser;
       3: aload_0
       4: aload_1
       5: invokeinterface #94,  3           // InterfaceMethod com/google/protobuf/Parser.parseFrom:(Lcom/google/protobuf/CodedInputStream;Lcom/google/protobuf/ExtensionRegistryLite;)Ljava/lang/Object;
      10: checkcast     #38                 // class org/apache/hadoop/hbase/protobuf/generated/ErrorHandlingProtos$GenericExceptionMessage
      13: areturn

  public static org.apache.hadoop.hbase.protobuf.generated.ErrorHandlingProtos$GenericExceptionMessage$Builder newBuilder();
    Code:
       0: invokestatic  #95                 // Method org/apache/hadoop/hbase/protobuf/generated/ErrorHandlingProtos$GenericExceptionMessage$Builder.access$1500:()Lorg/apache/hadoop/hbase/protobuf/generated/ErrorHandlingProtos$GenericExceptionMessage$Builder;
       3: areturn

  public org.apache.hadoop.hbase.protobuf.generated.ErrorHandlingProtos$GenericExceptionMessage$Builder newBuilderForType();
    Code:
       0: invokestatic  #96                 // Method newBuilder:()Lorg/apache/hadoop/hbase/protobuf/generated/ErrorHandlingProtos$GenericExceptionMessage$Builder;
       3: areturn

  public static org.apache.hadoop.hbase.protobuf.generated.ErrorHandlingProtos$GenericExceptionMessage$Builder newBuilder(org.apache.hadoop.hbase.protobuf.generated.ErrorHandlingProtos$GenericExceptionMessage);
    Code:
       0: invokestatic  #96                 // Method newBuilder:()Lorg/apache/hadoop/hbase/protobuf/generated/ErrorHandlingProtos$GenericExceptionMessage$Builder;
       3: aload_0
       4: invokevirtual #97                 // Method org/apache/hadoop/hbase/protobuf/generated/ErrorHandlingProtos$GenericExceptionMessage$Builder.mergeFrom:(Lorg/apache/hadoop/hbase/protobuf/generated/ErrorHandlingProtos$GenericExceptionMessage;)Lorg/apache/hadoop/hbase/protobuf/generated/ErrorHandlingProtos$GenericExceptionMessage$Builder;
       7: areturn

  public org.apache.hadoop.hbase.protobuf.generated.ErrorHandlingProtos$GenericExceptionMessage$Builder toBuilder();
    Code:
       0: aload_0
       1: invokestatic  #98                 // Method newBuilder:(Lorg/apache/hadoop/hbase/protobuf/generated/ErrorHandlingProtos$GenericExceptionMessage;)Lorg/apache/hadoop/hbase/protobuf/generated/ErrorHandlingProtos$GenericExceptionMessage$Builder;
       4: areturn

  protected org.apache.hadoop.hbase.protobuf.generated.ErrorHandlingProtos$GenericExceptionMessage$Builder newBuilderForType(com.google.protobuf.GeneratedMessage$BuilderParent);
    Code:
       0: new           #39                 // class org/apache/hadoop/hbase/protobuf/generated/ErrorHandlingProtos$GenericExceptionMessage$Builder
       3: dup
       4: aload_1
       5: aconst_null
       6: invokespecial #99                 // Method org/apache/hadoop/hbase/protobuf/generated/ErrorHandlingProtos$GenericExceptionMessage$Builder."<init>":(Lcom/google/protobuf/GeneratedMessage$BuilderParent;Lorg/apache/hadoop/hbase/protobuf/generated/ErrorHandlingProtos$1;)V
       9: astore_2
      10: aload_2
      11: areturn

  protected com.google.protobuf.Message$Builder newBuilderForType(com.google.protobuf.GeneratedMessage$BuilderParent);
    Code:
       0: aload_0
       1: aload_1
       2: invokevirtual #100                // Method newBuilderForType:(Lcom/google/protobuf/GeneratedMessage$BuilderParent;)Lorg/apache/hadoop/hbase/protobuf/generated/ErrorHandlingProtos$GenericExceptionMessage$Builder;
       5: areturn

  public com.google.protobuf.Message$Builder toBuilder();
    Code:
       0: aload_0
       1: invokevirtual #101                // Method toBuilder:()Lorg/apache/hadoop/hbase/protobuf/generated/ErrorHandlingProtos$GenericExceptionMessage$Builder;
       4: areturn

  public com.google.protobuf.Message$Builder newBuilderForType();
    Code:
       0: aload_0
       1: invokevirtual #102                // Method newBuilderForType:()Lorg/apache/hadoop/hbase/protobuf/generated/ErrorHandlingProtos$GenericExceptionMessage$Builder;
       4: areturn

  public com.google.protobuf.MessageLite$Builder toBuilder();
    Code:
       0: aload_0
       1: invokevirtual #101                // Method toBuilder:()Lorg/apache/hadoop/hbase/protobuf/generated/ErrorHandlingProtos$GenericExceptionMessage$Builder;
       4: areturn

  public com.google.protobuf.MessageLite$Builder newBuilderForType();
    Code:
       0: aload_0
       1: invokevirtual #102                // Method newBuilderForType:()Lorg/apache/hadoop/hbase/protobuf/generated/ErrorHandlingProtos$GenericExceptionMessage$Builder;
       4: areturn

  public com.google.protobuf.MessageLite getDefaultInstanceForType();
    Code:
       0: aload_0
       1: invokevirtual #103                // Method getDefaultInstanceForType:()Lorg/apache/hadoop/hbase/protobuf/generated/ErrorHandlingProtos$GenericExceptionMessage;
       4: areturn

  public com.google.protobuf.Message getDefaultInstanceForType();
    Code:
       0: aload_0
       1: invokevirtual #103                // Method getDefaultInstanceForType:()Lorg/apache/hadoop/hbase/protobuf/generated/ErrorHandlingProtos$GenericExceptionMessage;
       4: areturn

  org.apache.hadoop.hbase.protobuf.generated.ErrorHandlingProtos$GenericExceptionMessage(com.google.protobuf.CodedInputStream, com.google.protobuf.ExtensionRegistryLite, org.apache.hadoop.hbase.protobuf.generated.ErrorHandlingProtos$1) throws com.google.protobuf.InvalidProtocolBufferException;
    Code:
       0: aload_0
       1: aload_1
       2: aload_2
       3: invokespecial #8                  // Method "<init>":(Lcom/google/protobuf/CodedInputStream;Lcom/google/protobuf/ExtensionRegistryLite;)V
       6: return

  static boolean access$1700();
    Code:
       0: getstatic     #1                  // Field alwaysUseFieldBuilders:Z
       3: ireturn

  org.apache.hadoop.hbase.protobuf.generated.ErrorHandlingProtos$GenericExceptionMessage(com.google.protobuf.GeneratedMessage$Builder, org.apache.hadoop.hbase.protobuf.generated.ErrorHandlingProtos$1);
    Code:
       0: aload_0
       1: aload_1
       2: invokespecial #7                  // Method "<init>":(Lcom/google/protobuf/GeneratedMessage$Builder;)V
       5: return

  static java.lang.Object access$1902(org.apache.hadoop.hbase.protobuf.generated.ErrorHandlingProtos$GenericExceptionMessage, java.lang.Object);
    Code:
       0: aload_0
       1: aload_1
       2: dup_x1
       3: putfield      #6                  // Field className_:Ljava/lang/Object;
       6: areturn

  static java.lang.Object access$2002(org.apache.hadoop.hbase.protobuf.generated.ErrorHandlingProtos$GenericExceptionMessage, java.lang.Object);
    Code:
       0: aload_0
       1: aload_1
       2: dup_x1
       3: putfield      #5                  // Field message_:Ljava/lang/Object;
       6: areturn

  static com.google.protobuf.ByteString access$2102(org.apache.hadoop.hbase.protobuf.generated.ErrorHandlingProtos$GenericExceptionMessage, com.google.protobuf.ByteString);
    Code:
       0: aload_0
       1: aload_1
       2: dup_x1
       3: putfield      #4                  // Field errorInfo_:Lcom/google/protobuf/ByteString;
       6: areturn

  static java.util.List access$2202(org.apache.hadoop.hbase.protobuf.generated.ErrorHandlingProtos$GenericExceptionMessage, java.util.List);
    Code:
       0: aload_0
       1: aload_1
       2: dup_x1
       3: putfield      #3                  // Field trace_:Ljava/util/List;
       6: areturn

  static int access$2302(org.apache.hadoop.hbase.protobuf.generated.ErrorHandlingProtos$GenericExceptionMessage, int);
    Code:
       0: aload_0
       1: iload_1
       2: dup_x1
       3: putfield      #2                  // Field bitField0_:I
       6: ireturn

  static java.lang.Object access$1900(org.apache.hadoop.hbase.protobuf.generated.ErrorHandlingProtos$GenericExceptionMessage);
    Code:
       0: aload_0
       1: getfield      #6                  // Field className_:Ljava/lang/Object;
       4: areturn

  static java.lang.Object access$2000(org.apache.hadoop.hbase.protobuf.generated.ErrorHandlingProtos$GenericExceptionMessage);
    Code:
       0: aload_0
       1: getfield      #5                  // Field message_:Ljava/lang/Object;
       4: areturn

  static java.util.List access$2200(org.apache.hadoop.hbase.protobuf.generated.ErrorHandlingProtos$GenericExceptionMessage);
    Code:
       0: aload_0
       1: getfield      #3                  // Field trace_:Ljava/util/List;
       4: areturn

  static boolean access$2400();
    Code:
       0: getstatic     #1                  // Field alwaysUseFieldBuilders:Z
       3: ireturn

  static {};
    Code:
       0: new           #104                // class org/apache/hadoop/hbase/protobuf/generated/ErrorHandlingProtos$GenericExceptionMessage$1
       3: dup
       4: invokespecial #105                // Method org/apache/hadoop/hbase/protobuf/generated/ErrorHandlingProtos$GenericExceptionMessage$1."<init>":()V
       7: putstatic     #41                 // Field PARSER:Lcom/google/protobuf/Parser;
      10: new           #38                 // class org/apache/hadoop/hbase/protobuf/generated/ErrorHandlingProtos$GenericExceptionMessage
      13: dup
      14: iconst_1
      15: invokespecial #106                // Method "<init>":(Z)V
      18: putstatic     #17                 // Field defaultInstance:Lorg/apache/hadoop/hbase/protobuf/generated/ErrorHandlingProtos$GenericExceptionMessage;
      21: getstatic     #17                 // Field defaultInstance:Lorg/apache/hadoop/hbase/protobuf/generated/ErrorHandlingProtos$GenericExceptionMessage;
      24: invokespecial #18                 // Method initFields:()V
      27: return
}
