Compiled from "ExceedOperationQuota.java"
public class org.apache.hadoop.hbase.quotas.ExceedOperationQuota extends org.apache.hadoop.hbase.quotas.DefaultOperationQuota {
  public org.apache.hadoop.hbase.quotas.ExceedOperationQuota(org.apache.hadoop.conf.Configuration, org.apache.hadoop.hbase.quotas.QuotaLimiter, org.apache.hadoop.hbase.quotas.QuotaLimiter...);
    Code:
       0: aload_0
       1: aload_1
       2: aload_3
       3: invokespecial #1                  // Method org/apache/hadoop/hbase/quotas/DefaultOperationQuota."<init>":(Lorg/apache/hadoop/conf/Configuration;[Lorg/apache/hadoop/hbase/quotas/QuotaLimiter;)V
       6: aload_0
       7: aload_2
       8: putfield      #2                  // Field regionServerLimiter:Lorg/apache/hadoop/hbase/quotas/QuotaLimiter;
      11: return

  public void checkQuota(int, int, int) throws org.apache.hadoop.hbase.quotas.RpcThrottlingException;
    Code:
       0: aload_0
       1: getfield      #2                  // Field regionServerLimiter:Lorg/apache/hadoop/hbase/quotas/QuotaLimiter;
       4: invokeinterface #3,  1            // InterfaceMethod org/apache/hadoop/hbase/quotas/QuotaLimiter.isBypass:()Z
       9: ifeq          32
      12: getstatic     #4                  // Field LOG:Lorg/slf4j/Logger;
      15: ldc           #5                  // String Exceed throttle quota is enabled but no region server quotas found
      17: invokeinterface #6,  2            // InterfaceMethod org/slf4j/Logger.warn:(Ljava/lang/String;)V
      22: aload_0
      23: iload_1
      24: iload_2
      25: iload_3
      26: invokespecial #7                  // Method org/apache/hadoop/hbase/quotas/DefaultOperationQuota.checkQuota:(III)V
      29: goto          275
      32: aload_0
      33: iload_1
      34: iload_2
      35: iload_3
      36: invokevirtual #8                  // Method updateEstimateConsumeQuota:(III)V
      39: aload_0
      40: getfield      #2                  // Field regionServerLimiter:Lorg/apache/hadoop/hbase/quotas/QuotaLimiter;
      43: iload_1
      44: i2l
      45: aload_0
      46: getfield      #9                  // Field writeConsumed:J
      49: iload_2
      50: iload_3
      51: iadd
      52: i2l
      53: aload_0
      54: getfield      #10                 // Field readConsumed:J
      57: aload_0
      58: getfield      #11                 // Field writeCapacityUnitConsumed:J
      61: aload_0
      62: getfield      #12                 // Field readCapacityUnitConsumed:J
      65: invokeinterface #13,  13          // InterfaceMethod org/apache/hadoop/hbase/quotas/QuotaLimiter.checkQuota:(JJJJJJ)V
      70: iconst_0
      71: istore        4
      73: aload_0
      74: iload_1
      75: iload_2
      76: iload_3
      77: invokespecial #7                  // Method org/apache/hadoop/hbase/quotas/DefaultOperationQuota.checkQuota:(III)V
      80: goto          134
      83: astore        5
      85: iconst_1
      86: istore        4
      88: getstatic     #4                  // Field LOG:Lorg/slf4j/Logger;
      91: invokeinterface #15,  1           // InterfaceMethod org/slf4j/Logger.isDebugEnabled:()Z
      96: ifeq          134
      99: getstatic     #4                  // Field LOG:Lorg/slf4j/Logger;
     102: ldc           #16                 // String Read/Write requests num exceeds quota: writes:{} reads:{} scan:{}, try use region server quota
     104: iconst_3
     105: anewarray     #17                 // class java/lang/Object
     108: dup
     109: iconst_0
     110: iload_1
     111: invokestatic  #18                 // Method java/lang/Integer.valueOf:(I)Ljava/lang/Integer;
     114: aastore
     115: dup
     116: iconst_1
     117: iload_2
     118: invokestatic  #18                 // Method java/lang/Integer.valueOf:(I)Ljava/lang/Integer;
     121: aastore
     122: dup
     123: iconst_2
     124: iload_3
     125: invokestatic  #18                 // Method java/lang/Integer.valueOf:(I)Ljava/lang/Integer;
     128: aastore
     129: invokeinterface #19,  3           // InterfaceMethod org/slf4j/Logger.debug:(Ljava/lang/String;[Ljava/lang/Object;)V
     134: aload_0
     135: aload_0
     136: getfield      #20                 // Field readAvailable:J
     139: aload_0
     140: getfield      #2                  // Field regionServerLimiter:Lorg/apache/hadoop/hbase/quotas/QuotaLimiter;
     143: invokeinterface #21,  1           // InterfaceMethod org/apache/hadoop/hbase/quotas/QuotaLimiter.getReadAvailable:()J
     148: invokestatic  #22                 // Method java/lang/Math.max:(JJ)J
     151: putfield      #20                 // Field readAvailable:J
     154: aload_0
     155: aload_0
     156: getfield      #23                 // Field writeAvailable:J
     159: aload_0
     160: getfield      #2                  // Field regionServerLimiter:Lorg/apache/hadoop/hbase/quotas/QuotaLimiter;
     163: invokeinterface #24,  1           // InterfaceMethod org/apache/hadoop/hbase/quotas/QuotaLimiter.getWriteAvailable:()J
     168: invokestatic  #22                 // Method java/lang/Math.max:(JJ)J
     171: putfield      #23                 // Field writeAvailable:J
     174: aload_0
     175: getfield      #2                  // Field regionServerLimiter:Lorg/apache/hadoop/hbase/quotas/QuotaLimiter;
     178: iload_1
     179: i2l
     180: aload_0
     181: getfield      #9                  // Field writeConsumed:J
     184: iload_2
     185: iload_3
     186: iadd
     187: i2l
     188: aload_0
     189: getfield      #10                 // Field readConsumed:J
     192: aload_0
     193: getfield      #11                 // Field writeCapacityUnitConsumed:J
     196: aload_0
     197: getfield      #11                 // Field writeCapacityUnitConsumed:J
     200: invokeinterface #25,  13          // InterfaceMethod org/apache/hadoop/hbase/quotas/QuotaLimiter.grabQuota:(JJJJJJ)V
     205: iload         4
     207: ifeq          275
     210: aload_0
     211: getfield      #26                 // Field limiters:Ljava/util/List;
     214: invokeinterface #27,  1           // InterfaceMethod java/util/List.iterator:()Ljava/util/Iterator;
     219: astore        5
     221: aload         5
     223: invokeinterface #28,  1           // InterfaceMethod java/util/Iterator.hasNext:()Z
     228: ifeq          275
     231: aload         5
     233: invokeinterface #29,  1           // InterfaceMethod java/util/Iterator.next:()Ljava/lang/Object;
     238: checkcast     #30                 // class org/apache/hadoop/hbase/quotas/QuotaLimiter
     241: astore        6
     243: aload         6
     245: iload_1
     246: i2l
     247: aload_0
     248: getfield      #9                  // Field writeConsumed:J
     251: iload_2
     252: iload_3
     253: iadd
     254: i2l
     255: aload_0
     256: getfield      #10                 // Field readConsumed:J
     259: aload_0
     260: getfield      #11                 // Field writeCapacityUnitConsumed:J
     263: aload_0
     264: getfield      #11                 // Field writeCapacityUnitConsumed:J
     267: invokeinterface #25,  13          // InterfaceMethod org/apache/hadoop/hbase/quotas/QuotaLimiter.grabQuota:(JJJJJJ)V
     272: goto          221
     275: return
    Exception table:
       from    to  target type
          73    80    83   Class org/apache/hadoop/hbase/quotas/RpcThrottlingException

  public void close();
    Code:
       0: aload_0
       1: invokespecial #31                 // Method org/apache/hadoop/hbase/quotas/DefaultOperationQuota.close:()V
       4: aload_0
       5: getfield      #32                 // Field writeDiff:J
       8: lconst_0
       9: lcmp
      10: ifeq          30
      13: aload_0
      14: getfield      #2                  // Field regionServerLimiter:Lorg/apache/hadoop/hbase/quotas/QuotaLimiter;
      17: aload_0
      18: getfield      #32                 // Field writeDiff:J
      21: aload_0
      22: getfield      #33                 // Field writeCapacityUnitDiff:J
      25: invokeinterface #34,  5           // InterfaceMethod org/apache/hadoop/hbase/quotas/QuotaLimiter.consumeWrite:(JJ)V
      30: aload_0
      31: getfield      #35                 // Field readDiff:J
      34: lconst_0
      35: lcmp
      36: ifeq          56
      39: aload_0
      40: getfield      #2                  // Field regionServerLimiter:Lorg/apache/hadoop/hbase/quotas/QuotaLimiter;
      43: aload_0
      44: getfield      #35                 // Field readDiff:J
      47: aload_0
      48: getfield      #36                 // Field readCapacityUnitDiff:J
      51: invokeinterface #37,  5           // InterfaceMethod org/apache/hadoop/hbase/quotas/QuotaLimiter.consumeRead:(JJ)V
      56: return

  static {};
    Code:
       0: ldc           #38                 // class org/apache/hadoop/hbase/quotas/ExceedOperationQuota
       2: invokestatic  #39                 // Method org/slf4j/LoggerFactory.getLogger:(Ljava/lang/Class;)Lorg/slf4j/Logger;
       5: putstatic     #4                  // Field LOG:Lorg/slf4j/Logger;
       8: return
}
