Compiled from "ExpiredMobFileCleaner.java"
public class org.apache.hadoop.hbase.mob.ExpiredMobFileCleaner extends org.apache.hadoop.conf.Configured implements org.apache.hadoop.util.Tool {
  public org.apache.hadoop.hbase.mob.ExpiredMobFileCleaner();
    Code:
       0: aload_0
       1: invokespecial #1                  // Method org/apache/hadoop/conf/Configured."<init>":()V
       4: return

  public void cleanExpiredMobFiles(java.lang.String, org.apache.hadoop.hbase.client.ColumnFamilyDescriptor) throws java.io.IOException;
    Code:
       0: aload_0
       1: invokevirtual #2                  // Method getConf:()Lorg/apache/hadoop/conf/Configuration;
       4: astore_3
       5: aload_1
       6: invokestatic  #3                  // Method org/apache/hadoop/hbase/TableName.valueOf:(Ljava/lang/String;)Lorg/apache/hadoop/hbase/TableName;
       9: astore        4
      11: aload_3
      12: invokestatic  #4                  // Method org/apache/hadoop/fs/FileSystem.get:(Lorg/apache/hadoop/conf/Configuration;)Lorg/apache/hadoop/fs/FileSystem;
      15: astore        5
      17: getstatic     #5                  // Field LOG:Lorg/slf4j/Logger;
      20: new           #6                  // class java/lang/StringBuilder
      23: dup
      24: invokespecial #7                  // Method java/lang/StringBuilder."<init>":()V
      27: ldc           #8                  // String Cleaning the expired MOB files of
      29: invokevirtual #9                  // Method java/lang/StringBuilder.append:(Ljava/lang/String;)Ljava/lang/StringBuilder;
      32: aload_2
      33: invokeinterface #10,  1           // InterfaceMethod org/apache/hadoop/hbase/client/ColumnFamilyDescriptor.getNameAsString:()Ljava/lang/String;
      38: invokevirtual #9                  // Method java/lang/StringBuilder.append:(Ljava/lang/String;)Ljava/lang/StringBuilder;
      41: ldc           #11                 // String  in
      43: invokevirtual #9                  // Method java/lang/StringBuilder.append:(Ljava/lang/String;)Ljava/lang/StringBuilder;
      46: aload_1
      47: invokevirtual #9                  // Method java/lang/StringBuilder.append:(Ljava/lang/String;)Ljava/lang/StringBuilder;
      50: invokevirtual #12                 // Method java/lang/StringBuilder.toString:()Ljava/lang/String;
      53: invokeinterface #13,  2           // InterfaceMethod org/slf4j/Logger.info:(Ljava/lang/String;)V
      58: new           #14                 // class org/apache/hadoop/conf/Configuration
      61: dup
      62: aload_3
      63: invokespecial #15                 // Method org/apache/hadoop/conf/Configuration."<init>":(Lorg/apache/hadoop/conf/Configuration;)V
      66: astore        6
      68: aload         6
      70: ldc           #17                 // String hfile.block.cache.size
      72: fconst_0
      73: invokevirtual #18                 // Method org/apache/hadoop/conf/Configuration.setFloat:(Ljava/lang/String;F)V
      76: new           #19                 // class org/apache/hadoop/hbase/io/hfile/CacheConfig
      79: dup
      80: aload         6
      82: invokespecial #20                 // Method org/apache/hadoop/hbase/io/hfile/CacheConfig."<init>":(Lorg/apache/hadoop/conf/Configuration;)V
      85: astore        7
      87: aload         5
      89: aload_3
      90: aload         4
      92: aload_2
      93: aload         7
      95: invokestatic  #21                 // Method org/apache/hadoop/hbase/util/EnvironmentEdgeManager.currentTime:()J
      98: invokestatic  #22                 // Method org/apache/hadoop/hbase/mob/MobUtils.cleanExpiredMobFiles:(Lorg/apache/hadoop/fs/FileSystem;Lorg/apache/hadoop/conf/Configuration;Lorg/apache/hadoop/hbase/TableName;Lorg/apache/hadoop/hbase/client/ColumnFamilyDescriptor;Lorg/apache/hadoop/hbase/io/hfile/CacheConfig;J)V
     101: return

  public static void main(java.lang.String[]) throws java.lang.Exception;
    Code:
       0: invokestatic  #23                 // Method org/apache/hadoop/hbase/HBaseConfiguration.create:()Lorg/apache/hadoop/conf/Configuration;
       3: astore_1
       4: aload_1
       5: new           #24                 // class org/apache/hadoop/hbase/mob/ExpiredMobFileCleaner
       8: dup
       9: invokespecial #25                 // Method "<init>":()V
      12: aload_0
      13: invokestatic  #26                 // Method org/apache/hadoop/util/ToolRunner.run:(Lorg/apache/hadoop/conf/Configuration;Lorg/apache/hadoop/util/Tool;[Ljava/lang/String;)I
      16: pop
      17: return

  public int run(java.lang.String[]) throws java.lang.Exception;
    Code:
       0: aload_1
       1: arraylength
       2: iconst_2
       3: if_icmpeq     12
       6: aload_0
       7: invokespecial #34                 // Method printUsage:()V
      10: iconst_1
      11: ireturn
      12: aload_1
      13: iconst_0
      14: aaload
      15: astore_2
      16: aload_1
      17: iconst_1
      18: aaload
      19: astore_3
      20: aload_2
      21: invokestatic  #3                  // Method org/apache/hadoop/hbase/TableName.valueOf:(Ljava/lang/String;)Lorg/apache/hadoop/hbase/TableName;
      24: astore        4
      26: aload_0
      27: invokevirtual #2                  // Method getConf:()Lorg/apache/hadoop/conf/Configuration;
      30: invokestatic  #35                 // Method org/apache/hadoop/hbase/client/HBaseAdmin.available:(Lorg/apache/hadoop/conf/Configuration;)V
      33: aload_0
      34: invokevirtual #2                  // Method getConf:()Lorg/apache/hadoop/conf/Configuration;
      37: invokestatic  #36                 // Method org/apache/hadoop/hbase/client/ConnectionFactory.createConnection:(Lorg/apache/hadoop/conf/Configuration;)Lorg/apache/hadoop/hbase/client/Connection;
      40: astore        5
      42: aload         5
      44: invokeinterface #37,  1           // InterfaceMethod org/apache/hadoop/hbase/client/Connection.getAdmin:()Lorg/apache/hadoop/hbase/client/Admin;
      49: astore        6
      51: aload         6
      53: aload         4
      55: invokeinterface #38,  2           // InterfaceMethod org/apache/hadoop/hbase/client/Admin.getDescriptor:(Lorg/apache/hadoop/hbase/TableName;)Lorg/apache/hadoop/hbase/client/TableDescriptor;
      60: astore        7
      62: aload         7
      64: aload_3
      65: invokestatic  #39                 // Method org/apache/hadoop/hbase/util/Bytes.toBytes:(Ljava/lang/String;)[B
      68: invokeinterface #40,  2           // InterfaceMethod org/apache/hadoop/hbase/client/TableDescriptor.getColumnFamily:([B)Lorg/apache/hadoop/hbase/client/ColumnFamilyDescriptor;
      73: astore        8
      75: aload         8
      77: ifnull        90
      80: aload         8
      82: invokeinterface #41,  1           // InterfaceMethod org/apache/hadoop/hbase/client/ColumnFamilyDescriptor.isMobEnabled:()Z
      87: ifne          122
      90: new           #42                 // class java/io/IOException
      93: dup
      94: new           #6                  // class java/lang/StringBuilder
      97: dup
      98: invokespecial #7                  // Method java/lang/StringBuilder."<init>":()V
     101: ldc           #43                 // String Column family
     103: invokevirtual #9                  // Method java/lang/StringBuilder.append:(Ljava/lang/String;)Ljava/lang/StringBuilder;
     106: aload_3
     107: invokevirtual #9                  // Method java/lang/StringBuilder.append:(Ljava/lang/String;)Ljava/lang/StringBuilder;
     110: ldc           #44                 // String  is not a MOB column family
     112: invokevirtual #9                  // Method java/lang/StringBuilder.append:(Ljava/lang/String;)Ljava/lang/StringBuilder;
     115: invokevirtual #12                 // Method java/lang/StringBuilder.toString:()Ljava/lang/String;
     118: invokespecial #45                 // Method java/io/IOException."<init>":(Ljava/lang/String;)V
     121: athrow
     122: aload         8
     124: invokeinterface #46,  1           // InterfaceMethod org/apache/hadoop/hbase/client/ColumnFamilyDescriptor.getMinVersions:()I
     129: ifle          142
     132: new           #42                 // class java/io/IOException
     135: dup
     136: ldc           #47                 // String The minVersions of the column family is not 0, could not be handled by this cleaner
     138: invokespecial #45                 // Method java/io/IOException."<init>":(Ljava/lang/String;)V
     141: athrow
     142: aload_0
     143: aload_2
     144: aload         8
     146: invokevirtual #48                 // Method cleanExpiredMobFiles:(Ljava/lang/String;Lorg/apache/hadoop/hbase/client/ColumnFamilyDescriptor;)V
     149: iconst_0
     150: istore        9
     152: aload         6
     154: invokeinterface #49,  1           // InterfaceMethod org/apache/hadoop/hbase/client/Admin.close:()V
     159: aload         5
     161: invokeinterface #50,  1           // InterfaceMethod org/apache/hadoop/hbase/client/Connection.close:()V
     166: goto          183
     169: astore        10
     171: getstatic     #5                  // Field LOG:Lorg/slf4j/Logger;
     174: ldc           #51                 // String Failed to close the connection.
     176: aload         10
     178: invokeinterface #52,  3           // InterfaceMethod org/slf4j/Logger.error:(Ljava/lang/String;Ljava/lang/Throwable;)V
     183: iload         9
     185: ireturn
     186: astore        11
     188: aload         6
     190: invokeinterface #49,  1           // InterfaceMethod org/apache/hadoop/hbase/client/Admin.close:()V
     195: aload         5
     197: invokeinterface #50,  1           // InterfaceMethod org/apache/hadoop/hbase/client/Connection.close:()V
     202: goto          219
     205: astore        12
     207: getstatic     #5                  // Field LOG:Lorg/slf4j/Logger;
     210: ldc           #51                 // String Failed to close the connection.
     212: aload         12
     214: invokeinterface #52,  3           // InterfaceMethod org/slf4j/Logger.error:(Ljava/lang/String;Ljava/lang/Throwable;)V
     219: aload         11
     221: athrow
    Exception table:
       from    to  target type
         159   166   169   Class java/io/IOException
          51   152   186   any
         195   202   205   Class java/io/IOException
         186   188   186   any

  static {};
    Code:
       0: ldc           #24                 // class org/apache/hadoop/hbase/mob/ExpiredMobFileCleaner
       2: invokestatic  #53                 // Method org/slf4j/LoggerFactory.getLogger:(Ljava/lang/Class;)Lorg/slf4j/Logger;
       5: putstatic     #5                  // Field LOG:Lorg/slf4j/Logger;
       8: return
}
