Compiled from "ExplicitColumnTracker.java"
public class org.apache.hadoop.hbase.regionserver.querymatcher.ExplicitColumnTracker implements org.apache.hadoop.hbase.regionserver.querymatcher.ColumnTracker {
  static final boolean $assertionsDisabled;

  public org.apache.hadoop.hbase.regionserver.querymatcher.ExplicitColumnTracker(java.util.NavigableSet<byte[]>, int, int, long);
    Code:
       0: aload_0
       1: invokespecial #1                  // Method java/lang/Object."<init>":()V
       4: aload_0
       5: iload_3
       6: putfield      #2                  // Field maxVersions:I
       9: aload_0
      10: iload_2
      11: putfield      #3                  // Field minVersions:I
      14: aload_0
      15: lload         4
      17: putfield      #4                  // Field oldestStamp:J
      20: aload_0
      21: aload_1
      22: invokeinterface #5,  1            // InterfaceMethod java/util/NavigableSet.size:()I
      27: anewarray     #6                  // class org/apache/hadoop/hbase/regionserver/querymatcher/ColumnCount
      30: putfield      #7                  // Field columns:[Lorg/apache/hadoop/hbase/regionserver/querymatcher/ColumnCount;
      33: iconst_0
      34: istore        6
      36: aload_1
      37: invokeinterface #8,  1            // InterfaceMethod java/util/NavigableSet.iterator:()Ljava/util/Iterator;
      42: astore        7
      44: aload         7
      46: invokeinterface #9,  1            // InterfaceMethod java/util/Iterator.hasNext:()Z
      51: ifeq          88
      54: aload         7
      56: invokeinterface #10,  1           // InterfaceMethod java/util/Iterator.next:()Ljava/lang/Object;
      61: checkcast     #11                 // class "[B"
      64: astore        8
      66: aload_0
      67: getfield      #7                  // Field columns:[Lorg/apache/hadoop/hbase/regionserver/querymatcher/ColumnCount;
      70: iload         6
      72: iinc          6, 1
      75: new           #6                  // class org/apache/hadoop/hbase/regionserver/querymatcher/ColumnCount
      78: dup
      79: aload         8
      81: invokespecial #12                 // Method org/apache/hadoop/hbase/regionserver/querymatcher/ColumnCount."<init>":([B)V
      84: aastore
      85: goto          44
      88: aload_0
      89: invokevirtual #13                 // Method reset:()V
      92: return

  public boolean done();
    Code:
       0: aload_0
       1: getfield      #14                 // Field index:I
       4: aload_0
       5: getfield      #7                  // Field columns:[Lorg/apache/hadoop/hbase/regionserver/querymatcher/ColumnCount;
       8: arraylength
       9: if_icmplt     16
      12: iconst_1
      13: goto          17
      16: iconst_0
      17: ireturn

  public org.apache.hadoop.hbase.regionserver.querymatcher.ColumnCount getColumnHint();
    Code:
       0: aload_0
       1: getfield      #15                 // Field column:Lorg/apache/hadoop/hbase/regionserver/querymatcher/ColumnCount;
       4: areturn

  public org.apache.hadoop.hbase.regionserver.querymatcher.ScanQueryMatcher$MatchCode checkColumn(org.apache.hadoop.hbase.Cell, byte);
    Code:
       0: getstatic     #16                 // Field $assertionsDisabled:Z
       3: ifne          21
       6: iload_2
       7: invokestatic  #17                 // Method org/apache/hadoop/hbase/PrivateCellUtil.isDelete:(B)Z
      10: ifeq          21
      13: new           #18                 // class java/lang/AssertionError
      16: dup
      17: invokespecial #19                 // Method java/lang/AssertionError."<init>":()V
      20: athrow
      21: aload_0
      22: invokevirtual #20                 // Method done:()Z
      25: ifeq          32
      28: getstatic     #21                 // Field org/apache/hadoop/hbase/regionserver/querymatcher/ScanQueryMatcher$MatchCode.SEEK_NEXT_ROW:Lorg/apache/hadoop/hbase/regionserver/querymatcher/ScanQueryMatcher$MatchCode;
      31: areturn
      32: aload_0
      33: getfield      #15                 // Field column:Lorg/apache/hadoop/hbase/regionserver/querymatcher/ColumnCount;
      36: ifnonnull     43
      39: getstatic     #21                 // Field org/apache/hadoop/hbase/regionserver/querymatcher/ScanQueryMatcher$MatchCode.SEEK_NEXT_ROW:Lorg/apache/hadoop/hbase/regionserver/querymatcher/ScanQueryMatcher$MatchCode;
      42: areturn
      43: aload_1
      44: aload_0
      45: getfield      #15                 // Field column:Lorg/apache/hadoop/hbase/regionserver/querymatcher/ColumnCount;
      48: invokevirtual #22                 // Method org/apache/hadoop/hbase/regionserver/querymatcher/ColumnCount.getBuffer:()[B
      51: aload_0
      52: getfield      #15                 // Field column:Lorg/apache/hadoop/hbase/regionserver/querymatcher/ColumnCount;
      55: invokevirtual #23                 // Method org/apache/hadoop/hbase/regionserver/querymatcher/ColumnCount.getOffset:()I
      58: aload_0
      59: getfield      #15                 // Field column:Lorg/apache/hadoop/hbase/regionserver/querymatcher/ColumnCount;
      62: invokevirtual #24                 // Method org/apache/hadoop/hbase/regionserver/querymatcher/ColumnCount.getLength:()I
      65: invokestatic  #25                 // Method org/apache/hadoop/hbase/CellUtil.compareQualifiers:(Lorg/apache/hadoop/hbase/Cell;[BII)I
      68: istore_3
      69: iload_3
      70: ifne          77
      73: getstatic     #26                 // Field org/apache/hadoop/hbase/regionserver/querymatcher/ScanQueryMatcher$MatchCode.INCLUDE:Lorg/apache/hadoop/hbase/regionserver/querymatcher/ScanQueryMatcher$MatchCode;
      76: areturn
      77: aload_0
      78: invokespecial #27                 // Method resetTS:()V
      81: iload_3
      82: ifge          89
      85: getstatic     #28                 // Field org/apache/hadoop/hbase/regionserver/querymatcher/ScanQueryMatcher$MatchCode.SEEK_NEXT_COL:Lorg/apache/hadoop/hbase/regionserver/querymatcher/ScanQueryMatcher$MatchCode;
      88: areturn
      89: iload_3
      90: ifle          127
      93: aload_0
      94: dup
      95: getfield      #14                 // Field index:I
      98: iconst_1
      99: iadd
     100: putfield      #14                 // Field index:I
     103: aload_0
     104: invokevirtual #20                 // Method done:()Z
     107: ifeq          114
     110: getstatic     #21                 // Field org/apache/hadoop/hbase/regionserver/querymatcher/ScanQueryMatcher$MatchCode.SEEK_NEXT_ROW:Lorg/apache/hadoop/hbase/regionserver/querymatcher/ScanQueryMatcher$MatchCode;
     113: areturn
     114: aload_0
     115: aload_0
     116: getfield      #7                  // Field columns:[Lorg/apache/hadoop/hbase/regionserver/querymatcher/ColumnCount;
     119: aload_0
     120: getfield      #14                 // Field index:I
     123: aaload
     124: putfield      #15                 // Field column:Lorg/apache/hadoop/hbase/regionserver/querymatcher/ColumnCount;
     127: goto          21

  public org.apache.hadoop.hbase.regionserver.querymatcher.ScanQueryMatcher$MatchCode checkVersions(org.apache.hadoop.hbase.Cell, long, byte, boolean) throws java.io.IOException;
    Code:
       0: getstatic     #16                 // Field $assertionsDisabled:Z
       3: ifne          22
       6: iload         4
       8: invokestatic  #17                 // Method org/apache/hadoop/hbase/PrivateCellUtil.isDelete:(B)Z
      11: ifeq          22
      14: new           #18                 // class java/lang/AssertionError
      17: dup
      18: invokespecial #19                 // Method java/lang/AssertionError."<init>":()V
      21: athrow
      22: iload         5
      24: ifeq          31
      27: getstatic     #26                 // Field org/apache/hadoop/hbase/regionserver/querymatcher/ScanQueryMatcher$MatchCode.INCLUDE:Lorg/apache/hadoop/hbase/regionserver/querymatcher/ScanQueryMatcher$MatchCode;
      30: areturn
      31: aload_0
      32: lload_2
      33: invokespecial #29                 // Method sameAsPreviousTS:(J)Z
      36: ifeq          43
      39: getstatic     #30                 // Field org/apache/hadoop/hbase/regionserver/querymatcher/ScanQueryMatcher$MatchCode.SKIP:Lorg/apache/hadoop/hbase/regionserver/querymatcher/ScanQueryMatcher$MatchCode;
      42: areturn
      43: aload_0
      44: getfield      #15                 // Field column:Lorg/apache/hadoop/hbase/regionserver/querymatcher/ColumnCount;
      47: invokevirtual #31                 // Method org/apache/hadoop/hbase/regionserver/querymatcher/ColumnCount.increment:()I
      50: istore        6
      52: iload         6
      54: aload_0
      55: getfield      #2                  // Field maxVersions:I
      58: if_icmpge     78
      61: iload         6
      63: aload_0
      64: getfield      #3                  // Field minVersions:I
      67: if_icmplt     125
      70: aload_0
      71: lload_2
      72: invokespecial #32                 // Method isExpired:(J)Z
      75: ifeq          125
      78: aload_0
      79: dup
      80: getfield      #14                 // Field index:I
      83: iconst_1
      84: iadd
      85: putfield      #14                 // Field index:I
      88: aload_0
      89: invokespecial #27                 // Method resetTS:()V
      92: aload_0
      93: invokevirtual #20                 // Method done:()Z
      96: ifeq          108
      99: aload_0
     100: aconst_null
     101: putfield      #15                 // Field column:Lorg/apache/hadoop/hbase/regionserver/querymatcher/ColumnCount;
     104: getstatic     #33                 // Field org/apache/hadoop/hbase/regionserver/querymatcher/ScanQueryMatcher$MatchCode.INCLUDE_AND_SEEK_NEXT_ROW:Lorg/apache/hadoop/hbase/regionserver/querymatcher/ScanQueryMatcher$MatchCode;
     107: areturn
     108: aload_0
     109: aload_0
     110: getfield      #7                  // Field columns:[Lorg/apache/hadoop/hbase/regionserver/querymatcher/ColumnCount;
     113: aload_0
     114: getfield      #14                 // Field index:I
     117: aaload
     118: putfield      #15                 // Field column:Lorg/apache/hadoop/hbase/regionserver/querymatcher/ColumnCount;
     121: getstatic     #34                 // Field org/apache/hadoop/hbase/regionserver/querymatcher/ScanQueryMatcher$MatchCode.INCLUDE_AND_SEEK_NEXT_COL:Lorg/apache/hadoop/hbase/regionserver/querymatcher/ScanQueryMatcher$MatchCode;
     124: areturn
     125: aload_0
     126: lload_2
     127: invokespecial #35                 // Method setTS:(J)V
     130: getstatic     #26                 // Field org/apache/hadoop/hbase/regionserver/querymatcher/ScanQueryMatcher$MatchCode.INCLUDE:Lorg/apache/hadoop/hbase/regionserver/querymatcher/ScanQueryMatcher$MatchCode;
     133: areturn

  public void reset();
    Code:
       0: aload_0
       1: iconst_0
       2: putfield      #14                 // Field index:I
       5: aload_0
       6: aload_0
       7: getfield      #7                  // Field columns:[Lorg/apache/hadoop/hbase/regionserver/querymatcher/ColumnCount;
      10: aload_0
      11: getfield      #14                 // Field index:I
      14: aaload
      15: putfield      #15                 // Field column:Lorg/apache/hadoop/hbase/regionserver/querymatcher/ColumnCount;
      18: aload_0
      19: getfield      #7                  // Field columns:[Lorg/apache/hadoop/hbase/regionserver/querymatcher/ColumnCount;
      22: astore_1
      23: aload_1
      24: arraylength
      25: istore_2
      26: iconst_0
      27: istore_3
      28: iload_3
      29: iload_2
      30: if_icmpge     50
      33: aload_1
      34: iload_3
      35: aaload
      36: astore        4
      38: aload         4
      40: iconst_0
      41: invokevirtual #36                 // Method org/apache/hadoop/hbase/regionserver/querymatcher/ColumnCount.setCount:(I)V
      44: iinc          3, 1
      47: goto          28
      50: aload_0
      51: invokespecial #27                 // Method resetTS:()V
      54: return

  public void doneWithColumn(org.apache.hadoop.hbase.Cell);
    Code:
       0: aload_0
       1: getfield      #15                 // Field column:Lorg/apache/hadoop/hbase/regionserver/querymatcher/ColumnCount;
       4: ifnull        87
       7: aload_1
       8: aload_0
       9: getfield      #15                 // Field column:Lorg/apache/hadoop/hbase/regionserver/querymatcher/ColumnCount;
      12: invokevirtual #22                 // Method org/apache/hadoop/hbase/regionserver/querymatcher/ColumnCount.getBuffer:()[B
      15: aload_0
      16: getfield      #15                 // Field column:Lorg/apache/hadoop/hbase/regionserver/querymatcher/ColumnCount;
      19: invokevirtual #23                 // Method org/apache/hadoop/hbase/regionserver/querymatcher/ColumnCount.getOffset:()I
      22: aload_0
      23: getfield      #15                 // Field column:Lorg/apache/hadoop/hbase/regionserver/querymatcher/ColumnCount;
      26: invokevirtual #24                 // Method org/apache/hadoop/hbase/regionserver/querymatcher/ColumnCount.getLength:()I
      29: invokestatic  #25                 // Method org/apache/hadoop/hbase/CellUtil.compareQualifiers:(Lorg/apache/hadoop/hbase/Cell;[BII)I
      32: istore_2
      33: aload_0
      34: invokespecial #27                 // Method resetTS:()V
      37: iload_2
      38: iflt          86
      41: aload_0
      42: dup
      43: getfield      #14                 // Field index:I
      46: iconst_1
      47: iadd
      48: putfield      #14                 // Field index:I
      51: aload_0
      52: invokevirtual #20                 // Method done:()Z
      55: ifeq          66
      58: aload_0
      59: aconst_null
      60: putfield      #15                 // Field column:Lorg/apache/hadoop/hbase/regionserver/querymatcher/ColumnCount;
      63: goto          79
      66: aload_0
      67: aload_0
      68: getfield      #7                  // Field columns:[Lorg/apache/hadoop/hbase/regionserver/querymatcher/ColumnCount;
      71: aload_0
      72: getfield      #14                 // Field index:I
      75: aaload
      76: putfield      #15                 // Field column:Lorg/apache/hadoop/hbase/regionserver/querymatcher/ColumnCount;
      79: iload_2
      80: ifle          86
      83: goto          0
      86: return
      87: return

  public org.apache.hadoop.hbase.regionserver.querymatcher.ScanQueryMatcher$MatchCode getNextRowOrNextColumn(org.apache.hadoop.hbase.Cell);
    Code:
       0: aload_0
       1: aload_1
       2: invokevirtual #41                 // Method doneWithColumn:(Lorg/apache/hadoop/hbase/Cell;)V
       5: aload_0
       6: invokevirtual #42                 // Method getColumnHint:()Lorg/apache/hadoop/hbase/regionserver/querymatcher/ColumnCount;
       9: ifnonnull     16
      12: getstatic     #21                 // Field org/apache/hadoop/hbase/regionserver/querymatcher/ScanQueryMatcher$MatchCode.SEEK_NEXT_ROW:Lorg/apache/hadoop/hbase/regionserver/querymatcher/ScanQueryMatcher$MatchCode;
      15: areturn
      16: getstatic     #28                 // Field org/apache/hadoop/hbase/regionserver/querymatcher/ScanQueryMatcher$MatchCode.SEEK_NEXT_COL:Lorg/apache/hadoop/hbase/regionserver/querymatcher/ScanQueryMatcher$MatchCode;
      19: areturn

  public boolean isDone(long);
    Code:
       0: aload_0
       1: getfield      #3                  // Field minVersions:I
       4: ifgt          19
       7: aload_0
       8: lload_1
       9: invokespecial #32                 // Method isExpired:(J)Z
      12: ifeq          19
      15: iconst_1
      16: goto          20
      19: iconst_0
      20: ireturn

  public void beforeShipped() throws java.io.IOException;
    Code:
       0: return

  static {};
    Code:
       0: ldc           #43                 // class org/apache/hadoop/hbase/regionserver/querymatcher/ExplicitColumnTracker
       2: invokevirtual #44                 // Method java/lang/Class.desiredAssertionStatus:()Z
       5: ifne          12
       8: iconst_1
       9: goto          13
      12: iconst_0
      13: putstatic     #16                 // Field $assertionsDisabled:Z
      16: return
}
