Compiled from "ExtendedCellBuilder.java"
public interface org.apache.hadoop.hbase.ExtendedCellBuilder extends org.apache.hadoop.hbase.RawCellBuilder {
  public abstract org.apache.hadoop.hbase.ExtendedCellBuilder setRow(byte[]);

  public abstract org.apache.hadoop.hbase.ExtendedCellBuilder setRow(byte[], int, int);

  public abstract org.apache.hadoop.hbase.ExtendedCellBuilder setFamily(byte[]);

  public abstract org.apache.hadoop.hbase.ExtendedCellBuilder setFamily(byte[], int, int);

  public abstract org.apache.hadoop.hbase.ExtendedCellBuilder setQualifier(byte[]);

  public abstract org.apache.hadoop.hbase.ExtendedCellBuilder setQualifier(byte[], int, int);

  public abstract org.apache.hadoop.hbase.ExtendedCellBuilder setTimestamp(long);

  public abstract org.apache.hadoop.hbase.ExtendedCellBuilder setType(org.apache.hadoop.hbase.Cell$Type);

  public abstract org.apache.hadoop.hbase.ExtendedCellBuilder setType(byte);

  public abstract org.apache.hadoop.hbase.ExtendedCellBuilder setValue(byte[]);

  public abstract org.apache.hadoop.hbase.ExtendedCellBuilder setValue(byte[], int, int);

  public abstract org.apache.hadoop.hbase.ExtendedCell build();

  public abstract org.apache.hadoop.hbase.ExtendedCellBuilder clear();

  public abstract org.apache.hadoop.hbase.ExtendedCellBuilder setTags(byte[]);

  public abstract org.apache.hadoop.hbase.ExtendedCellBuilder setTags(byte[], int, int);

  public abstract org.apache.hadoop.hbase.ExtendedCellBuilder setTags(java.util.List<org.apache.hadoop.hbase.Tag>);

  public abstract org.apache.hadoop.hbase.ExtendedCellBuilder setSequenceId(long);

  public org.apache.hadoop.hbase.RawCellBuilder clear();
    Code:
       0: aload_0
       1: invokeinterface #1,  1            // InterfaceMethod clear:()Lorg/apache/hadoop/hbase/ExtendedCellBuilder;
       6: areturn

  public org.apache.hadoop.hbase.RawCell build();
    Code:
       0: aload_0
       1: invokeinterface #2,  1            // InterfaceMethod build:()Lorg/apache/hadoop/hbase/ExtendedCell;
       6: areturn

  public org.apache.hadoop.hbase.RawCellBuilder setTags(java.util.List);
    Code:
       0: aload_0
       1: aload_1
       2: invokeinterface #3,  2            // InterfaceMethod setTags:(Ljava/util/List;)Lorg/apache/hadoop/hbase/ExtendedCellBuilder;
       7: areturn

  public org.apache.hadoop.hbase.RawCellBuilder setValue(byte[], int, int);
    Code:
       0: aload_0
       1: aload_1
       2: iload_2
       3: iload_3
       4: invokeinterface #4,  4            // InterfaceMethod setValue:([BII)Lorg/apache/hadoop/hbase/ExtendedCellBuilder;
       9: areturn

  public org.apache.hadoop.hbase.RawCellBuilder setValue(byte[]);
    Code:
       0: aload_0
       1: aload_1
       2: invokeinterface #5,  2            // InterfaceMethod setValue:([B)Lorg/apache/hadoop/hbase/ExtendedCellBuilder;
       7: areturn

  public org.apache.hadoop.hbase.RawCellBuilder setType(org.apache.hadoop.hbase.Cell$Type);
    Code:
       0: aload_0
       1: aload_1
       2: invokeinterface #6,  2            // InterfaceMethod setType:(Lorg/apache/hadoop/hbase/Cell$Type;)Lorg/apache/hadoop/hbase/ExtendedCellBuilder;
       7: areturn

  public org.apache.hadoop.hbase.RawCellBuilder setTimestamp(long);
    Code:
       0: aload_0
       1: lload_1
       2: invokeinterface #7,  3            // InterfaceMethod setTimestamp:(J)Lorg/apache/hadoop/hbase/ExtendedCellBuilder;
       7: areturn

  public org.apache.hadoop.hbase.RawCellBuilder setQualifier(byte[], int, int);
    Code:
       0: aload_0
       1: aload_1
       2: iload_2
       3: iload_3
       4: invokeinterface #8,  4            // InterfaceMethod setQualifier:([BII)Lorg/apache/hadoop/hbase/ExtendedCellBuilder;
       9: areturn

  public org.apache.hadoop.hbase.RawCellBuilder setQualifier(byte[]);
    Code:
       0: aload_0
       1: aload_1
       2: invokeinterface #9,  2            // InterfaceMethod setQualifier:([B)Lorg/apache/hadoop/hbase/ExtendedCellBuilder;
       7: areturn

  public org.apache.hadoop.hbase.RawCellBuilder setFamily(byte[], int, int);
    Code:
       0: aload_0
       1: aload_1
       2: iload_2
       3: iload_3
       4: invokeinterface #10,  4           // InterfaceMethod setFamily:([BII)Lorg/apache/hadoop/hbase/ExtendedCellBuilder;
       9: areturn

  public org.apache.hadoop.hbase.RawCellBuilder setFamily(byte[]);
    Code:
       0: aload_0
       1: aload_1
       2: invokeinterface #11,  2           // InterfaceMethod setFamily:([B)Lorg/apache/hadoop/hbase/ExtendedCellBuilder;
       7: areturn

  public org.apache.hadoop.hbase.RawCellBuilder setRow(byte[], int, int);
    Code:
       0: aload_0
       1: aload_1
       2: iload_2
       3: iload_3
       4: invokeinterface #12,  4           // InterfaceMethod setRow:([BII)Lorg/apache/hadoop/hbase/ExtendedCellBuilder;
       9: areturn

  public org.apache.hadoop.hbase.RawCellBuilder setRow(byte[]);
    Code:
       0: aload_0
       1: aload_1
       2: invokeinterface #13,  2           // InterfaceMethod setRow:([B)Lorg/apache/hadoop/hbase/ExtendedCellBuilder;
       7: areturn

  public org.apache.hadoop.hbase.CellBuilder clear();
    Code:
       0: aload_0
       1: invokeinterface #1,  1            // InterfaceMethod clear:()Lorg/apache/hadoop/hbase/ExtendedCellBuilder;
       6: areturn

  public org.apache.hadoop.hbase.Cell build();
    Code:
       0: aload_0
       1: invokeinterface #2,  1            // InterfaceMethod build:()Lorg/apache/hadoop/hbase/ExtendedCell;
       6: areturn

  public org.apache.hadoop.hbase.CellBuilder setValue(byte[], int, int);
    Code:
       0: aload_0
       1: aload_1
       2: iload_2
       3: iload_3
       4: invokeinterface #4,  4            // InterfaceMethod setValue:([BII)Lorg/apache/hadoop/hbase/ExtendedCellBuilder;
       9: areturn

  public org.apache.hadoop.hbase.CellBuilder setValue(byte[]);
    Code:
       0: aload_0
       1: aload_1
       2: invokeinterface #5,  2            // InterfaceMethod setValue:([B)Lorg/apache/hadoop/hbase/ExtendedCellBuilder;
       7: areturn

  public org.apache.hadoop.hbase.CellBuilder setType(org.apache.hadoop.hbase.Cell$Type);
    Code:
       0: aload_0
       1: aload_1
       2: invokeinterface #6,  2            // InterfaceMethod setType:(Lorg/apache/hadoop/hbase/Cell$Type;)Lorg/apache/hadoop/hbase/ExtendedCellBuilder;
       7: areturn

  public org.apache.hadoop.hbase.CellBuilder setTimestamp(long);
    Code:
       0: aload_0
       1: lload_1
       2: invokeinterface #7,  3            // InterfaceMethod setTimestamp:(J)Lorg/apache/hadoop/hbase/ExtendedCellBuilder;
       7: areturn

  public org.apache.hadoop.hbase.CellBuilder setQualifier(byte[], int, int);
    Code:
       0: aload_0
       1: aload_1
       2: iload_2
       3: iload_3
       4: invokeinterface #8,  4            // InterfaceMethod setQualifier:([BII)Lorg/apache/hadoop/hbase/ExtendedCellBuilder;
       9: areturn

  public org.apache.hadoop.hbase.CellBuilder setQualifier(byte[]);
    Code:
       0: aload_0
       1: aload_1
       2: invokeinterface #9,  2            // InterfaceMethod setQualifier:([B)Lorg/apache/hadoop/hbase/ExtendedCellBuilder;
       7: areturn

  public org.apache.hadoop.hbase.CellBuilder setFamily(byte[], int, int);
    Code:
       0: aload_0
       1: aload_1
       2: iload_2
       3: iload_3
       4: invokeinterface #10,  4           // InterfaceMethod setFamily:([BII)Lorg/apache/hadoop/hbase/ExtendedCellBuilder;
       9: areturn

  public org.apache.hadoop.hbase.CellBuilder setFamily(byte[]);
    Code:
       0: aload_0
       1: aload_1
       2: invokeinterface #11,  2           // InterfaceMethod setFamily:([B)Lorg/apache/hadoop/hbase/ExtendedCellBuilder;
       7: areturn

  public org.apache.hadoop.hbase.CellBuilder setRow(byte[], int, int);
    Code:
       0: aload_0
       1: aload_1
       2: iload_2
       3: iload_3
       4: invokeinterface #12,  4           // InterfaceMethod setRow:([BII)Lorg/apache/hadoop/hbase/ExtendedCellBuilder;
       9: areturn

  public org.apache.hadoop.hbase.CellBuilder setRow(byte[]);
    Code:
       0: aload_0
       1: aload_1
       2: invokeinterface #13,  2           // InterfaceMethod setRow:([B)Lorg/apache/hadoop/hbase/ExtendedCellBuilder;
       7: areturn
}
