Compiled from "FailedProcedure.java"
public class org.apache.hadoop.hbase.procedure2.FailedProcedure<TEnvironment> extends org.apache.hadoop.hbase.procedure2.Procedure<TEnvironment> {
  public org.apache.hadoop.hbase.procedure2.FailedProcedure();
    Code:
       0: aload_0
       1: invokespecial #1                  // Method org/apache/hadoop/hbase/procedure2/Procedure."<init>":()V
       4: return

  public org.apache.hadoop.hbase.procedure2.FailedProcedure(long, java.lang.String, org.apache.hadoop.hbase.security.User, org.apache.hadoop.hbase.util.NonceKey, java.io.IOException);
    Code:
       0: aload_0
       1: invokespecial #1                  // Method org/apache/hadoop/hbase/procedure2/Procedure."<init>":()V
       4: aload_0
       5: aload_3
       6: putfield      #2                  // Field procName:Ljava/lang/String;
       9: aload_0
      10: lload_1
      11: invokevirtual #3                  // Method setProcId:(J)V
      14: aload_0
      15: getstatic     #4                  // Field org/apache/hadoop/hbase/shaded/protobuf/generated/ProcedureProtos$ProcedureState.ROLLEDBACK:Lorg/apache/hadoop/hbase/shaded/protobuf/generated/ProcedureProtos$ProcedureState;
      18: invokevirtual #5                  // Method setState:(Lorg/apache/hadoop/hbase/shaded/protobuf/generated/ProcedureProtos$ProcedureState;)V
      21: aload_0
      22: aload         4
      24: invokevirtual #6                  // Method setOwner:(Lorg/apache/hadoop/hbase/security/User;)V
      27: aload_0
      28: aload         5
      30: invokevirtual #7                  // Method setNonceKey:(Lorg/apache/hadoop/hbase/util/NonceKey;)V
      33: invokestatic  #8                  // Method org/apache/hadoop/hbase/util/EnvironmentEdgeManager.currentTime:()J
      36: lstore        7
      38: aload_0
      39: lload         7
      41: invokevirtual #9                  // Method setSubmittedTime:(J)V
      44: aload_0
      45: lload         7
      47: invokevirtual #10                 // Method setLastUpdate:(J)V
      50: aload_0
      51: aload         6
      53: invokevirtual #11                 // Method java/io/IOException.getMessage:()Ljava/lang/String;
      56: ldc           #12                 // String
      58: invokestatic  #13                 // Method java/util/Objects.toString:(Ljava/lang/Object;Ljava/lang/String;)Ljava/lang/String;
      61: aload         6
      63: invokevirtual #14                 // Method setFailure:(Ljava/lang/String;Ljava/lang/Throwable;)V
      66: return

  public java.lang.String getProcName();
    Code:
       0: aload_0
       1: getfield      #2                  // Field procName:Ljava/lang/String;
       4: areturn

  protected org.apache.hadoop.hbase.procedure2.Procedure<TEnvironment>[] execute(TEnvironment) throws org.apache.hadoop.hbase.procedure2.ProcedureYieldException, org.apache.hadoop.hbase.procedure2.ProcedureSuspendedException, java.lang.InterruptedException;
    Code:
       0: new           #15                 // class java/lang/UnsupportedOperationException
       3: dup
       4: invokespecial #16                 // Method java/lang/UnsupportedOperationException."<init>":()V
       7: athrow

  protected void rollback(TEnvironment) throws java.io.IOException, java.lang.InterruptedException;
    Code:
       0: new           #15                 // class java/lang/UnsupportedOperationException
       3: dup
       4: invokespecial #16                 // Method java/lang/UnsupportedOperationException."<init>":()V
       7: athrow

  protected boolean abort(TEnvironment);
    Code:
       0: new           #15                 // class java/lang/UnsupportedOperationException
       3: dup
       4: invokespecial #16                 // Method java/lang/UnsupportedOperationException."<init>":()V
       7: athrow

  protected void serializeStateData(org.apache.hadoop.hbase.procedure2.ProcedureStateSerializer) throws java.io.IOException;
    Code:
       0: return

  protected void deserializeStateData(org.apache.hadoop.hbase.procedure2.ProcedureStateSerializer) throws java.io.IOException;
    Code:
       0: return
}
