Compiled from "FanOutOneBlockAsyncDFSOutputHelper.java"
public final class org.apache.hadoop.hbase.io.asyncfs.FanOutOneBlockAsyncDFSOutputHelper {
  public static final java.lang.String ASYNC_DFS_OUTPUT_CREATE_MAX_RETRIES;

  public static final int DEFAULT_ASYNC_DFS_OUTPUT_CREATE_MAX_RETRIES;

  public static final long HEART_BEAT_SEQNO;

  public static final int READ_TIMEOUT;

  static void beginFileLease(org.apache.hadoop.hdfs.DFSClient, long);
    Code:
       0: getstatic     #38                 // Field LEASE_MANAGER:Lorg/apache/hadoop/hbase/io/asyncfs/FanOutOneBlockAsyncDFSOutputHelper$LeaseManager;
       3: aload_0
       4: lload_1
       5: invokeinterface #39,  4           // InterfaceMethod org/apache/hadoop/hbase/io/asyncfs/FanOutOneBlockAsyncDFSOutputHelper$LeaseManager.begin:(Lorg/apache/hadoop/hdfs/DFSClient;J)V
      10: return

  static void endFileLease(org.apache.hadoop.hdfs.DFSClient, long);
    Code:
       0: getstatic     #38                 // Field LEASE_MANAGER:Lorg/apache/hadoop/hbase/io/asyncfs/FanOutOneBlockAsyncDFSOutputHelper$LeaseManager;
       3: aload_0
       4: lload_1
       5: invokeinterface #40,  4           // InterfaceMethod org/apache/hadoop/hbase/io/asyncfs/FanOutOneBlockAsyncDFSOutputHelper$LeaseManager.end:(Lorg/apache/hadoop/hdfs/DFSClient;J)V
      10: return

  static org.apache.hadoop.util.DataChecksum createChecksum(org.apache.hadoop.hdfs.DFSClient);
    Code:
       0: aload_0
       1: invokevirtual #41                 // Method org/apache/hadoop/hdfs/DFSClient.getConf:()Lorg/apache/hadoop/hdfs/client/impl/DfsClientConf;
       4: aconst_null
       5: invokevirtual #42                 // Method org/apache/hadoop/hdfs/client/impl/DfsClientConf.createChecksum:(Lorg/apache/hadoop/fs/Options$ChecksumOpt;)Lorg/apache/hadoop/util/DataChecksum;
       8: areturn

  static org.apache.hadoop.hdfs.protocol.proto.DataTransferProtos$Status getStatus(org.apache.hadoop.hdfs.protocol.proto.DataTransferProtos$PipelineAckProto);
    Code:
       0: aload_0
       1: invokevirtual #43                 // Method org/apache/hadoop/hdfs/protocol/proto/DataTransferProtos$PipelineAckProto.getFlagList:()Ljava/util/List;
       4: astore_1
       5: aload_1
       6: invokeinterface #44,  1           // InterfaceMethod java/util/List.isEmpty:()Z
      11: ifeq          34
      14: aload_0
      15: iconst_0
      16: invokevirtual #45                 // Method org/apache/hadoop/hdfs/protocol/proto/DataTransferProtos$PipelineAckProto.getReply:(I)Lorg/apache/hadoop/hdfs/protocol/proto/DataTransferProtos$Status;
      19: astore_3
      20: getstatic     #46                 // Field org/apache/hadoop/hdfs/protocol/datatransfer/PipelineAck$ECN.DISABLED:Lorg/apache/hadoop/hdfs/protocol/datatransfer/PipelineAck$ECN;
      23: aload_3
      24: invokestatic  #47                 // Method org/apache/hadoop/hdfs/protocol/datatransfer/PipelineAck.combineHeader:(Lorg/apache/hadoop/hdfs/protocol/datatransfer/PipelineAck$ECN;Lorg/apache/hadoop/hdfs/protocol/proto/DataTransferProtos$Status;)I
      27: invokestatic  #48                 // Method java/lang/Integer.valueOf:(I)Ljava/lang/Integer;
      30: astore_2
      31: goto          45
      34: aload_1
      35: iconst_0
      36: invokeinterface #49,  2           // InterfaceMethod java/util/List.get:(I)Ljava/lang/Object;
      41: checkcast     #50                 // class java/lang/Integer
      44: astore_2
      45: aload_2
      46: invokevirtual #51                 // Method java/lang/Integer.intValue:()I
      49: invokestatic  #52                 // Method org/apache/hadoop/hdfs/protocol/datatransfer/PipelineAck.getStatusFromHeader:(I)Lorg/apache/hadoop/hdfs/protocol/proto/DataTransferProtos$Status;
      52: areturn

  public static org.apache.hadoop.hbase.io.asyncfs.FanOutOneBlockAsyncDFSOutput createOutput(org.apache.hadoop.hdfs.DistributedFileSystem, org.apache.hadoop.fs.Path, boolean, boolean, short, long, org.apache.hbase.thirdparty.io.netty.channel.EventLoopGroup, java.lang.Class<? extends org.apache.hbase.thirdparty.io.netty.channel.Channel>) throws java.io.IOException;
    Code:
       0: new           #205                // class org/apache/hadoop/hbase/io/asyncfs/FanOutOneBlockAsyncDFSOutputHelper$8
       3: dup
       4: aload_0
       5: iload_2
       6: iload_3
       7: iload         4
       9: lload         5
      11: aload         7
      13: aload         8
      15: invokespecial #206                // Method org/apache/hadoop/hbase/io/asyncfs/FanOutOneBlockAsyncDFSOutputHelper$8."<init>":(Lorg/apache/hadoop/hdfs/DistributedFileSystem;ZZSJLorg/apache/hbase/thirdparty/io/netty/channel/EventLoopGroup;Ljava/lang/Class;)V
      18: aload_0
      19: aload_1
      20: invokevirtual #207                // Method org/apache/hadoop/hbase/io/asyncfs/FanOutOneBlockAsyncDFSOutputHelper$8.resolve:(Lorg/apache/hadoop/fs/FileSystem;Lorg/apache/hadoop/fs/Path;)Ljava/lang/Object;
      23: checkcast     #182                // class org/apache/hadoop/hbase/io/asyncfs/FanOutOneBlockAsyncDFSOutput
      26: areturn

  public static boolean shouldRetryCreate(org.apache.hadoop.ipc.RemoteException);
    Code:
       0: aload_0
       1: invokevirtual #208                // Method org/apache/hadoop/ipc/RemoteException.getClassName:()Ljava/lang/String;
       4: ldc           #209                // String RetryStartFileException
       6: invokevirtual #210                // Method java/lang/String.endsWith:(Ljava/lang/String;)Z
       9: ireturn

  static void completeFile(org.apache.hadoop.hdfs.DFSClient, org.apache.hadoop.hdfs.protocol.ClientProtocol, java.lang.String, java.lang.String, org.apache.hadoop.hdfs.protocol.ExtendedBlock, long);
    Code:
       0: iconst_0
       1: istore        7
       3: aload_1
       4: aload_2
       5: aload_3
       6: aload         4
       8: lload         5
      10: invokeinterface #211,  6          // InterfaceMethod org/apache/hadoop/hdfs/protocol/ClientProtocol.complete:(Ljava/lang/String;Ljava/lang/String;Lorg/apache/hadoop/hdfs/protocol/ExtendedBlock;J)Z
      15: ifeq          25
      18: aload_0
      19: lload         5
      21: invokestatic  #191                // Method endFileLease:(Lorg/apache/hadoop/hdfs/DFSClient;J)V
      24: return
      25: getstatic     #34                 // Field LOG:Lorg/slf4j/Logger;
      28: new           #212                // class java/lang/StringBuilder
      31: dup
      32: invokespecial #213                // Method java/lang/StringBuilder."<init>":()V
      35: ldc           #214                // String complete file
      37: invokevirtual #215                // Method java/lang/StringBuilder.append:(Ljava/lang/String;)Ljava/lang/StringBuilder;
      40: aload_2
      41: invokevirtual #215                // Method java/lang/StringBuilder.append:(Ljava/lang/String;)Ljava/lang/StringBuilder;
      44: ldc           #216                // String  not finished, retry =
      46: invokevirtual #215                // Method java/lang/StringBuilder.append:(Ljava/lang/String;)Ljava/lang/StringBuilder;
      49: iload         7
      51: invokevirtual #217                // Method java/lang/StringBuilder.append:(I)Ljava/lang/StringBuilder;
      54: invokevirtual #218                // Method java/lang/StringBuilder.toString:()Ljava/lang/String;
      57: invokeinterface #219,  2          // InterfaceMethod org/slf4j/Logger.warn:(Ljava/lang/String;)V
      62: goto          200
      65: astore        8
      67: aload         8
      69: invokevirtual #196                // Method org/apache/hadoop/ipc/RemoteException.unwrapRemoteException:()Ljava/io/IOException;
      72: astore        9
      74: aload         9
      76: instanceof    #220                // class org/apache/hadoop/hdfs/server/namenode/LeaseExpiredException
      79: ifeq          117
      82: getstatic     #34                 // Field LOG:Lorg/slf4j/Logger;
      85: new           #212                // class java/lang/StringBuilder
      88: dup
      89: invokespecial #213                // Method java/lang/StringBuilder."<init>":()V
      92: ldc           #221                // String lease for file
      94: invokevirtual #215                // Method java/lang/StringBuilder.append:(Ljava/lang/String;)Ljava/lang/StringBuilder;
      97: aload_2
      98: invokevirtual #215                // Method java/lang/StringBuilder.append:(Ljava/lang/String;)Ljava/lang/StringBuilder;
     101: ldc           #222                // String  is expired, give up
     103: invokevirtual #215                // Method java/lang/StringBuilder.append:(Ljava/lang/String;)Ljava/lang/StringBuilder;
     106: invokevirtual #218                // Method java/lang/StringBuilder.toString:()Ljava/lang/String;
     109: aload         8
     111: invokeinterface #223,  3          // InterfaceMethod org/slf4j/Logger.warn:(Ljava/lang/String;Ljava/lang/Throwable;)V
     116: return
     117: getstatic     #34                 // Field LOG:Lorg/slf4j/Logger;
     120: new           #212                // class java/lang/StringBuilder
     123: dup
     124: invokespecial #213                // Method java/lang/StringBuilder."<init>":()V
     127: ldc           #214                // String complete file
     129: invokevirtual #215                // Method java/lang/StringBuilder.append:(Ljava/lang/String;)Ljava/lang/StringBuilder;
     132: aload_2
     133: invokevirtual #215                // Method java/lang/StringBuilder.append:(Ljava/lang/String;)Ljava/lang/StringBuilder;
     136: ldc           #224                // String  failed, retry =
     138: invokevirtual #215                // Method java/lang/StringBuilder.append:(Ljava/lang/String;)Ljava/lang/StringBuilder;
     141: iload         7
     143: invokevirtual #217                // Method java/lang/StringBuilder.append:(I)Ljava/lang/StringBuilder;
     146: invokevirtual #218                // Method java/lang/StringBuilder.toString:()Ljava/lang/String;
     149: aload         8
     151: invokeinterface #223,  3          // InterfaceMethod org/slf4j/Logger.warn:(Ljava/lang/String;Ljava/lang/Throwable;)V
     156: goto          200
     159: astore        8
     161: getstatic     #34                 // Field LOG:Lorg/slf4j/Logger;
     164: new           #212                // class java/lang/StringBuilder
     167: dup
     168: invokespecial #213                // Method java/lang/StringBuilder."<init>":()V
     171: ldc           #214                // String complete file
     173: invokevirtual #215                // Method java/lang/StringBuilder.append:(Ljava/lang/String;)Ljava/lang/StringBuilder;
     176: aload_2
     177: invokevirtual #215                // Method java/lang/StringBuilder.append:(Ljava/lang/String;)Ljava/lang/StringBuilder;
     180: ldc           #224                // String  failed, retry =
     182: invokevirtual #215                // Method java/lang/StringBuilder.append:(Ljava/lang/String;)Ljava/lang/StringBuilder;
     185: iload         7
     187: invokevirtual #217                // Method java/lang/StringBuilder.append:(I)Ljava/lang/StringBuilder;
     190: invokevirtual #218                // Method java/lang/StringBuilder.toString:()Ljava/lang/String;
     193: aload         8
     195: invokeinterface #223,  3          // InterfaceMethod org/slf4j/Logger.warn:(Ljava/lang/String;Ljava/lang/Throwable;)V
     200: iload         7
     202: invokestatic  #225                // Method sleepIgnoreInterrupt:(I)V
     205: iinc          7, 1
     208: goto          3
    Exception table:
       from    to  target type
           3    24    65   Class org/apache/hadoop/ipc/RemoteException
          25    62    65   Class org/apache/hadoop/ipc/RemoteException
           3    24   159   Class java/lang/Exception
          25    62   159   Class java/lang/Exception

  static void sleepIgnoreInterrupt(int);
    Code:
       0: ldc2_w        #198                // long 100l
       3: iload_0
       4: invokestatic  #200                // Method org/apache/hadoop/hbase/client/ConnectionUtils.getPauseTime:(JI)J
       7: invokestatic  #201                // Method java/lang/Thread.sleep:(J)V
      10: goto          14
      13: astore_1
      14: return
    Exception table:
       from    to  target type
           0    10    13   Class java/lang/InterruptedException

  static org.apache.hadoop.hbase.io.asyncfs.FanOutOneBlockAsyncDFSOutputHelper$DFSClientAdaptor access$000();
    Code:
       0: getstatic     #6                  // Field DFS_CLIENT_ADAPTOR:Lorg/apache/hadoop/hbase/io/asyncfs/FanOutOneBlockAsyncDFSOutputHelper$DFSClientAdaptor;
       3: areturn

  static void access$100(org.apache.hbase.thirdparty.io.netty.channel.Channel, org.apache.hadoop.hdfs.protocol.DatanodeInfo, org.apache.hbase.thirdparty.io.netty.util.concurrent.Promise, int);
    Code:
       0: aload_0
       1: aload_1
       2: aload_2
       3: iload_3
       4: invokestatic  #5                  // Method processWriteBlockResponse:(Lorg/apache/hbase/thirdparty/io/netty/channel/Channel;Lorg/apache/hadoop/hdfs/protocol/DatanodeInfo;Lorg/apache/hbase/thirdparty/io/netty/util/concurrent/Promise;I)V
       7: return

  static void access$200(org.apache.hbase.thirdparty.io.netty.channel.Channel, org.apache.hadoop.fs.StorageType, org.apache.hadoop.hdfs.protocol.proto.DataTransferProtos$OpWriteBlockProto$Builder) throws java.io.IOException;
    Code:
       0: aload_0
       1: aload_1
       2: aload_2
       3: invokestatic  #4                  // Method requestWriteBlock:(Lorg/apache/hbase/thirdparty/io/netty/channel/Channel;Lorg/apache/hadoop/fs/StorageType;Lorg/apache/hadoop/hdfs/protocol/proto/DataTransferProtos$OpWriteBlockProto$Builder;)V
       6: return

  static void access$300(org.apache.hadoop.conf.Configuration, org.apache.hbase.thirdparty.io.netty.channel.Channel, org.apache.hadoop.hdfs.protocol.DatanodeInfo, org.apache.hadoop.fs.StorageType, org.apache.hadoop.hdfs.protocol.proto.DataTransferProtos$OpWriteBlockProto$Builder, int, org.apache.hadoop.hdfs.DFSClient, org.apache.hadoop.security.token.Token, org.apache.hbase.thirdparty.io.netty.util.concurrent.Promise) throws java.io.IOException;
    Code:
       0: aload_0
       1: aload_1
       2: aload_2
       3: aload_3
       4: aload         4
       6: iload         5
       8: aload         6
      10: aload         7
      12: aload         8
      14: invokestatic  #3                  // Method initialize:(Lorg/apache/hadoop/conf/Configuration;Lorg/apache/hbase/thirdparty/io/netty/channel/Channel;Lorg/apache/hadoop/hdfs/protocol/DatanodeInfo;Lorg/apache/hadoop/fs/StorageType;Lorg/apache/hadoop/hdfs/protocol/proto/DataTransferProtos$OpWriteBlockProto$Builder;ILorg/apache/hadoop/hdfs/DFSClient;Lorg/apache/hadoop/security/token/Token;Lorg/apache/hbase/thirdparty/io/netty/util/concurrent/Promise;)V
      17: return

  static org.apache.hadoop.hbase.io.asyncfs.FanOutOneBlockAsyncDFSOutput access$400(org.apache.hadoop.hdfs.DistributedFileSystem, java.lang.String, boolean, boolean, short, long, org.apache.hbase.thirdparty.io.netty.channel.EventLoopGroup, java.lang.Class) throws java.io.IOException;
    Code:
       0: aload_0
       1: aload_1
       2: iload_2
       3: iload_3
       4: iload         4
       6: lload         5
       8: aload         7
      10: aload         8
      12: invokestatic  #2                  // Method createOutput:(Lorg/apache/hadoop/hdfs/DistributedFileSystem;Ljava/lang/String;ZZSJLorg/apache/hbase/thirdparty/io/netty/channel/EventLoopGroup;Ljava/lang/Class;)Lorg/apache/hadoop/hbase/io/asyncfs/FanOutOneBlockAsyncDFSOutput;
      15: areturn

  static {};
    Code:
       0: ldc           #93                 // class org/apache/hadoop/hbase/io/asyncfs/FanOutOneBlockAsyncDFSOutputHelper
       2: invokestatic  #231                // Method org/slf4j/LoggerFactory.getLogger:(Ljava/lang/Class;)Lorg/slf4j/Logger;
       5: putstatic     #34                 // Field LOG:Lorg/slf4j/Logger;
       8: getstatic     #232                // Field org/apache/hbase/thirdparty/io/netty/buffer/PooledByteBufAllocator.DEFAULT:Lorg/apache/hbase/thirdparty/io/netty/buffer/PooledByteBufAllocator;
      11: putstatic     #183                // Field ALLOC:Lorg/apache/hbase/thirdparty/io/netty/buffer/ByteBufAllocator;
      14: iconst_0
      15: anewarray     #233                // class org/apache/hadoop/hdfs/protocol/DatanodeInfo
      18: putstatic     #152                // Field EMPTY_DN_ARRAY:[Lorg/apache/hadoop/hdfs/protocol/DatanodeInfo;
      21: invokestatic  #234                // Method createLeaseManager:()Lorg/apache/hadoop/hbase/io/asyncfs/FanOutOneBlockAsyncDFSOutputHelper$LeaseManager;
      24: putstatic     #38                 // Field LEASE_MANAGER:Lorg/apache/hadoop/hbase/io/asyncfs/FanOutOneBlockAsyncDFSOutputHelper$LeaseManager;
      27: invokestatic  #235                // Method createDFSClientAdaptor:()Lorg/apache/hadoop/hbase/io/asyncfs/FanOutOneBlockAsyncDFSOutputHelper$DFSClientAdaptor;
      30: putstatic     #6                  // Field DFS_CLIENT_ADAPTOR:Lorg/apache/hadoop/hbase/io/asyncfs/FanOutOneBlockAsyncDFSOutputHelper$DFSClientAdaptor;
      33: invokestatic  #236                // Method createFileCreator:()Lorg/apache/hadoop/hbase/io/asyncfs/FanOutOneBlockAsyncDFSOutputHelper$FileCreator;
      36: putstatic     #153                // Field FILE_CREATOR:Lorg/apache/hadoop/hbase/io/asyncfs/FanOutOneBlockAsyncDFSOutputHelper$FileCreator;
      39: goto          66
      42: astore_0
      43: ldc           #237                // String Couldn't properly initialize access to HDFS internals. Please update your WAL Provider to not make use of the 'asyncfs' provider. See HBASE-16110 for more information.
      45: astore_1
      46: getstatic     #34                 // Field LOG:Lorg/slf4j/Logger;
      49: aload_1
      50: aload_0
      51: invokeinterface #238,  3          // InterfaceMethod org/slf4j/Logger.error:(Ljava/lang/String;Ljava/lang/Throwable;)V
      56: new           #239                // class java/lang/Error
      59: dup
      60: aload_1
      61: aload_0
      62: invokespecial #240                // Method java/lang/Error."<init>":(Ljava/lang/String;Ljava/lang/Throwable;)V
      65: athrow
      66: return
    Exception table:
       from    to  target type
          21    39    42   Class java/lang/Exception
}
