Compiled from "FanOutOneBlockAsyncDFSOutputSaslHelper.java"
final class org.apache.hadoop.hbase.io.asyncfs.FanOutOneBlockAsyncDFSOutputSaslHelper$EncryptHandler extends org.apache.hbase.thirdparty.io.netty.handler.codec.MessageToByteEncoder<org.apache.hbase.thirdparty.io.netty.buffer.ByteBuf> {
  public org.apache.hadoop.hbase.io.asyncfs.FanOutOneBlockAsyncDFSOutputSaslHelper$EncryptHandler(org.apache.hadoop.crypto.CryptoCodec, byte[], byte[]) throws java.security.GeneralSecurityException, java.io.IOException;
    Code:
       0: aload_0
       1: invokespecial #1                  // Method org/apache/hbase/thirdparty/io/netty/handler/codec/MessageToByteEncoder."<init>":()V
       4: aload_0
       5: aload_1
       6: invokevirtual #2                  // Method org/apache/hadoop/crypto/CryptoCodec.createEncryptor:()Lorg/apache/hadoop/crypto/Encryptor;
       9: putfield      #3                  // Field encryptor:Lorg/apache/hadoop/crypto/Encryptor;
      12: aload_0
      13: getfield      #3                  // Field encryptor:Lorg/apache/hadoop/crypto/Encryptor;
      16: aload_2
      17: aload_3
      18: aload_3
      19: arraylength
      20: invokestatic  #4                  // Method java/util/Arrays.copyOf:([BI)[B
      23: invokeinterface #5,  3            // InterfaceMethod org/apache/hadoop/crypto/Encryptor.init:([B[B)V
      28: return

  protected org.apache.hbase.thirdparty.io.netty.buffer.ByteBuf allocateBuffer(org.apache.hbase.thirdparty.io.netty.channel.ChannelHandlerContext, org.apache.hbase.thirdparty.io.netty.buffer.ByteBuf, boolean) throws java.lang.Exception;
    Code:
       0: iload_3
       1: ifeq          20
       4: aload_1
       5: invokeinterface #6,  1            // InterfaceMethod org/apache/hbase/thirdparty/io/netty/channel/ChannelHandlerContext.alloc:()Lorg/apache/hbase/thirdparty/io/netty/buffer/ByteBufAllocator;
      10: aload_2
      11: invokevirtual #7                  // Method org/apache/hbase/thirdparty/io/netty/buffer/ByteBuf.readableBytes:()I
      14: invokeinterface #8,  2            // InterfaceMethod org/apache/hbase/thirdparty/io/netty/buffer/ByteBufAllocator.directBuffer:(I)Lorg/apache/hbase/thirdparty/io/netty/buffer/ByteBuf;
      19: areturn
      20: aload_1
      21: invokeinterface #6,  1            // InterfaceMethod org/apache/hbase/thirdparty/io/netty/channel/ChannelHandlerContext.alloc:()Lorg/apache/hbase/thirdparty/io/netty/buffer/ByteBufAllocator;
      26: aload_2
      27: invokevirtual #7                  // Method org/apache/hbase/thirdparty/io/netty/buffer/ByteBuf.readableBytes:()I
      30: invokeinterface #9,  2            // InterfaceMethod org/apache/hbase/thirdparty/io/netty/buffer/ByteBufAllocator.buffer:(I)Lorg/apache/hbase/thirdparty/io/netty/buffer/ByteBuf;
      35: areturn

  protected void encode(org.apache.hbase.thirdparty.io.netty.channel.ChannelHandlerContext, org.apache.hbase.thirdparty.io.netty.buffer.ByteBuf, org.apache.hbase.thirdparty.io.netty.buffer.ByteBuf) throws java.lang.Exception;
    Code:
       0: iconst_0
       1: istore        5
       3: aload_2
       4: invokevirtual #10                 // Method org/apache/hbase/thirdparty/io/netty/buffer/ByteBuf.nioBufferCount:()I
       7: iconst_1
       8: if_icmpne     17
      11: aload_2
      12: astore        4
      14: goto          44
      17: aload_1
      18: invokeinterface #6,  1            // InterfaceMethod org/apache/hbase/thirdparty/io/netty/channel/ChannelHandlerContext.alloc:()Lorg/apache/hbase/thirdparty/io/netty/buffer/ByteBufAllocator;
      23: aload_2
      24: invokevirtual #7                  // Method org/apache/hbase/thirdparty/io/netty/buffer/ByteBuf.readableBytes:()I
      27: invokeinterface #8,  2            // InterfaceMethod org/apache/hbase/thirdparty/io/netty/buffer/ByteBufAllocator.directBuffer:(I)Lorg/apache/hbase/thirdparty/io/netty/buffer/ByteBuf;
      32: astore        4
      34: aload_2
      35: aload         4
      37: invokevirtual #11                 // Method org/apache/hbase/thirdparty/io/netty/buffer/ByteBuf.readBytes:(Lorg/apache/hbase/thirdparty/io/netty/buffer/ByteBuf;)Lorg/apache/hbase/thirdparty/io/netty/buffer/ByteBuf;
      40: pop
      41: iconst_1
      42: istore        5
      44: aload         4
      46: invokevirtual #12                 // Method org/apache/hbase/thirdparty/io/netty/buffer/ByteBuf.nioBuffer:()Ljava/nio/ByteBuffer;
      49: astore        6
      51: aload_3
      52: iconst_0
      53: aload         4
      55: invokevirtual #7                  // Method org/apache/hbase/thirdparty/io/netty/buffer/ByteBuf.readableBytes:()I
      58: invokevirtual #13                 // Method org/apache/hbase/thirdparty/io/netty/buffer/ByteBuf.nioBuffer:(II)Ljava/nio/ByteBuffer;
      61: astore        7
      63: aload_0
      64: getfield      #3                  // Field encryptor:Lorg/apache/hadoop/crypto/Encryptor;
      67: aload         6
      69: aload         7
      71: invokeinterface #14,  3           // InterfaceMethod org/apache/hadoop/crypto/Encryptor.encrypt:(Ljava/nio/ByteBuffer;Ljava/nio/ByteBuffer;)V
      76: aload_3
      77: aload         4
      79: invokevirtual #7                  // Method org/apache/hbase/thirdparty/io/netty/buffer/ByteBuf.readableBytes:()I
      82: invokevirtual #15                 // Method org/apache/hbase/thirdparty/io/netty/buffer/ByteBuf.writerIndex:(I)Lorg/apache/hbase/thirdparty/io/netty/buffer/ByteBuf;
      85: pop
      86: iload         5
      88: ifeq          97
      91: aload         4
      93: invokevirtual #16                 // Method org/apache/hbase/thirdparty/io/netty/buffer/ByteBuf.release:()Z
      96: pop
      97: return

  protected void encode(org.apache.hbase.thirdparty.io.netty.channel.ChannelHandlerContext, java.lang.Object, org.apache.hbase.thirdparty.io.netty.buffer.ByteBuf) throws java.lang.Exception;
    Code:
       0: aload_0
       1: aload_1
       2: aload_2
       3: checkcast     #17                 // class org/apache/hbase/thirdparty/io/netty/buffer/ByteBuf
       6: aload_3
       7: invokevirtual #18                 // Method encode:(Lorg/apache/hbase/thirdparty/io/netty/channel/ChannelHandlerContext;Lorg/apache/hbase/thirdparty/io/netty/buffer/ByteBuf;Lorg/apache/hbase/thirdparty/io/netty/buffer/ByteBuf;)V
      10: return

  protected org.apache.hbase.thirdparty.io.netty.buffer.ByteBuf allocateBuffer(org.apache.hbase.thirdparty.io.netty.channel.ChannelHandlerContext, java.lang.Object, boolean) throws java.lang.Exception;
    Code:
       0: aload_0
       1: aload_1
       2: aload_2
       3: checkcast     #17                 // class org/apache/hbase/thirdparty/io/netty/buffer/ByteBuf
       6: iload_3
       7: invokevirtual #19                 // Method allocateBuffer:(Lorg/apache/hbase/thirdparty/io/netty/channel/ChannelHandlerContext;Lorg/apache/hbase/thirdparty/io/netty/buffer/ByteBuf;Z)Lorg/apache/hbase/thirdparty/io/netty/buffer/ByteBuf;
      10: areturn
}
