Compiled from "FanOutOneBlockAsyncDFSOutput.java"
final class org.apache.hadoop.hbase.io.asyncfs.FanOutOneBlockAsyncDFSOutput$Callback {
  public org.apache.hadoop.hbase.io.asyncfs.FanOutOneBlockAsyncDFSOutput$Callback(java.util.concurrent.CompletableFuture<java.lang.Long>, long, java.util.Collection<org.apache.hbase.thirdparty.io.netty.channel.Channel>);
    Code:
       0: aload_0
       1: invokespecial #4                  // Method java/lang/Object."<init>":()V
       4: aload_0
       5: aload_1
       6: putfield      #1                  // Field future:Ljava/util/concurrent/CompletableFuture;
       9: aload_0
      10: lload_2
      11: putfield      #2                  // Field ackedLength:J
      14: aload         4
      16: invokeinterface #5,  1            // InterfaceMethod java/util/Collection.isEmpty:()Z
      21: ifeq          34
      24: aload_0
      25: invokestatic  #6                  // Method java/util/Collections.emptySet:()Ljava/util/Set;
      28: putfield      #3                  // Field unfinishedReplicas:Ljava/util/Set;
      31: goto          91
      34: aload_0
      35: new           #7                  // class java/util/concurrent/ConcurrentHashMap
      38: dup
      39: aload         4
      41: invokeinterface #8,  1            // InterfaceMethod java/util/Collection.size:()I
      46: invokespecial #9                  // Method java/util/concurrent/ConcurrentHashMap."<init>":(I)V
      49: invokestatic  #10                 // Method java/util/Collections.newSetFromMap:(Ljava/util/Map;)Ljava/util/Set;
      52: putfield      #3                  // Field unfinishedReplicas:Ljava/util/Set;
      55: aload         4
      57: invokeinterface #11,  1           // InterfaceMethod java/util/Collection.stream:()Ljava/util/stream/Stream;
      62: invokedynamic #12,  0             // InvokeDynamic #0:apply:()Ljava/util/function/Function;
      67: invokeinterface #13,  2           // InterfaceMethod java/util/stream/Stream.map:(Ljava/util/function/Function;)Ljava/util/stream/Stream;
      72: aload_0
      73: getfield      #3                  // Field unfinishedReplicas:Ljava/util/Set;
      76: dup
      77: invokevirtual #14                 // Method java/lang/Object.getClass:()Ljava/lang/Class;
      80: pop
      81: invokedynamic #15,  0             // InvokeDynamic #1:accept:(Ljava/util/Set;)Ljava/util/function/Consumer;
      86: invokeinterface #16,  2           // InterfaceMethod java/util/stream/Stream.forEachOrdered:(Ljava/util/function/Consumer;)V
      91: return

  static java.util.Set access$000(org.apache.hadoop.hbase.io.asyncfs.FanOutOneBlockAsyncDFSOutput$Callback);
    Code:
       0: aload_0
       1: getfield      #3                  // Field unfinishedReplicas:Ljava/util/Set;
       4: areturn

  static long access$100(org.apache.hadoop.hbase.io.asyncfs.FanOutOneBlockAsyncDFSOutput$Callback);
    Code:
       0: aload_0
       1: getfield      #2                  // Field ackedLength:J
       4: lreturn

  static java.util.concurrent.CompletableFuture access$200(org.apache.hadoop.hbase.io.asyncfs.FanOutOneBlockAsyncDFSOutput$Callback);
    Code:
       0: aload_0
       1: getfield      #1                  // Field future:Ljava/util/concurrent/CompletableFuture;
       4: areturn
}
