Compiled from "FileArchiverNotifierImpl.java"
class org.apache.hadoop.hbase.quotas.FileArchiverNotifierImpl$StoreFileReference {
  org.apache.hadoop.hbase.quotas.FileArchiverNotifierImpl$StoreFileReference(java.lang.String);
    Code:
       0: aload_0
       1: invokespecial #1                  // Method java/lang/Object."<init>":()V
       4: aload_0
       5: aload_1
       6: invokestatic  #2                  // Method java/util/Objects.requireNonNull:(Ljava/lang/Object;)Ljava/lang/Object;
       9: checkcast     #3                  // class java/lang/String
      12: putfield      #4                  // Field regionName:Ljava/lang/String;
      15: aload_0
      16: invokestatic  #5                  // Method org/apache/hbase/thirdparty/com/google/common/collect/HashMultimap.create:()Lorg/apache/hbase/thirdparty/com/google/common/collect/HashMultimap;
      19: putfield      #6                  // Field familyToFiles:Lorg/apache/hbase/thirdparty/com/google/common/collect/Multimap;
      22: return

  java.lang.String getRegionName();
    Code:
       0: aload_0
       1: getfield      #4                  // Field regionName:Ljava/lang/String;
       4: areturn

  org.apache.hbase.thirdparty.com.google.common.collect.Multimap<java.lang.String, java.lang.String> getFamilyToFilesMapping();
    Code:
       0: aload_0
       1: getfield      #6                  // Field familyToFiles:Lorg/apache/hbase/thirdparty/com/google/common/collect/Multimap;
       4: areturn

  void addFamilyStoreFile(java.lang.String, java.lang.String);
    Code:
       0: aload_0
       1: getfield      #6                  // Field familyToFiles:Lorg/apache/hbase/thirdparty/com/google/common/collect/Multimap;
       4: aload_1
       5: aload_2
       6: invokeinterface #7,  3            // InterfaceMethod org/apache/hbase/thirdparty/com/google/common/collect/Multimap.put:(Ljava/lang/Object;Ljava/lang/Object;)Z
      11: pop
      12: return

  public int hashCode();
    Code:
       0: new           #8                  // class org/apache/commons/lang3/builder/HashCodeBuilder
       3: dup
       4: invokespecial #9                  // Method org/apache/commons/lang3/builder/HashCodeBuilder."<init>":()V
       7: aload_0
       8: getfield      #4                  // Field regionName:Ljava/lang/String;
      11: invokevirtual #10                 // Method org/apache/commons/lang3/builder/HashCodeBuilder.append:(Ljava/lang/Object;)Lorg/apache/commons/lang3/builder/HashCodeBuilder;
      14: aload_0
      15: getfield      #6                  // Field familyToFiles:Lorg/apache/hbase/thirdparty/com/google/common/collect/Multimap;
      18: invokevirtual #10                 // Method org/apache/commons/lang3/builder/HashCodeBuilder.append:(Ljava/lang/Object;)Lorg/apache/commons/lang3/builder/HashCodeBuilder;
      21: invokevirtual #11                 // Method org/apache/commons/lang3/builder/HashCodeBuilder.toHashCode:()I
      24: ireturn

  public boolean equals(java.lang.Object);
    Code:
       0: aload_0
       1: aload_1
       2: if_acmpne     7
       5: iconst_1
       6: ireturn
       7: aload_1
       8: instanceof    #12                 // class org/apache/hadoop/hbase/quotas/FileArchiverNotifierImpl$StoreFileReference
      11: ifne          16
      14: iconst_0
      15: ireturn
      16: aload_1
      17: checkcast     #12                 // class org/apache/hadoop/hbase/quotas/FileArchiverNotifierImpl$StoreFileReference
      20: astore_2
      21: aload_0
      22: getfield      #4                  // Field regionName:Ljava/lang/String;
      25: aload_2
      26: getfield      #4                  // Field regionName:Ljava/lang/String;
      29: invokevirtual #13                 // Method java/lang/String.equals:(Ljava/lang/Object;)Z
      32: ifeq          55
      35: aload_0
      36: getfield      #6                  // Field familyToFiles:Lorg/apache/hbase/thirdparty/com/google/common/collect/Multimap;
      39: aload_2
      40: getfield      #6                  // Field familyToFiles:Lorg/apache/hbase/thirdparty/com/google/common/collect/Multimap;
      43: invokeinterface #14,  2           // InterfaceMethod org/apache/hbase/thirdparty/com/google/common/collect/Multimap.equals:(Ljava/lang/Object;)Z
      48: ifeq          55
      51: iconst_1
      52: goto          56
      55: iconst_0
      56: ireturn

  public java.lang.String toString();
    Code:
       0: new           #15                 // class java/lang/StringBuilder
       3: dup
       4: invokespecial #16                 // Method java/lang/StringBuilder."<init>":()V
       7: astore_1
       8: aload_1
       9: ldc           #17                 // String StoreFileReference[region=
      11: invokevirtual #18                 // Method java/lang/StringBuilder.append:(Ljava/lang/String;)Ljava/lang/StringBuilder;
      14: aload_0
      15: getfield      #4                  // Field regionName:Ljava/lang/String;
      18: invokevirtual #18                 // Method java/lang/StringBuilder.append:(Ljava/lang/String;)Ljava/lang/StringBuilder;
      21: ldc           #19                 // String , files=
      23: invokevirtual #18                 // Method java/lang/StringBuilder.append:(Ljava/lang/String;)Ljava/lang/StringBuilder;
      26: aload_0
      27: getfield      #6                  // Field familyToFiles:Lorg/apache/hbase/thirdparty/com/google/common/collect/Multimap;
      30: invokevirtual #20                 // Method java/lang/StringBuilder.append:(Ljava/lang/Object;)Ljava/lang/StringBuilder;
      33: ldc           #21                 // String ]
      35: invokevirtual #18                 // Method java/lang/StringBuilder.append:(Ljava/lang/String;)Ljava/lang/StringBuilder;
      38: invokevirtual #22                 // Method java/lang/StringBuilder.toString:()Ljava/lang/String;
      41: areturn
}
