Compiled from "FlushSnapshotSubprocedure.java"
public class org.apache.hadoop.hbase.regionserver.snapshot.FlushSnapshotSubprocedure$RegionSnapshotTask implements java.util.concurrent.Callable<java.lang.Void> {
  public org.apache.hadoop.hbase.regionserver.snapshot.FlushSnapshotSubprocedure$RegionSnapshotTask(org.apache.hadoop.hbase.regionserver.HRegion, org.apache.hadoop.hbase.shaded.protobuf.generated.SnapshotProtos$SnapshotDescription, boolean, org.apache.hadoop.hbase.errorhandling.ForeignExceptionDispatcher);
    Code:
       0: aload_0
       1: invokespecial #2                  // Method java/lang/Object."<init>":()V
       4: aload_0
       5: aload_1
       6: putfield      #3                  // Field region:Lorg/apache/hadoop/hbase/regionserver/HRegion;
       9: aload_0
      10: iload_3
      11: putfield      #4                  // Field skipFlush:Z
      14: aload_0
      15: aload         4
      17: putfield      #5                  // Field monitor:Lorg/apache/hadoop/hbase/errorhandling/ForeignExceptionDispatcher;
      20: aload_0
      21: aload_2
      22: putfield      #6                  // Field snapshotDesc:Lorg/apache/hadoop/hbase/shaded/protobuf/generated/SnapshotProtos$SnapshotDescription;
      25: return

  public java.lang.Void call() throws java.lang.Exception;
    Code:
       0: invokestatic  #7                  // Method org/apache/hadoop/hbase/regionserver/snapshot/FlushSnapshotSubprocedure.access$000:()Lorg/slf4j/Logger;
       3: new           #8                  // class java/lang/StringBuilder
       6: dup
       7: invokespecial #9                  // Method java/lang/StringBuilder."<init>":()V
      10: ldc           #10                 // String Starting snapshot operation on
      12: invokevirtual #11                 // Method java/lang/StringBuilder.append:(Ljava/lang/String;)Ljava/lang/StringBuilder;
      15: aload_0
      16: getfield      #3                  // Field region:Lorg/apache/hadoop/hbase/regionserver/HRegion;
      19: invokevirtual #12                 // Method java/lang/StringBuilder.append:(Ljava/lang/Object;)Ljava/lang/StringBuilder;
      22: invokevirtual #13                 // Method java/lang/StringBuilder.toString:()Ljava/lang/String;
      25: invokeinterface #14,  2           // InterfaceMethod org/slf4j/Logger.debug:(Ljava/lang/String;)V
      30: aload_0
      31: getfield      #3                  // Field region:Lorg/apache/hadoop/hbase/regionserver/HRegion;
      34: getstatic     #15                 // Field org/apache/hadoop/hbase/regionserver/Region$Operation.SNAPSHOT:Lorg/apache/hadoop/hbase/regionserver/Region$Operation;
      37: invokevirtual #16                 // Method org/apache/hadoop/hbase/regionserver/HRegion.startRegionOperation:(Lorg/apache/hadoop/hbase/regionserver/Region$Operation;)V
      40: aload_0
      41: getfield      #4                  // Field skipFlush:Z
      44: ifeq          60
      47: invokestatic  #7                  // Method org/apache/hadoop/hbase/regionserver/snapshot/FlushSnapshotSubprocedure.access$000:()Lorg/slf4j/Logger;
      50: ldc           #17                 // String take snapshot without flush memstore first
      52: invokeinterface #14,  2           // InterfaceMethod org/slf4j/Logger.debug:(Ljava/lang/String;)V
      57: goto          192
      60: invokestatic  #7                  // Method org/apache/hadoop/hbase/regionserver/snapshot/FlushSnapshotSubprocedure.access$000:()Lorg/slf4j/Logger;
      63: new           #8                  // class java/lang/StringBuilder
      66: dup
      67: invokespecial #9                  // Method java/lang/StringBuilder."<init>":()V
      70: ldc           #18                 // String Flush Snapshotting region
      72: invokevirtual #11                 // Method java/lang/StringBuilder.append:(Ljava/lang/String;)Ljava/lang/StringBuilder;
      75: aload_0
      76: getfield      #3                  // Field region:Lorg/apache/hadoop/hbase/regionserver/HRegion;
      79: invokevirtual #19                 // Method org/apache/hadoop/hbase/regionserver/HRegion.toString:()Ljava/lang/String;
      82: invokevirtual #11                 // Method java/lang/StringBuilder.append:(Ljava/lang/String;)Ljava/lang/StringBuilder;
      85: ldc           #20                 // String  started...
      87: invokevirtual #11                 // Method java/lang/StringBuilder.append:(Ljava/lang/String;)Ljava/lang/StringBuilder;
      90: invokevirtual #13                 // Method java/lang/StringBuilder.toString:()Ljava/lang/String;
      93: invokeinterface #14,  2           // InterfaceMethod org/slf4j/Logger.debug:(Ljava/lang/String;)V
      98: iconst_0
      99: istore_1
     100: aload_0
     101: getfield      #3                  // Field region:Lorg/apache/hadoop/hbase/regionserver/HRegion;
     104: getstatic     #21                 // Field org/apache/hadoop/hbase/client/IsolationLevel.READ_COMMITTED:Lorg/apache/hadoop/hbase/client/IsolationLevel;
     107: invokevirtual #22                 // Method org/apache/hadoop/hbase/regionserver/HRegion.getReadPoint:(Lorg/apache/hadoop/hbase/client/IsolationLevel;)J
     110: lstore_2
     111: iconst_0
     112: istore        4
     114: iload         4
     116: iconst_3
     117: if_icmpge     178
     120: aload_0
     121: getfield      #3                  // Field region:Lorg/apache/hadoop/hbase/regionserver/HRegion;
     124: iconst_1
     125: invokevirtual #23                 // Method org/apache/hadoop/hbase/regionserver/HRegion.flush:(Z)Lorg/apache/hadoop/hbase/regionserver/HRegion$FlushResult;
     128: astore        5
     130: aload         5
     132: invokeinterface #24,  1           // InterfaceMethod org/apache/hadoop/hbase/regionserver/HRegion$FlushResult.getResult:()Lorg/apache/hadoop/hbase/regionserver/HRegion$FlushResult$Result;
     137: getstatic     #25                 // Field org/apache/hadoop/hbase/regionserver/HRegion$FlushResult$Result.CANNOT_FLUSH:Lorg/apache/hadoop/hbase/regionserver/HRegion$FlushResult$Result;
     140: if_acmpne     167
     143: aload_0
     144: getfield      #3                  // Field region:Lorg/apache/hadoop/hbase/regionserver/HRegion;
     147: invokevirtual #26                 // Method org/apache/hadoop/hbase/regionserver/HRegion.waitForFlushes:()V
     150: aload_0
     151: getfield      #3                  // Field region:Lorg/apache/hadoop/hbase/regionserver/HRegion;
     154: invokevirtual #27                 // Method org/apache/hadoop/hbase/regionserver/HRegion.getMaxFlushedSeqId:()J
     157: lload_2
     158: lcmp
     159: iflt          172
     162: iconst_1
     163: istore_1
     164: goto          178
     167: iconst_1
     168: istore_1
     169: goto          178
     172: iinc          4, 1
     175: goto          114
     178: iload_1
     179: ifne          192
     182: new           #28                 // class java/io/IOException
     185: dup
     186: ldc           #29                 // String Unable to complete flush after 3 attempts
     188: invokespecial #30                 // Method java/io/IOException."<init>":(Ljava/lang/String;)V
     191: athrow
     192: aload_0
     193: getfield      #3                  // Field region:Lorg/apache/hadoop/hbase/regionserver/HRegion;
     196: aload_0
     197: getfield      #6                  // Field snapshotDesc:Lorg/apache/hadoop/hbase/shaded/protobuf/generated/SnapshotProtos$SnapshotDescription;
     200: aload_0
     201: getfield      #5                  // Field monitor:Lorg/apache/hadoop/hbase/errorhandling/ForeignExceptionDispatcher;
     204: invokevirtual #31                 // Method org/apache/hadoop/hbase/regionserver/HRegion.addRegionToSnapshot:(Lorg/apache/hadoop/hbase/shaded/protobuf/generated/SnapshotProtos$SnapshotDescription;Lorg/apache/hadoop/hbase/errorhandling/ForeignExceptionSnare;)V
     207: aload_0
     208: getfield      #4                  // Field skipFlush:Z
     211: ifeq          255
     214: invokestatic  #7                  // Method org/apache/hadoop/hbase/regionserver/snapshot/FlushSnapshotSubprocedure.access$000:()Lorg/slf4j/Logger;
     217: new           #8                  // class java/lang/StringBuilder
     220: dup
     221: invokespecial #9                  // Method java/lang/StringBuilder."<init>":()V
     224: ldc           #32                 // String ... SkipFlush Snapshotting region
     226: invokevirtual #11                 // Method java/lang/StringBuilder.append:(Ljava/lang/String;)Ljava/lang/StringBuilder;
     229: aload_0
     230: getfield      #3                  // Field region:Lorg/apache/hadoop/hbase/regionserver/HRegion;
     233: invokevirtual #19                 // Method org/apache/hadoop/hbase/regionserver/HRegion.toString:()Ljava/lang/String;
     236: invokevirtual #11                 // Method java/lang/StringBuilder.append:(Ljava/lang/String;)Ljava/lang/StringBuilder;
     239: ldc           #33                 // String  completed.
     241: invokevirtual #11                 // Method java/lang/StringBuilder.append:(Ljava/lang/String;)Ljava/lang/StringBuilder;
     244: invokevirtual #13                 // Method java/lang/StringBuilder.toString:()Ljava/lang/String;
     247: invokeinterface #14,  2           // InterfaceMethod org/slf4j/Logger.debug:(Ljava/lang/String;)V
     252: goto          293
     255: invokestatic  #7                  // Method org/apache/hadoop/hbase/regionserver/snapshot/FlushSnapshotSubprocedure.access$000:()Lorg/slf4j/Logger;
     258: new           #8                  // class java/lang/StringBuilder
     261: dup
     262: invokespecial #9                  // Method java/lang/StringBuilder."<init>":()V
     265: ldc           #34                 // String ... Flush Snapshotting region
     267: invokevirtual #11                 // Method java/lang/StringBuilder.append:(Ljava/lang/String;)Ljava/lang/StringBuilder;
     270: aload_0
     271: getfield      #3                  // Field region:Lorg/apache/hadoop/hbase/regionserver/HRegion;
     274: invokevirtual #19                 // Method org/apache/hadoop/hbase/regionserver/HRegion.toString:()Ljava/lang/String;
     277: invokevirtual #11                 // Method java/lang/StringBuilder.append:(Ljava/lang/String;)Ljava/lang/StringBuilder;
     280: ldc           #33                 // String  completed.
     282: invokevirtual #11                 // Method java/lang/StringBuilder.append:(Ljava/lang/String;)Ljava/lang/StringBuilder;
     285: invokevirtual #13                 // Method java/lang/StringBuilder.toString:()Ljava/lang/String;
     288: invokeinterface #14,  2           // InterfaceMethod org/slf4j/Logger.debug:(Ljava/lang/String;)V
     293: invokestatic  #7                  // Method org/apache/hadoop/hbase/regionserver/snapshot/FlushSnapshotSubprocedure.access$000:()Lorg/slf4j/Logger;
     296: new           #8                  // class java/lang/StringBuilder
     299: dup
     300: invokespecial #9                  // Method java/lang/StringBuilder."<init>":()V
     303: ldc           #35                 // String Closing snapshot operation on
     305: invokevirtual #11                 // Method java/lang/StringBuilder.append:(Ljava/lang/String;)Ljava/lang/StringBuilder;
     308: aload_0
     309: getfield      #3                  // Field region:Lorg/apache/hadoop/hbase/regionserver/HRegion;
     312: invokevirtual #12                 // Method java/lang/StringBuilder.append:(Ljava/lang/Object;)Ljava/lang/StringBuilder;
     315: invokevirtual #13                 // Method java/lang/StringBuilder.toString:()Ljava/lang/String;
     318: invokeinterface #14,  2           // InterfaceMethod org/slf4j/Logger.debug:(Ljava/lang/String;)V
     323: aload_0
     324: getfield      #3                  // Field region:Lorg/apache/hadoop/hbase/regionserver/HRegion;
     327: getstatic     #15                 // Field org/apache/hadoop/hbase/regionserver/Region$Operation.SNAPSHOT:Lorg/apache/hadoop/hbase/regionserver/Region$Operation;
     330: invokevirtual #36                 // Method org/apache/hadoop/hbase/regionserver/HRegion.closeRegionOperation:(Lorg/apache/hadoop/hbase/regionserver/Region$Operation;)V
     333: goto          381
     336: astore        6
     338: invokestatic  #7                  // Method org/apache/hadoop/hbase/regionserver/snapshot/FlushSnapshotSubprocedure.access$000:()Lorg/slf4j/Logger;
     341: new           #8                  // class java/lang/StringBuilder
     344: dup
     345: invokespecial #9                  // Method java/lang/StringBuilder."<init>":()V
     348: ldc           #35                 // String Closing snapshot operation on
     350: invokevirtual #11                 // Method java/lang/StringBuilder.append:(Ljava/lang/String;)Ljava/lang/StringBuilder;
     353: aload_0
     354: getfield      #3                  // Field region:Lorg/apache/hadoop/hbase/regionserver/HRegion;
     357: invokevirtual #12                 // Method java/lang/StringBuilder.append:(Ljava/lang/Object;)Ljava/lang/StringBuilder;
     360: invokevirtual #13                 // Method java/lang/StringBuilder.toString:()Ljava/lang/String;
     363: invokeinterface #14,  2           // InterfaceMethod org/slf4j/Logger.debug:(Ljava/lang/String;)V
     368: aload_0
     369: getfield      #3                  // Field region:Lorg/apache/hadoop/hbase/regionserver/HRegion;
     372: getstatic     #15                 // Field org/apache/hadoop/hbase/regionserver/Region$Operation.SNAPSHOT:Lorg/apache/hadoop/hbase/regionserver/Region$Operation;
     375: invokevirtual #36                 // Method org/apache/hadoop/hbase/regionserver/HRegion.closeRegionOperation:(Lorg/apache/hadoop/hbase/regionserver/Region$Operation;)V
     378: aload         6
     380: athrow
     381: aconst_null
     382: areturn
    Exception table:
       from    to  target type
          40   293   336   any
         336   338   336   any

  public java.lang.Object call() throws java.lang.Exception;
    Code:
       0: aload_0
       1: invokevirtual #37                 // Method call:()Ljava/lang/Void;
       4: areturn
}
