Compiled from "FlushAllLargeStoresPolicy.java"
public class org.apache.hadoop.hbase.regionserver.FlushAllLargeStoresPolicy extends org.apache.hadoop.hbase.regionserver.FlushLargeStoresPolicy {
  public org.apache.hadoop.hbase.regionserver.FlushAllLargeStoresPolicy();
    Code:
       0: aload_0
       1: invokespecial #1                  // Method org/apache/hadoop/hbase/regionserver/FlushLargeStoresPolicy."<init>":()V
       4: return

  protected void configureForRegion(org.apache.hadoop.hbase.regionserver.HRegion);
    Code:
       0: aload_0
       1: aload_1
       2: invokespecial #2                  // Method org/apache/hadoop/hbase/regionserver/FlushLargeStoresPolicy.configureForRegion:(Lorg/apache/hadoop/hbase/regionserver/HRegion;)V
       5: aload_1
       6: invokevirtual #3                  // Method org/apache/hadoop/hbase/regionserver/HRegion.getTableDescriptor:()Lorg/apache/hadoop/hbase/client/TableDescriptor;
       9: invokeinterface #4,  1            // InterfaceMethod org/apache/hadoop/hbase/client/TableDescriptor.getColumnFamilyCount:()I
      14: istore_2
      15: iload_2
      16: iconst_1
      17: if_icmpgt     21
      20: return
      21: aload_0
      22: aload_1
      23: invokevirtual #5                  // Method setFlushSizeLowerBounds:(Lorg/apache/hadoop/hbase/regionserver/HRegion;)V
      26: return

  public java.util.Collection<org.apache.hadoop.hbase.regionserver.HStore> selectStoresToFlush();
    Code:
       0: aload_0
       1: getfield      #6                  // Field region:Lorg/apache/hadoop/hbase/regionserver/HRegion;
       4: invokevirtual #3                  // Method org/apache/hadoop/hbase/regionserver/HRegion.getTableDescriptor:()Lorg/apache/hadoop/hbase/client/TableDescriptor;
       7: invokeinterface #4,  1            // InterfaceMethod org/apache/hadoop/hbase/client/TableDescriptor.getColumnFamilyCount:()I
      12: iconst_1
      13: if_icmpne     29
      16: aload_0
      17: getfield      #6                  // Field region:Lorg/apache/hadoop/hbase/regionserver/HRegion;
      20: getfield      #7                  // Field org/apache/hadoop/hbase/regionserver/HRegion.stores:Ljava/util/Map;
      23: invokeinterface #8,  1            // InterfaceMethod java/util/Map.values:()Ljava/util/Collection;
      28: areturn
      29: aload_0
      30: getfield      #6                  // Field region:Lorg/apache/hadoop/hbase/regionserver/HRegion;
      33: getfield      #7                  // Field org/apache/hadoop/hbase/regionserver/HRegion.stores:Ljava/util/Map;
      36: invokeinterface #8,  1            // InterfaceMethod java/util/Map.values:()Ljava/util/Collection;
      41: astore_1
      42: new           #9                  // class java/util/HashSet
      45: dup
      46: invokespecial #10                 // Method java/util/HashSet."<init>":()V
      49: astore_2
      50: aload_1
      51: invokeinterface #11,  1           // InterfaceMethod java/util/Collection.iterator:()Ljava/util/Iterator;
      56: astore_3
      57: aload_3
      58: invokeinterface #12,  1           // InterfaceMethod java/util/Iterator.hasNext:()Z
      63: ifeq          98
      66: aload_3
      67: invokeinterface #13,  1           // InterfaceMethod java/util/Iterator.next:()Ljava/lang/Object;
      72: checkcast     #14                 // class org/apache/hadoop/hbase/regionserver/HStore
      75: astore        4
      77: aload_0
      78: aload         4
      80: invokevirtual #15                 // Method shouldFlush:(Lorg/apache/hadoop/hbase/regionserver/HStore;)Z
      83: ifeq          95
      86: aload_2
      87: aload         4
      89: invokeinterface #16,  2           // InterfaceMethod java/util/Set.add:(Ljava/lang/Object;)Z
      94: pop
      95: goto          57
      98: aload_2
      99: invokeinterface #17,  1           // InterfaceMethod java/util/Set.isEmpty:()Z
     104: ifne          109
     107: aload_2
     108: areturn
     109: getstatic     #18                 // Field LOG:Lorg/slf4j/Logger;
     112: invokeinterface #19,  1           // InterfaceMethod org/slf4j/Logger.isDebugEnabled:()Z
     117: ifeq          130
     120: getstatic     #18                 // Field LOG:Lorg/slf4j/Logger;
     123: ldc           #20                 // String Since none of the CFs were above the size, flushing all.
     125: invokeinterface #21,  2           // InterfaceMethod org/slf4j/Logger.debug:(Ljava/lang/String;)V
     130: aload_1
     131: areturn

  protected boolean shouldFlush(org.apache.hadoop.hbase.regionserver.HStore);
    Code:
       0: aload_0
       1: aload_1
       2: invokespecial #22                 // Method org/apache/hadoop/hbase/regionserver/FlushLargeStoresPolicy.shouldFlush:(Lorg/apache/hadoop/hbase/regionserver/HStore;)Z
       5: ifne          19
       8: aload_0
       9: getfield      #6                  // Field region:Lorg/apache/hadoop/hbase/regionserver/HRegion;
      12: aload_1
      13: invokevirtual #23                 // Method org/apache/hadoop/hbase/regionserver/HRegion.shouldFlushStore:(Lorg/apache/hadoop/hbase/regionserver/HStore;)Z
      16: ifeq          23
      19: iconst_1
      20: goto          24
      23: iconst_0
      24: ireturn

  static {};
    Code:
       0: ldc           #24                 // class org/apache/hadoop/hbase/regionserver/FlushAllLargeStoresPolicy
       2: invokestatic  #25                 // Method org/slf4j/LoggerFactory.getLogger:(Ljava/lang/Class;)Lorg/slf4j/Logger;
       5: putstatic     #18                 // Field LOG:Lorg/slf4j/Logger;
       8: return
}
