Compiled from "ForeignExceptionUtil.java"
public final class org.apache.hadoop.hbase.util.ForeignExceptionUtil {
  public static java.lang.Exception toException(org.apache.hadoop.hbase.shaded.protobuf.generated.ErrorHandlingProtos$ForeignExceptionMessage);
    Code:
       0: ldc           #2                  // class java/lang/Exception
       2: aload_0
       3: invokestatic  #3                  // Method createException:(Ljava/lang/Class;Lorg/apache/hadoop/hbase/shaded/protobuf/generated/ErrorHandlingProtos$ForeignExceptionMessage;)Ljava/lang/Exception;
       6: astore_1
       7: goto          26
      10: astore_2
      11: new           #2                  // class java/lang/Exception
      14: dup
      15: aload_0
      16: invokevirtual #5                  // Method org/apache/hadoop/hbase/shaded/protobuf/generated/ErrorHandlingProtos$ForeignExceptionMessage.getGenericException:()Lorg/apache/hadoop/hbase/shaded/protobuf/generated/ErrorHandlingProtos$GenericExceptionMessage;
      19: invokevirtual #6                  // Method org/apache/hadoop/hbase/shaded/protobuf/generated/ErrorHandlingProtos$GenericExceptionMessage.getMessage:()Ljava/lang/String;
      22: invokespecial #7                  // Method java/lang/Exception."<init>":(Ljava/lang/String;)V
      25: astore_1
      26: aload_1
      27: aload_0
      28: invokestatic  #8                  // Method setExceptionDetails:(Ljava/lang/Exception;Lorg/apache/hadoop/hbase/shaded/protobuf/generated/ErrorHandlingProtos$ForeignExceptionMessage;)Ljava/lang/Exception;
      31: areturn
    Exception table:
       from    to  target type
           0     7    10   Class java/lang/Throwable

  public static java.io.IOException toIOException(org.apache.hadoop.hbase.shaded.protobuf.generated.ErrorHandlingProtos$ForeignExceptionMessage);
    Code:
       0: ldc           #9                  // class java/io/IOException
       2: aload_0
       3: invokestatic  #3                  // Method createException:(Ljava/lang/Class;Lorg/apache/hadoop/hbase/shaded/protobuf/generated/ErrorHandlingProtos$ForeignExceptionMessage;)Ljava/lang/Exception;
       6: checkcast     #9                  // class java/io/IOException
       9: astore_1
      10: goto          29
      13: astore_2
      14: new           #9                  // class java/io/IOException
      17: dup
      18: aload_0
      19: invokevirtual #5                  // Method org/apache/hadoop/hbase/shaded/protobuf/generated/ErrorHandlingProtos$ForeignExceptionMessage.getGenericException:()Lorg/apache/hadoop/hbase/shaded/protobuf/generated/ErrorHandlingProtos$GenericExceptionMessage;
      22: invokevirtual #6                  // Method org/apache/hadoop/hbase/shaded/protobuf/generated/ErrorHandlingProtos$GenericExceptionMessage.getMessage:()Ljava/lang/String;
      25: invokespecial #10                 // Method java/io/IOException."<init>":(Ljava/lang/String;)V
      28: astore_1
      29: aload_1
      30: aload_0
      31: invokestatic  #8                  // Method setExceptionDetails:(Ljava/lang/Exception;Lorg/apache/hadoop/hbase/shaded/protobuf/generated/ErrorHandlingProtos$ForeignExceptionMessage;)Ljava/lang/Exception;
      34: checkcast     #9                  // class java/io/IOException
      37: areturn
    Exception table:
       from    to  target type
           0    10    13   Class java/lang/Throwable

  public static org.apache.hadoop.hbase.shaded.protobuf.generated.ErrorHandlingProtos$ForeignExceptionMessage toProtoForeignException(java.lang.Throwable);
    Code:
       0: aconst_null
       1: aload_0
       2: invokestatic  #23                 // Method toProtoForeignException:(Ljava/lang/String;Ljava/lang/Throwable;)Lorg/apache/hadoop/hbase/shaded/protobuf/generated/ErrorHandlingProtos$ForeignExceptionMessage;
       5: areturn

  public static org.apache.hadoop.hbase.shaded.protobuf.generated.ErrorHandlingProtos$ForeignExceptionMessage toProtoForeignException(java.lang.String, java.lang.Throwable);
    Code:
       0: invokestatic  #24                 // Method org/apache/hadoop/hbase/shaded/protobuf/generated/ErrorHandlingProtos$GenericExceptionMessage.newBuilder:()Lorg/apache/hadoop/hbase/shaded/protobuf/generated/ErrorHandlingProtos$GenericExceptionMessage$Builder;
       3: astore_2
       4: aload_2
       5: aload_1
       6: invokevirtual #25                 // Method java/lang/Object.getClass:()Ljava/lang/Class;
       9: invokevirtual #26                 // Method java/lang/Class.getName:()Ljava/lang/String;
      12: invokevirtual #27                 // Method org/apache/hadoop/hbase/shaded/protobuf/generated/ErrorHandlingProtos$GenericExceptionMessage$Builder.setClassName:(Ljava/lang/String;)Lorg/apache/hadoop/hbase/shaded/protobuf/generated/ErrorHandlingProtos$GenericExceptionMessage$Builder;
      15: pop
      16: aload_1
      17: invokevirtual #28                 // Method java/lang/Throwable.getMessage:()Ljava/lang/String;
      20: ifnull        32
      23: aload_2
      24: aload_1
      25: invokevirtual #28                 // Method java/lang/Throwable.getMessage:()Ljava/lang/String;
      28: invokevirtual #29                 // Method org/apache/hadoop/hbase/shaded/protobuf/generated/ErrorHandlingProtos$GenericExceptionMessage$Builder.setMessage:(Ljava/lang/String;)Lorg/apache/hadoop/hbase/shaded/protobuf/generated/ErrorHandlingProtos$GenericExceptionMessage$Builder;
      31: pop
      32: aload_1
      33: invokevirtual #30                 // Method java/lang/Throwable.getStackTrace:()[Ljava/lang/StackTraceElement;
      36: invokestatic  #31                 // Method toProtoStackTraceElement:([Ljava/lang/StackTraceElement;)Ljava/util/List;
      39: astore_3
      40: aload_3
      41: ifnull        50
      44: aload_2
      45: aload_3
      46: invokevirtual #32                 // Method org/apache/hadoop/hbase/shaded/protobuf/generated/ErrorHandlingProtos$GenericExceptionMessage$Builder.addAllTrace:(Ljava/lang/Iterable;)Lorg/apache/hadoop/hbase/shaded/protobuf/generated/ErrorHandlingProtos$GenericExceptionMessage$Builder;
      49: pop
      50: aload_2
      51: invokevirtual #33                 // Method org/apache/hadoop/hbase/shaded/protobuf/generated/ErrorHandlingProtos$GenericExceptionMessage$Builder.build:()Lorg/apache/hadoop/hbase/shaded/protobuf/generated/ErrorHandlingProtos$GenericExceptionMessage;
      54: astore        4
      56: invokestatic  #34                 // Method org/apache/hadoop/hbase/shaded/protobuf/generated/ErrorHandlingProtos$ForeignExceptionMessage.newBuilder:()Lorg/apache/hadoop/hbase/shaded/protobuf/generated/ErrorHandlingProtos$ForeignExceptionMessage$Builder;
      59: astore        5
      61: aload         5
      63: aload         4
      65: invokevirtual #35                 // Method org/apache/hadoop/hbase/shaded/protobuf/generated/ErrorHandlingProtos$ForeignExceptionMessage$Builder.setGenericException:(Lorg/apache/hadoop/hbase/shaded/protobuf/generated/ErrorHandlingProtos$GenericExceptionMessage;)Lorg/apache/hadoop/hbase/shaded/protobuf/generated/ErrorHandlingProtos$ForeignExceptionMessage$Builder;
      68: pop
      69: aload_0
      70: ifnull        80
      73: aload         5
      75: aload_0
      76: invokevirtual #36                 // Method org/apache/hadoop/hbase/shaded/protobuf/generated/ErrorHandlingProtos$ForeignExceptionMessage$Builder.setSource:(Ljava/lang/String;)Lorg/apache/hadoop/hbase/shaded/protobuf/generated/ErrorHandlingProtos$ForeignExceptionMessage$Builder;
      79: pop
      80: aload         5
      82: invokevirtual #37                 // Method org/apache/hadoop/hbase/shaded/protobuf/generated/ErrorHandlingProtos$ForeignExceptionMessage$Builder.build:()Lorg/apache/hadoop/hbase/shaded/protobuf/generated/ErrorHandlingProtos$ForeignExceptionMessage;
      85: areturn

  public static java.util.List<org.apache.hadoop.hbase.shaded.protobuf.generated.ErrorHandlingProtos$StackTraceElementMessage> toProtoStackTraceElement(java.lang.StackTraceElement[]);
    Code:
       0: aload_0
       1: ifnonnull     6
       4: aconst_null
       5: areturn
       6: new           #38                 // class java/util/ArrayList
       9: dup
      10: aload_0
      11: arraylength
      12: invokespecial #39                 // Method java/util/ArrayList."<init>":(I)V
      15: astore_1
      16: aload_0
      17: astore_2
      18: aload_2
      19: arraylength
      20: istore_3
      21: iconst_0
      22: istore        4
      24: iload         4
      26: iload_3
      27: if_icmpge     111
      30: aload_2
      31: iload         4
      33: aaload
      34: astore        5
      36: invokestatic  #40                 // Method org/apache/hadoop/hbase/shaded/protobuf/generated/ErrorHandlingProtos$StackTraceElementMessage.newBuilder:()Lorg/apache/hadoop/hbase/shaded/protobuf/generated/ErrorHandlingProtos$StackTraceElementMessage$Builder;
      39: astore        6
      41: aload         6
      43: aload         5
      45: invokevirtual #41                 // Method java/lang/StackTraceElement.getClassName:()Ljava/lang/String;
      48: invokevirtual #42                 // Method org/apache/hadoop/hbase/shaded/protobuf/generated/ErrorHandlingProtos$StackTraceElementMessage$Builder.setDeclaringClass:(Ljava/lang/String;)Lorg/apache/hadoop/hbase/shaded/protobuf/generated/ErrorHandlingProtos$StackTraceElementMessage$Builder;
      51: pop
      52: aload         5
      54: invokevirtual #43                 // Method java/lang/StackTraceElement.getFileName:()Ljava/lang/String;
      57: ifnull        71
      60: aload         6
      62: aload         5
      64: invokevirtual #43                 // Method java/lang/StackTraceElement.getFileName:()Ljava/lang/String;
      67: invokevirtual #44                 // Method org/apache/hadoop/hbase/shaded/protobuf/generated/ErrorHandlingProtos$StackTraceElementMessage$Builder.setFileName:(Ljava/lang/String;)Lorg/apache/hadoop/hbase/shaded/protobuf/generated/ErrorHandlingProtos$StackTraceElementMessage$Builder;
      70: pop
      71: aload         6
      73: aload         5
      75: invokevirtual #45                 // Method java/lang/StackTraceElement.getLineNumber:()I
      78: invokevirtual #46                 // Method org/apache/hadoop/hbase/shaded/protobuf/generated/ErrorHandlingProtos$StackTraceElementMessage$Builder.setLineNumber:(I)Lorg/apache/hadoop/hbase/shaded/protobuf/generated/ErrorHandlingProtos$StackTraceElementMessage$Builder;
      81: pop
      82: aload         6
      84: aload         5
      86: invokevirtual #47                 // Method java/lang/StackTraceElement.getMethodName:()Ljava/lang/String;
      89: invokevirtual #48                 // Method org/apache/hadoop/hbase/shaded/protobuf/generated/ErrorHandlingProtos$StackTraceElementMessage$Builder.setMethodName:(Ljava/lang/String;)Lorg/apache/hadoop/hbase/shaded/protobuf/generated/ErrorHandlingProtos$StackTraceElementMessage$Builder;
      92: pop
      93: aload_1
      94: aload         6
      96: invokevirtual #49                 // Method org/apache/hadoop/hbase/shaded/protobuf/generated/ErrorHandlingProtos$StackTraceElementMessage$Builder.build:()Lorg/apache/hadoop/hbase/shaded/protobuf/generated/ErrorHandlingProtos$StackTraceElementMessage;
      99: invokeinterface #50,  2           // InterfaceMethod java/util/List.add:(Ljava/lang/Object;)Z
     104: pop
     105: iinc          4, 1
     108: goto          24
     111: aload_1
     112: areturn

  public static java.lang.StackTraceElement[] toStackTrace(java.util.List<org.apache.hadoop.hbase.shaded.protobuf.generated.ErrorHandlingProtos$StackTraceElementMessage>);
    Code:
       0: aload_0
       1: ifnull        13
       4: aload_0
       5: invokeinterface #51,  1           // InterfaceMethod java/util/List.isEmpty:()Z
      10: ifeq          18
      13: iconst_0
      14: anewarray     #52                 // class java/lang/StackTraceElement
      17: areturn
      18: aload_0
      19: invokeinterface #53,  1           // InterfaceMethod java/util/List.size:()I
      24: anewarray     #52                 // class java/lang/StackTraceElement
      27: astore_1
      28: iconst_0
      29: istore_2
      30: iload_2
      31: aload_0
      32: invokeinterface #53,  1           // InterfaceMethod java/util/List.size:()I
      37: if_icmpge     94
      40: aload_0
      41: iload_2
      42: invokeinterface #54,  2           // InterfaceMethod java/util/List.get:(I)Ljava/lang/Object;
      47: checkcast     #55                 // class org/apache/hadoop/hbase/shaded/protobuf/generated/ErrorHandlingProtos$StackTraceElementMessage
      50: astore_3
      51: aload_1
      52: iload_2
      53: new           #52                 // class java/lang/StackTraceElement
      56: dup
      57: aload_3
      58: invokevirtual #56                 // Method org/apache/hadoop/hbase/shaded/protobuf/generated/ErrorHandlingProtos$StackTraceElementMessage.getDeclaringClass:()Ljava/lang/String;
      61: aload_3
      62: invokevirtual #57                 // Method org/apache/hadoop/hbase/shaded/protobuf/generated/ErrorHandlingProtos$StackTraceElementMessage.getMethodName:()Ljava/lang/String;
      65: aload_3
      66: invokevirtual #58                 // Method org/apache/hadoop/hbase/shaded/protobuf/generated/ErrorHandlingProtos$StackTraceElementMessage.hasFileName:()Z
      69: ifeq          79
      72: aload_3
      73: invokevirtual #59                 // Method org/apache/hadoop/hbase/shaded/protobuf/generated/ErrorHandlingProtos$StackTraceElementMessage.getFileName:()Ljava/lang/String;
      76: goto          80
      79: aconst_null
      80: aload_3
      81: invokevirtual #60                 // Method org/apache/hadoop/hbase/shaded/protobuf/generated/ErrorHandlingProtos$StackTraceElementMessage.getLineNumber:()I
      84: invokespecial #61                 // Method java/lang/StackTraceElement."<init>":(Ljava/lang/String;Ljava/lang/String;Ljava/lang/String;I)V
      87: aastore
      88: iinc          2, 1
      91: goto          30
      94: aload_1
      95: areturn
}
