Compiled from "FSHLog.java"
class org.apache.hadoop.hbase.regionserver.wal.FSHLog$SyncRunner extends org.apache.hadoop.hbase.util.HasThread {
  final org.apache.hadoop.hbase.regionserver.wal.FSHLog this$0;

  org.apache.hadoop.hbase.regionserver.wal.FSHLog$SyncRunner(org.apache.hadoop.hbase.regionserver.wal.FSHLog, java.lang.String, int);
    Code:
       0: aload_0
       1: aload_1
       2: putfield      #1                  // Field this$0:Lorg/apache/hadoop/hbase/regionserver/wal/FSHLog;
       5: aload_0
       6: aload_2
       7: invokespecial #2                  // Method org/apache/hadoop/hbase/util/HasThread."<init>":(Ljava/lang/String;)V
      10: aload_0
      11: aconst_null
      12: putfield      #3                  // Field takeSyncFuture:Lorg/apache/hadoop/hbase/regionserver/wal/SyncFuture;
      15: aload_0
      16: new           #4                  // class java/util/concurrent/LinkedBlockingQueue
      19: dup
      20: iload_3
      21: iconst_3
      22: imul
      23: invokespecial #5                  // Method java/util/concurrent/LinkedBlockingQueue."<init>":(I)V
      26: putfield      #6                  // Field syncFutures:Ljava/util/concurrent/BlockingQueue;
      29: return

  void offer(long, org.apache.hadoop.hbase.regionserver.wal.SyncFuture[], int);
    Code:
       0: aload_0
       1: lload_1
       2: putfield      #7                  // Field sequence:J
       5: iconst_0
       6: istore        5
       8: iload         5
      10: iload         4
      12: if_icmpge     35
      15: aload_0
      16: getfield      #6                  // Field syncFutures:Ljava/util/concurrent/BlockingQueue;
      19: aload_3
      20: iload         5
      22: aaload
      23: invokeinterface #8,  2            // InterfaceMethod java/util/concurrent/BlockingQueue.add:(Ljava/lang/Object;)Z
      28: pop
      29: iinc          5, 1
      32: goto          8
      35: return

  boolean areSyncFuturesReleased();
    Code:
       0: aload_0
       1: getfield      #6                  // Field syncFutures:Ljava/util/concurrent/BlockingQueue;
       4: invokeinterface #22,  1           // InterfaceMethod java/util/concurrent/BlockingQueue.size:()I
       9: ifgt          23
      12: aload_0
      13: getfield      #3                  // Field takeSyncFuture:Lorg/apache/hadoop/hbase/regionserver/wal/SyncFuture;
      16: ifnonnull     23
      19: iconst_1
      20: goto          24
      23: iconst_0
      24: ireturn

  public void run();
    Code:
       0: aload_0
       1: invokevirtual #23                 // Method isInterrupted:()Z
       4: ifne          468
       7: iconst_0
       8: istore_3
       9: aload_0
      10: aconst_null
      11: putfield      #3                  // Field takeSyncFuture:Lorg/apache/hadoop/hbase/regionserver/wal/SyncFuture;
      14: aload_0
      15: aload_0
      16: getfield      #6                  // Field syncFutures:Ljava/util/concurrent/BlockingQueue;
      19: invokeinterface #24,  1           // InterfaceMethod java/util/concurrent/BlockingQueue.take:()Ljava/lang/Object;
      24: checkcast     #13                 // class org/apache/hadoop/hbase/regionserver/wal/SyncFuture
      27: putfield      #3                  // Field takeSyncFuture:Lorg/apache/hadoop/hbase/regionserver/wal/SyncFuture;
      30: aload_0
      31: getfield      #7                  // Field sequence:J
      34: lstore_1
      35: aload_0
      36: getfield      #3                  // Field takeSyncFuture:Lorg/apache/hadoop/hbase/regionserver/wal/SyncFuture;
      39: invokevirtual #14                 // Method org/apache/hadoop/hbase/regionserver/wal/SyncFuture.getTxid:()J
      42: lstore        4
      44: lload         4
      46: lload_1
      47: lcmp
      48: ifle          88
      51: new           #10                 // class java/lang/IllegalStateException
      54: dup
      55: new           #25                 // class java/lang/StringBuilder
      58: dup
      59: invokespecial #26                 // Method java/lang/StringBuilder."<init>":()V
      62: ldc           #27                 // String currentSequence=
      64: invokevirtual #28                 // Method java/lang/StringBuilder.append:(Ljava/lang/String;)Ljava/lang/StringBuilder;
      67: lload_1
      68: invokevirtual #29                 // Method java/lang/StringBuilder.append:(J)Ljava/lang/StringBuilder;
      71: ldc           #30                 // String , syncFutureSequence=
      73: invokevirtual #28                 // Method java/lang/StringBuilder.append:(Ljava/lang/String;)Ljava/lang/StringBuilder;
      76: lload         4
      78: invokevirtual #29                 // Method java/lang/StringBuilder.append:(J)Ljava/lang/StringBuilder;
      81: invokevirtual #31                 // Method java/lang/StringBuilder.toString:()Ljava/lang/String;
      84: invokespecial #18                 // Method java/lang/IllegalStateException."<init>":(Ljava/lang/String;)V
      87: athrow
      88: aload_0
      89: getfield      #1                  // Field this$0:Lorg/apache/hadoop/hbase/regionserver/wal/FSHLog;
      92: getfield      #19                 // Field org/apache/hadoop/hbase/regionserver/wal/FSHLog.highestSyncedTxid:Ljava/util/concurrent/atomic/AtomicLong;
      95: invokevirtual #20                 // Method java/util/concurrent/atomic/AtomicLong.get:()J
      98: lstore        6
     100: lload_1
     101: lload         6
     103: lcmp
     104: ifge          124
     107: iload_3
     108: aload_0
     109: aload_0
     110: getfield      #3                  // Field takeSyncFuture:Lorg/apache/hadoop/hbase/regionserver/wal/SyncFuture;
     113: lload         6
     115: aconst_null
     116: invokespecial #15                 // Method releaseSyncFuture:(Lorg/apache/hadoop/hbase/regionserver/wal/SyncFuture;JLjava/lang/Throwable;)I
     119: iadd
     120: istore_3
     121: goto          9
     124: invokestatic  #32                 // Method java/lang/System.nanoTime:()J
     127: lstore        4
     129: aconst_null
     130: astore        6
     132: iconst_0
     133: istore        7
     135: ldc           #33                 // String syncing writer
     137: invokestatic  #34                 // Method org/apache/hadoop/hbase/trace/TraceUtil.addTimelineAnnotation:(Ljava/lang/String;)V
     140: aload_0
     141: getfield      #1                  // Field this$0:Lorg/apache/hadoop/hbase/regionserver/wal/FSHLog;
     144: getfield      #35                 // Field org/apache/hadoop/hbase/regionserver/wal/FSHLog.writer:Lorg/apache/hadoop/hbase/wal/WALProvider$WriterBase;
     147: checkcast     #36                 // class org/apache/hadoop/hbase/wal/WALProvider$Writer
     150: aload_0
     151: getfield      #1                  // Field this$0:Lorg/apache/hadoop/hbase/regionserver/wal/FSHLog;
     154: invokestatic  #37                 // Method org/apache/hadoop/hbase/regionserver/wal/FSHLog.access$100:(Lorg/apache/hadoop/hbase/regionserver/wal/FSHLog;)Z
     157: invokeinterface #38,  2           // InterfaceMethod org/apache/hadoop/hbase/wal/WALProvider$Writer.sync:(Z)V
     162: ldc           #39                 // String writer synced
     164: invokestatic  #34                 // Method org/apache/hadoop/hbase/trace/TraceUtil.addTimelineAnnotation:(Ljava/lang/String;)V
     167: aload_0
     168: lload_1
     169: invokespecial #40                 // Method updateHighestSyncedSequence:(J)J
     172: lstore_1
     173: iload_3
     174: aload_0
     175: aload_0
     176: getfield      #3                  // Field takeSyncFuture:Lorg/apache/hadoop/hbase/regionserver/wal/SyncFuture;
     179: lload_1
     180: aload         6
     182: invokespecial #15                 // Method releaseSyncFuture:(Lorg/apache/hadoop/hbase/regionserver/wal/SyncFuture;JLjava/lang/Throwable;)I
     185: iadd
     186: istore_3
     187: iload_3
     188: aload_0
     189: lload_1
     190: aload         6
     192: invokespecial #41                 // Method releaseSyncFutures:(JLjava/lang/Throwable;)I
     195: iadd
     196: istore_3
     197: aload         6
     199: ifnull        215
     202: aload_0
     203: getfield      #1                  // Field this$0:Lorg/apache/hadoop/hbase/regionserver/wal/FSHLog;
     206: getstatic     #42                 // Field org/apache/hadoop/hbase/regionserver/wal/WALActionsListener$RollRequestReason.ERROR:Lorg/apache/hadoop/hbase/regionserver/wal/WALActionsListener$RollRequestReason;
     209: invokevirtual #43                 // Method org/apache/hadoop/hbase/regionserver/wal/FSHLog.requestLogRoll:(Lorg/apache/hadoop/hbase/regionserver/wal/WALActionsListener$RollRequestReason;)V
     212: goto          423
     215: aload_0
     216: getfield      #1                  // Field this$0:Lorg/apache/hadoop/hbase/regionserver/wal/FSHLog;
     219: invokestatic  #44                 // Method org/apache/hadoop/hbase/regionserver/wal/FSHLog.access$200:(Lorg/apache/hadoop/hbase/regionserver/wal/FSHLog;)Z
     222: pop
     223: goto          423
     226: astore        8
     228: invokestatic  #46                 // Method org/apache/hadoop/hbase/regionserver/wal/FSHLog.access$000:()Lorg/slf4j/Logger;
     231: ldc           #47                 // String Error syncing, request close of WAL
     233: aload         8
     235: invokeinterface #48,  3           // InterfaceMethod org/slf4j/Logger.error:(Ljava/lang/String;Ljava/lang/Throwable;)V
     240: aload         8
     242: astore        6
     244: iload_3
     245: aload_0
     246: aload_0
     247: getfield      #3                  // Field takeSyncFuture:Lorg/apache/hadoop/hbase/regionserver/wal/SyncFuture;
     250: lload_1
     251: aload         6
     253: invokespecial #15                 // Method releaseSyncFuture:(Lorg/apache/hadoop/hbase/regionserver/wal/SyncFuture;JLjava/lang/Throwable;)I
     256: iadd
     257: istore_3
     258: iload_3
     259: aload_0
     260: lload_1
     261: aload         6
     263: invokespecial #41                 // Method releaseSyncFutures:(JLjava/lang/Throwable;)I
     266: iadd
     267: istore_3
     268: aload         6
     270: ifnull        286
     273: aload_0
     274: getfield      #1                  // Field this$0:Lorg/apache/hadoop/hbase/regionserver/wal/FSHLog;
     277: getstatic     #42                 // Field org/apache/hadoop/hbase/regionserver/wal/WALActionsListener$RollRequestReason.ERROR:Lorg/apache/hadoop/hbase/regionserver/wal/WALActionsListener$RollRequestReason;
     280: invokevirtual #43                 // Method org/apache/hadoop/hbase/regionserver/wal/FSHLog.requestLogRoll:(Lorg/apache/hadoop/hbase/regionserver/wal/WALActionsListener$RollRequestReason;)V
     283: goto          423
     286: aload_0
     287: getfield      #1                  // Field this$0:Lorg/apache/hadoop/hbase/regionserver/wal/FSHLog;
     290: invokestatic  #44                 // Method org/apache/hadoop/hbase/regionserver/wal/FSHLog.access$200:(Lorg/apache/hadoop/hbase/regionserver/wal/FSHLog;)Z
     293: pop
     294: goto          423
     297: astore        8
     299: invokestatic  #46                 // Method org/apache/hadoop/hbase/regionserver/wal/FSHLog.access$000:()Lorg/slf4j/Logger;
     302: ldc           #50                 // String UNEXPECTED
     304: aload         8
     306: invokeinterface #51,  3           // InterfaceMethod org/slf4j/Logger.warn:(Ljava/lang/String;Ljava/lang/Throwable;)V
     311: aload         8
     313: astore        6
     315: iload_3
     316: aload_0
     317: aload_0
     318: getfield      #3                  // Field takeSyncFuture:Lorg/apache/hadoop/hbase/regionserver/wal/SyncFuture;
     321: lload_1
     322: aload         6
     324: invokespecial #15                 // Method releaseSyncFuture:(Lorg/apache/hadoop/hbase/regionserver/wal/SyncFuture;JLjava/lang/Throwable;)I
     327: iadd
     328: istore_3
     329: iload_3
     330: aload_0
     331: lload_1
     332: aload         6
     334: invokespecial #41                 // Method releaseSyncFutures:(JLjava/lang/Throwable;)I
     337: iadd
     338: istore_3
     339: aload         6
     341: ifnull        357
     344: aload_0
     345: getfield      #1                  // Field this$0:Lorg/apache/hadoop/hbase/regionserver/wal/FSHLog;
     348: getstatic     #42                 // Field org/apache/hadoop/hbase/regionserver/wal/WALActionsListener$RollRequestReason.ERROR:Lorg/apache/hadoop/hbase/regionserver/wal/WALActionsListener$RollRequestReason;
     351: invokevirtual #43                 // Method org/apache/hadoop/hbase/regionserver/wal/FSHLog.requestLogRoll:(Lorg/apache/hadoop/hbase/regionserver/wal/WALActionsListener$RollRequestReason;)V
     354: goto          423
     357: aload_0
     358: getfield      #1                  // Field this$0:Lorg/apache/hadoop/hbase/regionserver/wal/FSHLog;
     361: invokestatic  #44                 // Method org/apache/hadoop/hbase/regionserver/wal/FSHLog.access$200:(Lorg/apache/hadoop/hbase/regionserver/wal/FSHLog;)Z
     364: pop
     365: goto          423
     368: astore        9
     370: iload_3
     371: aload_0
     372: aload_0
     373: getfield      #3                  // Field takeSyncFuture:Lorg/apache/hadoop/hbase/regionserver/wal/SyncFuture;
     376: lload_1
     377: aload         6
     379: invokespecial #15                 // Method releaseSyncFuture:(Lorg/apache/hadoop/hbase/regionserver/wal/SyncFuture;JLjava/lang/Throwable;)I
     382: iadd
     383: istore_3
     384: iload_3
     385: aload_0
     386: lload_1
     387: aload         6
     389: invokespecial #41                 // Method releaseSyncFutures:(JLjava/lang/Throwable;)I
     392: iadd
     393: istore_3
     394: aload         6
     396: ifnull        412
     399: aload_0
     400: getfield      #1                  // Field this$0:Lorg/apache/hadoop/hbase/regionserver/wal/FSHLog;
     403: getstatic     #42                 // Field org/apache/hadoop/hbase/regionserver/wal/WALActionsListener$RollRequestReason.ERROR:Lorg/apache/hadoop/hbase/regionserver/wal/WALActionsListener$RollRequestReason;
     406: invokevirtual #43                 // Method org/apache/hadoop/hbase/regionserver/wal/FSHLog.requestLogRoll:(Lorg/apache/hadoop/hbase/regionserver/wal/WALActionsListener$RollRequestReason;)V
     409: goto          420
     412: aload_0
     413: getfield      #1                  // Field this$0:Lorg/apache/hadoop/hbase/regionserver/wal/FSHLog;
     416: invokestatic  #44                 // Method org/apache/hadoop/hbase/regionserver/wal/FSHLog.access$200:(Lorg/apache/hadoop/hbase/regionserver/wal/FSHLog;)Z
     419: pop
     420: aload         9
     422: athrow
     423: aload_0
     424: getfield      #1                  // Field this$0:Lorg/apache/hadoop/hbase/regionserver/wal/FSHLog;
     427: invokestatic  #32                 // Method java/lang/System.nanoTime:()J
     430: lload         4
     432: lsub
     433: iload_3
     434: invokevirtual #52                 // Method org/apache/hadoop/hbase/regionserver/wal/FSHLog.postSync:(JI)V
     437: goto          465
     440: astore        4
     442: invokestatic  #54                 // Method java/lang/Thread.currentThread:()Ljava/lang/Thread;
     445: invokevirtual #55                 // Method java/lang/Thread.interrupt:()V
     448: goto          465
     451: astore        4
     453: invokestatic  #46                 // Method org/apache/hadoop/hbase/regionserver/wal/FSHLog.access$000:()Lorg/slf4j/Logger;
     456: ldc           #57                 // String UNEXPECTED, continuing
     458: aload         4
     460: invokeinterface #51,  3           // InterfaceMethod org/slf4j/Logger.warn:(Ljava/lang/String;Ljava/lang/Throwable;)V
     465: goto          0
     468: return
    Exception table:
       from    to  target type
         135   173   226   Class java/io/IOException
         135   173   297   Class java/lang/Exception
         135   173   368   any
         226   244   368   any
         297   315   368   any
         368   370   368   any
           9   437   440   Class java/lang/InterruptedException
           9   437   451   Class java/lang/Throwable
}
