Compiled from "FSUtils.java"
public class org.apache.hadoop.hbase.util.FSUtils$UserTableDirFilter extends org.apache.hadoop.hbase.util.FSUtils$BlackListDirFilter {
  public org.apache.hadoop.hbase.util.FSUtils$UserTableDirFilter(org.apache.hadoop.fs.FileSystem);
    Code:
       0: aload_0
       1: aload_1
       2: getstatic     #1                  // Field org/apache/hadoop/hbase/HConstants.HBASE_NON_TABLE_DIRS:Ljava/util/List;
       5: invokespecial #2                  // Method org/apache/hadoop/hbase/util/FSUtils$BlackListDirFilter."<init>":(Lorg/apache/hadoop/fs/FileSystem;Ljava/util/List;)V
       8: return

  protected boolean isValidName(java.lang.String);
    Code:
       0: aload_0
       1: aload_1
       2: invokespecial #3                  // Method org/apache/hadoop/hbase/util/FSUtils$BlackListDirFilter.isValidName:(Ljava/lang/String;)Z
       5: ifne          10
       8: iconst_0
       9: ireturn
      10: aload_1
      11: invokestatic  #4                  // Method org/apache/hadoop/hbase/util/Bytes.toBytes:(Ljava/lang/String;)[B
      14: invokestatic  #5                  // Method org/apache/hadoop/hbase/TableName.isLegalTableQualifierName:([B)[B
      17: pop
      18: goto          51
      21: astore_2
      22: invokestatic  #7                  // Method org/apache/hadoop/hbase/util/FSUtils.access$000:()Lorg/slf4j/Logger;
      25: new           #8                  // class java/lang/StringBuilder
      28: dup
      29: invokespecial #9                  // Method java/lang/StringBuilder."<init>":()V
      32: ldc           #10                 // String INVALID NAME
      34: invokevirtual #11                 // Method java/lang/StringBuilder.append:(Ljava/lang/String;)Ljava/lang/StringBuilder;
      37: aload_1
      38: invokevirtual #11                 // Method java/lang/StringBuilder.append:(Ljava/lang/String;)Ljava/lang/StringBuilder;
      41: invokevirtual #12                 // Method java/lang/StringBuilder.toString:()Ljava/lang/String;
      44: invokeinterface #13,  2           // InterfaceMethod org/slf4j/Logger.info:(Ljava/lang/String;)V
      49: iconst_0
      50: ireturn
      51: iconst_1
      52: ireturn
    Exception table:
       from    to  target type
          10    18    21   Class java/lang/IllegalArgumentException
}
