Compiled from "GCMergedRegionsProcedure.java"
public class org.apache.hadoop.hbase.master.assignment.GCMergedRegionsProcedure extends org.apache.hadoop.hbase.master.procedure.AbstractStateMachineTableProcedure<org.apache.hadoop.hbase.shaded.protobuf.generated.MasterProcedureProtos$GCMergedRegionsState> {
  public org.apache.hadoop.hbase.master.assignment.GCMergedRegionsProcedure(org.apache.hadoop.hbase.master.procedure.MasterProcedureEnv, org.apache.hadoop.hbase.client.RegionInfo, org.apache.hadoop.hbase.client.RegionInfo, org.apache.hadoop.hbase.client.RegionInfo);
    Code:
       0: aload_0
       1: aload_1
       2: invokespecial #1                  // Method org/apache/hadoop/hbase/master/procedure/AbstractStateMachineTableProcedure."<init>":(Lorg/apache/hadoop/hbase/master/procedure/MasterProcedureEnv;)V
       5: aload_0
       6: aload_3
       7: putfield      #2                  // Field father:Lorg/apache/hadoop/hbase/client/RegionInfo;
      10: aload_0
      11: aload         4
      13: putfield      #3                  // Field mother:Lorg/apache/hadoop/hbase/client/RegionInfo;
      16: aload_0
      17: aload_2
      18: putfield      #4                  // Field mergedChild:Lorg/apache/hadoop/hbase/client/RegionInfo;
      21: return

  public org.apache.hadoop.hbase.master.assignment.GCMergedRegionsProcedure();
    Code:
       0: aload_0
       1: invokespecial #5                  // Method org/apache/hadoop/hbase/master/procedure/AbstractStateMachineTableProcedure."<init>":()V
       4: return

  public org.apache.hadoop.hbase.master.procedure.TableProcedureInterface$TableOperationType getTableOperationType();
    Code:
       0: getstatic     #6                  // Field org/apache/hadoop/hbase/master/procedure/TableProcedureInterface$TableOperationType.MERGED_REGIONS_GC:Lorg/apache/hadoop/hbase/master/procedure/TableProcedureInterface$TableOperationType;
       3: areturn

  protected org.apache.hadoop.hbase.procedure2.StateMachineProcedure$Flow executeFromState(org.apache.hadoop.hbase.master.procedure.MasterProcedureEnv, org.apache.hadoop.hbase.shaded.protobuf.generated.MasterProcedureProtos$GCMergedRegionsState) throws org.apache.hadoop.hbase.procedure2.ProcedureSuspendedException, org.apache.hadoop.hbase.procedure2.ProcedureYieldException, java.lang.InterruptedException;
    Code:
       0: getstatic     #7                  // Field LOG:Lorg/slf4j/Logger;
       3: invokeinterface #8,  1            // InterfaceMethod org/slf4j/Logger.isTraceEnabled:()Z
       8: ifeq          42
      11: getstatic     #7                  // Field LOG:Lorg/slf4j/Logger;
      14: new           #9                  // class java/lang/StringBuilder
      17: dup
      18: invokespecial #10                 // Method java/lang/StringBuilder."<init>":()V
      21: aload_0
      22: invokevirtual #11                 // Method java/lang/StringBuilder.append:(Ljava/lang/Object;)Ljava/lang/StringBuilder;
      25: ldc           #12                 // String  execute state=
      27: invokevirtual #13                 // Method java/lang/StringBuilder.append:(Ljava/lang/String;)Ljava/lang/StringBuilder;
      30: aload_2
      31: invokevirtual #11                 // Method java/lang/StringBuilder.append:(Ljava/lang/Object;)Ljava/lang/StringBuilder;
      34: invokevirtual #14                 // Method java/lang/StringBuilder.toString:()Ljava/lang/String;
      37: invokeinterface #15,  2           // InterfaceMethod org/slf4j/Logger.trace:(Ljava/lang/String;)V
      42: getstatic     #16                 // Field org/apache/hadoop/hbase/master/assignment/GCMergedRegionsProcedure$1.$SwitchMap$org$apache$hadoop$hbase$shaded$protobuf$generated$MasterProcedureProtos$GCMergedRegionsState:[I
      45: aload_2
      46: invokevirtual #17                 // Method org/apache/hadoop/hbase/shaded/protobuf/generated/MasterProcedureProtos$GCMergedRegionsState.ordinal:()I
      49: iaload
      50: tableswitch   { // 1 to 3
                     1: 76
                     2: 86
                     3: 105
               default: 125
          }
      76: aload_0
      77: getstatic     #18                 // Field org/apache/hadoop/hbase/shaded/protobuf/generated/MasterProcedureProtos$GCMergedRegionsState.GC_MERGED_REGIONS_PURGE:Lorg/apache/hadoop/hbase/shaded/protobuf/generated/MasterProcedureProtos$GCMergedRegionsState;
      80: invokevirtual #19                 // Method setNextState:(Ljava/lang/Object;)V
      83: goto          156
      86: aload_0
      87: aload_0
      88: aload_1
      89: invokespecial #20                 // Method createGCRegionProcedures:(Lorg/apache/hadoop/hbase/master/procedure/MasterProcedureEnv;)[Lorg/apache/hadoop/hbase/master/assignment/GCRegionProcedure;
      92: invokevirtual #21                 // Method addChildProcedure:([Lorg/apache/hadoop/hbase/procedure2/Procedure;)V
      95: aload_0
      96: getstatic     #22                 // Field org/apache/hadoop/hbase/shaded/protobuf/generated/MasterProcedureProtos$GCMergedRegionsState.GC_REGION_EDIT_METADATA:Lorg/apache/hadoop/hbase/shaded/protobuf/generated/MasterProcedureProtos$GCMergedRegionsState;
      99: invokevirtual #19                 // Method setNextState:(Ljava/lang/Object;)V
     102: goto          156
     105: aload_1
     106: invokevirtual #23                 // Method org/apache/hadoop/hbase/master/procedure/MasterProcedureEnv.getMasterServices:()Lorg/apache/hadoop/hbase/master/MasterServices;
     109: invokeinterface #24,  1           // InterfaceMethod org/apache/hadoop/hbase/master/MasterServices.getConnection:()Lorg/apache/hadoop/hbase/client/Connection;
     114: aload_0
     115: getfield      #4                  // Field mergedChild:Lorg/apache/hadoop/hbase/client/RegionInfo;
     118: invokestatic  #25                 // Method org/apache/hadoop/hbase/MetaTableAccessor.deleteMergeQualifiers:(Lorg/apache/hadoop/hbase/client/Connection;Lorg/apache/hadoop/hbase/client/RegionInfo;)V
     121: getstatic     #26                 // Field org/apache/hadoop/hbase/procedure2/StateMachineProcedure$Flow.NO_MORE_STATE:Lorg/apache/hadoop/hbase/procedure2/StateMachineProcedure$Flow;
     124: areturn
     125: new           #27                 // class java/lang/UnsupportedOperationException
     128: dup
     129: new           #9                  // class java/lang/StringBuilder
     132: dup
     133: invokespecial #10                 // Method java/lang/StringBuilder."<init>":()V
     136: aload_0
     137: invokevirtual #11                 // Method java/lang/StringBuilder.append:(Ljava/lang/Object;)Ljava/lang/StringBuilder;
     140: ldc           #28                 // String  unhandled state=
     142: invokevirtual #13                 // Method java/lang/StringBuilder.append:(Ljava/lang/String;)Ljava/lang/StringBuilder;
     145: aload_2
     146: invokevirtual #11                 // Method java/lang/StringBuilder.append:(Ljava/lang/Object;)Ljava/lang/StringBuilder;
     149: invokevirtual #14                 // Method java/lang/StringBuilder.toString:()Ljava/lang/String;
     152: invokespecial #29                 // Method java/lang/UnsupportedOperationException."<init>":(Ljava/lang/String;)V
     155: athrow
     156: goto          218
     159: astore_3
     160: getstatic     #7                  // Field LOG:Lorg/slf4j/Logger;
     163: new           #9                  // class java/lang/StringBuilder
     166: dup
     167: invokespecial #10                 // Method java/lang/StringBuilder."<init>":()V
     170: ldc           #31                 // String Error trying to GC merged regions
     172: invokevirtual #13                 // Method java/lang/StringBuilder.append:(Ljava/lang/String;)Ljava/lang/StringBuilder;
     175: aload_0
     176: getfield      #2                  // Field father:Lorg/apache/hadoop/hbase/client/RegionInfo;
     179: invokeinterface #32,  1           // InterfaceMethod org/apache/hadoop/hbase/client/RegionInfo.getShortNameToLog:()Ljava/lang/String;
     184: invokevirtual #13                 // Method java/lang/StringBuilder.append:(Ljava/lang/String;)Ljava/lang/StringBuilder;
     187: ldc           #33                 // String  &
     189: invokevirtual #13                 // Method java/lang/StringBuilder.append:(Ljava/lang/String;)Ljava/lang/StringBuilder;
     192: aload_0
     193: getfield      #3                  // Field mother:Lorg/apache/hadoop/hbase/client/RegionInfo;
     196: invokeinterface #32,  1           // InterfaceMethod org/apache/hadoop/hbase/client/RegionInfo.getShortNameToLog:()Ljava/lang/String;
     201: invokevirtual #13                 // Method java/lang/StringBuilder.append:(Ljava/lang/String;)Ljava/lang/StringBuilder;
     204: ldc           #34                 // String ; retrying...
     206: invokevirtual #13                 // Method java/lang/StringBuilder.append:(Ljava/lang/String;)Ljava/lang/StringBuilder;
     209: invokevirtual #14                 // Method java/lang/StringBuilder.toString:()Ljava/lang/String;
     212: aload_3
     213: invokeinterface #35,  3           // InterfaceMethod org/slf4j/Logger.warn:(Ljava/lang/String;Ljava/lang/Throwable;)V
     218: getstatic     #36                 // Field org/apache/hadoop/hbase/procedure2/StateMachineProcedure$Flow.HAS_MORE_STATE:Lorg/apache/hadoop/hbase/procedure2/StateMachineProcedure$Flow;
     221: areturn
    Exception table:
       from    to  target type
          42   124   159   Class java/io/IOException
         125   156   159   Class java/io/IOException

  protected void rollbackState(org.apache.hadoop.hbase.master.procedure.MasterProcedureEnv, org.apache.hadoop.hbase.shaded.protobuf.generated.MasterProcedureProtos$GCMergedRegionsState) throws java.io.IOException, java.lang.InterruptedException;
    Code:
       0: return

  protected org.apache.hadoop.hbase.shaded.protobuf.generated.MasterProcedureProtos$GCMergedRegionsState getState(int);
    Code:
       0: iload_1
       1: invokestatic  #43                 // Method org/apache/hadoop/hbase/shaded/protobuf/generated/MasterProcedureProtos$GCMergedRegionsState.forNumber:(I)Lorg/apache/hadoop/hbase/shaded/protobuf/generated/MasterProcedureProtos$GCMergedRegionsState;
       4: areturn

  protected int getStateId(org.apache.hadoop.hbase.shaded.protobuf.generated.MasterProcedureProtos$GCMergedRegionsState);
    Code:
       0: aload_1
       1: invokevirtual #44                 // Method org/apache/hadoop/hbase/shaded/protobuf/generated/MasterProcedureProtos$GCMergedRegionsState.getNumber:()I
       4: ireturn

  protected org.apache.hadoop.hbase.shaded.protobuf.generated.MasterProcedureProtos$GCMergedRegionsState getInitialState();
    Code:
       0: getstatic     #45                 // Field org/apache/hadoop/hbase/shaded/protobuf/generated/MasterProcedureProtos$GCMergedRegionsState.GC_MERGED_REGIONS_PREPARE:Lorg/apache/hadoop/hbase/shaded/protobuf/generated/MasterProcedureProtos$GCMergedRegionsState;
       3: areturn

  protected void serializeStateData(org.apache.hadoop.hbase.procedure2.ProcedureStateSerializer) throws java.io.IOException;
    Code:
       0: aload_0
       1: aload_1
       2: invokespecial #46                 // Method org/apache/hadoop/hbase/master/procedure/AbstractStateMachineTableProcedure.serializeStateData:(Lorg/apache/hadoop/hbase/procedure2/ProcedureStateSerializer;)V
       5: invokestatic  #47                 // Method org/apache/hadoop/hbase/shaded/protobuf/generated/MasterProcedureProtos$GCMergedRegionsStateData.newBuilder:()Lorg/apache/hadoop/hbase/shaded/protobuf/generated/MasterProcedureProtos$GCMergedRegionsStateData$Builder;
       8: aload_0
       9: getfield      #2                  // Field father:Lorg/apache/hadoop/hbase/client/RegionInfo;
      12: invokestatic  #48                 // Method org/apache/hadoop/hbase/shaded/protobuf/ProtobufUtil.toRegionInfo:(Lorg/apache/hadoop/hbase/client/RegionInfo;)Lorg/apache/hadoop/hbase/shaded/protobuf/generated/HBaseProtos$RegionInfo;
      15: invokevirtual #49                 // Method org/apache/hadoop/hbase/shaded/protobuf/generated/MasterProcedureProtos$GCMergedRegionsStateData$Builder.setParentA:(Lorg/apache/hadoop/hbase/shaded/protobuf/generated/HBaseProtos$RegionInfo;)Lorg/apache/hadoop/hbase/shaded/protobuf/generated/MasterProcedureProtos$GCMergedRegionsStateData$Builder;
      18: aload_0
      19: getfield      #3                  // Field mother:Lorg/apache/hadoop/hbase/client/RegionInfo;
      22: invokestatic  #48                 // Method org/apache/hadoop/hbase/shaded/protobuf/ProtobufUtil.toRegionInfo:(Lorg/apache/hadoop/hbase/client/RegionInfo;)Lorg/apache/hadoop/hbase/shaded/protobuf/generated/HBaseProtos$RegionInfo;
      25: invokevirtual #50                 // Method org/apache/hadoop/hbase/shaded/protobuf/generated/MasterProcedureProtos$GCMergedRegionsStateData$Builder.setParentB:(Lorg/apache/hadoop/hbase/shaded/protobuf/generated/HBaseProtos$RegionInfo;)Lorg/apache/hadoop/hbase/shaded/protobuf/generated/MasterProcedureProtos$GCMergedRegionsStateData$Builder;
      28: aload_0
      29: getfield      #4                  // Field mergedChild:Lorg/apache/hadoop/hbase/client/RegionInfo;
      32: invokestatic  #48                 // Method org/apache/hadoop/hbase/shaded/protobuf/ProtobufUtil.toRegionInfo:(Lorg/apache/hadoop/hbase/client/RegionInfo;)Lorg/apache/hadoop/hbase/shaded/protobuf/generated/HBaseProtos$RegionInfo;
      35: invokevirtual #51                 // Method org/apache/hadoop/hbase/shaded/protobuf/generated/MasterProcedureProtos$GCMergedRegionsStateData$Builder.setMergedChild:(Lorg/apache/hadoop/hbase/shaded/protobuf/generated/HBaseProtos$RegionInfo;)Lorg/apache/hadoop/hbase/shaded/protobuf/generated/MasterProcedureProtos$GCMergedRegionsStateData$Builder;
      38: astore_2
      39: aload_1
      40: aload_2
      41: invokevirtual #52                 // Method org/apache/hadoop/hbase/shaded/protobuf/generated/MasterProcedureProtos$GCMergedRegionsStateData$Builder.build:()Lorg/apache/hadoop/hbase/shaded/protobuf/generated/MasterProcedureProtos$GCMergedRegionsStateData;
      44: invokeinterface #53,  2           // InterfaceMethod org/apache/hadoop/hbase/procedure2/ProcedureStateSerializer.serialize:(Lorg/apache/hbase/thirdparty/com/google/protobuf/Message;)V
      49: return

  protected void deserializeStateData(org.apache.hadoop.hbase.procedure2.ProcedureStateSerializer) throws java.io.IOException;
    Code:
       0: aload_0
       1: aload_1
       2: invokespecial #54                 // Method org/apache/hadoop/hbase/master/procedure/AbstractStateMachineTableProcedure.deserializeStateData:(Lorg/apache/hadoop/hbase/procedure2/ProcedureStateSerializer;)V
       5: aload_1
       6: ldc           #55                 // class org/apache/hadoop/hbase/shaded/protobuf/generated/MasterProcedureProtos$GCMergedRegionsStateData
       8: invokeinterface #56,  2           // InterfaceMethod org/apache/hadoop/hbase/procedure2/ProcedureStateSerializer.deserialize:(Ljava/lang/Class;)Lorg/apache/hbase/thirdparty/com/google/protobuf/Message;
      13: checkcast     #55                 // class org/apache/hadoop/hbase/shaded/protobuf/generated/MasterProcedureProtos$GCMergedRegionsStateData
      16: astore_2
      17: aload_0
      18: aload_2
      19: invokevirtual #57                 // Method org/apache/hadoop/hbase/shaded/protobuf/generated/MasterProcedureProtos$GCMergedRegionsStateData.getParentA:()Lorg/apache/hadoop/hbase/shaded/protobuf/generated/HBaseProtos$RegionInfo;
      22: invokestatic  #58                 // Method org/apache/hadoop/hbase/shaded/protobuf/ProtobufUtil.toRegionInfo:(Lorg/apache/hadoop/hbase/shaded/protobuf/generated/HBaseProtos$RegionInfo;)Lorg/apache/hadoop/hbase/client/RegionInfo;
      25: putfield      #2                  // Field father:Lorg/apache/hadoop/hbase/client/RegionInfo;
      28: aload_0
      29: aload_2
      30: invokevirtual #59                 // Method org/apache/hadoop/hbase/shaded/protobuf/generated/MasterProcedureProtos$GCMergedRegionsStateData.getParentB:()Lorg/apache/hadoop/hbase/shaded/protobuf/generated/HBaseProtos$RegionInfo;
      33: invokestatic  #58                 // Method org/apache/hadoop/hbase/shaded/protobuf/ProtobufUtil.toRegionInfo:(Lorg/apache/hadoop/hbase/shaded/protobuf/generated/HBaseProtos$RegionInfo;)Lorg/apache/hadoop/hbase/client/RegionInfo;
      36: putfield      #3                  // Field mother:Lorg/apache/hadoop/hbase/client/RegionInfo;
      39: aload_0
      40: aload_2
      41: invokevirtual #60                 // Method org/apache/hadoop/hbase/shaded/protobuf/generated/MasterProcedureProtos$GCMergedRegionsStateData.getMergedChild:()Lorg/apache/hadoop/hbase/shaded/protobuf/generated/HBaseProtos$RegionInfo;
      44: invokestatic  #58                 // Method org/apache/hadoop/hbase/shaded/protobuf/ProtobufUtil.toRegionInfo:(Lorg/apache/hadoop/hbase/shaded/protobuf/generated/HBaseProtos$RegionInfo;)Lorg/apache/hadoop/hbase/client/RegionInfo;
      47: putfield      #4                  // Field mergedChild:Lorg/apache/hadoop/hbase/client/RegionInfo;
      50: return

  public void toStringClassDetails(java.lang.StringBuilder);
    Code:
       0: aload_1
       1: aload_0
       2: invokevirtual #61                 // Method java/lang/Object.getClass:()Ljava/lang/Class;
       5: invokevirtual #62                 // Method java/lang/Class.getSimpleName:()Ljava/lang/String;
       8: invokevirtual #13                 // Method java/lang/StringBuilder.append:(Ljava/lang/String;)Ljava/lang/StringBuilder;
      11: pop
      12: aload_1
      13: ldc           #63                 // String  child=
      15: invokevirtual #13                 // Method java/lang/StringBuilder.append:(Ljava/lang/String;)Ljava/lang/StringBuilder;
      18: pop
      19: aload_1
      20: aload_0
      21: getfield      #4                  // Field mergedChild:Lorg/apache/hadoop/hbase/client/RegionInfo;
      24: invokeinterface #32,  1           // InterfaceMethod org/apache/hadoop/hbase/client/RegionInfo.getShortNameToLog:()Ljava/lang/String;
      29: invokevirtual #13                 // Method java/lang/StringBuilder.append:(Ljava/lang/String;)Ljava/lang/StringBuilder;
      32: pop
      33: aload_1
      34: ldc           #64                 // String , father=
      36: invokevirtual #13                 // Method java/lang/StringBuilder.append:(Ljava/lang/String;)Ljava/lang/StringBuilder;
      39: pop
      40: aload_1
      41: aload_0
      42: getfield      #2                  // Field father:Lorg/apache/hadoop/hbase/client/RegionInfo;
      45: invokeinterface #32,  1           // InterfaceMethod org/apache/hadoop/hbase/client/RegionInfo.getShortNameToLog:()Ljava/lang/String;
      50: invokevirtual #13                 // Method java/lang/StringBuilder.append:(Ljava/lang/String;)Ljava/lang/StringBuilder;
      53: pop
      54: aload_1
      55: ldc           #65                 // String , mother=
      57: invokevirtual #13                 // Method java/lang/StringBuilder.append:(Ljava/lang/String;)Ljava/lang/StringBuilder;
      60: pop
      61: aload_1
      62: aload_0
      63: getfield      #3                  // Field mother:Lorg/apache/hadoop/hbase/client/RegionInfo;
      66: invokeinterface #32,  1           // InterfaceMethod org/apache/hadoop/hbase/client/RegionInfo.getShortNameToLog:()Ljava/lang/String;
      71: invokevirtual #13                 // Method java/lang/StringBuilder.append:(Ljava/lang/String;)Ljava/lang/StringBuilder;
      74: pop
      75: return

  public org.apache.hadoop.hbase.TableName getTableName();
    Code:
       0: aload_0
       1: getfield      #4                  // Field mergedChild:Lorg/apache/hadoop/hbase/client/RegionInfo;
       4: invokeinterface #66,  1           // InterfaceMethod org/apache/hadoop/hbase/client/RegionInfo.getTable:()Lorg/apache/hadoop/hbase/TableName;
       9: areturn

  protected java.lang.Object getInitialState();
    Code:
       0: aload_0
       1: invokevirtual #67                 // Method getInitialState:()Lorg/apache/hadoop/hbase/shaded/protobuf/generated/MasterProcedureProtos$GCMergedRegionsState;
       4: areturn

  protected int getStateId(java.lang.Object);
    Code:
       0: aload_0
       1: aload_1
       2: checkcast     #68                 // class org/apache/hadoop/hbase/shaded/protobuf/generated/MasterProcedureProtos$GCMergedRegionsState
       5: invokevirtual #69                 // Method getStateId:(Lorg/apache/hadoop/hbase/shaded/protobuf/generated/MasterProcedureProtos$GCMergedRegionsState;)I
       8: ireturn

  protected java.lang.Object getState(int);
    Code:
       0: aload_0
       1: iload_1
       2: invokevirtual #70                 // Method getState:(I)Lorg/apache/hadoop/hbase/shaded/protobuf/generated/MasterProcedureProtos$GCMergedRegionsState;
       5: areturn

  protected void rollbackState(java.lang.Object, java.lang.Object) throws java.io.IOException, java.lang.InterruptedException;
    Code:
       0: aload_0
       1: aload_1
       2: checkcast     #71                 // class org/apache/hadoop/hbase/master/procedure/MasterProcedureEnv
       5: aload_2
       6: checkcast     #68                 // class org/apache/hadoop/hbase/shaded/protobuf/generated/MasterProcedureProtos$GCMergedRegionsState
       9: invokevirtual #72                 // Method rollbackState:(Lorg/apache/hadoop/hbase/master/procedure/MasterProcedureEnv;Lorg/apache/hadoop/hbase/shaded/protobuf/generated/MasterProcedureProtos$GCMergedRegionsState;)V
      12: return

  protected org.apache.hadoop.hbase.procedure2.StateMachineProcedure$Flow executeFromState(java.lang.Object, java.lang.Object) throws org.apache.hadoop.hbase.procedure2.ProcedureSuspendedException, org.apache.hadoop.hbase.procedure2.ProcedureYieldException, java.lang.InterruptedException;
    Code:
       0: aload_0
       1: aload_1
       2: checkcast     #71                 // class org/apache/hadoop/hbase/master/procedure/MasterProcedureEnv
       5: aload_2
       6: checkcast     #68                 // class org/apache/hadoop/hbase/shaded/protobuf/generated/MasterProcedureProtos$GCMergedRegionsState
       9: invokevirtual #73                 // Method executeFromState:(Lorg/apache/hadoop/hbase/master/procedure/MasterProcedureEnv;Lorg/apache/hadoop/hbase/shaded/protobuf/generated/MasterProcedureProtos$GCMergedRegionsState;)Lorg/apache/hadoop/hbase/procedure2/StateMachineProcedure$Flow;
      12: areturn

  static {};
    Code:
       0: ldc           #74                 // class org/apache/hadoop/hbase/master/assignment/GCMergedRegionsProcedure
       2: invokestatic  #75                 // Method org/slf4j/LoggerFactory.getLogger:(Ljava/lang/Class;)Lorg/slf4j/Logger;
       5: putstatic     #7                  // Field LOG:Lorg/slf4j/Logger;
       8: return
}
