Compiled from "Get.java"
public class org.apache.hadoop.hbase.client.Get extends org.apache.hadoop.hbase.client.Query implements org.apache.hadoop.hbase.client.Row {
  public org.apache.hadoop.hbase.client.Get(byte[]);
    Code:
       0: aload_0
       1: invokespecial #1                  // Method org/apache/hadoop/hbase/client/Query."<init>":()V
       4: aload_0
       5: aconst_null
       6: putfield      #2                  // Field row:[B
       9: aload_0
      10: iconst_1
      11: putfield      #3                  // Field maxVersions:I
      14: aload_0
      15: iconst_1
      16: putfield      #4                  // Field cacheBlocks:Z
      19: aload_0
      20: iconst_m1
      21: putfield      #5                  // Field storeLimit:I
      24: aload_0
      25: iconst_0
      26: putfield      #6                  // Field storeOffset:I
      29: aload_0
      30: invokestatic  #7                  // Method org/apache/hadoop/hbase/io/TimeRange.allTime:()Lorg/apache/hadoop/hbase/io/TimeRange;
      33: putfield      #8                  // Field tr:Lorg/apache/hadoop/hbase/io/TimeRange;
      36: aload_0
      37: iconst_0
      38: putfield      #9                  // Field checkExistenceOnly:Z
      41: aload_0
      42: iconst_0
      43: putfield      #10                 // Field closestRowBefore:Z
      46: aload_0
      47: new           #11                 // class java/util/TreeMap
      50: dup
      51: getstatic     #12                 // Field org/apache/hadoop/hbase/util/Bytes.BYTES_COMPARATOR:Ljava/util/Comparator;
      54: invokespecial #13                 // Method java/util/TreeMap."<init>":(Ljava/util/Comparator;)V
      57: putfield      #14                 // Field familyMap:Ljava/util/Map;
      60: aload_1
      61: invokestatic  #15                 // Method org/apache/hadoop/hbase/client/Mutation.checkRow:([B)[B
      64: pop
      65: aload_0
      66: aload_1
      67: putfield      #2                  // Field row:[B
      70: return

  public org.apache.hadoop.hbase.client.Get(org.apache.hadoop.hbase.client.Get);
    Code:
       0: aload_0
       1: aload_1
       2: invokevirtual #16                 // Method getRow:()[B
       5: invokespecial #17                 // Method "<init>":([B)V
       8: aload_0
       9: aload_1
      10: invokevirtual #18                 // Method getFilter:()Lorg/apache/hadoop/hbase/filter/Filter;
      13: invokevirtual #19                 // Method setFilter:(Lorg/apache/hadoop/hbase/filter/Filter;)Lorg/apache/hadoop/hbase/client/Get;
      16: pop
      17: aload_0
      18: aload_1
      19: invokevirtual #20                 // Method getReplicaId:()I
      22: invokevirtual #21                 // Method setReplicaId:(I)Lorg/apache/hadoop/hbase/client/Get;
      25: pop
      26: aload_0
      27: aload_1
      28: invokevirtual #22                 // Method getConsistency:()Lorg/apache/hadoop/hbase/client/Consistency;
      31: invokevirtual #23                 // Method setConsistency:(Lorg/apache/hadoop/hbase/client/Consistency;)Lorg/apache/hadoop/hbase/client/Get;
      34: pop
      35: aload_0
      36: aload_1
      37: invokevirtual #24                 // Method getCacheBlocks:()Z
      40: putfield      #4                  // Field cacheBlocks:Z
      43: aload_0
      44: aload_1
      45: invokevirtual #25                 // Method getMaxVersions:()I
      48: putfield      #3                  // Field maxVersions:I
      51: aload_0
      52: aload_1
      53: invokevirtual #26                 // Method getMaxResultsPerColumnFamily:()I
      56: putfield      #5                  // Field storeLimit:I
      59: aload_0
      60: aload_1
      61: invokevirtual #27                 // Method getRowOffsetPerColumnFamily:()I
      64: putfield      #6                  // Field storeOffset:I
      67: aload_0
      68: aload_1
      69: invokevirtual #28                 // Method getTimeRange:()Lorg/apache/hadoop/hbase/io/TimeRange;
      72: putfield      #8                  // Field tr:Lorg/apache/hadoop/hbase/io/TimeRange;
      75: aload_0
      76: aload_1
      77: invokevirtual #29                 // Method isCheckExistenceOnly:()Z
      80: putfield      #9                  // Field checkExistenceOnly:Z
      83: aload_0
      84: aload_1
      85: invokevirtual #30                 // Method getLoadColumnFamiliesOnDemandValue:()Ljava/lang/Boolean;
      88: putfield      #31                 // Field loadColumnFamiliesOnDemand:Ljava/lang/Boolean;
      91: aload_1
      92: invokevirtual #32                 // Method getFamilyMap:()Ljava/util/Map;
      95: astore_2
      96: aload_2
      97: invokeinterface #33,  1           // InterfaceMethod java/util/Map.entrySet:()Ljava/util/Set;
     102: invokeinterface #34,  1           // InterfaceMethod java/util/Set.iterator:()Ljava/util/Iterator;
     107: astore_3
     108: aload_3
     109: invokeinterface #35,  1           // InterfaceMethod java/util/Iterator.hasNext:()Z
     114: ifeq          223
     117: aload_3
     118: invokeinterface #36,  1           // InterfaceMethod java/util/Iterator.next:()Ljava/lang/Object;
     123: checkcast     #37                 // class java/util/Map$Entry
     126: astore        4
     128: aload         4
     130: invokeinterface #38,  1           // InterfaceMethod java/util/Map$Entry.getKey:()Ljava/lang/Object;
     135: checkcast     #39                 // class "[B"
     138: astore        5
     140: aload         4
     142: invokeinterface #40,  1           // InterfaceMethod java/util/Map$Entry.getValue:()Ljava/lang/Object;
     147: checkcast     #41                 // class java/util/NavigableSet
     150: astore        6
     152: aload         6
     154: ifnull        213
     157: aload         6
     159: invokeinterface #42,  1           // InterfaceMethod java/util/NavigableSet.size:()I
     164: ifle          213
     167: aload         6
     169: invokeinterface #43,  1           // InterfaceMethod java/util/NavigableSet.iterator:()Ljava/util/Iterator;
     174: astore        7
     176: aload         7
     178: invokeinterface #35,  1           // InterfaceMethod java/util/Iterator.hasNext:()Z
     183: ifeq          210
     186: aload         7
     188: invokeinterface #36,  1           // InterfaceMethod java/util/Iterator.next:()Ljava/lang/Object;
     193: checkcast     #39                 // class "[B"
     196: astore        8
     198: aload_0
     199: aload         5
     201: aload         8
     203: invokevirtual #44                 // Method addColumn:([B[B)Lorg/apache/hadoop/hbase/client/Get;
     206: pop
     207: goto          176
     210: goto          220
     213: aload_0
     214: aload         5
     216: invokevirtual #45                 // Method addFamily:([B)Lorg/apache/hadoop/hbase/client/Get;
     219: pop
     220: goto          108
     223: aload_1
     224: invokevirtual #46                 // Method getAttributesMap:()Ljava/util/Map;
     227: invokeinterface #33,  1           // InterfaceMethod java/util/Map.entrySet:()Ljava/util/Set;
     232: invokeinterface #34,  1           // InterfaceMethod java/util/Set.iterator:()Ljava/util/Iterator;
     237: astore_3
     238: aload_3
     239: invokeinterface #35,  1           // InterfaceMethod java/util/Iterator.hasNext:()Z
     244: ifeq          286
     247: aload_3
     248: invokeinterface #36,  1           // InterfaceMethod java/util/Iterator.next:()Ljava/lang/Object;
     253: checkcast     #37                 // class java/util/Map$Entry
     256: astore        4
     258: aload_0
     259: aload         4
     261: invokeinterface #38,  1           // InterfaceMethod java/util/Map$Entry.getKey:()Ljava/lang/Object;
     266: checkcast     #47                 // class java/lang/String
     269: aload         4
     271: invokeinterface #40,  1           // InterfaceMethod java/util/Map$Entry.getValue:()Ljava/lang/Object;
     276: checkcast     #39                 // class "[B"
     279: invokevirtual #48                 // Method setAttribute:(Ljava/lang/String;[B)Lorg/apache/hadoop/hbase/client/Get;
     282: pop
     283: goto          238
     286: aload_1
     287: invokevirtual #49                 // Method getColumnFamilyTimeRange:()Ljava/util/Map;
     290: invokeinterface #33,  1           // InterfaceMethod java/util/Map.entrySet:()Ljava/util/Set;
     295: invokeinterface #34,  1           // InterfaceMethod java/util/Set.iterator:()Ljava/util/Iterator;
     300: astore_3
     301: aload_3
     302: invokeinterface #35,  1           // InterfaceMethod java/util/Iterator.hasNext:()Z
     307: ifeq          361
     310: aload_3
     311: invokeinterface #36,  1           // InterfaceMethod java/util/Iterator.next:()Ljava/lang/Object;
     316: checkcast     #37                 // class java/util/Map$Entry
     319: astore        4
     321: aload         4
     323: invokeinterface #40,  1           // InterfaceMethod java/util/Map$Entry.getValue:()Ljava/lang/Object;
     328: checkcast     #50                 // class org/apache/hadoop/hbase/io/TimeRange
     331: astore        5
     333: aload_0
     334: aload         4
     336: invokeinterface #38,  1           // InterfaceMethod java/util/Map$Entry.getKey:()Ljava/lang/Object;
     341: checkcast     #39                 // class "[B"
     344: aload         5
     346: invokevirtual #51                 // Method org/apache/hadoop/hbase/io/TimeRange.getMin:()J
     349: aload         5
     351: invokevirtual #52                 // Method org/apache/hadoop/hbase/io/TimeRange.getMax:()J
     354: invokevirtual #53                 // Method setColumnFamilyTimeRange:([BJJ)Lorg/apache/hadoop/hbase/client/Get;
     357: pop
     358: goto          301
     361: aload_0
     362: aload_1
     363: invokevirtual #54                 // Method getPriority:()I
     366: invokespecial #55                 // Method org/apache/hadoop/hbase/client/Query.setPriority:(I)Lorg/apache/hadoop/hbase/client/OperationWithAttributes;
     369: pop
     370: return

  public org.apache.hadoop.hbase.client.Get(byte[], int, int);
    Code:
       0: aload_0
       1: invokespecial #1                  // Method org/apache/hadoop/hbase/client/Query."<init>":()V
       4: aload_0
       5: aconst_null
       6: putfield      #2                  // Field row:[B
       9: aload_0
      10: iconst_1
      11: putfield      #3                  // Field maxVersions:I
      14: aload_0
      15: iconst_1
      16: putfield      #4                  // Field cacheBlocks:Z
      19: aload_0
      20: iconst_m1
      21: putfield      #5                  // Field storeLimit:I
      24: aload_0
      25: iconst_0
      26: putfield      #6                  // Field storeOffset:I
      29: aload_0
      30: invokestatic  #7                  // Method org/apache/hadoop/hbase/io/TimeRange.allTime:()Lorg/apache/hadoop/hbase/io/TimeRange;
      33: putfield      #8                  // Field tr:Lorg/apache/hadoop/hbase/io/TimeRange;
      36: aload_0
      37: iconst_0
      38: putfield      #9                  // Field checkExistenceOnly:Z
      41: aload_0
      42: iconst_0
      43: putfield      #10                 // Field closestRowBefore:Z
      46: aload_0
      47: new           #11                 // class java/util/TreeMap
      50: dup
      51: getstatic     #12                 // Field org/apache/hadoop/hbase/util/Bytes.BYTES_COMPARATOR:Ljava/util/Comparator;
      54: invokespecial #13                 // Method java/util/TreeMap."<init>":(Ljava/util/Comparator;)V
      57: putfield      #14                 // Field familyMap:Ljava/util/Map;
      60: aload_1
      61: iload_2
      62: iload_3
      63: invokestatic  #56                 // Method org/apache/hadoop/hbase/client/Mutation.checkRow:([BII)[B
      66: pop
      67: aload_0
      68: aload_1
      69: iload_2
      70: iload_3
      71: invokestatic  #57                 // Method org/apache/hadoop/hbase/util/Bytes.copy:([BII)[B
      74: putfield      #2                  // Field row:[B
      77: return

  public org.apache.hadoop.hbase.client.Get(java.nio.ByteBuffer);
    Code:
       0: aload_0
       1: invokespecial #1                  // Method org/apache/hadoop/hbase/client/Query."<init>":()V
       4: aload_0
       5: aconst_null
       6: putfield      #2                  // Field row:[B
       9: aload_0
      10: iconst_1
      11: putfield      #3                  // Field maxVersions:I
      14: aload_0
      15: iconst_1
      16: putfield      #4                  // Field cacheBlocks:Z
      19: aload_0
      20: iconst_m1
      21: putfield      #5                  // Field storeLimit:I
      24: aload_0
      25: iconst_0
      26: putfield      #6                  // Field storeOffset:I
      29: aload_0
      30: invokestatic  #7                  // Method org/apache/hadoop/hbase/io/TimeRange.allTime:()Lorg/apache/hadoop/hbase/io/TimeRange;
      33: putfield      #8                  // Field tr:Lorg/apache/hadoop/hbase/io/TimeRange;
      36: aload_0
      37: iconst_0
      38: putfield      #9                  // Field checkExistenceOnly:Z
      41: aload_0
      42: iconst_0
      43: putfield      #10                 // Field closestRowBefore:Z
      46: aload_0
      47: new           #11                 // class java/util/TreeMap
      50: dup
      51: getstatic     #12                 // Field org/apache/hadoop/hbase/util/Bytes.BYTES_COMPARATOR:Ljava/util/Comparator;
      54: invokespecial #13                 // Method java/util/TreeMap."<init>":(Ljava/util/Comparator;)V
      57: putfield      #14                 // Field familyMap:Ljava/util/Map;
      60: aload_1
      61: invokestatic  #58                 // Method org/apache/hadoop/hbase/client/Mutation.checkRow:(Ljava/nio/ByteBuffer;)V
      64: aload_0
      65: aload_1
      66: invokevirtual #59                 // Method java/nio/ByteBuffer.remaining:()I
      69: newarray       byte
      71: putfield      #2                  // Field row:[B
      74: aload_1
      75: aload_0
      76: getfield      #2                  // Field row:[B
      79: invokevirtual #60                 // Method java/nio/ByteBuffer.get:([B)Ljava/nio/ByteBuffer;
      82: pop
      83: return

  public boolean isCheckExistenceOnly();
    Code:
       0: aload_0
       1: getfield      #9                  // Field checkExistenceOnly:Z
       4: ireturn

  public org.apache.hadoop.hbase.client.Get setCheckExistenceOnly(boolean);
    Code:
       0: aload_0
       1: iload_1
       2: putfield      #9                  // Field checkExistenceOnly:Z
       5: aload_0
       6: areturn

  public org.apache.hadoop.hbase.client.Get addFamily(byte[]);
    Code:
       0: aload_0
       1: getfield      #14                 // Field familyMap:Ljava/util/Map;
       4: aload_1
       5: invokeinterface #61,  2           // InterfaceMethod java/util/Map.remove:(Ljava/lang/Object;)Ljava/lang/Object;
      10: pop
      11: aload_0
      12: getfield      #14                 // Field familyMap:Ljava/util/Map;
      15: aload_1
      16: aconst_null
      17: invokeinterface #62,  3           // InterfaceMethod java/util/Map.put:(Ljava/lang/Object;Ljava/lang/Object;)Ljava/lang/Object;
      22: pop
      23: aload_0
      24: areturn

  public org.apache.hadoop.hbase.client.Get addColumn(byte[], byte[]);
    Code:
       0: aload_0
       1: getfield      #14                 // Field familyMap:Ljava/util/Map;
       4: aload_1
       5: invokeinterface #63,  2           // InterfaceMethod java/util/Map.get:(Ljava/lang/Object;)Ljava/lang/Object;
      10: checkcast     #41                 // class java/util/NavigableSet
      13: astore_3
      14: aload_3
      15: ifnonnull     41
      18: new           #64                 // class java/util/TreeSet
      21: dup
      22: getstatic     #12                 // Field org/apache/hadoop/hbase/util/Bytes.BYTES_COMPARATOR:Ljava/util/Comparator;
      25: invokespecial #65                 // Method java/util/TreeSet."<init>":(Ljava/util/Comparator;)V
      28: astore_3
      29: aload_0
      30: getfield      #14                 // Field familyMap:Ljava/util/Map;
      33: aload_1
      34: aload_3
      35: invokeinterface #62,  3           // InterfaceMethod java/util/Map.put:(Ljava/lang/Object;Ljava/lang/Object;)Ljava/lang/Object;
      40: pop
      41: aload_2
      42: ifnonnull     49
      45: getstatic     #66                 // Field org/apache/hadoop/hbase/HConstants.EMPTY_BYTE_ARRAY:[B
      48: astore_2
      49: aload_3
      50: aload_2
      51: invokeinterface #67,  2           // InterfaceMethod java/util/NavigableSet.add:(Ljava/lang/Object;)Z
      56: pop
      57: aload_0
      58: areturn

  public org.apache.hadoop.hbase.client.Get setTimeRange(long, long) throws java.io.IOException;
    Code:
       0: aload_0
       1: new           #50                 // class org/apache/hadoop/hbase/io/TimeRange
       4: dup
       5: lload_1
       6: lload_3
       7: invokespecial #68                 // Method org/apache/hadoop/hbase/io/TimeRange."<init>":(JJ)V
      10: putfield      #8                  // Field tr:Lorg/apache/hadoop/hbase/io/TimeRange;
      13: aload_0
      14: areturn

  public org.apache.hadoop.hbase.client.Get setTimestamp(long);
    Code:
       0: aload_0
       1: new           #50                 // class org/apache/hadoop/hbase/io/TimeRange
       4: dup
       5: lload_1
       6: lload_1
       7: lconst_1
       8: ladd
       9: invokespecial #68                 // Method org/apache/hadoop/hbase/io/TimeRange."<init>":(JJ)V
      12: putfield      #8                  // Field tr:Lorg/apache/hadoop/hbase/io/TimeRange;
      15: goto          32
      18: astore_3
      19: getstatic     #70                 // Field LOG:Lorg/slf4j/Logger;
      22: ldc           #71                 // String TimeRange failed, likely caused by integer overflow.
      24: aload_3
      25: invokeinterface #72,  3           // InterfaceMethod org/slf4j/Logger.error:(Ljava/lang/String;Ljava/lang/Throwable;)V
      30: aload_3
      31: athrow
      32: aload_0
      33: areturn
    Exception table:
       from    to  target type
           0    15    18   Class java/lang/Exception

  public org.apache.hadoop.hbase.client.Get setColumnFamilyTimeRange(byte[], long, long);
    Code:
       0: aload_0
       1: aload_1
       2: lload_2
       3: lload         4
       5: invokespecial #73                 // Method org/apache/hadoop/hbase/client/Query.setColumnFamilyTimeRange:([BJJ)Lorg/apache/hadoop/hbase/client/Query;
       8: checkcast     #74                 // class org/apache/hadoop/hbase/client/Get
      11: areturn

  public org.apache.hadoop.hbase.client.Get readAllVersions();
    Code:
       0: aload_0
       1: ldc           #76                 // int 2147483647
       3: putfield      #3                  // Field maxVersions:I
       6: aload_0
       7: areturn

  public org.apache.hadoop.hbase.client.Get readVersions(int) throws java.io.IOException;
    Code:
       0: iload_1
       1: ifgt          14
       4: new           #77                 // class java/io/IOException
       7: dup
       8: ldc           #78                 // String versions must be positive
      10: invokespecial #79                 // Method java/io/IOException."<init>":(Ljava/lang/String;)V
      13: athrow
      14: aload_0
      15: iload_1
      16: putfield      #3                  // Field maxVersions:I
      19: aload_0
      20: areturn

  public org.apache.hadoop.hbase.client.Get setLoadColumnFamiliesOnDemand(boolean);
    Code:
       0: aload_0
       1: iload_1
       2: invokespecial #80                 // Method org/apache/hadoop/hbase/client/Query.setLoadColumnFamiliesOnDemand:(Z)Lorg/apache/hadoop/hbase/client/Query;
       5: checkcast     #74                 // class org/apache/hadoop/hbase/client/Get
       8: areturn

  public org.apache.hadoop.hbase.client.Get setMaxResultsPerColumnFamily(int);
    Code:
       0: aload_0
       1: iload_1
       2: putfield      #5                  // Field storeLimit:I
       5: aload_0
       6: areturn

  public org.apache.hadoop.hbase.client.Get setRowOffsetPerColumnFamily(int);
    Code:
       0: aload_0
       1: iload_1
       2: putfield      #6                  // Field storeOffset:I
       5: aload_0
       6: areturn

  public org.apache.hadoop.hbase.client.Get setFilter(org.apache.hadoop.hbase.filter.Filter);
    Code:
       0: aload_0
       1: aload_1
       2: invokespecial #81                 // Method org/apache/hadoop/hbase/client/Query.setFilter:(Lorg/apache/hadoop/hbase/filter/Filter;)Lorg/apache/hadoop/hbase/client/Query;
       5: pop
       6: aload_0
       7: areturn

  public org.apache.hadoop.hbase.client.Get setCacheBlocks(boolean);
    Code:
       0: aload_0
       1: iload_1
       2: putfield      #4                  // Field cacheBlocks:Z
       5: aload_0
       6: areturn

  public boolean getCacheBlocks();
    Code:
       0: aload_0
       1: getfield      #4                  // Field cacheBlocks:Z
       4: ireturn

  public byte[] getRow();
    Code:
       0: aload_0
       1: getfield      #2                  // Field row:[B
       4: areturn

  public int getMaxVersions();
    Code:
       0: aload_0
       1: getfield      #3                  // Field maxVersions:I
       4: ireturn

  public int getMaxResultsPerColumnFamily();
    Code:
       0: aload_0
       1: getfield      #5                  // Field storeLimit:I
       4: ireturn

  public int getRowOffsetPerColumnFamily();
    Code:
       0: aload_0
       1: getfield      #6                  // Field storeOffset:I
       4: ireturn

  public org.apache.hadoop.hbase.io.TimeRange getTimeRange();
    Code:
       0: aload_0
       1: getfield      #8                  // Field tr:Lorg/apache/hadoop/hbase/io/TimeRange;
       4: areturn

  public java.util.Set<byte[]> familySet();
    Code:
       0: aload_0
       1: getfield      #14                 // Field familyMap:Ljava/util/Map;
       4: invokeinterface #82,  1           // InterfaceMethod java/util/Map.keySet:()Ljava/util/Set;
       9: areturn

  public int numFamilies();
    Code:
       0: aload_0
       1: getfield      #14                 // Field familyMap:Ljava/util/Map;
       4: invokeinterface #83,  1           // InterfaceMethod java/util/Map.size:()I
       9: ireturn

  public boolean hasFamilies();
    Code:
       0: aload_0
       1: getfield      #14                 // Field familyMap:Ljava/util/Map;
       4: invokeinterface #84,  1           // InterfaceMethod java/util/Map.isEmpty:()Z
       9: ifne          16
      12: iconst_1
      13: goto          17
      16: iconst_0
      17: ireturn

  public java.util.Map<byte[], java.util.NavigableSet<byte[]>> getFamilyMap();
    Code:
       0: aload_0
       1: getfield      #14                 // Field familyMap:Ljava/util/Map;
       4: areturn

  public java.util.Map<java.lang.String, java.lang.Object> getFingerprint();
    Code:
       0: new           #85                 // class java/util/HashMap
       3: dup
       4: invokespecial #86                 // Method java/util/HashMap."<init>":()V
       7: astore_1
       8: new           #87                 // class java/util/ArrayList
      11: dup
      12: aload_0
      13: getfield      #14                 // Field familyMap:Ljava/util/Map;
      16: invokeinterface #33,  1           // InterfaceMethod java/util/Map.entrySet:()Ljava/util/Set;
      21: invokeinterface #88,  1           // InterfaceMethod java/util/Set.size:()I
      26: invokespecial #89                 // Method java/util/ArrayList."<init>":(I)V
      29: astore_2
      30: aload_1
      31: ldc           #90                 // String families
      33: aload_2
      34: invokeinterface #62,  3           // InterfaceMethod java/util/Map.put:(Ljava/lang/Object;Ljava/lang/Object;)Ljava/lang/Object;
      39: pop
      40: aload_0
      41: getfield      #14                 // Field familyMap:Ljava/util/Map;
      44: invokeinterface #33,  1           // InterfaceMethod java/util/Map.entrySet:()Ljava/util/Set;
      49: invokeinterface #34,  1           // InterfaceMethod java/util/Set.iterator:()Ljava/util/Iterator;
      54: astore_3
      55: aload_3
      56: invokeinterface #35,  1           // InterfaceMethod java/util/Iterator.hasNext:()Z
      61: ifeq          98
      64: aload_3
      65: invokeinterface #36,  1           // InterfaceMethod java/util/Iterator.next:()Ljava/lang/Object;
      70: checkcast     #37                 // class java/util/Map$Entry
      73: astore        4
      75: aload_2
      76: aload         4
      78: invokeinterface #38,  1           // InterfaceMethod java/util/Map$Entry.getKey:()Ljava/lang/Object;
      83: checkcast     #39                 // class "[B"
      86: invokestatic  #91                 // Method org/apache/hadoop/hbase/util/Bytes.toStringBinary:([B)Ljava/lang/String;
      89: invokeinterface #92,  2           // InterfaceMethod java/util/List.add:(Ljava/lang/Object;)Z
      94: pop
      95: goto          55
      98: aload_1
      99: areturn

  public java.util.Map<java.lang.String, java.lang.Object> toMap(int);
    Code:
       0: aload_0
       1: invokevirtual #93                 // Method getFingerprint:()Ljava/util/Map;
       4: astore_2
       5: new           #85                 // class java/util/HashMap
       8: dup
       9: invokespecial #86                 // Method java/util/HashMap."<init>":()V
      12: astore_3
      13: aload_2
      14: ldc           #90                 // String families
      16: aload_3
      17: invokeinterface #62,  3           // InterfaceMethod java/util/Map.put:(Ljava/lang/Object;Ljava/lang/Object;)Ljava/lang/Object;
      22: pop
      23: aload_2
      24: ldc           #94                 // String row
      26: aload_0
      27: getfield      #2                  // Field row:[B
      30: invokestatic  #91                 // Method org/apache/hadoop/hbase/util/Bytes.toStringBinary:([B)Ljava/lang/String;
      33: invokeinterface #62,  3           // InterfaceMethod java/util/Map.put:(Ljava/lang/Object;Ljava/lang/Object;)Ljava/lang/Object;
      38: pop
      39: aload_2
      40: ldc           #95                 // String maxVersions
      42: aload_0
      43: getfield      #3                  // Field maxVersions:I
      46: invokestatic  #96                 // Method java/lang/Integer.valueOf:(I)Ljava/lang/Integer;
      49: invokeinterface #62,  3           // InterfaceMethod java/util/Map.put:(Ljava/lang/Object;Ljava/lang/Object;)Ljava/lang/Object;
      54: pop
      55: aload_2
      56: ldc           #97                 // String cacheBlocks
      58: aload_0
      59: getfield      #4                  // Field cacheBlocks:Z
      62: invokestatic  #98                 // Method java/lang/Boolean.valueOf:(Z)Ljava/lang/Boolean;
      65: invokeinterface #62,  3           // InterfaceMethod java/util/Map.put:(Ljava/lang/Object;Ljava/lang/Object;)Ljava/lang/Object;
      70: pop
      71: new           #87                 // class java/util/ArrayList
      74: dup
      75: iconst_2
      76: invokespecial #89                 // Method java/util/ArrayList."<init>":(I)V
      79: astore        4
      81: aload         4
      83: aload_0
      84: getfield      #8                  // Field tr:Lorg/apache/hadoop/hbase/io/TimeRange;
      87: invokevirtual #51                 // Method org/apache/hadoop/hbase/io/TimeRange.getMin:()J
      90: invokestatic  #99                 // Method java/lang/Long.valueOf:(J)Ljava/lang/Long;
      93: invokeinterface #92,  2           // InterfaceMethod java/util/List.add:(Ljava/lang/Object;)Z
      98: pop
      99: aload         4
     101: aload_0
     102: getfield      #8                  // Field tr:Lorg/apache/hadoop/hbase/io/TimeRange;
     105: invokevirtual #52                 // Method org/apache/hadoop/hbase/io/TimeRange.getMax:()J
     108: invokestatic  #99                 // Method java/lang/Long.valueOf:(J)Ljava/lang/Long;
     111: invokeinterface #92,  2           // InterfaceMethod java/util/List.add:(Ljava/lang/Object;)Z
     116: pop
     117: aload_2
     118: ldc           #100                // String timeRange
     120: aload         4
     122: invokeinterface #62,  3           // InterfaceMethod java/util/Map.put:(Ljava/lang/Object;Ljava/lang/Object;)Ljava/lang/Object;
     127: pop
     128: iconst_0
     129: istore        5
     131: aload_0
     132: getfield      #14                 // Field familyMap:Ljava/util/Map;
     135: invokeinterface #33,  1           // InterfaceMethod java/util/Map.entrySet:()Ljava/util/Set;
     140: invokeinterface #34,  1           // InterfaceMethod java/util/Set.iterator:()Ljava/util/Iterator;
     145: astore        6
     147: aload         6
     149: invokeinterface #35,  1           // InterfaceMethod java/util/Iterator.hasNext:()Z
     154: ifeq          324
     157: aload         6
     159: invokeinterface #36,  1           // InterfaceMethod java/util/Iterator.next:()Ljava/lang/Object;
     164: checkcast     #37                 // class java/util/Map$Entry
     167: astore        7
     169: new           #87                 // class java/util/ArrayList
     172: dup
     173: invokespecial #101                // Method java/util/ArrayList."<init>":()V
     176: astore        8
     178: aload_3
     179: aload         7
     181: invokeinterface #38,  1           // InterfaceMethod java/util/Map$Entry.getKey:()Ljava/lang/Object;
     186: checkcast     #39                 // class "[B"
     189: invokestatic  #91                 // Method org/apache/hadoop/hbase/util/Bytes.toStringBinary:([B)Ljava/lang/String;
     192: aload         8
     194: invokeinterface #62,  3           // InterfaceMethod java/util/Map.put:(Ljava/lang/Object;Ljava/lang/Object;)Ljava/lang/Object;
     199: pop
     200: aload         7
     202: invokeinterface #40,  1           // InterfaceMethod java/util/Map$Entry.getValue:()Ljava/lang/Object;
     207: ifnonnull     229
     210: iinc          5, 1
     213: iinc          1, -1
     216: aload         8
     218: ldc           #102                // String ALL
     220: invokeinterface #92,  2           // InterfaceMethod java/util/List.add:(Ljava/lang/Object;)Z
     225: pop
     226: goto          321
     229: iload         5
     231: aload         7
     233: invokeinterface #40,  1           // InterfaceMethod java/util/Map$Entry.getValue:()Ljava/lang/Object;
     238: checkcast     #41                 // class java/util/NavigableSet
     241: invokeinterface #42,  1           // InterfaceMethod java/util/NavigableSet.size:()I
     246: iadd
     247: istore        5
     249: iload_1
     250: ifgt          256
     253: goto          147
     256: aload         7
     258: invokeinterface #40,  1           // InterfaceMethod java/util/Map$Entry.getValue:()Ljava/lang/Object;
     263: checkcast     #41                 // class java/util/NavigableSet
     266: invokeinterface #43,  1           // InterfaceMethod java/util/NavigableSet.iterator:()Ljava/util/Iterator;
     271: astore        9
     273: aload         9
     275: invokeinterface #35,  1           // InterfaceMethod java/util/Iterator.hasNext:()Z
     280: ifeq          321
     283: aload         9
     285: invokeinterface #36,  1           // InterfaceMethod java/util/Iterator.next:()Ljava/lang/Object;
     290: checkcast     #39                 // class "[B"
     293: astore        10
     295: iinc          1, -1
     298: iload_1
     299: ifgt          305
     302: goto          273
     305: aload         8
     307: aload         10
     309: invokestatic  #91                 // Method org/apache/hadoop/hbase/util/Bytes.toStringBinary:([B)Ljava/lang/String;
     312: invokeinterface #92,  2           // InterfaceMethod java/util/List.add:(Ljava/lang/Object;)Z
     317: pop
     318: goto          273
     321: goto          147
     324: aload_2
     325: ldc           #103                // String totalColumns
     327: iload         5
     329: invokestatic  #96                 // Method java/lang/Integer.valueOf:(I)Ljava/lang/Integer;
     332: invokeinterface #62,  3           // InterfaceMethod java/util/Map.put:(Ljava/lang/Object;Ljava/lang/Object;)Ljava/lang/Object;
     337: pop
     338: aload_0
     339: getfield      #104                // Field filter:Lorg/apache/hadoop/hbase/filter/Filter;
     342: ifnull        361
     345: aload_2
     346: ldc           #105                // String filter
     348: aload_0
     349: getfield      #104                // Field filter:Lorg/apache/hadoop/hbase/filter/Filter;
     352: invokevirtual #106                // Method java/lang/Object.toString:()Ljava/lang/String;
     355: invokeinterface #62,  3           // InterfaceMethod java/util/Map.put:(Ljava/lang/Object;Ljava/lang/Object;)Ljava/lang/Object;
     360: pop
     361: aload_0
     362: invokevirtual #107                // Method getId:()Ljava/lang/String;
     365: ifnull        381
     368: aload_2
     369: ldc           #108                // String id
     371: aload_0
     372: invokevirtual #107                // Method getId:()Ljava/lang/String;
     375: invokeinterface #62,  3           // InterfaceMethod java/util/Map.put:(Ljava/lang/Object;Ljava/lang/Object;)Ljava/lang/Object;
     380: pop
     381: aload_2
     382: areturn

  public int compareTo(org.apache.hadoop.hbase.client.Row);
    Code:
       0: aload_0
       1: invokevirtual #16                 // Method getRow:()[B
       4: aload_1
       5: invokeinterface #109,  1          // InterfaceMethod org/apache/hadoop/hbase/client/Row.getRow:()[B
      10: invokestatic  #110                // Method org/apache/hadoop/hbase/util/Bytes.compareTo:([B[B)I
      13: ireturn

  public int hashCode();
    Code:
       0: aload_0
       1: invokevirtual #16                 // Method getRow:()[B
       4: invokestatic  #111                // Method org/apache/hadoop/hbase/util/Bytes.hashCode:([B)I
       7: ireturn

  public boolean equals(java.lang.Object);
    Code:
       0: aload_0
       1: aload_1
       2: if_acmpne     7
       5: iconst_1
       6: ireturn
       7: aload_1
       8: ifnull        22
      11: aload_0
      12: invokevirtual #112                // Method java/lang/Object.getClass:()Ljava/lang/Class;
      15: aload_1
      16: invokevirtual #112                // Method java/lang/Object.getClass:()Ljava/lang/Class;
      19: if_acmpeq     24
      22: iconst_0
      23: ireturn
      24: aload_1
      25: checkcast     #113                // class org/apache/hadoop/hbase/client/Row
      28: astore_2
      29: aload_0
      30: aload_2
      31: invokevirtual #114                // Method compareTo:(Lorg/apache/hadoop/hbase/client/Row;)I
      34: ifne          41
      37: iconst_1
      38: goto          42
      41: iconst_0
      42: ireturn

  public org.apache.hadoop.hbase.client.Get setAttribute(java.lang.String, byte[]);
    Code:
       0: aload_0
       1: aload_1
       2: aload_2
       3: invokespecial #115                // Method org/apache/hadoop/hbase/client/Query.setAttribute:(Ljava/lang/String;[B)Lorg/apache/hadoop/hbase/client/OperationWithAttributes;
       6: checkcast     #74                 // class org/apache/hadoop/hbase/client/Get
       9: areturn

  public org.apache.hadoop.hbase.client.Get setId(java.lang.String);
    Code:
       0: aload_0
       1: aload_1
       2: invokespecial #116                // Method org/apache/hadoop/hbase/client/Query.setId:(Ljava/lang/String;)Lorg/apache/hadoop/hbase/client/OperationWithAttributes;
       5: checkcast     #74                 // class org/apache/hadoop/hbase/client/Get
       8: areturn

  public org.apache.hadoop.hbase.client.Get setAuthorizations(org.apache.hadoop.hbase.security.visibility.Authorizations);
    Code:
       0: aload_0
       1: aload_1
       2: invokespecial #117                // Method org/apache/hadoop/hbase/client/Query.setAuthorizations:(Lorg/apache/hadoop/hbase/security/visibility/Authorizations;)Lorg/apache/hadoop/hbase/client/Query;
       5: checkcast     #74                 // class org/apache/hadoop/hbase/client/Get
       8: areturn

  public org.apache.hadoop.hbase.client.Get setACL(java.util.Map<java.lang.String, org.apache.hadoop.hbase.security.access.Permission>);
    Code:
       0: aload_0
       1: aload_1
       2: invokespecial #118                // Method org/apache/hadoop/hbase/client/Query.setACL:(Ljava/util/Map;)Lorg/apache/hadoop/hbase/client/Query;
       5: checkcast     #74                 // class org/apache/hadoop/hbase/client/Get
       8: areturn

  public org.apache.hadoop.hbase.client.Get setACL(java.lang.String, org.apache.hadoop.hbase.security.access.Permission);
    Code:
       0: aload_0
       1: aload_1
       2: aload_2
       3: invokespecial #119                // Method org/apache/hadoop/hbase/client/Query.setACL:(Ljava/lang/String;Lorg/apache/hadoop/hbase/security/access/Permission;)Lorg/apache/hadoop/hbase/client/Query;
       6: checkcast     #74                 // class org/apache/hadoop/hbase/client/Get
       9: areturn

  public org.apache.hadoop.hbase.client.Get setConsistency(org.apache.hadoop.hbase.client.Consistency);
    Code:
       0: aload_0
       1: aload_1
       2: invokespecial #120                // Method org/apache/hadoop/hbase/client/Query.setConsistency:(Lorg/apache/hadoop/hbase/client/Consistency;)Lorg/apache/hadoop/hbase/client/Query;
       5: checkcast     #74                 // class org/apache/hadoop/hbase/client/Get
       8: areturn

  public org.apache.hadoop.hbase.client.Get setReplicaId(int);
    Code:
       0: aload_0
       1: iload_1
       2: invokespecial #121                // Method org/apache/hadoop/hbase/client/Query.setReplicaId:(I)Lorg/apache/hadoop/hbase/client/Query;
       5: checkcast     #74                 // class org/apache/hadoop/hbase/client/Get
       8: areturn

  public org.apache.hadoop.hbase.client.Get setIsolationLevel(org.apache.hadoop.hbase.client.IsolationLevel);
    Code:
       0: aload_0
       1: aload_1
       2: invokespecial #122                // Method org/apache/hadoop/hbase/client/Query.setIsolationLevel:(Lorg/apache/hadoop/hbase/client/IsolationLevel;)Lorg/apache/hadoop/hbase/client/Query;
       5: checkcast     #74                 // class org/apache/hadoop/hbase/client/Get
       8: areturn

  public org.apache.hadoop.hbase.client.Get setPriority(int);
    Code:
       0: aload_0
       1: iload_1
       2: invokespecial #55                 // Method org/apache/hadoop/hbase/client/Query.setPriority:(I)Lorg/apache/hadoop/hbase/client/OperationWithAttributes;
       5: checkcast     #74                 // class org/apache/hadoop/hbase/client/Get
       8: areturn

  public org.apache.hadoop.hbase.client.Query setColumnFamilyTimeRange(byte[], long, long);
    Code:
       0: aload_0
       1: aload_1
       2: lload_2
       3: lload         4
       5: invokevirtual #53                 // Method setColumnFamilyTimeRange:([BJJ)Lorg/apache/hadoop/hbase/client/Get;
       8: areturn

  public org.apache.hadoop.hbase.client.Query setLoadColumnFamiliesOnDemand(boolean);
    Code:
       0: aload_0
       1: iload_1
       2: invokevirtual #123                // Method setLoadColumnFamiliesOnDemand:(Z)Lorg/apache/hadoop/hbase/client/Get;
       5: areturn

  public org.apache.hadoop.hbase.client.Query setIsolationLevel(org.apache.hadoop.hbase.client.IsolationLevel);
    Code:
       0: aload_0
       1: aload_1
       2: invokevirtual #124                // Method setIsolationLevel:(Lorg/apache/hadoop/hbase/client/IsolationLevel;)Lorg/apache/hadoop/hbase/client/Get;
       5: areturn

  public org.apache.hadoop.hbase.client.Query setReplicaId(int);
    Code:
       0: aload_0
       1: iload_1
       2: invokevirtual #21                 // Method setReplicaId:(I)Lorg/apache/hadoop/hbase/client/Get;
       5: areturn

  public org.apache.hadoop.hbase.client.Query setConsistency(org.apache.hadoop.hbase.client.Consistency);
    Code:
       0: aload_0
       1: aload_1
       2: invokevirtual #23                 // Method setConsistency:(Lorg/apache/hadoop/hbase/client/Consistency;)Lorg/apache/hadoop/hbase/client/Get;
       5: areturn

  public org.apache.hadoop.hbase.client.Query setACL(java.util.Map);
    Code:
       0: aload_0
       1: aload_1
       2: invokevirtual #125                // Method setACL:(Ljava/util/Map;)Lorg/apache/hadoop/hbase/client/Get;
       5: areturn

  public org.apache.hadoop.hbase.client.Query setACL(java.lang.String, org.apache.hadoop.hbase.security.access.Permission);
    Code:
       0: aload_0
       1: aload_1
       2: aload_2
       3: invokevirtual #126                // Method setACL:(Ljava/lang/String;Lorg/apache/hadoop/hbase/security/access/Permission;)Lorg/apache/hadoop/hbase/client/Get;
       6: areturn

  public org.apache.hadoop.hbase.client.Query setAuthorizations(org.apache.hadoop.hbase.security.visibility.Authorizations);
    Code:
       0: aload_0
       1: aload_1
       2: invokevirtual #127                // Method setAuthorizations:(Lorg/apache/hadoop/hbase/security/visibility/Authorizations;)Lorg/apache/hadoop/hbase/client/Get;
       5: areturn

  public org.apache.hadoop.hbase.client.Query setFilter(org.apache.hadoop.hbase.filter.Filter);
    Code:
       0: aload_0
       1: aload_1
       2: invokevirtual #19                 // Method setFilter:(Lorg/apache/hadoop/hbase/filter/Filter;)Lorg/apache/hadoop/hbase/client/Get;
       5: areturn

  public org.apache.hadoop.hbase.client.OperationWithAttributes setPriority(int);
    Code:
       0: aload_0
       1: iload_1
       2: invokevirtual #128                // Method setPriority:(I)Lorg/apache/hadoop/hbase/client/Get;
       5: areturn

  public org.apache.hadoop.hbase.client.OperationWithAttributes setId(java.lang.String);
    Code:
       0: aload_0
       1: aload_1
       2: invokevirtual #129                // Method setId:(Ljava/lang/String;)Lorg/apache/hadoop/hbase/client/Get;
       5: areturn

  public org.apache.hadoop.hbase.client.OperationWithAttributes setAttribute(java.lang.String, byte[]);
    Code:
       0: aload_0
       1: aload_1
       2: aload_2
       3: invokevirtual #48                 // Method setAttribute:(Ljava/lang/String;[B)Lorg/apache/hadoop/hbase/client/Get;
       6: areturn

  public org.apache.hadoop.hbase.client.Attributes setAttribute(java.lang.String, byte[]);
    Code:
       0: aload_0
       1: aload_1
       2: aload_2
       3: invokevirtual #48                 // Method setAttribute:(Ljava/lang/String;[B)Lorg/apache/hadoop/hbase/client/Get;
       6: areturn

  public int compareTo(java.lang.Object);
    Code:
       0: aload_0
       1: aload_1
       2: checkcast     #113                // class org/apache/hadoop/hbase/client/Row
       5: invokevirtual #114                // Method compareTo:(Lorg/apache/hadoop/hbase/client/Row;)I
       8: ireturn

  static {};
    Code:
       0: ldc           #74                 // class org/apache/hadoop/hbase/client/Get
       2: invokestatic  #130                // Method org/slf4j/LoggerFactory.getLogger:(Ljava/lang/Class;)Lorg/slf4j/Logger;
       5: putstatic     #70                 // Field LOG:Lorg/slf4j/Logger;
       8: return
}
