Compiled from "GetUserPermissionsRequest.java"
public final class org.apache.hadoop.hbase.security.access.GetUserPermissionsRequest {
  public static org.apache.hadoop.hbase.security.access.GetUserPermissionsRequest$Builder newBuilder();
    Code:
       0: new           #8                  // class org/apache/hadoop/hbase/security/access/GetUserPermissionsRequest$Builder
       3: dup
       4: aconst_null
       5: invokespecial #9                  // Method org/apache/hadoop/hbase/security/access/GetUserPermissionsRequest$Builder."<init>":(Lorg/apache/hadoop/hbase/security/access/GetUserPermissionsRequest$1;)V
       8: areturn

  public static org.apache.hadoop.hbase.security.access.GetUserPermissionsRequest$Builder newBuilder(java.lang.String);
    Code:
       0: new           #8                  // class org/apache/hadoop/hbase/security/access/GetUserPermissionsRequest$Builder
       3: dup
       4: aload_0
       5: aconst_null
       6: invokespecial #10                 // Method org/apache/hadoop/hbase/security/access/GetUserPermissionsRequest$Builder."<init>":(Ljava/lang/String;Lorg/apache/hadoop/hbase/security/access/GetUserPermissionsRequest$1;)V
       9: areturn

  public static org.apache.hadoop.hbase.security.access.GetUserPermissionsRequest$Builder newBuilder(org.apache.hadoop.hbase.TableName);
    Code:
       0: new           #8                  // class org/apache/hadoop/hbase/security/access/GetUserPermissionsRequest$Builder
       3: dup
       4: aload_0
       5: aconst_null
       6: invokespecial #11                 // Method org/apache/hadoop/hbase/security/access/GetUserPermissionsRequest$Builder."<init>":(Lorg/apache/hadoop/hbase/TableName;Lorg/apache/hadoop/hbase/security/access/GetUserPermissionsRequest$1;)V
       9: areturn

  public java.lang.String getUserName();
    Code:
       0: aload_0
       1: getfield      #3                  // Field userName:Ljava/lang/String;
       4: areturn

  public java.lang.String getNamespace();
    Code:
       0: aload_0
       1: getfield      #4                  // Field namespace:Ljava/lang/String;
       4: areturn

  public org.apache.hadoop.hbase.TableName getTableName();
    Code:
       0: aload_0
       1: getfield      #5                  // Field tableName:Lorg/apache/hadoop/hbase/TableName;
       4: areturn

  public byte[] getFamily();
    Code:
       0: aload_0
       1: getfield      #6                  // Field family:[B
       4: areturn

  public byte[] getQualifier();
    Code:
       0: aload_0
       1: getfield      #7                  // Field qualifier:[B
       4: areturn

  org.apache.hadoop.hbase.security.access.GetUserPermissionsRequest(java.lang.String, java.lang.String, org.apache.hadoop.hbase.TableName, byte[], byte[], org.apache.hadoop.hbase.security.access.GetUserPermissionsRequest$1);
    Code:
       0: aload_0
       1: aload_1
       2: aload_2
       3: aload_3
       4: aload         4
       6: aload         5
       8: invokespecial #1                  // Method "<init>":(Ljava/lang/String;Ljava/lang/String;Lorg/apache/hadoop/hbase/TableName;[B[B)V
      11: return
}
