Compiled from "GlobalMetricRegistriesAdapter.java"
class org.apache.hadoop.hbase.metrics.impl.GlobalMetricRegistriesAdapter$MetricsSourceAdapter implements org.apache.hadoop.metrics2.MetricsSource {
  final org.apache.hadoop.hbase.metrics.impl.GlobalMetricRegistriesAdapter this$0;

  org.apache.hadoop.hbase.metrics.impl.GlobalMetricRegistriesAdapter$MetricsSourceAdapter(org.apache.hadoop.hbase.metrics.impl.GlobalMetricRegistriesAdapter, org.apache.hadoop.hbase.metrics.MetricRegistry);
    Code:
       0: aload_0
       1: aload_1
       2: putfield      #1                  // Field this$0:Lorg/apache/hadoop/hbase/metrics/impl/GlobalMetricRegistriesAdapter;
       5: aload_0
       6: invokespecial #2                  // Method java/lang/Object."<init>":()V
       9: aload_0
      10: aload_2
      11: putfield      #3                  // Field registry:Lorg/apache/hadoop/hbase/metrics/MetricRegistry;
      14: return

  public void getMetrics(org.apache.hadoop.metrics2.MetricsCollector, boolean);
    Code:
       0: aload_0
       1: getfield      #1                  // Field this$0:Lorg/apache/hadoop/hbase/metrics/impl/GlobalMetricRegistriesAdapter;
       4: invokestatic  #4                  // Method org/apache/hadoop/hbase/metrics/impl/GlobalMetricRegistriesAdapter.access$000:(Lorg/apache/hadoop/hbase/metrics/impl/GlobalMetricRegistriesAdapter;)Lorg/apache/hadoop/hbase/metrics/impl/HBaseMetrics2HadoopMetricsAdapter;
       7: aload_0
       8: getfield      #3                  // Field registry:Lorg/apache/hadoop/hbase/metrics/MetricRegistry;
      11: aload_1
      12: invokevirtual #5                  // Method org/apache/hadoop/hbase/metrics/impl/HBaseMetrics2HadoopMetricsAdapter.snapshotAllMetrics:(Lorg/apache/hadoop/hbase/metrics/MetricRegistry;Lorg/apache/hadoop/metrics2/MetricsCollector;)V
      15: return
}
