Compiled from "GsonUtil.java"
final class org.apache.hadoop.hbase.util.GsonUtil$1 extends org.apache.hbase.thirdparty.com.google.gson.TypeAdapter<java.util.concurrent.atomic.LongAdder> {
  org.apache.hadoop.hbase.util.GsonUtil$1();
    Code:
       0: aload_0
       1: invokespecial #1                  // Method org/apache/hbase/thirdparty/com/google/gson/TypeAdapter."<init>":()V
       4: return

  public void write(org.apache.hbase.thirdparty.com.google.gson.stream.JsonWriter, java.util.concurrent.atomic.LongAdder) throws java.io.IOException;
    Code:
       0: aload_1
       1: aload_2
       2: invokevirtual #2                  // Method java/util/concurrent/atomic/LongAdder.longValue:()J
       5: invokevirtual #3                  // Method org/apache/hbase/thirdparty/com/google/gson/stream/JsonWriter.value:(J)Lorg/apache/hbase/thirdparty/com/google/gson/stream/JsonWriter;
       8: pop
       9: return

  public java.util.concurrent.atomic.LongAdder read(org.apache.hbase.thirdparty.com.google.gson.stream.JsonReader) throws java.io.IOException;
    Code:
       0: new           #4                  // class java/util/concurrent/atomic/LongAdder
       3: dup
       4: invokespecial #5                  // Method java/util/concurrent/atomic/LongAdder."<init>":()V
       7: astore_2
       8: aload_2
       9: aload_1
      10: invokevirtual #6                  // Method org/apache/hbase/thirdparty/com/google/gson/stream/JsonReader.nextLong:()J
      13: invokevirtual #7                  // Method java/util/concurrent/atomic/LongAdder.add:(J)V
      16: aload_2
      17: areturn

  public java.lang.Object read(org.apache.hbase.thirdparty.com.google.gson.stream.JsonReader) throws java.io.IOException;
    Code:
       0: aload_0
       1: aload_1
       2: invokevirtual #8                  // Method read:(Lorg/apache/hbase/thirdparty/com/google/gson/stream/JsonReader;)Ljava/util/concurrent/atomic/LongAdder;
       5: areturn

  public void write(org.apache.hbase.thirdparty.com.google.gson.stream.JsonWriter, java.lang.Object) throws java.io.IOException;
    Code:
       0: aload_0
       1: aload_1
       2: aload_2
       3: checkcast     #4                  // class java/util/concurrent/atomic/LongAdder
       6: invokevirtual #9                  // Method write:(Lorg/apache/hbase/thirdparty/com/google/gson/stream/JsonWriter;Ljava/util/concurrent/atomic/LongAdder;)V
       9: return
}
