Compiled from "GsonUtil.java"
public final class org.apache.hadoop.hbase.util.GsonUtil {
  public static org.apache.hbase.thirdparty.com.google.gson.GsonBuilder createGson();
    Code:
       0: new           #2                  // class org/apache/hbase/thirdparty/com/google/gson/GsonBuilder
       3: dup
       4: invokespecial #3                  // Method org/apache/hbase/thirdparty/com/google/gson/GsonBuilder."<init>":()V
       7: getstatic     #4                  // Field org/apache/hbase/thirdparty/com/google/gson/LongSerializationPolicy.STRING:Lorg/apache/hbase/thirdparty/com/google/gson/LongSerializationPolicy;
      10: invokevirtual #5                  // Method org/apache/hbase/thirdparty/com/google/gson/GsonBuilder.setLongSerializationPolicy:(Lorg/apache/hbase/thirdparty/com/google/gson/LongSerializationPolicy;)Lorg/apache/hbase/thirdparty/com/google/gson/GsonBuilder;
      13: ldc           #6                  // class java/util/concurrent/atomic/LongAdder
      15: new           #7                  // class org/apache/hadoop/hbase/util/GsonUtil$1
      18: dup
      19: invokespecial #8                  // Method org/apache/hadoop/hbase/util/GsonUtil$1."<init>":()V
      22: invokevirtual #9                  // Method org/apache/hbase/thirdparty/com/google/gson/GsonBuilder.registerTypeAdapter:(Ljava/lang/reflect/Type;Ljava/lang/Object;)Lorg/apache/hbase/thirdparty/com/google/gson/GsonBuilder;
      25: areturn
}
