Compiled from "Hash.java"
public abstract class org.apache.hadoop.hbase.util.Hash {
  public static final int INVALID_HASH;

  public static final int JENKINS_HASH;

  public static final int MURMUR_HASH;

  public static final int MURMUR_HASH3;

  public org.apache.hadoop.hbase.util.Hash();
    Code:
       0: aload_0
       1: invokespecial #1                  // Method java/lang/Object."<init>":()V
       4: return

  public static int parseHashType(java.lang.String);
    Code:
       0: ldc           #2                  // String jenkins
       2: aload_0
       3: invokevirtual #3                  // Method java/lang/String.equalsIgnoreCase:(Ljava/lang/String;)Z
       6: ifeq          11
       9: iconst_0
      10: ireturn
      11: ldc           #5                  // String murmur
      13: aload_0
      14: invokevirtual #3                  // Method java/lang/String.equalsIgnoreCase:(Ljava/lang/String;)Z
      17: ifeq          22
      20: iconst_1
      21: ireturn
      22: ldc           #6                  // String murmur3
      24: aload_0
      25: invokevirtual #3                  // Method java/lang/String.equalsIgnoreCase:(Ljava/lang/String;)Z
      28: ifeq          33
      31: iconst_2
      32: ireturn
      33: iconst_m1
      34: ireturn

  public static int getHashType(org.apache.hadoop.conf.Configuration);
    Code:
       0: aload_0
       1: ldc           #7                  // String hbase.hash.type
       3: ldc           #5                  // String murmur
       5: invokevirtual #8                  // Method org/apache/hadoop/conf/Configuration.get:(Ljava/lang/String;Ljava/lang/String;)Ljava/lang/String;
       8: astore_1
       9: aload_1
      10: invokestatic  #9                  // Method parseHashType:(Ljava/lang/String;)I
      13: ireturn

  public static org.apache.hadoop.hbase.util.Hash getInstance(int);
    Code:
       0: iload_0
       1: tableswitch   { // 0 to 2
                     0: 28
                     1: 32
                     2: 36
               default: 40
          }
      28: invokestatic  #10                 // Method org/apache/hadoop/hbase/util/JenkinsHash.getInstance:()Lorg/apache/hadoop/hbase/util/Hash;
      31: areturn
      32: invokestatic  #11                 // Method org/apache/hadoop/hbase/util/MurmurHash.getInstance:()Lorg/apache/hadoop/hbase/util/Hash;
      35: areturn
      36: invokestatic  #12                 // Method org/apache/hadoop/hbase/util/MurmurHash3.getInstance:()Lorg/apache/hadoop/hbase/util/Hash;
      39: areturn
      40: aconst_null
      41: areturn

  public static org.apache.hadoop.hbase.util.Hash getInstance(org.apache.hadoop.conf.Configuration);
    Code:
       0: aload_0
       1: invokestatic  #13                 // Method getHashType:(Lorg/apache/hadoop/conf/Configuration;)I
       4: istore_1
       5: iload_1
       6: invokestatic  #14                 // Method getInstance:(I)Lorg/apache/hadoop/hbase/util/Hash;
       9: areturn

  public abstract <T> int hash(org.apache.hadoop.hbase.util.HashKey<T>, int);
}
