Compiled from "HBaseAdmin.java"
class org.apache.hadoop.hbase.client.HBaseAdmin$87 extends org.apache.hadoop.hbase.client.MasterCallable<java.util.List<org.apache.hadoop.hbase.replication.ReplicationPeerDescription>> {
  final java.util.regex.Pattern val$pattern;

  final org.apache.hadoop.hbase.client.HBaseAdmin this$0;

  org.apache.hadoop.hbase.client.HBaseAdmin$87(org.apache.hadoop.hbase.client.HBaseAdmin, org.apache.hadoop.hbase.client.Connection, org.apache.hadoop.hbase.ipc.RpcControllerFactory, java.util.regex.Pattern);
    Code:
       0: aload_0
       1: aload_1
       2: putfield      #1                  // Field this$0:Lorg/apache/hadoop/hbase/client/HBaseAdmin;
       5: aload_0
       6: aload         4
       8: putfield      #2                  // Field val$pattern:Ljava/util/regex/Pattern;
      11: aload_0
      12: aload_2
      13: aload_3
      14: invokespecial #3                  // Method org/apache/hadoop/hbase/client/MasterCallable."<init>":(Lorg/apache/hadoop/hbase/client/Connection;Lorg/apache/hadoop/hbase/ipc/RpcControllerFactory;)V
      17: return

  protected java.util.List<org.apache.hadoop.hbase.replication.ReplicationPeerDescription> rpcCall() throws java.lang.Exception;
    Code:
       0: aload_0
       1: getfield      #4                  // Field master:Lorg/apache/hadoop/hbase/client/MasterKeepAliveConnection;
       4: aload_0
       5: invokevirtual #5                  // Method getRpcController:()Lorg/apache/hadoop/hbase/ipc/HBaseRpcController;
       8: aload_0
       9: getfield      #2                  // Field val$pattern:Ljava/util/regex/Pattern;
      12: invokestatic  #6                  // Method org/apache/hadoop/hbase/shaded/protobuf/RequestConverter.buildListReplicationPeersRequest:(Ljava/util/regex/Pattern;)Lorg/apache/hadoop/hbase/shaded/protobuf/generated/ReplicationProtos$ListReplicationPeersRequest;
      15: invokeinterface #7,  3            // InterfaceMethod org/apache/hadoop/hbase/client/MasterKeepAliveConnection.listReplicationPeers:(Lorg/apache/hbase/thirdparty/com/google/protobuf/RpcController;Lorg/apache/hadoop/hbase/shaded/protobuf/generated/ReplicationProtos$ListReplicationPeersRequest;)Lorg/apache/hadoop/hbase/shaded/protobuf/generated/ReplicationProtos$ListReplicationPeersResponse;
      20: invokevirtual #8                  // Method org/apache/hadoop/hbase/shaded/protobuf/generated/ReplicationProtos$ListReplicationPeersResponse.getPeerDescList:()Ljava/util/List;
      23: astore_1
      24: new           #9                  // class java/util/ArrayList
      27: dup
      28: aload_1
      29: invokeinterface #10,  1           // InterfaceMethod java/util/List.size:()I
      34: invokespecial #11                 // Method java/util/ArrayList."<init>":(I)V
      37: astore_2
      38: aload_1
      39: invokeinterface #12,  1           // InterfaceMethod java/util/List.iterator:()Ljava/util/Iterator;
      44: astore_3
      45: aload_3
      46: invokeinterface #13,  1           // InterfaceMethod java/util/Iterator.hasNext:()Z
      51: ifeq          80
      54: aload_3
      55: invokeinterface #14,  1           // InterfaceMethod java/util/Iterator.next:()Ljava/lang/Object;
      60: checkcast     #15                 // class org/apache/hadoop/hbase/shaded/protobuf/generated/ReplicationProtos$ReplicationPeerDescription
      63: astore        4
      65: aload_2
      66: aload         4
      68: invokestatic  #16                 // Method org/apache/hadoop/hbase/client/replication/ReplicationPeerConfigUtil.toReplicationPeerDescription:(Lorg/apache/hadoop/hbase/shaded/protobuf/generated/ReplicationProtos$ReplicationPeerDescription;)Lorg/apache/hadoop/hbase/replication/ReplicationPeerDescription;
      71: invokeinterface #17,  2           // InterfaceMethod java/util/List.add:(Ljava/lang/Object;)Z
      76: pop
      77: goto          45
      80: aload_2
      81: areturn

  protected java.lang.Object rpcCall() throws java.lang.Exception;
    Code:
       0: aload_0
       1: invokevirtual #18                 // Method rpcCall:()Ljava/util/List;
       4: areturn
}
