Compiled from "HBaseAdmin.java"
public class org.apache.hadoop.hbase.client.HBaseAdmin$ProcedureFuture<V> implements java.util.concurrent.Future<V> {
  protected final java.lang.Long procId;

  public org.apache.hadoop.hbase.client.HBaseAdmin$ProcedureFuture(org.apache.hadoop.hbase.client.HBaseAdmin, java.lang.Long);
    Code:
       0: aload_0
       1: invokespecial #1                  // Method java/lang/Object."<init>":()V
       4: aload_0
       5: aconst_null
       6: putfield      #2                  // Field exception:Ljava/util/concurrent/ExecutionException;
       9: aload_0
      10: iconst_0
      11: putfield      #3                  // Field procResultFound:Z
      14: aload_0
      15: iconst_0
      16: putfield      #4                  // Field done:Z
      19: aload_0
      20: iconst_0
      21: putfield      #5                  // Field cancelled:Z
      24: aload_0
      25: aconst_null
      26: putfield      #6                  // Field result:Ljava/lang/Object;
      29: aload_0
      30: aload_1
      31: putfield      #7                  // Field admin:Lorg/apache/hadoop/hbase/client/HBaseAdmin;
      34: aload_0
      35: aload_2
      36: putfield      #8                  // Field procId:Ljava/lang/Long;
      39: return

  public boolean cancel(boolean);
    Code:
       0: invokestatic  #9                  // Method org/apache/hadoop/hbase/shaded/protobuf/generated/MasterProtos$AbortProcedureRequest.newBuilder:()Lorg/apache/hadoop/hbase/shaded/protobuf/generated/MasterProtos$AbortProcedureRequest$Builder;
       3: aload_0
       4: getfield      #8                  // Field procId:Ljava/lang/Long;
       7: invokevirtual #10                 // Method java/lang/Long.longValue:()J
      10: invokevirtual #11                 // Method org/apache/hadoop/hbase/shaded/protobuf/generated/MasterProtos$AbortProcedureRequest$Builder.setProcId:(J)Lorg/apache/hadoop/hbase/shaded/protobuf/generated/MasterProtos$AbortProcedureRequest$Builder;
      13: iload_1
      14: invokevirtual #12                 // Method org/apache/hadoop/hbase/shaded/protobuf/generated/MasterProtos$AbortProcedureRequest$Builder.setMayInterruptIfRunning:(Z)Lorg/apache/hadoop/hbase/shaded/protobuf/generated/MasterProtos$AbortProcedureRequest$Builder;
      17: invokevirtual #13                 // Method org/apache/hadoop/hbase/shaded/protobuf/generated/MasterProtos$AbortProcedureRequest$Builder.build:()Lorg/apache/hadoop/hbase/shaded/protobuf/generated/MasterProtos$AbortProcedureRequest;
      20: astore_2
      21: aload_0
      22: aload_0
      23: aload_2
      24: invokevirtual #14                 // Method abortProcedureResult:(Lorg/apache/hadoop/hbase/shaded/protobuf/generated/MasterProtos$AbortProcedureRequest;)Lorg/apache/hadoop/hbase/shaded/protobuf/generated/MasterProtos$AbortProcedureResponse;
      27: invokevirtual #15                 // Method org/apache/hadoop/hbase/shaded/protobuf/generated/MasterProtos$AbortProcedureResponse.getIsProcedureAborted:()Z
      30: putfield      #5                  // Field cancelled:Z
      33: aload_0
      34: getfield      #5                  // Field cancelled:Z
      37: ifeq          45
      40: aload_0
      41: iconst_1
      42: putfield      #4                  // Field done:Z
      45: goto          97
      48: astore_3
      49: invokestatic  #17                 // Method org/apache/hadoop/hbase/client/HBaseAdmin.access$200:()Lorg/slf4j/Logger;
      52: new           #18                 // class java/lang/StringBuilder
      55: dup
      56: invokespecial #19                 // Method java/lang/StringBuilder."<init>":()V
      59: ldc           #20                 // String Cancelling the procedure with procId=
      61: invokevirtual #21                 // Method java/lang/StringBuilder.append:(Ljava/lang/String;)Ljava/lang/StringBuilder;
      64: aload_0
      65: getfield      #8                  // Field procId:Ljava/lang/Long;
      68: invokevirtual #22                 // Method java/lang/StringBuilder.append:(Ljava/lang/Object;)Ljava/lang/StringBuilder;
      71: ldc           #23                 // String  throws exception
      73: invokevirtual #21                 // Method java/lang/StringBuilder.append:(Ljava/lang/String;)Ljava/lang/StringBuilder;
      76: aload_3
      77: invokevirtual #24                 // Method java/io/IOException.getMessage:()Ljava/lang/String;
      80: invokevirtual #21                 // Method java/lang/StringBuilder.append:(Ljava/lang/String;)Ljava/lang/StringBuilder;
      83: invokevirtual #25                 // Method java/lang/StringBuilder.toString:()Ljava/lang/String;
      86: aload_3
      87: invokeinterface #26,  3           // InterfaceMethod org/slf4j/Logger.warn:(Ljava/lang/String;Ljava/lang/Throwable;)V
      92: aload_0
      93: iconst_0
      94: putfield      #5                  // Field cancelled:Z
      97: aload_0
      98: getfield      #5                  // Field cancelled:Z
     101: ireturn
    Exception table:
       from    to  target type
          21    45    48   Class java/io/IOException

  public boolean isCancelled();
    Code:
       0: aload_0
       1: getfield      #5                  // Field cancelled:Z
       4: ireturn

  protected org.apache.hadoop.hbase.shaded.protobuf.generated.MasterProtos$AbortProcedureResponse abortProcedureResult(org.apache.hadoop.hbase.shaded.protobuf.generated.MasterProtos$AbortProcedureRequest) throws java.io.IOException;
    Code:
       0: aload_0
       1: getfield      #7                  // Field admin:Lorg/apache/hadoop/hbase/client/HBaseAdmin;
       4: new           #27                 // class org/apache/hadoop/hbase/client/HBaseAdmin$ProcedureFuture$1
       7: dup
       8: aload_0
       9: aload_0
      10: getfield      #7                  // Field admin:Lorg/apache/hadoop/hbase/client/HBaseAdmin;
      13: invokevirtual #28                 // Method org/apache/hadoop/hbase/client/HBaseAdmin.getConnection:()Lorg/apache/hadoop/hbase/client/Connection;
      16: aload_0
      17: getfield      #7                  // Field admin:Lorg/apache/hadoop/hbase/client/HBaseAdmin;
      20: invokestatic  #29                 // Method org/apache/hadoop/hbase/client/HBaseAdmin.access$600:(Lorg/apache/hadoop/hbase/client/HBaseAdmin;)Lorg/apache/hadoop/hbase/ipc/RpcControllerFactory;
      23: aload_1
      24: invokespecial #30                 // Method org/apache/hadoop/hbase/client/HBaseAdmin$ProcedureFuture$1."<init>":(Lorg/apache/hadoop/hbase/client/HBaseAdmin$ProcedureFuture;Lorg/apache/hadoop/hbase/client/Connection;Lorg/apache/hadoop/hbase/ipc/RpcControllerFactory;Lorg/apache/hadoop/hbase/shaded/protobuf/generated/MasterProtos$AbortProcedureRequest;)V
      27: invokestatic  #31                 // Method org/apache/hadoop/hbase/client/HBaseAdmin.access$700:(Lorg/apache/hadoop/hbase/client/HBaseAdmin;Lorg/apache/hadoop/hbase/client/RetryingCallable;)Ljava/lang/Object;
      30: checkcast     #32                 // class org/apache/hadoop/hbase/shaded/protobuf/generated/MasterProtos$AbortProcedureResponse
      33: areturn

  public V get() throws java.lang.InterruptedException, java.util.concurrent.ExecutionException;
    Code:
       0: aload_0
       1: aload_0
       2: getfield      #7                  // Field admin:Lorg/apache/hadoop/hbase/client/HBaseAdmin;
       5: invokestatic  #33                 // Method org/apache/hadoop/hbase/client/HBaseAdmin.access$800:(Lorg/apache/hadoop/hbase/client/HBaseAdmin;)I
       8: i2l
       9: getstatic     #34                 // Field java/util/concurrent/TimeUnit.MILLISECONDS:Ljava/util/concurrent/TimeUnit;
      12: invokevirtual #35                 // Method get:(JLjava/util/concurrent/TimeUnit;)Ljava/lang/Object;
      15: areturn
      16: astore_1
      17: invokestatic  #17                 // Method org/apache/hadoop/hbase/client/HBaseAdmin.access$200:()Lorg/slf4j/Logger;
      20: new           #18                 // class java/lang/StringBuilder
      23: dup
      24: invokespecial #19                 // Method java/lang/StringBuilder."<init>":()V
      27: ldc           #37                 // String Failed to get the procedure with procId=
      29: invokevirtual #21                 // Method java/lang/StringBuilder.append:(Ljava/lang/String;)Ljava/lang/StringBuilder;
      32: aload_0
      33: getfield      #8                  // Field procId:Ljava/lang/Long;
      36: invokevirtual #22                 // Method java/lang/StringBuilder.append:(Ljava/lang/Object;)Ljava/lang/StringBuilder;
      39: ldc           #23                 // String  throws exception
      41: invokevirtual #21                 // Method java/lang/StringBuilder.append:(Ljava/lang/String;)Ljava/lang/StringBuilder;
      44: aload_1
      45: invokevirtual #38                 // Method java/util/concurrent/TimeoutException.getMessage:()Ljava/lang/String;
      48: invokevirtual #21                 // Method java/lang/StringBuilder.append:(Ljava/lang/String;)Ljava/lang/StringBuilder;
      51: invokevirtual #25                 // Method java/lang/StringBuilder.toString:()Ljava/lang/String;
      54: aload_1
      55: invokeinterface #26,  3           // InterfaceMethod org/slf4j/Logger.warn:(Ljava/lang/String;Ljava/lang/Throwable;)V
      60: aconst_null
      61: areturn
    Exception table:
       from    to  target type
           0    15    16   Class java/util/concurrent/TimeoutException

  public V get(long, java.util.concurrent.TimeUnit) throws java.lang.InterruptedException, java.util.concurrent.ExecutionException, java.util.concurrent.TimeoutException;
    Code:
       0: aload_0
       1: getfield      #4                  // Field done:Z
       4: ifne          123
       7: invokestatic  #39                 // Method org/apache/hadoop/hbase/util/EnvironmentEdgeManager.currentTime:()J
      10: aload_3
      11: lload_1
      12: invokevirtual #40                 // Method java/util/concurrent/TimeUnit.toMillis:(J)J
      15: ladd
      16: lstore        4
      18: aload_0
      19: getfield      #8                  // Field procId:Ljava/lang/Long;
      22: ifnull        42
      25: aload_0
      26: aload_0
      27: aload_0
      28: getfield      #8                  // Field procId:Ljava/lang/Long;
      31: invokevirtual #10                 // Method java/lang/Long.longValue:()J
      34: lload         4
      36: invokespecial #41                 // Method waitProcedureResult:(JJ)Ljava/lang/Object;
      39: putfield      #6                  // Field result:Ljava/lang/Object;
      42: aload_0
      43: getfield      #3                  // Field procResultFound:Z
      46: ifne          59
      49: aload_0
      50: aload_0
      51: lload         4
      53: invokevirtual #42                 // Method waitOperationResult:(J)Ljava/lang/Object;
      56: putfield      #6                  // Field result:Ljava/lang/Object;
      59: aload_0
      60: aload_0
      61: aload_0
      62: getfield      #6                  // Field result:Ljava/lang/Object;
      65: lload         4
      67: invokevirtual #43                 // Method postOperationResult:(Ljava/lang/Object;J)Ljava/lang/Object;
      70: putfield      #6                  // Field result:Ljava/lang/Object;
      73: aload_0
      74: iconst_1
      75: putfield      #4                  // Field done:Z
      78: goto          100
      81: astore        6
      83: aload_0
      84: aload_0
      85: aload         6
      87: lload         4
      89: invokevirtual #44                 // Method postOperationFailure:(Ljava/io/IOException;J)Ljava/lang/Object;
      92: putfield      #6                  // Field result:Ljava/lang/Object;
      95: aload_0
      96: iconst_1
      97: putfield      #4                  // Field done:Z
     100: goto          123
     103: astore        6
     105: aload_0
     106: new           #45                 // class java/util/concurrent/ExecutionException
     109: dup
     110: aload         6
     112: invokespecial #46                 // Method java/util/concurrent/ExecutionException."<init>":(Ljava/lang/Throwable;)V
     115: putfield      #2                  // Field exception:Ljava/util/concurrent/ExecutionException;
     118: aload_0
     119: iconst_1
     120: putfield      #4                  // Field done:Z
     123: aload_0
     124: getfield      #2                  // Field exception:Ljava/util/concurrent/ExecutionException;
     127: ifnull        135
     130: aload_0
     131: getfield      #2                  // Field exception:Ljava/util/concurrent/ExecutionException;
     134: athrow
     135: aload_0
     136: getfield      #6                  // Field result:Ljava/lang/Object;
     139: areturn
    Exception table:
       from    to  target type
          18    78    81   Class java/io/IOException
          18   100   103   Class java/io/IOException

  public boolean isDone();
    Code:
       0: aload_0
       1: getfield      #4                  // Field done:Z
       4: ireturn

  protected org.apache.hadoop.hbase.client.HBaseAdmin getAdmin();
    Code:
       0: aload_0
       1: getfield      #7                  // Field admin:Lorg/apache/hadoop/hbase/client/HBaseAdmin;
       4: areturn

  protected org.apache.hadoop.hbase.shaded.protobuf.generated.MasterProtos$GetProcedureResultResponse getProcedureResult(org.apache.hadoop.hbase.shaded.protobuf.generated.MasterProtos$GetProcedureResultRequest) throws java.io.IOException;
    Code:
       0: aload_0
       1: getfield      #7                  // Field admin:Lorg/apache/hadoop/hbase/client/HBaseAdmin;
       4: new           #71                 // class org/apache/hadoop/hbase/client/HBaseAdmin$ProcedureFuture$2
       7: dup
       8: aload_0
       9: aload_0
      10: getfield      #7                  // Field admin:Lorg/apache/hadoop/hbase/client/HBaseAdmin;
      13: invokevirtual #28                 // Method org/apache/hadoop/hbase/client/HBaseAdmin.getConnection:()Lorg/apache/hadoop/hbase/client/Connection;
      16: aload_0
      17: getfield      #7                  // Field admin:Lorg/apache/hadoop/hbase/client/HBaseAdmin;
      20: invokestatic  #29                 // Method org/apache/hadoop/hbase/client/HBaseAdmin.access$600:(Lorg/apache/hadoop/hbase/client/HBaseAdmin;)Lorg/apache/hadoop/hbase/ipc/RpcControllerFactory;
      23: aload_1
      24: invokespecial #72                 // Method org/apache/hadoop/hbase/client/HBaseAdmin$ProcedureFuture$2."<init>":(Lorg/apache/hadoop/hbase/client/HBaseAdmin$ProcedureFuture;Lorg/apache/hadoop/hbase/client/Connection;Lorg/apache/hadoop/hbase/ipc/RpcControllerFactory;Lorg/apache/hadoop/hbase/shaded/protobuf/generated/MasterProtos$GetProcedureResultRequest;)V
      27: invokestatic  #31                 // Method org/apache/hadoop/hbase/client/HBaseAdmin.access$700:(Lorg/apache/hadoop/hbase/client/HBaseAdmin;Lorg/apache/hadoop/hbase/client/RetryingCallable;)Ljava/lang/Object;
      30: checkcast     #73                 // class org/apache/hadoop/hbase/shaded/protobuf/generated/MasterProtos$GetProcedureResultResponse
      33: areturn

  protected V convertResult(org.apache.hadoop.hbase.shaded.protobuf.generated.MasterProtos$GetProcedureResultResponse) throws java.io.IOException;
    Code:
       0: aload_1
       1: invokevirtual #74                 // Method org/apache/hadoop/hbase/shaded/protobuf/generated/MasterProtos$GetProcedureResultResponse.hasException:()Z
       4: ifeq          15
       7: aload_1
       8: invokevirtual #75                 // Method org/apache/hadoop/hbase/shaded/protobuf/generated/MasterProtos$GetProcedureResultResponse.getException:()Lorg/apache/hadoop/hbase/shaded/protobuf/generated/ErrorHandlingProtos$ForeignExceptionMessage;
      11: invokestatic  #76                 // Method org/apache/hadoop/hbase/util/ForeignExceptionUtil.toIOException:(Lorg/apache/hadoop/hbase/shaded/protobuf/generated/ErrorHandlingProtos$ForeignExceptionMessage;)Ljava/io/IOException;
      14: athrow
      15: aconst_null
      16: areturn

  protected V waitOperationResult(long) throws java.io.IOException, java.util.concurrent.TimeoutException;
    Code:
       0: aconst_null
       1: areturn

  protected V postOperationResult(V, long) throws java.io.IOException, java.util.concurrent.TimeoutException;
    Code:
       0: aload_1
       1: areturn

  protected V postOperationFailure(java.io.IOException, long) throws java.io.IOException, java.util.concurrent.TimeoutException;
    Code:
       0: aload_1
       1: athrow

  protected void waitForState(long, org.apache.hadoop.hbase.client.HBaseAdmin$ProcedureFuture$WaitForStateCallable) throws java.io.IOException, java.util.concurrent.TimeoutException;
    Code:
       0: iconst_0
       1: istore        4
       3: aconst_null
       4: astore        5
       6: invokestatic  #39                 // Method org/apache/hadoop/hbase/util/EnvironmentEdgeManager.currentTime:()J
       9: lstore        6
      11: invokestatic  #39                 // Method org/apache/hadoop/hbase/util/EnvironmentEdgeManager.currentTime:()J
      14: lload_1
      15: lcmp
      16: ifge          72
      19: aconst_null
      20: astore        5
      22: aload_3
      23: iload         4
      25: invokeinterface #77,  2           // InterfaceMethod org/apache/hadoop/hbase/client/HBaseAdmin$ProcedureFuture$WaitForStateCallable.checkState:(I)Z
      30: ifeq          34
      33: return
      34: goto          43
      37: astore        8
      39: aload         8
      41: astore        5
      43: aload_0
      44: invokevirtual #60                 // Method getAdmin:()Lorg/apache/hadoop/hbase/client/HBaseAdmin;
      47: iload         4
      49: iinc          4, 1
      52: invokestatic  #61                 // Method org/apache/hadoop/hbase/client/HBaseAdmin.access$900:(Lorg/apache/hadoop/hbase/client/HBaseAdmin;I)J
      55: invokestatic  #62                 // Method java/lang/Thread.sleep:(J)V
      58: goto          11
      61: astore        8
      63: aload_3
      64: invokeinterface #78,  1           // InterfaceMethod org/apache/hadoop/hbase/client/HBaseAdmin$ProcedureFuture$WaitForStateCallable.throwInterruptedException:()V
      69: goto          11
      72: aload         5
      74: ifnull        83
      77: aload         5
      79: invokestatic  #51                 // Method unwrapException:(Ljava/io/IOException;)Ljava/io/IOException;
      82: athrow
      83: aload_3
      84: invokestatic  #39                 // Method org/apache/hadoop/hbase/util/EnvironmentEdgeManager.currentTime:()J
      87: lload         6
      89: lsub
      90: invokeinterface #79,  3           // InterfaceMethod org/apache/hadoop/hbase/client/HBaseAdmin$ProcedureFuture$WaitForStateCallable.throwTimeoutException:(J)V
      95: return
    Exception table:
       from    to  target type
          22    33    37   Class java/io/IOException
          43    58    61   Class java/lang/InterruptedException
}
