Compiled from "HBaseFsck.java"
class org.apache.hadoop.hbase.util.HBaseFsck$3 implements org.apache.hadoop.hbase.MetaTableAccessor$Visitor {
  int countRecord;

  final java.util.Comparator<org.apache.hadoop.hbase.Cell> comp;

  final org.apache.hadoop.hbase.util.HBaseFsck this$0;

  org.apache.hadoop.hbase.util.HBaseFsck$3(org.apache.hadoop.hbase.util.HBaseFsck);
    Code:
       0: aload_0
       1: aload_1
       2: putfield      #1                  // Field this$0:Lorg/apache/hadoop/hbase/util/HBaseFsck;
       5: aload_0
       6: invokespecial #2                  // Method java/lang/Object."<init>":()V
       9: aload_0
      10: iconst_1
      11: putfield      #3                  // Field countRecord:I
      14: aload_0
      15: new           #4                  // class org/apache/hadoop/hbase/util/HBaseFsck$3$1
      18: dup
      19: aload_0
      20: invokespecial #5                  // Method org/apache/hadoop/hbase/util/HBaseFsck$3$1."<init>":(Lorg/apache/hadoop/hbase/util/HBaseFsck$3;)V
      23: putfield      #6                  // Field comp:Ljava/util/Comparator;
      26: return

  public boolean visit(org.apache.hadoop.hbase.client.Result) throws java.io.IOException;
    Code:
       0: aload_1
       1: invokevirtual #7                  // Method org/apache/hadoop/hbase/client/Result.listCells:()Ljava/util/List;
       4: aload_0
       5: getfield      #6                  // Field comp:Ljava/util/Comparator;
       8: invokestatic  #8                  // Method java/util/Collections.max:(Ljava/util/Collection;Ljava/util/Comparator;)Ljava/lang/Object;
      11: checkcast     #9                  // class org/apache/hadoop/hbase/Cell
      14: invokeinterface #10,  1           // InterfaceMethod org/apache/hadoop/hbase/Cell.getTimestamp:()J
      19: lstore_2
      20: aload_1
      21: invokestatic  #11                 // Method org/apache/hadoop/hbase/MetaTableAccessor.getRegionLocations:(Lorg/apache/hadoop/hbase/client/Result;)Lorg/apache/hadoop/hbase/RegionLocations;
      24: astore        4
      26: aload         4
      28: ifnonnull     64
      31: aload_0
      32: getfield      #1                  // Field this$0:Lorg/apache/hadoop/hbase/util/HBaseFsck;
      35: invokestatic  #12                 // Method org/apache/hadoop/hbase/util/HBaseFsck.access$2300:(Lorg/apache/hadoop/hbase/util/HBaseFsck;)Ljava/util/Set;
      38: aload_1
      39: invokeinterface #13,  2           // InterfaceMethod java/util/Set.add:(Ljava/lang/Object;)Z
      44: pop
      45: aload_0
      46: getfield      #1                  // Field this$0:Lorg/apache/hadoop/hbase/util/HBaseFsck;
      49: invokestatic  #14                 // Method org/apache/hadoop/hbase/util/HBaseFsck.access$1300:(Lorg/apache/hadoop/hbase/util/HBaseFsck;)Lorg/apache/hadoop/hbase/util/HBaseFsck$ErrorReporter;
      52: getstatic     #15                 // Field org/apache/hadoop/hbase/util/HBaseFsck$ErrorReporter$ERROR_CODE.EMPTY_META_CELL:Lorg/apache/hadoop/hbase/util/HBaseFsck$ErrorReporter$ERROR_CODE;
      55: ldc           #16                 // String Empty REGIONINFO_QUALIFIER found in hbase:meta
      57: invokeinterface #17,  3           // InterfaceMethod org/apache/hadoop/hbase/util/HBaseFsck$ErrorReporter.reportError:(Lorg/apache/hadoop/hbase/util/HBaseFsck$ErrorReporter$ERROR_CODE;Ljava/lang/String;)V
      62: iconst_1
      63: ireturn
      64: aconst_null
      65: astore        5
      67: aload         4
      69: iconst_0
      70: invokevirtual #19                 // Method org/apache/hadoop/hbase/RegionLocations.getRegionLocation:(I)Lorg/apache/hadoop/hbase/HRegionLocation;
      73: ifnull        88
      76: aload         4
      78: iconst_0
      79: invokevirtual #19                 // Method org/apache/hadoop/hbase/RegionLocations.getRegionLocation:(I)Lorg/apache/hadoop/hbase/HRegionLocation;
      82: invokevirtual #20                 // Method org/apache/hadoop/hbase/HRegionLocation.getRegionInfo:()Lorg/apache/hadoop/hbase/HRegionInfo;
      85: ifnonnull     121
      88: aload_0
      89: getfield      #1                  // Field this$0:Lorg/apache/hadoop/hbase/util/HBaseFsck;
      92: invokestatic  #12                 // Method org/apache/hadoop/hbase/util/HBaseFsck.access$2300:(Lorg/apache/hadoop/hbase/util/HBaseFsck;)Ljava/util/Set;
      95: aload_1
      96: invokeinterface #13,  2           // InterfaceMethod java/util/Set.add:(Ljava/lang/Object;)Z
     101: pop
     102: aload_0
     103: getfield      #1                  // Field this$0:Lorg/apache/hadoop/hbase/util/HBaseFsck;
     106: invokestatic  #14                 // Method org/apache/hadoop/hbase/util/HBaseFsck.access$1300:(Lorg/apache/hadoop/hbase/util/HBaseFsck;)Lorg/apache/hadoop/hbase/util/HBaseFsck$ErrorReporter;
     109: getstatic     #15                 // Field org/apache/hadoop/hbase/util/HBaseFsck$ErrorReporter$ERROR_CODE.EMPTY_META_CELL:Lorg/apache/hadoop/hbase/util/HBaseFsck$ErrorReporter$ERROR_CODE;
     112: ldc           #16                 // String Empty REGIONINFO_QUALIFIER found in hbase:meta
     114: invokeinterface #17,  3           // InterfaceMethod org/apache/hadoop/hbase/util/HBaseFsck$ErrorReporter.reportError:(Lorg/apache/hadoop/hbase/util/HBaseFsck$ErrorReporter$ERROR_CODE;Ljava/lang/String;)V
     119: iconst_1
     120: ireturn
     121: aload         4
     123: iconst_0
     124: invokevirtual #19                 // Method org/apache/hadoop/hbase/RegionLocations.getRegionLocation:(I)Lorg/apache/hadoop/hbase/HRegionLocation;
     127: invokevirtual #20                 // Method org/apache/hadoop/hbase/HRegionLocation.getRegionInfo:()Lorg/apache/hadoop/hbase/HRegionInfo;
     130: astore        6
     132: aload_0
     133: getfield      #1                  // Field this$0:Lorg/apache/hadoop/hbase/util/HBaseFsck;
     136: aload         6
     138: invokeinterface #21,  1           // InterfaceMethod org/apache/hadoop/hbase/client/RegionInfo.getTable:()Lorg/apache/hadoop/hbase/TableName;
     143: invokevirtual #22                 // Method org/apache/hadoop/hbase/util/HBaseFsck.isTableIncluded:(Lorg/apache/hadoop/hbase/TableName;)Z
     146: ifne          161
     149: aload         6
     151: invokeinterface #23,  1           // InterfaceMethod org/apache/hadoop/hbase/client/RegionInfo.isMetaRegion:()Z
     156: ifne          161
     159: iconst_1
     160: ireturn
     161: aload_1
     162: invokestatic  #24                 // Method org/apache/hadoop/hbase/MetaTableAccessor.getDaughterRegions:(Lorg/apache/hadoop/hbase/client/Result;)Lorg/apache/hadoop/hbase/util/PairOfSameType;
     165: astore        7
     167: aload         4
     169: invokevirtual #25                 // Method org/apache/hadoop/hbase/RegionLocations.getRegionLocations:()[Lorg/apache/hadoop/hbase/HRegionLocation;
     172: astore        8
     174: aload         8
     176: arraylength
     177: istore        9
     179: iconst_0
     180: istore        10
     182: iload         10
     184: iload         9
     186: if_icmpge     398
     189: aload         8
     191: iload         10
     193: aaload
     194: astore        11
     196: aload         11
     198: ifnull        392
     201: aload         11
     203: invokevirtual #20                 // Method org/apache/hadoop/hbase/HRegionLocation.getRegionInfo:()Lorg/apache/hadoop/hbase/HRegionInfo;
     206: ifnonnull     212
     209: goto          392
     212: aload         11
     214: invokevirtual #26                 // Method org/apache/hadoop/hbase/HRegionLocation.getServerName:()Lorg/apache/hadoop/hbase/ServerName;
     217: astore        5
     219: aload         11
     221: invokevirtual #20                 // Method org/apache/hadoop/hbase/HRegionLocation.getRegionInfo:()Lorg/apache/hadoop/hbase/HRegionInfo;
     224: astore        6
     226: aconst_null
     227: astore        12
     229: aload         6
     231: invokeinterface #27,  1           // InterfaceMethod org/apache/hadoop/hbase/client/RegionInfo.getReplicaId:()I
     236: ifne          272
     239: new           #28                 // class org/apache/hadoop/hbase/util/HBaseFsck$MetaEntry
     242: dup
     243: aload         6
     245: aload         5
     247: lload_2
     248: aload         7
     250: invokevirtual #29                 // Method org/apache/hadoop/hbase/util/PairOfSameType.getFirst:()Ljava/lang/Object;
     253: checkcast     #18                 // class org/apache/hadoop/hbase/client/RegionInfo
     256: aload         7
     258: invokevirtual #30                 // Method org/apache/hadoop/hbase/util/PairOfSameType.getSecond:()Ljava/lang/Object;
     261: checkcast     #18                 // class org/apache/hadoop/hbase/client/RegionInfo
     264: invokespecial #31                 // Method org/apache/hadoop/hbase/util/HBaseFsck$MetaEntry."<init>":(Lorg/apache/hadoop/hbase/client/RegionInfo;Lorg/apache/hadoop/hbase/ServerName;JLorg/apache/hadoop/hbase/client/RegionInfo;Lorg/apache/hadoop/hbase/client/RegionInfo;)V
     267: astore        12
     269: goto          288
     272: new           #28                 // class org/apache/hadoop/hbase/util/HBaseFsck$MetaEntry
     275: dup
     276: aload         6
     278: aload         5
     280: lload_2
     281: aconst_null
     282: aconst_null
     283: invokespecial #31                 // Method org/apache/hadoop/hbase/util/HBaseFsck$MetaEntry."<init>":(Lorg/apache/hadoop/hbase/client/RegionInfo;Lorg/apache/hadoop/hbase/ServerName;JLorg/apache/hadoop/hbase/client/RegionInfo;Lorg/apache/hadoop/hbase/client/RegionInfo;)V
     286: astore        12
     288: aload_0
     289: getfield      #1                  // Field this$0:Lorg/apache/hadoop/hbase/util/HBaseFsck;
     292: invokestatic  #32                 // Method org/apache/hadoop/hbase/util/HBaseFsck.access$1400:(Lorg/apache/hadoop/hbase/util/HBaseFsck;)Ljava/util/TreeMap;
     295: aload         6
     297: invokeinterface #33,  1           // InterfaceMethod org/apache/hadoop/hbase/client/RegionInfo.getEncodedName:()Ljava/lang/String;
     302: invokevirtual #34                 // Method java/util/TreeMap.get:(Ljava/lang/Object;)Ljava/lang/Object;
     305: checkcast     #35                 // class org/apache/hadoop/hbase/util/HBaseFsck$HbckInfo
     308: astore        13
     310: aload         13
     312: ifnonnull     345
     315: aload_0
     316: getfield      #1                  // Field this$0:Lorg/apache/hadoop/hbase/util/HBaseFsck;
     319: invokestatic  #32                 // Method org/apache/hadoop/hbase/util/HBaseFsck.access$1400:(Lorg/apache/hadoop/hbase/util/HBaseFsck;)Ljava/util/TreeMap;
     322: aload         6
     324: invokeinterface #33,  1           // InterfaceMethod org/apache/hadoop/hbase/client/RegionInfo.getEncodedName:()Ljava/lang/String;
     329: new           #35                 // class org/apache/hadoop/hbase/util/HBaseFsck$HbckInfo
     332: dup
     333: aload         12
     335: invokespecial #36                 // Method org/apache/hadoop/hbase/util/HBaseFsck$HbckInfo."<init>":(Lorg/apache/hadoop/hbase/util/HBaseFsck$MetaEntry;)V
     338: invokevirtual #37                 // Method java/util/TreeMap.put:(Ljava/lang/Object;Ljava/lang/Object;)Ljava/lang/Object;
     341: pop
     342: goto          392
     345: aload         13
     347: invokestatic  #38                 // Method org/apache/hadoop/hbase/util/HBaseFsck$HbckInfo.access$500:(Lorg/apache/hadoop/hbase/util/HBaseFsck$HbckInfo;)Lorg/apache/hadoop/hbase/util/HBaseFsck$MetaEntry;
     350: ifnonnull     364
     353: aload         13
     355: aload         12
     357: invokestatic  #39                 // Method org/apache/hadoop/hbase/util/HBaseFsck$HbckInfo.access$502:(Lorg/apache/hadoop/hbase/util/HBaseFsck$HbckInfo;Lorg/apache/hadoop/hbase/util/HBaseFsck$MetaEntry;)Lorg/apache/hadoop/hbase/util/HBaseFsck$MetaEntry;
     360: pop
     361: goto          392
     364: new           #40                 // class java/io/IOException
     367: dup
     368: new           #41                 // class java/lang/StringBuilder
     371: dup
     372: invokespecial #42                 // Method java/lang/StringBuilder."<init>":()V
     375: ldc           #43                 // String Two entries in hbase:meta are same
     377: invokevirtual #44                 // Method java/lang/StringBuilder.append:(Ljava/lang/String;)Ljava/lang/StringBuilder;
     380: aload         13
     382: invokevirtual #45                 // Method java/lang/StringBuilder.append:(Ljava/lang/Object;)Ljava/lang/StringBuilder;
     385: invokevirtual #46                 // Method java/lang/StringBuilder.toString:()Ljava/lang/String;
     388: invokespecial #47                 // Method java/io/IOException."<init>":(Ljava/lang/String;)V
     391: athrow
     392: iinc          10, 1
     395: goto          182
     398: aload_1
     399: invokestatic  #48                 // Method org/apache/hadoop/hbase/MetaTableAccessor.getMergeRegions:(Lorg/apache/hadoop/hbase/client/Result;)Lorg/apache/hadoop/hbase/util/PairOfSameType;
     402: astore        8
     404: iconst_2
     405: anewarray     #18                 // class org/apache/hadoop/hbase/client/RegionInfo
     408: dup
     409: iconst_0
     410: aload         8
     412: invokevirtual #29                 // Method org/apache/hadoop/hbase/util/PairOfSameType.getFirst:()Ljava/lang/Object;
     415: checkcast     #18                 // class org/apache/hadoop/hbase/client/RegionInfo
     418: aastore
     419: dup
     420: iconst_1
     421: aload         8
     423: invokevirtual #30                 // Method org/apache/hadoop/hbase/util/PairOfSameType.getSecond:()Ljava/lang/Object;
     426: checkcast     #18                 // class org/apache/hadoop/hbase/client/RegionInfo
     429: aastore
     430: astore        9
     432: aload         9
     434: arraylength
     435: istore        10
     437: iconst_0
     438: istore        11
     440: iload         11
     442: iload         10
     444: if_icmpge     487
     447: aload         9
     449: iload         11
     451: aaload
     452: astore        12
     454: aload         12
     456: ifnull        481
     459: aload_0
     460: getfield      #1                  // Field this$0:Lorg/apache/hadoop/hbase/util/HBaseFsck;
     463: aload         12
     465: invokeinterface #33,  1           // InterfaceMethod org/apache/hadoop/hbase/client/RegionInfo.getEncodedName:()Ljava/lang/String;
     470: invokestatic  #49                 // Method org/apache/hadoop/hbase/util/HBaseFsck.access$2400:(Lorg/apache/hadoop/hbase/util/HBaseFsck;Ljava/lang/String;)Lorg/apache/hadoop/hbase/util/HBaseFsck$HbckInfo;
     473: astore        13
     475: aload         13
     477: iconst_1
     478: invokevirtual #50                 // Method org/apache/hadoop/hbase/util/HBaseFsck$HbckInfo.setMerged:(Z)V
     481: iinc          11, 1
     484: goto          440
     487: aload_0
     488: getfield      #3                  // Field countRecord:I
     491: bipush        100
     493: irem
     494: ifne          509
     497: aload_0
     498: getfield      #1                  // Field this$0:Lorg/apache/hadoop/hbase/util/HBaseFsck;
     501: invokestatic  #14                 // Method org/apache/hadoop/hbase/util/HBaseFsck.access$1300:(Lorg/apache/hadoop/hbase/util/HBaseFsck;)Lorg/apache/hadoop/hbase/util/HBaseFsck$ErrorReporter;
     504: invokeinterface #51,  1           // InterfaceMethod org/apache/hadoop/hbase/util/HBaseFsck$ErrorReporter.progress:()V
     509: aload_0
     510: dup
     511: getfield      #3                  // Field countRecord:I
     514: iconst_1
     515: iadd
     516: putfield      #3                  // Field countRecord:I
     519: iconst_1
     520: ireturn
     521: astore_2
     522: invokestatic  #53                 // Method org/apache/hadoop/hbase/util/HBaseFsck.access$000:()Lorg/slf4j/Logger;
     525: new           #41                 // class java/lang/StringBuilder
     528: dup
     529: invokespecial #42                 // Method java/lang/StringBuilder."<init>":()V
     532: ldc           #54                 // String Result=
     534: invokevirtual #44                 // Method java/lang/StringBuilder.append:(Ljava/lang/String;)Ljava/lang/StringBuilder;
     537: aload_1
     538: invokevirtual #45                 // Method java/lang/StringBuilder.append:(Ljava/lang/Object;)Ljava/lang/StringBuilder;
     541: invokevirtual #46                 // Method java/lang/StringBuilder.toString:()Ljava/lang/String;
     544: invokeinterface #55,  2           // InterfaceMethod org/slf4j/Logger.error:(Ljava/lang/String;)V
     549: aload_2
     550: athrow
    Exception table:
       from    to  target type
           0    63   521   Class java/lang/RuntimeException
          64   120   521   Class java/lang/RuntimeException
         121   160   521   Class java/lang/RuntimeException
         161   520   521   Class java/lang/RuntimeException
}
