Compiled from "HBaseClassTestRule.java"
public final class org.apache.hadoop.hbase.HBaseClassTestRule implements org.junit.rules.TestRule {
  public java.lang.Class<?> getClazz();
    Code:
       0: aload_0
       1: getfield      #2                  // Field clazz:Ljava/lang/Class;
       4: areturn

  public static org.apache.hadoop.hbase.HBaseClassTestRule forClass(java.lang.Class<?>);
    Code:
       0: new           #27                 // class org/apache/hadoop/hbase/HBaseClassTestRule
       3: dup
       4: aload_0
       5: invokestatic  #28                 // Method org/junit/rules/Timeout.builder:()Lorg/junit/rules/Timeout$Builder;
       8: iconst_1
       9: invokevirtual #29                 // Method org/junit/rules/Timeout$Builder.withLookingForStuckThread:(Z)Lorg/junit/rules/Timeout$Builder;
      12: aload_0
      13: invokestatic  #30                 // Method getTimeoutInSeconds:(Ljava/lang/Class;)J
      16: getstatic     #31                 // Field java/util/concurrent/TimeUnit.SECONDS:Ljava/util/concurrent/TimeUnit;
      19: invokevirtual #32                 // Method org/junit/rules/Timeout$Builder.withTimeout:(JLjava/util/concurrent/TimeUnit;)Lorg/junit/rules/Timeout$Builder;
      22: invokevirtual #33                 // Method org/junit/rules/Timeout$Builder.build:()Lorg/junit/rules/Timeout;
      25: invokespecial #34                 // Method "<init>":(Ljava/lang/Class;Lorg/junit/rules/Timeout;)V
      28: areturn

  public org.junit.runners.model.Statement apply(org.junit.runners.model.Statement, org.junit.runner.Description);
    Code:
       0: aload_0
       1: getfield      #3                  // Field timeout:Lorg/junit/rules/Timeout;
       4: aload_1
       5: aload_2
       6: invokevirtual #35                 // Method org/junit/rules/Timeout.apply:(Lorg/junit/runners/model/Statement;Lorg/junit/runner/Description;)Lorg/junit/runners/model/Statement;
       9: areturn
}
