Compiled from "HBaseAdmin.java"
class org.apache.hadoop.hbase.client.HBaseAdmin$ReplicationFuture extends org.apache.hadoop.hbase.client.HBaseAdmin$ProcedureFuture<java.lang.Void> {
  public org.apache.hadoop.hbase.client.HBaseAdmin$ReplicationFuture(org.apache.hadoop.hbase.client.HBaseAdmin, java.lang.String, java.lang.Long, java.util.function.Supplier<java.lang.String>);
    Code:
       0: aload_0
       1: aload_1
       2: aload_3
       3: invokespecial #1                  // Method org/apache/hadoop/hbase/client/HBaseAdmin$ProcedureFuture."<init>":(Lorg/apache/hadoop/hbase/client/HBaseAdmin;Ljava/lang/Long;)V
       6: aload_0
       7: aload_2
       8: putfield      #2                  // Field peerId:Ljava/lang/String;
      11: aload_0
      12: aload         4
      14: putfield      #3                  // Field getOperation:Ljava/util/function/Supplier;
      17: return

  public java.lang.String toString();
    Code:
       0: new           #4                  // class java/lang/StringBuilder
       3: dup
       4: invokespecial #5                  // Method java/lang/StringBuilder."<init>":()V
       7: ldc           #6                  // String Operation:
       9: invokevirtual #7                  // Method java/lang/StringBuilder.append:(Ljava/lang/String;)Ljava/lang/StringBuilder;
      12: aload_0
      13: getfield      #3                  // Field getOperation:Ljava/util/function/Supplier;
      16: invokeinterface #8,  1            // InterfaceMethod java/util/function/Supplier.get:()Ljava/lang/Object;
      21: checkcast     #9                  // class java/lang/String
      24: invokevirtual #7                  // Method java/lang/StringBuilder.append:(Ljava/lang/String;)Ljava/lang/StringBuilder;
      27: ldc           #10                 // String , peerId:
      29: invokevirtual #7                  // Method java/lang/StringBuilder.append:(Ljava/lang/String;)Ljava/lang/StringBuilder;
      32: aload_0
      33: getfield      #2                  // Field peerId:Ljava/lang/String;
      36: invokevirtual #7                  // Method java/lang/StringBuilder.append:(Ljava/lang/String;)Ljava/lang/StringBuilder;
      39: invokevirtual #11                 // Method java/lang/StringBuilder.toString:()Ljava/lang/String;
      42: areturn
}
