Compiled from "HBaseFsck.java"
class org.apache.hadoop.hbase.util.HBaseFsck$PrintingErrorReporter implements org.apache.hadoop.hbase.util.HBaseFsck$ErrorReporter {
  public int errorCount;

  java.util.Set<org.apache.hadoop.hbase.util.HBaseFsck$TableInfo> errorTables;

  org.apache.hadoop.hbase.util.HBaseFsck$PrintingErrorReporter();
    Code:
       0: aload_0
       1: invokespecial #1                  // Method java/lang/Object."<init>":()V
       4: aload_0
       5: iconst_0
       6: putfield      #2                  // Field errorCount:I
       9: aload_0
      10: new           #3                  // class java/util/HashSet
      13: dup
      14: invokespecial #4                  // Method java/util/HashSet."<init>":()V
      17: putfield      #5                  // Field errorTables:Ljava/util/Set;
      20: aload_0
      21: new           #6                  // class java/util/ArrayList
      24: dup
      25: invokespecial #7                  // Method java/util/ArrayList."<init>":()V
      28: putfield      #8                  // Field errorList:Ljava/util/ArrayList;
      31: return

  public void clear();
    Code:
       0: aload_0
       1: getfield      #5                  // Field errorTables:Ljava/util/Set;
       4: invokeinterface #9,  1            // InterfaceMethod java/util/Set.clear:()V
       9: aload_0
      10: getfield      #8                  // Field errorList:Ljava/util/ArrayList;
      13: invokevirtual #10                 // Method java/util/ArrayList.clear:()V
      16: aload_0
      17: iconst_0
      18: putfield      #2                  // Field errorCount:I
      21: return

  public synchronized void reportError(org.apache.hadoop.hbase.util.HBaseFsck$ErrorReporter$ERROR_CODE, java.lang.String);
    Code:
       0: aload_1
       1: getstatic     #11                 // Field org/apache/hadoop/hbase/util/HBaseFsck$ErrorReporter$ERROR_CODE.WRONG_USAGE:Lorg/apache/hadoop/hbase/util/HBaseFsck$ErrorReporter$ERROR_CODE;
       4: if_acmpne     15
       7: getstatic     #12                 // Field java/lang/System.err:Ljava/io/PrintStream;
      10: aload_2
      11: invokevirtual #13                 // Method java/io/PrintStream.println:(Ljava/lang/String;)V
      14: return
      15: aload_0
      16: getfield      #8                  // Field errorList:Ljava/util/ArrayList;
      19: aload_1
      20: invokevirtual #14                 // Method java/util/ArrayList.add:(Ljava/lang/Object;)Z
      23: pop
      24: invokestatic  #15                 // Method org/apache/hadoop/hbase/util/HBaseFsck.access$2500:()Z
      27: ifne          55
      30: getstatic     #16                 // Field java/lang/System.out:Ljava/io/PrintStream;
      33: new           #17                 // class java/lang/StringBuilder
      36: dup
      37: invokespecial #18                 // Method java/lang/StringBuilder."<init>":()V
      40: ldc           #19                 // String ERROR:
      42: invokevirtual #20                 // Method java/lang/StringBuilder.append:(Ljava/lang/String;)Ljava/lang/StringBuilder;
      45: aload_2
      46: invokevirtual #20                 // Method java/lang/StringBuilder.append:(Ljava/lang/String;)Ljava/lang/StringBuilder;
      49: invokevirtual #21                 // Method java/lang/StringBuilder.toString:()Ljava/lang/String;
      52: invokevirtual #13                 // Method java/io/PrintStream.println:(Ljava/lang/String;)V
      55: aload_0
      56: dup
      57: getfield      #2                  // Field errorCount:I
      60: iconst_1
      61: iadd
      62: putfield      #2                  // Field errorCount:I
      65: aload_0
      66: iconst_0
      67: putfield      #22                 // Field showProgress:I
      70: return

  public synchronized void reportError(org.apache.hadoop.hbase.util.HBaseFsck$ErrorReporter$ERROR_CODE, java.lang.String, org.apache.hadoop.hbase.util.HBaseFsck$TableInfo);
    Code:
       0: aload_0
       1: getfield      #5                  // Field errorTables:Ljava/util/Set;
       4: aload_3
       5: invokeinterface #23,  2           // InterfaceMethod java/util/Set.add:(Ljava/lang/Object;)Z
      10: pop
      11: aload_0
      12: aload_1
      13: aload_2
      14: invokevirtual #24                 // Method reportError:(Lorg/apache/hadoop/hbase/util/HBaseFsck$ErrorReporter$ERROR_CODE;Ljava/lang/String;)V
      17: return

  public synchronized void reportError(org.apache.hadoop.hbase.util.HBaseFsck$ErrorReporter$ERROR_CODE, java.lang.String, org.apache.hadoop.hbase.util.HBaseFsck$TableInfo, org.apache.hadoop.hbase.util.HBaseFsck$HbckInfo);
    Code:
       0: aload_0
       1: getfield      #5                  // Field errorTables:Ljava/util/Set;
       4: aload_3
       5: invokeinterface #23,  2           // InterfaceMethod java/util/Set.add:(Ljava/lang/Object;)Z
      10: pop
      11: new           #17                 // class java/lang/StringBuilder
      14: dup
      15: invokespecial #18                 // Method java/lang/StringBuilder."<init>":()V
      18: ldc           #25                 // String (region
      20: invokevirtual #20                 // Method java/lang/StringBuilder.append:(Ljava/lang/String;)Ljava/lang/StringBuilder;
      23: aload         4
      25: invokevirtual #26                 // Method org/apache/hadoop/hbase/util/HBaseFsck$HbckInfo.getRegionNameAsString:()Ljava/lang/String;
      28: invokevirtual #20                 // Method java/lang/StringBuilder.append:(Ljava/lang/String;)Ljava/lang/StringBuilder;
      31: ldc           #27                 // String )
      33: invokevirtual #20                 // Method java/lang/StringBuilder.append:(Ljava/lang/String;)Ljava/lang/StringBuilder;
      36: invokevirtual #21                 // Method java/lang/StringBuilder.toString:()Ljava/lang/String;
      39: astore        5
      41: aload_0
      42: aload_1
      43: new           #17                 // class java/lang/StringBuilder
      46: dup
      47: invokespecial #18                 // Method java/lang/StringBuilder."<init>":()V
      50: aload         5
      52: invokevirtual #20                 // Method java/lang/StringBuilder.append:(Ljava/lang/String;)Ljava/lang/StringBuilder;
      55: ldc           #28                 // String
      57: invokevirtual #20                 // Method java/lang/StringBuilder.append:(Ljava/lang/String;)Ljava/lang/StringBuilder;
      60: aload_2
      61: invokevirtual #20                 // Method java/lang/StringBuilder.append:(Ljava/lang/String;)Ljava/lang/StringBuilder;
      64: invokevirtual #21                 // Method java/lang/StringBuilder.toString:()Ljava/lang/String;
      67: invokevirtual #24                 // Method reportError:(Lorg/apache/hadoop/hbase/util/HBaseFsck$ErrorReporter$ERROR_CODE;Ljava/lang/String;)V
      70: return

  public synchronized void reportError(org.apache.hadoop.hbase.util.HBaseFsck$ErrorReporter$ERROR_CODE, java.lang.String, org.apache.hadoop.hbase.util.HBaseFsck$TableInfo, org.apache.hadoop.hbase.util.HBaseFsck$HbckInfo, org.apache.hadoop.hbase.util.HBaseFsck$HbckInfo);
    Code:
       0: aload_0
       1: getfield      #5                  // Field errorTables:Ljava/util/Set;
       4: aload_3
       5: invokeinterface #23,  2           // InterfaceMethod java/util/Set.add:(Ljava/lang/Object;)Z
      10: pop
      11: new           #17                 // class java/lang/StringBuilder
      14: dup
      15: invokespecial #18                 // Method java/lang/StringBuilder."<init>":()V
      18: ldc           #29                 // String (regions
      20: invokevirtual #20                 // Method java/lang/StringBuilder.append:(Ljava/lang/String;)Ljava/lang/StringBuilder;
      23: aload         4
      25: invokevirtual #26                 // Method org/apache/hadoop/hbase/util/HBaseFsck$HbckInfo.getRegionNameAsString:()Ljava/lang/String;
      28: invokevirtual #20                 // Method java/lang/StringBuilder.append:(Ljava/lang/String;)Ljava/lang/StringBuilder;
      31: ldc           #30                 // String  and
      33: invokevirtual #20                 // Method java/lang/StringBuilder.append:(Ljava/lang/String;)Ljava/lang/StringBuilder;
      36: aload         5
      38: invokevirtual #26                 // Method org/apache/hadoop/hbase/util/HBaseFsck$HbckInfo.getRegionNameAsString:()Ljava/lang/String;
      41: invokevirtual #20                 // Method java/lang/StringBuilder.append:(Ljava/lang/String;)Ljava/lang/StringBuilder;
      44: ldc           #27                 // String )
      46: invokevirtual #20                 // Method java/lang/StringBuilder.append:(Ljava/lang/String;)Ljava/lang/StringBuilder;
      49: invokevirtual #21                 // Method java/lang/StringBuilder.toString:()Ljava/lang/String;
      52: astore        6
      54: aload_0
      55: aload_1
      56: new           #17                 // class java/lang/StringBuilder
      59: dup
      60: invokespecial #18                 // Method java/lang/StringBuilder."<init>":()V
      63: aload         6
      65: invokevirtual #20                 // Method java/lang/StringBuilder.append:(Ljava/lang/String;)Ljava/lang/StringBuilder;
      68: ldc           #28                 // String
      70: invokevirtual #20                 // Method java/lang/StringBuilder.append:(Ljava/lang/String;)Ljava/lang/StringBuilder;
      73: aload_2
      74: invokevirtual #20                 // Method java/lang/StringBuilder.append:(Ljava/lang/String;)Ljava/lang/StringBuilder;
      77: invokevirtual #21                 // Method java/lang/StringBuilder.toString:()Ljava/lang/String;
      80: invokevirtual #24                 // Method reportError:(Lorg/apache/hadoop/hbase/util/HBaseFsck$ErrorReporter$ERROR_CODE;Ljava/lang/String;)V
      83: return

  public synchronized void reportError(java.lang.String);
    Code:
       0: aload_0
       1: getstatic     #31                 // Field org/apache/hadoop/hbase/util/HBaseFsck$ErrorReporter$ERROR_CODE.UNKNOWN:Lorg/apache/hadoop/hbase/util/HBaseFsck$ErrorReporter$ERROR_CODE;
       4: aload_1
       5: invokevirtual #24                 // Method reportError:(Lorg/apache/hadoop/hbase/util/HBaseFsck$ErrorReporter$ERROR_CODE;Ljava/lang/String;)V
       8: return

  public synchronized void report(java.lang.String);
    Code:
       0: invokestatic  #15                 // Method org/apache/hadoop/hbase/util/HBaseFsck.access$2500:()Z
       3: ifne          31
       6: getstatic     #16                 // Field java/lang/System.out:Ljava/io/PrintStream;
       9: new           #17                 // class java/lang/StringBuilder
      12: dup
      13: invokespecial #18                 // Method java/lang/StringBuilder."<init>":()V
      16: ldc           #19                 // String ERROR:
      18: invokevirtual #20                 // Method java/lang/StringBuilder.append:(Ljava/lang/String;)Ljava/lang/StringBuilder;
      21: aload_1
      22: invokevirtual #20                 // Method java/lang/StringBuilder.append:(Ljava/lang/String;)Ljava/lang/StringBuilder;
      25: invokevirtual #21                 // Method java/lang/StringBuilder.toString:()Ljava/lang/String;
      28: invokevirtual #13                 // Method java/io/PrintStream.println:(Ljava/lang/String;)V
      31: aload_0
      32: iconst_0
      33: putfield      #22                 // Field showProgress:I
      36: return

  public synchronized int summarize();
    Code:
       0: getstatic     #16                 // Field java/lang/System.out:Ljava/io/PrintStream;
       3: new           #17                 // class java/lang/StringBuilder
       6: dup
       7: invokespecial #18                 // Method java/lang/StringBuilder."<init>":()V
      10: aload_0
      11: getfield      #2                  // Field errorCount:I
      14: invokestatic  #32                 // Method java/lang/Integer.toString:(I)Ljava/lang/String;
      17: invokevirtual #20                 // Method java/lang/StringBuilder.append:(Ljava/lang/String;)Ljava/lang/StringBuilder;
      20: ldc           #33                 // String  inconsistencies detected.
      22: invokevirtual #20                 // Method java/lang/StringBuilder.append:(Ljava/lang/String;)Ljava/lang/StringBuilder;
      25: invokevirtual #21                 // Method java/lang/StringBuilder.toString:()Ljava/lang/String;
      28: invokevirtual #13                 // Method java/io/PrintStream.println:(Ljava/lang/String;)V
      31: aload_0
      32: getfield      #2                  // Field errorCount:I
      35: ifne          48
      38: getstatic     #16                 // Field java/lang/System.out:Ljava/io/PrintStream;
      41: ldc           #34                 // String Status: OK
      43: invokevirtual #13                 // Method java/io/PrintStream.println:(Ljava/lang/String;)V
      46: iconst_0
      47: ireturn
      48: getstatic     #16                 // Field java/lang/System.out:Ljava/io/PrintStream;
      51: ldc           #35                 // String Status: INCONSISTENT
      53: invokevirtual #13                 // Method java/io/PrintStream.println:(Ljava/lang/String;)V
      56: iconst_m1
      57: ireturn

  public java.util.ArrayList<org.apache.hadoop.hbase.util.HBaseFsck$ErrorReporter$ERROR_CODE> getErrorList();
    Code:
       0: aload_0
       1: getfield      #8                  // Field errorList:Ljava/util/ArrayList;
       4: areturn

  public synchronized void print(java.lang.String);
    Code:
       0: invokestatic  #15                 // Method org/apache/hadoop/hbase/util/HBaseFsck.access$2500:()Z
       3: ifne          13
       6: getstatic     #16                 // Field java/lang/System.out:Ljava/io/PrintStream;
       9: aload_1
      10: invokevirtual #13                 // Method java/io/PrintStream.println:(Ljava/lang/String;)V
      13: return

  public boolean tableHasErrors(org.apache.hadoop.hbase.util.HBaseFsck$TableInfo);
    Code:
       0: aload_0
       1: getfield      #5                  // Field errorTables:Ljava/util/Set;
       4: aload_1
       5: invokeinterface #36,  2           // InterfaceMethod java/util/Set.contains:(Ljava/lang/Object;)Z
      10: ireturn

  public void resetErrors();
    Code:
       0: aload_0
       1: iconst_0
       2: putfield      #2                  // Field errorCount:I
       5: return

  public synchronized void detail(java.lang.String);
    Code:
       0: invokestatic  #37                 // Method org/apache/hadoop/hbase/util/HBaseFsck.access$2200:()Z
       3: ifeq          13
       6: getstatic     #16                 // Field java/lang/System.out:Ljava/io/PrintStream;
       9: aload_1
      10: invokevirtual #13                 // Method java/io/PrintStream.println:(Ljava/lang/String;)V
      13: aload_0
      14: iconst_0
      15: putfield      #22                 // Field showProgress:I
      18: return

  public synchronized void progress();
    Code:
       0: aload_0
       1: dup
       2: getfield      #22                 // Field showProgress:I
       5: dup_x1
       6: iconst_1
       7: iadd
       8: putfield      #22                 // Field showProgress:I
      11: bipush        100
      13: if_icmpne     35
      16: invokestatic  #15                 // Method org/apache/hadoop/hbase/util/HBaseFsck.access$2500:()Z
      19: ifne          30
      22: getstatic     #16                 // Field java/lang/System.out:Ljava/io/PrintStream;
      25: ldc           #39                 // String .
      27: invokevirtual #40                 // Method java/io/PrintStream.print:(Ljava/lang/String;)V
      30: aload_0
      31: iconst_0
      32: putfield      #22                 // Field showProgress:I
      35: return
}
