Compiled from "HBaseSaslRpcClient.java"
class org.apache.hadoop.hbase.security.HBaseSaslRpcClient$WrappedInputStream extends java.io.FilterInputStream {
  final org.apache.hadoop.hbase.security.HBaseSaslRpcClient this$0;

  public org.apache.hadoop.hbase.security.HBaseSaslRpcClient$WrappedInputStream(org.apache.hadoop.hbase.security.HBaseSaslRpcClient, java.io.InputStream) throws java.io.IOException;
    Code:
       0: aload_0
       1: aload_1
       2: putfield      #1                  // Field this$0:Lorg/apache/hadoop/hbase/security/HBaseSaslRpcClient;
       5: aload_0
       6: aload_2
       7: invokespecial #2                  // Method java/io/FilterInputStream."<init>":(Ljava/io/InputStream;)V
      10: aload_0
      11: iconst_0
      12: invokestatic  #3                  // Method java/nio/ByteBuffer.allocate:(I)Ljava/nio/ByteBuffer;
      15: putfield      #4                  // Field unwrappedRpcBuffer:Ljava/nio/ByteBuffer;
      18: return

  public int read() throws java.io.IOException;
    Code:
       0: iconst_1
       1: newarray       byte
       3: astore_1
       4: aload_0
       5: aload_1
       6: iconst_0
       7: iconst_1
       8: invokevirtual #5                  // Method read:([BII)I
      11: istore_2
      12: iload_2
      13: iconst_m1
      14: if_icmpeq     23
      17: aload_1
      18: iconst_0
      19: baload
      20: goto          24
      23: iconst_m1
      24: ireturn

  public int read(byte[]) throws java.io.IOException;
    Code:
       0: aload_0
       1: aload_1
       2: iconst_0
       3: aload_1
       4: arraylength
       5: invokevirtual #5                  // Method read:([BII)I
       8: ireturn

  public synchronized int read(byte[], int, int) throws java.io.IOException;
    Code:
       0: aload_0
       1: getfield      #4                  // Field unwrappedRpcBuffer:Ljava/nio/ByteBuffer;
       4: invokevirtual #6                  // Method java/nio/ByteBuffer.remaining:()I
       7: ifne          14
      10: aload_0
      11: invokespecial #7                  // Method readNextRpcPacket:()V
      14: iload_3
      15: aload_0
      16: getfield      #4                  // Field unwrappedRpcBuffer:Ljava/nio/ByteBuffer;
      19: invokevirtual #6                  // Method java/nio/ByteBuffer.remaining:()I
      22: invokestatic  #8                  // Method java/lang/Math.min:(II)I
      25: istore        4
      27: aload_0
      28: getfield      #4                  // Field unwrappedRpcBuffer:Ljava/nio/ByteBuffer;
      31: aload_1
      32: iload_2
      33: iload         4
      35: invokevirtual #9                  // Method java/nio/ByteBuffer.get:([BII)Ljava/nio/ByteBuffer;
      38: pop
      39: iload         4
      41: ireturn
}
