Compiled from "HBaseAdmin.java"
class org.apache.hadoop.hbase.client.HBaseAdmin$6 extends org.apache.hadoop.hbase.client.RpcRetryingCallable<java.lang.Boolean> {
  final org.apache.hadoop.hbase.TableName val$tableName;

  final org.apache.hadoop.hbase.client.HBaseAdmin this$0;

  org.apache.hadoop.hbase.client.HBaseAdmin$6(org.apache.hadoop.hbase.client.HBaseAdmin, org.apache.hadoop.hbase.TableName);
    Code:
       0: aload_0
       1: aload_1
       2: putfield      #1                  // Field this$0:Lorg/apache/hadoop/hbase/client/HBaseAdmin;
       5: aload_0
       6: aload_2
       7: putfield      #2                  // Field val$tableName:Lorg/apache/hadoop/hbase/TableName;
      10: aload_0
      11: invokespecial #3                  // Method org/apache/hadoop/hbase/client/RpcRetryingCallable."<init>":()V
      14: return

  protected java.lang.Boolean rpcCall(int) throws java.lang.Exception;
    Code:
       0: aload_0
       1: getfield      #1                  // Field this$0:Lorg/apache/hadoop/hbase/client/HBaseAdmin;
       4: invokestatic  #4                  // Method org/apache/hadoop/hbase/client/HBaseAdmin.access$100:(Lorg/apache/hadoop/hbase/client/HBaseAdmin;)Lorg/apache/hadoop/hbase/client/ClusterConnection;
       7: aload_0
       8: getfield      #2                  // Field val$tableName:Lorg/apache/hadoop/hbase/TableName;
      11: invokestatic  #5                  // Method org/apache/hadoop/hbase/MetaTableAccessor.tableExists:(Lorg/apache/hadoop/hbase/client/Connection;Lorg/apache/hadoop/hbase/TableName;)Z
      14: invokestatic  #6                  // Method java/lang/Boolean.valueOf:(Z)Ljava/lang/Boolean;
      17: areturn

  protected java.lang.Object rpcCall(int) throws java.lang.Exception;
    Code:
       0: aload_0
       1: iload_1
       2: invokevirtual #7                  // Method rpcCall:(I)Ljava/lang/Boolean;
       5: areturn
}
