Compiled from "HBaseFsck.java"
class org.apache.hadoop.hbase.util.HBaseFsck$2 implements org.apache.hadoop.hbase.Abortable {
  final org.apache.hadoop.hbase.util.HBaseFsck this$0;

  org.apache.hadoop.hbase.util.HBaseFsck$2(org.apache.hadoop.hbase.util.HBaseFsck);
    Code:
       0: aload_0
       1: aload_1
       2: putfield      #1                  // Field this$0:Lorg/apache/hadoop/hbase/util/HBaseFsck;
       5: aload_0
       6: invokespecial #2                  // Method java/lang/Object."<init>":()V
       9: return

  public void abort(java.lang.String, java.lang.Throwable);
    Code:
       0: invokestatic  #3                  // Method org/apache/hadoop/hbase/util/HBaseFsck.access$000:()Lorg/slf4j/Logger;
       3: aload_1
       4: aload_2
       5: invokeinterface #4,  3            // InterfaceMethod org/slf4j/Logger.error:(Ljava/lang/String;Ljava/lang/Throwable;)V
      10: iconst_1
      11: invokestatic  #5                  // Method java/lang/System.exit:(I)V
      14: return

  public boolean isAborted();
    Code:
       0: iconst_0
       1: ireturn
}
