Compiled from "HBaseAdmin.java"
class org.apache.hadoop.hbase.client.HBaseAdmin$72 extends org.apache.hadoop.hbase.client.MasterCallable<java.lang.Long> {
  final org.apache.hadoop.hbase.TableName val$tableName;

  final org.apache.hadoop.hbase.client.HBaseAdmin this$0;

  org.apache.hadoop.hbase.client.HBaseAdmin$72(org.apache.hadoop.hbase.client.HBaseAdmin, org.apache.hadoop.hbase.client.Connection, org.apache.hadoop.hbase.ipc.RpcControllerFactory, org.apache.hadoop.hbase.TableName);
    Code:
       0: aload_0
       1: aload_1
       2: putfield      #1                  // Field this$0:Lorg/apache/hadoop/hbase/client/HBaseAdmin;
       5: aload_0
       6: aload         4
       8: putfield      #2                  // Field val$tableName:Lorg/apache/hadoop/hbase/TableName;
      11: aload_0
      12: aload_2
      13: aload_3
      14: invokespecial #3                  // Method org/apache/hadoop/hbase/client/MasterCallable."<init>":(Lorg/apache/hadoop/hbase/client/Connection;Lorg/apache/hadoop/hbase/ipc/RpcControllerFactory;)V
      17: return

  protected java.lang.Long rpcCall() throws java.lang.Exception;
    Code:
       0: invokestatic  #4                  // Method org/apache/hadoop/hbase/shaded/protobuf/generated/MasterProtos$MajorCompactionTimestampRequest.newBuilder:()Lorg/apache/hadoop/hbase/shaded/protobuf/generated/MasterProtos$MajorCompactionTimestampRequest$Builder;
       3: aload_0
       4: getfield      #2                  // Field val$tableName:Lorg/apache/hadoop/hbase/TableName;
       7: invokestatic  #5                  // Method org/apache/hadoop/hbase/shaded/protobuf/ProtobufUtil.toProtoTableName:(Lorg/apache/hadoop/hbase/TableName;)Lorg/apache/hadoop/hbase/shaded/protobuf/generated/HBaseProtos$TableName;
      10: invokevirtual #6                  // Method org/apache/hadoop/hbase/shaded/protobuf/generated/MasterProtos$MajorCompactionTimestampRequest$Builder.setTableName:(Lorg/apache/hadoop/hbase/shaded/protobuf/generated/HBaseProtos$TableName;)Lorg/apache/hadoop/hbase/shaded/protobuf/generated/MasterProtos$MajorCompactionTimestampRequest$Builder;
      13: invokevirtual #7                  // Method org/apache/hadoop/hbase/shaded/protobuf/generated/MasterProtos$MajorCompactionTimestampRequest$Builder.build:()Lorg/apache/hadoop/hbase/shaded/protobuf/generated/MasterProtos$MajorCompactionTimestampRequest;
      16: astore_1
      17: aload_0
      18: getfield      #8                  // Field master:Lorg/apache/hadoop/hbase/client/MasterKeepAliveConnection;
      21: aload_0
      22: invokevirtual #9                  // Method getRpcController:()Lorg/apache/hadoop/hbase/ipc/HBaseRpcController;
      25: aload_1
      26: invokeinterface #10,  3           // InterfaceMethod org/apache/hadoop/hbase/client/MasterKeepAliveConnection.getLastMajorCompactionTimestamp:(Lorg/apache/hbase/thirdparty/com/google/protobuf/RpcController;Lorg/apache/hadoop/hbase/shaded/protobuf/generated/MasterProtos$MajorCompactionTimestampRequest;)Lorg/apache/hadoop/hbase/shaded/protobuf/generated/MasterProtos$MajorCompactionTimestampResponse;
      31: invokevirtual #11                 // Method org/apache/hadoop/hbase/shaded/protobuf/generated/MasterProtos$MajorCompactionTimestampResponse.getCompactionTimestamp:()J
      34: invokestatic  #12                 // Method java/lang/Long.valueOf:(J)Ljava/lang/Long;
      37: areturn

  protected java.lang.Object rpcCall() throws java.lang.Exception;
    Code:
       0: aload_0
       1: invokevirtual #13                 // Method rpcCall:()Ljava/lang/Long;
       4: areturn
}
