Compiled from "HBaseAdmin.java"
class org.apache.hadoop.hbase.client.HBaseAdmin$73 extends org.apache.hadoop.hbase.client.MasterCallable<java.lang.Long> {
  final byte[] val$regionName;

  final org.apache.hadoop.hbase.client.HBaseAdmin this$0;

  org.apache.hadoop.hbase.client.HBaseAdmin$73(org.apache.hadoop.hbase.client.HBaseAdmin, org.apache.hadoop.hbase.client.Connection, org.apache.hadoop.hbase.ipc.RpcControllerFactory, byte[]);
    Code:
       0: aload_0
       1: aload_1
       2: putfield      #1                  // Field this$0:Lorg/apache/hadoop/hbase/client/HBaseAdmin;
       5: aload_0
       6: aload         4
       8: putfield      #2                  // Field val$regionName:[B
      11: aload_0
      12: aload_2
      13: aload_3
      14: invokespecial #3                  // Method org/apache/hadoop/hbase/client/MasterCallable."<init>":(Lorg/apache/hadoop/hbase/client/Connection;Lorg/apache/hadoop/hbase/ipc/RpcControllerFactory;)V
      17: return

  protected java.lang.Long rpcCall() throws java.lang.Exception;
    Code:
       0: invokestatic  #4                  // Method org/apache/hadoop/hbase/shaded/protobuf/generated/MasterProtos$MajorCompactionTimestampForRegionRequest.newBuilder:()Lorg/apache/hadoop/hbase/shaded/protobuf/generated/MasterProtos$MajorCompactionTimestampForRegionRequest$Builder;
       3: getstatic     #5                  // Field org/apache/hadoop/hbase/shaded/protobuf/generated/HBaseProtos$RegionSpecifier$RegionSpecifierType.REGION_NAME:Lorg/apache/hadoop/hbase/shaded/protobuf/generated/HBaseProtos$RegionSpecifier$RegionSpecifierType;
       6: aload_0
       7: getfield      #2                  // Field val$regionName:[B
      10: invokestatic  #6                  // Method org/apache/hadoop/hbase/shaded/protobuf/RequestConverter.buildRegionSpecifier:(Lorg/apache/hadoop/hbase/shaded/protobuf/generated/HBaseProtos$RegionSpecifier$RegionSpecifierType;[B)Lorg/apache/hadoop/hbase/shaded/protobuf/generated/HBaseProtos$RegionSpecifier;
      13: invokevirtual #7                  // Method org/apache/hadoop/hbase/shaded/protobuf/generated/MasterProtos$MajorCompactionTimestampForRegionRequest$Builder.setRegion:(Lorg/apache/hadoop/hbase/shaded/protobuf/generated/HBaseProtos$RegionSpecifier;)Lorg/apache/hadoop/hbase/shaded/protobuf/generated/MasterProtos$MajorCompactionTimestampForRegionRequest$Builder;
      16: invokevirtual #8                  // Method org/apache/hadoop/hbase/shaded/protobuf/generated/MasterProtos$MajorCompactionTimestampForRegionRequest$Builder.build:()Lorg/apache/hadoop/hbase/shaded/protobuf/generated/MasterProtos$MajorCompactionTimestampForRegionRequest;
      19: astore_1
      20: aload_0
      21: getfield      #9                  // Field master:Lorg/apache/hadoop/hbase/client/MasterKeepAliveConnection;
      24: aload_0
      25: invokevirtual #10                 // Method getRpcController:()Lorg/apache/hadoop/hbase/ipc/HBaseRpcController;
      28: aload_1
      29: invokeinterface #11,  3           // InterfaceMethod org/apache/hadoop/hbase/client/MasterKeepAliveConnection.getLastMajorCompactionTimestampForRegion:(Lorg/apache/hbase/thirdparty/com/google/protobuf/RpcController;Lorg/apache/hadoop/hbase/shaded/protobuf/generated/MasterProtos$MajorCompactionTimestampForRegionRequest;)Lorg/apache/hadoop/hbase/shaded/protobuf/generated/MasterProtos$MajorCompactionTimestampResponse;
      34: invokevirtual #12                 // Method org/apache/hadoop/hbase/shaded/protobuf/generated/MasterProtos$MajorCompactionTimestampResponse.getCompactionTimestamp:()J
      37: invokestatic  #13                 // Method java/lang/Long.valueOf:(J)Ljava/lang/Long;
      40: areturn

  protected java.lang.Object rpcCall() throws java.lang.Exception;
    Code:
       0: aload_0
       1: invokevirtual #14                 // Method rpcCall:()Ljava/lang/Long;
       4: areturn
}
