Compiled from "HBaseProtos.java"
public final class org.apache.hadoop.hbase.protobuf.generated.HBaseProtos$RegionInfo$Builder extends com.google.protobuf.GeneratedMessage$Builder<org.apache.hadoop.hbase.protobuf.generated.HBaseProtos$RegionInfo$Builder> implements org.apache.hadoop.hbase.protobuf.generated.HBaseProtos$RegionInfoOrBuilder {
  public static final com.google.protobuf.Descriptors$Descriptor getDescriptor();
    Code:
       0: invokestatic  #3                  // Method org/apache/hadoop/hbase/protobuf/generated/HBaseProtos.access$4700:()Lcom/google/protobuf/Descriptors$Descriptor;
       3: areturn

  protected com.google.protobuf.GeneratedMessage$FieldAccessorTable internalGetFieldAccessorTable();
    Code:
       0: invokestatic  #4                  // Method org/apache/hadoop/hbase/protobuf/generated/HBaseProtos.access$4800:()Lcom/google/protobuf/GeneratedMessage$FieldAccessorTable;
       3: ldc           #5                  // class org/apache/hadoop/hbase/protobuf/generated/HBaseProtos$RegionInfo
       5: ldc           #6                  // class org/apache/hadoop/hbase/protobuf/generated/HBaseProtos$RegionInfo$Builder
       7: invokevirtual #7                  // Method com/google/protobuf/GeneratedMessage$FieldAccessorTable.ensureFieldAccessorsInitialized:(Ljava/lang/Class;Ljava/lang/Class;)Lcom/google/protobuf/GeneratedMessage$FieldAccessorTable;
      10: areturn

  public org.apache.hadoop.hbase.protobuf.generated.HBaseProtos$RegionInfo$Builder clear();
    Code:
       0: aload_0
       1: invokespecial #19                 // Method com/google/protobuf/GeneratedMessage$Builder.clear:()Lcom/google/protobuf/GeneratedMessage$Builder;
       4: pop
       5: aload_0
       6: lconst_0
       7: putfield      #20                 // Field regionId_:J
      10: aload_0
      11: aload_0
      12: getfield      #21                 // Field bitField0_:I
      15: bipush        -2
      17: iand
      18: putfield      #21                 // Field bitField0_:I
      21: aload_0
      22: getfield      #22                 // Field tableNameBuilder_:Lcom/google/protobuf/SingleFieldBuilder;
      25: ifnonnull     38
      28: aload_0
      29: invokestatic  #9                  // Method org/apache/hadoop/hbase/protobuf/generated/HBaseProtos$TableName.getDefaultInstance:()Lorg/apache/hadoop/hbase/protobuf/generated/HBaseProtos$TableName;
      32: putfield      #10                 // Field tableName_:Lorg/apache/hadoop/hbase/protobuf/generated/HBaseProtos$TableName;
      35: goto          46
      38: aload_0
      39: getfield      #22                 // Field tableNameBuilder_:Lcom/google/protobuf/SingleFieldBuilder;
      42: invokevirtual #23                 // Method com/google/protobuf/SingleFieldBuilder.clear:()Lcom/google/protobuf/SingleFieldBuilder;
      45: pop
      46: aload_0
      47: aload_0
      48: getfield      #21                 // Field bitField0_:I
      51: bipush        -3
      53: iand
      54: putfield      #21                 // Field bitField0_:I
      57: aload_0
      58: getstatic     #11                 // Field com/google/protobuf/ByteString.EMPTY:Lcom/google/protobuf/ByteString;
      61: putfield      #12                 // Field startKey_:Lcom/google/protobuf/ByteString;
      64: aload_0
      65: aload_0
      66: getfield      #21                 // Field bitField0_:I
      69: bipush        -5
      71: iand
      72: putfield      #21                 // Field bitField0_:I
      75: aload_0
      76: getstatic     #11                 // Field com/google/protobuf/ByteString.EMPTY:Lcom/google/protobuf/ByteString;
      79: putfield      #13                 // Field endKey_:Lcom/google/protobuf/ByteString;
      82: aload_0
      83: aload_0
      84: getfield      #21                 // Field bitField0_:I
      87: bipush        -9
      89: iand
      90: putfield      #21                 // Field bitField0_:I
      93: aload_0
      94: iconst_0
      95: putfield      #24                 // Field offline_:Z
      98: aload_0
      99: aload_0
     100: getfield      #21                 // Field bitField0_:I
     103: bipush        -17
     105: iand
     106: putfield      #21                 // Field bitField0_:I
     109: aload_0
     110: iconst_0
     111: putfield      #25                 // Field split_:Z
     114: aload_0
     115: aload_0
     116: getfield      #21                 // Field bitField0_:I
     119: bipush        -33
     121: iand
     122: putfield      #21                 // Field bitField0_:I
     125: aload_0
     126: iconst_0
     127: putfield      #26                 // Field replicaId_:I
     130: aload_0
     131: aload_0
     132: getfield      #21                 // Field bitField0_:I
     135: bipush        -65
     137: iand
     138: putfield      #21                 // Field bitField0_:I
     141: aload_0
     142: areturn

  public org.apache.hadoop.hbase.protobuf.generated.HBaseProtos$RegionInfo$Builder clone();
    Code:
       0: invokestatic  #2                  // Method create:()Lorg/apache/hadoop/hbase/protobuf/generated/HBaseProtos$RegionInfo$Builder;
       3: aload_0
       4: invokevirtual #27                 // Method buildPartial:()Lorg/apache/hadoop/hbase/protobuf/generated/HBaseProtos$RegionInfo;
       7: invokevirtual #28                 // Method mergeFrom:(Lorg/apache/hadoop/hbase/protobuf/generated/HBaseProtos$RegionInfo;)Lorg/apache/hadoop/hbase/protobuf/generated/HBaseProtos$RegionInfo$Builder;
      10: areturn

  public com.google.protobuf.Descriptors$Descriptor getDescriptorForType();
    Code:
       0: invokestatic  #3                  // Method org/apache/hadoop/hbase/protobuf/generated/HBaseProtos.access$4700:()Lcom/google/protobuf/Descriptors$Descriptor;
       3: areturn

  public org.apache.hadoop.hbase.protobuf.generated.HBaseProtos$RegionInfo getDefaultInstanceForType();
    Code:
       0: invokestatic  #29                 // Method org/apache/hadoop/hbase/protobuf/generated/HBaseProtos$RegionInfo.getDefaultInstance:()Lorg/apache/hadoop/hbase/protobuf/generated/HBaseProtos$RegionInfo;
       3: areturn

  public org.apache.hadoop.hbase.protobuf.generated.HBaseProtos$RegionInfo build();
    Code:
       0: aload_0
       1: invokevirtual #27                 // Method buildPartial:()Lorg/apache/hadoop/hbase/protobuf/generated/HBaseProtos$RegionInfo;
       4: astore_1
       5: aload_1
       6: invokevirtual #30                 // Method org/apache/hadoop/hbase/protobuf/generated/HBaseProtos$RegionInfo.isInitialized:()Z
       9: ifne          17
      12: aload_1
      13: invokestatic  #31                 // Method newUninitializedMessageException:(Lcom/google/protobuf/Message;)Lcom/google/protobuf/UninitializedMessageException;
      16: athrow
      17: aload_1
      18: areturn

  public org.apache.hadoop.hbase.protobuf.generated.HBaseProtos$RegionInfo buildPartial();
    Code:
       0: new           #5                  // class org/apache/hadoop/hbase/protobuf/generated/HBaseProtos$RegionInfo
       3: dup
       4: aload_0
       5: aconst_null
       6: invokespecial #32                 // Method org/apache/hadoop/hbase/protobuf/generated/HBaseProtos$RegionInfo."<init>":(Lcom/google/protobuf/GeneratedMessage$Builder;Lorg/apache/hadoop/hbase/protobuf/generated/HBaseProtos$1;)V
       9: astore_1
      10: aload_0
      11: getfield      #21                 // Field bitField0_:I
      14: istore_2
      15: iconst_0
      16: istore_3
      17: iload_2
      18: iconst_1
      19: iand
      20: iconst_1
      21: if_icmpne     28
      24: iload_3
      25: iconst_1
      26: ior
      27: istore_3
      28: aload_1
      29: aload_0
      30: getfield      #20                 // Field regionId_:J
      33: invokestatic  #33                 // Method org/apache/hadoop/hbase/protobuf/generated/HBaseProtos$RegionInfo.access$5402:(Lorg/apache/hadoop/hbase/protobuf/generated/HBaseProtos$RegionInfo;J)J
      36: pop2
      37: iload_2
      38: iconst_2
      39: iand
      40: iconst_2
      41: if_icmpne     48
      44: iload_3
      45: iconst_2
      46: ior
      47: istore_3
      48: aload_0
      49: getfield      #22                 // Field tableNameBuilder_:Lcom/google/protobuf/SingleFieldBuilder;
      52: ifnonnull     67
      55: aload_1
      56: aload_0
      57: getfield      #10                 // Field tableName_:Lorg/apache/hadoop/hbase/protobuf/generated/HBaseProtos$TableName;
      60: invokestatic  #34                 // Method org/apache/hadoop/hbase/protobuf/generated/HBaseProtos$RegionInfo.access$5502:(Lorg/apache/hadoop/hbase/protobuf/generated/HBaseProtos$RegionInfo;Lorg/apache/hadoop/hbase/protobuf/generated/HBaseProtos$TableName;)Lorg/apache/hadoop/hbase/protobuf/generated/HBaseProtos$TableName;
      63: pop
      64: goto          82
      67: aload_1
      68: aload_0
      69: getfield      #22                 // Field tableNameBuilder_:Lcom/google/protobuf/SingleFieldBuilder;
      72: invokevirtual #35                 // Method com/google/protobuf/SingleFieldBuilder.build:()Lcom/google/protobuf/GeneratedMessage;
      75: checkcast     #36                 // class org/apache/hadoop/hbase/protobuf/generated/HBaseProtos$TableName
      78: invokestatic  #34                 // Method org/apache/hadoop/hbase/protobuf/generated/HBaseProtos$RegionInfo.access$5502:(Lorg/apache/hadoop/hbase/protobuf/generated/HBaseProtos$RegionInfo;Lorg/apache/hadoop/hbase/protobuf/generated/HBaseProtos$TableName;)Lorg/apache/hadoop/hbase/protobuf/generated/HBaseProtos$TableName;
      81: pop
      82: iload_2
      83: iconst_4
      84: iand
      85: iconst_4
      86: if_icmpne     93
      89: iload_3
      90: iconst_4
      91: ior
      92: istore_3
      93: aload_1
      94: aload_0
      95: getfield      #12                 // Field startKey_:Lcom/google/protobuf/ByteString;
      98: invokestatic  #37                 // Method org/apache/hadoop/hbase/protobuf/generated/HBaseProtos$RegionInfo.access$5602:(Lorg/apache/hadoop/hbase/protobuf/generated/HBaseProtos$RegionInfo;Lcom/google/protobuf/ByteString;)Lcom/google/protobuf/ByteString;
     101: pop
     102: iload_2
     103: bipush        8
     105: iand
     106: bipush        8
     108: if_icmpne     116
     111: iload_3
     112: bipush        8
     114: ior
     115: istore_3
     116: aload_1
     117: aload_0
     118: getfield      #13                 // Field endKey_:Lcom/google/protobuf/ByteString;
     121: invokestatic  #38                 // Method org/apache/hadoop/hbase/protobuf/generated/HBaseProtos$RegionInfo.access$5702:(Lorg/apache/hadoop/hbase/protobuf/generated/HBaseProtos$RegionInfo;Lcom/google/protobuf/ByteString;)Lcom/google/protobuf/ByteString;
     124: pop
     125: iload_2
     126: bipush        16
     128: iand
     129: bipush        16
     131: if_icmpne     139
     134: iload_3
     135: bipush        16
     137: ior
     138: istore_3
     139: aload_1
     140: aload_0
     141: getfield      #24                 // Field offline_:Z
     144: invokestatic  #39                 // Method org/apache/hadoop/hbase/protobuf/generated/HBaseProtos$RegionInfo.access$5802:(Lorg/apache/hadoop/hbase/protobuf/generated/HBaseProtos$RegionInfo;Z)Z
     147: pop
     148: iload_2
     149: bipush        32
     151: iand
     152: bipush        32
     154: if_icmpne     162
     157: iload_3
     158: bipush        32
     160: ior
     161: istore_3
     162: aload_1
     163: aload_0
     164: getfield      #25                 // Field split_:Z
     167: invokestatic  #40                 // Method org/apache/hadoop/hbase/protobuf/generated/HBaseProtos$RegionInfo.access$5902:(Lorg/apache/hadoop/hbase/protobuf/generated/HBaseProtos$RegionInfo;Z)Z
     170: pop
     171: iload_2
     172: bipush        64
     174: iand
     175: bipush        64
     177: if_icmpne     185
     180: iload_3
     181: bipush        64
     183: ior
     184: istore_3
     185: aload_1
     186: aload_0
     187: getfield      #26                 // Field replicaId_:I
     190: invokestatic  #41                 // Method org/apache/hadoop/hbase/protobuf/generated/HBaseProtos$RegionInfo.access$6002:(Lorg/apache/hadoop/hbase/protobuf/generated/HBaseProtos$RegionInfo;I)I
     193: pop
     194: aload_1
     195: iload_3
     196: invokestatic  #42                 // Method org/apache/hadoop/hbase/protobuf/generated/HBaseProtos$RegionInfo.access$6102:(Lorg/apache/hadoop/hbase/protobuf/generated/HBaseProtos$RegionInfo;I)I
     199: pop
     200: aload_0
     201: invokevirtual #43                 // Method onBuilt:()V
     204: aload_1
     205: areturn

  public org.apache.hadoop.hbase.protobuf.generated.HBaseProtos$RegionInfo$Builder mergeFrom(com.google.protobuf.Message);
    Code:
       0: aload_1
       1: instanceof    #5                  // class org/apache/hadoop/hbase/protobuf/generated/HBaseProtos$RegionInfo
       4: ifeq          16
       7: aload_0
       8: aload_1
       9: checkcast     #5                  // class org/apache/hadoop/hbase/protobuf/generated/HBaseProtos$RegionInfo
      12: invokevirtual #28                 // Method mergeFrom:(Lorg/apache/hadoop/hbase/protobuf/generated/HBaseProtos$RegionInfo;)Lorg/apache/hadoop/hbase/protobuf/generated/HBaseProtos$RegionInfo$Builder;
      15: areturn
      16: aload_0
      17: aload_1
      18: invokespecial #44                 // Method com/google/protobuf/GeneratedMessage$Builder.mergeFrom:(Lcom/google/protobuf/Message;)Lcom/google/protobuf/AbstractMessage$Builder;
      21: pop
      22: aload_0
      23: areturn

  public org.apache.hadoop.hbase.protobuf.generated.HBaseProtos$RegionInfo$Builder mergeFrom(org.apache.hadoop.hbase.protobuf.generated.HBaseProtos$RegionInfo);
    Code:
       0: aload_1
       1: invokestatic  #29                 // Method org/apache/hadoop/hbase/protobuf/generated/HBaseProtos$RegionInfo.getDefaultInstance:()Lorg/apache/hadoop/hbase/protobuf/generated/HBaseProtos$RegionInfo;
       4: if_acmpne     9
       7: aload_0
       8: areturn
       9: aload_1
      10: invokevirtual #45                 // Method org/apache/hadoop/hbase/protobuf/generated/HBaseProtos$RegionInfo.hasRegionId:()Z
      13: ifeq          25
      16: aload_0
      17: aload_1
      18: invokevirtual #46                 // Method org/apache/hadoop/hbase/protobuf/generated/HBaseProtos$RegionInfo.getRegionId:()J
      21: invokevirtual #47                 // Method setRegionId:(J)Lorg/apache/hadoop/hbase/protobuf/generated/HBaseProtos$RegionInfo$Builder;
      24: pop
      25: aload_1
      26: invokevirtual #48                 // Method org/apache/hadoop/hbase/protobuf/generated/HBaseProtos$RegionInfo.hasTableName:()Z
      29: ifeq          41
      32: aload_0
      33: aload_1
      34: invokevirtual #49                 // Method org/apache/hadoop/hbase/protobuf/generated/HBaseProtos$RegionInfo.getTableName:()Lorg/apache/hadoop/hbase/protobuf/generated/HBaseProtos$TableName;
      37: invokevirtual #50                 // Method mergeTableName:(Lorg/apache/hadoop/hbase/protobuf/generated/HBaseProtos$TableName;)Lorg/apache/hadoop/hbase/protobuf/generated/HBaseProtos$RegionInfo$Builder;
      40: pop
      41: aload_1
      42: invokevirtual #51                 // Method org/apache/hadoop/hbase/protobuf/generated/HBaseProtos$RegionInfo.hasStartKey:()Z
      45: ifeq          57
      48: aload_0
      49: aload_1
      50: invokevirtual #52                 // Method org/apache/hadoop/hbase/protobuf/generated/HBaseProtos$RegionInfo.getStartKey:()Lcom/google/protobuf/ByteString;
      53: invokevirtual #53                 // Method setStartKey:(Lcom/google/protobuf/ByteString;)Lorg/apache/hadoop/hbase/protobuf/generated/HBaseProtos$RegionInfo$Builder;
      56: pop
      57: aload_1
      58: invokevirtual #54                 // Method org/apache/hadoop/hbase/protobuf/generated/HBaseProtos$RegionInfo.hasEndKey:()Z
      61: ifeq          73
      64: aload_0
      65: aload_1
      66: invokevirtual #55                 // Method org/apache/hadoop/hbase/protobuf/generated/HBaseProtos$RegionInfo.getEndKey:()Lcom/google/protobuf/ByteString;
      69: invokevirtual #56                 // Method setEndKey:(Lcom/google/protobuf/ByteString;)Lorg/apache/hadoop/hbase/protobuf/generated/HBaseProtos$RegionInfo$Builder;
      72: pop
      73: aload_1
      74: invokevirtual #57                 // Method org/apache/hadoop/hbase/protobuf/generated/HBaseProtos$RegionInfo.hasOffline:()Z
      77: ifeq          89
      80: aload_0
      81: aload_1
      82: invokevirtual #58                 // Method org/apache/hadoop/hbase/protobuf/generated/HBaseProtos$RegionInfo.getOffline:()Z
      85: invokevirtual #59                 // Method setOffline:(Z)Lorg/apache/hadoop/hbase/protobuf/generated/HBaseProtos$RegionInfo$Builder;
      88: pop
      89: aload_1
      90: invokevirtual #60                 // Method org/apache/hadoop/hbase/protobuf/generated/HBaseProtos$RegionInfo.hasSplit:()Z
      93: ifeq          105
      96: aload_0
      97: aload_1
      98: invokevirtual #61                 // Method org/apache/hadoop/hbase/protobuf/generated/HBaseProtos$RegionInfo.getSplit:()Z
     101: invokevirtual #62                 // Method setSplit:(Z)Lorg/apache/hadoop/hbase/protobuf/generated/HBaseProtos$RegionInfo$Builder;
     104: pop
     105: aload_1
     106: invokevirtual #63                 // Method org/apache/hadoop/hbase/protobuf/generated/HBaseProtos$RegionInfo.hasReplicaId:()Z
     109: ifeq          121
     112: aload_0
     113: aload_1
     114: invokevirtual #64                 // Method org/apache/hadoop/hbase/protobuf/generated/HBaseProtos$RegionInfo.getReplicaId:()I
     117: invokevirtual #65                 // Method setReplicaId:(I)Lorg/apache/hadoop/hbase/protobuf/generated/HBaseProtos$RegionInfo$Builder;
     120: pop
     121: aload_0
     122: aload_1
     123: invokevirtual #66                 // Method org/apache/hadoop/hbase/protobuf/generated/HBaseProtos$RegionInfo.getUnknownFields:()Lcom/google/protobuf/UnknownFieldSet;
     126: invokevirtual #67                 // Method mergeUnknownFields:(Lcom/google/protobuf/UnknownFieldSet;)Lcom/google/protobuf/GeneratedMessage$Builder;
     129: pop
     130: aload_0
     131: areturn

  public final boolean isInitialized();
    Code:
       0: aload_0
       1: invokevirtual #68                 // Method hasRegionId:()Z
       4: ifne          9
       7: iconst_0
       8: ireturn
       9: aload_0
      10: invokevirtual #69                 // Method hasTableName:()Z
      13: ifne          18
      16: iconst_0
      17: ireturn
      18: aload_0
      19: invokevirtual #70                 // Method getTableName:()Lorg/apache/hadoop/hbase/protobuf/generated/HBaseProtos$TableName;
      22: invokevirtual #71                 // Method org/apache/hadoop/hbase/protobuf/generated/HBaseProtos$TableName.isInitialized:()Z
      25: ifne          30
      28: iconst_0
      29: ireturn
      30: iconst_1
      31: ireturn

  public org.apache.hadoop.hbase.protobuf.generated.HBaseProtos$RegionInfo$Builder mergeFrom(com.google.protobuf.CodedInputStream, com.google.protobuf.ExtensionRegistryLite) throws java.io.IOException;
    Code:
       0: aconst_null
       1: astore_3
       2: getstatic     #72                 // Field org/apache/hadoop/hbase/protobuf/generated/HBaseProtos$RegionInfo.PARSER:Lcom/google/protobuf/Parser;
       5: aload_1
       6: aload_2
       7: invokeinterface #73,  3           // InterfaceMethod com/google/protobuf/Parser.parsePartialFrom:(Lcom/google/protobuf/CodedInputStream;Lcom/google/protobuf/ExtensionRegistryLite;)Ljava/lang/Object;
      12: checkcast     #5                  // class org/apache/hadoop/hbase/protobuf/generated/HBaseProtos$RegionInfo
      15: astore_3
      16: aload_3
      17: ifnull        58
      20: aload_0
      21: aload_3
      22: invokevirtual #28                 // Method mergeFrom:(Lorg/apache/hadoop/hbase/protobuf/generated/HBaseProtos$RegionInfo;)Lorg/apache/hadoop/hbase/protobuf/generated/HBaseProtos$RegionInfo$Builder;
      25: pop
      26: goto          58
      29: astore        4
      31: aload         4
      33: invokevirtual #75                 // Method com/google/protobuf/InvalidProtocolBufferException.getUnfinishedMessage:()Lcom/google/protobuf/MessageLite;
      36: checkcast     #5                  // class org/apache/hadoop/hbase/protobuf/generated/HBaseProtos$RegionInfo
      39: astore_3
      40: aload         4
      42: athrow
      43: astore        5
      45: aload_3
      46: ifnull        55
      49: aload_0
      50: aload_3
      51: invokevirtual #28                 // Method mergeFrom:(Lorg/apache/hadoop/hbase/protobuf/generated/HBaseProtos$RegionInfo;)Lorg/apache/hadoop/hbase/protobuf/generated/HBaseProtos$RegionInfo$Builder;
      54: pop
      55: aload         5
      57: athrow
      58: aload_0
      59: areturn
    Exception table:
       from    to  target type
           2    16    29   Class com/google/protobuf/InvalidProtocolBufferException
           2    16    43   any
          29    45    43   any

  public boolean hasRegionId();
    Code:
       0: aload_0
       1: getfield      #21                 // Field bitField0_:I
       4: iconst_1
       5: iand
       6: iconst_1
       7: if_icmpne     14
      10: iconst_1
      11: goto          15
      14: iconst_0
      15: ireturn

  public long getRegionId();
    Code:
       0: aload_0
       1: getfield      #20                 // Field regionId_:J
       4: lreturn

  public org.apache.hadoop.hbase.protobuf.generated.HBaseProtos$RegionInfo$Builder setRegionId(long);
    Code:
       0: aload_0
       1: dup
       2: getfield      #21                 // Field bitField0_:I
       5: iconst_1
       6: ior
       7: putfield      #21                 // Field bitField0_:I
      10: aload_0
      11: lload_1
      12: putfield      #20                 // Field regionId_:J
      15: aload_0
      16: invokevirtual #76                 // Method onChanged:()V
      19: aload_0
      20: areturn

  public org.apache.hadoop.hbase.protobuf.generated.HBaseProtos$RegionInfo$Builder clearRegionId();
    Code:
       0: aload_0
       1: aload_0
       2: getfield      #21                 // Field bitField0_:I
       5: bipush        -2
       7: iand
       8: putfield      #21                 // Field bitField0_:I
      11: aload_0
      12: lconst_0
      13: putfield      #20                 // Field regionId_:J
      16: aload_0
      17: invokevirtual #76                 // Method onChanged:()V
      20: aload_0
      21: areturn

  public boolean hasTableName();
    Code:
       0: aload_0
       1: getfield      #21                 // Field bitField0_:I
       4: iconst_2
       5: iand
       6: iconst_2
       7: if_icmpne     14
      10: iconst_1
      11: goto          15
      14: iconst_0
      15: ireturn

  public org.apache.hadoop.hbase.protobuf.generated.HBaseProtos$TableName getTableName();
    Code:
       0: aload_0
       1: getfield      #22                 // Field tableNameBuilder_:Lcom/google/protobuf/SingleFieldBuilder;
       4: ifnonnull     12
       7: aload_0
       8: getfield      #10                 // Field tableName_:Lorg/apache/hadoop/hbase/protobuf/generated/HBaseProtos$TableName;
      11: areturn
      12: aload_0
      13: getfield      #22                 // Field tableNameBuilder_:Lcom/google/protobuf/SingleFieldBuilder;
      16: invokevirtual #77                 // Method com/google/protobuf/SingleFieldBuilder.getMessage:()Lcom/google/protobuf/GeneratedMessage;
      19: checkcast     #36                 // class org/apache/hadoop/hbase/protobuf/generated/HBaseProtos$TableName
      22: areturn

  public org.apache.hadoop.hbase.protobuf.generated.HBaseProtos$RegionInfo$Builder setTableName(org.apache.hadoop.hbase.protobuf.generated.HBaseProtos$TableName);
    Code:
       0: aload_0
       1: getfield      #22                 // Field tableNameBuilder_:Lcom/google/protobuf/SingleFieldBuilder;
       4: ifnonnull     31
       7: aload_1
       8: ifnonnull     19
      11: new           #78                 // class java/lang/NullPointerException
      14: dup
      15: invokespecial #79                 // Method java/lang/NullPointerException."<init>":()V
      18: athrow
      19: aload_0
      20: aload_1
      21: putfield      #10                 // Field tableName_:Lorg/apache/hadoop/hbase/protobuf/generated/HBaseProtos$TableName;
      24: aload_0
      25: invokevirtual #76                 // Method onChanged:()V
      28: goto          40
      31: aload_0
      32: getfield      #22                 // Field tableNameBuilder_:Lcom/google/protobuf/SingleFieldBuilder;
      35: aload_1
      36: invokevirtual #80                 // Method com/google/protobuf/SingleFieldBuilder.setMessage:(Lcom/google/protobuf/GeneratedMessage;)Lcom/google/protobuf/SingleFieldBuilder;
      39: pop
      40: aload_0
      41: dup
      42: getfield      #21                 // Field bitField0_:I
      45: iconst_2
      46: ior
      47: putfield      #21                 // Field bitField0_:I
      50: aload_0
      51: areturn

  public org.apache.hadoop.hbase.protobuf.generated.HBaseProtos$RegionInfo$Builder setTableName(org.apache.hadoop.hbase.protobuf.generated.HBaseProtos$TableName$Builder);
    Code:
       0: aload_0
       1: getfield      #22                 // Field tableNameBuilder_:Lcom/google/protobuf/SingleFieldBuilder;
       4: ifnonnull     22
       7: aload_0
       8: aload_1
       9: invokevirtual #81                 // Method org/apache/hadoop/hbase/protobuf/generated/HBaseProtos$TableName$Builder.build:()Lorg/apache/hadoop/hbase/protobuf/generated/HBaseProtos$TableName;
      12: putfield      #10                 // Field tableName_:Lorg/apache/hadoop/hbase/protobuf/generated/HBaseProtos$TableName;
      15: aload_0
      16: invokevirtual #76                 // Method onChanged:()V
      19: goto          34
      22: aload_0
      23: getfield      #22                 // Field tableNameBuilder_:Lcom/google/protobuf/SingleFieldBuilder;
      26: aload_1
      27: invokevirtual #81                 // Method org/apache/hadoop/hbase/protobuf/generated/HBaseProtos$TableName$Builder.build:()Lorg/apache/hadoop/hbase/protobuf/generated/HBaseProtos$TableName;
      30: invokevirtual #80                 // Method com/google/protobuf/SingleFieldBuilder.setMessage:(Lcom/google/protobuf/GeneratedMessage;)Lcom/google/protobuf/SingleFieldBuilder;
      33: pop
      34: aload_0
      35: dup
      36: getfield      #21                 // Field bitField0_:I
      39: iconst_2
      40: ior
      41: putfield      #21                 // Field bitField0_:I
      44: aload_0
      45: areturn

  public org.apache.hadoop.hbase.protobuf.generated.HBaseProtos$RegionInfo$Builder mergeTableName(org.apache.hadoop.hbase.protobuf.generated.HBaseProtos$TableName);
    Code:
       0: aload_0
       1: getfield      #22                 // Field tableNameBuilder_:Lcom/google/protobuf/SingleFieldBuilder;
       4: ifnonnull     60
       7: aload_0
       8: getfield      #21                 // Field bitField0_:I
      11: iconst_2
      12: iand
      13: iconst_2
      14: if_icmpne     48
      17: aload_0
      18: getfield      #10                 // Field tableName_:Lorg/apache/hadoop/hbase/protobuf/generated/HBaseProtos$TableName;
      21: invokestatic  #9                  // Method org/apache/hadoop/hbase/protobuf/generated/HBaseProtos$TableName.getDefaultInstance:()Lorg/apache/hadoop/hbase/protobuf/generated/HBaseProtos$TableName;
      24: if_acmpeq     48
      27: aload_0
      28: aload_0
      29: getfield      #10                 // Field tableName_:Lorg/apache/hadoop/hbase/protobuf/generated/HBaseProtos$TableName;
      32: invokestatic  #82                 // Method org/apache/hadoop/hbase/protobuf/generated/HBaseProtos$TableName.newBuilder:(Lorg/apache/hadoop/hbase/protobuf/generated/HBaseProtos$TableName;)Lorg/apache/hadoop/hbase/protobuf/generated/HBaseProtos$TableName$Builder;
      35: aload_1
      36: invokevirtual #83                 // Method org/apache/hadoop/hbase/protobuf/generated/HBaseProtos$TableName$Builder.mergeFrom:(Lorg/apache/hadoop/hbase/protobuf/generated/HBaseProtos$TableName;)Lorg/apache/hadoop/hbase/protobuf/generated/HBaseProtos$TableName$Builder;
      39: invokevirtual #84                 // Method org/apache/hadoop/hbase/protobuf/generated/HBaseProtos$TableName$Builder.buildPartial:()Lorg/apache/hadoop/hbase/protobuf/generated/HBaseProtos$TableName;
      42: putfield      #10                 // Field tableName_:Lorg/apache/hadoop/hbase/protobuf/generated/HBaseProtos$TableName;
      45: goto          53
      48: aload_0
      49: aload_1
      50: putfield      #10                 // Field tableName_:Lorg/apache/hadoop/hbase/protobuf/generated/HBaseProtos$TableName;
      53: aload_0
      54: invokevirtual #76                 // Method onChanged:()V
      57: goto          69
      60: aload_0
      61: getfield      #22                 // Field tableNameBuilder_:Lcom/google/protobuf/SingleFieldBuilder;
      64: aload_1
      65: invokevirtual #85                 // Method com/google/protobuf/SingleFieldBuilder.mergeFrom:(Lcom/google/protobuf/GeneratedMessage;)Lcom/google/protobuf/SingleFieldBuilder;
      68: pop
      69: aload_0
      70: dup
      71: getfield      #21                 // Field bitField0_:I
      74: iconst_2
      75: ior
      76: putfield      #21                 // Field bitField0_:I
      79: aload_0
      80: areturn

  public org.apache.hadoop.hbase.protobuf.generated.HBaseProtos$RegionInfo$Builder clearTableName();
    Code:
       0: aload_0
       1: getfield      #22                 // Field tableNameBuilder_:Lcom/google/protobuf/SingleFieldBuilder;
       4: ifnonnull     21
       7: aload_0
       8: invokestatic  #9                  // Method org/apache/hadoop/hbase/protobuf/generated/HBaseProtos$TableName.getDefaultInstance:()Lorg/apache/hadoop/hbase/protobuf/generated/HBaseProtos$TableName;
      11: putfield      #10                 // Field tableName_:Lorg/apache/hadoop/hbase/protobuf/generated/HBaseProtos$TableName;
      14: aload_0
      15: invokevirtual #76                 // Method onChanged:()V
      18: goto          29
      21: aload_0
      22: getfield      #22                 // Field tableNameBuilder_:Lcom/google/protobuf/SingleFieldBuilder;
      25: invokevirtual #23                 // Method com/google/protobuf/SingleFieldBuilder.clear:()Lcom/google/protobuf/SingleFieldBuilder;
      28: pop
      29: aload_0
      30: aload_0
      31: getfield      #21                 // Field bitField0_:I
      34: bipush        -3
      36: iand
      37: putfield      #21                 // Field bitField0_:I
      40: aload_0
      41: areturn

  public org.apache.hadoop.hbase.protobuf.generated.HBaseProtos$TableName$Builder getTableNameBuilder();
    Code:
       0: aload_0
       1: dup
       2: getfield      #21                 // Field bitField0_:I
       5: iconst_2
       6: ior
       7: putfield      #21                 // Field bitField0_:I
      10: aload_0
      11: invokevirtual #76                 // Method onChanged:()V
      14: aload_0
      15: invokespecial #17                 // Method getTableNameFieldBuilder:()Lcom/google/protobuf/SingleFieldBuilder;
      18: invokevirtual #86                 // Method com/google/protobuf/SingleFieldBuilder.getBuilder:()Lcom/google/protobuf/GeneratedMessage$Builder;
      21: checkcast     #87                 // class org/apache/hadoop/hbase/protobuf/generated/HBaseProtos$TableName$Builder
      24: areturn

  public org.apache.hadoop.hbase.protobuf.generated.HBaseProtos$TableNameOrBuilder getTableNameOrBuilder();
    Code:
       0: aload_0
       1: getfield      #22                 // Field tableNameBuilder_:Lcom/google/protobuf/SingleFieldBuilder;
       4: ifnull        18
       7: aload_0
       8: getfield      #22                 // Field tableNameBuilder_:Lcom/google/protobuf/SingleFieldBuilder;
      11: invokevirtual #88                 // Method com/google/protobuf/SingleFieldBuilder.getMessageOrBuilder:()Lcom/google/protobuf/MessageOrBuilder;
      14: checkcast     #89                 // class org/apache/hadoop/hbase/protobuf/generated/HBaseProtos$TableNameOrBuilder
      17: areturn
      18: aload_0
      19: getfield      #10                 // Field tableName_:Lorg/apache/hadoop/hbase/protobuf/generated/HBaseProtos$TableName;
      22: areturn

  public boolean hasStartKey();
    Code:
       0: aload_0
       1: getfield      #21                 // Field bitField0_:I
       4: iconst_4
       5: iand
       6: iconst_4
       7: if_icmpne     14
      10: iconst_1
      11: goto          15
      14: iconst_0
      15: ireturn

  public com.google.protobuf.ByteString getStartKey();
    Code:
       0: aload_0
       1: getfield      #12                 // Field startKey_:Lcom/google/protobuf/ByteString;
       4: areturn

  public org.apache.hadoop.hbase.protobuf.generated.HBaseProtos$RegionInfo$Builder setStartKey(com.google.protobuf.ByteString);
    Code:
       0: aload_1
       1: ifnonnull     12
       4: new           #78                 // class java/lang/NullPointerException
       7: dup
       8: invokespecial #79                 // Method java/lang/NullPointerException."<init>":()V
      11: athrow
      12: aload_0
      13: dup
      14: getfield      #21                 // Field bitField0_:I
      17: iconst_4
      18: ior
      19: putfield      #21                 // Field bitField0_:I
      22: aload_0
      23: aload_1
      24: putfield      #12                 // Field startKey_:Lcom/google/protobuf/ByteString;
      27: aload_0
      28: invokevirtual #76                 // Method onChanged:()V
      31: aload_0
      32: areturn

  public org.apache.hadoop.hbase.protobuf.generated.HBaseProtos$RegionInfo$Builder clearStartKey();
    Code:
       0: aload_0
       1: aload_0
       2: getfield      #21                 // Field bitField0_:I
       5: bipush        -5
       7: iand
       8: putfield      #21                 // Field bitField0_:I
      11: aload_0
      12: invokestatic  #29                 // Method org/apache/hadoop/hbase/protobuf/generated/HBaseProtos$RegionInfo.getDefaultInstance:()Lorg/apache/hadoop/hbase/protobuf/generated/HBaseProtos$RegionInfo;
      15: invokevirtual #52                 // Method org/apache/hadoop/hbase/protobuf/generated/HBaseProtos$RegionInfo.getStartKey:()Lcom/google/protobuf/ByteString;
      18: putfield      #12                 // Field startKey_:Lcom/google/protobuf/ByteString;
      21: aload_0
      22: invokevirtual #76                 // Method onChanged:()V
      25: aload_0
      26: areturn

  public boolean hasEndKey();
    Code:
       0: aload_0
       1: getfield      #21                 // Field bitField0_:I
       4: bipush        8
       6: iand
       7: bipush        8
       9: if_icmpne     16
      12: iconst_1
      13: goto          17
      16: iconst_0
      17: ireturn

  public com.google.protobuf.ByteString getEndKey();
    Code:
       0: aload_0
       1: getfield      #13                 // Field endKey_:Lcom/google/protobuf/ByteString;
       4: areturn

  public org.apache.hadoop.hbase.protobuf.generated.HBaseProtos$RegionInfo$Builder setEndKey(com.google.protobuf.ByteString);
    Code:
       0: aload_1
       1: ifnonnull     12
       4: new           #78                 // class java/lang/NullPointerException
       7: dup
       8: invokespecial #79                 // Method java/lang/NullPointerException."<init>":()V
      11: athrow
      12: aload_0
      13: dup
      14: getfield      #21                 // Field bitField0_:I
      17: bipush        8
      19: ior
      20: putfield      #21                 // Field bitField0_:I
      23: aload_0
      24: aload_1
      25: putfield      #13                 // Field endKey_:Lcom/google/protobuf/ByteString;
      28: aload_0
      29: invokevirtual #76                 // Method onChanged:()V
      32: aload_0
      33: areturn

  public org.apache.hadoop.hbase.protobuf.generated.HBaseProtos$RegionInfo$Builder clearEndKey();
    Code:
       0: aload_0
       1: aload_0
       2: getfield      #21                 // Field bitField0_:I
       5: bipush        -9
       7: iand
       8: putfield      #21                 // Field bitField0_:I
      11: aload_0
      12: invokestatic  #29                 // Method org/apache/hadoop/hbase/protobuf/generated/HBaseProtos$RegionInfo.getDefaultInstance:()Lorg/apache/hadoop/hbase/protobuf/generated/HBaseProtos$RegionInfo;
      15: invokevirtual #55                 // Method org/apache/hadoop/hbase/protobuf/generated/HBaseProtos$RegionInfo.getEndKey:()Lcom/google/protobuf/ByteString;
      18: putfield      #13                 // Field endKey_:Lcom/google/protobuf/ByteString;
      21: aload_0
      22: invokevirtual #76                 // Method onChanged:()V
      25: aload_0
      26: areturn

  public boolean hasOffline();
    Code:
       0: aload_0
       1: getfield      #21                 // Field bitField0_:I
       4: bipush        16
       6: iand
       7: bipush        16
       9: if_icmpne     16
      12: iconst_1
      13: goto          17
      16: iconst_0
      17: ireturn

  public boolean getOffline();
    Code:
       0: aload_0
       1: getfield      #24                 // Field offline_:Z
       4: ireturn

  public org.apache.hadoop.hbase.protobuf.generated.HBaseProtos$RegionInfo$Builder setOffline(boolean);
    Code:
       0: aload_0
       1: dup
       2: getfield      #21                 // Field bitField0_:I
       5: bipush        16
       7: ior
       8: putfield      #21                 // Field bitField0_:I
      11: aload_0
      12: iload_1
      13: putfield      #24                 // Field offline_:Z
      16: aload_0
      17: invokevirtual #76                 // Method onChanged:()V
      20: aload_0
      21: areturn

  public org.apache.hadoop.hbase.protobuf.generated.HBaseProtos$RegionInfo$Builder clearOffline();
    Code:
       0: aload_0
       1: aload_0
       2: getfield      #21                 // Field bitField0_:I
       5: bipush        -17
       7: iand
       8: putfield      #21                 // Field bitField0_:I
      11: aload_0
      12: iconst_0
      13: putfield      #24                 // Field offline_:Z
      16: aload_0
      17: invokevirtual #76                 // Method onChanged:()V
      20: aload_0
      21: areturn

  public boolean hasSplit();
    Code:
       0: aload_0
       1: getfield      #21                 // Field bitField0_:I
       4: bipush        32
       6: iand
       7: bipush        32
       9: if_icmpne     16
      12: iconst_1
      13: goto          17
      16: iconst_0
      17: ireturn

  public boolean getSplit();
    Code:
       0: aload_0
       1: getfield      #25                 // Field split_:Z
       4: ireturn

  public org.apache.hadoop.hbase.protobuf.generated.HBaseProtos$RegionInfo$Builder setSplit(boolean);
    Code:
       0: aload_0
       1: dup
       2: getfield      #21                 // Field bitField0_:I
       5: bipush        32
       7: ior
       8: putfield      #21                 // Field bitField0_:I
      11: aload_0
      12: iload_1
      13: putfield      #25                 // Field split_:Z
      16: aload_0
      17: invokevirtual #76                 // Method onChanged:()V
      20: aload_0
      21: areturn

  public org.apache.hadoop.hbase.protobuf.generated.HBaseProtos$RegionInfo$Builder clearSplit();
    Code:
       0: aload_0
       1: aload_0
       2: getfield      #21                 // Field bitField0_:I
       5: bipush        -33
       7: iand
       8: putfield      #21                 // Field bitField0_:I
      11: aload_0
      12: iconst_0
      13: putfield      #25                 // Field split_:Z
      16: aload_0
      17: invokevirtual #76                 // Method onChanged:()V
      20: aload_0
      21: areturn

  public boolean hasReplicaId();
    Code:
       0: aload_0
       1: getfield      #21                 // Field bitField0_:I
       4: bipush        64
       6: iand
       7: bipush        64
       9: if_icmpne     16
      12: iconst_1
      13: goto          17
      16: iconst_0
      17: ireturn

  public int getReplicaId();
    Code:
       0: aload_0
       1: getfield      #26                 // Field replicaId_:I
       4: ireturn

  public org.apache.hadoop.hbase.protobuf.generated.HBaseProtos$RegionInfo$Builder setReplicaId(int);
    Code:
       0: aload_0
       1: dup
       2: getfield      #21                 // Field bitField0_:I
       5: bipush        64
       7: ior
       8: putfield      #21                 // Field bitField0_:I
      11: aload_0
      12: iload_1
      13: putfield      #26                 // Field replicaId_:I
      16: aload_0
      17: invokevirtual #76                 // Method onChanged:()V
      20: aload_0
      21: areturn

  public org.apache.hadoop.hbase.protobuf.generated.HBaseProtos$RegionInfo$Builder clearReplicaId();
    Code:
       0: aload_0
       1: aload_0
       2: getfield      #21                 // Field bitField0_:I
       5: bipush        -65
       7: iand
       8: putfield      #21                 // Field bitField0_:I
      11: aload_0
      12: iconst_0
      13: putfield      #26                 // Field replicaId_:I
      16: aload_0
      17: invokevirtual #76                 // Method onChanged:()V
      20: aload_0
      21: areturn

  public com.google.protobuf.GeneratedMessage$Builder clear();
    Code:
       0: aload_0
       1: invokevirtual #94                 // Method clear:()Lorg/apache/hadoop/hbase/protobuf/generated/HBaseProtos$RegionInfo$Builder;
       4: areturn

  public com.google.protobuf.GeneratedMessage$Builder clone();
    Code:
       0: aload_0
       1: invokevirtual #95                 // Method clone:()Lorg/apache/hadoop/hbase/protobuf/generated/HBaseProtos$RegionInfo$Builder;
       4: areturn

  public com.google.protobuf.AbstractMessage$Builder mergeFrom(com.google.protobuf.CodedInputStream, com.google.protobuf.ExtensionRegistryLite) throws java.io.IOException;
    Code:
       0: aload_0
       1: aload_1
       2: aload_2
       3: invokevirtual #96                 // Method mergeFrom:(Lcom/google/protobuf/CodedInputStream;Lcom/google/protobuf/ExtensionRegistryLite;)Lorg/apache/hadoop/hbase/protobuf/generated/HBaseProtos$RegionInfo$Builder;
       6: areturn

  public com.google.protobuf.AbstractMessage$Builder mergeFrom(com.google.protobuf.Message);
    Code:
       0: aload_0
       1: aload_1
       2: invokevirtual #97                 // Method mergeFrom:(Lcom/google/protobuf/Message;)Lorg/apache/hadoop/hbase/protobuf/generated/HBaseProtos$RegionInfo$Builder;
       5: areturn

  public com.google.protobuf.AbstractMessage$Builder clear();
    Code:
       0: aload_0
       1: invokevirtual #94                 // Method clear:()Lorg/apache/hadoop/hbase/protobuf/generated/HBaseProtos$RegionInfo$Builder;
       4: areturn

  public com.google.protobuf.AbstractMessage$Builder clone();
    Code:
       0: aload_0
       1: invokevirtual #95                 // Method clone:()Lorg/apache/hadoop/hbase/protobuf/generated/HBaseProtos$RegionInfo$Builder;
       4: areturn

  public com.google.protobuf.Message$Builder mergeFrom(com.google.protobuf.CodedInputStream, com.google.protobuf.ExtensionRegistryLite) throws java.io.IOException;
    Code:
       0: aload_0
       1: aload_1
       2: aload_2
       3: invokevirtual #96                 // Method mergeFrom:(Lcom/google/protobuf/CodedInputStream;Lcom/google/protobuf/ExtensionRegistryLite;)Lorg/apache/hadoop/hbase/protobuf/generated/HBaseProtos$RegionInfo$Builder;
       6: areturn

  public com.google.protobuf.Message$Builder clone();
    Code:
       0: aload_0
       1: invokevirtual #95                 // Method clone:()Lorg/apache/hadoop/hbase/protobuf/generated/HBaseProtos$RegionInfo$Builder;
       4: areturn

  public com.google.protobuf.Message buildPartial();
    Code:
       0: aload_0
       1: invokevirtual #27                 // Method buildPartial:()Lorg/apache/hadoop/hbase/protobuf/generated/HBaseProtos$RegionInfo;
       4: areturn

  public com.google.protobuf.Message build();
    Code:
       0: aload_0
       1: invokevirtual #98                 // Method build:()Lorg/apache/hadoop/hbase/protobuf/generated/HBaseProtos$RegionInfo;
       4: areturn

  public com.google.protobuf.Message$Builder mergeFrom(com.google.protobuf.Message);
    Code:
       0: aload_0
       1: aload_1
       2: invokevirtual #97                 // Method mergeFrom:(Lcom/google/protobuf/Message;)Lorg/apache/hadoop/hbase/protobuf/generated/HBaseProtos$RegionInfo$Builder;
       5: areturn

  public com.google.protobuf.Message$Builder clear();
    Code:
       0: aload_0
       1: invokevirtual #94                 // Method clear:()Lorg/apache/hadoop/hbase/protobuf/generated/HBaseProtos$RegionInfo$Builder;
       4: areturn

  public com.google.protobuf.MessageLite$Builder mergeFrom(com.google.protobuf.CodedInputStream, com.google.protobuf.ExtensionRegistryLite) throws java.io.IOException;
    Code:
       0: aload_0
       1: aload_1
       2: aload_2
       3: invokevirtual #96                 // Method mergeFrom:(Lcom/google/protobuf/CodedInputStream;Lcom/google/protobuf/ExtensionRegistryLite;)Lorg/apache/hadoop/hbase/protobuf/generated/HBaseProtos$RegionInfo$Builder;
       6: areturn

  public com.google.protobuf.MessageLite$Builder clone();
    Code:
       0: aload_0
       1: invokevirtual #95                 // Method clone:()Lorg/apache/hadoop/hbase/protobuf/generated/HBaseProtos$RegionInfo$Builder;
       4: areturn

  public com.google.protobuf.MessageLite buildPartial();
    Code:
       0: aload_0
       1: invokevirtual #27                 // Method buildPartial:()Lorg/apache/hadoop/hbase/protobuf/generated/HBaseProtos$RegionInfo;
       4: areturn

  public com.google.protobuf.MessageLite build();
    Code:
       0: aload_0
       1: invokevirtual #98                 // Method build:()Lorg/apache/hadoop/hbase/protobuf/generated/HBaseProtos$RegionInfo;
       4: areturn

  public com.google.protobuf.MessageLite$Builder clear();
    Code:
       0: aload_0
       1: invokevirtual #94                 // Method clear:()Lorg/apache/hadoop/hbase/protobuf/generated/HBaseProtos$RegionInfo$Builder;
       4: areturn

  public com.google.protobuf.MessageLite getDefaultInstanceForType();
    Code:
       0: aload_0
       1: invokevirtual #99                 // Method getDefaultInstanceForType:()Lorg/apache/hadoop/hbase/protobuf/generated/HBaseProtos$RegionInfo;
       4: areturn

  public com.google.protobuf.Message getDefaultInstanceForType();
    Code:
       0: aload_0
       1: invokevirtual #99                 // Method getDefaultInstanceForType:()Lorg/apache/hadoop/hbase/protobuf/generated/HBaseProtos$RegionInfo;
       4: areturn

  public com.google.protobuf.AbstractMessageLite$Builder mergeFrom(com.google.protobuf.CodedInputStream, com.google.protobuf.ExtensionRegistryLite) throws java.io.IOException;
    Code:
       0: aload_0
       1: aload_1
       2: aload_2
       3: invokevirtual #96                 // Method mergeFrom:(Lcom/google/protobuf/CodedInputStream;Lcom/google/protobuf/ExtensionRegistryLite;)Lorg/apache/hadoop/hbase/protobuf/generated/HBaseProtos$RegionInfo$Builder;
       6: areturn

  public com.google.protobuf.AbstractMessageLite$Builder clone();
    Code:
       0: aload_0
       1: invokevirtual #95                 // Method clone:()Lorg/apache/hadoop/hbase/protobuf/generated/HBaseProtos$RegionInfo$Builder;
       4: areturn

  public java.lang.Object clone() throws java.lang.CloneNotSupportedException;
    Code:
       0: aload_0
       1: invokevirtual #95                 // Method clone:()Lorg/apache/hadoop/hbase/protobuf/generated/HBaseProtos$RegionInfo$Builder;
       4: areturn

  static org.apache.hadoop.hbase.protobuf.generated.HBaseProtos$RegionInfo$Builder access$5000();
    Code:
       0: invokestatic  #2                  // Method create:()Lorg/apache/hadoop/hbase/protobuf/generated/HBaseProtos$RegionInfo$Builder;
       3: areturn

  org.apache.hadoop.hbase.protobuf.generated.HBaseProtos$RegionInfo$Builder(com.google.protobuf.GeneratedMessage$BuilderParent, org.apache.hadoop.hbase.protobuf.generated.HBaseProtos$1);
    Code:
       0: aload_0
       1: aload_1
       2: invokespecial #1                  // Method "<init>":(Lcom/google/protobuf/GeneratedMessage$BuilderParent;)V
       5: return
}
