Compiled from "HBaseAdmin.java"
class org.apache.hadoop.hbase.client.HBaseAdmin$74 implements java.util.concurrent.Callable<org.apache.hadoop.hbase.shaded.protobuf.generated.AdminProtos$GetRegionInfoResponse$CompactionState> {
  final org.apache.hadoop.hbase.TableName val$tableName;

  final org.apache.hadoop.hbase.shaded.protobuf.generated.AdminProtos$AdminService$BlockingInterface val$masterAdmin;

  final org.apache.hadoop.hbase.ipc.HBaseRpcController val$rpcController;

  final org.apache.hadoop.hbase.client.HBaseAdmin this$0;

  org.apache.hadoop.hbase.client.HBaseAdmin$74(org.apache.hadoop.hbase.client.HBaseAdmin, org.apache.hadoop.hbase.TableName, org.apache.hadoop.hbase.shaded.protobuf.generated.AdminProtos$AdminService$BlockingInterface, org.apache.hadoop.hbase.ipc.HBaseRpcController);
    Code:
       0: aload_0
       1: aload_1
       2: putfield      #1                  // Field this$0:Lorg/apache/hadoop/hbase/client/HBaseAdmin;
       5: aload_0
       6: aload_2
       7: putfield      #2                  // Field val$tableName:Lorg/apache/hadoop/hbase/TableName;
      10: aload_0
      11: aload_3
      12: putfield      #3                  // Field val$masterAdmin:Lorg/apache/hadoop/hbase/shaded/protobuf/generated/AdminProtos$AdminService$BlockingInterface;
      15: aload_0
      16: aload         4
      18: putfield      #4                  // Field val$rpcController:Lorg/apache/hadoop/hbase/ipc/HBaseRpcController;
      21: aload_0
      22: invokespecial #5                  // Method java/lang/Object."<init>":()V
      25: return

  public org.apache.hadoop.hbase.shaded.protobuf.generated.AdminProtos$GetRegionInfoResponse$CompactionState call() throws java.lang.Exception;
    Code:
       0: aload_0
       1: getfield      #2                  // Field val$tableName:Lorg/apache/hadoop/hbase/TableName;
       4: invokestatic  #6                  // InterfaceMethod org/apache/hadoop/hbase/client/RegionInfo.createMobRegionInfo:(Lorg/apache/hadoop/hbase/TableName;)Lorg/apache/hadoop/hbase/client/RegionInfo;
       7: astore_1
       8: aload_1
       9: invokeinterface #7,  1            // InterfaceMethod org/apache/hadoop/hbase/client/RegionInfo.getRegionName:()[B
      14: iconst_1
      15: invokestatic  #8                  // Method org/apache/hadoop/hbase/shaded/protobuf/RequestConverter.buildGetRegionInfoRequest:([BZ)Lorg/apache/hadoop/hbase/shaded/protobuf/generated/AdminProtos$GetRegionInfoRequest;
      18: astore_2
      19: aload_0
      20: getfield      #3                  // Field val$masterAdmin:Lorg/apache/hadoop/hbase/shaded/protobuf/generated/AdminProtos$AdminService$BlockingInterface;
      23: aload_0
      24: getfield      #4                  // Field val$rpcController:Lorg/apache/hadoop/hbase/ipc/HBaseRpcController;
      27: aload_2
      28: invokeinterface #9,  3            // InterfaceMethod org/apache/hadoop/hbase/shaded/protobuf/generated/AdminProtos$AdminService$BlockingInterface.getRegionInfo:(Lorg/apache/hbase/thirdparty/com/google/protobuf/RpcController;Lorg/apache/hadoop/hbase/shaded/protobuf/generated/AdminProtos$GetRegionInfoRequest;)Lorg/apache/hadoop/hbase/shaded/protobuf/generated/AdminProtos$GetRegionInfoResponse;
      33: astore_3
      34: aload_3
      35: invokevirtual #10                 // Method org/apache/hadoop/hbase/shaded/protobuf/generated/AdminProtos$GetRegionInfoResponse.getCompactionState:()Lorg/apache/hadoop/hbase/shaded/protobuf/generated/AdminProtos$GetRegionInfoResponse$CompactionState;
      38: areturn

  public java.lang.Object call() throws java.lang.Exception;
    Code:
       0: aload_0
       1: invokevirtual #11                 // Method call:()Lorg/apache/hadoop/hbase/shaded/protobuf/generated/AdminProtos$GetRegionInfoResponse$CompactionState;
       4: areturn
}
