Compiled from "HBaseTestingUtility.java"
public class org.apache.hadoop.hbase.HBaseTestingUtility$SeenRowTracker {
  int dim;

  int[][][] seenRows;

  byte[] startRow;

  byte[] stopRow;

  public org.apache.hadoop.hbase.HBaseTestingUtility$SeenRowTracker(byte[], byte[]);
    Code:
       0: aload_0
       1: invokespecial #1                  // Method java/lang/Object."<init>":()V
       4: aload_0
       5: bipush        26
       7: putfield      #2                  // Field dim:I
      10: aload_0
      11: aload_0
      12: getfield      #2                  // Field dim:I
      15: aload_0
      16: getfield      #2                  // Field dim:I
      19: aload_0
      20: getfield      #2                  // Field dim:I
      23: multianewarray #3,  3             // class "[[[I"
      27: putfield      #4                  // Field seenRows:[[[I
      30: aload_0
      31: aload_1
      32: putfield      #5                  // Field startRow:[B
      35: aload_0
      36: aload_2
      37: putfield      #6                  // Field stopRow:[B
      40: return

  void reset();
    Code:
       0: getstatic     #7                  // Field org/apache/hadoop/hbase/HBaseTestingUtility.ROWS:[[B
       3: astore_1
       4: aload_1
       5: arraylength
       6: istore_2
       7: iconst_0
       8: istore_3
       9: iload_3
      10: iload_2
      11: if_icmpge     57
      14: aload_1
      15: iload_3
      16: aaload
      17: astore        4
      19: aload_0
      20: getfield      #4                  // Field seenRows:[[[I
      23: aload_0
      24: aload         4
      26: iconst_0
      27: baload
      28: invokevirtual #8                  // Method i:(B)I
      31: aaload
      32: aload_0
      33: aload         4
      35: iconst_1
      36: baload
      37: invokevirtual #8                  // Method i:(B)I
      40: aaload
      41: aload_0
      42: aload         4
      44: iconst_2
      45: baload
      46: invokevirtual #8                  // Method i:(B)I
      49: iconst_0
      50: iastore
      51: iinc          3, 1
      54: goto          9
      57: return

  int i(byte);
    Code:
       0: iload_1
       1: bipush        97
       3: isub
       4: ireturn

  public void addRow(byte[]);
    Code:
       0: aload_0
       1: getfield      #4                  // Field seenRows:[[[I
       4: aload_0
       5: aload_1
       6: iconst_0
       7: baload
       8: invokevirtual #8                  // Method i:(B)I
      11: aaload
      12: aload_0
      13: aload_1
      14: iconst_1
      15: baload
      16: invokevirtual #8                  // Method i:(B)I
      19: aaload
      20: aload_0
      21: aload_1
      22: iconst_2
      23: baload
      24: invokevirtual #8                  // Method i:(B)I
      27: dup2
      28: iaload
      29: iconst_1
      30: iadd
      31: iastore
      32: return

  public void validate();
    Code:
       0: bipush        97
       2: istore_1
       3: iload_1
       4: bipush        122
       6: if_icmpgt     213
       9: bipush        97
      11: istore_2
      12: iload_2
      13: bipush        122
      15: if_icmpgt     205
      18: bipush        97
      20: istore_3
      21: iload_3
      22: bipush        122
      24: if_icmpgt     197
      27: aload_0
      28: getfield      #4                  // Field seenRows:[[[I
      31: aload_0
      32: iload_1
      33: invokevirtual #8                  // Method i:(B)I
      36: aaload
      37: aload_0
      38: iload_2
      39: invokevirtual #8                  // Method i:(B)I
      42: aaload
      43: aload_0
      44: iload_3
      45: invokevirtual #8                  // Method i:(B)I
      48: iaload
      49: istore        4
      51: iconst_0
      52: istore        5
      54: iconst_3
      55: newarray       byte
      57: dup
      58: iconst_0
      59: iload_1
      60: bastore
      61: dup
      62: iconst_1
      63: iload_2
      64: bastore
      65: dup
      66: iconst_2
      67: iload_3
      68: bastore
      69: aload_0
      70: getfield      #5                  // Field startRow:[B
      73: invokestatic  #9                  // Method org/apache/hadoop/hbase/util/Bytes.compareTo:([B[B)I
      76: iflt          107
      79: iconst_3
      80: newarray       byte
      82: dup
      83: iconst_0
      84: iload_1
      85: bastore
      86: dup
      87: iconst_1
      88: iload_2
      89: bastore
      90: dup
      91: iconst_2
      92: iload_3
      93: bastore
      94: aload_0
      95: getfield      #6                  // Field stopRow:[B
      98: invokestatic  #9                  // Method org/apache/hadoop/hbase/util/Bytes.compareTo:([B[B)I
     101: ifge          107
     104: iconst_1
     105: istore        5
     107: iload         4
     109: iload         5
     111: if_icmpeq     189
     114: new           #10                 // class java/lang/String
     117: dup
     118: iconst_3
     119: newarray       byte
     121: dup
     122: iconst_0
     123: iload_1
     124: bastore
     125: dup
     126: iconst_1
     127: iload_2
     128: bastore
     129: dup
     130: iconst_2
     131: iload_3
     132: bastore
     133: getstatic     #11                 // Field java/nio/charset/StandardCharsets.UTF_8:Ljava/nio/charset/Charset;
     136: invokespecial #12                 // Method java/lang/String."<init>":([BLjava/nio/charset/Charset;)V
     139: astore        6
     141: new           #13                 // class java/lang/RuntimeException
     144: dup
     145: new           #14                 // class java/lang/StringBuilder
     148: dup
     149: invokespecial #15                 // Method java/lang/StringBuilder."<init>":()V
     152: ldc           #16                 // String Row:
     154: invokevirtual #17                 // Method java/lang/StringBuilder.append:(Ljava/lang/String;)Ljava/lang/StringBuilder;
     157: aload         6
     159: invokevirtual #17                 // Method java/lang/StringBuilder.append:(Ljava/lang/String;)Ljava/lang/StringBuilder;
     162: ldc           #18                 // String  has a seen count of
     164: invokevirtual #17                 // Method java/lang/StringBuilder.append:(Ljava/lang/String;)Ljava/lang/StringBuilder;
     167: iload         4
     169: invokevirtual #19                 // Method java/lang/StringBuilder.append:(I)Ljava/lang/StringBuilder;
     172: ldc           #20                 // String  instead of
     174: invokevirtual #17                 // Method java/lang/StringBuilder.append:(Ljava/lang/String;)Ljava/lang/StringBuilder;
     177: iload         5
     179: invokevirtual #19                 // Method java/lang/StringBuilder.append:(I)Ljava/lang/StringBuilder;
     182: invokevirtual #21                 // Method java/lang/StringBuilder.toString:()Ljava/lang/String;
     185: invokespecial #22                 // Method java/lang/RuntimeException."<init>":(Ljava/lang/String;)V
     188: athrow
     189: iload_3
     190: iconst_1
     191: iadd
     192: i2b
     193: istore_3
     194: goto          21
     197: iload_2
     198: iconst_1
     199: iadd
     200: i2b
     201: istore_2
     202: goto          12
     205: iload_1
     206: iconst_1
     207: iadd
     208: i2b
     209: istore_1
     210: goto          3
     213: return
}
