Compiled from "HBaseTestingUtility.java"
class org.apache.hadoop.hbase.HBaseTestingUtility$3 implements org.apache.hadoop.hbase.Waiter$ExplainingPredicate<java.io.IOException> {
  final org.apache.hadoop.hbase.TableName val$tableName;

  final org.apache.hadoop.hbase.client.Table val$meta;

  final org.apache.hadoop.hbase.HBaseTestingUtility this$0;

  org.apache.hadoop.hbase.HBaseTestingUtility$3(org.apache.hadoop.hbase.HBaseTestingUtility, org.apache.hadoop.hbase.TableName, org.apache.hadoop.hbase.client.Table);
    Code:
       0: aload_0
       1: aload_1
       2: putfield      #1                  // Field this$0:Lorg/apache/hadoop/hbase/HBaseTestingUtility;
       5: aload_0
       6: aload_2
       7: putfield      #2                  // Field val$tableName:Lorg/apache/hadoop/hbase/TableName;
      10: aload_0
      11: aload_3
      12: putfield      #3                  // Field val$meta:Lorg/apache/hadoop/hbase/client/Table;
      15: aload_0
      16: invokespecial #4                  // Method java/lang/Object."<init>":()V
      19: return

  public java.lang.String explainFailure() throws java.io.IOException;
    Code:
       0: aload_0
       1: getfield      #1                  // Field this$0:Lorg/apache/hadoop/hbase/HBaseTestingUtility;
       4: aload_0
       5: getfield      #2                  // Field val$tableName:Lorg/apache/hadoop/hbase/TableName;
       8: invokevirtual #5                  // Method org/apache/hadoop/hbase/HBaseTestingUtility.explainTableAvailability:(Lorg/apache/hadoop/hbase/TableName;)Ljava/lang/String;
      11: areturn

  public boolean evaluate() throws java.io.IOException;
    Code:
       0: new           #6                  // class org/apache/hadoop/hbase/client/Scan
       3: dup
       4: invokespecial #7                  // Method org/apache/hadoop/hbase/client/Scan."<init>":()V
       7: astore_1
       8: aload_1
       9: getstatic     #8                  // Field org/apache/hadoop/hbase/HConstants.CATALOG_FAMILY:[B
      12: invokevirtual #9                  // Method org/apache/hadoop/hbase/client/Scan.addFamily:([B)Lorg/apache/hadoop/hbase/client/Scan;
      15: pop
      16: iconst_0
      17: istore_2
      18: aload_0
      19: getfield      #3                  // Field val$meta:Lorg/apache/hadoop/hbase/client/Table;
      22: aload_1
      23: invokeinterface #10,  2           // InterfaceMethod org/apache/hadoop/hbase/client/Table.getScanner:(Lorg/apache/hadoop/hbase/client/Scan;)Lorg/apache/hadoop/hbase/client/ResultScanner;
      28: astore_3
      29: aconst_null
      30: astore        4
      32: aload_3
      33: invokeinterface #11,  1           // InterfaceMethod org/apache/hadoop/hbase/client/ResultScanner.next:()Lorg/apache/hadoop/hbase/client/Result;
      38: dup
      39: astore        5
      41: ifnull        333
      44: aload         5
      46: getstatic     #8                  // Field org/apache/hadoop/hbase/HConstants.CATALOG_FAMILY:[B
      49: getstatic     #12                 // Field org/apache/hadoop/hbase/HConstants.REGIONINFO_QUALIFIER:[B
      52: invokevirtual #13                 // Method org/apache/hadoop/hbase/client/Result.getValue:([B[B)[B
      55: astore        6
      57: aload         6
      59: invokestatic  #14                 // Method org/apache/hadoop/hbase/HRegionInfo.parseFromOrNull:([B)Lorg/apache/hadoop/hbase/HRegionInfo;
      62: astore        7
      64: aload         7
      66: ifnull        330
      69: aload         7
      71: invokevirtual #15                 // Method org/apache/hadoop/hbase/HRegionInfo.getTable:()Lorg/apache/hadoop/hbase/TableName;
      74: aload_0
      75: getfield      #2                  // Field val$tableName:Lorg/apache/hadoop/hbase/TableName;
      78: invokevirtual #16                 // Method org/apache/hadoop/hbase/TableName.equals:(Ljava/lang/Object;)Z
      81: ifeq          330
      84: iconst_1
      85: istore_2
      86: aload         5
      88: getstatic     #8                  // Field org/apache/hadoop/hbase/HConstants.CATALOG_FAMILY:[B
      91: getstatic     #17                 // Field org/apache/hadoop/hbase/HConstants.SERVER_QUALIFIER:[B
      94: invokevirtual #13                 // Method org/apache/hadoop/hbase/client/Result.getValue:([B[B)[B
      97: astore        8
      99: aload         8
     101: ifnonnull     146
     104: iconst_0
     105: istore        9
     107: aload_3
     108: ifnull        143
     111: aload         4
     113: ifnull        137
     116: aload_3
     117: invokeinterface #18,  1           // InterfaceMethod org/apache/hadoop/hbase/client/ResultScanner.close:()V
     122: goto          143
     125: astore        10
     127: aload         4
     129: aload         10
     131: invokevirtual #20                 // Method java/lang/Throwable.addSuppressed:(Ljava/lang/Throwable;)V
     134: goto          143
     137: aload_3
     138: invokeinterface #18,  1           // InterfaceMethod org/apache/hadoop/hbase/client/ResultScanner.close:()V
     143: iload         9
     145: ireturn
     146: aload         5
     148: getstatic     #8                  // Field org/apache/hadoop/hbase/HConstants.CATALOG_FAMILY:[B
     151: getstatic     #21                 // Field org/apache/hadoop/hbase/HConstants.STARTCODE_QUALIFIER:[B
     154: invokevirtual #13                 // Method org/apache/hadoop/hbase/client/Result.getValue:([B[B)[B
     157: astore        9
     159: new           #22                 // class java/lang/StringBuilder
     162: dup
     163: invokespecial #23                 // Method java/lang/StringBuilder."<init>":()V
     166: aload         8
     168: invokestatic  #24                 // Method org/apache/hadoop/hbase/util/Bytes.toString:([B)Ljava/lang/String;
     171: ldc           #25                 // String :
     173: ldc           #26                 // String ,
     175: invokevirtual #27                 // Method java/lang/String.replaceFirst:(Ljava/lang/String;Ljava/lang/String;)Ljava/lang/String;
     178: invokevirtual #28                 // Method java/lang/StringBuilder.append:(Ljava/lang/String;)Ljava/lang/StringBuilder;
     181: ldc           #26                 // String ,
     183: invokevirtual #28                 // Method java/lang/StringBuilder.append:(Ljava/lang/String;)Ljava/lang/StringBuilder;
     186: aload         9
     188: invokestatic  #29                 // Method org/apache/hadoop/hbase/util/Bytes.toLong:([B)J
     191: invokevirtual #30                 // Method java/lang/StringBuilder.append:(J)Ljava/lang/StringBuilder;
     194: invokevirtual #31                 // Method java/lang/StringBuilder.toString:()Ljava/lang/String;
     197: invokestatic  #32                 // Method org/apache/hadoop/hbase/ServerName.valueOf:(Ljava/lang/String;)Lorg/apache/hadoop/hbase/ServerName;
     200: astore        10
     202: aload_0
     203: getfield      #1                  // Field this$0:Lorg/apache/hadoop/hbase/HBaseTestingUtility;
     206: invokevirtual #33                 // Method org/apache/hadoop/hbase/HBaseTestingUtility.getHBaseClusterInterface:()Lorg/apache/hadoop/hbase/HBaseCluster;
     209: invokevirtual #34                 // Method org/apache/hadoop/hbase/HBaseCluster.isDistributedCluster:()Z
     212: ifne          272
     215: aload_0
     216: getfield      #1                  // Field this$0:Lorg/apache/hadoop/hbase/HBaseTestingUtility;
     219: invokevirtual #35                 // Method org/apache/hadoop/hbase/HBaseTestingUtility.getHBaseCluster:()Lorg/apache/hadoop/hbase/MiniHBaseCluster;
     222: aload         10
     224: invokevirtual #36                 // Method org/apache/hadoop/hbase/MiniHBaseCluster.isKilledRS:(Lorg/apache/hadoop/hbase/ServerName;)Z
     227: ifeq          272
     230: iconst_0
     231: istore        11
     233: aload_3
     234: ifnull        269
     237: aload         4
     239: ifnull        263
     242: aload_3
     243: invokeinterface #18,  1           // InterfaceMethod org/apache/hadoop/hbase/client/ResultScanner.close:()V
     248: goto          269
     251: astore        12
     253: aload         4
     255: aload         12
     257: invokevirtual #20                 // Method java/lang/Throwable.addSuppressed:(Ljava/lang/Throwable;)V
     260: goto          269
     263: aload_3
     264: invokeinterface #18,  1           // InterfaceMethod org/apache/hadoop/hbase/client/ResultScanner.close:()V
     269: iload         11
     271: ireturn
     272: aload         5
     274: aload         7
     276: invokevirtual #37                 // Method org/apache/hadoop/hbase/HRegionInfo.getReplicaId:()I
     279: invokestatic  #38                 // Method org/apache/hadoop/hbase/master/assignment/RegionStateStore.getRegionState:(Lorg/apache/hadoop/hbase/client/Result;I)Lorg/apache/hadoop/hbase/master/RegionState$State;
     282: getstatic     #39                 // Field org/apache/hadoop/hbase/master/RegionState$State.OPEN:Lorg/apache/hadoop/hbase/master/RegionState$State;
     285: if_acmpeq     330
     288: iconst_0
     289: istore        9
     291: aload_3
     292: ifnull        327
     295: aload         4
     297: ifnull        321
     300: aload_3
     301: invokeinterface #18,  1           // InterfaceMethod org/apache/hadoop/hbase/client/ResultScanner.close:()V
     306: goto          327
     309: astore        10
     311: aload         4
     313: aload         10
     315: invokevirtual #20                 // Method java/lang/Throwable.addSuppressed:(Ljava/lang/Throwable;)V
     318: goto          327
     321: aload_3
     322: invokeinterface #18,  1           // InterfaceMethod org/apache/hadoop/hbase/client/ResultScanner.close:()V
     327: iload         9
     329: ireturn
     330: goto          32
     333: aload_3
     334: ifnull        422
     337: aload         4
     339: ifnull        363
     342: aload_3
     343: invokeinterface #18,  1           // InterfaceMethod org/apache/hadoop/hbase/client/ResultScanner.close:()V
     348: goto          422
     351: astore        5
     353: aload         4
     355: aload         5
     357: invokevirtual #20                 // Method java/lang/Throwable.addSuppressed:(Ljava/lang/Throwable;)V
     360: goto          422
     363: aload_3
     364: invokeinterface #18,  1           // InterfaceMethod org/apache/hadoop/hbase/client/ResultScanner.close:()V
     369: goto          422
     372: astore        5
     374: aload         5
     376: astore        4
     378: aload         5
     380: athrow
     381: astore        13
     383: aload_3
     384: ifnull        419
     387: aload         4
     389: ifnull        413
     392: aload_3
     393: invokeinterface #18,  1           // InterfaceMethod org/apache/hadoop/hbase/client/ResultScanner.close:()V
     398: goto          419
     401: astore        14
     403: aload         4
     405: aload         14
     407: invokevirtual #20                 // Method java/lang/Throwable.addSuppressed:(Ljava/lang/Throwable;)V
     410: goto          419
     413: aload_3
     414: invokeinterface #18,  1           // InterfaceMethod org/apache/hadoop/hbase/client/ResultScanner.close:()V
     419: aload         13
     421: athrow
     422: iload_2
     423: ifne          461
     426: getstatic     #40                 // Field org/apache/hadoop/hbase/HBaseCommonTestingUtility.LOG:Lorg/slf4j/Logger;
     429: new           #22                 // class java/lang/StringBuilder
     432: dup
     433: invokespecial #23                 // Method java/lang/StringBuilder."<init>":()V
     436: ldc           #41                 // String Didn't find the entries for table
     438: invokevirtual #28                 // Method java/lang/StringBuilder.append:(Ljava/lang/String;)Ljava/lang/StringBuilder;
     441: aload_0
     442: getfield      #2                  // Field val$tableName:Lorg/apache/hadoop/hbase/TableName;
     445: invokevirtual #42                 // Method java/lang/StringBuilder.append:(Ljava/lang/Object;)Ljava/lang/StringBuilder;
     448: ldc           #43                 // String  in meta, already deleted?
     450: invokevirtual #28                 // Method java/lang/StringBuilder.append:(Ljava/lang/String;)Ljava/lang/StringBuilder;
     453: invokevirtual #31                 // Method java/lang/StringBuilder.toString:()Ljava/lang/String;
     456: invokeinterface #44,  2           // InterfaceMethod org/slf4j/Logger.warn:(Ljava/lang/String;)V
     461: iload_2
     462: ireturn
    Exception table:
       from    to  target type
         116   122   125   Class java/lang/Throwable
         242   248   251   Class java/lang/Throwable
         300   306   309   Class java/lang/Throwable
         342   348   351   Class java/lang/Throwable
          32   107   372   Class java/lang/Throwable
         146   233   372   Class java/lang/Throwable
         272   291   372   Class java/lang/Throwable
         330   333   372   Class java/lang/Throwable
          32   107   381   any
         146   233   381   any
         272   291   381   any
         330   333   381   any
         392   398   401   Class java/lang/Throwable
         372   383   381   any
}
