Compiled from "HBaseAdmin.java"
class org.apache.hadoop.hbase.client.HBaseAdmin$47 extends org.apache.hadoop.hbase.client.MasterCallable<org.apache.hadoop.hbase.shaded.protobuf.generated.MasterProtos$ModifyNamespaceResponse> {
  final org.apache.hadoop.hbase.NamespaceDescriptor val$descriptor;

  final org.apache.hadoop.hbase.client.HBaseAdmin this$0;

  org.apache.hadoop.hbase.client.HBaseAdmin$47(org.apache.hadoop.hbase.client.HBaseAdmin, org.apache.hadoop.hbase.client.Connection, org.apache.hadoop.hbase.ipc.RpcControllerFactory, org.apache.hadoop.hbase.NamespaceDescriptor);
    Code:
       0: aload_0
       1: aload_1
       2: putfield      #1                  // Field this$0:Lorg/apache/hadoop/hbase/client/HBaseAdmin;
       5: aload_0
       6: aload         4
       8: putfield      #2                  // Field val$descriptor:Lorg/apache/hadoop/hbase/NamespaceDescriptor;
      11: aload_0
      12: aload_2
      13: aload_3
      14: invokespecial #3                  // Method org/apache/hadoop/hbase/client/MasterCallable."<init>":(Lorg/apache/hadoop/hbase/client/Connection;Lorg/apache/hadoop/hbase/ipc/RpcControllerFactory;)V
      17: return

  protected org.apache.hadoop.hbase.shaded.protobuf.generated.MasterProtos$ModifyNamespaceResponse rpcCall() throws java.lang.Exception;
    Code:
       0: aload_0
       1: getfield      #4                  // Field master:Lorg/apache/hadoop/hbase/client/MasterKeepAliveConnection;
       4: aload_0
       5: invokevirtual #5                  // Method getRpcController:()Lorg/apache/hadoop/hbase/ipc/HBaseRpcController;
       8: invokestatic  #6                  // Method org/apache/hadoop/hbase/shaded/protobuf/generated/MasterProtos$ModifyNamespaceRequest.newBuilder:()Lorg/apache/hadoop/hbase/shaded/protobuf/generated/MasterProtos$ModifyNamespaceRequest$Builder;
      11: aload_0
      12: getfield      #2                  // Field val$descriptor:Lorg/apache/hadoop/hbase/NamespaceDescriptor;
      15: invokestatic  #7                  // Method org/apache/hadoop/hbase/shaded/protobuf/ProtobufUtil.toProtoNamespaceDescriptor:(Lorg/apache/hadoop/hbase/NamespaceDescriptor;)Lorg/apache/hadoop/hbase/shaded/protobuf/generated/HBaseProtos$NamespaceDescriptor;
      18: invokevirtual #8                  // Method org/apache/hadoop/hbase/shaded/protobuf/generated/MasterProtos$ModifyNamespaceRequest$Builder.setNamespaceDescriptor:(Lorg/apache/hadoop/hbase/shaded/protobuf/generated/HBaseProtos$NamespaceDescriptor;)Lorg/apache/hadoop/hbase/shaded/protobuf/generated/MasterProtos$ModifyNamespaceRequest$Builder;
      21: invokevirtual #9                  // Method org/apache/hadoop/hbase/shaded/protobuf/generated/MasterProtos$ModifyNamespaceRequest$Builder.build:()Lorg/apache/hadoop/hbase/shaded/protobuf/generated/MasterProtos$ModifyNamespaceRequest;
      24: invokeinterface #10,  3           // InterfaceMethod org/apache/hadoop/hbase/client/MasterKeepAliveConnection.modifyNamespace:(Lorg/apache/hbase/thirdparty/com/google/protobuf/RpcController;Lorg/apache/hadoop/hbase/shaded/protobuf/generated/MasterProtos$ModifyNamespaceRequest;)Lorg/apache/hadoop/hbase/shaded/protobuf/generated/MasterProtos$ModifyNamespaceResponse;
      29: areturn

  protected java.lang.Object rpcCall() throws java.lang.Exception;
    Code:
       0: aload_0
       1: invokevirtual #11                 // Method rpcCall:()Lorg/apache/hadoop/hbase/shaded/protobuf/generated/MasterProtos$ModifyNamespaceResponse;
       4: areturn
}
