Compiled from "HBaseAdmin.java"
class org.apache.hadoop.hbase.client.HBaseAdmin$TruncateTableFuture extends org.apache.hadoop.hbase.client.HBaseAdmin$TableFuture<java.lang.Void> {
  public org.apache.hadoop.hbase.client.HBaseAdmin$TruncateTableFuture(org.apache.hadoop.hbase.client.HBaseAdmin, org.apache.hadoop.hbase.TableName, boolean, org.apache.hadoop.hbase.shaded.protobuf.generated.MasterProtos$TruncateTableResponse);
    Code:
       0: aload_0
       1: aload_1
       2: aload_2
       3: aload         4
       5: ifnull        27
       8: aload         4
      10: invokevirtual #1                  // Method org/apache/hadoop/hbase/shaded/protobuf/generated/MasterProtos$TruncateTableResponse.hasProcId:()Z
      13: ifeq          27
      16: aload         4
      18: invokevirtual #2                  // Method org/apache/hadoop/hbase/shaded/protobuf/generated/MasterProtos$TruncateTableResponse.getProcId:()J
      21: invokestatic  #3                  // Method java/lang/Long.valueOf:(J)Ljava/lang/Long;
      24: goto          28
      27: aconst_null
      28: invokespecial #4                  // Method org/apache/hadoop/hbase/client/HBaseAdmin$TableFuture."<init>":(Lorg/apache/hadoop/hbase/client/HBaseAdmin;Lorg/apache/hadoop/hbase/TableName;Ljava/lang/Long;)V
      31: aload_0
      32: iload_3
      33: putfield      #5                  // Field preserveSplits:Z
      36: return

  public java.lang.String getOperationType();
    Code:
       0: ldc           #6                  // String TRUNCATE
       2: areturn

  protected java.lang.Void waitOperationResult(long) throws java.io.IOException, java.util.concurrent.TimeoutException;
    Code:
       0: aload_0
       1: lload_1
       2: invokevirtual #7                  // Method waitForTableEnabled:(J)V
       5: aload_0
       6: getfield      #5                  // Field preserveSplits:Z
       9: ifeq          26
      12: aload_0
      13: invokevirtual #8                  // Method getAdmin:()Lorg/apache/hadoop/hbase/client/HBaseAdmin;
      16: aload_0
      17: invokevirtual #9                  // Method getTableName:()Lorg/apache/hadoop/hbase/TableName;
      20: invokestatic  #10                 // Method org/apache/hadoop/hbase/client/HBaseAdmin.access$300:(Lorg/apache/hadoop/hbase/client/HBaseAdmin;Lorg/apache/hadoop/hbase/TableName;)[[B
      23: goto          30
      26: aconst_null
      27: checkcast     #11                 // class "[[B"
      30: astore_3
      31: aload_0
      32: lload_1
      33: aload_3
      34: invokevirtual #12                 // Method waitForAllRegionsOnline:(J[[B)V
      37: aconst_null
      38: areturn

  protected java.lang.Object waitOperationResult(long) throws java.io.IOException, java.util.concurrent.TimeoutException;
    Code:
       0: aload_0
       1: lload_1
       2: invokevirtual #13                 // Method waitOperationResult:(J)Ljava/lang/Void;
       5: areturn
}
