Compiled from "HBaseAdmin.java"
class org.apache.hadoop.hbase.client.HBaseAdmin$52 extends org.apache.hadoop.hbase.client.MasterCallable<java.lang.String[]> {
  final org.apache.hadoop.hbase.client.HBaseAdmin this$0;

  org.apache.hadoop.hbase.client.HBaseAdmin$52(org.apache.hadoop.hbase.client.HBaseAdmin, org.apache.hadoop.hbase.client.Connection, org.apache.hadoop.hbase.ipc.RpcControllerFactory);
    Code:
       0: aload_0
       1: aload_1
       2: putfield      #1                  // Field this$0:Lorg/apache/hadoop/hbase/client/HBaseAdmin;
       5: aload_0
       6: aload_2
       7: aload_3
       8: invokespecial #2                  // Method org/apache/hadoop/hbase/client/MasterCallable."<init>":(Lorg/apache/hadoop/hbase/client/Connection;Lorg/apache/hadoop/hbase/ipc/RpcControllerFactory;)V
      11: return

  protected java.lang.String[] rpcCall() throws java.lang.Exception;
    Code:
       0: aload_0
       1: getfield      #3                  // Field master:Lorg/apache/hadoop/hbase/client/MasterKeepAliveConnection;
       4: aload_0
       5: invokevirtual #4                  // Method getRpcController:()Lorg/apache/hadoop/hbase/ipc/HBaseRpcController;
       8: invokestatic  #5                  // Method org/apache/hadoop/hbase/shaded/protobuf/generated/MasterProtos$ListNamespacesRequest.newBuilder:()Lorg/apache/hadoop/hbase/shaded/protobuf/generated/MasterProtos$ListNamespacesRequest$Builder;
      11: invokevirtual #6                  // Method org/apache/hadoop/hbase/shaded/protobuf/generated/MasterProtos$ListNamespacesRequest$Builder.build:()Lorg/apache/hadoop/hbase/shaded/protobuf/generated/MasterProtos$ListNamespacesRequest;
      14: invokeinterface #7,  3            // InterfaceMethod org/apache/hadoop/hbase/client/MasterKeepAliveConnection.listNamespaces:(Lorg/apache/hbase/thirdparty/com/google/protobuf/RpcController;Lorg/apache/hadoop/hbase/shaded/protobuf/generated/MasterProtos$ListNamespacesRequest;)Lorg/apache/hadoop/hbase/shaded/protobuf/generated/MasterProtos$ListNamespacesResponse;
      19: invokevirtual #8                  // Method org/apache/hadoop/hbase/shaded/protobuf/generated/MasterProtos$ListNamespacesResponse.getNamespaceNameList:()Lorg/apache/hbase/thirdparty/com/google/protobuf/ProtocolStringList;
      22: astore_1
      23: aload_1
      24: aload_1
      25: invokeinterface #9,  1            // InterfaceMethod java/util/List.size:()I
      30: anewarray     #10                 // class java/lang/String
      33: invokeinterface #11,  2           // InterfaceMethod java/util/List.toArray:([Ljava/lang/Object;)[Ljava/lang/Object;
      38: checkcast     #12                 // class "[Ljava/lang/String;"
      41: areturn

  protected java.lang.Object rpcCall() throws java.lang.Exception;
    Code:
       0: aload_0
       1: invokevirtual #13                 // Method rpcCall:()[Ljava/lang/String;
       4: areturn
}
