Compiled from "HBaseAdmin.java"
class org.apache.hadoop.hbase.client.HBaseAdmin$DeleteTableFuture extends org.apache.hadoop.hbase.client.HBaseAdmin$TableFuture<java.lang.Void> {
  public org.apache.hadoop.hbase.client.HBaseAdmin$DeleteTableFuture(org.apache.hadoop.hbase.client.HBaseAdmin, org.apache.hadoop.hbase.TableName, org.apache.hadoop.hbase.shaded.protobuf.generated.MasterProtos$DeleteTableResponse);
    Code:
       0: aload_0
       1: aload_1
       2: aload_2
       3: aload_3
       4: ifnull        24
       7: aload_3
       8: invokevirtual #1                  // Method org/apache/hadoop/hbase/shaded/protobuf/generated/MasterProtos$DeleteTableResponse.hasProcId:()Z
      11: ifeq          24
      14: aload_3
      15: invokevirtual #2                  // Method org/apache/hadoop/hbase/shaded/protobuf/generated/MasterProtos$DeleteTableResponse.getProcId:()J
      18: invokestatic  #3                  // Method java/lang/Long.valueOf:(J)Ljava/lang/Long;
      21: goto          25
      24: aconst_null
      25: invokespecial #4                  // Method org/apache/hadoop/hbase/client/HBaseAdmin$TableFuture."<init>":(Lorg/apache/hadoop/hbase/client/HBaseAdmin;Lorg/apache/hadoop/hbase/TableName;Ljava/lang/Long;)V
      28: return

  public java.lang.String getOperationType();
    Code:
       0: ldc           #5                  // String DELETE
       2: areturn

  protected java.lang.Void waitOperationResult(long) throws java.io.IOException, java.util.concurrent.TimeoutException;
    Code:
       0: aload_0
       1: lload_1
       2: invokevirtual #6                  // Method waitTableNotFound:(J)V
       5: aconst_null
       6: areturn

  protected java.lang.Void postOperationResult(java.lang.Void, long) throws java.io.IOException, java.util.concurrent.TimeoutException;
    Code:
       0: aload_0
       1: invokevirtual #7                  // Method getAdmin:()Lorg/apache/hadoop/hbase/client/HBaseAdmin;
       4: invokevirtual #8                  // Method org/apache/hadoop/hbase/client/HBaseAdmin.getConnection:()Lorg/apache/hadoop/hbase/client/Connection;
       7: checkcast     #9                  // class org/apache/hadoop/hbase/client/ClusterConnection
      10: aload_0
      11: invokevirtual #10                 // Method getTableName:()Lorg/apache/hadoop/hbase/TableName;
      14: invokeinterface #11,  2           // InterfaceMethod org/apache/hadoop/hbase/client/ClusterConnection.clearRegionCache:(Lorg/apache/hadoop/hbase/TableName;)V
      19: aload_0
      20: aload_1
      21: lload_2
      22: invokespecial #12                 // Method org/apache/hadoop/hbase/client/HBaseAdmin$TableFuture.postOperationResult:(Ljava/lang/Object;J)Ljava/lang/Object;
      25: checkcast     #13                 // class java/lang/Void
      28: areturn

  protected java.lang.Object postOperationResult(java.lang.Object, long) throws java.io.IOException, java.util.concurrent.TimeoutException;
    Code:
       0: aload_0
       1: aload_1
       2: checkcast     #13                 // class java/lang/Void
       5: lload_2
       6: invokevirtual #14                 // Method postOperationResult:(Ljava/lang/Void;J)Ljava/lang/Void;
       9: areturn

  protected java.lang.Object waitOperationResult(long) throws java.io.IOException, java.util.concurrent.TimeoutException;
    Code:
       0: aload_0
       1: lload_1
       2: invokevirtual #15                 // Method waitOperationResult:(J)Ljava/lang/Void;
       5: areturn
}
