Compiled from "HBaseTestingUtility.java"
class org.apache.hadoop.hbase.HBaseTestingUtility$PortAllocator {
  public org.apache.hadoop.hbase.HBaseTestingUtility$PortAllocator(java.util.Random);
    Code:
       0: aload_0
       1: invokespecial #1                  // Method java/lang/Object."<init>":()V
       4: aload_0
       5: new           #2                  // class java/util/HashSet
       8: dup
       9: invokespecial #3                  // Method java/util/HashSet."<init>":()V
      12: putfield      #4                  // Field takenRandomPorts:Ljava/util/Set;
      15: aload_0
      16: aload_1
      17: putfield      #5                  // Field random:Ljava/util/Random;
      20: aload_0
      21: new           #6                  // class org/apache/hadoop/hbase/HBaseTestingUtility$PortAllocator$1
      24: dup
      25: aload_0
      26: invokespecial #7                  // Method org/apache/hadoop/hbase/HBaseTestingUtility$PortAllocator$1."<init>":(Lorg/apache/hadoop/hbase/HBaseTestingUtility$PortAllocator;)V
      29: putfield      #8                  // Field portChecker:Lorg/apache/hadoop/hbase/HBaseTestingUtility$PortAllocator$AvailablePortChecker;
      32: return

  public org.apache.hadoop.hbase.HBaseTestingUtility$PortAllocator(java.util.Random, org.apache.hadoop.hbase.HBaseTestingUtility$PortAllocator$AvailablePortChecker);
    Code:
       0: aload_0
       1: invokespecial #1                  // Method java/lang/Object."<init>":()V
       4: aload_0
       5: new           #2                  // class java/util/HashSet
       8: dup
       9: invokespecial #3                  // Method java/util/HashSet."<init>":()V
      12: putfield      #4                  // Field takenRandomPorts:Ljava/util/Set;
      15: aload_0
      16: aload_1
      17: putfield      #5                  // Field random:Ljava/util/Random;
      20: aload_0
      21: aload_2
      22: putfield      #8                  // Field portChecker:Lorg/apache/hadoop/hbase/HBaseTestingUtility$PortAllocator$AvailablePortChecker;
      25: return

  public int randomFreePort();
    Code:
       0: iconst_0
       1: istore_1
       2: aload_0
       3: invokespecial #9                  // Method randomPort:()I
       6: istore_1
       7: aload_0
       8: getfield      #4                  // Field takenRandomPorts:Ljava/util/Set;
      11: iload_1
      12: invokestatic  #10                 // Method java/lang/Integer.valueOf:(I)Ljava/lang/Integer;
      15: invokeinterface #11,  2           // InterfaceMethod java/util/Set.contains:(Ljava/lang/Object;)Z
      20: ifeq          28
      23: iconst_0
      24: istore_1
      25: goto          57
      28: aload_0
      29: getfield      #4                  // Field takenRandomPorts:Ljava/util/Set;
      32: iload_1
      33: invokestatic  #10                 // Method java/lang/Integer.valueOf:(I)Ljava/lang/Integer;
      36: invokeinterface #12,  2           // InterfaceMethod java/util/Set.add:(Ljava/lang/Object;)Z
      41: pop
      42: aload_0
      43: getfield      #8                  // Field portChecker:Lorg/apache/hadoop/hbase/HBaseTestingUtility$PortAllocator$AvailablePortChecker;
      46: iload_1
      47: invokeinterface #13,  2           // InterfaceMethod org/apache/hadoop/hbase/HBaseTestingUtility$PortAllocator$AvailablePortChecker.available:(I)Z
      52: ifne          57
      55: iconst_0
      56: istore_1
      57: iload_1
      58: ifeq          2
      61: iload_1
      62: ireturn
}
