Compiled from "HBaseAdmin.java"
class org.apache.hadoop.hbase.client.HBaseAdmin$104 {
  static final int[] $SwitchMap$org$apache$hadoop$hbase$client$CompactType;

  static final int[] $SwitchMap$org$apache$hadoop$hbase$shaded$protobuf$generated$AdminProtos$GetRegionInfoResponse$CompactionState;

  static {};
    Code:
       0: invokestatic  #1                  // Method org/apache/hadoop/hbase/shaded/protobuf/generated/AdminProtos$GetRegionInfoResponse$CompactionState.values:()[Lorg/apache/hadoop/hbase/shaded/protobuf/generated/AdminProtos$GetRegionInfoResponse$CompactionState;
       3: arraylength
       4: newarray       int
       6: putstatic     #2                  // Field $SwitchMap$org$apache$hadoop$hbase$shaded$protobuf$generated$AdminProtos$GetRegionInfoResponse$CompactionState:[I
       9: getstatic     #2                  // Field $SwitchMap$org$apache$hadoop$hbase$shaded$protobuf$generated$AdminProtos$GetRegionInfoResponse$CompactionState:[I
      12: getstatic     #3                  // Field org/apache/hadoop/hbase/shaded/protobuf/generated/AdminProtos$GetRegionInfoResponse$CompactionState.MAJOR_AND_MINOR:Lorg/apache/hadoop/hbase/shaded/protobuf/generated/AdminProtos$GetRegionInfoResponse$CompactionState;
      15: invokevirtual #4                  // Method org/apache/hadoop/hbase/shaded/protobuf/generated/AdminProtos$GetRegionInfoResponse$CompactionState.ordinal:()I
      18: iconst_1
      19: iastore
      20: goto          24
      23: astore_0
      24: getstatic     #2                  // Field $SwitchMap$org$apache$hadoop$hbase$shaded$protobuf$generated$AdminProtos$GetRegionInfoResponse$CompactionState:[I
      27: getstatic     #6                  // Field org/apache/hadoop/hbase/shaded/protobuf/generated/AdminProtos$GetRegionInfoResponse$CompactionState.MAJOR:Lorg/apache/hadoop/hbase/shaded/protobuf/generated/AdminProtos$GetRegionInfoResponse$CompactionState;
      30: invokevirtual #4                  // Method org/apache/hadoop/hbase/shaded/protobuf/generated/AdminProtos$GetRegionInfoResponse$CompactionState.ordinal:()I
      33: iconst_2
      34: iastore
      35: goto          39
      38: astore_0
      39: getstatic     #2                  // Field $SwitchMap$org$apache$hadoop$hbase$shaded$protobuf$generated$AdminProtos$GetRegionInfoResponse$CompactionState:[I
      42: getstatic     #7                  // Field org/apache/hadoop/hbase/shaded/protobuf/generated/AdminProtos$GetRegionInfoResponse$CompactionState.MINOR:Lorg/apache/hadoop/hbase/shaded/protobuf/generated/AdminProtos$GetRegionInfoResponse$CompactionState;
      45: invokevirtual #4                  // Method org/apache/hadoop/hbase/shaded/protobuf/generated/AdminProtos$GetRegionInfoResponse$CompactionState.ordinal:()I
      48: iconst_3
      49: iastore
      50: goto          54
      53: astore_0
      54: getstatic     #2                  // Field $SwitchMap$org$apache$hadoop$hbase$shaded$protobuf$generated$AdminProtos$GetRegionInfoResponse$CompactionState:[I
      57: getstatic     #8                  // Field org/apache/hadoop/hbase/shaded/protobuf/generated/AdminProtos$GetRegionInfoResponse$CompactionState.NONE:Lorg/apache/hadoop/hbase/shaded/protobuf/generated/AdminProtos$GetRegionInfoResponse$CompactionState;
      60: invokevirtual #4                  // Method org/apache/hadoop/hbase/shaded/protobuf/generated/AdminProtos$GetRegionInfoResponse$CompactionState.ordinal:()I
      63: iconst_4
      64: iastore
      65: goto          69
      68: astore_0
      69: invokestatic  #9                  // Method org/apache/hadoop/hbase/client/CompactType.values:()[Lorg/apache/hadoop/hbase/client/CompactType;
      72: arraylength
      73: newarray       int
      75: putstatic     #10                 // Field $SwitchMap$org$apache$hadoop$hbase$client$CompactType:[I
      78: getstatic     #10                 // Field $SwitchMap$org$apache$hadoop$hbase$client$CompactType:[I
      81: getstatic     #11                 // Field org/apache/hadoop/hbase/client/CompactType.MOB:Lorg/apache/hadoop/hbase/client/CompactType;
      84: invokevirtual #12                 // Method org/apache/hadoop/hbase/client/CompactType.ordinal:()I
      87: iconst_1
      88: iastore
      89: goto          93
      92: astore_0
      93: getstatic     #10                 // Field $SwitchMap$org$apache$hadoop$hbase$client$CompactType:[I
      96: getstatic     #13                 // Field org/apache/hadoop/hbase/client/CompactType.NORMAL:Lorg/apache/hadoop/hbase/client/CompactType;
      99: invokevirtual #12                 // Method org/apache/hadoop/hbase/client/CompactType.ordinal:()I
     102: iconst_2
     103: iastore
     104: goto          108
     107: astore_0
     108: return
    Exception table:
       from    to  target type
           9    20    23   Class java/lang/NoSuchFieldError
          24    35    38   Class java/lang/NoSuchFieldError
          39    50    53   Class java/lang/NoSuchFieldError
          54    65    68   Class java/lang/NoSuchFieldError
          78    89    92   Class java/lang/NoSuchFieldError
          93   104   107   Class java/lang/NoSuchFieldError
}
