Compiled from "HBaseTestingUtility.java"
class org.apache.hadoop.hbase.HBaseTestingUtility$PortAllocator$1 implements org.apache.hadoop.hbase.HBaseTestingUtility$PortAllocator$AvailablePortChecker {
  final org.apache.hadoop.hbase.HBaseTestingUtility$PortAllocator this$0;

  org.apache.hadoop.hbase.HBaseTestingUtility$PortAllocator$1(org.apache.hadoop.hbase.HBaseTestingUtility$PortAllocator);
    Code:
       0: aload_0
       1: aload_1
       2: putfield      #1                  // Field this$0:Lorg/apache/hadoop/hbase/HBaseTestingUtility$PortAllocator;
       5: aload_0
       6: invokespecial #2                  // Method java/lang/Object."<init>":()V
       9: return

  public boolean available(int);
    Code:
       0: new           #3                  // class java/net/ServerSocket
       3: dup
       4: iload_1
       5: invokespecial #4                  // Method java/net/ServerSocket."<init>":(I)V
       8: astore_2
       9: aload_2
      10: invokevirtual #5                  // Method java/net/ServerSocket.close:()V
      13: iconst_1
      14: ireturn
      15: astore_2
      16: iconst_0
      17: ireturn
    Exception table:
       from    to  target type
           0    14    15   Class java/io/IOException
}
