Compiled from "HBaseAdmin.java"
class org.apache.hadoop.hbase.client.HBaseAdmin$99 extends org.apache.hadoop.hbase.client.MasterCallable<org.apache.hadoop.hbase.quotas.SpaceQuotaSnapshot> {
  final org.apache.hadoop.hbase.TableName val$tableName;

  final org.apache.hadoop.hbase.client.HBaseAdmin this$0;

  org.apache.hadoop.hbase.client.HBaseAdmin$99(org.apache.hadoop.hbase.client.HBaseAdmin, org.apache.hadoop.hbase.client.Connection, org.apache.hadoop.hbase.ipc.RpcControllerFactory, org.apache.hadoop.hbase.TableName);
    Code:
       0: aload_0
       1: aload_1
       2: putfield      #1                  // Field this$0:Lorg/apache/hadoop/hbase/client/HBaseAdmin;
       5: aload_0
       6: aload         4
       8: putfield      #2                  // Field val$tableName:Lorg/apache/hadoop/hbase/TableName;
      11: aload_0
      12: aload_2
      13: aload_3
      14: invokespecial #3                  // Method org/apache/hadoop/hbase/client/MasterCallable."<init>":(Lorg/apache/hadoop/hbase/client/Connection;Lorg/apache/hadoop/hbase/ipc/RpcControllerFactory;)V
      17: return

  protected org.apache.hadoop.hbase.quotas.SpaceQuotaSnapshot rpcCall() throws java.lang.Exception;
    Code:
       0: aload_0
       1: getfield      #4                  // Field master:Lorg/apache/hadoop/hbase/client/MasterKeepAliveConnection;
       4: aload_0
       5: invokevirtual #5                  // Method getRpcController:()Lorg/apache/hadoop/hbase/ipc/HBaseRpcController;
       8: invokestatic  #6                  // Method org/apache/hadoop/hbase/shaded/protobuf/RequestConverter.buildGetQuotaStatesRequest:()Lorg/apache/hadoop/hbase/shaded/protobuf/generated/QuotaProtos$GetQuotaStatesRequest;
      11: invokeinterface #7,  3            // InterfaceMethod org/apache/hadoop/hbase/client/MasterKeepAliveConnection.getQuotaStates:(Lorg/apache/hbase/thirdparty/com/google/protobuf/RpcController;Lorg/apache/hadoop/hbase/shaded/protobuf/generated/QuotaProtos$GetQuotaStatesRequest;)Lorg/apache/hadoop/hbase/shaded/protobuf/generated/QuotaProtos$GetQuotaStatesResponse;
      16: astore_1
      17: aload_0
      18: getfield      #2                  // Field val$tableName:Lorg/apache/hadoop/hbase/TableName;
      21: invokestatic  #8                  // Method org/apache/hadoop/hbase/shaded/protobuf/ProtobufUtil.toProtoTableName:(Lorg/apache/hadoop/hbase/TableName;)Lorg/apache/hadoop/hbase/shaded/protobuf/generated/HBaseProtos$TableName;
      24: astore_2
      25: aload_1
      26: invokevirtual #9                  // Method org/apache/hadoop/hbase/shaded/protobuf/generated/QuotaProtos$GetQuotaStatesResponse.getTableSnapshotsList:()Ljava/util/List;
      29: invokeinterface #10,  1           // InterfaceMethod java/util/List.iterator:()Ljava/util/Iterator;
      34: astore_3
      35: aload_3
      36: invokeinterface #11,  1           // InterfaceMethod java/util/Iterator.hasNext:()Z
      41: ifeq          79
      44: aload_3
      45: invokeinterface #12,  1           // InterfaceMethod java/util/Iterator.next:()Ljava/lang/Object;
      50: checkcast     #13                 // class org/apache/hadoop/hbase/shaded/protobuf/generated/QuotaProtos$GetQuotaStatesResponse$TableQuotaSnapshot
      53: astore        4
      55: aload_2
      56: aload         4
      58: invokevirtual #14                 // Method org/apache/hadoop/hbase/shaded/protobuf/generated/QuotaProtos$GetQuotaStatesResponse$TableQuotaSnapshot.getTableName:()Lorg/apache/hadoop/hbase/shaded/protobuf/generated/HBaseProtos$TableName;
      61: invokevirtual #15                 // Method org/apache/hadoop/hbase/shaded/protobuf/generated/HBaseProtos$TableName.equals:(Ljava/lang/Object;)Z
      64: ifeq          76
      67: aload         4
      69: invokevirtual #16                 // Method org/apache/hadoop/hbase/shaded/protobuf/generated/QuotaProtos$GetQuotaStatesResponse$TableQuotaSnapshot.getSnapshot:()Lorg/apache/hadoop/hbase/shaded/protobuf/generated/QuotaProtos$SpaceQuotaSnapshot;
      72: invokestatic  #17                 // Method org/apache/hadoop/hbase/quotas/SpaceQuotaSnapshot.toSpaceQuotaSnapshot:(Lorg/apache/hadoop/hbase/shaded/protobuf/generated/QuotaProtos$SpaceQuotaSnapshot;)Lorg/apache/hadoop/hbase/quotas/SpaceQuotaSnapshot;
      75: areturn
      76: goto          35
      79: aconst_null
      80: areturn

  protected java.lang.Object rpcCall() throws java.lang.Exception;
    Code:
       0: aload_0
       1: invokevirtual #18                 // Method rpcCall:()Lorg/apache/hadoop/hbase/quotas/SpaceQuotaSnapshot;
       4: areturn
}
