Compiled from "HBaseAdmin.java"
class org.apache.hadoop.hbase.client.HBaseAdmin$90 extends org.apache.hadoop.hbase.client.MasterCallable<java.lang.Void> {
  final org.apache.hadoop.hbase.ServerName val$server;

  final java.util.List val$encodedRegionNames;

  final org.apache.hadoop.hbase.client.HBaseAdmin this$0;

  org.apache.hadoop.hbase.client.HBaseAdmin$90(org.apache.hadoop.hbase.client.HBaseAdmin, org.apache.hadoop.hbase.client.Connection, org.apache.hadoop.hbase.ipc.RpcControllerFactory, org.apache.hadoop.hbase.ServerName, java.util.List);
    Code:
       0: aload_0
       1: aload_1
       2: putfield      #1                  // Field this$0:Lorg/apache/hadoop/hbase/client/HBaseAdmin;
       5: aload_0
       6: aload         4
       8: putfield      #2                  // Field val$server:Lorg/apache/hadoop/hbase/ServerName;
      11: aload_0
      12: aload         5
      14: putfield      #3                  // Field val$encodedRegionNames:Ljava/util/List;
      17: aload_0
      18: aload_2
      19: aload_3
      20: invokespecial #4                  // Method org/apache/hadoop/hbase/client/MasterCallable."<init>":(Lorg/apache/hadoop/hbase/client/Connection;Lorg/apache/hadoop/hbase/ipc/RpcControllerFactory;)V
      23: return

  public java.lang.Void rpcCall() throws org.apache.hbase.thirdparty.com.google.protobuf.ServiceException;
    Code:
       0: aload_0
       1: getfield      #5                  // Field master:Lorg/apache/hadoop/hbase/client/MasterKeepAliveConnection;
       4: aload_0
       5: invokevirtual #6                  // Method getRpcController:()Lorg/apache/hadoop/hbase/ipc/HBaseRpcController;
       8: aload_0
       9: getfield      #2                  // Field val$server:Lorg/apache/hadoop/hbase/ServerName;
      12: aload_0
      13: getfield      #3                  // Field val$encodedRegionNames:Ljava/util/List;
      16: invokestatic  #7                  // Method org/apache/hadoop/hbase/shaded/protobuf/RequestConverter.buildRecommissionRegionServerRequest:(Lorg/apache/hadoop/hbase/ServerName;Ljava/util/List;)Lorg/apache/hadoop/hbase/shaded/protobuf/generated/MasterProtos$RecommissionRegionServerRequest;
      19: invokeinterface #8,  3            // InterfaceMethod org/apache/hadoop/hbase/client/MasterKeepAliveConnection.recommissionRegionServer:(Lorg/apache/hbase/thirdparty/com/google/protobuf/RpcController;Lorg/apache/hadoop/hbase/shaded/protobuf/generated/MasterProtos$RecommissionRegionServerRequest;)Lorg/apache/hadoop/hbase/shaded/protobuf/generated/MasterProtos$RecommissionRegionServerResponse;
      24: pop
      25: aconst_null
      26: areturn

  public java.lang.Object rpcCall() throws java.lang.Exception;
    Code:
       0: aload_0
       1: invokevirtual #9                  // Method rpcCall:()Ljava/lang/Void;
       4: areturn
}
