Compiled from "HConnectionTestingUtility.java"
public class org.apache.hadoop.hbase.client.HConnectionTestingUtility {
  public org.apache.hadoop.hbase.client.HConnectionTestingUtility();
    Code:
       0: aload_0
       1: invokespecial #1                  // Method java/lang/Object."<init>":()V
       4: return

  public static org.apache.hadoop.hbase.client.ClusterConnection getMockedConnection(org.apache.hadoop.conf.Configuration) throws org.apache.hadoop.hbase.ZooKeeperConnectionException;
    Code:
       0: ldc           #2                  // class org/apache/hadoop/hbase/client/ConnectionImplementation
       2: invokestatic  #3                  // Method org/mockito/Mockito.mock:(Ljava/lang/Class;)Ljava/lang/Object;
       5: checkcast     #2                  // class org/apache/hadoop/hbase/client/ConnectionImplementation
       8: astore_1
       9: aload_1
      10: invokevirtual #4                  // Method org/apache/hadoop/hbase/client/ConnectionImplementation.getConfiguration:()Lorg/apache/hadoop/conf/Configuration;
      13: invokestatic  #5                  // Method org/mockito/Mockito.when:(Ljava/lang/Object;)Lorg/mockito/stubbing/OngoingStubbing;
      16: aload_0
      17: invokeinterface #6,  2            // InterfaceMethod org/mockito/stubbing/OngoingStubbing.thenReturn:(Ljava/lang/Object;)Lorg/mockito/stubbing/OngoingStubbing;
      22: pop
      23: aload_1
      24: invokevirtual #7                  // Method org/apache/hadoop/hbase/client/ConnectionImplementation.getRpcControllerFactory:()Lorg/apache/hadoop/hbase/ipc/RpcControllerFactory;
      27: invokestatic  #5                  // Method org/mockito/Mockito.when:(Ljava/lang/Object;)Lorg/mockito/stubbing/OngoingStubbing;
      30: ldc           #8                  // class org/apache/hadoop/hbase/ipc/RpcControllerFactory
      32: invokestatic  #3                  // Method org/mockito/Mockito.mock:(Ljava/lang/Class;)Ljava/lang/Object;
      35: invokeinterface #6,  2            // InterfaceMethod org/mockito/stubbing/OngoingStubbing.thenReturn:(Ljava/lang/Object;)Lorg/mockito/stubbing/OngoingStubbing;
      40: pop
      41: new           #9                  // class org/apache/hadoop/hbase/client/RpcRetryingCallerFactory
      44: dup
      45: aload_0
      46: invokespecial #10                 // Method org/apache/hadoop/hbase/client/RpcRetryingCallerFactory."<init>":(Lorg/apache/hadoop/conf/Configuration;)V
      49: astore_2
      50: aload_1
      51: invokevirtual #11                 // Method org/apache/hadoop/hbase/client/ConnectionImplementation.getRpcRetryingCallerFactory:()Lorg/apache/hadoop/hbase/client/RpcRetryingCallerFactory;
      54: invokestatic  #5                  // Method org/mockito/Mockito.when:(Ljava/lang/Object;)Lorg/mockito/stubbing/OngoingStubbing;
      57: aload_2
      58: invokeinterface #6,  2            // InterfaceMethod org/mockito/stubbing/OngoingStubbing.thenReturn:(Ljava/lang/Object;)Lorg/mockito/stubbing/OngoingStubbing;
      63: pop
      64: aload_1
      65: areturn

  public static org.apache.hadoop.hbase.client.ClusterConnection getMockedConnectionAndDecorate(org.apache.hadoop.conf.Configuration, org.apache.hadoop.hbase.shaded.protobuf.generated.AdminProtos$AdminService$BlockingInterface, org.apache.hadoop.hbase.shaded.protobuf.generated.ClientProtos$ClientService$BlockingInterface, org.apache.hadoop.hbase.ServerName, org.apache.hadoop.hbase.client.RegionInfo) throws java.io.IOException;
    Code:
       0: ldc           #2                  // class org/apache/hadoop/hbase/client/ConnectionImplementation
       2: invokestatic  #3                  // Method org/mockito/Mockito.mock:(Ljava/lang/Class;)Ljava/lang/Object;
       5: checkcast     #2                  // class org/apache/hadoop/hbase/client/ConnectionImplementation
       8: astore        5
      10: aload         5
      12: invokevirtual #4                  // Method org/apache/hadoop/hbase/client/ConnectionImplementation.getConfiguration:()Lorg/apache/hadoop/conf/Configuration;
      15: invokestatic  #5                  // Method org/mockito/Mockito.when:(Ljava/lang/Object;)Lorg/mockito/stubbing/OngoingStubbing;
      18: aload_0
      19: invokeinterface #6,  2            // InterfaceMethod org/mockito/stubbing/OngoingStubbing.thenReturn:(Ljava/lang/Object;)Lorg/mockito/stubbing/OngoingStubbing;
      24: pop
      25: invokestatic  #12                 // Method org/mockito/Mockito.doNothing:()Lorg/mockito/stubbing/Stubber;
      28: aload         5
      30: invokeinterface #13,  2           // InterfaceMethod org/mockito/stubbing/Stubber.when:(Ljava/lang/Object;)Ljava/lang/Object;
      35: checkcast     #2                  // class org/apache/hadoop/hbase/client/ConnectionImplementation
      38: invokevirtual #14                 // Method org/apache/hadoop/hbase/client/ConnectionImplementation.close:()V
      41: new           #15                 // class org/apache/hadoop/hbase/HRegionLocation
      44: dup
      45: aload         4
      47: aload_3
      48: invokespecial #16                 // Method org/apache/hadoop/hbase/HRegionLocation."<init>":(Lorg/apache/hadoop/hbase/client/RegionInfo;Lorg/apache/hadoop/hbase/ServerName;)V
      51: astore        6
      53: aload         5
      55: invokestatic  #17                 // Method org/mockito/Mockito.any:()Ljava/lang/Object;
      58: checkcast     #18                 // class org/apache/hadoop/hbase/TableName
      61: invokestatic  #17                 // Method org/mockito/Mockito.any:()Ljava/lang/Object;
      64: checkcast     #19                 // class "[B"
      67: checkcast     #19                 // class "[B"
      70: invokestatic  #20                 // Method org/mockito/Mockito.anyBoolean:()Z
      73: invokevirtual #21                 // Method org/apache/hadoop/hbase/client/ConnectionImplementation.getRegionLocation:(Lorg/apache/hadoop/hbase/TableName;[BZ)Lorg/apache/hadoop/hbase/HRegionLocation;
      76: invokestatic  #5                  // Method org/mockito/Mockito.when:(Ljava/lang/Object;)Lorg/mockito/stubbing/OngoingStubbing;
      79: aload         6
      81: invokeinterface #6,  2            // InterfaceMethod org/mockito/stubbing/OngoingStubbing.thenReturn:(Ljava/lang/Object;)Lorg/mockito/stubbing/OngoingStubbing;
      86: pop
      87: aload         5
      89: invokestatic  #17                 // Method org/mockito/Mockito.any:()Ljava/lang/Object;
      92: checkcast     #18                 // class org/apache/hadoop/hbase/TableName
      95: invokestatic  #17                 // Method org/mockito/Mockito.any:()Ljava/lang/Object;
      98: checkcast     #19                 // class "[B"
     101: checkcast     #19                 // class "[B"
     104: invokevirtual #22                 // Method org/apache/hadoop/hbase/client/ConnectionImplementation.locateRegion:(Lorg/apache/hadoop/hbase/TableName;[B)Lorg/apache/hadoop/hbase/HRegionLocation;
     107: invokestatic  #5                  // Method org/mockito/Mockito.when:(Ljava/lang/Object;)Lorg/mockito/stubbing/OngoingStubbing;
     110: aload         6
     112: invokeinterface #6,  2            // InterfaceMethod org/mockito/stubbing/OngoingStubbing.thenReturn:(Ljava/lang/Object;)Lorg/mockito/stubbing/OngoingStubbing;
     117: pop
     118: aload         5
     120: invokestatic  #17                 // Method org/mockito/Mockito.any:()Ljava/lang/Object;
     123: checkcast     #18                 // class org/apache/hadoop/hbase/TableName
     126: invokestatic  #17                 // Method org/mockito/Mockito.any:()Ljava/lang/Object;
     129: checkcast     #19                 // class "[B"
     132: checkcast     #19                 // class "[B"
     135: invokestatic  #20                 // Method org/mockito/Mockito.anyBoolean:()Z
     138: invokestatic  #20                 // Method org/mockito/Mockito.anyBoolean:()Z
     141: invokestatic  #23                 // Method org/mockito/Mockito.anyInt:()I
     144: invokevirtual #24                 // Method org/apache/hadoop/hbase/client/ConnectionImplementation.locateRegion:(Lorg/apache/hadoop/hbase/TableName;[BZZI)Lorg/apache/hadoop/hbase/RegionLocations;
     147: invokestatic  #5                  // Method org/mockito/Mockito.when:(Ljava/lang/Object;)Lorg/mockito/stubbing/OngoingStubbing;
     150: new           #25                 // class org/apache/hadoop/hbase/RegionLocations
     153: dup
     154: iconst_1
     155: anewarray     #15                 // class org/apache/hadoop/hbase/HRegionLocation
     158: dup
     159: iconst_0
     160: aload         6
     162: aastore
     163: invokespecial #26                 // Method org/apache/hadoop/hbase/RegionLocations."<init>":([Lorg/apache/hadoop/hbase/HRegionLocation;)V
     166: invokeinterface #6,  2            // InterfaceMethod org/mockito/stubbing/OngoingStubbing.thenReturn:(Ljava/lang/Object;)Lorg/mockito/stubbing/OngoingStubbing;
     171: pop
     172: aload_1
     173: ifnull        197
     176: aload         5
     178: invokestatic  #17                 // Method org/mockito/Mockito.any:()Ljava/lang/Object;
     181: checkcast     #27                 // class org/apache/hadoop/hbase/ServerName
     184: invokevirtual #28                 // Method org/apache/hadoop/hbase/client/ConnectionImplementation.getAdmin:(Lorg/apache/hadoop/hbase/ServerName;)Lorg/apache/hadoop/hbase/shaded/protobuf/generated/AdminProtos$AdminService$BlockingInterface;
     187: invokestatic  #5                  // Method org/mockito/Mockito.when:(Ljava/lang/Object;)Lorg/mockito/stubbing/OngoingStubbing;
     190: aload_1
     191: invokeinterface #6,  2            // InterfaceMethod org/mockito/stubbing/OngoingStubbing.thenReturn:(Ljava/lang/Object;)Lorg/mockito/stubbing/OngoingStubbing;
     196: pop
     197: aload_2
     198: ifnull        222
     201: aload         5
     203: invokestatic  #17                 // Method org/mockito/Mockito.any:()Ljava/lang/Object;
     206: checkcast     #27                 // class org/apache/hadoop/hbase/ServerName
     209: invokevirtual #29                 // Method org/apache/hadoop/hbase/client/ConnectionImplementation.getClient:(Lorg/apache/hadoop/hbase/ServerName;)Lorg/apache/hadoop/hbase/shaded/protobuf/generated/ClientProtos$ClientService$BlockingInterface;
     212: invokestatic  #5                  // Method org/mockito/Mockito.when:(Ljava/lang/Object;)Lorg/mockito/stubbing/OngoingStubbing;
     215: aload_2
     216: invokeinterface #6,  2            // InterfaceMethod org/mockito/stubbing/OngoingStubbing.thenReturn:(Ljava/lang/Object;)Lorg/mockito/stubbing/OngoingStubbing;
     221: pop
     222: ldc           #30                 // class org/apache/hadoop/hbase/client/NonceGenerator
     224: invokestatic  #3                  // Method org/mockito/Mockito.mock:(Ljava/lang/Class;)Ljava/lang/Object;
     227: checkcast     #30                 // class org/apache/hadoop/hbase/client/NonceGenerator
     230: astore        7
     232: aload         5
     234: invokevirtual #31                 // Method org/apache/hadoop/hbase/client/ConnectionImplementation.getNonceGenerator:()Lorg/apache/hadoop/hbase/client/NonceGenerator;
     237: invokestatic  #5                  // Method org/mockito/Mockito.when:(Ljava/lang/Object;)Lorg/mockito/stubbing/OngoingStubbing;
     240: aload         7
     242: invokeinterface #6,  2            // InterfaceMethod org/mockito/stubbing/OngoingStubbing.thenReturn:(Ljava/lang/Object;)Lorg/mockito/stubbing/OngoingStubbing;
     247: pop
     248: aload         5
     250: invokevirtual #32                 // Method org/apache/hadoop/hbase/client/ConnectionImplementation.getAsyncProcess:()Lorg/apache/hadoop/hbase/client/AsyncProcess;
     253: invokestatic  #5                  // Method org/mockito/Mockito.when:(Ljava/lang/Object;)Lorg/mockito/stubbing/OngoingStubbing;
     256: new           #33                 // class org/apache/hadoop/hbase/client/AsyncProcess
     259: dup
     260: aload         5
     262: aload_0
     263: aload_0
     264: invokestatic  #34                 // Method org/apache/hadoop/hbase/client/RpcRetryingCallerFactory.instantiate:(Lorg/apache/hadoop/conf/Configuration;)Lorg/apache/hadoop/hbase/client/RpcRetryingCallerFactory;
     267: aload_0
     268: invokestatic  #35                 // Method org/apache/hadoop/hbase/ipc/RpcControllerFactory.instantiate:(Lorg/apache/hadoop/conf/Configuration;)Lorg/apache/hadoop/hbase/ipc/RpcControllerFactory;
     271: invokespecial #36                 // Method org/apache/hadoop/hbase/client/AsyncProcess."<init>":(Lorg/apache/hadoop/hbase/client/ClusterConnection;Lorg/apache/hadoop/conf/Configuration;Lorg/apache/hadoop/hbase/client/RpcRetryingCallerFactory;Lorg/apache/hadoop/hbase/ipc/RpcControllerFactory;)V
     274: invokeinterface #6,  2            // InterfaceMethod org/mockito/stubbing/OngoingStubbing.thenReturn:(Ljava/lang/Object;)Lorg/mockito/stubbing/OngoingStubbing;
     279: pop
     280: aload         5
     282: aload_0
     283: invokevirtual #37                 // Method org/apache/hadoop/hbase/client/ConnectionImplementation.getNewRpcRetryingCallerFactory:(Lorg/apache/hadoop/conf/Configuration;)Lorg/apache/hadoop/hbase/client/RpcRetryingCallerFactory;
     286: invokestatic  #5                  // Method org/mockito/Mockito.when:(Ljava/lang/Object;)Lorg/mockito/stubbing/OngoingStubbing;
     289: aload_0
     290: getstatic     #38                 // Field org/apache/hadoop/hbase/client/RetryingCallerInterceptorFactory.NO_OP_INTERCEPTOR:Lorg/apache/hadoop/hbase/client/RetryingCallerInterceptor;
     293: aconst_null
     294: invokestatic  #39                 // Method org/apache/hadoop/hbase/client/RpcRetryingCallerFactory.instantiate:(Lorg/apache/hadoop/conf/Configuration;Lorg/apache/hadoop/hbase/client/RetryingCallerInterceptor;Lorg/apache/hadoop/hbase/client/ServerStatisticTracker;)Lorg/apache/hadoop/hbase/client/RpcRetryingCallerFactory;
     297: invokeinterface #6,  2            // InterfaceMethod org/mockito/stubbing/OngoingStubbing.thenReturn:(Ljava/lang/Object;)Lorg/mockito/stubbing/OngoingStubbing;
     302: pop
     303: aload         5
     305: invokevirtual #7                  // Method org/apache/hadoop/hbase/client/ConnectionImplementation.getRpcControllerFactory:()Lorg/apache/hadoop/hbase/ipc/RpcControllerFactory;
     308: invokestatic  #5                  // Method org/mockito/Mockito.when:(Ljava/lang/Object;)Lorg/mockito/stubbing/OngoingStubbing;
     311: ldc           #8                  // class org/apache/hadoop/hbase/ipc/RpcControllerFactory
     313: invokestatic  #3                  // Method org/mockito/Mockito.mock:(Ljava/lang/Class;)Ljava/lang/Object;
     316: invokeinterface #6,  2            // InterfaceMethod org/mockito/stubbing/OngoingStubbing.thenReturn:(Ljava/lang/Object;)Lorg/mockito/stubbing/OngoingStubbing;
     321: pop
     322: ldc           #40                 // class org/apache/hadoop/hbase/client/Table
     324: invokestatic  #3                  // Method org/mockito/Mockito.mock:(Ljava/lang/Class;)Ljava/lang/Object;
     327: checkcast     #40                 // class org/apache/hadoop/hbase/client/Table
     330: astore        8
     332: aload         5
     334: invokestatic  #17                 // Method org/mockito/Mockito.any:()Ljava/lang/Object;
     337: checkcast     #18                 // class org/apache/hadoop/hbase/TableName
     340: invokevirtual #41                 // Method org/apache/hadoop/hbase/client/ConnectionImplementation.getTable:(Lorg/apache/hadoop/hbase/TableName;)Lorg/apache/hadoop/hbase/client/Table;
     343: invokestatic  #5                  // Method org/mockito/Mockito.when:(Ljava/lang/Object;)Lorg/mockito/stubbing/OngoingStubbing;
     346: aload         8
     348: invokeinterface #6,  2            // InterfaceMethod org/mockito/stubbing/OngoingStubbing.thenReturn:(Ljava/lang/Object;)Lorg/mockito/stubbing/OngoingStubbing;
     353: pop
     354: ldc           #42                 // class org/apache/hadoop/hbase/client/ResultScanner
     356: invokestatic  #3                  // Method org/mockito/Mockito.mock:(Ljava/lang/Class;)Ljava/lang/Object;
     359: checkcast     #42                 // class org/apache/hadoop/hbase/client/ResultScanner
     362: astore        9
     364: aload         8
     366: invokestatic  #17                 // Method org/mockito/Mockito.any:()Ljava/lang/Object;
     369: checkcast     #43                 // class org/apache/hadoop/hbase/client/Scan
     372: invokeinterface #44,  2           // InterfaceMethod org/apache/hadoop/hbase/client/Table.getScanner:(Lorg/apache/hadoop/hbase/client/Scan;)Lorg/apache/hadoop/hbase/client/ResultScanner;
     377: invokestatic  #5                  // Method org/mockito/Mockito.when:(Ljava/lang/Object;)Lorg/mockito/stubbing/OngoingStubbing;
     380: aload         9
     382: invokeinterface #6,  2            // InterfaceMethod org/mockito/stubbing/OngoingStubbing.thenReturn:(Ljava/lang/Object;)Lorg/mockito/stubbing/OngoingStubbing;
     387: pop
     388: aload         5
     390: areturn

  public static org.apache.hadoop.hbase.client.ClusterConnection getSpiedConnection(org.apache.hadoop.conf.Configuration) throws java.io.IOException;
    Code:
       0: new           #2                  // class org/apache/hadoop/hbase/client/ConnectionImplementation
       3: dup
       4: aload_0
       5: aconst_null
       6: aconst_null
       7: invokespecial #45                 // Method org/apache/hadoop/hbase/client/ConnectionImplementation."<init>":(Lorg/apache/hadoop/conf/Configuration;Ljava/util/concurrent/ExecutorService;Lorg/apache/hadoop/hbase/security/User;)V
      10: invokestatic  #46                 // Method org/mockito/Mockito.spy:(Ljava/lang/Object;)Ljava/lang/Object;
      13: checkcast     #2                  // class org/apache/hadoop/hbase/client/ConnectionImplementation
      16: astore_1
      17: aload_1
      18: areturn
}
