Compiled from "HealthChecker.java"
class org.apache.hadoop.hbase.HealthChecker {
  org.apache.hadoop.hbase.HealthChecker();
    Code:
       0: aload_0
       1: invokespecial #1                  // Method java/lang/Object."<init>":()V
       4: aload_0
       5: aconst_null
       6: putfield      #2                  // Field shexec:Lorg/apache/hadoop/util/Shell$ShellCommandExecutor;
       9: return

  public void init(java.lang.String, long);
    Code:
       0: aload_0
       1: aload_1
       2: putfield      #3                  // Field healthCheckScript:Ljava/lang/String;
       5: aload_0
       6: lload_2
       7: putfield      #4                  // Field scriptTimeout:J
      10: new           #5                  // class java/util/ArrayList
      13: dup
      14: invokespecial #6                  // Method java/util/ArrayList."<init>":()V
      17: astore        4
      19: aload         4
      21: aload_0
      22: getfield      #3                  // Field healthCheckScript:Ljava/lang/String;
      25: invokevirtual #7                  // Method java/util/ArrayList.add:(Ljava/lang/Object;)Z
      28: pop
      29: aload_0
      30: new           #8                  // class org/apache/hadoop/util/Shell$ShellCommandExecutor
      33: dup
      34: aload         4
      36: aload         4
      38: invokevirtual #9                  // Method java/util/ArrayList.size:()I
      41: anewarray     #10                 // class java/lang/String
      44: invokevirtual #11                 // Method java/util/ArrayList.toArray:([Ljava/lang/Object;)[Ljava/lang/Object;
      47: checkcast     #12                 // class "[Ljava/lang/String;"
      50: aconst_null
      51: aconst_null
      52: aload_0
      53: getfield      #4                  // Field scriptTimeout:J
      56: invokespecial #13                 // Method org/apache/hadoop/util/Shell$ShellCommandExecutor."<init>":([Ljava/lang/String;Ljava/io/File;Ljava/util/Map;J)V
      59: putfield      #2                  // Field shexec:Lorg/apache/hadoop/util/Shell$ShellCommandExecutor;
      62: getstatic     #14                 // Field LOG:Lorg/slf4j/Logger;
      65: new           #15                 // class java/lang/StringBuilder
      68: dup
      69: invokespecial #16                 // Method java/lang/StringBuilder."<init>":()V
      72: ldc           #17                 // String HealthChecker initialized with script at
      74: invokevirtual #18                 // Method java/lang/StringBuilder.append:(Ljava/lang/String;)Ljava/lang/StringBuilder;
      77: aload_0
      78: getfield      #3                  // Field healthCheckScript:Ljava/lang/String;
      81: invokevirtual #18                 // Method java/lang/StringBuilder.append:(Ljava/lang/String;)Ljava/lang/StringBuilder;
      84: ldc           #19                 // String , timeout=
      86: invokevirtual #18                 // Method java/lang/StringBuilder.append:(Ljava/lang/String;)Ljava/lang/StringBuilder;
      89: lload_2
      90: invokevirtual #20                 // Method java/lang/StringBuilder.append:(J)Ljava/lang/StringBuilder;
      93: invokevirtual #21                 // Method java/lang/StringBuilder.toString:()Ljava/lang/String;
      96: invokeinterface #22,  2           // InterfaceMethod org/slf4j/Logger.info:(Ljava/lang/String;)V
     101: return

  public org.apache.hadoop.hbase.HealthReport checkHealth();
    Code:
       0: getstatic     #23                 // Field org/apache/hadoop/hbase/HealthChecker$HealthCheckerExitStatus.SUCCESS:Lorg/apache/hadoop/hbase/HealthChecker$HealthCheckerExitStatus;
       3: astore_1
       4: aload_0
       5: getfield      #2                  // Field shexec:Lorg/apache/hadoop/util/Shell$ShellCommandExecutor;
       8: invokevirtual #24                 // Method org/apache/hadoop/util/Shell$ShellCommandExecutor.execute:()V
      11: aload_0
      12: getfield      #2                  // Field shexec:Lorg/apache/hadoop/util/Shell$ShellCommandExecutor;
      15: invokevirtual #25                 // Method org/apache/hadoop/util/Shell$ShellCommandExecutor.isTimedOut:()Z
      18: ifeq          25
      21: getstatic     #26                 // Field org/apache/hadoop/hbase/HealthChecker$HealthCheckerExitStatus.TIMED_OUT:Lorg/apache/hadoop/hbase/HealthChecker$HealthCheckerExitStatus;
      24: astore_1
      25: aload_1
      26: getstatic     #23                 // Field org/apache/hadoop/hbase/HealthChecker$HealthCheckerExitStatus.SUCCESS:Lorg/apache/hadoop/hbase/HealthChecker$HealthCheckerExitStatus;
      29: if_acmpne     263
      32: aload_0
      33: aload_0
      34: getfield      #2                  // Field shexec:Lorg/apache/hadoop/util/Shell$ShellCommandExecutor;
      37: invokevirtual #27                 // Method org/apache/hadoop/util/Shell$ShellCommandExecutor.getOutput:()Ljava/lang/String;
      40: invokespecial #28                 // Method hasErrors:(Ljava/lang/String;)Z
      43: ifeq          263
      46: getstatic     #29                 // Field org/apache/hadoop/hbase/HealthChecker$HealthCheckerExitStatus.FAILED:Lorg/apache/hadoop/hbase/HealthChecker$HealthCheckerExitStatus;
      49: astore_1
      50: goto          263
      53: astore_2
      54: getstatic     #14                 // Field LOG:Lorg/slf4j/Logger;
      57: new           #15                 // class java/lang/StringBuilder
      60: dup
      61: invokespecial #16                 // Method java/lang/StringBuilder."<init>":()V
      64: ldc           #31                 // String Caught exception :
      66: invokevirtual #18                 // Method java/lang/StringBuilder.append:(Ljava/lang/String;)Ljava/lang/StringBuilder;
      69: aload_2
      70: invokevirtual #32                 // Method java/lang/StringBuilder.append:(Ljava/lang/Object;)Ljava/lang/StringBuilder;
      73: ldc           #33                 // String ,exit code:
      75: invokevirtual #18                 // Method java/lang/StringBuilder.append:(Ljava/lang/String;)Ljava/lang/StringBuilder;
      78: aload_2
      79: invokevirtual #34                 // Method org/apache/hadoop/util/Shell$ExitCodeException.getExitCode:()I
      82: invokevirtual #35                 // Method java/lang/StringBuilder.append:(I)Ljava/lang/StringBuilder;
      85: invokevirtual #21                 // Method java/lang/StringBuilder.toString:()Ljava/lang/String;
      88: invokeinterface #36,  2           // InterfaceMethod org/slf4j/Logger.warn:(Ljava/lang/String;)V
      93: getstatic     #37                 // Field org/apache/hadoop/hbase/HealthChecker$HealthCheckerExitStatus.FAILED_WITH_EXIT_CODE:Lorg/apache/hadoop/hbase/HealthChecker$HealthCheckerExitStatus;
      96: astore_1
      97: aload_0
      98: getfield      #2                  // Field shexec:Lorg/apache/hadoop/util/Shell$ShellCommandExecutor;
     101: invokevirtual #25                 // Method org/apache/hadoop/util/Shell$ShellCommandExecutor.isTimedOut:()Z
     104: ifeq          111
     107: getstatic     #26                 // Field org/apache/hadoop/hbase/HealthChecker$HealthCheckerExitStatus.TIMED_OUT:Lorg/apache/hadoop/hbase/HealthChecker$HealthCheckerExitStatus;
     110: astore_1
     111: aload_1
     112: getstatic     #23                 // Field org/apache/hadoop/hbase/HealthChecker$HealthCheckerExitStatus.SUCCESS:Lorg/apache/hadoop/hbase/HealthChecker$HealthCheckerExitStatus;
     115: if_acmpne     263
     118: aload_0
     119: aload_0
     120: getfield      #2                  // Field shexec:Lorg/apache/hadoop/util/Shell$ShellCommandExecutor;
     123: invokevirtual #27                 // Method org/apache/hadoop/util/Shell$ShellCommandExecutor.getOutput:()Ljava/lang/String;
     126: invokespecial #28                 // Method hasErrors:(Ljava/lang/String;)Z
     129: ifeq          263
     132: getstatic     #29                 // Field org/apache/hadoop/hbase/HealthChecker$HealthCheckerExitStatus.FAILED:Lorg/apache/hadoop/hbase/HealthChecker$HealthCheckerExitStatus;
     135: astore_1
     136: goto          263
     139: astore_2
     140: getstatic     #14                 // Field LOG:Lorg/slf4j/Logger;
     143: new           #15                 // class java/lang/StringBuilder
     146: dup
     147: invokespecial #16                 // Method java/lang/StringBuilder."<init>":()V
     150: ldc           #31                 // String Caught exception :
     152: invokevirtual #18                 // Method java/lang/StringBuilder.append:(Ljava/lang/String;)Ljava/lang/StringBuilder;
     155: aload_2
     156: invokevirtual #32                 // Method java/lang/StringBuilder.append:(Ljava/lang/Object;)Ljava/lang/StringBuilder;
     159: invokevirtual #21                 // Method java/lang/StringBuilder.toString:()Ljava/lang/String;
     162: invokeinterface #36,  2           // InterfaceMethod org/slf4j/Logger.warn:(Ljava/lang/String;)V
     167: getstatic     #39                 // Field org/apache/hadoop/hbase/HealthChecker$HealthCheckerExitStatus.FAILED_WITH_EXCEPTION:Lorg/apache/hadoop/hbase/HealthChecker$HealthCheckerExitStatus;
     170: astore_1
     171: aload_0
     172: aload_2
     173: invokestatic  #40                 // Method org/apache/hadoop/util/StringUtils.stringifyException:(Ljava/lang/Throwable;)Ljava/lang/String;
     176: putfield      #41                 // Field exceptionStackTrace:Ljava/lang/String;
     179: aload_0
     180: getfield      #2                  // Field shexec:Lorg/apache/hadoop/util/Shell$ShellCommandExecutor;
     183: invokevirtual #25                 // Method org/apache/hadoop/util/Shell$ShellCommandExecutor.isTimedOut:()Z
     186: ifeq          193
     189: getstatic     #26                 // Field org/apache/hadoop/hbase/HealthChecker$HealthCheckerExitStatus.TIMED_OUT:Lorg/apache/hadoop/hbase/HealthChecker$HealthCheckerExitStatus;
     192: astore_1
     193: aload_1
     194: getstatic     #23                 // Field org/apache/hadoop/hbase/HealthChecker$HealthCheckerExitStatus.SUCCESS:Lorg/apache/hadoop/hbase/HealthChecker$HealthCheckerExitStatus;
     197: if_acmpne     263
     200: aload_0
     201: aload_0
     202: getfield      #2                  // Field shexec:Lorg/apache/hadoop/util/Shell$ShellCommandExecutor;
     205: invokevirtual #27                 // Method org/apache/hadoop/util/Shell$ShellCommandExecutor.getOutput:()Ljava/lang/String;
     208: invokespecial #28                 // Method hasErrors:(Ljava/lang/String;)Z
     211: ifeq          263
     214: getstatic     #29                 // Field org/apache/hadoop/hbase/HealthChecker$HealthCheckerExitStatus.FAILED:Lorg/apache/hadoop/hbase/HealthChecker$HealthCheckerExitStatus;
     217: astore_1
     218: goto          263
     221: astore_3
     222: aload_0
     223: getfield      #2                  // Field shexec:Lorg/apache/hadoop/util/Shell$ShellCommandExecutor;
     226: invokevirtual #25                 // Method org/apache/hadoop/util/Shell$ShellCommandExecutor.isTimedOut:()Z
     229: ifeq          236
     232: getstatic     #26                 // Field org/apache/hadoop/hbase/HealthChecker$HealthCheckerExitStatus.TIMED_OUT:Lorg/apache/hadoop/hbase/HealthChecker$HealthCheckerExitStatus;
     235: astore_1
     236: aload_1
     237: getstatic     #23                 // Field org/apache/hadoop/hbase/HealthChecker$HealthCheckerExitStatus.SUCCESS:Lorg/apache/hadoop/hbase/HealthChecker$HealthCheckerExitStatus;
     240: if_acmpne     261
     243: aload_0
     244: aload_0
     245: getfield      #2                  // Field shexec:Lorg/apache/hadoop/util/Shell$ShellCommandExecutor;
     248: invokevirtual #27                 // Method org/apache/hadoop/util/Shell$ShellCommandExecutor.getOutput:()Ljava/lang/String;
     251: invokespecial #28                 // Method hasErrors:(Ljava/lang/String;)Z
     254: ifeq          261
     257: getstatic     #29                 // Field org/apache/hadoop/hbase/HealthChecker$HealthCheckerExitStatus.FAILED:Lorg/apache/hadoop/hbase/HealthChecker$HealthCheckerExitStatus;
     260: astore_1
     261: aload_3
     262: athrow
     263: new           #42                 // class org/apache/hadoop/hbase/HealthReport
     266: dup
     267: aload_1
     268: aload_0
     269: aload_1
     270: invokespecial #43                 // Method getHealthReport:(Lorg/apache/hadoop/hbase/HealthChecker$HealthCheckerExitStatus;)Ljava/lang/String;
     273: invokespecial #44                 // Method org/apache/hadoop/hbase/HealthReport."<init>":(Lorg/apache/hadoop/hbase/HealthChecker$HealthCheckerExitStatus;Ljava/lang/String;)V
     276: areturn
    Exception table:
       from    to  target type
           4    11    53   Class org/apache/hadoop/util/Shell$ExitCodeException
           4    11   139   Class java/io/IOException
           4    11   221   any
          53    97   221   any
         139   179   221   any

  static {};
    Code:
       0: ldc           #47                 // class org/apache/hadoop/hbase/HealthChecker
       2: invokestatic  #55                 // Method org/slf4j/LoggerFactory.getLogger:(Ljava/lang/Class;)Lorg/slf4j/Logger;
       5: putstatic     #14                 // Field LOG:Lorg/slf4j/Logger;
       8: return
}
