Compiled from "HFileBlock.java"
public class org.apache.hadoop.hbase.io.hfile.HFileBlock implements org.apache.hadoop.hbase.io.hfile.Cacheable {
  static final int CHECKSUM_VERIFICATION_NUM_IO_THRESHOLD;

  public static final boolean FILL_HEADER;

  public static final boolean DONT_FILL_HEADER;

  public static final int MULTI_BYTE_BUFFER_HEAP_SIZE;

  static final int BLOCK_METADATA_SPACE;

  static final int CHECKSUM_SIZE;

  static final byte[] DUMMY_HEADER_NO_CHECKSUM;

  public static final org.apache.hadoop.hbase.io.hfile.CacheableDeserializer<org.apache.hadoop.hbase.io.hfile.Cacheable> BLOCK_DESERIALIZER;

  static final boolean $assertionsDisabled;

  public org.apache.hadoop.hbase.io.hfile.HFileBlock(org.apache.hadoop.hbase.io.hfile.BlockType, int, int, long, java.nio.ByteBuffer, boolean, long, int, int, org.apache.hadoop.hbase.io.hfile.HFileContext);
    Code:
       0: aload_0
       1: invokespecial #7                  // Method java/lang/Object."<init>":()V
       4: aload_0
       5: getstatic     #4                  // Field UNSET:I
       8: i2l
       9: putfield      #8                  // Field offset:J
      12: aload_0
      13: getstatic     #9                  // Field org/apache/hadoop/hbase/io/hfile/Cacheable$MemoryType.EXCLUSIVE:Lorg/apache/hadoop/hbase/io/hfile/Cacheable$MemoryType;
      16: putfield      #10                 // Field memType:Lorg/apache/hadoop/hbase/io/hfile/Cacheable$MemoryType;
      19: aload_0
      20: getstatic     #4                  // Field UNSET:I
      23: putfield      #11                 // Field nextBlockOnDiskSize:I
      26: aload_0
      27: aload_1
      28: iload_2
      29: iload_3
      30: lload         4
      32: lload         8
      34: iload         11
      36: iload         10
      38: aload         12
      40: invokespecial #18                 // Method init:(Lorg/apache/hadoop/hbase/io/hfile/BlockType;IIJJIILorg/apache/hadoop/hbase/io/hfile/HFileContext;)V
      43: aload_0
      44: new           #19                 // class org/apache/hadoop/hbase/nio/SingleByteBuff
      47: dup
      48: aload         6
      50: invokespecial #24                 // Method org/apache/hadoop/hbase/nio/SingleByteBuff."<init>":(Ljava/nio/ByteBuffer;)V
      53: putfield      #20                 // Field buf:Lorg/apache/hadoop/hbase/nio/ByteBuff;
      56: iload         7
      58: ifeq          65
      61: aload_0
      62: invokespecial #26                 // Method overwriteHeader:()V
      65: aload_0
      66: getfield      #20                 // Field buf:Lorg/apache/hadoop/hbase/nio/ByteBuff;
      69: invokevirtual #27                 // Method org/apache/hadoop/hbase/nio/ByteBuff.rewind:()Lorg/apache/hadoop/hbase/nio/ByteBuff;
      72: pop
      73: return

  org.apache.hadoop.hbase.io.hfile.HFileBlock(org.apache.hadoop.hbase.nio.ByteBuff, boolean, org.apache.hadoop.hbase.io.hfile.Cacheable$MemoryType, long, int, org.apache.hadoop.hbase.io.hfile.HFileContext) throws java.io.IOException;
    Code:
       0: aload_0
       1: invokespecial #7                  // Method java/lang/Object."<init>":()V
       4: aload_0
       5: getstatic     #4                  // Field UNSET:I
       8: i2l
       9: putfield      #8                  // Field offset:J
      12: aload_0
      13: getstatic     #9                  // Field org/apache/hadoop/hbase/io/hfile/Cacheable$MemoryType.EXCLUSIVE:Lorg/apache/hadoop/hbase/io/hfile/Cacheable$MemoryType;
      16: putfield      #10                 // Field memType:Lorg/apache/hadoop/hbase/io/hfile/Cacheable$MemoryType;
      19: aload_0
      20: getstatic     #4                  // Field UNSET:I
      23: putfield      #11                 // Field nextBlockOnDiskSize:I
      26: aload_1
      27: invokevirtual #27                 // Method org/apache/hadoop/hbase/nio/ByteBuff.rewind:()Lorg/apache/hadoop/hbase/nio/ByteBuff;
      30: pop
      31: aload_1
      32: invokestatic  #28                 // Method org/apache/hadoop/hbase/io/hfile/BlockType.read:(Lorg/apache/hadoop/hbase/nio/ByteBuff;)Lorg/apache/hadoop/hbase/io/hfile/BlockType;
      35: astore        8
      37: aload_1
      38: getstatic     #29                 // Field org/apache/hadoop/hbase/io/hfile/HFileBlock$Header.ON_DISK_SIZE_WITHOUT_HEADER_INDEX:I
      41: invokevirtual #30                 // Method org/apache/hadoop/hbase/nio/ByteBuff.getInt:(I)I
      44: istore        9
      46: aload_1
      47: getstatic     #31                 // Field org/apache/hadoop/hbase/io/hfile/HFileBlock$Header.UNCOMPRESSED_SIZE_WITHOUT_HEADER_INDEX:I
      50: invokevirtual #30                 // Method org/apache/hadoop/hbase/nio/ByteBuff.getInt:(I)I
      53: istore        10
      55: aload_1
      56: getstatic     #32                 // Field org/apache/hadoop/hbase/io/hfile/HFileBlock$Header.PREV_BLOCK_OFFSET_INDEX:I
      59: invokevirtual #33                 // Method org/apache/hadoop/hbase/nio/ByteBuff.getLong:(I)J
      62: lstore        11
      64: aload         7
      66: ifnull        81
      69: new           #34                 // class org/apache/hadoop/hbase/io/hfile/HFileContextBuilder
      72: dup
      73: aload         7
      75: invokespecial #35                 // Method org/apache/hadoop/hbase/io/hfile/HFileContextBuilder."<init>":(Lorg/apache/hadoop/hbase/io/hfile/HFileContext;)V
      78: goto          88
      81: new           #34                 // class org/apache/hadoop/hbase/io/hfile/HFileContextBuilder
      84: dup
      85: invokespecial #36                 // Method org/apache/hadoop/hbase/io/hfile/HFileContextBuilder."<init>":()V
      88: astore        13
      90: aload         13
      92: iload_2
      93: invokevirtual #37                 // Method org/apache/hadoop/hbase/io/hfile/HFileContextBuilder.withHBaseCheckSum:(Z)Lorg/apache/hadoop/hbase/io/hfile/HFileContextBuilder;
      96: pop
      97: iload_2
      98: ifeq          150
     101: aload_1
     102: getstatic     #38                 // Field org/apache/hadoop/hbase/io/hfile/HFileBlock$Header.CHECKSUM_TYPE_INDEX:I
     105: invokevirtual #39                 // Method org/apache/hadoop/hbase/nio/ByteBuff.get:(I)B
     108: istore        15
     110: aload_1
     111: getstatic     #40                 // Field org/apache/hadoop/hbase/io/hfile/HFileBlock$Header.BYTES_PER_CHECKSUM_INDEX:I
     114: invokevirtual #30                 // Method org/apache/hadoop/hbase/nio/ByteBuff.getInt:(I)I
     117: istore        16
     119: aload_1
     120: getstatic     #41                 // Field org/apache/hadoop/hbase/io/hfile/HFileBlock$Header.ON_DISK_DATA_SIZE_WITH_HEADER_INDEX:I
     123: invokevirtual #30                 // Method org/apache/hadoop/hbase/nio/ByteBuff.getInt:(I)I
     126: istore        14
     128: aload         13
     130: iload         15
     132: invokestatic  #42                 // Method org/apache/hadoop/hbase/util/ChecksumType.codeToType:(B)Lorg/apache/hadoop/hbase/util/ChecksumType;
     135: invokevirtual #43                 // Method org/apache/hadoop/hbase/io/hfile/HFileContextBuilder.withChecksumType:(Lorg/apache/hadoop/hbase/util/ChecksumType;)Lorg/apache/hadoop/hbase/io/hfile/HFileContextBuilder;
     138: pop
     139: aload         13
     141: iload         16
     143: invokevirtual #44                 // Method org/apache/hadoop/hbase/io/hfile/HFileContextBuilder.withBytesPerCheckSum:(I)Lorg/apache/hadoop/hbase/io/hfile/HFileContextBuilder;
     146: pop
     147: goto          175
     150: aload         13
     152: getstatic     #45                 // Field org/apache/hadoop/hbase/util/ChecksumType.NULL:Lorg/apache/hadoop/hbase/util/ChecksumType;
     155: invokevirtual #43                 // Method org/apache/hadoop/hbase/io/hfile/HFileContextBuilder.withChecksumType:(Lorg/apache/hadoop/hbase/util/ChecksumType;)Lorg/apache/hadoop/hbase/io/hfile/HFileContextBuilder;
     158: pop
     159: aload         13
     161: iconst_0
     162: invokevirtual #44                 // Method org/apache/hadoop/hbase/io/hfile/HFileContextBuilder.withBytesPerCheckSum:(I)Lorg/apache/hadoop/hbase/io/hfile/HFileContextBuilder;
     165: pop
     166: iload         9
     168: iload_2
     169: invokestatic  #46                 // Method headerSize:(Z)I
     172: iadd
     173: istore        14
     175: aload         13
     177: invokevirtual #47                 // Method org/apache/hadoop/hbase/io/hfile/HFileContextBuilder.build:()Lorg/apache/hadoop/hbase/io/hfile/HFileContext;
     180: astore        7
     182: getstatic     #48                 // Field $assertionsDisabled:Z
     185: ifne          205
     188: iload_2
     189: aload         7
     191: invokevirtual #49                 // Method org/apache/hadoop/hbase/io/hfile/HFileContext.isUseHBaseChecksum:()Z
     194: if_icmpeq     205
     197: new           #50                 // class java/lang/AssertionError
     200: dup
     201: invokespecial #51                 // Method java/lang/AssertionError."<init>":()V
     204: athrow
     205: aload_0
     206: aload         8
     208: iload         9
     210: iload         10
     212: lload         11
     214: lload         4
     216: iload         14
     218: iload         6
     220: aload         7
     222: invokespecial #18                 // Method init:(Lorg/apache/hadoop/hbase/io/hfile/BlockType;IIJJIILorg/apache/hadoop/hbase/io/hfile/HFileContext;)V
     225: aload_0
     226: aload_3
     227: putfield      #10                 // Field memType:Lorg/apache/hadoop/hbase/io/hfile/Cacheable$MemoryType;
     230: aload_0
     231: lload         4
     233: putfield      #8                  // Field offset:J
     236: aload_0
     237: aload_1
     238: putfield      #20                 // Field buf:Lorg/apache/hadoop/hbase/nio/ByteBuff;
     241: aload_0
     242: getfield      #20                 // Field buf:Lorg/apache/hadoop/hbase/nio/ByteBuff;
     245: invokevirtual #27                 // Method org/apache/hadoop/hbase/nio/ByteBuff.rewind:()Lorg/apache/hadoop/hbase/nio/ByteBuff;
     248: pop
     249: return

  int getNextBlockOnDiskSize();
    Code:
       0: aload_0
       1: getfield      #11                 // Field nextBlockOnDiskSize:I
       4: ireturn

  public org.apache.hadoop.hbase.io.hfile.BlockType getBlockType();
    Code:
       0: aload_0
       1: getfield      #12                 // Field blockType:Lorg/apache/hadoop/hbase/io/hfile/BlockType;
       4: areturn

  short getDataBlockEncodingId();
    Code:
       0: aload_0
       1: getfield      #12                 // Field blockType:Lorg/apache/hadoop/hbase/io/hfile/BlockType;
       4: getstatic     #53                 // Field org/apache/hadoop/hbase/io/hfile/BlockType.ENCODED_DATA:Lorg/apache/hadoop/hbase/io/hfile/BlockType;
       7: if_acmpeq     51
      10: new           #54                 // class java/lang/IllegalArgumentException
      13: dup
      14: new           #55                 // class java/lang/StringBuilder
      17: dup
      18: invokespecial #56                 // Method java/lang/StringBuilder."<init>":()V
      21: ldc           #57                 // String Querying encoder ID of a block of type other than
      23: invokevirtual #58                 // Method java/lang/StringBuilder.append:(Ljava/lang/String;)Ljava/lang/StringBuilder;
      26: getstatic     #53                 // Field org/apache/hadoop/hbase/io/hfile/BlockType.ENCODED_DATA:Lorg/apache/hadoop/hbase/io/hfile/BlockType;
      29: invokevirtual #59                 // Method java/lang/StringBuilder.append:(Ljava/lang/Object;)Ljava/lang/StringBuilder;
      32: ldc           #60                 // String :
      34: invokevirtual #58                 // Method java/lang/StringBuilder.append:(Ljava/lang/String;)Ljava/lang/StringBuilder;
      37: aload_0
      38: getfield      #12                 // Field blockType:Lorg/apache/hadoop/hbase/io/hfile/BlockType;
      41: invokevirtual #59                 // Method java/lang/StringBuilder.append:(Ljava/lang/Object;)Ljava/lang/StringBuilder;
      44: invokevirtual #61                 // Method java/lang/StringBuilder.toString:()Ljava/lang/String;
      47: invokespecial #62                 // Method java/lang/IllegalArgumentException."<init>":(Ljava/lang/String;)V
      50: athrow
      51: aload_0
      52: getfield      #20                 // Field buf:Lorg/apache/hadoop/hbase/nio/ByteBuff;
      55: aload_0
      56: invokevirtual #63                 // Method headerSize:()I
      59: invokevirtual #64                 // Method org/apache/hadoop/hbase/nio/ByteBuff.getShort:(I)S
      62: ireturn

  public int getOnDiskSizeWithHeader();
    Code:
       0: aload_0
       1: getfield      #13                 // Field onDiskSizeWithoutHeader:I
       4: aload_0
       5: invokevirtual #63                 // Method headerSize:()I
       8: iadd
       9: ireturn

  int getOnDiskSizeWithoutHeader();
    Code:
       0: aload_0
       1: getfield      #13                 // Field onDiskSizeWithoutHeader:I
       4: ireturn

  int getUncompressedSizeWithoutHeader();
    Code:
       0: aload_0
       1: getfield      #14                 // Field uncompressedSizeWithoutHeader:I
       4: ireturn

  long getPrevBlockOffset();
    Code:
       0: aload_0
       1: getfield      #15                 // Field prevBlockOffset:J
       4: lreturn

  public org.apache.hadoop.hbase.nio.ByteBuff getBufferWithoutHeader();
    Code:
       0: aload_0
       1: invokevirtual #72                 // Method getBufferReadOnly:()Lorg/apache/hadoop/hbase/nio/ByteBuff;
       4: astore_1
       5: aload_1
       6: aload_0
       7: invokevirtual #63                 // Method headerSize:()I
      10: invokevirtual #73                 // Method org/apache/hadoop/hbase/nio/ByteBuff.position:(I)Lorg/apache/hadoop/hbase/nio/ByteBuff;
      13: aload_0
      14: getfield      #20                 // Field buf:Lorg/apache/hadoop/hbase/nio/ByteBuff;
      17: invokevirtual #21                 // Method org/apache/hadoop/hbase/nio/ByteBuff.limit:()I
      20: aload_0
      21: invokevirtual #74                 // Method totalChecksumBytes:()I
      24: isub
      25: invokevirtual #75                 // Method org/apache/hadoop/hbase/nio/ByteBuff.limit:(I)Lorg/apache/hadoop/hbase/nio/ByteBuff;
      28: invokevirtual #76                 // Method org/apache/hadoop/hbase/nio/ByteBuff.slice:()Lorg/apache/hadoop/hbase/nio/ByteBuff;
      31: areturn

  public org.apache.hadoop.hbase.nio.ByteBuff getBufferReadOnly();
    Code:
       0: aload_0
       1: getfield      #20                 // Field buf:Lorg/apache/hadoop/hbase/nio/ByteBuff;
       4: invokevirtual #25                 // Method org/apache/hadoop/hbase/nio/ByteBuff.duplicate:()Lorg/apache/hadoop/hbase/nio/ByteBuff;
       7: astore_1
       8: getstatic     #48                 // Field $assertionsDisabled:Z
      11: ifne          29
      14: aload_1
      15: invokevirtual #77                 // Method org/apache/hadoop/hbase/nio/ByteBuff.position:()I
      18: ifeq          29
      21: new           #50                 // class java/lang/AssertionError
      24: dup
      25: invokespecial #51                 // Method java/lang/AssertionError."<init>":()V
      28: athrow
      29: aload_1
      30: areturn

  void sanityCheck() throws java.io.IOException;
    Code:
       0: aload_0
       1: getfield      #20                 // Field buf:Lorg/apache/hadoop/hbase/nio/ByteBuff;
       4: invokevirtual #25                 // Method org/apache/hadoop/hbase/nio/ByteBuff.duplicate:()Lorg/apache/hadoop/hbase/nio/ByteBuff;
       7: invokevirtual #27                 // Method org/apache/hadoop/hbase/nio/ByteBuff.rewind:()Lorg/apache/hadoop/hbase/nio/ByteBuff;
      10: astore_1
      11: aload_0
      12: aload_1
      13: invokestatic  #28                 // Method org/apache/hadoop/hbase/io/hfile/BlockType.read:(Lorg/apache/hadoop/hbase/nio/ByteBuff;)Lorg/apache/hadoop/hbase/io/hfile/BlockType;
      16: aload_0
      17: getfield      #12                 // Field blockType:Lorg/apache/hadoop/hbase/io/hfile/BlockType;
      20: invokespecial #87                 // Method sanityCheckAssertion:(Lorg/apache/hadoop/hbase/io/hfile/BlockType;Lorg/apache/hadoop/hbase/io/hfile/BlockType;)V
      23: aload_0
      24: aload_1
      25: invokevirtual #88                 // Method org/apache/hadoop/hbase/nio/ByteBuff.getInt:()I
      28: i2l
      29: aload_0
      30: getfield      #13                 // Field onDiskSizeWithoutHeader:I
      33: i2l
      34: ldc           #89                 // String onDiskSizeWithoutHeader
      36: invokespecial #90                 // Method sanityCheckAssertion:(JJLjava/lang/String;)V
      39: aload_0
      40: aload_1
      41: invokevirtual #88                 // Method org/apache/hadoop/hbase/nio/ByteBuff.getInt:()I
      44: i2l
      45: aload_0
      46: getfield      #14                 // Field uncompressedSizeWithoutHeader:I
      49: i2l
      50: ldc           #91                 // String uncompressedSizeWithoutHeader
      52: invokespecial #90                 // Method sanityCheckAssertion:(JJLjava/lang/String;)V
      55: aload_0
      56: aload_1
      57: invokevirtual #92                 // Method org/apache/hadoop/hbase/nio/ByteBuff.getLong:()J
      60: aload_0
      61: getfield      #15                 // Field prevBlockOffset:J
      64: ldc           #93                 // String prevBlockOffset
      66: invokespecial #90                 // Method sanityCheckAssertion:(JJLjava/lang/String;)V
      69: aload_0
      70: getfield      #17                 // Field fileContext:Lorg/apache/hadoop/hbase/io/hfile/HFileContext;
      73: invokevirtual #49                 // Method org/apache/hadoop/hbase/io/hfile/HFileContext.isUseHBaseChecksum:()Z
      76: ifeq          136
      79: aload_0
      80: aload_1
      81: invokevirtual #94                 // Method org/apache/hadoop/hbase/nio/ByteBuff.get:()B
      84: i2l
      85: aload_0
      86: getfield      #17                 // Field fileContext:Lorg/apache/hadoop/hbase/io/hfile/HFileContext;
      89: invokevirtual #68                 // Method org/apache/hadoop/hbase/io/hfile/HFileContext.getChecksumType:()Lorg/apache/hadoop/hbase/util/ChecksumType;
      92: invokevirtual #69                 // Method org/apache/hadoop/hbase/util/ChecksumType.getCode:()B
      95: i2l
      96: ldc           #95                 // String checksumType
      98: invokespecial #90                 // Method sanityCheckAssertion:(JJLjava/lang/String;)V
     101: aload_0
     102: aload_1
     103: invokevirtual #88                 // Method org/apache/hadoop/hbase/nio/ByteBuff.getInt:()I
     106: i2l
     107: aload_0
     108: getfield      #17                 // Field fileContext:Lorg/apache/hadoop/hbase/io/hfile/HFileContext;
     111: invokevirtual #71                 // Method org/apache/hadoop/hbase/io/hfile/HFileContext.getBytesPerChecksum:()I
     114: i2l
     115: ldc           #96                 // String bytesPerChecksum
     117: invokespecial #90                 // Method sanityCheckAssertion:(JJLjava/lang/String;)V
     120: aload_0
     121: aload_1
     122: invokevirtual #88                 // Method org/apache/hadoop/hbase/nio/ByteBuff.getInt:()I
     125: i2l
     126: aload_0
     127: getfield      #16                 // Field onDiskDataSizeWithHeader:I
     130: i2l
     131: ldc           #97                 // String onDiskDataSizeWithHeader
     133: invokespecial #90                 // Method sanityCheckAssertion:(JJLjava/lang/String;)V
     136: aload_0
     137: invokevirtual #74                 // Method totalChecksumBytes:()I
     140: istore_2
     141: aload_0
     142: getfield      #16                 // Field onDiskDataSizeWithHeader:I
     145: iload_2
     146: iadd
     147: istore_3
     148: aload_1
     149: invokevirtual #21                 // Method org/apache/hadoop/hbase/nio/ByteBuff.limit:()I
     152: iload_3
     153: if_icmpeq     195
     156: new           #50                 // class java/lang/AssertionError
     159: dup
     160: new           #55                 // class java/lang/StringBuilder
     163: dup
     164: invokespecial #56                 // Method java/lang/StringBuilder."<init>":()V
     167: ldc           #98                 // String Expected limit
     169: invokevirtual #58                 // Method java/lang/StringBuilder.append:(Ljava/lang/String;)Ljava/lang/StringBuilder;
     172: iload_3
     173: invokevirtual #99                 // Method java/lang/StringBuilder.append:(I)Ljava/lang/StringBuilder;
     176: ldc           #100                // String , got
     178: invokevirtual #58                 // Method java/lang/StringBuilder.append:(Ljava/lang/String;)Ljava/lang/StringBuilder;
     181: aload_1
     182: invokevirtual #21                 // Method org/apache/hadoop/hbase/nio/ByteBuff.limit:()I
     185: invokevirtual #99                 // Method java/lang/StringBuilder.append:(I)Ljava/lang/StringBuilder;
     188: invokevirtual #61                 // Method java/lang/StringBuilder.toString:()Ljava/lang/String;
     191: invokespecial #82                 // Method java/lang/AssertionError."<init>":(Ljava/lang/Object;)V
     194: athrow
     195: aload_0
     196: invokevirtual #63                 // Method headerSize:()I
     199: istore        4
     201: aload_1
     202: invokevirtual #101                // Method org/apache/hadoop/hbase/nio/ByteBuff.capacity:()I
     205: iload_3
     206: if_icmpeq     271
     209: aload_1
     210: invokevirtual #101                // Method org/apache/hadoop/hbase/nio/ByteBuff.capacity:()I
     213: iload_3
     214: iload         4
     216: iadd
     217: if_icmpeq     271
     220: new           #50                 // class java/lang/AssertionError
     223: dup
     224: new           #55                 // class java/lang/StringBuilder
     227: dup
     228: invokespecial #56                 // Method java/lang/StringBuilder."<init>":()V
     231: ldc           #102                // String Invalid buffer capacity:
     233: invokevirtual #58                 // Method java/lang/StringBuilder.append:(Ljava/lang/String;)Ljava/lang/StringBuilder;
     236: aload_1
     237: invokevirtual #101                // Method org/apache/hadoop/hbase/nio/ByteBuff.capacity:()I
     240: invokevirtual #99                 // Method java/lang/StringBuilder.append:(I)Ljava/lang/StringBuilder;
     243: ldc           #103                // String , expected
     245: invokevirtual #58                 // Method java/lang/StringBuilder.append:(Ljava/lang/String;)Ljava/lang/StringBuilder;
     248: iload_3
     249: invokevirtual #99                 // Method java/lang/StringBuilder.append:(I)Ljava/lang/StringBuilder;
     252: ldc           #104                // String  or
     254: invokevirtual #58                 // Method java/lang/StringBuilder.append:(Ljava/lang/String;)Ljava/lang/StringBuilder;
     257: iload_3
     258: iload         4
     260: iadd
     261: invokevirtual #99                 // Method java/lang/StringBuilder.append:(I)Ljava/lang/StringBuilder;
     264: invokevirtual #61                 // Method java/lang/StringBuilder.toString:()Ljava/lang/String;
     267: invokespecial #82                 // Method java/lang/AssertionError."<init>":(Ljava/lang/Object;)V
     270: athrow
     271: return

  public java.lang.String toString();
    Code:
       0: new           #55                 // class java/lang/StringBuilder
       3: dup
       4: invokespecial #56                 // Method java/lang/StringBuilder."<init>":()V
       7: ldc           #105                // String [
       9: invokevirtual #58                 // Method java/lang/StringBuilder.append:(Ljava/lang/String;)Ljava/lang/StringBuilder;
      12: ldc           #106                // String blockType=
      14: invokevirtual #58                 // Method java/lang/StringBuilder.append:(Ljava/lang/String;)Ljava/lang/StringBuilder;
      17: aload_0
      18: getfield      #12                 // Field blockType:Lorg/apache/hadoop/hbase/io/hfile/BlockType;
      21: invokevirtual #59                 // Method java/lang/StringBuilder.append:(Ljava/lang/Object;)Ljava/lang/StringBuilder;
      24: ldc           #107                // String , fileOffset=
      26: invokevirtual #58                 // Method java/lang/StringBuilder.append:(Ljava/lang/String;)Ljava/lang/StringBuilder;
      29: aload_0
      30: getfield      #8                  // Field offset:J
      33: invokevirtual #79                 // Method java/lang/StringBuilder.append:(J)Ljava/lang/StringBuilder;
      36: ldc           #108                // String , headerSize=
      38: invokevirtual #58                 // Method java/lang/StringBuilder.append:(Ljava/lang/String;)Ljava/lang/StringBuilder;
      41: aload_0
      42: invokevirtual #63                 // Method headerSize:()I
      45: invokevirtual #99                 // Method java/lang/StringBuilder.append:(I)Ljava/lang/StringBuilder;
      48: ldc           #109                // String , onDiskSizeWithoutHeader=
      50: invokevirtual #58                 // Method java/lang/StringBuilder.append:(Ljava/lang/String;)Ljava/lang/StringBuilder;
      53: aload_0
      54: getfield      #13                 // Field onDiskSizeWithoutHeader:I
      57: invokevirtual #99                 // Method java/lang/StringBuilder.append:(I)Ljava/lang/StringBuilder;
      60: ldc           #110                // String , uncompressedSizeWithoutHeader=
      62: invokevirtual #58                 // Method java/lang/StringBuilder.append:(Ljava/lang/String;)Ljava/lang/StringBuilder;
      65: aload_0
      66: getfield      #14                 // Field uncompressedSizeWithoutHeader:I
      69: invokevirtual #99                 // Method java/lang/StringBuilder.append:(I)Ljava/lang/StringBuilder;
      72: ldc           #111                // String , prevBlockOffset=
      74: invokevirtual #58                 // Method java/lang/StringBuilder.append:(Ljava/lang/String;)Ljava/lang/StringBuilder;
      77: aload_0
      78: getfield      #15                 // Field prevBlockOffset:J
      81: invokevirtual #79                 // Method java/lang/StringBuilder.append:(J)Ljava/lang/StringBuilder;
      84: ldc           #112                // String , isUseHBaseChecksum=
      86: invokevirtual #58                 // Method java/lang/StringBuilder.append:(Ljava/lang/String;)Ljava/lang/StringBuilder;
      89: aload_0
      90: getfield      #17                 // Field fileContext:Lorg/apache/hadoop/hbase/io/hfile/HFileContext;
      93: invokevirtual #49                 // Method org/apache/hadoop/hbase/io/hfile/HFileContext.isUseHBaseChecksum:()Z
      96: invokevirtual #113                // Method java/lang/StringBuilder.append:(Z)Ljava/lang/StringBuilder;
      99: astore_1
     100: aload_0
     101: getfield      #17                 // Field fileContext:Lorg/apache/hadoop/hbase/io/hfile/HFileContext;
     104: invokevirtual #49                 // Method org/apache/hadoop/hbase/io/hfile/HFileContext.isUseHBaseChecksum:()Z
     107: ifeq          164
     110: aload_1
     111: ldc           #114                // String , checksumType=
     113: invokevirtual #58                 // Method java/lang/StringBuilder.append:(Ljava/lang/String;)Ljava/lang/StringBuilder;
     116: aload_0
     117: getfield      #20                 // Field buf:Lorg/apache/hadoop/hbase/nio/ByteBuff;
     120: bipush        24
     122: invokevirtual #39                 // Method org/apache/hadoop/hbase/nio/ByteBuff.get:(I)B
     125: invokestatic  #42                 // Method org/apache/hadoop/hbase/util/ChecksumType.codeToType:(B)Lorg/apache/hadoop/hbase/util/ChecksumType;
     128: invokevirtual #59                 // Method java/lang/StringBuilder.append:(Ljava/lang/Object;)Ljava/lang/StringBuilder;
     131: ldc           #115                // String , bytesPerChecksum=
     133: invokevirtual #58                 // Method java/lang/StringBuilder.append:(Ljava/lang/String;)Ljava/lang/StringBuilder;
     136: aload_0
     137: getfield      #20                 // Field buf:Lorg/apache/hadoop/hbase/nio/ByteBuff;
     140: bipush        25
     142: invokevirtual #30                 // Method org/apache/hadoop/hbase/nio/ByteBuff.getInt:(I)I
     145: invokevirtual #99                 // Method java/lang/StringBuilder.append:(I)Ljava/lang/StringBuilder;
     148: ldc           #116                // String , onDiskDataSizeWithHeader=
     150: invokevirtual #58                 // Method java/lang/StringBuilder.append:(Ljava/lang/String;)Ljava/lang/StringBuilder;
     153: aload_0
     154: getfield      #16                 // Field onDiskDataSizeWithHeader:I
     157: invokevirtual #99                 // Method java/lang/StringBuilder.append:(I)Ljava/lang/StringBuilder;
     160: pop
     161: goto          205
     164: aload_1
     165: ldc           #116                // String , onDiskDataSizeWithHeader=
     167: invokevirtual #58                 // Method java/lang/StringBuilder.append:(Ljava/lang/String;)Ljava/lang/StringBuilder;
     170: aload_0
     171: getfield      #16                 // Field onDiskDataSizeWithHeader:I
     174: invokevirtual #99                 // Method java/lang/StringBuilder.append:(I)Ljava/lang/StringBuilder;
     177: ldc           #117                // String (
     179: invokevirtual #58                 // Method java/lang/StringBuilder.append:(Ljava/lang/String;)Ljava/lang/StringBuilder;
     182: aload_0
     183: getfield      #13                 // Field onDiskSizeWithoutHeader:I
     186: invokevirtual #99                 // Method java/lang/StringBuilder.append:(I)Ljava/lang/StringBuilder;
     189: ldc           #118                // String +
     191: invokevirtual #58                 // Method java/lang/StringBuilder.append:(Ljava/lang/String;)Ljava/lang/StringBuilder;
     194: bipush        24
     196: invokevirtual #99                 // Method java/lang/StringBuilder.append:(I)Ljava/lang/StringBuilder;
     199: ldc           #81                 // String )
     201: invokevirtual #58                 // Method java/lang/StringBuilder.append:(Ljava/lang/String;)Ljava/lang/StringBuilder;
     204: pop
     205: aconst_null
     206: astore_2
     207: aload_0
     208: getfield      #20                 // Field buf:Lorg/apache/hadoop/hbase/nio/ByteBuff;
     211: invokevirtual #120                // Method org/apache/hadoop/hbase/nio/ByteBuff.hasArray:()Z
     214: ifeq          268
     217: aload_0
     218: getfield      #20                 // Field buf:Lorg/apache/hadoop/hbase/nio/ByteBuff;
     221: invokevirtual #121                // Method org/apache/hadoop/hbase/nio/ByteBuff.array:()[B
     224: aload_0
     225: getfield      #20                 // Field buf:Lorg/apache/hadoop/hbase/nio/ByteBuff;
     228: invokevirtual #122                // Method org/apache/hadoop/hbase/nio/ByteBuff.arrayOffset:()I
     231: aload_0
     232: invokevirtual #63                 // Method headerSize:()I
     235: iadd
     236: bipush        32
     238: aload_0
     239: getfield      #20                 // Field buf:Lorg/apache/hadoop/hbase/nio/ByteBuff;
     242: invokevirtual #21                 // Method org/apache/hadoop/hbase/nio/ByteBuff.limit:()I
     245: aload_0
     246: getfield      #20                 // Field buf:Lorg/apache/hadoop/hbase/nio/ByteBuff;
     249: invokevirtual #122                // Method org/apache/hadoop/hbase/nio/ByteBuff.arrayOffset:()I
     252: isub
     253: aload_0
     254: invokevirtual #63                 // Method headerSize:()I
     257: isub
     258: invokestatic  #123                // Method java/lang/Math.min:(II)I
     261: invokestatic  #124                // Method org/apache/hadoop/hbase/util/Bytes.toStringBinary:([BII)Ljava/lang/String;
     264: astore_2
     265: goto          303
     268: aload_0
     269: invokevirtual #125                // Method getBufferWithoutHeader:()Lorg/apache/hadoop/hbase/nio/ByteBuff;
     272: astore_3
     273: bipush        32
     275: aload_3
     276: invokevirtual #21                 // Method org/apache/hadoop/hbase/nio/ByteBuff.limit:()I
     279: aload_3
     280: invokevirtual #77                 // Method org/apache/hadoop/hbase/nio/ByteBuff.position:()I
     283: isub
     284: invokestatic  #123                // Method java/lang/Math.min:(II)I
     287: newarray       byte
     289: astore        4
     291: aload_3
     292: aload         4
     294: invokevirtual #126                // Method org/apache/hadoop/hbase/nio/ByteBuff.get:([B)V
     297: aload         4
     299: invokestatic  #127                // Method org/apache/hadoop/hbase/util/Bytes.toStringBinary:([B)Ljava/lang/String;
     302: astore_2
     303: aload_1
     304: ldc           #128                // String , getOnDiskSizeWithHeader=
     306: invokevirtual #58                 // Method java/lang/StringBuilder.append:(Ljava/lang/String;)Ljava/lang/StringBuilder;
     309: aload_0
     310: invokevirtual #129                // Method getOnDiskSizeWithHeader:()I
     313: invokevirtual #99                 // Method java/lang/StringBuilder.append:(I)Ljava/lang/StringBuilder;
     316: ldc           #130                // String , totalChecksumBytes=
     318: invokevirtual #58                 // Method java/lang/StringBuilder.append:(Ljava/lang/String;)Ljava/lang/StringBuilder;
     321: aload_0
     322: invokevirtual #74                 // Method totalChecksumBytes:()I
     325: invokevirtual #99                 // Method java/lang/StringBuilder.append:(I)Ljava/lang/StringBuilder;
     328: ldc           #131                // String , isUnpacked=
     330: invokevirtual #58                 // Method java/lang/StringBuilder.append:(Ljava/lang/String;)Ljava/lang/StringBuilder;
     333: aload_0
     334: invokevirtual #132                // Method isUnpacked:()Z
     337: invokevirtual #113                // Method java/lang/StringBuilder.append:(Z)Ljava/lang/StringBuilder;
     340: ldc           #133                // String , buf=[
     342: invokevirtual #58                 // Method java/lang/StringBuilder.append:(Ljava/lang/String;)Ljava/lang/StringBuilder;
     345: aload_0
     346: getfield      #20                 // Field buf:Lorg/apache/hadoop/hbase/nio/ByteBuff;
     349: invokevirtual #59                 // Method java/lang/StringBuilder.append:(Ljava/lang/Object;)Ljava/lang/StringBuilder;
     352: ldc           #134                // String ]
     354: invokevirtual #58                 // Method java/lang/StringBuilder.append:(Ljava/lang/String;)Ljava/lang/StringBuilder;
     357: ldc           #135                // String , dataBeginsWith=
     359: invokevirtual #58                 // Method java/lang/StringBuilder.append:(Ljava/lang/String;)Ljava/lang/StringBuilder;
     362: aload_2
     363: invokevirtual #58                 // Method java/lang/StringBuilder.append:(Ljava/lang/String;)Ljava/lang/StringBuilder;
     366: ldc           #136                // String , fileContext=
     368: invokevirtual #58                 // Method java/lang/StringBuilder.append:(Ljava/lang/String;)Ljava/lang/StringBuilder;
     371: aload_0
     372: getfield      #17                 // Field fileContext:Lorg/apache/hadoop/hbase/io/hfile/HFileContext;
     375: invokevirtual #59                 // Method java/lang/StringBuilder.append:(Ljava/lang/Object;)Ljava/lang/StringBuilder;
     378: ldc           #137                // String , nextBlockOnDiskSize=
     380: invokevirtual #58                 // Method java/lang/StringBuilder.append:(Ljava/lang/String;)Ljava/lang/StringBuilder;
     383: aload_0
     384: getfield      #11                 // Field nextBlockOnDiskSize:I
     387: invokevirtual #99                 // Method java/lang/StringBuilder.append:(I)Ljava/lang/StringBuilder;
     390: ldc           #134                // String ]
     392: invokevirtual #58                 // Method java/lang/StringBuilder.append:(Ljava/lang/String;)Ljava/lang/StringBuilder;
     395: pop
     396: aload_1
     397: invokevirtual #61                 // Method java/lang/StringBuilder.toString:()Ljava/lang/String;
     400: areturn

  org.apache.hadoop.hbase.io.hfile.HFileBlock unpack(org.apache.hadoop.hbase.io.hfile.HFileContext, org.apache.hadoop.hbase.io.hfile.HFileBlock$FSReader) throws java.io.IOException;
    Code:
       0: aload_1
       1: invokevirtual #138                // Method org/apache/hadoop/hbase/io/hfile/HFileContext.isCompressedOrEncrypted:()Z
       4: ifne          9
       7: aload_0
       8: areturn
       9: new           #139                // class org/apache/hadoop/hbase/io/hfile/HFileBlock
      12: dup
      13: aload_0
      14: invokespecial #140                // Method "<init>":(Lorg/apache/hadoop/hbase/io/hfile/HFileBlock;)V
      17: astore_3
      18: aload_3
      19: invokespecial #141                // Method allocateBuffer:()V
      22: aload_0
      23: getfield      #12                 // Field blockType:Lorg/apache/hadoop/hbase/io/hfile/BlockType;
      26: getstatic     #53                 // Field org/apache/hadoop/hbase/io/hfile/BlockType.ENCODED_DATA:Lorg/apache/hadoop/hbase/io/hfile/BlockType;
      29: if_acmpne     41
      32: aload_2
      33: invokeinterface #142,  1          // InterfaceMethod org/apache/hadoop/hbase/io/hfile/HFileBlock$FSReader.getBlockDecodingContext:()Lorg/apache/hadoop/hbase/io/encoding/HFileBlockDecodingContext;
      38: goto          47
      41: aload_2
      42: invokeinterface #143,  1          // InterfaceMethod org/apache/hadoop/hbase/io/hfile/HFileBlock$FSReader.getDefaultBlockDecodingContext:()Lorg/apache/hadoop/hbase/io/encoding/HFileBlockDecodingContext;
      47: astore        4
      49: aload_0
      50: getfield      #20                 // Field buf:Lorg/apache/hadoop/hbase/nio/ByteBuff;
      53: invokevirtual #25                 // Method org/apache/hadoop/hbase/nio/ByteBuff.duplicate:()Lorg/apache/hadoop/hbase/nio/ByteBuff;
      56: astore        5
      58: aload         5
      60: aload_0
      61: invokevirtual #63                 // Method headerSize:()I
      64: invokevirtual #73                 // Method org/apache/hadoop/hbase/nio/ByteBuff.position:(I)Lorg/apache/hadoop/hbase/nio/ByteBuff;
      67: pop
      68: aload         5
      70: invokevirtual #76                 // Method org/apache/hadoop/hbase/nio/ByteBuff.slice:()Lorg/apache/hadoop/hbase/nio/ByteBuff;
      73: astore        5
      75: aload         4
      77: aload_3
      78: invokevirtual #144                // Method getOnDiskSizeWithoutHeader:()I
      81: aload_3
      82: invokevirtual #145                // Method getUncompressedSizeWithoutHeader:()I
      85: aload_3
      86: invokevirtual #125                // Method getBufferWithoutHeader:()Lorg/apache/hadoop/hbase/nio/ByteBuff;
      89: aload         5
      91: invokeinterface #146,  5          // InterfaceMethod org/apache/hadoop/hbase/io/encoding/HFileBlockDecodingContext.prepareDecoding:(IILorg/apache/hadoop/hbase/nio/ByteBuff;Lorg/apache/hadoop/hbase/nio/ByteBuff;)V
      96: aload_3
      97: areturn

  public boolean isUnpacked();
    Code:
       0: aload_0
       1: invokevirtual #74                 // Method totalChecksumBytes:()I
       4: istore_1
       5: aload_0
       6: invokevirtual #63                 // Method headerSize:()I
       9: istore_2
      10: iload_2
      11: aload_0
      12: getfield      #14                 // Field uncompressedSizeWithoutHeader:I
      15: iadd
      16: iload_1
      17: iadd
      18: istore_3
      19: aload_0
      20: getfield      #20                 // Field buf:Lorg/apache/hadoop/hbase/nio/ByteBuff;
      23: invokevirtual #101                // Method org/apache/hadoop/hbase/nio/ByteBuff.capacity:()I
      26: istore        4
      28: iload         4
      30: iload_3
      31: if_icmpeq     42
      34: iload         4
      36: iload_3
      37: iload_2
      38: iadd
      39: if_icmpne     46
      42: iconst_1
      43: goto          47
      46: iconst_0
      47: ireturn

  void sanityCheckUncompressedSize() throws java.io.IOException;
    Code:
       0: aload_0
       1: getfield      #13                 // Field onDiskSizeWithoutHeader:I
       4: aload_0
       5: getfield      #14                 // Field uncompressedSizeWithoutHeader:I
       8: aload_0
       9: invokevirtual #74                 // Method totalChecksumBytes:()I
      12: iadd
      13: if_icmpeq     70
      16: new           #83                 // class java/io/IOException
      19: dup
      20: new           #55                 // class java/lang/StringBuilder
      23: dup
      24: invokespecial #56                 // Method java/lang/StringBuilder."<init>":()V
      27: ldc           #151                // String Using no compression but onDiskSizeWithoutHeader=
      29: invokevirtual #58                 // Method java/lang/StringBuilder.append:(Ljava/lang/String;)Ljava/lang/StringBuilder;
      32: aload_0
      33: getfield      #13                 // Field onDiskSizeWithoutHeader:I
      36: invokevirtual #99                 // Method java/lang/StringBuilder.append:(I)Ljava/lang/StringBuilder;
      39: ldc           #110                // String , uncompressedSizeWithoutHeader=
      41: invokevirtual #58                 // Method java/lang/StringBuilder.append:(Ljava/lang/String;)Ljava/lang/StringBuilder;
      44: aload_0
      45: getfield      #14                 // Field uncompressedSizeWithoutHeader:I
      48: invokevirtual #99                 // Method java/lang/StringBuilder.append:(I)Ljava/lang/StringBuilder;
      51: ldc           #152                // String , numChecksumbytes=
      53: invokevirtual #58                 // Method java/lang/StringBuilder.append:(Ljava/lang/String;)Ljava/lang/StringBuilder;
      56: aload_0
      57: invokevirtual #74                 // Method totalChecksumBytes:()I
      60: invokevirtual #99                 // Method java/lang/StringBuilder.append:(I)Ljava/lang/StringBuilder;
      63: invokevirtual #61                 // Method java/lang/StringBuilder.toString:()Ljava/lang/String;
      66: invokespecial #86                 // Method java/io/IOException."<init>":(Ljava/lang/String;)V
      69: athrow
      70: return

  long getOffset();
    Code:
       0: aload_0
       1: getfield      #8                  // Field offset:J
       4: lconst_0
       5: lcmp
       6: ifge          19
       9: new           #153                // class java/lang/IllegalStateException
      12: dup
      13: ldc           #154                // String HFile block offset not initialized properly
      15: invokespecial #155                // Method java/lang/IllegalStateException."<init>":(Ljava/lang/String;)V
      18: athrow
      19: aload_0
      20: getfield      #8                  // Field offset:J
      23: lreturn

  java.io.DataInputStream getByteStream();
    Code:
       0: aload_0
       1: getfield      #20                 // Field buf:Lorg/apache/hadoop/hbase/nio/ByteBuff;
       4: invokevirtual #25                 // Method org/apache/hadoop/hbase/nio/ByteBuff.duplicate:()Lorg/apache/hadoop/hbase/nio/ByteBuff;
       7: astore_1
       8: aload_1
       9: aload_0
      10: invokevirtual #63                 // Method headerSize:()I
      13: invokevirtual #73                 // Method org/apache/hadoop/hbase/nio/ByteBuff.position:(I)Lorg/apache/hadoop/hbase/nio/ByteBuff;
      16: pop
      17: new           #156                // class java/io/DataInputStream
      20: dup
      21: new           #157                // class org/apache/hadoop/hbase/io/ByteBuffInputStream
      24: dup
      25: aload_1
      26: invokespecial #158                // Method org/apache/hadoop/hbase/io/ByteBuffInputStream."<init>":(Lorg/apache/hadoop/hbase/nio/ByteBuff;)V
      29: invokespecial #159                // Method java/io/DataInputStream."<init>":(Ljava/io/InputStream;)V
      32: areturn

  public long heapSize();
    Code:
       0: getstatic     #160                // Field org/apache/hadoop/hbase/util/ClassSize.OBJECT:I
       3: iconst_4
       4: getstatic     #161                // Field org/apache/hadoop/hbase/util/ClassSize.REFERENCE:I
       7: imul
       8: iadd
       9: bipush        16
      11: iadd
      12: bipush        16
      14: iadd
      15: i2l
      16: aload_0
      17: getfield      #17                 // Field fileContext:Lorg/apache/hadoop/hbase/io/hfile/HFileContext;
      20: invokevirtual #162                // Method org/apache/hadoop/hbase/io/hfile/HFileContext.heapSize:()J
      23: ladd
      24: invokestatic  #163                // Method org/apache/hadoop/hbase/util/ClassSize.align:(J)J
      27: lstore_1
      28: aload_0
      29: getfield      #20                 // Field buf:Lorg/apache/hadoop/hbase/nio/ByteBuff;
      32: ifnull        53
      35: lload_1
      36: aload_0
      37: getfield      #20                 // Field buf:Lorg/apache/hadoop/hbase/nio/ByteBuff;
      40: invokevirtual #101                // Method org/apache/hadoop/hbase/nio/ByteBuff.capacity:()I
      43: getstatic     #164                // Field MULTI_BYTE_BUFFER_HEAP_SIZE:I
      46: iadd
      47: invokestatic  #165                // Method org/apache/hadoop/hbase/util/ClassSize.align:(I)I
      50: i2l
      51: ladd
      52: lstore_1
      53: lload_1
      54: invokestatic  #163                // Method org/apache/hadoop/hbase/util/ClassSize.align:(J)J
      57: lreturn

  static boolean readWithExtra(java.io.InputStream, byte[], int, int, int) throws java.io.IOException;
    Code:
       0: iload_3
       1: iload         4
       3: iadd
       4: istore        5
       6: iload         5
       8: ifle          119
      11: aload_0
      12: aload_1
      13: iload_2
      14: iload         5
      16: invokevirtual #166                // Method java/io/InputStream.read:([BII)I
      19: istore        6
      21: iload         6
      23: iconst_m1
      24: if_icmpne     37
      27: iload         5
      29: iload         4
      31: if_icmpgt     37
      34: goto          119
      37: iload         6
      39: ifge          104
      42: new           #83                 // class java/io/IOException
      45: dup
      46: new           #55                 // class java/lang/StringBuilder
      49: dup
      50: invokespecial #56                 // Method java/lang/StringBuilder."<init>":()V
      53: ldc           #167                // String Premature EOF from inputStream (read returned
      55: invokevirtual #58                 // Method java/lang/StringBuilder.append:(Ljava/lang/String;)Ljava/lang/StringBuilder;
      58: iload         6
      60: invokevirtual #99                 // Method java/lang/StringBuilder.append:(I)Ljava/lang/StringBuilder;
      63: ldc           #168                // String , was trying to read
      65: invokevirtual #58                 // Method java/lang/StringBuilder.append:(Ljava/lang/String;)Ljava/lang/StringBuilder;
      68: iload_3
      69: invokevirtual #99                 // Method java/lang/StringBuilder.append:(I)Ljava/lang/StringBuilder;
      72: ldc           #169                // String  necessary bytes and
      74: invokevirtual #58                 // Method java/lang/StringBuilder.append:(Ljava/lang/String;)Ljava/lang/StringBuilder;
      77: iload         4
      79: invokevirtual #99                 // Method java/lang/StringBuilder.append:(I)Ljava/lang/StringBuilder;
      82: ldc           #170                // String  extra bytes, successfully read
      84: invokevirtual #58                 // Method java/lang/StringBuilder.append:(Ljava/lang/String;)Ljava/lang/StringBuilder;
      87: iload_3
      88: iload         4
      90: iadd
      91: iload         5
      93: isub
      94: invokevirtual #99                 // Method java/lang/StringBuilder.append:(I)Ljava/lang/StringBuilder;
      97: invokevirtual #61                 // Method java/lang/StringBuilder.toString:()Ljava/lang/String;
     100: invokespecial #86                 // Method java/io/IOException."<init>":(Ljava/lang/String;)V
     103: athrow
     104: iload_2
     105: iload         6
     107: iadd
     108: istore_2
     109: iload         5
     111: iload         6
     113: isub
     114: istore        5
     116: goto          6
     119: iload         5
     121: ifgt          128
     124: iconst_1
     125: goto          129
     128: iconst_0
     129: ireturn

  static boolean positionalReadWithExtra(org.apache.hadoop.fs.FSDataInputStream, long, byte[], int, int, int) throws java.io.IOException;
    Code:
       0: iload         5
       2: iload         6
       4: iadd
       5: istore        7
       7: iconst_0
       8: istore        8
      10: iload         8
      12: iload         5
      14: if_icmpge     122
      17: aload_0
      18: lload_1
      19: aload_3
      20: iload         4
      22: iload         7
      24: invokevirtual #171                // Method org/apache/hadoop/fs/FSDataInputStream.read:(J[BII)I
      27: istore        9
      29: iload         9
      31: ifge          92
      34: new           #83                 // class java/io/IOException
      37: dup
      38: new           #55                 // class java/lang/StringBuilder
      41: dup
      42: invokespecial #56                 // Method java/lang/StringBuilder."<init>":()V
      45: ldc           #172                // String Premature EOF from inputStream (positional read returned
      47: invokevirtual #58                 // Method java/lang/StringBuilder.append:(Ljava/lang/String;)Ljava/lang/StringBuilder;
      50: iload         9
      52: invokevirtual #99                 // Method java/lang/StringBuilder.append:(I)Ljava/lang/StringBuilder;
      55: ldc           #168                // String , was trying to read
      57: invokevirtual #58                 // Method java/lang/StringBuilder.append:(Ljava/lang/String;)Ljava/lang/StringBuilder;
      60: iload         5
      62: invokevirtual #99                 // Method java/lang/StringBuilder.append:(I)Ljava/lang/StringBuilder;
      65: ldc           #169                // String  necessary bytes and
      67: invokevirtual #58                 // Method java/lang/StringBuilder.append:(Ljava/lang/String;)Ljava/lang/StringBuilder;
      70: iload         6
      72: invokevirtual #99                 // Method java/lang/StringBuilder.append:(I)Ljava/lang/StringBuilder;
      75: ldc           #170                // String  extra bytes, successfully read
      77: invokevirtual #58                 // Method java/lang/StringBuilder.append:(Ljava/lang/String;)Ljava/lang/StringBuilder;
      80: iload         8
      82: invokevirtual #99                 // Method java/lang/StringBuilder.append:(I)Ljava/lang/StringBuilder;
      85: invokevirtual #61                 // Method java/lang/StringBuilder.toString:()Ljava/lang/String;
      88: invokespecial #86                 // Method java/io/IOException."<init>":(Ljava/lang/String;)V
      91: athrow
      92: lload_1
      93: iload         9
      95: i2l
      96: ladd
      97: lstore_1
      98: iload         4
     100: iload         9
     102: iadd
     103: istore        4
     105: iload         7
     107: iload         9
     109: isub
     110: istore        7
     112: iload         8
     114: iload         9
     116: iadd
     117: istore        8
     119: goto          10
     122: iload         8
     124: iload         5
     126: if_icmpeq     138
     129: iload         7
     131: ifgt          138
     134: iconst_1
     135: goto          139
     138: iconst_0
     139: ireturn

  void sanityCheckUncompressed() throws java.io.IOException;
    Code:
       0: aload_0
       1: getfield      #13                 // Field onDiskSizeWithoutHeader:I
       4: aload_0
       5: getfield      #14                 // Field uncompressedSizeWithoutHeader:I
       8: aload_0
       9: invokevirtual #74                 // Method totalChecksumBytes:()I
      12: iadd
      13: if_icmpeq     70
      16: new           #83                 // class java/io/IOException
      19: dup
      20: new           #55                 // class java/lang/StringBuilder
      23: dup
      24: invokespecial #56                 // Method java/lang/StringBuilder."<init>":()V
      27: ldc           #151                // String Using no compression but onDiskSizeWithoutHeader=
      29: invokevirtual #58                 // Method java/lang/StringBuilder.append:(Ljava/lang/String;)Ljava/lang/StringBuilder;
      32: aload_0
      33: getfield      #13                 // Field onDiskSizeWithoutHeader:I
      36: invokevirtual #99                 // Method java/lang/StringBuilder.append:(I)Ljava/lang/StringBuilder;
      39: ldc           #110                // String , uncompressedSizeWithoutHeader=
      41: invokevirtual #58                 // Method java/lang/StringBuilder.append:(Ljava/lang/String;)Ljava/lang/StringBuilder;
      44: aload_0
      45: getfield      #14                 // Field uncompressedSizeWithoutHeader:I
      48: invokevirtual #99                 // Method java/lang/StringBuilder.append:(I)Ljava/lang/StringBuilder;
      51: ldc           #152                // String , numChecksumbytes=
      53: invokevirtual #58                 // Method java/lang/StringBuilder.append:(Ljava/lang/String;)Ljava/lang/StringBuilder;
      56: aload_0
      57: invokevirtual #74                 // Method totalChecksumBytes:()I
      60: invokevirtual #99                 // Method java/lang/StringBuilder.append:(I)Ljava/lang/StringBuilder;
      63: invokevirtual #61                 // Method java/lang/StringBuilder.toString:()Ljava/lang/String;
      66: invokespecial #86                 // Method java/io/IOException."<init>":(Ljava/lang/String;)V
      69: athrow
      70: return

  public int getSerializedLength();
    Code:
       0: aload_0
       1: getfield      #20                 // Field buf:Lorg/apache/hadoop/hbase/nio/ByteBuff;
       4: ifnull        18
       7: aload_0
       8: getfield      #20                 // Field buf:Lorg/apache/hadoop/hbase/nio/ByteBuff;
      11: invokevirtual #21                 // Method org/apache/hadoop/hbase/nio/ByteBuff.limit:()I
      14: bipush        13
      16: iadd
      17: ireturn
      18: iconst_0
      19: ireturn

  public void serialize(java.nio.ByteBuffer, boolean);
    Code:
       0: aload_0
       1: getfield      #20                 // Field buf:Lorg/apache/hadoop/hbase/nio/ByteBuff;
       4: aload_1
       5: iconst_0
       6: aload_0
       7: invokevirtual #173                // Method getSerializedLength:()I
      10: bipush        13
      12: isub
      13: invokevirtual #174                // Method org/apache/hadoop/hbase/nio/ByteBuff.get:(Ljava/nio/ByteBuffer;II)V
      16: aload_0
      17: aload_1
      18: iload_2
      19: invokespecial #175                // Method addMetaData:(Ljava/nio/ByteBuffer;Z)Ljava/nio/ByteBuffer;
      22: astore_1
      23: aload_1
      24: invokevirtual #176                // Method java/nio/ByteBuffer.flip:()Ljava/nio/Buffer;
      27: pop
      28: return

  public java.nio.ByteBuffer getMetaData();
    Code:
       0: bipush        13
       2: invokestatic  #147                // Method java/nio/ByteBuffer.allocate:(I)Ljava/nio/ByteBuffer;
       5: astore_1
       6: aload_0
       7: aload_1
       8: iconst_1
       9: invokespecial #175                // Method addMetaData:(Ljava/nio/ByteBuffer;Z)Ljava/nio/ByteBuffer;
      12: astore_1
      13: aload_1
      14: invokevirtual #176                // Method java/nio/ByteBuffer.flip:()Ljava/nio/Buffer;
      17: pop
      18: aload_1
      19: areturn

  public org.apache.hadoop.hbase.io.hfile.CacheableDeserializer<org.apache.hadoop.hbase.io.hfile.Cacheable> getDeserializer();
    Code:
       0: getstatic     #180                // Field BLOCK_DESERIALIZER:Lorg/apache/hadoop/hbase/io/hfile/CacheableDeserializer;
       3: areturn

  public int hashCode();
    Code:
       0: iconst_1
       1: istore_1
       2: iload_1
       3: bipush        31
       5: imul
       6: aload_0
       7: getfield      #12                 // Field blockType:Lorg/apache/hadoop/hbase/io/hfile/BlockType;
      10: invokevirtual #181                // Method org/apache/hadoop/hbase/io/hfile/BlockType.hashCode:()I
      13: iadd
      14: istore_1
      15: iload_1
      16: bipush        31
      18: imul
      19: aload_0
      20: getfield      #11                 // Field nextBlockOnDiskSize:I
      23: iadd
      24: istore_1
      25: iload_1
      26: bipush        31
      28: imul
      29: aload_0
      30: getfield      #8                  // Field offset:J
      33: aload_0
      34: getfield      #8                  // Field offset:J
      37: bipush        32
      39: lushr
      40: lxor
      41: l2i
      42: iadd
      43: istore_1
      44: iload_1
      45: bipush        31
      47: imul
      48: aload_0
      49: getfield      #13                 // Field onDiskSizeWithoutHeader:I
      52: iadd
      53: istore_1
      54: iload_1
      55: bipush        31
      57: imul
      58: aload_0
      59: getfield      #15                 // Field prevBlockOffset:J
      62: aload_0
      63: getfield      #15                 // Field prevBlockOffset:J
      66: bipush        32
      68: lushr
      69: lxor
      70: l2i
      71: iadd
      72: istore_1
      73: iload_1
      74: bipush        31
      76: imul
      77: aload_0
      78: getfield      #14                 // Field uncompressedSizeWithoutHeader:I
      81: iadd
      82: istore_1
      83: iload_1
      84: bipush        31
      86: imul
      87: aload_0
      88: getfield      #20                 // Field buf:Lorg/apache/hadoop/hbase/nio/ByteBuff;
      91: invokevirtual #182                // Method java/lang/Object.hashCode:()I
      94: iadd
      95: istore_1
      96: iload_1
      97: ireturn

  public boolean equals(java.lang.Object);
    Code:
       0: aload_0
       1: aload_1
       2: if_acmpne     7
       5: iconst_1
       6: ireturn
       7: aload_1
       8: ifnonnull     13
      11: iconst_0
      12: ireturn
      13: aload_1
      14: invokevirtual #183                // Method java/lang/Object.getClass:()Ljava/lang/Class;
      17: aload_0
      18: invokevirtual #183                // Method java/lang/Object.getClass:()Ljava/lang/Class;
      21: if_acmpeq     26
      24: iconst_0
      25: ireturn
      26: aload_1
      27: checkcast     #139                // class org/apache/hadoop/hbase/io/hfile/HFileBlock
      30: astore_2
      31: aload_2
      32: getfield      #12                 // Field blockType:Lorg/apache/hadoop/hbase/io/hfile/BlockType;
      35: aload_0
      36: getfield      #12                 // Field blockType:Lorg/apache/hadoop/hbase/io/hfile/BlockType;
      39: if_acmpeq     44
      42: iconst_0
      43: ireturn
      44: aload_2
      45: getfield      #11                 // Field nextBlockOnDiskSize:I
      48: aload_0
      49: getfield      #11                 // Field nextBlockOnDiskSize:I
      52: if_icmpeq     57
      55: iconst_0
      56: ireturn
      57: aload_2
      58: getfield      #8                  // Field offset:J
      61: aload_0
      62: getfield      #8                  // Field offset:J
      65: lcmp
      66: ifeq          71
      69: iconst_0
      70: ireturn
      71: aload_2
      72: getfield      #13                 // Field onDiskSizeWithoutHeader:I
      75: aload_0
      76: getfield      #13                 // Field onDiskSizeWithoutHeader:I
      79: if_icmpeq     84
      82: iconst_0
      83: ireturn
      84: aload_2
      85: getfield      #15                 // Field prevBlockOffset:J
      88: aload_0
      89: getfield      #15                 // Field prevBlockOffset:J
      92: lcmp
      93: ifeq          98
      96: iconst_0
      97: ireturn
      98: aload_2
      99: getfield      #14                 // Field uncompressedSizeWithoutHeader:I
     102: aload_0
     103: getfield      #14                 // Field uncompressedSizeWithoutHeader:I
     106: if_icmpeq     111
     109: iconst_0
     110: ireturn
     111: aload_0
     112: getfield      #20                 // Field buf:Lorg/apache/hadoop/hbase/nio/ByteBuff;
     115: iconst_0
     116: aload_0
     117: getfield      #20                 // Field buf:Lorg/apache/hadoop/hbase/nio/ByteBuff;
     120: invokevirtual #21                 // Method org/apache/hadoop/hbase/nio/ByteBuff.limit:()I
     123: aload_2
     124: getfield      #20                 // Field buf:Lorg/apache/hadoop/hbase/nio/ByteBuff;
     127: iconst_0
     128: aload_2
     129: getfield      #20                 // Field buf:Lorg/apache/hadoop/hbase/nio/ByteBuff;
     132: invokevirtual #21                 // Method org/apache/hadoop/hbase/nio/ByteBuff.limit:()I
     135: invokestatic  #184                // Method org/apache/hadoop/hbase/nio/ByteBuff.compareTo:(Lorg/apache/hadoop/hbase/nio/ByteBuff;IILorg/apache/hadoop/hbase/nio/ByteBuff;II)I
     138: ifeq          143
     141: iconst_0
     142: ireturn
     143: iconst_1
     144: ireturn

  org.apache.hadoop.hbase.io.encoding.DataBlockEncoding getDataBlockEncoding();
    Code:
       0: aload_0
       1: getfield      #12                 // Field blockType:Lorg/apache/hadoop/hbase/io/hfile/BlockType;
       4: getstatic     #53                 // Field org/apache/hadoop/hbase/io/hfile/BlockType.ENCODED_DATA:Lorg/apache/hadoop/hbase/io/hfile/BlockType;
       7: if_acmpne     18
      10: aload_0
      11: invokevirtual #185                // Method getDataBlockEncodingId:()S
      14: invokestatic  #186                // Method org/apache/hadoop/hbase/io/encoding/DataBlockEncoding.getEncodingById:(S)Lorg/apache/hadoop/hbase/io/encoding/DataBlockEncoding;
      17: areturn
      18: getstatic     #187                // Field org/apache/hadoop/hbase/io/encoding/DataBlockEncoding.NONE:Lorg/apache/hadoop/hbase/io/encoding/DataBlockEncoding;
      21: areturn

  byte getChecksumType();
    Code:
       0: aload_0
       1: getfield      #17                 // Field fileContext:Lorg/apache/hadoop/hbase/io/hfile/HFileContext;
       4: invokevirtual #68                 // Method org/apache/hadoop/hbase/io/hfile/HFileContext.getChecksumType:()Lorg/apache/hadoop/hbase/util/ChecksumType;
       7: invokevirtual #69                 // Method org/apache/hadoop/hbase/util/ChecksumType.getCode:()B
      10: ireturn

  int getBytesPerChecksum();
    Code:
       0: aload_0
       1: getfield      #17                 // Field fileContext:Lorg/apache/hadoop/hbase/io/hfile/HFileContext;
       4: invokevirtual #71                 // Method org/apache/hadoop/hbase/io/hfile/HFileContext.getBytesPerChecksum:()I
       7: ireturn

  int getOnDiskDataSizeWithHeader();
    Code:
       0: aload_0
       1: getfield      #16                 // Field onDiskDataSizeWithHeader:I
       4: ireturn

  int totalChecksumBytes();
    Code:
       0: aload_0
       1: getfield      #17                 // Field fileContext:Lorg/apache/hadoop/hbase/io/hfile/HFileContext;
       4: invokevirtual #49                 // Method org/apache/hadoop/hbase/io/hfile/HFileContext.isUseHBaseChecksum:()Z
       7: ifeq          20
      10: aload_0
      11: getfield      #17                 // Field fileContext:Lorg/apache/hadoop/hbase/io/hfile/HFileContext;
      14: invokevirtual #71                 // Method org/apache/hadoop/hbase/io/hfile/HFileContext.getBytesPerChecksum:()I
      17: ifne          22
      20: iconst_0
      21: ireturn
      22: aload_0
      23: getfield      #16                 // Field onDiskDataSizeWithHeader:I
      26: i2l
      27: aload_0
      28: getfield      #17                 // Field fileContext:Lorg/apache/hadoop/hbase/io/hfile/HFileContext;
      31: invokevirtual #71                 // Method org/apache/hadoop/hbase/io/hfile/HFileContext.getBytesPerChecksum:()I
      34: invokestatic  #188                // Method org/apache/hadoop/hbase/io/hfile/ChecksumUtil.numBytes:(JI)J
      37: l2i
      38: ireturn

  public int headerSize();
    Code:
       0: aload_0
       1: getfield      #17                 // Field fileContext:Lorg/apache/hadoop/hbase/io/hfile/HFileContext;
       4: invokevirtual #49                 // Method org/apache/hadoop/hbase/io/hfile/HFileContext.isUseHBaseChecksum:()Z
       7: invokestatic  #46                 // Method headerSize:(Z)I
      10: ireturn

  public static int headerSize(boolean);
    Code:
       0: iload_0
       1: ifeq          9
       4: bipush        33
       6: goto          11
       9: bipush        24
      11: ireturn

  byte[] getDummyHeaderForVersion();
    Code:
       0: aload_0
       1: getfield      #17                 // Field fileContext:Lorg/apache/hadoop/hbase/io/hfile/HFileContext;
       4: invokevirtual #49                 // Method org/apache/hadoop/hbase/io/hfile/HFileContext.isUseHBaseChecksum:()Z
       7: invokestatic  #189                // Method getDummyHeaderForVersion:(Z)[B
      10: areturn

  org.apache.hadoop.hbase.io.hfile.HFileContext getHFileContext();
    Code:
       0: aload_0
       1: getfield      #17                 // Field fileContext:Lorg/apache/hadoop/hbase/io/hfile/HFileContext;
       4: areturn

  public org.apache.hadoop.hbase.io.hfile.Cacheable$MemoryType getMemoryType();
    Code:
       0: aload_0
       1: getfield      #10                 // Field memType:Lorg/apache/hadoop/hbase/io/hfile/Cacheable$MemoryType;
       4: areturn

  boolean usesSharedMemory();
    Code:
       0: aload_0
       1: getfield      #10                 // Field memType:Lorg/apache/hadoop/hbase/io/hfile/Cacheable$MemoryType;
       4: getstatic     #192                // Field org/apache/hadoop/hbase/io/hfile/Cacheable$MemoryType.SHARED:Lorg/apache/hadoop/hbase/io/hfile/Cacheable$MemoryType;
       7: if_acmpne     14
      10: iconst_1
      11: goto          15
      14: iconst_0
      15: ireturn

  static java.lang.String toStringHeader(org.apache.hadoop.hbase.nio.ByteBuff) throws java.io.IOException;
    Code:
       0: aload_0
       1: invokevirtual #21                 // Method org/apache/hadoop/hbase/nio/ByteBuff.limit:()I
       4: aload_0
       5: invokevirtual #77                 // Method org/apache/hadoop/hbase/nio/ByteBuff.position:()I
       8: isub
       9: bipush        8
      11: invokestatic  #123                // Method java/lang/Math.min:(II)I
      14: newarray       byte
      16: astore_1
      17: aload_0
      18: aload_1
      19: invokevirtual #126                // Method org/apache/hadoop/hbase/nio/ByteBuff.get:([B)V
      22: aload_1
      23: iconst_0
      24: bipush        8
      26: invokestatic  #194                // Method org/apache/hadoop/hbase/io/hfile/BlockType.parse:([BII)Lorg/apache/hadoop/hbase/io/hfile/BlockType;
      29: astore_2
      30: aload_0
      31: invokevirtual #88                 // Method org/apache/hadoop/hbase/nio/ByteBuff.getInt:()I
      34: istore_3
      35: aload_0
      36: invokevirtual #88                 // Method org/apache/hadoop/hbase/nio/ByteBuff.getInt:()I
      39: istore        4
      41: aload_0
      42: invokevirtual #92                 // Method org/apache/hadoop/hbase/nio/ByteBuff.getLong:()J
      45: lstore        5
      47: aload_0
      48: invokevirtual #94                 // Method org/apache/hadoop/hbase/nio/ByteBuff.get:()B
      51: istore        7
      53: aload_0
      54: invokevirtual #88                 // Method org/apache/hadoop/hbase/nio/ByteBuff.getInt:()I
      57: i2l
      58: lstore        8
      60: aload_0
      61: invokevirtual #88                 // Method org/apache/hadoop/hbase/nio/ByteBuff.getInt:()I
      64: i2l
      65: lstore        10
      67: new           #55                 // class java/lang/StringBuilder
      70: dup
      71: invokespecial #56                 // Method java/lang/StringBuilder."<init>":()V
      74: ldc           #195                // String  Header dump: magic:
      76: invokevirtual #58                 // Method java/lang/StringBuilder.append:(Ljava/lang/String;)Ljava/lang/StringBuilder;
      79: aload_1
      80: invokestatic  #196                // Method org/apache/hadoop/hbase/util/Bytes.toString:([B)Ljava/lang/String;
      83: invokevirtual #58                 // Method java/lang/StringBuilder.append:(Ljava/lang/String;)Ljava/lang/StringBuilder;
      86: ldc           #197                // String  blockType
      88: invokevirtual #58                 // Method java/lang/StringBuilder.append:(Ljava/lang/String;)Ljava/lang/StringBuilder;
      91: aload_2
      92: invokevirtual #59                 // Method java/lang/StringBuilder.append:(Ljava/lang/Object;)Ljava/lang/StringBuilder;
      95: ldc           #198                // String  compressedBlockSizeNoHeader
      97: invokevirtual #58                 // Method java/lang/StringBuilder.append:(Ljava/lang/String;)Ljava/lang/StringBuilder;
     100: iload_3
     101: invokevirtual #99                 // Method java/lang/StringBuilder.append:(I)Ljava/lang/StringBuilder;
     104: ldc           #199                // String  uncompressedBlockSizeNoHeader
     106: invokevirtual #58                 // Method java/lang/StringBuilder.append:(Ljava/lang/String;)Ljava/lang/StringBuilder;
     109: iload         4
     111: invokevirtual #99                 // Method java/lang/StringBuilder.append:(I)Ljava/lang/StringBuilder;
     114: ldc           #200                // String  prevBlockOffset
     116: invokevirtual #58                 // Method java/lang/StringBuilder.append:(Ljava/lang/String;)Ljava/lang/StringBuilder;
     119: lload         5
     121: invokevirtual #79                 // Method java/lang/StringBuilder.append:(J)Ljava/lang/StringBuilder;
     124: ldc           #201                // String  checksumType
     126: invokevirtual #58                 // Method java/lang/StringBuilder.append:(Ljava/lang/String;)Ljava/lang/StringBuilder;
     129: iload         7
     131: invokestatic  #42                 // Method org/apache/hadoop/hbase/util/ChecksumType.codeToType:(B)Lorg/apache/hadoop/hbase/util/ChecksumType;
     134: invokevirtual #59                 // Method java/lang/StringBuilder.append:(Ljava/lang/Object;)Ljava/lang/StringBuilder;
     137: ldc           #202                // String  bytesPerChecksum
     139: invokevirtual #58                 // Method java/lang/StringBuilder.append:(Ljava/lang/String;)Ljava/lang/StringBuilder;
     142: lload         8
     144: invokevirtual #79                 // Method java/lang/StringBuilder.append:(J)Ljava/lang/StringBuilder;
     147: ldc           #203                // String  onDiskDataSizeWithHeader
     149: invokevirtual #58                 // Method java/lang/StringBuilder.append:(Ljava/lang/String;)Ljava/lang/StringBuilder;
     152: lload         10
     154: invokevirtual #79                 // Method java/lang/StringBuilder.append:(J)Ljava/lang/StringBuilder;
     157: invokevirtual #61                 // Method java/lang/StringBuilder.toString:()Ljava/lang/String;
     160: areturn

  public org.apache.hadoop.hbase.io.hfile.HFileBlock deepClone();
    Code:
       0: new           #139                // class org/apache/hadoop/hbase/io/hfile/HFileBlock
       3: dup
       4: aload_0
       5: iconst_1
       6: invokespecial #6                  // Method "<init>":(Lorg/apache/hadoop/hbase/io/hfile/HFileBlock;Z)V
       9: areturn

  static int access$100();
    Code:
       0: getstatic     #5                  // Field DESERIALIZER_IDENTIFIER:I
       3: ireturn

  static int access$200();
    Code:
       0: getstatic     #4                  // Field UNSET:I
       3: ireturn

  static int access$500(java.nio.ByteBuffer, boolean);
    Code:
       0: aload_0
       1: iload_1
       2: invokestatic  #3                  // Method getOnDiskSizeWithHeader:(Ljava/nio/ByteBuffer;Z)I
       5: ireturn

  static org.slf4j.Logger access$600();
    Code:
       0: getstatic     #2                  // Field LOG:Lorg/slf4j/Logger;
       3: areturn

  static {};
    Code:
       0: ldc           #139                // class org/apache/hadoop/hbase/io/hfile/HFileBlock
       2: invokevirtual #204                // Method java/lang/Class.desiredAssertionStatus:()Z
       5: ifne          12
       8: iconst_1
       9: goto          13
      12: iconst_0
      13: putstatic     #48                 // Field $assertionsDisabled:Z
      16: ldc           #139                // class org/apache/hadoop/hbase/io/hfile/HFileBlock
      18: invokestatic  #205                // Method org/slf4j/LoggerFactory.getLogger:(Ljava/lang/Class;)Lorg/slf4j/Logger;
      21: putstatic     #2                  // Field LOG:Lorg/slf4j/Logger;
      24: iconst_m1
      25: putstatic     #4                  // Field UNSET:I
      28: ldc           #206                // class org/apache/hadoop/hbase/nio/MultiByteBuff
      30: iconst_0
      31: invokestatic  #207                // Method org/apache/hadoop/hbase/util/ClassSize.estimateBase:(Ljava/lang/Class;Z)J
      34: l2i
      35: putstatic     #164                // Field MULTI_BYTE_BUFFER_HEAP_SIZE:I
      38: bipush        24
      40: newarray       byte
      42: putstatic     #191                // Field DUMMY_HEADER_NO_CHECKSUM:[B
      45: new           #208                // class org/apache/hadoop/hbase/io/hfile/HFileBlock$BlockDeserializer
      48: dup
      49: aconst_null
      50: invokespecial #209                // Method org/apache/hadoop/hbase/io/hfile/HFileBlock$BlockDeserializer."<init>":(Lorg/apache/hadoop/hbase/io/hfile/HFileBlock$1;)V
      53: putstatic     #180                // Field BLOCK_DESERIALIZER:Lorg/apache/hadoop/hbase/io/hfile/CacheableDeserializer;
      56: getstatic     #180                // Field BLOCK_DESERIALIZER:Lorg/apache/hadoop/hbase/io/hfile/CacheableDeserializer;
      59: invokestatic  #210                // Method org/apache/hadoop/hbase/io/hfile/CacheableDeserializerIdManager.registerDeserializer:(Lorg/apache/hadoop/hbase/io/hfile/CacheableDeserializer;)I
      62: putstatic     #5                  // Field DESERIALIZER_IDENTIFIER:I
      65: return
}
