Compiled from "HFileSystem.java"
class org.apache.hadoop.hbase.fs.HFileSystem$ReorderWALBlocks implements org.apache.hadoop.hbase.fs.HFileSystem$ReorderBlocks {
  org.apache.hadoop.hbase.fs.HFileSystem$ReorderWALBlocks();
    Code:
       0: aload_0
       1: invokespecial #1                  // Method java/lang/Object."<init>":()V
       4: return

  public void reorderBlocks(org.apache.hadoop.conf.Configuration, org.apache.hadoop.hdfs.protocol.LocatedBlocks, java.lang.String) throws java.io.IOException;
    Code:
       0: aload_1
       1: aload_3
       2: invokestatic  #2                  // Method org/apache/hadoop/hbase/wal/AbstractFSWALProvider.getServerNameFromWALDirectoryName:(Lorg/apache/hadoop/conf/Configuration;Ljava/lang/String;)Lorg/apache/hadoop/hbase/ServerName;
       5: astore        4
       7: aload         4
       9: ifnonnull     13
      12: return
      13: aload         4
      15: invokevirtual #3                  // Method org/apache/hadoop/hbase/ServerName.getHostname:()Ljava/lang/String;
      18: astore        5
      20: getstatic     #4                  // Field org/apache/hadoop/hbase/fs/HFileSystem.LOG:Lorg/slf4j/Logger;
      23: invokeinterface #5,  1            // InterfaceMethod org/slf4j/Logger.isTraceEnabled:()Z
      28: ifeq          63
      31: getstatic     #4                  // Field org/apache/hadoop/hbase/fs/HFileSystem.LOG:Lorg/slf4j/Logger;
      34: new           #6                  // class java/lang/StringBuilder
      37: dup
      38: invokespecial #7                  // Method java/lang/StringBuilder."<init>":()V
      41: aload_3
      42: invokevirtual #8                  // Method java/lang/StringBuilder.append:(Ljava/lang/String;)Ljava/lang/StringBuilder;
      45: ldc           #9                  // String  is an WAL file, so reordering blocks, last hostname will be:
      47: invokevirtual #8                  // Method java/lang/StringBuilder.append:(Ljava/lang/String;)Ljava/lang/StringBuilder;
      50: aload         5
      52: invokevirtual #8                  // Method java/lang/StringBuilder.append:(Ljava/lang/String;)Ljava/lang/StringBuilder;
      55: invokevirtual #10                 // Method java/lang/StringBuilder.toString:()Ljava/lang/String;
      58: invokeinterface #11,  2           // InterfaceMethod org/slf4j/Logger.trace:(Ljava/lang/String;)V
      63: aload_2
      64: invokevirtual #12                 // Method org/apache/hadoop/hdfs/protocol/LocatedBlocks.getLocatedBlocks:()Ljava/util/List;
      67: invokeinterface #13,  1           // InterfaceMethod java/util/List.iterator:()Ljava/util/Iterator;
      72: astore        6
      74: aload         6
      76: invokeinterface #14,  1           // InterfaceMethod java/util/Iterator.hasNext:()Z
      81: ifeq          202
      84: aload         6
      86: invokeinterface #15,  1           // InterfaceMethod java/util/Iterator.next:()Ljava/lang/Object;
      91: checkcast     #16                 // class org/apache/hadoop/hdfs/protocol/LocatedBlock
      94: astore        7
      96: aload         7
      98: invokevirtual #17                 // Method org/apache/hadoop/hdfs/protocol/LocatedBlock.getLocations:()[Lorg/apache/hadoop/hdfs/protocol/DatanodeInfo;
     101: astore        8
     103: aload         8
     105: ifnull        199
     108: aload         8
     110: arraylength
     111: iconst_1
     112: if_icmple     199
     115: iconst_0
     116: istore        9
     118: iconst_0
     119: istore        10
     121: iload         10
     123: aload         8
     125: arraylength
     126: iconst_1
     127: isub
     128: if_icmpge     199
     131: iload         9
     133: ifne          199
     136: aload         5
     138: aload         8
     140: iload         10
     142: aaload
     143: invokevirtual #18                 // Method org/apache/hadoop/hdfs/protocol/DatanodeInfo.getHostName:()Ljava/lang/String;
     146: invokevirtual #19                 // Method java/lang/String.equals:(Ljava/lang/Object;)Z
     149: ifeq          193
     152: aload         8
     154: iload         10
     156: aaload
     157: astore        11
     159: aload         8
     161: iload         10
     163: iconst_1
     164: iadd
     165: aload         8
     167: iload         10
     169: aload         8
     171: arraylength
     172: iload         10
     174: isub
     175: iconst_1
     176: isub
     177: invokestatic  #20                 // Method java/lang/System.arraycopy:(Ljava/lang/Object;ILjava/lang/Object;II)V
     180: aload         8
     182: aload         8
     184: arraylength
     185: iconst_1
     186: isub
     187: aload         11
     189: aastore
     190: iconst_1
     191: istore        9
     193: iinc          10, 1
     196: goto          121
     199: goto          74
     202: return
}
