Compiled from "HFileProtos.java"
final class org.apache.hadoop.hbase.protobuf.generated.HFileProtos$1 implements com.google.protobuf.Descriptors$FileDescriptor$InternalDescriptorAssigner {
  org.apache.hadoop.hbase.protobuf.generated.HFileProtos$1();
    Code:
       0: aload_0
       1: invokespecial #1                  // Method java/lang/Object."<init>":()V
       4: return

  public com.google.protobuf.ExtensionRegistry assignDescriptors(com.google.protobuf.Descriptors$FileDescriptor);
    Code:
       0: aload_1
       1: invokestatic  #2                  // Method org/apache/hadoop/hbase/protobuf/generated/HFileProtos.access$3002:(Lcom/google/protobuf/Descriptors$FileDescriptor;)Lcom/google/protobuf/Descriptors$FileDescriptor;
       4: pop
       5: invokestatic  #3                  // Method org/apache/hadoop/hbase/protobuf/generated/HFileProtos.getDescriptor:()Lcom/google/protobuf/Descriptors$FileDescriptor;
       8: invokevirtual #4                  // Method com/google/protobuf/Descriptors$FileDescriptor.getMessageTypes:()Ljava/util/List;
      11: iconst_0
      12: invokeinterface #5,  2            // InterfaceMethod java/util/List.get:(I)Ljava/lang/Object;
      17: checkcast     #6                  // class com/google/protobuf/Descriptors$Descriptor
      20: invokestatic  #7                  // Method org/apache/hadoop/hbase/protobuf/generated/HFileProtos.access$002:(Lcom/google/protobuf/Descriptors$Descriptor;)Lcom/google/protobuf/Descriptors$Descriptor;
      23: pop
      24: new           #8                  // class com/google/protobuf/GeneratedMessage$FieldAccessorTable
      27: dup
      28: invokestatic  #9                  // Method org/apache/hadoop/hbase/protobuf/generated/HFileProtos.access$000:()Lcom/google/protobuf/Descriptors$Descriptor;
      31: iconst_1
      32: anewarray     #10                 // class java/lang/String
      35: dup
      36: iconst_0
      37: ldc           #11                 // String MapEntry
      39: aastore
      40: invokespecial #12                 // Method com/google/protobuf/GeneratedMessage$FieldAccessorTable."<init>":(Lcom/google/protobuf/Descriptors$Descriptor;[Ljava/lang/String;)V
      43: invokestatic  #13                 // Method org/apache/hadoop/hbase/protobuf/generated/HFileProtos.access$102:(Lcom/google/protobuf/GeneratedMessage$FieldAccessorTable;)Lcom/google/protobuf/GeneratedMessage$FieldAccessorTable;
      46: pop
      47: invokestatic  #3                  // Method org/apache/hadoop/hbase/protobuf/generated/HFileProtos.getDescriptor:()Lcom/google/protobuf/Descriptors$FileDescriptor;
      50: invokevirtual #4                  // Method com/google/protobuf/Descriptors$FileDescriptor.getMessageTypes:()Ljava/util/List;
      53: iconst_1
      54: invokeinterface #5,  2            // InterfaceMethod java/util/List.get:(I)Ljava/lang/Object;
      59: checkcast     #6                  // class com/google/protobuf/Descriptors$Descriptor
      62: invokestatic  #14                 // Method org/apache/hadoop/hbase/protobuf/generated/HFileProtos.access$902:(Lcom/google/protobuf/Descriptors$Descriptor;)Lcom/google/protobuf/Descriptors$Descriptor;
      65: pop
      66: new           #8                  // class com/google/protobuf/GeneratedMessage$FieldAccessorTable
      69: dup
      70: invokestatic  #15                 // Method org/apache/hadoop/hbase/protobuf/generated/HFileProtos.access$900:()Lcom/google/protobuf/Descriptors$Descriptor;
      73: bipush        13
      75: anewarray     #10                 // class java/lang/String
      78: dup
      79: iconst_0
      80: ldc           #16                 // String FileInfoOffset
      82: aastore
      83: dup
      84: iconst_1
      85: ldc           #17                 // String LoadOnOpenDataOffset
      87: aastore
      88: dup
      89: iconst_2
      90: ldc           #18                 // String UncompressedDataIndexSize
      92: aastore
      93: dup
      94: iconst_3
      95: ldc           #19                 // String TotalUncompressedBytes
      97: aastore
      98: dup
      99: iconst_4
     100: ldc           #20                 // String DataIndexCount
     102: aastore
     103: dup
     104: iconst_5
     105: ldc           #21                 // String MetaIndexCount
     107: aastore
     108: dup
     109: bipush        6
     111: ldc           #22                 // String EntryCount
     113: aastore
     114: dup
     115: bipush        7
     117: ldc           #23                 // String NumDataIndexLevels
     119: aastore
     120: dup
     121: bipush        8
     123: ldc           #24                 // String FirstDataBlockOffset
     125: aastore
     126: dup
     127: bipush        9
     129: ldc           #25                 // String LastDataBlockOffset
     131: aastore
     132: dup
     133: bipush        10
     135: ldc           #26                 // String ComparatorClassName
     137: aastore
     138: dup
     139: bipush        11
     141: ldc           #27                 // String CompressionCodec
     143: aastore
     144: dup
     145: bipush        12
     147: ldc           #28                 // String EncryptionKey
     149: aastore
     150: invokespecial #12                 // Method com/google/protobuf/GeneratedMessage$FieldAccessorTable."<init>":(Lcom/google/protobuf/Descriptors$Descriptor;[Ljava/lang/String;)V
     153: invokestatic  #29                 // Method org/apache/hadoop/hbase/protobuf/generated/HFileProtos.access$1002:(Lcom/google/protobuf/GeneratedMessage$FieldAccessorTable;)Lcom/google/protobuf/GeneratedMessage$FieldAccessorTable;
     156: pop
     157: aconst_null
     158: areturn
}
