Compiled from "HFileCorruptionChecker.java"
class org.apache.hadoop.hbase.util.hbck.HFileCorruptionChecker$MobRegionDirChecker extends org.apache.hadoop.hbase.util.hbck.HFileCorruptionChecker$RegionDirChecker {
  final org.apache.hadoop.hbase.util.hbck.HFileCorruptionChecker this$0;

  org.apache.hadoop.hbase.util.hbck.HFileCorruptionChecker$MobRegionDirChecker(org.apache.hadoop.hbase.util.hbck.HFileCorruptionChecker, org.apache.hadoop.fs.Path);
    Code:
       0: aload_0
       1: aload_1
       2: putfield      #1                  // Field this$0:Lorg/apache/hadoop/hbase/util/hbck/HFileCorruptionChecker;
       5: aload_0
       6: aload_1
       7: aload_2
       8: invokespecial #2                  // Method org/apache/hadoop/hbase/util/hbck/HFileCorruptionChecker$RegionDirChecker."<init>":(Lorg/apache/hadoop/hbase/util/hbck/HFileCorruptionChecker;Lorg/apache/hadoop/fs/Path;)V
      11: return

  public java.lang.Void call() throws java.io.IOException;
    Code:
       0: aload_0
       1: getfield      #1                  // Field this$0:Lorg/apache/hadoop/hbase/util/hbck/HFileCorruptionChecker;
       4: aload_0
       5: getfield      #3                  // Field regionDir:Lorg/apache/hadoop/fs/Path;
       8: invokestatic  #4                  // Method org/apache/hadoop/hbase/util/hbck/HFileCorruptionChecker.access$000:(Lorg/apache/hadoop/hbase/util/hbck/HFileCorruptionChecker;Lorg/apache/hadoop/fs/Path;)V
      11: aconst_null
      12: areturn

  public java.lang.Object call() throws java.lang.Exception;
    Code:
       0: aload_0
       1: invokevirtual #5                  // Method call:()Ljava/lang/Void;
       4: areturn
}
