Compiled from "HFileArchiver.java"
class org.apache.hadoop.hbase.backup.HFileArchiver$FileStatusConverter extends org.apache.hadoop.hbase.backup.HFileArchiver$FileConverter<org.apache.hadoop.fs.FileStatus> {
  public org.apache.hadoop.hbase.backup.HFileArchiver$FileStatusConverter(org.apache.hadoop.fs.FileSystem);
    Code:
       0: aload_0
       1: aload_1
       2: invokespecial #1                  // Method org/apache/hadoop/hbase/backup/HFileArchiver$FileConverter."<init>":(Lorg/apache/hadoop/fs/FileSystem;)V
       5: return

  public org.apache.hadoop.hbase.backup.HFileArchiver$File apply(org.apache.hadoop.fs.FileStatus);
    Code:
       0: new           #2                  // class org/apache/hadoop/hbase/backup/HFileArchiver$FileablePath
       3: dup
       4: aload_0
       5: getfield      #3                  // Field fs:Lorg/apache/hadoop/fs/FileSystem;
       8: aload_1
       9: invokevirtual #4                  // Method org/apache/hadoop/fs/FileStatus.getPath:()Lorg/apache/hadoop/fs/Path;
      12: invokespecial #5                  // Method org/apache/hadoop/hbase/backup/HFileArchiver$FileablePath."<init>":(Lorg/apache/hadoop/fs/FileSystem;Lorg/apache/hadoop/fs/Path;)V
      15: areturn

  public java.lang.Object apply(java.lang.Object);
    Code:
       0: aload_0
       1: aload_1
       2: checkcast     #6                  // class org/apache/hadoop/fs/FileStatus
       5: invokevirtual #7                  // Method apply:(Lorg/apache/hadoop/fs/FileStatus;)Lorg/apache/hadoop/hbase/backup/HFileArchiver$File;
       8: areturn
}
