Compiled from "HFileBlock.java"
class org.apache.hadoop.hbase.io.hfile.HFileBlock$Header {
  static int BLOCK_MAGIC_INDEX;

  static int ON_DISK_SIZE_WITHOUT_HEADER_INDEX;

  static int UNCOMPRESSED_SIZE_WITHOUT_HEADER_INDEX;

  static int PREV_BLOCK_OFFSET_INDEX;

  static int CHECKSUM_TYPE_INDEX;

  static int BYTES_PER_CHECKSUM_INDEX;

  static int ON_DISK_DATA_SIZE_WITH_HEADER_INDEX;

  org.apache.hadoop.hbase.io.hfile.HFileBlock$Header();
    Code:
       0: aload_0
       1: invokespecial #1                  // Method java/lang/Object."<init>":()V
       4: return

  static {};
    Code:
       0: iconst_0
       1: putstatic     #2                  // Field BLOCK_MAGIC_INDEX:I
       4: bipush        8
       6: putstatic     #3                  // Field ON_DISK_SIZE_WITHOUT_HEADER_INDEX:I
       9: bipush        12
      11: putstatic     #4                  // Field UNCOMPRESSED_SIZE_WITHOUT_HEADER_INDEX:I
      14: bipush        16
      16: putstatic     #5                  // Field PREV_BLOCK_OFFSET_INDEX:I
      19: bipush        24
      21: putstatic     #6                  // Field CHECKSUM_TYPE_INDEX:I
      24: bipush        25
      26: putstatic     #7                  // Field BYTES_PER_CHECKSUM_INDEX:I
      29: bipush        29
      31: putstatic     #8                  // Field ON_DISK_DATA_SIZE_WITH_HEADER_INDEX:I
      34: return
}
