Compiled from "HMaster.java"
class org.apache.hadoop.hbase.master.HMaster$InitializationMonitor extends org.apache.hadoop.hbase.util.HasThread {
  public static final java.lang.String TIMEOUT_KEY;

  public static final long TIMEOUT_DEFAULT;

  public static final java.lang.String HALT_KEY;

  public static final boolean HALT_DEFAULT;

  org.apache.hadoop.hbase.master.HMaster$InitializationMonitor(org.apache.hadoop.hbase.master.HMaster);
    Code:
       0: aload_0
       1: ldc           #1                  // String MasterInitializationMonitor
       3: invokespecial #2                  // Method org/apache/hadoop/hbase/util/HasThread."<init>":(Ljava/lang/String;)V
       6: aload_0
       7: aload_1
       8: putfield      #3                  // Field master:Lorg/apache/hadoop/hbase/master/HMaster;
      11: aload_0
      12: aload_1
      13: invokevirtual #4                  // Method org/apache/hadoop/hbase/master/HMaster.getConfiguration:()Lorg/apache/hadoop/conf/Configuration;
      16: ldc           #6                  // String hbase.master.initializationmonitor.timeout
      18: getstatic     #7                  // Field TIMEOUT_DEFAULT:J
      21: invokevirtual #8                  // Method org/apache/hadoop/conf/Configuration.getLong:(Ljava/lang/String;J)J
      24: putfield      #9                  // Field timeout:J
      27: aload_0
      28: aload_1
      29: invokevirtual #4                  // Method org/apache/hadoop/hbase/master/HMaster.getConfiguration:()Lorg/apache/hadoop/conf/Configuration;
      32: ldc           #10                 // String hbase.master.initializationmonitor.haltontimeout
      34: iconst_0
      35: invokevirtual #11                 // Method org/apache/hadoop/conf/Configuration.getBoolean:(Ljava/lang/String;Z)Z
      38: putfield      #12                 // Field haltOnTimeout:Z
      41: aload_0
      42: iconst_1
      43: invokevirtual #13                 // Method setDaemon:(Z)V
      46: return

  public void run();
    Code:
       0: aload_0
       1: getfield      #3                  // Field master:Lorg/apache/hadoop/hbase/master/HMaster;
       4: invokevirtual #14                 // Method org/apache/hadoop/hbase/master/HMaster.isStopped:()Z
       7: ifne          117
      10: aload_0
      11: getfield      #3                  // Field master:Lorg/apache/hadoop/hbase/master/HMaster;
      14: invokevirtual #15                 // Method org/apache/hadoop/hbase/master/HMaster.isActiveMaster:()Z
      17: ifeq          117
      20: aload_0
      21: getfield      #9                  // Field timeout:J
      24: invokestatic  #16                 // Method java/lang/Thread.sleep:(J)V
      27: aload_0
      28: getfield      #3                  // Field master:Lorg/apache/hadoop/hbase/master/HMaster;
      31: invokevirtual #17                 // Method org/apache/hadoop/hbase/master/HMaster.isInitialized:()Z
      34: ifeq          50
      37: invokestatic  #18                 // Method org/apache/hadoop/hbase/master/HMaster.access$000:()Lorg/slf4j/Logger;
      40: ldc           #19                 // String Initialization completed within allotted tolerance. Monitor exiting.
      42: invokeinterface #20,  2           // InterfaceMethod org/slf4j/Logger.debug:(Ljava/lang/String;)V
      47: goto          0
      50: invokestatic  #18                 // Method org/apache/hadoop/hbase/master/HMaster.access$000:()Lorg/slf4j/Logger;
      53: new           #21                 // class java/lang/StringBuilder
      56: dup
      57: invokespecial #22                 // Method java/lang/StringBuilder."<init>":()V
      60: ldc           #23                 // String Master failed to complete initialization after
      62: invokevirtual #24                 // Method java/lang/StringBuilder.append:(Ljava/lang/String;)Ljava/lang/StringBuilder;
      65: aload_0
      66: getfield      #9                  // Field timeout:J
      69: invokevirtual #25                 // Method java/lang/StringBuilder.append:(J)Ljava/lang/StringBuilder;
      72: ldc           #26                 // String ms. Please consider submitting a bug report including a thread dump of this process.
      74: invokevirtual #24                 // Method java/lang/StringBuilder.append:(Ljava/lang/String;)Ljava/lang/StringBuilder;
      77: invokevirtual #27                 // Method java/lang/StringBuilder.toString:()Ljava/lang/String;
      80: invokeinterface #28,  2           // InterfaceMethod org/slf4j/Logger.error:(Ljava/lang/String;)V
      85: aload_0
      86: getfield      #12                 // Field haltOnTimeout:Z
      89: ifeq          0
      92: invokestatic  #18                 // Method org/apache/hadoop/hbase/master/HMaster.access$000:()Lorg/slf4j/Logger;
      95: ldc           #29                 // String Zombie Master exiting. Thread dump to stdout
      97: invokeinterface #28,  2           // InterfaceMethod org/slf4j/Logger.error:(Ljava/lang/String;)V
     102: getstatic     #30                 // Field java/lang/System.out:Ljava/io/PrintStream;
     105: ldc           #31                 // String Zombie HMaster
     107: invokestatic  #32                 // Method org/apache/hadoop/hbase/util/Threads.printThreadInfo:(Ljava/io/PrintStream;Ljava/lang/String;)V
     110: iconst_m1
     111: invokestatic  #33                 // Method java/lang/System.exit:(I)V
     114: goto          0
     117: goto          131
     120: astore_1
     121: invokestatic  #18                 // Method org/apache/hadoop/hbase/master/HMaster.access$000:()Lorg/slf4j/Logger;
     124: ldc           #35                 // String InitMonitor thread interrupted. Existing.
     126: invokeinterface #36,  2           // InterfaceMethod org/slf4j/Logger.trace:(Ljava/lang/String;)V
     131: return
    Exception table:
       from    to  target type
           0   117   120   Class java/lang/InterruptedException

  static {};
    Code:
       0: getstatic     #37                 // Field java/util/concurrent/TimeUnit.MILLISECONDS:Ljava/util/concurrent/TimeUnit;
       3: ldc2_w        #38                 // long 15l
       6: getstatic     #40                 // Field java/util/concurrent/TimeUnit.MINUTES:Ljava/util/concurrent/TimeUnit;
       9: invokevirtual #41                 // Method java/util/concurrent/TimeUnit.convert:(JLjava/util/concurrent/TimeUnit;)J
      12: putstatic     #7                  // Field TIMEOUT_DEFAULT:J
      15: return
}
