Compiled from "HMaster.java"
class org.apache.hadoop.hbase.master.HMaster$13 implements org.apache.hadoop.hbase.master.HMaster$TableDescriptorGetter {
  final org.apache.hadoop.hbase.client.TableDescriptor val$newDescriptor;

  final org.apache.hadoop.hbase.master.HMaster this$0;

  org.apache.hadoop.hbase.master.HMaster$13(org.apache.hadoop.hbase.master.HMaster, org.apache.hadoop.hbase.client.TableDescriptor);
    Code:
       0: aload_0
       1: aload_1
       2: putfield      #1                  // Field this$0:Lorg/apache/hadoop/hbase/master/HMaster;
       5: aload_0
       6: aload_2
       7: putfield      #2                  // Field val$newDescriptor:Lorg/apache/hadoop/hbase/client/TableDescriptor;
      10: aload_0
      11: invokespecial #3                  // Method java/lang/Object."<init>":()V
      14: return

  public org.apache.hadoop.hbase.client.TableDescriptor get() throws java.io.IOException;
    Code:
       0: aload_0
       1: getfield      #2                  // Field val$newDescriptor:Lorg/apache/hadoop/hbase/client/TableDescriptor;
       4: areturn
}
