Compiled from "HRegionServer.java"
class org.apache.hadoop.hbase.regionserver.HRegionServer$5 implements com.google.protobuf.RpcCallback<com.google.protobuf.Message> {
  final com.google.protobuf.Message$Builder val$responseBuilder;

  final org.apache.hadoop.hbase.regionserver.HRegionServer this$0;

  org.apache.hadoop.hbase.regionserver.HRegionServer$5(org.apache.hadoop.hbase.regionserver.HRegionServer, com.google.protobuf.Message$Builder);
    Code:
       0: aload_0
       1: aload_1
       2: putfield      #1                  // Field this$0:Lorg/apache/hadoop/hbase/regionserver/HRegionServer;
       5: aload_0
       6: aload_2
       7: putfield      #2                  // Field val$responseBuilder:Lcom/google/protobuf/Message$Builder;
      10: aload_0
      11: invokespecial #3                  // Method java/lang/Object."<init>":()V
      14: return

  public void run(com.google.protobuf.Message);
    Code:
       0: aload_1
       1: ifnull        15
       4: aload_0
       5: getfield      #2                  // Field val$responseBuilder:Lcom/google/protobuf/Message$Builder;
       8: aload_1
       9: invokeinterface #4,  2            // InterfaceMethod com/google/protobuf/Message$Builder.mergeFrom:(Lcom/google/protobuf/Message;)Lcom/google/protobuf/Message$Builder;
      14: pop
      15: return

  public void run(java.lang.Object);
    Code:
       0: aload_0
       1: aload_1
       2: checkcast     #5                  // class com/google/protobuf/Message
       5: invokevirtual #6                  // Method run:(Lcom/google/protobuf/Message;)V
       8: return
}
