Compiled from "HRegion.java"
class org.apache.hadoop.hbase.regionserver.HRegion$ReplayBatchOperation extends org.apache.hadoop.hbase.regionserver.HRegion$BatchOperation<org.apache.hadoop.hbase.wal.WALSplitUtil$MutationReplay> {
  public org.apache.hadoop.hbase.regionserver.HRegion$ReplayBatchOperation(org.apache.hadoop.hbase.regionserver.HRegion, org.apache.hadoop.hbase.wal.WALSplitUtil$MutationReplay[], long);
    Code:
       0: aload_0
       1: aload_1
       2: aload_2
       3: invokespecial #1                  // Method org/apache/hadoop/hbase/regionserver/HRegion$BatchOperation."<init>":(Lorg/apache/hadoop/hbase/regionserver/HRegion;[Ljava/lang/Object;)V
       6: aload_0
       7: lconst_0
       8: putfield      #2                  // Field origLogSeqNum:J
      11: aload_0
      12: lload_3
      13: putfield      #2                  // Field origLogSeqNum:J
      16: return

  public org.apache.hadoop.hbase.client.Mutation getMutation(int);
    Code:
       0: aload_0
       1: getfield      #3                  // Field operations:[Ljava/lang/Object;
       4: checkcast     #4                  // class "[Lorg/apache/hadoop/hbase/wal/WALSplitUtil$MutationReplay;"
       7: iload_1
       8: aaload
       9: getfield      #5                  // Field org/apache/hadoop/hbase/wal/WALSplitUtil$MutationReplay.mutation:Lorg/apache/hadoop/hbase/client/Mutation;
      12: areturn

  public long getNonceGroup(int);
    Code:
       0: aload_0
       1: getfield      #3                  // Field operations:[Ljava/lang/Object;
       4: checkcast     #4                  // class "[Lorg/apache/hadoop/hbase/wal/WALSplitUtil$MutationReplay;"
       7: iload_1
       8: aaload
       9: getfield      #6                  // Field org/apache/hadoop/hbase/wal/WALSplitUtil$MutationReplay.nonceGroup:J
      12: lreturn

  public long getNonce(int);
    Code:
       0: aload_0
       1: getfield      #3                  // Field operations:[Ljava/lang/Object;
       4: checkcast     #4                  // class "[Lorg/apache/hadoop/hbase/wal/WALSplitUtil$MutationReplay;"
       7: iload_1
       8: aaload
       9: getfield      #7                  // Field org/apache/hadoop/hbase/wal/WALSplitUtil$MutationReplay.nonce:J
      12: lreturn

  public org.apache.hadoop.hbase.client.Mutation[] getMutationsForCoprocs();
    Code:
       0: aconst_null
       1: areturn

  public boolean isInReplay();
    Code:
       0: iconst_1
       1: ireturn

  public long getOrigLogSeqNum();
    Code:
       0: aload_0
       1: getfield      #2                  // Field origLogSeqNum:J
       4: lreturn

  public void startRegionOperation() throws java.io.IOException;
    Code:
       0: aload_0
       1: getfield      #8                  // Field region:Lorg/apache/hadoop/hbase/regionserver/HRegion;
       4: getstatic     #9                  // Field org/apache/hadoop/hbase/regionserver/Region$Operation.REPLAY_BATCH_MUTATE:Lorg/apache/hadoop/hbase/regionserver/Region$Operation;
       7: invokevirtual #10                 // Method org/apache/hadoop/hbase/regionserver/HRegion.startRegionOperation:(Lorg/apache/hadoop/hbase/regionserver/Region$Operation;)V
      10: return

  public void closeRegionOperation() throws java.io.IOException;
    Code:
       0: aload_0
       1: getfield      #8                  // Field region:Lorg/apache/hadoop/hbase/regionserver/HRegion;
       4: getstatic     #9                  // Field org/apache/hadoop/hbase/regionserver/Region$Operation.REPLAY_BATCH_MUTATE:Lorg/apache/hadoop/hbase/regionserver/Region$Operation;
       7: invokevirtual #11                 // Method org/apache/hadoop/hbase/regionserver/HRegion.closeRegionOperation:(Lorg/apache/hadoop/hbase/regionserver/Region$Operation;)V
      10: return

  protected void checkAndPreparePut(org.apache.hadoop.hbase.client.Put) throws java.io.IOException;
    Code:
       0: aload_1
       1: invokevirtual #12                 // Method org/apache/hadoop/hbase/client/Put.getFamilyCellMap:()Ljava/util/NavigableMap;
       4: astore_2
       5: aconst_null
       6: astore_3
       7: aload_2
       8: invokeinterface #13,  1           // InterfaceMethod java/util/Map.keySet:()Ljava/util/Set;
      13: invokeinterface #14,  1           // InterfaceMethod java/util/Set.iterator:()Ljava/util/Iterator;
      18: astore        4
      20: aload         4
      22: invokeinterface #15,  1           // InterfaceMethod java/util/Iterator.hasNext:()Z
      27: ifeq          83
      30: aload         4
      32: invokeinterface #16,  1           // InterfaceMethod java/util/Iterator.next:()Ljava/lang/Object;
      37: checkcast     #17                 // class "[B"
      40: astore        5
      42: aload_0
      43: getfield      #8                  // Field region:Lorg/apache/hadoop/hbase/regionserver/HRegion;
      46: invokestatic  #18                 // Method org/apache/hadoop/hbase/regionserver/HRegion.access$1200:(Lorg/apache/hadoop/hbase/regionserver/HRegion;)Lorg/apache/hadoop/hbase/client/TableDescriptor;
      49: aload         5
      51: invokeinterface #19,  2           // InterfaceMethod org/apache/hadoop/hbase/client/TableDescriptor.hasColumnFamily:([B)Z
      56: ifne          80
      59: aload_3
      60: ifnonnull     71
      63: new           #20                 // class java/util/ArrayList
      66: dup
      67: invokespecial #21                 // Method java/util/ArrayList."<init>":()V
      70: astore_3
      71: aload_3
      72: aload         5
      74: invokeinterface #22,  2           // InterfaceMethod java/util/List.add:(Ljava/lang/Object;)Z
      79: pop
      80: goto          20
      83: aload_3
      84: ifnull        165
      87: aload_3
      88: invokeinterface #23,  1           // InterfaceMethod java/util/List.iterator:()Ljava/util/Iterator;
      93: astore        4
      95: aload         4
      97: invokeinterface #15,  1           // InterfaceMethod java/util/Iterator.hasNext:()Z
     102: ifeq          165
     105: aload         4
     107: invokeinterface #16,  1           // InterfaceMethod java/util/Iterator.next:()Ljava/lang/Object;
     112: checkcast     #17                 // class "[B"
     115: astore        5
     117: invokestatic  #24                 // Method org/apache/hadoop/hbase/regionserver/HRegion.access$000:()Lorg/slf4j/Logger;
     120: new           #25                 // class java/lang/StringBuilder
     123: dup
     124: invokespecial #26                 // Method java/lang/StringBuilder."<init>":()V
     127: ldc           #27                 // String No family for
     129: invokevirtual #28                 // Method java/lang/StringBuilder.append:(Ljava/lang/String;)Ljava/lang/StringBuilder;
     132: aload         5
     134: invokestatic  #29                 // Method org/apache/hadoop/hbase/util/Bytes.toString:([B)Ljava/lang/String;
     137: invokevirtual #28                 // Method java/lang/StringBuilder.append:(Ljava/lang/String;)Ljava/lang/StringBuilder;
     140: ldc           #30                 // String  omit from reply.
     142: invokevirtual #28                 // Method java/lang/StringBuilder.append:(Ljava/lang/String;)Ljava/lang/StringBuilder;
     145: invokevirtual #31                 // Method java/lang/StringBuilder.toString:()Ljava/lang/String;
     148: invokeinterface #32,  2           // InterfaceMethod org/slf4j/Logger.info:(Ljava/lang/String;)V
     153: aload_2
     154: aload         5
     156: invokeinterface #33,  2           // InterfaceMethod java/util/Map.remove:(Ljava/lang/Object;)Ljava/lang/Object;
     161: pop
     162: goto          95
     165: return

  public void checkAndPrepare() throws java.io.IOException;
    Code:
       0: invokestatic  #34                 // Method org/apache/hadoop/hbase/util/EnvironmentEdgeManager.currentTime:()J
       3: lstore_1
       4: aload_0
       5: iconst_1
       6: aload_0
       7: invokevirtual #35                 // Method size:()I
      10: aload_0
      11: lload_1
      12: invokedynamic #36,  0             // InvokeDynamic #0:visit:(Lorg/apache/hadoop/hbase/regionserver/HRegion$ReplayBatchOperation;J)Lorg/apache/hadoop/hbase/regionserver/HRegion$BatchOperation$Visitor;
      17: invokevirtual #37                 // Method visitBatchOperations:(ZILorg/apache/hadoop/hbase/regionserver/HRegion$BatchOperation$Visitor;)V
      20: return

  public void prepareMiniBatchOperations(org.apache.hadoop.hbase.regionserver.MiniBatchOperationInProgress<org.apache.hadoop.hbase.client.Mutation>, long, java.util.List<org.apache.hadoop.hbase.regionserver.Region$RowLock>) throws java.io.IOException;
    Code:
       0: aload_0
       1: iconst_1
       2: aload_1
       3: invokevirtual #38                 // Method org/apache/hadoop/hbase/regionserver/MiniBatchOperationInProgress.getLastIndexExclusive:()I
       6: aload_0
       7: aload_1
       8: invokedynamic #39,  0             // InvokeDynamic #1:visit:(Lorg/apache/hadoop/hbase/regionserver/HRegion$ReplayBatchOperation;Lorg/apache/hadoop/hbase/regionserver/MiniBatchOperationInProgress;)Lorg/apache/hadoop/hbase/regionserver/HRegion$BatchOperation$Visitor;
      13: invokevirtual #37                 // Method visitBatchOperations:(ZILorg/apache/hadoop/hbase/regionserver/HRegion$BatchOperation$Visitor;)V
      16: return

  public org.apache.hadoop.hbase.regionserver.MultiVersionConcurrencyControl$WriteEntry writeMiniBatchOperationsToMemStore(org.apache.hadoop.hbase.regionserver.MiniBatchOperationInProgress<org.apache.hadoop.hbase.client.Mutation>, org.apache.hadoop.hbase.regionserver.MultiVersionConcurrencyControl$WriteEntry) throws java.io.IOException;
    Code:
       0: aload_0
       1: aload_1
       2: aload_0
       3: invokevirtual #40                 // Method getOrigLogSeqNum:()J
       6: invokespecial #41                 // Method org/apache/hadoop/hbase/regionserver/HRegion$BatchOperation.writeMiniBatchOperationsToMemStore:(Lorg/apache/hadoop/hbase/regionserver/MiniBatchOperationInProgress;J)V
       9: aload_2
      10: areturn

  public void completeMiniBatchOperations(org.apache.hadoop.hbase.regionserver.MiniBatchOperationInProgress<org.apache.hadoop.hbase.client.Mutation>, org.apache.hadoop.hbase.regionserver.MultiVersionConcurrencyControl$WriteEntry) throws java.io.IOException;
    Code:
       0: aload_0
       1: aload_1
       2: aload_2
       3: invokespecial #42                 // Method org/apache/hadoop/hbase/regionserver/HRegion$BatchOperation.completeMiniBatchOperations:(Lorg/apache/hadoop/hbase/regionserver/MiniBatchOperationInProgress;Lorg/apache/hadoop/hbase/regionserver/MultiVersionConcurrencyControl$WriteEntry;)V
       6: aload_0
       7: getfield      #8                  // Field region:Lorg/apache/hadoop/hbase/regionserver/HRegion;
      10: invokestatic  #43                 // Method org/apache/hadoop/hbase/regionserver/HRegion.access$400:(Lorg/apache/hadoop/hbase/regionserver/HRegion;)Lorg/apache/hadoop/hbase/regionserver/MultiVersionConcurrencyControl;
      13: aload_0
      14: invokevirtual #40                 // Method getOrigLogSeqNum:()J
      17: invokevirtual #44                 // Method org/apache/hadoop/hbase/regionserver/MultiVersionConcurrencyControl.advanceTo:(J)V
      20: return
}
