Compiled from "HRegion.java"
class org.apache.hadoop.hbase.regionserver.HRegion$MutationBatchOperation extends org.apache.hadoop.hbase.regionserver.HRegion$BatchOperation<org.apache.hadoop.hbase.client.Mutation> {
  public org.apache.hadoop.hbase.regionserver.HRegion$MutationBatchOperation(org.apache.hadoop.hbase.regionserver.HRegion, org.apache.hadoop.hbase.client.Mutation[], boolean, long, long);
    Code:
       0: aload_0
       1: aload_1
       2: aload_2
       3: invokespecial #2                  // Method org/apache/hadoop/hbase/regionserver/HRegion$BatchOperation."<init>":(Lorg/apache/hadoop/hbase/regionserver/HRegion;[Ljava/lang/Object;)V
       6: aload_0
       7: iload_3
       8: putfield      #3                  // Field atomic:Z
      11: aload_0
      12: lload         4
      14: putfield      #4                  // Field nonceGroup:J
      17: aload_0
      18: lload         6
      20: putfield      #5                  // Field nonce:J
      23: return

  public org.apache.hadoop.hbase.client.Mutation getMutation(int);
    Code:
       0: aload_0
       1: getfield      #6                  // Field operations:[Ljava/lang/Object;
       4: checkcast     #7                  // class "[Lorg/apache/hadoop/hbase/client/Mutation;"
       7: iload_1
       8: aaload
       9: areturn

  public long getNonceGroup(int);
    Code:
       0: aload_0
       1: getfield      #4                  // Field nonceGroup:J
       4: lreturn

  public long getNonce(int);
    Code:
       0: aload_0
       1: getfield      #5                  // Field nonce:J
       4: lreturn

  public org.apache.hadoop.hbase.client.Mutation[] getMutationsForCoprocs();
    Code:
       0: aload_0
       1: getfield      #6                  // Field operations:[Ljava/lang/Object;
       4: checkcast     #7                  // class "[Lorg/apache/hadoop/hbase/client/Mutation;"
       7: areturn

  public boolean isInReplay();
    Code:
       0: iconst_0
       1: ireturn

  public long getOrigLogSeqNum();
    Code:
       0: ldc2_w        #9                  // long -1l
       3: lreturn

  public void startRegionOperation() throws java.io.IOException;
    Code:
       0: aload_0
       1: getfield      #11                 // Field region:Lorg/apache/hadoop/hbase/regionserver/HRegion;
       4: getstatic     #12                 // Field org/apache/hadoop/hbase/regionserver/Region$Operation.BATCH_MUTATE:Lorg/apache/hadoop/hbase/regionserver/Region$Operation;
       7: invokevirtual #13                 // Method org/apache/hadoop/hbase/regionserver/HRegion.startRegionOperation:(Lorg/apache/hadoop/hbase/regionserver/Region$Operation;)V
      10: return

  public void closeRegionOperation() throws java.io.IOException;
    Code:
       0: aload_0
       1: getfield      #11                 // Field region:Lorg/apache/hadoop/hbase/regionserver/HRegion;
       4: getstatic     #12                 // Field org/apache/hadoop/hbase/regionserver/Region$Operation.BATCH_MUTATE:Lorg/apache/hadoop/hbase/regionserver/Region$Operation;
       7: invokevirtual #14                 // Method org/apache/hadoop/hbase/regionserver/HRegion.closeRegionOperation:(Lorg/apache/hadoop/hbase/regionserver/Region$Operation;)V
      10: return

  public void checkAndPreparePut(org.apache.hadoop.hbase.client.Put) throws java.io.IOException;
    Code:
       0: aload_0
       1: getfield      #11                 // Field region:Lorg/apache/hadoop/hbase/regionserver/HRegion;
       4: aload_1
       5: invokevirtual #15                 // Method org/apache/hadoop/hbase/client/Put.getFamilyCellMap:()Ljava/util/NavigableMap;
       8: invokeinterface #16,  1           // InterfaceMethod java/util/NavigableMap.keySet:()Ljava/util/Set;
      13: aload_1
      14: invokevirtual #17                 // Method org/apache/hadoop/hbase/client/Put.getDurability:()Lorg/apache/hadoop/hbase/client/Durability;
      17: invokestatic  #18                 // Method org/apache/hadoop/hbase/regionserver/HRegion.access$700:(Lorg/apache/hadoop/hbase/regionserver/HRegion;Ljava/util/Collection;Lorg/apache/hadoop/hbase/client/Durability;)V
      20: return

  public void checkAndPrepare() throws java.io.IOException;
    Code:
       0: iconst_2
       1: newarray       int
       3: dup
       4: iconst_0
       5: iconst_0
       6: iastore
       7: dup
       8: iconst_1
       9: iconst_0
      10: iastore
      11: astore_1
      12: aload_0
      13: iconst_1
      14: aload_0
      15: invokevirtual #19                 // Method size:()I
      18: new           #20                 // class org/apache/hadoop/hbase/regionserver/HRegion$MutationBatchOperation$1
      21: dup
      22: aload_0
      23: aload_1
      24: invokespecial #21                 // Method org/apache/hadoop/hbase/regionserver/HRegion$MutationBatchOperation$1."<init>":(Lorg/apache/hadoop/hbase/regionserver/HRegion$MutationBatchOperation;[I)V
      27: invokevirtual #22                 // Method visitBatchOperations:(ZILorg/apache/hadoop/hbase/regionserver/HRegion$BatchOperation$Visitor;)V
      30: aload_0
      31: getfield      #11                 // Field region:Lorg/apache/hadoop/hbase/regionserver/HRegion;
      34: invokestatic  #23                 // Method org/apache/hadoop/hbase/regionserver/HRegion.access$1000:(Lorg/apache/hadoop/hbase/regionserver/HRegion;)Lorg/apache/hadoop/hbase/regionserver/MetricsRegion;
      37: ifnull        72
      40: aload_1
      41: iconst_0
      42: iaload
      43: ifle          56
      46: aload_0
      47: getfield      #11                 // Field region:Lorg/apache/hadoop/hbase/regionserver/HRegion;
      50: invokestatic  #23                 // Method org/apache/hadoop/hbase/regionserver/HRegion.access$1000:(Lorg/apache/hadoop/hbase/regionserver/HRegion;)Lorg/apache/hadoop/hbase/regionserver/MetricsRegion;
      53: invokevirtual #24                 // Method org/apache/hadoop/hbase/regionserver/MetricsRegion.updatePut:()V
      56: aload_1
      57: iconst_1
      58: iaload
      59: ifle          72
      62: aload_0
      63: getfield      #11                 // Field region:Lorg/apache/hadoop/hbase/regionserver/HRegion;
      66: invokestatic  #23                 // Method org/apache/hadoop/hbase/regionserver/HRegion.access$1000:(Lorg/apache/hadoop/hbase/regionserver/HRegion;)Lorg/apache/hadoop/hbase/regionserver/MetricsRegion;
      69: invokevirtual #25                 // Method org/apache/hadoop/hbase/regionserver/MetricsRegion.updateDelete:()V
      72: return

  public void prepareMiniBatchOperations(org.apache.hadoop.hbase.regionserver.MiniBatchOperationInProgress<org.apache.hadoop.hbase.client.Mutation>, long, java.util.List<org.apache.hadoop.hbase.regionserver.Region$RowLock>) throws java.io.IOException;
    Code:
       0: lload_2
       1: invokestatic  #26                 // Method org/apache/hadoop/hbase/util/Bytes.toBytes:(J)[B
       4: astore        5
       6: aload_0
       7: iconst_1
       8: aload_1
       9: invokevirtual #27                 // Method org/apache/hadoop/hbase/regionserver/MiniBatchOperationInProgress.getLastIndexExclusive:()I
      12: aload_0
      13: aload         5
      15: aload_1
      16: invokedynamic #28,  0             // InvokeDynamic #0:visit:(Lorg/apache/hadoop/hbase/regionserver/HRegion$MutationBatchOperation;[BLorg/apache/hadoop/hbase/regionserver/MiniBatchOperationInProgress;)Lorg/apache/hadoop/hbase/regionserver/HRegion$BatchOperation$Visitor;
      21: invokevirtual #22                 // Method visitBatchOperations:(ZILorg/apache/hadoop/hbase/regionserver/HRegion$BatchOperation$Visitor;)V
      24: aload_0
      25: getfield      #11                 // Field region:Lorg/apache/hadoop/hbase/regionserver/HRegion;
      28: invokestatic  #29                 // Method org/apache/hadoop/hbase/regionserver/HRegion.access$800:(Lorg/apache/hadoop/hbase/regionserver/HRegion;)Lorg/apache/hadoop/hbase/regionserver/RegionCoprocessorHost;
      31: ifnull        53
      34: aload_0
      35: getfield      #11                 // Field region:Lorg/apache/hadoop/hbase/regionserver/HRegion;
      38: invokestatic  #29                 // Method org/apache/hadoop/hbase/regionserver/HRegion.access$800:(Lorg/apache/hadoop/hbase/regionserver/HRegion;)Lorg/apache/hadoop/hbase/regionserver/RegionCoprocessorHost;
      41: aload_1
      42: invokevirtual #30                 // Method org/apache/hadoop/hbase/regionserver/RegionCoprocessorHost.preBatchMutate:(Lorg/apache/hadoop/hbase/regionserver/MiniBatchOperationInProgress;)V
      45: aload_0
      46: aload_1
      47: aload         4
      49: lload_2
      50: invokespecial #31                 // Method checkAndMergeCPMutations:(Lorg/apache/hadoop/hbase/regionserver/MiniBatchOperationInProgress;Ljava/util/List;J)V
      53: return

  public java.util.List<org.apache.hadoop.hbase.util.Pair<org.apache.hadoop.hbase.util.NonceKey, org.apache.hadoop.hbase.wal.WALEdit>> buildWALEdits(org.apache.hadoop.hbase.regionserver.MiniBatchOperationInProgress<org.apache.hadoop.hbase.client.Mutation>) throws java.io.IOException;
    Code:
       0: aload_0
       1: aload_1
       2: invokespecial #32                 // Method org/apache/hadoop/hbase/regionserver/HRegion$BatchOperation.buildWALEdits:(Lorg/apache/hadoop/hbase/regionserver/MiniBatchOperationInProgress;)Ljava/util/List;
       5: astore_2
       6: aload_2
       7: invokeinterface #33,  1           // InterfaceMethod java/util/List.size:()I
      12: iconst_1
      13: if_icmple     26
      16: new           #34                 // class java/io/IOException
      19: dup
      20: ldc           #35                 // String Found multiple nonce keys per batch!
      22: invokespecial #36                 // Method java/io/IOException."<init>":(Ljava/lang/String;)V
      25: athrow
      26: aload_2
      27: areturn

  public org.apache.hadoop.hbase.regionserver.MultiVersionConcurrencyControl$WriteEntry writeMiniBatchOperationsToMemStore(org.apache.hadoop.hbase.regionserver.MiniBatchOperationInProgress<org.apache.hadoop.hbase.client.Mutation>, org.apache.hadoop.hbase.regionserver.MultiVersionConcurrencyControl$WriteEntry) throws java.io.IOException;
    Code:
       0: aload_2
       1: ifnonnull     15
       4: aload_0
       5: getfield      #11                 // Field region:Lorg/apache/hadoop/hbase/regionserver/HRegion;
       8: invokestatic  #37                 // Method org/apache/hadoop/hbase/regionserver/HRegion.access$400:(Lorg/apache/hadoop/hbase/regionserver/HRegion;)Lorg/apache/hadoop/hbase/regionserver/MultiVersionConcurrencyControl;
      11: invokevirtual #38                 // Method org/apache/hadoop/hbase/regionserver/MultiVersionConcurrencyControl.begin:()Lorg/apache/hadoop/hbase/regionserver/MultiVersionConcurrencyControl$WriteEntry;
      14: astore_2
      15: aload_0
      16: aload_1
      17: aload_2
      18: invokevirtual #39                 // Method org/apache/hadoop/hbase/regionserver/MultiVersionConcurrencyControl$WriteEntry.getWriteNumber:()J
      21: invokespecial #40                 // Method org/apache/hadoop/hbase/regionserver/HRegion$BatchOperation.writeMiniBatchOperationsToMemStore:(Lorg/apache/hadoop/hbase/regionserver/MiniBatchOperationInProgress;J)V
      24: aload_2
      25: areturn

  public void completeMiniBatchOperations(org.apache.hadoop.hbase.regionserver.MiniBatchOperationInProgress<org.apache.hadoop.hbase.client.Mutation>, org.apache.hadoop.hbase.regionserver.MultiVersionConcurrencyControl$WriteEntry) throws java.io.IOException;
    Code:
       0: aload_0
       1: getfield      #11                 // Field region:Lorg/apache/hadoop/hbase/regionserver/HRegion;
       4: invokestatic  #29                 // Method org/apache/hadoop/hbase/regionserver/HRegion.access$800:(Lorg/apache/hadoop/hbase/regionserver/HRegion;)Lorg/apache/hadoop/hbase/regionserver/RegionCoprocessorHost;
       7: ifnull        21
      10: aload_0
      11: getfield      #11                 // Field region:Lorg/apache/hadoop/hbase/regionserver/HRegion;
      14: invokestatic  #29                 // Method org/apache/hadoop/hbase/regionserver/HRegion.access$800:(Lorg/apache/hadoop/hbase/regionserver/HRegion;)Lorg/apache/hadoop/hbase/regionserver/RegionCoprocessorHost;
      17: aload_1
      18: invokevirtual #41                 // Method org/apache/hadoop/hbase/regionserver/RegionCoprocessorHost.postBatchMutate:(Lorg/apache/hadoop/hbase/regionserver/MiniBatchOperationInProgress;)V
      21: aload_0
      22: aload_1
      23: aload_2
      24: invokespecial #42                 // Method org/apache/hadoop/hbase/regionserver/HRegion$BatchOperation.completeMiniBatchOperations:(Lorg/apache/hadoop/hbase/regionserver/MiniBatchOperationInProgress;Lorg/apache/hadoop/hbase/regionserver/MultiVersionConcurrencyControl$WriteEntry;)V
      27: return

  public void doPostOpCleanupForMiniBatch(org.apache.hadoop.hbase.regionserver.MiniBatchOperationInProgress<org.apache.hadoop.hbase.client.Mutation>, org.apache.hadoop.hbase.wal.WALEdit, boolean) throws java.io.IOException;
    Code:
       0: aload_0
       1: aload_1
       2: aload_2
       3: iload_3
       4: invokespecial #43                 // Method org/apache/hadoop/hbase/regionserver/HRegion$BatchOperation.doPostOpCleanupForMiniBatch:(Lorg/apache/hadoop/hbase/regionserver/MiniBatchOperationInProgress;Lorg/apache/hadoop/hbase/wal/WALEdit;Z)V
       7: aload_1
       8: ifnull        81
      11: aload_0
      12: getfield      #11                 // Field region:Lorg/apache/hadoop/hbase/regionserver/HRegion;
      15: invokestatic  #29                 // Method org/apache/hadoop/hbase/regionserver/HRegion.access$800:(Lorg/apache/hadoop/hbase/regionserver/HRegion;)Lorg/apache/hadoop/hbase/regionserver/RegionCoprocessorHost;
      18: ifnull        37
      21: aload_0
      22: iconst_0
      23: aload_1
      24: invokevirtual #27                 // Method org/apache/hadoop/hbase/regionserver/MiniBatchOperationInProgress.getLastIndexExclusive:()I
      27: aload_0
      28: aload_2
      29: invokedynamic #44,  0             // InvokeDynamic #1:visit:(Lorg/apache/hadoop/hbase/regionserver/HRegion$MutationBatchOperation;Lorg/apache/hadoop/hbase/wal/WALEdit;)Lorg/apache/hadoop/hbase/regionserver/HRegion$BatchOperation$Visitor;
      34: invokevirtual #22                 // Method visitBatchOperations:(ZILorg/apache/hadoop/hbase/regionserver/HRegion$BatchOperation$Visitor;)V
      37: aload_0
      38: getfield      #11                 // Field region:Lorg/apache/hadoop/hbase/regionserver/HRegion;
      41: invokestatic  #23                 // Method org/apache/hadoop/hbase/regionserver/HRegion.access$1000:(Lorg/apache/hadoop/hbase/regionserver/HRegion;)Lorg/apache/hadoop/hbase/regionserver/MetricsRegion;
      44: ifnull        81
      47: aload_1
      48: invokevirtual #45                 // Method org/apache/hadoop/hbase/regionserver/MiniBatchOperationInProgress.getNumOfPuts:()I
      51: ifle          64
      54: aload_0
      55: getfield      #11                 // Field region:Lorg/apache/hadoop/hbase/regionserver/HRegion;
      58: invokestatic  #23                 // Method org/apache/hadoop/hbase/regionserver/HRegion.access$1000:(Lorg/apache/hadoop/hbase/regionserver/HRegion;)Lorg/apache/hadoop/hbase/regionserver/MetricsRegion;
      61: invokevirtual #24                 // Method org/apache/hadoop/hbase/regionserver/MetricsRegion.updatePut:()V
      64: aload_1
      65: invokevirtual #46                 // Method org/apache/hadoop/hbase/regionserver/MiniBatchOperationInProgress.getNumOfDeletes:()I
      68: ifle          81
      71: aload_0
      72: getfield      #11                 // Field region:Lorg/apache/hadoop/hbase/regionserver/HRegion;
      75: invokestatic  #23                 // Method org/apache/hadoop/hbase/regionserver/HRegion.access$1000:(Lorg/apache/hadoop/hbase/regionserver/HRegion;)Lorg/apache/hadoop/hbase/regionserver/MetricsRegion;
      78: invokevirtual #25                 // Method org/apache/hadoop/hbase/regionserver/MetricsRegion.updateDelete:()V
      81: aload_0
      82: getfield      #11                 // Field region:Lorg/apache/hadoop/hbase/regionserver/HRegion;
      85: invokestatic  #29                 // Method org/apache/hadoop/hbase/regionserver/HRegion.access$800:(Lorg/apache/hadoop/hbase/regionserver/HRegion;)Lorg/apache/hadoop/hbase/regionserver/RegionCoprocessorHost;
      88: ifnull        119
      91: aload_0
      92: getfield      #11                 // Field region:Lorg/apache/hadoop/hbase/regionserver/HRegion;
      95: invokestatic  #29                 // Method org/apache/hadoop/hbase/regionserver/HRegion.access$800:(Lorg/apache/hadoop/hbase/regionserver/HRegion;)Lorg/apache/hadoop/hbase/regionserver/RegionCoprocessorHost;
      98: aload_1
      99: ifnull        106
     102: aload_1
     103: goto          115
     106: aload_0
     107: aload_0
     108: invokevirtual #19                 // Method size:()I
     111: iconst_0
     112: invokevirtual #47                 // Method createMiniBatch:(II)Lorg/apache/hadoop/hbase/regionserver/MiniBatchOperationInProgress;
     115: iload_3
     116: invokevirtual #48                 // Method org/apache/hadoop/hbase/regionserver/RegionCoprocessorHost.postBatchMutateIndispensably:(Lorg/apache/hadoop/hbase/regionserver/MiniBatchOperationInProgress;Z)V
     119: return

  static void access$900(org.apache.hadoop.hbase.regionserver.HRegion$MutationBatchOperation, int, org.apache.hadoop.hbase.wal.WALEdit, int[]) throws java.io.IOException;
    Code:
       0: aload_0
       1: iload_1
       2: aload_2
       3: aload_3
       4: invokespecial #1                  // Method callPreMutateCPHook:(ILorg/apache/hadoop/hbase/wal/WALEdit;[I)V
       7: return
}
