Compiled from "HRegion.java"
class org.apache.hadoop.hbase.regionserver.HRegion$1 implements java.util.concurrent.Callable<org.apache.hadoop.hbase.regionserver.HStore> {
  final org.apache.hadoop.hbase.client.ColumnFamilyDescriptor val$family;

  final boolean val$warmup;

  final org.apache.hadoop.hbase.regionserver.HRegion this$0;

  org.apache.hadoop.hbase.regionserver.HRegion$1(org.apache.hadoop.hbase.regionserver.HRegion, org.apache.hadoop.hbase.client.ColumnFamilyDescriptor, boolean);
    Code:
       0: aload_0
       1: aload_1
       2: putfield      #1                  // Field this$0:Lorg/apache/hadoop/hbase/regionserver/HRegion;
       5: aload_0
       6: aload_2
       7: putfield      #2                  // Field val$family:Lorg/apache/hadoop/hbase/client/ColumnFamilyDescriptor;
      10: aload_0
      11: iload_3
      12: putfield      #3                  // Field val$warmup:Z
      15: aload_0
      16: invokespecial #4                  // Method java/lang/Object."<init>":()V
      19: return

  public org.apache.hadoop.hbase.regionserver.HStore call() throws java.io.IOException;
    Code:
       0: aload_0
       1: getfield      #1                  // Field this$0:Lorg/apache/hadoop/hbase/regionserver/HRegion;
       4: aload_0
       5: getfield      #2                  // Field val$family:Lorg/apache/hadoop/hbase/client/ColumnFamilyDescriptor;
       8: aload_0
       9: getfield      #3                  // Field val$warmup:Z
      12: invokevirtual #5                  // Method org/apache/hadoop/hbase/regionserver/HRegion.instantiateHStore:(Lorg/apache/hadoop/hbase/client/ColumnFamilyDescriptor;Z)Lorg/apache/hadoop/hbase/regionserver/HStore;
      15: areturn

  public java.lang.Object call() throws java.lang.Exception;
    Code:
       0: aload_0
       1: invokevirtual #6                  // Method call:()Lorg/apache/hadoop/hbase/regionserver/HStore;
       4: areturn
}
