Compiled from "HRegionServer.java"
final class org.apache.hadoop.hbase.regionserver.HRegionServer$2 implements sun.misc.SignalHandler {
  final org.apache.hadoop.conf.Configuration val$conf;

  final org.apache.hadoop.hbase.conf.ConfigurationManager val$cm;

  org.apache.hadoop.hbase.regionserver.HRegionServer$2(org.apache.hadoop.conf.Configuration, org.apache.hadoop.hbase.conf.ConfigurationManager);
    Code:
       0: aload_0
       1: aload_1
       2: putfield      #1                  // Field val$conf:Lorg/apache/hadoop/conf/Configuration;
       5: aload_0
       6: aload_2
       7: putfield      #2                  // Field val$cm:Lorg/apache/hadoop/hbase/conf/ConfigurationManager;
      10: aload_0
      11: invokespecial #3                  // Method java/lang/Object."<init>":()V
      14: return

  public void handle(sun.misc.Signal);
    Code:
       0: aload_0
       1: getfield      #1                  // Field val$conf:Lorg/apache/hadoop/conf/Configuration;
       4: invokevirtual #4                  // Method org/apache/hadoop/conf/Configuration.reloadConfiguration:()V
       7: aload_0
       8: getfield      #2                  // Field val$cm:Lorg/apache/hadoop/hbase/conf/ConfigurationManager;
      11: aload_0
      12: getfield      #1                  // Field val$conf:Lorg/apache/hadoop/conf/Configuration;
      15: invokevirtual #5                  // Method org/apache/hadoop/hbase/conf/ConfigurationManager.notifyAllObservers:(Lorg/apache/hadoop/conf/Configuration;)V
      18: return
}
