Compiled from "HRegionServer.java"
class org.apache.hadoop.hbase.regionserver.HRegionServer$1 implements java.lang.Thread$UncaughtExceptionHandler {
  final org.apache.hadoop.hbase.regionserver.HRegionServer this$0;

  org.apache.hadoop.hbase.regionserver.HRegionServer$1(org.apache.hadoop.hbase.regionserver.HRegionServer);
    Code:
       0: aload_0
       1: aload_1
       2: putfield      #1                  // Field this$0:Lorg/apache/hadoop/hbase/regionserver/HRegionServer;
       5: aload_0
       6: invokespecial #2                  // Method java/lang/Object."<init>":()V
       9: return

  public void uncaughtException(java.lang.Thread, java.lang.Throwable);
    Code:
       0: aload_0
       1: getfield      #1                  // Field this$0:Lorg/apache/hadoop/hbase/regionserver/HRegionServer;
       4: new           #3                  // class java/lang/StringBuilder
       7: dup
       8: invokespecial #4                  // Method java/lang/StringBuilder."<init>":()V
      11: ldc           #5                  // String Uncaught exception in executorService thread
      13: invokevirtual #6                  // Method java/lang/StringBuilder.append:(Ljava/lang/String;)Ljava/lang/StringBuilder;
      16: aload_1
      17: invokevirtual #7                  // Method java/lang/Thread.getName:()Ljava/lang/String;
      20: invokevirtual #6                  // Method java/lang/StringBuilder.append:(Ljava/lang/String;)Ljava/lang/StringBuilder;
      23: invokevirtual #8                  // Method java/lang/StringBuilder.toString:()Ljava/lang/String;
      26: aload_2
      27: invokevirtual #9                  // Method org/apache/hadoop/hbase/regionserver/HRegionServer.abort:(Ljava/lang/String;Ljava/lang/Throwable;)V
      30: return
}
