Compiled from "HStore.java"
public class org.apache.hadoop.hbase.regionserver.HStore implements org.apache.hadoop.hbase.regionserver.Store,org.apache.hadoop.hbase.io.HeapSize,org.apache.hadoop.hbase.regionserver.StoreConfigInformation,org.apache.hadoop.hbase.conf.PropagatingConfigurationObserver {
  public static final java.lang.String MEMSTORE_CLASS_NAME;

  public static final java.lang.String COMPACTCHECKER_INTERVAL_MULTIPLIER_KEY;

  public static final java.lang.String BLOCKING_STOREFILES_KEY;

  public static final java.lang.String BLOCK_STORAGE_POLICY_KEY;

  public static final java.lang.String DEFAULT_BLOCK_STORAGE_POLICY;

  public static final int DEFAULT_COMPACTCHECKER_INTERVAL_MULTIPLIER;

  public static final int DEFAULT_BLOCKING_STOREFILE_COUNT;

  protected final org.apache.hadoop.hbase.regionserver.MemStore memstore;

  protected final org.apache.hadoop.hbase.regionserver.HRegion region;

  protected org.apache.hadoop.conf.Configuration conf;

  protected org.apache.hadoop.hbase.io.hfile.CacheConfig cacheConf;

  volatile boolean forceMajor;

  static int closeCheckInterval;

  final java.util.concurrent.locks.ReentrantReadWriteLock lock;

  final java.util.concurrent.locks.ReentrantLock archiveLock;

  protected final int blocksize;

  protected org.apache.hadoop.hbase.util.ChecksumType checksumType;

  protected int bytesPerChecksum;

  protected final org.apache.hadoop.hbase.CellComparator comparator;

  final org.apache.hadoop.hbase.regionserver.StoreEngine<?, ?, ?, ?> storeEngine;

  protected org.apache.hadoop.hbase.io.crypto.Encryption$Context cryptoContext;

  public static final long FIXED_OVERHEAD;

  public static final long DEEP_OVERHEAD;

  static final boolean $assertionsDisabled;

  protected org.apache.hadoop.hbase.regionserver.HStore(org.apache.hadoop.hbase.regionserver.HRegion, org.apache.hadoop.hbase.client.ColumnFamilyDescriptor, org.apache.hadoop.conf.Configuration, boolean) throws java.io.IOException;
    Code:
       0: aload_0
       1: invokespecial #11                 // Method java/lang/Object."<init>":()V
       4: aload_0
       5: lconst_0
       6: putfield      #12                 // Field lastCompactSize:J
       9: aload_0
      10: iconst_0
      11: putfield      #13                 // Field forceMajor:Z
      14: aload_0
      15: new           #14                 // class java/util/concurrent/atomic/AtomicLong
      18: dup
      19: invokespecial #15                 // Method java/util/concurrent/atomic/AtomicLong."<init>":()V
      22: putfield      #2                  // Field storeSize:Ljava/util/concurrent/atomic/AtomicLong;
      25: aload_0
      26: new           #14                 // class java/util/concurrent/atomic/AtomicLong
      29: dup
      30: invokespecial #15                 // Method java/util/concurrent/atomic/AtomicLong."<init>":()V
      33: putfield      #1                  // Field totalUncompressedBytes:Ljava/util/concurrent/atomic/AtomicLong;
      36: aload_0
      37: new           #16                 // class java/util/concurrent/locks/ReentrantReadWriteLock
      40: dup
      41: invokespecial #17                 // Method java/util/concurrent/locks/ReentrantReadWriteLock."<init>":()V
      44: putfield      #18                 // Field lock:Ljava/util/concurrent/locks/ReentrantReadWriteLock;
      47: aload_0
      48: new           #19                 // class java/util/concurrent/locks/ReentrantLock
      51: dup
      52: invokespecial #20                 // Method java/util/concurrent/locks/ReentrantLock."<init>":()V
      55: putfield      #21                 // Field archiveLock:Ljava/util/concurrent/locks/ReentrantLock;
      58: aload_0
      59: new           #22                 // class java/util/concurrent/atomic/AtomicInteger
      62: dup
      63: iconst_0
      64: invokespecial #23                 // Method java/util/concurrent/atomic/AtomicInteger."<init>":(I)V
      67: putfield      #24                 // Field currentParallelPutCount:Ljava/util/concurrent/atomic/AtomicInteger;
      70: aload_0
      71: invokestatic  #25                 // Method org/apache/hbase/thirdparty/com/google/common/collect/Lists.newArrayList:()Ljava/util/ArrayList;
      74: putfield      #26                 // Field filesCompacting:Ljava/util/List;
      77: aload_0
      78: new           #27                 // class java/util/concurrent/ConcurrentHashMap
      81: dup
      82: invokespecial #28                 // Method java/util/concurrent/ConcurrentHashMap."<init>":()V
      85: invokestatic  #29                 // Method java/util/Collections.newSetFromMap:(Ljava/util/Map;)Ljava/util/Set;
      88: putfield      #30                 // Field changedReaderObservers:Ljava/util/Set;
      91: aload_0
      92: getstatic     #31                 // Field org/apache/hadoop/hbase/io/crypto/Encryption$Context.NONE:Lorg/apache/hadoop/hbase/io/crypto/Encryption$Context;
      95: putfield      #32                 // Field cryptoContext:Lorg/apache/hadoop/hbase/io/crypto/Encryption$Context;
      98: aload_0
      99: new           #14                 // class java/util/concurrent/atomic/AtomicLong
     102: dup
     103: invokespecial #15                 // Method java/util/concurrent/atomic/AtomicLong."<init>":()V
     106: putfield      #8                  // Field flushedCellsCount:Ljava/util/concurrent/atomic/AtomicLong;
     109: aload_0
     110: new           #14                 // class java/util/concurrent/atomic/AtomicLong
     113: dup
     114: invokespecial #15                 // Method java/util/concurrent/atomic/AtomicLong."<init>":()V
     117: putfield      #33                 // Field compactedCellsCount:Ljava/util/concurrent/atomic/AtomicLong;
     120: aload_0
     121: new           #14                 // class java/util/concurrent/atomic/AtomicLong
     124: dup
     125: invokespecial #15                 // Method java/util/concurrent/atomic/AtomicLong."<init>":()V
     128: putfield      #34                 // Field majorCompactedCellsCount:Ljava/util/concurrent/atomic/AtomicLong;
     131: aload_0
     132: new           #14                 // class java/util/concurrent/atomic/AtomicLong
     135: dup
     136: invokespecial #15                 // Method java/util/concurrent/atomic/AtomicLong."<init>":()V
     139: putfield      #7                  // Field flushedCellsSize:Ljava/util/concurrent/atomic/AtomicLong;
     142: aload_0
     143: new           #14                 // class java/util/concurrent/atomic/AtomicLong
     146: dup
     147: invokespecial #15                 // Method java/util/concurrent/atomic/AtomicLong."<init>":()V
     150: putfield      #6                  // Field flushedOutputFileSize:Ljava/util/concurrent/atomic/AtomicLong;
     153: aload_0
     154: new           #14                 // class java/util/concurrent/atomic/AtomicLong
     157: dup
     158: invokespecial #15                 // Method java/util/concurrent/atomic/AtomicLong."<init>":()V
     161: putfield      #35                 // Field compactedCellsSize:Ljava/util/concurrent/atomic/AtomicLong;
     164: aload_0
     165: new           #14                 // class java/util/concurrent/atomic/AtomicLong
     168: dup
     169: invokespecial #15                 // Method java/util/concurrent/atomic/AtomicLong."<init>":()V
     172: putfield      #36                 // Field majorCompactedCellsSize:Ljava/util/concurrent/atomic/AtomicLong;
     175: aload_0
     176: aload_1
     177: invokevirtual #37                 // Method org/apache/hadoop/hbase/regionserver/HRegion.getRegionFileSystem:()Lorg/apache/hadoop/hbase/regionserver/HRegionFileSystem;
     180: putfield      #4                  // Field fs:Lorg/apache/hadoop/hbase/regionserver/HRegionFileSystem;
     183: aload_0
     184: getfield      #4                  // Field fs:Lorg/apache/hadoop/hbase/regionserver/HRegionFileSystem;
     187: aload_2
     188: invokeinterface #38,  1           // InterfaceMethod org/apache/hadoop/hbase/client/ColumnFamilyDescriptor.getNameAsString:()Ljava/lang/String;
     193: invokevirtual #39                 // Method org/apache/hadoop/hbase/regionserver/HRegionFileSystem.createStoreDir:(Ljava/lang/String;)Lorg/apache/hadoop/fs/Path;
     196: pop
     197: aload_0
     198: aload_1
     199: putfield      #40                 // Field region:Lorg/apache/hadoop/hbase/regionserver/HRegion;
     202: aload_0
     203: aload_2
     204: putfield      #41                 // Field family:Lorg/apache/hadoop/hbase/client/ColumnFamilyDescriptor;
     207: aload_0
     208: new           #42                 // class org/apache/hadoop/hbase/CompoundConfiguration
     211: dup
     212: invokespecial #43                 // Method org/apache/hadoop/hbase/CompoundConfiguration."<init>":()V
     215: aload_3
     216: invokevirtual #44                 // Method org/apache/hadoop/hbase/CompoundConfiguration.add:(Lorg/apache/hadoop/conf/Configuration;)Lorg/apache/hadoop/hbase/CompoundConfiguration;
     219: aload_1
     220: invokevirtual #45                 // Method org/apache/hadoop/hbase/regionserver/HRegion.getTableDescriptor:()Lorg/apache/hadoop/hbase/client/TableDescriptor;
     223: invokeinterface #46,  1           // InterfaceMethod org/apache/hadoop/hbase/client/TableDescriptor.getValues:()Ljava/util/Map;
     228: invokevirtual #47                 // Method org/apache/hadoop/hbase/CompoundConfiguration.addBytesMap:(Ljava/util/Map;)Lorg/apache/hadoop/hbase/CompoundConfiguration;
     231: aload_2
     232: invokeinterface #48,  1           // InterfaceMethod org/apache/hadoop/hbase/client/ColumnFamilyDescriptor.getConfiguration:()Ljava/util/Map;
     237: invokevirtual #49                 // Method org/apache/hadoop/hbase/CompoundConfiguration.addStringMap:(Ljava/util/Map;)Lorg/apache/hadoop/hbase/CompoundConfiguration;
     240: aload_2
     241: invokeinterface #50,  1           // InterfaceMethod org/apache/hadoop/hbase/client/ColumnFamilyDescriptor.getValues:()Ljava/util/Map;
     246: invokevirtual #47                 // Method org/apache/hadoop/hbase/CompoundConfiguration.addBytesMap:(Ljava/util/Map;)Lorg/apache/hadoop/hbase/CompoundConfiguration;
     249: putfield      #51                 // Field conf:Lorg/apache/hadoop/conf/Configuration;
     252: aload_0
     253: aload_2
     254: invokeinterface #52,  1           // InterfaceMethod org/apache/hadoop/hbase/client/ColumnFamilyDescriptor.getBlocksize:()I
     259: putfield      #53                 // Field blocksize:I
     262: aload_2
     263: invokeinterface #54,  1           // InterfaceMethod org/apache/hadoop/hbase/client/ColumnFamilyDescriptor.getStoragePolicy:()Ljava/lang/String;
     268: astore        5
     270: aconst_null
     271: aload         5
     273: if_acmpne     289
     276: aload_0
     277: getfield      #51                 // Field conf:Lorg/apache/hadoop/conf/Configuration;
     280: ldc           #56                 // String hbase.hstore.block.storage.policy
     282: ldc           #57                 // String HOT
     284: invokevirtual #58                 // Method org/apache/hadoop/conf/Configuration.get:(Ljava/lang/String;Ljava/lang/String;)Ljava/lang/String;
     287: astore        5
     289: aload_0
     290: getfield      #4                  // Field fs:Lorg/apache/hadoop/hbase/regionserver/HRegionFileSystem;
     293: aload_2
     294: invokeinterface #38,  1           // InterfaceMethod org/apache/hadoop/hbase/client/ColumnFamilyDescriptor.getNameAsString:()Ljava/lang/String;
     299: aload         5
     301: invokevirtual #59                 // Method java/lang/String.trim:()Ljava/lang/String;
     304: invokevirtual #60                 // Method org/apache/hadoop/hbase/regionserver/HRegionFileSystem.setStoragePolicy:(Ljava/lang/String;Ljava/lang/String;)V
     307: aload_0
     308: new           #61                 // class org/apache/hadoop/hbase/io/hfile/HFileDataBlockEncoderImpl
     311: dup
     312: aload_2
     313: invokeinterface #62,  1           // InterfaceMethod org/apache/hadoop/hbase/client/ColumnFamilyDescriptor.getDataBlockEncoding:()Lorg/apache/hadoop/hbase/io/encoding/DataBlockEncoding;
     318: invokespecial #63                 // Method org/apache/hadoop/hbase/io/hfile/HFileDataBlockEncoderImpl."<init>":(Lorg/apache/hadoop/hbase/io/encoding/DataBlockEncoding;)V
     321: putfield      #64                 // Field dataBlockEncoder:Lorg/apache/hadoop/hbase/io/hfile/HFileDataBlockEncoder;
     324: aload_0
     325: aload_1
     326: invokevirtual #65                 // Method org/apache/hadoop/hbase/regionserver/HRegion.getCellComparator:()Lorg/apache/hadoop/hbase/CellComparator;
     329: putfield      #66                 // Field comparator:Lorg/apache/hadoop/hbase/CellComparator;
     332: aload_0
     333: getfield      #51                 // Field conf:Lorg/apache/hadoop/conf/Configuration;
     336: ldc           #67                 // String hbase.hstore.time.to.purge.deletes
     338: lconst_0
     339: invokevirtual #68                 // Method org/apache/hadoop/conf/Configuration.getLong:(Ljava/lang/String;J)J
     342: lconst_0
     343: invokestatic  #69                 // Method java/lang/Math.max:(JJ)J
     346: lstore        6
     348: getstatic     #9                  // Field LOG:Lorg/slf4j/Logger;
     351: ldc           #70                 // String Time to purge deletes set to {}ms in store {}
     353: lload         6
     355: invokestatic  #71                 // Method java/lang/Long.valueOf:(J)Ljava/lang/Long;
     358: aload_0
     359: invokeinterface #72,  4           // InterfaceMethod org/slf4j/Logger.trace:(Ljava/lang/String;Ljava/lang/Object;Ljava/lang/Object;)V
     364: aload_2
     365: invokestatic  #73                 // Method determineTTLFromFamily:(Lorg/apache/hadoop/hbase/client/ColumnFamilyDescriptor;)J
     368: lstore        8
     370: aload_0
     371: new           #74                 // class org/apache/hadoop/hbase/regionserver/ScanInfo
     374: dup
     375: aload_0
     376: getfield      #51                 // Field conf:Lorg/apache/hadoop/conf/Configuration;
     379: aload_2
     380: lload         8
     382: lload         6
     384: aload_0
     385: getfield      #66                 // Field comparator:Lorg/apache/hadoop/hbase/CellComparator;
     388: invokespecial #75                 // Method org/apache/hadoop/hbase/regionserver/ScanInfo."<init>":(Lorg/apache/hadoop/conf/Configuration;Lorg/apache/hadoop/hbase/client/ColumnFamilyDescriptor;JJLorg/apache/hadoop/hbase/CellComparator;)V
     391: putfield      #76                 // Field scanInfo:Lorg/apache/hadoop/hbase/regionserver/ScanInfo;
     394: aload_0
     395: aload_0
     396: invokespecial #77                 // Method getMemstore:()Lorg/apache/hadoop/hbase/regionserver/MemStore;
     399: putfield      #78                 // Field memstore:Lorg/apache/hadoop/hbase/regionserver/MemStore;
     402: aload_0
     403: aload_0
     404: getfield      #51                 // Field conf:Lorg/apache/hadoop/conf/Configuration;
     407: invokestatic  #79                 // Method org/apache/hadoop/hbase/regionserver/compactions/OffPeakHours.getInstance:(Lorg/apache/hadoop/conf/Configuration;)Lorg/apache/hadoop/hbase/regionserver/compactions/OffPeakHours;
     410: putfield      #80                 // Field offPeakHours:Lorg/apache/hadoop/hbase/regionserver/compactions/OffPeakHours;
     413: aload_0
     414: aload_2
     415: invokevirtual #81                 // Method createCacheConf:(Lorg/apache/hadoop/hbase/client/ColumnFamilyDescriptor;)V
     418: aload_0
     419: aload_0
     420: getfield      #51                 // Field conf:Lorg/apache/hadoop/conf/Configuration;
     423: ldc           #82                 // String hbase.hstore.bulkload.verify
     425: iconst_0
     426: invokevirtual #83                 // Method org/apache/hadoop/conf/Configuration.getBoolean:(Ljava/lang/String;Z)Z
     429: putfield      #84                 // Field verifyBulkLoads:Z
     432: aload_0
     433: aload_0
     434: getfield      #51                 // Field conf:Lorg/apache/hadoop/conf/Configuration;
     437: ldc           #85                 // String hbase.hstore.blockingStoreFiles
     439: bipush        16
     441: invokevirtual #86                 // Method org/apache/hadoop/conf/Configuration.getInt:(Ljava/lang/String;I)I
     444: i2l
     445: putfield      #87                 // Field blockingFileCount:J
     448: aload_0
     449: aload_0
     450: getfield      #51                 // Field conf:Lorg/apache/hadoop/conf/Configuration;
     453: ldc           #88                 // String hbase.server.compactchecker.interval.multiplier
     455: sipush        1000
     458: invokevirtual #86                 // Method org/apache/hadoop/conf/Configuration.getInt:(Ljava/lang/String;I)I
     461: putfield      #89                 // Field compactionCheckMultiplier:I
     464: aload_0
     465: getfield      #89                 // Field compactionCheckMultiplier:I
     468: ifgt          494
     471: getstatic     #9                  // Field LOG:Lorg/slf4j/Logger;
     474: ldc           #90                 // String Compaction check period multiplier must be positive, setting default: {}
     476: sipush        1000
     479: invokestatic  #91                 // Method java/lang/Integer.valueOf:(I)Ljava/lang/Integer;
     482: invokeinterface #92,  3           // InterfaceMethod org/slf4j/Logger.error:(Ljava/lang/String;Ljava/lang/Object;)V
     487: aload_0
     488: sipush        1000
     491: putfield      #89                 // Field compactionCheckMultiplier:I
     494: getstatic     #93                 // Field closeCheckInterval:I
     497: ifne          514
     500: aload_0
     501: getfield      #51                 // Field conf:Lorg/apache/hadoop/conf/Configuration;
     504: ldc           #94                 // String hbase.hstore.close.check.interval
     506: ldc           #95                 // int 10000000
     508: invokevirtual #86                 // Method org/apache/hadoop/conf/Configuration.getInt:(Ljava/lang/String;I)I
     511: putstatic     #93                 // Field closeCheckInterval:I
     514: aload_0
     515: aload_0
     516: aload_0
     517: aload_0
     518: getfield      #51                 // Field conf:Lorg/apache/hadoop/conf/Configuration;
     521: aload_0
     522: getfield      #66                 // Field comparator:Lorg/apache/hadoop/hbase/CellComparator;
     525: invokevirtual #96                 // Method createStoreEngine:(Lorg/apache/hadoop/hbase/regionserver/HStore;Lorg/apache/hadoop/conf/Configuration;Lorg/apache/hadoop/hbase/CellComparator;)Lorg/apache/hadoop/hbase/regionserver/StoreEngine;
     528: putfield      #97                 // Field storeEngine:Lorg/apache/hadoop/hbase/regionserver/StoreEngine;
     531: aload_0
     532: iload         4
     534: invokespecial #98                 // Method loadStoreFiles:(Z)Ljava/util/List;
     537: astore        10
     539: aload_0
     540: getfield      #2                  // Field storeSize:Ljava/util/concurrent/atomic/AtomicLong;
     543: aload_0
     544: aload         10
     546: invokedynamic #99,  0             // InvokeDynamic #0:test:()Ljava/util/function/Predicate;
     551: invokespecial #100                // Method getStorefilesSize:(Ljava/util/Collection;Ljava/util/function/Predicate;)J
     554: invokevirtual #101                // Method java/util/concurrent/atomic/AtomicLong.addAndGet:(J)J
     557: pop2
     558: aload_0
     559: getfield      #1                  // Field totalUncompressedBytes:Ljava/util/concurrent/atomic/AtomicLong;
     562: aload_0
     563: aload         10
     565: invokespecial #102                // Method getTotalUmcompressedBytes:(Ljava/util/List;)J
     568: invokevirtual #101                // Method java/util/concurrent/atomic/AtomicLong.addAndGet:(J)J
     571: pop2
     572: aload_0
     573: getfield      #97                 // Field storeEngine:Lorg/apache/hadoop/hbase/regionserver/StoreEngine;
     576: invokevirtual #103                // Method org/apache/hadoop/hbase/regionserver/StoreEngine.getStoreFileManager:()Lorg/apache/hadoop/hbase/regionserver/StoreFileManager;
     579: aload         10
     581: invokeinterface #104,  2          // InterfaceMethod org/apache/hadoop/hbase/regionserver/StoreFileManager.loadFiles:(Ljava/util/List;)V
     586: aload_0
     587: aload_0
     588: getfield      #51                 // Field conf:Lorg/apache/hadoop/conf/Configuration;
     591: invokestatic  #105                // Method getChecksumType:(Lorg/apache/hadoop/conf/Configuration;)Lorg/apache/hadoop/hbase/util/ChecksumType;
     594: putfield      #106                // Field checksumType:Lorg/apache/hadoop/hbase/util/ChecksumType;
     597: aload_0
     598: aload_0
     599: getfield      #51                 // Field conf:Lorg/apache/hadoop/conf/Configuration;
     602: invokestatic  #107                // Method getBytesPerChecksum:(Lorg/apache/hadoop/conf/Configuration;)I
     605: putfield      #108                // Field bytesPerChecksum:I
     608: aload_0
     609: aload_0
     610: getfield      #51                 // Field conf:Lorg/apache/hadoop/conf/Configuration;
     613: ldc           #109                // String hbase.hstore.flush.retries.number
     615: bipush        10
     617: invokevirtual #86                 // Method org/apache/hadoop/conf/Configuration.getInt:(Ljava/lang/String;I)I
     620: putfield      #110                // Field flushRetriesNumber:I
     623: aload_0
     624: aload_0
     625: getfield      #51                 // Field conf:Lorg/apache/hadoop/conf/Configuration;
     628: ldc           #112                // String hbase.server.pause
     630: sipush        1000
     633: invokevirtual #86                 // Method org/apache/hadoop/conf/Configuration.getInt:(Ljava/lang/String;I)I
     636: putfield      #113                // Field pauseTime:I
     639: aload_0
     640: getfield      #110                // Field flushRetriesNumber:I
     643: ifgt          676
     646: new           #114                // class java/lang/IllegalArgumentException
     649: dup
     650: new           #115                // class java/lang/StringBuilder
     653: dup
     654: invokespecial #116                // Method java/lang/StringBuilder."<init>":()V
     657: ldc           #117                // String hbase.hstore.flush.retries.number must be > 0, not
     659: invokevirtual #118                // Method java/lang/StringBuilder.append:(Ljava/lang/String;)Ljava/lang/StringBuilder;
     662: aload_0
     663: getfield      #110                // Field flushRetriesNumber:I
     666: invokevirtual #119                // Method java/lang/StringBuilder.append:(I)Ljava/lang/StringBuilder;
     669: invokevirtual #120                // Method java/lang/StringBuilder.toString:()Ljava/lang/String;
     672: invokespecial #121                // Method java/lang/IllegalArgumentException."<init>":(Ljava/lang/String;)V
     675: athrow
     676: aload_0
     677: aload_0
     678: getfield      #51                 // Field conf:Lorg/apache/hadoop/conf/Configuration;
     681: aload_2
     682: invokestatic  #122                // Method org/apache/hadoop/hbase/security/EncryptionUtil.createEncryptionContext:(Lorg/apache/hadoop/conf/Configuration;Lorg/apache/hadoop/hbase/client/ColumnFamilyDescriptor;)Lorg/apache/hadoop/hbase/io/crypto/Encryption$Context;
     685: putfield      #32                 // Field cryptoContext:Lorg/apache/hadoop/hbase/io/crypto/Encryption$Context;
     688: aload_0
     689: getfield      #51                 // Field conf:Lorg/apache/hadoop/conf/Configuration;
     692: ldc           #123                // String hbase.region.store.parallel.put.print.threshold
     694: bipush        50
     696: invokevirtual #86                 // Method org/apache/hadoop/conf/Configuration.getInt:(Ljava/lang/String;I)I
     699: istore        11
     701: iload         11
     703: bipush        10
     705: if_icmpge     712
     708: bipush        10
     710: istore        11
     712: aload_0
     713: iload         11
     715: putfield      #124                // Field parallelPutCountPrintThreshold:I
     718: getstatic     #9                  // Field LOG:Lorg/slf4j/Logger;
     721: ldc           #125                // String Store={},  memstore type={}, storagePolicy={}, verifyBulkLoads={}, parallelPutCountPrintThreshold={}, encoding={}, compression={}
     723: bipush        7
     725: anewarray     #126                // class java/lang/Object
     728: dup
     729: iconst_0
     730: aload_0
     731: invokevirtual #127                // Method getColumnFamilyName:()Ljava/lang/String;
     734: aastore
     735: dup
     736: iconst_1
     737: aload_0
     738: getfield      #78                 // Field memstore:Lorg/apache/hadoop/hbase/regionserver/MemStore;
     741: invokevirtual #128                // Method java/lang/Object.getClass:()Ljava/lang/Class;
     744: invokevirtual #129                // Method java/lang/Class.getSimpleName:()Ljava/lang/String;
     747: aastore
     748: dup
     749: iconst_2
     750: aload         5
     752: aastore
     753: dup
     754: iconst_3
     755: aload_0
     756: getfield      #84                 // Field verifyBulkLoads:Z
     759: invokestatic  #130                // Method java/lang/Boolean.valueOf:(Z)Ljava/lang/Boolean;
     762: aastore
     763: dup
     764: iconst_4
     765: aload_0
     766: getfield      #124                // Field parallelPutCountPrintThreshold:I
     769: invokestatic  #91                 // Method java/lang/Integer.valueOf:(I)Ljava/lang/Integer;
     772: aastore
     773: dup
     774: iconst_5
     775: aload_2
     776: invokeinterface #62,  1           // InterfaceMethod org/apache/hadoop/hbase/client/ColumnFamilyDescriptor.getDataBlockEncoding:()Lorg/apache/hadoop/hbase/io/encoding/DataBlockEncoding;
     781: aastore
     782: dup
     783: bipush        6
     785: aload_2
     786: invokeinterface #131,  1          // InterfaceMethod org/apache/hadoop/hbase/client/ColumnFamilyDescriptor.getCompressionType:()Lorg/apache/hadoop/hbase/io/compress/Compression$Algorithm;
     791: aastore
     792: invokeinterface #132,  3          // InterfaceMethod org/slf4j/Logger.info:(Ljava/lang/String;[Ljava/lang/Object;)V
     797: return

  protected void createCacheConf(org.apache.hadoop.hbase.client.ColumnFamilyDescriptor);
    Code:
       0: aload_0
       1: new           #152                // class org/apache/hadoop/hbase/io/hfile/CacheConfig
       4: dup
       5: aload_0
       6: getfield      #51                 // Field conf:Lorg/apache/hadoop/conf/Configuration;
       9: aload_1
      10: aload_0
      11: getfield      #40                 // Field region:Lorg/apache/hadoop/hbase/regionserver/HRegion;
      14: invokevirtual #153                // Method org/apache/hadoop/hbase/regionserver/HRegion.getBlockCache:()Lorg/apache/hadoop/hbase/io/hfile/BlockCache;
      17: invokespecial #154                // Method org/apache/hadoop/hbase/io/hfile/CacheConfig."<init>":(Lorg/apache/hadoop/conf/Configuration;Lorg/apache/hadoop/hbase/client/ColumnFamilyDescriptor;Lorg/apache/hadoop/hbase/io/hfile/BlockCache;)V
      20: putfield      #155                // Field cacheConf:Lorg/apache/hadoop/hbase/io/hfile/CacheConfig;
      23: return

  protected org.apache.hadoop.hbase.regionserver.StoreEngine<?, ?, ?, ?> createStoreEngine(org.apache.hadoop.hbase.regionserver.HStore, org.apache.hadoop.conf.Configuration, org.apache.hadoop.hbase.CellComparator) throws java.io.IOException;
    Code:
       0: aload_1
       1: aload_2
       2: aload_0
       3: getfield      #66                 // Field comparator:Lorg/apache/hadoop/hbase/CellComparator;
       6: invokestatic  #156                // Method org/apache/hadoop/hbase/regionserver/StoreEngine.create:(Lorg/apache/hadoop/hbase/regionserver/HStore;Lorg/apache/hadoop/conf/Configuration;Lorg/apache/hadoop/hbase/CellComparator;)Lorg/apache/hadoop/hbase/regionserver/StoreEngine;
       9: areturn

  public static long determineTTLFromFamily(org.apache.hadoop.hbase.client.ColumnFamilyDescriptor);
    Code:
       0: aload_0
       1: invokeinterface #157,  1          // InterfaceMethod org/apache/hadoop/hbase/client/ColumnFamilyDescriptor.getTimeToLive:()I
       6: i2l
       7: lstore_1
       8: lload_1
       9: ldc2_w        #158                // long 2147483647l
      12: lcmp
      13: ifne          23
      16: ldc2_w        #161                // long 9223372036854775807l
      19: lstore_1
      20: goto          44
      23: lload_1
      24: ldc2_w        #163                // long -1l
      27: lcmp
      28: ifne          38
      31: ldc2_w        #161                // long 9223372036854775807l
      34: lstore_1
      35: goto          44
      38: lload_1
      39: ldc2_w        #165                // long 1000l
      42: lmul
      43: lstore_1
      44: lload_1
      45: lreturn

  public java.lang.String getColumnFamilyName();
    Code:
       0: aload_0
       1: getfield      #41                 // Field family:Lorg/apache/hadoop/hbase/client/ColumnFamilyDescriptor;
       4: invokeinterface #38,  1           // InterfaceMethod org/apache/hadoop/hbase/client/ColumnFamilyDescriptor.getNameAsString:()Ljava/lang/String;
       9: areturn

  public org.apache.hadoop.hbase.TableName getTableName();
    Code:
       0: aload_0
       1: invokevirtual #167                // Method getRegionInfo:()Lorg/apache/hadoop/hbase/client/RegionInfo;
       4: invokeinterface #168,  1          // InterfaceMethod org/apache/hadoop/hbase/client/RegionInfo.getTable:()Lorg/apache/hadoop/hbase/TableName;
       9: areturn

  public org.apache.hadoop.fs.FileSystem getFileSystem();
    Code:
       0: aload_0
       1: getfield      #4                  // Field fs:Lorg/apache/hadoop/hbase/regionserver/HRegionFileSystem;
       4: invokevirtual #169                // Method org/apache/hadoop/hbase/regionserver/HRegionFileSystem.getFileSystem:()Lorg/apache/hadoop/fs/FileSystem;
       7: areturn

  public org.apache.hadoop.hbase.regionserver.HRegionFileSystem getRegionFileSystem();
    Code:
       0: aload_0
       1: getfield      #4                  // Field fs:Lorg/apache/hadoop/hbase/regionserver/HRegionFileSystem;
       4: areturn

  public long getStoreFileTtl();
    Code:
       0: aload_0
       1: getfield      #76                 // Field scanInfo:Lorg/apache/hadoop/hbase/regionserver/ScanInfo;
       4: invokevirtual #170                // Method org/apache/hadoop/hbase/regionserver/ScanInfo.getMinVersions:()I
       7: ifne          20
      10: aload_0
      11: getfield      #76                 // Field scanInfo:Lorg/apache/hadoop/hbase/regionserver/ScanInfo;
      14: invokevirtual #171                // Method org/apache/hadoop/hbase/regionserver/ScanInfo.getTtl:()J
      17: goto          23
      20: ldc2_w        #161                // long 9223372036854775807l
      23: lreturn

  public long getMemStoreFlushSize();
    Code:
       0: aload_0
       1: getfield      #40                 // Field region:Lorg/apache/hadoop/hbase/regionserver/HRegion;
       4: getfield      #172                // Field org/apache/hadoop/hbase/regionserver/HRegion.memstoreFlushSize:J
       7: lreturn

  public org.apache.hadoop.hbase.regionserver.MemStoreSize getFlushableSize();
    Code:
       0: aload_0
       1: getfield      #78                 // Field memstore:Lorg/apache/hadoop/hbase/regionserver/MemStore;
       4: invokeinterface #173,  1          // InterfaceMethod org/apache/hadoop/hbase/regionserver/MemStore.getFlushableSize:()Lorg/apache/hadoop/hbase/regionserver/MemStoreSize;
       9: areturn

  public org.apache.hadoop.hbase.regionserver.MemStoreSize getSnapshotSize();
    Code:
       0: aload_0
       1: getfield      #78                 // Field memstore:Lorg/apache/hadoop/hbase/regionserver/MemStore;
       4: invokeinterface #174,  1          // InterfaceMethod org/apache/hadoop/hbase/regionserver/MemStore.getSnapshotSize:()Lorg/apache/hadoop/hbase/regionserver/MemStoreSize;
       9: areturn

  public long getCompactionCheckMultiplier();
    Code:
       0: aload_0
       1: getfield      #89                 // Field compactionCheckMultiplier:I
       4: i2l
       5: lreturn

  public long getBlockingFileCount();
    Code:
       0: aload_0
       1: getfield      #87                 // Field blockingFileCount:J
       4: lreturn

  public static int getBytesPerChecksum(org.apache.hadoop.conf.Configuration);
    Code:
       0: aload_0
       1: ldc           #175                // String hbase.hstore.bytes.per.checksum
       3: sipush        16384
       6: invokevirtual #86                 // Method org/apache/hadoop/conf/Configuration.getInt:(Ljava/lang/String;I)I
       9: ireturn

  public static org.apache.hadoop.hbase.util.ChecksumType getChecksumType(org.apache.hadoop.conf.Configuration);
    Code:
       0: aload_0
       1: ldc           #177                // String hbase.hstore.checksum.algorithm
       3: invokevirtual #178                // Method org/apache/hadoop/conf/Configuration.get:(Ljava/lang/String;)Ljava/lang/String;
       6: astore_1
       7: aload_1
       8: ifnonnull     15
      11: invokestatic  #179                // Method org/apache/hadoop/hbase/util/ChecksumType.getDefaultChecksumType:()Lorg/apache/hadoop/hbase/util/ChecksumType;
      14: areturn
      15: aload_1
      16: invokestatic  #180                // Method org/apache/hadoop/hbase/util/ChecksumType.nameToType:(Ljava/lang/String;)Lorg/apache/hadoop/hbase/util/ChecksumType;
      19: areturn

  public static int getCloseCheckInterval();
    Code:
       0: getstatic     #93                 // Field closeCheckInterval:I
       3: ireturn

  public org.apache.hadoop.hbase.client.ColumnFamilyDescriptor getColumnFamilyDescriptor();
    Code:
       0: aload_0
       1: getfield      #41                 // Field family:Lorg/apache/hadoop/hbase/client/ColumnFamilyDescriptor;
       4: areturn

  public java.util.OptionalLong getMaxSequenceId();
    Code:
       0: aload_0
       1: invokevirtual #181                // Method getStorefiles:()Ljava/util/Collection;
       4: invokestatic  #182                // Method org/apache/hadoop/hbase/regionserver/StoreUtils.getMaxSequenceIdInList:(Ljava/util/Collection;)Ljava/util/OptionalLong;
       7: areturn

  public java.util.OptionalLong getMaxMemStoreTS();
    Code:
       0: aload_0
       1: invokevirtual #181                // Method getStorefiles:()Ljava/util/Collection;
       4: invokestatic  #183                // Method org/apache/hadoop/hbase/regionserver/StoreUtils.getMaxMemStoreTSInList:(Ljava/util/Collection;)Ljava/util/OptionalLong;
       7: areturn

  public static org.apache.hadoop.fs.Path getStoreHomedir(org.apache.hadoop.fs.Path, org.apache.hadoop.hbase.client.RegionInfo, byte[]);
    Code:
       0: aload_0
       1: aload_1
       2: invokeinterface #184,  1          // InterfaceMethod org/apache/hadoop/hbase/client/RegionInfo.getEncodedName:()Ljava/lang/String;
       7: aload_2
       8: invokestatic  #185                // Method getStoreHomedir:(Lorg/apache/hadoop/fs/Path;Ljava/lang/String;[B)Lorg/apache/hadoop/fs/Path;
      11: areturn

  public static org.apache.hadoop.fs.Path getStoreHomedir(org.apache.hadoop.fs.Path, java.lang.String, byte[]);
    Code:
       0: new           #186                // class org/apache/hadoop/fs/Path
       3: dup
       4: aload_0
       5: new           #186                // class org/apache/hadoop/fs/Path
       8: dup
       9: aload_1
      10: aload_2
      11: invokestatic  #187                // Method org/apache/hadoop/hbase/util/Bytes.toString:([B)Ljava/lang/String;
      14: invokespecial #188                // Method org/apache/hadoop/fs/Path."<init>":(Ljava/lang/String;Ljava/lang/String;)V
      17: invokespecial #189                // Method org/apache/hadoop/fs/Path."<init>":(Lorg/apache/hadoop/fs/Path;Lorg/apache/hadoop/fs/Path;)V
      20: areturn

  public org.apache.hadoop.hbase.io.hfile.HFileDataBlockEncoder getDataBlockEncoder();
    Code:
       0: aload_0
       1: getfield      #64                 // Field dataBlockEncoder:Lorg/apache/hadoop/hbase/io/hfile/HFileDataBlockEncoder;
       4: areturn

  void setDataBlockEncoderInTest(org.apache.hadoop.hbase.io.hfile.HFileDataBlockEncoder);
    Code:
       0: aload_0
       1: aload_1
       2: putfield      #64                 // Field dataBlockEncoder:Lorg/apache/hadoop/hbase/io/hfile/HFileDataBlockEncoder;
       5: return

  public void refreshStoreFiles() throws java.io.IOException;
    Code:
       0: aload_0
       1: getfield      #4                  // Field fs:Lorg/apache/hadoop/hbase/regionserver/HRegionFileSystem;
       4: aload_0
       5: invokevirtual #127                // Method getColumnFamilyName:()Ljava/lang/String;
       8: invokevirtual #190                // Method org/apache/hadoop/hbase/regionserver/HRegionFileSystem.getStoreFiles:(Ljava/lang/String;)Ljava/util/Collection;
      11: astore_1
      12: aload_0
      13: aload_1
      14: invokespecial #248                // Method refreshStoreFilesInternal:(Ljava/util/Collection;)V
      17: return

  public void refreshStoreFiles(java.util.Collection<java.lang.String>) throws java.io.IOException;
    Code:
       0: new           #208                // class java/util/ArrayList
       3: dup
       4: aload_1
       5: invokeinterface #209,  1          // InterfaceMethod java/util/Collection.size:()I
      10: invokespecial #210                // Method java/util/ArrayList."<init>":(I)V
      13: astore_2
      14: aload_1
      15: invokeinterface #200,  1          // InterfaceMethod java/util/Collection.iterator:()Ljava/util/Iterator;
      20: astore_3
      21: aload_3
      22: invokeinterface #201,  1          // InterfaceMethod java/util/Iterator.hasNext:()Z
      27: ifeq          64
      30: aload_3
      31: invokeinterface #202,  1          // InterfaceMethod java/util/Iterator.next:()Ljava/lang/Object;
      36: checkcast     #249                // class java/lang/String
      39: astore        4
      41: aload_2
      42: aload_0
      43: getfield      #4                  // Field fs:Lorg/apache/hadoop/hbase/regionserver/HRegionFileSystem;
      46: aload_0
      47: invokevirtual #127                // Method getColumnFamilyName:()Ljava/lang/String;
      50: aload         4
      52: invokevirtual #250                // Method org/apache/hadoop/hbase/regionserver/HRegionFileSystem.getStoreFileInfo:(Ljava/lang/String;Ljava/lang/String;)Lorg/apache/hadoop/hbase/regionserver/StoreFileInfo;
      55: invokeinterface #241,  2          // InterfaceMethod java/util/List.add:(Ljava/lang/Object;)Z
      60: pop
      61: goto          21
      64: aload_0
      65: aload_2
      66: invokespecial #248                // Method refreshStoreFilesInternal:(Ljava/util/Collection;)V
      69: return

  protected org.apache.hadoop.hbase.regionserver.HStoreFile createStoreFileAndReader(org.apache.hadoop.fs.Path) throws java.io.IOException;
    Code:
       0: new           #203                // class org/apache/hadoop/hbase/regionserver/StoreFileInfo
       3: dup
       4: aload_0
       5: getfield      #51                 // Field conf:Lorg/apache/hadoop/conf/Configuration;
       8: aload_0
       9: invokevirtual #278                // Method getFileSystem:()Lorg/apache/hadoop/fs/FileSystem;
      12: aload_1
      13: invokespecial #279                // Method org/apache/hadoop/hbase/regionserver/StoreFileInfo."<init>":(Lorg/apache/hadoop/conf/Configuration;Lorg/apache/hadoop/fs/FileSystem;Lorg/apache/hadoop/fs/Path;)V
      16: astore_2
      17: aload_0
      18: aload_2
      19: invokespecial #3                  // Method createStoreFileAndReader:(Lorg/apache/hadoop/hbase/regionserver/StoreFileInfo;)Lorg/apache/hadoop/hbase/regionserver/HStoreFile;
      22: areturn

  public void startReplayingFromWAL();
    Code:
       0: aload_0
       1: getfield      #78                 // Field memstore:Lorg/apache/hadoop/hbase/regionserver/MemStore;
       4: invokeinterface #285,  1          // InterfaceMethod org/apache/hadoop/hbase/regionserver/MemStore.startReplayingFromWAL:()V
       9: return

  public void stopReplayingFromWAL();
    Code:
       0: aload_0
       1: getfield      #78                 // Field memstore:Lorg/apache/hadoop/hbase/regionserver/MemStore;
       4: invokeinterface #286,  1          // InterfaceMethod org/apache/hadoop/hbase/regionserver/MemStore.stopReplayingFromWAL:()V
       9: return

  public void add(org.apache.hadoop.hbase.Cell, org.apache.hadoop.hbase.regionserver.MemStoreSizing);
    Code:
       0: aload_0
       1: getfield      #18                 // Field lock:Ljava/util/concurrent/locks/ReentrantReadWriteLock;
       4: invokevirtual #287                // Method java/util/concurrent/locks/ReentrantReadWriteLock.readLock:()Ljava/util/concurrent/locks/ReentrantReadWriteLock$ReadLock;
       7: invokevirtual #288                // Method java/util/concurrent/locks/ReentrantReadWriteLock$ReadLock.lock:()V
      10: aload_0
      11: getfield      #24                 // Field currentParallelPutCount:Ljava/util/concurrent/atomic/AtomicInteger;
      14: invokevirtual #289                // Method java/util/concurrent/atomic/AtomicInteger.getAndIncrement:()I
      17: aload_0
      18: getfield      #124                // Field parallelPutCountPrintThreshold:I
      21: if_icmple     68
      24: getstatic     #9                  // Field LOG:Lorg/slf4j/Logger;
      27: new           #115                // class java/lang/StringBuilder
      30: dup
      31: invokespecial #116                // Method java/lang/StringBuilder."<init>":()V
      34: aload_0
      35: invokevirtual #133                // Method getTableName:()Lorg/apache/hadoop/hbase/TableName;
      38: invokevirtual #265                // Method java/lang/StringBuilder.append:(Ljava/lang/Object;)Ljava/lang/StringBuilder;
      41: ldc_w         #290                // String tableName={}, encodedName={}, columnFamilyName={} is too busy!
      44: invokevirtual #118                // Method java/lang/StringBuilder.append:(Ljava/lang/String;)Ljava/lang/StringBuilder;
      47: invokevirtual #120                // Method java/lang/StringBuilder.toString:()Ljava/lang/String;
      50: aload_0
      51: invokevirtual #167                // Method getRegionInfo:()Lorg/apache/hadoop/hbase/client/RegionInfo;
      54: invokeinterface #184,  1          // InterfaceMethod org/apache/hadoop/hbase/client/RegionInfo.getEncodedName:()Ljava/lang/String;
      59: aload_0
      60: invokevirtual #127                // Method getColumnFamilyName:()Ljava/lang/String;
      63: invokeinterface #72,  4           // InterfaceMethod org/slf4j/Logger.trace:(Ljava/lang/String;Ljava/lang/Object;Ljava/lang/Object;)V
      68: aload_0
      69: getfield      #78                 // Field memstore:Lorg/apache/hadoop/hbase/regionserver/MemStore;
      72: aload_1
      73: aload_2
      74: invokeinterface #291,  3          // InterfaceMethod org/apache/hadoop/hbase/regionserver/MemStore.add:(Lorg/apache/hadoop/hbase/Cell;Lorg/apache/hadoop/hbase/regionserver/MemStoreSizing;)V
      79: aload_0
      80: getfield      #18                 // Field lock:Ljava/util/concurrent/locks/ReentrantReadWriteLock;
      83: invokevirtual #287                // Method java/util/concurrent/locks/ReentrantReadWriteLock.readLock:()Ljava/util/concurrent/locks/ReentrantReadWriteLock$ReadLock;
      86: invokevirtual #292                // Method java/util/concurrent/locks/ReentrantReadWriteLock$ReadLock.unlock:()V
      89: aload_0
      90: getfield      #24                 // Field currentParallelPutCount:Ljava/util/concurrent/atomic/AtomicInteger;
      93: invokevirtual #293                // Method java/util/concurrent/atomic/AtomicInteger.decrementAndGet:()I
      96: pop
      97: goto          121
     100: astore_3
     101: aload_0
     102: getfield      #18                 // Field lock:Ljava/util/concurrent/locks/ReentrantReadWriteLock;
     105: invokevirtual #287                // Method java/util/concurrent/locks/ReentrantReadWriteLock.readLock:()Ljava/util/concurrent/locks/ReentrantReadWriteLock$ReadLock;
     108: invokevirtual #292                // Method java/util/concurrent/locks/ReentrantReadWriteLock$ReadLock.unlock:()V
     111: aload_0
     112: getfield      #24                 // Field currentParallelPutCount:Ljava/util/concurrent/atomic/AtomicInteger;
     115: invokevirtual #293                // Method java/util/concurrent/atomic/AtomicInteger.decrementAndGet:()I
     118: pop
     119: aload_3
     120: athrow
     121: return
    Exception table:
       from    to  target type
          10    79   100   any

  public void add(java.lang.Iterable<org.apache.hadoop.hbase.Cell>, org.apache.hadoop.hbase.regionserver.MemStoreSizing);
    Code:
       0: aload_0
       1: getfield      #18                 // Field lock:Ljava/util/concurrent/locks/ReentrantReadWriteLock;
       4: invokevirtual #287                // Method java/util/concurrent/locks/ReentrantReadWriteLock.readLock:()Ljava/util/concurrent/locks/ReentrantReadWriteLock$ReadLock;
       7: invokevirtual #288                // Method java/util/concurrent/locks/ReentrantReadWriteLock$ReadLock.lock:()V
      10: aload_0
      11: getfield      #24                 // Field currentParallelPutCount:Ljava/util/concurrent/atomic/AtomicInteger;
      14: invokevirtual #289                // Method java/util/concurrent/atomic/AtomicInteger.getAndIncrement:()I
      17: aload_0
      18: getfield      #124                // Field parallelPutCountPrintThreshold:I
      21: if_icmple     68
      24: getstatic     #9                  // Field LOG:Lorg/slf4j/Logger;
      27: new           #115                // class java/lang/StringBuilder
      30: dup
      31: invokespecial #116                // Method java/lang/StringBuilder."<init>":()V
      34: aload_0
      35: invokevirtual #133                // Method getTableName:()Lorg/apache/hadoop/hbase/TableName;
      38: invokevirtual #265                // Method java/lang/StringBuilder.append:(Ljava/lang/Object;)Ljava/lang/StringBuilder;
      41: ldc_w         #290                // String tableName={}, encodedName={}, columnFamilyName={} is too busy!
      44: invokevirtual #118                // Method java/lang/StringBuilder.append:(Ljava/lang/String;)Ljava/lang/StringBuilder;
      47: invokevirtual #120                // Method java/lang/StringBuilder.toString:()Ljava/lang/String;
      50: aload_0
      51: invokevirtual #167                // Method getRegionInfo:()Lorg/apache/hadoop/hbase/client/RegionInfo;
      54: invokeinterface #184,  1          // InterfaceMethod org/apache/hadoop/hbase/client/RegionInfo.getEncodedName:()Ljava/lang/String;
      59: aload_0
      60: invokevirtual #127                // Method getColumnFamilyName:()Ljava/lang/String;
      63: invokeinterface #72,  4           // InterfaceMethod org/slf4j/Logger.trace:(Ljava/lang/String;Ljava/lang/Object;Ljava/lang/Object;)V
      68: aload_0
      69: getfield      #78                 // Field memstore:Lorg/apache/hadoop/hbase/regionserver/MemStore;
      72: aload_1
      73: aload_2
      74: invokeinterface #294,  3          // InterfaceMethod org/apache/hadoop/hbase/regionserver/MemStore.add:(Ljava/lang/Iterable;Lorg/apache/hadoop/hbase/regionserver/MemStoreSizing;)V
      79: aload_0
      80: getfield      #18                 // Field lock:Ljava/util/concurrent/locks/ReentrantReadWriteLock;
      83: invokevirtual #287                // Method java/util/concurrent/locks/ReentrantReadWriteLock.readLock:()Ljava/util/concurrent/locks/ReentrantReadWriteLock$ReadLock;
      86: invokevirtual #292                // Method java/util/concurrent/locks/ReentrantReadWriteLock$ReadLock.unlock:()V
      89: aload_0
      90: getfield      #24                 // Field currentParallelPutCount:Ljava/util/concurrent/atomic/AtomicInteger;
      93: invokevirtual #293                // Method java/util/concurrent/atomic/AtomicInteger.decrementAndGet:()I
      96: pop
      97: goto          121
     100: astore_3
     101: aload_0
     102: getfield      #18                 // Field lock:Ljava/util/concurrent/locks/ReentrantReadWriteLock;
     105: invokevirtual #287                // Method java/util/concurrent/locks/ReentrantReadWriteLock.readLock:()Ljava/util/concurrent/locks/ReentrantReadWriteLock$ReadLock;
     108: invokevirtual #292                // Method java/util/concurrent/locks/ReentrantReadWriteLock$ReadLock.unlock:()V
     111: aload_0
     112: getfield      #24                 // Field currentParallelPutCount:Ljava/util/concurrent/atomic/AtomicInteger;
     115: invokevirtual #293                // Method java/util/concurrent/atomic/AtomicInteger.decrementAndGet:()I
     118: pop
     119: aload_3
     120: athrow
     121: return
    Exception table:
       from    to  target type
          10    79   100   any

  public long timeOfOldestEdit();
    Code:
       0: aload_0
       1: getfield      #78                 // Field memstore:Lorg/apache/hadoop/hbase/regionserver/MemStore;
       4: invokeinterface #295,  1          // InterfaceMethod org/apache/hadoop/hbase/regionserver/MemStore.timeOfOldestEdit:()J
       9: lreturn

  public java.util.Collection<org.apache.hadoop.hbase.regionserver.HStoreFile> getStorefiles();
    Code:
       0: aload_0
       1: getfield      #97                 // Field storeEngine:Lorg/apache/hadoop/hbase/regionserver/StoreEngine;
       4: invokevirtual #103                // Method org/apache/hadoop/hbase/regionserver/StoreEngine.getStoreFileManager:()Lorg/apache/hadoop/hbase/regionserver/StoreFileManager;
       7: invokeinterface #251,  1          // InterfaceMethod org/apache/hadoop/hbase/regionserver/StoreFileManager.getStorefiles:()Ljava/util/Collection;
      12: areturn

  public java.util.Collection<org.apache.hadoop.hbase.regionserver.HStoreFile> getCompactedFiles();
    Code:
       0: aload_0
       1: getfield      #97                 // Field storeEngine:Lorg/apache/hadoop/hbase/regionserver/StoreEngine;
       4: invokevirtual #103                // Method org/apache/hadoop/hbase/regionserver/StoreEngine.getStoreFileManager:()Lorg/apache/hadoop/hbase/regionserver/StoreFileManager;
       7: invokeinterface #252,  1          // InterfaceMethod org/apache/hadoop/hbase/regionserver/StoreFileManager.getCompactedfiles:()Ljava/util/Collection;
      12: areturn

  public void assertBulkLoadHFileOk(org.apache.hadoop.fs.Path) throws java.io.IOException;
    Code:
       0: aconst_null
       1: astore_2
       2: getstatic     #9                  // Field LOG:Lorg/slf4j/Logger;
       5: new           #115                // class java/lang/StringBuilder
       8: dup
       9: invokespecial #116                // Method java/lang/StringBuilder."<init>":()V
      12: ldc_w         #296                // String Validating hfile at
      15: invokevirtual #118                // Method java/lang/StringBuilder.append:(Ljava/lang/String;)Ljava/lang/StringBuilder;
      18: aload_1
      19: invokevirtual #265                // Method java/lang/StringBuilder.append:(Ljava/lang/Object;)Ljava/lang/StringBuilder;
      22: ldc_w         #297                // String  for inclusion in store
      25: invokevirtual #118                // Method java/lang/StringBuilder.append:(Ljava/lang/String;)Ljava/lang/StringBuilder;
      28: aload_0
      29: invokevirtual #265                // Method java/lang/StringBuilder.append:(Ljava/lang/Object;)Ljava/lang/StringBuilder;
      32: ldc_w         #298                // String  region
      35: invokevirtual #118                // Method java/lang/StringBuilder.append:(Ljava/lang/String;)Ljava/lang/StringBuilder;
      38: aload_0
      39: invokevirtual #167                // Method getRegionInfo:()Lorg/apache/hadoop/hbase/client/RegionInfo;
      42: invokeinterface #263,  1          // InterfaceMethod org/apache/hadoop/hbase/client/RegionInfo.getRegionNameAsString:()Ljava/lang/String;
      47: invokevirtual #118                // Method java/lang/StringBuilder.append:(Ljava/lang/String;)Ljava/lang/StringBuilder;
      50: invokevirtual #120                // Method java/lang/StringBuilder.toString:()Ljava/lang/String;
      53: invokeinterface #267,  2          // InterfaceMethod org/slf4j/Logger.info:(Ljava/lang/String;)V
      58: aload_1
      59: aload_0
      60: getfield      #51                 // Field conf:Lorg/apache/hadoop/conf/Configuration;
      63: invokevirtual #299                // Method org/apache/hadoop/fs/Path.getFileSystem:(Lorg/apache/hadoop/conf/Configuration;)Lorg/apache/hadoop/fs/FileSystem;
      66: astore_3
      67: aload_3
      68: aload_1
      69: getstatic     #300                // Field org/apache/hadoop/fs/permission/FsAction.READ_WRITE:Lorg/apache/hadoop/fs/permission/FsAction;
      72: invokevirtual #301                // Method org/apache/hadoop/fs/FileSystem.access:(Lorg/apache/hadoop/fs/Path;Lorg/apache/hadoop/fs/permission/FsAction;)V
      75: aload_3
      76: aload_1
      77: aload_0
      78: getfield      #155                // Field cacheConf:Lorg/apache/hadoop/hbase/io/hfile/CacheConfig;
      81: aload_0
      82: invokevirtual #244                // Method isPrimaryReplicaStore:()Z
      85: aload_0
      86: getfield      #51                 // Field conf:Lorg/apache/hadoop/conf/Configuration;
      89: invokestatic  #302                // Method org/apache/hadoop/hbase/io/hfile/HFile.createReader:(Lorg/apache/hadoop/fs/FileSystem;Lorg/apache/hadoop/fs/Path;Lorg/apache/hadoop/hbase/io/hfile/CacheConfig;ZLorg/apache/hadoop/conf/Configuration;)Lorg/apache/hadoop/hbase/io/hfile/HFile$Reader;
      92: astore_2
      93: aload_2
      94: invokeinterface #303,  1          // InterfaceMethod org/apache/hadoop/hbase/io/hfile/HFile$Reader.loadFileInfo:()Ljava/util/Map;
      99: pop
     100: aload_2
     101: invokeinterface #304,  1          // InterfaceMethod org/apache/hadoop/hbase/io/hfile/HFile$Reader.getFirstRowKey:()Ljava/util/Optional;
     106: astore        4
     108: aload         4
     110: invokevirtual #305                // Method java/util/Optional.isPresent:()Z
     113: ldc_w         #306                // String First key can not be null
     116: invokestatic  #307                // Method org/apache/hbase/thirdparty/com/google/common/base/Preconditions.checkState:(ZLjava/lang/Object;)V
     119: aload_2
     120: invokeinterface #308,  1          // InterfaceMethod org/apache/hadoop/hbase/io/hfile/HFile$Reader.getLastKey:()Ljava/util/Optional;
     125: astore        5
     127: aload         5
     129: invokevirtual #305                // Method java/util/Optional.isPresent:()Z
     132: ldc_w         #309                // String Last key can not be null
     135: invokestatic  #307                // Method org/apache/hbase/thirdparty/com/google/common/base/Preconditions.checkState:(ZLjava/lang/Object;)V
     138: aload         5
     140: invokevirtual #310                // Method java/util/Optional.get:()Ljava/lang/Object;
     143: checkcast     #311                // class org/apache/hadoop/hbase/Cell
     146: invokestatic  #312                // Method org/apache/hadoop/hbase/CellUtil.cloneRow:(Lorg/apache/hadoop/hbase/Cell;)[B
     149: astore        6
     151: getstatic     #9                  // Field LOG:Lorg/slf4j/Logger;
     154: invokeinterface #313,  1          // InterfaceMethod org/slf4j/Logger.isDebugEnabled:()Z
     159: ifeq          274
     162: getstatic     #9                  // Field LOG:Lorg/slf4j/Logger;
     165: new           #115                // class java/lang/StringBuilder
     168: dup
     169: invokespecial #116                // Method java/lang/StringBuilder."<init>":()V
     172: ldc_w         #314                // String HFile bounds: first=
     175: invokevirtual #118                // Method java/lang/StringBuilder.append:(Ljava/lang/String;)Ljava/lang/StringBuilder;
     178: aload         4
     180: invokevirtual #310                // Method java/util/Optional.get:()Ljava/lang/Object;
     183: checkcast     #315                // class "[B"
     186: invokestatic  #316                // Method org/apache/hadoop/hbase/util/Bytes.toStringBinary:([B)Ljava/lang/String;
     189: invokevirtual #118                // Method java/lang/StringBuilder.append:(Ljava/lang/String;)Ljava/lang/StringBuilder;
     192: ldc_w         #317                // String  last=
     195: invokevirtual #118                // Method java/lang/StringBuilder.append:(Ljava/lang/String;)Ljava/lang/StringBuilder;
     198: aload         6
     200: invokestatic  #316                // Method org/apache/hadoop/hbase/util/Bytes.toStringBinary:([B)Ljava/lang/String;
     203: invokevirtual #118                // Method java/lang/StringBuilder.append:(Ljava/lang/String;)Ljava/lang/StringBuilder;
     206: invokevirtual #120                // Method java/lang/StringBuilder.toString:()Ljava/lang/String;
     209: invokeinterface #318,  2          // InterfaceMethod org/slf4j/Logger.debug:(Ljava/lang/String;)V
     214: getstatic     #9                  // Field LOG:Lorg/slf4j/Logger;
     217: new           #115                // class java/lang/StringBuilder
     220: dup
     221: invokespecial #116                // Method java/lang/StringBuilder."<init>":()V
     224: ldc_w         #319                // String Region bounds: first=
     227: invokevirtual #118                // Method java/lang/StringBuilder.append:(Ljava/lang/String;)Ljava/lang/StringBuilder;
     230: aload_0
     231: invokevirtual #167                // Method getRegionInfo:()Lorg/apache/hadoop/hbase/client/RegionInfo;
     234: invokeinterface #320,  1          // InterfaceMethod org/apache/hadoop/hbase/client/RegionInfo.getStartKey:()[B
     239: invokestatic  #316                // Method org/apache/hadoop/hbase/util/Bytes.toStringBinary:([B)Ljava/lang/String;
     242: invokevirtual #118                // Method java/lang/StringBuilder.append:(Ljava/lang/String;)Ljava/lang/StringBuilder;
     245: ldc_w         #317                // String  last=
     248: invokevirtual #118                // Method java/lang/StringBuilder.append:(Ljava/lang/String;)Ljava/lang/StringBuilder;
     251: aload_0
     252: invokevirtual #167                // Method getRegionInfo:()Lorg/apache/hadoop/hbase/client/RegionInfo;
     255: invokeinterface #321,  1          // InterfaceMethod org/apache/hadoop/hbase/client/RegionInfo.getEndKey:()[B
     260: invokestatic  #316                // Method org/apache/hadoop/hbase/util/Bytes.toStringBinary:([B)Ljava/lang/String;
     263: invokevirtual #118                // Method java/lang/StringBuilder.append:(Ljava/lang/String;)Ljava/lang/StringBuilder;
     266: invokevirtual #120                // Method java/lang/StringBuilder.toString:()Ljava/lang/String;
     269: invokeinterface #318,  2          // InterfaceMethod org/slf4j/Logger.debug:(Ljava/lang/String;)V
     274: aload_0
     275: invokevirtual #167                // Method getRegionInfo:()Lorg/apache/hadoop/hbase/client/RegionInfo;
     278: aload         4
     280: invokevirtual #310                // Method java/util/Optional.get:()Ljava/lang/Object;
     283: checkcast     #315                // class "[B"
     286: aload         6
     288: invokeinterface #322,  3          // InterfaceMethod org/apache/hadoop/hbase/client/RegionInfo.containsRange:([B[B)Z
     293: ifne          345
     296: new           #323                // class org/apache/hadoop/hbase/regionserver/WrongRegionException
     299: dup
     300: new           #115                // class java/lang/StringBuilder
     303: dup
     304: invokespecial #116                // Method java/lang/StringBuilder."<init>":()V
     307: ldc_w         #324                // String Bulk load file
     310: invokevirtual #118                // Method java/lang/StringBuilder.append:(Ljava/lang/String;)Ljava/lang/StringBuilder;
     313: aload_1
     314: invokevirtual #325                // Method org/apache/hadoop/fs/Path.toString:()Ljava/lang/String;
     317: invokevirtual #118                // Method java/lang/StringBuilder.append:(Ljava/lang/String;)Ljava/lang/StringBuilder;
     320: ldc_w         #326                // String  does not fit inside region
     323: invokevirtual #118                // Method java/lang/StringBuilder.append:(Ljava/lang/String;)Ljava/lang/StringBuilder;
     326: aload_0
     327: invokevirtual #167                // Method getRegionInfo:()Lorg/apache/hadoop/hbase/client/RegionInfo;
     330: invokeinterface #263,  1          // InterfaceMethod org/apache/hadoop/hbase/client/RegionInfo.getRegionNameAsString:()Ljava/lang/String;
     335: invokevirtual #118                // Method java/lang/StringBuilder.append:(Ljava/lang/String;)Ljava/lang/StringBuilder;
     338: invokevirtual #120                // Method java/lang/StringBuilder.toString:()Ljava/lang/String;
     341: invokespecial #327                // Method org/apache/hadoop/hbase/regionserver/WrongRegionException."<init>":(Ljava/lang/String;)V
     344: athrow
     345: aload_2
     346: invokeinterface #328,  1          // InterfaceMethod org/apache/hadoop/hbase/io/hfile/HFile$Reader.length:()J
     351: aload_0
     352: getfield      #51                 // Field conf:Lorg/apache/hadoop/conf/Configuration;
     355: ldc_w         #329                // String hbase.hregion.max.filesize
     358: ldc2_w        #330                // long 10737418240l
     361: invokevirtual #68                 // Method org/apache/hadoop/conf/Configuration.getLong:(Ljava/lang/String;J)J
     364: lcmp
     365: ifle          417
     368: getstatic     #9                  // Field LOG:Lorg/slf4j/Logger;
     371: new           #115                // class java/lang/StringBuilder
     374: dup
     375: invokespecial #116                // Method java/lang/StringBuilder."<init>":()V
     378: ldc_w         #332                // String Trying to bulk load hfile
     381: invokevirtual #118                // Method java/lang/StringBuilder.append:(Ljava/lang/String;)Ljava/lang/StringBuilder;
     384: aload_1
     385: invokevirtual #265                // Method java/lang/StringBuilder.append:(Ljava/lang/Object;)Ljava/lang/StringBuilder;
     388: ldc_w         #333                // String  with size:
     391: invokevirtual #118                // Method java/lang/StringBuilder.append:(Ljava/lang/String;)Ljava/lang/StringBuilder;
     394: aload_2
     395: invokeinterface #328,  1          // InterfaceMethod org/apache/hadoop/hbase/io/hfile/HFile$Reader.length:()J
     400: invokevirtual #334                // Method java/lang/StringBuilder.append:(J)Ljava/lang/StringBuilder;
     403: ldc_w         #335                // String  bytes can be problematic as it may lead to oversplitting.
     406: invokevirtual #118                // Method java/lang/StringBuilder.append:(Ljava/lang/String;)Ljava/lang/StringBuilder;
     409: invokevirtual #120                // Method java/lang/StringBuilder.toString:()Ljava/lang/String;
     412: invokeinterface #336,  2          // InterfaceMethod org/slf4j/Logger.warn:(Ljava/lang/String;)V
     417: aload_0
     418: getfield      #84                 // Field verifyBulkLoads:Z
     421: ifeq          724
     424: invokestatic  #337                // Method org/apache/hadoop/hbase/util/EnvironmentEdgeManager.currentTime:()J
     427: lstore        7
     429: getstatic     #9                  // Field LOG:Lorg/slf4j/Logger;
     432: ldc_w         #338                // String Full verification started for bulk load hfile: {}
     435: aload_1
     436: invokeinterface #339,  3          // InterfaceMethod org/slf4j/Logger.info:(Ljava/lang/String;Ljava/lang/Object;)V
     441: aconst_null
     442: astore        9
     444: aload_2
     445: iconst_0
     446: iconst_0
     447: iconst_0
     448: invokeinterface #340,  4          // InterfaceMethod org/apache/hadoop/hbase/io/hfile/HFile$Reader.getScanner:(ZZZ)Lorg/apache/hadoop/hbase/io/hfile/HFileScanner;
     453: astore        10
     455: aload         10
     457: invokeinterface #341,  1          // InterfaceMethod org/apache/hadoop/hbase/io/hfile/HFileScanner.seekTo:()Z
     462: pop
     463: aload         10
     465: invokeinterface #342,  1          // InterfaceMethod org/apache/hadoop/hbase/io/hfile/HFileScanner.getCell:()Lorg/apache/hadoop/hbase/Cell;
     470: astore        11
     472: aload         9
     474: ifnull        658
     477: aload_0
     478: getfield      #66                 // Field comparator:Lorg/apache/hadoop/hbase/CellComparator;
     481: aload         9
     483: aload         11
     485: invokeinterface #343,  3          // InterfaceMethod org/apache/hadoop/hbase/CellComparator.compareRows:(Lorg/apache/hadoop/hbase/Cell;Lorg/apache/hadoop/hbase/Cell;)I
     490: ifle          549
     493: new           #344                // class org/apache/hadoop/hbase/io/hfile/InvalidHFileException
     496: dup
     497: new           #115                // class java/lang/StringBuilder
     500: dup
     501: invokespecial #116                // Method java/lang/StringBuilder."<init>":()V
     504: ldc_w         #345                // String Previous row is greater than current row: path=
     507: invokevirtual #118                // Method java/lang/StringBuilder.append:(Ljava/lang/String;)Ljava/lang/StringBuilder;
     510: aload_1
     511: invokevirtual #265                // Method java/lang/StringBuilder.append:(Ljava/lang/Object;)Ljava/lang/StringBuilder;
     514: ldc_w         #346                // String  previous=
     517: invokevirtual #118                // Method java/lang/StringBuilder.append:(Ljava/lang/String;)Ljava/lang/StringBuilder;
     520: aload         9
     522: invokestatic  #347                // Method org/apache/hadoop/hbase/CellUtil.getCellKeyAsString:(Lorg/apache/hadoop/hbase/Cell;)Ljava/lang/String;
     525: invokevirtual #118                // Method java/lang/StringBuilder.append:(Ljava/lang/String;)Ljava/lang/StringBuilder;
     528: ldc_w         #348                // String  current=
     531: invokevirtual #118                // Method java/lang/StringBuilder.append:(Ljava/lang/String;)Ljava/lang/StringBuilder;
     534: aload         11
     536: invokestatic  #347                // Method org/apache/hadoop/hbase/CellUtil.getCellKeyAsString:(Lorg/apache/hadoop/hbase/Cell;)Ljava/lang/String;
     539: invokevirtual #118                // Method java/lang/StringBuilder.append:(Ljava/lang/String;)Ljava/lang/StringBuilder;
     542: invokevirtual #120                // Method java/lang/StringBuilder.toString:()Ljava/lang/String;
     545: invokespecial #349                // Method org/apache/hadoop/hbase/io/hfile/InvalidHFileException."<init>":(Ljava/lang/String;)V
     548: athrow
     549: invokestatic  #350                // InterfaceMethod org/apache/hadoop/hbase/CellComparator.getInstance:()Lorg/apache/hadoop/hbase/CellComparator;
     552: aload         9
     554: aload         11
     556: invokeinterface #351,  3          // InterfaceMethod org/apache/hadoop/hbase/CellComparator.compareFamilies:(Lorg/apache/hadoop/hbase/Cell;Lorg/apache/hadoop/hbase/Cell;)I
     561: ifeq          658
     564: new           #344                // class org/apache/hadoop/hbase/io/hfile/InvalidHFileException
     567: dup
     568: new           #115                // class java/lang/StringBuilder
     571: dup
     572: invokespecial #116                // Method java/lang/StringBuilder."<init>":()V
     575: ldc_w         #352                // String Previous key had different family compared to current key: path=
     578: invokevirtual #118                // Method java/lang/StringBuilder.append:(Ljava/lang/String;)Ljava/lang/StringBuilder;
     581: aload_1
     582: invokevirtual #265                // Method java/lang/StringBuilder.append:(Ljava/lang/Object;)Ljava/lang/StringBuilder;
     585: ldc_w         #346                // String  previous=
     588: invokevirtual #118                // Method java/lang/StringBuilder.append:(Ljava/lang/String;)Ljava/lang/StringBuilder;
     591: aload         9
     593: invokeinterface #353,  1          // InterfaceMethod org/apache/hadoop/hbase/Cell.getFamilyArray:()[B
     598: aload         9
     600: invokeinterface #354,  1          // InterfaceMethod org/apache/hadoop/hbase/Cell.getFamilyOffset:()I
     605: aload         9
     607: invokeinterface #355,  1          // InterfaceMethod org/apache/hadoop/hbase/Cell.getFamilyLength:()B
     612: invokestatic  #356                // Method org/apache/hadoop/hbase/util/Bytes.toStringBinary:([BII)Ljava/lang/String;
     615: invokevirtual #118                // Method java/lang/StringBuilder.append:(Ljava/lang/String;)Ljava/lang/StringBuilder;
     618: ldc_w         #348                // String  current=
     621: invokevirtual #118                // Method java/lang/StringBuilder.append:(Ljava/lang/String;)Ljava/lang/StringBuilder;
     624: aload         11
     626: invokeinterface #353,  1          // InterfaceMethod org/apache/hadoop/hbase/Cell.getFamilyArray:()[B
     631: aload         11
     633: invokeinterface #354,  1          // InterfaceMethod org/apache/hadoop/hbase/Cell.getFamilyOffset:()I
     638: aload         11
     640: invokeinterface #355,  1          // InterfaceMethod org/apache/hadoop/hbase/Cell.getFamilyLength:()B
     645: invokestatic  #356                // Method org/apache/hadoop/hbase/util/Bytes.toStringBinary:([BII)Ljava/lang/String;
     648: invokevirtual #118                // Method java/lang/StringBuilder.append:(Ljava/lang/String;)Ljava/lang/StringBuilder;
     651: invokevirtual #120                // Method java/lang/StringBuilder.toString:()Ljava/lang/String;
     654: invokespecial #349                // Method org/apache/hadoop/hbase/io/hfile/InvalidHFileException."<init>":(Ljava/lang/String;)V
     657: athrow
     658: aload         11
     660: astore        9
     662: aload         10
     664: invokeinterface #357,  1          // InterfaceMethod org/apache/hadoop/hbase/io/hfile/HFileScanner.next:()Z
     669: ifne          463
     672: getstatic     #9                  // Field LOG:Lorg/slf4j/Logger;
     675: new           #115                // class java/lang/StringBuilder
     678: dup
     679: invokespecial #116                // Method java/lang/StringBuilder."<init>":()V
     682: ldc_w         #358                // String Full verification complete for bulk load hfile:
     685: invokevirtual #118                // Method java/lang/StringBuilder.append:(Ljava/lang/String;)Ljava/lang/StringBuilder;
     688: aload_1
     689: invokevirtual #325                // Method org/apache/hadoop/fs/Path.toString:()Ljava/lang/String;
     692: invokevirtual #118                // Method java/lang/StringBuilder.append:(Ljava/lang/String;)Ljava/lang/StringBuilder;
     695: ldc_w         #359                // String  took
     698: invokevirtual #118                // Method java/lang/StringBuilder.append:(Ljava/lang/String;)Ljava/lang/StringBuilder;
     701: invokestatic  #337                // Method org/apache/hadoop/hbase/util/EnvironmentEdgeManager.currentTime:()J
     704: lload         7
     706: lsub
     707: invokevirtual #334                // Method java/lang/StringBuilder.append:(J)Ljava/lang/StringBuilder;
     710: ldc_w         #360                // String  ms
     713: invokevirtual #118                // Method java/lang/StringBuilder.append:(Ljava/lang/String;)Ljava/lang/StringBuilder;
     716: invokevirtual #120                // Method java/lang/StringBuilder.toString:()Ljava/lang/String;
     719: invokeinterface #267,  2          // InterfaceMethod org/slf4j/Logger.info:(Ljava/lang/String;)V
     724: aload_2
     725: ifnull        752
     728: aload_2
     729: invokeinterface #361,  1          // InterfaceMethod org/apache/hadoop/hbase/io/hfile/HFile$Reader.close:()V
     734: goto          752
     737: astore        12
     739: aload_2
     740: ifnull        749
     743: aload_2
     744: invokeinterface #361,  1          // InterfaceMethod org/apache/hadoop/hbase/io/hfile/HFile$Reader.close:()V
     749: aload         12
     751: athrow
     752: return
    Exception table:
       from    to  target type
           2   724   737   any
         737   739   737   any

  public org.apache.hadoop.hbase.util.Pair<org.apache.hadoop.fs.Path, org.apache.hadoop.fs.Path> preBulkLoadHFile(java.lang.String, long) throws java.io.IOException;
    Code:
       0: new           #186                // class org/apache/hadoop/fs/Path
       3: dup
       4: aload_1
       5: invokespecial #362                // Method org/apache/hadoop/fs/Path."<init>":(Ljava/lang/String;)V
       8: astore        4
      10: aload_0
      11: getfield      #4                  // Field fs:Lorg/apache/hadoop/hbase/regionserver/HRegionFileSystem;
      14: aload_0
      15: invokevirtual #127                // Method getColumnFamilyName:()Ljava/lang/String;
      18: aload         4
      20: lload_2
      21: invokevirtual #363                // Method org/apache/hadoop/hbase/regionserver/HRegionFileSystem.bulkLoadStoreFile:(Ljava/lang/String;Lorg/apache/hadoop/fs/Path;J)Lorg/apache/hadoop/hbase/util/Pair;
      24: areturn

  public org.apache.hadoop.fs.Path bulkLoadHFile(byte[], java.lang.String, org.apache.hadoop.fs.Path) throws java.io.IOException;
    Code:
       0: new           #186                // class org/apache/hadoop/fs/Path
       3: dup
       4: aload_2
       5: invokespecial #362                // Method org/apache/hadoop/fs/Path."<init>":(Ljava/lang/String;)V
       8: astore        4
      10: aload_0
      11: getfield      #4                  // Field fs:Lorg/apache/hadoop/hbase/regionserver/HRegionFileSystem;
      14: aload         4
      16: aload_3
      17: invokevirtual #364                // Method org/apache/hadoop/hbase/regionserver/HRegionFileSystem.commitStoreFile:(Lorg/apache/hadoop/fs/Path;Lorg/apache/hadoop/fs/Path;)Lorg/apache/hadoop/fs/Path;
      20: pop
      21: aload_0
      22: invokevirtual #365                // Method getCoprocessorHost:()Lorg/apache/hadoop/hbase/regionserver/RegionCoprocessorHost;
      25: ifnull        65
      28: aload_0
      29: invokevirtual #365                // Method getCoprocessorHost:()Lorg/apache/hadoop/hbase/regionserver/RegionCoprocessorHost;
      32: aload_1
      33: aload         4
      35: aload_3
      36: invokevirtual #366                // Method org/apache/hadoop/hbase/regionserver/RegionCoprocessorHost.postCommitStoreFile:([BLorg/apache/hadoop/fs/Path;Lorg/apache/hadoop/fs/Path;)V
      39: goto          65
      42: astore        5
      44: aload_0
      45: invokevirtual #365                // Method getCoprocessorHost:()Lorg/apache/hadoop/hbase/regionserver/RegionCoprocessorHost;
      48: ifnull        62
      51: aload_0
      52: invokevirtual #365                // Method getCoprocessorHost:()Lorg/apache/hadoop/hbase/regionserver/RegionCoprocessorHost;
      55: aload_1
      56: aload         4
      58: aload_3
      59: invokevirtual #366                // Method org/apache/hadoop/hbase/regionserver/RegionCoprocessorHost.postCommitStoreFile:([BLorg/apache/hadoop/fs/Path;Lorg/apache/hadoop/fs/Path;)V
      62: aload         5
      64: athrow
      65: getstatic     #9                  // Field LOG:Lorg/slf4j/Logger;
      68: new           #115                // class java/lang/StringBuilder
      71: dup
      72: invokespecial #116                // Method java/lang/StringBuilder."<init>":()V
      75: ldc_w         #367                // String Loaded HFile
      78: invokevirtual #118                // Method java/lang/StringBuilder.append:(Ljava/lang/String;)Ljava/lang/StringBuilder;
      81: aload         4
      83: invokevirtual #265                // Method java/lang/StringBuilder.append:(Ljava/lang/Object;)Ljava/lang/StringBuilder;
      86: ldc_w         #368                // String  into store '
      89: invokevirtual #118                // Method java/lang/StringBuilder.append:(Ljava/lang/String;)Ljava/lang/StringBuilder;
      92: aload_0
      93: invokevirtual #127                // Method getColumnFamilyName:()Ljava/lang/String;
      96: invokevirtual #118                // Method java/lang/StringBuilder.append:(Ljava/lang/String;)Ljava/lang/StringBuilder;
      99: ldc_w         #369                // String ' as
     102: invokevirtual #118                // Method java/lang/StringBuilder.append:(Ljava/lang/String;)Ljava/lang/StringBuilder;
     105: aload_3
     106: invokevirtual #265                // Method java/lang/StringBuilder.append:(Ljava/lang/Object;)Ljava/lang/StringBuilder;
     109: ldc_w         #370                // String  - updating store file list.
     112: invokevirtual #118                // Method java/lang/StringBuilder.append:(Ljava/lang/String;)Ljava/lang/StringBuilder;
     115: invokevirtual #120                // Method java/lang/StringBuilder.toString:()Ljava/lang/String;
     118: invokeinterface #267,  2          // InterfaceMethod org/slf4j/Logger.info:(Ljava/lang/String;)V
     123: aload_0
     124: aload_3
     125: invokevirtual #371                // Method createStoreFileAndReader:(Lorg/apache/hadoop/fs/Path;)Lorg/apache/hadoop/hbase/regionserver/HStoreFile;
     128: astore        5
     130: aload_0
     131: aload         5
     133: invokespecial #372                // Method bulkLoadHFile:(Lorg/apache/hadoop/hbase/regionserver/HStoreFile;)V
     136: getstatic     #9                  // Field LOG:Lorg/slf4j/Logger;
     139: ldc_w         #373                // String Successfully loaded store file {} into store {} (new location: {})
     142: iconst_3
     143: anewarray     #126                // class java/lang/Object
     146: dup
     147: iconst_0
     148: aload         4
     150: aastore
     151: dup
     152: iconst_1
     153: aload_0
     154: aastore
     155: dup
     156: iconst_2
     157: aload_3
     158: aastore
     159: invokeinterface #132,  3          // InterfaceMethod org/slf4j/Logger.info:(Ljava/lang/String;[Ljava/lang/Object;)V
     164: aload_3
     165: areturn
    Exception table:
       from    to  target type
          10    21    42   any
          42    44    42   any

  public void bulkLoadHFile(org.apache.hadoop.hbase.regionserver.StoreFileInfo) throws java.io.IOException;
    Code:
       0: aload_0
       1: aload_1
       2: invokespecial #3                  // Method createStoreFileAndReader:(Lorg/apache/hadoop/hbase/regionserver/StoreFileInfo;)Lorg/apache/hadoop/hbase/regionserver/HStoreFile;
       5: astore_2
       6: aload_0
       7: aload_2
       8: invokespecial #372                // Method bulkLoadHFile:(Lorg/apache/hadoop/hbase/regionserver/HStoreFile;)V
      11: return

  public org.apache.hbase.thirdparty.com.google.common.collect.ImmutableCollection<org.apache.hadoop.hbase.regionserver.HStoreFile> close() throws java.io.IOException;
    Code:
       0: aload_0
       1: getfield      #21                 // Field archiveLock:Ljava/util/concurrent/locks/ReentrantLock;
       4: invokevirtual #387                // Method java/util/concurrent/locks/ReentrantLock.lock:()V
       7: aload_0
       8: getfield      #18                 // Field lock:Ljava/util/concurrent/locks/ReentrantReadWriteLock;
      11: invokevirtual #376                // Method java/util/concurrent/locks/ReentrantReadWriteLock.writeLock:()Ljava/util/concurrent/locks/ReentrantReadWriteLock$WriteLock;
      14: invokevirtual #377                // Method java/util/concurrent/locks/ReentrantReadWriteLock$WriteLock.lock:()V
      17: aload_0
      18: getfield      #97                 // Field storeEngine:Lorg/apache/hadoop/hbase/regionserver/StoreEngine;
      21: invokevirtual #103                // Method org/apache/hadoop/hbase/regionserver/StoreEngine.getStoreFileManager:()Lorg/apache/hadoop/hbase/regionserver/StoreFileManager;
      24: invokeinterface #388,  1          // InterfaceMethod org/apache/hadoop/hbase/regionserver/StoreFileManager.clearFiles:()Lorg/apache/hbase/thirdparty/com/google/common/collect/ImmutableCollection;
      29: astore_1
      30: aload_0
      31: getfield      #97                 // Field storeEngine:Lorg/apache/hadoop/hbase/regionserver/StoreEngine;
      34: invokevirtual #103                // Method org/apache/hadoop/hbase/regionserver/StoreEngine.getStoreFileManager:()Lorg/apache/hadoop/hbase/regionserver/StoreFileManager;
      37: invokeinterface #389,  1          // InterfaceMethod org/apache/hadoop/hbase/regionserver/StoreFileManager.clearCompactedFiles:()Ljava/util/Collection;
      42: astore_2
      43: aload_2
      44: invokestatic  #390                // Method org/apache/hbase/thirdparty/org/apache/commons/collections4/CollectionUtils.isNotEmpty:(Ljava/util/Collection;)Z
      47: ifeq          55
      50: aload_0
      51: aload_2
      52: invokespecial #391                // Method removeCompactedfiles:(Ljava/util/Collection;)V
      55: aload_1
      56: invokevirtual #392                // Method org/apache/hbase/thirdparty/com/google/common/collect/ImmutableCollection.isEmpty:()Z
      59: ifne          287
      62: aload_0
      63: getfield      #40                 // Field region:Lorg/apache/hadoop/hbase/regionserver/HRegion;
      66: new           #115                // class java/lang/StringBuilder
      69: dup
      70: invokespecial #116                // Method java/lang/StringBuilder."<init>":()V
      73: ldc_w         #393                // String StoreFileCloserThread-
      76: invokevirtual #118                // Method java/lang/StringBuilder.append:(Ljava/lang/String;)Ljava/lang/StringBuilder;
      79: aload_0
      80: getfield      #40                 // Field region:Lorg/apache/hadoop/hbase/regionserver/HRegion;
      83: invokevirtual #195                // Method org/apache/hadoop/hbase/regionserver/HRegion.getRegionInfo:()Lorg/apache/hadoop/hbase/client/RegionInfo;
      86: invokeinterface #184,  1          // InterfaceMethod org/apache/hadoop/hbase/client/RegionInfo.getEncodedName:()Ljava/lang/String;
      91: invokevirtual #118                // Method java/lang/StringBuilder.append:(Ljava/lang/String;)Ljava/lang/StringBuilder;
      94: ldc           #196                // String -
      96: invokevirtual #118                // Method java/lang/StringBuilder.append:(Ljava/lang/String;)Ljava/lang/StringBuilder;
      99: aload_0
     100: invokevirtual #127                // Method getColumnFamilyName:()Ljava/lang/String;
     103: invokevirtual #118                // Method java/lang/StringBuilder.append:(Ljava/lang/String;)Ljava/lang/StringBuilder;
     106: invokevirtual #120                // Method java/lang/StringBuilder.toString:()Ljava/lang/String;
     109: invokevirtual #197                // Method org/apache/hadoop/hbase/regionserver/HRegion.getStoreFileOpenAndCloseThreadPool:(Ljava/lang/String;)Ljava/util/concurrent/ThreadPoolExecutor;
     112: astore_3
     113: new           #198                // class java/util/concurrent/ExecutorCompletionService
     116: dup
     117: aload_3
     118: invokespecial #199                // Method java/util/concurrent/ExecutorCompletionService."<init>":(Ljava/util/concurrent/Executor;)V
     121: astore        4
     123: aload_1
     124: invokevirtual #394                // Method org/apache/hbase/thirdparty/com/google/common/collect/ImmutableCollection.iterator:()Lorg/apache/hbase/thirdparty/com/google/common/collect/UnmodifiableIterator;
     127: astore        5
     129: aload         5
     131: invokeinterface #201,  1          // InterfaceMethod java/util/Iterator.hasNext:()Z
     136: ifeq          172
     139: aload         5
     141: invokeinterface #202,  1          // InterfaceMethod java/util/Iterator.next:()Ljava/lang/Object;
     146: checkcast     #213                // class org/apache/hadoop/hbase/regionserver/HStoreFile
     149: astore        6
     151: aload         4
     153: new           #395                // class org/apache/hadoop/hbase/regionserver/HStore$1
     156: dup
     157: aload_0
     158: aload         6
     160: invokespecial #396                // Method org/apache/hadoop/hbase/regionserver/HStore$1."<init>":(Lorg/apache/hadoop/hbase/regionserver/HStore;Lorg/apache/hadoop/hbase/regionserver/HStoreFile;)V
     163: invokeinterface #205,  2          // InterfaceMethod java/util/concurrent/CompletionService.submit:(Ljava/util/concurrent/Callable;)Ljava/util/concurrent/Future;
     168: pop
     169: goto          129
     172: aconst_null
     173: astore        5
     175: iconst_0
     176: istore        6
     178: iload         6
     180: aload_1
     181: invokevirtual #397                // Method org/apache/hbase/thirdparty/com/google/common/collect/ImmutableCollection.size:()I
     184: if_icmpge     261
     187: aload         4
     189: invokeinterface #211,  1          // InterfaceMethod java/util/concurrent/CompletionService.take:()Ljava/util/concurrent/Future;
     194: astore        7
     196: aload         7
     198: invokeinterface #212,  1          // InterfaceMethod java/util/concurrent/Future.get:()Ljava/lang/Object;
     203: pop
     204: goto          255
     207: astore        7
     209: aload         5
     211: ifnonnull     231
     214: new           #220                // class java/io/InterruptedIOException
     217: dup
     218: invokespecial #398                // Method java/io/InterruptedIOException."<init>":()V
     221: astore        5
     223: aload         5
     225: aload         7
     227: invokevirtual #399                // Method java/io/IOException.initCause:(Ljava/lang/Throwable;)Ljava/lang/Throwable;
     230: pop
     231: goto          255
     234: astore        7
     236: aload         5
     238: ifnonnull     255
     241: new           #224                // class java/io/IOException
     244: dup
     245: aload         7
     247: invokevirtual #225                // Method java/util/concurrent/ExecutionException.getCause:()Ljava/lang/Throwable;
     250: invokespecial #226                // Method java/io/IOException."<init>":(Ljava/lang/Throwable;)V
     253: astore        5
     255: iinc          6, 1
     258: goto          178
     261: aload_3
     262: invokevirtual #227                // Method java/util/concurrent/ThreadPoolExecutor.shutdownNow:()Ljava/util/List;
     265: pop
     266: goto          279
     269: astore        8
     271: aload_3
     272: invokevirtual #227                // Method java/util/concurrent/ThreadPoolExecutor.shutdownNow:()Ljava/util/List;
     275: pop
     276: aload         8
     278: athrow
     279: aload         5
     281: ifnull        287
     284: aload         5
     286: athrow
     287: getstatic     #9                  // Field LOG:Lorg/slf4j/Logger;
     290: ldc_w         #400                // String Closed {}
     293: aload_0
     294: invokeinterface #401,  3          // InterfaceMethod org/slf4j/Logger.trace:(Ljava/lang/String;Ljava/lang/Object;)V
     299: aload_1
     300: astore_3
     301: aload_0
     302: getfield      #18                 // Field lock:Ljava/util/concurrent/locks/ReentrantReadWriteLock;
     305: invokevirtual #376                // Method java/util/concurrent/locks/ReentrantReadWriteLock.writeLock:()Ljava/util/concurrent/locks/ReentrantReadWriteLock$WriteLock;
     308: invokevirtual #380                // Method java/util/concurrent/locks/ReentrantReadWriteLock$WriteLock.unlock:()V
     311: aload_0
     312: getfield      #21                 // Field archiveLock:Ljava/util/concurrent/locks/ReentrantLock;
     315: invokevirtual #402                // Method java/util/concurrent/locks/ReentrantLock.unlock:()V
     318: aload_3
     319: areturn
     320: astore        9
     322: aload_0
     323: getfield      #18                 // Field lock:Ljava/util/concurrent/locks/ReentrantReadWriteLock;
     326: invokevirtual #376                // Method java/util/concurrent/locks/ReentrantReadWriteLock.writeLock:()Ljava/util/concurrent/locks/ReentrantReadWriteLock$WriteLock;
     329: invokevirtual #380                // Method java/util/concurrent/locks/ReentrantReadWriteLock$WriteLock.unlock:()V
     332: aload_0
     333: getfield      #21                 // Field archiveLock:Ljava/util/concurrent/locks/ReentrantLock;
     336: invokevirtual #402                // Method java/util/concurrent/locks/ReentrantLock.unlock:()V
     339: aload         9
     341: athrow
    Exception table:
       from    to  target type
         187   204   207   Class java/lang/InterruptedException
         187   204   234   Class java/util/concurrent/ExecutionException
         175   261   269   any
         269   271   269   any
          17   301   320   any
         320   322   320   any

  void snapshot();
    Code:
       0: aload_0
       1: getfield      #18                 // Field lock:Ljava/util/concurrent/locks/ReentrantReadWriteLock;
       4: invokevirtual #376                // Method java/util/concurrent/locks/ReentrantReadWriteLock.writeLock:()Ljava/util/concurrent/locks/ReentrantReadWriteLock$WriteLock;
       7: invokevirtual #377                // Method java/util/concurrent/locks/ReentrantReadWriteLock$WriteLock.lock:()V
      10: aload_0
      11: getfield      #78                 // Field memstore:Lorg/apache/hadoop/hbase/regionserver/MemStore;
      14: invokeinterface #403,  1          // InterfaceMethod org/apache/hadoop/hbase/regionserver/MemStore.snapshot:()Lorg/apache/hadoop/hbase/regionserver/MemStoreSnapshot;
      19: pop
      20: aload_0
      21: getfield      #18                 // Field lock:Ljava/util/concurrent/locks/ReentrantReadWriteLock;
      24: invokevirtual #376                // Method java/util/concurrent/locks/ReentrantReadWriteLock.writeLock:()Ljava/util/concurrent/locks/ReentrantReadWriteLock$WriteLock;
      27: invokevirtual #380                // Method java/util/concurrent/locks/ReentrantReadWriteLock$WriteLock.unlock:()V
      30: goto          46
      33: astore_1
      34: aload_0
      35: getfield      #18                 // Field lock:Ljava/util/concurrent/locks/ReentrantReadWriteLock;
      38: invokevirtual #376                // Method java/util/concurrent/locks/ReentrantReadWriteLock.writeLock:()Ljava/util/concurrent/locks/ReentrantReadWriteLock$WriteLock;
      41: invokevirtual #380                // Method java/util/concurrent/locks/ReentrantReadWriteLock$WriteLock.unlock:()V
      44: aload_1
      45: athrow
      46: return
    Exception table:
       from    to  target type
          10    20    33   any

  protected java.util.List<org.apache.hadoop.fs.Path> flushCache(long, org.apache.hadoop.hbase.regionserver.MemStoreSnapshot, org.apache.hadoop.hbase.monitoring.MonitoredTask, org.apache.hadoop.hbase.regionserver.throttle.ThroughputController, org.apache.hadoop.hbase.regionserver.FlushLifeCycleTracker) throws java.io.IOException;
    Code:
       0: aload_0
       1: getfield      #97                 // Field storeEngine:Lorg/apache/hadoop/hbase/regionserver/StoreEngine;
       4: invokevirtual #404                // Method org/apache/hadoop/hbase/regionserver/StoreEngine.getStoreFlusher:()Lorg/apache/hadoop/hbase/regionserver/StoreFlusher;
       7: astore        7
       9: aconst_null
      10: astore        8
      12: iconst_0
      13: istore        9
      15: iload         9
      17: aload_0
      18: getfield      #110                // Field flushRetriesNumber:I
      21: if_icmpge     235
      24: aload         7
      26: aload_3
      27: lload_1
      28: aload         4
      30: aload         5
      32: aload         6
      34: invokevirtual #405                // Method org/apache/hadoop/hbase/regionserver/StoreFlusher.flushSnapshot:(Lorg/apache/hadoop/hbase/regionserver/MemStoreSnapshot;JLorg/apache/hadoop/hbase/monitoring/MonitoredTask;Lorg/apache/hadoop/hbase/regionserver/throttle/ThroughputController;Lorg/apache/hadoop/hbase/regionserver/FlushLifeCycleTracker;)Ljava/util/List;
      37: astore        10
      39: aconst_null
      40: astore        11
      42: aload         10
      44: invokeinterface #406,  1          // InterfaceMethod java/util/List.iterator:()Ljava/util/Iterator;
      49: astore        12
      51: aload         12
      53: invokeinterface #201,  1          // InterfaceMethod java/util/Iterator.hasNext:()Z
      58: ifeq          86
      61: aload         12
      63: invokeinterface #202,  1          // InterfaceMethod java/util/Iterator.next:()Ljava/lang/Object;
      68: checkcast     #186                // class org/apache/hadoop/fs/Path
      71: astore        13
      73: aload         13
      75: astore        11
      77: aload_0
      78: aload         13
      80: invokespecial #407                // Method validateStoreFile:(Lorg/apache/hadoop/fs/Path;)V
      83: goto          51
      86: aload         10
      88: areturn
      89: astore        12
      91: getstatic     #9                  // Field LOG:Lorg/slf4j/Logger;
      94: ldc_w         #409                // String Failed validating store file {}, retrying num={}
      97: iconst_3
      98: anewarray     #126                // class java/lang/Object
     101: dup
     102: iconst_0
     103: aload         11
     105: aastore
     106: dup
     107: iconst_1
     108: iload         9
     110: invokestatic  #91                 // Method java/lang/Integer.valueOf:(I)Ljava/lang/Integer;
     113: aastore
     114: dup
     115: iconst_2
     116: aload         12
     118: aastore
     119: invokeinterface #410,  3          // InterfaceMethod org/slf4j/Logger.warn:(Ljava/lang/String;[Ljava/lang/Object;)V
     124: aload         12
     126: instanceof    #224                // class java/io/IOException
     129: ifeq          142
     132: aload         12
     134: checkcast     #224                // class java/io/IOException
     137: astore        8
     139: goto          153
     142: new           #224                // class java/io/IOException
     145: dup
     146: aload         12
     148: invokespecial #226                // Method java/io/IOException."<init>":(Ljava/lang/Throwable;)V
     151: astore        8
     153: goto          180
     156: astore        10
     158: getstatic     #9                  // Field LOG:Lorg/slf4j/Logger;
     161: ldc_w         #411                // String Failed flushing store file, retrying num={}
     164: iload         9
     166: invokestatic  #91                 // Method java/lang/Integer.valueOf:(I)Ljava/lang/Integer;
     169: aload         10
     171: invokeinterface #412,  4          // InterfaceMethod org/slf4j/Logger.warn:(Ljava/lang/String;Ljava/lang/Object;Ljava/lang/Object;)V
     176: aload         10
     178: astore        8
     180: aload         8
     182: ifnull        229
     185: iload         9
     187: aload_0
     188: getfield      #110                // Field flushRetriesNumber:I
     191: iconst_1
     192: isub
     193: if_icmpge     229
     196: aload_0
     197: getfield      #113                // Field pauseTime:I
     200: i2l
     201: invokestatic  #413                // Method java/lang/Thread.sleep:(J)V
     204: goto          229
     207: astore        10
     209: new           #220                // class java/io/InterruptedIOException
     212: dup
     213: invokespecial #398                // Method java/io/InterruptedIOException."<init>":()V
     216: astore        11
     218: aload         11
     220: aload         10
     222: invokevirtual #399                // Method java/io/IOException.initCause:(Ljava/lang/Throwable;)Ljava/lang/Throwable;
     225: pop
     226: aload         11
     228: athrow
     229: iinc          9, 1
     232: goto          15
     235: aload         8
     237: athrow
    Exception table:
       from    to  target type
          42    88    89   Class java/lang/Exception
          24    88   156   Class java/io/IOException
          89   153   156   Class java/io/IOException
         196   204   207   Class java/lang/InterruptedException

  public org.apache.hadoop.hbase.regionserver.StoreFileWriter createWriterInTmp(long, org.apache.hadoop.hbase.io.compress.Compression$Algorithm, boolean, boolean, boolean, boolean) throws java.io.IOException;
    Code:
       0: iload         4
       2: ifeq          27
       5: new           #152                // class org/apache/hadoop/hbase/io/hfile/CacheConfig
       8: dup
       9: aload_0
      10: getfield      #155                // Field cacheConf:Lorg/apache/hadoop/hbase/io/hfile/CacheConfig;
      13: invokespecial #426                // Method org/apache/hadoop/hbase/io/hfile/CacheConfig."<init>":(Lorg/apache/hadoop/hbase/io/hfile/CacheConfig;)V
      16: astore        8
      18: aload         8
      20: iconst_0
      21: invokevirtual #427                // Method org/apache/hadoop/hbase/io/hfile/CacheConfig.setCacheDataOnWrite:(Z)V
      24: goto          33
      27: aload_0
      28: getfield      #155                // Field cacheConf:Lorg/apache/hadoop/hbase/io/hfile/CacheConfig;
      31: astore        8
      33: aconst_null
      34: astore        9
      36: aload_0
      37: getfield      #40                 // Field region:Lorg/apache/hadoop/hbase/regionserver/HRegion;
      40: invokevirtual #428                // Method org/apache/hadoop/hbase/regionserver/HRegion.getRegionServerServices:()Lorg/apache/hadoop/hbase/regionserver/RegionServerServices;
      43: ifnull        72
      46: aload_0
      47: getfield      #40                 // Field region:Lorg/apache/hadoop/hbase/regionserver/HRegion;
      50: invokevirtual #428                // Method org/apache/hadoop/hbase/regionserver/HRegion.getRegionServerServices:()Lorg/apache/hadoop/hbase/regionserver/RegionServerServices;
      53: aload_0
      54: getfield      #40                 // Field region:Lorg/apache/hadoop/hbase/regionserver/HRegion;
      57: invokevirtual #195                // Method org/apache/hadoop/hbase/regionserver/HRegion.getRegionInfo:()Lorg/apache/hadoop/hbase/client/RegionInfo;
      60: invokeinterface #184,  1          // InterfaceMethod org/apache/hadoop/hbase/client/RegionInfo.getEncodedName:()Ljava/lang/String;
      65: invokeinterface #429,  2          // InterfaceMethod org/apache/hadoop/hbase/regionserver/RegionServerServices.getFavoredNodesForRegion:(Ljava/lang/String;)[Ljava/net/InetSocketAddress;
      70: astore        9
      72: aload_0
      73: aload_3
      74: iload         5
      76: iload         6
      78: aload_0
      79: getfield      #32                 // Field cryptoContext:Lorg/apache/hadoop/hbase/io/crypto/Encryption$Context;
      82: invokespecial #430                // Method createFileContext:(Lorg/apache/hadoop/hbase/io/compress/Compression$Algorithm;ZZLorg/apache/hadoop/hbase/io/crypto/Encryption$Context;)Lorg/apache/hadoop/hbase/io/hfile/HFileContext;
      85: astore        10
      87: new           #186                // class org/apache/hadoop/fs/Path
      90: dup
      91: aload_0
      92: getfield      #4                  // Field fs:Lorg/apache/hadoop/hbase/regionserver/HRegionFileSystem;
      95: invokevirtual #431                // Method org/apache/hadoop/hbase/regionserver/HRegionFileSystem.getTempDir:()Lorg/apache/hadoop/fs/Path;
      98: aload_0
      99: getfield      #41                 // Field family:Lorg/apache/hadoop/hbase/client/ColumnFamilyDescriptor;
     102: invokeinterface #38,  1           // InterfaceMethod org/apache/hadoop/hbase/client/ColumnFamilyDescriptor.getNameAsString:()Ljava/lang/String;
     107: invokespecial #432                // Method org/apache/hadoop/fs/Path."<init>":(Lorg/apache/hadoop/fs/Path;Ljava/lang/String;)V
     110: astore        11
     112: new           #433                // class org/apache/hadoop/hbase/regionserver/StoreFileWriter$Builder
     115: dup
     116: aload_0
     117: getfield      #51                 // Field conf:Lorg/apache/hadoop/conf/Configuration;
     120: aload         8
     122: aload_0
     123: invokevirtual #278                // Method getFileSystem:()Lorg/apache/hadoop/fs/FileSystem;
     126: invokespecial #434                // Method org/apache/hadoop/hbase/regionserver/StoreFileWriter$Builder."<init>":(Lorg/apache/hadoop/conf/Configuration;Lorg/apache/hadoop/hbase/io/hfile/CacheConfig;Lorg/apache/hadoop/fs/FileSystem;)V
     129: aload         11
     131: invokevirtual #435                // Method org/apache/hadoop/hbase/regionserver/StoreFileWriter$Builder.withOutputDir:(Lorg/apache/hadoop/fs/Path;)Lorg/apache/hadoop/hbase/regionserver/StoreFileWriter$Builder;
     134: aload_0
     135: getfield      #66                 // Field comparator:Lorg/apache/hadoop/hbase/CellComparator;
     138: invokevirtual #436                // Method org/apache/hadoop/hbase/regionserver/StoreFileWriter$Builder.withComparator:(Lorg/apache/hadoop/hbase/CellComparator;)Lorg/apache/hadoop/hbase/regionserver/StoreFileWriter$Builder;
     141: aload_0
     142: getfield      #41                 // Field family:Lorg/apache/hadoop/hbase/client/ColumnFamilyDescriptor;
     145: invokeinterface #282,  1          // InterfaceMethod org/apache/hadoop/hbase/client/ColumnFamilyDescriptor.getBloomFilterType:()Lorg/apache/hadoop/hbase/regionserver/BloomType;
     150: invokevirtual #437                // Method org/apache/hadoop/hbase/regionserver/StoreFileWriter$Builder.withBloomType:(Lorg/apache/hadoop/hbase/regionserver/BloomType;)Lorg/apache/hadoop/hbase/regionserver/StoreFileWriter$Builder;
     153: lload_1
     154: invokevirtual #438                // Method org/apache/hadoop/hbase/regionserver/StoreFileWriter$Builder.withMaxKeyCount:(J)Lorg/apache/hadoop/hbase/regionserver/StoreFileWriter$Builder;
     157: aload         9
     159: invokevirtual #439                // Method org/apache/hadoop/hbase/regionserver/StoreFileWriter$Builder.withFavoredNodes:([Ljava/net/InetSocketAddress;)Lorg/apache/hadoop/hbase/regionserver/StoreFileWriter$Builder;
     162: aload         10
     164: invokevirtual #440                // Method org/apache/hadoop/hbase/regionserver/StoreFileWriter$Builder.withFileContext:(Lorg/apache/hadoop/hbase/io/hfile/HFileContext;)Lorg/apache/hadoop/hbase/regionserver/StoreFileWriter$Builder;
     167: iload         7
     169: invokevirtual #441                // Method org/apache/hadoop/hbase/regionserver/StoreFileWriter$Builder.withShouldDropCacheBehind:(Z)Lorg/apache/hadoop/hbase/regionserver/StoreFileWriter$Builder;
     172: aload_0
     173: invokedynamic #442,  0            // InvokeDynamic #2:get:(Lorg/apache/hadoop/hbase/regionserver/HStore;)Ljava/util/function/Supplier;
     178: invokevirtual #443                // Method org/apache/hadoop/hbase/regionserver/StoreFileWriter$Builder.withCompactedFilesSupplier:(Ljava/util/function/Supplier;)Lorg/apache/hadoop/hbase/regionserver/StoreFileWriter$Builder;
     181: astore        12
     183: aload         12
     185: invokevirtual #444                // Method org/apache/hadoop/hbase/regionserver/StoreFileWriter$Builder.build:()Lorg/apache/hadoop/hbase/regionserver/StoreFileWriter;
     188: areturn

  public java.util.List<org.apache.hadoop.hbase.regionserver.KeyValueScanner> getScanners(boolean, boolean, boolean, boolean, org.apache.hadoop.hbase.regionserver.querymatcher.ScanQueryMatcher, byte[], byte[], long) throws java.io.IOException;
    Code:
       0: aload_0
       1: iload_1
       2: iload_3
       3: iload         4
       5: aload         5
       7: aload         6
       9: iconst_1
      10: aload         7
      12: iconst_0
      13: lload         8
      15: invokevirtual #475                // Method getScanners:(ZZZLorg/apache/hadoop/hbase/regionserver/querymatcher/ScanQueryMatcher;[BZ[BZJ)Ljava/util/List;
      18: areturn

  public java.util.List<org.apache.hadoop.hbase.regionserver.KeyValueScanner> getScanners(boolean, boolean, boolean, org.apache.hadoop.hbase.regionserver.querymatcher.ScanQueryMatcher, byte[], boolean, byte[], boolean, long) throws java.io.IOException;
    Code:
       0: aload_0
       1: getfield      #18                 // Field lock:Ljava/util/concurrent/locks/ReentrantReadWriteLock;
       4: invokevirtual #287                // Method java/util/concurrent/locks/ReentrantReadWriteLock.readLock:()Ljava/util/concurrent/locks/ReentrantReadWriteLock$ReadLock;
       7: invokevirtual #288                // Method java/util/concurrent/locks/ReentrantReadWriteLock$ReadLock.lock:()V
      10: aload_0
      11: getfield      #97                 // Field storeEngine:Lorg/apache/hadoop/hbase/regionserver/StoreEngine;
      14: invokevirtual #103                // Method org/apache/hadoop/hbase/regionserver/StoreEngine.getStoreFileManager:()Lorg/apache/hadoop/hbase/regionserver/StoreFileManager;
      17: aload         5
      19: iload         6
      21: aload         7
      23: iload         8
      25: invokeinterface #476,  5          // InterfaceMethod org/apache/hadoop/hbase/regionserver/StoreFileManager.getFilesForScan:([BZ[BZ)Ljava/util/Collection;
      30: astore        11
      32: aload_0
      33: getfield      #78                 // Field memstore:Lorg/apache/hadoop/hbase/regionserver/MemStore;
      36: lload         9
      38: invokeinterface #473,  3          // InterfaceMethod org/apache/hadoop/hbase/regionserver/MemStore.getScanners:(J)Ljava/util/List;
      43: astore        12
      45: aload_0
      46: getfield      #18                 // Field lock:Ljava/util/concurrent/locks/ReentrantReadWriteLock;
      49: invokevirtual #287                // Method java/util/concurrent/locks/ReentrantReadWriteLock.readLock:()Ljava/util/concurrent/locks/ReentrantReadWriteLock$ReadLock;
      52: invokevirtual #292                // Method java/util/concurrent/locks/ReentrantReadWriteLock$ReadLock.unlock:()V
      55: goto          73
      58: astore        13
      60: aload_0
      61: getfield      #18                 // Field lock:Ljava/util/concurrent/locks/ReentrantReadWriteLock;
      64: invokevirtual #287                // Method java/util/concurrent/locks/ReentrantReadWriteLock.readLock:()Ljava/util/concurrent/locks/ReentrantReadWriteLock$ReadLock;
      67: invokevirtual #292                // Method java/util/concurrent/locks/ReentrantReadWriteLock$ReadLock.unlock:()V
      70: aload         13
      72: athrow
      73: aload         11
      75: iload_1
      76: iload_2
      77: iload_3
      78: iconst_0
      79: aload         4
      81: lload         9
      83: invokestatic  #477                // Method org/apache/hadoop/hbase/regionserver/StoreFileScanner.getScannersForStoreFiles:(Ljava/util/Collection;ZZZZLorg/apache/hadoop/hbase/regionserver/querymatcher/ScanQueryMatcher;J)Ljava/util/List;
      86: astore        13
      88: new           #208                // class java/util/ArrayList
      91: dup
      92: aload         13
      94: invokeinterface #469,  1          // InterfaceMethod java/util/List.size:()I
      99: iconst_1
     100: iadd
     101: invokespecial #210                // Method java/util/ArrayList."<init>":(I)V
     104: astore        14
     106: aload         14
     108: aload         13
     110: invokeinterface #478,  2          // InterfaceMethod java/util/List.addAll:(Ljava/util/Collection;)Z
     115: pop
     116: aload         14
     118: aload         12
     120: invokeinterface #478,  2          // InterfaceMethod java/util/List.addAll:(Ljava/util/Collection;)Z
     125: pop
     126: aload         14
     128: areturn
    Exception table:
       from    to  target type
          10    45    58   any
          58    60    58   any

  public java.util.List<org.apache.hadoop.hbase.regionserver.KeyValueScanner> getScanners(java.util.List<org.apache.hadoop.hbase.regionserver.HStoreFile>, boolean, boolean, boolean, boolean, org.apache.hadoop.hbase.regionserver.querymatcher.ScanQueryMatcher, byte[], byte[], long, boolean) throws java.io.IOException;
    Code:
       0: aload_0
       1: aload_1
       2: iload_2
       3: iload         4
       5: iload         5
       7: aload         6
       9: aload         7
      11: iconst_1
      12: aload         8
      14: iconst_0
      15: lload         9
      17: iload         11
      19: invokevirtual #479                // Method getScanners:(Ljava/util/List;ZZZLorg/apache/hadoop/hbase/regionserver/querymatcher/ScanQueryMatcher;[BZ[BZJZ)Ljava/util/List;
      22: areturn

  public java.util.List<org.apache.hadoop.hbase.regionserver.KeyValueScanner> getScanners(java.util.List<org.apache.hadoop.hbase.regionserver.HStoreFile>, boolean, boolean, boolean, org.apache.hadoop.hbase.regionserver.querymatcher.ScanQueryMatcher, byte[], boolean, byte[], boolean, long, boolean) throws java.io.IOException;
    Code:
       0: aconst_null
       1: astore        13
       3: iload         12
       5: ifeq          59
       8: aload_0
       9: getfield      #18                 // Field lock:Ljava/util/concurrent/locks/ReentrantReadWriteLock;
      12: invokevirtual #287                // Method java/util/concurrent/locks/ReentrantReadWriteLock.readLock:()Ljava/util/concurrent/locks/ReentrantReadWriteLock$ReadLock;
      15: invokevirtual #288                // Method java/util/concurrent/locks/ReentrantReadWriteLock$ReadLock.lock:()V
      18: aload_0
      19: getfield      #78                 // Field memstore:Lorg/apache/hadoop/hbase/regionserver/MemStore;
      22: lload         10
      24: invokeinterface #473,  3          // InterfaceMethod org/apache/hadoop/hbase/regionserver/MemStore.getScanners:(J)Ljava/util/List;
      29: astore        13
      31: aload_0
      32: getfield      #18                 // Field lock:Ljava/util/concurrent/locks/ReentrantReadWriteLock;
      35: invokevirtual #287                // Method java/util/concurrent/locks/ReentrantReadWriteLock.readLock:()Ljava/util/concurrent/locks/ReentrantReadWriteLock$ReadLock;
      38: invokevirtual #292                // Method java/util/concurrent/locks/ReentrantReadWriteLock$ReadLock.unlock:()V
      41: goto          59
      44: astore        14
      46: aload_0
      47: getfield      #18                 // Field lock:Ljava/util/concurrent/locks/ReentrantReadWriteLock;
      50: invokevirtual #287                // Method java/util/concurrent/locks/ReentrantReadWriteLock.readLock:()Ljava/util/concurrent/locks/ReentrantReadWriteLock$ReadLock;
      53: invokevirtual #292                // Method java/util/concurrent/locks/ReentrantReadWriteLock$ReadLock.unlock:()V
      56: aload         14
      58: athrow
      59: aload_1
      60: iload_2
      61: iload_3
      62: iload         4
      64: iconst_0
      65: aload         5
      67: lload         10
      69: invokestatic  #477                // Method org/apache/hadoop/hbase/regionserver/StoreFileScanner.getScannersForStoreFiles:(Ljava/util/Collection;ZZZZLorg/apache/hadoop/hbase/regionserver/querymatcher/ScanQueryMatcher;J)Ljava/util/List;
      72: astore        14
      74: new           #208                // class java/util/ArrayList
      77: dup
      78: aload         14
      80: invokeinterface #469,  1          // InterfaceMethod java/util/List.size:()I
      85: iconst_1
      86: iadd
      87: invokespecial #210                // Method java/util/ArrayList."<init>":(I)V
      90: astore        15
      92: aload         15
      94: aload         14
      96: invokeinterface #478,  2          // InterfaceMethod java/util/List.addAll:(Ljava/util/Collection;)Z
     101: pop
     102: aload         13
     104: ifnull        117
     107: aload         15
     109: aload         13
     111: invokeinterface #478,  2          // InterfaceMethod java/util/List.addAll:(Ljava/util/Collection;)Z
     116: pop
     117: aload         15
     119: areturn
    Exception table:
       from    to  target type
          18    31    44   any
          44    46    44   any

  public void addChangedReaderObserver(org.apache.hadoop.hbase.regionserver.ChangedReadersObserver);
    Code:
       0: aload_0
       1: getfield      #30                 // Field changedReaderObservers:Ljava/util/Set;
       4: aload_1
       5: invokeinterface #271,  2          // InterfaceMethod java/util/Set.add:(Ljava/lang/Object;)Z
      10: pop
      11: return

  public void deleteChangedReaderObserver(org.apache.hadoop.hbase.regionserver.ChangedReadersObserver);
    Code:
       0: aload_0
       1: getfield      #30                 // Field changedReaderObservers:Ljava/util/Set;
       4: aload_1
       5: invokeinterface #480,  2          // InterfaceMethod java/util/Set.remove:(Ljava/lang/Object;)Z
      10: pop
      11: return

  public java.util.List<org.apache.hadoop.hbase.regionserver.HStoreFile> compact(org.apache.hadoop.hbase.regionserver.compactions.CompactionContext, org.apache.hadoop.hbase.regionserver.throttle.ThroughputController, org.apache.hadoop.hbase.security.User) throws java.io.IOException;
    Code:
       0: getstatic     #481                // Field $assertionsDisabled:Z
       3: ifne          18
       6: aload_1
       7: ifnonnull     18
      10: new           #482                // class java/lang/AssertionError
      13: dup
      14: invokespecial #483                // Method java/lang/AssertionError."<init>":()V
      17: athrow
      18: aconst_null
      19: astore        4
      21: aload_1
      22: invokevirtual #484                // Method org/apache/hadoop/hbase/regionserver/compactions/CompactionContext.getRequest:()Lorg/apache/hadoop/hbase/regionserver/compactions/CompactionRequestImpl;
      25: astore        5
      27: invokestatic  #337                // Method org/apache/hadoop/hbase/util/EnvironmentEdgeManager.currentTime:()J
      30: lstore        6
      32: getstatic     #481                // Field $assertionsDisabled:Z
      35: ifne          53
      38: aload_1
      39: invokevirtual #485                // Method org/apache/hadoop/hbase/regionserver/compactions/CompactionContext.hasSelection:()Z
      42: ifne          53
      45: new           #482                // class java/lang/AssertionError
      48: dup
      49: invokespecial #483                // Method java/lang/AssertionError."<init>":()V
      52: athrow
      53: aload         5
      55: invokevirtual #486                // Method org/apache/hadoop/hbase/regionserver/compactions/CompactionRequestImpl.getFiles:()Ljava/util/Collection;
      58: astore        8
      60: getstatic     #481                // Field $assertionsDisabled:Z
      63: ifne          84
      66: aload         8
      68: invokeinterface #487,  1          // InterfaceMethod java/util/Collection.isEmpty:()Z
      73: ifeq          84
      76: new           #482                // class java/lang/AssertionError
      79: dup
      80: invokespecial #483                // Method java/lang/AssertionError."<init>":()V
      83: athrow
      84: aload_0
      85: getfield      #26                 // Field filesCompacting:Ljava/util/List;
      88: dup
      89: astore        9
      91: monitorenter
      92: aload_0
      93: getfield      #26                 // Field filesCompacting:Ljava/util/List;
      96: aload         8
      98: invokeinterface #488,  2          // InterfaceMethod java/util/List.containsAll:(Ljava/util/Collection;)Z
     103: invokestatic  #489                // Method org/apache/hbase/thirdparty/com/google/common/base/Preconditions.checkArgument:(Z)V
     106: aload         9
     108: monitorexit
     109: goto          120
     112: astore        10
     114: aload         9
     116: monitorexit
     117: aload         10
     119: athrow
     120: getstatic     #9                  // Field LOG:Lorg/slf4j/Logger;
     123: new           #115                // class java/lang/StringBuilder
     126: dup
     127: invokespecial #116                // Method java/lang/StringBuilder."<init>":()V
     130: ldc_w         #490                // String Starting compaction of
     133: invokevirtual #118                // Method java/lang/StringBuilder.append:(Ljava/lang/String;)Ljava/lang/StringBuilder;
     136: aload         8
     138: invokevirtual #265                // Method java/lang/StringBuilder.append:(Ljava/lang/Object;)Ljava/lang/StringBuilder;
     141: ldc_w         #491                // String  into tmpdir=
     144: invokevirtual #118                // Method java/lang/StringBuilder.append:(Ljava/lang/String;)Ljava/lang/StringBuilder;
     147: aload_0
     148: getfield      #4                  // Field fs:Lorg/apache/hadoop/hbase/regionserver/HRegionFileSystem;
     151: invokevirtual #431                // Method org/apache/hadoop/hbase/regionserver/HRegionFileSystem.getTempDir:()Lorg/apache/hadoop/fs/Path;
     154: invokevirtual #265                // Method java/lang/StringBuilder.append:(Ljava/lang/Object;)Ljava/lang/StringBuilder;
     157: ldc_w         #492                // String , totalSize=
     160: invokevirtual #118                // Method java/lang/StringBuilder.append:(Ljava/lang/String;)Ljava/lang/StringBuilder;
     163: aload         5
     165: invokevirtual #493                // Method org/apache/hadoop/hbase/regionserver/compactions/CompactionRequestImpl.getSize:()J
     168: ldc_w         #424                // String
     171: iconst_1
     172: invokestatic  #425                // Method org/apache/hadoop/util/StringUtils$TraditionalBinaryPrefix.long2String:(JLjava/lang/String;I)Ljava/lang/String;
     175: invokevirtual #118                // Method java/lang/StringBuilder.append:(Ljava/lang/String;)Ljava/lang/StringBuilder;
     178: invokevirtual #120                // Method java/lang/StringBuilder.toString:()Ljava/lang/String;
     181: invokeinterface #267,  2          // InterfaceMethod org/slf4j/Logger.info:(Ljava/lang/String;)V
     186: aload_0
     187: aload         5
     189: aload         8
     191: aload_3
     192: lload         6
     194: aload_1
     195: aload_2
     196: aload_3
     197: invokevirtual #494                // Method org/apache/hadoop/hbase/regionserver/compactions/CompactionContext.compact:(Lorg/apache/hadoop/hbase/regionserver/throttle/ThroughputController;Lorg/apache/hadoop/hbase/security/User;)Ljava/util/List;
     200: invokevirtual #495                // Method doCompaction:(Lorg/apache/hadoop/hbase/regionserver/compactions/CompactionRequestImpl;Ljava/util/Collection;Lorg/apache/hadoop/hbase/security/User;JLjava/util/List;)Ljava/util/List;
     203: astore        9
     205: aload_0
     206: aload         5
     208: invokespecial #496                // Method finishCompactionRequest:(Lorg/apache/hadoop/hbase/regionserver/compactions/CompactionRequestImpl;)V
     211: aload         9
     213: areturn
     214: astore        11
     216: aload_0
     217: aload         5
     219: invokespecial #496                // Method finishCompactionRequest:(Lorg/apache/hadoop/hbase/regionserver/compactions/CompactionRequestImpl;)V
     222: aload         11
     224: athrow
    Exception table:
       from    to  target type
          92   109   112   any
         112   117   112   any
          27   205   214   any
         214   216   214   any

  protected java.util.List<org.apache.hadoop.hbase.regionserver.HStoreFile> doCompaction(org.apache.hadoop.hbase.regionserver.compactions.CompactionRequestImpl, java.util.Collection<org.apache.hadoop.hbase.regionserver.HStoreFile>, org.apache.hadoop.hbase.security.User, long, java.util.List<org.apache.hadoop.fs.Path>) throws java.io.IOException;
    Code:
       0: aload_0
       1: aload_1
       2: aload         6
       4: aload_3
       5: invokespecial #497                // Method moveCompactedFilesIntoPlace:(Lorg/apache/hadoop/hbase/regionserver/compactions/CompactionRequestImpl;Ljava/util/List;Lorg/apache/hadoop/hbase/security/User;)Ljava/util/List;
       8: astore        7
      10: aload_0
      11: aload_2
      12: aload         7
      14: invokespecial #498                // Method writeCompactionWalRecord:(Ljava/util/Collection;Ljava/util/Collection;)V
      17: aload_0
      18: aload_2
      19: aload         7
      21: invokevirtual #272                // Method replaceStoreFiles:(Ljava/util/Collection;Ljava/util/Collection;)V
      24: aload_1
      25: invokevirtual #499                // Method org/apache/hadoop/hbase/regionserver/compactions/CompactionRequestImpl.isMajor:()Z
      28: ifeq          64
      31: aload_0
      32: getfield      #34                 // Field majorCompactedCellsCount:Ljava/util/concurrent/atomic/AtomicLong;
      35: aload_0
      36: invokevirtual #500                // Method getCompactionProgress:()Lorg/apache/hadoop/hbase/regionserver/compactions/CompactionProgress;
      39: invokevirtual #501                // Method org/apache/hadoop/hbase/regionserver/compactions/CompactionProgress.getTotalCompactingKVs:()J
      42: invokevirtual #101                // Method java/util/concurrent/atomic/AtomicLong.addAndGet:(J)J
      45: pop2
      46: aload_0
      47: getfield      #36                 // Field majorCompactedCellsSize:Ljava/util/concurrent/atomic/AtomicLong;
      50: aload_0
      51: invokevirtual #500                // Method getCompactionProgress:()Lorg/apache/hadoop/hbase/regionserver/compactions/CompactionProgress;
      54: getfield      #502                // Field org/apache/hadoop/hbase/regionserver/compactions/CompactionProgress.totalCompactedSize:J
      57: invokevirtual #101                // Method java/util/concurrent/atomic/AtomicLong.addAndGet:(J)J
      60: pop2
      61: goto          94
      64: aload_0
      65: getfield      #33                 // Field compactedCellsCount:Ljava/util/concurrent/atomic/AtomicLong;
      68: aload_0
      69: invokevirtual #500                // Method getCompactionProgress:()Lorg/apache/hadoop/hbase/regionserver/compactions/CompactionProgress;
      72: invokevirtual #501                // Method org/apache/hadoop/hbase/regionserver/compactions/CompactionProgress.getTotalCompactingKVs:()J
      75: invokevirtual #101                // Method java/util/concurrent/atomic/AtomicLong.addAndGet:(J)J
      78: pop2
      79: aload_0
      80: getfield      #35                 // Field compactedCellsSize:Ljava/util/concurrent/atomic/AtomicLong;
      83: aload_0
      84: invokevirtual #500                // Method getCompactionProgress:()Lorg/apache/hadoop/hbase/regionserver/compactions/CompactionProgress;
      87: getfield      #502                // Field org/apache/hadoop/hbase/regionserver/compactions/CompactionProgress.totalCompactedSize:J
      90: invokevirtual #101                // Method java/util/concurrent/atomic/AtomicLong.addAndGet:(J)J
      93: pop2
      94: aload_0
      95: aload         7
      97: invokespecial #467                // Method getTotalSize:(Ljava/util/Collection;)J
     100: lstore        8
     102: aload_0
     103: aload_2
     104: invokevirtual #277                // Method completeCompaction:(Ljava/util/Collection;)V
     107: invokestatic  #337                // Method org/apache/hadoop/hbase/util/EnvironmentEdgeManager.currentTime:()J
     110: lstore        10
     112: aload_0
     113: getfield      #40                 // Field region:Lorg/apache/hadoop/hbase/regionserver/HRegion;
     116: invokevirtual #428                // Method org/apache/hadoop/hbase/regionserver/HRegion.getRegionServerServices:()Lorg/apache/hadoop/hbase/regionserver/RegionServerServices;
     119: ifnull        198
     122: aload_0
     123: getfield      #40                 // Field region:Lorg/apache/hadoop/hbase/regionserver/HRegion;
     126: invokevirtual #428                // Method org/apache/hadoop/hbase/regionserver/HRegion.getRegionServerServices:()Lorg/apache/hadoop/hbase/regionserver/RegionServerServices;
     129: invokeinterface #503,  1          // InterfaceMethod org/apache/hadoop/hbase/regionserver/RegionServerServices.getMetrics:()Lorg/apache/hadoop/hbase/regionserver/MetricsRegionServer;
     134: ifnull        198
     137: aload_0
     138: getfield      #40                 // Field region:Lorg/apache/hadoop/hbase/regionserver/HRegion;
     141: invokevirtual #428                // Method org/apache/hadoop/hbase/regionserver/HRegion.getRegionServerServices:()Lorg/apache/hadoop/hbase/regionserver/RegionServerServices;
     144: invokeinterface #503,  1          // InterfaceMethod org/apache/hadoop/hbase/regionserver/RegionServerServices.getMetrics:()Lorg/apache/hadoop/hbase/regionserver/MetricsRegionServer;
     149: aload_0
     150: getfield      #40                 // Field region:Lorg/apache/hadoop/hbase/regionserver/HRegion;
     153: invokevirtual #45                 // Method org/apache/hadoop/hbase/regionserver/HRegion.getTableDescriptor:()Lorg/apache/hadoop/hbase/client/TableDescriptor;
     156: invokeinterface #504,  1          // InterfaceMethod org/apache/hadoop/hbase/client/TableDescriptor.getTableName:()Lorg/apache/hadoop/hbase/TableName;
     161: invokevirtual #505                // Method org/apache/hadoop/hbase/TableName.getNameAsString:()Ljava/lang/String;
     164: aload_1
     165: invokevirtual #499                // Method org/apache/hadoop/hbase/regionserver/compactions/CompactionRequestImpl.isMajor:()Z
     168: lload         10
     170: lload         4
     172: lsub
     173: aload_1
     174: invokevirtual #486                // Method org/apache/hadoop/hbase/regionserver/compactions/CompactionRequestImpl.getFiles:()Ljava/util/Collection;
     177: invokeinterface #209,  1          // InterfaceMethod java/util/Collection.size:()I
     182: aload         6
     184: invokeinterface #469,  1          // InterfaceMethod java/util/List.size:()I
     189: aload_1
     190: invokevirtual #493                // Method org/apache/hadoop/hbase/regionserver/compactions/CompactionRequestImpl.getSize:()J
     193: lload         8
     195: invokevirtual #506                // Method org/apache/hadoop/hbase/regionserver/MetricsRegionServer.updateCompaction:(Ljava/lang/String;ZJIIJJ)V
     198: aload_0
     199: aload_1
     200: aload         7
     202: lload         10
     204: lload         4
     206: invokespecial #507                // Method logCompactionEndMessage:(Lorg/apache/hadoop/hbase/regionserver/compactions/CompactionRequestImpl;Ljava/util/List;JJ)V
     209: aload         7
     211: areturn

  org.apache.hadoop.hbase.regionserver.HStoreFile moveFileIntoPlace(org.apache.hadoop.fs.Path) throws java.io.IOException;
    Code:
       0: aload_0
       1: aload_1
       2: invokespecial #407                // Method validateStoreFile:(Lorg/apache/hadoop/fs/Path;)V
       5: aload_0
       6: getfield      #4                  // Field fs:Lorg/apache/hadoop/hbase/regionserver/HRegionFileSystem;
       9: aload_0
      10: invokevirtual #127                // Method getColumnFamilyName:()Ljava/lang/String;
      13: aload_1
      14: invokevirtual #414                // Method org/apache/hadoop/hbase/regionserver/HRegionFileSystem.commitStoreFile:(Ljava/lang/String;Lorg/apache/hadoop/fs/Path;)Lorg/apache/hadoop/fs/Path;
      17: astore_2
      18: aload_0
      19: aload_2
      20: invokevirtual #371                // Method createStoreFileAndReader:(Lorg/apache/hadoop/fs/Path;)Lorg/apache/hadoop/hbase/regionserver/HStoreFile;
      23: areturn

  void replaceStoreFiles(java.util.Collection<org.apache.hadoop.hbase.regionserver.HStoreFile>, java.util.Collection<org.apache.hadoop.hbase.regionserver.HStoreFile>) throws java.io.IOException;
    Code:
       0: aload_0
       1: getfield      #18                 // Field lock:Ljava/util/concurrent/locks/ReentrantReadWriteLock;
       4: invokevirtual #376                // Method java/util/concurrent/locks/ReentrantReadWriteLock.writeLock:()Ljava/util/concurrent/locks/ReentrantReadWriteLock$WriteLock;
       7: invokevirtual #377                // Method java/util/concurrent/locks/ReentrantReadWriteLock$WriteLock.lock:()V
      10: aload_0
      11: getfield      #97                 // Field storeEngine:Lorg/apache/hadoop/hbase/regionserver/StoreEngine;
      14: invokevirtual #103                // Method org/apache/hadoop/hbase/regionserver/StoreEngine.getStoreFileManager:()Lorg/apache/hadoop/hbase/regionserver/StoreFileManager;
      17: aload_1
      18: aload_2
      19: invokeinterface #522,  3          // InterfaceMethod org/apache/hadoop/hbase/regionserver/StoreFileManager.addCompactionResults:(Ljava/util/Collection;Ljava/util/Collection;)V
      24: aload_0
      25: getfield      #26                 // Field filesCompacting:Ljava/util/List;
      28: dup
      29: astore_3
      30: monitorenter
      31: aload_0
      32: getfield      #26                 // Field filesCompacting:Ljava/util/List;
      35: aload_1
      36: invokeinterface #523,  2          // InterfaceMethod java/util/List.removeAll:(Ljava/util/Collection;)Z
      41: pop
      42: aload_3
      43: monitorexit
      44: goto          54
      47: astore        4
      49: aload_3
      50: monitorexit
      51: aload         4
      53: athrow
      54: aload_0
      55: getfield      #40                 // Field region:Lorg/apache/hadoop/hbase/regionserver/HRegion;
      58: invokevirtual #428                // Method org/apache/hadoop/hbase/regionserver/HRegion.getRegionServerServices:()Lorg/apache/hadoop/hbase/regionserver/RegionServerServices;
      61: astore_3
      62: aload_3
      63: ifnull        94
      66: aload_3
      67: invokeinterface #524,  1          // InterfaceMethod org/apache/hadoop/hbase/regionserver/RegionServerServices.getRegionServerSpaceQuotaManager:()Lorg/apache/hadoop/hbase/quotas/RegionServerSpaceQuotaManager;
      72: ifnull        94
      75: aload_0
      76: aload_3
      77: invokeinterface #524,  1          // InterfaceMethod org/apache/hadoop/hbase/regionserver/RegionServerServices.getRegionServerSpaceQuotaManager:()Lorg/apache/hadoop/hbase/quotas/RegionServerSpaceQuotaManager;
      82: invokevirtual #525                // Method org/apache/hadoop/hbase/quotas/RegionServerSpaceQuotaManager.getRegionSizeStore:()Lorg/apache/hadoop/hbase/quotas/RegionSizeStore;
      85: aload_0
      86: invokevirtual #167                // Method getRegionInfo:()Lorg/apache/hadoop/hbase/client/RegionInfo;
      89: aload_1
      90: aload_2
      91: invokevirtual #526                // Method updateSpaceQuotaAfterFileReplacement:(Lorg/apache/hadoop/hbase/quotas/RegionSizeStore;Lorg/apache/hadoop/hbase/client/RegionInfo;Ljava/util/Collection;Ljava/util/Collection;)V
      94: aload_0
      95: getfield      #18                 // Field lock:Ljava/util/concurrent/locks/ReentrantReadWriteLock;
      98: invokevirtual #376                // Method java/util/concurrent/locks/ReentrantReadWriteLock.writeLock:()Ljava/util/concurrent/locks/ReentrantReadWriteLock$WriteLock;
     101: invokevirtual #380                // Method java/util/concurrent/locks/ReentrantReadWriteLock$WriteLock.unlock:()V
     104: goto          122
     107: astore        5
     109: aload_0
     110: getfield      #18                 // Field lock:Ljava/util/concurrent/locks/ReentrantReadWriteLock;
     113: invokevirtual #376                // Method java/util/concurrent/locks/ReentrantReadWriteLock.writeLock:()Ljava/util/concurrent/locks/ReentrantReadWriteLock$WriteLock;
     116: invokevirtual #380                // Method java/util/concurrent/locks/ReentrantReadWriteLock$WriteLock.unlock:()V
     119: aload         5
     121: athrow
     122: return
    Exception table:
       from    to  target type
          31    44    47   any
          47    51    47   any
          10    94   107   any
         107   109   107   any

  void updateSpaceQuotaAfterFileReplacement(org.apache.hadoop.hbase.quotas.RegionSizeStore, org.apache.hadoop.hbase.client.RegionInfo, java.util.Collection<org.apache.hadoop.hbase.regionserver.HStoreFile>, java.util.Collection<org.apache.hadoop.hbase.regionserver.HStoreFile>);
    Code:
       0: lconst_0
       1: lstore        5
       3: aload_3
       4: ifnull        61
       7: aload_3
       8: invokeinterface #200,  1          // InterfaceMethod java/util/Collection.iterator:()Ljava/util/Iterator;
      13: astore        7
      15: aload         7
      17: invokeinterface #201,  1          // InterfaceMethod java/util/Iterator.hasNext:()Z
      22: ifeq          61
      25: aload         7
      27: invokeinterface #202,  1          // InterfaceMethod java/util/Iterator.next:()Ljava/lang/Object;
      32: checkcast     #213                // class org/apache/hadoop/hbase/regionserver/HStoreFile
      35: astore        8
      37: aload         8
      39: invokevirtual #527                // Method org/apache/hadoop/hbase/regionserver/HStoreFile.isHFile:()Z
      42: ifeq          58
      45: lload         5
      47: aload         8
      49: invokevirtual #239                // Method org/apache/hadoop/hbase/regionserver/HStoreFile.getReader:()Lorg/apache/hadoop/hbase/regionserver/StoreFileReader;
      52: invokevirtual #374                // Method org/apache/hadoop/hbase/regionserver/StoreFileReader.length:()J
      55: lsub
      56: lstore        5
      58: goto          15
      61: aload         4
      63: ifnull        121
      66: aload         4
      68: invokeinterface #200,  1          // InterfaceMethod java/util/Collection.iterator:()Ljava/util/Iterator;
      73: astore        7
      75: aload         7
      77: invokeinterface #201,  1          // InterfaceMethod java/util/Iterator.hasNext:()Z
      82: ifeq          121
      85: aload         7
      87: invokeinterface #202,  1          // InterfaceMethod java/util/Iterator.next:()Ljava/lang/Object;
      92: checkcast     #213                // class org/apache/hadoop/hbase/regionserver/HStoreFile
      95: astore        8
      97: aload         8
      99: invokevirtual #527                // Method org/apache/hadoop/hbase/regionserver/HStoreFile.isHFile:()Z
     102: ifeq          118
     105: lload         5
     107: aload         8
     109: invokevirtual #239                // Method org/apache/hadoop/hbase/regionserver/HStoreFile.getReader:()Lorg/apache/hadoop/hbase/regionserver/StoreFileReader;
     112: invokevirtual #374                // Method org/apache/hadoop/hbase/regionserver/StoreFileReader.length:()J
     115: ladd
     116: lstore        5
     118: goto          75
     121: aload_1
     122: aload_2
     123: lload         5
     125: invokeinterface #528,  4          // InterfaceMethod org/apache/hadoop/hbase/quotas/RegionSizeStore.incrementRegionSize:(Lorg/apache/hadoop/hbase/client/RegionInfo;J)V
     130: return

  public void replayCompactionMarker(org.apache.hadoop.hbase.shaded.protobuf.generated.WALProtos$CompactionDescriptor, boolean, boolean) throws java.io.IOException;
    Code:
       0: getstatic     #9                  // Field LOG:Lorg/slf4j/Logger;
       3: ldc_w         #550                // String Completing compaction from the WAL marker
       6: invokeinterface #318,  2          // InterfaceMethod org/slf4j/Logger.debug:(Ljava/lang/String;)V
      11: aload_1
      12: invokevirtual #551                // Method org/apache/hadoop/hbase/shaded/protobuf/generated/WALProtos$CompactionDescriptor.getCompactionInputList:()Lorg/apache/hbase/thirdparty/com/google/protobuf/ProtocolStringList;
      15: astore        4
      17: aload_1
      18: invokevirtual #552                // Method org/apache/hadoop/hbase/shaded/protobuf/generated/WALProtos$CompactionDescriptor.getCompactionOutputList:()Lorg/apache/hbase/thirdparty/com/google/protobuf/ProtocolStringList;
      21: invokestatic  #553                // Method org/apache/hbase/thirdparty/com/google/common/collect/Lists.newArrayList:(Ljava/lang/Iterable;)Ljava/util/ArrayList;
      24: astore        5
      26: aload_0
      27: invokevirtual #127                // Method getColumnFamilyName:()Ljava/lang/String;
      30: astore        6
      32: new           #206                // class java/util/HashSet
      35: dup
      36: invokespecial #207                // Method java/util/HashSet."<init>":()V
      39: astore        7
      41: aload         4
      43: invokeinterface #406,  1          // InterfaceMethod java/util/List.iterator:()Ljava/util/Iterator;
      48: astore        8
      50: aload         8
      52: invokeinterface #201,  1          // InterfaceMethod java/util/Iterator.hasNext:()Z
      57: ifeq          101
      60: aload         8
      62: invokeinterface #202,  1          // InterfaceMethod java/util/Iterator.next:()Ljava/lang/Object;
      67: checkcast     #249                // class java/lang/String
      70: astore        9
      72: aload_0
      73: getfield      #4                  // Field fs:Lorg/apache/hadoop/hbase/regionserver/HRegionFileSystem;
      76: aload         6
      78: aload         9
      80: invokevirtual #554                // Method org/apache/hadoop/hbase/regionserver/HRegionFileSystem.getStoreFilePath:(Ljava/lang/String;Ljava/lang/String;)Lorg/apache/hadoop/fs/Path;
      83: astore        10
      85: aload         7
      87: aload         10
      89: invokevirtual #235                // Method org/apache/hadoop/fs/Path.getName:()Ljava/lang/String;
      92: invokeinterface #271,  2          // InterfaceMethod java/util/Set.add:(Ljava/lang/Object;)Z
      97: pop
      98: goto          50
     101: new           #208                // class java/util/ArrayList
     104: dup
     105: aload         4
     107: invokeinterface #469,  1          // InterfaceMethod java/util/List.size:()I
     112: invokespecial #210                // Method java/util/ArrayList."<init>":(I)V
     115: astore        8
     117: aload_0
     118: invokevirtual #181                // Method getStorefiles:()Ljava/util/Collection;
     121: invokeinterface #200,  1          // InterfaceMethod java/util/Collection.iterator:()Ljava/util/Iterator;
     126: astore        9
     128: aload         9
     130: invokeinterface #201,  1          // InterfaceMethod java/util/Iterator.hasNext:()Z
     135: ifeq          181
     138: aload         9
     140: invokeinterface #202,  1          // InterfaceMethod java/util/Iterator.next:()Ljava/lang/Object;
     145: checkcast     #213                // class org/apache/hadoop/hbase/regionserver/HStoreFile
     148: astore        10
     150: aload         7
     152: aload         10
     154: invokevirtual #234                // Method org/apache/hadoop/hbase/regionserver/HStoreFile.getPath:()Lorg/apache/hadoop/fs/Path;
     157: invokevirtual #235                // Method org/apache/hadoop/fs/Path.getName:()Ljava/lang/String;
     160: invokeinterface #236,  2          // InterfaceMethod java/util/Set.contains:(Ljava/lang/Object;)Z
     165: ifeq          178
     168: aload         8
     170: aload         10
     172: invokeinterface #241,  2          // InterfaceMethod java/util/List.add:(Ljava/lang/Object;)Z
     177: pop
     178: goto          128
     181: new           #208                // class java/util/ArrayList
     184: dup
     185: aload         5
     187: invokeinterface #469,  1          // InterfaceMethod java/util/List.size:()I
     192: invokespecial #210                // Method java/util/ArrayList."<init>":(I)V
     195: astore        9
     197: iload_2
     198: ifeq          320
     201: aload_0
     202: invokevirtual #181                // Method getStorefiles:()Ljava/util/Collection;
     205: invokeinterface #200,  1          // InterfaceMethod java/util/Collection.iterator:()Ljava/util/Iterator;
     210: astore        10
     212: aload         10
     214: invokeinterface #201,  1          // InterfaceMethod java/util/Iterator.hasNext:()Z
     219: ifeq          253
     222: aload         10
     224: invokeinterface #202,  1          // InterfaceMethod java/util/Iterator.next:()Ljava/lang/Object;
     229: checkcast     #213                // class org/apache/hadoop/hbase/regionserver/HStoreFile
     232: astore        11
     234: aload         5
     236: aload         11
     238: invokevirtual #234                // Method org/apache/hadoop/hbase/regionserver/HStoreFile.getPath:()Lorg/apache/hadoop/fs/Path;
     241: invokevirtual #235                // Method org/apache/hadoop/fs/Path.getName:()Ljava/lang/String;
     244: invokeinterface #555,  2          // InterfaceMethod java/util/List.remove:(Ljava/lang/Object;)Z
     249: pop
     250: goto          212
     253: aload         5
     255: invokeinterface #406,  1          // InterfaceMethod java/util/List.iterator:()Ljava/util/Iterator;
     260: astore        10
     262: aload         10
     264: invokeinterface #201,  1          // InterfaceMethod java/util/Iterator.hasNext:()Z
     269: ifeq          320
     272: aload         10
     274: invokeinterface #202,  1          // InterfaceMethod java/util/Iterator.next:()Ljava/lang/Object;
     279: checkcast     #249                // class java/lang/String
     282: astore        11
     284: aload_0
     285: getfield      #4                  // Field fs:Lorg/apache/hadoop/hbase/regionserver/HRegionFileSystem;
     288: aload_0
     289: invokevirtual #127                // Method getColumnFamilyName:()Ljava/lang/String;
     292: aload         11
     294: invokevirtual #250                // Method org/apache/hadoop/hbase/regionserver/HRegionFileSystem.getStoreFileInfo:(Ljava/lang/String;Ljava/lang/String;)Lorg/apache/hadoop/hbase/regionserver/StoreFileInfo;
     297: astore        12
     299: aload_0
     300: aload         12
     302: invokespecial #3                  // Method createStoreFileAndReader:(Lorg/apache/hadoop/hbase/regionserver/StoreFileInfo;)Lorg/apache/hadoop/hbase/regionserver/HStoreFile;
     305: astore        13
     307: aload         9
     309: aload         13
     311: invokeinterface #241,  2          // InterfaceMethod java/util/List.add:(Ljava/lang/Object;)Z
     316: pop
     317: goto          262
     320: aload         8
     322: invokeinterface #243,  1          // InterfaceMethod java/util/List.isEmpty:()Z
     327: ifeq          340
     330: aload         9
     332: invokeinterface #243,  1          // InterfaceMethod java/util/List.isEmpty:()Z
     337: ifne          394
     340: getstatic     #9                  // Field LOG:Lorg/slf4j/Logger;
     343: new           #115                // class java/lang/StringBuilder
     346: dup
     347: invokespecial #116                // Method java/lang/StringBuilder."<init>":()V
     350: ldc_w         #556                // String Replaying compaction marker, replacing input files:
     353: invokevirtual #118                // Method java/lang/StringBuilder.append:(Ljava/lang/String;)Ljava/lang/StringBuilder;
     356: aload         8
     358: invokevirtual #265                // Method java/lang/StringBuilder.append:(Ljava/lang/Object;)Ljava/lang/StringBuilder;
     361: ldc_w         #557                // String  with output files :
     364: invokevirtual #118                // Method java/lang/StringBuilder.append:(Ljava/lang/String;)Ljava/lang/StringBuilder;
     367: aload         9
     369: invokevirtual #265                // Method java/lang/StringBuilder.append:(Ljava/lang/Object;)Ljava/lang/StringBuilder;
     372: invokevirtual #120                // Method java/lang/StringBuilder.toString:()Ljava/lang/String;
     375: invokeinterface #267,  2          // InterfaceMethod org/slf4j/Logger.info:(Ljava/lang/String;)V
     380: aload_0
     381: aload         8
     383: aload         9
     385: invokevirtual #272                // Method replaceStoreFiles:(Ljava/util/Collection;Ljava/util/Collection;)V
     388: aload_0
     389: aload         8
     391: invokevirtual #277                // Method completeCompaction:(Ljava/util/Collection;)V
     394: return

  public void compactRecentForTestingAssumingDefaultPolicy(int) throws java.io.IOException;
    Code:
       0: aload_0
       1: getfield      #18                 // Field lock:Ljava/util/concurrent/locks/ReentrantReadWriteLock;
       4: invokevirtual #287                // Method java/util/concurrent/locks/ReentrantReadWriteLock.readLock:()Ljava/util/concurrent/locks/ReentrantReadWriteLock$ReadLock;
       7: invokevirtual #288                // Method java/util/concurrent/locks/ReentrantReadWriteLock$ReadLock.lock:()V
      10: aload_0
      11: getfield      #26                 // Field filesCompacting:Ljava/util/List;
      14: dup
      15: astore        4
      17: monitorenter
      18: aload_0
      19: getfield      #97                 // Field storeEngine:Lorg/apache/hadoop/hbase/regionserver/StoreEngine;
      22: invokevirtual #103                // Method org/apache/hadoop/hbase/regionserver/StoreEngine.getStoreFileManager:()Lorg/apache/hadoop/hbase/regionserver/StoreFileManager;
      25: invokeinterface #251,  1          // InterfaceMethod org/apache/hadoop/hbase/regionserver/StoreFileManager.getStorefiles:()Ljava/util/Collection;
      30: invokestatic  #553                // Method org/apache/hbase/thirdparty/com/google/common/collect/Lists.newArrayList:(Ljava/lang/Iterable;)Ljava/util/ArrayList;
      33: astore_2
      34: aload_0
      35: getfield      #26                 // Field filesCompacting:Ljava/util/List;
      38: invokeinterface #243,  1          // InterfaceMethod java/util/List.isEmpty:()Z
      43: ifne          111
      46: aload_0
      47: getfield      #26                 // Field filesCompacting:Ljava/util/List;
      50: aload_0
      51: getfield      #26                 // Field filesCompacting:Ljava/util/List;
      54: invokeinterface #469,  1          // InterfaceMethod java/util/List.size:()I
      59: iconst_1
      60: isub
      61: invokeinterface #558,  2          // InterfaceMethod java/util/List.get:(I)Ljava/lang/Object;
      66: checkcast     #213                // class org/apache/hadoop/hbase/regionserver/HStoreFile
      69: astore        5
      71: aload_2
      72: aload         5
      74: invokeinterface #559,  2          // InterfaceMethod java/util/List.indexOf:(Ljava/lang/Object;)I
      79: istore        6
      81: iload         6
      83: iconst_m1
      84: if_icmpeq     91
      87: iconst_1
      88: goto          92
      91: iconst_0
      92: invokestatic  #489                // Method org/apache/hbase/thirdparty/com/google/common/base/Preconditions.checkArgument:(Z)V
      95: aload_2
      96: iconst_0
      97: iload         6
      99: iconst_1
     100: iadd
     101: invokeinterface #560,  3          // InterfaceMethod java/util/List.subList:(II)Ljava/util/List;
     106: invokeinterface #561,  1          // InterfaceMethod java/util/List.clear:()V
     111: aload_2
     112: invokeinterface #469,  1          // InterfaceMethod java/util/List.size:()I
     117: istore        5
     119: iload_1
     120: iload         5
     122: if_icmple     136
     125: new           #562                // class java/lang/RuntimeException
     128: dup
     129: ldc_w         #563                // String Not enough files
     132: invokespecial #564                // Method java/lang/RuntimeException."<init>":(Ljava/lang/String;)V
     135: athrow
     136: aload_2
     137: iload         5
     139: iload_1
     140: isub
     141: iload         5
     143: invokeinterface #560,  3          // InterfaceMethod java/util/List.subList:(II)Ljava/util/List;
     148: astore_2
     149: aload_2
     150: invokeinterface #469,  1          // InterfaceMethod java/util/List.size:()I
     155: aload_0
     156: getfield      #97                 // Field storeEngine:Lorg/apache/hadoop/hbase/regionserver/StoreEngine;
     159: invokevirtual #103                // Method org/apache/hadoop/hbase/regionserver/StoreEngine.getStoreFileManager:()Lorg/apache/hadoop/hbase/regionserver/StoreFileManager;
     162: invokeinterface #384,  1          // InterfaceMethod org/apache/hadoop/hbase/regionserver/StoreFileManager.getStorefileCount:()I
     167: if_icmpne     174
     170: iconst_1
     171: goto          175
     174: iconst_0
     175: istore_3
     176: aload_0
     177: getfield      #26                 // Field filesCompacting:Ljava/util/List;
     180: aload_2
     181: invokeinterface #478,  2          // InterfaceMethod java/util/List.addAll:(Ljava/util/Collection;)Z
     186: pop
     187: aload_0
     188: getfield      #26                 // Field filesCompacting:Ljava/util/List;
     191: aload_0
     192: getfield      #97                 // Field storeEngine:Lorg/apache/hadoop/hbase/regionserver/StoreEngine;
     195: invokevirtual #103                // Method org/apache/hadoop/hbase/regionserver/StoreEngine.getStoreFileManager:()Lorg/apache/hadoop/hbase/regionserver/StoreFileManager;
     198: invokeinterface #565,  1          // InterfaceMethod org/apache/hadoop/hbase/regionserver/StoreFileManager.getStoreFileComparator:()Ljava/util/Comparator;
     203: invokestatic  #566                // Method java/util/Collections.sort:(Ljava/util/List;Ljava/util/Comparator;)V
     206: aload         4
     208: monitorexit
     209: goto          220
     212: astore        7
     214: aload         4
     216: monitorexit
     217: aload         7
     219: athrow
     220: aload_0
     221: getfield      #18                 // Field lock:Ljava/util/concurrent/locks/ReentrantReadWriteLock;
     224: invokevirtual #287                // Method java/util/concurrent/locks/ReentrantReadWriteLock.readLock:()Ljava/util/concurrent/locks/ReentrantReadWriteLock$ReadLock;
     227: invokevirtual #292                // Method java/util/concurrent/locks/ReentrantReadWriteLock$ReadLock.unlock:()V
     230: goto          248
     233: astore        8
     235: aload_0
     236: getfield      #18                 // Field lock:Ljava/util/concurrent/locks/ReentrantReadWriteLock;
     239: invokevirtual #287                // Method java/util/concurrent/locks/ReentrantReadWriteLock.readLock:()Ljava/util/concurrent/locks/ReentrantReadWriteLock$ReadLock;
     242: invokevirtual #292                // Method java/util/concurrent/locks/ReentrantReadWriteLock$ReadLock.unlock:()V
     245: aload         8
     247: athrow
     248: aload_0
     249: getfield      #97                 // Field storeEngine:Lorg/apache/hadoop/hbase/regionserver/StoreEngine;
     252: invokevirtual #567                // Method org/apache/hadoop/hbase/regionserver/StoreEngine.getCompactor:()Lorg/apache/hadoop/hbase/regionserver/compactions/Compactor;
     255: checkcast     #568                // class org/apache/hadoop/hbase/regionserver/compactions/DefaultCompactor
     258: aload_2
     259: iload_3
     260: invokevirtual #569                // Method org/apache/hadoop/hbase/regionserver/compactions/DefaultCompactor.compactForTesting:(Ljava/util/Collection;Z)Ljava/util/List;
     263: astore        4
     265: aload         4
     267: invokeinterface #406,  1          // InterfaceMethod java/util/List.iterator:()Ljava/util/Iterator;
     272: astore        5
     274: aload         5
     276: invokeinterface #201,  1          // InterfaceMethod java/util/Iterator.hasNext:()Z
     281: ifeq          342
     284: aload         5
     286: invokeinterface #202,  1          // InterfaceMethod java/util/Iterator.next:()Ljava/lang/Object;
     291: checkcast     #186                // class org/apache/hadoop/fs/Path
     294: astore        6
     296: aload_0
     297: aload         6
     299: invokevirtual #508                // Method moveFileIntoPlace:(Lorg/apache/hadoop/fs/Path;)Lorg/apache/hadoop/hbase/regionserver/HStoreFile;
     302: astore        7
     304: aload_0
     305: invokevirtual #365                // Method getCoprocessorHost:()Lorg/apache/hadoop/hbase/regionserver/RegionCoprocessorHost;
     308: ifnull        324
     311: aload_0
     312: invokevirtual #365                // Method getCoprocessorHost:()Lorg/apache/hadoop/hbase/regionserver/RegionCoprocessorHost;
     315: aload_0
     316: aload         7
     318: aconst_null
     319: aconst_null
     320: aconst_null
     321: invokevirtual #510                // Method org/apache/hadoop/hbase/regionserver/RegionCoprocessorHost.postCompact:(Lorg/apache/hadoop/hbase/regionserver/HStore;Lorg/apache/hadoop/hbase/regionserver/HStoreFile;Lorg/apache/hadoop/hbase/regionserver/compactions/CompactionLifeCycleTracker;Lorg/apache/hadoop/hbase/regionserver/compactions/CompactionRequest;Lorg/apache/hadoop/hbase/security/User;)V
     324: aload_0
     325: aload_2
     326: aload         7
     328: invokestatic  #570                // Method java/util/Collections.singletonList:(Ljava/lang/Object;)Ljava/util/List;
     331: invokevirtual #272                // Method replaceStoreFiles:(Ljava/util/Collection;Ljava/util/Collection;)V
     334: aload_0
     335: aload_2
     336: invokevirtual #277                // Method completeCompaction:(Ljava/util/Collection;)V
     339: goto          274
     342: aload_0
     343: getfield      #26                 // Field filesCompacting:Ljava/util/List;
     346: dup
     347: astore        4
     349: monitorenter
     350: aload_0
     351: getfield      #26                 // Field filesCompacting:Ljava/util/List;
     354: aload_2
     355: invokeinterface #523,  2          // InterfaceMethod java/util/List.removeAll:(Ljava/util/Collection;)Z
     360: pop
     361: aload         4
     363: monitorexit
     364: goto          375
     367: astore        9
     369: aload         4
     371: monitorexit
     372: aload         9
     374: athrow
     375: goto          416
     378: astore        10
     380: aload_0
     381: getfield      #26                 // Field filesCompacting:Ljava/util/List;
     384: dup
     385: astore        11
     387: monitorenter
     388: aload_0
     389: getfield      #26                 // Field filesCompacting:Ljava/util/List;
     392: aload_2
     393: invokeinterface #523,  2          // InterfaceMethod java/util/List.removeAll:(Ljava/util/Collection;)Z
     398: pop
     399: aload         11
     401: monitorexit
     402: goto          413
     405: astore        12
     407: aload         11
     409: monitorexit
     410: aload         12
     412: athrow
     413: aload         10
     415: athrow
     416: return
    Exception table:
       from    to  target type
          18   209   212   any
         212   217   212   any
          10   220   233   any
         233   235   233   any
         350   364   367   any
         367   372   367   any
         248   342   378   any
         388   402   405   any
         405   410   405   any
         378   380   378   any

  public boolean hasReferences();
    Code:
       0: aload_0
       1: getfield      #18                 // Field lock:Ljava/util/concurrent/locks/ReentrantReadWriteLock;
       4: invokevirtual #287                // Method java/util/concurrent/locks/ReentrantReadWriteLock.readLock:()Ljava/util/concurrent/locks/ReentrantReadWriteLock$ReadLock;
       7: invokevirtual #288                // Method java/util/concurrent/locks/ReentrantReadWriteLock$ReadLock.lock:()V
      10: new           #208                // class java/util/ArrayList
      13: dup
      14: aload_0
      15: invokevirtual #181                // Method getStorefiles:()Ljava/util/Collection;
      18: invokespecial #571                // Method java/util/ArrayList."<init>":(Ljava/util/Collection;)V
      21: astore_1
      22: aload_1
      23: aload_0
      24: invokevirtual #572                // Method getCompactedFiles:()Ljava/util/Collection;
      27: invokeinterface #573,  2          // InterfaceMethod java/util/Collection.addAll:(Ljava/util/Collection;)Z
      32: pop
      33: aload_1
      34: invokestatic  #574                // Method org/apache/hadoop/hbase/regionserver/StoreUtils.hasReferences:(Ljava/util/Collection;)Z
      37: istore_2
      38: aload_0
      39: getfield      #18                 // Field lock:Ljava/util/concurrent/locks/ReentrantReadWriteLock;
      42: invokevirtual #287                // Method java/util/concurrent/locks/ReentrantReadWriteLock.readLock:()Ljava/util/concurrent/locks/ReentrantReadWriteLock$ReadLock;
      45: invokevirtual #292                // Method java/util/concurrent/locks/ReentrantReadWriteLock$ReadLock.unlock:()V
      48: iload_2
      49: ireturn
      50: astore_3
      51: aload_0
      52: getfield      #18                 // Field lock:Ljava/util/concurrent/locks/ReentrantReadWriteLock;
      55: invokevirtual #287                // Method java/util/concurrent/locks/ReentrantReadWriteLock.readLock:()Ljava/util/concurrent/locks/ReentrantReadWriteLock$ReadLock;
      58: invokevirtual #292                // Method java/util/concurrent/locks/ReentrantReadWriteLock$ReadLock.unlock:()V
      61: aload_3
      62: athrow
    Exception table:
       from    to  target type
          10    38    50   any

  public org.apache.hadoop.hbase.regionserver.compactions.CompactionProgress getCompactionProgress();
    Code:
       0: aload_0
       1: getfield      #97                 // Field storeEngine:Lorg/apache/hadoop/hbase/regionserver/StoreEngine;
       4: invokevirtual #567                // Method org/apache/hadoop/hbase/regionserver/StoreEngine.getCompactor:()Lorg/apache/hadoop/hbase/regionserver/compactions/Compactor;
       7: invokevirtual #575                // Method org/apache/hadoop/hbase/regionserver/compactions/Compactor.getProgress:()Lorg/apache/hadoop/hbase/regionserver/compactions/CompactionProgress;
      10: areturn

  public boolean shouldPerformMajorCompaction() throws java.io.IOException;
    Code:
       0: aload_0
       1: getfield      #97                 // Field storeEngine:Lorg/apache/hadoop/hbase/regionserver/StoreEngine;
       4: invokevirtual #103                // Method org/apache/hadoop/hbase/regionserver/StoreEngine.getStoreFileManager:()Lorg/apache/hadoop/hbase/regionserver/StoreFileManager;
       7: invokeinterface #251,  1          // InterfaceMethod org/apache/hadoop/hbase/regionserver/StoreFileManager.getStorefiles:()Ljava/util/Collection;
      12: invokeinterface #200,  1          // InterfaceMethod java/util/Collection.iterator:()Ljava/util/Iterator;
      17: astore_1
      18: aload_1
      19: invokeinterface #201,  1          // InterfaceMethod java/util/Iterator.hasNext:()Z
      24: ifeq          61
      27: aload_1
      28: invokeinterface #202,  1          // InterfaceMethod java/util/Iterator.next:()Ljava/lang/Object;
      33: checkcast     #213                // class org/apache/hadoop/hbase/regionserver/HStoreFile
      36: astore_2
      37: aload_2
      38: invokevirtual #239                // Method org/apache/hadoop/hbase/regionserver/HStoreFile.getReader:()Lorg/apache/hadoop/hbase/regionserver/StoreFileReader;
      41: ifnonnull     58
      44: getstatic     #9                  // Field LOG:Lorg/slf4j/Logger;
      47: ldc_w         #576                // String StoreFile {} has null Reader
      50: aload_2
      51: invokeinterface #215,  3          // InterfaceMethod org/slf4j/Logger.debug:(Ljava/lang/String;Ljava/lang/Object;)V
      56: iconst_0
      57: ireturn
      58: goto          18
      61: aload_0
      62: getfield      #97                 // Field storeEngine:Lorg/apache/hadoop/hbase/regionserver/StoreEngine;
      65: invokevirtual #577                // Method org/apache/hadoop/hbase/regionserver/StoreEngine.getCompactionPolicy:()Lorg/apache/hadoop/hbase/regionserver/compactions/CompactionPolicy;
      68: aload_0
      69: getfield      #97                 // Field storeEngine:Lorg/apache/hadoop/hbase/regionserver/StoreEngine;
      72: invokevirtual #103                // Method org/apache/hadoop/hbase/regionserver/StoreEngine.getStoreFileManager:()Lorg/apache/hadoop/hbase/regionserver/StoreFileManager;
      75: invokeinterface #251,  1          // InterfaceMethod org/apache/hadoop/hbase/regionserver/StoreFileManager.getStorefiles:()Ljava/util/Collection;
      80: invokevirtual #578                // Method org/apache/hadoop/hbase/regionserver/compactions/CompactionPolicy.shouldPerformMajorCompaction:(Ljava/util/Collection;)Z
      83: ireturn

  public java.util.Optional<org.apache.hadoop.hbase.regionserver.compactions.CompactionContext> requestCompaction() throws java.io.IOException;
    Code:
       0: aload_0
       1: ldc_w         #580                // int -2147483648
       4: getstatic     #581                // Field org/apache/hadoop/hbase/regionserver/compactions/CompactionLifeCycleTracker.DUMMY:Lorg/apache/hadoop/hbase/regionserver/compactions/CompactionLifeCycleTracker;
       7: aconst_null
       8: invokevirtual #582                // Method requestCompaction:(ILorg/apache/hadoop/hbase/regionserver/compactions/CompactionLifeCycleTracker;Lorg/apache/hadoop/hbase/security/User;)Ljava/util/Optional;
      11: areturn

  public java.util.Optional<org.apache.hadoop.hbase.regionserver.compactions.CompactionContext> requestCompaction(int, org.apache.hadoop.hbase.regionserver.compactions.CompactionLifeCycleTracker, org.apache.hadoop.hbase.security.User) throws java.io.IOException;
    Code:
       0: aload_0
       1: invokevirtual #583                // Method areWritesEnabled:()Z
       4: ifne          11
       7: invokestatic  #584                // Method java/util/Optional.empty:()Ljava/util/Optional;
      10: areturn
      11: aload_0
      12: invokespecial #585                // Method removeUnneededFiles:()V
      15: aload_0
      16: getfield      #97                 // Field storeEngine:Lorg/apache/hadoop/hbase/regionserver/StoreEngine;
      19: invokevirtual #586                // Method org/apache/hadoop/hbase/regionserver/StoreEngine.createCompaction:()Lorg/apache/hadoop/hbase/regionserver/compactions/CompactionContext;
      22: astore        4
      24: aconst_null
      25: astore        5
      27: aload_0
      28: getfield      #18                 // Field lock:Ljava/util/concurrent/locks/ReentrantReadWriteLock;
      31: invokevirtual #287                // Method java/util/concurrent/locks/ReentrantReadWriteLock.readLock:()Ljava/util/concurrent/locks/ReentrantReadWriteLock$ReadLock;
      34: invokevirtual #288                // Method java/util/concurrent/locks/ReentrantReadWriteLock$ReadLock.lock:()V
      37: aload_0
      38: getfield      #26                 // Field filesCompacting:Ljava/util/List;
      41: dup
      42: astore        6
      44: monitorenter
      45: aload_0
      46: invokevirtual #365                // Method getCoprocessorHost:()Lorg/apache/hadoop/hbase/regionserver/RegionCoprocessorHost;
      49: ifnull        96
      52: aload         4
      54: aload_0
      55: getfield      #26                 // Field filesCompacting:Ljava/util/List;
      58: invokevirtual #587                // Method org/apache/hadoop/hbase/regionserver/compactions/CompactionContext.preSelect:(Ljava/util/List;)Ljava/util/List;
      61: astore        7
      63: aload_0
      64: invokevirtual #365                // Method getCoprocessorHost:()Lorg/apache/hadoop/hbase/regionserver/RegionCoprocessorHost;
      67: aload_0
      68: aload         7
      70: aload_2
      71: aload_3
      72: invokevirtual #588                // Method org/apache/hadoop/hbase/regionserver/RegionCoprocessorHost.preCompactSelection:(Lorg/apache/hadoop/hbase/regionserver/HStore;Ljava/util/List;Lorg/apache/hadoop/hbase/regionserver/compactions/CompactionLifeCycleTracker;Lorg/apache/hadoop/hbase/security/User;)Z
      75: istore        8
      77: iload         8
      79: ifeq          96
      82: aload         4
      84: new           #589                // class org/apache/hadoop/hbase/regionserver/compactions/CompactionRequestImpl
      87: dup
      88: aload         7
      90: invokespecial #590                // Method org/apache/hadoop/hbase/regionserver/compactions/CompactionRequestImpl."<init>":(Ljava/util/Collection;)V
      93: invokevirtual #591                // Method org/apache/hadoop/hbase/regionserver/compactions/CompactionContext.forceSelect:(Lorg/apache/hadoop/hbase/regionserver/compactions/CompactionRequestImpl;)V
      96: aload         4
      98: invokevirtual #485                // Method org/apache/hadoop/hbase/regionserver/compactions/CompactionContext.hasSelection:()Z
     101: ifne          247
     104: iload_1
     105: iconst_1
     106: if_icmpne     113
     109: iconst_1
     110: goto          114
     113: iconst_0
     114: istore        7
     116: aload_0
     117: getfield      #80                 // Field offPeakHours:Lorg/apache/hadoop/hbase/regionserver/compactions/OffPeakHours;
     120: invokevirtual #592                // Method org/apache/hadoop/hbase/regionserver/compactions/OffPeakHours.isOffPeakHour:()Z
     123: ifeq          141
     126: getstatic     #593                // Field offPeakCompactionTracker:Ljava/util/concurrent/atomic/AtomicBoolean;
     129: iconst_0
     130: iconst_1
     131: invokevirtual #594                // Method java/util/concurrent/atomic/AtomicBoolean.compareAndSet:(ZZ)Z
     134: ifeq          141
     137: iconst_1
     138: goto          142
     141: iconst_0
     142: istore        8
     144: aload         4
     146: aload_0
     147: getfield      #26                 // Field filesCompacting:Ljava/util/List;
     150: iload         7
     152: iload         8
     154: aload_0
     155: getfield      #13                 // Field forceMajor:Z
     158: ifeq          177
     161: aload_0
     162: getfield      #26                 // Field filesCompacting:Ljava/util/List;
     165: invokeinterface #243,  1          // InterfaceMethod java/util/List.isEmpty:()Z
     170: ifeq          177
     173: iconst_1
     174: goto          178
     177: iconst_0
     178: invokevirtual #595                // Method org/apache/hadoop/hbase/regionserver/compactions/CompactionContext.select:(Ljava/util/List;ZZZ)Z
     181: pop
     182: goto          202
     185: astore        9
     187: iload         8
     189: ifeq          199
     192: getstatic     #593                // Field offPeakCompactionTracker:Ljava/util/concurrent/atomic/AtomicBoolean;
     195: iconst_0
     196: invokevirtual #596                // Method java/util/concurrent/atomic/AtomicBoolean.set:(Z)V
     199: aload         9
     201: athrow
     202: getstatic     #481                // Field $assertionsDisabled:Z
     205: ifne          224
     208: aload         4
     210: invokevirtual #485                // Method org/apache/hadoop/hbase/regionserver/compactions/CompactionContext.hasSelection:()Z
     213: ifne          224
     216: new           #482                // class java/lang/AssertionError
     219: dup
     220: invokespecial #483                // Method java/lang/AssertionError."<init>":()V
     223: athrow
     224: iload         8
     226: ifeq          247
     229: aload         4
     231: invokevirtual #484                // Method org/apache/hadoop/hbase/regionserver/compactions/CompactionContext.getRequest:()Lorg/apache/hadoop/hbase/regionserver/compactions/CompactionRequestImpl;
     234: invokevirtual #597                // Method org/apache/hadoop/hbase/regionserver/compactions/CompactionRequestImpl.isOffPeak:()Z
     237: ifne          247
     240: getstatic     #593                // Field offPeakCompactionTracker:Ljava/util/concurrent/atomic/AtomicBoolean;
     243: iconst_0
     244: invokevirtual #596                // Method java/util/concurrent/atomic/AtomicBoolean.set:(Z)V
     247: aload_0
     248: invokevirtual #365                // Method getCoprocessorHost:()Lorg/apache/hadoop/hbase/regionserver/RegionCoprocessorHost;
     251: ifnull        280
     254: aload_0
     255: invokevirtual #365                // Method getCoprocessorHost:()Lorg/apache/hadoop/hbase/regionserver/RegionCoprocessorHost;
     258: aload_0
     259: aload         4
     261: invokevirtual #484                // Method org/apache/hadoop/hbase/regionserver/compactions/CompactionContext.getRequest:()Lorg/apache/hadoop/hbase/regionserver/compactions/CompactionRequestImpl;
     264: invokevirtual #486                // Method org/apache/hadoop/hbase/regionserver/compactions/CompactionRequestImpl.getFiles:()Ljava/util/Collection;
     267: invokestatic  #598                // Method org/apache/hbase/thirdparty/com/google/common/collect/ImmutableList.copyOf:(Ljava/util/Collection;)Lorg/apache/hbase/thirdparty/com/google/common/collect/ImmutableList;
     270: aload_2
     271: aload         4
     273: invokevirtual #484                // Method org/apache/hadoop/hbase/regionserver/compactions/CompactionContext.getRequest:()Lorg/apache/hadoop/hbase/regionserver/compactions/CompactionRequestImpl;
     276: aload_3
     277: invokevirtual #599                // Method org/apache/hadoop/hbase/regionserver/RegionCoprocessorHost.postCompactSelection:(Lorg/apache/hadoop/hbase/regionserver/HStore;Ljava/util/List;Lorg/apache/hadoop/hbase/regionserver/compactions/CompactionLifeCycleTracker;Lorg/apache/hadoop/hbase/regionserver/compactions/CompactionRequest;Lorg/apache/hadoop/hbase/security/User;)V
     280: aload         4
     282: invokevirtual #484                // Method org/apache/hadoop/hbase/regionserver/compactions/CompactionContext.getRequest:()Lorg/apache/hadoop/hbase/regionserver/compactions/CompactionRequestImpl;
     285: astore        5
     287: aload         5
     289: invokevirtual #486                // Method org/apache/hadoop/hbase/regionserver/compactions/CompactionRequestImpl.getFiles:()Ljava/util/Collection;
     292: astore        7
     294: aload         7
     296: invokeinterface #487,  1          // InterfaceMethod java/util/Collection.isEmpty:()Z
     301: ifeq          325
     304: invokestatic  #584                // Method java/util/Optional.empty:()Ljava/util/Optional;
     307: astore        8
     309: aload         6
     311: monitorexit
     312: aload_0
     313: getfield      #18                 // Field lock:Ljava/util/concurrent/locks/ReentrantReadWriteLock;
     316: invokevirtual #287                // Method java/util/concurrent/locks/ReentrantReadWriteLock.readLock:()Ljava/util/concurrent/locks/ReentrantReadWriteLock$ReadLock;
     319: invokevirtual #292                // Method java/util/concurrent/locks/ReentrantReadWriteLock$ReadLock.unlock:()V
     322: aload         8
     324: areturn
     325: aload_0
     326: aload         7
     328: invokespecial #600                // Method addToCompactingFiles:(Ljava/util/Collection;)V
     331: aload_0
     332: aload_0
     333: getfield      #13                 // Field forceMajor:Z
     336: ifeq          351
     339: aload         5
     341: invokevirtual #499                // Method org/apache/hadoop/hbase/regionserver/compactions/CompactionRequestImpl.isMajor:()Z
     344: ifne          351
     347: iconst_1
     348: goto          352
     351: iconst_0
     352: putfield      #13                 // Field forceMajor:Z
     355: aload         5
     357: iload_1
     358: ldc_w         #580                // int -2147483648
     361: if_icmpeq     368
     364: iload_1
     365: goto          372
     368: aload_0
     369: invokevirtual #601                // Method getCompactPriority:()I
     372: invokevirtual #602                // Method org/apache/hadoop/hbase/regionserver/compactions/CompactionRequestImpl.setPriority:(I)V
     375: aload         5
     377: aload_0
     378: invokevirtual #167                // Method getRegionInfo:()Lorg/apache/hadoop/hbase/client/RegionInfo;
     381: invokeinterface #263,  1          // InterfaceMethod org/apache/hadoop/hbase/client/RegionInfo.getRegionNameAsString:()Ljava/lang/String;
     386: aload_0
     387: invokevirtual #127                // Method getColumnFamilyName:()Ljava/lang/String;
     390: invokevirtual #603                // Method org/apache/hadoop/hbase/regionserver/compactions/CompactionRequestImpl.setDescription:(Ljava/lang/String;Ljava/lang/String;)V
     393: aload         5
     395: aload_2
     396: invokevirtual #604                // Method org/apache/hadoop/hbase/regionserver/compactions/CompactionRequestImpl.setTracker:(Lorg/apache/hadoop/hbase/regionserver/compactions/CompactionLifeCycleTracker;)V
     399: aload         6
     401: monitorexit
     402: goto          413
     405: astore        10
     407: aload         6
     409: monitorexit
     410: aload         10
     412: athrow
     413: aload_0
     414: getfield      #18                 // Field lock:Ljava/util/concurrent/locks/ReentrantReadWriteLock;
     417: invokevirtual #287                // Method java/util/concurrent/locks/ReentrantReadWriteLock.readLock:()Ljava/util/concurrent/locks/ReentrantReadWriteLock$ReadLock;
     420: invokevirtual #292                // Method java/util/concurrent/locks/ReentrantReadWriteLock$ReadLock.unlock:()V
     423: goto          441
     426: astore        11
     428: aload_0
     429: getfield      #18                 // Field lock:Ljava/util/concurrent/locks/ReentrantReadWriteLock;
     432: invokevirtual #287                // Method java/util/concurrent/locks/ReentrantReadWriteLock.readLock:()Ljava/util/concurrent/locks/ReentrantReadWriteLock$ReadLock;
     435: invokevirtual #292                // Method java/util/concurrent/locks/ReentrantReadWriteLock$ReadLock.unlock:()V
     438: aload         11
     440: athrow
     441: getstatic     #9                  // Field LOG:Lorg/slf4j/Logger;
     444: invokeinterface #313,  1          // InterfaceMethod org/slf4j/Logger.isDebugEnabled:()Z
     449: ifeq          547
     452: getstatic     #9                  // Field LOG:Lorg/slf4j/Logger;
     455: new           #115                // class java/lang/StringBuilder
     458: dup
     459: invokespecial #116                // Method java/lang/StringBuilder."<init>":()V
     462: aload_0
     463: invokevirtual #167                // Method getRegionInfo:()Lorg/apache/hadoop/hbase/client/RegionInfo;
     466: invokeinterface #184,  1          // InterfaceMethod org/apache/hadoop/hbase/client/RegionInfo.getEncodedName:()Ljava/lang/String;
     471: invokevirtual #118                // Method java/lang/StringBuilder.append:(Ljava/lang/String;)Ljava/lang/StringBuilder;
     474: ldc_w         #605                // String  -
     477: invokevirtual #118                // Method java/lang/StringBuilder.append:(Ljava/lang/String;)Ljava/lang/StringBuilder;
     480: aload_0
     481: invokevirtual #127                // Method getColumnFamilyName:()Ljava/lang/String;
     484: invokevirtual #118                // Method java/lang/StringBuilder.append:(Ljava/lang/String;)Ljava/lang/StringBuilder;
     487: ldc_w         #606                // String : Initiating
     490: invokevirtual #118                // Method java/lang/StringBuilder.append:(Ljava/lang/String;)Ljava/lang/StringBuilder;
     493: aload         5
     495: invokevirtual #499                // Method org/apache/hadoop/hbase/regionserver/compactions/CompactionRequestImpl.isMajor:()Z
     498: ifeq          507
     501: ldc_w         #607                // String major
     504: goto          510
     507: ldc_w         #608                // String minor
     510: invokevirtual #118                // Method java/lang/StringBuilder.append:(Ljava/lang/String;)Ljava/lang/StringBuilder;
     513: ldc_w         #609                // String  compaction
     516: invokevirtual #118                // Method java/lang/StringBuilder.append:(Ljava/lang/String;)Ljava/lang/StringBuilder;
     519: aload         5
     521: invokevirtual #532                // Method org/apache/hadoop/hbase/regionserver/compactions/CompactionRequestImpl.isAllFiles:()Z
     524: ifeq          533
     527: ldc_w         #610                // String  (all files)
     530: goto          536
     533: ldc_w         #424                // String
     536: invokevirtual #118                // Method java/lang/StringBuilder.append:(Ljava/lang/String;)Ljava/lang/StringBuilder;
     539: invokevirtual #120                // Method java/lang/StringBuilder.toString:()Ljava/lang/String;
     542: invokeinterface #318,  2          // InterfaceMethod org/slf4j/Logger.debug:(Ljava/lang/String;)V
     547: aload_0
     548: getfield      #40                 // Field region:Lorg/apache/hadoop/hbase/regionserver/HRegion;
     551: aload         5
     553: invokevirtual #499                // Method org/apache/hadoop/hbase/regionserver/compactions/CompactionRequestImpl.isMajor:()Z
     556: invokevirtual #611                // Method org/apache/hadoop/hbase/regionserver/HRegion.reportCompactionRequestStart:(Z)V
     559: aload         4
     561: invokestatic  #612                // Method java/util/Optional.of:(Ljava/lang/Object;)Ljava/util/Optional;
     564: areturn
    Exception table:
       from    to  target type
         144   182   185   Class java/io/IOException
          45   312   405   any
         325   402   405   any
         405   410   405   any
          37   312   426   any
         325   413   426   any
         426   428   426   any

  public void cancelRequestedCompaction(org.apache.hadoop.hbase.regionserver.compactions.CompactionContext);
    Code:
       0: aload_0
       1: aload_1
       2: invokevirtual #484                // Method org/apache/hadoop/hbase/regionserver/compactions/CompactionContext.getRequest:()Lorg/apache/hadoop/hbase/regionserver/compactions/CompactionRequestImpl;
       5: invokespecial #496                // Method finishCompactionRequest:(Lorg/apache/hadoop/hbase/regionserver/compactions/CompactionRequestImpl;)V
       8: return

  protected void completeCompaction(java.util.Collection<org.apache.hadoop.hbase.regionserver.HStoreFile>) throws java.io.IOException;
    Code:
       0: aload_0
       1: getfield      #2                  // Field storeSize:Ljava/util/concurrent/atomic/AtomicLong;
       4: lconst_0
       5: invokevirtual #628                // Method java/util/concurrent/atomic/AtomicLong.set:(J)V
       8: aload_0
       9: getfield      #1                  // Field totalUncompressedBytes:Ljava/util/concurrent/atomic/AtomicLong;
      12: lconst_0
      13: invokevirtual #628                // Method java/util/concurrent/atomic/AtomicLong.set:(J)V
      16: aload_0
      17: getfield      #97                 // Field storeEngine:Lorg/apache/hadoop/hbase/regionserver/StoreEngine;
      20: invokevirtual #103                // Method org/apache/hadoop/hbase/regionserver/StoreEngine.getStoreFileManager:()Lorg/apache/hadoop/hbase/regionserver/StoreFileManager;
      23: invokeinterface #251,  1          // InterfaceMethod org/apache/hadoop/hbase/regionserver/StoreFileManager.getStorefiles:()Ljava/util/Collection;
      28: invokeinterface #200,  1          // InterfaceMethod java/util/Collection.iterator:()Ljava/util/Iterator;
      33: astore_2
      34: aload_2
      35: invokeinterface #201,  1          // InterfaceMethod java/util/Iterator.hasNext:()Z
      40: ifeq          108
      43: aload_2
      44: invokeinterface #202,  1          // InterfaceMethod java/util/Iterator.next:()Ljava/lang/Object;
      49: checkcast     #213                // class org/apache/hadoop/hbase/regionserver/HStoreFile
      52: astore_3
      53: aload_3
      54: invokevirtual #239                // Method org/apache/hadoop/hbase/regionserver/HStoreFile.getReader:()Lorg/apache/hadoop/hbase/regionserver/StoreFileReader;
      57: astore        4
      59: aload         4
      61: ifnonnull     79
      64: getstatic     #9                  // Field LOG:Lorg/slf4j/Logger;
      67: ldc_w         #629                // String StoreFile {} has a null Reader
      70: aload_3
      71: invokeinterface #238,  3          // InterfaceMethod org/slf4j/Logger.warn:(Ljava/lang/String;Ljava/lang/Object;)V
      76: goto          34
      79: aload_0
      80: getfield      #2                  // Field storeSize:Ljava/util/concurrent/atomic/AtomicLong;
      83: aload         4
      85: invokevirtual #374                // Method org/apache/hadoop/hbase/regionserver/StoreFileReader.length:()J
      88: invokevirtual #101                // Method java/util/concurrent/atomic/AtomicLong.addAndGet:(J)J
      91: pop2
      92: aload_0
      93: getfield      #1                  // Field totalUncompressedBytes:Ljava/util/concurrent/atomic/AtomicLong;
      96: aload         4
      98: invokevirtual #375                // Method org/apache/hadoop/hbase/regionserver/StoreFileReader.getTotalUncompressedBytes:()J
     101: invokevirtual #101                // Method java/util/concurrent/atomic/AtomicLong.addAndGet:(J)J
     104: pop2
     105: goto          34
     108: return

  int versionsToReturn(int);
    Code:
       0: iload_1
       1: ifgt          15
       4: new           #114                // class java/lang/IllegalArgumentException
       7: dup
       8: ldc_w         #630                // String Number of versions must be > 0
      11: invokespecial #121                // Method java/lang/IllegalArgumentException."<init>":(Ljava/lang/String;)V
      14: athrow
      15: aload_0
      16: getfield      #41                 // Field family:Lorg/apache/hadoop/hbase/client/ColumnFamilyDescriptor;
      19: invokeinterface #631,  1          // InterfaceMethod org/apache/hadoop/hbase/client/ColumnFamilyDescriptor.getMaxVersions:()I
      24: istore_2
      25: iload_1
      26: iload_2
      27: if_icmple     34
      30: iload_2
      31: goto          35
      34: iload_1
      35: ireturn

  public boolean canSplit();
    Code:
       0: aload_0
       1: getfield      #18                 // Field lock:Ljava/util/concurrent/locks/ReentrantReadWriteLock;
       4: invokevirtual #287                // Method java/util/concurrent/locks/ReentrantReadWriteLock.readLock:()Ljava/util/concurrent/locks/ReentrantReadWriteLock$ReadLock;
       7: invokevirtual #288                // Method java/util/concurrent/locks/ReentrantReadWriteLock$ReadLock.lock:()V
      10: aload_0
      11: invokevirtual #632                // Method hasReferences:()Z
      14: ifne          21
      17: iconst_1
      18: goto          22
      21: iconst_0
      22: istore_1
      23: iload_1
      24: ifne          39
      27: getstatic     #9                  // Field LOG:Lorg/slf4j/Logger;
      30: ldc_w         #633                // String Not splittable; has references: {}
      33: aload_0
      34: invokeinterface #401,  3          // InterfaceMethod org/slf4j/Logger.trace:(Ljava/lang/String;Ljava/lang/Object;)V
      39: iload_1
      40: istore_2
      41: aload_0
      42: getfield      #18                 // Field lock:Ljava/util/concurrent/locks/ReentrantReadWriteLock;
      45: invokevirtual #287                // Method java/util/concurrent/locks/ReentrantReadWriteLock.readLock:()Ljava/util/concurrent/locks/ReentrantReadWriteLock$ReadLock;
      48: invokevirtual #292                // Method java/util/concurrent/locks/ReentrantReadWriteLock$ReadLock.unlock:()V
      51: iload_2
      52: ireturn
      53: astore_3
      54: aload_0
      55: getfield      #18                 // Field lock:Ljava/util/concurrent/locks/ReentrantReadWriteLock;
      58: invokevirtual #287                // Method java/util/concurrent/locks/ReentrantReadWriteLock.readLock:()Ljava/util/concurrent/locks/ReentrantReadWriteLock$ReadLock;
      61: invokevirtual #292                // Method java/util/concurrent/locks/ReentrantReadWriteLock$ReadLock.unlock:()V
      64: aload_3
      65: athrow
    Exception table:
       from    to  target type
          10    41    53   any

  public java.util.Optional<byte[]> getSplitPoint();
    Code:
       0: aload_0
       1: getfield      #18                 // Field lock:Ljava/util/concurrent/locks/ReentrantReadWriteLock;
       4: invokevirtual #287                // Method java/util/concurrent/locks/ReentrantReadWriteLock.readLock:()Ljava/util/concurrent/locks/ReentrantReadWriteLock$ReadLock;
       7: invokevirtual #288                // Method java/util/concurrent/locks/ReentrantReadWriteLock$ReadLock.lock:()V
      10: getstatic     #481                // Field $assertionsDisabled:Z
      13: ifne          36
      16: aload_0
      17: invokevirtual #167                // Method getRegionInfo:()Lorg/apache/hadoop/hbase/client/RegionInfo;
      20: invokeinterface #634,  1          // InterfaceMethod org/apache/hadoop/hbase/client/RegionInfo.isMetaRegion:()Z
      25: ifeq          36
      28: new           #482                // class java/lang/AssertionError
      31: dup
      32: invokespecial #483                // Method java/lang/AssertionError."<init>":()V
      35: athrow
      36: aload_0
      37: invokevirtual #632                // Method hasReferences:()Z
      40: ifeq          71
      43: getstatic     #9                  // Field LOG:Lorg/slf4j/Logger;
      46: ldc_w         #633                // String Not splittable; has references: {}
      49: aload_0
      50: invokeinterface #401,  3          // InterfaceMethod org/slf4j/Logger.trace:(Ljava/lang/String;Ljava/lang/Object;)V
      55: invokestatic  #584                // Method java/util/Optional.empty:()Ljava/util/Optional;
      58: astore_1
      59: aload_0
      60: getfield      #18                 // Field lock:Ljava/util/concurrent/locks/ReentrantReadWriteLock;
      63: invokevirtual #287                // Method java/util/concurrent/locks/ReentrantReadWriteLock.readLock:()Ljava/util/concurrent/locks/ReentrantReadWriteLock$ReadLock;
      66: invokevirtual #292                // Method java/util/concurrent/locks/ReentrantReadWriteLock$ReadLock.unlock:()V
      69: aload_1
      70: areturn
      71: aload_0
      72: getfield      #97                 // Field storeEngine:Lorg/apache/hadoop/hbase/regionserver/StoreEngine;
      75: invokevirtual #103                // Method org/apache/hadoop/hbase/regionserver/StoreEngine.getStoreFileManager:()Lorg/apache/hadoop/hbase/regionserver/StoreFileManager;
      78: invokeinterface #635,  1          // InterfaceMethod org/apache/hadoop/hbase/regionserver/StoreFileManager.getSplitPoint:()Ljava/util/Optional;
      83: astore_1
      84: aload_0
      85: getfield      #18                 // Field lock:Ljava/util/concurrent/locks/ReentrantReadWriteLock;
      88: invokevirtual #287                // Method java/util/concurrent/locks/ReentrantReadWriteLock.readLock:()Ljava/util/concurrent/locks/ReentrantReadWriteLock$ReadLock;
      91: invokevirtual #292                // Method java/util/concurrent/locks/ReentrantReadWriteLock$ReadLock.unlock:()V
      94: aload_1
      95: areturn
      96: astore_1
      97: getstatic     #9                  // Field LOG:Lorg/slf4j/Logger;
     100: ldc_w         #636                // String Failed getting store size for {}
     103: aload_0
     104: aload_1
     105: invokeinterface #412,  4          // InterfaceMethod org/slf4j/Logger.warn:(Ljava/lang/String;Ljava/lang/Object;Ljava/lang/Object;)V
     110: aload_0
     111: getfield      #18                 // Field lock:Ljava/util/concurrent/locks/ReentrantReadWriteLock;
     114: invokevirtual #287                // Method java/util/concurrent/locks/ReentrantReadWriteLock.readLock:()Ljava/util/concurrent/locks/ReentrantReadWriteLock$ReadLock;
     117: invokevirtual #292                // Method java/util/concurrent/locks/ReentrantReadWriteLock$ReadLock.unlock:()V
     120: goto          136
     123: astore_2
     124: aload_0
     125: getfield      #18                 // Field lock:Ljava/util/concurrent/locks/ReentrantReadWriteLock;
     128: invokevirtual #287                // Method java/util/concurrent/locks/ReentrantReadWriteLock.readLock:()Ljava/util/concurrent/locks/ReentrantReadWriteLock$ReadLock;
     131: invokevirtual #292                // Method java/util/concurrent/locks/ReentrantReadWriteLock$ReadLock.unlock:()V
     134: aload_2
     135: athrow
     136: invokestatic  #584                // Method java/util/Optional.empty:()Ljava/util/Optional;
     139: areturn
    Exception table:
       from    to  target type
          10    59    96   Class java/io/IOException
          71    84    96   Class java/io/IOException
          10    59   123   any
          71    84   123   any
          96   110   123   any

  public long getLastCompactSize();
    Code:
       0: aload_0
       1: getfield      #12                 // Field lastCompactSize:J
       4: lreturn

  public long getSize();
    Code:
       0: aload_0
       1: getfield      #2                  // Field storeSize:Ljava/util/concurrent/atomic/AtomicLong;
       4: invokevirtual #543                // Method java/util/concurrent/atomic/AtomicLong.get:()J
       7: lreturn

  public void triggerMajorCompaction();
    Code:
       0: aload_0
       1: iconst_1
       2: putfield      #13                 // Field forceMajor:Z
       5: return

  public org.apache.hadoop.hbase.regionserver.KeyValueScanner getScanner(org.apache.hadoop.hbase.client.Scan, java.util.NavigableSet<byte[]>, long) throws java.io.IOException;
    Code:
       0: aload_0
       1: getfield      #18                 // Field lock:Ljava/util/concurrent/locks/ReentrantReadWriteLock;
       4: invokevirtual #287                // Method java/util/concurrent/locks/ReentrantReadWriteLock.readLock:()Ljava/util/concurrent/locks/ReentrantReadWriteLock$ReadLock;
       7: invokevirtual #288                // Method java/util/concurrent/locks/ReentrantReadWriteLock$ReadLock.lock:()V
      10: aload_0
      11: invokevirtual #365                // Method getCoprocessorHost:()Lorg/apache/hadoop/hbase/regionserver/RegionCoprocessorHost;
      14: ifnull        30
      17: aload_0
      18: invokevirtual #365                // Method getCoprocessorHost:()Lorg/apache/hadoop/hbase/regionserver/RegionCoprocessorHost;
      21: aload_0
      22: invokevirtual #637                // Method org/apache/hadoop/hbase/regionserver/RegionCoprocessorHost.preStoreScannerOpen:(Lorg/apache/hadoop/hbase/regionserver/HStore;)Lorg/apache/hadoop/hbase/regionserver/ScanInfo;
      25: astore        5
      27: goto          36
      30: aload_0
      31: invokevirtual #638                // Method getScanInfo:()Lorg/apache/hadoop/hbase/regionserver/ScanInfo;
      34: astore        5
      36: aload_0
      37: aload_1
      38: aload         5
      40: aload_2
      41: lload_3
      42: invokevirtual #639                // Method createScanner:(Lorg/apache/hadoop/hbase/client/Scan;Lorg/apache/hadoop/hbase/regionserver/ScanInfo;Ljava/util/NavigableSet;J)Lorg/apache/hadoop/hbase/regionserver/KeyValueScanner;
      45: astore        6
      47: aload_0
      48: getfield      #18                 // Field lock:Ljava/util/concurrent/locks/ReentrantReadWriteLock;
      51: invokevirtual #287                // Method java/util/concurrent/locks/ReentrantReadWriteLock.readLock:()Ljava/util/concurrent/locks/ReentrantReadWriteLock$ReadLock;
      54: invokevirtual #292                // Method java/util/concurrent/locks/ReentrantReadWriteLock$ReadLock.unlock:()V
      57: aload         6
      59: areturn
      60: astore        7
      62: aload_0
      63: getfield      #18                 // Field lock:Ljava/util/concurrent/locks/ReentrantReadWriteLock;
      66: invokevirtual #287                // Method java/util/concurrent/locks/ReentrantReadWriteLock.readLock:()Ljava/util/concurrent/locks/ReentrantReadWriteLock$ReadLock;
      69: invokevirtual #292                // Method java/util/concurrent/locks/ReentrantReadWriteLock$ReadLock.unlock:()V
      72: aload         7
      74: athrow
    Exception table:
       from    to  target type
          10    47    60   any
          60    62    60   any

  protected org.apache.hadoop.hbase.regionserver.KeyValueScanner createScanner(org.apache.hadoop.hbase.client.Scan, org.apache.hadoop.hbase.regionserver.ScanInfo, java.util.NavigableSet<byte[]>, long) throws java.io.IOException;
    Code:
       0: aload_1
       1: invokevirtual #640                // Method org/apache/hadoop/hbase/client/Scan.isReversed:()Z
       4: ifeq          23
       7: new           #641                // class org/apache/hadoop/hbase/regionserver/ReversedStoreScanner
      10: dup
      11: aload_0
      12: aload_2
      13: aload_1
      14: aload_3
      15: lload         4
      17: invokespecial #642                // Method org/apache/hadoop/hbase/regionserver/ReversedStoreScanner."<init>":(Lorg/apache/hadoop/hbase/regionserver/HStore;Lorg/apache/hadoop/hbase/regionserver/ScanInfo;Lorg/apache/hadoop/hbase/client/Scan;Ljava/util/NavigableSet;J)V
      20: goto          36
      23: new           #643                // class org/apache/hadoop/hbase/regionserver/StoreScanner
      26: dup
      27: aload_0
      28: aload_2
      29: aload_1
      30: aload_3
      31: lload         4
      33: invokespecial #644                // Method org/apache/hadoop/hbase/regionserver/StoreScanner."<init>":(Lorg/apache/hadoop/hbase/regionserver/HStore;Lorg/apache/hadoop/hbase/regionserver/ScanInfo;Lorg/apache/hadoop/hbase/client/Scan;Ljava/util/NavigableSet;J)V
      36: areturn

  public java.util.List<org.apache.hadoop.hbase.regionserver.KeyValueScanner> recreateScanners(java.util.List<org.apache.hadoop.hbase.regionserver.KeyValueScanner>, boolean, boolean, boolean, org.apache.hadoop.hbase.regionserver.querymatcher.ScanQueryMatcher, byte[], boolean, byte[], boolean, long, boolean) throws java.io.IOException;
    Code:
       0: aload_0
       1: getfield      #18                 // Field lock:Ljava/util/concurrent/locks/ReentrantReadWriteLock;
       4: invokevirtual #287                // Method java/util/concurrent/locks/ReentrantReadWriteLock.readLock:()Ljava/util/concurrent/locks/ReentrantReadWriteLock$ReadLock;
       7: invokevirtual #288                // Method java/util/concurrent/locks/ReentrantReadWriteLock$ReadLock.lock:()V
      10: new           #254                // class java/util/HashMap
      13: dup
      14: aload_0
      15: invokevirtual #645                // Method getStorefilesCount:()I
      18: aload_0
      19: invokevirtual #646                // Method getCompactedFilesCount:()I
      22: iadd
      23: invokespecial #255                // Method java/util/HashMap."<init>":(I)V
      26: astore        13
      28: aload_0
      29: invokevirtual #181                // Method getStorefiles:()Ljava/util/Collection;
      32: invokeinterface #200,  1          // InterfaceMethod java/util/Collection.iterator:()Ljava/util/Iterator;
      37: astore        14
      39: aload         14
      41: invokeinterface #201,  1          // InterfaceMethod java/util/Iterator.hasNext:()Z
      46: ifeq          82
      49: aload         14
      51: invokeinterface #202,  1          // InterfaceMethod java/util/Iterator.next:()Ljava/lang/Object;
      56: checkcast     #213                // class org/apache/hadoop/hbase/regionserver/HStoreFile
      59: astore        15
      61: aload         13
      63: aload         15
      65: invokevirtual #256                // Method org/apache/hadoop/hbase/regionserver/HStoreFile.getFileInfo:()Lorg/apache/hadoop/hbase/regionserver/StoreFileInfo;
      68: invokevirtual #647                // Method org/apache/hadoop/hbase/regionserver/StoreFileInfo.getActiveFileName:()Ljava/lang/String;
      71: aload         15
      73: invokeinterface #648,  3          // InterfaceMethod java/util/Map.put:(Ljava/lang/Object;Ljava/lang/Object;)Ljava/lang/Object;
      78: pop
      79: goto          39
      82: aload_0
      83: invokevirtual #572                // Method getCompactedFiles:()Ljava/util/Collection;
      86: astore        14
      88: aload         14
      90: invokestatic  #649                // Method org/apache/hbase/thirdparty/org/apache/commons/collections4/IterableUtils.emptyIfNull:(Ljava/lang/Iterable;)Ljava/lang/Iterable;
      93: invokeinterface #650,  1          // InterfaceMethod java/lang/Iterable.iterator:()Ljava/util/Iterator;
      98: astore        15
     100: aload         15
     102: invokeinterface #201,  1          // InterfaceMethod java/util/Iterator.hasNext:()Z
     107: ifeq          143
     110: aload         15
     112: invokeinterface #202,  1          // InterfaceMethod java/util/Iterator.next:()Ljava/lang/Object;
     117: checkcast     #213                // class org/apache/hadoop/hbase/regionserver/HStoreFile
     120: astore        16
     122: aload         13
     124: aload         16
     126: invokevirtual #256                // Method org/apache/hadoop/hbase/regionserver/HStoreFile.getFileInfo:()Lorg/apache/hadoop/hbase/regionserver/StoreFileInfo;
     129: invokevirtual #647                // Method org/apache/hadoop/hbase/regionserver/StoreFileInfo.getActiveFileName:()Ljava/lang/String;
     132: aload         16
     134: invokeinterface #648,  3          // InterfaceMethod java/util/Map.put:(Ljava/lang/Object;Ljava/lang/Object;)Ljava/lang/Object;
     139: pop
     140: goto          100
     143: new           #208                // class java/util/ArrayList
     146: dup
     147: invokespecial #651                // Method java/util/ArrayList."<init>":()V
     150: astore        15
     152: aload_1
     153: invokeinterface #406,  1          // InterfaceMethod java/util/List.iterator:()Ljava/util/Iterator;
     158: astore        16
     160: aload         16
     162: invokeinterface #201,  1          // InterfaceMethod java/util/Iterator.hasNext:()Z
     167: ifeq          247
     170: aload         16
     172: invokeinterface #202,  1          // InterfaceMethod java/util/Iterator.next:()Ljava/lang/Object;
     177: checkcast     #652                // class org/apache/hadoop/hbase/regionserver/KeyValueScanner
     180: astore        17
     182: getstatic     #481                // Field $assertionsDisabled:Z
     185: ifne          206
     188: aload         17
     190: invokeinterface #653,  1          // InterfaceMethod org/apache/hadoop/hbase/regionserver/KeyValueScanner.isFileScanner:()Z
     195: ifne          206
     198: new           #482                // class java/lang/AssertionError
     201: dup
     202: invokespecial #483                // Method java/lang/AssertionError."<init>":()V
     205: athrow
     206: aload         17
     208: invokeinterface #654,  1          // InterfaceMethod org/apache/hadoop/hbase/regionserver/KeyValueScanner.peek:()Lorg/apache/hadoop/hbase/Cell;
     213: ifnonnull     219
     216: goto          160
     219: aload         15
     221: aload         13
     223: aload         17
     225: invokeinterface #655,  1          // InterfaceMethod org/apache/hadoop/hbase/regionserver/KeyValueScanner.getFilePath:()Lorg/apache/hadoop/fs/Path;
     230: invokevirtual #235                // Method org/apache/hadoop/fs/Path.getName:()Ljava/lang/String;
     233: invokeinterface #656,  2          // InterfaceMethod java/util/Map.get:(Ljava/lang/Object;)Ljava/lang/Object;
     238: invokeinterface #241,  2          // InterfaceMethod java/util/List.add:(Ljava/lang/Object;)Z
     243: pop
     244: goto          160
     247: aload         15
     249: invokeinterface #243,  1          // InterfaceMethod java/util/List.isEmpty:()Z
     254: ifeq          273
     257: aconst_null
     258: astore        16
     260: aload_0
     261: getfield      #18                 // Field lock:Ljava/util/concurrent/locks/ReentrantReadWriteLock;
     264: invokevirtual #287                // Method java/util/concurrent/locks/ReentrantReadWriteLock.readLock:()Ljava/util/concurrent/locks/ReentrantReadWriteLock$ReadLock;
     267: invokevirtual #292                // Method java/util/concurrent/locks/ReentrantReadWriteLock$ReadLock.unlock:()V
     270: aload         16
     272: areturn
     273: aload_0
     274: aload         15
     276: iload_2
     277: iconst_0
     278: iconst_0
     279: aload         5
     281: aload         6
     283: iload         7
     285: aload         8
     287: iload         9
     289: lload         10
     291: iconst_0
     292: invokevirtual #479                // Method getScanners:(Ljava/util/List;ZZZLorg/apache/hadoop/hbase/regionserver/querymatcher/ScanQueryMatcher;[BZ[BZJZ)Ljava/util/List;
     295: astore        16
     297: aload_0
     298: getfield      #18                 // Field lock:Ljava/util/concurrent/locks/ReentrantReadWriteLock;
     301: invokevirtual #287                // Method java/util/concurrent/locks/ReentrantReadWriteLock.readLock:()Ljava/util/concurrent/locks/ReentrantReadWriteLock$ReadLock;
     304: invokevirtual #292                // Method java/util/concurrent/locks/ReentrantReadWriteLock$ReadLock.unlock:()V
     307: aload         16
     309: areturn
     310: astore        18
     312: aload_0
     313: getfield      #18                 // Field lock:Ljava/util/concurrent/locks/ReentrantReadWriteLock;
     316: invokevirtual #287                // Method java/util/concurrent/locks/ReentrantReadWriteLock.readLock:()Ljava/util/concurrent/locks/ReentrantReadWriteLock$ReadLock;
     319: invokevirtual #292                // Method java/util/concurrent/locks/ReentrantReadWriteLock$ReadLock.unlock:()V
     322: aload         18
     324: athrow
    Exception table:
       from    to  target type
          10   260   310   any
         273   297   310   any
         310   312   310   any

  public java.lang.String toString();
    Code:
       0: aload_0
       1: invokevirtual #127                // Method getColumnFamilyName:()Ljava/lang/String;
       4: areturn

  public int getStorefilesCount();
    Code:
       0: aload_0
       1: getfield      #97                 // Field storeEngine:Lorg/apache/hadoop/hbase/regionserver/StoreEngine;
       4: invokevirtual #103                // Method org/apache/hadoop/hbase/regionserver/StoreEngine.getStoreFileManager:()Lorg/apache/hadoop/hbase/regionserver/StoreFileManager;
       7: invokeinterface #384,  1          // InterfaceMethod org/apache/hadoop/hbase/regionserver/StoreFileManager.getStorefileCount:()I
      12: ireturn

  public int getCompactedFilesCount();
    Code:
       0: aload_0
       1: getfield      #97                 // Field storeEngine:Lorg/apache/hadoop/hbase/regionserver/StoreEngine;
       4: invokevirtual #103                // Method org/apache/hadoop/hbase/regionserver/StoreEngine.getStoreFileManager:()Lorg/apache/hadoop/hbase/regionserver/StoreFileManager;
       7: invokeinterface #657,  1          // InterfaceMethod org/apache/hadoop/hbase/regionserver/StoreFileManager.getCompactedFilesCount:()I
      12: ireturn

  public java.util.OptionalLong getMaxStoreFileAge();
    Code:
       0: aload_0
       1: invokespecial #664                // Method getStoreFileAgeStream:()Ljava/util/stream/LongStream;
       4: invokeinterface #665,  1          // InterfaceMethod java/util/stream/LongStream.max:()Ljava/util/OptionalLong;
       9: areturn

  public java.util.OptionalLong getMinStoreFileAge();
    Code:
       0: aload_0
       1: invokespecial #664                // Method getStoreFileAgeStream:()Ljava/util/stream/LongStream;
       4: invokeinterface #666,  1          // InterfaceMethod java/util/stream/LongStream.min:()Ljava/util/OptionalLong;
       9: areturn

  public java.util.OptionalDouble getAvgStoreFileAge();
    Code:
       0: aload_0
       1: invokespecial #664                // Method getStoreFileAgeStream:()Ljava/util/stream/LongStream;
       4: invokeinterface #667,  1          // InterfaceMethod java/util/stream/LongStream.average:()Ljava/util/OptionalDouble;
       9: areturn

  public long getNumReferenceFiles();
    Code:
       0: aload_0
       1: getfield      #97                 // Field storeEngine:Lorg/apache/hadoop/hbase/regionserver/StoreEngine;
       4: invokevirtual #103                // Method org/apache/hadoop/hbase/regionserver/StoreEngine.getStoreFileManager:()Lorg/apache/hadoop/hbase/regionserver/StoreFileManager;
       7: invokeinterface #251,  1          // InterfaceMethod org/apache/hadoop/hbase/regionserver/StoreFileManager.getStorefiles:()Ljava/util/Collection;
      12: invokeinterface #461,  1          // InterfaceMethod java/util/Collection.stream:()Ljava/util/stream/Stream;
      17: invokedynamic #668,  0            // InvokeDynamic #9:test:()Ljava/util/function/Predicate;
      22: invokeinterface #659,  2          // InterfaceMethod java/util/stream/Stream.filter:(Ljava/util/function/Predicate;)Ljava/util/stream/Stream;
      27: invokeinterface #669,  1          // InterfaceMethod java/util/stream/Stream.count:()J
      32: lreturn

  public long getNumHFiles();
    Code:
       0: aload_0
       1: getfield      #97                 // Field storeEngine:Lorg/apache/hadoop/hbase/regionserver/StoreEngine;
       4: invokevirtual #103                // Method org/apache/hadoop/hbase/regionserver/StoreEngine.getStoreFileManager:()Lorg/apache/hadoop/hbase/regionserver/StoreFileManager;
       7: invokeinterface #251,  1          // InterfaceMethod org/apache/hadoop/hbase/regionserver/StoreFileManager.getStorefiles:()Ljava/util/Collection;
      12: invokeinterface #461,  1          // InterfaceMethod java/util/Collection.stream:()Ljava/util/stream/Stream;
      17: invokedynamic #660,  0            // InvokeDynamic #6:test:()Ljava/util/function/Predicate;
      22: invokeinterface #659,  2          // InterfaceMethod java/util/stream/Stream.filter:(Ljava/util/function/Predicate;)Ljava/util/stream/Stream;
      27: invokeinterface #669,  1          // InterfaceMethod java/util/stream/Stream.count:()J
      32: lreturn

  public long getStoreSizeUncompressed();
    Code:
       0: aload_0
       1: getfield      #1                  // Field totalUncompressedBytes:Ljava/util/concurrent/atomic/AtomicLong;
       4: invokevirtual #543                // Method java/util/concurrent/atomic/AtomicLong.get:()J
       7: lreturn

  public long getStorefilesSize();
    Code:
       0: aload_0
       1: aload_0
       2: getfield      #97                 // Field storeEngine:Lorg/apache/hadoop/hbase/regionserver/StoreEngine;
       5: invokevirtual #103                // Method org/apache/hadoop/hbase/regionserver/StoreEngine.getStoreFileManager:()Lorg/apache/hadoop/hbase/regionserver/StoreFileManager;
       8: invokeinterface #251,  1          // InterfaceMethod org/apache/hadoop/hbase/regionserver/StoreFileManager.getStorefiles:()Ljava/util/Collection;
      13: invokedynamic #670,  0            // InvokeDynamic #10:test:()Ljava/util/function/Predicate;
      18: invokespecial #100                // Method getStorefilesSize:(Ljava/util/Collection;Ljava/util/function/Predicate;)J
      21: lreturn

  public long getHFilesSize();
    Code:
       0: aload_0
       1: aload_0
       2: getfield      #97                 // Field storeEngine:Lorg/apache/hadoop/hbase/regionserver/StoreEngine;
       5: invokevirtual #103                // Method org/apache/hadoop/hbase/regionserver/StoreEngine.getStoreFileManager:()Lorg/apache/hadoop/hbase/regionserver/StoreFileManager;
       8: invokeinterface #251,  1          // InterfaceMethod org/apache/hadoop/hbase/regionserver/StoreFileManager.getStorefiles:()Ljava/util/Collection;
      13: invokedynamic #660,  0            // InvokeDynamic #6:test:()Ljava/util/function/Predicate;
      18: invokespecial #100                // Method getStorefilesSize:(Ljava/util/Collection;Ljava/util/function/Predicate;)J
      21: lreturn

  public long getStorefilesRootLevelIndexSize();
    Code:
       0: aload_0
       1: invokedynamic #678,  0            // InvokeDynamic #17:applyAsLong:()Ljava/util/function/ToLongFunction;
       6: invokespecial #679                // Method getStoreFileFieldSize:(Ljava/util/function/ToLongFunction;)J
       9: lreturn

  public long getTotalStaticIndexSize();
    Code:
       0: aload_0
       1: invokedynamic #680,  0            // InvokeDynamic #18:applyAsLong:()Ljava/util/function/ToLongFunction;
       6: invokespecial #679                // Method getStoreFileFieldSize:(Ljava/util/function/ToLongFunction;)J
       9: lreturn

  public long getTotalStaticBloomSize();
    Code:
       0: aload_0
       1: invokedynamic #681,  0            // InvokeDynamic #19:applyAsLong:()Ljava/util/function/ToLongFunction;
       6: invokespecial #679                // Method getStoreFileFieldSize:(Ljava/util/function/ToLongFunction;)J
       9: lreturn

  public org.apache.hadoop.hbase.regionserver.MemStoreSize getMemStoreSize();
    Code:
       0: aload_0
       1: getfield      #78                 // Field memstore:Lorg/apache/hadoop/hbase/regionserver/MemStore;
       4: invokeinterface #682,  1          // InterfaceMethod org/apache/hadoop/hbase/regionserver/MemStore.size:()Lorg/apache/hadoop/hbase/regionserver/MemStoreSize;
       9: areturn

  public int getCompactPriority();
    Code:
       0: aload_0
       1: getfield      #97                 // Field storeEngine:Lorg/apache/hadoop/hbase/regionserver/StoreEngine;
       4: invokevirtual #103                // Method org/apache/hadoop/hbase/regionserver/StoreEngine.getStoreFileManager:()Lorg/apache/hadoop/hbase/regionserver/StoreFileManager;
       7: invokeinterface #683,  1          // InterfaceMethod org/apache/hadoop/hbase/regionserver/StoreFileManager.getStoreCompactionPriority:()I
      12: istore_1
      13: iload_1
      14: iconst_1
      15: if_icmpne     29
      18: getstatic     #9                  // Field LOG:Lorg/slf4j/Logger;
      21: ldc_w         #684                // String Compaction priority is USER despite there being no user compaction
      24: invokeinterface #336,  2          // InterfaceMethod org/slf4j/Logger.warn:(Ljava/lang/String;)V
      29: iload_1
      30: ireturn

  public boolean throttleCompaction(long);
    Code:
       0: aload_0
       1: getfield      #97                 // Field storeEngine:Lorg/apache/hadoop/hbase/regionserver/StoreEngine;
       4: invokevirtual #577                // Method org/apache/hadoop/hbase/regionserver/StoreEngine.getCompactionPolicy:()Lorg/apache/hadoop/hbase/regionserver/compactions/CompactionPolicy;
       7: lload_1
       8: invokevirtual #685                // Method org/apache/hadoop/hbase/regionserver/compactions/CompactionPolicy.throttleCompaction:(J)Z
      11: ireturn

  public org.apache.hadoop.hbase.regionserver.HRegion getHRegion();
    Code:
       0: aload_0
       1: getfield      #40                 // Field region:Lorg/apache/hadoop/hbase/regionserver/HRegion;
       4: areturn

  public org.apache.hadoop.hbase.regionserver.RegionCoprocessorHost getCoprocessorHost();
    Code:
       0: aload_0
       1: getfield      #40                 // Field region:Lorg/apache/hadoop/hbase/regionserver/HRegion;
       4: invokevirtual #280                // Method org/apache/hadoop/hbase/regionserver/HRegion.getCoprocessorHost:()Lorg/apache/hadoop/hbase/regionserver/RegionCoprocessorHost;
       7: areturn

  public org.apache.hadoop.hbase.client.RegionInfo getRegionInfo();
    Code:
       0: aload_0
       1: getfield      #4                  // Field fs:Lorg/apache/hadoop/hbase/regionserver/HRegionFileSystem;
       4: invokevirtual #686                // Method org/apache/hadoop/hbase/regionserver/HRegionFileSystem.getRegionInfo:()Lorg/apache/hadoop/hbase/client/RegionInfo;
       7: areturn

  public boolean areWritesEnabled();
    Code:
       0: aload_0
       1: getfield      #40                 // Field region:Lorg/apache/hadoop/hbase/regionserver/HRegion;
       4: invokevirtual #687                // Method org/apache/hadoop/hbase/regionserver/HRegion.areWritesEnabled:()Z
       7: ireturn

  public long getSmallestReadPoint();
    Code:
       0: aload_0
       1: getfield      #40                 // Field region:Lorg/apache/hadoop/hbase/regionserver/HRegion;
       4: invokevirtual #688                // Method org/apache/hadoop/hbase/regionserver/HRegion.getSmallestReadPoint:()J
       7: lreturn

  public void upsert(java.lang.Iterable<org.apache.hadoop.hbase.Cell>, long, org.apache.hadoop.hbase.regionserver.MemStoreSizing) throws java.io.IOException;
    Code:
       0: aload_0
       1: getfield      #18                 // Field lock:Ljava/util/concurrent/locks/ReentrantReadWriteLock;
       4: invokevirtual #287                // Method java/util/concurrent/locks/ReentrantReadWriteLock.readLock:()Ljava/util/concurrent/locks/ReentrantReadWriteLock$ReadLock;
       7: invokevirtual #288                // Method java/util/concurrent/locks/ReentrantReadWriteLock$ReadLock.lock:()V
      10: aload_0
      11: getfield      #78                 // Field memstore:Lorg/apache/hadoop/hbase/regionserver/MemStore;
      14: aload_1
      15: lload_2
      16: aload         4
      18: invokeinterface #689,  5          // InterfaceMethod org/apache/hadoop/hbase/regionserver/MemStore.upsert:(Ljava/lang/Iterable;JLorg/apache/hadoop/hbase/regionserver/MemStoreSizing;)V
      23: aload_0
      24: getfield      #18                 // Field lock:Ljava/util/concurrent/locks/ReentrantReadWriteLock;
      27: invokevirtual #287                // Method java/util/concurrent/locks/ReentrantReadWriteLock.readLock:()Ljava/util/concurrent/locks/ReentrantReadWriteLock$ReadLock;
      30: invokevirtual #292                // Method java/util/concurrent/locks/ReentrantReadWriteLock$ReadLock.unlock:()V
      33: goto          51
      36: astore        5
      38: aload_0
      39: getfield      #18                 // Field lock:Ljava/util/concurrent/locks/ReentrantReadWriteLock;
      42: invokevirtual #287                // Method java/util/concurrent/locks/ReentrantReadWriteLock.readLock:()Ljava/util/concurrent/locks/ReentrantReadWriteLock$ReadLock;
      45: invokevirtual #292                // Method java/util/concurrent/locks/ReentrantReadWriteLock$ReadLock.unlock:()V
      48: aload         5
      50: athrow
      51: return
    Exception table:
       from    to  target type
          10    23    36   any
          36    38    36   any

  public org.apache.hadoop.hbase.regionserver.StoreFlushContext createFlushContext(long, org.apache.hadoop.hbase.regionserver.FlushLifeCycleTracker);
    Code:
       0: new           #690                // class org/apache/hadoop/hbase/regionserver/HStore$StoreFlusherImpl
       3: dup
       4: aload_0
       5: lload_1
       6: aload_3
       7: aconst_null
       8: invokespecial #691                // Method org/apache/hadoop/hbase/regionserver/HStore$StoreFlusherImpl."<init>":(Lorg/apache/hadoop/hbase/regionserver/HStore;JLorg/apache/hadoop/hbase/regionserver/FlushLifeCycleTracker;Lorg/apache/hadoop/hbase/regionserver/HStore$1;)V
      11: areturn

  public boolean needsCompaction();
    Code:
       0: aconst_null
       1: astore_1
       2: aload_0
       3: getfield      #26                 // Field filesCompacting:Ljava/util/List;
       6: dup
       7: astore_2
       8: monitorenter
       9: aload_0
      10: getfield      #26                 // Field filesCompacting:Ljava/util/List;
      13: invokestatic  #553                // Method org/apache/hbase/thirdparty/com/google/common/collect/Lists.newArrayList:(Ljava/lang/Iterable;)Ljava/util/ArrayList;
      16: astore_1
      17: aload_2
      18: monitorexit
      19: goto          27
      22: astore_3
      23: aload_2
      24: monitorexit
      25: aload_3
      26: athrow
      27: aload_0
      28: getfield      #97                 // Field storeEngine:Lorg/apache/hadoop/hbase/regionserver/StoreEngine;
      31: aload_1
      32: invokevirtual #692                // Method org/apache/hadoop/hbase/regionserver/StoreEngine.needsCompaction:(Ljava/util/List;)Z
      35: ireturn
    Exception table:
       from    to  target type
           9    19    22   any
          22    25    22   any

  public org.apache.hadoop.hbase.io.hfile.CacheConfig getCacheConfig();
    Code:
       0: aload_0
       1: getfield      #155                // Field cacheConf:Lorg/apache/hadoop/hbase/io/hfile/CacheConfig;
       4: areturn

  public long heapSize();
    Code:
       0: aload_0
       1: getfield      #78                 // Field memstore:Lorg/apache/hadoop/hbase/regionserver/MemStore;
       4: invokeinterface #682,  1          // InterfaceMethod org/apache/hadoop/hbase/regionserver/MemStore.size:()Lorg/apache/hadoop/hbase/regionserver/MemStoreSize;
       9: astore_1
      10: getstatic     #693                // Field DEEP_OVERHEAD:J
      13: aload_1
      14: invokevirtual #694                // Method org/apache/hadoop/hbase/regionserver/MemStoreSize.getHeapSize:()J
      17: ladd
      18: lreturn

  public org.apache.hadoop.hbase.CellComparator getComparator();
    Code:
       0: aload_0
       1: getfield      #66                 // Field comparator:Lorg/apache/hadoop/hbase/CellComparator;
       4: areturn

  public org.apache.hadoop.hbase.regionserver.ScanInfo getScanInfo();
    Code:
       0: aload_0
       1: getfield      #76                 // Field scanInfo:Lorg/apache/hadoop/hbase/regionserver/ScanInfo;
       4: areturn

  void setScanInfo(org.apache.hadoop.hbase.regionserver.ScanInfo);
    Code:
       0: aload_0
       1: aload_1
       2: putfield      #76                 // Field scanInfo:Lorg/apache/hadoop/hbase/regionserver/ScanInfo;
       5: return

  public boolean hasTooManyStoreFiles();
    Code:
       0: aload_0
       1: invokevirtual #645                // Method getStorefilesCount:()I
       4: i2l
       5: aload_0
       6: getfield      #87                 // Field blockingFileCount:J
       9: lcmp
      10: ifle          17
      13: iconst_1
      14: goto          18
      17: iconst_0
      18: ireturn

  public long getFlushedCellsCount();
    Code:
       0: aload_0
       1: getfield      #8                  // Field flushedCellsCount:Ljava/util/concurrent/atomic/AtomicLong;
       4: invokevirtual #543                // Method java/util/concurrent/atomic/AtomicLong.get:()J
       7: lreturn

  public long getFlushedCellsSize();
    Code:
       0: aload_0
       1: getfield      #7                  // Field flushedCellsSize:Ljava/util/concurrent/atomic/AtomicLong;
       4: invokevirtual #543                // Method java/util/concurrent/atomic/AtomicLong.get:()J
       7: lreturn

  public long getFlushedOutputFileSize();
    Code:
       0: aload_0
       1: getfield      #6                  // Field flushedOutputFileSize:Ljava/util/concurrent/atomic/AtomicLong;
       4: invokevirtual #543                // Method java/util/concurrent/atomic/AtomicLong.get:()J
       7: lreturn

  public long getCompactedCellsCount();
    Code:
       0: aload_0
       1: getfield      #33                 // Field compactedCellsCount:Ljava/util/concurrent/atomic/AtomicLong;
       4: invokevirtual #543                // Method java/util/concurrent/atomic/AtomicLong.get:()J
       7: lreturn

  public long getCompactedCellsSize();
    Code:
       0: aload_0
       1: getfield      #35                 // Field compactedCellsSize:Ljava/util/concurrent/atomic/AtomicLong;
       4: invokevirtual #543                // Method java/util/concurrent/atomic/AtomicLong.get:()J
       7: lreturn

  public long getMajorCompactedCellsCount();
    Code:
       0: aload_0
       1: getfield      #34                 // Field majorCompactedCellsCount:Ljava/util/concurrent/atomic/AtomicLong;
       4: invokevirtual #543                // Method java/util/concurrent/atomic/AtomicLong.get:()J
       7: lreturn

  public long getMajorCompactedCellsSize();
    Code:
       0: aload_0
       1: getfield      #36                 // Field majorCompactedCellsSize:Ljava/util/concurrent/atomic/AtomicLong;
       4: invokevirtual #543                // Method java/util/concurrent/atomic/AtomicLong.get:()J
       7: lreturn

  public org.apache.hadoop.hbase.regionserver.StoreEngine<?, ?, ?, ?> getStoreEngine();
    Code:
       0: aload_0
       1: getfield      #97                 // Field storeEngine:Lorg/apache/hadoop/hbase/regionserver/StoreEngine;
       4: areturn

  protected org.apache.hadoop.hbase.regionserver.compactions.OffPeakHours getOffPeakHours();
    Code:
       0: aload_0
       1: getfield      #80                 // Field offPeakHours:Lorg/apache/hadoop/hbase/regionserver/compactions/OffPeakHours;
       4: areturn

  public void onConfigurationChange(org.apache.hadoop.conf.Configuration);
    Code:
       0: aload_0
       1: new           #42                 // class org/apache/hadoop/hbase/CompoundConfiguration
       4: dup
       5: invokespecial #43                 // Method org/apache/hadoop/hbase/CompoundConfiguration."<init>":()V
       8: aload_1
       9: invokevirtual #44                 // Method org/apache/hadoop/hbase/CompoundConfiguration.add:(Lorg/apache/hadoop/conf/Configuration;)Lorg/apache/hadoop/hbase/CompoundConfiguration;
      12: aload_0
      13: getfield      #41                 // Field family:Lorg/apache/hadoop/hbase/client/ColumnFamilyDescriptor;
      16: invokeinterface #50,  1           // InterfaceMethod org/apache/hadoop/hbase/client/ColumnFamilyDescriptor.getValues:()Ljava/util/Map;
      21: invokevirtual #47                 // Method org/apache/hadoop/hbase/CompoundConfiguration.addBytesMap:(Ljava/util/Map;)Lorg/apache/hadoop/hbase/CompoundConfiguration;
      24: putfield      #51                 // Field conf:Lorg/apache/hadoop/conf/Configuration;
      27: aload_0
      28: getfield      #97                 // Field storeEngine:Lorg/apache/hadoop/hbase/regionserver/StoreEngine;
      31: getfield      #695                // Field org/apache/hadoop/hbase/regionserver/StoreEngine.compactionPolicy:Lorg/apache/hadoop/hbase/regionserver/compactions/CompactionPolicy;
      34: aload_1
      35: invokevirtual #696                // Method org/apache/hadoop/hbase/regionserver/compactions/CompactionPolicy.setConf:(Lorg/apache/hadoop/conf/Configuration;)V
      38: aload_0
      39: aload_1
      40: invokestatic  #79                 // Method org/apache/hadoop/hbase/regionserver/compactions/OffPeakHours.getInstance:(Lorg/apache/hadoop/conf/Configuration;)Lorg/apache/hadoop/hbase/regionserver/compactions/OffPeakHours;
      43: putfield      #80                 // Field offPeakHours:Lorg/apache/hadoop/hbase/regionserver/compactions/OffPeakHours;
      46: return

  public void registerChildren(org.apache.hadoop.hbase.conf.ConfigurationManager);
    Code:
       0: return

  public void deregisterChildren(org.apache.hadoop.hbase.conf.ConfigurationManager);
    Code:
       0: return

  public double getCompactionPressure();
    Code:
       0: aload_0
       1: getfield      #97                 // Field storeEngine:Lorg/apache/hadoop/hbase/regionserver/StoreEngine;
       4: invokevirtual #103                // Method org/apache/hadoop/hbase/regionserver/StoreEngine.getStoreFileManager:()Lorg/apache/hadoop/hbase/regionserver/StoreFileManager;
       7: invokeinterface #697,  1          // InterfaceMethod org/apache/hadoop/hbase/regionserver/StoreFileManager.getCompactionPressure:()D
      12: dreturn

  public boolean isPrimaryReplicaStore();
    Code:
       0: aload_0
       1: invokevirtual #167                // Method getRegionInfo:()Lorg/apache/hadoop/hbase/client/RegionInfo;
       4: invokeinterface #698,  1          // InterfaceMethod org/apache/hadoop/hbase/client/RegionInfo.getReplicaId:()I
       9: ifne          16
      12: iconst_1
      13: goto          17
      16: iconst_0
      17: ireturn

  public void preSnapshotOperation();
    Code:
       0: aload_0
       1: getfield      #21                 // Field archiveLock:Ljava/util/concurrent/locks/ReentrantLock;
       4: invokevirtual #387                // Method java/util/concurrent/locks/ReentrantLock.lock:()V
       7: return

  public void postSnapshotOperation();
    Code:
       0: aload_0
       1: getfield      #21                 // Field archiveLock:Ljava/util/concurrent/locks/ReentrantLock;
       4: invokevirtual #402                // Method java/util/concurrent/locks/ReentrantLock.unlock:()V
       7: return

  public synchronized void closeAndArchiveCompactedFiles() throws java.io.IOException;
    Code:
       0: aload_0
       1: getfield      #21                 // Field archiveLock:Ljava/util/concurrent/locks/ReentrantLock;
       4: invokevirtual #387                // Method java/util/concurrent/locks/ReentrantLock.lock:()V
       7: aload_0
       8: getfield      #18                 // Field lock:Ljava/util/concurrent/locks/ReentrantReadWriteLock;
      11: invokevirtual #287                // Method java/util/concurrent/locks/ReentrantReadWriteLock.readLock:()Ljava/util/concurrent/locks/ReentrantReadWriteLock$ReadLock;
      14: invokevirtual #288                // Method java/util/concurrent/locks/ReentrantReadWriteLock$ReadLock.lock:()V
      17: aconst_null
      18: astore_1
      19: aload_0
      20: invokevirtual #699                // Method getStoreEngine:()Lorg/apache/hadoop/hbase/regionserver/StoreEngine;
      23: invokevirtual #103                // Method org/apache/hadoop/hbase/regionserver/StoreEngine.getStoreFileManager:()Lorg/apache/hadoop/hbase/regionserver/StoreFileManager;
      26: invokeinterface #252,  1          // InterfaceMethod org/apache/hadoop/hbase/regionserver/StoreFileManager.getCompactedfiles:()Ljava/util/Collection;
      31: astore_2
      32: aload_2
      33: invokestatic  #390                // Method org/apache/hbase/thirdparty/org/apache/commons/collections4/CollectionUtils.isNotEmpty:(Ljava/util/Collection;)Z
      36: ifeq          51
      39: new           #208                // class java/util/ArrayList
      42: dup
      43: aload_2
      44: invokespecial #571                // Method java/util/ArrayList."<init>":(Ljava/util/Collection;)V
      47: astore_1
      48: goto          62
      51: getstatic     #9                  // Field LOG:Lorg/slf4j/Logger;
      54: ldc_w         #700                // String No compacted files to archive
      57: invokeinterface #386,  2          // InterfaceMethod org/slf4j/Logger.trace:(Ljava/lang/String;)V
      62: aload_0
      63: getfield      #18                 // Field lock:Ljava/util/concurrent/locks/ReentrantReadWriteLock;
      66: invokevirtual #287                // Method java/util/concurrent/locks/ReentrantReadWriteLock.readLock:()Ljava/util/concurrent/locks/ReentrantReadWriteLock$ReadLock;
      69: invokevirtual #292                // Method java/util/concurrent/locks/ReentrantReadWriteLock$ReadLock.unlock:()V
      72: goto          88
      75: astore_3
      76: aload_0
      77: getfield      #18                 // Field lock:Ljava/util/concurrent/locks/ReentrantReadWriteLock;
      80: invokevirtual #287                // Method java/util/concurrent/locks/ReentrantReadWriteLock.readLock:()Ljava/util/concurrent/locks/ReentrantReadWriteLock$ReadLock;
      83: invokevirtual #292                // Method java/util/concurrent/locks/ReentrantReadWriteLock$ReadLock.unlock:()V
      86: aload_3
      87: athrow
      88: aload_1
      89: invokestatic  #390                // Method org/apache/hbase/thirdparty/org/apache/commons/collections4/CollectionUtils.isNotEmpty:(Ljava/util/Collection;)Z
      92: ifeq          100
      95: aload_0
      96: aload_1
      97: invokespecial #391                // Method removeCompactedfiles:(Ljava/util/Collection;)V
     100: aload_0
     101: getfield      #21                 // Field archiveLock:Ljava/util/concurrent/locks/ReentrantLock;
     104: invokevirtual #402                // Method java/util/concurrent/locks/ReentrantLock.unlock:()V
     107: goto          122
     110: astore        4
     112: aload_0
     113: getfield      #21                 // Field archiveLock:Ljava/util/concurrent/locks/ReentrantLock;
     116: invokevirtual #402                // Method java/util/concurrent/locks/ReentrantLock.unlock:()V
     119: aload         4
     121: athrow
     122: return
    Exception table:
       from    to  target type
          19    62    75   any
           7   100   110   any
         110   112   110   any

  long getStoreFileSize(org.apache.hadoop.hbase.regionserver.HStoreFile);
    Code:
       0: lconst_0
       1: lstore_2
       2: aload_1
       3: invokevirtual #284                // Method org/apache/hadoop/hbase/regionserver/HStoreFile.initReader:()V
       6: aload_1
       7: invokevirtual #239                // Method org/apache/hadoop/hbase/regionserver/HStoreFile.getReader:()Lorg/apache/hadoop/hbase/regionserver/StoreFileReader;
      10: invokevirtual #374                // Method org/apache/hadoop/hbase/regionserver/StoreFileReader.length:()J
      13: lstore_2
      14: aload_1
      15: aload_1
      16: invokevirtual #720                // Method org/apache/hadoop/hbase/regionserver/HStoreFile.getCacheConf:()Lorg/apache/hadoop/hbase/io/hfile/CacheConfig;
      19: ifnull        32
      22: aload_1
      23: invokevirtual #720                // Method org/apache/hadoop/hbase/regionserver/HStoreFile.getCacheConf:()Lorg/apache/hadoop/hbase/io/hfile/CacheConfig;
      26: invokevirtual #228                // Method org/apache/hadoop/hbase/io/hfile/CacheConfig.shouldEvictOnClose:()Z
      29: goto          33
      32: iconst_1
      33: invokevirtual #230                // Method org/apache/hadoop/hbase/regionserver/HStoreFile.closeStoreFile:(Z)V
      36: goto          160
      39: astore        4
      41: getstatic     #9                  // Field LOG:Lorg/slf4j/Logger;
      44: ldc_w         #721                // String Failed to close reader after computing store file size, ignoring
      47: aload         4
      49: invokeinterface #722,  3          // InterfaceMethod org/slf4j/Logger.trace:(Ljava/lang/String;Ljava/lang/Throwable;)V
      54: goto          160
      57: astore        4
      59: getstatic     #9                  // Field LOG:Lorg/slf4j/Logger;
      62: ldc_w         #723                // String Failed to open reader when trying to compute store file size, ignoring
      65: aload         4
      67: invokeinterface #722,  3          // InterfaceMethod org/slf4j/Logger.trace:(Ljava/lang/String;Ljava/lang/Throwable;)V
      72: aload_1
      73: aload_1
      74: invokevirtual #720                // Method org/apache/hadoop/hbase/regionserver/HStoreFile.getCacheConf:()Lorg/apache/hadoop/hbase/io/hfile/CacheConfig;
      77: ifnull        90
      80: aload_1
      81: invokevirtual #720                // Method org/apache/hadoop/hbase/regionserver/HStoreFile.getCacheConf:()Lorg/apache/hadoop/hbase/io/hfile/CacheConfig;
      84: invokevirtual #228                // Method org/apache/hadoop/hbase/io/hfile/CacheConfig.shouldEvictOnClose:()Z
      87: goto          91
      90: iconst_1
      91: invokevirtual #230                // Method org/apache/hadoop/hbase/regionserver/HStoreFile.closeStoreFile:(Z)V
      94: goto          160
      97: astore        4
      99: getstatic     #9                  // Field LOG:Lorg/slf4j/Logger;
     102: ldc_w         #721                // String Failed to close reader after computing store file size, ignoring
     105: aload         4
     107: invokeinterface #722,  3          // InterfaceMethod org/slf4j/Logger.trace:(Ljava/lang/String;Ljava/lang/Throwable;)V
     112: goto          160
     115: astore        5
     117: aload_1
     118: aload_1
     119: invokevirtual #720                // Method org/apache/hadoop/hbase/regionserver/HStoreFile.getCacheConf:()Lorg/apache/hadoop/hbase/io/hfile/CacheConfig;
     122: ifnull        135
     125: aload_1
     126: invokevirtual #720                // Method org/apache/hadoop/hbase/regionserver/HStoreFile.getCacheConf:()Lorg/apache/hadoop/hbase/io/hfile/CacheConfig;
     129: invokevirtual #228                // Method org/apache/hadoop/hbase/io/hfile/CacheConfig.shouldEvictOnClose:()Z
     132: goto          136
     135: iconst_1
     136: invokevirtual #230                // Method org/apache/hadoop/hbase/regionserver/HStoreFile.closeStoreFile:(Z)V
     139: goto          157
     142: astore        6
     144: getstatic     #9                  // Field LOG:Lorg/slf4j/Logger;
     147: ldc_w         #721                // String Failed to close reader after computing store file size, ignoring
     150: aload         6
     152: invokeinterface #722,  3          // InterfaceMethod org/slf4j/Logger.trace:(Ljava/lang/String;Ljava/lang/Throwable;)V
     157: aload         5
     159: athrow
     160: lload_2
     161: lreturn
    Exception table:
       from    to  target type
          14    36    39   Class java/io/IOException
           2    14    57   Class java/io/IOException
          72    94    97   Class java/io/IOException
           2    14   115   any
          57    72   115   any
         117   139   142   Class java/io/IOException
         115   117   115   any

  public java.lang.Long preFlushSeqIDEstimation();
    Code:
       0: aload_0
       1: getfield      #78                 // Field memstore:Lorg/apache/hadoop/hbase/regionserver/MemStore;
       4: invokeinterface #724,  1          // InterfaceMethod org/apache/hadoop/hbase/regionserver/MemStore.preFlushSeqIDEstimation:()J
       9: invokestatic  #71                 // Method java/lang/Long.valueOf:(J)Ljava/lang/Long;
      12: areturn

  public boolean isSloppyMemStore();
    Code:
       0: aload_0
       1: getfield      #78                 // Field memstore:Lorg/apache/hadoop/hbase/regionserver/MemStore;
       4: invokeinterface #725,  1          // InterfaceMethod org/apache/hadoop/hbase/regionserver/MemStore.isSloppy:()Z
       9: ireturn

  void reportArchivedFilesForQuota(java.util.List<? extends org.apache.hadoop.hbase.regionserver.StoreFile>, java.util.List<java.lang.Long>);
    Code:
       0: aload_1
       1: invokeinterface #469,  1          // InterfaceMethod java/util/List.size:()I
       6: aload_2
       7: invokeinterface #469,  1          // InterfaceMethod java/util/List.size:()I
      12: if_icmpeq     26
      15: new           #562                // class java/lang/RuntimeException
      18: dup
      19: ldc_w         #728                // String Coding error: should never see lists of varying size
      22: invokespecial #564                // Method java/lang/RuntimeException."<init>":(Ljava/lang/String;)V
      25: athrow
      26: aload_0
      27: getfield      #40                 // Field region:Lorg/apache/hadoop/hbase/regionserver/HRegion;
      30: invokevirtual #428                // Method org/apache/hadoop/hbase/regionserver/HRegion.getRegionServerServices:()Lorg/apache/hadoop/hbase/regionserver/RegionServerServices;
      33: astore_3
      34: aload_3
      35: ifnonnull     39
      38: return
      39: new           #208                // class java/util/ArrayList
      42: dup
      43: aload_1
      44: invokeinterface #469,  1          // InterfaceMethod java/util/List.size:()I
      49: invokespecial #210                // Method java/util/ArrayList."<init>":(I)V
      52: astore        4
      54: aload_2
      55: invokeinterface #406,  1          // InterfaceMethod java/util/List.iterator:()Ljava/util/Iterator;
      60: astore        5
      62: aload_1
      63: invokeinterface #406,  1          // InterfaceMethod java/util/List.iterator:()Ljava/util/Iterator;
      68: astore        6
      70: aload         6
      72: invokeinterface #201,  1          // InterfaceMethod java/util/Iterator.hasNext:()Z
      77: ifeq          153
      80: aload         6
      82: invokeinterface #202,  1          // InterfaceMethod java/util/Iterator.next:()Ljava/lang/Object;
      87: checkcast     #729                // class org/apache/hadoop/hbase/regionserver/StoreFile
      90: astore        7
      92: aload         5
      94: invokeinterface #202,  1          // InterfaceMethod java/util/Iterator.next:()Ljava/lang/Object;
      99: checkcast     #160                // class java/lang/Long
     102: invokevirtual #730                // Method java/lang/Long.longValue:()J
     105: lstore        8
     107: aload         7
     109: invokeinterface #731,  1          // InterfaceMethod org/apache/hadoop/hbase/regionserver/StoreFile.isHFile:()Z
     114: ifeq          150
     117: lload         8
     119: lconst_0
     120: lcmp
     121: ifeq          150
     124: aload         4
     126: aload         7
     128: invokeinterface #732,  1          // InterfaceMethod org/apache/hadoop/hbase/regionserver/StoreFile.getPath:()Lorg/apache/hadoop/fs/Path;
     133: invokevirtual #235                // Method org/apache/hadoop/fs/Path.getName:()Ljava/lang/String;
     136: lload         8
     138: invokestatic  #71                 // Method java/lang/Long.valueOf:(J)Ljava/lang/Long;
     141: invokestatic  #733                // Method org/apache/hbase/thirdparty/com/google/common/collect/Maps.immutableEntry:(Ljava/lang/Object;Ljava/lang/Object;)Ljava/util/Map$Entry;
     144: invokeinterface #241,  2          // InterfaceMethod java/util/List.add:(Ljava/lang/Object;)Z
     149: pop
     150: goto          70
     153: getstatic     #9                  // Field LOG:Lorg/slf4j/Logger;
     156: invokeinterface #381,  1          // InterfaceMethod org/slf4j/Logger.isTraceEnabled:()Z
     161: ifeq          203
     164: getstatic     #9                  // Field LOG:Lorg/slf4j/Logger;
     167: new           #115                // class java/lang/StringBuilder
     170: dup
     171: invokespecial #116                // Method java/lang/StringBuilder."<init>":()V
     174: ldc_w         #734                // String Files archived:
     177: invokevirtual #118                // Method java/lang/StringBuilder.append:(Ljava/lang/String;)Ljava/lang/StringBuilder;
     180: aload_1
     181: invokevirtual #265                // Method java/lang/StringBuilder.append:(Ljava/lang/Object;)Ljava/lang/StringBuilder;
     184: ldc_w         #735                // String , reporting the following to the Master:
     187: invokevirtual #118                // Method java/lang/StringBuilder.append:(Ljava/lang/String;)Ljava/lang/StringBuilder;
     190: aload         4
     192: invokevirtual #265                // Method java/lang/StringBuilder.append:(Ljava/lang/Object;)Ljava/lang/StringBuilder;
     195: invokevirtual #120                // Method java/lang/StringBuilder.toString:()Ljava/lang/String;
     198: invokeinterface #386,  2          // InterfaceMethod org/slf4j/Logger.trace:(Ljava/lang/String;)V
     203: aload_3
     204: aload_0
     205: invokevirtual #133                // Method getTableName:()Lorg/apache/hadoop/hbase/TableName;
     208: aload         4
     210: invokeinterface #736,  3          // InterfaceMethod org/apache/hadoop/hbase/regionserver/RegionServerServices.reportFileArchivalForQuotas:(Lorg/apache/hadoop/hbase/TableName;Ljava/util/Collection;)Z
     215: istore        6
     217: iload         6
     219: ifne          251
     222: getstatic     #9                  // Field LOG:Lorg/slf4j/Logger;
     225: new           #115                // class java/lang/StringBuilder
     228: dup
     229: invokespecial #116                // Method java/lang/StringBuilder."<init>":()V
     232: ldc_w         #737                // String Failed to report archival of files:
     235: invokevirtual #118                // Method java/lang/StringBuilder.append:(Ljava/lang/String;)Ljava/lang/StringBuilder;
     238: aload         4
     240: invokevirtual #265                // Method java/lang/StringBuilder.append:(Ljava/lang/Object;)Ljava/lang/StringBuilder;
     243: invokevirtual #120                // Method java/lang/StringBuilder.toString:()Ljava/lang/String;
     246: invokeinterface #336,  2          // InterfaceMethod org/slf4j/Logger.warn:(Ljava/lang/String;)V
     251: return

  public int getCurrentParallelPutCount();
    Code:
       0: aload_0
       1: getfield      #24                 // Field currentParallelPutCount:Ljava/util/concurrent/atomic/AtomicInteger;
       4: invokevirtual #738                // Method java/util/concurrent/atomic/AtomicInteger.get:()I
       7: ireturn

  public int getStoreRefCount();
    Code:
       0: aload_0
       1: getfield      #97                 // Field storeEngine:Lorg/apache/hadoop/hbase/regionserver/StoreEngine;
       4: invokevirtual #103                // Method org/apache/hadoop/hbase/regionserver/StoreEngine.getStoreFileManager:()Lorg/apache/hadoop/hbase/regionserver/StoreFileManager;
       7: invokeinterface #251,  1          // InterfaceMethod org/apache/hadoop/hbase/regionserver/StoreFileManager.getStorefiles:()Ljava/util/Collection;
      12: invokeinterface #461,  1          // InterfaceMethod java/util/Collection.stream:()Ljava/util/stream/Stream;
      17: invokedynamic #739,  0            // InvokeDynamic #20:test:()Ljava/util/function/Predicate;
      22: invokeinterface #659,  2          // InterfaceMethod java/util/stream/Stream.filter:(Ljava/util/function/Predicate;)Ljava/util/stream/Stream;
      27: invokedynamic #660,  0            // InvokeDynamic #6:test:()Ljava/util/function/Predicate;
      32: invokeinterface #659,  2          // InterfaceMethod java/util/stream/Stream.filter:(Ljava/util/function/Predicate;)Ljava/util/stream/Stream;
      37: invokedynamic #740,  0            // InvokeDynamic #21:applyAsInt:()Ljava/util/function/ToIntFunction;
      42: invokeinterface #741,  2          // InterfaceMethod java/util/stream/Stream.mapToInt:(Ljava/util/function/ToIntFunction;)Ljava/util/stream/IntStream;
      47: invokeinterface #742,  1          // InterfaceMethod java/util/stream/IntStream.sum:()I
      52: ireturn

  static org.apache.hadoop.hbase.regionserver.HStoreFile access$100(org.apache.hadoop.hbase.regionserver.HStore, org.apache.hadoop.fs.Path, long, org.apache.hadoop.hbase.monitoring.MonitoredTask) throws java.io.IOException;
    Code:
       0: aload_0
       1: aload_1
       2: lload_2
       3: aload         4
       5: invokespecial #10                 // Method commitFile:(Lorg/apache/hadoop/fs/Path;JLorg/apache/hadoop/hbase/monitoring/MonitoredTask;)Lorg/apache/hadoop/hbase/regionserver/HStoreFile;
       8: areturn

  static org.slf4j.Logger access$200();
    Code:
       0: getstatic     #9                  // Field LOG:Lorg/slf4j/Logger;
       3: areturn

  static java.util.concurrent.atomic.AtomicLong access$300(org.apache.hadoop.hbase.regionserver.HStore);
    Code:
       0: aload_0
       1: getfield      #8                  // Field flushedCellsCount:Ljava/util/concurrent/atomic/AtomicLong;
       4: areturn

  static java.util.concurrent.atomic.AtomicLong access$400(org.apache.hadoop.hbase.regionserver.HStore);
    Code:
       0: aload_0
       1: getfield      #7                  // Field flushedCellsSize:Ljava/util/concurrent/atomic/AtomicLong;
       4: areturn

  static java.util.concurrent.atomic.AtomicLong access$500(org.apache.hadoop.hbase.regionserver.HStore);
    Code:
       0: aload_0
       1: getfield      #6                  // Field flushedOutputFileSize:Ljava/util/concurrent/atomic/AtomicLong;
       4: areturn

  static boolean access$600(org.apache.hadoop.hbase.regionserver.HStore, java.util.List, long) throws java.io.IOException;
    Code:
       0: aload_0
       1: aload_1
       2: lload_2
       3: invokespecial #5                  // Method updateStorefiles:(Ljava/util/List;J)Z
       6: ireturn

  static org.apache.hadoop.hbase.regionserver.HRegionFileSystem access$700(org.apache.hadoop.hbase.regionserver.HStore);
    Code:
       0: aload_0
       1: getfield      #4                  // Field fs:Lorg/apache/hadoop/hbase/regionserver/HRegionFileSystem;
       4: areturn

  static org.apache.hadoop.hbase.regionserver.HStoreFile access$800(org.apache.hadoop.hbase.regionserver.HStore, org.apache.hadoop.hbase.regionserver.StoreFileInfo) throws java.io.IOException;
    Code:
       0: aload_0
       1: aload_1
       2: invokespecial #3                  // Method createStoreFileAndReader:(Lorg/apache/hadoop/hbase/regionserver/StoreFileInfo;)Lorg/apache/hadoop/hbase/regionserver/HStoreFile;
       5: areturn

  static java.util.concurrent.atomic.AtomicLong access$900(org.apache.hadoop.hbase.regionserver.HStore);
    Code:
       0: aload_0
       1: getfield      #2                  // Field storeSize:Ljava/util/concurrent/atomic/AtomicLong;
       4: areturn

  static java.util.concurrent.atomic.AtomicLong access$1000(org.apache.hadoop.hbase.regionserver.HStore);
    Code:
       0: aload_0
       1: getfield      #1                  // Field totalUncompressedBytes:Ljava/util/concurrent/atomic/AtomicLong;
       4: areturn

  static {};
    Code:
       0: ldc           #55                 // class org/apache/hadoop/hbase/regionserver/HStore
       2: invokevirtual #744                // Method java/lang/Class.desiredAssertionStatus:()Z
       5: ifne          12
       8: iconst_1
       9: goto          13
      12: iconst_0
      13: putstatic     #481                // Field $assertionsDisabled:Z
      16: ldc           #55                 // class org/apache/hadoop/hbase/regionserver/HStore
      18: invokestatic  #745                // Method org/slf4j/LoggerFactory.getLogger:(Ljava/lang/Class;)Lorg/slf4j/Logger;
      21: putstatic     #9                  // Field LOG:Lorg/slf4j/Logger;
      24: iconst_0
      25: putstatic     #93                 // Field closeCheckInterval:I
      28: new           #746                // class java/util/concurrent/atomic/AtomicBoolean
      31: dup
      32: invokespecial #747                // Method java/util/concurrent/atomic/AtomicBoolean."<init>":()V
      35: putstatic     #593                // Field offPeakCompactionTracker:Ljava/util/concurrent/atomic/AtomicBoolean;
      38: getstatic     #748                // Field org/apache/hadoop/hbase/util/ClassSize.OBJECT:I
      41: bipush        27
      43: getstatic     #749                // Field org/apache/hadoop/hbase/util/ClassSize.REFERENCE:I
      46: imul
      47: iadd
      48: bipush        16
      50: iadd
      51: bipush        24
      53: iadd
      54: iconst_2
      55: iadd
      56: invokestatic  #751                // Method org/apache/hadoop/hbase/util/ClassSize.align:(I)I
      59: i2l
      60: putstatic     #752                // Field FIXED_OVERHEAD:J
      63: getstatic     #752                // Field FIXED_OVERHEAD:J
      66: getstatic     #748                // Field org/apache/hadoop/hbase/util/ClassSize.OBJECT:I
      69: i2l
      70: ladd
      71: getstatic     #753                // Field org/apache/hadoop/hbase/util/ClassSize.REENTRANT_LOCK:I
      74: i2l
      75: ladd
      76: getstatic     #754                // Field org/apache/hadoop/hbase/util/ClassSize.CONCURRENT_SKIPLISTMAP:I
      79: i2l
      80: ladd
      81: getstatic     #755                // Field org/apache/hadoop/hbase/util/ClassSize.CONCURRENT_SKIPLISTMAP_ENTRY:I
      84: i2l
      85: ladd
      86: getstatic     #748                // Field org/apache/hadoop/hbase/util/ClassSize.OBJECT:I
      89: i2l
      90: ladd
      91: getstatic     #756                // Field org/apache/hadoop/hbase/regionserver/ScanInfo.FIXED_OVERHEAD:J
      94: ladd
      95: invokestatic  #757                // Method org/apache/hadoop/hbase/util/ClassSize.align:(J)J
      98: putstatic     #693                // Field DEEP_OVERHEAD:J
     101: return
}
