Compiled from "HStore.java"
class org.apache.hadoop.hbase.regionserver.HStore$1 implements java.util.concurrent.Callable<java.lang.Void> {
  final org.apache.hadoop.hbase.regionserver.HStoreFile val$f;

  final org.apache.hadoop.hbase.regionserver.HStore this$0;

  org.apache.hadoop.hbase.regionserver.HStore$1(org.apache.hadoop.hbase.regionserver.HStore, org.apache.hadoop.hbase.regionserver.HStoreFile);
    Code:
       0: aload_0
       1: aload_1
       2: putfield      #1                  // Field this$0:Lorg/apache/hadoop/hbase/regionserver/HStore;
       5: aload_0
       6: aload_2
       7: putfield      #2                  // Field val$f:Lorg/apache/hadoop/hbase/regionserver/HStoreFile;
      10: aload_0
      11: invokespecial #3                  // Method java/lang/Object."<init>":()V
      14: return

  public java.lang.Void call() throws java.io.IOException;
    Code:
       0: aload_0
       1: getfield      #1                  // Field this$0:Lorg/apache/hadoop/hbase/regionserver/HStore;
       4: getfield      #4                  // Field org/apache/hadoop/hbase/regionserver/HStore.cacheConf:Lorg/apache/hadoop/hbase/io/hfile/CacheConfig;
       7: ifnull        23
      10: aload_0
      11: getfield      #1                  // Field this$0:Lorg/apache/hadoop/hbase/regionserver/HStore;
      14: getfield      #4                  // Field org/apache/hadoop/hbase/regionserver/HStore.cacheConf:Lorg/apache/hadoop/hbase/io/hfile/CacheConfig;
      17: invokevirtual #5                  // Method org/apache/hadoop/hbase/io/hfile/CacheConfig.shouldEvictOnClose:()Z
      20: goto          24
      23: iconst_1
      24: istore_1
      25: aload_0
      26: getfield      #2                  // Field val$f:Lorg/apache/hadoop/hbase/regionserver/HStoreFile;
      29: iload_1
      30: invokevirtual #6                  // Method org/apache/hadoop/hbase/regionserver/HStoreFile.closeStoreFile:(Z)V
      33: aconst_null
      34: areturn

  public java.lang.Object call() throws java.lang.Exception;
    Code:
       0: aload_0
       1: invokevirtual #7                  // Method call:()Ljava/lang/Void;
       4: areturn
}
