Compiled from "HTable.java"
class org.apache.hadoop.hbase.client.HTable$5 extends org.apache.hadoop.hbase.client.NoncedRegionServerCallable<org.apache.hadoop.hbase.client.Result> {
  final org.apache.hadoop.hbase.client.Append val$append;

  final org.apache.hadoop.hbase.client.HTable this$0;

  org.apache.hadoop.hbase.client.HTable$5(org.apache.hadoop.hbase.client.HTable, org.apache.hadoop.hbase.client.Connection, org.apache.hadoop.hbase.TableName, byte[], org.apache.hadoop.hbase.ipc.HBaseRpcController, int, org.apache.hadoop.hbase.client.Append);
    Code:
       0: aload_0
       1: aload_1
       2: putfield      #1                  // Field this$0:Lorg/apache/hadoop/hbase/client/HTable;
       5: aload_0
       6: aload         7
       8: putfield      #2                  // Field val$append:Lorg/apache/hadoop/hbase/client/Append;
      11: aload_0
      12: aload_2
      13: aload_3
      14: aload         4
      16: aload         5
      18: iload         6
      20: invokespecial #3                  // Method org/apache/hadoop/hbase/client/NoncedRegionServerCallable."<init>":(Lorg/apache/hadoop/hbase/client/Connection;Lorg/apache/hadoop/hbase/TableName;[BLorg/apache/hadoop/hbase/ipc/HBaseRpcController;I)V
      23: return

  protected org.apache.hadoop.hbase.client.Result rpcCall() throws java.lang.Exception;
    Code:
       0: aload_0
       1: invokevirtual #4                  // Method getLocation:()Lorg/apache/hadoop/hbase/HRegionLocation;
       4: invokevirtual #5                  // Method org/apache/hadoop/hbase/HRegionLocation.getRegionInfo:()Lorg/apache/hadoop/hbase/HRegionInfo;
       7: invokevirtual #6                  // Method org/apache/hadoop/hbase/HRegionInfo.getRegionName:()[B
      10: aload_0
      11: getfield      #2                  // Field val$append:Lorg/apache/hadoop/hbase/client/Append;
      14: aload_0
      15: invokevirtual #7                  // Method getNonceGroup:()J
      18: aload_0
      19: invokevirtual #8                  // Method getNonce:()J
      22: invokestatic  #9                  // Method org/apache/hadoop/hbase/shaded/protobuf/RequestConverter.buildMutateRequest:([BLorg/apache/hadoop/hbase/client/Append;JJ)Lorg/apache/hadoop/hbase/shaded/protobuf/generated/ClientProtos$MutateRequest;
      25: astore_1
      26: aload_0
      27: aload_1
      28: invokevirtual #10                 // Method doMutate:(Lorg/apache/hadoop/hbase/shaded/protobuf/generated/ClientProtos$MutateRequest;)Lorg/apache/hadoop/hbase/shaded/protobuf/generated/ClientProtos$MutateResponse;
      31: astore_2
      32: aload_2
      33: invokevirtual #11                 // Method org/apache/hadoop/hbase/shaded/protobuf/generated/ClientProtos$MutateResponse.hasResult:()Z
      36: ifne          41
      39: aconst_null
      40: areturn
      41: aload_2
      42: invokevirtual #12                 // Method org/apache/hadoop/hbase/shaded/protobuf/generated/ClientProtos$MutateResponse.getResult:()Lorg/apache/hadoop/hbase/shaded/protobuf/generated/ClientProtos$Result;
      45: aload_0
      46: invokevirtual #13                 // Method getRpcControllerCellScanner:()Lorg/apache/hadoop/hbase/CellScanner;
      49: invokestatic  #14                 // Method org/apache/hadoop/hbase/shaded/protobuf/ProtobufUtil.toResult:(Lorg/apache/hadoop/hbase/shaded/protobuf/generated/ClientProtos$Result;Lorg/apache/hadoop/hbase/CellScanner;)Lorg/apache/hadoop/hbase/client/Result;
      52: areturn

  protected java.lang.Object rpcCall() throws java.lang.Exception;
    Code:
       0: aload_0
       1: invokevirtual #15                 // Method rpcCall:()Lorg/apache/hadoop/hbase/client/Result;
       4: areturn
}
