Compiled from "HTable.java"
class org.apache.hadoop.hbase.client.HTable$12 implements java.util.concurrent.Callable<R> {
  final java.lang.Class val$service;

  final org.apache.hadoop.hbase.client.RegionCoprocessorRpcChannel val$channel;

  final org.apache.hadoop.hbase.client.coprocessor.Batch$Call val$callable;

  final org.apache.hadoop.hbase.client.coprocessor.Batch$Callback val$callback;

  final byte[] val$r;

  final org.apache.hadoop.hbase.client.HTable this$0;

  org.apache.hadoop.hbase.client.HTable$12(org.apache.hadoop.hbase.client.HTable, java.lang.Class, org.apache.hadoop.hbase.client.RegionCoprocessorRpcChannel, org.apache.hadoop.hbase.client.coprocessor.Batch$Call, org.apache.hadoop.hbase.client.coprocessor.Batch$Callback, byte[]);
    Code:
       0: aload_0
       1: aload_1
       2: putfield      #1                  // Field this$0:Lorg/apache/hadoop/hbase/client/HTable;
       5: aload_0
       6: aload_2
       7: putfield      #2                  // Field val$service:Ljava/lang/Class;
      10: aload_0
      11: aload_3
      12: putfield      #3                  // Field val$channel:Lorg/apache/hadoop/hbase/client/RegionCoprocessorRpcChannel;
      15: aload_0
      16: aload         4
      18: putfield      #4                  // Field val$callable:Lorg/apache/hadoop/hbase/client/coprocessor/Batch$Call;
      21: aload_0
      22: aload         5
      24: putfield      #5                  // Field val$callback:Lorg/apache/hadoop/hbase/client/coprocessor/Batch$Callback;
      27: aload_0
      28: aload         6
      30: putfield      #6                  // Field val$r:[B
      33: aload_0
      34: invokespecial #7                  // Method java/lang/Object."<init>":()V
      37: return

  public R call() throws java.lang.Exception;
    Code:
       0: aload_0
       1: getfield      #2                  // Field val$service:Ljava/lang/Class;
       4: aload_0
       5: getfield      #3                  // Field val$channel:Lorg/apache/hadoop/hbase/client/RegionCoprocessorRpcChannel;
       8: invokestatic  #8                  // Method org/apache/hadoop/hbase/protobuf/ProtobufUtil.newServiceStub:(Ljava/lang/Class;Lcom/google/protobuf/RpcChannel;)Lcom/google/protobuf/Service;
      11: astore_1
      12: aload_0
      13: getfield      #4                  // Field val$callable:Lorg/apache/hadoop/hbase/client/coprocessor/Batch$Call;
      16: aload_1
      17: invokeinterface #9,  2            // InterfaceMethod org/apache/hadoop/hbase/client/coprocessor/Batch$Call.call:(Ljava/lang/Object;)Ljava/lang/Object;
      22: astore_2
      23: aload_0
      24: getfield      #3                  // Field val$channel:Lorg/apache/hadoop/hbase/client/RegionCoprocessorRpcChannel;
      27: invokevirtual #10                 // Method org/apache/hadoop/hbase/client/RegionCoprocessorRpcChannel.getLastRegion:()[B
      30: astore_3
      31: aload_0
      32: getfield      #5                  // Field val$callback:Lorg/apache/hadoop/hbase/client/coprocessor/Batch$Callback;
      35: ifnull        53
      38: aload_0
      39: getfield      #5                  // Field val$callback:Lorg/apache/hadoop/hbase/client/coprocessor/Batch$Callback;
      42: aload_3
      43: aload_0
      44: getfield      #6                  // Field val$r:[B
      47: aload_2
      48: invokeinterface #11,  4           // InterfaceMethod org/apache/hadoop/hbase/client/coprocessor/Batch$Callback.update:([B[BLjava/lang/Object;)V
      53: aload_2
      54: areturn
}
