Compiled from "HTestConst.java"
public class org.apache.hadoop.hbase.HTestConst {
  public static final java.lang.String DEFAULT_TABLE_STR;

  public static final byte[] DEFAULT_TABLE_BYTES;

  public static final org.apache.hadoop.hbase.TableName DEFAULT_TABLE;

  public static final java.lang.String DEFAULT_CF_STR;

  public static final byte[] DEFAULT_CF_BYTES;

  public static final java.util.Set<java.lang.String> DEFAULT_CF_STR_SET;

  public static final java.lang.String DEFAULT_ROW_STR;

  public static final byte[] DEFAULT_ROW_BYTES;

  public static final java.lang.String DEFAULT_QUALIFIER_STR;

  public static final byte[] DEFAULT_QUALIFIER_BYTES;

  public static java.lang.String DEFAULT_VALUE_STR;

  public static byte[] DEFAULT_VALUE_BYTES;

  public static byte[][] makeNAscii(byte[], int);
    Code:
       0: iload_1
       1: anewarray     #2                  // class "[B"
       4: astore_2
       5: iconst_0
       6: istore_3
       7: iload_3
       8: iload_1
       9: if_icmpge     36
      12: iload_3
      13: invokestatic  #3                  // Method java/lang/Integer.toString:(I)Ljava/lang/String;
      16: invokestatic  #4                  // Method org/apache/hadoop/hbase/util/Bytes.toBytes:(Ljava/lang/String;)[B
      19: astore        4
      21: aload_2
      22: iload_3
      23: aload_0
      24: aload         4
      26: invokestatic  #5                  // Method org/apache/hadoop/hbase/util/Bytes.add:([B[B)[B
      29: aastore
      30: iinc          3, 1
      33: goto          7
      36: aload_2
      37: areturn

  static {};
    Code:
       0: ldc           #7                  // String MyTestTable
       2: invokestatic  #4                  // Method org/apache/hadoop/hbase/util/Bytes.toBytes:(Ljava/lang/String;)[B
       5: putstatic     #8                  // Field DEFAULT_TABLE_BYTES:[B
       8: getstatic     #8                  // Field DEFAULT_TABLE_BYTES:[B
      11: invokestatic  #9                  // Method org/apache/hadoop/hbase/TableName.valueOf:([B)Lorg/apache/hadoop/hbase/TableName;
      14: putstatic     #10                 // Field DEFAULT_TABLE:Lorg/apache/hadoop/hbase/TableName;
      17: ldc           #11                 // String MyDefaultCF
      19: invokestatic  #4                  // Method org/apache/hadoop/hbase/util/Bytes.toBytes:(Ljava/lang/String;)[B
      22: putstatic     #12                 // Field DEFAULT_CF_BYTES:[B
      25: new           #13                 // class java/util/HashSet
      28: dup
      29: iconst_1
      30: anewarray     #14                 // class java/lang/String
      33: dup
      34: iconst_0
      35: ldc           #11                 // String MyDefaultCF
      37: aastore
      38: invokestatic  #15                 // Method java/util/Arrays.asList:([Ljava/lang/Object;)Ljava/util/List;
      41: invokespecial #16                 // Method java/util/HashSet."<init>":(Ljava/util/Collection;)V
      44: invokestatic  #17                 // Method java/util/Collections.unmodifiableSet:(Ljava/util/Set;)Ljava/util/Set;
      47: putstatic     #18                 // Field DEFAULT_CF_STR_SET:Ljava/util/Set;
      50: ldc           #19                 // String MyTestRow
      52: invokestatic  #4                  // Method org/apache/hadoop/hbase/util/Bytes.toBytes:(Ljava/lang/String;)[B
      55: putstatic     #20                 // Field DEFAULT_ROW_BYTES:[B
      58: ldc           #21                 // String MyColumnQualifier
      60: invokestatic  #4                  // Method org/apache/hadoop/hbase/util/Bytes.toBytes:(Ljava/lang/String;)[B
      63: putstatic     #22                 // Field DEFAULT_QUALIFIER_BYTES:[B
      66: ldc           #23                 // String MyTestValue
      68: putstatic     #24                 // Field DEFAULT_VALUE_STR:Ljava/lang/String;
      71: getstatic     #24                 // Field DEFAULT_VALUE_STR:Ljava/lang/String;
      74: invokestatic  #4                  // Method org/apache/hadoop/hbase/util/Bytes.toBytes:(Ljava/lang/String;)[B
      77: putstatic     #25                 // Field DEFAULT_VALUE_BYTES:[B
      80: return
}
