Compiled from "IncrementingEnvironmentEdge.java"
public class org.apache.hadoop.hbase.util.IncrementingEnvironmentEdge implements org.apache.hadoop.hbase.util.EnvironmentEdge {
  public org.apache.hadoop.hbase.util.IncrementingEnvironmentEdge();
    Code:
       0: aload_0
       1: invokestatic  #1                  // Method java/lang/System.currentTimeMillis:()J
       4: invokespecial #2                  // Method "<init>":(J)V
       7: return

  public org.apache.hadoop.hbase.util.IncrementingEnvironmentEdge(long);
    Code:
       0: aload_0
       1: invokespecial #3                  // Method java/lang/Object."<init>":()V
       4: aload_0
       5: lload_1
       6: putfield      #4                  // Field timeIncrement:J
       9: return

  public synchronized long currentTime();
    Code:
       0: aload_0
       1: dup
       2: getfield      #4                  // Field timeIncrement:J
       5: dup2_x1
       6: lconst_1
       7: ladd
       8: putfield      #4                  // Field timeIncrement:J
      11: lreturn

  public synchronized long incrementTime(long);
    Code:
       0: aload_0
       1: dup
       2: getfield      #4                  // Field timeIncrement:J
       5: lload_1
       6: ladd
       7: putfield      #4                  // Field timeIncrement:J
      10: aload_0
      11: getfield      #4                  // Field timeIncrement:J
      14: lreturn
}
