Compiled from "InlineChore.java"
abstract class org.apache.hadoop.hbase.procedure2.InlineChore extends org.apache.hadoop.hbase.procedure2.util.DelayedUtil$DelayedObject implements java.lang.Runnable {
  org.apache.hadoop.hbase.procedure2.InlineChore();
    Code:
       0: aload_0
       1: invokespecial #1                  // Method org/apache/hadoop/hbase/procedure2/util/DelayedUtil$DelayedObject."<init>":()V
       4: return

  public abstract int getTimeoutInterval();

  protected void refreshTimeout();
    Code:
       0: aload_0
       1: invokestatic  #2                  // Method org/apache/hadoop/hbase/util/EnvironmentEdgeManager.currentTime:()J
       4: aload_0
       5: invokevirtual #3                  // Method getTimeoutInterval:()I
       8: i2l
       9: ladd
      10: putfield      #4                  // Field timeout:J
      13: return

  public long getTimeout();
    Code:
       0: aload_0
       1: getfield      #4                  // Field timeout:J
       4: lreturn
}
