Compiled from "Interns.java"
final class org.apache.hadoop.hbase.metrics.Interns$2 extends org.apache.hbase.thirdparty.com.google.common.cache.CacheLoader<org.apache.hadoop.metrics2.MetricsInfo, java.util.concurrent.ConcurrentHashMap<java.lang.String, org.apache.hadoop.metrics2.MetricsTag>> {
  org.apache.hadoop.hbase.metrics.Interns$2();
    Code:
       0: aload_0
       1: invokespecial #1                  // Method org/apache/hbase/thirdparty/com/google/common/cache/CacheLoader."<init>":()V
       4: return

  public java.util.concurrent.ConcurrentHashMap<java.lang.String, org.apache.hadoop.metrics2.MetricsTag> load(org.apache.hadoop.metrics2.MetricsInfo);
    Code:
       0: new           #2                  // class java/util/concurrent/ConcurrentHashMap
       3: dup
       4: invokespecial #3                  // Method java/util/concurrent/ConcurrentHashMap."<init>":()V
       7: areturn

  public java.lang.Object load(java.lang.Object) throws java.lang.Exception;
    Code:
       0: aload_0
       1: aload_1
       2: checkcast     #4                  // class org/apache/hadoop/metrics2/MetricsInfo
       5: invokevirtual #5                  // Method load:(Lorg/apache/hadoop/metrics2/MetricsInfo;)Ljava/util/concurrent/ConcurrentHashMap;
       8: areturn
}
