Compiled from "JVMClusterUtil.java"
public class org.apache.hadoop.hbase.util.JVMClusterUtil {
  public org.apache.hadoop.hbase.util.JVMClusterUtil();
    Code:
       0: aload_0
       1: invokespecial #1                  // Method java/lang/Object."<init>":()V
       4: return

  public static org.apache.hadoop.hbase.util.JVMClusterUtil$RegionServerThread createRegionServerThread(org.apache.hadoop.conf.Configuration, java.lang.Class<? extends org.apache.hadoop.hbase.regionserver.HRegionServer>, int) throws java.io.IOException;
    Code:
       0: aload_1
       1: iconst_1
       2: anewarray     #2                  // class java/lang/Class
       5: dup
       6: iconst_0
       7: ldc           #3                  // class org/apache/hadoop/conf/Configuration
       9: aastore
      10: invokevirtual #4                  // Method java/lang/Class.getConstructor:([Ljava/lang/Class;)Ljava/lang/reflect/Constructor;
      13: astore        4
      15: aload         4
      17: iconst_1
      18: invokevirtual #5                  // Method java/lang/reflect/Constructor.setAccessible:(Z)V
      21: aload         4
      23: iconst_1
      24: anewarray     #6                  // class java/lang/Object
      27: dup
      28: iconst_0
      29: aload_0
      30: aastore
      31: invokevirtual #7                  // Method java/lang/reflect/Constructor.newInstance:([Ljava/lang/Object;)Ljava/lang/Object;
      34: checkcast     #8                  // class org/apache/hadoop/hbase/regionserver/HRegionServer
      37: astore_3
      38: goto          128
      41: astore        4
      43: aload         4
      45: invokevirtual #10                 // Method java/lang/reflect/InvocationTargetException.getTargetException:()Ljava/lang/Throwable;
      48: astore        5
      50: new           #11                 // class java/lang/RuntimeException
      53: dup
      54: new           #12                 // class java/lang/StringBuilder
      57: dup
      58: invokespecial #13                 // Method java/lang/StringBuilder."<init>":()V
      61: ldc           #14                 // String Failed construction of RegionServer:
      63: invokevirtual #15                 // Method java/lang/StringBuilder.append:(Ljava/lang/String;)Ljava/lang/StringBuilder;
      66: aload_1
      67: invokevirtual #16                 // Method java/lang/Class.toString:()Ljava/lang/String;
      70: invokevirtual #15                 // Method java/lang/StringBuilder.append:(Ljava/lang/String;)Ljava/lang/StringBuilder;
      73: aload         5
      75: invokevirtual #17                 // Method java/lang/Throwable.getCause:()Ljava/lang/Throwable;
      78: ifnull        92
      81: aload         5
      83: invokevirtual #17                 // Method java/lang/Throwable.getCause:()Ljava/lang/Throwable;
      86: invokevirtual #18                 // Method java/lang/Throwable.getMessage:()Ljava/lang/String;
      89: goto          94
      92: ldc           #19                 // String
      94: invokevirtual #15                 // Method java/lang/StringBuilder.append:(Ljava/lang/String;)Ljava/lang/StringBuilder;
      97: invokevirtual #20                 // Method java/lang/StringBuilder.toString:()Ljava/lang/String;
     100: aload         5
     102: invokespecial #21                 // Method java/lang/RuntimeException."<init>":(Ljava/lang/String;Ljava/lang/Throwable;)V
     105: athrow
     106: astore        4
     108: new           #23                 // class java/io/IOException
     111: dup
     112: invokespecial #24                 // Method java/io/IOException."<init>":()V
     115: astore        5
     117: aload         5
     119: aload         4
     121: invokevirtual #25                 // Method java/io/IOException.initCause:(Ljava/lang/Throwable;)Ljava/lang/Throwable;
     124: pop
     125: aload         5
     127: athrow
     128: new           #26                 // class org/apache/hadoop/hbase/util/JVMClusterUtil$RegionServerThread
     131: dup
     132: aload_3
     133: iload_2
     134: invokespecial #27                 // Method org/apache/hadoop/hbase/util/JVMClusterUtil$RegionServerThread."<init>":(Lorg/apache/hadoop/hbase/regionserver/HRegionServer;I)V
     137: areturn
    Exception table:
       from    to  target type
           0    38    41   Class java/lang/reflect/InvocationTargetException
           0    38   106   Class java/lang/Exception

  public static org.apache.hadoop.hbase.util.JVMClusterUtil$MasterThread createMasterThread(org.apache.hadoop.conf.Configuration, java.lang.Class<? extends org.apache.hadoop.hbase.master.HMaster>, int) throws java.io.IOException;
    Code:
       0: aload_1
       1: iconst_1
       2: anewarray     #2                  // class java/lang/Class
       5: dup
       6: iconst_0
       7: ldc           #3                  // class org/apache/hadoop/conf/Configuration
       9: aastore
      10: invokevirtual #4                  // Method java/lang/Class.getConstructor:([Ljava/lang/Class;)Ljava/lang/reflect/Constructor;
      13: iconst_1
      14: anewarray     #6                  // class java/lang/Object
      17: dup
      18: iconst_0
      19: aload_0
      20: aastore
      21: invokevirtual #7                  // Method java/lang/reflect/Constructor.newInstance:([Ljava/lang/Object;)Ljava/lang/Object;
      24: checkcast     #28                 // class org/apache/hadoop/hbase/master/HMaster
      27: astore_3
      28: goto          118
      31: astore        4
      33: aload         4
      35: invokevirtual #10                 // Method java/lang/reflect/InvocationTargetException.getTargetException:()Ljava/lang/Throwable;
      38: astore        5
      40: new           #11                 // class java/lang/RuntimeException
      43: dup
      44: new           #12                 // class java/lang/StringBuilder
      47: dup
      48: invokespecial #13                 // Method java/lang/StringBuilder."<init>":()V
      51: ldc           #29                 // String Failed construction of Master:
      53: invokevirtual #15                 // Method java/lang/StringBuilder.append:(Ljava/lang/String;)Ljava/lang/StringBuilder;
      56: aload_1
      57: invokevirtual #16                 // Method java/lang/Class.toString:()Ljava/lang/String;
      60: invokevirtual #15                 // Method java/lang/StringBuilder.append:(Ljava/lang/String;)Ljava/lang/StringBuilder;
      63: aload         5
      65: invokevirtual #17                 // Method java/lang/Throwable.getCause:()Ljava/lang/Throwable;
      68: ifnull        82
      71: aload         5
      73: invokevirtual #17                 // Method java/lang/Throwable.getCause:()Ljava/lang/Throwable;
      76: invokevirtual #18                 // Method java/lang/Throwable.getMessage:()Ljava/lang/String;
      79: goto          84
      82: ldc           #19                 // String
      84: invokevirtual #15                 // Method java/lang/StringBuilder.append:(Ljava/lang/String;)Ljava/lang/StringBuilder;
      87: invokevirtual #20                 // Method java/lang/StringBuilder.toString:()Ljava/lang/String;
      90: aload         5
      92: invokespecial #21                 // Method java/lang/RuntimeException."<init>":(Ljava/lang/String;Ljava/lang/Throwable;)V
      95: athrow
      96: astore        4
      98: new           #23                 // class java/io/IOException
     101: dup
     102: invokespecial #24                 // Method java/io/IOException."<init>":()V
     105: astore        5
     107: aload         5
     109: aload         4
     111: invokevirtual #25                 // Method java/io/IOException.initCause:(Ljava/lang/Throwable;)Ljava/lang/Throwable;
     114: pop
     115: aload         5
     117: athrow
     118: new           #30                 // class org/apache/hadoop/hbase/util/JVMClusterUtil$MasterThread
     121: dup
     122: aload_3
     123: iload_2
     124: invokespecial #31                 // Method org/apache/hadoop/hbase/util/JVMClusterUtil$MasterThread."<init>":(Lorg/apache/hadoop/hbase/master/HMaster;I)V
     127: areturn
    Exception table:
       from    to  target type
           0    28    31   Class java/lang/reflect/InvocationTargetException
           0    28    96   Class java/lang/Exception

  public static java.lang.String startup(java.util.List<org.apache.hadoop.hbase.util.JVMClusterUtil$MasterThread>, java.util.List<org.apache.hadoop.hbase.util.JVMClusterUtil$RegionServerThread>) throws java.io.IOException;
    Code:
       0: aconst_null
       1: astore_2
       2: aload_0
       3: ifnull        15
       6: aload_0
       7: invokeinterface #37,  1           // InterfaceMethod java/util/List.isEmpty:()Z
      12: ifeq          17
      15: aconst_null
      16: areturn
      17: aload_0
      18: invokeinterface #32,  1           // InterfaceMethod java/util/List.iterator:()Ljava/util/Iterator;
      23: astore_3
      24: aload_3
      25: invokeinterface #33,  1           // InterfaceMethod java/util/Iterator.hasNext:()Z
      30: ifeq          61
      33: aload_3
      34: invokeinterface #34,  1           // InterfaceMethod java/util/Iterator.next:()Ljava/lang/Object;
      39: checkcast     #30                 // class org/apache/hadoop/hbase/util/JVMClusterUtil$MasterThread
      42: astore        4
      44: aload         4
      46: invokevirtual #38                 // Method org/apache/hadoop/hbase/util/JVMClusterUtil$MasterThread.getMaster:()Lorg/apache/hadoop/hbase/master/HMaster;
      49: invokevirtual #39                 // Method org/apache/hadoop/hbase/master/HMaster.getConfiguration:()Lorg/apache/hadoop/conf/Configuration;
      52: astore_2
      53: aload         4
      55: invokevirtual #40                 // Method org/apache/hadoop/hbase/util/JVMClusterUtil$MasterThread.start:()V
      58: goto          24
      61: aload_2
      62: ifnull        79
      65: aload_2
      66: ldc           #41                 // String hbase.master.start.timeout.localHBaseCluster
      68: ldc           #42                 // String 30000
      70: invokevirtual #43                 // Method org/apache/hadoop/conf/Configuration.get:(Ljava/lang/String;Ljava/lang/String;)Ljava/lang/String;
      73: invokestatic  #44                 // Method java/lang/Integer.parseInt:(Ljava/lang/String;)I
      76: goto          82
      79: sipush        30000
      82: istore_3
      83: iload_3
      84: i2l
      85: ldc           #45                 // String active
      87: aload_0
      88: invokedynamic #46,  0             // InvokeDynamic #0:get:(Ljava/util/List;)Ljava/util/function/Supplier;
      93: invokestatic  #47                 // Method waitForEvent:(JLjava/lang/String;Ljava/util/function/Supplier;)V
      96: aload_1
      97: ifnull        138
     100: aload_1
     101: invokeinterface #32,  1           // InterfaceMethod java/util/List.iterator:()Ljava/util/Iterator;
     106: astore        4
     108: aload         4
     110: invokeinterface #33,  1           // InterfaceMethod java/util/Iterator.hasNext:()Z
     115: ifeq          138
     118: aload         4
     120: invokeinterface #34,  1           // InterfaceMethod java/util/Iterator.next:()Ljava/lang/Object;
     125: checkcast     #26                 // class org/apache/hadoop/hbase/util/JVMClusterUtil$RegionServerThread
     128: astore        5
     130: aload         5
     132: invokevirtual #48                 // Method org/apache/hadoop/hbase/util/JVMClusterUtil$RegionServerThread.start:()V
     135: goto          108
     138: aload_2
     139: ifnull        156
     142: aload_2
     143: ldc           #49                 // String hbase.master.init.timeout.localHBaseCluster
     145: ldc           #50                 // String 200000
     147: invokevirtual #43                 // Method org/apache/hadoop/conf/Configuration.get:(Ljava/lang/String;Ljava/lang/String;)Ljava/lang/String;
     150: invokestatic  #44                 // Method java/lang/Integer.parseInt:(Ljava/lang/String;)I
     153: goto          158
     156: ldc           #51                 // int 200000
     158: istore        4
     160: iload         4
     162: i2l
     163: ldc           #52                 // String initialized
     165: aload_0
     166: invokedynamic #53,  0             // InvokeDynamic #1:get:(Ljava/util/List;)Ljava/util/function/Supplier;
     171: invokestatic  #47                 // Method waitForEvent:(JLjava/lang/String;Ljava/util/function/Supplier;)V
     174: aload_0
     175: invokestatic  #54                 // Method findActiveMaster:(Ljava/util/List;)Lorg/apache/hadoop/hbase/util/JVMClusterUtil$MasterThread;
     178: invokestatic  #35                 // Method org/apache/hadoop/hbase/util/JVMClusterUtil$MasterThread.access$000:(Lorg/apache/hadoop/hbase/util/JVMClusterUtil$MasterThread;)Lorg/apache/hadoop/hbase/master/HMaster;
     181: invokevirtual #55                 // Method org/apache/hadoop/hbase/master/HMaster.getServerName:()Lorg/apache/hadoop/hbase/ServerName;
     184: invokevirtual #56                 // Method org/apache/hadoop/hbase/ServerName.toString:()Ljava/lang/String;
     187: areturn

  public static void shutdown(java.util.List<org.apache.hadoop.hbase.util.JVMClusterUtil$MasterThread>, java.util.List<org.apache.hadoop.hbase.util.JVMClusterUtil$RegionServerThread>);
    Code:
       0: getstatic     #78                 // Field LOG:Lorg/slf4j/Logger;
       3: ldc           #79                 // String Shutting down HBase Cluster
       5: invokeinterface #80,  2           // InterfaceMethod org/slf4j/Logger.debug:(Ljava/lang/String;)V
      10: aload_0
      11: ifnull        213
      14: aconst_null
      15: astore_2
      16: aload_0
      17: invokeinterface #32,  1           // InterfaceMethod java/util/List.iterator:()Ljava/util/Iterator;
      22: astore_3
      23: aload_3
      24: invokeinterface #33,  1           // InterfaceMethod java/util/Iterator.hasNext:()Z
      29: ifeq          187
      32: aload_3
      33: invokeinterface #34,  1           // InterfaceMethod java/util/Iterator.next:()Ljava/lang/Object;
      38: checkcast     #30                 // class org/apache/hadoop/hbase/util/JVMClusterUtil$MasterThread
      41: astore        4
      43: aload         4
      45: invokestatic  #35                 // Method org/apache/hadoop/hbase/util/JVMClusterUtil$MasterThread.access$000:(Lorg/apache/hadoop/hbase/util/JVMClusterUtil$MasterThread;)Lorg/apache/hadoop/hbase/master/HMaster;
      48: invokevirtual #81                 // Method org/apache/hadoop/hbase/master/HMaster.isStopped:()Z
      51: ifne          184
      54: aload         4
      56: invokestatic  #35                 // Method org/apache/hadoop/hbase/util/JVMClusterUtil$MasterThread.access$000:(Lorg/apache/hadoop/hbase/util/JVMClusterUtil$MasterThread;)Lorg/apache/hadoop/hbase/master/HMaster;
      59: invokevirtual #36                 // Method org/apache/hadoop/hbase/master/HMaster.isActiveMaster:()Z
      62: ifne          125
      65: aload         4
      67: invokestatic  #35                 // Method org/apache/hadoop/hbase/util/JVMClusterUtil$MasterThread.access$000:(Lorg/apache/hadoop/hbase/util/JVMClusterUtil$MasterThread;)Lorg/apache/hadoop/hbase/master/HMaster;
      70: invokevirtual #82                 // Method org/apache/hadoop/hbase/master/HMaster.stopMaster:()V
      73: goto          90
      76: astore        5
      78: getstatic     #78                 // Field LOG:Lorg/slf4j/Logger;
      81: ldc           #83                 // String Exception occurred while stopping master
      83: aload         5
      85: invokeinterface #84,  3           // InterfaceMethod org/slf4j/Logger.error:(Ljava/lang/String;Ljava/lang/Throwable;)V
      90: getstatic     #78                 // Field LOG:Lorg/slf4j/Logger;
      93: ldc           #85                 // String Stopped backup Master {} is stopped: {}
      95: aload         4
      97: invokestatic  #35                 // Method org/apache/hadoop/hbase/util/JVMClusterUtil$MasterThread.access$000:(Lorg/apache/hadoop/hbase/util/JVMClusterUtil$MasterThread;)Lorg/apache/hadoop/hbase/master/HMaster;
     100: invokevirtual #86                 // Method java/lang/Object.hashCode:()I
     103: invokestatic  #87                 // Method java/lang/Integer.valueOf:(I)Ljava/lang/Integer;
     106: aload         4
     108: invokestatic  #35                 // Method org/apache/hadoop/hbase/util/JVMClusterUtil$MasterThread.access$000:(Lorg/apache/hadoop/hbase/util/JVMClusterUtil$MasterThread;)Lorg/apache/hadoop/hbase/master/HMaster;
     111: invokevirtual #81                 // Method org/apache/hadoop/hbase/master/HMaster.isStopped:()Z
     114: invokestatic  #88                 // Method java/lang/Boolean.valueOf:(Z)Ljava/lang/Boolean;
     117: invokeinterface #89,  4           // InterfaceMethod org/slf4j/Logger.info:(Ljava/lang/String;Ljava/lang/Object;Ljava/lang/Object;)V
     122: goto          184
     125: aload_2
     126: ifnull        149
     129: getstatic     #78                 // Field LOG:Lorg/slf4j/Logger;
     132: ldc           #90                 // String Found more than 1 active master, hash {}
     134: aload_2
     135: invokestatic  #35                 // Method org/apache/hadoop/hbase/util/JVMClusterUtil$MasterThread.access$000:(Lorg/apache/hadoop/hbase/util/JVMClusterUtil$MasterThread;)Lorg/apache/hadoop/hbase/master/HMaster;
     138: invokevirtual #86                 // Method java/lang/Object.hashCode:()I
     141: invokestatic  #87                 // Method java/lang/Integer.valueOf:(I)Ljava/lang/Integer;
     144: invokeinterface #91,  3           // InterfaceMethod org/slf4j/Logger.warn:(Ljava/lang/String;Ljava/lang/Object;)V
     149: aload         4
     151: astore_2
     152: getstatic     #78                 // Field LOG:Lorg/slf4j/Logger;
     155: ldc           #92                 // String Found active master hash={}, stopped={}
     157: aload         4
     159: invokestatic  #35                 // Method org/apache/hadoop/hbase/util/JVMClusterUtil$MasterThread.access$000:(Lorg/apache/hadoop/hbase/util/JVMClusterUtil$MasterThread;)Lorg/apache/hadoop/hbase/master/HMaster;
     162: invokevirtual #86                 // Method java/lang/Object.hashCode:()I
     165: invokestatic  #87                 // Method java/lang/Integer.valueOf:(I)Ljava/lang/Integer;
     168: aload         4
     170: invokestatic  #35                 // Method org/apache/hadoop/hbase/util/JVMClusterUtil$MasterThread.access$000:(Lorg/apache/hadoop/hbase/util/JVMClusterUtil$MasterThread;)Lorg/apache/hadoop/hbase/master/HMaster;
     173: invokevirtual #81                 // Method org/apache/hadoop/hbase/master/HMaster.isStopped:()Z
     176: invokestatic  #88                 // Method java/lang/Boolean.valueOf:(Z)Ljava/lang/Boolean;
     179: invokeinterface #93,  4           // InterfaceMethod org/slf4j/Logger.debug:(Ljava/lang/String;Ljava/lang/Object;Ljava/lang/Object;)V
     184: goto          23
     187: aload_2
     188: ifnull        213
     191: aload_2
     192: invokestatic  #35                 // Method org/apache/hadoop/hbase/util/JVMClusterUtil$MasterThread.access$000:(Lorg/apache/hadoop/hbase/util/JVMClusterUtil$MasterThread;)Lorg/apache/hadoop/hbase/master/HMaster;
     195: invokevirtual #94                 // Method org/apache/hadoop/hbase/master/HMaster.shutdown:()V
     198: goto          213
     201: astore_3
     202: getstatic     #78                 // Field LOG:Lorg/slf4j/Logger;
     205: ldc           #95                 // String Exception occurred in HMaster.shutdown()
     207: aload_3
     208: invokeinterface #84,  3           // InterfaceMethod org/slf4j/Logger.error:(Ljava/lang/String;Ljava/lang/Throwable;)V
     213: iconst_0
     214: istore_2
     215: invokestatic  #96                 // Method java/lang/System.currentTimeMillis:()J
     218: ldc2_w        #97                 // long 30000l
     221: ladd
     222: lstore_3
     223: aload_1
     224: ifnull        560
     227: aload_1
     228: invokeinterface #32,  1           // InterfaceMethod java/util/List.iterator:()Ljava/util/Iterator;
     233: astore        5
     235: aload         5
     237: invokeinterface #33,  1           // InterfaceMethod java/util/Iterator.hasNext:()Z
     242: ifeq          270
     245: aload         5
     247: invokeinterface #34,  1           // InterfaceMethod java/util/Iterator.next:()Ljava/lang/Object;
     252: checkcast     #26                 // class org/apache/hadoop/hbase/util/JVMClusterUtil$RegionServerThread
     255: astore        6
     257: aload         6
     259: invokevirtual #99                 // Method org/apache/hadoop/hbase/util/JVMClusterUtil$RegionServerThread.getRegionServer:()Lorg/apache/hadoop/hbase/regionserver/HRegionServer;
     262: ldc           #100                // String Shutdown requested
     264: invokevirtual #101                // Method org/apache/hadoop/hbase/regionserver/HRegionServer.stop:(Ljava/lang/String;)V
     267: goto          235
     270: aload_1
     271: invokeinterface #32,  1           // InterfaceMethod java/util/List.iterator:()Ljava/util/Iterator;
     276: astore        5
     278: aload         5
     280: invokeinterface #33,  1           // InterfaceMethod java/util/Iterator.hasNext:()Z
     285: ifeq          355
     288: aload         5
     290: invokeinterface #34,  1           // InterfaceMethod java/util/Iterator.next:()Ljava/lang/Object;
     295: checkcast     #26                 // class org/apache/hadoop/hbase/util/JVMClusterUtil$RegionServerThread
     298: astore        6
     300: invokestatic  #96                 // Method java/lang/System.currentTimeMillis:()J
     303: lstore        7
     305: aload         6
     307: invokevirtual #102                // Method org/apache/hadoop/hbase/util/JVMClusterUtil$RegionServerThread.isAlive:()Z
     310: ifeq          352
     313: iload_2
     314: ifne          352
     317: lload         7
     319: lload_3
     320: lcmp
     321: ifge          352
     324: aload         6
     326: lload_3
     327: lload         7
     329: lsub
     330: invokevirtual #103                // Method org/apache/hadoop/hbase/util/JVMClusterUtil$RegionServerThread.join:(J)V
     333: goto          352
     336: astore        9
     338: getstatic     #78                 // Field LOG:Lorg/slf4j/Logger;
     341: ldc           #104                // String Got InterruptedException on shutdown - not waiting anymore on region server ends
     343: aload         9
     345: invokeinterface #105,  3          // InterfaceMethod org/slf4j/Logger.info:(Ljava/lang/String;Ljava/lang/Throwable;)V
     350: iconst_1
     351: istore_2
     352: goto          278
     355: iconst_0
     356: istore        5
     358: iload         5
     360: bipush        100
     362: if_icmpge     560
     365: iconst_0
     366: istore        6
     368: aload_1
     369: invokeinterface #32,  1           // InterfaceMethod java/util/List.iterator:()Ljava/util/Iterator;
     374: astore        7
     376: aload         7
     378: invokeinterface #33,  1           // InterfaceMethod java/util/Iterator.hasNext:()Z
     383: ifeq          437
     386: aload         7
     388: invokeinterface #34,  1           // InterfaceMethod java/util/Iterator.next:()Ljava/lang/Object;
     393: checkcast     #26                 // class org/apache/hadoop/hbase/util/JVMClusterUtil$RegionServerThread
     396: astore        8
     398: aload         8
     400: invokevirtual #102                // Method org/apache/hadoop/hbase/util/JVMClusterUtil$RegionServerThread.isAlive:()Z
     403: ifeq          434
     406: iconst_1
     407: istore        6
     409: getstatic     #78                 // Field LOG:Lorg/slf4j/Logger;
     412: ldc           #106                // String RegionServerThreads remaining, give one more chance before interrupting
     414: invokeinterface #107,  2          // InterfaceMethod org/slf4j/Logger.warn:(Ljava/lang/String;)V
     419: aload         8
     421: ldc2_w        #108                // long 1000l
     424: invokevirtual #103                // Method org/apache/hadoop/hbase/util/JVMClusterUtil$RegionServerThread.join:(J)V
     427: goto          434
     430: astore        9
     432: iconst_1
     433: istore_2
     434: goto          376
     437: iload         6
     439: ifne          445
     442: goto          560
     445: aload_1
     446: invokeinterface #32,  1           // InterfaceMethod java/util/List.iterator:()Ljava/util/Iterator;
     451: astore        7
     453: aload         7
     455: invokeinterface #33,  1           // InterfaceMethod java/util/Iterator.hasNext:()Z
     460: ifeq          554
     463: aload         7
     465: invokeinterface #34,  1           // InterfaceMethod java/util/Iterator.next:()Ljava/lang/Object;
     470: checkcast     #26                 // class org/apache/hadoop/hbase/util/JVMClusterUtil$RegionServerThread
     473: astore        8
     475: aload         8
     477: invokevirtual #102                // Method org/apache/hadoop/hbase/util/JVMClusterUtil$RegionServerThread.isAlive:()Z
     480: ifeq          551
     483: getstatic     #78                 // Field LOG:Lorg/slf4j/Logger;
     486: new           #12                 // class java/lang/StringBuilder
     489: dup
     490: invokespecial #13                 // Method java/lang/StringBuilder."<init>":()V
     493: ldc           #110                // String RegionServerThreads taking too long to stop, interrupting; thread dump if > 3 attempts: i=
     495: invokevirtual #15                 // Method java/lang/StringBuilder.append:(Ljava/lang/String;)Ljava/lang/StringBuilder;
     498: iload         5
     500: invokevirtual #111                // Method java/lang/StringBuilder.append:(I)Ljava/lang/StringBuilder;
     503: invokevirtual #20                 // Method java/lang/StringBuilder.toString:()Ljava/lang/String;
     506: invokeinterface #107,  2          // InterfaceMethod org/slf4j/Logger.warn:(Ljava/lang/String;)V
     511: iload         5
     513: iconst_3
     514: if_icmple     546
     517: getstatic     #67                 // Field java/lang/System.out:Ljava/io/PrintStream;
     520: new           #12                 // class java/lang/StringBuilder
     523: dup
     524: invokespecial #13                 // Method java/lang/StringBuilder."<init>":()V
     527: ldc           #112                // String Thread dump
     529: invokevirtual #15                 // Method java/lang/StringBuilder.append:(Ljava/lang/String;)Ljava/lang/StringBuilder;
     532: aload         8
     534: invokevirtual #113                // Method org/apache/hadoop/hbase/util/JVMClusterUtil$RegionServerThread.getName:()Ljava/lang/String;
     537: invokevirtual #15                 // Method java/lang/StringBuilder.append:(Ljava/lang/String;)Ljava/lang/StringBuilder;
     540: invokevirtual #20                 // Method java/lang/StringBuilder.toString:()Ljava/lang/String;
     543: invokestatic  #69                 // Method org/apache/hadoop/hbase/util/Threads.printThreadInfo:(Ljava/io/PrintStream;Ljava/lang/String;)V
     546: aload         8
     548: invokevirtual #114                // Method org/apache/hadoop/hbase/util/JVMClusterUtil$RegionServerThread.interrupt:()V
     551: goto          453
     554: iinc          5, 1
     557: goto          358
     560: aload_0
     561: ifnull        645
     564: aload_0
     565: invokeinterface #32,  1           // InterfaceMethod java/util/List.iterator:()Ljava/util/Iterator;
     570: astore        5
     572: aload         5
     574: invokeinterface #33,  1           // InterfaceMethod java/util/Iterator.hasNext:()Z
     579: ifeq          645
     582: aload         5
     584: invokeinterface #34,  1           // InterfaceMethod java/util/Iterator.next:()Ljava/lang/Object;
     589: checkcast     #30                 // class org/apache/hadoop/hbase/util/JVMClusterUtil$MasterThread
     592: astore        6
     594: aload         6
     596: invokestatic  #35                 // Method org/apache/hadoop/hbase/util/JVMClusterUtil$MasterThread.access$000:(Lorg/apache/hadoop/hbase/util/JVMClusterUtil$MasterThread;)Lorg/apache/hadoop/hbase/master/HMaster;
     599: invokevirtual #115                // Method org/apache/hadoop/hbase/master/HMaster.isAlive:()Z
     602: ifeq          642
     605: iload_2
     606: ifne          642
     609: aload         6
     611: invokestatic  #35                 // Method org/apache/hadoop/hbase/util/JVMClusterUtil$MasterThread.access$000:(Lorg/apache/hadoop/hbase/util/JVMClusterUtil$MasterThread;)Lorg/apache/hadoop/hbase/master/HMaster;
     614: invokevirtual #116                // Method org/apache/hadoop/hbase/master/HMaster.getThread:()Ljava/lang/Thread;
     617: invokestatic  #117                // Method org/apache/hadoop/hbase/util/Threads.threadDumpingIsAlive:(Ljava/lang/Thread;)V
     620: goto          594
     623: astore        7
     625: getstatic     #78                 // Field LOG:Lorg/slf4j/Logger;
     628: ldc           #118                // String Got InterruptedException on shutdown - not waiting anymore on master ends
     630: aload         7
     632: invokeinterface #105,  3          // InterfaceMethod org/slf4j/Logger.info:(Ljava/lang/String;Ljava/lang/Throwable;)V
     637: iconst_1
     638: istore_2
     639: goto          594
     642: goto          572
     645: getstatic     #78                 // Field LOG:Lorg/slf4j/Logger;
     648: new           #12                 // class java/lang/StringBuilder
     651: dup
     652: invokespecial #13                 // Method java/lang/StringBuilder."<init>":()V
     655: ldc           #119                // String Shutdown of
     657: invokevirtual #15                 // Method java/lang/StringBuilder.append:(Ljava/lang/String;)Ljava/lang/StringBuilder;
     660: aload_0
     661: ifnull        676
     664: aload_0
     665: invokeinterface #120,  1          // InterfaceMethod java/util/List.size:()I
     670: invokestatic  #87                 // Method java/lang/Integer.valueOf:(I)Ljava/lang/Integer;
     673: goto          678
     676: ldc           #121                // String 0
     678: invokevirtual #122                // Method java/lang/StringBuilder.append:(Ljava/lang/Object;)Ljava/lang/StringBuilder;
     681: ldc           #123                // String  master(s) and
     683: invokevirtual #15                 // Method java/lang/StringBuilder.append:(Ljava/lang/String;)Ljava/lang/StringBuilder;
     686: aload_1
     687: ifnull        702
     690: aload_1
     691: invokeinterface #120,  1          // InterfaceMethod java/util/List.size:()I
     696: invokestatic  #87                 // Method java/lang/Integer.valueOf:(I)Ljava/lang/Integer;
     699: goto          704
     702: ldc           #121                // String 0
     704: invokevirtual #122                // Method java/lang/StringBuilder.append:(Ljava/lang/Object;)Ljava/lang/StringBuilder;
     707: ldc           #124                // String  regionserver(s)
     709: invokevirtual #15                 // Method java/lang/StringBuilder.append:(Ljava/lang/String;)Ljava/lang/StringBuilder;
     712: iload_2
     713: ifeq          721
     716: ldc           #125                // String interrupted
     718: goto          723
     721: ldc           #126                // String complete
     723: invokevirtual #15                 // Method java/lang/StringBuilder.append:(Ljava/lang/String;)Ljava/lang/StringBuilder;
     726: invokevirtual #20                 // Method java/lang/StringBuilder.toString:()Ljava/lang/String;
     729: invokeinterface #127,  2          // InterfaceMethod org/slf4j/Logger.info:(Ljava/lang/String;)V
     734: iload_2
     735: ifeq          744
     738: invokestatic  #128                // Method java/lang/Thread.currentThread:()Ljava/lang/Thread;
     741: invokevirtual #129                // Method java/lang/Thread.interrupt:()V
     744: return
    Exception table:
       from    to  target type
          65    73    76   Class java/io/IOException
         191   198   201   Class java/io/IOException
         324   333   336   Class java/lang/InterruptedException
         409   427   430   Class java/lang/InterruptedException
         609   620   623   Class java/lang/InterruptedException

  static {};
    Code:
       0: ldc           #131                // class org/apache/hadoop/hbase/util/JVMClusterUtil
       2: invokestatic  #132                // Method org/slf4j/LoggerFactory.getLogger:(Ljava/lang/Class;)Lorg/slf4j/Logger;
       5: putstatic     #78                 // Field LOG:Lorg/slf4j/Logger;
       8: return
}
