Compiled from "KeyProviderForTesting.java"
public class org.apache.hadoop.hbase.io.crypto.KeyProviderForTesting implements org.apache.hadoop.hbase.io.crypto.KeyProvider {
  public org.apache.hadoop.hbase.io.crypto.KeyProviderForTesting();
    Code:
       0: aload_0
       1: invokespecial #1                  // Method java/lang/Object."<init>":()V
       4: return

  public void init(java.lang.String);
    Code:
       0: return

  public java.security.Key getKey(java.lang.String);
    Code:
       0: new           #2                  // class javax/crypto/spec/SecretKeySpec
       3: dup
       4: iconst_1
       5: anewarray     #3                  // class java/lang/String
       8: dup
       9: iconst_0
      10: aload_1
      11: aastore
      12: invokestatic  #4                  // Method org/apache/hadoop/hbase/io/crypto/Encryption.hash128:([Ljava/lang/String;)[B
      15: ldc           #5                  // String AES
      17: invokespecial #6                  // Method javax/crypto/spec/SecretKeySpec."<init>":([BLjava/lang/String;)V
      20: areturn

  public java.security.Key[] getKeys(java.lang.String[]);
    Code:
       0: aload_1
       1: arraylength
       2: anewarray     #7                  // class java/security/Key
       5: astore_2
       6: iconst_0
       7: istore_3
       8: iload_3
       9: aload_1
      10: arraylength
      11: if_icmpge     45
      14: aload_2
      15: iload_3
      16: new           #2                  // class javax/crypto/spec/SecretKeySpec
      19: dup
      20: iconst_1
      21: anewarray     #3                  // class java/lang/String
      24: dup
      25: iconst_0
      26: aload_1
      27: iload_3
      28: aaload
      29: aastore
      30: invokestatic  #4                  // Method org/apache/hadoop/hbase/io/crypto/Encryption.hash128:([Ljava/lang/String;)[B
      33: ldc           #5                  // String AES
      35: invokespecial #6                  // Method javax/crypto/spec/SecretKeySpec."<init>":([BLjava/lang/String;)V
      38: aastore
      39: iinc          3, 1
      42: goto          8
      45: aload_2
      46: areturn
}
