Compiled from "KeyPrefixRegionSplitPolicy.java"
public class org.apache.hadoop.hbase.regionserver.KeyPrefixRegionSplitPolicy extends org.apache.hadoop.hbase.regionserver.IncreasingToUpperBoundRegionSplitPolicy {
  public static final java.lang.String PREFIX_LENGTH_KEY_DEPRECATED;

  public static final java.lang.String PREFIX_LENGTH_KEY;

  public org.apache.hadoop.hbase.regionserver.KeyPrefixRegionSplitPolicy();
    Code:
       0: aload_0
       1: invokespecial #1                  // Method org/apache/hadoop/hbase/regionserver/IncreasingToUpperBoundRegionSplitPolicy."<init>":()V
       4: aload_0
       5: iconst_0
       6: putfield      #2                  // Field prefixLength:I
       9: return

  protected void configureForRegion(org.apache.hadoop.hbase.regionserver.HRegion);
    Code:
       0: aload_0
       1: aload_1
       2: invokespecial #3                  // Method org/apache/hadoop/hbase/regionserver/IncreasingToUpperBoundRegionSplitPolicy.configureForRegion:(Lorg/apache/hadoop/hbase/regionserver/HRegion;)V
       5: aload_0
       6: iconst_0
       7: putfield      #2                  // Field prefixLength:I
      10: aload_1
      11: invokevirtual #4                  // Method org/apache/hadoop/hbase/regionserver/HRegion.getTableDescriptor:()Lorg/apache/hadoop/hbase/client/TableDescriptor;
      14: ldc           #6                  // String KeyPrefixRegionSplitPolicy.prefix_length
      16: invokeinterface #7,  2            // InterfaceMethod org/apache/hadoop/hbase/client/TableDescriptor.getValue:(Ljava/lang/String;)Ljava/lang/String;
      21: astore_2
      22: aload_2
      23: ifnonnull     83
      26: aload_1
      27: invokevirtual #4                  // Method org/apache/hadoop/hbase/regionserver/HRegion.getTableDescriptor:()Lorg/apache/hadoop/hbase/client/TableDescriptor;
      30: ldc           #8                  // String prefix_split_key_policy.prefix_length
      32: invokeinterface #7,  2            // InterfaceMethod org/apache/hadoop/hbase/client/TableDescriptor.getValue:(Ljava/lang/String;)Ljava/lang/String;
      37: astore_2
      38: aload_2
      39: ifnonnull     83
      42: getstatic     #9                  // Field LOG:Lorg/slf4j/Logger;
      45: new           #10                 // class java/lang/StringBuilder
      48: dup
      49: invokespecial #11                 // Method java/lang/StringBuilder."<init>":()V
      52: ldc           #12                 // String KeyPrefixRegionSplitPolicy.prefix_length not specified for table
      54: invokevirtual #13                 // Method java/lang/StringBuilder.append:(Ljava/lang/String;)Ljava/lang/StringBuilder;
      57: aload_1
      58: invokevirtual #4                  // Method org/apache/hadoop/hbase/regionserver/HRegion.getTableDescriptor:()Lorg/apache/hadoop/hbase/client/TableDescriptor;
      61: invokeinterface #14,  1           // InterfaceMethod org/apache/hadoop/hbase/client/TableDescriptor.getTableName:()Lorg/apache/hadoop/hbase/TableName;
      66: invokevirtual #15                 // Method java/lang/StringBuilder.append:(Ljava/lang/Object;)Ljava/lang/StringBuilder;
      69: ldc           #16                 // String . Using default RegionSplitPolicy
      71: invokevirtual #13                 // Method java/lang/StringBuilder.append:(Ljava/lang/String;)Ljava/lang/StringBuilder;
      74: invokevirtual #17                 // Method java/lang/StringBuilder.toString:()Ljava/lang/String;
      77: invokeinterface #18,  2           // InterfaceMethod org/slf4j/Logger.error:(Ljava/lang/String;)V
      82: return
      83: aload_0
      84: aload_2
      85: invokestatic  #19                 // Method java/lang/Integer.parseInt:(Ljava/lang/String;)I
      88: putfield      #2                  // Field prefixLength:I
      91: goto          149
      94: astore_3
      95: getstatic     #9                  // Field LOG:Lorg/slf4j/Logger;
      98: new           #10                 // class java/lang/StringBuilder
     101: dup
     102: invokespecial #11                 // Method java/lang/StringBuilder."<init>":()V
     105: ldc           #21                 // String Number format exception when parsing KeyPrefixRegionSplitPolicy.prefix_length for table
     107: invokevirtual #13                 // Method java/lang/StringBuilder.append:(Ljava/lang/String;)Ljava/lang/StringBuilder;
     110: aload_1
     111: invokevirtual #4                  // Method org/apache/hadoop/hbase/regionserver/HRegion.getTableDescriptor:()Lorg/apache/hadoop/hbase/client/TableDescriptor;
     114: invokeinterface #14,  1           // InterfaceMethod org/apache/hadoop/hbase/client/TableDescriptor.getTableName:()Lorg/apache/hadoop/hbase/TableName;
     119: invokevirtual #15                 // Method java/lang/StringBuilder.append:(Ljava/lang/Object;)Ljava/lang/StringBuilder;
     122: ldc           #22                 // String :
     124: invokevirtual #13                 // Method java/lang/StringBuilder.append:(Ljava/lang/String;)Ljava/lang/StringBuilder;
     127: aload_2
     128: invokevirtual #13                 // Method java/lang/StringBuilder.append:(Ljava/lang/String;)Ljava/lang/StringBuilder;
     131: ldc           #23                 // String .
     133: invokevirtual #13                 // Method java/lang/StringBuilder.append:(Ljava/lang/String;)Ljava/lang/StringBuilder;
     136: aload_3
     137: invokevirtual #15                 // Method java/lang/StringBuilder.append:(Ljava/lang/Object;)Ljava/lang/StringBuilder;
     140: invokevirtual #17                 // Method java/lang/StringBuilder.toString:()Ljava/lang/String;
     143: invokeinterface #18,  2           // InterfaceMethod org/slf4j/Logger.error:(Ljava/lang/String;)V
     148: return
     149: aload_0
     150: getfield      #2                  // Field prefixLength:I
     153: ifgt          205
     156: getstatic     #9                  // Field LOG:Lorg/slf4j/Logger;
     159: new           #10                 // class java/lang/StringBuilder
     162: dup
     163: invokespecial #11                 // Method java/lang/StringBuilder."<init>":()V
     166: ldc           #24                 // String Invalid value for KeyPrefixRegionSplitPolicy.prefix_length for table
     168: invokevirtual #13                 // Method java/lang/StringBuilder.append:(Ljava/lang/String;)Ljava/lang/StringBuilder;
     171: aload_1
     172: invokevirtual #4                  // Method org/apache/hadoop/hbase/regionserver/HRegion.getTableDescriptor:()Lorg/apache/hadoop/hbase/client/TableDescriptor;
     175: invokeinterface #14,  1           // InterfaceMethod org/apache/hadoop/hbase/client/TableDescriptor.getTableName:()Lorg/apache/hadoop/hbase/TableName;
     180: invokevirtual #15                 // Method java/lang/StringBuilder.append:(Ljava/lang/Object;)Ljava/lang/StringBuilder;
     183: ldc           #22                 // String :
     185: invokevirtual #13                 // Method java/lang/StringBuilder.append:(Ljava/lang/String;)Ljava/lang/StringBuilder;
     188: aload_2
     189: invokevirtual #13                 // Method java/lang/StringBuilder.append:(Ljava/lang/String;)Ljava/lang/StringBuilder;
     192: ldc           #16                 // String . Using default RegionSplitPolicy
     194: invokevirtual #13                 // Method java/lang/StringBuilder.append:(Ljava/lang/String;)Ljava/lang/StringBuilder;
     197: invokevirtual #17                 // Method java/lang/StringBuilder.toString:()Ljava/lang/String;
     200: invokeinterface #18,  2           // InterfaceMethod org/slf4j/Logger.error:(Ljava/lang/String;)V
     205: return
    Exception table:
       from    to  target type
          83    91    94   Class java/lang/NumberFormatException

  protected byte[] getSplitPoint();
    Code:
       0: aload_0
       1: invokespecial #25                 // Method org/apache/hadoop/hbase/regionserver/IncreasingToUpperBoundRegionSplitPolicy.getSplitPoint:()[B
       4: astore_1
       5: aload_0
       6: getfield      #2                  // Field prefixLength:I
       9: ifle          35
      12: aload_1
      13: ifnull        35
      16: aload_1
      17: arraylength
      18: ifle          35
      21: aload_1
      22: aload_0
      23: getfield      #2                  // Field prefixLength:I
      26: aload_1
      27: arraylength
      28: invokestatic  #26                 // Method java/lang/Math.min:(II)I
      31: invokestatic  #27                 // Method java/util/Arrays.copyOf:([BI)[B
      34: areturn
      35: aload_1
      36: areturn

  static {};
    Code:
       0: ldc           #5                  // class org/apache/hadoop/hbase/regionserver/KeyPrefixRegionSplitPolicy
       2: invokestatic  #28                 // Method org/slf4j/LoggerFactory.getLogger:(Ljava/lang/Class;)Lorg/slf4j/Logger;
       5: putstatic     #9                  // Field LOG:Lorg/slf4j/Logger;
       8: return
}
