Compiled from "KeyValueCodec.java"
public class org.apache.hadoop.hbase.codec.KeyValueCodec$ByteBuffKeyValueDecoder implements org.apache.hadoop.hbase.codec.Codec$Decoder {
  protected final org.apache.hadoop.hbase.nio.ByteBuff buf;

  protected org.apache.hadoop.hbase.Cell current;

  public org.apache.hadoop.hbase.codec.KeyValueCodec$ByteBuffKeyValueDecoder(org.apache.hadoop.hbase.nio.ByteBuff);
    Code:
       0: aload_0
       1: invokespecial #1                  // Method java/lang/Object."<init>":()V
       4: aload_0
       5: aconst_null
       6: putfield      #2                  // Field current:Lorg/apache/hadoop/hbase/Cell;
       9: aload_0
      10: aload_1
      11: putfield      #3                  // Field buf:Lorg/apache/hadoop/hbase/nio/ByteBuff;
      14: return

  public boolean advance() throws java.io.IOException;
    Code:
       0: aload_0
       1: getfield      #3                  // Field buf:Lorg/apache/hadoop/hbase/nio/ByteBuff;
       4: invokevirtual #4                  // Method org/apache/hadoop/hbase/nio/ByteBuff.hasRemaining:()Z
       7: ifne          12
      10: iconst_0
      11: ireturn
      12: aload_0
      13: getfield      #3                  // Field buf:Lorg/apache/hadoop/hbase/nio/ByteBuff;
      16: invokevirtual #5                  // Method org/apache/hadoop/hbase/nio/ByteBuff.getInt:()I
      19: istore_1
      20: aload_0
      21: getfield      #3                  // Field buf:Lorg/apache/hadoop/hbase/nio/ByteBuff;
      24: iload_1
      25: invokevirtual #6                  // Method org/apache/hadoop/hbase/nio/ByteBuff.asSubByteBuffer:(I)Ljava/nio/ByteBuffer;
      28: astore_2
      29: aload_2
      30: invokevirtual #7                  // Method java/nio/ByteBuffer.isDirect:()Z
      33: ifeq          53
      36: aload_0
      37: aload_0
      38: aload_2
      39: aload_2
      40: invokevirtual #8                  // Method java/nio/ByteBuffer.position:()I
      43: iload_1
      44: invokevirtual #9                  // Method createCell:(Ljava/nio/ByteBuffer;II)Lorg/apache/hadoop/hbase/Cell;
      47: putfield      #2                  // Field current:Lorg/apache/hadoop/hbase/Cell;
      50: goto          75
      53: aload_0
      54: aload_0
      55: aload_2
      56: invokevirtual #10                 // Method java/nio/ByteBuffer.array:()[B
      59: aload_2
      60: invokevirtual #11                 // Method java/nio/ByteBuffer.arrayOffset:()I
      63: aload_2
      64: invokevirtual #8                  // Method java/nio/ByteBuffer.position:()I
      67: iadd
      68: iload_1
      69: invokevirtual #12                 // Method createCell:([BII)Lorg/apache/hadoop/hbase/Cell;
      72: putfield      #2                  // Field current:Lorg/apache/hadoop/hbase/Cell;
      75: aload_0
      76: getfield      #3                  // Field buf:Lorg/apache/hadoop/hbase/nio/ByteBuff;
      79: iload_1
      80: invokevirtual #13                 // Method org/apache/hadoop/hbase/nio/ByteBuff.skip:(I)Lorg/apache/hadoop/hbase/nio/ByteBuff;
      83: pop
      84: iconst_1
      85: ireturn

  public org.apache.hadoop.hbase.Cell current();
    Code:
       0: aload_0
       1: getfield      #2                  // Field current:Lorg/apache/hadoop/hbase/Cell;
       4: areturn

  protected org.apache.hadoop.hbase.Cell createCell(byte[], int, int);
    Code:
       0: new           #14                 // class org/apache/hadoop/hbase/NoTagsKeyValue
       3: dup
       4: aload_1
       5: iload_2
       6: iload_3
       7: invokespecial #15                 // Method org/apache/hadoop/hbase/NoTagsKeyValue."<init>":([BII)V
      10: areturn

  protected org.apache.hadoop.hbase.Cell createCell(java.nio.ByteBuffer, int, int);
    Code:
       0: new           #16                 // class org/apache/hadoop/hbase/NoTagsByteBufferKeyValue
       3: dup
       4: aload_1
       5: iload_2
       6: iload_3
       7: invokespecial #17                 // Method org/apache/hadoop/hbase/NoTagsByteBufferKeyValue."<init>":(Ljava/nio/ByteBuffer;II)V
      10: areturn
}
