Compiled from "KeyValueTestUtil.java"
public class org.apache.hadoop.hbase.KeyValueTestUtil {
  public org.apache.hadoop.hbase.KeyValueTestUtil();
    Code:
       0: aload_0
       1: invokespecial #1                  // Method java/lang/Object."<init>":()V
       4: return

  public static org.apache.hadoop.hbase.KeyValue create(java.lang.String, java.lang.String, java.lang.String, long, java.lang.String);
    Code:
       0: aload_0
       1: aload_1
       2: aload_2
       3: lload_3
       4: getstatic     #2                  // Field org/apache/hadoop/hbase/KeyValue$Type.Put:Lorg/apache/hadoop/hbase/KeyValue$Type;
       7: aload         5
       9: invokestatic  #3                  // Method create:(Ljava/lang/String;Ljava/lang/String;Ljava/lang/String;JLorg/apache/hadoop/hbase/KeyValue$Type;Ljava/lang/String;)Lorg/apache/hadoop/hbase/KeyValue;
      12: areturn

  public static org.apache.hadoop.hbase.KeyValue create(java.lang.String, java.lang.String, java.lang.String, long, org.apache.hadoop.hbase.KeyValue$Type, java.lang.String);
    Code:
       0: new           #4                  // class org/apache/hadoop/hbase/KeyValue
       3: dup
       4: aload_0
       5: invokestatic  #5                  // Method org/apache/hadoop/hbase/util/Bytes.toBytes:(Ljava/lang/String;)[B
       8: aload_1
       9: invokestatic  #5                  // Method org/apache/hadoop/hbase/util/Bytes.toBytes:(Ljava/lang/String;)[B
      12: aload_2
      13: invokestatic  #5                  // Method org/apache/hadoop/hbase/util/Bytes.toBytes:(Ljava/lang/String;)[B
      16: lload_3
      17: aload         5
      19: aload         6
      21: invokestatic  #5                  // Method org/apache/hadoop/hbase/util/Bytes.toBytes:(Ljava/lang/String;)[B
      24: invokespecial #6                  // Method org/apache/hadoop/hbase/KeyValue."<init>":([B[B[BJLorg/apache/hadoop/hbase/KeyValue$Type;[B)V
      27: areturn

  public static java.nio.ByteBuffer toByteBufferAndRewind(java.lang.Iterable<? extends org.apache.hadoop.hbase.KeyValue>, boolean);
    Code:
       0: aload_0
       1: iload_1
       2: invokestatic  #7                  // Method org/apache/hadoop/hbase/KeyValueUtil.totalLengthWithMvccVersion:(Ljava/lang/Iterable;Z)I
       5: istore_2
       6: iload_2
       7: invokestatic  #8                  // Method java/nio/ByteBuffer.allocate:(I)Ljava/nio/ByteBuffer;
      10: astore_3
      11: aload_0
      12: invokestatic  #9                  // Method org/apache/hbase/thirdparty/org/apache/commons/collections4/IterableUtils.emptyIfNull:(Ljava/lang/Iterable;)Ljava/lang/Iterable;
      15: invokeinterface #10,  1           // InterfaceMethod java/lang/Iterable.iterator:()Ljava/util/Iterator;
      20: astore        4
      22: aload         4
      24: invokeinterface #11,  1           // InterfaceMethod java/util/Iterator.hasNext:()Z
      29: ifeq          54
      32: aload         4
      34: invokeinterface #12,  1           // InterfaceMethod java/util/Iterator.next:()Ljava/lang/Object;
      39: checkcast     #4                  // class org/apache/hadoop/hbase/KeyValue
      42: astore        5
      44: aload_3
      45: aload         5
      47: iload_1
      48: invokestatic  #13                 // Method org/apache/hadoop/hbase/KeyValueUtil.appendToByteBuffer:(Ljava/nio/ByteBuffer;Lorg/apache/hadoop/hbase/KeyValue;Z)V
      51: goto          22
      54: aload_3
      55: invokevirtual #14                 // Method java/nio/ByteBuffer.rewind:()Ljava/nio/Buffer;
      58: pop
      59: aload_3
      60: areturn

  public static boolean containsIgnoreMvccVersion(java.util.Collection<? extends org.apache.hadoop.hbase.Cell>, java.util.Collection<? extends org.apache.hadoop.hbase.Cell>);
    Code:
       0: aload_0
       1: invokeinterface #15,  1           // InterfaceMethod java/util/Collection.iterator:()Ljava/util/Iterator;
       6: astore_2
       7: aload_2
       8: invokeinterface #11,  1           // InterfaceMethod java/util/Iterator.hasNext:()Z
      13: ifeq          84
      16: aload_2
      17: invokeinterface #12,  1           // InterfaceMethod java/util/Iterator.next:()Ljava/lang/Object;
      22: checkcast     #16                 // class org/apache/hadoop/hbase/Cell
      25: astore_3
      26: iconst_0
      27: istore        4
      29: aload_1
      30: invokeinterface #15,  1           // InterfaceMethod java/util/Collection.iterator:()Ljava/util/Iterator;
      35: astore        5
      37: aload         5
      39: invokeinterface #11,  1           // InterfaceMethod java/util/Iterator.hasNext:()Z
      44: ifeq          74
      47: aload         5
      49: invokeinterface #12,  1           // InterfaceMethod java/util/Iterator.next:()Ljava/lang/Object;
      54: checkcast     #16                 // class org/apache/hadoop/hbase/Cell
      57: astore        6
      59: aload_3
      60: aload         6
      62: invokestatic  #17                 // Method org/apache/hadoop/hbase/PrivateCellUtil.equalsIgnoreMvccVersion:(Lorg/apache/hadoop/hbase/Cell;Lorg/apache/hadoop/hbase/Cell;)Z
      65: ifeq          71
      68: iconst_1
      69: istore        4
      71: goto          37
      74: iload         4
      76: ifne          81
      79: iconst_0
      80: ireturn
      81: goto          7
      84: iconst_1
      85: ireturn

  public static java.util.List<org.apache.hadoop.hbase.KeyValue> rewindThenToList(java.nio.ByteBuffer, boolean, boolean);
    Code:
       0: aload_0
       1: invokevirtual #14                 // Method java/nio/ByteBuffer.rewind:()Ljava/nio/Buffer;
       4: pop
       5: invokestatic  #18                 // Method org/apache/hbase/thirdparty/com/google/common/collect/Lists.newArrayList:()Ljava/util/ArrayList;
       8: astore_3
       9: aconst_null
      10: astore        4
      12: aload_0
      13: iload_1
      14: iload_2
      15: invokestatic  #19                 // Method org/apache/hadoop/hbase/KeyValueUtil.nextShallowCopy:(Ljava/nio/ByteBuffer;ZZ)Lorg/apache/hadoop/hbase/KeyValue;
      18: astore        4
      20: aload         4
      22: ifnonnull     28
      25: goto          40
      28: aload_3
      29: aload         4
      31: invokeinterface #20,  2           // InterfaceMethod java/util/List.add:(Ljava/lang/Object;)Z
      36: pop
      37: goto          12
      40: aload_3
      41: areturn

  public static java.lang.String toStringWithPadding(java.util.Collection<? extends org.apache.hadoop.hbase.KeyValue>, boolean);
    Code:
       0: iconst_0
       1: istore_2
       2: iconst_0
       3: istore_3
       4: iconst_0
       5: istore        4
       7: iconst_0
       8: istore        5
      10: aload_0
      11: invokeinterface #15,  1           // InterfaceMethod java/util/Collection.iterator:()Ljava/util/Iterator;
      16: astore        6
      18: aload         6
      20: invokeinterface #11,  1           // InterfaceMethod java/util/Iterator.hasNext:()Z
      25: ifeq          105
      28: aload         6
      30: invokeinterface #12,  1           // InterfaceMethod java/util/Iterator.next:()Ljava/lang/Object;
      35: checkcast     #4                  // class org/apache/hadoop/hbase/KeyValue
      38: astore        7
      40: iload_2
      41: aload         7
      43: invokestatic  #21                 // Method getRowString:(Lorg/apache/hadoop/hbase/KeyValue;)Ljava/lang/String;
      46: invokevirtual #22                 // Method java/lang/String.length:()I
      49: invokestatic  #23                 // Method java/lang/Math.max:(II)I
      52: istore_2
      53: iload_3
      54: aload         7
      56: invokestatic  #24                 // Method getFamilyString:(Lorg/apache/hadoop/hbase/KeyValue;)Ljava/lang/String;
      59: invokevirtual #22                 // Method java/lang/String.length:()I
      62: invokestatic  #23                 // Method java/lang/Math.max:(II)I
      65: istore_3
      66: iload         4
      68: aload         7
      70: invokestatic  #25                 // Method getQualifierString:(Lorg/apache/hadoop/hbase/KeyValue;)Ljava/lang/String;
      73: invokevirtual #22                 // Method java/lang/String.length:()I
      76: invokestatic  #23                 // Method java/lang/Math.max:(II)I
      79: istore        4
      81: iload         5
      83: aload         7
      85: invokevirtual #26                 // Method org/apache/hadoop/hbase/KeyValue.getTimestamp:()J
      88: invokestatic  #27                 // Method java/lang/Long.valueOf:(J)Ljava/lang/Long;
      91: invokevirtual #28                 // Method java/lang/Long.toString:()Ljava/lang/String;
      94: invokevirtual #22                 // Method java/lang/String.length:()I
      97: invokestatic  #23                 // Method java/lang/Math.max:(II)I
     100: istore        5
     102: goto          18
     105: new           #29                 // class java/lang/StringBuilder
     108: dup
     109: invokespecial #30                 // Method java/lang/StringBuilder."<init>":()V
     112: astore        6
     114: aload_0
     115: invokeinterface #15,  1           // InterfaceMethod java/util/Collection.iterator:()Ljava/util/Iterator;
     120: astore        7
     122: aload         7
     124: invokeinterface #11,  1           // InterfaceMethod java/util/Iterator.hasNext:()Z
     129: ifeq          185
     132: aload         7
     134: invokeinterface #12,  1           // InterfaceMethod java/util/Iterator.next:()Ljava/lang/Object;
     139: checkcast     #4                  // class org/apache/hadoop/hbase/KeyValue
     142: astore        8
     144: aload         6
     146: invokevirtual #31                 // Method java/lang/StringBuilder.length:()I
     149: ifle          160
     152: aload         6
     154: ldc           #32                 // String \n
     156: invokevirtual #33                 // Method java/lang/StringBuilder.append:(Ljava/lang/String;)Ljava/lang/StringBuilder;
     159: pop
     160: aload         8
     162: iload_2
     163: iload_3
     164: iload         4
     166: iload         5
     168: iload_1
     169: invokestatic  #34                 // Method toStringWithPadding:(Lorg/apache/hadoop/hbase/KeyValue;IIIIZ)Ljava/lang/String;
     172: astore        9
     174: aload         6
     176: aload         9
     178: invokevirtual #33                 // Method java/lang/StringBuilder.append:(Ljava/lang/String;)Ljava/lang/StringBuilder;
     181: pop
     182: goto          122
     185: aload         6
     187: invokevirtual #35                 // Method java/lang/StringBuilder.toString:()Ljava/lang/String;
     190: areturn

  protected static java.lang.String toStringWithPadding(org.apache.hadoop.hbase.KeyValue, int, int, int, int, boolean);
    Code:
       0: ldc           #36                 // String
       2: astore        6
       4: new           #29                 // class java/lang/StringBuilder
       7: dup
       8: invokespecial #30                 // Method java/lang/StringBuilder."<init>":()V
      11: aload_0
      12: invokevirtual #37                 // Method org/apache/hadoop/hbase/KeyValue.getFamilyLength:()B
      15: invokevirtual #38                 // Method java/lang/StringBuilder.append:(I)Ljava/lang/StringBuilder;
      18: ldc           #39                 // String
      20: invokevirtual #33                 // Method java/lang/StringBuilder.append:(Ljava/lang/String;)Ljava/lang/StringBuilder;
      23: invokevirtual #35                 // Method java/lang/StringBuilder.toString:()Ljava/lang/String;
      26: astore        7
      28: iload         5
      30: ifeq          243
      33: new           #29                 // class java/lang/StringBuilder
      36: dup
      37: invokespecial #30                 // Method java/lang/StringBuilder."<init>":()V
      40: aload         6
      42: invokevirtual #33                 // Method java/lang/StringBuilder.append:(Ljava/lang/String;)Ljava/lang/StringBuilder;
      45: new           #29                 // class java/lang/StringBuilder
      48: dup
      49: invokespecial #30                 // Method java/lang/StringBuilder."<init>":()V
      52: aload_0
      53: invokevirtual #40                 // Method org/apache/hadoop/hbase/KeyValue.getKeyLength:()I
      56: invokevirtual #38                 // Method java/lang/StringBuilder.append:(I)Ljava/lang/StringBuilder;
      59: ldc           #36                 // String
      61: invokevirtual #33                 // Method java/lang/StringBuilder.append:(Ljava/lang/String;)Ljava/lang/StringBuilder;
      64: invokevirtual #35                 // Method java/lang/StringBuilder.toString:()Ljava/lang/String;
      67: bipush        48
      69: iconst_4
      70: invokestatic  #41                 // Method org/apache/hadoop/hbase/util/Strings.padFront:(Ljava/lang/String;CI)Ljava/lang/String;
      73: invokevirtual #33                 // Method java/lang/StringBuilder.append:(Ljava/lang/String;)Ljava/lang/StringBuilder;
      76: invokevirtual #35                 // Method java/lang/StringBuilder.toString:()Ljava/lang/String;
      79: astore        6
      81: new           #29                 // class java/lang/StringBuilder
      84: dup
      85: invokespecial #30                 // Method java/lang/StringBuilder."<init>":()V
      88: aload         6
      90: invokevirtual #33                 // Method java/lang/StringBuilder.append:(Ljava/lang/String;)Ljava/lang/StringBuilder;
      93: ldc           #39                 // String
      95: invokevirtual #33                 // Method java/lang/StringBuilder.append:(Ljava/lang/String;)Ljava/lang/StringBuilder;
      98: invokevirtual #35                 // Method java/lang/StringBuilder.toString:()Ljava/lang/String;
     101: astore        6
     103: new           #29                 // class java/lang/StringBuilder
     106: dup
     107: invokespecial #30                 // Method java/lang/StringBuilder."<init>":()V
     110: aload         6
     112: invokevirtual #33                 // Method java/lang/StringBuilder.append:(Ljava/lang/String;)Ljava/lang/StringBuilder;
     115: new           #29                 // class java/lang/StringBuilder
     118: dup
     119: invokespecial #30                 // Method java/lang/StringBuilder."<init>":()V
     122: aload_0
     123: invokevirtual #42                 // Method org/apache/hadoop/hbase/KeyValue.getValueLength:()I
     126: invokevirtual #38                 // Method java/lang/StringBuilder.append:(I)Ljava/lang/StringBuilder;
     129: ldc           #36                 // String
     131: invokevirtual #33                 // Method java/lang/StringBuilder.append:(Ljava/lang/String;)Ljava/lang/StringBuilder;
     134: invokevirtual #35                 // Method java/lang/StringBuilder.toString:()Ljava/lang/String;
     137: bipush        48
     139: iconst_4
     140: invokestatic  #41                 // Method org/apache/hadoop/hbase/util/Strings.padFront:(Ljava/lang/String;CI)Ljava/lang/String;
     143: invokevirtual #33                 // Method java/lang/StringBuilder.append:(Ljava/lang/String;)Ljava/lang/StringBuilder;
     146: invokevirtual #35                 // Method java/lang/StringBuilder.toString:()Ljava/lang/String;
     149: astore        6
     151: new           #29                 // class java/lang/StringBuilder
     154: dup
     155: invokespecial #30                 // Method java/lang/StringBuilder."<init>":()V
     158: aload         6
     160: invokevirtual #33                 // Method java/lang/StringBuilder.append:(Ljava/lang/String;)Ljava/lang/StringBuilder;
     163: ldc           #39                 // String
     165: invokevirtual #33                 // Method java/lang/StringBuilder.append:(Ljava/lang/String;)Ljava/lang/StringBuilder;
     168: invokevirtual #35                 // Method java/lang/StringBuilder.toString:()Ljava/lang/String;
     171: astore        6
     173: new           #29                 // class java/lang/StringBuilder
     176: dup
     177: invokespecial #30                 // Method java/lang/StringBuilder."<init>":()V
     180: aload         6
     182: invokevirtual #33                 // Method java/lang/StringBuilder.append:(Ljava/lang/String;)Ljava/lang/StringBuilder;
     185: new           #29                 // class java/lang/StringBuilder
     188: dup
     189: invokespecial #30                 // Method java/lang/StringBuilder."<init>":()V
     192: aload_0
     193: invokevirtual #43                 // Method org/apache/hadoop/hbase/KeyValue.getRowLength:()S
     196: invokevirtual #38                 // Method java/lang/StringBuilder.append:(I)Ljava/lang/StringBuilder;
     199: ldc           #36                 // String
     201: invokevirtual #33                 // Method java/lang/StringBuilder.append:(Ljava/lang/String;)Ljava/lang/StringBuilder;
     204: invokevirtual #35                 // Method java/lang/StringBuilder.toString:()Ljava/lang/String;
     207: bipush        48
     209: iconst_2
     210: invokestatic  #41                 // Method org/apache/hadoop/hbase/util/Strings.padFront:(Ljava/lang/String;CI)Ljava/lang/String;
     213: invokevirtual #33                 // Method java/lang/StringBuilder.append:(Ljava/lang/String;)Ljava/lang/StringBuilder;
     216: invokevirtual #35                 // Method java/lang/StringBuilder.toString:()Ljava/lang/String;
     219: astore        6
     221: new           #29                 // class java/lang/StringBuilder
     224: dup
     225: invokespecial #30                 // Method java/lang/StringBuilder."<init>":()V
     228: aload         6
     230: invokevirtual #33                 // Method java/lang/StringBuilder.append:(Ljava/lang/String;)Ljava/lang/StringBuilder;
     233: ldc           #39                 // String
     235: invokevirtual #33                 // Method java/lang/StringBuilder.append:(Ljava/lang/String;)Ljava/lang/StringBuilder;
     238: invokevirtual #35                 // Method java/lang/StringBuilder.toString:()Ljava/lang/String;
     241: astore        6
     243: iload_1
     244: aload_0
     245: invokestatic  #21                 // Method getRowString:(Lorg/apache/hadoop/hbase/KeyValue;)Ljava/lang/String;
     248: invokevirtual #22                 // Method java/lang/String.length:()I
     251: isub
     252: iconst_2
     253: iadd
     254: istore        8
     256: iload_2
     257: aload_0
     258: invokestatic  #24                 // Method getFamilyString:(Lorg/apache/hadoop/hbase/KeyValue;)Ljava/lang/String;
     261: invokevirtual #22                 // Method java/lang/String.length:()I
     264: isub
     265: iconst_2
     266: iadd
     267: istore        9
     269: iload_3
     270: aload_0
     271: invokestatic  #25                 // Method getQualifierString:(Lorg/apache/hadoop/hbase/KeyValue;)Ljava/lang/String;
     274: invokevirtual #22                 // Method java/lang/String.length:()I
     277: isub
     278: iconst_1
     279: iadd
     280: istore        10
     282: iload         4
     284: aload_0
     285: invokevirtual #26                 // Method org/apache/hadoop/hbase/KeyValue.getTimestamp:()J
     288: invokestatic  #27                 // Method java/lang/Long.valueOf:(J)Ljava/lang/Long;
     291: invokevirtual #28                 // Method java/lang/Long.toString:()Ljava/lang/String;
     294: invokevirtual #22                 // Method java/lang/String.length:()I
     297: isub
     298: iconst_1
     299: iadd
     300: istore        11
     302: new           #29                 // class java/lang/StringBuilder
     305: dup
     306: invokespecial #30                 // Method java/lang/StringBuilder."<init>":()V
     309: aload         6
     311: invokevirtual #33                 // Method java/lang/StringBuilder.append:(Ljava/lang/String;)Ljava/lang/StringBuilder;
     314: aload_0
     315: invokestatic  #21                 // Method getRowString:(Lorg/apache/hadoop/hbase/KeyValue;)Ljava/lang/String;
     318: invokevirtual #33                 // Method java/lang/StringBuilder.append:(Ljava/lang/String;)Ljava/lang/StringBuilder;
     321: bipush        32
     323: iload         8
     325: invokestatic  #44                 // Method org/apache/commons/lang3/StringUtils.repeat:(CI)Ljava/lang/String;
     328: invokevirtual #33                 // Method java/lang/StringBuilder.append:(Ljava/lang/String;)Ljava/lang/StringBuilder;
     331: aload         7
     333: invokevirtual #33                 // Method java/lang/StringBuilder.append:(Ljava/lang/String;)Ljava/lang/StringBuilder;
     336: aload_0
     337: invokestatic  #24                 // Method getFamilyString:(Lorg/apache/hadoop/hbase/KeyValue;)Ljava/lang/String;
     340: invokevirtual #33                 // Method java/lang/StringBuilder.append:(Ljava/lang/String;)Ljava/lang/StringBuilder;
     343: bipush        32
     345: iload         9
     347: invokestatic  #44                 // Method org/apache/commons/lang3/StringUtils.repeat:(CI)Ljava/lang/String;
     350: invokevirtual #33                 // Method java/lang/StringBuilder.append:(Ljava/lang/String;)Ljava/lang/StringBuilder;
     353: aload_0
     354: invokestatic  #25                 // Method getQualifierString:(Lorg/apache/hadoop/hbase/KeyValue;)Ljava/lang/String;
     357: invokevirtual #33                 // Method java/lang/StringBuilder.append:(Ljava/lang/String;)Ljava/lang/StringBuilder;
     360: bipush        32
     362: iload         10
     364: invokestatic  #44                 // Method org/apache/commons/lang3/StringUtils.repeat:(CI)Ljava/lang/String;
     367: invokevirtual #33                 // Method java/lang/StringBuilder.append:(Ljava/lang/String;)Ljava/lang/StringBuilder;
     370: aload_0
     371: invokestatic  #45                 // Method getTimestampString:(Lorg/apache/hadoop/hbase/KeyValue;)Ljava/lang/String;
     374: invokevirtual #33                 // Method java/lang/StringBuilder.append:(Ljava/lang/String;)Ljava/lang/StringBuilder;
     377: bipush        32
     379: iload         11
     381: invokestatic  #44                 // Method org/apache/commons/lang3/StringUtils.repeat:(CI)Ljava/lang/String;
     384: invokevirtual #33                 // Method java/lang/StringBuilder.append:(Ljava/lang/String;)Ljava/lang/StringBuilder;
     387: aload_0
     388: invokestatic  #46                 // Method getTypeString:(Lorg/apache/hadoop/hbase/KeyValue;)Ljava/lang/String;
     391: invokevirtual #33                 // Method java/lang/StringBuilder.append:(Ljava/lang/String;)Ljava/lang/StringBuilder;
     394: ldc           #39                 // String
     396: invokevirtual #33                 // Method java/lang/StringBuilder.append:(Ljava/lang/String;)Ljava/lang/StringBuilder;
     399: aload_0
     400: invokestatic  #47                 // Method getValueString:(Lorg/apache/hadoop/hbase/KeyValue;)Ljava/lang/String;
     403: invokevirtual #33                 // Method java/lang/StringBuilder.append:(Ljava/lang/String;)Ljava/lang/StringBuilder;
     406: invokevirtual #35                 // Method java/lang/StringBuilder.toString:()Ljava/lang/String;
     409: areturn

  protected static java.lang.String getRowString(org.apache.hadoop.hbase.KeyValue);
    Code:
       0: aload_0
       1: invokevirtual #48                 // Method org/apache/hadoop/hbase/KeyValue.getRowArray:()[B
       4: aload_0
       5: invokevirtual #49                 // Method org/apache/hadoop/hbase/KeyValue.getRowOffset:()I
       8: aload_0
       9: invokevirtual #43                 // Method org/apache/hadoop/hbase/KeyValue.getRowLength:()S
      12: invokestatic  #50                 // Method org/apache/hadoop/hbase/util/Bytes.toStringBinary:([BII)Ljava/lang/String;
      15: areturn

  protected static java.lang.String getFamilyString(org.apache.hadoop.hbase.KeyValue);
    Code:
       0: aload_0
       1: invokevirtual #51                 // Method org/apache/hadoop/hbase/KeyValue.getFamilyArray:()[B
       4: aload_0
       5: invokevirtual #52                 // Method org/apache/hadoop/hbase/KeyValue.getFamilyOffset:()I
       8: aload_0
       9: invokevirtual #37                 // Method org/apache/hadoop/hbase/KeyValue.getFamilyLength:()B
      12: invokestatic  #50                 // Method org/apache/hadoop/hbase/util/Bytes.toStringBinary:([BII)Ljava/lang/String;
      15: areturn

  protected static java.lang.String getQualifierString(org.apache.hadoop.hbase.KeyValue);
    Code:
       0: aload_0
       1: invokevirtual #53                 // Method org/apache/hadoop/hbase/KeyValue.getQualifierArray:()[B
       4: aload_0
       5: invokevirtual #54                 // Method org/apache/hadoop/hbase/KeyValue.getQualifierOffset:()I
       8: aload_0
       9: invokevirtual #55                 // Method org/apache/hadoop/hbase/KeyValue.getQualifierLength:()I
      12: invokestatic  #50                 // Method org/apache/hadoop/hbase/util/Bytes.toStringBinary:([BII)Ljava/lang/String;
      15: areturn

  protected static java.lang.String getTimestampString(org.apache.hadoop.hbase.KeyValue);
    Code:
       0: new           #29                 // class java/lang/StringBuilder
       3: dup
       4: invokespecial #30                 // Method java/lang/StringBuilder."<init>":()V
       7: aload_0
       8: invokevirtual #26                 // Method org/apache/hadoop/hbase/KeyValue.getTimestamp:()J
      11: invokevirtual #56                 // Method java/lang/StringBuilder.append:(J)Ljava/lang/StringBuilder;
      14: ldc           #36                 // String
      16: invokevirtual #33                 // Method java/lang/StringBuilder.append:(Ljava/lang/String;)Ljava/lang/StringBuilder;
      19: invokevirtual #35                 // Method java/lang/StringBuilder.toString:()Ljava/lang/String;
      22: areturn

  protected static java.lang.String getTypeString(org.apache.hadoop.hbase.KeyValue);
    Code:
       0: aload_0
       1: invokevirtual #57                 // Method org/apache/hadoop/hbase/KeyValue.getTypeByte:()B
       4: invokestatic  #58                 // Method org/apache/hadoop/hbase/KeyValue$Type.codeToType:(B)Lorg/apache/hadoop/hbase/KeyValue$Type;
       7: invokevirtual #59                 // Method org/apache/hadoop/hbase/KeyValue$Type.toString:()Ljava/lang/String;
      10: areturn

  protected static java.lang.String getValueString(org.apache.hadoop.hbase.KeyValue);
    Code:
       0: aload_0
       1: invokevirtual #60                 // Method org/apache/hadoop/hbase/KeyValue.getValueArray:()[B
       4: aload_0
       5: invokevirtual #61                 // Method org/apache/hadoop/hbase/KeyValue.getValueOffset:()I
       8: aload_0
       9: invokevirtual #42                 // Method org/apache/hadoop/hbase/KeyValue.getValueLength:()I
      12: invokestatic  #50                 // Method org/apache/hadoop/hbase/util/Bytes.toStringBinary:([BII)Ljava/lang/String;
      15: areturn
}
