Compiled from "KeyValueUtil.java"
public class org.apache.hadoop.hbase.KeyValueUtil {
  public org.apache.hadoop.hbase.KeyValueUtil();
    Code:
       0: aload_0
       1: invokespecial #1                  // Method java/lang/Object."<init>":()V
       4: return

  public static int length(short, byte, int, int, int, boolean);
    Code:
       0: iload         5
       2: ifeq          16
       5: iload_0
       6: iload_1
       7: iload_2
       8: iload_3
       9: iload         4
      11: invokestatic  #2                  // Method org/apache/hadoop/hbase/KeyValue.getKeyValueDataStructureSize:(IIIII)J
      14: l2i
      15: ireturn
      16: iload_0
      17: iload_1
      18: iload_2
      19: iload_3
      20: invokestatic  #3                  // Method org/apache/hadoop/hbase/KeyValue.getKeyValueDataStructureSize:(IIII)J
      23: l2i
      24: ireturn

  public static int keyLength(org.apache.hadoop.hbase.Cell);
    Code:
       0: aload_0
       1: invokeinterface #4,  1            // InterfaceMethod org/apache/hadoop/hbase/Cell.getRowLength:()S
       6: aload_0
       7: invokeinterface #5,  1            // InterfaceMethod org/apache/hadoop/hbase/Cell.getFamilyLength:()B
      12: aload_0
      13: invokeinterface #6,  1            // InterfaceMethod org/apache/hadoop/hbase/Cell.getQualifierLength:()I
      18: invokestatic  #7                  // Method keyLength:(SBI)I
      21: ireturn

  public static int lengthWithMvccVersion(org.apache.hadoop.hbase.KeyValue, boolean);
    Code:
       0: aload_0
       1: invokevirtual #9                  // Method org/apache/hadoop/hbase/KeyValue.getLength:()I
       4: istore_2
       5: iload_1
       6: ifeq          19
       9: iload_2
      10: aload_0
      11: invokevirtual #10                 // Method org/apache/hadoop/hbase/KeyValue.getSequenceId:()J
      14: invokestatic  #11                 // Method org/apache/hadoop/io/WritableUtils.getVIntSize:(J)I
      17: iadd
      18: istore_2
      19: iload_2
      20: ireturn

  public static int totalLengthWithMvccVersion(java.lang.Iterable<? extends org.apache.hadoop.hbase.KeyValue>, boolean);
    Code:
       0: iconst_0
       1: istore_2
       2: aload_0
       3: invokestatic  #12                 // Method org/apache/hbase/thirdparty/org/apache/commons/collections4/IterableUtils.emptyIfNull:(Ljava/lang/Iterable;)Ljava/lang/Iterable;
       6: invokeinterface #13,  1           // InterfaceMethod java/lang/Iterable.iterator:()Ljava/util/Iterator;
      11: astore_3
      12: aload_3
      13: invokeinterface #14,  1           // InterfaceMethod java/util/Iterator.hasNext:()Z
      18: ifeq          44
      21: aload_3
      22: invokeinterface #15,  1           // InterfaceMethod java/util/Iterator.next:()Ljava/lang/Object;
      27: checkcast     #16                 // class org/apache/hadoop/hbase/KeyValue
      30: astore        4
      32: iload_2
      33: aload         4
      35: iload_1
      36: invokestatic  #17                 // Method lengthWithMvccVersion:(Lorg/apache/hadoop/hbase/KeyValue;Z)I
      39: iadd
      40: istore_2
      41: goto          12
      44: iload_2
      45: ireturn

  public static org.apache.hadoop.hbase.KeyValue copyToNewKeyValue(org.apache.hadoop.hbase.Cell);
    Code:
       0: aload_0
       1: invokestatic  #18                 // Method copyToNewByteArray:(Lorg/apache/hadoop/hbase/Cell;)[B
       4: astore_1
       5: new           #16                 // class org/apache/hadoop/hbase/KeyValue
       8: dup
       9: aload_1
      10: iconst_0
      11: aload_1
      12: arraylength
      13: invokespecial #19                 // Method org/apache/hadoop/hbase/KeyValue."<init>":([BII)V
      16: astore_2
      17: aload_2
      18: aload_0
      19: invokeinterface #20,  1           // InterfaceMethod org/apache/hadoop/hbase/Cell.getSequenceId:()J
      24: invokevirtual #21                 // Method org/apache/hadoop/hbase/KeyValue.setSequenceId:(J)V
      27: aload_2
      28: areturn

  public static java.nio.ByteBuffer copyKeyToNewByteBuffer(org.apache.hadoop.hbase.Cell);
    Code:
       0: aload_0
       1: invokestatic  #22                 // Method keyLength:(Lorg/apache/hadoop/hbase/Cell;)I
       4: newarray       byte
       6: astore_1
       7: aload_0
       8: aload_1
       9: iconst_0
      10: invokestatic  #23                 // Method appendKeyTo:(Lorg/apache/hadoop/hbase/Cell;[BI)I
      13: pop
      14: aload_1
      15: invokestatic  #24                 // Method java/nio/ByteBuffer.wrap:([B)Ljava/nio/ByteBuffer;
      18: astore_2
      19: aload_2
      20: areturn

  public static org.apache.hadoop.hbase.KeyValue toNewKeyCell(org.apache.hadoop.hbase.Cell);
    Code:
       0: aload_0
       1: invokestatic  #22                 // Method keyLength:(Lorg/apache/hadoop/hbase/Cell;)I
       4: newarray       byte
       6: astore_1
       7: aload_0
       8: aload_1
       9: iconst_0
      10: invokestatic  #23                 // Method appendKeyTo:(Lorg/apache/hadoop/hbase/Cell;[BI)I
      13: pop
      14: new           #25                 // class org/apache/hadoop/hbase/KeyValue$KeyOnlyKeyValue
      17: dup
      18: aload_1
      19: iconst_0
      20: aload_1
      21: arraylength
      22: invokespecial #26                 // Method org/apache/hadoop/hbase/KeyValue$KeyOnlyKeyValue."<init>":([BII)V
      25: astore_2
      26: aload_2
      27: aload_0
      28: invokeinterface #20,  1           // InterfaceMethod org/apache/hadoop/hbase/Cell.getSequenceId:()J
      33: invokevirtual #21                 // Method org/apache/hadoop/hbase/KeyValue.setSequenceId:(J)V
      36: aload_2
      37: areturn

  public static byte[] copyToNewByteArray(org.apache.hadoop.hbase.Cell);
    Code:
       0: aload_0
       1: invokeinterface #27,  1           // InterfaceMethod org/apache/hadoop/hbase/Cell.getSerializedSize:()I
       6: istore_1
       7: iload_1
       8: newarray       byte
      10: astore_2
      11: aload_0
      12: aload_2
      13: iconst_0
      14: iconst_1
      15: invokestatic  #28                 // Method appendToByteArray:(Lorg/apache/hadoop/hbase/Cell;[BIZ)I
      18: pop
      19: aload_2
      20: areturn

  public static int appendKeyTo(org.apache.hadoop.hbase.Cell, byte[], int);
    Code:
       0: iload_2
       1: istore_3
       2: aload_1
       3: iload_3
       4: aload_0
       5: invokeinterface #4,  1            // InterfaceMethod org/apache/hadoop/hbase/Cell.getRowLength:()S
      10: invokestatic  #29                 // Method org/apache/hadoop/hbase/util/Bytes.putShort:([BIS)I
      13: istore_3
      14: aload_0
      15: aload_1
      16: iload_3
      17: invokestatic  #30                 // Method org/apache/hadoop/hbase/CellUtil.copyRowTo:(Lorg/apache/hadoop/hbase/Cell;[BI)I
      20: istore_3
      21: aload_1
      22: iload_3
      23: aload_0
      24: invokeinterface #5,  1            // InterfaceMethod org/apache/hadoop/hbase/Cell.getFamilyLength:()B
      29: invokestatic  #31                 // Method org/apache/hadoop/hbase/util/Bytes.putByte:([BIB)I
      32: istore_3
      33: aload_0
      34: aload_1
      35: iload_3
      36: invokestatic  #32                 // Method org/apache/hadoop/hbase/CellUtil.copyFamilyTo:(Lorg/apache/hadoop/hbase/Cell;[BI)I
      39: istore_3
      40: aload_0
      41: aload_1
      42: iload_3
      43: invokestatic  #33                 // Method org/apache/hadoop/hbase/CellUtil.copyQualifierTo:(Lorg/apache/hadoop/hbase/Cell;[BI)I
      46: istore_3
      47: aload_1
      48: iload_3
      49: aload_0
      50: invokeinterface #34,  1           // InterfaceMethod org/apache/hadoop/hbase/Cell.getTimestamp:()J
      55: invokestatic  #35                 // Method org/apache/hadoop/hbase/util/Bytes.putLong:([BIJ)I
      58: istore_3
      59: aload_1
      60: iload_3
      61: aload_0
      62: invokeinterface #36,  1           // InterfaceMethod org/apache/hadoop/hbase/Cell.getTypeByte:()B
      67: invokestatic  #31                 // Method org/apache/hadoop/hbase/util/Bytes.putByte:([BIB)I
      70: istore_3
      71: iload_3
      72: ireturn

  public static int appendToByteArray(org.apache.hadoop.hbase.Cell, byte[], int, boolean);
    Code:
       0: iload_2
       1: istore        4
       3: aload_1
       4: iload         4
       6: aload_0
       7: invokestatic  #22                 // Method keyLength:(Lorg/apache/hadoop/hbase/Cell;)I
      10: invokestatic  #37                 // Method org/apache/hadoop/hbase/util/Bytes.putInt:([BII)I
      13: istore        4
      15: aload_1
      16: iload         4
      18: aload_0
      19: invokeinterface #38,  1           // InterfaceMethod org/apache/hadoop/hbase/Cell.getValueLength:()I
      24: invokestatic  #37                 // Method org/apache/hadoop/hbase/util/Bytes.putInt:([BII)I
      27: istore        4
      29: aload_0
      30: aload_1
      31: iload         4
      33: invokestatic  #23                 // Method appendKeyTo:(Lorg/apache/hadoop/hbase/Cell;[BI)I
      36: istore        4
      38: aload_0
      39: aload_1
      40: iload         4
      42: invokestatic  #39                 // Method org/apache/hadoop/hbase/CellUtil.copyValueTo:(Lorg/apache/hadoop/hbase/Cell;[BI)I
      45: istore        4
      47: iload_3
      48: ifeq          83
      51: aload_0
      52: invokeinterface #40,  1           // InterfaceMethod org/apache/hadoop/hbase/Cell.getTagsLength:()I
      57: ifle          83
      60: aload_1
      61: iload         4
      63: aload_0
      64: invokeinterface #40,  1           // InterfaceMethod org/apache/hadoop/hbase/Cell.getTagsLength:()I
      69: invokestatic  #41                 // Method org/apache/hadoop/hbase/util/Bytes.putAsShort:([BII)I
      72: istore        4
      74: aload_0
      75: aload_1
      76: iload         4
      78: invokestatic  #42                 // Method org/apache/hadoop/hbase/PrivateCellUtil.copyTagsTo:(Lorg/apache/hadoop/hbase/Cell;[BI)I
      81: istore        4
      83: iload         4
      85: ireturn

  public static int appendTo(org.apache.hadoop.hbase.Cell, java.nio.ByteBuffer, int, boolean);
    Code:
       0: aload_1
       1: iload_2
       2: aload_0
       3: invokestatic  #22                 // Method keyLength:(Lorg/apache/hadoop/hbase/Cell;)I
       6: invokestatic  #43                 // Method org/apache/hadoop/hbase/util/ByteBufferUtils.putInt:(Ljava/nio/ByteBuffer;II)I
       9: istore_2
      10: aload_1
      11: iload_2
      12: aload_0
      13: invokeinterface #38,  1           // InterfaceMethod org/apache/hadoop/hbase/Cell.getValueLength:()I
      18: invokestatic  #43                 // Method org/apache/hadoop/hbase/util/ByteBufferUtils.putInt:(Ljava/nio/ByteBuffer;II)I
      21: istore_2
      22: aload_0
      23: aload_1
      24: iload_2
      25: invokestatic  #44                 // Method appendKeyTo:(Lorg/apache/hadoop/hbase/Cell;Ljava/nio/ByteBuffer;I)I
      28: istore_2
      29: aload_0
      30: aload_1
      31: iload_2
      32: invokestatic  #45                 // Method org/apache/hadoop/hbase/CellUtil.copyValueTo:(Lorg/apache/hadoop/hbase/Cell;Ljava/nio/ByteBuffer;I)I
      35: istore_2
      36: aload_0
      37: invokeinterface #40,  1           // InterfaceMethod org/apache/hadoop/hbase/Cell.getTagsLength:()I
      42: istore        4
      44: iload_3
      45: ifeq          68
      48: iload         4
      50: ifle          68
      53: aload_1
      54: iload_2
      55: iload         4
      57: invokestatic  #46                 // Method org/apache/hadoop/hbase/util/ByteBufferUtils.putAsShort:(Ljava/nio/ByteBuffer;II)I
      60: istore_2
      61: aload_0
      62: aload_1
      63: iload_2
      64: invokestatic  #47                 // Method org/apache/hadoop/hbase/PrivateCellUtil.copyTagsTo:(Lorg/apache/hadoop/hbase/Cell;Ljava/nio/ByteBuffer;I)I
      67: istore_2
      68: iload_2
      69: ireturn

  public static int appendKeyTo(org.apache.hadoop.hbase.Cell, java.nio.ByteBuffer, int);
    Code:
       0: aload_1
       1: iload_2
       2: aload_0
       3: invokeinterface #4,  1            // InterfaceMethod org/apache/hadoop/hbase/Cell.getRowLength:()S
       8: invokestatic  #48                 // Method org/apache/hadoop/hbase/util/ByteBufferUtils.putShort:(Ljava/nio/ByteBuffer;IS)I
      11: istore_2
      12: aload_0
      13: aload_1
      14: iload_2
      15: invokestatic  #49                 // Method org/apache/hadoop/hbase/CellUtil.copyRowTo:(Lorg/apache/hadoop/hbase/Cell;Ljava/nio/ByteBuffer;I)I
      18: istore_2
      19: aload_1
      20: iload_2
      21: aload_0
      22: invokeinterface #5,  1            // InterfaceMethod org/apache/hadoop/hbase/Cell.getFamilyLength:()B
      27: invokestatic  #50                 // Method org/apache/hadoop/hbase/util/ByteBufferUtils.putByte:(Ljava/nio/ByteBuffer;IB)I
      30: istore_2
      31: aload_0
      32: aload_1
      33: iload_2
      34: invokestatic  #51                 // Method org/apache/hadoop/hbase/CellUtil.copyFamilyTo:(Lorg/apache/hadoop/hbase/Cell;Ljava/nio/ByteBuffer;I)I
      37: istore_2
      38: aload_0
      39: aload_1
      40: iload_2
      41: invokestatic  #52                 // Method org/apache/hadoop/hbase/CellUtil.copyQualifierTo:(Lorg/apache/hadoop/hbase/Cell;Ljava/nio/ByteBuffer;I)I
      44: istore_2
      45: aload_1
      46: iload_2
      47: aload_0
      48: invokeinterface #34,  1           // InterfaceMethod org/apache/hadoop/hbase/Cell.getTimestamp:()J
      53: invokestatic  #53                 // Method org/apache/hadoop/hbase/util/ByteBufferUtils.putLong:(Ljava/nio/ByteBuffer;IJ)I
      56: istore_2
      57: aload_1
      58: iload_2
      59: aload_0
      60: invokeinterface #36,  1           // InterfaceMethod org/apache/hadoop/hbase/Cell.getTypeByte:()B
      65: invokestatic  #50                 // Method org/apache/hadoop/hbase/util/ByteBufferUtils.putByte:(Ljava/nio/ByteBuffer;IB)I
      68: istore_2
      69: iload_2
      70: ireturn

  public static void appendToByteBuffer(java.nio.ByteBuffer, org.apache.hadoop.hbase.KeyValue, boolean);
    Code:
       0: aload_0
       1: aload_0
       2: invokevirtual #54                 // Method java/nio/ByteBuffer.position:()I
       5: aload_1
       6: invokevirtual #9                  // Method org/apache/hadoop/hbase/KeyValue.getLength:()I
       9: iadd
      10: invokevirtual #55                 // Method java/nio/ByteBuffer.limit:(I)Ljava/nio/Buffer;
      13: pop
      14: aload_0
      15: aload_1
      16: invokevirtual #56                 // Method org/apache/hadoop/hbase/KeyValue.getBuffer:()[B
      19: aload_1
      20: invokevirtual #57                 // Method org/apache/hadoop/hbase/KeyValue.getOffset:()I
      23: aload_1
      24: invokevirtual #9                  // Method org/apache/hadoop/hbase/KeyValue.getLength:()I
      27: invokevirtual #58                 // Method java/nio/ByteBuffer.put:([BII)Ljava/nio/ByteBuffer;
      30: pop
      31: iload_2
      32: ifeq          56
      35: aload_1
      36: invokevirtual #10                 // Method org/apache/hadoop/hbase/KeyValue.getSequenceId:()J
      39: invokestatic  #11                 // Method org/apache/hadoop/io/WritableUtils.getVIntSize:(J)I
      42: istore_3
      43: aload_0
      44: iload_3
      45: invokestatic  #59                 // Method org/apache/hadoop/hbase/util/ByteBufferUtils.extendLimit:(Ljava/nio/ByteBuffer;I)V
      48: aload_0
      49: aload_1
      50: invokevirtual #10                 // Method org/apache/hadoop/hbase/KeyValue.getSequenceId:()J
      53: invokestatic  #60                 // Method org/apache/hadoop/hbase/util/ByteBufferUtils.writeVLong:(Ljava/nio/ByteBuffer;J)V
      56: return

  public static org.apache.hadoop.hbase.KeyValue nextShallowCopy(java.nio.ByteBuffer, boolean, boolean);
    Code:
       0: aload_0
       1: invokevirtual #61                 // Method java/nio/ByteBuffer.isDirect:()Z
       4: ifeq          17
       7: new           #62                 // class java/lang/IllegalArgumentException
      10: dup
      11: ldc           #63                 // String only supports heap buffers
      13: invokespecial #64                 // Method java/lang/IllegalArgumentException."<init>":(Ljava/lang/String;)V
      16: athrow
      17: aload_0
      18: invokevirtual #65                 // Method java/nio/ByteBuffer.remaining:()I
      21: iconst_1
      22: if_icmpge     27
      25: aconst_null
      26: areturn
      27: aconst_null
      28: astore_3
      29: aload_0
      30: invokevirtual #66                 // Method java/nio/ByteBuffer.arrayOffset:()I
      33: aload_0
      34: invokevirtual #54                 // Method java/nio/ByteBuffer.position:()I
      37: iadd
      38: istore        4
      40: aload_0
      41: invokevirtual #67                 // Method java/nio/ByteBuffer.getInt:()I
      44: istore        5
      46: aload_0
      47: invokevirtual #67                 // Method java/nio/ByteBuffer.getInt:()I
      50: istore        6
      52: aload_0
      53: iload         5
      55: iload         6
      57: iadd
      58: invokestatic  #68                 // Method org/apache/hadoop/hbase/util/ByteBufferUtils.skip:(Ljava/nio/ByteBuffer;I)V
      61: iconst_0
      62: istore        7
      64: iload_2
      65: ifeq          96
      68: aload_0
      69: invokevirtual #69                 // Method java/nio/ByteBuffer.get:()B
      72: sipush        255
      75: iand
      76: bipush        8
      78: ishl
      79: aload_0
      80: invokevirtual #69                 // Method java/nio/ByteBuffer.get:()B
      83: sipush        255
      86: iand
      87: ixor
      88: istore        7
      90: aload_0
      91: iload         7
      93: invokestatic  #68                 // Method org/apache/hadoop/hbase/util/ByteBufferUtils.skip:(Ljava/nio/ByteBuffer;I)V
      96: iload         5
      98: iload         6
     100: iload         7
     102: invokestatic  #70                 // Method org/apache/hadoop/hbase/KeyValue.getKeyValueDataStructureSize:(III)J
     105: l2i
     106: istore        8
     108: new           #16                 // class org/apache/hadoop/hbase/KeyValue
     111: dup
     112: aload_0
     113: invokevirtual #71                 // Method java/nio/ByteBuffer.array:()[B
     116: iload         4
     118: iload         8
     120: invokespecial #19                 // Method org/apache/hadoop/hbase/KeyValue."<init>":([BII)V
     123: astore_3
     124: iload_1
     125: ifeq          140
     128: aload_0
     129: invokestatic  #72                 // Method org/apache/hadoop/hbase/util/ByteBufferUtils.readVLong:(Ljava/nio/ByteBuffer;)J
     132: lstore        9
     134: aload_3
     135: lload         9
     137: invokevirtual #21                 // Method org/apache/hadoop/hbase/KeyValue.setSequenceId:(J)V
     140: aload_3
     141: areturn

  public static org.apache.hadoop.hbase.KeyValue previousKey(org.apache.hadoop.hbase.KeyValue);
    Code:
       0: aload_0
       1: invokestatic  #73                 // Method org/apache/hadoop/hbase/CellUtil.cloneRow:(Lorg/apache/hadoop/hbase/Cell;)[B
       4: aload_0
       5: invokestatic  #74                 // Method org/apache/hadoop/hbase/CellUtil.cloneFamily:(Lorg/apache/hadoop/hbase/Cell;)[B
       8: aload_0
       9: invokestatic  #75                 // Method org/apache/hadoop/hbase/CellUtil.cloneQualifier:(Lorg/apache/hadoop/hbase/Cell;)[B
      12: aload_0
      13: invokevirtual #76                 // Method org/apache/hadoop/hbase/KeyValue.getTimestamp:()J
      16: lconst_1
      17: lsub
      18: invokestatic  #77                 // Method createFirstOnRow:([B[B[BJ)Lorg/apache/hadoop/hbase/KeyValue;
      21: areturn

  public static org.apache.hadoop.hbase.KeyValue createLastOnRow(byte[], int, int, byte[], int, int, byte[], int, int);
    Code:
       0: new           #16                 // class org/apache/hadoop/hbase/KeyValue
       3: dup
       4: aload_0
       5: iload_1
       6: iload_2
       7: aload_3
       8: iload         4
      10: iload         5
      12: aload         6
      14: iload         7
      16: iload         8
      18: ldc2_w        #79                 // long -9223372036854775808l
      21: getstatic     #81                 // Field org/apache/hadoop/hbase/KeyValue$Type.Minimum:Lorg/apache/hadoop/hbase/KeyValue$Type;
      24: aconst_null
      25: iconst_0
      26: iconst_0
      27: invokespecial #82                 // Method org/apache/hadoop/hbase/KeyValue."<init>":([BII[BII[BIIJLorg/apache/hadoop/hbase/KeyValue$Type;[BII)V
      30: areturn

  public static org.apache.hadoop.hbase.KeyValue createFirstOnRow(byte[], int, short);
    Code:
       0: new           #16                 // class org/apache/hadoop/hbase/KeyValue
       3: dup
       4: aload_0
       5: iload_1
       6: iload_2
       7: aconst_null
       8: iconst_0
       9: iconst_0
      10: aconst_null
      11: iconst_0
      12: iconst_0
      13: ldc2_w        #83                 // long 9223372036854775807l
      16: getstatic     #85                 // Field org/apache/hadoop/hbase/KeyValue$Type.Maximum:Lorg/apache/hadoop/hbase/KeyValue$Type;
      19: aconst_null
      20: iconst_0
      21: iconst_0
      22: invokespecial #82                 // Method org/apache/hadoop/hbase/KeyValue."<init>":([BII[BII[BIIJLorg/apache/hadoop/hbase/KeyValue$Type;[BII)V
      25: areturn

  public static org.apache.hadoop.hbase.KeyValue createLastOnRow(byte[]);
    Code:
       0: new           #16                 // class org/apache/hadoop/hbase/KeyValue
       3: dup
       4: aload_0
       5: aconst_null
       6: aconst_null
       7: ldc2_w        #83                 // long 9223372036854775807l
      10: getstatic     #81                 // Field org/apache/hadoop/hbase/KeyValue$Type.Minimum:Lorg/apache/hadoop/hbase/KeyValue$Type;
      13: invokespecial #86                 // Method org/apache/hadoop/hbase/KeyValue."<init>":([B[B[BJLorg/apache/hadoop/hbase/KeyValue$Type;)V
      16: areturn

  public static org.apache.hadoop.hbase.KeyValue createFirstOnRow(byte[]);
    Code:
       0: aload_0
       1: ldc2_w        #83                 // long 9223372036854775807l
       4: invokestatic  #87                 // Method createFirstOnRow:([BJ)Lorg/apache/hadoop/hbase/KeyValue;
       7: areturn

  public static org.apache.hadoop.hbase.KeyValue createFirstOnRow(byte[], long);
    Code:
       0: new           #16                 // class org/apache/hadoop/hbase/KeyValue
       3: dup
       4: aload_0
       5: aconst_null
       6: aconst_null
       7: lload_1
       8: getstatic     #85                 // Field org/apache/hadoop/hbase/KeyValue$Type.Maximum:Lorg/apache/hadoop/hbase/KeyValue$Type;
      11: invokespecial #86                 // Method org/apache/hadoop/hbase/KeyValue."<init>":([B[B[BJLorg/apache/hadoop/hbase/KeyValue$Type;)V
      14: areturn

  public static org.apache.hadoop.hbase.KeyValue createFirstOnRow(byte[], byte[], byte[]);
    Code:
       0: new           #16                 // class org/apache/hadoop/hbase/KeyValue
       3: dup
       4: aload_0
       5: aload_1
       6: aload_2
       7: ldc2_w        #83                 // long 9223372036854775807l
      10: getstatic     #85                 // Field org/apache/hadoop/hbase/KeyValue$Type.Maximum:Lorg/apache/hadoop/hbase/KeyValue$Type;
      13: invokespecial #86                 // Method org/apache/hadoop/hbase/KeyValue."<init>":([B[B[BJLorg/apache/hadoop/hbase/KeyValue$Type;)V
      16: areturn

  public static org.apache.hadoop.hbase.KeyValue createFirstOnRow(byte[], byte[], byte[], long);
    Code:
       0: new           #16                 // class org/apache/hadoop/hbase/KeyValue
       3: dup
       4: aload_0
       5: aload_1
       6: aload_2
       7: lload_3
       8: getstatic     #85                 // Field org/apache/hadoop/hbase/KeyValue$Type.Maximum:Lorg/apache/hadoop/hbase/KeyValue$Type;
      11: invokespecial #86                 // Method org/apache/hadoop/hbase/KeyValue."<init>":([B[B[BJLorg/apache/hadoop/hbase/KeyValue$Type;)V
      14: areturn

  public static org.apache.hadoop.hbase.KeyValue createFirstOnRow(byte[], int, int, byte[], int, int, byte[], int, int);
    Code:
       0: new           #16                 // class org/apache/hadoop/hbase/KeyValue
       3: dup
       4: aload_0
       5: iload_1
       6: iload_2
       7: aload_3
       8: iload         4
      10: iload         5
      12: aload         6
      14: iload         7
      16: iload         8
      18: ldc2_w        #83                 // long 9223372036854775807l
      21: getstatic     #85                 // Field org/apache/hadoop/hbase/KeyValue$Type.Maximum:Lorg/apache/hadoop/hbase/KeyValue$Type;
      24: aconst_null
      25: iconst_0
      26: iconst_0
      27: invokespecial #82                 // Method org/apache/hadoop/hbase/KeyValue."<init>":([BII[BII[BIIJLorg/apache/hadoop/hbase/KeyValue$Type;[BII)V
      30: areturn

  public static org.apache.hadoop.hbase.KeyValue createFirstOnRow(byte[], byte[], byte[], byte[]) throws java.lang.IllegalArgumentException;
    Code:
       0: aload_0
       1: iconst_0
       2: aload_1
       3: iconst_0
       4: aload_1
       5: arraylength
       6: aload_2
       7: iconst_0
       8: aload_2
       9: arraylength
      10: aload_3
      11: iconst_0
      12: aload_3
      13: arraylength
      14: invokestatic  #88                 // Method createFirstOnRow:([BI[BII[BII[BII)Lorg/apache/hadoop/hbase/KeyValue;
      17: areturn

  public static org.apache.hadoop.hbase.KeyValue createFirstOnRow(byte[], int, byte[], int, int, byte[], int, int, byte[], int, int) throws java.lang.IllegalArgumentException;
    Code:
       0: iload         4
       2: iload         7
       4: iload         10
       6: iconst_0
       7: invokestatic  #3                  // Method org/apache/hadoop/hbase/KeyValue.getKeyValueDataStructureSize:(IIII)J
      10: lstore        11
      12: lload         11
      14: ldc2_w        #90                 // long 2147483647l
      17: lcmp
      18: ifle          59
      21: new           #62                 // class java/lang/IllegalArgumentException
      24: dup
      25: new           #92                 // class java/lang/StringBuilder
      28: dup
      29: invokespecial #93                 // Method java/lang/StringBuilder."<init>":()V
      32: ldc           #94                 // String KeyValue length
      34: invokevirtual #95                 // Method java/lang/StringBuilder.append:(Ljava/lang/String;)Ljava/lang/StringBuilder;
      37: lload         11
      39: invokevirtual #96                 // Method java/lang/StringBuilder.append:(J)Ljava/lang/StringBuilder;
      42: ldc           #97                 // String  >
      44: invokevirtual #95                 // Method java/lang/StringBuilder.append:(Ljava/lang/String;)Ljava/lang/StringBuilder;
      47: ldc           #98                 // int 2147483647
      49: invokevirtual #99                 // Method java/lang/StringBuilder.append:(I)Ljava/lang/StringBuilder;
      52: invokevirtual #100                // Method java/lang/StringBuilder.toString:()Ljava/lang/String;
      55: invokespecial #64                 // Method java/lang/IllegalArgumentException."<init>":(Ljava/lang/String;)V
      58: athrow
      59: lload         11
      61: l2i
      62: istore        13
      64: aload_0
      65: arraylength
      66: iload_1
      67: isub
      68: iload         13
      70: if_icmpge     113
      73: new           #62                 // class java/lang/IllegalArgumentException
      76: dup
      77: new           #92                 // class java/lang/StringBuilder
      80: dup
      81: invokespecial #93                 // Method java/lang/StringBuilder."<init>":()V
      84: ldc           #101                // String Buffer size
      86: invokevirtual #95                 // Method java/lang/StringBuilder.append:(Ljava/lang/String;)Ljava/lang/StringBuilder;
      89: aload_0
      90: arraylength
      91: iload_1
      92: isub
      93: invokevirtual #99                 // Method java/lang/StringBuilder.append:(I)Ljava/lang/StringBuilder;
      96: ldc           #102                // String  <
      98: invokevirtual #95                 // Method java/lang/StringBuilder.append:(Ljava/lang/String;)Ljava/lang/StringBuilder;
     101: iload         13
     103: invokevirtual #99                 // Method java/lang/StringBuilder.append:(I)Ljava/lang/StringBuilder;
     106: invokevirtual #100                // Method java/lang/StringBuilder.toString:()Ljava/lang/String;
     109: invokespecial #64                 // Method java/lang/IllegalArgumentException."<init>":(Ljava/lang/String;)V
     112: athrow
     113: aload_0
     114: iload_1
     115: aload_2
     116: iload_3
     117: iload         4
     119: aload         5
     121: iload         6
     123: iload         7
     125: aload         8
     127: iload         9
     129: iload         10
     131: ldc2_w        #83                 // long 9223372036854775807l
     134: getstatic     #85                 // Field org/apache/hadoop/hbase/KeyValue$Type.Maximum:Lorg/apache/hadoop/hbase/KeyValue$Type;
     137: aconst_null
     138: iconst_0
     139: iconst_0
     140: aconst_null
     141: invokestatic  #103                // Method org/apache/hadoop/hbase/KeyValue.writeByteArray:([BI[BII[BII[BIIJLorg/apache/hadoop/hbase/KeyValue$Type;[BII[Lorg/apache/hadoop/hbase/Tag;)I
     144: istore        14
     146: new           #16                 // class org/apache/hadoop/hbase/KeyValue
     149: dup
     150: aload_0
     151: iload_1
     152: iload         14
     154: invokespecial #19                 // Method org/apache/hadoop/hbase/KeyValue."<init>":([BII)V
     157: areturn

  public static org.apache.hadoop.hbase.KeyValue ensureKeyValue(org.apache.hadoop.hbase.Cell);
    Code:
       0: aload_0
       1: ifnonnull     6
       4: aconst_null
       5: areturn
       6: aload_0
       7: instanceof    #16                 // class org/apache/hadoop/hbase/KeyValue
      10: ifeq          71
      13: aload_0
      14: invokevirtual #104                // Method java/lang/Object.getClass:()Ljava/lang/Class;
      17: invokevirtual #105                // Method java/lang/Class.getName:()Ljava/lang/String;
      20: ldc           #16                 // class org/apache/hadoop/hbase/KeyValue
      22: invokevirtual #105                // Method java/lang/Class.getName:()Ljava/lang/String;
      25: invokevirtual #106                // Method java/lang/String.equals:(Ljava/lang/Object;)Z
      28: ifeq          36
      31: aload_0
      32: checkcast     #16                 // class org/apache/hadoop/hbase/KeyValue
      35: areturn
      36: aload_0
      37: checkcast     #16                 // class org/apache/hadoop/hbase/KeyValue
      40: astore_1
      41: new           #16                 // class org/apache/hadoop/hbase/KeyValue
      44: dup
      45: aload_1
      46: getfield      #107                // Field org/apache/hadoop/hbase/KeyValue.bytes:[B
      49: aload_1
      50: getfield      #108                // Field org/apache/hadoop/hbase/KeyValue.offset:I
      53: aload_1
      54: getfield      #109                // Field org/apache/hadoop/hbase/KeyValue.length:I
      57: invokespecial #19                 // Method org/apache/hadoop/hbase/KeyValue."<init>":([BII)V
      60: astore_2
      61: aload_2
      62: aload_1
      63: invokevirtual #10                 // Method org/apache/hadoop/hbase/KeyValue.getSequenceId:()J
      66: invokevirtual #21                 // Method org/apache/hadoop/hbase/KeyValue.setSequenceId:(J)V
      69: aload_2
      70: areturn
      71: aload_0
      72: invokestatic  #110                // Method copyToNewKeyValue:(Lorg/apache/hadoop/hbase/Cell;)Lorg/apache/hadoop/hbase/KeyValue;
      75: areturn

  public static java.util.List<org.apache.hadoop.hbase.KeyValue> ensureKeyValues(java.util.List<org.apache.hadoop.hbase.Cell>);
    Code:
       0: aload_0
       1: new           #111                // class org/apache/hadoop/hbase/KeyValueUtil$1
       4: dup
       5: invokespecial #112                // Method org/apache/hadoop/hbase/KeyValueUtil$1."<init>":()V
       8: invokestatic  #113                // Method org/apache/hbase/thirdparty/com/google/common/collect/Lists.transform:(Ljava/util/List;Lorg/apache/hbase/thirdparty/com/google/common/base/Function;)Ljava/util/List;
      11: astore_1
      12: new           #114                // class java/util/ArrayList
      15: dup
      16: aload_1
      17: invokespecial #115                // Method java/util/ArrayList."<init>":(Ljava/util/Collection;)V
      20: areturn

  public static long write(org.apache.hadoop.hbase.KeyValue, java.io.DataOutput) throws java.io.IOException;
    Code:
       0: aload_0
       1: invokevirtual #9                  // Method org/apache/hadoop/hbase/KeyValue.getLength:()I
       4: istore_2
       5: aload_1
       6: iload_2
       7: invokeinterface #116,  2          // InterfaceMethod java/io/DataOutput.writeInt:(I)V
      12: aload_1
      13: aload_0
      14: invokevirtual #56                 // Method org/apache/hadoop/hbase/KeyValue.getBuffer:()[B
      17: aload_0
      18: invokevirtual #57                 // Method org/apache/hadoop/hbase/KeyValue.getOffset:()I
      21: iload_2
      22: invokeinterface #117,  4          // InterfaceMethod java/io/DataOutput.write:([BII)V
      27: iload_2
      28: i2l
      29: ldc2_w        #119                // long 4l
      32: ladd
      33: lreturn

  static java.lang.String bytesToHex(byte[], int, int);
    Code:
       0: aload_0
       1: ifnull        13
       4: aload_0
       5: iload_1
       6: iload_2
       7: invokestatic  #121                // Method org/apache/hadoop/hbase/util/Bytes.toStringBinary:([BII)Ljava/lang/String;
      10: goto          15
      13: ldc           #122                // String <null>
      15: astore_3
      16: new           #92                 // class java/lang/StringBuilder
      19: dup
      20: invokespecial #93                 // Method java/lang/StringBuilder."<init>":()V
      23: ldc           #123                // String , KeyValueBytesHex=
      25: invokevirtual #95                 // Method java/lang/StringBuilder.append:(Ljava/lang/String;)Ljava/lang/StringBuilder;
      28: aload_3
      29: invokevirtual #95                 // Method java/lang/StringBuilder.append:(Ljava/lang/String;)Ljava/lang/StringBuilder;
      32: ldc           #124                // String , offset=
      34: invokevirtual #95                 // Method java/lang/StringBuilder.append:(Ljava/lang/String;)Ljava/lang/StringBuilder;
      37: iload_1
      38: invokevirtual #99                 // Method java/lang/StringBuilder.append:(I)Ljava/lang/StringBuilder;
      41: ldc           #125                // String , length=
      43: invokevirtual #95                 // Method java/lang/StringBuilder.append:(Ljava/lang/String;)Ljava/lang/StringBuilder;
      46: iload_2
      47: invokevirtual #99                 // Method java/lang/StringBuilder.append:(I)Ljava/lang/StringBuilder;
      50: invokevirtual #100                // Method java/lang/StringBuilder.toString:()Ljava/lang/String;
      53: areturn

  static void checkKeyValueBytes(byte[], int, int, boolean);
    Code:
       0: aload_0
       1: ifnonnull     28
       4: ldc           #126                // String Invalid to have null byte array in KeyValue.
       6: astore        4
       8: getstatic     #127                // Field LOG:Lorg/slf4j/Logger;
      11: aload         4
      13: invokeinterface #128,  2          // InterfaceMethod org/slf4j/Logger.warn:(Ljava/lang/String;)V
      18: new           #62                 // class java/lang/IllegalArgumentException
      21: dup
      22: aload         4
      24: invokespecial #64                 // Method java/lang/IllegalArgumentException."<init>":(Ljava/lang/String;)V
      27: athrow
      28: iload_1
      29: istore        4
      31: iload_1
      32: iload_2
      33: iadd
      34: istore        5
      36: iload         4
      38: iconst_4
      39: iadd
      40: iload         5
      42: if_icmple     96
      45: new           #92                 // class java/lang/StringBuilder
      48: dup
      49: invokespecial #93                 // Method java/lang/StringBuilder."<init>":()V
      52: ldc           #129                // String Overflow when reading key length at position=
      54: invokevirtual #95                 // Method java/lang/StringBuilder.append:(Ljava/lang/String;)Ljava/lang/StringBuilder;
      57: iload         4
      59: invokevirtual #99                 // Method java/lang/StringBuilder.append:(I)Ljava/lang/StringBuilder;
      62: aload_0
      63: iload_1
      64: iload_2
      65: invokestatic  #130                // Method bytesToHex:([BII)Ljava/lang/String;
      68: invokevirtual #95                 // Method java/lang/StringBuilder.append:(Ljava/lang/String;)Ljava/lang/StringBuilder;
      71: invokevirtual #100                // Method java/lang/StringBuilder.toString:()Ljava/lang/String;
      74: astore        6
      76: getstatic     #127                // Field LOG:Lorg/slf4j/Logger;
      79: aload         6
      81: invokeinterface #128,  2          // InterfaceMethod org/slf4j/Logger.warn:(Ljava/lang/String;)V
      86: new           #62                 // class java/lang/IllegalArgumentException
      89: dup
      90: aload         6
      92: invokespecial #64                 // Method java/lang/IllegalArgumentException."<init>":(Ljava/lang/String;)V
      95: athrow
      96: aload_0
      97: iload         4
      99: iconst_4
     100: invokestatic  #131                // Method org/apache/hadoop/hbase/util/Bytes.toInt:([BII)I
     103: istore        6
     105: iinc          4, 4
     108: iload         6
     110: ifle          123
     113: iload         4
     115: iload         6
     117: iadd
     118: iload         5
     120: if_icmple     174
     123: new           #92                 // class java/lang/StringBuilder
     126: dup
     127: invokespecial #93                 // Method java/lang/StringBuilder."<init>":()V
     130: ldc           #132                // String Invalid key length in KeyValue. keyLength=
     132: invokevirtual #95                 // Method java/lang/StringBuilder.append:(Ljava/lang/String;)Ljava/lang/StringBuilder;
     135: iload         6
     137: invokevirtual #99                 // Method java/lang/StringBuilder.append:(I)Ljava/lang/StringBuilder;
     140: aload_0
     141: iload_1
     142: iload_2
     143: invokestatic  #130                // Method bytesToHex:([BII)Ljava/lang/String;
     146: invokevirtual #95                 // Method java/lang/StringBuilder.append:(Ljava/lang/String;)Ljava/lang/StringBuilder;
     149: invokevirtual #100                // Method java/lang/StringBuilder.toString:()Ljava/lang/String;
     152: astore        7
     154: getstatic     #127                // Field LOG:Lorg/slf4j/Logger;
     157: aload         7
     159: invokeinterface #128,  2          // InterfaceMethod org/slf4j/Logger.warn:(Ljava/lang/String;)V
     164: new           #62                 // class java/lang/IllegalArgumentException
     167: dup
     168: aload         7
     170: invokespecial #64                 // Method java/lang/IllegalArgumentException."<init>":(Ljava/lang/String;)V
     173: athrow
     174: iload         4
     176: iconst_4
     177: iadd
     178: iload         5
     180: if_icmple     234
     183: new           #92                 // class java/lang/StringBuilder
     186: dup
     187: invokespecial #93                 // Method java/lang/StringBuilder."<init>":()V
     190: ldc           #133                // String Overflow when reading value length at position=
     192: invokevirtual #95                 // Method java/lang/StringBuilder.append:(Ljava/lang/String;)Ljava/lang/StringBuilder;
     195: iload         4
     197: invokevirtual #99                 // Method java/lang/StringBuilder.append:(I)Ljava/lang/StringBuilder;
     200: aload_0
     201: iload_1
     202: iload_2
     203: invokestatic  #130                // Method bytesToHex:([BII)Ljava/lang/String;
     206: invokevirtual #95                 // Method java/lang/StringBuilder.append:(Ljava/lang/String;)Ljava/lang/StringBuilder;
     209: invokevirtual #100                // Method java/lang/StringBuilder.toString:()Ljava/lang/String;
     212: astore        7
     214: getstatic     #127                // Field LOG:Lorg/slf4j/Logger;
     217: aload         7
     219: invokeinterface #128,  2          // InterfaceMethod org/slf4j/Logger.warn:(Ljava/lang/String;)V
     224: new           #62                 // class java/lang/IllegalArgumentException
     227: dup
     228: aload         7
     230: invokespecial #64                 // Method java/lang/IllegalArgumentException."<init>":(Ljava/lang/String;)V
     233: athrow
     234: aload_0
     235: iload         4
     237: iconst_4
     238: invokestatic  #131                // Method org/apache/hadoop/hbase/util/Bytes.toInt:([BII)I
     241: istore        7
     243: iinc          4, 4
     246: iload         7
     248: iflt          261
     251: iload         4
     253: iload         7
     255: iadd
     256: iload         5
     258: if_icmple     312
     261: new           #92                 // class java/lang/StringBuilder
     264: dup
     265: invokespecial #93                 // Method java/lang/StringBuilder."<init>":()V
     268: ldc           #134                // String Invalid value length in KeyValue, valueLength=
     270: invokevirtual #95                 // Method java/lang/StringBuilder.append:(Ljava/lang/String;)Ljava/lang/StringBuilder;
     273: iload         7
     275: invokevirtual #99                 // Method java/lang/StringBuilder.append:(I)Ljava/lang/StringBuilder;
     278: aload_0
     279: iload_1
     280: iload_2
     281: invokestatic  #130                // Method bytesToHex:([BII)Ljava/lang/String;
     284: invokevirtual #95                 // Method java/lang/StringBuilder.append:(Ljava/lang/String;)Ljava/lang/StringBuilder;
     287: invokevirtual #100                // Method java/lang/StringBuilder.toString:()Ljava/lang/String;
     290: astore        8
     292: getstatic     #127                // Field LOG:Lorg/slf4j/Logger;
     295: aload         8
     297: invokeinterface #128,  2          // InterfaceMethod org/slf4j/Logger.warn:(Ljava/lang/String;)V
     302: new           #62                 // class java/lang/IllegalArgumentException
     305: dup
     306: aload         8
     308: invokespecial #64                 // Method java/lang/IllegalArgumentException."<init>":(Ljava/lang/String;)V
     311: athrow
     312: iload         4
     314: iconst_2
     315: iadd
     316: iload         5
     318: if_icmple     372
     321: new           #92                 // class java/lang/StringBuilder
     324: dup
     325: invokespecial #93                 // Method java/lang/StringBuilder."<init>":()V
     328: ldc           #135                // String Overflow when reading row length at position=
     330: invokevirtual #95                 // Method java/lang/StringBuilder.append:(Ljava/lang/String;)Ljava/lang/StringBuilder;
     333: iload         4
     335: invokevirtual #99                 // Method java/lang/StringBuilder.append:(I)Ljava/lang/StringBuilder;
     338: aload_0
     339: iload_1
     340: iload_2
     341: invokestatic  #130                // Method bytesToHex:([BII)Ljava/lang/String;
     344: invokevirtual #95                 // Method java/lang/StringBuilder.append:(Ljava/lang/String;)Ljava/lang/StringBuilder;
     347: invokevirtual #100                // Method java/lang/StringBuilder.toString:()Ljava/lang/String;
     350: astore        8
     352: getstatic     #127                // Field LOG:Lorg/slf4j/Logger;
     355: aload         8
     357: invokeinterface #128,  2          // InterfaceMethod org/slf4j/Logger.warn:(Ljava/lang/String;)V
     362: new           #62                 // class java/lang/IllegalArgumentException
     365: dup
     366: aload         8
     368: invokespecial #64                 // Method java/lang/IllegalArgumentException."<init>":(Ljava/lang/String;)V
     371: athrow
     372: aload_0
     373: iload         4
     375: iconst_2
     376: invokestatic  #136                // Method org/apache/hadoop/hbase/util/Bytes.toShort:([BII)S
     379: istore        8
     381: iinc          4, 2
     384: iload         8
     386: iflt          399
     389: iload         4
     391: iload         8
     393: iadd
     394: iload         5
     396: if_icmple     450
     399: new           #92                 // class java/lang/StringBuilder
     402: dup
     403: invokespecial #93                 // Method java/lang/StringBuilder."<init>":()V
     406: ldc           #137                // String Invalid row length in KeyValue, rowLength=
     408: invokevirtual #95                 // Method java/lang/StringBuilder.append:(Ljava/lang/String;)Ljava/lang/StringBuilder;
     411: iload         8
     413: invokevirtual #99                 // Method java/lang/StringBuilder.append:(I)Ljava/lang/StringBuilder;
     416: aload_0
     417: iload_1
     418: iload_2
     419: invokestatic  #130                // Method bytesToHex:([BII)Ljava/lang/String;
     422: invokevirtual #95                 // Method java/lang/StringBuilder.append:(Ljava/lang/String;)Ljava/lang/StringBuilder;
     425: invokevirtual #100                // Method java/lang/StringBuilder.toString:()Ljava/lang/String;
     428: astore        9
     430: getstatic     #127                // Field LOG:Lorg/slf4j/Logger;
     433: aload         9
     435: invokeinterface #128,  2          // InterfaceMethod org/slf4j/Logger.warn:(Ljava/lang/String;)V
     440: new           #62                 // class java/lang/IllegalArgumentException
     443: dup
     444: aload         9
     446: invokespecial #64                 // Method java/lang/IllegalArgumentException."<init>":(Ljava/lang/String;)V
     449: athrow
     450: iload         4
     452: iload         8
     454: iadd
     455: istore        4
     457: iload         4
     459: iconst_1
     460: iadd
     461: iload         5
     463: if_icmple     517
     466: new           #92                 // class java/lang/StringBuilder
     469: dup
     470: invokespecial #93                 // Method java/lang/StringBuilder."<init>":()V
     473: ldc           #138                // String Overflow when reading family length at position=
     475: invokevirtual #95                 // Method java/lang/StringBuilder.append:(Ljava/lang/String;)Ljava/lang/StringBuilder;
     478: iload         4
     480: invokevirtual #99                 // Method java/lang/StringBuilder.append:(I)Ljava/lang/StringBuilder;
     483: aload_0
     484: iload_1
     485: iload_2
     486: invokestatic  #130                // Method bytesToHex:([BII)Ljava/lang/String;
     489: invokevirtual #95                 // Method java/lang/StringBuilder.append:(Ljava/lang/String;)Ljava/lang/StringBuilder;
     492: invokevirtual #100                // Method java/lang/StringBuilder.toString:()Ljava/lang/String;
     495: astore        9
     497: getstatic     #127                // Field LOG:Lorg/slf4j/Logger;
     500: aload         9
     502: invokeinterface #128,  2          // InterfaceMethod org/slf4j/Logger.warn:(Ljava/lang/String;)V
     507: new           #62                 // class java/lang/IllegalArgumentException
     510: dup
     511: aload         9
     513: invokespecial #64                 // Method java/lang/IllegalArgumentException."<init>":(Ljava/lang/String;)V
     516: athrow
     517: aload_0
     518: iload         4
     520: baload
     521: istore        9
     523: iinc          4, 1
     526: iload         9
     528: iflt          541
     531: iload         4
     533: iload         9
     535: iadd
     536: iload         5
     538: if_icmple     592
     541: new           #92                 // class java/lang/StringBuilder
     544: dup
     545: invokespecial #93                 // Method java/lang/StringBuilder."<init>":()V
     548: ldc           #139                // String Invalid family length in KeyValue, familyLength=
     550: invokevirtual #95                 // Method java/lang/StringBuilder.append:(Ljava/lang/String;)Ljava/lang/StringBuilder;
     553: iload         9
     555: invokevirtual #99                 // Method java/lang/StringBuilder.append:(I)Ljava/lang/StringBuilder;
     558: aload_0
     559: iload_1
     560: iload_2
     561: invokestatic  #130                // Method bytesToHex:([BII)Ljava/lang/String;
     564: invokevirtual #95                 // Method java/lang/StringBuilder.append:(Ljava/lang/String;)Ljava/lang/StringBuilder;
     567: invokevirtual #100                // Method java/lang/StringBuilder.toString:()Ljava/lang/String;
     570: astore        10
     572: getstatic     #127                // Field LOG:Lorg/slf4j/Logger;
     575: aload         10
     577: invokeinterface #128,  2          // InterfaceMethod org/slf4j/Logger.warn:(Ljava/lang/String;)V
     582: new           #62                 // class java/lang/IllegalArgumentException
     585: dup
     586: aload         10
     588: invokespecial #64                 // Method java/lang/IllegalArgumentException."<init>":(Ljava/lang/String;)V
     591: athrow
     592: iload         4
     594: iload         9
     596: iadd
     597: istore        4
     599: iload         6
     601: iconst_2
     602: isub
     603: iload         8
     605: isub
     606: iconst_1
     607: isub
     608: iload         9
     610: isub
     611: bipush        8
     613: isub
     614: iconst_1
     615: isub
     616: istore        10
     618: iload         10
     620: iflt          633
     623: iload         4
     625: iload         10
     627: iadd
     628: iload         5
     630: if_icmple     684
     633: new           #92                 // class java/lang/StringBuilder
     636: dup
     637: invokespecial #93                 // Method java/lang/StringBuilder."<init>":()V
     640: ldc           #140                // String Invalid qualifier length in KeyValue, qualifierLen=
     642: invokevirtual #95                 // Method java/lang/StringBuilder.append:(Ljava/lang/String;)Ljava/lang/StringBuilder;
     645: iload         10
     647: invokevirtual #99                 // Method java/lang/StringBuilder.append:(I)Ljava/lang/StringBuilder;
     650: aload_0
     651: iload_1
     652: iload_2
     653: invokestatic  #130                // Method bytesToHex:([BII)Ljava/lang/String;
     656: invokevirtual #95                 // Method java/lang/StringBuilder.append:(Ljava/lang/String;)Ljava/lang/StringBuilder;
     659: invokevirtual #100                // Method java/lang/StringBuilder.toString:()Ljava/lang/String;
     662: astore        11
     664: getstatic     #127                // Field LOG:Lorg/slf4j/Logger;
     667: aload         11
     669: invokeinterface #128,  2          // InterfaceMethod org/slf4j/Logger.warn:(Ljava/lang/String;)V
     674: new           #62                 // class java/lang/IllegalArgumentException
     677: dup
     678: aload         11
     680: invokespecial #64                 // Method java/lang/IllegalArgumentException."<init>":(Ljava/lang/String;)V
     683: athrow
     684: iload         4
     686: iload         10
     688: iadd
     689: istore        4
     691: iload         4
     693: bipush        8
     695: iadd
     696: iload         5
     698: if_icmple     752
     701: new           #92                 // class java/lang/StringBuilder
     704: dup
     705: invokespecial #93                 // Method java/lang/StringBuilder."<init>":()V
     708: ldc           #141                // String Overflow when reading timestamp at position=
     710: invokevirtual #95                 // Method java/lang/StringBuilder.append:(Ljava/lang/String;)Ljava/lang/StringBuilder;
     713: iload         4
     715: invokevirtual #99                 // Method java/lang/StringBuilder.append:(I)Ljava/lang/StringBuilder;
     718: aload_0
     719: iload_1
     720: iload_2
     721: invokestatic  #130                // Method bytesToHex:([BII)Ljava/lang/String;
     724: invokevirtual #95                 // Method java/lang/StringBuilder.append:(Ljava/lang/String;)Ljava/lang/StringBuilder;
     727: invokevirtual #100                // Method java/lang/StringBuilder.toString:()Ljava/lang/String;
     730: astore        11
     732: getstatic     #127                // Field LOG:Lorg/slf4j/Logger;
     735: aload         11
     737: invokeinterface #128,  2          // InterfaceMethod org/slf4j/Logger.warn:(Ljava/lang/String;)V
     742: new           #62                 // class java/lang/IllegalArgumentException
     745: dup
     746: aload         11
     748: invokespecial #64                 // Method java/lang/IllegalArgumentException."<init>":(Ljava/lang/String;)V
     751: athrow
     752: aload_0
     753: iload         4
     755: bipush        8
     757: invokestatic  #142                // Method org/apache/hadoop/hbase/util/Bytes.toLong:([BII)J
     760: lstore        11
     762: lload         11
     764: lconst_0
     765: lcmp
     766: ifge          820
     769: new           #92                 // class java/lang/StringBuilder
     772: dup
     773: invokespecial #93                 // Method java/lang/StringBuilder."<init>":()V
     776: ldc           #143                // String Timestamp cannot be negative, ts=
     778: invokevirtual #95                 // Method java/lang/StringBuilder.append:(Ljava/lang/String;)Ljava/lang/StringBuilder;
     781: lload         11
     783: invokevirtual #96                 // Method java/lang/StringBuilder.append:(J)Ljava/lang/StringBuilder;
     786: aload_0
     787: iload_1
     788: iload_2
     789: invokestatic  #130                // Method bytesToHex:([BII)Ljava/lang/String;
     792: invokevirtual #95                 // Method java/lang/StringBuilder.append:(Ljava/lang/String;)Ljava/lang/StringBuilder;
     795: invokevirtual #100                // Method java/lang/StringBuilder.toString:()Ljava/lang/String;
     798: astore        13
     800: getstatic     #127                // Field LOG:Lorg/slf4j/Logger;
     803: aload         13
     805: invokeinterface #128,  2          // InterfaceMethod org/slf4j/Logger.warn:(Ljava/lang/String;)V
     810: new           #62                 // class java/lang/IllegalArgumentException
     813: dup
     814: aload         13
     816: invokespecial #64                 // Method java/lang/IllegalArgumentException."<init>":(Ljava/lang/String;)V
     819: athrow
     820: iinc          4, 8
     823: iload         4
     825: iconst_1
     826: iadd
     827: iload         5
     829: if_icmple     883
     832: new           #92                 // class java/lang/StringBuilder
     835: dup
     836: invokespecial #93                 // Method java/lang/StringBuilder."<init>":()V
     839: ldc           #144                // String Overflow when reading type at position=
     841: invokevirtual #95                 // Method java/lang/StringBuilder.append:(Ljava/lang/String;)Ljava/lang/StringBuilder;
     844: iload         4
     846: invokevirtual #99                 // Method java/lang/StringBuilder.append:(I)Ljava/lang/StringBuilder;
     849: aload_0
     850: iload_1
     851: iload_2
     852: invokestatic  #130                // Method bytesToHex:([BII)Ljava/lang/String;
     855: invokevirtual #95                 // Method java/lang/StringBuilder.append:(Ljava/lang/String;)Ljava/lang/StringBuilder;
     858: invokevirtual #100                // Method java/lang/StringBuilder.toString:()Ljava/lang/String;
     861: astore        13
     863: getstatic     #127                // Field LOG:Lorg/slf4j/Logger;
     866: aload         13
     868: invokeinterface #128,  2          // InterfaceMethod org/slf4j/Logger.warn:(Ljava/lang/String;)V
     873: new           #62                 // class java/lang/IllegalArgumentException
     876: dup
     877: aload         13
     879: invokespecial #64                 // Method java/lang/IllegalArgumentException."<init>":(Ljava/lang/String;)V
     882: athrow
     883: aload_0
     884: iload         4
     886: baload
     887: istore        13
     889: iload         13
     891: invokestatic  #145                // Method org/apache/hadoop/hbase/KeyValue$Type.isValidType:(B)Z
     894: ifne          948
     897: new           #92                 // class java/lang/StringBuilder
     900: dup
     901: invokespecial #93                 // Method java/lang/StringBuilder."<init>":()V
     904: ldc           #146                // String Invalid type in KeyValue, type=
     906: invokevirtual #95                 // Method java/lang/StringBuilder.append:(Ljava/lang/String;)Ljava/lang/StringBuilder;
     909: iload         13
     911: invokevirtual #99                 // Method java/lang/StringBuilder.append:(I)Ljava/lang/StringBuilder;
     914: aload_0
     915: iload_1
     916: iload_2
     917: invokestatic  #130                // Method bytesToHex:([BII)Ljava/lang/String;
     920: invokevirtual #95                 // Method java/lang/StringBuilder.append:(Ljava/lang/String;)Ljava/lang/StringBuilder;
     923: invokevirtual #100                // Method java/lang/StringBuilder.toString:()Ljava/lang/String;
     926: astore        14
     928: getstatic     #127                // Field LOG:Lorg/slf4j/Logger;
     931: aload         14
     933: invokeinterface #128,  2          // InterfaceMethod org/slf4j/Logger.warn:(Ljava/lang/String;)V
     938: new           #62                 // class java/lang/IllegalArgumentException
     941: dup
     942: aload         14
     944: invokespecial #64                 // Method java/lang/IllegalArgumentException."<init>":(Ljava/lang/String;)V
     947: athrow
     948: iinc          4, 1
     951: iload         4
     953: iload         7
     955: iadd
     956: iload         5
     958: if_icmple     1012
     961: new           #92                 // class java/lang/StringBuilder
     964: dup
     965: invokespecial #93                 // Method java/lang/StringBuilder."<init>":()V
     968: ldc           #147                // String Overflow when reading value part at position=
     970: invokevirtual #95                 // Method java/lang/StringBuilder.append:(Ljava/lang/String;)Ljava/lang/StringBuilder;
     973: iload         4
     975: invokevirtual #99                 // Method java/lang/StringBuilder.append:(I)Ljava/lang/StringBuilder;
     978: aload_0
     979: iload_1
     980: iload_2
     981: invokestatic  #130                // Method bytesToHex:([BII)Ljava/lang/String;
     984: invokevirtual #95                 // Method java/lang/StringBuilder.append:(Ljava/lang/String;)Ljava/lang/StringBuilder;
     987: invokevirtual #100                // Method java/lang/StringBuilder.toString:()Ljava/lang/String;
     990: astore        14
     992: getstatic     #127                // Field LOG:Lorg/slf4j/Logger;
     995: aload         14
     997: invokeinterface #128,  2          // InterfaceMethod org/slf4j/Logger.warn:(Ljava/lang/String;)V
    1002: new           #62                 // class java/lang/IllegalArgumentException
    1005: dup
    1006: aload         14
    1008: invokespecial #64                 // Method java/lang/IllegalArgumentException."<init>":(Ljava/lang/String;)V
    1011: athrow
    1012: iload         4
    1014: iload         7
    1016: iadd
    1017: istore        4
    1019: iload_3
    1020: ifeq          1043
    1023: iload         4
    1025: iload         5
    1027: if_icmpne     1031
    1030: return
    1031: aload_0
    1032: iload_1
    1033: iload_2
    1034: iload         4
    1036: iload         5
    1038: invokestatic  #148                // Method checkKeyValueTagBytes:([BIIII)I
    1041: istore        4
    1043: iload         4
    1045: iload         5
    1047: if_icmpeq     1111
    1050: new           #92                 // class java/lang/StringBuilder
    1053: dup
    1054: invokespecial #93                 // Method java/lang/StringBuilder."<init>":()V
    1057: ldc           #149                // String Some redundant bytes in KeyValue's buffer, startOffset=
    1059: invokevirtual #95                 // Method java/lang/StringBuilder.append:(Ljava/lang/String;)Ljava/lang/StringBuilder;
    1062: iload         4
    1064: invokevirtual #99                 // Method java/lang/StringBuilder.append:(I)Ljava/lang/StringBuilder;
    1067: ldc           #150                // String , endOffset=
    1069: invokevirtual #95                 // Method java/lang/StringBuilder.append:(Ljava/lang/String;)Ljava/lang/StringBuilder;
    1072: iload         5
    1074: invokevirtual #99                 // Method java/lang/StringBuilder.append:(I)Ljava/lang/StringBuilder;
    1077: aload_0
    1078: iload_1
    1079: iload_2
    1080: invokestatic  #130                // Method bytesToHex:([BII)Ljava/lang/String;
    1083: invokevirtual #95                 // Method java/lang/StringBuilder.append:(Ljava/lang/String;)Ljava/lang/StringBuilder;
    1086: invokevirtual #100                // Method java/lang/StringBuilder.toString:()Ljava/lang/String;
    1089: astore        14
    1091: getstatic     #127                // Field LOG:Lorg/slf4j/Logger;
    1094: aload         14
    1096: invokeinterface #128,  2          // InterfaceMethod org/slf4j/Logger.warn:(Ljava/lang/String;)V
    1101: new           #62                 // class java/lang/IllegalArgumentException
    1104: dup
    1105: aload         14
    1107: invokespecial #64                 // Method java/lang/IllegalArgumentException."<init>":(Ljava/lang/String;)V
    1110: athrow
    1111: return

  public static org.apache.hadoop.hbase.KeyValue createKeyValueFromInputStream(java.io.InputStream, boolean) throws java.io.IOException;
    Code:
       0: iconst_4
       1: newarray       byte
       3: astore_2
       4: iconst_0
       5: istore_3
       6: iload_3
       7: aload_2
       8: arraylength
       9: if_icmpge     81
      12: aload_0
      13: aload_2
      14: iload_3
      15: aload_2
      16: arraylength
      17: iload_3
      18: isub
      19: invokevirtual #158                // Method java/io/InputStream.read:([BII)I
      22: istore        4
      24: iload         4
      26: ifge          73
      29: iload_3
      30: ifne          41
      33: new           #159                // class java/io/EOFException
      36: dup
      37: invokespecial #160                // Method java/io/EOFException."<init>":()V
      40: athrow
      41: new           #161                // class java/io/IOException
      44: dup
      45: new           #92                 // class java/lang/StringBuilder
      48: dup
      49: invokespecial #93                 // Method java/lang/StringBuilder."<init>":()V
      52: ldc           #162                // String Failed read of int, read
      54: invokevirtual #95                 // Method java/lang/StringBuilder.append:(Ljava/lang/String;)Ljava/lang/StringBuilder;
      57: iload_3
      58: invokevirtual #99                 // Method java/lang/StringBuilder.append:(I)Ljava/lang/StringBuilder;
      61: ldc           #163                // String  bytes
      63: invokevirtual #95                 // Method java/lang/StringBuilder.append:(Ljava/lang/String;)Ljava/lang/StringBuilder;
      66: invokevirtual #100                // Method java/lang/StringBuilder.toString:()Ljava/lang/String;
      69: invokespecial #164                // Method java/io/IOException."<init>":(Ljava/lang/String;)V
      72: athrow
      73: iload_3
      74: iload         4
      76: iadd
      77: istore_3
      78: goto          6
      81: aload_2
      82: invokestatic  #165                // Method org/apache/hadoop/hbase/util/Bytes.toInt:([B)I
      85: newarray       byte
      87: astore        4
      89: aload_0
      90: aload         4
      92: iconst_0
      93: aload         4
      95: arraylength
      96: invokestatic  #166                // Method org/apache/hadoop/io/IOUtils.readFully:(Ljava/io/InputStream;[BII)V
      99: iload_1
     100: ifeq          119
     103: new           #16                 // class org/apache/hadoop/hbase/KeyValue
     106: dup
     107: aload         4
     109: iconst_0
     110: aload         4
     112: arraylength
     113: invokespecial #19                 // Method org/apache/hadoop/hbase/KeyValue."<init>":([BII)V
     116: goto          132
     119: new           #167                // class org/apache/hadoop/hbase/NoTagsKeyValue
     122: dup
     123: aload         4
     125: iconst_0
     126: aload         4
     128: arraylength
     129: invokespecial #168                // Method org/apache/hadoop/hbase/NoTagsKeyValue."<init>":([BII)V
     132: areturn

  public static org.apache.hadoop.hbase.KeyValue createKeyValueFromKey(byte[]);
    Code:
       0: aload_0
       1: iconst_0
       2: aload_0
       3: arraylength
       4: invokestatic  #169                // Method createKeyValueFromKey:([BII)Lorg/apache/hadoop/hbase/KeyValue;
       7: areturn

  public static org.apache.hadoop.hbase.KeyValue createKeyValueFromKey(java.nio.ByteBuffer);
    Code:
       0: aload_0
       1: invokevirtual #71                 // Method java/nio/ByteBuffer.array:()[B
       4: aload_0
       5: invokevirtual #66                 // Method java/nio/ByteBuffer.arrayOffset:()I
       8: aload_0
       9: invokevirtual #170                // Method java/nio/ByteBuffer.limit:()I
      12: invokestatic  #169                // Method createKeyValueFromKey:([BII)Lorg/apache/hadoop/hbase/KeyValue;
      15: areturn

  public static org.apache.hadoop.hbase.KeyValue createKeyValueFromKey(byte[], int, int);
    Code:
       0: iload_2
       1: bipush        8
       3: iadd
       4: newarray       byte
       6: astore_3
       7: aload_0
       8: iload_1
       9: aload_3
      10: bipush        8
      12: iload_2
      13: invokestatic  #171                // Method java/lang/System.arraycopy:(Ljava/lang/Object;ILjava/lang/Object;II)V
      16: aload_3
      17: iconst_0
      18: iload_2
      19: invokestatic  #37                 // Method org/apache/hadoop/hbase/util/Bytes.putInt:([BII)I
      22: pop
      23: aload_3
      24: iconst_4
      25: iconst_0
      26: invokestatic  #37                 // Method org/apache/hadoop/hbase/util/Bytes.putInt:([BII)I
      29: pop
      30: new           #16                 // class org/apache/hadoop/hbase/KeyValue
      33: dup
      34: aload_3
      35: invokespecial #172                // Method org/apache/hadoop/hbase/KeyValue."<init>":([B)V
      38: areturn

  public static org.apache.hadoop.hbase.KeyValue create(java.io.DataInput) throws java.io.IOException;
    Code:
       0: aload_0
       1: invokeinterface #173,  1          // InterfaceMethod java/io/DataInput.readInt:()I
       6: aload_0
       7: invokestatic  #174                // Method create:(ILjava/io/DataInput;)Lorg/apache/hadoop/hbase/KeyValue;
      10: areturn

  public static org.apache.hadoop.hbase.KeyValue create(int, java.io.DataInput) throws java.io.IOException;
    Code:
       0: iload_0
       1: ifgt          42
       4: iload_0
       5: ifne          10
       8: aconst_null
       9: areturn
      10: new           #161                // class java/io/IOException
      13: dup
      14: new           #92                 // class java/lang/StringBuilder
      17: dup
      18: invokespecial #93                 // Method java/lang/StringBuilder."<init>":()V
      21: ldc           #175                // String Failed read
      23: invokevirtual #95                 // Method java/lang/StringBuilder.append:(Ljava/lang/String;)Ljava/lang/StringBuilder;
      26: iload_0
      27: invokevirtual #99                 // Method java/lang/StringBuilder.append:(I)Ljava/lang/StringBuilder;
      30: ldc           #176                // String  bytes, stream corrupt?
      32: invokevirtual #95                 // Method java/lang/StringBuilder.append:(Ljava/lang/String;)Ljava/lang/StringBuilder;
      35: invokevirtual #100                // Method java/lang/StringBuilder.toString:()Ljava/lang/String;
      38: invokespecial #164                // Method java/io/IOException."<init>":(Ljava/lang/String;)V
      41: athrow
      42: iload_0
      43: newarray       byte
      45: astore_2
      46: aload_1
      47: aload_2
      48: invokeinterface #177,  2          // InterfaceMethod java/io/DataInput.readFully:([B)V
      53: new           #16                 // class org/apache/hadoop/hbase/KeyValue
      56: dup
      57: aload_2
      58: iconst_0
      59: iload_0
      60: invokespecial #19                 // Method org/apache/hadoop/hbase/KeyValue."<init>":([BII)V
      63: areturn

  public static int getSerializedSize(org.apache.hadoop.hbase.Cell, boolean);
    Code:
       0: iload_1
       1: ifeq          11
       4: aload_0
       5: invokeinterface #27,  1           // InterfaceMethod org/apache/hadoop/hbase/Cell.getSerializedSize:()I
      10: ireturn
      11: aload_0
      12: instanceof    #178                // class org/apache/hadoop/hbase/ExtendedCell
      15: ifeq          29
      18: aload_0
      19: checkcast     #178                // class org/apache/hadoop/hbase/ExtendedCell
      22: iload_1
      23: invokeinterface #179,  2          // InterfaceMethod org/apache/hadoop/hbase/ExtendedCell.getSerializedSize:(Z)I
      28: ireturn
      29: aload_0
      30: invokeinterface #4,  1            // InterfaceMethod org/apache/hadoop/hbase/Cell.getRowLength:()S
      35: aload_0
      36: invokeinterface #5,  1            // InterfaceMethod org/apache/hadoop/hbase/Cell.getFamilyLength:()B
      41: aload_0
      42: invokeinterface #6,  1            // InterfaceMethod org/apache/hadoop/hbase/Cell.getQualifierLength:()I
      47: aload_0
      48: invokeinterface #38,  1           // InterfaceMethod org/apache/hadoop/hbase/Cell.getValueLength:()I
      53: aload_0
      54: invokeinterface #40,  1           // InterfaceMethod org/apache/hadoop/hbase/Cell.getTagsLength:()I
      59: iload_1
      60: invokestatic  #180                // Method length:(SBIIIZ)I
      63: ireturn

  public static int oswrite(org.apache.hadoop.hbase.Cell, java.io.OutputStream, boolean) throws java.io.IOException;
    Code:
       0: aload_0
       1: instanceof    #178                // class org/apache/hadoop/hbase/ExtendedCell
       4: ifeq          19
       7: aload_0
       8: checkcast     #178                // class org/apache/hadoop/hbase/ExtendedCell
      11: aload_1
      12: iload_2
      13: invokeinterface #181,  3          // InterfaceMethod org/apache/hadoop/hbase/ExtendedCell.write:(Ljava/io/OutputStream;Z)I
      18: ireturn
      19: aload_0
      20: invokeinterface #4,  1            // InterfaceMethod org/apache/hadoop/hbase/Cell.getRowLength:()S
      25: istore_3
      26: aload_0
      27: invokeinterface #5,  1            // InterfaceMethod org/apache/hadoop/hbase/Cell.getFamilyLength:()B
      32: istore        4
      34: aload_0
      35: invokeinterface #6,  1            // InterfaceMethod org/apache/hadoop/hbase/Cell.getQualifierLength:()I
      40: istore        5
      42: aload_0
      43: invokeinterface #38,  1           // InterfaceMethod org/apache/hadoop/hbase/Cell.getValueLength:()I
      48: istore        6
      50: aload_0
      51: invokeinterface #40,  1           // InterfaceMethod org/apache/hadoop/hbase/Cell.getTagsLength:()I
      56: istore        7
      58: iconst_0
      59: istore        8
      61: iload_3
      62: iload         4
      64: iload         5
      66: invokestatic  #7                  // Method keyLength:(SBI)I
      69: istore        9
      71: aload_1
      72: iload         9
      74: invokestatic  #182                // Method org/apache/hadoop/hbase/util/ByteBufferUtils.putInt:(Ljava/io/OutputStream;I)V
      77: aload_1
      78: iload         6
      80: invokestatic  #182                // Method org/apache/hadoop/hbase/util/ByteBufferUtils.putInt:(Ljava/io/OutputStream;I)V
      83: aload_1
      84: iload_3
      85: invokestatic  #183                // Method org/apache/hadoop/hbase/io/util/StreamUtils.writeShort:(Ljava/io/OutputStream;S)V
      88: aload_1
      89: aload_0
      90: invokeinterface #184,  1          // InterfaceMethod org/apache/hadoop/hbase/Cell.getRowArray:()[B
      95: aload_0
      96: invokeinterface #185,  1          // InterfaceMethod org/apache/hadoop/hbase/Cell.getRowOffset:()I
     101: iload_3
     102: invokevirtual #186                // Method java/io/OutputStream.write:([BII)V
     105: aload_1
     106: iload         4
     108: invokevirtual #187                // Method java/io/OutputStream.write:(I)V
     111: aload_1
     112: aload_0
     113: invokeinterface #188,  1          // InterfaceMethod org/apache/hadoop/hbase/Cell.getFamilyArray:()[B
     118: aload_0
     119: invokeinterface #189,  1          // InterfaceMethod org/apache/hadoop/hbase/Cell.getFamilyOffset:()I
     124: iload         4
     126: invokevirtual #186                // Method java/io/OutputStream.write:([BII)V
     129: aload_1
     130: aload_0
     131: invokeinterface #190,  1          // InterfaceMethod org/apache/hadoop/hbase/Cell.getQualifierArray:()[B
     136: aload_0
     137: invokeinterface #191,  1          // InterfaceMethod org/apache/hadoop/hbase/Cell.getQualifierOffset:()I
     142: iload         5
     144: invokevirtual #186                // Method java/io/OutputStream.write:([BII)V
     147: aload_1
     148: aload_0
     149: invokeinterface #34,  1           // InterfaceMethod org/apache/hadoop/hbase/Cell.getTimestamp:()J
     154: invokestatic  #192                // Method org/apache/hadoop/hbase/io/util/StreamUtils.writeLong:(Ljava/io/OutputStream;J)V
     157: aload_1
     158: aload_0
     159: invokeinterface #36,  1           // InterfaceMethod org/apache/hadoop/hbase/Cell.getTypeByte:()B
     164: invokevirtual #187                // Method java/io/OutputStream.write:(I)V
     167: aload_1
     168: aload_0
     169: invokeinterface #193,  1          // InterfaceMethod org/apache/hadoop/hbase/Cell.getValueArray:()[B
     174: aload_0
     175: invokeinterface #194,  1          // InterfaceMethod org/apache/hadoop/hbase/Cell.getValueOffset:()I
     180: iload         6
     182: invokevirtual #186                // Method java/io/OutputStream.write:([BII)V
     185: iload         9
     187: iload         6
     189: iadd
     190: bipush        8
     192: iadd
     193: istore        8
     195: iload_2
     196: ifeq          256
     199: iload         7
     201: ifle          256
     204: aload_1
     205: sipush        255
     208: iload         7
     210: bipush        8
     212: ishr
     213: iand
     214: i2b
     215: invokevirtual #187                // Method java/io/OutputStream.write:(I)V
     218: aload_1
     219: sipush        255
     222: iload         7
     224: iand
     225: i2b
     226: invokevirtual #187                // Method java/io/OutputStream.write:(I)V
     229: aload_1
     230: aload_0
     231: invokeinterface #195,  1          // InterfaceMethod org/apache/hadoop/hbase/Cell.getTagsArray:()[B
     236: aload_0
     237: invokeinterface #196,  1          // InterfaceMethod org/apache/hadoop/hbase/Cell.getTagsOffset:()I
     242: iload         7
     244: invokevirtual #186                // Method java/io/OutputStream.write:([BII)V
     247: iload         8
     249: iload         7
     251: iconst_2
     252: iadd
     253: iadd
     254: istore        8
     256: iload         8
     258: ireturn

  static {};
    Code:
       0: ldc           #197                // class org/apache/hadoop/hbase/KeyValueUtil
       2: invokestatic  #198                // Method org/slf4j/LoggerFactory.getLogger:(Ljava/lang/Class;)Lorg/slf4j/Logger;
       5: putstatic     #127                // Field LOG:Lorg/slf4j/Logger;
       8: return
}
