Compiled from "KeyValueCodec.java"
public class org.apache.hadoop.hbase.codec.KeyValueCodec$KeyValueDecoder extends org.apache.hadoop.hbase.codec.BaseDecoder {
  public org.apache.hadoop.hbase.codec.KeyValueCodec$KeyValueDecoder(java.io.InputStream);
    Code:
       0: aload_0
       1: aload_1
       2: invokespecial #1                  // Method org/apache/hadoop/hbase/codec/BaseDecoder."<init>":(Ljava/io/InputStream;)V
       5: return

  protected org.apache.hadoop.hbase.Cell parseCell() throws java.io.IOException;
    Code:
       0: aload_0
       1: getfield      #2                  // Field in:Ljava/io/InputStream;
       4: iconst_0
       5: invokestatic  #3                  // Method org/apache/hadoop/hbase/KeyValueUtil.createKeyValueFromInputStream:(Ljava/io/InputStream;Z)Lorg/apache/hadoop/hbase/KeyValue;
       8: areturn
}
