Compiled from "LeafExpressionNode.java"
public class org.apache.hadoop.hbase.security.visibility.expression.LeafExpressionNode implements org.apache.hadoop.hbase.security.visibility.expression.ExpressionNode {
  public static final org.apache.hadoop.hbase.security.visibility.expression.LeafExpressionNode OPEN_PARAN_NODE;

  public static final org.apache.hadoop.hbase.security.visibility.expression.LeafExpressionNode CLOSE_PARAN_NODE;

  public org.apache.hadoop.hbase.security.visibility.expression.LeafExpressionNode(java.lang.String);
    Code:
       0: aload_0
       1: invokespecial #1                  // Method java/lang/Object."<init>":()V
       4: aload_0
       5: aload_1
       6: putfield      #2                  // Field identifier:Ljava/lang/String;
       9: return

  public java.lang.String getIdentifier();
    Code:
       0: aload_0
       1: getfield      #2                  // Field identifier:Ljava/lang/String;
       4: areturn

  public int hashCode();
    Code:
       0: aload_0
       1: getfield      #2                  // Field identifier:Ljava/lang/String;
       4: invokevirtual #3                  // Method java/lang/String.hashCode:()I
       7: ireturn

  public boolean equals(java.lang.Object);
    Code:
       0: aload_1
       1: instanceof    #4                  // class org/apache/hadoop/hbase/security/visibility/expression/LeafExpressionNode
       4: ifeq          24
       7: aload_1
       8: checkcast     #4                  // class org/apache/hadoop/hbase/security/visibility/expression/LeafExpressionNode
      11: astore_2
      12: aload_0
      13: getfield      #2                  // Field identifier:Ljava/lang/String;
      16: aload_2
      17: getfield      #2                  // Field identifier:Ljava/lang/String;
      20: invokevirtual #5                  // Method java/lang/String.equals:(Ljava/lang/Object;)Z
      23: ireturn
      24: iconst_0
      25: ireturn

  public java.lang.String toString();
    Code:
       0: aload_0
       1: getfield      #2                  // Field identifier:Ljava/lang/String;
       4: areturn

  public boolean isSingleNode();
    Code:
       0: iconst_1
       1: ireturn

  public org.apache.hadoop.hbase.security.visibility.expression.LeafExpressionNode deepClone();
    Code:
       0: new           #4                  // class org/apache/hadoop/hbase/security/visibility/expression/LeafExpressionNode
       3: dup
       4: aload_0
       5: getfield      #2                  // Field identifier:Ljava/lang/String;
       8: invokespecial #6                  // Method "<init>":(Ljava/lang/String;)V
      11: astore_1
      12: aload_1
      13: areturn

  public org.apache.hadoop.hbase.security.visibility.expression.ExpressionNode deepClone();
    Code:
       0: aload_0
       1: invokevirtual #7                  // Method deepClone:()Lorg/apache/hadoop/hbase/security/visibility/expression/LeafExpressionNode;
       4: areturn

  static {};
    Code:
       0: new           #4                  // class org/apache/hadoop/hbase/security/visibility/expression/LeafExpressionNode
       3: dup
       4: ldc           #8                  // String (
       6: invokespecial #6                  // Method "<init>":(Ljava/lang/String;)V
       9: putstatic     #9                  // Field OPEN_PARAN_NODE:Lorg/apache/hadoop/hbase/security/visibility/expression/LeafExpressionNode;
      12: new           #4                  // class org/apache/hadoop/hbase/security/visibility/expression/LeafExpressionNode
      15: dup
      16: ldc           #10                 // String )
      18: invokespecial #6                  // Method "<init>":(Ljava/lang/String;)V
      21: putstatic     #11                 // Field CLOSE_PARAN_NODE:Lorg/apache/hadoop/hbase/security/visibility/expression/LeafExpressionNode;
      24: return
}
