Compiled from "LockServiceProtos.java"
final class org.apache.hadoop.hbase.shaded.protobuf.generated.LockServiceProtos$1 implements org.apache.hbase.thirdparty.com.google.protobuf.Descriptors$FileDescriptor$InternalDescriptorAssigner {
  org.apache.hadoop.hbase.shaded.protobuf.generated.LockServiceProtos$1();
    Code:
       0: aload_0
       1: invokespecial #1                  // Method java/lang/Object."<init>":()V
       4: return

  public org.apache.hbase.thirdparty.com.google.protobuf.ExtensionRegistry assignDescriptors(org.apache.hbase.thirdparty.com.google.protobuf.Descriptors$FileDescriptor);
    Code:
       0: aload_1
       1: invokestatic  #2                  // Method org/apache/hadoop/hbase/shaded/protobuf/generated/LockServiceProtos.access$8302:(Lorg/apache/hbase/thirdparty/com/google/protobuf/Descriptors$FileDescriptor;)Lorg/apache/hbase/thirdparty/com/google/protobuf/Descriptors$FileDescriptor;
       4: pop
       5: aconst_null
       6: areturn
}
