Compiled from "LockManager.java"
public class org.apache.hadoop.hbase.master.locking.LockManager$MasterLock {
  final org.apache.hadoop.hbase.master.locking.LockManager this$0;

  public org.apache.hadoop.hbase.master.locking.LockManager$MasterLock(org.apache.hadoop.hbase.master.locking.LockManager, java.lang.String, org.apache.hadoop.hbase.procedure2.LockType, java.lang.String);
    Code:
       0: aload_0
       1: aload_1
       2: putfield      #1                  // Field this$0:Lorg/apache/hadoop/hbase/master/locking/LockManager;
       5: aload_0
       6: invokespecial #2                  // Method java/lang/Object."<init>":()V
       9: aload_0
      10: aconst_null
      11: putfield      #3                  // Field proc:Lorg/apache/hadoop/hbase/master/locking/LockProcedure;
      14: aload_0
      15: aload_2
      16: putfield      #4                  // Field namespace:Ljava/lang/String;
      19: aload_0
      20: aconst_null
      21: putfield      #5                  // Field tableName:Lorg/apache/hadoop/hbase/TableName;
      24: aload_0
      25: aconst_null
      26: putfield      #6                  // Field regionInfos:[Lorg/apache/hadoop/hbase/client/RegionInfo;
      29: aload_0
      30: aload_3
      31: putfield      #7                  // Field type:Lorg/apache/hadoop/hbase/procedure2/LockType;
      34: aload_0
      35: aload         4
      37: putfield      #8                  // Field description:Ljava/lang/String;
      40: return

  public org.apache.hadoop.hbase.master.locking.LockManager$MasterLock(org.apache.hadoop.hbase.master.locking.LockManager, org.apache.hadoop.hbase.TableName, org.apache.hadoop.hbase.procedure2.LockType, java.lang.String);
    Code:
       0: aload_0
       1: aload_1
       2: putfield      #1                  // Field this$0:Lorg/apache/hadoop/hbase/master/locking/LockManager;
       5: aload_0
       6: invokespecial #2                  // Method java/lang/Object."<init>":()V
       9: aload_0
      10: aconst_null
      11: putfield      #3                  // Field proc:Lorg/apache/hadoop/hbase/master/locking/LockProcedure;
      14: aload_0
      15: aconst_null
      16: putfield      #4                  // Field namespace:Ljava/lang/String;
      19: aload_0
      20: aload_2
      21: putfield      #5                  // Field tableName:Lorg/apache/hadoop/hbase/TableName;
      24: aload_0
      25: aconst_null
      26: putfield      #6                  // Field regionInfos:[Lorg/apache/hadoop/hbase/client/RegionInfo;
      29: aload_0
      30: aload_3
      31: putfield      #7                  // Field type:Lorg/apache/hadoop/hbase/procedure2/LockType;
      34: aload_0
      35: aload         4
      37: putfield      #8                  // Field description:Ljava/lang/String;
      40: return

  public org.apache.hadoop.hbase.master.locking.LockManager$MasterLock(org.apache.hadoop.hbase.master.locking.LockManager, org.apache.hadoop.hbase.client.RegionInfo[], java.lang.String);
    Code:
       0: aload_0
       1: aload_1
       2: putfield      #1                  // Field this$0:Lorg/apache/hadoop/hbase/master/locking/LockManager;
       5: aload_0
       6: invokespecial #2                  // Method java/lang/Object."<init>":()V
       9: aload_0
      10: aconst_null
      11: putfield      #3                  // Field proc:Lorg/apache/hadoop/hbase/master/locking/LockProcedure;
      14: aload_0
      15: aconst_null
      16: putfield      #4                  // Field namespace:Ljava/lang/String;
      19: aload_0
      20: aconst_null
      21: putfield      #5                  // Field tableName:Lorg/apache/hadoop/hbase/TableName;
      24: aload_0
      25: aload_2
      26: putfield      #6                  // Field regionInfos:[Lorg/apache/hadoop/hbase/client/RegionInfo;
      29: aload_0
      30: getstatic     #9                  // Field org/apache/hadoop/hbase/procedure2/LockType.EXCLUSIVE:Lorg/apache/hadoop/hbase/procedure2/LockType;
      33: putfield      #7                  // Field type:Lorg/apache/hadoop/hbase/procedure2/LockType;
      36: aload_0
      37: aload_3
      38: putfield      #8                  // Field description:Ljava/lang/String;
      41: return

  public boolean acquire() throws java.lang.InterruptedException;
    Code:
       0: aload_0
       1: lconst_0
       2: invokevirtual #10                 // Method tryAcquire:(J)Z
       5: ireturn

  public boolean tryAcquire(long) throws java.lang.InterruptedException;
    Code:
       0: aload_0
       1: getfield      #3                  // Field proc:Lorg/apache/hadoop/hbase/master/locking/LockProcedure;
       4: ifnull        19
       7: aload_0
       8: getfield      #3                  // Field proc:Lorg/apache/hadoop/hbase/master/locking/LockProcedure;
      11: invokevirtual #11                 // Method org/apache/hadoop/hbase/master/locking/LockProcedure.isLocked:()Z
      14: ifeq          19
      17: iconst_1
      18: ireturn
      19: new           #12                 // class java/util/concurrent/CountDownLatch
      22: dup
      23: iconst_1
      24: invokespecial #13                 // Method java/util/concurrent/CountDownLatch."<init>":(I)V
      27: astore_3
      28: aload_0
      29: getfield      #6                  // Field regionInfos:[Lorg/apache/hadoop/hbase/client/RegionInfo;
      32: ifnull        72
      35: aload_0
      36: new           #14                 // class org/apache/hadoop/hbase/master/locking/LockProcedure
      39: dup
      40: aload_0
      41: getfield      #1                  // Field this$0:Lorg/apache/hadoop/hbase/master/locking/LockManager;
      44: invokestatic  #15                 // Method org/apache/hadoop/hbase/master/locking/LockManager.access$000:(Lorg/apache/hadoop/hbase/master/locking/LockManager;)Lorg/apache/hadoop/hbase/master/HMaster;
      47: invokevirtual #16                 // Method org/apache/hadoop/hbase/master/HMaster.getConfiguration:()Lorg/apache/hadoop/conf/Configuration;
      50: aload_0
      51: getfield      #6                  // Field regionInfos:[Lorg/apache/hadoop/hbase/client/RegionInfo;
      54: aload_0
      55: getfield      #7                  // Field type:Lorg/apache/hadoop/hbase/procedure2/LockType;
      58: aload_0
      59: getfield      #8                  // Field description:Ljava/lang/String;
      62: aload_3
      63: invokespecial #17                 // Method org/apache/hadoop/hbase/master/locking/LockProcedure."<init>":(Lorg/apache/hadoop/conf/Configuration;[Lorg/apache/hadoop/hbase/client/RegionInfo;Lorg/apache/hadoop/hbase/procedure2/LockType;Ljava/lang/String;Ljava/util/concurrent/CountDownLatch;)V
      66: putfield      #3                  // Field proc:Lorg/apache/hadoop/hbase/master/locking/LockProcedure;
      69: goto          170
      72: aload_0
      73: getfield      #5                  // Field tableName:Lorg/apache/hadoop/hbase/TableName;
      76: ifnull        116
      79: aload_0
      80: new           #14                 // class org/apache/hadoop/hbase/master/locking/LockProcedure
      83: dup
      84: aload_0
      85: getfield      #1                  // Field this$0:Lorg/apache/hadoop/hbase/master/locking/LockManager;
      88: invokestatic  #15                 // Method org/apache/hadoop/hbase/master/locking/LockManager.access$000:(Lorg/apache/hadoop/hbase/master/locking/LockManager;)Lorg/apache/hadoop/hbase/master/HMaster;
      91: invokevirtual #16                 // Method org/apache/hadoop/hbase/master/HMaster.getConfiguration:()Lorg/apache/hadoop/conf/Configuration;
      94: aload_0
      95: getfield      #5                  // Field tableName:Lorg/apache/hadoop/hbase/TableName;
      98: aload_0
      99: getfield      #7                  // Field type:Lorg/apache/hadoop/hbase/procedure2/LockType;
     102: aload_0
     103: getfield      #8                  // Field description:Ljava/lang/String;
     106: aload_3
     107: invokespecial #18                 // Method org/apache/hadoop/hbase/master/locking/LockProcedure."<init>":(Lorg/apache/hadoop/conf/Configuration;Lorg/apache/hadoop/hbase/TableName;Lorg/apache/hadoop/hbase/procedure2/LockType;Ljava/lang/String;Ljava/util/concurrent/CountDownLatch;)V
     110: putfield      #3                  // Field proc:Lorg/apache/hadoop/hbase/master/locking/LockProcedure;
     113: goto          170
     116: aload_0
     117: getfield      #4                  // Field namespace:Ljava/lang/String;
     120: ifnull        160
     123: aload_0
     124: new           #14                 // class org/apache/hadoop/hbase/master/locking/LockProcedure
     127: dup
     128: aload_0
     129: getfield      #1                  // Field this$0:Lorg/apache/hadoop/hbase/master/locking/LockManager;
     132: invokestatic  #15                 // Method org/apache/hadoop/hbase/master/locking/LockManager.access$000:(Lorg/apache/hadoop/hbase/master/locking/LockManager;)Lorg/apache/hadoop/hbase/master/HMaster;
     135: invokevirtual #16                 // Method org/apache/hadoop/hbase/master/HMaster.getConfiguration:()Lorg/apache/hadoop/conf/Configuration;
     138: aload_0
     139: getfield      #4                  // Field namespace:Ljava/lang/String;
     142: aload_0
     143: getfield      #7                  // Field type:Lorg/apache/hadoop/hbase/procedure2/LockType;
     146: aload_0
     147: getfield      #8                  // Field description:Ljava/lang/String;
     150: aload_3
     151: invokespecial #19                 // Method org/apache/hadoop/hbase/master/locking/LockProcedure."<init>":(Lorg/apache/hadoop/conf/Configuration;Ljava/lang/String;Lorg/apache/hadoop/hbase/procedure2/LockType;Ljava/lang/String;Ljava/util/concurrent/CountDownLatch;)V
     154: putfield      #3                  // Field proc:Lorg/apache/hadoop/hbase/master/locking/LockProcedure;
     157: goto          170
     160: new           #20                 // class java/lang/UnsupportedOperationException
     163: dup
     164: ldc           #21                 // String no namespace/table/region provided
     166: invokespecial #22                 // Method java/lang/UnsupportedOperationException."<init>":(Ljava/lang/String;)V
     169: athrow
     170: aload_0
     171: getfield      #3                  // Field proc:Lorg/apache/hadoop/hbase/master/locking/LockProcedure;
     174: aload_0
     175: getfield      #1                  // Field this$0:Lorg/apache/hadoop/hbase/master/locking/LockManager;
     178: invokestatic  #15                 // Method org/apache/hadoop/hbase/master/locking/LockManager.access$000:(Lorg/apache/hadoop/hbase/master/locking/LockManager;)Lorg/apache/hadoop/hbase/master/HMaster;
     181: invokevirtual #23                 // Method org/apache/hadoop/hbase/master/HMaster.getMasterProcedureExecutor:()Lorg/apache/hadoop/hbase/procedure2/ProcedureExecutor;
     184: invokevirtual #24                 // Method org/apache/hadoop/hbase/procedure2/ProcedureExecutor.getEnvironment:()Ljava/lang/Object;
     187: checkcast     #25                 // class org/apache/hadoop/hbase/master/procedure/MasterProcedureEnv
     190: invokevirtual #26                 // Method org/apache/hadoop/hbase/master/procedure/MasterProcedureEnv.getRequestUser:()Lorg/apache/hadoop/hbase/security/User;
     193: invokevirtual #27                 // Method org/apache/hadoop/hbase/master/locking/LockProcedure.setOwner:(Lorg/apache/hadoop/hbase/security/User;)V
     196: aload_0
     197: getfield      #1                  // Field this$0:Lorg/apache/hadoop/hbase/master/locking/LockManager;
     200: invokestatic  #15                 // Method org/apache/hadoop/hbase/master/locking/LockManager.access$000:(Lorg/apache/hadoop/hbase/master/locking/LockManager;)Lorg/apache/hadoop/hbase/master/HMaster;
     203: invokevirtual #23                 // Method org/apache/hadoop/hbase/master/HMaster.getMasterProcedureExecutor:()Lorg/apache/hadoop/hbase/procedure2/ProcedureExecutor;
     206: aload_0
     207: getfield      #3                  // Field proc:Lorg/apache/hadoop/hbase/master/locking/LockProcedure;
     210: invokevirtual #28                 // Method org/apache/hadoop/hbase/procedure2/ProcedureExecutor.submitProcedure:(Lorg/apache/hadoop/hbase/procedure2/Procedure;)J
     213: pop2
     214: lload_1
     215: lconst_0
     216: lcmp
     217: ifle          228
     220: invokestatic  #29                 // Method java/lang/System.currentTimeMillis:()J
     223: lload_1
     224: ladd
     225: goto          231
     228: ldc2_w        #31                 // long 9223372036854775807l
     231: lstore        4
     233: lload         4
     235: invokestatic  #29                 // Method java/lang/System.currentTimeMillis:()J
     238: lcmp
     239: iflt          311
     242: aload_0
     243: getfield      #3                  // Field proc:Lorg/apache/hadoop/hbase/master/locking/LockProcedure;
     246: invokevirtual #11                 // Method org/apache/hadoop/hbase/master/locking/LockProcedure.isLocked:()Z
     249: ifne          311
     252: aload_3
     253: lload         4
     255: invokestatic  #29                 // Method java/lang/System.currentTimeMillis:()J
     258: lsub
     259: getstatic     #33                 // Field java/util/concurrent/TimeUnit.MILLISECONDS:Ljava/util/concurrent/TimeUnit;
     262: invokevirtual #34                 // Method java/util/concurrent/CountDownLatch.await:(JLjava/util/concurrent/TimeUnit;)Z
     265: pop
     266: goto          233
     269: astore        6
     271: invokestatic  #36                 // Method org/apache/hadoop/hbase/master/locking/LockManager.access$100:()Lorg/slf4j/Logger;
     274: new           #37                 // class java/lang/StringBuilder
     277: dup
     278: invokespecial #38                 // Method java/lang/StringBuilder."<init>":()V
     281: ldc           #39                 // String InterruptedException when waiting for lock:
     283: invokevirtual #40                 // Method java/lang/StringBuilder.append:(Ljava/lang/String;)Ljava/lang/StringBuilder;
     286: aload_0
     287: getfield      #3                  // Field proc:Lorg/apache/hadoop/hbase/master/locking/LockProcedure;
     290: invokevirtual #41                 // Method org/apache/hadoop/hbase/master/locking/LockProcedure.toString:()Ljava/lang/String;
     293: invokevirtual #40                 // Method java/lang/StringBuilder.append:(Ljava/lang/String;)Ljava/lang/StringBuilder;
     296: invokevirtual #42                 // Method java/lang/StringBuilder.toString:()Ljava/lang/String;
     299: invokeinterface #43,  2           // InterfaceMethod org/slf4j/Logger.info:(Ljava/lang/String;)V
     304: aload_0
     305: invokevirtual #44                 // Method release:()V
     308: aload         6
     310: athrow
     311: aload_0
     312: getfield      #3                  // Field proc:Lorg/apache/hadoop/hbase/master/locking/LockProcedure;
     315: invokevirtual #11                 // Method org/apache/hadoop/hbase/master/locking/LockProcedure.isLocked:()Z
     318: ifne          360
     321: invokestatic  #36                 // Method org/apache/hadoop/hbase/master/locking/LockManager.access$100:()Lorg/slf4j/Logger;
     324: new           #37                 // class java/lang/StringBuilder
     327: dup
     328: invokespecial #38                 // Method java/lang/StringBuilder."<init>":()V
     331: ldc           #45                 // String Timed out waiting to acquire procedure lock:
     333: invokevirtual #40                 // Method java/lang/StringBuilder.append:(Ljava/lang/String;)Ljava/lang/StringBuilder;
     336: aload_0
     337: getfield      #3                  // Field proc:Lorg/apache/hadoop/hbase/master/locking/LockProcedure;
     340: invokevirtual #41                 // Method org/apache/hadoop/hbase/master/locking/LockProcedure.toString:()Ljava/lang/String;
     343: invokevirtual #40                 // Method java/lang/StringBuilder.append:(Ljava/lang/String;)Ljava/lang/StringBuilder;
     346: invokevirtual #42                 // Method java/lang/StringBuilder.toString:()Ljava/lang/String;
     349: invokeinterface #43,  2           // InterfaceMethod org/slf4j/Logger.info:(Ljava/lang/String;)V
     354: aload_0
     355: invokevirtual #44                 // Method release:()V
     358: iconst_0
     359: ireturn
     360: iconst_1
     361: ireturn
    Exception table:
       from    to  target type
         252   266   269   Class java/lang/InterruptedException

  public void release();
    Code:
       0: aload_0
       1: getfield      #3                  // Field proc:Lorg/apache/hadoop/hbase/master/locking/LockProcedure;
       4: ifnull        30
       7: aload_0
       8: getfield      #3                  // Field proc:Lorg/apache/hadoop/hbase/master/locking/LockProcedure;
      11: aload_0
      12: getfield      #1                  // Field this$0:Lorg/apache/hadoop/hbase/master/locking/LockManager;
      15: invokestatic  #15                 // Method org/apache/hadoop/hbase/master/locking/LockManager.access$000:(Lorg/apache/hadoop/hbase/master/locking/LockManager;)Lorg/apache/hadoop/hbase/master/HMaster;
      18: invokevirtual #23                 // Method org/apache/hadoop/hbase/master/HMaster.getMasterProcedureExecutor:()Lorg/apache/hadoop/hbase/procedure2/ProcedureExecutor;
      21: invokevirtual #24                 // Method org/apache/hadoop/hbase/procedure2/ProcedureExecutor.getEnvironment:()Ljava/lang/Object;
      24: checkcast     #25                 // class org/apache/hadoop/hbase/master/procedure/MasterProcedureEnv
      27: invokevirtual #46                 // Method org/apache/hadoop/hbase/master/locking/LockProcedure.unlock:(Lorg/apache/hadoop/hbase/master/procedure/MasterProcedureEnv;)V
      30: aload_0
      31: aconst_null
      32: putfield      #3                  // Field proc:Lorg/apache/hadoop/hbase/master/locking/LockProcedure;
      35: return

  public java.lang.String toString();
    Code:
       0: new           #37                 // class java/lang/StringBuilder
       3: dup
       4: invokespecial #38                 // Method java/lang/StringBuilder."<init>":()V
       7: ldc           #47                 // String MasterLock: proc =
       9: invokevirtual #40                 // Method java/lang/StringBuilder.append:(Ljava/lang/String;)Ljava/lang/StringBuilder;
      12: aload_0
      13: getfield      #3                  // Field proc:Lorg/apache/hadoop/hbase/master/locking/LockProcedure;
      16: invokevirtual #41                 // Method org/apache/hadoop/hbase/master/locking/LockProcedure.toString:()Ljava/lang/String;
      19: invokevirtual #40                 // Method java/lang/StringBuilder.append:(Ljava/lang/String;)Ljava/lang/StringBuilder;
      22: invokevirtual #42                 // Method java/lang/StringBuilder.toString:()Ljava/lang/String;
      25: areturn

  org.apache.hadoop.hbase.master.locking.LockProcedure getProc();
    Code:
       0: aload_0
       1: getfield      #3                  // Field proc:Lorg/apache/hadoop/hbase/master/locking/LockProcedure;
       4: areturn
}
