Compiled from "LockProcedure.java"
public final class org.apache.hadoop.hbase.master.locking.LockProcedure extends org.apache.hadoop.hbase.procedure2.Procedure<org.apache.hadoop.hbase.master.procedure.MasterProcedureEnv> implements org.apache.hadoop.hbase.master.procedure.TableProcedureInterface {
  public static final int DEFAULT_REMOTE_LOCKS_TIMEOUT_MS;

  public static final java.lang.String REMOTE_LOCKS_TIMEOUT_MS_CONF;

  public static final int DEFAULT_LOCAL_MASTER_LOCKS_TIMEOUT_MS;

  public static final java.lang.String LOCAL_MASTER_LOCKS_TIMEOUT_MS_CONF;

  public org.apache.hadoop.hbase.TableName getTableName();
    Code:
       0: aload_0
       1: getfield      #3                  // Field tableName:Lorg/apache/hadoop/hbase/TableName;
       4: areturn

  public org.apache.hadoop.hbase.master.procedure.TableProcedureInterface$TableOperationType getTableOperationType();
    Code:
       0: aload_0
       1: getfield      #4                  // Field opType:Lorg/apache/hadoop/hbase/master/procedure/TableProcedureInterface$TableOperationType;
       4: areturn

  public org.apache.hadoop.hbase.master.locking.LockProcedure();
    Code:
       0: aload_0
       1: invokespecial #5                  // Method org/apache/hadoop/hbase/procedure2/Procedure."<init>":()V
       4: aload_0
       5: new           #6                  // class org/apache/hadoop/hbase/procedure2/ProcedureEvent
       8: dup
       9: aload_0
      10: invokespecial #7                  // Method org/apache/hadoop/hbase/procedure2/ProcedureEvent."<init>":(Ljava/lang/Object;)V
      13: putfield      #8                  // Field event:Lorg/apache/hadoop/hbase/procedure2/ProcedureEvent;
      16: aload_0
      17: new           #9                  // class java/util/concurrent/atomic/AtomicBoolean
      20: dup
      21: iconst_0
      22: invokespecial #10                 // Method java/util/concurrent/atomic/AtomicBoolean."<init>":(Z)V
      25: putfield      #11                 // Field locked:Ljava/util/concurrent/atomic/AtomicBoolean;
      28: aload_0
      29: new           #12                 // class java/util/concurrent/atomic/AtomicLong
      32: dup
      33: invokespecial #13                 // Method java/util/concurrent/atomic/AtomicLong."<init>":()V
      36: putfield      #14                 // Field lastHeartBeat:Ljava/util/concurrent/atomic/AtomicLong;
      39: aload_0
      40: new           #9                  // class java/util/concurrent/atomic/AtomicBoolean
      43: dup
      44: iconst_0
      45: invokespecial #10                 // Method java/util/concurrent/atomic/AtomicBoolean."<init>":(Z)V
      48: putfield      #15                 // Field unlock:Ljava/util/concurrent/atomic/AtomicBoolean;
      51: aload_0
      52: iconst_0
      53: putfield      #16                 // Field suspended:Z
      56: aload_0
      57: aconst_null
      58: putfield      #17                 // Field lockAcquireLatch:Ljava/util/concurrent/CountDownLatch;
      61: return

  public org.apache.hadoop.hbase.master.locking.LockProcedure(org.apache.hadoop.conf.Configuration, java.lang.String, org.apache.hadoop.hbase.procedure2.LockType, java.lang.String, java.util.concurrent.CountDownLatch) throws java.lang.IllegalArgumentException;
    Code:
       0: aload_0
       1: aload_1
       2: aload_3
       3: aload         4
       5: aload         5
       7: invokespecial #26                 // Method "<init>":(Lorg/apache/hadoop/conf/Configuration;Lorg/apache/hadoop/hbase/procedure2/LockType;Ljava/lang/String;Ljava/util/concurrent/CountDownLatch;)V
      10: aload_2
      11: invokevirtual #27                 // Method java/lang/String.isEmpty:()Z
      14: ifeq          27
      17: new           #28                 // class java/lang/IllegalArgumentException
      20: dup
      21: ldc           #29                 // String Empty namespace
      23: invokespecial #30                 // Method java/lang/IllegalArgumentException."<init>":(Ljava/lang/String;)V
      26: athrow
      27: aload_0
      28: aload_2
      29: putfield      #2                  // Field namespace:Ljava/lang/String;
      32: aload_0
      33: aload_0
      34: invokespecial #31                 // Method setupNamespaceLock:()Lorg/apache/hadoop/hbase/master/locking/LockProcedure$LockInterface;
      37: putfield      #32                 // Field lock:Lorg/apache/hadoop/hbase/master/locking/LockProcedure$LockInterface;
      40: return

  public org.apache.hadoop.hbase.master.locking.LockProcedure(org.apache.hadoop.conf.Configuration, org.apache.hadoop.hbase.TableName, org.apache.hadoop.hbase.procedure2.LockType, java.lang.String, java.util.concurrent.CountDownLatch) throws java.lang.IllegalArgumentException;
    Code:
       0: aload_0
       1: aload_1
       2: aload_3
       3: aload         4
       5: aload         5
       7: invokespecial #26                 // Method "<init>":(Lorg/apache/hadoop/conf/Configuration;Lorg/apache/hadoop/hbase/procedure2/LockType;Ljava/lang/String;Ljava/util/concurrent/CountDownLatch;)V
      10: aload_0
      11: aload_2
      12: putfield      #3                  // Field tableName:Lorg/apache/hadoop/hbase/TableName;
      15: aload_0
      16: aload_0
      17: invokespecial #33                 // Method setupTableLock:()Lorg/apache/hadoop/hbase/master/locking/LockProcedure$LockInterface;
      20: putfield      #32                 // Field lock:Lorg/apache/hadoop/hbase/master/locking/LockProcedure$LockInterface;
      23: return

  public org.apache.hadoop.hbase.master.locking.LockProcedure(org.apache.hadoop.conf.Configuration, org.apache.hadoop.hbase.client.RegionInfo[], org.apache.hadoop.hbase.procedure2.LockType, java.lang.String, java.util.concurrent.CountDownLatch) throws java.lang.IllegalArgumentException;
    Code:
       0: aload_0
       1: aload_1
       2: aload_3
       3: aload         4
       5: aload         5
       7: invokespecial #26                 // Method "<init>":(Lorg/apache/hadoop/conf/Configuration;Lorg/apache/hadoop/hbase/procedure2/LockType;Ljava/lang/String;Ljava/util/concurrent/CountDownLatch;)V
      10: aload_2
      11: arraylength
      12: ifne          25
      15: new           #28                 // class java/lang/IllegalArgumentException
      18: dup
      19: ldc           #34                 // String No regions specified for region lock
      21: invokespecial #30                 // Method java/lang/IllegalArgumentException."<init>":(Ljava/lang/String;)V
      24: athrow
      25: aload_2
      26: iconst_0
      27: aaload
      28: invokeinterface #35,  1           // InterfaceMethod org/apache/hadoop/hbase/client/RegionInfo.getTable:()Lorg/apache/hadoop/hbase/TableName;
      33: astore        6
      35: iconst_1
      36: istore        7
      38: iload         7
      40: aload_2
      41: arraylength
      42: if_icmpge     78
      45: aload_2
      46: iload         7
      48: aaload
      49: invokeinterface #35,  1           // InterfaceMethod org/apache/hadoop/hbase/client/RegionInfo.getTable:()Lorg/apache/hadoop/hbase/TableName;
      54: aload         6
      56: invokevirtual #36                 // Method org/apache/hadoop/hbase/TableName.equals:(Ljava/lang/Object;)Z
      59: ifne          72
      62: new           #28                 // class java/lang/IllegalArgumentException
      65: dup
      66: ldc           #37                 // String All regions should be from same table
      68: invokespecial #30                 // Method java/lang/IllegalArgumentException."<init>":(Ljava/lang/String;)V
      71: athrow
      72: iinc          7, 1
      75: goto          38
      78: aload_0
      79: aload_2
      80: putfield      #1                  // Field regionInfos:[Lorg/apache/hadoop/hbase/client/RegionInfo;
      83: aload_0
      84: aload_0
      85: invokespecial #38                 // Method setupRegionLock:()Lorg/apache/hadoop/hbase/master/locking/LockProcedure$LockInterface;
      88: putfield      #32                 // Field lock:Lorg/apache/hadoop/hbase/master/locking/LockProcedure$LockInterface;
      91: return

  public void updateHeartBeat();
    Code:
       0: aload_0
       1: getfield      #14                 // Field lastHeartBeat:Ljava/util/concurrent/atomic/AtomicLong;
       4: invokestatic  #39                 // Method java/lang/System.currentTimeMillis:()J
       7: invokevirtual #42                 // Method java/util/concurrent/atomic/AtomicLong.set:(J)V
      10: getstatic     #43                 // Field LOG:Lorg/slf4j/Logger;
      13: invokeinterface #44,  1           // InterfaceMethod org/slf4j/Logger.isDebugEnabled:()Z
      18: ifeq          51
      21: getstatic     #43                 // Field LOG:Lorg/slf4j/Logger;
      24: new           #45                 // class java/lang/StringBuilder
      27: dup
      28: invokespecial #46                 // Method java/lang/StringBuilder."<init>":()V
      31: ldc           #47                 // String Heartbeat
      33: invokevirtual #48                 // Method java/lang/StringBuilder.append:(Ljava/lang/String;)Ljava/lang/StringBuilder;
      36: aload_0
      37: invokevirtual #49                 // Method toString:()Ljava/lang/String;
      40: invokevirtual #48                 // Method java/lang/StringBuilder.append:(Ljava/lang/String;)Ljava/lang/StringBuilder;
      43: invokevirtual #50                 // Method java/lang/StringBuilder.toString:()Ljava/lang/String;
      46: invokeinterface #51,  2           // InterfaceMethod org/slf4j/Logger.debug:(Ljava/lang/String;)V
      51: return

  protected synchronized boolean setTimeoutFailure(org.apache.hadoop.hbase.master.procedure.MasterProcedureEnv);
    Code:
       0: aload_0
       1: getfield      #8                  // Field event:Lorg/apache/hadoop/hbase/procedure2/ProcedureEvent;
       4: dup
       5: astore_2
       6: monitorenter
       7: getstatic     #43                 // Field LOG:Lorg/slf4j/Logger;
      10: invokeinterface #44,  1           // InterfaceMethod org/slf4j/Logger.isDebugEnabled:()Z
      15: ifeq          48
      18: getstatic     #43                 // Field LOG:Lorg/slf4j/Logger;
      21: new           #45                 // class java/lang/StringBuilder
      24: dup
      25: invokespecial #46                 // Method java/lang/StringBuilder."<init>":()V
      28: ldc           #52                 // String Timeout failure
      30: invokevirtual #48                 // Method java/lang/StringBuilder.append:(Ljava/lang/String;)Ljava/lang/StringBuilder;
      33: aload_0
      34: getfield      #8                  // Field event:Lorg/apache/hadoop/hbase/procedure2/ProcedureEvent;
      37: invokevirtual #53                 // Method java/lang/StringBuilder.append:(Ljava/lang/Object;)Ljava/lang/StringBuilder;
      40: invokevirtual #50                 // Method java/lang/StringBuilder.toString:()Ljava/lang/String;
      43: invokeinterface #51,  2           // InterfaceMethod org/slf4j/Logger.debug:(Ljava/lang/String;)V
      48: aload_0
      49: getfield      #8                  // Field event:Lorg/apache/hadoop/hbase/procedure2/ProcedureEvent;
      52: invokevirtual #54                 // Method org/apache/hadoop/hbase/procedure2/ProcedureEvent.isReady:()Z
      55: ifne          117
      58: aload_0
      59: getstatic     #55                 // Field org/apache/hadoop/hbase/shaded/protobuf/generated/ProcedureProtos$ProcedureState.RUNNABLE:Lorg/apache/hadoop/hbase/shaded/protobuf/generated/ProcedureProtos$ProcedureState;
      62: invokevirtual #56                 // Method setState:(Lorg/apache/hadoop/hbase/shaded/protobuf/generated/ProcedureProtos$ProcedureState;)V
      65: getstatic     #43                 // Field LOG:Lorg/slf4j/Logger;
      68: invokeinterface #44,  1           // InterfaceMethod org/slf4j/Logger.isDebugEnabled:()Z
      73: ifeq          106
      76: getstatic     #43                 // Field LOG:Lorg/slf4j/Logger;
      79: new           #45                 // class java/lang/StringBuilder
      82: dup
      83: invokespecial #46                 // Method java/lang/StringBuilder."<init>":()V
      86: ldc           #57                 // String Calling wake on
      88: invokevirtual #48                 // Method java/lang/StringBuilder.append:(Ljava/lang/String;)Ljava/lang/StringBuilder;
      91: aload_0
      92: getfield      #8                  // Field event:Lorg/apache/hadoop/hbase/procedure2/ProcedureEvent;
      95: invokevirtual #53                 // Method java/lang/StringBuilder.append:(Ljava/lang/Object;)Ljava/lang/StringBuilder;
      98: invokevirtual #50                 // Method java/lang/StringBuilder.toString:()Ljava/lang/String;
     101: invokeinterface #51,  2           // InterfaceMethod org/slf4j/Logger.debug:(Ljava/lang/String;)V
     106: aload_0
     107: getfield      #8                  // Field event:Lorg/apache/hadoop/hbase/procedure2/ProcedureEvent;
     110: aload_1
     111: invokevirtual #58                 // Method org/apache/hadoop/hbase/master/procedure/MasterProcedureEnv.getProcedureScheduler:()Lorg/apache/hadoop/hbase/master/procedure/MasterProcedureScheduler;
     114: invokevirtual #59                 // Method org/apache/hadoop/hbase/procedure2/ProcedureEvent.wake:(Lorg/apache/hadoop/hbase/procedure2/AbstractProcedureScheduler;)V
     117: aload_2
     118: monitorexit
     119: goto          127
     122: astore_3
     123: aload_2
     124: monitorexit
     125: aload_3
     126: athrow
     127: iconst_0
     128: ireturn
    Exception table:
       from    to  target type
           7   119   122   any
         122   125   122   any

  public void unlock(org.apache.hadoop.hbase.master.procedure.MasterProcedureEnv);
    Code:
       0: aload_0
       1: getfield      #15                 // Field unlock:Ljava/util/concurrent/atomic/AtomicBoolean;
       4: iconst_1
       5: invokevirtual #60                 // Method java/util/concurrent/atomic/AtomicBoolean.set:(Z)V
       8: aload_0
       9: getfield      #11                 // Field locked:Ljava/util/concurrent/atomic/AtomicBoolean;
      12: iconst_0
      13: invokevirtual #60                 // Method java/util/concurrent/atomic/AtomicBoolean.set:(Z)V
      16: aload_0
      17: getfield      #8                  // Field event:Lorg/apache/hadoop/hbase/procedure2/ProcedureEvent;
      20: dup
      21: astore_2
      22: monitorenter
      23: aload_0
      24: getfield      #8                  // Field event:Lorg/apache/hadoop/hbase/procedure2/ProcedureEvent;
      27: invokevirtual #54                 // Method org/apache/hadoop/hbase/procedure2/ProcedureEvent.isReady:()Z
      30: ifne          63
      33: aload_0
      34: getfield      #16                 // Field suspended:Z
      37: ifeq          63
      40: aload_0
      41: getstatic     #55                 // Field org/apache/hadoop/hbase/shaded/protobuf/generated/ProcedureProtos$ProcedureState.RUNNABLE:Lorg/apache/hadoop/hbase/shaded/protobuf/generated/ProcedureProtos$ProcedureState;
      44: invokevirtual #56                 // Method setState:(Lorg/apache/hadoop/hbase/shaded/protobuf/generated/ProcedureProtos$ProcedureState;)V
      47: aload_0
      48: getfield      #8                  // Field event:Lorg/apache/hadoop/hbase/procedure2/ProcedureEvent;
      51: aload_1
      52: invokevirtual #58                 // Method org/apache/hadoop/hbase/master/procedure/MasterProcedureEnv.getProcedureScheduler:()Lorg/apache/hadoop/hbase/master/procedure/MasterProcedureScheduler;
      55: invokevirtual #59                 // Method org/apache/hadoop/hbase/procedure2/ProcedureEvent.wake:(Lorg/apache/hadoop/hbase/procedure2/AbstractProcedureScheduler;)V
      58: aload_0
      59: iconst_0
      60: putfield      #16                 // Field suspended:Z
      63: aload_2
      64: monitorexit
      65: goto          73
      68: astore_3
      69: aload_2
      70: monitorexit
      71: aload_3
      72: athrow
      73: return
    Exception table:
       from    to  target type
          23    65    68   any
          68    71    68   any

  protected org.apache.hadoop.hbase.procedure2.Procedure<org.apache.hadoop.hbase.master.procedure.MasterProcedureEnv>[] execute(org.apache.hadoop.hbase.master.procedure.MasterProcedureEnv) throws org.apache.hadoop.hbase.procedure2.ProcedureSuspendedException;
    Code:
       0: aload_0
       1: getfield      #61                 // Field recoveredMasterLock:Z
       4: ifeq          9
       7: aconst_null
       8: areturn
       9: aload_0
      10: getfield      #17                 // Field lockAcquireLatch:Ljava/util/concurrent/CountDownLatch;
      13: ifnull        23
      16: aload_0
      17: getfield      #17                 // Field lockAcquireLatch:Ljava/util/concurrent/CountDownLatch;
      20: invokevirtual #62                 // Method java/util/concurrent/CountDownLatch.countDown:()V
      23: aload_0
      24: getfield      #15                 // Field unlock:Ljava/util/concurrent/atomic/AtomicBoolean;
      27: invokevirtual #63                 // Method java/util/concurrent/atomic/AtomicBoolean.get:()Z
      30: ifne          40
      33: aload_0
      34: invokespecial #64                 // Method hasHeartbeatExpired:()Z
      37: ifeq          95
      40: aload_0
      41: getfield      #11                 // Field locked:Ljava/util/concurrent/atomic/AtomicBoolean;
      44: iconst_0
      45: invokevirtual #60                 // Method java/util/concurrent/atomic/AtomicBoolean.set:(Z)V
      48: getstatic     #43                 // Field LOG:Lorg/slf4j/Logger;
      51: new           #45                 // class java/lang/StringBuilder
      54: dup
      55: invokespecial #46                 // Method java/lang/StringBuilder."<init>":()V
      58: aload_0
      59: getfield      #15                 // Field unlock:Ljava/util/concurrent/atomic/AtomicBoolean;
      62: invokevirtual #63                 // Method java/util/concurrent/atomic/AtomicBoolean.get:()Z
      65: ifeq          73
      68: ldc           #65                 // String UNLOCKED
      70: goto          75
      73: ldc           #66                 // String TIMED OUT
      75: invokevirtual #48                 // Method java/lang/StringBuilder.append:(Ljava/lang/String;)Ljava/lang/StringBuilder;
      78: aload_0
      79: invokevirtual #49                 // Method toString:()Ljava/lang/String;
      82: invokevirtual #48                 // Method java/lang/StringBuilder.append:(Ljava/lang/String;)Ljava/lang/StringBuilder;
      85: invokevirtual #50                 // Method java/lang/StringBuilder.toString:()Ljava/lang/String;
      88: invokeinterface #51,  2           // InterfaceMethod org/slf4j/Logger.debug:(Ljava/lang/String;)V
      93: aconst_null
      94: areturn
      95: aload_0
      96: getfield      #8                  // Field event:Lorg/apache/hadoop/hbase/procedure2/ProcedureEvent;
      99: dup
     100: astore_2
     101: monitorenter
     102: aload_0
     103: getfield      #8                  // Field event:Lorg/apache/hadoop/hbase/procedure2/ProcedureEvent;
     106: invokevirtual #67                 // Method org/apache/hadoop/hbase/procedure2/ProcedureEvent.suspend:()V
     109: aload_0
     110: getfield      #8                  // Field event:Lorg/apache/hadoop/hbase/procedure2/ProcedureEvent;
     113: aload_0
     114: invokevirtual #68                 // Method org/apache/hadoop/hbase/procedure2/ProcedureEvent.suspendIfNotReady:(Lorg/apache/hadoop/hbase/procedure2/Procedure;)Z
     117: pop
     118: aload_0
     119: getstatic     #69                 // Field org/apache/hadoop/hbase/shaded/protobuf/generated/ProcedureProtos$ProcedureState.WAITING_TIMEOUT:Lorg/apache/hadoop/hbase/shaded/protobuf/generated/ProcedureProtos$ProcedureState;
     122: invokevirtual #56                 // Method setState:(Lorg/apache/hadoop/hbase/shaded/protobuf/generated/ProcedureProtos$ProcedureState;)V
     125: aload_0
     126: iconst_1
     127: putfield      #16                 // Field suspended:Z
     130: aload_2
     131: monitorexit
     132: goto          140
     135: astore_3
     136: aload_2
     137: monitorexit
     138: aload_3
     139: athrow
     140: new           #70                 // class org/apache/hadoop/hbase/procedure2/ProcedureSuspendedException
     143: dup
     144: invokespecial #71                 // Method org/apache/hadoop/hbase/procedure2/ProcedureSuspendedException."<init>":()V
     147: athrow
    Exception table:
       from    to  target type
         102   132   135   any
         135   138   135   any

  protected void rollback(org.apache.hadoop.hbase.master.procedure.MasterProcedureEnv);
    Code:
       0: new           #72                 // class java/lang/UnsupportedOperationException
       3: dup
       4: invokespecial #73                 // Method java/lang/UnsupportedOperationException."<init>":()V
       7: athrow

  protected boolean abort(org.apache.hadoop.hbase.master.procedure.MasterProcedureEnv);
    Code:
       0: aload_0
       1: aload_1
       2: invokevirtual #74                 // Method unlock:(Lorg/apache/hadoop/hbase/master/procedure/MasterProcedureEnv;)V
       5: iconst_1
       6: ireturn

  protected void serializeStateData(org.apache.hadoop.hbase.procedure2.ProcedureStateSerializer) throws java.io.IOException;
    Code:
       0: invokestatic  #75                 // Method org/apache/hadoop/hbase/shaded/protobuf/generated/LockServiceProtos$LockProcedureData.newBuilder:()Lorg/apache/hadoop/hbase/shaded/protobuf/generated/LockServiceProtos$LockProcedureData$Builder;
       3: aload_0
       4: getfield      #18                 // Field type:Lorg/apache/hadoop/hbase/procedure2/LockType;
       7: invokevirtual #76                 // Method org/apache/hadoop/hbase/procedure2/LockType.name:()Ljava/lang/String;
      10: invokestatic  #77                 // Method org/apache/hadoop/hbase/shaded/protobuf/generated/LockServiceProtos$LockType.valueOf:(Ljava/lang/String;)Lorg/apache/hadoop/hbase/shaded/protobuf/generated/LockServiceProtos$LockType;
      13: invokevirtual #78                 // Method org/apache/hadoop/hbase/shaded/protobuf/generated/LockServiceProtos$LockProcedureData$Builder.setLockType:(Lorg/apache/hadoop/hbase/shaded/protobuf/generated/LockServiceProtos$LockType;)Lorg/apache/hadoop/hbase/shaded/protobuf/generated/LockServiceProtos$LockProcedureData$Builder;
      16: aload_0
      17: getfield      #19                 // Field description:Ljava/lang/String;
      20: invokevirtual #79                 // Method org/apache/hadoop/hbase/shaded/protobuf/generated/LockServiceProtos$LockProcedureData$Builder.setDescription:(Ljava/lang/String;)Lorg/apache/hadoop/hbase/shaded/protobuf/generated/LockServiceProtos$LockProcedureData$Builder;
      23: astore_2
      24: aload_0
      25: getfield      #1                  // Field regionInfos:[Lorg/apache/hadoop/hbase/client/RegionInfo;
      28: ifnull        65
      31: iconst_0
      32: istore_3
      33: iload_3
      34: aload_0
      35: getfield      #1                  // Field regionInfos:[Lorg/apache/hadoop/hbase/client/RegionInfo;
      38: arraylength
      39: if_icmpge     62
      42: aload_2
      43: aload_0
      44: getfield      #1                  // Field regionInfos:[Lorg/apache/hadoop/hbase/client/RegionInfo;
      47: iload_3
      48: aaload
      49: invokestatic  #80                 // Method org/apache/hadoop/hbase/shaded/protobuf/ProtobufUtil.toRegionInfo:(Lorg/apache/hadoop/hbase/client/RegionInfo;)Lorg/apache/hadoop/hbase/shaded/protobuf/generated/HBaseProtos$RegionInfo;
      52: invokevirtual #81                 // Method org/apache/hadoop/hbase/shaded/protobuf/generated/LockServiceProtos$LockProcedureData$Builder.addRegionInfo:(Lorg/apache/hadoop/hbase/shaded/protobuf/generated/HBaseProtos$RegionInfo;)Lorg/apache/hadoop/hbase/shaded/protobuf/generated/LockServiceProtos$LockProcedureData$Builder;
      55: pop
      56: iinc          3, 1
      59: goto          33
      62: goto          103
      65: aload_0
      66: getfield      #2                  // Field namespace:Ljava/lang/String;
      69: ifnull        84
      72: aload_2
      73: aload_0
      74: getfield      #2                  // Field namespace:Ljava/lang/String;
      77: invokevirtual #82                 // Method org/apache/hadoop/hbase/shaded/protobuf/generated/LockServiceProtos$LockProcedureData$Builder.setNamespace:(Ljava/lang/String;)Lorg/apache/hadoop/hbase/shaded/protobuf/generated/LockServiceProtos$LockProcedureData$Builder;
      80: pop
      81: goto          103
      84: aload_0
      85: getfield      #3                  // Field tableName:Lorg/apache/hadoop/hbase/TableName;
      88: ifnull        103
      91: aload_2
      92: aload_0
      93: getfield      #3                  // Field tableName:Lorg/apache/hadoop/hbase/TableName;
      96: invokestatic  #83                 // Method org/apache/hadoop/hbase/shaded/protobuf/ProtobufUtil.toProtoTableName:(Lorg/apache/hadoop/hbase/TableName;)Lorg/apache/hadoop/hbase/shaded/protobuf/generated/HBaseProtos$TableName;
      99: invokevirtual #84                 // Method org/apache/hadoop/hbase/shaded/protobuf/generated/LockServiceProtos$LockProcedureData$Builder.setTableName:(Lorg/apache/hadoop/hbase/shaded/protobuf/generated/HBaseProtos$TableName;)Lorg/apache/hadoop/hbase/shaded/protobuf/generated/LockServiceProtos$LockProcedureData$Builder;
     102: pop
     103: aload_0
     104: getfield      #17                 // Field lockAcquireLatch:Ljava/util/concurrent/CountDownLatch;
     107: ifnull        116
     110: aload_2
     111: iconst_1
     112: invokevirtual #85                 // Method org/apache/hadoop/hbase/shaded/protobuf/generated/LockServiceProtos$LockProcedureData$Builder.setIsMasterLock:(Z)Lorg/apache/hadoop/hbase/shaded/protobuf/generated/LockServiceProtos$LockProcedureData$Builder;
     115: pop
     116: aload_1
     117: aload_2
     118: invokevirtual #86                 // Method org/apache/hadoop/hbase/shaded/protobuf/generated/LockServiceProtos$LockProcedureData$Builder.build:()Lorg/apache/hadoop/hbase/shaded/protobuf/generated/LockServiceProtos$LockProcedureData;
     121: invokeinterface #87,  2           // InterfaceMethod org/apache/hadoop/hbase/procedure2/ProcedureStateSerializer.serialize:(Lorg/apache/hbase/thirdparty/com/google/protobuf/Message;)V
     126: return

  protected void deserializeStateData(org.apache.hadoop.hbase.procedure2.ProcedureStateSerializer) throws java.io.IOException;
    Code:
       0: aload_1
       1: ldc           #88                 // class org/apache/hadoop/hbase/shaded/protobuf/generated/LockServiceProtos$LockProcedureData
       3: invokeinterface #89,  2           // InterfaceMethod org/apache/hadoop/hbase/procedure2/ProcedureStateSerializer.deserialize:(Ljava/lang/Class;)Lorg/apache/hbase/thirdparty/com/google/protobuf/Message;
       8: checkcast     #88                 // class org/apache/hadoop/hbase/shaded/protobuf/generated/LockServiceProtos$LockProcedureData
      11: astore_2
      12: aload_0
      13: aload_2
      14: invokevirtual #90                 // Method org/apache/hadoop/hbase/shaded/protobuf/generated/LockServiceProtos$LockProcedureData.getLockType:()Lorg/apache/hadoop/hbase/shaded/protobuf/generated/LockServiceProtos$LockType;
      17: invokevirtual #91                 // Method org/apache/hadoop/hbase/shaded/protobuf/generated/LockServiceProtos$LockType.name:()Ljava/lang/String;
      20: invokestatic  #92                 // Method org/apache/hadoop/hbase/procedure2/LockType.valueOf:(Ljava/lang/String;)Lorg/apache/hadoop/hbase/procedure2/LockType;
      23: putfield      #18                 // Field type:Lorg/apache/hadoop/hbase/procedure2/LockType;
      26: aload_0
      27: aload_2
      28: invokevirtual #93                 // Method org/apache/hadoop/hbase/shaded/protobuf/generated/LockServiceProtos$LockProcedureData.getDescription:()Ljava/lang/String;
      31: putfield      #19                 // Field description:Ljava/lang/String;
      34: aload_2
      35: invokevirtual #94                 // Method org/apache/hadoop/hbase/shaded/protobuf/generated/LockServiceProtos$LockProcedureData.getRegionInfoCount:()I
      38: ifle          85
      41: aload_0
      42: aload_2
      43: invokevirtual #94                 // Method org/apache/hadoop/hbase/shaded/protobuf/generated/LockServiceProtos$LockProcedureData.getRegionInfoCount:()I
      46: anewarray     #95                 // class org/apache/hadoop/hbase/client/RegionInfo
      49: putfield      #1                  // Field regionInfos:[Lorg/apache/hadoop/hbase/client/RegionInfo;
      52: iconst_0
      53: istore_3
      54: iload_3
      55: aload_2
      56: invokevirtual #94                 // Method org/apache/hadoop/hbase/shaded/protobuf/generated/LockServiceProtos$LockProcedureData.getRegionInfoCount:()I
      59: if_icmpge     82
      62: aload_0
      63: getfield      #1                  // Field regionInfos:[Lorg/apache/hadoop/hbase/client/RegionInfo;
      66: iload_3
      67: aload_2
      68: iload_3
      69: invokevirtual #96                 // Method org/apache/hadoop/hbase/shaded/protobuf/generated/LockServiceProtos$LockProcedureData.getRegionInfo:(I)Lorg/apache/hadoop/hbase/shaded/protobuf/generated/HBaseProtos$RegionInfo;
      72: invokestatic  #97                 // Method org/apache/hadoop/hbase/shaded/protobuf/ProtobufUtil.toRegionInfo:(Lorg/apache/hadoop/hbase/shaded/protobuf/generated/HBaseProtos$RegionInfo;)Lorg/apache/hadoop/hbase/client/RegionInfo;
      75: aastore
      76: iinc          3, 1
      79: goto          54
      82: goto          121
      85: aload_2
      86: invokevirtual #98                 // Method org/apache/hadoop/hbase/shaded/protobuf/generated/LockServiceProtos$LockProcedureData.hasNamespace:()Z
      89: ifeq          103
      92: aload_0
      93: aload_2
      94: invokevirtual #99                 // Method org/apache/hadoop/hbase/shaded/protobuf/generated/LockServiceProtos$LockProcedureData.getNamespace:()Ljava/lang/String;
      97: putfield      #2                  // Field namespace:Ljava/lang/String;
     100: goto          121
     103: aload_2
     104: invokevirtual #100                // Method org/apache/hadoop/hbase/shaded/protobuf/generated/LockServiceProtos$LockProcedureData.hasTableName:()Z
     107: ifeq          121
     110: aload_0
     111: aload_2
     112: invokevirtual #101                // Method org/apache/hadoop/hbase/shaded/protobuf/generated/LockServiceProtos$LockProcedureData.getTableName:()Lorg/apache/hadoop/hbase/shaded/protobuf/generated/HBaseProtos$TableName;
     115: invokestatic  #102                // Method org/apache/hadoop/hbase/shaded/protobuf/ProtobufUtil.toTableName:(Lorg/apache/hadoop/hbase/shaded/protobuf/generated/HBaseProtos$TableName;)Lorg/apache/hadoop/hbase/TableName;
     118: putfield      #3                  // Field tableName:Lorg/apache/hadoop/hbase/TableName;
     121: aload_0
     122: aload_2
     123: invokevirtual #103                // Method org/apache/hadoop/hbase/shaded/protobuf/generated/LockServiceProtos$LockProcedureData.getIsMasterLock:()Z
     126: putfield      #61                 // Field recoveredMasterLock:Z
     129: aload_0
     130: aload_0
     131: invokespecial #104                // Method setupLock:()Lorg/apache/hadoop/hbase/master/locking/LockProcedure$LockInterface;
     134: putfield      #32                 // Field lock:Lorg/apache/hadoop/hbase/master/locking/LockProcedure$LockInterface;
     137: return

  protected org.apache.hadoop.hbase.procedure2.Procedure$LockState acquireLock(org.apache.hadoop.hbase.master.procedure.MasterProcedureEnv);
    Code:
       0: aload_0
       1: getfield      #32                 // Field lock:Lorg/apache/hadoop/hbase/master/locking/LockProcedure$LockInterface;
       4: aload_1
       5: invokeinterface #105,  2          // InterfaceMethod org/apache/hadoop/hbase/master/locking/LockProcedure$LockInterface.acquireLock:(Lorg/apache/hadoop/hbase/master/procedure/MasterProcedureEnv;)Z
      10: istore_2
      11: aload_0
      12: getfield      #11                 // Field locked:Ljava/util/concurrent/atomic/AtomicBoolean;
      15: iload_2
      16: invokevirtual #60                 // Method java/util/concurrent/atomic/AtomicBoolean.set:(Z)V
      19: iload_2
      20: ifeq          78
      23: getstatic     #43                 // Field LOG:Lorg/slf4j/Logger;
      26: invokeinterface #44,  1           // InterfaceMethod org/slf4j/Logger.isDebugEnabled:()Z
      31: ifeq          64
      34: getstatic     #43                 // Field LOG:Lorg/slf4j/Logger;
      37: new           #45                 // class java/lang/StringBuilder
      40: dup
      41: invokespecial #46                 // Method java/lang/StringBuilder."<init>":()V
      44: ldc           #106                // String LOCKED
      46: invokevirtual #48                 // Method java/lang/StringBuilder.append:(Ljava/lang/String;)Ljava/lang/StringBuilder;
      49: aload_0
      50: invokevirtual #49                 // Method toString:()Ljava/lang/String;
      53: invokevirtual #48                 // Method java/lang/StringBuilder.append:(Ljava/lang/String;)Ljava/lang/StringBuilder;
      56: invokevirtual #50                 // Method java/lang/StringBuilder.toString:()Ljava/lang/String;
      59: invokeinterface #51,  2           // InterfaceMethod org/slf4j/Logger.debug:(Ljava/lang/String;)V
      64: aload_0
      65: getfield      #14                 // Field lastHeartBeat:Ljava/util/concurrent/atomic/AtomicLong;
      68: invokestatic  #39                 // Method java/lang/System.currentTimeMillis:()J
      71: invokevirtual #42                 // Method java/util/concurrent/atomic/AtomicLong.set:(J)V
      74: getstatic     #107                // Field org/apache/hadoop/hbase/procedure2/Procedure$LockState.LOCK_ACQUIRED:Lorg/apache/hadoop/hbase/procedure2/Procedure$LockState;
      77: areturn
      78: getstatic     #43                 // Field LOG:Lorg/slf4j/Logger;
      81: new           #45                 // class java/lang/StringBuilder
      84: dup
      85: invokespecial #46                 // Method java/lang/StringBuilder."<init>":()V
      88: ldc           #108                // String Failed acquire LOCK
      90: invokevirtual #48                 // Method java/lang/StringBuilder.append:(Ljava/lang/String;)Ljava/lang/StringBuilder;
      93: aload_0
      94: invokevirtual #49                 // Method toString:()Ljava/lang/String;
      97: invokevirtual #48                 // Method java/lang/StringBuilder.append:(Ljava/lang/String;)Ljava/lang/StringBuilder;
     100: ldc           #109                // String ; YIELDING
     102: invokevirtual #48                 // Method java/lang/StringBuilder.append:(Ljava/lang/String;)Ljava/lang/StringBuilder;
     105: invokevirtual #50                 // Method java/lang/StringBuilder.toString:()Ljava/lang/String;
     108: invokeinterface #110,  2          // InterfaceMethod org/slf4j/Logger.warn:(Ljava/lang/String;)V
     113: getstatic     #111                // Field org/apache/hadoop/hbase/procedure2/Procedure$LockState.LOCK_EVENT_WAIT:Lorg/apache/hadoop/hbase/procedure2/Procedure$LockState;
     116: areturn

  protected void releaseLock(org.apache.hadoop.hbase.master.procedure.MasterProcedureEnv);
    Code:
       0: aload_0
       1: getfield      #32                 // Field lock:Lorg/apache/hadoop/hbase/master/locking/LockProcedure$LockInterface;
       4: aload_1
       5: invokeinterface #112,  2          // InterfaceMethod org/apache/hadoop/hbase/master/locking/LockProcedure$LockInterface.releaseLock:(Lorg/apache/hadoop/hbase/master/procedure/MasterProcedureEnv;)V
      10: return

  protected void beforeReplay(org.apache.hadoop.hbase.master.procedure.MasterProcedureEnv);
    Code:
       0: aload_0
       1: getstatic     #55                 // Field org/apache/hadoop/hbase/shaded/protobuf/generated/ProcedureProtos$ProcedureState.RUNNABLE:Lorg/apache/hadoop/hbase/shaded/protobuf/generated/ProcedureProtos$ProcedureState;
       4: invokevirtual #56                 // Method setState:(Lorg/apache/hadoop/hbase/shaded/protobuf/generated/ProcedureProtos$ProcedureState;)V
       7: return

  protected void toStringClassDetails(java.lang.StringBuilder);
    Code:
       0: aload_0
       1: aload_1
       2: invokespecial #113                // Method org/apache/hadoop/hbase/procedure2/Procedure.toStringClassDetails:(Ljava/lang/StringBuilder;)V
       5: aload_0
       6: getfield      #1                  // Field regionInfos:[Lorg/apache/hadoop/hbase/client/RegionInfo;
       9: ifnull        66
      12: aload_1
      13: ldc           #114                // String  regions=
      15: invokevirtual #48                 // Method java/lang/StringBuilder.append:(Ljava/lang/String;)Ljava/lang/StringBuilder;
      18: pop
      19: iconst_0
      20: istore_2
      21: iload_2
      22: aload_0
      23: getfield      #1                  // Field regionInfos:[Lorg/apache/hadoop/hbase/client/RegionInfo;
      26: arraylength
      27: if_icmpge     63
      30: iload_2
      31: ifle          41
      34: aload_1
      35: ldc           #115                // String ,
      37: invokevirtual #48                 // Method java/lang/StringBuilder.append:(Ljava/lang/String;)Ljava/lang/StringBuilder;
      40: pop
      41: aload_1
      42: aload_0
      43: getfield      #1                  // Field regionInfos:[Lorg/apache/hadoop/hbase/client/RegionInfo;
      46: iload_2
      47: aaload
      48: invokeinterface #116,  1          // InterfaceMethod org/apache/hadoop/hbase/client/RegionInfo.getShortNameToLog:()Ljava/lang/String;
      53: invokevirtual #48                 // Method java/lang/StringBuilder.append:(Ljava/lang/String;)Ljava/lang/StringBuilder;
      56: pop
      57: iinc          2, 1
      60: goto          21
      63: goto          111
      66: aload_0
      67: getfield      #2                  // Field namespace:Ljava/lang/String;
      70: ifnull        90
      73: aload_1
      74: ldc           #117                // String , namespace=
      76: invokevirtual #48                 // Method java/lang/StringBuilder.append:(Ljava/lang/String;)Ljava/lang/StringBuilder;
      79: aload_0
      80: getfield      #2                  // Field namespace:Ljava/lang/String;
      83: invokevirtual #48                 // Method java/lang/StringBuilder.append:(Ljava/lang/String;)Ljava/lang/StringBuilder;
      86: pop
      87: goto          111
      90: aload_0
      91: getfield      #3                  // Field tableName:Lorg/apache/hadoop/hbase/TableName;
      94: ifnull        111
      97: aload_1
      98: ldc           #118                // String , tableName=
     100: invokevirtual #48                 // Method java/lang/StringBuilder.append:(Ljava/lang/String;)Ljava/lang/StringBuilder;
     103: aload_0
     104: getfield      #3                  // Field tableName:Lorg/apache/hadoop/hbase/TableName;
     107: invokevirtual #53                 // Method java/lang/StringBuilder.append:(Ljava/lang/Object;)Ljava/lang/StringBuilder;
     110: pop
     111: aload_1
     112: ldc           #119                // String , type=
     114: invokevirtual #48                 // Method java/lang/StringBuilder.append:(Ljava/lang/String;)Ljava/lang/StringBuilder;
     117: aload_0
     118: getfield      #18                 // Field type:Lorg/apache/hadoop/hbase/procedure2/LockType;
     121: invokevirtual #53                 // Method java/lang/StringBuilder.append:(Ljava/lang/Object;)Ljava/lang/StringBuilder;
     124: pop
     125: return

  public org.apache.hadoop.hbase.procedure2.LockType getType();
    Code:
       0: aload_0
       1: getfield      #18                 // Field type:Lorg/apache/hadoop/hbase/procedure2/LockType;
       4: areturn

  public java.lang.String getDescription();
    Code:
       0: aload_0
       1: getfield      #19                 // Field description:Ljava/lang/String;
       4: areturn

  public boolean isLocked();
    Code:
       0: aload_0
       1: getfield      #11                 // Field locked:Ljava/util/concurrent/atomic/AtomicBoolean;
       4: invokevirtual #63                 // Method java/util/concurrent/atomic/AtomicBoolean.get:()Z
       7: ireturn

  public boolean holdLock(org.apache.hadoop.hbase.master.procedure.MasterProcedureEnv);
    Code:
       0: iconst_1
       1: ireturn

  protected boolean setTimeoutFailure(java.lang.Object);
    Code:
       0: aload_0
       1: aload_1
       2: checkcast     #145                // class org/apache/hadoop/hbase/master/procedure/MasterProcedureEnv
       5: invokevirtual #146                // Method setTimeoutFailure:(Lorg/apache/hadoop/hbase/master/procedure/MasterProcedureEnv;)Z
       8: ireturn

  protected void beforeReplay(java.lang.Object);
    Code:
       0: aload_0
       1: aload_1
       2: checkcast     #145                // class org/apache/hadoop/hbase/master/procedure/MasterProcedureEnv
       5: invokevirtual #147                // Method beforeReplay:(Lorg/apache/hadoop/hbase/master/procedure/MasterProcedureEnv;)V
       8: return

  public boolean holdLock(java.lang.Object);
    Code:
       0: aload_0
       1: aload_1
       2: checkcast     #145                // class org/apache/hadoop/hbase/master/procedure/MasterProcedureEnv
       5: invokevirtual #148                // Method holdLock:(Lorg/apache/hadoop/hbase/master/procedure/MasterProcedureEnv;)Z
       8: ireturn

  protected void releaseLock(java.lang.Object);
    Code:
       0: aload_0
       1: aload_1
       2: checkcast     #145                // class org/apache/hadoop/hbase/master/procedure/MasterProcedureEnv
       5: invokevirtual #149                // Method releaseLock:(Lorg/apache/hadoop/hbase/master/procedure/MasterProcedureEnv;)V
       8: return

  protected org.apache.hadoop.hbase.procedure2.Procedure$LockState acquireLock(java.lang.Object);
    Code:
       0: aload_0
       1: aload_1
       2: checkcast     #145                // class org/apache/hadoop/hbase/master/procedure/MasterProcedureEnv
       5: invokevirtual #150                // Method acquireLock:(Lorg/apache/hadoop/hbase/master/procedure/MasterProcedureEnv;)Lorg/apache/hadoop/hbase/procedure2/Procedure$LockState;
       8: areturn

  protected boolean abort(java.lang.Object);
    Code:
       0: aload_0
       1: aload_1
       2: checkcast     #145                // class org/apache/hadoop/hbase/master/procedure/MasterProcedureEnv
       5: invokevirtual #151                // Method abort:(Lorg/apache/hadoop/hbase/master/procedure/MasterProcedureEnv;)Z
       8: ireturn

  protected void rollback(java.lang.Object) throws java.io.IOException, java.lang.InterruptedException;
    Code:
       0: aload_0
       1: aload_1
       2: checkcast     #145                // class org/apache/hadoop/hbase/master/procedure/MasterProcedureEnv
       5: invokevirtual #152                // Method rollback:(Lorg/apache/hadoop/hbase/master/procedure/MasterProcedureEnv;)V
       8: return

  protected org.apache.hadoop.hbase.procedure2.Procedure[] execute(java.lang.Object) throws org.apache.hadoop.hbase.procedure2.ProcedureYieldException, org.apache.hadoop.hbase.procedure2.ProcedureSuspendedException, java.lang.InterruptedException;
    Code:
       0: aload_0
       1: aload_1
       2: checkcast     #145                // class org/apache/hadoop/hbase/master/procedure/MasterProcedureEnv
       5: invokevirtual #153                // Method execute:(Lorg/apache/hadoop/hbase/master/procedure/MasterProcedureEnv;)[Lorg/apache/hadoop/hbase/procedure2/Procedure;
       8: areturn

  static org.apache.hadoop.hbase.TableName access$400(org.apache.hadoop.hbase.master.locking.LockProcedure);
    Code:
       0: aload_0
       1: getfield      #3                  // Field tableName:Lorg/apache/hadoop/hbase/TableName;
       4: areturn

  static java.lang.String access$500(org.apache.hadoop.hbase.master.locking.LockProcedure);
    Code:
       0: aload_0
       1: getfield      #2                  // Field namespace:Ljava/lang/String;
       4: areturn

  static org.apache.hadoop.hbase.client.RegionInfo[] access$600(org.apache.hadoop.hbase.master.locking.LockProcedure);
    Code:
       0: aload_0
       1: getfield      #1                  // Field regionInfos:[Lorg/apache/hadoop/hbase/client/RegionInfo;
       4: areturn

  static {};
    Code:
       0: ldc           #20                 // class org/apache/hadoop/hbase/master/locking/LockProcedure
       2: invokestatic  #154                // Method org/slf4j/LoggerFactory.getLogger:(Ljava/lang/Class;)Lorg/slf4j/Logger;
       5: putstatic     #43                 // Field LOG:Lorg/slf4j/Logger;
       8: return
}
