Compiled from "LogCleaner.java"
final class org.apache.hadoop.hbase.master.cleaner.LogCleaner$CleanerContext {
  final org.apache.hadoop.fs.FileStatus target;

  final java.util.concurrent.atomic.AtomicBoolean result;

  final java.util.concurrent.CountDownLatch remainingResults;

  void setResult(boolean);
    Code:
       0: aload_0
       1: getfield      #6                  // Field result:Ljava/util/concurrent/atomic/AtomicBoolean;
       4: iload_1
       5: invokevirtual #10                 // Method java/util/concurrent/atomic/AtomicBoolean.set:(Z)V
       8: aload_0
       9: getfield      #9                  // Field remainingResults:Ljava/util/concurrent/CountDownLatch;
      12: invokevirtual #11                 // Method java/util/concurrent/CountDownLatch.countDown:()V
      15: return

  boolean getResult(long);
    Code:
       0: aload_0
       1: getfield      #9                  // Field remainingResults:Ljava/util/concurrent/CountDownLatch;
       4: lload_1
       5: getstatic     #12                 // Field java/util/concurrent/TimeUnit.MILLISECONDS:Ljava/util/concurrent/TimeUnit;
       8: invokevirtual #13                 // Method java/util/concurrent/CountDownLatch.await:(JLjava/util/concurrent/TimeUnit;)Z
      11: istore_3
      12: iload_3
      13: ifne          36
      16: invokestatic  #14                 // Method org/apache/hadoop/hbase/master/cleaner/LogCleaner.access$100:()Lorg/slf4j/Logger;
      19: ldc           #15                 // String Spend too much time [{}ms] to delete old WAL file: {}
      21: lload_1
      22: invokestatic  #16                 // Method java/lang/Long.valueOf:(J)Ljava/lang/Long;
      25: aload_0
      26: getfield      #3                  // Field target:Lorg/apache/hadoop/fs/FileStatus;
      29: invokeinterface #17,  4           // InterfaceMethod org/slf4j/Logger.warn:(Ljava/lang/String;Ljava/lang/Object;Ljava/lang/Object;)V
      34: iconst_0
      35: ireturn
      36: goto          56
      39: astore_3
      40: invokestatic  #14                 // Method org/apache/hadoop/hbase/master/cleaner/LogCleaner.access$100:()Lorg/slf4j/Logger;
      43: ldc           #19                 // String Interrupted while awaiting deletion of WAL file: {}
      45: aload_0
      46: getfield      #3                  // Field target:Lorg/apache/hadoop/fs/FileStatus;
      49: invokeinterface #20,  3           // InterfaceMethod org/slf4j/Logger.warn:(Ljava/lang/String;Ljava/lang/Object;)V
      54: iconst_0
      55: ireturn
      56: aload_0
      57: getfield      #6                  // Field result:Ljava/util/concurrent/atomic/AtomicBoolean;
      60: invokevirtual #21                 // Method java/util/concurrent/atomic/AtomicBoolean.get:()Z
      63: ireturn
    Exception table:
       from    to  target type
           0    35    39   Class java/lang/InterruptedException

  org.apache.hadoop.fs.FileStatus getTargetToClean();
    Code:
       0: aload_0
       1: getfield      #3                  // Field target:Lorg/apache/hadoop/fs/FileStatus;
       4: areturn

  public java.lang.String toString();
    Code:
       0: new           #22                 // class java/lang/StringBuilder
       3: dup
       4: invokespecial #23                 // Method java/lang/StringBuilder."<init>":()V
       7: ldc           #24                 // String CleanerContext [target=
       9: invokevirtual #25                 // Method java/lang/StringBuilder.append:(Ljava/lang/String;)Ljava/lang/StringBuilder;
      12: aload_0
      13: getfield      #3                  // Field target:Lorg/apache/hadoop/fs/FileStatus;
      16: invokevirtual #26                 // Method java/lang/StringBuilder.append:(Ljava/lang/Object;)Ljava/lang/StringBuilder;
      19: ldc           #27                 // String , result=
      21: invokevirtual #25                 // Method java/lang/StringBuilder.append:(Ljava/lang/String;)Ljava/lang/StringBuilder;
      24: aload_0
      25: getfield      #6                  // Field result:Ljava/util/concurrent/atomic/AtomicBoolean;
      28: invokevirtual #26                 // Method java/lang/StringBuilder.append:(Ljava/lang/Object;)Ljava/lang/StringBuilder;
      31: ldc           #28                 // String ]
      33: invokevirtual #25                 // Method java/lang/StringBuilder.append:(Ljava/lang/String;)Ljava/lang/StringBuilder;
      36: invokevirtual #29                 // Method java/lang/StringBuilder.toString:()Ljava/lang/String;
      39: areturn

  org.apache.hadoop.hbase.master.cleaner.LogCleaner$CleanerContext(org.apache.hadoop.fs.FileStatus, org.apache.hadoop.hbase.master.cleaner.LogCleaner$1);
    Code:
       0: aload_0
       1: aload_1
       2: invokespecial #1                  // Method "<init>":(Lorg/apache/hadoop/fs/FileStatus;)V
       5: return
}
