Compiled from "LogRoller.java"
class org.apache.hadoop.hbase.regionserver.LogRoller$1 implements org.apache.hadoop.hbase.regionserver.wal.WALActionsListener {
  final org.apache.hadoop.hbase.wal.WAL val$wal;

  final org.apache.hadoop.hbase.regionserver.LogRoller this$0;

  org.apache.hadoop.hbase.regionserver.LogRoller$1(org.apache.hadoop.hbase.regionserver.LogRoller, org.apache.hadoop.hbase.wal.WAL);
    Code:
       0: aload_0
       1: aload_1
       2: putfield      #1                  // Field this$0:Lorg/apache/hadoop/hbase/regionserver/LogRoller;
       5: aload_0
       6: aload_2
       7: putfield      #2                  // Field val$wal:Lorg/apache/hadoop/hbase/wal/WAL;
      10: aload_0
      11: invokespecial #3                  // Method java/lang/Object."<init>":()V
      14: return

  public void logRollRequested(org.apache.hadoop.hbase.regionserver.wal.WALActionsListener$RollRequestReason);
    Code:
       0: aload_0
       1: getfield      #1                  // Field this$0:Lorg/apache/hadoop/hbase/regionserver/LogRoller;
       4: invokestatic  #4                  // Method org/apache/hadoop/hbase/regionserver/LogRoller.access$000:(Lorg/apache/hadoop/hbase/regionserver/LogRoller;)Ljava/util/concurrent/ConcurrentHashMap;
       7: aload_0
       8: getfield      #2                  // Field val$wal:Lorg/apache/hadoop/hbase/wal/WAL;
      11: getstatic     #5                  // Field java/lang/Boolean.TRUE:Ljava/lang/Boolean;
      14: invokevirtual #6                  // Method java/util/concurrent/ConcurrentHashMap.put:(Ljava/lang/Object;Ljava/lang/Object;)Ljava/lang/Object;
      17: pop
      18: aload_0
      19: getfield      #1                  // Field this$0:Lorg/apache/hadoop/hbase/regionserver/LogRoller;
      22: invokestatic  #7                  // Method org/apache/hadoop/hbase/regionserver/LogRoller.access$100:(Lorg/apache/hadoop/hbase/regionserver/LogRoller;)Ljava/util/concurrent/atomic/AtomicBoolean;
      25: dup
      26: astore_2
      27: monitorenter
      28: aload_0
      29: getfield      #1                  // Field this$0:Lorg/apache/hadoop/hbase/regionserver/LogRoller;
      32: invokestatic  #7                  // Method org/apache/hadoop/hbase/regionserver/LogRoller.access$100:(Lorg/apache/hadoop/hbase/regionserver/LogRoller;)Ljava/util/concurrent/atomic/AtomicBoolean;
      35: iconst_1
      36: invokevirtual #8                  // Method java/util/concurrent/atomic/AtomicBoolean.set:(Z)V
      39: aload_0
      40: getfield      #1                  // Field this$0:Lorg/apache/hadoop/hbase/regionserver/LogRoller;
      43: invokestatic  #7                  // Method org/apache/hadoop/hbase/regionserver/LogRoller.access$100:(Lorg/apache/hadoop/hbase/regionserver/LogRoller;)Ljava/util/concurrent/atomic/AtomicBoolean;
      46: invokevirtual #9                  // Method java/lang/Object.notifyAll:()V
      49: aload_2
      50: monitorexit
      51: goto          59
      54: astore_3
      55: aload_2
      56: monitorexit
      57: aload_3
      58: athrow
      59: return
    Exception table:
       from    to  target type
          28    51    54   any
          54    57    54   any
}
