Compiled from "LongTermArchivingHFileCleaner.java"
public class org.apache.hadoop.hbase.backup.example.LongTermArchivingHFileCleaner extends org.apache.hadoop.hbase.master.cleaner.BaseHFileCleanerDelegate {
  org.apache.hadoop.hbase.backup.example.TableHFileArchiveTracker archiveTracker;

  public org.apache.hadoop.hbase.backup.example.LongTermArchivingHFileCleaner();
    Code:
       0: aload_0
       1: invokespecial #1                  // Method org/apache/hadoop/hbase/master/cleaner/BaseHFileCleanerDelegate."<init>":()V
       4: return

  public boolean isFileDeletable(org.apache.hadoop.fs.FileStatus);
    Code:
       0: aload_1
       1: invokevirtual #2                  // Method org/apache/hadoop/fs/FileStatus.isDirectory:()Z
       4: ifeq          9
       7: iconst_1
       8: ireturn
       9: aload_1
      10: invokevirtual #3                  // Method org/apache/hadoop/fs/FileStatus.getPath:()Lorg/apache/hadoop/fs/Path;
      13: astore_2
      14: aload_0
      15: getfield      #4                  // Field fs:Lorg/apache/hadoop/fs/FileSystem;
      18: aload_2
      19: aconst_null
      20: invokestatic  #5                  // Method org/apache/hadoop/hbase/util/FSUtils.listStatus:(Lorg/apache/hadoop/fs/FileSystem;Lorg/apache/hadoop/fs/Path;Lorg/apache/hadoop/fs/PathFilter;)[Lorg/apache/hadoop/fs/FileStatus;
      23: astore_3
      24: aload_3
      25: ifnonnull     30
      28: iconst_1
      29: ireturn
      30: aload_2
      31: invokevirtual #6                  // Method org/apache/hadoop/fs/Path.getParent:()Lorg/apache/hadoop/fs/Path;
      34: astore        4
      36: aload         4
      38: invokevirtual #6                  // Method org/apache/hadoop/fs/Path.getParent:()Lorg/apache/hadoop/fs/Path;
      41: astore        5
      43: aload         5
      45: invokevirtual #6                  // Method org/apache/hadoop/fs/Path.getParent:()Lorg/apache/hadoop/fs/Path;
      48: astore        6
      50: aload         6
      52: invokevirtual #7                  // Method org/apache/hadoop/fs/Path.getName:()Ljava/lang/String;
      55: astore        7
      57: aload_0
      58: getfield      #8                  // Field archiveTracker:Lorg/apache/hadoop/hbase/backup/example/TableHFileArchiveTracker;
      61: aload         7
      63: invokevirtual #9                  // Method org/apache/hadoop/hbase/backup/example/TableHFileArchiveTracker.keepHFiles:(Ljava/lang/String;)Z
      66: ifne          73
      69: iconst_1
      70: goto          74
      73: iconst_0
      74: istore        8
      76: getstatic     #10                 // Field LOG:Lorg/slf4j/Logger;
      79: new           #11                 // class java/lang/StringBuilder
      82: dup
      83: invokespecial #12                 // Method java/lang/StringBuilder."<init>":()V
      86: ldc           #13                 // String Archiver says to [
      88: invokevirtual #14                 // Method java/lang/StringBuilder.append:(Ljava/lang/String;)Ljava/lang/StringBuilder;
      91: iload         8
      93: ifeq          101
      96: ldc           #15                 // String delete
      98: goto          103
     101: ldc           #16                 // String keep
     103: invokevirtual #14                 // Method java/lang/StringBuilder.append:(Ljava/lang/String;)Ljava/lang/StringBuilder;
     106: ldc           #17                 // String ] files for table:
     108: invokevirtual #14                 // Method java/lang/StringBuilder.append:(Ljava/lang/String;)Ljava/lang/StringBuilder;
     111: aload         7
     113: invokevirtual #14                 // Method java/lang/StringBuilder.append:(Ljava/lang/String;)Ljava/lang/StringBuilder;
     116: invokevirtual #18                 // Method java/lang/StringBuilder.toString:()Ljava/lang/String;
     119: invokeinterface #19,  2           // InterfaceMethod org/slf4j/Logger.debug:(Ljava/lang/String;)V
     124: iload         8
     126: ireturn
     127: astore_2
     128: getstatic     #10                 // Field LOG:Lorg/slf4j/Logger;
     131: new           #11                 // class java/lang/StringBuilder
     134: dup
     135: invokespecial #12                 // Method java/lang/StringBuilder."<init>":()V
     138: ldc           #21                 // String Failed to lookup status of:
     140: invokevirtual #14                 // Method java/lang/StringBuilder.append:(Ljava/lang/String;)Ljava/lang/StringBuilder;
     143: aload_1
     144: invokevirtual #3                  // Method org/apache/hadoop/fs/FileStatus.getPath:()Lorg/apache/hadoop/fs/Path;
     147: invokevirtual #22                 // Method java/lang/StringBuilder.append:(Ljava/lang/Object;)Ljava/lang/StringBuilder;
     150: ldc           #23                 // String , keeping it just incase.
     152: invokevirtual #14                 // Method java/lang/StringBuilder.append:(Ljava/lang/String;)Ljava/lang/StringBuilder;
     155: invokevirtual #18                 // Method java/lang/StringBuilder.toString:()Ljava/lang/String;
     158: aload_2
     159: invokeinterface #24,  3           // InterfaceMethod org/slf4j/Logger.error:(Ljava/lang/String;Ljava/lang/Throwable;)V
     164: iconst_0
     165: ireturn
    Exception table:
       from    to  target type
           0     8   127   Class java/io/IOException
           9    29   127   Class java/io/IOException
          30   126   127   Class java/io/IOException

  public void setConf(org.apache.hadoop.conf.Configuration);
    Code:
       0: new           #25                 // class org/apache/hadoop/conf/Configuration
       3: dup
       4: aload_1
       5: invokespecial #26                 // Method org/apache/hadoop/conf/Configuration."<init>":(Lorg/apache/hadoop/conf/Configuration;)V
       8: astore_2
       9: aload_0
      10: aload_2
      11: invokespecial #27                 // Method org/apache/hadoop/hbase/master/cleaner/BaseHFileCleanerDelegate.setConf:(Lorg/apache/hadoop/conf/Configuration;)V
      14: aload_0
      15: aload_2
      16: invokestatic  #28                 // Method org/apache/hadoop/fs/FileSystem.get:(Lorg/apache/hadoop/conf/Configuration;)Lorg/apache/hadoop/fs/FileSystem;
      19: putfield      #4                  // Field fs:Lorg/apache/hadoop/fs/FileSystem;
      22: aload_0
      23: aload_2
      24: invokestatic  #29                 // Method org/apache/hadoop/hbase/backup/example/TableHFileArchiveTracker.create:(Lorg/apache/hadoop/conf/Configuration;)Lorg/apache/hadoop/hbase/backup/example/TableHFileArchiveTracker;
      27: putfield      #8                  // Field archiveTracker:Lorg/apache/hadoop/hbase/backup/example/TableHFileArchiveTracker;
      30: aload_0
      31: getfield      #8                  // Field archiveTracker:Lorg/apache/hadoop/hbase/backup/example/TableHFileArchiveTracker;
      34: invokevirtual #30                 // Method org/apache/hadoop/hbase/backup/example/TableHFileArchiveTracker.start:()V
      37: goto          113
      40: astore_3
      41: getstatic     #10                 // Field LOG:Lorg/slf4j/Logger;
      44: new           #11                 // class java/lang/StringBuilder
      47: dup
      48: invokespecial #12                 // Method java/lang/StringBuilder."<init>":()V
      51: ldc           #32                 // String Error while configuring
      53: invokevirtual #14                 // Method java/lang/StringBuilder.append:(Ljava/lang/String;)Ljava/lang/StringBuilder;
      56: aload_0
      57: invokevirtual #33                 // Method java/lang/Object.getClass:()Ljava/lang/Class;
      60: invokevirtual #34                 // Method java/lang/Class.getName:()Ljava/lang/String;
      63: invokevirtual #14                 // Method java/lang/StringBuilder.append:(Ljava/lang/String;)Ljava/lang/StringBuilder;
      66: invokevirtual #18                 // Method java/lang/StringBuilder.toString:()Ljava/lang/String;
      69: aload_3
      70: invokeinterface #24,  3           // InterfaceMethod org/slf4j/Logger.error:(Ljava/lang/String;Ljava/lang/Throwable;)V
      75: goto          113
      78: astore_3
      79: getstatic     #10                 // Field LOG:Lorg/slf4j/Logger;
      82: new           #11                 // class java/lang/StringBuilder
      85: dup
      86: invokespecial #12                 // Method java/lang/StringBuilder."<init>":()V
      89: ldc           #32                 // String Error while configuring
      91: invokevirtual #14                 // Method java/lang/StringBuilder.append:(Ljava/lang/String;)Ljava/lang/StringBuilder;
      94: aload_0
      95: invokevirtual #33                 // Method java/lang/Object.getClass:()Ljava/lang/Class;
      98: invokevirtual #34                 // Method java/lang/Class.getName:()Ljava/lang/String;
     101: invokevirtual #14                 // Method java/lang/StringBuilder.append:(Ljava/lang/String;)Ljava/lang/StringBuilder;
     104: invokevirtual #18                 // Method java/lang/StringBuilder.toString:()Ljava/lang/String;
     107: aload_3
     108: invokeinterface #24,  3           // InterfaceMethod org/slf4j/Logger.error:(Ljava/lang/String;Ljava/lang/Throwable;)V
     113: return
    Exception table:
       from    to  target type
          14    37    40   Class org/apache/zookeeper/KeeperException
          14    37    78   Class java/io/IOException

  public void stop(java.lang.String);
    Code:
       0: aload_0
       1: invokevirtual #35                 // Method isStopped:()Z
       4: ifeq          8
       7: return
       8: aload_0
       9: aload_1
      10: invokespecial #36                 // Method org/apache/hadoop/hbase/master/cleaner/BaseHFileCleanerDelegate.stop:(Ljava/lang/String;)V
      13: aload_0
      14: getfield      #8                  // Field archiveTracker:Lorg/apache/hadoop/hbase/backup/example/TableHFileArchiveTracker;
      17: ifnull        57
      20: getstatic     #10                 // Field LOG:Lorg/slf4j/Logger;
      23: new           #11                 // class java/lang/StringBuilder
      26: dup
      27: invokespecial #12                 // Method java/lang/StringBuilder."<init>":()V
      30: ldc           #37                 // String Stopping
      32: invokevirtual #14                 // Method java/lang/StringBuilder.append:(Ljava/lang/String;)Ljava/lang/StringBuilder;
      35: aload_0
      36: getfield      #8                  // Field archiveTracker:Lorg/apache/hadoop/hbase/backup/example/TableHFileArchiveTracker;
      39: invokevirtual #22                 // Method java/lang/StringBuilder.append:(Ljava/lang/Object;)Ljava/lang/StringBuilder;
      42: invokevirtual #18                 // Method java/lang/StringBuilder.toString:()Ljava/lang/String;
      45: invokeinterface #38,  2           // InterfaceMethod org/slf4j/Logger.info:(Ljava/lang/String;)V
      50: aload_0
      51: getfield      #8                  // Field archiveTracker:Lorg/apache/hadoop/hbase/backup/example/TableHFileArchiveTracker;
      54: invokevirtual #39                 // Method org/apache/hadoop/hbase/backup/example/TableHFileArchiveTracker.stop:()V
      57: return

  static {};
    Code:
       0: ldc           #40                 // class org/apache/hadoop/hbase/backup/example/LongTermArchivingHFileCleaner
       2: invokestatic  #41                 // Method org/slf4j/LoggerFactory.getLogger:(Ljava/lang/Class;)Lorg/slf4j/Logger;
       5: putstatic     #10                 // Field LOG:Lorg/slf4j/Logger;
       8: return
}
