Compiled from "MajorCompactor.java"
class org.apache.hadoop.hbase.util.compaction.MajorCompactor$Compact implements java.lang.Runnable {
  final org.apache.hadoop.hbase.util.compaction.MajorCompactor this$0;

  org.apache.hadoop.hbase.util.compaction.MajorCompactor$Compact(org.apache.hadoop.hbase.util.compaction.MajorCompactor, org.apache.hadoop.hbase.ServerName, org.apache.hadoop.hbase.util.compaction.MajorCompactionRequest);
    Code:
       0: aload_0
       1: aload_1
       2: putfield      #1                  // Field this$0:Lorg/apache/hadoop/hbase/util/compaction/MajorCompactor;
       5: aload_0
       6: invokespecial #2                  // Method java/lang/Object."<init>":()V
       9: aload_0
      10: aload_2
      11: putfield      #3                  // Field serverName:Lorg/apache/hadoop/hbase/ServerName;
      14: aload_0
      15: aload_3
      16: putfield      #4                  // Field request:Lorg/apache/hadoop/hbase/util/compaction/MajorCompactionRequest;
      19: return

  public void run();
    Code:
       0: aload_0
       1: aload_0
       2: getfield      #4                  // Field request:Lorg/apache/hadoop/hbase/util/compaction/MajorCompactionRequest;
       5: invokevirtual #5                  // Method compactAndWait:(Lorg/apache/hadoop/hbase/util/compaction/MajorCompactionRequest;)V
       8: aload_0
       9: getfield      #1                  // Field this$0:Lorg/apache/hadoop/hbase/util/compaction/MajorCompactor;
      12: getfield      #6                  // Field org/apache/hadoop/hbase/util/compaction/MajorCompactor.clusterCompactionQueues:Lorg/apache/hadoop/hbase/util/compaction/ClusterCompactionQueues;
      15: aload_0
      16: getfield      #3                  // Field serverName:Lorg/apache/hadoop/hbase/ServerName;
      19: invokevirtual #7                  // Method org/apache/hadoop/hbase/util/compaction/ClusterCompactionQueues.releaseCompaction:(Lorg/apache/hadoop/hbase/ServerName;)V
      22: goto          107
      25: astore_1
      26: invokestatic  #9                  // Method org/apache/hadoop/hbase/util/compaction/MajorCompactor.access$000:()Lorg/slf4j/Logger;
      29: ldc           #10                 // String Region is invalid, requesting updated regions
      31: aload_1
      32: invokeinterface #11,  3           // InterfaceMethod org/slf4j/Logger.warn:(Ljava/lang/String;Ljava/lang/Throwable;)V
      37: aload_0
      38: getfield      #1                  // Field this$0:Lorg/apache/hadoop/hbase/util/compaction/MajorCompactor;
      41: invokestatic  #12                 // Method org/apache/hadoop/hbase/util/compaction/MajorCompactor.access$100:(Lorg/apache/hadoop/hbase/util/compaction/MajorCompactor;)V
      44: aload_0
      45: getfield      #1                  // Field this$0:Lorg/apache/hadoop/hbase/util/compaction/MajorCompactor;
      48: getfield      #6                  // Field org/apache/hadoop/hbase/util/compaction/MajorCompactor.clusterCompactionQueues:Lorg/apache/hadoop/hbase/util/compaction/ClusterCompactionQueues;
      51: aload_0
      52: getfield      #3                  // Field serverName:Lorg/apache/hadoop/hbase/ServerName;
      55: invokevirtual #7                  // Method org/apache/hadoop/hbase/util/compaction/ClusterCompactionQueues.releaseCompaction:(Lorg/apache/hadoop/hbase/ServerName;)V
      58: goto          107
      61: astore_1
      62: invokestatic  #9                  // Method org/apache/hadoop/hbase/util/compaction/MajorCompactor.access$000:()Lorg/slf4j/Logger;
      65: ldc           #14                 // String Error compacting:
      67: aload_1
      68: invokeinterface #11,  3           // InterfaceMethod org/slf4j/Logger.warn:(Ljava/lang/String;Ljava/lang/Throwable;)V
      73: aload_0
      74: getfield      #1                  // Field this$0:Lorg/apache/hadoop/hbase/util/compaction/MajorCompactor;
      77: getfield      #6                  // Field org/apache/hadoop/hbase/util/compaction/MajorCompactor.clusterCompactionQueues:Lorg/apache/hadoop/hbase/util/compaction/ClusterCompactionQueues;
      80: aload_0
      81: getfield      #3                  // Field serverName:Lorg/apache/hadoop/hbase/ServerName;
      84: invokevirtual #7                  // Method org/apache/hadoop/hbase/util/compaction/ClusterCompactionQueues.releaseCompaction:(Lorg/apache/hadoop/hbase/ServerName;)V
      87: goto          107
      90: astore_2
      91: aload_0
      92: getfield      #1                  // Field this$0:Lorg/apache/hadoop/hbase/util/compaction/MajorCompactor;
      95: getfield      #6                  // Field org/apache/hadoop/hbase/util/compaction/MajorCompactor.clusterCompactionQueues:Lorg/apache/hadoop/hbase/util/compaction/ClusterCompactionQueues;
      98: aload_0
      99: getfield      #3                  // Field serverName:Lorg/apache/hadoop/hbase/ServerName;
     102: invokevirtual #7                  // Method org/apache/hadoop/hbase/util/compaction/ClusterCompactionQueues.releaseCompaction:(Lorg/apache/hadoop/hbase/ServerName;)V
     105: aload_2
     106: athrow
     107: return
    Exception table:
       from    to  target type
           0     8    25   Class org/apache/hadoop/hbase/NotServingRegionException
           0     8    61   Class java/lang/Exception
           0     8    90   any
          25    44    90   any
          61    73    90   any

  void compactAndWait(org.apache.hadoop.hbase.util.compaction.MajorCompactionRequest) throws java.lang.Exception;
    Code:
       0: aload_0
       1: getfield      #1                  // Field this$0:Lorg/apache/hadoop/hbase/util/compaction/MajorCompactor;
       4: getfield      #15                 // Field org/apache/hadoop/hbase/util/compaction/MajorCompactor.connection:Lorg/apache/hadoop/hbase/client/Connection;
       7: invokeinterface #16,  1           // InterfaceMethod org/apache/hadoop/hbase/client/Connection.getAdmin:()Lorg/apache/hadoop/hbase/client/Admin;
      12: astore_2
      13: aload_0
      14: getfield      #1                  // Field this$0:Lorg/apache/hadoop/hbase/util/compaction/MajorCompactor;
      17: aload_1
      18: invokestatic  #17                 // Method org/apache/hadoop/hbase/util/compaction/MajorCompactor.access$200:(Lorg/apache/hadoop/hbase/util/compaction/MajorCompactor;Lorg/apache/hadoop/hbase/util/compaction/MajorCompactionRequest;)Z
      21: ifne          91
      24: aload_0
      25: getfield      #1                  // Field this$0:Lorg/apache/hadoop/hbase/util/compaction/MajorCompactor;
      28: aload_1
      29: invokevirtual #18                 // Method org/apache/hadoop/hbase/util/compaction/MajorCompactor.getStoresRequiringCompaction:(Lorg/apache/hadoop/hbase/util/compaction/MajorCompactionRequest;)Ljava/util/Set;
      32: astore_3
      33: aload_3
      34: invokeinterface #19,  1           // InterfaceMethod java/util/Set.isEmpty:()Z
      39: ifne          91
      42: aload_1
      43: aload_3
      44: invokevirtual #20                 // Method org/apache/hadoop/hbase/util/compaction/MajorCompactionRequest.setStores:(Ljava/util/Set;)V
      47: aload_1
      48: invokevirtual #21                 // Method org/apache/hadoop/hbase/util/compaction/MajorCompactionRequest.getStores:()Ljava/util/Set;
      51: invokeinterface #22,  1           // InterfaceMethod java/util/Set.iterator:()Ljava/util/Iterator;
      56: astore        4
      58: aload         4
      60: invokeinterface #23,  1           // InterfaceMethod java/util/Iterator.hasNext:()Z
      65: ifeq          91
      68: aload         4
      70: invokeinterface #24,  1           // InterfaceMethod java/util/Iterator.next:()Ljava/lang/Object;
      75: checkcast     #25                 // class java/lang/String
      78: astore        5
      80: aload_0
      81: aload_1
      82: aload_2
      83: aload         5
      85: invokespecial #26                 // Method compactRegionOnServer:(Lorg/apache/hadoop/hbase/util/compaction/MajorCompactionRequest;Lorg/apache/hadoop/hbase/client/Admin;Ljava/lang/String;)V
      88: goto          58
      91: aload_0
      92: getfield      #1                  // Field this$0:Lorg/apache/hadoop/hbase/util/compaction/MajorCompactor;
      95: invokestatic  #27                 // Method org/apache/hadoop/hbase/util/compaction/MajorCompactor.access$300:(Lorg/apache/hadoop/hbase/util/compaction/MajorCompactor;)Z
      98: ifne          160
     101: aload_0
     102: getfield      #1                  // Field this$0:Lorg/apache/hadoop/hbase/util/compaction/MajorCompactor;
     105: aload_1
     106: invokestatic  #17                 // Method org/apache/hadoop/hbase/util/compaction/MajorCompactor.access$200:(Lorg/apache/hadoop/hbase/util/compaction/MajorCompactor;Lorg/apache/hadoop/hbase/util/compaction/MajorCompactionRequest;)Z
     109: ifeq          160
     112: aload_0
     113: getfield      #1                  // Field this$0:Lorg/apache/hadoop/hbase/util/compaction/MajorCompactor;
     116: getfield      #28                 // Field org/apache/hadoop/hbase/util/compaction/MajorCompactor.sleepForMs:J
     119: invokestatic  #29                 // Method java/lang/Thread.sleep:(J)V
     122: invokestatic  #9                  // Method org/apache/hadoop/hbase/util/compaction/MajorCompactor.access$000:()Lorg/slf4j/Logger;
     125: new           #30                 // class java/lang/StringBuilder
     128: dup
     129: invokespecial #31                 // Method java/lang/StringBuilder."<init>":()V
     132: ldc           #32                 // String Waiting for compaction to complete for region:
     134: invokevirtual #33                 // Method java/lang/StringBuilder.append:(Ljava/lang/String;)Ljava/lang/StringBuilder;
     137: aload_1
     138: invokevirtual #34                 // Method org/apache/hadoop/hbase/util/compaction/MajorCompactionRequest.getRegion:()Lorg/apache/hadoop/hbase/client/RegionInfo;
     141: invokeinterface #35,  1           // InterfaceMethod org/apache/hadoop/hbase/client/RegionInfo.getEncodedName:()Ljava/lang/String;
     146: invokevirtual #33                 // Method java/lang/StringBuilder.append:(Ljava/lang/String;)Ljava/lang/StringBuilder;
     149: invokevirtual #36                 // Method java/lang/StringBuilder.toString:()Ljava/lang/String;
     152: invokeinterface #37,  2           // InterfaceMethod org/slf4j/Logger.debug:(Ljava/lang/String;)V
     157: goto          101
     160: aload_0
     161: getfield      #1                  // Field this$0:Lorg/apache/hadoop/hbase/util/compaction/MajorCompactor;
     164: invokestatic  #27                 // Method org/apache/hadoop/hbase/util/compaction/MajorCompactor.access$300:(Lorg/apache/hadoop/hbase/util/compaction/MajorCompactor;)Z
     167: ifne          692
     170: aload_0
     171: getfield      #1                  // Field this$0:Lorg/apache/hadoop/hbase/util/compaction/MajorCompactor;
     174: getfield      #15                 // Field org/apache/hadoop/hbase/util/compaction/MajorCompactor.connection:Lorg/apache/hadoop/hbase/client/Connection;
     177: invokeinterface #38,  1           // InterfaceMethod org/apache/hadoop/hbase/client/Connection.getConfiguration:()Lorg/apache/hadoop/conf/Configuration;
     182: ldc           #39                 // String hbase.hfile.compaction.discharger.interval
     184: ldc           #40                 // int 120000
     186: invokevirtual #41                 // Method org/apache/hadoop/conf/Configuration.getInt:(Ljava/lang/String;I)I
     189: istore_3
     190: iload_3
     191: i2l
     192: invokestatic  #29                 // Method java/lang/Thread.sleep:(J)V
     195: aload_0
     196: getfield      #1                  // Field this$0:Lorg/apache/hadoop/hbase/util/compaction/MajorCompactor;
     199: aload_1
     200: invokevirtual #18                 // Method org/apache/hadoop/hbase/util/compaction/MajorCompactor.getStoresRequiringCompaction:(Lorg/apache/hadoop/hbase/util/compaction/MajorCompactionRequest;)Ljava/util/Set;
     203: astore        4
     205: aload         4
     207: invokeinterface #19,  1           // InterfaceMethod java/util/Set.isEmpty:()Z
     212: ifne          374
     215: aload_0
     216: getfield      #1                  // Field this$0:Lorg/apache/hadoop/hbase/util/compaction/MajorCompactor;
     219: getfield      #15                 // Field org/apache/hadoop/hbase/util/compaction/MajorCompactor.connection:Lorg/apache/hadoop/hbase/client/Connection;
     222: aload_0
     223: getfield      #1                  // Field this$0:Lorg/apache/hadoop/hbase/util/compaction/MajorCompactor;
     226: getfield      #42                 // Field org/apache/hadoop/hbase/util/compaction/MajorCompactor.tableName:Lorg/apache/hadoop/hbase/TableName;
     229: invokeinterface #43,  2           // InterfaceMethod org/apache/hadoop/hbase/client/Connection.getRegionLocator:(Lorg/apache/hadoop/hbase/TableName;)Lorg/apache/hadoop/hbase/client/RegionLocator;
     234: aload_1
     235: invokevirtual #34                 // Method org/apache/hadoop/hbase/util/compaction/MajorCompactionRequest.getRegion:()Lorg/apache/hadoop/hbase/client/RegionInfo;
     238: invokeinterface #44,  1           // InterfaceMethod org/apache/hadoop/hbase/client/RegionInfo.getStartKey:()[B
     243: invokeinterface #45,  2           // InterfaceMethod org/apache/hadoop/hbase/client/RegionLocator.getRegionLocation:([B)Lorg/apache/hadoop/hbase/HRegionLocation;
     248: invokevirtual #46                 // Method org/apache/hadoop/hbase/HRegionLocation.getServerName:()Lorg/apache/hadoop/hbase/ServerName;
     251: aload_0
     252: getfield      #3                  // Field serverName:Lorg/apache/hadoop/hbase/ServerName;
     255: invokevirtual #47                 // Method org/apache/hadoop/hbase/ServerName.equals:(Ljava/lang/Object;)Z
     258: istore        5
     260: iload         5
     262: ifeq          305
     265: invokestatic  #9                  // Method org/apache/hadoop/hbase/util/compaction/MajorCompactor.access$000:()Lorg/slf4j/Logger;
     268: new           #30                 // class java/lang/StringBuilder
     271: dup
     272: invokespecial #31                 // Method java/lang/StringBuilder."<init>":()V
     275: ldc           #48                 // String Not all store files were compacted, this may be due to the regionserver not being aware of all store files.  Will not reattempt compacting,
     277: invokevirtual #33                 // Method java/lang/StringBuilder.append:(Ljava/lang/String;)Ljava/lang/StringBuilder;
     280: aload_1
     281: invokevirtual #49                 // Method java/lang/StringBuilder.append:(Ljava/lang/Object;)Ljava/lang/StringBuilder;
     284: invokevirtual #36                 // Method java/lang/StringBuilder.toString:()Ljava/lang/String;
     287: invokeinterface #50,  2           // InterfaceMethod org/slf4j/Logger.error:(Ljava/lang/String;)V
     292: getstatic     #51                 // Field org/apache/hadoop/hbase/util/compaction/MajorCompactor.ERRORS:Ljava/util/Set;
     295: aload_1
     296: invokeinterface #52,  2           // InterfaceMethod java/util/Set.add:(Ljava/lang/Object;)Z
     301: pop
     302: goto          371
     305: aload_1
     306: aload         4
     308: invokevirtual #20                 // Method org/apache/hadoop/hbase/util/compaction/MajorCompactionRequest.setStores:(Ljava/util/Set;)V
     311: aload_0
     312: getfield      #1                  // Field this$0:Lorg/apache/hadoop/hbase/util/compaction/MajorCompactor;
     315: getfield      #6                  // Field org/apache/hadoop/hbase/util/compaction/MajorCompactor.clusterCompactionQueues:Lorg/apache/hadoop/hbase/util/compaction/ClusterCompactionQueues;
     318: aload_0
     319: getfield      #3                  // Field serverName:Lorg/apache/hadoop/hbase/ServerName;
     322: aload_1
     323: invokevirtual #53                 // Method org/apache/hadoop/hbase/util/compaction/ClusterCompactionQueues.addToCompactionQueue:(Lorg/apache/hadoop/hbase/ServerName;Lorg/apache/hadoop/hbase/util/compaction/MajorCompactionRequest;)V
     326: invokestatic  #9                  // Method org/apache/hadoop/hbase/util/compaction/MajorCompactor.access$000:()Lorg/slf4j/Logger;
     329: new           #30                 // class java/lang/StringBuilder
     332: dup
     333: invokespecial #31                 // Method java/lang/StringBuilder."<init>":()V
     336: ldc           #54                 // String Compaction failed for the following stores:
     338: invokevirtual #33                 // Method java/lang/StringBuilder.append:(Ljava/lang/String;)Ljava/lang/StringBuilder;
     341: aload         4
     343: invokevirtual #49                 // Method java/lang/StringBuilder.append:(Ljava/lang/Object;)Ljava/lang/StringBuilder;
     346: ldc           #55                 // String  region:
     348: invokevirtual #33                 // Method java/lang/StringBuilder.append:(Ljava/lang/String;)Ljava/lang/StringBuilder;
     351: aload_1
     352: invokevirtual #34                 // Method org/apache/hadoop/hbase/util/compaction/MajorCompactionRequest.getRegion:()Lorg/apache/hadoop/hbase/client/RegionInfo;
     355: invokeinterface #35,  1           // InterfaceMethod org/apache/hadoop/hbase/client/RegionInfo.getEncodedName:()Ljava/lang/String;
     360: invokevirtual #33                 // Method java/lang/StringBuilder.append:(Ljava/lang/String;)Ljava/lang/StringBuilder;
     363: invokevirtual #36                 // Method java/lang/StringBuilder.toString:()Ljava/lang/String;
     366: invokeinterface #56,  2           // InterfaceMethod org/slf4j/Logger.info:(Ljava/lang/String;)V
     371: goto          421
     374: invokestatic  #9                  // Method org/apache/hadoop/hbase/util/compaction/MajorCompactor.access$000:()Lorg/slf4j/Logger;
     377: new           #30                 // class java/lang/StringBuilder
     380: dup
     381: invokespecial #31                 // Method java/lang/StringBuilder."<init>":()V
     384: ldc           #57                 // String Compaction complete for region:
     386: invokevirtual #33                 // Method java/lang/StringBuilder.append:(Ljava/lang/String;)Ljava/lang/StringBuilder;
     389: aload_1
     390: invokevirtual #34                 // Method org/apache/hadoop/hbase/util/compaction/MajorCompactionRequest.getRegion:()Lorg/apache/hadoop/hbase/client/RegionInfo;
     393: invokeinterface #35,  1           // InterfaceMethod org/apache/hadoop/hbase/client/RegionInfo.getEncodedName:()Ljava/lang/String;
     398: invokevirtual #33                 // Method java/lang/StringBuilder.append:(Ljava/lang/String;)Ljava/lang/StringBuilder;
     401: ldc           #58                 // String  -> cf(s):
     403: invokevirtual #33                 // Method java/lang/StringBuilder.append:(Ljava/lang/String;)Ljava/lang/StringBuilder;
     406: aload_1
     407: invokevirtual #21                 // Method org/apache/hadoop/hbase/util/compaction/MajorCompactionRequest.getStores:()Ljava/util/Set;
     410: invokevirtual #49                 // Method java/lang/StringBuilder.append:(Ljava/lang/Object;)Ljava/lang/StringBuilder;
     413: invokevirtual #36                 // Method java/lang/StringBuilder.toString:()Ljava/lang/String;
     416: invokeinterface #56,  2           // InterfaceMethod org/slf4j/Logger.info:(Ljava/lang/String;)V
     421: goto          692
     424: astore        6
     426: aload_0
     427: getfield      #1                  // Field this$0:Lorg/apache/hadoop/hbase/util/compaction/MajorCompactor;
     430: invokestatic  #27                 // Method org/apache/hadoop/hbase/util/compaction/MajorCompactor.access$300:(Lorg/apache/hadoop/hbase/util/compaction/MajorCompactor;)Z
     433: ifne          689
     436: aload_0
     437: getfield      #1                  // Field this$0:Lorg/apache/hadoop/hbase/util/compaction/MajorCompactor;
     440: getfield      #15                 // Field org/apache/hadoop/hbase/util/compaction/MajorCompactor.connection:Lorg/apache/hadoop/hbase/client/Connection;
     443: invokeinterface #38,  1           // InterfaceMethod org/apache/hadoop/hbase/client/Connection.getConfiguration:()Lorg/apache/hadoop/conf/Configuration;
     448: ldc           #39                 // String hbase.hfile.compaction.discharger.interval
     450: ldc           #40                 // int 120000
     452: invokevirtual #41                 // Method org/apache/hadoop/conf/Configuration.getInt:(Ljava/lang/String;I)I
     455: istore        7
     457: iload         7
     459: i2l
     460: invokestatic  #29                 // Method java/lang/Thread.sleep:(J)V
     463: aload_0
     464: getfield      #1                  // Field this$0:Lorg/apache/hadoop/hbase/util/compaction/MajorCompactor;
     467: aload_1
     468: invokevirtual #18                 // Method org/apache/hadoop/hbase/util/compaction/MajorCompactor.getStoresRequiringCompaction:(Lorg/apache/hadoop/hbase/util/compaction/MajorCompactionRequest;)Ljava/util/Set;
     471: astore        8
     473: aload         8
     475: invokeinterface #19,  1           // InterfaceMethod java/util/Set.isEmpty:()Z
     480: ifne          642
     483: aload_0
     484: getfield      #1                  // Field this$0:Lorg/apache/hadoop/hbase/util/compaction/MajorCompactor;
     487: getfield      #15                 // Field org/apache/hadoop/hbase/util/compaction/MajorCompactor.connection:Lorg/apache/hadoop/hbase/client/Connection;
     490: aload_0
     491: getfield      #1                  // Field this$0:Lorg/apache/hadoop/hbase/util/compaction/MajorCompactor;
     494: getfield      #42                 // Field org/apache/hadoop/hbase/util/compaction/MajorCompactor.tableName:Lorg/apache/hadoop/hbase/TableName;
     497: invokeinterface #43,  2           // InterfaceMethod org/apache/hadoop/hbase/client/Connection.getRegionLocator:(Lorg/apache/hadoop/hbase/TableName;)Lorg/apache/hadoop/hbase/client/RegionLocator;
     502: aload_1
     503: invokevirtual #34                 // Method org/apache/hadoop/hbase/util/compaction/MajorCompactionRequest.getRegion:()Lorg/apache/hadoop/hbase/client/RegionInfo;
     506: invokeinterface #44,  1           // InterfaceMethod org/apache/hadoop/hbase/client/RegionInfo.getStartKey:()[B
     511: invokeinterface #45,  2           // InterfaceMethod org/apache/hadoop/hbase/client/RegionLocator.getRegionLocation:([B)Lorg/apache/hadoop/hbase/HRegionLocation;
     516: invokevirtual #46                 // Method org/apache/hadoop/hbase/HRegionLocation.getServerName:()Lorg/apache/hadoop/hbase/ServerName;
     519: aload_0
     520: getfield      #3                  // Field serverName:Lorg/apache/hadoop/hbase/ServerName;
     523: invokevirtual #47                 // Method org/apache/hadoop/hbase/ServerName.equals:(Ljava/lang/Object;)Z
     526: istore        9
     528: iload         9
     530: ifeq          573
     533: invokestatic  #9                  // Method org/apache/hadoop/hbase/util/compaction/MajorCompactor.access$000:()Lorg/slf4j/Logger;
     536: new           #30                 // class java/lang/StringBuilder
     539: dup
     540: invokespecial #31                 // Method java/lang/StringBuilder."<init>":()V
     543: ldc           #48                 // String Not all store files were compacted, this may be due to the regionserver not being aware of all store files.  Will not reattempt compacting,
     545: invokevirtual #33                 // Method java/lang/StringBuilder.append:(Ljava/lang/String;)Ljava/lang/StringBuilder;
     548: aload_1
     549: invokevirtual #49                 // Method java/lang/StringBuilder.append:(Ljava/lang/Object;)Ljava/lang/StringBuilder;
     552: invokevirtual #36                 // Method java/lang/StringBuilder.toString:()Ljava/lang/String;
     555: invokeinterface #50,  2           // InterfaceMethod org/slf4j/Logger.error:(Ljava/lang/String;)V
     560: getstatic     #51                 // Field org/apache/hadoop/hbase/util/compaction/MajorCompactor.ERRORS:Ljava/util/Set;
     563: aload_1
     564: invokeinterface #52,  2           // InterfaceMethod java/util/Set.add:(Ljava/lang/Object;)Z
     569: pop
     570: goto          639
     573: aload_1
     574: aload         8
     576: invokevirtual #20                 // Method org/apache/hadoop/hbase/util/compaction/MajorCompactionRequest.setStores:(Ljava/util/Set;)V
     579: aload_0
     580: getfield      #1                  // Field this$0:Lorg/apache/hadoop/hbase/util/compaction/MajorCompactor;
     583: getfield      #6                  // Field org/apache/hadoop/hbase/util/compaction/MajorCompactor.clusterCompactionQueues:Lorg/apache/hadoop/hbase/util/compaction/ClusterCompactionQueues;
     586: aload_0
     587: getfield      #3                  // Field serverName:Lorg/apache/hadoop/hbase/ServerName;
     590: aload_1
     591: invokevirtual #53                 // Method org/apache/hadoop/hbase/util/compaction/ClusterCompactionQueues.addToCompactionQueue:(Lorg/apache/hadoop/hbase/ServerName;Lorg/apache/hadoop/hbase/util/compaction/MajorCompactionRequest;)V
     594: invokestatic  #9                  // Method org/apache/hadoop/hbase/util/compaction/MajorCompactor.access$000:()Lorg/slf4j/Logger;
     597: new           #30                 // class java/lang/StringBuilder
     600: dup
     601: invokespecial #31                 // Method java/lang/StringBuilder."<init>":()V
     604: ldc           #54                 // String Compaction failed for the following stores:
     606: invokevirtual #33                 // Method java/lang/StringBuilder.append:(Ljava/lang/String;)Ljava/lang/StringBuilder;
     609: aload         8
     611: invokevirtual #49                 // Method java/lang/StringBuilder.append:(Ljava/lang/Object;)Ljava/lang/StringBuilder;
     614: ldc           #55                 // String  region:
     616: invokevirtual #33                 // Method java/lang/StringBuilder.append:(Ljava/lang/String;)Ljava/lang/StringBuilder;
     619: aload_1
     620: invokevirtual #34                 // Method org/apache/hadoop/hbase/util/compaction/MajorCompactionRequest.getRegion:()Lorg/apache/hadoop/hbase/client/RegionInfo;
     623: invokeinterface #35,  1           // InterfaceMethod org/apache/hadoop/hbase/client/RegionInfo.getEncodedName:()Ljava/lang/String;
     628: invokevirtual #33                 // Method java/lang/StringBuilder.append:(Ljava/lang/String;)Ljava/lang/StringBuilder;
     631: invokevirtual #36                 // Method java/lang/StringBuilder.toString:()Ljava/lang/String;
     634: invokeinterface #56,  2           // InterfaceMethod org/slf4j/Logger.info:(Ljava/lang/String;)V
     639: goto          689
     642: invokestatic  #9                  // Method org/apache/hadoop/hbase/util/compaction/MajorCompactor.access$000:()Lorg/slf4j/Logger;
     645: new           #30                 // class java/lang/StringBuilder
     648: dup
     649: invokespecial #31                 // Method java/lang/StringBuilder."<init>":()V
     652: ldc           #57                 // String Compaction complete for region:
     654: invokevirtual #33                 // Method java/lang/StringBuilder.append:(Ljava/lang/String;)Ljava/lang/StringBuilder;
     657: aload_1
     658: invokevirtual #34                 // Method org/apache/hadoop/hbase/util/compaction/MajorCompactionRequest.getRegion:()Lorg/apache/hadoop/hbase/client/RegionInfo;
     661: invokeinterface #35,  1           // InterfaceMethod org/apache/hadoop/hbase/client/RegionInfo.getEncodedName:()Ljava/lang/String;
     666: invokevirtual #33                 // Method java/lang/StringBuilder.append:(Ljava/lang/String;)Ljava/lang/StringBuilder;
     669: ldc           #58                 // String  -> cf(s):
     671: invokevirtual #33                 // Method java/lang/StringBuilder.append:(Ljava/lang/String;)Ljava/lang/StringBuilder;
     674: aload_1
     675: invokevirtual #21                 // Method org/apache/hadoop/hbase/util/compaction/MajorCompactionRequest.getStores:()Ljava/util/Set;
     678: invokevirtual #49                 // Method java/lang/StringBuilder.append:(Ljava/lang/Object;)Ljava/lang/StringBuilder;
     681: invokevirtual #36                 // Method java/lang/StringBuilder.toString:()Ljava/lang/String;
     684: invokeinterface #56,  2           // InterfaceMethod org/slf4j/Logger.info:(Ljava/lang/String;)V
     689: aload         6
     691: athrow
     692: return
    Exception table:
       from    to  target type
          13   160   424   any
         424   426   424   any
}
