Compiled from "MapReduceProtos.java"
public final class org.apache.hadoop.hbase.protobuf.generated.MapReduceProtos$TableSnapshotRegionSplit extends com.google.protobuf.GeneratedMessage implements org.apache.hadoop.hbase.protobuf.generated.MapReduceProtos$TableSnapshotRegionSplitOrBuilder {
  public static com.google.protobuf.Parser<org.apache.hadoop.hbase.protobuf.generated.MapReduceProtos$TableSnapshotRegionSplit> PARSER;

  public static final int LOCATIONS_FIELD_NUMBER;

  public static final int TABLE_FIELD_NUMBER;

  public static final int REGION_FIELD_NUMBER;

  public static org.apache.hadoop.hbase.protobuf.generated.MapReduceProtos$TableSnapshotRegionSplit getDefaultInstance();
    Code:
       0: getstatic     #16                 // Field defaultInstance:Lorg/apache/hadoop/hbase/protobuf/generated/MapReduceProtos$TableSnapshotRegionSplit;
       3: areturn

  public org.apache.hadoop.hbase.protobuf.generated.MapReduceProtos$TableSnapshotRegionSplit getDefaultInstanceForType();
    Code:
       0: getstatic     #16                 // Field defaultInstance:Lorg/apache/hadoop/hbase/protobuf/generated/MapReduceProtos$TableSnapshotRegionSplit;
       3: areturn

  public final com.google.protobuf.UnknownFieldSet getUnknownFields();
    Code:
       0: aload_0
       1: getfield      #13                 // Field unknownFields:Lcom/google/protobuf/UnknownFieldSet;
       4: areturn

  public static final com.google.protobuf.Descriptors$Descriptor getDescriptor();
    Code:
       0: invokestatic  #45                 // Method org/apache/hadoop/hbase/protobuf/generated/MapReduceProtos.access$900:()Lcom/google/protobuf/Descriptors$Descriptor;
       3: areturn

  protected com.google.protobuf.GeneratedMessage$FieldAccessorTable internalGetFieldAccessorTable();
    Code:
       0: invokestatic  #46                 // Method org/apache/hadoop/hbase/protobuf/generated/MapReduceProtos.access$1000:()Lcom/google/protobuf/GeneratedMessage$FieldAccessorTable;
       3: ldc           #47                 // class org/apache/hadoop/hbase/protobuf/generated/MapReduceProtos$TableSnapshotRegionSplit
       5: ldc           #48                 // class org/apache/hadoop/hbase/protobuf/generated/MapReduceProtos$TableSnapshotRegionSplit$Builder
       7: invokevirtual #49                 // Method com/google/protobuf/GeneratedMessage$FieldAccessorTable.ensureFieldAccessorsInitialized:(Ljava/lang/Class;Ljava/lang/Class;)Lcom/google/protobuf/GeneratedMessage$FieldAccessorTable;
      10: areturn

  public com.google.protobuf.Parser<org.apache.hadoop.hbase.protobuf.generated.MapReduceProtos$TableSnapshotRegionSplit> getParserForType();
    Code:
       0: getstatic     #50                 // Field PARSER:Lcom/google/protobuf/Parser;
       3: areturn

  public java.util.List<java.lang.String> getLocationsList();
    Code:
       0: aload_0
       1: getfield      #4                  // Field locations_:Lcom/google/protobuf/LazyStringList;
       4: areturn

  public int getLocationsCount();
    Code:
       0: aload_0
       1: getfield      #4                  // Field locations_:Lcom/google/protobuf/LazyStringList;
       4: invokeinterface #51,  1           // InterfaceMethod com/google/protobuf/LazyStringList.size:()I
       9: ireturn

  public java.lang.String getLocations(int);
    Code:
       0: aload_0
       1: getfield      #4                  // Field locations_:Lcom/google/protobuf/LazyStringList;
       4: iload_1
       5: invokeinterface #52,  2           // InterfaceMethod com/google/protobuf/LazyStringList.get:(I)Ljava/lang/Object;
      10: checkcast     #53                 // class java/lang/String
      13: areturn

  public com.google.protobuf.ByteString getLocationsBytes(int);
    Code:
       0: aload_0
       1: getfield      #4                  // Field locations_:Lcom/google/protobuf/LazyStringList;
       4: iload_1
       5: invokeinterface #54,  2           // InterfaceMethod com/google/protobuf/LazyStringList.getByteString:(I)Lcom/google/protobuf/ByteString;
      10: areturn

  public boolean hasTable();
    Code:
       0: aload_0
       1: getfield      #1                  // Field bitField0_:I
       4: iconst_1
       5: iand
       6: iconst_1
       7: if_icmpne     14
      10: iconst_1
      11: goto          15
      14: iconst_0
      15: ireturn

  public org.apache.hadoop.hbase.protobuf.generated.HBaseProtos$TableSchema getTable();
    Code:
       0: aload_0
       1: getfield      #3                  // Field table_:Lorg/apache/hadoop/hbase/protobuf/generated/HBaseProtos$TableSchema;
       4: areturn

  public org.apache.hadoop.hbase.protobuf.generated.HBaseProtos$TableSchemaOrBuilder getTableOrBuilder();
    Code:
       0: aload_0
       1: getfield      #3                  // Field table_:Lorg/apache/hadoop/hbase/protobuf/generated/HBaseProtos$TableSchema;
       4: areturn

  public boolean hasRegion();
    Code:
       0: aload_0
       1: getfield      #1                  // Field bitField0_:I
       4: iconst_2
       5: iand
       6: iconst_2
       7: if_icmpne     14
      10: iconst_1
      11: goto          15
      14: iconst_0
      15: ireturn

  public org.apache.hadoop.hbase.protobuf.generated.HBaseProtos$RegionInfo getRegion();
    Code:
       0: aload_0
       1: getfield      #2                  // Field region_:Lorg/apache/hadoop/hbase/protobuf/generated/HBaseProtos$RegionInfo;
       4: areturn

  public org.apache.hadoop.hbase.protobuf.generated.HBaseProtos$RegionInfoOrBuilder getRegionOrBuilder();
    Code:
       0: aload_0
       1: getfield      #2                  // Field region_:Lorg/apache/hadoop/hbase/protobuf/generated/HBaseProtos$RegionInfo;
       4: areturn

  public final boolean isInitialized();
    Code:
       0: aload_0
       1: getfield      #9                  // Field memoizedIsInitialized:B
       4: istore_1
       5: iload_1
       6: iconst_m1
       7: if_icmpeq     21
      10: iload_1
      11: iconst_1
      12: if_icmpne     19
      15: iconst_1
      16: goto          20
      19: iconst_0
      20: ireturn
      21: aload_0
      22: invokevirtual #58                 // Method hasTable:()Z
      25: ifeq          45
      28: aload_0
      29: invokevirtual #59                 // Method getTable:()Lorg/apache/hadoop/hbase/protobuf/generated/HBaseProtos$TableSchema;
      32: invokevirtual #60                 // Method org/apache/hadoop/hbase/protobuf/generated/HBaseProtos$TableSchema.isInitialized:()Z
      35: ifne          45
      38: aload_0
      39: iconst_0
      40: putfield      #9                  // Field memoizedIsInitialized:B
      43: iconst_0
      44: ireturn
      45: aload_0
      46: invokevirtual #61                 // Method hasRegion:()Z
      49: ifeq          69
      52: aload_0
      53: invokevirtual #62                 // Method getRegion:()Lorg/apache/hadoop/hbase/protobuf/generated/HBaseProtos$RegionInfo;
      56: invokevirtual #63                 // Method org/apache/hadoop/hbase/protobuf/generated/HBaseProtos$RegionInfo.isInitialized:()Z
      59: ifne          69
      62: aload_0
      63: iconst_0
      64: putfield      #9                  // Field memoizedIsInitialized:B
      67: iconst_0
      68: ireturn
      69: aload_0
      70: iconst_1
      71: putfield      #9                  // Field memoizedIsInitialized:B
      74: iconst_1
      75: ireturn

  public void writeTo(com.google.protobuf.CodedOutputStream) throws java.io.IOException;
    Code:
       0: aload_0
       1: invokevirtual #64                 // Method getSerializedSize:()I
       4: pop
       5: iconst_0
       6: istore_2
       7: iload_2
       8: aload_0
       9: getfield      #4                  // Field locations_:Lcom/google/protobuf/LazyStringList;
      12: invokeinterface #51,  1           // InterfaceMethod com/google/protobuf/LazyStringList.size:()I
      17: if_icmpge     41
      20: aload_1
      21: iconst_2
      22: aload_0
      23: getfield      #4                  // Field locations_:Lcom/google/protobuf/LazyStringList;
      26: iload_2
      27: invokeinterface #54,  2           // InterfaceMethod com/google/protobuf/LazyStringList.getByteString:(I)Lcom/google/protobuf/ByteString;
      32: invokevirtual #65                 // Method com/google/protobuf/CodedOutputStream.writeBytes:(ILcom/google/protobuf/ByteString;)V
      35: iinc          2, 1
      38: goto          7
      41: aload_0
      42: getfield      #1                  // Field bitField0_:I
      45: iconst_1
      46: iand
      47: iconst_1
      48: if_icmpne     60
      51: aload_1
      52: iconst_3
      53: aload_0
      54: getfield      #3                  // Field table_:Lorg/apache/hadoop/hbase/protobuf/generated/HBaseProtos$TableSchema;
      57: invokevirtual #66                 // Method com/google/protobuf/CodedOutputStream.writeMessage:(ILcom/google/protobuf/MessageLite;)V
      60: aload_0
      61: getfield      #1                  // Field bitField0_:I
      64: iconst_2
      65: iand
      66: iconst_2
      67: if_icmpne     79
      70: aload_1
      71: iconst_4
      72: aload_0
      73: getfield      #2                  // Field region_:Lorg/apache/hadoop/hbase/protobuf/generated/HBaseProtos$RegionInfo;
      76: invokevirtual #66                 // Method com/google/protobuf/CodedOutputStream.writeMessage:(ILcom/google/protobuf/MessageLite;)V
      79: aload_0
      80: invokevirtual #67                 // Method getUnknownFields:()Lcom/google/protobuf/UnknownFieldSet;
      83: aload_1
      84: invokevirtual #68                 // Method com/google/protobuf/UnknownFieldSet.writeTo:(Lcom/google/protobuf/CodedOutputStream;)V
      87: return

  public int getSerializedSize();
    Code:
       0: aload_0
       1: getfield      #10                 // Field memoizedSerializedSize:I
       4: istore_1
       5: iload_1
       6: iconst_m1
       7: if_icmpeq     12
      10: iload_1
      11: ireturn
      12: iconst_0
      13: istore_1
      14: iconst_0
      15: istore_2
      16: iconst_0
      17: istore_3
      18: iload_3
      19: aload_0
      20: getfield      #4                  // Field locations_:Lcom/google/protobuf/LazyStringList;
      23: invokeinterface #51,  1           // InterfaceMethod com/google/protobuf/LazyStringList.size:()I
      28: if_icmpge     53
      31: iload_2
      32: aload_0
      33: getfield      #4                  // Field locations_:Lcom/google/protobuf/LazyStringList;
      36: iload_3
      37: invokeinterface #54,  2           // InterfaceMethod com/google/protobuf/LazyStringList.getByteString:(I)Lcom/google/protobuf/ByteString;
      42: invokestatic  #69                 // Method com/google/protobuf/CodedOutputStream.computeBytesSizeNoTag:(Lcom/google/protobuf/ByteString;)I
      45: iadd
      46: istore_2
      47: iinc          3, 1
      50: goto          18
      53: iload_1
      54: iload_2
      55: iadd
      56: istore_1
      57: iload_1
      58: iconst_1
      59: aload_0
      60: invokevirtual #70                 // Method getLocationsList:()Ljava/util/List;
      63: invokeinterface #71,  1           // InterfaceMethod java/util/List.size:()I
      68: imul
      69: iadd
      70: istore_1
      71: aload_0
      72: getfield      #1                  // Field bitField0_:I
      75: iconst_1
      76: iand
      77: iconst_1
      78: if_icmpne     92
      81: iload_1
      82: iconst_3
      83: aload_0
      84: getfield      #3                  // Field table_:Lorg/apache/hadoop/hbase/protobuf/generated/HBaseProtos$TableSchema;
      87: invokestatic  #72                 // Method com/google/protobuf/CodedOutputStream.computeMessageSize:(ILcom/google/protobuf/MessageLite;)I
      90: iadd
      91: istore_1
      92: aload_0
      93: getfield      #1                  // Field bitField0_:I
      96: iconst_2
      97: iand
      98: iconst_2
      99: if_icmpne     113
     102: iload_1
     103: iconst_4
     104: aload_0
     105: getfield      #2                  // Field region_:Lorg/apache/hadoop/hbase/protobuf/generated/HBaseProtos$RegionInfo;
     108: invokestatic  #72                 // Method com/google/protobuf/CodedOutputStream.computeMessageSize:(ILcom/google/protobuf/MessageLite;)I
     111: iadd
     112: istore_1
     113: iload_1
     114: aload_0
     115: invokevirtual #67                 // Method getUnknownFields:()Lcom/google/protobuf/UnknownFieldSet;
     118: invokevirtual #73                 // Method com/google/protobuf/UnknownFieldSet.getSerializedSize:()I
     121: iadd
     122: istore_1
     123: aload_0
     124: iload_1
     125: putfield      #10                 // Field memoizedSerializedSize:I
     128: iload_1
     129: ireturn

  protected java.lang.Object writeReplace() throws java.io.ObjectStreamException;
    Code:
       0: aload_0
       1: invokespecial #74                 // Method com/google/protobuf/GeneratedMessage.writeReplace:()Ljava/lang/Object;
       4: areturn

  public boolean equals(java.lang.Object);
    Code:
       0: aload_1
       1: aload_0
       2: if_acmpne     7
       5: iconst_1
       6: ireturn
       7: aload_1
       8: instanceof    #47                 // class org/apache/hadoop/hbase/protobuf/generated/MapReduceProtos$TableSnapshotRegionSplit
      11: ifne          20
      14: aload_0
      15: aload_1
      16: invokespecial #75                 // Method com/google/protobuf/GeneratedMessage.equals:(Ljava/lang/Object;)Z
      19: ireturn
      20: aload_1
      21: checkcast     #47                 // class org/apache/hadoop/hbase/protobuf/generated/MapReduceProtos$TableSnapshotRegionSplit
      24: astore_2
      25: iconst_1
      26: istore_3
      27: iload_3
      28: ifeq          51
      31: aload_0
      32: invokevirtual #70                 // Method getLocationsList:()Ljava/util/List;
      35: aload_2
      36: invokevirtual #70                 // Method getLocationsList:()Ljava/util/List;
      39: invokeinterface #76,  2           // InterfaceMethod java/util/List.equals:(Ljava/lang/Object;)Z
      44: ifeq          51
      47: iconst_1
      48: goto          52
      51: iconst_0
      52: istore_3
      53: iload_3
      54: ifeq          72
      57: aload_0
      58: invokevirtual #58                 // Method hasTable:()Z
      61: aload_2
      62: invokevirtual #58                 // Method hasTable:()Z
      65: if_icmpne     72
      68: iconst_1
      69: goto          73
      72: iconst_0
      73: istore_3
      74: aload_0
      75: invokevirtual #58                 // Method hasTable:()Z
      78: ifeq          105
      81: iload_3
      82: ifeq          103
      85: aload_0
      86: invokevirtual #59                 // Method getTable:()Lorg/apache/hadoop/hbase/protobuf/generated/HBaseProtos$TableSchema;
      89: aload_2
      90: invokevirtual #59                 // Method getTable:()Lorg/apache/hadoop/hbase/protobuf/generated/HBaseProtos$TableSchema;
      93: invokevirtual #77                 // Method org/apache/hadoop/hbase/protobuf/generated/HBaseProtos$TableSchema.equals:(Ljava/lang/Object;)Z
      96: ifeq          103
      99: iconst_1
     100: goto          104
     103: iconst_0
     104: istore_3
     105: iload_3
     106: ifeq          124
     109: aload_0
     110: invokevirtual #61                 // Method hasRegion:()Z
     113: aload_2
     114: invokevirtual #61                 // Method hasRegion:()Z
     117: if_icmpne     124
     120: iconst_1
     121: goto          125
     124: iconst_0
     125: istore_3
     126: aload_0
     127: invokevirtual #61                 // Method hasRegion:()Z
     130: ifeq          157
     133: iload_3
     134: ifeq          155
     137: aload_0
     138: invokevirtual #62                 // Method getRegion:()Lorg/apache/hadoop/hbase/protobuf/generated/HBaseProtos$RegionInfo;
     141: aload_2
     142: invokevirtual #62                 // Method getRegion:()Lorg/apache/hadoop/hbase/protobuf/generated/HBaseProtos$RegionInfo;
     145: invokevirtual #78                 // Method org/apache/hadoop/hbase/protobuf/generated/HBaseProtos$RegionInfo.equals:(Ljava/lang/Object;)Z
     148: ifeq          155
     151: iconst_1
     152: goto          156
     155: iconst_0
     156: istore_3
     157: iload_3
     158: ifeq          179
     161: aload_0
     162: invokevirtual #67                 // Method getUnknownFields:()Lcom/google/protobuf/UnknownFieldSet;
     165: aload_2
     166: invokevirtual #67                 // Method getUnknownFields:()Lcom/google/protobuf/UnknownFieldSet;
     169: invokevirtual #79                 // Method com/google/protobuf/UnknownFieldSet.equals:(Ljava/lang/Object;)Z
     172: ifeq          179
     175: iconst_1
     176: goto          180
     179: iconst_0
     180: istore_3
     181: iload_3
     182: ireturn

  public int hashCode();
    Code:
       0: aload_0
       1: getfield      #11                 // Field memoizedHashCode:I
       4: ifeq          12
       7: aload_0
       8: getfield      #11                 // Field memoizedHashCode:I
      11: ireturn
      12: bipush        41
      14: istore_1
      15: bipush        19
      17: iload_1
      18: imul
      19: aload_0
      20: invokevirtual #80                 // Method getDescriptorForType:()Lcom/google/protobuf/Descriptors$Descriptor;
      23: invokevirtual #81                 // Method java/lang/Object.hashCode:()I
      26: iadd
      27: istore_1
      28: aload_0
      29: invokevirtual #82                 // Method getLocationsCount:()I
      32: ifle          57
      35: bipush        37
      37: iload_1
      38: imul
      39: iconst_2
      40: iadd
      41: istore_1
      42: bipush        53
      44: iload_1
      45: imul
      46: aload_0
      47: invokevirtual #70                 // Method getLocationsList:()Ljava/util/List;
      50: invokeinterface #83,  1           // InterfaceMethod java/util/List.hashCode:()I
      55: iadd
      56: istore_1
      57: aload_0
      58: invokevirtual #58                 // Method hasTable:()Z
      61: ifeq          84
      64: bipush        37
      66: iload_1
      67: imul
      68: iconst_3
      69: iadd
      70: istore_1
      71: bipush        53
      73: iload_1
      74: imul
      75: aload_0
      76: invokevirtual #59                 // Method getTable:()Lorg/apache/hadoop/hbase/protobuf/generated/HBaseProtos$TableSchema;
      79: invokevirtual #84                 // Method org/apache/hadoop/hbase/protobuf/generated/HBaseProtos$TableSchema.hashCode:()I
      82: iadd
      83: istore_1
      84: aload_0
      85: invokevirtual #61                 // Method hasRegion:()Z
      88: ifeq          111
      91: bipush        37
      93: iload_1
      94: imul
      95: iconst_4
      96: iadd
      97: istore_1
      98: bipush        53
     100: iload_1
     101: imul
     102: aload_0
     103: invokevirtual #62                 // Method getRegion:()Lorg/apache/hadoop/hbase/protobuf/generated/HBaseProtos$RegionInfo;
     106: invokevirtual #85                 // Method org/apache/hadoop/hbase/protobuf/generated/HBaseProtos$RegionInfo.hashCode:()I
     109: iadd
     110: istore_1
     111: bipush        29
     113: iload_1
     114: imul
     115: aload_0
     116: invokevirtual #67                 // Method getUnknownFields:()Lcom/google/protobuf/UnknownFieldSet;
     119: invokevirtual #86                 // Method com/google/protobuf/UnknownFieldSet.hashCode:()I
     122: iadd
     123: istore_1
     124: aload_0
     125: iload_1
     126: putfield      #11                 // Field memoizedHashCode:I
     129: iload_1
     130: ireturn

  public static org.apache.hadoop.hbase.protobuf.generated.MapReduceProtos$TableSnapshotRegionSplit parseFrom(com.google.protobuf.ByteString) throws com.google.protobuf.InvalidProtocolBufferException;
    Code:
       0: getstatic     #50                 // Field PARSER:Lcom/google/protobuf/Parser;
       3: aload_0
       4: invokeinterface #87,  2           // InterfaceMethod com/google/protobuf/Parser.parseFrom:(Lcom/google/protobuf/ByteString;)Ljava/lang/Object;
       9: checkcast     #47                 // class org/apache/hadoop/hbase/protobuf/generated/MapReduceProtos$TableSnapshotRegionSplit
      12: areturn

  public static org.apache.hadoop.hbase.protobuf.generated.MapReduceProtos$TableSnapshotRegionSplit parseFrom(com.google.protobuf.ByteString, com.google.protobuf.ExtensionRegistryLite) throws com.google.protobuf.InvalidProtocolBufferException;
    Code:
       0: getstatic     #50                 // Field PARSER:Lcom/google/protobuf/Parser;
       3: aload_0
       4: aload_1
       5: invokeinterface #88,  3           // InterfaceMethod com/google/protobuf/Parser.parseFrom:(Lcom/google/protobuf/ByteString;Lcom/google/protobuf/ExtensionRegistryLite;)Ljava/lang/Object;
      10: checkcast     #47                 // class org/apache/hadoop/hbase/protobuf/generated/MapReduceProtos$TableSnapshotRegionSplit
      13: areturn

  public static org.apache.hadoop.hbase.protobuf.generated.MapReduceProtos$TableSnapshotRegionSplit parseFrom(byte[]) throws com.google.protobuf.InvalidProtocolBufferException;
    Code:
       0: getstatic     #50                 // Field PARSER:Lcom/google/protobuf/Parser;
       3: aload_0
       4: invokeinterface #89,  2           // InterfaceMethod com/google/protobuf/Parser.parseFrom:([B)Ljava/lang/Object;
       9: checkcast     #47                 // class org/apache/hadoop/hbase/protobuf/generated/MapReduceProtos$TableSnapshotRegionSplit
      12: areturn

  public static org.apache.hadoop.hbase.protobuf.generated.MapReduceProtos$TableSnapshotRegionSplit parseFrom(byte[], com.google.protobuf.ExtensionRegistryLite) throws com.google.protobuf.InvalidProtocolBufferException;
    Code:
       0: getstatic     #50                 // Field PARSER:Lcom/google/protobuf/Parser;
       3: aload_0
       4: aload_1
       5: invokeinterface #90,  3           // InterfaceMethod com/google/protobuf/Parser.parseFrom:([BLcom/google/protobuf/ExtensionRegistryLite;)Ljava/lang/Object;
      10: checkcast     #47                 // class org/apache/hadoop/hbase/protobuf/generated/MapReduceProtos$TableSnapshotRegionSplit
      13: areturn

  public static org.apache.hadoop.hbase.protobuf.generated.MapReduceProtos$TableSnapshotRegionSplit parseFrom(java.io.InputStream) throws java.io.IOException;
    Code:
       0: getstatic     #50                 // Field PARSER:Lcom/google/protobuf/Parser;
       3: aload_0
       4: invokeinterface #91,  2           // InterfaceMethod com/google/protobuf/Parser.parseFrom:(Ljava/io/InputStream;)Ljava/lang/Object;
       9: checkcast     #47                 // class org/apache/hadoop/hbase/protobuf/generated/MapReduceProtos$TableSnapshotRegionSplit
      12: areturn

  public static org.apache.hadoop.hbase.protobuf.generated.MapReduceProtos$TableSnapshotRegionSplit parseFrom(java.io.InputStream, com.google.protobuf.ExtensionRegistryLite) throws java.io.IOException;
    Code:
       0: getstatic     #50                 // Field PARSER:Lcom/google/protobuf/Parser;
       3: aload_0
       4: aload_1
       5: invokeinterface #92,  3           // InterfaceMethod com/google/protobuf/Parser.parseFrom:(Ljava/io/InputStream;Lcom/google/protobuf/ExtensionRegistryLite;)Ljava/lang/Object;
      10: checkcast     #47                 // class org/apache/hadoop/hbase/protobuf/generated/MapReduceProtos$TableSnapshotRegionSplit
      13: areturn

  public static org.apache.hadoop.hbase.protobuf.generated.MapReduceProtos$TableSnapshotRegionSplit parseDelimitedFrom(java.io.InputStream) throws java.io.IOException;
    Code:
       0: getstatic     #50                 // Field PARSER:Lcom/google/protobuf/Parser;
       3: aload_0
       4: invokeinterface #93,  2           // InterfaceMethod com/google/protobuf/Parser.parseDelimitedFrom:(Ljava/io/InputStream;)Ljava/lang/Object;
       9: checkcast     #47                 // class org/apache/hadoop/hbase/protobuf/generated/MapReduceProtos$TableSnapshotRegionSplit
      12: areturn

  public static org.apache.hadoop.hbase.protobuf.generated.MapReduceProtos$TableSnapshotRegionSplit parseDelimitedFrom(java.io.InputStream, com.google.protobuf.ExtensionRegistryLite) throws java.io.IOException;
    Code:
       0: getstatic     #50                 // Field PARSER:Lcom/google/protobuf/Parser;
       3: aload_0
       4: aload_1
       5: invokeinterface #94,  3           // InterfaceMethod com/google/protobuf/Parser.parseDelimitedFrom:(Ljava/io/InputStream;Lcom/google/protobuf/ExtensionRegistryLite;)Ljava/lang/Object;
      10: checkcast     #47                 // class org/apache/hadoop/hbase/protobuf/generated/MapReduceProtos$TableSnapshotRegionSplit
      13: areturn

  public static org.apache.hadoop.hbase.protobuf.generated.MapReduceProtos$TableSnapshotRegionSplit parseFrom(com.google.protobuf.CodedInputStream) throws java.io.IOException;
    Code:
       0: getstatic     #50                 // Field PARSER:Lcom/google/protobuf/Parser;
       3: aload_0
       4: invokeinterface #95,  2           // InterfaceMethod com/google/protobuf/Parser.parseFrom:(Lcom/google/protobuf/CodedInputStream;)Ljava/lang/Object;
       9: checkcast     #47                 // class org/apache/hadoop/hbase/protobuf/generated/MapReduceProtos$TableSnapshotRegionSplit
      12: areturn

  public static org.apache.hadoop.hbase.protobuf.generated.MapReduceProtos$TableSnapshotRegionSplit parseFrom(com.google.protobuf.CodedInputStream, com.google.protobuf.ExtensionRegistryLite) throws java.io.IOException;
    Code:
       0: getstatic     #50                 // Field PARSER:Lcom/google/protobuf/Parser;
       3: aload_0
       4: aload_1
       5: invokeinterface #96,  3           // InterfaceMethod com/google/protobuf/Parser.parseFrom:(Lcom/google/protobuf/CodedInputStream;Lcom/google/protobuf/ExtensionRegistryLite;)Ljava/lang/Object;
      10: checkcast     #47                 // class org/apache/hadoop/hbase/protobuf/generated/MapReduceProtos$TableSnapshotRegionSplit
      13: areturn

  public static org.apache.hadoop.hbase.protobuf.generated.MapReduceProtos$TableSnapshotRegionSplit$Builder newBuilder();
    Code:
       0: invokestatic  #97                 // Method org/apache/hadoop/hbase/protobuf/generated/MapReduceProtos$TableSnapshotRegionSplit$Builder.access$1200:()Lorg/apache/hadoop/hbase/protobuf/generated/MapReduceProtos$TableSnapshotRegionSplit$Builder;
       3: areturn

  public org.apache.hadoop.hbase.protobuf.generated.MapReduceProtos$TableSnapshotRegionSplit$Builder newBuilderForType();
    Code:
       0: invokestatic  #98                 // Method newBuilder:()Lorg/apache/hadoop/hbase/protobuf/generated/MapReduceProtos$TableSnapshotRegionSplit$Builder;
       3: areturn

  public static org.apache.hadoop.hbase.protobuf.generated.MapReduceProtos$TableSnapshotRegionSplit$Builder newBuilder(org.apache.hadoop.hbase.protobuf.generated.MapReduceProtos$TableSnapshotRegionSplit);
    Code:
       0: invokestatic  #98                 // Method newBuilder:()Lorg/apache/hadoop/hbase/protobuf/generated/MapReduceProtos$TableSnapshotRegionSplit$Builder;
       3: aload_0
       4: invokevirtual #99                 // Method org/apache/hadoop/hbase/protobuf/generated/MapReduceProtos$TableSnapshotRegionSplit$Builder.mergeFrom:(Lorg/apache/hadoop/hbase/protobuf/generated/MapReduceProtos$TableSnapshotRegionSplit;)Lorg/apache/hadoop/hbase/protobuf/generated/MapReduceProtos$TableSnapshotRegionSplit$Builder;
       7: areturn

  public org.apache.hadoop.hbase.protobuf.generated.MapReduceProtos$TableSnapshotRegionSplit$Builder toBuilder();
    Code:
       0: aload_0
       1: invokestatic  #100                // Method newBuilder:(Lorg/apache/hadoop/hbase/protobuf/generated/MapReduceProtos$TableSnapshotRegionSplit;)Lorg/apache/hadoop/hbase/protobuf/generated/MapReduceProtos$TableSnapshotRegionSplit$Builder;
       4: areturn

  protected org.apache.hadoop.hbase.protobuf.generated.MapReduceProtos$TableSnapshotRegionSplit$Builder newBuilderForType(com.google.protobuf.GeneratedMessage$BuilderParent);
    Code:
       0: new           #48                 // class org/apache/hadoop/hbase/protobuf/generated/MapReduceProtos$TableSnapshotRegionSplit$Builder
       3: dup
       4: aload_1
       5: aconst_null
       6: invokespecial #101                // Method org/apache/hadoop/hbase/protobuf/generated/MapReduceProtos$TableSnapshotRegionSplit$Builder."<init>":(Lcom/google/protobuf/GeneratedMessage$BuilderParent;Lorg/apache/hadoop/hbase/protobuf/generated/MapReduceProtos$1;)V
       9: astore_2
      10: aload_2
      11: areturn

  protected com.google.protobuf.Message$Builder newBuilderForType(com.google.protobuf.GeneratedMessage$BuilderParent);
    Code:
       0: aload_0
       1: aload_1
       2: invokevirtual #102                // Method newBuilderForType:(Lcom/google/protobuf/GeneratedMessage$BuilderParent;)Lorg/apache/hadoop/hbase/protobuf/generated/MapReduceProtos$TableSnapshotRegionSplit$Builder;
       5: areturn

  public com.google.protobuf.Message$Builder toBuilder();
    Code:
       0: aload_0
       1: invokevirtual #103                // Method toBuilder:()Lorg/apache/hadoop/hbase/protobuf/generated/MapReduceProtos$TableSnapshotRegionSplit$Builder;
       4: areturn

  public com.google.protobuf.Message$Builder newBuilderForType();
    Code:
       0: aload_0
       1: invokevirtual #104                // Method newBuilderForType:()Lorg/apache/hadoop/hbase/protobuf/generated/MapReduceProtos$TableSnapshotRegionSplit$Builder;
       4: areturn

  public com.google.protobuf.MessageLite$Builder toBuilder();
    Code:
       0: aload_0
       1: invokevirtual #103                // Method toBuilder:()Lorg/apache/hadoop/hbase/protobuf/generated/MapReduceProtos$TableSnapshotRegionSplit$Builder;
       4: areturn

  public com.google.protobuf.MessageLite$Builder newBuilderForType();
    Code:
       0: aload_0
       1: invokevirtual #104                // Method newBuilderForType:()Lorg/apache/hadoop/hbase/protobuf/generated/MapReduceProtos$TableSnapshotRegionSplit$Builder;
       4: areturn

  public com.google.protobuf.MessageLite getDefaultInstanceForType();
    Code:
       0: aload_0
       1: invokevirtual #105                // Method getDefaultInstanceForType:()Lorg/apache/hadoop/hbase/protobuf/generated/MapReduceProtos$TableSnapshotRegionSplit;
       4: areturn

  public com.google.protobuf.Message getDefaultInstanceForType();
    Code:
       0: aload_0
       1: invokevirtual #105                // Method getDefaultInstanceForType:()Lorg/apache/hadoop/hbase/protobuf/generated/MapReduceProtos$TableSnapshotRegionSplit;
       4: areturn

  org.apache.hadoop.hbase.protobuf.generated.MapReduceProtos$TableSnapshotRegionSplit(com.google.protobuf.CodedInputStream, com.google.protobuf.ExtensionRegistryLite, org.apache.hadoop.hbase.protobuf.generated.MapReduceProtos$1) throws com.google.protobuf.InvalidProtocolBufferException;
    Code:
       0: aload_0
       1: aload_1
       2: aload_2
       3: invokespecial #7                  // Method "<init>":(Lcom/google/protobuf/CodedInputStream;Lcom/google/protobuf/ExtensionRegistryLite;)V
       6: return

  static boolean access$1400();
    Code:
       0: getstatic     #6                  // Field alwaysUseFieldBuilders:Z
       3: ireturn

  org.apache.hadoop.hbase.protobuf.generated.MapReduceProtos$TableSnapshotRegionSplit(com.google.protobuf.GeneratedMessage$Builder, org.apache.hadoop.hbase.protobuf.generated.MapReduceProtos$1);
    Code:
       0: aload_0
       1: aload_1
       2: invokespecial #5                  // Method "<init>":(Lcom/google/protobuf/GeneratedMessage$Builder;)V
       5: return

  static com.google.protobuf.LazyStringList access$1602(org.apache.hadoop.hbase.protobuf.generated.MapReduceProtos$TableSnapshotRegionSplit, com.google.protobuf.LazyStringList);
    Code:
       0: aload_0
       1: aload_1
       2: dup_x1
       3: putfield      #4                  // Field locations_:Lcom/google/protobuf/LazyStringList;
       6: areturn

  static org.apache.hadoop.hbase.protobuf.generated.HBaseProtos$TableSchema access$1702(org.apache.hadoop.hbase.protobuf.generated.MapReduceProtos$TableSnapshotRegionSplit, org.apache.hadoop.hbase.protobuf.generated.HBaseProtos$TableSchema);
    Code:
       0: aload_0
       1: aload_1
       2: dup_x1
       3: putfield      #3                  // Field table_:Lorg/apache/hadoop/hbase/protobuf/generated/HBaseProtos$TableSchema;
       6: areturn

  static org.apache.hadoop.hbase.protobuf.generated.HBaseProtos$RegionInfo access$1802(org.apache.hadoop.hbase.protobuf.generated.MapReduceProtos$TableSnapshotRegionSplit, org.apache.hadoop.hbase.protobuf.generated.HBaseProtos$RegionInfo);
    Code:
       0: aload_0
       1: aload_1
       2: dup_x1
       3: putfield      #2                  // Field region_:Lorg/apache/hadoop/hbase/protobuf/generated/HBaseProtos$RegionInfo;
       6: areturn

  static int access$1902(org.apache.hadoop.hbase.protobuf.generated.MapReduceProtos$TableSnapshotRegionSplit, int);
    Code:
       0: aload_0
       1: iload_1
       2: dup_x1
       3: putfield      #1                  // Field bitField0_:I
       6: ireturn

  static com.google.protobuf.LazyStringList access$1600(org.apache.hadoop.hbase.protobuf.generated.MapReduceProtos$TableSnapshotRegionSplit);
    Code:
       0: aload_0
       1: getfield      #4                  // Field locations_:Lcom/google/protobuf/LazyStringList;
       4: areturn

  static {};
    Code:
       0: new           #106                // class org/apache/hadoop/hbase/protobuf/generated/MapReduceProtos$TableSnapshotRegionSplit$1
       3: dup
       4: invokespecial #107                // Method org/apache/hadoop/hbase/protobuf/generated/MapReduceProtos$TableSnapshotRegionSplit$1."<init>":()V
       7: putstatic     #50                 // Field PARSER:Lcom/google/protobuf/Parser;
      10: new           #47                 // class org/apache/hadoop/hbase/protobuf/generated/MapReduceProtos$TableSnapshotRegionSplit
      13: dup
      14: iconst_1
      15: invokespecial #108                // Method "<init>":(Z)V
      18: putstatic     #16                 // Field defaultInstance:Lorg/apache/hadoop/hbase/protobuf/generated/MapReduceProtos$TableSnapshotRegionSplit;
      21: getstatic     #16                 // Field defaultInstance:Lorg/apache/hadoop/hbase/protobuf/generated/MapReduceProtos$TableSnapshotRegionSplit;
      24: invokespecial #17                 // Method initFields:()V
      27: return
}
