Compiled from "MapreduceTestingShim.java"
class org.apache.hadoop.hbase.mapreduce.MapreduceTestingShim$MapreduceV1Shim extends org.apache.hadoop.hbase.mapreduce.MapreduceTestingShim {
  public org.apache.hadoop.mapreduce.JobContext newJobContext(org.apache.hadoop.conf.Configuration) throws java.io.IOException;
    Code:
       0: new           #3                  // class org/apache/hadoop/mapreduce/JobID
       3: dup
       4: invokespecial #4                  // Method org/apache/hadoop/mapreduce/JobID."<init>":()V
       7: astore_2
       8: ldc           #5                  // class org/apache/hadoop/mapreduce/JobContext
      10: iconst_2
      11: anewarray     #6                  // class java/lang/Class
      14: dup
      15: iconst_0
      16: ldc           #7                  // class org/apache/hadoop/conf/Configuration
      18: aastore
      19: dup
      20: iconst_1
      21: ldc           #3                  // class org/apache/hadoop/mapreduce/JobID
      23: aastore
      24: invokevirtual #8                  // Method java/lang/Class.getConstructor:([Ljava/lang/Class;)Ljava/lang/reflect/Constructor;
      27: astore_3
      28: aload_3
      29: iconst_2
      30: anewarray     #9                  // class java/lang/Object
      33: dup
      34: iconst_0
      35: aload_1
      36: aastore
      37: dup
      38: iconst_1
      39: aload_2
      40: aastore
      41: invokevirtual #10                 // Method java/lang/reflect/Constructor.newInstance:([Ljava/lang/Object;)Ljava/lang/Object;
      44: checkcast     #5                  // class org/apache/hadoop/mapreduce/JobContext
      47: areturn
      48: astore        4
      50: new           #12                 // class java/lang/IllegalStateException
      53: dup
      54: ldc           #13                 // String Failed to instantiate new JobContext(jobConf, new JobID())
      56: aload         4
      58: invokespecial #14                 // Method java/lang/IllegalStateException."<init>":(Ljava/lang/String;Ljava/lang/Throwable;)V
      61: athrow
    Exception table:
       from    to  target type
           8    47    48   Class java/lang/Exception

  public org.apache.hadoop.mapreduce.Job newJob(org.apache.hadoop.conf.Configuration) throws java.io.IOException;
    Code:
       0: ldc           #15                 // class org/apache/hadoop/mapreduce/Job
       2: iconst_1
       3: anewarray     #6                  // class java/lang/Class
       6: dup
       7: iconst_0
       8: ldc           #7                  // class org/apache/hadoop/conf/Configuration
      10: aastore
      11: invokevirtual #8                  // Method java/lang/Class.getConstructor:([Ljava/lang/Class;)Ljava/lang/reflect/Constructor;
      14: astore_2
      15: aload_2
      16: iconst_1
      17: anewarray     #9                  // class java/lang/Object
      20: dup
      21: iconst_0
      22: aload_1
      23: aastore
      24: invokevirtual #10                 // Method java/lang/reflect/Constructor.newInstance:([Ljava/lang/Object;)Ljava/lang/Object;
      27: checkcast     #15                 // class org/apache/hadoop/mapreduce/Job
      30: areturn
      31: astore_3
      32: new           #12                 // class java/lang/IllegalStateException
      35: dup
      36: ldc           #16                 // String Failed to instantiate new Job(conf)
      38: aload_3
      39: invokespecial #14                 // Method java/lang/IllegalStateException."<init>":(Ljava/lang/String;Ljava/lang/Throwable;)V
      42: athrow
    Exception table:
       from    to  target type
           0    30    31   Class java/lang/Exception

  public org.apache.hadoop.mapred.JobConf obtainJobConf(org.apache.hadoop.mapred.MiniMRCluster);
    Code:
       0: aload_1
       1: ifnonnull     6
       4: aconst_null
       5: areturn
       6: aload_1
       7: invokevirtual #17                 // Method org/apache/hadoop/mapred/MiniMRCluster.getJobTrackerRunner:()Lorg/apache/hadoop/mapred/MiniMRCluster$JobTrackerRunner;
      10: astore_2
      11: aload_2
      12: invokevirtual #18                 // Method java/lang/Object.getClass:()Ljava/lang/Class;
      15: ldc           #19                 // String getJobTracker
      17: invokestatic  #20                 // Method org/apache/hadoop/hbase/mapreduce/MapreduceTestingShim.access$200:()[Ljava/lang/Class;
      20: invokevirtual #21                 // Method java/lang/Class.getDeclaredMethod:(Ljava/lang/String;[Ljava/lang/Class;)Ljava/lang/reflect/Method;
      23: astore_3
      24: aload_3
      25: aload_2
      26: iconst_0
      27: anewarray     #9                  // class java/lang/Object
      30: invokevirtual #22                 // Method java/lang/reflect/Method.invoke:(Ljava/lang/Object;[Ljava/lang/Object;)Ljava/lang/Object;
      33: astore        4
      35: aload         4
      37: invokevirtual #18                 // Method java/lang/Object.getClass:()Ljava/lang/Class;
      40: ldc           #23                 // String getConf
      42: invokestatic  #20                 // Method org/apache/hadoop/hbase/mapreduce/MapreduceTestingShim.access$200:()[Ljava/lang/Class;
      45: invokevirtual #21                 // Method java/lang/Class.getDeclaredMethod:(Ljava/lang/String;[Ljava/lang/Class;)Ljava/lang/reflect/Method;
      48: astore        5
      50: aload         5
      52: aload         4
      54: iconst_0
      55: anewarray     #9                  // class java/lang/Object
      58: invokevirtual #22                 // Method java/lang/reflect/Method.invoke:(Ljava/lang/Object;[Ljava/lang/Object;)Ljava/lang/Object;
      61: checkcast     #24                 // class org/apache/hadoop/mapred/JobConf
      64: areturn
      65: astore_2
      66: aconst_null
      67: areturn
      68: astore_2
      69: aconst_null
      70: areturn
      71: astore_2
      72: aconst_null
      73: areturn
    Exception table:
       from    to  target type
           6    64    65   Class java/lang/NoSuchMethodException
           6    64    68   Class java/lang/reflect/InvocationTargetException
           6    64    71   Class java/lang/IllegalAccessException

  public java.lang.String obtainMROutputDirProp();
    Code:
       0: ldc           #28                 // String mapred.output.dir
       2: areturn

  org.apache.hadoop.hbase.mapreduce.MapreduceTestingShim$MapreduceV1Shim(org.apache.hadoop.hbase.mapreduce.MapreduceTestingShim$1);
    Code:
       0: aload_0
       1: invokespecial #1                  // Method "<init>":()V
       4: return
}
