Compiled from "MasterProtos.java"
public abstract class org.apache.hadoop.hbase.shaded.protobuf.generated.MasterProtos$HbckService implements org.apache.hbase.thirdparty.com.google.protobuf.Service {
  protected org.apache.hadoop.hbase.shaded.protobuf.generated.MasterProtos$HbckService();
    Code:
       0: aload_0
       1: invokespecial #1                  // Method java/lang/Object."<init>":()V
       4: return

  public static org.apache.hbase.thirdparty.com.google.protobuf.Service newReflectiveService(org.apache.hadoop.hbase.shaded.protobuf.generated.MasterProtos$HbckService$Interface);
    Code:
       0: new           #2                  // class org/apache/hadoop/hbase/shaded/protobuf/generated/MasterProtos$HbckService$1
       3: dup
       4: aload_0
       5: invokespecial #3                  // Method org/apache/hadoop/hbase/shaded/protobuf/generated/MasterProtos$HbckService$1."<init>":(Lorg/apache/hadoop/hbase/shaded/protobuf/generated/MasterProtos$HbckService$Interface;)V
       8: areturn

  public static org.apache.hbase.thirdparty.com.google.protobuf.BlockingService newReflectiveBlockingService(org.apache.hadoop.hbase.shaded.protobuf.generated.MasterProtos$HbckService$BlockingInterface);
    Code:
       0: new           #4                  // class org/apache/hadoop/hbase/shaded/protobuf/generated/MasterProtos$HbckService$2
       3: dup
       4: aload_0
       5: invokespecial #5                  // Method org/apache/hadoop/hbase/shaded/protobuf/generated/MasterProtos$HbckService$2."<init>":(Lorg/apache/hadoop/hbase/shaded/protobuf/generated/MasterProtos$HbckService$BlockingInterface;)V
       8: areturn

  public abstract void setTableStateInMeta(org.apache.hbase.thirdparty.com.google.protobuf.RpcController, org.apache.hadoop.hbase.shaded.protobuf.generated.MasterProtos$SetTableStateInMetaRequest, org.apache.hbase.thirdparty.com.google.protobuf.RpcCallback<org.apache.hadoop.hbase.shaded.protobuf.generated.MasterProtos$GetTableStateResponse>);

  public abstract void assigns(org.apache.hbase.thirdparty.com.google.protobuf.RpcController, org.apache.hadoop.hbase.shaded.protobuf.generated.MasterProtos$AssignsRequest, org.apache.hbase.thirdparty.com.google.protobuf.RpcCallback<org.apache.hadoop.hbase.shaded.protobuf.generated.MasterProtos$AssignsResponse>);

  public abstract void unassigns(org.apache.hbase.thirdparty.com.google.protobuf.RpcController, org.apache.hadoop.hbase.shaded.protobuf.generated.MasterProtos$UnassignsRequest, org.apache.hbase.thirdparty.com.google.protobuf.RpcCallback<org.apache.hadoop.hbase.shaded.protobuf.generated.MasterProtos$UnassignsResponse>);

  public abstract void bypassProcedure(org.apache.hbase.thirdparty.com.google.protobuf.RpcController, org.apache.hadoop.hbase.shaded.protobuf.generated.MasterProtos$BypassProcedureRequest, org.apache.hbase.thirdparty.com.google.protobuf.RpcCallback<org.apache.hadoop.hbase.shaded.protobuf.generated.MasterProtos$BypassProcedureResponse>);

  public abstract void scheduleServerCrashProcedure(org.apache.hbase.thirdparty.com.google.protobuf.RpcController, org.apache.hadoop.hbase.shaded.protobuf.generated.MasterProtos$ScheduleServerCrashProcedureRequest, org.apache.hbase.thirdparty.com.google.protobuf.RpcCallback<org.apache.hadoop.hbase.shaded.protobuf.generated.MasterProtos$ScheduleServerCrashProcedureResponse>);

  public abstract void getFailedSplitMergeLegacyRegions(org.apache.hbase.thirdparty.com.google.protobuf.RpcController, org.apache.hadoop.hbase.shaded.protobuf.generated.MasterProtos$GetFailedSplitMergeLegacyRegionsRequest, org.apache.hbase.thirdparty.com.google.protobuf.RpcCallback<org.apache.hadoop.hbase.shaded.protobuf.generated.MasterProtos$GetFailedSplitMergeLegacyRegionsResponse>);

  public static final org.apache.hbase.thirdparty.com.google.protobuf.Descriptors$ServiceDescriptor getDescriptor();
    Code:
       0: invokestatic  #6                  // Method org/apache/hadoop/hbase/shaded/protobuf/generated/MasterProtos.getDescriptor:()Lorg/apache/hbase/thirdparty/com/google/protobuf/Descriptors$FileDescriptor;
       3: invokevirtual #7                  // Method org/apache/hbase/thirdparty/com/google/protobuf/Descriptors$FileDescriptor.getServices:()Ljava/util/List;
       6: iconst_1
       7: invokeinterface #8,  2            // InterfaceMethod java/util/List.get:(I)Ljava/lang/Object;
      12: checkcast     #9                  // class org/apache/hbase/thirdparty/com/google/protobuf/Descriptors$ServiceDescriptor
      15: areturn

  public final org.apache.hbase.thirdparty.com.google.protobuf.Descriptors$ServiceDescriptor getDescriptorForType();
    Code:
       0: invokestatic  #10                 // Method getDescriptor:()Lorg/apache/hbase/thirdparty/com/google/protobuf/Descriptors$ServiceDescriptor;
       3: areturn

  public final void callMethod(org.apache.hbase.thirdparty.com.google.protobuf.Descriptors$MethodDescriptor, org.apache.hbase.thirdparty.com.google.protobuf.RpcController, org.apache.hbase.thirdparty.com.google.protobuf.Message, org.apache.hbase.thirdparty.com.google.protobuf.RpcCallback<org.apache.hbase.thirdparty.com.google.protobuf.Message>);
    Code:
       0: aload_1
       1: invokevirtual #11                 // Method org/apache/hbase/thirdparty/com/google/protobuf/Descriptors$MethodDescriptor.getService:()Lorg/apache/hbase/thirdparty/com/google/protobuf/Descriptors$ServiceDescriptor;
       4: invokestatic  #10                 // Method getDescriptor:()Lorg/apache/hbase/thirdparty/com/google/protobuf/Descriptors$ServiceDescriptor;
       7: if_acmpeq     20
      10: new           #12                 // class java/lang/IllegalArgumentException
      13: dup
      14: ldc           #13                 // String Service.callMethod() given method descriptor for wrong service type.
      16: invokespecial #14                 // Method java/lang/IllegalArgumentException."<init>":(Ljava/lang/String;)V
      19: athrow
      20: aload_1
      21: invokevirtual #15                 // Method org/apache/hbase/thirdparty/com/google/protobuf/Descriptors$MethodDescriptor.getIndex:()I
      24: tableswitch   { // 0 to 5
                     0: 64
                     1: 79
                     2: 94
                     3: 109
                     4: 124
                     5: 139
               default: 154
          }
      64: aload_0
      65: aload_2
      66: aload_3
      67: checkcast     #16                 // class org/apache/hadoop/hbase/shaded/protobuf/generated/MasterProtos$SetTableStateInMetaRequest
      70: aload         4
      72: invokestatic  #17                 // Method org/apache/hbase/thirdparty/com/google/protobuf/RpcUtil.specializeCallback:(Lorg/apache/hbase/thirdparty/com/google/protobuf/RpcCallback;)Lorg/apache/hbase/thirdparty/com/google/protobuf/RpcCallback;
      75: invokevirtual #18                 // Method setTableStateInMeta:(Lorg/apache/hbase/thirdparty/com/google/protobuf/RpcController;Lorg/apache/hadoop/hbase/shaded/protobuf/generated/MasterProtos$SetTableStateInMetaRequest;Lorg/apache/hbase/thirdparty/com/google/protobuf/RpcCallback;)V
      78: return
      79: aload_0
      80: aload_2
      81: aload_3
      82: checkcast     #19                 // class org/apache/hadoop/hbase/shaded/protobuf/generated/MasterProtos$AssignsRequest
      85: aload         4
      87: invokestatic  #17                 // Method org/apache/hbase/thirdparty/com/google/protobuf/RpcUtil.specializeCallback:(Lorg/apache/hbase/thirdparty/com/google/protobuf/RpcCallback;)Lorg/apache/hbase/thirdparty/com/google/protobuf/RpcCallback;
      90: invokevirtual #20                 // Method assigns:(Lorg/apache/hbase/thirdparty/com/google/protobuf/RpcController;Lorg/apache/hadoop/hbase/shaded/protobuf/generated/MasterProtos$AssignsRequest;Lorg/apache/hbase/thirdparty/com/google/protobuf/RpcCallback;)V
      93: return
      94: aload_0
      95: aload_2
      96: aload_3
      97: checkcast     #21                 // class org/apache/hadoop/hbase/shaded/protobuf/generated/MasterProtos$UnassignsRequest
     100: aload         4
     102: invokestatic  #17                 // Method org/apache/hbase/thirdparty/com/google/protobuf/RpcUtil.specializeCallback:(Lorg/apache/hbase/thirdparty/com/google/protobuf/RpcCallback;)Lorg/apache/hbase/thirdparty/com/google/protobuf/RpcCallback;
     105: invokevirtual #22                 // Method unassigns:(Lorg/apache/hbase/thirdparty/com/google/protobuf/RpcController;Lorg/apache/hadoop/hbase/shaded/protobuf/generated/MasterProtos$UnassignsRequest;Lorg/apache/hbase/thirdparty/com/google/protobuf/RpcCallback;)V
     108: return
     109: aload_0
     110: aload_2
     111: aload_3
     112: checkcast     #23                 // class org/apache/hadoop/hbase/shaded/protobuf/generated/MasterProtos$BypassProcedureRequest
     115: aload         4
     117: invokestatic  #17                 // Method org/apache/hbase/thirdparty/com/google/protobuf/RpcUtil.specializeCallback:(Lorg/apache/hbase/thirdparty/com/google/protobuf/RpcCallback;)Lorg/apache/hbase/thirdparty/com/google/protobuf/RpcCallback;
     120: invokevirtual #24                 // Method bypassProcedure:(Lorg/apache/hbase/thirdparty/com/google/protobuf/RpcController;Lorg/apache/hadoop/hbase/shaded/protobuf/generated/MasterProtos$BypassProcedureRequest;Lorg/apache/hbase/thirdparty/com/google/protobuf/RpcCallback;)V
     123: return
     124: aload_0
     125: aload_2
     126: aload_3
     127: checkcast     #25                 // class org/apache/hadoop/hbase/shaded/protobuf/generated/MasterProtos$ScheduleServerCrashProcedureRequest
     130: aload         4
     132: invokestatic  #17                 // Method org/apache/hbase/thirdparty/com/google/protobuf/RpcUtil.specializeCallback:(Lorg/apache/hbase/thirdparty/com/google/protobuf/RpcCallback;)Lorg/apache/hbase/thirdparty/com/google/protobuf/RpcCallback;
     135: invokevirtual #26                 // Method scheduleServerCrashProcedure:(Lorg/apache/hbase/thirdparty/com/google/protobuf/RpcController;Lorg/apache/hadoop/hbase/shaded/protobuf/generated/MasterProtos$ScheduleServerCrashProcedureRequest;Lorg/apache/hbase/thirdparty/com/google/protobuf/RpcCallback;)V
     138: return
     139: aload_0
     140: aload_2
     141: aload_3
     142: checkcast     #27                 // class org/apache/hadoop/hbase/shaded/protobuf/generated/MasterProtos$GetFailedSplitMergeLegacyRegionsRequest
     145: aload         4
     147: invokestatic  #17                 // Method org/apache/hbase/thirdparty/com/google/protobuf/RpcUtil.specializeCallback:(Lorg/apache/hbase/thirdparty/com/google/protobuf/RpcCallback;)Lorg/apache/hbase/thirdparty/com/google/protobuf/RpcCallback;
     150: invokevirtual #28                 // Method getFailedSplitMergeLegacyRegions:(Lorg/apache/hbase/thirdparty/com/google/protobuf/RpcController;Lorg/apache/hadoop/hbase/shaded/protobuf/generated/MasterProtos$GetFailedSplitMergeLegacyRegionsRequest;Lorg/apache/hbase/thirdparty/com/google/protobuf/RpcCallback;)V
     153: return
     154: new           #29                 // class java/lang/AssertionError
     157: dup
     158: ldc           #30                 // String Can't get here.
     160: invokespecial #31                 // Method java/lang/AssertionError."<init>":(Ljava/lang/Object;)V
     163: athrow

  public final org.apache.hbase.thirdparty.com.google.protobuf.Message getRequestPrototype(org.apache.hbase.thirdparty.com.google.protobuf.Descriptors$MethodDescriptor);
    Code:
       0: aload_1
       1: invokevirtual #11                 // Method org/apache/hbase/thirdparty/com/google/protobuf/Descriptors$MethodDescriptor.getService:()Lorg/apache/hbase/thirdparty/com/google/protobuf/Descriptors$ServiceDescriptor;
       4: invokestatic  #10                 // Method getDescriptor:()Lorg/apache/hbase/thirdparty/com/google/protobuf/Descriptors$ServiceDescriptor;
       7: if_acmpeq     20
      10: new           #12                 // class java/lang/IllegalArgumentException
      13: dup
      14: ldc           #32                 // String Service.getRequestPrototype() given method descriptor for wrong service type.
      16: invokespecial #14                 // Method java/lang/IllegalArgumentException."<init>":(Ljava/lang/String;)V
      19: athrow
      20: aload_1
      21: invokevirtual #15                 // Method org/apache/hbase/thirdparty/com/google/protobuf/Descriptors$MethodDescriptor.getIndex:()I
      24: tableswitch   { // 0 to 5
                     0: 64
                     1: 68
                     2: 72
                     3: 76
                     4: 80
                     5: 84
               default: 88
          }
      64: invokestatic  #33                 // Method org/apache/hadoop/hbase/shaded/protobuf/generated/MasterProtos$SetTableStateInMetaRequest.getDefaultInstance:()Lorg/apache/hadoop/hbase/shaded/protobuf/generated/MasterProtos$SetTableStateInMetaRequest;
      67: areturn
      68: invokestatic  #34                 // Method org/apache/hadoop/hbase/shaded/protobuf/generated/MasterProtos$AssignsRequest.getDefaultInstance:()Lorg/apache/hadoop/hbase/shaded/protobuf/generated/MasterProtos$AssignsRequest;
      71: areturn
      72: invokestatic  #35                 // Method org/apache/hadoop/hbase/shaded/protobuf/generated/MasterProtos$UnassignsRequest.getDefaultInstance:()Lorg/apache/hadoop/hbase/shaded/protobuf/generated/MasterProtos$UnassignsRequest;
      75: areturn
      76: invokestatic  #36                 // Method org/apache/hadoop/hbase/shaded/protobuf/generated/MasterProtos$BypassProcedureRequest.getDefaultInstance:()Lorg/apache/hadoop/hbase/shaded/protobuf/generated/MasterProtos$BypassProcedureRequest;
      79: areturn
      80: invokestatic  #37                 // Method org/apache/hadoop/hbase/shaded/protobuf/generated/MasterProtos$ScheduleServerCrashProcedureRequest.getDefaultInstance:()Lorg/apache/hadoop/hbase/shaded/protobuf/generated/MasterProtos$ScheduleServerCrashProcedureRequest;
      83: areturn
      84: invokestatic  #38                 // Method org/apache/hadoop/hbase/shaded/protobuf/generated/MasterProtos$GetFailedSplitMergeLegacyRegionsRequest.getDefaultInstance:()Lorg/apache/hadoop/hbase/shaded/protobuf/generated/MasterProtos$GetFailedSplitMergeLegacyRegionsRequest;
      87: areturn
      88: new           #29                 // class java/lang/AssertionError
      91: dup
      92: ldc           #30                 // String Can't get here.
      94: invokespecial #31                 // Method java/lang/AssertionError."<init>":(Ljava/lang/Object;)V
      97: athrow

  public final org.apache.hbase.thirdparty.com.google.protobuf.Message getResponsePrototype(org.apache.hbase.thirdparty.com.google.protobuf.Descriptors$MethodDescriptor);
    Code:
       0: aload_1
       1: invokevirtual #11                 // Method org/apache/hbase/thirdparty/com/google/protobuf/Descriptors$MethodDescriptor.getService:()Lorg/apache/hbase/thirdparty/com/google/protobuf/Descriptors$ServiceDescriptor;
       4: invokestatic  #10                 // Method getDescriptor:()Lorg/apache/hbase/thirdparty/com/google/protobuf/Descriptors$ServiceDescriptor;
       7: if_acmpeq     20
      10: new           #12                 // class java/lang/IllegalArgumentException
      13: dup
      14: ldc           #39                 // String Service.getResponsePrototype() given method descriptor for wrong service type.
      16: invokespecial #14                 // Method java/lang/IllegalArgumentException."<init>":(Ljava/lang/String;)V
      19: athrow
      20: aload_1
      21: invokevirtual #15                 // Method org/apache/hbase/thirdparty/com/google/protobuf/Descriptors$MethodDescriptor.getIndex:()I
      24: tableswitch   { // 0 to 5
                     0: 64
                     1: 68
                     2: 72
                     3: 76
                     4: 80
                     5: 84
               default: 88
          }
      64: invokestatic  #40                 // Method org/apache/hadoop/hbase/shaded/protobuf/generated/MasterProtos$GetTableStateResponse.getDefaultInstance:()Lorg/apache/hadoop/hbase/shaded/protobuf/generated/MasterProtos$GetTableStateResponse;
      67: areturn
      68: invokestatic  #41                 // Method org/apache/hadoop/hbase/shaded/protobuf/generated/MasterProtos$AssignsResponse.getDefaultInstance:()Lorg/apache/hadoop/hbase/shaded/protobuf/generated/MasterProtos$AssignsResponse;
      71: areturn
      72: invokestatic  #42                 // Method org/apache/hadoop/hbase/shaded/protobuf/generated/MasterProtos$UnassignsResponse.getDefaultInstance:()Lorg/apache/hadoop/hbase/shaded/protobuf/generated/MasterProtos$UnassignsResponse;
      75: areturn
      76: invokestatic  #43                 // Method org/apache/hadoop/hbase/shaded/protobuf/generated/MasterProtos$BypassProcedureResponse.getDefaultInstance:()Lorg/apache/hadoop/hbase/shaded/protobuf/generated/MasterProtos$BypassProcedureResponse;
      79: areturn
      80: invokestatic  #44                 // Method org/apache/hadoop/hbase/shaded/protobuf/generated/MasterProtos$ScheduleServerCrashProcedureResponse.getDefaultInstance:()Lorg/apache/hadoop/hbase/shaded/protobuf/generated/MasterProtos$ScheduleServerCrashProcedureResponse;
      83: areturn
      84: invokestatic  #45                 // Method org/apache/hadoop/hbase/shaded/protobuf/generated/MasterProtos$GetFailedSplitMergeLegacyRegionsResponse.getDefaultInstance:()Lorg/apache/hadoop/hbase/shaded/protobuf/generated/MasterProtos$GetFailedSplitMergeLegacyRegionsResponse;
      87: areturn
      88: new           #29                 // class java/lang/AssertionError
      91: dup
      92: ldc           #30                 // String Can't get here.
      94: invokespecial #31                 // Method java/lang/AssertionError."<init>":(Ljava/lang/Object;)V
      97: athrow

  public static org.apache.hadoop.hbase.shaded.protobuf.generated.MasterProtos$HbckService$Stub newStub(org.apache.hbase.thirdparty.com.google.protobuf.RpcChannel);
    Code:
       0: new           #46                 // class org/apache/hadoop/hbase/shaded/protobuf/generated/MasterProtos$HbckService$Stub
       3: dup
       4: aload_0
       5: aconst_null
       6: invokespecial #47                 // Method org/apache/hadoop/hbase/shaded/protobuf/generated/MasterProtos$HbckService$Stub."<init>":(Lorg/apache/hbase/thirdparty/com/google/protobuf/RpcChannel;Lorg/apache/hadoop/hbase/shaded/protobuf/generated/MasterProtos$1;)V
       9: areturn

  public static org.apache.hadoop.hbase.shaded.protobuf.generated.MasterProtos$HbckService$BlockingInterface newBlockingStub(org.apache.hbase.thirdparty.com.google.protobuf.BlockingRpcChannel);
    Code:
       0: new           #48                 // class org/apache/hadoop/hbase/shaded/protobuf/generated/MasterProtos$HbckService$BlockingStub
       3: dup
       4: aload_0
       5: aconst_null
       6: invokespecial #49                 // Method org/apache/hadoop/hbase/shaded/protobuf/generated/MasterProtos$HbckService$BlockingStub."<init>":(Lorg/apache/hbase/thirdparty/com/google/protobuf/BlockingRpcChannel;Lorg/apache/hadoop/hbase/shaded/protobuf/generated/MasterProtos$1;)V
       9: areturn
}
