Compiled from "MasterCoprocessorHost.java"
class org.apache.hadoop.hbase.master.MasterCoprocessorHost$141 extends org.apache.hadoop.hbase.master.MasterCoprocessorHost$MasterObserverOperation {
  final java.lang.String val$namespace;

  final org.apache.hadoop.hbase.TableName val$tableName;

  final org.apache.hadoop.hbase.client.RegionInfo[] val$regionInfos;

  final java.lang.String val$description;

  final org.apache.hadoop.hbase.master.MasterCoprocessorHost this$0;

  org.apache.hadoop.hbase.master.MasterCoprocessorHost$141(org.apache.hadoop.hbase.master.MasterCoprocessorHost, java.lang.String, org.apache.hadoop.hbase.TableName, org.apache.hadoop.hbase.client.RegionInfo[], java.lang.String);
    Code:
       0: aload_0
       1: aload_1
       2: putfield      #1                  // Field this$0:Lorg/apache/hadoop/hbase/master/MasterCoprocessorHost;
       5: aload_0
       6: aload_2
       7: putfield      #2                  // Field val$namespace:Ljava/lang/String;
      10: aload_0
      11: aload_3
      12: putfield      #3                  // Field val$tableName:Lorg/apache/hadoop/hbase/TableName;
      15: aload_0
      16: aload         4
      18: putfield      #4                  // Field val$regionInfos:[Lorg/apache/hadoop/hbase/client/RegionInfo;
      21: aload_0
      22: aload         5
      24: putfield      #5                  // Field val$description:Ljava/lang/String;
      27: aload_0
      28: aload_1
      29: invokespecial #6                  // Method org/apache/hadoop/hbase/master/MasterCoprocessorHost$MasterObserverOperation."<init>":(Lorg/apache/hadoop/hbase/master/MasterCoprocessorHost;)V
      32: return

  public void call(org.apache.hadoop.hbase.coprocessor.MasterObserver) throws java.io.IOException;
    Code:
       0: aload_1
       1: aload_0
       2: aload_0
       3: getfield      #2                  // Field val$namespace:Ljava/lang/String;
       6: aload_0
       7: getfield      #3                  // Field val$tableName:Lorg/apache/hadoop/hbase/TableName;
      10: aload_0
      11: getfield      #4                  // Field val$regionInfos:[Lorg/apache/hadoop/hbase/client/RegionInfo;
      14: aload_0
      15: getfield      #5                  // Field val$description:Ljava/lang/String;
      18: invokeinterface #7,  6            // InterfaceMethod org/apache/hadoop/hbase/coprocessor/MasterObserver.preRequestLock:(Lorg/apache/hadoop/hbase/coprocessor/ObserverContext;Ljava/lang/String;Lorg/apache/hadoop/hbase/TableName;[Lorg/apache/hadoop/hbase/client/RegionInfo;Ljava/lang/String;)V
      23: return

  public void call(java.lang.Object) throws java.io.IOException;
    Code:
       0: aload_0
       1: aload_1
       2: checkcast     #8                  // class org/apache/hadoop/hbase/coprocessor/MasterObserver
       5: invokevirtual #9                  // Method call:(Lorg/apache/hadoop/hbase/coprocessor/MasterObserver;)V
       8: return
}
