Compiled from "MasterCoprocessorHost.java"
class org.apache.hadoop.hbase.master.MasterCoprocessorHost$166 extends org.apache.hadoop.hbase.master.MasterCoprocessorHost$MasterObserverOperation {
  final java.lang.String val$userName;

  final java.lang.String val$namespace;

  final org.apache.hadoop.hbase.TableName val$tableName;

  final byte[] val$family;

  final byte[] val$qualifier;

  final org.apache.hadoop.hbase.master.MasterCoprocessorHost this$0;

  org.apache.hadoop.hbase.master.MasterCoprocessorHost$166(org.apache.hadoop.hbase.master.MasterCoprocessorHost, java.lang.String, java.lang.String, org.apache.hadoop.hbase.TableName, byte[], byte[]);
    Code:
       0: aload_0
       1: aload_1
       2: putfield      #1                  // Field this$0:Lorg/apache/hadoop/hbase/master/MasterCoprocessorHost;
       5: aload_0
       6: aload_2
       7: putfield      #2                  // Field val$userName:Ljava/lang/String;
      10: aload_0
      11: aload_3
      12: putfield      #3                  // Field val$namespace:Ljava/lang/String;
      15: aload_0
      16: aload         4
      18: putfield      #4                  // Field val$tableName:Lorg/apache/hadoop/hbase/TableName;
      21: aload_0
      22: aload         5
      24: putfield      #5                  // Field val$family:[B
      27: aload_0
      28: aload         6
      30: putfield      #6                  // Field val$qualifier:[B
      33: aload_0
      34: aload_1
      35: invokespecial #7                  // Method org/apache/hadoop/hbase/master/MasterCoprocessorHost$MasterObserverOperation."<init>":(Lorg/apache/hadoop/hbase/master/MasterCoprocessorHost;)V
      38: return

  public void call(org.apache.hadoop.hbase.coprocessor.MasterObserver) throws java.io.IOException;
    Code:
       0: aload_1
       1: aload_0
       2: aload_0
       3: getfield      #2                  // Field val$userName:Ljava/lang/String;
       6: aload_0
       7: getfield      #3                  // Field val$namespace:Ljava/lang/String;
      10: aload_0
      11: getfield      #4                  // Field val$tableName:Lorg/apache/hadoop/hbase/TableName;
      14: aload_0
      15: getfield      #5                  // Field val$family:[B
      18: aload_0
      19: getfield      #6                  // Field val$qualifier:[B
      22: invokeinterface #8,  7            // InterfaceMethod org/apache/hadoop/hbase/coprocessor/MasterObserver.postGetUserPermissions:(Lorg/apache/hadoop/hbase/coprocessor/ObserverContext;Ljava/lang/String;Ljava/lang/String;Lorg/apache/hadoop/hbase/TableName;[B[B)V
      27: return

  public void call(java.lang.Object) throws java.io.IOException;
    Code:
       0: aload_0
       1: aload_1
       2: checkcast     #9                  // class org/apache/hadoop/hbase/coprocessor/MasterObserver
       5: invokevirtual #10                 // Method call:(Lorg/apache/hadoop/hbase/coprocessor/MasterObserver;)V
       8: return
}
