Compiled from "MasterProtos.java"
final class org.apache.hadoop.hbase.shaded.protobuf.generated.MasterProtos$HbckService$2 implements org.apache.hbase.thirdparty.com.google.protobuf.BlockingService {
  final org.apache.hadoop.hbase.shaded.protobuf.generated.MasterProtos$HbckService$BlockingInterface val$impl;

  org.apache.hadoop.hbase.shaded.protobuf.generated.MasterProtos$HbckService$2(org.apache.hadoop.hbase.shaded.protobuf.generated.MasterProtos$HbckService$BlockingInterface);
    Code:
       0: aload_0
       1: aload_1
       2: putfield      #1                  // Field val$impl:Lorg/apache/hadoop/hbase/shaded/protobuf/generated/MasterProtos$HbckService$BlockingInterface;
       5: aload_0
       6: invokespecial #2                  // Method java/lang/Object."<init>":()V
       9: return

  public final org.apache.hbase.thirdparty.com.google.protobuf.Descriptors$ServiceDescriptor getDescriptorForType();
    Code:
       0: invokestatic  #3                  // Method org/apache/hadoop/hbase/shaded/protobuf/generated/MasterProtos$HbckService.getDescriptor:()Lorg/apache/hbase/thirdparty/com/google/protobuf/Descriptors$ServiceDescriptor;
       3: areturn

  public final org.apache.hbase.thirdparty.com.google.protobuf.Message callBlockingMethod(org.apache.hbase.thirdparty.com.google.protobuf.Descriptors$MethodDescriptor, org.apache.hbase.thirdparty.com.google.protobuf.RpcController, org.apache.hbase.thirdparty.com.google.protobuf.Message) throws org.apache.hbase.thirdparty.com.google.protobuf.ServiceException;
    Code:
       0: aload_1
       1: invokevirtual #4                  // Method org/apache/hbase/thirdparty/com/google/protobuf/Descriptors$MethodDescriptor.getService:()Lorg/apache/hbase/thirdparty/com/google/protobuf/Descriptors$ServiceDescriptor;
       4: invokestatic  #3                  // Method org/apache/hadoop/hbase/shaded/protobuf/generated/MasterProtos$HbckService.getDescriptor:()Lorg/apache/hbase/thirdparty/com/google/protobuf/Descriptors$ServiceDescriptor;
       7: if_acmpeq     20
      10: new           #5                  // class java/lang/IllegalArgumentException
      13: dup
      14: ldc           #6                  // String Service.callBlockingMethod() given method descriptor for wrong service type.
      16: invokespecial #7                  // Method java/lang/IllegalArgumentException."<init>":(Ljava/lang/String;)V
      19: athrow
      20: aload_1
      21: invokevirtual #8                  // Method org/apache/hbase/thirdparty/com/google/protobuf/Descriptors$MethodDescriptor.getIndex:()I
      24: tableswitch   { // 0 to 5
                     0: 64
                     1: 79
                     2: 94
                     3: 109
                     4: 124
                     5: 139
               default: 154
          }
      64: aload_0
      65: getfield      #1                  // Field val$impl:Lorg/apache/hadoop/hbase/shaded/protobuf/generated/MasterProtos$HbckService$BlockingInterface;
      68: aload_2
      69: aload_3
      70: checkcast     #9                  // class org/apache/hadoop/hbase/shaded/protobuf/generated/MasterProtos$SetTableStateInMetaRequest
      73: invokeinterface #10,  3           // InterfaceMethod org/apache/hadoop/hbase/shaded/protobuf/generated/MasterProtos$HbckService$BlockingInterface.setTableStateInMeta:(Lorg/apache/hbase/thirdparty/com/google/protobuf/RpcController;Lorg/apache/hadoop/hbase/shaded/protobuf/generated/MasterProtos$SetTableStateInMetaRequest;)Lorg/apache/hadoop/hbase/shaded/protobuf/generated/MasterProtos$GetTableStateResponse;
      78: areturn
      79: aload_0
      80: getfield      #1                  // Field val$impl:Lorg/apache/hadoop/hbase/shaded/protobuf/generated/MasterProtos$HbckService$BlockingInterface;
      83: aload_2
      84: aload_3
      85: checkcast     #11                 // class org/apache/hadoop/hbase/shaded/protobuf/generated/MasterProtos$AssignsRequest
      88: invokeinterface #12,  3           // InterfaceMethod org/apache/hadoop/hbase/shaded/protobuf/generated/MasterProtos$HbckService$BlockingInterface.assigns:(Lorg/apache/hbase/thirdparty/com/google/protobuf/RpcController;Lorg/apache/hadoop/hbase/shaded/protobuf/generated/MasterProtos$AssignsRequest;)Lorg/apache/hadoop/hbase/shaded/protobuf/generated/MasterProtos$AssignsResponse;
      93: areturn
      94: aload_0
      95: getfield      #1                  // Field val$impl:Lorg/apache/hadoop/hbase/shaded/protobuf/generated/MasterProtos$HbckService$BlockingInterface;
      98: aload_2
      99: aload_3
     100: checkcast     #13                 // class org/apache/hadoop/hbase/shaded/protobuf/generated/MasterProtos$UnassignsRequest
     103: invokeinterface #14,  3           // InterfaceMethod org/apache/hadoop/hbase/shaded/protobuf/generated/MasterProtos$HbckService$BlockingInterface.unassigns:(Lorg/apache/hbase/thirdparty/com/google/protobuf/RpcController;Lorg/apache/hadoop/hbase/shaded/protobuf/generated/MasterProtos$UnassignsRequest;)Lorg/apache/hadoop/hbase/shaded/protobuf/generated/MasterProtos$UnassignsResponse;
     108: areturn
     109: aload_0
     110: getfield      #1                  // Field val$impl:Lorg/apache/hadoop/hbase/shaded/protobuf/generated/MasterProtos$HbckService$BlockingInterface;
     113: aload_2
     114: aload_3
     115: checkcast     #15                 // class org/apache/hadoop/hbase/shaded/protobuf/generated/MasterProtos$BypassProcedureRequest
     118: invokeinterface #16,  3           // InterfaceMethod org/apache/hadoop/hbase/shaded/protobuf/generated/MasterProtos$HbckService$BlockingInterface.bypassProcedure:(Lorg/apache/hbase/thirdparty/com/google/protobuf/RpcController;Lorg/apache/hadoop/hbase/shaded/protobuf/generated/MasterProtos$BypassProcedureRequest;)Lorg/apache/hadoop/hbase/shaded/protobuf/generated/MasterProtos$BypassProcedureResponse;
     123: areturn
     124: aload_0
     125: getfield      #1                  // Field val$impl:Lorg/apache/hadoop/hbase/shaded/protobuf/generated/MasterProtos$HbckService$BlockingInterface;
     128: aload_2
     129: aload_3
     130: checkcast     #17                 // class org/apache/hadoop/hbase/shaded/protobuf/generated/MasterProtos$ScheduleServerCrashProcedureRequest
     133: invokeinterface #18,  3           // InterfaceMethod org/apache/hadoop/hbase/shaded/protobuf/generated/MasterProtos$HbckService$BlockingInterface.scheduleServerCrashProcedure:(Lorg/apache/hbase/thirdparty/com/google/protobuf/RpcController;Lorg/apache/hadoop/hbase/shaded/protobuf/generated/MasterProtos$ScheduleServerCrashProcedureRequest;)Lorg/apache/hadoop/hbase/shaded/protobuf/generated/MasterProtos$ScheduleServerCrashProcedureResponse;
     138: areturn
     139: aload_0
     140: getfield      #1                  // Field val$impl:Lorg/apache/hadoop/hbase/shaded/protobuf/generated/MasterProtos$HbckService$BlockingInterface;
     143: aload_2
     144: aload_3
     145: checkcast     #19                 // class org/apache/hadoop/hbase/shaded/protobuf/generated/MasterProtos$GetFailedSplitMergeLegacyRegionsRequest
     148: invokeinterface #20,  3           // InterfaceMethod org/apache/hadoop/hbase/shaded/protobuf/generated/MasterProtos$HbckService$BlockingInterface.getFailedSplitMergeLegacyRegions:(Lorg/apache/hbase/thirdparty/com/google/protobuf/RpcController;Lorg/apache/hadoop/hbase/shaded/protobuf/generated/MasterProtos$GetFailedSplitMergeLegacyRegionsRequest;)Lorg/apache/hadoop/hbase/shaded/protobuf/generated/MasterProtos$GetFailedSplitMergeLegacyRegionsResponse;
     153: areturn
     154: new           #21                 // class java/lang/AssertionError
     157: dup
     158: ldc           #22                 // String Can't get here.
     160: invokespecial #23                 // Method java/lang/AssertionError."<init>":(Ljava/lang/Object;)V
     163: athrow

  public final org.apache.hbase.thirdparty.com.google.protobuf.Message getRequestPrototype(org.apache.hbase.thirdparty.com.google.protobuf.Descriptors$MethodDescriptor);
    Code:
       0: aload_1
       1: invokevirtual #4                  // Method org/apache/hbase/thirdparty/com/google/protobuf/Descriptors$MethodDescriptor.getService:()Lorg/apache/hbase/thirdparty/com/google/protobuf/Descriptors$ServiceDescriptor;
       4: invokestatic  #3                  // Method org/apache/hadoop/hbase/shaded/protobuf/generated/MasterProtos$HbckService.getDescriptor:()Lorg/apache/hbase/thirdparty/com/google/protobuf/Descriptors$ServiceDescriptor;
       7: if_acmpeq     20
      10: new           #5                  // class java/lang/IllegalArgumentException
      13: dup
      14: ldc           #24                 // String Service.getRequestPrototype() given method descriptor for wrong service type.
      16: invokespecial #7                  // Method java/lang/IllegalArgumentException."<init>":(Ljava/lang/String;)V
      19: athrow
      20: aload_1
      21: invokevirtual #8                  // Method org/apache/hbase/thirdparty/com/google/protobuf/Descriptors$MethodDescriptor.getIndex:()I
      24: tableswitch   { // 0 to 5
                     0: 64
                     1: 68
                     2: 72
                     3: 76
                     4: 80
                     5: 84
               default: 88
          }
      64: invokestatic  #25                 // Method org/apache/hadoop/hbase/shaded/protobuf/generated/MasterProtos$SetTableStateInMetaRequest.getDefaultInstance:()Lorg/apache/hadoop/hbase/shaded/protobuf/generated/MasterProtos$SetTableStateInMetaRequest;
      67: areturn
      68: invokestatic  #26                 // Method org/apache/hadoop/hbase/shaded/protobuf/generated/MasterProtos$AssignsRequest.getDefaultInstance:()Lorg/apache/hadoop/hbase/shaded/protobuf/generated/MasterProtos$AssignsRequest;
      71: areturn
      72: invokestatic  #27                 // Method org/apache/hadoop/hbase/shaded/protobuf/generated/MasterProtos$UnassignsRequest.getDefaultInstance:()Lorg/apache/hadoop/hbase/shaded/protobuf/generated/MasterProtos$UnassignsRequest;
      75: areturn
      76: invokestatic  #28                 // Method org/apache/hadoop/hbase/shaded/protobuf/generated/MasterProtos$BypassProcedureRequest.getDefaultInstance:()Lorg/apache/hadoop/hbase/shaded/protobuf/generated/MasterProtos$BypassProcedureRequest;
      79: areturn
      80: invokestatic  #29                 // Method org/apache/hadoop/hbase/shaded/protobuf/generated/MasterProtos$ScheduleServerCrashProcedureRequest.getDefaultInstance:()Lorg/apache/hadoop/hbase/shaded/protobuf/generated/MasterProtos$ScheduleServerCrashProcedureRequest;
      83: areturn
      84: invokestatic  #30                 // Method org/apache/hadoop/hbase/shaded/protobuf/generated/MasterProtos$GetFailedSplitMergeLegacyRegionsRequest.getDefaultInstance:()Lorg/apache/hadoop/hbase/shaded/protobuf/generated/MasterProtos$GetFailedSplitMergeLegacyRegionsRequest;
      87: areturn
      88: new           #21                 // class java/lang/AssertionError
      91: dup
      92: ldc           #22                 // String Can't get here.
      94: invokespecial #23                 // Method java/lang/AssertionError."<init>":(Ljava/lang/Object;)V
      97: athrow

  public final org.apache.hbase.thirdparty.com.google.protobuf.Message getResponsePrototype(org.apache.hbase.thirdparty.com.google.protobuf.Descriptors$MethodDescriptor);
    Code:
       0: aload_1
       1: invokevirtual #4                  // Method org/apache/hbase/thirdparty/com/google/protobuf/Descriptors$MethodDescriptor.getService:()Lorg/apache/hbase/thirdparty/com/google/protobuf/Descriptors$ServiceDescriptor;
       4: invokestatic  #3                  // Method org/apache/hadoop/hbase/shaded/protobuf/generated/MasterProtos$HbckService.getDescriptor:()Lorg/apache/hbase/thirdparty/com/google/protobuf/Descriptors$ServiceDescriptor;
       7: if_acmpeq     20
      10: new           #5                  // class java/lang/IllegalArgumentException
      13: dup
      14: ldc           #31                 // String Service.getResponsePrototype() given method descriptor for wrong service type.
      16: invokespecial #7                  // Method java/lang/IllegalArgumentException."<init>":(Ljava/lang/String;)V
      19: athrow
      20: aload_1
      21: invokevirtual #8                  // Method org/apache/hbase/thirdparty/com/google/protobuf/Descriptors$MethodDescriptor.getIndex:()I
      24: tableswitch   { // 0 to 5
                     0: 64
                     1: 68
                     2: 72
                     3: 76
                     4: 80
                     5: 84
               default: 88
          }
      64: invokestatic  #32                 // Method org/apache/hadoop/hbase/shaded/protobuf/generated/MasterProtos$GetTableStateResponse.getDefaultInstance:()Lorg/apache/hadoop/hbase/shaded/protobuf/generated/MasterProtos$GetTableStateResponse;
      67: areturn
      68: invokestatic  #33                 // Method org/apache/hadoop/hbase/shaded/protobuf/generated/MasterProtos$AssignsResponse.getDefaultInstance:()Lorg/apache/hadoop/hbase/shaded/protobuf/generated/MasterProtos$AssignsResponse;
      71: areturn
      72: invokestatic  #34                 // Method org/apache/hadoop/hbase/shaded/protobuf/generated/MasterProtos$UnassignsResponse.getDefaultInstance:()Lorg/apache/hadoop/hbase/shaded/protobuf/generated/MasterProtos$UnassignsResponse;
      75: areturn
      76: invokestatic  #35                 // Method org/apache/hadoop/hbase/shaded/protobuf/generated/MasterProtos$BypassProcedureResponse.getDefaultInstance:()Lorg/apache/hadoop/hbase/shaded/protobuf/generated/MasterProtos$BypassProcedureResponse;
      79: areturn
      80: invokestatic  #36                 // Method org/apache/hadoop/hbase/shaded/protobuf/generated/MasterProtos$ScheduleServerCrashProcedureResponse.getDefaultInstance:()Lorg/apache/hadoop/hbase/shaded/protobuf/generated/MasterProtos$ScheduleServerCrashProcedureResponse;
      83: areturn
      84: invokestatic  #37                 // Method org/apache/hadoop/hbase/shaded/protobuf/generated/MasterProtos$GetFailedSplitMergeLegacyRegionsResponse.getDefaultInstance:()Lorg/apache/hadoop/hbase/shaded/protobuf/generated/MasterProtos$GetFailedSplitMergeLegacyRegionsResponse;
      87: areturn
      88: new           #21                 // class java/lang/AssertionError
      91: dup
      92: ldc           #22                 // String Can't get here.
      94: invokespecial #23                 // Method java/lang/AssertionError."<init>":(Ljava/lang/Object;)V
      97: athrow
}
