Compiled from "MasterProcedureTestingUtility.java"
final class org.apache.hadoop.hbase.master.procedure.MasterProcedureTestingUtility$2 implements java.util.concurrent.Callable<java.lang.Void> {
  final org.apache.hadoop.hbase.master.procedure.MasterProcedureEnv val$env;

  final org.apache.hadoop.hbase.procedure2.ProcedureExecutor val$procExec;

  org.apache.hadoop.hbase.master.procedure.MasterProcedureTestingUtility$2(org.apache.hadoop.hbase.master.procedure.MasterProcedureEnv, org.apache.hadoop.hbase.procedure2.ProcedureExecutor);
    Code:
       0: aload_0
       1: aload_1
       2: putfield      #1                  // Field val$env:Lorg/apache/hadoop/hbase/master/procedure/MasterProcedureEnv;
       5: aload_0
       6: aload_2
       7: putfield      #2                  // Field val$procExec:Lorg/apache/hadoop/hbase/procedure2/ProcedureExecutor;
      10: aload_0
      11: invokespecial #3                  // Method java/lang/Object."<init>":()V
      14: return

  public java.lang.Void call() throws java.lang.Exception;
    Code:
       0: aload_0
       1: getfield      #1                  // Field val$env:Lorg/apache/hadoop/hbase/master/procedure/MasterProcedureEnv;
       4: invokevirtual #4                  // Method org/apache/hadoop/hbase/master/procedure/MasterProcedureEnv.getAssignmentManager:()Lorg/apache/hadoop/hbase/master/assignment/AssignmentManager;
       7: astore_1
       8: aload_1
       9: invokevirtual #5                  // Method org/apache/hadoop/hbase/master/assignment/AssignmentManager.start:()V
      12: aload_1
      13: aload_0
      14: getfield      #2                  // Field val$procExec:Lorg/apache/hadoop/hbase/procedure2/ProcedureExecutor;
      17: invokevirtual #6                  // Method org/apache/hadoop/hbase/procedure2/ProcedureExecutor.getActiveProceduresNoCopy:()Ljava/util/Collection;
      20: invokeinterface #7,  1            // InterfaceMethod java/util/Collection.stream:()Ljava/util/stream/Stream;
      25: invokedynamic #8,  0              // InvokeDynamic #0:test:()Ljava/util/function/Predicate;
      30: invokeinterface #9,  2            // InterfaceMethod java/util/stream/Stream.filter:(Ljava/util/function/Predicate;)Ljava/util/stream/Stream;
      35: invokedynamic #10,  0             // InvokeDynamic #1:test:()Ljava/util/function/Predicate;
      40: invokeinterface #9,  2            // InterfaceMethod java/util/stream/Stream.filter:(Ljava/util/function/Predicate;)Ljava/util/stream/Stream;
      45: invokedynamic #11,  0             // InvokeDynamic #2:apply:()Ljava/util/function/Function;
      50: invokeinterface #12,  2           // InterfaceMethod java/util/stream/Stream.map:(Ljava/util/function/Function;)Ljava/util/stream/Stream;
      55: invokestatic  #13                 // Method java/util/stream/Collectors.toList:()Ljava/util/stream/Collector;
      58: invokeinterface #14,  2           // InterfaceMethod java/util/stream/Stream.collect:(Ljava/util/stream/Collector;)Ljava/lang/Object;
      63: checkcast     #15                 // class java/util/List
      66: invokevirtual #16                 // Method org/apache/hadoop/hbase/master/assignment/AssignmentManager.setupRIT:(Ljava/util/List;)V
      69: aconst_null
      70: areturn

  public java.lang.Object call() throws java.lang.Exception;
    Code:
       0: aload_0
       1: invokevirtual #17                 // Method call:()Ljava/lang/Void;
       4: areturn
}
