Compiled from "MasterProcedureProtos.java"
public final class org.apache.hadoop.hbase.shaded.protobuf.generated.MasterProcedureProtos$RestoreSnapshotStateData extends org.apache.hbase.thirdparty.com.google.protobuf.GeneratedMessageV3 implements org.apache.hadoop.hbase.shaded.protobuf.generated.MasterProcedureProtos$RestoreSnapshotStateDataOrBuilder {
  public static final int USER_INFO_FIELD_NUMBER;

  public static final int SNAPSHOT_FIELD_NUMBER;

  public static final int MODIFIED_TABLE_SCHEMA_FIELD_NUMBER;

  public static final int REGION_INFO_FOR_RESTORE_FIELD_NUMBER;

  public static final int REGION_INFO_FOR_REMOVE_FIELD_NUMBER;

  public static final int REGION_INFO_FOR_ADD_FIELD_NUMBER;

  public static final int PARENT_TO_CHILD_REGIONS_PAIR_LIST_FIELD_NUMBER;

  public static final org.apache.hbase.thirdparty.com.google.protobuf.Parser<org.apache.hadoop.hbase.shaded.protobuf.generated.MasterProcedureProtos$RestoreSnapshotStateData> PARSER;

  public final org.apache.hbase.thirdparty.com.google.protobuf.UnknownFieldSet getUnknownFields();
    Code:
       0: aload_0
       1: getfield      #2                  // Field unknownFields:Lorg/apache/hbase/thirdparty/com/google/protobuf/UnknownFieldSet;
       4: areturn

  public static final org.apache.hbase.thirdparty.com.google.protobuf.Descriptors$Descriptor getDescriptor();
    Code:
       0: invokestatic  #51                 // Method org/apache/hadoop/hbase/shaded/protobuf/generated/MasterProcedureProtos.access$13900:()Lorg/apache/hbase/thirdparty/com/google/protobuf/Descriptors$Descriptor;
       3: areturn

  protected org.apache.hbase.thirdparty.com.google.protobuf.GeneratedMessageV3$FieldAccessorTable internalGetFieldAccessorTable();
    Code:
       0: invokestatic  #52                 // Method org/apache/hadoop/hbase/shaded/protobuf/generated/MasterProcedureProtos.access$14000:()Lorg/apache/hbase/thirdparty/com/google/protobuf/GeneratedMessageV3$FieldAccessorTable;
       3: ldc           #53                 // class org/apache/hadoop/hbase/shaded/protobuf/generated/MasterProcedureProtos$RestoreSnapshotStateData
       5: ldc           #54                 // class org/apache/hadoop/hbase/shaded/protobuf/generated/MasterProcedureProtos$RestoreSnapshotStateData$Builder
       7: invokevirtual #55                 // Method org/apache/hbase/thirdparty/com/google/protobuf/GeneratedMessageV3$FieldAccessorTable.ensureFieldAccessorsInitialized:(Ljava/lang/Class;Ljava/lang/Class;)Lorg/apache/hbase/thirdparty/com/google/protobuf/GeneratedMessageV3$FieldAccessorTable;
      10: areturn

  public boolean hasUserInfo();
    Code:
       0: aload_0
       1: getfield      #4                  // Field bitField0_:I
       4: iconst_1
       5: iand
       6: iconst_1
       7: if_icmpne     14
      10: iconst_1
      11: goto          15
      14: iconst_0
      15: ireturn

  public org.apache.hadoop.hbase.shaded.protobuf.generated.RPCProtos$UserInformation getUserInfo();
    Code:
       0: aload_0
       1: getfield      #11                 // Field userInfo_:Lorg/apache/hadoop/hbase/shaded/protobuf/generated/RPCProtos$UserInformation;
       4: ifnonnull     13
       7: invokestatic  #56                 // Method org/apache/hadoop/hbase/shaded/protobuf/generated/RPCProtos$UserInformation.getDefaultInstance:()Lorg/apache/hadoop/hbase/shaded/protobuf/generated/RPCProtos$UserInformation;
      10: goto          17
      13: aload_0
      14: getfield      #11                 // Field userInfo_:Lorg/apache/hadoop/hbase/shaded/protobuf/generated/RPCProtos$UserInformation;
      17: areturn

  public org.apache.hadoop.hbase.shaded.protobuf.generated.RPCProtos$UserInformationOrBuilder getUserInfoOrBuilder();
    Code:
       0: aload_0
       1: getfield      #11                 // Field userInfo_:Lorg/apache/hadoop/hbase/shaded/protobuf/generated/RPCProtos$UserInformation;
       4: ifnonnull     13
       7: invokestatic  #56                 // Method org/apache/hadoop/hbase/shaded/protobuf/generated/RPCProtos$UserInformation.getDefaultInstance:()Lorg/apache/hadoop/hbase/shaded/protobuf/generated/RPCProtos$UserInformation;
      10: goto          17
      13: aload_0
      14: getfield      #11                 // Field userInfo_:Lorg/apache/hadoop/hbase/shaded/protobuf/generated/RPCProtos$UserInformation;
      17: areturn

  public boolean hasSnapshot();
    Code:
       0: aload_0
       1: getfield      #4                  // Field bitField0_:I
       4: iconst_2
       5: iand
       6: iconst_2
       7: if_icmpne     14
      10: iconst_1
      11: goto          15
      14: iconst_0
      15: ireturn

  public org.apache.hadoop.hbase.shaded.protobuf.generated.SnapshotProtos$SnapshotDescription getSnapshot();
    Code:
       0: aload_0
       1: getfield      #10                 // Field snapshot_:Lorg/apache/hadoop/hbase/shaded/protobuf/generated/SnapshotProtos$SnapshotDescription;
       4: ifnonnull     13
       7: invokestatic  #57                 // Method org/apache/hadoop/hbase/shaded/protobuf/generated/SnapshotProtos$SnapshotDescription.getDefaultInstance:()Lorg/apache/hadoop/hbase/shaded/protobuf/generated/SnapshotProtos$SnapshotDescription;
      10: goto          17
      13: aload_0
      14: getfield      #10                 // Field snapshot_:Lorg/apache/hadoop/hbase/shaded/protobuf/generated/SnapshotProtos$SnapshotDescription;
      17: areturn

  public org.apache.hadoop.hbase.shaded.protobuf.generated.SnapshotProtos$SnapshotDescriptionOrBuilder getSnapshotOrBuilder();
    Code:
       0: aload_0
       1: getfield      #10                 // Field snapshot_:Lorg/apache/hadoop/hbase/shaded/protobuf/generated/SnapshotProtos$SnapshotDescription;
       4: ifnonnull     13
       7: invokestatic  #57                 // Method org/apache/hadoop/hbase/shaded/protobuf/generated/SnapshotProtos$SnapshotDescription.getDefaultInstance:()Lorg/apache/hadoop/hbase/shaded/protobuf/generated/SnapshotProtos$SnapshotDescription;
      10: goto          17
      13: aload_0
      14: getfield      #10                 // Field snapshot_:Lorg/apache/hadoop/hbase/shaded/protobuf/generated/SnapshotProtos$SnapshotDescription;
      17: areturn

  public boolean hasModifiedTableSchema();
    Code:
       0: aload_0
       1: getfield      #4                  // Field bitField0_:I
       4: iconst_4
       5: iand
       6: iconst_4
       7: if_icmpne     14
      10: iconst_1
      11: goto          15
      14: iconst_0
      15: ireturn

  public org.apache.hadoop.hbase.shaded.protobuf.generated.HBaseProtos$TableSchema getModifiedTableSchema();
    Code:
       0: aload_0
       1: getfield      #9                  // Field modifiedTableSchema_:Lorg/apache/hadoop/hbase/shaded/protobuf/generated/HBaseProtos$TableSchema;
       4: ifnonnull     13
       7: invokestatic  #58                 // Method org/apache/hadoop/hbase/shaded/protobuf/generated/HBaseProtos$TableSchema.getDefaultInstance:()Lorg/apache/hadoop/hbase/shaded/protobuf/generated/HBaseProtos$TableSchema;
      10: goto          17
      13: aload_0
      14: getfield      #9                  // Field modifiedTableSchema_:Lorg/apache/hadoop/hbase/shaded/protobuf/generated/HBaseProtos$TableSchema;
      17: areturn

  public org.apache.hadoop.hbase.shaded.protobuf.generated.HBaseProtos$TableSchemaOrBuilder getModifiedTableSchemaOrBuilder();
    Code:
       0: aload_0
       1: getfield      #9                  // Field modifiedTableSchema_:Lorg/apache/hadoop/hbase/shaded/protobuf/generated/HBaseProtos$TableSchema;
       4: ifnonnull     13
       7: invokestatic  #58                 // Method org/apache/hadoop/hbase/shaded/protobuf/generated/HBaseProtos$TableSchema.getDefaultInstance:()Lorg/apache/hadoop/hbase/shaded/protobuf/generated/HBaseProtos$TableSchema;
      10: goto          17
      13: aload_0
      14: getfield      #9                  // Field modifiedTableSchema_:Lorg/apache/hadoop/hbase/shaded/protobuf/generated/HBaseProtos$TableSchema;
      17: areturn

  public java.util.List<org.apache.hadoop.hbase.shaded.protobuf.generated.HBaseProtos$RegionInfo> getRegionInfoForRestoreList();
    Code:
       0: aload_0
       1: getfield      #8                  // Field regionInfoForRestore_:Ljava/util/List;
       4: areturn

  public java.util.List<? extends org.apache.hadoop.hbase.shaded.protobuf.generated.HBaseProtos$RegionInfoOrBuilder> getRegionInfoForRestoreOrBuilderList();
    Code:
       0: aload_0
       1: getfield      #8                  // Field regionInfoForRestore_:Ljava/util/List;
       4: areturn

  public int getRegionInfoForRestoreCount();
    Code:
       0: aload_0
       1: getfield      #8                  // Field regionInfoForRestore_:Ljava/util/List;
       4: invokeinterface #59,  1           // InterfaceMethod java/util/List.size:()I
       9: ireturn

  public org.apache.hadoop.hbase.shaded.protobuf.generated.HBaseProtos$RegionInfo getRegionInfoForRestore(int);
    Code:
       0: aload_0
       1: getfield      #8                  // Field regionInfoForRestore_:Ljava/util/List;
       4: iload_1
       5: invokeinterface #60,  2           // InterfaceMethod java/util/List.get:(I)Ljava/lang/Object;
      10: checkcast     #61                 // class org/apache/hadoop/hbase/shaded/protobuf/generated/HBaseProtos$RegionInfo
      13: areturn

  public org.apache.hadoop.hbase.shaded.protobuf.generated.HBaseProtos$RegionInfoOrBuilder getRegionInfoForRestoreOrBuilder(int);
    Code:
       0: aload_0
       1: getfield      #8                  // Field regionInfoForRestore_:Ljava/util/List;
       4: iload_1
       5: invokeinterface #60,  2           // InterfaceMethod java/util/List.get:(I)Ljava/lang/Object;
      10: checkcast     #62                 // class org/apache/hadoop/hbase/shaded/protobuf/generated/HBaseProtos$RegionInfoOrBuilder
      13: areturn

  public java.util.List<org.apache.hadoop.hbase.shaded.protobuf.generated.HBaseProtos$RegionInfo> getRegionInfoForRemoveList();
    Code:
       0: aload_0
       1: getfield      #7                  // Field regionInfoForRemove_:Ljava/util/List;
       4: areturn

  public java.util.List<? extends org.apache.hadoop.hbase.shaded.protobuf.generated.HBaseProtos$RegionInfoOrBuilder> getRegionInfoForRemoveOrBuilderList();
    Code:
       0: aload_0
       1: getfield      #7                  // Field regionInfoForRemove_:Ljava/util/List;
       4: areturn

  public int getRegionInfoForRemoveCount();
    Code:
       0: aload_0
       1: getfield      #7                  // Field regionInfoForRemove_:Ljava/util/List;
       4: invokeinterface #59,  1           // InterfaceMethod java/util/List.size:()I
       9: ireturn

  public org.apache.hadoop.hbase.shaded.protobuf.generated.HBaseProtos$RegionInfo getRegionInfoForRemove(int);
    Code:
       0: aload_0
       1: getfield      #7                  // Field regionInfoForRemove_:Ljava/util/List;
       4: iload_1
       5: invokeinterface #60,  2           // InterfaceMethod java/util/List.get:(I)Ljava/lang/Object;
      10: checkcast     #61                 // class org/apache/hadoop/hbase/shaded/protobuf/generated/HBaseProtos$RegionInfo
      13: areturn

  public org.apache.hadoop.hbase.shaded.protobuf.generated.HBaseProtos$RegionInfoOrBuilder getRegionInfoForRemoveOrBuilder(int);
    Code:
       0: aload_0
       1: getfield      #7                  // Field regionInfoForRemove_:Ljava/util/List;
       4: iload_1
       5: invokeinterface #60,  2           // InterfaceMethod java/util/List.get:(I)Ljava/lang/Object;
      10: checkcast     #62                 // class org/apache/hadoop/hbase/shaded/protobuf/generated/HBaseProtos$RegionInfoOrBuilder
      13: areturn

  public java.util.List<org.apache.hadoop.hbase.shaded.protobuf.generated.HBaseProtos$RegionInfo> getRegionInfoForAddList();
    Code:
       0: aload_0
       1: getfield      #6                  // Field regionInfoForAdd_:Ljava/util/List;
       4: areturn

  public java.util.List<? extends org.apache.hadoop.hbase.shaded.protobuf.generated.HBaseProtos$RegionInfoOrBuilder> getRegionInfoForAddOrBuilderList();
    Code:
       0: aload_0
       1: getfield      #6                  // Field regionInfoForAdd_:Ljava/util/List;
       4: areturn

  public int getRegionInfoForAddCount();
    Code:
       0: aload_0
       1: getfield      #6                  // Field regionInfoForAdd_:Ljava/util/List;
       4: invokeinterface #59,  1           // InterfaceMethod java/util/List.size:()I
       9: ireturn

  public org.apache.hadoop.hbase.shaded.protobuf.generated.HBaseProtos$RegionInfo getRegionInfoForAdd(int);
    Code:
       0: aload_0
       1: getfield      #6                  // Field regionInfoForAdd_:Ljava/util/List;
       4: iload_1
       5: invokeinterface #60,  2           // InterfaceMethod java/util/List.get:(I)Ljava/lang/Object;
      10: checkcast     #61                 // class org/apache/hadoop/hbase/shaded/protobuf/generated/HBaseProtos$RegionInfo
      13: areturn

  public org.apache.hadoop.hbase.shaded.protobuf.generated.HBaseProtos$RegionInfoOrBuilder getRegionInfoForAddOrBuilder(int);
    Code:
       0: aload_0
       1: getfield      #6                  // Field regionInfoForAdd_:Ljava/util/List;
       4: iload_1
       5: invokeinterface #60,  2           // InterfaceMethod java/util/List.get:(I)Ljava/lang/Object;
      10: checkcast     #62                 // class org/apache/hadoop/hbase/shaded/protobuf/generated/HBaseProtos$RegionInfoOrBuilder
      13: areturn

  public java.util.List<org.apache.hadoop.hbase.shaded.protobuf.generated.MasterProcedureProtos$RestoreParentToChildRegionsPair> getParentToChildRegionsPairListList();
    Code:
       0: aload_0
       1: getfield      #5                  // Field parentToChildRegionsPairList_:Ljava/util/List;
       4: areturn

  public java.util.List<? extends org.apache.hadoop.hbase.shaded.protobuf.generated.MasterProcedureProtos$RestoreParentToChildRegionsPairOrBuilder> getParentToChildRegionsPairListOrBuilderList();
    Code:
       0: aload_0
       1: getfield      #5                  // Field parentToChildRegionsPairList_:Ljava/util/List;
       4: areturn

  public int getParentToChildRegionsPairListCount();
    Code:
       0: aload_0
       1: getfield      #5                  // Field parentToChildRegionsPairList_:Ljava/util/List;
       4: invokeinterface #59,  1           // InterfaceMethod java/util/List.size:()I
       9: ireturn

  public org.apache.hadoop.hbase.shaded.protobuf.generated.MasterProcedureProtos$RestoreParentToChildRegionsPair getParentToChildRegionsPairList(int);
    Code:
       0: aload_0
       1: getfield      #5                  // Field parentToChildRegionsPairList_:Ljava/util/List;
       4: iload_1
       5: invokeinterface #60,  2           // InterfaceMethod java/util/List.get:(I)Ljava/lang/Object;
      10: checkcast     #63                 // class org/apache/hadoop/hbase/shaded/protobuf/generated/MasterProcedureProtos$RestoreParentToChildRegionsPair
      13: areturn

  public org.apache.hadoop.hbase.shaded.protobuf.generated.MasterProcedureProtos$RestoreParentToChildRegionsPairOrBuilder getParentToChildRegionsPairListOrBuilder(int);
    Code:
       0: aload_0
       1: getfield      #5                  // Field parentToChildRegionsPairList_:Ljava/util/List;
       4: iload_1
       5: invokeinterface #60,  2           // InterfaceMethod java/util/List.get:(I)Ljava/lang/Object;
      10: checkcast     #64                 // class org/apache/hadoop/hbase/shaded/protobuf/generated/MasterProcedureProtos$RestoreParentToChildRegionsPairOrBuilder
      13: areturn

  public final boolean isInitialized();
    Code:
       0: aload_0
       1: getfield      #14                 // Field memoizedIsInitialized:B
       4: istore_1
       5: iload_1
       6: iconst_1
       7: if_icmpne     12
      10: iconst_1
      11: ireturn
      12: iload_1
      13: ifne          18
      16: iconst_0
      17: ireturn
      18: aload_0
      19: invokevirtual #65                 // Method hasUserInfo:()Z
      22: ifne          32
      25: aload_0
      26: iconst_0
      27: putfield      #14                 // Field memoizedIsInitialized:B
      30: iconst_0
      31: ireturn
      32: aload_0
      33: invokevirtual #66                 // Method hasSnapshot:()Z
      36: ifne          46
      39: aload_0
      40: iconst_0
      41: putfield      #14                 // Field memoizedIsInitialized:B
      44: iconst_0
      45: ireturn
      46: aload_0
      47: invokevirtual #67                 // Method hasModifiedTableSchema:()Z
      50: ifne          60
      53: aload_0
      54: iconst_0
      55: putfield      #14                 // Field memoizedIsInitialized:B
      58: iconst_0
      59: ireturn
      60: aload_0
      61: invokevirtual #68                 // Method getUserInfo:()Lorg/apache/hadoop/hbase/shaded/protobuf/generated/RPCProtos$UserInformation;
      64: invokevirtual #69                 // Method org/apache/hadoop/hbase/shaded/protobuf/generated/RPCProtos$UserInformation.isInitialized:()Z
      67: ifne          77
      70: aload_0
      71: iconst_0
      72: putfield      #14                 // Field memoizedIsInitialized:B
      75: iconst_0
      76: ireturn
      77: aload_0
      78: invokevirtual #70                 // Method getSnapshot:()Lorg/apache/hadoop/hbase/shaded/protobuf/generated/SnapshotProtos$SnapshotDescription;
      81: invokevirtual #71                 // Method org/apache/hadoop/hbase/shaded/protobuf/generated/SnapshotProtos$SnapshotDescription.isInitialized:()Z
      84: ifne          94
      87: aload_0
      88: iconst_0
      89: putfield      #14                 // Field memoizedIsInitialized:B
      92: iconst_0
      93: ireturn
      94: aload_0
      95: invokevirtual #72                 // Method getModifiedTableSchema:()Lorg/apache/hadoop/hbase/shaded/protobuf/generated/HBaseProtos$TableSchema;
      98: invokevirtual #73                 // Method org/apache/hadoop/hbase/shaded/protobuf/generated/HBaseProtos$TableSchema.isInitialized:()Z
     101: ifne          111
     104: aload_0
     105: iconst_0
     106: putfield      #14                 // Field memoizedIsInitialized:B
     109: iconst_0
     110: ireturn
     111: iconst_0
     112: istore_2
     113: iload_2
     114: aload_0
     115: invokevirtual #74                 // Method getRegionInfoForRestoreCount:()I
     118: if_icmpge     145
     121: aload_0
     122: iload_2
     123: invokevirtual #75                 // Method getRegionInfoForRestore:(I)Lorg/apache/hadoop/hbase/shaded/protobuf/generated/HBaseProtos$RegionInfo;
     126: invokevirtual #76                 // Method org/apache/hadoop/hbase/shaded/protobuf/generated/HBaseProtos$RegionInfo.isInitialized:()Z
     129: ifne          139
     132: aload_0
     133: iconst_0
     134: putfield      #14                 // Field memoizedIsInitialized:B
     137: iconst_0
     138: ireturn
     139: iinc          2, 1
     142: goto          113
     145: iconst_0
     146: istore_2
     147: iload_2
     148: aload_0
     149: invokevirtual #77                 // Method getRegionInfoForRemoveCount:()I
     152: if_icmpge     179
     155: aload_0
     156: iload_2
     157: invokevirtual #78                 // Method getRegionInfoForRemove:(I)Lorg/apache/hadoop/hbase/shaded/protobuf/generated/HBaseProtos$RegionInfo;
     160: invokevirtual #76                 // Method org/apache/hadoop/hbase/shaded/protobuf/generated/HBaseProtos$RegionInfo.isInitialized:()Z
     163: ifne          173
     166: aload_0
     167: iconst_0
     168: putfield      #14                 // Field memoizedIsInitialized:B
     171: iconst_0
     172: ireturn
     173: iinc          2, 1
     176: goto          147
     179: iconst_0
     180: istore_2
     181: iload_2
     182: aload_0
     183: invokevirtual #79                 // Method getRegionInfoForAddCount:()I
     186: if_icmpge     213
     189: aload_0
     190: iload_2
     191: invokevirtual #80                 // Method getRegionInfoForAdd:(I)Lorg/apache/hadoop/hbase/shaded/protobuf/generated/HBaseProtos$RegionInfo;
     194: invokevirtual #76                 // Method org/apache/hadoop/hbase/shaded/protobuf/generated/HBaseProtos$RegionInfo.isInitialized:()Z
     197: ifne          207
     200: aload_0
     201: iconst_0
     202: putfield      #14                 // Field memoizedIsInitialized:B
     205: iconst_0
     206: ireturn
     207: iinc          2, 1
     210: goto          181
     213: iconst_0
     214: istore_2
     215: iload_2
     216: aload_0
     217: invokevirtual #81                 // Method getParentToChildRegionsPairListCount:()I
     220: if_icmpge     247
     223: aload_0
     224: iload_2
     225: invokevirtual #82                 // Method getParentToChildRegionsPairList:(I)Lorg/apache/hadoop/hbase/shaded/protobuf/generated/MasterProcedureProtos$RestoreParentToChildRegionsPair;
     228: invokevirtual #83                 // Method org/apache/hadoop/hbase/shaded/protobuf/generated/MasterProcedureProtos$RestoreParentToChildRegionsPair.isInitialized:()Z
     231: ifne          241
     234: aload_0
     235: iconst_0
     236: putfield      #14                 // Field memoizedIsInitialized:B
     239: iconst_0
     240: ireturn
     241: iinc          2, 1
     244: goto          215
     247: aload_0
     248: iconst_1
     249: putfield      #14                 // Field memoizedIsInitialized:B
     252: iconst_1
     253: ireturn

  public void writeTo(org.apache.hbase.thirdparty.com.google.protobuf.CodedOutputStream) throws java.io.IOException;
    Code:
       0: aload_0
       1: getfield      #4                  // Field bitField0_:I
       4: iconst_1
       5: iand
       6: iconst_1
       7: if_icmpne     19
      10: aload_1
      11: iconst_1
      12: aload_0
      13: invokevirtual #68                 // Method getUserInfo:()Lorg/apache/hadoop/hbase/shaded/protobuf/generated/RPCProtos$UserInformation;
      16: invokevirtual #84                 // Method org/apache/hbase/thirdparty/com/google/protobuf/CodedOutputStream.writeMessage:(ILorg/apache/hbase/thirdparty/com/google/protobuf/MessageLite;)V
      19: aload_0
      20: getfield      #4                  // Field bitField0_:I
      23: iconst_2
      24: iand
      25: iconst_2
      26: if_icmpne     38
      29: aload_1
      30: iconst_2
      31: aload_0
      32: invokevirtual #70                 // Method getSnapshot:()Lorg/apache/hadoop/hbase/shaded/protobuf/generated/SnapshotProtos$SnapshotDescription;
      35: invokevirtual #84                 // Method org/apache/hbase/thirdparty/com/google/protobuf/CodedOutputStream.writeMessage:(ILorg/apache/hbase/thirdparty/com/google/protobuf/MessageLite;)V
      38: aload_0
      39: getfield      #4                  // Field bitField0_:I
      42: iconst_4
      43: iand
      44: iconst_4
      45: if_icmpne     57
      48: aload_1
      49: iconst_3
      50: aload_0
      51: invokevirtual #72                 // Method getModifiedTableSchema:()Lorg/apache/hadoop/hbase/shaded/protobuf/generated/HBaseProtos$TableSchema;
      54: invokevirtual #84                 // Method org/apache/hbase/thirdparty/com/google/protobuf/CodedOutputStream.writeMessage:(ILorg/apache/hbase/thirdparty/com/google/protobuf/MessageLite;)V
      57: iconst_0
      58: istore_2
      59: iload_2
      60: aload_0
      61: getfield      #8                  // Field regionInfoForRestore_:Ljava/util/List;
      64: invokeinterface #59,  1           // InterfaceMethod java/util/List.size:()I
      69: if_icmpge     96
      72: aload_1
      73: iconst_4
      74: aload_0
      75: getfield      #8                  // Field regionInfoForRestore_:Ljava/util/List;
      78: iload_2
      79: invokeinterface #60,  2           // InterfaceMethod java/util/List.get:(I)Ljava/lang/Object;
      84: checkcast     #85                 // class org/apache/hbase/thirdparty/com/google/protobuf/MessageLite
      87: invokevirtual #84                 // Method org/apache/hbase/thirdparty/com/google/protobuf/CodedOutputStream.writeMessage:(ILorg/apache/hbase/thirdparty/com/google/protobuf/MessageLite;)V
      90: iinc          2, 1
      93: goto          59
      96: iconst_0
      97: istore_2
      98: iload_2
      99: aload_0
     100: getfield      #7                  // Field regionInfoForRemove_:Ljava/util/List;
     103: invokeinterface #59,  1           // InterfaceMethod java/util/List.size:()I
     108: if_icmpge     135
     111: aload_1
     112: iconst_5
     113: aload_0
     114: getfield      #7                  // Field regionInfoForRemove_:Ljava/util/List;
     117: iload_2
     118: invokeinterface #60,  2           // InterfaceMethod java/util/List.get:(I)Ljava/lang/Object;
     123: checkcast     #85                 // class org/apache/hbase/thirdparty/com/google/protobuf/MessageLite
     126: invokevirtual #84                 // Method org/apache/hbase/thirdparty/com/google/protobuf/CodedOutputStream.writeMessage:(ILorg/apache/hbase/thirdparty/com/google/protobuf/MessageLite;)V
     129: iinc          2, 1
     132: goto          98
     135: iconst_0
     136: istore_2
     137: iload_2
     138: aload_0
     139: getfield      #6                  // Field regionInfoForAdd_:Ljava/util/List;
     142: invokeinterface #59,  1           // InterfaceMethod java/util/List.size:()I
     147: if_icmpge     175
     150: aload_1
     151: bipush        6
     153: aload_0
     154: getfield      #6                  // Field regionInfoForAdd_:Ljava/util/List;
     157: iload_2
     158: invokeinterface #60,  2           // InterfaceMethod java/util/List.get:(I)Ljava/lang/Object;
     163: checkcast     #85                 // class org/apache/hbase/thirdparty/com/google/protobuf/MessageLite
     166: invokevirtual #84                 // Method org/apache/hbase/thirdparty/com/google/protobuf/CodedOutputStream.writeMessage:(ILorg/apache/hbase/thirdparty/com/google/protobuf/MessageLite;)V
     169: iinc          2, 1
     172: goto          137
     175: iconst_0
     176: istore_2
     177: iload_2
     178: aload_0
     179: getfield      #5                  // Field parentToChildRegionsPairList_:Ljava/util/List;
     182: invokeinterface #59,  1           // InterfaceMethod java/util/List.size:()I
     187: if_icmpge     215
     190: aload_1
     191: bipush        7
     193: aload_0
     194: getfield      #5                  // Field parentToChildRegionsPairList_:Ljava/util/List;
     197: iload_2
     198: invokeinterface #60,  2           // InterfaceMethod java/util/List.get:(I)Ljava/lang/Object;
     203: checkcast     #85                 // class org/apache/hbase/thirdparty/com/google/protobuf/MessageLite
     206: invokevirtual #84                 // Method org/apache/hbase/thirdparty/com/google/protobuf/CodedOutputStream.writeMessage:(ILorg/apache/hbase/thirdparty/com/google/protobuf/MessageLite;)V
     209: iinc          2, 1
     212: goto          177
     215: aload_0
     216: getfield      #2                  // Field unknownFields:Lorg/apache/hbase/thirdparty/com/google/protobuf/UnknownFieldSet;
     219: aload_1
     220: invokevirtual #86                 // Method org/apache/hbase/thirdparty/com/google/protobuf/UnknownFieldSet.writeTo:(Lorg/apache/hbase/thirdparty/com/google/protobuf/CodedOutputStream;)V
     223: return

  public int getSerializedSize();
    Code:
       0: aload_0
       1: getfield      #87                 // Field memoizedSize:I
       4: istore_1
       5: iload_1
       6: iconst_m1
       7: if_icmpeq     12
      10: iload_1
      11: ireturn
      12: iconst_0
      13: istore_1
      14: aload_0
      15: getfield      #4                  // Field bitField0_:I
      18: iconst_1
      19: iand
      20: iconst_1
      21: if_icmpne     35
      24: iload_1
      25: iconst_1
      26: aload_0
      27: invokevirtual #68                 // Method getUserInfo:()Lorg/apache/hadoop/hbase/shaded/protobuf/generated/RPCProtos$UserInformation;
      30: invokestatic  #88                 // Method org/apache/hbase/thirdparty/com/google/protobuf/CodedOutputStream.computeMessageSize:(ILorg/apache/hbase/thirdparty/com/google/protobuf/MessageLite;)I
      33: iadd
      34: istore_1
      35: aload_0
      36: getfield      #4                  // Field bitField0_:I
      39: iconst_2
      40: iand
      41: iconst_2
      42: if_icmpne     56
      45: iload_1
      46: iconst_2
      47: aload_0
      48: invokevirtual #70                 // Method getSnapshot:()Lorg/apache/hadoop/hbase/shaded/protobuf/generated/SnapshotProtos$SnapshotDescription;
      51: invokestatic  #88                 // Method org/apache/hbase/thirdparty/com/google/protobuf/CodedOutputStream.computeMessageSize:(ILorg/apache/hbase/thirdparty/com/google/protobuf/MessageLite;)I
      54: iadd
      55: istore_1
      56: aload_0
      57: getfield      #4                  // Field bitField0_:I
      60: iconst_4
      61: iand
      62: iconst_4
      63: if_icmpne     77
      66: iload_1
      67: iconst_3
      68: aload_0
      69: invokevirtual #72                 // Method getModifiedTableSchema:()Lorg/apache/hadoop/hbase/shaded/protobuf/generated/HBaseProtos$TableSchema;
      72: invokestatic  #88                 // Method org/apache/hbase/thirdparty/com/google/protobuf/CodedOutputStream.computeMessageSize:(ILorg/apache/hbase/thirdparty/com/google/protobuf/MessageLite;)I
      75: iadd
      76: istore_1
      77: iconst_0
      78: istore_2
      79: iload_2
      80: aload_0
      81: getfield      #8                  // Field regionInfoForRestore_:Ljava/util/List;
      84: invokeinterface #59,  1           // InterfaceMethod java/util/List.size:()I
      89: if_icmpge     118
      92: iload_1
      93: iconst_4
      94: aload_0
      95: getfield      #8                  // Field regionInfoForRestore_:Ljava/util/List;
      98: iload_2
      99: invokeinterface #60,  2           // InterfaceMethod java/util/List.get:(I)Ljava/lang/Object;
     104: checkcast     #85                 // class org/apache/hbase/thirdparty/com/google/protobuf/MessageLite
     107: invokestatic  #88                 // Method org/apache/hbase/thirdparty/com/google/protobuf/CodedOutputStream.computeMessageSize:(ILorg/apache/hbase/thirdparty/com/google/protobuf/MessageLite;)I
     110: iadd
     111: istore_1
     112: iinc          2, 1
     115: goto          79
     118: iconst_0
     119: istore_2
     120: iload_2
     121: aload_0
     122: getfield      #7                  // Field regionInfoForRemove_:Ljava/util/List;
     125: invokeinterface #59,  1           // InterfaceMethod java/util/List.size:()I
     130: if_icmpge     159
     133: iload_1
     134: iconst_5
     135: aload_0
     136: getfield      #7                  // Field regionInfoForRemove_:Ljava/util/List;
     139: iload_2
     140: invokeinterface #60,  2           // InterfaceMethod java/util/List.get:(I)Ljava/lang/Object;
     145: checkcast     #85                 // class org/apache/hbase/thirdparty/com/google/protobuf/MessageLite
     148: invokestatic  #88                 // Method org/apache/hbase/thirdparty/com/google/protobuf/CodedOutputStream.computeMessageSize:(ILorg/apache/hbase/thirdparty/com/google/protobuf/MessageLite;)I
     151: iadd
     152: istore_1
     153: iinc          2, 1
     156: goto          120
     159: iconst_0
     160: istore_2
     161: iload_2
     162: aload_0
     163: getfield      #6                  // Field regionInfoForAdd_:Ljava/util/List;
     166: invokeinterface #59,  1           // InterfaceMethod java/util/List.size:()I
     171: if_icmpge     201
     174: iload_1
     175: bipush        6
     177: aload_0
     178: getfield      #6                  // Field regionInfoForAdd_:Ljava/util/List;
     181: iload_2
     182: invokeinterface #60,  2           // InterfaceMethod java/util/List.get:(I)Ljava/lang/Object;
     187: checkcast     #85                 // class org/apache/hbase/thirdparty/com/google/protobuf/MessageLite
     190: invokestatic  #88                 // Method org/apache/hbase/thirdparty/com/google/protobuf/CodedOutputStream.computeMessageSize:(ILorg/apache/hbase/thirdparty/com/google/protobuf/MessageLite;)I
     193: iadd
     194: istore_1
     195: iinc          2, 1
     198: goto          161
     201: iconst_0
     202: istore_2
     203: iload_2
     204: aload_0
     205: getfield      #5                  // Field parentToChildRegionsPairList_:Ljava/util/List;
     208: invokeinterface #59,  1           // InterfaceMethod java/util/List.size:()I
     213: if_icmpge     243
     216: iload_1
     217: bipush        7
     219: aload_0
     220: getfield      #5                  // Field parentToChildRegionsPairList_:Ljava/util/List;
     223: iload_2
     224: invokeinterface #60,  2           // InterfaceMethod java/util/List.get:(I)Ljava/lang/Object;
     229: checkcast     #85                 // class org/apache/hbase/thirdparty/com/google/protobuf/MessageLite
     232: invokestatic  #88                 // Method org/apache/hbase/thirdparty/com/google/protobuf/CodedOutputStream.computeMessageSize:(ILorg/apache/hbase/thirdparty/com/google/protobuf/MessageLite;)I
     235: iadd
     236: istore_1
     237: iinc          2, 1
     240: goto          203
     243: iload_1
     244: aload_0
     245: getfield      #2                  // Field unknownFields:Lorg/apache/hbase/thirdparty/com/google/protobuf/UnknownFieldSet;
     248: invokevirtual #89                 // Method org/apache/hbase/thirdparty/com/google/protobuf/UnknownFieldSet.getSerializedSize:()I
     251: iadd
     252: istore_1
     253: aload_0
     254: iload_1
     255: putfield      #87                 // Field memoizedSize:I
     258: iload_1
     259: ireturn

  public boolean equals(java.lang.Object);
    Code:
       0: aload_1
       1: aload_0
       2: if_acmpne     7
       5: iconst_1
       6: ireturn
       7: aload_1
       8: instanceof    #53                 // class org/apache/hadoop/hbase/shaded/protobuf/generated/MasterProcedureProtos$RestoreSnapshotStateData
      11: ifne          20
      14: aload_0
      15: aload_1
      16: invokespecial #90                 // Method org/apache/hbase/thirdparty/com/google/protobuf/GeneratedMessageV3.equals:(Ljava/lang/Object;)Z
      19: ireturn
      20: aload_1
      21: checkcast     #53                 // class org/apache/hadoop/hbase/shaded/protobuf/generated/MasterProcedureProtos$RestoreSnapshotStateData
      24: astore_2
      25: iconst_1
      26: istore_3
      27: iload_3
      28: ifeq          46
      31: aload_0
      32: invokevirtual #65                 // Method hasUserInfo:()Z
      35: aload_2
      36: invokevirtual #65                 // Method hasUserInfo:()Z
      39: if_icmpne     46
      42: iconst_1
      43: goto          47
      46: iconst_0
      47: istore_3
      48: aload_0
      49: invokevirtual #65                 // Method hasUserInfo:()Z
      52: ifeq          79
      55: iload_3
      56: ifeq          77
      59: aload_0
      60: invokevirtual #68                 // Method getUserInfo:()Lorg/apache/hadoop/hbase/shaded/protobuf/generated/RPCProtos$UserInformation;
      63: aload_2
      64: invokevirtual #68                 // Method getUserInfo:()Lorg/apache/hadoop/hbase/shaded/protobuf/generated/RPCProtos$UserInformation;
      67: invokevirtual #91                 // Method org/apache/hadoop/hbase/shaded/protobuf/generated/RPCProtos$UserInformation.equals:(Ljava/lang/Object;)Z
      70: ifeq          77
      73: iconst_1
      74: goto          78
      77: iconst_0
      78: istore_3
      79: iload_3
      80: ifeq          98
      83: aload_0
      84: invokevirtual #66                 // Method hasSnapshot:()Z
      87: aload_2
      88: invokevirtual #66                 // Method hasSnapshot:()Z
      91: if_icmpne     98
      94: iconst_1
      95: goto          99
      98: iconst_0
      99: istore_3
     100: aload_0
     101: invokevirtual #66                 // Method hasSnapshot:()Z
     104: ifeq          131
     107: iload_3
     108: ifeq          129
     111: aload_0
     112: invokevirtual #70                 // Method getSnapshot:()Lorg/apache/hadoop/hbase/shaded/protobuf/generated/SnapshotProtos$SnapshotDescription;
     115: aload_2
     116: invokevirtual #70                 // Method getSnapshot:()Lorg/apache/hadoop/hbase/shaded/protobuf/generated/SnapshotProtos$SnapshotDescription;
     119: invokevirtual #92                 // Method org/apache/hadoop/hbase/shaded/protobuf/generated/SnapshotProtos$SnapshotDescription.equals:(Ljava/lang/Object;)Z
     122: ifeq          129
     125: iconst_1
     126: goto          130
     129: iconst_0
     130: istore_3
     131: iload_3
     132: ifeq          150
     135: aload_0
     136: invokevirtual #67                 // Method hasModifiedTableSchema:()Z
     139: aload_2
     140: invokevirtual #67                 // Method hasModifiedTableSchema:()Z
     143: if_icmpne     150
     146: iconst_1
     147: goto          151
     150: iconst_0
     151: istore_3
     152: aload_0
     153: invokevirtual #67                 // Method hasModifiedTableSchema:()Z
     156: ifeq          183
     159: iload_3
     160: ifeq          181
     163: aload_0
     164: invokevirtual #72                 // Method getModifiedTableSchema:()Lorg/apache/hadoop/hbase/shaded/protobuf/generated/HBaseProtos$TableSchema;
     167: aload_2
     168: invokevirtual #72                 // Method getModifiedTableSchema:()Lorg/apache/hadoop/hbase/shaded/protobuf/generated/HBaseProtos$TableSchema;
     171: invokevirtual #93                 // Method org/apache/hadoop/hbase/shaded/protobuf/generated/HBaseProtos$TableSchema.equals:(Ljava/lang/Object;)Z
     174: ifeq          181
     177: iconst_1
     178: goto          182
     181: iconst_0
     182: istore_3
     183: iload_3
     184: ifeq          207
     187: aload_0
     188: invokevirtual #94                 // Method getRegionInfoForRestoreList:()Ljava/util/List;
     191: aload_2
     192: invokevirtual #94                 // Method getRegionInfoForRestoreList:()Ljava/util/List;
     195: invokeinterface #95,  2           // InterfaceMethod java/util/List.equals:(Ljava/lang/Object;)Z
     200: ifeq          207
     203: iconst_1
     204: goto          208
     207: iconst_0
     208: istore_3
     209: iload_3
     210: ifeq          233
     213: aload_0
     214: invokevirtual #96                 // Method getRegionInfoForRemoveList:()Ljava/util/List;
     217: aload_2
     218: invokevirtual #96                 // Method getRegionInfoForRemoveList:()Ljava/util/List;
     221: invokeinterface #95,  2           // InterfaceMethod java/util/List.equals:(Ljava/lang/Object;)Z
     226: ifeq          233
     229: iconst_1
     230: goto          234
     233: iconst_0
     234: istore_3
     235: iload_3
     236: ifeq          259
     239: aload_0
     240: invokevirtual #97                 // Method getRegionInfoForAddList:()Ljava/util/List;
     243: aload_2
     244: invokevirtual #97                 // Method getRegionInfoForAddList:()Ljava/util/List;
     247: invokeinterface #95,  2           // InterfaceMethod java/util/List.equals:(Ljava/lang/Object;)Z
     252: ifeq          259
     255: iconst_1
     256: goto          260
     259: iconst_0
     260: istore_3
     261: iload_3
     262: ifeq          285
     265: aload_0
     266: invokevirtual #98                 // Method getParentToChildRegionsPairListList:()Ljava/util/List;
     269: aload_2
     270: invokevirtual #98                 // Method getParentToChildRegionsPairListList:()Ljava/util/List;
     273: invokeinterface #95,  2           // InterfaceMethod java/util/List.equals:(Ljava/lang/Object;)Z
     278: ifeq          285
     281: iconst_1
     282: goto          286
     285: iconst_0
     286: istore_3
     287: iload_3
     288: ifeq          309
     291: aload_0
     292: getfield      #2                  // Field unknownFields:Lorg/apache/hbase/thirdparty/com/google/protobuf/UnknownFieldSet;
     295: aload_2
     296: getfield      #2                  // Field unknownFields:Lorg/apache/hbase/thirdparty/com/google/protobuf/UnknownFieldSet;
     299: invokevirtual #99                 // Method org/apache/hbase/thirdparty/com/google/protobuf/UnknownFieldSet.equals:(Ljava/lang/Object;)Z
     302: ifeq          309
     305: iconst_1
     306: goto          310
     309: iconst_0
     310: istore_3
     311: iload_3
     312: ireturn

  public int hashCode();
    Code:
       0: aload_0
       1: getfield      #100                // Field memoizedHashCode:I
       4: ifeq          12
       7: aload_0
       8: getfield      #100                // Field memoizedHashCode:I
      11: ireturn
      12: bipush        41
      14: istore_1
      15: bipush        19
      17: iload_1
      18: imul
      19: invokestatic  #101                // Method getDescriptor:()Lorg/apache/hbase/thirdparty/com/google/protobuf/Descriptors$Descriptor;
      22: invokevirtual #102                // Method java/lang/Object.hashCode:()I
      25: iadd
      26: istore_1
      27: aload_0
      28: invokevirtual #65                 // Method hasUserInfo:()Z
      31: ifeq          54
      34: bipush        37
      36: iload_1
      37: imul
      38: iconst_1
      39: iadd
      40: istore_1
      41: bipush        53
      43: iload_1
      44: imul
      45: aload_0
      46: invokevirtual #68                 // Method getUserInfo:()Lorg/apache/hadoop/hbase/shaded/protobuf/generated/RPCProtos$UserInformation;
      49: invokevirtual #103                // Method org/apache/hadoop/hbase/shaded/protobuf/generated/RPCProtos$UserInformation.hashCode:()I
      52: iadd
      53: istore_1
      54: aload_0
      55: invokevirtual #66                 // Method hasSnapshot:()Z
      58: ifeq          81
      61: bipush        37
      63: iload_1
      64: imul
      65: iconst_2
      66: iadd
      67: istore_1
      68: bipush        53
      70: iload_1
      71: imul
      72: aload_0
      73: invokevirtual #70                 // Method getSnapshot:()Lorg/apache/hadoop/hbase/shaded/protobuf/generated/SnapshotProtos$SnapshotDescription;
      76: invokevirtual #104                // Method org/apache/hadoop/hbase/shaded/protobuf/generated/SnapshotProtos$SnapshotDescription.hashCode:()I
      79: iadd
      80: istore_1
      81: aload_0
      82: invokevirtual #67                 // Method hasModifiedTableSchema:()Z
      85: ifeq          108
      88: bipush        37
      90: iload_1
      91: imul
      92: iconst_3
      93: iadd
      94: istore_1
      95: bipush        53
      97: iload_1
      98: imul
      99: aload_0
     100: invokevirtual #72                 // Method getModifiedTableSchema:()Lorg/apache/hadoop/hbase/shaded/protobuf/generated/HBaseProtos$TableSchema;
     103: invokevirtual #105                // Method org/apache/hadoop/hbase/shaded/protobuf/generated/HBaseProtos$TableSchema.hashCode:()I
     106: iadd
     107: istore_1
     108: aload_0
     109: invokevirtual #74                 // Method getRegionInfoForRestoreCount:()I
     112: ifle          137
     115: bipush        37
     117: iload_1
     118: imul
     119: iconst_4
     120: iadd
     121: istore_1
     122: bipush        53
     124: iload_1
     125: imul
     126: aload_0
     127: invokevirtual #94                 // Method getRegionInfoForRestoreList:()Ljava/util/List;
     130: invokeinterface #106,  1          // InterfaceMethod java/util/List.hashCode:()I
     135: iadd
     136: istore_1
     137: aload_0
     138: invokevirtual #77                 // Method getRegionInfoForRemoveCount:()I
     141: ifle          166
     144: bipush        37
     146: iload_1
     147: imul
     148: iconst_5
     149: iadd
     150: istore_1
     151: bipush        53
     153: iload_1
     154: imul
     155: aload_0
     156: invokevirtual #96                 // Method getRegionInfoForRemoveList:()Ljava/util/List;
     159: invokeinterface #106,  1          // InterfaceMethod java/util/List.hashCode:()I
     164: iadd
     165: istore_1
     166: aload_0
     167: invokevirtual #79                 // Method getRegionInfoForAddCount:()I
     170: ifle          196
     173: bipush        37
     175: iload_1
     176: imul
     177: bipush        6
     179: iadd
     180: istore_1
     181: bipush        53
     183: iload_1
     184: imul
     185: aload_0
     186: invokevirtual #97                 // Method getRegionInfoForAddList:()Ljava/util/List;
     189: invokeinterface #106,  1          // InterfaceMethod java/util/List.hashCode:()I
     194: iadd
     195: istore_1
     196: aload_0
     197: invokevirtual #81                 // Method getParentToChildRegionsPairListCount:()I
     200: ifle          226
     203: bipush        37
     205: iload_1
     206: imul
     207: bipush        7
     209: iadd
     210: istore_1
     211: bipush        53
     213: iload_1
     214: imul
     215: aload_0
     216: invokevirtual #98                 // Method getParentToChildRegionsPairListList:()Ljava/util/List;
     219: invokeinterface #106,  1          // InterfaceMethod java/util/List.hashCode:()I
     224: iadd
     225: istore_1
     226: bipush        29
     228: iload_1
     229: imul
     230: aload_0
     231: getfield      #2                  // Field unknownFields:Lorg/apache/hbase/thirdparty/com/google/protobuf/UnknownFieldSet;
     234: invokevirtual #107                // Method org/apache/hbase/thirdparty/com/google/protobuf/UnknownFieldSet.hashCode:()I
     237: iadd
     238: istore_1
     239: aload_0
     240: iload_1
     241: putfield      #100                // Field memoizedHashCode:I
     244: iload_1
     245: ireturn

  public static org.apache.hadoop.hbase.shaded.protobuf.generated.MasterProcedureProtos$RestoreSnapshotStateData parseFrom(java.nio.ByteBuffer) throws org.apache.hbase.thirdparty.com.google.protobuf.InvalidProtocolBufferException;
    Code:
       0: getstatic     #108                // Field PARSER:Lorg/apache/hbase/thirdparty/com/google/protobuf/Parser;
       3: aload_0
       4: invokeinterface #109,  2          // InterfaceMethod org/apache/hbase/thirdparty/com/google/protobuf/Parser.parseFrom:(Ljava/nio/ByteBuffer;)Ljava/lang/Object;
       9: checkcast     #53                 // class org/apache/hadoop/hbase/shaded/protobuf/generated/MasterProcedureProtos$RestoreSnapshotStateData
      12: areturn

  public static org.apache.hadoop.hbase.shaded.protobuf.generated.MasterProcedureProtos$RestoreSnapshotStateData parseFrom(java.nio.ByteBuffer, org.apache.hbase.thirdparty.com.google.protobuf.ExtensionRegistryLite) throws org.apache.hbase.thirdparty.com.google.protobuf.InvalidProtocolBufferException;
    Code:
       0: getstatic     #108                // Field PARSER:Lorg/apache/hbase/thirdparty/com/google/protobuf/Parser;
       3: aload_0
       4: aload_1
       5: invokeinterface #110,  3          // InterfaceMethod org/apache/hbase/thirdparty/com/google/protobuf/Parser.parseFrom:(Ljava/nio/ByteBuffer;Lorg/apache/hbase/thirdparty/com/google/protobuf/ExtensionRegistryLite;)Ljava/lang/Object;
      10: checkcast     #53                 // class org/apache/hadoop/hbase/shaded/protobuf/generated/MasterProcedureProtos$RestoreSnapshotStateData
      13: areturn

  public static org.apache.hadoop.hbase.shaded.protobuf.generated.MasterProcedureProtos$RestoreSnapshotStateData parseFrom(org.apache.hbase.thirdparty.com.google.protobuf.ByteString) throws org.apache.hbase.thirdparty.com.google.protobuf.InvalidProtocolBufferException;
    Code:
       0: getstatic     #108                // Field PARSER:Lorg/apache/hbase/thirdparty/com/google/protobuf/Parser;
       3: aload_0
       4: invokeinterface #111,  2          // InterfaceMethod org/apache/hbase/thirdparty/com/google/protobuf/Parser.parseFrom:(Lorg/apache/hbase/thirdparty/com/google/protobuf/ByteString;)Ljava/lang/Object;
       9: checkcast     #53                 // class org/apache/hadoop/hbase/shaded/protobuf/generated/MasterProcedureProtos$RestoreSnapshotStateData
      12: areturn

  public static org.apache.hadoop.hbase.shaded.protobuf.generated.MasterProcedureProtos$RestoreSnapshotStateData parseFrom(org.apache.hbase.thirdparty.com.google.protobuf.ByteString, org.apache.hbase.thirdparty.com.google.protobuf.ExtensionRegistryLite) throws org.apache.hbase.thirdparty.com.google.protobuf.InvalidProtocolBufferException;
    Code:
       0: getstatic     #108                // Field PARSER:Lorg/apache/hbase/thirdparty/com/google/protobuf/Parser;
       3: aload_0
       4: aload_1
       5: invokeinterface #112,  3          // InterfaceMethod org/apache/hbase/thirdparty/com/google/protobuf/Parser.parseFrom:(Lorg/apache/hbase/thirdparty/com/google/protobuf/ByteString;Lorg/apache/hbase/thirdparty/com/google/protobuf/ExtensionRegistryLite;)Ljava/lang/Object;
      10: checkcast     #53                 // class org/apache/hadoop/hbase/shaded/protobuf/generated/MasterProcedureProtos$RestoreSnapshotStateData
      13: areturn

  public static org.apache.hadoop.hbase.shaded.protobuf.generated.MasterProcedureProtos$RestoreSnapshotStateData parseFrom(byte[]) throws org.apache.hbase.thirdparty.com.google.protobuf.InvalidProtocolBufferException;
    Code:
       0: getstatic     #108                // Field PARSER:Lorg/apache/hbase/thirdparty/com/google/protobuf/Parser;
       3: aload_0
       4: invokeinterface #113,  2          // InterfaceMethod org/apache/hbase/thirdparty/com/google/protobuf/Parser.parseFrom:([B)Ljava/lang/Object;
       9: checkcast     #53                 // class org/apache/hadoop/hbase/shaded/protobuf/generated/MasterProcedureProtos$RestoreSnapshotStateData
      12: areturn

  public static org.apache.hadoop.hbase.shaded.protobuf.generated.MasterProcedureProtos$RestoreSnapshotStateData parseFrom(byte[], org.apache.hbase.thirdparty.com.google.protobuf.ExtensionRegistryLite) throws org.apache.hbase.thirdparty.com.google.protobuf.InvalidProtocolBufferException;
    Code:
       0: getstatic     #108                // Field PARSER:Lorg/apache/hbase/thirdparty/com/google/protobuf/Parser;
       3: aload_0
       4: aload_1
       5: invokeinterface #114,  3          // InterfaceMethod org/apache/hbase/thirdparty/com/google/protobuf/Parser.parseFrom:([BLorg/apache/hbase/thirdparty/com/google/protobuf/ExtensionRegistryLite;)Ljava/lang/Object;
      10: checkcast     #53                 // class org/apache/hadoop/hbase/shaded/protobuf/generated/MasterProcedureProtos$RestoreSnapshotStateData
      13: areturn

  public static org.apache.hadoop.hbase.shaded.protobuf.generated.MasterProcedureProtos$RestoreSnapshotStateData parseFrom(java.io.InputStream) throws java.io.IOException;
    Code:
       0: getstatic     #108                // Field PARSER:Lorg/apache/hbase/thirdparty/com/google/protobuf/Parser;
       3: aload_0
       4: invokestatic  #115                // Method org/apache/hbase/thirdparty/com/google/protobuf/GeneratedMessageV3.parseWithIOException:(Lorg/apache/hbase/thirdparty/com/google/protobuf/Parser;Ljava/io/InputStream;)Lorg/apache/hbase/thirdparty/com/google/protobuf/Message;
       7: checkcast     #53                 // class org/apache/hadoop/hbase/shaded/protobuf/generated/MasterProcedureProtos$RestoreSnapshotStateData
      10: areturn

  public static org.apache.hadoop.hbase.shaded.protobuf.generated.MasterProcedureProtos$RestoreSnapshotStateData parseFrom(java.io.InputStream, org.apache.hbase.thirdparty.com.google.protobuf.ExtensionRegistryLite) throws java.io.IOException;
    Code:
       0: getstatic     #108                // Field PARSER:Lorg/apache/hbase/thirdparty/com/google/protobuf/Parser;
       3: aload_0
       4: aload_1
       5: invokestatic  #116                // Method org/apache/hbase/thirdparty/com/google/protobuf/GeneratedMessageV3.parseWithIOException:(Lorg/apache/hbase/thirdparty/com/google/protobuf/Parser;Ljava/io/InputStream;Lorg/apache/hbase/thirdparty/com/google/protobuf/ExtensionRegistryLite;)Lorg/apache/hbase/thirdparty/com/google/protobuf/Message;
       8: checkcast     #53                 // class org/apache/hadoop/hbase/shaded/protobuf/generated/MasterProcedureProtos$RestoreSnapshotStateData
      11: areturn

  public static org.apache.hadoop.hbase.shaded.protobuf.generated.MasterProcedureProtos$RestoreSnapshotStateData parseDelimitedFrom(java.io.InputStream) throws java.io.IOException;
    Code:
       0: getstatic     #108                // Field PARSER:Lorg/apache/hbase/thirdparty/com/google/protobuf/Parser;
       3: aload_0
       4: invokestatic  #117                // Method org/apache/hbase/thirdparty/com/google/protobuf/GeneratedMessageV3.parseDelimitedWithIOException:(Lorg/apache/hbase/thirdparty/com/google/protobuf/Parser;Ljava/io/InputStream;)Lorg/apache/hbase/thirdparty/com/google/protobuf/Message;
       7: checkcast     #53                 // class org/apache/hadoop/hbase/shaded/protobuf/generated/MasterProcedureProtos$RestoreSnapshotStateData
      10: areturn

  public static org.apache.hadoop.hbase.shaded.protobuf.generated.MasterProcedureProtos$RestoreSnapshotStateData parseDelimitedFrom(java.io.InputStream, org.apache.hbase.thirdparty.com.google.protobuf.ExtensionRegistryLite) throws java.io.IOException;
    Code:
       0: getstatic     #108                // Field PARSER:Lorg/apache/hbase/thirdparty/com/google/protobuf/Parser;
       3: aload_0
       4: aload_1
       5: invokestatic  #118                // Method org/apache/hbase/thirdparty/com/google/protobuf/GeneratedMessageV3.parseDelimitedWithIOException:(Lorg/apache/hbase/thirdparty/com/google/protobuf/Parser;Ljava/io/InputStream;Lorg/apache/hbase/thirdparty/com/google/protobuf/ExtensionRegistryLite;)Lorg/apache/hbase/thirdparty/com/google/protobuf/Message;
       8: checkcast     #53                 // class org/apache/hadoop/hbase/shaded/protobuf/generated/MasterProcedureProtos$RestoreSnapshotStateData
      11: areturn

  public static org.apache.hadoop.hbase.shaded.protobuf.generated.MasterProcedureProtos$RestoreSnapshotStateData parseFrom(org.apache.hbase.thirdparty.com.google.protobuf.CodedInputStream) throws java.io.IOException;
    Code:
       0: getstatic     #108                // Field PARSER:Lorg/apache/hbase/thirdparty/com/google/protobuf/Parser;
       3: aload_0
       4: invokestatic  #119                // Method org/apache/hbase/thirdparty/com/google/protobuf/GeneratedMessageV3.parseWithIOException:(Lorg/apache/hbase/thirdparty/com/google/protobuf/Parser;Lorg/apache/hbase/thirdparty/com/google/protobuf/CodedInputStream;)Lorg/apache/hbase/thirdparty/com/google/protobuf/Message;
       7: checkcast     #53                 // class org/apache/hadoop/hbase/shaded/protobuf/generated/MasterProcedureProtos$RestoreSnapshotStateData
      10: areturn

  public static org.apache.hadoop.hbase.shaded.protobuf.generated.MasterProcedureProtos$RestoreSnapshotStateData parseFrom(org.apache.hbase.thirdparty.com.google.protobuf.CodedInputStream, org.apache.hbase.thirdparty.com.google.protobuf.ExtensionRegistryLite) throws java.io.IOException;
    Code:
       0: getstatic     #108                // Field PARSER:Lorg/apache/hbase/thirdparty/com/google/protobuf/Parser;
       3: aload_0
       4: aload_1
       5: invokestatic  #120                // Method org/apache/hbase/thirdparty/com/google/protobuf/GeneratedMessageV3.parseWithIOException:(Lorg/apache/hbase/thirdparty/com/google/protobuf/Parser;Lorg/apache/hbase/thirdparty/com/google/protobuf/CodedInputStream;Lorg/apache/hbase/thirdparty/com/google/protobuf/ExtensionRegistryLite;)Lorg/apache/hbase/thirdparty/com/google/protobuf/Message;
       8: checkcast     #53                 // class org/apache/hadoop/hbase/shaded/protobuf/generated/MasterProcedureProtos$RestoreSnapshotStateData
      11: areturn

  public org.apache.hadoop.hbase.shaded.protobuf.generated.MasterProcedureProtos$RestoreSnapshotStateData$Builder newBuilderForType();
    Code:
       0: invokestatic  #121                // Method newBuilder:()Lorg/apache/hadoop/hbase/shaded/protobuf/generated/MasterProcedureProtos$RestoreSnapshotStateData$Builder;
       3: areturn

  public static org.apache.hadoop.hbase.shaded.protobuf.generated.MasterProcedureProtos$RestoreSnapshotStateData$Builder newBuilder();
    Code:
       0: getstatic     #122                // Field DEFAULT_INSTANCE:Lorg/apache/hadoop/hbase/shaded/protobuf/generated/MasterProcedureProtos$RestoreSnapshotStateData;
       3: invokevirtual #123                // Method toBuilder:()Lorg/apache/hadoop/hbase/shaded/protobuf/generated/MasterProcedureProtos$RestoreSnapshotStateData$Builder;
       6: areturn

  public static org.apache.hadoop.hbase.shaded.protobuf.generated.MasterProcedureProtos$RestoreSnapshotStateData$Builder newBuilder(org.apache.hadoop.hbase.shaded.protobuf.generated.MasterProcedureProtos$RestoreSnapshotStateData);
    Code:
       0: getstatic     #122                // Field DEFAULT_INSTANCE:Lorg/apache/hadoop/hbase/shaded/protobuf/generated/MasterProcedureProtos$RestoreSnapshotStateData;
       3: invokevirtual #123                // Method toBuilder:()Lorg/apache/hadoop/hbase/shaded/protobuf/generated/MasterProcedureProtos$RestoreSnapshotStateData$Builder;
       6: aload_0
       7: invokevirtual #124                // Method org/apache/hadoop/hbase/shaded/protobuf/generated/MasterProcedureProtos$RestoreSnapshotStateData$Builder.mergeFrom:(Lorg/apache/hadoop/hbase/shaded/protobuf/generated/MasterProcedureProtos$RestoreSnapshotStateData;)Lorg/apache/hadoop/hbase/shaded/protobuf/generated/MasterProcedureProtos$RestoreSnapshotStateData$Builder;
      10: areturn

  public org.apache.hadoop.hbase.shaded.protobuf.generated.MasterProcedureProtos$RestoreSnapshotStateData$Builder toBuilder();
    Code:
       0: aload_0
       1: getstatic     #122                // Field DEFAULT_INSTANCE:Lorg/apache/hadoop/hbase/shaded/protobuf/generated/MasterProcedureProtos$RestoreSnapshotStateData;
       4: if_acmpne     18
       7: new           #54                 // class org/apache/hadoop/hbase/shaded/protobuf/generated/MasterProcedureProtos$RestoreSnapshotStateData$Builder
      10: dup
      11: aconst_null
      12: invokespecial #125                // Method org/apache/hadoop/hbase/shaded/protobuf/generated/MasterProcedureProtos$RestoreSnapshotStateData$Builder."<init>":(Lorg/apache/hadoop/hbase/shaded/protobuf/generated/MasterProcedureProtos$1;)V
      15: goto          30
      18: new           #54                 // class org/apache/hadoop/hbase/shaded/protobuf/generated/MasterProcedureProtos$RestoreSnapshotStateData$Builder
      21: dup
      22: aconst_null
      23: invokespecial #125                // Method org/apache/hadoop/hbase/shaded/protobuf/generated/MasterProcedureProtos$RestoreSnapshotStateData$Builder."<init>":(Lorg/apache/hadoop/hbase/shaded/protobuf/generated/MasterProcedureProtos$1;)V
      26: aload_0
      27: invokevirtual #124                // Method org/apache/hadoop/hbase/shaded/protobuf/generated/MasterProcedureProtos$RestoreSnapshotStateData$Builder.mergeFrom:(Lorg/apache/hadoop/hbase/shaded/protobuf/generated/MasterProcedureProtos$RestoreSnapshotStateData;)Lorg/apache/hadoop/hbase/shaded/protobuf/generated/MasterProcedureProtos$RestoreSnapshotStateData$Builder;
      30: areturn

  protected org.apache.hadoop.hbase.shaded.protobuf.generated.MasterProcedureProtos$RestoreSnapshotStateData$Builder newBuilderForType(org.apache.hbase.thirdparty.com.google.protobuf.GeneratedMessageV3$BuilderParent);
    Code:
       0: new           #54                 // class org/apache/hadoop/hbase/shaded/protobuf/generated/MasterProcedureProtos$RestoreSnapshotStateData$Builder
       3: dup
       4: aload_1
       5: aconst_null
       6: invokespecial #126                // Method org/apache/hadoop/hbase/shaded/protobuf/generated/MasterProcedureProtos$RestoreSnapshotStateData$Builder."<init>":(Lorg/apache/hbase/thirdparty/com/google/protobuf/GeneratedMessageV3$BuilderParent;Lorg/apache/hadoop/hbase/shaded/protobuf/generated/MasterProcedureProtos$1;)V
       9: astore_2
      10: aload_2
      11: areturn

  public static org.apache.hadoop.hbase.shaded.protobuf.generated.MasterProcedureProtos$RestoreSnapshotStateData getDefaultInstance();
    Code:
       0: getstatic     #122                // Field DEFAULT_INSTANCE:Lorg/apache/hadoop/hbase/shaded/protobuf/generated/MasterProcedureProtos$RestoreSnapshotStateData;
       3: areturn

  public static org.apache.hbase.thirdparty.com.google.protobuf.Parser<org.apache.hadoop.hbase.shaded.protobuf.generated.MasterProcedureProtos$RestoreSnapshotStateData> parser();
    Code:
       0: getstatic     #108                // Field PARSER:Lorg/apache/hbase/thirdparty/com/google/protobuf/Parser;
       3: areturn

  public org.apache.hbase.thirdparty.com.google.protobuf.Parser<org.apache.hadoop.hbase.shaded.protobuf.generated.MasterProcedureProtos$RestoreSnapshotStateData> getParserForType();
    Code:
       0: getstatic     #108                // Field PARSER:Lorg/apache/hbase/thirdparty/com/google/protobuf/Parser;
       3: areturn

  public org.apache.hadoop.hbase.shaded.protobuf.generated.MasterProcedureProtos$RestoreSnapshotStateData getDefaultInstanceForType();
    Code:
       0: getstatic     #122                // Field DEFAULT_INSTANCE:Lorg/apache/hadoop/hbase/shaded/protobuf/generated/MasterProcedureProtos$RestoreSnapshotStateData;
       3: areturn

  protected org.apache.hbase.thirdparty.com.google.protobuf.Message$Builder newBuilderForType(org.apache.hbase.thirdparty.com.google.protobuf.GeneratedMessageV3$BuilderParent);
    Code:
       0: aload_0
       1: aload_1
       2: invokevirtual #127                // Method newBuilderForType:(Lorg/apache/hbase/thirdparty/com/google/protobuf/GeneratedMessageV3$BuilderParent;)Lorg/apache/hadoop/hbase/shaded/protobuf/generated/MasterProcedureProtos$RestoreSnapshotStateData$Builder;
       5: areturn

  public org.apache.hbase.thirdparty.com.google.protobuf.Message$Builder toBuilder();
    Code:
       0: aload_0
       1: invokevirtual #123                // Method toBuilder:()Lorg/apache/hadoop/hbase/shaded/protobuf/generated/MasterProcedureProtos$RestoreSnapshotStateData$Builder;
       4: areturn

  public org.apache.hbase.thirdparty.com.google.protobuf.Message$Builder newBuilderForType();
    Code:
       0: aload_0
       1: invokevirtual #128                // Method newBuilderForType:()Lorg/apache/hadoop/hbase/shaded/protobuf/generated/MasterProcedureProtos$RestoreSnapshotStateData$Builder;
       4: areturn

  public org.apache.hbase.thirdparty.com.google.protobuf.MessageLite$Builder toBuilder();
    Code:
       0: aload_0
       1: invokevirtual #123                // Method toBuilder:()Lorg/apache/hadoop/hbase/shaded/protobuf/generated/MasterProcedureProtos$RestoreSnapshotStateData$Builder;
       4: areturn

  public org.apache.hbase.thirdparty.com.google.protobuf.MessageLite$Builder newBuilderForType();
    Code:
       0: aload_0
       1: invokevirtual #128                // Method newBuilderForType:()Lorg/apache/hadoop/hbase/shaded/protobuf/generated/MasterProcedureProtos$RestoreSnapshotStateData$Builder;
       4: areturn

  public org.apache.hbase.thirdparty.com.google.protobuf.MessageLite getDefaultInstanceForType();
    Code:
       0: aload_0
       1: invokevirtual #129                // Method getDefaultInstanceForType:()Lorg/apache/hadoop/hbase/shaded/protobuf/generated/MasterProcedureProtos$RestoreSnapshotStateData;
       4: areturn

  public org.apache.hbase.thirdparty.com.google.protobuf.Message getDefaultInstanceForType();
    Code:
       0: aload_0
       1: invokevirtual #129                // Method getDefaultInstanceForType:()Lorg/apache/hadoop/hbase/shaded/protobuf/generated/MasterProcedureProtos$RestoreSnapshotStateData;
       4: areturn

  static boolean access$14300();
    Code:
       0: getstatic     #3                  // Field alwaysUseFieldBuilders:Z
       3: ireturn

  org.apache.hadoop.hbase.shaded.protobuf.generated.MasterProcedureProtos$RestoreSnapshotStateData(org.apache.hbase.thirdparty.com.google.protobuf.GeneratedMessageV3$Builder, org.apache.hadoop.hbase.shaded.protobuf.generated.MasterProcedureProtos$1);
    Code:
       0: aload_0
       1: aload_1
       2: invokespecial #12                 // Method "<init>":(Lorg/apache/hbase/thirdparty/com/google/protobuf/GeneratedMessageV3$Builder;)V
       5: return

  static org.apache.hadoop.hbase.shaded.protobuf.generated.RPCProtos$UserInformation access$14502(org.apache.hadoop.hbase.shaded.protobuf.generated.MasterProcedureProtos$RestoreSnapshotStateData, org.apache.hadoop.hbase.shaded.protobuf.generated.RPCProtos$UserInformation);
    Code:
       0: aload_0
       1: aload_1
       2: dup_x1
       3: putfield      #11                 // Field userInfo_:Lorg/apache/hadoop/hbase/shaded/protobuf/generated/RPCProtos$UserInformation;
       6: areturn

  static org.apache.hadoop.hbase.shaded.protobuf.generated.SnapshotProtos$SnapshotDescription access$14602(org.apache.hadoop.hbase.shaded.protobuf.generated.MasterProcedureProtos$RestoreSnapshotStateData, org.apache.hadoop.hbase.shaded.protobuf.generated.SnapshotProtos$SnapshotDescription);
    Code:
       0: aload_0
       1: aload_1
       2: dup_x1
       3: putfield      #10                 // Field snapshot_:Lorg/apache/hadoop/hbase/shaded/protobuf/generated/SnapshotProtos$SnapshotDescription;
       6: areturn

  static org.apache.hadoop.hbase.shaded.protobuf.generated.HBaseProtos$TableSchema access$14702(org.apache.hadoop.hbase.shaded.protobuf.generated.MasterProcedureProtos$RestoreSnapshotStateData, org.apache.hadoop.hbase.shaded.protobuf.generated.HBaseProtos$TableSchema);
    Code:
       0: aload_0
       1: aload_1
       2: dup_x1
       3: putfield      #9                  // Field modifiedTableSchema_:Lorg/apache/hadoop/hbase/shaded/protobuf/generated/HBaseProtos$TableSchema;
       6: areturn

  static java.util.List access$14802(org.apache.hadoop.hbase.shaded.protobuf.generated.MasterProcedureProtos$RestoreSnapshotStateData, java.util.List);
    Code:
       0: aload_0
       1: aload_1
       2: dup_x1
       3: putfield      #8                  // Field regionInfoForRestore_:Ljava/util/List;
       6: areturn

  static java.util.List access$14902(org.apache.hadoop.hbase.shaded.protobuf.generated.MasterProcedureProtos$RestoreSnapshotStateData, java.util.List);
    Code:
       0: aload_0
       1: aload_1
       2: dup_x1
       3: putfield      #7                  // Field regionInfoForRemove_:Ljava/util/List;
       6: areturn

  static java.util.List access$15002(org.apache.hadoop.hbase.shaded.protobuf.generated.MasterProcedureProtos$RestoreSnapshotStateData, java.util.List);
    Code:
       0: aload_0
       1: aload_1
       2: dup_x1
       3: putfield      #6                  // Field regionInfoForAdd_:Ljava/util/List;
       6: areturn

  static java.util.List access$15102(org.apache.hadoop.hbase.shaded.protobuf.generated.MasterProcedureProtos$RestoreSnapshotStateData, java.util.List);
    Code:
       0: aload_0
       1: aload_1
       2: dup_x1
       3: putfield      #5                  // Field parentToChildRegionsPairList_:Ljava/util/List;
       6: areturn

  static int access$15202(org.apache.hadoop.hbase.shaded.protobuf.generated.MasterProcedureProtos$RestoreSnapshotStateData, int);
    Code:
       0: aload_0
       1: iload_1
       2: dup_x1
       3: putfield      #4                  // Field bitField0_:I
       6: ireturn

  static java.util.List access$14800(org.apache.hadoop.hbase.shaded.protobuf.generated.MasterProcedureProtos$RestoreSnapshotStateData);
    Code:
       0: aload_0
       1: getfield      #8                  // Field regionInfoForRestore_:Ljava/util/List;
       4: areturn

  static boolean access$15300();
    Code:
       0: getstatic     #3                  // Field alwaysUseFieldBuilders:Z
       3: ireturn

  static java.util.List access$14900(org.apache.hadoop.hbase.shaded.protobuf.generated.MasterProcedureProtos$RestoreSnapshotStateData);
    Code:
       0: aload_0
       1: getfield      #7                  // Field regionInfoForRemove_:Ljava/util/List;
       4: areturn

  static boolean access$15400();
    Code:
       0: getstatic     #3                  // Field alwaysUseFieldBuilders:Z
       3: ireturn

  static java.util.List access$15000(org.apache.hadoop.hbase.shaded.protobuf.generated.MasterProcedureProtos$RestoreSnapshotStateData);
    Code:
       0: aload_0
       1: getfield      #6                  // Field regionInfoForAdd_:Ljava/util/List;
       4: areturn

  static boolean access$15500();
    Code:
       0: getstatic     #3                  // Field alwaysUseFieldBuilders:Z
       3: ireturn

  static java.util.List access$15100(org.apache.hadoop.hbase.shaded.protobuf.generated.MasterProcedureProtos$RestoreSnapshotStateData);
    Code:
       0: aload_0
       1: getfield      #5                  // Field parentToChildRegionsPairList_:Ljava/util/List;
       4: areturn

  static boolean access$15600();
    Code:
       0: getstatic     #3                  // Field alwaysUseFieldBuilders:Z
       3: ireturn

  static org.apache.hbase.thirdparty.com.google.protobuf.UnknownFieldSet access$15700(org.apache.hadoop.hbase.shaded.protobuf.generated.MasterProcedureProtos$RestoreSnapshotStateData);
    Code:
       0: aload_0
       1: getfield      #2                  // Field unknownFields:Lorg/apache/hbase/thirdparty/com/google/protobuf/UnknownFieldSet;
       4: areturn

  org.apache.hadoop.hbase.shaded.protobuf.generated.MasterProcedureProtos$RestoreSnapshotStateData(org.apache.hbase.thirdparty.com.google.protobuf.CodedInputStream, org.apache.hbase.thirdparty.com.google.protobuf.ExtensionRegistryLite, org.apache.hadoop.hbase.shaded.protobuf.generated.MasterProcedureProtos$1) throws org.apache.hbase.thirdparty.com.google.protobuf.InvalidProtocolBufferException;
    Code:
       0: aload_0
       1: aload_1
       2: aload_2
       3: invokespecial #1                  // Method "<init>":(Lorg/apache/hbase/thirdparty/com/google/protobuf/CodedInputStream;Lorg/apache/hbase/thirdparty/com/google/protobuf/ExtensionRegistryLite;)V
       6: return

  static {};
    Code:
       0: new           #53                 // class org/apache/hadoop/hbase/shaded/protobuf/generated/MasterProcedureProtos$RestoreSnapshotStateData
       3: dup
       4: invokespecial #17                 // Method "<init>":()V
       7: putstatic     #122                // Field DEFAULT_INSTANCE:Lorg/apache/hadoop/hbase/shaded/protobuf/generated/MasterProcedureProtos$RestoreSnapshotStateData;
      10: new           #130                // class org/apache/hadoop/hbase/shaded/protobuf/generated/MasterProcedureProtos$RestoreSnapshotStateData$1
      13: dup
      14: invokespecial #131                // Method org/apache/hadoop/hbase/shaded/protobuf/generated/MasterProcedureProtos$RestoreSnapshotStateData$1."<init>":()V
      17: putstatic     #108                // Field PARSER:Lorg/apache/hbase/thirdparty/com/google/protobuf/Parser;
      20: return
}
