Compiled from "MasterProcedureEnv.java"
public class org.apache.hadoop.hbase.master.procedure.MasterProcedureEnv$WALStoreLeaseRecovery implements org.apache.hadoop.hbase.procedure2.store.wal.WALProcedureStore$LeaseRecovery {
  public org.apache.hadoop.hbase.master.procedure.MasterProcedureEnv$WALStoreLeaseRecovery(org.apache.hadoop.hbase.master.MasterServices);
    Code:
       0: aload_0
       1: invokespecial #2                  // Method java/lang/Object."<init>":()V
       4: aload_0
       5: aload_1
       6: putfield      #3                  // Field master:Lorg/apache/hadoop/hbase/master/MasterServices;
       9: return

  public void recoverFileLease(org.apache.hadoop.fs.FileSystem, org.apache.hadoop.fs.Path) throws java.io.IOException;
    Code:
       0: aload_0
       1: getfield      #3                  // Field master:Lorg/apache/hadoop/hbase/master/MasterServices;
       4: invokeinterface #4,  1            // InterfaceMethod org/apache/hadoop/hbase/master/MasterServices.getConfiguration:()Lorg/apache/hadoop/conf/Configuration;
       9: astore_3
      10: aload_1
      11: aload_3
      12: invokestatic  #5                  // Method org/apache/hadoop/hbase/util/FSUtils.getInstance:(Lorg/apache/hadoop/fs/FileSystem;Lorg/apache/hadoop/conf/Configuration;)Lorg/apache/hadoop/hbase/util/FSUtils;
      15: astore        4
      17: aload         4
      19: aload_1
      20: aload_2
      21: aload_3
      22: new           #6                  // class org/apache/hadoop/hbase/master/procedure/MasterProcedureEnv$WALStoreLeaseRecovery$1
      25: dup
      26: aload_0
      27: aload_2
      28: invokespecial #7                  // Method org/apache/hadoop/hbase/master/procedure/MasterProcedureEnv$WALStoreLeaseRecovery$1."<init>":(Lorg/apache/hadoop/hbase/master/procedure/MasterProcedureEnv$WALStoreLeaseRecovery;Lorg/apache/hadoop/fs/Path;)V
      31: invokevirtual #8                  // Method org/apache/hadoop/hbase/util/FSUtils.recoverFileLease:(Lorg/apache/hadoop/fs/FileSystem;Lorg/apache/hadoop/fs/Path;Lorg/apache/hadoop/conf/Configuration;Lorg/apache/hadoop/hbase/util/CancelableProgressable;)V
      34: return

  static boolean access$100(org.apache.hadoop.hbase.master.procedure.MasterProcedureEnv$WALStoreLeaseRecovery);
    Code:
       0: aload_0
       1: invokespecial #1                  // Method isRunning:()Z
       4: ireturn
}
