Compiled from "MasterProcedureProtos.java"
public final class org.apache.hadoop.hbase.shaded.protobuf.generated.MasterProcedureProtos$SyncReplicationReplayWALStateData$Builder extends org.apache.hbase.thirdparty.com.google.protobuf.GeneratedMessageV3$Builder<org.apache.hadoop.hbase.shaded.protobuf.generated.MasterProcedureProtos$SyncReplicationReplayWALStateData$Builder> implements org.apache.hadoop.hbase.shaded.protobuf.generated.MasterProcedureProtos$SyncReplicationReplayWALStateDataOrBuilder {
  public static final org.apache.hbase.thirdparty.com.google.protobuf.Descriptors$Descriptor getDescriptor();
    Code:
       0: invokestatic  #3                  // Method org/apache/hadoop/hbase/shaded/protobuf/generated/MasterProcedureProtos.access$42800:()Lorg/apache/hbase/thirdparty/com/google/protobuf/Descriptors$Descriptor;
       3: areturn

  protected org.apache.hbase.thirdparty.com.google.protobuf.GeneratedMessageV3$FieldAccessorTable internalGetFieldAccessorTable();
    Code:
       0: invokestatic  #4                  // Method org/apache/hadoop/hbase/shaded/protobuf/generated/MasterProcedureProtos.access$42900:()Lorg/apache/hbase/thirdparty/com/google/protobuf/GeneratedMessageV3$FieldAccessorTable;
       3: ldc           #5                  // class org/apache/hadoop/hbase/shaded/protobuf/generated/MasterProcedureProtos$SyncReplicationReplayWALStateData
       5: ldc           #6                  // class org/apache/hadoop/hbase/shaded/protobuf/generated/MasterProcedureProtos$SyncReplicationReplayWALStateData$Builder
       7: invokevirtual #7                  // Method org/apache/hbase/thirdparty/com/google/protobuf/GeneratedMessageV3$FieldAccessorTable.ensureFieldAccessorsInitialized:(Ljava/lang/Class;Ljava/lang/Class;)Lorg/apache/hbase/thirdparty/com/google/protobuf/GeneratedMessageV3$FieldAccessorTable;
      10: areturn

  public org.apache.hadoop.hbase.shaded.protobuf.generated.MasterProcedureProtos$SyncReplicationReplayWALStateData$Builder clear();
    Code:
       0: aload_0
       1: invokespecial #18                 // Method org/apache/hbase/thirdparty/com/google/protobuf/GeneratedMessageV3$Builder.clear:()Lorg/apache/hbase/thirdparty/com/google/protobuf/GeneratedMessageV3$Builder;
       4: pop
       5: aload_0
       6: ldc           #9                  // String
       8: putfield      #10                 // Field peerId_:Ljava/lang/Object;
      11: aload_0
      12: aload_0
      13: getfield      #19                 // Field bitField0_:I
      16: bipush        -2
      18: iand
      19: putfield      #19                 // Field bitField0_:I
      22: aload_0
      23: getstatic     #11                 // Field org/apache/hbase/thirdparty/com/google/protobuf/LazyStringArrayList.EMPTY:Lorg/apache/hbase/thirdparty/com/google/protobuf/LazyStringList;
      26: putfield      #12                 // Field wal_:Lorg/apache/hbase/thirdparty/com/google/protobuf/LazyStringList;
      29: aload_0
      30: aload_0
      31: getfield      #19                 // Field bitField0_:I
      34: bipush        -3
      36: iand
      37: putfield      #19                 // Field bitField0_:I
      40: aload_0
      41: getfield      #20                 // Field workerBuilder_:Lorg/apache/hbase/thirdparty/com/google/protobuf/SingleFieldBuilderV3;
      44: ifnonnull     55
      47: aload_0
      48: aconst_null
      49: putfield      #13                 // Field worker_:Lorg/apache/hadoop/hbase/shaded/protobuf/generated/HBaseProtos$ServerName;
      52: goto          63
      55: aload_0
      56: getfield      #20                 // Field workerBuilder_:Lorg/apache/hbase/thirdparty/com/google/protobuf/SingleFieldBuilderV3;
      59: invokevirtual #21                 // Method org/apache/hbase/thirdparty/com/google/protobuf/SingleFieldBuilderV3.clear:()Lorg/apache/hbase/thirdparty/com/google/protobuf/SingleFieldBuilderV3;
      62: pop
      63: aload_0
      64: aload_0
      65: getfield      #19                 // Field bitField0_:I
      68: bipush        -5
      70: iand
      71: putfield      #19                 // Field bitField0_:I
      74: aload_0
      75: areturn

  public org.apache.hbase.thirdparty.com.google.protobuf.Descriptors$Descriptor getDescriptorForType();
    Code:
       0: invokestatic  #3                  // Method org/apache/hadoop/hbase/shaded/protobuf/generated/MasterProcedureProtos.access$42800:()Lorg/apache/hbase/thirdparty/com/google/protobuf/Descriptors$Descriptor;
       3: areturn

  public org.apache.hadoop.hbase.shaded.protobuf.generated.MasterProcedureProtos$SyncReplicationReplayWALStateData getDefaultInstanceForType();
    Code:
       0: invokestatic  #22                 // Method org/apache/hadoop/hbase/shaded/protobuf/generated/MasterProcedureProtos$SyncReplicationReplayWALStateData.getDefaultInstance:()Lorg/apache/hadoop/hbase/shaded/protobuf/generated/MasterProcedureProtos$SyncReplicationReplayWALStateData;
       3: areturn

  public org.apache.hadoop.hbase.shaded.protobuf.generated.MasterProcedureProtos$SyncReplicationReplayWALStateData build();
    Code:
       0: aload_0
       1: invokevirtual #23                 // Method buildPartial:()Lorg/apache/hadoop/hbase/shaded/protobuf/generated/MasterProcedureProtos$SyncReplicationReplayWALStateData;
       4: astore_1
       5: aload_1
       6: invokevirtual #24                 // Method org/apache/hadoop/hbase/shaded/protobuf/generated/MasterProcedureProtos$SyncReplicationReplayWALStateData.isInitialized:()Z
       9: ifne          17
      12: aload_1
      13: invokestatic  #25                 // Method newUninitializedMessageException:(Lorg/apache/hbase/thirdparty/com/google/protobuf/Message;)Lorg/apache/hbase/thirdparty/com/google/protobuf/UninitializedMessageException;
      16: athrow
      17: aload_1
      18: areturn

  public org.apache.hadoop.hbase.shaded.protobuf.generated.MasterProcedureProtos$SyncReplicationReplayWALStateData buildPartial();
    Code:
       0: new           #5                  // class org/apache/hadoop/hbase/shaded/protobuf/generated/MasterProcedureProtos$SyncReplicationReplayWALStateData
       3: dup
       4: aload_0
       5: aconst_null
       6: invokespecial #26                 // Method org/apache/hadoop/hbase/shaded/protobuf/generated/MasterProcedureProtos$SyncReplicationReplayWALStateData."<init>":(Lorg/apache/hbase/thirdparty/com/google/protobuf/GeneratedMessageV3$Builder;Lorg/apache/hadoop/hbase/shaded/protobuf/generated/MasterProcedureProtos$1;)V
       9: astore_1
      10: aload_0
      11: getfield      #19                 // Field bitField0_:I
      14: istore_2
      15: iconst_0
      16: istore_3
      17: iload_2
      18: iconst_1
      19: iand
      20: iconst_1
      21: if_icmpne     28
      24: iload_3
      25: iconst_1
      26: ior
      27: istore_3
      28: aload_1
      29: aload_0
      30: getfield      #10                 // Field peerId_:Ljava/lang/Object;
      33: invokestatic  #27                 // Method org/apache/hadoop/hbase/shaded/protobuf/generated/MasterProcedureProtos$SyncReplicationReplayWALStateData.access$43402:(Lorg/apache/hadoop/hbase/shaded/protobuf/generated/MasterProcedureProtos$SyncReplicationReplayWALStateData;Ljava/lang/Object;)Ljava/lang/Object;
      36: pop
      37: aload_0
      38: getfield      #19                 // Field bitField0_:I
      41: iconst_2
      42: iand
      43: iconst_2
      44: if_icmpne     71
      47: aload_0
      48: aload_0
      49: getfield      #12                 // Field wal_:Lorg/apache/hbase/thirdparty/com/google/protobuf/LazyStringList;
      52: invokeinterface #28,  1           // InterfaceMethod org/apache/hbase/thirdparty/com/google/protobuf/LazyStringList.getUnmodifiableView:()Lorg/apache/hbase/thirdparty/com/google/protobuf/LazyStringList;
      57: putfield      #12                 // Field wal_:Lorg/apache/hbase/thirdparty/com/google/protobuf/LazyStringList;
      60: aload_0
      61: aload_0
      62: getfield      #19                 // Field bitField0_:I
      65: bipush        -3
      67: iand
      68: putfield      #19                 // Field bitField0_:I
      71: aload_1
      72: aload_0
      73: getfield      #12                 // Field wal_:Lorg/apache/hbase/thirdparty/com/google/protobuf/LazyStringList;
      76: invokestatic  #29                 // Method org/apache/hadoop/hbase/shaded/protobuf/generated/MasterProcedureProtos$SyncReplicationReplayWALStateData.access$43502:(Lorg/apache/hadoop/hbase/shaded/protobuf/generated/MasterProcedureProtos$SyncReplicationReplayWALStateData;Lorg/apache/hbase/thirdparty/com/google/protobuf/LazyStringList;)Lorg/apache/hbase/thirdparty/com/google/protobuf/LazyStringList;
      79: pop
      80: iload_2
      81: iconst_4
      82: iand
      83: iconst_4
      84: if_icmpne     91
      87: iload_3
      88: iconst_2
      89: ior
      90: istore_3
      91: aload_0
      92: getfield      #20                 // Field workerBuilder_:Lorg/apache/hbase/thirdparty/com/google/protobuf/SingleFieldBuilderV3;
      95: ifnonnull     110
      98: aload_1
      99: aload_0
     100: getfield      #13                 // Field worker_:Lorg/apache/hadoop/hbase/shaded/protobuf/generated/HBaseProtos$ServerName;
     103: invokestatic  #30                 // Method org/apache/hadoop/hbase/shaded/protobuf/generated/MasterProcedureProtos$SyncReplicationReplayWALStateData.access$43602:(Lorg/apache/hadoop/hbase/shaded/protobuf/generated/MasterProcedureProtos$SyncReplicationReplayWALStateData;Lorg/apache/hadoop/hbase/shaded/protobuf/generated/HBaseProtos$ServerName;)Lorg/apache/hadoop/hbase/shaded/protobuf/generated/HBaseProtos$ServerName;
     106: pop
     107: goto          125
     110: aload_1
     111: aload_0
     112: getfield      #20                 // Field workerBuilder_:Lorg/apache/hbase/thirdparty/com/google/protobuf/SingleFieldBuilderV3;
     115: invokevirtual #31                 // Method org/apache/hbase/thirdparty/com/google/protobuf/SingleFieldBuilderV3.build:()Lorg/apache/hbase/thirdparty/com/google/protobuf/AbstractMessage;
     118: checkcast     #32                 // class org/apache/hadoop/hbase/shaded/protobuf/generated/HBaseProtos$ServerName
     121: invokestatic  #30                 // Method org/apache/hadoop/hbase/shaded/protobuf/generated/MasterProcedureProtos$SyncReplicationReplayWALStateData.access$43602:(Lorg/apache/hadoop/hbase/shaded/protobuf/generated/MasterProcedureProtos$SyncReplicationReplayWALStateData;Lorg/apache/hadoop/hbase/shaded/protobuf/generated/HBaseProtos$ServerName;)Lorg/apache/hadoop/hbase/shaded/protobuf/generated/HBaseProtos$ServerName;
     124: pop
     125: aload_1
     126: iload_3
     127: invokestatic  #33                 // Method org/apache/hadoop/hbase/shaded/protobuf/generated/MasterProcedureProtos$SyncReplicationReplayWALStateData.access$43702:(Lorg/apache/hadoop/hbase/shaded/protobuf/generated/MasterProcedureProtos$SyncReplicationReplayWALStateData;I)I
     130: pop
     131: aload_0
     132: invokevirtual #34                 // Method onBuilt:()V
     135: aload_1
     136: areturn

  public org.apache.hadoop.hbase.shaded.protobuf.generated.MasterProcedureProtos$SyncReplicationReplayWALStateData$Builder clone();
    Code:
       0: aload_0
       1: invokespecial #35                 // Method org/apache/hbase/thirdparty/com/google/protobuf/GeneratedMessageV3$Builder.clone:()Lorg/apache/hbase/thirdparty/com/google/protobuf/GeneratedMessageV3$Builder;
       4: checkcast     #6                  // class org/apache/hadoop/hbase/shaded/protobuf/generated/MasterProcedureProtos$SyncReplicationReplayWALStateData$Builder
       7: areturn

  public org.apache.hadoop.hbase.shaded.protobuf.generated.MasterProcedureProtos$SyncReplicationReplayWALStateData$Builder setField(org.apache.hbase.thirdparty.com.google.protobuf.Descriptors$FieldDescriptor, java.lang.Object);
    Code:
       0: aload_0
       1: aload_1
       2: aload_2
       3: invokespecial #36                 // Method org/apache/hbase/thirdparty/com/google/protobuf/GeneratedMessageV3$Builder.setField:(Lorg/apache/hbase/thirdparty/com/google/protobuf/Descriptors$FieldDescriptor;Ljava/lang/Object;)Lorg/apache/hbase/thirdparty/com/google/protobuf/GeneratedMessageV3$Builder;
       6: checkcast     #6                  // class org/apache/hadoop/hbase/shaded/protobuf/generated/MasterProcedureProtos$SyncReplicationReplayWALStateData$Builder
       9: areturn

  public org.apache.hadoop.hbase.shaded.protobuf.generated.MasterProcedureProtos$SyncReplicationReplayWALStateData$Builder clearField(org.apache.hbase.thirdparty.com.google.protobuf.Descriptors$FieldDescriptor);
    Code:
       0: aload_0
       1: aload_1
       2: invokespecial #37                 // Method org/apache/hbase/thirdparty/com/google/protobuf/GeneratedMessageV3$Builder.clearField:(Lorg/apache/hbase/thirdparty/com/google/protobuf/Descriptors$FieldDescriptor;)Lorg/apache/hbase/thirdparty/com/google/protobuf/GeneratedMessageV3$Builder;
       5: checkcast     #6                  // class org/apache/hadoop/hbase/shaded/protobuf/generated/MasterProcedureProtos$SyncReplicationReplayWALStateData$Builder
       8: areturn

  public org.apache.hadoop.hbase.shaded.protobuf.generated.MasterProcedureProtos$SyncReplicationReplayWALStateData$Builder clearOneof(org.apache.hbase.thirdparty.com.google.protobuf.Descriptors$OneofDescriptor);
    Code:
       0: aload_0
       1: aload_1
       2: invokespecial #38                 // Method org/apache/hbase/thirdparty/com/google/protobuf/GeneratedMessageV3$Builder.clearOneof:(Lorg/apache/hbase/thirdparty/com/google/protobuf/Descriptors$OneofDescriptor;)Lorg/apache/hbase/thirdparty/com/google/protobuf/GeneratedMessageV3$Builder;
       5: checkcast     #6                  // class org/apache/hadoop/hbase/shaded/protobuf/generated/MasterProcedureProtos$SyncReplicationReplayWALStateData$Builder
       8: areturn

  public org.apache.hadoop.hbase.shaded.protobuf.generated.MasterProcedureProtos$SyncReplicationReplayWALStateData$Builder setRepeatedField(org.apache.hbase.thirdparty.com.google.protobuf.Descriptors$FieldDescriptor, int, java.lang.Object);
    Code:
       0: aload_0
       1: aload_1
       2: iload_2
       3: aload_3
       4: invokespecial #39                 // Method org/apache/hbase/thirdparty/com/google/protobuf/GeneratedMessageV3$Builder.setRepeatedField:(Lorg/apache/hbase/thirdparty/com/google/protobuf/Descriptors$FieldDescriptor;ILjava/lang/Object;)Lorg/apache/hbase/thirdparty/com/google/protobuf/GeneratedMessageV3$Builder;
       7: checkcast     #6                  // class org/apache/hadoop/hbase/shaded/protobuf/generated/MasterProcedureProtos$SyncReplicationReplayWALStateData$Builder
      10: areturn

  public org.apache.hadoop.hbase.shaded.protobuf.generated.MasterProcedureProtos$SyncReplicationReplayWALStateData$Builder addRepeatedField(org.apache.hbase.thirdparty.com.google.protobuf.Descriptors$FieldDescriptor, java.lang.Object);
    Code:
       0: aload_0
       1: aload_1
       2: aload_2
       3: invokespecial #40                 // Method org/apache/hbase/thirdparty/com/google/protobuf/GeneratedMessageV3$Builder.addRepeatedField:(Lorg/apache/hbase/thirdparty/com/google/protobuf/Descriptors$FieldDescriptor;Ljava/lang/Object;)Lorg/apache/hbase/thirdparty/com/google/protobuf/GeneratedMessageV3$Builder;
       6: checkcast     #6                  // class org/apache/hadoop/hbase/shaded/protobuf/generated/MasterProcedureProtos$SyncReplicationReplayWALStateData$Builder
       9: areturn

  public org.apache.hadoop.hbase.shaded.protobuf.generated.MasterProcedureProtos$SyncReplicationReplayWALStateData$Builder mergeFrom(org.apache.hbase.thirdparty.com.google.protobuf.Message);
    Code:
       0: aload_1
       1: instanceof    #5                  // class org/apache/hadoop/hbase/shaded/protobuf/generated/MasterProcedureProtos$SyncReplicationReplayWALStateData
       4: ifeq          16
       7: aload_0
       8: aload_1
       9: checkcast     #5                  // class org/apache/hadoop/hbase/shaded/protobuf/generated/MasterProcedureProtos$SyncReplicationReplayWALStateData
      12: invokevirtual #41                 // Method mergeFrom:(Lorg/apache/hadoop/hbase/shaded/protobuf/generated/MasterProcedureProtos$SyncReplicationReplayWALStateData;)Lorg/apache/hadoop/hbase/shaded/protobuf/generated/MasterProcedureProtos$SyncReplicationReplayWALStateData$Builder;
      15: areturn
      16: aload_0
      17: aload_1
      18: invokespecial #42                 // Method org/apache/hbase/thirdparty/com/google/protobuf/GeneratedMessageV3$Builder.mergeFrom:(Lorg/apache/hbase/thirdparty/com/google/protobuf/Message;)Lorg/apache/hbase/thirdparty/com/google/protobuf/AbstractMessage$Builder;
      21: pop
      22: aload_0
      23: areturn

  public org.apache.hadoop.hbase.shaded.protobuf.generated.MasterProcedureProtos$SyncReplicationReplayWALStateData$Builder mergeFrom(org.apache.hadoop.hbase.shaded.protobuf.generated.MasterProcedureProtos$SyncReplicationReplayWALStateData);
    Code:
       0: aload_1
       1: invokestatic  #22                 // Method org/apache/hadoop/hbase/shaded/protobuf/generated/MasterProcedureProtos$SyncReplicationReplayWALStateData.getDefaultInstance:()Lorg/apache/hadoop/hbase/shaded/protobuf/generated/MasterProcedureProtos$SyncReplicationReplayWALStateData;
       4: if_acmpne     9
       7: aload_0
       8: areturn
       9: aload_1
      10: invokevirtual #43                 // Method org/apache/hadoop/hbase/shaded/protobuf/generated/MasterProcedureProtos$SyncReplicationReplayWALStateData.hasPeerId:()Z
      13: ifeq          38
      16: aload_0
      17: dup
      18: getfield      #19                 // Field bitField0_:I
      21: iconst_1
      22: ior
      23: putfield      #19                 // Field bitField0_:I
      26: aload_0
      27: aload_1
      28: invokestatic  #44                 // Method org/apache/hadoop/hbase/shaded/protobuf/generated/MasterProcedureProtos$SyncReplicationReplayWALStateData.access$43400:(Lorg/apache/hadoop/hbase/shaded/protobuf/generated/MasterProcedureProtos$SyncReplicationReplayWALStateData;)Ljava/lang/Object;
      31: putfield      #10                 // Field peerId_:Ljava/lang/Object;
      34: aload_0
      35: invokevirtual #45                 // Method onChanged:()V
      38: aload_1
      39: invokestatic  #46                 // Method org/apache/hadoop/hbase/shaded/protobuf/generated/MasterProcedureProtos$SyncReplicationReplayWALStateData.access$43500:(Lorg/apache/hadoop/hbase/shaded/protobuf/generated/MasterProcedureProtos$SyncReplicationReplayWALStateData;)Lorg/apache/hbase/thirdparty/com/google/protobuf/LazyStringList;
      42: invokeinterface #47,  1           // InterfaceMethod org/apache/hbase/thirdparty/com/google/protobuf/LazyStringList.isEmpty:()Z
      47: ifne          106
      50: aload_0
      51: getfield      #12                 // Field wal_:Lorg/apache/hbase/thirdparty/com/google/protobuf/LazyStringList;
      54: invokeinterface #47,  1           // InterfaceMethod org/apache/hbase/thirdparty/com/google/protobuf/LazyStringList.isEmpty:()Z
      59: ifeq          84
      62: aload_0
      63: aload_1
      64: invokestatic  #46                 // Method org/apache/hadoop/hbase/shaded/protobuf/generated/MasterProcedureProtos$SyncReplicationReplayWALStateData.access$43500:(Lorg/apache/hadoop/hbase/shaded/protobuf/generated/MasterProcedureProtos$SyncReplicationReplayWALStateData;)Lorg/apache/hbase/thirdparty/com/google/protobuf/LazyStringList;
      67: putfield      #12                 // Field wal_:Lorg/apache/hbase/thirdparty/com/google/protobuf/LazyStringList;
      70: aload_0
      71: aload_0
      72: getfield      #19                 // Field bitField0_:I
      75: bipush        -3
      77: iand
      78: putfield      #19                 // Field bitField0_:I
      81: goto          102
      84: aload_0
      85: invokespecial #48                 // Method ensureWalIsMutable:()V
      88: aload_0
      89: getfield      #12                 // Field wal_:Lorg/apache/hbase/thirdparty/com/google/protobuf/LazyStringList;
      92: aload_1
      93: invokestatic  #46                 // Method org/apache/hadoop/hbase/shaded/protobuf/generated/MasterProcedureProtos$SyncReplicationReplayWALStateData.access$43500:(Lorg/apache/hadoop/hbase/shaded/protobuf/generated/MasterProcedureProtos$SyncReplicationReplayWALStateData;)Lorg/apache/hbase/thirdparty/com/google/protobuf/LazyStringList;
      96: invokeinterface #49,  2           // InterfaceMethod org/apache/hbase/thirdparty/com/google/protobuf/LazyStringList.addAll:(Ljava/util/Collection;)Z
     101: pop
     102: aload_0
     103: invokevirtual #45                 // Method onChanged:()V
     106: aload_1
     107: invokevirtual #50                 // Method org/apache/hadoop/hbase/shaded/protobuf/generated/MasterProcedureProtos$SyncReplicationReplayWALStateData.hasWorker:()Z
     110: ifeq          122
     113: aload_0
     114: aload_1
     115: invokevirtual #51                 // Method org/apache/hadoop/hbase/shaded/protobuf/generated/MasterProcedureProtos$SyncReplicationReplayWALStateData.getWorker:()Lorg/apache/hadoop/hbase/shaded/protobuf/generated/HBaseProtos$ServerName;
     118: invokevirtual #52                 // Method mergeWorker:(Lorg/apache/hadoop/hbase/shaded/protobuf/generated/HBaseProtos$ServerName;)Lorg/apache/hadoop/hbase/shaded/protobuf/generated/MasterProcedureProtos$SyncReplicationReplayWALStateData$Builder;
     121: pop
     122: aload_0
     123: aload_1
     124: invokestatic  #53                 // Method org/apache/hadoop/hbase/shaded/protobuf/generated/MasterProcedureProtos$SyncReplicationReplayWALStateData.access$43800:(Lorg/apache/hadoop/hbase/shaded/protobuf/generated/MasterProcedureProtos$SyncReplicationReplayWALStateData;)Lorg/apache/hbase/thirdparty/com/google/protobuf/UnknownFieldSet;
     127: invokevirtual #54                 // Method mergeUnknownFields:(Lorg/apache/hbase/thirdparty/com/google/protobuf/UnknownFieldSet;)Lorg/apache/hadoop/hbase/shaded/protobuf/generated/MasterProcedureProtos$SyncReplicationReplayWALStateData$Builder;
     130: pop
     131: aload_0
     132: invokevirtual #45                 // Method onChanged:()V
     135: aload_0
     136: areturn

  public final boolean isInitialized();
    Code:
       0: aload_0
       1: invokevirtual #55                 // Method hasPeerId:()Z
       4: ifne          9
       7: iconst_0
       8: ireturn
       9: aload_0
      10: invokevirtual #56                 // Method hasWorker:()Z
      13: ifeq          28
      16: aload_0
      17: invokevirtual #57                 // Method getWorker:()Lorg/apache/hadoop/hbase/shaded/protobuf/generated/HBaseProtos$ServerName;
      20: invokevirtual #58                 // Method org/apache/hadoop/hbase/shaded/protobuf/generated/HBaseProtos$ServerName.isInitialized:()Z
      23: ifne          28
      26: iconst_0
      27: ireturn
      28: iconst_1
      29: ireturn

  public org.apache.hadoop.hbase.shaded.protobuf.generated.MasterProcedureProtos$SyncReplicationReplayWALStateData$Builder mergeFrom(org.apache.hbase.thirdparty.com.google.protobuf.CodedInputStream, org.apache.hbase.thirdparty.com.google.protobuf.ExtensionRegistryLite) throws java.io.IOException;
    Code:
       0: aconst_null
       1: astore_3
       2: getstatic     #59                 // Field org/apache/hadoop/hbase/shaded/protobuf/generated/MasterProcedureProtos$SyncReplicationReplayWALStateData.PARSER:Lorg/apache/hbase/thirdparty/com/google/protobuf/Parser;
       5: aload_1
       6: aload_2
       7: invokeinterface #60,  3           // InterfaceMethod org/apache/hbase/thirdparty/com/google/protobuf/Parser.parsePartialFrom:(Lorg/apache/hbase/thirdparty/com/google/protobuf/CodedInputStream;Lorg/apache/hbase/thirdparty/com/google/protobuf/ExtensionRegistryLite;)Ljava/lang/Object;
      12: checkcast     #5                  // class org/apache/hadoop/hbase/shaded/protobuf/generated/MasterProcedureProtos$SyncReplicationReplayWALStateData
      15: astore_3
      16: aload_3
      17: ifnull        61
      20: aload_0
      21: aload_3
      22: invokevirtual #41                 // Method mergeFrom:(Lorg/apache/hadoop/hbase/shaded/protobuf/generated/MasterProcedureProtos$SyncReplicationReplayWALStateData;)Lorg/apache/hadoop/hbase/shaded/protobuf/generated/MasterProcedureProtos$SyncReplicationReplayWALStateData$Builder;
      25: pop
      26: goto          61
      29: astore        4
      31: aload         4
      33: invokevirtual #62                 // Method org/apache/hbase/thirdparty/com/google/protobuf/InvalidProtocolBufferException.getUnfinishedMessage:()Lorg/apache/hbase/thirdparty/com/google/protobuf/MessageLite;
      36: checkcast     #5                  // class org/apache/hadoop/hbase/shaded/protobuf/generated/MasterProcedureProtos$SyncReplicationReplayWALStateData
      39: astore_3
      40: aload         4
      42: invokevirtual #63                 // Method org/apache/hbase/thirdparty/com/google/protobuf/InvalidProtocolBufferException.unwrapIOException:()Ljava/io/IOException;
      45: athrow
      46: astore        5
      48: aload_3
      49: ifnull        58
      52: aload_0
      53: aload_3
      54: invokevirtual #41                 // Method mergeFrom:(Lorg/apache/hadoop/hbase/shaded/protobuf/generated/MasterProcedureProtos$SyncReplicationReplayWALStateData;)Lorg/apache/hadoop/hbase/shaded/protobuf/generated/MasterProcedureProtos$SyncReplicationReplayWALStateData$Builder;
      57: pop
      58: aload         5
      60: athrow
      61: aload_0
      62: areturn
    Exception table:
       from    to  target type
           2    16    29   Class org/apache/hbase/thirdparty/com/google/protobuf/InvalidProtocolBufferException
           2    16    46   any
          29    48    46   any

  public boolean hasPeerId();
    Code:
       0: aload_0
       1: getfield      #19                 // Field bitField0_:I
       4: iconst_1
       5: iand
       6: iconst_1
       7: if_icmpne     14
      10: iconst_1
      11: goto          15
      14: iconst_0
      15: ireturn

  public java.lang.String getPeerId();
    Code:
       0: aload_0
       1: getfield      #10                 // Field peerId_:Ljava/lang/Object;
       4: astore_1
       5: aload_1
       6: instanceof    #64                 // class java/lang/String
       9: ifne          36
      12: aload_1
      13: checkcast     #65                 // class org/apache/hbase/thirdparty/com/google/protobuf/ByteString
      16: astore_2
      17: aload_2
      18: invokevirtual #66                 // Method org/apache/hbase/thirdparty/com/google/protobuf/ByteString.toStringUtf8:()Ljava/lang/String;
      21: astore_3
      22: aload_2
      23: invokevirtual #67                 // Method org/apache/hbase/thirdparty/com/google/protobuf/ByteString.isValidUtf8:()Z
      26: ifeq          34
      29: aload_0
      30: aload_3
      31: putfield      #10                 // Field peerId_:Ljava/lang/Object;
      34: aload_3
      35: areturn
      36: aload_1
      37: checkcast     #64                 // class java/lang/String
      40: areturn

  public org.apache.hbase.thirdparty.com.google.protobuf.ByteString getPeerIdBytes();
    Code:
       0: aload_0
       1: getfield      #10                 // Field peerId_:Ljava/lang/Object;
       4: astore_1
       5: aload_1
       6: instanceof    #64                 // class java/lang/String
       9: ifeq          27
      12: aload_1
      13: checkcast     #64                 // class java/lang/String
      16: invokestatic  #68                 // Method org/apache/hbase/thirdparty/com/google/protobuf/ByteString.copyFromUtf8:(Ljava/lang/String;)Lorg/apache/hbase/thirdparty/com/google/protobuf/ByteString;
      19: astore_2
      20: aload_0
      21: aload_2
      22: putfield      #10                 // Field peerId_:Ljava/lang/Object;
      25: aload_2
      26: areturn
      27: aload_1
      28: checkcast     #65                 // class org/apache/hbase/thirdparty/com/google/protobuf/ByteString
      31: areturn

  public org.apache.hadoop.hbase.shaded.protobuf.generated.MasterProcedureProtos$SyncReplicationReplayWALStateData$Builder setPeerId(java.lang.String);
    Code:
       0: aload_1
       1: ifnonnull     12
       4: new           #69                 // class java/lang/NullPointerException
       7: dup
       8: invokespecial #70                 // Method java/lang/NullPointerException."<init>":()V
      11: athrow
      12: aload_0
      13: dup
      14: getfield      #19                 // Field bitField0_:I
      17: iconst_1
      18: ior
      19: putfield      #19                 // Field bitField0_:I
      22: aload_0
      23: aload_1
      24: putfield      #10                 // Field peerId_:Ljava/lang/Object;
      27: aload_0
      28: invokevirtual #45                 // Method onChanged:()V
      31: aload_0
      32: areturn

  public org.apache.hadoop.hbase.shaded.protobuf.generated.MasterProcedureProtos$SyncReplicationReplayWALStateData$Builder clearPeerId();
    Code:
       0: aload_0
       1: aload_0
       2: getfield      #19                 // Field bitField0_:I
       5: bipush        -2
       7: iand
       8: putfield      #19                 // Field bitField0_:I
      11: aload_0
      12: invokestatic  #22                 // Method org/apache/hadoop/hbase/shaded/protobuf/generated/MasterProcedureProtos$SyncReplicationReplayWALStateData.getDefaultInstance:()Lorg/apache/hadoop/hbase/shaded/protobuf/generated/MasterProcedureProtos$SyncReplicationReplayWALStateData;
      15: invokevirtual #71                 // Method org/apache/hadoop/hbase/shaded/protobuf/generated/MasterProcedureProtos$SyncReplicationReplayWALStateData.getPeerId:()Ljava/lang/String;
      18: putfield      #10                 // Field peerId_:Ljava/lang/Object;
      21: aload_0
      22: invokevirtual #45                 // Method onChanged:()V
      25: aload_0
      26: areturn

  public org.apache.hadoop.hbase.shaded.protobuf.generated.MasterProcedureProtos$SyncReplicationReplayWALStateData$Builder setPeerIdBytes(org.apache.hbase.thirdparty.com.google.protobuf.ByteString);
    Code:
       0: aload_1
       1: ifnonnull     12
       4: new           #69                 // class java/lang/NullPointerException
       7: dup
       8: invokespecial #70                 // Method java/lang/NullPointerException."<init>":()V
      11: athrow
      12: aload_0
      13: dup
      14: getfield      #19                 // Field bitField0_:I
      17: iconst_1
      18: ior
      19: putfield      #19                 // Field bitField0_:I
      22: aload_0
      23: aload_1
      24: putfield      #10                 // Field peerId_:Ljava/lang/Object;
      27: aload_0
      28: invokevirtual #45                 // Method onChanged:()V
      31: aload_0
      32: areturn

  public org.apache.hbase.thirdparty.com.google.protobuf.ProtocolStringList getWalList();
    Code:
       0: aload_0
       1: getfield      #12                 // Field wal_:Lorg/apache/hbase/thirdparty/com/google/protobuf/LazyStringList;
       4: invokeinterface #28,  1           // InterfaceMethod org/apache/hbase/thirdparty/com/google/protobuf/LazyStringList.getUnmodifiableView:()Lorg/apache/hbase/thirdparty/com/google/protobuf/LazyStringList;
       9: areturn

  public int getWalCount();
    Code:
       0: aload_0
       1: getfield      #12                 // Field wal_:Lorg/apache/hbase/thirdparty/com/google/protobuf/LazyStringList;
       4: invokeinterface #74,  1           // InterfaceMethod org/apache/hbase/thirdparty/com/google/protobuf/LazyStringList.size:()I
       9: ireturn

  public java.lang.String getWal(int);
    Code:
       0: aload_0
       1: getfield      #12                 // Field wal_:Lorg/apache/hbase/thirdparty/com/google/protobuf/LazyStringList;
       4: iload_1
       5: invokeinterface #75,  2           // InterfaceMethod org/apache/hbase/thirdparty/com/google/protobuf/LazyStringList.get:(I)Ljava/lang/Object;
      10: checkcast     #64                 // class java/lang/String
      13: areturn

  public org.apache.hbase.thirdparty.com.google.protobuf.ByteString getWalBytes(int);
    Code:
       0: aload_0
       1: getfield      #12                 // Field wal_:Lorg/apache/hbase/thirdparty/com/google/protobuf/LazyStringList;
       4: iload_1
       5: invokeinterface #76,  2           // InterfaceMethod org/apache/hbase/thirdparty/com/google/protobuf/LazyStringList.getByteString:(I)Lorg/apache/hbase/thirdparty/com/google/protobuf/ByteString;
      10: areturn

  public org.apache.hadoop.hbase.shaded.protobuf.generated.MasterProcedureProtos$SyncReplicationReplayWALStateData$Builder setWal(int, java.lang.String);
    Code:
       0: aload_2
       1: ifnonnull     12
       4: new           #69                 // class java/lang/NullPointerException
       7: dup
       8: invokespecial #70                 // Method java/lang/NullPointerException."<init>":()V
      11: athrow
      12: aload_0
      13: invokespecial #48                 // Method ensureWalIsMutable:()V
      16: aload_0
      17: getfield      #12                 // Field wal_:Lorg/apache/hbase/thirdparty/com/google/protobuf/LazyStringList;
      20: iload_1
      21: aload_2
      22: invokeinterface #77,  3           // InterfaceMethod org/apache/hbase/thirdparty/com/google/protobuf/LazyStringList.set:(ILjava/lang/Object;)Ljava/lang/Object;
      27: pop
      28: aload_0
      29: invokevirtual #45                 // Method onChanged:()V
      32: aload_0
      33: areturn

  public org.apache.hadoop.hbase.shaded.protobuf.generated.MasterProcedureProtos$SyncReplicationReplayWALStateData$Builder addWal(java.lang.String);
    Code:
       0: aload_1
       1: ifnonnull     12
       4: new           #69                 // class java/lang/NullPointerException
       7: dup
       8: invokespecial #70                 // Method java/lang/NullPointerException."<init>":()V
      11: athrow
      12: aload_0
      13: invokespecial #48                 // Method ensureWalIsMutable:()V
      16: aload_0
      17: getfield      #12                 // Field wal_:Lorg/apache/hbase/thirdparty/com/google/protobuf/LazyStringList;
      20: aload_1
      21: invokeinterface #78,  2           // InterfaceMethod org/apache/hbase/thirdparty/com/google/protobuf/LazyStringList.add:(Ljava/lang/Object;)Z
      26: pop
      27: aload_0
      28: invokevirtual #45                 // Method onChanged:()V
      31: aload_0
      32: areturn

  public org.apache.hadoop.hbase.shaded.protobuf.generated.MasterProcedureProtos$SyncReplicationReplayWALStateData$Builder addAllWal(java.lang.Iterable<java.lang.String>);
    Code:
       0: aload_0
       1: invokespecial #48                 // Method ensureWalIsMutable:()V
       4: aload_1
       5: aload_0
       6: getfield      #12                 // Field wal_:Lorg/apache/hbase/thirdparty/com/google/protobuf/LazyStringList;
       9: invokestatic  #79                 // Method org/apache/hbase/thirdparty/com/google/protobuf/AbstractMessageLite$Builder.addAll:(Ljava/lang/Iterable;Ljava/util/List;)V
      12: aload_0
      13: invokevirtual #45                 // Method onChanged:()V
      16: aload_0
      17: areturn

  public org.apache.hadoop.hbase.shaded.protobuf.generated.MasterProcedureProtos$SyncReplicationReplayWALStateData$Builder clearWal();
    Code:
       0: aload_0
       1: getstatic     #11                 // Field org/apache/hbase/thirdparty/com/google/protobuf/LazyStringArrayList.EMPTY:Lorg/apache/hbase/thirdparty/com/google/protobuf/LazyStringList;
       4: putfield      #12                 // Field wal_:Lorg/apache/hbase/thirdparty/com/google/protobuf/LazyStringList;
       7: aload_0
       8: aload_0
       9: getfield      #19                 // Field bitField0_:I
      12: bipush        -3
      14: iand
      15: putfield      #19                 // Field bitField0_:I
      18: aload_0
      19: invokevirtual #45                 // Method onChanged:()V
      22: aload_0
      23: areturn

  public org.apache.hadoop.hbase.shaded.protobuf.generated.MasterProcedureProtos$SyncReplicationReplayWALStateData$Builder addWalBytes(org.apache.hbase.thirdparty.com.google.protobuf.ByteString);
    Code:
       0: aload_1
       1: ifnonnull     12
       4: new           #69                 // class java/lang/NullPointerException
       7: dup
       8: invokespecial #70                 // Method java/lang/NullPointerException."<init>":()V
      11: athrow
      12: aload_0
      13: invokespecial #48                 // Method ensureWalIsMutable:()V
      16: aload_0
      17: getfield      #12                 // Field wal_:Lorg/apache/hbase/thirdparty/com/google/protobuf/LazyStringList;
      20: aload_1
      21: invokeinterface #80,  2           // InterfaceMethod org/apache/hbase/thirdparty/com/google/protobuf/LazyStringList.add:(Lorg/apache/hbase/thirdparty/com/google/protobuf/ByteString;)V
      26: aload_0
      27: invokevirtual #45                 // Method onChanged:()V
      30: aload_0
      31: areturn

  public boolean hasWorker();
    Code:
       0: aload_0
       1: getfield      #19                 // Field bitField0_:I
       4: iconst_4
       5: iand
       6: iconst_4
       7: if_icmpne     14
      10: iconst_1
      11: goto          15
      14: iconst_0
      15: ireturn

  public org.apache.hadoop.hbase.shaded.protobuf.generated.HBaseProtos$ServerName getWorker();
    Code:
       0: aload_0
       1: getfield      #20                 // Field workerBuilder_:Lorg/apache/hbase/thirdparty/com/google/protobuf/SingleFieldBuilderV3;
       4: ifnonnull     25
       7: aload_0
       8: getfield      #13                 // Field worker_:Lorg/apache/hadoop/hbase/shaded/protobuf/generated/HBaseProtos$ServerName;
      11: ifnonnull     20
      14: invokestatic  #81                 // Method org/apache/hadoop/hbase/shaded/protobuf/generated/HBaseProtos$ServerName.getDefaultInstance:()Lorg/apache/hadoop/hbase/shaded/protobuf/generated/HBaseProtos$ServerName;
      17: goto          24
      20: aload_0
      21: getfield      #13                 // Field worker_:Lorg/apache/hadoop/hbase/shaded/protobuf/generated/HBaseProtos$ServerName;
      24: areturn
      25: aload_0
      26: getfield      #20                 // Field workerBuilder_:Lorg/apache/hbase/thirdparty/com/google/protobuf/SingleFieldBuilderV3;
      29: invokevirtual #82                 // Method org/apache/hbase/thirdparty/com/google/protobuf/SingleFieldBuilderV3.getMessage:()Lorg/apache/hbase/thirdparty/com/google/protobuf/AbstractMessage;
      32: checkcast     #32                 // class org/apache/hadoop/hbase/shaded/protobuf/generated/HBaseProtos$ServerName
      35: areturn

  public org.apache.hadoop.hbase.shaded.protobuf.generated.MasterProcedureProtos$SyncReplicationReplayWALStateData$Builder setWorker(org.apache.hadoop.hbase.shaded.protobuf.generated.HBaseProtos$ServerName);
    Code:
       0: aload_0
       1: getfield      #20                 // Field workerBuilder_:Lorg/apache/hbase/thirdparty/com/google/protobuf/SingleFieldBuilderV3;
       4: ifnonnull     31
       7: aload_1
       8: ifnonnull     19
      11: new           #69                 // class java/lang/NullPointerException
      14: dup
      15: invokespecial #70                 // Method java/lang/NullPointerException."<init>":()V
      18: athrow
      19: aload_0
      20: aload_1
      21: putfield      #13                 // Field worker_:Lorg/apache/hadoop/hbase/shaded/protobuf/generated/HBaseProtos$ServerName;
      24: aload_0
      25: invokevirtual #45                 // Method onChanged:()V
      28: goto          40
      31: aload_0
      32: getfield      #20                 // Field workerBuilder_:Lorg/apache/hbase/thirdparty/com/google/protobuf/SingleFieldBuilderV3;
      35: aload_1
      36: invokevirtual #83                 // Method org/apache/hbase/thirdparty/com/google/protobuf/SingleFieldBuilderV3.setMessage:(Lorg/apache/hbase/thirdparty/com/google/protobuf/AbstractMessage;)Lorg/apache/hbase/thirdparty/com/google/protobuf/SingleFieldBuilderV3;
      39: pop
      40: aload_0
      41: dup
      42: getfield      #19                 // Field bitField0_:I
      45: iconst_4
      46: ior
      47: putfield      #19                 // Field bitField0_:I
      50: aload_0
      51: areturn

  public org.apache.hadoop.hbase.shaded.protobuf.generated.MasterProcedureProtos$SyncReplicationReplayWALStateData$Builder setWorker(org.apache.hadoop.hbase.shaded.protobuf.generated.HBaseProtos$ServerName$Builder);
    Code:
       0: aload_0
       1: getfield      #20                 // Field workerBuilder_:Lorg/apache/hbase/thirdparty/com/google/protobuf/SingleFieldBuilderV3;
       4: ifnonnull     22
       7: aload_0
       8: aload_1
       9: invokevirtual #84                 // Method org/apache/hadoop/hbase/shaded/protobuf/generated/HBaseProtos$ServerName$Builder.build:()Lorg/apache/hadoop/hbase/shaded/protobuf/generated/HBaseProtos$ServerName;
      12: putfield      #13                 // Field worker_:Lorg/apache/hadoop/hbase/shaded/protobuf/generated/HBaseProtos$ServerName;
      15: aload_0
      16: invokevirtual #45                 // Method onChanged:()V
      19: goto          34
      22: aload_0
      23: getfield      #20                 // Field workerBuilder_:Lorg/apache/hbase/thirdparty/com/google/protobuf/SingleFieldBuilderV3;
      26: aload_1
      27: invokevirtual #84                 // Method org/apache/hadoop/hbase/shaded/protobuf/generated/HBaseProtos$ServerName$Builder.build:()Lorg/apache/hadoop/hbase/shaded/protobuf/generated/HBaseProtos$ServerName;
      30: invokevirtual #83                 // Method org/apache/hbase/thirdparty/com/google/protobuf/SingleFieldBuilderV3.setMessage:(Lorg/apache/hbase/thirdparty/com/google/protobuf/AbstractMessage;)Lorg/apache/hbase/thirdparty/com/google/protobuf/SingleFieldBuilderV3;
      33: pop
      34: aload_0
      35: dup
      36: getfield      #19                 // Field bitField0_:I
      39: iconst_4
      40: ior
      41: putfield      #19                 // Field bitField0_:I
      44: aload_0
      45: areturn

  public org.apache.hadoop.hbase.shaded.protobuf.generated.MasterProcedureProtos$SyncReplicationReplayWALStateData$Builder mergeWorker(org.apache.hadoop.hbase.shaded.protobuf.generated.HBaseProtos$ServerName);
    Code:
       0: aload_0
       1: getfield      #20                 // Field workerBuilder_:Lorg/apache/hbase/thirdparty/com/google/protobuf/SingleFieldBuilderV3;
       4: ifnonnull     67
       7: aload_0
       8: getfield      #19                 // Field bitField0_:I
      11: iconst_4
      12: iand
      13: iconst_4
      14: if_icmpne     55
      17: aload_0
      18: getfield      #13                 // Field worker_:Lorg/apache/hadoop/hbase/shaded/protobuf/generated/HBaseProtos$ServerName;
      21: ifnull        55
      24: aload_0
      25: getfield      #13                 // Field worker_:Lorg/apache/hadoop/hbase/shaded/protobuf/generated/HBaseProtos$ServerName;
      28: invokestatic  #81                 // Method org/apache/hadoop/hbase/shaded/protobuf/generated/HBaseProtos$ServerName.getDefaultInstance:()Lorg/apache/hadoop/hbase/shaded/protobuf/generated/HBaseProtos$ServerName;
      31: if_acmpeq     55
      34: aload_0
      35: aload_0
      36: getfield      #13                 // Field worker_:Lorg/apache/hadoop/hbase/shaded/protobuf/generated/HBaseProtos$ServerName;
      39: invokestatic  #85                 // Method org/apache/hadoop/hbase/shaded/protobuf/generated/HBaseProtos$ServerName.newBuilder:(Lorg/apache/hadoop/hbase/shaded/protobuf/generated/HBaseProtos$ServerName;)Lorg/apache/hadoop/hbase/shaded/protobuf/generated/HBaseProtos$ServerName$Builder;
      42: aload_1
      43: invokevirtual #86                 // Method org/apache/hadoop/hbase/shaded/protobuf/generated/HBaseProtos$ServerName$Builder.mergeFrom:(Lorg/apache/hadoop/hbase/shaded/protobuf/generated/HBaseProtos$ServerName;)Lorg/apache/hadoop/hbase/shaded/protobuf/generated/HBaseProtos$ServerName$Builder;
      46: invokevirtual #87                 // Method org/apache/hadoop/hbase/shaded/protobuf/generated/HBaseProtos$ServerName$Builder.buildPartial:()Lorg/apache/hadoop/hbase/shaded/protobuf/generated/HBaseProtos$ServerName;
      49: putfield      #13                 // Field worker_:Lorg/apache/hadoop/hbase/shaded/protobuf/generated/HBaseProtos$ServerName;
      52: goto          60
      55: aload_0
      56: aload_1
      57: putfield      #13                 // Field worker_:Lorg/apache/hadoop/hbase/shaded/protobuf/generated/HBaseProtos$ServerName;
      60: aload_0
      61: invokevirtual #45                 // Method onChanged:()V
      64: goto          76
      67: aload_0
      68: getfield      #20                 // Field workerBuilder_:Lorg/apache/hbase/thirdparty/com/google/protobuf/SingleFieldBuilderV3;
      71: aload_1
      72: invokevirtual #88                 // Method org/apache/hbase/thirdparty/com/google/protobuf/SingleFieldBuilderV3.mergeFrom:(Lorg/apache/hbase/thirdparty/com/google/protobuf/AbstractMessage;)Lorg/apache/hbase/thirdparty/com/google/protobuf/SingleFieldBuilderV3;
      75: pop
      76: aload_0
      77: dup
      78: getfield      #19                 // Field bitField0_:I
      81: iconst_4
      82: ior
      83: putfield      #19                 // Field bitField0_:I
      86: aload_0
      87: areturn

  public org.apache.hadoop.hbase.shaded.protobuf.generated.MasterProcedureProtos$SyncReplicationReplayWALStateData$Builder clearWorker();
    Code:
       0: aload_0
       1: getfield      #20                 // Field workerBuilder_:Lorg/apache/hbase/thirdparty/com/google/protobuf/SingleFieldBuilderV3;
       4: ifnonnull     19
       7: aload_0
       8: aconst_null
       9: putfield      #13                 // Field worker_:Lorg/apache/hadoop/hbase/shaded/protobuf/generated/HBaseProtos$ServerName;
      12: aload_0
      13: invokevirtual #45                 // Method onChanged:()V
      16: goto          27
      19: aload_0
      20: getfield      #20                 // Field workerBuilder_:Lorg/apache/hbase/thirdparty/com/google/protobuf/SingleFieldBuilderV3;
      23: invokevirtual #21                 // Method org/apache/hbase/thirdparty/com/google/protobuf/SingleFieldBuilderV3.clear:()Lorg/apache/hbase/thirdparty/com/google/protobuf/SingleFieldBuilderV3;
      26: pop
      27: aload_0
      28: aload_0
      29: getfield      #19                 // Field bitField0_:I
      32: bipush        -5
      34: iand
      35: putfield      #19                 // Field bitField0_:I
      38: aload_0
      39: areturn

  public org.apache.hadoop.hbase.shaded.protobuf.generated.HBaseProtos$ServerName$Builder getWorkerBuilder();
    Code:
       0: aload_0
       1: dup
       2: getfield      #19                 // Field bitField0_:I
       5: iconst_4
       6: ior
       7: putfield      #19                 // Field bitField0_:I
      10: aload_0
      11: invokevirtual #45                 // Method onChanged:()V
      14: aload_0
      15: invokespecial #17                 // Method getWorkerFieldBuilder:()Lorg/apache/hbase/thirdparty/com/google/protobuf/SingleFieldBuilderV3;
      18: invokevirtual #89                 // Method org/apache/hbase/thirdparty/com/google/protobuf/SingleFieldBuilderV3.getBuilder:()Lorg/apache/hbase/thirdparty/com/google/protobuf/AbstractMessage$Builder;
      21: checkcast     #90                 // class org/apache/hadoop/hbase/shaded/protobuf/generated/HBaseProtos$ServerName$Builder
      24: areturn

  public org.apache.hadoop.hbase.shaded.protobuf.generated.HBaseProtos$ServerNameOrBuilder getWorkerOrBuilder();
    Code:
       0: aload_0
       1: getfield      #20                 // Field workerBuilder_:Lorg/apache/hbase/thirdparty/com/google/protobuf/SingleFieldBuilderV3;
       4: ifnull        18
       7: aload_0
       8: getfield      #20                 // Field workerBuilder_:Lorg/apache/hbase/thirdparty/com/google/protobuf/SingleFieldBuilderV3;
      11: invokevirtual #91                 // Method org/apache/hbase/thirdparty/com/google/protobuf/SingleFieldBuilderV3.getMessageOrBuilder:()Lorg/apache/hbase/thirdparty/com/google/protobuf/MessageOrBuilder;
      14: checkcast     #92                 // class org/apache/hadoop/hbase/shaded/protobuf/generated/HBaseProtos$ServerNameOrBuilder
      17: areturn
      18: aload_0
      19: getfield      #13                 // Field worker_:Lorg/apache/hadoop/hbase/shaded/protobuf/generated/HBaseProtos$ServerName;
      22: ifnonnull     31
      25: invokestatic  #81                 // Method org/apache/hadoop/hbase/shaded/protobuf/generated/HBaseProtos$ServerName.getDefaultInstance:()Lorg/apache/hadoop/hbase/shaded/protobuf/generated/HBaseProtos$ServerName;
      28: goto          35
      31: aload_0
      32: getfield      #13                 // Field worker_:Lorg/apache/hadoop/hbase/shaded/protobuf/generated/HBaseProtos$ServerName;
      35: areturn

  public final org.apache.hadoop.hbase.shaded.protobuf.generated.MasterProcedureProtos$SyncReplicationReplayWALStateData$Builder setUnknownFields(org.apache.hbase.thirdparty.com.google.protobuf.UnknownFieldSet);
    Code:
       0: aload_0
       1: aload_1
       2: invokespecial #97                 // Method org/apache/hbase/thirdparty/com/google/protobuf/GeneratedMessageV3$Builder.setUnknownFields:(Lorg/apache/hbase/thirdparty/com/google/protobuf/UnknownFieldSet;)Lorg/apache/hbase/thirdparty/com/google/protobuf/GeneratedMessageV3$Builder;
       5: checkcast     #6                  // class org/apache/hadoop/hbase/shaded/protobuf/generated/MasterProcedureProtos$SyncReplicationReplayWALStateData$Builder
       8: areturn

  public final org.apache.hadoop.hbase.shaded.protobuf.generated.MasterProcedureProtos$SyncReplicationReplayWALStateData$Builder mergeUnknownFields(org.apache.hbase.thirdparty.com.google.protobuf.UnknownFieldSet);
    Code:
       0: aload_0
       1: aload_1
       2: invokespecial #98                 // Method org/apache/hbase/thirdparty/com/google/protobuf/GeneratedMessageV3$Builder.mergeUnknownFields:(Lorg/apache/hbase/thirdparty/com/google/protobuf/UnknownFieldSet;)Lorg/apache/hbase/thirdparty/com/google/protobuf/GeneratedMessageV3$Builder;
       5: checkcast     #6                  // class org/apache/hadoop/hbase/shaded/protobuf/generated/MasterProcedureProtos$SyncReplicationReplayWALStateData$Builder
       8: areturn

  public org.apache.hbase.thirdparty.com.google.protobuf.GeneratedMessageV3$Builder mergeUnknownFields(org.apache.hbase.thirdparty.com.google.protobuf.UnknownFieldSet);
    Code:
       0: aload_0
       1: aload_1
       2: invokevirtual #54                 // Method mergeUnknownFields:(Lorg/apache/hbase/thirdparty/com/google/protobuf/UnknownFieldSet;)Lorg/apache/hadoop/hbase/shaded/protobuf/generated/MasterProcedureProtos$SyncReplicationReplayWALStateData$Builder;
       5: areturn

  public org.apache.hbase.thirdparty.com.google.protobuf.GeneratedMessageV3$Builder setUnknownFields(org.apache.hbase.thirdparty.com.google.protobuf.UnknownFieldSet);
    Code:
       0: aload_0
       1: aload_1
       2: invokevirtual #99                 // Method setUnknownFields:(Lorg/apache/hbase/thirdparty/com/google/protobuf/UnknownFieldSet;)Lorg/apache/hadoop/hbase/shaded/protobuf/generated/MasterProcedureProtos$SyncReplicationReplayWALStateData$Builder;
       5: areturn

  public org.apache.hbase.thirdparty.com.google.protobuf.GeneratedMessageV3$Builder addRepeatedField(org.apache.hbase.thirdparty.com.google.protobuf.Descriptors$FieldDescriptor, java.lang.Object);
    Code:
       0: aload_0
       1: aload_1
       2: aload_2
       3: invokevirtual #100                // Method addRepeatedField:(Lorg/apache/hbase/thirdparty/com/google/protobuf/Descriptors$FieldDescriptor;Ljava/lang/Object;)Lorg/apache/hadoop/hbase/shaded/protobuf/generated/MasterProcedureProtos$SyncReplicationReplayWALStateData$Builder;
       6: areturn

  public org.apache.hbase.thirdparty.com.google.protobuf.GeneratedMessageV3$Builder setRepeatedField(org.apache.hbase.thirdparty.com.google.protobuf.Descriptors$FieldDescriptor, int, java.lang.Object);
    Code:
       0: aload_0
       1: aload_1
       2: iload_2
       3: aload_3
       4: invokevirtual #101                // Method setRepeatedField:(Lorg/apache/hbase/thirdparty/com/google/protobuf/Descriptors$FieldDescriptor;ILjava/lang/Object;)Lorg/apache/hadoop/hbase/shaded/protobuf/generated/MasterProcedureProtos$SyncReplicationReplayWALStateData$Builder;
       7: areturn

  public org.apache.hbase.thirdparty.com.google.protobuf.GeneratedMessageV3$Builder clearOneof(org.apache.hbase.thirdparty.com.google.protobuf.Descriptors$OneofDescriptor);
    Code:
       0: aload_0
       1: aload_1
       2: invokevirtual #102                // Method clearOneof:(Lorg/apache/hbase/thirdparty/com/google/protobuf/Descriptors$OneofDescriptor;)Lorg/apache/hadoop/hbase/shaded/protobuf/generated/MasterProcedureProtos$SyncReplicationReplayWALStateData$Builder;
       5: areturn

  public org.apache.hbase.thirdparty.com.google.protobuf.GeneratedMessageV3$Builder clearField(org.apache.hbase.thirdparty.com.google.protobuf.Descriptors$FieldDescriptor);
    Code:
       0: aload_0
       1: aload_1
       2: invokevirtual #103                // Method clearField:(Lorg/apache/hbase/thirdparty/com/google/protobuf/Descriptors$FieldDescriptor;)Lorg/apache/hadoop/hbase/shaded/protobuf/generated/MasterProcedureProtos$SyncReplicationReplayWALStateData$Builder;
       5: areturn

  public org.apache.hbase.thirdparty.com.google.protobuf.GeneratedMessageV3$Builder setField(org.apache.hbase.thirdparty.com.google.protobuf.Descriptors$FieldDescriptor, java.lang.Object);
    Code:
       0: aload_0
       1: aload_1
       2: aload_2
       3: invokevirtual #104                // Method setField:(Lorg/apache/hbase/thirdparty/com/google/protobuf/Descriptors$FieldDescriptor;Ljava/lang/Object;)Lorg/apache/hadoop/hbase/shaded/protobuf/generated/MasterProcedureProtos$SyncReplicationReplayWALStateData$Builder;
       6: areturn

  public org.apache.hbase.thirdparty.com.google.protobuf.GeneratedMessageV3$Builder clear();
    Code:
       0: aload_0
       1: invokevirtual #105                // Method clear:()Lorg/apache/hadoop/hbase/shaded/protobuf/generated/MasterProcedureProtos$SyncReplicationReplayWALStateData$Builder;
       4: areturn

  public org.apache.hbase.thirdparty.com.google.protobuf.GeneratedMessageV3$Builder clone();
    Code:
       0: aload_0
       1: invokevirtual #106                // Method clone:()Lorg/apache/hadoop/hbase/shaded/protobuf/generated/MasterProcedureProtos$SyncReplicationReplayWALStateData$Builder;
       4: areturn

  public org.apache.hbase.thirdparty.com.google.protobuf.AbstractMessage$Builder mergeUnknownFields(org.apache.hbase.thirdparty.com.google.protobuf.UnknownFieldSet);
    Code:
       0: aload_0
       1: aload_1
       2: invokevirtual #54                 // Method mergeUnknownFields:(Lorg/apache/hbase/thirdparty/com/google/protobuf/UnknownFieldSet;)Lorg/apache/hadoop/hbase/shaded/protobuf/generated/MasterProcedureProtos$SyncReplicationReplayWALStateData$Builder;
       5: areturn

  public org.apache.hbase.thirdparty.com.google.protobuf.AbstractMessage$Builder mergeFrom(org.apache.hbase.thirdparty.com.google.protobuf.CodedInputStream, org.apache.hbase.thirdparty.com.google.protobuf.ExtensionRegistryLite) throws java.io.IOException;
    Code:
       0: aload_0
       1: aload_1
       2: aload_2
       3: invokevirtual #107                // Method mergeFrom:(Lorg/apache/hbase/thirdparty/com/google/protobuf/CodedInputStream;Lorg/apache/hbase/thirdparty/com/google/protobuf/ExtensionRegistryLite;)Lorg/apache/hadoop/hbase/shaded/protobuf/generated/MasterProcedureProtos$SyncReplicationReplayWALStateData$Builder;
       6: areturn

  public org.apache.hbase.thirdparty.com.google.protobuf.AbstractMessage$Builder mergeFrom(org.apache.hbase.thirdparty.com.google.protobuf.Message);
    Code:
       0: aload_0
       1: aload_1
       2: invokevirtual #108                // Method mergeFrom:(Lorg/apache/hbase/thirdparty/com/google/protobuf/Message;)Lorg/apache/hadoop/hbase/shaded/protobuf/generated/MasterProcedureProtos$SyncReplicationReplayWALStateData$Builder;
       5: areturn

  public org.apache.hbase.thirdparty.com.google.protobuf.AbstractMessage$Builder clear();
    Code:
       0: aload_0
       1: invokevirtual #105                // Method clear:()Lorg/apache/hadoop/hbase/shaded/protobuf/generated/MasterProcedureProtos$SyncReplicationReplayWALStateData$Builder;
       4: areturn

  public org.apache.hbase.thirdparty.com.google.protobuf.AbstractMessage$Builder clearOneof(org.apache.hbase.thirdparty.com.google.protobuf.Descriptors$OneofDescriptor);
    Code:
       0: aload_0
       1: aload_1
       2: invokevirtual #102                // Method clearOneof:(Lorg/apache/hbase/thirdparty/com/google/protobuf/Descriptors$OneofDescriptor;)Lorg/apache/hadoop/hbase/shaded/protobuf/generated/MasterProcedureProtos$SyncReplicationReplayWALStateData$Builder;
       5: areturn

  public org.apache.hbase.thirdparty.com.google.protobuf.AbstractMessage$Builder clone();
    Code:
       0: aload_0
       1: invokevirtual #106                // Method clone:()Lorg/apache/hadoop/hbase/shaded/protobuf/generated/MasterProcedureProtos$SyncReplicationReplayWALStateData$Builder;
       4: areturn

  public org.apache.hbase.thirdparty.com.google.protobuf.Message$Builder mergeUnknownFields(org.apache.hbase.thirdparty.com.google.protobuf.UnknownFieldSet);
    Code:
       0: aload_0
       1: aload_1
       2: invokevirtual #54                 // Method mergeUnknownFields:(Lorg/apache/hbase/thirdparty/com/google/protobuf/UnknownFieldSet;)Lorg/apache/hadoop/hbase/shaded/protobuf/generated/MasterProcedureProtos$SyncReplicationReplayWALStateData$Builder;
       5: areturn

  public org.apache.hbase.thirdparty.com.google.protobuf.Message$Builder setUnknownFields(org.apache.hbase.thirdparty.com.google.protobuf.UnknownFieldSet);
    Code:
       0: aload_0
       1: aload_1
       2: invokevirtual #99                 // Method setUnknownFields:(Lorg/apache/hbase/thirdparty/com/google/protobuf/UnknownFieldSet;)Lorg/apache/hadoop/hbase/shaded/protobuf/generated/MasterProcedureProtos$SyncReplicationReplayWALStateData$Builder;
       5: areturn

  public org.apache.hbase.thirdparty.com.google.protobuf.Message$Builder addRepeatedField(org.apache.hbase.thirdparty.com.google.protobuf.Descriptors$FieldDescriptor, java.lang.Object);
    Code:
       0: aload_0
       1: aload_1
       2: aload_2
       3: invokevirtual #100                // Method addRepeatedField:(Lorg/apache/hbase/thirdparty/com/google/protobuf/Descriptors$FieldDescriptor;Ljava/lang/Object;)Lorg/apache/hadoop/hbase/shaded/protobuf/generated/MasterProcedureProtos$SyncReplicationReplayWALStateData$Builder;
       6: areturn

  public org.apache.hbase.thirdparty.com.google.protobuf.Message$Builder setRepeatedField(org.apache.hbase.thirdparty.com.google.protobuf.Descriptors$FieldDescriptor, int, java.lang.Object);
    Code:
       0: aload_0
       1: aload_1
       2: iload_2
       3: aload_3
       4: invokevirtual #101                // Method setRepeatedField:(Lorg/apache/hbase/thirdparty/com/google/protobuf/Descriptors$FieldDescriptor;ILjava/lang/Object;)Lorg/apache/hadoop/hbase/shaded/protobuf/generated/MasterProcedureProtos$SyncReplicationReplayWALStateData$Builder;
       7: areturn

  public org.apache.hbase.thirdparty.com.google.protobuf.Message$Builder clearOneof(org.apache.hbase.thirdparty.com.google.protobuf.Descriptors$OneofDescriptor);
    Code:
       0: aload_0
       1: aload_1
       2: invokevirtual #102                // Method clearOneof:(Lorg/apache/hbase/thirdparty/com/google/protobuf/Descriptors$OneofDescriptor;)Lorg/apache/hadoop/hbase/shaded/protobuf/generated/MasterProcedureProtos$SyncReplicationReplayWALStateData$Builder;
       5: areturn

  public org.apache.hbase.thirdparty.com.google.protobuf.Message$Builder clearField(org.apache.hbase.thirdparty.com.google.protobuf.Descriptors$FieldDescriptor);
    Code:
       0: aload_0
       1: aload_1
       2: invokevirtual #103                // Method clearField:(Lorg/apache/hbase/thirdparty/com/google/protobuf/Descriptors$FieldDescriptor;)Lorg/apache/hadoop/hbase/shaded/protobuf/generated/MasterProcedureProtos$SyncReplicationReplayWALStateData$Builder;
       5: areturn

  public org.apache.hbase.thirdparty.com.google.protobuf.Message$Builder setField(org.apache.hbase.thirdparty.com.google.protobuf.Descriptors$FieldDescriptor, java.lang.Object);
    Code:
       0: aload_0
       1: aload_1
       2: aload_2
       3: invokevirtual #104                // Method setField:(Lorg/apache/hbase/thirdparty/com/google/protobuf/Descriptors$FieldDescriptor;Ljava/lang/Object;)Lorg/apache/hadoop/hbase/shaded/protobuf/generated/MasterProcedureProtos$SyncReplicationReplayWALStateData$Builder;
       6: areturn

  public org.apache.hbase.thirdparty.com.google.protobuf.Message$Builder mergeFrom(org.apache.hbase.thirdparty.com.google.protobuf.CodedInputStream, org.apache.hbase.thirdparty.com.google.protobuf.ExtensionRegistryLite) throws java.io.IOException;
    Code:
       0: aload_0
       1: aload_1
       2: aload_2
       3: invokevirtual #107                // Method mergeFrom:(Lorg/apache/hbase/thirdparty/com/google/protobuf/CodedInputStream;Lorg/apache/hbase/thirdparty/com/google/protobuf/ExtensionRegistryLite;)Lorg/apache/hadoop/hbase/shaded/protobuf/generated/MasterProcedureProtos$SyncReplicationReplayWALStateData$Builder;
       6: areturn

  public org.apache.hbase.thirdparty.com.google.protobuf.Message$Builder clone();
    Code:
       0: aload_0
       1: invokevirtual #106                // Method clone:()Lorg/apache/hadoop/hbase/shaded/protobuf/generated/MasterProcedureProtos$SyncReplicationReplayWALStateData$Builder;
       4: areturn

  public org.apache.hbase.thirdparty.com.google.protobuf.Message buildPartial();
    Code:
       0: aload_0
       1: invokevirtual #23                 // Method buildPartial:()Lorg/apache/hadoop/hbase/shaded/protobuf/generated/MasterProcedureProtos$SyncReplicationReplayWALStateData;
       4: areturn

  public org.apache.hbase.thirdparty.com.google.protobuf.Message build();
    Code:
       0: aload_0
       1: invokevirtual #109                // Method build:()Lorg/apache/hadoop/hbase/shaded/protobuf/generated/MasterProcedureProtos$SyncReplicationReplayWALStateData;
       4: areturn

  public org.apache.hbase.thirdparty.com.google.protobuf.Message$Builder mergeFrom(org.apache.hbase.thirdparty.com.google.protobuf.Message);
    Code:
       0: aload_0
       1: aload_1
       2: invokevirtual #108                // Method mergeFrom:(Lorg/apache/hbase/thirdparty/com/google/protobuf/Message;)Lorg/apache/hadoop/hbase/shaded/protobuf/generated/MasterProcedureProtos$SyncReplicationReplayWALStateData$Builder;
       5: areturn

  public org.apache.hbase.thirdparty.com.google.protobuf.Message$Builder clear();
    Code:
       0: aload_0
       1: invokevirtual #105                // Method clear:()Lorg/apache/hadoop/hbase/shaded/protobuf/generated/MasterProcedureProtos$SyncReplicationReplayWALStateData$Builder;
       4: areturn

  public org.apache.hbase.thirdparty.com.google.protobuf.MessageLite$Builder mergeFrom(org.apache.hbase.thirdparty.com.google.protobuf.CodedInputStream, org.apache.hbase.thirdparty.com.google.protobuf.ExtensionRegistryLite) throws java.io.IOException;
    Code:
       0: aload_0
       1: aload_1
       2: aload_2
       3: invokevirtual #107                // Method mergeFrom:(Lorg/apache/hbase/thirdparty/com/google/protobuf/CodedInputStream;Lorg/apache/hbase/thirdparty/com/google/protobuf/ExtensionRegistryLite;)Lorg/apache/hadoop/hbase/shaded/protobuf/generated/MasterProcedureProtos$SyncReplicationReplayWALStateData$Builder;
       6: areturn

  public org.apache.hbase.thirdparty.com.google.protobuf.MessageLite$Builder clone();
    Code:
       0: aload_0
       1: invokevirtual #106                // Method clone:()Lorg/apache/hadoop/hbase/shaded/protobuf/generated/MasterProcedureProtos$SyncReplicationReplayWALStateData$Builder;
       4: areturn

  public org.apache.hbase.thirdparty.com.google.protobuf.MessageLite buildPartial();
    Code:
       0: aload_0
       1: invokevirtual #23                 // Method buildPartial:()Lorg/apache/hadoop/hbase/shaded/protobuf/generated/MasterProcedureProtos$SyncReplicationReplayWALStateData;
       4: areturn

  public org.apache.hbase.thirdparty.com.google.protobuf.MessageLite build();
    Code:
       0: aload_0
       1: invokevirtual #109                // Method build:()Lorg/apache/hadoop/hbase/shaded/protobuf/generated/MasterProcedureProtos$SyncReplicationReplayWALStateData;
       4: areturn

  public org.apache.hbase.thirdparty.com.google.protobuf.MessageLite$Builder clear();
    Code:
       0: aload_0
       1: invokevirtual #105                // Method clear:()Lorg/apache/hadoop/hbase/shaded/protobuf/generated/MasterProcedureProtos$SyncReplicationReplayWALStateData$Builder;
       4: areturn

  public org.apache.hbase.thirdparty.com.google.protobuf.MessageLite getDefaultInstanceForType();
    Code:
       0: aload_0
       1: invokevirtual #110                // Method getDefaultInstanceForType:()Lorg/apache/hadoop/hbase/shaded/protobuf/generated/MasterProcedureProtos$SyncReplicationReplayWALStateData;
       4: areturn

  public org.apache.hbase.thirdparty.com.google.protobuf.Message getDefaultInstanceForType();
    Code:
       0: aload_0
       1: invokevirtual #110                // Method getDefaultInstanceForType:()Lorg/apache/hadoop/hbase/shaded/protobuf/generated/MasterProcedureProtos$SyncReplicationReplayWALStateData;
       4: areturn

  public org.apache.hbase.thirdparty.com.google.protobuf.AbstractMessageLite$Builder mergeFrom(org.apache.hbase.thirdparty.com.google.protobuf.CodedInputStream, org.apache.hbase.thirdparty.com.google.protobuf.ExtensionRegistryLite) throws java.io.IOException;
    Code:
       0: aload_0
       1: aload_1
       2: aload_2
       3: invokevirtual #107                // Method mergeFrom:(Lorg/apache/hbase/thirdparty/com/google/protobuf/CodedInputStream;Lorg/apache/hbase/thirdparty/com/google/protobuf/ExtensionRegistryLite;)Lorg/apache/hadoop/hbase/shaded/protobuf/generated/MasterProcedureProtos$SyncReplicationReplayWALStateData$Builder;
       6: areturn

  public org.apache.hbase.thirdparty.com.google.protobuf.AbstractMessageLite$Builder clone();
    Code:
       0: aload_0
       1: invokevirtual #106                // Method clone:()Lorg/apache/hadoop/hbase/shaded/protobuf/generated/MasterProcedureProtos$SyncReplicationReplayWALStateData$Builder;
       4: areturn

  public java.lang.Object clone() throws java.lang.CloneNotSupportedException;
    Code:
       0: aload_0
       1: invokevirtual #106                // Method clone:()Lorg/apache/hadoop/hbase/shaded/protobuf/generated/MasterProcedureProtos$SyncReplicationReplayWALStateData$Builder;
       4: areturn

  public java.util.List getWalList();
    Code:
       0: aload_0
       1: invokevirtual #111                // Method getWalList:()Lorg/apache/hbase/thirdparty/com/google/protobuf/ProtocolStringList;
       4: areturn

  org.apache.hadoop.hbase.shaded.protobuf.generated.MasterProcedureProtos$SyncReplicationReplayWALStateData$Builder(org.apache.hadoop.hbase.shaded.protobuf.generated.MasterProcedureProtos$1);
    Code:
       0: aload_0
       1: invokespecial #2                  // Method "<init>":()V
       4: return

  org.apache.hadoop.hbase.shaded.protobuf.generated.MasterProcedureProtos$SyncReplicationReplayWALStateData$Builder(org.apache.hbase.thirdparty.com.google.protobuf.GeneratedMessageV3$BuilderParent, org.apache.hadoop.hbase.shaded.protobuf.generated.MasterProcedureProtos$1);
    Code:
       0: aload_0
       1: aload_1
       2: invokespecial #1                  // Method "<init>":(Lorg/apache/hbase/thirdparty/com/google/protobuf/GeneratedMessageV3$BuilderParent;)V
       5: return
}
