Compiled from "MasterProcedureTestingUtility.java"
public class org.apache.hadoop.hbase.master.procedure.MasterProcedureTestingUtility {
  public static void restartMasterProcedureExecutor(org.apache.hadoop.hbase.procedure2.ProcedureExecutor<org.apache.hadoop.hbase.master.procedure.MasterProcedureEnv>) throws java.lang.Exception;
    Code:
       0: aload_0
       1: invokevirtual #3                  // Method org/apache/hadoop/hbase/procedure2/ProcedureExecutor.getEnvironment:()Ljava/lang/Object;
       4: checkcast     #4                  // class org/apache/hadoop/hbase/master/procedure/MasterProcedureEnv
       7: astore_1
       8: aload_1
       9: invokevirtual #5                  // Method org/apache/hadoop/hbase/master/procedure/MasterProcedureEnv.getMasterServices:()Lorg/apache/hadoop/hbase/master/MasterServices;
      12: checkcast     #6                  // class org/apache/hadoop/hbase/master/HMaster
      15: astore_2
      16: aload_0
      17: iconst_1
      18: iconst_1
      19: new           #7                  // class org/apache/hadoop/hbase/master/procedure/MasterProcedureTestingUtility$1
      22: dup
      23: aload_1
      24: aload_2
      25: invokespecial #8                  // Method org/apache/hadoop/hbase/master/procedure/MasterProcedureTestingUtility$1."<init>":(Lorg/apache/hadoop/hbase/master/procedure/MasterProcedureEnv;Lorg/apache/hadoop/hbase/master/HMaster;)V
      28: new           #9                  // class org/apache/hadoop/hbase/master/procedure/MasterProcedureTestingUtility$2
      31: dup
      32: aload_1
      33: aload_0
      34: invokespecial #10                 // Method org/apache/hadoop/hbase/master/procedure/MasterProcedureTestingUtility$2."<init>":(Lorg/apache/hadoop/hbase/master/procedure/MasterProcedureEnv;Lorg/apache/hadoop/hbase/procedure2/ProcedureExecutor;)V
      37: new           #11                 // class org/apache/hadoop/hbase/master/procedure/MasterProcedureTestingUtility$3
      40: dup
      41: aload_1
      42: aload_2
      43: invokespecial #12                 // Method org/apache/hadoop/hbase/master/procedure/MasterProcedureTestingUtility$3."<init>":(Lorg/apache/hadoop/hbase/master/procedure/MasterProcedureEnv;Lorg/apache/hadoop/hbase/master/HMaster;)V
      46: invokestatic  #13                 // Method org/apache/hadoop/hbase/procedure2/ProcedureTestingUtility.restart:(Lorg/apache/hadoop/hbase/procedure2/ProcedureExecutor;ZZLjava/util/concurrent/Callable;Ljava/util/concurrent/Callable;Ljava/util/concurrent/Callable;)V
      49: return

  public static void masterFailover(org.apache.hadoop.hbase.HBaseTestingUtility) throws java.lang.Exception;
    Code:
       0: aload_0
       1: invokevirtual #14                 // Method org/apache/hadoop/hbase/HBaseTestingUtility.getMiniHBaseCluster:()Lorg/apache/hadoop/hbase/MiniHBaseCluster;
       4: astore_1
       5: aload_1
       6: invokevirtual #15                 // Method org/apache/hadoop/hbase/MiniHBaseCluster.getMaster:()Lorg/apache/hadoop/hbase/master/HMaster;
       9: astore_2
      10: aload_1
      11: aload_1
      12: invokevirtual #15                 // Method org/apache/hadoop/hbase/MiniHBaseCluster.getMaster:()Lorg/apache/hadoop/hbase/master/HMaster;
      15: invokevirtual #16                 // Method org/apache/hadoop/hbase/master/HMaster.getServerName:()Lorg/apache/hadoop/hbase/ServerName;
      18: invokevirtual #17                 // Method org/apache/hadoop/hbase/MiniHBaseCluster.killMaster:(Lorg/apache/hadoop/hbase/ServerName;)V
      21: aload_0
      22: aload_2
      23: invokestatic  #18                 // Method waitBackupMaster:(Lorg/apache/hadoop/hbase/HBaseTestingUtility;Lorg/apache/hadoop/hbase/master/HMaster;)V
      26: return

  public static void waitBackupMaster(org.apache.hadoop.hbase.HBaseTestingUtility, org.apache.hadoop.hbase.master.HMaster) throws java.lang.Exception;
    Code:
       0: aload_0
       1: invokevirtual #14                 // Method org/apache/hadoop/hbase/HBaseTestingUtility.getMiniHBaseCluster:()Lorg/apache/hadoop/hbase/MiniHBaseCluster;
       4: astore_2
       5: aload_2
       6: invokevirtual #15                 // Method org/apache/hadoop/hbase/MiniHBaseCluster.getMaster:()Lorg/apache/hadoop/hbase/master/HMaster;
       9: astore_3
      10: aload_3
      11: ifnull        19
      14: aload_3
      15: aload_1
      16: if_acmpne     33
      19: ldc2_w        #19                 // long 250l
      22: invokestatic  #21                 // Method java/lang/Thread.sleep:(J)V
      25: aload_2
      26: invokevirtual #15                 // Method org/apache/hadoop/hbase/MiniHBaseCluster.getMaster:()Lorg/apache/hadoop/hbase/master/HMaster;
      29: astore_3
      30: goto          10
      33: aload_3
      34: invokevirtual #22                 // Method org/apache/hadoop/hbase/master/HMaster.isActiveMaster:()Z
      37: ifeq          47
      40: aload_3
      41: invokevirtual #23                 // Method org/apache/hadoop/hbase/master/HMaster.isInitialized:()Z
      44: ifne          56
      47: ldc2_w        #19                 // long 250l
      50: invokestatic  #21                 // Method java/lang/Thread.sleep:(J)V
      53: goto          33
      56: return

  public static org.apache.hadoop.hbase.client.TableDescriptor createHTD(org.apache.hadoop.hbase.TableName, java.lang.String...);
    Code:
       0: aload_0
       1: invokestatic  #24                 // Method org/apache/hadoop/hbase/client/TableDescriptorBuilder.newBuilder:(Lorg/apache/hadoop/hbase/TableName;)Lorg/apache/hadoop/hbase/client/TableDescriptorBuilder;
       4: astore_2
       5: iconst_0
       6: istore_3
       7: iload_3
       8: aload_1
       9: arraylength
      10: if_icmpge     30
      13: aload_2
      14: aload_1
      15: iload_3
      16: aaload
      17: invokestatic  #25                 // Method org/apache/hadoop/hbase/client/ColumnFamilyDescriptorBuilder.of:(Ljava/lang/String;)Lorg/apache/hadoop/hbase/client/ColumnFamilyDescriptor;
      20: invokevirtual #26                 // Method org/apache/hadoop/hbase/client/TableDescriptorBuilder.setColumnFamily:(Lorg/apache/hadoop/hbase/client/ColumnFamilyDescriptor;)Lorg/apache/hadoop/hbase/client/TableDescriptorBuilder;
      23: pop
      24: iinc          3, 1
      27: goto          7
      30: aload_2
      31: invokevirtual #27                 // Method org/apache/hadoop/hbase/client/TableDescriptorBuilder.build:()Lorg/apache/hadoop/hbase/client/TableDescriptor;
      34: areturn

  public static org.apache.hadoop.hbase.client.RegionInfo[] createTable(org.apache.hadoop.hbase.procedure2.ProcedureExecutor<org.apache.hadoop.hbase.master.procedure.MasterProcedureEnv>, org.apache.hadoop.hbase.TableName, byte[][], java.lang.String...) throws java.io.IOException;
    Code:
       0: aload_1
       1: aload_3
       2: invokestatic  #28                 // Method createHTD:(Lorg/apache/hadoop/hbase/TableName;[Ljava/lang/String;)Lorg/apache/hadoop/hbase/client/TableDescriptor;
       5: astore        4
       7: aload         4
       9: aload_2
      10: invokestatic  #29                 // Method org/apache/hadoop/hbase/util/ModifyRegionUtils.createRegionInfos:(Lorg/apache/hadoop/hbase/client/TableDescriptor;[[B)[Lorg/apache/hadoop/hbase/client/RegionInfo;
      13: astore        5
      15: aload_0
      16: new           #30                 // class org/apache/hadoop/hbase/master/procedure/CreateTableProcedure
      19: dup
      20: aload_0
      21: invokevirtual #3                  // Method org/apache/hadoop/hbase/procedure2/ProcedureExecutor.getEnvironment:()Ljava/lang/Object;
      24: checkcast     #4                  // class org/apache/hadoop/hbase/master/procedure/MasterProcedureEnv
      27: aload         4
      29: aload         5
      31: invokespecial #31                 // Method org/apache/hadoop/hbase/master/procedure/CreateTableProcedure."<init>":(Lorg/apache/hadoop/hbase/master/procedure/MasterProcedureEnv;Lorg/apache/hadoop/hbase/client/TableDescriptor;[Lorg/apache/hadoop/hbase/client/RegionInfo;)V
      34: invokestatic  #32                 // Method org/apache/hadoop/hbase/procedure2/ProcedureTestingUtility.submitAndWait:(Lorg/apache/hadoop/hbase/procedure2/ProcedureExecutor;Lorg/apache/hadoop/hbase/procedure2/Procedure;)J
      37: lstore        6
      39: aload_0
      40: lload         6
      42: invokevirtual #33                 // Method org/apache/hadoop/hbase/procedure2/ProcedureExecutor.getResult:(J)Lorg/apache/hadoop/hbase/procedure2/Procedure;
      45: invokestatic  #34                 // Method org/apache/hadoop/hbase/procedure2/ProcedureTestingUtility.assertProcNotFailed:(Lorg/apache/hadoop/hbase/procedure2/Procedure;)V
      48: aload         5
      50: areturn

  public static void validateTableCreation(org.apache.hadoop.hbase.master.HMaster, org.apache.hadoop.hbase.TableName, org.apache.hadoop.hbase.client.RegionInfo[], java.lang.String...) throws java.io.IOException;
    Code:
       0: aload_0
       1: aload_1
       2: aload_2
       3: iconst_1
       4: aload_3
       5: invokestatic  #35                 // Method validateTableCreation:(Lorg/apache/hadoop/hbase/master/HMaster;Lorg/apache/hadoop/hbase/TableName;[Lorg/apache/hadoop/hbase/client/RegionInfo;Z[Ljava/lang/String;)V
       8: return

  public static void validateTableCreation(org.apache.hadoop.hbase.master.HMaster, org.apache.hadoop.hbase.TableName, org.apache.hadoop.hbase.client.RegionInfo[], boolean, java.lang.String...) throws java.io.IOException;
    Code:
       0: aload_0
       1: invokevirtual #36                 // Method org/apache/hadoop/hbase/master/HMaster.getMasterFileSystem:()Lorg/apache/hadoop/hbase/master/MasterFileSystem;
       4: invokevirtual #37                 // Method org/apache/hadoop/hbase/master/MasterFileSystem.getFileSystem:()Lorg/apache/hadoop/fs/FileSystem;
       7: astore        5
       9: aload_0
      10: invokevirtual #36                 // Method org/apache/hadoop/hbase/master/HMaster.getMasterFileSystem:()Lorg/apache/hadoop/hbase/master/MasterFileSystem;
      13: invokevirtual #38                 // Method org/apache/hadoop/hbase/master/MasterFileSystem.getRootDir:()Lorg/apache/hadoop/fs/Path;
      16: aload_1
      17: invokestatic  #39                 // Method org/apache/hadoop/hbase/util/FSUtils.getTableDir:(Lorg/apache/hadoop/fs/Path;Lorg/apache/hadoop/hbase/TableName;)Lorg/apache/hadoop/fs/Path;
      20: astore        6
      22: aload         5
      24: aload         6
      26: invokevirtual #40                 // Method org/apache/hadoop/fs/FileSystem.exists:(Lorg/apache/hadoop/fs/Path;)Z
      29: invokestatic  #41                 // Method org/junit/Assert.assertTrue:(Z)V
      32: aload         5
      34: aload         6
      36: getstatic     #1                  // Field LOG:Lorg/slf4j/Logger;
      39: invokestatic  #42                 // Method org/apache/hadoop/hbase/util/FSUtils.logFileSystemState:(Lorg/apache/hadoop/fs/FileSystem;Lorg/apache/hadoop/fs/Path;Lorg/slf4j/Logger;)V
      42: aload         5
      44: aload         6
      46: invokestatic  #43                 // Method org/apache/hadoop/hbase/util/FSUtils.getRegionDirs:(Lorg/apache/hadoop/fs/FileSystem;Lorg/apache/hadoop/fs/Path;)Ljava/util/List;
      49: astore        7
      51: iconst_0
      52: istore        8
      54: iload         8
      56: aload_2
      57: arraylength
      58: if_icmpge     306
      61: new           #44                 // class org/apache/hadoop/fs/Path
      64: dup
      65: aload         6
      67: aload_2
      68: iload         8
      70: aaload
      71: invokeinterface #45,  1           // InterfaceMethod org/apache/hadoop/hbase/client/RegionInfo.getEncodedName:()Ljava/lang/String;
      76: invokespecial #46                 // Method org/apache/hadoop/fs/Path."<init>":(Lorg/apache/hadoop/fs/Path;Ljava/lang/String;)V
      79: astore        9
      81: new           #47                 // class java/lang/StringBuilder
      84: dup
      85: invokespecial #48                 // Method java/lang/StringBuilder."<init>":()V
      88: aload_2
      89: iload         8
      91: aaload
      92: invokevirtual #49                 // Method java/lang/StringBuilder.append:(Ljava/lang/Object;)Ljava/lang/StringBuilder;
      95: ldc           #50                 // String  region dir does not exist
      97: invokevirtual #51                 // Method java/lang/StringBuilder.append:(Ljava/lang/String;)Ljava/lang/StringBuilder;
     100: invokevirtual #52                 // Method java/lang/StringBuilder.toString:()Ljava/lang/String;
     103: aload         5
     105: aload         9
     107: invokevirtual #40                 // Method org/apache/hadoop/fs/FileSystem.exists:(Lorg/apache/hadoop/fs/Path;)Z
     110: invokestatic  #53                 // Method org/junit/Assert.assertTrue:(Ljava/lang/String;Z)V
     113: aload         7
     115: aload         9
     117: invokeinterface #54,  2           // InterfaceMethod java/util/List.remove:(Ljava/lang/Object;)Z
     122: invokestatic  #41                 // Method org/junit/Assert.assertTrue:(Z)V
     125: aload         5
     127: aload         9
     129: invokestatic  #55                 // Method org/apache/hadoop/hbase/util/FSUtils.getFamilyDirs:(Lorg/apache/hadoop/fs/FileSystem;Lorg/apache/hadoop/fs/Path;)Ljava/util/List;
     132: astore        10
     134: iconst_0
     135: istore        11
     137: iload         11
     139: aload         4
     141: arraylength
     142: if_icmpge     270
     145: new           #44                 // class org/apache/hadoop/fs/Path
     148: dup
     149: aload         9
     151: aload         4
     153: iload         11
     155: aaload
     156: invokespecial #46                 // Method org/apache/hadoop/fs/Path."<init>":(Lorg/apache/hadoop/fs/Path;Ljava/lang/String;)V
     159: astore        12
     161: iload_3
     162: ifeq          213
     165: new           #47                 // class java/lang/StringBuilder
     168: dup
     169: invokespecial #48                 // Method java/lang/StringBuilder."<init>":()V
     172: aload         4
     174: iload         11
     176: aaload
     177: invokevirtual #51                 // Method java/lang/StringBuilder.append:(Ljava/lang/String;)Ljava/lang/StringBuilder;
     180: ldc           #56                 // String  family dir does not exist
     182: invokevirtual #51                 // Method java/lang/StringBuilder.append:(Ljava/lang/String;)Ljava/lang/StringBuilder;
     185: invokevirtual #52                 // Method java/lang/StringBuilder.toString:()Ljava/lang/String;
     188: aload         5
     190: aload         12
     192: invokevirtual #40                 // Method org/apache/hadoop/fs/FileSystem.exists:(Lorg/apache/hadoop/fs/Path;)Z
     195: invokestatic  #53                 // Method org/junit/Assert.assertTrue:(Ljava/lang/String;Z)V
     198: aload         10
     200: aload         12
     202: invokeinterface #54,  2           // InterfaceMethod java/util/List.remove:(Ljava/lang/Object;)Z
     207: invokestatic  #41                 // Method org/junit/Assert.assertTrue:(Z)V
     210: goto          264
     213: aload         5
     215: aload         12
     217: invokevirtual #40                 // Method org/apache/hadoop/fs/FileSystem.exists:(Lorg/apache/hadoop/fs/Path;)Z
     220: ifne          254
     223: getstatic     #1                  // Field LOG:Lorg/slf4j/Logger;
     226: new           #47                 // class java/lang/StringBuilder
     229: dup
     230: invokespecial #48                 // Method java/lang/StringBuilder."<init>":()V
     233: aload         4
     235: iload         11
     237: aaload
     238: invokevirtual #51                 // Method java/lang/StringBuilder.append:(Ljava/lang/String;)Ljava/lang/StringBuilder;
     241: ldc           #56                 // String  family dir does not exist
     243: invokevirtual #51                 // Method java/lang/StringBuilder.append:(Ljava/lang/String;)Ljava/lang/StringBuilder;
     246: invokevirtual #52                 // Method java/lang/StringBuilder.toString:()Ljava/lang/String;
     249: invokeinterface #57,  2           // InterfaceMethod org/slf4j/Logger.warn:(Ljava/lang/String;)V
     254: aload         10
     256: aload         12
     258: invokeinterface #54,  2           // InterfaceMethod java/util/List.remove:(Ljava/lang/Object;)Z
     263: pop
     264: iinc          11, 1
     267: goto          137
     270: new           #47                 // class java/lang/StringBuilder
     273: dup
     274: invokespecial #48                 // Method java/lang/StringBuilder."<init>":()V
     277: ldc           #58                 // String found extraneous families:
     279: invokevirtual #51                 // Method java/lang/StringBuilder.append:(Ljava/lang/String;)Ljava/lang/StringBuilder;
     282: aload         10
     284: invokevirtual #49                 // Method java/lang/StringBuilder.append:(Ljava/lang/Object;)Ljava/lang/StringBuilder;
     287: invokevirtual #52                 // Method java/lang/StringBuilder.toString:()Ljava/lang/String;
     290: aload         10
     292: invokeinterface #59,  1           // InterfaceMethod java/util/List.isEmpty:()Z
     297: invokestatic  #53                 // Method org/junit/Assert.assertTrue:(Ljava/lang/String;Z)V
     300: iinc          8, 1
     303: goto          54
     306: new           #47                 // class java/lang/StringBuilder
     309: dup
     310: invokespecial #48                 // Method java/lang/StringBuilder."<init>":()V
     313: ldc           #60                 // String found extraneous regions:
     315: invokevirtual #51                 // Method java/lang/StringBuilder.append:(Ljava/lang/String;)Ljava/lang/StringBuilder;
     318: aload         7
     320: invokevirtual #49                 // Method java/lang/StringBuilder.append:(Ljava/lang/Object;)Ljava/lang/StringBuilder;
     323: invokevirtual #52                 // Method java/lang/StringBuilder.toString:()Ljava/lang/String;
     326: aload         7
     328: invokeinterface #59,  1           // InterfaceMethod java/util/List.isEmpty:()Z
     333: invokestatic  #53                 // Method org/junit/Assert.assertTrue:(Ljava/lang/String;Z)V
     336: getstatic     #1                  // Field LOG:Lorg/slf4j/Logger;
     339: ldc           #61                 // String Table directory layout is as expected.
     341: invokeinterface #62,  2           // InterfaceMethod org/slf4j/Logger.debug:(Ljava/lang/String;)V
     346: aload_0
     347: invokevirtual #63                 // Method org/apache/hadoop/hbase/master/HMaster.getConnection:()Lorg/apache/hadoop/hbase/client/Connection;
     350: aload_1
     351: invokestatic  #64                 // Method org/apache/hadoop/hbase/MetaTableAccessor.tableExists:(Lorg/apache/hadoop/hbase/client/Connection;Lorg/apache/hadoop/hbase/TableName;)Z
     354: invokestatic  #41                 // Method org/junit/Assert.assertTrue:(Z)V
     357: aload_2
     358: arraylength
     359: i2l
     360: aload_0
     361: aload_1
     362: invokestatic  #65                 // Method countMetaRegions:(Lorg/apache/hadoop/hbase/master/HMaster;Lorg/apache/hadoop/hbase/TableName;)I
     365: i2l
     366: invokestatic  #66                 // Method org/junit/Assert.assertEquals:(JJ)V
     369: aload_0
     370: invokevirtual #67                 // Method org/apache/hadoop/hbase/master/HMaster.getTableDescriptors:()Lorg/apache/hadoop/hbase/TableDescriptors;
     373: aload_1
     374: invokeinterface #68,  2           // InterfaceMethod org/apache/hadoop/hbase/TableDescriptors.get:(Lorg/apache/hadoop/hbase/TableName;)Lorg/apache/hadoop/hbase/client/TableDescriptor;
     379: astore        8
     381: ldc           #69                 // String table descriptor not found
     383: aload         8
     385: ifnull        392
     388: iconst_1
     389: goto          393
     392: iconst_0
     393: invokestatic  #53                 // Method org/junit/Assert.assertTrue:(Ljava/lang/String;Z)V
     396: iconst_0
     397: istore        9
     399: iload         9
     401: aload         4
     403: arraylength
     404: if_icmpge     462
     407: new           #47                 // class java/lang/StringBuilder
     410: dup
     411: invokespecial #48                 // Method java/lang/StringBuilder."<init>":()V
     414: ldc           #70                 // String family not found
     416: invokevirtual #51                 // Method java/lang/StringBuilder.append:(Ljava/lang/String;)Ljava/lang/StringBuilder;
     419: aload         4
     421: iload         9
     423: aaload
     424: invokevirtual #51                 // Method java/lang/StringBuilder.append:(Ljava/lang/String;)Ljava/lang/StringBuilder;
     427: invokevirtual #52                 // Method java/lang/StringBuilder.toString:()Ljava/lang/String;
     430: aload         8
     432: aload         4
     434: iload         9
     436: aaload
     437: invokestatic  #71                 // Method org/apache/hadoop/hbase/util/Bytes.toBytes:(Ljava/lang/String;)[B
     440: invokeinterface #72,  2           // InterfaceMethod org/apache/hadoop/hbase/client/TableDescriptor.getColumnFamily:([B)Lorg/apache/hadoop/hbase/client/ColumnFamilyDescriptor;
     445: ifnull        452
     448: iconst_1
     449: goto          453
     452: iconst_0
     453: invokestatic  #53                 // Method org/junit/Assert.assertTrue:(Ljava/lang/String;Z)V
     456: iinc          9, 1
     459: goto          399
     462: aload         4
     464: arraylength
     465: i2l
     466: aload         8
     468: invokeinterface #73,  1           // InterfaceMethod org/apache/hadoop/hbase/client/TableDescriptor.getColumnFamilyCount:()I
     473: i2l
     474: invokestatic  #66                 // Method org/junit/Assert.assertEquals:(JJ)V
     477: return

  public static void validateTableDeletion(org.apache.hadoop.hbase.master.HMaster, org.apache.hadoop.hbase.TableName) throws java.io.IOException;
    Code:
       0: aload_0
       1: invokevirtual #36                 // Method org/apache/hadoop/hbase/master/HMaster.getMasterFileSystem:()Lorg/apache/hadoop/hbase/master/MasterFileSystem;
       4: invokevirtual #37                 // Method org/apache/hadoop/hbase/master/MasterFileSystem.getFileSystem:()Lorg/apache/hadoop/fs/FileSystem;
       7: astore_2
       8: aload_0
       9: invokevirtual #36                 // Method org/apache/hadoop/hbase/master/HMaster.getMasterFileSystem:()Lorg/apache/hadoop/hbase/master/MasterFileSystem;
      12: invokevirtual #38                 // Method org/apache/hadoop/hbase/master/MasterFileSystem.getRootDir:()Lorg/apache/hadoop/fs/Path;
      15: aload_1
      16: invokestatic  #39                 // Method org/apache/hadoop/hbase/util/FSUtils.getTableDir:(Lorg/apache/hadoop/fs/Path;Lorg/apache/hadoop/hbase/TableName;)Lorg/apache/hadoop/fs/Path;
      19: astore_3
      20: aload_2
      21: aload_3
      22: invokevirtual #40                 // Method org/apache/hadoop/fs/FileSystem.exists:(Lorg/apache/hadoop/fs/Path;)Z
      25: invokestatic  #74                 // Method org/junit/Assert.assertFalse:(Z)V
      28: aload_0
      29: invokevirtual #63                 // Method org/apache/hadoop/hbase/master/HMaster.getConnection:()Lorg/apache/hadoop/hbase/client/Connection;
      32: aload_1
      33: invokestatic  #64                 // Method org/apache/hadoop/hbase/MetaTableAccessor.tableExists:(Lorg/apache/hadoop/hbase/client/Connection;Lorg/apache/hadoop/hbase/TableName;)Z
      36: invokestatic  #74                 // Method org/junit/Assert.assertFalse:(Z)V
      39: lconst_0
      40: aload_0
      41: aload_1
      42: invokestatic  #65                 // Method countMetaRegions:(Lorg/apache/hadoop/hbase/master/HMaster;Lorg/apache/hadoop/hbase/TableName;)I
      45: i2l
      46: invokestatic  #66                 // Method org/junit/Assert.assertEquals:(JJ)V
      49: ldc           #75                 // String found htd of deleted table
      51: aload_0
      52: invokevirtual #67                 // Method org/apache/hadoop/hbase/master/HMaster.getTableDescriptors:()Lorg/apache/hadoop/hbase/TableDescriptors;
      55: aload_1
      56: invokeinterface #68,  2           // InterfaceMethod org/apache/hadoop/hbase/TableDescriptors.get:(Lorg/apache/hadoop/hbase/TableName;)Lorg/apache/hadoop/hbase/client/TableDescriptor;
      61: ifnonnull     68
      64: iconst_1
      65: goto          69
      68: iconst_0
      69: invokestatic  #53                 // Method org/junit/Assert.assertTrue:(Ljava/lang/String;Z)V
      72: return

  public static void validateTableIsEnabled(org.apache.hadoop.hbase.master.HMaster, org.apache.hadoop.hbase.TableName) throws java.io.IOException;
    Code:
       0: aload_0
       1: invokevirtual #82                 // Method org/apache/hadoop/hbase/master/HMaster.getTableStateManager:()Lorg/apache/hadoop/hbase/master/TableStateManager;
       4: astore_2
       5: aload_2
       6: aload_1
       7: invokevirtual #83                 // Method org/apache/hadoop/hbase/master/TableStateManager.getTableState:(Lorg/apache/hadoop/hbase/TableName;)Lorg/apache/hadoop/hbase/client/TableState;
      10: invokevirtual #84                 // Method org/apache/hadoop/hbase/client/TableState.getState:()Lorg/apache/hadoop/hbase/client/TableState$State;
      13: getstatic     #85                 // Field org/apache/hadoop/hbase/client/TableState$State.ENABLED:Lorg/apache/hadoop/hbase/client/TableState$State;
      16: invokevirtual #86                 // Method org/apache/hadoop/hbase/client/TableState$State.equals:(Ljava/lang/Object;)Z
      19: invokestatic  #41                 // Method org/junit/Assert.assertTrue:(Z)V
      22: return

  public static void validateTableIsDisabled(org.apache.hadoop.hbase.master.HMaster, org.apache.hadoop.hbase.TableName) throws java.io.IOException;
    Code:
       0: aload_0
       1: invokevirtual #82                 // Method org/apache/hadoop/hbase/master/HMaster.getTableStateManager:()Lorg/apache/hadoop/hbase/master/TableStateManager;
       4: astore_2
       5: aload_2
       6: aload_1
       7: invokevirtual #83                 // Method org/apache/hadoop/hbase/master/TableStateManager.getTableState:(Lorg/apache/hadoop/hbase/TableName;)Lorg/apache/hadoop/hbase/client/TableState;
      10: invokevirtual #84                 // Method org/apache/hadoop/hbase/client/TableState.getState:()Lorg/apache/hadoop/hbase/client/TableState$State;
      13: getstatic     #87                 // Field org/apache/hadoop/hbase/client/TableState$State.DISABLED:Lorg/apache/hadoop/hbase/client/TableState$State;
      16: invokevirtual #86                 // Method org/apache/hadoop/hbase/client/TableState$State.equals:(Ljava/lang/Object;)Z
      19: invokestatic  #41                 // Method org/junit/Assert.assertTrue:(Z)V
      22: return

  public static void validateColumnFamilyAddition(org.apache.hadoop.hbase.master.HMaster, org.apache.hadoop.hbase.TableName, java.lang.String) throws java.io.IOException;
    Code:
       0: aload_0
       1: invokevirtual #67                 // Method org/apache/hadoop/hbase/master/HMaster.getTableDescriptors:()Lorg/apache/hadoop/hbase/TableDescriptors;
       4: aload_1
       5: invokeinterface #68,  2           // InterfaceMethod org/apache/hadoop/hbase/TableDescriptors.get:(Lorg/apache/hadoop/hbase/TableName;)Lorg/apache/hadoop/hbase/client/TableDescriptor;
      10: astore_3
      11: aload_3
      12: ifnull        19
      15: iconst_1
      16: goto          20
      19: iconst_0
      20: invokestatic  #41                 // Method org/junit/Assert.assertTrue:(Z)V
      23: aload_3
      24: aload_2
      25: invokestatic  #71                 // Method org/apache/hadoop/hbase/util/Bytes.toBytes:(Ljava/lang/String;)[B
      28: invokeinterface #88,  2           // InterfaceMethod org/apache/hadoop/hbase/client/TableDescriptor.hasColumnFamily:([B)Z
      33: invokestatic  #41                 // Method org/junit/Assert.assertTrue:(Z)V
      36: return

  public static void validateColumnFamilyDeletion(org.apache.hadoop.hbase.master.HMaster, org.apache.hadoop.hbase.TableName, java.lang.String) throws java.io.IOException;
    Code:
       0: aload_0
       1: invokevirtual #67                 // Method org/apache/hadoop/hbase/master/HMaster.getTableDescriptors:()Lorg/apache/hadoop/hbase/TableDescriptors;
       4: aload_1
       5: invokeinterface #68,  2           // InterfaceMethod org/apache/hadoop/hbase/TableDescriptors.get:(Lorg/apache/hadoop/hbase/TableName;)Lorg/apache/hadoop/hbase/client/TableDescriptor;
      10: astore_3
      11: aload_3
      12: ifnull        19
      15: iconst_1
      16: goto          20
      19: iconst_0
      20: invokestatic  #41                 // Method org/junit/Assert.assertTrue:(Z)V
      23: aload_3
      24: aload_2
      25: invokestatic  #71                 // Method org/apache/hadoop/hbase/util/Bytes.toBytes:(Ljava/lang/String;)[B
      28: invokeinterface #88,  2           // InterfaceMethod org/apache/hadoop/hbase/client/TableDescriptor.hasColumnFamily:([B)Z
      33: invokestatic  #74                 // Method org/junit/Assert.assertFalse:(Z)V
      36: aload_0
      37: invokevirtual #36                 // Method org/apache/hadoop/hbase/master/HMaster.getMasterFileSystem:()Lorg/apache/hadoop/hbase/master/MasterFileSystem;
      40: invokevirtual #37                 // Method org/apache/hadoop/hbase/master/MasterFileSystem.getFileSystem:()Lorg/apache/hadoop/fs/FileSystem;
      43: astore        4
      45: aload_0
      46: invokevirtual #36                 // Method org/apache/hadoop/hbase/master/HMaster.getMasterFileSystem:()Lorg/apache/hadoop/hbase/master/MasterFileSystem;
      49: invokevirtual #38                 // Method org/apache/hadoop/hbase/master/MasterFileSystem.getRootDir:()Lorg/apache/hadoop/fs/Path;
      52: aload_1
      53: invokestatic  #39                 // Method org/apache/hadoop/hbase/util/FSUtils.getTableDir:(Lorg/apache/hadoop/fs/Path;Lorg/apache/hadoop/hbase/TableName;)Lorg/apache/hadoop/fs/Path;
      56: astore        5
      58: aload         4
      60: aload         5
      62: invokestatic  #43                 // Method org/apache/hadoop/hbase/util/FSUtils.getRegionDirs:(Lorg/apache/hadoop/fs/FileSystem;Lorg/apache/hadoop/fs/Path;)Ljava/util/List;
      65: invokeinterface #89,  1           // InterfaceMethod java/util/List.iterator:()Ljava/util/Iterator;
      70: astore        6
      72: aload         6
      74: invokeinterface #90,  1           // InterfaceMethod java/util/Iterator.hasNext:()Z
      79: ifeq          138
      82: aload         6
      84: invokeinterface #91,  1           // InterfaceMethod java/util/Iterator.next:()Ljava/lang/Object;
      89: checkcast     #44                 // class org/apache/hadoop/fs/Path
      92: astore        7
      94: new           #44                 // class org/apache/hadoop/fs/Path
      97: dup
      98: aload         7
     100: aload_2
     101: invokespecial #46                 // Method org/apache/hadoop/fs/Path."<init>":(Lorg/apache/hadoop/fs/Path;Ljava/lang/String;)V
     104: astore        8
     106: new           #47                 // class java/lang/StringBuilder
     109: dup
     110: invokespecial #48                 // Method java/lang/StringBuilder."<init>":()V
     113: aload_2
     114: invokevirtual #51                 // Method java/lang/StringBuilder.append:(Ljava/lang/String;)Ljava/lang/StringBuilder;
     117: ldc           #92                 // String  family dir should not exist
     119: invokevirtual #51                 // Method java/lang/StringBuilder.append:(Ljava/lang/String;)Ljava/lang/StringBuilder;
     122: invokevirtual #52                 // Method java/lang/StringBuilder.toString:()Ljava/lang/String;
     125: aload         4
     127: aload         8
     129: invokevirtual #40                 // Method org/apache/hadoop/fs/FileSystem.exists:(Lorg/apache/hadoop/fs/Path;)Z
     132: invokestatic  #93                 // Method org/junit/Assert.assertFalse:(Ljava/lang/String;Z)V
     135: goto          72
     138: return

  public static void validateColumnFamilyModification(org.apache.hadoop.hbase.master.HMaster, org.apache.hadoop.hbase.TableName, java.lang.String, org.apache.hadoop.hbase.client.ColumnFamilyDescriptor) throws java.io.IOException;
    Code:
       0: aload_0
       1: invokevirtual #67                 // Method org/apache/hadoop/hbase/master/HMaster.getTableDescriptors:()Lorg/apache/hadoop/hbase/TableDescriptors;
       4: aload_1
       5: invokeinterface #68,  2           // InterfaceMethod org/apache/hadoop/hbase/TableDescriptors.get:(Lorg/apache/hadoop/hbase/TableName;)Lorg/apache/hadoop/hbase/client/TableDescriptor;
      10: astore        4
      12: aload         4
      14: ifnull        21
      17: iconst_1
      18: goto          22
      21: iconst_0
      22: invokestatic  #41                 // Method org/junit/Assert.assertTrue:(Z)V
      25: aload         4
      27: aload_2
      28: invokestatic  #71                 // Method org/apache/hadoop/hbase/util/Bytes.toBytes:(Ljava/lang/String;)[B
      31: invokeinterface #72,  2           // InterfaceMethod org/apache/hadoop/hbase/client/TableDescriptor.getColumnFamily:([B)Lorg/apache/hadoop/hbase/client/ColumnFamilyDescriptor;
      36: astore        5
      38: lconst_0
      39: getstatic     #94                 // Field org/apache/hadoop/hbase/client/ColumnFamilyDescriptor.COMPARATOR:Ljava/util/Comparator;
      42: aload         5
      44: aload_3
      45: invokeinterface #95,  3           // InterfaceMethod java/util/Comparator.compare:(Ljava/lang/Object;Ljava/lang/Object;)I
      50: i2l
      51: invokestatic  #66                 // Method org/junit/Assert.assertEquals:(JJ)V
      54: return

  public static void loadData(org.apache.hadoop.hbase.client.Connection, org.apache.hadoop.hbase.TableName, int, byte[][], java.lang.String...) throws java.io.IOException;
    Code:
       0: aload         4
       2: arraylength
       3: anewarray     #96                 // class "[B"
       6: astore        5
       8: iconst_0
       9: istore        6
      11: iload         6
      13: aload         5
      15: arraylength
      16: if_icmpge     38
      19: aload         5
      21: iload         6
      23: aload         4
      25: iload         6
      27: aaload
      28: invokestatic  #71                 // Method org/apache/hadoop/hbase/util/Bytes.toBytes:(Ljava/lang/String;)[B
      31: aastore
      32: iinc          6, 1
      35: goto          11
      38: aload_0
      39: aload_1
      40: invokeinterface #97,  2           // InterfaceMethod org/apache/hadoop/hbase/client/Connection.getBufferedMutator:(Lorg/apache/hadoop/hbase/TableName;)Lorg/apache/hadoop/hbase/client/BufferedMutator;
      45: astore        6
      47: iload_2
      48: aload_3
      49: arraylength
      50: if_icmplt     57
      53: iconst_1
      54: goto          58
      57: iconst_0
      58: invokestatic  #41                 // Method org/junit/Assert.assertTrue:(Z)V
      61: aload_3
      62: astore        7
      64: aload         7
      66: arraylength
      67: istore        8
      69: iconst_0
      70: istore        9
      72: iload         9
      74: iload         8
      76: if_icmpge     139
      79: aload         7
      81: iload         9
      83: aaload
      84: astore        10
      86: invokestatic  #98                 // Method java/lang/System.currentTimeMillis:()J
      89: invokestatic  #99                 // Method org/apache/hadoop/hbase/util/Bytes.toBytes:(J)[B
      92: aload         10
      94: invokestatic  #100                // Method org/apache/hadoop/hbase/util/Bytes.add:([B[B)[B
      97: astore        11
      99: aload         10
     101: aload         11
     103: invokestatic  #101                // Method org/apache/hadoop/hbase/util/MD5Hash.getMD5AsHex:([B)Ljava/lang/String;
     106: invokestatic  #71                 // Method org/apache/hadoop/hbase/util/Bytes.toBytes:(Ljava/lang/String;)[B
     109: invokestatic  #100                // Method org/apache/hadoop/hbase/util/Bytes.add:([B[B)[B
     112: astore        12
     114: aload         6
     116: aload         5
     118: aload         12
     120: aload         11
     122: invokestatic  #102                // Method createPut:([[B[B[B)Lorg/apache/hadoop/hbase/client/Put;
     125: invokeinterface #103,  2          // InterfaceMethod org/apache/hadoop/hbase/client/BufferedMutator.mutate:(Lorg/apache/hadoop/hbase/client/Mutation;)V
     130: iinc          2, -1
     133: iinc          9, 1
     136: goto          72
     139: iload_2
     140: iinc          2, -1
     143: ifle          190
     146: invokestatic  #98                 // Method java/lang/System.currentTimeMillis:()J
     149: invokestatic  #99                 // Method org/apache/hadoop/hbase/util/Bytes.toBytes:(J)[B
     152: iload_2
     153: invokestatic  #104                // Method org/apache/hadoop/hbase/util/Bytes.toBytes:(I)[B
     156: invokestatic  #100                // Method org/apache/hadoop/hbase/util/Bytes.add:([B[B)[B
     159: astore        7
     161: aload         7
     163: invokestatic  #101                // Method org/apache/hadoop/hbase/util/MD5Hash.getMD5AsHex:([B)Ljava/lang/String;
     166: invokestatic  #71                 // Method org/apache/hadoop/hbase/util/Bytes.toBytes:(Ljava/lang/String;)[B
     169: astore        8
     171: aload         6
     173: aload         5
     175: aload         8
     177: aload         7
     179: invokestatic  #102                // Method createPut:([[B[B[B)Lorg/apache/hadoop/hbase/client/Put;
     182: invokeinterface #103,  2          // InterfaceMethod org/apache/hadoop/hbase/client/BufferedMutator.mutate:(Lorg/apache/hadoop/hbase/client/Mutation;)V
     187: goto          139
     190: aload         6
     192: invokeinterface #105,  1          // InterfaceMethod org/apache/hadoop/hbase/client/BufferedMutator.flush:()V
     197: return

  public static long generateNonceGroup(org.apache.hadoop.hbase.master.HMaster);
    Code:
       0: aload_0
       1: invokevirtual #112                // Method org/apache/hadoop/hbase/master/HMaster.getClusterConnection:()Lorg/apache/hadoop/hbase/client/ClusterConnection;
       4: invokeinterface #113,  1          // InterfaceMethod org/apache/hadoop/hbase/client/ClusterConnection.getNonceGenerator:()Lorg/apache/hadoop/hbase/client/NonceGenerator;
       9: invokeinterface #114,  1          // InterfaceMethod org/apache/hadoop/hbase/client/NonceGenerator.getNonceGroup:()J
      14: lreturn

  public static long generateNonce(org.apache.hadoop.hbase.master.HMaster);
    Code:
       0: aload_0
       1: invokevirtual #112                // Method org/apache/hadoop/hbase/master/HMaster.getClusterConnection:()Lorg/apache/hadoop/hbase/client/ClusterConnection;
       4: invokeinterface #113,  1          // InterfaceMethod org/apache/hadoop/hbase/client/ClusterConnection.getNonceGenerator:()Lorg/apache/hadoop/hbase/client/NonceGenerator;
       9: invokeinterface #115,  1          // InterfaceMethod org/apache/hadoop/hbase/client/NonceGenerator.newNonce:()J
      14: lreturn

  public static void testRecoveryAndDoubleExecution(org.apache.hadoop.hbase.procedure2.ProcedureExecutor<org.apache.hadoop.hbase.master.procedure.MasterProcedureEnv>, long, int, boolean) throws java.lang.Exception;
    Code:
       0: aload_0
       1: lload_1
       2: invokestatic  #116                // Method org/apache/hadoop/hbase/procedure2/ProcedureTestingUtility.waitProcedure:(Lorg/apache/hadoop/hbase/procedure2/ProcedureExecutor;J)V
       5: iconst_0
       6: invokestatic  #117                // Method java/lang/Boolean.valueOf:(Z)Ljava/lang/Boolean;
       9: aload_0
      10: invokevirtual #118                // Method org/apache/hadoop/hbase/procedure2/ProcedureExecutor.isRunning:()Z
      13: invokestatic  #117                // Method java/lang/Boolean.valueOf:(Z)Ljava/lang/Boolean;
      16: invokestatic  #119                // Method org/junit/Assert.assertEquals:(Ljava/lang/Object;Ljava/lang/Object;)V
      19: aload_0
      20: lload_1
      21: invokevirtual #120                // Method org/apache/hadoop/hbase/procedure2/ProcedureExecutor.getProcedure:(J)Lorg/apache/hadoop/hbase/procedure2/Procedure;
      24: astore        5
      26: aload         5
      28: instanceof    #121                // class org/apache/hadoop/hbase/procedure2/StateMachineProcedure
      31: ifeq          45
      34: aload         5
      36: checkcast     #121                // class org/apache/hadoop/hbase/procedure2/StateMachineProcedure
      39: invokevirtual #122                // Method org/apache/hadoop/hbase/procedure2/StateMachineProcedure.getCurrentStateId:()I
      42: goto          46
      45: iconst_0
      46: istore        6
      48: iload         6
      50: iload_3
      51: if_icmpne     57
      54: goto          144
      57: getstatic     #1                  // Field LOG:Lorg/slf4j/Logger;
      60: new           #47                 // class java/lang/StringBuilder
      63: dup
      64: invokespecial #48                 // Method java/lang/StringBuilder."<init>":()V
      67: ldc           #123                // String Restart
      69: invokevirtual #51                 // Method java/lang/StringBuilder.append:(Ljava/lang/String;)Ljava/lang/StringBuilder;
      72: iload         6
      74: invokevirtual #124                // Method java/lang/StringBuilder.append:(I)Ljava/lang/StringBuilder;
      77: ldc           #125                // String  exec state=
      79: invokevirtual #51                 // Method java/lang/StringBuilder.append:(Ljava/lang/String;)Ljava/lang/StringBuilder;
      82: aload         5
      84: invokevirtual #49                 // Method java/lang/StringBuilder.append:(Ljava/lang/Object;)Ljava/lang/StringBuilder;
      87: invokevirtual #52                 // Method java/lang/StringBuilder.toString:()Ljava/lang/String;
      90: invokeinterface #126,  2          // InterfaceMethod org/slf4j/Logger.info:(Ljava/lang/String;)V
      95: aload_0
      96: lload_1
      97: invokestatic  #127                // Method org/apache/hadoop/hbase/procedure2/ProcedureTestingUtility.assertProcNotYetCompleted:(Lorg/apache/hadoop/hbase/procedure2/ProcedureExecutor;J)V
     100: aload_0
     101: invokestatic  #128                // Method restartMasterProcedureExecutor:(Lorg/apache/hadoop/hbase/procedure2/ProcedureExecutor;)V
     104: aload_0
     105: lload_1
     106: invokestatic  #116                // Method org/apache/hadoop/hbase/procedure2/ProcedureTestingUtility.waitProcedure:(Lorg/apache/hadoop/hbase/procedure2/ProcedureExecutor;J)V
     109: aload_0
     110: lload_1
     111: invokevirtual #120                // Method org/apache/hadoop/hbase/procedure2/ProcedureExecutor.getProcedure:(J)Lorg/apache/hadoop/hbase/procedure2/Procedure;
     114: astore        5
     116: aload         5
     118: instanceof    #121                // class org/apache/hadoop/hbase/procedure2/StateMachineProcedure
     121: ifeq          135
     124: aload         5
     126: checkcast     #121                // class org/apache/hadoop/hbase/procedure2/StateMachineProcedure
     129: invokevirtual #122                // Method org/apache/hadoop/hbase/procedure2/StateMachineProcedure.getCurrentStateId:()I
     132: goto          139
     135: iload         6
     137: iconst_1
     138: iadd
     139: istore        6
     141: goto          48
     144: iload         4
     146: invokestatic  #117                // Method java/lang/Boolean.valueOf:(Z)Ljava/lang/Boolean;
     149: aload_0
     150: invokevirtual #118                // Method org/apache/hadoop/hbase/procedure2/ProcedureExecutor.isRunning:()Z
     153: invokestatic  #117                // Method java/lang/Boolean.valueOf:(Z)Ljava/lang/Boolean;
     156: invokestatic  #119                // Method org/junit/Assert.assertEquals:(Ljava/lang/Object;Ljava/lang/Object;)V
     159: return

  public static void testRecoveryAndDoubleExecution(org.apache.hadoop.hbase.procedure2.ProcedureExecutor<org.apache.hadoop.hbase.master.procedure.MasterProcedureEnv>, long, org.apache.hadoop.hbase.master.procedure.MasterProcedureTestingUtility$StepHook) throws java.lang.Exception;
    Code:
       0: aload_0
       1: lload_1
       2: invokestatic  #116                // Method org/apache/hadoop/hbase/procedure2/ProcedureTestingUtility.waitProcedure:(Lorg/apache/hadoop/hbase/procedure2/ProcedureExecutor;J)V
       5: iconst_0
       6: invokestatic  #117                // Method java/lang/Boolean.valueOf:(Z)Ljava/lang/Boolean;
       9: aload_0
      10: invokevirtual #118                // Method org/apache/hadoop/hbase/procedure2/ProcedureExecutor.isRunning:()Z
      13: invokestatic  #117                // Method java/lang/Boolean.valueOf:(Z)Ljava/lang/Boolean;
      16: invokestatic  #119                // Method org/junit/Assert.assertEquals:(Ljava/lang/Object;Ljava/lang/Object;)V
      19: iconst_0
      20: istore        4
      22: aload_0
      23: lload_1
      24: invokevirtual #129                // Method org/apache/hadoop/hbase/procedure2/ProcedureExecutor.isFinished:(J)Z
      27: ifne          101
      30: getstatic     #1                  // Field LOG:Lorg/slf4j/Logger;
      33: new           #47                 // class java/lang/StringBuilder
      36: dup
      37: invokespecial #48                 // Method java/lang/StringBuilder."<init>":()V
      40: ldc           #123                // String Restart
      42: invokevirtual #51                 // Method java/lang/StringBuilder.append:(Ljava/lang/String;)Ljava/lang/StringBuilder;
      45: iload         4
      47: invokevirtual #124                // Method java/lang/StringBuilder.append:(I)Ljava/lang/StringBuilder;
      50: ldc           #125                // String  exec state=
      52: invokevirtual #51                 // Method java/lang/StringBuilder.append:(Ljava/lang/String;)Ljava/lang/StringBuilder;
      55: aload_0
      56: lload_1
      57: invokevirtual #120                // Method org/apache/hadoop/hbase/procedure2/ProcedureExecutor.getProcedure:(J)Lorg/apache/hadoop/hbase/procedure2/Procedure;
      60: invokevirtual #49                 // Method java/lang/StringBuilder.append:(Ljava/lang/Object;)Ljava/lang/StringBuilder;
      63: invokevirtual #52                 // Method java/lang/StringBuilder.toString:()Ljava/lang/String;
      66: invokeinterface #126,  2          // InterfaceMethod org/slf4j/Logger.info:(Ljava/lang/String;)V
      71: aload_3
      72: ifnull        86
      75: aload_3
      76: iload         4
      78: invokeinterface #130,  2          // InterfaceMethod org/apache/hadoop/hbase/master/procedure/MasterProcedureTestingUtility$StepHook.execute:(I)Z
      83: invokestatic  #41                 // Method org/junit/Assert.assertTrue:(Z)V
      86: aload_0
      87: invokestatic  #128                // Method restartMasterProcedureExecutor:(Lorg/apache/hadoop/hbase/procedure2/ProcedureExecutor;)V
      90: aload_0
      91: lload_1
      92: invokestatic  #116                // Method org/apache/hadoop/hbase/procedure2/ProcedureTestingUtility.waitProcedure:(Lorg/apache/hadoop/hbase/procedure2/ProcedureExecutor;J)V
      95: iinc          4, 1
      98: goto          22
     101: iconst_1
     102: invokestatic  #117                // Method java/lang/Boolean.valueOf:(Z)Ljava/lang/Boolean;
     105: aload_0
     106: invokevirtual #118                // Method org/apache/hadoop/hbase/procedure2/ProcedureExecutor.isRunning:()Z
     109: invokestatic  #117                // Method java/lang/Boolean.valueOf:(Z)Ljava/lang/Boolean;
     112: invokestatic  #119                // Method org/junit/Assert.assertEquals:(Ljava/lang/Object;Ljava/lang/Object;)V
     115: aload_0
     116: lload_1
     117: invokestatic  #131                // Method org/apache/hadoop/hbase/procedure2/ProcedureTestingUtility.assertProcNotFailed:(Lorg/apache/hadoop/hbase/procedure2/ProcedureExecutor;J)V
     120: return

  public static void testRecoveryAndDoubleExecution(org.apache.hadoop.hbase.procedure2.ProcedureExecutor<org.apache.hadoop.hbase.master.procedure.MasterProcedureEnv>, long) throws java.lang.Exception;
    Code:
       0: aload_0
       1: lload_1
       2: aconst_null
       3: invokestatic  #132                // Method testRecoveryAndDoubleExecution:(Lorg/apache/hadoop/hbase/procedure2/ProcedureExecutor;JLorg/apache/hadoop/hbase/master/procedure/MasterProcedureTestingUtility$StepHook;)V
       6: return

  public static void testRollbackAndDoubleExecution(org.apache.hadoop.hbase.procedure2.ProcedureExecutor<org.apache.hadoop.hbase.master.procedure.MasterProcedureEnv>, long, int) throws java.lang.Exception;
    Code:
       0: aload_0
       1: lload_1
       2: iload_3
       3: iconst_0
       4: invokestatic  #133                // Method testRollbackAndDoubleExecution:(Lorg/apache/hadoop/hbase/procedure2/ProcedureExecutor;JIZ)V
       7: return

  public static void testRollbackAndDoubleExecution(org.apache.hadoop.hbase.procedure2.ProcedureExecutor<org.apache.hadoop.hbase.master.procedure.MasterProcedureEnv>, long, int, boolean) throws java.lang.Exception;
    Code:
       0: aload_0
       1: lload_1
       2: iload_3
       3: iconst_0
       4: invokestatic  #134                // Method testRecoveryAndDoubleExecution:(Lorg/apache/hadoop/hbase/procedure2/ProcedureExecutor;JIZ)V
       7: new           #135                // class org/apache/hadoop/hbase/master/procedure/MasterProcedureTestingUtility$InjectAbortOnLoadListener
      10: dup
      11: aload_0
      12: invokespecial #136                // Method org/apache/hadoop/hbase/master/procedure/MasterProcedureTestingUtility$InjectAbortOnLoadListener."<init>":(Lorg/apache/hadoop/hbase/procedure2/ProcedureExecutor;)V
      15: astore        5
      17: aload         5
      19: lload_1
      20: invokevirtual #137                // Method org/apache/hadoop/hbase/master/procedure/MasterProcedureTestingUtility$InjectAbortOnLoadListener.addProcId:(J)V
      23: aload_0
      24: aload         5
      26: invokevirtual #138                // Method org/apache/hadoop/hbase/procedure2/ProcedureExecutor.registerListener:(Lorg/apache/hadoop/hbase/procedure2/ProcedureExecutor$ProcedureExecutorListener;)V
      29: iconst_0
      30: istore        6
      32: aload_0
      33: lload_1
      34: invokevirtual #129                // Method org/apache/hadoop/hbase/procedure2/ProcedureExecutor.isFinished:(J)Z
      37: ifne          101
      40: getstatic     #1                  // Field LOG:Lorg/slf4j/Logger;
      43: new           #47                 // class java/lang/StringBuilder
      46: dup
      47: invokespecial #48                 // Method java/lang/StringBuilder."<init>":()V
      50: ldc           #123                // String Restart
      52: invokevirtual #51                 // Method java/lang/StringBuilder.append:(Ljava/lang/String;)Ljava/lang/StringBuilder;
      55: iload         6
      57: invokevirtual #124                // Method java/lang/StringBuilder.append:(I)Ljava/lang/StringBuilder;
      60: ldc           #139                // String  rollback state:
      62: invokevirtual #51                 // Method java/lang/StringBuilder.append:(Ljava/lang/String;)Ljava/lang/StringBuilder;
      65: aload_0
      66: lload_1
      67: invokevirtual #120                // Method org/apache/hadoop/hbase/procedure2/ProcedureExecutor.getProcedure:(J)Lorg/apache/hadoop/hbase/procedure2/Procedure;
      70: invokevirtual #49                 // Method java/lang/StringBuilder.append:(Ljava/lang/Object;)Ljava/lang/StringBuilder;
      73: invokevirtual #52                 // Method java/lang/StringBuilder.toString:()Ljava/lang/String;
      76: invokeinterface #126,  2          // InterfaceMethod org/slf4j/Logger.info:(Ljava/lang/String;)V
      81: aload_0
      82: lload_1
      83: invokestatic  #127                // Method org/apache/hadoop/hbase/procedure2/ProcedureTestingUtility.assertProcNotYetCompleted:(Lorg/apache/hadoop/hbase/procedure2/ProcedureExecutor;J)V
      86: aload_0
      87: invokestatic  #128                // Method restartMasterProcedureExecutor:(Lorg/apache/hadoop/hbase/procedure2/ProcedureExecutor;)V
      90: aload_0
      91: lload_1
      92: invokestatic  #116                // Method org/apache/hadoop/hbase/procedure2/ProcedureTestingUtility.waitProcedure:(Lorg/apache/hadoop/hbase/procedure2/ProcedureExecutor;J)V
      95: iinc          6, 1
      98: goto          32
     101: aload_0
     102: aload         5
     104: invokevirtual #140                // Method org/apache/hadoop/hbase/procedure2/ProcedureExecutor.unregisterListener:(Lorg/apache/hadoop/hbase/procedure2/ProcedureExecutor$ProcedureExecutorListener;)Z
     107: invokestatic  #41                 // Method org/junit/Assert.assertTrue:(Z)V
     110: goto          127
     113: astore        7
     115: aload_0
     116: aload         5
     118: invokevirtual #140                // Method org/apache/hadoop/hbase/procedure2/ProcedureExecutor.unregisterListener:(Lorg/apache/hadoop/hbase/procedure2/ProcedureExecutor$ProcedureExecutorListener;)Z
     121: invokestatic  #41                 // Method org/junit/Assert.assertTrue:(Z)V
     124: aload         7
     126: athrow
     127: iload         4
     129: ifeq          186
     132: aload_0
     133: iconst_0
     134: invokestatic  #141                // Method org/apache/hadoop/hbase/procedure2/ProcedureTestingUtility.setKillAndToggleBeforeStoreUpdate:(Lorg/apache/hadoop/hbase/procedure2/ProcedureExecutor;Z)V
     137: iconst_0
     138: istore        6
     140: iload         6
     142: iconst_3
     143: if_icmpge     182
     146: aload_0
     147: invokevirtual #118                // Method org/apache/hadoop/hbase/procedure2/ProcedureExecutor.isRunning:()Z
     150: ifne          170
     153: getstatic     #1                  // Field LOG:Lorg/slf4j/Logger;
     156: ldc           #142                // String ProcedureExecutor not running, may have been stopped by pending procedure due to KillAndToggleBeforeStoreUpdate flag.
     158: invokeinterface #57,  2           // InterfaceMethod org/slf4j/Logger.warn:(Ljava/lang/String;)V
     163: aload_0
     164: invokestatic  #128                // Method restartMasterProcedureExecutor:(Lorg/apache/hadoop/hbase/procedure2/ProcedureExecutor;)V
     167: goto          182
     170: ldc2_w        #143                // long 1000l
     173: invokestatic  #21                 // Method java/lang/Thread.sleep:(J)V
     176: iinc          6, 1
     179: goto          140
     182: aload_0
     183: invokestatic  #145                // Method org/apache/hadoop/hbase/procedure2/ProcedureTestingUtility.waitNoProcedureRunning:(Lorg/apache/hadoop/hbase/procedure2/ProcedureExecutor;)V
     186: iconst_1
     187: invokestatic  #117                // Method java/lang/Boolean.valueOf:(Z)Ljava/lang/Boolean;
     190: aload_0
     191: invokevirtual #118                // Method org/apache/hadoop/hbase/procedure2/ProcedureExecutor.isRunning:()Z
     194: invokestatic  #117                // Method java/lang/Boolean.valueOf:(Z)Ljava/lang/Boolean;
     197: invokestatic  #119                // Method org/junit/Assert.assertEquals:(Ljava/lang/Object;Ljava/lang/Object;)V
     200: aload_0
     201: lload_1
     202: invokevirtual #33                 // Method org/apache/hadoop/hbase/procedure2/ProcedureExecutor.getResult:(J)Lorg/apache/hadoop/hbase/procedure2/Procedure;
     205: invokestatic  #146                // Method org/apache/hadoop/hbase/procedure2/ProcedureTestingUtility.assertIsAbortException:(Lorg/apache/hadoop/hbase/procedure2/Procedure;)V
     208: return
    Exception table:
       from    to  target type
          29   101   113   any
         113   115   113   any

  public static void testRollbackRetriableFailure(org.apache.hadoop.hbase.procedure2.ProcedureExecutor<org.apache.hadoop.hbase.master.procedure.MasterProcedureEnv>, long, int) throws java.lang.Exception;
    Code:
       0: aload_0
       1: lload_1
       2: iload_3
       3: iconst_0
       4: invokestatic  #134                // Method testRecoveryAndDoubleExecution:(Lorg/apache/hadoop/hbase/procedure2/ProcedureExecutor;JIZ)V
       7: aload_0
       8: lload_1
       9: invokestatic  #147                // Method testRestartWithAbort:(Lorg/apache/hadoop/hbase/procedure2/ProcedureExecutor;J)V
      12: iconst_1
      13: invokestatic  #117                // Method java/lang/Boolean.valueOf:(Z)Ljava/lang/Boolean;
      16: aload_0
      17: invokevirtual #118                // Method org/apache/hadoop/hbase/procedure2/ProcedureExecutor.isRunning:()Z
      20: invokestatic  #117                // Method java/lang/Boolean.valueOf:(Z)Ljava/lang/Boolean;
      23: invokestatic  #119                // Method org/junit/Assert.assertEquals:(Ljava/lang/Object;Ljava/lang/Object;)V
      26: aload_0
      27: lload_1
      28: invokevirtual #33                 // Method org/apache/hadoop/hbase/procedure2/ProcedureExecutor.getResult:(J)Lorg/apache/hadoop/hbase/procedure2/Procedure;
      31: invokestatic  #146                // Method org/apache/hadoop/hbase/procedure2/ProcedureTestingUtility.assertIsAbortException:(Lorg/apache/hadoop/hbase/procedure2/Procedure;)V
      34: return

  public static void testRestartWithAbort(org.apache.hadoop.hbase.procedure2.ProcedureExecutor<org.apache.hadoop.hbase.master.procedure.MasterProcedureEnv>, long) throws java.lang.Exception;
    Code:
       0: aload_0
       1: iconst_0
       2: invokestatic  #141                // Method org/apache/hadoop/hbase/procedure2/ProcedureTestingUtility.setKillAndToggleBeforeStoreUpdate:(Lorg/apache/hadoop/hbase/procedure2/ProcedureExecutor;Z)V
       5: new           #135                // class org/apache/hadoop/hbase/master/procedure/MasterProcedureTestingUtility$InjectAbortOnLoadListener
       8: dup
       9: aload_0
      10: invokespecial #136                // Method org/apache/hadoop/hbase/master/procedure/MasterProcedureTestingUtility$InjectAbortOnLoadListener."<init>":(Lorg/apache/hadoop/hbase/procedure2/ProcedureExecutor;)V
      13: astore_3
      14: aload_3
      15: lload_1
      16: invokevirtual #137                // Method org/apache/hadoop/hbase/master/procedure/MasterProcedureTestingUtility$InjectAbortOnLoadListener.addProcId:(J)V
      19: aload_0
      20: aload_3
      21: invokevirtual #138                // Method org/apache/hadoop/hbase/procedure2/ProcedureExecutor.registerListener:(Lorg/apache/hadoop/hbase/procedure2/ProcedureExecutor$ProcedureExecutorListener;)V
      24: aload_0
      25: lload_1
      26: invokestatic  #127                // Method org/apache/hadoop/hbase/procedure2/ProcedureTestingUtility.assertProcNotYetCompleted:(Lorg/apache/hadoop/hbase/procedure2/ProcedureExecutor;J)V
      29: getstatic     #1                  // Field LOG:Lorg/slf4j/Logger;
      32: new           #47                 // class java/lang/StringBuilder
      35: dup
      36: invokespecial #48                 // Method java/lang/StringBuilder."<init>":()V
      39: ldc           #148                // String Restart and rollback procId=
      41: invokevirtual #51                 // Method java/lang/StringBuilder.append:(Ljava/lang/String;)Ljava/lang/StringBuilder;
      44: lload_1
      45: invokevirtual #149                // Method java/lang/StringBuilder.append:(J)Ljava/lang/StringBuilder;
      48: invokevirtual #52                 // Method java/lang/StringBuilder.toString:()Ljava/lang/String;
      51: invokeinterface #126,  2          // InterfaceMethod org/slf4j/Logger.info:(Ljava/lang/String;)V
      56: aload_0
      57: invokestatic  #128                // Method restartMasterProcedureExecutor:(Lorg/apache/hadoop/hbase/procedure2/ProcedureExecutor;)V
      60: aload_0
      61: lload_1
      62: invokestatic  #116                // Method org/apache/hadoop/hbase/procedure2/ProcedureTestingUtility.waitProcedure:(Lorg/apache/hadoop/hbase/procedure2/ProcedureExecutor;J)V
      65: aload_0
      66: aload_3
      67: invokevirtual #140                // Method org/apache/hadoop/hbase/procedure2/ProcedureExecutor.unregisterListener:(Lorg/apache/hadoop/hbase/procedure2/ProcedureExecutor$ProcedureExecutorListener;)Z
      70: invokestatic  #41                 // Method org/junit/Assert.assertTrue:(Z)V
      73: goto          89
      76: astore        4
      78: aload_0
      79: aload_3
      80: invokevirtual #140                // Method org/apache/hadoop/hbase/procedure2/ProcedureExecutor.unregisterListener:(Lorg/apache/hadoop/hbase/procedure2/ProcedureExecutor$ProcedureExecutorListener;)Z
      83: invokestatic  #41                 // Method org/junit/Assert.assertTrue:(Z)V
      86: aload         4
      88: athrow
      89: return
    Exception table:
       from    to  target type
          24    65    76   any
          76    78    76   any

  static org.slf4j.Logger access$000();
    Code:
       0: getstatic     #1                  // Field LOG:Lorg/slf4j/Logger;
       3: areturn

  static {};
    Code:
       0: ldc           #150                // class org/apache/hadoop/hbase/master/procedure/MasterProcedureTestingUtility
       2: invokestatic  #151                // Method org/slf4j/LoggerFactory.getLogger:(Ljava/lang/Class;)Lorg/slf4j/Logger;
       5: putstatic     #1                  // Field LOG:Lorg/slf4j/Logger;
       8: return
}
