Compiled from "MasterProtos.java"
public final class org.apache.hadoop.hbase.shaded.protobuf.generated.MasterProtos$SetSplitOrMergeEnabledRequest extends org.apache.hbase.thirdparty.com.google.protobuf.GeneratedMessageV3 implements org.apache.hadoop.hbase.shaded.protobuf.generated.MasterProtos$SetSplitOrMergeEnabledRequestOrBuilder {
  public static final int ENABLED_FIELD_NUMBER;

  public static final int SYNCHRONOUS_FIELD_NUMBER;

  public static final int SWITCH_TYPES_FIELD_NUMBER;

  public static final org.apache.hbase.thirdparty.com.google.protobuf.Parser<org.apache.hadoop.hbase.shaded.protobuf.generated.MasterProtos$SetSplitOrMergeEnabledRequest> PARSER;

  public final org.apache.hbase.thirdparty.com.google.protobuf.UnknownFieldSet getUnknownFields();
    Code:
       0: aload_0
       1: getfield      #3                  // Field unknownFields:Lorg/apache/hbase/thirdparty/com/google/protobuf/UnknownFieldSet;
       4: areturn

  public static final org.apache.hbase.thirdparty.com.google.protobuf.Descriptors$Descriptor getDescriptor();
    Code:
       0: invokestatic  #39                 // Method org/apache/hadoop/hbase/shaded/protobuf/generated/MasterProtos.access$59600:()Lorg/apache/hbase/thirdparty/com/google/protobuf/Descriptors$Descriptor;
       3: areturn

  protected org.apache.hbase.thirdparty.com.google.protobuf.GeneratedMessageV3$FieldAccessorTable internalGetFieldAccessorTable();
    Code:
       0: invokestatic  #40                 // Method org/apache/hadoop/hbase/shaded/protobuf/generated/MasterProtos.access$59700:()Lorg/apache/hbase/thirdparty/com/google/protobuf/GeneratedMessageV3$FieldAccessorTable;
       3: ldc           #41                 // class org/apache/hadoop/hbase/shaded/protobuf/generated/MasterProtos$SetSplitOrMergeEnabledRequest
       5: ldc           #42                 // class org/apache/hadoop/hbase/shaded/protobuf/generated/MasterProtos$SetSplitOrMergeEnabledRequest$Builder
       7: invokevirtual #43                 // Method org/apache/hbase/thirdparty/com/google/protobuf/GeneratedMessageV3$FieldAccessorTable.ensureFieldAccessorsInitialized:(Ljava/lang/Class;Ljava/lang/Class;)Lorg/apache/hbase/thirdparty/com/google/protobuf/GeneratedMessageV3$FieldAccessorTable;
      10: areturn

  public boolean hasEnabled();
    Code:
       0: aload_0
       1: getfield      #4                  // Field bitField0_:I
       4: iconst_1
       5: iand
       6: iconst_1
       7: if_icmpne     14
      10: iconst_1
      11: goto          15
      14: iconst_0
      15: ireturn

  public boolean getEnabled();
    Code:
       0: aload_0
       1: getfield      #7                  // Field enabled_:Z
       4: ireturn

  public boolean hasSynchronous();
    Code:
       0: aload_0
       1: getfield      #4                  // Field bitField0_:I
       4: iconst_2
       5: iand
       6: iconst_2
       7: if_icmpne     14
      10: iconst_1
      11: goto          15
      14: iconst_0
      15: ireturn

  public boolean getSynchronous();
    Code:
       0: aload_0
       1: getfield      #6                  // Field synchronous_:Z
       4: ireturn

  public java.util.List<org.apache.hadoop.hbase.shaded.protobuf.generated.MasterProtos$MasterSwitchType> getSwitchTypesList();
    Code:
       0: new           #44                 // class org/apache/hbase/thirdparty/com/google/protobuf/Internal$ListAdapter
       3: dup
       4: aload_0
       5: getfield      #5                  // Field switchTypes_:Ljava/util/List;
       8: getstatic     #2                  // Field switchTypes_converter_:Lorg/apache/hbase/thirdparty/com/google/protobuf/Internal$ListAdapter$Converter;
      11: invokespecial #45                 // Method org/apache/hbase/thirdparty/com/google/protobuf/Internal$ListAdapter."<init>":(Ljava/util/List;Lorg/apache/hbase/thirdparty/com/google/protobuf/Internal$ListAdapter$Converter;)V
      14: areturn

  public int getSwitchTypesCount();
    Code:
       0: aload_0
       1: getfield      #5                  // Field switchTypes_:Ljava/util/List;
       4: invokeinterface #46,  1           // InterfaceMethod java/util/List.size:()I
       9: ireturn

  public org.apache.hadoop.hbase.shaded.protobuf.generated.MasterProtos$MasterSwitchType getSwitchTypes(int);
    Code:
       0: getstatic     #2                  // Field switchTypes_converter_:Lorg/apache/hbase/thirdparty/com/google/protobuf/Internal$ListAdapter$Converter;
       3: aload_0
       4: getfield      #5                  // Field switchTypes_:Ljava/util/List;
       7: iload_1
       8: invokeinterface #47,  2           // InterfaceMethod java/util/List.get:(I)Ljava/lang/Object;
      13: invokeinterface #48,  2           // InterfaceMethod org/apache/hbase/thirdparty/com/google/protobuf/Internal$ListAdapter$Converter.convert:(Ljava/lang/Object;)Ljava/lang/Object;
      18: checkcast     #49                 // class org/apache/hadoop/hbase/shaded/protobuf/generated/MasterProtos$MasterSwitchType
      21: areturn

  public final boolean isInitialized();
    Code:
       0: aload_0
       1: getfield      #11                 // Field memoizedIsInitialized:B
       4: istore_1
       5: iload_1
       6: iconst_1
       7: if_icmpne     12
      10: iconst_1
      11: ireturn
      12: iload_1
      13: ifne          18
      16: iconst_0
      17: ireturn
      18: aload_0
      19: invokevirtual #50                 // Method hasEnabled:()Z
      22: ifne          32
      25: aload_0
      26: iconst_0
      27: putfield      #11                 // Field memoizedIsInitialized:B
      30: iconst_0
      31: ireturn
      32: aload_0
      33: iconst_1
      34: putfield      #11                 // Field memoizedIsInitialized:B
      37: iconst_1
      38: ireturn

  public void writeTo(org.apache.hbase.thirdparty.com.google.protobuf.CodedOutputStream) throws java.io.IOException;
    Code:
       0: aload_0
       1: getfield      #4                  // Field bitField0_:I
       4: iconst_1
       5: iand
       6: iconst_1
       7: if_icmpne     19
      10: aload_1
      11: iconst_1
      12: aload_0
      13: getfield      #7                  // Field enabled_:Z
      16: invokevirtual #51                 // Method org/apache/hbase/thirdparty/com/google/protobuf/CodedOutputStream.writeBool:(IZ)V
      19: aload_0
      20: getfield      #4                  // Field bitField0_:I
      23: iconst_2
      24: iand
      25: iconst_2
      26: if_icmpne     38
      29: aload_1
      30: iconst_2
      31: aload_0
      32: getfield      #6                  // Field synchronous_:Z
      35: invokevirtual #51                 // Method org/apache/hbase/thirdparty/com/google/protobuf/CodedOutputStream.writeBool:(IZ)V
      38: iconst_0
      39: istore_2
      40: iload_2
      41: aload_0
      42: getfield      #5                  // Field switchTypes_:Ljava/util/List;
      45: invokeinterface #46,  1           // InterfaceMethod java/util/List.size:()I
      50: if_icmpge     80
      53: aload_1
      54: iconst_3
      55: aload_0
      56: getfield      #5                  // Field switchTypes_:Ljava/util/List;
      59: iload_2
      60: invokeinterface #47,  2           // InterfaceMethod java/util/List.get:(I)Ljava/lang/Object;
      65: checkcast     #52                 // class java/lang/Integer
      68: invokevirtual #53                 // Method java/lang/Integer.intValue:()I
      71: invokevirtual #54                 // Method org/apache/hbase/thirdparty/com/google/protobuf/CodedOutputStream.writeEnum:(II)V
      74: iinc          2, 1
      77: goto          40
      80: aload_0
      81: getfield      #3                  // Field unknownFields:Lorg/apache/hbase/thirdparty/com/google/protobuf/UnknownFieldSet;
      84: aload_1
      85: invokevirtual #55                 // Method org/apache/hbase/thirdparty/com/google/protobuf/UnknownFieldSet.writeTo:(Lorg/apache/hbase/thirdparty/com/google/protobuf/CodedOutputStream;)V
      88: return

  public int getSerializedSize();
    Code:
       0: aload_0
       1: getfield      #56                 // Field memoizedSize:I
       4: istore_1
       5: iload_1
       6: iconst_m1
       7: if_icmpeq     12
      10: iload_1
      11: ireturn
      12: iconst_0
      13: istore_1
      14: aload_0
      15: getfield      #4                  // Field bitField0_:I
      18: iconst_1
      19: iand
      20: iconst_1
      21: if_icmpne     35
      24: iload_1
      25: iconst_1
      26: aload_0
      27: getfield      #7                  // Field enabled_:Z
      30: invokestatic  #57                 // Method org/apache/hbase/thirdparty/com/google/protobuf/CodedOutputStream.computeBoolSize:(IZ)I
      33: iadd
      34: istore_1
      35: aload_0
      36: getfield      #4                  // Field bitField0_:I
      39: iconst_2
      40: iand
      41: iconst_2
      42: if_icmpne     56
      45: iload_1
      46: iconst_2
      47: aload_0
      48: getfield      #6                  // Field synchronous_:Z
      51: invokestatic  #57                 // Method org/apache/hbase/thirdparty/com/google/protobuf/CodedOutputStream.computeBoolSize:(IZ)I
      54: iadd
      55: istore_1
      56: iconst_0
      57: istore_2
      58: iconst_0
      59: istore_3
      60: iload_3
      61: aload_0
      62: getfield      #5                  // Field switchTypes_:Ljava/util/List;
      65: invokeinterface #46,  1           // InterfaceMethod java/util/List.size:()I
      70: if_icmpge     101
      73: iload_2
      74: aload_0
      75: getfield      #5                  // Field switchTypes_:Ljava/util/List;
      78: iload_3
      79: invokeinterface #47,  2           // InterfaceMethod java/util/List.get:(I)Ljava/lang/Object;
      84: checkcast     #52                 // class java/lang/Integer
      87: invokevirtual #53                 // Method java/lang/Integer.intValue:()I
      90: invokestatic  #58                 // Method org/apache/hbase/thirdparty/com/google/protobuf/CodedOutputStream.computeEnumSizeNoTag:(I)I
      93: iadd
      94: istore_2
      95: iinc          3, 1
      98: goto          60
     101: iload_1
     102: iload_2
     103: iadd
     104: istore_1
     105: iload_1
     106: iconst_1
     107: aload_0
     108: getfield      #5                  // Field switchTypes_:Ljava/util/List;
     111: invokeinterface #46,  1           // InterfaceMethod java/util/List.size:()I
     116: imul
     117: iadd
     118: istore_1
     119: iload_1
     120: aload_0
     121: getfield      #3                  // Field unknownFields:Lorg/apache/hbase/thirdparty/com/google/protobuf/UnknownFieldSet;
     124: invokevirtual #59                 // Method org/apache/hbase/thirdparty/com/google/protobuf/UnknownFieldSet.getSerializedSize:()I
     127: iadd
     128: istore_1
     129: aload_0
     130: iload_1
     131: putfield      #56                 // Field memoizedSize:I
     134: iload_1
     135: ireturn

  public boolean equals(java.lang.Object);
    Code:
       0: aload_1
       1: aload_0
       2: if_acmpne     7
       5: iconst_1
       6: ireturn
       7: aload_1
       8: instanceof    #41                 // class org/apache/hadoop/hbase/shaded/protobuf/generated/MasterProtos$SetSplitOrMergeEnabledRequest
      11: ifne          20
      14: aload_0
      15: aload_1
      16: invokespecial #60                 // Method org/apache/hbase/thirdparty/com/google/protobuf/GeneratedMessageV3.equals:(Ljava/lang/Object;)Z
      19: ireturn
      20: aload_1
      21: checkcast     #41                 // class org/apache/hadoop/hbase/shaded/protobuf/generated/MasterProtos$SetSplitOrMergeEnabledRequest
      24: astore_2
      25: iconst_1
      26: istore_3
      27: iload_3
      28: ifeq          46
      31: aload_0
      32: invokevirtual #50                 // Method hasEnabled:()Z
      35: aload_2
      36: invokevirtual #50                 // Method hasEnabled:()Z
      39: if_icmpne     46
      42: iconst_1
      43: goto          47
      46: iconst_0
      47: istore_3
      48: aload_0
      49: invokevirtual #50                 // Method hasEnabled:()Z
      52: ifeq          76
      55: iload_3
      56: ifeq          74
      59: aload_0
      60: invokevirtual #61                 // Method getEnabled:()Z
      63: aload_2
      64: invokevirtual #61                 // Method getEnabled:()Z
      67: if_icmpne     74
      70: iconst_1
      71: goto          75
      74: iconst_0
      75: istore_3
      76: iload_3
      77: ifeq          95
      80: aload_0
      81: invokevirtual #62                 // Method hasSynchronous:()Z
      84: aload_2
      85: invokevirtual #62                 // Method hasSynchronous:()Z
      88: if_icmpne     95
      91: iconst_1
      92: goto          96
      95: iconst_0
      96: istore_3
      97: aload_0
      98: invokevirtual #62                 // Method hasSynchronous:()Z
     101: ifeq          125
     104: iload_3
     105: ifeq          123
     108: aload_0
     109: invokevirtual #63                 // Method getSynchronous:()Z
     112: aload_2
     113: invokevirtual #63                 // Method getSynchronous:()Z
     116: if_icmpne     123
     119: iconst_1
     120: goto          124
     123: iconst_0
     124: istore_3
     125: iload_3
     126: ifeq          149
     129: aload_0
     130: getfield      #5                  // Field switchTypes_:Ljava/util/List;
     133: aload_2
     134: getfield      #5                  // Field switchTypes_:Ljava/util/List;
     137: invokeinterface #64,  2           // InterfaceMethod java/util/List.equals:(Ljava/lang/Object;)Z
     142: ifeq          149
     145: iconst_1
     146: goto          150
     149: iconst_0
     150: istore_3
     151: iload_3
     152: ifeq          173
     155: aload_0
     156: getfield      #3                  // Field unknownFields:Lorg/apache/hbase/thirdparty/com/google/protobuf/UnknownFieldSet;
     159: aload_2
     160: getfield      #3                  // Field unknownFields:Lorg/apache/hbase/thirdparty/com/google/protobuf/UnknownFieldSet;
     163: invokevirtual #65                 // Method org/apache/hbase/thirdparty/com/google/protobuf/UnknownFieldSet.equals:(Ljava/lang/Object;)Z
     166: ifeq          173
     169: iconst_1
     170: goto          174
     173: iconst_0
     174: istore_3
     175: iload_3
     176: ireturn

  public int hashCode();
    Code:
       0: aload_0
       1: getfield      #66                 // Field memoizedHashCode:I
       4: ifeq          12
       7: aload_0
       8: getfield      #66                 // Field memoizedHashCode:I
      11: ireturn
      12: bipush        41
      14: istore_1
      15: bipush        19
      17: iload_1
      18: imul
      19: invokestatic  #67                 // Method getDescriptor:()Lorg/apache/hbase/thirdparty/com/google/protobuf/Descriptors$Descriptor;
      22: invokevirtual #68                 // Method java/lang/Object.hashCode:()I
      25: iadd
      26: istore_1
      27: aload_0
      28: invokevirtual #50                 // Method hasEnabled:()Z
      31: ifeq          54
      34: bipush        37
      36: iload_1
      37: imul
      38: iconst_1
      39: iadd
      40: istore_1
      41: bipush        53
      43: iload_1
      44: imul
      45: aload_0
      46: invokevirtual #61                 // Method getEnabled:()Z
      49: invokestatic  #69                 // Method org/apache/hbase/thirdparty/com/google/protobuf/Internal.hashBoolean:(Z)I
      52: iadd
      53: istore_1
      54: aload_0
      55: invokevirtual #62                 // Method hasSynchronous:()Z
      58: ifeq          81
      61: bipush        37
      63: iload_1
      64: imul
      65: iconst_2
      66: iadd
      67: istore_1
      68: bipush        53
      70: iload_1
      71: imul
      72: aload_0
      73: invokevirtual #63                 // Method getSynchronous:()Z
      76: invokestatic  #69                 // Method org/apache/hbase/thirdparty/com/google/protobuf/Internal.hashBoolean:(Z)I
      79: iadd
      80: istore_1
      81: aload_0
      82: invokevirtual #70                 // Method getSwitchTypesCount:()I
      85: ifle          110
      88: bipush        37
      90: iload_1
      91: imul
      92: iconst_3
      93: iadd
      94: istore_1
      95: bipush        53
      97: iload_1
      98: imul
      99: aload_0
     100: getfield      #5                  // Field switchTypes_:Ljava/util/List;
     103: invokeinterface #71,  1           // InterfaceMethod java/util/List.hashCode:()I
     108: iadd
     109: istore_1
     110: bipush        29
     112: iload_1
     113: imul
     114: aload_0
     115: getfield      #3                  // Field unknownFields:Lorg/apache/hbase/thirdparty/com/google/protobuf/UnknownFieldSet;
     118: invokevirtual #72                 // Method org/apache/hbase/thirdparty/com/google/protobuf/UnknownFieldSet.hashCode:()I
     121: iadd
     122: istore_1
     123: aload_0
     124: iload_1
     125: putfield      #66                 // Field memoizedHashCode:I
     128: iload_1
     129: ireturn

  public static org.apache.hadoop.hbase.shaded.protobuf.generated.MasterProtos$SetSplitOrMergeEnabledRequest parseFrom(java.nio.ByteBuffer) throws org.apache.hbase.thirdparty.com.google.protobuf.InvalidProtocolBufferException;
    Code:
       0: getstatic     #73                 // Field PARSER:Lorg/apache/hbase/thirdparty/com/google/protobuf/Parser;
       3: aload_0
       4: invokeinterface #74,  2           // InterfaceMethod org/apache/hbase/thirdparty/com/google/protobuf/Parser.parseFrom:(Ljava/nio/ByteBuffer;)Ljava/lang/Object;
       9: checkcast     #41                 // class org/apache/hadoop/hbase/shaded/protobuf/generated/MasterProtos$SetSplitOrMergeEnabledRequest
      12: areturn

  public static org.apache.hadoop.hbase.shaded.protobuf.generated.MasterProtos$SetSplitOrMergeEnabledRequest parseFrom(java.nio.ByteBuffer, org.apache.hbase.thirdparty.com.google.protobuf.ExtensionRegistryLite) throws org.apache.hbase.thirdparty.com.google.protobuf.InvalidProtocolBufferException;
    Code:
       0: getstatic     #73                 // Field PARSER:Lorg/apache/hbase/thirdparty/com/google/protobuf/Parser;
       3: aload_0
       4: aload_1
       5: invokeinterface #75,  3           // InterfaceMethod org/apache/hbase/thirdparty/com/google/protobuf/Parser.parseFrom:(Ljava/nio/ByteBuffer;Lorg/apache/hbase/thirdparty/com/google/protobuf/ExtensionRegistryLite;)Ljava/lang/Object;
      10: checkcast     #41                 // class org/apache/hadoop/hbase/shaded/protobuf/generated/MasterProtos$SetSplitOrMergeEnabledRequest
      13: areturn

  public static org.apache.hadoop.hbase.shaded.protobuf.generated.MasterProtos$SetSplitOrMergeEnabledRequest parseFrom(org.apache.hbase.thirdparty.com.google.protobuf.ByteString) throws org.apache.hbase.thirdparty.com.google.protobuf.InvalidProtocolBufferException;
    Code:
       0: getstatic     #73                 // Field PARSER:Lorg/apache/hbase/thirdparty/com/google/protobuf/Parser;
       3: aload_0
       4: invokeinterface #76,  2           // InterfaceMethod org/apache/hbase/thirdparty/com/google/protobuf/Parser.parseFrom:(Lorg/apache/hbase/thirdparty/com/google/protobuf/ByteString;)Ljava/lang/Object;
       9: checkcast     #41                 // class org/apache/hadoop/hbase/shaded/protobuf/generated/MasterProtos$SetSplitOrMergeEnabledRequest
      12: areturn

  public static org.apache.hadoop.hbase.shaded.protobuf.generated.MasterProtos$SetSplitOrMergeEnabledRequest parseFrom(org.apache.hbase.thirdparty.com.google.protobuf.ByteString, org.apache.hbase.thirdparty.com.google.protobuf.ExtensionRegistryLite) throws org.apache.hbase.thirdparty.com.google.protobuf.InvalidProtocolBufferException;
    Code:
       0: getstatic     #73                 // Field PARSER:Lorg/apache/hbase/thirdparty/com/google/protobuf/Parser;
       3: aload_0
       4: aload_1
       5: invokeinterface #77,  3           // InterfaceMethod org/apache/hbase/thirdparty/com/google/protobuf/Parser.parseFrom:(Lorg/apache/hbase/thirdparty/com/google/protobuf/ByteString;Lorg/apache/hbase/thirdparty/com/google/protobuf/ExtensionRegistryLite;)Ljava/lang/Object;
      10: checkcast     #41                 // class org/apache/hadoop/hbase/shaded/protobuf/generated/MasterProtos$SetSplitOrMergeEnabledRequest
      13: areturn

  public static org.apache.hadoop.hbase.shaded.protobuf.generated.MasterProtos$SetSplitOrMergeEnabledRequest parseFrom(byte[]) throws org.apache.hbase.thirdparty.com.google.protobuf.InvalidProtocolBufferException;
    Code:
       0: getstatic     #73                 // Field PARSER:Lorg/apache/hbase/thirdparty/com/google/protobuf/Parser;
       3: aload_0
       4: invokeinterface #78,  2           // InterfaceMethod org/apache/hbase/thirdparty/com/google/protobuf/Parser.parseFrom:([B)Ljava/lang/Object;
       9: checkcast     #41                 // class org/apache/hadoop/hbase/shaded/protobuf/generated/MasterProtos$SetSplitOrMergeEnabledRequest
      12: areturn

  public static org.apache.hadoop.hbase.shaded.protobuf.generated.MasterProtos$SetSplitOrMergeEnabledRequest parseFrom(byte[], org.apache.hbase.thirdparty.com.google.protobuf.ExtensionRegistryLite) throws org.apache.hbase.thirdparty.com.google.protobuf.InvalidProtocolBufferException;
    Code:
       0: getstatic     #73                 // Field PARSER:Lorg/apache/hbase/thirdparty/com/google/protobuf/Parser;
       3: aload_0
       4: aload_1
       5: invokeinterface #79,  3           // InterfaceMethod org/apache/hbase/thirdparty/com/google/protobuf/Parser.parseFrom:([BLorg/apache/hbase/thirdparty/com/google/protobuf/ExtensionRegistryLite;)Ljava/lang/Object;
      10: checkcast     #41                 // class org/apache/hadoop/hbase/shaded/protobuf/generated/MasterProtos$SetSplitOrMergeEnabledRequest
      13: areturn

  public static org.apache.hadoop.hbase.shaded.protobuf.generated.MasterProtos$SetSplitOrMergeEnabledRequest parseFrom(java.io.InputStream) throws java.io.IOException;
    Code:
       0: getstatic     #73                 // Field PARSER:Lorg/apache/hbase/thirdparty/com/google/protobuf/Parser;
       3: aload_0
       4: invokestatic  #80                 // Method org/apache/hbase/thirdparty/com/google/protobuf/GeneratedMessageV3.parseWithIOException:(Lorg/apache/hbase/thirdparty/com/google/protobuf/Parser;Ljava/io/InputStream;)Lorg/apache/hbase/thirdparty/com/google/protobuf/Message;
       7: checkcast     #41                 // class org/apache/hadoop/hbase/shaded/protobuf/generated/MasterProtos$SetSplitOrMergeEnabledRequest
      10: areturn

  public static org.apache.hadoop.hbase.shaded.protobuf.generated.MasterProtos$SetSplitOrMergeEnabledRequest parseFrom(java.io.InputStream, org.apache.hbase.thirdparty.com.google.protobuf.ExtensionRegistryLite) throws java.io.IOException;
    Code:
       0: getstatic     #73                 // Field PARSER:Lorg/apache/hbase/thirdparty/com/google/protobuf/Parser;
       3: aload_0
       4: aload_1
       5: invokestatic  #81                 // Method org/apache/hbase/thirdparty/com/google/protobuf/GeneratedMessageV3.parseWithIOException:(Lorg/apache/hbase/thirdparty/com/google/protobuf/Parser;Ljava/io/InputStream;Lorg/apache/hbase/thirdparty/com/google/protobuf/ExtensionRegistryLite;)Lorg/apache/hbase/thirdparty/com/google/protobuf/Message;
       8: checkcast     #41                 // class org/apache/hadoop/hbase/shaded/protobuf/generated/MasterProtos$SetSplitOrMergeEnabledRequest
      11: areturn

  public static org.apache.hadoop.hbase.shaded.protobuf.generated.MasterProtos$SetSplitOrMergeEnabledRequest parseDelimitedFrom(java.io.InputStream) throws java.io.IOException;
    Code:
       0: getstatic     #73                 // Field PARSER:Lorg/apache/hbase/thirdparty/com/google/protobuf/Parser;
       3: aload_0
       4: invokestatic  #82                 // Method org/apache/hbase/thirdparty/com/google/protobuf/GeneratedMessageV3.parseDelimitedWithIOException:(Lorg/apache/hbase/thirdparty/com/google/protobuf/Parser;Ljava/io/InputStream;)Lorg/apache/hbase/thirdparty/com/google/protobuf/Message;
       7: checkcast     #41                 // class org/apache/hadoop/hbase/shaded/protobuf/generated/MasterProtos$SetSplitOrMergeEnabledRequest
      10: areturn

  public static org.apache.hadoop.hbase.shaded.protobuf.generated.MasterProtos$SetSplitOrMergeEnabledRequest parseDelimitedFrom(java.io.InputStream, org.apache.hbase.thirdparty.com.google.protobuf.ExtensionRegistryLite) throws java.io.IOException;
    Code:
       0: getstatic     #73                 // Field PARSER:Lorg/apache/hbase/thirdparty/com/google/protobuf/Parser;
       3: aload_0
       4: aload_1
       5: invokestatic  #83                 // Method org/apache/hbase/thirdparty/com/google/protobuf/GeneratedMessageV3.parseDelimitedWithIOException:(Lorg/apache/hbase/thirdparty/com/google/protobuf/Parser;Ljava/io/InputStream;Lorg/apache/hbase/thirdparty/com/google/protobuf/ExtensionRegistryLite;)Lorg/apache/hbase/thirdparty/com/google/protobuf/Message;
       8: checkcast     #41                 // class org/apache/hadoop/hbase/shaded/protobuf/generated/MasterProtos$SetSplitOrMergeEnabledRequest
      11: areturn

  public static org.apache.hadoop.hbase.shaded.protobuf.generated.MasterProtos$SetSplitOrMergeEnabledRequest parseFrom(org.apache.hbase.thirdparty.com.google.protobuf.CodedInputStream) throws java.io.IOException;
    Code:
       0: getstatic     #73                 // Field PARSER:Lorg/apache/hbase/thirdparty/com/google/protobuf/Parser;
       3: aload_0
       4: invokestatic  #84                 // Method org/apache/hbase/thirdparty/com/google/protobuf/GeneratedMessageV3.parseWithIOException:(Lorg/apache/hbase/thirdparty/com/google/protobuf/Parser;Lorg/apache/hbase/thirdparty/com/google/protobuf/CodedInputStream;)Lorg/apache/hbase/thirdparty/com/google/protobuf/Message;
       7: checkcast     #41                 // class org/apache/hadoop/hbase/shaded/protobuf/generated/MasterProtos$SetSplitOrMergeEnabledRequest
      10: areturn

  public static org.apache.hadoop.hbase.shaded.protobuf.generated.MasterProtos$SetSplitOrMergeEnabledRequest parseFrom(org.apache.hbase.thirdparty.com.google.protobuf.CodedInputStream, org.apache.hbase.thirdparty.com.google.protobuf.ExtensionRegistryLite) throws java.io.IOException;
    Code:
       0: getstatic     #73                 // Field PARSER:Lorg/apache/hbase/thirdparty/com/google/protobuf/Parser;
       3: aload_0
       4: aload_1
       5: invokestatic  #85                 // Method org/apache/hbase/thirdparty/com/google/protobuf/GeneratedMessageV3.parseWithIOException:(Lorg/apache/hbase/thirdparty/com/google/protobuf/Parser;Lorg/apache/hbase/thirdparty/com/google/protobuf/CodedInputStream;Lorg/apache/hbase/thirdparty/com/google/protobuf/ExtensionRegistryLite;)Lorg/apache/hbase/thirdparty/com/google/protobuf/Message;
       8: checkcast     #41                 // class org/apache/hadoop/hbase/shaded/protobuf/generated/MasterProtos$SetSplitOrMergeEnabledRequest
      11: areturn

  public org.apache.hadoop.hbase.shaded.protobuf.generated.MasterProtos$SetSplitOrMergeEnabledRequest$Builder newBuilderForType();
    Code:
       0: invokestatic  #86                 // Method newBuilder:()Lorg/apache/hadoop/hbase/shaded/protobuf/generated/MasterProtos$SetSplitOrMergeEnabledRequest$Builder;
       3: areturn

  public static org.apache.hadoop.hbase.shaded.protobuf.generated.MasterProtos$SetSplitOrMergeEnabledRequest$Builder newBuilder();
    Code:
       0: getstatic     #87                 // Field DEFAULT_INSTANCE:Lorg/apache/hadoop/hbase/shaded/protobuf/generated/MasterProtos$SetSplitOrMergeEnabledRequest;
       3: invokevirtual #88                 // Method toBuilder:()Lorg/apache/hadoop/hbase/shaded/protobuf/generated/MasterProtos$SetSplitOrMergeEnabledRequest$Builder;
       6: areturn

  public static org.apache.hadoop.hbase.shaded.protobuf.generated.MasterProtos$SetSplitOrMergeEnabledRequest$Builder newBuilder(org.apache.hadoop.hbase.shaded.protobuf.generated.MasterProtos$SetSplitOrMergeEnabledRequest);
    Code:
       0: getstatic     #87                 // Field DEFAULT_INSTANCE:Lorg/apache/hadoop/hbase/shaded/protobuf/generated/MasterProtos$SetSplitOrMergeEnabledRequest;
       3: invokevirtual #88                 // Method toBuilder:()Lorg/apache/hadoop/hbase/shaded/protobuf/generated/MasterProtos$SetSplitOrMergeEnabledRequest$Builder;
       6: aload_0
       7: invokevirtual #89                 // Method org/apache/hadoop/hbase/shaded/protobuf/generated/MasterProtos$SetSplitOrMergeEnabledRequest$Builder.mergeFrom:(Lorg/apache/hadoop/hbase/shaded/protobuf/generated/MasterProtos$SetSplitOrMergeEnabledRequest;)Lorg/apache/hadoop/hbase/shaded/protobuf/generated/MasterProtos$SetSplitOrMergeEnabledRequest$Builder;
      10: areturn

  public org.apache.hadoop.hbase.shaded.protobuf.generated.MasterProtos$SetSplitOrMergeEnabledRequest$Builder toBuilder();
    Code:
       0: aload_0
       1: getstatic     #87                 // Field DEFAULT_INSTANCE:Lorg/apache/hadoop/hbase/shaded/protobuf/generated/MasterProtos$SetSplitOrMergeEnabledRequest;
       4: if_acmpne     18
       7: new           #42                 // class org/apache/hadoop/hbase/shaded/protobuf/generated/MasterProtos$SetSplitOrMergeEnabledRequest$Builder
      10: dup
      11: aconst_null
      12: invokespecial #90                 // Method org/apache/hadoop/hbase/shaded/protobuf/generated/MasterProtos$SetSplitOrMergeEnabledRequest$Builder."<init>":(Lorg/apache/hadoop/hbase/shaded/protobuf/generated/MasterProtos$1;)V
      15: goto          30
      18: new           #42                 // class org/apache/hadoop/hbase/shaded/protobuf/generated/MasterProtos$SetSplitOrMergeEnabledRequest$Builder
      21: dup
      22: aconst_null
      23: invokespecial #90                 // Method org/apache/hadoop/hbase/shaded/protobuf/generated/MasterProtos$SetSplitOrMergeEnabledRequest$Builder."<init>":(Lorg/apache/hadoop/hbase/shaded/protobuf/generated/MasterProtos$1;)V
      26: aload_0
      27: invokevirtual #89                 // Method org/apache/hadoop/hbase/shaded/protobuf/generated/MasterProtos$SetSplitOrMergeEnabledRequest$Builder.mergeFrom:(Lorg/apache/hadoop/hbase/shaded/protobuf/generated/MasterProtos$SetSplitOrMergeEnabledRequest;)Lorg/apache/hadoop/hbase/shaded/protobuf/generated/MasterProtos$SetSplitOrMergeEnabledRequest$Builder;
      30: areturn

  protected org.apache.hadoop.hbase.shaded.protobuf.generated.MasterProtos$SetSplitOrMergeEnabledRequest$Builder newBuilderForType(org.apache.hbase.thirdparty.com.google.protobuf.GeneratedMessageV3$BuilderParent);
    Code:
       0: new           #42                 // class org/apache/hadoop/hbase/shaded/protobuf/generated/MasterProtos$SetSplitOrMergeEnabledRequest$Builder
       3: dup
       4: aload_1
       5: aconst_null
       6: invokespecial #91                 // Method org/apache/hadoop/hbase/shaded/protobuf/generated/MasterProtos$SetSplitOrMergeEnabledRequest$Builder."<init>":(Lorg/apache/hbase/thirdparty/com/google/protobuf/GeneratedMessageV3$BuilderParent;Lorg/apache/hadoop/hbase/shaded/protobuf/generated/MasterProtos$1;)V
       9: astore_2
      10: aload_2
      11: areturn

  public static org.apache.hadoop.hbase.shaded.protobuf.generated.MasterProtos$SetSplitOrMergeEnabledRequest getDefaultInstance();
    Code:
       0: getstatic     #87                 // Field DEFAULT_INSTANCE:Lorg/apache/hadoop/hbase/shaded/protobuf/generated/MasterProtos$SetSplitOrMergeEnabledRequest;
       3: areturn

  public static org.apache.hbase.thirdparty.com.google.protobuf.Parser<org.apache.hadoop.hbase.shaded.protobuf.generated.MasterProtos$SetSplitOrMergeEnabledRequest> parser();
    Code:
       0: getstatic     #73                 // Field PARSER:Lorg/apache/hbase/thirdparty/com/google/protobuf/Parser;
       3: areturn

  public org.apache.hbase.thirdparty.com.google.protobuf.Parser<org.apache.hadoop.hbase.shaded.protobuf.generated.MasterProtos$SetSplitOrMergeEnabledRequest> getParserForType();
    Code:
       0: getstatic     #73                 // Field PARSER:Lorg/apache/hbase/thirdparty/com/google/protobuf/Parser;
       3: areturn

  public org.apache.hadoop.hbase.shaded.protobuf.generated.MasterProtos$SetSplitOrMergeEnabledRequest getDefaultInstanceForType();
    Code:
       0: getstatic     #87                 // Field DEFAULT_INSTANCE:Lorg/apache/hadoop/hbase/shaded/protobuf/generated/MasterProtos$SetSplitOrMergeEnabledRequest;
       3: areturn

  protected org.apache.hbase.thirdparty.com.google.protobuf.Message$Builder newBuilderForType(org.apache.hbase.thirdparty.com.google.protobuf.GeneratedMessageV3$BuilderParent);
    Code:
       0: aload_0
       1: aload_1
       2: invokevirtual #92                 // Method newBuilderForType:(Lorg/apache/hbase/thirdparty/com/google/protobuf/GeneratedMessageV3$BuilderParent;)Lorg/apache/hadoop/hbase/shaded/protobuf/generated/MasterProtos$SetSplitOrMergeEnabledRequest$Builder;
       5: areturn

  public org.apache.hbase.thirdparty.com.google.protobuf.Message$Builder toBuilder();
    Code:
       0: aload_0
       1: invokevirtual #88                 // Method toBuilder:()Lorg/apache/hadoop/hbase/shaded/protobuf/generated/MasterProtos$SetSplitOrMergeEnabledRequest$Builder;
       4: areturn

  public org.apache.hbase.thirdparty.com.google.protobuf.Message$Builder newBuilderForType();
    Code:
       0: aload_0
       1: invokevirtual #93                 // Method newBuilderForType:()Lorg/apache/hadoop/hbase/shaded/protobuf/generated/MasterProtos$SetSplitOrMergeEnabledRequest$Builder;
       4: areturn

  public org.apache.hbase.thirdparty.com.google.protobuf.MessageLite$Builder toBuilder();
    Code:
       0: aload_0
       1: invokevirtual #88                 // Method toBuilder:()Lorg/apache/hadoop/hbase/shaded/protobuf/generated/MasterProtos$SetSplitOrMergeEnabledRequest$Builder;
       4: areturn

  public org.apache.hbase.thirdparty.com.google.protobuf.MessageLite$Builder newBuilderForType();
    Code:
       0: aload_0
       1: invokevirtual #93                 // Method newBuilderForType:()Lorg/apache/hadoop/hbase/shaded/protobuf/generated/MasterProtos$SetSplitOrMergeEnabledRequest$Builder;
       4: areturn

  public org.apache.hbase.thirdparty.com.google.protobuf.MessageLite getDefaultInstanceForType();
    Code:
       0: aload_0
       1: invokevirtual #94                 // Method getDefaultInstanceForType:()Lorg/apache/hadoop/hbase/shaded/protobuf/generated/MasterProtos$SetSplitOrMergeEnabledRequest;
       4: areturn

  public org.apache.hbase.thirdparty.com.google.protobuf.Message getDefaultInstanceForType();
    Code:
       0: aload_0
       1: invokevirtual #94                 // Method getDefaultInstanceForType:()Lorg/apache/hadoop/hbase/shaded/protobuf/generated/MasterProtos$SetSplitOrMergeEnabledRequest;
       4: areturn

  static boolean access$60000();
    Code:
       0: getstatic     #9                  // Field alwaysUseFieldBuilders:Z
       3: ireturn

  org.apache.hadoop.hbase.shaded.protobuf.generated.MasterProtos$SetSplitOrMergeEnabledRequest(org.apache.hbase.thirdparty.com.google.protobuf.GeneratedMessageV3$Builder, org.apache.hadoop.hbase.shaded.protobuf.generated.MasterProtos$1);
    Code:
       0: aload_0
       1: aload_1
       2: invokespecial #8                  // Method "<init>":(Lorg/apache/hbase/thirdparty/com/google/protobuf/GeneratedMessageV3$Builder;)V
       5: return

  static boolean access$60202(org.apache.hadoop.hbase.shaded.protobuf.generated.MasterProtos$SetSplitOrMergeEnabledRequest, boolean);
    Code:
       0: aload_0
       1: iload_1
       2: dup_x1
       3: putfield      #7                  // Field enabled_:Z
       6: ireturn

  static boolean access$60302(org.apache.hadoop.hbase.shaded.protobuf.generated.MasterProtos$SetSplitOrMergeEnabledRequest, boolean);
    Code:
       0: aload_0
       1: iload_1
       2: dup_x1
       3: putfield      #6                  // Field synchronous_:Z
       6: ireturn

  static java.util.List access$60402(org.apache.hadoop.hbase.shaded.protobuf.generated.MasterProtos$SetSplitOrMergeEnabledRequest, java.util.List);
    Code:
       0: aload_0
       1: aload_1
       2: dup_x1
       3: putfield      #5                  // Field switchTypes_:Ljava/util/List;
       6: areturn

  static int access$60502(org.apache.hadoop.hbase.shaded.protobuf.generated.MasterProtos$SetSplitOrMergeEnabledRequest, int);
    Code:
       0: aload_0
       1: iload_1
       2: dup_x1
       3: putfield      #4                  // Field bitField0_:I
       6: ireturn

  static java.util.List access$60400(org.apache.hadoop.hbase.shaded.protobuf.generated.MasterProtos$SetSplitOrMergeEnabledRequest);
    Code:
       0: aload_0
       1: getfield      #5                  // Field switchTypes_:Ljava/util/List;
       4: areturn

  static org.apache.hbase.thirdparty.com.google.protobuf.UnknownFieldSet access$60600(org.apache.hadoop.hbase.shaded.protobuf.generated.MasterProtos$SetSplitOrMergeEnabledRequest);
    Code:
       0: aload_0
       1: getfield      #3                  // Field unknownFields:Lorg/apache/hbase/thirdparty/com/google/protobuf/UnknownFieldSet;
       4: areturn

  static org.apache.hbase.thirdparty.com.google.protobuf.Internal$ListAdapter$Converter access$60700();
    Code:
       0: getstatic     #2                  // Field switchTypes_converter_:Lorg/apache/hbase/thirdparty/com/google/protobuf/Internal$ListAdapter$Converter;
       3: areturn

  org.apache.hadoop.hbase.shaded.protobuf.generated.MasterProtos$SetSplitOrMergeEnabledRequest(org.apache.hbase.thirdparty.com.google.protobuf.CodedInputStream, org.apache.hbase.thirdparty.com.google.protobuf.ExtensionRegistryLite, org.apache.hadoop.hbase.shaded.protobuf.generated.MasterProtos$1) throws org.apache.hbase.thirdparty.com.google.protobuf.InvalidProtocolBufferException;
    Code:
       0: aload_0
       1: aload_1
       2: aload_2
       3: invokespecial #1                  // Method "<init>":(Lorg/apache/hbase/thirdparty/com/google/protobuf/CodedInputStream;Lorg/apache/hbase/thirdparty/com/google/protobuf/ExtensionRegistryLite;)V
       6: return

  static {};
    Code:
       0: new           #95                 // class org/apache/hadoop/hbase/shaded/protobuf/generated/MasterProtos$SetSplitOrMergeEnabledRequest$1
       3: dup
       4: invokespecial #96                 // Method org/apache/hadoop/hbase/shaded/protobuf/generated/MasterProtos$SetSplitOrMergeEnabledRequest$1."<init>":()V
       7: putstatic     #2                  // Field switchTypes_converter_:Lorg/apache/hbase/thirdparty/com/google/protobuf/Internal$ListAdapter$Converter;
      10: new           #41                 // class org/apache/hadoop/hbase/shaded/protobuf/generated/MasterProtos$SetSplitOrMergeEnabledRequest
      13: dup
      14: invokespecial #14                 // Method "<init>":()V
      17: putstatic     #87                 // Field DEFAULT_INSTANCE:Lorg/apache/hadoop/hbase/shaded/protobuf/generated/MasterProtos$SetSplitOrMergeEnabledRequest;
      20: new           #97                 // class org/apache/hadoop/hbase/shaded/protobuf/generated/MasterProtos$SetSplitOrMergeEnabledRequest$2
      23: dup
      24: invokespecial #98                 // Method org/apache/hadoop/hbase/shaded/protobuf/generated/MasterProtos$SetSplitOrMergeEnabledRequest$2."<init>":()V
      27: putstatic     #73                 // Field PARSER:Lorg/apache/hbase/thirdparty/com/google/protobuf/Parser;
      30: return
}
