Compiled from "MasterProtos.java"
final class org.apache.hadoop.hbase.shaded.protobuf.generated.MasterProtos$HbckService$BlockingStub implements org.apache.hadoop.hbase.shaded.protobuf.generated.MasterProtos$HbckService$BlockingInterface {
  public org.apache.hadoop.hbase.shaded.protobuf.generated.MasterProtos$GetTableStateResponse setTableStateInMeta(org.apache.hbase.thirdparty.com.google.protobuf.RpcController, org.apache.hadoop.hbase.shaded.protobuf.generated.MasterProtos$SetTableStateInMetaRequest) throws org.apache.hbase.thirdparty.com.google.protobuf.ServiceException;
    Code:
       0: aload_0
       1: getfield      #3                  // Field channel:Lorg/apache/hbase/thirdparty/com/google/protobuf/BlockingRpcChannel;
       4: invokestatic  #4                  // Method org/apache/hadoop/hbase/shaded/protobuf/generated/MasterProtos$HbckService.getDescriptor:()Lorg/apache/hbase/thirdparty/com/google/protobuf/Descriptors$ServiceDescriptor;
       7: invokevirtual #5                  // Method org/apache/hbase/thirdparty/com/google/protobuf/Descriptors$ServiceDescriptor.getMethods:()Ljava/util/List;
      10: iconst_0
      11: invokeinterface #6,  2            // InterfaceMethod java/util/List.get:(I)Ljava/lang/Object;
      16: checkcast     #7                  // class org/apache/hbase/thirdparty/com/google/protobuf/Descriptors$MethodDescriptor
      19: aload_1
      20: aload_2
      21: invokestatic  #8                  // Method org/apache/hadoop/hbase/shaded/protobuf/generated/MasterProtos$GetTableStateResponse.getDefaultInstance:()Lorg/apache/hadoop/hbase/shaded/protobuf/generated/MasterProtos$GetTableStateResponse;
      24: invokeinterface #9,  5            // InterfaceMethod org/apache/hbase/thirdparty/com/google/protobuf/BlockingRpcChannel.callBlockingMethod:(Lorg/apache/hbase/thirdparty/com/google/protobuf/Descriptors$MethodDescriptor;Lorg/apache/hbase/thirdparty/com/google/protobuf/RpcController;Lorg/apache/hbase/thirdparty/com/google/protobuf/Message;Lorg/apache/hbase/thirdparty/com/google/protobuf/Message;)Lorg/apache/hbase/thirdparty/com/google/protobuf/Message;
      29: checkcast     #10                 // class org/apache/hadoop/hbase/shaded/protobuf/generated/MasterProtos$GetTableStateResponse
      32: areturn

  public org.apache.hadoop.hbase.shaded.protobuf.generated.MasterProtos$AssignsResponse assigns(org.apache.hbase.thirdparty.com.google.protobuf.RpcController, org.apache.hadoop.hbase.shaded.protobuf.generated.MasterProtos$AssignsRequest) throws org.apache.hbase.thirdparty.com.google.protobuf.ServiceException;
    Code:
       0: aload_0
       1: getfield      #3                  // Field channel:Lorg/apache/hbase/thirdparty/com/google/protobuf/BlockingRpcChannel;
       4: invokestatic  #4                  // Method org/apache/hadoop/hbase/shaded/protobuf/generated/MasterProtos$HbckService.getDescriptor:()Lorg/apache/hbase/thirdparty/com/google/protobuf/Descriptors$ServiceDescriptor;
       7: invokevirtual #5                  // Method org/apache/hbase/thirdparty/com/google/protobuf/Descriptors$ServiceDescriptor.getMethods:()Ljava/util/List;
      10: iconst_1
      11: invokeinterface #6,  2            // InterfaceMethod java/util/List.get:(I)Ljava/lang/Object;
      16: checkcast     #7                  // class org/apache/hbase/thirdparty/com/google/protobuf/Descriptors$MethodDescriptor
      19: aload_1
      20: aload_2
      21: invokestatic  #11                 // Method org/apache/hadoop/hbase/shaded/protobuf/generated/MasterProtos$AssignsResponse.getDefaultInstance:()Lorg/apache/hadoop/hbase/shaded/protobuf/generated/MasterProtos$AssignsResponse;
      24: invokeinterface #9,  5            // InterfaceMethod org/apache/hbase/thirdparty/com/google/protobuf/BlockingRpcChannel.callBlockingMethod:(Lorg/apache/hbase/thirdparty/com/google/protobuf/Descriptors$MethodDescriptor;Lorg/apache/hbase/thirdparty/com/google/protobuf/RpcController;Lorg/apache/hbase/thirdparty/com/google/protobuf/Message;Lorg/apache/hbase/thirdparty/com/google/protobuf/Message;)Lorg/apache/hbase/thirdparty/com/google/protobuf/Message;
      29: checkcast     #12                 // class org/apache/hadoop/hbase/shaded/protobuf/generated/MasterProtos$AssignsResponse
      32: areturn

  public org.apache.hadoop.hbase.shaded.protobuf.generated.MasterProtos$UnassignsResponse unassigns(org.apache.hbase.thirdparty.com.google.protobuf.RpcController, org.apache.hadoop.hbase.shaded.protobuf.generated.MasterProtos$UnassignsRequest) throws org.apache.hbase.thirdparty.com.google.protobuf.ServiceException;
    Code:
       0: aload_0
       1: getfield      #3                  // Field channel:Lorg/apache/hbase/thirdparty/com/google/protobuf/BlockingRpcChannel;
       4: invokestatic  #4                  // Method org/apache/hadoop/hbase/shaded/protobuf/generated/MasterProtos$HbckService.getDescriptor:()Lorg/apache/hbase/thirdparty/com/google/protobuf/Descriptors$ServiceDescriptor;
       7: invokevirtual #5                  // Method org/apache/hbase/thirdparty/com/google/protobuf/Descriptors$ServiceDescriptor.getMethods:()Ljava/util/List;
      10: iconst_2
      11: invokeinterface #6,  2            // InterfaceMethod java/util/List.get:(I)Ljava/lang/Object;
      16: checkcast     #7                  // class org/apache/hbase/thirdparty/com/google/protobuf/Descriptors$MethodDescriptor
      19: aload_1
      20: aload_2
      21: invokestatic  #13                 // Method org/apache/hadoop/hbase/shaded/protobuf/generated/MasterProtos$UnassignsResponse.getDefaultInstance:()Lorg/apache/hadoop/hbase/shaded/protobuf/generated/MasterProtos$UnassignsResponse;
      24: invokeinterface #9,  5            // InterfaceMethod org/apache/hbase/thirdparty/com/google/protobuf/BlockingRpcChannel.callBlockingMethod:(Lorg/apache/hbase/thirdparty/com/google/protobuf/Descriptors$MethodDescriptor;Lorg/apache/hbase/thirdparty/com/google/protobuf/RpcController;Lorg/apache/hbase/thirdparty/com/google/protobuf/Message;Lorg/apache/hbase/thirdparty/com/google/protobuf/Message;)Lorg/apache/hbase/thirdparty/com/google/protobuf/Message;
      29: checkcast     #14                 // class org/apache/hadoop/hbase/shaded/protobuf/generated/MasterProtos$UnassignsResponse
      32: areturn

  public org.apache.hadoop.hbase.shaded.protobuf.generated.MasterProtos$BypassProcedureResponse bypassProcedure(org.apache.hbase.thirdparty.com.google.protobuf.RpcController, org.apache.hadoop.hbase.shaded.protobuf.generated.MasterProtos$BypassProcedureRequest) throws org.apache.hbase.thirdparty.com.google.protobuf.ServiceException;
    Code:
       0: aload_0
       1: getfield      #3                  // Field channel:Lorg/apache/hbase/thirdparty/com/google/protobuf/BlockingRpcChannel;
       4: invokestatic  #4                  // Method org/apache/hadoop/hbase/shaded/protobuf/generated/MasterProtos$HbckService.getDescriptor:()Lorg/apache/hbase/thirdparty/com/google/protobuf/Descriptors$ServiceDescriptor;
       7: invokevirtual #5                  // Method org/apache/hbase/thirdparty/com/google/protobuf/Descriptors$ServiceDescriptor.getMethods:()Ljava/util/List;
      10: iconst_3
      11: invokeinterface #6,  2            // InterfaceMethod java/util/List.get:(I)Ljava/lang/Object;
      16: checkcast     #7                  // class org/apache/hbase/thirdparty/com/google/protobuf/Descriptors$MethodDescriptor
      19: aload_1
      20: aload_2
      21: invokestatic  #15                 // Method org/apache/hadoop/hbase/shaded/protobuf/generated/MasterProtos$BypassProcedureResponse.getDefaultInstance:()Lorg/apache/hadoop/hbase/shaded/protobuf/generated/MasterProtos$BypassProcedureResponse;
      24: invokeinterface #9,  5            // InterfaceMethod org/apache/hbase/thirdparty/com/google/protobuf/BlockingRpcChannel.callBlockingMethod:(Lorg/apache/hbase/thirdparty/com/google/protobuf/Descriptors$MethodDescriptor;Lorg/apache/hbase/thirdparty/com/google/protobuf/RpcController;Lorg/apache/hbase/thirdparty/com/google/protobuf/Message;Lorg/apache/hbase/thirdparty/com/google/protobuf/Message;)Lorg/apache/hbase/thirdparty/com/google/protobuf/Message;
      29: checkcast     #16                 // class org/apache/hadoop/hbase/shaded/protobuf/generated/MasterProtos$BypassProcedureResponse
      32: areturn

  public org.apache.hadoop.hbase.shaded.protobuf.generated.MasterProtos$ScheduleServerCrashProcedureResponse scheduleServerCrashProcedure(org.apache.hbase.thirdparty.com.google.protobuf.RpcController, org.apache.hadoop.hbase.shaded.protobuf.generated.MasterProtos$ScheduleServerCrashProcedureRequest) throws org.apache.hbase.thirdparty.com.google.protobuf.ServiceException;
    Code:
       0: aload_0
       1: getfield      #3                  // Field channel:Lorg/apache/hbase/thirdparty/com/google/protobuf/BlockingRpcChannel;
       4: invokestatic  #4                  // Method org/apache/hadoop/hbase/shaded/protobuf/generated/MasterProtos$HbckService.getDescriptor:()Lorg/apache/hbase/thirdparty/com/google/protobuf/Descriptors$ServiceDescriptor;
       7: invokevirtual #5                  // Method org/apache/hbase/thirdparty/com/google/protobuf/Descriptors$ServiceDescriptor.getMethods:()Ljava/util/List;
      10: iconst_4
      11: invokeinterface #6,  2            // InterfaceMethod java/util/List.get:(I)Ljava/lang/Object;
      16: checkcast     #7                  // class org/apache/hbase/thirdparty/com/google/protobuf/Descriptors$MethodDescriptor
      19: aload_1
      20: aload_2
      21: invokestatic  #17                 // Method org/apache/hadoop/hbase/shaded/protobuf/generated/MasterProtos$ScheduleServerCrashProcedureResponse.getDefaultInstance:()Lorg/apache/hadoop/hbase/shaded/protobuf/generated/MasterProtos$ScheduleServerCrashProcedureResponse;
      24: invokeinterface #9,  5            // InterfaceMethod org/apache/hbase/thirdparty/com/google/protobuf/BlockingRpcChannel.callBlockingMethod:(Lorg/apache/hbase/thirdparty/com/google/protobuf/Descriptors$MethodDescriptor;Lorg/apache/hbase/thirdparty/com/google/protobuf/RpcController;Lorg/apache/hbase/thirdparty/com/google/protobuf/Message;Lorg/apache/hbase/thirdparty/com/google/protobuf/Message;)Lorg/apache/hbase/thirdparty/com/google/protobuf/Message;
      29: checkcast     #18                 // class org/apache/hadoop/hbase/shaded/protobuf/generated/MasterProtos$ScheduleServerCrashProcedureResponse
      32: areturn

  public org.apache.hadoop.hbase.shaded.protobuf.generated.MasterProtos$GetFailedSplitMergeLegacyRegionsResponse getFailedSplitMergeLegacyRegions(org.apache.hbase.thirdparty.com.google.protobuf.RpcController, org.apache.hadoop.hbase.shaded.protobuf.generated.MasterProtos$GetFailedSplitMergeLegacyRegionsRequest) throws org.apache.hbase.thirdparty.com.google.protobuf.ServiceException;
    Code:
       0: aload_0
       1: getfield      #3                  // Field channel:Lorg/apache/hbase/thirdparty/com/google/protobuf/BlockingRpcChannel;
       4: invokestatic  #4                  // Method org/apache/hadoop/hbase/shaded/protobuf/generated/MasterProtos$HbckService.getDescriptor:()Lorg/apache/hbase/thirdparty/com/google/protobuf/Descriptors$ServiceDescriptor;
       7: invokevirtual #5                  // Method org/apache/hbase/thirdparty/com/google/protobuf/Descriptors$ServiceDescriptor.getMethods:()Ljava/util/List;
      10: iconst_5
      11: invokeinterface #6,  2            // InterfaceMethod java/util/List.get:(I)Ljava/lang/Object;
      16: checkcast     #7                  // class org/apache/hbase/thirdparty/com/google/protobuf/Descriptors$MethodDescriptor
      19: aload_1
      20: aload_2
      21: invokestatic  #19                 // Method org/apache/hadoop/hbase/shaded/protobuf/generated/MasterProtos$GetFailedSplitMergeLegacyRegionsResponse.getDefaultInstance:()Lorg/apache/hadoop/hbase/shaded/protobuf/generated/MasterProtos$GetFailedSplitMergeLegacyRegionsResponse;
      24: invokeinterface #9,  5            // InterfaceMethod org/apache/hbase/thirdparty/com/google/protobuf/BlockingRpcChannel.callBlockingMethod:(Lorg/apache/hbase/thirdparty/com/google/protobuf/Descriptors$MethodDescriptor;Lorg/apache/hbase/thirdparty/com/google/protobuf/RpcController;Lorg/apache/hbase/thirdparty/com/google/protobuf/Message;Lorg/apache/hbase/thirdparty/com/google/protobuf/Message;)Lorg/apache/hbase/thirdparty/com/google/protobuf/Message;
      29: checkcast     #20                 // class org/apache/hadoop/hbase/shaded/protobuf/generated/MasterProtos$GetFailedSplitMergeLegacyRegionsResponse
      32: areturn

  org.apache.hadoop.hbase.shaded.protobuf.generated.MasterProtos$HbckService$BlockingStub(org.apache.hbase.thirdparty.com.google.protobuf.BlockingRpcChannel, org.apache.hadoop.hbase.shaded.protobuf.generated.MasterProtos$1);
    Code:
       0: aload_0
       1: aload_1
       2: invokespecial #1                  // Method "<init>":(Lorg/apache/hbase/thirdparty/com/google/protobuf/BlockingRpcChannel;)V
       5: return
}
