Compiled from "MasterProcedureUtil.java"
public abstract class org.apache.hadoop.hbase.master.procedure.MasterProcedureUtil$NonceProcedureRunnable {
  static final boolean $assertionsDisabled;

  public org.apache.hadoop.hbase.master.procedure.MasterProcedureUtil$NonceProcedureRunnable(org.apache.hadoop.hbase.master.MasterServices, long, long);
    Code:
       0: aload_0
       1: invokespecial #1                  // Method java/lang/Object."<init>":()V
       4: aload_0
       5: aload_1
       6: putfield      #2                  // Field master:Lorg/apache/hadoop/hbase/master/MasterServices;
       9: aload_0
      10: aload_0
      11: invokevirtual #3                  // Method getProcedureExecutor:()Lorg/apache/hadoop/hbase/procedure2/ProcedureExecutor;
      14: lload_2
      15: lload         4
      17: invokevirtual #4                  // Method org/apache/hadoop/hbase/procedure2/ProcedureExecutor.createNonceKey:(JJ)Lorg/apache/hadoop/hbase/util/NonceKey;
      20: putfield      #5                  // Field nonceKey:Lorg/apache/hadoop/hbase/util/NonceKey;
      23: return

  protected org.apache.hadoop.hbase.util.NonceKey getNonceKey();
    Code:
       0: aload_0
       1: getfield      #5                  // Field nonceKey:Lorg/apache/hadoop/hbase/util/NonceKey;
       4: areturn

  protected org.apache.hadoop.hbase.master.MasterServices getMaster();
    Code:
       0: aload_0
       1: getfield      #2                  // Field master:Lorg/apache/hadoop/hbase/master/MasterServices;
       4: areturn

  protected org.apache.hadoop.hbase.procedure2.ProcedureExecutor<org.apache.hadoop.hbase.master.procedure.MasterProcedureEnv> getProcedureExecutor();
    Code:
       0: aload_0
       1: getfield      #2                  // Field master:Lorg/apache/hadoop/hbase/master/MasterServices;
       4: invokeinterface #6,  1            // InterfaceMethod org/apache/hadoop/hbase/master/MasterServices.getMasterProcedureExecutor:()Lorg/apache/hadoop/hbase/procedure2/ProcedureExecutor;
       9: areturn

  protected long getProcId();
    Code:
       0: aload_0
       1: getfield      #7                  // Field procId:Ljava/lang/Long;
       4: ifnull        17
       7: aload_0
       8: getfield      #7                  // Field procId:Ljava/lang/Long;
      11: invokevirtual #8                  // Method java/lang/Long.longValue:()J
      14: goto          20
      17: ldc2_w        #9                  // long -1l
      20: lreturn

  protected long setProcId(long);
    Code:
       0: aload_0
       1: lload_1
       2: invokestatic  #11                 // Method java/lang/Long.valueOf:(J)Ljava/lang/Long;
       5: putfield      #7                  // Field procId:Ljava/lang/Long;
       8: lload_1
       9: lreturn

  protected abstract void run() throws java.io.IOException;

  protected abstract java.lang.String getDescription();

  protected long submitProcedure(org.apache.hadoop.hbase.procedure2.Procedure<org.apache.hadoop.hbase.master.procedure.MasterProcedureEnv>);
    Code:
       0: getstatic     #12                 // Field $assertionsDisabled:Z
       3: ifne          43
       6: aload_0
       7: getfield      #7                  // Field procId:Ljava/lang/Long;
      10: ifnull        43
      13: new           #13                 // class java/lang/AssertionError
      16: dup
      17: new           #14                 // class java/lang/StringBuilder
      20: dup
      21: invokespecial #15                 // Method java/lang/StringBuilder."<init>":()V
      24: ldc           #16                 // String submitProcedure() was already called, running procId=
      26: invokevirtual #17                 // Method java/lang/StringBuilder.append:(Ljava/lang/String;)Ljava/lang/StringBuilder;
      29: aload_0
      30: getfield      #7                  // Field procId:Ljava/lang/Long;
      33: invokevirtual #18                 // Method java/lang/StringBuilder.append:(Ljava/lang/Object;)Ljava/lang/StringBuilder;
      36: invokevirtual #19                 // Method java/lang/StringBuilder.toString:()Ljava/lang/String;
      39: invokespecial #20                 // Method java/lang/AssertionError."<init>":(Ljava/lang/Object;)V
      42: athrow
      43: aload_0
      44: aload_0
      45: invokevirtual #3                  // Method getProcedureExecutor:()Lorg/apache/hadoop/hbase/procedure2/ProcedureExecutor;
      48: aload_1
      49: aload_0
      50: getfield      #5                  // Field nonceKey:Lorg/apache/hadoop/hbase/util/NonceKey;
      53: invokevirtual #21                 // Method org/apache/hadoop/hbase/procedure2/ProcedureExecutor.submitProcedure:(Lorg/apache/hadoop/hbase/procedure2/Procedure;Lorg/apache/hadoop/hbase/util/NonceKey;)J
      56: invokestatic  #11                 // Method java/lang/Long.valueOf:(J)Ljava/lang/Long;
      59: putfield      #7                  // Field procId:Ljava/lang/Long;
      62: aload_0
      63: getfield      #7                  // Field procId:Ljava/lang/Long;
      66: invokevirtual #8                  // Method java/lang/Long.longValue:()J
      69: lreturn

  static {};
    Code:
       0: ldc           #22                 // class org/apache/hadoop/hbase/master/procedure/MasterProcedureUtil
       2: invokevirtual #23                 // Method java/lang/Class.desiredAssertionStatus:()Z
       5: ifne          12
       8: iconst_1
       9: goto          13
      12: iconst_0
      13: putstatic     #12                 // Field $assertionsDisabled:Z
      16: return
}
