Compiled from "MasterSnapshotVerifier.java"
public final class org.apache.hadoop.hbase.master.snapshot.MasterSnapshotVerifier {
  public org.apache.hadoop.hbase.master.snapshot.MasterSnapshotVerifier(org.apache.hadoop.hbase.master.MasterServices, org.apache.hadoop.hbase.shaded.protobuf.generated.SnapshotProtos$SnapshotDescription, org.apache.hadoop.fs.FileSystem);
    Code:
       0: aload_0
       1: invokespecial #1                  // Method java/lang/Object."<init>":()V
       4: aload_0
       5: aload_3
       6: putfield      #2                  // Field workingDirFs:Lorg/apache/hadoop/fs/FileSystem;
       9: aload_0
      10: aload_1
      11: putfield      #3                  // Field services:Lorg/apache/hadoop/hbase/master/MasterServices;
      14: aload_0
      15: aload_2
      16: putfield      #4                  // Field snapshot:Lorg/apache/hadoop/hbase/shaded/protobuf/generated/SnapshotProtos$SnapshotDescription;
      19: aload_0
      20: aload_2
      21: invokevirtual #5                  // Method org/apache/hadoop/hbase/shaded/protobuf/generated/SnapshotProtos$SnapshotDescription.getTable:()Ljava/lang/String;
      24: invokestatic  #6                  // Method org/apache/hadoop/hbase/TableName.valueOf:(Ljava/lang/String;)Lorg/apache/hadoop/hbase/TableName;
      27: putfield      #7                  // Field tableName:Lorg/apache/hadoop/hbase/TableName;
      30: return

  public void verifySnapshot(org.apache.hadoop.fs.Path, java.util.Set<java.lang.String>) throws org.apache.hadoop.hbase.snapshot.CorruptedSnapshotException, java.io.IOException;
    Code:
       0: aload_0
       1: getfield      #3                  // Field services:Lorg/apache/hadoop/hbase/master/MasterServices;
       4: invokeinterface #8,  1            // InterfaceMethod org/apache/hadoop/hbase/master/MasterServices.getConfiguration:()Lorg/apache/hadoop/conf/Configuration;
       9: aload_0
      10: getfield      #2                  // Field workingDirFs:Lorg/apache/hadoop/fs/FileSystem;
      13: aload_1
      14: aload_0
      15: getfield      #4                  // Field snapshot:Lorg/apache/hadoop/hbase/shaded/protobuf/generated/SnapshotProtos$SnapshotDescription;
      18: invokestatic  #9                  // Method org/apache/hadoop/hbase/snapshot/SnapshotManifest.open:(Lorg/apache/hadoop/conf/Configuration;Lorg/apache/hadoop/fs/FileSystem;Lorg/apache/hadoop/fs/Path;Lorg/apache/hadoop/hbase/shaded/protobuf/generated/SnapshotProtos$SnapshotDescription;)Lorg/apache/hadoop/hbase/snapshot/SnapshotManifest;
      21: astore_3
      22: aload_0
      23: aload_1
      24: invokespecial #10                 // Method verifySnapshotDescription:(Lorg/apache/hadoop/fs/Path;)V
      27: aload_0
      28: aload_3
      29: invokespecial #11                 // Method verifyTableInfo:(Lorg/apache/hadoop/hbase/snapshot/SnapshotManifest;)V
      32: aload_0
      33: aload_3
      34: invokespecial #12                 // Method verifyRegions:(Lorg/apache/hadoop/hbase/snapshot/SnapshotManifest;)V
      37: return

  static {};
    Code:
       0: ldc           #74                 // class org/apache/hadoop/hbase/master/snapshot/MasterSnapshotVerifier
       2: invokestatic  #75                 // Method org/slf4j/LoggerFactory.getLogger:(Ljava/lang/Class;)Lorg/slf4j/Logger;
       5: putstatic     #44                 // Field LOG:Lorg/slf4j/Logger;
       8: return
}
