Compiled from "MasterProtos.java"
final class org.apache.hadoop.hbase.shaded.protobuf.generated.MasterProtos$GetFailedSplitMergeLegacyRegionsResponse$ErrorsDefaultEntryHolder {
  static final org.apache.hbase.thirdparty.com.google.protobuf.MapEntry<java.lang.String, java.lang.Integer> defaultEntry;

  static {};
    Code:
       0: invokestatic  #2                  // Method org/apache/hadoop/hbase/shaded/protobuf/generated/MasterProtos.access$149000:()Lorg/apache/hbase/thirdparty/com/google/protobuf/Descriptors$Descriptor;
       3: getstatic     #3                  // Field org/apache/hbase/thirdparty/com/google/protobuf/WireFormat$FieldType.STRING:Lorg/apache/hbase/thirdparty/com/google/protobuf/WireFormat$FieldType;
       6: ldc           #4                  // String
       8: getstatic     #5                  // Field org/apache/hbase/thirdparty/com/google/protobuf/WireFormat$FieldType.ENUM:Lorg/apache/hbase/thirdparty/com/google/protobuf/WireFormat$FieldType;
      11: getstatic     #6                  // Field org/apache/hadoop/hbase/shaded/protobuf/generated/MasterProtos$RegionErrorType.DAUGHTER_MERGED_REGION_NOT_ONLINE:Lorg/apache/hadoop/hbase/shaded/protobuf/generated/MasterProtos$RegionErrorType;
      14: invokevirtual #7                  // Method org/apache/hadoop/hbase/shaded/protobuf/generated/MasterProtos$RegionErrorType.getNumber:()I
      17: invokestatic  #8                  // Method java/lang/Integer.valueOf:(I)Ljava/lang/Integer;
      20: invokestatic  #9                  // Method org/apache/hbase/thirdparty/com/google/protobuf/MapEntry.newDefaultInstance:(Lorg/apache/hbase/thirdparty/com/google/protobuf/Descriptors$Descriptor;Lorg/apache/hbase/thirdparty/com/google/protobuf/WireFormat$FieldType;Ljava/lang/Object;Lorg/apache/hbase/thirdparty/com/google/protobuf/WireFormat$FieldType;Ljava/lang/Object;)Lorg/apache/hbase/thirdparty/com/google/protobuf/MapEntry;
      23: putstatic     #10                 // Field defaultEntry:Lorg/apache/hbase/thirdparty/com/google/protobuf/MapEntry;
      26: return
}
