Compiled from "MemStoreMergerSegmentsIterator.java"
public class org.apache.hadoop.hbase.regionserver.MemStoreMergerSegmentsIterator extends org.apache.hadoop.hbase.regionserver.MemStoreSegmentsIterator {
  java.util.List<org.apache.hadoop.hbase.regionserver.KeyValueScanner> scanners;

  public org.apache.hadoop.hbase.regionserver.MemStoreMergerSegmentsIterator(java.util.List<org.apache.hadoop.hbase.regionserver.ImmutableSegment>, org.apache.hadoop.hbase.CellComparator, int) throws java.io.IOException;
    Code:
       0: aload_0
       1: iload_3
       2: invokespecial #1                  // Method org/apache/hadoop/hbase/regionserver/MemStoreSegmentsIterator."<init>":(I)V
       5: aload_0
       6: aconst_null
       7: putfield      #2                  // Field heap:Lorg/apache/hadoop/hbase/regionserver/KeyValueHeap;
      10: aload_0
      11: new           #3                  // class java/util/ArrayList
      14: dup
      15: invokespecial #4                  // Method java/util/ArrayList."<init>":()V
      18: putfield      #5                  // Field scanners:Ljava/util/List;
      21: aload_0
      22: iconst_0
      23: putfield      #6                  // Field closed:Z
      26: aload_1
      27: ldc2_w        #8                  // long 9223372036854775807l
      30: aload_0
      31: getfield      #5                  // Field scanners:Ljava/util/List;
      34: invokestatic  #10                 // Method org/apache/hadoop/hbase/regionserver/AbstractMemStore.addToScanners:(Ljava/util/List;JLjava/util/List;)V
      37: aload_0
      38: new           #11                 // class org/apache/hadoop/hbase/regionserver/KeyValueHeap
      41: dup
      42: aload_0
      43: getfield      #5                  // Field scanners:Ljava/util/List;
      46: aload_2
      47: invokespecial #12                 // Method org/apache/hadoop/hbase/regionserver/KeyValueHeap."<init>":(Ljava/util/List;Lorg/apache/hadoop/hbase/CellComparator;)V
      50: putfield      #2                  // Field heap:Lorg/apache/hadoop/hbase/regionserver/KeyValueHeap;
      53: return

  public boolean hasNext();
    Code:
       0: aload_0
       1: getfield      #6                  // Field closed:Z
       4: ifeq          9
       7: iconst_0
       8: ireturn
       9: aload_0
      10: getfield      #2                  // Field heap:Lorg/apache/hadoop/hbase/regionserver/KeyValueHeap;
      13: ifnull        32
      16: aload_0
      17: getfield      #2                  // Field heap:Lorg/apache/hadoop/hbase/regionserver/KeyValueHeap;
      20: invokevirtual #13                 // Method org/apache/hadoop/hbase/regionserver/KeyValueHeap.peek:()Lorg/apache/hadoop/hbase/Cell;
      23: ifnull        30
      26: iconst_1
      27: goto          31
      30: iconst_0
      31: ireturn
      32: iconst_0
      33: ireturn

  public org.apache.hadoop.hbase.Cell next();
    Code:
       0: aload_0
       1: getfield      #6                  // Field closed:Z
       4: ifne          22
       7: aload_0
       8: getfield      #2                  // Field heap:Lorg/apache/hadoop/hbase/regionserver/KeyValueHeap;
      11: ifnull        22
      14: aload_0
      15: getfield      #2                  // Field heap:Lorg/apache/hadoop/hbase/regionserver/KeyValueHeap;
      18: invokevirtual #14                 // Method org/apache/hadoop/hbase/regionserver/KeyValueHeap.next:()Lorg/apache/hadoop/hbase/Cell;
      21: areturn
      22: goto          35
      25: astore_1
      26: new           #16                 // class java/lang/IllegalStateException
      29: dup
      30: aload_1
      31: invokespecial #17                 // Method java/lang/IllegalStateException."<init>":(Ljava/lang/Throwable;)V
      34: athrow
      35: aconst_null
      36: areturn
    Exception table:
       from    to  target type
           0    21    25   Class java/io/IOException

  public void close();
    Code:
       0: aload_0
       1: getfield      #6                  // Field closed:Z
       4: ifeq          8
       7: return
       8: aload_0
       9: getfield      #2                  // Field heap:Lorg/apache/hadoop/hbase/regionserver/KeyValueHeap;
      12: ifnull        30
      15: aload_0
      16: getfield      #2                  // Field heap:Lorg/apache/hadoop/hbase/regionserver/KeyValueHeap;
      19: invokevirtual #18                 // Method org/apache/hadoop/hbase/regionserver/KeyValueHeap.close:()V
      22: aload_0
      23: aconst_null
      24: putfield      #2                  // Field heap:Lorg/apache/hadoop/hbase/regionserver/KeyValueHeap;
      27: goto          68
      30: aload_0
      31: getfield      #5                  // Field scanners:Ljava/util/List;
      34: invokeinterface #19,  1           // InterfaceMethod java/util/List.iterator:()Ljava/util/Iterator;
      39: astore_1
      40: aload_1
      41: invokeinterface #20,  1           // InterfaceMethod java/util/Iterator.hasNext:()Z
      46: ifeq          68
      49: aload_1
      50: invokeinterface #21,  1           // InterfaceMethod java/util/Iterator.next:()Ljava/lang/Object;
      55: checkcast     #22                 // class org/apache/hadoop/hbase/regionserver/KeyValueScanner
      58: astore_2
      59: aload_2
      60: invokeinterface #23,  1           // InterfaceMethod org/apache/hadoop/hbase/regionserver/KeyValueScanner.close:()V
      65: goto          40
      68: aload_0
      69: iconst_1
      70: putfield      #6                  // Field closed:Z
      73: return

  public void remove();
    Code:
       0: new           #24                 // class java/lang/UnsupportedOperationException
       3: dup
       4: invokespecial #25                 // Method java/lang/UnsupportedOperationException."<init>":()V
       7: athrow

  public java.lang.Object next();
    Code:
       0: aload_0
       1: invokevirtual #26                 // Method next:()Lorg/apache/hadoop/hbase/Cell;
       4: areturn
}
