Compiled from "MemStoreCompactor.java"
public class org.apache.hadoop.hbase.regionserver.MemStoreCompactor {
  public static final long DEEP_OVERHEAD;

  static final boolean $assertionsDisabled;

  public org.apache.hadoop.hbase.regionserver.MemStoreCompactor(org.apache.hadoop.hbase.regionserver.CompactingMemStore, org.apache.hadoop.hbase.MemoryCompactionPolicy) throws org.apache.hadoop.hbase.exceptions.IllegalArgumentIOException;
    Code:
       0: aload_0
       1: invokespecial #1                  // Method java/lang/Object."<init>":()V
       4: aload_0
       5: new           #2                  // class java/util/concurrent/atomic/AtomicBoolean
       8: dup
       9: iconst_0
      10: invokespecial #3                  // Method java/util/concurrent/atomic/AtomicBoolean."<init>":(Z)V
      13: putfield      #4                  // Field isInterrupted:Ljava/util/concurrent/atomic/AtomicBoolean;
      16: aload_0
      17: aload_1
      18: putfield      #5                  // Field compactingMemStore:Lorg/apache/hadoop/hbase/regionserver/CompactingMemStore;
      21: aload_0
      22: aload_1
      23: invokevirtual #6                  // Method org/apache/hadoop/hbase/regionserver/CompactingMemStore.getConfiguration:()Lorg/apache/hadoop/conf/Configuration;
      26: ldc           #8                  // String hbase.hstore.compaction.kv.max
      28: bipush        10
      30: invokevirtual #9                  // Method org/apache/hadoop/conf/Configuration.getInt:(Ljava/lang/String;I)I
      33: putfield      #10                 // Field compactionKVMax:I
      36: aload_0
      37: aload_2
      38: aload_1
      39: invokevirtual #6                  // Method org/apache/hadoop/hbase/regionserver/CompactingMemStore.getConfiguration:()Lorg/apache/hadoop/conf/Configuration;
      42: aload_1
      43: invokevirtual #11                 // Method org/apache/hadoop/hbase/regionserver/CompactingMemStore.getFamilyName:()Ljava/lang/String;
      46: invokevirtual #12                 // Method initiateCompactionStrategy:(Lorg/apache/hadoop/hbase/MemoryCompactionPolicy;Lorg/apache/hadoop/conf/Configuration;Ljava/lang/String;)V
      49: return

  public java.lang.String toString();
    Code:
       0: new           #13                 // class java/lang/StringBuilder
       3: dup
       4: invokespecial #14                 // Method java/lang/StringBuilder."<init>":()V
       7: aload_0
       8: getfield      #15                 // Field strategy:Lorg/apache/hadoop/hbase/regionserver/MemStoreCompactionStrategy;
      11: invokevirtual #16                 // Method java/lang/StringBuilder.append:(Ljava/lang/Object;)Ljava/lang/StringBuilder;
      14: ldc           #17                 // String , compactionCellMax=
      16: invokevirtual #18                 // Method java/lang/StringBuilder.append:(Ljava/lang/String;)Ljava/lang/StringBuilder;
      19: aload_0
      20: getfield      #10                 // Field compactionKVMax:I
      23: invokevirtual #19                 // Method java/lang/StringBuilder.append:(I)Ljava/lang/StringBuilder;
      26: invokevirtual #20                 // Method java/lang/StringBuilder.toString:()Ljava/lang/String;
      29: areturn

  public boolean start() throws java.io.IOException;
    Code:
       0: aload_0
       1: getfield      #5                  // Field compactingMemStore:Lorg/apache/hadoop/hbase/regionserver/CompactingMemStore;
       4: invokevirtual #21                 // Method org/apache/hadoop/hbase/regionserver/CompactingMemStore.hasImmutableSegments:()Z
       7: ifne          12
      10: iconst_0
      11: ireturn
      12: aload_0
      13: aload_0
      14: getfield      #5                  // Field compactingMemStore:Lorg/apache/hadoop/hbase/regionserver/CompactingMemStore;
      17: invokevirtual #22                 // Method org/apache/hadoop/hbase/regionserver/CompactingMemStore.getImmutableSegments:()Lorg/apache/hadoop/hbase/regionserver/VersionedSegmentsList;
      20: putfield      #23                 // Field versionedList:Lorg/apache/hadoop/hbase/regionserver/VersionedSegmentsList;
      23: getstatic     #24                 // Field LOG:Lorg/slf4j/Logger;
      26: ldc           #25                 // String Speculative compaction starting on {}/{}
      28: aload_0
      29: getfield      #5                  // Field compactingMemStore:Lorg/apache/hadoop/hbase/regionserver/CompactingMemStore;
      32: invokevirtual #26                 // Method org/apache/hadoop/hbase/regionserver/CompactingMemStore.getStore:()Lorg/apache/hadoop/hbase/regionserver/HStore;
      35: invokevirtual #27                 // Method org/apache/hadoop/hbase/regionserver/HStore.getHRegion:()Lorg/apache/hadoop/hbase/regionserver/HRegion;
      38: invokevirtual #28                 // Method org/apache/hadoop/hbase/regionserver/HRegion.getRegionInfo:()Lorg/apache/hadoop/hbase/client/RegionInfo;
      41: invokeinterface #29,  1           // InterfaceMethod org/apache/hadoop/hbase/client/RegionInfo.getEncodedName:()Ljava/lang/String;
      46: aload_0
      47: getfield      #5                  // Field compactingMemStore:Lorg/apache/hadoop/hbase/regionserver/CompactingMemStore;
      50: invokevirtual #26                 // Method org/apache/hadoop/hbase/regionserver/CompactingMemStore.getStore:()Lorg/apache/hadoop/hbase/regionserver/HStore;
      53: invokevirtual #30                 // Method org/apache/hadoop/hbase/regionserver/HStore.getColumnFamilyName:()Ljava/lang/String;
      56: invokeinterface #31,  4           // InterfaceMethod org/slf4j/Logger.trace:(Ljava/lang/String;Ljava/lang/Object;Ljava/lang/Object;)V
      61: aload_0
      62: getfield      #5                  // Field compactingMemStore:Lorg/apache/hadoop/hbase/regionserver/CompactingMemStore;
      65: invokevirtual #26                 // Method org/apache/hadoop/hbase/regionserver/CompactingMemStore.getStore:()Lorg/apache/hadoop/hbase/regionserver/HStore;
      68: astore_1
      69: aload_1
      70: invokevirtual #32                 // Method org/apache/hadoop/hbase/regionserver/HStore.getCoprocessorHost:()Lorg/apache/hadoop/hbase/regionserver/RegionCoprocessorHost;
      73: astore_2
      74: aload_2
      75: ifnull        83
      78: aload_2
      79: aload_1
      80: invokevirtual #33                 // Method org/apache/hadoop/hbase/regionserver/RegionCoprocessorHost.preMemStoreCompaction:(Lorg/apache/hadoop/hbase/regionserver/HStore;)V
      83: aload_0
      84: invokespecial #34                 // Method doCompaction:()V
      87: aload_2
      88: ifnull        111
      91: aload_2
      92: aload_1
      93: invokevirtual #35                 // Method org/apache/hadoop/hbase/regionserver/RegionCoprocessorHost.postMemStoreCompaction:(Lorg/apache/hadoop/hbase/regionserver/HStore;)V
      96: goto          111
      99: astore_3
     100: aload_2
     101: ifnull        109
     104: aload_2
     105: aload_1
     106: invokevirtual #35                 // Method org/apache/hadoop/hbase/regionserver/RegionCoprocessorHost.postMemStoreCompaction:(Lorg/apache/hadoop/hbase/regionserver/HStore;)V
     109: aload_3
     110: athrow
     111: iconst_1
     112: ireturn
    Exception table:
       from    to  target type
          83    87    99   any

  public void stop();
    Code:
       0: aload_0
       1: getfield      #4                  // Field isInterrupted:Ljava/util/concurrent/atomic/AtomicBoolean;
       4: iconst_0
       5: iconst_1
       6: invokevirtual #36                 // Method java/util/concurrent/atomic/AtomicBoolean.compareAndSet:(ZZ)Z
       9: pop
      10: return

  public void resetStats();
    Code:
       0: aload_0
       1: getfield      #15                 // Field strategy:Lorg/apache/hadoop/hbase/regionserver/MemStoreCompactionStrategy;
       4: invokevirtual #37                 // Method org/apache/hadoop/hbase/regionserver/MemStoreCompactionStrategy.resetStats:()V
       7: return

  void initiateCompactionStrategy(org.apache.hadoop.hbase.MemoryCompactionPolicy, org.apache.hadoop.conf.Configuration, java.lang.String) throws org.apache.hadoop.hbase.exceptions.IllegalArgumentIOException;
    Code:
       0: getstatic     #82                 // Field $assertionsDisabled:Z
       3: ifne          21
       6: aload_1
       7: getstatic     #83                 // Field org/apache/hadoop/hbase/MemoryCompactionPolicy.NONE:Lorg/apache/hadoop/hbase/MemoryCompactionPolicy;
      10: if_acmpne     21
      13: new           #84                 // class java/lang/AssertionError
      16: dup
      17: invokespecial #85                 // Method java/lang/AssertionError."<init>":()V
      20: athrow
      21: getstatic     #86                 // Field org/apache/hadoop/hbase/regionserver/MemStoreCompactor$1.$SwitchMap$org$apache$hadoop$hbase$MemoryCompactionPolicy:[I
      24: aload_1
      25: invokevirtual #87                 // Method org/apache/hadoop/hbase/MemoryCompactionPolicy.ordinal:()I
      28: iaload
      29: tableswitch   { // 1 to 3
                     1: 56
                     2: 72
                     3: 88
               default: 104
          }
      56: aload_0
      57: new           #88                 // class org/apache/hadoop/hbase/regionserver/BasicMemStoreCompactionStrategy
      60: dup
      61: aload_2
      62: aload_3
      63: invokespecial #89                 // Method org/apache/hadoop/hbase/regionserver/BasicMemStoreCompactionStrategy."<init>":(Lorg/apache/hadoop/conf/Configuration;Ljava/lang/String;)V
      66: putfield      #15                 // Field strategy:Lorg/apache/hadoop/hbase/regionserver/MemStoreCompactionStrategy;
      69: goto          131
      72: aload_0
      73: new           #90                 // class org/apache/hadoop/hbase/regionserver/EagerMemStoreCompactionStrategy
      76: dup
      77: aload_2
      78: aload_3
      79: invokespecial #91                 // Method org/apache/hadoop/hbase/regionserver/EagerMemStoreCompactionStrategy."<init>":(Lorg/apache/hadoop/conf/Configuration;Ljava/lang/String;)V
      82: putfield      #15                 // Field strategy:Lorg/apache/hadoop/hbase/regionserver/MemStoreCompactionStrategy;
      85: goto          131
      88: aload_0
      89: new           #92                 // class org/apache/hadoop/hbase/regionserver/AdaptiveMemStoreCompactionStrategy
      92: dup
      93: aload_2
      94: aload_3
      95: invokespecial #93                 // Method org/apache/hadoop/hbase/regionserver/AdaptiveMemStoreCompactionStrategy."<init>":(Lorg/apache/hadoop/conf/Configuration;Ljava/lang/String;)V
      98: putfield      #15                 // Field strategy:Lorg/apache/hadoop/hbase/regionserver/MemStoreCompactionStrategy;
     101: goto          131
     104: new           #94                 // class org/apache/hadoop/hbase/exceptions/IllegalArgumentIOException
     107: dup
     108: new           #13                 // class java/lang/StringBuilder
     111: dup
     112: invokespecial #14                 // Method java/lang/StringBuilder."<init>":()V
     115: ldc           #95                 // String Unknown memory compaction type
     117: invokevirtual #18                 // Method java/lang/StringBuilder.append:(Ljava/lang/String;)Ljava/lang/StringBuilder;
     120: aload_1
     121: invokevirtual #16                 // Method java/lang/StringBuilder.append:(Ljava/lang/Object;)Ljava/lang/StringBuilder;
     124: invokevirtual #20                 // Method java/lang/StringBuilder.toString:()Ljava/lang/String;
     127: invokespecial #96                 // Method org/apache/hadoop/hbase/exceptions/IllegalArgumentIOException."<init>":(Ljava/lang/String;)V
     130: athrow
     131: return

  static {};
    Code:
       0: ldc           #97                 // class org/apache/hadoop/hbase/regionserver/MemStoreCompactor
       2: invokevirtual #98                 // Method java/lang/Class.desiredAssertionStatus:()Z
       5: ifne          12
       8: iconst_1
       9: goto          13
      12: iconst_0
      13: putstatic     #82                 // Field $assertionsDisabled:Z
      16: getstatic     #99                 // Field org/apache/hadoop/hbase/util/ClassSize.OBJECT:I
      19: iconst_4
      20: getstatic     #100                // Field org/apache/hadoop/hbase/util/ClassSize.REFERENCE:I
      23: imul
      24: iadd
      25: iconst_4
      26: iadd
      27: getstatic     #102                // Field org/apache/hadoop/hbase/util/ClassSize.ATOMIC_BOOLEAN:I
      30: iadd
      31: invokestatic  #103                // Method org/apache/hadoop/hbase/util/ClassSize.align:(I)I
      34: i2l
      35: putstatic     #104                // Field DEEP_OVERHEAD:J
      38: ldc           #97                 // class org/apache/hadoop/hbase/regionserver/MemStoreCompactor
      40: invokestatic  #105                // Method org/slf4j/LoggerFactory.getLogger:(Ljava/lang/Class;)Lorg/slf4j/Logger;
      43: putstatic     #24                 // Field LOG:Lorg/slf4j/Logger;
      46: return
}
