Compiled from "MemStoreSizing.java"
public interface org.apache.hadoop.hbase.regionserver.MemStoreSizing {
  public static final org.apache.hadoop.hbase.regionserver.MemStoreSizing DUD;

  public abstract long incMemStoreSize(long, long, long, int);

  public long incMemStoreSize(org.apache.hadoop.hbase.regionserver.MemStoreSize);
    Code:
       0: aload_0
       1: aload_1
       2: invokevirtual #1                  // Method org/apache/hadoop/hbase/regionserver/MemStoreSize.getDataSize:()J
       5: aload_1
       6: invokevirtual #2                  // Method org/apache/hadoop/hbase/regionserver/MemStoreSize.getHeapSize:()J
       9: aload_1
      10: invokevirtual #3                  // Method org/apache/hadoop/hbase/regionserver/MemStoreSize.getOffHeapSize:()J
      13: aload_1
      14: invokevirtual #4                  // Method org/apache/hadoop/hbase/regionserver/MemStoreSize.getCellsCount:()I
      17: invokeinterface #5,  8            // InterfaceMethod incMemStoreSize:(JJJI)J
      22: lreturn

  public long decMemStoreSize(long, long, long, int);
    Code:
       0: aload_0
       1: lload_1
       2: lneg
       3: lload_3
       4: lneg
       5: lload         5
       7: lneg
       8: iload         7
      10: ineg
      11: invokeinterface #5,  8            // InterfaceMethod incMemStoreSize:(JJJI)J
      16: lreturn

  public long decMemStoreSize(org.apache.hadoop.hbase.regionserver.MemStoreSize);
    Code:
       0: aload_0
       1: aload_1
       2: invokevirtual #1                  // Method org/apache/hadoop/hbase/regionserver/MemStoreSize.getDataSize:()J
       5: lneg
       6: aload_1
       7: invokevirtual #2                  // Method org/apache/hadoop/hbase/regionserver/MemStoreSize.getHeapSize:()J
      10: lneg
      11: aload_1
      12: invokevirtual #3                  // Method org/apache/hadoop/hbase/regionserver/MemStoreSize.getOffHeapSize:()J
      15: lneg
      16: aload_1
      17: invokevirtual #4                  // Method org/apache/hadoop/hbase/regionserver/MemStoreSize.getCellsCount:()I
      20: ineg
      21: invokeinterface #5,  8            // InterfaceMethod incMemStoreSize:(JJJI)J
      26: lreturn

  public abstract boolean compareAndSetDataSize(long, long);

  public abstract long getDataSize();

  public abstract long getHeapSize();

  public abstract long getOffHeapSize();

  public abstract int getCellsCount();

  public abstract org.apache.hadoop.hbase.regionserver.MemStoreSize getMemStoreSize();

  static {};
    Code:
       0: new           #6                  // class org/apache/hadoop/hbase/regionserver/MemStoreSizing$1
       3: dup
       4: invokespecial #7                  // Method org/apache/hadoop/hbase/regionserver/MemStoreSizing$1."<init>":()V
       7: putstatic     #8                  // Field DUD:Lorg/apache/hadoop/hbase/regionserver/MemStoreSizing;
      10: return
}
