Compiled from "MergeNormalizationPlan.java"
public class org.apache.hadoop.hbase.master.normalizer.MergeNormalizationPlan implements org.apache.hadoop.hbase.master.normalizer.NormalizationPlan {
  public org.apache.hadoop.hbase.master.normalizer.MergeNormalizationPlan(org.apache.hadoop.hbase.client.RegionInfo, org.apache.hadoop.hbase.client.RegionInfo);
    Code:
       0: aload_0
       1: invokespecial #1                  // Method java/lang/Object."<init>":()V
       4: aload_0
       5: aload_1
       6: putfield      #2                  // Field firstRegion:Lorg/apache/hadoop/hbase/client/RegionInfo;
       9: aload_0
      10: aload_2
      11: putfield      #3                  // Field secondRegion:Lorg/apache/hadoop/hbase/client/RegionInfo;
      14: return

  public org.apache.hadoop.hbase.master.normalizer.NormalizationPlan$PlanType getType();
    Code:
       0: getstatic     #4                  // Field org/apache/hadoop/hbase/master/normalizer/NormalizationPlan$PlanType.MERGE:Lorg/apache/hadoop/hbase/master/normalizer/NormalizationPlan$PlanType;
       3: areturn

  org.apache.hadoop.hbase.client.RegionInfo getFirstRegion();
    Code:
       0: aload_0
       1: getfield      #2                  // Field firstRegion:Lorg/apache/hadoop/hbase/client/RegionInfo;
       4: areturn

  org.apache.hadoop.hbase.client.RegionInfo getSecondRegion();
    Code:
       0: aload_0
       1: getfield      #3                  // Field secondRegion:Lorg/apache/hadoop/hbase/client/RegionInfo;
       4: areturn

  public java.lang.String toString();
    Code:
       0: new           #5                  // class java/lang/StringBuilder
       3: dup
       4: invokespecial #6                  // Method java/lang/StringBuilder."<init>":()V
       7: ldc           #7                  // String MergeNormalizationPlan{firstRegion=
       9: invokevirtual #8                  // Method java/lang/StringBuilder.append:(Ljava/lang/String;)Ljava/lang/StringBuilder;
      12: aload_0
      13: getfield      #2                  // Field firstRegion:Lorg/apache/hadoop/hbase/client/RegionInfo;
      16: invokevirtual #9                  // Method java/lang/StringBuilder.append:(Ljava/lang/Object;)Ljava/lang/StringBuilder;
      19: ldc           #10                 // String , secondRegion=
      21: invokevirtual #8                  // Method java/lang/StringBuilder.append:(Ljava/lang/String;)Ljava/lang/StringBuilder;
      24: aload_0
      25: getfield      #3                  // Field secondRegion:Lorg/apache/hadoop/hbase/client/RegionInfo;
      28: invokevirtual #9                  // Method java/lang/StringBuilder.append:(Ljava/lang/Object;)Ljava/lang/StringBuilder;
      31: bipush        125
      33: invokevirtual #11                 // Method java/lang/StringBuilder.append:(C)Ljava/lang/StringBuilder;
      36: invokevirtual #12                 // Method java/lang/StringBuilder.toString:()Ljava/lang/String;
      39: areturn

  public void execute(org.apache.hadoop.hbase.client.Admin);
    Code:
       0: getstatic     #13                 // Field LOG:Lorg/slf4j/Logger;
       3: new           #5                  // class java/lang/StringBuilder
       6: dup
       7: invokespecial #6                  // Method java/lang/StringBuilder."<init>":()V
      10: ldc           #14                 // String Executing merging normalization plan:
      12: invokevirtual #8                  // Method java/lang/StringBuilder.append:(Ljava/lang/String;)Ljava/lang/StringBuilder;
      15: aload_0
      16: invokevirtual #9                  // Method java/lang/StringBuilder.append:(Ljava/lang/Object;)Ljava/lang/StringBuilder;
      19: invokevirtual #12                 // Method java/lang/StringBuilder.toString:()Ljava/lang/String;
      22: invokeinterface #15,  2           // InterfaceMethod org/slf4j/Logger.info:(Ljava/lang/String;)V
      27: aload_1
      28: aload_0
      29: getfield      #2                  // Field firstRegion:Lorg/apache/hadoop/hbase/client/RegionInfo;
      32: invokeinterface #16,  1           // InterfaceMethod org/apache/hadoop/hbase/client/RegionInfo.getEncodedNameAsBytes:()[B
      37: aload_0
      38: getfield      #3                  // Field secondRegion:Lorg/apache/hadoop/hbase/client/RegionInfo;
      41: invokeinterface #16,  1           // InterfaceMethod org/apache/hadoop/hbase/client/RegionInfo.getEncodedNameAsBytes:()[B
      46: iconst_1
      47: invokeinterface #17,  4           // InterfaceMethod org/apache/hadoop/hbase/client/Admin.mergeRegionsAsync:([B[BZ)Ljava/util/concurrent/Future;
      52: pop
      53: goto          68
      56: astore_2
      57: getstatic     #13                 // Field LOG:Lorg/slf4j/Logger;
      60: ldc           #19                 // String Error during region merge:
      62: aload_2
      63: invokeinterface #20,  3           // InterfaceMethod org/slf4j/Logger.error:(Ljava/lang/String;Ljava/lang/Throwable;)V
      68: return
    Exception table:
       from    to  target type
          27    53    56   Class java/io/IOException

  static {};
    Code:
       0: ldc           #21                 // class org/apache/hadoop/hbase/master/normalizer/MergeNormalizationPlan
       2: invokevirtual #22                 // Method java/lang/Class.getName:()Ljava/lang/String;
       5: invokestatic  #23                 // Method org/slf4j/LoggerFactory.getLogger:(Ljava/lang/String;)Lorg/slf4j/Logger;
       8: putstatic     #13                 // Field LOG:Lorg/slf4j/Logger;
      11: return
}
