Compiled from "MetaTableAccessor.java"
public abstract class org.apache.hadoop.hbase.MetaTableAccessor$TableVisitorBase extends org.apache.hadoop.hbase.MetaTableAccessor$DefaultVisitorBase {
  public org.apache.hadoop.hbase.MetaTableAccessor$TableVisitorBase(org.apache.hadoop.hbase.TableName);
    Code:
       0: aload_0
       1: invokespecial #1                  // Method org/apache/hadoop/hbase/MetaTableAccessor$DefaultVisitorBase."<init>":()V
       4: aload_0
       5: aload_1
       6: putfield      #2                  // Field tableName:Lorg/apache/hadoop/hbase/TableName;
       9: return

  public final boolean visit(org.apache.hadoop.hbase.client.Result) throws java.io.IOException;
    Code:
       0: aload_1
       1: invokestatic  #3                  // Method org/apache/hadoop/hbase/MetaTableAccessor.getRegionInfo:(Lorg/apache/hadoop/hbase/client/Result;)Lorg/apache/hadoop/hbase/client/RegionInfo;
       4: astore_2
       5: aload_2
       6: ifnonnull     11
       9: iconst_1
      10: ireturn
      11: aload_2
      12: invokeinterface #4,  1            // InterfaceMethod org/apache/hadoop/hbase/client/RegionInfo.getTable:()Lorg/apache/hadoop/hbase/TableName;
      17: aload_0
      18: getfield      #2                  // Field tableName:Lorg/apache/hadoop/hbase/TableName;
      21: invokevirtual #5                  // Method org/apache/hadoop/hbase/TableName.equals:(Ljava/lang/Object;)Z
      24: ifne          29
      27: iconst_0
      28: ireturn
      29: aload_0
      30: aload_1
      31: invokespecial #6                  // Method org/apache/hadoop/hbase/MetaTableAccessor$DefaultVisitorBase.visit:(Lorg/apache/hadoop/hbase/client/Result;)Z
      34: ireturn
}
