Compiled from "MetaTableMetrics.java"
class org.apache.hadoop.hbase.coprocessor.MetaTableMetrics$ExampleRegionObserverMeta implements org.apache.hadoop.hbase.coprocessor.RegionCoprocessor,org.apache.hadoop.hbase.coprocessor.RegionObserver {
  final org.apache.hadoop.hbase.coprocessor.MetaTableMetrics this$0;

  org.apache.hadoop.hbase.coprocessor.MetaTableMetrics$ExampleRegionObserverMeta(org.apache.hadoop.hbase.coprocessor.MetaTableMetrics);
    Code:
       0: aload_0
       1: aload_1
       2: putfield      #1                  // Field this$0:Lorg/apache/hadoop/hbase/coprocessor/MetaTableMetrics;
       5: aload_0
       6: invokespecial #2                  // Method java/lang/Object."<init>":()V
       9: return

  public java.util.Optional<org.apache.hadoop.hbase.coprocessor.RegionObserver> getRegionObserver();
    Code:
       0: aload_0
       1: invokestatic  #3                  // Method java/util/Optional.of:(Ljava/lang/Object;)Ljava/util/Optional;
       4: areturn

  public void preGetOp(org.apache.hadoop.hbase.coprocessor.ObserverContext<org.apache.hadoop.hbase.coprocessor.RegionCoprocessorEnvironment>, org.apache.hadoop.hbase.client.Get, java.util.List<org.apache.hadoop.hbase.Cell>) throws java.io.IOException;
    Code:
       0: aload_0
       1: aload_1
       2: aload_2
       3: invokespecial #4                  // Method registerAndMarkMetrics:(Lorg/apache/hadoop/hbase/coprocessor/ObserverContext;Lorg/apache/hadoop/hbase/client/Row;)V
       6: return

  public void prePut(org.apache.hadoop.hbase.coprocessor.ObserverContext<org.apache.hadoop.hbase.coprocessor.RegionCoprocessorEnvironment>, org.apache.hadoop.hbase.client.Put, org.apache.hadoop.hbase.wal.WALEdit, org.apache.hadoop.hbase.client.Durability) throws java.io.IOException;
    Code:
       0: aload_0
       1: aload_1
       2: aload_2
       3: invokespecial #4                  // Method registerAndMarkMetrics:(Lorg/apache/hadoop/hbase/coprocessor/ObserverContext;Lorg/apache/hadoop/hbase/client/Row;)V
       6: return

  public void preDelete(org.apache.hadoop.hbase.coprocessor.ObserverContext<org.apache.hadoop.hbase.coprocessor.RegionCoprocessorEnvironment>, org.apache.hadoop.hbase.client.Delete, org.apache.hadoop.hbase.wal.WALEdit, org.apache.hadoop.hbase.client.Durability) throws java.io.IOException;
    Code:
       0: aload_0
       1: aload_1
       2: aload_2
       3: invokespecial #4                  // Method registerAndMarkMetrics:(Lorg/apache/hadoop/hbase/coprocessor/ObserverContext;Lorg/apache/hadoop/hbase/client/Row;)V
       6: return
}
