Compiled from "MetaTableMetrics.java"
public class org.apache.hadoop.hbase.coprocessor.MetaTableMetrics implements org.apache.hadoop.hbase.coprocessor.RegionCoprocessor {
  public org.apache.hadoop.hbase.coprocessor.MetaTableMetrics();
    Code:
       0: aload_0
       1: invokespecial #7                  // Method java/lang/Object."<init>":()V
       4: aload_0
       5: iconst_0
       6: putfield      #6                  // Field active:Z
       9: aload_0
      10: invokestatic  #8                  // Method org/apache/hbase/thirdparty/com/google/common/collect/ImmutableMap.builder:()Lorg/apache/hbase/thirdparty/com/google/common/collect/ImmutableMap$Builder;
      13: ldc           #9                  // class org/apache/hadoop/hbase/client/Put
      15: getstatic     #10                 // Field org/apache/hadoop/hbase/coprocessor/MetaTableMetrics$MetaTableOps.PUT:Lorg/apache/hadoop/hbase/coprocessor/MetaTableMetrics$MetaTableOps;
      18: invokevirtual #11                 // Method org/apache/hbase/thirdparty/com/google/common/collect/ImmutableMap$Builder.put:(Ljava/lang/Object;Ljava/lang/Object;)Lorg/apache/hbase/thirdparty/com/google/common/collect/ImmutableMap$Builder;
      21: ldc           #12                 // class org/apache/hadoop/hbase/client/Get
      23: getstatic     #13                 // Field org/apache/hadoop/hbase/coprocessor/MetaTableMetrics$MetaTableOps.GET:Lorg/apache/hadoop/hbase/coprocessor/MetaTableMetrics$MetaTableOps;
      26: invokevirtual #11                 // Method org/apache/hbase/thirdparty/com/google/common/collect/ImmutableMap$Builder.put:(Ljava/lang/Object;Ljava/lang/Object;)Lorg/apache/hbase/thirdparty/com/google/common/collect/ImmutableMap$Builder;
      29: ldc           #14                 // class org/apache/hadoop/hbase/client/Delete
      31: getstatic     #15                 // Field org/apache/hadoop/hbase/coprocessor/MetaTableMetrics$MetaTableOps.DELETE:Lorg/apache/hadoop/hbase/coprocessor/MetaTableMetrics$MetaTableOps;
      34: invokevirtual #11                 // Method org/apache/hbase/thirdparty/com/google/common/collect/ImmutableMap$Builder.put:(Ljava/lang/Object;Ljava/lang/Object;)Lorg/apache/hbase/thirdparty/com/google/common/collect/ImmutableMap$Builder;
      37: invokevirtual #16                 // Method org/apache/hbase/thirdparty/com/google/common/collect/ImmutableMap$Builder.build:()Lorg/apache/hbase/thirdparty/com/google/common/collect/ImmutableMap;
      40: putfield      #1                  // Field opsNameMap:Lorg/apache/hbase/thirdparty/com/google/common/collect/ImmutableMap;
      43: return

  public java.util.Optional<org.apache.hadoop.hbase.coprocessor.RegionObserver> getRegionObserver();
    Code:
       0: aload_0
       1: getfield      #17                 // Field observer:Lorg/apache/hadoop/hbase/coprocessor/MetaTableMetrics$ExampleRegionObserverMeta;
       4: invokestatic  #18                 // Method java/util/Optional.of:(Ljava/lang/Object;)Ljava/util/Optional;
       7: areturn

  public void start(org.apache.hadoop.hbase.CoprocessorEnvironment) throws java.io.IOException;
    Code:
       0: aload_0
       1: new           #19                 // class org/apache/hadoop/hbase/coprocessor/MetaTableMetrics$ExampleRegionObserverMeta
       4: dup
       5: aload_0
       6: invokespecial #20                 // Method org/apache/hadoop/hbase/coprocessor/MetaTableMetrics$ExampleRegionObserverMeta."<init>":(Lorg/apache/hadoop/hbase/coprocessor/MetaTableMetrics;)V
       9: putfield      #17                 // Field observer:Lorg/apache/hadoop/hbase/coprocessor/MetaTableMetrics$ExampleRegionObserverMeta;
      12: aload_1
      13: instanceof    #21                 // class org/apache/hadoop/hbase/coprocessor/RegionCoprocessorEnvironment
      16: ifeq          116
      19: aload_1
      20: checkcast     #21                 // class org/apache/hadoop/hbase/coprocessor/RegionCoprocessorEnvironment
      23: invokeinterface #22,  1           // InterfaceMethod org/apache/hadoop/hbase/coprocessor/RegionCoprocessorEnvironment.getRegionInfo:()Lorg/apache/hadoop/hbase/client/RegionInfo;
      28: invokeinterface #23,  1           // InterfaceMethod org/apache/hadoop/hbase/client/RegionInfo.getTable:()Lorg/apache/hadoop/hbase/TableName;
      33: ifnull        116
      36: aload_1
      37: checkcast     #21                 // class org/apache/hadoop/hbase/coprocessor/RegionCoprocessorEnvironment
      40: invokeinterface #22,  1           // InterfaceMethod org/apache/hadoop/hbase/coprocessor/RegionCoprocessorEnvironment.getRegionInfo:()Lorg/apache/hadoop/hbase/client/RegionInfo;
      45: invokeinterface #23,  1           // InterfaceMethod org/apache/hadoop/hbase/client/RegionInfo.getTable:()Lorg/apache/hadoop/hbase/TableName;
      50: getstatic     #24                 // Field org/apache/hadoop/hbase/TableName.META_TABLE_NAME:Lorg/apache/hadoop/hbase/TableName;
      53: invokevirtual #25                 // Method org/apache/hadoop/hbase/TableName.equals:(Ljava/lang/Object;)Z
      56: ifeq          116
      59: aload_1
      60: checkcast     #21                 // class org/apache/hadoop/hbase/coprocessor/RegionCoprocessorEnvironment
      63: astore_2
      64: aload_0
      65: aload_2
      66: invokeinterface #26,  1           // InterfaceMethod org/apache/hadoop/hbase/coprocessor/RegionCoprocessorEnvironment.getMetricRegistryForRegionServer:()Lorg/apache/hadoop/hbase/metrics/MetricRegistry;
      71: putfield      #4                  // Field registry:Lorg/apache/hadoop/hbase/metrics/MetricRegistry;
      74: aload_0
      75: new           #27                 // class java/util/concurrent/ConcurrentHashMap
      78: dup
      79: invokespecial #28                 // Method java/util/concurrent/ConcurrentHashMap."<init>":()V
      82: putfield      #5                  // Field requestsMap:Ljava/util/Map;
      85: aload_0
      86: new           #29                 // class org/apache/hadoop/hbase/util/LossyCounting
      89: dup
      90: ldc           #30                 // String clientMetaMetrics
      92: invokespecial #31                 // Method org/apache/hadoop/hbase/util/LossyCounting."<init>":(Ljava/lang/String;)V
      95: putfield      #3                  // Field clientMetricsLossyCounting:Lorg/apache/hadoop/hbase/util/LossyCounting;
      98: aload_0
      99: new           #29                 // class org/apache/hadoop/hbase/util/LossyCounting
     102: dup
     103: ldc           #32                 // String regionMetaMetrics
     105: invokespecial #31                 // Method org/apache/hadoop/hbase/util/LossyCounting."<init>":(Ljava/lang/String;)V
     108: putfield      #2                  // Field regionMetricsLossyCounting:Lorg/apache/hadoop/hbase/util/LossyCounting;
     111: aload_0
     112: iconst_1
     113: putfield      #6                  // Field active:Z
     116: return

  public void stop(org.apache.hadoop.hbase.CoprocessorEnvironment) throws java.io.IOException;
    Code:
       0: aload_0
       1: getfield      #5                  // Field requestsMap:Ljava/util/Map;
       4: ifnull        55
       7: aload_0
       8: getfield      #5                  // Field requestsMap:Ljava/util/Map;
      11: invokeinterface #33,  1           // InterfaceMethod java/util/Map.keySet:()Ljava/util/Set;
      16: invokeinterface #34,  1           // InterfaceMethod java/util/Set.iterator:()Ljava/util/Iterator;
      21: astore_2
      22: aload_2
      23: invokeinterface #35,  1           // InterfaceMethod java/util/Iterator.hasNext:()Z
      28: ifeq          55
      31: aload_2
      32: invokeinterface #36,  1           // InterfaceMethod java/util/Iterator.next:()Ljava/lang/Object;
      37: checkcast     #37                 // class java/lang/String
      40: astore_3
      41: aload_0
      42: getfield      #4                  // Field registry:Lorg/apache/hadoop/hbase/metrics/MetricRegistry;
      45: aload_3
      46: invokeinterface #38,  2           // InterfaceMethod org/apache/hadoop/hbase/metrics/MetricRegistry.remove:(Ljava/lang/String;)Z
      51: pop
      52: goto          22
      55: return

  static boolean access$000(org.apache.hadoop.hbase.coprocessor.MetaTableMetrics);
    Code:
       0: aload_0
       1: getfield      #6                  // Field active:Z
       4: ireturn

  static java.util.Map access$100(org.apache.hadoop.hbase.coprocessor.MetaTableMetrics);
    Code:
       0: aload_0
       1: getfield      #5                  // Field requestsMap:Ljava/util/Map;
       4: areturn

  static org.apache.hadoop.hbase.metrics.MetricRegistry access$200(org.apache.hadoop.hbase.coprocessor.MetaTableMetrics);
    Code:
       0: aload_0
       1: getfield      #4                  // Field registry:Lorg/apache/hadoop/hbase/metrics/MetricRegistry;
       4: areturn

  static org.apache.hadoop.hbase.util.LossyCounting access$300(org.apache.hadoop.hbase.coprocessor.MetaTableMetrics);
    Code:
       0: aload_0
       1: getfield      #3                  // Field clientMetricsLossyCounting:Lorg/apache/hadoop/hbase/util/LossyCounting;
       4: areturn

  static org.apache.hadoop.hbase.util.LossyCounting access$400(org.apache.hadoop.hbase.coprocessor.MetaTableMetrics);
    Code:
       0: aload_0
       1: getfield      #2                  // Field regionMetricsLossyCounting:Lorg/apache/hadoop/hbase/util/LossyCounting;
       4: areturn

  static org.apache.hbase.thirdparty.com.google.common.collect.ImmutableMap access$500(org.apache.hadoop.hbase.coprocessor.MetaTableMetrics);
    Code:
       0: aload_0
       1: getfield      #1                  // Field opsNameMap:Lorg/apache/hbase/thirdparty/com/google/common/collect/ImmutableMap;
       4: areturn
}
