Compiled from "MetricsConnection.java"
class org.apache.hadoop.hbase.client.MetricsConnection$2 implements org.apache.hadoop.hbase.client.MetricsConnection$NewMetric<com.codahale.metrics.Histogram> {
  final org.apache.hadoop.hbase.client.MetricsConnection this$0;

  org.apache.hadoop.hbase.client.MetricsConnection$2(org.apache.hadoop.hbase.client.MetricsConnection);
    Code:
       0: aload_0
       1: aload_1
       2: putfield      #1                  // Field this$0:Lorg/apache/hadoop/hbase/client/MetricsConnection;
       5: aload_0
       6: invokespecial #2                  // Method java/lang/Object."<init>":()V
       9: return

  public com.codahale.metrics.Histogram newMetric(java.lang.Class<?>, java.lang.String, java.lang.String);
    Code:
       0: aload_0
       1: getfield      #1                  // Field this$0:Lorg/apache/hadoop/hbase/client/MetricsConnection;
       4: invokestatic  #3                  // Method org/apache/hadoop/hbase/client/MetricsConnection.access$100:(Lorg/apache/hadoop/hbase/client/MetricsConnection;)Lcom/codahale/metrics/MetricRegistry;
       7: aload_1
       8: iconst_2
       9: anewarray     #4                  // class java/lang/String
      12: dup
      13: iconst_0
      14: aload_2
      15: aastore
      16: dup
      17: iconst_1
      18: aload_3
      19: aastore
      20: invokestatic  #5                  // Method com/codahale/metrics/MetricRegistry.name:(Ljava/lang/Class;[Ljava/lang/String;)Ljava/lang/String;
      23: invokevirtual #6                  // Method com/codahale/metrics/MetricRegistry.histogram:(Ljava/lang/String;)Lcom/codahale/metrics/Histogram;
      26: areturn

  public java.lang.Object newMetric(java.lang.Class, java.lang.String, java.lang.String);
    Code:
       0: aload_0
       1: aload_1
       2: aload_2
       3: aload_3
       4: invokevirtual #7                  // Method newMetric:(Ljava/lang/Class;Ljava/lang/String;Ljava/lang/String;)Lcom/codahale/metrics/Histogram;
       7: areturn
}
