Compiled from "MetricsRegionServerQuotaSourceImpl.java"
public class org.apache.hadoop.hbase.regionserver.MetricsRegionServerQuotaSourceImpl extends org.apache.hadoop.hbase.metrics.BaseSourceImpl implements org.apache.hadoop.hbase.regionserver.MetricsRegionServerQuotaSource {
  public org.apache.hadoop.hbase.regionserver.MetricsRegionServerQuotaSourceImpl();
    Code:
       0: aload_0
       1: ldc           #2                  // String Quotas
       3: ldc           #3                  // String Metrics about HBase RegionServer Quotas
       5: ldc           #4                  // String regionserver
       7: ldc           #5                  // String RegionServer,sub=Quotas
       9: invokespecial #6                  // Method "<init>":(Ljava/lang/String;Ljava/lang/String;Ljava/lang/String;Ljava/lang/String;)V
      12: return

  public org.apache.hadoop.hbase.regionserver.MetricsRegionServerQuotaSourceImpl(java.lang.String, java.lang.String, java.lang.String, java.lang.String);
    Code:
       0: aload_0
       1: aload_1
       2: aload_2
       3: aload_3
       4: aload         4
       6: invokespecial #7                  // Method org/apache/hadoop/hbase/metrics/BaseSourceImpl."<init>":(Ljava/lang/String;Ljava/lang/String;Ljava/lang/String;Ljava/lang/String;)V
       9: aload_0
      10: aload_0
      11: getfield      #8                  // Field registry:Lorg/apache/hadoop/hbase/metrics/MetricRegistry;
      14: ldc           #9                  // String numTablesInViolation
      16: invokeinterface #10,  2           // InterfaceMethod org/apache/hadoop/hbase/metrics/MetricRegistry.meter:(Ljava/lang/String;)Lorg/apache/hadoop/hbase/metrics/Meter;
      21: putfield      #11                 // Field tablesInViolationCounter:Lorg/apache/hadoop/hbase/metrics/Meter;
      24: aload_0
      25: aload_0
      26: getfield      #8                  // Field registry:Lorg/apache/hadoop/hbase/metrics/MetricRegistry;
      29: ldc           #12                 // String numSpaceSnapshotsReceived
      31: invokeinterface #10,  2           // InterfaceMethod org/apache/hadoop/hbase/metrics/MetricRegistry.meter:(Ljava/lang/String;)Lorg/apache/hadoop/hbase/metrics/Meter;
      36: putfield      #13                 // Field spaceQuotaSnapshotsReceived:Lorg/apache/hadoop/hbase/metrics/Meter;
      39: aload_0
      40: aload_0
      41: getfield      #8                  // Field registry:Lorg/apache/hadoop/hbase/metrics/MetricRegistry;
      44: ldc           #14                 // String fileSystemUtilizationChoreTime
      46: invokeinterface #15,  2           // InterfaceMethod org/apache/hadoop/hbase/metrics/MetricRegistry.timer:(Ljava/lang/String;)Lorg/apache/hadoop/hbase/metrics/Timer;
      51: putfield      #16                 // Field fileSystemUtilizationChoreTimer:Lorg/apache/hadoop/hbase/metrics/Timer;
      54: aload_0
      55: aload_0
      56: getfield      #8                  // Field registry:Lorg/apache/hadoop/hbase/metrics/MetricRegistry;
      59: ldc           #17                 // String spaceQuotaRefresherChoreTime
      61: invokeinterface #15,  2           // InterfaceMethod org/apache/hadoop/hbase/metrics/MetricRegistry.timer:(Ljava/lang/String;)Lorg/apache/hadoop/hbase/metrics/Timer;
      66: putfield      #18                 // Field spaceQuotaRefresherChoreTimer:Lorg/apache/hadoop/hbase/metrics/Timer;
      69: aload_0
      70: aload_0
      71: getfield      #8                  // Field registry:Lorg/apache/hadoop/hbase/metrics/MetricRegistry;
      74: ldc           #19                 // String numRegionSizeReports
      76: invokeinterface #20,  2           // InterfaceMethod org/apache/hadoop/hbase/metrics/MetricRegistry.counter:(Ljava/lang/String;)Lorg/apache/hadoop/hbase/metrics/Counter;
      81: putfield      #21                 // Field regionSizeReportCounter:Lorg/apache/hadoop/hbase/metrics/Counter;
      84: aload_0
      85: aload_0
      86: getfield      #8                  // Field registry:Lorg/apache/hadoop/hbase/metrics/MetricRegistry;
      89: ldc           #22                 // String regionSizeReportingChoreTime
      91: invokeinterface #15,  2           // InterfaceMethod org/apache/hadoop/hbase/metrics/MetricRegistry.timer:(Ljava/lang/String;)Lorg/apache/hadoop/hbase/metrics/Timer;
      96: putfield      #23                 // Field regionSizeReportingChoreTimer:Lorg/apache/hadoop/hbase/metrics/Timer;
      99: return

  public void updateNumTablesInSpaceQuotaViolation(long);
    Code:
       0: aload_0
       1: getfield      #11                 // Field tablesInViolationCounter:Lorg/apache/hadoop/hbase/metrics/Meter;
       4: lload_1
       5: invokeinterface #24,  3           // InterfaceMethod org/apache/hadoop/hbase/metrics/Meter.mark:(J)V
      10: return

  public void updateNumTableSpaceQuotaSnapshots(long);
    Code:
       0: aload_0
       1: getfield      #13                 // Field spaceQuotaSnapshotsReceived:Lorg/apache/hadoop/hbase/metrics/Meter;
       4: lload_1
       5: invokeinterface #24,  3           // InterfaceMethod org/apache/hadoop/hbase/metrics/Meter.mark:(J)V
      10: return

  public void incrementSpaceQuotaFileSystemScannerChoreTime(long);
    Code:
       0: aload_0
       1: getfield      #16                 // Field fileSystemUtilizationChoreTimer:Lorg/apache/hadoop/hbase/metrics/Timer;
       4: lload_1
       5: invokeinterface #25,  3           // InterfaceMethod org/apache/hadoop/hbase/metrics/Timer.updateMillis:(J)V
      10: return

  public void incrementSpaceQuotaRefresherChoreTime(long);
    Code:
       0: aload_0
       1: getfield      #18                 // Field spaceQuotaRefresherChoreTimer:Lorg/apache/hadoop/hbase/metrics/Timer;
       4: lload_1
       5: invokeinterface #25,  3           // InterfaceMethod org/apache/hadoop/hbase/metrics/Timer.updateMillis:(J)V
      10: return

  public void incrementNumRegionSizeReportsSent(long);
    Code:
       0: aload_0
       1: getfield      #21                 // Field regionSizeReportCounter:Lorg/apache/hadoop/hbase/metrics/Counter;
       4: lload_1
       5: invokeinterface #26,  3           // InterfaceMethod org/apache/hadoop/hbase/metrics/Counter.increment:(J)V
      10: return

  public void incrementRegionSizeReportingChoreTime(long);
    Code:
       0: aload_0
       1: getfield      #23                 // Field regionSizeReportingChoreTimer:Lorg/apache/hadoop/hbase/metrics/Timer;
       4: lload_1
       5: getstatic     #27                 // Field java/util/concurrent/TimeUnit.MILLISECONDS:Ljava/util/concurrent/TimeUnit;
       8: invokeinterface #28,  4           // InterfaceMethod org/apache/hadoop/hbase/metrics/Timer.update:(JLjava/util/concurrent/TimeUnit;)V
      13: return
}
