Compiled from "MetricSampleQuantiles.java"
class org.apache.hadoop.metrics2.util.MetricSampleQuantiles$SampleItem {
  public org.apache.hadoop.metrics2.util.MetricSampleQuantiles$SampleItem(long, int, int);
    Code:
       0: aload_0
       1: invokespecial #4                  // Method java/lang/Object."<init>":()V
       4: aload_0
       5: lload_1
       6: putfield      #3                  // Field value:J
       9: aload_0
      10: iload_3
      11: putfield      #2                  // Field g:I
      14: aload_0
      15: iload         4
      17: putfield      #1                  // Field delta:I
      20: return

  public java.lang.String toString();
    Code:
       0: ldc           #5                  // String %d, %d, %d
       2: iconst_3
       3: anewarray     #6                  // class java/lang/Object
       6: dup
       7: iconst_0
       8: aload_0
       9: getfield      #3                  // Field value:J
      12: invokestatic  #7                  // Method java/lang/Long.valueOf:(J)Ljava/lang/Long;
      15: aastore
      16: dup
      17: iconst_1
      18: aload_0
      19: getfield      #2                  // Field g:I
      22: invokestatic  #8                  // Method java/lang/Integer.valueOf:(I)Ljava/lang/Integer;
      25: aastore
      26: dup
      27: iconst_2
      28: aload_0
      29: getfield      #1                  // Field delta:I
      32: invokestatic  #8                  // Method java/lang/Integer.valueOf:(I)Ljava/lang/Integer;
      35: aastore
      36: invokestatic  #9                  // Method java/lang/String.format:(Ljava/lang/String;[Ljava/lang/Object;)Ljava/lang/String;
      39: areturn

  static long access$000(org.apache.hadoop.metrics2.util.MetricSampleQuantiles$SampleItem);
    Code:
       0: aload_0
       1: getfield      #3                  // Field value:J
       4: lreturn

  static int access$100(org.apache.hadoop.metrics2.util.MetricSampleQuantiles$SampleItem);
    Code:
       0: aload_0
       1: getfield      #2                  // Field g:I
       4: ireturn

  static int access$200(org.apache.hadoop.metrics2.util.MetricSampleQuantiles$SampleItem);
    Code:
       0: aload_0
       1: getfield      #1                  // Field delta:I
       4: ireturn

  static int access$102(org.apache.hadoop.metrics2.util.MetricSampleQuantiles$SampleItem, int);
    Code:
       0: aload_0
       1: iload_1
       2: dup_x1
       3: putfield      #2                  // Field g:I
       6: ireturn
}
