Compiled from "MetricRegistriesLoader.java"
public final class org.apache.hadoop.hbase.metrics.MetricRegistriesLoader {
  public static org.apache.hadoop.hbase.metrics.MetricRegistries load();
    Code:
       0: invokestatic  #2                  // Method getDefinedImplemantations:()Ljava/util/List;
       3: astore_0
       4: aload_0
       5: invokestatic  #3                  // Method load:(Ljava/util/List;)Lorg/apache/hadoop/hbase/metrics/MetricRegistries;
       8: areturn

  static org.apache.hadoop.hbase.metrics.MetricRegistries load(java.util.List<org.apache.hadoop.hbase.metrics.MetricRegistries>);
    Code:
       0: aload_0
       1: invokeinterface #4,  1            // InterfaceMethod java/util/List.size:()I
       6: iconst_1
       7: if_icmpne     53
      10: aload_0
      11: iconst_0
      12: invokeinterface #5,  2            // InterfaceMethod java/util/List.get:(I)Ljava/lang/Object;
      17: checkcast     #6                  // class org/apache/hadoop/hbase/metrics/MetricRegistries
      20: astore_1
      21: getstatic     #7                  // Field LOG:Lorg/slf4j/Logger;
      24: new           #8                  // class java/lang/StringBuilder
      27: dup
      28: invokespecial #9                  // Method java/lang/StringBuilder."<init>":()V
      31: ldc           #10                 // String Loaded MetricRegistries
      33: invokevirtual #11                 // Method java/lang/StringBuilder.append:(Ljava/lang/String;)Ljava/lang/StringBuilder;
      36: aload_1
      37: invokevirtual #12                 // Method java/lang/Object.getClass:()Ljava/lang/Class;
      40: invokevirtual #13                 // Method java/lang/StringBuilder.append:(Ljava/lang/Object;)Ljava/lang/StringBuilder;
      43: invokevirtual #14                 // Method java/lang/StringBuilder.toString:()Ljava/lang/String;
      46: invokeinterface #15,  2           // InterfaceMethod org/slf4j/Logger.info:(Ljava/lang/String;)V
      51: aload_1
      52: areturn
      53: aload_0
      54: invokeinterface #16,  1           // InterfaceMethod java/util/List.isEmpty:()Z
      59: ifeq          88
      62: ldc           #18                 // String org.apache.hadoop.hbase.metrics.impl.MetricRegistriesImpl
      64: invokestatic  #19                 // Method java/lang/Class.forName:(Ljava/lang/String;)Ljava/lang/Class;
      67: iconst_0
      68: anewarray     #20                 // class java/lang/Object
      71: invokestatic  #21                 // Method org/apache/hadoop/hbase/util/ReflectionUtils.newInstance:(Ljava/lang/Class;[Ljava/lang/Object;)Ljava/lang/Object;
      74: checkcast     #6                  // class org/apache/hadoop/hbase/metrics/MetricRegistries
      77: areturn
      78: astore_1
      79: new           #23                 // class java/lang/RuntimeException
      82: dup
      83: aload_1
      84: invokespecial #24                 // Method java/lang/RuntimeException."<init>":(Ljava/lang/Throwable;)V
      87: athrow
      88: new           #8                  // class java/lang/StringBuilder
      91: dup
      92: invokespecial #9                  // Method java/lang/StringBuilder."<init>":()V
      95: astore_1
      96: aload_0
      97: invokeinterface #25,  1           // InterfaceMethod java/util/List.iterator:()Ljava/util/Iterator;
     102: astore_2
     103: aload_2
     104: invokeinterface #26,  1           // InterfaceMethod java/util/Iterator.hasNext:()Z
     109: ifeq          148
     112: aload_2
     113: invokeinterface #27,  1           // InterfaceMethod java/util/Iterator.next:()Ljava/lang/Object;
     118: checkcast     #6                  // class org/apache/hadoop/hbase/metrics/MetricRegistries
     121: astore_3
     122: aload_1
     123: invokevirtual #28                 // Method java/lang/StringBuilder.length:()I
     126: ifle          136
     129: aload_1
     130: ldc           #29                 // String ,
     132: invokevirtual #11                 // Method java/lang/StringBuilder.append:(Ljava/lang/String;)Ljava/lang/StringBuilder;
     135: pop
     136: aload_1
     137: aload_3
     138: invokevirtual #12                 // Method java/lang/Object.getClass:()Ljava/lang/Class;
     141: invokevirtual #13                 // Method java/lang/StringBuilder.append:(Ljava/lang/Object;)Ljava/lang/StringBuilder;
     144: pop
     145: goto          103
     148: getstatic     #7                  // Field LOG:Lorg/slf4j/Logger;
     151: new           #8                  // class java/lang/StringBuilder
     154: dup
     155: invokespecial #9                  // Method java/lang/StringBuilder."<init>":()V
     158: ldc           #30                 // String Found multiple MetricRegistries implementations:
     160: invokevirtual #11                 // Method java/lang/StringBuilder.append:(Ljava/lang/String;)Ljava/lang/StringBuilder;
     163: aload_1
     164: invokevirtual #13                 // Method java/lang/StringBuilder.append:(Ljava/lang/Object;)Ljava/lang/StringBuilder;
     167: ldc           #31                 // String . Using first found implementation:
     169: invokevirtual #11                 // Method java/lang/StringBuilder.append:(Ljava/lang/String;)Ljava/lang/StringBuilder;
     172: aload_0
     173: iconst_0
     174: invokeinterface #5,  2            // InterfaceMethod java/util/List.get:(I)Ljava/lang/Object;
     179: invokevirtual #13                 // Method java/lang/StringBuilder.append:(Ljava/lang/Object;)Ljava/lang/StringBuilder;
     182: invokevirtual #14                 // Method java/lang/StringBuilder.toString:()Ljava/lang/String;
     185: invokeinterface #32,  2           // InterfaceMethod org/slf4j/Logger.warn:(Ljava/lang/String;)V
     190: aload_0
     191: iconst_0
     192: invokeinterface #5,  2            // InterfaceMethod java/util/List.get:(I)Ljava/lang/Object;
     197: checkcast     #6                  // class org/apache/hadoop/hbase/metrics/MetricRegistries
     200: areturn
    Exception table:
       from    to  target type
          62    77    78   Class java/lang/ClassNotFoundException

  static {};
    Code:
       0: ldc           #6                  // class org/apache/hadoop/hbase/metrics/MetricRegistries
       2: invokestatic  #38                 // Method org/slf4j/LoggerFactory.getLogger:(Ljava/lang/Class;)Lorg/slf4j/Logger;
       5: putstatic     #7                  // Field LOG:Lorg/slf4j/Logger;
       8: return
}
