Compiled from "MetricsConnection.java"
public class org.apache.hadoop.hbase.client.MetricsConnection$RunnerStats {
  final com.codahale.metrics.Counter normalRunners;

  final com.codahale.metrics.Counter delayRunners;

  final com.codahale.metrics.Histogram delayIntevalHist;

  public org.apache.hadoop.hbase.client.MetricsConnection$RunnerStats(com.codahale.metrics.MetricRegistry);
    Code:
       0: aload_0
       1: invokespecial #1                  // Method java/lang/Object."<init>":()V
       4: aload_0
       5: aload_1
       6: ldc           #2                  // class org/apache/hadoop/hbase/client/MetricsConnection
       8: iconst_1
       9: anewarray     #3                  // class java/lang/String
      12: dup
      13: iconst_0
      14: ldc           #4                  // String normalRunnersCount
      16: aastore
      17: invokestatic  #5                  // Method com/codahale/metrics/MetricRegistry.name:(Ljava/lang/Class;[Ljava/lang/String;)Ljava/lang/String;
      20: invokevirtual #6                  // Method com/codahale/metrics/MetricRegistry.counter:(Ljava/lang/String;)Lcom/codahale/metrics/Counter;
      23: putfield      #7                  // Field normalRunners:Lcom/codahale/metrics/Counter;
      26: aload_0
      27: aload_1
      28: ldc           #2                  // class org/apache/hadoop/hbase/client/MetricsConnection
      30: iconst_1
      31: anewarray     #3                  // class java/lang/String
      34: dup
      35: iconst_0
      36: ldc           #8                  // String delayRunnersCount
      38: aastore
      39: invokestatic  #5                  // Method com/codahale/metrics/MetricRegistry.name:(Ljava/lang/Class;[Ljava/lang/String;)Ljava/lang/String;
      42: invokevirtual #6                  // Method com/codahale/metrics/MetricRegistry.counter:(Ljava/lang/String;)Lcom/codahale/metrics/Counter;
      45: putfield      #9                  // Field delayRunners:Lcom/codahale/metrics/Counter;
      48: aload_0
      49: aload_1
      50: ldc           #2                  // class org/apache/hadoop/hbase/client/MetricsConnection
      52: iconst_1
      53: anewarray     #3                  // class java/lang/String
      56: dup
      57: iconst_0
      58: ldc           #10                 // String delayIntervalHist
      60: aastore
      61: invokestatic  #5                  // Method com/codahale/metrics/MetricRegistry.name:(Ljava/lang/Class;[Ljava/lang/String;)Ljava/lang/String;
      64: invokevirtual #11                 // Method com/codahale/metrics/MetricRegistry.histogram:(Ljava/lang/String;)Lcom/codahale/metrics/Histogram;
      67: putfield      #12                 // Field delayIntevalHist:Lcom/codahale/metrics/Histogram;
      70: return

  public void incrNormalRunners();
    Code:
       0: aload_0
       1: getfield      #7                  // Field normalRunners:Lcom/codahale/metrics/Counter;
       4: invokevirtual #13                 // Method com/codahale/metrics/Counter.inc:()V
       7: return

  public void incrDelayRunners();
    Code:
       0: aload_0
       1: getfield      #9                  // Field delayRunners:Lcom/codahale/metrics/Counter;
       4: invokevirtual #13                 // Method com/codahale/metrics/Counter.inc:()V
       7: return

  public void updateDelayInterval(long);
    Code:
       0: aload_0
       1: getfield      #12                 // Field delayIntevalHist:Lcom/codahale/metrics/Histogram;
       4: lload_1
       5: invokevirtual #14                 // Method com/codahale/metrics/Histogram.update:(J)V
       8: return
}
