Compiled from "MetricsSource.java"
public class org.apache.hadoop.hbase.replication.regionserver.MetricsSource implements org.apache.hadoop.hbase.metrics.BaseSource {
  public org.apache.hadoop.hbase.replication.regionserver.MetricsSource(java.lang.String);
    Code:
       0: aload_0
       1: invokespecial #1                  // Method java/lang/Object."<init>":()V
       4: aload_0
       5: new           #2                  // class java/util/HashMap
       8: dup
       9: invokespecial #3                  // Method java/util/HashMap."<init>":()V
      12: putfield      #4                  // Field lastShippedTimeStamps:Ljava/util/Map;
      15: aload_0
      16: new           #2                  // class java/util/HashMap
      19: dup
      20: invokespecial #3                  // Method java/util/HashMap."<init>":()V
      23: putfield      #5                  // Field ageOfLastShippedOp:Ljava/util/Map;
      26: aload_0
      27: lconst_0
      28: putfield      #6                  // Field lastHFileRefsQueueSize:J
      31: aload_0
      32: aload_1
      33: putfield      #7                  // Field id:Ljava/lang/String;
      36: aload_0
      37: ldc           #8                  // class org/apache/hadoop/hbase/replication/regionserver/MetricsReplicationSourceFactory
      39: invokestatic  #9                  // Method org/apache/hadoop/hbase/CompatibilitySingletonFactory.getInstance:(Ljava/lang/Class;)Ljava/lang/Object;
      42: checkcast     #8                  // class org/apache/hadoop/hbase/replication/regionserver/MetricsReplicationSourceFactory
      45: aload_1
      46: invokeinterface #10,  2           // InterfaceMethod org/apache/hadoop/hbase/replication/regionserver/MetricsReplicationSourceFactory.getSource:(Ljava/lang/String;)Lorg/apache/hadoop/hbase/replication/regionserver/MetricsReplicationSourceSource;
      51: putfield      #11                 // Field singleSourceSource:Lorg/apache/hadoop/hbase/replication/regionserver/MetricsReplicationSourceSource;
      54: aload_0
      55: ldc           #8                  // class org/apache/hadoop/hbase/replication/regionserver/MetricsReplicationSourceFactory
      57: invokestatic  #9                  // Method org/apache/hadoop/hbase/CompatibilitySingletonFactory.getInstance:(Ljava/lang/Class;)Ljava/lang/Object;
      60: checkcast     #8                  // class org/apache/hadoop/hbase/replication/regionserver/MetricsReplicationSourceFactory
      63: invokeinterface #12,  1           // InterfaceMethod org/apache/hadoop/hbase/replication/regionserver/MetricsReplicationSourceFactory.getGlobalSource:()Lorg/apache/hadoop/hbase/replication/regionserver/MetricsReplicationSourceSource;
      68: putfield      #13                 // Field globalSourceSource:Lorg/apache/hadoop/hbase/replication/regionserver/MetricsReplicationSourceSource;
      71: aload_0
      72: new           #2                  // class java/util/HashMap
      75: dup
      76: invokespecial #3                  // Method java/util/HashMap."<init>":()V
      79: putfield      #14                 // Field singleSourceSourceByTable:Ljava/util/Map;
      82: return

  public org.apache.hadoop.hbase.replication.regionserver.MetricsSource(java.lang.String, org.apache.hadoop.hbase.replication.regionserver.MetricsReplicationSourceSource, org.apache.hadoop.hbase.replication.regionserver.MetricsReplicationSourceSource, java.util.Map<java.lang.String, org.apache.hadoop.hbase.replication.regionserver.MetricsReplicationSourceSource>);
    Code:
       0: aload_0
       1: invokespecial #1                  // Method java/lang/Object."<init>":()V
       4: aload_0
       5: new           #2                  // class java/util/HashMap
       8: dup
       9: invokespecial #3                  // Method java/util/HashMap."<init>":()V
      12: putfield      #4                  // Field lastShippedTimeStamps:Ljava/util/Map;
      15: aload_0
      16: new           #2                  // class java/util/HashMap
      19: dup
      20: invokespecial #3                  // Method java/util/HashMap."<init>":()V
      23: putfield      #5                  // Field ageOfLastShippedOp:Ljava/util/Map;
      26: aload_0
      27: lconst_0
      28: putfield      #6                  // Field lastHFileRefsQueueSize:J
      31: aload_0
      32: aload_1
      33: putfield      #7                  // Field id:Ljava/lang/String;
      36: aload_0
      37: aload_2
      38: putfield      #11                 // Field singleSourceSource:Lorg/apache/hadoop/hbase/replication/regionserver/MetricsReplicationSourceSource;
      41: aload_0
      42: aload_3
      43: putfield      #13                 // Field globalSourceSource:Lorg/apache/hadoop/hbase/replication/regionserver/MetricsReplicationSourceSource;
      46: aload_0
      47: aload         4
      49: putfield      #14                 // Field singleSourceSourceByTable:Ljava/util/Map;
      52: return

  public void setAgeOfLastShippedOp(long, java.lang.String);
    Code:
       0: invokestatic  #15                 // Method org/apache/hadoop/hbase/util/EnvironmentEdgeManager.currentTime:()J
       3: lload_1
       4: lsub
       5: lstore        4
       7: aload_0
       8: getfield      #11                 // Field singleSourceSource:Lorg/apache/hadoop/hbase/replication/regionserver/MetricsReplicationSourceSource;
      11: lload         4
      13: invokeinterface #16,  3           // InterfaceMethod org/apache/hadoop/hbase/replication/regionserver/MetricsReplicationSourceSource.setLastShippedAge:(J)V
      18: aload_0
      19: getfield      #13                 // Field globalSourceSource:Lorg/apache/hadoop/hbase/replication/regionserver/MetricsReplicationSourceSource;
      22: lload         4
      24: invokeinterface #16,  3           // InterfaceMethod org/apache/hadoop/hbase/replication/regionserver/MetricsReplicationSourceSource.setLastShippedAge:(J)V
      29: aload_0
      30: getfield      #5                  // Field ageOfLastShippedOp:Ljava/util/Map;
      33: aload_3
      34: lload         4
      36: invokestatic  #17                 // Method java/lang/Long.valueOf:(J)Ljava/lang/Long;
      39: invokeinterface #18,  3           // InterfaceMethod java/util/Map.put:(Ljava/lang/Object;Ljava/lang/Object;)Ljava/lang/Object;
      44: pop
      45: aload_0
      46: getfield      #4                  // Field lastShippedTimeStamps:Ljava/util/Map;
      49: aload_3
      50: lload_1
      51: invokestatic  #17                 // Method java/lang/Long.valueOf:(J)Ljava/lang/Long;
      54: invokeinterface #18,  3           // InterfaceMethod java/util/Map.put:(Ljava/lang/Object;Ljava/lang/Object;)Ljava/lang/Object;
      59: pop
      60: return

  public void setAgeOfLastShippedOpByTable(long, java.lang.String);
    Code:
       0: invokestatic  #15                 // Method org/apache/hadoop/hbase/util/EnvironmentEdgeManager.currentTime:()J
       3: lload_1
       4: lsub
       5: lstore        4
       7: aload_0
       8: invokevirtual #19                 // Method getSingleSourceSourceByTable:()Ljava/util/Map;
      11: aload_3
      12: invokedynamic #20,  0             // InvokeDynamic #0:apply:()Ljava/util/function/Function;
      17: invokeinterface #21,  3           // InterfaceMethod java/util/Map.computeIfAbsent:(Ljava/lang/Object;Ljava/util/function/Function;)Ljava/lang/Object;
      22: checkcast     #22                 // class org/apache/hadoop/hbase/replication/regionserver/MetricsReplicationSourceSource
      25: lload         4
      27: invokeinterface #16,  3           // InterfaceMethod org/apache/hadoop/hbase/replication/regionserver/MetricsReplicationSourceSource.setLastShippedAge:(J)V
      32: return

  public long getAgeofLastShippedOp(java.lang.String);
    Code:
       0: aload_0
       1: getfield      #5                  // Field ageOfLastShippedOp:Ljava/util/Map;
       4: aload_1
       5: invokeinterface #23,  2           // InterfaceMethod java/util/Map.get:(Ljava/lang/Object;)Ljava/lang/Object;
      10: ifnonnull     17
      13: lconst_0
      14: goto          33
      17: aload_0
      18: getfield      #5                  // Field ageOfLastShippedOp:Ljava/util/Map;
      21: aload_1
      22: invokeinterface #23,  2           // InterfaceMethod java/util/Map.get:(Ljava/lang/Object;)Ljava/lang/Object;
      27: checkcast     #24                 // class java/lang/Long
      30: invokevirtual #25                 // Method java/lang/Long.longValue:()J
      33: lreturn

  public void refreshAgeOfLastShippedOp(java.lang.String);
    Code:
       0: aload_0
       1: getfield      #4                  // Field lastShippedTimeStamps:Ljava/util/Map;
       4: aload_1
       5: invokeinterface #23,  2           // InterfaceMethod java/util/Map.get:(Ljava/lang/Object;)Ljava/lang/Object;
      10: checkcast     #24                 // class java/lang/Long
      13: astore_2
      14: aload_2
      15: ifnonnull     38
      18: aload_0
      19: getfield      #4                  // Field lastShippedTimeStamps:Ljava/util/Map;
      22: aload_1
      23: lconst_0
      24: invokestatic  #17                 // Method java/lang/Long.valueOf:(J)Ljava/lang/Long;
      27: invokeinterface #18,  3           // InterfaceMethod java/util/Map.put:(Ljava/lang/Object;Ljava/lang/Object;)Ljava/lang/Object;
      32: pop
      33: lconst_0
      34: invokestatic  #17                 // Method java/lang/Long.valueOf:(J)Ljava/lang/Long;
      37: astore_2
      38: aload_2
      39: invokevirtual #25                 // Method java/lang/Long.longValue:()J
      42: lconst_0
      43: lcmp
      44: ifle          56
      47: aload_0
      48: aload_2
      49: invokevirtual #25                 // Method java/lang/Long.longValue:()J
      52: aload_1
      53: invokevirtual #26                 // Method setAgeOfLastShippedOp:(JLjava/lang/String;)V
      56: return

  public void incrSizeOfLogQueue();
    Code:
       0: aload_0
       1: getfield      #11                 // Field singleSourceSource:Lorg/apache/hadoop/hbase/replication/regionserver/MetricsReplicationSourceSource;
       4: iconst_1
       5: invokeinterface #27,  2           // InterfaceMethod org/apache/hadoop/hbase/replication/regionserver/MetricsReplicationSourceSource.incrSizeOfLogQueue:(I)V
      10: aload_0
      11: getfield      #13                 // Field globalSourceSource:Lorg/apache/hadoop/hbase/replication/regionserver/MetricsReplicationSourceSource;
      14: iconst_1
      15: invokeinterface #27,  2           // InterfaceMethod org/apache/hadoop/hbase/replication/regionserver/MetricsReplicationSourceSource.incrSizeOfLogQueue:(I)V
      20: return

  public void decrSizeOfLogQueue();
    Code:
       0: aload_0
       1: getfield      #11                 // Field singleSourceSource:Lorg/apache/hadoop/hbase/replication/regionserver/MetricsReplicationSourceSource;
       4: iconst_1
       5: invokeinterface #28,  2           // InterfaceMethod org/apache/hadoop/hbase/replication/regionserver/MetricsReplicationSourceSource.decrSizeOfLogQueue:(I)V
      10: aload_0
      11: getfield      #13                 // Field globalSourceSource:Lorg/apache/hadoop/hbase/replication/regionserver/MetricsReplicationSourceSource;
      14: iconst_1
      15: invokeinterface #28,  2           // InterfaceMethod org/apache/hadoop/hbase/replication/regionserver/MetricsReplicationSourceSource.decrSizeOfLogQueue:(I)V
      20: return

  public void incrLogEditsRead();
    Code:
       0: aload_0
       1: lconst_1
       2: invokespecial #30                 // Method incrLogEditsRead:(J)V
       5: return

  public void incrLogEditsFiltered(long);
    Code:
       0: aload_0
       1: getfield      #11                 // Field singleSourceSource:Lorg/apache/hadoop/hbase/replication/regionserver/MetricsReplicationSourceSource;
       4: lload_1
       5: invokeinterface #31,  3           // InterfaceMethod org/apache/hadoop/hbase/replication/regionserver/MetricsReplicationSourceSource.incrLogEditsFiltered:(J)V
      10: aload_0
      11: getfield      #13                 // Field globalSourceSource:Lorg/apache/hadoop/hbase/replication/regionserver/MetricsReplicationSourceSource;
      14: lload_1
      15: invokeinterface #31,  3           // InterfaceMethod org/apache/hadoop/hbase/replication/regionserver/MetricsReplicationSourceSource.incrLogEditsFiltered:(J)V
      20: return

  public void incrLogEditsFiltered();
    Code:
       0: aload_0
       1: lconst_1
       2: invokevirtual #32                 // Method incrLogEditsFiltered:(J)V
       5: return

  public void shipBatch(long, int);
    Code:
       0: aload_0
       1: getfield      #11                 // Field singleSourceSource:Lorg/apache/hadoop/hbase/replication/regionserver/MetricsReplicationSourceSource;
       4: iconst_1
       5: invokeinterface #33,  2           // InterfaceMethod org/apache/hadoop/hbase/replication/regionserver/MetricsReplicationSourceSource.incrBatchesShipped:(I)V
      10: aload_0
      11: getfield      #13                 // Field globalSourceSource:Lorg/apache/hadoop/hbase/replication/regionserver/MetricsReplicationSourceSource;
      14: iconst_1
      15: invokeinterface #33,  2           // InterfaceMethod org/apache/hadoop/hbase/replication/regionserver/MetricsReplicationSourceSource.incrBatchesShipped:(I)V
      20: aload_0
      21: getfield      #11                 // Field singleSourceSource:Lorg/apache/hadoop/hbase/replication/regionserver/MetricsReplicationSourceSource;
      24: lload_1
      25: invokeinterface #34,  3           // InterfaceMethod org/apache/hadoop/hbase/replication/regionserver/MetricsReplicationSourceSource.incrOpsShipped:(J)V
      30: aload_0
      31: getfield      #13                 // Field globalSourceSource:Lorg/apache/hadoop/hbase/replication/regionserver/MetricsReplicationSourceSource;
      34: lload_1
      35: invokeinterface #34,  3           // InterfaceMethod org/apache/hadoop/hbase/replication/regionserver/MetricsReplicationSourceSource.incrOpsShipped:(J)V
      40: aload_0
      41: getfield      #11                 // Field singleSourceSource:Lorg/apache/hadoop/hbase/replication/regionserver/MetricsReplicationSourceSource;
      44: iload_3
      45: i2l
      46: invokeinterface #35,  3           // InterfaceMethod org/apache/hadoop/hbase/replication/regionserver/MetricsReplicationSourceSource.incrShippedBytes:(J)V
      51: aload_0
      52: getfield      #13                 // Field globalSourceSource:Lorg/apache/hadoop/hbase/replication/regionserver/MetricsReplicationSourceSource;
      55: iload_3
      56: i2l
      57: invokeinterface #35,  3           // InterfaceMethod org/apache/hadoop/hbase/replication/regionserver/MetricsReplicationSourceSource.incrShippedBytes:(J)V
      62: return

  public long getEditsFiltered();
    Code:
       0: aload_0
       1: getfield      #11                 // Field singleSourceSource:Lorg/apache/hadoop/hbase/replication/regionserver/MetricsReplicationSourceSource;
       4: invokeinterface #36,  1           // InterfaceMethod org/apache/hadoop/hbase/replication/regionserver/MetricsReplicationSourceSource.getEditsFiltered:()J
       9: lreturn

  public long getReplicableEdits();
    Code:
       0: aload_0
       1: getfield      #11                 // Field singleSourceSource:Lorg/apache/hadoop/hbase/replication/regionserver/MetricsReplicationSourceSource;
       4: invokeinterface #37,  1           // InterfaceMethod org/apache/hadoop/hbase/replication/regionserver/MetricsReplicationSourceSource.getWALEditsRead:()J
       9: aload_0
      10: getfield      #11                 // Field singleSourceSource:Lorg/apache/hadoop/hbase/replication/regionserver/MetricsReplicationSourceSource;
      13: invokeinterface #36,  1           // InterfaceMethod org/apache/hadoop/hbase/replication/regionserver/MetricsReplicationSourceSource.getEditsFiltered:()J
      18: lsub
      19: lreturn

  public long getOpsShipped();
    Code:
       0: aload_0
       1: getfield      #11                 // Field singleSourceSource:Lorg/apache/hadoop/hbase/replication/regionserver/MetricsReplicationSourceSource;
       4: invokeinterface #38,  1           // InterfaceMethod org/apache/hadoop/hbase/replication/regionserver/MetricsReplicationSourceSource.getShippedOps:()J
       9: lreturn

  public void shipBatch(long, int, long);
    Code:
       0: aload_0
       1: lload_1
       2: iload_3
       3: invokevirtual #39                 // Method shipBatch:(JI)V
       6: aload_0
       7: getfield      #11                 // Field singleSourceSource:Lorg/apache/hadoop/hbase/replication/regionserver/MetricsReplicationSourceSource;
      10: lload         4
      12: invokeinterface #40,  3           // InterfaceMethod org/apache/hadoop/hbase/replication/regionserver/MetricsReplicationSourceSource.incrHFilesShipped:(J)V
      17: aload_0
      18: getfield      #13                 // Field globalSourceSource:Lorg/apache/hadoop/hbase/replication/regionserver/MetricsReplicationSourceSource;
      21: lload         4
      23: invokeinterface #40,  3           // InterfaceMethod org/apache/hadoop/hbase/replication/regionserver/MetricsReplicationSourceSource.incrHFilesShipped:(J)V
      28: return

  public void incrLogReadInBytes(long);
    Code:
       0: aload_0
       1: getfield      #11                 // Field singleSourceSource:Lorg/apache/hadoop/hbase/replication/regionserver/MetricsReplicationSourceSource;
       4: lload_1
       5: invokeinterface #41,  3           // InterfaceMethod org/apache/hadoop/hbase/replication/regionserver/MetricsReplicationSourceSource.incrLogReadInBytes:(J)V
      10: aload_0
      11: getfield      #13                 // Field globalSourceSource:Lorg/apache/hadoop/hbase/replication/regionserver/MetricsReplicationSourceSource;
      14: lload_1
      15: invokeinterface #41,  3           // InterfaceMethod org/apache/hadoop/hbase/replication/regionserver/MetricsReplicationSourceSource.incrLogReadInBytes:(J)V
      20: return

  public void clear();
    Code:
       0: aload_0
       1: getfield      #11                 // Field singleSourceSource:Lorg/apache/hadoop/hbase/replication/regionserver/MetricsReplicationSourceSource;
       4: invokeinterface #42,  1           // InterfaceMethod org/apache/hadoop/hbase/replication/regionserver/MetricsReplicationSourceSource.getSizeOfLogQueue:()I
       9: istore_1
      10: aload_0
      11: getfield      #13                 // Field globalSourceSource:Lorg/apache/hadoop/hbase/replication/regionserver/MetricsReplicationSourceSource;
      14: iload_1
      15: invokeinterface #28,  2           // InterfaceMethod org/apache/hadoop/hbase/replication/regionserver/MetricsReplicationSourceSource.decrSizeOfLogQueue:(I)V
      20: aload_0
      21: getfield      #11                 // Field singleSourceSource:Lorg/apache/hadoop/hbase/replication/regionserver/MetricsReplicationSourceSource;
      24: iload_1
      25: invokeinterface #28,  2           // InterfaceMethod org/apache/hadoop/hbase/replication/regionserver/MetricsReplicationSourceSource.decrSizeOfLogQueue:(I)V
      30: aload_0
      31: getfield      #11                 // Field singleSourceSource:Lorg/apache/hadoop/hbase/replication/regionserver/MetricsReplicationSourceSource;
      34: invokeinterface #43,  1           // InterfaceMethod org/apache/hadoop/hbase/replication/regionserver/MetricsReplicationSourceSource.clear:()V
      39: aload_0
      40: getfield      #13                 // Field globalSourceSource:Lorg/apache/hadoop/hbase/replication/regionserver/MetricsReplicationSourceSource;
      43: aload_0
      44: getfield      #6                  // Field lastHFileRefsQueueSize:J
      47: invokeinterface #44,  3           // InterfaceMethod org/apache/hadoop/hbase/replication/regionserver/MetricsReplicationSourceSource.decrSizeOfHFileRefsQueue:(J)V
      52: aload_0
      53: getfield      #4                  // Field lastShippedTimeStamps:Ljava/util/Map;
      56: invokeinterface #45,  1           // InterfaceMethod java/util/Map.clear:()V
      61: aload_0
      62: lconst_0
      63: putfield      #6                  // Field lastHFileRefsQueueSize:J
      66: aload_0
      67: lconst_0
      68: putfield      #46                 // Field timeStampNextToReplicate:J
      71: return

  public java.lang.Long getAgeOfLastShippedOp();
    Code:
       0: aload_0
       1: getfield      #11                 // Field singleSourceSource:Lorg/apache/hadoop/hbase/replication/regionserver/MetricsReplicationSourceSource;
       4: invokeinterface #47,  1           // InterfaceMethod org/apache/hadoop/hbase/replication/regionserver/MetricsReplicationSourceSource.getLastShippedAge:()J
       9: invokestatic  #17                 // Method java/lang/Long.valueOf:(J)Ljava/lang/Long;
      12: areturn

  public int getSizeOfLogQueue();
    Code:
       0: aload_0
       1: getfield      #11                 // Field singleSourceSource:Lorg/apache/hadoop/hbase/replication/regionserver/MetricsReplicationSourceSource;
       4: invokeinterface #42,  1           // InterfaceMethod org/apache/hadoop/hbase/replication/regionserver/MetricsReplicationSourceSource.getSizeOfLogQueue:()I
       9: ireturn

  public long getTimeStampOfLastShippedOp();
    Code:
       0: aload_0
       1: invokevirtual #48                 // Method getTimestampOfLastShippedOp:()J
       4: lreturn

  public long getTimestampOfLastShippedOp();
    Code:
       0: lconst_0
       1: lstore_1
       2: aload_0
       3: getfield      #4                  // Field lastShippedTimeStamps:Ljava/util/Map;
       6: invokeinterface #49,  1           // InterfaceMethod java/util/Map.values:()Ljava/util/Collection;
      11: invokeinterface #50,  1           // InterfaceMethod java/util/Collection.iterator:()Ljava/util/Iterator;
      16: astore_3
      17: aload_3
      18: invokeinterface #51,  1           // InterfaceMethod java/util/Iterator.hasNext:()Z
      23: ifeq          53
      26: aload_3
      27: invokeinterface #52,  1           // InterfaceMethod java/util/Iterator.next:()Ljava/lang/Object;
      32: checkcast     #24                 // class java/lang/Long
      35: invokevirtual #25                 // Method java/lang/Long.longValue:()J
      38: lstore        4
      40: lload         4
      42: lload_1
      43: lcmp
      44: ifle          50
      47: lload         4
      49: lstore_1
      50: goto          17
      53: lload_1
      54: lreturn

  public long getTimeStampNextToReplicate();
    Code:
       0: aload_0
       1: getfield      #46                 // Field timeStampNextToReplicate:J
       4: lreturn

  public void setTimeStampNextToReplicate(long);
    Code:
       0: aload_0
       1: lload_1
       2: putfield      #46                 // Field timeStampNextToReplicate:J
       5: return

  public long getReplicationDelay();
    Code:
       0: aload_0
       1: invokevirtual #48                 // Method getTimestampOfLastShippedOp:()J
       4: aload_0
       5: getfield      #46                 // Field timeStampNextToReplicate:J
       8: lcmp
       9: iflt          14
      12: lconst_0
      13: lreturn
      14: invokestatic  #15                 // Method org/apache/hadoop/hbase/util/EnvironmentEdgeManager.currentTime:()J
      17: aload_0
      18: getfield      #46                 // Field timeStampNextToReplicate:J
      21: lsub
      22: lreturn

  public java.lang.String getPeerID();
    Code:
       0: aload_0
       1: getfield      #7                  // Field id:Ljava/lang/String;
       4: areturn

  public void incrSizeOfHFileRefsQueue(long);
    Code:
       0: aload_0
       1: getfield      #11                 // Field singleSourceSource:Lorg/apache/hadoop/hbase/replication/regionserver/MetricsReplicationSourceSource;
       4: lload_1
       5: invokeinterface #53,  3           // InterfaceMethod org/apache/hadoop/hbase/replication/regionserver/MetricsReplicationSourceSource.incrSizeOfHFileRefsQueue:(J)V
      10: aload_0
      11: getfield      #13                 // Field globalSourceSource:Lorg/apache/hadoop/hbase/replication/regionserver/MetricsReplicationSourceSource;
      14: lload_1
      15: invokeinterface #53,  3           // InterfaceMethod org/apache/hadoop/hbase/replication/regionserver/MetricsReplicationSourceSource.incrSizeOfHFileRefsQueue:(J)V
      20: aload_0
      21: lload_1
      22: putfield      #6                  // Field lastHFileRefsQueueSize:J
      25: return

  public void decrSizeOfHFileRefsQueue(int);
    Code:
       0: aload_0
       1: getfield      #11                 // Field singleSourceSource:Lorg/apache/hadoop/hbase/replication/regionserver/MetricsReplicationSourceSource;
       4: iload_1
       5: i2l
       6: invokeinterface #44,  3           // InterfaceMethod org/apache/hadoop/hbase/replication/regionserver/MetricsReplicationSourceSource.decrSizeOfHFileRefsQueue:(J)V
      11: aload_0
      12: getfield      #13                 // Field globalSourceSource:Lorg/apache/hadoop/hbase/replication/regionserver/MetricsReplicationSourceSource;
      15: iload_1
      16: i2l
      17: invokeinterface #44,  3           // InterfaceMethod org/apache/hadoop/hbase/replication/regionserver/MetricsReplicationSourceSource.decrSizeOfHFileRefsQueue:(J)V
      22: aload_0
      23: dup
      24: getfield      #6                  // Field lastHFileRefsQueueSize:J
      27: iload_1
      28: i2l
      29: lsub
      30: putfield      #6                  // Field lastHFileRefsQueueSize:J
      33: aload_0
      34: getfield      #6                  // Field lastHFileRefsQueueSize:J
      37: lconst_0
      38: lcmp
      39: ifge          47
      42: aload_0
      43: lconst_0
      44: putfield      #6                  // Field lastHFileRefsQueueSize:J
      47: return

  public void incrUnknownFileLengthForClosedWAL();
    Code:
       0: aload_0
       1: getfield      #11                 // Field singleSourceSource:Lorg/apache/hadoop/hbase/replication/regionserver/MetricsReplicationSourceSource;
       4: invokeinterface #54,  1           // InterfaceMethod org/apache/hadoop/hbase/replication/regionserver/MetricsReplicationSourceSource.incrUnknownFileLengthForClosedWAL:()V
       9: aload_0
      10: getfield      #13                 // Field globalSourceSource:Lorg/apache/hadoop/hbase/replication/regionserver/MetricsReplicationSourceSource;
      13: invokeinterface #54,  1           // InterfaceMethod org/apache/hadoop/hbase/replication/regionserver/MetricsReplicationSourceSource.incrUnknownFileLengthForClosedWAL:()V
      18: return

  public void incrUncleanlyClosedWALs();
    Code:
       0: aload_0
       1: getfield      #11                 // Field singleSourceSource:Lorg/apache/hadoop/hbase/replication/regionserver/MetricsReplicationSourceSource;
       4: invokeinterface #55,  1           // InterfaceMethod org/apache/hadoop/hbase/replication/regionserver/MetricsReplicationSourceSource.incrUncleanlyClosedWALs:()V
       9: aload_0
      10: getfield      #13                 // Field globalSourceSource:Lorg/apache/hadoop/hbase/replication/regionserver/MetricsReplicationSourceSource;
      13: invokeinterface #55,  1           // InterfaceMethod org/apache/hadoop/hbase/replication/regionserver/MetricsReplicationSourceSource.incrUncleanlyClosedWALs:()V
      18: return

  public void incrBytesSkippedInUncleanlyClosedWALs(long);
    Code:
       0: aload_0
       1: getfield      #11                 // Field singleSourceSource:Lorg/apache/hadoop/hbase/replication/regionserver/MetricsReplicationSourceSource;
       4: lload_1
       5: invokeinterface #56,  3           // InterfaceMethod org/apache/hadoop/hbase/replication/regionserver/MetricsReplicationSourceSource.incrBytesSkippedInUncleanlyClosedWALs:(J)V
      10: aload_0
      11: getfield      #13                 // Field globalSourceSource:Lorg/apache/hadoop/hbase/replication/regionserver/MetricsReplicationSourceSource;
      14: lload_1
      15: invokeinterface #56,  3           // InterfaceMethod org/apache/hadoop/hbase/replication/regionserver/MetricsReplicationSourceSource.incrBytesSkippedInUncleanlyClosedWALs:(J)V
      20: return

  public void incrRestartedWALReading();
    Code:
       0: aload_0
       1: getfield      #11                 // Field singleSourceSource:Lorg/apache/hadoop/hbase/replication/regionserver/MetricsReplicationSourceSource;
       4: invokeinterface #57,  1           // InterfaceMethod org/apache/hadoop/hbase/replication/regionserver/MetricsReplicationSourceSource.incrRestartedWALReading:()V
       9: aload_0
      10: getfield      #13                 // Field globalSourceSource:Lorg/apache/hadoop/hbase/replication/regionserver/MetricsReplicationSourceSource;
      13: invokeinterface #57,  1           // InterfaceMethod org/apache/hadoop/hbase/replication/regionserver/MetricsReplicationSourceSource.incrRestartedWALReading:()V
      18: return

  public void incrRepeatedFileBytes(long);
    Code:
       0: aload_0
       1: getfield      #11                 // Field singleSourceSource:Lorg/apache/hadoop/hbase/replication/regionserver/MetricsReplicationSourceSource;
       4: lload_1
       5: invokeinterface #58,  3           // InterfaceMethod org/apache/hadoop/hbase/replication/regionserver/MetricsReplicationSourceSource.incrRepeatedFileBytes:(J)V
      10: aload_0
      11: getfield      #13                 // Field globalSourceSource:Lorg/apache/hadoop/hbase/replication/regionserver/MetricsReplicationSourceSource;
      14: lload_1
      15: invokeinterface #58,  3           // InterfaceMethod org/apache/hadoop/hbase/replication/regionserver/MetricsReplicationSourceSource.incrRepeatedFileBytes:(J)V
      20: return

  public void incrCompletedWAL();
    Code:
       0: aload_0
       1: getfield      #11                 // Field singleSourceSource:Lorg/apache/hadoop/hbase/replication/regionserver/MetricsReplicationSourceSource;
       4: invokeinterface #59,  1           // InterfaceMethod org/apache/hadoop/hbase/replication/regionserver/MetricsReplicationSourceSource.incrCompletedWAL:()V
       9: aload_0
      10: getfield      #13                 // Field globalSourceSource:Lorg/apache/hadoop/hbase/replication/regionserver/MetricsReplicationSourceSource;
      13: invokeinterface #59,  1           // InterfaceMethod org/apache/hadoop/hbase/replication/regionserver/MetricsReplicationSourceSource.incrCompletedWAL:()V
      18: return

  public void incrCompletedRecoveryQueue();
    Code:
       0: aload_0
       1: getfield      #11                 // Field singleSourceSource:Lorg/apache/hadoop/hbase/replication/regionserver/MetricsReplicationSourceSource;
       4: invokeinterface #60,  1           // InterfaceMethod org/apache/hadoop/hbase/replication/regionserver/MetricsReplicationSourceSource.incrCompletedRecoveryQueue:()V
       9: aload_0
      10: getfield      #13                 // Field globalSourceSource:Lorg/apache/hadoop/hbase/replication/regionserver/MetricsReplicationSourceSource;
      13: invokeinterface #60,  1           // InterfaceMethod org/apache/hadoop/hbase/replication/regionserver/MetricsReplicationSourceSource.incrCompletedRecoveryQueue:()V
      18: return

  public void incrFailedRecoveryQueue();
    Code:
       0: aload_0
       1: getfield      #13                 // Field globalSourceSource:Lorg/apache/hadoop/hbase/replication/regionserver/MetricsReplicationSourceSource;
       4: invokeinterface #61,  1           // InterfaceMethod org/apache/hadoop/hbase/replication/regionserver/MetricsReplicationSourceSource.incrFailedRecoveryQueue:()V
       9: return

  public void init();
    Code:
       0: aload_0
       1: getfield      #11                 // Field singleSourceSource:Lorg/apache/hadoop/hbase/replication/regionserver/MetricsReplicationSourceSource;
       4: invokeinterface #62,  1           // InterfaceMethod org/apache/hadoop/hbase/replication/regionserver/MetricsReplicationSourceSource.init:()V
       9: aload_0
      10: getfield      #13                 // Field globalSourceSource:Lorg/apache/hadoop/hbase/replication/regionserver/MetricsReplicationSourceSource;
      13: invokeinterface #62,  1           // InterfaceMethod org/apache/hadoop/hbase/replication/regionserver/MetricsReplicationSourceSource.init:()V
      18: return

  public void setGauge(java.lang.String, long);
    Code:
       0: aload_0
       1: getfield      #11                 // Field singleSourceSource:Lorg/apache/hadoop/hbase/replication/regionserver/MetricsReplicationSourceSource;
       4: aload_1
       5: lload_2
       6: invokeinterface #63,  4           // InterfaceMethod org/apache/hadoop/hbase/replication/regionserver/MetricsReplicationSourceSource.setGauge:(Ljava/lang/String;J)V
      11: aload_0
      12: getfield      #13                 // Field globalSourceSource:Lorg/apache/hadoop/hbase/replication/regionserver/MetricsReplicationSourceSource;
      15: aload_1
      16: lload_2
      17: invokeinterface #63,  4           // InterfaceMethod org/apache/hadoop/hbase/replication/regionserver/MetricsReplicationSourceSource.setGauge:(Ljava/lang/String;J)V
      22: return

  public void incGauge(java.lang.String, long);
    Code:
       0: aload_0
       1: getfield      #11                 // Field singleSourceSource:Lorg/apache/hadoop/hbase/replication/regionserver/MetricsReplicationSourceSource;
       4: aload_1
       5: lload_2
       6: invokeinterface #64,  4           // InterfaceMethod org/apache/hadoop/hbase/replication/regionserver/MetricsReplicationSourceSource.incGauge:(Ljava/lang/String;J)V
      11: aload_0
      12: getfield      #13                 // Field globalSourceSource:Lorg/apache/hadoop/hbase/replication/regionserver/MetricsReplicationSourceSource;
      15: aload_1
      16: lload_2
      17: invokeinterface #64,  4           // InterfaceMethod org/apache/hadoop/hbase/replication/regionserver/MetricsReplicationSourceSource.incGauge:(Ljava/lang/String;J)V
      22: return

  public void decGauge(java.lang.String, long);
    Code:
       0: aload_0
       1: getfield      #11                 // Field singleSourceSource:Lorg/apache/hadoop/hbase/replication/regionserver/MetricsReplicationSourceSource;
       4: aload_1
       5: lload_2
       6: invokeinterface #65,  4           // InterfaceMethod org/apache/hadoop/hbase/replication/regionserver/MetricsReplicationSourceSource.decGauge:(Ljava/lang/String;J)V
      11: aload_0
      12: getfield      #13                 // Field globalSourceSource:Lorg/apache/hadoop/hbase/replication/regionserver/MetricsReplicationSourceSource;
      15: aload_1
      16: lload_2
      17: invokeinterface #65,  4           // InterfaceMethod org/apache/hadoop/hbase/replication/regionserver/MetricsReplicationSourceSource.decGauge:(Ljava/lang/String;J)V
      22: return

  public void removeMetric(java.lang.String);
    Code:
       0: aload_0
       1: getfield      #11                 // Field singleSourceSource:Lorg/apache/hadoop/hbase/replication/regionserver/MetricsReplicationSourceSource;
       4: aload_1
       5: invokeinterface #66,  2           // InterfaceMethod org/apache/hadoop/hbase/replication/regionserver/MetricsReplicationSourceSource.removeMetric:(Ljava/lang/String;)V
      10: aload_0
      11: getfield      #13                 // Field globalSourceSource:Lorg/apache/hadoop/hbase/replication/regionserver/MetricsReplicationSourceSource;
      14: aload_1
      15: invokeinterface #66,  2           // InterfaceMethod org/apache/hadoop/hbase/replication/regionserver/MetricsReplicationSourceSource.removeMetric:(Ljava/lang/String;)V
      20: return

  public void incCounters(java.lang.String, long);
    Code:
       0: aload_0
       1: getfield      #11                 // Field singleSourceSource:Lorg/apache/hadoop/hbase/replication/regionserver/MetricsReplicationSourceSource;
       4: aload_1
       5: lload_2
       6: invokeinterface #67,  4           // InterfaceMethod org/apache/hadoop/hbase/replication/regionserver/MetricsReplicationSourceSource.incCounters:(Ljava/lang/String;J)V
      11: aload_0
      12: getfield      #13                 // Field globalSourceSource:Lorg/apache/hadoop/hbase/replication/regionserver/MetricsReplicationSourceSource;
      15: aload_1
      16: lload_2
      17: invokeinterface #67,  4           // InterfaceMethod org/apache/hadoop/hbase/replication/regionserver/MetricsReplicationSourceSource.incCounters:(Ljava/lang/String;J)V
      22: return

  public void updateHistogram(java.lang.String, long);
    Code:
       0: aload_0
       1: getfield      #11                 // Field singleSourceSource:Lorg/apache/hadoop/hbase/replication/regionserver/MetricsReplicationSourceSource;
       4: aload_1
       5: lload_2
       6: invokeinterface #68,  4           // InterfaceMethod org/apache/hadoop/hbase/replication/regionserver/MetricsReplicationSourceSource.updateHistogram:(Ljava/lang/String;J)V
      11: aload_0
      12: getfield      #13                 // Field globalSourceSource:Lorg/apache/hadoop/hbase/replication/regionserver/MetricsReplicationSourceSource;
      15: aload_1
      16: lload_2
      17: invokeinterface #68,  4           // InterfaceMethod org/apache/hadoop/hbase/replication/regionserver/MetricsReplicationSourceSource.updateHistogram:(Ljava/lang/String;J)V
      22: return

  public java.lang.String getMetricsContext();
    Code:
       0: aload_0
       1: getfield      #13                 // Field globalSourceSource:Lorg/apache/hadoop/hbase/replication/regionserver/MetricsReplicationSourceSource;
       4: invokeinterface #69,  1           // InterfaceMethod org/apache/hadoop/hbase/replication/regionserver/MetricsReplicationSourceSource.getMetricsContext:()Ljava/lang/String;
       9: areturn

  public java.lang.String getMetricsDescription();
    Code:
       0: aload_0
       1: getfield      #13                 // Field globalSourceSource:Lorg/apache/hadoop/hbase/replication/regionserver/MetricsReplicationSourceSource;
       4: invokeinterface #70,  1           // InterfaceMethod org/apache/hadoop/hbase/replication/regionserver/MetricsReplicationSourceSource.getMetricsDescription:()Ljava/lang/String;
       9: areturn

  public java.lang.String getMetricsJmxContext();
    Code:
       0: aload_0
       1: getfield      #13                 // Field globalSourceSource:Lorg/apache/hadoop/hbase/replication/regionserver/MetricsReplicationSourceSource;
       4: invokeinterface #71,  1           // InterfaceMethod org/apache/hadoop/hbase/replication/regionserver/MetricsReplicationSourceSource.getMetricsJmxContext:()Ljava/lang/String;
       9: areturn

  public java.lang.String getMetricsName();
    Code:
       0: aload_0
       1: getfield      #13                 // Field globalSourceSource:Lorg/apache/hadoop/hbase/replication/regionserver/MetricsReplicationSourceSource;
       4: invokeinterface #72,  1           // InterfaceMethod org/apache/hadoop/hbase/replication/regionserver/MetricsReplicationSourceSource.getMetricsName:()Ljava/lang/String;
       9: areturn

  public java.util.Map<java.lang.String, org.apache.hadoop.hbase.replication.regionserver.MetricsReplicationSourceSource> getSingleSourceSourceByTable();
    Code:
       0: aload_0
       1: getfield      #14                 // Field singleSourceSourceByTable:Ljava/util/Map;
       4: areturn

  static {};
    Code:
       0: ldc           #73                 // class org/apache/hadoop/hbase/replication/regionserver/MetricsSource
       2: invokestatic  #74                 // Method org/slf4j/LoggerFactory.getLogger:(Ljava/lang/Class;)Lorg/slf4j/Logger;
       5: putstatic     #75                 // Field LOG:Lorg/slf4j/Logger;
       8: return
}
