Compiled from "MetricsStochasticBalancerSourceImpl.java"
public class org.apache.hadoop.hbase.master.balancer.MetricsStochasticBalancerSourceImpl extends org.apache.hadoop.hbase.master.balancer.MetricsBalancerSourceImpl implements org.apache.hadoop.hbase.master.balancer.MetricsStochasticBalancerSource {
  public org.apache.hadoop.hbase.master.balancer.MetricsStochasticBalancerSourceImpl();
    Code:
       0: aload_0
       1: invokespecial #2                  // Method org/apache/hadoop/hbase/master/balancer/MetricsBalancerSourceImpl."<init>":()V
       4: aload_0
       5: sipush        1000
       8: putfield      #3                  // Field metricsSize:I
      11: aload_0
      12: aload_0
      13: getfield      #3                  // Field metricsSize:I
      16: invokestatic  #4                  // Method calcMruCap:(I)I
      19: putfield      #1                  // Field mruCap:I
      22: aload_0
      23: new           #5                  // class org/apache/hadoop/hbase/master/balancer/MetricsStochasticBalancerSourceImpl$1
      26: dup
      27: aload_0
      28: aload_0
      29: getfield      #1                  // Field mruCap:I
      32: ldc           #7                  // float 0.75f
      34: iconst_1
      35: invokespecial #8                  // Method org/apache/hadoop/hbase/master/balancer/MetricsStochasticBalancerSourceImpl$1."<init>":(Lorg/apache/hadoop/hbase/master/balancer/MetricsStochasticBalancerSourceImpl;IFZ)V
      38: putfield      #9                  // Field stochasticCosts:Ljava/util/Map;
      41: aload_0
      42: new           #10                 // class java/util/concurrent/ConcurrentHashMap
      45: dup
      46: invokespecial #11                 // Method java/util/concurrent/ConcurrentHashMap."<init>":()V
      49: putfield      #12                 // Field costFunctionDescs:Ljava/util/Map;
      52: return

  public void updateMetricsSize(int);
    Code:
       0: iload_1
       1: ifle          17
       4: aload_0
       5: iload_1
       6: putfield      #3                  // Field metricsSize:I
       9: aload_0
      10: iload_1
      11: invokestatic  #4                  // Method calcMruCap:(I)I
      14: putfield      #1                  // Field mruCap:I
      17: return

  public void updateStochasticCost(java.lang.String, java.lang.String, java.lang.String, java.lang.Double);
    Code:
       0: aload_1
       1: ifnull        13
       4: aload_2
       5: ifnull        13
       8: aload         4
      10: ifnonnull     14
      13: return
      14: aload_3
      15: ifnull        30
      18: aload_0
      19: getfield      #12                 // Field costFunctionDescs:Ljava/util/Map;
      22: aload_2
      23: aload_3
      24: invokeinterface #14,  3           // InterfaceMethod java/util/Map.put:(Ljava/lang/Object;Ljava/lang/Object;)Ljava/lang/Object;
      29: pop
      30: aload_0
      31: getfield      #9                  // Field stochasticCosts:Ljava/util/Map;
      34: dup
      35: astore        5
      37: monitorenter
      38: aload_0
      39: getfield      #9                  // Field stochasticCosts:Ljava/util/Map;
      42: aload_1
      43: invokeinterface #15,  2           // InterfaceMethod java/util/Map.get:(Ljava/lang/Object;)Ljava/lang/Object;
      48: checkcast     #16                 // class java/util/Map
      51: astore        6
      53: aload         6
      55: ifnonnull     67
      58: new           #10                 // class java/util/concurrent/ConcurrentHashMap
      61: dup
      62: invokespecial #11                 // Method java/util/concurrent/ConcurrentHashMap."<init>":()V
      65: astore        6
      67: aload         6
      69: aload_2
      70: aload         4
      72: invokeinterface #14,  3           // InterfaceMethod java/util/Map.put:(Ljava/lang/Object;Ljava/lang/Object;)Ljava/lang/Object;
      77: pop
      78: aload_0
      79: getfield      #9                  // Field stochasticCosts:Ljava/util/Map;
      82: aload_1
      83: aload         6
      85: invokeinterface #14,  3           // InterfaceMethod java/util/Map.put:(Ljava/lang/Object;Ljava/lang/Object;)Ljava/lang/Object;
      90: pop
      91: aload         5
      93: monitorexit
      94: goto          105
      97: astore        7
      99: aload         5
     101: monitorexit
     102: aload         7
     104: athrow
     105: return
    Exception table:
       from    to  target type
          38    94    97   any
          97   102    97   any

  public void getMetrics(org.apache.hadoop.metrics2.MetricsCollector, boolean);
    Code:
       0: aload_1
       1: aload_0
       2: getfield      #17                 // Field metricsName:Ljava/lang/String;
       5: invokeinterface #18,  2           // InterfaceMethod org/apache/hadoop/metrics2/MetricsCollector.addRecord:(Ljava/lang/String;)Lorg/apache/hadoop/metrics2/MetricsRecordBuilder;
      10: astore_3
      11: aload_0
      12: getfield      #9                  // Field stochasticCosts:Ljava/util/Map;
      15: ifnull        238
      18: aload_0
      19: getfield      #9                  // Field stochasticCosts:Ljava/util/Map;
      22: dup
      23: astore        4
      25: monitorenter
      26: aload_0
      27: getfield      #9                  // Field stochasticCosts:Ljava/util/Map;
      30: invokeinterface #19,  1           // InterfaceMethod java/util/Map.entrySet:()Ljava/util/Set;
      35: invokeinterface #20,  1           // InterfaceMethod java/util/Set.iterator:()Ljava/util/Iterator;
      40: astore        5
      42: aload         5
      44: invokeinterface #21,  1           // InterfaceMethod java/util/Iterator.hasNext:()Z
      49: ifeq          224
      52: aload         5
      54: invokeinterface #22,  1           // InterfaceMethod java/util/Iterator.next:()Ljava/lang/Object;
      59: checkcast     #23                 // class java/util/Map$Entry
      62: astore        6
      64: aload         6
      66: invokeinterface #24,  1           // InterfaceMethod java/util/Map$Entry.getValue:()Ljava/lang/Object;
      71: checkcast     #16                 // class java/util/Map
      74: invokeinterface #19,  1           // InterfaceMethod java/util/Map.entrySet:()Ljava/util/Set;
      79: invokeinterface #20,  1           // InterfaceMethod java/util/Set.iterator:()Ljava/util/Iterator;
      84: astore        7
      86: aload         7
      88: invokeinterface #21,  1           // InterfaceMethod java/util/Iterator.hasNext:()Z
      93: ifeq          221
      96: aload         7
      98: invokeinterface #22,  1           // InterfaceMethod java/util/Iterator.next:()Ljava/lang/Object;
     103: checkcast     #23                 // class java/util/Map$Entry
     106: astore        8
     108: new           #25                 // class java/lang/StringBuilder
     111: dup
     112: invokespecial #26                 // Method java/lang/StringBuilder."<init>":()V
     115: aload         6
     117: invokeinterface #27,  1           // InterfaceMethod java/util/Map$Entry.getKey:()Ljava/lang/Object;
     122: checkcast     #28                 // class java/lang/String
     125: invokevirtual #29                 // Method java/lang/StringBuilder.append:(Ljava/lang/String;)Ljava/lang/StringBuilder;
     128: ldc           #30                 // String _
     130: invokevirtual #29                 // Method java/lang/StringBuilder.append:(Ljava/lang/String;)Ljava/lang/StringBuilder;
     133: aload         8
     135: invokeinterface #27,  1           // InterfaceMethod java/util/Map$Entry.getKey:()Ljava/lang/Object;
     140: checkcast     #28                 // class java/lang/String
     143: invokevirtual #29                 // Method java/lang/StringBuilder.append:(Ljava/lang/String;)Ljava/lang/StringBuilder;
     146: invokevirtual #31                 // Method java/lang/StringBuilder.toString:()Ljava/lang/String;
     149: astore        9
     151: aload         8
     153: invokeinterface #24,  1           // InterfaceMethod java/util/Map$Entry.getValue:()Ljava/lang/Object;
     158: checkcast     #32                 // class java/lang/Double
     161: astore        10
     163: aload_0
     164: getfield      #12                 // Field costFunctionDescs:Ljava/util/Map;
     167: aload         8
     169: invokeinterface #27,  1           // InterfaceMethod java/util/Map$Entry.getKey:()Ljava/lang/Object;
     174: invokeinterface #15,  2           // InterfaceMethod java/util/Map.get:(Ljava/lang/Object;)Ljava/lang/Object;
     179: checkcast     #28                 // class java/lang/String
     182: astore        11
     184: aload         11
     186: ifnonnull     201
     189: aload         8
     191: invokeinterface #27,  1           // InterfaceMethod java/util/Map$Entry.getKey:()Ljava/lang/Object;
     196: checkcast     #28                 // class java/lang/String
     199: astore        11
     201: aload_3
     202: aload         9
     204: aload         11
     206: invokestatic  #33                 // Method org/apache/hadoop/hbase/metrics/Interns.info:(Ljava/lang/String;Ljava/lang/String;)Lorg/apache/hadoop/metrics2/MetricsInfo;
     209: aload         10
     211: invokevirtual #34                 // Method java/lang/Double.doubleValue:()D
     214: invokevirtual #35                 // Method org/apache/hadoop/metrics2/MetricsRecordBuilder.addGauge:(Lorg/apache/hadoop/metrics2/MetricsInfo;D)Lorg/apache/hadoop/metrics2/MetricsRecordBuilder;
     217: pop
     218: goto          86
     221: goto          42
     224: aload         4
     226: monitorexit
     227: goto          238
     230: astore        12
     232: aload         4
     234: monitorexit
     235: aload         12
     237: athrow
     238: aload_0
     239: getfield      #36                 // Field metricsRegistry:Lorg/apache/hadoop/metrics2/lib/DynamicMetricsRegistry;
     242: aload_3
     243: iload_2
     244: invokevirtual #37                 // Method org/apache/hadoop/metrics2/lib/DynamicMetricsRegistry.snapshot:(Lorg/apache/hadoop/metrics2/MetricsRecordBuilder;Z)V
     247: return
    Exception table:
       from    to  target type
          26   227   230   any
         230   235   230   any

  static int access$000(org.apache.hadoop.hbase.master.balancer.MetricsStochasticBalancerSourceImpl);
    Code:
       0: aload_0
       1: getfield      #1                  // Field mruCap:I
       4: ireturn
}
