Compiled from "MetricsSnapshot.java"
public class org.apache.hadoop.hbase.master.MetricsSnapshot {
  public org.apache.hadoop.hbase.master.MetricsSnapshot();
    Code:
       0: aload_0
       1: invokespecial #1                  // Method java/lang/Object."<init>":()V
       4: aload_0
       5: ldc           #2                  // class org/apache/hadoop/hbase/master/MetricsSnapshotSource
       7: invokestatic  #3                  // Method org/apache/hadoop/hbase/CompatibilitySingletonFactory.getInstance:(Ljava/lang/Class;)Ljava/lang/Object;
      10: checkcast     #2                  // class org/apache/hadoop/hbase/master/MetricsSnapshotSource
      13: putfield      #4                  // Field source:Lorg/apache/hadoop/hbase/master/MetricsSnapshotSource;
      16: return

  public void addSnapshot(long);
    Code:
       0: aload_0
       1: getfield      #4                  // Field source:Lorg/apache/hadoop/hbase/master/MetricsSnapshotSource;
       4: lload_1
       5: invokeinterface #5,  3            // InterfaceMethod org/apache/hadoop/hbase/master/MetricsSnapshotSource.updateSnapshotTime:(J)V
      10: return

  public void addSnapshotRestore(long);
    Code:
       0: aload_0
       1: getfield      #4                  // Field source:Lorg/apache/hadoop/hbase/master/MetricsSnapshotSource;
       4: lload_1
       5: invokeinterface #6,  3            // InterfaceMethod org/apache/hadoop/hbase/master/MetricsSnapshotSource.updateSnapshotRestoreTime:(J)V
      10: return

  public void addSnapshotClone(long);
    Code:
       0: aload_0
       1: getfield      #4                  // Field source:Lorg/apache/hadoop/hbase/master/MetricsSnapshotSource;
       4: lload_1
       5: invokeinterface #7,  3            // InterfaceMethod org/apache/hadoop/hbase/master/MetricsSnapshotSource.updateSnapshotCloneTime:(J)V
      10: return
}
