Compiled from "MetricsMasterSourceFactoryImpl.java"
public class org.apache.hadoop.hbase.master.MetricsMasterSourceFactoryImpl implements org.apache.hadoop.hbase.master.MetricsMasterSourceFactory {
  public org.apache.hadoop.hbase.master.MetricsMasterSourceFactoryImpl();
    Code:
       0: aload_0
       1: invokespecial #1                  // Method java/lang/Object."<init>":()V
       4: return

  public synchronized org.apache.hadoop.hbase.master.MetricsMasterSource create(org.apache.hadoop.hbase.master.MetricsMasterWrapper);
    Code:
       0: getstatic     #2                  // Field org/apache/hadoop/hbase/master/MetricsMasterSourceFactoryImpl$FactoryStorage.INSTANCE:Lorg/apache/hadoop/hbase/master/MetricsMasterSourceFactoryImpl$FactoryStorage;
       3: getfield      #3                  // Field org/apache/hadoop/hbase/master/MetricsMasterSourceFactoryImpl$FactoryStorage.masterSource:Lorg/apache/hadoop/hbase/master/MetricsMasterSource;
       6: ifnonnull     23
       9: getstatic     #2                  // Field org/apache/hadoop/hbase/master/MetricsMasterSourceFactoryImpl$FactoryStorage.INSTANCE:Lorg/apache/hadoop/hbase/master/MetricsMasterSourceFactoryImpl$FactoryStorage;
      12: new           #4                  // class org/apache/hadoop/hbase/master/MetricsMasterSourceImpl
      15: dup
      16: aload_1
      17: invokespecial #5                  // Method org/apache/hadoop/hbase/master/MetricsMasterSourceImpl."<init>":(Lorg/apache/hadoop/hbase/master/MetricsMasterWrapper;)V
      20: putfield      #3                  // Field org/apache/hadoop/hbase/master/MetricsMasterSourceFactoryImpl$FactoryStorage.masterSource:Lorg/apache/hadoop/hbase/master/MetricsMasterSource;
      23: getstatic     #2                  // Field org/apache/hadoop/hbase/master/MetricsMasterSourceFactoryImpl$FactoryStorage.INSTANCE:Lorg/apache/hadoop/hbase/master/MetricsMasterSourceFactoryImpl$FactoryStorage;
      26: getfield      #3                  // Field org/apache/hadoop/hbase/master/MetricsMasterSourceFactoryImpl$FactoryStorage.masterSource:Lorg/apache/hadoop/hbase/master/MetricsMasterSource;
      29: areturn
}
