Compiled from "MetricsRegionServerSourceFactoryImpl.java"
public final class org.apache.hadoop.hbase.regionserver.MetricsRegionServerSourceFactoryImpl$FactoryStorage extends java.lang.Enum<org.apache.hadoop.hbase.regionserver.MetricsRegionServerSourceFactoryImpl$FactoryStorage> {
  public static final org.apache.hadoop.hbase.regionserver.MetricsRegionServerSourceFactoryImpl$FactoryStorage INSTANCE;

  public static org.apache.hadoop.hbase.regionserver.MetricsRegionServerSourceFactoryImpl$FactoryStorage[] values();
    Code:
       0: getstatic     #5                  // Field $VALUES:[Lorg/apache/hadoop/hbase/regionserver/MetricsRegionServerSourceFactoryImpl$FactoryStorage;
       3: invokevirtual #6                  // Method "[Lorg/apache/hadoop/hbase/regionserver/MetricsRegionServerSourceFactoryImpl$FactoryStorage;".clone:()Ljava/lang/Object;
       6: checkcast     #7                  // class "[Lorg/apache/hadoop/hbase/regionserver/MetricsRegionServerSourceFactoryImpl$FactoryStorage;"
       9: areturn

  public static org.apache.hadoop.hbase.regionserver.MetricsRegionServerSourceFactoryImpl$FactoryStorage valueOf(java.lang.String);
    Code:
       0: ldc           #8                  // class org/apache/hadoop/hbase/regionserver/MetricsRegionServerSourceFactoryImpl$FactoryStorage
       2: aload_0
       3: invokestatic  #9                  // Method java/lang/Enum.valueOf:(Ljava/lang/Class;Ljava/lang/String;)Ljava/lang/Enum;
       6: checkcast     #8                  // class org/apache/hadoop/hbase/regionserver/MetricsRegionServerSourceFactoryImpl$FactoryStorage
       9: areturn

  static java.lang.Object access$000(org.apache.hadoop.hbase.regionserver.MetricsRegionServerSourceFactoryImpl$FactoryStorage);
    Code:
       0: aload_0
       1: getfield      #4                  // Field aggLock:Ljava/lang/Object;
       4: areturn

  static org.apache.hadoop.hbase.regionserver.MetricsRegionAggregateSourceImpl access$100(org.apache.hadoop.hbase.regionserver.MetricsRegionServerSourceFactoryImpl$FactoryStorage);
    Code:
       0: aload_0
       1: getfield      #3                  // Field aggImpl:Lorg/apache/hadoop/hbase/regionserver/MetricsRegionAggregateSourceImpl;
       4: areturn

  static org.apache.hadoop.hbase.regionserver.MetricsRegionAggregateSourceImpl access$102(org.apache.hadoop.hbase.regionserver.MetricsRegionServerSourceFactoryImpl$FactoryStorage, org.apache.hadoop.hbase.regionserver.MetricsRegionAggregateSourceImpl);
    Code:
       0: aload_0
       1: aload_1
       2: dup_x1
       3: putfield      #3                  // Field aggImpl:Lorg/apache/hadoop/hbase/regionserver/MetricsRegionAggregateSourceImpl;
       6: areturn

  static org.apache.hadoop.hbase.regionserver.MetricsTableAggregateSourceImpl access$200(org.apache.hadoop.hbase.regionserver.MetricsRegionServerSourceFactoryImpl$FactoryStorage);
    Code:
       0: aload_0
       1: getfield      #2                  // Field tblAggImpl:Lorg/apache/hadoop/hbase/regionserver/MetricsTableAggregateSourceImpl;
       4: areturn

  static org.apache.hadoop.hbase.regionserver.MetricsTableAggregateSourceImpl access$202(org.apache.hadoop.hbase.regionserver.MetricsRegionServerSourceFactoryImpl$FactoryStorage, org.apache.hadoop.hbase.regionserver.MetricsTableAggregateSourceImpl);
    Code:
       0: aload_0
       1: aload_1
       2: dup_x1
       3: putfield      #2                  // Field tblAggImpl:Lorg/apache/hadoop/hbase/regionserver/MetricsTableAggregateSourceImpl;
       6: areturn

  static org.apache.hadoop.hbase.regionserver.MetricsHeapMemoryManagerSourceImpl access$300(org.apache.hadoop.hbase.regionserver.MetricsRegionServerSourceFactoryImpl$FactoryStorage);
    Code:
       0: aload_0
       1: getfield      #1                  // Field heapMemMngImpl:Lorg/apache/hadoop/hbase/regionserver/MetricsHeapMemoryManagerSourceImpl;
       4: areturn

  static org.apache.hadoop.hbase.regionserver.MetricsHeapMemoryManagerSourceImpl access$302(org.apache.hadoop.hbase.regionserver.MetricsRegionServerSourceFactoryImpl$FactoryStorage, org.apache.hadoop.hbase.regionserver.MetricsHeapMemoryManagerSourceImpl);
    Code:
       0: aload_0
       1: aload_1
       2: dup_x1
       3: putfield      #1                  // Field heapMemMngImpl:Lorg/apache/hadoop/hbase/regionserver/MetricsHeapMemoryManagerSourceImpl;
       6: areturn

  static {};
    Code:
       0: new           #8                  // class org/apache/hadoop/hbase/regionserver/MetricsRegionServerSourceFactoryImpl$FactoryStorage
       3: dup
       4: ldc           #13                 // String INSTANCE
       6: iconst_0
       7: invokespecial #14                 // Method "<init>":(Ljava/lang/String;I)V
      10: putstatic     #15                 // Field INSTANCE:Lorg/apache/hadoop/hbase/regionserver/MetricsRegionServerSourceFactoryImpl$FactoryStorage;
      13: iconst_1
      14: anewarray     #8                  // class org/apache/hadoop/hbase/regionserver/MetricsRegionServerSourceFactoryImpl$FactoryStorage
      17: dup
      18: iconst_0
      19: getstatic     #15                 // Field INSTANCE:Lorg/apache/hadoop/hbase/regionserver/MetricsRegionServerSourceFactoryImpl$FactoryStorage;
      22: aastore
      23: putstatic     #5                  // Field $VALUES:[Lorg/apache/hadoop/hbase/regionserver/MetricsRegionServerSourceFactoryImpl$FactoryStorage;
      26: return
}
