Compiled from "MetricsMasterFileSystem.java"
public class org.apache.hadoop.hbase.master.MetricsMasterFileSystem {
  public org.apache.hadoop.hbase.master.MetricsMasterFileSystem();
    Code:
       0: aload_0
       1: invokespecial #1                  // Method java/lang/Object."<init>":()V
       4: aload_0
       5: ldc           #2                  // class org/apache/hadoop/hbase/master/MetricsMasterFileSystemSource
       7: invokestatic  #3                  // Method org/apache/hadoop/hbase/CompatibilitySingletonFactory.getInstance:(Ljava/lang/Class;)Ljava/lang/Object;
      10: checkcast     #2                  // class org/apache/hadoop/hbase/master/MetricsMasterFileSystemSource
      13: putfield      #4                  // Field source:Lorg/apache/hadoop/hbase/master/MetricsMasterFileSystemSource;
      16: return

  public synchronized void addSplit(long, long);
    Code:
       0: aload_0
       1: getfield      #4                  // Field source:Lorg/apache/hadoop/hbase/master/MetricsMasterFileSystemSource;
       4: lload_1
       5: invokeinterface #5,  3            // InterfaceMethod org/apache/hadoop/hbase/master/MetricsMasterFileSystemSource.updateSplitTime:(J)V
      10: aload_0
      11: getfield      #4                  // Field source:Lorg/apache/hadoop/hbase/master/MetricsMasterFileSystemSource;
      14: lload_3
      15: invokeinterface #6,  3            // InterfaceMethod org/apache/hadoop/hbase/master/MetricsMasterFileSystemSource.updateSplitSize:(J)V
      20: return

  public synchronized void addMetaWALSplit(long, long);
    Code:
       0: aload_0
       1: getfield      #4                  // Field source:Lorg/apache/hadoop/hbase/master/MetricsMasterFileSystemSource;
       4: lload_1
       5: invokeinterface #7,  3            // InterfaceMethod org/apache/hadoop/hbase/master/MetricsMasterFileSystemSource.updateMetaWALSplitTime:(J)V
      10: aload_0
      11: getfield      #4                  // Field source:Lorg/apache/hadoop/hbase/master/MetricsMasterFileSystemSource;
      14: lload_3
      15: invokeinterface #8,  3            // InterfaceMethod org/apache/hadoop/hbase/master/MetricsMasterFileSystemSource.updateMetaWALSplitSize:(J)V
      20: return
}
