Compiled from "MiniZooKeeperCluster.java"
public class org.apache.hadoop.hbase.zookeeper.MiniZooKeeperCluster {
  public org.apache.hadoop.hbase.zookeeper.MiniZooKeeperCluster();
    Code:
       0: aload_0
       1: new           #1                  // class org/apache/hadoop/conf/Configuration
       4: dup
       5: invokespecial #2                  // Method org/apache/hadoop/conf/Configuration."<init>":()V
       8: invokespecial #3                  // Method "<init>":(Lorg/apache/hadoop/conf/Configuration;)V
      11: return

  public org.apache.hadoop.hbase.zookeeper.MiniZooKeeperCluster(org.apache.hadoop.conf.Configuration);
    Code:
       0: aload_0
       1: invokespecial #4                  // Method java/lang/Object."<init>":()V
       4: aload_0
       5: iconst_0
       6: putfield      #5                  // Field defaultClientPort:I
       9: aload_0
      10: iconst_0
      11: putfield      #6                  // Field tickTime:I
      14: aload_0
      15: iconst_0
      16: putfield      #7                  // Field started:Z
      19: aload_0
      20: aload_1
      21: putfield      #8                  // Field configuration:Lorg/apache/hadoop/conf/Configuration;
      24: aload_0
      25: iconst_m1
      26: putfield      #9                  // Field activeZKServerIndex:I
      29: aload_0
      30: new           #10                 // class java/util/ArrayList
      33: dup
      34: invokespecial #11                 // Method java/util/ArrayList."<init>":()V
      37: putfield      #12                 // Field zooKeeperServers:Ljava/util/List;
      40: aload_0
      41: new           #10                 // class java/util/ArrayList
      44: dup
      45: invokespecial #11                 // Method java/util/ArrayList."<init>":()V
      48: putfield      #13                 // Field clientPortList:Ljava/util/List;
      51: aload_0
      52: new           #10                 // class java/util/ArrayList
      55: dup
      56: invokespecial #11                 // Method java/util/ArrayList."<init>":()V
      59: putfield      #14                 // Field standaloneServerFactoryList:Ljava/util/List;
      62: aload_0
      63: aload_1
      64: ldc           #16                 // String zookeeper.session.timeout.localHBaseCluster
      66: sipush        30000
      69: invokevirtual #18                 // Method org/apache/hadoop/conf/Configuration.getInt:(Ljava/lang/String;I)I
      72: putfield      #19                 // Field connectionTimeout:I
      75: return

  public void addClientPort(int);
    Code:
       0: aload_0
       1: getfield      #13                 // Field clientPortList:Ljava/util/List;
       4: iload_1
       5: invokestatic  #20                 // Method java/lang/Integer.valueOf:(I)Ljava/lang/Integer;
       8: invokeinterface #21,  2           // InterfaceMethod java/util/List.add:(Ljava/lang/Object;)Z
      13: pop
      14: return

  public java.util.List<java.lang.Integer> getClientPortList();
    Code:
       0: aload_0
       1: getfield      #13                 // Field clientPortList:Ljava/util/List;
       4: areturn

  public void setDefaultClientPort(int);
    Code:
       0: iload_1
       1: ifgt          31
       4: new           #26                 // class java/lang/IllegalArgumentException
       7: dup
       8: new           #27                 // class java/lang/StringBuilder
      11: dup
      12: invokespecial #28                 // Method java/lang/StringBuilder."<init>":()V
      15: ldc           #29                 // String Invalid default ZK client port:
      17: invokevirtual #30                 // Method java/lang/StringBuilder.append:(Ljava/lang/String;)Ljava/lang/StringBuilder;
      20: iload_1
      21: invokevirtual #31                 // Method java/lang/StringBuilder.append:(I)Ljava/lang/StringBuilder;
      24: invokevirtual #32                 // Method java/lang/StringBuilder.toString:()Ljava/lang/String;
      27: invokespecial #33                 // Method java/lang/IllegalArgumentException."<init>":(Ljava/lang/String;)V
      30: athrow
      31: aload_0
      32: iload_1
      33: putfield      #5                  // Field defaultClientPort:I
      36: return

  public void setTickTime(int);
    Code:
       0: aload_0
       1: iload_1
       2: putfield      #6                  // Field tickTime:I
       5: return

  public int getBackupZooKeeperServerNum();
    Code:
       0: aload_0
       1: getfield      #12                 // Field zooKeeperServers:Ljava/util/List;
       4: invokeinterface #22,  1           // InterfaceMethod java/util/List.size:()I
       9: iconst_1
      10: isub
      11: ireturn

  public int getZooKeeperServerNum();
    Code:
       0: aload_0
       1: getfield      #12                 // Field zooKeeperServers:Ljava/util/List;
       4: invokeinterface #22,  1           // InterfaceMethod java/util/List.size:()I
       9: ireturn

  public int startup(java.io.File) throws java.io.IOException, java.lang.InterruptedException;
    Code:
       0: aload_0
       1: getfield      #13                 // Field clientPortList:Ljava/util/List;
       4: invokeinterface #22,  1           // InterfaceMethod java/util/List.size:()I
       9: istore_2
      10: iload_2
      11: ifne          16
      14: iconst_1
      15: istore_2
      16: aload_0
      17: aload_1
      18: iload_2
      19: invokevirtual #46                 // Method startup:(Ljava/io/File;I)I
      22: ireturn

  public int startup(java.io.File, int) throws java.io.IOException, java.lang.InterruptedException;
    Code:
       0: iload_2
       1: ifgt          6
       4: iconst_m1
       5: ireturn
       6: invokestatic  #47                 // Method setupTestEnv:()V
       9: aload_0
      10: invokevirtual #48                 // Method shutdown:()V
      13: iconst_m1
      14: istore_3
      15: iconst_0
      16: istore        5
      18: iload         5
      20: iload_2
      21: if_icmpge     402
      24: new           #49                 // class java/io/File
      27: dup
      28: aload_1
      29: new           #27                 // class java/lang/StringBuilder
      32: dup
      33: invokespecial #28                 // Method java/lang/StringBuilder."<init>":()V
      36: ldc           #50                 // String zookeeper_
      38: invokevirtual #30                 // Method java/lang/StringBuilder.append:(Ljava/lang/String;)Ljava/lang/StringBuilder;
      41: iload         5
      43: invokevirtual #31                 // Method java/lang/StringBuilder.append:(I)Ljava/lang/StringBuilder;
      46: invokevirtual #32                 // Method java/lang/StringBuilder.toString:()Ljava/lang/String;
      49: invokespecial #51                 // Method java/io/File."<init>":(Ljava/io/File;Ljava/lang/String;)V
      52: invokevirtual #52                 // Method java/io/File.getAbsoluteFile:()Ljava/io/File;
      55: astore        6
      57: aload_0
      58: aload         6
      60: invokespecial #53                 // Method createDir:(Ljava/io/File;)V
      63: aload_0
      64: getfield      #6                  // Field tickTime:I
      67: ifle          79
      70: aload_0
      71: getfield      #6                  // Field tickTime:I
      74: istore        7
      76: goto          84
      79: sipush        2000
      82: istore        7
      84: aload_0
      85: iload         5
      87: invokespecial #54                 // Method hasValidClientPortInList:(I)Z
      90: ifeq          115
      93: aload_0
      94: getfield      #13                 // Field clientPortList:Ljava/util/List;
      97: iload         5
      99: invokeinterface #23,  2           // InterfaceMethod java/util/List.get:(I)Ljava/lang/Object;
     104: checkcast     #24                 // class java/lang/Integer
     107: invokevirtual #25                 // Method java/lang/Integer.intValue:()I
     110: istore        4
     112: goto          124
     115: aload_0
     116: iload_3
     117: invokespecial #55                 // Method selectClientPort:(I)I
     120: istore_3
     121: iload_3
     122: istore        4
     124: new           #56                 // class org/apache/zookeeper/server/ZooKeeperServer
     127: dup
     128: aload         6
     130: aload         6
     132: iload         7
     134: invokespecial #57                 // Method org/apache/zookeeper/server/ZooKeeperServer."<init>":(Ljava/io/File;Ljava/io/File;I)V
     137: astore        8
     139: aload         8
     141: aload_0
     142: getfield      #8                  // Field configuration:Lorg/apache/hadoop/conf/Configuration;
     145: ldc           #58                 // String hbase.zookeeper.property.minSessionTimeout
     147: iconst_m1
     148: invokevirtual #18                 // Method org/apache/hadoop/conf/Configuration.getInt:(Ljava/lang/String;I)I
     151: invokevirtual #59                 // Method org/apache/zookeeper/server/ZooKeeperServer.setMinSessionTimeout:(I)V
     154: aload         8
     156: aload_0
     157: getfield      #8                  // Field configuration:Lorg/apache/hadoop/conf/Configuration;
     160: ldc           #60                 // String hbase.zookeeper.property.maxSessionTimeout
     162: iconst_m1
     163: invokevirtual #18                 // Method org/apache/hadoop/conf/Configuration.getInt:(Ljava/lang/String;I)I
     166: invokevirtual #61                 // Method org/apache/zookeeper/server/ZooKeeperServer.setMaxSessionTimeout:(I)V
     169: new           #62                 // class org/apache/zookeeper/server/NIOServerCnxnFactory
     172: dup
     173: invokespecial #63                 // Method org/apache/zookeeper/server/NIOServerCnxnFactory."<init>":()V
     176: astore        9
     178: aload         9
     180: new           #64                 // class java/net/InetSocketAddress
     183: dup
     184: iload         4
     186: invokespecial #65                 // Method java/net/InetSocketAddress."<init>":(I)V
     189: aload_0
     190: getfield      #8                  // Field configuration:Lorg/apache/hadoop/conf/Configuration;
     193: ldc           #66                 // String hbase.zookeeper.property.maxClientCnxns
     195: sipush        300
     198: invokevirtual #18                 // Method org/apache/hadoop/conf/Configuration.getInt:(Ljava/lang/String;I)I
     201: invokevirtual #67                 // Method org/apache/zookeeper/server/NIOServerCnxnFactory.configure:(Ljava/net/InetSocketAddress;I)V
     204: goto          262
     207: astore        10
     209: getstatic     #69                 // Field LOG:Lorg/slf4j/Logger;
     212: new           #27                 // class java/lang/StringBuilder
     215: dup
     216: invokespecial #28                 // Method java/lang/StringBuilder."<init>":()V
     219: ldc           #70                 // String Failed binding ZK Server to client port:
     221: invokevirtual #30                 // Method java/lang/StringBuilder.append:(Ljava/lang/String;)Ljava/lang/StringBuilder;
     224: iload         4
     226: invokevirtual #31                 // Method java/lang/StringBuilder.append:(I)Ljava/lang/StringBuilder;
     229: invokevirtual #32                 // Method java/lang/StringBuilder.toString:()Ljava/lang/String;
     232: aload         10
     234: invokeinterface #71,  3           // InterfaceMethod org/slf4j/Logger.debug:(Ljava/lang/String;Ljava/lang/Throwable;)V
     239: aload_0
     240: iload         5
     242: invokespecial #54                 // Method hasValidClientPortInList:(I)Z
     245: ifeq          250
     248: iconst_m1
     249: ireturn
     250: aload_0
     251: iload_3
     252: invokespecial #55                 // Method selectClientPort:(I)I
     255: istore_3
     256: iload_3
     257: istore        4
     259: goto          169
     262: aload         9
     264: aload         8
     266: invokevirtual #72                 // Method org/apache/zookeeper/server/NIOServerCnxnFactory.startup:(Lorg/apache/zookeeper/server/ZooKeeperServer;)V
     269: iload         4
     271: aload_0
     272: getfield      #19                 // Field connectionTimeout:I
     275: i2l
     276: invokestatic  #73                 // Method waitForServerUp:(IJ)Z
     279: ifne          292
     282: new           #74                 // class java/io/IOException
     285: dup
     286: ldc           #75                 // String Waiting for startup of standalone server
     288: invokespecial #76                 // Method java/io/IOException."<init>":(Ljava/lang/String;)V
     291: athrow
     292: aload_0
     293: getfield      #13                 // Field clientPortList:Ljava/util/List;
     296: invokeinterface #22,  1           // InterfaceMethod java/util/List.size:()I
     301: iload         5
     303: if_icmpgt     324
     306: aload_0
     307: getfield      #13                 // Field clientPortList:Ljava/util/List;
     310: iload         4
     312: invokestatic  #20                 // Method java/lang/Integer.valueOf:(I)Ljava/lang/Integer;
     315: invokeinterface #21,  2           // InterfaceMethod java/util/List.add:(Ljava/lang/Object;)Z
     320: pop
     321: goto          372
     324: aload_0
     325: getfield      #13                 // Field clientPortList:Ljava/util/List;
     328: iload         5
     330: invokeinterface #23,  2           // InterfaceMethod java/util/List.get:(I)Ljava/lang/Object;
     335: checkcast     #24                 // class java/lang/Integer
     338: invokevirtual #25                 // Method java/lang/Integer.intValue:()I
     341: ifgt          372
     344: aload_0
     345: getfield      #13                 // Field clientPortList:Ljava/util/List;
     348: iload         5
     350: invokeinterface #77,  2           // InterfaceMethod java/util/List.remove:(I)Ljava/lang/Object;
     355: pop
     356: aload_0
     357: getfield      #13                 // Field clientPortList:Ljava/util/List;
     360: iload         5
     362: iload         4
     364: invokestatic  #20                 // Method java/lang/Integer.valueOf:(I)Ljava/lang/Integer;
     367: invokeinterface #78,  3           // InterfaceMethod java/util/List.add:(ILjava/lang/Object;)V
     372: aload_0
     373: getfield      #14                 // Field standaloneServerFactoryList:Ljava/util/List;
     376: aload         9
     378: invokeinterface #21,  2           // InterfaceMethod java/util/List.add:(Ljava/lang/Object;)Z
     383: pop
     384: aload_0
     385: getfield      #12                 // Field zooKeeperServers:Ljava/util/List;
     388: aload         8
     390: invokeinterface #21,  2           // InterfaceMethod java/util/List.add:(Ljava/lang/Object;)Z
     395: pop
     396: iinc          5, 1
     399: goto          18
     402: aload_0
     403: iconst_0
     404: putfield      #9                  // Field activeZKServerIndex:I
     407: aload_0
     408: iconst_1
     409: putfield      #7                  // Field started:Z
     412: aload_0
     413: getfield      #13                 // Field clientPortList:Ljava/util/List;
     416: aload_0
     417: getfield      #9                  // Field activeZKServerIndex:I
     420: invokeinterface #23,  2           // InterfaceMethod java/util/List.get:(I)Ljava/lang/Object;
     425: checkcast     #24                 // class java/lang/Integer
     428: invokevirtual #25                 // Method java/lang/Integer.intValue:()I
     431: istore        5
     433: getstatic     #69                 // Field LOG:Lorg/slf4j/Logger;
     436: new           #27                 // class java/lang/StringBuilder
     439: dup
     440: invokespecial #28                 // Method java/lang/StringBuilder."<init>":()V
     443: ldc           #79                 // String Started MiniZooKeeperCluster and ran successful 'stat' on client port=
     445: invokevirtual #30                 // Method java/lang/StringBuilder.append:(Ljava/lang/String;)Ljava/lang/StringBuilder;
     448: iload         5
     450: invokevirtual #31                 // Method java/lang/StringBuilder.append:(I)Ljava/lang/StringBuilder;
     453: invokevirtual #32                 // Method java/lang/StringBuilder.toString:()Ljava/lang/String;
     456: invokeinterface #80,  2           // InterfaceMethod org/slf4j/Logger.info:(Ljava/lang/String;)V
     461: iload         5
     463: ireturn
    Exception table:
       from    to  target type
         169   204   207   Class java/net/BindException

  public void shutdown() throws java.io.IOException;
    Code:
       0: iconst_0
       1: istore_1
       2: iload_1
       3: aload_0
       4: getfield      #14                 // Field standaloneServerFactoryList:Ljava/util/List;
       7: invokeinterface #22,  1           // InterfaceMethod java/util/List.size:()I
      12: if_icmpge     78
      15: aload_0
      16: getfield      #14                 // Field standaloneServerFactoryList:Ljava/util/List;
      19: iload_1
      20: invokeinterface #23,  2           // InterfaceMethod java/util/List.get:(I)Ljava/lang/Object;
      25: checkcast     #62                 // class org/apache/zookeeper/server/NIOServerCnxnFactory
      28: astore_2
      29: aload_0
      30: getfield      #13                 // Field clientPortList:Ljava/util/List;
      33: iload_1
      34: invokeinterface #23,  2           // InterfaceMethod java/util/List.get:(I)Ljava/lang/Object;
      39: checkcast     #24                 // class java/lang/Integer
      42: invokevirtual #25                 // Method java/lang/Integer.intValue:()I
      45: istore_3
      46: aload_2
      47: invokevirtual #87                 // Method org/apache/zookeeper/server/NIOServerCnxnFactory.shutdown:()V
      50: iload_3
      51: aload_0
      52: getfield      #19                 // Field connectionTimeout:I
      55: i2l
      56: invokestatic  #88                 // Method waitForServerDown:(IJ)Z
      59: ifne          72
      62: new           #74                 // class java/io/IOException
      65: dup
      66: ldc           #89                 // String Waiting for shutdown of standalone server
      68: invokespecial #76                 // Method java/io/IOException."<init>":(Ljava/lang/String;)V
      71: athrow
      72: iinc          1, 1
      75: goto          2
      78: aload_0
      79: getfield      #14                 // Field standaloneServerFactoryList:Ljava/util/List;
      82: invokeinterface #90,  1           // InterfaceMethod java/util/List.clear:()V
      87: aload_0
      88: getfield      #12                 // Field zooKeeperServers:Ljava/util/List;
      91: invokeinterface #91,  1           // InterfaceMethod java/util/List.iterator:()Ljava/util/Iterator;
      96: astore_1
      97: aload_1
      98: invokeinterface #92,  1           // InterfaceMethod java/util/Iterator.hasNext:()Z
     103: ifeq          126
     106: aload_1
     107: invokeinterface #93,  1           // InterfaceMethod java/util/Iterator.next:()Ljava/lang/Object;
     112: checkcast     #56                 // class org/apache/zookeeper/server/ZooKeeperServer
     115: astore_2
     116: aload_2
     117: invokevirtual #94                 // Method org/apache/zookeeper/server/ZooKeeperServer.getZKDatabase:()Lorg/apache/zookeeper/server/ZKDatabase;
     120: invokevirtual #95                 // Method org/apache/zookeeper/server/ZKDatabase.close:()V
     123: goto          97
     126: aload_0
     127: getfield      #12                 // Field zooKeeperServers:Ljava/util/List;
     130: invokeinterface #90,  1           // InterfaceMethod java/util/List.clear:()V
     135: aload_0
     136: getfield      #7                  // Field started:Z
     139: ifeq          171
     142: aload_0
     143: iconst_0
     144: putfield      #7                  // Field started:Z
     147: aload_0
     148: iconst_0
     149: putfield      #9                  // Field activeZKServerIndex:I
     152: aload_0
     153: getfield      #13                 // Field clientPortList:Ljava/util/List;
     156: invokeinterface #90,  1           // InterfaceMethod java/util/List.clear:()V
     161: getstatic     #69                 // Field LOG:Lorg/slf4j/Logger;
     164: ldc           #96                 // String Shutdown MiniZK cluster with all ZK servers
     166: invokeinterface #80,  2           // InterfaceMethod org/slf4j/Logger.info:(Ljava/lang/String;)V
     171: return

  public int killCurrentActiveZooKeeperServer() throws java.io.IOException, java.lang.InterruptedException;
    Code:
       0: aload_0
       1: getfield      #7                  // Field started:Z
       4: ifeq          14
       7: aload_0
       8: getfield      #9                  // Field activeZKServerIndex:I
      11: ifge          16
      14: iconst_m1
      15: ireturn
      16: aload_0
      17: getfield      #14                 // Field standaloneServerFactoryList:Ljava/util/List;
      20: aload_0
      21: getfield      #9                  // Field activeZKServerIndex:I
      24: invokeinterface #23,  2           // InterfaceMethod java/util/List.get:(I)Ljava/lang/Object;
      29: checkcast     #62                 // class org/apache/zookeeper/server/NIOServerCnxnFactory
      32: astore_1
      33: aload_0
      34: getfield      #13                 // Field clientPortList:Ljava/util/List;
      37: aload_0
      38: getfield      #9                  // Field activeZKServerIndex:I
      41: invokeinterface #23,  2           // InterfaceMethod java/util/List.get:(I)Ljava/lang/Object;
      46: checkcast     #24                 // class java/lang/Integer
      49: invokevirtual #25                 // Method java/lang/Integer.intValue:()I
      52: istore_2
      53: aload_1
      54: invokevirtual #87                 // Method org/apache/zookeeper/server/NIOServerCnxnFactory.shutdown:()V
      57: iload_2
      58: aload_0
      59: getfield      #19                 // Field connectionTimeout:I
      62: i2l
      63: invokestatic  #88                 // Method waitForServerDown:(IJ)Z
      66: ifne          79
      69: new           #74                 // class java/io/IOException
      72: dup
      73: ldc           #89                 // String Waiting for shutdown of standalone server
      75: invokespecial #76                 // Method java/io/IOException."<init>":(Ljava/lang/String;)V
      78: athrow
      79: aload_0
      80: getfield      #12                 // Field zooKeeperServers:Ljava/util/List;
      83: aload_0
      84: getfield      #9                  // Field activeZKServerIndex:I
      87: invokeinterface #23,  2           // InterfaceMethod java/util/List.get:(I)Ljava/lang/Object;
      92: checkcast     #56                 // class org/apache/zookeeper/server/ZooKeeperServer
      95: invokevirtual #94                 // Method org/apache/zookeeper/server/ZooKeeperServer.getZKDatabase:()Lorg/apache/zookeeper/server/ZKDatabase;
      98: invokevirtual #95                 // Method org/apache/zookeeper/server/ZKDatabase.close:()V
     101: aload_0
     102: getfield      #14                 // Field standaloneServerFactoryList:Ljava/util/List;
     105: aload_0
     106: getfield      #9                  // Field activeZKServerIndex:I
     109: invokeinterface #77,  2           // InterfaceMethod java/util/List.remove:(I)Ljava/lang/Object;
     114: pop
     115: aload_0
     116: getfield      #13                 // Field clientPortList:Ljava/util/List;
     119: aload_0
     120: getfield      #9                  // Field activeZKServerIndex:I
     123: invokeinterface #77,  2           // InterfaceMethod java/util/List.remove:(I)Ljava/lang/Object;
     128: pop
     129: aload_0
     130: getfield      #12                 // Field zooKeeperServers:Ljava/util/List;
     133: aload_0
     134: getfield      #9                  // Field activeZKServerIndex:I
     137: invokeinterface #77,  2           // InterfaceMethod java/util/List.remove:(I)Ljava/lang/Object;
     142: pop
     143: getstatic     #69                 // Field LOG:Lorg/slf4j/Logger;
     146: new           #27                 // class java/lang/StringBuilder
     149: dup
     150: invokespecial #28                 // Method java/lang/StringBuilder."<init>":()V
     153: ldc           #97                 // String Kill the current active ZK servers in the cluster on client port:
     155: invokevirtual #30                 // Method java/lang/StringBuilder.append:(Ljava/lang/String;)Ljava/lang/StringBuilder;
     158: iload_2
     159: invokevirtual #31                 // Method java/lang/StringBuilder.append:(I)Ljava/lang/StringBuilder;
     162: invokevirtual #32                 // Method java/lang/StringBuilder.toString:()Ljava/lang/String;
     165: invokeinterface #80,  2           // InterfaceMethod org/slf4j/Logger.info:(Ljava/lang/String;)V
     170: aload_0
     171: getfield      #14                 // Field standaloneServerFactoryList:Ljava/util/List;
     174: invokeinterface #98,  1           // InterfaceMethod java/util/List.isEmpty:()Z
     179: ifeq          184
     182: iconst_m1
     183: ireturn
     184: aload_0
     185: getfield      #13                 // Field clientPortList:Ljava/util/List;
     188: aload_0
     189: getfield      #9                  // Field activeZKServerIndex:I
     192: invokeinterface #23,  2           // InterfaceMethod java/util/List.get:(I)Ljava/lang/Object;
     197: checkcast     #24                 // class java/lang/Integer
     200: invokevirtual #25                 // Method java/lang/Integer.intValue:()I
     203: istore_2
     204: getstatic     #69                 // Field LOG:Lorg/slf4j/Logger;
     207: new           #27                 // class java/lang/StringBuilder
     210: dup
     211: invokespecial #28                 // Method java/lang/StringBuilder."<init>":()V
     214: ldc           #99                 // String Activate a backup zk server in the cluster on client port:
     216: invokevirtual #30                 // Method java/lang/StringBuilder.append:(Ljava/lang/String;)Ljava/lang/StringBuilder;
     219: iload_2
     220: invokevirtual #31                 // Method java/lang/StringBuilder.append:(I)Ljava/lang/StringBuilder;
     223: invokevirtual #32                 // Method java/lang/StringBuilder.toString:()Ljava/lang/String;
     226: invokeinterface #80,  2           // InterfaceMethod org/slf4j/Logger.info:(Ljava/lang/String;)V
     231: iload_2
     232: ireturn

  public void killOneBackupZooKeeperServer() throws java.io.IOException, java.lang.InterruptedException;
    Code:
       0: aload_0
       1: getfield      #7                  // Field started:Z
       4: ifeq          27
       7: aload_0
       8: getfield      #9                  // Field activeZKServerIndex:I
      11: iflt          27
      14: aload_0
      15: getfield      #14                 // Field standaloneServerFactoryList:Ljava/util/List;
      18: invokeinterface #22,  1           // InterfaceMethod java/util/List.size:()I
      23: iconst_1
      24: if_icmpgt     28
      27: return
      28: aload_0
      29: getfield      #9                  // Field activeZKServerIndex:I
      32: iconst_1
      33: iadd
      34: istore_1
      35: aload_0
      36: getfield      #14                 // Field standaloneServerFactoryList:Ljava/util/List;
      39: iload_1
      40: invokeinterface #23,  2           // InterfaceMethod java/util/List.get:(I)Ljava/lang/Object;
      45: checkcast     #62                 // class org/apache/zookeeper/server/NIOServerCnxnFactory
      48: astore_2
      49: aload_0
      50: getfield      #13                 // Field clientPortList:Ljava/util/List;
      53: iload_1
      54: invokeinterface #23,  2           // InterfaceMethod java/util/List.get:(I)Ljava/lang/Object;
      59: checkcast     #24                 // class java/lang/Integer
      62: invokevirtual #25                 // Method java/lang/Integer.intValue:()I
      65: istore_3
      66: aload_2
      67: invokevirtual #87                 // Method org/apache/zookeeper/server/NIOServerCnxnFactory.shutdown:()V
      70: iload_3
      71: aload_0
      72: getfield      #19                 // Field connectionTimeout:I
      75: i2l
      76: invokestatic  #88                 // Method waitForServerDown:(IJ)Z
      79: ifne          92
      82: new           #74                 // class java/io/IOException
      85: dup
      86: ldc           #89                 // String Waiting for shutdown of standalone server
      88: invokespecial #76                 // Method java/io/IOException."<init>":(Ljava/lang/String;)V
      91: athrow
      92: aload_0
      93: getfield      #12                 // Field zooKeeperServers:Ljava/util/List;
      96: iload_1
      97: invokeinterface #23,  2           // InterfaceMethod java/util/List.get:(I)Ljava/lang/Object;
     102: checkcast     #56                 // class org/apache/zookeeper/server/ZooKeeperServer
     105: invokevirtual #94                 // Method org/apache/zookeeper/server/ZooKeeperServer.getZKDatabase:()Lorg/apache/zookeeper/server/ZKDatabase;
     108: invokevirtual #95                 // Method org/apache/zookeeper/server/ZKDatabase.close:()V
     111: aload_0
     112: getfield      #14                 // Field standaloneServerFactoryList:Ljava/util/List;
     115: iload_1
     116: invokeinterface #77,  2           // InterfaceMethod java/util/List.remove:(I)Ljava/lang/Object;
     121: pop
     122: aload_0
     123: getfield      #13                 // Field clientPortList:Ljava/util/List;
     126: iload_1
     127: invokeinterface #77,  2           // InterfaceMethod java/util/List.remove:(I)Ljava/lang/Object;
     132: pop
     133: aload_0
     134: getfield      #12                 // Field zooKeeperServers:Ljava/util/List;
     137: iload_1
     138: invokeinterface #77,  2           // InterfaceMethod java/util/List.remove:(I)Ljava/lang/Object;
     143: pop
     144: getstatic     #69                 // Field LOG:Lorg/slf4j/Logger;
     147: new           #27                 // class java/lang/StringBuilder
     150: dup
     151: invokespecial #28                 // Method java/lang/StringBuilder."<init>":()V
     154: ldc           #100                // String Kill one backup ZK servers in the cluster on client port:
     156: invokevirtual #30                 // Method java/lang/StringBuilder.append:(Ljava/lang/String;)Ljava/lang/StringBuilder;
     159: iload_3
     160: invokevirtual #31                 // Method java/lang/StringBuilder.append:(I)Ljava/lang/StringBuilder;
     163: invokevirtual #32                 // Method java/lang/StringBuilder.toString:()Ljava/lang/String;
     166: invokeinterface #80,  2           // InterfaceMethod org/slf4j/Logger.info:(Ljava/lang/String;)V
     171: return

  public int getClientPort();
    Code:
       0: aload_0
       1: getfield      #9                  // Field activeZKServerIndex:I
       4: iflt          23
       7: aload_0
       8: getfield      #9                  // Field activeZKServerIndex:I
      11: aload_0
      12: getfield      #13                 // Field clientPortList:Ljava/util/List;
      15: invokeinterface #22,  1           // InterfaceMethod java/util/List.size:()I
      20: if_icmplt     27
      23: iconst_m1
      24: goto          46
      27: aload_0
      28: getfield      #13                 // Field clientPortList:Ljava/util/List;
      31: aload_0
      32: getfield      #9                  // Field activeZKServerIndex:I
      35: invokeinterface #23,  2           // InterfaceMethod java/util/List.get:(I)Ljava/lang/Object;
      40: checkcast     #24                 // class java/lang/Integer
      43: invokevirtual #25                 // Method java/lang/Integer.intValue:()I
      46: ireturn

  java.util.List<org.apache.zookeeper.server.ZooKeeperServer> getZooKeeperServers();
    Code:
       0: aload_0
       1: getfield      #12                 // Field zooKeeperServers:Ljava/util/List;
       4: areturn

  static {};
    Code:
       0: ldc           #17                 // class org/apache/hadoop/hbase/zookeeper/MiniZooKeeperCluster
       2: invokestatic  #128                // Method org/slf4j/LoggerFactory.getLogger:(Ljava/lang/Class;)Lorg/slf4j/Logger;
       5: putstatic     #69                 // Field LOG:Lorg/slf4j/Logger;
       8: ldc           #129                // String stat
      10: invokestatic  #130                // Method org/apache/hadoop/hbase/util/Bytes.toBytes:(Ljava/lang/String;)[B
      13: putstatic     #106                // Field STATIC_BYTES:[B
      16: return
}
