Compiled from "MiniHBaseCluster.java"
class org.apache.hadoop.hbase.MiniHBaseCluster$MiniHBaseClusterRegionServer$1 implements java.security.PrivilegedAction<java.lang.Object> {
  final org.apache.hadoop.hbase.MiniHBaseCluster$MiniHBaseClusterRegionServer this$0;

  org.apache.hadoop.hbase.MiniHBaseCluster$MiniHBaseClusterRegionServer$1(org.apache.hadoop.hbase.MiniHBaseCluster$MiniHBaseClusterRegionServer);
    Code:
       0: aload_0
       1: aload_1
       2: putfield      #1                  // Field this$0:Lorg/apache/hadoop/hbase/MiniHBaseCluster$MiniHBaseClusterRegionServer;
       5: aload_0
       6: invokespecial #2                  // Method java/lang/Object."<init>":()V
       9: return

  public java.lang.Object run();
    Code:
       0: aload_0
       1: getfield      #1                  // Field this$0:Lorg/apache/hadoop/hbase/MiniHBaseCluster$MiniHBaseClusterRegionServer;
       4: invokestatic  #3                  // Method org/apache/hadoop/hbase/MiniHBaseCluster$MiniHBaseClusterRegionServer.access$000:(Lorg/apache/hadoop/hbase/MiniHBaseCluster$MiniHBaseClusterRegionServer;)V
       7: aconst_null
       8: areturn
}
