Compiled from "MobCompactor.java"
public abstract class org.apache.hadoop.hbase.mob.compactions.MobCompactor {
  protected org.apache.hadoop.fs.FileSystem fs;

  protected org.apache.hadoop.conf.Configuration conf;

  protected org.apache.hadoop.hbase.TableName tableName;

  protected org.apache.hadoop.hbase.client.ColumnFamilyDescriptor column;

  protected org.apache.hadoop.fs.Path mobTableDir;

  protected org.apache.hadoop.fs.Path mobFamilyDir;

  protected java.util.concurrent.ExecutorService pool;

  public org.apache.hadoop.hbase.mob.compactions.MobCompactor(org.apache.hadoop.conf.Configuration, org.apache.hadoop.fs.FileSystem, org.apache.hadoop.hbase.TableName, org.apache.hadoop.hbase.client.ColumnFamilyDescriptor, java.util.concurrent.ExecutorService);
    Code:
       0: aload_0
       1: invokespecial #1                  // Method java/lang/Object."<init>":()V
       4: aload_0
       5: aload_1
       6: putfield      #2                  // Field conf:Lorg/apache/hadoop/conf/Configuration;
       9: aload_0
      10: aload_2
      11: putfield      #3                  // Field fs:Lorg/apache/hadoop/fs/FileSystem;
      14: aload_0
      15: aload_3
      16: putfield      #4                  // Field tableName:Lorg/apache/hadoop/hbase/TableName;
      19: aload_0
      20: aload         4
      22: putfield      #5                  // Field column:Lorg/apache/hadoop/hbase/client/ColumnFamilyDescriptor;
      25: aload_0
      26: aload         5
      28: putfield      #6                  // Field pool:Ljava/util/concurrent/ExecutorService;
      31: aload_0
      32: aload_1
      33: invokestatic  #7                  // Method org/apache/hadoop/hbase/mob/MobUtils.getMobHome:(Lorg/apache/hadoop/conf/Configuration;)Lorg/apache/hadoop/fs/Path;
      36: aload_3
      37: invokestatic  #8                  // Method org/apache/hadoop/hbase/util/FSUtils.getTableDir:(Lorg/apache/hadoop/fs/Path;Lorg/apache/hadoop/hbase/TableName;)Lorg/apache/hadoop/fs/Path;
      40: putfield      #9                  // Field mobTableDir:Lorg/apache/hadoop/fs/Path;
      43: aload_0
      44: aload_1
      45: aload_3
      46: aload         4
      48: invokeinterface #10,  1           // InterfaceMethod org/apache/hadoop/hbase/client/ColumnFamilyDescriptor.getNameAsString:()Ljava/lang/String;
      53: invokestatic  #11                 // Method org/apache/hadoop/hbase/mob/MobUtils.getMobFamilyPath:(Lorg/apache/hadoop/conf/Configuration;Lorg/apache/hadoop/hbase/TableName;Ljava/lang/String;)Lorg/apache/hadoop/fs/Path;
      56: putfield      #12                 // Field mobFamilyDir:Lorg/apache/hadoop/fs/Path;
      59: return

  public java.util.List<org.apache.hadoop.fs.Path> compact() throws java.io.IOException;
    Code:
       0: aload_0
       1: iconst_0
       2: invokevirtual #13                 // Method compact:(Z)Ljava/util/List;
       5: areturn

  public java.util.List<org.apache.hadoop.fs.Path> compact(boolean) throws java.io.IOException;
    Code:
       0: aload_0
       1: aload_0
       2: getfield      #3                  // Field fs:Lorg/apache/hadoop/fs/FileSystem;
       5: aload_0
       6: getfield      #12                 // Field mobFamilyDir:Lorg/apache/hadoop/fs/Path;
       9: invokevirtual #14                 // Method org/apache/hadoop/fs/FileSystem.listStatus:(Lorg/apache/hadoop/fs/Path;)[Lorg/apache/hadoop/fs/FileStatus;
      12: invokestatic  #15                 // Method java/util/Arrays.asList:([Ljava/lang/Object;)Ljava/util/List;
      15: iload_1
      16: invokevirtual #16                 // Method compact:(Ljava/util/List;Z)Ljava/util/List;
      19: areturn

  public abstract java.util.List<org.apache.hadoop.fs.Path> compact(java.util.List<org.apache.hadoop.fs.FileStatus>, boolean) throws java.io.IOException;
}
