Compiled from "MockNoopMasterServices.java"
public class org.apache.hadoop.hbase.master.MockNoopMasterServices implements org.apache.hadoop.hbase.master.MasterServices {
  public org.apache.hadoop.hbase.master.MockNoopMasterServices();
    Code:
       0: aload_0
       1: aconst_null
       2: invokespecial #1                  // Method "<init>":(Lorg/apache/hadoop/conf/Configuration;)V
       5: return

  public org.apache.hadoop.hbase.master.MockNoopMasterServices(org.apache.hadoop.conf.Configuration);
    Code:
       0: aload_0
       1: invokespecial #2                  // Method java/lang/Object."<init>":()V
       4: aload_0
       5: iconst_0
       6: putfield      #3                  // Field stopped:Z
       9: aload_0
      10: aload_1
      11: putfield      #4                  // Field conf:Lorg/apache/hadoop/conf/Configuration;
      14: aload_0
      15: new           #5                  // class org/apache/hadoop/hbase/master/MetricsMaster
      18: dup
      19: new           #6                  // class org/apache/hadoop/hbase/master/MetricsMasterWrapperImpl
      22: dup
      23: aconst_null
      24: invokespecial #7                  // Method org/apache/hadoop/hbase/master/MetricsMasterWrapperImpl."<init>":(Lorg/apache/hadoop/hbase/master/HMaster;)V
      27: invokespecial #8                  // Method org/apache/hadoop/hbase/master/MetricsMaster."<init>":(Lorg/apache/hadoop/hbase/master/MetricsMasterWrapper;)V
      30: putfield      #9                  // Field metricsMaster:Lorg/apache/hadoop/hbase/master/MetricsMaster;
      33: return

  public void checkTableModifiable(org.apache.hadoop.hbase.TableName) throws java.io.IOException;
    Code:
       0: return

  public long createTable(org.apache.hadoop.hbase.client.TableDescriptor, byte[][], long, long) throws java.io.IOException;
    Code:
       0: ldc2_w        #10                 // long -1l
       3: lreturn

  public long createSystemTable(org.apache.hadoop.hbase.client.TableDescriptor) throws java.io.IOException;
    Code:
       0: ldc2_w        #10                 // long -1l
       3: lreturn

  public org.apache.hadoop.hbase.master.assignment.AssignmentManager getAssignmentManager();
    Code:
       0: aconst_null
       1: areturn

  public org.apache.hadoop.hbase.executor.ExecutorService getExecutorService();
    Code:
       0: aconst_null
       1: areturn

  public org.apache.hadoop.hbase.ChoreService getChoreService();
    Code:
       0: aconst_null
       1: areturn

  public org.apache.hadoop.hbase.master.normalizer.RegionNormalizer getRegionNormalizer();
    Code:
       0: aconst_null
       1: areturn

  public org.apache.hadoop.hbase.master.CatalogJanitor getCatalogJanitor();
    Code:
       0: aconst_null
       1: areturn

  public org.apache.hadoop.hbase.master.MasterFileSystem getMasterFileSystem();
    Code:
       0: aconst_null
       1: areturn

  public org.apache.hadoop.hbase.master.MasterWalManager getMasterWalManager();
    Code:
       0: aconst_null
       1: areturn

  public org.apache.hadoop.hbase.master.MasterCoprocessorHost getMasterCoprocessorHost();
    Code:
       0: aconst_null
       1: areturn

  public org.apache.hadoop.hbase.quotas.MasterQuotaManager getMasterQuotaManager();
    Code:
       0: aconst_null
       1: areturn

  public org.apache.hadoop.hbase.procedure2.ProcedureExecutor<org.apache.hadoop.hbase.master.procedure.MasterProcedureEnv> getMasterProcedureExecutor();
    Code:
       0: aconst_null
       1: areturn

  public org.apache.hadoop.hbase.master.MetricsMaster getMasterMetrics();
    Code:
       0: aload_0
       1: getfield      #9                  // Field metricsMaster:Lorg/apache/hadoop/hbase/master/MetricsMaster;
       4: areturn

  public org.apache.hadoop.hbase.master.ServerManager getServerManager();
    Code:
       0: aconst_null
       1: areturn

  public org.apache.hadoop.hbase.zookeeper.ZKWatcher getZooKeeper();
    Code:
       0: aconst_null
       1: areturn

  public org.apache.hadoop.hbase.CoordinatedStateManager getCoordinatedStateManager();
    Code:
       0: aconst_null
       1: areturn

  public org.apache.hadoop.hbase.client.ClusterConnection getConnection();
    Code:
       0: aconst_null
       1: areturn

  public org.apache.hadoop.conf.Configuration getConfiguration();
    Code:
       0: aload_0
       1: getfield      #4                  // Field conf:Lorg/apache/hadoop/conf/Configuration;
       4: areturn

  public org.apache.hadoop.hbase.ServerName getServerName();
    Code:
       0: ldc           #12                 // String mock.master
       2: sipush        12345
       5: lconst_1
       6: invokestatic  #13                 // Method org/apache/hadoop/hbase/ServerName.valueOf:(Ljava/lang/String;IJ)Lorg/apache/hadoop/hbase/ServerName;
       9: areturn

  public void abort(java.lang.String, java.lang.Throwable);
    Code:
       0: return

  public boolean isAborted();
    Code:
       0: iconst_0
       1: ireturn

  public void stop(java.lang.String);
    Code:
       0: aload_0
       1: iconst_1
       2: putfield      #3                  // Field stopped:Z
       5: return

  public boolean isStopping();
    Code:
       0: aload_0
       1: getfield      #3                  // Field stopped:Z
       4: ireturn

  public boolean isStopped();
    Code:
       0: aload_0
       1: getfield      #3                  // Field stopped:Z
       4: ireturn

  public org.apache.hadoop.hbase.TableDescriptors getTableDescriptors();
    Code:
       0: aconst_null
       1: areturn

  public boolean registerService(com.google.protobuf.Service);
    Code:
       0: iconst_0
       1: ireturn

  public boolean abortProcedure(long, boolean) throws java.io.IOException;
    Code:
       0: iconst_0
       1: ireturn

  public java.util.List<org.apache.hadoop.hbase.procedure2.Procedure<?>> getProcedures() throws java.io.IOException;
    Code:
       0: aconst_null
       1: areturn

  public java.util.List<org.apache.hadoop.hbase.procedure2.LockedResource> getLocks() throws java.io.IOException;
    Code:
       0: aconst_null
       1: areturn

  public java.util.List<org.apache.hadoop.hbase.client.TableDescriptor> listTableDescriptorsByNamespace(java.lang.String) throws java.io.IOException;
    Code:
       0: aconst_null
       1: areturn

  public java.util.List<org.apache.hadoop.hbase.TableName> listTableNamesByNamespace(java.lang.String) throws java.io.IOException;
    Code:
       0: aconst_null
       1: areturn

  public long deleteTable(org.apache.hadoop.hbase.TableName, long, long) throws java.io.IOException;
    Code:
       0: ldc2_w        #10                 // long -1l
       3: lreturn

  public long truncateTable(org.apache.hadoop.hbase.TableName, boolean, long, long) throws java.io.IOException;
    Code:
       0: ldc2_w        #10                 // long -1l
       3: lreturn

  public long modifyTable(org.apache.hadoop.hbase.TableName, org.apache.hadoop.hbase.client.TableDescriptor, long, long) throws java.io.IOException;
    Code:
       0: ldc2_w        #10                 // long -1l
       3: lreturn

  public long enableTable(org.apache.hadoop.hbase.TableName, long, long) throws java.io.IOException;
    Code:
       0: ldc2_w        #10                 // long -1l
       3: lreturn

  public long disableTable(org.apache.hadoop.hbase.TableName, long, long) throws java.io.IOException;
    Code:
       0: ldc2_w        #10                 // long -1l
       3: lreturn

  public long addColumn(org.apache.hadoop.hbase.TableName, org.apache.hadoop.hbase.client.ColumnFamilyDescriptor, long, long) throws java.io.IOException;
    Code:
       0: ldc2_w        #10                 // long -1l
       3: lreturn

  public long modifyColumn(org.apache.hadoop.hbase.TableName, org.apache.hadoop.hbase.client.ColumnFamilyDescriptor, long, long) throws java.io.IOException;
    Code:
       0: ldc2_w        #10                 // long -1l
       3: lreturn

  public long deleteColumn(org.apache.hadoop.hbase.TableName, byte[], long, long) throws java.io.IOException;
    Code:
       0: ldc2_w        #10                 // long -1l
       3: lreturn

  public long mergeRegions(org.apache.hadoop.hbase.client.RegionInfo[], boolean, long, long) throws java.io.IOException;
    Code:
       0: ldc2_w        #10                 // long -1l
       3: lreturn

  public long splitRegion(org.apache.hadoop.hbase.client.RegionInfo, byte[], long, long) throws java.io.IOException;
    Code:
       0: ldc2_w        #10                 // long -1l
       3: lreturn

  public org.apache.hadoop.hbase.master.TableStateManager getTableStateManager();
    Code:
       0: ldc           #14                 // class org/apache/hadoop/hbase/master/TableStateManager
       2: invokestatic  #15                 // Method org/mockito/Mockito.mock:(Ljava/lang/Class;)Ljava/lang/Object;
       5: checkcast     #14                 // class org/apache/hadoop/hbase/master/TableStateManager
       8: areturn

  public boolean isActiveMaster();
    Code:
       0: iconst_1
       1: ireturn

  public boolean isInitialized();
    Code:
       0: iconst_0
       1: ireturn

  public boolean isInMaintenanceMode();
    Code:
       0: iconst_0
       1: ireturn

  public long getLastMajorCompactionTimestamp(org.apache.hadoop.hbase.TableName) throws java.io.IOException;
    Code:
       0: lconst_0
       1: lreturn

  public long getLastMajorCompactionTimestampForRegion(byte[]) throws java.io.IOException;
    Code:
       0: lconst_0
       1: lreturn

  public org.apache.hadoop.hbase.master.ClusterSchema getClusterSchema();
    Code:
       0: aconst_null
       1: areturn

  public org.apache.hadoop.hbase.client.ClusterConnection getClusterConnection();
    Code:
       0: aconst_null
       1: areturn

  public org.apache.hadoop.hbase.master.LoadBalancer getLoadBalancer();
    Code:
       0: aconst_null
       1: areturn

  public org.apache.hadoop.hbase.favored.FavoredNodesManager getFavoredNodesManager();
    Code:
       0: aconst_null
       1: areturn

  public org.apache.hadoop.hbase.master.snapshot.SnapshotManager getSnapshotManager();
    Code:
       0: aconst_null
       1: areturn

  public org.apache.hadoop.hbase.procedure.MasterProcedureManagerHost getMasterProcedureManagerHost();
    Code:
       0: aconst_null
       1: areturn

  public boolean isSplitOrMergeEnabled(org.apache.hadoop.hbase.client.MasterSwitchType);
    Code:
       0: iconst_0
       1: ireturn

  public long addReplicationPeer(java.lang.String, org.apache.hadoop.hbase.replication.ReplicationPeerConfig, boolean) throws org.apache.hadoop.hbase.replication.ReplicationException;
    Code:
       0: lconst_0
       1: lreturn

  public long removeReplicationPeer(java.lang.String) throws org.apache.hadoop.hbase.replication.ReplicationException;
    Code:
       0: lconst_0
       1: lreturn

  public long enableReplicationPeer(java.lang.String) throws org.apache.hadoop.hbase.replication.ReplicationException, java.io.IOException;
    Code:
       0: lconst_0
       1: lreturn

  public long disableReplicationPeer(java.lang.String) throws org.apache.hadoop.hbase.replication.ReplicationException, java.io.IOException;
    Code:
       0: lconst_0
       1: lreturn

  public org.apache.hadoop.hbase.replication.ReplicationPeerConfig getReplicationPeerConfig(java.lang.String) throws org.apache.hadoop.hbase.replication.ReplicationException, java.io.IOException;
    Code:
       0: aconst_null
       1: areturn

  public long updateReplicationPeerConfig(java.lang.String, org.apache.hadoop.hbase.replication.ReplicationPeerConfig) throws org.apache.hadoop.hbase.replication.ReplicationException, java.io.IOException;
    Code:
       0: lconst_0
       1: lreturn

  public java.util.List<org.apache.hadoop.hbase.replication.ReplicationPeerDescription> listReplicationPeers(java.lang.String) throws org.apache.hadoop.hbase.replication.ReplicationException, java.io.IOException;
    Code:
       0: aconst_null
       1: areturn

  public org.apache.hadoop.hbase.master.locking.LockManager getLockManager();
    Code:
       0: aconst_null
       1: areturn

  public java.lang.String getRegionServerVersion(org.apache.hadoop.hbase.ServerName);
    Code:
       0: ldc           #16                 // String 0.0.0
       2: areturn

  public void checkIfShouldMoveSystemRegionAsync();
    Code:
       0: return

  public java.lang.String getClientIdAuditPrefix();
    Code:
       0: aconst_null
       1: areturn

  public org.apache.hadoop.hbase.procedure2.ProcedureEvent<?> getInitializedEvent();
    Code:
       0: aconst_null
       1: areturn

  public org.apache.hadoop.fs.FileSystem getFileSystem();
    Code:
       0: aconst_null
       1: areturn

  public org.apache.hadoop.hbase.client.Connection createConnection(org.apache.hadoop.conf.Configuration) throws java.io.IOException;
    Code:
       0: aconst_null
       1: areturn

  public org.apache.hadoop.hbase.master.replication.ReplicationPeerManager getReplicationPeerManager();
    Code:
       0: aconst_null
       1: areturn

  public boolean isClusterUp();
    Code:
       0: iconst_1
       1: ireturn

  public long transitReplicationPeerSyncReplicationState(java.lang.String, org.apache.hadoop.hbase.replication.SyncReplicationState) throws org.apache.hadoop.hbase.replication.ReplicationException, java.io.IOException;
    Code:
       0: lconst_0
       1: lreturn

  public org.apache.hadoop.hbase.master.replication.SyncReplicationReplayWALManager getSyncReplicationReplayWALManager();
    Code:
       0: aconst_null
       1: areturn

  public org.apache.hadoop.hbase.security.access.AccessChecker getAccessChecker();
    Code:
       0: aconst_null
       1: areturn

  public org.apache.hadoop.hbase.security.access.ZKPermissionWatcher getZKPermissionWatcher();
    Code:
       0: aconst_null
       1: areturn

  public org.apache.hadoop.hbase.client.Connection getConnection();
    Code:
       0: aload_0
       1: invokevirtual #17                 // Method getConnection:()Lorg/apache/hadoop/hbase/client/ClusterConnection;
       4: areturn
}
