Compiled from "ModifyPeerProcedure.java"
public abstract class org.apache.hadoop.hbase.master.replication.ModifyPeerProcedure extends org.apache.hadoop.hbase.master.replication.AbstractPeerProcedure<org.apache.hadoop.hbase.shaded.protobuf.generated.MasterProcedureProtos$PeerModificationState> {
  protected org.apache.hadoop.hbase.master.replication.ModifyPeerProcedure();
    Code:
       0: aload_0
       1: invokespecial #1                  // Method org/apache/hadoop/hbase/master/replication/AbstractPeerProcedure."<init>":()V
       4: return

  protected org.apache.hadoop.hbase.master.replication.ModifyPeerProcedure(java.lang.String);
    Code:
       0: aload_0
       1: aload_1
       2: invokespecial #2                  // Method org/apache/hadoop/hbase/master/replication/AbstractPeerProcedure."<init>":(Ljava/lang/String;)V
       5: return

  protected abstract void prePeerModification(org.apache.hadoop.hbase.master.procedure.MasterProcedureEnv) throws java.io.IOException, org.apache.hadoop.hbase.replication.ReplicationException, java.lang.InterruptedException;

  protected abstract void updatePeerStorage(org.apache.hadoop.hbase.master.procedure.MasterProcedureEnv) throws org.apache.hadoop.hbase.replication.ReplicationException;

  protected abstract void postPeerModification(org.apache.hadoop.hbase.master.procedure.MasterProcedureEnv) throws java.io.IOException, org.apache.hadoop.hbase.replication.ReplicationException;

  protected void releaseLatch(org.apache.hadoop.hbase.master.procedure.MasterProcedureEnv);
    Code:
       0: aload_0
       1: getfield      #3                  // Field latch:Lorg/apache/hadoop/hbase/master/procedure/ProcedurePrepareLatch;
       4: aload_0
       5: invokestatic  #4                  // Method org/apache/hadoop/hbase/master/procedure/ProcedurePrepareLatch.releaseLatch:(Lorg/apache/hadoop/hbase/master/procedure/ProcedurePrepareLatch;Lorg/apache/hadoop/hbase/procedure2/Procedure;)V
       8: return

  protected org.apache.hadoop.hbase.shaded.protobuf.generated.MasterProcedureProtos$PeerModificationState nextStateAfterRefresh();
    Code:
       0: getstatic     #5                  // Field org/apache/hadoop/hbase/shaded/protobuf/generated/MasterProcedureProtos$PeerModificationState.POST_PEER_MODIFICATION:Lorg/apache/hadoop/hbase/shaded/protobuf/generated/MasterProcedureProtos$PeerModificationState;
       3: areturn

  protected boolean enablePeerBeforeFinish();
    Code:
       0: new           #6                  // class java/lang/UnsupportedOperationException
       3: dup
       4: invokespecial #7                  // Method java/lang/UnsupportedOperationException."<init>":()V
       7: athrow

  protected org.apache.hadoop.hbase.replication.ReplicationPeerConfig getOldPeerConfig();
    Code:
       0: aconst_null
       1: areturn

  protected org.apache.hadoop.hbase.replication.ReplicationPeerConfig getNewPeerConfig();
    Code:
       0: new           #6                  // class java/lang/UnsupportedOperationException
       3: dup
       4: invokespecial #7                  // Method java/lang/UnsupportedOperationException."<init>":()V
       7: athrow

  protected void updateLastPushedSequenceIdForSerialPeer(org.apache.hadoop.hbase.master.procedure.MasterProcedureEnv) throws java.io.IOException, org.apache.hadoop.hbase.replication.ReplicationException;
    Code:
       0: new           #6                  // class java/lang/UnsupportedOperationException
       3: dup
       4: invokespecial #7                  // Method java/lang/UnsupportedOperationException."<init>":()V
       7: athrow

  protected void reopenRegions(org.apache.hadoop.hbase.master.procedure.MasterProcedureEnv) throws java.io.IOException;
    Code:
       0: aload_0
       1: invokevirtual #22                 // Method getNewPeerConfig:()Lorg/apache/hadoop/hbase/replication/ReplicationPeerConfig;
       4: astore_2
       5: aload_0
       6: invokevirtual #23                 // Method getOldPeerConfig:()Lorg/apache/hadoop/hbase/replication/ReplicationPeerConfig;
       9: astore_3
      10: aload_1
      11: invokevirtual #24                 // Method org/apache/hadoop/hbase/master/procedure/MasterProcedureEnv.getMasterServices:()Lorg/apache/hadoop/hbase/master/MasterServices;
      14: invokeinterface #25,  1           // InterfaceMethod org/apache/hadoop/hbase/master/MasterServices.getTableStateManager:()Lorg/apache/hadoop/hbase/master/TableStateManager;
      19: astore        4
      21: aload_1
      22: invokevirtual #24                 // Method org/apache/hadoop/hbase/master/procedure/MasterProcedureEnv.getMasterServices:()Lorg/apache/hadoop/hbase/master/MasterServices;
      25: invokeinterface #26,  1           // InterfaceMethod org/apache/hadoop/hbase/master/MasterServices.getTableDescriptors:()Lorg/apache/hadoop/hbase/TableDescriptors;
      30: invokeinterface #27,  1           // InterfaceMethod org/apache/hadoop/hbase/TableDescriptors.getAll:()Ljava/util/Map;
      35: invokeinterface #28,  1           // InterfaceMethod java/util/Map.values:()Ljava/util/Collection;
      40: invokeinterface #29,  1           // InterfaceMethod java/util/Collection.iterator:()Ljava/util/Iterator;
      45: astore        5
      47: aload         5
      49: invokeinterface #30,  1           // InterfaceMethod java/util/Iterator.hasNext:()Z
      54: ifeq          160
      57: aload         5
      59: invokeinterface #31,  1           // InterfaceMethod java/util/Iterator.next:()Ljava/lang/Object;
      64: checkcast     #32                 // class org/apache/hadoop/hbase/client/TableDescriptor
      67: astore        6
      69: aload         6
      71: invokeinterface #33,  1           // InterfaceMethod org/apache/hadoop/hbase/client/TableDescriptor.hasGlobalReplicationScope:()Z
      76: ifne          82
      79: goto          47
      82: aload         6
      84: invokeinterface #34,  1           // InterfaceMethod org/apache/hadoop/hbase/client/TableDescriptor.getTableName:()Lorg/apache/hadoop/hbase/TableName;
      89: astore        7
      91: aload_2
      92: aload         7
      94: invokestatic  #35                 // Method org/apache/hadoop/hbase/replication/ReplicationUtils.contains:(Lorg/apache/hadoop/hbase/replication/ReplicationPeerConfig;Lorg/apache/hadoop/hbase/TableName;)Z
      97: ifne          103
     100: goto          47
     103: aload_3
     104: ifnull        126
     107: aload_3
     108: invokevirtual #36                 // Method org/apache/hadoop/hbase/replication/ReplicationPeerConfig.isSerial:()Z
     111: ifeq          126
     114: aload_3
     115: aload         7
     117: invokestatic  #35                 // Method org/apache/hadoop/hbase/replication/ReplicationUtils.contains:(Lorg/apache/hadoop/hbase/replication/ReplicationPeerConfig;Lorg/apache/hadoop/hbase/TableName;)Z
     120: ifeq          126
     123: goto          47
     126: aload_0
     127: aload         4
     129: aload         7
     131: invokespecial #37                 // Method needReopen:(Lorg/apache/hadoop/hbase/master/TableStateManager;Lorg/apache/hadoop/hbase/TableName;)Z
     134: ifeq          157
     137: aload_0
     138: iconst_1
     139: anewarray     #38                 // class org/apache/hadoop/hbase/master/procedure/ReopenTableRegionsProcedure
     142: dup
     143: iconst_0
     144: new           #38                 // class org/apache/hadoop/hbase/master/procedure/ReopenTableRegionsProcedure
     147: dup
     148: aload         7
     150: invokespecial #39                 // Method org/apache/hadoop/hbase/master/procedure/ReopenTableRegionsProcedure."<init>":(Lorg/apache/hadoop/hbase/TableName;)V
     153: aastore
     154: invokevirtual #40                 // Method addChildProcedure:([Lorg/apache/hadoop/hbase/procedure2/Procedure;)V
     157: goto          47
     160: return

  protected org.apache.hadoop.hbase.procedure2.StateMachineProcedure$Flow executeFromState(org.apache.hadoop.hbase.master.procedure.MasterProcedureEnv, org.apache.hadoop.hbase.shaded.protobuf.generated.MasterProcedureProtos$PeerModificationState) throws org.apache.hadoop.hbase.procedure2.ProcedureSuspendedException, java.lang.InterruptedException;
    Code:
       0: getstatic     #41                 // Field org/apache/hadoop/hbase/master/replication/ModifyPeerProcedure$1.$SwitchMap$org$apache$hadoop$hbase$shaded$protobuf$generated$MasterProcedureProtos$PeerModificationState:[I
       3: aload_2
       4: invokevirtual #42                 // Method org/apache/hadoop/hbase/shaded/protobuf/generated/MasterProcedureProtos$PeerModificationState.ordinal:()I
       7: iaload
       8: tableswitch   { // 1 to 8
                     1: 56
                     2: 179
                     3: 219
                     4: 240
                     5: 280
                     6: 333
                     7: 373
                     8: 392
               default: 462
          }
      56: aload_0
      57: aload_1
      58: invokevirtual #43                 // Method prePeerModification:(Lorg/apache/hadoop/hbase/master/procedure/MasterProcedureEnv;)V
      61: goto          164
      64: astore_3
      65: getstatic     #44                 // Field LOG:Lorg/slf4j/Logger;
      68: ldc           #45                 // String {} failed to call pre CP hook or the pre check is failed for peer {}, mark the procedure as failure and give up
      70: iconst_3
      71: anewarray     #46                 // class java/lang/Object
      74: dup
      75: iconst_0
      76: aload_0
      77: invokevirtual #47                 // Method java/lang/Object.getClass:()Ljava/lang/Class;
      80: invokevirtual #48                 // Method java/lang/Class.getName:()Ljava/lang/String;
      83: aastore
      84: dup
      85: iconst_1
      86: aload_0
      87: getfield      #49                 // Field peerId:Ljava/lang/String;
      90: aastore
      91: dup
      92: iconst_2
      93: aload_3
      94: aastore
      95: invokeinterface #50,  3           // InterfaceMethod org/slf4j/Logger.warn:(Ljava/lang/String;[Ljava/lang/Object;)V
     100: aload_0
     101: new           #51                 // class java/lang/StringBuilder
     104: dup
     105: invokespecial #52                 // Method java/lang/StringBuilder."<init>":()V
     108: ldc           #53                 // String master-
     110: invokevirtual #54                 // Method java/lang/StringBuilder.append:(Ljava/lang/String;)Ljava/lang/StringBuilder;
     113: aload_0
     114: invokevirtual #55                 // Method getPeerOperationType:()Lorg/apache/hadoop/hbase/master/procedure/PeerProcedureInterface$PeerOperationType;
     117: invokevirtual #56                 // Method org/apache/hadoop/hbase/master/procedure/PeerProcedureInterface$PeerOperationType.name:()Ljava/lang/String;
     120: invokevirtual #57                 // Method java/lang/String.toLowerCase:()Ljava/lang/String;
     123: invokevirtual #54                 // Method java/lang/StringBuilder.append:(Ljava/lang/String;)Ljava/lang/StringBuilder;
     126: ldc           #58                 // String -peer
     128: invokevirtual #54                 // Method java/lang/StringBuilder.append:(Ljava/lang/String;)Ljava/lang/StringBuilder;
     131: invokevirtual #59                 // Method java/lang/StringBuilder.toString:()Ljava/lang/String;
     134: aload_3
     135: invokevirtual #60                 // Method setFailure:(Ljava/lang/String;Ljava/lang/Throwable;)V
     138: aload_0
     139: aload_1
     140: invokevirtual #61                 // Method releaseLatch:(Lorg/apache/hadoop/hbase/master/procedure/MasterProcedureEnv;)V
     143: getstatic     #62                 // Field org/apache/hadoop/hbase/procedure2/StateMachineProcedure$Flow.NO_MORE_STATE:Lorg/apache/hadoop/hbase/procedure2/StateMachineProcedure$Flow;
     146: areturn
     147: astore_3
     148: aload_0
     149: aload_1
     150: invokevirtual #64                 // Method org/apache/hadoop/hbase/master/procedure/MasterProcedureEnv.getMasterConfiguration:()Lorg/apache/hadoop/conf/Configuration;
     153: aload_0
     154: aload_3
     155: invokedynamic #65,  0             // InvokeDynamic #0:accept:(Lorg/apache/hadoop/hbase/master/replication/ModifyPeerProcedure;Lorg/apache/hadoop/hbase/replication/ReplicationException;)Ljava/util/function/LongConsumer;
     160: invokevirtual #66                 // Method suspend:(Lorg/apache/hadoop/conf/Configuration;Ljava/util/function/LongConsumer;)Lorg/apache/hadoop/hbase/procedure2/ProcedureSuspendedException;
     163: athrow
     164: aload_0
     165: invokevirtual #67                 // Method resetRetry:()V
     168: aload_0
     169: getstatic     #68                 // Field org/apache/hadoop/hbase/shaded/protobuf/generated/MasterProcedureProtos$PeerModificationState.UPDATE_PEER_STORAGE:Lorg/apache/hadoop/hbase/shaded/protobuf/generated/MasterProcedureProtos$PeerModificationState;
     172: invokevirtual #69                 // Method setNextState:(Ljava/lang/Object;)V
     175: getstatic     #70                 // Field org/apache/hadoop/hbase/procedure2/StateMachineProcedure$Flow.HAS_MORE_STATE:Lorg/apache/hadoop/hbase/procedure2/StateMachineProcedure$Flow;
     178: areturn
     179: aload_0
     180: aload_1
     181: invokevirtual #71                 // Method updatePeerStorage:(Lorg/apache/hadoop/hbase/master/procedure/MasterProcedureEnv;)V
     184: goto          204
     187: astore_3
     188: aload_0
     189: aload_1
     190: invokevirtual #64                 // Method org/apache/hadoop/hbase/master/procedure/MasterProcedureEnv.getMasterConfiguration:()Lorg/apache/hadoop/conf/Configuration;
     193: aload_0
     194: aload_3
     195: invokedynamic #72,  0             // InvokeDynamic #1:accept:(Lorg/apache/hadoop/hbase/master/replication/ModifyPeerProcedure;Lorg/apache/hadoop/hbase/replication/ReplicationException;)Ljava/util/function/LongConsumer;
     200: invokevirtual #66                 // Method suspend:(Lorg/apache/hadoop/conf/Configuration;Ljava/util/function/LongConsumer;)Lorg/apache/hadoop/hbase/procedure2/ProcedureSuspendedException;
     203: athrow
     204: aload_0
     205: invokevirtual #67                 // Method resetRetry:()V
     208: aload_0
     209: getstatic     #73                 // Field org/apache/hadoop/hbase/shaded/protobuf/generated/MasterProcedureProtos$PeerModificationState.REFRESH_PEER_ON_RS:Lorg/apache/hadoop/hbase/shaded/protobuf/generated/MasterProcedureProtos$PeerModificationState;
     212: invokevirtual #69                 // Method setNextState:(Ljava/lang/Object;)V
     215: getstatic     #70                 // Field org/apache/hadoop/hbase/procedure2/StateMachineProcedure$Flow.HAS_MORE_STATE:Lorg/apache/hadoop/hbase/procedure2/StateMachineProcedure$Flow;
     218: areturn
     219: aload_0
     220: aload_1
     221: aload_0
     222: invokevirtual #55                 // Method getPeerOperationType:()Lorg/apache/hadoop/hbase/master/procedure/PeerProcedureInterface$PeerOperationType;
     225: invokevirtual #74                 // Method refreshPeer:(Lorg/apache/hadoop/hbase/master/procedure/MasterProcedureEnv;Lorg/apache/hadoop/hbase/master/procedure/PeerProcedureInterface$PeerOperationType;)V
     228: aload_0
     229: aload_0
     230: invokevirtual #75                 // Method nextStateAfterRefresh:()Lorg/apache/hadoop/hbase/shaded/protobuf/generated/MasterProcedureProtos$PeerModificationState;
     233: invokevirtual #69                 // Method setNextState:(Ljava/lang/Object;)V
     236: getstatic     #70                 // Field org/apache/hadoop/hbase/procedure2/StateMachineProcedure$Flow.HAS_MORE_STATE:Lorg/apache/hadoop/hbase/procedure2/StateMachineProcedure$Flow;
     239: areturn
     240: aload_0
     241: aload_1
     242: invokevirtual #76                 // Method reopenRegions:(Lorg/apache/hadoop/hbase/master/procedure/MasterProcedureEnv;)V
     245: goto          265
     248: astore_3
     249: aload_0
     250: aload_1
     251: invokevirtual #64                 // Method org/apache/hadoop/hbase/master/procedure/MasterProcedureEnv.getMasterConfiguration:()Lorg/apache/hadoop/conf/Configuration;
     254: aload_0
     255: aload_3
     256: invokedynamic #78,  0             // InvokeDynamic #2:accept:(Lorg/apache/hadoop/hbase/master/replication/ModifyPeerProcedure;Ljava/lang/Exception;)Ljava/util/function/LongConsumer;
     261: invokevirtual #66                 // Method suspend:(Lorg/apache/hadoop/conf/Configuration;Ljava/util/function/LongConsumer;)Lorg/apache/hadoop/hbase/procedure2/ProcedureSuspendedException;
     264: athrow
     265: aload_0
     266: invokevirtual #67                 // Method resetRetry:()V
     269: aload_0
     270: getstatic     #79                 // Field org/apache/hadoop/hbase/shaded/protobuf/generated/MasterProcedureProtos$PeerModificationState.SERIAL_PEER_UPDATE_LAST_PUSHED_SEQ_ID:Lorg/apache/hadoop/hbase/shaded/protobuf/generated/MasterProcedureProtos$PeerModificationState;
     273: invokevirtual #69                 // Method setNextState:(Ljava/lang/Object;)V
     276: getstatic     #70                 // Field org/apache/hadoop/hbase/procedure2/StateMachineProcedure$Flow.HAS_MORE_STATE:Lorg/apache/hadoop/hbase/procedure2/StateMachineProcedure$Flow;
     279: areturn
     280: aload_0
     281: aload_1
     282: invokevirtual #80                 // Method updateLastPushedSequenceIdForSerialPeer:(Lorg/apache/hadoop/hbase/master/procedure/MasterProcedureEnv;)V
     285: goto          305
     288: astore_3
     289: aload_0
     290: aload_1
     291: invokevirtual #64                 // Method org/apache/hadoop/hbase/master/procedure/MasterProcedureEnv.getMasterConfiguration:()Lorg/apache/hadoop/conf/Configuration;
     294: aload_0
     295: aload_3
     296: invokedynamic #81,  0             // InvokeDynamic #3:accept:(Lorg/apache/hadoop/hbase/master/replication/ModifyPeerProcedure;Ljava/lang/Exception;)Ljava/util/function/LongConsumer;
     301: invokevirtual #66                 // Method suspend:(Lorg/apache/hadoop/conf/Configuration;Ljava/util/function/LongConsumer;)Lorg/apache/hadoop/hbase/procedure2/ProcedureSuspendedException;
     304: athrow
     305: aload_0
     306: invokevirtual #67                 // Method resetRetry:()V
     309: aload_0
     310: aload_0
     311: invokevirtual #82                 // Method enablePeerBeforeFinish:()Z
     314: ifeq          323
     317: getstatic     #83                 // Field org/apache/hadoop/hbase/shaded/protobuf/generated/MasterProcedureProtos$PeerModificationState.SERIAL_PEER_SET_PEER_ENABLED:Lorg/apache/hadoop/hbase/shaded/protobuf/generated/MasterProcedureProtos$PeerModificationState;
     320: goto          326
     323: getstatic     #5                  // Field org/apache/hadoop/hbase/shaded/protobuf/generated/MasterProcedureProtos$PeerModificationState.POST_PEER_MODIFICATION:Lorg/apache/hadoop/hbase/shaded/protobuf/generated/MasterProcedureProtos$PeerModificationState;
     326: invokevirtual #69                 // Method setNextState:(Ljava/lang/Object;)V
     329: getstatic     #70                 // Field org/apache/hadoop/hbase/procedure2/StateMachineProcedure$Flow.HAS_MORE_STATE:Lorg/apache/hadoop/hbase/procedure2/StateMachineProcedure$Flow;
     332: areturn
     333: aload_0
     334: aload_1
     335: invokevirtual #84                 // Method enablePeer:(Lorg/apache/hadoop/hbase/master/procedure/MasterProcedureEnv;)V
     338: goto          358
     341: astore_3
     342: aload_0
     343: aload_1
     344: invokevirtual #64                 // Method org/apache/hadoop/hbase/master/procedure/MasterProcedureEnv.getMasterConfiguration:()Lorg/apache/hadoop/conf/Configuration;
     347: aload_0
     348: aload_3
     349: invokedynamic #85,  0             // InvokeDynamic #4:accept:(Lorg/apache/hadoop/hbase/master/replication/ModifyPeerProcedure;Lorg/apache/hadoop/hbase/replication/ReplicationException;)Ljava/util/function/LongConsumer;
     354: invokevirtual #66                 // Method suspend:(Lorg/apache/hadoop/conf/Configuration;Ljava/util/function/LongConsumer;)Lorg/apache/hadoop/hbase/procedure2/ProcedureSuspendedException;
     357: athrow
     358: aload_0
     359: invokevirtual #67                 // Method resetRetry:()V
     362: aload_0
     363: getstatic     #86                 // Field org/apache/hadoop/hbase/shaded/protobuf/generated/MasterProcedureProtos$PeerModificationState.SERIAL_PEER_ENABLE_PEER_REFRESH_PEER_ON_RS:Lorg/apache/hadoop/hbase/shaded/protobuf/generated/MasterProcedureProtos$PeerModificationState;
     366: invokevirtual #69                 // Method setNextState:(Ljava/lang/Object;)V
     369: getstatic     #70                 // Field org/apache/hadoop/hbase/procedure2/StateMachineProcedure$Flow.HAS_MORE_STATE:Lorg/apache/hadoop/hbase/procedure2/StateMachineProcedure$Flow;
     372: areturn
     373: aload_0
     374: aload_1
     375: getstatic     #87                 // Field org/apache/hadoop/hbase/master/procedure/PeerProcedureInterface$PeerOperationType.ENABLE:Lorg/apache/hadoop/hbase/master/procedure/PeerProcedureInterface$PeerOperationType;
     378: invokevirtual #74                 // Method refreshPeer:(Lorg/apache/hadoop/hbase/master/procedure/MasterProcedureEnv;Lorg/apache/hadoop/hbase/master/procedure/PeerProcedureInterface$PeerOperationType;)V
     381: aload_0
     382: getstatic     #5                  // Field org/apache/hadoop/hbase/shaded/protobuf/generated/MasterProcedureProtos$PeerModificationState.POST_PEER_MODIFICATION:Lorg/apache/hadoop/hbase/shaded/protobuf/generated/MasterProcedureProtos$PeerModificationState;
     385: invokevirtual #69                 // Method setNextState:(Ljava/lang/Object;)V
     388: getstatic     #70                 // Field org/apache/hadoop/hbase/procedure2/StateMachineProcedure$Flow.HAS_MORE_STATE:Lorg/apache/hadoop/hbase/procedure2/StateMachineProcedure$Flow;
     391: areturn
     392: aload_0
     393: aload_1
     394: invokevirtual #88                 // Method postPeerModification:(Lorg/apache/hadoop/hbase/master/procedure/MasterProcedureEnv;)V
     397: goto          453
     400: astore_3
     401: aload_0
     402: aload_1
     403: invokevirtual #64                 // Method org/apache/hadoop/hbase/master/procedure/MasterProcedureEnv.getMasterConfiguration:()Lorg/apache/hadoop/conf/Configuration;
     406: aload_0
     407: aload_3
     408: invokedynamic #89,  0             // InvokeDynamic #5:accept:(Lorg/apache/hadoop/hbase/master/replication/ModifyPeerProcedure;Lorg/apache/hadoop/hbase/replication/ReplicationException;)Ljava/util/function/LongConsumer;
     413: invokevirtual #66                 // Method suspend:(Lorg/apache/hadoop/conf/Configuration;Ljava/util/function/LongConsumer;)Lorg/apache/hadoop/hbase/procedure2/ProcedureSuspendedException;
     416: athrow
     417: astore_3
     418: getstatic     #44                 // Field LOG:Lorg/slf4j/Logger;
     421: ldc           #90                 // String {} failed to call post CP hook for peer {}, ignore since the procedure has already done
     423: iconst_3
     424: anewarray     #46                 // class java/lang/Object
     427: dup
     428: iconst_0
     429: aload_0
     430: invokevirtual #47                 // Method java/lang/Object.getClass:()Ljava/lang/Class;
     433: invokevirtual #48                 // Method java/lang/Class.getName:()Ljava/lang/String;
     436: aastore
     437: dup
     438: iconst_1
     439: aload_0
     440: getfield      #49                 // Field peerId:Ljava/lang/String;
     443: aastore
     444: dup
     445: iconst_2
     446: aload_3
     447: aastore
     448: invokeinterface #50,  3           // InterfaceMethod org/slf4j/Logger.warn:(Ljava/lang/String;[Ljava/lang/Object;)V
     453: aload_0
     454: aload_1
     455: invokevirtual #61                 // Method releaseLatch:(Lorg/apache/hadoop/hbase/master/procedure/MasterProcedureEnv;)V
     458: getstatic     #62                 // Field org/apache/hadoop/hbase/procedure2/StateMachineProcedure$Flow.NO_MORE_STATE:Lorg/apache/hadoop/hbase/procedure2/StateMachineProcedure$Flow;
     461: areturn
     462: new           #6                  // class java/lang/UnsupportedOperationException
     465: dup
     466: new           #51                 // class java/lang/StringBuilder
     469: dup
     470: invokespecial #52                 // Method java/lang/StringBuilder."<init>":()V
     473: ldc           #91                 // String unhandled state=
     475: invokevirtual #54                 // Method java/lang/StringBuilder.append:(Ljava/lang/String;)Ljava/lang/StringBuilder;
     478: aload_2
     479: invokevirtual #92                 // Method java/lang/StringBuilder.append:(Ljava/lang/Object;)Ljava/lang/StringBuilder;
     482: invokevirtual #59                 // Method java/lang/StringBuilder.toString:()Ljava/lang/String;
     485: invokespecial #93                 // Method java/lang/UnsupportedOperationException."<init>":(Ljava/lang/String;)V
     488: athrow
    Exception table:
       from    to  target type
          56    61    64   Class java/io/IOException
          56    61   147   Class org/apache/hadoop/hbase/replication/ReplicationException
         179   184   187   Class org/apache/hadoop/hbase/replication/ReplicationException
         240   245   248   Class java/lang/Exception
         280   285   288   Class java/lang/Exception
         333   338   341   Class org/apache/hadoop/hbase/replication/ReplicationException
         392   397   400   Class org/apache/hadoop/hbase/replication/ReplicationException
         392   397   417   Class java/io/IOException

  protected org.apache.hadoop.hbase.shaded.protobuf.generated.MasterProcedureProtos$PeerModificationState getState(int);
    Code:
       0: iload_1
       1: invokestatic  #94                 // Method org/apache/hadoop/hbase/shaded/protobuf/generated/MasterProcedureProtos$PeerModificationState.forNumber:(I)Lorg/apache/hadoop/hbase/shaded/protobuf/generated/MasterProcedureProtos$PeerModificationState;
       4: areturn

  protected int getStateId(org.apache.hadoop.hbase.shaded.protobuf.generated.MasterProcedureProtos$PeerModificationState);
    Code:
       0: aload_1
       1: invokevirtual #95                 // Method org/apache/hadoop/hbase/shaded/protobuf/generated/MasterProcedureProtos$PeerModificationState.getNumber:()I
       4: ireturn

  protected org.apache.hadoop.hbase.shaded.protobuf.generated.MasterProcedureProtos$PeerModificationState getInitialState();
    Code:
       0: getstatic     #96                 // Field org/apache/hadoop/hbase/shaded/protobuf/generated/MasterProcedureProtos$PeerModificationState.PRE_PEER_MODIFICATION:Lorg/apache/hadoop/hbase/shaded/protobuf/generated/MasterProcedureProtos$PeerModificationState;
       3: areturn

  protected java.lang.Object getInitialState();
    Code:
       0: aload_0
       1: invokevirtual #97                 // Method getInitialState:()Lorg/apache/hadoop/hbase/shaded/protobuf/generated/MasterProcedureProtos$PeerModificationState;
       4: areturn

  protected int getStateId(java.lang.Object);
    Code:
       0: aload_0
       1: aload_1
       2: checkcast     #98                 // class org/apache/hadoop/hbase/shaded/protobuf/generated/MasterProcedureProtos$PeerModificationState
       5: invokevirtual #99                 // Method getStateId:(Lorg/apache/hadoop/hbase/shaded/protobuf/generated/MasterProcedureProtos$PeerModificationState;)I
       8: ireturn

  protected java.lang.Object getState(int);
    Code:
       0: aload_0
       1: iload_1
       2: invokevirtual #100                // Method getState:(I)Lorg/apache/hadoop/hbase/shaded/protobuf/generated/MasterProcedureProtos$PeerModificationState;
       5: areturn

  protected org.apache.hadoop.hbase.procedure2.StateMachineProcedure$Flow executeFromState(java.lang.Object, java.lang.Object) throws org.apache.hadoop.hbase.procedure2.ProcedureSuspendedException, org.apache.hadoop.hbase.procedure2.ProcedureYieldException, java.lang.InterruptedException;
    Code:
       0: aload_0
       1: aload_1
       2: checkcast     #101                // class org/apache/hadoop/hbase/master/procedure/MasterProcedureEnv
       5: aload_2
       6: checkcast     #98                 // class org/apache/hadoop/hbase/shaded/protobuf/generated/MasterProcedureProtos$PeerModificationState
       9: invokevirtual #102                // Method executeFromState:(Lorg/apache/hadoop/hbase/master/procedure/MasterProcedureEnv;Lorg/apache/hadoop/hbase/shaded/protobuf/generated/MasterProcedureProtos$PeerModificationState;)Lorg/apache/hadoop/hbase/procedure2/StateMachineProcedure$Flow;
      12: areturn

  static {};
    Code:
       0: ldc           #110                // class org/apache/hadoop/hbase/master/replication/ModifyPeerProcedure
       2: invokestatic  #111                // Method org/slf4j/LoggerFactory.getLogger:(Ljava/lang/Class;)Lorg/slf4j/Logger;
       5: putstatic     #44                 // Field LOG:Lorg/slf4j/Logger;
       8: return
}
