Compiled from "MonitoredTaskImpl.java"
class org.apache.hadoop.hbase.monitoring.MonitoredTaskImpl implements org.apache.hadoop.hbase.monitoring.MonitoredTask {
  protected volatile org.apache.hadoop.hbase.monitoring.MonitoredTask$State state;

  public org.apache.hadoop.hbase.monitoring.MonitoredTaskImpl();
    Code:
       0: aload_0
       1: invokespecial #1                  // Method java/lang/Object."<init>":()V
       4: aload_0
       5: getstatic     #2                  // Field org/apache/hadoop/hbase/monitoring/MonitoredTask$State.RUNNING:Lorg/apache/hadoop/hbase/monitoring/MonitoredTask$State;
       8: putfield      #3                  // Field state:Lorg/apache/hadoop/hbase/monitoring/MonitoredTask$State;
      11: aload_0
      12: iconst_0
      13: putfield      #4                  // Field journalEnabled:Z
      16: aload_0
      17: invokestatic  #5                  // Method java/lang/System.currentTimeMillis:()J
      20: putfield      #6                  // Field startTime:J
      23: aload_0
      24: aload_0
      25: getfield      #6                  // Field startTime:J
      28: putfield      #7                  // Field statusTime:J
      31: aload_0
      32: aload_0
      33: getfield      #6                  // Field startTime:J
      36: putfield      #8                  // Field stateTime:J
      39: aload_0
      40: aload_0
      41: getfield      #6                  // Field startTime:J
      44: putfield      #9                  // Field warnTime:J
      47: return

  public synchronized org.apache.hadoop.hbase.monitoring.MonitoredTaskImpl clone();
    Code:
       0: aload_0
       1: invokespecial #10                 // Method java/lang/Object.clone:()Ljava/lang/Object;
       4: checkcast     #11                 // class org/apache/hadoop/hbase/monitoring/MonitoredTaskImpl
       7: areturn
       8: astore_1
       9: new           #13                 // class java/lang/AssertionError
      12: dup
      13: invokespecial #14                 // Method java/lang/AssertionError."<init>":()V
      16: athrow
    Exception table:
       from    to  target type
           0     7     8   Class java/lang/CloneNotSupportedException

  public long getStartTime();
    Code:
       0: aload_0
       1: getfield      #6                  // Field startTime:J
       4: lreturn

  public java.lang.String getDescription();
    Code:
       0: aload_0
       1: getfield      #15                 // Field description:Ljava/lang/String;
       4: areturn

  public java.lang.String getStatus();
    Code:
       0: aload_0
       1: getfield      #16                 // Field status:Ljava/lang/String;
       4: areturn

  public long getStatusTime();
    Code:
       0: aload_0
       1: getfield      #7                  // Field statusTime:J
       4: lreturn

  public org.apache.hadoop.hbase.monitoring.MonitoredTask$State getState();
    Code:
       0: aload_0
       1: getfield      #3                  // Field state:Lorg/apache/hadoop/hbase/monitoring/MonitoredTask$State;
       4: areturn

  public long getStateTime();
    Code:
       0: aload_0
       1: getfield      #8                  // Field stateTime:J
       4: lreturn

  public long getWarnTime();
    Code:
       0: aload_0
       1: getfield      #9                  // Field warnTime:J
       4: lreturn

  public long getCompletionTimestamp();
    Code:
       0: aload_0
       1: getfield      #3                  // Field state:Lorg/apache/hadoop/hbase/monitoring/MonitoredTask$State;
       4: getstatic     #17                 // Field org/apache/hadoop/hbase/monitoring/MonitoredTask$State.COMPLETE:Lorg/apache/hadoop/hbase/monitoring/MonitoredTask$State;
       7: if_acmpeq     20
      10: aload_0
      11: getfield      #3                  // Field state:Lorg/apache/hadoop/hbase/monitoring/MonitoredTask$State;
      14: getstatic     #18                 // Field org/apache/hadoop/hbase/monitoring/MonitoredTask$State.ABORTED:Lorg/apache/hadoop/hbase/monitoring/MonitoredTask$State;
      17: if_acmpne     25
      20: aload_0
      21: getfield      #8                  // Field stateTime:J
      24: lreturn
      25: ldc2_w        #19                 // long -1l
      28: lreturn

  public void markComplete(java.lang.String);
    Code:
       0: aload_0
       1: getstatic     #17                 // Field org/apache/hadoop/hbase/monitoring/MonitoredTask$State.COMPLETE:Lorg/apache/hadoop/hbase/monitoring/MonitoredTask$State;
       4: invokevirtual #21                 // Method setState:(Lorg/apache/hadoop/hbase/monitoring/MonitoredTask$State;)V
       7: aload_0
       8: aload_1
       9: invokevirtual #22                 // Method setStatus:(Ljava/lang/String;)V
      12: return

  public void pause(java.lang.String);
    Code:
       0: aload_0
       1: getstatic     #23                 // Field org/apache/hadoop/hbase/monitoring/MonitoredTask$State.WAITING:Lorg/apache/hadoop/hbase/monitoring/MonitoredTask$State;
       4: invokevirtual #21                 // Method setState:(Lorg/apache/hadoop/hbase/monitoring/MonitoredTask$State;)V
       7: aload_0
       8: aload_1
       9: invokevirtual #22                 // Method setStatus:(Ljava/lang/String;)V
      12: return

  public void resume(java.lang.String);
    Code:
       0: aload_0
       1: getstatic     #2                  // Field org/apache/hadoop/hbase/monitoring/MonitoredTask$State.RUNNING:Lorg/apache/hadoop/hbase/monitoring/MonitoredTask$State;
       4: invokevirtual #21                 // Method setState:(Lorg/apache/hadoop/hbase/monitoring/MonitoredTask$State;)V
       7: aload_0
       8: aload_1
       9: invokevirtual #22                 // Method setStatus:(Ljava/lang/String;)V
      12: return

  public void abort(java.lang.String);
    Code:
       0: aload_0
       1: aload_1
       2: invokevirtual #22                 // Method setStatus:(Ljava/lang/String;)V
       5: aload_0
       6: getstatic     #18                 // Field org/apache/hadoop/hbase/monitoring/MonitoredTask$State.ABORTED:Lorg/apache/hadoop/hbase/monitoring/MonitoredTask$State;
       9: invokevirtual #21                 // Method setState:(Lorg/apache/hadoop/hbase/monitoring/MonitoredTask$State;)V
      12: return

  public void setStatus(java.lang.String);
    Code:
       0: aload_0
       1: aload_1
       2: putfield      #16                 // Field status:Ljava/lang/String;
       5: aload_0
       6: invokestatic  #5                  // Method java/lang/System.currentTimeMillis:()J
       9: putfield      #7                  // Field statusTime:J
      12: aload_0
      13: getfield      #4                  // Field journalEnabled:Z
      16: ifeq          44
      19: aload_0
      20: getfield      #24                 // Field journal:Ljava/util/List;
      23: new           #25                 // class org/apache/hadoop/hbase/monitoring/MonitoredTaskImpl$StatusJournalEntryImpl
      26: dup
      27: aload_0
      28: getfield      #16                 // Field status:Ljava/lang/String;
      31: aload_0
      32: getfield      #7                  // Field statusTime:J
      35: invokespecial #26                 // Method org/apache/hadoop/hbase/monitoring/MonitoredTaskImpl$StatusJournalEntryImpl."<init>":(Ljava/lang/String;J)V
      38: invokeinterface #27,  2           // InterfaceMethod java/util/List.add:(Ljava/lang/Object;)Z
      43: pop
      44: return

  protected void setState(org.apache.hadoop.hbase.monitoring.MonitoredTask$State);
    Code:
       0: aload_0
       1: aload_1
       2: putfield      #3                  // Field state:Lorg/apache/hadoop/hbase/monitoring/MonitoredTask$State;
       5: aload_0
       6: invokestatic  #5                  // Method java/lang/System.currentTimeMillis:()J
       9: putfield      #8                  // Field stateTime:J
      12: return

  public void setDescription(java.lang.String);
    Code:
       0: aload_0
       1: aload_1
       2: putfield      #15                 // Field description:Ljava/lang/String;
       5: return

  public void setWarnTime(long);
    Code:
       0: aload_0
       1: lload_1
       2: putfield      #9                  // Field warnTime:J
       5: return

  public void cleanup();
    Code:
       0: aload_0
       1: getfield      #3                  // Field state:Lorg/apache/hadoop/hbase/monitoring/MonitoredTask$State;
       4: getstatic     #2                  // Field org/apache/hadoop/hbase/monitoring/MonitoredTask$State.RUNNING:Lorg/apache/hadoop/hbase/monitoring/MonitoredTask$State;
       7: if_acmpne     17
      10: aload_0
      11: getstatic     #18                 // Field org/apache/hadoop/hbase/monitoring/MonitoredTask$State.ABORTED:Lorg/apache/hadoop/hbase/monitoring/MonitoredTask$State;
      14: invokevirtual #21                 // Method setState:(Lorg/apache/hadoop/hbase/monitoring/MonitoredTask$State;)V
      17: return

  public void expireNow();
    Code:
       0: aload_0
       1: dup
       2: getfield      #8                  // Field stateTime:J
       5: ldc2_w        #28                 // long 180000l
       8: lsub
       9: putfield      #8                  // Field stateTime:J
      12: return

  public java.util.Map<java.lang.String, java.lang.Object> toMap();
    Code:
       0: new           #30                 // class java/util/HashMap
       3: dup
       4: invokespecial #31                 // Method java/util/HashMap."<init>":()V
       7: astore_1
       8: aload_1
       9: ldc           #32                 // String description
      11: aload_0
      12: invokevirtual #33                 // Method getDescription:()Ljava/lang/String;
      15: invokeinterface #34,  3           // InterfaceMethod java/util/Map.put:(Ljava/lang/Object;Ljava/lang/Object;)Ljava/lang/Object;
      20: pop
      21: aload_1
      22: ldc           #35                 // String status
      24: aload_0
      25: invokevirtual #36                 // Method getStatus:()Ljava/lang/String;
      28: invokeinterface #34,  3           // InterfaceMethod java/util/Map.put:(Ljava/lang/Object;Ljava/lang/Object;)Ljava/lang/Object;
      33: pop
      34: aload_1
      35: ldc           #37                 // String state
      37: aload_0
      38: invokevirtual #38                 // Method getState:()Lorg/apache/hadoop/hbase/monitoring/MonitoredTask$State;
      41: invokeinterface #34,  3           // InterfaceMethod java/util/Map.put:(Ljava/lang/Object;Ljava/lang/Object;)Ljava/lang/Object;
      46: pop
      47: aload_1
      48: ldc           #39                 // String starttimems
      50: aload_0
      51: invokevirtual #40                 // Method getStartTime:()J
      54: invokestatic  #41                 // Method java/lang/Long.valueOf:(J)Ljava/lang/Long;
      57: invokeinterface #34,  3           // InterfaceMethod java/util/Map.put:(Ljava/lang/Object;Ljava/lang/Object;)Ljava/lang/Object;
      62: pop
      63: aload_1
      64: ldc           #42                 // String statustimems
      66: aload_0
      67: invokevirtual #43                 // Method getCompletionTimestamp:()J
      70: invokestatic  #41                 // Method java/lang/Long.valueOf:(J)Ljava/lang/Long;
      73: invokeinterface #34,  3           // InterfaceMethod java/util/Map.put:(Ljava/lang/Object;Ljava/lang/Object;)Ljava/lang/Object;
      78: pop
      79: aload_1
      80: ldc           #44                 // String statetimems
      82: aload_0
      83: invokevirtual #43                 // Method getCompletionTimestamp:()J
      86: invokestatic  #41                 // Method java/lang/Long.valueOf:(J)Ljava/lang/Long;
      89: invokeinterface #34,  3           // InterfaceMethod java/util/Map.put:(Ljava/lang/Object;Ljava/lang/Object;)Ljava/lang/Object;
      94: pop
      95: aload_1
      96: areturn

  public java.lang.String toJSON() throws java.io.IOException;
    Code:
       0: getstatic     #45                 // Field GSON:Lorg/apache/hbase/thirdparty/com/google/gson/Gson;
       3: aload_0
       4: invokevirtual #46                 // Method toMap:()Ljava/util/Map;
       7: invokevirtual #47                 // Method org/apache/hbase/thirdparty/com/google/gson/Gson.toJson:(Ljava/lang/Object;)Ljava/lang/String;
      10: areturn

  public java.lang.String toString();
    Code:
       0: new           #48                 // class java/lang/StringBuilder
       3: dup
       4: sipush        512
       7: invokespecial #49                 // Method java/lang/StringBuilder."<init>":(I)V
      10: astore_1
      11: aload_1
      12: aload_0
      13: invokevirtual #33                 // Method getDescription:()Ljava/lang/String;
      16: invokevirtual #50                 // Method java/lang/StringBuilder.append:(Ljava/lang/String;)Ljava/lang/StringBuilder;
      19: pop
      20: aload_1
      21: ldc           #51                 // String : status=
      23: invokevirtual #50                 // Method java/lang/StringBuilder.append:(Ljava/lang/String;)Ljava/lang/StringBuilder;
      26: pop
      27: aload_1
      28: aload_0
      29: invokevirtual #36                 // Method getStatus:()Ljava/lang/String;
      32: invokevirtual #50                 // Method java/lang/StringBuilder.append:(Ljava/lang/String;)Ljava/lang/StringBuilder;
      35: pop
      36: aload_1
      37: ldc           #52                 // String , state=
      39: invokevirtual #50                 // Method java/lang/StringBuilder.append:(Ljava/lang/String;)Ljava/lang/StringBuilder;
      42: pop
      43: aload_1
      44: aload_0
      45: invokevirtual #38                 // Method getState:()Lorg/apache/hadoop/hbase/monitoring/MonitoredTask$State;
      48: invokevirtual #53                 // Method java/lang/StringBuilder.append:(Ljava/lang/Object;)Ljava/lang/StringBuilder;
      51: pop
      52: aload_1
      53: ldc           #54                 // String , startTime=
      55: invokevirtual #50                 // Method java/lang/StringBuilder.append:(Ljava/lang/String;)Ljava/lang/StringBuilder;
      58: pop
      59: aload_1
      60: aload_0
      61: invokevirtual #40                 // Method getStartTime:()J
      64: invokevirtual #55                 // Method java/lang/StringBuilder.append:(J)Ljava/lang/StringBuilder;
      67: pop
      68: aload_1
      69: ldc           #56                 // String , completionTime=
      71: invokevirtual #50                 // Method java/lang/StringBuilder.append:(Ljava/lang/String;)Ljava/lang/StringBuilder;
      74: pop
      75: aload_1
      76: aload_0
      77: invokevirtual #43                 // Method getCompletionTimestamp:()J
      80: invokevirtual #55                 // Method java/lang/StringBuilder.append:(J)Ljava/lang/StringBuilder;
      83: pop
      84: aload_1
      85: invokevirtual #57                 // Method java/lang/StringBuilder.toString:()Ljava/lang/String;
      88: areturn

  public java.util.List<org.apache.hadoop.hbase.monitoring.MonitoredTask$StatusJournalEntry> getStatusJournal();
    Code:
       0: aload_0
       1: getfield      #24                 // Field journal:Ljava/util/List;
       4: ifnonnull     11
       7: invokestatic  #58                 // Method java/util/Collections.emptyList:()Ljava/util/List;
      10: areturn
      11: aload_0
      12: getfield      #24                 // Field journal:Ljava/util/List;
      15: invokestatic  #59                 // Method java/util/Collections.unmodifiableList:(Ljava/util/List;)Ljava/util/List;
      18: areturn

  public void enableStatusJournal(boolean);
    Code:
       0: aload_0
       1: getfield      #4                  // Field journalEnabled:Z
       4: ifeq          15
       7: aload_0
       8: getfield      #24                 // Field journal:Ljava/util/List;
      11: ifnull        15
      14: return
      15: aload_0
      16: iconst_1
      17: putfield      #4                  // Field journalEnabled:Z
      20: aload_0
      21: getfield      #24                 // Field journal:Ljava/util/List;
      24: ifnonnull     38
      27: aload_0
      28: new           #60                 // class java/util/ArrayList
      31: dup
      32: invokespecial #61                 // Method java/util/ArrayList."<init>":()V
      35: putfield      #24                 // Field journal:Ljava/util/List;
      38: iload_1
      39: ifeq          67
      42: aload_0
      43: getfield      #24                 // Field journal:Ljava/util/List;
      46: new           #25                 // class org/apache/hadoop/hbase/monitoring/MonitoredTaskImpl$StatusJournalEntryImpl
      49: dup
      50: aload_0
      51: getfield      #16                 // Field status:Ljava/lang/String;
      54: aload_0
      55: getfield      #7                  // Field statusTime:J
      58: invokespecial #26                 // Method org/apache/hadoop/hbase/monitoring/MonitoredTaskImpl$StatusJournalEntryImpl."<init>":(Ljava/lang/String;J)V
      61: invokeinterface #27,  2           // InterfaceMethod java/util/List.add:(Ljava/lang/Object;)Z
      66: pop
      67: return

  public void disableStatusJournal();
    Code:
       0: aload_0
       1: iconst_0
       2: putfield      #4                  // Field journalEnabled:Z
       5: return

  public java.lang.String prettyPrintJournal();
    Code:
       0: ldc           #62                 // String \n\t
       2: aload_0
       3: invokevirtual #63                 // Method getStatusJournal:()Ljava/util/List;
       6: invokestatic  #64                 // Method org/apache/hadoop/util/StringUtils.join:(Ljava/lang/CharSequence;Ljava/lang/Iterable;)Ljava/lang/String;
       9: areturn

  public java.lang.Object clone() throws java.lang.CloneNotSupportedException;
    Code:
       0: aload_0
       1: invokevirtual #65                 // Method clone:()Lorg/apache/hadoop/hbase/monitoring/MonitoredTaskImpl;
       4: areturn

  public org.apache.hadoop.hbase.monitoring.MonitoredTask clone();
    Code:
       0: aload_0
       1: invokevirtual #65                 // Method clone:()Lorg/apache/hadoop/hbase/monitoring/MonitoredTaskImpl;
       4: areturn

  static {};
    Code:
       0: invokestatic  #66                 // Method org/apache/hadoop/hbase/util/GsonUtil.createGson:()Lorg/apache/hbase/thirdparty/com/google/gson/GsonBuilder;
       3: invokevirtual #67                 // Method org/apache/hbase/thirdparty/com/google/gson/GsonBuilder.create:()Lorg/apache/hbase/thirdparty/com/google/gson/Gson;
       6: putstatic     #45                 // Field GSON:Lorg/apache/hbase/thirdparty/com/google/gson/Gson;
       9: return
}
