Compiled from "MultipleColumnPrefixFilter.java"
class org.apache.hadoop.hbase.filter.MultipleColumnPrefixFilter$1 implements java.util.Comparator<java.lang.Object> {
  final org.apache.hadoop.hbase.filter.MultipleColumnPrefixFilter this$0;

  org.apache.hadoop.hbase.filter.MultipleColumnPrefixFilter$1(org.apache.hadoop.hbase.filter.MultipleColumnPrefixFilter);
    Code:
       0: aload_0
       1: aload_1
       2: putfield      #1                  // Field this$0:Lorg/apache/hadoop/hbase/filter/MultipleColumnPrefixFilter;
       5: aload_0
       6: invokespecial #2                  // Method java/lang/Object."<init>":()V
       9: return

  public int compare(java.lang.Object, java.lang.Object);
    Code:
       0: aload_1
       1: ifnull        8
       4: aload_2
       5: ifnonnull     18
       8: new           #3                  // class java/lang/IllegalArgumentException
      11: dup
      12: ldc           #4                  // String prefixes can't be null
      14: invokespecial #5                  // Method java/lang/IllegalArgumentException."<init>":(Ljava/lang/String;)V
      17: athrow
      18: aload_1
      19: checkcast     #6                  // class "[B"
      22: checkcast     #6                  // class "[B"
      25: astore_3
      26: aload_2
      27: checkcast     #6                  // class "[B"
      30: checkcast     #6                  // class "[B"
      33: astore        4
      35: aload_3
      36: iconst_0
      37: aload_3
      38: arraylength
      39: aload         4
      41: iconst_0
      42: aload         4
      44: arraylength
      45: invokestatic  #7                  // Method org/apache/hadoop/hbase/util/Bytes.compareTo:([BII[BII)I
      48: ireturn
}
