Compiled from "MultithreadedTestUtil.java"
public abstract class org.apache.hadoop.hbase.MultithreadedTestUtil {
  public org.apache.hadoop.hbase.MultithreadedTestUtil();
    Code:
       0: aload_0
       1: invokespecial #2                  // Method java/lang/Object."<init>":()V
       4: return

  public static void assertOnFutures(java.util.List<java.util.concurrent.Future<?>>) throws java.lang.InterruptedException, java.util.concurrent.ExecutionException;
    Code:
       0: aload_0
       1: invokeinterface #3,  1            // InterfaceMethod java/util/List.iterator:()Ljava/util/Iterator;
       6: astore_1
       7: aload_1
       8: invokeinterface #4,  1            // InterfaceMethod java/util/Iterator.hasNext:()Z
      13: ifeq          60
      16: aload_1
      17: invokeinterface #5,  1            // InterfaceMethod java/util/Iterator.next:()Ljava/lang/Object;
      22: checkcast     #6                  // class java/util/concurrent/Future
      25: astore_2
      26: aload_2
      27: invokeinterface #7,  1            // InterfaceMethod java/util/concurrent/Future.get:()Ljava/lang/Object;
      32: pop
      33: goto          57
      36: astore_3
      37: aload_3
      38: invokevirtual #9                  // Method java/util/concurrent/ExecutionException.getCause:()Ljava/lang/Throwable;
      41: instanceof    #10                 // class java/lang/AssertionError
      44: ifeq          55
      47: aload_3
      48: invokevirtual #9                  // Method java/util/concurrent/ExecutionException.getCause:()Ljava/lang/Throwable;
      51: checkcast     #10                 // class java/lang/AssertionError
      54: athrow
      55: aload_3
      56: athrow
      57: goto          7
      60: return
    Exception table:
       from    to  target type
          26    33    36   Class java/util/concurrent/ExecutionException

  static org.slf4j.Logger access$000();
    Code:
       0: getstatic     #1                  // Field LOG:Lorg/slf4j/Logger;
       3: areturn

  static {};
    Code:
       0: ldc           #11                 // class org/apache/hadoop/hbase/MultithreadedTestUtil
       2: invokestatic  #12                 // Method org/slf4j/LoggerFactory.getLogger:(Ljava/lang/Class;)Lorg/slf4j/Logger;
       5: putstatic     #1                  // Field LOG:Lorg/slf4j/Logger;
       8: return
}
