Compiled from "MultiThreadedWriter.java"
public class org.apache.hadoop.hbase.util.MultiThreadedWriter extends org.apache.hadoop.hbase.util.MultiThreadedWriterBase {
  protected java.util.Set<org.apache.hadoop.hbase.util.MultiThreadedWriter$HBaseWriterThread> writers;

  protected boolean isMultiPut;

  public org.apache.hadoop.hbase.util.MultiThreadedWriter(org.apache.hadoop.hbase.util.test.LoadTestDataGenerator, org.apache.hadoop.conf.Configuration, org.apache.hadoop.hbase.TableName) throws java.io.IOException;
    Code:
       0: aload_0
       1: aload_1
       2: aload_2
       3: aload_3
       4: ldc           #2                  // String W
       6: invokespecial #3                  // Method org/apache/hadoop/hbase/util/MultiThreadedWriterBase."<init>":(Lorg/apache/hadoop/hbase/util/test/LoadTestDataGenerator;Lorg/apache/hadoop/conf/Configuration;Lorg/apache/hadoop/hbase/TableName;Ljava/lang/String;)V
       9: aload_0
      10: new           #4                  // class java/util/HashSet
      13: dup
      14: invokespecial #5                  // Method java/util/HashSet."<init>":()V
      17: putfield      #6                  // Field writers:Ljava/util/Set;
      20: aload_0
      21: iconst_0
      22: putfield      #7                  // Field isMultiPut:Z
      25: return

  public void setMultiPut(boolean);
    Code:
       0: aload_0
       1: iload_1
       2: putfield      #7                  // Field isMultiPut:Z
       5: return

  public void start(long, long, int) throws java.io.IOException;
    Code:
       0: aload_0
       1: lload_1
       2: lload_3
       3: iload         5
       5: invokespecial #8                  // Method org/apache/hadoop/hbase/util/MultiThreadedWriterBase.start:(JJI)V
       8: aload_0
       9: getfield      #9                  // Field verbose:Z
      12: ifeq          56
      15: getstatic     #1                  // Field LOG:Lorg/slf4j/Logger;
      18: new           #10                 // class java/lang/StringBuilder
      21: dup
      22: invokespecial #11                 // Method java/lang/StringBuilder."<init>":()V
      25: ldc           #12                 // String Inserting keys [
      27: invokevirtual #13                 // Method java/lang/StringBuilder.append:(Ljava/lang/String;)Ljava/lang/StringBuilder;
      30: lload_1
      31: invokevirtual #14                 // Method java/lang/StringBuilder.append:(J)Ljava/lang/StringBuilder;
      34: ldc           #15                 // String ,
      36: invokevirtual #13                 // Method java/lang/StringBuilder.append:(Ljava/lang/String;)Ljava/lang/StringBuilder;
      39: lload_3
      40: invokevirtual #14                 // Method java/lang/StringBuilder.append:(J)Ljava/lang/StringBuilder;
      43: ldc           #16                 // String )
      45: invokevirtual #13                 // Method java/lang/StringBuilder.append:(Ljava/lang/String;)Ljava/lang/StringBuilder;
      48: invokevirtual #17                 // Method java/lang/StringBuilder.toString:()Ljava/lang/String;
      51: invokeinterface #18,  2           // InterfaceMethod org/slf4j/Logger.debug:(Ljava/lang/String;)V
      56: aload_0
      57: iload         5
      59: invokevirtual #19                 // Method createWriterThreads:(I)V
      62: aload_0
      63: aload_0
      64: getfield      #6                  // Field writers:Ljava/util/Set;
      67: invokevirtual #20                 // Method startThreads:(Ljava/util/Collection;)V
      70: return

  protected void createWriterThreads(int) throws java.io.IOException;
    Code:
       0: iconst_0
       1: istore_2
       2: iload_2
       3: iload_1
       4: if_icmpge     38
       7: new           #21                 // class org/apache/hadoop/hbase/util/MultiThreadedWriter$HBaseWriterThread
      10: dup
      11: aload_0
      12: iload_2
      13: invokespecial #22                 // Method org/apache/hadoop/hbase/util/MultiThreadedWriter$HBaseWriterThread."<init>":(Lorg/apache/hadoop/hbase/util/MultiThreadedWriter;I)V
      16: astore_3
      17: aload_3
      18: invokestatic  #23                 // Method org/apache/hadoop/hbase/util/Threads.setLoggingUncaughtExceptionHandler:(Ljava/lang/Thread;)V
      21: aload_0
      22: getfield      #6                  // Field writers:Ljava/util/Set;
      25: aload_3
      26: invokeinterface #24,  2           // InterfaceMethod java/util/Set.add:(Ljava/lang/Object;)Z
      31: pop
      32: iinc          2, 1
      35: goto          2
      38: return

  public void waitForFinish();
    Code:
       0: aload_0
       1: invokespecial #25                 // Method org/apache/hadoop/hbase/util/MultiThreadedWriterBase.waitForFinish:()V
       4: getstatic     #26                 // Field java/lang/System.out:Ljava/io/PrintStream;
       7: new           #10                 // class java/lang/StringBuilder
      10: dup
      11: invokespecial #11                 // Method java/lang/StringBuilder."<init>":()V
      14: ldc           #27                 // String Failed to write keys:
      16: invokevirtual #13                 // Method java/lang/StringBuilder.append:(Ljava/lang/String;)Ljava/lang/StringBuilder;
      19: aload_0
      20: getfield      #28                 // Field failedKeySet:Ljava/util/Set;
      23: invokeinterface #29,  1           // InterfaceMethod java/util/Set.size:()I
      28: invokevirtual #30                 // Method java/lang/StringBuilder.append:(I)Ljava/lang/StringBuilder;
      31: invokevirtual #17                 // Method java/lang/StringBuilder.toString:()Ljava/lang/String;
      34: invokevirtual #31                 // Method java/io/PrintStream.println:(Ljava/lang/String;)V
      37: aload_0
      38: getfield      #28                 // Field failedKeySet:Ljava/util/Set;
      41: invokeinterface #32,  1           // InterfaceMethod java/util/Set.iterator:()Ljava/util/Iterator;
      46: astore_1
      47: aload_1
      48: invokeinterface #33,  1           // InterfaceMethod java/util/Iterator.hasNext:()Z
      53: ifeq          94
      56: aload_1
      57: invokeinterface #34,  1           // InterfaceMethod java/util/Iterator.next:()Ljava/lang/Object;
      62: checkcast     #35                 // class java/lang/Long
      65: astore_2
      66: getstatic     #26                 // Field java/lang/System.out:Ljava/io/PrintStream;
      69: new           #10                 // class java/lang/StringBuilder
      72: dup
      73: invokespecial #11                 // Method java/lang/StringBuilder."<init>":()V
      76: ldc           #36                 // String Failed to write key:
      78: invokevirtual #13                 // Method java/lang/StringBuilder.append:(Ljava/lang/String;)Ljava/lang/StringBuilder;
      81: aload_2
      82: invokevirtual #37                 // Method java/lang/StringBuilder.append:(Ljava/lang/Object;)Ljava/lang/StringBuilder;
      85: invokevirtual #17                 // Method java/lang/StringBuilder.toString:()Ljava/lang/String;
      88: invokevirtual #31                 // Method java/io/PrintStream.println:(Ljava/lang/String;)V
      91: goto          47
      94: return

  static org.slf4j.Logger access$000();
    Code:
       0: getstatic     #1                  // Field LOG:Lorg/slf4j/Logger;
       3: areturn

  static {};
    Code:
       0: ldc           #38                 // class org/apache/hadoop/hbase/util/MultiThreadedWriter
       2: invokestatic  #39                 // Method org/slf4j/LoggerFactory.getLogger:(Ljava/lang/Class;)Lorg/slf4j/Logger;
       5: putstatic     #1                  // Field LOG:Lorg/slf4j/Logger;
       8: return
}
