Compiled from "MultiThreadedReaderWithACL.java"
class org.apache.hadoop.hbase.util.MultiThreadedReaderWithACL$HBaseReaderThreadWithACL$1 implements java.security.PrivilegedExceptionAction<java.lang.Object> {
  final long val$keyToRead;

  final org.apache.hadoop.hbase.client.Get val$get;

  final boolean val$verify;

  final long val$start;

  final org.apache.hadoop.hbase.util.MultiThreadedReaderWithACL$HBaseReaderThreadWithACL this$1;

  org.apache.hadoop.hbase.util.MultiThreadedReaderWithACL$HBaseReaderThreadWithACL$1(org.apache.hadoop.hbase.util.MultiThreadedReaderWithACL$HBaseReaderThreadWithACL, long, org.apache.hadoop.hbase.client.Get, boolean, long);
    Code:
       0: aload_0
       1: aload_1
       2: putfield      #1                  // Field this$1:Lorg/apache/hadoop/hbase/util/MultiThreadedReaderWithACL$HBaseReaderThreadWithACL;
       5: aload_0
       6: lload_2
       7: putfield      #2                  // Field val$keyToRead:J
      10: aload_0
      11: aload         4
      13: putfield      #3                  // Field val$get:Lorg/apache/hadoop/hbase/client/Get;
      16: aload_0
      17: iload         5
      19: putfield      #4                  // Field val$verify:Z
      22: aload_0
      23: lload         6
      25: putfield      #5                  // Field val$start:J
      28: aload_0
      29: invokespecial #6                  // Method java/lang/Object."<init>":()V
      32: return

  public java.lang.Object run() throws java.lang.Exception;
    Code:
       0: aconst_null
       1: astore_1
       2: aconst_null
       3: astore_2
       4: aload_0
       5: getfield      #1                  // Field this$1:Lorg/apache/hadoop/hbase/util/MultiThreadedReaderWithACL$HBaseReaderThreadWithACL;
       8: getfield      #7                  // Field org/apache/hadoop/hbase/util/MultiThreadedReaderWithACL$HBaseReaderThreadWithACL.this$0:Lorg/apache/hadoop/hbase/util/MultiThreadedReaderWithACL;
      11: getfield      #8                  // Field org/apache/hadoop/hbase/util/MultiThreadedReaderWithACL.dataGenerator:Lorg/apache/hadoop/hbase/util/test/LoadTestDataGenerator;
      14: invokevirtual #9                  // Method org/apache/hadoop/hbase/util/test/LoadTestDataGenerator.getArgs:()[Ljava/lang/String;
      17: iconst_2
      18: aaload
      19: invokestatic  #10                 // Method java/lang/Integer.parseInt:(Ljava/lang/String;)I
      22: istore_3
      23: aload_0
      24: getfield      #2                  // Field val$keyToRead:J
      27: l2i
      28: aload_0
      29: getfield      #1                  // Field this$1:Lorg/apache/hadoop/hbase/util/MultiThreadedReaderWithACL$HBaseReaderThreadWithACL;
      32: getfield      #7                  // Field org/apache/hadoop/hbase/util/MultiThreadedReaderWithACL$HBaseReaderThreadWithACL.this$0:Lorg/apache/hadoop/hbase/util/MultiThreadedReaderWithACL;
      35: invokestatic  #11                 // Method org/apache/hadoop/hbase/util/MultiThreadedReaderWithACL.access$200:(Lorg/apache/hadoop/hbase/util/MultiThreadedReaderWithACL;)[Ljava/lang/String;
      38: arraylength
      39: irem
      40: istore        4
      42: aload_0
      43: getfield      #1                  // Field this$1:Lorg/apache/hadoop/hbase/util/MultiThreadedReaderWithACL$HBaseReaderThreadWithACL;
      46: getfield      #7                  // Field org/apache/hadoop/hbase/util/MultiThreadedReaderWithACL$HBaseReaderThreadWithACL.this$0:Lorg/apache/hadoop/hbase/util/MultiThreadedReaderWithACL;
      49: invokestatic  #12                 // Method org/apache/hadoop/hbase/util/MultiThreadedReaderWithACL.access$000:(Lorg/apache/hadoop/hbase/util/MultiThreadedReaderWithACL;)Ljava/util/Map;
      52: aload_0
      53: getfield      #1                  // Field this$1:Lorg/apache/hadoop/hbase/util/MultiThreadedReaderWithACL$HBaseReaderThreadWithACL;
      56: getfield      #7                  // Field org/apache/hadoop/hbase/util/MultiThreadedReaderWithACL$HBaseReaderThreadWithACL.this$0:Lorg/apache/hadoop/hbase/util/MultiThreadedReaderWithACL;
      59: invokestatic  #11                 // Method org/apache/hadoop/hbase/util/MultiThreadedReaderWithACL.access$200:(Lorg/apache/hadoop/hbase/util/MultiThreadedReaderWithACL;)[Ljava/lang/String;
      62: iload         4
      64: aaload
      65: invokeinterface #13,  2           // InterfaceMethod java/util/Map.get:(Ljava/lang/Object;)Ljava/lang/Object;
      70: ifnonnull     143
      73: aload_0
      74: getfield      #1                  // Field this$1:Lorg/apache/hadoop/hbase/util/MultiThreadedReaderWithACL$HBaseReaderThreadWithACL;
      77: getfield      #7                  // Field org/apache/hadoop/hbase/util/MultiThreadedReaderWithACL$HBaseReaderThreadWithACL.this$0:Lorg/apache/hadoop/hbase/util/MultiThreadedReaderWithACL;
      80: getfield      #14                 // Field org/apache/hadoop/hbase/util/MultiThreadedReaderWithACL.connection:Lorg/apache/hadoop/hbase/client/ClusterConnection;
      83: aload_0
      84: getfield      #1                  // Field this$1:Lorg/apache/hadoop/hbase/util/MultiThreadedReaderWithACL$HBaseReaderThreadWithACL;
      87: getfield      #7                  // Field org/apache/hadoop/hbase/util/MultiThreadedReaderWithACL$HBaseReaderThreadWithACL.this$0:Lorg/apache/hadoop/hbase/util/MultiThreadedReaderWithACL;
      90: getfield      #15                 // Field org/apache/hadoop/hbase/util/MultiThreadedReaderWithACL.tableName:Lorg/apache/hadoop/hbase/TableName;
      93: invokeinterface #16,  2           // InterfaceMethod org/apache/hadoop/hbase/client/ClusterConnection.getTable:(Lorg/apache/hadoop/hbase/TableName;)Lorg/apache/hadoop/hbase/client/Table;
      98: astore_1
      99: aload_0
     100: getfield      #1                  // Field this$1:Lorg/apache/hadoop/hbase/util/MultiThreadedReaderWithACL$HBaseReaderThreadWithACL;
     103: getfield      #7                  // Field org/apache/hadoop/hbase/util/MultiThreadedReaderWithACL$HBaseReaderThreadWithACL.this$0:Lorg/apache/hadoop/hbase/util/MultiThreadedReaderWithACL;
     106: invokestatic  #12                 // Method org/apache/hadoop/hbase/util/MultiThreadedReaderWithACL.access$000:(Lorg/apache/hadoop/hbase/util/MultiThreadedReaderWithACL;)Ljava/util/Map;
     109: aload_0
     110: getfield      #1                  // Field this$1:Lorg/apache/hadoop/hbase/util/MultiThreadedReaderWithACL$HBaseReaderThreadWithACL;
     113: getfield      #7                  // Field org/apache/hadoop/hbase/util/MultiThreadedReaderWithACL$HBaseReaderThreadWithACL.this$0:Lorg/apache/hadoop/hbase/util/MultiThreadedReaderWithACL;
     116: invokestatic  #11                 // Method org/apache/hadoop/hbase/util/MultiThreadedReaderWithACL.access$200:(Lorg/apache/hadoop/hbase/util/MultiThreadedReaderWithACL;)[Ljava/lang/String;
     119: iload         4
     121: aaload
     122: aload_1
     123: invokeinterface #17,  3           // InterfaceMethod java/util/Map.put:(Ljava/lang/Object;Ljava/lang/Object;)Ljava/lang/Object;
     128: pop
     129: aload_1
     130: aload_0
     131: getfield      #3                  // Field val$get:Lorg/apache/hadoop/hbase/client/Get;
     134: invokeinterface #18,  2           // InterfaceMethod org/apache/hadoop/hbase/client/Table.get:(Lorg/apache/hadoop/hbase/client/Get;)Lorg/apache/hadoop/hbase/client/Result;
     139: astore_2
     140: goto          186
     143: aload_0
     144: getfield      #1                  // Field this$1:Lorg/apache/hadoop/hbase/util/MultiThreadedReaderWithACL$HBaseReaderThreadWithACL;
     147: getfield      #7                  // Field org/apache/hadoop/hbase/util/MultiThreadedReaderWithACL$HBaseReaderThreadWithACL.this$0:Lorg/apache/hadoop/hbase/util/MultiThreadedReaderWithACL;
     150: invokestatic  #12                 // Method org/apache/hadoop/hbase/util/MultiThreadedReaderWithACL.access$000:(Lorg/apache/hadoop/hbase/util/MultiThreadedReaderWithACL;)Ljava/util/Map;
     153: aload_0
     154: getfield      #1                  // Field this$1:Lorg/apache/hadoop/hbase/util/MultiThreadedReaderWithACL$HBaseReaderThreadWithACL;
     157: getfield      #7                  // Field org/apache/hadoop/hbase/util/MultiThreadedReaderWithACL$HBaseReaderThreadWithACL.this$0:Lorg/apache/hadoop/hbase/util/MultiThreadedReaderWithACL;
     160: invokestatic  #11                 // Method org/apache/hadoop/hbase/util/MultiThreadedReaderWithACL.access$200:(Lorg/apache/hadoop/hbase/util/MultiThreadedReaderWithACL;)[Ljava/lang/String;
     163: iload         4
     165: aaload
     166: invokeinterface #13,  2           // InterfaceMethod java/util/Map.get:(Ljava/lang/Object;)Ljava/lang/Object;
     171: checkcast     #19                 // class org/apache/hadoop/hbase/client/Table
     174: astore_1
     175: aload_1
     176: aload_0
     177: getfield      #3                  // Field val$get:Lorg/apache/hadoop/hbase/client/Get;
     180: invokeinterface #18,  2           // InterfaceMethod org/apache/hadoop/hbase/client/Table.get:(Lorg/apache/hadoop/hbase/client/Get;)Lorg/apache/hadoop/hbase/client/Result;
     185: astore_2
     186: aload_0
     187: getfield      #2                  // Field val$keyToRead:J
     190: l2i
     191: iload_3
     192: irem
     193: ifne          200
     196: iconst_1
     197: goto          201
     200: iconst_0
     201: istore        5
     203: invokestatic  #20                 // Method java/lang/System.nanoTime:()J
     206: lstore        6
     208: aload_0
     209: getfield      #1                  // Field this$1:Lorg/apache/hadoop/hbase/util/MultiThreadedReaderWithACL$HBaseReaderThreadWithACL;
     212: aload_0
     213: getfield      #4                  // Field val$verify:Z
     216: aload_0
     217: getfield      #3                  // Field val$get:Lorg/apache/hadoop/hbase/client/Get;
     220: lload         6
     222: aload_0
     223: getfield      #5                  // Field val$start:J
     226: lsub
     227: aload_2
     228: aload_1
     229: iload         5
     231: invokevirtual #21                 // Method org/apache/hadoop/hbase/util/MultiThreadedReaderWithACL$HBaseReaderThreadWithACL.verifyResultsAndUpdateMetrics:(ZLorg/apache/hadoop/hbase/client/Get;JLorg/apache/hadoop/hbase/client/Result;Lorg/apache/hadoop/hbase/client/Table;Z)V
     234: goto          249
     237: astore_2
     238: aload_0
     239: getfield      #1                  // Field this$1:Lorg/apache/hadoop/hbase/util/MultiThreadedReaderWithACL$HBaseReaderThreadWithACL;
     242: aload_0
     243: getfield      #2                  // Field val$keyToRead:J
     246: invokestatic  #23                 // Method org/apache/hadoop/hbase/util/MultiThreadedReaderWithACL$HBaseReaderThreadWithACL.access$300:(Lorg/apache/hadoop/hbase/util/MultiThreadedReaderWithACL$HBaseReaderThreadWithACL;J)V
     249: aconst_null
     250: areturn
    Exception table:
       from    to  target type
           2   234   237   Class java/io/IOException
}
