Compiled from "MultiRowMutationProtos.java"
public final class org.apache.hadoop.hbase.protobuf.generated.MultiRowMutationProtos$MutateRowsRequest extends com.google.protobuf.GeneratedMessage implements org.apache.hadoop.hbase.protobuf.generated.MultiRowMutationProtos$MutateRowsRequestOrBuilder {
  public static com.google.protobuf.Parser<org.apache.hadoop.hbase.protobuf.generated.MultiRowMutationProtos$MutateRowsRequest> PARSER;

  public static final int MUTATION_REQUEST_FIELD_NUMBER;

  public static final int NONCE_GROUP_FIELD_NUMBER;

  public static final int NONCE_FIELD_NUMBER;

  public static final int REGION_FIELD_NUMBER;

  public static org.apache.hadoop.hbase.protobuf.generated.MultiRowMutationProtos$MutateRowsRequest getDefaultInstance();
    Code:
       0: getstatic     #17                 // Field defaultInstance:Lorg/apache/hadoop/hbase/protobuf/generated/MultiRowMutationProtos$MutateRowsRequest;
       3: areturn

  public org.apache.hadoop.hbase.protobuf.generated.MultiRowMutationProtos$MutateRowsRequest getDefaultInstanceForType();
    Code:
       0: getstatic     #17                 // Field defaultInstance:Lorg/apache/hadoop/hbase/protobuf/generated/MultiRowMutationProtos$MutateRowsRequest;
       3: areturn

  public final com.google.protobuf.UnknownFieldSet getUnknownFields();
    Code:
       0: aload_0
       1: getfield      #14                 // Field unknownFields:Lcom/google/protobuf/UnknownFieldSet;
       4: areturn

  public static final com.google.protobuf.Descriptors$Descriptor getDescriptor();
    Code:
       0: invokestatic  #41                 // Method org/apache/hadoop/hbase/protobuf/generated/MultiRowMutationProtos.access$1400:()Lcom/google/protobuf/Descriptors$Descriptor;
       3: areturn

  protected com.google.protobuf.GeneratedMessage$FieldAccessorTable internalGetFieldAccessorTable();
    Code:
       0: invokestatic  #42                 // Method org/apache/hadoop/hbase/protobuf/generated/MultiRowMutationProtos.access$1500:()Lcom/google/protobuf/GeneratedMessage$FieldAccessorTable;
       3: ldc           #43                 // class org/apache/hadoop/hbase/protobuf/generated/MultiRowMutationProtos$MutateRowsRequest
       5: ldc           #44                 // class org/apache/hadoop/hbase/protobuf/generated/MultiRowMutationProtos$MutateRowsRequest$Builder
       7: invokevirtual #45                 // Method com/google/protobuf/GeneratedMessage$FieldAccessorTable.ensureFieldAccessorsInitialized:(Ljava/lang/Class;Ljava/lang/Class;)Lcom/google/protobuf/GeneratedMessage$FieldAccessorTable;
      10: areturn

  public com.google.protobuf.Parser<org.apache.hadoop.hbase.protobuf.generated.MultiRowMutationProtos$MutateRowsRequest> getParserForType();
    Code:
       0: getstatic     #46                 // Field PARSER:Lcom/google/protobuf/Parser;
       3: areturn

  public java.util.List<org.apache.hadoop.hbase.protobuf.generated.ClientProtos$MutationProto> getMutationRequestList();
    Code:
       0: aload_0
       1: getfield      #6                  // Field mutationRequest_:Ljava/util/List;
       4: areturn

  public java.util.List<? extends org.apache.hadoop.hbase.protobuf.generated.ClientProtos$MutationProtoOrBuilder> getMutationRequestOrBuilderList();
    Code:
       0: aload_0
       1: getfield      #6                  // Field mutationRequest_:Ljava/util/List;
       4: areturn

  public int getMutationRequestCount();
    Code:
       0: aload_0
       1: getfield      #6                  // Field mutationRequest_:Ljava/util/List;
       4: invokeinterface #47,  1           // InterfaceMethod java/util/List.size:()I
       9: ireturn

  public org.apache.hadoop.hbase.protobuf.generated.ClientProtos$MutationProto getMutationRequest(int);
    Code:
       0: aload_0
       1: getfield      #6                  // Field mutationRequest_:Ljava/util/List;
       4: iload_1
       5: invokeinterface #48,  2           // InterfaceMethod java/util/List.get:(I)Ljava/lang/Object;
      10: checkcast     #49                 // class org/apache/hadoop/hbase/protobuf/generated/ClientProtos$MutationProto
      13: areturn

  public org.apache.hadoop.hbase.protobuf.generated.ClientProtos$MutationProtoOrBuilder getMutationRequestOrBuilder(int);
    Code:
       0: aload_0
       1: getfield      #6                  // Field mutationRequest_:Ljava/util/List;
       4: iload_1
       5: invokeinterface #48,  2           // InterfaceMethod java/util/List.get:(I)Ljava/lang/Object;
      10: checkcast     #50                 // class org/apache/hadoop/hbase/protobuf/generated/ClientProtos$MutationProtoOrBuilder
      13: areturn

  public boolean hasNonceGroup();
    Code:
       0: aload_0
       1: getfield      #2                  // Field bitField0_:I
       4: iconst_1
       5: iand
       6: iconst_1
       7: if_icmpne     14
      10: iconst_1
      11: goto          15
      14: iconst_0
      15: ireturn

  public long getNonceGroup();
    Code:
       0: aload_0
       1: getfield      #5                  // Field nonceGroup_:J
       4: lreturn

  public boolean hasNonce();
    Code:
       0: aload_0
       1: getfield      #2                  // Field bitField0_:I
       4: iconst_2
       5: iand
       6: iconst_2
       7: if_icmpne     14
      10: iconst_1
      11: goto          15
      14: iconst_0
      15: ireturn

  public long getNonce();
    Code:
       0: aload_0
       1: getfield      #4                  // Field nonce_:J
       4: lreturn

  public boolean hasRegion();
    Code:
       0: aload_0
       1: getfield      #2                  // Field bitField0_:I
       4: iconst_4
       5: iand
       6: iconst_4
       7: if_icmpne     14
      10: iconst_1
      11: goto          15
      14: iconst_0
      15: ireturn

  public org.apache.hadoop.hbase.protobuf.generated.HBaseProtos$RegionSpecifier getRegion();
    Code:
       0: aload_0
       1: getfield      #3                  // Field region_:Lorg/apache/hadoop/hbase/protobuf/generated/HBaseProtos$RegionSpecifier;
       4: areturn

  public org.apache.hadoop.hbase.protobuf.generated.HBaseProtos$RegionSpecifierOrBuilder getRegionOrBuilder();
    Code:
       0: aload_0
       1: getfield      #3                  // Field region_:Lorg/apache/hadoop/hbase/protobuf/generated/HBaseProtos$RegionSpecifier;
       4: areturn

  public final boolean isInitialized();
    Code:
       0: aload_0
       1: getfield      #10                 // Field memoizedIsInitialized:B
       4: istore_1
       5: iload_1
       6: iconst_m1
       7: if_icmpeq     21
      10: iload_1
      11: iconst_1
      12: if_icmpne     19
      15: iconst_1
      16: goto          20
      19: iconst_0
      20: ireturn
      21: iconst_0
      22: istore_2
      23: iload_2
      24: aload_0
      25: invokevirtual #53                 // Method getMutationRequestCount:()I
      28: if_icmpge     55
      31: aload_0
      32: iload_2
      33: invokevirtual #54                 // Method getMutationRequest:(I)Lorg/apache/hadoop/hbase/protobuf/generated/ClientProtos$MutationProto;
      36: invokevirtual #55                 // Method org/apache/hadoop/hbase/protobuf/generated/ClientProtos$MutationProto.isInitialized:()Z
      39: ifne          49
      42: aload_0
      43: iconst_0
      44: putfield      #10                 // Field memoizedIsInitialized:B
      47: iconst_0
      48: ireturn
      49: iinc          2, 1
      52: goto          23
      55: aload_0
      56: invokevirtual #56                 // Method hasRegion:()Z
      59: ifeq          79
      62: aload_0
      63: invokevirtual #57                 // Method getRegion:()Lorg/apache/hadoop/hbase/protobuf/generated/HBaseProtos$RegionSpecifier;
      66: invokevirtual #58                 // Method org/apache/hadoop/hbase/protobuf/generated/HBaseProtos$RegionSpecifier.isInitialized:()Z
      69: ifne          79
      72: aload_0
      73: iconst_0
      74: putfield      #10                 // Field memoizedIsInitialized:B
      77: iconst_0
      78: ireturn
      79: aload_0
      80: iconst_1
      81: putfield      #10                 // Field memoizedIsInitialized:B
      84: iconst_1
      85: ireturn

  public void writeTo(com.google.protobuf.CodedOutputStream) throws java.io.IOException;
    Code:
       0: aload_0
       1: invokevirtual #59                 // Method getSerializedSize:()I
       4: pop
       5: iconst_0
       6: istore_2
       7: iload_2
       8: aload_0
       9: getfield      #6                  // Field mutationRequest_:Ljava/util/List;
      12: invokeinterface #47,  1           // InterfaceMethod java/util/List.size:()I
      17: if_icmpge     44
      20: aload_1
      21: iconst_1
      22: aload_0
      23: getfield      #6                  // Field mutationRequest_:Ljava/util/List;
      26: iload_2
      27: invokeinterface #48,  2           // InterfaceMethod java/util/List.get:(I)Ljava/lang/Object;
      32: checkcast     #60                 // class com/google/protobuf/MessageLite
      35: invokevirtual #61                 // Method com/google/protobuf/CodedOutputStream.writeMessage:(ILcom/google/protobuf/MessageLite;)V
      38: iinc          2, 1
      41: goto          7
      44: aload_0
      45: getfield      #2                  // Field bitField0_:I
      48: iconst_1
      49: iand
      50: iconst_1
      51: if_icmpne     63
      54: aload_1
      55: iconst_2
      56: aload_0
      57: getfield      #5                  // Field nonceGroup_:J
      60: invokevirtual #62                 // Method com/google/protobuf/CodedOutputStream.writeUInt64:(IJ)V
      63: aload_0
      64: getfield      #2                  // Field bitField0_:I
      67: iconst_2
      68: iand
      69: iconst_2
      70: if_icmpne     82
      73: aload_1
      74: iconst_3
      75: aload_0
      76: getfield      #4                  // Field nonce_:J
      79: invokevirtual #62                 // Method com/google/protobuf/CodedOutputStream.writeUInt64:(IJ)V
      82: aload_0
      83: getfield      #2                  // Field bitField0_:I
      86: iconst_4
      87: iand
      88: iconst_4
      89: if_icmpne     101
      92: aload_1
      93: iconst_4
      94: aload_0
      95: getfield      #3                  // Field region_:Lorg/apache/hadoop/hbase/protobuf/generated/HBaseProtos$RegionSpecifier;
      98: invokevirtual #61                 // Method com/google/protobuf/CodedOutputStream.writeMessage:(ILcom/google/protobuf/MessageLite;)V
     101: aload_0
     102: invokevirtual #63                 // Method getUnknownFields:()Lcom/google/protobuf/UnknownFieldSet;
     105: aload_1
     106: invokevirtual #64                 // Method com/google/protobuf/UnknownFieldSet.writeTo:(Lcom/google/protobuf/CodedOutputStream;)V
     109: return

  public int getSerializedSize();
    Code:
       0: aload_0
       1: getfield      #11                 // Field memoizedSerializedSize:I
       4: istore_1
       5: iload_1
       6: iconst_m1
       7: if_icmpeq     12
      10: iload_1
      11: ireturn
      12: iconst_0
      13: istore_1
      14: iconst_0
      15: istore_2
      16: iload_2
      17: aload_0
      18: getfield      #6                  // Field mutationRequest_:Ljava/util/List;
      21: invokeinterface #47,  1           // InterfaceMethod java/util/List.size:()I
      26: if_icmpge     55
      29: iload_1
      30: iconst_1
      31: aload_0
      32: getfield      #6                  // Field mutationRequest_:Ljava/util/List;
      35: iload_2
      36: invokeinterface #48,  2           // InterfaceMethod java/util/List.get:(I)Ljava/lang/Object;
      41: checkcast     #60                 // class com/google/protobuf/MessageLite
      44: invokestatic  #65                 // Method com/google/protobuf/CodedOutputStream.computeMessageSize:(ILcom/google/protobuf/MessageLite;)I
      47: iadd
      48: istore_1
      49: iinc          2, 1
      52: goto          16
      55: aload_0
      56: getfield      #2                  // Field bitField0_:I
      59: iconst_1
      60: iand
      61: iconst_1
      62: if_icmpne     76
      65: iload_1
      66: iconst_2
      67: aload_0
      68: getfield      #5                  // Field nonceGroup_:J
      71: invokestatic  #66                 // Method com/google/protobuf/CodedOutputStream.computeUInt64Size:(IJ)I
      74: iadd
      75: istore_1
      76: aload_0
      77: getfield      #2                  // Field bitField0_:I
      80: iconst_2
      81: iand
      82: iconst_2
      83: if_icmpne     97
      86: iload_1
      87: iconst_3
      88: aload_0
      89: getfield      #4                  // Field nonce_:J
      92: invokestatic  #66                 // Method com/google/protobuf/CodedOutputStream.computeUInt64Size:(IJ)I
      95: iadd
      96: istore_1
      97: aload_0
      98: getfield      #2                  // Field bitField0_:I
     101: iconst_4
     102: iand
     103: iconst_4
     104: if_icmpne     118
     107: iload_1
     108: iconst_4
     109: aload_0
     110: getfield      #3                  // Field region_:Lorg/apache/hadoop/hbase/protobuf/generated/HBaseProtos$RegionSpecifier;
     113: invokestatic  #65                 // Method com/google/protobuf/CodedOutputStream.computeMessageSize:(ILcom/google/protobuf/MessageLite;)I
     116: iadd
     117: istore_1
     118: iload_1
     119: aload_0
     120: invokevirtual #63                 // Method getUnknownFields:()Lcom/google/protobuf/UnknownFieldSet;
     123: invokevirtual #67                 // Method com/google/protobuf/UnknownFieldSet.getSerializedSize:()I
     126: iadd
     127: istore_1
     128: aload_0
     129: iload_1
     130: putfield      #11                 // Field memoizedSerializedSize:I
     133: iload_1
     134: ireturn

  protected java.lang.Object writeReplace() throws java.io.ObjectStreamException;
    Code:
       0: aload_0
       1: invokespecial #68                 // Method com/google/protobuf/GeneratedMessage.writeReplace:()Ljava/lang/Object;
       4: areturn

  public boolean equals(java.lang.Object);
    Code:
       0: aload_1
       1: aload_0
       2: if_acmpne     7
       5: iconst_1
       6: ireturn
       7: aload_1
       8: instanceof    #43                 // class org/apache/hadoop/hbase/protobuf/generated/MultiRowMutationProtos$MutateRowsRequest
      11: ifne          20
      14: aload_0
      15: aload_1
      16: invokespecial #69                 // Method com/google/protobuf/GeneratedMessage.equals:(Ljava/lang/Object;)Z
      19: ireturn
      20: aload_1
      21: checkcast     #43                 // class org/apache/hadoop/hbase/protobuf/generated/MultiRowMutationProtos$MutateRowsRequest
      24: astore_2
      25: iconst_1
      26: istore_3
      27: iload_3
      28: ifeq          51
      31: aload_0
      32: invokevirtual #70                 // Method getMutationRequestList:()Ljava/util/List;
      35: aload_2
      36: invokevirtual #70                 // Method getMutationRequestList:()Ljava/util/List;
      39: invokeinterface #71,  2           // InterfaceMethod java/util/List.equals:(Ljava/lang/Object;)Z
      44: ifeq          51
      47: iconst_1
      48: goto          52
      51: iconst_0
      52: istore_3
      53: iload_3
      54: ifeq          72
      57: aload_0
      58: invokevirtual #72                 // Method hasNonceGroup:()Z
      61: aload_2
      62: invokevirtual #72                 // Method hasNonceGroup:()Z
      65: if_icmpne     72
      68: iconst_1
      69: goto          73
      72: iconst_0
      73: istore_3
      74: aload_0
      75: invokevirtual #72                 // Method hasNonceGroup:()Z
      78: ifeq          103
      81: iload_3
      82: ifeq          101
      85: aload_0
      86: invokevirtual #73                 // Method getNonceGroup:()J
      89: aload_2
      90: invokevirtual #73                 // Method getNonceGroup:()J
      93: lcmp
      94: ifne          101
      97: iconst_1
      98: goto          102
     101: iconst_0
     102: istore_3
     103: iload_3
     104: ifeq          122
     107: aload_0
     108: invokevirtual #74                 // Method hasNonce:()Z
     111: aload_2
     112: invokevirtual #74                 // Method hasNonce:()Z
     115: if_icmpne     122
     118: iconst_1
     119: goto          123
     122: iconst_0
     123: istore_3
     124: aload_0
     125: invokevirtual #74                 // Method hasNonce:()Z
     128: ifeq          153
     131: iload_3
     132: ifeq          151
     135: aload_0
     136: invokevirtual #75                 // Method getNonce:()J
     139: aload_2
     140: invokevirtual #75                 // Method getNonce:()J
     143: lcmp
     144: ifne          151
     147: iconst_1
     148: goto          152
     151: iconst_0
     152: istore_3
     153: iload_3
     154: ifeq          172
     157: aload_0
     158: invokevirtual #56                 // Method hasRegion:()Z
     161: aload_2
     162: invokevirtual #56                 // Method hasRegion:()Z
     165: if_icmpne     172
     168: iconst_1
     169: goto          173
     172: iconst_0
     173: istore_3
     174: aload_0
     175: invokevirtual #56                 // Method hasRegion:()Z
     178: ifeq          205
     181: iload_3
     182: ifeq          203
     185: aload_0
     186: invokevirtual #57                 // Method getRegion:()Lorg/apache/hadoop/hbase/protobuf/generated/HBaseProtos$RegionSpecifier;
     189: aload_2
     190: invokevirtual #57                 // Method getRegion:()Lorg/apache/hadoop/hbase/protobuf/generated/HBaseProtos$RegionSpecifier;
     193: invokevirtual #76                 // Method org/apache/hadoop/hbase/protobuf/generated/HBaseProtos$RegionSpecifier.equals:(Ljava/lang/Object;)Z
     196: ifeq          203
     199: iconst_1
     200: goto          204
     203: iconst_0
     204: istore_3
     205: iload_3
     206: ifeq          227
     209: aload_0
     210: invokevirtual #63                 // Method getUnknownFields:()Lcom/google/protobuf/UnknownFieldSet;
     213: aload_2
     214: invokevirtual #63                 // Method getUnknownFields:()Lcom/google/protobuf/UnknownFieldSet;
     217: invokevirtual #77                 // Method com/google/protobuf/UnknownFieldSet.equals:(Ljava/lang/Object;)Z
     220: ifeq          227
     223: iconst_1
     224: goto          228
     227: iconst_0
     228: istore_3
     229: iload_3
     230: ireturn

  public int hashCode();
    Code:
       0: aload_0
       1: getfield      #12                 // Field memoizedHashCode:I
       4: ifeq          12
       7: aload_0
       8: getfield      #12                 // Field memoizedHashCode:I
      11: ireturn
      12: bipush        41
      14: istore_1
      15: bipush        19
      17: iload_1
      18: imul
      19: aload_0
      20: invokevirtual #78                 // Method getDescriptorForType:()Lcom/google/protobuf/Descriptors$Descriptor;
      23: invokevirtual #79                 // Method java/lang/Object.hashCode:()I
      26: iadd
      27: istore_1
      28: aload_0
      29: invokevirtual #53                 // Method getMutationRequestCount:()I
      32: ifle          57
      35: bipush        37
      37: iload_1
      38: imul
      39: iconst_1
      40: iadd
      41: istore_1
      42: bipush        53
      44: iload_1
      45: imul
      46: aload_0
      47: invokevirtual #70                 // Method getMutationRequestList:()Ljava/util/List;
      50: invokeinterface #80,  1           // InterfaceMethod java/util/List.hashCode:()I
      55: iadd
      56: istore_1
      57: aload_0
      58: invokevirtual #72                 // Method hasNonceGroup:()Z
      61: ifeq          84
      64: bipush        37
      66: iload_1
      67: imul
      68: iconst_2
      69: iadd
      70: istore_1
      71: bipush        53
      73: iload_1
      74: imul
      75: aload_0
      76: invokevirtual #73                 // Method getNonceGroup:()J
      79: invokestatic  #81                 // Method hashLong:(J)I
      82: iadd
      83: istore_1
      84: aload_0
      85: invokevirtual #74                 // Method hasNonce:()Z
      88: ifeq          111
      91: bipush        37
      93: iload_1
      94: imul
      95: iconst_3
      96: iadd
      97: istore_1
      98: bipush        53
     100: iload_1
     101: imul
     102: aload_0
     103: invokevirtual #75                 // Method getNonce:()J
     106: invokestatic  #81                 // Method hashLong:(J)I
     109: iadd
     110: istore_1
     111: aload_0
     112: invokevirtual #56                 // Method hasRegion:()Z
     115: ifeq          138
     118: bipush        37
     120: iload_1
     121: imul
     122: iconst_4
     123: iadd
     124: istore_1
     125: bipush        53
     127: iload_1
     128: imul
     129: aload_0
     130: invokevirtual #57                 // Method getRegion:()Lorg/apache/hadoop/hbase/protobuf/generated/HBaseProtos$RegionSpecifier;
     133: invokevirtual #82                 // Method org/apache/hadoop/hbase/protobuf/generated/HBaseProtos$RegionSpecifier.hashCode:()I
     136: iadd
     137: istore_1
     138: bipush        29
     140: iload_1
     141: imul
     142: aload_0
     143: invokevirtual #63                 // Method getUnknownFields:()Lcom/google/protobuf/UnknownFieldSet;
     146: invokevirtual #83                 // Method com/google/protobuf/UnknownFieldSet.hashCode:()I
     149: iadd
     150: istore_1
     151: aload_0
     152: iload_1
     153: putfield      #12                 // Field memoizedHashCode:I
     156: iload_1
     157: ireturn

  public static org.apache.hadoop.hbase.protobuf.generated.MultiRowMutationProtos$MutateRowsRequest parseFrom(com.google.protobuf.ByteString) throws com.google.protobuf.InvalidProtocolBufferException;
    Code:
       0: getstatic     #46                 // Field PARSER:Lcom/google/protobuf/Parser;
       3: aload_0
       4: invokeinterface #84,  2           // InterfaceMethod com/google/protobuf/Parser.parseFrom:(Lcom/google/protobuf/ByteString;)Ljava/lang/Object;
       9: checkcast     #43                 // class org/apache/hadoop/hbase/protobuf/generated/MultiRowMutationProtos$MutateRowsRequest
      12: areturn

  public static org.apache.hadoop.hbase.protobuf.generated.MultiRowMutationProtos$MutateRowsRequest parseFrom(com.google.protobuf.ByteString, com.google.protobuf.ExtensionRegistryLite) throws com.google.protobuf.InvalidProtocolBufferException;
    Code:
       0: getstatic     #46                 // Field PARSER:Lcom/google/protobuf/Parser;
       3: aload_0
       4: aload_1
       5: invokeinterface #85,  3           // InterfaceMethod com/google/protobuf/Parser.parseFrom:(Lcom/google/protobuf/ByteString;Lcom/google/protobuf/ExtensionRegistryLite;)Ljava/lang/Object;
      10: checkcast     #43                 // class org/apache/hadoop/hbase/protobuf/generated/MultiRowMutationProtos$MutateRowsRequest
      13: areturn

  public static org.apache.hadoop.hbase.protobuf.generated.MultiRowMutationProtos$MutateRowsRequest parseFrom(byte[]) throws com.google.protobuf.InvalidProtocolBufferException;
    Code:
       0: getstatic     #46                 // Field PARSER:Lcom/google/protobuf/Parser;
       3: aload_0
       4: invokeinterface #86,  2           // InterfaceMethod com/google/protobuf/Parser.parseFrom:([B)Ljava/lang/Object;
       9: checkcast     #43                 // class org/apache/hadoop/hbase/protobuf/generated/MultiRowMutationProtos$MutateRowsRequest
      12: areturn

  public static org.apache.hadoop.hbase.protobuf.generated.MultiRowMutationProtos$MutateRowsRequest parseFrom(byte[], com.google.protobuf.ExtensionRegistryLite) throws com.google.protobuf.InvalidProtocolBufferException;
    Code:
       0: getstatic     #46                 // Field PARSER:Lcom/google/protobuf/Parser;
       3: aload_0
       4: aload_1
       5: invokeinterface #87,  3           // InterfaceMethod com/google/protobuf/Parser.parseFrom:([BLcom/google/protobuf/ExtensionRegistryLite;)Ljava/lang/Object;
      10: checkcast     #43                 // class org/apache/hadoop/hbase/protobuf/generated/MultiRowMutationProtos$MutateRowsRequest
      13: areturn

  public static org.apache.hadoop.hbase.protobuf.generated.MultiRowMutationProtos$MutateRowsRequest parseFrom(java.io.InputStream) throws java.io.IOException;
    Code:
       0: getstatic     #46                 // Field PARSER:Lcom/google/protobuf/Parser;
       3: aload_0
       4: invokeinterface #88,  2           // InterfaceMethod com/google/protobuf/Parser.parseFrom:(Ljava/io/InputStream;)Ljava/lang/Object;
       9: checkcast     #43                 // class org/apache/hadoop/hbase/protobuf/generated/MultiRowMutationProtos$MutateRowsRequest
      12: areturn

  public static org.apache.hadoop.hbase.protobuf.generated.MultiRowMutationProtos$MutateRowsRequest parseFrom(java.io.InputStream, com.google.protobuf.ExtensionRegistryLite) throws java.io.IOException;
    Code:
       0: getstatic     #46                 // Field PARSER:Lcom/google/protobuf/Parser;
       3: aload_0
       4: aload_1
       5: invokeinterface #89,  3           // InterfaceMethod com/google/protobuf/Parser.parseFrom:(Ljava/io/InputStream;Lcom/google/protobuf/ExtensionRegistryLite;)Ljava/lang/Object;
      10: checkcast     #43                 // class org/apache/hadoop/hbase/protobuf/generated/MultiRowMutationProtos$MutateRowsRequest
      13: areturn

  public static org.apache.hadoop.hbase.protobuf.generated.MultiRowMutationProtos$MutateRowsRequest parseDelimitedFrom(java.io.InputStream) throws java.io.IOException;
    Code:
       0: getstatic     #46                 // Field PARSER:Lcom/google/protobuf/Parser;
       3: aload_0
       4: invokeinterface #90,  2           // InterfaceMethod com/google/protobuf/Parser.parseDelimitedFrom:(Ljava/io/InputStream;)Ljava/lang/Object;
       9: checkcast     #43                 // class org/apache/hadoop/hbase/protobuf/generated/MultiRowMutationProtos$MutateRowsRequest
      12: areturn

  public static org.apache.hadoop.hbase.protobuf.generated.MultiRowMutationProtos$MutateRowsRequest parseDelimitedFrom(java.io.InputStream, com.google.protobuf.ExtensionRegistryLite) throws java.io.IOException;
    Code:
       0: getstatic     #46                 // Field PARSER:Lcom/google/protobuf/Parser;
       3: aload_0
       4: aload_1
       5: invokeinterface #91,  3           // InterfaceMethod com/google/protobuf/Parser.parseDelimitedFrom:(Ljava/io/InputStream;Lcom/google/protobuf/ExtensionRegistryLite;)Ljava/lang/Object;
      10: checkcast     #43                 // class org/apache/hadoop/hbase/protobuf/generated/MultiRowMutationProtos$MutateRowsRequest
      13: areturn

  public static org.apache.hadoop.hbase.protobuf.generated.MultiRowMutationProtos$MutateRowsRequest parseFrom(com.google.protobuf.CodedInputStream) throws java.io.IOException;
    Code:
       0: getstatic     #46                 // Field PARSER:Lcom/google/protobuf/Parser;
       3: aload_0
       4: invokeinterface #92,  2           // InterfaceMethod com/google/protobuf/Parser.parseFrom:(Lcom/google/protobuf/CodedInputStream;)Ljava/lang/Object;
       9: checkcast     #43                 // class org/apache/hadoop/hbase/protobuf/generated/MultiRowMutationProtos$MutateRowsRequest
      12: areturn

  public static org.apache.hadoop.hbase.protobuf.generated.MultiRowMutationProtos$MutateRowsRequest parseFrom(com.google.protobuf.CodedInputStream, com.google.protobuf.ExtensionRegistryLite) throws java.io.IOException;
    Code:
       0: getstatic     #46                 // Field PARSER:Lcom/google/protobuf/Parser;
       3: aload_0
       4: aload_1
       5: invokeinterface #93,  3           // InterfaceMethod com/google/protobuf/Parser.parseFrom:(Lcom/google/protobuf/CodedInputStream;Lcom/google/protobuf/ExtensionRegistryLite;)Ljava/lang/Object;
      10: checkcast     #43                 // class org/apache/hadoop/hbase/protobuf/generated/MultiRowMutationProtos$MutateRowsRequest
      13: areturn

  public static org.apache.hadoop.hbase.protobuf.generated.MultiRowMutationProtos$MutateRowsRequest$Builder newBuilder();
    Code:
       0: invokestatic  #94                 // Method org/apache/hadoop/hbase/protobuf/generated/MultiRowMutationProtos$MutateRowsRequest$Builder.access$1700:()Lorg/apache/hadoop/hbase/protobuf/generated/MultiRowMutationProtos$MutateRowsRequest$Builder;
       3: areturn

  public org.apache.hadoop.hbase.protobuf.generated.MultiRowMutationProtos$MutateRowsRequest$Builder newBuilderForType();
    Code:
       0: invokestatic  #95                 // Method newBuilder:()Lorg/apache/hadoop/hbase/protobuf/generated/MultiRowMutationProtos$MutateRowsRequest$Builder;
       3: areturn

  public static org.apache.hadoop.hbase.protobuf.generated.MultiRowMutationProtos$MutateRowsRequest$Builder newBuilder(org.apache.hadoop.hbase.protobuf.generated.MultiRowMutationProtos$MutateRowsRequest);
    Code:
       0: invokestatic  #95                 // Method newBuilder:()Lorg/apache/hadoop/hbase/protobuf/generated/MultiRowMutationProtos$MutateRowsRequest$Builder;
       3: aload_0
       4: invokevirtual #96                 // Method org/apache/hadoop/hbase/protobuf/generated/MultiRowMutationProtos$MutateRowsRequest$Builder.mergeFrom:(Lorg/apache/hadoop/hbase/protobuf/generated/MultiRowMutationProtos$MutateRowsRequest;)Lorg/apache/hadoop/hbase/protobuf/generated/MultiRowMutationProtos$MutateRowsRequest$Builder;
       7: areturn

  public org.apache.hadoop.hbase.protobuf.generated.MultiRowMutationProtos$MutateRowsRequest$Builder toBuilder();
    Code:
       0: aload_0
       1: invokestatic  #97                 // Method newBuilder:(Lorg/apache/hadoop/hbase/protobuf/generated/MultiRowMutationProtos$MutateRowsRequest;)Lorg/apache/hadoop/hbase/protobuf/generated/MultiRowMutationProtos$MutateRowsRequest$Builder;
       4: areturn

  protected org.apache.hadoop.hbase.protobuf.generated.MultiRowMutationProtos$MutateRowsRequest$Builder newBuilderForType(com.google.protobuf.GeneratedMessage$BuilderParent);
    Code:
       0: new           #44                 // class org/apache/hadoop/hbase/protobuf/generated/MultiRowMutationProtos$MutateRowsRequest$Builder
       3: dup
       4: aload_1
       5: aconst_null
       6: invokespecial #98                 // Method org/apache/hadoop/hbase/protobuf/generated/MultiRowMutationProtos$MutateRowsRequest$Builder."<init>":(Lcom/google/protobuf/GeneratedMessage$BuilderParent;Lorg/apache/hadoop/hbase/protobuf/generated/MultiRowMutationProtos$1;)V
       9: astore_2
      10: aload_2
      11: areturn

  protected com.google.protobuf.Message$Builder newBuilderForType(com.google.protobuf.GeneratedMessage$BuilderParent);
    Code:
       0: aload_0
       1: aload_1
       2: invokevirtual #99                 // Method newBuilderForType:(Lcom/google/protobuf/GeneratedMessage$BuilderParent;)Lorg/apache/hadoop/hbase/protobuf/generated/MultiRowMutationProtos$MutateRowsRequest$Builder;
       5: areturn

  public com.google.protobuf.Message$Builder toBuilder();
    Code:
       0: aload_0
       1: invokevirtual #100                // Method toBuilder:()Lorg/apache/hadoop/hbase/protobuf/generated/MultiRowMutationProtos$MutateRowsRequest$Builder;
       4: areturn

  public com.google.protobuf.Message$Builder newBuilderForType();
    Code:
       0: aload_0
       1: invokevirtual #101                // Method newBuilderForType:()Lorg/apache/hadoop/hbase/protobuf/generated/MultiRowMutationProtos$MutateRowsRequest$Builder;
       4: areturn

  public com.google.protobuf.MessageLite$Builder toBuilder();
    Code:
       0: aload_0
       1: invokevirtual #100                // Method toBuilder:()Lorg/apache/hadoop/hbase/protobuf/generated/MultiRowMutationProtos$MutateRowsRequest$Builder;
       4: areturn

  public com.google.protobuf.MessageLite$Builder newBuilderForType();
    Code:
       0: aload_0
       1: invokevirtual #101                // Method newBuilderForType:()Lorg/apache/hadoop/hbase/protobuf/generated/MultiRowMutationProtos$MutateRowsRequest$Builder;
       4: areturn

  public com.google.protobuf.MessageLite getDefaultInstanceForType();
    Code:
       0: aload_0
       1: invokevirtual #102                // Method getDefaultInstanceForType:()Lorg/apache/hadoop/hbase/protobuf/generated/MultiRowMutationProtos$MutateRowsRequest;
       4: areturn

  public com.google.protobuf.Message getDefaultInstanceForType();
    Code:
       0: aload_0
       1: invokevirtual #102                // Method getDefaultInstanceForType:()Lorg/apache/hadoop/hbase/protobuf/generated/MultiRowMutationProtos$MutateRowsRequest;
       4: areturn

  org.apache.hadoop.hbase.protobuf.generated.MultiRowMutationProtos$MutateRowsRequest(com.google.protobuf.CodedInputStream, com.google.protobuf.ExtensionRegistryLite, org.apache.hadoop.hbase.protobuf.generated.MultiRowMutationProtos$1) throws com.google.protobuf.InvalidProtocolBufferException;
    Code:
       0: aload_0
       1: aload_1
       2: aload_2
       3: invokespecial #8                  // Method "<init>":(Lcom/google/protobuf/CodedInputStream;Lcom/google/protobuf/ExtensionRegistryLite;)V
       6: return

  static boolean access$1900();
    Code:
       0: getstatic     #1                  // Field alwaysUseFieldBuilders:Z
       3: ireturn

  org.apache.hadoop.hbase.protobuf.generated.MultiRowMutationProtos$MutateRowsRequest(com.google.protobuf.GeneratedMessage$Builder, org.apache.hadoop.hbase.protobuf.generated.MultiRowMutationProtos$1);
    Code:
       0: aload_0
       1: aload_1
       2: invokespecial #7                  // Method "<init>":(Lcom/google/protobuf/GeneratedMessage$Builder;)V
       5: return

  static java.util.List access$2102(org.apache.hadoop.hbase.protobuf.generated.MultiRowMutationProtos$MutateRowsRequest, java.util.List);
    Code:
       0: aload_0
       1: aload_1
       2: dup_x1
       3: putfield      #6                  // Field mutationRequest_:Ljava/util/List;
       6: areturn

  static long access$2202(org.apache.hadoop.hbase.protobuf.generated.MultiRowMutationProtos$MutateRowsRequest, long);
    Code:
       0: aload_0
       1: lload_1
       2: dup2_x1
       3: putfield      #5                  // Field nonceGroup_:J
       6: lreturn

  static long access$2302(org.apache.hadoop.hbase.protobuf.generated.MultiRowMutationProtos$MutateRowsRequest, long);
    Code:
       0: aload_0
       1: lload_1
       2: dup2_x1
       3: putfield      #4                  // Field nonce_:J
       6: lreturn

  static org.apache.hadoop.hbase.protobuf.generated.HBaseProtos$RegionSpecifier access$2402(org.apache.hadoop.hbase.protobuf.generated.MultiRowMutationProtos$MutateRowsRequest, org.apache.hadoop.hbase.protobuf.generated.HBaseProtos$RegionSpecifier);
    Code:
       0: aload_0
       1: aload_1
       2: dup_x1
       3: putfield      #3                  // Field region_:Lorg/apache/hadoop/hbase/protobuf/generated/HBaseProtos$RegionSpecifier;
       6: areturn

  static int access$2502(org.apache.hadoop.hbase.protobuf.generated.MultiRowMutationProtos$MutateRowsRequest, int);
    Code:
       0: aload_0
       1: iload_1
       2: dup_x1
       3: putfield      #2                  // Field bitField0_:I
       6: ireturn

  static java.util.List access$2100(org.apache.hadoop.hbase.protobuf.generated.MultiRowMutationProtos$MutateRowsRequest);
    Code:
       0: aload_0
       1: getfield      #6                  // Field mutationRequest_:Ljava/util/List;
       4: areturn

  static boolean access$2600();
    Code:
       0: getstatic     #1                  // Field alwaysUseFieldBuilders:Z
       3: ireturn

  static {};
    Code:
       0: new           #103                // class org/apache/hadoop/hbase/protobuf/generated/MultiRowMutationProtos$MutateRowsRequest$1
       3: dup
       4: invokespecial #104                // Method org/apache/hadoop/hbase/protobuf/generated/MultiRowMutationProtos$MutateRowsRequest$1."<init>":()V
       7: putstatic     #46                 // Field PARSER:Lcom/google/protobuf/Parser;
      10: new           #43                 // class org/apache/hadoop/hbase/protobuf/generated/MultiRowMutationProtos$MutateRowsRequest
      13: dup
      14: iconst_1
      15: invokespecial #105                // Method "<init>":(Z)V
      18: putstatic     #17                 // Field defaultInstance:Lorg/apache/hadoop/hbase/protobuf/generated/MultiRowMutationProtos$MutateRowsRequest;
      21: getstatic     #17                 // Field defaultInstance:Lorg/apache/hadoop/hbase/protobuf/generated/MultiRowMutationProtos$MutateRowsRequest;
      24: invokespecial #18                 // Method initFields:()V
      27: return
}
