Compiled from "MultiRowMutationProtos.java"
final class org.apache.hadoop.hbase.protobuf.generated.MultiRowMutationProtos$MultiRowMutationService$1 extends org.apache.hadoop.hbase.protobuf.generated.MultiRowMutationProtos$MultiRowMutationService {
  final org.apache.hadoop.hbase.protobuf.generated.MultiRowMutationProtos$MultiRowMutationService$Interface val$impl;

  org.apache.hadoop.hbase.protobuf.generated.MultiRowMutationProtos$MultiRowMutationService$1(org.apache.hadoop.hbase.protobuf.generated.MultiRowMutationProtos$MultiRowMutationService$Interface);
    Code:
       0: aload_0
       1: aload_1
       2: putfield      #1                  // Field val$impl:Lorg/apache/hadoop/hbase/protobuf/generated/MultiRowMutationProtos$MultiRowMutationService$Interface;
       5: aload_0
       6: invokespecial #2                  // Method org/apache/hadoop/hbase/protobuf/generated/MultiRowMutationProtos$MultiRowMutationService."<init>":()V
       9: return

  public void mutateRows(com.google.protobuf.RpcController, org.apache.hadoop.hbase.protobuf.generated.MultiRowMutationProtos$MutateRowsRequest, com.google.protobuf.RpcCallback<org.apache.hadoop.hbase.protobuf.generated.MultiRowMutationProtos$MutateRowsResponse>);
    Code:
       0: aload_0
       1: getfield      #1                  // Field val$impl:Lorg/apache/hadoop/hbase/protobuf/generated/MultiRowMutationProtos$MultiRowMutationService$Interface;
       4: aload_1
       5: aload_2
       6: aload_3
       7: invokeinterface #3,  4            // InterfaceMethod org/apache/hadoop/hbase/protobuf/generated/MultiRowMutationProtos$MultiRowMutationService$Interface.mutateRows:(Lcom/google/protobuf/RpcController;Lorg/apache/hadoop/hbase/protobuf/generated/MultiRowMutationProtos$MutateRowsRequest;Lcom/google/protobuf/RpcCallback;)V
      12: return
}
