Compiled from "MutableHistogram.java"
public class org.apache.hadoop.metrics2.lib.MutableHistogram extends org.apache.hadoop.metrics2.lib.MutableMetric implements org.apache.hadoop.metrics2.MetricHistogram {
  protected org.apache.hadoop.hbase.metrics.impl.HistogramImpl histogram;

  protected final java.lang.String name;

  protected final java.lang.String desc;

  public org.apache.hadoop.metrics2.lib.MutableHistogram(org.apache.hadoop.metrics2.MetricsInfo);
    Code:
       0: aload_0
       1: aload_1
       2: invokeinterface #1,  1            // InterfaceMethod org/apache/hadoop/metrics2/MetricsInfo.name:()Ljava/lang/String;
       7: aload_1
       8: invokeinterface #2,  1            // InterfaceMethod org/apache/hadoop/metrics2/MetricsInfo.description:()Ljava/lang/String;
      13: invokespecial #3                  // Method "<init>":(Ljava/lang/String;Ljava/lang/String;)V
      16: return

  public org.apache.hadoop.metrics2.lib.MutableHistogram(java.lang.String, java.lang.String);
    Code:
       0: aload_0
       1: aload_1
       2: aload_2
       3: ldc2_w        #5                  // long -4l
       6: invokespecial #7                  // Method "<init>":(Ljava/lang/String;Ljava/lang/String;J)V
       9: return

  protected org.apache.hadoop.metrics2.lib.MutableHistogram(java.lang.String, java.lang.String, long);
    Code:
       0: aload_0
       1: invokespecial #8                  // Method org/apache/hadoop/metrics2/lib/MutableMetric."<init>":()V
       4: aload_0
       5: aload_1
       6: invokestatic  #9                  // Method org/apache/commons/lang3/StringUtils.capitalize:(Ljava/lang/String;)Ljava/lang/String;
       9: putfield      #10                 // Field name:Ljava/lang/String;
      12: aload_0
      13: aload_2
      14: invokestatic  #11                 // Method org/apache/commons/lang3/StringUtils.uncapitalize:(Ljava/lang/String;)Ljava/lang/String;
      17: putfield      #12                 // Field desc:Ljava/lang/String;
      20: aload_0
      21: new           #13                 // class org/apache/hadoop/hbase/metrics/impl/HistogramImpl
      24: dup
      25: invokespecial #14                 // Method org/apache/hadoop/hbase/metrics/impl/HistogramImpl."<init>":()V
      28: putfield      #15                 // Field histogram:Lorg/apache/hadoop/hbase/metrics/impl/HistogramImpl;
      31: return

  public void add(long);
    Code:
       0: aload_0
       1: getfield      #15                 // Field histogram:Lorg/apache/hadoop/hbase/metrics/impl/HistogramImpl;
       4: lload_1
       5: invokevirtual #16                 // Method org/apache/hadoop/hbase/metrics/impl/HistogramImpl.update:(J)V
       8: return

  public long getMax();
    Code:
       0: aload_0
       1: getfield      #15                 // Field histogram:Lorg/apache/hadoop/hbase/metrics/impl/HistogramImpl;
       4: invokevirtual #17                 // Method org/apache/hadoop/hbase/metrics/impl/HistogramImpl.getMax:()J
       7: lreturn

  public synchronized void snapshot(org.apache.hadoop.metrics2.MetricsRecordBuilder, boolean);
    Code:
       0: aload_0
       1: getfield      #10                 // Field name:Ljava/lang/String;
       4: aload_0
       5: getfield      #12                 // Field desc:Ljava/lang/String;
       8: aload_0
       9: getfield      #15                 // Field histogram:Lorg/apache/hadoop/hbase/metrics/impl/HistogramImpl;
      12: aload_1
      13: iload_2
      14: invokestatic  #18                 // Method snapshot:(Ljava/lang/String;Ljava/lang/String;Lorg/apache/hadoop/hbase/metrics/Histogram;Lorg/apache/hadoop/metrics2/MetricsRecordBuilder;Z)V
      17: return

  public static void snapshot(java.lang.String, java.lang.String, org.apache.hadoop.hbase.metrics.Histogram, org.apache.hadoop.metrics2.MetricsRecordBuilder, boolean);
    Code:
       0: aload_2
       1: invokeinterface #19,  1           // InterfaceMethod org/apache/hadoop/hbase/metrics/Histogram.snapshot:()Lorg/apache/hadoop/hbase/metrics/Snapshot;
       6: astore        5
       8: aload         5
      10: ifnull        22
      13: aload_0
      14: aload_1
      15: aload_2
      16: aload         5
      18: aload_3
      19: invokestatic  #20                 // Method updateSnapshotMetrics:(Ljava/lang/String;Ljava/lang/String;Lorg/apache/hadoop/hbase/metrics/Histogram;Lorg/apache/hadoop/hbase/metrics/Snapshot;Lorg/apache/hadoop/metrics2/MetricsRecordBuilder;)V
      22: return

  protected static void updateSnapshotMetrics(java.lang.String, java.lang.String, org.apache.hadoop.hbase.metrics.Histogram, org.apache.hadoop.hbase.metrics.Snapshot, org.apache.hadoop.metrics2.MetricsRecordBuilder);
    Code:
       0: aload         4
       2: new           #21                 // class java/lang/StringBuilder
       5: dup
       6: invokespecial #22                 // Method java/lang/StringBuilder."<init>":()V
       9: aload_0
      10: invokevirtual #23                 // Method java/lang/StringBuilder.append:(Ljava/lang/String;)Ljava/lang/StringBuilder;
      13: ldc           #25                 // String _num_ops
      15: invokevirtual #23                 // Method java/lang/StringBuilder.append:(Ljava/lang/String;)Ljava/lang/StringBuilder;
      18: invokevirtual #26                 // Method java/lang/StringBuilder.toString:()Ljava/lang/String;
      21: aload_1
      22: invokestatic  #27                 // Method org/apache/hadoop/hbase/metrics/Interns.info:(Ljava/lang/String;Ljava/lang/String;)Lorg/apache/hadoop/metrics2/MetricsInfo;
      25: aload_2
      26: invokeinterface #28,  1           // InterfaceMethod org/apache/hadoop/hbase/metrics/Histogram.getCount:()J
      31: invokevirtual #29                 // Method org/apache/hadoop/metrics2/MetricsRecordBuilder.addCounter:(Lorg/apache/hadoop/metrics2/MetricsInfo;J)Lorg/apache/hadoop/metrics2/MetricsRecordBuilder;
      34: pop
      35: aload         4
      37: new           #21                 // class java/lang/StringBuilder
      40: dup
      41: invokespecial #22                 // Method java/lang/StringBuilder."<init>":()V
      44: aload_0
      45: invokevirtual #23                 // Method java/lang/StringBuilder.append:(Ljava/lang/String;)Ljava/lang/StringBuilder;
      48: ldc           #30                 // String _min
      50: invokevirtual #23                 // Method java/lang/StringBuilder.append:(Ljava/lang/String;)Ljava/lang/StringBuilder;
      53: invokevirtual #26                 // Method java/lang/StringBuilder.toString:()Ljava/lang/String;
      56: aload_1
      57: invokestatic  #27                 // Method org/apache/hadoop/hbase/metrics/Interns.info:(Ljava/lang/String;Ljava/lang/String;)Lorg/apache/hadoop/metrics2/MetricsInfo;
      60: aload_3
      61: invokeinterface #31,  1           // InterfaceMethod org/apache/hadoop/hbase/metrics/Snapshot.getMin:()J
      66: invokevirtual #32                 // Method org/apache/hadoop/metrics2/MetricsRecordBuilder.addGauge:(Lorg/apache/hadoop/metrics2/MetricsInfo;J)Lorg/apache/hadoop/metrics2/MetricsRecordBuilder;
      69: pop
      70: aload         4
      72: new           #21                 // class java/lang/StringBuilder
      75: dup
      76: invokespecial #22                 // Method java/lang/StringBuilder."<init>":()V
      79: aload_0
      80: invokevirtual #23                 // Method java/lang/StringBuilder.append:(Ljava/lang/String;)Ljava/lang/StringBuilder;
      83: ldc           #33                 // String _max
      85: invokevirtual #23                 // Method java/lang/StringBuilder.append:(Ljava/lang/String;)Ljava/lang/StringBuilder;
      88: invokevirtual #26                 // Method java/lang/StringBuilder.toString:()Ljava/lang/String;
      91: aload_1
      92: invokestatic  #27                 // Method org/apache/hadoop/hbase/metrics/Interns.info:(Ljava/lang/String;Ljava/lang/String;)Lorg/apache/hadoop/metrics2/MetricsInfo;
      95: aload_3
      96: invokeinterface #34,  1           // InterfaceMethod org/apache/hadoop/hbase/metrics/Snapshot.getMax:()J
     101: invokevirtual #32                 // Method org/apache/hadoop/metrics2/MetricsRecordBuilder.addGauge:(Lorg/apache/hadoop/metrics2/MetricsInfo;J)Lorg/apache/hadoop/metrics2/MetricsRecordBuilder;
     104: pop
     105: aload         4
     107: new           #21                 // class java/lang/StringBuilder
     110: dup
     111: invokespecial #22                 // Method java/lang/StringBuilder."<init>":()V
     114: aload_0
     115: invokevirtual #23                 // Method java/lang/StringBuilder.append:(Ljava/lang/String;)Ljava/lang/StringBuilder;
     118: ldc           #35                 // String _mean
     120: invokevirtual #23                 // Method java/lang/StringBuilder.append:(Ljava/lang/String;)Ljava/lang/StringBuilder;
     123: invokevirtual #26                 // Method java/lang/StringBuilder.toString:()Ljava/lang/String;
     126: aload_1
     127: invokestatic  #27                 // Method org/apache/hadoop/hbase/metrics/Interns.info:(Ljava/lang/String;Ljava/lang/String;)Lorg/apache/hadoop/metrics2/MetricsInfo;
     130: aload_3
     131: invokeinterface #36,  1           // InterfaceMethod org/apache/hadoop/hbase/metrics/Snapshot.getMean:()J
     136: invokevirtual #32                 // Method org/apache/hadoop/metrics2/MetricsRecordBuilder.addGauge:(Lorg/apache/hadoop/metrics2/MetricsInfo;J)Lorg/apache/hadoop/metrics2/MetricsRecordBuilder;
     139: pop
     140: aload         4
     142: new           #21                 // class java/lang/StringBuilder
     145: dup
     146: invokespecial #22                 // Method java/lang/StringBuilder."<init>":()V
     149: aload_0
     150: invokevirtual #23                 // Method java/lang/StringBuilder.append:(Ljava/lang/String;)Ljava/lang/StringBuilder;
     153: ldc           #37                 // String _25th_percentile
     155: invokevirtual #23                 // Method java/lang/StringBuilder.append:(Ljava/lang/String;)Ljava/lang/StringBuilder;
     158: invokevirtual #26                 // Method java/lang/StringBuilder.toString:()Ljava/lang/String;
     161: aload_1
     162: invokestatic  #27                 // Method org/apache/hadoop/hbase/metrics/Interns.info:(Ljava/lang/String;Ljava/lang/String;)Lorg/apache/hadoop/metrics2/MetricsInfo;
     165: aload_3
     166: invokeinterface #38,  1           // InterfaceMethod org/apache/hadoop/hbase/metrics/Snapshot.get25thPercentile:()J
     171: invokevirtual #32                 // Method org/apache/hadoop/metrics2/MetricsRecordBuilder.addGauge:(Lorg/apache/hadoop/metrics2/MetricsInfo;J)Lorg/apache/hadoop/metrics2/MetricsRecordBuilder;
     174: pop
     175: aload         4
     177: new           #21                 // class java/lang/StringBuilder
     180: dup
     181: invokespecial #22                 // Method java/lang/StringBuilder."<init>":()V
     184: aload_0
     185: invokevirtual #23                 // Method java/lang/StringBuilder.append:(Ljava/lang/String;)Ljava/lang/StringBuilder;
     188: ldc           #39                 // String _median
     190: invokevirtual #23                 // Method java/lang/StringBuilder.append:(Ljava/lang/String;)Ljava/lang/StringBuilder;
     193: invokevirtual #26                 // Method java/lang/StringBuilder.toString:()Ljava/lang/String;
     196: aload_1
     197: invokestatic  #27                 // Method org/apache/hadoop/hbase/metrics/Interns.info:(Ljava/lang/String;Ljava/lang/String;)Lorg/apache/hadoop/metrics2/MetricsInfo;
     200: aload_3
     201: invokeinterface #40,  1           // InterfaceMethod org/apache/hadoop/hbase/metrics/Snapshot.getMedian:()J
     206: invokevirtual #32                 // Method org/apache/hadoop/metrics2/MetricsRecordBuilder.addGauge:(Lorg/apache/hadoop/metrics2/MetricsInfo;J)Lorg/apache/hadoop/metrics2/MetricsRecordBuilder;
     209: pop
     210: aload         4
     212: new           #21                 // class java/lang/StringBuilder
     215: dup
     216: invokespecial #22                 // Method java/lang/StringBuilder."<init>":()V
     219: aload_0
     220: invokevirtual #23                 // Method java/lang/StringBuilder.append:(Ljava/lang/String;)Ljava/lang/StringBuilder;
     223: ldc           #41                 // String _75th_percentile
     225: invokevirtual #23                 // Method java/lang/StringBuilder.append:(Ljava/lang/String;)Ljava/lang/StringBuilder;
     228: invokevirtual #26                 // Method java/lang/StringBuilder.toString:()Ljava/lang/String;
     231: aload_1
     232: invokestatic  #27                 // Method org/apache/hadoop/hbase/metrics/Interns.info:(Ljava/lang/String;Ljava/lang/String;)Lorg/apache/hadoop/metrics2/MetricsInfo;
     235: aload_3
     236: invokeinterface #42,  1           // InterfaceMethod org/apache/hadoop/hbase/metrics/Snapshot.get75thPercentile:()J
     241: invokevirtual #32                 // Method org/apache/hadoop/metrics2/MetricsRecordBuilder.addGauge:(Lorg/apache/hadoop/metrics2/MetricsInfo;J)Lorg/apache/hadoop/metrics2/MetricsRecordBuilder;
     244: pop
     245: aload         4
     247: new           #21                 // class java/lang/StringBuilder
     250: dup
     251: invokespecial #22                 // Method java/lang/StringBuilder."<init>":()V
     254: aload_0
     255: invokevirtual #23                 // Method java/lang/StringBuilder.append:(Ljava/lang/String;)Ljava/lang/StringBuilder;
     258: ldc           #43                 // String _90th_percentile
     260: invokevirtual #23                 // Method java/lang/StringBuilder.append:(Ljava/lang/String;)Ljava/lang/StringBuilder;
     263: invokevirtual #26                 // Method java/lang/StringBuilder.toString:()Ljava/lang/String;
     266: aload_1
     267: invokestatic  #27                 // Method org/apache/hadoop/hbase/metrics/Interns.info:(Ljava/lang/String;Ljava/lang/String;)Lorg/apache/hadoop/metrics2/MetricsInfo;
     270: aload_3
     271: invokeinterface #44,  1           // InterfaceMethod org/apache/hadoop/hbase/metrics/Snapshot.get90thPercentile:()J
     276: invokevirtual #32                 // Method org/apache/hadoop/metrics2/MetricsRecordBuilder.addGauge:(Lorg/apache/hadoop/metrics2/MetricsInfo;J)Lorg/apache/hadoop/metrics2/MetricsRecordBuilder;
     279: pop
     280: aload         4
     282: new           #21                 // class java/lang/StringBuilder
     285: dup
     286: invokespecial #22                 // Method java/lang/StringBuilder."<init>":()V
     289: aload_0
     290: invokevirtual #23                 // Method java/lang/StringBuilder.append:(Ljava/lang/String;)Ljava/lang/StringBuilder;
     293: ldc           #45                 // String _95th_percentile
     295: invokevirtual #23                 // Method java/lang/StringBuilder.append:(Ljava/lang/String;)Ljava/lang/StringBuilder;
     298: invokevirtual #26                 // Method java/lang/StringBuilder.toString:()Ljava/lang/String;
     301: aload_1
     302: invokestatic  #27                 // Method org/apache/hadoop/hbase/metrics/Interns.info:(Ljava/lang/String;Ljava/lang/String;)Lorg/apache/hadoop/metrics2/MetricsInfo;
     305: aload_3
     306: invokeinterface #46,  1           // InterfaceMethod org/apache/hadoop/hbase/metrics/Snapshot.get95thPercentile:()J
     311: invokevirtual #32                 // Method org/apache/hadoop/metrics2/MetricsRecordBuilder.addGauge:(Lorg/apache/hadoop/metrics2/MetricsInfo;J)Lorg/apache/hadoop/metrics2/MetricsRecordBuilder;
     314: pop
     315: aload         4
     317: new           #21                 // class java/lang/StringBuilder
     320: dup
     321: invokespecial #22                 // Method java/lang/StringBuilder."<init>":()V
     324: aload_0
     325: invokevirtual #23                 // Method java/lang/StringBuilder.append:(Ljava/lang/String;)Ljava/lang/StringBuilder;
     328: ldc           #47                 // String _98th_percentile
     330: invokevirtual #23                 // Method java/lang/StringBuilder.append:(Ljava/lang/String;)Ljava/lang/StringBuilder;
     333: invokevirtual #26                 // Method java/lang/StringBuilder.toString:()Ljava/lang/String;
     336: aload_1
     337: invokestatic  #27                 // Method org/apache/hadoop/hbase/metrics/Interns.info:(Ljava/lang/String;Ljava/lang/String;)Lorg/apache/hadoop/metrics2/MetricsInfo;
     340: aload_3
     341: invokeinterface #48,  1           // InterfaceMethod org/apache/hadoop/hbase/metrics/Snapshot.get98thPercentile:()J
     346: invokevirtual #32                 // Method org/apache/hadoop/metrics2/MetricsRecordBuilder.addGauge:(Lorg/apache/hadoop/metrics2/MetricsInfo;J)Lorg/apache/hadoop/metrics2/MetricsRecordBuilder;
     349: pop
     350: aload         4
     352: new           #21                 // class java/lang/StringBuilder
     355: dup
     356: invokespecial #22                 // Method java/lang/StringBuilder."<init>":()V
     359: aload_0
     360: invokevirtual #23                 // Method java/lang/StringBuilder.append:(Ljava/lang/String;)Ljava/lang/StringBuilder;
     363: ldc           #49                 // String _99th_percentile
     365: invokevirtual #23                 // Method java/lang/StringBuilder.append:(Ljava/lang/String;)Ljava/lang/StringBuilder;
     368: invokevirtual #26                 // Method java/lang/StringBuilder.toString:()Ljava/lang/String;
     371: aload_1
     372: invokestatic  #27                 // Method org/apache/hadoop/hbase/metrics/Interns.info:(Ljava/lang/String;Ljava/lang/String;)Lorg/apache/hadoop/metrics2/MetricsInfo;
     375: aload_3
     376: invokeinterface #50,  1           // InterfaceMethod org/apache/hadoop/hbase/metrics/Snapshot.get99thPercentile:()J
     381: invokevirtual #32                 // Method org/apache/hadoop/metrics2/MetricsRecordBuilder.addGauge:(Lorg/apache/hadoop/metrics2/MetricsInfo;J)Lorg/apache/hadoop/metrics2/MetricsRecordBuilder;
     384: pop
     385: aload         4
     387: new           #21                 // class java/lang/StringBuilder
     390: dup
     391: invokespecial #22                 // Method java/lang/StringBuilder."<init>":()V
     394: aload_0
     395: invokevirtual #23                 // Method java/lang/StringBuilder.append:(Ljava/lang/String;)Ljava/lang/StringBuilder;
     398: ldc           #51                 // String _99.9th_percentile
     400: invokevirtual #23                 // Method java/lang/StringBuilder.append:(Ljava/lang/String;)Ljava/lang/StringBuilder;
     403: invokevirtual #26                 // Method java/lang/StringBuilder.toString:()Ljava/lang/String;
     406: aload_1
     407: invokestatic  #27                 // Method org/apache/hadoop/hbase/metrics/Interns.info:(Ljava/lang/String;Ljava/lang/String;)Lorg/apache/hadoop/metrics2/MetricsInfo;
     410: aload_3
     411: invokeinterface #52,  1           // InterfaceMethod org/apache/hadoop/hbase/metrics/Snapshot.get999thPercentile:()J
     416: invokevirtual #32                 // Method org/apache/hadoop/metrics2/MetricsRecordBuilder.addGauge:(Lorg/apache/hadoop/metrics2/MetricsInfo;J)Lorg/apache/hadoop/metrics2/MetricsRecordBuilder;
     419: pop
     420: return
}
