Compiled from "NamespaceTableCfWALEntryFilter.java"
public class org.apache.hadoop.hbase.replication.NamespaceTableCfWALEntryFilter implements org.apache.hadoop.hbase.replication.WALEntryFilter,org.apache.hadoop.hbase.replication.WALCellFilter {
  public org.apache.hadoop.hbase.replication.NamespaceTableCfWALEntryFilter(org.apache.hadoop.hbase.replication.ReplicationPeer);
    Code:
       0: aload_0
       1: invokespecial #1                  // Method java/lang/Object."<init>":()V
       4: aload_0
       5: new           #2                  // class org/apache/hadoop/hbase/replication/BulkLoadCellFilter
       8: dup
       9: invokespecial #3                  // Method org/apache/hadoop/hbase/replication/BulkLoadCellFilter."<init>":()V
      12: putfield      #4                  // Field bulkLoadFilter:Lorg/apache/hadoop/hbase/replication/BulkLoadCellFilter;
      15: aload_0
      16: aload_1
      17: putfield      #5                  // Field peer:Lorg/apache/hadoop/hbase/replication/ReplicationPeer;
      20: return

  public org.apache.hadoop.hbase.wal.WAL$Entry filter(org.apache.hadoop.hbase.wal.WAL$Entry);
    Code:
       0: aload_0
       1: getfield      #5                  // Field peer:Lorg/apache/hadoop/hbase/replication/ReplicationPeer;
       4: invokeinterface #6,  1            // InterfaceMethod org/apache/hadoop/hbase/replication/ReplicationPeer.getPeerConfig:()Lorg/apache/hadoop/hbase/replication/ReplicationPeerConfig;
       9: aload_1
      10: invokevirtual #7                  // Method org/apache/hadoop/hbase/wal/WAL$Entry.getKey:()Lorg/apache/hadoop/hbase/wal/WALKeyImpl;
      13: invokevirtual #8                  // Method org/apache/hadoop/hbase/wal/WALKeyImpl.getTableName:()Lorg/apache/hadoop/hbase/TableName;
      16: invokestatic  #9                  // Method org/apache/hadoop/hbase/replication/ReplicationUtils.contains:(Lorg/apache/hadoop/hbase/replication/ReplicationPeerConfig;Lorg/apache/hadoop/hbase/TableName;)Z
      19: ifeq          24
      22: aload_1
      23: areturn
      24: aconst_null
      25: areturn

  public org.apache.hadoop.hbase.Cell filterCell(org.apache.hadoop.hbase.wal.WAL$Entry, org.apache.hadoop.hbase.Cell);
    Code:
       0: aload_0
       1: getfield      #5                  // Field peer:Lorg/apache/hadoop/hbase/replication/ReplicationPeer;
       4: invokeinterface #6,  1            // InterfaceMethod org/apache/hadoop/hbase/replication/ReplicationPeer.getPeerConfig:()Lorg/apache/hadoop/hbase/replication/ReplicationPeerConfig;
       9: astore_3
      10: aload_3
      11: invokevirtual #10                 // Method org/apache/hadoop/hbase/replication/ReplicationPeerConfig.replicateAllUserTables:()Z
      14: ifeq          105
      17: aload_3
      18: invokevirtual #11                 // Method org/apache/hadoop/hbase/replication/ReplicationPeerConfig.getExcludeTableCFsMap:()Ljava/util/Map;
      21: astore        4
      23: aload         4
      25: ifnonnull     30
      28: aload_2
      29: areturn
      30: aload_2
      31: getstatic     #12                 // Field org/apache/hadoop/hbase/wal/WALEdit.METAFAMILY:[B
      34: getstatic     #13                 // Field org/apache/hadoop/hbase/wal/WALEdit.BULK_LOAD:[B
      37: invokestatic  #14                 // Method org/apache/hadoop/hbase/CellUtil.matchingColumn:(Lorg/apache/hadoop/hbase/Cell;[B[B)Z
      40: ifeq          64
      43: aload_0
      44: getfield      #4                  // Field bulkLoadFilter:Lorg/apache/hadoop/hbase/replication/BulkLoadCellFilter;
      47: aload_2
      48: aload_0
      49: aload_1
      50: aload         4
      52: invokedynamic #15,  0             // InvokeDynamic #0:apply:(Lorg/apache/hadoop/hbase/replication/NamespaceTableCfWALEntryFilter;Lorg/apache/hadoop/hbase/wal/WAL$Entry;Ljava/util/Map;)Lorg/apache/hbase/thirdparty/com/google/common/base/Predicate;
      57: invokevirtual #16                 // Method org/apache/hadoop/hbase/replication/BulkLoadCellFilter.filterCell:(Lorg/apache/hadoop/hbase/Cell;Lorg/apache/hbase/thirdparty/com/google/common/base/Predicate;)Lorg/apache/hadoop/hbase/Cell;
      60: astore_2
      61: goto          103
      64: aload_0
      65: aload_1
      66: invokevirtual #7                  // Method org/apache/hadoop/hbase/wal/WAL$Entry.getKey:()Lorg/apache/hadoop/hbase/wal/WALKeyImpl;
      69: invokevirtual #8                  // Method org/apache/hadoop/hbase/wal/WALKeyImpl.getTableName:()Lorg/apache/hadoop/hbase/TableName;
      72: aload_2
      73: invokeinterface #17,  1           // InterfaceMethod org/apache/hadoop/hbase/Cell.getFamilyArray:()[B
      78: aload_2
      79: invokeinterface #18,  1           // InterfaceMethod org/apache/hadoop/hbase/Cell.getFamilyOffset:()I
      84: aload_2
      85: invokeinterface #19,  1           // InterfaceMethod org/apache/hadoop/hbase/Cell.getFamilyLength:()B
      90: invokestatic  #20                 // Method org/apache/hadoop/hbase/util/Bytes.toString:([BII)Ljava/lang/String;
      93: aload         4
      95: invokespecial #21                 // Method filterByExcludeTableCfs:(Lorg/apache/hadoop/hbase/TableName;Ljava/lang/String;Ljava/util/Map;)Z
      98: ifeq          103
     101: aconst_null
     102: areturn
     103: aload_2
     104: areturn
     105: aload_3
     106: invokevirtual #22                 // Method org/apache/hadoop/hbase/replication/ReplicationPeerConfig.getTableCFsMap:()Ljava/util/Map;
     109: astore        4
     111: aload         4
     113: ifnonnull     118
     116: aload_2
     117: areturn
     118: aload_2
     119: getstatic     #12                 // Field org/apache/hadoop/hbase/wal/WALEdit.METAFAMILY:[B
     122: getstatic     #13                 // Field org/apache/hadoop/hbase/wal/WALEdit.BULK_LOAD:[B
     125: invokestatic  #14                 // Method org/apache/hadoop/hbase/CellUtil.matchingColumn:(Lorg/apache/hadoop/hbase/Cell;[B[B)Z
     128: ifeq          152
     131: aload_0
     132: getfield      #4                  // Field bulkLoadFilter:Lorg/apache/hadoop/hbase/replication/BulkLoadCellFilter;
     135: aload_2
     136: aload_0
     137: aload_1
     138: aload         4
     140: invokedynamic #23,  0             // InvokeDynamic #1:apply:(Lorg/apache/hadoop/hbase/replication/NamespaceTableCfWALEntryFilter;Lorg/apache/hadoop/hbase/wal/WAL$Entry;Ljava/util/Map;)Lorg/apache/hbase/thirdparty/com/google/common/base/Predicate;
     145: invokevirtual #16                 // Method org/apache/hadoop/hbase/replication/BulkLoadCellFilter.filterCell:(Lorg/apache/hadoop/hbase/Cell;Lorg/apache/hbase/thirdparty/com/google/common/base/Predicate;)Lorg/apache/hadoop/hbase/Cell;
     148: astore_2
     149: goto          191
     152: aload_0
     153: aload_1
     154: invokevirtual #7                  // Method org/apache/hadoop/hbase/wal/WAL$Entry.getKey:()Lorg/apache/hadoop/hbase/wal/WALKeyImpl;
     157: invokevirtual #8                  // Method org/apache/hadoop/hbase/wal/WALKeyImpl.getTableName:()Lorg/apache/hadoop/hbase/TableName;
     160: aload_2
     161: invokeinterface #17,  1           // InterfaceMethod org/apache/hadoop/hbase/Cell.getFamilyArray:()[B
     166: aload_2
     167: invokeinterface #18,  1           // InterfaceMethod org/apache/hadoop/hbase/Cell.getFamilyOffset:()I
     172: aload_2
     173: invokeinterface #19,  1           // InterfaceMethod org/apache/hadoop/hbase/Cell.getFamilyLength:()B
     178: invokestatic  #20                 // Method org/apache/hadoop/hbase/util/Bytes.toString:([BII)Ljava/lang/String;
     181: aload         4
     183: invokespecial #24                 // Method filterByTableCfs:(Lorg/apache/hadoop/hbase/TableName;Ljava/lang/String;Ljava/util/Map;)Z
     186: ifeq          191
     189: aconst_null
     190: areturn
     191: aload_2
     192: areturn
}
