Compiled from "NamespaceDescriptor.java"
public class org.apache.hadoop.hbase.NamespaceDescriptor$Builder {
  public org.apache.hadoop.hbase.NamespaceDescriptor$Builder addConfiguration(java.util.Map<java.lang.String, java.lang.String>);
    Code:
       0: aload_0
       1: getfield      #6                  // Field bConfiguration:Ljava/util/Map;
       4: aload_1
       5: invokeinterface #10,  2           // InterfaceMethod java/util/Map.putAll:(Ljava/util/Map;)V
      10: aload_0
      11: areturn

  public org.apache.hadoop.hbase.NamespaceDescriptor$Builder addConfiguration(java.lang.String, java.lang.String);
    Code:
       0: aload_0
       1: getfield      #6                  // Field bConfiguration:Ljava/util/Map;
       4: aload_1
       5: aload_2
       6: invokeinterface #11,  3           // InterfaceMethod java/util/Map.put:(Ljava/lang/Object;Ljava/lang/Object;)Ljava/lang/Object;
      11: pop
      12: aload_0
      13: areturn

  public org.apache.hadoop.hbase.NamespaceDescriptor$Builder removeConfiguration(java.lang.String);
    Code:
       0: aload_0
       1: getfield      #6                  // Field bConfiguration:Ljava/util/Map;
       4: aload_1
       5: invokeinterface #12,  2           // InterfaceMethod java/util/Map.remove:(Ljava/lang/Object;)Ljava/lang/Object;
      10: pop
      11: aload_0
      12: areturn

  public org.apache.hadoop.hbase.NamespaceDescriptor build();
    Code:
       0: aload_0
       1: getfield      #8                  // Field bName:Ljava/lang/String;
       4: ifnonnull     17
       7: new           #13                 // class java/lang/IllegalArgumentException
      10: dup
      11: ldc           #14                 // String A name has to be specified in a namespace.
      13: invokespecial #15                 // Method java/lang/IllegalArgumentException."<init>":(Ljava/lang/String;)V
      16: athrow
      17: new           #16                 // class org/apache/hadoop/hbase/NamespaceDescriptor
      20: dup
      21: aload_0
      22: getfield      #8                  // Field bName:Ljava/lang/String;
      25: aconst_null
      26: invokespecial #17                 // Method org/apache/hadoop/hbase/NamespaceDescriptor."<init>":(Ljava/lang/String;Lorg/apache/hadoop/hbase/NamespaceDescriptor$1;)V
      29: astore_1
      30: aload_1
      31: aload_0
      32: getfield      #6                  // Field bConfiguration:Ljava/util/Map;
      35: invokestatic  #18                 // Method org/apache/hadoop/hbase/NamespaceDescriptor.access$302:(Lorg/apache/hadoop/hbase/NamespaceDescriptor;Ljava/util/Map;)Ljava/util/Map;
      38: pop
      39: aload_1
      40: areturn

  org.apache.hadoop.hbase.NamespaceDescriptor$Builder(java.lang.String, org.apache.hadoop.hbase.NamespaceDescriptor$1);
    Code:
       0: aload_0
       1: aload_1
       2: invokespecial #2                  // Method "<init>":(Ljava/lang/String;)V
       5: return

  org.apache.hadoop.hbase.NamespaceDescriptor$Builder(org.apache.hadoop.hbase.NamespaceDescriptor, org.apache.hadoop.hbase.NamespaceDescriptor$1);
    Code:
       0: aload_0
       1: aload_1
       2: invokespecial #1                  // Method "<init>":(Lorg/apache/hadoop/hbase/NamespaceDescriptor;)V
       5: return
}
