Compiled from "NettyServerRpcConnection.java"
class org.apache.hadoop.hbase.ipc.NettyServerRpcConnection$1 implements org.apache.hadoop.hbase.ipc.RpcServer$CallCleanup {
  final org.apache.hbase.thirdparty.io.netty.buffer.ByteBuf val$buf;

  final org.apache.hadoop.hbase.ipc.NettyServerRpcConnection this$0;

  org.apache.hadoop.hbase.ipc.NettyServerRpcConnection$1(org.apache.hadoop.hbase.ipc.NettyServerRpcConnection, org.apache.hbase.thirdparty.io.netty.buffer.ByteBuf);
    Code:
       0: aload_0
       1: aload_1
       2: putfield      #1                  // Field this$0:Lorg/apache/hadoop/hbase/ipc/NettyServerRpcConnection;
       5: aload_0
       6: aload_2
       7: putfield      #2                  // Field val$buf:Lorg/apache/hbase/thirdparty/io/netty/buffer/ByteBuf;
      10: aload_0
      11: invokespecial #3                  // Method java/lang/Object."<init>":()V
      14: return

  public void run();
    Code:
       0: aload_0
       1: getfield      #2                  // Field val$buf:Lorg/apache/hbase/thirdparty/io/netty/buffer/ByteBuf;
       4: invokevirtual #4                  // Method org/apache/hbase/thirdparty/io/netty/buffer/ByteBuf.release:()Z
       7: pop
       8: return
}
