Compiled from "NettyRpcConnection.java"
class org.apache.hadoop.hbase.ipc.NettyRpcConnection$6 implements org.apache.hadoop.hbase.ipc.HBaseRpcController$CancellationCallback {
  final org.apache.hadoop.hbase.ipc.Call val$call;

  final org.apache.hadoop.hbase.ipc.NettyRpcConnection this$0;

  org.apache.hadoop.hbase.ipc.NettyRpcConnection$6(org.apache.hadoop.hbase.ipc.NettyRpcConnection, org.apache.hadoop.hbase.ipc.Call);
    Code:
       0: aload_0
       1: aload_1
       2: putfield      #1                  // Field this$0:Lorg/apache/hadoop/hbase/ipc/NettyRpcConnection;
       5: aload_0
       6: aload_2
       7: putfield      #2                  // Field val$call:Lorg/apache/hadoop/hbase/ipc/Call;
      10: aload_0
      11: invokespecial #3                  // Method java/lang/Object."<init>":()V
      14: return

  public void run(boolean) throws java.io.IOException;
    Code:
       0: iload_1
       1: ifeq          14
       4: aload_0
       5: getfield      #2                  // Field val$call:Lorg/apache/hadoop/hbase/ipc/Call;
       8: invokestatic  #4                  // Method org/apache/hadoop/hbase/ipc/IPCUtil.setCancelled:(Lorg/apache/hadoop/hbase/ipc/Call;)V
      11: goto          99
      14: aload_0
      15: getfield      #1                  // Field this$0:Lorg/apache/hadoop/hbase/ipc/NettyRpcConnection;
      18: invokestatic  #5                  // Method org/apache/hadoop/hbase/ipc/NettyRpcConnection.access$900:(Lorg/apache/hadoop/hbase/ipc/NettyRpcConnection;)Lorg/apache/hbase/thirdparty/io/netty/channel/Channel;
      21: ifnonnull     31
      24: aload_0
      25: getfield      #1                  // Field this$0:Lorg/apache/hadoop/hbase/ipc/NettyRpcConnection;
      28: invokestatic  #6                  // Method org/apache/hadoop/hbase/ipc/NettyRpcConnection.access$1000:(Lorg/apache/hadoop/hbase/ipc/NettyRpcConnection;)V
      31: aload_0
      32: getfield      #1                  // Field this$0:Lorg/apache/hadoop/hbase/ipc/NettyRpcConnection;
      35: aload_0
      36: getfield      #2                  // Field val$call:Lorg/apache/hadoop/hbase/ipc/Call;
      39: invokevirtual #7                  // Method org/apache/hadoop/hbase/ipc/NettyRpcConnection.scheduleTimeoutTask:(Lorg/apache/hadoop/hbase/ipc/Call;)V
      42: aload_0
      43: getfield      #1                  // Field this$0:Lorg/apache/hadoop/hbase/ipc/NettyRpcConnection;
      46: invokestatic  #5                  // Method org/apache/hadoop/hbase/ipc/NettyRpcConnection.access$900:(Lorg/apache/hadoop/hbase/ipc/NettyRpcConnection;)Lorg/apache/hbase/thirdparty/io/netty/channel/Channel;
      49: astore_2
      50: aload_2
      51: invokeinterface #8,  1            // InterfaceMethod org/apache/hbase/thirdparty/io/netty/channel/Channel.eventLoop:()Lorg/apache/hbase/thirdparty/io/netty/channel/EventLoop;
      56: invokeinterface #9,  1            // InterfaceMethod org/apache/hbase/thirdparty/io/netty/channel/EventLoop.inEventLoop:()Z
      61: ifeq          79
      64: aload_0
      65: getfield      #1                  // Field this$0:Lorg/apache/hadoop/hbase/ipc/NettyRpcConnection;
      68: aload_2
      69: aload_0
      70: getfield      #2                  // Field val$call:Lorg/apache/hadoop/hbase/ipc/Call;
      73: invokestatic  #10                 // Method org/apache/hadoop/hbase/ipc/NettyRpcConnection.access$1100:(Lorg/apache/hadoop/hbase/ipc/NettyRpcConnection;Lorg/apache/hbase/thirdparty/io/netty/channel/Channel;Lorg/apache/hadoop/hbase/ipc/Call;)V
      76: goto          99
      79: aload_2
      80: invokeinterface #8,  1            // InterfaceMethod org/apache/hbase/thirdparty/io/netty/channel/Channel.eventLoop:()Lorg/apache/hbase/thirdparty/io/netty/channel/EventLoop;
      85: new           #11                 // class org/apache/hadoop/hbase/ipc/NettyRpcConnection$6$1
      88: dup
      89: aload_0
      90: aload_2
      91: invokespecial #12                 // Method org/apache/hadoop/hbase/ipc/NettyRpcConnection$6$1."<init>":(Lorg/apache/hadoop/hbase/ipc/NettyRpcConnection$6;Lorg/apache/hbase/thirdparty/io/netty/channel/Channel;)V
      94: invokeinterface #13,  2           // InterfaceMethod org/apache/hbase/thirdparty/io/netty/channel/EventLoop.execute:(Ljava/lang/Runnable;)V
      99: return
}
