Compiled from "NettyRpcDuplexHandler.java"
class org.apache.hadoop.hbase.ipc.NettyRpcDuplexHandler extends org.apache.hbase.thirdparty.io.netty.channel.ChannelDuplexHandler {
  public org.apache.hadoop.hbase.ipc.NettyRpcDuplexHandler(org.apache.hadoop.hbase.ipc.NettyRpcConnection, org.apache.hadoop.hbase.ipc.CellBlockBuilder, org.apache.hadoop.hbase.codec.Codec, org.apache.hadoop.io.compress.CompressionCodec);
    Code:
       0: aload_0
       1: invokespecial #1                  // Method org/apache/hbase/thirdparty/io/netty/channel/ChannelDuplexHandler."<init>":()V
       4: aload_0
       5: new           #2                  // class java/util/HashMap
       8: dup
       9: invokespecial #3                  // Method java/util/HashMap."<init>":()V
      12: putfield      #4                  // Field id2Call:Ljava/util/Map;
      15: aload_0
      16: aload_1
      17: putfield      #5                  // Field conn:Lorg/apache/hadoop/hbase/ipc/NettyRpcConnection;
      20: aload_0
      21: aload_2
      22: putfield      #6                  // Field cellBlockBuilder:Lorg/apache/hadoop/hbase/ipc/CellBlockBuilder;
      25: aload_0
      26: aload_3
      27: putfield      #7                  // Field codec:Lorg/apache/hadoop/hbase/codec/Codec;
      30: aload_0
      31: aload         4
      33: putfield      #8                  // Field compressor:Lorg/apache/hadoop/io/compress/CompressionCodec;
      36: return

  public void write(org.apache.hbase.thirdparty.io.netty.channel.ChannelHandlerContext, java.lang.Object, org.apache.hbase.thirdparty.io.netty.channel.ChannelPromise) throws java.lang.Exception;
    Code:
       0: aload_2
       1: instanceof    #39                 // class org/apache/hadoop/hbase/ipc/Call
       4: ifeq          20
       7: aload_0
       8: aload_1
       9: aload_2
      10: checkcast     #39                 // class org/apache/hadoop/hbase/ipc/Call
      13: aload_3
      14: invokespecial #40                 // Method writeRequest:(Lorg/apache/hbase/thirdparty/io/netty/channel/ChannelHandlerContext;Lorg/apache/hadoop/hbase/ipc/Call;Lorg/apache/hbase/thirdparty/io/netty/channel/ChannelPromise;)V
      17: goto          29
      20: aload_1
      21: aload_2
      22: aload_3
      23: invokeinterface #30,  3           // InterfaceMethod org/apache/hbase/thirdparty/io/netty/channel/ChannelHandlerContext.write:(Ljava/lang/Object;Lorg/apache/hbase/thirdparty/io/netty/channel/ChannelPromise;)Lorg/apache/hbase/thirdparty/io/netty/channel/ChannelFuture;
      28: pop
      29: return

  public void channelRead(org.apache.hbase.thirdparty.io.netty.channel.ChannelHandlerContext, java.lang.Object) throws java.lang.Exception;
    Code:
       0: aload_2
       1: instanceof    #79                 // class org/apache/hbase/thirdparty/io/netty/buffer/ByteBuf
       4: ifeq          39
       7: aload_2
       8: checkcast     #79                 // class org/apache/hbase/thirdparty/io/netty/buffer/ByteBuf
      11: astore_3
      12: aload_0
      13: aload_1
      14: aload_3
      15: invokespecial #80                 // Method readResponse:(Lorg/apache/hbase/thirdparty/io/netty/channel/ChannelHandlerContext;Lorg/apache/hbase/thirdparty/io/netty/buffer/ByteBuf;)V
      18: aload_3
      19: invokevirtual #81                 // Method org/apache/hbase/thirdparty/io/netty/buffer/ByteBuf.release:()Z
      22: pop
      23: goto          36
      26: astore        4
      28: aload_3
      29: invokevirtual #81                 // Method org/apache/hbase/thirdparty/io/netty/buffer/ByteBuf.release:()Z
      32: pop
      33: aload         4
      35: athrow
      36: goto          45
      39: aload_0
      40: aload_1
      41: aload_2
      42: invokespecial #82                 // Method org/apache/hbase/thirdparty/io/netty/channel/ChannelDuplexHandler.channelRead:(Lorg/apache/hbase/thirdparty/io/netty/channel/ChannelHandlerContext;Ljava/lang/Object;)V
      45: return
    Exception table:
       from    to  target type
          12    18    26   any
          26    28    26   any

  public void channelInactive(org.apache.hbase.thirdparty.io.netty.channel.ChannelHandlerContext) throws java.lang.Exception;
    Code:
       0: aload_0
       1: getfield      #4                  // Field id2Call:Ljava/util/Map;
       4: invokeinterface #88,  1           // InterfaceMethod java/util/Map.isEmpty:()Z
       9: ifne          26
      12: aload_0
      13: aload_1
      14: new           #89                 // class org/apache/hadoop/hbase/exceptions/ConnectionClosedException
      17: dup
      18: ldc           #90                 // String Connection closed
      20: invokespecial #91                 // Method org/apache/hadoop/hbase/exceptions/ConnectionClosedException."<init>":(Ljava/lang/String;)V
      23: invokespecial #92                 // Method cleanupCalls:(Lorg/apache/hbase/thirdparty/io/netty/channel/ChannelHandlerContext;Ljava/io/IOException;)V
      26: aload_0
      27: getfield      #5                  // Field conn:Lorg/apache/hadoop/hbase/ipc/NettyRpcConnection;
      30: invokevirtual #93                 // Method org/apache/hadoop/hbase/ipc/NettyRpcConnection.shutdown:()V
      33: aload_1
      34: invokeinterface #94,  1           // InterfaceMethod org/apache/hbase/thirdparty/io/netty/channel/ChannelHandlerContext.fireChannelInactive:()Lorg/apache/hbase/thirdparty/io/netty/channel/ChannelHandlerContext;
      39: pop
      40: return

  public void exceptionCaught(org.apache.hbase.thirdparty.io.netty.channel.ChannelHandlerContext, java.lang.Throwable);
    Code:
       0: aload_0
       1: getfield      #4                  // Field id2Call:Ljava/util/Map;
       4: invokeinterface #88,  1           // InterfaceMethod java/util/Map.isEmpty:()Z
       9: ifne          21
      12: aload_0
      13: aload_1
      14: aload_2
      15: invokestatic  #95                 // Method org/apache/hadoop/hbase/ipc/IPCUtil.toIOE:(Ljava/lang/Throwable;)Ljava/io/IOException;
      18: invokespecial #92                 // Method cleanupCalls:(Lorg/apache/hbase/thirdparty/io/netty/channel/ChannelHandlerContext;Ljava/io/IOException;)V
      21: aload_0
      22: getfield      #5                  // Field conn:Lorg/apache/hadoop/hbase/ipc/NettyRpcConnection;
      25: invokevirtual #93                 // Method org/apache/hadoop/hbase/ipc/NettyRpcConnection.shutdown:()V
      28: return

  public void userEventTriggered(org.apache.hbase.thirdparty.io.netty.channel.ChannelHandlerContext, java.lang.Object) throws java.lang.Exception;
    Code:
       0: aload_2
       1: instanceof    #96                 // class org/apache/hbase/thirdparty/io/netty/handler/timeout/IdleStateEvent
       4: ifeq          147
       7: aload_2
       8: checkcast     #96                 // class org/apache/hbase/thirdparty/io/netty/handler/timeout/IdleStateEvent
      11: astore_3
      12: getstatic     #97                 // Field org/apache/hadoop/hbase/ipc/NettyRpcDuplexHandler$1.$SwitchMap$org$apache$hbase$thirdparty$io$netty$handler$timeout$IdleState:[I
      15: aload_3
      16: invokevirtual #98                 // Method org/apache/hbase/thirdparty/io/netty/handler/timeout/IdleStateEvent.state:()Lorg/apache/hbase/thirdparty/io/netty/handler/timeout/IdleState;
      19: invokevirtual #99                 // Method org/apache/hbase/thirdparty/io/netty/handler/timeout/IdleState.ordinal:()I
      22: iaload
      23: lookupswitch  { // 1
                     1: 40
               default: 114
          }
      40: aload_0
      41: getfield      #4                  // Field id2Call:Ljava/util/Map;
      44: invokeinterface #88,  1           // InterfaceMethod java/util/Map.isEmpty:()Z
      49: ifeq          144
      52: getstatic     #46                 // Field LOG:Lorg/slf4j/Logger;
      55: invokeinterface #47,  1           // InterfaceMethod org/slf4j/Logger.isTraceEnabled:()Z
      60: ifeq          104
      63: getstatic     #46                 // Field LOG:Lorg/slf4j/Logger;
      66: new           #48                 // class java/lang/StringBuilder
      69: dup
      70: invokespecial #49                 // Method java/lang/StringBuilder."<init>":()V
      73: ldc           #100                // String shutdown connection to
      75: invokevirtual #51                 // Method java/lang/StringBuilder.append:(Ljava/lang/String;)Ljava/lang/StringBuilder;
      78: aload_0
      79: getfield      #5                  // Field conn:Lorg/apache/hadoop/hbase/ipc/NettyRpcConnection;
      82: invokevirtual #101                // Method org/apache/hadoop/hbase/ipc/NettyRpcConnection.remoteId:()Lorg/apache/hadoop/hbase/ipc/ConnectionId;
      85: getfield      #102                // Field org/apache/hadoop/hbase/ipc/ConnectionId.address:Ljava/net/InetSocketAddress;
      88: invokevirtual #103                // Method java/lang/StringBuilder.append:(Ljava/lang/Object;)Ljava/lang/StringBuilder;
      91: ldc           #104                // String  because idle for a long time
      93: invokevirtual #51                 // Method java/lang/StringBuilder.append:(Ljava/lang/String;)Ljava/lang/StringBuilder;
      96: invokevirtual #56                 // Method java/lang/StringBuilder.toString:()Ljava/lang/String;
      99: invokeinterface #57,  2           // InterfaceMethod org/slf4j/Logger.trace:(Ljava/lang/String;)V
     104: aload_0
     105: getfield      #5                  // Field conn:Lorg/apache/hadoop/hbase/ipc/NettyRpcConnection;
     108: invokevirtual #93                 // Method org/apache/hadoop/hbase/ipc/NettyRpcConnection.shutdown:()V
     111: goto          144
     114: getstatic     #46                 // Field LOG:Lorg/slf4j/Logger;
     117: new           #48                 // class java/lang/StringBuilder
     120: dup
     121: invokespecial #49                 // Method java/lang/StringBuilder."<init>":()V
     124: ldc           #105                // String Unrecognized idle state
     126: invokevirtual #51                 // Method java/lang/StringBuilder.append:(Ljava/lang/String;)Ljava/lang/StringBuilder;
     129: aload_3
     130: invokevirtual #98                 // Method org/apache/hbase/thirdparty/io/netty/handler/timeout/IdleStateEvent.state:()Lorg/apache/hbase/thirdparty/io/netty/handler/timeout/IdleState;
     133: invokevirtual #103                // Method java/lang/StringBuilder.append:(Ljava/lang/Object;)Ljava/lang/StringBuilder;
     136: invokevirtual #56                 // Method java/lang/StringBuilder.toString:()Ljava/lang/String;
     139: invokeinterface #106,  2          // InterfaceMethod org/slf4j/Logger.warn:(Ljava/lang/String;)V
     144: goto          188
     147: aload_2
     148: instanceof    #107                // class org/apache/hadoop/hbase/ipc/CallEvent
     151: ifeq          180
     154: aload_0
     155: getfield      #4                  // Field id2Call:Ljava/util/Map;
     158: aload_2
     159: checkcast     #107                // class org/apache/hadoop/hbase/ipc/CallEvent
     162: getfield      #108                // Field org/apache/hadoop/hbase/ipc/CallEvent.call:Lorg/apache/hadoop/hbase/ipc/Call;
     165: getfield      #9                  // Field org/apache/hadoop/hbase/ipc/Call.id:I
     168: invokestatic  #10                 // Method java/lang/Integer.valueOf:(I)Ljava/lang/Integer;
     171: invokeinterface #63,  2           // InterfaceMethod java/util/Map.remove:(Ljava/lang/Object;)Ljava/lang/Object;
     176: pop
     177: goto          188
     180: aload_1
     181: aload_2
     182: invokeinterface #109,  2          // InterfaceMethod org/apache/hbase/thirdparty/io/netty/channel/ChannelHandlerContext.fireUserEventTriggered:(Ljava/lang/Object;)Lorg/apache/hbase/thirdparty/io/netty/channel/ChannelHandlerContext;
     187: pop
     188: return

  static {};
    Code:
       0: ldc           #110                // class org/apache/hadoop/hbase/ipc/NettyRpcDuplexHandler
       2: invokestatic  #111                // Method org/slf4j/LoggerFactory.getLogger:(Ljava/lang/Class;)Lorg/slf4j/Logger;
       5: putstatic     #46                 // Field LOG:Lorg/slf4j/Logger;
       8: return
}
