Compiled from "NettyRpcConnection.java"
class org.apache.hadoop.hbase.ipc.NettyRpcConnection$6$1 implements java.lang.Runnable {
  final org.apache.hbase.thirdparty.io.netty.channel.Channel val$ch;

  final org.apache.hadoop.hbase.ipc.NettyRpcConnection$6 this$1;

  org.apache.hadoop.hbase.ipc.NettyRpcConnection$6$1(org.apache.hadoop.hbase.ipc.NettyRpcConnection$6, org.apache.hbase.thirdparty.io.netty.channel.Channel);
    Code:
       0: aload_0
       1: aload_1
       2: putfield      #1                  // Field this$1:Lorg/apache/hadoop/hbase/ipc/NettyRpcConnection$6;
       5: aload_0
       6: aload_2
       7: putfield      #2                  // Field val$ch:Lorg/apache/hbase/thirdparty/io/netty/channel/Channel;
      10: aload_0
      11: invokespecial #3                  // Method java/lang/Object."<init>":()V
      14: return

  public void run();
    Code:
       0: aload_0
       1: getfield      #1                  // Field this$1:Lorg/apache/hadoop/hbase/ipc/NettyRpcConnection$6;
       4: getfield      #4                  // Field org/apache/hadoop/hbase/ipc/NettyRpcConnection$6.this$0:Lorg/apache/hadoop/hbase/ipc/NettyRpcConnection;
       7: aload_0
       8: getfield      #2                  // Field val$ch:Lorg/apache/hbase/thirdparty/io/netty/channel/Channel;
      11: aload_0
      12: getfield      #1                  // Field this$1:Lorg/apache/hadoop/hbase/ipc/NettyRpcConnection$6;
      15: getfield      #5                  // Field org/apache/hadoop/hbase/ipc/NettyRpcConnection$6.val$call:Lorg/apache/hadoop/hbase/ipc/Call;
      18: invokestatic  #6                  // Method org/apache/hadoop/hbase/ipc/NettyRpcConnection.access$1100:(Lorg/apache/hadoop/hbase/ipc/NettyRpcConnection;Lorg/apache/hbase/thirdparty/io/netty/channel/Channel;Lorg/apache/hadoop/hbase/ipc/Call;)V
      21: return
}
