Compiled from "NoneEncoder.java"
public class org.apache.hadoop.hbase.io.encoding.NoneEncoder {
  public org.apache.hadoop.hbase.io.encoding.NoneEncoder(java.io.DataOutputStream, org.apache.hadoop.hbase.io.encoding.HFileBlockDefaultEncodingContext);
    Code:
       0: aload_0
       1: invokespecial #1                  // Method java/lang/Object."<init>":()V
       4: aload_0
       5: aload_1
       6: putfield      #2                  // Field out:Ljava/io/DataOutputStream;
       9: aload_0
      10: aload_2
      11: putfield      #3                  // Field encodingCtx:Lorg/apache/hadoop/hbase/io/encoding/HFileBlockDefaultEncodingContext;
      14: return

  public int write(org.apache.hadoop.hbase.Cell) throws java.io.IOException;
    Code:
       0: aload_1
       1: aload_0
       2: getfield      #2                  // Field out:Ljava/io/DataOutputStream;
       5: iconst_0
       6: invokestatic  #4                  // Method org/apache/hadoop/hbase/KeyValueUtil.oswrite:(Lorg/apache/hadoop/hbase/Cell;Ljava/io/OutputStream;Z)I
       9: istore_2
      10: aload_0
      11: getfield      #3                  // Field encodingCtx:Lorg/apache/hadoop/hbase/io/encoding/HFileBlockDefaultEncodingContext;
      14: invokevirtual #5                  // Method org/apache/hadoop/hbase/io/encoding/HFileBlockDefaultEncodingContext.getHFileContext:()Lorg/apache/hadoop/hbase/io/hfile/HFileContext;
      17: invokevirtual #6                  // Method org/apache/hadoop/hbase/io/hfile/HFileContext.isIncludesTags:()Z
      20: ifeq          57
      23: aload_1
      24: invokeinterface #7,  1            // InterfaceMethod org/apache/hadoop/hbase/Cell.getTagsLength:()I
      29: istore_3
      30: aload_0
      31: getfield      #2                  // Field out:Ljava/io/DataOutputStream;
      34: iload_3
      35: invokevirtual #8                  // Method java/io/DataOutputStream.writeShort:(I)V
      38: iload_3
      39: ifle          51
      42: aload_0
      43: getfield      #2                  // Field out:Ljava/io/DataOutputStream;
      46: aload_1
      47: iload_3
      48: invokestatic  #9                  // Method org/apache/hadoop/hbase/PrivateCellUtil.writeTags:(Ljava/io/OutputStream;Lorg/apache/hadoop/hbase/Cell;I)V
      51: iload_2
      52: iload_3
      53: iconst_2
      54: iadd
      55: iadd
      56: istore_2
      57: aload_0
      58: getfield      #3                  // Field encodingCtx:Lorg/apache/hadoop/hbase/io/encoding/HFileBlockDefaultEncodingContext;
      61: invokevirtual #5                  // Method org/apache/hadoop/hbase/io/encoding/HFileBlockDefaultEncodingContext.getHFileContext:()Lorg/apache/hadoop/hbase/io/hfile/HFileContext;
      64: invokevirtual #11                 // Method org/apache/hadoop/hbase/io/hfile/HFileContext.isIncludesMvcc:()Z
      67: ifeq          95
      70: aload_0
      71: getfield      #2                  // Field out:Ljava/io/DataOutputStream;
      74: aload_1
      75: invokeinterface #12,  1           // InterfaceMethod org/apache/hadoop/hbase/Cell.getSequenceId:()J
      80: invokestatic  #13                 // Method org/apache/hadoop/io/WritableUtils.writeVLong:(Ljava/io/DataOutput;J)V
      83: iload_2
      84: aload_1
      85: invokeinterface #12,  1           // InterfaceMethod org/apache/hadoop/hbase/Cell.getSequenceId:()J
      90: invokestatic  #14                 // Method org/apache/hadoop/io/WritableUtils.getVIntSize:(J)I
      93: iadd
      94: istore_2
      95: iload_2
      96: ireturn
}
