Compiled from "NoOpRegionSizeStore.java"
public final class org.apache.hadoop.hbase.quotas.NoOpRegionSizeStore implements org.apache.hadoop.hbase.quotas.RegionSizeStore {
  public static org.apache.hadoop.hbase.quotas.NoOpRegionSizeStore getInstance();
    Code:
       0: getstatic     #2                  // Field INSTANCE:Lorg/apache/hadoop/hbase/quotas/NoOpRegionSizeStore;
       3: areturn

  public java.util.Iterator<java.util.Map$Entry<org.apache.hadoop.hbase.client.RegionInfo, org.apache.hadoop.hbase.quotas.RegionSize>> iterator();
    Code:
       0: aconst_null
       1: areturn

  public long heapSize();
    Code:
       0: lconst_0
       1: lreturn

  public org.apache.hadoop.hbase.quotas.RegionSize getRegionSize(org.apache.hadoop.hbase.client.RegionInfo);
    Code:
       0: aconst_null
       1: areturn

  public void put(org.apache.hadoop.hbase.client.RegionInfo, long);
    Code:
       0: return

  public void incrementRegionSize(org.apache.hadoop.hbase.client.RegionInfo, long);
    Code:
       0: return

  public org.apache.hadoop.hbase.quotas.RegionSize remove(org.apache.hadoop.hbase.client.RegionInfo);
    Code:
       0: aconst_null
       1: areturn

  public int size();
    Code:
       0: iconst_0
       1: ireturn

  public boolean isEmpty();
    Code:
       0: iconst_1
       1: ireturn

  public void clear();
    Code:
       0: return

  static {};
    Code:
       0: new           #3                  // class org/apache/hadoop/hbase/quotas/NoOpRegionSizeStore
       3: dup
       4: invokespecial #4                  // Method "<init>":()V
       7: putstatic     #2                  // Field INSTANCE:Lorg/apache/hadoop/hbase/quotas/NoOpRegionSizeStore;
      10: return
}
