Compiled from "NormalUserScanQueryMatcher.java"
final class org.apache.hadoop.hbase.regionserver.querymatcher.NormalUserScanQueryMatcher$2 extends org.apache.hadoop.hbase.regionserver.querymatcher.NormalUserScanQueryMatcher {
  org.apache.hadoop.hbase.regionserver.querymatcher.NormalUserScanQueryMatcher$2(org.apache.hadoop.hbase.client.Scan, org.apache.hadoop.hbase.regionserver.ScanInfo, org.apache.hadoop.hbase.regionserver.querymatcher.ColumnTracker, boolean, org.apache.hadoop.hbase.regionserver.querymatcher.DeleteTracker, long, long);
    Code:
       0: aload_0
       1: aload_1
       2: aload_2
       3: aload_3
       4: iload         4
       6: aload         5
       8: lload         6
      10: lload         8
      12: invokespecial #1                  // Method org/apache/hadoop/hbase/regionserver/querymatcher/NormalUserScanQueryMatcher."<init>":(Lorg/apache/hadoop/hbase/client/Scan;Lorg/apache/hadoop/hbase/regionserver/ScanInfo;Lorg/apache/hadoop/hbase/regionserver/querymatcher/ColumnTracker;ZLorg/apache/hadoop/hbase/regionserver/querymatcher/DeleteTracker;JJ)V
      15: return

  protected boolean moreRowsMayExistsAfter(int);
    Code:
       0: iload_1
       1: ifle          8
       4: iconst_1
       5: goto          9
       8: iconst_0
       9: ireturn
}
