Compiled from "NoTagsByteBufferKeyValue.java"
public class org.apache.hadoop.hbase.NoTagsByteBufferKeyValue extends org.apache.hadoop.hbase.ByteBufferKeyValue {
  public org.apache.hadoop.hbase.NoTagsByteBufferKeyValue(java.nio.ByteBuffer, int, int);
    Code:
       0: aload_0
       1: aload_1
       2: iload_2
       3: iload_3
       4: invokespecial #1                  // Method org/apache/hadoop/hbase/ByteBufferKeyValue."<init>":(Ljava/nio/ByteBuffer;II)V
       7: return

  public org.apache.hadoop.hbase.NoTagsByteBufferKeyValue(java.nio.ByteBuffer, int, int, long);
    Code:
       0: aload_0
       1: aload_1
       2: iload_2
       3: iload_3
       4: lload         4
       6: invokespecial #2                  // Method org/apache/hadoop/hbase/ByteBufferKeyValue."<init>":(Ljava/nio/ByteBuffer;IIJ)V
       9: return

  public byte[] getTagsArray();
    Code:
       0: getstatic     #3                  // Field org/apache/hadoop/hbase/HConstants.EMPTY_BYTE_ARRAY:[B
       3: areturn

  public int getTagsLength();
    Code:
       0: iconst_0
       1: ireturn

  public int getSerializedSize(boolean);
    Code:
       0: aload_0
       1: getfield      #4                  // Field length:I
       4: ireturn

  public org.apache.hadoop.hbase.ExtendedCell deepClone();
    Code:
       0: aload_0
       1: getfield      #4                  // Field length:I
       4: newarray       byte
       6: astore_1
       7: aload_1
       8: aload_0
       9: getfield      #5                  // Field buf:Ljava/nio/ByteBuffer;
      12: aload_0
      13: getfield      #6                  // Field offset:I
      16: iconst_0
      17: aload_0
      18: getfield      #4                  // Field length:I
      21: invokestatic  #7                  // Method org/apache/hadoop/hbase/util/ByteBufferUtils.copyFromBufferToArray:([BLjava/nio/ByteBuffer;III)V
      24: new           #8                  // class org/apache/hadoop/hbase/NoTagsKeyValue
      27: dup
      28: aload_1
      29: iconst_0
      30: aload_1
      31: arraylength
      32: invokespecial #9                  // Method org/apache/hadoop/hbase/NoTagsKeyValue."<init>":([BII)V
      35: astore_2
      36: aload_2
      37: aload_0
      38: invokevirtual #10                 // Method getSequenceId:()J
      41: invokevirtual #11                 // Method org/apache/hadoop/hbase/KeyValue.setSequenceId:(J)V
      44: aload_2
      45: areturn
}
