Compiled from "NoTagsKeyValue.java"
public class org.apache.hadoop.hbase.NoTagsKeyValue extends org.apache.hadoop.hbase.KeyValue {
  public org.apache.hadoop.hbase.NoTagsKeyValue(byte[], int, int);
    Code:
       0: aload_0
       1: aload_1
       2: iload_2
       3: iload_3
       4: invokespecial #1                  // Method org/apache/hadoop/hbase/KeyValue."<init>":([BII)V
       7: return

  public int getTagsLength();
    Code:
       0: iconst_0
       1: ireturn

  public int write(java.io.OutputStream, boolean) throws java.io.IOException;
    Code:
       0: aload_1
       1: aload_0
       2: getfield      #2                  // Field bytes:[B
       5: aload_0
       6: getfield      #3                  // Field offset:I
       9: aload_0
      10: getfield      #4                  // Field length:I
      13: invokevirtual #5                  // Method java/io/OutputStream.write:([BII)V
      16: aload_0
      17: getfield      #4                  // Field length:I
      20: ireturn

  public int getSerializedSize(boolean);
    Code:
       0: aload_0
       1: getfield      #4                  // Field length:I
       4: ireturn

  public org.apache.hadoop.hbase.ExtendedCell deepClone();
    Code:
       0: aload_0
       1: getfield      #2                  // Field bytes:[B
       4: aload_0
       5: getfield      #3                  // Field offset:I
       8: aload_0
       9: getfield      #4                  // Field length:I
      12: invokestatic  #6                  // Method org/apache/hadoop/hbase/util/Bytes.copy:([BII)[B
      15: astore_1
      16: new           #7                  // class org/apache/hadoop/hbase/NoTagsKeyValue
      19: dup
      20: aload_1
      21: iconst_0
      22: aload_1
      23: arraylength
      24: invokespecial #8                  // Method "<init>":([BII)V
      27: astore_2
      28: aload_2
      29: aload_0
      30: invokevirtual #9                  // Method getSequenceId:()J
      33: invokevirtual #10                 // Method org/apache/hadoop/hbase/KeyValue.setSequenceId:(J)V
      36: aload_2
      37: areturn
}
