Compiled from "OpenRegionHandler.java"
class org.apache.hadoop.hbase.regionserver.handler.OpenRegionHandler$PostOpenDeployTasksThread extends java.lang.Thread {
  org.apache.hadoop.hbase.regionserver.handler.OpenRegionHandler$PostOpenDeployTasksThread(org.apache.hadoop.hbase.regionserver.HRegion, org.apache.hadoop.hbase.Server, org.apache.hadoop.hbase.regionserver.RegionServerServices, java.util.concurrent.atomic.AtomicBoolean, long);
    Code:
       0: aload_0
       1: new           #1                  // class java/lang/StringBuilder
       4: dup
       5: invokespecial #2                  // Method java/lang/StringBuilder."<init>":()V
       8: ldc           #3                  // String PostOpenDeployTasks:
      10: invokevirtual #4                  // Method java/lang/StringBuilder.append:(Ljava/lang/String;)Ljava/lang/StringBuilder;
      13: aload_1
      14: invokevirtual #5                  // Method org/apache/hadoop/hbase/regionserver/HRegion.getRegionInfo:()Lorg/apache/hadoop/hbase/client/RegionInfo;
      17: invokeinterface #6,  1            // InterfaceMethod org/apache/hadoop/hbase/client/RegionInfo.getEncodedName:()Ljava/lang/String;
      22: invokevirtual #4                  // Method java/lang/StringBuilder.append:(Ljava/lang/String;)Ljava/lang/StringBuilder;
      25: invokevirtual #7                  // Method java/lang/StringBuilder.toString:()Ljava/lang/String;
      28: invokespecial #8                  // Method java/lang/Thread."<init>":(Ljava/lang/String;)V
      31: aload_0
      32: aconst_null
      33: putfield      #9                  // Field exception:Ljava/lang/Throwable;
      36: aload_0
      37: iconst_1
      38: invokevirtual #10                 // Method setDaemon:(Z)V
      41: aload_0
      42: aload_2
      43: putfield      #11                 // Field server:Lorg/apache/hadoop/hbase/Server;
      46: aload_0
      47: aload_3
      48: putfield      #12                 // Field services:Lorg/apache/hadoop/hbase/regionserver/RegionServerServices;
      51: aload_0
      52: aload_1
      53: putfield      #13                 // Field region:Lorg/apache/hadoop/hbase/regionserver/HRegion;
      56: aload_0
      57: aload         4
      59: putfield      #14                 // Field signaller:Ljava/util/concurrent/atomic/AtomicBoolean;
      62: aload_0
      63: lload         5
      65: putfield      #15                 // Field masterSystemTime:J
      68: return

  public void run();
    Code:
       0: aload_0
       1: getfield      #12                 // Field services:Lorg/apache/hadoop/hbase/regionserver/RegionServerServices;
       4: new           #16                 // class org/apache/hadoop/hbase/regionserver/RegionServerServices$PostOpenDeployContext
       7: dup
       8: aload_0
       9: getfield      #13                 // Field region:Lorg/apache/hadoop/hbase/regionserver/HRegion;
      12: ldc2_w        #18                 // long -1l
      15: aload_0
      16: getfield      #15                 // Field masterSystemTime:J
      19: invokespecial #20                 // Method org/apache/hadoop/hbase/regionserver/RegionServerServices$PostOpenDeployContext."<init>":(Lorg/apache/hadoop/hbase/regionserver/HRegion;JJ)V
      22: invokeinterface #21,  2           // InterfaceMethod org/apache/hadoop/hbase/regionserver/RegionServerServices.postOpenDeployTasks:(Lorg/apache/hadoop/hbase/regionserver/RegionServerServices$PostOpenDeployContext;)V
      27: goto          115
      30: astore_1
      31: new           #1                  // class java/lang/StringBuilder
      34: dup
      35: invokespecial #2                  // Method java/lang/StringBuilder."<init>":()V
      38: ldc           #23                 // String Exception running postOpenDeployTasks; region=
      40: invokevirtual #4                  // Method java/lang/StringBuilder.append:(Ljava/lang/String;)Ljava/lang/StringBuilder;
      43: aload_0
      44: getfield      #13                 // Field region:Lorg/apache/hadoop/hbase/regionserver/HRegion;
      47: invokevirtual #5                  // Method org/apache/hadoop/hbase/regionserver/HRegion.getRegionInfo:()Lorg/apache/hadoop/hbase/client/RegionInfo;
      50: invokeinterface #6,  1            // InterfaceMethod org/apache/hadoop/hbase/client/RegionInfo.getEncodedName:()Ljava/lang/String;
      55: invokevirtual #4                  // Method java/lang/StringBuilder.append:(Ljava/lang/String;)Ljava/lang/StringBuilder;
      58: invokevirtual #7                  // Method java/lang/StringBuilder.toString:()Ljava/lang/String;
      61: astore_2
      62: aload_0
      63: aload_1
      64: putfield      #9                  // Field exception:Ljava/lang/Throwable;
      67: aload_1
      68: instanceof    #24                 // class java/io/IOException
      71: ifeq          105
      74: aload_0
      75: getfield      #13                 // Field region:Lorg/apache/hadoop/hbase/regionserver/HRegion;
      78: invokevirtual #5                  // Method org/apache/hadoop/hbase/regionserver/HRegion.getRegionInfo:()Lorg/apache/hadoop/hbase/client/RegionInfo;
      81: aload_0
      82: getfield      #12                 // Field services:Lorg/apache/hadoop/hbase/regionserver/RegionServerServices;
      85: invokestatic  #25                 // Method org/apache/hadoop/hbase/regionserver/handler/OpenRegionHandler.access$000:(Lorg/apache/hadoop/hbase/client/RegionInfo;Lorg/apache/hadoop/hbase/regionserver/RegionServerServices;)Z
      88: ifeq          105
      91: aload_0
      92: getfield      #11                 // Field server:Lorg/apache/hadoop/hbase/Server;
      95: aload_2
      96: aload_1
      97: invokeinterface #26,  3           // InterfaceMethod org/apache/hadoop/hbase/Server.abort:(Ljava/lang/String;Ljava/lang/Throwable;)V
     102: goto          115
     105: invokestatic  #27                 // Method org/apache/hadoop/hbase/regionserver/handler/OpenRegionHandler.access$100:()Lorg/slf4j/Logger;
     108: aload_2
     109: aload_1
     110: invokeinterface #28,  3           // InterfaceMethod org/slf4j/Logger.warn:(Ljava/lang/String;Ljava/lang/Throwable;)V
     115: aload_0
     116: getfield      #14                 // Field signaller:Ljava/util/concurrent/atomic/AtomicBoolean;
     119: iconst_1
     120: invokevirtual #29                 // Method java/util/concurrent/atomic/AtomicBoolean.set:(Z)V
     123: aload_0
     124: getfield      #14                 // Field signaller:Ljava/util/concurrent/atomic/AtomicBoolean;
     127: dup
     128: astore_1
     129: monitorenter
     130: aload_0
     131: getfield      #14                 // Field signaller:Ljava/util/concurrent/atomic/AtomicBoolean;
     134: invokevirtual #30                 // Method java/lang/Object.notify:()V
     137: aload_1
     138: monitorexit
     139: goto          147
     142: astore_3
     143: aload_1
     144: monitorexit
     145: aload_3
     146: athrow
     147: return
    Exception table:
       from    to  target type
           0    27    30   Class java/lang/Throwable
         130   139   142   any
         142   145   142   any

  java.lang.Throwable getException();
    Code:
       0: aload_0
       1: getfield      #9                  // Field exception:Ljava/lang/Throwable;
       4: areturn
}
