Compiled from "Operator.java"
public final class org.apache.hadoop.hbase.security.visibility.expression.Operator extends java.lang.Enum<org.apache.hadoop.hbase.security.visibility.expression.Operator> {
  public static final org.apache.hadoop.hbase.security.visibility.expression.Operator AND;

  public static final org.apache.hadoop.hbase.security.visibility.expression.Operator OR;

  public static final org.apache.hadoop.hbase.security.visibility.expression.Operator NOT;

  public static org.apache.hadoop.hbase.security.visibility.expression.Operator[] values();
    Code:
       0: getstatic     #1                  // Field $VALUES:[Lorg/apache/hadoop/hbase/security/visibility/expression/Operator;
       3: invokevirtual #2                  // Method "[Lorg/apache/hadoop/hbase/security/visibility/expression/Operator;".clone:()Ljava/lang/Object;
       6: checkcast     #3                  // class "[Lorg/apache/hadoop/hbase/security/visibility/expression/Operator;"
       9: areturn

  public static org.apache.hadoop.hbase.security.visibility.expression.Operator valueOf(java.lang.String);
    Code:
       0: ldc           #4                  // class org/apache/hadoop/hbase/security/visibility/expression/Operator
       2: aload_0
       3: invokestatic  #5                  // Method java/lang/Enum.valueOf:(Ljava/lang/Class;Ljava/lang/String;)Ljava/lang/Enum;
       6: checkcast     #4                  // class org/apache/hadoop/hbase/security/visibility/expression/Operator
       9: areturn

  public java.lang.String toString();
    Code:
       0: aload_0
       1: getfield      #7                  // Field rep:C
       4: invokestatic  #8                  // Method java/lang/String.valueOf:(C)Ljava/lang/String;
       7: areturn

  static {};
    Code:
       0: new           #4                  // class org/apache/hadoop/hbase/security/visibility/expression/Operator
       3: dup
       4: ldc           #9                  // String AND
       6: iconst_0
       7: bipush        38
       9: invokespecial #10                 // Method "<init>":(Ljava/lang/String;IC)V
      12: putstatic     #11                 // Field AND:Lorg/apache/hadoop/hbase/security/visibility/expression/Operator;
      15: new           #4                  // class org/apache/hadoop/hbase/security/visibility/expression/Operator
      18: dup
      19: ldc           #12                 // String OR
      21: iconst_1
      22: bipush        124
      24: invokespecial #10                 // Method "<init>":(Ljava/lang/String;IC)V
      27: putstatic     #13                 // Field OR:Lorg/apache/hadoop/hbase/security/visibility/expression/Operator;
      30: new           #4                  // class org/apache/hadoop/hbase/security/visibility/expression/Operator
      33: dup
      34: ldc           #14                 // String NOT
      36: iconst_2
      37: bipush        33
      39: invokespecial #10                 // Method "<init>":(Ljava/lang/String;IC)V
      42: putstatic     #15                 // Field NOT:Lorg/apache/hadoop/hbase/security/visibility/expression/Operator;
      45: iconst_3
      46: anewarray     #4                  // class org/apache/hadoop/hbase/security/visibility/expression/Operator
      49: dup
      50: iconst_0
      51: getstatic     #11                 // Field AND:Lorg/apache/hadoop/hbase/security/visibility/expression/Operator;
      54: aastore
      55: dup
      56: iconst_1
      57: getstatic     #13                 // Field OR:Lorg/apache/hadoop/hbase/security/visibility/expression/Operator;
      60: aastore
      61: dup
      62: iconst_2
      63: getstatic     #15                 // Field NOT:Lorg/apache/hadoop/hbase/security/visibility/expression/Operator;
      66: aastore
      67: putstatic     #1                  // Field $VALUES:[Lorg/apache/hadoop/hbase/security/visibility/expression/Operator;
      70: return
}
