Compiled from "OperationWithAttributes.java"
public abstract class org.apache.hadoop.hbase.client.OperationWithAttributes extends org.apache.hadoop.hbase.client.Operation implements org.apache.hadoop.hbase.client.Attributes {
  public static final java.lang.String ID_ATRIBUTE;

  protected org.apache.hadoop.hbase.client.OperationWithAttributes();
    Code:
       0: aload_0
       1: invokespecial #1                  // Method org/apache/hadoop/hbase/client/Operation."<init>":()V
       4: aload_0
       5: iconst_m1
       6: putfield      #3                  // Field priority:I
       9: return

  protected org.apache.hadoop.hbase.client.OperationWithAttributes(org.apache.hadoop.hbase.client.OperationWithAttributes);
    Code:
       0: aload_0
       1: invokespecial #1                  // Method org/apache/hadoop/hbase/client/Operation."<init>":()V
       4: aload_0
       5: iconst_m1
       6: putfield      #3                  // Field priority:I
       9: aload_0
      10: aload_1
      11: invokevirtual #4                  // Method getAttributesMap:()Ljava/util/Map;
      14: ifnonnull     21
      17: aconst_null
      18: goto          66
      21: aload_1
      22: invokevirtual #4                  // Method getAttributesMap:()Ljava/util/Map;
      25: invokeinterface #5,  1            // InterfaceMethod java/util/Map.entrySet:()Ljava/util/Set;
      30: invokeinterface #6,  1            // InterfaceMethod java/util/Set.stream:()Ljava/util/stream/Stream;
      35: invokedynamic #7,  0              // InvokeDynamic #0:apply:()Ljava/util/function/Function;
      40: invokedynamic #8,  0              // InvokeDynamic #1:apply:()Ljava/util/function/Function;
      45: invokedynamic #9,  0              // InvokeDynamic #2:apply:()Ljava/util/function/BinaryOperator;
      50: invokedynamic #10,  0             // InvokeDynamic #3:get:()Ljava/util/function/Supplier;
      55: invokestatic  #11                 // Method java/util/stream/Collectors.toMap:(Ljava/util/function/Function;Ljava/util/function/Function;Ljava/util/function/BinaryOperator;Ljava/util/function/Supplier;)Ljava/util/stream/Collector;
      58: invokeinterface #12,  2           // InterfaceMethod java/util/stream/Stream.collect:(Ljava/util/stream/Collector;)Ljava/lang/Object;
      63: checkcast     #13                 // class java/util/Map
      66: putfield      #14                 // Field attributes:Ljava/util/Map;
      69: aload_0
      70: aload_1
      71: invokevirtual #15                 // Method getPriority:()I
      74: putfield      #3                  // Field priority:I
      77: return

  public org.apache.hadoop.hbase.client.OperationWithAttributes setAttribute(java.lang.String, byte[]);
    Code:
       0: aload_0
       1: getfield      #14                 // Field attributes:Ljava/util/Map;
       4: ifnonnull     13
       7: aload_2
       8: ifnonnull     13
      11: aload_0
      12: areturn
      13: aload_0
      14: getfield      #14                 // Field attributes:Ljava/util/Map;
      17: ifnonnull     31
      20: aload_0
      21: new           #16                 // class java/util/HashMap
      24: dup
      25: invokespecial #17                 // Method java/util/HashMap."<init>":()V
      28: putfield      #14                 // Field attributes:Ljava/util/Map;
      31: aload_2
      32: ifnonnull     66
      35: aload_0
      36: getfield      #14                 // Field attributes:Ljava/util/Map;
      39: aload_1
      40: invokeinterface #18,  2           // InterfaceMethod java/util/Map.remove:(Ljava/lang/Object;)Ljava/lang/Object;
      45: pop
      46: aload_0
      47: getfield      #14                 // Field attributes:Ljava/util/Map;
      50: invokeinterface #19,  1           // InterfaceMethod java/util/Map.isEmpty:()Z
      55: ifeq          78
      58: aload_0
      59: aconst_null
      60: putfield      #14                 // Field attributes:Ljava/util/Map;
      63: goto          78
      66: aload_0
      67: getfield      #14                 // Field attributes:Ljava/util/Map;
      70: aload_1
      71: aload_2
      72: invokeinterface #20,  3           // InterfaceMethod java/util/Map.put:(Ljava/lang/Object;Ljava/lang/Object;)Ljava/lang/Object;
      77: pop
      78: aload_0
      79: areturn

  public byte[] getAttribute(java.lang.String);
    Code:
       0: aload_0
       1: getfield      #14                 // Field attributes:Ljava/util/Map;
       4: ifnonnull     9
       7: aconst_null
       8: areturn
       9: aload_0
      10: getfield      #14                 // Field attributes:Ljava/util/Map;
      13: aload_1
      14: invokeinterface #21,  2           // InterfaceMethod java/util/Map.get:(Ljava/lang/Object;)Ljava/lang/Object;
      19: checkcast     #22                 // class "[B"
      22: areturn

  public java.util.Map<java.lang.String, byte[]> getAttributesMap();
    Code:
       0: aload_0
       1: getfield      #14                 // Field attributes:Ljava/util/Map;
       4: ifnonnull     11
       7: invokestatic  #23                 // Method java/util/Collections.emptyMap:()Ljava/util/Map;
      10: areturn
      11: aload_0
      12: getfield      #14                 // Field attributes:Ljava/util/Map;
      15: invokestatic  #24                 // Method java/util/Collections.unmodifiableMap:(Ljava/util/Map;)Ljava/util/Map;
      18: areturn

  protected long getAttributeSize();
    Code:
       0: lconst_0
       1: lstore_1
       2: aload_0
       3: getfield      #14                 // Field attributes:Ljava/util/Map;
       6: ifnull        113
       9: lload_1
      10: aload_0
      11: getfield      #14                 // Field attributes:Ljava/util/Map;
      14: invokeinterface #25,  1           // InterfaceMethod java/util/Map.size:()I
      19: getstatic     #26                 // Field org/apache/hadoop/hbase/util/ClassSize.MAP_ENTRY:I
      22: imul
      23: invokestatic  #27                 // Method org/apache/hadoop/hbase/util/ClassSize.align:(I)I
      26: i2l
      27: ladd
      28: lstore_1
      29: aload_0
      30: getfield      #14                 // Field attributes:Ljava/util/Map;
      33: invokeinterface #5,  1            // InterfaceMethod java/util/Map.entrySet:()Ljava/util/Set;
      38: invokeinterface #28,  1           // InterfaceMethod java/util/Set.iterator:()Ljava/util/Iterator;
      43: astore_3
      44: aload_3
      45: invokeinterface #29,  1           // InterfaceMethod java/util/Iterator.hasNext:()Z
      50: ifeq          113
      53: aload_3
      54: invokeinterface #30,  1           // InterfaceMethod java/util/Iterator.next:()Ljava/lang/Object;
      59: checkcast     #31                 // class java/util/Map$Entry
      62: astore        4
      64: lload_1
      65: getstatic     #32                 // Field org/apache/hadoop/hbase/util/ClassSize.STRING:I
      68: aload         4
      70: invokeinterface #33,  1           // InterfaceMethod java/util/Map$Entry.getKey:()Ljava/lang/Object;
      75: checkcast     #34                 // class java/lang/String
      78: invokevirtual #35                 // Method java/lang/String.length:()I
      81: iadd
      82: invokestatic  #27                 // Method org/apache/hadoop/hbase/util/ClassSize.align:(I)I
      85: i2l
      86: ladd
      87: lstore_1
      88: lload_1
      89: getstatic     #36                 // Field org/apache/hadoop/hbase/util/ClassSize.ARRAY:I
      92: aload         4
      94: invokeinterface #37,  1           // InterfaceMethod java/util/Map$Entry.getValue:()Ljava/lang/Object;
      99: checkcast     #22                 // class "[B"
     102: arraylength
     103: iadd
     104: invokestatic  #27                 // Method org/apache/hadoop/hbase/util/ClassSize.align:(I)I
     107: i2l
     108: ladd
     109: lstore_1
     110: goto          44
     113: lload_1
     114: lreturn

  public org.apache.hadoop.hbase.client.OperationWithAttributes setId(java.lang.String);
    Code:
       0: aload_0
       1: ldc           #39                 // String _operation.attributes.id
       3: aload_1
       4: invokestatic  #40                 // Method org/apache/hadoop/hbase/util/Bytes.toBytes:(Ljava/lang/String;)[B
       7: invokevirtual #41                 // Method setAttribute:(Ljava/lang/String;[B)Lorg/apache/hadoop/hbase/client/OperationWithAttributes;
      10: pop
      11: aload_0
      12: areturn

  public java.lang.String getId();
    Code:
       0: aload_0
       1: ldc           #39                 // String _operation.attributes.id
       3: invokevirtual #42                 // Method getAttribute:(Ljava/lang/String;)[B
       6: astore_1
       7: aload_1
       8: ifnonnull     15
      11: aconst_null
      12: goto          19
      15: aload_1
      16: invokestatic  #43                 // Method org/apache/hadoop/hbase/util/Bytes.toString:([B)Ljava/lang/String;
      19: areturn

  public org.apache.hadoop.hbase.client.OperationWithAttributes setPriority(int);
    Code:
       0: aload_0
       1: iload_1
       2: putfield      #3                  // Field priority:I
       5: aload_0
       6: areturn

  public int getPriority();
    Code:
       0: aload_0
       1: getfield      #3                  // Field priority:I
       4: ireturn

  public org.apache.hadoop.hbase.client.Attributes setAttribute(java.lang.String, byte[]);
    Code:
       0: aload_0
       1: aload_1
       2: aload_2
       3: invokevirtual #41                 // Method setAttribute:(Ljava/lang/String;[B)Lorg/apache/hadoop/hbase/client/OperationWithAttributes;
       6: areturn
}
