Compiled from "OrderedInt32.java"
public class org.apache.hadoop.hbase.types.OrderedInt32 extends org.apache.hadoop.hbase.types.OrderedBytesBase<java.lang.Integer> {
  public static final org.apache.hadoop.hbase.types.OrderedInt32 ASCENDING;

  public static final org.apache.hadoop.hbase.types.OrderedInt32 DESCENDING;

  protected org.apache.hadoop.hbase.types.OrderedInt32(org.apache.hadoop.hbase.util.Order);
    Code:
       0: aload_0
       1: aload_1
       2: invokespecial #1                  // Method org/apache/hadoop/hbase/types/OrderedBytesBase."<init>":(Lorg/apache/hadoop/hbase/util/Order;)V
       5: return

  public boolean isNullable();
    Code:
       0: iconst_0
       1: ireturn

  public int encodedLength(java.lang.Integer);
    Code:
       0: iconst_5
       1: ireturn

  public java.lang.Class<java.lang.Integer> encodedClass();
    Code:
       0: ldc           #2                  // class java/lang/Integer
       2: areturn

  public java.lang.Integer decode(org.apache.hadoop.hbase.util.PositionedByteRange);
    Code:
       0: aload_1
       1: invokestatic  #3                  // Method org/apache/hadoop/hbase/util/OrderedBytes.decodeInt32:(Lorg/apache/hadoop/hbase/util/PositionedByteRange;)I
       4: invokestatic  #4                  // Method java/lang/Integer.valueOf:(I)Ljava/lang/Integer;
       7: areturn

  public int encode(org.apache.hadoop.hbase.util.PositionedByteRange, java.lang.Integer);
    Code:
       0: aconst_null
       1: aload_2
       2: if_acmpne     15
       5: new           #5                  // class java/lang/IllegalArgumentException
       8: dup
       9: ldc           #6                  // String Null values not supported.
      11: invokespecial #7                  // Method java/lang/IllegalArgumentException."<init>":(Ljava/lang/String;)V
      14: athrow
      15: aload_1
      16: aload_2
      17: invokevirtual #8                  // Method java/lang/Integer.intValue:()I
      20: aload_0
      21: getfield      #9                  // Field order:Lorg/apache/hadoop/hbase/util/Order;
      24: invokestatic  #10                 // Method org/apache/hadoop/hbase/util/OrderedBytes.encodeInt32:(Lorg/apache/hadoop/hbase/util/PositionedByteRange;ILorg/apache/hadoop/hbase/util/Order;)I
      27: ireturn

  public int decodeInt(org.apache.hadoop.hbase.util.PositionedByteRange);
    Code:
       0: aload_1
       1: invokestatic  #3                  // Method org/apache/hadoop/hbase/util/OrderedBytes.decodeInt32:(Lorg/apache/hadoop/hbase/util/PositionedByteRange;)I
       4: ireturn

  public int encodeInt(org.apache.hadoop.hbase.util.PositionedByteRange, int);
    Code:
       0: aload_1
       1: iload_2
       2: aload_0
       3: getfield      #9                  // Field order:Lorg/apache/hadoop/hbase/util/Order;
       6: invokestatic  #10                 // Method org/apache/hadoop/hbase/util/OrderedBytes.encodeInt32:(Lorg/apache/hadoop/hbase/util/PositionedByteRange;ILorg/apache/hadoop/hbase/util/Order;)I
       9: ireturn

  public int encode(org.apache.hadoop.hbase.util.PositionedByteRange, java.lang.Object);
    Code:
       0: aload_0
       1: aload_1
       2: aload_2
       3: checkcast     #2                  // class java/lang/Integer
       6: invokevirtual #11                 // Method encode:(Lorg/apache/hadoop/hbase/util/PositionedByteRange;Ljava/lang/Integer;)I
       9: ireturn

  public java.lang.Object decode(org.apache.hadoop.hbase.util.PositionedByteRange);
    Code:
       0: aload_0
       1: aload_1
       2: invokevirtual #12                 // Method decode:(Lorg/apache/hadoop/hbase/util/PositionedByteRange;)Ljava/lang/Integer;
       5: areturn

  public int encodedLength(java.lang.Object);
    Code:
       0: aload_0
       1: aload_1
       2: checkcast     #2                  // class java/lang/Integer
       5: invokevirtual #13                 // Method encodedLength:(Ljava/lang/Integer;)I
       8: ireturn

  static {};
    Code:
       0: new           #14                 // class org/apache/hadoop/hbase/types/OrderedInt32
       3: dup
       4: getstatic     #15                 // Field org/apache/hadoop/hbase/util/Order.ASCENDING:Lorg/apache/hadoop/hbase/util/Order;
       7: invokespecial #16                 // Method "<init>":(Lorg/apache/hadoop/hbase/util/Order;)V
      10: putstatic     #17                 // Field ASCENDING:Lorg/apache/hadoop/hbase/types/OrderedInt32;
      13: new           #14                 // class org/apache/hadoop/hbase/types/OrderedInt32
      16: dup
      17: getstatic     #18                 // Field org/apache/hadoop/hbase/util/Order.DESCENDING:Lorg/apache/hadoop/hbase/util/Order;
      20: invokespecial #16                 // Method "<init>":(Lorg/apache/hadoop/hbase/util/Order;)V
      23: putstatic     #19                 // Field DESCENDING:Lorg/apache/hadoop/hbase/types/OrderedInt32;
      26: return
}
