Compiled from "OrderedString.java"
public class org.apache.hadoop.hbase.types.OrderedString extends org.apache.hadoop.hbase.types.OrderedBytesBase<java.lang.String> {
  public static final org.apache.hadoop.hbase.types.OrderedString ASCENDING;

  public static final org.apache.hadoop.hbase.types.OrderedString DESCENDING;

  protected org.apache.hadoop.hbase.types.OrderedString(org.apache.hadoop.hbase.util.Order);
    Code:
       0: aload_0
       1: aload_1
       2: invokespecial #1                  // Method org/apache/hadoop/hbase/types/OrderedBytesBase."<init>":(Lorg/apache/hadoop/hbase/util/Order;)V
       5: return

  public int encodedLength(java.lang.String);
    Code:
       0: aconst_null
       1: aload_1
       2: if_acmpne     9
       5: iconst_1
       6: goto          19
       9: aload_1
      10: getstatic     #2                  // Field org/apache/hadoop/hbase/util/OrderedBytes.UTF8:Ljava/nio/charset/Charset;
      13: invokevirtual #3                  // Method java/lang/String.getBytes:(Ljava/nio/charset/Charset;)[B
      16: arraylength
      17: iconst_2
      18: iadd
      19: ireturn

  public java.lang.Class<java.lang.String> encodedClass();
    Code:
       0: ldc           #4                  // class java/lang/String
       2: areturn

  public java.lang.String decode(org.apache.hadoop.hbase.util.PositionedByteRange);
    Code:
       0: aload_1
       1: invokestatic  #5                  // Method org/apache/hadoop/hbase/util/OrderedBytes.decodeString:(Lorg/apache/hadoop/hbase/util/PositionedByteRange;)Ljava/lang/String;
       4: areturn

  public int encode(org.apache.hadoop.hbase.util.PositionedByteRange, java.lang.String);
    Code:
       0: aload_1
       1: aload_2
       2: aload_0
       3: getfield      #6                  // Field order:Lorg/apache/hadoop/hbase/util/Order;
       6: invokestatic  #7                  // Method org/apache/hadoop/hbase/util/OrderedBytes.encodeString:(Lorg/apache/hadoop/hbase/util/PositionedByteRange;Ljava/lang/String;Lorg/apache/hadoop/hbase/util/Order;)I
       9: ireturn

  public int encode(org.apache.hadoop.hbase.util.PositionedByteRange, java.lang.Object);
    Code:
       0: aload_0
       1: aload_1
       2: aload_2
       3: checkcast     #4                  // class java/lang/String
       6: invokevirtual #8                  // Method encode:(Lorg/apache/hadoop/hbase/util/PositionedByteRange;Ljava/lang/String;)I
       9: ireturn

  public java.lang.Object decode(org.apache.hadoop.hbase.util.PositionedByteRange);
    Code:
       0: aload_0
       1: aload_1
       2: invokevirtual #9                  // Method decode:(Lorg/apache/hadoop/hbase/util/PositionedByteRange;)Ljava/lang/String;
       5: areturn

  public int encodedLength(java.lang.Object);
    Code:
       0: aload_0
       1: aload_1
       2: checkcast     #4                  // class java/lang/String
       5: invokevirtual #10                 // Method encodedLength:(Ljava/lang/String;)I
       8: ireturn

  static {};
    Code:
       0: new           #11                 // class org/apache/hadoop/hbase/types/OrderedString
       3: dup
       4: getstatic     #12                 // Field org/apache/hadoop/hbase/util/Order.ASCENDING:Lorg/apache/hadoop/hbase/util/Order;
       7: invokespecial #13                 // Method "<init>":(Lorg/apache/hadoop/hbase/util/Order;)V
      10: putstatic     #14                 // Field ASCENDING:Lorg/apache/hadoop/hbase/types/OrderedString;
      13: new           #11                 // class org/apache/hadoop/hbase/types/OrderedString
      16: dup
      17: getstatic     #15                 // Field org/apache/hadoop/hbase/util/Order.DESCENDING:Lorg/apache/hadoop/hbase/util/Order;
      20: invokespecial #13                 // Method "<init>":(Lorg/apache/hadoop/hbase/util/Order;)V
      23: putstatic     #16                 // Field DESCENDING:Lorg/apache/hadoop/hbase/types/OrderedString;
      26: return
}
