Compiled from "PageFilter.java"
public class org.apache.hadoop.hbase.filter.PageFilter extends org.apache.hadoop.hbase.filter.FilterBase {
  public org.apache.hadoop.hbase.filter.PageFilter(long);
    Code:
       0: aload_0
       1: invokespecial #1                  // Method org/apache/hadoop/hbase/filter/FilterBase."<init>":()V
       4: aload_0
       5: ldc2_w        #3                  // long 9223372036854775807l
       8: putfield      #5                  // Field pageSize:J
      11: aload_0
      12: iconst_0
      13: putfield      #6                  // Field rowsAccepted:I
      16: lload_1
      17: lconst_0
      18: lcmp
      19: iflt          26
      22: iconst_1
      23: goto          27
      26: iconst_0
      27: ldc           #7                  // String must be positive %s
      29: lload_1
      30: invokestatic  #8                  // Method org/apache/hbase/thirdparty/com/google/common/base/Preconditions.checkArgument:(ZLjava/lang/String;J)V
      33: aload_0
      34: lload_1
      35: putfield      #5                  // Field pageSize:J
      38: return

  public long getPageSize();
    Code:
       0: aload_0
       1: getfield      #5                  // Field pageSize:J
       4: lreturn

  public boolean filterRowKey(org.apache.hadoop.hbase.Cell) throws java.io.IOException;
    Code:
       0: aload_0
       1: invokevirtual #9                  // Method filterAllRemaining:()Z
       4: ifeq          9
       7: iconst_1
       8: ireturn
       9: iconst_0
      10: ireturn

  public org.apache.hadoop.hbase.filter.Filter$ReturnCode filterKeyValue(org.apache.hadoop.hbase.Cell) throws java.io.IOException;
    Code:
       0: aload_0
       1: aload_1
       2: invokevirtual #10                 // Method filterCell:(Lorg/apache/hadoop/hbase/Cell;)Lorg/apache/hadoop/hbase/filter/Filter$ReturnCode;
       5: areturn

  public org.apache.hadoop.hbase.filter.Filter$ReturnCode filterCell(org.apache.hadoop.hbase.Cell) throws java.io.IOException;
    Code:
       0: getstatic     #11                 // Field org/apache/hadoop/hbase/filter/Filter$ReturnCode.INCLUDE:Lorg/apache/hadoop/hbase/filter/Filter$ReturnCode;
       3: areturn

  public boolean filterAllRemaining();
    Code:
       0: aload_0
       1: getfield      #6                  // Field rowsAccepted:I
       4: i2l
       5: aload_0
       6: getfield      #5                  // Field pageSize:J
       9: lcmp
      10: iflt          17
      13: iconst_1
      14: goto          18
      17: iconst_0
      18: ireturn

  public boolean filterRow();
    Code:
       0: aload_0
       1: dup
       2: getfield      #6                  // Field rowsAccepted:I
       5: iconst_1
       6: iadd
       7: putfield      #6                  // Field rowsAccepted:I
      10: aload_0
      11: getfield      #6                  // Field rowsAccepted:I
      14: i2l
      15: aload_0
      16: getfield      #5                  // Field pageSize:J
      19: lcmp
      20: ifle          27
      23: iconst_1
      24: goto          28
      27: iconst_0
      28: ireturn

  public boolean hasFilterRow();
    Code:
       0: iconst_1
       1: ireturn

  public static org.apache.hadoop.hbase.filter.Filter createFilterFromArguments(java.util.ArrayList<byte[]>);
    Code:
       0: aload_0
       1: invokevirtual #12                 // Method java/util/ArrayList.size:()I
       4: iconst_1
       5: if_icmpne     12
       8: iconst_1
       9: goto          13
      12: iconst_0
      13: ldc           #13                 // String Expected 1 but got: %s
      15: aload_0
      16: invokevirtual #12                 // Method java/util/ArrayList.size:()I
      19: invokestatic  #14                 // Method org/apache/hbase/thirdparty/com/google/common/base/Preconditions.checkArgument:(ZLjava/lang/String;I)V
      22: aload_0
      23: iconst_0
      24: invokevirtual #15                 // Method java/util/ArrayList.get:(I)Ljava/lang/Object;
      27: checkcast     #16                 // class "[B"
      30: invokestatic  #17                 // Method org/apache/hadoop/hbase/filter/ParseFilter.convertByteArrayToLong:([B)J
      33: lstore_1
      34: new           #18                 // class org/apache/hadoop/hbase/filter/PageFilter
      37: dup
      38: lload_1
      39: invokespecial #19                 // Method "<init>":(J)V
      42: areturn

  public byte[] toByteArray();
    Code:
       0: invokestatic  #20                 // Method org/apache/hadoop/hbase/shaded/protobuf/generated/FilterProtos$PageFilter.newBuilder:()Lorg/apache/hadoop/hbase/shaded/protobuf/generated/FilterProtos$PageFilter$Builder;
       3: astore_1
       4: aload_1
       5: aload_0
       6: getfield      #5                  // Field pageSize:J
       9: invokevirtual #21                 // Method org/apache/hadoop/hbase/shaded/protobuf/generated/FilterProtos$PageFilter$Builder.setPageSize:(J)Lorg/apache/hadoop/hbase/shaded/protobuf/generated/FilterProtos$PageFilter$Builder;
      12: pop
      13: aload_1
      14: invokevirtual #22                 // Method org/apache/hadoop/hbase/shaded/protobuf/generated/FilterProtos$PageFilter$Builder.build:()Lorg/apache/hadoop/hbase/shaded/protobuf/generated/FilterProtos$PageFilter;
      17: invokevirtual #23                 // Method org/apache/hadoop/hbase/shaded/protobuf/generated/FilterProtos$PageFilter.toByteArray:()[B
      20: areturn

  public static org.apache.hadoop.hbase.filter.PageFilter parseFrom(byte[]) throws org.apache.hadoop.hbase.exceptions.DeserializationException;
    Code:
       0: aload_0
       1: invokestatic  #24                 // Method org/apache/hadoop/hbase/shaded/protobuf/generated/FilterProtos$PageFilter.parseFrom:([B)Lorg/apache/hadoop/hbase/shaded/protobuf/generated/FilterProtos$PageFilter;
       4: astore_1
       5: goto          18
       8: astore_2
       9: new           #26                 // class org/apache/hadoop/hbase/exceptions/DeserializationException
      12: dup
      13: aload_2
      14: invokespecial #27                 // Method org/apache/hadoop/hbase/exceptions/DeserializationException."<init>":(Ljava/lang/Throwable;)V
      17: athrow
      18: new           #18                 // class org/apache/hadoop/hbase/filter/PageFilter
      21: dup
      22: aload_1
      23: invokevirtual #28                 // Method org/apache/hadoop/hbase/shaded/protobuf/generated/FilterProtos$PageFilter.getPageSize:()J
      26: invokespecial #19                 // Method "<init>":(J)V
      29: areturn
    Exception table:
       from    to  target type
           0     5     8   Class org/apache/hbase/thirdparty/com/google/protobuf/InvalidProtocolBufferException

  boolean areSerializedFieldsEqual(org.apache.hadoop.hbase.filter.Filter);
    Code:
       0: aload_1
       1: aload_0
       2: if_acmpne     7
       5: iconst_1
       6: ireturn
       7: aload_1
       8: instanceof    #18                 // class org/apache/hadoop/hbase/filter/PageFilter
      11: ifne          16
      14: iconst_0
      15: ireturn
      16: aload_1
      17: checkcast     #18                 // class org/apache/hadoop/hbase/filter/PageFilter
      20: astore_2
      21: aload_0
      22: invokevirtual #29                 // Method getPageSize:()J
      25: aload_2
      26: invokevirtual #29                 // Method getPageSize:()J
      29: lcmp
      30: ifne          37
      33: iconst_1
      34: goto          38
      37: iconst_0
      38: ireturn

  public java.lang.String toString();
    Code:
       0: new           #30                 // class java/lang/StringBuilder
       3: dup
       4: invokespecial #31                 // Method java/lang/StringBuilder."<init>":()V
       7: aload_0
       8: invokevirtual #32                 // Method java/lang/Object.getClass:()Ljava/lang/Class;
      11: invokevirtual #33                 // Method java/lang/Class.getSimpleName:()Ljava/lang/String;
      14: invokevirtual #34                 // Method java/lang/StringBuilder.append:(Ljava/lang/String;)Ljava/lang/StringBuilder;
      17: ldc           #35                 // String
      19: invokevirtual #34                 // Method java/lang/StringBuilder.append:(Ljava/lang/String;)Ljava/lang/StringBuilder;
      22: aload_0
      23: getfield      #5                  // Field pageSize:J
      26: invokevirtual #36                 // Method java/lang/StringBuilder.append:(J)Ljava/lang/StringBuilder;
      29: invokevirtual #37                 // Method java/lang/StringBuilder.toString:()Ljava/lang/String;
      32: areturn

  public boolean equals(java.lang.Object);
    Code:
       0: aload_1
       1: instanceof    #38                 // class org/apache/hadoop/hbase/filter/Filter
       4: ifeq          22
       7: aload_0
       8: aload_1
       9: checkcast     #38                 // class org/apache/hadoop/hbase/filter/Filter
      12: invokevirtual #39                 // Method areSerializedFieldsEqual:(Lorg/apache/hadoop/hbase/filter/Filter;)Z
      15: ifeq          22
      18: iconst_1
      19: goto          23
      22: iconst_0
      23: ireturn

  public int hashCode();
    Code:
       0: iconst_1
       1: anewarray     #40                 // class java/lang/Object
       4: dup
       5: iconst_0
       6: aload_0
       7: getfield      #5                  // Field pageSize:J
      10: invokestatic  #41                 // Method java/lang/Long.valueOf:(J)Ljava/lang/Long;
      13: aastore
      14: invokestatic  #42                 // Method java/util/Objects.hash:([Ljava/lang/Object;)I
      17: ireturn
}
