Compiled from "PartitionedMobCompactionRequest.java"
public class org.apache.hadoop.hbase.mob.compactions.PartitionedMobCompactionRequest extends org.apache.hadoop.hbase.mob.compactions.MobCompactionRequest {
  protected java.util.List<org.apache.hadoop.hbase.mob.compactions.PartitionedMobCompactionRequest$CompactionDelPartition> delPartitions;

  protected java.util.Collection<org.apache.hadoop.hbase.mob.compactions.PartitionedMobCompactionRequest$CompactionPartition> compactionPartitions;

  public org.apache.hadoop.hbase.mob.compactions.PartitionedMobCompactionRequest(java.util.Collection<org.apache.hadoop.hbase.mob.compactions.PartitionedMobCompactionRequest$CompactionPartition>, java.util.List<org.apache.hadoop.hbase.mob.compactions.PartitionedMobCompactionRequest$CompactionDelPartition>);
    Code:
       0: aload_0
       1: invokespecial #1                  // Method org/apache/hadoop/hbase/mob/compactions/MobCompactionRequest."<init>":()V
       4: aload_0
       5: invokestatic  #2                  // Method org/apache/hadoop/hbase/util/EnvironmentEdgeManager.currentTime:()J
       8: putfield      #3                  // Field selectionTime:J
      11: aload_0
      12: aload_1
      13: putfield      #4                  // Field compactionPartitions:Ljava/util/Collection;
      16: aload_0
      17: aload_2
      18: putfield      #5                  // Field delPartitions:Ljava/util/List;
      21: return

  public java.util.Collection<org.apache.hadoop.hbase.mob.compactions.PartitionedMobCompactionRequest$CompactionPartition> getCompactionPartitions();
    Code:
       0: aload_0
       1: getfield      #4                  // Field compactionPartitions:Ljava/util/Collection;
       4: areturn

  public java.util.List<org.apache.hadoop.hbase.mob.compactions.PartitionedMobCompactionRequest$CompactionDelPartition> getDelPartitions();
    Code:
       0: aload_0
       1: getfield      #5                  // Field delPartitions:Ljava/util/List;
       4: areturn
}
