Compiled from "PartitionedMobCompactor.java"
class org.apache.hadoop.hbase.mob.compactions.PartitionedMobCompactor$DelPartitionComparator implements java.util.Comparator<org.apache.hadoop.hbase.mob.compactions.PartitionedMobCompactionRequest$CompactionDelPartition> {
  org.apache.hadoop.hbase.mob.compactions.PartitionedMobCompactor$DelPartitionComparator(boolean);
    Code:
       0: aload_0
       1: invokespecial #1                  // Method java/lang/Object."<init>":()V
       4: aload_0
       5: iload_1
       6: putfield      #2                  // Field compareStartKey:Z
       9: return

  public boolean getCompareStartKey();
    Code:
       0: aload_0
       1: getfield      #2                  // Field compareStartKey:Z
       4: ireturn

  public void setCompareStartKey(boolean);
    Code:
       0: aload_0
       1: iload_1
       2: putfield      #2                  // Field compareStartKey:Z
       5: return

  public int compare(org.apache.hadoop.hbase.mob.compactions.PartitionedMobCompactionRequest$CompactionDelPartition, org.apache.hadoop.hbase.mob.compactions.PartitionedMobCompactionRequest$CompactionDelPartition);
    Code:
       0: aload_0
       1: getfield      #2                  // Field compareStartKey:Z
       4: ifeq          25
       7: aload_1
       8: invokevirtual #3                  // Method org/apache/hadoop/hbase/mob/compactions/PartitionedMobCompactionRequest$CompactionDelPartition.getId:()Lorg/apache/hadoop/hbase/mob/compactions/PartitionedMobCompactionRequest$CompactionDelPartitionId;
      11: invokevirtual #4                  // Method org/apache/hadoop/hbase/mob/compactions/PartitionedMobCompactionRequest$CompactionDelPartitionId.getStartKey:()[B
      14: aload_2
      15: invokevirtual #3                  // Method org/apache/hadoop/hbase/mob/compactions/PartitionedMobCompactionRequest$CompactionDelPartition.getId:()Lorg/apache/hadoop/hbase/mob/compactions/PartitionedMobCompactionRequest$CompactionDelPartitionId;
      18: invokevirtual #4                  // Method org/apache/hadoop/hbase/mob/compactions/PartitionedMobCompactionRequest$CompactionDelPartitionId.getStartKey:()[B
      21: invokestatic  #5                  // Method org/apache/hadoop/hbase/util/Bytes.compareTo:([B[B)I
      24: ireturn
      25: aload_1
      26: invokevirtual #3                  // Method org/apache/hadoop/hbase/mob/compactions/PartitionedMobCompactionRequest$CompactionDelPartition.getId:()Lorg/apache/hadoop/hbase/mob/compactions/PartitionedMobCompactionRequest$CompactionDelPartitionId;
      29: invokevirtual #6                  // Method org/apache/hadoop/hbase/mob/compactions/PartitionedMobCompactionRequest$CompactionDelPartitionId.getEndKey:()[B
      32: aload_2
      33: invokevirtual #3                  // Method org/apache/hadoop/hbase/mob/compactions/PartitionedMobCompactionRequest$CompactionDelPartition.getId:()Lorg/apache/hadoop/hbase/mob/compactions/PartitionedMobCompactionRequest$CompactionDelPartitionId;
      36: invokevirtual #6                  // Method org/apache/hadoop/hbase/mob/compactions/PartitionedMobCompactionRequest$CompactionDelPartitionId.getEndKey:()[B
      39: invokestatic  #5                  // Method org/apache/hadoop/hbase/util/Bytes.compareTo:([B[B)I
      42: ireturn

  public int compare(java.lang.Object, java.lang.Object);
    Code:
       0: aload_0
       1: aload_1
       2: checkcast     #7                  // class org/apache/hadoop/hbase/mob/compactions/PartitionedMobCompactionRequest$CompactionDelPartition
       5: aload_2
       6: checkcast     #7                  // class org/apache/hadoop/hbase/mob/compactions/PartitionedMobCompactionRequest$CompactionDelPartition
       9: invokevirtual #8                  // Method compare:(Lorg/apache/hadoop/hbase/mob/compactions/PartitionedMobCompactionRequest$CompactionDelPartition;Lorg/apache/hadoop/hbase/mob/compactions/PartitionedMobCompactionRequest$CompactionDelPartition;)I
      12: ireturn
}
