Compiled from "PartitionedMobCompactionRequest.java"
public class org.apache.hadoop.hbase.mob.compactions.PartitionedMobCompactionRequest$CompactionDelPartitionId implements java.lang.Comparable<org.apache.hadoop.hbase.mob.compactions.PartitionedMobCompactionRequest$CompactionDelPartitionId> {
  public org.apache.hadoop.hbase.mob.compactions.PartitionedMobCompactionRequest$CompactionDelPartitionId();
    Code:
       0: aload_0
       1: invokespecial #1                  // Method java/lang/Object."<init>":()V
       4: return

  public org.apache.hadoop.hbase.mob.compactions.PartitionedMobCompactionRequest$CompactionDelPartitionId(byte[], byte[]);
    Code:
       0: aload_0
       1: invokespecial #1                  // Method java/lang/Object."<init>":()V
       4: aload_0
       5: aload_1
       6: putfield      #2                  // Field startKey:[B
       9: aload_0
      10: aload_2
      11: putfield      #3                  // Field endKey:[B
      14: return

  public byte[] getStartKey();
    Code:
       0: aload_0
       1: getfield      #2                  // Field startKey:[B
       4: areturn

  public void setStartKey(byte[]);
    Code:
       0: aload_0
       1: aload_1
       2: putfield      #2                  // Field startKey:[B
       5: return

  public byte[] getEndKey();
    Code:
       0: aload_0
       1: getfield      #3                  // Field endKey:[B
       4: areturn

  public void setEndKey(byte[]);
    Code:
       0: aload_0
       1: aload_1
       2: putfield      #3                  // Field endKey:[B
       5: return

  public int compareTo(org.apache.hadoop.hbase.mob.compactions.PartitionedMobCompactionRequest$CompactionDelPartitionId);
    Code:
       0: aload_0
       1: getfield      #2                  // Field startKey:[B
       4: aload_1
       5: invokevirtual #4                  // Method getStartKey:()[B
       8: invokestatic  #5                  // Method org/apache/hadoop/hbase/util/Bytes.compareTo:([B[B)I
      11: istore_2
      12: iload_2
      13: ifeq          18
      16: iload_2
      17: ireturn
      18: aload_0
      19: getfield      #3                  // Field endKey:[B
      22: aload_1
      23: invokevirtual #6                  // Method getEndKey:()[B
      26: invokestatic  #5                  // Method org/apache/hadoop/hbase/util/Bytes.compareTo:([B[B)I
      29: ireturn

  public int hashCode();
    Code:
       0: bipush        17
       2: istore_1
       3: bipush        31
       5: iload_1
       6: imul
       7: aload_0
       8: getfield      #2                  // Field startKey:[B
      11: invokestatic  #7                  // Method java/util/Arrays.hashCode:([B)I
      14: iadd
      15: istore_1
      16: bipush        31
      18: iload_1
      19: imul
      20: aload_0
      21: getfield      #3                  // Field endKey:[B
      24: invokestatic  #7                  // Method java/util/Arrays.hashCode:([B)I
      27: iadd
      28: istore_1
      29: iload_1
      30: ireturn

  public boolean equals(java.lang.Object);
    Code:
       0: aload_0
       1: aload_1
       2: if_acmpne     7
       5: iconst_1
       6: ireturn
       7: aload_1
       8: instanceof    #8                  // class org/apache/hadoop/hbase/mob/compactions/PartitionedMobCompactionRequest$CompactionDelPartitionId
      11: ifne          16
      14: iconst_0
      15: ireturn
      16: aload_1
      17: checkcast     #8                  // class org/apache/hadoop/hbase/mob/compactions/PartitionedMobCompactionRequest$CompactionDelPartitionId
      20: astore_2
      21: aload_0
      22: aload_2
      23: invokevirtual #9                  // Method compareTo:(Lorg/apache/hadoop/hbase/mob/compactions/PartitionedMobCompactionRequest$CompactionDelPartitionId;)I
      26: ifne          33
      29: iconst_1
      30: goto          34
      33: iconst_0
      34: ireturn

  public int compareTo(java.lang.Object);
    Code:
       0: aload_0
       1: aload_1
       2: checkcast     #8                  // class org/apache/hadoop/hbase/mob/compactions/PartitionedMobCompactionRequest$CompactionDelPartitionId
       5: invokevirtual #9                  // Method compareTo:(Lorg/apache/hadoop/hbase/mob/compactions/PartitionedMobCompactionRequest$CompactionDelPartitionId;)I
       8: ireturn
}
