Compiled from "PartitionedMobCompactionRequest.java"
public class org.apache.hadoop.hbase.mob.compactions.PartitionedMobCompactionRequest$CompactionDelPartition {
  public org.apache.hadoop.hbase.mob.compactions.PartitionedMobCompactionRequest$CompactionDelPartition(org.apache.hadoop.hbase.mob.compactions.PartitionedMobCompactionRequest$CompactionDelPartitionId);
    Code:
       0: aload_0
       1: invokespecial #1                  // Method java/lang/Object."<init>":()V
       4: aload_0
       5: new           #2                  // class java/util/ArrayList
       8: dup
       9: invokespecial #3                  // Method java/util/ArrayList."<init>":()V
      12: putfield      #4                  // Field delFiles:Ljava/util/List;
      15: aload_0
      16: new           #2                  // class java/util/ArrayList
      19: dup
      20: invokespecial #3                  // Method java/util/ArrayList."<init>":()V
      23: putfield      #5                  // Field storeFiles:Ljava/util/List;
      26: aload_0
      27: aload_1
      28: putfield      #6                  // Field id:Lorg/apache/hadoop/hbase/mob/compactions/PartitionedMobCompactionRequest$CompactionDelPartitionId;
      31: return

  public org.apache.hadoop.hbase.mob.compactions.PartitionedMobCompactionRequest$CompactionDelPartitionId getId();
    Code:
       0: aload_0
       1: getfield      #6                  // Field id:Lorg/apache/hadoop/hbase/mob/compactions/PartitionedMobCompactionRequest$CompactionDelPartitionId;
       4: areturn

  void addDelFile(org.apache.hadoop.fs.FileStatus);
    Code:
       0: aload_0
       1: getfield      #4                  // Field delFiles:Ljava/util/List;
       4: aload_1
       5: invokevirtual #7                  // Method org/apache/hadoop/fs/FileStatus.getPath:()Lorg/apache/hadoop/fs/Path;
       8: invokeinterface #8,  2            // InterfaceMethod java/util/List.add:(Ljava/lang/Object;)Z
      13: pop
      14: return

  public void addStoreFile(org.apache.hadoop.hbase.regionserver.HStoreFile);
    Code:
       0: aload_0
       1: getfield      #5                  // Field storeFiles:Ljava/util/List;
       4: aload_1
       5: invokeinterface #8,  2            // InterfaceMethod java/util/List.add:(Ljava/lang/Object;)Z
      10: pop
      11: return

  public java.util.List<org.apache.hadoop.hbase.regionserver.HStoreFile> getStoreFiles();
    Code:
       0: aload_0
       1: getfield      #5                  // Field storeFiles:Ljava/util/List;
       4: areturn

  java.util.List<org.apache.hadoop.fs.Path> listDelFiles();
    Code:
       0: aload_0
       1: getfield      #4                  // Field delFiles:Ljava/util/List;
       4: invokestatic  #9                  // Method java/util/Collections.unmodifiableList:(Ljava/util/List;)Ljava/util/List;
       7: areturn

  void addDelFileList(java.util.Collection<org.apache.hadoop.fs.Path>);
    Code:
       0: aload_0
       1: getfield      #4                  // Field delFiles:Ljava/util/List;
       4: aload_1
       5: invokeinterface #10,  2           // InterfaceMethod java/util/List.addAll:(Ljava/util/Collection;)Z
      10: pop
      11: return

  int getDelFileCount();
    Code:
       0: aload_0
       1: getfield      #4                  // Field delFiles:Ljava/util/List;
       4: invokeinterface #11,  1           // InterfaceMethod java/util/List.size:()I
       9: ireturn

  void cleanDelFiles();
    Code:
       0: aload_0
       1: getfield      #4                  // Field delFiles:Ljava/util/List;
       4: invokeinterface #12,  1           // InterfaceMethod java/util/List.clear:()V
       9: return
}
