Compiled from "PartitionedMobCompactionRequest.java"
public class org.apache.hadoop.hbase.mob.compactions.PartitionedMobCompactionRequest$CompactionPartition {
  public org.apache.hadoop.hbase.mob.compactions.PartitionedMobCompactionRequest$CompactionPartition(org.apache.hadoop.hbase.mob.compactions.PartitionedMobCompactionRequest$CompactionPartitionId);
    Code:
       0: aload_0
       1: invokespecial #1                  // Method java/lang/Object."<init>":()V
       4: aload_0
       5: new           #2                  // class java/util/ArrayList
       8: dup
       9: invokespecial #3                  // Method java/util/ArrayList."<init>":()V
      12: putfield      #4                  // Field files:Ljava/util/List;
      15: aload_0
      16: aload_1
      17: putfield      #5                  // Field partitionId:Lorg/apache/hadoop/hbase/mob/compactions/PartitionedMobCompactionRequest$CompactionPartitionId;
      20: return

  public org.apache.hadoop.hbase.mob.compactions.PartitionedMobCompactionRequest$CompactionPartitionId getPartitionId();
    Code:
       0: aload_0
       1: getfield      #5                  // Field partitionId:Lorg/apache/hadoop/hbase/mob/compactions/PartitionedMobCompactionRequest$CompactionPartitionId;
       4: areturn

  public void addFile(org.apache.hadoop.fs.FileStatus);
    Code:
       0: aload_0
       1: getfield      #4                  // Field files:Ljava/util/List;
       4: aload_1
       5: invokeinterface #6,  2            // InterfaceMethod java/util/List.add:(Ljava/lang/Object;)Z
      10: pop
      11: return

  public java.util.List<org.apache.hadoop.fs.FileStatus> listFiles();
    Code:
       0: aload_0
       1: getfield      #4                  // Field files:Ljava/util/List;
       4: invokestatic  #7                  // Method java/util/Collections.unmodifiableList:(Ljava/util/List;)Ljava/util/List;
       7: areturn

  public int getFileCount();
    Code:
       0: aload_0
       1: getfield      #4                  // Field files:Ljava/util/List;
       4: invokeinterface #8,  1            // InterfaceMethod java/util/List.size:()I
       9: ireturn

  public byte[] getStartKey();
    Code:
       0: aload_0
       1: getfield      #9                  // Field startKey:[B
       4: areturn

  public void setStartKey(byte[]);
    Code:
       0: aload_0
       1: getfield      #9                  // Field startKey:[B
       4: ifnull        18
       7: aload_1
       8: aload_0
       9: getfield      #9                  // Field startKey:[B
      12: invokestatic  #10                 // Method org/apache/hadoop/hbase/util/Bytes.compareTo:([B[B)I
      15: ifge          23
      18: aload_0
      19: aload_1
      20: putfield      #9                  // Field startKey:[B
      23: return

  public byte[] getEndKey();
    Code:
       0: aload_0
       1: getfield      #11                 // Field endKey:[B
       4: areturn

  public void setEndKey(byte[]);
    Code:
       0: aload_0
       1: getfield      #11                 // Field endKey:[B
       4: ifnull        18
       7: aload_1
       8: aload_0
       9: getfield      #11                 // Field endKey:[B
      12: invokestatic  #10                 // Method org/apache/hadoop/hbase/util/Bytes.compareTo:([B[B)I
      15: ifle          23
      18: aload_0
      19: aload_1
      20: putfield      #11                 // Field endKey:[B
      23: return
}
