Compiled from "PartitionedMobCompactionRequest.java"
public class org.apache.hadoop.hbase.mob.compactions.PartitionedMobCompactionRequest$CompactionPartitionId {
  public org.apache.hadoop.hbase.mob.compactions.PartitionedMobCompactionRequest$CompactionPartitionId();
    Code:
       0: aload_0
       1: invokespecial #1                  // Method java/lang/Object."<init>":()V
       4: aload_0
       5: ldc           #2                  // String
       7: putfield      #3                  // Field startKey:Ljava/lang/String;
      10: aload_0
      11: ldc           #2                  // String
      13: putfield      #4                  // Field date:Ljava/lang/String;
      16: aload_0
      17: ldc           #2                  // String
      19: putfield      #5                  // Field latestDate:Ljava/lang/String;
      22: aload_0
      23: lconst_0
      24: putfield      #6                  // Field threshold:J
      27: return

  public org.apache.hadoop.hbase.mob.compactions.PartitionedMobCompactionRequest$CompactionPartitionId(java.lang.String, java.lang.String);
    Code:
       0: aload_0
       1: invokespecial #1                  // Method java/lang/Object."<init>":()V
       4: aload_1
       5: ifnull        12
       8: aload_2
       9: ifnonnull     22
      12: new           #7                  // class java/lang/IllegalArgumentException
      15: dup
      16: ldc           #8                  // String Neither of start key and date could be null
      18: invokespecial #9                  // Method java/lang/IllegalArgumentException."<init>":(Ljava/lang/String;)V
      21: athrow
      22: aload_0
      23: aload_1
      24: putfield      #3                  // Field startKey:Ljava/lang/String;
      27: aload_0
      28: aload_2
      29: putfield      #4                  // Field date:Ljava/lang/String;
      32: aload_0
      33: ldc           #2                  // String
      35: putfield      #5                  // Field latestDate:Ljava/lang/String;
      38: aload_0
      39: lconst_0
      40: putfield      #6                  // Field threshold:J
      43: return

  public void setThreshold(long);
    Code:
       0: aload_0
       1: lload_1
       2: putfield      #6                  // Field threshold:J
       5: return

  public long getThreshold();
    Code:
       0: aload_0
       1: getfield      #6                  // Field threshold:J
       4: lreturn

  public java.lang.String getStartKey();
    Code:
       0: aload_0
       1: getfield      #3                  // Field startKey:Ljava/lang/String;
       4: areturn

  public void setStartKey(java.lang.String);
    Code:
       0: aload_0
       1: aload_1
       2: putfield      #3                  // Field startKey:Ljava/lang/String;
       5: return

  public java.lang.String getDate();
    Code:
       0: aload_0
       1: getfield      #4                  // Field date:Ljava/lang/String;
       4: areturn

  public void setDate(java.lang.String);
    Code:
       0: aload_0
       1: aload_1
       2: putfield      #4                  // Field date:Ljava/lang/String;
       5: return

  public java.lang.String getLatestDate();
    Code:
       0: aload_0
       1: getfield      #5                  // Field latestDate:Ljava/lang/String;
       4: areturn

  public void updateLatestDate(java.lang.String);
    Code:
       0: aload_0
       1: getfield      #5                  // Field latestDate:Ljava/lang/String;
       4: aload_1
       5: invokevirtual #10                 // Method java/lang/String.compareTo:(Ljava/lang/String;)I
       8: ifge          16
      11: aload_0
      12: aload_1
      13: putfield      #5                  // Field latestDate:Ljava/lang/String;
      16: return

  public int hashCode();
    Code:
       0: bipush        17
       2: istore_1
       3: bipush        31
       5: iload_1
       6: imul
       7: aload_0
       8: getfield      #3                  // Field startKey:Ljava/lang/String;
      11: invokevirtual #11                 // Method java/lang/String.hashCode:()I
      14: iadd
      15: istore_1
      16: bipush        31
      18: iload_1
      19: imul
      20: aload_0
      21: getfield      #4                  // Field date:Ljava/lang/String;
      24: invokevirtual #11                 // Method java/lang/String.hashCode:()I
      27: iadd
      28: istore_1
      29: iload_1
      30: ireturn

  public boolean equals(java.lang.Object);
    Code:
       0: aload_0
       1: aload_1
       2: if_acmpne     7
       5: iconst_1
       6: ireturn
       7: aload_1
       8: instanceof    #12                 // class org/apache/hadoop/hbase/mob/compactions/PartitionedMobCompactionRequest$CompactionPartitionId
      11: ifne          16
      14: iconst_0
      15: ireturn
      16: aload_1
      17: checkcast     #12                 // class org/apache/hadoop/hbase/mob/compactions/PartitionedMobCompactionRequest$CompactionPartitionId
      20: astore_2
      21: aload_0
      22: getfield      #3                  // Field startKey:Ljava/lang/String;
      25: aload_2
      26: getfield      #3                  // Field startKey:Ljava/lang/String;
      29: invokevirtual #13                 // Method java/lang/String.equals:(Ljava/lang/Object;)Z
      32: ifne          37
      35: iconst_0
      36: ireturn
      37: aload_0
      38: getfield      #4                  // Field date:Ljava/lang/String;
      41: aload_2
      42: getfield      #4                  // Field date:Ljava/lang/String;
      45: invokevirtual #13                 // Method java/lang/String.equals:(Ljava/lang/Object;)Z
      48: ifne          53
      51: iconst_0
      52: ireturn
      53: iconst_1
      54: ireturn

  public java.lang.String toString();
    Code:
       0: new           #14                 // class java/lang/StringBuilder
       3: dup
       4: aload_0
       5: getfield      #3                  // Field startKey:Ljava/lang/String;
       8: invokespecial #15                 // Method java/lang/StringBuilder."<init>":(Ljava/lang/String;)V
      11: aload_0
      12: getfield      #4                  // Field date:Ljava/lang/String;
      15: invokevirtual #16                 // Method java/lang/StringBuilder.append:(Ljava/lang/String;)Ljava/lang/StringBuilder;
      18: invokevirtual #17                 // Method java/lang/StringBuilder.toString:()Ljava/lang/String;
      21: areturn
}
