Compiled from "PeerQueue.java"
class org.apache.hadoop.hbase.master.procedure.PeerQueue extends org.apache.hadoop.hbase.master.procedure.Queue<java.lang.String> {
  public org.apache.hadoop.hbase.master.procedure.PeerQueue(java.lang.String, org.apache.hadoop.hbase.procedure2.LockStatus);
    Code:
       0: aload_0
       1: aload_1
       2: aload_2
       3: invokespecial #1                  // Method org/apache/hadoop/hbase/master/procedure/Queue."<init>":(Ljava/lang/Comparable;Lorg/apache/hadoop/hbase/procedure2/LockStatus;)V
       6: return

  public boolean requireExclusiveLock(org.apache.hadoop.hbase.procedure2.Procedure<?>);
    Code:
       0: aload_1
       1: checkcast     #2                  // class org/apache/hadoop/hbase/master/procedure/PeerProcedureInterface
       4: invokestatic  #3                  // Method requirePeerExclusiveLock:(Lorg/apache/hadoop/hbase/master/procedure/PeerProcedureInterface;)Z
       7: ireturn
}
