Compiled from "PendingWatcher.java"
class org.apache.hadoop.hbase.zookeeper.PendingWatcher implements org.apache.zookeeper.Watcher {
  org.apache.hadoop.hbase.zookeeper.PendingWatcher();
    Code:
       0: aload_0
       1: invokespecial #1                  // Method java/lang/Object."<init>":()V
       4: aload_0
       5: new           #2                  // class org/apache/hadoop/hbase/zookeeper/InstancePending
       8: dup
       9: invokespecial #3                  // Method org/apache/hadoop/hbase/zookeeper/InstancePending."<init>":()V
      12: putfield      #4                  // Field pending:Lorg/apache/hadoop/hbase/zookeeper/InstancePending;
      15: return

  public void process(org.apache.zookeeper.WatchedEvent);
    Code:
       0: aload_0
       1: getfield      #4                  // Field pending:Lorg/apache/hadoop/hbase/zookeeper/InstancePending;
       4: invokevirtual #5                  // Method org/apache/hadoop/hbase/zookeeper/InstancePending.get:()Ljava/lang/Object;
       7: checkcast     #6                  // class org/apache/zookeeper/Watcher
      10: aload_1
      11: invokeinterface #7,  2            // InterfaceMethod org/apache/zookeeper/Watcher.process:(Lorg/apache/zookeeper/WatchedEvent;)V
      16: return

  void prepare(org.apache.zookeeper.Watcher);
    Code:
       0: aload_0
       1: getfield      #4                  // Field pending:Lorg/apache/hadoop/hbase/zookeeper/InstancePending;
       4: aload_1
       5: invokevirtual #8                  // Method org/apache/hadoop/hbase/zookeeper/InstancePending.prepare:(Ljava/lang/Object;)V
       8: return
}
