Compiled from "PingProtos.java"
public abstract class org.apache.hadoop.hbase.coprocessor.protobuf.generated.PingProtos$PingService implements com.google.protobuf.Service {
  protected org.apache.hadoop.hbase.coprocessor.protobuf.generated.PingProtos$PingService();
    Code:
       0: aload_0
       1: invokespecial #1                  // Method java/lang/Object."<init>":()V
       4: return

  public static com.google.protobuf.Service newReflectiveService(org.apache.hadoop.hbase.coprocessor.protobuf.generated.PingProtos$PingService$Interface);
    Code:
       0: new           #2                  // class org/apache/hadoop/hbase/coprocessor/protobuf/generated/PingProtos$PingService$1
       3: dup
       4: aload_0
       5: invokespecial #3                  // Method org/apache/hadoop/hbase/coprocessor/protobuf/generated/PingProtos$PingService$1."<init>":(Lorg/apache/hadoop/hbase/coprocessor/protobuf/generated/PingProtos$PingService$Interface;)V
       8: areturn

  public static com.google.protobuf.BlockingService newReflectiveBlockingService(org.apache.hadoop.hbase.coprocessor.protobuf.generated.PingProtos$PingService$BlockingInterface);
    Code:
       0: new           #4                  // class org/apache/hadoop/hbase/coprocessor/protobuf/generated/PingProtos$PingService$2
       3: dup
       4: aload_0
       5: invokespecial #5                  // Method org/apache/hadoop/hbase/coprocessor/protobuf/generated/PingProtos$PingService$2."<init>":(Lorg/apache/hadoop/hbase/coprocessor/protobuf/generated/PingProtos$PingService$BlockingInterface;)V
       8: areturn

  public abstract void ping(com.google.protobuf.RpcController, org.apache.hadoop.hbase.coprocessor.protobuf.generated.PingProtos$PingRequest, com.google.protobuf.RpcCallback<org.apache.hadoop.hbase.coprocessor.protobuf.generated.PingProtos$PingResponse>);

  public abstract void count(com.google.protobuf.RpcController, org.apache.hadoop.hbase.coprocessor.protobuf.generated.PingProtos$CountRequest, com.google.protobuf.RpcCallback<org.apache.hadoop.hbase.coprocessor.protobuf.generated.PingProtos$CountResponse>);

  public abstract void increment(com.google.protobuf.RpcController, org.apache.hadoop.hbase.coprocessor.protobuf.generated.PingProtos$IncrementCountRequest, com.google.protobuf.RpcCallback<org.apache.hadoop.hbase.coprocessor.protobuf.generated.PingProtos$IncrementCountResponse>);

  public abstract void hello(com.google.protobuf.RpcController, org.apache.hadoop.hbase.coprocessor.protobuf.generated.PingProtos$HelloRequest, com.google.protobuf.RpcCallback<org.apache.hadoop.hbase.coprocessor.protobuf.generated.PingProtos$HelloResponse>);

  public abstract void noop(com.google.protobuf.RpcController, org.apache.hadoop.hbase.coprocessor.protobuf.generated.PingProtos$NoopRequest, com.google.protobuf.RpcCallback<org.apache.hadoop.hbase.coprocessor.protobuf.generated.PingProtos$NoopResponse>);

  public static final com.google.protobuf.Descriptors$ServiceDescriptor getDescriptor();
    Code:
       0: invokestatic  #6                  // Method org/apache/hadoop/hbase/coprocessor/protobuf/generated/PingProtos.getDescriptor:()Lcom/google/protobuf/Descriptors$FileDescriptor;
       3: invokevirtual #7                  // Method com/google/protobuf/Descriptors$FileDescriptor.getServices:()Ljava/util/List;
       6: iconst_0
       7: invokeinterface #8,  2            // InterfaceMethod java/util/List.get:(I)Ljava/lang/Object;
      12: checkcast     #9                  // class com/google/protobuf/Descriptors$ServiceDescriptor
      15: areturn

  public final com.google.protobuf.Descriptors$ServiceDescriptor getDescriptorForType();
    Code:
       0: invokestatic  #10                 // Method getDescriptor:()Lcom/google/protobuf/Descriptors$ServiceDescriptor;
       3: areturn

  public final void callMethod(com.google.protobuf.Descriptors$MethodDescriptor, com.google.protobuf.RpcController, com.google.protobuf.Message, com.google.protobuf.RpcCallback<com.google.protobuf.Message>);
    Code:
       0: aload_1
       1: invokevirtual #11                 // Method com/google/protobuf/Descriptors$MethodDescriptor.getService:()Lcom/google/protobuf/Descriptors$ServiceDescriptor;
       4: invokestatic  #10                 // Method getDescriptor:()Lcom/google/protobuf/Descriptors$ServiceDescriptor;
       7: if_acmpeq     20
      10: new           #12                 // class java/lang/IllegalArgumentException
      13: dup
      14: ldc           #13                 // String Service.callMethod() given method descriptor for wrong service type.
      16: invokespecial #14                 // Method java/lang/IllegalArgumentException."<init>":(Ljava/lang/String;)V
      19: athrow
      20: aload_1
      21: invokevirtual #15                 // Method com/google/protobuf/Descriptors$MethodDescriptor.getIndex:()I
      24: tableswitch   { // 0 to 4
                     0: 60
                     1: 75
                     2: 90
                     3: 105
                     4: 120
               default: 135
          }
      60: aload_0
      61: aload_2
      62: aload_3
      63: checkcast     #16                 // class org/apache/hadoop/hbase/coprocessor/protobuf/generated/PingProtos$PingRequest
      66: aload         4
      68: invokestatic  #17                 // Method com/google/protobuf/RpcUtil.specializeCallback:(Lcom/google/protobuf/RpcCallback;)Lcom/google/protobuf/RpcCallback;
      71: invokevirtual #18                 // Method ping:(Lcom/google/protobuf/RpcController;Lorg/apache/hadoop/hbase/coprocessor/protobuf/generated/PingProtos$PingRequest;Lcom/google/protobuf/RpcCallback;)V
      74: return
      75: aload_0
      76: aload_2
      77: aload_3
      78: checkcast     #19                 // class org/apache/hadoop/hbase/coprocessor/protobuf/generated/PingProtos$CountRequest
      81: aload         4
      83: invokestatic  #17                 // Method com/google/protobuf/RpcUtil.specializeCallback:(Lcom/google/protobuf/RpcCallback;)Lcom/google/protobuf/RpcCallback;
      86: invokevirtual #20                 // Method count:(Lcom/google/protobuf/RpcController;Lorg/apache/hadoop/hbase/coprocessor/protobuf/generated/PingProtos$CountRequest;Lcom/google/protobuf/RpcCallback;)V
      89: return
      90: aload_0
      91: aload_2
      92: aload_3
      93: checkcast     #21                 // class org/apache/hadoop/hbase/coprocessor/protobuf/generated/PingProtos$IncrementCountRequest
      96: aload         4
      98: invokestatic  #17                 // Method com/google/protobuf/RpcUtil.specializeCallback:(Lcom/google/protobuf/RpcCallback;)Lcom/google/protobuf/RpcCallback;
     101: invokevirtual #22                 // Method increment:(Lcom/google/protobuf/RpcController;Lorg/apache/hadoop/hbase/coprocessor/protobuf/generated/PingProtos$IncrementCountRequest;Lcom/google/protobuf/RpcCallback;)V
     104: return
     105: aload_0
     106: aload_2
     107: aload_3
     108: checkcast     #23                 // class org/apache/hadoop/hbase/coprocessor/protobuf/generated/PingProtos$HelloRequest
     111: aload         4
     113: invokestatic  #17                 // Method com/google/protobuf/RpcUtil.specializeCallback:(Lcom/google/protobuf/RpcCallback;)Lcom/google/protobuf/RpcCallback;
     116: invokevirtual #24                 // Method hello:(Lcom/google/protobuf/RpcController;Lorg/apache/hadoop/hbase/coprocessor/protobuf/generated/PingProtos$HelloRequest;Lcom/google/protobuf/RpcCallback;)V
     119: return
     120: aload_0
     121: aload_2
     122: aload_3
     123: checkcast     #25                 // class org/apache/hadoop/hbase/coprocessor/protobuf/generated/PingProtos$NoopRequest
     126: aload         4
     128: invokestatic  #17                 // Method com/google/protobuf/RpcUtil.specializeCallback:(Lcom/google/protobuf/RpcCallback;)Lcom/google/protobuf/RpcCallback;
     131: invokevirtual #26                 // Method noop:(Lcom/google/protobuf/RpcController;Lorg/apache/hadoop/hbase/coprocessor/protobuf/generated/PingProtos$NoopRequest;Lcom/google/protobuf/RpcCallback;)V
     134: return
     135: new           #27                 // class java/lang/AssertionError
     138: dup
     139: ldc           #28                 // String Can't get here.
     141: invokespecial #29                 // Method java/lang/AssertionError."<init>":(Ljava/lang/Object;)V
     144: athrow

  public final com.google.protobuf.Message getRequestPrototype(com.google.protobuf.Descriptors$MethodDescriptor);
    Code:
       0: aload_1
       1: invokevirtual #11                 // Method com/google/protobuf/Descriptors$MethodDescriptor.getService:()Lcom/google/protobuf/Descriptors$ServiceDescriptor;
       4: invokestatic  #10                 // Method getDescriptor:()Lcom/google/protobuf/Descriptors$ServiceDescriptor;
       7: if_acmpeq     20
      10: new           #12                 // class java/lang/IllegalArgumentException
      13: dup
      14: ldc           #30                 // String Service.getRequestPrototype() given method descriptor for wrong service type.
      16: invokespecial #14                 // Method java/lang/IllegalArgumentException."<init>":(Ljava/lang/String;)V
      19: athrow
      20: aload_1
      21: invokevirtual #15                 // Method com/google/protobuf/Descriptors$MethodDescriptor.getIndex:()I
      24: tableswitch   { // 0 to 4
                     0: 60
                     1: 64
                     2: 68
                     3: 72
                     4: 76
               default: 80
          }
      60: invokestatic  #31                 // Method org/apache/hadoop/hbase/coprocessor/protobuf/generated/PingProtos$PingRequest.getDefaultInstance:()Lorg/apache/hadoop/hbase/coprocessor/protobuf/generated/PingProtos$PingRequest;
      63: areturn
      64: invokestatic  #32                 // Method org/apache/hadoop/hbase/coprocessor/protobuf/generated/PingProtos$CountRequest.getDefaultInstance:()Lorg/apache/hadoop/hbase/coprocessor/protobuf/generated/PingProtos$CountRequest;
      67: areturn
      68: invokestatic  #33                 // Method org/apache/hadoop/hbase/coprocessor/protobuf/generated/PingProtos$IncrementCountRequest.getDefaultInstance:()Lorg/apache/hadoop/hbase/coprocessor/protobuf/generated/PingProtos$IncrementCountRequest;
      71: areturn
      72: invokestatic  #34                 // Method org/apache/hadoop/hbase/coprocessor/protobuf/generated/PingProtos$HelloRequest.getDefaultInstance:()Lorg/apache/hadoop/hbase/coprocessor/protobuf/generated/PingProtos$HelloRequest;
      75: areturn
      76: invokestatic  #35                 // Method org/apache/hadoop/hbase/coprocessor/protobuf/generated/PingProtos$NoopRequest.getDefaultInstance:()Lorg/apache/hadoop/hbase/coprocessor/protobuf/generated/PingProtos$NoopRequest;
      79: areturn
      80: new           #27                 // class java/lang/AssertionError
      83: dup
      84: ldc           #28                 // String Can't get here.
      86: invokespecial #29                 // Method java/lang/AssertionError."<init>":(Ljava/lang/Object;)V
      89: athrow

  public final com.google.protobuf.Message getResponsePrototype(com.google.protobuf.Descriptors$MethodDescriptor);
    Code:
       0: aload_1
       1: invokevirtual #11                 // Method com/google/protobuf/Descriptors$MethodDescriptor.getService:()Lcom/google/protobuf/Descriptors$ServiceDescriptor;
       4: invokestatic  #10                 // Method getDescriptor:()Lcom/google/protobuf/Descriptors$ServiceDescriptor;
       7: if_acmpeq     20
      10: new           #12                 // class java/lang/IllegalArgumentException
      13: dup
      14: ldc           #36                 // String Service.getResponsePrototype() given method descriptor for wrong service type.
      16: invokespecial #14                 // Method java/lang/IllegalArgumentException."<init>":(Ljava/lang/String;)V
      19: athrow
      20: aload_1
      21: invokevirtual #15                 // Method com/google/protobuf/Descriptors$MethodDescriptor.getIndex:()I
      24: tableswitch   { // 0 to 4
                     0: 60
                     1: 64
                     2: 68
                     3: 72
                     4: 76
               default: 80
          }
      60: invokestatic  #37                 // Method org/apache/hadoop/hbase/coprocessor/protobuf/generated/PingProtos$PingResponse.getDefaultInstance:()Lorg/apache/hadoop/hbase/coprocessor/protobuf/generated/PingProtos$PingResponse;
      63: areturn
      64: invokestatic  #38                 // Method org/apache/hadoop/hbase/coprocessor/protobuf/generated/PingProtos$CountResponse.getDefaultInstance:()Lorg/apache/hadoop/hbase/coprocessor/protobuf/generated/PingProtos$CountResponse;
      67: areturn
      68: invokestatic  #39                 // Method org/apache/hadoop/hbase/coprocessor/protobuf/generated/PingProtos$IncrementCountResponse.getDefaultInstance:()Lorg/apache/hadoop/hbase/coprocessor/protobuf/generated/PingProtos$IncrementCountResponse;
      71: areturn
      72: invokestatic  #40                 // Method org/apache/hadoop/hbase/coprocessor/protobuf/generated/PingProtos$HelloResponse.getDefaultInstance:()Lorg/apache/hadoop/hbase/coprocessor/protobuf/generated/PingProtos$HelloResponse;
      75: areturn
      76: invokestatic  #41                 // Method org/apache/hadoop/hbase/coprocessor/protobuf/generated/PingProtos$NoopResponse.getDefaultInstance:()Lorg/apache/hadoop/hbase/coprocessor/protobuf/generated/PingProtos$NoopResponse;
      79: areturn
      80: new           #27                 // class java/lang/AssertionError
      83: dup
      84: ldc           #28                 // String Can't get here.
      86: invokespecial #29                 // Method java/lang/AssertionError."<init>":(Ljava/lang/Object;)V
      89: athrow

  public static org.apache.hadoop.hbase.coprocessor.protobuf.generated.PingProtos$PingService$Stub newStub(com.google.protobuf.RpcChannel);
    Code:
       0: new           #42                 // class org/apache/hadoop/hbase/coprocessor/protobuf/generated/PingProtos$PingService$Stub
       3: dup
       4: aload_0
       5: aconst_null
       6: invokespecial #43                 // Method org/apache/hadoop/hbase/coprocessor/protobuf/generated/PingProtos$PingService$Stub."<init>":(Lcom/google/protobuf/RpcChannel;Lorg/apache/hadoop/hbase/coprocessor/protobuf/generated/PingProtos$1;)V
       9: areturn

  public static org.apache.hadoop.hbase.coprocessor.protobuf.generated.PingProtos$PingService$BlockingInterface newBlockingStub(com.google.protobuf.BlockingRpcChannel);
    Code:
       0: new           #44                 // class org/apache/hadoop/hbase/coprocessor/protobuf/generated/PingProtos$PingService$BlockingStub
       3: dup
       4: aload_0
       5: aconst_null
       6: invokespecial #45                 // Method org/apache/hadoop/hbase/coprocessor/protobuf/generated/PingProtos$PingService$BlockingStub."<init>":(Lcom/google/protobuf/BlockingRpcChannel;Lorg/apache/hadoop/hbase/coprocessor/protobuf/generated/PingProtos$1;)V
       9: areturn
}
