Compiled from "PressureAwareCompactionThroughputController.java"
class org.apache.hadoop.hbase.regionserver.throttle.PressureAwareCompactionThroughputController$1 extends org.apache.hadoop.hbase.ScheduledChore {
  final org.apache.hadoop.hbase.regionserver.RegionServerServices val$server;

  final org.apache.hadoop.hbase.regionserver.throttle.PressureAwareCompactionThroughputController this$0;

  org.apache.hadoop.hbase.regionserver.throttle.PressureAwareCompactionThroughputController$1(org.apache.hadoop.hbase.regionserver.throttle.PressureAwareCompactionThroughputController, java.lang.String, org.apache.hadoop.hbase.Stoppable, int, org.apache.hadoop.hbase.regionserver.RegionServerServices);
    Code:
       0: aload_0
       1: aload_1
       2: putfield      #1                  // Field this$0:Lorg/apache/hadoop/hbase/regionserver/throttle/PressureAwareCompactionThroughputController;
       5: aload_0
       6: aload         5
       8: putfield      #2                  // Field val$server:Lorg/apache/hadoop/hbase/regionserver/RegionServerServices;
      11: aload_0
      12: aload_2
      13: aload_3
      14: iload         4
      16: invokespecial #3                  // Method org/apache/hadoop/hbase/ScheduledChore."<init>":(Ljava/lang/String;Lorg/apache/hadoop/hbase/Stoppable;I)V
      19: return

  protected void chore();
    Code:
       0: aload_0
       1: getfield      #1                  // Field this$0:Lorg/apache/hadoop/hbase/regionserver/throttle/PressureAwareCompactionThroughputController;
       4: aload_0
       5: getfield      #2                  // Field val$server:Lorg/apache/hadoop/hbase/regionserver/RegionServerServices;
       8: invokeinterface #4,  1            // InterfaceMethod org/apache/hadoop/hbase/regionserver/RegionServerServices.getCompactionPressure:()D
      13: invokestatic  #5                  // Method org/apache/hadoop/hbase/regionserver/throttle/PressureAwareCompactionThroughputController.access$000:(Lorg/apache/hadoop/hbase/regionserver/throttle/PressureAwareCompactionThroughputController;D)V
      16: return
}
