Compiled from "PressureAwareThroughputController.java"
public abstract class org.apache.hadoop.hbase.regionserver.throttle.PressureAwareThroughputController extends org.apache.hadoop.conf.Configured implements org.apache.hadoop.hbase.regionserver.throttle.ThroughputController,org.apache.hadoop.hbase.Stoppable {
  protected long maxThroughputUpperBound;

  protected long maxThroughputLowerBound;

  protected org.apache.hadoop.hbase.regionserver.compactions.OffPeakHours offPeakHours;

  protected long controlPerSize;

  protected int tuningPeriod;

  protected final java.util.concurrent.ConcurrentMap<java.lang.String, org.apache.hadoop.hbase.regionserver.throttle.PressureAwareThroughputController$ActiveOperation> activeOperations;

  public org.apache.hadoop.hbase.regionserver.throttle.PressureAwareThroughputController();
    Code:
       0: aload_0
       1: invokespecial #1                  // Method org/apache/hadoop/conf/Configured."<init>":()V
       4: aload_0
       5: new           #2                  // class java/util/concurrent/ConcurrentHashMap
       8: dup
       9: invokespecial #3                  // Method java/util/concurrent/ConcurrentHashMap."<init>":()V
      12: putfield      #4                  // Field activeOperations:Ljava/util/concurrent/ConcurrentMap;
      15: aload_0
      16: iconst_0
      17: putfield      #5                  // Field stopped:Z
      20: return

  public abstract void setup(org.apache.hadoop.hbase.regionserver.RegionServerServices);

  protected java.lang.String throughputDesc(long, long);
    Code:
       0: aload_0
       1: lload_1
       2: l2d
       3: lload_3
       4: l2d
       5: ddiv
       6: ldc2_w        #6                  // double 1000.0d
       9: dmul
      10: invokevirtual #8                  // Method throughputDesc:(D)Ljava/lang/String;
      13: areturn

  protected java.lang.String throughputDesc(double);
    Code:
       0: dload_1
       1: ldc2_w        #9                  // double 1.0E15d
       4: dcmpl
       5: iflt          11
       8: ldc           #11                 // String unlimited
      10: areturn
      11: ldc           #12                 // String %.2f MB/second
      13: iconst_1
      14: anewarray     #13                 // class java/lang/Object
      17: dup
      18: iconst_0
      19: dload_1
      20: ldc2_w        #14                 // double 1024.0d
      23: ddiv
      24: ldc2_w        #14                 // double 1024.0d
      27: ddiv
      28: invokestatic  #16                 // Method java/lang/Double.valueOf:(D)Ljava/lang/Double;
      31: aastore
      32: invokestatic  #17                 // Method java/lang/String.format:(Ljava/lang/String;[Ljava/lang/Object;)Ljava/lang/String;
      35: areturn

  public void start(java.lang.String);
    Code:
       0: aload_0
       1: getfield      #4                  // Field activeOperations:Ljava/util/concurrent/ConcurrentMap;
       4: aload_1
       5: new           #18                 // class org/apache/hadoop/hbase/regionserver/throttle/PressureAwareThroughputController$ActiveOperation
       8: dup
       9: invokespecial #19                 // Method org/apache/hadoop/hbase/regionserver/throttle/PressureAwareThroughputController$ActiveOperation."<init>":()V
      12: invokeinterface #20,  3           // InterfaceMethod java/util/concurrent/ConcurrentMap.put:(Ljava/lang/Object;Ljava/lang/Object;)Ljava/lang/Object;
      17: pop
      18: aload_0
      19: aload_0
      20: invokevirtual #21                 // Method getMaxThroughput:()D
      23: aload_0
      24: getfield      #4                  // Field activeOperations:Ljava/util/concurrent/ConcurrentMap;
      27: invokeinterface #22,  1           // InterfaceMethod java/util/concurrent/ConcurrentMap.size:()I
      32: i2d
      33: ddiv
      34: putfield      #23                 // Field maxThroughputPerOperation:D
      37: return

  public long control(java.lang.String, long) throws java.lang.InterruptedException;
    Code:
       0: aload_0
       1: getfield      #4                  // Field activeOperations:Ljava/util/concurrent/ConcurrentMap;
       4: aload_1
       5: invokeinterface #24,  2           // InterfaceMethod java/util/concurrent/ConcurrentMap.get:(Ljava/lang/Object;)Ljava/lang/Object;
      10: checkcast     #18                 // class org/apache/hadoop/hbase/regionserver/throttle/PressureAwareThroughputController$ActiveOperation
      13: astore        4
      15: aload         4
      17: astore        5
      19: aload         5
      21: aload         5
      23: invokestatic  #25                 // Method org/apache/hadoop/hbase/regionserver/throttle/PressureAwareThroughputController$ActiveOperation.access$000:(Lorg/apache/hadoop/hbase/regionserver/throttle/PressureAwareThroughputController$ActiveOperation;)J
      26: lload_2
      27: ladd
      28: invokestatic  #26                 // Method org/apache/hadoop/hbase/regionserver/throttle/PressureAwareThroughputController$ActiveOperation.access$002:(Lorg/apache/hadoop/hbase/regionserver/throttle/PressureAwareThroughputController$ActiveOperation;J)J
      31: pop2
      32: aload         4
      34: invokestatic  #25                 // Method org/apache/hadoop/hbase/regionserver/throttle/PressureAwareThroughputController$ActiveOperation.access$000:(Lorg/apache/hadoop/hbase/regionserver/throttle/PressureAwareThroughputController$ActiveOperation;)J
      37: aload         4
      39: invokestatic  #27                 // Method org/apache/hadoop/hbase/regionserver/throttle/PressureAwareThroughputController$ActiveOperation.access$100:(Lorg/apache/hadoop/hbase/regionserver/throttle/PressureAwareThroughputController$ActiveOperation;)J
      42: lsub
      43: lstore        5
      45: lload         5
      47: aload_0
      48: getfield      #28                 // Field controlPerSize:J
      51: lcmp
      52: ifge          57
      55: lconst_0
      56: lreturn
      57: invokestatic  #29                 // Method org/apache/hadoop/hbase/util/EnvironmentEdgeManager.currentTime:()J
      60: lstore        7
      62: lload         5
      64: l2d
      65: aload_0
      66: getfield      #23                 // Field maxThroughputPerOperation:D
      69: ddiv
      70: ldc2_w        #6                  // double 1000.0d
      73: dmul
      74: d2l
      75: lstore        9
      77: lload         7
      79: aload         4
      81: invokestatic  #30                 // Method org/apache/hadoop/hbase/regionserver/throttle/PressureAwareThroughputController$ActiveOperation.access$200:(Lorg/apache/hadoop/hbase/regionserver/throttle/PressureAwareThroughputController$ActiveOperation;)J
      84: lsub
      85: lstore        11
      87: aload         4
      89: aload         4
      91: invokestatic  #25                 // Method org/apache/hadoop/hbase/regionserver/throttle/PressureAwareThroughputController$ActiveOperation.access$000:(Lorg/apache/hadoop/hbase/regionserver/throttle/PressureAwareThroughputController$ActiveOperation;)J
      94: invokestatic  #31                 // Method org/apache/hadoop/hbase/regionserver/throttle/PressureAwareThroughputController$ActiveOperation.access$102:(Lorg/apache/hadoop/hbase/regionserver/throttle/PressureAwareThroughputController$ActiveOperation;J)J
      97: pop2
      98: lload         11
     100: lload         9
     102: lcmp
     103: iflt          117
     106: aload         4
     108: invokestatic  #29                 // Method org/apache/hadoop/hbase/util/EnvironmentEdgeManager.currentTime:()J
     111: invokestatic  #32                 // Method org/apache/hadoop/hbase/regionserver/throttle/PressureAwareThroughputController$ActiveOperation.access$202:(Lorg/apache/hadoop/hbase/regionserver/throttle/PressureAwareThroughputController$ActiveOperation;J)J
     114: pop2
     115: lconst_0
     116: lreturn
     117: lload         9
     119: lload         11
     121: lsub
     122: lstore        13
     124: getstatic     #33                 // Field LOG:Lorg/slf4j/Logger;
     127: invokeinterface #34,  1           // InterfaceMethod org/slf4j/Logger.isDebugEnabled:()Z
     132: ifeq          296
     135: lload         7
     137: aload         4
     139: invokestatic  #35                 // Method org/apache/hadoop/hbase/regionserver/throttle/PressureAwareThroughputController$ActiveOperation.access$300:(Lorg/apache/hadoop/hbase/regionserver/throttle/PressureAwareThroughputController$ActiveOperation;)J
     142: lsub
     143: ldc2_w        #36                 // long 5000l
     146: lcmp
     147: ifle          296
     150: getstatic     #33                 // Field LOG:Lorg/slf4j/Logger;
     153: new           #38                 // class java/lang/StringBuilder
     156: dup
     157: invokespecial #39                 // Method java/lang/StringBuilder."<init>":()V
     160: ldc           #40                 // String deltaSize:
     162: invokevirtual #41                 // Method java/lang/StringBuilder.append:(Ljava/lang/String;)Ljava/lang/StringBuilder;
     165: lload         5
     167: invokevirtual #42                 // Method java/lang/StringBuilder.append:(J)Ljava/lang/StringBuilder;
     170: ldc           #43                 // String  bytes; elapseTime:
     172: invokevirtual #41                 // Method java/lang/StringBuilder.append:(Ljava/lang/String;)Ljava/lang/StringBuilder;
     175: lload         11
     177: invokevirtual #42                 // Method java/lang/StringBuilder.append:(J)Ljava/lang/StringBuilder;
     180: ldc           #44                 // String  ns
     182: invokevirtual #41                 // Method java/lang/StringBuilder.append:(Ljava/lang/String;)Ljava/lang/StringBuilder;
     185: invokevirtual #45                 // Method java/lang/StringBuilder.toString:()Ljava/lang/String;
     188: invokeinterface #46,  2           // InterfaceMethod org/slf4j/Logger.debug:(Ljava/lang/String;)V
     193: getstatic     #33                 // Field LOG:Lorg/slf4j/Logger;
     196: new           #38                 // class java/lang/StringBuilder
     199: dup
     200: invokespecial #39                 // Method java/lang/StringBuilder."<init>":()V
     203: aload_1
     204: invokevirtual #41                 // Method java/lang/StringBuilder.append:(Ljava/lang/String;)Ljava/lang/StringBuilder;
     207: ldc           #47                 // String  sleep=
     209: invokevirtual #41                 // Method java/lang/StringBuilder.append:(Ljava/lang/String;)Ljava/lang/StringBuilder;
     212: lload         13
     214: invokevirtual #42                 // Method java/lang/StringBuilder.append:(J)Ljava/lang/StringBuilder;
     217: ldc           #48                 // String ms because current throughput is
     219: invokevirtual #41                 // Method java/lang/StringBuilder.append:(Ljava/lang/String;)Ljava/lang/StringBuilder;
     222: aload_0
     223: lload         5
     225: lload         11
     227: invokevirtual #49                 // Method throughputDesc:(JJ)Ljava/lang/String;
     230: invokevirtual #41                 // Method java/lang/StringBuilder.append:(Ljava/lang/String;)Ljava/lang/StringBuilder;
     233: ldc           #50                 // String , max allowed is
     235: invokevirtual #41                 // Method java/lang/StringBuilder.append:(Ljava/lang/String;)Ljava/lang/StringBuilder;
     238: aload_0
     239: aload_0
     240: getfield      #23                 // Field maxThroughputPerOperation:D
     243: invokevirtual #8                  // Method throughputDesc:(D)Ljava/lang/String;
     246: invokevirtual #41                 // Method java/lang/StringBuilder.append:(Ljava/lang/String;)Ljava/lang/StringBuilder;
     249: ldc           #51                 // String , already slept
     251: invokevirtual #41                 // Method java/lang/StringBuilder.append:(Ljava/lang/String;)Ljava/lang/StringBuilder;
     254: aload         4
     256: invokestatic  #52                 // Method org/apache/hadoop/hbase/regionserver/throttle/PressureAwareThroughputController$ActiveOperation.access$400:(Lorg/apache/hadoop/hbase/regionserver/throttle/PressureAwareThroughputController$ActiveOperation;)J
     259: invokevirtual #42                 // Method java/lang/StringBuilder.append:(J)Ljava/lang/StringBuilder;
     262: ldc           #53                 // String  time(s) and total slept time is
     264: invokevirtual #41                 // Method java/lang/StringBuilder.append:(Ljava/lang/String;)Ljava/lang/StringBuilder;
     267: aload         4
     269: invokestatic  #54                 // Method org/apache/hadoop/hbase/regionserver/throttle/PressureAwareThroughputController$ActiveOperation.access$500:(Lorg/apache/hadoop/hbase/regionserver/throttle/PressureAwareThroughputController$ActiveOperation;)J
     272: invokevirtual #42                 // Method java/lang/StringBuilder.append:(J)Ljava/lang/StringBuilder;
     275: ldc           #55                 // String  ms till now.
     277: invokevirtual #41                 // Method java/lang/StringBuilder.append:(Ljava/lang/String;)Ljava/lang/StringBuilder;
     280: invokevirtual #45                 // Method java/lang/StringBuilder.toString:()Ljava/lang/String;
     283: invokeinterface #46,  2           // InterfaceMethod org/slf4j/Logger.debug:(Ljava/lang/String;)V
     288: aload         4
     290: lload         7
     292: invokestatic  #56                 // Method org/apache/hadoop/hbase/regionserver/throttle/PressureAwareThroughputController$ActiveOperation.access$302:(Lorg/apache/hadoop/hbase/regionserver/throttle/PressureAwareThroughputController$ActiveOperation;J)J
     295: pop2
     296: lload         13
     298: invokestatic  #57                 // Method java/lang/Thread.sleep:(J)V
     301: aload         4
     303: invokestatic  #58                 // Method org/apache/hadoop/hbase/regionserver/throttle/PressureAwareThroughputController$ActiveOperation.access$408:(Lorg/apache/hadoop/hbase/regionserver/throttle/PressureAwareThroughputController$ActiveOperation;)J
     306: pop2
     307: aload         4
     309: astore        15
     311: aload         15
     313: aload         15
     315: invokestatic  #54                 // Method org/apache/hadoop/hbase/regionserver/throttle/PressureAwareThroughputController$ActiveOperation.access$500:(Lorg/apache/hadoop/hbase/regionserver/throttle/PressureAwareThroughputController$ActiveOperation;)J
     318: lload         13
     320: ladd
     321: invokestatic  #59                 // Method org/apache/hadoop/hbase/regionserver/throttle/PressureAwareThroughputController$ActiveOperation.access$502:(Lorg/apache/hadoop/hbase/regionserver/throttle/PressureAwareThroughputController$ActiveOperation;J)J
     324: pop2
     325: aload         4
     327: invokestatic  #29                 // Method org/apache/hadoop/hbase/util/EnvironmentEdgeManager.currentTime:()J
     330: invokestatic  #32                 // Method org/apache/hadoop/hbase/regionserver/throttle/PressureAwareThroughputController$ActiveOperation.access$202:(Lorg/apache/hadoop/hbase/regionserver/throttle/PressureAwareThroughputController$ActiveOperation;J)J
     333: pop2
     334: lload         13
     336: lreturn

  protected abstract boolean skipControl(long, long);

  public void finish(java.lang.String);
    Code:
       0: aload_0
       1: getfield      #4                  // Field activeOperations:Ljava/util/concurrent/ConcurrentMap;
       4: aload_1
       5: invokeinterface #60,  2           // InterfaceMethod java/util/concurrent/ConcurrentMap.remove:(Ljava/lang/Object;)Ljava/lang/Object;
      10: checkcast     #18                 // class org/apache/hadoop/hbase/regionserver/throttle/PressureAwareThroughputController$ActiveOperation
      13: astore_2
      14: aload_0
      15: aload_0
      16: invokevirtual #21                 // Method getMaxThroughput:()D
      19: aload_0
      20: getfield      #4                  // Field activeOperations:Ljava/util/concurrent/ConcurrentMap;
      23: invokeinterface #22,  1           // InterfaceMethod java/util/concurrent/ConcurrentMap.size:()I
      28: i2d
      29: ddiv
      30: putfield      #23                 // Field maxThroughputPerOperation:D
      33: invokestatic  #29                 // Method org/apache/hadoop/hbase/util/EnvironmentEdgeManager.currentTime:()J
      36: aload_2
      37: invokestatic  #61                 // Method org/apache/hadoop/hbase/regionserver/throttle/PressureAwareThroughputController$ActiveOperation.access$600:(Lorg/apache/hadoop/hbase/regionserver/throttle/PressureAwareThroughputController$ActiveOperation;)J
      40: lsub
      41: lstore_3
      42: getstatic     #33                 // Field LOG:Lorg/slf4j/Logger;
      45: new           #38                 // class java/lang/StringBuilder
      48: dup
      49: invokespecial #39                 // Method java/lang/StringBuilder."<init>":()V
      52: aload_1
      53: invokevirtual #41                 // Method java/lang/StringBuilder.append:(Ljava/lang/String;)Ljava/lang/StringBuilder;
      56: ldc           #62                 // String  average throughput is
      58: invokevirtual #41                 // Method java/lang/StringBuilder.append:(Ljava/lang/String;)Ljava/lang/StringBuilder;
      61: aload_0
      62: aload_2
      63: invokestatic  #25                 // Method org/apache/hadoop/hbase/regionserver/throttle/PressureAwareThroughputController$ActiveOperation.access$000:(Lorg/apache/hadoop/hbase/regionserver/throttle/PressureAwareThroughputController$ActiveOperation;)J
      66: lload_3
      67: invokevirtual #49                 // Method throughputDesc:(JJ)Ljava/lang/String;
      70: invokevirtual #41                 // Method java/lang/StringBuilder.append:(Ljava/lang/String;)Ljava/lang/StringBuilder;
      73: ldc           #63                 // String , slept
      75: invokevirtual #41                 // Method java/lang/StringBuilder.append:(Ljava/lang/String;)Ljava/lang/StringBuilder;
      78: aload_2
      79: invokestatic  #52                 // Method org/apache/hadoop/hbase/regionserver/throttle/PressureAwareThroughputController$ActiveOperation.access$400:(Lorg/apache/hadoop/hbase/regionserver/throttle/PressureAwareThroughputController$ActiveOperation;)J
      82: invokevirtual #42                 // Method java/lang/StringBuilder.append:(J)Ljava/lang/StringBuilder;
      85: ldc           #53                 // String  time(s) and total slept time is
      87: invokevirtual #41                 // Method java/lang/StringBuilder.append:(Ljava/lang/String;)Ljava/lang/StringBuilder;
      90: aload_2
      91: invokestatic  #54                 // Method org/apache/hadoop/hbase/regionserver/throttle/PressureAwareThroughputController$ActiveOperation.access$500:(Lorg/apache/hadoop/hbase/regionserver/throttle/PressureAwareThroughputController$ActiveOperation;)J
      94: invokevirtual #42                 // Method java/lang/StringBuilder.append:(J)Ljava/lang/StringBuilder;
      97: ldc           #64                 // String  ms.
      99: invokevirtual #41                 // Method java/lang/StringBuilder.append:(Ljava/lang/String;)Ljava/lang/StringBuilder;
     102: aload_0
     103: getfield      #4                  // Field activeOperations:Ljava/util/concurrent/ConcurrentMap;
     106: invokeinterface #22,  1           // InterfaceMethod java/util/concurrent/ConcurrentMap.size:()I
     111: invokevirtual #65                 // Method java/lang/StringBuilder.append:(I)Ljava/lang/StringBuilder;
     114: ldc           #66                 // String  active operations remaining, total limit is
     116: invokevirtual #41                 // Method java/lang/StringBuilder.append:(Ljava/lang/String;)Ljava/lang/StringBuilder;
     119: aload_0
     120: aload_0
     121: invokevirtual #21                 // Method getMaxThroughput:()D
     124: invokevirtual #8                  // Method throughputDesc:(D)Ljava/lang/String;
     127: invokevirtual #41                 // Method java/lang/StringBuilder.append:(Ljava/lang/String;)Ljava/lang/StringBuilder;
     130: invokevirtual #45                 // Method java/lang/StringBuilder.toString:()Ljava/lang/String;
     133: invokeinterface #67,  2           // InterfaceMethod org/slf4j/Logger.info:(Ljava/lang/String;)V
     138: return

  public void stop(java.lang.String);
    Code:
       0: aload_0
       1: iconst_1
       2: putfield      #5                  // Field stopped:Z
       5: return

  public boolean isStopped();
    Code:
       0: aload_0
       1: getfield      #5                  // Field stopped:Z
       4: ireturn

  public double getMaxThroughput();
    Code:
       0: aload_0
       1: getfield      #68                 // Field maxThroughput:D
       4: dreturn

  public void setMaxThroughput(double);
    Code:
       0: aload_0
       1: dload_1
       2: putfield      #68                 // Field maxThroughput:D
       5: aload_0
       6: aload_0
       7: invokevirtual #21                 // Method getMaxThroughput:()D
      10: aload_0
      11: getfield      #4                  // Field activeOperations:Ljava/util/concurrent/ConcurrentMap;
      14: invokeinterface #22,  1           // InterfaceMethod java/util/concurrent/ConcurrentMap.size:()I
      19: i2d
      20: ddiv
      21: putfield      #23                 // Field maxThroughputPerOperation:D
      24: return

  static {};
    Code:
       0: ldc           #69                 // class org/apache/hadoop/hbase/regionserver/throttle/PressureAwareThroughputController
       2: invokestatic  #70                 // Method org/slf4j/LoggerFactory.getLogger:(Ljava/lang/Class;)Lorg/slf4j/Logger;
       5: putstatic     #33                 // Field LOG:Lorg/slf4j/Logger;
       8: return
}
