Compiled from "PrivateCellUtil.java"
class org.apache.hadoop.hbase.PrivateCellUtil$LastOnRowByteBufferExtendedCell extends org.apache.hadoop.hbase.PrivateCellUtil$EmptyByteBufferExtendedCell {
  public org.apache.hadoop.hbase.PrivateCellUtil$LastOnRowByteBufferExtendedCell(java.nio.ByteBuffer, int, short);
    Code:
       0: aload_0
       1: aconst_null
       2: invokespecial #2                  // Method org/apache/hadoop/hbase/PrivateCellUtil$EmptyByteBufferExtendedCell."<init>":(Lorg/apache/hadoop/hbase/PrivateCellUtil$1;)V
       5: aload_0
       6: aload_1
       7: putfield      #3                  // Field rowBuff:Ljava/nio/ByteBuffer;
      10: aload_0
      11: iload_2
      12: putfield      #4                  // Field roffset:I
      15: aload_0
      16: iload_3
      17: putfield      #5                  // Field rlength:S
      20: return

  public long heapSize();
    Code:
       0: aload_0
       1: getfield      #3                  // Field rowBuff:Ljava/nio/ByteBuffer;
       4: invokevirtual #6                  // Method java/nio/ByteBuffer.hasArray:()Z
       7: ifeq          23
      10: getstatic     #1                  // Field FIXED_OVERHEAD:I
      13: aload_0
      14: getfield      #5                  // Field rlength:S
      17: iadd
      18: invokestatic  #7                  // Method org/apache/hadoop/hbase/util/ClassSize.align:(I)I
      21: i2l
      22: lreturn
      23: getstatic     #1                  // Field FIXED_OVERHEAD:I
      26: invokestatic  #7                  // Method org/apache/hadoop/hbase/util/ClassSize.align:(I)I
      29: i2l
      30: lreturn

  public java.nio.ByteBuffer getRowByteBuffer();
    Code:
       0: aload_0
       1: getfield      #3                  // Field rowBuff:Ljava/nio/ByteBuffer;
       4: areturn

  public int getRowPosition();
    Code:
       0: aload_0
       1: getfield      #4                  // Field roffset:I
       4: ireturn

  public short getRowLength();
    Code:
       0: aload_0
       1: getfield      #5                  // Field rlength:S
       4: ireturn

  public long getTimestamp();
    Code:
       0: ldc2_w        #9                  // long -9223372036854775808l
       3: lreturn

  public byte getTypeByte();
    Code:
       0: getstatic     #11                 // Field org/apache/hadoop/hbase/KeyValue$Type.Minimum:Lorg/apache/hadoop/hbase/KeyValue$Type;
       3: invokevirtual #12                 // Method org/apache/hadoop/hbase/KeyValue$Type.getCode:()B
       6: ireturn

  public org.apache.hadoop.hbase.Cell$Type getType();
    Code:
       0: new           #13                 // class java/lang/UnsupportedOperationException
       3: dup
       4: invokespecial #14                 // Method java/lang/UnsupportedOperationException."<init>":()V
       7: athrow

  static int access$700();
    Code:
       0: getstatic     #1                  // Field FIXED_OVERHEAD:I
       3: ireturn

  static {};
    Code:
       0: getstatic     #15                 // Field org/apache/hadoop/hbase/util/ClassSize.OBJECT:I
       3: getstatic     #16                 // Field org/apache/hadoop/hbase/util/ClassSize.REFERENCE:I
       6: iadd
       7: iconst_4
       8: iadd
       9: iconst_2
      10: iadd
      11: putstatic     #1                  // Field FIXED_OVERHEAD:I
      14: return
}
