Compiled from "procedures_jsp.java"
class org.apache.hadoop.hbase.generated.master.procedures_jsp$1 implements java.util.Comparator<org.apache.hadoop.hbase.procedure2.Procedure> {
  final org.apache.hadoop.hbase.generated.master.procedures_jsp this$0;

  org.apache.hadoop.hbase.generated.master.procedures_jsp$1(org.apache.hadoop.hbase.generated.master.procedures_jsp);
    Code:
       0: aload_0
       1: aload_1
       2: putfield      #1                  // Field this$0:Lorg/apache/hadoop/hbase/generated/master/procedures_jsp;
       5: aload_0
       6: invokespecial #2                  // Method java/lang/Object."<init>":()V
       9: return

  public int compare(org.apache.hadoop.hbase.procedure2.Procedure, org.apache.hadoop.hbase.procedure2.Procedure);
    Code:
       0: aload_1
       1: invokevirtual #3                  // Method org/apache/hadoop/hbase/procedure2/Procedure.getParentProcId:()J
       4: aload_2
       5: invokevirtual #3                  // Method org/apache/hadoop/hbase/procedure2/Procedure.getParentProcId:()J
       8: lsub
       9: lstore_3
      10: lload_3
      11: lconst_0
      12: lcmp
      13: ifeq          20
      16: lload_3
      17: goto          29
      20: aload_1
      21: invokevirtual #4                  // Method org/apache/hadoop/hbase/procedure2/Procedure.getProcId:()J
      24: aload_2
      25: invokevirtual #4                  // Method org/apache/hadoop/hbase/procedure2/Procedure.getProcId:()J
      28: lsub
      29: lstore_3
      30: lload_3
      31: lconst_0
      32: lcmp
      33: ifge          40
      36: iconst_m1
      37: goto          51
      40: lload_3
      41: lconst_0
      42: lcmp
      43: ifle          50
      46: iconst_1
      47: goto          51
      50: iconst_0
      51: ireturn

  public int compare(java.lang.Object, java.lang.Object);
    Code:
       0: aload_0
       1: aload_1
       2: checkcast     #5                  // class org/apache/hadoop/hbase/procedure2/Procedure
       5: aload_2
       6: checkcast     #5                  // class org/apache/hadoop/hbase/procedure2/Procedure
       9: invokevirtual #6                  // Method compare:(Lorg/apache/hadoop/hbase/procedure2/Procedure;Lorg/apache/hadoop/hbase/procedure2/Procedure;)I
      12: ireturn
}
