Compiled from "Procedure.java"
public final class org.apache.hadoop.hbase.procedure2.Procedure$LockState extends java.lang.Enum<org.apache.hadoop.hbase.procedure2.Procedure$LockState> {
  public static final org.apache.hadoop.hbase.procedure2.Procedure$LockState LOCK_ACQUIRED;

  public static final org.apache.hadoop.hbase.procedure2.Procedure$LockState LOCK_YIELD_WAIT;

  public static final org.apache.hadoop.hbase.procedure2.Procedure$LockState LOCK_EVENT_WAIT;

  public static org.apache.hadoop.hbase.procedure2.Procedure$LockState[] values();
    Code:
       0: getstatic     #1                  // Field $VALUES:[Lorg/apache/hadoop/hbase/procedure2/Procedure$LockState;
       3: invokevirtual #2                  // Method "[Lorg/apache/hadoop/hbase/procedure2/Procedure$LockState;".clone:()Ljava/lang/Object;
       6: checkcast     #3                  // class "[Lorg/apache/hadoop/hbase/procedure2/Procedure$LockState;"
       9: areturn

  public static org.apache.hadoop.hbase.procedure2.Procedure$LockState valueOf(java.lang.String);
    Code:
       0: ldc           #4                  // class org/apache/hadoop/hbase/procedure2/Procedure$LockState
       2: aload_0
       3: invokestatic  #5                  // Method java/lang/Enum.valueOf:(Ljava/lang/Class;Ljava/lang/String;)Ljava/lang/Enum;
       6: checkcast     #4                  // class org/apache/hadoop/hbase/procedure2/Procedure$LockState
       9: areturn

  static {};
    Code:
       0: new           #4                  // class org/apache/hadoop/hbase/procedure2/Procedure$LockState
       3: dup
       4: ldc           #7                  // String LOCK_ACQUIRED
       6: iconst_0
       7: invokespecial #8                  // Method "<init>":(Ljava/lang/String;I)V
      10: putstatic     #9                  // Field LOCK_ACQUIRED:Lorg/apache/hadoop/hbase/procedure2/Procedure$LockState;
      13: new           #4                  // class org/apache/hadoop/hbase/procedure2/Procedure$LockState
      16: dup
      17: ldc           #10                 // String LOCK_YIELD_WAIT
      19: iconst_1
      20: invokespecial #8                  // Method "<init>":(Ljava/lang/String;I)V
      23: putstatic     #11                 // Field LOCK_YIELD_WAIT:Lorg/apache/hadoop/hbase/procedure2/Procedure$LockState;
      26: new           #4                  // class org/apache/hadoop/hbase/procedure2/Procedure$LockState
      29: dup
      30: ldc           #12                 // String LOCK_EVENT_WAIT
      32: iconst_2
      33: invokespecial #8                  // Method "<init>":(Ljava/lang/String;I)V
      36: putstatic     #13                 // Field LOCK_EVENT_WAIT:Lorg/apache/hadoop/hbase/procedure2/Procedure$LockState;
      39: iconst_3
      40: anewarray     #4                  // class org/apache/hadoop/hbase/procedure2/Procedure$LockState
      43: dup
      44: iconst_0
      45: getstatic     #9                  // Field LOCK_ACQUIRED:Lorg/apache/hadoop/hbase/procedure2/Procedure$LockState;
      48: aastore
      49: dup
      50: iconst_1
      51: getstatic     #11                 // Field LOCK_YIELD_WAIT:Lorg/apache/hadoop/hbase/procedure2/Procedure$LockState;
      54: aastore
      55: dup
      56: iconst_2
      57: getstatic     #13                 // Field LOCK_EVENT_WAIT:Lorg/apache/hadoop/hbase/procedure2/Procedure$LockState;
      60: aastore
      61: putstatic     #1                  // Field $VALUES:[Lorg/apache/hadoop/hbase/procedure2/Procedure$LockState;
      64: return
}
