Compiled from "ProcedureSyncWait.java"
class org.apache.hadoop.hbase.master.procedure.ProcedureSyncWait$ProcedureFuture implements java.util.concurrent.Future<byte[]> {
  public org.apache.hadoop.hbase.master.procedure.ProcedureSyncWait$ProcedureFuture(org.apache.hadoop.hbase.procedure2.ProcedureExecutor<org.apache.hadoop.hbase.master.procedure.MasterProcedureEnv>, org.apache.hadoop.hbase.procedure2.Procedure<?>);
    Code:
       0: aload_0
       1: invokespecial #1                  // Method java/lang/Object."<init>":()V
       4: aload_0
       5: iconst_0
       6: putfield      #2                  // Field hasResult:Z
       9: aload_0
      10: aconst_null
      11: putfield      #3                  // Field result:[B
      14: aload_0
      15: aload_1
      16: putfield      #4                  // Field procExec:Lorg/apache/hadoop/hbase/procedure2/ProcedureExecutor;
      19: aload_0
      20: aload_2
      21: putfield      #5                  // Field proc:Lorg/apache/hadoop/hbase/procedure2/Procedure;
      24: return

  public boolean cancel(boolean);
    Code:
       0: iconst_0
       1: ireturn

  public boolean isCancelled();
    Code:
       0: iconst_0
       1: ireturn

  public boolean isDone();
    Code:
       0: aload_0
       1: getfield      #2                  // Field hasResult:Z
       4: ireturn

  public byte[] get() throws java.lang.InterruptedException, java.util.concurrent.ExecutionException;
    Code:
       0: aload_0
       1: getfield      #2                  // Field hasResult:Z
       4: ifeq          12
       7: aload_0
       8: getfield      #3                  // Field result:[B
      11: areturn
      12: aload_0
      13: getfield      #4                  // Field procExec:Lorg/apache/hadoop/hbase/procedure2/ProcedureExecutor;
      16: aload_0
      17: getfield      #5                  // Field proc:Lorg/apache/hadoop/hbase/procedure2/Procedure;
      20: ldc2_w        #7                  // long 9223372036854775807l
      23: invokestatic  #9                  // Method org/apache/hadoop/hbase/master/procedure/ProcedureSyncWait.waitForProcedureToComplete:(Lorg/apache/hadoop/hbase/procedure2/ProcedureExecutor;Lorg/apache/hadoop/hbase/procedure2/Procedure;J)[B
      26: areturn
      27: astore_1
      28: new           #11                 // class java/util/concurrent/ExecutionException
      31: dup
      32: aload_1
      33: invokespecial #12                 // Method java/util/concurrent/ExecutionException."<init>":(Ljava/lang/Throwable;)V
      36: athrow
    Exception table:
       from    to  target type
          12    26    27   Class java/lang/Exception

  public byte[] get(long, java.util.concurrent.TimeUnit) throws java.lang.InterruptedException, java.util.concurrent.ExecutionException, java.util.concurrent.TimeoutException;
    Code:
       0: aload_0
       1: getfield      #2                  // Field hasResult:Z
       4: ifeq          12
       7: aload_0
       8: getfield      #3                  // Field result:[B
      11: areturn
      12: aload_0
      13: aload_0
      14: getfield      #4                  // Field procExec:Lorg/apache/hadoop/hbase/procedure2/ProcedureExecutor;
      17: aload_0
      18: getfield      #5                  // Field proc:Lorg/apache/hadoop/hbase/procedure2/Procedure;
      21: aload_3
      22: lload_1
      23: invokevirtual #13                 // Method java/util/concurrent/TimeUnit.toMillis:(J)J
      26: invokestatic  #9                  // Method org/apache/hadoop/hbase/master/procedure/ProcedureSyncWait.waitForProcedureToComplete:(Lorg/apache/hadoop/hbase/procedure2/ProcedureExecutor;Lorg/apache/hadoop/hbase/procedure2/Procedure;J)[B
      29: putfield      #3                  // Field result:[B
      32: aload_0
      33: iconst_1
      34: putfield      #2                  // Field hasResult:Z
      37: aload_0
      38: getfield      #3                  // Field result:[B
      41: areturn
      42: astore        4
      44: new           #15                 // class java/util/concurrent/TimeoutException
      47: dup
      48: aload         4
      50: invokevirtual #16                 // Method org/apache/hadoop/hbase/exceptions/TimeoutIOException.getMessage:()Ljava/lang/String;
      53: invokespecial #17                 // Method java/util/concurrent/TimeoutException."<init>":(Ljava/lang/String;)V
      56: athrow
      57: astore        4
      59: new           #11                 // class java/util/concurrent/ExecutionException
      62: dup
      63: aload         4
      65: invokespecial #12                 // Method java/util/concurrent/ExecutionException."<init>":(Ljava/lang/Throwable;)V
      68: athrow
    Exception table:
       from    to  target type
          12    41    42   Class org/apache/hadoop/hbase/exceptions/TimeoutIOException
          12    41    57   Class java/lang/Exception

  public java.lang.Object get(long, java.util.concurrent.TimeUnit) throws java.lang.InterruptedException, java.util.concurrent.ExecutionException, java.util.concurrent.TimeoutException;
    Code:
       0: aload_0
       1: lload_1
       2: aload_3
       3: invokevirtual #18                 // Method get:(JLjava/util/concurrent/TimeUnit;)[B
       6: areturn

  public java.lang.Object get() throws java.lang.InterruptedException, java.util.concurrent.ExecutionException;
    Code:
       0: aload_0
       1: invokevirtual #19                 // Method get:()[B
       4: areturn
}
