Compiled from "ProcedureTestingUtility.java"
public class org.apache.hadoop.hbase.procedure2.ProcedureTestingUtility$NoopStateMachineProcedure<TEnv, TState> extends org.apache.hadoop.hbase.procedure2.StateMachineProcedure<TEnv, TState> {
  public org.apache.hadoop.hbase.procedure2.ProcedureTestingUtility$NoopStateMachineProcedure();
    Code:
       0: aload_0
       1: invokespecial #1                  // Method org/apache/hadoop/hbase/procedure2/StateMachineProcedure."<init>":()V
       4: return

  public org.apache.hadoop.hbase.procedure2.ProcedureTestingUtility$NoopStateMachineProcedure(TEnv, TState);
    Code:
       0: aload_0
       1: invokespecial #1                  // Method org/apache/hadoop/hbase/procedure2/StateMachineProcedure."<init>":()V
       4: aload_0
       5: aload_1
       6: putfield      #2                  // Field env:Ljava/lang/Object;
       9: aload_0
      10: aload_2
      11: putfield      #3                  // Field initialState:Ljava/lang/Object;
      14: return

  protected org.apache.hadoop.hbase.procedure2.StateMachineProcedure$Flow executeFromState(TEnv, TState) throws org.apache.hadoop.hbase.procedure2.ProcedureSuspendedException, org.apache.hadoop.hbase.procedure2.ProcedureYieldException, java.lang.InterruptedException;
    Code:
       0: aconst_null
       1: areturn

  protected void rollbackState(TEnv, TState) throws java.io.IOException, java.lang.InterruptedException;
    Code:
       0: return

  protected TState getState(int);
    Code:
       0: aconst_null
       1: areturn

  protected int getStateId(TState);
    Code:
       0: iconst_0
       1: ireturn

  protected TState getInitialState();
    Code:
       0: aload_0
       1: getfield      #3                  // Field initialState:Ljava/lang/Object;
       4: areturn
}
