Compiled from "ProcedureSyncWait.java"
final class org.apache.hadoop.hbase.master.procedure.ProcedureSyncWait$3 implements org.apache.hadoop.hbase.master.procedure.ProcedureSyncWait$Predicate<org.apache.hadoop.hbase.quotas.MasterQuotaManager> {
  final org.apache.hadoop.hbase.master.procedure.MasterProcedureEnv val$env;

  org.apache.hadoop.hbase.master.procedure.ProcedureSyncWait$3(org.apache.hadoop.hbase.master.procedure.MasterProcedureEnv);
    Code:
       0: aload_0
       1: aload_1
       2: putfield      #1                  // Field val$env:Lorg/apache/hadoop/hbase/master/procedure/MasterProcedureEnv;
       5: aload_0
       6: invokespecial #2                  // Method java/lang/Object."<init>":()V
       9: return

  public org.apache.hadoop.hbase.quotas.MasterQuotaManager evaluate() throws java.io.IOException;
    Code:
       0: aload_0
       1: getfield      #1                  // Field val$env:Lorg/apache/hadoop/hbase/master/procedure/MasterProcedureEnv;
       4: invokevirtual #3                  // Method org/apache/hadoop/hbase/master/procedure/MasterProcedureEnv.getMasterServices:()Lorg/apache/hadoop/hbase/master/MasterServices;
       7: invokeinterface #4,  1            // InterfaceMethod org/apache/hadoop/hbase/master/MasterServices.getMasterQuotaManager:()Lorg/apache/hadoop/hbase/quotas/MasterQuotaManager;
      12: areturn

  public java.lang.Object evaluate() throws java.io.IOException;
    Code:
       0: aload_0
       1: invokevirtual #5                  // Method evaluate:()Lorg/apache/hadoop/hbase/quotas/MasterQuotaManager;
       4: areturn
}
