Compiled from "ProcedureSyncWait.java"
final class org.apache.hadoop.hbase.master.procedure.ProcedureSyncWait$2 implements org.apache.hadoop.hbase.master.procedure.ProcedureSyncWait$Predicate<java.lang.Boolean> {
  final org.apache.hadoop.hbase.master.assignment.RegionStates val$states;

  final org.apache.hadoop.hbase.client.RegionInfo val$region;

  org.apache.hadoop.hbase.master.procedure.ProcedureSyncWait$2(org.apache.hadoop.hbase.master.assignment.RegionStates, org.apache.hadoop.hbase.client.RegionInfo);
    Code:
       0: aload_0
       1: aload_1
       2: putfield      #1                  // Field val$states:Lorg/apache/hadoop/hbase/master/assignment/RegionStates;
       5: aload_0
       6: aload_2
       7: putfield      #2                  // Field val$region:Lorg/apache/hadoop/hbase/client/RegionInfo;
      10: aload_0
      11: invokespecial #3                  // Method java/lang/Object."<init>":()V
      14: return

  public java.lang.Boolean evaluate() throws java.io.IOException;
    Code:
       0: aload_0
       1: getfield      #1                  // Field val$states:Lorg/apache/hadoop/hbase/master/assignment/RegionStates;
       4: aload_0
       5: getfield      #2                  // Field val$region:Lorg/apache/hadoop/hbase/client/RegionInfo;
       8: invokevirtual #4                  // Method org/apache/hadoop/hbase/master/assignment/RegionStates.isRegionInTransition:(Lorg/apache/hadoop/hbase/client/RegionInfo;)Z
      11: ifne          18
      14: iconst_1
      15: goto          19
      18: iconst_0
      19: invokestatic  #5                  // Method java/lang/Boolean.valueOf:(Z)Ljava/lang/Boolean;
      22: areturn

  public java.lang.Object evaluate() throws java.io.IOException;
    Code:
       0: aload_0
       1: invokevirtual #6                  // Method evaluate:()Ljava/lang/Boolean;
       4: areturn
}
