Compiled from "ProcedureWALPrettyPrinter.java"
class org.apache.hadoop.hbase.procedure2.store.wal.ProcedureWALPrettyPrinter$1 {
  static final int[] $SwitchMap$org$apache$hadoop$hbase$shaded$protobuf$generated$ProcedureProtos$ProcedureWALEntry$Type;

  static {};
    Code:
       0: invokestatic  #1                  // Method org/apache/hadoop/hbase/shaded/protobuf/generated/ProcedureProtos$ProcedureWALEntry$Type.values:()[Lorg/apache/hadoop/hbase/shaded/protobuf/generated/ProcedureProtos$ProcedureWALEntry$Type;
       3: arraylength
       4: newarray       int
       6: putstatic     #2                  // Field $SwitchMap$org$apache$hadoop$hbase$shaded$protobuf$generated$ProcedureProtos$ProcedureWALEntry$Type:[I
       9: getstatic     #2                  // Field $SwitchMap$org$apache$hadoop$hbase$shaded$protobuf$generated$ProcedureProtos$ProcedureWALEntry$Type:[I
      12: getstatic     #3                  // Field org/apache/hadoop/hbase/shaded/protobuf/generated/ProcedureProtos$ProcedureWALEntry$Type.PROCEDURE_WAL_EOF:Lorg/apache/hadoop/hbase/shaded/protobuf/generated/ProcedureProtos$ProcedureWALEntry$Type;
      15: invokevirtual #4                  // Method org/apache/hadoop/hbase/shaded/protobuf/generated/ProcedureProtos$ProcedureWALEntry$Type.ordinal:()I
      18: iconst_1
      19: iastore
      20: goto          24
      23: astore_0
      24: return
    Exception table:
       from    to  target type
           9    20    23   Class java/lang/NoSuchFieldError
}
