Compiled from "ProcessBasedLocalHBaseCluster.java"
final class org.apache.hadoop.hbase.util.ProcessBasedLocalHBaseCluster$ServerType extends java.lang.Enum<org.apache.hadoop.hbase.util.ProcessBasedLocalHBaseCluster$ServerType> {
  public static final org.apache.hadoop.hbase.util.ProcessBasedLocalHBaseCluster$ServerType MASTER;

  public static final org.apache.hadoop.hbase.util.ProcessBasedLocalHBaseCluster$ServerType RS;

  public static final org.apache.hadoop.hbase.util.ProcessBasedLocalHBaseCluster$ServerType ZK;

  public static org.apache.hadoop.hbase.util.ProcessBasedLocalHBaseCluster$ServerType[] values();
    Code:
       0: getstatic     #2                  // Field $VALUES:[Lorg/apache/hadoop/hbase/util/ProcessBasedLocalHBaseCluster$ServerType;
       3: invokevirtual #3                  // Method "[Lorg/apache/hadoop/hbase/util/ProcessBasedLocalHBaseCluster$ServerType;".clone:()Ljava/lang/Object;
       6: checkcast     #4                  // class "[Lorg/apache/hadoop/hbase/util/ProcessBasedLocalHBaseCluster$ServerType;"
       9: areturn

  public static org.apache.hadoop.hbase.util.ProcessBasedLocalHBaseCluster$ServerType valueOf(java.lang.String);
    Code:
       0: ldc           #5                  // class org/apache/hadoop/hbase/util/ProcessBasedLocalHBaseCluster$ServerType
       2: aload_0
       3: invokestatic  #6                  // Method java/lang/Enum.valueOf:(Ljava/lang/Class;Ljava/lang/String;)Ljava/lang/Enum;
       6: checkcast     #5                  // class org/apache/hadoop/hbase/util/ProcessBasedLocalHBaseCluster$ServerType
       9: areturn

  static java.lang.String access$100(org.apache.hadoop.hbase.util.ProcessBasedLocalHBaseCluster$ServerType);
    Code:
       0: aload_0
       1: getfield      #1                  // Field fullName:Ljava/lang/String;
       4: areturn

  static {};
    Code:
       0: new           #5                  // class org/apache/hadoop/hbase/util/ProcessBasedLocalHBaseCluster$ServerType
       3: dup
       4: ldc           #8                  // String MASTER
       6: iconst_0
       7: ldc           #9                  // String master
       9: invokespecial #10                 // Method "<init>":(Ljava/lang/String;ILjava/lang/String;)V
      12: putstatic     #11                 // Field MASTER:Lorg/apache/hadoop/hbase/util/ProcessBasedLocalHBaseCluster$ServerType;
      15: new           #5                  // class org/apache/hadoop/hbase/util/ProcessBasedLocalHBaseCluster$ServerType
      18: dup
      19: ldc           #12                 // String RS
      21: iconst_1
      22: ldc           #13                 // String regionserver
      24: invokespecial #10                 // Method "<init>":(Ljava/lang/String;ILjava/lang/String;)V
      27: putstatic     #14                 // Field RS:Lorg/apache/hadoop/hbase/util/ProcessBasedLocalHBaseCluster$ServerType;
      30: new           #5                  // class org/apache/hadoop/hbase/util/ProcessBasedLocalHBaseCluster$ServerType
      33: dup
      34: ldc           #15                 // String ZK
      36: iconst_2
      37: ldc           #16                 // String zookeeper
      39: invokespecial #10                 // Method "<init>":(Ljava/lang/String;ILjava/lang/String;)V
      42: putstatic     #17                 // Field ZK:Lorg/apache/hadoop/hbase/util/ProcessBasedLocalHBaseCluster$ServerType;
      45: iconst_3
      46: anewarray     #5                  // class org/apache/hadoop/hbase/util/ProcessBasedLocalHBaseCluster$ServerType
      49: dup
      50: iconst_0
      51: getstatic     #11                 // Field MASTER:Lorg/apache/hadoop/hbase/util/ProcessBasedLocalHBaseCluster$ServerType;
      54: aastore
      55: dup
      56: iconst_1
      57: getstatic     #14                 // Field RS:Lorg/apache/hadoop/hbase/util/ProcessBasedLocalHBaseCluster$ServerType;
      60: aastore
      61: dup
      62: iconst_2
      63: getstatic     #17                 // Field ZK:Lorg/apache/hadoop/hbase/util/ProcessBasedLocalHBaseCluster$ServerType;
      66: aastore
      67: putstatic     #2                  // Field $VALUES:[Lorg/apache/hadoop/hbase/util/ProcessBasedLocalHBaseCluster$ServerType;
      70: return
}
