Compiled from "ProcedureSyncWait.java"
final class org.apache.hadoop.hbase.master.procedure.ProcedureSyncWait$1 implements org.apache.hadoop.hbase.master.procedure.ProcedureSyncWait$Predicate<java.lang.Boolean> {
  final org.apache.hadoop.hbase.procedure2.ProcedureExecutor val$procExec;

  final org.apache.hadoop.hbase.procedure2.Procedure val$proc;

  org.apache.hadoop.hbase.master.procedure.ProcedureSyncWait$1(org.apache.hadoop.hbase.procedure2.ProcedureExecutor, org.apache.hadoop.hbase.procedure2.Procedure);
    Code:
       0: aload_0
       1: aload_1
       2: putfield      #1                  // Field val$procExec:Lorg/apache/hadoop/hbase/procedure2/ProcedureExecutor;
       5: aload_0
       6: aload_2
       7: putfield      #2                  // Field val$proc:Lorg/apache/hadoop/hbase/procedure2/Procedure;
      10: aload_0
      11: invokespecial #3                  // Method java/lang/Object."<init>":()V
      14: return

  public java.lang.Boolean evaluate() throws java.io.IOException;
    Code:
       0: aload_0
       1: getfield      #1                  // Field val$procExec:Lorg/apache/hadoop/hbase/procedure2/ProcedureExecutor;
       4: invokevirtual #4                  // Method org/apache/hadoop/hbase/procedure2/ProcedureExecutor.isRunning:()Z
       7: ifne          15
      10: iconst_1
      11: invokestatic  #5                  // Method java/lang/Boolean.valueOf:(Z)Ljava/lang/Boolean;
      14: areturn
      15: aload_0
      16: getfield      #2                  // Field val$proc:Lorg/apache/hadoop/hbase/procedure2/Procedure;
      19: invokevirtual #6                  // Method org/apache/hadoop/hbase/procedure2/Procedure.getState:()Lorg/apache/hadoop/hbase/shaded/protobuf/generated/ProcedureProtos$ProcedureState;
      22: astore_1
      23: aload_1
      24: getstatic     #7                  // Field org/apache/hadoop/hbase/shaded/protobuf/generated/ProcedureProtos$ProcedureState.INITIALIZING:Lorg/apache/hadoop/hbase/shaded/protobuf/generated/ProcedureProtos$ProcedureState;
      27: if_acmpeq     37
      30: aload_1
      31: getstatic     #8                  // Field org/apache/hadoop/hbase/shaded/protobuf/generated/ProcedureProtos$ProcedureState.RUNNABLE:Lorg/apache/hadoop/hbase/shaded/protobuf/generated/ProcedureProtos$ProcedureState;
      34: if_acmpne     42
      37: iconst_0
      38: invokestatic  #5                  // Method java/lang/Boolean.valueOf:(Z)Ljava/lang/Boolean;
      41: areturn
      42: aload_0
      43: getfield      #1                  // Field val$procExec:Lorg/apache/hadoop/hbase/procedure2/ProcedureExecutor;
      46: aload_0
      47: getfield      #2                  // Field val$proc:Lorg/apache/hadoop/hbase/procedure2/Procedure;
      50: invokevirtual #9                  // Method org/apache/hadoop/hbase/procedure2/Procedure.getProcId:()J
      53: invokevirtual #10                 // Method org/apache/hadoop/hbase/procedure2/ProcedureExecutor.isFinished:(J)Z
      56: invokestatic  #5                  // Method java/lang/Boolean.valueOf:(Z)Ljava/lang/Boolean;
      59: areturn

  public java.lang.Object evaluate() throws java.io.IOException;
    Code:
       0: aload_0
       1: invokevirtual #11                 // Method evaluate:()Ljava/lang/Boolean;
       4: areturn
}
