Compiled from "ProcedurePrepareLatch.java"
public class org.apache.hadoop.hbase.master.procedure.ProcedurePrepareLatch$CompatibilityLatch extends org.apache.hadoop.hbase.master.procedure.ProcedurePrepareLatch {
  protected org.apache.hadoop.hbase.master.procedure.ProcedurePrepareLatch$CompatibilityLatch();
    Code:
       0: aload_0
       1: invokespecial #1                  // Method org/apache/hadoop/hbase/master/procedure/ProcedurePrepareLatch."<init>":()V
       4: aload_0
       5: new           #2                  // class java/util/concurrent/CountDownLatch
       8: dup
       9: iconst_1
      10: invokespecial #3                  // Method java/util/concurrent/CountDownLatch."<init>":(I)V
      13: putfield      #4                  // Field latch:Ljava/util/concurrent/CountDownLatch;
      16: aload_0
      17: aconst_null
      18: putfield      #5                  // Field exception:Ljava/io/IOException;
      21: return

  protected void countDown(org.apache.hadoop.hbase.procedure2.Procedure);
    Code:
       0: aload_1
       1: invokevirtual #6                  // Method org/apache/hadoop/hbase/procedure2/Procedure.hasException:()Z
       4: ifeq          15
       7: aload_0
       8: aload_1
       9: invokestatic  #7                  // Method org/apache/hadoop/hbase/master/procedure/MasterProcedureUtil.unwrapRemoteIOException:(Lorg/apache/hadoop/hbase/procedure2/Procedure;)Ljava/io/IOException;
      12: putfield      #5                  // Field exception:Ljava/io/IOException;
      15: aload_0
      16: getfield      #4                  // Field latch:Ljava/util/concurrent/CountDownLatch;
      19: invokevirtual #8                  // Method java/util/concurrent/CountDownLatch.countDown:()V
      22: return

  public void await() throws java.io.IOException;
    Code:
       0: aload_0
       1: getfield      #4                  // Field latch:Ljava/util/concurrent/CountDownLatch;
       4: invokevirtual #9                  // Method java/util/concurrent/CountDownLatch.await:()V
       7: goto          26
      10: astore_1
      11: new           #11                 // class java/io/InterruptedIOException
      14: dup
      15: invokespecial #12                 // Method java/io/InterruptedIOException."<init>":()V
      18: aload_1
      19: invokevirtual #13                 // Method java/io/InterruptedIOException.initCause:(Ljava/lang/Throwable;)Ljava/lang/Throwable;
      22: checkcast     #11                 // class java/io/InterruptedIOException
      25: athrow
      26: aload_0
      27: getfield      #5                  // Field exception:Ljava/io/IOException;
      30: ifnull        38
      33: aload_0
      34: getfield      #5                  // Field exception:Ljava/io/IOException;
      37: athrow
      38: return
    Exception table:
       from    to  target type
           0     7    10   Class java/lang/InterruptedException
}
