Compiled from "ProcedureExecutor.java"
public class org.apache.hadoop.hbase.procedure2.ProcedureExecutor<TEnvironment> {
  public static final java.lang.String CHECK_OWNER_SET_CONF_KEY;

  public static final java.lang.String WORKER_KEEP_ALIVE_TIME_CONF_KEY;

  public static final java.lang.String EVICT_TTL_CONF_KEY;

  static final int DEFAULT_EVICT_TTL;

  public static final java.lang.String EVICT_ACKED_TTL_CONF_KEY;

  static final int DEFAULT_ACKED_EVICT_TTL;

  volatile org.apache.hadoop.hbase.procedure2.ProcedureExecutor$Testing testing;

  static final boolean $assertionsDisabled;

  public org.apache.hadoop.hbase.procedure2.ProcedureExecutor(org.apache.hadoop.conf.Configuration, TEnvironment, org.apache.hadoop.hbase.procedure2.store.ProcedureStore);
    Code:
       0: aload_0
       1: aload_1
       2: aload_2
       3: aload_3
       4: new           #17                 // class org/apache/hadoop/hbase/procedure2/SimpleProcedureScheduler
       7: dup
       8: invokespecial #18                 // Method org/apache/hadoop/hbase/procedure2/SimpleProcedureScheduler."<init>":()V
      11: invokespecial #19                 // Method "<init>":(Lorg/apache/hadoop/conf/Configuration;Ljava/lang/Object;Lorg/apache/hadoop/hbase/procedure2/store/ProcedureStore;Lorg/apache/hadoop/hbase/procedure2/ProcedureScheduler;)V
      14: return

  public org.apache.hadoop.hbase.procedure2.ProcedureExecutor(org.apache.hadoop.conf.Configuration, TEnvironment, org.apache.hadoop.hbase.procedure2.store.ProcedureStore, org.apache.hadoop.hbase.procedure2.ProcedureScheduler);
    Code:
       0: aload_0
       1: invokespecial #48                 // Method java/lang/Object."<init>":()V
       4: aload_0
       5: aconst_null
       6: putfield      #49                 // Field testing:Lorg/apache/hadoop/hbase/procedure2/ProcedureExecutor$Testing;
       9: aload_0
      10: new           #50                 // class java/util/concurrent/ConcurrentHashMap
      13: dup
      14: invokespecial #51                 // Method java/util/concurrent/ConcurrentHashMap."<init>":()V
      17: putfield      #32                 // Field completed:Ljava/util/concurrent/ConcurrentHashMap;
      20: aload_0
      21: new           #50                 // class java/util/concurrent/ConcurrentHashMap
      24: dup
      25: invokespecial #51                 // Method java/util/concurrent/ConcurrentHashMap."<init>":()V
      28: putfield      #52                 // Field rollbackStack:Ljava/util/concurrent/ConcurrentHashMap;
      31: aload_0
      32: new           #50                 // class java/util/concurrent/ConcurrentHashMap
      35: dup
      36: invokespecial #51                 // Method java/util/concurrent/ConcurrentHashMap."<init>":()V
      39: putfield      #20                 // Field procedures:Ljava/util/concurrent/ConcurrentHashMap;
      42: aload_0
      43: new           #50                 // class java/util/concurrent/ConcurrentHashMap
      46: dup
      47: invokespecial #51                 // Method java/util/concurrent/ConcurrentHashMap."<init>":()V
      50: putfield      #53                 // Field nonceKeysToProcIdsMap:Ljava/util/concurrent/ConcurrentHashMap;
      53: aload_0
      54: new           #54                 // class java/util/concurrent/CopyOnWriteArrayList
      57: dup
      58: invokespecial #55                 // Method java/util/concurrent/CopyOnWriteArrayList."<init>":()V
      61: putfield      #56                 // Field listeners:Ljava/util/concurrent/CopyOnWriteArrayList;
      64: aload_0
      65: new           #57                 // class org/apache/hbase/thirdparty/com/google/common/util/concurrent/ThreadFactoryBuilder
      68: dup
      69: invokespecial #58                 // Method org/apache/hbase/thirdparty/com/google/common/util/concurrent/ThreadFactoryBuilder."<init>":()V
      72: iconst_1
      73: invokevirtual #59                 // Method org/apache/hbase/thirdparty/com/google/common/util/concurrent/ThreadFactoryBuilder.setDaemon:(Z)Lorg/apache/hbase/thirdparty/com/google/common/util/concurrent/ThreadFactoryBuilder;
      76: ldc           #60                 // String Force-Update-PEWorker-%d
      78: invokevirtual #61                 // Method org/apache/hbase/thirdparty/com/google/common/util/concurrent/ThreadFactoryBuilder.setNameFormat:(Ljava/lang/String;)Lorg/apache/hbase/thirdparty/com/google/common/util/concurrent/ThreadFactoryBuilder;
      81: invokevirtual #62                 // Method org/apache/hbase/thirdparty/com/google/common/util/concurrent/ThreadFactoryBuilder.build:()Ljava/util/concurrent/ThreadFactory;
      84: invokestatic  #63                 // Method java/util/concurrent/Executors.newSingleThreadExecutor:(Ljava/util/concurrent/ThreadFactory;)Ljava/util/concurrent/ExecutorService;
      87: putfield      #15                 // Field forceUpdateExecutor:Ljava/util/concurrent/Executor;
      90: aload_0
      91: new           #64                 // class java/util/concurrent/atomic/AtomicLong
      94: dup
      95: ldc2_w        #65                 // long -1l
      98: invokespecial #67                 // Method java/util/concurrent/atomic/AtomicLong."<init>":(J)V
     101: putfield      #13                 // Field lastProcId:Ljava/util/concurrent/atomic/AtomicLong;
     104: aload_0
     105: new           #64                 // class java/util/concurrent/atomic/AtomicLong
     108: dup
     109: lconst_0
     110: invokespecial #67                 // Method java/util/concurrent/atomic/AtomicLong."<init>":(J)V
     113: putfield      #11                 // Field workerId:Ljava/util/concurrent/atomic/AtomicLong;
     116: aload_0
     117: new           #68                 // class java/util/concurrent/atomic/AtomicInteger
     120: dup
     121: iconst_0
     122: invokespecial #69                 // Method java/util/concurrent/atomic/AtomicInteger."<init>":(I)V
     125: putfield      #8                  // Field activeExecutorCount:Ljava/util/concurrent/atomic/AtomicInteger;
     128: aload_0
     129: new           #70                 // class java/util/concurrent/atomic/AtomicBoolean
     132: dup
     133: iconst_0
     134: invokespecial #71                 // Method java/util/concurrent/atomic/AtomicBoolean."<init>":(Z)V
     137: putfield      #72                 // Field running:Ljava/util/concurrent/atomic/AtomicBoolean;
     140: aload_0
     141: new           #73                 // class org/apache/hadoop/hbase/util/IdLock
     144: dup
     145: invokespecial #74                 // Method org/apache/hadoop/hbase/util/IdLock."<init>":()V
     148: putfield      #6                  // Field procExecutionLock:Lorg/apache/hadoop/hbase/util/IdLock;
     151: aload_0
     152: aload_2
     153: putfield      #75                 // Field environment:Ljava/lang/Object;
     156: aload_0
     157: aload         4
     159: putfield      #10                 // Field scheduler:Lorg/apache/hadoop/hbase/procedure2/ProcedureScheduler;
     162: aload_0
     163: aload_3
     164: putfield      #7                  // Field store:Lorg/apache/hadoop/hbase/procedure2/store/ProcedureStore;
     167: aload_0
     168: aload_1
     169: putfield      #1                  // Field conf:Lorg/apache/hadoop/conf/Configuration;
     172: aload_0
     173: aload_1
     174: ldc           #76                 // String hbase.procedure.check.owner.set
     176: iconst_0
     177: invokevirtual #77                 // Method org/apache/hadoop/conf/Configuration.getBoolean:(Ljava/lang/String;Z)Z
     180: putfield      #78                 // Field checkOwnerSet:Z
     183: aload_0
     184: aload_1
     185: invokevirtual #79                 // Method refreshConfiguration:(Lorg/apache/hadoop/conf/Configuration;)V
     188: aload_3
     189: new           #80                 // class org/apache/hadoop/hbase/procedure2/ProcedureExecutor$1
     192: dup
     193: aload_0
     194: invokespecial #81                 // Method org/apache/hadoop/hbase/procedure2/ProcedureExecutor$1."<init>":(Lorg/apache/hadoop/hbase/procedure2/ProcedureExecutor;)V
     197: invokeinterface #82,  2           // InterfaceMethod org/apache/hadoop/hbase/procedure2/store/ProcedureStore.registerListener:(Lorg/apache/hadoop/hbase/procedure2/store/ProcedureStore$ProcedureStoreListener;)V
     202: return

  public void init(int, boolean) throws java.io.IOException;
    Code:
       0: aload_0
       1: iload_1
       2: putfield      #156                // Field corePoolSize:I
       5: aload_0
       6: bipush        10
       8: iload_1
       9: imul
      10: putfield      #3                  // Field maxPoolSize:I
      13: getstatic     #16                 // Field LOG:Lorg/slf4j/Logger;
      16: ldc           #157                // String Starting {} core workers (bigger of cpus/4 or 16) with max (burst) worker count={}
      18: aload_0
      19: getfield      #156                // Field corePoolSize:I
      22: invokestatic  #158                // Method java/lang/Integer.valueOf:(I)Ljava/lang/Integer;
      25: aload_0
      26: getfield      #3                  // Field maxPoolSize:I
      29: invokestatic  #158                // Method java/lang/Integer.valueOf:(I)Ljava/lang/Integer;
      32: invokeinterface #159,  4          // InterfaceMethod org/slf4j/Logger.info:(Ljava/lang/String;Ljava/lang/Object;Ljava/lang/Object;)V
      37: aload_0
      38: new           #160                // class java/lang/ThreadGroup
      41: dup
      42: ldc           #161                // String PEWorkerGroup
      44: invokespecial #162                // Method java/lang/ThreadGroup."<init>":(Ljava/lang/String;)V
      47: putfield      #2                  // Field threadGroup:Ljava/lang/ThreadGroup;
      50: aload_0
      51: new           #163                // class org/apache/hadoop/hbase/procedure2/TimeoutExecutorThread
      54: dup
      55: aload_0
      56: aload_0
      57: getfield      #2                  // Field threadGroup:Ljava/lang/ThreadGroup;
      60: invokespecial #164                // Method org/apache/hadoop/hbase/procedure2/TimeoutExecutorThread."<init>":(Lorg/apache/hadoop/hbase/procedure2/ProcedureExecutor;Ljava/lang/ThreadGroup;)V
      63: putfield      #165                // Field timeoutExecutor:Lorg/apache/hadoop/hbase/procedure2/TimeoutExecutorThread;
      66: aload_0
      67: getfield      #11                 // Field workerId:Ljava/util/concurrent/atomic/AtomicLong;
      70: lconst_0
      71: invokevirtual #166                // Method java/util/concurrent/atomic/AtomicLong.set:(J)V
      74: aload_0
      75: new           #54                 // class java/util/concurrent/CopyOnWriteArrayList
      78: dup
      79: invokespecial #55                 // Method java/util/concurrent/CopyOnWriteArrayList."<init>":()V
      82: putfield      #4                  // Field workerThreads:Ljava/util/concurrent/CopyOnWriteArrayList;
      85: iconst_0
      86: istore_3
      87: iload_3
      88: aload_0
      89: getfield      #156                // Field corePoolSize:I
      92: if_icmpge     121
      95: aload_0
      96: getfield      #4                  // Field workerThreads:Ljava/util/concurrent/CopyOnWriteArrayList;
      99: new           #167                // class org/apache/hadoop/hbase/procedure2/ProcedureExecutor$WorkerThread
     102: dup
     103: aload_0
     104: aload_0
     105: getfield      #2                  // Field threadGroup:Ljava/lang/ThreadGroup;
     108: invokespecial #168                // Method org/apache/hadoop/hbase/procedure2/ProcedureExecutor$WorkerThread."<init>":(Lorg/apache/hadoop/hbase/procedure2/ProcedureExecutor;Ljava/lang/ThreadGroup;)V
     111: invokevirtual #169                // Method java/util/concurrent/CopyOnWriteArrayList.add:(Ljava/lang/Object;)Z
     114: pop
     115: iinc          3, 1
     118: goto          87
     121: invokestatic  #170                // Method java/lang/System.nanoTime:()J
     124: lstore_3
     125: aload_0
     126: getfield      #7                  // Field store:Lorg/apache/hadoop/hbase/procedure2/store/ProcedureStore;
     129: invokeinterface #171,  1          // InterfaceMethod org/apache/hadoop/hbase/procedure2/store/ProcedureStore.recoverLease:()V
     134: invokestatic  #170                // Method java/lang/System.nanoTime:()J
     137: lstore        5
     139: getstatic     #16                 // Field LOG:Lorg/slf4j/Logger;
     142: ldc           #172                // String Recovered {} lease in {}
     144: aload_0
     145: getfield      #7                  // Field store:Lorg/apache/hadoop/hbase/procedure2/store/ProcedureStore;
     148: invokevirtual #152                // Method java/lang/Object.getClass:()Ljava/lang/Class;
     151: invokevirtual #173                // Method java/lang/Class.getSimpleName:()Ljava/lang/String;
     154: getstatic     #174                // Field java/util/concurrent/TimeUnit.NANOSECONDS:Ljava/util/concurrent/TimeUnit;
     157: lload         5
     159: lload_3
     160: lsub
     161: invokevirtual #175                // Method java/util/concurrent/TimeUnit.toMillis:(J)J
     164: invokestatic  #176                // Method org/apache/hadoop/hbase/procedure2/util/StringUtils.humanTimeDiff:(J)Ljava/lang/String;
     167: invokeinterface #159,  4          // InterfaceMethod org/slf4j/Logger.info:(Ljava/lang/String;Ljava/lang/Object;Ljava/lang/Object;)V
     172: aload_0
     173: getfield      #10                 // Field scheduler:Lorg/apache/hadoop/hbase/procedure2/ProcedureScheduler;
     176: invokeinterface #177,  1          // InterfaceMethod org/apache/hadoop/hbase/procedure2/ProcedureScheduler.start:()V
     181: invokestatic  #170                // Method java/lang/System.nanoTime:()J
     184: lstore_3
     185: aload_0
     186: iload_2
     187: invokespecial #178                // Method load:(Z)V
     190: invokestatic  #170                // Method java/lang/System.nanoTime:()J
     193: lstore        5
     195: getstatic     #16                 // Field LOG:Lorg/slf4j/Logger;
     198: ldc           #179                // String Loaded {} in {}
     200: aload_0
     201: getfield      #7                  // Field store:Lorg/apache/hadoop/hbase/procedure2/store/ProcedureStore;
     204: invokevirtual #152                // Method java/lang/Object.getClass:()Ljava/lang/Class;
     207: invokevirtual #173                // Method java/lang/Class.getSimpleName:()Ljava/lang/String;
     210: getstatic     #174                // Field java/util/concurrent/TimeUnit.NANOSECONDS:Ljava/util/concurrent/TimeUnit;
     213: lload         5
     215: lload_3
     216: lsub
     217: invokevirtual #175                // Method java/util/concurrent/TimeUnit.toMillis:(J)J
     220: invokestatic  #176                // Method org/apache/hadoop/hbase/procedure2/util/StringUtils.humanTimeDiff:(J)Ljava/lang/String;
     223: invokeinterface #159,  4          // InterfaceMethod org/slf4j/Logger.info:(Ljava/lang/String;Ljava/lang/Object;Ljava/lang/Object;)V
     228: return

  public void startWorkers() throws java.io.IOException;
    Code:
       0: aload_0
       1: getfield      #72                 // Field running:Ljava/util/concurrent/atomic/AtomicBoolean;
       4: iconst_0
       5: iconst_1
       6: invokevirtual #180                // Method java/util/concurrent/atomic/AtomicBoolean.compareAndSet:(ZZ)Z
       9: ifne          23
      12: getstatic     #16                 // Field LOG:Lorg/slf4j/Logger;
      15: ldc           #181                // String Already running
      17: invokeinterface #182,  2          // InterfaceMethod org/slf4j/Logger.warn:(Ljava/lang/String;)V
      22: return
      23: getstatic     #16                 // Field LOG:Lorg/slf4j/Logger;
      26: ldc           #183                // String Start workers {}
      28: aload_0
      29: getfield      #4                  // Field workerThreads:Ljava/util/concurrent/CopyOnWriteArrayList;
      32: invokevirtual #184                // Method java/util/concurrent/CopyOnWriteArrayList.size:()I
      35: invokestatic  #158                // Method java/lang/Integer.valueOf:(I)Ljava/lang/Integer;
      38: invokeinterface #185,  3          // InterfaceMethod org/slf4j/Logger.trace:(Ljava/lang/String;Ljava/lang/Object;)V
      43: aload_0
      44: getfield      #165                // Field timeoutExecutor:Lorg/apache/hadoop/hbase/procedure2/TimeoutExecutorThread;
      47: invokevirtual #186                // Method org/apache/hadoop/hbase/procedure2/TimeoutExecutorThread.start:()V
      50: aload_0
      51: getfield      #4                  // Field workerThreads:Ljava/util/concurrent/CopyOnWriteArrayList;
      54: invokevirtual #187                // Method java/util/concurrent/CopyOnWriteArrayList.iterator:()Ljava/util/Iterator;
      57: astore_1
      58: aload_1
      59: invokeinterface #188,  1          // InterfaceMethod java/util/Iterator.hasNext:()Z
      64: ifeq          84
      67: aload_1
      68: invokeinterface #189,  1          // InterfaceMethod java/util/Iterator.next:()Ljava/lang/Object;
      73: checkcast     #167                // class org/apache/hadoop/hbase/procedure2/ProcedureExecutor$WorkerThread
      76: astore_2
      77: aload_2
      78: invokevirtual #190                // Method org/apache/hadoop/hbase/procedure2/ProcedureExecutor$WorkerThread.start:()V
      81: goto          58
      84: aload_0
      85: getfield      #165                // Field timeoutExecutor:Lorg/apache/hadoop/hbase/procedure2/TimeoutExecutorThread;
      88: new           #191                // class org/apache/hadoop/hbase/procedure2/ProcedureExecutor$WorkerMonitor
      91: dup
      92: aload_0
      93: invokespecial #192                // Method org/apache/hadoop/hbase/procedure2/ProcedureExecutor$WorkerMonitor."<init>":(Lorg/apache/hadoop/hbase/procedure2/ProcedureExecutor;)V
      96: invokevirtual #193                // Method org/apache/hadoop/hbase/procedure2/TimeoutExecutorThread.add:(Lorg/apache/hadoop/hbase/procedure2/InlineChore;)V
      99: aload_0
     100: new           #194                // class org/apache/hadoop/hbase/procedure2/CompletedProcedureCleaner
     103: dup
     104: aload_0
     105: getfield      #1                  // Field conf:Lorg/apache/hadoop/conf/Configuration;
     108: aload_0
     109: getfield      #7                  // Field store:Lorg/apache/hadoop/hbase/procedure2/store/ProcedureStore;
     112: aload_0
     113: getfield      #6                  // Field procExecutionLock:Lorg/apache/hadoop/hbase/util/IdLock;
     116: aload_0
     117: getfield      #32                 // Field completed:Ljava/util/concurrent/ConcurrentHashMap;
     120: aload_0
     121: getfield      #53                 // Field nonceKeysToProcIdsMap:Ljava/util/concurrent/ConcurrentHashMap;
     124: invokespecial #195                // Method org/apache/hadoop/hbase/procedure2/CompletedProcedureCleaner."<init>":(Lorg/apache/hadoop/conf/Configuration;Lorg/apache/hadoop/hbase/procedure2/store/ProcedureStore;Lorg/apache/hadoop/hbase/util/IdLock;Ljava/util/Map;Ljava/util/Map;)V
     127: invokevirtual #196                // Method addChore:(Lorg/apache/hadoop/hbase/procedure2/ProcedureInMemoryChore;)V
     130: return

  public void stop();
    Code:
       0: aload_0
       1: getfield      #72                 // Field running:Ljava/util/concurrent/atomic/AtomicBoolean;
       4: iconst_0
       5: invokevirtual #197                // Method java/util/concurrent/atomic/AtomicBoolean.getAndSet:(Z)Z
       8: ifne          12
      11: return
      12: getstatic     #16                 // Field LOG:Lorg/slf4j/Logger;
      15: ldc           #198                // String Stopping
      17: invokeinterface #199,  2          // InterfaceMethod org/slf4j/Logger.info:(Ljava/lang/String;)V
      22: aload_0
      23: getfield      #10                 // Field scheduler:Lorg/apache/hadoop/hbase/procedure2/ProcedureScheduler;
      26: invokeinterface #200,  1          // InterfaceMethod org/apache/hadoop/hbase/procedure2/ProcedureScheduler.stop:()V
      31: aload_0
      32: getfield      #165                // Field timeoutExecutor:Lorg/apache/hadoop/hbase/procedure2/TimeoutExecutorThread;
      35: invokevirtual #201                // Method org/apache/hadoop/hbase/procedure2/TimeoutExecutorThread.sendStopSignal:()V
      38: return

  public void join();
    Code:
       0: getstatic     #114                // Field $assertionsDisabled:Z
       3: ifne          23
       6: aload_0
       7: invokevirtual #202                // Method isRunning:()Z
      10: ifeq          23
      13: new           #115                // class java/lang/AssertionError
      16: dup
      17: ldc           #203                // String expected not running
      19: invokespecial #117                // Method java/lang/AssertionError."<init>":(Ljava/lang/Object;)V
      22: athrow
      23: aload_0
      24: getfield      #165                // Field timeoutExecutor:Lorg/apache/hadoop/hbase/procedure2/TimeoutExecutorThread;
      27: invokevirtual #204                // Method org/apache/hadoop/hbase/procedure2/TimeoutExecutorThread.awaitTermination:()V
      30: aload_0
      31: getfield      #4                  // Field workerThreads:Ljava/util/concurrent/CopyOnWriteArrayList;
      34: invokevirtual #187                // Method java/util/concurrent/CopyOnWriteArrayList.iterator:()Ljava/util/Iterator;
      37: astore_1
      38: aload_1
      39: invokeinterface #188,  1          // InterfaceMethod java/util/Iterator.hasNext:()Z
      44: ifeq          64
      47: aload_1
      48: invokeinterface #189,  1          // InterfaceMethod java/util/Iterator.next:()Ljava/lang/Object;
      53: checkcast     #167                // class org/apache/hadoop/hbase/procedure2/ProcedureExecutor$WorkerThread
      56: astore_2
      57: aload_2
      58: invokevirtual #205                // Method org/apache/hadoop/hbase/procedure2/ProcedureExecutor$WorkerThread.awaitTermination:()V
      61: goto          38
      64: aload_0
      65: getfield      #2                  // Field threadGroup:Ljava/lang/ThreadGroup;
      68: invokevirtual #206                // Method java/lang/ThreadGroup.destroy:()V
      71: goto          100
      74: astore_1
      75: getstatic     #16                 // Field LOG:Lorg/slf4j/Logger;
      78: ldc           #208                // String ThreadGroup {} contains running threads; {}: See STDOUT
      80: aload_0
      81: getfield      #2                  // Field threadGroup:Ljava/lang/ThreadGroup;
      84: aload_1
      85: invokevirtual #209                // Method java/lang/IllegalThreadStateException.getMessage:()Ljava/lang/String;
      88: invokeinterface #210,  4          // InterfaceMethod org/slf4j/Logger.error:(Ljava/lang/String;Ljava/lang/Object;Ljava/lang/Object;)V
      93: aload_0
      94: getfield      #2                  // Field threadGroup:Ljava/lang/ThreadGroup;
      97: invokevirtual #211                // Method java/lang/ThreadGroup.list:()V
     100: aload_0
     101: getfield      #32                 // Field completed:Ljava/util/concurrent/ConcurrentHashMap;
     104: invokevirtual #212                // Method java/util/concurrent/ConcurrentHashMap.clear:()V
     107: aload_0
     108: getfield      #52                 // Field rollbackStack:Ljava/util/concurrent/ConcurrentHashMap;
     111: invokevirtual #212                // Method java/util/concurrent/ConcurrentHashMap.clear:()V
     114: aload_0
     115: getfield      #20                 // Field procedures:Ljava/util/concurrent/ConcurrentHashMap;
     118: invokevirtual #212                // Method java/util/concurrent/ConcurrentHashMap.clear:()V
     121: aload_0
     122: getfield      #53                 // Field nonceKeysToProcIdsMap:Ljava/util/concurrent/ConcurrentHashMap;
     125: invokevirtual #212                // Method java/util/concurrent/ConcurrentHashMap.clear:()V
     128: aload_0
     129: getfield      #10                 // Field scheduler:Lorg/apache/hadoop/hbase/procedure2/ProcedureScheduler;
     132: invokeinterface #213,  1          // InterfaceMethod org/apache/hadoop/hbase/procedure2/ProcedureScheduler.clear:()V
     137: aload_0
     138: getfield      #13                 // Field lastProcId:Ljava/util/concurrent/atomic/AtomicLong;
     141: ldc2_w        #65                 // long -1l
     144: invokevirtual #166                // Method java/util/concurrent/atomic/AtomicLong.set:(J)V
     147: return
    Exception table:
       from    to  target type
          64    71    74   Class java/lang/IllegalThreadStateException

  public void refreshConfiguration(org.apache.hadoop.conf.Configuration);
    Code:
       0: aload_0
       1: aload_1
       2: putfield      #1                  // Field conf:Lorg/apache/hadoop/conf/Configuration;
       5: aload_0
       6: aload_1
       7: ldc           #214                // String hbase.procedure.worker.keep.alive.time.msec
       9: getstatic     #215                // Field DEFAULT_WORKER_KEEP_ALIVE_TIME:J
      12: invokevirtual #216                // Method org/apache/hadoop/conf/Configuration.getLong:(Ljava/lang/String;J)J
      15: getstatic     #217                // Field java/util/concurrent/TimeUnit.MILLISECONDS:Ljava/util/concurrent/TimeUnit;
      18: invokevirtual #218                // Method setKeepAliveTime:(JLjava/util/concurrent/TimeUnit;)V
      21: return

  public boolean isRunning();
    Code:
       0: aload_0
       1: getfield      #72                 // Field running:Ljava/util/concurrent/atomic/AtomicBoolean;
       4: invokevirtual #219                // Method java/util/concurrent/atomic/AtomicBoolean.get:()Z
       7: ireturn

  public int getWorkerThreadCount();
    Code:
       0: aload_0
       1: getfield      #4                  // Field workerThreads:Ljava/util/concurrent/CopyOnWriteArrayList;
       4: invokevirtual #184                // Method java/util/concurrent/CopyOnWriteArrayList.size:()I
       7: ireturn

  public int getCorePoolSize();
    Code:
       0: aload_0
       1: getfield      #156                // Field corePoolSize:I
       4: ireturn

  public int getActiveExecutorCount();
    Code:
       0: aload_0
       1: getfield      #8                  // Field activeExecutorCount:Ljava/util/concurrent/atomic/AtomicInteger;
       4: invokevirtual #220                // Method java/util/concurrent/atomic/AtomicInteger.get:()I
       7: ireturn

  public TEnvironment getEnvironment();
    Code:
       0: aload_0
       1: getfield      #75                 // Field environment:Ljava/lang/Object;
       4: areturn

  public org.apache.hadoop.hbase.procedure2.store.ProcedureStore getStore();
    Code:
       0: aload_0
       1: getfield      #7                  // Field store:Lorg/apache/hadoop/hbase/procedure2/store/ProcedureStore;
       4: areturn

  org.apache.hadoop.hbase.procedure2.ProcedureScheduler getScheduler();
    Code:
       0: aload_0
       1: getfield      #10                 // Field scheduler:Lorg/apache/hadoop/hbase/procedure2/ProcedureScheduler;
       4: areturn

  public void setKeepAliveTime(long, java.util.concurrent.TimeUnit);
    Code:
       0: aload_0
       1: aload_3
       2: lload_1
       3: invokevirtual #175                // Method java/util/concurrent/TimeUnit.toMillis:(J)J
       6: putfield      #9                  // Field keepAliveTime:J
       9: aload_0
      10: getfield      #10                 // Field scheduler:Lorg/apache/hadoop/hbase/procedure2/ProcedureScheduler;
      13: invokeinterface #155,  1          // InterfaceMethod org/apache/hadoop/hbase/procedure2/ProcedureScheduler.signalAll:()V
      18: return

  public long getKeepAliveTime(java.util.concurrent.TimeUnit);
    Code:
       0: aload_1
       1: aload_0
       2: getfield      #9                  // Field keepAliveTime:J
       5: getstatic     #217                // Field java/util/concurrent/TimeUnit.MILLISECONDS:Ljava/util/concurrent/TimeUnit;
       8: invokevirtual #221                // Method java/util/concurrent/TimeUnit.convert:(JLjava/util/concurrent/TimeUnit;)J
      11: lreturn

  public void addChore(org.apache.hadoop.hbase.procedure2.ProcedureInMemoryChore<TEnvironment>);
    Code:
       0: aload_1
       1: getstatic     #222                // Field org/apache/hadoop/hbase/shaded/protobuf/generated/ProcedureProtos$ProcedureState.WAITING_TIMEOUT:Lorg/apache/hadoop/hbase/shaded/protobuf/generated/ProcedureProtos$ProcedureState;
       4: invokevirtual #223                // Method org/apache/hadoop/hbase/procedure2/ProcedureInMemoryChore.setState:(Lorg/apache/hadoop/hbase/shaded/protobuf/generated/ProcedureProtos$ProcedureState;)V
       7: aload_0
       8: getfield      #165                // Field timeoutExecutor:Lorg/apache/hadoop/hbase/procedure2/TimeoutExecutorThread;
      11: aload_1
      12: invokevirtual #224                // Method org/apache/hadoop/hbase/procedure2/TimeoutExecutorThread.add:(Lorg/apache/hadoop/hbase/procedure2/Procedure;)V
      15: return

  public boolean removeChore(org.apache.hadoop.hbase.procedure2.ProcedureInMemoryChore<TEnvironment>);
    Code:
       0: aload_1
       1: getstatic     #225                // Field org/apache/hadoop/hbase/shaded/protobuf/generated/ProcedureProtos$ProcedureState.SUCCESS:Lorg/apache/hadoop/hbase/shaded/protobuf/generated/ProcedureProtos$ProcedureState;
       4: invokevirtual #223                // Method org/apache/hadoop/hbase/procedure2/ProcedureInMemoryChore.setState:(Lorg/apache/hadoop/hbase/shaded/protobuf/generated/ProcedureProtos$ProcedureState;)V
       7: aload_0
       8: getfield      #165                // Field timeoutExecutor:Lorg/apache/hadoop/hbase/procedure2/TimeoutExecutorThread;
      11: aload_1
      12: invokevirtual #226                // Method org/apache/hadoop/hbase/procedure2/TimeoutExecutorThread.remove:(Lorg/apache/hadoop/hbase/procedure2/Procedure;)Z
      15: ireturn

  public org.apache.hadoop.hbase.util.NonceKey createNonceKey(long, long);
    Code:
       0: lload_3
       1: lconst_0
       2: lcmp
       3: ifne          10
       6: aconst_null
       7: goto          19
      10: new           #228                // class org/apache/hadoop/hbase/util/NonceKey
      13: dup
      14: lload_1
      15: lload_3
      16: invokespecial #229                // Method org/apache/hadoop/hbase/util/NonceKey."<init>":(JJ)V
      19: areturn

  public long registerNonce(org.apache.hadoop.hbase.util.NonceKey);
    Code:
       0: aload_1
       1: ifnonnull     8
       4: ldc2_w        #65                 // long -1l
       7: lreturn
       8: aload_0
       9: getfield      #53                 // Field nonceKeysToProcIdsMap:Ljava/util/concurrent/ConcurrentHashMap;
      12: aload_1
      13: invokevirtual #23                 // Method java/util/concurrent/ConcurrentHashMap.get:(Ljava/lang/Object;)Ljava/lang/Object;
      16: checkcast     #230                // class java/lang/Long
      19: astore_2
      20: aload_2
      21: ifnonnull     53
      24: aload_0
      25: invokespecial #231                // Method nextProcId:()J
      28: lstore_3
      29: aload_0
      30: getfield      #53                 // Field nonceKeysToProcIdsMap:Ljava/util/concurrent/ConcurrentHashMap;
      33: aload_1
      34: lload_3
      35: invokestatic  #22                 // Method java/lang/Long.valueOf:(J)Ljava/lang/Long;
      38: invokevirtual #232                // Method java/util/concurrent/ConcurrentHashMap.putIfAbsent:(Ljava/lang/Object;Ljava/lang/Object;)Ljava/lang/Object;
      41: checkcast     #230                // class java/lang/Long
      44: astore_2
      45: aload_2
      46: ifnonnull     53
      49: ldc2_w        #65                 // long -1l
      52: lreturn
      53: getstatic     #16                 // Field LOG:Lorg/slf4j/Logger;
      56: invokeinterface #233,  1          // InterfaceMethod org/slf4j/Logger.isTraceEnabled:()Z
      61: istore_3
      62: aload_0
      63: invokevirtual #202                // Method isRunning:()Z
      66: ifeq          150
      69: aload_0
      70: getfield      #20                 // Field procedures:Ljava/util/concurrent/ConcurrentHashMap;
      73: aload_2
      74: invokevirtual #234                // Method java/util/concurrent/ConcurrentHashMap.containsKey:(Ljava/lang/Object;)Z
      77: ifne          150
      80: aload_0
      81: getfield      #32                 // Field completed:Ljava/util/concurrent/ConcurrentHashMap;
      84: aload_2
      85: invokevirtual #234                // Method java/util/concurrent/ConcurrentHashMap.containsKey:(Ljava/lang/Object;)Z
      88: ifne          150
      91: aload_0
      92: getfield      #53                 // Field nonceKeysToProcIdsMap:Ljava/util/concurrent/ConcurrentHashMap;
      95: aload_1
      96: invokevirtual #234                // Method java/util/concurrent/ConcurrentHashMap.containsKey:(Ljava/lang/Object;)Z
      99: ifeq          150
     102: iload_3
     103: ifeq          141
     106: getstatic     #16                 // Field LOG:Lorg/slf4j/Logger;
     109: new           #128                // class java/lang/StringBuilder
     112: dup
     113: invokespecial #129                // Method java/lang/StringBuilder."<init>":()V
     116: ldc           #235                // String Waiting for pid=
     118: invokevirtual #131                // Method java/lang/StringBuilder.append:(Ljava/lang/String;)Ljava/lang/StringBuilder;
     121: aload_2
     122: invokevirtual #140                // Method java/lang/Long.longValue:()J
     125: invokevirtual #236                // Method java/lang/StringBuilder.append:(J)Ljava/lang/StringBuilder;
     128: ldc           #237                // String  to be submitted
     130: invokevirtual #131                // Method java/lang/StringBuilder.append:(Ljava/lang/String;)Ljava/lang/StringBuilder;
     133: invokevirtual #133                // Method java/lang/StringBuilder.toString:()Ljava/lang/String;
     136: invokeinterface #238,  2          // InterfaceMethod org/slf4j/Logger.trace:(Ljava/lang/String;)V
     141: ldc2_w        #239                // long 100l
     144: invokestatic  #241                // Method org/apache/hadoop/hbase/util/Threads.sleep:(J)V
     147: goto          62
     150: aload_2
     151: invokevirtual #140                // Method java/lang/Long.longValue:()J
     154: lreturn

  public void unregisterNonceIfProcedureWasNotSubmitted(org.apache.hadoop.hbase.util.NonceKey);
    Code:
       0: aload_1
       1: ifnonnull     5
       4: return
       5: aload_0
       6: getfield      #53                 // Field nonceKeysToProcIdsMap:Ljava/util/concurrent/ConcurrentHashMap;
       9: aload_1
      10: invokevirtual #23                 // Method java/util/concurrent/ConcurrentHashMap.get:(Ljava/lang/Object;)Ljava/lang/Object;
      13: checkcast     #230                // class java/lang/Long
      16: astore_2
      17: aload_2
      18: ifnonnull     22
      21: return
      22: aload_0
      23: getfield      #20                 // Field procedures:Ljava/util/concurrent/ConcurrentHashMap;
      26: aload_2
      27: invokevirtual #234                // Method java/util/concurrent/ConcurrentHashMap.containsKey:(Ljava/lang/Object;)Z
      30: ifne          53
      33: aload_0
      34: getfield      #32                 // Field completed:Ljava/util/concurrent/ConcurrentHashMap;
      37: aload_2
      38: invokevirtual #234                // Method java/util/concurrent/ConcurrentHashMap.containsKey:(Ljava/lang/Object;)Z
      41: ifne          53
      44: aload_0
      45: getfield      #53                 // Field nonceKeysToProcIdsMap:Ljava/util/concurrent/ConcurrentHashMap;
      48: aload_1
      49: invokevirtual #242                // Method java/util/concurrent/ConcurrentHashMap.remove:(Ljava/lang/Object;)Ljava/lang/Object;
      52: pop
      53: return

  public void setFailureResultForNonce(org.apache.hadoop.hbase.util.NonceKey, java.lang.String, org.apache.hadoop.hbase.security.User, java.io.IOException);
    Code:
       0: aload_1
       1: ifnonnull     5
       4: return
       5: aload_0
       6: getfield      #53                 // Field nonceKeysToProcIdsMap:Ljava/util/concurrent/ConcurrentHashMap;
       9: aload_1
      10: invokevirtual #23                 // Method java/util/concurrent/ConcurrentHashMap.get:(Ljava/lang/Object;)Ljava/lang/Object;
      13: checkcast     #230                // class java/lang/Long
      16: astore        5
      18: aload         5
      20: ifnull        35
      23: aload_0
      24: getfield      #32                 // Field completed:Ljava/util/concurrent/ConcurrentHashMap;
      27: aload         5
      29: invokevirtual #234                // Method java/util/concurrent/ConcurrentHashMap.containsKey:(Ljava/lang/Object;)Z
      32: ifeq          36
      35: return
      36: new           #35                 // class org/apache/hadoop/hbase/procedure2/FailedProcedure
      39: dup
      40: aload         5
      42: invokevirtual #140                // Method java/lang/Long.longValue:()J
      45: aload_2
      46: aload_3
      47: aload_1
      48: aload         4
      50: invokespecial #243                // Method org/apache/hadoop/hbase/procedure2/FailedProcedure."<init>":(JLjava/lang/String;Lorg/apache/hadoop/hbase/security/User;Lorg/apache/hadoop/hbase/util/NonceKey;Ljava/io/IOException;)V
      53: astore        6
      55: aload_0
      56: getfield      #32                 // Field completed:Ljava/util/concurrent/ConcurrentHashMap;
      59: aload         5
      61: new           #33                 // class org/apache/hadoop/hbase/procedure2/CompletedProcedureRetainer
      64: dup
      65: aload         6
      67: invokespecial #111                // Method org/apache/hadoop/hbase/procedure2/CompletedProcedureRetainer."<init>":(Lorg/apache/hadoop/hbase/procedure2/Procedure;)V
      70: invokevirtual #232                // Method java/util/concurrent/ConcurrentHashMap.putIfAbsent:(Ljava/lang/Object;Ljava/lang/Object;)Ljava/lang/Object;
      73: pop
      74: return

  public long submitProcedure(org.apache.hadoop.hbase.procedure2.Procedure<TEnvironment>);
    Code:
       0: aload_0
       1: aload_1
       2: aconst_null
       3: invokevirtual #244                // Method submitProcedure:(Lorg/apache/hadoop/hbase/procedure2/Procedure;Lorg/apache/hadoop/hbase/util/NonceKey;)J
       6: lreturn

  public java.util.List<java.lang.Boolean> bypassProcedure(java.util.List<java.lang.Long>, long, boolean, boolean) throws java.io.IOException;
    Code:
       0: new           #124                // class java/util/ArrayList
       3: dup
       4: aload_1
       5: invokeinterface #245,  1          // InterfaceMethod java/util/List.size:()I
      10: invokespecial #125                // Method java/util/ArrayList."<init>":(I)V
      13: astore        6
      15: aload_1
      16: invokeinterface #246,  1          // InterfaceMethod java/util/List.iterator:()Ljava/util/Iterator;
      21: astore        7
      23: aload         7
      25: invokeinterface #188,  1          // InterfaceMethod java/util/Iterator.hasNext:()Z
      30: ifeq          73
      33: aload         7
      35: invokeinterface #189,  1          // InterfaceMethod java/util/Iterator.next:()Ljava/lang/Object;
      40: checkcast     #230                // class java/lang/Long
      43: invokevirtual #140                // Method java/lang/Long.longValue:()J
      46: lstore        8
      48: aload         6
      50: aload_0
      51: lload         8
      53: lload_2
      54: iload         4
      56: iload         5
      58: invokevirtual #247                // Method bypassProcedure:(JJZZ)Z
      61: invokestatic  #248                // Method java/lang/Boolean.valueOf:(Z)Ljava/lang/Boolean;
      64: invokeinterface #142,  2          // InterfaceMethod java/util/List.add:(Ljava/lang/Object;)Z
      69: pop
      70: goto          23
      73: aload         6
      75: areturn

  boolean bypassProcedure(long, long, boolean, boolean) throws java.io.IOException;
    Code:
       0: lload_3
       1: lconst_0
       2: lcmp
       3: ifle          10
       6: iconst_1
       7: goto          11
      10: iconst_0
      11: ldc           #249                // String lockWait should be positive
      13: invokestatic  #85                 // Method org/apache/hbase/thirdparty/com/google/common/base/Preconditions.checkArgument:(ZLjava/lang/Object;)V
      16: aload_0
      17: lload_1
      18: invokevirtual #250                // Method getProcedure:(J)Lorg/apache/hadoop/hbase/procedure2/Procedure;
      21: astore        7
      23: aload         7
      25: ifnonnull     44
      28: getstatic     #16                 // Field LOG:Lorg/slf4j/Logger;
      31: ldc           #251                // String Procedure pid={} does not exist, skipping bypass
      33: lload_1
      34: invokestatic  #22                 // Method java/lang/Long.valueOf:(J)Ljava/lang/Long;
      37: invokeinterface #30,  3           // InterfaceMethod org/slf4j/Logger.debug:(Ljava/lang/String;Ljava/lang/Object;)V
      42: iconst_0
      43: ireturn
      44: getstatic     #16                 // Field LOG:Lorg/slf4j/Logger;
      47: ldc           #252                // String Begin bypass {} with lockWait={}, override={}, recursive={}
      49: iconst_4
      50: anewarray     #253                // class java/lang/Object
      53: dup
      54: iconst_0
      55: aload         7
      57: aastore
      58: dup
      59: iconst_1
      60: lload_3
      61: invokestatic  #22                 // Method java/lang/Long.valueOf:(J)Ljava/lang/Long;
      64: aastore
      65: dup
      66: iconst_2
      67: iload         5
      69: invokestatic  #248                // Method java/lang/Boolean.valueOf:(Z)Ljava/lang/Boolean;
      72: aastore
      73: dup
      74: iconst_3
      75: iload         6
      77: invokestatic  #248                // Method java/lang/Boolean.valueOf:(Z)Ljava/lang/Boolean;
      80: aastore
      81: invokeinterface #254,  3          // InterfaceMethod org/slf4j/Logger.debug:(Ljava/lang/String;[Ljava/lang/Object;)V
      86: aload_0
      87: getfield      #6                  // Field procExecutionLock:Lorg/apache/hadoop/hbase/util/IdLock;
      90: aload         7
      92: invokevirtual #95                 // Method org/apache/hadoop/hbase/procedure2/Procedure.getProcId:()J
      95: lload_3
      96: invokevirtual #255                // Method org/apache/hadoop/hbase/util/IdLock.tryLockEntry:(JJ)Lorg/apache/hadoop/hbase/util/IdLock$Entry;
      99: astore        8
     101: aload         8
     103: ifnonnull     148
     106: iload         5
     108: ifne          148
     111: getstatic     #16                 // Field LOG:Lorg/slf4j/Logger;
     114: ldc_w         #256                // String Waited {} ms, but {} is still running, skipping bypass with force={}
     117: iconst_3
     118: anewarray     #253                // class java/lang/Object
     121: dup
     122: iconst_0
     123: lload_3
     124: invokestatic  #22                 // Method java/lang/Long.valueOf:(J)Ljava/lang/Long;
     127: aastore
     128: dup
     129: iconst_1
     130: aload         7
     132: aastore
     133: dup
     134: iconst_2
     135: iload         5
     137: invokestatic  #248                // Method java/lang/Boolean.valueOf:(Z)Ljava/lang/Boolean;
     140: aastore
     141: invokeinterface #254,  3          // InterfaceMethod org/slf4j/Logger.debug:(Ljava/lang/String;[Ljava/lang/Object;)V
     146: iconst_0
     147: ireturn
     148: aload         8
     150: ifnonnull     188
     153: getstatic     #16                 // Field LOG:Lorg/slf4j/Logger;
     156: ldc_w         #257                // String Waited {} ms, but {} is still running, begin bypass with force={}
     159: iconst_3
     160: anewarray     #253                // class java/lang/Object
     163: dup
     164: iconst_0
     165: lload_3
     166: invokestatic  #22                 // Method java/lang/Long.valueOf:(J)Ljava/lang/Long;
     169: aastore
     170: dup
     171: iconst_1
     172: aload         7
     174: aastore
     175: dup
     176: iconst_2
     177: iload         5
     179: invokestatic  #248                // Method java/lang/Boolean.valueOf:(Z)Ljava/lang/Boolean;
     182: aastore
     183: invokeinterface #254,  3          // InterfaceMethod org/slf4j/Logger.debug:(Ljava/lang/String;[Ljava/lang/Object;)V
     188: aload         7
     190: invokevirtual #25                 // Method org/apache/hadoop/hbase/procedure2/Procedure.isFinished:()Z
     193: ifeq          229
     196: getstatic     #16                 // Field LOG:Lorg/slf4j/Logger;
     199: ldc_w         #258                // String {} is already finished, skipping bypass
     202: aload         7
     204: invokeinterface #30,  3           // InterfaceMethod org/slf4j/Logger.debug:(Ljava/lang/String;Ljava/lang/Object;)V
     209: iconst_0
     210: istore        9
     212: aload         8
     214: ifnull        226
     217: aload_0
     218: getfield      #6                  // Field procExecutionLock:Lorg/apache/hadoop/hbase/util/IdLock;
     221: aload         8
     223: invokevirtual #31                 // Method org/apache/hadoop/hbase/util/IdLock.releaseLockEntry:(Lorg/apache/hadoop/hbase/util/IdLock$Entry;)V
     226: iload         9
     228: ireturn
     229: aload         7
     231: invokevirtual #259                // Method org/apache/hadoop/hbase/procedure2/Procedure.hasChildren:()Z
     234: ifeq          323
     237: iload         6
     239: ifeq          290
     242: getstatic     #16                 // Field LOG:Lorg/slf4j/Logger;
     245: ldc_w         #260                // String Recursive bypass on children of pid={}
     248: aload         7
     250: invokevirtual #95                 // Method org/apache/hadoop/hbase/procedure2/Procedure.getProcId:()J
     253: invokestatic  #22                 // Method java/lang/Long.valueOf:(J)Ljava/lang/Long;
     256: invokeinterface #261,  3          // InterfaceMethod org/slf4j/Logger.info:(Ljava/lang/String;Ljava/lang/Object;)V
     261: aload_0
     262: getfield      #20                 // Field procedures:Ljava/util/concurrent/ConcurrentHashMap;
     265: lconst_1
     266: aload         7
     268: invokedynamic #262,  0            // InvokeDynamic #5:apply:(Lorg/apache/hadoop/hbase/procedure2/Procedure;)Ljava/util/function/Function;
     273: aload_0
     274: lload_3
     275: iload         5
     277: iload         6
     279: invokedynamic #263,  0            // InvokeDynamic #6:accept:(Lorg/apache/hadoop/hbase/procedure2/ProcedureExecutor;JZZ)Ljava/util/function/Consumer;
     284: invokevirtual #264                // Method java/util/concurrent/ConcurrentHashMap.forEachValue:(JLjava/util/function/Function;Ljava/util/function/Consumer;)V
     287: goto          323
     290: getstatic     #16                 // Field LOG:Lorg/slf4j/Logger;
     293: ldc_w         #265                // String {} has children, skipping bypass
     296: aload         7
     298: invokeinterface #30,  3           // InterfaceMethod org/slf4j/Logger.debug:(Ljava/lang/String;Ljava/lang/Object;)V
     303: iconst_0
     304: istore        9
     306: aload         8
     308: ifnull        320
     311: aload_0
     312: getfield      #6                  // Field procExecutionLock:Lorg/apache/hadoop/hbase/util/IdLock;
     315: aload         8
     317: invokevirtual #31                 // Method org/apache/hadoop/hbase/util/IdLock.releaseLockEntry:(Lorg/apache/hadoop/hbase/util/IdLock$Entry;)V
     320: iload         9
     322: ireturn
     323: aload         7
     325: invokevirtual #27                 // Method org/apache/hadoop/hbase/procedure2/Procedure.hasParent:()Z
     328: ifeq          397
     331: aload         7
     333: invokevirtual #122                // Method org/apache/hadoop/hbase/procedure2/Procedure.getState:()Lorg/apache/hadoop/hbase/shaded/protobuf/generated/ProcedureProtos$ProcedureState;
     336: getstatic     #266                // Field org/apache/hadoop/hbase/shaded/protobuf/generated/ProcedureProtos$ProcedureState.RUNNABLE:Lorg/apache/hadoop/hbase/shaded/protobuf/generated/ProcedureProtos$ProcedureState;
     339: if_acmpeq     397
     342: aload         7
     344: invokevirtual #122                // Method org/apache/hadoop/hbase/procedure2/Procedure.getState:()Lorg/apache/hadoop/hbase/shaded/protobuf/generated/ProcedureProtos$ProcedureState;
     347: getstatic     #267                // Field org/apache/hadoop/hbase/shaded/protobuf/generated/ProcedureProtos$ProcedureState.WAITING:Lorg/apache/hadoop/hbase/shaded/protobuf/generated/ProcedureProtos$ProcedureState;
     350: if_acmpeq     397
     353: aload         7
     355: invokevirtual #122                // Method org/apache/hadoop/hbase/procedure2/Procedure.getState:()Lorg/apache/hadoop/hbase/shaded/protobuf/generated/ProcedureProtos$ProcedureState;
     358: getstatic     #222                // Field org/apache/hadoop/hbase/shaded/protobuf/generated/ProcedureProtos$ProcedureState.WAITING_TIMEOUT:Lorg/apache/hadoop/hbase/shaded/protobuf/generated/ProcedureProtos$ProcedureState;
     361: if_acmpeq     397
     364: getstatic     #16                 // Field LOG:Lorg/slf4j/Logger;
     367: ldc_w         #268                // String Bypassing procedures in RUNNABLE, WAITING and WAITING_TIMEOUT states (with no parent), {}
     370: aload         7
     372: invokeinterface #30,  3           // InterfaceMethod org/slf4j/Logger.debug:(Ljava/lang/String;Ljava/lang/Object;)V
     377: iconst_0
     378: istore        9
     380: aload         8
     382: ifnull        394
     385: aload_0
     386: getfield      #6                  // Field procExecutionLock:Lorg/apache/hadoop/hbase/util/IdLock;
     389: aload         8
     391: invokevirtual #31                 // Method org/apache/hadoop/hbase/util/IdLock.releaseLockEntry:(Lorg/apache/hadoop/hbase/util/IdLock$Entry;)V
     394: iload         9
     396: ireturn
     397: aload         7
     399: astore        9
     401: aload         9
     403: ifnull        457
     406: getstatic     #16                 // Field LOG:Lorg/slf4j/Logger;
     409: ldc_w         #269                // String Bypassing {}
     412: aload         9
     414: invokeinterface #30,  3           // InterfaceMethod org/slf4j/Logger.debug:(Ljava/lang/String;Ljava/lang/Object;)V
     419: aload         9
     421: aload_0
     422: invokevirtual #93                 // Method getEnvironment:()Ljava/lang/Object;
     425: invokevirtual #270                // Method org/apache/hadoop/hbase/procedure2/Procedure.bypass:(Ljava/lang/Object;)V
     428: aload_0
     429: getfield      #7                  // Field store:Lorg/apache/hadoop/hbase/procedure2/store/ProcedureStore;
     432: aload         7
     434: invokeinterface #47,  2           // InterfaceMethod org/apache/hadoop/hbase/procedure2/store/ProcedureStore.update:(Lorg/apache/hadoop/hbase/procedure2/Procedure;)V
     439: aload         9
     441: invokevirtual #137                // Method org/apache/hadoop/hbase/procedure2/Procedure.getParentProcId:()J
     444: lstore        10
     446: aload_0
     447: lload         10
     449: invokevirtual #250                // Method getProcedure:(J)Lorg/apache/hadoop/hbase/procedure2/Procedure;
     452: astore        9
     454: goto          401
     457: aload         7
     459: invokevirtual #122                // Method org/apache/hadoop/hbase/procedure2/Procedure.getState:()Lorg/apache/hadoop/hbase/shaded/protobuf/generated/ProcedureProtos$ProcedureState;
     462: getstatic     #267                // Field org/apache/hadoop/hbase/shaded/protobuf/generated/ProcedureProtos$ProcedureState.WAITING:Lorg/apache/hadoop/hbase/shaded/protobuf/generated/ProcedureProtos$ProcedureState;
     465: if_acmpne     487
     468: aload         7
     470: getstatic     #266                // Field org/apache/hadoop/hbase/shaded/protobuf/generated/ProcedureProtos$ProcedureState.RUNNABLE:Lorg/apache/hadoop/hbase/shaded/protobuf/generated/ProcedureProtos$ProcedureState;
     473: invokevirtual #271                // Method org/apache/hadoop/hbase/procedure2/Procedure.setState:(Lorg/apache/hadoop/hbase/shaded/protobuf/generated/ProcedureProtos$ProcedureState;)V
     476: aload_0
     477: getfield      #7                  // Field store:Lorg/apache/hadoop/hbase/procedure2/store/ProcedureStore;
     480: aload         7
     482: invokeinterface #47,  2           // InterfaceMethod org/apache/hadoop/hbase/procedure2/store/ProcedureStore.update:(Lorg/apache/hadoop/hbase/procedure2/Procedure;)V
     487: aload         7
     489: invokevirtual #122                // Method org/apache/hadoop/hbase/procedure2/Procedure.getState:()Lorg/apache/hadoop/hbase/shaded/protobuf/generated/ProcedureProtos$ProcedureState;
     492: getstatic     #222                // Field org/apache/hadoop/hbase/shaded/protobuf/generated/ProcedureProtos$ProcedureState.WAITING_TIMEOUT:Lorg/apache/hadoop/hbase/shaded/protobuf/generated/ProcedureProtos$ProcedureState;
     495: if_acmpne     548
     498: getstatic     #16                 // Field LOG:Lorg/slf4j/Logger;
     501: ldc_w         #272                // String transform procedure {} from WAITING_TIMEOUT to RUNNABLE
     504: aload         7
     506: invokeinterface #30,  3           // InterfaceMethod org/slf4j/Logger.debug:(Ljava/lang/String;Ljava/lang/Object;)V
     511: aload_0
     512: getfield      #165                // Field timeoutExecutor:Lorg/apache/hadoop/hbase/procedure2/TimeoutExecutorThread;
     515: aload         7
     517: invokevirtual #226                // Method org/apache/hadoop/hbase/procedure2/TimeoutExecutorThread.remove:(Lorg/apache/hadoop/hbase/procedure2/Procedure;)Z
     520: ifeq          593
     523: getstatic     #16                 // Field LOG:Lorg/slf4j/Logger;
     526: ldc_w         #273                // String removed procedure {} from timeoutExecutor
     529: aload         7
     531: invokeinterface #30,  3           // InterfaceMethod org/slf4j/Logger.debug:(Ljava/lang/String;Ljava/lang/Object;)V
     536: aload_0
     537: getfield      #165                // Field timeoutExecutor:Lorg/apache/hadoop/hbase/procedure2/TimeoutExecutorThread;
     540: aload         7
     542: invokevirtual #274                // Method org/apache/hadoop/hbase/procedure2/TimeoutExecutorThread.executeTimedoutProcedure:(Lorg/apache/hadoop/hbase/procedure2/Procedure;)V
     545: goto          593
     548: aload         8
     550: ifnull        580
     553: aload_0
     554: getfield      #10                 // Field scheduler:Lorg/apache/hadoop/hbase/procedure2/ProcedureScheduler;
     557: aload         7
     559: invokeinterface #275,  2          // InterfaceMethod org/apache/hadoop/hbase/procedure2/ProcedureScheduler.addFront:(Lorg/apache/hadoop/hbase/procedure2/Procedure;)V
     564: getstatic     #16                 // Field LOG:Lorg/slf4j/Logger;
     567: ldc_w         #276                // String Bypassing {} and its ancestors successfully, adding to queue
     570: aload         7
     572: invokeinterface #30,  3           // InterfaceMethod org/slf4j/Logger.debug:(Ljava/lang/String;Ljava/lang/Object;)V
     577: goto          593
     580: getstatic     #16                 // Field LOG:Lorg/slf4j/Logger;
     583: ldc_w         #277                // String Bypassing {} and its ancestors successfully, but since it is already running, skipping add to queue
     586: aload         7
     588: invokeinterface #30,  3           // InterfaceMethod org/slf4j/Logger.debug:(Ljava/lang/String;Ljava/lang/Object;)V
     593: iconst_1
     594: istore        10
     596: aload         8
     598: ifnull        610
     601: aload_0
     602: getfield      #6                  // Field procExecutionLock:Lorg/apache/hadoop/hbase/util/IdLock;
     605: aload         8
     607: invokevirtual #31                 // Method org/apache/hadoop/hbase/util/IdLock.releaseLockEntry:(Lorg/apache/hadoop/hbase/util/IdLock$Entry;)V
     610: iload         10
     612: ireturn
     613: astore        12
     615: aload         8
     617: ifnull        629
     620: aload_0
     621: getfield      #6                  // Field procExecutionLock:Lorg/apache/hadoop/hbase/util/IdLock;
     624: aload         8
     626: invokevirtual #31                 // Method org/apache/hadoop/hbase/util/IdLock.releaseLockEntry:(Lorg/apache/hadoop/hbase/util/IdLock$Entry;)V
     629: aload         12
     631: athrow
    Exception table:
       from    to  target type
         188   212   613   any
         229   306   613   any
         323   380   613   any
         397   596   613   any
         613   615   613   any

  public long submitProcedure(org.apache.hadoop.hbase.procedure2.Procedure<TEnvironment>, org.apache.hadoop.hbase.util.NonceKey);
    Code:
       0: aload_0
       1: getfield      #13                 // Field lastProcId:Ljava/util/concurrent/atomic/AtomicLong;
       4: invokevirtual #278                // Method java/util/concurrent/atomic/AtomicLong.get:()J
       7: lconst_0
       8: lcmp
       9: iflt          16
      12: iconst_1
      13: goto          17
      16: iconst_0
      17: invokestatic  #279                // Method org/apache/hbase/thirdparty/com/google/common/base/Preconditions.checkArgument:(Z)V
      20: aload_0
      21: aload_1
      22: invokespecial #280                // Method prepareProcedure:(Lorg/apache/hadoop/hbase/procedure2/Procedure;)Lorg/apache/hadoop/hbase/procedure2/Procedure;
      25: pop
      26: aload_2
      27: ifnull        87
      30: aload_0
      31: getfield      #53                 // Field nonceKeysToProcIdsMap:Ljava/util/concurrent/ConcurrentHashMap;
      34: aload_2
      35: invokevirtual #23                 // Method java/util/concurrent/ConcurrentHashMap.get:(Ljava/lang/Object;)Ljava/lang/Object;
      38: checkcast     #230                // class java/lang/Long
      41: astore_3
      42: aload_3
      43: ifnull        50
      46: iconst_1
      47: goto          51
      50: iconst_0
      51: new           #128                // class java/lang/StringBuilder
      54: dup
      55: invokespecial #129                // Method java/lang/StringBuilder."<init>":()V
      58: ldc_w         #281                // String Expected nonceKey=
      61: invokevirtual #131                // Method java/lang/StringBuilder.append:(Ljava/lang/String;)Ljava/lang/StringBuilder;
      64: aload_2
      65: invokevirtual #132                // Method java/lang/StringBuilder.append:(Ljava/lang/Object;)Ljava/lang/StringBuilder;
      68: ldc_w         #282                // String  to be reserved, use registerNonce(); proc=
      71: invokevirtual #131                // Method java/lang/StringBuilder.append:(Ljava/lang/String;)Ljava/lang/StringBuilder;
      74: aload_1
      75: invokevirtual #132                // Method java/lang/StringBuilder.append:(Ljava/lang/Object;)Ljava/lang/StringBuilder;
      78: invokevirtual #133                // Method java/lang/StringBuilder.toString:()Ljava/lang/String;
      81: invokestatic  #85                 // Method org/apache/hbase/thirdparty/com/google/common/base/Preconditions.checkArgument:(ZLjava/lang/Object;)V
      84: goto          95
      87: aload_0
      88: invokespecial #231                // Method nextProcId:()J
      91: invokestatic  #22                 // Method java/lang/Long.valueOf:(J)Ljava/lang/Long;
      94: astore_3
      95: aload_1
      96: aload_2
      97: invokevirtual #283                // Method org/apache/hadoop/hbase/procedure2/Procedure.setNonceKey:(Lorg/apache/hadoop/hbase/util/NonceKey;)V
     100: aload_1
     101: aload_3
     102: invokevirtual #140                // Method java/lang/Long.longValue:()J
     105: invokevirtual #284                // Method org/apache/hadoop/hbase/procedure2/Procedure.setProcId:(J)V
     108: aload_0
     109: getfield      #7                  // Field store:Lorg/apache/hadoop/hbase/procedure2/store/ProcedureStore;
     112: aload_1
     113: aconst_null
     114: invokeinterface #285,  3          // InterfaceMethod org/apache/hadoop/hbase/procedure2/store/ProcedureStore.insert:(Lorg/apache/hadoop/hbase/procedure2/Procedure;[Lorg/apache/hadoop/hbase/procedure2/Procedure;)V
     119: getstatic     #16                 // Field LOG:Lorg/slf4j/Logger;
     122: ldc_w         #286                // String Stored {}
     125: aload_1
     126: invokeinterface #30,  3           // InterfaceMethod org/slf4j/Logger.debug:(Ljava/lang/String;Ljava/lang/Object;)V
     131: aload_0
     132: aload_1
     133: invokespecial #287                // Method pushProcedure:(Lorg/apache/hadoop/hbase/procedure2/Procedure;)J
     136: lreturn

  public void submitProcedures(org.apache.hadoop.hbase.procedure2.Procedure<TEnvironment>[]);
    Code:
       0: aload_0
       1: getfield      #13                 // Field lastProcId:Ljava/util/concurrent/atomic/AtomicLong;
       4: invokevirtual #278                // Method java/util/concurrent/atomic/AtomicLong.get:()J
       7: lconst_0
       8: lcmp
       9: iflt          16
      12: iconst_1
      13: goto          17
      16: iconst_0
      17: invokestatic  #279                // Method org/apache/hbase/thirdparty/com/google/common/base/Preconditions.checkArgument:(Z)V
      20: aload_1
      21: ifnull        29
      24: aload_1
      25: arraylength
      26: ifgt          30
      29: return
      30: iconst_0
      31: istore_2
      32: iload_2
      33: aload_1
      34: arraylength
      35: if_icmpge     58
      38: aload_0
      39: aload_1
      40: iload_2
      41: aaload
      42: invokespecial #280                // Method prepareProcedure:(Lorg/apache/hadoop/hbase/procedure2/Procedure;)Lorg/apache/hadoop/hbase/procedure2/Procedure;
      45: aload_0
      46: invokespecial #231                // Method nextProcId:()J
      49: invokevirtual #284                // Method org/apache/hadoop/hbase/procedure2/Procedure.setProcId:(J)V
      52: iinc          2, 1
      55: goto          32
      58: aload_0
      59: getfield      #7                  // Field store:Lorg/apache/hadoop/hbase/procedure2/store/ProcedureStore;
      62: aload_1
      63: invokeinterface #288,  2          // InterfaceMethod org/apache/hadoop/hbase/procedure2/store/ProcedureStore.insert:([Lorg/apache/hadoop/hbase/procedure2/Procedure;)V
      68: getstatic     #16                 // Field LOG:Lorg/slf4j/Logger;
      71: invokeinterface #289,  1          // InterfaceMethod org/slf4j/Logger.isDebugEnabled:()Z
      76: ifeq          110
      79: getstatic     #16                 // Field LOG:Lorg/slf4j/Logger;
      82: new           #128                // class java/lang/StringBuilder
      85: dup
      86: invokespecial #129                // Method java/lang/StringBuilder."<init>":()V
      89: ldc_w         #290                // String Stored
      92: invokevirtual #131                // Method java/lang/StringBuilder.append:(Ljava/lang/String;)Ljava/lang/StringBuilder;
      95: aload_1
      96: invokestatic  #291                // Method java/util/Arrays.toString:([Ljava/lang/Object;)Ljava/lang/String;
      99: invokevirtual #131                // Method java/lang/StringBuilder.append:(Ljava/lang/String;)Ljava/lang/StringBuilder;
     102: invokevirtual #133                // Method java/lang/StringBuilder.toString:()Ljava/lang/String;
     105: invokeinterface #292,  2          // InterfaceMethod org/slf4j/Logger.debug:(Ljava/lang/String;)V
     110: iconst_0
     111: istore_2
     112: iload_2
     113: aload_1
     114: arraylength
     115: if_icmpge     132
     118: aload_0
     119: aload_1
     120: iload_2
     121: aaload
     122: invokespecial #287                // Method pushProcedure:(Lorg/apache/hadoop/hbase/procedure2/Procedure;)J
     125: pop2
     126: iinc          2, 1
     129: goto          112
     132: return

  public boolean abort(long);
    Code:
       0: aload_0
       1: lload_1
       2: iconst_1
       3: invokevirtual #301                // Method abort:(JZ)Z
       6: ireturn

  public boolean abort(long, boolean);
    Code:
       0: aload_0
       1: getfield      #20                 // Field procedures:Ljava/util/concurrent/ConcurrentHashMap;
       4: lload_1
       5: invokestatic  #22                 // Method java/lang/Long.valueOf:(J)Ljava/lang/Long;
       8: invokevirtual #23                 // Method java/util/concurrent/ConcurrentHashMap.get:(Ljava/lang/Object;)Ljava/lang/Object;
      11: checkcast     #24                 // class org/apache/hadoop/hbase/procedure2/Procedure
      14: astore        4
      16: aload         4
      18: ifnull        45
      21: iload_3
      22: ifne          35
      25: aload         4
      27: invokevirtual #302                // Method org/apache/hadoop/hbase/procedure2/Procedure.wasExecuted:()Z
      30: ifeq          35
      33: iconst_0
      34: ireturn
      35: aload         4
      37: aload_0
      38: invokevirtual #93                 // Method getEnvironment:()Ljava/lang/Object;
      41: invokevirtual #303                // Method org/apache/hadoop/hbase/procedure2/Procedure.abort:(Ljava/lang/Object;)Z
      44: ireturn
      45: iconst_0
      46: ireturn

  public org.apache.hadoop.hbase.procedure2.Procedure<TEnvironment> getProcedure(long);
    Code:
       0: aload_0
       1: getfield      #20                 // Field procedures:Ljava/util/concurrent/ConcurrentHashMap;
       4: lload_1
       5: invokestatic  #22                 // Method java/lang/Long.valueOf:(J)Ljava/lang/Long;
       8: invokevirtual #23                 // Method java/util/concurrent/ConcurrentHashMap.get:(Ljava/lang/Object;)Ljava/lang/Object;
      11: checkcast     #24                 // class org/apache/hadoop/hbase/procedure2/Procedure
      14: areturn

  public <T extends org.apache.hadoop.hbase.procedure2.Procedure<TEnvironment>> T getProcedure(java.lang.Class<T>, long);
    Code:
       0: aload_0
       1: lload_2
       2: invokevirtual #250                // Method getProcedure:(J)Lorg/apache/hadoop/hbase/procedure2/Procedure;
       5: astore        4
       7: aload_1
       8: aload         4
      10: invokevirtual #304                // Method java/lang/Class.isInstance:(Ljava/lang/Object;)Z
      13: ifeq          26
      16: aload_1
      17: aload         4
      19: invokevirtual #305                // Method java/lang/Class.cast:(Ljava/lang/Object;)Ljava/lang/Object;
      22: checkcast     #24                 // class org/apache/hadoop/hbase/procedure2/Procedure
      25: areturn
      26: aconst_null
      27: areturn

  public org.apache.hadoop.hbase.procedure2.Procedure<TEnvironment> getResult(long);
    Code:
       0: aload_0
       1: getfield      #32                 // Field completed:Ljava/util/concurrent/ConcurrentHashMap;
       4: lload_1
       5: invokestatic  #22                 // Method java/lang/Long.valueOf:(J)Ljava/lang/Long;
       8: invokevirtual #23                 // Method java/util/concurrent/ConcurrentHashMap.get:(Ljava/lang/Object;)Ljava/lang/Object;
      11: checkcast     #33                 // class org/apache/hadoop/hbase/procedure2/CompletedProcedureRetainer
      14: astore_3
      15: aload_3
      16: ifnonnull     21
      19: aconst_null
      20: areturn
      21: aload_3
      22: invokevirtual #34                 // Method org/apache/hadoop/hbase/procedure2/CompletedProcedureRetainer.getProcedure:()Lorg/apache/hadoop/hbase/procedure2/Procedure;
      25: areturn

  public boolean isFinished(long);
    Code:
       0: aload_0
       1: getfield      #20                 // Field procedures:Ljava/util/concurrent/ConcurrentHashMap;
       4: lload_1
       5: invokestatic  #22                 // Method java/lang/Long.valueOf:(J)Ljava/lang/Long;
       8: invokevirtual #234                // Method java/util/concurrent/ConcurrentHashMap.containsKey:(Ljava/lang/Object;)Z
      11: ifne          18
      14: iconst_1
      15: goto          19
      18: iconst_0
      19: ireturn

  public boolean isStarted(long);
    Code:
       0: aload_0
       1: getfield      #20                 // Field procedures:Ljava/util/concurrent/ConcurrentHashMap;
       4: lload_1
       5: invokestatic  #22                 // Method java/lang/Long.valueOf:(J)Ljava/lang/Long;
       8: invokevirtual #23                 // Method java/util/concurrent/ConcurrentHashMap.get:(Ljava/lang/Object;)Ljava/lang/Object;
      11: checkcast     #24                 // class org/apache/hadoop/hbase/procedure2/Procedure
      14: astore_3
      15: aload_3
      16: ifnonnull     39
      19: aload_0
      20: getfield      #32                 // Field completed:Ljava/util/concurrent/ConcurrentHashMap;
      23: lload_1
      24: invokestatic  #22                 // Method java/lang/Long.valueOf:(J)Ljava/lang/Long;
      27: invokevirtual #23                 // Method java/util/concurrent/ConcurrentHashMap.get:(Ljava/lang/Object;)Ljava/lang/Object;
      30: ifnull        37
      33: iconst_1
      34: goto          38
      37: iconst_0
      38: ireturn
      39: aload_3
      40: invokevirtual #302                // Method org/apache/hadoop/hbase/procedure2/Procedure.wasExecuted:()Z
      43: ireturn

  public void removeResult(long);
    Code:
       0: aload_0
       1: getfield      #32                 // Field completed:Ljava/util/concurrent/ConcurrentHashMap;
       4: lload_1
       5: invokestatic  #22                 // Method java/lang/Long.valueOf:(J)Ljava/lang/Long;
       8: invokevirtual #23                 // Method java/util/concurrent/ConcurrentHashMap.get:(Ljava/lang/Object;)Ljava/lang/Object;
      11: checkcast     #33                 // class org/apache/hadoop/hbase/procedure2/CompletedProcedureRetainer
      14: astore_3
      15: aload_3
      16: ifnonnull     89
      19: getstatic     #114                // Field $assertionsDisabled:Z
      22: ifne          73
      25: aload_0
      26: getfield      #20                 // Field procedures:Ljava/util/concurrent/ConcurrentHashMap;
      29: lload_1
      30: invokestatic  #22                 // Method java/lang/Long.valueOf:(J)Ljava/lang/Long;
      33: invokevirtual #234                // Method java/util/concurrent/ConcurrentHashMap.containsKey:(Ljava/lang/Object;)Z
      36: ifeq          73
      39: new           #115                // class java/lang/AssertionError
      42: dup
      43: new           #128                // class java/lang/StringBuilder
      46: dup
      47: invokespecial #129                // Method java/lang/StringBuilder."<init>":()V
      50: ldc_w         #306                // String pid=
      53: invokevirtual #131                // Method java/lang/StringBuilder.append:(Ljava/lang/String;)Ljava/lang/StringBuilder;
      56: lload_1
      57: invokevirtual #236                // Method java/lang/StringBuilder.append:(J)Ljava/lang/StringBuilder;
      60: ldc_w         #307                // String  is still running
      63: invokevirtual #131                // Method java/lang/StringBuilder.append:(Ljava/lang/String;)Ljava/lang/StringBuilder;
      66: invokevirtual #133                // Method java/lang/StringBuilder.toString:()Ljava/lang/String;
      69: invokespecial #117                // Method java/lang/AssertionError."<init>":(Ljava/lang/Object;)V
      72: athrow
      73: getstatic     #16                 // Field LOG:Lorg/slf4j/Logger;
      76: ldc_w         #308                // String pid={} already removed by the cleaner.
      79: lload_1
      80: invokestatic  #22                 // Method java/lang/Long.valueOf:(J)Ljava/lang/Long;
      83: invokeinterface #30,  3           // InterfaceMethod org/slf4j/Logger.debug:(Ljava/lang/String;Ljava/lang/Object;)V
      88: return
      89: aload_3
      90: invokestatic  #309                // Method org/apache/hadoop/hbase/util/EnvironmentEdgeManager.currentTime:()J
      93: invokevirtual #310                // Method org/apache/hadoop/hbase/procedure2/CompletedProcedureRetainer.setClientAckTime:(J)V
      96: return

  public org.apache.hadoop.hbase.procedure2.Procedure<TEnvironment> getResultOrProcedure(long);
    Code:
       0: aload_0
       1: getfield      #32                 // Field completed:Ljava/util/concurrent/ConcurrentHashMap;
       4: lload_1
       5: invokestatic  #22                 // Method java/lang/Long.valueOf:(J)Ljava/lang/Long;
       8: invokevirtual #23                 // Method java/util/concurrent/ConcurrentHashMap.get:(Ljava/lang/Object;)Ljava/lang/Object;
      11: checkcast     #33                 // class org/apache/hadoop/hbase/procedure2/CompletedProcedureRetainer
      14: astore_3
      15: aload_3
      16: ifnonnull     34
      19: aload_0
      20: getfield      #20                 // Field procedures:Ljava/util/concurrent/ConcurrentHashMap;
      23: lload_1
      24: invokestatic  #22                 // Method java/lang/Long.valueOf:(J)Ljava/lang/Long;
      27: invokevirtual #23                 // Method java/util/concurrent/ConcurrentHashMap.get:(Ljava/lang/Object;)Ljava/lang/Object;
      30: checkcast     #24                 // class org/apache/hadoop/hbase/procedure2/Procedure
      33: areturn
      34: aload_3
      35: invokevirtual #34                 // Method org/apache/hadoop/hbase/procedure2/CompletedProcedureRetainer.getProcedure:()Lorg/apache/hadoop/hbase/procedure2/Procedure;
      38: areturn

  public boolean isProcedureOwner(long, org.apache.hadoop.hbase.security.User);
    Code:
       0: aload_3
       1: ifnonnull     6
       4: iconst_0
       5: ireturn
       6: aload_0
       7: getfield      #20                 // Field procedures:Ljava/util/concurrent/ConcurrentHashMap;
      10: lload_1
      11: invokestatic  #22                 // Method java/lang/Long.valueOf:(J)Ljava/lang/Long;
      14: invokevirtual #23                 // Method java/util/concurrent/ConcurrentHashMap.get:(Ljava/lang/Object;)Ljava/lang/Object;
      17: checkcast     #24                 // class org/apache/hadoop/hbase/procedure2/Procedure
      20: astore        4
      22: aload         4
      24: ifnull        40
      27: aload         4
      29: invokevirtual #311                // Method org/apache/hadoop/hbase/procedure2/Procedure.getOwner:()Ljava/lang/String;
      32: aload_3
      33: invokevirtual #312                // Method org/apache/hadoop/hbase/security/User.getShortName:()Ljava/lang/String;
      36: invokevirtual #313                // Method java/lang/String.equals:(Ljava/lang/Object;)Z
      39: ireturn
      40: aload_0
      41: getfield      #32                 // Field completed:Ljava/util/concurrent/ConcurrentHashMap;
      44: lload_1
      45: invokestatic  #22                 // Method java/lang/Long.valueOf:(J)Ljava/lang/Long;
      48: invokevirtual #23                 // Method java/util/concurrent/ConcurrentHashMap.get:(Ljava/lang/Object;)Ljava/lang/Object;
      51: checkcast     #33                 // class org/apache/hadoop/hbase/procedure2/CompletedProcedureRetainer
      54: astore        5
      56: aload         5
      58: ifnull        77
      61: aload         5
      63: invokevirtual #34                 // Method org/apache/hadoop/hbase/procedure2/CompletedProcedureRetainer.getProcedure:()Lorg/apache/hadoop/hbase/procedure2/Procedure;
      66: invokevirtual #311                // Method org/apache/hadoop/hbase/procedure2/Procedure.getOwner:()Ljava/lang/String;
      69: aload_3
      70: invokevirtual #312                // Method org/apache/hadoop/hbase/security/User.getShortName:()Ljava/lang/String;
      73: invokevirtual #313                // Method java/lang/String.equals:(Ljava/lang/Object;)Z
      76: ireturn
      77: iconst_0
      78: ireturn

  public java.util.Collection<org.apache.hadoop.hbase.procedure2.Procedure<TEnvironment>> getActiveProceduresNoCopy();
    Code:
       0: aload_0
       1: getfield      #20                 // Field procedures:Ljava/util/concurrent/ConcurrentHashMap;
       4: invokevirtual #104                // Method java/util/concurrent/ConcurrentHashMap.values:()Ljava/util/Collection;
       7: areturn

  public java.util.List<org.apache.hadoop.hbase.procedure2.Procedure<TEnvironment>> getProcedures();
    Code:
       0: new           #124                // class java/util/ArrayList
       3: dup
       4: aload_0
       5: getfield      #20                 // Field procedures:Ljava/util/concurrent/ConcurrentHashMap;
       8: invokevirtual #314                // Method java/util/concurrent/ConcurrentHashMap.size:()I
      11: aload_0
      12: getfield      #32                 // Field completed:Ljava/util/concurrent/ConcurrentHashMap;
      15: invokevirtual #314                // Method java/util/concurrent/ConcurrentHashMap.size:()I
      18: iadd
      19: invokespecial #125                // Method java/util/ArrayList."<init>":(I)V
      22: astore_1
      23: aload_1
      24: aload_0
      25: getfield      #20                 // Field procedures:Ljava/util/concurrent/ConcurrentHashMap;
      28: invokevirtual #104                // Method java/util/concurrent/ConcurrentHashMap.values:()Ljava/util/Collection;
      31: invokeinterface #315,  2          // InterfaceMethod java/util/List.addAll:(Ljava/util/Collection;)Z
      36: pop
      37: aload_0
      38: getfield      #32                 // Field completed:Ljava/util/concurrent/ConcurrentHashMap;
      41: invokevirtual #104                // Method java/util/concurrent/ConcurrentHashMap.values:()Ljava/util/Collection;
      44: invokeinterface #316,  1          // InterfaceMethod java/util/Collection.stream:()Ljava/util/stream/Stream;
      49: invokedynamic #317,  0            // InvokeDynamic #7:apply:()Ljava/util/function/Function;
      54: invokeinterface #318,  2          // InterfaceMethod java/util/stream/Stream.map:(Ljava/util/function/Function;)Ljava/util/stream/Stream;
      59: aload_1
      60: dup
      61: invokevirtual #152                // Method java/lang/Object.getClass:()Ljava/lang/Class;
      64: pop
      65: invokedynamic #319,  0            // InvokeDynamic #8:accept:(Ljava/util/List;)Ljava/util/function/Consumer;
      70: invokeinterface #320,  2          // InterfaceMethod java/util/stream/Stream.forEach:(Ljava/util/function/Consumer;)V
      75: aload_1
      76: areturn

  public void registerListener(org.apache.hadoop.hbase.procedure2.ProcedureExecutor$ProcedureExecutorListener);
    Code:
       0: aload_0
       1: getfield      #56                 // Field listeners:Ljava/util/concurrent/CopyOnWriteArrayList;
       4: aload_1
       5: invokevirtual #169                // Method java/util/concurrent/CopyOnWriteArrayList.add:(Ljava/lang/Object;)Z
       8: pop
       9: return

  public boolean unregisterListener(org.apache.hadoop.hbase.procedure2.ProcedureExecutor$ProcedureExecutorListener);
    Code:
       0: aload_0
       1: getfield      #56                 // Field listeners:Ljava/util/concurrent/CopyOnWriteArrayList;
       4: aload_1
       5: invokevirtual #321                // Method java/util/concurrent/CopyOnWriteArrayList.remove:(Ljava/lang/Object;)Z
       8: ireturn

  protected long getLastProcId();
    Code:
       0: aload_0
       1: getfield      #13                 // Field lastProcId:Ljava/util/concurrent/atomic/AtomicLong;
       4: invokevirtual #278                // Method java/util/concurrent/atomic/AtomicLong.get:()J
       7: lreturn

  public java.util.Set<java.lang.Long> getActiveProcIds();
    Code:
       0: aload_0
       1: getfield      #20                 // Field procedures:Ljava/util/concurrent/ConcurrentHashMap;
       4: invokevirtual #335                // Method java/util/concurrent/ConcurrentHashMap.keySet:()Ljava/util/concurrent/ConcurrentHashMap$KeySetView;
       7: areturn

  java.lang.Long getRootProcedureId(org.apache.hadoop.hbase.procedure2.Procedure<TEnvironment>);
    Code:
       0: aload_0
       1: getfield      #20                 // Field procedures:Ljava/util/concurrent/ConcurrentHashMap;
       4: aload_1
       5: invokestatic  #336                // Method org/apache/hadoop/hbase/procedure2/Procedure.getRootProcedureId:(Ljava/util/Map;Lorg/apache/hadoop/hbase/procedure2/Procedure;)Ljava/lang/Long;
       8: areturn

  org.apache.hadoop.hbase.procedure2.RootProcedureState<TEnvironment> getProcStack(long);
    Code:
       0: aload_0
       1: getfield      #52                 // Field rollbackStack:Ljava/util/concurrent/ConcurrentHashMap;
       4: lload_1
       5: invokestatic  #22                 // Method java/lang/Long.valueOf:(J)Ljava/lang/Long;
       8: invokevirtual #23                 // Method java/util/concurrent/ConcurrentHashMap.get:(Ljava/lang/Object;)Ljava/lang/Object;
      11: checkcast     #118                // class org/apache/hadoop/hbase/procedure2/RootProcedureState
      14: areturn

  org.apache.hadoop.hbase.procedure2.ProcedureScheduler getProcedureScheduler();
    Code:
       0: aload_0
       1: getfield      #10                 // Field scheduler:Lorg/apache/hadoop/hbase/procedure2/ProcedureScheduler;
       4: areturn

  int getCompletedSize();
    Code:
       0: aload_0
       1: getfield      #32                 // Field completed:Ljava/util/concurrent/ConcurrentHashMap;
       4: invokevirtual #314                // Method java/util/concurrent/ConcurrentHashMap.size:()I
       7: ireturn

  public org.apache.hadoop.hbase.util.IdLock getProcExecutionLock();
    Code:
       0: aload_0
       1: getfield      #6                  // Field procExecutionLock:Lorg/apache/hadoop/hbase/util/IdLock;
       4: areturn

  static org.slf4j.Logger access$000();
    Code:
       0: getstatic     #16                 // Field LOG:Lorg/slf4j/Logger;
       3: areturn

  static java.util.concurrent.Executor access$100(org.apache.hadoop.hbase.procedure2.ProcedureExecutor);
    Code:
       0: aload_0
       1: getfield      #15                 // Field forceUpdateExecutor:Ljava/util/concurrent/Executor;
       4: areturn

  static void access$200(org.apache.hadoop.hbase.procedure2.ProcedureExecutor, long) throws java.io.IOException;
    Code:
       0: aload_0
       1: lload_1
       2: invokespecial #14                 // Method forceUpdateProcedure:(J)V
       5: return

  static java.util.concurrent.atomic.AtomicLong access$300(org.apache.hadoop.hbase.procedure2.ProcedureExecutor);
    Code:
       0: aload_0
       1: getfield      #13                 // Field lastProcId:Ljava/util/concurrent/atomic/AtomicLong;
       4: areturn

  static void access$400(org.apache.hadoop.hbase.procedure2.ProcedureExecutor, org.apache.hadoop.hbase.procedure2.store.ProcedureStore$ProcedureIterator, boolean) throws java.io.IOException;
    Code:
       0: aload_0
       1: aload_1
       2: iload_2
       3: invokespecial #12                 // Method loadProcedures:(Lorg/apache/hadoop/hbase/procedure2/store/ProcedureStore$ProcedureIterator;Z)V
       6: return

  static java.util.concurrent.atomic.AtomicLong access$500(org.apache.hadoop.hbase.procedure2.ProcedureExecutor);
    Code:
       0: aload_0
       1: getfield      #11                 // Field workerId:Ljava/util/concurrent/atomic/AtomicLong;
       4: areturn

  static org.apache.hadoop.hbase.procedure2.ProcedureScheduler access$600(org.apache.hadoop.hbase.procedure2.ProcedureExecutor);
    Code:
       0: aload_0
       1: getfield      #10                 // Field scheduler:Lorg/apache/hadoop/hbase/procedure2/ProcedureScheduler;
       4: areturn

  static long access$700(org.apache.hadoop.hbase.procedure2.ProcedureExecutor);
    Code:
       0: aload_0
       1: getfield      #9                  // Field keepAliveTime:J
       4: lreturn

  static java.util.concurrent.atomic.AtomicInteger access$800(org.apache.hadoop.hbase.procedure2.ProcedureExecutor);
    Code:
       0: aload_0
       1: getfield      #8                  // Field activeExecutorCount:Ljava/util/concurrent/atomic/AtomicInteger;
       4: areturn

  static org.apache.hadoop.hbase.procedure2.store.ProcedureStore access$900(org.apache.hadoop.hbase.procedure2.ProcedureExecutor);
    Code:
       0: aload_0
       1: getfield      #7                  // Field store:Lorg/apache/hadoop/hbase/procedure2/store/ProcedureStore;
       4: areturn

  static org.apache.hadoop.hbase.util.IdLock access$1000(org.apache.hadoop.hbase.procedure2.ProcedureExecutor);
    Code:
       0: aload_0
       1: getfield      #6                  // Field procExecutionLock:Lorg/apache/hadoop/hbase/util/IdLock;
       4: areturn

  static void access$1100(org.apache.hadoop.hbase.procedure2.ProcedureExecutor, org.apache.hadoop.hbase.procedure2.Procedure);
    Code:
       0: aload_0
       1: aload_1
       2: invokespecial #5                  // Method executeProcedure:(Lorg/apache/hadoop/hbase/procedure2/Procedure;)V
       5: return

  static java.util.concurrent.CopyOnWriteArrayList access$1200(org.apache.hadoop.hbase.procedure2.ProcedureExecutor);
    Code:
       0: aload_0
       1: getfield      #4                  // Field workerThreads:Ljava/util/concurrent/CopyOnWriteArrayList;
       4: areturn

  static int access$1300(org.apache.hadoop.hbase.procedure2.ProcedureExecutor);
    Code:
       0: aload_0
       1: getfield      #3                  // Field maxPoolSize:I
       4: ireturn

  static java.lang.ThreadGroup access$1400(org.apache.hadoop.hbase.procedure2.ProcedureExecutor);
    Code:
       0: aload_0
       1: getfield      #2                  // Field threadGroup:Ljava/lang/ThreadGroup;
       4: areturn

  static org.apache.hadoop.conf.Configuration access$1500(org.apache.hadoop.hbase.procedure2.ProcedureExecutor);
    Code:
       0: aload_0
       1: getfield      #1                  // Field conf:Lorg/apache/hadoop/conf/Configuration;
       4: areturn

  static {};
    Code:
       0: ldc           #37                 // class org/apache/hadoop/hbase/procedure2/ProcedureExecutor
       2: invokevirtual #471                // Method java/lang/Class.desiredAssertionStatus:()Z
       5: ifne          12
       8: iconst_1
       9: goto          13
      12: iconst_0
      13: putstatic     #114                // Field $assertionsDisabled:Z
      16: ldc           #37                 // class org/apache/hadoop/hbase/procedure2/ProcedureExecutor
      18: invokestatic  #472                // Method org/slf4j/LoggerFactory.getLogger:(Ljava/lang/Class;)Lorg/slf4j/Logger;
      21: putstatic     #16                 // Field LOG:Lorg/slf4j/Logger;
      24: getstatic     #473                // Field java/util/concurrent/TimeUnit.MINUTES:Ljava/util/concurrent/TimeUnit;
      27: lconst_1
      28: invokevirtual #175                // Method java/util/concurrent/TimeUnit.toMillis:(J)J
      31: putstatic     #215                // Field DEFAULT_WORKER_KEEP_ALIVE_TIME:J
      34: return
}
