Compiled from "ProcedureExecutor.java"
class org.apache.hadoop.hbase.procedure2.ProcedureExecutor$WorkerThread extends org.apache.hadoop.hbase.procedure2.StoppableThread {
  final org.apache.hadoop.hbase.procedure2.ProcedureExecutor this$0;

  public org.apache.hadoop.hbase.procedure2.ProcedureExecutor$WorkerThread(org.apache.hadoop.hbase.procedure2.ProcedureExecutor, java.lang.ThreadGroup);
    Code:
       0: aload_0
       1: aload_1
       2: aload_2
       3: ldc           #1                  // String PEWorker-
       5: invokespecial #2                  // Method "<init>":(Lorg/apache/hadoop/hbase/procedure2/ProcedureExecutor;Ljava/lang/ThreadGroup;Ljava/lang/String;)V
       8: return

  protected org.apache.hadoop.hbase.procedure2.ProcedureExecutor$WorkerThread(org.apache.hadoop.hbase.procedure2.ProcedureExecutor, java.lang.ThreadGroup, java.lang.String);
    Code:
       0: aload_0
       1: aload_1
       2: putfield      #3                  // Field this$0:Lorg/apache/hadoop/hbase/procedure2/ProcedureExecutor;
       5: aload_0
       6: aload_2
       7: new           #4                  // class java/lang/StringBuilder
      10: dup
      11: invokespecial #5                  // Method java/lang/StringBuilder."<init>":()V
      14: aload_3
      15: invokevirtual #6                  // Method java/lang/StringBuilder.append:(Ljava/lang/String;)Ljava/lang/StringBuilder;
      18: aload_1
      19: invokestatic  #7                  // Method org/apache/hadoop/hbase/procedure2/ProcedureExecutor.access$500:(Lorg/apache/hadoop/hbase/procedure2/ProcedureExecutor;)Ljava/util/concurrent/atomic/AtomicLong;
      22: invokevirtual #8                  // Method java/util/concurrent/atomic/AtomicLong.incrementAndGet:()J
      25: invokevirtual #9                  // Method java/lang/StringBuilder.append:(J)Ljava/lang/StringBuilder;
      28: invokevirtual #10                 // Method java/lang/StringBuilder.toString:()Ljava/lang/String;
      31: invokespecial #11                 // Method org/apache/hadoop/hbase/procedure2/StoppableThread."<init>":(Ljava/lang/ThreadGroup;Ljava/lang/String;)V
      34: aload_0
      35: new           #12                 // class java/util/concurrent/atomic/AtomicLong
      38: dup
      39: ldc2_w        #14                 // long 9223372036854775807l
      42: invokespecial #16                 // Method java/util/concurrent/atomic/AtomicLong."<init>":(J)V
      45: putfield      #17                 // Field executionStartTime:Ljava/util/concurrent/atomic/AtomicLong;
      48: aload_0
      49: iconst_1
      50: invokevirtual #18                 // Method setDaemon:(Z)V
      53: return

  public void sendStopSignal();
    Code:
       0: aload_0
       1: getfield      #3                  // Field this$0:Lorg/apache/hadoop/hbase/procedure2/ProcedureExecutor;
       4: invokestatic  #19                 // Method org/apache/hadoop/hbase/procedure2/ProcedureExecutor.access$600:(Lorg/apache/hadoop/hbase/procedure2/ProcedureExecutor;)Lorg/apache/hadoop/hbase/procedure2/ProcedureScheduler;
       7: invokeinterface #20,  1           // InterfaceMethod org/apache/hadoop/hbase/procedure2/ProcedureScheduler.signalAll:()V
      12: return

  public void run();
    Code:
       0: invokestatic  #21                 // Method org/apache/hadoop/hbase/util/EnvironmentEdgeManager.currentTime:()J
       3: lstore_1
       4: aload_0
       5: getfield      #3                  // Field this$0:Lorg/apache/hadoop/hbase/procedure2/ProcedureExecutor;
       8: invokevirtual #22                 // Method org/apache/hadoop/hbase/procedure2/ProcedureExecutor.isRunning:()Z
      11: ifeq          405
      14: aload_0
      15: lload_1
      16: invokevirtual #23                 // Method keepAlive:(J)Z
      19: ifeq          405
      22: aload_0
      23: getfield      #3                  // Field this$0:Lorg/apache/hadoop/hbase/procedure2/ProcedureExecutor;
      26: invokestatic  #19                 // Method org/apache/hadoop/hbase/procedure2/ProcedureExecutor.access$600:(Lorg/apache/hadoop/hbase/procedure2/ProcedureExecutor;)Lorg/apache/hadoop/hbase/procedure2/ProcedureScheduler;
      29: aload_0
      30: getfield      #3                  // Field this$0:Lorg/apache/hadoop/hbase/procedure2/ProcedureExecutor;
      33: invokestatic  #24                 // Method org/apache/hadoop/hbase/procedure2/ProcedureExecutor.access$700:(Lorg/apache/hadoop/hbase/procedure2/ProcedureExecutor;)J
      36: getstatic     #25                 // Field java/util/concurrent/TimeUnit.MILLISECONDS:Ljava/util/concurrent/TimeUnit;
      39: invokeinterface #26,  4           // InterfaceMethod org/apache/hadoop/hbase/procedure2/ProcedureScheduler.poll:(JLjava/util/concurrent/TimeUnit;)Lorg/apache/hadoop/hbase/procedure2/Procedure;
      44: astore_3
      45: aload_3
      46: ifnonnull     52
      49: goto          4
      52: aload_0
      53: aload_3
      54: putfield      #27                 // Field activeProcedure:Lorg/apache/hadoop/hbase/procedure2/Procedure;
      57: aload_0
      58: getfield      #3                  // Field this$0:Lorg/apache/hadoop/hbase/procedure2/ProcedureExecutor;
      61: invokestatic  #28                 // Method org/apache/hadoop/hbase/procedure2/ProcedureExecutor.access$800:(Lorg/apache/hadoop/hbase/procedure2/ProcedureExecutor;)Ljava/util/concurrent/atomic/AtomicInteger;
      64: invokevirtual #29                 // Method java/util/concurrent/atomic/AtomicInteger.incrementAndGet:()I
      67: istore        4
      69: aload_0
      70: getfield      #3                  // Field this$0:Lorg/apache/hadoop/hbase/procedure2/ProcedureExecutor;
      73: invokestatic  #30                 // Method org/apache/hadoop/hbase/procedure2/ProcedureExecutor.access$900:(Lorg/apache/hadoop/hbase/procedure2/ProcedureExecutor;)Lorg/apache/hadoop/hbase/procedure2/store/ProcedureStore;
      76: iload         4
      78: invokeinterface #31,  2           // InterfaceMethod org/apache/hadoop/hbase/procedure2/store/ProcedureStore.setRunningProcedureCount:(I)I
      83: istore        5
      85: invokestatic  #32                 // Method org/apache/hadoop/hbase/procedure2/ProcedureExecutor.access$000:()Lorg/slf4j/Logger;
      88: ldc           #33                 // String Execute pid={} runningCount={}, activeCount={}
      90: iconst_3
      91: anewarray     #34                 // class java/lang/Object
      94: dup
      95: iconst_0
      96: aload_3
      97: invokevirtual #35                 // Method org/apache/hadoop/hbase/procedure2/Procedure.getProcId:()J
     100: invokestatic  #36                 // Method java/lang/Long.valueOf:(J)Ljava/lang/Long;
     103: aastore
     104: dup
     105: iconst_1
     106: iload         5
     108: invokestatic  #37                 // Method java/lang/Integer.valueOf:(I)Ljava/lang/Integer;
     111: aastore
     112: dup
     113: iconst_2
     114: iload         4
     116: invokestatic  #37                 // Method java/lang/Integer.valueOf:(I)Ljava/lang/Integer;
     119: aastore
     120: invokeinterface #38,  3           // InterfaceMethod org/slf4j/Logger.trace:(Ljava/lang/String;[Ljava/lang/Object;)V
     125: aload_0
     126: getfield      #17                 // Field executionStartTime:Ljava/util/concurrent/atomic/AtomicLong;
     129: invokestatic  #21                 // Method org/apache/hadoop/hbase/util/EnvironmentEdgeManager.currentTime:()J
     132: invokevirtual #39                 // Method java/util/concurrent/atomic/AtomicLong.set:(J)V
     135: aload_0
     136: getfield      #3                  // Field this$0:Lorg/apache/hadoop/hbase/procedure2/ProcedureExecutor;
     139: invokestatic  #40                 // Method org/apache/hadoop/hbase/procedure2/ProcedureExecutor.access$1000:(Lorg/apache/hadoop/hbase/procedure2/ProcedureExecutor;)Lorg/apache/hadoop/hbase/util/IdLock;
     142: aload_3
     143: invokevirtual #35                 // Method org/apache/hadoop/hbase/procedure2/Procedure.getProcId:()J
     146: invokevirtual #41                 // Method org/apache/hadoop/hbase/util/IdLock.getLockEntry:(J)Lorg/apache/hadoop/hbase/util/IdLock$Entry;
     149: astore        6
     151: aload_0
     152: getfield      #3                  // Field this$0:Lorg/apache/hadoop/hbase/procedure2/ProcedureExecutor;
     155: aload_3
     156: invokestatic  #42                 // Method org/apache/hadoop/hbase/procedure2/ProcedureExecutor.access$1100:(Lorg/apache/hadoop/hbase/procedure2/ProcedureExecutor;Lorg/apache/hadoop/hbase/procedure2/Procedure;)V
     159: aload_0
     160: getfield      #3                  // Field this$0:Lorg/apache/hadoop/hbase/procedure2/ProcedureExecutor;
     163: invokestatic  #40                 // Method org/apache/hadoop/hbase/procedure2/ProcedureExecutor.access$1000:(Lorg/apache/hadoop/hbase/procedure2/ProcedureExecutor;)Lorg/apache/hadoop/hbase/util/IdLock;
     166: aload         6
     168: invokevirtual #43                 // Method org/apache/hadoop/hbase/util/IdLock.releaseLockEntry:(Lorg/apache/hadoop/hbase/util/IdLock$Entry;)V
     171: aload_0
     172: getfield      #3                  // Field this$0:Lorg/apache/hadoop/hbase/procedure2/ProcedureExecutor;
     175: invokestatic  #28                 // Method org/apache/hadoop/hbase/procedure2/ProcedureExecutor.access$800:(Lorg/apache/hadoop/hbase/procedure2/ProcedureExecutor;)Ljava/util/concurrent/atomic/AtomicInteger;
     178: invokevirtual #44                 // Method java/util/concurrent/atomic/AtomicInteger.decrementAndGet:()I
     181: istore        4
     183: aload_0
     184: getfield      #3                  // Field this$0:Lorg/apache/hadoop/hbase/procedure2/ProcedureExecutor;
     187: invokestatic  #30                 // Method org/apache/hadoop/hbase/procedure2/ProcedureExecutor.access$900:(Lorg/apache/hadoop/hbase/procedure2/ProcedureExecutor;)Lorg/apache/hadoop/hbase/procedure2/store/ProcedureStore;
     190: iload         4
     192: invokeinterface #31,  2           // InterfaceMethod org/apache/hadoop/hbase/procedure2/store/ProcedureStore.setRunningProcedureCount:(I)I
     197: istore        5
     199: invokestatic  #32                 // Method org/apache/hadoop/hbase/procedure2/ProcedureExecutor.access$000:()Lorg/slf4j/Logger;
     202: ldc           #45                 // String Halt pid={} runningCount={}, activeCount={}
     204: iconst_3
     205: anewarray     #34                 // class java/lang/Object
     208: dup
     209: iconst_0
     210: aload_3
     211: invokevirtual #35                 // Method org/apache/hadoop/hbase/procedure2/Procedure.getProcId:()J
     214: invokestatic  #36                 // Method java/lang/Long.valueOf:(J)Ljava/lang/Long;
     217: aastore
     218: dup
     219: iconst_1
     220: iload         5
     222: invokestatic  #37                 // Method java/lang/Integer.valueOf:(I)Ljava/lang/Integer;
     225: aastore
     226: dup
     227: iconst_2
     228: iload         4
     230: invokestatic  #37                 // Method java/lang/Integer.valueOf:(I)Ljava/lang/Integer;
     233: aastore
     234: invokeinterface #38,  3           // InterfaceMethod org/slf4j/Logger.trace:(Ljava/lang/String;[Ljava/lang/Object;)V
     239: aload_0
     240: aconst_null
     241: putfield      #27                 // Field activeProcedure:Lorg/apache/hadoop/hbase/procedure2/Procedure;
     244: invokestatic  #21                 // Method org/apache/hadoop/hbase/util/EnvironmentEdgeManager.currentTime:()J
     247: lstore_1
     248: aload_0
     249: getfield      #17                 // Field executionStartTime:Ljava/util/concurrent/atomic/AtomicLong;
     252: ldc2_w        #14                 // long 9223372036854775807l
     255: invokevirtual #39                 // Method java/util/concurrent/atomic/AtomicLong.set:(J)V
     258: goto          402
     261: astore        7
     263: invokestatic  #32                 // Method org/apache/hadoop/hbase/procedure2/ProcedureExecutor.access$000:()Lorg/slf4j/Logger;
     266: new           #4                  // class java/lang/StringBuilder
     269: dup
     270: invokespecial #5                  // Method java/lang/StringBuilder."<init>":()V
     273: ldc           #47                 // String ASSERT pid=
     275: invokevirtual #6                  // Method java/lang/StringBuilder.append:(Ljava/lang/String;)Ljava/lang/StringBuilder;
     278: aload_3
     279: invokevirtual #35                 // Method org/apache/hadoop/hbase/procedure2/Procedure.getProcId:()J
     282: invokevirtual #9                  // Method java/lang/StringBuilder.append:(J)Ljava/lang/StringBuilder;
     285: invokevirtual #10                 // Method java/lang/StringBuilder.toString:()Ljava/lang/String;
     288: aload         7
     290: invokeinterface #48,  3           // InterfaceMethod org/slf4j/Logger.info:(Ljava/lang/String;Ljava/lang/Throwable;)V
     295: aload         7
     297: athrow
     298: astore        8
     300: aload_0
     301: getfield      #3                  // Field this$0:Lorg/apache/hadoop/hbase/procedure2/ProcedureExecutor;
     304: invokestatic  #40                 // Method org/apache/hadoop/hbase/procedure2/ProcedureExecutor.access$1000:(Lorg/apache/hadoop/hbase/procedure2/ProcedureExecutor;)Lorg/apache/hadoop/hbase/util/IdLock;
     307: aload         6
     309: invokevirtual #43                 // Method org/apache/hadoop/hbase/util/IdLock.releaseLockEntry:(Lorg/apache/hadoop/hbase/util/IdLock$Entry;)V
     312: aload_0
     313: getfield      #3                  // Field this$0:Lorg/apache/hadoop/hbase/procedure2/ProcedureExecutor;
     316: invokestatic  #28                 // Method org/apache/hadoop/hbase/procedure2/ProcedureExecutor.access$800:(Lorg/apache/hadoop/hbase/procedure2/ProcedureExecutor;)Ljava/util/concurrent/atomic/AtomicInteger;
     319: invokevirtual #44                 // Method java/util/concurrent/atomic/AtomicInteger.decrementAndGet:()I
     322: istore        4
     324: aload_0
     325: getfield      #3                  // Field this$0:Lorg/apache/hadoop/hbase/procedure2/ProcedureExecutor;
     328: invokestatic  #30                 // Method org/apache/hadoop/hbase/procedure2/ProcedureExecutor.access$900:(Lorg/apache/hadoop/hbase/procedure2/ProcedureExecutor;)Lorg/apache/hadoop/hbase/procedure2/store/ProcedureStore;
     331: iload         4
     333: invokeinterface #31,  2           // InterfaceMethod org/apache/hadoop/hbase/procedure2/store/ProcedureStore.setRunningProcedureCount:(I)I
     338: istore        5
     340: invokestatic  #32                 // Method org/apache/hadoop/hbase/procedure2/ProcedureExecutor.access$000:()Lorg/slf4j/Logger;
     343: ldc           #45                 // String Halt pid={} runningCount={}, activeCount={}
     345: iconst_3
     346: anewarray     #34                 // class java/lang/Object
     349: dup
     350: iconst_0
     351: aload_3
     352: invokevirtual #35                 // Method org/apache/hadoop/hbase/procedure2/Procedure.getProcId:()J
     355: invokestatic  #36                 // Method java/lang/Long.valueOf:(J)Ljava/lang/Long;
     358: aastore
     359: dup
     360: iconst_1
     361: iload         5
     363: invokestatic  #37                 // Method java/lang/Integer.valueOf:(I)Ljava/lang/Integer;
     366: aastore
     367: dup
     368: iconst_2
     369: iload         4
     371: invokestatic  #37                 // Method java/lang/Integer.valueOf:(I)Ljava/lang/Integer;
     374: aastore
     375: invokeinterface #38,  3           // InterfaceMethod org/slf4j/Logger.trace:(Ljava/lang/String;[Ljava/lang/Object;)V
     380: aload_0
     381: aconst_null
     382: putfield      #27                 // Field activeProcedure:Lorg/apache/hadoop/hbase/procedure2/Procedure;
     385: invokestatic  #21                 // Method org/apache/hadoop/hbase/util/EnvironmentEdgeManager.currentTime:()J
     388: lstore_1
     389: aload_0
     390: getfield      #17                 // Field executionStartTime:Ljava/util/concurrent/atomic/AtomicLong;
     393: ldc2_w        #14                 // long 9223372036854775807l
     396: invokevirtual #39                 // Method java/util/concurrent/atomic/AtomicLong.set:(J)V
     399: aload         8
     401: athrow
     402: goto          4
     405: invokestatic  #32                 // Method org/apache/hadoop/hbase/procedure2/ProcedureExecutor.access$000:()Lorg/slf4j/Logger;
     408: ldc           #49                 // String Worker terminated.
     410: invokeinterface #50,  2           // InterfaceMethod org/slf4j/Logger.trace:(Ljava/lang/String;)V
     415: goto          462
     418: astore_3
     419: invokestatic  #32                 // Method org/apache/hadoop/hbase/procedure2/ProcedureExecutor.access$000:()Lorg/slf4j/Logger;
     422: ldc           #52                 // String Worker terminating UNNATURALLY {}
     424: aload_0
     425: getfield      #27                 // Field activeProcedure:Lorg/apache/hadoop/hbase/procedure2/Procedure;
     428: aload_3
     429: invokeinterface #53,  4           // InterfaceMethod org/slf4j/Logger.warn:(Ljava/lang/String;Ljava/lang/Object;Ljava/lang/Object;)V
     434: invokestatic  #32                 // Method org/apache/hadoop/hbase/procedure2/ProcedureExecutor.access$000:()Lorg/slf4j/Logger;
     437: ldc           #49                 // String Worker terminated.
     439: invokeinterface #50,  2           // InterfaceMethod org/slf4j/Logger.trace:(Ljava/lang/String;)V
     444: goto          462
     447: astore        9
     449: invokestatic  #32                 // Method org/apache/hadoop/hbase/procedure2/ProcedureExecutor.access$000:()Lorg/slf4j/Logger;
     452: ldc           #49                 // String Worker terminated.
     454: invokeinterface #50,  2           // InterfaceMethod org/slf4j/Logger.trace:(Ljava/lang/String;)V
     459: aload         9
     461: athrow
     462: aload_0
     463: getfield      #3                  // Field this$0:Lorg/apache/hadoop/hbase/procedure2/ProcedureExecutor;
     466: invokestatic  #54                 // Method org/apache/hadoop/hbase/procedure2/ProcedureExecutor.access$1200:(Lorg/apache/hadoop/hbase/procedure2/ProcedureExecutor;)Ljava/util/concurrent/CopyOnWriteArrayList;
     469: aload_0
     470: invokevirtual #55                 // Method java/util/concurrent/CopyOnWriteArrayList.remove:(Ljava/lang/Object;)Z
     473: pop
     474: return
    Exception table:
       from    to  target type
         151   159   261   Class java/lang/AssertionError
         151   159   298   any
         261   300   298   any
           4   405   418   Class java/lang/Throwable
           4   405   447   any
         418   434   447   any
         447   449   447   any

  public java.lang.String toString();
    Code:
       0: aload_0
       1: getfield      #27                 // Field activeProcedure:Lorg/apache/hadoop/hbase/procedure2/Procedure;
       4: astore_1
       5: new           #4                  // class java/lang/StringBuilder
       8: dup
       9: invokespecial #5                  // Method java/lang/StringBuilder."<init>":()V
      12: aload_0
      13: invokevirtual #56                 // Method getName:()Ljava/lang/String;
      16: invokevirtual #6                  // Method java/lang/StringBuilder.append:(Ljava/lang/String;)Ljava/lang/StringBuilder;
      19: ldc           #57                 // String (pid=
      21: invokevirtual #6                  // Method java/lang/StringBuilder.append:(Ljava/lang/String;)Ljava/lang/StringBuilder;
      24: aload_1
      25: ifnonnull     37
      28: ldc2_w        #59                 // long -1l
      31: invokestatic  #36                 // Method java/lang/Long.valueOf:(J)Ljava/lang/Long;
      34: goto          59
      37: new           #4                  // class java/lang/StringBuilder
      40: dup
      41: invokespecial #5                  // Method java/lang/StringBuilder."<init>":()V
      44: aload_1
      45: invokevirtual #35                 // Method org/apache/hadoop/hbase/procedure2/Procedure.getProcId:()J
      48: invokevirtual #9                  // Method java/lang/StringBuilder.append:(J)Ljava/lang/StringBuilder;
      51: ldc           #61                 // String )
      53: invokevirtual #6                  // Method java/lang/StringBuilder.append:(Ljava/lang/String;)Ljava/lang/StringBuilder;
      56: invokevirtual #10                 // Method java/lang/StringBuilder.toString:()Ljava/lang/String;
      59: invokevirtual #62                 // Method java/lang/StringBuilder.append:(Ljava/lang/Object;)Ljava/lang/StringBuilder;
      62: invokevirtual #10                 // Method java/lang/StringBuilder.toString:()Ljava/lang/String;
      65: areturn

  public long getCurrentRunTime();
    Code:
       0: invokestatic  #21                 // Method org/apache/hadoop/hbase/util/EnvironmentEdgeManager.currentTime:()J
       3: aload_0
       4: getfield      #17                 // Field executionStartTime:Ljava/util/concurrent/atomic/AtomicLong;
       7: invokevirtual #63                 // Method java/util/concurrent/atomic/AtomicLong.get:()J
      10: lsub
      11: lreturn

  protected boolean keepAlive(long);
    Code:
       0: iconst_1
       1: ireturn
}
