Compiled from "ProcedureWALPrettyPrinter.java"
public class org.apache.hadoop.hbase.procedure2.store.wal.ProcedureWALPrettyPrinter extends org.apache.hadoop.conf.Configured implements org.apache.hadoop.util.Tool {
  public org.apache.hadoop.hbase.procedure2.store.wal.ProcedureWALPrettyPrinter();
    Code:
       0: aload_0
       1: invokespecial #1                  // Method org/apache/hadoop/conf/Configured."<init>":()V
       4: aload_0
       5: getstatic     #2                  // Field java/lang/System.out:Ljava/io/PrintStream;
       8: putfield      #3                  // Field out:Ljava/io/PrintStream;
      11: return

  public void processFile(org.apache.hadoop.conf.Configuration, org.apache.hadoop.fs.Path) throws java.io.IOException;
    Code:
       0: aload_2
       1: aload_1
       2: invokevirtual #4                  // Method org/apache/hadoop/fs/Path.getFileSystem:(Lorg/apache/hadoop/conf/Configuration;)Lorg/apache/hadoop/fs/FileSystem;
       5: astore_3
       6: aload_3
       7: aload_2
       8: invokevirtual #5                  // Method org/apache/hadoop/fs/FileSystem.exists:(Lorg/apache/hadoop/fs/Path;)Z
      11: ifne          40
      14: getstatic     #6                  // Field java/lang/System.err:Ljava/io/PrintStream;
      17: new           #7                  // class java/lang/StringBuilder
      20: dup
      21: invokespecial #8                  // Method java/lang/StringBuilder."<init>":()V
      24: ldc           #9                  // String ERROR, file doesnt exist:
      26: invokevirtual #10                 // Method java/lang/StringBuilder.append:(Ljava/lang/String;)Ljava/lang/StringBuilder;
      29: aload_2
      30: invokevirtual #11                 // Method java/lang/StringBuilder.append:(Ljava/lang/Object;)Ljava/lang/StringBuilder;
      33: invokevirtual #12                 // Method java/lang/StringBuilder.toString:()Ljava/lang/String;
      36: invokevirtual #13                 // Method java/io/PrintStream.println:(Ljava/lang/String;)V
      39: return
      40: aload_3
      41: aload_2
      42: invokevirtual #14                 // Method org/apache/hadoop/fs/FileSystem.isFile:(Lorg/apache/hadoop/fs/Path;)Z
      45: ifne          74
      48: getstatic     #6                  // Field java/lang/System.err:Ljava/io/PrintStream;
      51: new           #7                  // class java/lang/StringBuilder
      54: dup
      55: invokespecial #8                  // Method java/lang/StringBuilder."<init>":()V
      58: aload_2
      59: invokevirtual #11                 // Method java/lang/StringBuilder.append:(Ljava/lang/Object;)Ljava/lang/StringBuilder;
      62: ldc           #15                 // String  is not a file
      64: invokevirtual #10                 // Method java/lang/StringBuilder.append:(Ljava/lang/String;)Ljava/lang/StringBuilder;
      67: invokevirtual #12                 // Method java/lang/StringBuilder.toString:()Ljava/lang/String;
      70: invokevirtual #13                 // Method java/io/PrintStream.println:(Ljava/lang/String;)V
      73: return
      74: aload_3
      75: aload_2
      76: invokevirtual #16                 // Method org/apache/hadoop/fs/FileSystem.getFileStatus:(Lorg/apache/hadoop/fs/Path;)Lorg/apache/hadoop/fs/FileStatus;
      79: astore        4
      81: aload         4
      83: invokevirtual #17                 // Method org/apache/hadoop/fs/FileStatus.getLen:()J
      86: lconst_0
      87: lcmp
      88: ifne          118
      91: aload_0
      92: getfield      #3                  // Field out:Ljava/io/PrintStream;
      95: new           #7                  // class java/lang/StringBuilder
      98: dup
      99: invokespecial #8                  // Method java/lang/StringBuilder."<init>":()V
     102: ldc           #18                 // String Zero length file:
     104: invokevirtual #10                 // Method java/lang/StringBuilder.append:(Ljava/lang/String;)Ljava/lang/StringBuilder;
     107: aload_2
     108: invokevirtual #11                 // Method java/lang/StringBuilder.append:(Ljava/lang/Object;)Ljava/lang/StringBuilder;
     111: invokevirtual #12                 // Method java/lang/StringBuilder.toString:()Ljava/lang/String;
     114: invokevirtual #13                 // Method java/io/PrintStream.println:(Ljava/lang/String;)V
     117: return
     118: aload_0
     119: getfield      #3                  // Field out:Ljava/io/PrintStream;
     122: new           #7                  // class java/lang/StringBuilder
     125: dup
     126: invokespecial #8                  // Method java/lang/StringBuilder."<init>":()V
     129: ldc           #19                 // String Opening procedure state-log:
     131: invokevirtual #10                 // Method java/lang/StringBuilder.append:(Ljava/lang/String;)Ljava/lang/StringBuilder;
     134: aload_2
     135: invokevirtual #11                 // Method java/lang/StringBuilder.append:(Ljava/lang/Object;)Ljava/lang/StringBuilder;
     138: invokevirtual #12                 // Method java/lang/StringBuilder.toString:()Ljava/lang/String;
     141: invokevirtual #13                 // Method java/io/PrintStream.println:(Ljava/lang/String;)V
     144: new           #20                 // class org/apache/hadoop/hbase/procedure2/store/wal/ProcedureWALFile
     147: dup
     148: aload_3
     149: aload         4
     151: invokespecial #21                 // Method org/apache/hadoop/hbase/procedure2/store/wal/ProcedureWALFile."<init>":(Lorg/apache/hadoop/fs/FileSystem;Lorg/apache/hadoop/fs/FileStatus;)V
     154: astore        5
     156: aload_0
     157: aload         5
     159: invokevirtual #22                 // Method processProcedureWALFile:(Lorg/apache/hadoop/hbase/procedure2/store/wal/ProcedureWALFile;)V
     162: return

  public void processProcedureWALFile(org.apache.hadoop.hbase.procedure2.store.wal.ProcedureWALFile) throws java.io.IOException;
    Code:
       0: aload_1
       1: invokevirtual #23                 // Method org/apache/hadoop/hbase/procedure2/store/wal/ProcedureWALFile.open:()V
       4: aload_1
       5: invokevirtual #24                 // Method org/apache/hadoop/hbase/procedure2/store/wal/ProcedureWALFile.getHeader:()Lorg/apache/hadoop/hbase/shaded/protobuf/generated/ProcedureProtos$ProcedureWALHeader;
       8: astore_2
       9: aload_0
      10: aload_2
      11: invokespecial #25                 // Method printHeader:(Lorg/apache/hadoop/hbase/shaded/protobuf/generated/ProcedureProtos$ProcedureWALHeader;)V
      14: aload_1
      15: invokevirtual #26                 // Method org/apache/hadoop/hbase/procedure2/store/wal/ProcedureWALFile.getStream:()Lorg/apache/hadoop/fs/FSDataInputStream;
      18: astore_3
      19: iconst_1
      20: istore        4
      22: iload         4
      24: ifeq          99
      27: aload_3
      28: invokestatic  #27                 // Method org/apache/hadoop/hbase/procedure2/store/wal/ProcedureWALFormat.readEntry:(Ljava/io/InputStream;)Lorg/apache/hadoop/hbase/shaded/protobuf/generated/ProcedureProtos$ProcedureWALEntry;
      31: astore        5
      33: aload         5
      35: ifnonnull     53
      38: aload_0
      39: getfield      #3                  // Field out:Ljava/io/PrintStream;
      42: ldc           #28                 // String No more entry, exiting with missing EOF
      44: invokevirtual #13                 // Method java/io/PrintStream.println:(Ljava/lang/String;)V
      47: iconst_0
      48: istore        4
      50: goto          99
      53: getstatic     #29                 // Field org/apache/hadoop/hbase/procedure2/store/wal/ProcedureWALPrettyPrinter$1.$SwitchMap$org$apache$hadoop$hbase$shaded$protobuf$generated$ProcedureProtos$ProcedureWALEntry$Type:[I
      56: aload         5
      58: invokevirtual #30                 // Method org/apache/hadoop/hbase/shaded/protobuf/generated/ProcedureProtos$ProcedureWALEntry.getType:()Lorg/apache/hadoop/hbase/shaded/protobuf/generated/ProcedureProtos$ProcedureWALEntry$Type;
      61: invokevirtual #31                 // Method org/apache/hadoop/hbase/shaded/protobuf/generated/ProcedureProtos$ProcedureWALEntry$Type.ordinal:()I
      64: iaload
      65: lookupswitch  { // 1
                     1: 84
               default: 90
          }
      84: iconst_0
      85: istore        4
      87: goto          96
      90: aload_0
      91: aload         5
      93: invokespecial #32                 // Method printEntry:(Lorg/apache/hadoop/hbase/shaded/protobuf/generated/ProcedureProtos$ProcedureWALEntry;)V
      96: goto          22
      99: aload_1
     100: invokevirtual #33                 // Method org/apache/hadoop/hbase/procedure2/store/wal/ProcedureWALFile.close:()V
     103: goto          154
     106: astore        4
     108: aload_0
     109: getfield      #3                  // Field out:Ljava/io/PrintStream;
     112: new           #7                  // class java/lang/StringBuilder
     115: dup
     116: invokespecial #8                  // Method java/lang/StringBuilder."<init>":()V
     119: ldc           #35                 // String got an exception while reading the procedure WAL
     121: invokevirtual #10                 // Method java/lang/StringBuilder.append:(Ljava/lang/String;)Ljava/lang/StringBuilder;
     124: aload         4
     126: invokevirtual #36                 // Method java/io/IOException.getMessage:()Ljava/lang/String;
     129: invokevirtual #10                 // Method java/lang/StringBuilder.append:(Ljava/lang/String;)Ljava/lang/StringBuilder;
     132: invokevirtual #12                 // Method java/lang/StringBuilder.toString:()Ljava/lang/String;
     135: invokevirtual #13                 // Method java/io/PrintStream.println:(Ljava/lang/String;)V
     138: aload_1
     139: invokevirtual #33                 // Method org/apache/hadoop/hbase/procedure2/store/wal/ProcedureWALFile.close:()V
     142: goto          154
     145: astore        6
     147: aload_1
     148: invokevirtual #33                 // Method org/apache/hadoop/hbase/procedure2/store/wal/ProcedureWALFile.close:()V
     151: aload         6
     153: athrow
     154: return
    Exception table:
       from    to  target type
          19    99   106   Class java/io/IOException
          19    99   145   any
         106   138   145   any
         145   147   145   any

  public int run(java.lang.String[]) throws java.io.IOException;
    Code:
       0: new           #55                 // class org/apache/hbase/thirdparty/org/apache/commons/cli/Options
       3: dup
       4: invokespecial #56                 // Method org/apache/hbase/thirdparty/org/apache/commons/cli/Options."<init>":()V
       7: astore_2
       8: aload_2
       9: ldc           #57                 // String h
      11: ldc           #58                 // String help
      13: iconst_0
      14: ldc           #59                 // String Output help message
      16: invokevirtual #60                 // Method org/apache/hbase/thirdparty/org/apache/commons/cli/Options.addOption:(Ljava/lang/String;Ljava/lang/String;ZLjava/lang/String;)Lorg/apache/hbase/thirdparty/org/apache/commons/cli/Options;
      19: pop
      20: aload_2
      21: ldc           #61                 // String f
      23: ldc           #62                 // String file
      25: iconst_1
      26: ldc           #63                 // String File to print
      28: invokevirtual #60                 // Method org/apache/hbase/thirdparty/org/apache/commons/cli/Options.addOption:(Ljava/lang/String;Ljava/lang/String;ZLjava/lang/String;)Lorg/apache/hbase/thirdparty/org/apache/commons/cli/Options;
      31: pop
      32: new           #64                 // class java/util/ArrayList
      35: dup
      36: invokespecial #65                 // Method java/util/ArrayList."<init>":()V
      39: astore_3
      40: new           #66                 // class org/apache/hbase/thirdparty/org/apache/commons/cli/DefaultParser
      43: dup
      44: invokespecial #67                 // Method org/apache/hbase/thirdparty/org/apache/commons/cli/DefaultParser."<init>":()V
      47: aload_2
      48: aload_1
      49: invokevirtual #68                 // Method org/apache/hbase/thirdparty/org/apache/commons/cli/DefaultParser.parse:(Lorg/apache/hbase/thirdparty/org/apache/commons/cli/Options;[Ljava/lang/String;)Lorg/apache/hbase/thirdparty/org/apache/commons/cli/CommandLine;
      52: astore        4
      54: aload         4
      56: ldc           #61                 // String f
      58: invokevirtual #69                 // Method org/apache/hbase/thirdparty/org/apache/commons/cli/CommandLine.hasOption:(Ljava/lang/String;)Z
      61: ifeq          85
      64: aload_3
      65: new           #70                 // class org/apache/hadoop/fs/Path
      68: dup
      69: aload         4
      71: ldc           #61                 // String f
      73: invokevirtual #71                 // Method org/apache/hbase/thirdparty/org/apache/commons/cli/CommandLine.getOptionValue:(Ljava/lang/String;)Ljava/lang/String;
      76: invokespecial #72                 // Method org/apache/hadoop/fs/Path."<init>":(Ljava/lang/String;)V
      79: invokeinterface #73,  2           // InterfaceMethod java/util/List.add:(Ljava/lang/Object;)Z
      84: pop
      85: aload_3
      86: invokeinterface #74,  1           // InterfaceMethod java/util/List.isEmpty:()Z
      91: ifne          104
      94: aload         4
      96: ldc           #57                 // String h
      98: invokevirtual #69                 // Method org/apache/hbase/thirdparty/org/apache/commons/cli/CommandLine.hasOption:(Ljava/lang/String;)Z
     101: ifeq          124
     104: new           #75                 // class org/apache/hbase/thirdparty/org/apache/commons/cli/HelpFormatter
     107: dup
     108: invokespecial #76                 // Method org/apache/hbase/thirdparty/org/apache/commons/cli/HelpFormatter."<init>":()V
     111: astore        5
     113: aload         5
     115: ldc           #77                 // String ProcedureWALPrettyPrinter
     117: aload_2
     118: iconst_1
     119: invokevirtual #78                 // Method org/apache/hbase/thirdparty/org/apache/commons/cli/HelpFormatter.printHelp:(Ljava/lang/String;Lorg/apache/hbase/thirdparty/org/apache/commons/cli/Options;Z)V
     122: iconst_m1
     123: ireturn
     124: goto          161
     127: astore        4
     129: getstatic     #80                 // Field LOG:Lorg/slf4j/Logger;
     132: ldc           #81                 // String Failed to parse commandLine arguments
     134: aload         4
     136: invokeinterface #82,  3           // InterfaceMethod org/slf4j/Logger.error:(Ljava/lang/String;Ljava/lang/Throwable;)V
     141: new           #75                 // class org/apache/hbase/thirdparty/org/apache/commons/cli/HelpFormatter
     144: dup
     145: invokespecial #76                 // Method org/apache/hbase/thirdparty/org/apache/commons/cli/HelpFormatter."<init>":()V
     148: astore        5
     150: aload         5
     152: ldc           #77                 // String ProcedureWALPrettyPrinter
     154: aload_2
     155: iconst_1
     156: invokevirtual #78                 // Method org/apache/hbase/thirdparty/org/apache/commons/cli/HelpFormatter.printHelp:(Ljava/lang/String;Lorg/apache/hbase/thirdparty/org/apache/commons/cli/Options;Z)V
     159: iconst_m1
     160: ireturn
     161: aload_3
     162: invokeinterface #83,  1           // InterfaceMethod java/util/List.iterator:()Ljava/util/Iterator;
     167: astore        4
     169: aload         4
     171: invokeinterface #84,  1           // InterfaceMethod java/util/Iterator.hasNext:()Z
     176: ifeq          204
     179: aload         4
     181: invokeinterface #85,  1           // InterfaceMethod java/util/Iterator.next:()Ljava/lang/Object;
     186: checkcast     #70                 // class org/apache/hadoop/fs/Path
     189: astore        5
     191: aload_0
     192: aload_0
     193: invokevirtual #86                 // Method getConf:()Lorg/apache/hadoop/conf/Configuration;
     196: aload         5
     198: invokevirtual #87                 // Method processFile:(Lorg/apache/hadoop/conf/Configuration;Lorg/apache/hadoop/fs/Path;)V
     201: goto          169
     204: iconst_0
     205: ireturn
    Exception table:
       from    to  target type
          40   123   127   Class org/apache/hbase/thirdparty/org/apache/commons/cli/ParseException

  public static void main(java.lang.String[]) throws java.lang.Exception;
    Code:
       0: invokestatic  #88                 // Method org/apache/hadoop/hbase/HBaseConfiguration.create:()Lorg/apache/hadoop/conf/Configuration;
       3: astore_1
       4: aload_1
       5: new           #89                 // class org/apache/hadoop/hbase/procedure2/store/wal/ProcedureWALPrettyPrinter
       8: dup
       9: invokespecial #90                 // Method "<init>":()V
      12: aload_0
      13: invokestatic  #91                 // Method org/apache/hadoop/util/ToolRunner.run:(Lorg/apache/hadoop/conf/Configuration;Lorg/apache/hadoop/util/Tool;[Ljava/lang/String;)I
      16: istore_2
      17: iload_2
      18: invokestatic  #92                 // Method java/lang/System.exit:(I)V
      21: return

  static {};
    Code:
       0: ldc           #89                 // class org/apache/hadoop/hbase/procedure2/store/wal/ProcedureWALPrettyPrinter
       2: invokestatic  #93                 // Method org/slf4j/LoggerFactory.getLogger:(Ljava/lang/Class;)Lorg/slf4j/Logger;
       5: putstatic     #80                 // Field LOG:Lorg/slf4j/Logger;
       8: return
}
