Compiled from "ProfileOutputServlet.java"
public class org.apache.hadoop.hbase.http.ProfileOutputServlet extends org.eclipse.jetty.servlet.DefaultServlet {
  public org.apache.hadoop.hbase.http.ProfileOutputServlet();
    Code:
       0: aload_0
       1: invokespecial #1                  // Method org/eclipse/jetty/servlet/DefaultServlet."<init>":()V
       4: return

  protected void doGet(javax.servlet.http.HttpServletRequest, javax.servlet.http.HttpServletResponse) throws javax.servlet.ServletException, java.io.IOException;
    Code:
       0: aload_0
       1: invokevirtual #2                  // Method getServletContext:()Ljavax/servlet/ServletContext;
       4: aload_1
       5: invokeinterface #3,  1            // InterfaceMethod javax/servlet/http/HttpServletRequest.getPathInfo:()Ljava/lang/String;
      10: invokeinterface #4,  2            // InterfaceMethod javax/servlet/ServletContext.getRealPath:(Ljava/lang/String;)Ljava/lang/String;
      15: astore_3
      16: new           #5                  // class java/io/File
      19: dup
      20: aload_3
      21: invokespecial #6                  // Method java/io/File."<init>":(Ljava/lang/String;)V
      24: astore        4
      26: aload         4
      28: invokevirtual #7                  // Method java/io/File.length:()J
      31: ldc2_w        #8                  // long 100l
      34: lcmp
      35: ifge          181
      38: getstatic     #10                 // Field LOG:Lorg/slf4j/Logger;
      41: new           #11                 // class java/lang/StringBuilder
      44: dup
      45: invokespecial #12                 // Method java/lang/StringBuilder."<init>":()V
      48: aload         4
      50: invokevirtual #13                 // Method java/lang/StringBuilder.append:(Ljava/lang/Object;)Ljava/lang/StringBuilder;
      53: ldc           #14                 // String  is incomplete. Sending auto-refresh header.
      55: invokevirtual #15                 // Method java/lang/StringBuilder.append:(Ljava/lang/String;)Ljava/lang/StringBuilder;
      58: invokevirtual #16                 // Method java/lang/StringBuilder.toString:()Ljava/lang/String;
      61: invokeinterface #17,  2           // InterfaceMethod org/slf4j/Logger.info:(Ljava/lang/String;)V
      66: aload_1
      67: invokeinterface #18,  1           // InterfaceMethod javax/servlet/http/HttpServletRequest.getRequestURI:()Ljava/lang/String;
      72: astore        5
      74: aload_1
      75: invokeinterface #19,  1           // InterfaceMethod javax/servlet/http/HttpServletRequest.getQueryString:()Ljava/lang/String;
      80: ifnull        117
      83: new           #11                 // class java/lang/StringBuilder
      86: dup
      87: invokespecial #12                 // Method java/lang/StringBuilder."<init>":()V
      90: aload         5
      92: invokevirtual #15                 // Method java/lang/StringBuilder.append:(Ljava/lang/String;)Ljava/lang/StringBuilder;
      95: ldc           #20                 // String ?
      97: invokevirtual #15                 // Method java/lang/StringBuilder.append:(Ljava/lang/String;)Ljava/lang/StringBuilder;
     100: aload_1
     101: invokeinterface #19,  1           // InterfaceMethod javax/servlet/http/HttpServletRequest.getQueryString:()Ljava/lang/String;
     106: invokestatic  #21                 // Method sanitize:(Ljava/lang/String;)Ljava/lang/String;
     109: invokevirtual #15                 // Method java/lang/StringBuilder.append:(Ljava/lang/String;)Ljava/lang/StringBuilder;
     112: invokevirtual #16                 // Method java/lang/StringBuilder.toString:()Ljava/lang/String;
     115: astore        5
     117: aload_2
     118: invokestatic  #22                 // Method org/apache/hadoop/hbase/http/ProfileServlet.setResponseHeader:(Ljavax/servlet/http/HttpServletResponse;)V
     121: aload_2
     122: ldc           #23                 // String Refresh
     124: new           #11                 // class java/lang/StringBuilder
     127: dup
     128: invokespecial #12                 // Method java/lang/StringBuilder."<init>":()V
     131: ldc           #25                 // String 2;
     133: invokevirtual #15                 // Method java/lang/StringBuilder.append:(Ljava/lang/String;)Ljava/lang/StringBuilder;
     136: aload         5
     138: invokevirtual #15                 // Method java/lang/StringBuilder.append:(Ljava/lang/String;)Ljava/lang/StringBuilder;
     141: invokevirtual #16                 // Method java/lang/StringBuilder.toString:()Ljava/lang/String;
     144: invokeinterface #26,  3           // InterfaceMethod javax/servlet/http/HttpServletResponse.setHeader:(Ljava/lang/String;Ljava/lang/String;)V
     149: aload_2
     150: invokeinterface #27,  1           // InterfaceMethod javax/servlet/http/HttpServletResponse.getWriter:()Ljava/io/PrintWriter;
     155: new           #11                 // class java/lang/StringBuilder
     158: dup
     159: invokespecial #12                 // Method java/lang/StringBuilder."<init>":()V
     162: ldc           #28                 // String This page will be auto-refreshed every 2 seconds until the output file is ready. Redirecting to
     164: invokevirtual #15                 // Method java/lang/StringBuilder.append:(Ljava/lang/String;)Ljava/lang/StringBuilder;
     167: aload         5
     169: invokevirtual #15                 // Method java/lang/StringBuilder.append:(Ljava/lang/String;)Ljava/lang/StringBuilder;
     172: invokevirtual #16                 // Method java/lang/StringBuilder.toString:()Ljava/lang/String;
     175: invokevirtual #29                 // Method java/io/PrintWriter.write:(Ljava/lang/String;)V
     178: goto          187
     181: aload_0
     182: aload_1
     183: aload_2
     184: invokespecial #30                 // Method org/eclipse/jetty/servlet/DefaultServlet.doGet:(Ljavax/servlet/http/HttpServletRequest;Ljavax/servlet/http/HttpServletResponse;)V
     187: return

  static java.lang.String sanitize(java.lang.String);
    Code:
       0: getstatic     #31                 // Field ALPHA_NUMERIC:Ljava/util/regex/Pattern;
       3: aload_0
       4: invokevirtual #32                 // Method java/util/regex/Pattern.matcher:(Ljava/lang/CharSequence;)Ljava/util/regex/Matcher;
       7: invokevirtual #33                 // Method java/util/regex/Matcher.matches:()Z
      10: ifeq          15
      13: aload_0
      14: areturn
      15: new           #34                 // class java/lang/RuntimeException
      18: dup
      19: ldc           #35                 // String Non-alphanumeric data found in input, aborting.
      21: invokespecial #36                 // Method java/lang/RuntimeException."<init>":(Ljava/lang/String;)V
      24: athrow

  static {};
    Code:
       0: ldc           #24                 // class org/apache/hadoop/hbase/http/ProfileOutputServlet
       2: invokestatic  #37                 // Method org/slf4j/LoggerFactory.getLogger:(Ljava/lang/Class;)Lorg/slf4j/Logger;
       5: putstatic     #10                 // Field LOG:Lorg/slf4j/Logger;
       8: ldc           #38                 // String [a-zA-Z0-9\%\=\&]*
      10: invokestatic  #39                 // Method java/util/regex/Pattern.compile:(Ljava/lang/String;)Ljava/util/regex/Pattern;
      13: putstatic     #31                 // Field ALPHA_NUMERIC:Ljava/util/regex/Pattern;
      16: return
}
