Compiled from "ProfileServlet.java"
final class org.apache.hadoop.hbase.http.ProfileServlet$Output extends java.lang.Enum<org.apache.hadoop.hbase.http.ProfileServlet$Output> {
  public static final org.apache.hadoop.hbase.http.ProfileServlet$Output SUMMARY;

  public static final org.apache.hadoop.hbase.http.ProfileServlet$Output TRACES;

  public static final org.apache.hadoop.hbase.http.ProfileServlet$Output FLAT;

  public static final org.apache.hadoop.hbase.http.ProfileServlet$Output COLLAPSED;

  public static final org.apache.hadoop.hbase.http.ProfileServlet$Output SVG;

  public static final org.apache.hadoop.hbase.http.ProfileServlet$Output TREE;

  public static final org.apache.hadoop.hbase.http.ProfileServlet$Output JFR;

  public static org.apache.hadoop.hbase.http.ProfileServlet$Output[] values();
    Code:
       0: getstatic     #1                  // Field $VALUES:[Lorg/apache/hadoop/hbase/http/ProfileServlet$Output;
       3: invokevirtual #2                  // Method "[Lorg/apache/hadoop/hbase/http/ProfileServlet$Output;".clone:()Ljava/lang/Object;
       6: checkcast     #3                  // class "[Lorg/apache/hadoop/hbase/http/ProfileServlet$Output;"
       9: areturn

  public static org.apache.hadoop.hbase.http.ProfileServlet$Output valueOf(java.lang.String);
    Code:
       0: ldc           #4                  // class org/apache/hadoop/hbase/http/ProfileServlet$Output
       2: aload_0
       3: invokestatic  #5                  // Method java/lang/Enum.valueOf:(Ljava/lang/Class;Ljava/lang/String;)Ljava/lang/Enum;
       6: checkcast     #4                  // class org/apache/hadoop/hbase/http/ProfileServlet$Output
       9: areturn

  static {};
    Code:
       0: new           #4                  // class org/apache/hadoop/hbase/http/ProfileServlet$Output
       3: dup
       4: ldc           #7                  // String SUMMARY
       6: iconst_0
       7: invokespecial #8                  // Method "<init>":(Ljava/lang/String;I)V
      10: putstatic     #9                  // Field SUMMARY:Lorg/apache/hadoop/hbase/http/ProfileServlet$Output;
      13: new           #4                  // class org/apache/hadoop/hbase/http/ProfileServlet$Output
      16: dup
      17: ldc           #10                 // String TRACES
      19: iconst_1
      20: invokespecial #8                  // Method "<init>":(Ljava/lang/String;I)V
      23: putstatic     #11                 // Field TRACES:Lorg/apache/hadoop/hbase/http/ProfileServlet$Output;
      26: new           #4                  // class org/apache/hadoop/hbase/http/ProfileServlet$Output
      29: dup
      30: ldc           #12                 // String FLAT
      32: iconst_2
      33: invokespecial #8                  // Method "<init>":(Ljava/lang/String;I)V
      36: putstatic     #13                 // Field FLAT:Lorg/apache/hadoop/hbase/http/ProfileServlet$Output;
      39: new           #4                  // class org/apache/hadoop/hbase/http/ProfileServlet$Output
      42: dup
      43: ldc           #14                 // String COLLAPSED
      45: iconst_3
      46: invokespecial #8                  // Method "<init>":(Ljava/lang/String;I)V
      49: putstatic     #15                 // Field COLLAPSED:Lorg/apache/hadoop/hbase/http/ProfileServlet$Output;
      52: new           #4                  // class org/apache/hadoop/hbase/http/ProfileServlet$Output
      55: dup
      56: ldc           #16                 // String SVG
      58: iconst_4
      59: invokespecial #8                  // Method "<init>":(Ljava/lang/String;I)V
      62: putstatic     #17                 // Field SVG:Lorg/apache/hadoop/hbase/http/ProfileServlet$Output;
      65: new           #4                  // class org/apache/hadoop/hbase/http/ProfileServlet$Output
      68: dup
      69: ldc           #18                 // String TREE
      71: iconst_5
      72: invokespecial #8                  // Method "<init>":(Ljava/lang/String;I)V
      75: putstatic     #19                 // Field TREE:Lorg/apache/hadoop/hbase/http/ProfileServlet$Output;
      78: new           #4                  // class org/apache/hadoop/hbase/http/ProfileServlet$Output
      81: dup
      82: ldc           #20                 // String JFR
      84: bipush        6
      86: invokespecial #8                  // Method "<init>":(Ljava/lang/String;I)V
      89: putstatic     #21                 // Field JFR:Lorg/apache/hadoop/hbase/http/ProfileServlet$Output;
      92: bipush        7
      94: anewarray     #4                  // class org/apache/hadoop/hbase/http/ProfileServlet$Output
      97: dup
      98: iconst_0
      99: getstatic     #9                  // Field SUMMARY:Lorg/apache/hadoop/hbase/http/ProfileServlet$Output;
     102: aastore
     103: dup
     104: iconst_1
     105: getstatic     #11                 // Field TRACES:Lorg/apache/hadoop/hbase/http/ProfileServlet$Output;
     108: aastore
     109: dup
     110: iconst_2
     111: getstatic     #13                 // Field FLAT:Lorg/apache/hadoop/hbase/http/ProfileServlet$Output;
     114: aastore
     115: dup
     116: iconst_3
     117: getstatic     #15                 // Field COLLAPSED:Lorg/apache/hadoop/hbase/http/ProfileServlet$Output;
     120: aastore
     121: dup
     122: iconst_4
     123: getstatic     #17                 // Field SVG:Lorg/apache/hadoop/hbase/http/ProfileServlet$Output;
     126: aastore
     127: dup
     128: iconst_5
     129: getstatic     #19                 // Field TREE:Lorg/apache/hadoop/hbase/http/ProfileServlet$Output;
     132: aastore
     133: dup
     134: bipush        6
     136: getstatic     #21                 // Field JFR:Lorg/apache/hadoop/hbase/http/ProfileServlet$Output;
     139: aastore
     140: putstatic     #1                  // Field $VALUES:[Lorg/apache/hadoop/hbase/http/ProfileServlet$Output;
     143: return
}
