Compiled from "QosTestHelper.java"
public class org.apache.hadoop.hbase.QosTestHelper {
  public org.apache.hadoop.hbase.QosTestHelper();
    Code:
       0: aload_0
       1: invokespecial #1                  // Method java/lang/Object."<init>":()V
       4: return

  protected void checkMethod(org.apache.hadoop.conf.Configuration, java.lang.String, int, org.apache.hadoop.hbase.regionserver.AnnotationReadingPriorityFunction);
    Code:
       0: aload_0
       1: aload_1
       2: aload_2
       3: iload_3
       4: aload         4
       6: aconst_null
       7: invokevirtual #2                  // Method checkMethod:(Lorg/apache/hadoop/conf/Configuration;Ljava/lang/String;ILorg/apache/hadoop/hbase/regionserver/AnnotationReadingPriorityFunction;Lorg/apache/hbase/thirdparty/com/google/protobuf/Message;)V
      10: return

  protected void checkMethod(org.apache.hadoop.conf.Configuration, java.lang.String, int, org.apache.hadoop.hbase.regionserver.AnnotationReadingPriorityFunction, org.apache.hbase.thirdparty.com.google.protobuf.Message);
    Code:
       0: invokestatic  #3                  // Method org/apache/hadoop/hbase/shaded/protobuf/generated/RPCProtos$RequestHeader.newBuilder:()Lorg/apache/hadoop/hbase/shaded/protobuf/generated/RPCProtos$RequestHeader$Builder;
       3: astore        6
       5: aload         6
       7: aload_2
       8: invokevirtual #4                  // Method org/apache/hadoop/hbase/shaded/protobuf/generated/RPCProtos$RequestHeader$Builder.setMethodName:(Ljava/lang/String;)Lorg/apache/hadoop/hbase/shaded/protobuf/generated/RPCProtos$RequestHeader$Builder;
      11: pop
      12: aload_2
      13: iload_3
      14: i2l
      15: aload         4
      17: aload         6
      19: invokevirtual #5                  // Method org/apache/hadoop/hbase/shaded/protobuf/generated/RPCProtos$RequestHeader$Builder.build:()Lorg/apache/hadoop/hbase/shaded/protobuf/generated/RPCProtos$RequestHeader;
      22: aload         5
      24: aload_1
      25: ldc           #6                  // String someuser
      27: iconst_1
      28: anewarray     #7                  // class java/lang/String
      31: dup
      32: iconst_0
      33: ldc           #8                  // String somegroup
      35: aastore
      36: invokestatic  #9                  // Method org/apache/hadoop/hbase/security/User.createUserForTesting:(Lorg/apache/hadoop/conf/Configuration;Ljava/lang/String;[Ljava/lang/String;)Lorg/apache/hadoop/hbase/security/User;
      39: invokevirtual #10                 // Method org/apache/hadoop/hbase/regionserver/AnnotationReadingPriorityFunction.getPriority:(Lorg/apache/hadoop/hbase/shaded/protobuf/generated/RPCProtos$RequestHeader;Lorg/apache/hbase/thirdparty/com/google/protobuf/Message;Lorg/apache/hadoop/hbase/security/User;)I
      42: i2l
      43: invokestatic  #11                 // Method org/junit/Assert.assertEquals:(Ljava/lang/String;JJ)V
      46: return
}
