Compiled from "Queue.java"
abstract class org.apache.hadoop.hbase.master.procedure.Queue<TKey extends java.lang.Comparable<TKey>> extends org.apache.hadoop.hbase.util.AvlUtil$AvlLinkedNode<org.apache.hadoop.hbase.master.procedure.Queue<TKey>> {
  static final boolean $assertionsDisabled;

  abstract boolean requireExclusiveLock(org.apache.hadoop.hbase.procedure2.Procedure<?>);

  protected org.apache.hadoop.hbase.master.procedure.Queue(TKey, org.apache.hadoop.hbase.procedure2.LockStatus);
    Code:
       0: aload_0
       1: aload_1
       2: iconst_1
       3: aload_2
       4: invokespecial #1                  // Method "<init>":(Ljava/lang/Comparable;ILorg/apache/hadoop/hbase/procedure2/LockStatus;)V
       7: return

  protected org.apache.hadoop.hbase.master.procedure.Queue(TKey, int, org.apache.hadoop.hbase.procedure2.LockStatus);
    Code:
       0: aload_0
       1: invokespecial #2                  // Method org/apache/hadoop/hbase/util/AvlUtil$AvlLinkedNode."<init>":()V
       4: aload_0
       5: new           #3                  // class org/apache/hadoop/hbase/procedure2/ProcedureDeque
       8: dup
       9: invokespecial #4                  // Method org/apache/hadoop/hbase/procedure2/ProcedureDeque."<init>":()V
      12: putfield      #5                  // Field runnables:Lorg/apache/hadoop/hbase/procedure2/ProcedureDeque;
      15: getstatic     #6                  // Field $assertionsDisabled:Z
      18: ifne          36
      21: iload_2
      22: iconst_1
      23: if_icmpge     36
      26: new           #7                  // class java/lang/AssertionError
      29: dup
      30: ldc           #8                  // String priority must be greater than or equal to 1
      32: invokespecial #9                  // Method java/lang/AssertionError."<init>":(Ljava/lang/Object;)V
      35: athrow
      36: aload_0
      37: aload_1
      38: putfield      #10                 // Field key:Ljava/lang/Comparable;
      41: aload_0
      42: iload_2
      43: putfield      #11                 // Field priority:I
      46: aload_0
      47: aload_3
      48: putfield      #12                 // Field lockStatus:Lorg/apache/hadoop/hbase/procedure2/LockStatus;
      51: return

  protected TKey getKey();
    Code:
       0: aload_0
       1: getfield      #10                 // Field key:Ljava/lang/Comparable;
       4: areturn

  public int getPriority();
    Code:
       0: aload_0
       1: getfield      #11                 // Field priority:I
       4: ireturn

  protected org.apache.hadoop.hbase.procedure2.LockStatus getLockStatus();
    Code:
       0: aload_0
       1: getfield      #12                 // Field lockStatus:Lorg/apache/hadoop/hbase/procedure2/LockStatus;
       4: areturn

  public boolean isAvailable();
    Code:
       0: aload_0
       1: invokevirtual #13                 // Method isEmpty:()Z
       4: ifne          11
       7: iconst_1
       8: goto          12
      11: iconst_0
      12: ireturn

  public void add(org.apache.hadoop.hbase.procedure2.Procedure<?>, boolean);
    Code:
       0: iload_2
       1: ifeq          15
       4: aload_0
       5: getfield      #5                  // Field runnables:Lorg/apache/hadoop/hbase/procedure2/ProcedureDeque;
       8: aload_1
       9: invokevirtual #14                 // Method org/apache/hadoop/hbase/procedure2/ProcedureDeque.addFirst:(Ljava/lang/Object;)V
      12: goto          23
      15: aload_0
      16: getfield      #5                  // Field runnables:Lorg/apache/hadoop/hbase/procedure2/ProcedureDeque;
      19: aload_1
      20: invokevirtual #15                 // Method org/apache/hadoop/hbase/procedure2/ProcedureDeque.addLast:(Ljava/lang/Object;)V
      23: return

  public org.apache.hadoop.hbase.procedure2.Procedure<?> peek();
    Code:
       0: aload_0
       1: getfield      #5                  // Field runnables:Lorg/apache/hadoop/hbase/procedure2/ProcedureDeque;
       4: invokevirtual #16                 // Method org/apache/hadoop/hbase/procedure2/ProcedureDeque.peek:()Ljava/lang/Object;
       7: checkcast     #17                 // class org/apache/hadoop/hbase/procedure2/Procedure
      10: areturn

  public org.apache.hadoop.hbase.procedure2.Procedure<?> poll();
    Code:
       0: aload_0
       1: getfield      #5                  // Field runnables:Lorg/apache/hadoop/hbase/procedure2/ProcedureDeque;
       4: invokevirtual #18                 // Method org/apache/hadoop/hbase/procedure2/ProcedureDeque.poll:()Ljava/lang/Object;
       7: checkcast     #17                 // class org/apache/hadoop/hbase/procedure2/Procedure
      10: areturn

  public boolean isEmpty();
    Code:
       0: aload_0
       1: getfield      #5                  // Field runnables:Lorg/apache/hadoop/hbase/procedure2/ProcedureDeque;
       4: invokevirtual #19                 // Method org/apache/hadoop/hbase/procedure2/ProcedureDeque.isEmpty:()Z
       7: ireturn

  public int size();
    Code:
       0: aload_0
       1: getfield      #5                  // Field runnables:Lorg/apache/hadoop/hbase/procedure2/ProcedureDeque;
       4: invokevirtual #20                 // Method org/apache/hadoop/hbase/procedure2/ProcedureDeque.size:()I
       7: ireturn

  public int compareKey(TKey);
    Code:
       0: aload_0
       1: getfield      #10                 // Field key:Ljava/lang/Comparable;
       4: aload_1
       5: invokeinterface #21,  2           // InterfaceMethod java/lang/Comparable.compareTo:(Ljava/lang/Object;)I
      10: ireturn

  public int compareTo(org.apache.hadoop.hbase.master.procedure.Queue<TKey>);
    Code:
       0: aload_0
       1: aload_1
       2: getfield      #10                 // Field key:Ljava/lang/Comparable;
       5: invokevirtual #22                 // Method compareKey:(Ljava/lang/Comparable;)I
       8: ireturn

  public java.lang.String toString();
    Code:
       0: ldc           #23                 // String %s(%s, xlock=%s sharedLock=%s size=%s)
       2: iconst_5
       3: anewarray     #24                 // class java/lang/Object
       6: dup
       7: iconst_0
       8: aload_0
       9: invokevirtual #25                 // Method java/lang/Object.getClass:()Ljava/lang/Class;
      12: invokevirtual #26                 // Method java/lang/Class.getSimpleName:()Ljava/lang/String;
      15: aastore
      16: dup
      17: iconst_1
      18: aload_0
      19: getfield      #10                 // Field key:Ljava/lang/Comparable;
      22: aastore
      23: dup
      24: iconst_2
      25: aload_0
      26: getfield      #12                 // Field lockStatus:Lorg/apache/hadoop/hbase/procedure2/LockStatus;
      29: invokeinterface #27,  1           // InterfaceMethod org/apache/hadoop/hbase/procedure2/LockStatus.hasExclusiveLock:()Z
      34: ifeq          72
      37: new           #28                 // class java/lang/StringBuilder
      40: dup
      41: invokespecial #29                 // Method java/lang/StringBuilder."<init>":()V
      44: ldc           #30                 // String true (
      46: invokevirtual #31                 // Method java/lang/StringBuilder.append:(Ljava/lang/String;)Ljava/lang/StringBuilder;
      49: aload_0
      50: getfield      #12                 // Field lockStatus:Lorg/apache/hadoop/hbase/procedure2/LockStatus;
      53: invokeinterface #32,  1           // InterfaceMethod org/apache/hadoop/hbase/procedure2/LockStatus.getExclusiveLockProcIdOwner:()J
      58: invokevirtual #33                 // Method java/lang/StringBuilder.append:(J)Ljava/lang/StringBuilder;
      61: ldc           #34                 // String )
      63: invokevirtual #31                 // Method java/lang/StringBuilder.append:(Ljava/lang/String;)Ljava/lang/StringBuilder;
      66: invokevirtual #35                 // Method java/lang/StringBuilder.toString:()Ljava/lang/String;
      69: goto          74
      72: ldc           #36                 // String false
      74: aastore
      75: dup
      76: iconst_3
      77: aload_0
      78: getfield      #12                 // Field lockStatus:Lorg/apache/hadoop/hbase/procedure2/LockStatus;
      81: invokeinterface #37,  1           // InterfaceMethod org/apache/hadoop/hbase/procedure2/LockStatus.getSharedLockCount:()I
      86: invokestatic  #38                 // Method java/lang/Integer.valueOf:(I)Ljava/lang/Integer;
      89: aastore
      90: dup
      91: iconst_4
      92: aload_0
      93: invokevirtual #39                 // Method size:()I
      96: invokestatic  #38                 // Method java/lang/Integer.valueOf:(I)Ljava/lang/Integer;
      99: aastore
     100: invokestatic  #40                 // Method java/lang/String.format:(Ljava/lang/String;[Ljava/lang/Object;)Ljava/lang/String;
     103: areturn

  public int compareTo(org.apache.hadoop.hbase.util.AvlUtil$AvlNode);
    Code:
       0: aload_0
       1: aload_1
       2: checkcast     #41                 // class org/apache/hadoop/hbase/master/procedure/Queue
       5: invokevirtual #42                 // Method compareTo:(Lorg/apache/hadoop/hbase/master/procedure/Queue;)I
       8: ireturn

  static {};
    Code:
       0: ldc           #41                 // class org/apache/hadoop/hbase/master/procedure/Queue
       2: invokevirtual #43                 // Method java/lang/Class.desiredAssertionStatus:()Z
       5: ifne          12
       8: iconst_1
       9: goto          13
      12: iconst_0
      13: putstatic     #6                  // Field $assertionsDisabled:Z
      16: return
}
