Compiled from "QuotaTableUtil.java"
public class org.apache.hadoop.hbase.quotas.QuotaTableUtil {
  public static final org.apache.hadoop.hbase.TableName QUOTA_TABLE_NAME;

  protected static final byte[] QUOTA_FAMILY_INFO;

  protected static final byte[] QUOTA_FAMILY_USAGE;

  protected static final byte[] QUOTA_QUALIFIER_SETTINGS;

  protected static final byte[] QUOTA_QUALIFIER_SETTINGS_PREFIX;

  protected static final byte[] QUOTA_QUALIFIER_POLICY;

  protected static final byte[] QUOTA_SNAPSHOT_SIZE_QUALIFIER;

  protected static final java.lang.String QUOTA_POLICY_COLUMN;

  protected static final byte[] QUOTA_USER_ROW_KEY_PREFIX;

  protected static final byte[] QUOTA_TABLE_ROW_KEY_PREFIX;

  protected static final byte[] QUOTA_NAMESPACE_ROW_KEY_PREFIX;

  protected static final byte[] QUOTA_REGION_SERVER_ROW_KEY_PREFIX;

  public static final java.lang.String QUOTA_REGION_SERVER_ROW_KEY;

  public org.apache.hadoop.hbase.quotas.QuotaTableUtil();
    Code:
       0: aload_0
       1: invokespecial #1                  // Method java/lang/Object."<init>":()V
       4: return

  public static org.apache.hadoop.hbase.shaded.protobuf.generated.QuotaProtos$Quotas getTableQuota(org.apache.hadoop.hbase.client.Connection, org.apache.hadoop.hbase.TableName) throws java.io.IOException;
    Code:
       0: aload_0
       1: aload_1
       2: invokestatic  #2                  // Method getTableRowKey:(Lorg/apache/hadoop/hbase/TableName;)[B
       5: invokestatic  #3                  // Method getQuotas:(Lorg/apache/hadoop/hbase/client/Connection;[B)Lorg/apache/hadoop/hbase/shaded/protobuf/generated/QuotaProtos$Quotas;
       8: areturn

  public static org.apache.hadoop.hbase.shaded.protobuf.generated.QuotaProtos$Quotas getNamespaceQuota(org.apache.hadoop.hbase.client.Connection, java.lang.String) throws java.io.IOException;
    Code:
       0: aload_0
       1: aload_1
       2: invokestatic  #4                  // Method getNamespaceRowKey:(Ljava/lang/String;)[B
       5: invokestatic  #3                  // Method getQuotas:(Lorg/apache/hadoop/hbase/client/Connection;[B)Lorg/apache/hadoop/hbase/shaded/protobuf/generated/QuotaProtos$Quotas;
       8: areturn

  public static org.apache.hadoop.hbase.shaded.protobuf.generated.QuotaProtos$Quotas getUserQuota(org.apache.hadoop.hbase.client.Connection, java.lang.String) throws java.io.IOException;
    Code:
       0: aload_0
       1: aload_1
       2: invokestatic  #5                  // Method getUserRowKey:(Ljava/lang/String;)[B
       5: invokestatic  #3                  // Method getQuotas:(Lorg/apache/hadoop/hbase/client/Connection;[B)Lorg/apache/hadoop/hbase/shaded/protobuf/generated/QuotaProtos$Quotas;
       8: areturn

  public static org.apache.hadoop.hbase.shaded.protobuf.generated.QuotaProtos$Quotas getUserQuota(org.apache.hadoop.hbase.client.Connection, java.lang.String, org.apache.hadoop.hbase.TableName) throws java.io.IOException;
    Code:
       0: aload_0
       1: aload_1
       2: invokestatic  #5                  // Method getUserRowKey:(Ljava/lang/String;)[B
       5: aload_2
       6: invokestatic  #6                  // Method getSettingsQualifierForUserTable:(Lorg/apache/hadoop/hbase/TableName;)[B
       9: invokestatic  #7                  // Method getQuotas:(Lorg/apache/hadoop/hbase/client/Connection;[B[B)Lorg/apache/hadoop/hbase/shaded/protobuf/generated/QuotaProtos$Quotas;
      12: areturn

  public static org.apache.hadoop.hbase.shaded.protobuf.generated.QuotaProtos$Quotas getUserQuota(org.apache.hadoop.hbase.client.Connection, java.lang.String, java.lang.String) throws java.io.IOException;
    Code:
       0: aload_0
       1: aload_1
       2: invokestatic  #5                  // Method getUserRowKey:(Ljava/lang/String;)[B
       5: aload_2
       6: invokestatic  #8                  // Method getSettingsQualifierForUserNamespace:(Ljava/lang/String;)[B
       9: invokestatic  #7                  // Method getQuotas:(Lorg/apache/hadoop/hbase/client/Connection;[B[B)Lorg/apache/hadoop/hbase/shaded/protobuf/generated/QuotaProtos$Quotas;
      12: areturn

  public static org.apache.hadoop.hbase.shaded.protobuf.generated.QuotaProtos$Quotas getRegionServerQuota(org.apache.hadoop.hbase.client.Connection, java.lang.String) throws java.io.IOException;
    Code:
       0: aload_0
       1: aload_1
       2: invokestatic  #10                 // Method getRegionServerRowKey:(Ljava/lang/String;)[B
       5: invokestatic  #3                  // Method getQuotas:(Lorg/apache/hadoop/hbase/client/Connection;[B)Lorg/apache/hadoop/hbase/shaded/protobuf/generated/QuotaProtos$Quotas;
       8: areturn

  public static org.apache.hadoop.hbase.client.Get makeGetForTableQuotas(org.apache.hadoop.hbase.TableName);
    Code:
       0: new           #11                 // class org/apache/hadoop/hbase/client/Get
       3: dup
       4: aload_0
       5: invokestatic  #2                  // Method getTableRowKey:(Lorg/apache/hadoop/hbase/TableName;)[B
       8: invokespecial #12                 // Method org/apache/hadoop/hbase/client/Get."<init>":([B)V
      11: astore_1
      12: aload_1
      13: getstatic     #13                 // Field QUOTA_FAMILY_INFO:[B
      16: invokevirtual #19                 // Method org/apache/hadoop/hbase/client/Get.addFamily:([B)Lorg/apache/hadoop/hbase/client/Get;
      19: pop
      20: aload_1
      21: areturn

  public static org.apache.hadoop.hbase.client.Get makeGetForNamespaceQuotas(java.lang.String);
    Code:
       0: new           #11                 // class org/apache/hadoop/hbase/client/Get
       3: dup
       4: aload_0
       5: invokestatic  #4                  // Method getNamespaceRowKey:(Ljava/lang/String;)[B
       8: invokespecial #12                 // Method org/apache/hadoop/hbase/client/Get."<init>":([B)V
      11: astore_1
      12: aload_1
      13: getstatic     #13                 // Field QUOTA_FAMILY_INFO:[B
      16: invokevirtual #19                 // Method org/apache/hadoop/hbase/client/Get.addFamily:([B)Lorg/apache/hadoop/hbase/client/Get;
      19: pop
      20: aload_1
      21: areturn

  public static org.apache.hadoop.hbase.client.Get makeGetForRegionServerQuotas(java.lang.String);
    Code:
       0: new           #11                 // class org/apache/hadoop/hbase/client/Get
       3: dup
       4: aload_0
       5: invokestatic  #10                 // Method getRegionServerRowKey:(Ljava/lang/String;)[B
       8: invokespecial #12                 // Method org/apache/hadoop/hbase/client/Get."<init>":([B)V
      11: astore_1
      12: aload_1
      13: getstatic     #13                 // Field QUOTA_FAMILY_INFO:[B
      16: invokevirtual #19                 // Method org/apache/hadoop/hbase/client/Get.addFamily:([B)Lorg/apache/hadoop/hbase/client/Get;
      19: pop
      20: aload_1
      21: areturn

  public static org.apache.hadoop.hbase.client.Get makeGetForUserQuotas(java.lang.String, java.lang.Iterable<org.apache.hadoop.hbase.TableName>, java.lang.Iterable<java.lang.String>);
    Code:
       0: new           #11                 // class org/apache/hadoop/hbase/client/Get
       3: dup
       4: aload_0
       5: invokestatic  #5                  // Method getUserRowKey:(Ljava/lang/String;)[B
       8: invokespecial #12                 // Method org/apache/hadoop/hbase/client/Get."<init>":([B)V
      11: astore_3
      12: aload_3
      13: getstatic     #13                 // Field QUOTA_FAMILY_INFO:[B
      16: getstatic     #9                  // Field QUOTA_QUALIFIER_SETTINGS:[B
      19: invokevirtual #14                 // Method org/apache/hadoop/hbase/client/Get.addColumn:([B[B)Lorg/apache/hadoop/hbase/client/Get;
      22: pop
      23: aload_1
      24: invokeinterface #20,  1           // InterfaceMethod java/lang/Iterable.iterator:()Ljava/util/Iterator;
      29: astore        4
      31: aload         4
      33: invokeinterface #21,  1           // InterfaceMethod java/util/Iterator.hasNext:()Z
      38: ifeq          69
      41: aload         4
      43: invokeinterface #22,  1           // InterfaceMethod java/util/Iterator.next:()Ljava/lang/Object;
      48: checkcast     #23                 // class org/apache/hadoop/hbase/TableName
      51: astore        5
      53: aload_3
      54: getstatic     #13                 // Field QUOTA_FAMILY_INFO:[B
      57: aload         5
      59: invokestatic  #6                  // Method getSettingsQualifierForUserTable:(Lorg/apache/hadoop/hbase/TableName;)[B
      62: invokevirtual #14                 // Method org/apache/hadoop/hbase/client/Get.addColumn:([B[B)Lorg/apache/hadoop/hbase/client/Get;
      65: pop
      66: goto          31
      69: aload_2
      70: invokeinterface #20,  1           // InterfaceMethod java/lang/Iterable.iterator:()Ljava/util/Iterator;
      75: astore        4
      77: aload         4
      79: invokeinterface #21,  1           // InterfaceMethod java/util/Iterator.hasNext:()Z
      84: ifeq          115
      87: aload         4
      89: invokeinterface #22,  1           // InterfaceMethod java/util/Iterator.next:()Ljava/lang/Object;
      94: checkcast     #24                 // class java/lang/String
      97: astore        5
      99: aload_3
     100: getstatic     #13                 // Field QUOTA_FAMILY_INFO:[B
     103: aload         5
     105: invokestatic  #8                  // Method getSettingsQualifierForUserNamespace:(Ljava/lang/String;)[B
     108: invokevirtual #14                 // Method org/apache/hadoop/hbase/client/Get.addColumn:([B[B)Lorg/apache/hadoop/hbase/client/Get;
     111: pop
     112: goto          77
     115: aload_3
     116: areturn

  public static org.apache.hadoop.hbase.client.Scan makeScan(org.apache.hadoop.hbase.quotas.QuotaFilter);
    Code:
       0: new           #25                 // class org/apache/hadoop/hbase/client/Scan
       3: dup
       4: invokespecial #26                 // Method org/apache/hadoop/hbase/client/Scan."<init>":()V
       7: astore_1
       8: aload_1
       9: getstatic     #13                 // Field QUOTA_FAMILY_INFO:[B
      12: invokevirtual #27                 // Method org/apache/hadoop/hbase/client/Scan.addFamily:([B)Lorg/apache/hadoop/hbase/client/Scan;
      15: pop
      16: aload_0
      17: ifnull        36
      20: aload_0
      21: invokevirtual #28                 // Method org/apache/hadoop/hbase/quotas/QuotaFilter.isNull:()Z
      24: ifne          36
      27: aload_1
      28: aload_0
      29: invokestatic  #29                 // Method makeFilter:(Lorg/apache/hadoop/hbase/quotas/QuotaFilter;)Lorg/apache/hadoop/hbase/filter/Filter;
      32: invokevirtual #30                 // Method org/apache/hadoop/hbase/client/Scan.setFilter:(Lorg/apache/hadoop/hbase/filter/Filter;)Lorg/apache/hadoop/hbase/client/Scan;
      35: pop
      36: aload_1
      37: areturn

  public static org.apache.hadoop.hbase.filter.Filter makeFilter(org.apache.hadoop.hbase.quotas.QuotaFilter);
    Code:
       0: new           #31                 // class org/apache/hadoop/hbase/filter/FilterList
       3: dup
       4: getstatic     #32                 // Field org/apache/hadoop/hbase/filter/FilterList$Operator.MUST_PASS_ALL:Lorg/apache/hadoop/hbase/filter/FilterList$Operator;
       7: invokespecial #33                 // Method org/apache/hadoop/hbase/filter/FilterList."<init>":(Lorg/apache/hadoop/hbase/filter/FilterList$Operator;)V
      10: astore_1
      11: aload_0
      12: invokevirtual #34                 // Method org/apache/hadoop/hbase/quotas/QuotaFilter.getUserFilter:()Ljava/lang/String;
      15: invokestatic  #35                 // Method org/apache/commons/lang3/StringUtils.isNotEmpty:(Ljava/lang/CharSequence;)Z
      18: ifeq          255
      21: new           #31                 // class org/apache/hadoop/hbase/filter/FilterList
      24: dup
      25: getstatic     #36                 // Field org/apache/hadoop/hbase/filter/FilterList$Operator.MUST_PASS_ONE:Lorg/apache/hadoop/hbase/filter/FilterList$Operator;
      28: invokespecial #33                 // Method org/apache/hadoop/hbase/filter/FilterList."<init>":(Lorg/apache/hadoop/hbase/filter/FilterList$Operator;)V
      31: astore_2
      32: iconst_0
      33: istore_3
      34: aload_0
      35: invokevirtual #37                 // Method org/apache/hadoop/hbase/quotas/QuotaFilter.getNamespaceFilter:()Ljava/lang/String;
      38: invokestatic  #35                 // Method org/apache/commons/lang3/StringUtils.isNotEmpty:(Ljava/lang/CharSequence;)Z
      41: ifeq          124
      44: new           #31                 // class org/apache/hadoop/hbase/filter/FilterList
      47: dup
      48: getstatic     #32                 // Field org/apache/hadoop/hbase/filter/FilterList$Operator.MUST_PASS_ALL:Lorg/apache/hadoop/hbase/filter/FilterList$Operator;
      51: invokespecial #33                 // Method org/apache/hadoop/hbase/filter/FilterList."<init>":(Lorg/apache/hadoop/hbase/filter/FilterList$Operator;)V
      54: astore        4
      56: aload         4
      58: new           #38                 // class org/apache/hadoop/hbase/filter/RowFilter
      61: dup
      62: getstatic     #39                 // Field org/apache/hadoop/hbase/CompareOperator.EQUAL:Lorg/apache/hadoop/hbase/CompareOperator;
      65: new           #40                 // class org/apache/hadoop/hbase/filter/RegexStringComparator
      68: dup
      69: aload_0
      70: invokevirtual #34                 // Method org/apache/hadoop/hbase/quotas/QuotaFilter.getUserFilter:()Ljava/lang/String;
      73: invokestatic  #41                 // Method getUserRowKeyRegex:(Ljava/lang/String;)Ljava/lang/String;
      76: iconst_0
      77: invokespecial #42                 // Method org/apache/hadoop/hbase/filter/RegexStringComparator."<init>":(Ljava/lang/String;I)V
      80: invokespecial #43                 // Method org/apache/hadoop/hbase/filter/RowFilter."<init>":(Lorg/apache/hadoop/hbase/CompareOperator;Lorg/apache/hadoop/hbase/filter/ByteArrayComparable;)V
      83: invokevirtual #44                 // Method org/apache/hadoop/hbase/filter/FilterList.addFilter:(Lorg/apache/hadoop/hbase/filter/Filter;)V
      86: aload         4
      88: new           #45                 // class org/apache/hadoop/hbase/filter/QualifierFilter
      91: dup
      92: getstatic     #39                 // Field org/apache/hadoop/hbase/CompareOperator.EQUAL:Lorg/apache/hadoop/hbase/CompareOperator;
      95: new           #40                 // class org/apache/hadoop/hbase/filter/RegexStringComparator
      98: dup
      99: aload_0
     100: invokevirtual #37                 // Method org/apache/hadoop/hbase/quotas/QuotaFilter.getNamespaceFilter:()Ljava/lang/String;
     103: invokestatic  #46                 // Method getSettingsQualifierRegexForUserNamespace:(Ljava/lang/String;)Ljava/lang/String;
     106: iconst_0
     107: invokespecial #42                 // Method org/apache/hadoop/hbase/filter/RegexStringComparator."<init>":(Ljava/lang/String;I)V
     110: invokespecial #47                 // Method org/apache/hadoop/hbase/filter/QualifierFilter."<init>":(Lorg/apache/hadoop/hbase/CompareOperator;Lorg/apache/hadoop/hbase/filter/ByteArrayComparable;)V
     113: invokevirtual #44                 // Method org/apache/hadoop/hbase/filter/FilterList.addFilter:(Lorg/apache/hadoop/hbase/filter/Filter;)V
     116: aload_2
     117: aload         4
     119: invokevirtual #44                 // Method org/apache/hadoop/hbase/filter/FilterList.addFilter:(Lorg/apache/hadoop/hbase/filter/Filter;)V
     122: iconst_1
     123: istore_3
     124: aload_0
     125: invokevirtual #48                 // Method org/apache/hadoop/hbase/quotas/QuotaFilter.getTableFilter:()Ljava/lang/String;
     128: invokestatic  #35                 // Method org/apache/commons/lang3/StringUtils.isNotEmpty:(Ljava/lang/CharSequence;)Z
     131: ifeq          214
     134: new           #31                 // class org/apache/hadoop/hbase/filter/FilterList
     137: dup
     138: getstatic     #32                 // Field org/apache/hadoop/hbase/filter/FilterList$Operator.MUST_PASS_ALL:Lorg/apache/hadoop/hbase/filter/FilterList$Operator;
     141: invokespecial #33                 // Method org/apache/hadoop/hbase/filter/FilterList."<init>":(Lorg/apache/hadoop/hbase/filter/FilterList$Operator;)V
     144: astore        4
     146: aload         4
     148: new           #38                 // class org/apache/hadoop/hbase/filter/RowFilter
     151: dup
     152: getstatic     #39                 // Field org/apache/hadoop/hbase/CompareOperator.EQUAL:Lorg/apache/hadoop/hbase/CompareOperator;
     155: new           #40                 // class org/apache/hadoop/hbase/filter/RegexStringComparator
     158: dup
     159: aload_0
     160: invokevirtual #34                 // Method org/apache/hadoop/hbase/quotas/QuotaFilter.getUserFilter:()Ljava/lang/String;
     163: invokestatic  #41                 // Method getUserRowKeyRegex:(Ljava/lang/String;)Ljava/lang/String;
     166: iconst_0
     167: invokespecial #42                 // Method org/apache/hadoop/hbase/filter/RegexStringComparator."<init>":(Ljava/lang/String;I)V
     170: invokespecial #43                 // Method org/apache/hadoop/hbase/filter/RowFilter."<init>":(Lorg/apache/hadoop/hbase/CompareOperator;Lorg/apache/hadoop/hbase/filter/ByteArrayComparable;)V
     173: invokevirtual #44                 // Method org/apache/hadoop/hbase/filter/FilterList.addFilter:(Lorg/apache/hadoop/hbase/filter/Filter;)V
     176: aload         4
     178: new           #45                 // class org/apache/hadoop/hbase/filter/QualifierFilter
     181: dup
     182: getstatic     #39                 // Field org/apache/hadoop/hbase/CompareOperator.EQUAL:Lorg/apache/hadoop/hbase/CompareOperator;
     185: new           #40                 // class org/apache/hadoop/hbase/filter/RegexStringComparator
     188: dup
     189: aload_0
     190: invokevirtual #48                 // Method org/apache/hadoop/hbase/quotas/QuotaFilter.getTableFilter:()Ljava/lang/String;
     193: invokestatic  #49                 // Method getSettingsQualifierRegexForUserTable:(Ljava/lang/String;)Ljava/lang/String;
     196: iconst_0
     197: invokespecial #42                 // Method org/apache/hadoop/hbase/filter/RegexStringComparator."<init>":(Ljava/lang/String;I)V
     200: invokespecial #47                 // Method org/apache/hadoop/hbase/filter/QualifierFilter."<init>":(Lorg/apache/hadoop/hbase/CompareOperator;Lorg/apache/hadoop/hbase/filter/ByteArrayComparable;)V
     203: invokevirtual #44                 // Method org/apache/hadoop/hbase/filter/FilterList.addFilter:(Lorg/apache/hadoop/hbase/filter/Filter;)V
     206: aload_2
     207: aload         4
     209: invokevirtual #44                 // Method org/apache/hadoop/hbase/filter/FilterList.addFilter:(Lorg/apache/hadoop/hbase/filter/Filter;)V
     212: iconst_1
     213: istore_3
     214: iload_3
     215: ifne          247
     218: aload_2
     219: new           #38                 // class org/apache/hadoop/hbase/filter/RowFilter
     222: dup
     223: getstatic     #39                 // Field org/apache/hadoop/hbase/CompareOperator.EQUAL:Lorg/apache/hadoop/hbase/CompareOperator;
     226: new           #40                 // class org/apache/hadoop/hbase/filter/RegexStringComparator
     229: dup
     230: aload_0
     231: invokevirtual #34                 // Method org/apache/hadoop/hbase/quotas/QuotaFilter.getUserFilter:()Ljava/lang/String;
     234: invokestatic  #41                 // Method getUserRowKeyRegex:(Ljava/lang/String;)Ljava/lang/String;
     237: iconst_0
     238: invokespecial #42                 // Method org/apache/hadoop/hbase/filter/RegexStringComparator."<init>":(Ljava/lang/String;I)V
     241: invokespecial #43                 // Method org/apache/hadoop/hbase/filter/RowFilter."<init>":(Lorg/apache/hadoop/hbase/CompareOperator;Lorg/apache/hadoop/hbase/filter/ByteArrayComparable;)V
     244: invokevirtual #44                 // Method org/apache/hadoop/hbase/filter/FilterList.addFilter:(Lorg/apache/hadoop/hbase/filter/Filter;)V
     247: aload_1
     248: aload_2
     249: invokevirtual #44                 // Method org/apache/hadoop/hbase/filter/FilterList.addFilter:(Lorg/apache/hadoop/hbase/filter/Filter;)V
     252: goto          378
     255: aload_0
     256: invokevirtual #48                 // Method org/apache/hadoop/hbase/quotas/QuotaFilter.getTableFilter:()Ljava/lang/String;
     259: invokestatic  #35                 // Method org/apache/commons/lang3/StringUtils.isNotEmpty:(Ljava/lang/CharSequence;)Z
     262: ifeq          297
     265: aload_1
     266: new           #38                 // class org/apache/hadoop/hbase/filter/RowFilter
     269: dup
     270: getstatic     #39                 // Field org/apache/hadoop/hbase/CompareOperator.EQUAL:Lorg/apache/hadoop/hbase/CompareOperator;
     273: new           #40                 // class org/apache/hadoop/hbase/filter/RegexStringComparator
     276: dup
     277: aload_0
     278: invokevirtual #48                 // Method org/apache/hadoop/hbase/quotas/QuotaFilter.getTableFilter:()Ljava/lang/String;
     281: invokestatic  #50                 // Method getTableRowKeyRegex:(Ljava/lang/String;)Ljava/lang/String;
     284: iconst_0
     285: invokespecial #42                 // Method org/apache/hadoop/hbase/filter/RegexStringComparator."<init>":(Ljava/lang/String;I)V
     288: invokespecial #43                 // Method org/apache/hadoop/hbase/filter/RowFilter."<init>":(Lorg/apache/hadoop/hbase/CompareOperator;Lorg/apache/hadoop/hbase/filter/ByteArrayComparable;)V
     291: invokevirtual #44                 // Method org/apache/hadoop/hbase/filter/FilterList.addFilter:(Lorg/apache/hadoop/hbase/filter/Filter;)V
     294: goto          378
     297: aload_0
     298: invokevirtual #37                 // Method org/apache/hadoop/hbase/quotas/QuotaFilter.getNamespaceFilter:()Ljava/lang/String;
     301: invokestatic  #35                 // Method org/apache/commons/lang3/StringUtils.isNotEmpty:(Ljava/lang/CharSequence;)Z
     304: ifeq          339
     307: aload_1
     308: new           #38                 // class org/apache/hadoop/hbase/filter/RowFilter
     311: dup
     312: getstatic     #39                 // Field org/apache/hadoop/hbase/CompareOperator.EQUAL:Lorg/apache/hadoop/hbase/CompareOperator;
     315: new           #40                 // class org/apache/hadoop/hbase/filter/RegexStringComparator
     318: dup
     319: aload_0
     320: invokevirtual #37                 // Method org/apache/hadoop/hbase/quotas/QuotaFilter.getNamespaceFilter:()Ljava/lang/String;
     323: invokestatic  #51                 // Method getNamespaceRowKeyRegex:(Ljava/lang/String;)Ljava/lang/String;
     326: iconst_0
     327: invokespecial #42                 // Method org/apache/hadoop/hbase/filter/RegexStringComparator."<init>":(Ljava/lang/String;I)V
     330: invokespecial #43                 // Method org/apache/hadoop/hbase/filter/RowFilter."<init>":(Lorg/apache/hadoop/hbase/CompareOperator;Lorg/apache/hadoop/hbase/filter/ByteArrayComparable;)V
     333: invokevirtual #44                 // Method org/apache/hadoop/hbase/filter/FilterList.addFilter:(Lorg/apache/hadoop/hbase/filter/Filter;)V
     336: goto          378
     339: aload_0
     340: invokevirtual #52                 // Method org/apache/hadoop/hbase/quotas/QuotaFilter.getRegionServerFilter:()Ljava/lang/String;
     343: invokestatic  #35                 // Method org/apache/commons/lang3/StringUtils.isNotEmpty:(Ljava/lang/CharSequence;)Z
     346: ifeq          378
     349: aload_1
     350: new           #38                 // class org/apache/hadoop/hbase/filter/RowFilter
     353: dup
     354: getstatic     #39                 // Field org/apache/hadoop/hbase/CompareOperator.EQUAL:Lorg/apache/hadoop/hbase/CompareOperator;
     357: new           #40                 // class org/apache/hadoop/hbase/filter/RegexStringComparator
     360: dup
     361: aload_0
     362: invokevirtual #52                 // Method org/apache/hadoop/hbase/quotas/QuotaFilter.getRegionServerFilter:()Ljava/lang/String;
     365: invokestatic  #53                 // Method getRegionServerRowKeyRegex:(Ljava/lang/String;)Ljava/lang/String;
     368: iconst_0
     369: invokespecial #42                 // Method org/apache/hadoop/hbase/filter/RegexStringComparator."<init>":(Ljava/lang/String;I)V
     372: invokespecial #43                 // Method org/apache/hadoop/hbase/filter/RowFilter."<init>":(Lorg/apache/hadoop/hbase/CompareOperator;Lorg/apache/hadoop/hbase/filter/ByteArrayComparable;)V
     375: invokevirtual #44                 // Method org/apache/hadoop/hbase/filter/FilterList.addFilter:(Lorg/apache/hadoop/hbase/filter/Filter;)V
     378: aload_1
     379: areturn

  public static org.apache.hadoop.hbase.client.Scan makeQuotaSnapshotScan();
    Code:
       0: aconst_null
       1: invokestatic  #54                 // Method makeQuotaSnapshotScanForTable:(Lorg/apache/hadoop/hbase/TableName;)Lorg/apache/hadoop/hbase/client/Scan;
       4: areturn

  public static java.util.Map<org.apache.hadoop.hbase.TableName, org.apache.hadoop.hbase.quotas.SpaceQuotaSnapshot> getSnapshots(org.apache.hadoop.hbase.client.Connection) throws java.io.IOException;
    Code:
       0: new           #55                 // class java/util/HashMap
       3: dup
       4: invokespecial #56                 // Method java/util/HashMap."<init>":()V
       7: astore_1
       8: aload_0
       9: getstatic     #57                 // Field QUOTA_TABLE_NAME:Lorg/apache/hadoop/hbase/TableName;
      12: invokeinterface #58,  2           // InterfaceMethod org/apache/hadoop/hbase/client/Connection.getTable:(Lorg/apache/hadoop/hbase/TableName;)Lorg/apache/hadoop/hbase/client/Table;
      17: astore_2
      18: aconst_null
      19: astore_3
      20: aload_2
      21: invokestatic  #59                 // Method makeQuotaSnapshotScan:()Lorg/apache/hadoop/hbase/client/Scan;
      24: invokeinterface #60,  2           // InterfaceMethod org/apache/hadoop/hbase/client/Table.getScanner:(Lorg/apache/hadoop/hbase/client/Scan;)Lorg/apache/hadoop/hbase/client/ResultScanner;
      29: astore        4
      31: aconst_null
      32: astore        5
      34: aload         4
      36: invokeinterface #61,  1           // InterfaceMethod org/apache/hadoop/hbase/client/ResultScanner.iterator:()Ljava/util/Iterator;
      41: astore        6
      43: aload         6
      45: invokeinterface #21,  1           // InterfaceMethod java/util/Iterator.hasNext:()Z
      50: ifeq          74
      53: aload         6
      55: invokeinterface #22,  1           // InterfaceMethod java/util/Iterator.next:()Ljava/lang/Object;
      60: checkcast     #62                 // class org/apache/hadoop/hbase/client/Result
      63: astore        7
      65: aload         7
      67: aload_1
      68: invokestatic  #63                 // Method extractQuotaSnapshot:(Lorg/apache/hadoop/hbase/client/Result;Ljava/util/Map;)V
      71: goto          43
      74: aload         4
      76: ifnull        169
      79: aload         5
      81: ifnull        106
      84: aload         4
      86: invokeinterface #64,  1           // InterfaceMethod org/apache/hadoop/hbase/client/ResultScanner.close:()V
      91: goto          169
      94: astore        6
      96: aload         5
      98: aload         6
     100: invokevirtual #66                 // Method java/lang/Throwable.addSuppressed:(Ljava/lang/Throwable;)V
     103: goto          169
     106: aload         4
     108: invokeinterface #64,  1           // InterfaceMethod org/apache/hadoop/hbase/client/ResultScanner.close:()V
     113: goto          169
     116: astore        6
     118: aload         6
     120: astore        5
     122: aload         6
     124: athrow
     125: astore        8
     127: aload         4
     129: ifnull        166
     132: aload         5
     134: ifnull        159
     137: aload         4
     139: invokeinterface #64,  1           // InterfaceMethod org/apache/hadoop/hbase/client/ResultScanner.close:()V
     144: goto          166
     147: astore        9
     149: aload         5
     151: aload         9
     153: invokevirtual #66                 // Method java/lang/Throwable.addSuppressed:(Ljava/lang/Throwable;)V
     156: goto          166
     159: aload         4
     161: invokeinterface #64,  1           // InterfaceMethod org/apache/hadoop/hbase/client/ResultScanner.close:()V
     166: aload         8
     168: athrow
     169: aload_2
     170: ifnull        253
     173: aload_3
     174: ifnull        197
     177: aload_2
     178: invokeinterface #67,  1           // InterfaceMethod org/apache/hadoop/hbase/client/Table.close:()V
     183: goto          253
     186: astore        4
     188: aload_3
     189: aload         4
     191: invokevirtual #66                 // Method java/lang/Throwable.addSuppressed:(Ljava/lang/Throwable;)V
     194: goto          253
     197: aload_2
     198: invokeinterface #67,  1           // InterfaceMethod org/apache/hadoop/hbase/client/Table.close:()V
     203: goto          253
     206: astore        4
     208: aload         4
     210: astore_3
     211: aload         4
     213: athrow
     214: astore        10
     216: aload_2
     217: ifnull        250
     220: aload_3
     221: ifnull        244
     224: aload_2
     225: invokeinterface #67,  1           // InterfaceMethod org/apache/hadoop/hbase/client/Table.close:()V
     230: goto          250
     233: astore        11
     235: aload_3
     236: aload         11
     238: invokevirtual #66                 // Method java/lang/Throwable.addSuppressed:(Ljava/lang/Throwable;)V
     241: goto          250
     244: aload_2
     245: invokeinterface #67,  1           // InterfaceMethod org/apache/hadoop/hbase/client/Table.close:()V
     250: aload         10
     252: athrow
     253: aload_1
     254: areturn
    Exception table:
       from    to  target type
          84    91    94   Class java/lang/Throwable
          34    74   116   Class java/lang/Throwable
          34    74   125   any
         137   144   147   Class java/lang/Throwable
         116   127   125   any
         177   183   186   Class java/lang/Throwable
          20   169   206   Class java/lang/Throwable
          20   169   214   any
         224   230   233   Class java/lang/Throwable
         206   216   214   any

  public static org.apache.hadoop.hbase.client.Scan makeQuotaSnapshotScanForTable(org.apache.hadoop.hbase.TableName);
    Code:
       0: new           #25                 // class org/apache/hadoop/hbase/client/Scan
       3: dup
       4: invokespecial #26                 // Method org/apache/hadoop/hbase/client/Scan."<init>":()V
       7: astore_1
       8: aload_1
       9: getstatic     #68                 // Field QUOTA_FAMILY_USAGE:[B
      12: getstatic     #69                 // Field QUOTA_QUALIFIER_POLICY:[B
      15: invokevirtual #70                 // Method org/apache/hadoop/hbase/client/Scan.addColumn:([B[B)Lorg/apache/hadoop/hbase/client/Scan;
      18: pop
      19: aconst_null
      20: aload_0
      21: if_acmpne     35
      24: aload_1
      25: getstatic     #71                 // Field QUOTA_TABLE_ROW_KEY_PREFIX:[B
      28: invokevirtual #72                 // Method org/apache/hadoop/hbase/client/Scan.setRowPrefixFilter:([B)Lorg/apache/hadoop/hbase/client/Scan;
      31: pop
      32: goto          52
      35: aload_0
      36: invokestatic  #2                  // Method getTableRowKey:(Lorg/apache/hadoop/hbase/TableName;)[B
      39: astore_2
      40: aload_1
      41: aload_2
      42: iconst_1
      43: invokevirtual #73                 // Method org/apache/hadoop/hbase/client/Scan.withStartRow:([BZ)Lorg/apache/hadoop/hbase/client/Scan;
      46: aload_2
      47: iconst_1
      48: invokevirtual #74                 // Method org/apache/hadoop/hbase/client/Scan.withStopRow:([BZ)Lorg/apache/hadoop/hbase/client/Scan;
      51: pop
      52: aload_1
      53: areturn

  public static org.apache.hadoop.hbase.client.Get makeQuotaSnapshotGetForTable(org.apache.hadoop.hbase.TableName);
    Code:
       0: new           #11                 // class org/apache/hadoop/hbase/client/Get
       3: dup
       4: aload_0
       5: invokestatic  #2                  // Method getTableRowKey:(Lorg/apache/hadoop/hbase/TableName;)[B
       8: invokespecial #12                 // Method org/apache/hadoop/hbase/client/Get."<init>":([B)V
      11: astore_1
      12: aload_1
      13: getstatic     #68                 // Field QUOTA_FAMILY_USAGE:[B
      16: getstatic     #69                 // Field QUOTA_QUALIFIER_POLICY:[B
      19: invokevirtual #14                 // Method org/apache/hadoop/hbase/client/Get.addColumn:([B[B)Lorg/apache/hadoop/hbase/client/Get;
      22: pop
      23: aload_1
      24: areturn

  public static void extractQuotaSnapshot(org.apache.hadoop.hbase.client.Result, java.util.Map<org.apache.hadoop.hbase.TableName, org.apache.hadoop.hbase.quotas.SpaceQuotaSnapshot>);
    Code:
       0: aload_0
       1: invokestatic  #75                 // Method java/util/Objects.requireNonNull:(Ljava/lang/Object;)Ljava/lang/Object;
       4: checkcast     #62                 // class org/apache/hadoop/hbase/client/Result
       7: invokevirtual #76                 // Method org/apache/hadoop/hbase/client/Result.getRow:()[B
      10: astore_2
      11: aload_2
      12: ifnull        20
      15: aload_2
      16: arraylength
      17: ifne          30
      20: new           #77                 // class java/lang/IllegalArgumentException
      23: dup
      24: ldc           #78                 // String Provided result had a null row
      26: invokespecial #79                 // Method java/lang/IllegalArgumentException."<init>":(Ljava/lang/String;)V
      29: athrow
      30: aload_2
      31: invokestatic  #80                 // Method getTableFromRowKey:([B)Lorg/apache/hadoop/hbase/TableName;
      34: astore_3
      35: aload_0
      36: getstatic     #68                 // Field QUOTA_FAMILY_USAGE:[B
      39: getstatic     #69                 // Field QUOTA_QUALIFIER_POLICY:[B
      42: invokevirtual #81                 // Method org/apache/hadoop/hbase/client/Result.getColumnLatestCell:([B[B)Lorg/apache/hadoop/hbase/Cell;
      45: astore        4
      47: aload         4
      49: ifnonnull     93
      52: new           #77                 // class java/lang/IllegalArgumentException
      55: dup
      56: new           #82                 // class java/lang/StringBuilder
      59: dup
      60: invokespecial #83                 // Method java/lang/StringBuilder."<init>":()V
      63: ldc           #84                 // String Result did not contain the expected column
      65: invokevirtual #85                 // Method java/lang/StringBuilder.append:(Ljava/lang/String;)Ljava/lang/StringBuilder;
      68: getstatic     #86                 // Field QUOTA_POLICY_COLUMN:Ljava/lang/String;
      71: invokevirtual #85                 // Method java/lang/StringBuilder.append:(Ljava/lang/String;)Ljava/lang/StringBuilder;
      74: ldc           #87                 // String ,
      76: invokevirtual #85                 // Method java/lang/StringBuilder.append:(Ljava/lang/String;)Ljava/lang/StringBuilder;
      79: aload_0
      80: invokevirtual #88                 // Method org/apache/hadoop/hbase/client/Result.toString:()Ljava/lang/String;
      83: invokevirtual #85                 // Method java/lang/StringBuilder.append:(Ljava/lang/String;)Ljava/lang/StringBuilder;
      86: invokevirtual #89                 // Method java/lang/StringBuilder.toString:()Ljava/lang/String;
      89: invokespecial #79                 // Method java/lang/IllegalArgumentException."<init>":(Ljava/lang/String;)V
      92: athrow
      93: aload         4
      95: invokeinterface #90,  1           // InterfaceMethod org/apache/hadoop/hbase/Cell.getValueArray:()[B
     100: aload         4
     102: invokeinterface #91,  1           // InterfaceMethod org/apache/hadoop/hbase/Cell.getValueOffset:()I
     107: aload         4
     109: invokeinterface #92,  1           // InterfaceMethod org/apache/hadoop/hbase/Cell.getValueLength:()I
     114: invokestatic  #93                 // Method org/apache/hbase/thirdparty/com/google/protobuf/UnsafeByteOperations.unsafeWrap:([BII)Lorg/apache/hbase/thirdparty/com/google/protobuf/ByteString;
     117: astore        5
     119: aload         5
     121: invokestatic  #94                 // Method org/apache/hadoop/hbase/shaded/protobuf/generated/QuotaProtos$SpaceQuotaSnapshot.parseFrom:(Lorg/apache/hbase/thirdparty/com/google/protobuf/ByteString;)Lorg/apache/hadoop/hbase/shaded/protobuf/generated/QuotaProtos$SpaceQuotaSnapshot;
     124: astore        6
     126: aload_1
     127: aload_3
     128: aload         6
     130: invokestatic  #95                 // Method org/apache/hadoop/hbase/quotas/SpaceQuotaSnapshot.toSpaceQuotaSnapshot:(Lorg/apache/hadoop/hbase/shaded/protobuf/generated/QuotaProtos$SpaceQuotaSnapshot;)Lorg/apache/hadoop/hbase/quotas/SpaceQuotaSnapshot;
     133: invokeinterface #96,  3           // InterfaceMethod java/util/Map.put:(Ljava/lang/Object;Ljava/lang/Object;)Ljava/lang/Object;
     138: pop
     139: goto          156
     142: astore        6
     144: new           #77                 // class java/lang/IllegalArgumentException
     147: dup
     148: ldc           #98                 // String Result did not contain a valid SpaceQuota protocol buffer message
     150: aload         6
     152: invokespecial #99                 // Method java/lang/IllegalArgumentException."<init>":(Ljava/lang/String;Ljava/lang/Throwable;)V
     155: athrow
     156: return
    Exception table:
       from    to  target type
         119   139   142   Class org/apache/hbase/thirdparty/com/google/protobuf/InvalidProtocolBufferException

  public static void parseResult(org.apache.hadoop.hbase.client.Result, org.apache.hadoop.hbase.quotas.QuotaTableUtil$QuotasVisitor) throws java.io.IOException;
    Code:
       0: aload_0
       1: invokevirtual #76                 // Method org/apache/hadoop/hbase/client/Result.getRow:()[B
       4: astore_2
       5: aload_2
       6: invokestatic  #100                // Method isNamespaceRowKey:([B)Z
       9: ifeq          20
      12: aload_0
      13: aload_1
      14: invokestatic  #101                // Method parseNamespaceResult:(Lorg/apache/hadoop/hbase/client/Result;Lorg/apache/hadoop/hbase/quotas/QuotaTableUtil$NamespaceQuotasVisitor;)V
      17: goto          126
      20: aload_2
      21: invokestatic  #102                // Method isTableRowKey:([B)Z
      24: ifeq          35
      27: aload_0
      28: aload_1
      29: invokestatic  #103                // Method parseTableResult:(Lorg/apache/hadoop/hbase/client/Result;Lorg/apache/hadoop/hbase/quotas/QuotaTableUtil$TableQuotasVisitor;)V
      32: goto          126
      35: aload_2
      36: invokestatic  #104                // Method isUserRowKey:([B)Z
      39: ifeq          50
      42: aload_0
      43: aload_1
      44: invokestatic  #105                // Method parseUserResult:(Lorg/apache/hadoop/hbase/client/Result;Lorg/apache/hadoop/hbase/quotas/QuotaTableUtil$UserQuotasVisitor;)V
      47: goto          126
      50: aload_2
      51: invokestatic  #106                // Method isRegionServerRowKey:([B)Z
      54: ifeq          65
      57: aload_0
      58: aload_1
      59: invokestatic  #107                // Method parseRegionServerResult:(Lorg/apache/hadoop/hbase/client/Result;Lorg/apache/hadoop/hbase/quotas/QuotaTableUtil$RegionServerQuotasVisitor;)V
      62: goto          126
      65: aload_2
      66: invokestatic  #108                // Method isExceedThrottleQuotaRowKey:([B)Z
      69: ifeq          96
      72: getstatic     #109                // Field LOG:Lorg/slf4j/Logger;
      75: invokeinterface #110,  1          // InterfaceMethod org/slf4j/Logger.isDebugEnabled:()Z
      80: ifeq          126
      83: getstatic     #109                // Field LOG:Lorg/slf4j/Logger;
      86: ldc           #111                // String Skip exceedThrottleQuota row-key when parse quota result
      88: invokeinterface #112,  2          // InterfaceMethod org/slf4j/Logger.debug:(Ljava/lang/String;)V
      93: goto          126
      96: getstatic     #109                // Field LOG:Lorg/slf4j/Logger;
      99: new           #82                 // class java/lang/StringBuilder
     102: dup
     103: invokespecial #83                 // Method java/lang/StringBuilder."<init>":()V
     106: ldc           #113                // String unexpected row-key:
     108: invokevirtual #85                 // Method java/lang/StringBuilder.append:(Ljava/lang/String;)Ljava/lang/StringBuilder;
     111: aload_2
     112: invokestatic  #114                // Method org/apache/hadoop/hbase/util/Bytes.toString:([B)Ljava/lang/String;
     115: invokevirtual #85                 // Method java/lang/StringBuilder.append:(Ljava/lang/String;)Ljava/lang/StringBuilder;
     118: invokevirtual #89                 // Method java/lang/StringBuilder.toString:()Ljava/lang/String;
     121: invokeinterface #115,  2          // InterfaceMethod org/slf4j/Logger.warn:(Ljava/lang/String;)V
     126: return

  public static void parseResultToCollection(org.apache.hadoop.hbase.client.Result, java.util.Collection<org.apache.hadoop.hbase.quotas.QuotaSettings>) throws java.io.IOException;
    Code:
       0: aload_0
       1: new           #116                // class org/apache/hadoop/hbase/quotas/QuotaTableUtil$1
       4: dup
       5: aload_1
       6: invokespecial #117                // Method org/apache/hadoop/hbase/quotas/QuotaTableUtil$1."<init>":(Ljava/util/Collection;)V
       9: invokestatic  #118                // Method parseResult:(Lorg/apache/hadoop/hbase/client/Result;Lorg/apache/hadoop/hbase/quotas/QuotaTableUtil$QuotasVisitor;)V
      12: return

  public static void parseNamespaceResult(org.apache.hadoop.hbase.client.Result, org.apache.hadoop.hbase.quotas.QuotaTableUtil$NamespaceQuotasVisitor) throws java.io.IOException;
    Code:
       0: aload_0
       1: invokevirtual #76                 // Method org/apache/hadoop/hbase/client/Result.getRow:()[B
       4: invokestatic  #119                // Method getNamespaceFromRowKey:([B)Ljava/lang/String;
       7: astore_2
       8: aload_2
       9: aload_0
      10: aload_1
      11: invokestatic  #120                // Method parseNamespaceResult:(Ljava/lang/String;Lorg/apache/hadoop/hbase/client/Result;Lorg/apache/hadoop/hbase/quotas/QuotaTableUtil$NamespaceQuotasVisitor;)V
      14: return

  protected static void parseNamespaceResult(java.lang.String, org.apache.hadoop.hbase.client.Result, org.apache.hadoop.hbase.quotas.QuotaTableUtil$NamespaceQuotasVisitor) throws java.io.IOException;
    Code:
       0: aload_1
       1: getstatic     #13                 // Field QUOTA_FAMILY_INFO:[B
       4: getstatic     #9                  // Field QUOTA_QUALIFIER_SETTINGS:[B
       7: invokevirtual #17                 // Method org/apache/hadoop/hbase/client/Result.getValue:([B[B)[B
      10: astore_3
      11: aload_3
      12: ifnull        30
      15: aload_3
      16: invokestatic  #18                 // Method quotasFromData:([B)Lorg/apache/hadoop/hbase/shaded/protobuf/generated/QuotaProtos$Quotas;
      19: astore        4
      21: aload_2
      22: aload_0
      23: aload         4
      25: invokeinterface #121,  3          // InterfaceMethod org/apache/hadoop/hbase/quotas/QuotaTableUtil$NamespaceQuotasVisitor.visitNamespaceQuotas:(Ljava/lang/String;Lorg/apache/hadoop/hbase/shaded/protobuf/generated/QuotaProtos$Quotas;)V
      30: return

  public static void parseTableResult(org.apache.hadoop.hbase.client.Result, org.apache.hadoop.hbase.quotas.QuotaTableUtil$TableQuotasVisitor) throws java.io.IOException;
    Code:
       0: aload_0
       1: invokevirtual #76                 // Method org/apache/hadoop/hbase/client/Result.getRow:()[B
       4: invokestatic  #80                 // Method getTableFromRowKey:([B)Lorg/apache/hadoop/hbase/TableName;
       7: astore_2
       8: aload_2
       9: aload_0
      10: aload_1
      11: invokestatic  #125                // Method parseTableResult:(Lorg/apache/hadoop/hbase/TableName;Lorg/apache/hadoop/hbase/client/Result;Lorg/apache/hadoop/hbase/quotas/QuotaTableUtil$TableQuotasVisitor;)V
      14: return

  protected static void parseTableResult(org.apache.hadoop.hbase.TableName, org.apache.hadoop.hbase.client.Result, org.apache.hadoop.hbase.quotas.QuotaTableUtil$TableQuotasVisitor) throws java.io.IOException;
    Code:
       0: aload_1
       1: getstatic     #13                 // Field QUOTA_FAMILY_INFO:[B
       4: getstatic     #9                  // Field QUOTA_QUALIFIER_SETTINGS:[B
       7: invokevirtual #17                 // Method org/apache/hadoop/hbase/client/Result.getValue:([B[B)[B
      10: astore_3
      11: aload_3
      12: ifnull        30
      15: aload_3
      16: invokestatic  #18                 // Method quotasFromData:([B)Lorg/apache/hadoop/hbase/shaded/protobuf/generated/QuotaProtos$Quotas;
      19: astore        4
      21: aload_2
      22: aload_0
      23: aload         4
      25: invokeinterface #126,  3          // InterfaceMethod org/apache/hadoop/hbase/quotas/QuotaTableUtil$TableQuotasVisitor.visitTableQuotas:(Lorg/apache/hadoop/hbase/TableName;Lorg/apache/hadoop/hbase/shaded/protobuf/generated/QuotaProtos$Quotas;)V
      30: return

  public static void parseUserResult(org.apache.hadoop.hbase.client.Result, org.apache.hadoop.hbase.quotas.QuotaTableUtil$UserQuotasVisitor) throws java.io.IOException;
    Code:
       0: aload_0
       1: invokevirtual #76                 // Method org/apache/hadoop/hbase/client/Result.getRow:()[B
       4: invokestatic  #127                // Method getUserFromRowKey:([B)Ljava/lang/String;
       7: astore_2
       8: aload_2
       9: aload_0
      10: aload_1
      11: invokestatic  #128                // Method parseUserResult:(Ljava/lang/String;Lorg/apache/hadoop/hbase/client/Result;Lorg/apache/hadoop/hbase/quotas/QuotaTableUtil$UserQuotasVisitor;)V
      14: return

  protected static void parseUserResult(java.lang.String, org.apache.hadoop.hbase.client.Result, org.apache.hadoop.hbase.quotas.QuotaTableUtil$UserQuotasVisitor) throws java.io.IOException;
    Code:
       0: aload_1
       1: getstatic     #13                 // Field QUOTA_FAMILY_INFO:[B
       4: invokevirtual #129                // Method org/apache/hadoop/hbase/client/Result.getFamilyMap:([B)Ljava/util/NavigableMap;
       7: astore_3
       8: aload_3
       9: ifnull        21
      12: aload_3
      13: invokeinterface #130,  1          // InterfaceMethod java/util/Map.isEmpty:()Z
      18: ifeq          22
      21: return
      22: aload_3
      23: invokeinterface #131,  1          // InterfaceMethod java/util/Map.entrySet:()Ljava/util/Set;
      28: invokeinterface #132,  1          // InterfaceMethod java/util/Set.iterator:()Ljava/util/Iterator;
      33: astore        4
      35: aload         4
      37: invokeinterface #21,  1           // InterfaceMethod java/util/Iterator.hasNext:()Z
      42: ifeq          208
      45: aload         4
      47: invokeinterface #22,  1           // InterfaceMethod java/util/Iterator.next:()Ljava/lang/Object;
      52: checkcast     #133                // class java/util/Map$Entry
      55: astore        5
      57: aload         5
      59: invokeinterface #134,  1          // InterfaceMethod java/util/Map$Entry.getValue:()Ljava/lang/Object;
      64: checkcast     #135                // class "[B"
      67: invokestatic  #18                 // Method quotasFromData:([B)Lorg/apache/hadoop/hbase/shaded/protobuf/generated/QuotaProtos$Quotas;
      70: astore        6
      72: aload         5
      74: invokeinterface #136,  1          // InterfaceMethod java/util/Map$Entry.getKey:()Ljava/lang/Object;
      79: checkcast     #135                // class "[B"
      82: getstatic     #137                // Field QUOTA_QUALIFIER_SETTINGS_PREFIX:[B
      85: invokestatic  #138                // Method org/apache/hadoop/hbase/util/Bytes.startsWith:([B[B)Z
      88: ifeq          177
      91: aload         5
      93: invokeinterface #136,  1          // InterfaceMethod java/util/Map$Entry.getKey:()Ljava/lang/Object;
      98: checkcast     #135                // class "[B"
     101: getstatic     #137                // Field QUOTA_QUALIFIER_SETTINGS_PREFIX:[B
     104: arraylength
     105: invokestatic  #139                // Method org/apache/hadoop/hbase/util/Bytes.toString:([BI)Ljava/lang/String;
     108: astore        7
     110: aload         7
     112: aload         7
     114: invokevirtual #140                // Method java/lang/String.length:()I
     117: iconst_1
     118: isub
     119: invokevirtual #141                // Method java/lang/String.charAt:(I)C
     122: bipush        58
     124: if_icmpne     156
     127: aload         7
     129: iconst_0
     130: aload         7
     132: invokevirtual #140                // Method java/lang/String.length:()I
     135: iconst_1
     136: isub
     137: invokevirtual #142                // Method java/lang/String.substring:(II)Ljava/lang/String;
     140: astore        8
     142: aload_2
     143: aload_0
     144: aload         8
     146: aload         6
     148: invokeinterface #143,  4          // InterfaceMethod org/apache/hadoop/hbase/quotas/QuotaTableUtil$UserQuotasVisitor.visitUserQuotas:(Ljava/lang/String;Ljava/lang/String;Lorg/apache/hadoop/hbase/shaded/protobuf/generated/QuotaProtos$Quotas;)V
     153: goto          174
     156: aload         7
     158: invokestatic  #144                // Method org/apache/hadoop/hbase/TableName.valueOf:(Ljava/lang/String;)Lorg/apache/hadoop/hbase/TableName;
     161: astore        8
     163: aload_2
     164: aload_0
     165: aload         8
     167: aload         6
     169: invokeinterface #145,  4          // InterfaceMethod org/apache/hadoop/hbase/quotas/QuotaTableUtil$UserQuotasVisitor.visitUserQuotas:(Ljava/lang/String;Lorg/apache/hadoop/hbase/TableName;Lorg/apache/hadoop/hbase/shaded/protobuf/generated/QuotaProtos$Quotas;)V
     174: goto          205
     177: aload         5
     179: invokeinterface #136,  1          // InterfaceMethod java/util/Map$Entry.getKey:()Ljava/lang/Object;
     184: checkcast     #135                // class "[B"
     187: getstatic     #9                  // Field QUOTA_QUALIFIER_SETTINGS:[B
     190: invokestatic  #146                // Method org/apache/hadoop/hbase/util/Bytes.equals:([B[B)Z
     193: ifeq          205
     196: aload_2
     197: aload_0
     198: aload         6
     200: invokeinterface #147,  3          // InterfaceMethod org/apache/hadoop/hbase/quotas/QuotaTableUtil$UserQuotasVisitor.visitUserQuotas:(Ljava/lang/String;Lorg/apache/hadoop/hbase/shaded/protobuf/generated/QuotaProtos$Quotas;)V
     205: goto          35
     208: return

  static org.apache.hadoop.hbase.client.Put createPutForSpaceSnapshot(org.apache.hadoop.hbase.TableName, org.apache.hadoop.hbase.quotas.SpaceQuotaSnapshot);
    Code:
       0: new           #148                // class org/apache/hadoop/hbase/client/Put
       3: dup
       4: aload_0
       5: invokestatic  #2                  // Method getTableRowKey:(Lorg/apache/hadoop/hbase/TableName;)[B
       8: invokespecial #149                // Method org/apache/hadoop/hbase/client/Put."<init>":([B)V
      11: astore_2
      12: aload_2
      13: getstatic     #68                 // Field QUOTA_FAMILY_USAGE:[B
      16: getstatic     #69                 // Field QUOTA_QUALIFIER_POLICY:[B
      19: aload_1
      20: invokestatic  #150                // Method org/apache/hadoop/hbase/quotas/SpaceQuotaSnapshot.toProtoSnapshot:(Lorg/apache/hadoop/hbase/quotas/SpaceQuotaSnapshot;)Lorg/apache/hadoop/hbase/shaded/protobuf/generated/QuotaProtos$SpaceQuotaSnapshot;
      23: invokevirtual #151                // Method org/apache/hadoop/hbase/shaded/protobuf/generated/QuotaProtos$SpaceQuotaSnapshot.toByteArray:()[B
      26: invokevirtual #152                // Method org/apache/hadoop/hbase/client/Put.addColumn:([B[B[B)Lorg/apache/hadoop/hbase/client/Put;
      29: pop
      30: aload_2
      31: areturn

  static org.apache.hadoop.hbase.client.Get makeGetForSnapshotSize(org.apache.hadoop.hbase.TableName, java.lang.String);
    Code:
       0: new           #11                 // class org/apache/hadoop/hbase/client/Get
       3: dup
       4: getstatic     #71                 // Field QUOTA_TABLE_ROW_KEY_PREFIX:[B
       7: aload_0
       8: invokevirtual #153                // Method org/apache/hadoop/hbase/TableName.toString:()Ljava/lang/String;
      11: invokestatic  #154                // Method org/apache/hadoop/hbase/util/Bytes.toBytes:(Ljava/lang/String;)[B
      14: invokestatic  #155                // Method org/apache/hadoop/hbase/util/Bytes.add:([B[B)[B
      17: invokespecial #12                 // Method org/apache/hadoop/hbase/client/Get."<init>":([B)V
      20: astore_2
      21: aload_2
      22: getstatic     #68                 // Field QUOTA_FAMILY_USAGE:[B
      25: getstatic     #156                // Field QUOTA_SNAPSHOT_SIZE_QUALIFIER:[B
      28: aload_1
      29: invokestatic  #154                // Method org/apache/hadoop/hbase/util/Bytes.toBytes:(Ljava/lang/String;)[B
      32: invokestatic  #155                // Method org/apache/hadoop/hbase/util/Bytes.add:([B[B)[B
      35: invokevirtual #14                 // Method org/apache/hadoop/hbase/client/Get.addColumn:([B[B)Lorg/apache/hadoop/hbase/client/Get;
      38: pop
      39: aload_2
      40: areturn

  static org.apache.hadoop.hbase.client.Put createPutForSnapshotSize(org.apache.hadoop.hbase.TableName, java.lang.String, long);
    Code:
       0: new           #148                // class org/apache/hadoop/hbase/client/Put
       3: dup
       4: aload_0
       5: invokestatic  #2                  // Method getTableRowKey:(Lorg/apache/hadoop/hbase/TableName;)[B
       8: invokespecial #149                // Method org/apache/hadoop/hbase/client/Put."<init>":([B)V
      11: astore        4
      13: aload         4
      15: getstatic     #68                 // Field QUOTA_FAMILY_USAGE:[B
      18: aload_1
      19: invokestatic  #157                // Method getSnapshotSizeQualifier:(Ljava/lang/String;)[B
      22: invokestatic  #158                // Method org/apache/hadoop/hbase/shaded/protobuf/generated/QuotaProtos$SpaceQuotaSnapshot.newBuilder:()Lorg/apache/hadoop/hbase/shaded/protobuf/generated/QuotaProtos$SpaceQuotaSnapshot$Builder;
      25: lload_2
      26: invokevirtual #159                // Method org/apache/hadoop/hbase/shaded/protobuf/generated/QuotaProtos$SpaceQuotaSnapshot$Builder.setQuotaUsage:(J)Lorg/apache/hadoop/hbase/shaded/protobuf/generated/QuotaProtos$SpaceQuotaSnapshot$Builder;
      29: invokevirtual #160                // Method org/apache/hadoop/hbase/shaded/protobuf/generated/QuotaProtos$SpaceQuotaSnapshot$Builder.build:()Lorg/apache/hadoop/hbase/shaded/protobuf/generated/QuotaProtos$SpaceQuotaSnapshot;
      32: invokevirtual #151                // Method org/apache/hadoop/hbase/shaded/protobuf/generated/QuotaProtos$SpaceQuotaSnapshot.toByteArray:()[B
      35: invokevirtual #152                // Method org/apache/hadoop/hbase/client/Put.addColumn:([B[B[B)Lorg/apache/hadoop/hbase/client/Put;
      38: pop
      39: aload         4
      41: areturn

  static org.apache.hadoop.hbase.client.Put createPutForNamespaceSnapshotSize(java.lang.String, long);
    Code:
       0: new           #148                // class org/apache/hadoop/hbase/client/Put
       3: dup
       4: aload_0
       5: invokestatic  #4                  // Method getNamespaceRowKey:(Ljava/lang/String;)[B
       8: invokespecial #149                // Method org/apache/hadoop/hbase/client/Put."<init>":([B)V
      11: astore_3
      12: aload_3
      13: getstatic     #68                 // Field QUOTA_FAMILY_USAGE:[B
      16: getstatic     #156                // Field QUOTA_SNAPSHOT_SIZE_QUALIFIER:[B
      19: invokestatic  #158                // Method org/apache/hadoop/hbase/shaded/protobuf/generated/QuotaProtos$SpaceQuotaSnapshot.newBuilder:()Lorg/apache/hadoop/hbase/shaded/protobuf/generated/QuotaProtos$SpaceQuotaSnapshot$Builder;
      22: lload_1
      23: invokevirtual #159                // Method org/apache/hadoop/hbase/shaded/protobuf/generated/QuotaProtos$SpaceQuotaSnapshot$Builder.setQuotaUsage:(J)Lorg/apache/hadoop/hbase/shaded/protobuf/generated/QuotaProtos$SpaceQuotaSnapshot$Builder;
      26: invokevirtual #160                // Method org/apache/hadoop/hbase/shaded/protobuf/generated/QuotaProtos$SpaceQuotaSnapshot$Builder.build:()Lorg/apache/hadoop/hbase/shaded/protobuf/generated/QuotaProtos$SpaceQuotaSnapshot;
      29: invokevirtual #151                // Method org/apache/hadoop/hbase/shaded/protobuf/generated/QuotaProtos$SpaceQuotaSnapshot.toByteArray:()[B
      32: invokevirtual #152                // Method org/apache/hadoop/hbase/client/Put.addColumn:([B[B[B)Lorg/apache/hadoop/hbase/client/Put;
      35: pop
      36: aload_3
      37: areturn

  static java.util.List<org.apache.hadoop.hbase.client.Delete> createDeletesForExistingTableSnapshotSizes(org.apache.hbase.thirdparty.com.google.common.collect.Multimap<org.apache.hadoop.hbase.TableName, java.lang.String>);
    Code:
       0: new           #161                // class java/util/ArrayList
       3: dup
       4: invokespecial #162                // Method java/util/ArrayList."<init>":()V
       7: astore_1
       8: aload_0
       9: invokeinterface #163,  1          // InterfaceMethod org/apache/hbase/thirdparty/com/google/common/collect/Multimap.asMap:()Ljava/util/Map;
      14: invokeinterface #131,  1          // InterfaceMethod java/util/Map.entrySet:()Ljava/util/Set;
      19: invokeinterface #132,  1          // InterfaceMethod java/util/Set.iterator:()Ljava/util/Iterator;
      24: astore_2
      25: aload_2
      26: invokeinterface #21,  1           // InterfaceMethod java/util/Iterator.hasNext:()Z
      31: ifeq          138
      34: aload_2
      35: invokeinterface #22,  1           // InterfaceMethod java/util/Iterator.next:()Ljava/lang/Object;
      40: checkcast     #133                // class java/util/Map$Entry
      43: astore_3
      44: aload_3
      45: invokeinterface #134,  1          // InterfaceMethod java/util/Map$Entry.getValue:()Ljava/lang/Object;
      50: checkcast     #164                // class java/util/Collection
      53: invokeinterface #165,  1          // InterfaceMethod java/util/Collection.iterator:()Ljava/util/Iterator;
      58: astore        4
      60: aload         4
      62: invokeinterface #21,  1           // InterfaceMethod java/util/Iterator.hasNext:()Z
      67: ifeq          135
      70: aload         4
      72: invokeinterface #22,  1           // InterfaceMethod java/util/Iterator.next:()Ljava/lang/Object;
      77: checkcast     #24                 // class java/lang/String
      80: astore        5
      82: new           #166                // class org/apache/hadoop/hbase/client/Delete
      85: dup
      86: aload_3
      87: invokeinterface #136,  1          // InterfaceMethod java/util/Map$Entry.getKey:()Ljava/lang/Object;
      92: checkcast     #23                 // class org/apache/hadoop/hbase/TableName
      95: invokestatic  #2                  // Method getTableRowKey:(Lorg/apache/hadoop/hbase/TableName;)[B
      98: invokespecial #167                // Method org/apache/hadoop/hbase/client/Delete."<init>":([B)V
     101: astore        6
     103: aload         6
     105: getstatic     #68                 // Field QUOTA_FAMILY_USAGE:[B
     108: getstatic     #156                // Field QUOTA_SNAPSHOT_SIZE_QUALIFIER:[B
     111: aload         5
     113: invokestatic  #154                // Method org/apache/hadoop/hbase/util/Bytes.toBytes:(Ljava/lang/String;)[B
     116: invokestatic  #155                // Method org/apache/hadoop/hbase/util/Bytes.add:([B[B)[B
     119: invokevirtual #168                // Method org/apache/hadoop/hbase/client/Delete.addColumns:([B[B)Lorg/apache/hadoop/hbase/client/Delete;
     122: pop
     123: aload_1
     124: aload         6
     126: invokeinterface #169,  2          // InterfaceMethod java/util/List.add:(Ljava/lang/Object;)Z
     131: pop
     132: goto          60
     135: goto          25
     138: aload_1
     139: areturn

  static java.util.List<org.apache.hadoop.hbase.client.Delete> createDeletesForExistingTableSnapshotSizes(org.apache.hadoop.hbase.client.Connection) throws java.io.IOException;
    Code:
       0: aload_0
       1: invokestatic  #170                // Method createScanForSpaceSnapshotSizes:()Lorg/apache/hadoop/hbase/client/Scan;
       4: invokestatic  #171                // Method createDeletesForExistingSnapshotsFromScan:(Lorg/apache/hadoop/hbase/client/Connection;Lorg/apache/hadoop/hbase/client/Scan;)Ljava/util/List;
       7: areturn

  static java.util.List<org.apache.hadoop.hbase.client.Delete> createDeletesForExistingNamespaceSnapshotSizes(java.util.Set<java.lang.String>);
    Code:
       0: new           #161                // class java/util/ArrayList
       3: dup
       4: invokespecial #162                // Method java/util/ArrayList."<init>":()V
       7: astore_1
       8: aload_0
       9: invokeinterface #132,  1          // InterfaceMethod java/util/Set.iterator:()Ljava/util/Iterator;
      14: astore_2
      15: aload_2
      16: invokeinterface #21,  1           // InterfaceMethod java/util/Iterator.hasNext:()Z
      21: ifeq          71
      24: aload_2
      25: invokeinterface #22,  1           // InterfaceMethod java/util/Iterator.next:()Ljava/lang/Object;
      30: checkcast     #24                 // class java/lang/String
      33: astore_3
      34: new           #166                // class org/apache/hadoop/hbase/client/Delete
      37: dup
      38: aload_3
      39: invokestatic  #4                  // Method getNamespaceRowKey:(Ljava/lang/String;)[B
      42: invokespecial #167                // Method org/apache/hadoop/hbase/client/Delete."<init>":([B)V
      45: astore        4
      47: aload         4
      49: getstatic     #68                 // Field QUOTA_FAMILY_USAGE:[B
      52: getstatic     #156                // Field QUOTA_SNAPSHOT_SIZE_QUALIFIER:[B
      55: invokevirtual #168                // Method org/apache/hadoop/hbase/client/Delete.addColumns:([B[B)Lorg/apache/hadoop/hbase/client/Delete;
      58: pop
      59: aload_1
      60: aload         4
      62: invokeinterface #169,  2          // InterfaceMethod java/util/List.add:(Ljava/lang/Object;)Z
      67: pop
      68: goto          15
      71: aload_1
      72: areturn

  static java.util.List<org.apache.hadoop.hbase.client.Delete> createDeletesForExistingNamespaceSnapshotSizes(org.apache.hadoop.hbase.client.Connection) throws java.io.IOException;
    Code:
       0: aload_0
       1: invokestatic  #172                // Method createScanForNamespaceSnapshotSizes:()Lorg/apache/hadoop/hbase/client/Scan;
       4: invokestatic  #171                // Method createDeletesForExistingSnapshotsFromScan:(Lorg/apache/hadoop/hbase/client/Connection;Lorg/apache/hadoop/hbase/client/Scan;)Ljava/util/List;
       7: areturn

  static java.util.List<org.apache.hadoop.hbase.client.Delete> createDeletesForExistingSnapshotsFromScan(org.apache.hadoop.hbase.client.Connection, org.apache.hadoop.hbase.client.Scan) throws java.io.IOException;
    Code:
       0: new           #161                // class java/util/ArrayList
       3: dup
       4: invokespecial #162                // Method java/util/ArrayList."<init>":()V
       7: astore_2
       8: aload_0
       9: getstatic     #57                 // Field QUOTA_TABLE_NAME:Lorg/apache/hadoop/hbase/TableName;
      12: invokeinterface #58,  2           // InterfaceMethod org/apache/hadoop/hbase/client/Connection.getTable:(Lorg/apache/hadoop/hbase/TableName;)Lorg/apache/hadoop/hbase/client/Table;
      17: astore_3
      18: aconst_null
      19: astore        4
      21: aload_3
      22: aload_1
      23: invokeinterface #60,  2           // InterfaceMethod org/apache/hadoop/hbase/client/Table.getScanner:(Lorg/apache/hadoop/hbase/client/Scan;)Lorg/apache/hadoop/hbase/client/ResultScanner;
      28: astore        5
      30: aconst_null
      31: astore        6
      33: aload         5
      35: invokeinterface #61,  1           // InterfaceMethod org/apache/hadoop/hbase/client/ResultScanner.iterator:()Ljava/util/Iterator;
      40: astore        7
      42: aload         7
      44: invokeinterface #21,  1           // InterfaceMethod java/util/Iterator.hasNext:()Z
      49: ifeq          181
      52: aload         7
      54: invokeinterface #22,  1           // InterfaceMethod java/util/Iterator.next:()Ljava/lang/Object;
      59: checkcast     #62                 // class org/apache/hadoop/hbase/client/Result
      62: astore        8
      64: aload         8
      66: invokevirtual #173                // Method org/apache/hadoop/hbase/client/Result.cellScanner:()Lorg/apache/hadoop/hbase/CellScanner;
      69: astore        9
      71: aload         9
      73: invokeinterface #174,  1          // InterfaceMethod org/apache/hadoop/hbase/CellScanner.advance:()Z
      78: ifeq          178
      81: aload         9
      83: invokeinterface #175,  1          // InterfaceMethod org/apache/hadoop/hbase/CellScanner.current:()Lorg/apache/hadoop/hbase/Cell;
      88: astore        10
      90: aload         10
      92: invokeinterface #176,  1          // InterfaceMethod org/apache/hadoop/hbase/Cell.getFamilyArray:()[B
      97: aload         10
      99: invokeinterface #177,  1          // InterfaceMethod org/apache/hadoop/hbase/Cell.getFamilyOffset:()I
     104: aload         10
     106: invokeinterface #178,  1          // InterfaceMethod org/apache/hadoop/hbase/Cell.getFamilyLength:()B
     111: invokestatic  #179                // Method org/apache/hadoop/hbase/util/Bytes.copy:([BII)[B
     114: astore        11
     116: aload         10
     118: invokeinterface #180,  1          // InterfaceMethod org/apache/hadoop/hbase/Cell.getQualifierArray:()[B
     123: aload         10
     125: invokeinterface #181,  1          // InterfaceMethod org/apache/hadoop/hbase/Cell.getQualifierOffset:()I
     130: aload         10
     132: invokeinterface #182,  1          // InterfaceMethod org/apache/hadoop/hbase/Cell.getQualifierLength:()I
     137: invokestatic  #179                // Method org/apache/hadoop/hbase/util/Bytes.copy:([BII)[B
     140: astore        12
     142: new           #166                // class org/apache/hadoop/hbase/client/Delete
     145: dup
     146: aload         8
     148: invokevirtual #76                 // Method org/apache/hadoop/hbase/client/Result.getRow:()[B
     151: invokespecial #167                // Method org/apache/hadoop/hbase/client/Delete."<init>":([B)V
     154: astore        13
     156: aload         13
     158: aload         11
     160: aload         12
     162: invokevirtual #168                // Method org/apache/hadoop/hbase/client/Delete.addColumns:([B[B)Lorg/apache/hadoop/hbase/client/Delete;
     165: pop
     166: aload_2
     167: aload         13
     169: invokeinterface #169,  2          // InterfaceMethod java/util/List.add:(Ljava/lang/Object;)Z
     174: pop
     175: goto          71
     178: goto          42
     181: aload_2
     182: astore        7
     184: aload         5
     186: ifnull        223
     189: aload         6
     191: ifnull        216
     194: aload         5
     196: invokeinterface #64,  1           // InterfaceMethod org/apache/hadoop/hbase/client/ResultScanner.close:()V
     201: goto          223
     204: astore        8
     206: aload         6
     208: aload         8
     210: invokevirtual #66                 // Method java/lang/Throwable.addSuppressed:(Ljava/lang/Throwable;)V
     213: goto          223
     216: aload         5
     218: invokeinterface #64,  1           // InterfaceMethod org/apache/hadoop/hbase/client/ResultScanner.close:()V
     223: aload_3
     224: ifnull        259
     227: aload         4
     229: ifnull        253
     232: aload_3
     233: invokeinterface #67,  1           // InterfaceMethod org/apache/hadoop/hbase/client/Table.close:()V
     238: goto          259
     241: astore        8
     243: aload         4
     245: aload         8
     247: invokevirtual #66                 // Method java/lang/Throwable.addSuppressed:(Ljava/lang/Throwable;)V
     250: goto          259
     253: aload_3
     254: invokeinterface #67,  1           // InterfaceMethod org/apache/hadoop/hbase/client/Table.close:()V
     259: aload         7
     261: areturn
     262: astore        7
     264: aload         7
     266: astore        6
     268: aload         7
     270: athrow
     271: astore        14
     273: aload         5
     275: ifnull        312
     278: aload         6
     280: ifnull        305
     283: aload         5
     285: invokeinterface #64,  1           // InterfaceMethod org/apache/hadoop/hbase/client/ResultScanner.close:()V
     290: goto          312
     293: astore        15
     295: aload         6
     297: aload         15
     299: invokevirtual #66                 // Method java/lang/Throwable.addSuppressed:(Ljava/lang/Throwable;)V
     302: goto          312
     305: aload         5
     307: invokeinterface #64,  1           // InterfaceMethod org/apache/hadoop/hbase/client/ResultScanner.close:()V
     312: aload         14
     314: athrow
     315: astore        5
     317: aload         5
     319: astore        4
     321: aload         5
     323: athrow
     324: astore        16
     326: aload_3
     327: ifnull        362
     330: aload         4
     332: ifnull        356
     335: aload_3
     336: invokeinterface #67,  1           // InterfaceMethod org/apache/hadoop/hbase/client/Table.close:()V
     341: goto          362
     344: astore        17
     346: aload         4
     348: aload         17
     350: invokevirtual #66                 // Method java/lang/Throwable.addSuppressed:(Ljava/lang/Throwable;)V
     353: goto          362
     356: aload_3
     357: invokeinterface #67,  1           // InterfaceMethod org/apache/hadoop/hbase/client/Table.close:()V
     362: aload         16
     364: athrow
    Exception table:
       from    to  target type
         194   201   204   Class java/lang/Throwable
         232   238   241   Class java/lang/Throwable
          33   184   262   Class java/lang/Throwable
          33   184   271   any
         283   290   293   Class java/lang/Throwable
         262   273   271   any
          21   223   315   Class java/lang/Throwable
         262   315   315   Class java/lang/Throwable
          21   223   324   any
         335   341   344   Class java/lang/Throwable
         262   326   324   any

  static long getNamespaceSnapshotSize(org.apache.hadoop.hbase.client.Connection, java.lang.String) throws java.io.IOException;
    Code:
       0: aload_0
       1: getstatic     #57                 // Field QUOTA_TABLE_NAME:Lorg/apache/hadoop/hbase/TableName;
       4: invokeinterface #58,  2           // InterfaceMethod org/apache/hadoop/hbase/client/Connection.getTable:(Lorg/apache/hadoop/hbase/TableName;)Lorg/apache/hadoop/hbase/client/Table;
       9: astore_2
      10: aconst_null
      11: astore_3
      12: aload_2
      13: aload_1
      14: invokestatic  #183                // Method createGetNamespaceSnapshotSize:(Ljava/lang/String;)Lorg/apache/hadoop/hbase/client/Get;
      17: invokeinterface #184,  2          // InterfaceMethod org/apache/hadoop/hbase/client/Table.get:(Lorg/apache/hadoop/hbase/client/Get;)Lorg/apache/hadoop/hbase/client/Result;
      22: astore        4
      24: aload         4
      26: invokevirtual #16                 // Method org/apache/hadoop/hbase/client/Result.isEmpty:()Z
      29: ifeq          72
      32: lconst_0
      33: lstore        5
      35: aload_2
      36: ifnull        69
      39: aload_3
      40: ifnull        63
      43: aload_2
      44: invokeinterface #67,  1           // InterfaceMethod org/apache/hadoop/hbase/client/Table.close:()V
      49: goto          69
      52: astore        7
      54: aload_3
      55: aload         7
      57: invokevirtual #66                 // Method java/lang/Throwable.addSuppressed:(Ljava/lang/Throwable;)V
      60: goto          69
      63: aload_2
      64: invokeinterface #67,  1           // InterfaceMethod org/apache/hadoop/hbase/client/Table.close:()V
      69: lload         5
      71: lreturn
      72: aload         4
      74: invokevirtual #185                // Method org/apache/hadoop/hbase/client/Result.advance:()Z
      77: pop
      78: aload         4
      80: invokevirtual #186                // Method org/apache/hadoop/hbase/client/Result.current:()Lorg/apache/hadoop/hbase/Cell;
      83: invokestatic  #187                // Method parseSnapshotSize:(Lorg/apache/hadoop/hbase/Cell;)J
      86: lstore        5
      88: aload_2
      89: ifnull        122
      92: aload_3
      93: ifnull        116
      96: aload_2
      97: invokeinterface #67,  1           // InterfaceMethod org/apache/hadoop/hbase/client/Table.close:()V
     102: goto          122
     105: astore        7
     107: aload_3
     108: aload         7
     110: invokevirtual #66                 // Method java/lang/Throwable.addSuppressed:(Ljava/lang/Throwable;)V
     113: goto          122
     116: aload_2
     117: invokeinterface #67,  1           // InterfaceMethod org/apache/hadoop/hbase/client/Table.close:()V
     122: lload         5
     124: lreturn
     125: astore        4
     127: aload         4
     129: astore_3
     130: aload         4
     132: athrow
     133: astore        8
     135: aload_2
     136: ifnull        169
     139: aload_3
     140: ifnull        163
     143: aload_2
     144: invokeinterface #67,  1           // InterfaceMethod org/apache/hadoop/hbase/client/Table.close:()V
     149: goto          169
     152: astore        9
     154: aload_3
     155: aload         9
     157: invokevirtual #66                 // Method java/lang/Throwable.addSuppressed:(Ljava/lang/Throwable;)V
     160: goto          169
     163: aload_2
     164: invokeinterface #67,  1           // InterfaceMethod org/apache/hadoop/hbase/client/Table.close:()V
     169: aload         8
     171: athrow
     172: astore_2
     173: new           #188                // class java/io/IOException
     176: dup
     177: new           #82                 // class java/lang/StringBuilder
     180: dup
     181: invokespecial #83                 // Method java/lang/StringBuilder."<init>":()V
     184: ldc           #189                // String Could not parse snapshot size value for namespace
     186: invokevirtual #85                 // Method java/lang/StringBuilder.append:(Ljava/lang/String;)Ljava/lang/StringBuilder;
     189: aload_1
     190: invokevirtual #85                 // Method java/lang/StringBuilder.append:(Ljava/lang/String;)Ljava/lang/StringBuilder;
     193: invokevirtual #89                 // Method java/lang/StringBuilder.toString:()Ljava/lang/String;
     196: aload_2
     197: invokespecial #190                // Method java/io/IOException."<init>":(Ljava/lang/String;Ljava/lang/Throwable;)V
     200: athrow
    Exception table:
       from    to  target type
          43    49    52   Class java/lang/Throwable
          96   102   105   Class java/lang/Throwable
          12    35   125   Class java/lang/Throwable
          72    88   125   Class java/lang/Throwable
          12    35   133   any
          72    88   133   any
         143   149   152   Class java/lang/Throwable
         125   135   133   any
           0    69   172   Class org/apache/hbase/thirdparty/com/google/protobuf/InvalidProtocolBufferException
          72   122   172   Class org/apache/hbase/thirdparty/com/google/protobuf/InvalidProtocolBufferException
         125   172   172   Class org/apache/hbase/thirdparty/com/google/protobuf/InvalidProtocolBufferException

  static org.apache.hadoop.hbase.client.Get createGetNamespaceSnapshotSize(java.lang.String);
    Code:
       0: new           #11                 // class org/apache/hadoop/hbase/client/Get
       3: dup
       4: aload_0
       5: invokestatic  #4                  // Method getNamespaceRowKey:(Ljava/lang/String;)[B
       8: invokespecial #12                 // Method org/apache/hadoop/hbase/client/Get."<init>":([B)V
      11: astore_1
      12: aload_1
      13: getstatic     #68                 // Field QUOTA_FAMILY_USAGE:[B
      16: getstatic     #156                // Field QUOTA_SNAPSHOT_SIZE_QUALIFIER:[B
      19: invokevirtual #14                 // Method org/apache/hadoop/hbase/client/Get.addColumn:([B[B)Lorg/apache/hadoop/hbase/client/Get;
      22: pop
      23: aload_1
      24: areturn

  static long parseSnapshotSize(org.apache.hadoop.hbase.Cell) throws org.apache.hbase.thirdparty.com.google.protobuf.InvalidProtocolBufferException;
    Code:
       0: aload_0
       1: invokeinterface #90,  1           // InterfaceMethod org/apache/hadoop/hbase/Cell.getValueArray:()[B
       6: aload_0
       7: invokeinterface #91,  1           // InterfaceMethod org/apache/hadoop/hbase/Cell.getValueOffset:()I
      12: aload_0
      13: invokeinterface #92,  1           // InterfaceMethod org/apache/hadoop/hbase/Cell.getValueLength:()I
      18: invokestatic  #93                 // Method org/apache/hbase/thirdparty/com/google/protobuf/UnsafeByteOperations.unsafeWrap:([BII)Lorg/apache/hbase/thirdparty/com/google/protobuf/ByteString;
      21: astore_1
      22: aload_1
      23: invokestatic  #94                 // Method org/apache/hadoop/hbase/shaded/protobuf/generated/QuotaProtos$SpaceQuotaSnapshot.parseFrom:(Lorg/apache/hbase/thirdparty/com/google/protobuf/ByteString;)Lorg/apache/hadoop/hbase/shaded/protobuf/generated/QuotaProtos$SpaceQuotaSnapshot;
      26: invokevirtual #191                // Method org/apache/hadoop/hbase/shaded/protobuf/generated/QuotaProtos$SpaceQuotaSnapshot.getQuotaUsage:()J
      29: lreturn

  static org.apache.hadoop.hbase.client.Scan createScanForNamespaceSnapshotSizes();
    Code:
       0: aconst_null
       1: invokestatic  #192                // Method createScanForNamespaceSnapshotSizes:(Ljava/lang/String;)Lorg/apache/hadoop/hbase/client/Scan;
       4: areturn

  static org.apache.hadoop.hbase.client.Scan createScanForNamespaceSnapshotSizes(java.lang.String);
    Code:
       0: new           #25                 // class org/apache/hadoop/hbase/client/Scan
       3: dup
       4: invokespecial #26                 // Method org/apache/hadoop/hbase/client/Scan."<init>":()V
       7: astore_1
       8: aload_0
       9: ifnull        19
      12: aload_0
      13: invokevirtual #193                // Method java/lang/String.isEmpty:()Z
      16: ifeq          30
      19: aload_1
      20: getstatic     #194                // Field QUOTA_NAMESPACE_ROW_KEY_PREFIX:[B
      23: invokevirtual #72                 // Method org/apache/hadoop/hbase/client/Scan.setRowPrefixFilter:([B)Lorg/apache/hadoop/hbase/client/Scan;
      26: pop
      27: goto          46
      30: aload_0
      31: invokestatic  #4                  // Method getNamespaceRowKey:(Ljava/lang/String;)[B
      34: astore_2
      35: aload_1
      36: aload_2
      37: invokevirtual #195                // Method org/apache/hadoop/hbase/client/Scan.withStartRow:([B)Lorg/apache/hadoop/hbase/client/Scan;
      40: aload_2
      41: iconst_1
      42: invokevirtual #74                 // Method org/apache/hadoop/hbase/client/Scan.withStopRow:([BZ)Lorg/apache/hadoop/hbase/client/Scan;
      45: pop
      46: aload_1
      47: getstatic     #68                 // Field QUOTA_FAMILY_USAGE:[B
      50: invokevirtual #27                 // Method org/apache/hadoop/hbase/client/Scan.addFamily:([B)Lorg/apache/hadoop/hbase/client/Scan;
      53: new           #196                // class org/apache/hadoop/hbase/filter/ColumnPrefixFilter
      56: dup
      57: getstatic     #156                // Field QUOTA_SNAPSHOT_SIZE_QUALIFIER:[B
      60: invokespecial #197                // Method org/apache/hadoop/hbase/filter/ColumnPrefixFilter."<init>":([B)V
      63: invokevirtual #30                 // Method org/apache/hadoop/hbase/client/Scan.setFilter:(Lorg/apache/hadoop/hbase/filter/Filter;)Lorg/apache/hadoop/hbase/client/Scan;
      66: areturn

  static org.apache.hadoop.hbase.client.Scan createScanForSpaceSnapshotSizes();
    Code:
       0: aconst_null
       1: invokestatic  #198                // Method createScanForSpaceSnapshotSizes:(Lorg/apache/hadoop/hbase/TableName;)Lorg/apache/hadoop/hbase/client/Scan;
       4: areturn

  static org.apache.hadoop.hbase.client.Scan createScanForSpaceSnapshotSizes(org.apache.hadoop.hbase.TableName);
    Code:
       0: new           #25                 // class org/apache/hadoop/hbase/client/Scan
       3: dup
       4: invokespecial #26                 // Method org/apache/hadoop/hbase/client/Scan."<init>":()V
       7: astore_1
       8: aconst_null
       9: aload_0
      10: if_acmpne     24
      13: aload_1
      14: getstatic     #71                 // Field QUOTA_TABLE_ROW_KEY_PREFIX:[B
      17: invokevirtual #72                 // Method org/apache/hadoop/hbase/client/Scan.setRowPrefixFilter:([B)Lorg/apache/hadoop/hbase/client/Scan;
      20: pop
      21: goto          40
      24: aload_0
      25: invokestatic  #2                  // Method getTableRowKey:(Lorg/apache/hadoop/hbase/TableName;)[B
      28: astore_2
      29: aload_1
      30: aload_2
      31: invokevirtual #195                // Method org/apache/hadoop/hbase/client/Scan.withStartRow:([B)Lorg/apache/hadoop/hbase/client/Scan;
      34: aload_2
      35: iconst_1
      36: invokevirtual #74                 // Method org/apache/hadoop/hbase/client/Scan.withStopRow:([BZ)Lorg/apache/hadoop/hbase/client/Scan;
      39: pop
      40: aload_1
      41: getstatic     #68                 // Field QUOTA_FAMILY_USAGE:[B
      44: invokevirtual #27                 // Method org/apache/hadoop/hbase/client/Scan.addFamily:([B)Lorg/apache/hadoop/hbase/client/Scan;
      47: new           #196                // class org/apache/hadoop/hbase/filter/ColumnPrefixFilter
      50: dup
      51: getstatic     #156                // Field QUOTA_SNAPSHOT_SIZE_QUALIFIER:[B
      54: invokespecial #197                // Method org/apache/hadoop/hbase/filter/ColumnPrefixFilter."<init>":([B)V
      57: invokevirtual #30                 // Method org/apache/hadoop/hbase/client/Scan.setFilter:(Lorg/apache/hadoop/hbase/filter/Filter;)Lorg/apache/hadoop/hbase/client/Scan;
      60: areturn

  public static java.util.Map<java.lang.String, java.lang.Long> getObservedSnapshotSizes(org.apache.hadoop.hbase.client.Connection) throws java.io.IOException;
    Code:
       0: aload_0
       1: getstatic     #57                 // Field QUOTA_TABLE_NAME:Lorg/apache/hadoop/hbase/TableName;
       4: invokeinterface #58,  2           // InterfaceMethod org/apache/hadoop/hbase/client/Connection.getTable:(Lorg/apache/hadoop/hbase/TableName;)Lorg/apache/hadoop/hbase/client/Table;
       9: astore_1
      10: aconst_null
      11: astore_2
      12: aload_1
      13: invokestatic  #170                // Method createScanForSpaceSnapshotSizes:()Lorg/apache/hadoop/hbase/client/Scan;
      16: invokeinterface #60,  2           // InterfaceMethod org/apache/hadoop/hbase/client/Table.getScanner:(Lorg/apache/hadoop/hbase/client/Scan;)Lorg/apache/hadoop/hbase/client/ResultScanner;
      21: astore_3
      22: aconst_null
      23: astore        4
      25: new           #55                 // class java/util/HashMap
      28: dup
      29: invokespecial #56                 // Method java/util/HashMap."<init>":()V
      32: astore        5
      34: aload_3
      35: invokeinterface #61,  1           // InterfaceMethod org/apache/hadoop/hbase/client/ResultScanner.iterator:()Ljava/util/Iterator;
      40: astore        6
      42: aload         6
      44: invokeinterface #21,  1           // InterfaceMethod java/util/Iterator.hasNext:()Z
      49: ifeq          125
      52: aload         6
      54: invokeinterface #22,  1           // InterfaceMethod java/util/Iterator.next:()Ljava/lang/Object;
      59: checkcast     #62                 // class org/apache/hadoop/hbase/client/Result
      62: astore        7
      64: aload         7
      66: invokevirtual #173                // Method org/apache/hadoop/hbase/client/Result.cellScanner:()Lorg/apache/hadoop/hbase/CellScanner;
      69: astore        8
      71: aload         8
      73: invokeinterface #174,  1          // InterfaceMethod org/apache/hadoop/hbase/CellScanner.advance:()Z
      78: ifeq          122
      81: aload         8
      83: invokeinterface #175,  1          // InterfaceMethod org/apache/hadoop/hbase/CellScanner.current:()Lorg/apache/hadoop/hbase/Cell;
      88: astore        9
      90: aload         9
      92: invokestatic  #199                // Method extractSnapshotNameFromSizeCell:(Lorg/apache/hadoop/hbase/Cell;)Ljava/lang/String;
      95: astore        10
      97: aload         9
      99: invokestatic  #187                // Method parseSnapshotSize:(Lorg/apache/hadoop/hbase/Cell;)J
     102: lstore        11
     104: aload         5
     106: aload         10
     108: lload         11
     110: invokestatic  #200                // Method java/lang/Long.valueOf:(J)Ljava/lang/Long;
     113: invokeinterface #96,  3           // InterfaceMethod java/util/Map.put:(Ljava/lang/Object;Ljava/lang/Object;)Ljava/lang/Object;
     118: pop
     119: goto          71
     122: goto          42
     125: aload         5
     127: astore        6
     129: aload_3
     130: ifnull        165
     133: aload         4
     135: ifnull        159
     138: aload_3
     139: invokeinterface #64,  1           // InterfaceMethod org/apache/hadoop/hbase/client/ResultScanner.close:()V
     144: goto          165
     147: astore        7
     149: aload         4
     151: aload         7
     153: invokevirtual #66                 // Method java/lang/Throwable.addSuppressed:(Ljava/lang/Throwable;)V
     156: goto          165
     159: aload_3
     160: invokeinterface #64,  1           // InterfaceMethod org/apache/hadoop/hbase/client/ResultScanner.close:()V
     165: aload_1
     166: ifnull        199
     169: aload_2
     170: ifnull        193
     173: aload_1
     174: invokeinterface #67,  1           // InterfaceMethod org/apache/hadoop/hbase/client/Table.close:()V
     179: goto          199
     182: astore        7
     184: aload_2
     185: aload         7
     187: invokevirtual #66                 // Method java/lang/Throwable.addSuppressed:(Ljava/lang/Throwable;)V
     190: goto          199
     193: aload_1
     194: invokeinterface #67,  1           // InterfaceMethod org/apache/hadoop/hbase/client/Table.close:()V
     199: aload         6
     201: areturn
     202: astore        5
     204: aload         5
     206: astore        4
     208: aload         5
     210: athrow
     211: astore        13
     213: aload_3
     214: ifnull        249
     217: aload         4
     219: ifnull        243
     222: aload_3
     223: invokeinterface #64,  1           // InterfaceMethod org/apache/hadoop/hbase/client/ResultScanner.close:()V
     228: goto          249
     231: astore        14
     233: aload         4
     235: aload         14
     237: invokevirtual #66                 // Method java/lang/Throwable.addSuppressed:(Ljava/lang/Throwable;)V
     240: goto          249
     243: aload_3
     244: invokeinterface #64,  1           // InterfaceMethod org/apache/hadoop/hbase/client/ResultScanner.close:()V
     249: aload         13
     251: athrow
     252: astore_3
     253: aload_3
     254: astore_2
     255: aload_3
     256: athrow
     257: astore        15
     259: aload_1
     260: ifnull        293
     263: aload_2
     264: ifnull        287
     267: aload_1
     268: invokeinterface #67,  1           // InterfaceMethod org/apache/hadoop/hbase/client/Table.close:()V
     273: goto          293
     276: astore        16
     278: aload_2
     279: aload         16
     281: invokevirtual #66                 // Method java/lang/Throwable.addSuppressed:(Ljava/lang/Throwable;)V
     284: goto          293
     287: aload_1
     288: invokeinterface #67,  1           // InterfaceMethod org/apache/hadoop/hbase/client/Table.close:()V
     293: aload         15
     295: athrow
    Exception table:
       from    to  target type
         138   144   147   Class java/lang/Throwable
         173   179   182   Class java/lang/Throwable
          25   129   202   Class java/lang/Throwable
          25   129   211   any
         222   228   231   Class java/lang/Throwable
         202   213   211   any
          12   165   252   Class java/lang/Throwable
         202   252   252   Class java/lang/Throwable
          12   165   257   any
         267   273   276   Class java/lang/Throwable
         202   259   257   any

  public static org.apache.hbase.thirdparty.com.google.common.collect.Multimap<org.apache.hadoop.hbase.TableName, java.lang.String> getTableSnapshots(org.apache.hadoop.hbase.client.Connection) throws java.io.IOException;
    Code:
       0: aload_0
       1: getstatic     #57                 // Field QUOTA_TABLE_NAME:Lorg/apache/hadoop/hbase/TableName;
       4: invokeinterface #58,  2           // InterfaceMethod org/apache/hadoop/hbase/client/Connection.getTable:(Lorg/apache/hadoop/hbase/TableName;)Lorg/apache/hadoop/hbase/client/Table;
       9: astore_1
      10: aconst_null
      11: astore_2
      12: aload_1
      13: invokestatic  #170                // Method createScanForSpaceSnapshotSizes:()Lorg/apache/hadoop/hbase/client/Scan;
      16: invokeinterface #60,  2           // InterfaceMethod org/apache/hadoop/hbase/client/Table.getScanner:(Lorg/apache/hadoop/hbase/client/Scan;)Lorg/apache/hadoop/hbase/client/ResultScanner;
      21: astore_3
      22: aconst_null
      23: astore        4
      25: invokestatic  #201                // Method org/apache/hbase/thirdparty/com/google/common/collect/HashMultimap.create:()Lorg/apache/hbase/thirdparty/com/google/common/collect/HashMultimap;
      28: astore        5
      30: aload_3
      31: invokeinterface #61,  1           // InterfaceMethod org/apache/hadoop/hbase/client/ResultScanner.iterator:()Ljava/util/Iterator;
      36: astore        6
      38: aload         6
      40: invokeinterface #21,  1           // InterfaceMethod java/util/Iterator.hasNext:()Z
      45: ifeq          117
      48: aload         6
      50: invokeinterface #22,  1           // InterfaceMethod java/util/Iterator.next:()Ljava/lang/Object;
      55: checkcast     #62                 // class org/apache/hadoop/hbase/client/Result
      58: astore        7
      60: aload         7
      62: invokevirtual #173                // Method org/apache/hadoop/hbase/client/Result.cellScanner:()Lorg/apache/hadoop/hbase/CellScanner;
      65: astore        8
      67: aload         8
      69: invokeinterface #174,  1          // InterfaceMethod org/apache/hadoop/hbase/CellScanner.advance:()Z
      74: ifeq          114
      77: aload         8
      79: invokeinterface #175,  1          // InterfaceMethod org/apache/hadoop/hbase/CellScanner.current:()Lorg/apache/hadoop/hbase/Cell;
      84: astore        9
      86: aload         9
      88: invokestatic  #199                // Method extractSnapshotNameFromSizeCell:(Lorg/apache/hadoop/hbase/Cell;)Ljava/lang/String;
      91: astore        10
      93: aload         5
      95: aload         7
      97: invokevirtual #76                 // Method org/apache/hadoop/hbase/client/Result.getRow:()[B
     100: invokestatic  #80                 // Method getTableFromRowKey:([B)Lorg/apache/hadoop/hbase/TableName;
     103: aload         10
     105: invokeinterface #202,  3          // InterfaceMethod org/apache/hbase/thirdparty/com/google/common/collect/Multimap.put:(Ljava/lang/Object;Ljava/lang/Object;)Z
     110: pop
     111: goto          67
     114: goto          38
     117: aload         5
     119: astore        6
     121: aload_3
     122: ifnull        157
     125: aload         4
     127: ifnull        151
     130: aload_3
     131: invokeinterface #64,  1           // InterfaceMethod org/apache/hadoop/hbase/client/ResultScanner.close:()V
     136: goto          157
     139: astore        7
     141: aload         4
     143: aload         7
     145: invokevirtual #66                 // Method java/lang/Throwable.addSuppressed:(Ljava/lang/Throwable;)V
     148: goto          157
     151: aload_3
     152: invokeinterface #64,  1           // InterfaceMethod org/apache/hadoop/hbase/client/ResultScanner.close:()V
     157: aload_1
     158: ifnull        191
     161: aload_2
     162: ifnull        185
     165: aload_1
     166: invokeinterface #67,  1           // InterfaceMethod org/apache/hadoop/hbase/client/Table.close:()V
     171: goto          191
     174: astore        7
     176: aload_2
     177: aload         7
     179: invokevirtual #66                 // Method java/lang/Throwable.addSuppressed:(Ljava/lang/Throwable;)V
     182: goto          191
     185: aload_1
     186: invokeinterface #67,  1           // InterfaceMethod org/apache/hadoop/hbase/client/Table.close:()V
     191: aload         6
     193: areturn
     194: astore        5
     196: aload         5
     198: astore        4
     200: aload         5
     202: athrow
     203: astore        11
     205: aload_3
     206: ifnull        241
     209: aload         4
     211: ifnull        235
     214: aload_3
     215: invokeinterface #64,  1           // InterfaceMethod org/apache/hadoop/hbase/client/ResultScanner.close:()V
     220: goto          241
     223: astore        12
     225: aload         4
     227: aload         12
     229: invokevirtual #66                 // Method java/lang/Throwable.addSuppressed:(Ljava/lang/Throwable;)V
     232: goto          241
     235: aload_3
     236: invokeinterface #64,  1           // InterfaceMethod org/apache/hadoop/hbase/client/ResultScanner.close:()V
     241: aload         11
     243: athrow
     244: astore_3
     245: aload_3
     246: astore_2
     247: aload_3
     248: athrow
     249: astore        13
     251: aload_1
     252: ifnull        285
     255: aload_2
     256: ifnull        279
     259: aload_1
     260: invokeinterface #67,  1           // InterfaceMethod org/apache/hadoop/hbase/client/Table.close:()V
     265: goto          285
     268: astore        14
     270: aload_2
     271: aload         14
     273: invokevirtual #66                 // Method java/lang/Throwable.addSuppressed:(Ljava/lang/Throwable;)V
     276: goto          285
     279: aload_1
     280: invokeinterface #67,  1           // InterfaceMethod org/apache/hadoop/hbase/client/Table.close:()V
     285: aload         13
     287: athrow
    Exception table:
       from    to  target type
         130   136   139   Class java/lang/Throwable
         165   171   174   Class java/lang/Throwable
          25   121   194   Class java/lang/Throwable
          25   121   203   any
         214   220   223   Class java/lang/Throwable
         194   205   203   any
          12   157   244   Class java/lang/Throwable
         194   244   244   Class java/lang/Throwable
          12   157   249   any
         259   265   268   Class java/lang/Throwable
         194   251   249   any

  public static java.util.Set<java.lang.String> getNamespaceSnapshots(org.apache.hadoop.hbase.client.Connection) throws java.io.IOException;
    Code:
       0: aload_0
       1: getstatic     #57                 // Field QUOTA_TABLE_NAME:Lorg/apache/hadoop/hbase/TableName;
       4: invokeinterface #58,  2           // InterfaceMethod org/apache/hadoop/hbase/client/Connection.getTable:(Lorg/apache/hadoop/hbase/TableName;)Lorg/apache/hadoop/hbase/client/Table;
       9: astore_1
      10: aconst_null
      11: astore_2
      12: aload_1
      13: invokestatic  #172                // Method createScanForNamespaceSnapshotSizes:()Lorg/apache/hadoop/hbase/client/Scan;
      16: invokeinterface #60,  2           // InterfaceMethod org/apache/hadoop/hbase/client/Table.getScanner:(Lorg/apache/hadoop/hbase/client/Scan;)Lorg/apache/hadoop/hbase/client/ResultScanner;
      21: astore_3
      22: aconst_null
      23: astore        4
      25: new           #203                // class java/util/HashSet
      28: dup
      29: invokespecial #204                // Method java/util/HashSet."<init>":()V
      32: astore        5
      34: aload_3
      35: invokeinterface #61,  1           // InterfaceMethod org/apache/hadoop/hbase/client/ResultScanner.iterator:()Ljava/util/Iterator;
      40: astore        6
      42: aload         6
      44: invokeinterface #21,  1           // InterfaceMethod java/util/Iterator.hasNext:()Z
      49: ifeq          111
      52: aload         6
      54: invokeinterface #22,  1           // InterfaceMethod java/util/Iterator.next:()Ljava/lang/Object;
      59: checkcast     #62                 // class org/apache/hadoop/hbase/client/Result
      62: astore        7
      64: aload         7
      66: invokevirtual #173                // Method org/apache/hadoop/hbase/client/Result.cellScanner:()Lorg/apache/hadoop/hbase/CellScanner;
      69: astore        8
      71: aload         8
      73: invokeinterface #174,  1          // InterfaceMethod org/apache/hadoop/hbase/CellScanner.advance:()Z
      78: ifeq          108
      81: aload         8
      83: invokeinterface #175,  1          // InterfaceMethod org/apache/hadoop/hbase/CellScanner.current:()Lorg/apache/hadoop/hbase/Cell;
      88: pop
      89: aload         5
      91: aload         7
      93: invokevirtual #76                 // Method org/apache/hadoop/hbase/client/Result.getRow:()[B
      96: invokestatic  #119                // Method getNamespaceFromRowKey:([B)Ljava/lang/String;
      99: invokeinterface #205,  2          // InterfaceMethod java/util/Set.add:(Ljava/lang/Object;)Z
     104: pop
     105: goto          71
     108: goto          42
     111: aload         5
     113: astore        6
     115: aload_3
     116: ifnull        151
     119: aload         4
     121: ifnull        145
     124: aload_3
     125: invokeinterface #64,  1           // InterfaceMethod org/apache/hadoop/hbase/client/ResultScanner.close:()V
     130: goto          151
     133: astore        7
     135: aload         4
     137: aload         7
     139: invokevirtual #66                 // Method java/lang/Throwable.addSuppressed:(Ljava/lang/Throwable;)V
     142: goto          151
     145: aload_3
     146: invokeinterface #64,  1           // InterfaceMethod org/apache/hadoop/hbase/client/ResultScanner.close:()V
     151: aload_1
     152: ifnull        185
     155: aload_2
     156: ifnull        179
     159: aload_1
     160: invokeinterface #67,  1           // InterfaceMethod org/apache/hadoop/hbase/client/Table.close:()V
     165: goto          185
     168: astore        7
     170: aload_2
     171: aload         7
     173: invokevirtual #66                 // Method java/lang/Throwable.addSuppressed:(Ljava/lang/Throwable;)V
     176: goto          185
     179: aload_1
     180: invokeinterface #67,  1           // InterfaceMethod org/apache/hadoop/hbase/client/Table.close:()V
     185: aload         6
     187: areturn
     188: astore        5
     190: aload         5
     192: astore        4
     194: aload         5
     196: athrow
     197: astore        9
     199: aload_3
     200: ifnull        235
     203: aload         4
     205: ifnull        229
     208: aload_3
     209: invokeinterface #64,  1           // InterfaceMethod org/apache/hadoop/hbase/client/ResultScanner.close:()V
     214: goto          235
     217: astore        10
     219: aload         4
     221: aload         10
     223: invokevirtual #66                 // Method java/lang/Throwable.addSuppressed:(Ljava/lang/Throwable;)V
     226: goto          235
     229: aload_3
     230: invokeinterface #64,  1           // InterfaceMethod org/apache/hadoop/hbase/client/ResultScanner.close:()V
     235: aload         9
     237: athrow
     238: astore_3
     239: aload_3
     240: astore_2
     241: aload_3
     242: athrow
     243: astore        11
     245: aload_1
     246: ifnull        279
     249: aload_2
     250: ifnull        273
     253: aload_1
     254: invokeinterface #67,  1           // InterfaceMethod org/apache/hadoop/hbase/client/Table.close:()V
     259: goto          279
     262: astore        12
     264: aload_2
     265: aload         12
     267: invokevirtual #66                 // Method java/lang/Throwable.addSuppressed:(Ljava/lang/Throwable;)V
     270: goto          279
     273: aload_1
     274: invokeinterface #67,  1           // InterfaceMethod org/apache/hadoop/hbase/client/Table.close:()V
     279: aload         11
     281: athrow
    Exception table:
       from    to  target type
         124   130   133   Class java/lang/Throwable
         159   165   168   Class java/lang/Throwable
          25   115   188   Class java/lang/Throwable
          25   115   197   any
         208   214   217   Class java/lang/Throwable
         188   199   197   any
          12   151   238   Class java/lang/Throwable
         188   238   238   Class java/lang/Throwable
          12   151   243   any
         253   259   262   Class java/lang/Throwable
         188   245   243   any

  public static org.apache.hadoop.hbase.quotas.SpaceQuotaSnapshot getCurrentSnapshotFromQuotaTable(org.apache.hadoop.hbase.client.Connection, org.apache.hadoop.hbase.TableName) throws java.io.IOException;
    Code:
       0: aload_0
       1: getstatic     #57                 // Field QUOTA_TABLE_NAME:Lorg/apache/hadoop/hbase/TableName;
       4: invokeinterface #58,  2           // InterfaceMethod org/apache/hadoop/hbase/client/Connection.getTable:(Lorg/apache/hadoop/hbase/TableName;)Lorg/apache/hadoop/hbase/client/Table;
       9: astore_2
      10: aconst_null
      11: astore_3
      12: new           #55                 // class java/util/HashMap
      15: dup
      16: iconst_1
      17: invokespecial #206                // Method java/util/HashMap."<init>":(I)V
      20: astore        4
      22: aload_2
      23: aload_1
      24: invokestatic  #207                // Method makeQuotaSnapshotGetForTable:(Lorg/apache/hadoop/hbase/TableName;)Lorg/apache/hadoop/hbase/client/Get;
      27: invokeinterface #184,  2          // InterfaceMethod org/apache/hadoop/hbase/client/Table.get:(Lorg/apache/hadoop/hbase/client/Get;)Lorg/apache/hadoop/hbase/client/Result;
      32: astore        5
      34: aload         5
      36: invokevirtual #16                 // Method org/apache/hadoop/hbase/client/Result.isEmpty:()Z
      39: ifeq          82
      42: aconst_null
      43: astore        6
      45: aload_2
      46: ifnull        79
      49: aload_3
      50: ifnull        73
      53: aload_2
      54: invokeinterface #67,  1           // InterfaceMethod org/apache/hadoop/hbase/client/Table.close:()V
      59: goto          79
      62: astore        7
      64: aload_3
      65: aload         7
      67: invokevirtual #66                 // Method java/lang/Throwable.addSuppressed:(Ljava/lang/Throwable;)V
      70: goto          79
      73: aload_2
      74: invokeinterface #67,  1           // InterfaceMethod org/apache/hadoop/hbase/client/Table.close:()V
      79: aload         6
      81: areturn
      82: aload         5
      84: aload         4
      86: invokestatic  #63                 // Method extractQuotaSnapshot:(Lorg/apache/hadoop/hbase/client/Result;Ljava/util/Map;)V
      89: aload         4
      91: aload_1
      92: invokeinterface #208,  2          // InterfaceMethod java/util/Map.get:(Ljava/lang/Object;)Ljava/lang/Object;
      97: checkcast     #209                // class org/apache/hadoop/hbase/quotas/SpaceQuotaSnapshot
     100: astore        6
     102: aload_2
     103: ifnull        136
     106: aload_3
     107: ifnull        130
     110: aload_2
     111: invokeinterface #67,  1           // InterfaceMethod org/apache/hadoop/hbase/client/Table.close:()V
     116: goto          136
     119: astore        7
     121: aload_3
     122: aload         7
     124: invokevirtual #66                 // Method java/lang/Throwable.addSuppressed:(Ljava/lang/Throwable;)V
     127: goto          136
     130: aload_2
     131: invokeinterface #67,  1           // InterfaceMethod org/apache/hadoop/hbase/client/Table.close:()V
     136: aload         6
     138: areturn
     139: astore        4
     141: aload         4
     143: astore_3
     144: aload         4
     146: athrow
     147: astore        8
     149: aload_2
     150: ifnull        183
     153: aload_3
     154: ifnull        177
     157: aload_2
     158: invokeinterface #67,  1           // InterfaceMethod org/apache/hadoop/hbase/client/Table.close:()V
     163: goto          183
     166: astore        9
     168: aload_3
     169: aload         9
     171: invokevirtual #66                 // Method java/lang/Throwable.addSuppressed:(Ljava/lang/Throwable;)V
     174: goto          183
     177: aload_2
     178: invokeinterface #67,  1           // InterfaceMethod org/apache/hadoop/hbase/client/Table.close:()V
     183: aload         8
     185: athrow
    Exception table:
       from    to  target type
          53    59    62   Class java/lang/Throwable
         110   116   119   Class java/lang/Throwable
          12    45   139   Class java/lang/Throwable
          82   102   139   Class java/lang/Throwable
          12    45   147   any
          82   102   147   any
         157   163   166   Class java/lang/Throwable
         139   149   147   any

  protected static org.apache.hadoop.hbase.shaded.protobuf.generated.QuotaProtos$Quotas quotasFromData(byte[]) throws java.io.IOException;
    Code:
       0: aload_0
       1: iconst_0
       2: aload_0
       3: arraylength
       4: invokestatic  #210                // Method quotasFromData:([BII)Lorg/apache/hadoop/hbase/shaded/protobuf/generated/QuotaProtos$Quotas;
       7: areturn

  protected static org.apache.hadoop.hbase.shaded.protobuf.generated.QuotaProtos$Quotas quotasFromData(byte[], int, int) throws java.io.IOException;
    Code:
       0: invokestatic  #211                // Method org/apache/hadoop/hbase/protobuf/ProtobufMagic.lengthOfPBMagic:()I
       3: istore_3
       4: aload_0
       5: iload_1
       6: iload_3
       7: invokestatic  #212                // Method org/apache/hadoop/hbase/protobuf/ProtobufMagic.isPBMagicPrefix:([BII)Z
      10: ifne          23
      13: new           #188                // class java/io/IOException
      16: dup
      17: ldc           #213                // String Missing pb magic prefix
      19: invokespecial #214                // Method java/io/IOException."<init>":(Ljava/lang/String;)V
      22: athrow
      23: new           #215                // class java/io/ByteArrayInputStream
      26: dup
      27: aload_0
      28: iload_1
      29: iload_3
      30: iadd
      31: iload_2
      32: iload_3
      33: isub
      34: invokespecial #216                // Method java/io/ByteArrayInputStream."<init>":([BII)V
      37: invokestatic  #217                // Method org/apache/hadoop/hbase/shaded/protobuf/generated/QuotaProtos$Quotas.parseFrom:(Ljava/io/InputStream;)Lorg/apache/hadoop/hbase/shaded/protobuf/generated/QuotaProtos$Quotas;
      40: areturn

  protected static byte[] quotasToData(org.apache.hadoop.hbase.shaded.protobuf.generated.QuotaProtos$Quotas) throws java.io.IOException;
    Code:
       0: new           #218                // class java/io/ByteArrayOutputStream
       3: dup
       4: invokespecial #219                // Method java/io/ByteArrayOutputStream."<init>":()V
       7: astore_1
       8: aload_1
       9: getstatic     #220                // Field org/apache/hadoop/hbase/protobuf/ProtobufMagic.PB_MAGIC:[B
      12: invokevirtual #221                // Method java/io/ByteArrayOutputStream.write:([B)V
      15: aload_0
      16: aload_1
      17: invokevirtual #222                // Method org/apache/hadoop/hbase/shaded/protobuf/generated/QuotaProtos$Quotas.writeTo:(Ljava/io/OutputStream;)V
      20: aload_1
      21: invokevirtual #223                // Method java/io/ByteArrayOutputStream.toByteArray:()[B
      24: areturn

  public static boolean isEmptyQuota(org.apache.hadoop.hbase.shaded.protobuf.generated.QuotaProtos$Quotas);
    Code:
       0: iconst_0
       1: istore_1
       2: iload_1
       3: aload_0
       4: invokevirtual #224                // Method org/apache/hadoop/hbase/shaded/protobuf/generated/QuotaProtos$Quotas.hasThrottle:()Z
       7: ior
       8: istore_1
       9: iload_1
      10: aload_0
      11: invokevirtual #225                // Method org/apache/hadoop/hbase/shaded/protobuf/generated/QuotaProtos$Quotas.hasBypassGlobals:()Z
      14: ior
      15: istore_1
      16: aload_0
      17: invokevirtual #226                // Method org/apache/hadoop/hbase/shaded/protobuf/generated/QuotaProtos$Quotas.hasSpace:()Z
      20: ifeq          51
      23: iload_1
      24: aload_0
      25: invokevirtual #227                // Method org/apache/hadoop/hbase/shaded/protobuf/generated/QuotaProtos$Quotas.getSpace:()Lorg/apache/hadoop/hbase/shaded/protobuf/generated/QuotaProtos$SpaceQuota;
      28: invokevirtual #228                // Method org/apache/hadoop/hbase/shaded/protobuf/generated/QuotaProtos$SpaceQuota.hasSoftLimit:()Z
      31: ifeq          48
      34: aload_0
      35: invokevirtual #227                // Method org/apache/hadoop/hbase/shaded/protobuf/generated/QuotaProtos$Quotas.getSpace:()Lorg/apache/hadoop/hbase/shaded/protobuf/generated/QuotaProtos$SpaceQuota;
      38: invokevirtual #229                // Method org/apache/hadoop/hbase/shaded/protobuf/generated/QuotaProtos$SpaceQuota.hasViolationPolicy:()Z
      41: ifeq          48
      44: iconst_1
      45: goto          49
      48: iconst_0
      49: ior
      50: istore_1
      51: iload_1
      52: ifne          59
      55: iconst_1
      56: goto          60
      59: iconst_0
      60: ireturn

  protected static org.apache.hadoop.hbase.client.Result doGet(org.apache.hadoop.hbase.client.Connection, org.apache.hadoop.hbase.client.Get) throws java.io.IOException;
    Code:
       0: aload_0
       1: getstatic     #57                 // Field QUOTA_TABLE_NAME:Lorg/apache/hadoop/hbase/TableName;
       4: invokeinterface #58,  2           // InterfaceMethod org/apache/hadoop/hbase/client/Connection.getTable:(Lorg/apache/hadoop/hbase/TableName;)Lorg/apache/hadoop/hbase/client/Table;
       9: astore_2
      10: aconst_null
      11: astore_3
      12: aload_2
      13: aload_1
      14: invokeinterface #184,  2          // InterfaceMethod org/apache/hadoop/hbase/client/Table.get:(Lorg/apache/hadoop/hbase/client/Get;)Lorg/apache/hadoop/hbase/client/Result;
      19: astore        4
      21: aload_2
      22: ifnull        55
      25: aload_3
      26: ifnull        49
      29: aload_2
      30: invokeinterface #67,  1           // InterfaceMethod org/apache/hadoop/hbase/client/Table.close:()V
      35: goto          55
      38: astore        5
      40: aload_3
      41: aload         5
      43: invokevirtual #66                 // Method java/lang/Throwable.addSuppressed:(Ljava/lang/Throwable;)V
      46: goto          55
      49: aload_2
      50: invokeinterface #67,  1           // InterfaceMethod org/apache/hadoop/hbase/client/Table.close:()V
      55: aload         4
      57: areturn
      58: astore        4
      60: aload         4
      62: astore_3
      63: aload         4
      65: athrow
      66: astore        6
      68: aload_2
      69: ifnull        102
      72: aload_3
      73: ifnull        96
      76: aload_2
      77: invokeinterface #67,  1           // InterfaceMethod org/apache/hadoop/hbase/client/Table.close:()V
      82: goto          102
      85: astore        7
      87: aload_3
      88: aload         7
      90: invokevirtual #66                 // Method java/lang/Throwable.addSuppressed:(Ljava/lang/Throwable;)V
      93: goto          102
      96: aload_2
      97: invokeinterface #67,  1           // InterfaceMethod org/apache/hadoop/hbase/client/Table.close:()V
     102: aload         6
     104: athrow
    Exception table:
       from    to  target type
          29    35    38   Class java/lang/Throwable
          12    21    58   Class java/lang/Throwable
          12    21    66   any
          76    82    85   Class java/lang/Throwable
          58    68    66   any

  protected static org.apache.hadoop.hbase.client.Result[] doGet(org.apache.hadoop.hbase.client.Connection, java.util.List<org.apache.hadoop.hbase.client.Get>) throws java.io.IOException;
    Code:
       0: aload_0
       1: getstatic     #57                 // Field QUOTA_TABLE_NAME:Lorg/apache/hadoop/hbase/TableName;
       4: invokeinterface #58,  2           // InterfaceMethod org/apache/hadoop/hbase/client/Connection.getTable:(Lorg/apache/hadoop/hbase/TableName;)Lorg/apache/hadoop/hbase/client/Table;
       9: astore_2
      10: aconst_null
      11: astore_3
      12: aload_2
      13: aload_1
      14: invokeinterface #230,  2          // InterfaceMethod org/apache/hadoop/hbase/client/Table.get:(Ljava/util/List;)[Lorg/apache/hadoop/hbase/client/Result;
      19: astore        4
      21: aload_2
      22: ifnull        55
      25: aload_3
      26: ifnull        49
      29: aload_2
      30: invokeinterface #67,  1           // InterfaceMethod org/apache/hadoop/hbase/client/Table.close:()V
      35: goto          55
      38: astore        5
      40: aload_3
      41: aload         5
      43: invokevirtual #66                 // Method java/lang/Throwable.addSuppressed:(Ljava/lang/Throwable;)V
      46: goto          55
      49: aload_2
      50: invokeinterface #67,  1           // InterfaceMethod org/apache/hadoop/hbase/client/Table.close:()V
      55: aload         4
      57: areturn
      58: astore        4
      60: aload         4
      62: astore_3
      63: aload         4
      65: athrow
      66: astore        6
      68: aload_2
      69: ifnull        102
      72: aload_3
      73: ifnull        96
      76: aload_2
      77: invokeinterface #67,  1           // InterfaceMethod org/apache/hadoop/hbase/client/Table.close:()V
      82: goto          102
      85: astore        7
      87: aload_3
      88: aload         7
      90: invokevirtual #66                 // Method java/lang/Throwable.addSuppressed:(Ljava/lang/Throwable;)V
      93: goto          102
      96: aload_2
      97: invokeinterface #67,  1           // InterfaceMethod org/apache/hadoop/hbase/client/Table.close:()V
     102: aload         6
     104: athrow
    Exception table:
       from    to  target type
          29    35    38   Class java/lang/Throwable
          12    21    58   Class java/lang/Throwable
          12    21    66   any
          76    82    85   Class java/lang/Throwable
          58    68    66   any

  protected static byte[] getUserRowKey(java.lang.String);
    Code:
       0: getstatic     #231                // Field QUOTA_USER_ROW_KEY_PREFIX:[B
       3: aload_0
       4: invokestatic  #154                // Method org/apache/hadoop/hbase/util/Bytes.toBytes:(Ljava/lang/String;)[B
       7: invokestatic  #155                // Method org/apache/hadoop/hbase/util/Bytes.add:([B[B)[B
      10: areturn

  protected static byte[] getTableRowKey(org.apache.hadoop.hbase.TableName);
    Code:
       0: getstatic     #71                 // Field QUOTA_TABLE_ROW_KEY_PREFIX:[B
       3: aload_0
       4: invokevirtual #232                // Method org/apache/hadoop/hbase/TableName.getName:()[B
       7: invokestatic  #155                // Method org/apache/hadoop/hbase/util/Bytes.add:([B[B)[B
      10: areturn

  protected static byte[] getNamespaceRowKey(java.lang.String);
    Code:
       0: getstatic     #194                // Field QUOTA_NAMESPACE_ROW_KEY_PREFIX:[B
       3: aload_0
       4: invokestatic  #154                // Method org/apache/hadoop/hbase/util/Bytes.toBytes:(Ljava/lang/String;)[B
       7: invokestatic  #155                // Method org/apache/hadoop/hbase/util/Bytes.add:([B[B)[B
      10: areturn

  protected static byte[] getRegionServerRowKey(java.lang.String);
    Code:
       0: getstatic     #233                // Field QUOTA_REGION_SERVER_ROW_KEY_PREFIX:[B
       3: aload_0
       4: invokestatic  #154                // Method org/apache/hadoop/hbase/util/Bytes.toBytes:(Ljava/lang/String;)[B
       7: invokestatic  #155                // Method org/apache/hadoop/hbase/util/Bytes.add:([B[B)[B
      10: areturn

  protected static byte[] getSettingsQualifierForUserTable(org.apache.hadoop.hbase.TableName);
    Code:
       0: getstatic     #137                // Field QUOTA_QUALIFIER_SETTINGS_PREFIX:[B
       3: aload_0
       4: invokevirtual #232                // Method org/apache/hadoop/hbase/TableName.getName:()[B
       7: invokestatic  #155                // Method org/apache/hadoop/hbase/util/Bytes.add:([B[B)[B
      10: areturn

  protected static byte[] getSettingsQualifierForUserNamespace(java.lang.String);
    Code:
       0: getstatic     #137                // Field QUOTA_QUALIFIER_SETTINGS_PREFIX:[B
       3: new           #82                 // class java/lang/StringBuilder
       6: dup
       7: invokespecial #83                 // Method java/lang/StringBuilder."<init>":()V
      10: aload_0
      11: invokevirtual #85                 // Method java/lang/StringBuilder.append:(Ljava/lang/String;)Ljava/lang/StringBuilder;
      14: bipush        58
      16: invokevirtual #234                // Method java/lang/StringBuilder.append:(C)Ljava/lang/StringBuilder;
      19: invokevirtual #89                 // Method java/lang/StringBuilder.toString:()Ljava/lang/String;
      22: invokestatic  #154                // Method org/apache/hadoop/hbase/util/Bytes.toBytes:(Ljava/lang/String;)[B
      25: invokestatic  #155                // Method org/apache/hadoop/hbase/util/Bytes.add:([B[B)[B
      28: areturn

  protected static java.lang.String getUserRowKeyRegex(java.lang.String);
    Code:
       0: getstatic     #231                // Field QUOTA_USER_ROW_KEY_PREFIX:[B
       3: aload_0
       4: invokestatic  #235                // Method getRowKeyRegEx:([BLjava/lang/String;)Ljava/lang/String;
       7: areturn

  protected static java.lang.String getTableRowKeyRegex(java.lang.String);
    Code:
       0: getstatic     #71                 // Field QUOTA_TABLE_ROW_KEY_PREFIX:[B
       3: aload_0
       4: invokestatic  #235                // Method getRowKeyRegEx:([BLjava/lang/String;)Ljava/lang/String;
       7: areturn

  protected static java.lang.String getNamespaceRowKeyRegex(java.lang.String);
    Code:
       0: getstatic     #194                // Field QUOTA_NAMESPACE_ROW_KEY_PREFIX:[B
       3: aload_0
       4: invokestatic  #235                // Method getRowKeyRegEx:([BLjava/lang/String;)Ljava/lang/String;
       7: areturn

  protected static byte[] getExceedThrottleQuotaRowKey();
    Code:
       0: getstatic     #236                // Field QUOTA_EXCEED_THROTTLE_QUOTA_ROW_KEY:[B
       3: areturn

  protected static java.lang.String getSettingsQualifierRegexForUserTable(java.lang.String);
    Code:
       0: new           #82                 // class java/lang/StringBuilder
       3: dup
       4: invokespecial #83                 // Method java/lang/StringBuilder."<init>":()V
       7: bipush        94
       9: invokevirtual #234                // Method java/lang/StringBuilder.append:(C)Ljava/lang/StringBuilder;
      12: getstatic     #137                // Field QUOTA_QUALIFIER_SETTINGS_PREFIX:[B
      15: invokestatic  #114                // Method org/apache/hadoop/hbase/util/Bytes.toString:([B)Ljava/lang/String;
      18: invokestatic  #237                // Method java/util/regex/Pattern.quote:(Ljava/lang/String;)Ljava/lang/String;
      21: invokevirtual #85                 // Method java/lang/StringBuilder.append:(Ljava/lang/String;)Ljava/lang/StringBuilder;
      24: aload_0
      25: invokevirtual #85                 // Method java/lang/StringBuilder.append:(Ljava/lang/String;)Ljava/lang/StringBuilder;
      28: ldc           #238                // String (?<!
      30: invokevirtual #85                 // Method java/lang/StringBuilder.append:(Ljava/lang/String;)Ljava/lang/StringBuilder;
      33: bipush        58
      35: invokestatic  #239                // Method java/lang/Character.toString:(C)Ljava/lang/String;
      38: invokestatic  #237                // Method java/util/regex/Pattern.quote:(Ljava/lang/String;)Ljava/lang/String;
      41: invokevirtual #85                 // Method java/lang/StringBuilder.append:(Ljava/lang/String;)Ljava/lang/StringBuilder;
      44: ldc           #240                // String )$
      46: invokevirtual #85                 // Method java/lang/StringBuilder.append:(Ljava/lang/String;)Ljava/lang/StringBuilder;
      49: invokevirtual #89                 // Method java/lang/StringBuilder.toString:()Ljava/lang/String;
      52: areturn

  protected static java.lang.String getSettingsQualifierRegexForUserNamespace(java.lang.String);
    Code:
       0: new           #82                 // class java/lang/StringBuilder
       3: dup
       4: invokespecial #83                 // Method java/lang/StringBuilder."<init>":()V
       7: bipush        94
       9: invokevirtual #234                // Method java/lang/StringBuilder.append:(C)Ljava/lang/StringBuilder;
      12: getstatic     #137                // Field QUOTA_QUALIFIER_SETTINGS_PREFIX:[B
      15: invokestatic  #114                // Method org/apache/hadoop/hbase/util/Bytes.toString:([B)Ljava/lang/String;
      18: invokestatic  #237                // Method java/util/regex/Pattern.quote:(Ljava/lang/String;)Ljava/lang/String;
      21: invokevirtual #85                 // Method java/lang/StringBuilder.append:(Ljava/lang/String;)Ljava/lang/StringBuilder;
      24: aload_0
      25: invokevirtual #85                 // Method java/lang/StringBuilder.append:(Ljava/lang/String;)Ljava/lang/StringBuilder;
      28: bipush        58
      30: invokestatic  #239                // Method java/lang/Character.toString:(C)Ljava/lang/String;
      33: invokestatic  #237                // Method java/util/regex/Pattern.quote:(Ljava/lang/String;)Ljava/lang/String;
      36: invokevirtual #85                 // Method java/lang/StringBuilder.append:(Ljava/lang/String;)Ljava/lang/StringBuilder;
      39: bipush        36
      41: invokevirtual #234                // Method java/lang/StringBuilder.append:(C)Ljava/lang/StringBuilder;
      44: invokevirtual #89                 // Method java/lang/StringBuilder.toString:()Ljava/lang/String;
      47: areturn

  protected static boolean isNamespaceRowKey(byte[]);
    Code:
       0: aload_0
       1: getstatic     #194                // Field QUOTA_NAMESPACE_ROW_KEY_PREFIX:[B
       4: invokestatic  #138                // Method org/apache/hadoop/hbase/util/Bytes.startsWith:([B[B)Z
       7: ireturn

  protected static java.lang.String getNamespaceFromRowKey(byte[]);
    Code:
       0: aload_0
       1: getstatic     #194                // Field QUOTA_NAMESPACE_ROW_KEY_PREFIX:[B
       4: arraylength
       5: invokestatic  #139                // Method org/apache/hadoop/hbase/util/Bytes.toString:([BI)Ljava/lang/String;
       8: areturn

  protected static boolean isRegionServerRowKey(byte[]);
    Code:
       0: aload_0
       1: getstatic     #233                // Field QUOTA_REGION_SERVER_ROW_KEY_PREFIX:[B
       4: invokestatic  #138                // Method org/apache/hadoop/hbase/util/Bytes.startsWith:([B[B)Z
       7: ireturn

  protected static java.lang.String getRegionServerFromRowKey(byte[]);
    Code:
       0: aload_0
       1: getstatic     #233                // Field QUOTA_REGION_SERVER_ROW_KEY_PREFIX:[B
       4: arraylength
       5: invokestatic  #139                // Method org/apache/hadoop/hbase/util/Bytes.toString:([BI)Ljava/lang/String;
       8: areturn

  protected static boolean isTableRowKey(byte[]);
    Code:
       0: aload_0
       1: getstatic     #71                 // Field QUOTA_TABLE_ROW_KEY_PREFIX:[B
       4: invokestatic  #138                // Method org/apache/hadoop/hbase/util/Bytes.startsWith:([B[B)Z
       7: ireturn

  protected static org.apache.hadoop.hbase.TableName getTableFromRowKey(byte[]);
    Code:
       0: aload_0
       1: getstatic     #71                 // Field QUOTA_TABLE_ROW_KEY_PREFIX:[B
       4: arraylength
       5: invokestatic  #139                // Method org/apache/hadoop/hbase/util/Bytes.toString:([BI)Ljava/lang/String;
       8: invokestatic  #144                // Method org/apache/hadoop/hbase/TableName.valueOf:(Ljava/lang/String;)Lorg/apache/hadoop/hbase/TableName;
      11: areturn

  protected static boolean isUserRowKey(byte[]);
    Code:
       0: aload_0
       1: getstatic     #231                // Field QUOTA_USER_ROW_KEY_PREFIX:[B
       4: invokestatic  #138                // Method org/apache/hadoop/hbase/util/Bytes.startsWith:([B[B)Z
       7: ireturn

  protected static java.lang.String getUserFromRowKey(byte[]);
    Code:
       0: aload_0
       1: getstatic     #231                // Field QUOTA_USER_ROW_KEY_PREFIX:[B
       4: arraylength
       5: invokestatic  #139                // Method org/apache/hadoop/hbase/util/Bytes.toString:([BI)Ljava/lang/String;
       8: areturn

  protected static org.apache.hadoop.hbase.shaded.protobuf.generated.QuotaProtos$SpaceQuota getProtoViolationPolicy(org.apache.hadoop.hbase.quotas.SpaceViolationPolicy);
    Code:
       0: invokestatic  #241                // Method org/apache/hadoop/hbase/shaded/protobuf/generated/QuotaProtos$SpaceQuota.newBuilder:()Lorg/apache/hadoop/hbase/shaded/protobuf/generated/QuotaProtos$SpaceQuota$Builder;
       3: aload_0
       4: invokestatic  #242                // Method org/apache/hadoop/hbase/shaded/protobuf/ProtobufUtil.toProtoViolationPolicy:(Lorg/apache/hadoop/hbase/quotas/SpaceViolationPolicy;)Lorg/apache/hadoop/hbase/shaded/protobuf/generated/QuotaProtos$SpaceViolationPolicy;
       7: invokevirtual #243                // Method org/apache/hadoop/hbase/shaded/protobuf/generated/QuotaProtos$SpaceQuota$Builder.setViolationPolicy:(Lorg/apache/hadoop/hbase/shaded/protobuf/generated/QuotaProtos$SpaceViolationPolicy;)Lorg/apache/hadoop/hbase/shaded/protobuf/generated/QuotaProtos$SpaceQuota$Builder;
      10: invokevirtual #244                // Method org/apache/hadoop/hbase/shaded/protobuf/generated/QuotaProtos$SpaceQuota$Builder.build:()Lorg/apache/hadoop/hbase/shaded/protobuf/generated/QuotaProtos$SpaceQuota;
      13: areturn

  protected static org.apache.hadoop.hbase.quotas.SpaceViolationPolicy getViolationPolicy(org.apache.hadoop.hbase.shaded.protobuf.generated.QuotaProtos$SpaceQuota);
    Code:
       0: aload_0
       1: invokevirtual #229                // Method org/apache/hadoop/hbase/shaded/protobuf/generated/QuotaProtos$SpaceQuota.hasViolationPolicy:()Z
       4: ifne          17
       7: new           #77                 // class java/lang/IllegalArgumentException
      10: dup
      11: ldc           #245                // String Protobuf SpaceQuota does not have violation policy.
      13: invokespecial #79                 // Method java/lang/IllegalArgumentException."<init>":(Ljava/lang/String;)V
      16: athrow
      17: aload_0
      18: invokevirtual #246                // Method org/apache/hadoop/hbase/shaded/protobuf/generated/QuotaProtos$SpaceQuota.getViolationPolicy:()Lorg/apache/hadoop/hbase/shaded/protobuf/generated/QuotaProtos$SpaceViolationPolicy;
      21: invokestatic  #247                // Method org/apache/hadoop/hbase/shaded/protobuf/ProtobufUtil.toViolationPolicy:(Lorg/apache/hadoop/hbase/shaded/protobuf/generated/QuotaProtos$SpaceViolationPolicy;)Lorg/apache/hadoop/hbase/quotas/SpaceViolationPolicy;
      24: areturn

  protected static byte[] getSnapshotSizeQualifier(java.lang.String);
    Code:
       0: getstatic     #156                // Field QUOTA_SNAPSHOT_SIZE_QUALIFIER:[B
       3: aload_0
       4: invokestatic  #154                // Method org/apache/hadoop/hbase/util/Bytes.toBytes:(Ljava/lang/String;)[B
       7: invokestatic  #155                // Method org/apache/hadoop/hbase/util/Bytes.add:([B[B)[B
      10: areturn

  protected static java.lang.String extractSnapshotNameFromSizeCell(org.apache.hadoop.hbase.Cell);
    Code:
       0: aload_0
       1: invokeinterface #180,  1          // InterfaceMethod org/apache/hadoop/hbase/Cell.getQualifierArray:()[B
       6: aload_0
       7: invokeinterface #181,  1          // InterfaceMethod org/apache/hadoop/hbase/Cell.getQualifierOffset:()I
      12: getstatic     #156                // Field QUOTA_SNAPSHOT_SIZE_QUALIFIER:[B
      15: arraylength
      16: iadd
      17: aload_0
      18: invokeinterface #182,  1          // InterfaceMethod org/apache/hadoop/hbase/Cell.getQualifierLength:()I
      23: getstatic     #156                // Field QUOTA_SNAPSHOT_SIZE_QUALIFIER:[B
      26: arraylength
      27: isub
      28: invokestatic  #248                // Method org/apache/hadoop/hbase/util/Bytes.toString:([BII)Ljava/lang/String;
      31: areturn

  protected static long extractSnapshotSize(byte[], int, int) throws org.apache.hbase.thirdparty.com.google.protobuf.InvalidProtocolBufferException;
    Code:
       0: aload_0
       1: iload_1
       2: iload_2
       3: invokestatic  #93                 // Method org/apache/hbase/thirdparty/com/google/protobuf/UnsafeByteOperations.unsafeWrap:([BII)Lorg/apache/hbase/thirdparty/com/google/protobuf/ByteString;
       6: astore_3
       7: aload_3
       8: invokestatic  #94                 // Method org/apache/hadoop/hbase/shaded/protobuf/generated/QuotaProtos$SpaceQuotaSnapshot.parseFrom:(Lorg/apache/hbase/thirdparty/com/google/protobuf/ByteString;)Lorg/apache/hadoop/hbase/shaded/protobuf/generated/QuotaProtos$SpaceQuotaSnapshot;
      11: invokevirtual #191                // Method org/apache/hadoop/hbase/shaded/protobuf/generated/QuotaProtos$SpaceQuotaSnapshot.getQuotaUsage:()J
      14: lreturn

  static {};
    Code:
       0: ldc           #249                // class org/apache/hadoop/hbase/quotas/QuotaTableUtil
       2: invokestatic  #250                // Method org/slf4j/LoggerFactory.getLogger:(Ljava/lang/Class;)Lorg/slf4j/Logger;
       5: putstatic     #109                // Field LOG:Lorg/slf4j/Logger;
       8: getstatic     #251                // Field org/apache/hadoop/hbase/NamespaceDescriptor.SYSTEM_NAMESPACE_NAME_STR:Ljava/lang/String;
      11: ldc           #252                // String quota
      13: invokestatic  #253                // Method org/apache/hadoop/hbase/TableName.valueOf:(Ljava/lang/String;Ljava/lang/String;)Lorg/apache/hadoop/hbase/TableName;
      16: putstatic     #57                 // Field QUOTA_TABLE_NAME:Lorg/apache/hadoop/hbase/TableName;
      19: ldc           #254                // String q
      21: invokestatic  #154                // Method org/apache/hadoop/hbase/util/Bytes.toBytes:(Ljava/lang/String;)[B
      24: putstatic     #13                 // Field QUOTA_FAMILY_INFO:[B
      27: ldc           #255                // String u
      29: invokestatic  #154                // Method org/apache/hadoop/hbase/util/Bytes.toBytes:(Ljava/lang/String;)[B
      32: putstatic     #68                 // Field QUOTA_FAMILY_USAGE:[B
      35: ldc_w         #256                // String s
      38: invokestatic  #154                // Method org/apache/hadoop/hbase/util/Bytes.toBytes:(Ljava/lang/String;)[B
      41: putstatic     #9                  // Field QUOTA_QUALIFIER_SETTINGS:[B
      44: ldc_w         #257                // String s.
      47: invokestatic  #154                // Method org/apache/hadoop/hbase/util/Bytes.toBytes:(Ljava/lang/String;)[B
      50: putstatic     #137                // Field QUOTA_QUALIFIER_SETTINGS_PREFIX:[B
      53: ldc_w         #258                // String p
      56: invokestatic  #154                // Method org/apache/hadoop/hbase/util/Bytes.toBytes:(Ljava/lang/String;)[B
      59: putstatic     #69                 // Field QUOTA_QUALIFIER_POLICY:[B
      62: ldc_w         #259                // String ss
      65: invokestatic  #154                // Method org/apache/hadoop/hbase/util/Bytes.toBytes:(Ljava/lang/String;)[B
      68: putstatic     #156                // Field QUOTA_SNAPSHOT_SIZE_QUALIFIER:[B
      71: new           #82                 // class java/lang/StringBuilder
      74: dup
      75: invokespecial #83                 // Method java/lang/StringBuilder."<init>":()V
      78: getstatic     #68                 // Field QUOTA_FAMILY_USAGE:[B
      81: invokestatic  #114                // Method org/apache/hadoop/hbase/util/Bytes.toString:([B)Ljava/lang/String;
      84: invokevirtual #85                 // Method java/lang/StringBuilder.append:(Ljava/lang/String;)Ljava/lang/StringBuilder;
      87: ldc_w         #260                // String :
      90: invokevirtual #85                 // Method java/lang/StringBuilder.append:(Ljava/lang/String;)Ljava/lang/StringBuilder;
      93: getstatic     #69                 // Field QUOTA_QUALIFIER_POLICY:[B
      96: invokestatic  #114                // Method org/apache/hadoop/hbase/util/Bytes.toString:([B)Ljava/lang/String;
      99: invokevirtual #85                 // Method java/lang/StringBuilder.append:(Ljava/lang/String;)Ljava/lang/StringBuilder;
     102: invokevirtual #89                 // Method java/lang/StringBuilder.toString:()Ljava/lang/String;
     105: putstatic     #86                 // Field QUOTA_POLICY_COLUMN:Ljava/lang/String;
     108: ldc_w         #261                // String u.
     111: invokestatic  #154                // Method org/apache/hadoop/hbase/util/Bytes.toBytes:(Ljava/lang/String;)[B
     114: putstatic     #231                // Field QUOTA_USER_ROW_KEY_PREFIX:[B
     117: ldc_w         #262                // String t.
     120: invokestatic  #154                // Method org/apache/hadoop/hbase/util/Bytes.toBytes:(Ljava/lang/String;)[B
     123: putstatic     #71                 // Field QUOTA_TABLE_ROW_KEY_PREFIX:[B
     126: ldc_w         #263                // String n.
     129: invokestatic  #154                // Method org/apache/hadoop/hbase/util/Bytes.toBytes:(Ljava/lang/String;)[B
     132: putstatic     #194                // Field QUOTA_NAMESPACE_ROW_KEY_PREFIX:[B
     135: ldc_w         #264                // String r.
     138: invokestatic  #154                // Method org/apache/hadoop/hbase/util/Bytes.toBytes:(Ljava/lang/String;)[B
     141: putstatic     #233                // Field QUOTA_REGION_SERVER_ROW_KEY_PREFIX:[B
     144: ldc_w         #265                // String exceedThrottleQuota
     147: invokestatic  #154                // Method org/apache/hadoop/hbase/util/Bytes.toBytes:(Ljava/lang/String;)[B
     150: putstatic     #236                // Field QUOTA_EXCEED_THROTTLE_QUOTA_ROW_KEY:[B
     153: return
}
