Compiled from "QuotaState.java"
public class org.apache.hadoop.hbase.quotas.QuotaState {
  protected long lastUpdate;

  protected long lastQuery;

  protected org.apache.hadoop.hbase.quotas.QuotaLimiter globalLimiter;

  public org.apache.hadoop.hbase.quotas.QuotaState();
    Code:
       0: aload_0
       1: lconst_0
       2: invokespecial #1                  // Method "<init>":(J)V
       5: return

  public org.apache.hadoop.hbase.quotas.QuotaState(long);
    Code:
       0: aload_0
       1: invokespecial #2                  // Method java/lang/Object."<init>":()V
       4: aload_0
       5: lconst_0
       6: putfield      #3                  // Field lastUpdate:J
       9: aload_0
      10: lconst_0
      11: putfield      #4                  // Field lastQuery:J
      14: aload_0
      15: invokestatic  #5                  // Method org/apache/hadoop/hbase/quotas/NoopQuotaLimiter.get:()Lorg/apache/hadoop/hbase/quotas/QuotaLimiter;
      18: putfield      #6                  // Field globalLimiter:Lorg/apache/hadoop/hbase/quotas/QuotaLimiter;
      21: aload_0
      22: lload_1
      23: putfield      #3                  // Field lastUpdate:J
      26: return

  public synchronized long getLastUpdate();
    Code:
       0: aload_0
       1: getfield      #3                  // Field lastUpdate:J
       4: lreturn

  public synchronized long getLastQuery();
    Code:
       0: aload_0
       1: getfield      #4                  // Field lastQuery:J
       4: lreturn

  public synchronized java.lang.String toString();
    Code:
       0: new           #7                  // class java/lang/StringBuilder
       3: dup
       4: invokespecial #8                  // Method java/lang/StringBuilder."<init>":()V
       7: astore_1
       8: aload_1
       9: new           #7                  // class java/lang/StringBuilder
      12: dup
      13: invokespecial #8                  // Method java/lang/StringBuilder."<init>":()V
      16: ldc           #9                  // String QuotaState(ts=
      18: invokevirtual #10                 // Method java/lang/StringBuilder.append:(Ljava/lang/String;)Ljava/lang/StringBuilder;
      21: aload_0
      22: invokevirtual #11                 // Method getLastUpdate:()J
      25: invokevirtual #12                 // Method java/lang/StringBuilder.append:(J)Ljava/lang/StringBuilder;
      28: invokevirtual #13                 // Method java/lang/StringBuilder.toString:()Ljava/lang/String;
      31: invokevirtual #10                 // Method java/lang/StringBuilder.append:(Ljava/lang/String;)Ljava/lang/StringBuilder;
      34: pop
      35: aload_0
      36: invokevirtual #14                 // Method isBypass:()Z
      39: ifeq          52
      42: aload_1
      43: ldc           #15                 // String  bypass
      45: invokevirtual #10                 // Method java/lang/StringBuilder.append:(Ljava/lang/String;)Ljava/lang/StringBuilder;
      48: pop
      49: goto          89
      52: aload_0
      53: getfield      #6                  // Field globalLimiter:Lorg/apache/hadoop/hbase/quotas/QuotaLimiter;
      56: invokestatic  #5                  // Method org/apache/hadoop/hbase/quotas/NoopQuotaLimiter.get:()Lorg/apache/hadoop/hbase/quotas/QuotaLimiter;
      59: if_acmpeq     89
      62: aload_1
      63: new           #7                  // class java/lang/StringBuilder
      66: dup
      67: invokespecial #8                  // Method java/lang/StringBuilder."<init>":()V
      70: ldc           #16                 // String
      72: invokevirtual #10                 // Method java/lang/StringBuilder.append:(Ljava/lang/String;)Ljava/lang/StringBuilder;
      75: aload_0
      76: getfield      #6                  // Field globalLimiter:Lorg/apache/hadoop/hbase/quotas/QuotaLimiter;
      79: invokevirtual #17                 // Method java/lang/StringBuilder.append:(Ljava/lang/Object;)Ljava/lang/StringBuilder;
      82: invokevirtual #13                 // Method java/lang/StringBuilder.toString:()Ljava/lang/String;
      85: invokevirtual #10                 // Method java/lang/StringBuilder.append:(Ljava/lang/String;)Ljava/lang/StringBuilder;
      88: pop
      89: aload_1
      90: bipush        41
      92: invokevirtual #18                 // Method java/lang/StringBuilder.append:(C)Ljava/lang/StringBuilder;
      95: pop
      96: aload_1
      97: invokevirtual #13                 // Method java/lang/StringBuilder.toString:()Ljava/lang/String;
     100: areturn

  public synchronized boolean isBypass();
    Code:
       0: aload_0
       1: getfield      #6                  // Field globalLimiter:Lorg/apache/hadoop/hbase/quotas/QuotaLimiter;
       4: invokestatic  #5                  // Method org/apache/hadoop/hbase/quotas/NoopQuotaLimiter.get:()Lorg/apache/hadoop/hbase/quotas/QuotaLimiter;
       7: if_acmpne     14
      10: iconst_1
      11: goto          15
      14: iconst_0
      15: ireturn

  public synchronized void setQuotas(org.apache.hadoop.hbase.shaded.protobuf.generated.QuotaProtos$Quotas);
    Code:
       0: aload_1
       1: invokevirtual #19                 // Method org/apache/hadoop/hbase/shaded/protobuf/generated/QuotaProtos$Quotas.hasThrottle:()Z
       4: ifeq          21
       7: aload_0
       8: aload_1
       9: invokevirtual #20                 // Method org/apache/hadoop/hbase/shaded/protobuf/generated/QuotaProtos$Quotas.getThrottle:()Lorg/apache/hadoop/hbase/shaded/protobuf/generated/QuotaProtos$Throttle;
      12: invokestatic  #21                 // Method org/apache/hadoop/hbase/quotas/QuotaLimiterFactory.fromThrottle:(Lorg/apache/hadoop/hbase/shaded/protobuf/generated/QuotaProtos$Throttle;)Lorg/apache/hadoop/hbase/quotas/QuotaLimiter;
      15: putfield      #6                  // Field globalLimiter:Lorg/apache/hadoop/hbase/quotas/QuotaLimiter;
      18: goto          28
      21: aload_0
      22: invokestatic  #5                  // Method org/apache/hadoop/hbase/quotas/NoopQuotaLimiter.get:()Lorg/apache/hadoop/hbase/quotas/QuotaLimiter;
      25: putfield      #6                  // Field globalLimiter:Lorg/apache/hadoop/hbase/quotas/QuotaLimiter;
      28: return

  public synchronized void update(org.apache.hadoop.hbase.quotas.QuotaState);
    Code:
       0: aload_0
       1: getfield      #6                  // Field globalLimiter:Lorg/apache/hadoop/hbase/quotas/QuotaLimiter;
       4: invokestatic  #5                  // Method org/apache/hadoop/hbase/quotas/NoopQuotaLimiter.get:()Lorg/apache/hadoop/hbase/quotas/QuotaLimiter;
       7: if_acmpne     21
      10: aload_0
      11: aload_1
      12: getfield      #6                  // Field globalLimiter:Lorg/apache/hadoop/hbase/quotas/QuotaLimiter;
      15: putfield      #6                  // Field globalLimiter:Lorg/apache/hadoop/hbase/quotas/QuotaLimiter;
      18: goto          56
      21: aload_1
      22: getfield      #6                  // Field globalLimiter:Lorg/apache/hadoop/hbase/quotas/QuotaLimiter;
      25: invokestatic  #5                  // Method org/apache/hadoop/hbase/quotas/NoopQuotaLimiter.get:()Lorg/apache/hadoop/hbase/quotas/QuotaLimiter;
      28: if_acmpne     41
      31: aload_0
      32: invokestatic  #5                  // Method org/apache/hadoop/hbase/quotas/NoopQuotaLimiter.get:()Lorg/apache/hadoop/hbase/quotas/QuotaLimiter;
      35: putfield      #6                  // Field globalLimiter:Lorg/apache/hadoop/hbase/quotas/QuotaLimiter;
      38: goto          56
      41: aload_0
      42: aload_0
      43: getfield      #6                  // Field globalLimiter:Lorg/apache/hadoop/hbase/quotas/QuotaLimiter;
      46: aload_1
      47: getfield      #6                  // Field globalLimiter:Lorg/apache/hadoop/hbase/quotas/QuotaLimiter;
      50: invokestatic  #22                 // Method org/apache/hadoop/hbase/quotas/QuotaLimiterFactory.update:(Lorg/apache/hadoop/hbase/quotas/QuotaLimiter;Lorg/apache/hadoop/hbase/quotas/QuotaLimiter;)Lorg/apache/hadoop/hbase/quotas/QuotaLimiter;
      53: putfield      #6                  // Field globalLimiter:Lorg/apache/hadoop/hbase/quotas/QuotaLimiter;
      56: aload_0
      57: aload_1
      58: getfield      #3                  // Field lastUpdate:J
      61: putfield      #3                  // Field lastUpdate:J
      64: return

  public synchronized org.apache.hadoop.hbase.quotas.QuotaLimiter getGlobalLimiter();
    Code:
       0: aload_0
       1: invokestatic  #23                 // Method org/apache/hadoop/hbase/util/EnvironmentEdgeManager.currentTime:()J
       4: putfield      #4                  // Field lastQuery:J
       7: aload_0
       8: getfield      #6                  // Field globalLimiter:Lorg/apache/hadoop/hbase/quotas/QuotaLimiter;
      11: areturn

  synchronized org.apache.hadoop.hbase.quotas.QuotaLimiter getGlobalLimiterWithoutUpdatingLastQuery();
    Code:
       0: aload_0
       1: getfield      #6                  // Field globalLimiter:Lorg/apache/hadoop/hbase/quotas/QuotaLimiter;
       4: areturn
}
