Compiled from "QuotaProtos.java"
public final class org.apache.hadoop.hbase.protobuf.generated.QuotaProtos$Quotas$Builder extends com.google.protobuf.GeneratedMessage$Builder<org.apache.hadoop.hbase.protobuf.generated.QuotaProtos$Quotas$Builder> implements org.apache.hadoop.hbase.protobuf.generated.QuotaProtos$QuotasOrBuilder {
  public static final com.google.protobuf.Descriptors$Descriptor getDescriptor();
    Code:
       0: invokestatic  #3                  // Method org/apache/hadoop/hbase/protobuf/generated/QuotaProtos.access$3600:()Lcom/google/protobuf/Descriptors$Descriptor;
       3: areturn

  protected com.google.protobuf.GeneratedMessage$FieldAccessorTable internalGetFieldAccessorTable();
    Code:
       0: invokestatic  #4                  // Method org/apache/hadoop/hbase/protobuf/generated/QuotaProtos.access$3700:()Lcom/google/protobuf/GeneratedMessage$FieldAccessorTable;
       3: ldc           #5                  // class org/apache/hadoop/hbase/protobuf/generated/QuotaProtos$Quotas
       5: ldc           #6                  // class org/apache/hadoop/hbase/protobuf/generated/QuotaProtos$Quotas$Builder
       7: invokevirtual #7                  // Method com/google/protobuf/GeneratedMessage$FieldAccessorTable.ensureFieldAccessorsInitialized:(Ljava/lang/Class;Ljava/lang/Class;)Lcom/google/protobuf/GeneratedMessage$FieldAccessorTable;
      10: areturn

  public org.apache.hadoop.hbase.protobuf.generated.QuotaProtos$Quotas$Builder clear();
    Code:
       0: aload_0
       1: invokespecial #19                 // Method com/google/protobuf/GeneratedMessage$Builder.clear:()Lcom/google/protobuf/GeneratedMessage$Builder;
       4: pop
       5: aload_0
       6: iconst_0
       7: putfield      #20                 // Field bypassGlobals_:Z
      10: aload_0
      11: aload_0
      12: getfield      #21                 // Field bitField0_:I
      15: bipush        -2
      17: iand
      18: putfield      #21                 // Field bitField0_:I
      21: aload_0
      22: getfield      #22                 // Field throttleBuilder_:Lcom/google/protobuf/SingleFieldBuilder;
      25: ifnonnull     38
      28: aload_0
      29: invokestatic  #9                  // Method org/apache/hadoop/hbase/protobuf/generated/QuotaProtos$Throttle.getDefaultInstance:()Lorg/apache/hadoop/hbase/protobuf/generated/QuotaProtos$Throttle;
      32: putfield      #10                 // Field throttle_:Lorg/apache/hadoop/hbase/protobuf/generated/QuotaProtos$Throttle;
      35: goto          46
      38: aload_0
      39: getfield      #22                 // Field throttleBuilder_:Lcom/google/protobuf/SingleFieldBuilder;
      42: invokevirtual #23                 // Method com/google/protobuf/SingleFieldBuilder.clear:()Lcom/google/protobuf/SingleFieldBuilder;
      45: pop
      46: aload_0
      47: aload_0
      48: getfield      #21                 // Field bitField0_:I
      51: bipush        -3
      53: iand
      54: putfield      #21                 // Field bitField0_:I
      57: aload_0
      58: getfield      #24                 // Field spaceBuilder_:Lcom/google/protobuf/SingleFieldBuilder;
      61: ifnonnull     74
      64: aload_0
      65: invokestatic  #11                 // Method org/apache/hadoop/hbase/protobuf/generated/QuotaProtos$SpaceQuota.getDefaultInstance:()Lorg/apache/hadoop/hbase/protobuf/generated/QuotaProtos$SpaceQuota;
      68: putfield      #12                 // Field space_:Lorg/apache/hadoop/hbase/protobuf/generated/QuotaProtos$SpaceQuota;
      71: goto          82
      74: aload_0
      75: getfield      #24                 // Field spaceBuilder_:Lcom/google/protobuf/SingleFieldBuilder;
      78: invokevirtual #23                 // Method com/google/protobuf/SingleFieldBuilder.clear:()Lcom/google/protobuf/SingleFieldBuilder;
      81: pop
      82: aload_0
      83: aload_0
      84: getfield      #21                 // Field bitField0_:I
      87: bipush        -5
      89: iand
      90: putfield      #21                 // Field bitField0_:I
      93: aload_0
      94: areturn

  public org.apache.hadoop.hbase.protobuf.generated.QuotaProtos$Quotas$Builder clone();
    Code:
       0: invokestatic  #2                  // Method create:()Lorg/apache/hadoop/hbase/protobuf/generated/QuotaProtos$Quotas$Builder;
       3: aload_0
       4: invokevirtual #25                 // Method buildPartial:()Lorg/apache/hadoop/hbase/protobuf/generated/QuotaProtos$Quotas;
       7: invokevirtual #26                 // Method mergeFrom:(Lorg/apache/hadoop/hbase/protobuf/generated/QuotaProtos$Quotas;)Lorg/apache/hadoop/hbase/protobuf/generated/QuotaProtos$Quotas$Builder;
      10: areturn

  public com.google.protobuf.Descriptors$Descriptor getDescriptorForType();
    Code:
       0: invokestatic  #3                  // Method org/apache/hadoop/hbase/protobuf/generated/QuotaProtos.access$3600:()Lcom/google/protobuf/Descriptors$Descriptor;
       3: areturn

  public org.apache.hadoop.hbase.protobuf.generated.QuotaProtos$Quotas getDefaultInstanceForType();
    Code:
       0: invokestatic  #27                 // Method org/apache/hadoop/hbase/protobuf/generated/QuotaProtos$Quotas.getDefaultInstance:()Lorg/apache/hadoop/hbase/protobuf/generated/QuotaProtos$Quotas;
       3: areturn

  public org.apache.hadoop.hbase.protobuf.generated.QuotaProtos$Quotas build();
    Code:
       0: aload_0
       1: invokevirtual #25                 // Method buildPartial:()Lorg/apache/hadoop/hbase/protobuf/generated/QuotaProtos$Quotas;
       4: astore_1
       5: aload_1
       6: invokevirtual #28                 // Method org/apache/hadoop/hbase/protobuf/generated/QuotaProtos$Quotas.isInitialized:()Z
       9: ifne          17
      12: aload_1
      13: invokestatic  #29                 // Method newUninitializedMessageException:(Lcom/google/protobuf/Message;)Lcom/google/protobuf/UninitializedMessageException;
      16: athrow
      17: aload_1
      18: areturn

  public org.apache.hadoop.hbase.protobuf.generated.QuotaProtos$Quotas buildPartial();
    Code:
       0: new           #5                  // class org/apache/hadoop/hbase/protobuf/generated/QuotaProtos$Quotas
       3: dup
       4: aload_0
       5: aconst_null
       6: invokespecial #30                 // Method org/apache/hadoop/hbase/protobuf/generated/QuotaProtos$Quotas."<init>":(Lcom/google/protobuf/GeneratedMessage$Builder;Lorg/apache/hadoop/hbase/protobuf/generated/QuotaProtos$1;)V
       9: astore_1
      10: aload_0
      11: getfield      #21                 // Field bitField0_:I
      14: istore_2
      15: iconst_0
      16: istore_3
      17: iload_2
      18: iconst_1
      19: iand
      20: iconst_1
      21: if_icmpne     28
      24: iload_3
      25: iconst_1
      26: ior
      27: istore_3
      28: aload_1
      29: aload_0
      30: getfield      #20                 // Field bypassGlobals_:Z
      33: invokestatic  #31                 // Method org/apache/hadoop/hbase/protobuf/generated/QuotaProtos$Quotas.access$4302:(Lorg/apache/hadoop/hbase/protobuf/generated/QuotaProtos$Quotas;Z)Z
      36: pop
      37: iload_2
      38: iconst_2
      39: iand
      40: iconst_2
      41: if_icmpne     48
      44: iload_3
      45: iconst_2
      46: ior
      47: istore_3
      48: aload_0
      49: getfield      #22                 // Field throttleBuilder_:Lcom/google/protobuf/SingleFieldBuilder;
      52: ifnonnull     67
      55: aload_1
      56: aload_0
      57: getfield      #10                 // Field throttle_:Lorg/apache/hadoop/hbase/protobuf/generated/QuotaProtos$Throttle;
      60: invokestatic  #32                 // Method org/apache/hadoop/hbase/protobuf/generated/QuotaProtos$Quotas.access$4402:(Lorg/apache/hadoop/hbase/protobuf/generated/QuotaProtos$Quotas;Lorg/apache/hadoop/hbase/protobuf/generated/QuotaProtos$Throttle;)Lorg/apache/hadoop/hbase/protobuf/generated/QuotaProtos$Throttle;
      63: pop
      64: goto          82
      67: aload_1
      68: aload_0
      69: getfield      #22                 // Field throttleBuilder_:Lcom/google/protobuf/SingleFieldBuilder;
      72: invokevirtual #33                 // Method com/google/protobuf/SingleFieldBuilder.build:()Lcom/google/protobuf/GeneratedMessage;
      75: checkcast     #34                 // class org/apache/hadoop/hbase/protobuf/generated/QuotaProtos$Throttle
      78: invokestatic  #32                 // Method org/apache/hadoop/hbase/protobuf/generated/QuotaProtos$Quotas.access$4402:(Lorg/apache/hadoop/hbase/protobuf/generated/QuotaProtos$Quotas;Lorg/apache/hadoop/hbase/protobuf/generated/QuotaProtos$Throttle;)Lorg/apache/hadoop/hbase/protobuf/generated/QuotaProtos$Throttle;
      81: pop
      82: iload_2
      83: iconst_4
      84: iand
      85: iconst_4
      86: if_icmpne     93
      89: iload_3
      90: iconst_4
      91: ior
      92: istore_3
      93: aload_0
      94: getfield      #24                 // Field spaceBuilder_:Lcom/google/protobuf/SingleFieldBuilder;
      97: ifnonnull     112
     100: aload_1
     101: aload_0
     102: getfield      #12                 // Field space_:Lorg/apache/hadoop/hbase/protobuf/generated/QuotaProtos$SpaceQuota;
     105: invokestatic  #35                 // Method org/apache/hadoop/hbase/protobuf/generated/QuotaProtos$Quotas.access$4502:(Lorg/apache/hadoop/hbase/protobuf/generated/QuotaProtos$Quotas;Lorg/apache/hadoop/hbase/protobuf/generated/QuotaProtos$SpaceQuota;)Lorg/apache/hadoop/hbase/protobuf/generated/QuotaProtos$SpaceQuota;
     108: pop
     109: goto          127
     112: aload_1
     113: aload_0
     114: getfield      #24                 // Field spaceBuilder_:Lcom/google/protobuf/SingleFieldBuilder;
     117: invokevirtual #33                 // Method com/google/protobuf/SingleFieldBuilder.build:()Lcom/google/protobuf/GeneratedMessage;
     120: checkcast     #36                 // class org/apache/hadoop/hbase/protobuf/generated/QuotaProtos$SpaceQuota
     123: invokestatic  #35                 // Method org/apache/hadoop/hbase/protobuf/generated/QuotaProtos$Quotas.access$4502:(Lorg/apache/hadoop/hbase/protobuf/generated/QuotaProtos$Quotas;Lorg/apache/hadoop/hbase/protobuf/generated/QuotaProtos$SpaceQuota;)Lorg/apache/hadoop/hbase/protobuf/generated/QuotaProtos$SpaceQuota;
     126: pop
     127: aload_1
     128: iload_3
     129: invokestatic  #37                 // Method org/apache/hadoop/hbase/protobuf/generated/QuotaProtos$Quotas.access$4602:(Lorg/apache/hadoop/hbase/protobuf/generated/QuotaProtos$Quotas;I)I
     132: pop
     133: aload_0
     134: invokevirtual #38                 // Method onBuilt:()V
     137: aload_1
     138: areturn

  public org.apache.hadoop.hbase.protobuf.generated.QuotaProtos$Quotas$Builder mergeFrom(com.google.protobuf.Message);
    Code:
       0: aload_1
       1: instanceof    #5                  // class org/apache/hadoop/hbase/protobuf/generated/QuotaProtos$Quotas
       4: ifeq          16
       7: aload_0
       8: aload_1
       9: checkcast     #5                  // class org/apache/hadoop/hbase/protobuf/generated/QuotaProtos$Quotas
      12: invokevirtual #26                 // Method mergeFrom:(Lorg/apache/hadoop/hbase/protobuf/generated/QuotaProtos$Quotas;)Lorg/apache/hadoop/hbase/protobuf/generated/QuotaProtos$Quotas$Builder;
      15: areturn
      16: aload_0
      17: aload_1
      18: invokespecial #39                 // Method com/google/protobuf/GeneratedMessage$Builder.mergeFrom:(Lcom/google/protobuf/Message;)Lcom/google/protobuf/AbstractMessage$Builder;
      21: pop
      22: aload_0
      23: areturn

  public org.apache.hadoop.hbase.protobuf.generated.QuotaProtos$Quotas$Builder mergeFrom(org.apache.hadoop.hbase.protobuf.generated.QuotaProtos$Quotas);
    Code:
       0: aload_1
       1: invokestatic  #27                 // Method org/apache/hadoop/hbase/protobuf/generated/QuotaProtos$Quotas.getDefaultInstance:()Lorg/apache/hadoop/hbase/protobuf/generated/QuotaProtos$Quotas;
       4: if_acmpne     9
       7: aload_0
       8: areturn
       9: aload_1
      10: invokevirtual #40                 // Method org/apache/hadoop/hbase/protobuf/generated/QuotaProtos$Quotas.hasBypassGlobals:()Z
      13: ifeq          25
      16: aload_0
      17: aload_1
      18: invokevirtual #41                 // Method org/apache/hadoop/hbase/protobuf/generated/QuotaProtos$Quotas.getBypassGlobals:()Z
      21: invokevirtual #42                 // Method setBypassGlobals:(Z)Lorg/apache/hadoop/hbase/protobuf/generated/QuotaProtos$Quotas$Builder;
      24: pop
      25: aload_1
      26: invokevirtual #43                 // Method org/apache/hadoop/hbase/protobuf/generated/QuotaProtos$Quotas.hasThrottle:()Z
      29: ifeq          41
      32: aload_0
      33: aload_1
      34: invokevirtual #44                 // Method org/apache/hadoop/hbase/protobuf/generated/QuotaProtos$Quotas.getThrottle:()Lorg/apache/hadoop/hbase/protobuf/generated/QuotaProtos$Throttle;
      37: invokevirtual #45                 // Method mergeThrottle:(Lorg/apache/hadoop/hbase/protobuf/generated/QuotaProtos$Throttle;)Lorg/apache/hadoop/hbase/protobuf/generated/QuotaProtos$Quotas$Builder;
      40: pop
      41: aload_1
      42: invokevirtual #46                 // Method org/apache/hadoop/hbase/protobuf/generated/QuotaProtos$Quotas.hasSpace:()Z
      45: ifeq          57
      48: aload_0
      49: aload_1
      50: invokevirtual #47                 // Method org/apache/hadoop/hbase/protobuf/generated/QuotaProtos$Quotas.getSpace:()Lorg/apache/hadoop/hbase/protobuf/generated/QuotaProtos$SpaceQuota;
      53: invokevirtual #48                 // Method mergeSpace:(Lorg/apache/hadoop/hbase/protobuf/generated/QuotaProtos$SpaceQuota;)Lorg/apache/hadoop/hbase/protobuf/generated/QuotaProtos$Quotas$Builder;
      56: pop
      57: aload_0
      58: aload_1
      59: invokevirtual #49                 // Method org/apache/hadoop/hbase/protobuf/generated/QuotaProtos$Quotas.getUnknownFields:()Lcom/google/protobuf/UnknownFieldSet;
      62: invokevirtual #50                 // Method mergeUnknownFields:(Lcom/google/protobuf/UnknownFieldSet;)Lcom/google/protobuf/GeneratedMessage$Builder;
      65: pop
      66: aload_0
      67: areturn

  public final boolean isInitialized();
    Code:
       0: aload_0
       1: invokevirtual #51                 // Method hasThrottle:()Z
       4: ifeq          19
       7: aload_0
       8: invokevirtual #52                 // Method getThrottle:()Lorg/apache/hadoop/hbase/protobuf/generated/QuotaProtos$Throttle;
      11: invokevirtual #53                 // Method org/apache/hadoop/hbase/protobuf/generated/QuotaProtos$Throttle.isInitialized:()Z
      14: ifne          19
      17: iconst_0
      18: ireturn
      19: iconst_1
      20: ireturn

  public org.apache.hadoop.hbase.protobuf.generated.QuotaProtos$Quotas$Builder mergeFrom(com.google.protobuf.CodedInputStream, com.google.protobuf.ExtensionRegistryLite) throws java.io.IOException;
    Code:
       0: aconst_null
       1: astore_3
       2: getstatic     #54                 // Field org/apache/hadoop/hbase/protobuf/generated/QuotaProtos$Quotas.PARSER:Lcom/google/protobuf/Parser;
       5: aload_1
       6: aload_2
       7: invokeinterface #55,  3           // InterfaceMethod com/google/protobuf/Parser.parsePartialFrom:(Lcom/google/protobuf/CodedInputStream;Lcom/google/protobuf/ExtensionRegistryLite;)Ljava/lang/Object;
      12: checkcast     #5                  // class org/apache/hadoop/hbase/protobuf/generated/QuotaProtos$Quotas
      15: astore_3
      16: aload_3
      17: ifnull        58
      20: aload_0
      21: aload_3
      22: invokevirtual #26                 // Method mergeFrom:(Lorg/apache/hadoop/hbase/protobuf/generated/QuotaProtos$Quotas;)Lorg/apache/hadoop/hbase/protobuf/generated/QuotaProtos$Quotas$Builder;
      25: pop
      26: goto          58
      29: astore        4
      31: aload         4
      33: invokevirtual #57                 // Method com/google/protobuf/InvalidProtocolBufferException.getUnfinishedMessage:()Lcom/google/protobuf/MessageLite;
      36: checkcast     #5                  // class org/apache/hadoop/hbase/protobuf/generated/QuotaProtos$Quotas
      39: astore_3
      40: aload         4
      42: athrow
      43: astore        5
      45: aload_3
      46: ifnull        55
      49: aload_0
      50: aload_3
      51: invokevirtual #26                 // Method mergeFrom:(Lorg/apache/hadoop/hbase/protobuf/generated/QuotaProtos$Quotas;)Lorg/apache/hadoop/hbase/protobuf/generated/QuotaProtos$Quotas$Builder;
      54: pop
      55: aload         5
      57: athrow
      58: aload_0
      59: areturn
    Exception table:
       from    to  target type
           2    16    29   Class com/google/protobuf/InvalidProtocolBufferException
           2    16    43   any
          29    45    43   any

  public boolean hasBypassGlobals();
    Code:
       0: aload_0
       1: getfield      #21                 // Field bitField0_:I
       4: iconst_1
       5: iand
       6: iconst_1
       7: if_icmpne     14
      10: iconst_1
      11: goto          15
      14: iconst_0
      15: ireturn

  public boolean getBypassGlobals();
    Code:
       0: aload_0
       1: getfield      #20                 // Field bypassGlobals_:Z
       4: ireturn

  public org.apache.hadoop.hbase.protobuf.generated.QuotaProtos$Quotas$Builder setBypassGlobals(boolean);
    Code:
       0: aload_0
       1: dup
       2: getfield      #21                 // Field bitField0_:I
       5: iconst_1
       6: ior
       7: putfield      #21                 // Field bitField0_:I
      10: aload_0
      11: iload_1
      12: putfield      #20                 // Field bypassGlobals_:Z
      15: aload_0
      16: invokevirtual #58                 // Method onChanged:()V
      19: aload_0
      20: areturn

  public org.apache.hadoop.hbase.protobuf.generated.QuotaProtos$Quotas$Builder clearBypassGlobals();
    Code:
       0: aload_0
       1: aload_0
       2: getfield      #21                 // Field bitField0_:I
       5: bipush        -2
       7: iand
       8: putfield      #21                 // Field bitField0_:I
      11: aload_0
      12: iconst_0
      13: putfield      #20                 // Field bypassGlobals_:Z
      16: aload_0
      17: invokevirtual #58                 // Method onChanged:()V
      20: aload_0
      21: areturn

  public boolean hasThrottle();
    Code:
       0: aload_0
       1: getfield      #21                 // Field bitField0_:I
       4: iconst_2
       5: iand
       6: iconst_2
       7: if_icmpne     14
      10: iconst_1
      11: goto          15
      14: iconst_0
      15: ireturn

  public org.apache.hadoop.hbase.protobuf.generated.QuotaProtos$Throttle getThrottle();
    Code:
       0: aload_0
       1: getfield      #22                 // Field throttleBuilder_:Lcom/google/protobuf/SingleFieldBuilder;
       4: ifnonnull     12
       7: aload_0
       8: getfield      #10                 // Field throttle_:Lorg/apache/hadoop/hbase/protobuf/generated/QuotaProtos$Throttle;
      11: areturn
      12: aload_0
      13: getfield      #22                 // Field throttleBuilder_:Lcom/google/protobuf/SingleFieldBuilder;
      16: invokevirtual #59                 // Method com/google/protobuf/SingleFieldBuilder.getMessage:()Lcom/google/protobuf/GeneratedMessage;
      19: checkcast     #34                 // class org/apache/hadoop/hbase/protobuf/generated/QuotaProtos$Throttle
      22: areturn

  public org.apache.hadoop.hbase.protobuf.generated.QuotaProtos$Quotas$Builder setThrottle(org.apache.hadoop.hbase.protobuf.generated.QuotaProtos$Throttle);
    Code:
       0: aload_0
       1: getfield      #22                 // Field throttleBuilder_:Lcom/google/protobuf/SingleFieldBuilder;
       4: ifnonnull     31
       7: aload_1
       8: ifnonnull     19
      11: new           #60                 // class java/lang/NullPointerException
      14: dup
      15: invokespecial #61                 // Method java/lang/NullPointerException."<init>":()V
      18: athrow
      19: aload_0
      20: aload_1
      21: putfield      #10                 // Field throttle_:Lorg/apache/hadoop/hbase/protobuf/generated/QuotaProtos$Throttle;
      24: aload_0
      25: invokevirtual #58                 // Method onChanged:()V
      28: goto          40
      31: aload_0
      32: getfield      #22                 // Field throttleBuilder_:Lcom/google/protobuf/SingleFieldBuilder;
      35: aload_1
      36: invokevirtual #62                 // Method com/google/protobuf/SingleFieldBuilder.setMessage:(Lcom/google/protobuf/GeneratedMessage;)Lcom/google/protobuf/SingleFieldBuilder;
      39: pop
      40: aload_0
      41: dup
      42: getfield      #21                 // Field bitField0_:I
      45: iconst_2
      46: ior
      47: putfield      #21                 // Field bitField0_:I
      50: aload_0
      51: areturn

  public org.apache.hadoop.hbase.protobuf.generated.QuotaProtos$Quotas$Builder setThrottle(org.apache.hadoop.hbase.protobuf.generated.QuotaProtos$Throttle$Builder);
    Code:
       0: aload_0
       1: getfield      #22                 // Field throttleBuilder_:Lcom/google/protobuf/SingleFieldBuilder;
       4: ifnonnull     22
       7: aload_0
       8: aload_1
       9: invokevirtual #63                 // Method org/apache/hadoop/hbase/protobuf/generated/QuotaProtos$Throttle$Builder.build:()Lorg/apache/hadoop/hbase/protobuf/generated/QuotaProtos$Throttle;
      12: putfield      #10                 // Field throttle_:Lorg/apache/hadoop/hbase/protobuf/generated/QuotaProtos$Throttle;
      15: aload_0
      16: invokevirtual #58                 // Method onChanged:()V
      19: goto          34
      22: aload_0
      23: getfield      #22                 // Field throttleBuilder_:Lcom/google/protobuf/SingleFieldBuilder;
      26: aload_1
      27: invokevirtual #63                 // Method org/apache/hadoop/hbase/protobuf/generated/QuotaProtos$Throttle$Builder.build:()Lorg/apache/hadoop/hbase/protobuf/generated/QuotaProtos$Throttle;
      30: invokevirtual #62                 // Method com/google/protobuf/SingleFieldBuilder.setMessage:(Lcom/google/protobuf/GeneratedMessage;)Lcom/google/protobuf/SingleFieldBuilder;
      33: pop
      34: aload_0
      35: dup
      36: getfield      #21                 // Field bitField0_:I
      39: iconst_2
      40: ior
      41: putfield      #21                 // Field bitField0_:I
      44: aload_0
      45: areturn

  public org.apache.hadoop.hbase.protobuf.generated.QuotaProtos$Quotas$Builder mergeThrottle(org.apache.hadoop.hbase.protobuf.generated.QuotaProtos$Throttle);
    Code:
       0: aload_0
       1: getfield      #22                 // Field throttleBuilder_:Lcom/google/protobuf/SingleFieldBuilder;
       4: ifnonnull     60
       7: aload_0
       8: getfield      #21                 // Field bitField0_:I
      11: iconst_2
      12: iand
      13: iconst_2
      14: if_icmpne     48
      17: aload_0
      18: getfield      #10                 // Field throttle_:Lorg/apache/hadoop/hbase/protobuf/generated/QuotaProtos$Throttle;
      21: invokestatic  #9                  // Method org/apache/hadoop/hbase/protobuf/generated/QuotaProtos$Throttle.getDefaultInstance:()Lorg/apache/hadoop/hbase/protobuf/generated/QuotaProtos$Throttle;
      24: if_acmpeq     48
      27: aload_0
      28: aload_0
      29: getfield      #10                 // Field throttle_:Lorg/apache/hadoop/hbase/protobuf/generated/QuotaProtos$Throttle;
      32: invokestatic  #64                 // Method org/apache/hadoop/hbase/protobuf/generated/QuotaProtos$Throttle.newBuilder:(Lorg/apache/hadoop/hbase/protobuf/generated/QuotaProtos$Throttle;)Lorg/apache/hadoop/hbase/protobuf/generated/QuotaProtos$Throttle$Builder;
      35: aload_1
      36: invokevirtual #65                 // Method org/apache/hadoop/hbase/protobuf/generated/QuotaProtos$Throttle$Builder.mergeFrom:(Lorg/apache/hadoop/hbase/protobuf/generated/QuotaProtos$Throttle;)Lorg/apache/hadoop/hbase/protobuf/generated/QuotaProtos$Throttle$Builder;
      39: invokevirtual #66                 // Method org/apache/hadoop/hbase/protobuf/generated/QuotaProtos$Throttle$Builder.buildPartial:()Lorg/apache/hadoop/hbase/protobuf/generated/QuotaProtos$Throttle;
      42: putfield      #10                 // Field throttle_:Lorg/apache/hadoop/hbase/protobuf/generated/QuotaProtos$Throttle;
      45: goto          53
      48: aload_0
      49: aload_1
      50: putfield      #10                 // Field throttle_:Lorg/apache/hadoop/hbase/protobuf/generated/QuotaProtos$Throttle;
      53: aload_0
      54: invokevirtual #58                 // Method onChanged:()V
      57: goto          69
      60: aload_0
      61: getfield      #22                 // Field throttleBuilder_:Lcom/google/protobuf/SingleFieldBuilder;
      64: aload_1
      65: invokevirtual #67                 // Method com/google/protobuf/SingleFieldBuilder.mergeFrom:(Lcom/google/protobuf/GeneratedMessage;)Lcom/google/protobuf/SingleFieldBuilder;
      68: pop
      69: aload_0
      70: dup
      71: getfield      #21                 // Field bitField0_:I
      74: iconst_2
      75: ior
      76: putfield      #21                 // Field bitField0_:I
      79: aload_0
      80: areturn

  public org.apache.hadoop.hbase.protobuf.generated.QuotaProtos$Quotas$Builder clearThrottle();
    Code:
       0: aload_0
       1: getfield      #22                 // Field throttleBuilder_:Lcom/google/protobuf/SingleFieldBuilder;
       4: ifnonnull     21
       7: aload_0
       8: invokestatic  #9                  // Method org/apache/hadoop/hbase/protobuf/generated/QuotaProtos$Throttle.getDefaultInstance:()Lorg/apache/hadoop/hbase/protobuf/generated/QuotaProtos$Throttle;
      11: putfield      #10                 // Field throttle_:Lorg/apache/hadoop/hbase/protobuf/generated/QuotaProtos$Throttle;
      14: aload_0
      15: invokevirtual #58                 // Method onChanged:()V
      18: goto          29
      21: aload_0
      22: getfield      #22                 // Field throttleBuilder_:Lcom/google/protobuf/SingleFieldBuilder;
      25: invokevirtual #23                 // Method com/google/protobuf/SingleFieldBuilder.clear:()Lcom/google/protobuf/SingleFieldBuilder;
      28: pop
      29: aload_0
      30: aload_0
      31: getfield      #21                 // Field bitField0_:I
      34: bipush        -3
      36: iand
      37: putfield      #21                 // Field bitField0_:I
      40: aload_0
      41: areturn

  public org.apache.hadoop.hbase.protobuf.generated.QuotaProtos$Throttle$Builder getThrottleBuilder();
    Code:
       0: aload_0
       1: dup
       2: getfield      #21                 // Field bitField0_:I
       5: iconst_2
       6: ior
       7: putfield      #21                 // Field bitField0_:I
      10: aload_0
      11: invokevirtual #58                 // Method onChanged:()V
      14: aload_0
      15: invokespecial #16                 // Method getThrottleFieldBuilder:()Lcom/google/protobuf/SingleFieldBuilder;
      18: invokevirtual #68                 // Method com/google/protobuf/SingleFieldBuilder.getBuilder:()Lcom/google/protobuf/GeneratedMessage$Builder;
      21: checkcast     #69                 // class org/apache/hadoop/hbase/protobuf/generated/QuotaProtos$Throttle$Builder
      24: areturn

  public org.apache.hadoop.hbase.protobuf.generated.QuotaProtos$ThrottleOrBuilder getThrottleOrBuilder();
    Code:
       0: aload_0
       1: getfield      #22                 // Field throttleBuilder_:Lcom/google/protobuf/SingleFieldBuilder;
       4: ifnull        18
       7: aload_0
       8: getfield      #22                 // Field throttleBuilder_:Lcom/google/protobuf/SingleFieldBuilder;
      11: invokevirtual #70                 // Method com/google/protobuf/SingleFieldBuilder.getMessageOrBuilder:()Lcom/google/protobuf/MessageOrBuilder;
      14: checkcast     #71                 // class org/apache/hadoop/hbase/protobuf/generated/QuotaProtos$ThrottleOrBuilder
      17: areturn
      18: aload_0
      19: getfield      #10                 // Field throttle_:Lorg/apache/hadoop/hbase/protobuf/generated/QuotaProtos$Throttle;
      22: areturn

  public boolean hasSpace();
    Code:
       0: aload_0
       1: getfield      #21                 // Field bitField0_:I
       4: iconst_4
       5: iand
       6: iconst_4
       7: if_icmpne     14
      10: iconst_1
      11: goto          15
      14: iconst_0
      15: ireturn

  public org.apache.hadoop.hbase.protobuf.generated.QuotaProtos$SpaceQuota getSpace();
    Code:
       0: aload_0
       1: getfield      #24                 // Field spaceBuilder_:Lcom/google/protobuf/SingleFieldBuilder;
       4: ifnonnull     12
       7: aload_0
       8: getfield      #12                 // Field space_:Lorg/apache/hadoop/hbase/protobuf/generated/QuotaProtos$SpaceQuota;
      11: areturn
      12: aload_0
      13: getfield      #24                 // Field spaceBuilder_:Lcom/google/protobuf/SingleFieldBuilder;
      16: invokevirtual #59                 // Method com/google/protobuf/SingleFieldBuilder.getMessage:()Lcom/google/protobuf/GeneratedMessage;
      19: checkcast     #36                 // class org/apache/hadoop/hbase/protobuf/generated/QuotaProtos$SpaceQuota
      22: areturn

  public org.apache.hadoop.hbase.protobuf.generated.QuotaProtos$Quotas$Builder setSpace(org.apache.hadoop.hbase.protobuf.generated.QuotaProtos$SpaceQuota);
    Code:
       0: aload_0
       1: getfield      #24                 // Field spaceBuilder_:Lcom/google/protobuf/SingleFieldBuilder;
       4: ifnonnull     31
       7: aload_1
       8: ifnonnull     19
      11: new           #60                 // class java/lang/NullPointerException
      14: dup
      15: invokespecial #61                 // Method java/lang/NullPointerException."<init>":()V
      18: athrow
      19: aload_0
      20: aload_1
      21: putfield      #12                 // Field space_:Lorg/apache/hadoop/hbase/protobuf/generated/QuotaProtos$SpaceQuota;
      24: aload_0
      25: invokevirtual #58                 // Method onChanged:()V
      28: goto          40
      31: aload_0
      32: getfield      #24                 // Field spaceBuilder_:Lcom/google/protobuf/SingleFieldBuilder;
      35: aload_1
      36: invokevirtual #62                 // Method com/google/protobuf/SingleFieldBuilder.setMessage:(Lcom/google/protobuf/GeneratedMessage;)Lcom/google/protobuf/SingleFieldBuilder;
      39: pop
      40: aload_0
      41: dup
      42: getfield      #21                 // Field bitField0_:I
      45: iconst_4
      46: ior
      47: putfield      #21                 // Field bitField0_:I
      50: aload_0
      51: areturn

  public org.apache.hadoop.hbase.protobuf.generated.QuotaProtos$Quotas$Builder setSpace(org.apache.hadoop.hbase.protobuf.generated.QuotaProtos$SpaceQuota$Builder);
    Code:
       0: aload_0
       1: getfield      #24                 // Field spaceBuilder_:Lcom/google/protobuf/SingleFieldBuilder;
       4: ifnonnull     22
       7: aload_0
       8: aload_1
       9: invokevirtual #76                 // Method org/apache/hadoop/hbase/protobuf/generated/QuotaProtos$SpaceQuota$Builder.build:()Lorg/apache/hadoop/hbase/protobuf/generated/QuotaProtos$SpaceQuota;
      12: putfield      #12                 // Field space_:Lorg/apache/hadoop/hbase/protobuf/generated/QuotaProtos$SpaceQuota;
      15: aload_0
      16: invokevirtual #58                 // Method onChanged:()V
      19: goto          34
      22: aload_0
      23: getfield      #24                 // Field spaceBuilder_:Lcom/google/protobuf/SingleFieldBuilder;
      26: aload_1
      27: invokevirtual #76                 // Method org/apache/hadoop/hbase/protobuf/generated/QuotaProtos$SpaceQuota$Builder.build:()Lorg/apache/hadoop/hbase/protobuf/generated/QuotaProtos$SpaceQuota;
      30: invokevirtual #62                 // Method com/google/protobuf/SingleFieldBuilder.setMessage:(Lcom/google/protobuf/GeneratedMessage;)Lcom/google/protobuf/SingleFieldBuilder;
      33: pop
      34: aload_0
      35: dup
      36: getfield      #21                 // Field bitField0_:I
      39: iconst_4
      40: ior
      41: putfield      #21                 // Field bitField0_:I
      44: aload_0
      45: areturn

  public org.apache.hadoop.hbase.protobuf.generated.QuotaProtos$Quotas$Builder mergeSpace(org.apache.hadoop.hbase.protobuf.generated.QuotaProtos$SpaceQuota);
    Code:
       0: aload_0
       1: getfield      #24                 // Field spaceBuilder_:Lcom/google/protobuf/SingleFieldBuilder;
       4: ifnonnull     60
       7: aload_0
       8: getfield      #21                 // Field bitField0_:I
      11: iconst_4
      12: iand
      13: iconst_4
      14: if_icmpne     48
      17: aload_0
      18: getfield      #12                 // Field space_:Lorg/apache/hadoop/hbase/protobuf/generated/QuotaProtos$SpaceQuota;
      21: invokestatic  #11                 // Method org/apache/hadoop/hbase/protobuf/generated/QuotaProtos$SpaceQuota.getDefaultInstance:()Lorg/apache/hadoop/hbase/protobuf/generated/QuotaProtos$SpaceQuota;
      24: if_acmpeq     48
      27: aload_0
      28: aload_0
      29: getfield      #12                 // Field space_:Lorg/apache/hadoop/hbase/protobuf/generated/QuotaProtos$SpaceQuota;
      32: invokestatic  #77                 // Method org/apache/hadoop/hbase/protobuf/generated/QuotaProtos$SpaceQuota.newBuilder:(Lorg/apache/hadoop/hbase/protobuf/generated/QuotaProtos$SpaceQuota;)Lorg/apache/hadoop/hbase/protobuf/generated/QuotaProtos$SpaceQuota$Builder;
      35: aload_1
      36: invokevirtual #78                 // Method org/apache/hadoop/hbase/protobuf/generated/QuotaProtos$SpaceQuota$Builder.mergeFrom:(Lorg/apache/hadoop/hbase/protobuf/generated/QuotaProtos$SpaceQuota;)Lorg/apache/hadoop/hbase/protobuf/generated/QuotaProtos$SpaceQuota$Builder;
      39: invokevirtual #79                 // Method org/apache/hadoop/hbase/protobuf/generated/QuotaProtos$SpaceQuota$Builder.buildPartial:()Lorg/apache/hadoop/hbase/protobuf/generated/QuotaProtos$SpaceQuota;
      42: putfield      #12                 // Field space_:Lorg/apache/hadoop/hbase/protobuf/generated/QuotaProtos$SpaceQuota;
      45: goto          53
      48: aload_0
      49: aload_1
      50: putfield      #12                 // Field space_:Lorg/apache/hadoop/hbase/protobuf/generated/QuotaProtos$SpaceQuota;
      53: aload_0
      54: invokevirtual #58                 // Method onChanged:()V
      57: goto          69
      60: aload_0
      61: getfield      #24                 // Field spaceBuilder_:Lcom/google/protobuf/SingleFieldBuilder;
      64: aload_1
      65: invokevirtual #67                 // Method com/google/protobuf/SingleFieldBuilder.mergeFrom:(Lcom/google/protobuf/GeneratedMessage;)Lcom/google/protobuf/SingleFieldBuilder;
      68: pop
      69: aload_0
      70: dup
      71: getfield      #21                 // Field bitField0_:I
      74: iconst_4
      75: ior
      76: putfield      #21                 // Field bitField0_:I
      79: aload_0
      80: areturn

  public org.apache.hadoop.hbase.protobuf.generated.QuotaProtos$Quotas$Builder clearSpace();
    Code:
       0: aload_0
       1: getfield      #24                 // Field spaceBuilder_:Lcom/google/protobuf/SingleFieldBuilder;
       4: ifnonnull     21
       7: aload_0
       8: invokestatic  #11                 // Method org/apache/hadoop/hbase/protobuf/generated/QuotaProtos$SpaceQuota.getDefaultInstance:()Lorg/apache/hadoop/hbase/protobuf/generated/QuotaProtos$SpaceQuota;
      11: putfield      #12                 // Field space_:Lorg/apache/hadoop/hbase/protobuf/generated/QuotaProtos$SpaceQuota;
      14: aload_0
      15: invokevirtual #58                 // Method onChanged:()V
      18: goto          29
      21: aload_0
      22: getfield      #24                 // Field spaceBuilder_:Lcom/google/protobuf/SingleFieldBuilder;
      25: invokevirtual #23                 // Method com/google/protobuf/SingleFieldBuilder.clear:()Lcom/google/protobuf/SingleFieldBuilder;
      28: pop
      29: aload_0
      30: aload_0
      31: getfield      #21                 // Field bitField0_:I
      34: bipush        -5
      36: iand
      37: putfield      #21                 // Field bitField0_:I
      40: aload_0
      41: areturn

  public org.apache.hadoop.hbase.protobuf.generated.QuotaProtos$SpaceQuota$Builder getSpaceBuilder();
    Code:
       0: aload_0
       1: dup
       2: getfield      #21                 // Field bitField0_:I
       5: iconst_4
       6: ior
       7: putfield      #21                 // Field bitField0_:I
      10: aload_0
      11: invokevirtual #58                 // Method onChanged:()V
      14: aload_0
      15: invokespecial #17                 // Method getSpaceFieldBuilder:()Lcom/google/protobuf/SingleFieldBuilder;
      18: invokevirtual #68                 // Method com/google/protobuf/SingleFieldBuilder.getBuilder:()Lcom/google/protobuf/GeneratedMessage$Builder;
      21: checkcast     #80                 // class org/apache/hadoop/hbase/protobuf/generated/QuotaProtos$SpaceQuota$Builder
      24: areturn

  public org.apache.hadoop.hbase.protobuf.generated.QuotaProtos$SpaceQuotaOrBuilder getSpaceOrBuilder();
    Code:
       0: aload_0
       1: getfield      #24                 // Field spaceBuilder_:Lcom/google/protobuf/SingleFieldBuilder;
       4: ifnull        18
       7: aload_0
       8: getfield      #24                 // Field spaceBuilder_:Lcom/google/protobuf/SingleFieldBuilder;
      11: invokevirtual #70                 // Method com/google/protobuf/SingleFieldBuilder.getMessageOrBuilder:()Lcom/google/protobuf/MessageOrBuilder;
      14: checkcast     #81                 // class org/apache/hadoop/hbase/protobuf/generated/QuotaProtos$SpaceQuotaOrBuilder
      17: areturn
      18: aload_0
      19: getfield      #12                 // Field space_:Lorg/apache/hadoop/hbase/protobuf/generated/QuotaProtos$SpaceQuota;
      22: areturn

  public com.google.protobuf.GeneratedMessage$Builder clear();
    Code:
       0: aload_0
       1: invokevirtual #82                 // Method clear:()Lorg/apache/hadoop/hbase/protobuf/generated/QuotaProtos$Quotas$Builder;
       4: areturn

  public com.google.protobuf.GeneratedMessage$Builder clone();
    Code:
       0: aload_0
       1: invokevirtual #83                 // Method clone:()Lorg/apache/hadoop/hbase/protobuf/generated/QuotaProtos$Quotas$Builder;
       4: areturn

  public com.google.protobuf.AbstractMessage$Builder mergeFrom(com.google.protobuf.CodedInputStream, com.google.protobuf.ExtensionRegistryLite) throws java.io.IOException;
    Code:
       0: aload_0
       1: aload_1
       2: aload_2
       3: invokevirtual #84                 // Method mergeFrom:(Lcom/google/protobuf/CodedInputStream;Lcom/google/protobuf/ExtensionRegistryLite;)Lorg/apache/hadoop/hbase/protobuf/generated/QuotaProtos$Quotas$Builder;
       6: areturn

  public com.google.protobuf.AbstractMessage$Builder mergeFrom(com.google.protobuf.Message);
    Code:
       0: aload_0
       1: aload_1
       2: invokevirtual #85                 // Method mergeFrom:(Lcom/google/protobuf/Message;)Lorg/apache/hadoop/hbase/protobuf/generated/QuotaProtos$Quotas$Builder;
       5: areturn

  public com.google.protobuf.AbstractMessage$Builder clear();
    Code:
       0: aload_0
       1: invokevirtual #82                 // Method clear:()Lorg/apache/hadoop/hbase/protobuf/generated/QuotaProtos$Quotas$Builder;
       4: areturn

  public com.google.protobuf.AbstractMessage$Builder clone();
    Code:
       0: aload_0
       1: invokevirtual #83                 // Method clone:()Lorg/apache/hadoop/hbase/protobuf/generated/QuotaProtos$Quotas$Builder;
       4: areturn

  public com.google.protobuf.Message$Builder mergeFrom(com.google.protobuf.CodedInputStream, com.google.protobuf.ExtensionRegistryLite) throws java.io.IOException;
    Code:
       0: aload_0
       1: aload_1
       2: aload_2
       3: invokevirtual #84                 // Method mergeFrom:(Lcom/google/protobuf/CodedInputStream;Lcom/google/protobuf/ExtensionRegistryLite;)Lorg/apache/hadoop/hbase/protobuf/generated/QuotaProtos$Quotas$Builder;
       6: areturn

  public com.google.protobuf.Message$Builder clone();
    Code:
       0: aload_0
       1: invokevirtual #83                 // Method clone:()Lorg/apache/hadoop/hbase/protobuf/generated/QuotaProtos$Quotas$Builder;
       4: areturn

  public com.google.protobuf.Message buildPartial();
    Code:
       0: aload_0
       1: invokevirtual #25                 // Method buildPartial:()Lorg/apache/hadoop/hbase/protobuf/generated/QuotaProtos$Quotas;
       4: areturn

  public com.google.protobuf.Message build();
    Code:
       0: aload_0
       1: invokevirtual #86                 // Method build:()Lorg/apache/hadoop/hbase/protobuf/generated/QuotaProtos$Quotas;
       4: areturn

  public com.google.protobuf.Message$Builder mergeFrom(com.google.protobuf.Message);
    Code:
       0: aload_0
       1: aload_1
       2: invokevirtual #85                 // Method mergeFrom:(Lcom/google/protobuf/Message;)Lorg/apache/hadoop/hbase/protobuf/generated/QuotaProtos$Quotas$Builder;
       5: areturn

  public com.google.protobuf.Message$Builder clear();
    Code:
       0: aload_0
       1: invokevirtual #82                 // Method clear:()Lorg/apache/hadoop/hbase/protobuf/generated/QuotaProtos$Quotas$Builder;
       4: areturn

  public com.google.protobuf.MessageLite$Builder mergeFrom(com.google.protobuf.CodedInputStream, com.google.protobuf.ExtensionRegistryLite) throws java.io.IOException;
    Code:
       0: aload_0
       1: aload_1
       2: aload_2
       3: invokevirtual #84                 // Method mergeFrom:(Lcom/google/protobuf/CodedInputStream;Lcom/google/protobuf/ExtensionRegistryLite;)Lorg/apache/hadoop/hbase/protobuf/generated/QuotaProtos$Quotas$Builder;
       6: areturn

  public com.google.protobuf.MessageLite$Builder clone();
    Code:
       0: aload_0
       1: invokevirtual #83                 // Method clone:()Lorg/apache/hadoop/hbase/protobuf/generated/QuotaProtos$Quotas$Builder;
       4: areturn

  public com.google.protobuf.MessageLite buildPartial();
    Code:
       0: aload_0
       1: invokevirtual #25                 // Method buildPartial:()Lorg/apache/hadoop/hbase/protobuf/generated/QuotaProtos$Quotas;
       4: areturn

  public com.google.protobuf.MessageLite build();
    Code:
       0: aload_0
       1: invokevirtual #86                 // Method build:()Lorg/apache/hadoop/hbase/protobuf/generated/QuotaProtos$Quotas;
       4: areturn

  public com.google.protobuf.MessageLite$Builder clear();
    Code:
       0: aload_0
       1: invokevirtual #82                 // Method clear:()Lorg/apache/hadoop/hbase/protobuf/generated/QuotaProtos$Quotas$Builder;
       4: areturn

  public com.google.protobuf.MessageLite getDefaultInstanceForType();
    Code:
       0: aload_0
       1: invokevirtual #87                 // Method getDefaultInstanceForType:()Lorg/apache/hadoop/hbase/protobuf/generated/QuotaProtos$Quotas;
       4: areturn

  public com.google.protobuf.Message getDefaultInstanceForType();
    Code:
       0: aload_0
       1: invokevirtual #87                 // Method getDefaultInstanceForType:()Lorg/apache/hadoop/hbase/protobuf/generated/QuotaProtos$Quotas;
       4: areturn

  public com.google.protobuf.AbstractMessageLite$Builder mergeFrom(com.google.protobuf.CodedInputStream, com.google.protobuf.ExtensionRegistryLite) throws java.io.IOException;
    Code:
       0: aload_0
       1: aload_1
       2: aload_2
       3: invokevirtual #84                 // Method mergeFrom:(Lcom/google/protobuf/CodedInputStream;Lcom/google/protobuf/ExtensionRegistryLite;)Lorg/apache/hadoop/hbase/protobuf/generated/QuotaProtos$Quotas$Builder;
       6: areturn

  public com.google.protobuf.AbstractMessageLite$Builder clone();
    Code:
       0: aload_0
       1: invokevirtual #83                 // Method clone:()Lorg/apache/hadoop/hbase/protobuf/generated/QuotaProtos$Quotas$Builder;
       4: areturn

  public java.lang.Object clone() throws java.lang.CloneNotSupportedException;
    Code:
       0: aload_0
       1: invokevirtual #83                 // Method clone:()Lorg/apache/hadoop/hbase/protobuf/generated/QuotaProtos$Quotas$Builder;
       4: areturn

  static org.apache.hadoop.hbase.protobuf.generated.QuotaProtos$Quotas$Builder access$3900();
    Code:
       0: invokestatic  #2                  // Method create:()Lorg/apache/hadoop/hbase/protobuf/generated/QuotaProtos$Quotas$Builder;
       3: areturn

  org.apache.hadoop.hbase.protobuf.generated.QuotaProtos$Quotas$Builder(com.google.protobuf.GeneratedMessage$BuilderParent, org.apache.hadoop.hbase.protobuf.generated.QuotaProtos$1);
    Code:
       0: aload_0
       1: aload_1
       2: invokespecial #1                  // Method "<init>":(Lcom/google/protobuf/GeneratedMessage$BuilderParent;)V
       5: return
}
