Compiled from "QuotaProtos.java"
public final class org.apache.hadoop.hbase.protobuf.generated.QuotaProtos$TimedQuota extends com.google.protobuf.GeneratedMessage implements org.apache.hadoop.hbase.protobuf.generated.QuotaProtos$TimedQuotaOrBuilder {
  public static com.google.protobuf.Parser<org.apache.hadoop.hbase.protobuf.generated.QuotaProtos$TimedQuota> PARSER;

  public static final int TIME_UNIT_FIELD_NUMBER;

  public static final int SOFT_LIMIT_FIELD_NUMBER;

  public static final int SHARE_FIELD_NUMBER;

  public static final int SCOPE_FIELD_NUMBER;

  public static org.apache.hadoop.hbase.protobuf.generated.QuotaProtos$TimedQuota getDefaultInstance();
    Code:
       0: getstatic     #17                 // Field defaultInstance:Lorg/apache/hadoop/hbase/protobuf/generated/QuotaProtos$TimedQuota;
       3: areturn

  public org.apache.hadoop.hbase.protobuf.generated.QuotaProtos$TimedQuota getDefaultInstanceForType();
    Code:
       0: getstatic     #17                 // Field defaultInstance:Lorg/apache/hadoop/hbase/protobuf/generated/QuotaProtos$TimedQuota;
       3: areturn

  public final com.google.protobuf.UnknownFieldSet getUnknownFields();
    Code:
       0: aload_0
       1: getfield      #14                 // Field unknownFields:Lcom/google/protobuf/UnknownFieldSet;
       4: areturn

  public static final com.google.protobuf.Descriptors$Descriptor getDescriptor();
    Code:
       0: invokestatic  #35                 // Method org/apache/hadoop/hbase/protobuf/generated/QuotaProtos.access$000:()Lcom/google/protobuf/Descriptors$Descriptor;
       3: areturn

  protected com.google.protobuf.GeneratedMessage$FieldAccessorTable internalGetFieldAccessorTable();
    Code:
       0: invokestatic  #36                 // Method org/apache/hadoop/hbase/protobuf/generated/QuotaProtos.access$100:()Lcom/google/protobuf/GeneratedMessage$FieldAccessorTable;
       3: ldc           #37                 // class org/apache/hadoop/hbase/protobuf/generated/QuotaProtos$TimedQuota
       5: ldc           #38                 // class org/apache/hadoop/hbase/protobuf/generated/QuotaProtos$TimedQuota$Builder
       7: invokevirtual #39                 // Method com/google/protobuf/GeneratedMessage$FieldAccessorTable.ensureFieldAccessorsInitialized:(Ljava/lang/Class;Ljava/lang/Class;)Lcom/google/protobuf/GeneratedMessage$FieldAccessorTable;
      10: areturn

  public com.google.protobuf.Parser<org.apache.hadoop.hbase.protobuf.generated.QuotaProtos$TimedQuota> getParserForType();
    Code:
       0: getstatic     #40                 // Field PARSER:Lcom/google/protobuf/Parser;
       3: areturn

  public boolean hasTimeUnit();
    Code:
       0: aload_0
       1: getfield      #1                  // Field bitField0_:I
       4: iconst_1
       5: iand
       6: iconst_1
       7: if_icmpne     14
      10: iconst_1
      11: goto          15
      14: iconst_0
      15: ireturn

  public org.apache.hadoop.hbase.protobuf.generated.HBaseProtos$TimeUnit getTimeUnit();
    Code:
       0: aload_0
       1: getfield      #5                  // Field timeUnit_:Lorg/apache/hadoop/hbase/protobuf/generated/HBaseProtos$TimeUnit;
       4: areturn

  public boolean hasSoftLimit();
    Code:
       0: aload_0
       1: getfield      #1                  // Field bitField0_:I
       4: iconst_2
       5: iand
       6: iconst_2
       7: if_icmpne     14
      10: iconst_1
      11: goto          15
      14: iconst_0
      15: ireturn

  public long getSoftLimit();
    Code:
       0: aload_0
       1: getfield      #4                  // Field softLimit_:J
       4: lreturn

  public boolean hasShare();
    Code:
       0: aload_0
       1: getfield      #1                  // Field bitField0_:I
       4: iconst_4
       5: iand
       6: iconst_4
       7: if_icmpne     14
      10: iconst_1
      11: goto          15
      14: iconst_0
      15: ireturn

  public float getShare();
    Code:
       0: aload_0
       1: getfield      #3                  // Field share_:F
       4: freturn

  public boolean hasScope();
    Code:
       0: aload_0
       1: getfield      #1                  // Field bitField0_:I
       4: bipush        8
       6: iand
       7: bipush        8
       9: if_icmpne     16
      12: iconst_1
      13: goto          17
      16: iconst_0
      17: ireturn

  public org.apache.hadoop.hbase.protobuf.generated.QuotaProtos$QuotaScope getScope();
    Code:
       0: aload_0
       1: getfield      #2                  // Field scope_:Lorg/apache/hadoop/hbase/protobuf/generated/QuotaProtos$QuotaScope;
       4: areturn

  public final boolean isInitialized();
    Code:
       0: aload_0
       1: getfield      #10                 // Field memoizedIsInitialized:B
       4: istore_1
       5: iload_1
       6: iconst_m1
       7: if_icmpeq     21
      10: iload_1
      11: iconst_1
      12: if_icmpne     19
      15: iconst_1
      16: goto          20
      19: iconst_0
      20: ireturn
      21: aload_0
      22: invokevirtual #43                 // Method hasTimeUnit:()Z
      25: ifne          35
      28: aload_0
      29: iconst_0
      30: putfield      #10                 // Field memoizedIsInitialized:B
      33: iconst_0
      34: ireturn
      35: aload_0
      36: iconst_1
      37: putfield      #10                 // Field memoizedIsInitialized:B
      40: iconst_1
      41: ireturn

  public void writeTo(com.google.protobuf.CodedOutputStream) throws java.io.IOException;
    Code:
       0: aload_0
       1: invokevirtual #44                 // Method getSerializedSize:()I
       4: pop
       5: aload_0
       6: getfield      #1                  // Field bitField0_:I
       9: iconst_1
      10: iand
      11: iconst_1
      12: if_icmpne     27
      15: aload_1
      16: iconst_1
      17: aload_0
      18: getfield      #5                  // Field timeUnit_:Lorg/apache/hadoop/hbase/protobuf/generated/HBaseProtos$TimeUnit;
      21: invokevirtual #45                 // Method org/apache/hadoop/hbase/protobuf/generated/HBaseProtos$TimeUnit.getNumber:()I
      24: invokevirtual #46                 // Method com/google/protobuf/CodedOutputStream.writeEnum:(II)V
      27: aload_0
      28: getfield      #1                  // Field bitField0_:I
      31: iconst_2
      32: iand
      33: iconst_2
      34: if_icmpne     46
      37: aload_1
      38: iconst_2
      39: aload_0
      40: getfield      #4                  // Field softLimit_:J
      43: invokevirtual #47                 // Method com/google/protobuf/CodedOutputStream.writeUInt64:(IJ)V
      46: aload_0
      47: getfield      #1                  // Field bitField0_:I
      50: iconst_4
      51: iand
      52: iconst_4
      53: if_icmpne     65
      56: aload_1
      57: iconst_3
      58: aload_0
      59: getfield      #3                  // Field share_:F
      62: invokevirtual #48                 // Method com/google/protobuf/CodedOutputStream.writeFloat:(IF)V
      65: aload_0
      66: getfield      #1                  // Field bitField0_:I
      69: bipush        8
      71: iand
      72: bipush        8
      74: if_icmpne     89
      77: aload_1
      78: iconst_4
      79: aload_0
      80: getfield      #2                  // Field scope_:Lorg/apache/hadoop/hbase/protobuf/generated/QuotaProtos$QuotaScope;
      83: invokevirtual #49                 // Method org/apache/hadoop/hbase/protobuf/generated/QuotaProtos$QuotaScope.getNumber:()I
      86: invokevirtual #46                 // Method com/google/protobuf/CodedOutputStream.writeEnum:(II)V
      89: aload_0
      90: invokevirtual #50                 // Method getUnknownFields:()Lcom/google/protobuf/UnknownFieldSet;
      93: aload_1
      94: invokevirtual #51                 // Method com/google/protobuf/UnknownFieldSet.writeTo:(Lcom/google/protobuf/CodedOutputStream;)V
      97: return

  public int getSerializedSize();
    Code:
       0: aload_0
       1: getfield      #11                 // Field memoizedSerializedSize:I
       4: istore_1
       5: iload_1
       6: iconst_m1
       7: if_icmpeq     12
      10: iload_1
      11: ireturn
      12: iconst_0
      13: istore_1
      14: aload_0
      15: getfield      #1                  // Field bitField0_:I
      18: iconst_1
      19: iand
      20: iconst_1
      21: if_icmpne     38
      24: iload_1
      25: iconst_1
      26: aload_0
      27: getfield      #5                  // Field timeUnit_:Lorg/apache/hadoop/hbase/protobuf/generated/HBaseProtos$TimeUnit;
      30: invokevirtual #45                 // Method org/apache/hadoop/hbase/protobuf/generated/HBaseProtos$TimeUnit.getNumber:()I
      33: invokestatic  #52                 // Method com/google/protobuf/CodedOutputStream.computeEnumSize:(II)I
      36: iadd
      37: istore_1
      38: aload_0
      39: getfield      #1                  // Field bitField0_:I
      42: iconst_2
      43: iand
      44: iconst_2
      45: if_icmpne     59
      48: iload_1
      49: iconst_2
      50: aload_0
      51: getfield      #4                  // Field softLimit_:J
      54: invokestatic  #53                 // Method com/google/protobuf/CodedOutputStream.computeUInt64Size:(IJ)I
      57: iadd
      58: istore_1
      59: aload_0
      60: getfield      #1                  // Field bitField0_:I
      63: iconst_4
      64: iand
      65: iconst_4
      66: if_icmpne     80
      69: iload_1
      70: iconst_3
      71: aload_0
      72: getfield      #3                  // Field share_:F
      75: invokestatic  #54                 // Method com/google/protobuf/CodedOutputStream.computeFloatSize:(IF)I
      78: iadd
      79: istore_1
      80: aload_0
      81: getfield      #1                  // Field bitField0_:I
      84: bipush        8
      86: iand
      87: bipush        8
      89: if_icmpne     106
      92: iload_1
      93: iconst_4
      94: aload_0
      95: getfield      #2                  // Field scope_:Lorg/apache/hadoop/hbase/protobuf/generated/QuotaProtos$QuotaScope;
      98: invokevirtual #49                 // Method org/apache/hadoop/hbase/protobuf/generated/QuotaProtos$QuotaScope.getNumber:()I
     101: invokestatic  #52                 // Method com/google/protobuf/CodedOutputStream.computeEnumSize:(II)I
     104: iadd
     105: istore_1
     106: iload_1
     107: aload_0
     108: invokevirtual #50                 // Method getUnknownFields:()Lcom/google/protobuf/UnknownFieldSet;
     111: invokevirtual #55                 // Method com/google/protobuf/UnknownFieldSet.getSerializedSize:()I
     114: iadd
     115: istore_1
     116: aload_0
     117: iload_1
     118: putfield      #11                 // Field memoizedSerializedSize:I
     121: iload_1
     122: ireturn

  protected java.lang.Object writeReplace() throws java.io.ObjectStreamException;
    Code:
       0: aload_0
       1: invokespecial #56                 // Method com/google/protobuf/GeneratedMessage.writeReplace:()Ljava/lang/Object;
       4: areturn

  public boolean equals(java.lang.Object);
    Code:
       0: aload_1
       1: aload_0
       2: if_acmpne     7
       5: iconst_1
       6: ireturn
       7: aload_1
       8: instanceof    #37                 // class org/apache/hadoop/hbase/protobuf/generated/QuotaProtos$TimedQuota
      11: ifne          20
      14: aload_0
      15: aload_1
      16: invokespecial #57                 // Method com/google/protobuf/GeneratedMessage.equals:(Ljava/lang/Object;)Z
      19: ireturn
      20: aload_1
      21: checkcast     #37                 // class org/apache/hadoop/hbase/protobuf/generated/QuotaProtos$TimedQuota
      24: astore_2
      25: iconst_1
      26: istore_3
      27: iload_3
      28: ifeq          46
      31: aload_0
      32: invokevirtual #43                 // Method hasTimeUnit:()Z
      35: aload_2
      36: invokevirtual #43                 // Method hasTimeUnit:()Z
      39: if_icmpne     46
      42: iconst_1
      43: goto          47
      46: iconst_0
      47: istore_3
      48: aload_0
      49: invokevirtual #43                 // Method hasTimeUnit:()Z
      52: ifeq          76
      55: iload_3
      56: ifeq          74
      59: aload_0
      60: invokevirtual #58                 // Method getTimeUnit:()Lorg/apache/hadoop/hbase/protobuf/generated/HBaseProtos$TimeUnit;
      63: aload_2
      64: invokevirtual #58                 // Method getTimeUnit:()Lorg/apache/hadoop/hbase/protobuf/generated/HBaseProtos$TimeUnit;
      67: if_acmpne     74
      70: iconst_1
      71: goto          75
      74: iconst_0
      75: istore_3
      76: iload_3
      77: ifeq          95
      80: aload_0
      81: invokevirtual #59                 // Method hasSoftLimit:()Z
      84: aload_2
      85: invokevirtual #59                 // Method hasSoftLimit:()Z
      88: if_icmpne     95
      91: iconst_1
      92: goto          96
      95: iconst_0
      96: istore_3
      97: aload_0
      98: invokevirtual #59                 // Method hasSoftLimit:()Z
     101: ifeq          126
     104: iload_3
     105: ifeq          124
     108: aload_0
     109: invokevirtual #60                 // Method getSoftLimit:()J
     112: aload_2
     113: invokevirtual #60                 // Method getSoftLimit:()J
     116: lcmp
     117: ifne          124
     120: iconst_1
     121: goto          125
     124: iconst_0
     125: istore_3
     126: iload_3
     127: ifeq          145
     130: aload_0
     131: invokevirtual #61                 // Method hasShare:()Z
     134: aload_2
     135: invokevirtual #61                 // Method hasShare:()Z
     138: if_icmpne     145
     141: iconst_1
     142: goto          146
     145: iconst_0
     146: istore_3
     147: aload_0
     148: invokevirtual #61                 // Method hasShare:()Z
     151: ifeq          181
     154: iload_3
     155: ifeq          179
     158: aload_0
     159: invokevirtual #62                 // Method getShare:()F
     162: invokestatic  #63                 // Method java/lang/Float.floatToIntBits:(F)I
     165: aload_2
     166: invokevirtual #62                 // Method getShare:()F
     169: invokestatic  #63                 // Method java/lang/Float.floatToIntBits:(F)I
     172: if_icmpne     179
     175: iconst_1
     176: goto          180
     179: iconst_0
     180: istore_3
     181: iload_3
     182: ifeq          200
     185: aload_0
     186: invokevirtual #64                 // Method hasScope:()Z
     189: aload_2
     190: invokevirtual #64                 // Method hasScope:()Z
     193: if_icmpne     200
     196: iconst_1
     197: goto          201
     200: iconst_0
     201: istore_3
     202: aload_0
     203: invokevirtual #64                 // Method hasScope:()Z
     206: ifeq          230
     209: iload_3
     210: ifeq          228
     213: aload_0
     214: invokevirtual #65                 // Method getScope:()Lorg/apache/hadoop/hbase/protobuf/generated/QuotaProtos$QuotaScope;
     217: aload_2
     218: invokevirtual #65                 // Method getScope:()Lorg/apache/hadoop/hbase/protobuf/generated/QuotaProtos$QuotaScope;
     221: if_acmpne     228
     224: iconst_1
     225: goto          229
     228: iconst_0
     229: istore_3
     230: iload_3
     231: ifeq          252
     234: aload_0
     235: invokevirtual #50                 // Method getUnknownFields:()Lcom/google/protobuf/UnknownFieldSet;
     238: aload_2
     239: invokevirtual #50                 // Method getUnknownFields:()Lcom/google/protobuf/UnknownFieldSet;
     242: invokevirtual #66                 // Method com/google/protobuf/UnknownFieldSet.equals:(Ljava/lang/Object;)Z
     245: ifeq          252
     248: iconst_1
     249: goto          253
     252: iconst_0
     253: istore_3
     254: iload_3
     255: ireturn

  public int hashCode();
    Code:
       0: aload_0
       1: getfield      #12                 // Field memoizedHashCode:I
       4: ifeq          12
       7: aload_0
       8: getfield      #12                 // Field memoizedHashCode:I
      11: ireturn
      12: bipush        41
      14: istore_1
      15: bipush        19
      17: iload_1
      18: imul
      19: aload_0
      20: invokevirtual #67                 // Method getDescriptorForType:()Lcom/google/protobuf/Descriptors$Descriptor;
      23: invokevirtual #68                 // Method java/lang/Object.hashCode:()I
      26: iadd
      27: istore_1
      28: aload_0
      29: invokevirtual #43                 // Method hasTimeUnit:()Z
      32: ifeq          55
      35: bipush        37
      37: iload_1
      38: imul
      39: iconst_1
      40: iadd
      41: istore_1
      42: bipush        53
      44: iload_1
      45: imul
      46: aload_0
      47: invokevirtual #58                 // Method getTimeUnit:()Lorg/apache/hadoop/hbase/protobuf/generated/HBaseProtos$TimeUnit;
      50: invokestatic  #69                 // Method hashEnum:(Lcom/google/protobuf/Internal$EnumLite;)I
      53: iadd
      54: istore_1
      55: aload_0
      56: invokevirtual #59                 // Method hasSoftLimit:()Z
      59: ifeq          82
      62: bipush        37
      64: iload_1
      65: imul
      66: iconst_2
      67: iadd
      68: istore_1
      69: bipush        53
      71: iload_1
      72: imul
      73: aload_0
      74: invokevirtual #60                 // Method getSoftLimit:()J
      77: invokestatic  #70                 // Method hashLong:(J)I
      80: iadd
      81: istore_1
      82: aload_0
      83: invokevirtual #61                 // Method hasShare:()Z
      86: ifeq          109
      89: bipush        37
      91: iload_1
      92: imul
      93: iconst_3
      94: iadd
      95: istore_1
      96: bipush        53
      98: iload_1
      99: imul
     100: aload_0
     101: invokevirtual #62                 // Method getShare:()F
     104: invokestatic  #63                 // Method java/lang/Float.floatToIntBits:(F)I
     107: iadd
     108: istore_1
     109: aload_0
     110: invokevirtual #64                 // Method hasScope:()Z
     113: ifeq          136
     116: bipush        37
     118: iload_1
     119: imul
     120: iconst_4
     121: iadd
     122: istore_1
     123: bipush        53
     125: iload_1
     126: imul
     127: aload_0
     128: invokevirtual #65                 // Method getScope:()Lorg/apache/hadoop/hbase/protobuf/generated/QuotaProtos$QuotaScope;
     131: invokestatic  #69                 // Method hashEnum:(Lcom/google/protobuf/Internal$EnumLite;)I
     134: iadd
     135: istore_1
     136: bipush        29
     138: iload_1
     139: imul
     140: aload_0
     141: invokevirtual #50                 // Method getUnknownFields:()Lcom/google/protobuf/UnknownFieldSet;
     144: invokevirtual #71                 // Method com/google/protobuf/UnknownFieldSet.hashCode:()I
     147: iadd
     148: istore_1
     149: aload_0
     150: iload_1
     151: putfield      #12                 // Field memoizedHashCode:I
     154: iload_1
     155: ireturn

  public static org.apache.hadoop.hbase.protobuf.generated.QuotaProtos$TimedQuota parseFrom(com.google.protobuf.ByteString) throws com.google.protobuf.InvalidProtocolBufferException;
    Code:
       0: getstatic     #40                 // Field PARSER:Lcom/google/protobuf/Parser;
       3: aload_0
       4: invokeinterface #72,  2           // InterfaceMethod com/google/protobuf/Parser.parseFrom:(Lcom/google/protobuf/ByteString;)Ljava/lang/Object;
       9: checkcast     #37                 // class org/apache/hadoop/hbase/protobuf/generated/QuotaProtos$TimedQuota
      12: areturn

  public static org.apache.hadoop.hbase.protobuf.generated.QuotaProtos$TimedQuota parseFrom(com.google.protobuf.ByteString, com.google.protobuf.ExtensionRegistryLite) throws com.google.protobuf.InvalidProtocolBufferException;
    Code:
       0: getstatic     #40                 // Field PARSER:Lcom/google/protobuf/Parser;
       3: aload_0
       4: aload_1
       5: invokeinterface #73,  3           // InterfaceMethod com/google/protobuf/Parser.parseFrom:(Lcom/google/protobuf/ByteString;Lcom/google/protobuf/ExtensionRegistryLite;)Ljava/lang/Object;
      10: checkcast     #37                 // class org/apache/hadoop/hbase/protobuf/generated/QuotaProtos$TimedQuota
      13: areturn

  public static org.apache.hadoop.hbase.protobuf.generated.QuotaProtos$TimedQuota parseFrom(byte[]) throws com.google.protobuf.InvalidProtocolBufferException;
    Code:
       0: getstatic     #40                 // Field PARSER:Lcom/google/protobuf/Parser;
       3: aload_0
       4: invokeinterface #74,  2           // InterfaceMethod com/google/protobuf/Parser.parseFrom:([B)Ljava/lang/Object;
       9: checkcast     #37                 // class org/apache/hadoop/hbase/protobuf/generated/QuotaProtos$TimedQuota
      12: areturn

  public static org.apache.hadoop.hbase.protobuf.generated.QuotaProtos$TimedQuota parseFrom(byte[], com.google.protobuf.ExtensionRegistryLite) throws com.google.protobuf.InvalidProtocolBufferException;
    Code:
       0: getstatic     #40                 // Field PARSER:Lcom/google/protobuf/Parser;
       3: aload_0
       4: aload_1
       5: invokeinterface #75,  3           // InterfaceMethod com/google/protobuf/Parser.parseFrom:([BLcom/google/protobuf/ExtensionRegistryLite;)Ljava/lang/Object;
      10: checkcast     #37                 // class org/apache/hadoop/hbase/protobuf/generated/QuotaProtos$TimedQuota
      13: areturn

  public static org.apache.hadoop.hbase.protobuf.generated.QuotaProtos$TimedQuota parseFrom(java.io.InputStream) throws java.io.IOException;
    Code:
       0: getstatic     #40                 // Field PARSER:Lcom/google/protobuf/Parser;
       3: aload_0
       4: invokeinterface #76,  2           // InterfaceMethod com/google/protobuf/Parser.parseFrom:(Ljava/io/InputStream;)Ljava/lang/Object;
       9: checkcast     #37                 // class org/apache/hadoop/hbase/protobuf/generated/QuotaProtos$TimedQuota
      12: areturn

  public static org.apache.hadoop.hbase.protobuf.generated.QuotaProtos$TimedQuota parseFrom(java.io.InputStream, com.google.protobuf.ExtensionRegistryLite) throws java.io.IOException;
    Code:
       0: getstatic     #40                 // Field PARSER:Lcom/google/protobuf/Parser;
       3: aload_0
       4: aload_1
       5: invokeinterface #77,  3           // InterfaceMethod com/google/protobuf/Parser.parseFrom:(Ljava/io/InputStream;Lcom/google/protobuf/ExtensionRegistryLite;)Ljava/lang/Object;
      10: checkcast     #37                 // class org/apache/hadoop/hbase/protobuf/generated/QuotaProtos$TimedQuota
      13: areturn

  public static org.apache.hadoop.hbase.protobuf.generated.QuotaProtos$TimedQuota parseDelimitedFrom(java.io.InputStream) throws java.io.IOException;
    Code:
       0: getstatic     #40                 // Field PARSER:Lcom/google/protobuf/Parser;
       3: aload_0
       4: invokeinterface #78,  2           // InterfaceMethod com/google/protobuf/Parser.parseDelimitedFrom:(Ljava/io/InputStream;)Ljava/lang/Object;
       9: checkcast     #37                 // class org/apache/hadoop/hbase/protobuf/generated/QuotaProtos$TimedQuota
      12: areturn

  public static org.apache.hadoop.hbase.protobuf.generated.QuotaProtos$TimedQuota parseDelimitedFrom(java.io.InputStream, com.google.protobuf.ExtensionRegistryLite) throws java.io.IOException;
    Code:
       0: getstatic     #40                 // Field PARSER:Lcom/google/protobuf/Parser;
       3: aload_0
       4: aload_1
       5: invokeinterface #79,  3           // InterfaceMethod com/google/protobuf/Parser.parseDelimitedFrom:(Ljava/io/InputStream;Lcom/google/protobuf/ExtensionRegistryLite;)Ljava/lang/Object;
      10: checkcast     #37                 // class org/apache/hadoop/hbase/protobuf/generated/QuotaProtos$TimedQuota
      13: areturn

  public static org.apache.hadoop.hbase.protobuf.generated.QuotaProtos$TimedQuota parseFrom(com.google.protobuf.CodedInputStream) throws java.io.IOException;
    Code:
       0: getstatic     #40                 // Field PARSER:Lcom/google/protobuf/Parser;
       3: aload_0
       4: invokeinterface #80,  2           // InterfaceMethod com/google/protobuf/Parser.parseFrom:(Lcom/google/protobuf/CodedInputStream;)Ljava/lang/Object;
       9: checkcast     #37                 // class org/apache/hadoop/hbase/protobuf/generated/QuotaProtos$TimedQuota
      12: areturn

  public static org.apache.hadoop.hbase.protobuf.generated.QuotaProtos$TimedQuota parseFrom(com.google.protobuf.CodedInputStream, com.google.protobuf.ExtensionRegistryLite) throws java.io.IOException;
    Code:
       0: getstatic     #40                 // Field PARSER:Lcom/google/protobuf/Parser;
       3: aload_0
       4: aload_1
       5: invokeinterface #81,  3           // InterfaceMethod com/google/protobuf/Parser.parseFrom:(Lcom/google/protobuf/CodedInputStream;Lcom/google/protobuf/ExtensionRegistryLite;)Ljava/lang/Object;
      10: checkcast     #37                 // class org/apache/hadoop/hbase/protobuf/generated/QuotaProtos$TimedQuota
      13: areturn

  public static org.apache.hadoop.hbase.protobuf.generated.QuotaProtos$TimedQuota$Builder newBuilder();
    Code:
       0: invokestatic  #82                 // Method org/apache/hadoop/hbase/protobuf/generated/QuotaProtos$TimedQuota$Builder.access$300:()Lorg/apache/hadoop/hbase/protobuf/generated/QuotaProtos$TimedQuota$Builder;
       3: areturn

  public org.apache.hadoop.hbase.protobuf.generated.QuotaProtos$TimedQuota$Builder newBuilderForType();
    Code:
       0: invokestatic  #83                 // Method newBuilder:()Lorg/apache/hadoop/hbase/protobuf/generated/QuotaProtos$TimedQuota$Builder;
       3: areturn

  public static org.apache.hadoop.hbase.protobuf.generated.QuotaProtos$TimedQuota$Builder newBuilder(org.apache.hadoop.hbase.protobuf.generated.QuotaProtos$TimedQuota);
    Code:
       0: invokestatic  #83                 // Method newBuilder:()Lorg/apache/hadoop/hbase/protobuf/generated/QuotaProtos$TimedQuota$Builder;
       3: aload_0
       4: invokevirtual #84                 // Method org/apache/hadoop/hbase/protobuf/generated/QuotaProtos$TimedQuota$Builder.mergeFrom:(Lorg/apache/hadoop/hbase/protobuf/generated/QuotaProtos$TimedQuota;)Lorg/apache/hadoop/hbase/protobuf/generated/QuotaProtos$TimedQuota$Builder;
       7: areturn

  public org.apache.hadoop.hbase.protobuf.generated.QuotaProtos$TimedQuota$Builder toBuilder();
    Code:
       0: aload_0
       1: invokestatic  #85                 // Method newBuilder:(Lorg/apache/hadoop/hbase/protobuf/generated/QuotaProtos$TimedQuota;)Lorg/apache/hadoop/hbase/protobuf/generated/QuotaProtos$TimedQuota$Builder;
       4: areturn

  protected org.apache.hadoop.hbase.protobuf.generated.QuotaProtos$TimedQuota$Builder newBuilderForType(com.google.protobuf.GeneratedMessage$BuilderParent);
    Code:
       0: new           #38                 // class org/apache/hadoop/hbase/protobuf/generated/QuotaProtos$TimedQuota$Builder
       3: dup
       4: aload_1
       5: aconst_null
       6: invokespecial #86                 // Method org/apache/hadoop/hbase/protobuf/generated/QuotaProtos$TimedQuota$Builder."<init>":(Lcom/google/protobuf/GeneratedMessage$BuilderParent;Lorg/apache/hadoop/hbase/protobuf/generated/QuotaProtos$1;)V
       9: astore_2
      10: aload_2
      11: areturn

  protected com.google.protobuf.Message$Builder newBuilderForType(com.google.protobuf.GeneratedMessage$BuilderParent);
    Code:
       0: aload_0
       1: aload_1
       2: invokevirtual #87                 // Method newBuilderForType:(Lcom/google/protobuf/GeneratedMessage$BuilderParent;)Lorg/apache/hadoop/hbase/protobuf/generated/QuotaProtos$TimedQuota$Builder;
       5: areturn

  public com.google.protobuf.Message$Builder toBuilder();
    Code:
       0: aload_0
       1: invokevirtual #88                 // Method toBuilder:()Lorg/apache/hadoop/hbase/protobuf/generated/QuotaProtos$TimedQuota$Builder;
       4: areturn

  public com.google.protobuf.Message$Builder newBuilderForType();
    Code:
       0: aload_0
       1: invokevirtual #89                 // Method newBuilderForType:()Lorg/apache/hadoop/hbase/protobuf/generated/QuotaProtos$TimedQuota$Builder;
       4: areturn

  public com.google.protobuf.MessageLite$Builder toBuilder();
    Code:
       0: aload_0
       1: invokevirtual #88                 // Method toBuilder:()Lorg/apache/hadoop/hbase/protobuf/generated/QuotaProtos$TimedQuota$Builder;
       4: areturn

  public com.google.protobuf.MessageLite$Builder newBuilderForType();
    Code:
       0: aload_0
       1: invokevirtual #89                 // Method newBuilderForType:()Lorg/apache/hadoop/hbase/protobuf/generated/QuotaProtos$TimedQuota$Builder;
       4: areturn

  public com.google.protobuf.MessageLite getDefaultInstanceForType();
    Code:
       0: aload_0
       1: invokevirtual #90                 // Method getDefaultInstanceForType:()Lorg/apache/hadoop/hbase/protobuf/generated/QuotaProtos$TimedQuota;
       4: areturn

  public com.google.protobuf.Message getDefaultInstanceForType();
    Code:
       0: aload_0
       1: invokevirtual #90                 // Method getDefaultInstanceForType:()Lorg/apache/hadoop/hbase/protobuf/generated/QuotaProtos$TimedQuota;
       4: areturn

  org.apache.hadoop.hbase.protobuf.generated.QuotaProtos$TimedQuota(com.google.protobuf.CodedInputStream, com.google.protobuf.ExtensionRegistryLite, org.apache.hadoop.hbase.protobuf.generated.QuotaProtos$1) throws com.google.protobuf.InvalidProtocolBufferException;
    Code:
       0: aload_0
       1: aload_1
       2: aload_2
       3: invokespecial #8                  // Method "<init>":(Lcom/google/protobuf/CodedInputStream;Lcom/google/protobuf/ExtensionRegistryLite;)V
       6: return

  static boolean access$500();
    Code:
       0: getstatic     #7                  // Field alwaysUseFieldBuilders:Z
       3: ireturn

  org.apache.hadoop.hbase.protobuf.generated.QuotaProtos$TimedQuota(com.google.protobuf.GeneratedMessage$Builder, org.apache.hadoop.hbase.protobuf.generated.QuotaProtos$1);
    Code:
       0: aload_0
       1: aload_1
       2: invokespecial #6                  // Method "<init>":(Lcom/google/protobuf/GeneratedMessage$Builder;)V
       5: return

  static org.apache.hadoop.hbase.protobuf.generated.HBaseProtos$TimeUnit access$702(org.apache.hadoop.hbase.protobuf.generated.QuotaProtos$TimedQuota, org.apache.hadoop.hbase.protobuf.generated.HBaseProtos$TimeUnit);
    Code:
       0: aload_0
       1: aload_1
       2: dup_x1
       3: putfield      #5                  // Field timeUnit_:Lorg/apache/hadoop/hbase/protobuf/generated/HBaseProtos$TimeUnit;
       6: areturn

  static long access$802(org.apache.hadoop.hbase.protobuf.generated.QuotaProtos$TimedQuota, long);
    Code:
       0: aload_0
       1: lload_1
       2: dup2_x1
       3: putfield      #4                  // Field softLimit_:J
       6: lreturn

  static float access$902(org.apache.hadoop.hbase.protobuf.generated.QuotaProtos$TimedQuota, float);
    Code:
       0: aload_0
       1: fload_1
       2: dup_x1
       3: putfield      #3                  // Field share_:F
       6: freturn

  static org.apache.hadoop.hbase.protobuf.generated.QuotaProtos$QuotaScope access$1002(org.apache.hadoop.hbase.protobuf.generated.QuotaProtos$TimedQuota, org.apache.hadoop.hbase.protobuf.generated.QuotaProtos$QuotaScope);
    Code:
       0: aload_0
       1: aload_1
       2: dup_x1
       3: putfield      #2                  // Field scope_:Lorg/apache/hadoop/hbase/protobuf/generated/QuotaProtos$QuotaScope;
       6: areturn

  static int access$1102(org.apache.hadoop.hbase.protobuf.generated.QuotaProtos$TimedQuota, int);
    Code:
       0: aload_0
       1: iload_1
       2: dup_x1
       3: putfield      #1                  // Field bitField0_:I
       6: ireturn

  static {};
    Code:
       0: new           #91                 // class org/apache/hadoop/hbase/protobuf/generated/QuotaProtos$TimedQuota$1
       3: dup
       4: invokespecial #92                 // Method org/apache/hadoop/hbase/protobuf/generated/QuotaProtos$TimedQuota$1."<init>":()V
       7: putstatic     #40                 // Field PARSER:Lcom/google/protobuf/Parser;
      10: new           #37                 // class org/apache/hadoop/hbase/protobuf/generated/QuotaProtos$TimedQuota
      13: dup
      14: iconst_1
      15: invokespecial #93                 // Method "<init>":(Z)V
      18: putstatic     #17                 // Field defaultInstance:Lorg/apache/hadoop/hbase/protobuf/generated/QuotaProtos$TimedQuota;
      21: getstatic     #17                 // Field defaultInstance:Lorg/apache/hadoop/hbase/protobuf/generated/QuotaProtos$TimedQuota;
      24: invokespecial #18                 // Method initFields:()V
      27: return
}
