Compiled from "QuotaProtos.java"
public final class org.apache.hadoop.hbase.shaded.protobuf.generated.QuotaProtos$GetQuotaStatesResponse$TableQuotaSnapshot extends org.apache.hbase.thirdparty.com.google.protobuf.GeneratedMessageV3 implements org.apache.hadoop.hbase.shaded.protobuf.generated.QuotaProtos$GetQuotaStatesResponse$TableQuotaSnapshotOrBuilder {
  public static final int TABLE_NAME_FIELD_NUMBER;

  public static final int SNAPSHOT_FIELD_NUMBER;

  public static final org.apache.hbase.thirdparty.com.google.protobuf.Parser<org.apache.hadoop.hbase.shaded.protobuf.generated.QuotaProtos$GetQuotaStatesResponse$TableQuotaSnapshot> PARSER;

  public final org.apache.hbase.thirdparty.com.google.protobuf.UnknownFieldSet getUnknownFields();
    Code:
       0: aload_0
       1: getfield      #2                  // Field unknownFields:Lorg/apache/hbase/thirdparty/com/google/protobuf/UnknownFieldSet;
       4: areturn

  public static final org.apache.hbase.thirdparty.com.google.protobuf.Descriptors$Descriptor getDescriptor();
    Code:
       0: invokestatic  #34                 // Method org/apache/hadoop/hbase/shaded/protobuf/generated/QuotaProtos.access$17500:()Lorg/apache/hbase/thirdparty/com/google/protobuf/Descriptors$Descriptor;
       3: areturn

  protected org.apache.hbase.thirdparty.com.google.protobuf.GeneratedMessageV3$FieldAccessorTable internalGetFieldAccessorTable();
    Code:
       0: invokestatic  #35                 // Method org/apache/hadoop/hbase/shaded/protobuf/generated/QuotaProtos.access$17600:()Lorg/apache/hbase/thirdparty/com/google/protobuf/GeneratedMessageV3$FieldAccessorTable;
       3: ldc           #36                 // class org/apache/hadoop/hbase/shaded/protobuf/generated/QuotaProtos$GetQuotaStatesResponse$TableQuotaSnapshot
       5: ldc           #37                 // class org/apache/hadoop/hbase/shaded/protobuf/generated/QuotaProtos$GetQuotaStatesResponse$TableQuotaSnapshot$Builder
       7: invokevirtual #38                 // Method org/apache/hbase/thirdparty/com/google/protobuf/GeneratedMessageV3$FieldAccessorTable.ensureFieldAccessorsInitialized:(Ljava/lang/Class;Ljava/lang/Class;)Lorg/apache/hbase/thirdparty/com/google/protobuf/GeneratedMessageV3$FieldAccessorTable;
      10: areturn

  public boolean hasTableName();
    Code:
       0: aload_0
       1: getfield      #3                  // Field bitField0_:I
       4: iconst_1
       5: iand
       6: iconst_1
       7: if_icmpne     14
      10: iconst_1
      11: goto          15
      14: iconst_0
      15: ireturn

  public org.apache.hadoop.hbase.shaded.protobuf.generated.HBaseProtos$TableName getTableName();
    Code:
       0: aload_0
       1: getfield      #5                  // Field tableName_:Lorg/apache/hadoop/hbase/shaded/protobuf/generated/HBaseProtos$TableName;
       4: ifnonnull     13
       7: invokestatic  #39                 // Method org/apache/hadoop/hbase/shaded/protobuf/generated/HBaseProtos$TableName.getDefaultInstance:()Lorg/apache/hadoop/hbase/shaded/protobuf/generated/HBaseProtos$TableName;
      10: goto          17
      13: aload_0
      14: getfield      #5                  // Field tableName_:Lorg/apache/hadoop/hbase/shaded/protobuf/generated/HBaseProtos$TableName;
      17: areturn

  public org.apache.hadoop.hbase.shaded.protobuf.generated.HBaseProtos$TableNameOrBuilder getTableNameOrBuilder();
    Code:
       0: aload_0
       1: getfield      #5                  // Field tableName_:Lorg/apache/hadoop/hbase/shaded/protobuf/generated/HBaseProtos$TableName;
       4: ifnonnull     13
       7: invokestatic  #39                 // Method org/apache/hadoop/hbase/shaded/protobuf/generated/HBaseProtos$TableName.getDefaultInstance:()Lorg/apache/hadoop/hbase/shaded/protobuf/generated/HBaseProtos$TableName;
      10: goto          17
      13: aload_0
      14: getfield      #5                  // Field tableName_:Lorg/apache/hadoop/hbase/shaded/protobuf/generated/HBaseProtos$TableName;
      17: areturn

  public boolean hasSnapshot();
    Code:
       0: aload_0
       1: getfield      #3                  // Field bitField0_:I
       4: iconst_2
       5: iand
       6: iconst_2
       7: if_icmpne     14
      10: iconst_1
      11: goto          15
      14: iconst_0
      15: ireturn

  public org.apache.hadoop.hbase.shaded.protobuf.generated.QuotaProtos$SpaceQuotaSnapshot getSnapshot();
    Code:
       0: aload_0
       1: getfield      #4                  // Field snapshot_:Lorg/apache/hadoop/hbase/shaded/protobuf/generated/QuotaProtos$SpaceQuotaSnapshot;
       4: ifnonnull     13
       7: invokestatic  #40                 // Method org/apache/hadoop/hbase/shaded/protobuf/generated/QuotaProtos$SpaceQuotaSnapshot.getDefaultInstance:()Lorg/apache/hadoop/hbase/shaded/protobuf/generated/QuotaProtos$SpaceQuotaSnapshot;
      10: goto          17
      13: aload_0
      14: getfield      #4                  // Field snapshot_:Lorg/apache/hadoop/hbase/shaded/protobuf/generated/QuotaProtos$SpaceQuotaSnapshot;
      17: areturn

  public org.apache.hadoop.hbase.shaded.protobuf.generated.QuotaProtos$SpaceQuotaSnapshotOrBuilder getSnapshotOrBuilder();
    Code:
       0: aload_0
       1: getfield      #4                  // Field snapshot_:Lorg/apache/hadoop/hbase/shaded/protobuf/generated/QuotaProtos$SpaceQuotaSnapshot;
       4: ifnonnull     13
       7: invokestatic  #40                 // Method org/apache/hadoop/hbase/shaded/protobuf/generated/QuotaProtos$SpaceQuotaSnapshot.getDefaultInstance:()Lorg/apache/hadoop/hbase/shaded/protobuf/generated/QuotaProtos$SpaceQuotaSnapshot;
      10: goto          17
      13: aload_0
      14: getfield      #4                  // Field snapshot_:Lorg/apache/hadoop/hbase/shaded/protobuf/generated/QuotaProtos$SpaceQuotaSnapshot;
      17: areturn

  public final boolean isInitialized();
    Code:
       0: aload_0
       1: getfield      #9                  // Field memoizedIsInitialized:B
       4: istore_1
       5: iload_1
       6: iconst_1
       7: if_icmpne     12
      10: iconst_1
      11: ireturn
      12: iload_1
      13: ifne          18
      16: iconst_0
      17: ireturn
      18: aload_0
      19: invokevirtual #41                 // Method hasTableName:()Z
      22: ifeq          42
      25: aload_0
      26: invokevirtual #42                 // Method getTableName:()Lorg/apache/hadoop/hbase/shaded/protobuf/generated/HBaseProtos$TableName;
      29: invokevirtual #43                 // Method org/apache/hadoop/hbase/shaded/protobuf/generated/HBaseProtos$TableName.isInitialized:()Z
      32: ifne          42
      35: aload_0
      36: iconst_0
      37: putfield      #9                  // Field memoizedIsInitialized:B
      40: iconst_0
      41: ireturn
      42: aload_0
      43: iconst_1
      44: putfield      #9                  // Field memoizedIsInitialized:B
      47: iconst_1
      48: ireturn

  public void writeTo(org.apache.hbase.thirdparty.com.google.protobuf.CodedOutputStream) throws java.io.IOException;
    Code:
       0: aload_0
       1: getfield      #3                  // Field bitField0_:I
       4: iconst_1
       5: iand
       6: iconst_1
       7: if_icmpne     19
      10: aload_1
      11: iconst_1
      12: aload_0
      13: invokevirtual #42                 // Method getTableName:()Lorg/apache/hadoop/hbase/shaded/protobuf/generated/HBaseProtos$TableName;
      16: invokevirtual #44                 // Method org/apache/hbase/thirdparty/com/google/protobuf/CodedOutputStream.writeMessage:(ILorg/apache/hbase/thirdparty/com/google/protobuf/MessageLite;)V
      19: aload_0
      20: getfield      #3                  // Field bitField0_:I
      23: iconst_2
      24: iand
      25: iconst_2
      26: if_icmpne     38
      29: aload_1
      30: iconst_2
      31: aload_0
      32: invokevirtual #45                 // Method getSnapshot:()Lorg/apache/hadoop/hbase/shaded/protobuf/generated/QuotaProtos$SpaceQuotaSnapshot;
      35: invokevirtual #44                 // Method org/apache/hbase/thirdparty/com/google/protobuf/CodedOutputStream.writeMessage:(ILorg/apache/hbase/thirdparty/com/google/protobuf/MessageLite;)V
      38: aload_0
      39: getfield      #2                  // Field unknownFields:Lorg/apache/hbase/thirdparty/com/google/protobuf/UnknownFieldSet;
      42: aload_1
      43: invokevirtual #46                 // Method org/apache/hbase/thirdparty/com/google/protobuf/UnknownFieldSet.writeTo:(Lorg/apache/hbase/thirdparty/com/google/protobuf/CodedOutputStream;)V
      46: return

  public int getSerializedSize();
    Code:
       0: aload_0
       1: getfield      #47                 // Field memoizedSize:I
       4: istore_1
       5: iload_1
       6: iconst_m1
       7: if_icmpeq     12
      10: iload_1
      11: ireturn
      12: iconst_0
      13: istore_1
      14: aload_0
      15: getfield      #3                  // Field bitField0_:I
      18: iconst_1
      19: iand
      20: iconst_1
      21: if_icmpne     35
      24: iload_1
      25: iconst_1
      26: aload_0
      27: invokevirtual #42                 // Method getTableName:()Lorg/apache/hadoop/hbase/shaded/protobuf/generated/HBaseProtos$TableName;
      30: invokestatic  #48                 // Method org/apache/hbase/thirdparty/com/google/protobuf/CodedOutputStream.computeMessageSize:(ILorg/apache/hbase/thirdparty/com/google/protobuf/MessageLite;)I
      33: iadd
      34: istore_1
      35: aload_0
      36: getfield      #3                  // Field bitField0_:I
      39: iconst_2
      40: iand
      41: iconst_2
      42: if_icmpne     56
      45: iload_1
      46: iconst_2
      47: aload_0
      48: invokevirtual #45                 // Method getSnapshot:()Lorg/apache/hadoop/hbase/shaded/protobuf/generated/QuotaProtos$SpaceQuotaSnapshot;
      51: invokestatic  #48                 // Method org/apache/hbase/thirdparty/com/google/protobuf/CodedOutputStream.computeMessageSize:(ILorg/apache/hbase/thirdparty/com/google/protobuf/MessageLite;)I
      54: iadd
      55: istore_1
      56: iload_1
      57: aload_0
      58: getfield      #2                  // Field unknownFields:Lorg/apache/hbase/thirdparty/com/google/protobuf/UnknownFieldSet;
      61: invokevirtual #49                 // Method org/apache/hbase/thirdparty/com/google/protobuf/UnknownFieldSet.getSerializedSize:()I
      64: iadd
      65: istore_1
      66: aload_0
      67: iload_1
      68: putfield      #47                 // Field memoizedSize:I
      71: iload_1
      72: ireturn

  public boolean equals(java.lang.Object);
    Code:
       0: aload_1
       1: aload_0
       2: if_acmpne     7
       5: iconst_1
       6: ireturn
       7: aload_1
       8: instanceof    #36                 // class org/apache/hadoop/hbase/shaded/protobuf/generated/QuotaProtos$GetQuotaStatesResponse$TableQuotaSnapshot
      11: ifne          20
      14: aload_0
      15: aload_1
      16: invokespecial #50                 // Method org/apache/hbase/thirdparty/com/google/protobuf/GeneratedMessageV3.equals:(Ljava/lang/Object;)Z
      19: ireturn
      20: aload_1
      21: checkcast     #36                 // class org/apache/hadoop/hbase/shaded/protobuf/generated/QuotaProtos$GetQuotaStatesResponse$TableQuotaSnapshot
      24: astore_2
      25: iconst_1
      26: istore_3
      27: iload_3
      28: ifeq          46
      31: aload_0
      32: invokevirtual #41                 // Method hasTableName:()Z
      35: aload_2
      36: invokevirtual #41                 // Method hasTableName:()Z
      39: if_icmpne     46
      42: iconst_1
      43: goto          47
      46: iconst_0
      47: istore_3
      48: aload_0
      49: invokevirtual #41                 // Method hasTableName:()Z
      52: ifeq          79
      55: iload_3
      56: ifeq          77
      59: aload_0
      60: invokevirtual #42                 // Method getTableName:()Lorg/apache/hadoop/hbase/shaded/protobuf/generated/HBaseProtos$TableName;
      63: aload_2
      64: invokevirtual #42                 // Method getTableName:()Lorg/apache/hadoop/hbase/shaded/protobuf/generated/HBaseProtos$TableName;
      67: invokevirtual #51                 // Method org/apache/hadoop/hbase/shaded/protobuf/generated/HBaseProtos$TableName.equals:(Ljava/lang/Object;)Z
      70: ifeq          77
      73: iconst_1
      74: goto          78
      77: iconst_0
      78: istore_3
      79: iload_3
      80: ifeq          98
      83: aload_0
      84: invokevirtual #52                 // Method hasSnapshot:()Z
      87: aload_2
      88: invokevirtual #52                 // Method hasSnapshot:()Z
      91: if_icmpne     98
      94: iconst_1
      95: goto          99
      98: iconst_0
      99: istore_3
     100: aload_0
     101: invokevirtual #52                 // Method hasSnapshot:()Z
     104: ifeq          131
     107: iload_3
     108: ifeq          129
     111: aload_0
     112: invokevirtual #45                 // Method getSnapshot:()Lorg/apache/hadoop/hbase/shaded/protobuf/generated/QuotaProtos$SpaceQuotaSnapshot;
     115: aload_2
     116: invokevirtual #45                 // Method getSnapshot:()Lorg/apache/hadoop/hbase/shaded/protobuf/generated/QuotaProtos$SpaceQuotaSnapshot;
     119: invokevirtual #53                 // Method org/apache/hadoop/hbase/shaded/protobuf/generated/QuotaProtos$SpaceQuotaSnapshot.equals:(Ljava/lang/Object;)Z
     122: ifeq          129
     125: iconst_1
     126: goto          130
     129: iconst_0
     130: istore_3
     131: iload_3
     132: ifeq          153
     135: aload_0
     136: getfield      #2                  // Field unknownFields:Lorg/apache/hbase/thirdparty/com/google/protobuf/UnknownFieldSet;
     139: aload_2
     140: getfield      #2                  // Field unknownFields:Lorg/apache/hbase/thirdparty/com/google/protobuf/UnknownFieldSet;
     143: invokevirtual #54                 // Method org/apache/hbase/thirdparty/com/google/protobuf/UnknownFieldSet.equals:(Ljava/lang/Object;)Z
     146: ifeq          153
     149: iconst_1
     150: goto          154
     153: iconst_0
     154: istore_3
     155: iload_3
     156: ireturn

  public int hashCode();
    Code:
       0: aload_0
       1: getfield      #55                 // Field memoizedHashCode:I
       4: ifeq          12
       7: aload_0
       8: getfield      #55                 // Field memoizedHashCode:I
      11: ireturn
      12: bipush        41
      14: istore_1
      15: bipush        19
      17: iload_1
      18: imul
      19: invokestatic  #56                 // Method getDescriptor:()Lorg/apache/hbase/thirdparty/com/google/protobuf/Descriptors$Descriptor;
      22: invokevirtual #57                 // Method java/lang/Object.hashCode:()I
      25: iadd
      26: istore_1
      27: aload_0
      28: invokevirtual #41                 // Method hasTableName:()Z
      31: ifeq          54
      34: bipush        37
      36: iload_1
      37: imul
      38: iconst_1
      39: iadd
      40: istore_1
      41: bipush        53
      43: iload_1
      44: imul
      45: aload_0
      46: invokevirtual #42                 // Method getTableName:()Lorg/apache/hadoop/hbase/shaded/protobuf/generated/HBaseProtos$TableName;
      49: invokevirtual #58                 // Method org/apache/hadoop/hbase/shaded/protobuf/generated/HBaseProtos$TableName.hashCode:()I
      52: iadd
      53: istore_1
      54: aload_0
      55: invokevirtual #52                 // Method hasSnapshot:()Z
      58: ifeq          81
      61: bipush        37
      63: iload_1
      64: imul
      65: iconst_2
      66: iadd
      67: istore_1
      68: bipush        53
      70: iload_1
      71: imul
      72: aload_0
      73: invokevirtual #45                 // Method getSnapshot:()Lorg/apache/hadoop/hbase/shaded/protobuf/generated/QuotaProtos$SpaceQuotaSnapshot;
      76: invokevirtual #59                 // Method org/apache/hadoop/hbase/shaded/protobuf/generated/QuotaProtos$SpaceQuotaSnapshot.hashCode:()I
      79: iadd
      80: istore_1
      81: bipush        29
      83: iload_1
      84: imul
      85: aload_0
      86: getfield      #2                  // Field unknownFields:Lorg/apache/hbase/thirdparty/com/google/protobuf/UnknownFieldSet;
      89: invokevirtual #60                 // Method org/apache/hbase/thirdparty/com/google/protobuf/UnknownFieldSet.hashCode:()I
      92: iadd
      93: istore_1
      94: aload_0
      95: iload_1
      96: putfield      #55                 // Field memoizedHashCode:I
      99: iload_1
     100: ireturn

  public static org.apache.hadoop.hbase.shaded.protobuf.generated.QuotaProtos$GetQuotaStatesResponse$TableQuotaSnapshot parseFrom(java.nio.ByteBuffer) throws org.apache.hbase.thirdparty.com.google.protobuf.InvalidProtocolBufferException;
    Code:
       0: getstatic     #61                 // Field PARSER:Lorg/apache/hbase/thirdparty/com/google/protobuf/Parser;
       3: aload_0
       4: invokeinterface #62,  2           // InterfaceMethod org/apache/hbase/thirdparty/com/google/protobuf/Parser.parseFrom:(Ljava/nio/ByteBuffer;)Ljava/lang/Object;
       9: checkcast     #36                 // class org/apache/hadoop/hbase/shaded/protobuf/generated/QuotaProtos$GetQuotaStatesResponse$TableQuotaSnapshot
      12: areturn

  public static org.apache.hadoop.hbase.shaded.protobuf.generated.QuotaProtos$GetQuotaStatesResponse$TableQuotaSnapshot parseFrom(java.nio.ByteBuffer, org.apache.hbase.thirdparty.com.google.protobuf.ExtensionRegistryLite) throws org.apache.hbase.thirdparty.com.google.protobuf.InvalidProtocolBufferException;
    Code:
       0: getstatic     #61                 // Field PARSER:Lorg/apache/hbase/thirdparty/com/google/protobuf/Parser;
       3: aload_0
       4: aload_1
       5: invokeinterface #63,  3           // InterfaceMethod org/apache/hbase/thirdparty/com/google/protobuf/Parser.parseFrom:(Ljava/nio/ByteBuffer;Lorg/apache/hbase/thirdparty/com/google/protobuf/ExtensionRegistryLite;)Ljava/lang/Object;
      10: checkcast     #36                 // class org/apache/hadoop/hbase/shaded/protobuf/generated/QuotaProtos$GetQuotaStatesResponse$TableQuotaSnapshot
      13: areturn

  public static org.apache.hadoop.hbase.shaded.protobuf.generated.QuotaProtos$GetQuotaStatesResponse$TableQuotaSnapshot parseFrom(org.apache.hbase.thirdparty.com.google.protobuf.ByteString) throws org.apache.hbase.thirdparty.com.google.protobuf.InvalidProtocolBufferException;
    Code:
       0: getstatic     #61                 // Field PARSER:Lorg/apache/hbase/thirdparty/com/google/protobuf/Parser;
       3: aload_0
       4: invokeinterface #64,  2           // InterfaceMethod org/apache/hbase/thirdparty/com/google/protobuf/Parser.parseFrom:(Lorg/apache/hbase/thirdparty/com/google/protobuf/ByteString;)Ljava/lang/Object;
       9: checkcast     #36                 // class org/apache/hadoop/hbase/shaded/protobuf/generated/QuotaProtos$GetQuotaStatesResponse$TableQuotaSnapshot
      12: areturn

  public static org.apache.hadoop.hbase.shaded.protobuf.generated.QuotaProtos$GetQuotaStatesResponse$TableQuotaSnapshot parseFrom(org.apache.hbase.thirdparty.com.google.protobuf.ByteString, org.apache.hbase.thirdparty.com.google.protobuf.ExtensionRegistryLite) throws org.apache.hbase.thirdparty.com.google.protobuf.InvalidProtocolBufferException;
    Code:
       0: getstatic     #61                 // Field PARSER:Lorg/apache/hbase/thirdparty/com/google/protobuf/Parser;
       3: aload_0
       4: aload_1
       5: invokeinterface #65,  3           // InterfaceMethod org/apache/hbase/thirdparty/com/google/protobuf/Parser.parseFrom:(Lorg/apache/hbase/thirdparty/com/google/protobuf/ByteString;Lorg/apache/hbase/thirdparty/com/google/protobuf/ExtensionRegistryLite;)Ljava/lang/Object;
      10: checkcast     #36                 // class org/apache/hadoop/hbase/shaded/protobuf/generated/QuotaProtos$GetQuotaStatesResponse$TableQuotaSnapshot
      13: areturn

  public static org.apache.hadoop.hbase.shaded.protobuf.generated.QuotaProtos$GetQuotaStatesResponse$TableQuotaSnapshot parseFrom(byte[]) throws org.apache.hbase.thirdparty.com.google.protobuf.InvalidProtocolBufferException;
    Code:
       0: getstatic     #61                 // Field PARSER:Lorg/apache/hbase/thirdparty/com/google/protobuf/Parser;
       3: aload_0
       4: invokeinterface #66,  2           // InterfaceMethod org/apache/hbase/thirdparty/com/google/protobuf/Parser.parseFrom:([B)Ljava/lang/Object;
       9: checkcast     #36                 // class org/apache/hadoop/hbase/shaded/protobuf/generated/QuotaProtos$GetQuotaStatesResponse$TableQuotaSnapshot
      12: areturn

  public static org.apache.hadoop.hbase.shaded.protobuf.generated.QuotaProtos$GetQuotaStatesResponse$TableQuotaSnapshot parseFrom(byte[], org.apache.hbase.thirdparty.com.google.protobuf.ExtensionRegistryLite) throws org.apache.hbase.thirdparty.com.google.protobuf.InvalidProtocolBufferException;
    Code:
       0: getstatic     #61                 // Field PARSER:Lorg/apache/hbase/thirdparty/com/google/protobuf/Parser;
       3: aload_0
       4: aload_1
       5: invokeinterface #67,  3           // InterfaceMethod org/apache/hbase/thirdparty/com/google/protobuf/Parser.parseFrom:([BLorg/apache/hbase/thirdparty/com/google/protobuf/ExtensionRegistryLite;)Ljava/lang/Object;
      10: checkcast     #36                 // class org/apache/hadoop/hbase/shaded/protobuf/generated/QuotaProtos$GetQuotaStatesResponse$TableQuotaSnapshot
      13: areturn

  public static org.apache.hadoop.hbase.shaded.protobuf.generated.QuotaProtos$GetQuotaStatesResponse$TableQuotaSnapshot parseFrom(java.io.InputStream) throws java.io.IOException;
    Code:
       0: getstatic     #61                 // Field PARSER:Lorg/apache/hbase/thirdparty/com/google/protobuf/Parser;
       3: aload_0
       4: invokestatic  #68                 // Method org/apache/hbase/thirdparty/com/google/protobuf/GeneratedMessageV3.parseWithIOException:(Lorg/apache/hbase/thirdparty/com/google/protobuf/Parser;Ljava/io/InputStream;)Lorg/apache/hbase/thirdparty/com/google/protobuf/Message;
       7: checkcast     #36                 // class org/apache/hadoop/hbase/shaded/protobuf/generated/QuotaProtos$GetQuotaStatesResponse$TableQuotaSnapshot
      10: areturn

  public static org.apache.hadoop.hbase.shaded.protobuf.generated.QuotaProtos$GetQuotaStatesResponse$TableQuotaSnapshot parseFrom(java.io.InputStream, org.apache.hbase.thirdparty.com.google.protobuf.ExtensionRegistryLite) throws java.io.IOException;
    Code:
       0: getstatic     #61                 // Field PARSER:Lorg/apache/hbase/thirdparty/com/google/protobuf/Parser;
       3: aload_0
       4: aload_1
       5: invokestatic  #69                 // Method org/apache/hbase/thirdparty/com/google/protobuf/GeneratedMessageV3.parseWithIOException:(Lorg/apache/hbase/thirdparty/com/google/protobuf/Parser;Ljava/io/InputStream;Lorg/apache/hbase/thirdparty/com/google/protobuf/ExtensionRegistryLite;)Lorg/apache/hbase/thirdparty/com/google/protobuf/Message;
       8: checkcast     #36                 // class org/apache/hadoop/hbase/shaded/protobuf/generated/QuotaProtos$GetQuotaStatesResponse$TableQuotaSnapshot
      11: areturn

  public static org.apache.hadoop.hbase.shaded.protobuf.generated.QuotaProtos$GetQuotaStatesResponse$TableQuotaSnapshot parseDelimitedFrom(java.io.InputStream) throws java.io.IOException;
    Code:
       0: getstatic     #61                 // Field PARSER:Lorg/apache/hbase/thirdparty/com/google/protobuf/Parser;
       3: aload_0
       4: invokestatic  #70                 // Method org/apache/hbase/thirdparty/com/google/protobuf/GeneratedMessageV3.parseDelimitedWithIOException:(Lorg/apache/hbase/thirdparty/com/google/protobuf/Parser;Ljava/io/InputStream;)Lorg/apache/hbase/thirdparty/com/google/protobuf/Message;
       7: checkcast     #36                 // class org/apache/hadoop/hbase/shaded/protobuf/generated/QuotaProtos$GetQuotaStatesResponse$TableQuotaSnapshot
      10: areturn

  public static org.apache.hadoop.hbase.shaded.protobuf.generated.QuotaProtos$GetQuotaStatesResponse$TableQuotaSnapshot parseDelimitedFrom(java.io.InputStream, org.apache.hbase.thirdparty.com.google.protobuf.ExtensionRegistryLite) throws java.io.IOException;
    Code:
       0: getstatic     #61                 // Field PARSER:Lorg/apache/hbase/thirdparty/com/google/protobuf/Parser;
       3: aload_0
       4: aload_1
       5: invokestatic  #71                 // Method org/apache/hbase/thirdparty/com/google/protobuf/GeneratedMessageV3.parseDelimitedWithIOException:(Lorg/apache/hbase/thirdparty/com/google/protobuf/Parser;Ljava/io/InputStream;Lorg/apache/hbase/thirdparty/com/google/protobuf/ExtensionRegistryLite;)Lorg/apache/hbase/thirdparty/com/google/protobuf/Message;
       8: checkcast     #36                 // class org/apache/hadoop/hbase/shaded/protobuf/generated/QuotaProtos$GetQuotaStatesResponse$TableQuotaSnapshot
      11: areturn

  public static org.apache.hadoop.hbase.shaded.protobuf.generated.QuotaProtos$GetQuotaStatesResponse$TableQuotaSnapshot parseFrom(org.apache.hbase.thirdparty.com.google.protobuf.CodedInputStream) throws java.io.IOException;
    Code:
       0: getstatic     #61                 // Field PARSER:Lorg/apache/hbase/thirdparty/com/google/protobuf/Parser;
       3: aload_0
       4: invokestatic  #72                 // Method org/apache/hbase/thirdparty/com/google/protobuf/GeneratedMessageV3.parseWithIOException:(Lorg/apache/hbase/thirdparty/com/google/protobuf/Parser;Lorg/apache/hbase/thirdparty/com/google/protobuf/CodedInputStream;)Lorg/apache/hbase/thirdparty/com/google/protobuf/Message;
       7: checkcast     #36                 // class org/apache/hadoop/hbase/shaded/protobuf/generated/QuotaProtos$GetQuotaStatesResponse$TableQuotaSnapshot
      10: areturn

  public static org.apache.hadoop.hbase.shaded.protobuf.generated.QuotaProtos$GetQuotaStatesResponse$TableQuotaSnapshot parseFrom(org.apache.hbase.thirdparty.com.google.protobuf.CodedInputStream, org.apache.hbase.thirdparty.com.google.protobuf.ExtensionRegistryLite) throws java.io.IOException;
    Code:
       0: getstatic     #61                 // Field PARSER:Lorg/apache/hbase/thirdparty/com/google/protobuf/Parser;
       3: aload_0
       4: aload_1
       5: invokestatic  #73                 // Method org/apache/hbase/thirdparty/com/google/protobuf/GeneratedMessageV3.parseWithIOException:(Lorg/apache/hbase/thirdparty/com/google/protobuf/Parser;Lorg/apache/hbase/thirdparty/com/google/protobuf/CodedInputStream;Lorg/apache/hbase/thirdparty/com/google/protobuf/ExtensionRegistryLite;)Lorg/apache/hbase/thirdparty/com/google/protobuf/Message;
       8: checkcast     #36                 // class org/apache/hadoop/hbase/shaded/protobuf/generated/QuotaProtos$GetQuotaStatesResponse$TableQuotaSnapshot
      11: areturn

  public org.apache.hadoop.hbase.shaded.protobuf.generated.QuotaProtos$GetQuotaStatesResponse$TableQuotaSnapshot$Builder newBuilderForType();
    Code:
       0: invokestatic  #74                 // Method newBuilder:()Lorg/apache/hadoop/hbase/shaded/protobuf/generated/QuotaProtos$GetQuotaStatesResponse$TableQuotaSnapshot$Builder;
       3: areturn

  public static org.apache.hadoop.hbase.shaded.protobuf.generated.QuotaProtos$GetQuotaStatesResponse$TableQuotaSnapshot$Builder newBuilder();
    Code:
       0: getstatic     #75                 // Field DEFAULT_INSTANCE:Lorg/apache/hadoop/hbase/shaded/protobuf/generated/QuotaProtos$GetQuotaStatesResponse$TableQuotaSnapshot;
       3: invokevirtual #76                 // Method toBuilder:()Lorg/apache/hadoop/hbase/shaded/protobuf/generated/QuotaProtos$GetQuotaStatesResponse$TableQuotaSnapshot$Builder;
       6: areturn

  public static org.apache.hadoop.hbase.shaded.protobuf.generated.QuotaProtos$GetQuotaStatesResponse$TableQuotaSnapshot$Builder newBuilder(org.apache.hadoop.hbase.shaded.protobuf.generated.QuotaProtos$GetQuotaStatesResponse$TableQuotaSnapshot);
    Code:
       0: getstatic     #75                 // Field DEFAULT_INSTANCE:Lorg/apache/hadoop/hbase/shaded/protobuf/generated/QuotaProtos$GetQuotaStatesResponse$TableQuotaSnapshot;
       3: invokevirtual #76                 // Method toBuilder:()Lorg/apache/hadoop/hbase/shaded/protobuf/generated/QuotaProtos$GetQuotaStatesResponse$TableQuotaSnapshot$Builder;
       6: aload_0
       7: invokevirtual #77                 // Method org/apache/hadoop/hbase/shaded/protobuf/generated/QuotaProtos$GetQuotaStatesResponse$TableQuotaSnapshot$Builder.mergeFrom:(Lorg/apache/hadoop/hbase/shaded/protobuf/generated/QuotaProtos$GetQuotaStatesResponse$TableQuotaSnapshot;)Lorg/apache/hadoop/hbase/shaded/protobuf/generated/QuotaProtos$GetQuotaStatesResponse$TableQuotaSnapshot$Builder;
      10: areturn

  public org.apache.hadoop.hbase.shaded.protobuf.generated.QuotaProtos$GetQuotaStatesResponse$TableQuotaSnapshot$Builder toBuilder();
    Code:
       0: aload_0
       1: getstatic     #75                 // Field DEFAULT_INSTANCE:Lorg/apache/hadoop/hbase/shaded/protobuf/generated/QuotaProtos$GetQuotaStatesResponse$TableQuotaSnapshot;
       4: if_acmpne     18
       7: new           #37                 // class org/apache/hadoop/hbase/shaded/protobuf/generated/QuotaProtos$GetQuotaStatesResponse$TableQuotaSnapshot$Builder
      10: dup
      11: aconst_null
      12: invokespecial #78                 // Method org/apache/hadoop/hbase/shaded/protobuf/generated/QuotaProtos$GetQuotaStatesResponse$TableQuotaSnapshot$Builder."<init>":(Lorg/apache/hadoop/hbase/shaded/protobuf/generated/QuotaProtos$1;)V
      15: goto          30
      18: new           #37                 // class org/apache/hadoop/hbase/shaded/protobuf/generated/QuotaProtos$GetQuotaStatesResponse$TableQuotaSnapshot$Builder
      21: dup
      22: aconst_null
      23: invokespecial #78                 // Method org/apache/hadoop/hbase/shaded/protobuf/generated/QuotaProtos$GetQuotaStatesResponse$TableQuotaSnapshot$Builder."<init>":(Lorg/apache/hadoop/hbase/shaded/protobuf/generated/QuotaProtos$1;)V
      26: aload_0
      27: invokevirtual #77                 // Method org/apache/hadoop/hbase/shaded/protobuf/generated/QuotaProtos$GetQuotaStatesResponse$TableQuotaSnapshot$Builder.mergeFrom:(Lorg/apache/hadoop/hbase/shaded/protobuf/generated/QuotaProtos$GetQuotaStatesResponse$TableQuotaSnapshot;)Lorg/apache/hadoop/hbase/shaded/protobuf/generated/QuotaProtos$GetQuotaStatesResponse$TableQuotaSnapshot$Builder;
      30: areturn

  protected org.apache.hadoop.hbase.shaded.protobuf.generated.QuotaProtos$GetQuotaStatesResponse$TableQuotaSnapshot$Builder newBuilderForType(org.apache.hbase.thirdparty.com.google.protobuf.GeneratedMessageV3$BuilderParent);
    Code:
       0: new           #37                 // class org/apache/hadoop/hbase/shaded/protobuf/generated/QuotaProtos$GetQuotaStatesResponse$TableQuotaSnapshot$Builder
       3: dup
       4: aload_1
       5: aconst_null
       6: invokespecial #79                 // Method org/apache/hadoop/hbase/shaded/protobuf/generated/QuotaProtos$GetQuotaStatesResponse$TableQuotaSnapshot$Builder."<init>":(Lorg/apache/hbase/thirdparty/com/google/protobuf/GeneratedMessageV3$BuilderParent;Lorg/apache/hadoop/hbase/shaded/protobuf/generated/QuotaProtos$1;)V
       9: astore_2
      10: aload_2
      11: areturn

  public static org.apache.hadoop.hbase.shaded.protobuf.generated.QuotaProtos$GetQuotaStatesResponse$TableQuotaSnapshot getDefaultInstance();
    Code:
       0: getstatic     #75                 // Field DEFAULT_INSTANCE:Lorg/apache/hadoop/hbase/shaded/protobuf/generated/QuotaProtos$GetQuotaStatesResponse$TableQuotaSnapshot;
       3: areturn

  public static org.apache.hbase.thirdparty.com.google.protobuf.Parser<org.apache.hadoop.hbase.shaded.protobuf.generated.QuotaProtos$GetQuotaStatesResponse$TableQuotaSnapshot> parser();
    Code:
       0: getstatic     #61                 // Field PARSER:Lorg/apache/hbase/thirdparty/com/google/protobuf/Parser;
       3: areturn

  public org.apache.hbase.thirdparty.com.google.protobuf.Parser<org.apache.hadoop.hbase.shaded.protobuf.generated.QuotaProtos$GetQuotaStatesResponse$TableQuotaSnapshot> getParserForType();
    Code:
       0: getstatic     #61                 // Field PARSER:Lorg/apache/hbase/thirdparty/com/google/protobuf/Parser;
       3: areturn

  public org.apache.hadoop.hbase.shaded.protobuf.generated.QuotaProtos$GetQuotaStatesResponse$TableQuotaSnapshot getDefaultInstanceForType();
    Code:
       0: getstatic     #75                 // Field DEFAULT_INSTANCE:Lorg/apache/hadoop/hbase/shaded/protobuf/generated/QuotaProtos$GetQuotaStatesResponse$TableQuotaSnapshot;
       3: areturn

  protected org.apache.hbase.thirdparty.com.google.protobuf.Message$Builder newBuilderForType(org.apache.hbase.thirdparty.com.google.protobuf.GeneratedMessageV3$BuilderParent);
    Code:
       0: aload_0
       1: aload_1
       2: invokevirtual #80                 // Method newBuilderForType:(Lorg/apache/hbase/thirdparty/com/google/protobuf/GeneratedMessageV3$BuilderParent;)Lorg/apache/hadoop/hbase/shaded/protobuf/generated/QuotaProtos$GetQuotaStatesResponse$TableQuotaSnapshot$Builder;
       5: areturn

  public org.apache.hbase.thirdparty.com.google.protobuf.Message$Builder toBuilder();
    Code:
       0: aload_0
       1: invokevirtual #76                 // Method toBuilder:()Lorg/apache/hadoop/hbase/shaded/protobuf/generated/QuotaProtos$GetQuotaStatesResponse$TableQuotaSnapshot$Builder;
       4: areturn

  public org.apache.hbase.thirdparty.com.google.protobuf.Message$Builder newBuilderForType();
    Code:
       0: aload_0
       1: invokevirtual #81                 // Method newBuilderForType:()Lorg/apache/hadoop/hbase/shaded/protobuf/generated/QuotaProtos$GetQuotaStatesResponse$TableQuotaSnapshot$Builder;
       4: areturn

  public org.apache.hbase.thirdparty.com.google.protobuf.MessageLite$Builder toBuilder();
    Code:
       0: aload_0
       1: invokevirtual #76                 // Method toBuilder:()Lorg/apache/hadoop/hbase/shaded/protobuf/generated/QuotaProtos$GetQuotaStatesResponse$TableQuotaSnapshot$Builder;
       4: areturn

  public org.apache.hbase.thirdparty.com.google.protobuf.MessageLite$Builder newBuilderForType();
    Code:
       0: aload_0
       1: invokevirtual #81                 // Method newBuilderForType:()Lorg/apache/hadoop/hbase/shaded/protobuf/generated/QuotaProtos$GetQuotaStatesResponse$TableQuotaSnapshot$Builder;
       4: areturn

  public org.apache.hbase.thirdparty.com.google.protobuf.MessageLite getDefaultInstanceForType();
    Code:
       0: aload_0
       1: invokevirtual #82                 // Method getDefaultInstanceForType:()Lorg/apache/hadoop/hbase/shaded/protobuf/generated/QuotaProtos$GetQuotaStatesResponse$TableQuotaSnapshot;
       4: areturn

  public org.apache.hbase.thirdparty.com.google.protobuf.Message getDefaultInstanceForType();
    Code:
       0: aload_0
       1: invokevirtual #82                 // Method getDefaultInstanceForType:()Lorg/apache/hadoop/hbase/shaded/protobuf/generated/QuotaProtos$GetQuotaStatesResponse$TableQuotaSnapshot;
       4: areturn

  static boolean access$17900();
    Code:
       0: getstatic     #7                  // Field alwaysUseFieldBuilders:Z
       3: ireturn

  org.apache.hadoop.hbase.shaded.protobuf.generated.QuotaProtos$GetQuotaStatesResponse$TableQuotaSnapshot(org.apache.hbase.thirdparty.com.google.protobuf.GeneratedMessageV3$Builder, org.apache.hadoop.hbase.shaded.protobuf.generated.QuotaProtos$1);
    Code:
       0: aload_0
       1: aload_1
       2: invokespecial #6                  // Method "<init>":(Lorg/apache/hbase/thirdparty/com/google/protobuf/GeneratedMessageV3$Builder;)V
       5: return

  static org.apache.hadoop.hbase.shaded.protobuf.generated.HBaseProtos$TableName access$18102(org.apache.hadoop.hbase.shaded.protobuf.generated.QuotaProtos$GetQuotaStatesResponse$TableQuotaSnapshot, org.apache.hadoop.hbase.shaded.protobuf.generated.HBaseProtos$TableName);
    Code:
       0: aload_0
       1: aload_1
       2: dup_x1
       3: putfield      #5                  // Field tableName_:Lorg/apache/hadoop/hbase/shaded/protobuf/generated/HBaseProtos$TableName;
       6: areturn

  static org.apache.hadoop.hbase.shaded.protobuf.generated.QuotaProtos$SpaceQuotaSnapshot access$18202(org.apache.hadoop.hbase.shaded.protobuf.generated.QuotaProtos$GetQuotaStatesResponse$TableQuotaSnapshot, org.apache.hadoop.hbase.shaded.protobuf.generated.QuotaProtos$SpaceQuotaSnapshot);
    Code:
       0: aload_0
       1: aload_1
       2: dup_x1
       3: putfield      #4                  // Field snapshot_:Lorg/apache/hadoop/hbase/shaded/protobuf/generated/QuotaProtos$SpaceQuotaSnapshot;
       6: areturn

  static int access$18302(org.apache.hadoop.hbase.shaded.protobuf.generated.QuotaProtos$GetQuotaStatesResponse$TableQuotaSnapshot, int);
    Code:
       0: aload_0
       1: iload_1
       2: dup_x1
       3: putfield      #3                  // Field bitField0_:I
       6: ireturn

  static org.apache.hbase.thirdparty.com.google.protobuf.UnknownFieldSet access$18400(org.apache.hadoop.hbase.shaded.protobuf.generated.QuotaProtos$GetQuotaStatesResponse$TableQuotaSnapshot);
    Code:
       0: aload_0
       1: getfield      #2                  // Field unknownFields:Lorg/apache/hbase/thirdparty/com/google/protobuf/UnknownFieldSet;
       4: areturn

  org.apache.hadoop.hbase.shaded.protobuf.generated.QuotaProtos$GetQuotaStatesResponse$TableQuotaSnapshot(org.apache.hbase.thirdparty.com.google.protobuf.CodedInputStream, org.apache.hbase.thirdparty.com.google.protobuf.ExtensionRegistryLite, org.apache.hadoop.hbase.shaded.protobuf.generated.QuotaProtos$1) throws org.apache.hbase.thirdparty.com.google.protobuf.InvalidProtocolBufferException;
    Code:
       0: aload_0
       1: aload_1
       2: aload_2
       3: invokespecial #1                  // Method "<init>":(Lorg/apache/hbase/thirdparty/com/google/protobuf/CodedInputStream;Lorg/apache/hbase/thirdparty/com/google/protobuf/ExtensionRegistryLite;)V
       6: return

  static {};
    Code:
       0: new           #36                 // class org/apache/hadoop/hbase/shaded/protobuf/generated/QuotaProtos$GetQuotaStatesResponse$TableQuotaSnapshot
       3: dup
       4: invokespecial #11                 // Method "<init>":()V
       7: putstatic     #75                 // Field DEFAULT_INSTANCE:Lorg/apache/hadoop/hbase/shaded/protobuf/generated/QuotaProtos$GetQuotaStatesResponse$TableQuotaSnapshot;
      10: new           #83                 // class org/apache/hadoop/hbase/shaded/protobuf/generated/QuotaProtos$GetQuotaStatesResponse$TableQuotaSnapshot$1
      13: dup
      14: invokespecial #84                 // Method org/apache/hadoop/hbase/shaded/protobuf/generated/QuotaProtos$GetQuotaStatesResponse$TableQuotaSnapshot$1."<init>":()V
      17: putstatic     #61                 // Field PARSER:Lorg/apache/hbase/thirdparty/com/google/protobuf/Parser;
      20: return
}
