Compiled from "RandomStringGeneratorImpl.java"
public class org.apache.hadoop.hbase.RandomStringGeneratorImpl implements org.apache.hadoop.hbase.RandomStringGenerator {
  public org.apache.hadoop.hbase.RandomStringGeneratorImpl();
    Code:
       0: aload_0
       1: invokespecial #1                  // Method java/lang/Object."<init>":()V
       4: aload_0
       5: new           #2                  // class java/util/UUID
       8: dup
       9: invokestatic  #3                  // Method java/util/concurrent/ThreadLocalRandom.current:()Ljava/util/concurrent/ThreadLocalRandom;
      12: invokevirtual #4                  // Method java/util/concurrent/ThreadLocalRandom.nextLong:()J
      15: invokestatic  #3                  // Method java/util/concurrent/ThreadLocalRandom.current:()Ljava/util/concurrent/ThreadLocalRandom;
      18: invokevirtual #4                  // Method java/util/concurrent/ThreadLocalRandom.nextLong:()J
      21: invokespecial #5                  // Method java/util/UUID."<init>":(JJ)V
      24: invokevirtual #6                  // Method java/util/UUID.toString:()Ljava/lang/String;
      27: putfield      #7                  // Field s:Ljava/lang/String;
      30: return

  public java.lang.String getRandString();
    Code:
       0: aload_0
       1: getfield      #7                  // Field s:Ljava/lang/String;
       4: areturn
}
