Compiled from "RatioBasedCompactionPolicy.java"
public class org.apache.hadoop.hbase.regionserver.compactions.RatioBasedCompactionPolicy extends org.apache.hadoop.hbase.regionserver.compactions.SortedCompactionPolicy {
  public org.apache.hadoop.hbase.regionserver.compactions.RatioBasedCompactionPolicy(org.apache.hadoop.conf.Configuration, org.apache.hadoop.hbase.regionserver.StoreConfigInformation);
    Code:
       0: aload_0
       1: aload_1
       2: aload_2
       3: invokespecial #1                  // Method org/apache/hadoop/hbase/regionserver/compactions/SortedCompactionPolicy."<init>":(Lorg/apache/hadoop/conf/Configuration;Lorg/apache/hadoop/hbase/regionserver/StoreConfigInformation;)V
       6: return

  public boolean shouldPerformMajorCompaction(java.util.Collection<org.apache.hadoop.hbase.regionserver.HStoreFile>) throws java.io.IOException;
    Code:
       0: iconst_0
       1: istore_2
       2: aload_0
       3: aload_1
       4: invokevirtual #2                  // Method getNextMajorCompactTime:(Ljava/util/Collection;)J
       7: lstore_3
       8: aload_1
       9: ifnull        27
      12: aload_1
      13: invokeinterface #3,  1            // InterfaceMethod java/util/Collection.isEmpty:()Z
      18: ifne          27
      21: lload_3
      22: lconst_0
      23: lcmp
      24: ifne          29
      27: iload_2
      28: ireturn
      29: aload_1
      30: invokestatic  #4                  // Method org/apache/hadoop/hbase/regionserver/StoreUtils.getLowestTimestamp:(Ljava/util/Collection;)J
      33: lstore        5
      35: invokestatic  #5                  // Method org/apache/hadoop/hbase/util/EnvironmentEdgeManager.currentTime:()J
      38: lstore        7
      40: lload         5
      42: lconst_0
      43: lcmp
      44: ifle          499
      47: lload         5
      49: lload         7
      51: lload_3
      52: lsub
      53: lcmp
      54: ifge          499
      57: aload_0
      58: getfield      #6                  // Field storeConfigInfo:Lorg/apache/hadoop/hbase/regionserver/StoreConfigInformation;
      61: ifnull        94
      64: aload_0
      65: getfield      #6                  // Field storeConfigInfo:Lorg/apache/hadoop/hbase/regionserver/StoreConfigInformation;
      68: instanceof    #7                  // class org/apache/hadoop/hbase/regionserver/HStore
      71: ifeq          94
      74: aload_0
      75: getfield      #6                  // Field storeConfigInfo:Lorg/apache/hadoop/hbase/regionserver/StoreConfigInformation;
      78: checkcast     #7                  // class org/apache/hadoop/hbase/regionserver/HStore
      81: invokevirtual #8                  // Method org/apache/hadoop/hbase/regionserver/HStore.getRegionInfo:()Lorg/apache/hadoop/hbase/client/RegionInfo;
      84: invokeinterface #9,  1            // InterfaceMethod org/apache/hadoop/hbase/client/RegionInfo.getRegionNameAsString:()Ljava/lang/String;
      89: astore        9
      91: goto          100
      94: aload_0
      95: invokevirtual #10                 // Method java/lang/Object.toString:()Ljava/lang/String;
      98: astore        9
     100: ldc2_w        #12                 // long 2147483647l
     103: lstore        10
     105: aload_0
     106: getfield      #6                  // Field storeConfigInfo:Lorg/apache/hadoop/hbase/regionserver/StoreConfigInformation;
     109: ifnull        123
     112: aload_0
     113: getfield      #6                  // Field storeConfigInfo:Lorg/apache/hadoop/hbase/regionserver/StoreConfigInformation;
     116: invokeinterface #14,  1           // InterfaceMethod org/apache/hadoop/hbase/regionserver/StoreConfigInformation.getStoreFileTtl:()J
     121: lstore        10
     123: aload_1
     124: invokeinterface #15,  1           // InterfaceMethod java/util/Collection.size:()I
     129: iconst_1
     130: if_icmpne     451
     133: aload_1
     134: invokeinterface #16,  1           // InterfaceMethod java/util/Collection.iterator:()Ljava/util/Iterator;
     139: invokeinterface #17,  1           // InterfaceMethod java/util/Iterator.next:()Ljava/lang/Object;
     144: checkcast     #18                 // class org/apache/hadoop/hbase/regionserver/HStoreFile
     147: astore        12
     149: aload         12
     151: invokevirtual #19                 // Method org/apache/hadoop/hbase/regionserver/HStoreFile.getMinimumTimestamp:()Ljava/util/OptionalLong;
     154: astore        13
     156: aload         13
     158: invokevirtual #20                 // Method java/util/OptionalLong.isPresent:()Z
     161: ifeq          175
     164: lload         7
     166: aload         13
     168: invokevirtual #21                 // Method java/util/OptionalLong.getAsLong:()J
     171: lsub
     172: goto          178
     175: ldc2_w        #23                 // long -9223372036854775808l
     178: lstore        14
     180: aload         12
     182: invokevirtual #25                 // Method org/apache/hadoop/hbase/regionserver/HStoreFile.isMajorCompactionResult:()Z
     185: ifeq          383
     188: lload         10
     190: ldc2_w        #26                 // long 9223372036854775807l
     193: lcmp
     194: ifeq          205
     197: lload         14
     199: lload         10
     201: lcmp
     202: ifge          383
     205: aload         12
     207: invokevirtual #28                 // Method org/apache/hadoop/hbase/regionserver/HStoreFile.getHDFSBlockDistribution:()Lorg/apache/hadoop/hbase/HDFSBlocksDistribution;
     210: aload_0
     211: getfield      #29                 // Field comConf:Lorg/apache/hadoop/hbase/regionserver/compactions/CompactionConfiguration;
     214: getfield      #30                 // Field org/apache/hadoop/hbase/regionserver/compactions/CompactionConfiguration.conf:Lorg/apache/hadoop/conf/Configuration;
     217: iconst_0
     218: invokestatic  #31                 // Method org/apache/hadoop/hbase/regionserver/RSRpcServices.getHostname:(Lorg/apache/hadoop/conf/Configuration;Z)Ljava/lang/String;
     221: invokevirtual #32                 // Method org/apache/hadoop/hbase/HDFSBlocksDistribution.getBlockLocalityIndex:(Ljava/lang/String;)F
     224: fstore        16
     226: fload         16
     228: aload_0
     229: getfield      #29                 // Field comConf:Lorg/apache/hadoop/hbase/regionserver/compactions/CompactionConfiguration;
     232: invokevirtual #33                 // Method org/apache/hadoop/hbase/regionserver/compactions/CompactionConfiguration.getMinLocalityToForceCompact:()F
     235: fcmpg
     236: ifge          302
     239: getstatic     #34                 // Field LOG:Lorg/slf4j/Logger;
     242: new           #35                 // class java/lang/StringBuilder
     245: dup
     246: invokespecial #36                 // Method java/lang/StringBuilder."<init>":()V
     249: ldc           #37                 // String Major compaction triggered on only store
     251: invokevirtual #38                 // Method java/lang/StringBuilder.append:(Ljava/lang/String;)Ljava/lang/StringBuilder;
     254: aload         9
     256: invokevirtual #38                 // Method java/lang/StringBuilder.append:(Ljava/lang/String;)Ljava/lang/StringBuilder;
     259: ldc           #39                 // String ; to make hdfs blocks local, current blockLocalityIndex is
     261: invokevirtual #38                 // Method java/lang/StringBuilder.append:(Ljava/lang/String;)Ljava/lang/StringBuilder;
     264: fload         16
     266: invokevirtual #40                 // Method java/lang/StringBuilder.append:(F)Ljava/lang/StringBuilder;
     269: ldc           #41                 // String  (min
     271: invokevirtual #38                 // Method java/lang/StringBuilder.append:(Ljava/lang/String;)Ljava/lang/StringBuilder;
     274: aload_0
     275: getfield      #29                 // Field comConf:Lorg/apache/hadoop/hbase/regionserver/compactions/CompactionConfiguration;
     278: invokevirtual #33                 // Method org/apache/hadoop/hbase/regionserver/compactions/CompactionConfiguration.getMinLocalityToForceCompact:()F
     281: invokevirtual #40                 // Method java/lang/StringBuilder.append:(F)Ljava/lang/StringBuilder;
     284: ldc           #42                 // String )
     286: invokevirtual #38                 // Method java/lang/StringBuilder.append:(Ljava/lang/String;)Ljava/lang/StringBuilder;
     289: invokevirtual #43                 // Method java/lang/StringBuilder.toString:()Ljava/lang/String;
     292: invokeinterface #44,  2           // InterfaceMethod org/slf4j/Logger.debug:(Ljava/lang/String;)V
     297: iconst_1
     298: istore_2
     299: goto          380
     302: getstatic     #34                 // Field LOG:Lorg/slf4j/Logger;
     305: new           #35                 // class java/lang/StringBuilder
     308: dup
     309: invokespecial #36                 // Method java/lang/StringBuilder."<init>":()V
     312: ldc           #45                 // String Skipping major compaction of
     314: invokevirtual #38                 // Method java/lang/StringBuilder.append:(Ljava/lang/String;)Ljava/lang/StringBuilder;
     317: aload         9
     319: invokevirtual #38                 // Method java/lang/StringBuilder.append:(Ljava/lang/String;)Ljava/lang/StringBuilder;
     322: ldc           #46                 // String  because one (major) compacted file only, oldestTime
     324: invokevirtual #38                 // Method java/lang/StringBuilder.append:(Ljava/lang/String;)Ljava/lang/StringBuilder;
     327: lload         14
     329: invokevirtual #47                 // Method java/lang/StringBuilder.append:(J)Ljava/lang/StringBuilder;
     332: ldc           #48                 // String ms is < TTL=
     334: invokevirtual #38                 // Method java/lang/StringBuilder.append:(Ljava/lang/String;)Ljava/lang/StringBuilder;
     337: lload         10
     339: invokevirtual #47                 // Method java/lang/StringBuilder.append:(J)Ljava/lang/StringBuilder;
     342: ldc           #49                 // String  and blockLocalityIndex is
     344: invokevirtual #38                 // Method java/lang/StringBuilder.append:(Ljava/lang/String;)Ljava/lang/StringBuilder;
     347: fload         16
     349: invokevirtual #40                 // Method java/lang/StringBuilder.append:(F)Ljava/lang/StringBuilder;
     352: ldc           #41                 // String  (min
     354: invokevirtual #38                 // Method java/lang/StringBuilder.append:(Ljava/lang/String;)Ljava/lang/StringBuilder;
     357: aload_0
     358: getfield      #29                 // Field comConf:Lorg/apache/hadoop/hbase/regionserver/compactions/CompactionConfiguration;
     361: invokevirtual #33                 // Method org/apache/hadoop/hbase/regionserver/compactions/CompactionConfiguration.getMinLocalityToForceCompact:()F
     364: invokevirtual #40                 // Method java/lang/StringBuilder.append:(F)Ljava/lang/StringBuilder;
     367: ldc           #42                 // String )
     369: invokevirtual #38                 // Method java/lang/StringBuilder.append:(Ljava/lang/String;)Ljava/lang/StringBuilder;
     372: invokevirtual #43                 // Method java/lang/StringBuilder.toString:()Ljava/lang/String;
     375: invokeinterface #44,  2           // InterfaceMethod org/slf4j/Logger.debug:(Ljava/lang/String;)V
     380: goto          448
     383: lload         10
     385: ldc2_w        #12                 // long 2147483647l
     388: lcmp
     389: ifeq          448
     392: lload         14
     394: lload         10
     396: lcmp
     397: ifle          448
     400: getstatic     #34                 // Field LOG:Lorg/slf4j/Logger;
     403: new           #35                 // class java/lang/StringBuilder
     406: dup
     407: invokespecial #36                 // Method java/lang/StringBuilder."<init>":()V
     410: ldc           #50                 // String Major compaction triggered on store
     412: invokevirtual #38                 // Method java/lang/StringBuilder.append:(Ljava/lang/String;)Ljava/lang/StringBuilder;
     415: aload         9
     417: invokevirtual #38                 // Method java/lang/StringBuilder.append:(Ljava/lang/String;)Ljava/lang/StringBuilder;
     420: ldc           #51                 // String , because keyvalues outdated; time since last major compaction
     422: invokevirtual #38                 // Method java/lang/StringBuilder.append:(Ljava/lang/String;)Ljava/lang/StringBuilder;
     425: lload         7
     427: lload         5
     429: lsub
     430: invokevirtual #47                 // Method java/lang/StringBuilder.append:(J)Ljava/lang/StringBuilder;
     433: ldc           #52                 // String ms
     435: invokevirtual #38                 // Method java/lang/StringBuilder.append:(Ljava/lang/String;)Ljava/lang/StringBuilder;
     438: invokevirtual #43                 // Method java/lang/StringBuilder.toString:()Ljava/lang/String;
     441: invokeinterface #44,  2           // InterfaceMethod org/slf4j/Logger.debug:(Ljava/lang/String;)V
     446: iconst_1
     447: istore_2
     448: goto          499
     451: getstatic     #34                 // Field LOG:Lorg/slf4j/Logger;
     454: new           #35                 // class java/lang/StringBuilder
     457: dup
     458: invokespecial #36                 // Method java/lang/StringBuilder."<init>":()V
     461: ldc           #50                 // String Major compaction triggered on store
     463: invokevirtual #38                 // Method java/lang/StringBuilder.append:(Ljava/lang/String;)Ljava/lang/StringBuilder;
     466: aload         9
     468: invokevirtual #38                 // Method java/lang/StringBuilder.append:(Ljava/lang/String;)Ljava/lang/StringBuilder;
     471: ldc           #53                 // String ; time since last major compaction
     473: invokevirtual #38                 // Method java/lang/StringBuilder.append:(Ljava/lang/String;)Ljava/lang/StringBuilder;
     476: lload         7
     478: lload         5
     480: lsub
     481: invokevirtual #47                 // Method java/lang/StringBuilder.append:(J)Ljava/lang/StringBuilder;
     484: ldc           #52                 // String ms
     486: invokevirtual #38                 // Method java/lang/StringBuilder.append:(Ljava/lang/String;)Ljava/lang/StringBuilder;
     489: invokevirtual #43                 // Method java/lang/StringBuilder.toString:()Ljava/lang/String;
     492: invokeinterface #44,  2           // InterfaceMethod org/slf4j/Logger.debug:(Ljava/lang/String;)V
     497: iconst_1
     498: istore_2
     499: iload_2
     500: ireturn

  protected org.apache.hadoop.hbase.regionserver.compactions.CompactionRequestImpl createCompactionRequest(java.util.ArrayList<org.apache.hadoop.hbase.regionserver.HStoreFile>, boolean, boolean, boolean) throws java.io.IOException;
    Code:
       0: iload_2
       1: ifne          31
       4: aload_0
       5: aload_1
       6: invokevirtual #54                 // Method filterBulk:(Ljava/util/ArrayList;)V
       9: aload_0
      10: aload_1
      11: iload_3
      12: iload         4
      14: invokevirtual #55                 // Method applyCompactionPolicy:(Ljava/util/ArrayList;ZZ)Ljava/util/ArrayList;
      17: astore_1
      18: aload_0
      19: aload_1
      20: aload_0
      21: getfield      #29                 // Field comConf:Lorg/apache/hadoop/hbase/regionserver/compactions/CompactionConfiguration;
      24: invokevirtual #56                 // Method org/apache/hadoop/hbase/regionserver/compactions/CompactionConfiguration.getMinFilesToCompact:()I
      27: invokevirtual #57                 // Method checkMinFilesCriteria:(Ljava/util/ArrayList;I)Ljava/util/ArrayList;
      30: astore_1
      31: new           #58                 // class org/apache/hadoop/hbase/regionserver/compactions/CompactionRequestImpl
      34: dup
      35: aload_1
      36: invokespecial #59                 // Method org/apache/hadoop/hbase/regionserver/compactions/CompactionRequestImpl."<init>":(Ljava/util/Collection;)V
      39: areturn

  protected java.util.ArrayList<org.apache.hadoop.hbase.regionserver.HStoreFile> applyCompactionPolicy(java.util.ArrayList<org.apache.hadoop.hbase.regionserver.HStoreFile>, boolean, boolean) throws java.io.IOException;
    Code:
       0: aload_1
       1: invokevirtual #60                 // Method java/util/ArrayList.isEmpty:()Z
       4: ifeq          9
       7: aload_1
       8: areturn
       9: iconst_0
      10: istore        4
      12: aload_0
      13: getfield      #29                 // Field comConf:Lorg/apache/hadoop/hbase/regionserver/compactions/CompactionConfiguration;
      16: invokevirtual #61                 // Method org/apache/hadoop/hbase/regionserver/compactions/CompactionConfiguration.getCompactionRatio:()D
      19: dstore        5
      21: iload_2
      22: ifeq          62
      25: aload_0
      26: getfield      #29                 // Field comConf:Lorg/apache/hadoop/hbase/regionserver/compactions/CompactionConfiguration;
      29: invokevirtual #62                 // Method org/apache/hadoop/hbase/regionserver/compactions/CompactionConfiguration.getCompactionRatioOffPeak:()D
      32: dstore        5
      34: getstatic     #34                 // Field LOG:Lorg/slf4j/Logger;
      37: new           #35                 // class java/lang/StringBuilder
      40: dup
      41: invokespecial #36                 // Method java/lang/StringBuilder."<init>":()V
      44: ldc           #63                 // String Running an off-peak compaction, selection ratio =
      46: invokevirtual #38                 // Method java/lang/StringBuilder.append:(Ljava/lang/String;)Ljava/lang/StringBuilder;
      49: dload         5
      51: invokevirtual #64                 // Method java/lang/StringBuilder.append:(D)Ljava/lang/StringBuilder;
      54: invokevirtual #43                 // Method java/lang/StringBuilder.toString:()Ljava/lang/String;
      57: invokeinterface #65,  2           // InterfaceMethod org/slf4j/Logger.info:(Ljava/lang/String;)V
      62: aload_1
      63: invokevirtual #66                 // Method java/util/ArrayList.size:()I
      66: istore        7
      68: iload         7
      70: newarray       long
      72: astore        8
      74: iload         7
      76: newarray       long
      78: astore        9
      80: iload         7
      82: iconst_1
      83: isub
      84: istore        10
      86: iload         10
      88: iflt          183
      91: aload_1
      92: iload         10
      94: invokevirtual #67                 // Method java/util/ArrayList.get:(I)Ljava/lang/Object;
      97: checkcast     #18                 // class org/apache/hadoop/hbase/regionserver/HStoreFile
     100: astore        11
     102: aload         8
     104: iload         10
     106: aload         11
     108: invokevirtual #68                 // Method org/apache/hadoop/hbase/regionserver/HStoreFile.getReader:()Lorg/apache/hadoop/hbase/regionserver/StoreFileReader;
     111: invokevirtual #69                 // Method org/apache/hadoop/hbase/regionserver/StoreFileReader.length:()J
     114: lastore
     115: iload         10
     117: aload_0
     118: getfield      #29                 // Field comConf:Lorg/apache/hadoop/hbase/regionserver/compactions/CompactionConfiguration;
     121: invokevirtual #70                 // Method org/apache/hadoop/hbase/regionserver/compactions/CompactionConfiguration.getMaxFilesToCompact:()I
     124: iadd
     125: iconst_1
     126: isub
     127: istore        12
     129: aload         9
     131: iload         10
     133: aload         8
     135: iload         10
     137: laload
     138: iload         10
     140: iconst_1
     141: iadd
     142: iload         7
     144: if_icmpge     157
     147: aload         9
     149: iload         10
     151: iconst_1
     152: iadd
     153: laload
     154: goto          158
     157: lconst_0
     158: ladd
     159: iload         12
     161: iload         7
     163: if_icmpge     174
     166: aload         8
     168: iload         12
     170: laload
     171: goto          175
     174: lconst_0
     175: lsub
     176: lastore
     177: iinc          10, -1
     180: goto          86
     183: iload         7
     185: iload         4
     187: isub
     188: aload_0
     189: getfield      #29                 // Field comConf:Lorg/apache/hadoop/hbase/regionserver/compactions/CompactionConfiguration;
     192: invokevirtual #56                 // Method org/apache/hadoop/hbase/regionserver/compactions/CompactionConfiguration.getMinFilesToCompact:()I
     195: if_icmplt     235
     198: aload         8
     200: iload         4
     202: laload
     203: aload_0
     204: getfield      #29                 // Field comConf:Lorg/apache/hadoop/hbase/regionserver/compactions/CompactionConfiguration;
     207: invokevirtual #71                 // Method org/apache/hadoop/hbase/regionserver/compactions/CompactionConfiguration.getMinCompactSize:()J
     210: aload         9
     212: iload         4
     214: iconst_1
     215: iadd
     216: laload
     217: l2d
     218: dload         5
     220: dmul
     221: d2l
     222: invokestatic  #72                 // Method java/lang/Math.max:(JJ)J
     225: lcmp
     226: ifle          235
     229: iinc          4, 1
     232: goto          183
     235: iload         4
     237: iload         7
     239: if_icmpge     291
     242: getstatic     #34                 // Field LOG:Lorg/slf4j/Logger;
     245: new           #35                 // class java/lang/StringBuilder
     248: dup
     249: invokespecial #36                 // Method java/lang/StringBuilder."<init>":()V
     252: ldc           #73                 // String Default compaction algorithm has selected
     254: invokevirtual #38                 // Method java/lang/StringBuilder.append:(Ljava/lang/String;)Ljava/lang/StringBuilder;
     257: iload         7
     259: iload         4
     261: isub
     262: invokevirtual #74                 // Method java/lang/StringBuilder.append:(I)Ljava/lang/StringBuilder;
     265: ldc           #75                 // String  files from
     267: invokevirtual #38                 // Method java/lang/StringBuilder.append:(Ljava/lang/String;)Ljava/lang/StringBuilder;
     270: iload         7
     272: invokevirtual #74                 // Method java/lang/StringBuilder.append:(I)Ljava/lang/StringBuilder;
     275: ldc           #76                 // String  candidates
     277: invokevirtual #38                 // Method java/lang/StringBuilder.append:(Ljava/lang/String;)Ljava/lang/StringBuilder;
     280: invokevirtual #43                 // Method java/lang/StringBuilder.toString:()Ljava/lang/String;
     283: invokeinterface #65,  2           // InterfaceMethod org/slf4j/Logger.info:(Ljava/lang/String;)V
     288: goto          318
     291: iload_3
     292: ifeq          318
     295: aload_1
     296: invokevirtual #66                 // Method java/util/ArrayList.size:()I
     299: aload_0
     300: getfield      #29                 // Field comConf:Lorg/apache/hadoop/hbase/regionserver/compactions/CompactionConfiguration;
     303: invokevirtual #56                 // Method org/apache/hadoop/hbase/regionserver/compactions/CompactionConfiguration.getMinFilesToCompact:()I
     306: isub
     307: istore        10
     309: iload         10
     311: iflt          318
     314: iload         10
     316: istore        4
     318: aload_1
     319: iconst_0
     320: iload         4
     322: invokevirtual #77                 // Method java/util/ArrayList.subList:(II)Ljava/util/List;
     325: invokeinterface #78,  1           // InterfaceMethod java/util/List.clear:()V
     330: aload_1
     331: areturn

  public boolean needsCompaction(java.util.Collection<org.apache.hadoop.hbase.regionserver.HStoreFile>, java.util.List<org.apache.hadoop.hbase.regionserver.HStoreFile>);
    Code:
       0: aload_1
       1: invokeinterface #15,  1           // InterfaceMethod java/util/Collection.size:()I
       6: aload_2
       7: invokeinterface #79,  1           // InterfaceMethod java/util/List.size:()I
      12: isub
      13: istore_3
      14: iload_3
      15: aload_0
      16: getfield      #29                 // Field comConf:Lorg/apache/hadoop/hbase/regionserver/compactions/CompactionConfiguration;
      19: invokevirtual #56                 // Method org/apache/hadoop/hbase/regionserver/compactions/CompactionConfiguration.getMinFilesToCompact:()I
      22: if_icmplt     29
      25: iconst_1
      26: goto          30
      29: iconst_0
      30: ireturn

  public void setMinThreshold(int);
    Code:
       0: aload_0
       1: getfield      #29                 // Field comConf:Lorg/apache/hadoop/hbase/regionserver/compactions/CompactionConfiguration;
       4: iload_1
       5: invokevirtual #80                 // Method org/apache/hadoop/hbase/regionserver/compactions/CompactionConfiguration.setMinFilesToCompact:(I)V
       8: return

  static {};
    Code:
       0: ldc           #81                 // class org/apache/hadoop/hbase/regionserver/compactions/RatioBasedCompactionPolicy
       2: invokestatic  #82                 // Method org/slf4j/LoggerFactory.getLogger:(Ljava/lang/Class;)Lorg/slf4j/Logger;
       5: putstatic     #34                 // Field LOG:Lorg/slf4j/Logger;
       8: return
}
