Compiled from "RawAsyncHBaseAdmin.java"
class org.apache.hadoop.hbase.client.RawAsyncHBaseAdmin$ReplicationProcedureBiConsumer extends org.apache.hadoop.hbase.client.RawAsyncHBaseAdmin$ProcedureBiConsumer {
  org.apache.hadoop.hbase.client.RawAsyncHBaseAdmin$ReplicationProcedureBiConsumer(java.lang.String, java.util.function.Supplier<java.lang.String>);
    Code:
       0: aload_0
       1: aconst_null
       2: invokespecial #1                  // Method org/apache/hadoop/hbase/client/RawAsyncHBaseAdmin$ProcedureBiConsumer."<init>":(Lorg/apache/hadoop/hbase/client/RawAsyncHBaseAdmin$1;)V
       5: aload_0
       6: aload_1
       7: putfield      #2                  // Field peerId:Ljava/lang/String;
      10: aload_0
      11: aload_2
      12: putfield      #3                  // Field getOperation:Ljava/util/function/Supplier;
      15: return

  java.lang.String getDescription();
    Code:
       0: new           #4                  // class java/lang/StringBuilder
       3: dup
       4: invokespecial #5                  // Method java/lang/StringBuilder."<init>":()V
       7: ldc           #6                  // String Operation:
       9: invokevirtual #7                  // Method java/lang/StringBuilder.append:(Ljava/lang/String;)Ljava/lang/StringBuilder;
      12: aload_0
      13: getfield      #3                  // Field getOperation:Ljava/util/function/Supplier;
      16: invokeinterface #8,  1            // InterfaceMethod java/util/function/Supplier.get:()Ljava/lang/Object;
      21: checkcast     #9                  // class java/lang/String
      24: invokevirtual #7                  // Method java/lang/StringBuilder.append:(Ljava/lang/String;)Ljava/lang/StringBuilder;
      27: ldc           #10                 // String , peerId:
      29: invokevirtual #7                  // Method java/lang/StringBuilder.append:(Ljava/lang/String;)Ljava/lang/StringBuilder;
      32: aload_0
      33: getfield      #2                  // Field peerId:Ljava/lang/String;
      36: invokevirtual #7                  // Method java/lang/StringBuilder.append:(Ljava/lang/String;)Ljava/lang/StringBuilder;
      39: invokevirtual #11                 // Method java/lang/StringBuilder.toString:()Ljava/lang/String;
      42: areturn

  void onFinished();
    Code:
       0: invokestatic  #12                 // Method org/apache/hadoop/hbase/client/RawAsyncHBaseAdmin.access$100:()Lorg/slf4j/Logger;
       3: new           #4                  // class java/lang/StringBuilder
       6: dup
       7: invokespecial #5                  // Method java/lang/StringBuilder."<init>":()V
      10: aload_0
      11: invokevirtual #13                 // Method getDescription:()Ljava/lang/String;
      14: invokevirtual #7                  // Method java/lang/StringBuilder.append:(Ljava/lang/String;)Ljava/lang/StringBuilder;
      17: ldc           #14                 // String  completed
      19: invokevirtual #7                  // Method java/lang/StringBuilder.append:(Ljava/lang/String;)Ljava/lang/StringBuilder;
      22: invokevirtual #11                 // Method java/lang/StringBuilder.toString:()Ljava/lang/String;
      25: invokeinterface #15,  2           // InterfaceMethod org/slf4j/Logger.info:(Ljava/lang/String;)V
      30: return

  void onError(java.lang.Throwable);
    Code:
       0: invokestatic  #12                 // Method org/apache/hadoop/hbase/client/RawAsyncHBaseAdmin.access$100:()Lorg/slf4j/Logger;
       3: new           #4                  // class java/lang/StringBuilder
       6: dup
       7: invokespecial #5                  // Method java/lang/StringBuilder."<init>":()V
      10: aload_0
      11: invokevirtual #13                 // Method getDescription:()Ljava/lang/String;
      14: invokevirtual #7                  // Method java/lang/StringBuilder.append:(Ljava/lang/String;)Ljava/lang/StringBuilder;
      17: ldc           #16                 // String  failed with
      19: invokevirtual #7                  // Method java/lang/StringBuilder.append:(Ljava/lang/String;)Ljava/lang/StringBuilder;
      22: aload_1
      23: invokevirtual #17                 // Method java/lang/Throwable.getMessage:()Ljava/lang/String;
      26: invokevirtual #7                  // Method java/lang/StringBuilder.append:(Ljava/lang/String;)Ljava/lang/StringBuilder;
      29: invokevirtual #11                 // Method java/lang/StringBuilder.toString:()Ljava/lang/String;
      32: invokeinterface #15,  2           // InterfaceMethod org/slf4j/Logger.info:(Ljava/lang/String;)V
      37: return
}
