Compiled from "RawDouble.java"
public class org.apache.hadoop.hbase.types.RawDouble implements org.apache.hadoop.hbase.types.DataType<java.lang.Double> {
  public org.apache.hadoop.hbase.types.RawDouble();
    Code:
       0: aload_0
       1: invokespecial #1                  // Method java/lang/Object."<init>":()V
       4: return

  public boolean isOrderPreserving();
    Code:
       0: iconst_0
       1: ireturn

  public org.apache.hadoop.hbase.util.Order getOrder();
    Code:
       0: aconst_null
       1: areturn

  public boolean isNullable();
    Code:
       0: iconst_0
       1: ireturn

  public boolean isSkippable();
    Code:
       0: iconst_1
       1: ireturn

  public int encodedLength(java.lang.Double);
    Code:
       0: bipush        8
       2: ireturn

  public java.lang.Class<java.lang.Double> encodedClass();
    Code:
       0: ldc           #3                  // class java/lang/Double
       2: areturn

  public int skip(org.apache.hadoop.hbase.util.PositionedByteRange);
    Code:
       0: aload_1
       1: aload_1
       2: invokeinterface #4,  1            // InterfaceMethod org/apache/hadoop/hbase/util/PositionedByteRange.getPosition:()I
       7: bipush        8
       9: iadd
      10: invokeinterface #5,  2            // InterfaceMethod org/apache/hadoop/hbase/util/PositionedByteRange.setPosition:(I)Lorg/apache/hadoop/hbase/util/PositionedByteRange;
      15: pop
      16: bipush        8
      18: ireturn

  public java.lang.Double decode(org.apache.hadoop.hbase.util.PositionedByteRange);
    Code:
       0: aload_1
       1: invokeinterface #6,  1            // InterfaceMethod org/apache/hadoop/hbase/util/PositionedByteRange.getBytes:()[B
       6: aload_1
       7: invokeinterface #7,  1            // InterfaceMethod org/apache/hadoop/hbase/util/PositionedByteRange.getOffset:()I
      12: aload_1
      13: invokeinterface #4,  1            // InterfaceMethod org/apache/hadoop/hbase/util/PositionedByteRange.getPosition:()I
      18: iadd
      19: invokestatic  #8                  // Method org/apache/hadoop/hbase/util/Bytes.toDouble:([BI)D
      22: dstore_2
      23: aload_0
      24: aload_1
      25: invokevirtual #9                  // Method skip:(Lorg/apache/hadoop/hbase/util/PositionedByteRange;)I
      28: pop
      29: dload_2
      30: invokestatic  #10                 // Method java/lang/Double.valueOf:(D)Ljava/lang/Double;
      33: areturn

  public int encode(org.apache.hadoop.hbase.util.PositionedByteRange, java.lang.Double);
    Code:
       0: aload_1
       1: invokeinterface #6,  1            // InterfaceMethod org/apache/hadoop/hbase/util/PositionedByteRange.getBytes:()[B
       6: aload_1
       7: invokeinterface #7,  1            // InterfaceMethod org/apache/hadoop/hbase/util/PositionedByteRange.getOffset:()I
      12: aload_1
      13: invokeinterface #4,  1            // InterfaceMethod org/apache/hadoop/hbase/util/PositionedByteRange.getPosition:()I
      18: iadd
      19: aload_2
      20: invokevirtual #11                 // Method java/lang/Double.doubleValue:()D
      23: invokestatic  #12                 // Method org/apache/hadoop/hbase/util/Bytes.putDouble:([BID)I
      26: pop
      27: aload_0
      28: aload_1
      29: invokevirtual #9                  // Method skip:(Lorg/apache/hadoop/hbase/util/PositionedByteRange;)I
      32: ireturn

  public double decodeDouble(byte[], int);
    Code:
       0: aload_1
       1: iload_2
       2: invokestatic  #8                  // Method org/apache/hadoop/hbase/util/Bytes.toDouble:([BI)D
       5: dstore_3
       6: dload_3
       7: dreturn

  public int encodeDouble(byte[], int, double);
    Code:
       0: aload_1
       1: iload_2
       2: dload_3
       3: invokestatic  #12                 // Method org/apache/hadoop/hbase/util/Bytes.putDouble:([BID)I
       6: ireturn

  public int encode(org.apache.hadoop.hbase.util.PositionedByteRange, java.lang.Object);
    Code:
       0: aload_0
       1: aload_1
       2: aload_2
       3: checkcast     #3                  // class java/lang/Double
       6: invokevirtual #13                 // Method encode:(Lorg/apache/hadoop/hbase/util/PositionedByteRange;Ljava/lang/Double;)I
       9: ireturn

  public java.lang.Object decode(org.apache.hadoop.hbase.util.PositionedByteRange);
    Code:
       0: aload_0
       1: aload_1
       2: invokevirtual #14                 // Method decode:(Lorg/apache/hadoop/hbase/util/PositionedByteRange;)Ljava/lang/Double;
       5: areturn

  public int encodedLength(java.lang.Object);
    Code:
       0: aload_0
       1: aload_1
       2: checkcast     #3                  // class java/lang/Double
       5: invokevirtual #15                 // Method encodedLength:(Ljava/lang/Double;)I
       8: ireturn
}
