Compiled from "ReadOnlyZKClient.java"
class org.apache.hadoop.hbase.zookeeper.ReadOnlyZKClient$4 extends org.apache.hadoop.hbase.zookeeper.ReadOnlyZKClient$ZKTask<java.util.List<java.lang.String>> {
  final org.apache.hadoop.hbase.zookeeper.ReadOnlyZKClient this$0;

  org.apache.hadoop.hbase.zookeeper.ReadOnlyZKClient$4(org.apache.hadoop.hbase.zookeeper.ReadOnlyZKClient, java.lang.String, java.util.concurrent.CompletableFuture, java.lang.String);
    Code:
       0: aload_0
       1: aload_1
       2: putfield      #1                  // Field this$0:Lorg/apache/hadoop/hbase/zookeeper/ReadOnlyZKClient;
       5: aload_0
       6: aload_1
       7: aload_2
       8: aload_3
       9: aload         4
      11: invokespecial #2                  // Method org/apache/hadoop/hbase/zookeeper/ReadOnlyZKClient$ZKTask."<init>":(Lorg/apache/hadoop/hbase/zookeeper/ReadOnlyZKClient;Ljava/lang/String;Ljava/util/concurrent/CompletableFuture;Ljava/lang/String;)V
      14: return

  protected void doExec(org.apache.zookeeper.ZooKeeper);
    Code:
       0: aload_1
       1: aload_0
       2: getfield      #3                  // Field path:Ljava/lang/String;
       5: iconst_0
       6: aload_0
       7: aload_1
       8: invokedynamic #4,  0              // InvokeDynamic #0:processResult:(Lorg/apache/hadoop/hbase/zookeeper/ReadOnlyZKClient$4;Lorg/apache/zookeeper/ZooKeeper;)Lorg/apache/zookeeper/AsyncCallback$ChildrenCallback;
      13: aconst_null
      14: invokevirtual #5                  // Method org/apache/zookeeper/ZooKeeper.getChildren:(Ljava/lang/String;ZLorg/apache/zookeeper/AsyncCallback$ChildrenCallback;Ljava/lang/Object;)V
      17: return
}
