Compiled from "RegionStates.java"
class org.apache.hadoop.hbase.master.assignment.RegionStates$RegionStateStampComparator implements java.util.Comparator<org.apache.hadoop.hbase.master.RegionState> {
  public int compare(org.apache.hadoop.hbase.master.RegionState, org.apache.hadoop.hbase.master.RegionState);
    Code:
       0: aload_1
       1: invokevirtual #3                  // Method org/apache/hadoop/hbase/master/RegionState.getStamp:()J
       4: aload_2
       5: invokevirtual #3                  // Method org/apache/hadoop/hbase/master/RegionState.getStamp:()J
       8: invokestatic  #4                  // Method java/lang/Long.compare:(JJ)I
      11: istore_3
      12: iload_3
      13: ifeq          20
      16: iload_3
      17: goto          36
      20: getstatic     #5                  // Field org/apache/hadoop/hbase/client/RegionInfo.COMPARATOR:Ljava/util/Comparator;
      23: aload_1
      24: invokevirtual #6                  // Method org/apache/hadoop/hbase/master/RegionState.getRegion:()Lorg/apache/hadoop/hbase/client/RegionInfo;
      27: aload_2
      28: invokevirtual #6                  // Method org/apache/hadoop/hbase/master/RegionState.getRegion:()Lorg/apache/hadoop/hbase/client/RegionInfo;
      31: invokeinterface #7,  3            // InterfaceMethod java/util/Comparator.compare:(Ljava/lang/Object;Ljava/lang/Object;)I
      36: ireturn

  public int compare(java.lang.Object, java.lang.Object);
    Code:
       0: aload_0
       1: aload_1
       2: checkcast     #8                  // class org/apache/hadoop/hbase/master/RegionState
       5: aload_2
       6: checkcast     #8                  // class org/apache/hadoop/hbase/master/RegionState
       9: invokevirtual #9                  // Method compare:(Lorg/apache/hadoop/hbase/master/RegionState;Lorg/apache/hadoop/hbase/master/RegionState;)I
      12: ireturn

  org.apache.hadoop.hbase.master.assignment.RegionStates$RegionStateStampComparator(org.apache.hadoop.hbase.master.assignment.RegionStates$1);
    Code:
       0: aload_0
       1: invokespecial #1                  // Method "<init>":()V
       4: return
}
