Compiled from "RegionServerStatusProtos.java"
public final class org.apache.hadoop.hbase.shaded.protobuf.generated.RegionServerStatusProtos$RegionStateTransition$TransitionCode extends java.lang.Enum<org.apache.hadoop.hbase.shaded.protobuf.generated.RegionServerStatusProtos$RegionStateTransition$TransitionCode> implements org.apache.hbase.thirdparty.com.google.protobuf.ProtocolMessageEnum {
  public static final org.apache.hadoop.hbase.shaded.protobuf.generated.RegionServerStatusProtos$RegionStateTransition$TransitionCode OPENED;

  public static final org.apache.hadoop.hbase.shaded.protobuf.generated.RegionServerStatusProtos$RegionStateTransition$TransitionCode FAILED_OPEN;

  public static final org.apache.hadoop.hbase.shaded.protobuf.generated.RegionServerStatusProtos$RegionStateTransition$TransitionCode CLOSED;

  public static final org.apache.hadoop.hbase.shaded.protobuf.generated.RegionServerStatusProtos$RegionStateTransition$TransitionCode READY_TO_SPLIT;

  public static final org.apache.hadoop.hbase.shaded.protobuf.generated.RegionServerStatusProtos$RegionStateTransition$TransitionCode READY_TO_MERGE;

  public static final org.apache.hadoop.hbase.shaded.protobuf.generated.RegionServerStatusProtos$RegionStateTransition$TransitionCode SPLIT;

  public static final org.apache.hadoop.hbase.shaded.protobuf.generated.RegionServerStatusProtos$RegionStateTransition$TransitionCode MERGED;

  public static final org.apache.hadoop.hbase.shaded.protobuf.generated.RegionServerStatusProtos$RegionStateTransition$TransitionCode SPLIT_REVERTED;

  public static final org.apache.hadoop.hbase.shaded.protobuf.generated.RegionServerStatusProtos$RegionStateTransition$TransitionCode MERGE_REVERTED;

  public static final int OPENED_VALUE;

  public static final int FAILED_OPEN_VALUE;

  public static final int CLOSED_VALUE;

  public static final int READY_TO_SPLIT_VALUE;

  public static final int READY_TO_MERGE_VALUE;

  public static final int SPLIT_VALUE;

  public static final int MERGED_VALUE;

  public static final int SPLIT_REVERTED_VALUE;

  public static final int MERGE_REVERTED_VALUE;

  public static org.apache.hadoop.hbase.shaded.protobuf.generated.RegionServerStatusProtos$RegionStateTransition$TransitionCode[] values();
    Code:
       0: getstatic     #1                  // Field $VALUES:[Lorg/apache/hadoop/hbase/shaded/protobuf/generated/RegionServerStatusProtos$RegionStateTransition$TransitionCode;
       3: invokevirtual #2                  // Method "[Lorg/apache/hadoop/hbase/shaded/protobuf/generated/RegionServerStatusProtos$RegionStateTransition$TransitionCode;".clone:()Ljava/lang/Object;
       6: checkcast     #3                  // class "[Lorg/apache/hadoop/hbase/shaded/protobuf/generated/RegionServerStatusProtos$RegionStateTransition$TransitionCode;"
       9: areturn

  public static org.apache.hadoop.hbase.shaded.protobuf.generated.RegionServerStatusProtos$RegionStateTransition$TransitionCode valueOf(java.lang.String);
    Code:
       0: ldc           #4                  // class org/apache/hadoop/hbase/shaded/protobuf/generated/RegionServerStatusProtos$RegionStateTransition$TransitionCode
       2: aload_0
       3: invokestatic  #5                  // Method java/lang/Enum.valueOf:(Ljava/lang/Class;Ljava/lang/String;)Ljava/lang/Enum;
       6: checkcast     #4                  // class org/apache/hadoop/hbase/shaded/protobuf/generated/RegionServerStatusProtos$RegionStateTransition$TransitionCode
       9: areturn

  public final int getNumber();
    Code:
       0: aload_0
       1: getfield      #6                  // Field value:I
       4: ireturn

  public static org.apache.hadoop.hbase.shaded.protobuf.generated.RegionServerStatusProtos$RegionStateTransition$TransitionCode valueOf(int);
    Code:
       0: iload_0
       1: invokestatic  #7                  // Method forNumber:(I)Lorg/apache/hadoop/hbase/shaded/protobuf/generated/RegionServerStatusProtos$RegionStateTransition$TransitionCode;
       4: areturn

  public static org.apache.hadoop.hbase.shaded.protobuf.generated.RegionServerStatusProtos$RegionStateTransition$TransitionCode forNumber(int);
    Code:
       0: iload_0
       1: tableswitch   { // 0 to 10
                     0: 60
                     1: 64
                     2: 68
                     3: 72
                     4: 76
                     5: 96
                     6: 96
                     7: 80
                     8: 84
                     9: 88
                    10: 92
               default: 96
          }
      60: getstatic     #8                  // Field OPENED:Lorg/apache/hadoop/hbase/shaded/protobuf/generated/RegionServerStatusProtos$RegionStateTransition$TransitionCode;
      63: areturn
      64: getstatic     #9                  // Field FAILED_OPEN:Lorg/apache/hadoop/hbase/shaded/protobuf/generated/RegionServerStatusProtos$RegionStateTransition$TransitionCode;
      67: areturn
      68: getstatic     #10                 // Field CLOSED:Lorg/apache/hadoop/hbase/shaded/protobuf/generated/RegionServerStatusProtos$RegionStateTransition$TransitionCode;
      71: areturn
      72: getstatic     #11                 // Field READY_TO_SPLIT:Lorg/apache/hadoop/hbase/shaded/protobuf/generated/RegionServerStatusProtos$RegionStateTransition$TransitionCode;
      75: areturn
      76: getstatic     #12                 // Field READY_TO_MERGE:Lorg/apache/hadoop/hbase/shaded/protobuf/generated/RegionServerStatusProtos$RegionStateTransition$TransitionCode;
      79: areturn
      80: getstatic     #13                 // Field SPLIT:Lorg/apache/hadoop/hbase/shaded/protobuf/generated/RegionServerStatusProtos$RegionStateTransition$TransitionCode;
      83: areturn
      84: getstatic     #14                 // Field MERGED:Lorg/apache/hadoop/hbase/shaded/protobuf/generated/RegionServerStatusProtos$RegionStateTransition$TransitionCode;
      87: areturn
      88: getstatic     #15                 // Field SPLIT_REVERTED:Lorg/apache/hadoop/hbase/shaded/protobuf/generated/RegionServerStatusProtos$RegionStateTransition$TransitionCode;
      91: areturn
      92: getstatic     #16                 // Field MERGE_REVERTED:Lorg/apache/hadoop/hbase/shaded/protobuf/generated/RegionServerStatusProtos$RegionStateTransition$TransitionCode;
      95: areturn
      96: aconst_null
      97: areturn

  public static org.apache.hbase.thirdparty.com.google.protobuf.Internal$EnumLiteMap<org.apache.hadoop.hbase.shaded.protobuf.generated.RegionServerStatusProtos$RegionStateTransition$TransitionCode> internalGetValueMap();
    Code:
       0: getstatic     #17                 // Field internalValueMap:Lorg/apache/hbase/thirdparty/com/google/protobuf/Internal$EnumLiteMap;
       3: areturn

  public final org.apache.hbase.thirdparty.com.google.protobuf.Descriptors$EnumValueDescriptor getValueDescriptor();
    Code:
       0: invokestatic  #18                 // Method getDescriptor:()Lorg/apache/hbase/thirdparty/com/google/protobuf/Descriptors$EnumDescriptor;
       3: invokevirtual #19                 // Method org/apache/hbase/thirdparty/com/google/protobuf/Descriptors$EnumDescriptor.getValues:()Ljava/util/List;
       6: aload_0
       7: invokevirtual #20                 // Method ordinal:()I
      10: invokeinterface #21,  2           // InterfaceMethod java/util/List.get:(I)Ljava/lang/Object;
      15: checkcast     #22                 // class org/apache/hbase/thirdparty/com/google/protobuf/Descriptors$EnumValueDescriptor
      18: areturn

  public final org.apache.hbase.thirdparty.com.google.protobuf.Descriptors$EnumDescriptor getDescriptorForType();
    Code:
       0: invokestatic  #18                 // Method getDescriptor:()Lorg/apache/hbase/thirdparty/com/google/protobuf/Descriptors$EnumDescriptor;
       3: areturn

  public static final org.apache.hbase.thirdparty.com.google.protobuf.Descriptors$EnumDescriptor getDescriptor();
    Code:
       0: invokestatic  #23                 // Method org/apache/hadoop/hbase/shaded/protobuf/generated/RegionServerStatusProtos$RegionStateTransition.getDescriptor:()Lorg/apache/hbase/thirdparty/com/google/protobuf/Descriptors$Descriptor;
       3: invokevirtual #24                 // Method org/apache/hbase/thirdparty/com/google/protobuf/Descriptors$Descriptor.getEnumTypes:()Ljava/util/List;
       6: iconst_0
       7: invokeinterface #21,  2           // InterfaceMethod java/util/List.get:(I)Ljava/lang/Object;
      12: checkcast     #25                 // class org/apache/hbase/thirdparty/com/google/protobuf/Descriptors$EnumDescriptor
      15: areturn

  public static org.apache.hadoop.hbase.shaded.protobuf.generated.RegionServerStatusProtos$RegionStateTransition$TransitionCode valueOf(org.apache.hbase.thirdparty.com.google.protobuf.Descriptors$EnumValueDescriptor);
    Code:
       0: aload_0
       1: invokevirtual #26                 // Method org/apache/hbase/thirdparty/com/google/protobuf/Descriptors$EnumValueDescriptor.getType:()Lorg/apache/hbase/thirdparty/com/google/protobuf/Descriptors$EnumDescriptor;
       4: invokestatic  #18                 // Method getDescriptor:()Lorg/apache/hbase/thirdparty/com/google/protobuf/Descriptors$EnumDescriptor;
       7: if_acmpeq     20
      10: new           #27                 // class java/lang/IllegalArgumentException
      13: dup
      14: ldc           #28                 // String EnumValueDescriptor is not for this type.
      16: invokespecial #29                 // Method java/lang/IllegalArgumentException."<init>":(Ljava/lang/String;)V
      19: athrow
      20: getstatic     #30                 // Field VALUES:[Lorg/apache/hadoop/hbase/shaded/protobuf/generated/RegionServerStatusProtos$RegionStateTransition$TransitionCode;
      23: aload_0
      24: invokevirtual #31                 // Method org/apache/hbase/thirdparty/com/google/protobuf/Descriptors$EnumValueDescriptor.getIndex:()I
      27: aaload
      28: areturn

  static {};
    Code:
       0: new           #4                  // class org/apache/hadoop/hbase/shaded/protobuf/generated/RegionServerStatusProtos$RegionStateTransition$TransitionCode
       3: dup
       4: ldc           #33                 // String OPENED
       6: iconst_0
       7: iconst_0
       8: invokespecial #34                 // Method "<init>":(Ljava/lang/String;II)V
      11: putstatic     #8                  // Field OPENED:Lorg/apache/hadoop/hbase/shaded/protobuf/generated/RegionServerStatusProtos$RegionStateTransition$TransitionCode;
      14: new           #4                  // class org/apache/hadoop/hbase/shaded/protobuf/generated/RegionServerStatusProtos$RegionStateTransition$TransitionCode
      17: dup
      18: ldc           #35                 // String FAILED_OPEN
      20: iconst_1
      21: iconst_1
      22: invokespecial #34                 // Method "<init>":(Ljava/lang/String;II)V
      25: putstatic     #9                  // Field FAILED_OPEN:Lorg/apache/hadoop/hbase/shaded/protobuf/generated/RegionServerStatusProtos$RegionStateTransition$TransitionCode;
      28: new           #4                  // class org/apache/hadoop/hbase/shaded/protobuf/generated/RegionServerStatusProtos$RegionStateTransition$TransitionCode
      31: dup
      32: ldc           #36                 // String CLOSED
      34: iconst_2
      35: iconst_2
      36: invokespecial #34                 // Method "<init>":(Ljava/lang/String;II)V
      39: putstatic     #10                 // Field CLOSED:Lorg/apache/hadoop/hbase/shaded/protobuf/generated/RegionServerStatusProtos$RegionStateTransition$TransitionCode;
      42: new           #4                  // class org/apache/hadoop/hbase/shaded/protobuf/generated/RegionServerStatusProtos$RegionStateTransition$TransitionCode
      45: dup
      46: ldc           #37                 // String READY_TO_SPLIT
      48: iconst_3
      49: iconst_3
      50: invokespecial #34                 // Method "<init>":(Ljava/lang/String;II)V
      53: putstatic     #11                 // Field READY_TO_SPLIT:Lorg/apache/hadoop/hbase/shaded/protobuf/generated/RegionServerStatusProtos$RegionStateTransition$TransitionCode;
      56: new           #4                  // class org/apache/hadoop/hbase/shaded/protobuf/generated/RegionServerStatusProtos$RegionStateTransition$TransitionCode
      59: dup
      60: ldc           #38                 // String READY_TO_MERGE
      62: iconst_4
      63: iconst_4
      64: invokespecial #34                 // Method "<init>":(Ljava/lang/String;II)V
      67: putstatic     #12                 // Field READY_TO_MERGE:Lorg/apache/hadoop/hbase/shaded/protobuf/generated/RegionServerStatusProtos$RegionStateTransition$TransitionCode;
      70: new           #4                  // class org/apache/hadoop/hbase/shaded/protobuf/generated/RegionServerStatusProtos$RegionStateTransition$TransitionCode
      73: dup
      74: ldc           #39                 // String SPLIT
      76: iconst_5
      77: bipush        7
      79: invokespecial #34                 // Method "<init>":(Ljava/lang/String;II)V
      82: putstatic     #13                 // Field SPLIT:Lorg/apache/hadoop/hbase/shaded/protobuf/generated/RegionServerStatusProtos$RegionStateTransition$TransitionCode;
      85: new           #4                  // class org/apache/hadoop/hbase/shaded/protobuf/generated/RegionServerStatusProtos$RegionStateTransition$TransitionCode
      88: dup
      89: ldc           #40                 // String MERGED
      91: bipush        6
      93: bipush        8
      95: invokespecial #34                 // Method "<init>":(Ljava/lang/String;II)V
      98: putstatic     #14                 // Field MERGED:Lorg/apache/hadoop/hbase/shaded/protobuf/generated/RegionServerStatusProtos$RegionStateTransition$TransitionCode;
     101: new           #4                  // class org/apache/hadoop/hbase/shaded/protobuf/generated/RegionServerStatusProtos$RegionStateTransition$TransitionCode
     104: dup
     105: ldc           #41                 // String SPLIT_REVERTED
     107: bipush        7
     109: bipush        9
     111: invokespecial #34                 // Method "<init>":(Ljava/lang/String;II)V
     114: putstatic     #15                 // Field SPLIT_REVERTED:Lorg/apache/hadoop/hbase/shaded/protobuf/generated/RegionServerStatusProtos$RegionStateTransition$TransitionCode;
     117: new           #4                  // class org/apache/hadoop/hbase/shaded/protobuf/generated/RegionServerStatusProtos$RegionStateTransition$TransitionCode
     120: dup
     121: ldc           #42                 // String MERGE_REVERTED
     123: bipush        8
     125: bipush        10
     127: invokespecial #34                 // Method "<init>":(Ljava/lang/String;II)V
     130: putstatic     #16                 // Field MERGE_REVERTED:Lorg/apache/hadoop/hbase/shaded/protobuf/generated/RegionServerStatusProtos$RegionStateTransition$TransitionCode;
     133: bipush        9
     135: anewarray     #4                  // class org/apache/hadoop/hbase/shaded/protobuf/generated/RegionServerStatusProtos$RegionStateTransition$TransitionCode
     138: dup
     139: iconst_0
     140: getstatic     #8                  // Field OPENED:Lorg/apache/hadoop/hbase/shaded/protobuf/generated/RegionServerStatusProtos$RegionStateTransition$TransitionCode;
     143: aastore
     144: dup
     145: iconst_1
     146: getstatic     #9                  // Field FAILED_OPEN:Lorg/apache/hadoop/hbase/shaded/protobuf/generated/RegionServerStatusProtos$RegionStateTransition$TransitionCode;
     149: aastore
     150: dup
     151: iconst_2
     152: getstatic     #10                 // Field CLOSED:Lorg/apache/hadoop/hbase/shaded/protobuf/generated/RegionServerStatusProtos$RegionStateTransition$TransitionCode;
     155: aastore
     156: dup
     157: iconst_3
     158: getstatic     #11                 // Field READY_TO_SPLIT:Lorg/apache/hadoop/hbase/shaded/protobuf/generated/RegionServerStatusProtos$RegionStateTransition$TransitionCode;
     161: aastore
     162: dup
     163: iconst_4
     164: getstatic     #12                 // Field READY_TO_MERGE:Lorg/apache/hadoop/hbase/shaded/protobuf/generated/RegionServerStatusProtos$RegionStateTransition$TransitionCode;
     167: aastore
     168: dup
     169: iconst_5
     170: getstatic     #13                 // Field SPLIT:Lorg/apache/hadoop/hbase/shaded/protobuf/generated/RegionServerStatusProtos$RegionStateTransition$TransitionCode;
     173: aastore
     174: dup
     175: bipush        6
     177: getstatic     #14                 // Field MERGED:Lorg/apache/hadoop/hbase/shaded/protobuf/generated/RegionServerStatusProtos$RegionStateTransition$TransitionCode;
     180: aastore
     181: dup
     182: bipush        7
     184: getstatic     #15                 // Field SPLIT_REVERTED:Lorg/apache/hadoop/hbase/shaded/protobuf/generated/RegionServerStatusProtos$RegionStateTransition$TransitionCode;
     187: aastore
     188: dup
     189: bipush        8
     191: getstatic     #16                 // Field MERGE_REVERTED:Lorg/apache/hadoop/hbase/shaded/protobuf/generated/RegionServerStatusProtos$RegionStateTransition$TransitionCode;
     194: aastore
     195: putstatic     #1                  // Field $VALUES:[Lorg/apache/hadoop/hbase/shaded/protobuf/generated/RegionServerStatusProtos$RegionStateTransition$TransitionCode;
     198: new           #43                 // class org/apache/hadoop/hbase/shaded/protobuf/generated/RegionServerStatusProtos$RegionStateTransition$TransitionCode$1
     201: dup
     202: invokespecial #44                 // Method org/apache/hadoop/hbase/shaded/protobuf/generated/RegionServerStatusProtos$RegionStateTransition$TransitionCode$1."<init>":()V
     205: putstatic     #17                 // Field internalValueMap:Lorg/apache/hbase/thirdparty/com/google/protobuf/Internal$EnumLiteMap;
     208: invokestatic  #45                 // Method values:()[Lorg/apache/hadoop/hbase/shaded/protobuf/generated/RegionServerStatusProtos$RegionStateTransition$TransitionCode;
     211: putstatic     #30                 // Field VALUES:[Lorg/apache/hadoop/hbase/shaded/protobuf/generated/RegionServerStatusProtos$RegionStateTransition$TransitionCode;
     214: return
}
