Compiled from "RegionCoprocessorHost.java"
class org.apache.hadoop.hbase.regionserver.RegionCoprocessorHost$26 extends org.apache.hadoop.hbase.regionserver.RegionCoprocessorHost$RegionObserverOperationWithoutResult {
  final org.apache.hadoop.hbase.client.Delete val$delete;

  final org.apache.hadoop.hbase.wal.WALEdit val$edit;

  final org.apache.hadoop.hbase.client.Durability val$durability;

  final org.apache.hadoop.hbase.regionserver.RegionCoprocessorHost this$0;

  org.apache.hadoop.hbase.regionserver.RegionCoprocessorHost$26(org.apache.hadoop.hbase.regionserver.RegionCoprocessorHost, boolean, org.apache.hadoop.hbase.client.Delete, org.apache.hadoop.hbase.wal.WALEdit, org.apache.hadoop.hbase.client.Durability);
    Code:
       0: aload_0
       1: aload_1
       2: putfield      #1                  // Field this$0:Lorg/apache/hadoop/hbase/regionserver/RegionCoprocessorHost;
       5: aload_0
       6: aload_3
       7: putfield      #2                  // Field val$delete:Lorg/apache/hadoop/hbase/client/Delete;
      10: aload_0
      11: aload         4
      13: putfield      #3                  // Field val$edit:Lorg/apache/hadoop/hbase/wal/WALEdit;
      16: aload_0
      17: aload         5
      19: putfield      #4                  // Field val$durability:Lorg/apache/hadoop/hbase/client/Durability;
      22: aload_0
      23: aload_1
      24: iload_2
      25: invokespecial #5                  // Method org/apache/hadoop/hbase/regionserver/RegionCoprocessorHost$RegionObserverOperationWithoutResult."<init>":(Lorg/apache/hadoop/hbase/regionserver/RegionCoprocessorHost;Z)V
      28: return

  public void call(org.apache.hadoop.hbase.coprocessor.RegionObserver) throws java.io.IOException;
    Code:
       0: aload_1
       1: aload_0
       2: aload_0
       3: getfield      #2                  // Field val$delete:Lorg/apache/hadoop/hbase/client/Delete;
       6: aload_0
       7: getfield      #3                  // Field val$edit:Lorg/apache/hadoop/hbase/wal/WALEdit;
      10: aload_0
      11: getfield      #4                  // Field val$durability:Lorg/apache/hadoop/hbase/client/Durability;
      14: invokeinterface #6,  5            // InterfaceMethod org/apache/hadoop/hbase/coprocessor/RegionObserver.preDelete:(Lorg/apache/hadoop/hbase/coprocessor/ObserverContext;Lorg/apache/hadoop/hbase/client/Delete;Lorg/apache/hadoop/hbase/wal/WALEdit;Lorg/apache/hadoop/hbase/client/Durability;)V
      19: return

  public void call(java.lang.Object) throws java.io.IOException;
    Code:
       0: aload_0
       1: aload_1
       2: checkcast     #7                  // class org/apache/hadoop/hbase/coprocessor/RegionObserver
       5: invokevirtual #8                  // Method call:(Lorg/apache/hadoop/hbase/coprocessor/RegionObserver;)V
       8: return
}
