Compiled from "RegionNormalizerFactory.java"
public final class org.apache.hadoop.hbase.master.normalizer.RegionNormalizerFactory {
  public static org.apache.hadoop.hbase.master.normalizer.RegionNormalizer getRegionNormalizer(org.apache.hadoop.conf.Configuration);
    Code:
       0: aload_0
       1: ldc           #3                  // String hbase.master.normalizer.class
       3: ldc           #4                  // class org/apache/hadoop/hbase/master/normalizer/SimpleRegionNormalizer
       5: ldc           #5                  // class org/apache/hadoop/hbase/master/normalizer/RegionNormalizer
       7: invokevirtual #6                  // Method org/apache/hadoop/conf/Configuration.getClass:(Ljava/lang/String;Ljava/lang/Class;Ljava/lang/Class;)Ljava/lang/Class;
      10: astore_1
      11: aload_1
      12: aload_0
      13: invokestatic  #7                  // Method org/apache/hadoop/util/ReflectionUtils.newInstance:(Ljava/lang/Class;Lorg/apache/hadoop/conf/Configuration;)Ljava/lang/Object;
      16: checkcast     #5                  // class org/apache/hadoop/hbase/master/normalizer/RegionNormalizer
      19: areturn
}
