Compiled from "RegionSplitPolicy.java"
public abstract class org.apache.hadoop.hbase.regionserver.RegionSplitPolicy extends org.apache.hadoop.conf.Configured {
  protected org.apache.hadoop.hbase.regionserver.HRegion region;

  public org.apache.hadoop.hbase.regionserver.RegionSplitPolicy();
    Code:
       0: aload_0
       1: invokespecial #1                  // Method org/apache/hadoop/conf/Configured."<init>":()V
       4: return

  protected void configureForRegion(org.apache.hadoop.hbase.regionserver.HRegion);
    Code:
       0: aload_0
       1: getfield      #2                  // Field region:Lorg/apache/hadoop/hbase/regionserver/HRegion;
       4: ifnonnull     11
       7: iconst_1
       8: goto          12
      11: iconst_0
      12: ldc           #3                  // String Policy already configured for region {}
      14: aload_0
      15: getfield      #2                  // Field region:Lorg/apache/hadoop/hbase/regionserver/HRegion;
      18: invokestatic  #4                  // Method org/apache/hbase/thirdparty/com/google/common/base/Preconditions.checkState:(ZLjava/lang/String;Ljava/lang/Object;)V
      21: aload_0
      22: aload_1
      23: putfield      #2                  // Field region:Lorg/apache/hadoop/hbase/regionserver/HRegion;
      26: return

  protected abstract boolean shouldSplit();

  protected byte[] getSplitPoint();
    Code:
       0: aload_0
       1: getfield      #2                  // Field region:Lorg/apache/hadoop/hbase/regionserver/HRegion;
       4: invokevirtual #5                  // Method org/apache/hadoop/hbase/regionserver/HRegion.getExplicitSplitPoint:()[B
       7: astore_1
       8: aload_1
       9: ifnull        14
      12: aload_1
      13: areturn
      14: aload_0
      15: getfield      #2                  // Field region:Lorg/apache/hadoop/hbase/regionserver/HRegion;
      18: invokevirtual #6                  // Method org/apache/hadoop/hbase/regionserver/HRegion.getStores:()Ljava/util/List;
      21: astore_2
      22: aconst_null
      23: astore_3
      24: lconst_0
      25: lstore        4
      27: aload_2
      28: invokeinterface #7,  1            // InterfaceMethod java/util/List.iterator:()Ljava/util/Iterator;
      33: astore        6
      35: aload         6
      37: invokeinterface #8,  1            // InterfaceMethod java/util/Iterator.hasNext:()Z
      42: ifeq          103
      45: aload         6
      47: invokeinterface #9,  1            // InterfaceMethod java/util/Iterator.next:()Ljava/lang/Object;
      52: checkcast     #10                 // class org/apache/hadoop/hbase/regionserver/HStore
      55: astore        7
      57: aload         7
      59: invokevirtual #11                 // Method org/apache/hadoop/hbase/regionserver/HStore.getSplitPoint:()Ljava/util/Optional;
      62: astore        8
      64: aload         7
      66: invokevirtual #12                 // Method org/apache/hadoop/hbase/regionserver/HStore.getSize:()J
      69: lstore        9
      71: aload         8
      73: invokevirtual #13                 // Method java/util/Optional.isPresent:()Z
      76: ifeq          100
      79: lload         4
      81: lload         9
      83: lcmp
      84: ifge          100
      87: aload         8
      89: invokevirtual #14                 // Method java/util/Optional.get:()Ljava/lang/Object;
      92: checkcast     #15                 // class "[B"
      95: astore_3
      96: lload         9
      98: lstore        4
     100: goto          35
     103: aload_3
     104: areturn

  public static org.apache.hadoop.hbase.regionserver.RegionSplitPolicy create(org.apache.hadoop.hbase.regionserver.HRegion, org.apache.hadoop.conf.Configuration) throws java.io.IOException;
    Code:
       0: aload_0
       1: ldc           #16                 // String Region should not be null.
       3: invokestatic  #17                 // Method org/apache/hbase/thirdparty/com/google/common/base/Preconditions.checkNotNull:(Ljava/lang/Object;Ljava/lang/Object;)Ljava/lang/Object;
       6: pop
       7: aload_0
       8: invokevirtual #18                 // Method org/apache/hadoop/hbase/regionserver/HRegion.getTableDescriptor:()Lorg/apache/hadoop/hbase/client/TableDescriptor;
      11: aload_1
      12: invokestatic  #19                 // Method getSplitPolicyClass:(Lorg/apache/hadoop/hbase/client/TableDescriptor;Lorg/apache/hadoop/conf/Configuration;)Ljava/lang/Class;
      15: astore_2
      16: aload_2
      17: aload_1
      18: invokestatic  #20                 // Method org/apache/hadoop/util/ReflectionUtils.newInstance:(Ljava/lang/Class;Lorg/apache/hadoop/conf/Configuration;)Ljava/lang/Object;
      21: checkcast     #21                 // class org/apache/hadoop/hbase/regionserver/RegionSplitPolicy
      24: astore_3
      25: aload_3
      26: aload_0
      27: invokevirtual #22                 // Method configureForRegion:(Lorg/apache/hadoop/hbase/regionserver/HRegion;)V
      30: aload_3
      31: areturn

  public static java.lang.Class<? extends org.apache.hadoop.hbase.regionserver.RegionSplitPolicy> getSplitPolicyClass(org.apache.hadoop.hbase.client.TableDescriptor, org.apache.hadoop.conf.Configuration) throws java.io.IOException;
    Code:
       0: aload_0
       1: invokeinterface #23,  1           // InterfaceMethod org/apache/hadoop/hbase/client/TableDescriptor.getRegionSplitPolicyClassName:()Ljava/lang/String;
       6: astore_2
       7: aload_2
       8: ifnonnull     24
      11: aload_1
      12: ldc           #25                 // String hbase.regionserver.region.split.policy
      14: getstatic     #26                 // Field DEFAULT_SPLIT_POLICY_CLASS:Ljava/lang/Class;
      17: invokevirtual #27                 // Method java/lang/Class.getName:()Ljava/lang/String;
      20: invokevirtual #28                 // Method org/apache/hadoop/conf/Configuration.get:(Ljava/lang/String;Ljava/lang/String;)Ljava/lang/String;
      23: astore_2
      24: aload_2
      25: invokestatic  #29                 // Method java/lang/Class.forName:(Ljava/lang/String;)Ljava/lang/Class;
      28: ldc           #21                 // class org/apache/hadoop/hbase/regionserver/RegionSplitPolicy
      30: invokevirtual #30                 // Method java/lang/Class.asSubclass:(Ljava/lang/Class;)Ljava/lang/Class;
      33: astore_3
      34: aload_3
      35: areturn
      36: astore_3
      37: new           #32                 // class java/io/IOException
      40: dup
      41: new           #33                 // class java/lang/StringBuilder
      44: dup
      45: invokespecial #34                 // Method java/lang/StringBuilder."<init>":()V
      48: ldc           #35                 // String Unable to load configured region split policy '
      50: invokevirtual #36                 // Method java/lang/StringBuilder.append:(Ljava/lang/String;)Ljava/lang/StringBuilder;
      53: aload_2
      54: invokevirtual #36                 // Method java/lang/StringBuilder.append:(Ljava/lang/String;)Ljava/lang/StringBuilder;
      57: ldc           #37                 // String ' for table '
      59: invokevirtual #36                 // Method java/lang/StringBuilder.append:(Ljava/lang/String;)Ljava/lang/StringBuilder;
      62: aload_0
      63: invokeinterface #38,  1           // InterfaceMethod org/apache/hadoop/hbase/client/TableDescriptor.getTableName:()Lorg/apache/hadoop/hbase/TableName;
      68: invokevirtual #39                 // Method java/lang/StringBuilder.append:(Ljava/lang/Object;)Ljava/lang/StringBuilder;
      71: ldc           #40                 // String '
      73: invokevirtual #36                 // Method java/lang/StringBuilder.append:(Ljava/lang/String;)Ljava/lang/StringBuilder;
      76: invokevirtual #41                 // Method java/lang/StringBuilder.toString:()Ljava/lang/String;
      79: aload_3
      80: invokespecial #42                 // Method java/io/IOException."<init>":(Ljava/lang/String;Ljava/lang/Throwable;)V
      83: athrow
    Exception table:
       from    to  target type
          24    35    36   Class java/lang/Exception

  protected boolean skipStoreFileRangeCheck(java.lang.String);
    Code:
       0: iconst_0
       1: ireturn

  static {};
    Code:
       0: ldc           #43                 // class org/apache/hadoop/hbase/regionserver/SteppingSplitPolicy
       2: putstatic     #26                 // Field DEFAULT_SPLIT_POLICY_CLASS:Ljava/lang/Class;
       5: return
}
