Compiled from "RegionMover.java"
class org.apache.hadoop.hbase.util.RegionMover$MoveWithAck implements java.util.concurrent.Callable<java.lang.Boolean> {
  final org.apache.hadoop.hbase.util.RegionMover this$0;

  public org.apache.hadoop.hbase.util.RegionMover$MoveWithAck(org.apache.hadoop.hbase.client.RegionInfo, org.apache.hadoop.hbase.ServerName, org.apache.hadoop.hbase.ServerName, java.util.List<org.apache.hadoop.hbase.client.RegionInfo>);
    Code:
       0: aload_0
       1: aload_1
       2: putfield      #2                  // Field this$0:Lorg/apache/hadoop/hbase/util/RegionMover;
       5: aload_0
       6: invokespecial #3                  // Method java/lang/Object."<init>":()V
       9: aload_0
      10: aload_2
      11: putfield      #4                  // Field region:Lorg/apache/hadoop/hbase/client/RegionInfo;
      14: aload_0
      15: aload         4
      17: putfield      #5                  // Field targetServer:Lorg/apache/hadoop/hbase/ServerName;
      20: aload_0
      21: aload         5
      23: putfield      #6                  // Field movedRegions:Ljava/util/List;
      26: aload_0
      27: aload_3
      28: putfield      #7                  // Field sourceServer:Lorg/apache/hadoop/hbase/ServerName;
      31: return

  public java.lang.Boolean call() throws java.io.IOException, java.lang.InterruptedException;
    Code:
       0: iconst_0
       1: istore_1
       2: iconst_0
       3: istore_2
       4: aload_0
       5: getfield      #2                  // Field this$0:Lorg/apache/hadoop/hbase/util/RegionMover;
       8: invokestatic  #8                  // Method org/apache/hadoop/hbase/util/RegionMover.access$800:(Lorg/apache/hadoop/hbase/util/RegionMover;)Lorg/apache/hadoop/hbase/client/Admin;
      11: invokeinterface #9,  1            // InterfaceMethod org/apache/hadoop/hbase/client/Admin.getConfiguration:()Lorg/apache/hadoop/conf/Configuration;
      16: ldc           #10                 // String hbase.move.retries.max
      18: iconst_5
      19: invokevirtual #11                 // Method org/apache/hadoop/conf/Configuration.getInt:(Ljava/lang/String;I)I
      22: istore_3
      23: aload_0
      24: getfield      #2                  // Field this$0:Lorg/apache/hadoop/hbase/util/RegionMover;
      27: invokestatic  #8                  // Method org/apache/hadoop/hbase/util/RegionMover.access$800:(Lorg/apache/hadoop/hbase/util/RegionMover;)Lorg/apache/hadoop/hbase/client/Admin;
      30: invokeinterface #9,  1            // InterfaceMethod org/apache/hadoop/hbase/client/Admin.getConfiguration:()Lorg/apache/hadoop/conf/Configuration;
      35: ldc           #12                 // String hbase.move.wait.max
      37: bipush        60
      39: invokevirtual #11                 // Method org/apache/hadoop/conf/Configuration.getInt:(Ljava/lang/String;I)I
      42: istore        4
      44: invokestatic  #13                 // Method org/apache/hadoop/hbase/util/EnvironmentEdgeManager.currentTime:()J
      47: lstore        5
      49: iconst_1
      50: istore        7
      52: aload_0
      53: getfield      #2                  // Field this$0:Lorg/apache/hadoop/hbase/util/RegionMover;
      56: aload_0
      57: getfield      #4                  // Field region:Lorg/apache/hadoop/hbase/client/RegionInfo;
      60: invokestatic  #14                 // Method org/apache/hadoop/hbase/util/RegionMover.access$900:(Lorg/apache/hadoop/hbase/util/RegionMover;Lorg/apache/hadoop/hbase/client/RegionInfo;)V
      63: getstatic     #15                 // Field org/apache/hadoop/hbase/util/RegionMover.LOG:Lorg/slf4j/Logger;
      66: new           #16                 // class java/lang/StringBuilder
      69: dup
      70: invokespecial #17                 // Method java/lang/StringBuilder."<init>":()V
      73: ldc           #18                 // String Moving region:
      75: invokevirtual #19                 // Method java/lang/StringBuilder.append:(Ljava/lang/String;)Ljava/lang/StringBuilder;
      78: aload_0
      79: getfield      #4                  // Field region:Lorg/apache/hadoop/hbase/client/RegionInfo;
      82: invokeinterface #20,  1           // InterfaceMethod org/apache/hadoop/hbase/client/RegionInfo.getEncodedName:()Ljava/lang/String;
      87: invokevirtual #19                 // Method java/lang/StringBuilder.append:(Ljava/lang/String;)Ljava/lang/StringBuilder;
      90: ldc           #21                 // String  from
      92: invokevirtual #19                 // Method java/lang/StringBuilder.append:(Ljava/lang/String;)Ljava/lang/StringBuilder;
      95: aload_0
      96: getfield      #7                  // Field sourceServer:Lorg/apache/hadoop/hbase/ServerName;
      99: invokevirtual #22                 // Method java/lang/StringBuilder.append:(Ljava/lang/Object;)Ljava/lang/StringBuilder;
     102: ldc           #23                 // String  to
     104: invokevirtual #19                 // Method java/lang/StringBuilder.append:(Ljava/lang/String;)Ljava/lang/StringBuilder;
     107: aload_0
     108: getfield      #5                  // Field targetServer:Lorg/apache/hadoop/hbase/ServerName;
     111: invokevirtual #22                 // Method java/lang/StringBuilder.append:(Ljava/lang/Object;)Ljava/lang/StringBuilder;
     114: invokevirtual #24                 // Method java/lang/StringBuilder.toString:()Ljava/lang/String;
     117: invokeinterface #25,  2           // InterfaceMethod org/slf4j/Logger.info:(Ljava/lang/String;)V
     122: iload_2
     123: iload_3
     124: if_icmpge     265
     127: iload         7
     129: ifeq          265
     132: iload_2
     133: ifle          178
     136: getstatic     #15                 // Field org/apache/hadoop/hbase/util/RegionMover.LOG:Lorg/slf4j/Logger;
     139: new           #16                 // class java/lang/StringBuilder
     142: dup
     143: invokespecial #17                 // Method java/lang/StringBuilder."<init>":()V
     146: ldc           #26                 // String Retry
     148: invokevirtual #19                 // Method java/lang/StringBuilder.append:(Ljava/lang/String;)Ljava/lang/StringBuilder;
     151: iload_2
     152: invokestatic  #27                 // Method java/lang/Integer.toString:(I)Ljava/lang/String;
     155: invokevirtual #19                 // Method java/lang/StringBuilder.append:(Ljava/lang/String;)Ljava/lang/StringBuilder;
     158: ldc           #28                 // String  of maximum
     160: invokevirtual #19                 // Method java/lang/StringBuilder.append:(Ljava/lang/String;)Ljava/lang/StringBuilder;
     163: iload_3
     164: invokestatic  #27                 // Method java/lang/Integer.toString:(I)Ljava/lang/String;
     167: invokevirtual #19                 // Method java/lang/StringBuilder.append:(Ljava/lang/String;)Ljava/lang/StringBuilder;
     170: invokevirtual #24                 // Method java/lang/StringBuilder.toString:()Ljava/lang/String;
     173: invokeinterface #25,  2           // InterfaceMethod org/slf4j/Logger.info:(Ljava/lang/String;)V
     178: iload_2
     179: iconst_1
     180: iadd
     181: istore_2
     182: aload_0
     183: getfield      #2                  // Field this$0:Lorg/apache/hadoop/hbase/util/RegionMover;
     186: invokestatic  #8                  // Method org/apache/hadoop/hbase/util/RegionMover.access$800:(Lorg/apache/hadoop/hbase/util/RegionMover;)Lorg/apache/hadoop/hbase/client/Admin;
     189: aload_0
     190: getfield      #4                  // Field region:Lorg/apache/hadoop/hbase/client/RegionInfo;
     193: invokeinterface #29,  1           // InterfaceMethod org/apache/hadoop/hbase/client/RegionInfo.getEncodedNameAsBytes:()[B
     198: aload_0
     199: getfield      #5                  // Field targetServer:Lorg/apache/hadoop/hbase/ServerName;
     202: invokeinterface #30,  3           // InterfaceMethod org/apache/hadoop/hbase/client/Admin.move:([BLorg/apache/hadoop/hbase/ServerName;)V
     207: lload         5
     209: iload         4
     211: sipush        1000
     214: imul
     215: i2l
     216: ladd
     217: lstore        8
     219: invokestatic  #13                 // Method org/apache/hadoop/hbase/util/EnvironmentEdgeManager.currentTime:()J
     222: lload         8
     224: lcmp
     225: ifge          262
     228: aload_0
     229: getfield      #2                  // Field this$0:Lorg/apache/hadoop/hbase/util/RegionMover;
     232: aload_0
     233: getfield      #4                  // Field region:Lorg/apache/hadoop/hbase/client/RegionInfo;
     236: aload_0
     237: getfield      #7                  // Field sourceServer:Lorg/apache/hadoop/hbase/ServerName;
     240: invokestatic  #31                 // Method org/apache/hadoop/hbase/util/RegionMover.access$1000:(Lorg/apache/hadoop/hbase/util/RegionMover;Lorg/apache/hadoop/hbase/client/RegionInfo;Lorg/apache/hadoop/hbase/ServerName;)Z
     243: istore        7
     245: iload         7
     247: ifne          253
     250: goto          262
     253: ldc2_w        #32                 // long 100l
     256: invokestatic  #34                 // Method java/lang/Thread.sleep:(J)V
     259: goto          219
     262: goto          122
     265: iload         7
     267: ifeq          332
     270: getstatic     #15                 // Field org/apache/hadoop/hbase/util/RegionMover.LOG:Lorg/slf4j/Logger;
     273: new           #16                 // class java/lang/StringBuilder
     276: dup
     277: invokespecial #17                 // Method java/lang/StringBuilder."<init>":()V
     280: ldc           #35                 // String Region:
     282: invokevirtual #19                 // Method java/lang/StringBuilder.append:(Ljava/lang/String;)Ljava/lang/StringBuilder;
     285: aload_0
     286: getfield      #4                  // Field region:Lorg/apache/hadoop/hbase/client/RegionInfo;
     289: invokeinterface #36,  1           // InterfaceMethod org/apache/hadoop/hbase/client/RegionInfo.getRegionNameAsString:()Ljava/lang/String;
     294: invokevirtual #19                 // Method java/lang/StringBuilder.append:(Ljava/lang/String;)Ljava/lang/StringBuilder;
     297: ldc           #37                 // String  stuck on
     299: invokevirtual #19                 // Method java/lang/StringBuilder.append:(Ljava/lang/String;)Ljava/lang/StringBuilder;
     302: aload_0
     303: getfield      #7                  // Field sourceServer:Lorg/apache/hadoop/hbase/ServerName;
     306: invokevirtual #22                 // Method java/lang/StringBuilder.append:(Ljava/lang/Object;)Ljava/lang/StringBuilder;
     309: ldc           #38                 // String ,newServer=
     311: invokevirtual #19                 // Method java/lang/StringBuilder.append:(Ljava/lang/String;)Ljava/lang/StringBuilder;
     314: aload_0
     315: getfield      #5                  // Field targetServer:Lorg/apache/hadoop/hbase/ServerName;
     318: invokevirtual #22                 // Method java/lang/StringBuilder.append:(Ljava/lang/Object;)Ljava/lang/StringBuilder;
     321: invokevirtual #24                 // Method java/lang/StringBuilder.toString:()Ljava/lang/String;
     324: invokeinterface #39,  2           // InterfaceMethod org/slf4j/Logger.error:(Ljava/lang/String;)V
     329: goto          427
     332: aload_0
     333: getfield      #2                  // Field this$0:Lorg/apache/hadoop/hbase/util/RegionMover;
     336: aload_0
     337: getfield      #4                  // Field region:Lorg/apache/hadoop/hbase/client/RegionInfo;
     340: invokestatic  #14                 // Method org/apache/hadoop/hbase/util/RegionMover.access$900:(Lorg/apache/hadoop/hbase/util/RegionMover;Lorg/apache/hadoop/hbase/client/RegionInfo;)V
     343: getstatic     #15                 // Field org/apache/hadoop/hbase/util/RegionMover.LOG:Lorg/slf4j/Logger;
     346: new           #16                 // class java/lang/StringBuilder
     349: dup
     350: invokespecial #17                 // Method java/lang/StringBuilder."<init>":()V
     353: ldc           #40                 // String Moved Region
     355: invokevirtual #19                 // Method java/lang/StringBuilder.append:(Ljava/lang/String;)Ljava/lang/StringBuilder;
     358: aload_0
     359: getfield      #4                  // Field region:Lorg/apache/hadoop/hbase/client/RegionInfo;
     362: invokeinterface #36,  1           // InterfaceMethod org/apache/hadoop/hbase/client/RegionInfo.getRegionNameAsString:()Ljava/lang/String;
     367: invokevirtual #19                 // Method java/lang/StringBuilder.append:(Ljava/lang/String;)Ljava/lang/StringBuilder;
     370: ldc           #41                 // String  cost:
     372: invokevirtual #19                 // Method java/lang/StringBuilder.append:(Ljava/lang/String;)Ljava/lang/StringBuilder;
     375: ldc           #42                 // String %.3f
     377: iconst_1
     378: anewarray     #43                 // class java/lang/Object
     381: dup
     382: iconst_0
     383: invokestatic  #13                 // Method org/apache/hadoop/hbase/util/EnvironmentEdgeManager.currentTime:()J
     386: lload         5
     388: lsub
     389: l2f
     390: ldc           #44                 // float 1000.0f
     392: fdiv
     393: invokestatic  #45                 // Method java/lang/Float.valueOf:(F)Ljava/lang/Float;
     396: aastore
     397: invokestatic  #46                 // Method java/lang/String.format:(Ljava/lang/String;[Ljava/lang/Object;)Ljava/lang/String;
     400: invokevirtual #19                 // Method java/lang/StringBuilder.append:(Ljava/lang/String;)Ljava/lang/StringBuilder;
     403: invokevirtual #24                 // Method java/lang/StringBuilder.toString:()Ljava/lang/String;
     406: invokeinterface #25,  2           // InterfaceMethod org/slf4j/Logger.info:(Ljava/lang/String;)V
     411: iconst_1
     412: istore_1
     413: aload_0
     414: getfield      #6                  // Field movedRegions:Ljava/util/List;
     417: aload_0
     418: getfield      #4                  // Field region:Lorg/apache/hadoop/hbase/client/RegionInfo;
     421: invokeinterface #47,  2           // InterfaceMethod java/util/List.add:(Ljava/lang/Object;)Z
     426: pop
     427: iload_1
     428: invokestatic  #48                 // Method java/lang/Boolean.valueOf:(Z)Ljava/lang/Boolean;
     431: areturn

  public java.lang.Object call() throws java.lang.Exception;
    Code:
       0: aload_0
       1: invokevirtual #49                 // Method call:()Ljava/lang/Boolean;
       4: areturn
}
