Compiled from "RegionServerCoprocessorRpcChannelImpl.java"
public class org.apache.hadoop.hbase.client.RegionServerCoprocessorRpcChannelImpl implements com.google.protobuf.RpcChannel {
  org.apache.hadoop.hbase.client.AsyncRpcRetryingCallerFactory$ServerRequestCallerBuilder<com.google.protobuf.Message> callerBuilder;

  org.apache.hadoop.hbase.client.RegionServerCoprocessorRpcChannelImpl(org.apache.hadoop.hbase.client.AsyncRpcRetryingCallerFactory$ServerRequestCallerBuilder<com.google.protobuf.Message>);
    Code:
       0: aload_0
       1: invokespecial #1                  // Method java/lang/Object."<init>":()V
       4: aload_0
       5: aload_1
       6: putfield      #2                  // Field callerBuilder:Lorg/apache/hadoop/hbase/client/AsyncRpcRetryingCallerFactory$ServerRequestCallerBuilder;
       9: return

  public void callMethod(com.google.protobuf.Descriptors$MethodDescriptor, com.google.protobuf.RpcController, com.google.protobuf.Message, com.google.protobuf.Message, com.google.protobuf.RpcCallback<com.google.protobuf.Message>);
    Code:
       0: aload_0
       1: getfield      #2                  // Field callerBuilder:Lorg/apache/hadoop/hbase/client/AsyncRpcRetryingCallerFactory$ServerRequestCallerBuilder;
       4: aload_0
       5: aload_1
       6: aload_3
       7: aload         4
       9: invokedynamic #9,  0              // InvokeDynamic #0:call:(Lorg/apache/hadoop/hbase/client/RegionServerCoprocessorRpcChannelImpl;Lcom/google/protobuf/Descriptors$MethodDescriptor;Lcom/google/protobuf/Message;Lcom/google/protobuf/Message;)Lorg/apache/hadoop/hbase/client/AsyncServerRequestRpcRetryingCaller$Callable;
      14: invokevirtual #10                 // Method org/apache/hadoop/hbase/client/AsyncRpcRetryingCallerFactory$ServerRequestCallerBuilder.action:(Lorg/apache/hadoop/hbase/client/AsyncServerRequestRpcRetryingCaller$Callable;)Lorg/apache/hadoop/hbase/client/AsyncRpcRetryingCallerFactory$ServerRequestCallerBuilder;
      17: invokevirtual #11                 // Method org/apache/hadoop/hbase/client/AsyncRpcRetryingCallerFactory$ServerRequestCallerBuilder.call:()Ljava/util/concurrent/CompletableFuture;
      20: aload_2
      21: aload         5
      23: invokedynamic #12,  0             // InvokeDynamic #1:accept:(Lcom/google/protobuf/RpcController;Lcom/google/protobuf/RpcCallback;)Ljava/util/function/BiConsumer;
      28: invokestatic  #13                 // Method org/apache/hadoop/hbase/util/FutureUtils.addListener:(Ljava/util/concurrent/CompletableFuture;Ljava/util/function/BiConsumer;)V
      31: return
}
