Compiled from "RegionCoprocessorRpcChannel.java"
class org.apache.hadoop.hbase.client.RegionCoprocessorRpcChannel$1 extends org.apache.hadoop.hbase.client.ClientServiceCallable<org.apache.hadoop.hbase.shaded.protobuf.generated.ClientProtos$CoprocessorServiceResponse> {
  final com.google.protobuf.Descriptors$MethodDescriptor val$method;

  final com.google.protobuf.Message val$request;

  final org.apache.hadoop.hbase.client.RegionCoprocessorRpcChannel this$0;

  org.apache.hadoop.hbase.client.RegionCoprocessorRpcChannel$1(org.apache.hadoop.hbase.client.RegionCoprocessorRpcChannel, org.apache.hadoop.hbase.client.Connection, org.apache.hadoop.hbase.TableName, byte[], org.apache.hbase.thirdparty.com.google.protobuf.RpcController, int, com.google.protobuf.Descriptors$MethodDescriptor, com.google.protobuf.Message);
    Code:
       0: aload_0
       1: aload_1
       2: putfield      #1                  // Field this$0:Lorg/apache/hadoop/hbase/client/RegionCoprocessorRpcChannel;
       5: aload_0
       6: aload         7
       8: putfield      #2                  // Field val$method:Lcom/google/protobuf/Descriptors$MethodDescriptor;
      11: aload_0
      12: aload         8
      14: putfield      #3                  // Field val$request:Lcom/google/protobuf/Message;
      17: aload_0
      18: aload_2
      19: aload_3
      20: aload         4
      22: aload         5
      24: iload         6
      26: invokespecial #4                  // Method org/apache/hadoop/hbase/client/ClientServiceCallable."<init>":(Lorg/apache/hadoop/hbase/client/Connection;Lorg/apache/hadoop/hbase/TableName;[BLorg/apache/hbase/thirdparty/com/google/protobuf/RpcController;I)V
      29: return

  protected org.apache.hadoop.hbase.shaded.protobuf.generated.ClientProtos$CoprocessorServiceResponse rpcCall() throws java.lang.Exception;
    Code:
       0: aload_0
       1: invokevirtual #5                  // Method getLocation:()Lorg/apache/hadoop/hbase/HRegionLocation;
       4: invokevirtual #6                  // Method org/apache/hadoop/hbase/HRegionLocation.getRegionInfo:()Lorg/apache/hadoop/hbase/HRegionInfo;
       7: invokevirtual #7                  // Method org/apache/hadoop/hbase/HRegionInfo.getRegionName:()[B
      10: astore_1
      11: aload_0
      12: getfield      #2                  // Field val$method:Lcom/google/protobuf/Descriptors$MethodDescriptor;
      15: aload_0
      16: getfield      #3                  // Field val$request:Lcom/google/protobuf/Message;
      19: aload_0
      20: getfield      #1                  // Field this$0:Lorg/apache/hadoop/hbase/client/RegionCoprocessorRpcChannel;
      23: invokestatic  #8                  // Method org/apache/hadoop/hbase/client/RegionCoprocessorRpcChannel.access$000:(Lorg/apache/hadoop/hbase/client/RegionCoprocessorRpcChannel;)[B
      26: aload_1
      27: invokestatic  #9                  // Method org/apache/hadoop/hbase/ipc/CoprocessorRpcUtils.getCoprocessorServiceRequest:(Lcom/google/protobuf/Descriptors$MethodDescriptor;Lcom/google/protobuf/Message;[B[B)Lorg/apache/hadoop/hbase/shaded/protobuf/generated/ClientProtos$CoprocessorServiceRequest;
      30: astore_2
      31: aload_0
      32: invokevirtual #10                 // Method getStub:()Ljava/lang/Object;
      35: checkcast     #11                 // class org/apache/hadoop/hbase/shaded/protobuf/generated/ClientProtos$ClientService$BlockingInterface
      38: aload_0
      39: invokevirtual #12                 // Method getRpcController:()Lorg/apache/hbase/thirdparty/com/google/protobuf/RpcController;
      42: aload_2
      43: invokeinterface #13,  3           // InterfaceMethod org/apache/hadoop/hbase/shaded/protobuf/generated/ClientProtos$ClientService$BlockingInterface.execService:(Lorg/apache/hbase/thirdparty/com/google/protobuf/RpcController;Lorg/apache/hadoop/hbase/shaded/protobuf/generated/ClientProtos$CoprocessorServiceRequest;)Lorg/apache/hadoop/hbase/shaded/protobuf/generated/ClientProtos$CoprocessorServiceResponse;
      48: areturn

  protected java.lang.Object rpcCall() throws java.lang.Exception;
    Code:
       0: aload_0
       1: invokevirtual #14                 // Method rpcCall:()Lorg/apache/hadoop/hbase/shaded/protobuf/generated/ClientProtos$CoprocessorServiceResponse;
       4: areturn
}
