Compiled from "RegionServerCoprocessorHost.java"
class org.apache.hadoop.hbase.regionserver.RegionServerCoprocessorHost$RegionServerEnvironmentForCoreCoprocessors extends org.apache.hadoop.hbase.regionserver.RegionServerCoprocessorHost$RegionServerEnvironment implements org.apache.hadoop.hbase.coprocessor.HasRegionServerServices {
  final org.apache.hadoop.hbase.regionserver.RegionServerServices regionServerServices;

  public org.apache.hadoop.hbase.regionserver.RegionServerCoprocessorHost$RegionServerEnvironmentForCoreCoprocessors(org.apache.hadoop.hbase.coprocessor.RegionServerCoprocessor, int, int, org.apache.hadoop.conf.Configuration, org.apache.hadoop.hbase.regionserver.RegionServerServices);
    Code:
       0: aload_0
       1: aload_1
       2: iload_2
       3: iload_3
       4: aload         4
       6: aload         5
       8: invokespecial #1                  // Method org/apache/hadoop/hbase/regionserver/RegionServerCoprocessorHost$RegionServerEnvironment."<init>":(Lorg/apache/hadoop/hbase/coprocessor/RegionServerCoprocessor;IILorg/apache/hadoop/conf/Configuration;Lorg/apache/hadoop/hbase/regionserver/RegionServerServices;)V
      11: aload_0
      12: aload         5
      14: putfield      #2                  // Field regionServerServices:Lorg/apache/hadoop/hbase/regionserver/RegionServerServices;
      17: return

  public org.apache.hadoop.hbase.regionserver.RegionServerServices getRegionServerServices();
    Code:
       0: aload_0
       1: getfield      #2                  // Field regionServerServices:Lorg/apache/hadoop/hbase/regionserver/RegionServerServices;
       4: areturn
}
