Compiled from "RegionMetrics.java"
public interface org.apache.hadoop.hbase.RegionMetrics {
  public abstract byte[] getRegionName();

  public abstract int getStoreCount();

  public abstract int getStoreFileCount();

  public abstract org.apache.hadoop.hbase.Size getStoreFileSize();

  public abstract org.apache.hadoop.hbase.Size getMemStoreSize();

  public abstract long getReadRequestCount();

  public abstract long getWriteRequestCount();

  public abstract long getCpRequestCount();

  public long getRequestCount();
    Code:
       0: aload_0
       1: invokeinterface #1,  1            // InterfaceMethod getReadRequestCount:()J
       6: aload_0
       7: invokeinterface #2,  1            // InterfaceMethod getWriteRequestCount:()J
      12: ladd
      13: aload_0
      14: invokeinterface #3,  1            // InterfaceMethod getCpRequestCount:()J
      19: ladd
      20: lreturn

  public java.lang.String getNameAsString();
    Code:
       0: aload_0
       1: invokeinterface #4,  1            // InterfaceMethod getRegionName:()[B
       6: invokestatic  #5                  // Method org/apache/hadoop/hbase/util/Bytes.toStringBinary:([B)Ljava/lang/String;
       9: areturn

  public abstract long getFilteredReadRequestCount();

  public abstract org.apache.hadoop.hbase.Size getStoreFileIndexSize();

  public abstract org.apache.hadoop.hbase.Size getStoreFileRootLevelIndexSize();

  public abstract org.apache.hadoop.hbase.Size getStoreFileUncompressedDataIndexSize();

  public abstract org.apache.hadoop.hbase.Size getBloomFilterSize();

  public abstract long getCompactingCellCount();

  public abstract long getCompactedCellCount();

  public abstract long getCompletedSequenceId();

  public abstract java.util.Map<byte[], java.lang.Long> getStoreSequenceId();

  public abstract org.apache.hadoop.hbase.Size getUncompressedStoreFileSize();

  public abstract float getDataLocality();

  public abstract long getLastMajorCompactionTimestamp();

  public abstract int getStoreRefCount();
}
