Compiled from "RegionInfoDisplay.java"
public class org.apache.hadoop.hbase.client.RegionInfoDisplay {
  public static final java.lang.String DISPLAY_KEYS_KEY;

  public static final byte[] HIDDEN_END_KEY;

  public static final byte[] HIDDEN_START_KEY;

  public org.apache.hadoop.hbase.client.RegionInfoDisplay();
    Code:
       0: aload_0
       1: invokespecial #1                  // Method java/lang/Object."<init>":()V
       4: return

  public static java.lang.String getDescriptiveNameFromRegionStateForDisplay(org.apache.hadoop.hbase.master.RegionState, org.apache.hadoop.conf.Configuration);
    Code:
       0: aload_1
       1: ldc           #3                  // String hbase.display.keys
       3: iconst_1
       4: invokevirtual #4                  // Method org/apache/hadoop/conf/Configuration.getBoolean:(Ljava/lang/String;Z)Z
       7: ifeq          15
      10: aload_0
      11: invokevirtual #5                  // Method org/apache/hadoop/hbase/master/RegionState.toDescriptiveString:()Ljava/lang/String;
      14: areturn
      15: aload_0
      16: invokevirtual #5                  // Method org/apache/hadoop/hbase/master/RegionState.toDescriptiveString:()Ljava/lang/String;
      19: astore_2
      20: aload_2
      21: ldc           #6                  // String  state=
      23: invokevirtual #7                  // Method java/lang/String.lastIndexOf:(Ljava/lang/String;)I
      26: istore_3
      27: aload_0
      28: invokevirtual #8                  // Method org/apache/hadoop/hbase/master/RegionState.getRegion:()Lorg/apache/hadoop/hbase/client/RegionInfo;
      31: invokestatic  #9                  // Method org/apache/hadoop/hbase/client/RegionInfoBuilder.newBuilder:(Lorg/apache/hadoop/hbase/client/RegionInfo;)Lorg/apache/hadoop/hbase/client/RegionInfoBuilder;
      34: invokevirtual #10                 // Method org/apache/hadoop/hbase/client/RegionInfoBuilder.build:()Lorg/apache/hadoop/hbase/client/RegionInfo;
      37: aload_1
      38: invokestatic  #11                 // Method getRegionNameAsStringForDisplay:(Lorg/apache/hadoop/hbase/client/RegionInfo;Lorg/apache/hadoop/conf/Configuration;)Ljava/lang/String;
      41: astore        4
      43: new           #12                 // class java/lang/StringBuilder
      46: dup
      47: invokespecial #13                 // Method java/lang/StringBuilder."<init>":()V
      50: aload         4
      52: invokevirtual #14                 // Method java/lang/StringBuilder.append:(Ljava/lang/String;)Ljava/lang/StringBuilder;
      55: aload_2
      56: iload_3
      57: invokevirtual #15                 // Method java/lang/String.substring:(I)Ljava/lang/String;
      60: invokevirtual #14                 // Method java/lang/StringBuilder.append:(Ljava/lang/String;)Ljava/lang/StringBuilder;
      63: invokevirtual #16                 // Method java/lang/StringBuilder.toString:()Ljava/lang/String;
      66: areturn

  public static byte[] getEndKeyForDisplay(org.apache.hadoop.hbase.client.RegionInfo, org.apache.hadoop.conf.Configuration);
    Code:
       0: aload_1
       1: ldc           #3                  // String hbase.display.keys
       3: iconst_1
       4: invokevirtual #4                  // Method org/apache/hadoop/conf/Configuration.getBoolean:(Ljava/lang/String;Z)Z
       7: istore_2
       8: iload_2
       9: ifeq          19
      12: aload_0
      13: invokeinterface #17,  1           // InterfaceMethod org/apache/hadoop/hbase/client/RegionInfo.getEndKey:()[B
      18: areturn
      19: getstatic     #18                 // Field HIDDEN_END_KEY:[B
      22: areturn

  public static byte[] getStartKeyForDisplay(org.apache.hadoop.hbase.client.RegionInfo, org.apache.hadoop.conf.Configuration);
    Code:
       0: aload_1
       1: ldc           #3                  // String hbase.display.keys
       3: iconst_1
       4: invokevirtual #4                  // Method org/apache/hadoop/conf/Configuration.getBoolean:(Ljava/lang/String;Z)Z
       7: istore_2
       8: iload_2
       9: ifeq          19
      12: aload_0
      13: invokeinterface #19,  1           // InterfaceMethod org/apache/hadoop/hbase/client/RegionInfo.getStartKey:()[B
      18: areturn
      19: getstatic     #20                 // Field HIDDEN_START_KEY:[B
      22: areturn

  public static java.lang.String getRegionNameAsStringForDisplay(org.apache.hadoop.hbase.client.RegionInfo, org.apache.hadoop.conf.Configuration);
    Code:
       0: aload_0
       1: aload_1
       2: invokestatic  #21                 // Method getRegionNameForDisplay:(Lorg/apache/hadoop/hbase/client/RegionInfo;Lorg/apache/hadoop/conf/Configuration;)[B
       5: invokestatic  #22                 // Method org/apache/hadoop/hbase/util/Bytes.toStringBinary:([B)Ljava/lang/String;
       8: areturn

  public static byte[] getRegionNameForDisplay(org.apache.hadoop.hbase.client.RegionInfo, org.apache.hadoop.conf.Configuration);
    Code:
       0: aload_1
       1: ldc           #3                  // String hbase.display.keys
       3: iconst_1
       4: invokevirtual #4                  // Method org/apache/hadoop/conf/Configuration.getBoolean:(Ljava/lang/String;Z)Z
       7: istore_2
       8: iload_2
       9: ifne          27
      12: aload_0
      13: invokeinterface #23,  1           // InterfaceMethod org/apache/hadoop/hbase/client/RegionInfo.getTable:()Lorg/apache/hadoop/hbase/TableName;
      18: getstatic     #24                 // Field org/apache/hadoop/hbase/TableName.META_TABLE_NAME:Lorg/apache/hadoop/hbase/TableName;
      21: invokevirtual #25                 // Method org/apache/hadoop/hbase/TableName.equals:(Ljava/lang/Object;)Z
      24: ifeq          34
      27: aload_0
      28: invokeinterface #26,  1           // InterfaceMethod org/apache/hadoop/hbase/client/RegionInfo.getRegionName:()[B
      33: areturn
      34: aload_0
      35: invokeinterface #26,  1           // InterfaceMethod org/apache/hadoop/hbase/client/RegionInfo.getRegionName:()[B
      40: invokestatic  #27                 // InterfaceMethod org/apache/hadoop/hbase/client/RegionInfo.parseRegionName:([B)[[B
      43: astore_3
      44: aload_3
      45: iconst_1
      46: getstatic     #20                 // Field HIDDEN_START_KEY:[B
      49: aastore
      50: iconst_0
      51: istore        4
      53: aload_3
      54: astore        5
      56: aload         5
      58: arraylength
      59: istore        6
      61: iconst_0
      62: istore        7
      64: iload         7
      66: iload         6
      68: if_icmpge     92
      71: aload         5
      73: iload         7
      75: aaload
      76: astore        8
      78: iload         4
      80: aload         8
      82: arraylength
      83: iadd
      84: istore        4
      86: iinc          7, 1
      89: goto          64
      92: aload_0
      93: invokeinterface #26,  1           // InterfaceMethod org/apache/hadoop/hbase/client/RegionInfo.getRegionName:()[B
      98: invokestatic  #28                 // InterfaceMethod org/apache/hadoop/hbase/client/RegionInfo.encodeRegionName:([B)Ljava/lang/String;
     101: invokestatic  #29                 // Method org/apache/hadoop/hbase/util/Bytes.toBytes:(Ljava/lang/String;)[B
     104: astore        5
     106: iload         4
     108: aload         5
     110: arraylength
     111: iadd
     112: istore        4
     114: iload         4
     116: aload_3
     117: arraylength
     118: iadd
     119: iconst_1
     120: iadd
     121: newarray       byte
     123: astore        6
     125: iconst_0
     126: istore        7
     128: iconst_0
     129: istore        8
     131: aload_3
     132: astore        9
     134: aload         9
     136: arraylength
     137: istore        10
     139: iconst_0
     140: istore        11
     142: iload         11
     144: iload         10
     146: if_icmpge     215
     149: aload         9
     151: iload         11
     153: aaload
     154: astore        12
     156: aload         12
     158: iconst_0
     159: aload         6
     161: iload         7
     163: aload         12
     165: arraylength
     166: invokestatic  #30                 // Method java/lang/System.arraycopy:(Ljava/lang/Object;ILjava/lang/Object;II)V
     169: iload         7
     171: aload         12
     173: arraylength
     174: iadd
     175: istore        7
     177: iload         8
     179: iinc          8, 1
     182: iconst_2
     183: if_icmpne     199
     186: aload         6
     188: iload         7
     190: iinc          7, 1
     193: bipush        95
     195: bastore
     196: goto          209
     199: aload         6
     201: iload         7
     203: iinc          7, 1
     206: bipush        44
     208: bastore
     209: iinc          11, 1
     212: goto          142
     215: aload         6
     217: iload         7
     219: iconst_1
     220: isub
     221: bipush        46
     223: bastore
     224: aload         5
     226: iconst_0
     227: aload         6
     229: iload         7
     231: aload         5
     233: arraylength
     234: invokestatic  #30                 // Method java/lang/System.arraycopy:(Ljava/lang/Object;ILjava/lang/Object;II)V
     237: iload         7
     239: aload         5
     241: arraylength
     242: iadd
     243: istore        7
     245: aload         6
     247: iload         7
     249: bipush        46
     251: bastore
     252: aload         6
     254: areturn
     255: astore_3
     256: new           #34                 // class java/lang/RuntimeException
     259: dup
     260: aload_3
     261: invokespecial #35                 // Method java/lang/RuntimeException."<init>":(Ljava/lang/Throwable;)V
     264: athrow
    Exception table:
       from    to  target type
          34   254   255   Class java/io/IOException

  static {};
    Code:
       0: ldc           #36                 // String hidden-end-key
       2: invokestatic  #29                 // Method org/apache/hadoop/hbase/util/Bytes.toBytes:(Ljava/lang/String;)[B
       5: putstatic     #18                 // Field HIDDEN_END_KEY:[B
       8: ldc           #37                 // String hidden-start-key
      10: invokestatic  #29                 // Method org/apache/hadoop/hbase/util/Bytes.toBytes:(Ljava/lang/String;)[B
      13: putstatic     #20                 // Field HIDDEN_START_KEY:[B
      16: return
}
