Compiled from "RegionServerCallable.java"
public abstract class org.apache.hadoop.hbase.client.RegionServerCallable<T, S> implements org.apache.hadoop.hbase.client.RetryingCallable<T> {
  protected org.apache.hadoop.hbase.HRegionLocation location;

  protected S stub;

  protected final org.apache.hbase.thirdparty.com.google.protobuf.RpcController rpcController;

  public org.apache.hadoop.hbase.client.RegionServerCallable(org.apache.hadoop.hbase.client.Connection, org.apache.hadoop.hbase.TableName, byte[], org.apache.hbase.thirdparty.com.google.protobuf.RpcController);
    Code:
       0: aload_0
       1: aload_1
       2: aload_2
       3: aload_3
       4: aload         4
       6: iconst_0
       7: invokespecial #2                  // Method "<init>":(Lorg/apache/hadoop/hbase/client/Connection;Lorg/apache/hadoop/hbase/TableName;[BLorg/apache/hbase/thirdparty/com/google/protobuf/RpcController;I)V
      10: return

  public org.apache.hadoop.hbase.client.RegionServerCallable(org.apache.hadoop.hbase.client.Connection, org.apache.hadoop.hbase.TableName, byte[], org.apache.hbase.thirdparty.com.google.protobuf.RpcController, int);
    Code:
       0: aload_0
       1: invokespecial #3                  // Method java/lang/Object."<init>":()V
       4: aload_0
       5: iconst_0
       6: putfield      #4                  // Field priority:I
       9: aload_0
      10: aload_1
      11: putfield      #5                  // Field connection:Lorg/apache/hadoop/hbase/client/Connection;
      14: aload_0
      15: aload_2
      16: putfield      #6                  // Field tableName:Lorg/apache/hadoop/hbase/TableName;
      19: aload_0
      20: aload_3
      21: putfield      #7                  // Field row:[B
      24: aload_0
      25: aload         4
      27: putfield      #8                  // Field rpcController:Lorg/apache/hbase/thirdparty/com/google/protobuf/RpcController;
      30: aload_0
      31: iload         5
      33: putfield      #4                  // Field priority:I
      36: return

  protected org.apache.hbase.thirdparty.com.google.protobuf.RpcController getRpcController();
    Code:
       0: aload_0
       1: getfield      #8                  // Field rpcController:Lorg/apache/hbase/thirdparty/com/google/protobuf/RpcController;
       4: areturn

  protected void setStub(S);
    Code:
       0: aload_0
       1: aload_1
       2: putfield      #9                  // Field stub:Ljava/lang/Object;
       5: return

  protected S getStub();
    Code:
       0: aload_0
       1: getfield      #9                  // Field stub:Ljava/lang/Object;
       4: areturn

  public T call(int) throws java.io.IOException;
    Code:
       0: aload_0
       1: invokevirtual #10                 // Method getRpcController:()Lorg/apache/hbase/thirdparty/com/google/protobuf/RpcController;
       4: ifnull        60
       7: aload_0
       8: invokevirtual #10                 // Method getRpcController:()Lorg/apache/hbase/thirdparty/com/google/protobuf/RpcController;
      11: astore_2
      12: aload_2
      13: invokeinterface #11,  1           // InterfaceMethod org/apache/hbase/thirdparty/com/google/protobuf/RpcController.reset:()V
      18: aload_2
      19: instanceof    #12                 // class org/apache/hadoop/hbase/ipc/HBaseRpcController
      22: ifeq          60
      25: aload_0
      26: invokevirtual #10                 // Method getRpcController:()Lorg/apache/hbase/thirdparty/com/google/protobuf/RpcController;
      29: checkcast     #12                 // class org/apache/hadoop/hbase/ipc/HBaseRpcController
      32: astore_3
      33: aload_3
      34: aload_0
      35: getfield      #6                  // Field tableName:Lorg/apache/hadoop/hbase/TableName;
      38: invokeinterface #13,  2           // InterfaceMethod org/apache/hadoop/hbase/ipc/HBaseRpcController.setPriority:(Lorg/apache/hadoop/hbase/TableName;)V
      43: aload_3
      44: aload_0
      45: getfield      #4                  // Field priority:I
      48: invokeinterface #14,  2           // InterfaceMethod org/apache/hadoop/hbase/ipc/HBaseRpcController.setPriority:(I)V
      53: aload_3
      54: iload_1
      55: invokeinterface #15,  2           // InterfaceMethod org/apache/hadoop/hbase/ipc/HBaseRpcController.setCallTimeout:(I)V
      60: aload_0
      61: invokevirtual #16                 // Method rpcCall:()Ljava/lang/Object;
      64: areturn
      65: astore_2
      66: aload_2
      67: invokestatic  #18                 // Method org/apache/hadoop/hbase/protobuf/ProtobufUtil.handleRemoteException:(Ljava/lang/Exception;)Ljava/io/IOException;
      70: athrow
    Exception table:
       from    to  target type
           0    64    65   Class java/lang/Exception

  protected abstract T rpcCall() throws java.lang.Exception;

  protected org.apache.hadoop.hbase.CellScanner getRpcControllerCellScanner();
    Code:
       0: aload_0
       1: invokevirtual #10                 // Method getRpcController:()Lorg/apache/hbase/thirdparty/com/google/protobuf/RpcController;
       4: ifnull        32
       7: aload_0
       8: invokevirtual #10                 // Method getRpcController:()Lorg/apache/hbase/thirdparty/com/google/protobuf/RpcController;
      11: instanceof    #12                 // class org/apache/hadoop/hbase/ipc/HBaseRpcController
      14: ifeq          32
      17: aload_0
      18: invokevirtual #10                 // Method getRpcController:()Lorg/apache/hbase/thirdparty/com/google/protobuf/RpcController;
      21: checkcast     #12                 // class org/apache/hadoop/hbase/ipc/HBaseRpcController
      24: invokeinterface #19,  1           // InterfaceMethod org/apache/hadoop/hbase/ipc/HBaseRpcController.cellScanner:()Lorg/apache/hadoop/hbase/CellScanner;
      29: goto          33
      32: aconst_null
      33: areturn

  protected void setRpcControllerCellScanner(org.apache.hadoop.hbase.CellScanner);
    Code:
       0: aload_0
       1: invokevirtual #10                 // Method getRpcController:()Lorg/apache/hbase/thirdparty/com/google/protobuf/RpcController;
       4: ifnull        30
       7: aload_0
       8: invokevirtual #10                 // Method getRpcController:()Lorg/apache/hbase/thirdparty/com/google/protobuf/RpcController;
      11: instanceof    #12                 // class org/apache/hadoop/hbase/ipc/HBaseRpcController
      14: ifeq          30
      17: aload_0
      18: getfield      #8                  // Field rpcController:Lorg/apache/hbase/thirdparty/com/google/protobuf/RpcController;
      21: checkcast     #12                 // class org/apache/hadoop/hbase/ipc/HBaseRpcController
      24: aload_1
      25: invokeinterface #20,  2           // InterfaceMethod org/apache/hadoop/hbase/ipc/HBaseRpcController.setCellScanner:(Lorg/apache/hadoop/hbase/CellScanner;)V
      30: return

  protected org.apache.hadoop.hbase.client.ClusterConnection getConnection();
    Code:
       0: aload_0
       1: getfield      #5                  // Field connection:Lorg/apache/hadoop/hbase/client/Connection;
       4: checkcast     #21                 // class org/apache/hadoop/hbase/client/ClusterConnection
       7: areturn

  protected org.apache.hadoop.hbase.HRegionLocation getLocation();
    Code:
       0: aload_0
       1: getfield      #22                 // Field location:Lorg/apache/hadoop/hbase/HRegionLocation;
       4: areturn

  protected void setLocation(org.apache.hadoop.hbase.HRegionLocation);
    Code:
       0: aload_0
       1: aload_1
       2: putfield      #22                 // Field location:Lorg/apache/hadoop/hbase/HRegionLocation;
       5: return

  public org.apache.hadoop.hbase.TableName getTableName();
    Code:
       0: aload_0
       1: getfield      #6                  // Field tableName:Lorg/apache/hadoop/hbase/TableName;
       4: areturn

  public byte[] getRow();
    Code:
       0: aload_0
       1: getfield      #7                  // Field row:[B
       4: areturn

  protected int getPriority();
    Code:
       0: aload_0
       1: getfield      #4                  // Field priority:I
       4: ireturn

  public void throwable(java.lang.Throwable, boolean);
    Code:
       0: aload_0
       1: getfield      #22                 // Field location:Lorg/apache/hadoop/hbase/HRegionLocation;
       4: ifnull        42
       7: aload_0
       8: invokevirtual #23                 // Method getConnection:()Lorg/apache/hadoop/hbase/client/ClusterConnection;
      11: aload_0
      12: getfield      #6                  // Field tableName:Lorg/apache/hadoop/hbase/TableName;
      15: aload_0
      16: getfield      #22                 // Field location:Lorg/apache/hadoop/hbase/HRegionLocation;
      19: invokevirtual #24                 // Method org/apache/hadoop/hbase/HRegionLocation.getRegionInfo:()Lorg/apache/hadoop/hbase/HRegionInfo;
      22: invokevirtual #25                 // Method org/apache/hadoop/hbase/HRegionInfo.getRegionName:()[B
      25: aload_0
      26: getfield      #7                  // Field row:[B
      29: aload_1
      30: aload_0
      31: getfield      #22                 // Field location:Lorg/apache/hadoop/hbase/HRegionLocation;
      34: invokevirtual #26                 // Method org/apache/hadoop/hbase/HRegionLocation.getServerName:()Lorg/apache/hadoop/hbase/ServerName;
      37: invokeinterface #27,  6           // InterfaceMethod org/apache/hadoop/hbase/client/ClusterConnection.updateCachedLocations:(Lorg/apache/hadoop/hbase/TableName;[B[BLjava/lang/Object;Lorg/apache/hadoop/hbase/ServerName;)V
      42: return

  public java.lang.String getExceptionMessageAdditionalDetail();
    Code:
       0: new           #28                 // class java/lang/StringBuilder
       3: dup
       4: invokespecial #29                 // Method java/lang/StringBuilder."<init>":()V
       7: ldc           #30                 // String row '
       9: invokevirtual #31                 // Method java/lang/StringBuilder.append:(Ljava/lang/String;)Ljava/lang/StringBuilder;
      12: aload_0
      13: getfield      #7                  // Field row:[B
      16: invokestatic  #32                 // Method org/apache/hadoop/hbase/util/Bytes.toString:([B)Ljava/lang/String;
      19: invokevirtual #31                 // Method java/lang/StringBuilder.append:(Ljava/lang/String;)Ljava/lang/StringBuilder;
      22: ldc           #33                 // String ' on table '
      24: invokevirtual #31                 // Method java/lang/StringBuilder.append:(Ljava/lang/String;)Ljava/lang/StringBuilder;
      27: aload_0
      28: getfield      #6                  // Field tableName:Lorg/apache/hadoop/hbase/TableName;
      31: invokevirtual #34                 // Method java/lang/StringBuilder.append:(Ljava/lang/Object;)Ljava/lang/StringBuilder;
      34: ldc           #35                 // String ' at
      36: invokevirtual #31                 // Method java/lang/StringBuilder.append:(Ljava/lang/String;)Ljava/lang/StringBuilder;
      39: aload_0
      40: getfield      #22                 // Field location:Lorg/apache/hadoop/hbase/HRegionLocation;
      43: invokevirtual #34                 // Method java/lang/StringBuilder.append:(Ljava/lang/Object;)Ljava/lang/StringBuilder;
      46: invokevirtual #36                 // Method java/lang/StringBuilder.toString:()Ljava/lang/String;
      49: areturn

  public long sleep(long, int);
    Code:
       0: lload_1
       1: iload_3
       2: invokestatic  #37                 // Method org/apache/hadoop/hbase/client/ConnectionUtils.getPauseTime:(JI)J
       5: lreturn

  public org.apache.hadoop.hbase.HRegionInfo getHRegionInfo();
    Code:
       0: aload_0
       1: getfield      #22                 // Field location:Lorg/apache/hadoop/hbase/HRegionLocation;
       4: ifnonnull     9
       7: aconst_null
       8: areturn
       9: aload_0
      10: getfield      #22                 // Field location:Lorg/apache/hadoop/hbase/HRegionLocation;
      13: invokevirtual #24                 // Method org/apache/hadoop/hbase/HRegionLocation.getRegionInfo:()Lorg/apache/hadoop/hbase/HRegionInfo;
      16: areturn

  public void prepare(boolean) throws java.io.IOException;
    Code:
       0: iload_1
       1: ifeq          73
       4: aload_0
       5: getfield      #6                  // Field tableName:Lorg/apache/hadoop/hbase/TableName;
       8: ifnull        73
      11: aload_0
      12: getfield      #6                  // Field tableName:Lorg/apache/hadoop/hbase/TableName;
      15: getstatic     #38                 // Field org/apache/hadoop/hbase/TableName.META_TABLE_NAME:Lorg/apache/hadoop/hbase/TableName;
      18: invokevirtual #39                 // Method org/apache/hadoop/hbase/TableName.equals:(Ljava/lang/Object;)Z
      21: ifne          73
      24: aload_0
      25: invokevirtual #23                 // Method getConnection:()Lorg/apache/hadoop/hbase/client/ClusterConnection;
      28: aload_0
      29: getfield      #6                  // Field tableName:Lorg/apache/hadoop/hbase/TableName;
      32: invokeinterface #40,  2           // InterfaceMethod org/apache/hadoop/hbase/client/ClusterConnection.isTableDisabled:(Lorg/apache/hadoop/hbase/TableName;)Z
      37: ifeq          73
      40: new           #41                 // class org/apache/hadoop/hbase/TableNotEnabledException
      43: dup
      44: new           #28                 // class java/lang/StringBuilder
      47: dup
      48: invokespecial #29                 // Method java/lang/StringBuilder."<init>":()V
      51: aload_0
      52: getfield      #6                  // Field tableName:Lorg/apache/hadoop/hbase/TableName;
      55: invokevirtual #42                 // Method org/apache/hadoop/hbase/TableName.getNameAsString:()Ljava/lang/String;
      58: invokevirtual #31                 // Method java/lang/StringBuilder.append:(Ljava/lang/String;)Ljava/lang/StringBuilder;
      61: ldc           #43                 // String  is disabled.
      63: invokevirtual #31                 // Method java/lang/StringBuilder.append:(Ljava/lang/String;)Ljava/lang/StringBuilder;
      66: invokevirtual #36                 // Method java/lang/StringBuilder.toString:()Ljava/lang/String;
      69: invokespecial #44                 // Method org/apache/hadoop/hbase/TableNotEnabledException."<init>":(Ljava/lang/String;)V
      72: athrow
      73: aload_0
      74: getfield      #5                  // Field connection:Lorg/apache/hadoop/hbase/client/Connection;
      77: aload_0
      78: getfield      #6                  // Field tableName:Lorg/apache/hadoop/hbase/TableName;
      81: invokeinterface #45,  2           // InterfaceMethod org/apache/hadoop/hbase/client/Connection.getRegionLocator:(Lorg/apache/hadoop/hbase/TableName;)Lorg/apache/hadoop/hbase/client/RegionLocator;
      86: astore_2
      87: aconst_null
      88: astore_3
      89: aload_0
      90: aload_2
      91: aload_0
      92: getfield      #7                  // Field row:[B
      95: invokeinterface #46,  2           // InterfaceMethod org/apache/hadoop/hbase/client/RegionLocator.getRegionLocation:([B)Lorg/apache/hadoop/hbase/HRegionLocation;
     100: putfield      #22                 // Field location:Lorg/apache/hadoop/hbase/HRegionLocation;
     103: aload_2
     104: ifnull        187
     107: aload_3
     108: ifnull        131
     111: aload_2
     112: invokeinterface #47,  1           // InterfaceMethod org/apache/hadoop/hbase/client/RegionLocator.close:()V
     117: goto          187
     120: astore        4
     122: aload_3
     123: aload         4
     125: invokevirtual #49                 // Method java/lang/Throwable.addSuppressed:(Ljava/lang/Throwable;)V
     128: goto          187
     131: aload_2
     132: invokeinterface #47,  1           // InterfaceMethod org/apache/hadoop/hbase/client/RegionLocator.close:()V
     137: goto          187
     140: astore        4
     142: aload         4
     144: astore_3
     145: aload         4
     147: athrow
     148: astore        5
     150: aload_2
     151: ifnull        184
     154: aload_3
     155: ifnull        178
     158: aload_2
     159: invokeinterface #47,  1           // InterfaceMethod org/apache/hadoop/hbase/client/RegionLocator.close:()V
     164: goto          184
     167: astore        6
     169: aload_3
     170: aload         6
     172: invokevirtual #49                 // Method java/lang/Throwable.addSuppressed:(Ljava/lang/Throwable;)V
     175: goto          184
     178: aload_2
     179: invokeinterface #47,  1           // InterfaceMethod org/apache/hadoop/hbase/client/RegionLocator.close:()V
     184: aload         5
     186: athrow
     187: aload_0
     188: getfield      #22                 // Field location:Lorg/apache/hadoop/hbase/HRegionLocation;
     191: ifnonnull     248
     194: new           #50                 // class java/io/IOException
     197: dup
     198: new           #28                 // class java/lang/StringBuilder
     201: dup
     202: invokespecial #29                 // Method java/lang/StringBuilder."<init>":()V
     205: ldc           #51                 // String Failed to find location, tableName=
     207: invokevirtual #31                 // Method java/lang/StringBuilder.append:(Ljava/lang/String;)Ljava/lang/StringBuilder;
     210: aload_0
     211: getfield      #6                  // Field tableName:Lorg/apache/hadoop/hbase/TableName;
     214: invokevirtual #34                 // Method java/lang/StringBuilder.append:(Ljava/lang/Object;)Ljava/lang/StringBuilder;
     217: ldc           #52                 // String , row=
     219: invokevirtual #31                 // Method java/lang/StringBuilder.append:(Ljava/lang/String;)Ljava/lang/StringBuilder;
     222: aload_0
     223: getfield      #7                  // Field row:[B
     226: invokestatic  #32                 // Method org/apache/hadoop/hbase/util/Bytes.toString:([B)Ljava/lang/String;
     229: invokevirtual #31                 // Method java/lang/StringBuilder.append:(Ljava/lang/String;)Ljava/lang/StringBuilder;
     232: ldc           #53                 // String , reload=
     234: invokevirtual #31                 // Method java/lang/StringBuilder.append:(Ljava/lang/String;)Ljava/lang/StringBuilder;
     237: iload_1
     238: invokevirtual #54                 // Method java/lang/StringBuilder.append:(Z)Ljava/lang/StringBuilder;
     241: invokevirtual #36                 // Method java/lang/StringBuilder.toString:()Ljava/lang/String;
     244: invokespecial #55                 // Method java/io/IOException."<init>":(Ljava/lang/String;)V
     247: athrow
     248: aload_0
     249: aload_0
     250: getfield      #22                 // Field location:Lorg/apache/hadoop/hbase/HRegionLocation;
     253: invokevirtual #26                 // Method org/apache/hadoop/hbase/HRegionLocation.getServerName:()Lorg/apache/hadoop/hbase/ServerName;
     256: invokevirtual #56                 // Method setStubByServiceName:(Lorg/apache/hadoop/hbase/ServerName;)V
     259: return
    Exception table:
       from    to  target type
         111   117   120   Class java/lang/Throwable
          89   103   140   Class java/lang/Throwable
          89   103   148   any
         158   164   167   Class java/lang/Throwable
         140   150   148   any

  protected abstract void setStubByServiceName(org.apache.hadoop.hbase.ServerName) throws java.io.IOException;
}
