Compiled from "RegionMover.java"
class org.apache.hadoop.hbase.util.RegionMover$MoveWithoutAck implements java.util.concurrent.Callable<java.lang.Boolean> {
  final org.apache.hadoop.hbase.util.RegionMover this$0;

  public org.apache.hadoop.hbase.util.RegionMover$MoveWithoutAck(org.apache.hadoop.hbase.client.RegionInfo, org.apache.hadoop.hbase.ServerName, org.apache.hadoop.hbase.ServerName, java.util.List<org.apache.hadoop.hbase.client.RegionInfo>);
    Code:
       0: aload_0
       1: aload_1
       2: putfield      #1                  // Field this$0:Lorg/apache/hadoop/hbase/util/RegionMover;
       5: aload_0
       6: invokespecial #2                  // Method java/lang/Object."<init>":()V
       9: aload_0
      10: aload_2
      11: putfield      #3                  // Field region:Lorg/apache/hadoop/hbase/client/RegionInfo;
      14: aload_0
      15: aload         4
      17: putfield      #4                  // Field targetServer:Lorg/apache/hadoop/hbase/ServerName;
      20: aload_0
      21: aload         5
      23: putfield      #5                  // Field movedRegions:Ljava/util/List;
      26: aload_0
      27: aload_3
      28: putfield      #6                  // Field sourceServer:Lorg/apache/hadoop/hbase/ServerName;
      31: return

  public java.lang.Boolean call();
    Code:
       0: getstatic     #7                  // Field org/apache/hadoop/hbase/util/RegionMover.LOG:Lorg/slf4j/Logger;
       3: new           #8                  // class java/lang/StringBuilder
       6: dup
       7: invokespecial #9                  // Method java/lang/StringBuilder."<init>":()V
      10: ldc           #10                 // String Moving region:
      12: invokevirtual #11                 // Method java/lang/StringBuilder.append:(Ljava/lang/String;)Ljava/lang/StringBuilder;
      15: aload_0
      16: getfield      #3                  // Field region:Lorg/apache/hadoop/hbase/client/RegionInfo;
      19: invokeinterface #12,  1           // InterfaceMethod org/apache/hadoop/hbase/client/RegionInfo.getEncodedName:()Ljava/lang/String;
      24: invokevirtual #11                 // Method java/lang/StringBuilder.append:(Ljava/lang/String;)Ljava/lang/StringBuilder;
      27: ldc           #13                 // String  from
      29: invokevirtual #11                 // Method java/lang/StringBuilder.append:(Ljava/lang/String;)Ljava/lang/StringBuilder;
      32: aload_0
      33: getfield      #6                  // Field sourceServer:Lorg/apache/hadoop/hbase/ServerName;
      36: invokevirtual #14                 // Method java/lang/StringBuilder.append:(Ljava/lang/Object;)Ljava/lang/StringBuilder;
      39: ldc           #15                 // String  to
      41: invokevirtual #11                 // Method java/lang/StringBuilder.append:(Ljava/lang/String;)Ljava/lang/StringBuilder;
      44: aload_0
      45: getfield      #4                  // Field targetServer:Lorg/apache/hadoop/hbase/ServerName;
      48: invokevirtual #14                 // Method java/lang/StringBuilder.append:(Ljava/lang/Object;)Ljava/lang/StringBuilder;
      51: invokevirtual #16                 // Method java/lang/StringBuilder.toString:()Ljava/lang/String;
      54: invokeinterface #17,  2           // InterfaceMethod org/slf4j/Logger.info:(Ljava/lang/String;)V
      59: aload_0
      60: getfield      #1                  // Field this$0:Lorg/apache/hadoop/hbase/util/RegionMover;
      63: invokestatic  #18                 // Method org/apache/hadoop/hbase/util/RegionMover.access$800:(Lorg/apache/hadoop/hbase/util/RegionMover;)Lorg/apache/hadoop/hbase/client/Admin;
      66: aload_0
      67: getfield      #3                  // Field region:Lorg/apache/hadoop/hbase/client/RegionInfo;
      70: invokeinterface #19,  1           // InterfaceMethod org/apache/hadoop/hbase/client/RegionInfo.getEncodedNameAsBytes:()[B
      75: aload_0
      76: getfield      #4                  // Field targetServer:Lorg/apache/hadoop/hbase/ServerName;
      79: invokeinterface #20,  3           // InterfaceMethod org/apache/hadoop/hbase/client/Admin.move:([BLorg/apache/hadoop/hbase/ServerName;)V
      84: getstatic     #7                  // Field org/apache/hadoop/hbase/util/RegionMover.LOG:Lorg/slf4j/Logger;
      87: new           #8                  // class java/lang/StringBuilder
      90: dup
      91: invokespecial #9                  // Method java/lang/StringBuilder."<init>":()V
      94: ldc           #21                 // String Moved
      96: invokevirtual #11                 // Method java/lang/StringBuilder.append:(Ljava/lang/String;)Ljava/lang/StringBuilder;
      99: aload_0
     100: getfield      #3                  // Field region:Lorg/apache/hadoop/hbase/client/RegionInfo;
     103: invokeinterface #12,  1           // InterfaceMethod org/apache/hadoop/hbase/client/RegionInfo.getEncodedName:()Ljava/lang/String;
     108: invokevirtual #11                 // Method java/lang/StringBuilder.append:(Ljava/lang/String;)Ljava/lang/StringBuilder;
     111: ldc           #13                 // String  from
     113: invokevirtual #11                 // Method java/lang/StringBuilder.append:(Ljava/lang/String;)Ljava/lang/StringBuilder;
     116: aload_0
     117: getfield      #6                  // Field sourceServer:Lorg/apache/hadoop/hbase/ServerName;
     120: invokevirtual #14                 // Method java/lang/StringBuilder.append:(Ljava/lang/Object;)Ljava/lang/StringBuilder;
     123: ldc           #15                 // String  to
     125: invokevirtual #11                 // Method java/lang/StringBuilder.append:(Ljava/lang/String;)Ljava/lang/StringBuilder;
     128: aload_0
     129: getfield      #4                  // Field targetServer:Lorg/apache/hadoop/hbase/ServerName;
     132: invokevirtual #14                 // Method java/lang/StringBuilder.append:(Ljava/lang/Object;)Ljava/lang/StringBuilder;
     135: invokevirtual #16                 // Method java/lang/StringBuilder.toString:()Ljava/lang/String;
     138: invokeinterface #17,  2           // InterfaceMethod org/slf4j/Logger.info:(Ljava/lang/String;)V
     143: aload_0
     144: getfield      #5                  // Field movedRegions:Ljava/util/List;
     147: aload_0
     148: getfield      #3                  // Field region:Lorg/apache/hadoop/hbase/client/RegionInfo;
     151: invokeinterface #22,  2           // InterfaceMethod java/util/List.add:(Ljava/lang/Object;)Z
     156: pop
     157: goto          231
     160: astore_1
     161: getstatic     #7                  // Field org/apache/hadoop/hbase/util/RegionMover.LOG:Lorg/slf4j/Logger;
     164: new           #8                  // class java/lang/StringBuilder
     167: dup
     168: invokespecial #9                  // Method java/lang/StringBuilder."<init>":()V
     171: ldc           #24                 // String Error Moving Region:
     173: invokevirtual #11                 // Method java/lang/StringBuilder.append:(Ljava/lang/String;)Ljava/lang/StringBuilder;
     176: aload_0
     177: getfield      #3                  // Field region:Lorg/apache/hadoop/hbase/client/RegionInfo;
     180: invokeinterface #12,  1           // InterfaceMethod org/apache/hadoop/hbase/client/RegionInfo.getEncodedName:()Ljava/lang/String;
     185: invokevirtual #11                 // Method java/lang/StringBuilder.append:(Ljava/lang/String;)Ljava/lang/StringBuilder;
     188: invokevirtual #16                 // Method java/lang/StringBuilder.toString:()Ljava/lang/String;
     191: aload_1
     192: invokeinterface #25,  3           // InterfaceMethod org/slf4j/Logger.error:(Ljava/lang/String;Ljava/lang/Throwable;)V
     197: aload_0
     198: getfield      #5                  // Field movedRegions:Ljava/util/List;
     201: aload_0
     202: getfield      #3                  // Field region:Lorg/apache/hadoop/hbase/client/RegionInfo;
     205: invokeinterface #22,  2           // InterfaceMethod java/util/List.add:(Ljava/lang/Object;)Z
     210: pop
     211: goto          231
     214: astore_2
     215: aload_0
     216: getfield      #5                  // Field movedRegions:Ljava/util/List;
     219: aload_0
     220: getfield      #3                  // Field region:Lorg/apache/hadoop/hbase/client/RegionInfo;
     223: invokeinterface #22,  2           // InterfaceMethod java/util/List.add:(Ljava/lang/Object;)Z
     228: pop
     229: aload_2
     230: athrow
     231: iconst_1
     232: invokestatic  #26                 // Method java/lang/Boolean.valueOf:(Z)Ljava/lang/Boolean;
     235: areturn
    Exception table:
       from    to  target type
           0   143   160   Class java/lang/Exception
           0   143   214   any
         160   197   214   any

  public java.lang.Object call() throws java.lang.Exception;
    Code:
       0: aload_0
       1: invokevirtual #27                 // Method call:()Ljava/lang/Boolean;
       4: areturn
}
