Compiled from "RegionMetricsBuilder.java"
class org.apache.hadoop.hbase.RegionMetricsBuilder$RegionMetricsImpl implements org.apache.hadoop.hbase.RegionMetrics {
  org.apache.hadoop.hbase.RegionMetricsBuilder$RegionMetricsImpl(byte[], int, int, int, long, long, org.apache.hadoop.hbase.Size, org.apache.hadoop.hbase.Size, org.apache.hadoop.hbase.Size, org.apache.hadoop.hbase.Size, org.apache.hadoop.hbase.Size, org.apache.hadoop.hbase.Size, org.apache.hadoop.hbase.Size, long, long, long, long, long, java.util.Map<byte[], java.lang.Long>, float, long);
    Code:
       0: aload_0
       1: invokespecial #1                  // Method java/lang/Object."<init>":()V
       4: aload_0
       5: aload_1
       6: invokestatic  #2                  // Method org/apache/hbase/thirdparty/com/google/common/base/Preconditions.checkNotNull:(Ljava/lang/Object;)Ljava/lang/Object;
       9: checkcast     #3                  // class "[B"
      12: putfield      #4                  // Field name:[B
      15: aload_0
      16: iload_2
      17: putfield      #5                  // Field storeCount:I
      20: aload_0
      21: iload_3
      22: putfield      #6                  // Field storeFileCount:I
      25: aload_0
      26: iload         4
      28: putfield      #7                  // Field storeRefCount:I
      31: aload_0
      32: lload         5
      34: putfield      #8                  // Field compactingCellCount:J
      37: aload_0
      38: lload         7
      40: putfield      #9                  // Field compactedCellCount:J
      43: aload_0
      44: aload         9
      46: invokestatic  #2                  // Method org/apache/hbase/thirdparty/com/google/common/base/Preconditions.checkNotNull:(Ljava/lang/Object;)Ljava/lang/Object;
      49: checkcast     #10                 // class org/apache/hadoop/hbase/Size
      52: putfield      #11                 // Field storeFileSize:Lorg/apache/hadoop/hbase/Size;
      55: aload_0
      56: aload         10
      58: invokestatic  #2                  // Method org/apache/hbase/thirdparty/com/google/common/base/Preconditions.checkNotNull:(Ljava/lang/Object;)Ljava/lang/Object;
      61: checkcast     #10                 // class org/apache/hadoop/hbase/Size
      64: putfield      #12                 // Field memStoreSize:Lorg/apache/hadoop/hbase/Size;
      67: aload_0
      68: aload         11
      70: invokestatic  #2                  // Method org/apache/hbase/thirdparty/com/google/common/base/Preconditions.checkNotNull:(Ljava/lang/Object;)Ljava/lang/Object;
      73: checkcast     #10                 // class org/apache/hadoop/hbase/Size
      76: putfield      #13                 // Field indexSize:Lorg/apache/hadoop/hbase/Size;
      79: aload_0
      80: aload         12
      82: invokestatic  #2                  // Method org/apache/hbase/thirdparty/com/google/common/base/Preconditions.checkNotNull:(Ljava/lang/Object;)Ljava/lang/Object;
      85: checkcast     #10                 // class org/apache/hadoop/hbase/Size
      88: putfield      #14                 // Field rootLevelIndexSize:Lorg/apache/hadoop/hbase/Size;
      91: aload_0
      92: aload         13
      94: invokestatic  #2                  // Method org/apache/hbase/thirdparty/com/google/common/base/Preconditions.checkNotNull:(Ljava/lang/Object;)Ljava/lang/Object;
      97: checkcast     #10                 // class org/apache/hadoop/hbase/Size
     100: putfield      #15                 // Field uncompressedDataIndexSize:Lorg/apache/hadoop/hbase/Size;
     103: aload_0
     104: aload         14
     106: invokestatic  #2                  // Method org/apache/hbase/thirdparty/com/google/common/base/Preconditions.checkNotNull:(Ljava/lang/Object;)Ljava/lang/Object;
     109: checkcast     #10                 // class org/apache/hadoop/hbase/Size
     112: putfield      #16                 // Field bloomFilterSize:Lorg/apache/hadoop/hbase/Size;
     115: aload_0
     116: aload         15
     118: invokestatic  #2                  // Method org/apache/hbase/thirdparty/com/google/common/base/Preconditions.checkNotNull:(Ljava/lang/Object;)Ljava/lang/Object;
     121: checkcast     #10                 // class org/apache/hadoop/hbase/Size
     124: putfield      #17                 // Field uncompressedStoreFileSize:Lorg/apache/hadoop/hbase/Size;
     127: aload_0
     128: lload         16
     130: putfield      #18                 // Field writeRequestCount:J
     133: aload_0
     134: lload         18
     136: putfield      #19                 // Field readRequestCount:J
     139: aload_0
     140: lload         20
     142: putfield      #20                 // Field cpRequestCount:J
     145: aload_0
     146: lload         22
     148: putfield      #21                 // Field filteredReadRequestCount:J
     151: aload_0
     152: lload         24
     154: putfield      #22                 // Field completedSequenceId:J
     157: aload_0
     158: aload         26
     160: invokestatic  #2                  // Method org/apache/hbase/thirdparty/com/google/common/base/Preconditions.checkNotNull:(Ljava/lang/Object;)Ljava/lang/Object;
     163: checkcast     #23                 // class java/util/Map
     166: putfield      #24                 // Field storeSequenceIds:Ljava/util/Map;
     169: aload_0
     170: fload         27
     172: putfield      #25                 // Field dataLocality:F
     175: aload_0
     176: lload         28
     178: putfield      #26                 // Field lastMajorCompactionTimestamp:J
     181: return

  public byte[] getRegionName();
    Code:
       0: aload_0
       1: getfield      #4                  // Field name:[B
       4: areturn

  public int getStoreCount();
    Code:
       0: aload_0
       1: getfield      #5                  // Field storeCount:I
       4: ireturn

  public int getStoreFileCount();
    Code:
       0: aload_0
       1: getfield      #6                  // Field storeFileCount:I
       4: ireturn

  public int getStoreRefCount();
    Code:
       0: aload_0
       1: getfield      #7                  // Field storeRefCount:I
       4: ireturn

  public org.apache.hadoop.hbase.Size getStoreFileSize();
    Code:
       0: aload_0
       1: getfield      #11                 // Field storeFileSize:Lorg/apache/hadoop/hbase/Size;
       4: areturn

  public org.apache.hadoop.hbase.Size getMemStoreSize();
    Code:
       0: aload_0
       1: getfield      #12                 // Field memStoreSize:Lorg/apache/hadoop/hbase/Size;
       4: areturn

  public long getReadRequestCount();
    Code:
       0: aload_0
       1: getfield      #19                 // Field readRequestCount:J
       4: lreturn

  public long getCpRequestCount();
    Code:
       0: aload_0
       1: getfield      #20                 // Field cpRequestCount:J
       4: lreturn

  public long getFilteredReadRequestCount();
    Code:
       0: aload_0
       1: getfield      #21                 // Field filteredReadRequestCount:J
       4: lreturn

  public long getWriteRequestCount();
    Code:
       0: aload_0
       1: getfield      #18                 // Field writeRequestCount:J
       4: lreturn

  public org.apache.hadoop.hbase.Size getStoreFileIndexSize();
    Code:
       0: aload_0
       1: getfield      #13                 // Field indexSize:Lorg/apache/hadoop/hbase/Size;
       4: areturn

  public org.apache.hadoop.hbase.Size getStoreFileRootLevelIndexSize();
    Code:
       0: aload_0
       1: getfield      #14                 // Field rootLevelIndexSize:Lorg/apache/hadoop/hbase/Size;
       4: areturn

  public org.apache.hadoop.hbase.Size getStoreFileUncompressedDataIndexSize();
    Code:
       0: aload_0
       1: getfield      #15                 // Field uncompressedDataIndexSize:Lorg/apache/hadoop/hbase/Size;
       4: areturn

  public org.apache.hadoop.hbase.Size getBloomFilterSize();
    Code:
       0: aload_0
       1: getfield      #16                 // Field bloomFilterSize:Lorg/apache/hadoop/hbase/Size;
       4: areturn

  public long getCompactingCellCount();
    Code:
       0: aload_0
       1: getfield      #8                  // Field compactingCellCount:J
       4: lreturn

  public long getCompactedCellCount();
    Code:
       0: aload_0
       1: getfield      #9                  // Field compactedCellCount:J
       4: lreturn

  public long getCompletedSequenceId();
    Code:
       0: aload_0
       1: getfield      #22                 // Field completedSequenceId:J
       4: lreturn

  public java.util.Map<byte[], java.lang.Long> getStoreSequenceId();
    Code:
       0: aload_0
       1: getfield      #24                 // Field storeSequenceIds:Ljava/util/Map;
       4: invokestatic  #27                 // Method java/util/Collections.unmodifiableMap:(Ljava/util/Map;)Ljava/util/Map;
       7: areturn

  public org.apache.hadoop.hbase.Size getUncompressedStoreFileSize();
    Code:
       0: aload_0
       1: getfield      #17                 // Field uncompressedStoreFileSize:Lorg/apache/hadoop/hbase/Size;
       4: areturn

  public float getDataLocality();
    Code:
       0: aload_0
       1: getfield      #25                 // Field dataLocality:F
       4: freturn

  public long getLastMajorCompactionTimestamp();
    Code:
       0: aload_0
       1: getfield      #26                 // Field lastMajorCompactionTimestamp:J
       4: lreturn

  public java.lang.String toString();
    Code:
       0: new           #28                 // class java/lang/StringBuilder
       3: dup
       4: invokespecial #29                 // Method java/lang/StringBuilder."<init>":()V
       7: ldc           #30                 // String storeCount
       9: aload_0
      10: invokevirtual #31                 // Method getStoreCount:()I
      13: invokestatic  #32                 // Method java/lang/Integer.valueOf:(I)Ljava/lang/Integer;
      16: invokestatic  #33                 // Method org/apache/hadoop/hbase/util/Strings.appendKeyValue:(Ljava/lang/StringBuilder;Ljava/lang/String;Ljava/lang/Object;)Ljava/lang/StringBuilder;
      19: astore_1
      20: aload_1
      21: ldc           #34                 // String storeFileCount
      23: aload_0
      24: invokevirtual #35                 // Method getStoreFileCount:()I
      27: invokestatic  #32                 // Method java/lang/Integer.valueOf:(I)Ljava/lang/Integer;
      30: invokestatic  #33                 // Method org/apache/hadoop/hbase/util/Strings.appendKeyValue:(Ljava/lang/StringBuilder;Ljava/lang/String;Ljava/lang/Object;)Ljava/lang/StringBuilder;
      33: pop
      34: aload_1
      35: ldc           #36                 // String storeRefCount
      37: aload_0
      38: invokevirtual #37                 // Method getStoreRefCount:()I
      41: invokestatic  #32                 // Method java/lang/Integer.valueOf:(I)Ljava/lang/Integer;
      44: invokestatic  #33                 // Method org/apache/hadoop/hbase/util/Strings.appendKeyValue:(Ljava/lang/StringBuilder;Ljava/lang/String;Ljava/lang/Object;)Ljava/lang/StringBuilder;
      47: pop
      48: aload_1
      49: ldc           #38                 // String uncompressedStoreFileSize
      51: aload_0
      52: invokevirtual #39                 // Method getUncompressedStoreFileSize:()Lorg/apache/hadoop/hbase/Size;
      55: invokestatic  #33                 // Method org/apache/hadoop/hbase/util/Strings.appendKeyValue:(Ljava/lang/StringBuilder;Ljava/lang/String;Ljava/lang/Object;)Ljava/lang/StringBuilder;
      58: pop
      59: aload_1
      60: ldc           #40                 // String lastMajorCompactionTimestamp
      62: aload_0
      63: invokevirtual #41                 // Method getLastMajorCompactionTimestamp:()J
      66: invokestatic  #42                 // Method java/lang/Long.valueOf:(J)Ljava/lang/Long;
      69: invokestatic  #33                 // Method org/apache/hadoop/hbase/util/Strings.appendKeyValue:(Ljava/lang/StringBuilder;Ljava/lang/String;Ljava/lang/Object;)Ljava/lang/StringBuilder;
      72: pop
      73: aload_1
      74: ldc           #43                 // String storeFileSize
      76: aload_0
      77: invokevirtual #44                 // Method getStoreFileSize:()Lorg/apache/hadoop/hbase/Size;
      80: invokestatic  #33                 // Method org/apache/hadoop/hbase/util/Strings.appendKeyValue:(Ljava/lang/StringBuilder;Ljava/lang/String;Ljava/lang/Object;)Ljava/lang/StringBuilder;
      83: pop
      84: aload_0
      85: invokevirtual #39                 // Method getUncompressedStoreFileSize:()Lorg/apache/hadoop/hbase/Size;
      88: invokevirtual #45                 // Method org/apache/hadoop/hbase/Size.get:()D
      91: dconst_0
      92: dcmpl
      93: ifeq          141
      96: aload_1
      97: ldc           #46                 // String compressionRatio
      99: ldc           #47                 // String %.4f
     101: iconst_1
     102: anewarray     #48                 // class java/lang/Object
     105: dup
     106: iconst_0
     107: aload_0
     108: invokevirtual #44                 // Method getStoreFileSize:()Lorg/apache/hadoop/hbase/Size;
     111: getstatic     #49                 // Field org/apache/hadoop/hbase/Size$Unit.MEGABYTE:Lorg/apache/hadoop/hbase/Size$Unit;
     114: invokevirtual #50                 // Method org/apache/hadoop/hbase/Size.get:(Lorg/apache/hadoop/hbase/Size$Unit;)D
     117: d2f
     118: aload_0
     119: invokevirtual #39                 // Method getUncompressedStoreFileSize:()Lorg/apache/hadoop/hbase/Size;
     122: getstatic     #49                 // Field org/apache/hadoop/hbase/Size$Unit.MEGABYTE:Lorg/apache/hadoop/hbase/Size$Unit;
     125: invokevirtual #50                 // Method org/apache/hadoop/hbase/Size.get:(Lorg/apache/hadoop/hbase/Size$Unit;)D
     128: d2f
     129: fdiv
     130: invokestatic  #51                 // Method java/lang/Float.valueOf:(F)Ljava/lang/Float;
     133: aastore
     134: invokestatic  #52                 // Method java/lang/String.format:(Ljava/lang/String;[Ljava/lang/Object;)Ljava/lang/String;
     137: invokestatic  #33                 // Method org/apache/hadoop/hbase/util/Strings.appendKeyValue:(Ljava/lang/StringBuilder;Ljava/lang/String;Ljava/lang/Object;)Ljava/lang/StringBuilder;
     140: pop
     141: aload_1
     142: ldc           #53                 // String memStoreSize
     144: aload_0
     145: invokevirtual #54                 // Method getMemStoreSize:()Lorg/apache/hadoop/hbase/Size;
     148: invokestatic  #33                 // Method org/apache/hadoop/hbase/util/Strings.appendKeyValue:(Ljava/lang/StringBuilder;Ljava/lang/String;Ljava/lang/Object;)Ljava/lang/StringBuilder;
     151: pop
     152: aload_1
     153: ldc           #55                 // String readRequestCount
     155: aload_0
     156: invokevirtual #56                 // Method getReadRequestCount:()J
     159: invokestatic  #42                 // Method java/lang/Long.valueOf:(J)Ljava/lang/Long;
     162: invokestatic  #33                 // Method org/apache/hadoop/hbase/util/Strings.appendKeyValue:(Ljava/lang/StringBuilder;Ljava/lang/String;Ljava/lang/Object;)Ljava/lang/StringBuilder;
     165: pop
     166: aload_1
     167: ldc           #57                 // String cpRequestCount
     169: aload_0
     170: invokevirtual #58                 // Method getCpRequestCount:()J
     173: invokestatic  #42                 // Method java/lang/Long.valueOf:(J)Ljava/lang/Long;
     176: invokestatic  #33                 // Method org/apache/hadoop/hbase/util/Strings.appendKeyValue:(Ljava/lang/StringBuilder;Ljava/lang/String;Ljava/lang/Object;)Ljava/lang/StringBuilder;
     179: pop
     180: aload_1
     181: ldc           #59                 // String writeRequestCount
     183: aload_0
     184: invokevirtual #60                 // Method getWriteRequestCount:()J
     187: invokestatic  #42                 // Method java/lang/Long.valueOf:(J)Ljava/lang/Long;
     190: invokestatic  #33                 // Method org/apache/hadoop/hbase/util/Strings.appendKeyValue:(Ljava/lang/StringBuilder;Ljava/lang/String;Ljava/lang/Object;)Ljava/lang/StringBuilder;
     193: pop
     194: aload_1
     195: ldc           #61                 // String rootLevelIndexSize
     197: aload_0
     198: invokevirtual #62                 // Method getStoreFileRootLevelIndexSize:()Lorg/apache/hadoop/hbase/Size;
     201: invokestatic  #33                 // Method org/apache/hadoop/hbase/util/Strings.appendKeyValue:(Ljava/lang/StringBuilder;Ljava/lang/String;Ljava/lang/Object;)Ljava/lang/StringBuilder;
     204: pop
     205: aload_1
     206: ldc           #63                 // String uncompressedDataIndexSize
     208: aload_0
     209: invokevirtual #64                 // Method getStoreFileUncompressedDataIndexSize:()Lorg/apache/hadoop/hbase/Size;
     212: invokestatic  #33                 // Method org/apache/hadoop/hbase/util/Strings.appendKeyValue:(Ljava/lang/StringBuilder;Ljava/lang/String;Ljava/lang/Object;)Ljava/lang/StringBuilder;
     215: pop
     216: aload_1
     217: ldc           #65                 // String bloomFilterSize
     219: aload_0
     220: invokevirtual #66                 // Method getBloomFilterSize:()Lorg/apache/hadoop/hbase/Size;
     223: invokestatic  #33                 // Method org/apache/hadoop/hbase/util/Strings.appendKeyValue:(Ljava/lang/StringBuilder;Ljava/lang/String;Ljava/lang/Object;)Ljava/lang/StringBuilder;
     226: pop
     227: aload_1
     228: ldc           #67                 // String compactingCellCount
     230: aload_0
     231: invokevirtual #68                 // Method getCompactingCellCount:()J
     234: invokestatic  #42                 // Method java/lang/Long.valueOf:(J)Ljava/lang/Long;
     237: invokestatic  #33                 // Method org/apache/hadoop/hbase/util/Strings.appendKeyValue:(Ljava/lang/StringBuilder;Ljava/lang/String;Ljava/lang/Object;)Ljava/lang/StringBuilder;
     240: pop
     241: aload_1
     242: ldc           #69                 // String compactedCellCount
     244: aload_0
     245: invokevirtual #70                 // Method getCompactedCellCount:()J
     248: invokestatic  #42                 // Method java/lang/Long.valueOf:(J)Ljava/lang/Long;
     251: invokestatic  #33                 // Method org/apache/hadoop/hbase/util/Strings.appendKeyValue:(Ljava/lang/StringBuilder;Ljava/lang/String;Ljava/lang/Object;)Ljava/lang/StringBuilder;
     254: pop
     255: ldc           #72                 // float NaNf
     257: fstore_2
     258: aload_0
     259: invokevirtual #68                 // Method getCompactingCellCount:()J
     262: lconst_0
     263: lcmp
     264: ifle          279
     267: aload_0
     268: invokevirtual #70                 // Method getCompactedCellCount:()J
     271: l2f
     272: aload_0
     273: invokevirtual #68                 // Method getCompactingCellCount:()J
     276: l2f
     277: fdiv
     278: fstore_2
     279: aload_1
     280: ldc           #73                 // String compactionProgressPct
     282: fload_2
     283: invokestatic  #51                 // Method java/lang/Float.valueOf:(F)Ljava/lang/Float;
     286: invokestatic  #33                 // Method org/apache/hadoop/hbase/util/Strings.appendKeyValue:(Ljava/lang/StringBuilder;Ljava/lang/String;Ljava/lang/Object;)Ljava/lang/StringBuilder;
     289: pop
     290: aload_1
     291: ldc           #74                 // String completedSequenceId
     293: aload_0
     294: invokevirtual #75                 // Method getCompletedSequenceId:()J
     297: invokestatic  #42                 // Method java/lang/Long.valueOf:(J)Ljava/lang/Long;
     300: invokestatic  #33                 // Method org/apache/hadoop/hbase/util/Strings.appendKeyValue:(Ljava/lang/StringBuilder;Ljava/lang/String;Ljava/lang/Object;)Ljava/lang/StringBuilder;
     303: pop
     304: aload_1
     305: ldc           #76                 // String dataLocality
     307: aload_0
     308: invokevirtual #77                 // Method getDataLocality:()F
     311: invokestatic  #51                 // Method java/lang/Float.valueOf:(F)Ljava/lang/Float;
     314: invokestatic  #33                 // Method org/apache/hadoop/hbase/util/Strings.appendKeyValue:(Ljava/lang/StringBuilder;Ljava/lang/String;Ljava/lang/Object;)Ljava/lang/StringBuilder;
     317: pop
     318: aload_1
     319: invokevirtual #78                 // Method java/lang/StringBuilder.toString:()Ljava/lang/String;
     322: areturn
}
