Compiled from "RegionSizeStoreImpl.java"
public class org.apache.hadoop.hbase.quotas.RegionSizeStoreImpl implements org.apache.hadoop.hbase.quotas.RegionSizeStore {
  public org.apache.hadoop.hbase.quotas.RegionSizeStoreImpl();
    Code:
       0: aload_0
       1: invokespecial #1                  // Method java/lang/Object."<init>":()V
       4: aload_0
       5: new           #2                  // class java/util/concurrent/ConcurrentHashMap
       8: dup
       9: invokespecial #3                  // Method java/util/concurrent/ConcurrentHashMap."<init>":()V
      12: putfield      #4                  // Field store:Ljava/util/concurrent/ConcurrentHashMap;
      15: return

  public java.util.Iterator<java.util.Map$Entry<org.apache.hadoop.hbase.client.RegionInfo, org.apache.hadoop.hbase.quotas.RegionSize>> iterator();
    Code:
       0: aload_0
       1: getfield      #4                  // Field store:Ljava/util/concurrent/ConcurrentHashMap;
       4: invokevirtual #5                  // Method java/util/concurrent/ConcurrentHashMap.entrySet:()Ljava/util/Set;
       7: invokeinterface #6,  1            // InterfaceMethod java/util/Set.iterator:()Ljava/util/Iterator;
      12: areturn

  public org.apache.hadoop.hbase.quotas.RegionSize getRegionSize(org.apache.hadoop.hbase.client.RegionInfo);
    Code:
       0: aload_0
       1: getfield      #4                  // Field store:Ljava/util/concurrent/ConcurrentHashMap;
       4: aload_1
       5: invokevirtual #7                  // Method java/util/concurrent/ConcurrentHashMap.get:(Ljava/lang/Object;)Ljava/lang/Object;
       8: checkcast     #8                  // class org/apache/hadoop/hbase/quotas/RegionSize
      11: areturn

  public void put(org.apache.hadoop.hbase.client.RegionInfo, long);
    Code:
       0: getstatic     #9                  // Field LOG:Lorg/slf4j/Logger;
       3: invokeinterface #10,  1           // InterfaceMethod org/slf4j/Logger.isTraceEnabled:()Z
       8: ifeq          47
      11: getstatic     #9                  // Field LOG:Lorg/slf4j/Logger;
      14: new           #11                 // class java/lang/StringBuilder
      17: dup
      18: invokespecial #12                 // Method java/lang/StringBuilder."<init>":()V
      21: ldc           #13                 // String Setting space quota size for
      23: invokevirtual #14                 // Method java/lang/StringBuilder.append:(Ljava/lang/String;)Ljava/lang/StringBuilder;
      26: aload_1
      27: invokevirtual #15                 // Method java/lang/StringBuilder.append:(Ljava/lang/Object;)Ljava/lang/StringBuilder;
      30: ldc           #16                 // String  to
      32: invokevirtual #14                 // Method java/lang/StringBuilder.append:(Ljava/lang/String;)Ljava/lang/StringBuilder;
      35: lload_2
      36: invokevirtual #17                 // Method java/lang/StringBuilder.append:(J)Ljava/lang/StringBuilder;
      39: invokevirtual #18                 // Method java/lang/StringBuilder.toString:()Ljava/lang/String;
      42: invokeinterface #19,  2           // InterfaceMethod org/slf4j/Logger.trace:(Ljava/lang/String;)V
      47: aload_0
      48: getfield      #4                  // Field store:Ljava/util/concurrent/ConcurrentHashMap;
      51: aload_1
      52: lload_2
      53: invokedynamic #20,  0             // InvokeDynamic #0:apply:(J)Ljava/util/function/BiFunction;
      58: invokevirtual #21                 // Method java/util/concurrent/ConcurrentHashMap.compute:(Ljava/lang/Object;Ljava/util/function/BiFunction;)Ljava/lang/Object;
      61: pop
      62: return

  public void incrementRegionSize(org.apache.hadoop.hbase.client.RegionInfo, long);
    Code:
       0: getstatic     #9                  // Field LOG:Lorg/slf4j/Logger;
       3: invokeinterface #10,  1           // InterfaceMethod org/slf4j/Logger.isTraceEnabled:()Z
       8: ifeq          47
      11: getstatic     #9                  // Field LOG:Lorg/slf4j/Logger;
      14: new           #11                 // class java/lang/StringBuilder
      17: dup
      18: invokespecial #12                 // Method java/lang/StringBuilder."<init>":()V
      21: ldc           #22                 // String Updating space quota size for
      23: invokevirtual #14                 // Method java/lang/StringBuilder.append:(Ljava/lang/String;)Ljava/lang/StringBuilder;
      26: aload_1
      27: invokevirtual #15                 // Method java/lang/StringBuilder.append:(Ljava/lang/Object;)Ljava/lang/StringBuilder;
      30: ldc           #23                 // String  with a delta of
      32: invokevirtual #14                 // Method java/lang/StringBuilder.append:(Ljava/lang/String;)Ljava/lang/StringBuilder;
      35: lload_2
      36: invokevirtual #17                 // Method java/lang/StringBuilder.append:(J)Ljava/lang/StringBuilder;
      39: invokevirtual #18                 // Method java/lang/StringBuilder.toString:()Ljava/lang/String;
      42: invokeinterface #19,  2           // InterfaceMethod org/slf4j/Logger.trace:(Ljava/lang/String;)V
      47: aload_0
      48: getfield      #4                  // Field store:Ljava/util/concurrent/ConcurrentHashMap;
      51: aload_1
      52: lload_2
      53: invokedynamic #24,  0             // InvokeDynamic #1:apply:(J)Ljava/util/function/BiFunction;
      58: invokevirtual #21                 // Method java/util/concurrent/ConcurrentHashMap.compute:(Ljava/lang/Object;Ljava/util/function/BiFunction;)Ljava/lang/Object;
      61: pop
      62: return

  public org.apache.hadoop.hbase.quotas.RegionSize remove(org.apache.hadoop.hbase.client.RegionInfo);
    Code:
       0: aload_0
       1: getfield      #4                  // Field store:Ljava/util/concurrent/ConcurrentHashMap;
       4: aload_1
       5: invokevirtual #25                 // Method java/util/concurrent/ConcurrentHashMap.remove:(Ljava/lang/Object;)Ljava/lang/Object;
       8: checkcast     #8                  // class org/apache/hadoop/hbase/quotas/RegionSize
      11: areturn

  public long heapSize();
    Code:
       0: getstatic     #26                 // Field sizeOfEntry:J
       3: aload_0
       4: getfield      #4                  // Field store:Ljava/util/concurrent/ConcurrentHashMap;
       7: invokevirtual #27                 // Method java/util/concurrent/ConcurrentHashMap.size:()I
      10: i2l
      11: lmul
      12: lreturn

  public int size();
    Code:
       0: aload_0
       1: getfield      #4                  // Field store:Ljava/util/concurrent/ConcurrentHashMap;
       4: invokevirtual #27                 // Method java/util/concurrent/ConcurrentHashMap.size:()I
       7: ireturn

  public boolean isEmpty();
    Code:
       0: aload_0
       1: getfield      #4                  // Field store:Ljava/util/concurrent/ConcurrentHashMap;
       4: invokevirtual #28                 // Method java/util/concurrent/ConcurrentHashMap.isEmpty:()Z
       7: ireturn

  public void clear();
    Code:
       0: aload_0
       1: getfield      #4                  // Field store:Ljava/util/concurrent/ConcurrentHashMap;
       4: invokevirtual #29                 // Method java/util/concurrent/ConcurrentHashMap.clear:()V
       7: return

  static {};
    Code:
       0: ldc           #34                 // class org/apache/hadoop/hbase/quotas/RegionSizeStoreImpl
       2: invokestatic  #35                 // Method org/slf4j/LoggerFactory.getLogger:(Ljava/lang/Class;)Lorg/slf4j/Logger;
       5: putstatic     #9                  // Field LOG:Lorg/slf4j/Logger;
       8: getstatic     #36                 // Field org/apache/hadoop/hbase/util/ClassSize.CONCURRENT_HASHMAP_ENTRY:I
      11: getstatic     #37                 // Field org/apache/hadoop/hbase/util/ClassSize.OBJECT:I
      14: iadd
      15: bipush        8
      17: iadd
      18: getstatic     #37                 // Field org/apache/hadoop/hbase/util/ClassSize.OBJECT:I
      21: iadd
      22: bipush        100
      24: iadd
      25: invokestatic  #39                 // Method org/apache/hadoop/hbase/util/ClassSize.align:(I)I
      28: i2l
      29: putstatic     #26                 // Field sizeOfEntry:J
      32: return
}
