Compiled from "RegionCoprocessorHost.java"
class org.apache.hadoop.hbase.regionserver.RegionCoprocessorHost$24 extends org.apache.hadoop.hbase.regionserver.RegionCoprocessorHost$RegionObserverOperationWithoutResult {
  final org.apache.hadoop.hbase.client.Mutation val$mutation;

  final org.apache.hadoop.hbase.Cell val$kv;

  final byte[] val$byteNow;

  final org.apache.hadoop.hbase.client.Get val$get;

  final org.apache.hadoop.hbase.regionserver.RegionCoprocessorHost this$0;

  org.apache.hadoop.hbase.regionserver.RegionCoprocessorHost$24(org.apache.hadoop.hbase.regionserver.RegionCoprocessorHost, boolean, org.apache.hadoop.hbase.client.Mutation, org.apache.hadoop.hbase.Cell, byte[], org.apache.hadoop.hbase.client.Get);
    Code:
       0: aload_0
       1: aload_1
       2: putfield      #1                  // Field this$0:Lorg/apache/hadoop/hbase/regionserver/RegionCoprocessorHost;
       5: aload_0
       6: aload_3
       7: putfield      #2                  // Field val$mutation:Lorg/apache/hadoop/hbase/client/Mutation;
      10: aload_0
      11: aload         4
      13: putfield      #3                  // Field val$kv:Lorg/apache/hadoop/hbase/Cell;
      16: aload_0
      17: aload         5
      19: putfield      #4                  // Field val$byteNow:[B
      22: aload_0
      23: aload         6
      25: putfield      #5                  // Field val$get:Lorg/apache/hadoop/hbase/client/Get;
      28: aload_0
      29: aload_1
      30: iload_2
      31: invokespecial #6                  // Method org/apache/hadoop/hbase/regionserver/RegionCoprocessorHost$RegionObserverOperationWithoutResult."<init>":(Lorg/apache/hadoop/hbase/regionserver/RegionCoprocessorHost;Z)V
      34: return

  public void call(org.apache.hadoop.hbase.coprocessor.RegionObserver) throws java.io.IOException;
    Code:
       0: aload_1
       1: aload_0
       2: aload_0
       3: getfield      #2                  // Field val$mutation:Lorg/apache/hadoop/hbase/client/Mutation;
       6: aload_0
       7: getfield      #3                  // Field val$kv:Lorg/apache/hadoop/hbase/Cell;
      10: aload_0
      11: getfield      #4                  // Field val$byteNow:[B
      14: aload_0
      15: getfield      #5                  // Field val$get:Lorg/apache/hadoop/hbase/client/Get;
      18: invokeinterface #7,  6            // InterfaceMethod org/apache/hadoop/hbase/coprocessor/RegionObserver.prePrepareTimeStampForDeleteVersion:(Lorg/apache/hadoop/hbase/coprocessor/ObserverContext;Lorg/apache/hadoop/hbase/client/Mutation;Lorg/apache/hadoop/hbase/Cell;[BLorg/apache/hadoop/hbase/client/Get;)V
      23: return

  public void call(java.lang.Object) throws java.io.IOException;
    Code:
       0: aload_0
       1: aload_1
       2: checkcast     #8                  // class org/apache/hadoop/hbase/coprocessor/RegionObserver
       5: invokevirtual #9                  // Method call:(Lorg/apache/hadoop/hbase/coprocessor/RegionObserver;)V
       8: return
}
