Compiled from "RegionRemoteProcedureBase.java"
public abstract class org.apache.hadoop.hbase.master.assignment.RegionRemoteProcedureBase extends org.apache.hadoop.hbase.procedure2.Procedure<org.apache.hadoop.hbase.master.procedure.MasterProcedureEnv> implements org.apache.hadoop.hbase.master.procedure.TableProcedureInterface, org.apache.hadoop.hbase.procedure2.RemoteProcedureDispatcher$RemoteProcedure<org.apache.hadoop.hbase.master.procedure.MasterProcedureEnv, org.apache.hadoop.hbase.ServerName> {
  protected org.apache.hadoop.hbase.client.RegionInfo region;

  protected org.apache.hadoop.hbase.ServerName targetServer;

  protected org.apache.hadoop.hbase.master.assignment.RegionRemoteProcedureBase();
    Code:
       0: aload_0
       1: invokespecial #1                  // Method org/apache/hadoop/hbase/procedure2/Procedure."<init>":()V
       4: aload_0
       5: getstatic     #2                  // Field org/apache/hadoop/hbase/shaded/protobuf/generated/MasterProcedureProtos$RegionRemoteProcedureBaseState.REGION_REMOTE_PROCEDURE_DISPATCH:Lorg/apache/hadoop/hbase/shaded/protobuf/generated/MasterProcedureProtos$RegionRemoteProcedureBaseState;
       8: putfield      #3                  // Field state:Lorg/apache/hadoop/hbase/shaded/protobuf/generated/MasterProcedureProtos$RegionRemoteProcedureBaseState;
      11: return

  protected org.apache.hadoop.hbase.master.assignment.RegionRemoteProcedureBase(org.apache.hadoop.hbase.master.assignment.TransitRegionStateProcedure, org.apache.hadoop.hbase.client.RegionInfo, org.apache.hadoop.hbase.ServerName);
    Code:
       0: aload_0
       1: invokespecial #1                  // Method org/apache/hadoop/hbase/procedure2/Procedure."<init>":()V
       4: aload_0
       5: getstatic     #2                  // Field org/apache/hadoop/hbase/shaded/protobuf/generated/MasterProcedureProtos$RegionRemoteProcedureBaseState.REGION_REMOTE_PROCEDURE_DISPATCH:Lorg/apache/hadoop/hbase/shaded/protobuf/generated/MasterProcedureProtos$RegionRemoteProcedureBaseState;
       8: putfield      #3                  // Field state:Lorg/apache/hadoop/hbase/shaded/protobuf/generated/MasterProcedureProtos$RegionRemoteProcedureBaseState;
      11: aload_0
      12: aload_2
      13: putfield      #4                  // Field region:Lorg/apache/hadoop/hbase/client/RegionInfo;
      16: aload_0
      17: aload_3
      18: putfield      #5                  // Field targetServer:Lorg/apache/hadoop/hbase/ServerName;
      21: aload_1
      22: aload_0
      23: invokevirtual #6                  // Method org/apache/hadoop/hbase/master/assignment/TransitRegionStateProcedure.attachRemoteProc:(Lorg/apache/hadoop/hbase/master/assignment/RegionRemoteProcedureBase;)V
      26: return

  public java.util.Optional<org.apache.hadoop.hbase.procedure2.RemoteProcedureDispatcher$RemoteOperation> remoteCallBuild(org.apache.hadoop.hbase.master.procedure.MasterProcedureEnv, org.apache.hadoop.hbase.ServerName);
    Code:
       0: aload_0
       1: getfield      #3                  // Field state:Lorg/apache/hadoop/hbase/shaded/protobuf/generated/MasterProcedureProtos$RegionRemoteProcedureBaseState;
       4: getstatic     #7                  // Field org/apache/hadoop/hbase/shaded/protobuf/generated/MasterProcedureProtos$RegionRemoteProcedureBaseState.REGION_REMOTE_PROCEDURE_REPORT_SUCCEED:Lorg/apache/hadoop/hbase/shaded/protobuf/generated/MasterProcedureProtos$RegionRemoteProcedureBaseState;
       7: if_acmpne     14
      10: invokestatic  #8                  // Method java/util/Optional.empty:()Ljava/util/Optional;
      13: areturn
      14: aload_0
      15: invokevirtual #9                  // Method newRemoteOperation:()Lorg/apache/hadoop/hbase/procedure2/RemoteProcedureDispatcher$RemoteOperation;
      18: invokestatic  #10                 // Method java/util/Optional.of:(Ljava/lang/Object;)Ljava/util/Optional;
      21: areturn

  protected abstract org.apache.hadoop.hbase.procedure2.RemoteProcedureDispatcher$RemoteOperation newRemoteOperation();

  public void remoteOperationCompleted(org.apache.hadoop.hbase.master.procedure.MasterProcedureEnv);
    Code:
       0: new           #11                 // class java/lang/UnsupportedOperationException
       3: dup
       4: invokespecial #12                 // Method java/lang/UnsupportedOperationException."<init>":()V
       7: athrow

  public void remoteOperationFailed(org.apache.hadoop.hbase.master.procedure.MasterProcedureEnv, org.apache.hadoop.hbase.procedure2.RemoteProcedureException);
    Code:
       0: new           #11                 // class java/lang/UnsupportedOperationException
       3: dup
       4: invokespecial #12                 // Method java/lang/UnsupportedOperationException."<init>":()V
       7: athrow

  public void remoteCallFailed(org.apache.hadoop.hbase.master.procedure.MasterProcedureEnv, org.apache.hadoop.hbase.ServerName, java.io.IOException);
    Code:
       0: aload_0
       1: aload_1
       2: invokespecial #16                 // Method getRegionNode:(Lorg/apache/hadoop/hbase/master/procedure/MasterProcedureEnv;)Lorg/apache/hadoop/hbase/master/assignment/RegionStateNode;
       5: astore        4
       7: aload         4
       9: invokevirtual #17                 // Method org/apache/hadoop/hbase/master/assignment/RegionStateNode.lock:()V
      12: aload_1
      13: invokevirtual #18                 // Method org/apache/hadoop/hbase/master/procedure/MasterProcedureEnv.getMasterServices:()Lorg/apache/hadoop/hbase/master/MasterServices;
      16: invokeinterface #19,  1           // InterfaceMethod org/apache/hadoop/hbase/master/MasterServices.getServerManager:()Lorg/apache/hadoop/hbase/master/ServerManager;
      21: aload_2
      22: invokevirtual #20                 // Method org/apache/hadoop/hbase/master/ServerManager.isServerOnline:(Lorg/apache/hadoop/hbase/ServerName;)Z
      25: ifne          61
      28: getstatic     #21                 // Field LOG:Lorg/slf4j/Logger;
      31: ldc           #22                 // String {} for region {}, targetServer {} is dead, SCP will interrupt us, give up
      33: iconst_3
      34: anewarray     #23                 // class java/lang/Object
      37: dup
      38: iconst_0
      39: aload_0
      40: aastore
      41: dup
      42: iconst_1
      43: aload         4
      45: aastore
      46: dup
      47: iconst_2
      48: aload_2
      49: aastore
      50: invokeinterface #24,  3           // InterfaceMethod org/slf4j/Logger.debug:(Ljava/lang/String;[Ljava/lang/Object;)V
      55: aload         4
      57: invokevirtual #25                 // Method org/apache/hadoop/hbase/master/assignment/RegionStateNode.unlock:()V
      60: return
      61: aload_0
      62: getfield      #3                  // Field state:Lorg/apache/hadoop/hbase/shaded/protobuf/generated/MasterProcedureProtos$RegionRemoteProcedureBaseState;
      65: getstatic     #2                  // Field org/apache/hadoop/hbase/shaded/protobuf/generated/MasterProcedureProtos$RegionRemoteProcedureBaseState.REGION_REMOTE_PROCEDURE_DISPATCH:Lorg/apache/hadoop/hbase/shaded/protobuf/generated/MasterProcedureProtos$RegionRemoteProcedureBaseState;
      68: if_acmpeq     104
      71: getstatic     #21                 // Field LOG:Lorg/slf4j/Logger;
      74: ldc           #26                 // String {} for region {}, targetServer={} has already been woken up, ignore
      76: iconst_3
      77: anewarray     #23                 // class java/lang/Object
      80: dup
      81: iconst_0
      82: aload_0
      83: aastore
      84: dup
      85: iconst_1
      86: aload         4
      88: aastore
      89: dup
      90: iconst_2
      91: aload_2
      92: aastore
      93: invokeinterface #27,  3           // InterfaceMethod org/slf4j/Logger.warn:(Ljava/lang/String;[Ljava/lang/Object;)V
      98: aload         4
     100: invokevirtual #25                 // Method org/apache/hadoop/hbase/master/assignment/RegionStateNode.unlock:()V
     103: return
     104: getstatic     #21                 // Field LOG:Lorg/slf4j/Logger;
     107: ldc           #28                 // String The remote operation {} for region {} to server {} failed
     109: iconst_4
     110: anewarray     #23                 // class java/lang/Object
     113: dup
     114: iconst_0
     115: aload_0
     116: aastore
     117: dup
     118: iconst_1
     119: aload         4
     121: aastore
     122: dup
     123: iconst_2
     124: aload_2
     125: aastore
     126: dup
     127: iconst_3
     128: aload_3
     129: aastore
     130: invokeinterface #27,  3           // InterfaceMethod org/slf4j/Logger.warn:(Ljava/lang/String;[Ljava/lang/Object;)V
     135: aload_0
     136: getstatic     #29                 // Field org/apache/hadoop/hbase/shaded/protobuf/generated/MasterProcedureProtos$RegionRemoteProcedureBaseState.REGION_REMOTE_PROCEDURE_DISPATCH_FAIL:Lorg/apache/hadoop/hbase/shaded/protobuf/generated/MasterProcedureProtos$RegionRemoteProcedureBaseState;
     139: putfield      #3                  // Field state:Lorg/apache/hadoop/hbase/shaded/protobuf/generated/MasterProcedureProtos$RegionRemoteProcedureBaseState;
     142: aload         4
     144: invokevirtual #30                 // Method org/apache/hadoop/hbase/master/assignment/RegionStateNode.getProcedureEvent:()Lorg/apache/hadoop/hbase/procedure2/ProcedureEvent;
     147: aload_1
     148: invokevirtual #31                 // Method org/apache/hadoop/hbase/master/procedure/MasterProcedureEnv.getProcedureScheduler:()Lorg/apache/hadoop/hbase/master/procedure/MasterProcedureScheduler;
     151: invokevirtual #32                 // Method org/apache/hadoop/hbase/procedure2/ProcedureEvent.wake:(Lorg/apache/hadoop/hbase/procedure2/AbstractProcedureScheduler;)V
     154: aload         4
     156: invokevirtual #25                 // Method org/apache/hadoop/hbase/master/assignment/RegionStateNode.unlock:()V
     159: goto          172
     162: astore        5
     164: aload         4
     166: invokevirtual #25                 // Method org/apache/hadoop/hbase/master/assignment/RegionStateNode.unlock:()V
     169: aload         5
     171: athrow
     172: return
    Exception table:
       from    to  target type
          12    55   162   any
          61    98   162   any
         104   154   162   any
         162   164   162   any

  public org.apache.hadoop.hbase.TableName getTableName();
    Code:
       0: aload_0
       1: getfield      #4                  // Field region:Lorg/apache/hadoop/hbase/client/RegionInfo;
       4: invokeinterface #33,  1           // InterfaceMethod org/apache/hadoop/hbase/client/RegionInfo.getTable:()Lorg/apache/hadoop/hbase/TableName;
       9: areturn

  protected boolean waitInitialized(org.apache.hadoop.hbase.master.procedure.MasterProcedureEnv);
    Code:
       0: aload_0
       1: invokevirtual #34                 // Method getTableName:()Lorg/apache/hadoop/hbase/TableName;
       4: invokestatic  #35                 // Method org/apache/hadoop/hbase/TableName.isMetaTableName:(Lorg/apache/hadoop/hbase/TableName;)Z
       7: ifeq          12
      10: iconst_0
      11: ireturn
      12: aload_1
      13: invokevirtual #13                 // Method org/apache/hadoop/hbase/master/procedure/MasterProcedureEnv.getAssignmentManager:()Lorg/apache/hadoop/hbase/master/assignment/AssignmentManager;
      16: astore_2
      17: aload_2
      18: aload_0
      19: invokevirtual #36                 // Method org/apache/hadoop/hbase/master/assignment/AssignmentManager.waitMetaLoaded:(Lorg/apache/hadoop/hbase/procedure2/Procedure;)Z
      22: ifne          37
      25: aload_2
      26: aload_0
      27: aload_0
      28: getfield      #4                  // Field region:Lorg/apache/hadoop/hbase/client/RegionInfo;
      31: invokevirtual #37                 // Method org/apache/hadoop/hbase/master/assignment/AssignmentManager.waitMetaAssigned:(Lorg/apache/hadoop/hbase/procedure2/Procedure;Lorg/apache/hadoop/hbase/client/RegionInfo;)Z
      34: ifeq          41
      37: iconst_1
      38: goto          42
      41: iconst_0
      42: ireturn

  protected void rollback(org.apache.hadoop.hbase.master.procedure.MasterProcedureEnv) throws java.io.IOException, java.lang.InterruptedException;
    Code:
       0: new           #11                 // class java/lang/UnsupportedOperationException
       3: dup
       4: invokespecial #12                 // Method java/lang/UnsupportedOperationException."<init>":()V
       7: athrow

  protected boolean abort(org.apache.hadoop.hbase.master.procedure.MasterProcedureEnv);
    Code:
       0: iconst_0
       1: ireturn

  protected abstract void checkTransition(org.apache.hadoop.hbase.master.assignment.RegionStateNode, org.apache.hadoop.hbase.shaded.protobuf.generated.RegionServerStatusProtos$RegionStateTransition$TransitionCode, long) throws org.apache.hadoop.hbase.exceptions.UnexpectedStateException;

  protected abstract void updateTransitionWithoutPersistingToMeta(org.apache.hadoop.hbase.master.procedure.MasterProcedureEnv, org.apache.hadoop.hbase.master.assignment.RegionStateNode, org.apache.hadoop.hbase.shaded.protobuf.generated.RegionServerStatusProtos$RegionStateTransition$TransitionCode, long) throws java.io.IOException;

  void reportTransition(org.apache.hadoop.hbase.master.procedure.MasterProcedureEnv, org.apache.hadoop.hbase.master.assignment.RegionStateNode, org.apache.hadoop.hbase.ServerName, org.apache.hadoop.hbase.shaded.protobuf.generated.RegionServerStatusProtos$RegionStateTransition$TransitionCode, long) throws java.io.IOException;
    Code:
       0: aload_0
       1: getfield      #3                  // Field state:Lorg/apache/hadoop/hbase/shaded/protobuf/generated/MasterProcedureProtos$RegionRemoteProcedureBaseState;
       4: getstatic     #2                  // Field org/apache/hadoop/hbase/shaded/protobuf/generated/MasterProcedureProtos$RegionRemoteProcedureBaseState.REGION_REMOTE_PROCEDURE_DISPATCH:Lorg/apache/hadoop/hbase/shaded/protobuf/generated/MasterProcedureProtos$RegionRemoteProcedureBaseState;
       7: if_acmpeq     11
      10: return
      11: aload_0
      12: getfield      #5                  // Field targetServer:Lorg/apache/hadoop/hbase/ServerName;
      15: aload_3
      16: invokevirtual #41                 // Method org/apache/hadoop/hbase/ServerName.equals:(Ljava/lang/Object;)Z
      19: ifne          79
      22: new           #42                 // class org/apache/hadoop/hbase/exceptions/UnexpectedStateException
      25: dup
      26: new           #43                 // class java/lang/StringBuilder
      29: dup
      30: invokespecial #44                 // Method java/lang/StringBuilder."<init>":()V
      33: ldc           #45                 // String Received report from
      35: invokevirtual #46                 // Method java/lang/StringBuilder.append:(Ljava/lang/String;)Ljava/lang/StringBuilder;
      38: aload_3
      39: invokevirtual #47                 // Method java/lang/StringBuilder.append:(Ljava/lang/Object;)Ljava/lang/StringBuilder;
      42: ldc           #48                 // String , expected
      44: invokevirtual #46                 // Method java/lang/StringBuilder.append:(Ljava/lang/String;)Ljava/lang/StringBuilder;
      47: aload_0
      48: getfield      #5                  // Field targetServer:Lorg/apache/hadoop/hbase/ServerName;
      51: invokevirtual #47                 // Method java/lang/StringBuilder.append:(Ljava/lang/Object;)Ljava/lang/StringBuilder;
      54: ldc           #49                 // String ,
      56: invokevirtual #46                 // Method java/lang/StringBuilder.append:(Ljava/lang/String;)Ljava/lang/StringBuilder;
      59: aload_2
      60: invokevirtual #47                 // Method java/lang/StringBuilder.append:(Ljava/lang/Object;)Ljava/lang/StringBuilder;
      63: ldc           #50                 // String , proc=
      65: invokevirtual #46                 // Method java/lang/StringBuilder.append:(Ljava/lang/String;)Ljava/lang/StringBuilder;
      68: aload_0
      69: invokevirtual #47                 // Method java/lang/StringBuilder.append:(Ljava/lang/Object;)Ljava/lang/StringBuilder;
      72: invokevirtual #51                 // Method java/lang/StringBuilder.toString:()Ljava/lang/String;
      75: invokespecial #52                 // Method org/apache/hadoop/hbase/exceptions/UnexpectedStateException."<init>":(Ljava/lang/String;)V
      78: athrow
      79: aload_0
      80: aload_2
      81: aload         4
      83: lload         5
      85: invokevirtual #53                 // Method checkTransition:(Lorg/apache/hadoop/hbase/master/assignment/RegionStateNode;Lorg/apache/hadoop/hbase/shaded/protobuf/generated/RegionServerStatusProtos$RegionStateTransition$TransitionCode;J)V
      88: aload_0
      89: getstatic     #7                  // Field org/apache/hadoop/hbase/shaded/protobuf/generated/MasterProcedureProtos$RegionRemoteProcedureBaseState.REGION_REMOTE_PROCEDURE_REPORT_SUCCEED:Lorg/apache/hadoop/hbase/shaded/protobuf/generated/MasterProcedureProtos$RegionRemoteProcedureBaseState;
      92: putfield      #3                  // Field state:Lorg/apache/hadoop/hbase/shaded/protobuf/generated/MasterProcedureProtos$RegionRemoteProcedureBaseState;
      95: aload_0
      96: aload         4
      98: putfield      #54                 // Field transitionCode:Lorg/apache/hadoop/hbase/shaded/protobuf/generated/RegionServerStatusProtos$RegionStateTransition$TransitionCode;
     101: aload_0
     102: lload         5
     104: putfield      #55                 // Field seqId:J
     107: iconst_0
     108: istore        7
     110: aload_0
     111: aload_1
     112: aload_2
     113: invokespecial #56                 // Method persistAndWake:(Lorg/apache/hadoop/hbase/master/procedure/MasterProcedureEnv;Lorg/apache/hadoop/hbase/master/assignment/RegionStateNode;)V
     116: iconst_1
     117: istore        7
     119: iload         7
     121: ifne          175
     124: aload_0
     125: getstatic     #2                  // Field org/apache/hadoop/hbase/shaded/protobuf/generated/MasterProcedureProtos$RegionRemoteProcedureBaseState.REGION_REMOTE_PROCEDURE_DISPATCH:Lorg/apache/hadoop/hbase/shaded/protobuf/generated/MasterProcedureProtos$RegionRemoteProcedureBaseState;
     128: putfield      #3                  // Field state:Lorg/apache/hadoop/hbase/shaded/protobuf/generated/MasterProcedureProtos$RegionRemoteProcedureBaseState;
     131: aload_0
     132: aconst_null
     133: putfield      #54                 // Field transitionCode:Lorg/apache/hadoop/hbase/shaded/protobuf/generated/RegionServerStatusProtos$RegionStateTransition$TransitionCode;
     136: aload_0
     137: ldc2_w        #58                 // long -1l
     140: putfield      #55                 // Field seqId:J
     143: goto          175
     146: astore        8
     148: iload         7
     150: ifne          172
     153: aload_0
     154: getstatic     #2                  // Field org/apache/hadoop/hbase/shaded/protobuf/generated/MasterProcedureProtos$RegionRemoteProcedureBaseState.REGION_REMOTE_PROCEDURE_DISPATCH:Lorg/apache/hadoop/hbase/shaded/protobuf/generated/MasterProcedureProtos$RegionRemoteProcedureBaseState;
     157: putfield      #3                  // Field state:Lorg/apache/hadoop/hbase/shaded/protobuf/generated/MasterProcedureProtos$RegionRemoteProcedureBaseState;
     160: aload_0
     161: aconst_null
     162: putfield      #54                 // Field transitionCode:Lorg/apache/hadoop/hbase/shaded/protobuf/generated/RegionServerStatusProtos$RegionStateTransition$TransitionCode;
     165: aload_0
     166: ldc2_w        #58                 // long -1l
     169: putfield      #55                 // Field seqId:J
     172: aload         8
     174: athrow
     175: aload_0
     176: aload_1
     177: aload_2
     178: aload         4
     180: lload         5
     182: invokevirtual #60                 // Method updateTransitionWithoutPersistingToMeta:(Lorg/apache/hadoop/hbase/master/procedure/MasterProcedureEnv;Lorg/apache/hadoop/hbase/master/assignment/RegionStateNode;Lorg/apache/hadoop/hbase/shaded/protobuf/generated/RegionServerStatusProtos$RegionStateTransition$TransitionCode;J)V
     185: goto          202
     188: astore        8
     190: new           #62                 // class java/lang/AssertionError
     193: dup
     194: ldc           #63                 // String should not happen
     196: aload         8
     198: invokespecial #64                 // Method java/lang/AssertionError."<init>":(Ljava/lang/String;Ljava/lang/Throwable;)V
     201: athrow
     202: return
    Exception table:
       from    to  target type
         110   119   146   any
         146   148   146   any
         175   185   188   Class java/io/IOException

  void serverCrashed(org.apache.hadoop.hbase.master.procedure.MasterProcedureEnv, org.apache.hadoop.hbase.master.assignment.RegionStateNode, org.apache.hadoop.hbase.ServerName);
    Code:
       0: aload_0
       1: getfield      #3                  // Field state:Lorg/apache/hadoop/hbase/shaded/protobuf/generated/MasterProcedureProtos$RegionRemoteProcedureBaseState;
       4: getstatic     #65                 // Field org/apache/hadoop/hbase/shaded/protobuf/generated/MasterProcedureProtos$RegionRemoteProcedureBaseState.REGION_REMOTE_PROCEDURE_SERVER_CRASH:Lorg/apache/hadoop/hbase/shaded/protobuf/generated/MasterProcedureProtos$RegionRemoteProcedureBaseState;
       7: if_acmpne     11
      10: return
      11: aload_0
      12: getfield      #3                  // Field state:Lorg/apache/hadoop/hbase/shaded/protobuf/generated/MasterProcedureProtos$RegionRemoteProcedureBaseState;
      15: astore        4
      17: aload_0
      18: getstatic     #65                 // Field org/apache/hadoop/hbase/shaded/protobuf/generated/MasterProcedureProtos$RegionRemoteProcedureBaseState.REGION_REMOTE_PROCEDURE_SERVER_CRASH:Lorg/apache/hadoop/hbase/shaded/protobuf/generated/MasterProcedureProtos$RegionRemoteProcedureBaseState;
      21: putfield      #3                  // Field state:Lorg/apache/hadoop/hbase/shaded/protobuf/generated/MasterProcedureProtos$RegionRemoteProcedureBaseState;
      24: iconst_0
      25: istore        5
      27: aload_0
      28: aload_1
      29: aload_2
      30: invokespecial #56                 // Method persistAndWake:(Lorg/apache/hadoop/hbase/master/procedure/MasterProcedureEnv;Lorg/apache/hadoop/hbase/master/assignment/RegionStateNode;)V
      33: iconst_1
      34: istore        5
      36: iload         5
      38: ifne          66
      41: aload_0
      42: aload         4
      44: putfield      #3                  // Field state:Lorg/apache/hadoop/hbase/shaded/protobuf/generated/MasterProcedureProtos$RegionRemoteProcedureBaseState;
      47: goto          66
      50: astore        6
      52: iload         5
      54: ifne          63
      57: aload_0
      58: aload         4
      60: putfield      #3                  // Field state:Lorg/apache/hadoop/hbase/shaded/protobuf/generated/MasterProcedureProtos$RegionRemoteProcedureBaseState;
      63: aload         6
      65: athrow
      66: return
    Exception table:
       from    to  target type
          27    36    50   any
          50    52    50   any

  protected abstract void restoreSucceedState(org.apache.hadoop.hbase.master.assignment.AssignmentManager, org.apache.hadoop.hbase.master.assignment.RegionStateNode, long) throws java.io.IOException;

  void stateLoaded(org.apache.hadoop.hbase.master.assignment.AssignmentManager, org.apache.hadoop.hbase.master.assignment.RegionStateNode);
    Code:
       0: aload_0
       1: getfield      #3                  // Field state:Lorg/apache/hadoop/hbase/shaded/protobuf/generated/MasterProcedureProtos$RegionRemoteProcedureBaseState;
       4: getstatic     #7                  // Field org/apache/hadoop/hbase/shaded/protobuf/generated/MasterProcedureProtos$RegionRemoteProcedureBaseState.REGION_REMOTE_PROCEDURE_REPORT_SUCCEED:Lorg/apache/hadoop/hbase/shaded/protobuf/generated/MasterProcedureProtos$RegionRemoteProcedureBaseState;
       7: if_acmpne     33
      10: aload_0
      11: aload_1
      12: aload_2
      13: aload_0
      14: getfield      #55                 // Field seqId:J
      17: invokevirtual #66                 // Method restoreSucceedState:(Lorg/apache/hadoop/hbase/master/assignment/AssignmentManager;Lorg/apache/hadoop/hbase/master/assignment/RegionStateNode;J)V
      20: goto          33
      23: astore_3
      24: new           #62                 // class java/lang/AssertionError
      27: dup
      28: aload_3
      29: invokespecial #67                 // Method java/lang/AssertionError."<init>":(Ljava/lang/Object;)V
      32: athrow
      33: return
    Exception table:
       from    to  target type
          10    20    23   Class java/io/IOException

  protected org.apache.hadoop.hbase.procedure2.Procedure<org.apache.hadoop.hbase.master.procedure.MasterProcedureEnv>[] execute(org.apache.hadoop.hbase.master.procedure.MasterProcedureEnv) throws org.apache.hadoop.hbase.procedure2.ProcedureYieldException, org.apache.hadoop.hbase.procedure2.ProcedureSuspendedException, java.lang.InterruptedException;
    Code:
       0: aload_0
       1: aload_1
       2: invokespecial #16                 // Method getRegionNode:(Lorg/apache/hadoop/hbase/master/procedure/MasterProcedureEnv;)Lorg/apache/hadoop/hbase/master/assignment/RegionStateNode;
       5: astore_2
       6: aload_2
       7: invokevirtual #17                 // Method org/apache/hadoop/hbase/master/assignment/RegionStateNode.lock:()V
      10: getstatic     #73                 // Field org/apache/hadoop/hbase/master/assignment/RegionRemoteProcedureBase$1.$SwitchMap$org$apache$hadoop$hbase$shaded$protobuf$generated$MasterProcedureProtos$RegionRemoteProcedureBaseState:[I
      13: aload_0
      14: getfield      #3                  // Field state:Lorg/apache/hadoop/hbase/shaded/protobuf/generated/MasterProcedureProtos$RegionRemoteProcedureBaseState;
      17: invokevirtual #74                 // Method org/apache/hadoop/hbase/shaded/protobuf/generated/MasterProcedureProtos$RegionRemoteProcedureBaseState.ordinal:()I
      20: iaload
      21: tableswitch   { // 1 to 4
                     1: 52
                     2: 144
                     3: 165
                     4: 178
               default: 199
          }
      52: aload_2
      53: invokevirtual #30                 // Method org/apache/hadoop/hbase/master/assignment/RegionStateNode.getProcedureEvent:()Lorg/apache/hadoop/hbase/procedure2/ProcedureEvent;
      56: astore_3
      57: aload_1
      58: invokevirtual #75                 // Method org/apache/hadoop/hbase/master/procedure/MasterProcedureEnv.getRemoteDispatcher:()Lorg/apache/hadoop/hbase/master/procedure/RSProcedureDispatcher;
      61: aload_0
      62: getfield      #5                  // Field targetServer:Lorg/apache/hadoop/hbase/ServerName;
      65: aload_0
      66: invokevirtual #76                 // Method org/apache/hadoop/hbase/master/procedure/RSProcedureDispatcher.addOperationToNode:(Ljava/lang/Comparable;Lorg/apache/hadoop/hbase/procedure2/RemoteProcedureDispatcher$RemoteProcedure;)V
      69: goto          126
      72: astore        4
      74: getstatic     #21                 // Field LOG:Lorg/slf4j/Logger;
      77: ldc           #78                 // String Can not add remote operation {} for region {} to server {}, this usually because the server is alread dead, give up and mark the procedure as complete, the parent procedure will take care of this.
      79: iconst_4
      80: anewarray     #23                 // class java/lang/Object
      83: dup
      84: iconst_0
      85: aload_0
      86: aastore
      87: dup
      88: iconst_1
      89: aload_0
      90: getfield      #4                  // Field region:Lorg/apache/hadoop/hbase/client/RegionInfo;
      93: aastore
      94: dup
      95: iconst_2
      96: aload_0
      97: getfield      #5                  // Field targetServer:Lorg/apache/hadoop/hbase/ServerName;
     100: aastore
     101: dup
     102: iconst_3
     103: aload         4
     105: aastore
     106: invokeinterface #27,  3           // InterfaceMethod org/slf4j/Logger.warn:(Ljava/lang/String;[Ljava/lang/Object;)V
     111: aload_0
     112: aload_1
     113: invokespecial #79                 // Method unattach:(Lorg/apache/hadoop/hbase/master/procedure/MasterProcedureEnv;)V
     116: aconst_null
     117: astore        5
     119: aload_2
     120: invokevirtual #25                 // Method org/apache/hadoop/hbase/master/assignment/RegionStateNode.unlock:()V
     123: aload         5
     125: areturn
     126: aload_3
     127: invokevirtual #80                 // Method org/apache/hadoop/hbase/procedure2/ProcedureEvent.suspend:()V
     130: aload_3
     131: aload_0
     132: invokevirtual #81                 // Method org/apache/hadoop/hbase/procedure2/ProcedureEvent.suspendIfNotReady:(Lorg/apache/hadoop/hbase/procedure2/Procedure;)Z
     135: pop
     136: new           #82                 // class org/apache/hadoop/hbase/procedure2/ProcedureSuspendedException
     139: dup
     140: invokespecial #83                 // Method org/apache/hadoop/hbase/procedure2/ProcedureSuspendedException."<init>":()V
     143: athrow
     144: aload_1
     145: invokevirtual #13                 // Method org/apache/hadoop/hbase/master/procedure/MasterProcedureEnv.getAssignmentManager:()Lorg/apache/hadoop/hbase/master/assignment/AssignmentManager;
     148: aload_2
     149: invokevirtual #84                 // Method org/apache/hadoop/hbase/master/assignment/AssignmentManager.persistToMeta:(Lorg/apache/hadoop/hbase/master/assignment/RegionStateNode;)V
     152: aload_0
     153: aload_1
     154: invokespecial #79                 // Method unattach:(Lorg/apache/hadoop/hbase/master/procedure/MasterProcedureEnv;)V
     157: aconst_null
     158: astore_3
     159: aload_2
     160: invokevirtual #25                 // Method org/apache/hadoop/hbase/master/assignment/RegionStateNode.unlock:()V
     163: aload_3
     164: areturn
     165: aload_0
     166: aload_1
     167: invokespecial #79                 // Method unattach:(Lorg/apache/hadoop/hbase/master/procedure/MasterProcedureEnv;)V
     170: aconst_null
     171: astore_3
     172: aload_2
     173: invokevirtual #25                 // Method org/apache/hadoop/hbase/master/assignment/RegionStateNode.unlock:()V
     176: aload_3
     177: areturn
     178: aload_1
     179: invokevirtual #13                 // Method org/apache/hadoop/hbase/master/procedure/MasterProcedureEnv.getAssignmentManager:()Lorg/apache/hadoop/hbase/master/assignment/AssignmentManager;
     182: aload_2
     183: invokevirtual #85                 // Method org/apache/hadoop/hbase/master/assignment/AssignmentManager.regionClosedAbnormally:(Lorg/apache/hadoop/hbase/master/assignment/RegionStateNode;)V
     186: aload_0
     187: aload_1
     188: invokespecial #79                 // Method unattach:(Lorg/apache/hadoop/hbase/master/procedure/MasterProcedureEnv;)V
     191: aconst_null
     192: astore_3
     193: aload_2
     194: invokevirtual #25                 // Method org/apache/hadoop/hbase/master/assignment/RegionStateNode.unlock:()V
     197: aload_3
     198: areturn
     199: new           #86                 // class java/lang/IllegalStateException
     202: dup
     203: new           #43                 // class java/lang/StringBuilder
     206: dup
     207: invokespecial #44                 // Method java/lang/StringBuilder."<init>":()V
     210: ldc           #87                 // String Unknown state:
     212: invokevirtual #46                 // Method java/lang/StringBuilder.append:(Ljava/lang/String;)Ljava/lang/StringBuilder;
     215: aload_0
     216: getfield      #3                  // Field state:Lorg/apache/hadoop/hbase/shaded/protobuf/generated/MasterProcedureProtos$RegionRemoteProcedureBaseState;
     219: invokevirtual #47                 // Method java/lang/StringBuilder.append:(Ljava/lang/Object;)Ljava/lang/StringBuilder;
     222: invokevirtual #51                 // Method java/lang/StringBuilder.toString:()Ljava/lang/String;
     225: invokespecial #88                 // Method java/lang/IllegalStateException."<init>":(Ljava/lang/String;)V
     228: athrow
     229: astore_3
     230: aload_0
     231: getfield      #89                 // Field retryCounter:Lorg/apache/hadoop/hbase/util/RetryCounter;
     234: ifnonnull     248
     237: aload_0
     238: aload_1
     239: invokevirtual #90                 // Method org/apache/hadoop/hbase/master/procedure/MasterProcedureEnv.getMasterConfiguration:()Lorg/apache/hadoop/conf/Configuration;
     242: invokestatic  #91                 // Method org/apache/hadoop/hbase/procedure2/ProcedureUtil.createRetryCounter:(Lorg/apache/hadoop/conf/Configuration;)Lorg/apache/hadoop/hbase/util/RetryCounter;
     245: putfield      #89                 // Field retryCounter:Lorg/apache/hadoop/hbase/util/RetryCounter;
     248: aload_0
     249: getfield      #89                 // Field retryCounter:Lorg/apache/hadoop/hbase/util/RetryCounter;
     252: invokevirtual #92                 // Method org/apache/hadoop/hbase/util/RetryCounter.getBackoffTimeAndIncrementAttempts:()J
     255: lstore        4
     257: getstatic     #21                 // Field LOG:Lorg/slf4j/Logger;
     260: ldc           #93                 // String Failed updating meta, suspend {}secs {}; {};
     262: iconst_4
     263: anewarray     #23                 // class java/lang/Object
     266: dup
     267: iconst_0
     268: lload         4
     270: ldc2_w        #94                 // long 1000l
     273: ldiv
     274: invokestatic  #96                 // Method java/lang/Long.valueOf:(J)Ljava/lang/Long;
     277: aastore
     278: dup
     279: iconst_1
     280: aload_0
     281: aastore
     282: dup
     283: iconst_2
     284: aload_2
     285: aastore
     286: dup
     287: iconst_3
     288: aload_3
     289: aastore
     290: invokeinterface #27,  3           // InterfaceMethod org/slf4j/Logger.warn:(Ljava/lang/String;[Ljava/lang/Object;)V
     295: aload_0
     296: lload         4
     298: invokestatic  #97                 // Method java/lang/Math.toIntExact:(J)I
     301: invokevirtual #98                 // Method setTimeout:(I)V
     304: aload_0
     305: getstatic     #99                 // Field org/apache/hadoop/hbase/shaded/protobuf/generated/ProcedureProtos$ProcedureState.WAITING_TIMEOUT:Lorg/apache/hadoop/hbase/shaded/protobuf/generated/ProcedureProtos$ProcedureState;
     308: invokevirtual #100                // Method setState:(Lorg/apache/hadoop/hbase/shaded/protobuf/generated/ProcedureProtos$ProcedureState;)V
     311: aload_0
     312: invokevirtual #101                // Method skipPersistence:()V
     315: new           #82                 // class org/apache/hadoop/hbase/procedure2/ProcedureSuspendedException
     318: dup
     319: invokespecial #83                 // Method org/apache/hadoop/hbase/procedure2/ProcedureSuspendedException."<init>":()V
     322: athrow
     323: astore        6
     325: aload_2
     326: invokevirtual #25                 // Method org/apache/hadoop/hbase/master/assignment/RegionStateNode.unlock:()V
     329: aload         6
     331: athrow
    Exception table:
       from    to  target type
          57    69    72   Class org/apache/hadoop/hbase/procedure2/FailedRemoteDispatchException
          10   119   229   Class java/io/IOException
         126   159   229   Class java/io/IOException
         165   172   229   Class java/io/IOException
         178   193   229   Class java/io/IOException
         199   229   229   Class java/io/IOException
          10   119   323   any
         126   159   323   any
         165   172   323   any
         178   193   323   any
         199   325   323   any

  public boolean storeInDispatchedQueue();
    Code:
       0: iconst_0
       1: ireturn

  protected void serializeStateData(org.apache.hadoop.hbase.procedure2.ProcedureStateSerializer) throws java.io.IOException;
    Code:
       0: invokestatic  #102                // Method org/apache/hadoop/hbase/shaded/protobuf/generated/MasterProcedureProtos$RegionRemoteProcedureBaseStateData.newBuilder:()Lorg/apache/hadoop/hbase/shaded/protobuf/generated/MasterProcedureProtos$RegionRemoteProcedureBaseStateData$Builder;
       3: aload_0
       4: getfield      #4                  // Field region:Lorg/apache/hadoop/hbase/client/RegionInfo;
       7: invokestatic  #103                // Method org/apache/hadoop/hbase/shaded/protobuf/ProtobufUtil.toRegionInfo:(Lorg/apache/hadoop/hbase/client/RegionInfo;)Lorg/apache/hadoop/hbase/shaded/protobuf/generated/HBaseProtos$RegionInfo;
      10: invokevirtual #104                // Method org/apache/hadoop/hbase/shaded/protobuf/generated/MasterProcedureProtos$RegionRemoteProcedureBaseStateData$Builder.setRegion:(Lorg/apache/hadoop/hbase/shaded/protobuf/generated/HBaseProtos$RegionInfo;)Lorg/apache/hadoop/hbase/shaded/protobuf/generated/MasterProcedureProtos$RegionRemoteProcedureBaseStateData$Builder;
      13: aload_0
      14: getfield      #5                  // Field targetServer:Lorg/apache/hadoop/hbase/ServerName;
      17: invokestatic  #105                // Method org/apache/hadoop/hbase/shaded/protobuf/ProtobufUtil.toServerName:(Lorg/apache/hadoop/hbase/ServerName;)Lorg/apache/hadoop/hbase/shaded/protobuf/generated/HBaseProtos$ServerName;
      20: invokevirtual #106                // Method org/apache/hadoop/hbase/shaded/protobuf/generated/MasterProcedureProtos$RegionRemoteProcedureBaseStateData$Builder.setTargetServer:(Lorg/apache/hadoop/hbase/shaded/protobuf/generated/HBaseProtos$ServerName;)Lorg/apache/hadoop/hbase/shaded/protobuf/generated/MasterProcedureProtos$RegionRemoteProcedureBaseStateData$Builder;
      23: aload_0
      24: getfield      #3                  // Field state:Lorg/apache/hadoop/hbase/shaded/protobuf/generated/MasterProcedureProtos$RegionRemoteProcedureBaseState;
      27: invokevirtual #107                // Method org/apache/hadoop/hbase/shaded/protobuf/generated/MasterProcedureProtos$RegionRemoteProcedureBaseStateData$Builder.setState:(Lorg/apache/hadoop/hbase/shaded/protobuf/generated/MasterProcedureProtos$RegionRemoteProcedureBaseState;)Lorg/apache/hadoop/hbase/shaded/protobuf/generated/MasterProcedureProtos$RegionRemoteProcedureBaseStateData$Builder;
      30: astore_2
      31: aload_0
      32: getfield      #54                 // Field transitionCode:Lorg/apache/hadoop/hbase/shaded/protobuf/generated/RegionServerStatusProtos$RegionStateTransition$TransitionCode;
      35: ifnull        56
      38: aload_2
      39: aload_0
      40: getfield      #54                 // Field transitionCode:Lorg/apache/hadoop/hbase/shaded/protobuf/generated/RegionServerStatusProtos$RegionStateTransition$TransitionCode;
      43: invokevirtual #108                // Method org/apache/hadoop/hbase/shaded/protobuf/generated/MasterProcedureProtos$RegionRemoteProcedureBaseStateData$Builder.setTransitionCode:(Lorg/apache/hadoop/hbase/shaded/protobuf/generated/RegionServerStatusProtos$RegionStateTransition$TransitionCode;)Lorg/apache/hadoop/hbase/shaded/protobuf/generated/MasterProcedureProtos$RegionRemoteProcedureBaseStateData$Builder;
      46: pop
      47: aload_2
      48: aload_0
      49: getfield      #55                 // Field seqId:J
      52: invokevirtual #109                // Method org/apache/hadoop/hbase/shaded/protobuf/generated/MasterProcedureProtos$RegionRemoteProcedureBaseStateData$Builder.setSeqId:(J)Lorg/apache/hadoop/hbase/shaded/protobuf/generated/MasterProcedureProtos$RegionRemoteProcedureBaseStateData$Builder;
      55: pop
      56: aload_1
      57: aload_2
      58: invokevirtual #110                // Method org/apache/hadoop/hbase/shaded/protobuf/generated/MasterProcedureProtos$RegionRemoteProcedureBaseStateData$Builder.build:()Lorg/apache/hadoop/hbase/shaded/protobuf/generated/MasterProcedureProtos$RegionRemoteProcedureBaseStateData;
      61: invokeinterface #111,  2          // InterfaceMethod org/apache/hadoop/hbase/procedure2/ProcedureStateSerializer.serialize:(Lorg/apache/hbase/thirdparty/com/google/protobuf/Message;)V
      66: return

  protected void deserializeStateData(org.apache.hadoop.hbase.procedure2.ProcedureStateSerializer) throws java.io.IOException;
    Code:
       0: aload_1
       1: ldc           #112                // class org/apache/hadoop/hbase/shaded/protobuf/generated/MasterProcedureProtos$RegionRemoteProcedureBaseStateData
       3: invokeinterface #113,  2          // InterfaceMethod org/apache/hadoop/hbase/procedure2/ProcedureStateSerializer.deserialize:(Ljava/lang/Class;)Lorg/apache/hbase/thirdparty/com/google/protobuf/Message;
       8: checkcast     #112                // class org/apache/hadoop/hbase/shaded/protobuf/generated/MasterProcedureProtos$RegionRemoteProcedureBaseStateData
      11: astore_2
      12: aload_0
      13: aload_2
      14: invokevirtual #114                // Method org/apache/hadoop/hbase/shaded/protobuf/generated/MasterProcedureProtos$RegionRemoteProcedureBaseStateData.getRegion:()Lorg/apache/hadoop/hbase/shaded/protobuf/generated/HBaseProtos$RegionInfo;
      17: invokestatic  #115                // Method org/apache/hadoop/hbase/shaded/protobuf/ProtobufUtil.toRegionInfo:(Lorg/apache/hadoop/hbase/shaded/protobuf/generated/HBaseProtos$RegionInfo;)Lorg/apache/hadoop/hbase/client/RegionInfo;
      20: putfield      #4                  // Field region:Lorg/apache/hadoop/hbase/client/RegionInfo;
      23: aload_0
      24: aload_2
      25: invokevirtual #116                // Method org/apache/hadoop/hbase/shaded/protobuf/generated/MasterProcedureProtos$RegionRemoteProcedureBaseStateData.getTargetServer:()Lorg/apache/hadoop/hbase/shaded/protobuf/generated/HBaseProtos$ServerName;
      28: invokestatic  #117                // Method org/apache/hadoop/hbase/shaded/protobuf/ProtobufUtil.toServerName:(Lorg/apache/hadoop/hbase/shaded/protobuf/generated/HBaseProtos$ServerName;)Lorg/apache/hadoop/hbase/ServerName;
      31: putfield      #5                  // Field targetServer:Lorg/apache/hadoop/hbase/ServerName;
      34: aload_0
      35: aload_2
      36: invokevirtual #118                // Method org/apache/hadoop/hbase/shaded/protobuf/generated/MasterProcedureProtos$RegionRemoteProcedureBaseStateData.getState:()Lorg/apache/hadoop/hbase/shaded/protobuf/generated/MasterProcedureProtos$RegionRemoteProcedureBaseState;
      39: putfield      #3                  // Field state:Lorg/apache/hadoop/hbase/shaded/protobuf/generated/MasterProcedureProtos$RegionRemoteProcedureBaseState;
      42: aload_2
      43: invokevirtual #119                // Method org/apache/hadoop/hbase/shaded/protobuf/generated/MasterProcedureProtos$RegionRemoteProcedureBaseStateData.hasTransitionCode:()Z
      46: ifeq          65
      49: aload_0
      50: aload_2
      51: invokevirtual #120                // Method org/apache/hadoop/hbase/shaded/protobuf/generated/MasterProcedureProtos$RegionRemoteProcedureBaseStateData.getTransitionCode:()Lorg/apache/hadoop/hbase/shaded/protobuf/generated/RegionServerStatusProtos$RegionStateTransition$TransitionCode;
      54: putfield      #54                 // Field transitionCode:Lorg/apache/hadoop/hbase/shaded/protobuf/generated/RegionServerStatusProtos$RegionStateTransition$TransitionCode;
      57: aload_0
      58: aload_2
      59: invokevirtual #121                // Method org/apache/hadoop/hbase/shaded/protobuf/generated/MasterProcedureProtos$RegionRemoteProcedureBaseStateData.getSeqId:()J
      62: putfield      #55                 // Field seqId:J
      65: return

  protected void afterReplay(org.apache.hadoop.hbase.master.procedure.MasterProcedureEnv);
    Code:
       0: aload_0
       1: aload_1
       2: invokespecial #71                 // Method getParent:(Lorg/apache/hadoop/hbase/master/procedure/MasterProcedureEnv;)Lorg/apache/hadoop/hbase/master/assignment/TransitRegionStateProcedure;
       5: aload_0
       6: invokevirtual #6                  // Method org/apache/hadoop/hbase/master/assignment/TransitRegionStateProcedure.attachRemoteProc:(Lorg/apache/hadoop/hbase/master/assignment/RegionRemoteProcedureBase;)V
       9: return

  protected void afterReplay(java.lang.Object);
    Code:
       0: aload_0
       1: aload_1
       2: checkcast     #122                // class org/apache/hadoop/hbase/master/procedure/MasterProcedureEnv
       5: invokevirtual #123                // Method afterReplay:(Lorg/apache/hadoop/hbase/master/procedure/MasterProcedureEnv;)V
       8: return

  protected boolean waitInitialized(java.lang.Object);
    Code:
       0: aload_0
       1: aload_1
       2: checkcast     #122                // class org/apache/hadoop/hbase/master/procedure/MasterProcedureEnv
       5: invokevirtual #124                // Method waitInitialized:(Lorg/apache/hadoop/hbase/master/procedure/MasterProcedureEnv;)Z
       8: ireturn

  protected boolean abort(java.lang.Object);
    Code:
       0: aload_0
       1: aload_1
       2: checkcast     #122                // class org/apache/hadoop/hbase/master/procedure/MasterProcedureEnv
       5: invokevirtual #125                // Method abort:(Lorg/apache/hadoop/hbase/master/procedure/MasterProcedureEnv;)Z
       8: ireturn

  protected void rollback(java.lang.Object) throws java.io.IOException, java.lang.InterruptedException;
    Code:
       0: aload_0
       1: aload_1
       2: checkcast     #122                // class org/apache/hadoop/hbase/master/procedure/MasterProcedureEnv
       5: invokevirtual #126                // Method rollback:(Lorg/apache/hadoop/hbase/master/procedure/MasterProcedureEnv;)V
       8: return

  protected org.apache.hadoop.hbase.procedure2.Procedure[] execute(java.lang.Object) throws org.apache.hadoop.hbase.procedure2.ProcedureYieldException, org.apache.hadoop.hbase.procedure2.ProcedureSuspendedException, java.lang.InterruptedException;
    Code:
       0: aload_0
       1: aload_1
       2: checkcast     #122                // class org/apache/hadoop/hbase/master/procedure/MasterProcedureEnv
       5: invokevirtual #127                // Method execute:(Lorg/apache/hadoop/hbase/master/procedure/MasterProcedureEnv;)[Lorg/apache/hadoop/hbase/procedure2/Procedure;
       8: areturn

  public void remoteOperationFailed(java.lang.Object, org.apache.hadoop.hbase.procedure2.RemoteProcedureException);
    Code:
       0: aload_0
       1: aload_1
       2: checkcast     #122                // class org/apache/hadoop/hbase/master/procedure/MasterProcedureEnv
       5: aload_2
       6: invokevirtual #128                // Method remoteOperationFailed:(Lorg/apache/hadoop/hbase/master/procedure/MasterProcedureEnv;Lorg/apache/hadoop/hbase/procedure2/RemoteProcedureException;)V
       9: return

  public void remoteOperationCompleted(java.lang.Object);
    Code:
       0: aload_0
       1: aload_1
       2: checkcast     #122                // class org/apache/hadoop/hbase/master/procedure/MasterProcedureEnv
       5: invokevirtual #129                // Method remoteOperationCompleted:(Lorg/apache/hadoop/hbase/master/procedure/MasterProcedureEnv;)V
       8: return

  public void remoteCallFailed(java.lang.Object, java.lang.Object, java.io.IOException);
    Code:
       0: aload_0
       1: aload_1
       2: checkcast     #122                // class org/apache/hadoop/hbase/master/procedure/MasterProcedureEnv
       5: aload_2
       6: checkcast     #130                // class org/apache/hadoop/hbase/ServerName
       9: aload_3
      10: invokevirtual #131                // Method remoteCallFailed:(Lorg/apache/hadoop/hbase/master/procedure/MasterProcedureEnv;Lorg/apache/hadoop/hbase/ServerName;Ljava/io/IOException;)V
      13: return

  public java.util.Optional remoteCallBuild(java.lang.Object, java.lang.Object);
    Code:
       0: aload_0
       1: aload_1
       2: checkcast     #122                // class org/apache/hadoop/hbase/master/procedure/MasterProcedureEnv
       5: aload_2
       6: checkcast     #130                // class org/apache/hadoop/hbase/ServerName
       9: invokevirtual #132                // Method remoteCallBuild:(Lorg/apache/hadoop/hbase/master/procedure/MasterProcedureEnv;Lorg/apache/hadoop/hbase/ServerName;)Ljava/util/Optional;
      12: areturn

  static {};
    Code:
       0: ldc           #133                // class org/apache/hadoop/hbase/master/assignment/RegionRemoteProcedureBase
       2: invokestatic  #134                // Method org/slf4j/LoggerFactory.getLogger:(Ljava/lang/Class;)Lorg/slf4j/Logger;
       5: putstatic     #21                 // Field LOG:Lorg/slf4j/Logger;
       8: return
}
