Compiled from "RejectRequestsFromClientStateChecker.java"
public class org.apache.hadoop.hbase.replication.regionserver.RejectRequestsFromClientStateChecker implements java.util.function.BiPredicate<org.apache.hadoop.hbase.replication.SyncReplicationState, org.apache.hadoop.hbase.replication.SyncReplicationState> {
  public org.apache.hadoop.hbase.replication.regionserver.RejectRequestsFromClientStateChecker();
    Code:
       0: aload_0
       1: invokespecial #1                  // Method java/lang/Object."<init>":()V
       4: return

  public boolean test(org.apache.hadoop.hbase.replication.SyncReplicationState, org.apache.hadoop.hbase.replication.SyncReplicationState);
    Code:
       0: aload_1
       1: getstatic     #2                  // Field org/apache/hadoop/hbase/replication/SyncReplicationState.STANDBY:Lorg/apache/hadoop/hbase/replication/SyncReplicationState;
       4: if_acmpeq     14
       7: aload_2
       8: getstatic     #2                  // Field org/apache/hadoop/hbase/replication/SyncReplicationState.STANDBY:Lorg/apache/hadoop/hbase/replication/SyncReplicationState;
      11: if_acmpne     18
      14: iconst_1
      15: goto          19
      18: iconst_0
      19: ireturn

  public static org.apache.hadoop.hbase.replication.regionserver.RejectRequestsFromClientStateChecker get();
    Code:
       0: getstatic     #3                  // Field INST:Lorg/apache/hadoop/hbase/replication/regionserver/RejectRequestsFromClientStateChecker;
       3: areturn

  public boolean test(java.lang.Object, java.lang.Object);
    Code:
       0: aload_0
       1: aload_1
       2: checkcast     #4                  // class org/apache/hadoop/hbase/replication/SyncReplicationState
       5: aload_2
       6: checkcast     #4                  // class org/apache/hadoop/hbase/replication/SyncReplicationState
       9: invokevirtual #5                  // Method test:(Lorg/apache/hadoop/hbase/replication/SyncReplicationState;Lorg/apache/hadoop/hbase/replication/SyncReplicationState;)Z
      12: ireturn

  static {};
    Code:
       0: new           #6                  // class org/apache/hadoop/hbase/replication/regionserver/RejectRequestsFromClientStateChecker
       3: dup
       4: invokespecial #7                  // Method "<init>":()V
       7: putstatic     #3                  // Field INST:Lorg/apache/hadoop/hbase/replication/regionserver/RejectRequestsFromClientStateChecker;
      10: return
}
