Compiled from "RemoteProcedureDispatcher.java"
public abstract class org.apache.hadoop.hbase.procedure2.RemoteProcedureDispatcher$RemoteOperation {
  protected org.apache.hadoop.hbase.procedure2.RemoteProcedureDispatcher$RemoteOperation(org.apache.hadoop.hbase.procedure2.RemoteProcedureDispatcher$RemoteProcedure);
    Code:
       0: aload_0
       1: invokespecial #1                  // Method java/lang/Object."<init>":()V
       4: aload_0
       5: aload_1
       6: putfield      #2                  // Field remoteProcedure:Lorg/apache/hadoop/hbase/procedure2/RemoteProcedureDispatcher$RemoteProcedure;
       9: return

  public org.apache.hadoop.hbase.procedure2.RemoteProcedureDispatcher$RemoteProcedure getRemoteProcedure();
    Code:
       0: aload_0
       1: getfield      #2                  // Field remoteProcedure:Lorg/apache/hadoop/hbase/procedure2/RemoteProcedureDispatcher$RemoteProcedure;
       4: areturn
}
