Compiled from "RemoteWithExtrasException.java"
public class org.apache.hadoop.hbase.ipc.RemoteWithExtrasException extends org.apache.hadoop.ipc.RemoteException {
  public org.apache.hadoop.hbase.ipc.RemoteWithExtrasException(java.lang.String, java.lang.String, boolean);
    Code:
       0: aload_0
       1: aload_1
       2: aload_2
       3: aconst_null
       4: iconst_m1
       5: iload_3
       6: invokespecial #1                  // Method "<init>":(Ljava/lang/String;Ljava/lang/String;Ljava/lang/String;IZ)V
       9: return

  public org.apache.hadoop.hbase.ipc.RemoteWithExtrasException(java.lang.String, java.lang.String, java.lang.String, int, boolean);
    Code:
       0: aload_0
       1: aload_1
       2: aload_2
       3: invokespecial #2                  // Method org/apache/hadoop/ipc/RemoteException."<init>":(Ljava/lang/String;Ljava/lang/String;)V
       6: aload_0
       7: aload_3
       8: putfield      #3                  // Field hostname:Ljava/lang/String;
      11: aload_0
      12: iload         4
      14: putfield      #4                  // Field port:I
      17: aload_0
      18: iload         5
      20: putfield      #5                  // Field doNotRetry:Z
      23: return

  public java.io.IOException unwrapRemoteException();
    Code:
       0: aload_0
       1: invokevirtual #6                  // Method getClassName:()Ljava/lang/String;
       4: iconst_0
       5: invokestatic  #7                  // Method org/apache/hadoop/hbase/ipc/RemoteWithExtrasException$ClassLoaderHolder.access$000:()Ljava/lang/ClassLoader;
       8: invokestatic  #8                  // Method java/lang/Class.forName:(Ljava/lang/String;ZLjava/lang/ClassLoader;)Ljava/lang/Class;
      11: astore_1
      12: goto          67
      15: astore_2
      16: aload_0
      17: invokevirtual #6                  // Method getClassName:()Ljava/lang/String;
      20: iconst_0
      21: aload_0
      22: invokespecial #10                 // Method java/lang/Object.getClass:()Ljava/lang/Class;
      25: invokevirtual #11                 // Method java/lang/Class.getClassLoader:()Ljava/lang/ClassLoader;
      28: invokestatic  #8                  // Method java/lang/Class.forName:(Ljava/lang/String;ZLjava/lang/ClassLoader;)Ljava/lang/Class;
      31: astore_1
      32: goto          67
      35: astore_3
      36: new           #12                 // class org/apache/hadoop/hbase/DoNotRetryIOException
      39: dup
      40: new           #13                 // class java/lang/StringBuilder
      43: dup
      44: invokespecial #14                 // Method java/lang/StringBuilder."<init>":()V
      47: ldc           #15                 // String Unable to load exception received from server:
      49: invokevirtual #16                 // Method java/lang/StringBuilder.append:(Ljava/lang/String;)Ljava/lang/StringBuilder;
      52: aload_3
      53: invokevirtual #17                 // Method java/lang/ClassNotFoundException.getMessage:()Ljava/lang/String;
      56: invokevirtual #16                 // Method java/lang/StringBuilder.append:(Ljava/lang/String;)Ljava/lang/StringBuilder;
      59: invokevirtual #18                 // Method java/lang/StringBuilder.toString:()Ljava/lang/String;
      62: aload_0
      63: invokespecial #19                 // Method org/apache/hadoop/hbase/DoNotRetryIOException."<init>":(Ljava/lang/String;Ljava/lang/Throwable;)V
      66: areturn
      67: aload_0
      68: aload_1
      69: ldc           #20                 // class java/io/IOException
      71: invokevirtual #21                 // Method java/lang/Class.asSubclass:(Ljava/lang/Class;)Ljava/lang/Class;
      74: invokespecial #22                 // Method instantiateException:(Ljava/lang/Class;)Ljava/io/IOException;
      77: areturn
      78: astore_2
      79: new           #12                 // class org/apache/hadoop/hbase/DoNotRetryIOException
      82: dup
      83: new           #13                 // class java/lang/StringBuilder
      86: dup
      87: invokespecial #14                 // Method java/lang/StringBuilder."<init>":()V
      90: ldc           #24                 // String Unable to instantiate exception received from server:
      92: invokevirtual #16                 // Method java/lang/StringBuilder.append:(Ljava/lang/String;)Ljava/lang/StringBuilder;
      95: aload_2
      96: invokevirtual #25                 // Method java/lang/Exception.getMessage:()Ljava/lang/String;
      99: invokevirtual #16                 // Method java/lang/StringBuilder.append:(Ljava/lang/String;)Ljava/lang/StringBuilder;
     102: invokevirtual #18                 // Method java/lang/StringBuilder.toString:()Ljava/lang/String;
     105: aload_0
     106: invokespecial #19                 // Method org/apache/hadoop/hbase/DoNotRetryIOException."<init>":(Ljava/lang/String;Ljava/lang/Throwable;)V
     109: areturn
    Exception table:
       from    to  target type
           0    12    15   Class java/lang/ClassNotFoundException
          16    32    35   Class java/lang/ClassNotFoundException
          67    77    78   Class java/lang/Exception

  public java.lang.String getHostname();
    Code:
       0: aload_0
       1: getfield      #3                  // Field hostname:Ljava/lang/String;
       4: areturn

  public int getPort();
    Code:
       0: aload_0
       1: getfield      #4                  // Field port:I
       4: ireturn

  public boolean isDoNotRetry();
    Code:
       0: aload_0
       1: getfield      #5                  // Field doNotRetry:Z
       4: ireturn
}
