Compiled from "ReplicationStatus.java"
public class org.apache.hadoop.hbase.replication.regionserver.ReplicationStatus$ReplicationStatusBuilder {
  public org.apache.hadoop.hbase.replication.regionserver.ReplicationStatus$ReplicationStatusBuilder();
    Code:
       0: aload_0
       1: invokespecial #9                  // Method java/lang/Object."<init>":()V
       4: aload_0
       5: ldc           #10                 // String UNKNOWN
       7: putfield      #8                  // Field peerId:Ljava/lang/String;
      10: aload_0
      11: ldc           #10                 // String UNKNOWN
      13: putfield      #7                  // Field walGroup:Ljava/lang/String;
      16: aload_0
      17: new           #11                 // class org/apache/hadoop/fs/Path
      20: dup
      21: ldc           #10                 // String UNKNOWN
      23: invokespecial #12                 // Method org/apache/hadoop/fs/Path."<init>":(Ljava/lang/String;)V
      26: putfield      #6                  // Field currentPath:Lorg/apache/hadoop/fs/Path;
      29: aload_0
      30: iconst_m1
      31: putfield      #5                  // Field queueSize:I
      34: aload_0
      35: ldc2_w        #13                 // long -1l
      38: putfield      #4                  // Field ageOfLastShippedOp:J
      41: aload_0
      42: ldc2_w        #13                 // long -1l
      45: putfield      #3                  // Field replicationDelay:J
      48: aload_0
      49: ldc2_w        #13                 // long -1l
      52: putfield      #2                  // Field currentPosition:J
      55: aload_0
      56: ldc2_w        #13                 // long -1l
      59: putfield      #1                  // Field fileSize:J
      62: return

  public org.apache.hadoop.hbase.replication.regionserver.ReplicationStatus$ReplicationStatusBuilder withPeerId(java.lang.String);
    Code:
       0: aload_0
       1: aload_1
       2: putfield      #8                  // Field peerId:Ljava/lang/String;
       5: aload_0
       6: areturn

  public org.apache.hadoop.hbase.replication.regionserver.ReplicationStatus$ReplicationStatusBuilder withFileSize(long);
    Code:
       0: aload_0
       1: lload_1
       2: putfield      #1                  // Field fileSize:J
       5: aload_0
       6: areturn

  public org.apache.hadoop.hbase.replication.regionserver.ReplicationStatus$ReplicationStatusBuilder withWalGroup(java.lang.String);
    Code:
       0: aload_0
       1: aload_1
       2: putfield      #7                  // Field walGroup:Ljava/lang/String;
       5: aload_0
       6: areturn

  public org.apache.hadoop.hbase.replication.regionserver.ReplicationStatus$ReplicationStatusBuilder withCurrentPath(org.apache.hadoop.fs.Path);
    Code:
       0: aload_0
       1: aload_1
       2: putfield      #6                  // Field currentPath:Lorg/apache/hadoop/fs/Path;
       5: aload_0
       6: areturn

  public org.apache.hadoop.hbase.replication.regionserver.ReplicationStatus$ReplicationStatusBuilder withQueueSize(int);
    Code:
       0: aload_0
       1: iload_1
       2: putfield      #5                  // Field queueSize:I
       5: aload_0
       6: areturn

  public org.apache.hadoop.hbase.replication.regionserver.ReplicationStatus$ReplicationStatusBuilder withAgeOfLastShippedOp(long);
    Code:
       0: aload_0
       1: lload_1
       2: putfield      #4                  // Field ageOfLastShippedOp:J
       5: aload_0
       6: areturn

  public org.apache.hadoop.hbase.replication.regionserver.ReplicationStatus$ReplicationStatusBuilder withReplicationDelay(long);
    Code:
       0: aload_0
       1: lload_1
       2: putfield      #3                  // Field replicationDelay:J
       5: aload_0
       6: areturn

  public org.apache.hadoop.hbase.replication.regionserver.ReplicationStatus$ReplicationStatusBuilder withCurrentPosition(long);
    Code:
       0: aload_0
       1: lload_1
       2: putfield      #2                  // Field currentPosition:J
       5: aload_0
       6: areturn

  public org.apache.hadoop.hbase.replication.regionserver.ReplicationStatus build();
    Code:
       0: new           #15                 // class org/apache/hadoop/hbase/replication/regionserver/ReplicationStatus
       3: dup
       4: aload_0
       5: aconst_null
       6: invokespecial #16                 // Method org/apache/hadoop/hbase/replication/regionserver/ReplicationStatus."<init>":(Lorg/apache/hadoop/hbase/replication/regionserver/ReplicationStatus$ReplicationStatusBuilder;Lorg/apache/hadoop/hbase/replication/regionserver/ReplicationStatus$1;)V
       9: areturn

  static java.lang.String access$000(org.apache.hadoop.hbase.replication.regionserver.ReplicationStatus$ReplicationStatusBuilder);
    Code:
       0: aload_0
       1: getfield      #8                  // Field peerId:Ljava/lang/String;
       4: areturn

  static java.lang.String access$100(org.apache.hadoop.hbase.replication.regionserver.ReplicationStatus$ReplicationStatusBuilder);
    Code:
       0: aload_0
       1: getfield      #7                  // Field walGroup:Ljava/lang/String;
       4: areturn

  static org.apache.hadoop.fs.Path access$200(org.apache.hadoop.hbase.replication.regionserver.ReplicationStatus$ReplicationStatusBuilder);
    Code:
       0: aload_0
       1: getfield      #6                  // Field currentPath:Lorg/apache/hadoop/fs/Path;
       4: areturn

  static int access$300(org.apache.hadoop.hbase.replication.regionserver.ReplicationStatus$ReplicationStatusBuilder);
    Code:
       0: aload_0
       1: getfield      #5                  // Field queueSize:I
       4: ireturn

  static long access$400(org.apache.hadoop.hbase.replication.regionserver.ReplicationStatus$ReplicationStatusBuilder);
    Code:
       0: aload_0
       1: getfield      #4                  // Field ageOfLastShippedOp:J
       4: lreturn

  static long access$500(org.apache.hadoop.hbase.replication.regionserver.ReplicationStatus$ReplicationStatusBuilder);
    Code:
       0: aload_0
       1: getfield      #3                  // Field replicationDelay:J
       4: lreturn

  static long access$600(org.apache.hadoop.hbase.replication.regionserver.ReplicationStatus$ReplicationStatusBuilder);
    Code:
       0: aload_0
       1: getfield      #2                  // Field currentPosition:J
       4: lreturn

  static long access$700(org.apache.hadoop.hbase.replication.regionserver.ReplicationStatus$ReplicationStatusBuilder);
    Code:
       0: aload_0
       1: getfield      #1                  // Field fileSize:J
       4: lreturn
}
