Compiled from "ReplicationPeers.java"
public class org.apache.hadoop.hbase.replication.ReplicationPeers {
  org.apache.hadoop.hbase.replication.ReplicationPeers(org.apache.hadoop.hbase.zookeeper.ZKWatcher, org.apache.hadoop.conf.Configuration);
    Code:
       0: aload_0
       1: invokespecial #1                  // Method java/lang/Object."<init>":()V
       4: aload_0
       5: aload_2
       6: putfield      #2                  // Field conf:Lorg/apache/hadoop/conf/Configuration;
       9: aload_0
      10: new           #3                  // class java/util/concurrent/ConcurrentHashMap
      13: dup
      14: invokespecial #4                  // Method java/util/concurrent/ConcurrentHashMap."<init>":()V
      17: putfield      #5                  // Field peerCache:Ljava/util/concurrent/ConcurrentMap;
      20: aload_0
      21: aload_1
      22: aload_2
      23: invokestatic  #6                  // Method org/apache/hadoop/hbase/replication/ReplicationStorageFactory.getReplicationPeerStorage:(Lorg/apache/hadoop/hbase/zookeeper/ZKWatcher;Lorg/apache/hadoop/conf/Configuration;)Lorg/apache/hadoop/hbase/replication/ReplicationPeerStorage;
      26: putfield      #7                  // Field peerStorage:Lorg/apache/hadoop/hbase/replication/ReplicationPeerStorage;
      29: return

  public org.apache.hadoop.conf.Configuration getConf();
    Code:
       0: aload_0
       1: getfield      #2                  // Field conf:Lorg/apache/hadoop/conf/Configuration;
       4: areturn

  public void init() throws org.apache.hadoop.hbase.replication.ReplicationException;
    Code:
       0: aload_0
       1: getfield      #7                  // Field peerStorage:Lorg/apache/hadoop/hbase/replication/ReplicationPeerStorage;
       4: invokeinterface #8,  1            // InterfaceMethod org/apache/hadoop/hbase/replication/ReplicationPeerStorage.listPeerIds:()Ljava/util/List;
       9: invokeinterface #9,  1            // InterfaceMethod java/util/List.iterator:()Ljava/util/Iterator;
      14: astore_1
      15: aload_1
      16: invokeinterface #10,  1           // InterfaceMethod java/util/Iterator.hasNext:()Z
      21: ifeq          43
      24: aload_1
      25: invokeinterface #11,  1           // InterfaceMethod java/util/Iterator.next:()Ljava/lang/Object;
      30: checkcast     #12                 // class java/lang/String
      33: astore_2
      34: aload_0
      35: aload_2
      36: invokevirtual #13                 // Method addPeer:(Ljava/lang/String;)Z
      39: pop
      40: goto          15
      43: return

  public org.apache.hadoop.hbase.replication.ReplicationPeerStorage getPeerStorage();
    Code:
       0: aload_0
       1: getfield      #7                  // Field peerStorage:Lorg/apache/hadoop/hbase/replication/ReplicationPeerStorage;
       4: areturn

  public boolean addPeer(java.lang.String) throws org.apache.hadoop.hbase.replication.ReplicationException;
    Code:
       0: aload_0
       1: getfield      #5                  // Field peerCache:Ljava/util/concurrent/ConcurrentMap;
       4: aload_1
       5: invokeinterface #14,  2           // InterfaceMethod java/util/concurrent/ConcurrentMap.containsKey:(Ljava/lang/Object;)Z
      10: ifeq          15
      13: iconst_0
      14: ireturn
      15: aload_0
      16: getfield      #5                  // Field peerCache:Ljava/util/concurrent/ConcurrentMap;
      19: aload_1
      20: aload_0
      21: aload_1
      22: invokespecial #15                 // Method createPeer:(Ljava/lang/String;)Lorg/apache/hadoop/hbase/replication/ReplicationPeerImpl;
      25: invokeinterface #16,  3           // InterfaceMethod java/util/concurrent/ConcurrentMap.put:(Ljava/lang/Object;Ljava/lang/Object;)Ljava/lang/Object;
      30: pop
      31: iconst_1
      32: ireturn

  public org.apache.hadoop.hbase.replication.ReplicationPeerImpl removePeer(java.lang.String);
    Code:
       0: aload_0
       1: getfield      #5                  // Field peerCache:Ljava/util/concurrent/ConcurrentMap;
       4: aload_1
       5: invokeinterface #17,  2           // InterfaceMethod java/util/concurrent/ConcurrentMap.remove:(Ljava/lang/Object;)Ljava/lang/Object;
      10: checkcast     #18                 // class org/apache/hadoop/hbase/replication/ReplicationPeerImpl
      13: areturn

  public org.apache.hadoop.hbase.replication.ReplicationPeerImpl getPeer(java.lang.String);
    Code:
       0: aload_0
       1: getfield      #5                  // Field peerCache:Ljava/util/concurrent/ConcurrentMap;
       4: aload_1
       5: invokeinterface #19,  2           // InterfaceMethod java/util/concurrent/ConcurrentMap.get:(Ljava/lang/Object;)Ljava/lang/Object;
      10: checkcast     #18                 // class org/apache/hadoop/hbase/replication/ReplicationPeerImpl
      13: areturn

  public java.util.Set<java.lang.String> getAllPeerIds();
    Code:
       0: aload_0
       1: getfield      #5                  // Field peerCache:Ljava/util/concurrent/ConcurrentMap;
       4: invokeinterface #20,  1           // InterfaceMethod java/util/concurrent/ConcurrentMap.keySet:()Ljava/util/Set;
       9: invokestatic  #21                 // Method java/util/Collections.unmodifiableSet:(Ljava/util/Set;)Ljava/util/Set;
      12: areturn

  public java.util.Map<java.lang.String, org.apache.hadoop.hbase.replication.ReplicationPeerImpl> getPeerCache();
    Code:
       0: aload_0
       1: getfield      #5                  // Field peerCache:Ljava/util/concurrent/ConcurrentMap;
       4: invokestatic  #22                 // Method java/util/Collections.unmodifiableMap:(Ljava/util/Map;)Ljava/util/Map;
       7: areturn

  public org.apache.hadoop.hbase.replication.ReplicationPeer$PeerState refreshPeerState(java.lang.String) throws org.apache.hadoop.hbase.replication.ReplicationException;
    Code:
       0: aload_0
       1: getfield      #5                  // Field peerCache:Ljava/util/concurrent/ConcurrentMap;
       4: aload_1
       5: invokeinterface #19,  2           // InterfaceMethod java/util/concurrent/ConcurrentMap.get:(Ljava/lang/Object;)Ljava/lang/Object;
      10: checkcast     #18                 // class org/apache/hadoop/hbase/replication/ReplicationPeerImpl
      13: astore_2
      14: aload_2
      15: aload_0
      16: getfield      #7                  // Field peerStorage:Lorg/apache/hadoop/hbase/replication/ReplicationPeerStorage;
      19: aload_1
      20: invokeinterface #23,  2           // InterfaceMethod org/apache/hadoop/hbase/replication/ReplicationPeerStorage.isPeerEnabled:(Ljava/lang/String;)Z
      25: invokevirtual #24                 // Method org/apache/hadoop/hbase/replication/ReplicationPeerImpl.setPeerState:(Z)V
      28: aload_2
      29: invokevirtual #25                 // Method org/apache/hadoop/hbase/replication/ReplicationPeerImpl.getPeerState:()Lorg/apache/hadoop/hbase/replication/ReplicationPeer$PeerState;
      32: areturn

  public org.apache.hadoop.hbase.replication.ReplicationPeerConfig refreshPeerConfig(java.lang.String) throws org.apache.hadoop.hbase.replication.ReplicationException;
    Code:
       0: aload_0
       1: getfield      #5                  // Field peerCache:Ljava/util/concurrent/ConcurrentMap;
       4: aload_1
       5: invokeinterface #19,  2           // InterfaceMethod java/util/concurrent/ConcurrentMap.get:(Ljava/lang/Object;)Ljava/lang/Object;
      10: checkcast     #18                 // class org/apache/hadoop/hbase/replication/ReplicationPeerImpl
      13: astore_2
      14: aload_2
      15: aload_0
      16: getfield      #7                  // Field peerStorage:Lorg/apache/hadoop/hbase/replication/ReplicationPeerStorage;
      19: aload_1
      20: invokeinterface #26,  2           // InterfaceMethod org/apache/hadoop/hbase/replication/ReplicationPeerStorage.getPeerConfig:(Ljava/lang/String;)Lorg/apache/hadoop/hbase/replication/ReplicationPeerConfig;
      25: invokevirtual #27                 // Method org/apache/hadoop/hbase/replication/ReplicationPeerImpl.setPeerConfig:(Lorg/apache/hadoop/hbase/replication/ReplicationPeerConfig;)V
      28: aload_2
      29: invokevirtual #28                 // Method org/apache/hadoop/hbase/replication/ReplicationPeerImpl.getPeerConfig:()Lorg/apache/hadoop/hbase/replication/ReplicationPeerConfig;
      32: areturn

  public org.apache.hadoop.hbase.replication.SyncReplicationState refreshPeerNewSyncReplicationState(java.lang.String) throws org.apache.hadoop.hbase.replication.ReplicationException;
    Code:
       0: aload_0
       1: getfield      #5                  // Field peerCache:Ljava/util/concurrent/ConcurrentMap;
       4: aload_1
       5: invokeinterface #19,  2           // InterfaceMethod java/util/concurrent/ConcurrentMap.get:(Ljava/lang/Object;)Ljava/lang/Object;
      10: checkcast     #18                 // class org/apache/hadoop/hbase/replication/ReplicationPeerImpl
      13: astore_2
      14: aload_0
      15: getfield      #7                  // Field peerStorage:Lorg/apache/hadoop/hbase/replication/ReplicationPeerStorage;
      18: aload_1
      19: invokeinterface #29,  2           // InterfaceMethod org/apache/hadoop/hbase/replication/ReplicationPeerStorage.getPeerNewSyncReplicationState:(Ljava/lang/String;)Lorg/apache/hadoop/hbase/replication/SyncReplicationState;
      24: astore_3
      25: aload_2
      26: aload_3
      27: invokevirtual #30                 // Method org/apache/hadoop/hbase/replication/ReplicationPeerImpl.setNewSyncReplicationState:(Lorg/apache/hadoop/hbase/replication/SyncReplicationState;)V
      30: aload_3
      31: areturn

  public void transitPeerSyncReplicationState(java.lang.String);
    Code:
       0: aload_0
       1: getfield      #5                  // Field peerCache:Ljava/util/concurrent/ConcurrentMap;
       4: aload_1
       5: invokeinterface #19,  2           // InterfaceMethod java/util/concurrent/ConcurrentMap.get:(Ljava/lang/Object;)Ljava/lang/Object;
      10: checkcast     #18                 // class org/apache/hadoop/hbase/replication/ReplicationPeerImpl
      13: astore_2
      14: aload_2
      15: invokevirtual #31                 // Method org/apache/hadoop/hbase/replication/ReplicationPeerImpl.transitSyncReplicationState:()V
      18: return
}
