Compiled from "ReplicationTrackerZKImpl.java"
public class org.apache.hadoop.hbase.replication.ReplicationTrackerZKImpl$OtherRegionServerWatcher extends org.apache.hadoop.hbase.zookeeper.ZKListener {
  final org.apache.hadoop.hbase.replication.ReplicationTrackerZKImpl this$0;

  public org.apache.hadoop.hbase.replication.ReplicationTrackerZKImpl$OtherRegionServerWatcher(org.apache.hadoop.hbase.replication.ReplicationTrackerZKImpl, org.apache.hadoop.hbase.zookeeper.ZKWatcher);
    Code:
       0: aload_0
       1: aload_1
       2: putfield      #1                  // Field this$0:Lorg/apache/hadoop/hbase/replication/ReplicationTrackerZKImpl;
       5: aload_0
       6: aload_2
       7: invokespecial #2                  // Method org/apache/hadoop/hbase/zookeeper/ZKListener."<init>":(Lorg/apache/hadoop/hbase/zookeeper/ZKWatcher;)V
      10: return

  public void nodeCreated(java.lang.String);
    Code:
       0: aload_0
       1: aload_1
       2: invokespecial #3                  // Method refreshListIfRightPath:(Ljava/lang/String;)Z
       5: pop
       6: return

  public void nodeDeleted(java.lang.String);
    Code:
       0: aload_0
       1: getfield      #1                  // Field this$0:Lorg/apache/hadoop/hbase/replication/ReplicationTrackerZKImpl;
       4: invokestatic  #4                  // Method org/apache/hadoop/hbase/replication/ReplicationTrackerZKImpl.access$000:(Lorg/apache/hadoop/hbase/replication/ReplicationTrackerZKImpl;)Lorg/apache/hadoop/hbase/Stoppable;
       7: invokeinterface #5,  1            // InterfaceMethod org/apache/hadoop/hbase/Stoppable.isStopped:()Z
      12: ifeq          16
      15: return
      16: aload_0
      17: aload_1
      18: invokespecial #3                  // Method refreshListIfRightPath:(Ljava/lang/String;)Z
      21: istore_2
      22: iload_2
      23: ifne          27
      26: return
      27: invokestatic  #6                  // Method org/apache/hadoop/hbase/replication/ReplicationTrackerZKImpl.access$100:()Lorg/slf4j/Logger;
      30: new           #7                  // class java/lang/StringBuilder
      33: dup
      34: invokespecial #8                  // Method java/lang/StringBuilder."<init>":()V
      37: aload_1
      38: invokevirtual #9                  // Method java/lang/StringBuilder.append:(Ljava/lang/String;)Ljava/lang/StringBuilder;
      41: ldc           #10                 // String  znode expired, triggering replicatorRemoved event
      43: invokevirtual #9                  // Method java/lang/StringBuilder.append:(Ljava/lang/String;)Ljava/lang/StringBuilder;
      46: invokevirtual #11                 // Method java/lang/StringBuilder.toString:()Ljava/lang/String;
      49: invokeinterface #12,  2           // InterfaceMethod org/slf4j/Logger.info:(Ljava/lang/String;)V
      54: aload_0
      55: getfield      #1                  // Field this$0:Lorg/apache/hadoop/hbase/replication/ReplicationTrackerZKImpl;
      58: invokestatic  #13                 // Method org/apache/hadoop/hbase/replication/ReplicationTrackerZKImpl.access$200:(Lorg/apache/hadoop/hbase/replication/ReplicationTrackerZKImpl;)Ljava/util/List;
      61: invokeinterface #14,  1           // InterfaceMethod java/util/List.iterator:()Ljava/util/Iterator;
      66: astore_3
      67: aload_3
      68: invokeinterface #15,  1           // InterfaceMethod java/util/Iterator.hasNext:()Z
      73: ifeq          105
      76: aload_3
      77: invokeinterface #16,  1           // InterfaceMethod java/util/Iterator.next:()Ljava/lang/Object;
      82: checkcast     #17                 // class org/apache/hadoop/hbase/replication/ReplicationListener
      85: astore        4
      87: aload         4
      89: aload_0
      90: getfield      #1                  // Field this$0:Lorg/apache/hadoop/hbase/replication/ReplicationTrackerZKImpl;
      93: aload_1
      94: invokestatic  #18                 // Method org/apache/hadoop/hbase/replication/ReplicationTrackerZKImpl.access$300:(Lorg/apache/hadoop/hbase/replication/ReplicationTrackerZKImpl;Ljava/lang/String;)Ljava/lang/String;
      97: invokeinterface #19,  2           // InterfaceMethod org/apache/hadoop/hbase/replication/ReplicationListener.regionServerRemoved:(Ljava/lang/String;)V
     102: goto          67
     105: return

  public void nodeChildrenChanged(java.lang.String);
    Code:
       0: aload_0
       1: getfield      #1                  // Field this$0:Lorg/apache/hadoop/hbase/replication/ReplicationTrackerZKImpl;
       4: invokestatic  #4                  // Method org/apache/hadoop/hbase/replication/ReplicationTrackerZKImpl.access$000:(Lorg/apache/hadoop/hbase/replication/ReplicationTrackerZKImpl;)Lorg/apache/hadoop/hbase/Stoppable;
       7: invokeinterface #5,  1            // InterfaceMethod org/apache/hadoop/hbase/Stoppable.isStopped:()Z
      12: ifeq          16
      15: return
      16: aload_0
      17: aload_1
      18: invokespecial #3                  // Method refreshListIfRightPath:(Ljava/lang/String;)Z
      21: pop
      22: return
}
