Compiled from "ReplicationProtos.java"
public final class org.apache.hadoop.hbase.shaded.protobuf.generated.ReplicationProtos$ReplicationPeerDescription$Builder extends org.apache.hbase.thirdparty.com.google.protobuf.GeneratedMessageV3$Builder<org.apache.hadoop.hbase.shaded.protobuf.generated.ReplicationProtos$ReplicationPeerDescription$Builder> implements org.apache.hadoop.hbase.shaded.protobuf.generated.ReplicationProtos$ReplicationPeerDescriptionOrBuilder {
  public static final org.apache.hbase.thirdparty.com.google.protobuf.Descriptors$Descriptor getDescriptor();
    Code:
       0: invokestatic  #3                  // Method org/apache/hadoop/hbase/shaded/protobuf/generated/ReplicationProtos.access$5600:()Lorg/apache/hbase/thirdparty/com/google/protobuf/Descriptors$Descriptor;
       3: areturn

  protected org.apache.hbase.thirdparty.com.google.protobuf.GeneratedMessageV3$FieldAccessorTable internalGetFieldAccessorTable();
    Code:
       0: invokestatic  #4                  // Method org/apache/hadoop/hbase/shaded/protobuf/generated/ReplicationProtos.access$5700:()Lorg/apache/hbase/thirdparty/com/google/protobuf/GeneratedMessageV3$FieldAccessorTable;
       3: ldc           #5                  // class org/apache/hadoop/hbase/shaded/protobuf/generated/ReplicationProtos$ReplicationPeerDescription
       5: ldc           #6                  // class org/apache/hadoop/hbase/shaded/protobuf/generated/ReplicationProtos$ReplicationPeerDescription$Builder
       7: invokevirtual #7                  // Method org/apache/hbase/thirdparty/com/google/protobuf/GeneratedMessageV3$FieldAccessorTable.ensureFieldAccessorsInitialized:(Ljava/lang/Class;Ljava/lang/Class;)Lorg/apache/hbase/thirdparty/com/google/protobuf/GeneratedMessageV3$FieldAccessorTable;
      10: areturn

  public org.apache.hadoop.hbase.shaded.protobuf.generated.ReplicationProtos$ReplicationPeerDescription$Builder clear();
    Code:
       0: aload_0
       1: invokespecial #20                 // Method org/apache/hbase/thirdparty/com/google/protobuf/GeneratedMessageV3$Builder.clear:()Lorg/apache/hbase/thirdparty/com/google/protobuf/GeneratedMessageV3$Builder;
       4: pop
       5: aload_0
       6: ldc           #9                  // String
       8: putfield      #10                 // Field id_:Ljava/lang/Object;
      11: aload_0
      12: aload_0
      13: getfield      #21                 // Field bitField0_:I
      16: bipush        -2
      18: iand
      19: putfield      #21                 // Field bitField0_:I
      22: aload_0
      23: getfield      #22                 // Field stateBuilder_:Lorg/apache/hbase/thirdparty/com/google/protobuf/SingleFieldBuilderV3;
      26: ifnonnull     37
      29: aload_0
      30: aconst_null
      31: putfield      #11                 // Field state_:Lorg/apache/hadoop/hbase/shaded/protobuf/generated/ReplicationProtos$ReplicationState;
      34: goto          45
      37: aload_0
      38: getfield      #22                 // Field stateBuilder_:Lorg/apache/hbase/thirdparty/com/google/protobuf/SingleFieldBuilderV3;
      41: invokevirtual #23                 // Method org/apache/hbase/thirdparty/com/google/protobuf/SingleFieldBuilderV3.clear:()Lorg/apache/hbase/thirdparty/com/google/protobuf/SingleFieldBuilderV3;
      44: pop
      45: aload_0
      46: aload_0
      47: getfield      #21                 // Field bitField0_:I
      50: bipush        -3
      52: iand
      53: putfield      #21                 // Field bitField0_:I
      56: aload_0
      57: getfield      #24                 // Field configBuilder_:Lorg/apache/hbase/thirdparty/com/google/protobuf/SingleFieldBuilderV3;
      60: ifnonnull     71
      63: aload_0
      64: aconst_null
      65: putfield      #12                 // Field config_:Lorg/apache/hadoop/hbase/shaded/protobuf/generated/ReplicationProtos$ReplicationPeer;
      68: goto          79
      71: aload_0
      72: getfield      #24                 // Field configBuilder_:Lorg/apache/hbase/thirdparty/com/google/protobuf/SingleFieldBuilderV3;
      75: invokevirtual #23                 // Method org/apache/hbase/thirdparty/com/google/protobuf/SingleFieldBuilderV3.clear:()Lorg/apache/hbase/thirdparty/com/google/protobuf/SingleFieldBuilderV3;
      78: pop
      79: aload_0
      80: aload_0
      81: getfield      #21                 // Field bitField0_:I
      84: bipush        -5
      86: iand
      87: putfield      #21                 // Field bitField0_:I
      90: aload_0
      91: getfield      #25                 // Field syncReplicationStateBuilder_:Lorg/apache/hbase/thirdparty/com/google/protobuf/SingleFieldBuilderV3;
      94: ifnonnull     105
      97: aload_0
      98: aconst_null
      99: putfield      #13                 // Field syncReplicationState_:Lorg/apache/hadoop/hbase/shaded/protobuf/generated/ReplicationProtos$SyncReplicationState;
     102: goto          113
     105: aload_0
     106: getfield      #25                 // Field syncReplicationStateBuilder_:Lorg/apache/hbase/thirdparty/com/google/protobuf/SingleFieldBuilderV3;
     109: invokevirtual #23                 // Method org/apache/hbase/thirdparty/com/google/protobuf/SingleFieldBuilderV3.clear:()Lorg/apache/hbase/thirdparty/com/google/protobuf/SingleFieldBuilderV3;
     112: pop
     113: aload_0
     114: aload_0
     115: getfield      #21                 // Field bitField0_:I
     118: bipush        -9
     120: iand
     121: putfield      #21                 // Field bitField0_:I
     124: aload_0
     125: areturn

  public org.apache.hbase.thirdparty.com.google.protobuf.Descriptors$Descriptor getDescriptorForType();
    Code:
       0: invokestatic  #3                  // Method org/apache/hadoop/hbase/shaded/protobuf/generated/ReplicationProtos.access$5600:()Lorg/apache/hbase/thirdparty/com/google/protobuf/Descriptors$Descriptor;
       3: areturn

  public org.apache.hadoop.hbase.shaded.protobuf.generated.ReplicationProtos$ReplicationPeerDescription getDefaultInstanceForType();
    Code:
       0: invokestatic  #26                 // Method org/apache/hadoop/hbase/shaded/protobuf/generated/ReplicationProtos$ReplicationPeerDescription.getDefaultInstance:()Lorg/apache/hadoop/hbase/shaded/protobuf/generated/ReplicationProtos$ReplicationPeerDescription;
       3: areturn

  public org.apache.hadoop.hbase.shaded.protobuf.generated.ReplicationProtos$ReplicationPeerDescription build();
    Code:
       0: aload_0
       1: invokevirtual #27                 // Method buildPartial:()Lorg/apache/hadoop/hbase/shaded/protobuf/generated/ReplicationProtos$ReplicationPeerDescription;
       4: astore_1
       5: aload_1
       6: invokevirtual #28                 // Method org/apache/hadoop/hbase/shaded/protobuf/generated/ReplicationProtos$ReplicationPeerDescription.isInitialized:()Z
       9: ifne          17
      12: aload_1
      13: invokestatic  #29                 // Method newUninitializedMessageException:(Lorg/apache/hbase/thirdparty/com/google/protobuf/Message;)Lorg/apache/hbase/thirdparty/com/google/protobuf/UninitializedMessageException;
      16: athrow
      17: aload_1
      18: areturn

  public org.apache.hadoop.hbase.shaded.protobuf.generated.ReplicationProtos$ReplicationPeerDescription buildPartial();
    Code:
       0: new           #5                  // class org/apache/hadoop/hbase/shaded/protobuf/generated/ReplicationProtos$ReplicationPeerDescription
       3: dup
       4: aload_0
       5: aconst_null
       6: invokespecial #30                 // Method org/apache/hadoop/hbase/shaded/protobuf/generated/ReplicationProtos$ReplicationPeerDescription."<init>":(Lorg/apache/hbase/thirdparty/com/google/protobuf/GeneratedMessageV3$Builder;Lorg/apache/hadoop/hbase/shaded/protobuf/generated/ReplicationProtos$1;)V
       9: astore_1
      10: aload_0
      11: getfield      #21                 // Field bitField0_:I
      14: istore_2
      15: iconst_0
      16: istore_3
      17: iload_2
      18: iconst_1
      19: iand
      20: iconst_1
      21: if_icmpne     28
      24: iload_3
      25: iconst_1
      26: ior
      27: istore_3
      28: aload_1
      29: aload_0
      30: getfield      #10                 // Field id_:Ljava/lang/Object;
      33: invokestatic  #31                 // Method org/apache/hadoop/hbase/shaded/protobuf/generated/ReplicationProtos$ReplicationPeerDescription.access$6202:(Lorg/apache/hadoop/hbase/shaded/protobuf/generated/ReplicationProtos$ReplicationPeerDescription;Ljava/lang/Object;)Ljava/lang/Object;
      36: pop
      37: iload_2
      38: iconst_2
      39: iand
      40: iconst_2
      41: if_icmpne     48
      44: iload_3
      45: iconst_2
      46: ior
      47: istore_3
      48: aload_0
      49: getfield      #22                 // Field stateBuilder_:Lorg/apache/hbase/thirdparty/com/google/protobuf/SingleFieldBuilderV3;
      52: ifnonnull     67
      55: aload_1
      56: aload_0
      57: getfield      #11                 // Field state_:Lorg/apache/hadoop/hbase/shaded/protobuf/generated/ReplicationProtos$ReplicationState;
      60: invokestatic  #32                 // Method org/apache/hadoop/hbase/shaded/protobuf/generated/ReplicationProtos$ReplicationPeerDescription.access$6302:(Lorg/apache/hadoop/hbase/shaded/protobuf/generated/ReplicationProtos$ReplicationPeerDescription;Lorg/apache/hadoop/hbase/shaded/protobuf/generated/ReplicationProtos$ReplicationState;)Lorg/apache/hadoop/hbase/shaded/protobuf/generated/ReplicationProtos$ReplicationState;
      63: pop
      64: goto          82
      67: aload_1
      68: aload_0
      69: getfield      #22                 // Field stateBuilder_:Lorg/apache/hbase/thirdparty/com/google/protobuf/SingleFieldBuilderV3;
      72: invokevirtual #33                 // Method org/apache/hbase/thirdparty/com/google/protobuf/SingleFieldBuilderV3.build:()Lorg/apache/hbase/thirdparty/com/google/protobuf/AbstractMessage;
      75: checkcast     #34                 // class org/apache/hadoop/hbase/shaded/protobuf/generated/ReplicationProtos$ReplicationState
      78: invokestatic  #32                 // Method org/apache/hadoop/hbase/shaded/protobuf/generated/ReplicationProtos$ReplicationPeerDescription.access$6302:(Lorg/apache/hadoop/hbase/shaded/protobuf/generated/ReplicationProtos$ReplicationPeerDescription;Lorg/apache/hadoop/hbase/shaded/protobuf/generated/ReplicationProtos$ReplicationState;)Lorg/apache/hadoop/hbase/shaded/protobuf/generated/ReplicationProtos$ReplicationState;
      81: pop
      82: iload_2
      83: iconst_4
      84: iand
      85: iconst_4
      86: if_icmpne     93
      89: iload_3
      90: iconst_4
      91: ior
      92: istore_3
      93: aload_0
      94: getfield      #24                 // Field configBuilder_:Lorg/apache/hbase/thirdparty/com/google/protobuf/SingleFieldBuilderV3;
      97: ifnonnull     112
     100: aload_1
     101: aload_0
     102: getfield      #12                 // Field config_:Lorg/apache/hadoop/hbase/shaded/protobuf/generated/ReplicationProtos$ReplicationPeer;
     105: invokestatic  #35                 // Method org/apache/hadoop/hbase/shaded/protobuf/generated/ReplicationProtos$ReplicationPeerDescription.access$6402:(Lorg/apache/hadoop/hbase/shaded/protobuf/generated/ReplicationProtos$ReplicationPeerDescription;Lorg/apache/hadoop/hbase/shaded/protobuf/generated/ReplicationProtos$ReplicationPeer;)Lorg/apache/hadoop/hbase/shaded/protobuf/generated/ReplicationProtos$ReplicationPeer;
     108: pop
     109: goto          127
     112: aload_1
     113: aload_0
     114: getfield      #24                 // Field configBuilder_:Lorg/apache/hbase/thirdparty/com/google/protobuf/SingleFieldBuilderV3;
     117: invokevirtual #33                 // Method org/apache/hbase/thirdparty/com/google/protobuf/SingleFieldBuilderV3.build:()Lorg/apache/hbase/thirdparty/com/google/protobuf/AbstractMessage;
     120: checkcast     #36                 // class org/apache/hadoop/hbase/shaded/protobuf/generated/ReplicationProtos$ReplicationPeer
     123: invokestatic  #35                 // Method org/apache/hadoop/hbase/shaded/protobuf/generated/ReplicationProtos$ReplicationPeerDescription.access$6402:(Lorg/apache/hadoop/hbase/shaded/protobuf/generated/ReplicationProtos$ReplicationPeerDescription;Lorg/apache/hadoop/hbase/shaded/protobuf/generated/ReplicationProtos$ReplicationPeer;)Lorg/apache/hadoop/hbase/shaded/protobuf/generated/ReplicationProtos$ReplicationPeer;
     126: pop
     127: iload_2
     128: bipush        8
     130: iand
     131: bipush        8
     133: if_icmpne     141
     136: iload_3
     137: bipush        8
     139: ior
     140: istore_3
     141: aload_0
     142: getfield      #25                 // Field syncReplicationStateBuilder_:Lorg/apache/hbase/thirdparty/com/google/protobuf/SingleFieldBuilderV3;
     145: ifnonnull     160
     148: aload_1
     149: aload_0
     150: getfield      #13                 // Field syncReplicationState_:Lorg/apache/hadoop/hbase/shaded/protobuf/generated/ReplicationProtos$SyncReplicationState;
     153: invokestatic  #37                 // Method org/apache/hadoop/hbase/shaded/protobuf/generated/ReplicationProtos$ReplicationPeerDescription.access$6502:(Lorg/apache/hadoop/hbase/shaded/protobuf/generated/ReplicationProtos$ReplicationPeerDescription;Lorg/apache/hadoop/hbase/shaded/protobuf/generated/ReplicationProtos$SyncReplicationState;)Lorg/apache/hadoop/hbase/shaded/protobuf/generated/ReplicationProtos$SyncReplicationState;
     156: pop
     157: goto          175
     160: aload_1
     161: aload_0
     162: getfield      #25                 // Field syncReplicationStateBuilder_:Lorg/apache/hbase/thirdparty/com/google/protobuf/SingleFieldBuilderV3;
     165: invokevirtual #33                 // Method org/apache/hbase/thirdparty/com/google/protobuf/SingleFieldBuilderV3.build:()Lorg/apache/hbase/thirdparty/com/google/protobuf/AbstractMessage;
     168: checkcast     #38                 // class org/apache/hadoop/hbase/shaded/protobuf/generated/ReplicationProtos$SyncReplicationState
     171: invokestatic  #37                 // Method org/apache/hadoop/hbase/shaded/protobuf/generated/ReplicationProtos$ReplicationPeerDescription.access$6502:(Lorg/apache/hadoop/hbase/shaded/protobuf/generated/ReplicationProtos$ReplicationPeerDescription;Lorg/apache/hadoop/hbase/shaded/protobuf/generated/ReplicationProtos$SyncReplicationState;)Lorg/apache/hadoop/hbase/shaded/protobuf/generated/ReplicationProtos$SyncReplicationState;
     174: pop
     175: aload_1
     176: iload_3
     177: invokestatic  #39                 // Method org/apache/hadoop/hbase/shaded/protobuf/generated/ReplicationProtos$ReplicationPeerDescription.access$6602:(Lorg/apache/hadoop/hbase/shaded/protobuf/generated/ReplicationProtos$ReplicationPeerDescription;I)I
     180: pop
     181: aload_0
     182: invokevirtual #40                 // Method onBuilt:()V
     185: aload_1
     186: areturn

  public org.apache.hadoop.hbase.shaded.protobuf.generated.ReplicationProtos$ReplicationPeerDescription$Builder clone();
    Code:
       0: aload_0
       1: invokespecial #41                 // Method org/apache/hbase/thirdparty/com/google/protobuf/GeneratedMessageV3$Builder.clone:()Lorg/apache/hbase/thirdparty/com/google/protobuf/GeneratedMessageV3$Builder;
       4: checkcast     #6                  // class org/apache/hadoop/hbase/shaded/protobuf/generated/ReplicationProtos$ReplicationPeerDescription$Builder
       7: areturn

  public org.apache.hadoop.hbase.shaded.protobuf.generated.ReplicationProtos$ReplicationPeerDescription$Builder setField(org.apache.hbase.thirdparty.com.google.protobuf.Descriptors$FieldDescriptor, java.lang.Object);
    Code:
       0: aload_0
       1: aload_1
       2: aload_2
       3: invokespecial #42                 // Method org/apache/hbase/thirdparty/com/google/protobuf/GeneratedMessageV3$Builder.setField:(Lorg/apache/hbase/thirdparty/com/google/protobuf/Descriptors$FieldDescriptor;Ljava/lang/Object;)Lorg/apache/hbase/thirdparty/com/google/protobuf/GeneratedMessageV3$Builder;
       6: checkcast     #6                  // class org/apache/hadoop/hbase/shaded/protobuf/generated/ReplicationProtos$ReplicationPeerDescription$Builder
       9: areturn

  public org.apache.hadoop.hbase.shaded.protobuf.generated.ReplicationProtos$ReplicationPeerDescription$Builder clearField(org.apache.hbase.thirdparty.com.google.protobuf.Descriptors$FieldDescriptor);
    Code:
       0: aload_0
       1: aload_1
       2: invokespecial #43                 // Method org/apache/hbase/thirdparty/com/google/protobuf/GeneratedMessageV3$Builder.clearField:(Lorg/apache/hbase/thirdparty/com/google/protobuf/Descriptors$FieldDescriptor;)Lorg/apache/hbase/thirdparty/com/google/protobuf/GeneratedMessageV3$Builder;
       5: checkcast     #6                  // class org/apache/hadoop/hbase/shaded/protobuf/generated/ReplicationProtos$ReplicationPeerDescription$Builder
       8: areturn

  public org.apache.hadoop.hbase.shaded.protobuf.generated.ReplicationProtos$ReplicationPeerDescription$Builder clearOneof(org.apache.hbase.thirdparty.com.google.protobuf.Descriptors$OneofDescriptor);
    Code:
       0: aload_0
       1: aload_1
       2: invokespecial #44                 // Method org/apache/hbase/thirdparty/com/google/protobuf/GeneratedMessageV3$Builder.clearOneof:(Lorg/apache/hbase/thirdparty/com/google/protobuf/Descriptors$OneofDescriptor;)Lorg/apache/hbase/thirdparty/com/google/protobuf/GeneratedMessageV3$Builder;
       5: checkcast     #6                  // class org/apache/hadoop/hbase/shaded/protobuf/generated/ReplicationProtos$ReplicationPeerDescription$Builder
       8: areturn

  public org.apache.hadoop.hbase.shaded.protobuf.generated.ReplicationProtos$ReplicationPeerDescription$Builder setRepeatedField(org.apache.hbase.thirdparty.com.google.protobuf.Descriptors$FieldDescriptor, int, java.lang.Object);
    Code:
       0: aload_0
       1: aload_1
       2: iload_2
       3: aload_3
       4: invokespecial #45                 // Method org/apache/hbase/thirdparty/com/google/protobuf/GeneratedMessageV3$Builder.setRepeatedField:(Lorg/apache/hbase/thirdparty/com/google/protobuf/Descriptors$FieldDescriptor;ILjava/lang/Object;)Lorg/apache/hbase/thirdparty/com/google/protobuf/GeneratedMessageV3$Builder;
       7: checkcast     #6                  // class org/apache/hadoop/hbase/shaded/protobuf/generated/ReplicationProtos$ReplicationPeerDescription$Builder
      10: areturn

  public org.apache.hadoop.hbase.shaded.protobuf.generated.ReplicationProtos$ReplicationPeerDescription$Builder addRepeatedField(org.apache.hbase.thirdparty.com.google.protobuf.Descriptors$FieldDescriptor, java.lang.Object);
    Code:
       0: aload_0
       1: aload_1
       2: aload_2
       3: invokespecial #46                 // Method org/apache/hbase/thirdparty/com/google/protobuf/GeneratedMessageV3$Builder.addRepeatedField:(Lorg/apache/hbase/thirdparty/com/google/protobuf/Descriptors$FieldDescriptor;Ljava/lang/Object;)Lorg/apache/hbase/thirdparty/com/google/protobuf/GeneratedMessageV3$Builder;
       6: checkcast     #6                  // class org/apache/hadoop/hbase/shaded/protobuf/generated/ReplicationProtos$ReplicationPeerDescription$Builder
       9: areturn

  public org.apache.hadoop.hbase.shaded.protobuf.generated.ReplicationProtos$ReplicationPeerDescription$Builder mergeFrom(org.apache.hbase.thirdparty.com.google.protobuf.Message);
    Code:
       0: aload_1
       1: instanceof    #5                  // class org/apache/hadoop/hbase/shaded/protobuf/generated/ReplicationProtos$ReplicationPeerDescription
       4: ifeq          16
       7: aload_0
       8: aload_1
       9: checkcast     #5                  // class org/apache/hadoop/hbase/shaded/protobuf/generated/ReplicationProtos$ReplicationPeerDescription
      12: invokevirtual #47                 // Method mergeFrom:(Lorg/apache/hadoop/hbase/shaded/protobuf/generated/ReplicationProtos$ReplicationPeerDescription;)Lorg/apache/hadoop/hbase/shaded/protobuf/generated/ReplicationProtos$ReplicationPeerDescription$Builder;
      15: areturn
      16: aload_0
      17: aload_1
      18: invokespecial #48                 // Method org/apache/hbase/thirdparty/com/google/protobuf/GeneratedMessageV3$Builder.mergeFrom:(Lorg/apache/hbase/thirdparty/com/google/protobuf/Message;)Lorg/apache/hbase/thirdparty/com/google/protobuf/AbstractMessage$Builder;
      21: pop
      22: aload_0
      23: areturn

  public org.apache.hadoop.hbase.shaded.protobuf.generated.ReplicationProtos$ReplicationPeerDescription$Builder mergeFrom(org.apache.hadoop.hbase.shaded.protobuf.generated.ReplicationProtos$ReplicationPeerDescription);
    Code:
       0: aload_1
       1: invokestatic  #26                 // Method org/apache/hadoop/hbase/shaded/protobuf/generated/ReplicationProtos$ReplicationPeerDescription.getDefaultInstance:()Lorg/apache/hadoop/hbase/shaded/protobuf/generated/ReplicationProtos$ReplicationPeerDescription;
       4: if_acmpne     9
       7: aload_0
       8: areturn
       9: aload_1
      10: invokevirtual #49                 // Method org/apache/hadoop/hbase/shaded/protobuf/generated/ReplicationProtos$ReplicationPeerDescription.hasId:()Z
      13: ifeq          38
      16: aload_0
      17: dup
      18: getfield      #21                 // Field bitField0_:I
      21: iconst_1
      22: ior
      23: putfield      #21                 // Field bitField0_:I
      26: aload_0
      27: aload_1
      28: invokestatic  #50                 // Method org/apache/hadoop/hbase/shaded/protobuf/generated/ReplicationProtos$ReplicationPeerDescription.access$6200:(Lorg/apache/hadoop/hbase/shaded/protobuf/generated/ReplicationProtos$ReplicationPeerDescription;)Ljava/lang/Object;
      31: putfield      #10                 // Field id_:Ljava/lang/Object;
      34: aload_0
      35: invokevirtual #51                 // Method onChanged:()V
      38: aload_1
      39: invokevirtual #52                 // Method org/apache/hadoop/hbase/shaded/protobuf/generated/ReplicationProtos$ReplicationPeerDescription.hasState:()Z
      42: ifeq          54
      45: aload_0
      46: aload_1
      47: invokevirtual #53                 // Method org/apache/hadoop/hbase/shaded/protobuf/generated/ReplicationProtos$ReplicationPeerDescription.getState:()Lorg/apache/hadoop/hbase/shaded/protobuf/generated/ReplicationProtos$ReplicationState;
      50: invokevirtual #54                 // Method mergeState:(Lorg/apache/hadoop/hbase/shaded/protobuf/generated/ReplicationProtos$ReplicationState;)Lorg/apache/hadoop/hbase/shaded/protobuf/generated/ReplicationProtos$ReplicationPeerDescription$Builder;
      53: pop
      54: aload_1
      55: invokevirtual #55                 // Method org/apache/hadoop/hbase/shaded/protobuf/generated/ReplicationProtos$ReplicationPeerDescription.hasConfig:()Z
      58: ifeq          70
      61: aload_0
      62: aload_1
      63: invokevirtual #56                 // Method org/apache/hadoop/hbase/shaded/protobuf/generated/ReplicationProtos$ReplicationPeerDescription.getConfig:()Lorg/apache/hadoop/hbase/shaded/protobuf/generated/ReplicationProtos$ReplicationPeer;
      66: invokevirtual #57                 // Method mergeConfig:(Lorg/apache/hadoop/hbase/shaded/protobuf/generated/ReplicationProtos$ReplicationPeer;)Lorg/apache/hadoop/hbase/shaded/protobuf/generated/ReplicationProtos$ReplicationPeerDescription$Builder;
      69: pop
      70: aload_1
      71: invokevirtual #58                 // Method org/apache/hadoop/hbase/shaded/protobuf/generated/ReplicationProtos$ReplicationPeerDescription.hasSyncReplicationState:()Z
      74: ifeq          86
      77: aload_0
      78: aload_1
      79: invokevirtual #59                 // Method org/apache/hadoop/hbase/shaded/protobuf/generated/ReplicationProtos$ReplicationPeerDescription.getSyncReplicationState:()Lorg/apache/hadoop/hbase/shaded/protobuf/generated/ReplicationProtos$SyncReplicationState;
      82: invokevirtual #60                 // Method mergeSyncReplicationState:(Lorg/apache/hadoop/hbase/shaded/protobuf/generated/ReplicationProtos$SyncReplicationState;)Lorg/apache/hadoop/hbase/shaded/protobuf/generated/ReplicationProtos$ReplicationPeerDescription$Builder;
      85: pop
      86: aload_0
      87: aload_1
      88: invokestatic  #61                 // Method org/apache/hadoop/hbase/shaded/protobuf/generated/ReplicationProtos$ReplicationPeerDescription.access$6700:(Lorg/apache/hadoop/hbase/shaded/protobuf/generated/ReplicationProtos$ReplicationPeerDescription;)Lorg/apache/hbase/thirdparty/com/google/protobuf/UnknownFieldSet;
      91: invokevirtual #62                 // Method mergeUnknownFields:(Lorg/apache/hbase/thirdparty/com/google/protobuf/UnknownFieldSet;)Lorg/apache/hadoop/hbase/shaded/protobuf/generated/ReplicationProtos$ReplicationPeerDescription$Builder;
      94: pop
      95: aload_0
      96: invokevirtual #51                 // Method onChanged:()V
      99: aload_0
     100: areturn

  public final boolean isInitialized();
    Code:
       0: aload_0
       1: invokevirtual #63                 // Method hasId:()Z
       4: ifne          9
       7: iconst_0
       8: ireturn
       9: aload_0
      10: invokevirtual #64                 // Method hasState:()Z
      13: ifne          18
      16: iconst_0
      17: ireturn
      18: aload_0
      19: invokevirtual #65                 // Method hasConfig:()Z
      22: ifne          27
      25: iconst_0
      26: ireturn
      27: aload_0
      28: invokevirtual #66                 // Method getState:()Lorg/apache/hadoop/hbase/shaded/protobuf/generated/ReplicationProtos$ReplicationState;
      31: invokevirtual #67                 // Method org/apache/hadoop/hbase/shaded/protobuf/generated/ReplicationProtos$ReplicationState.isInitialized:()Z
      34: ifne          39
      37: iconst_0
      38: ireturn
      39: aload_0
      40: invokevirtual #68                 // Method getConfig:()Lorg/apache/hadoop/hbase/shaded/protobuf/generated/ReplicationProtos$ReplicationPeer;
      43: invokevirtual #69                 // Method org/apache/hadoop/hbase/shaded/protobuf/generated/ReplicationProtos$ReplicationPeer.isInitialized:()Z
      46: ifne          51
      49: iconst_0
      50: ireturn
      51: aload_0
      52: invokevirtual #70                 // Method hasSyncReplicationState:()Z
      55: ifeq          70
      58: aload_0
      59: invokevirtual #71                 // Method getSyncReplicationState:()Lorg/apache/hadoop/hbase/shaded/protobuf/generated/ReplicationProtos$SyncReplicationState;
      62: invokevirtual #72                 // Method org/apache/hadoop/hbase/shaded/protobuf/generated/ReplicationProtos$SyncReplicationState.isInitialized:()Z
      65: ifne          70
      68: iconst_0
      69: ireturn
      70: iconst_1
      71: ireturn

  public org.apache.hadoop.hbase.shaded.protobuf.generated.ReplicationProtos$ReplicationPeerDescription$Builder mergeFrom(org.apache.hbase.thirdparty.com.google.protobuf.CodedInputStream, org.apache.hbase.thirdparty.com.google.protobuf.ExtensionRegistryLite) throws java.io.IOException;
    Code:
       0: aconst_null
       1: astore_3
       2: getstatic     #73                 // Field org/apache/hadoop/hbase/shaded/protobuf/generated/ReplicationProtos$ReplicationPeerDescription.PARSER:Lorg/apache/hbase/thirdparty/com/google/protobuf/Parser;
       5: aload_1
       6: aload_2
       7: invokeinterface #74,  3           // InterfaceMethod org/apache/hbase/thirdparty/com/google/protobuf/Parser.parsePartialFrom:(Lorg/apache/hbase/thirdparty/com/google/protobuf/CodedInputStream;Lorg/apache/hbase/thirdparty/com/google/protobuf/ExtensionRegistryLite;)Ljava/lang/Object;
      12: checkcast     #5                  // class org/apache/hadoop/hbase/shaded/protobuf/generated/ReplicationProtos$ReplicationPeerDescription
      15: astore_3
      16: aload_3
      17: ifnull        61
      20: aload_0
      21: aload_3
      22: invokevirtual #47                 // Method mergeFrom:(Lorg/apache/hadoop/hbase/shaded/protobuf/generated/ReplicationProtos$ReplicationPeerDescription;)Lorg/apache/hadoop/hbase/shaded/protobuf/generated/ReplicationProtos$ReplicationPeerDescription$Builder;
      25: pop
      26: goto          61
      29: astore        4
      31: aload         4
      33: invokevirtual #76                 // Method org/apache/hbase/thirdparty/com/google/protobuf/InvalidProtocolBufferException.getUnfinishedMessage:()Lorg/apache/hbase/thirdparty/com/google/protobuf/MessageLite;
      36: checkcast     #5                  // class org/apache/hadoop/hbase/shaded/protobuf/generated/ReplicationProtos$ReplicationPeerDescription
      39: astore_3
      40: aload         4
      42: invokevirtual #77                 // Method org/apache/hbase/thirdparty/com/google/protobuf/InvalidProtocolBufferException.unwrapIOException:()Ljava/io/IOException;
      45: athrow
      46: astore        5
      48: aload_3
      49: ifnull        58
      52: aload_0
      53: aload_3
      54: invokevirtual #47                 // Method mergeFrom:(Lorg/apache/hadoop/hbase/shaded/protobuf/generated/ReplicationProtos$ReplicationPeerDescription;)Lorg/apache/hadoop/hbase/shaded/protobuf/generated/ReplicationProtos$ReplicationPeerDescription$Builder;
      57: pop
      58: aload         5
      60: athrow
      61: aload_0
      62: areturn
    Exception table:
       from    to  target type
           2    16    29   Class org/apache/hbase/thirdparty/com/google/protobuf/InvalidProtocolBufferException
           2    16    46   any
          29    48    46   any

  public boolean hasId();
    Code:
       0: aload_0
       1: getfield      #21                 // Field bitField0_:I
       4: iconst_1
       5: iand
       6: iconst_1
       7: if_icmpne     14
      10: iconst_1
      11: goto          15
      14: iconst_0
      15: ireturn

  public java.lang.String getId();
    Code:
       0: aload_0
       1: getfield      #10                 // Field id_:Ljava/lang/Object;
       4: astore_1
       5: aload_1
       6: instanceof    #78                 // class java/lang/String
       9: ifne          36
      12: aload_1
      13: checkcast     #79                 // class org/apache/hbase/thirdparty/com/google/protobuf/ByteString
      16: astore_2
      17: aload_2
      18: invokevirtual #80                 // Method org/apache/hbase/thirdparty/com/google/protobuf/ByteString.toStringUtf8:()Ljava/lang/String;
      21: astore_3
      22: aload_2
      23: invokevirtual #81                 // Method org/apache/hbase/thirdparty/com/google/protobuf/ByteString.isValidUtf8:()Z
      26: ifeq          34
      29: aload_0
      30: aload_3
      31: putfield      #10                 // Field id_:Ljava/lang/Object;
      34: aload_3
      35: areturn
      36: aload_1
      37: checkcast     #78                 // class java/lang/String
      40: areturn

  public org.apache.hbase.thirdparty.com.google.protobuf.ByteString getIdBytes();
    Code:
       0: aload_0
       1: getfield      #10                 // Field id_:Ljava/lang/Object;
       4: astore_1
       5: aload_1
       6: instanceof    #78                 // class java/lang/String
       9: ifeq          27
      12: aload_1
      13: checkcast     #78                 // class java/lang/String
      16: invokestatic  #82                 // Method org/apache/hbase/thirdparty/com/google/protobuf/ByteString.copyFromUtf8:(Ljava/lang/String;)Lorg/apache/hbase/thirdparty/com/google/protobuf/ByteString;
      19: astore_2
      20: aload_0
      21: aload_2
      22: putfield      #10                 // Field id_:Ljava/lang/Object;
      25: aload_2
      26: areturn
      27: aload_1
      28: checkcast     #79                 // class org/apache/hbase/thirdparty/com/google/protobuf/ByteString
      31: areturn

  public org.apache.hadoop.hbase.shaded.protobuf.generated.ReplicationProtos$ReplicationPeerDescription$Builder setId(java.lang.String);
    Code:
       0: aload_1
       1: ifnonnull     12
       4: new           #83                 // class java/lang/NullPointerException
       7: dup
       8: invokespecial #84                 // Method java/lang/NullPointerException."<init>":()V
      11: athrow
      12: aload_0
      13: dup
      14: getfield      #21                 // Field bitField0_:I
      17: iconst_1
      18: ior
      19: putfield      #21                 // Field bitField0_:I
      22: aload_0
      23: aload_1
      24: putfield      #10                 // Field id_:Ljava/lang/Object;
      27: aload_0
      28: invokevirtual #51                 // Method onChanged:()V
      31: aload_0
      32: areturn

  public org.apache.hadoop.hbase.shaded.protobuf.generated.ReplicationProtos$ReplicationPeerDescription$Builder clearId();
    Code:
       0: aload_0
       1: aload_0
       2: getfield      #21                 // Field bitField0_:I
       5: bipush        -2
       7: iand
       8: putfield      #21                 // Field bitField0_:I
      11: aload_0
      12: invokestatic  #26                 // Method org/apache/hadoop/hbase/shaded/protobuf/generated/ReplicationProtos$ReplicationPeerDescription.getDefaultInstance:()Lorg/apache/hadoop/hbase/shaded/protobuf/generated/ReplicationProtos$ReplicationPeerDescription;
      15: invokevirtual #85                 // Method org/apache/hadoop/hbase/shaded/protobuf/generated/ReplicationProtos$ReplicationPeerDescription.getId:()Ljava/lang/String;
      18: putfield      #10                 // Field id_:Ljava/lang/Object;
      21: aload_0
      22: invokevirtual #51                 // Method onChanged:()V
      25: aload_0
      26: areturn

  public org.apache.hadoop.hbase.shaded.protobuf.generated.ReplicationProtos$ReplicationPeerDescription$Builder setIdBytes(org.apache.hbase.thirdparty.com.google.protobuf.ByteString);
    Code:
       0: aload_1
       1: ifnonnull     12
       4: new           #83                 // class java/lang/NullPointerException
       7: dup
       8: invokespecial #84                 // Method java/lang/NullPointerException."<init>":()V
      11: athrow
      12: aload_0
      13: dup
      14: getfield      #21                 // Field bitField0_:I
      17: iconst_1
      18: ior
      19: putfield      #21                 // Field bitField0_:I
      22: aload_0
      23: aload_1
      24: putfield      #10                 // Field id_:Ljava/lang/Object;
      27: aload_0
      28: invokevirtual #51                 // Method onChanged:()V
      31: aload_0
      32: areturn

  public boolean hasState();
    Code:
       0: aload_0
       1: getfield      #21                 // Field bitField0_:I
       4: iconst_2
       5: iand
       6: iconst_2
       7: if_icmpne     14
      10: iconst_1
      11: goto          15
      14: iconst_0
      15: ireturn

  public org.apache.hadoop.hbase.shaded.protobuf.generated.ReplicationProtos$ReplicationState getState();
    Code:
       0: aload_0
       1: getfield      #22                 // Field stateBuilder_:Lorg/apache/hbase/thirdparty/com/google/protobuf/SingleFieldBuilderV3;
       4: ifnonnull     25
       7: aload_0
       8: getfield      #11                 // Field state_:Lorg/apache/hadoop/hbase/shaded/protobuf/generated/ReplicationProtos$ReplicationState;
      11: ifnonnull     20
      14: invokestatic  #86                 // Method org/apache/hadoop/hbase/shaded/protobuf/generated/ReplicationProtos$ReplicationState.getDefaultInstance:()Lorg/apache/hadoop/hbase/shaded/protobuf/generated/ReplicationProtos$ReplicationState;
      17: goto          24
      20: aload_0
      21: getfield      #11                 // Field state_:Lorg/apache/hadoop/hbase/shaded/protobuf/generated/ReplicationProtos$ReplicationState;
      24: areturn
      25: aload_0
      26: getfield      #22                 // Field stateBuilder_:Lorg/apache/hbase/thirdparty/com/google/protobuf/SingleFieldBuilderV3;
      29: invokevirtual #87                 // Method org/apache/hbase/thirdparty/com/google/protobuf/SingleFieldBuilderV3.getMessage:()Lorg/apache/hbase/thirdparty/com/google/protobuf/AbstractMessage;
      32: checkcast     #34                 // class org/apache/hadoop/hbase/shaded/protobuf/generated/ReplicationProtos$ReplicationState
      35: areturn

  public org.apache.hadoop.hbase.shaded.protobuf.generated.ReplicationProtos$ReplicationPeerDescription$Builder setState(org.apache.hadoop.hbase.shaded.protobuf.generated.ReplicationProtos$ReplicationState);
    Code:
       0: aload_0
       1: getfield      #22                 // Field stateBuilder_:Lorg/apache/hbase/thirdparty/com/google/protobuf/SingleFieldBuilderV3;
       4: ifnonnull     31
       7: aload_1
       8: ifnonnull     19
      11: new           #83                 // class java/lang/NullPointerException
      14: dup
      15: invokespecial #84                 // Method java/lang/NullPointerException."<init>":()V
      18: athrow
      19: aload_0
      20: aload_1
      21: putfield      #11                 // Field state_:Lorg/apache/hadoop/hbase/shaded/protobuf/generated/ReplicationProtos$ReplicationState;
      24: aload_0
      25: invokevirtual #51                 // Method onChanged:()V
      28: goto          40
      31: aload_0
      32: getfield      #22                 // Field stateBuilder_:Lorg/apache/hbase/thirdparty/com/google/protobuf/SingleFieldBuilderV3;
      35: aload_1
      36: invokevirtual #88                 // Method org/apache/hbase/thirdparty/com/google/protobuf/SingleFieldBuilderV3.setMessage:(Lorg/apache/hbase/thirdparty/com/google/protobuf/AbstractMessage;)Lorg/apache/hbase/thirdparty/com/google/protobuf/SingleFieldBuilderV3;
      39: pop
      40: aload_0
      41: dup
      42: getfield      #21                 // Field bitField0_:I
      45: iconst_2
      46: ior
      47: putfield      #21                 // Field bitField0_:I
      50: aload_0
      51: areturn

  public org.apache.hadoop.hbase.shaded.protobuf.generated.ReplicationProtos$ReplicationPeerDescription$Builder setState(org.apache.hadoop.hbase.shaded.protobuf.generated.ReplicationProtos$ReplicationState$Builder);
    Code:
       0: aload_0
       1: getfield      #22                 // Field stateBuilder_:Lorg/apache/hbase/thirdparty/com/google/protobuf/SingleFieldBuilderV3;
       4: ifnonnull     22
       7: aload_0
       8: aload_1
       9: invokevirtual #89                 // Method org/apache/hadoop/hbase/shaded/protobuf/generated/ReplicationProtos$ReplicationState$Builder.build:()Lorg/apache/hadoop/hbase/shaded/protobuf/generated/ReplicationProtos$ReplicationState;
      12: putfield      #11                 // Field state_:Lorg/apache/hadoop/hbase/shaded/protobuf/generated/ReplicationProtos$ReplicationState;
      15: aload_0
      16: invokevirtual #51                 // Method onChanged:()V
      19: goto          34
      22: aload_0
      23: getfield      #22                 // Field stateBuilder_:Lorg/apache/hbase/thirdparty/com/google/protobuf/SingleFieldBuilderV3;
      26: aload_1
      27: invokevirtual #89                 // Method org/apache/hadoop/hbase/shaded/protobuf/generated/ReplicationProtos$ReplicationState$Builder.build:()Lorg/apache/hadoop/hbase/shaded/protobuf/generated/ReplicationProtos$ReplicationState;
      30: invokevirtual #88                 // Method org/apache/hbase/thirdparty/com/google/protobuf/SingleFieldBuilderV3.setMessage:(Lorg/apache/hbase/thirdparty/com/google/protobuf/AbstractMessage;)Lorg/apache/hbase/thirdparty/com/google/protobuf/SingleFieldBuilderV3;
      33: pop
      34: aload_0
      35: dup
      36: getfield      #21                 // Field bitField0_:I
      39: iconst_2
      40: ior
      41: putfield      #21                 // Field bitField0_:I
      44: aload_0
      45: areturn

  public org.apache.hadoop.hbase.shaded.protobuf.generated.ReplicationProtos$ReplicationPeerDescription$Builder mergeState(org.apache.hadoop.hbase.shaded.protobuf.generated.ReplicationProtos$ReplicationState);
    Code:
       0: aload_0
       1: getfield      #22                 // Field stateBuilder_:Lorg/apache/hbase/thirdparty/com/google/protobuf/SingleFieldBuilderV3;
       4: ifnonnull     67
       7: aload_0
       8: getfield      #21                 // Field bitField0_:I
      11: iconst_2
      12: iand
      13: iconst_2
      14: if_icmpne     55
      17: aload_0
      18: getfield      #11                 // Field state_:Lorg/apache/hadoop/hbase/shaded/protobuf/generated/ReplicationProtos$ReplicationState;
      21: ifnull        55
      24: aload_0
      25: getfield      #11                 // Field state_:Lorg/apache/hadoop/hbase/shaded/protobuf/generated/ReplicationProtos$ReplicationState;
      28: invokestatic  #86                 // Method org/apache/hadoop/hbase/shaded/protobuf/generated/ReplicationProtos$ReplicationState.getDefaultInstance:()Lorg/apache/hadoop/hbase/shaded/protobuf/generated/ReplicationProtos$ReplicationState;
      31: if_acmpeq     55
      34: aload_0
      35: aload_0
      36: getfield      #11                 // Field state_:Lorg/apache/hadoop/hbase/shaded/protobuf/generated/ReplicationProtos$ReplicationState;
      39: invokestatic  #90                 // Method org/apache/hadoop/hbase/shaded/protobuf/generated/ReplicationProtos$ReplicationState.newBuilder:(Lorg/apache/hadoop/hbase/shaded/protobuf/generated/ReplicationProtos$ReplicationState;)Lorg/apache/hadoop/hbase/shaded/protobuf/generated/ReplicationProtos$ReplicationState$Builder;
      42: aload_1
      43: invokevirtual #91                 // Method org/apache/hadoop/hbase/shaded/protobuf/generated/ReplicationProtos$ReplicationState$Builder.mergeFrom:(Lorg/apache/hadoop/hbase/shaded/protobuf/generated/ReplicationProtos$ReplicationState;)Lorg/apache/hadoop/hbase/shaded/protobuf/generated/ReplicationProtos$ReplicationState$Builder;
      46: invokevirtual #92                 // Method org/apache/hadoop/hbase/shaded/protobuf/generated/ReplicationProtos$ReplicationState$Builder.buildPartial:()Lorg/apache/hadoop/hbase/shaded/protobuf/generated/ReplicationProtos$ReplicationState;
      49: putfield      #11                 // Field state_:Lorg/apache/hadoop/hbase/shaded/protobuf/generated/ReplicationProtos$ReplicationState;
      52: goto          60
      55: aload_0
      56: aload_1
      57: putfield      #11                 // Field state_:Lorg/apache/hadoop/hbase/shaded/protobuf/generated/ReplicationProtos$ReplicationState;
      60: aload_0
      61: invokevirtual #51                 // Method onChanged:()V
      64: goto          76
      67: aload_0
      68: getfield      #22                 // Field stateBuilder_:Lorg/apache/hbase/thirdparty/com/google/protobuf/SingleFieldBuilderV3;
      71: aload_1
      72: invokevirtual #93                 // Method org/apache/hbase/thirdparty/com/google/protobuf/SingleFieldBuilderV3.mergeFrom:(Lorg/apache/hbase/thirdparty/com/google/protobuf/AbstractMessage;)Lorg/apache/hbase/thirdparty/com/google/protobuf/SingleFieldBuilderV3;
      75: pop
      76: aload_0
      77: dup
      78: getfield      #21                 // Field bitField0_:I
      81: iconst_2
      82: ior
      83: putfield      #21                 // Field bitField0_:I
      86: aload_0
      87: areturn

  public org.apache.hadoop.hbase.shaded.protobuf.generated.ReplicationProtos$ReplicationPeerDescription$Builder clearState();
    Code:
       0: aload_0
       1: getfield      #22                 // Field stateBuilder_:Lorg/apache/hbase/thirdparty/com/google/protobuf/SingleFieldBuilderV3;
       4: ifnonnull     19
       7: aload_0
       8: aconst_null
       9: putfield      #11                 // Field state_:Lorg/apache/hadoop/hbase/shaded/protobuf/generated/ReplicationProtos$ReplicationState;
      12: aload_0
      13: invokevirtual #51                 // Method onChanged:()V
      16: goto          27
      19: aload_0
      20: getfield      #22                 // Field stateBuilder_:Lorg/apache/hbase/thirdparty/com/google/protobuf/SingleFieldBuilderV3;
      23: invokevirtual #23                 // Method org/apache/hbase/thirdparty/com/google/protobuf/SingleFieldBuilderV3.clear:()Lorg/apache/hbase/thirdparty/com/google/protobuf/SingleFieldBuilderV3;
      26: pop
      27: aload_0
      28: aload_0
      29: getfield      #21                 // Field bitField0_:I
      32: bipush        -3
      34: iand
      35: putfield      #21                 // Field bitField0_:I
      38: aload_0
      39: areturn

  public org.apache.hadoop.hbase.shaded.protobuf.generated.ReplicationProtos$ReplicationState$Builder getStateBuilder();
    Code:
       0: aload_0
       1: dup
       2: getfield      #21                 // Field bitField0_:I
       5: iconst_2
       6: ior
       7: putfield      #21                 // Field bitField0_:I
      10: aload_0
      11: invokevirtual #51                 // Method onChanged:()V
      14: aload_0
      15: invokespecial #17                 // Method getStateFieldBuilder:()Lorg/apache/hbase/thirdparty/com/google/protobuf/SingleFieldBuilderV3;
      18: invokevirtual #94                 // Method org/apache/hbase/thirdparty/com/google/protobuf/SingleFieldBuilderV3.getBuilder:()Lorg/apache/hbase/thirdparty/com/google/protobuf/AbstractMessage$Builder;
      21: checkcast     #95                 // class org/apache/hadoop/hbase/shaded/protobuf/generated/ReplicationProtos$ReplicationState$Builder
      24: areturn

  public org.apache.hadoop.hbase.shaded.protobuf.generated.ReplicationProtos$ReplicationStateOrBuilder getStateOrBuilder();
    Code:
       0: aload_0
       1: getfield      #22                 // Field stateBuilder_:Lorg/apache/hbase/thirdparty/com/google/protobuf/SingleFieldBuilderV3;
       4: ifnull        18
       7: aload_0
       8: getfield      #22                 // Field stateBuilder_:Lorg/apache/hbase/thirdparty/com/google/protobuf/SingleFieldBuilderV3;
      11: invokevirtual #96                 // Method org/apache/hbase/thirdparty/com/google/protobuf/SingleFieldBuilderV3.getMessageOrBuilder:()Lorg/apache/hbase/thirdparty/com/google/protobuf/MessageOrBuilder;
      14: checkcast     #97                 // class org/apache/hadoop/hbase/shaded/protobuf/generated/ReplicationProtos$ReplicationStateOrBuilder
      17: areturn
      18: aload_0
      19: getfield      #11                 // Field state_:Lorg/apache/hadoop/hbase/shaded/protobuf/generated/ReplicationProtos$ReplicationState;
      22: ifnonnull     31
      25: invokestatic  #86                 // Method org/apache/hadoop/hbase/shaded/protobuf/generated/ReplicationProtos$ReplicationState.getDefaultInstance:()Lorg/apache/hadoop/hbase/shaded/protobuf/generated/ReplicationProtos$ReplicationState;
      28: goto          35
      31: aload_0
      32: getfield      #11                 // Field state_:Lorg/apache/hadoop/hbase/shaded/protobuf/generated/ReplicationProtos$ReplicationState;
      35: areturn

  public boolean hasConfig();
    Code:
       0: aload_0
       1: getfield      #21                 // Field bitField0_:I
       4: iconst_4
       5: iand
       6: iconst_4
       7: if_icmpne     14
      10: iconst_1
      11: goto          15
      14: iconst_0
      15: ireturn

  public org.apache.hadoop.hbase.shaded.protobuf.generated.ReplicationProtos$ReplicationPeer getConfig();
    Code:
       0: aload_0
       1: getfield      #24                 // Field configBuilder_:Lorg/apache/hbase/thirdparty/com/google/protobuf/SingleFieldBuilderV3;
       4: ifnonnull     25
       7: aload_0
       8: getfield      #12                 // Field config_:Lorg/apache/hadoop/hbase/shaded/protobuf/generated/ReplicationProtos$ReplicationPeer;
      11: ifnonnull     20
      14: invokestatic  #102                // Method org/apache/hadoop/hbase/shaded/protobuf/generated/ReplicationProtos$ReplicationPeer.getDefaultInstance:()Lorg/apache/hadoop/hbase/shaded/protobuf/generated/ReplicationProtos$ReplicationPeer;
      17: goto          24
      20: aload_0
      21: getfield      #12                 // Field config_:Lorg/apache/hadoop/hbase/shaded/protobuf/generated/ReplicationProtos$ReplicationPeer;
      24: areturn
      25: aload_0
      26: getfield      #24                 // Field configBuilder_:Lorg/apache/hbase/thirdparty/com/google/protobuf/SingleFieldBuilderV3;
      29: invokevirtual #87                 // Method org/apache/hbase/thirdparty/com/google/protobuf/SingleFieldBuilderV3.getMessage:()Lorg/apache/hbase/thirdparty/com/google/protobuf/AbstractMessage;
      32: checkcast     #36                 // class org/apache/hadoop/hbase/shaded/protobuf/generated/ReplicationProtos$ReplicationPeer
      35: areturn

  public org.apache.hadoop.hbase.shaded.protobuf.generated.ReplicationProtos$ReplicationPeerDescription$Builder setConfig(org.apache.hadoop.hbase.shaded.protobuf.generated.ReplicationProtos$ReplicationPeer);
    Code:
       0: aload_0
       1: getfield      #24                 // Field configBuilder_:Lorg/apache/hbase/thirdparty/com/google/protobuf/SingleFieldBuilderV3;
       4: ifnonnull     31
       7: aload_1
       8: ifnonnull     19
      11: new           #83                 // class java/lang/NullPointerException
      14: dup
      15: invokespecial #84                 // Method java/lang/NullPointerException."<init>":()V
      18: athrow
      19: aload_0
      20: aload_1
      21: putfield      #12                 // Field config_:Lorg/apache/hadoop/hbase/shaded/protobuf/generated/ReplicationProtos$ReplicationPeer;
      24: aload_0
      25: invokevirtual #51                 // Method onChanged:()V
      28: goto          40
      31: aload_0
      32: getfield      #24                 // Field configBuilder_:Lorg/apache/hbase/thirdparty/com/google/protobuf/SingleFieldBuilderV3;
      35: aload_1
      36: invokevirtual #88                 // Method org/apache/hbase/thirdparty/com/google/protobuf/SingleFieldBuilderV3.setMessage:(Lorg/apache/hbase/thirdparty/com/google/protobuf/AbstractMessage;)Lorg/apache/hbase/thirdparty/com/google/protobuf/SingleFieldBuilderV3;
      39: pop
      40: aload_0
      41: dup
      42: getfield      #21                 // Field bitField0_:I
      45: iconst_4
      46: ior
      47: putfield      #21                 // Field bitField0_:I
      50: aload_0
      51: areturn

  public org.apache.hadoop.hbase.shaded.protobuf.generated.ReplicationProtos$ReplicationPeerDescription$Builder setConfig(org.apache.hadoop.hbase.shaded.protobuf.generated.ReplicationProtos$ReplicationPeer$Builder);
    Code:
       0: aload_0
       1: getfield      #24                 // Field configBuilder_:Lorg/apache/hbase/thirdparty/com/google/protobuf/SingleFieldBuilderV3;
       4: ifnonnull     22
       7: aload_0
       8: aload_1
       9: invokevirtual #103                // Method org/apache/hadoop/hbase/shaded/protobuf/generated/ReplicationProtos$ReplicationPeer$Builder.build:()Lorg/apache/hadoop/hbase/shaded/protobuf/generated/ReplicationProtos$ReplicationPeer;
      12: putfield      #12                 // Field config_:Lorg/apache/hadoop/hbase/shaded/protobuf/generated/ReplicationProtos$ReplicationPeer;
      15: aload_0
      16: invokevirtual #51                 // Method onChanged:()V
      19: goto          34
      22: aload_0
      23: getfield      #24                 // Field configBuilder_:Lorg/apache/hbase/thirdparty/com/google/protobuf/SingleFieldBuilderV3;
      26: aload_1
      27: invokevirtual #103                // Method org/apache/hadoop/hbase/shaded/protobuf/generated/ReplicationProtos$ReplicationPeer$Builder.build:()Lorg/apache/hadoop/hbase/shaded/protobuf/generated/ReplicationProtos$ReplicationPeer;
      30: invokevirtual #88                 // Method org/apache/hbase/thirdparty/com/google/protobuf/SingleFieldBuilderV3.setMessage:(Lorg/apache/hbase/thirdparty/com/google/protobuf/AbstractMessage;)Lorg/apache/hbase/thirdparty/com/google/protobuf/SingleFieldBuilderV3;
      33: pop
      34: aload_0
      35: dup
      36: getfield      #21                 // Field bitField0_:I
      39: iconst_4
      40: ior
      41: putfield      #21                 // Field bitField0_:I
      44: aload_0
      45: areturn

  public org.apache.hadoop.hbase.shaded.protobuf.generated.ReplicationProtos$ReplicationPeerDescription$Builder mergeConfig(org.apache.hadoop.hbase.shaded.protobuf.generated.ReplicationProtos$ReplicationPeer);
    Code:
       0: aload_0
       1: getfield      #24                 // Field configBuilder_:Lorg/apache/hbase/thirdparty/com/google/protobuf/SingleFieldBuilderV3;
       4: ifnonnull     67
       7: aload_0
       8: getfield      #21                 // Field bitField0_:I
      11: iconst_4
      12: iand
      13: iconst_4
      14: if_icmpne     55
      17: aload_0
      18: getfield      #12                 // Field config_:Lorg/apache/hadoop/hbase/shaded/protobuf/generated/ReplicationProtos$ReplicationPeer;
      21: ifnull        55
      24: aload_0
      25: getfield      #12                 // Field config_:Lorg/apache/hadoop/hbase/shaded/protobuf/generated/ReplicationProtos$ReplicationPeer;
      28: invokestatic  #102                // Method org/apache/hadoop/hbase/shaded/protobuf/generated/ReplicationProtos$ReplicationPeer.getDefaultInstance:()Lorg/apache/hadoop/hbase/shaded/protobuf/generated/ReplicationProtos$ReplicationPeer;
      31: if_acmpeq     55
      34: aload_0
      35: aload_0
      36: getfield      #12                 // Field config_:Lorg/apache/hadoop/hbase/shaded/protobuf/generated/ReplicationProtos$ReplicationPeer;
      39: invokestatic  #104                // Method org/apache/hadoop/hbase/shaded/protobuf/generated/ReplicationProtos$ReplicationPeer.newBuilder:(Lorg/apache/hadoop/hbase/shaded/protobuf/generated/ReplicationProtos$ReplicationPeer;)Lorg/apache/hadoop/hbase/shaded/protobuf/generated/ReplicationProtos$ReplicationPeer$Builder;
      42: aload_1
      43: invokevirtual #105                // Method org/apache/hadoop/hbase/shaded/protobuf/generated/ReplicationProtos$ReplicationPeer$Builder.mergeFrom:(Lorg/apache/hadoop/hbase/shaded/protobuf/generated/ReplicationProtos$ReplicationPeer;)Lorg/apache/hadoop/hbase/shaded/protobuf/generated/ReplicationProtos$ReplicationPeer$Builder;
      46: invokevirtual #106                // Method org/apache/hadoop/hbase/shaded/protobuf/generated/ReplicationProtos$ReplicationPeer$Builder.buildPartial:()Lorg/apache/hadoop/hbase/shaded/protobuf/generated/ReplicationProtos$ReplicationPeer;
      49: putfield      #12                 // Field config_:Lorg/apache/hadoop/hbase/shaded/protobuf/generated/ReplicationProtos$ReplicationPeer;
      52: goto          60
      55: aload_0
      56: aload_1
      57: putfield      #12                 // Field config_:Lorg/apache/hadoop/hbase/shaded/protobuf/generated/ReplicationProtos$ReplicationPeer;
      60: aload_0
      61: invokevirtual #51                 // Method onChanged:()V
      64: goto          76
      67: aload_0
      68: getfield      #24                 // Field configBuilder_:Lorg/apache/hbase/thirdparty/com/google/protobuf/SingleFieldBuilderV3;
      71: aload_1
      72: invokevirtual #93                 // Method org/apache/hbase/thirdparty/com/google/protobuf/SingleFieldBuilderV3.mergeFrom:(Lorg/apache/hbase/thirdparty/com/google/protobuf/AbstractMessage;)Lorg/apache/hbase/thirdparty/com/google/protobuf/SingleFieldBuilderV3;
      75: pop
      76: aload_0
      77: dup
      78: getfield      #21                 // Field bitField0_:I
      81: iconst_4
      82: ior
      83: putfield      #21                 // Field bitField0_:I
      86: aload_0
      87: areturn

  public org.apache.hadoop.hbase.shaded.protobuf.generated.ReplicationProtos$ReplicationPeerDescription$Builder clearConfig();
    Code:
       0: aload_0
       1: getfield      #24                 // Field configBuilder_:Lorg/apache/hbase/thirdparty/com/google/protobuf/SingleFieldBuilderV3;
       4: ifnonnull     19
       7: aload_0
       8: aconst_null
       9: putfield      #12                 // Field config_:Lorg/apache/hadoop/hbase/shaded/protobuf/generated/ReplicationProtos$ReplicationPeer;
      12: aload_0
      13: invokevirtual #51                 // Method onChanged:()V
      16: goto          27
      19: aload_0
      20: getfield      #24                 // Field configBuilder_:Lorg/apache/hbase/thirdparty/com/google/protobuf/SingleFieldBuilderV3;
      23: invokevirtual #23                 // Method org/apache/hbase/thirdparty/com/google/protobuf/SingleFieldBuilderV3.clear:()Lorg/apache/hbase/thirdparty/com/google/protobuf/SingleFieldBuilderV3;
      26: pop
      27: aload_0
      28: aload_0
      29: getfield      #21                 // Field bitField0_:I
      32: bipush        -5
      34: iand
      35: putfield      #21                 // Field bitField0_:I
      38: aload_0
      39: areturn

  public org.apache.hadoop.hbase.shaded.protobuf.generated.ReplicationProtos$ReplicationPeer$Builder getConfigBuilder();
    Code:
       0: aload_0
       1: dup
       2: getfield      #21                 // Field bitField0_:I
       5: iconst_4
       6: ior
       7: putfield      #21                 // Field bitField0_:I
      10: aload_0
      11: invokevirtual #51                 // Method onChanged:()V
      14: aload_0
      15: invokespecial #18                 // Method getConfigFieldBuilder:()Lorg/apache/hbase/thirdparty/com/google/protobuf/SingleFieldBuilderV3;
      18: invokevirtual #94                 // Method org/apache/hbase/thirdparty/com/google/protobuf/SingleFieldBuilderV3.getBuilder:()Lorg/apache/hbase/thirdparty/com/google/protobuf/AbstractMessage$Builder;
      21: checkcast     #107                // class org/apache/hadoop/hbase/shaded/protobuf/generated/ReplicationProtos$ReplicationPeer$Builder
      24: areturn

  public org.apache.hadoop.hbase.shaded.protobuf.generated.ReplicationProtos$ReplicationPeerOrBuilder getConfigOrBuilder();
    Code:
       0: aload_0
       1: getfield      #24                 // Field configBuilder_:Lorg/apache/hbase/thirdparty/com/google/protobuf/SingleFieldBuilderV3;
       4: ifnull        18
       7: aload_0
       8: getfield      #24                 // Field configBuilder_:Lorg/apache/hbase/thirdparty/com/google/protobuf/SingleFieldBuilderV3;
      11: invokevirtual #96                 // Method org/apache/hbase/thirdparty/com/google/protobuf/SingleFieldBuilderV3.getMessageOrBuilder:()Lorg/apache/hbase/thirdparty/com/google/protobuf/MessageOrBuilder;
      14: checkcast     #108                // class org/apache/hadoop/hbase/shaded/protobuf/generated/ReplicationProtos$ReplicationPeerOrBuilder
      17: areturn
      18: aload_0
      19: getfield      #12                 // Field config_:Lorg/apache/hadoop/hbase/shaded/protobuf/generated/ReplicationProtos$ReplicationPeer;
      22: ifnonnull     31
      25: invokestatic  #102                // Method org/apache/hadoop/hbase/shaded/protobuf/generated/ReplicationProtos$ReplicationPeer.getDefaultInstance:()Lorg/apache/hadoop/hbase/shaded/protobuf/generated/ReplicationProtos$ReplicationPeer;
      28: goto          35
      31: aload_0
      32: getfield      #12                 // Field config_:Lorg/apache/hadoop/hbase/shaded/protobuf/generated/ReplicationProtos$ReplicationPeer;
      35: areturn

  public boolean hasSyncReplicationState();
    Code:
       0: aload_0
       1: getfield      #21                 // Field bitField0_:I
       4: bipush        8
       6: iand
       7: bipush        8
       9: if_icmpne     16
      12: iconst_1
      13: goto          17
      16: iconst_0
      17: ireturn

  public org.apache.hadoop.hbase.shaded.protobuf.generated.ReplicationProtos$SyncReplicationState getSyncReplicationState();
    Code:
       0: aload_0
       1: getfield      #25                 // Field syncReplicationStateBuilder_:Lorg/apache/hbase/thirdparty/com/google/protobuf/SingleFieldBuilderV3;
       4: ifnonnull     25
       7: aload_0
       8: getfield      #13                 // Field syncReplicationState_:Lorg/apache/hadoop/hbase/shaded/protobuf/generated/ReplicationProtos$SyncReplicationState;
      11: ifnonnull     20
      14: invokestatic  #109                // Method org/apache/hadoop/hbase/shaded/protobuf/generated/ReplicationProtos$SyncReplicationState.getDefaultInstance:()Lorg/apache/hadoop/hbase/shaded/protobuf/generated/ReplicationProtos$SyncReplicationState;
      17: goto          24
      20: aload_0
      21: getfield      #13                 // Field syncReplicationState_:Lorg/apache/hadoop/hbase/shaded/protobuf/generated/ReplicationProtos$SyncReplicationState;
      24: areturn
      25: aload_0
      26: getfield      #25                 // Field syncReplicationStateBuilder_:Lorg/apache/hbase/thirdparty/com/google/protobuf/SingleFieldBuilderV3;
      29: invokevirtual #87                 // Method org/apache/hbase/thirdparty/com/google/protobuf/SingleFieldBuilderV3.getMessage:()Lorg/apache/hbase/thirdparty/com/google/protobuf/AbstractMessage;
      32: checkcast     #38                 // class org/apache/hadoop/hbase/shaded/protobuf/generated/ReplicationProtos$SyncReplicationState
      35: areturn

  public org.apache.hadoop.hbase.shaded.protobuf.generated.ReplicationProtos$ReplicationPeerDescription$Builder setSyncReplicationState(org.apache.hadoop.hbase.shaded.protobuf.generated.ReplicationProtos$SyncReplicationState);
    Code:
       0: aload_0
       1: getfield      #25                 // Field syncReplicationStateBuilder_:Lorg/apache/hbase/thirdparty/com/google/protobuf/SingleFieldBuilderV3;
       4: ifnonnull     31
       7: aload_1
       8: ifnonnull     19
      11: new           #83                 // class java/lang/NullPointerException
      14: dup
      15: invokespecial #84                 // Method java/lang/NullPointerException."<init>":()V
      18: athrow
      19: aload_0
      20: aload_1
      21: putfield      #13                 // Field syncReplicationState_:Lorg/apache/hadoop/hbase/shaded/protobuf/generated/ReplicationProtos$SyncReplicationState;
      24: aload_0
      25: invokevirtual #51                 // Method onChanged:()V
      28: goto          40
      31: aload_0
      32: getfield      #25                 // Field syncReplicationStateBuilder_:Lorg/apache/hbase/thirdparty/com/google/protobuf/SingleFieldBuilderV3;
      35: aload_1
      36: invokevirtual #88                 // Method org/apache/hbase/thirdparty/com/google/protobuf/SingleFieldBuilderV3.setMessage:(Lorg/apache/hbase/thirdparty/com/google/protobuf/AbstractMessage;)Lorg/apache/hbase/thirdparty/com/google/protobuf/SingleFieldBuilderV3;
      39: pop
      40: aload_0
      41: dup
      42: getfield      #21                 // Field bitField0_:I
      45: bipush        8
      47: ior
      48: putfield      #21                 // Field bitField0_:I
      51: aload_0
      52: areturn

  public org.apache.hadoop.hbase.shaded.protobuf.generated.ReplicationProtos$ReplicationPeerDescription$Builder setSyncReplicationState(org.apache.hadoop.hbase.shaded.protobuf.generated.ReplicationProtos$SyncReplicationState$Builder);
    Code:
       0: aload_0
       1: getfield      #25                 // Field syncReplicationStateBuilder_:Lorg/apache/hbase/thirdparty/com/google/protobuf/SingleFieldBuilderV3;
       4: ifnonnull     22
       7: aload_0
       8: aload_1
       9: invokevirtual #110                // Method org/apache/hadoop/hbase/shaded/protobuf/generated/ReplicationProtos$SyncReplicationState$Builder.build:()Lorg/apache/hadoop/hbase/shaded/protobuf/generated/ReplicationProtos$SyncReplicationState;
      12: putfield      #13                 // Field syncReplicationState_:Lorg/apache/hadoop/hbase/shaded/protobuf/generated/ReplicationProtos$SyncReplicationState;
      15: aload_0
      16: invokevirtual #51                 // Method onChanged:()V
      19: goto          34
      22: aload_0
      23: getfield      #25                 // Field syncReplicationStateBuilder_:Lorg/apache/hbase/thirdparty/com/google/protobuf/SingleFieldBuilderV3;
      26: aload_1
      27: invokevirtual #110                // Method org/apache/hadoop/hbase/shaded/protobuf/generated/ReplicationProtos$SyncReplicationState$Builder.build:()Lorg/apache/hadoop/hbase/shaded/protobuf/generated/ReplicationProtos$SyncReplicationState;
      30: invokevirtual #88                 // Method org/apache/hbase/thirdparty/com/google/protobuf/SingleFieldBuilderV3.setMessage:(Lorg/apache/hbase/thirdparty/com/google/protobuf/AbstractMessage;)Lorg/apache/hbase/thirdparty/com/google/protobuf/SingleFieldBuilderV3;
      33: pop
      34: aload_0
      35: dup
      36: getfield      #21                 // Field bitField0_:I
      39: bipush        8
      41: ior
      42: putfield      #21                 // Field bitField0_:I
      45: aload_0
      46: areturn

  public org.apache.hadoop.hbase.shaded.protobuf.generated.ReplicationProtos$ReplicationPeerDescription$Builder mergeSyncReplicationState(org.apache.hadoop.hbase.shaded.protobuf.generated.ReplicationProtos$SyncReplicationState);
    Code:
       0: aload_0
       1: getfield      #25                 // Field syncReplicationStateBuilder_:Lorg/apache/hbase/thirdparty/com/google/protobuf/SingleFieldBuilderV3;
       4: ifnonnull     69
       7: aload_0
       8: getfield      #21                 // Field bitField0_:I
      11: bipush        8
      13: iand
      14: bipush        8
      16: if_icmpne     57
      19: aload_0
      20: getfield      #13                 // Field syncReplicationState_:Lorg/apache/hadoop/hbase/shaded/protobuf/generated/ReplicationProtos$SyncReplicationState;
      23: ifnull        57
      26: aload_0
      27: getfield      #13                 // Field syncReplicationState_:Lorg/apache/hadoop/hbase/shaded/protobuf/generated/ReplicationProtos$SyncReplicationState;
      30: invokestatic  #109                // Method org/apache/hadoop/hbase/shaded/protobuf/generated/ReplicationProtos$SyncReplicationState.getDefaultInstance:()Lorg/apache/hadoop/hbase/shaded/protobuf/generated/ReplicationProtos$SyncReplicationState;
      33: if_acmpeq     57
      36: aload_0
      37: aload_0
      38: getfield      #13                 // Field syncReplicationState_:Lorg/apache/hadoop/hbase/shaded/protobuf/generated/ReplicationProtos$SyncReplicationState;
      41: invokestatic  #111                // Method org/apache/hadoop/hbase/shaded/protobuf/generated/ReplicationProtos$SyncReplicationState.newBuilder:(Lorg/apache/hadoop/hbase/shaded/protobuf/generated/ReplicationProtos$SyncReplicationState;)Lorg/apache/hadoop/hbase/shaded/protobuf/generated/ReplicationProtos$SyncReplicationState$Builder;
      44: aload_1
      45: invokevirtual #112                // Method org/apache/hadoop/hbase/shaded/protobuf/generated/ReplicationProtos$SyncReplicationState$Builder.mergeFrom:(Lorg/apache/hadoop/hbase/shaded/protobuf/generated/ReplicationProtos$SyncReplicationState;)Lorg/apache/hadoop/hbase/shaded/protobuf/generated/ReplicationProtos$SyncReplicationState$Builder;
      48: invokevirtual #113                // Method org/apache/hadoop/hbase/shaded/protobuf/generated/ReplicationProtos$SyncReplicationState$Builder.buildPartial:()Lorg/apache/hadoop/hbase/shaded/protobuf/generated/ReplicationProtos$SyncReplicationState;
      51: putfield      #13                 // Field syncReplicationState_:Lorg/apache/hadoop/hbase/shaded/protobuf/generated/ReplicationProtos$SyncReplicationState;
      54: goto          62
      57: aload_0
      58: aload_1
      59: putfield      #13                 // Field syncReplicationState_:Lorg/apache/hadoop/hbase/shaded/protobuf/generated/ReplicationProtos$SyncReplicationState;
      62: aload_0
      63: invokevirtual #51                 // Method onChanged:()V
      66: goto          78
      69: aload_0
      70: getfield      #25                 // Field syncReplicationStateBuilder_:Lorg/apache/hbase/thirdparty/com/google/protobuf/SingleFieldBuilderV3;
      73: aload_1
      74: invokevirtual #93                 // Method org/apache/hbase/thirdparty/com/google/protobuf/SingleFieldBuilderV3.mergeFrom:(Lorg/apache/hbase/thirdparty/com/google/protobuf/AbstractMessage;)Lorg/apache/hbase/thirdparty/com/google/protobuf/SingleFieldBuilderV3;
      77: pop
      78: aload_0
      79: dup
      80: getfield      #21                 // Field bitField0_:I
      83: bipush        8
      85: ior
      86: putfield      #21                 // Field bitField0_:I
      89: aload_0
      90: areturn

  public org.apache.hadoop.hbase.shaded.protobuf.generated.ReplicationProtos$ReplicationPeerDescription$Builder clearSyncReplicationState();
    Code:
       0: aload_0
       1: getfield      #25                 // Field syncReplicationStateBuilder_:Lorg/apache/hbase/thirdparty/com/google/protobuf/SingleFieldBuilderV3;
       4: ifnonnull     19
       7: aload_0
       8: aconst_null
       9: putfield      #13                 // Field syncReplicationState_:Lorg/apache/hadoop/hbase/shaded/protobuf/generated/ReplicationProtos$SyncReplicationState;
      12: aload_0
      13: invokevirtual #51                 // Method onChanged:()V
      16: goto          27
      19: aload_0
      20: getfield      #25                 // Field syncReplicationStateBuilder_:Lorg/apache/hbase/thirdparty/com/google/protobuf/SingleFieldBuilderV3;
      23: invokevirtual #23                 // Method org/apache/hbase/thirdparty/com/google/protobuf/SingleFieldBuilderV3.clear:()Lorg/apache/hbase/thirdparty/com/google/protobuf/SingleFieldBuilderV3;
      26: pop
      27: aload_0
      28: aload_0
      29: getfield      #21                 // Field bitField0_:I
      32: bipush        -9
      34: iand
      35: putfield      #21                 // Field bitField0_:I
      38: aload_0
      39: areturn

  public org.apache.hadoop.hbase.shaded.protobuf.generated.ReplicationProtos$SyncReplicationState$Builder getSyncReplicationStateBuilder();
    Code:
       0: aload_0
       1: dup
       2: getfield      #21                 // Field bitField0_:I
       5: bipush        8
       7: ior
       8: putfield      #21                 // Field bitField0_:I
      11: aload_0
      12: invokevirtual #51                 // Method onChanged:()V
      15: aload_0
      16: invokespecial #19                 // Method getSyncReplicationStateFieldBuilder:()Lorg/apache/hbase/thirdparty/com/google/protobuf/SingleFieldBuilderV3;
      19: invokevirtual #94                 // Method org/apache/hbase/thirdparty/com/google/protobuf/SingleFieldBuilderV3.getBuilder:()Lorg/apache/hbase/thirdparty/com/google/protobuf/AbstractMessage$Builder;
      22: checkcast     #114                // class org/apache/hadoop/hbase/shaded/protobuf/generated/ReplicationProtos$SyncReplicationState$Builder
      25: areturn

  public org.apache.hadoop.hbase.shaded.protobuf.generated.ReplicationProtos$SyncReplicationStateOrBuilder getSyncReplicationStateOrBuilder();
    Code:
       0: aload_0
       1: getfield      #25                 // Field syncReplicationStateBuilder_:Lorg/apache/hbase/thirdparty/com/google/protobuf/SingleFieldBuilderV3;
       4: ifnull        18
       7: aload_0
       8: getfield      #25                 // Field syncReplicationStateBuilder_:Lorg/apache/hbase/thirdparty/com/google/protobuf/SingleFieldBuilderV3;
      11: invokevirtual #96                 // Method org/apache/hbase/thirdparty/com/google/protobuf/SingleFieldBuilderV3.getMessageOrBuilder:()Lorg/apache/hbase/thirdparty/com/google/protobuf/MessageOrBuilder;
      14: checkcast     #115                // class org/apache/hadoop/hbase/shaded/protobuf/generated/ReplicationProtos$SyncReplicationStateOrBuilder
      17: areturn
      18: aload_0
      19: getfield      #13                 // Field syncReplicationState_:Lorg/apache/hadoop/hbase/shaded/protobuf/generated/ReplicationProtos$SyncReplicationState;
      22: ifnonnull     31
      25: invokestatic  #109                // Method org/apache/hadoop/hbase/shaded/protobuf/generated/ReplicationProtos$SyncReplicationState.getDefaultInstance:()Lorg/apache/hadoop/hbase/shaded/protobuf/generated/ReplicationProtos$SyncReplicationState;
      28: goto          35
      31: aload_0
      32: getfield      #13                 // Field syncReplicationState_:Lorg/apache/hadoop/hbase/shaded/protobuf/generated/ReplicationProtos$SyncReplicationState;
      35: areturn

  public final org.apache.hadoop.hbase.shaded.protobuf.generated.ReplicationProtos$ReplicationPeerDescription$Builder setUnknownFields(org.apache.hbase.thirdparty.com.google.protobuf.UnknownFieldSet);
    Code:
       0: aload_0
       1: aload_1
       2: invokespecial #116                // Method org/apache/hbase/thirdparty/com/google/protobuf/GeneratedMessageV3$Builder.setUnknownFields:(Lorg/apache/hbase/thirdparty/com/google/protobuf/UnknownFieldSet;)Lorg/apache/hbase/thirdparty/com/google/protobuf/GeneratedMessageV3$Builder;
       5: checkcast     #6                  // class org/apache/hadoop/hbase/shaded/protobuf/generated/ReplicationProtos$ReplicationPeerDescription$Builder
       8: areturn

  public final org.apache.hadoop.hbase.shaded.protobuf.generated.ReplicationProtos$ReplicationPeerDescription$Builder mergeUnknownFields(org.apache.hbase.thirdparty.com.google.protobuf.UnknownFieldSet);
    Code:
       0: aload_0
       1: aload_1
       2: invokespecial #117                // Method org/apache/hbase/thirdparty/com/google/protobuf/GeneratedMessageV3$Builder.mergeUnknownFields:(Lorg/apache/hbase/thirdparty/com/google/protobuf/UnknownFieldSet;)Lorg/apache/hbase/thirdparty/com/google/protobuf/GeneratedMessageV3$Builder;
       5: checkcast     #6                  // class org/apache/hadoop/hbase/shaded/protobuf/generated/ReplicationProtos$ReplicationPeerDescription$Builder
       8: areturn

  public org.apache.hbase.thirdparty.com.google.protobuf.GeneratedMessageV3$Builder mergeUnknownFields(org.apache.hbase.thirdparty.com.google.protobuf.UnknownFieldSet);
    Code:
       0: aload_0
       1: aload_1
       2: invokevirtual #62                 // Method mergeUnknownFields:(Lorg/apache/hbase/thirdparty/com/google/protobuf/UnknownFieldSet;)Lorg/apache/hadoop/hbase/shaded/protobuf/generated/ReplicationProtos$ReplicationPeerDescription$Builder;
       5: areturn

  public org.apache.hbase.thirdparty.com.google.protobuf.GeneratedMessageV3$Builder setUnknownFields(org.apache.hbase.thirdparty.com.google.protobuf.UnknownFieldSet);
    Code:
       0: aload_0
       1: aload_1
       2: invokevirtual #118                // Method setUnknownFields:(Lorg/apache/hbase/thirdparty/com/google/protobuf/UnknownFieldSet;)Lorg/apache/hadoop/hbase/shaded/protobuf/generated/ReplicationProtos$ReplicationPeerDescription$Builder;
       5: areturn

  public org.apache.hbase.thirdparty.com.google.protobuf.GeneratedMessageV3$Builder addRepeatedField(org.apache.hbase.thirdparty.com.google.protobuf.Descriptors$FieldDescriptor, java.lang.Object);
    Code:
       0: aload_0
       1: aload_1
       2: aload_2
       3: invokevirtual #119                // Method addRepeatedField:(Lorg/apache/hbase/thirdparty/com/google/protobuf/Descriptors$FieldDescriptor;Ljava/lang/Object;)Lorg/apache/hadoop/hbase/shaded/protobuf/generated/ReplicationProtos$ReplicationPeerDescription$Builder;
       6: areturn

  public org.apache.hbase.thirdparty.com.google.protobuf.GeneratedMessageV3$Builder setRepeatedField(org.apache.hbase.thirdparty.com.google.protobuf.Descriptors$FieldDescriptor, int, java.lang.Object);
    Code:
       0: aload_0
       1: aload_1
       2: iload_2
       3: aload_3
       4: invokevirtual #120                // Method setRepeatedField:(Lorg/apache/hbase/thirdparty/com/google/protobuf/Descriptors$FieldDescriptor;ILjava/lang/Object;)Lorg/apache/hadoop/hbase/shaded/protobuf/generated/ReplicationProtos$ReplicationPeerDescription$Builder;
       7: areturn

  public org.apache.hbase.thirdparty.com.google.protobuf.GeneratedMessageV3$Builder clearOneof(org.apache.hbase.thirdparty.com.google.protobuf.Descriptors$OneofDescriptor);
    Code:
       0: aload_0
       1: aload_1
       2: invokevirtual #121                // Method clearOneof:(Lorg/apache/hbase/thirdparty/com/google/protobuf/Descriptors$OneofDescriptor;)Lorg/apache/hadoop/hbase/shaded/protobuf/generated/ReplicationProtos$ReplicationPeerDescription$Builder;
       5: areturn

  public org.apache.hbase.thirdparty.com.google.protobuf.GeneratedMessageV3$Builder clearField(org.apache.hbase.thirdparty.com.google.protobuf.Descriptors$FieldDescriptor);
    Code:
       0: aload_0
       1: aload_1
       2: invokevirtual #122                // Method clearField:(Lorg/apache/hbase/thirdparty/com/google/protobuf/Descriptors$FieldDescriptor;)Lorg/apache/hadoop/hbase/shaded/protobuf/generated/ReplicationProtos$ReplicationPeerDescription$Builder;
       5: areturn

  public org.apache.hbase.thirdparty.com.google.protobuf.GeneratedMessageV3$Builder setField(org.apache.hbase.thirdparty.com.google.protobuf.Descriptors$FieldDescriptor, java.lang.Object);
    Code:
       0: aload_0
       1: aload_1
       2: aload_2
       3: invokevirtual #123                // Method setField:(Lorg/apache/hbase/thirdparty/com/google/protobuf/Descriptors$FieldDescriptor;Ljava/lang/Object;)Lorg/apache/hadoop/hbase/shaded/protobuf/generated/ReplicationProtos$ReplicationPeerDescription$Builder;
       6: areturn

  public org.apache.hbase.thirdparty.com.google.protobuf.GeneratedMessageV3$Builder clear();
    Code:
       0: aload_0
       1: invokevirtual #124                // Method clear:()Lorg/apache/hadoop/hbase/shaded/protobuf/generated/ReplicationProtos$ReplicationPeerDescription$Builder;
       4: areturn

  public org.apache.hbase.thirdparty.com.google.protobuf.GeneratedMessageV3$Builder clone();
    Code:
       0: aload_0
       1: invokevirtual #125                // Method clone:()Lorg/apache/hadoop/hbase/shaded/protobuf/generated/ReplicationProtos$ReplicationPeerDescription$Builder;
       4: areturn

  public org.apache.hbase.thirdparty.com.google.protobuf.AbstractMessage$Builder mergeUnknownFields(org.apache.hbase.thirdparty.com.google.protobuf.UnknownFieldSet);
    Code:
       0: aload_0
       1: aload_1
       2: invokevirtual #62                 // Method mergeUnknownFields:(Lorg/apache/hbase/thirdparty/com/google/protobuf/UnknownFieldSet;)Lorg/apache/hadoop/hbase/shaded/protobuf/generated/ReplicationProtos$ReplicationPeerDescription$Builder;
       5: areturn

  public org.apache.hbase.thirdparty.com.google.protobuf.AbstractMessage$Builder mergeFrom(org.apache.hbase.thirdparty.com.google.protobuf.CodedInputStream, org.apache.hbase.thirdparty.com.google.protobuf.ExtensionRegistryLite) throws java.io.IOException;
    Code:
       0: aload_0
       1: aload_1
       2: aload_2
       3: invokevirtual #126                // Method mergeFrom:(Lorg/apache/hbase/thirdparty/com/google/protobuf/CodedInputStream;Lorg/apache/hbase/thirdparty/com/google/protobuf/ExtensionRegistryLite;)Lorg/apache/hadoop/hbase/shaded/protobuf/generated/ReplicationProtos$ReplicationPeerDescription$Builder;
       6: areturn

  public org.apache.hbase.thirdparty.com.google.protobuf.AbstractMessage$Builder mergeFrom(org.apache.hbase.thirdparty.com.google.protobuf.Message);
    Code:
       0: aload_0
       1: aload_1
       2: invokevirtual #127                // Method mergeFrom:(Lorg/apache/hbase/thirdparty/com/google/protobuf/Message;)Lorg/apache/hadoop/hbase/shaded/protobuf/generated/ReplicationProtos$ReplicationPeerDescription$Builder;
       5: areturn

  public org.apache.hbase.thirdparty.com.google.protobuf.AbstractMessage$Builder clear();
    Code:
       0: aload_0
       1: invokevirtual #124                // Method clear:()Lorg/apache/hadoop/hbase/shaded/protobuf/generated/ReplicationProtos$ReplicationPeerDescription$Builder;
       4: areturn

  public org.apache.hbase.thirdparty.com.google.protobuf.AbstractMessage$Builder clearOneof(org.apache.hbase.thirdparty.com.google.protobuf.Descriptors$OneofDescriptor);
    Code:
       0: aload_0
       1: aload_1
       2: invokevirtual #121                // Method clearOneof:(Lorg/apache/hbase/thirdparty/com/google/protobuf/Descriptors$OneofDescriptor;)Lorg/apache/hadoop/hbase/shaded/protobuf/generated/ReplicationProtos$ReplicationPeerDescription$Builder;
       5: areturn

  public org.apache.hbase.thirdparty.com.google.protobuf.AbstractMessage$Builder clone();
    Code:
       0: aload_0
       1: invokevirtual #125                // Method clone:()Lorg/apache/hadoop/hbase/shaded/protobuf/generated/ReplicationProtos$ReplicationPeerDescription$Builder;
       4: areturn

  public org.apache.hbase.thirdparty.com.google.protobuf.Message$Builder mergeUnknownFields(org.apache.hbase.thirdparty.com.google.protobuf.UnknownFieldSet);
    Code:
       0: aload_0
       1: aload_1
       2: invokevirtual #62                 // Method mergeUnknownFields:(Lorg/apache/hbase/thirdparty/com/google/protobuf/UnknownFieldSet;)Lorg/apache/hadoop/hbase/shaded/protobuf/generated/ReplicationProtos$ReplicationPeerDescription$Builder;
       5: areturn

  public org.apache.hbase.thirdparty.com.google.protobuf.Message$Builder setUnknownFields(org.apache.hbase.thirdparty.com.google.protobuf.UnknownFieldSet);
    Code:
       0: aload_0
       1: aload_1
       2: invokevirtual #118                // Method setUnknownFields:(Lorg/apache/hbase/thirdparty/com/google/protobuf/UnknownFieldSet;)Lorg/apache/hadoop/hbase/shaded/protobuf/generated/ReplicationProtos$ReplicationPeerDescription$Builder;
       5: areturn

  public org.apache.hbase.thirdparty.com.google.protobuf.Message$Builder addRepeatedField(org.apache.hbase.thirdparty.com.google.protobuf.Descriptors$FieldDescriptor, java.lang.Object);
    Code:
       0: aload_0
       1: aload_1
       2: aload_2
       3: invokevirtual #119                // Method addRepeatedField:(Lorg/apache/hbase/thirdparty/com/google/protobuf/Descriptors$FieldDescriptor;Ljava/lang/Object;)Lorg/apache/hadoop/hbase/shaded/protobuf/generated/ReplicationProtos$ReplicationPeerDescription$Builder;
       6: areturn

  public org.apache.hbase.thirdparty.com.google.protobuf.Message$Builder setRepeatedField(org.apache.hbase.thirdparty.com.google.protobuf.Descriptors$FieldDescriptor, int, java.lang.Object);
    Code:
       0: aload_0
       1: aload_1
       2: iload_2
       3: aload_3
       4: invokevirtual #120                // Method setRepeatedField:(Lorg/apache/hbase/thirdparty/com/google/protobuf/Descriptors$FieldDescriptor;ILjava/lang/Object;)Lorg/apache/hadoop/hbase/shaded/protobuf/generated/ReplicationProtos$ReplicationPeerDescription$Builder;
       7: areturn

  public org.apache.hbase.thirdparty.com.google.protobuf.Message$Builder clearOneof(org.apache.hbase.thirdparty.com.google.protobuf.Descriptors$OneofDescriptor);
    Code:
       0: aload_0
       1: aload_1
       2: invokevirtual #121                // Method clearOneof:(Lorg/apache/hbase/thirdparty/com/google/protobuf/Descriptors$OneofDescriptor;)Lorg/apache/hadoop/hbase/shaded/protobuf/generated/ReplicationProtos$ReplicationPeerDescription$Builder;
       5: areturn

  public org.apache.hbase.thirdparty.com.google.protobuf.Message$Builder clearField(org.apache.hbase.thirdparty.com.google.protobuf.Descriptors$FieldDescriptor);
    Code:
       0: aload_0
       1: aload_1
       2: invokevirtual #122                // Method clearField:(Lorg/apache/hbase/thirdparty/com/google/protobuf/Descriptors$FieldDescriptor;)Lorg/apache/hadoop/hbase/shaded/protobuf/generated/ReplicationProtos$ReplicationPeerDescription$Builder;
       5: areturn

  public org.apache.hbase.thirdparty.com.google.protobuf.Message$Builder setField(org.apache.hbase.thirdparty.com.google.protobuf.Descriptors$FieldDescriptor, java.lang.Object);
    Code:
       0: aload_0
       1: aload_1
       2: aload_2
       3: invokevirtual #123                // Method setField:(Lorg/apache/hbase/thirdparty/com/google/protobuf/Descriptors$FieldDescriptor;Ljava/lang/Object;)Lorg/apache/hadoop/hbase/shaded/protobuf/generated/ReplicationProtos$ReplicationPeerDescription$Builder;
       6: areturn

  public org.apache.hbase.thirdparty.com.google.protobuf.Message$Builder mergeFrom(org.apache.hbase.thirdparty.com.google.protobuf.CodedInputStream, org.apache.hbase.thirdparty.com.google.protobuf.ExtensionRegistryLite) throws java.io.IOException;
    Code:
       0: aload_0
       1: aload_1
       2: aload_2
       3: invokevirtual #126                // Method mergeFrom:(Lorg/apache/hbase/thirdparty/com/google/protobuf/CodedInputStream;Lorg/apache/hbase/thirdparty/com/google/protobuf/ExtensionRegistryLite;)Lorg/apache/hadoop/hbase/shaded/protobuf/generated/ReplicationProtos$ReplicationPeerDescription$Builder;
       6: areturn

  public org.apache.hbase.thirdparty.com.google.protobuf.Message$Builder clone();
    Code:
       0: aload_0
       1: invokevirtual #125                // Method clone:()Lorg/apache/hadoop/hbase/shaded/protobuf/generated/ReplicationProtos$ReplicationPeerDescription$Builder;
       4: areturn

  public org.apache.hbase.thirdparty.com.google.protobuf.Message buildPartial();
    Code:
       0: aload_0
       1: invokevirtual #27                 // Method buildPartial:()Lorg/apache/hadoop/hbase/shaded/protobuf/generated/ReplicationProtos$ReplicationPeerDescription;
       4: areturn

  public org.apache.hbase.thirdparty.com.google.protobuf.Message build();
    Code:
       0: aload_0
       1: invokevirtual #128                // Method build:()Lorg/apache/hadoop/hbase/shaded/protobuf/generated/ReplicationProtos$ReplicationPeerDescription;
       4: areturn

  public org.apache.hbase.thirdparty.com.google.protobuf.Message$Builder mergeFrom(org.apache.hbase.thirdparty.com.google.protobuf.Message);
    Code:
       0: aload_0
       1: aload_1
       2: invokevirtual #127                // Method mergeFrom:(Lorg/apache/hbase/thirdparty/com/google/protobuf/Message;)Lorg/apache/hadoop/hbase/shaded/protobuf/generated/ReplicationProtos$ReplicationPeerDescription$Builder;
       5: areturn

  public org.apache.hbase.thirdparty.com.google.protobuf.Message$Builder clear();
    Code:
       0: aload_0
       1: invokevirtual #124                // Method clear:()Lorg/apache/hadoop/hbase/shaded/protobuf/generated/ReplicationProtos$ReplicationPeerDescription$Builder;
       4: areturn

  public org.apache.hbase.thirdparty.com.google.protobuf.MessageLite$Builder mergeFrom(org.apache.hbase.thirdparty.com.google.protobuf.CodedInputStream, org.apache.hbase.thirdparty.com.google.protobuf.ExtensionRegistryLite) throws java.io.IOException;
    Code:
       0: aload_0
       1: aload_1
       2: aload_2
       3: invokevirtual #126                // Method mergeFrom:(Lorg/apache/hbase/thirdparty/com/google/protobuf/CodedInputStream;Lorg/apache/hbase/thirdparty/com/google/protobuf/ExtensionRegistryLite;)Lorg/apache/hadoop/hbase/shaded/protobuf/generated/ReplicationProtos$ReplicationPeerDescription$Builder;
       6: areturn

  public org.apache.hbase.thirdparty.com.google.protobuf.MessageLite$Builder clone();
    Code:
       0: aload_0
       1: invokevirtual #125                // Method clone:()Lorg/apache/hadoop/hbase/shaded/protobuf/generated/ReplicationProtos$ReplicationPeerDescription$Builder;
       4: areturn

  public org.apache.hbase.thirdparty.com.google.protobuf.MessageLite buildPartial();
    Code:
       0: aload_0
       1: invokevirtual #27                 // Method buildPartial:()Lorg/apache/hadoop/hbase/shaded/protobuf/generated/ReplicationProtos$ReplicationPeerDescription;
       4: areturn

  public org.apache.hbase.thirdparty.com.google.protobuf.MessageLite build();
    Code:
       0: aload_0
       1: invokevirtual #128                // Method build:()Lorg/apache/hadoop/hbase/shaded/protobuf/generated/ReplicationProtos$ReplicationPeerDescription;
       4: areturn

  public org.apache.hbase.thirdparty.com.google.protobuf.MessageLite$Builder clear();
    Code:
       0: aload_0
       1: invokevirtual #124                // Method clear:()Lorg/apache/hadoop/hbase/shaded/protobuf/generated/ReplicationProtos$ReplicationPeerDescription$Builder;
       4: areturn

  public org.apache.hbase.thirdparty.com.google.protobuf.MessageLite getDefaultInstanceForType();
    Code:
       0: aload_0
       1: invokevirtual #129                // Method getDefaultInstanceForType:()Lorg/apache/hadoop/hbase/shaded/protobuf/generated/ReplicationProtos$ReplicationPeerDescription;
       4: areturn

  public org.apache.hbase.thirdparty.com.google.protobuf.Message getDefaultInstanceForType();
    Code:
       0: aload_0
       1: invokevirtual #129                // Method getDefaultInstanceForType:()Lorg/apache/hadoop/hbase/shaded/protobuf/generated/ReplicationProtos$ReplicationPeerDescription;
       4: areturn

  public org.apache.hbase.thirdparty.com.google.protobuf.AbstractMessageLite$Builder mergeFrom(org.apache.hbase.thirdparty.com.google.protobuf.CodedInputStream, org.apache.hbase.thirdparty.com.google.protobuf.ExtensionRegistryLite) throws java.io.IOException;
    Code:
       0: aload_0
       1: aload_1
       2: aload_2
       3: invokevirtual #126                // Method mergeFrom:(Lorg/apache/hbase/thirdparty/com/google/protobuf/CodedInputStream;Lorg/apache/hbase/thirdparty/com/google/protobuf/ExtensionRegistryLite;)Lorg/apache/hadoop/hbase/shaded/protobuf/generated/ReplicationProtos$ReplicationPeerDescription$Builder;
       6: areturn

  public org.apache.hbase.thirdparty.com.google.protobuf.AbstractMessageLite$Builder clone();
    Code:
       0: aload_0
       1: invokevirtual #125                // Method clone:()Lorg/apache/hadoop/hbase/shaded/protobuf/generated/ReplicationProtos$ReplicationPeerDescription$Builder;
       4: areturn

  public java.lang.Object clone() throws java.lang.CloneNotSupportedException;
    Code:
       0: aload_0
       1: invokevirtual #125                // Method clone:()Lorg/apache/hadoop/hbase/shaded/protobuf/generated/ReplicationProtos$ReplicationPeerDescription$Builder;
       4: areturn

  org.apache.hadoop.hbase.shaded.protobuf.generated.ReplicationProtos$ReplicationPeerDescription$Builder(org.apache.hadoop.hbase.shaded.protobuf.generated.ReplicationProtos$1);
    Code:
       0: aload_0
       1: invokespecial #2                  // Method "<init>":()V
       4: return

  org.apache.hadoop.hbase.shaded.protobuf.generated.ReplicationProtos$ReplicationPeerDescription$Builder(org.apache.hbase.thirdparty.com.google.protobuf.GeneratedMessageV3$BuilderParent, org.apache.hadoop.hbase.shaded.protobuf.generated.ReplicationProtos$1);
    Code:
       0: aload_0
       1: aload_1
       2: invokespecial #1                  // Method "<init>":(Lorg/apache/hbase/thirdparty/com/google/protobuf/GeneratedMessageV3$BuilderParent;)V
       5: return
}
