Compiled from "RequestControllerFactory.java"
public final class org.apache.hadoop.hbase.client.RequestControllerFactory {
  public static final java.lang.String REQUEST_CONTROLLER_IMPL_CONF_KEY;

  public org.apache.hadoop.hbase.client.RequestControllerFactory();
    Code:
       0: aload_0
       1: invokespecial #1                  // Method java/lang/Object."<init>":()V
       4: return

  public static org.apache.hadoop.hbase.client.RequestController create(org.apache.hadoop.conf.Configuration);
    Code:
       0: aload_0
       1: ldc           #3                  // String hbase.client.request.controller.impl
       3: ldc           #4                  // class org/apache/hadoop/hbase/client/SimpleRequestController
       5: ldc           #5                  // class org/apache/hadoop/hbase/client/RequestController
       7: invokevirtual #6                  // Method org/apache/hadoop/conf/Configuration.getClass:(Ljava/lang/String;Ljava/lang/Class;Ljava/lang/Class;)Ljava/lang/Class;
      10: astore_1
      11: aload_1
      12: iconst_1
      13: anewarray     #7                  // class java/lang/Object
      16: dup
      17: iconst_0
      18: aload_0
      19: aastore
      20: invokestatic  #8                  // Method org/apache/hadoop/hbase/util/ReflectionUtils.newInstance:(Ljava/lang/Class;[Ljava/lang/Object;)Ljava/lang/Object;
      23: checkcast     #5                  // class org/apache/hadoop/hbase/client/RequestController
      26: areturn
}
