Compiled from "ResourceCheckerJUnitListener.java"
class org.apache.hadoop.hbase.ResourceCheckerJUnitListener$ThreadResourceAnalyzer extends org.apache.hadoop.hbase.ResourceChecker$ResourceAnalyzer {
  org.apache.hadoop.hbase.ResourceCheckerJUnitListener$ThreadResourceAnalyzer();
    Code:
       0: aload_0
       1: invokespecial #1                  // Method org/apache/hadoop/hbase/ResourceChecker$ResourceAnalyzer."<init>":()V
       4: return

  public int getVal(org.apache.hadoop.hbase.ResourceChecker$Phase);
    Code:
       0: invokestatic  #2                  // Method java/lang/Thread.getAllStackTraces:()Ljava/util/Map;
       3: astore_2
       4: aload_1
       5: getstatic     #3                  // Field org/apache/hadoop/hbase/ResourceChecker$Phase.INITIAL:Lorg/apache/hadoop/hbase/ResourceChecker$Phase;
       8: if_acmpne     67
      11: aconst_null
      12: putstatic     #4                  // Field stringsToLog:Ljava/util/List;
      15: aload_2
      16: invokeinterface #5,  1            // InterfaceMethod java/util/Map.keySet:()Ljava/util/Set;
      21: invokeinterface #6,  1            // InterfaceMethod java/util/Set.iterator:()Ljava/util/Iterator;
      26: astore_3
      27: aload_3
      28: invokeinterface #7,  1            // InterfaceMethod java/util/Iterator.hasNext:()Z
      33: ifeq          64
      36: aload_3
      37: invokeinterface #8,  1            // InterfaceMethod java/util/Iterator.next:()Ljava/lang/Object;
      42: checkcast     #9                  // class java/lang/Thread
      45: astore        4
      47: getstatic     #10                 // Field initialThreadNames:Ljava/util/Set;
      50: aload         4
      52: invokevirtual #11                 // Method java/lang/Thread.getName:()Ljava/lang/String;
      55: invokeinterface #12,  2           // InterfaceMethod java/util/Set.add:(Ljava/lang/Object;)Z
      60: pop
      61: goto          27
      64: goto          268
      67: aload_1
      68: getstatic     #13                 // Field org/apache/hadoop/hbase/ResourceChecker$Phase.END:Lorg/apache/hadoop/hbase/ResourceChecker$Phase;
      71: if_acmpne     268
      74: aload_2
      75: invokeinterface #14,  1           // InterfaceMethod java/util/Map.size:()I
      80: getstatic     #10                 // Field initialThreadNames:Ljava/util/Set;
      83: invokeinterface #15,  1           // InterfaceMethod java/util/Set.size:()I
      88: if_icmple     268
      91: new           #16                 // class java/util/ArrayList
      94: dup
      95: invokespecial #17                 // Method java/util/ArrayList."<init>":()V
      98: putstatic     #4                  // Field stringsToLog:Ljava/util/List;
     101: aload_2
     102: invokeinterface #5,  1            // InterfaceMethod java/util/Map.keySet:()Ljava/util/Set;
     107: invokeinterface #6,  1            // InterfaceMethod java/util/Set.iterator:()Ljava/util/Iterator;
     112: astore_3
     113: aload_3
     114: invokeinterface #7,  1            // InterfaceMethod java/util/Iterator.hasNext:()Z
     119: ifeq          268
     122: aload_3
     123: invokeinterface #8,  1            // InterfaceMethod java/util/Iterator.next:()Ljava/lang/Object;
     128: checkcast     #9                  // class java/lang/Thread
     131: astore        4
     133: getstatic     #10                 // Field initialThreadNames:Ljava/util/Set;
     136: aload         4
     138: invokevirtual #11                 // Method java/lang/Thread.getName:()Ljava/lang/String;
     141: invokeinterface #18,  2           // InterfaceMethod java/util/Set.contains:(Ljava/lang/Object;)Z
     146: ifne          265
     149: getstatic     #4                  // Field stringsToLog:Ljava/util/List;
     152: new           #19                 // class java/lang/StringBuilder
     155: dup
     156: invokespecial #20                 // Method java/lang/StringBuilder."<init>":()V
     159: ldc           #21                 // String \nPotentially hanging thread:
     161: invokevirtual #22                 // Method java/lang/StringBuilder.append:(Ljava/lang/String;)Ljava/lang/StringBuilder;
     164: aload         4
     166: invokevirtual #11                 // Method java/lang/Thread.getName:()Ljava/lang/String;
     169: invokevirtual #22                 // Method java/lang/StringBuilder.append:(Ljava/lang/String;)Ljava/lang/StringBuilder;
     172: ldc           #23                 // String \n
     174: invokevirtual #22                 // Method java/lang/StringBuilder.append:(Ljava/lang/String;)Ljava/lang/StringBuilder;
     177: invokevirtual #24                 // Method java/lang/StringBuilder.toString:()Ljava/lang/String;
     180: invokeinterface #25,  2           // InterfaceMethod java/util/List.add:(Ljava/lang/Object;)Z
     185: pop
     186: aload_2
     187: aload         4
     189: invokeinterface #26,  2           // InterfaceMethod java/util/Map.get:(Ljava/lang/Object;)Ljava/lang/Object;
     194: checkcast     #27                 // class "[Ljava/lang/StackTraceElement;"
     197: astore        5
     199: aload         5
     201: astore        6
     203: aload         6
     205: arraylength
     206: istore        7
     208: iconst_0
     209: istore        8
     211: iload         8
     213: iload         7
     215: if_icmpge     265
     218: aload         6
     220: iload         8
     222: aaload
     223: astore        9
     225: getstatic     #4                  // Field stringsToLog:Ljava/util/List;
     228: new           #19                 // class java/lang/StringBuilder
     231: dup
     232: invokespecial #20                 // Method java/lang/StringBuilder."<init>":()V
     235: ldc           #28                 // String \t
     237: invokevirtual #22                 // Method java/lang/StringBuilder.append:(Ljava/lang/String;)Ljava/lang/StringBuilder;
     240: aload         9
     242: invokevirtual #29                 // Method java/lang/StringBuilder.append:(Ljava/lang/Object;)Ljava/lang/StringBuilder;
     245: ldc           #23                 // String \n
     247: invokevirtual #22                 // Method java/lang/StringBuilder.append:(Ljava/lang/String;)Ljava/lang/StringBuilder;
     250: invokevirtual #24                 // Method java/lang/StringBuilder.toString:()Ljava/lang/String;
     253: invokeinterface #25,  2           // InterfaceMethod java/util/List.add:(Ljava/lang/Object;)Z
     258: pop
     259: iinc          8, 1
     262: goto          211
     265: goto          113
     268: aload_2
     269: invokeinterface #14,  1           // InterfaceMethod java/util/Map.size:()I
     274: ireturn

  public int getMax();
    Code:
       0: sipush        500
       3: ireturn

  public java.util.List<java.lang.String> getStringsToLog();
    Code:
       0: getstatic     #4                  // Field stringsToLog:Ljava/util/List;
       3: areturn

  static {};
    Code:
       0: new           #30                 // class java/util/HashSet
       3: dup
       4: invokespecial #31                 // Method java/util/HashSet."<init>":()V
       7: putstatic     #10                 // Field initialThreadNames:Ljava/util/Set;
      10: aconst_null
      11: putstatic     #4                  // Field stringsToLog:Ljava/util/List;
      14: return
}
