Compiled from "RestoreSnapshotFromClientGetCompactionStateTestBase.java"
public class org.apache.hadoop.hbase.client.RestoreSnapshotFromClientGetCompactionStateTestBase extends org.apache.hadoop.hbase.client.RestoreSnapshotFromClientTestBase {
  public org.apache.hadoop.hbase.client.RestoreSnapshotFromClientGetCompactionStateTestBase();
    Code:
       0: aload_0
       1: invokespecial #1                  // Method org/apache/hadoop/hbase/client/RestoreSnapshotFromClientTestBase."<init>":()V
       4: return

  public void testGetCompactionStateAfterRestoringSnapshot() throws java.io.IOException, java.lang.InterruptedException;
    Code:
       0: aload_0
       1: getfield      #2                  // Field admin:Lorg/apache/hadoop/hbase/client/Admin;
       4: aload_0
       5: getfield      #3                  // Field snapshotName1:Ljava/lang/String;
       8: aload_0
       9: getfield      #4                  // Field tableName:Lorg/apache/hadoop/hbase/TableName;
      12: invokeinterface #5,  3            // InterfaceMethod org/apache/hadoop/hbase/client/Admin.snapshot:(Ljava/lang/String;Lorg/apache/hadoop/hbase/TableName;)V
      17: aload_0
      18: getfield      #2                  // Field admin:Lorg/apache/hadoop/hbase/client/Admin;
      21: aload_0
      22: getfield      #4                  // Field tableName:Lorg/apache/hadoop/hbase/TableName;
      25: invokeinterface #6,  2            // InterfaceMethod org/apache/hadoop/hbase/client/Admin.disableTable:(Lorg/apache/hadoop/hbase/TableName;)V
      30: aload_0
      31: getfield      #2                  // Field admin:Lorg/apache/hadoop/hbase/client/Admin;
      34: aload_0
      35: getfield      #3                  // Field snapshotName1:Ljava/lang/String;
      38: invokeinterface #7,  2            // InterfaceMethod org/apache/hadoop/hbase/client/Admin.restoreSnapshot:(Ljava/lang/String;)V
      43: aload_0
      44: getfield      #2                  // Field admin:Lorg/apache/hadoop/hbase/client/Admin;
      47: aload_0
      48: getfield      #4                  // Field tableName:Lorg/apache/hadoop/hbase/TableName;
      51: invokeinterface #8,  2            // InterfaceMethod org/apache/hadoop/hbase/client/Admin.getCompactionState:(Lorg/apache/hadoop/hbase/TableName;)Lorg/apache/hadoop/hbase/client/CompactionState;
      56: astore_1
      57: getstatic     #9                  // Field org/apache/hadoop/hbase/client/CompactionState.NONE:Lorg/apache/hadoop/hbase/client/CompactionState;
      60: aload_1
      61: invokestatic  #10                 // Method org/junit/Assert.assertEquals:(Ljava/lang/Object;Ljava/lang/Object;)V
      64: return
}
