Compiled from "ReversedKeyValueHeap.java"
class org.apache.hadoop.hbase.regionserver.ReversedKeyValueHeap$ReversedKVScannerComparator extends org.apache.hadoop.hbase.regionserver.KeyValueHeap$KVScannerComparator {
  public org.apache.hadoop.hbase.regionserver.ReversedKeyValueHeap$ReversedKVScannerComparator(org.apache.hadoop.hbase.CellComparator);
    Code:
       0: aload_0
       1: aload_1
       2: invokespecial #1                  // Method org/apache/hadoop/hbase/regionserver/KeyValueHeap$KVScannerComparator."<init>":(Lorg/apache/hadoop/hbase/CellComparator;)V
       5: return

  public int compare(org.apache.hadoop.hbase.regionserver.KeyValueScanner, org.apache.hadoop.hbase.regionserver.KeyValueScanner);
    Code:
       0: aload_0
       1: aload_1
       2: invokeinterface #2,  1            // InterfaceMethod org/apache/hadoop/hbase/regionserver/KeyValueScanner.peek:()Lorg/apache/hadoop/hbase/Cell;
       7: aload_2
       8: invokeinterface #2,  1            // InterfaceMethod org/apache/hadoop/hbase/regionserver/KeyValueScanner.peek:()Lorg/apache/hadoop/hbase/Cell;
      13: invokevirtual #3                  // Method compareRows:(Lorg/apache/hadoop/hbase/Cell;Lorg/apache/hadoop/hbase/Cell;)I
      16: istore_3
      17: iload_3
      18: ifeq          24
      21: iload_3
      22: ineg
      23: ireturn
      24: aload_0
      25: aload_1
      26: aload_2
      27: invokespecial #4                  // Method org/apache/hadoop/hbase/regionserver/KeyValueHeap$KVScannerComparator.compare:(Lorg/apache/hadoop/hbase/regionserver/KeyValueScanner;Lorg/apache/hadoop/hbase/regionserver/KeyValueScanner;)I
      30: ireturn

  public int compareRows(org.apache.hadoop.hbase.Cell, org.apache.hadoop.hbase.Cell);
    Code:
       0: aload_0
       1: getfield      #5                  // Field org/apache/hadoop/hbase/regionserver/KeyValueHeap$KVScannerComparator.kvComparator:Lorg/apache/hadoop/hbase/CellComparator;
       4: aload_1
       5: aload_2
       6: invokeinterface #6,  3            // InterfaceMethod org/apache/hadoop/hbase/CellComparator.compareRows:(Lorg/apache/hadoop/hbase/Cell;Lorg/apache/hadoop/hbase/Cell;)I
      11: ireturn

  public int compare(java.lang.Object, java.lang.Object);
    Code:
       0: aload_0
       1: aload_1
       2: checkcast     #7                  // class org/apache/hadoop/hbase/regionserver/KeyValueScanner
       5: aload_2
       6: checkcast     #7                  // class org/apache/hadoop/hbase/regionserver/KeyValueScanner
       9: invokevirtual #8                  // Method compare:(Lorg/apache/hadoop/hbase/regionserver/KeyValueScanner;Lorg/apache/hadoop/hbase/regionserver/KeyValueScanner;)I
      12: ireturn
}
