Compiled from "RowIndexSeekerV1.java"
public class org.apache.hadoop.hbase.io.encoding.RowIndexSeekerV1 extends org.apache.hadoop.hbase.io.encoding.AbstractDataBlockEncoder$AbstractEncodedSeeker {
  protected final org.apache.hadoop.hbase.util.ObjectIntPair<java.nio.ByteBuffer> tmpPair;

  public org.apache.hadoop.hbase.io.encoding.RowIndexSeekerV1(org.apache.hadoop.hbase.CellComparator, org.apache.hadoop.hbase.io.encoding.HFileBlockDecodingContext);
    Code:
       0: aload_0
       1: aload_1
       2: aload_2
       3: invokespecial #1                  // Method org/apache/hadoop/hbase/io/encoding/AbstractDataBlockEncoder$AbstractEncodedSeeker."<init>":(Lorg/apache/hadoop/hbase/CellComparator;Lorg/apache/hadoop/hbase/io/encoding/HFileBlockDecodingContext;)V
       6: aload_0
       7: new           #2                  // class org/apache/hadoop/hbase/util/ObjectIntPair
      10: dup
      11: invokespecial #3                  // Method org/apache/hadoop/hbase/util/ObjectIntPair."<init>":()V
      14: putfield      #4                  // Field tmpPair:Lorg/apache/hadoop/hbase/util/ObjectIntPair;
      17: aload_0
      18: new           #5                  // class org/apache/hadoop/hbase/io/encoding/RowIndexSeekerV1$SeekerState
      21: dup
      22: aload_0
      23: aconst_null
      24: invokespecial #6                  // Method org/apache/hadoop/hbase/io/encoding/RowIndexSeekerV1$SeekerState."<init>":(Lorg/apache/hadoop/hbase/io/encoding/RowIndexSeekerV1;Lorg/apache/hadoop/hbase/io/encoding/RowIndexSeekerV1$1;)V
      27: putfield      #7                  // Field current:Lorg/apache/hadoop/hbase/io/encoding/RowIndexSeekerV1$SeekerState;
      30: aload_0
      31: new           #5                  // class org/apache/hadoop/hbase/io/encoding/RowIndexSeekerV1$SeekerState
      34: dup
      35: aload_0
      36: aconst_null
      37: invokespecial #6                  // Method org/apache/hadoop/hbase/io/encoding/RowIndexSeekerV1$SeekerState."<init>":(Lorg/apache/hadoop/hbase/io/encoding/RowIndexSeekerV1;Lorg/apache/hadoop/hbase/io/encoding/RowIndexSeekerV1$1;)V
      40: putfield      #8                  // Field previous:Lorg/apache/hadoop/hbase/io/encoding/RowIndexSeekerV1$SeekerState;
      43: aload_0
      44: aconst_null
      45: putfield      #9                  // Field rowOffsets:Lorg/apache/hadoop/hbase/nio/ByteBuff;
      48: return

  public void setCurrentBuffer(org.apache.hadoop.hbase.nio.ByteBuff);
    Code:
       0: aload_1
       1: aload_1
       2: invokevirtual #10                 // Method org/apache/hadoop/hbase/nio/ByteBuff.limit:()I
       5: iconst_4
       6: isub
       7: invokevirtual #12                 // Method org/apache/hadoop/hbase/nio/ByteBuff.getInt:(I)I
      10: istore_2
      11: aload_1
      12: invokevirtual #13                 // Method org/apache/hadoop/hbase/nio/ByteBuff.duplicate:()Lorg/apache/hadoop/hbase/nio/ByteBuff;
      15: astore_3
      16: aload_3
      17: aload_1
      18: invokevirtual #14                 // Method org/apache/hadoop/hbase/nio/ByteBuff.position:()I
      21: invokevirtual #15                 // Method org/apache/hadoop/hbase/nio/ByteBuff.position:(I)Lorg/apache/hadoop/hbase/nio/ByteBuff;
      24: pop
      25: aload_3
      26: aload_1
      27: invokevirtual #14                 // Method org/apache/hadoop/hbase/nio/ByteBuff.position:()I
      30: iload_2
      31: iadd
      32: invokevirtual #16                 // Method org/apache/hadoop/hbase/nio/ByteBuff.limit:(I)Lorg/apache/hadoop/hbase/nio/ByteBuff;
      35: pop
      36: aload_0
      37: aload_3
      38: invokevirtual #17                 // Method org/apache/hadoop/hbase/nio/ByteBuff.slice:()Lorg/apache/hadoop/hbase/nio/ByteBuff;
      41: putfield      #18                 // Field currentBuffer:Lorg/apache/hadoop/hbase/nio/ByteBuff;
      44: aload_0
      45: getfield      #7                  // Field current:Lorg/apache/hadoop/hbase/io/encoding/RowIndexSeekerV1$SeekerState;
      48: aload_0
      49: getfield      #18                 // Field currentBuffer:Lorg/apache/hadoop/hbase/nio/ByteBuff;
      52: putfield      #19                 // Field org/apache/hadoop/hbase/io/encoding/RowIndexSeekerV1$SeekerState.currentBuffer:Lorg/apache/hadoop/hbase/nio/ByteBuff;
      55: aload_1
      56: iload_2
      57: invokevirtual #20                 // Method org/apache/hadoop/hbase/nio/ByteBuff.skip:(I)Lorg/apache/hadoop/hbase/nio/ByteBuff;
      60: pop
      61: aload_0
      62: aload_1
      63: invokevirtual #21                 // Method org/apache/hadoop/hbase/nio/ByteBuff.getInt:()I
      66: putfield      #22                 // Field rowNumber:I
      69: iconst_4
      70: aload_0
      71: getfield      #22                 // Field rowNumber:I
      74: imul
      75: istore        4
      77: aload_1
      78: invokevirtual #13                 // Method org/apache/hadoop/hbase/nio/ByteBuff.duplicate:()Lorg/apache/hadoop/hbase/nio/ByteBuff;
      81: astore        5
      83: aload         5
      85: aload_1
      86: invokevirtual #14                 // Method org/apache/hadoop/hbase/nio/ByteBuff.position:()I
      89: invokevirtual #15                 // Method org/apache/hadoop/hbase/nio/ByteBuff.position:(I)Lorg/apache/hadoop/hbase/nio/ByteBuff;
      92: pop
      93: aload         5
      95: aload_1
      96: invokevirtual #14                 // Method org/apache/hadoop/hbase/nio/ByteBuff.position:()I
      99: iload         4
     101: iadd
     102: invokevirtual #16                 // Method org/apache/hadoop/hbase/nio/ByteBuff.limit:(I)Lorg/apache/hadoop/hbase/nio/ByteBuff;
     105: pop
     106: aload_0
     107: aload         5
     109: invokevirtual #17                 // Method org/apache/hadoop/hbase/nio/ByteBuff.slice:()Lorg/apache/hadoop/hbase/nio/ByteBuff;
     112: putfield      #9                  // Field rowOffsets:Lorg/apache/hadoop/hbase/nio/ByteBuff;
     115: aload_0
     116: invokevirtual #23                 // Method decodeFirst:()V
     119: return

  public org.apache.hadoop.hbase.Cell getKey();
    Code:
       0: aload_0
       1: getfield      #7                  // Field current:Lorg/apache/hadoop/hbase/io/encoding/RowIndexSeekerV1$SeekerState;
       4: getfield      #24                 // Field org/apache/hadoop/hbase/io/encoding/RowIndexSeekerV1$SeekerState.keyBuffer:Ljava/nio/ByteBuffer;
       7: invokevirtual #25                 // Method java/nio/ByteBuffer.hasArray:()Z
      10: ifeq          59
      13: new           #26                 // class org/apache/hadoop/hbase/KeyValue$KeyOnlyKeyValue
      16: dup
      17: aload_0
      18: getfield      #7                  // Field current:Lorg/apache/hadoop/hbase/io/encoding/RowIndexSeekerV1$SeekerState;
      21: getfield      #24                 // Field org/apache/hadoop/hbase/io/encoding/RowIndexSeekerV1$SeekerState.keyBuffer:Ljava/nio/ByteBuffer;
      24: invokevirtual #27                 // Method java/nio/ByteBuffer.array:()[B
      27: aload_0
      28: getfield      #7                  // Field current:Lorg/apache/hadoop/hbase/io/encoding/RowIndexSeekerV1$SeekerState;
      31: getfield      #24                 // Field org/apache/hadoop/hbase/io/encoding/RowIndexSeekerV1$SeekerState.keyBuffer:Ljava/nio/ByteBuffer;
      34: invokevirtual #28                 // Method java/nio/ByteBuffer.arrayOffset:()I
      37: aload_0
      38: getfield      #7                  // Field current:Lorg/apache/hadoop/hbase/io/encoding/RowIndexSeekerV1$SeekerState;
      41: getfield      #24                 // Field org/apache/hadoop/hbase/io/encoding/RowIndexSeekerV1$SeekerState.keyBuffer:Ljava/nio/ByteBuffer;
      44: invokevirtual #29                 // Method java/nio/ByteBuffer.position:()I
      47: iadd
      48: aload_0
      49: getfield      #7                  // Field current:Lorg/apache/hadoop/hbase/io/encoding/RowIndexSeekerV1$SeekerState;
      52: getfield      #30                 // Field org/apache/hadoop/hbase/io/encoding/RowIndexSeekerV1$SeekerState.keyLength:I
      55: invokespecial #31                 // Method org/apache/hadoop/hbase/KeyValue$KeyOnlyKeyValue."<init>":([BII)V
      58: areturn
      59: aload_0
      60: getfield      #7                  // Field current:Lorg/apache/hadoop/hbase/io/encoding/RowIndexSeekerV1$SeekerState;
      63: getfield      #30                 // Field org/apache/hadoop/hbase/io/encoding/RowIndexSeekerV1$SeekerState.keyLength:I
      66: newarray       byte
      68: astore_1
      69: aload_1
      70: aload_0
      71: getfield      #7                  // Field current:Lorg/apache/hadoop/hbase/io/encoding/RowIndexSeekerV1$SeekerState;
      74: getfield      #24                 // Field org/apache/hadoop/hbase/io/encoding/RowIndexSeekerV1$SeekerState.keyBuffer:Ljava/nio/ByteBuffer;
      77: aload_0
      78: getfield      #7                  // Field current:Lorg/apache/hadoop/hbase/io/encoding/RowIndexSeekerV1$SeekerState;
      81: getfield      #24                 // Field org/apache/hadoop/hbase/io/encoding/RowIndexSeekerV1$SeekerState.keyBuffer:Ljava/nio/ByteBuffer;
      84: invokevirtual #29                 // Method java/nio/ByteBuffer.position:()I
      87: iconst_0
      88: aload_0
      89: getfield      #7                  // Field current:Lorg/apache/hadoop/hbase/io/encoding/RowIndexSeekerV1$SeekerState;
      92: getfield      #30                 // Field org/apache/hadoop/hbase/io/encoding/RowIndexSeekerV1$SeekerState.keyLength:I
      95: invokestatic  #32                 // Method org/apache/hadoop/hbase/util/ByteBufferUtils.copyFromBufferToArray:([BLjava/nio/ByteBuffer;III)V
      98: new           #26                 // class org/apache/hadoop/hbase/KeyValue$KeyOnlyKeyValue
     101: dup
     102: aload_1
     103: iconst_0
     104: aload_0
     105: getfield      #7                  // Field current:Lorg/apache/hadoop/hbase/io/encoding/RowIndexSeekerV1$SeekerState;
     108: getfield      #30                 // Field org/apache/hadoop/hbase/io/encoding/RowIndexSeekerV1$SeekerState.keyLength:I
     111: invokespecial #31                 // Method org/apache/hadoop/hbase/KeyValue$KeyOnlyKeyValue."<init>":([BII)V
     114: areturn

  public java.nio.ByteBuffer getValueShallowCopy();
    Code:
       0: aload_0
       1: getfield      #18                 // Field currentBuffer:Lorg/apache/hadoop/hbase/nio/ByteBuff;
       4: aload_0
       5: getfield      #7                  // Field current:Lorg/apache/hadoop/hbase/io/encoding/RowIndexSeekerV1$SeekerState;
       8: getfield      #33                 // Field org/apache/hadoop/hbase/io/encoding/RowIndexSeekerV1$SeekerState.valueOffset:I
      11: aload_0
      12: getfield      #7                  // Field current:Lorg/apache/hadoop/hbase/io/encoding/RowIndexSeekerV1$SeekerState;
      15: getfield      #34                 // Field org/apache/hadoop/hbase/io/encoding/RowIndexSeekerV1$SeekerState.valueLength:I
      18: aload_0
      19: getfield      #4                  // Field tmpPair:Lorg/apache/hadoop/hbase/util/ObjectIntPair;
      22: invokevirtual #35                 // Method org/apache/hadoop/hbase/nio/ByteBuff.asSubByteBuffer:(IILorg/apache/hadoop/hbase/util/ObjectIntPair;)V
      25: aload_0
      26: getfield      #4                  // Field tmpPair:Lorg/apache/hadoop/hbase/util/ObjectIntPair;
      29: invokevirtual #36                 // Method org/apache/hadoop/hbase/util/ObjectIntPair.getFirst:()Ljava/lang/Object;
      32: checkcast     #37                 // class java/nio/ByteBuffer
      35: invokevirtual #38                 // Method java/nio/ByteBuffer.duplicate:()Ljava/nio/ByteBuffer;
      38: astore_1
      39: aload_1
      40: aload_0
      41: getfield      #4                  // Field tmpPair:Lorg/apache/hadoop/hbase/util/ObjectIntPair;
      44: invokevirtual #39                 // Method org/apache/hadoop/hbase/util/ObjectIntPair.getSecond:()I
      47: invokevirtual #40                 // Method java/nio/ByteBuffer.position:(I)Ljava/nio/Buffer;
      50: pop
      51: aload_1
      52: aload_0
      53: getfield      #4                  // Field tmpPair:Lorg/apache/hadoop/hbase/util/ObjectIntPair;
      56: invokevirtual #39                 // Method org/apache/hadoop/hbase/util/ObjectIntPair.getSecond:()I
      59: aload_0
      60: getfield      #7                  // Field current:Lorg/apache/hadoop/hbase/io/encoding/RowIndexSeekerV1$SeekerState;
      63: getfield      #34                 // Field org/apache/hadoop/hbase/io/encoding/RowIndexSeekerV1$SeekerState.valueLength:I
      66: iadd
      67: invokevirtual #41                 // Method java/nio/ByteBuffer.limit:(I)Ljava/nio/Buffer;
      70: pop
      71: aload_1
      72: invokevirtual #42                 // Method java/nio/ByteBuffer.slice:()Ljava/nio/ByteBuffer;
      75: areturn

  public org.apache.hadoop.hbase.Cell getCell();
    Code:
       0: aload_0
       1: getfield      #7                  // Field current:Lorg/apache/hadoop/hbase/io/encoding/RowIndexSeekerV1$SeekerState;
       4: invokevirtual #43                 // Method org/apache/hadoop/hbase/io/encoding/RowIndexSeekerV1$SeekerState.toCell:()Lorg/apache/hadoop/hbase/Cell;
       7: areturn

  public void rewind();
    Code:
       0: aload_0
       1: getfield      #18                 // Field currentBuffer:Lorg/apache/hadoop/hbase/nio/ByteBuff;
       4: invokevirtual #44                 // Method org/apache/hadoop/hbase/nio/ByteBuff.rewind:()Lorg/apache/hadoop/hbase/nio/ByteBuff;
       7: pop
       8: aload_0
       9: invokevirtual #23                 // Method decodeFirst:()V
      12: return

  public boolean next();
    Code:
       0: aload_0
       1: getfield      #18                 // Field currentBuffer:Lorg/apache/hadoop/hbase/nio/ByteBuff;
       4: invokevirtual #45                 // Method org/apache/hadoop/hbase/nio/ByteBuff.hasRemaining:()Z
       7: ifne          12
      10: iconst_0
      11: ireturn
      12: aload_0
      13: invokevirtual #46                 // Method decodeNext:()V
      16: aload_0
      17: getfield      #8                  // Field previous:Lorg/apache/hadoop/hbase/io/encoding/RowIndexSeekerV1$SeekerState;
      20: invokevirtual #47                 // Method org/apache/hadoop/hbase/io/encoding/RowIndexSeekerV1$SeekerState.invalidate:()V
      23: iconst_1
      24: ireturn

  public int seekToKeyInBlock(org.apache.hadoop.hbase.Cell, boolean);
    Code:
       0: aload_0
       1: getfield      #8                  // Field previous:Lorg/apache/hadoop/hbase/io/encoding/RowIndexSeekerV1$SeekerState;
       4: invokevirtual #47                 // Method org/apache/hadoop/hbase/io/encoding/RowIndexSeekerV1$SeekerState.invalidate:()V
       7: aload_0
       8: aload_1
       9: iload_2
      10: invokespecial #62                 // Method binarySearch:(Lorg/apache/hadoop/hbase/Cell;Z)I
      13: istore_3
      14: iload_3
      15: ifge          21
      18: bipush        -2
      20: ireturn
      21: aload_0
      22: getfield      #9                  // Field rowOffsets:Lorg/apache/hadoop/hbase/nio/ByteBuff;
      25: iload_3
      26: iconst_4
      27: imul
      28: invokevirtual #59                 // Method org/apache/hadoop/hbase/nio/ByteBuff.getIntAfterPosition:(I)I
      31: istore        4
      33: iload         4
      35: ifeq          44
      38: aload_0
      39: iload         4
      41: invokevirtual #64                 // Method decodeAtPosition:(I)V
      44: aload_0
      45: getfield      #65                 // Field comparator:Lorg/apache/hadoop/hbase/CellComparator;
      48: aload_1
      49: aload_0
      50: getfield      #7                  // Field current:Lorg/apache/hadoop/hbase/io/encoding/RowIndexSeekerV1$SeekerState;
      53: invokestatic  #66                 // Method org/apache/hadoop/hbase/io/encoding/RowIndexSeekerV1$SeekerState.access$100:(Lorg/apache/hadoop/hbase/io/encoding/RowIndexSeekerV1$SeekerState;)Lorg/apache/hadoop/hbase/ByteBufferKeyOnlyKeyValue;
      56: invokestatic  #67                 // Method org/apache/hadoop/hbase/PrivateCellUtil.compareKeyIgnoresMvcc:(Lorg/apache/hadoop/hbase/CellComparator;Lorg/apache/hadoop/hbase/Cell;Lorg/apache/hadoop/hbase/Cell;)I
      59: istore        4
      61: iload         4
      63: ifne          123
      66: iload_2
      67: ifeq          121
      70: aload_0
      71: getfield      #8                  // Field previous:Lorg/apache/hadoop/hbase/io/encoding/RowIndexSeekerV1$SeekerState;
      74: invokevirtual #68                 // Method org/apache/hadoop/hbase/io/encoding/RowIndexSeekerV1$SeekerState.isValid:()Z
      77: ifne          115
      80: new           #69                 // class java/lang/IllegalStateException
      83: dup
      84: new           #70                 // class java/lang/StringBuilder
      87: dup
      88: invokespecial #71                 // Method java/lang/StringBuilder."<init>":()V
      91: ldc           #72                 // String Cannot seekBefore if positioned at the first key in the block: key=
      93: invokevirtual #73                 // Method java/lang/StringBuilder.append:(Ljava/lang/String;)Ljava/lang/StringBuilder;
      96: aload_1
      97: invokeinterface #56,  1           // InterfaceMethod org/apache/hadoop/hbase/Cell.getRowArray:()[B
     102: invokestatic  #74                 // Method org/apache/hadoop/hbase/util/Bytes.toStringBinary:([B)Ljava/lang/String;
     105: invokevirtual #73                 // Method java/lang/StringBuilder.append:(Ljava/lang/String;)Ljava/lang/StringBuilder;
     108: invokevirtual #75                 // Method java/lang/StringBuilder.toString:()Ljava/lang/String;
     111: invokespecial #76                 // Method java/lang/IllegalStateException."<init>":(Ljava/lang/String;)V
     114: athrow
     115: aload_0
     116: invokespecial #77                 // Method moveToPrevious:()V
     119: iconst_1
     120: ireturn
     121: iconst_0
     122: ireturn
     123: iload         4
     125: ifge          150
     128: aload_0
     129: getfield      #8                  // Field previous:Lorg/apache/hadoop/hbase/io/encoding/RowIndexSeekerV1$SeekerState;
     132: invokevirtual #68                 // Method org/apache/hadoop/hbase/io/encoding/RowIndexSeekerV1$SeekerState.isValid:()Z
     135: ifeq          145
     138: aload_0
     139: invokespecial #77                 // Method moveToPrevious:()V
     142: goto          148
     145: bipush        -2
     147: ireturn
     148: iconst_1
     149: ireturn
     150: aload_0
     151: getfield      #18                 // Field currentBuffer:Lorg/apache/hadoop/hbase/nio/ByteBuff;
     154: invokevirtual #45                 // Method org/apache/hadoop/hbase/nio/ByteBuff.hasRemaining:()Z
     157: ifeq          178
     160: aload_0
     161: getfield      #8                  // Field previous:Lorg/apache/hadoop/hbase/io/encoding/RowIndexSeekerV1$SeekerState;
     164: aload_0
     165: getfield      #7                  // Field current:Lorg/apache/hadoop/hbase/io/encoding/RowIndexSeekerV1$SeekerState;
     168: invokevirtual #78                 // Method org/apache/hadoop/hbase/io/encoding/RowIndexSeekerV1$SeekerState.copyFromNext:(Lorg/apache/hadoop/hbase/io/encoding/RowIndexSeekerV1$SeekerState;)V
     171: aload_0
     172: invokevirtual #46                 // Method decodeNext:()V
     175: goto          44
     178: iconst_1
     179: ireturn

  public int compareKey(org.apache.hadoop.hbase.CellComparator, org.apache.hadoop.hbase.Cell);
    Code:
       0: aload_1
       1: aload_2
       2: aload_0
       3: getfield      #7                  // Field current:Lorg/apache/hadoop/hbase/io/encoding/RowIndexSeekerV1$SeekerState;
       6: invokestatic  #66                 // Method org/apache/hadoop/hbase/io/encoding/RowIndexSeekerV1$SeekerState.access$100:(Lorg/apache/hadoop/hbase/io/encoding/RowIndexSeekerV1$SeekerState;)Lorg/apache/hadoop/hbase/ByteBufferKeyOnlyKeyValue;
       9: invokestatic  #67                 // Method org/apache/hadoop/hbase/PrivateCellUtil.compareKeyIgnoresMvcc:(Lorg/apache/hadoop/hbase/CellComparator;Lorg/apache/hadoop/hbase/Cell;Lorg/apache/hadoop/hbase/Cell;)I
      12: ireturn

  protected void decodeFirst();
    Code:
       0: aload_0
       1: invokevirtual #46                 // Method decodeNext:()V
       4: aload_0
       5: getfield      #8                  // Field previous:Lorg/apache/hadoop/hbase/io/encoding/RowIndexSeekerV1$SeekerState;
       8: invokevirtual #47                 // Method org/apache/hadoop/hbase/io/encoding/RowIndexSeekerV1$SeekerState.invalidate:()V
      11: return

  protected void decodeAtPosition(int);
    Code:
       0: aload_0
       1: getfield      #18                 // Field currentBuffer:Lorg/apache/hadoop/hbase/nio/ByteBuff;
       4: iload_1
       5: invokevirtual #15                 // Method org/apache/hadoop/hbase/nio/ByteBuff.position:(I)Lorg/apache/hadoop/hbase/nio/ByteBuff;
       8: pop
       9: aload_0
      10: invokevirtual #46                 // Method decodeNext:()V
      13: aload_0
      14: getfield      #8                  // Field previous:Lorg/apache/hadoop/hbase/io/encoding/RowIndexSeekerV1$SeekerState;
      17: invokevirtual #47                 // Method org/apache/hadoop/hbase/io/encoding/RowIndexSeekerV1$SeekerState.invalidate:()V
      20: return

  protected void decodeNext();
    Code:
       0: aload_0
       1: getfield      #7                  // Field current:Lorg/apache/hadoop/hbase/io/encoding/RowIndexSeekerV1$SeekerState;
       4: aload_0
       5: getfield      #18                 // Field currentBuffer:Lorg/apache/hadoop/hbase/nio/ByteBuff;
       8: invokevirtual #14                 // Method org/apache/hadoop/hbase/nio/ByteBuff.position:()I
      11: putfield      #81                 // Field org/apache/hadoop/hbase/io/encoding/RowIndexSeekerV1$SeekerState.startOffset:I
      14: aload_0
      15: getfield      #18                 // Field currentBuffer:Lorg/apache/hadoop/hbase/nio/ByteBuff;
      18: iconst_0
      19: invokevirtual #82                 // Method org/apache/hadoop/hbase/nio/ByteBuff.getLongAfterPosition:(I)J
      22: lstore_1
      23: aload_0
      24: getfield      #7                  // Field current:Lorg/apache/hadoop/hbase/io/encoding/RowIndexSeekerV1$SeekerState;
      27: lload_1
      28: bipush        32
      30: lshr
      31: l2i
      32: putfield      #30                 // Field org/apache/hadoop/hbase/io/encoding/RowIndexSeekerV1$SeekerState.keyLength:I
      35: aload_0
      36: getfield      #7                  // Field current:Lorg/apache/hadoop/hbase/io/encoding/RowIndexSeekerV1$SeekerState;
      39: ldc2_w        #84                 // long -4294967296l
      42: lload_1
      43: lxor
      44: l2i
      45: putfield      #34                 // Field org/apache/hadoop/hbase/io/encoding/RowIndexSeekerV1$SeekerState.valueLength:I
      48: aload_0
      49: getfield      #18                 // Field currentBuffer:Lorg/apache/hadoop/hbase/nio/ByteBuff;
      52: bipush        8
      54: invokevirtual #20                 // Method org/apache/hadoop/hbase/nio/ByteBuff.skip:(I)Lorg/apache/hadoop/hbase/nio/ByteBuff;
      57: pop
      58: aload_0
      59: getfield      #18                 // Field currentBuffer:Lorg/apache/hadoop/hbase/nio/ByteBuff;
      62: aload_0
      63: getfield      #18                 // Field currentBuffer:Lorg/apache/hadoop/hbase/nio/ByteBuff;
      66: invokevirtual #14                 // Method org/apache/hadoop/hbase/nio/ByteBuff.position:()I
      69: aload_0
      70: getfield      #7                  // Field current:Lorg/apache/hadoop/hbase/io/encoding/RowIndexSeekerV1$SeekerState;
      73: getfield      #30                 // Field org/apache/hadoop/hbase/io/encoding/RowIndexSeekerV1$SeekerState.keyLength:I
      76: aload_0
      77: getfield      #4                  // Field tmpPair:Lorg/apache/hadoop/hbase/util/ObjectIntPair;
      80: invokevirtual #35                 // Method org/apache/hadoop/hbase/nio/ByteBuff.asSubByteBuffer:(IILorg/apache/hadoop/hbase/util/ObjectIntPair;)V
      83: aload_0
      84: getfield      #4                  // Field tmpPair:Lorg/apache/hadoop/hbase/util/ObjectIntPair;
      87: invokevirtual #36                 // Method org/apache/hadoop/hbase/util/ObjectIntPair.getFirst:()Ljava/lang/Object;
      90: checkcast     #37                 // class java/nio/ByteBuffer
      93: invokevirtual #38                 // Method java/nio/ByteBuffer.duplicate:()Ljava/nio/ByteBuffer;
      96: astore_3
      97: aload_3
      98: aload_0
      99: getfield      #4                  // Field tmpPair:Lorg/apache/hadoop/hbase/util/ObjectIntPair;
     102: invokevirtual #39                 // Method org/apache/hadoop/hbase/util/ObjectIntPair.getSecond:()I
     105: invokevirtual #40                 // Method java/nio/ByteBuffer.position:(I)Ljava/nio/Buffer;
     108: aload_0
     109: getfield      #4                  // Field tmpPair:Lorg/apache/hadoop/hbase/util/ObjectIntPair;
     112: invokevirtual #39                 // Method org/apache/hadoop/hbase/util/ObjectIntPair.getSecond:()I
     115: aload_0
     116: getfield      #7                  // Field current:Lorg/apache/hadoop/hbase/io/encoding/RowIndexSeekerV1$SeekerState;
     119: getfield      #30                 // Field org/apache/hadoop/hbase/io/encoding/RowIndexSeekerV1$SeekerState.keyLength:I
     122: iadd
     123: invokevirtual #61                 // Method java/nio/Buffer.limit:(I)Ljava/nio/Buffer;
     126: pop
     127: aload_0
     128: getfield      #7                  // Field current:Lorg/apache/hadoop/hbase/io/encoding/RowIndexSeekerV1$SeekerState;
     131: aload_3
     132: putfield      #24                 // Field org/apache/hadoop/hbase/io/encoding/RowIndexSeekerV1$SeekerState.keyBuffer:Ljava/nio/ByteBuffer;
     135: aload_0
     136: getfield      #18                 // Field currentBuffer:Lorg/apache/hadoop/hbase/nio/ByteBuff;
     139: aload_0
     140: getfield      #7                  // Field current:Lorg/apache/hadoop/hbase/io/encoding/RowIndexSeekerV1$SeekerState;
     143: getfield      #30                 // Field org/apache/hadoop/hbase/io/encoding/RowIndexSeekerV1$SeekerState.keyLength:I
     146: invokevirtual #20                 // Method org/apache/hadoop/hbase/nio/ByteBuff.skip:(I)Lorg/apache/hadoop/hbase/nio/ByteBuff;
     149: pop
     150: aload_0
     151: getfield      #7                  // Field current:Lorg/apache/hadoop/hbase/io/encoding/RowIndexSeekerV1$SeekerState;
     154: aload_0
     155: getfield      #18                 // Field currentBuffer:Lorg/apache/hadoop/hbase/nio/ByteBuff;
     158: invokevirtual #14                 // Method org/apache/hadoop/hbase/nio/ByteBuff.position:()I
     161: putfield      #33                 // Field org/apache/hadoop/hbase/io/encoding/RowIndexSeekerV1$SeekerState.valueOffset:I
     164: aload_0
     165: getfield      #18                 // Field currentBuffer:Lorg/apache/hadoop/hbase/nio/ByteBuff;
     168: aload_0
     169: getfield      #7                  // Field current:Lorg/apache/hadoop/hbase/io/encoding/RowIndexSeekerV1$SeekerState;
     172: getfield      #34                 // Field org/apache/hadoop/hbase/io/encoding/RowIndexSeekerV1$SeekerState.valueLength:I
     175: invokevirtual #20                 // Method org/apache/hadoop/hbase/nio/ByteBuff.skip:(I)Lorg/apache/hadoop/hbase/nio/ByteBuff;
     178: pop
     179: aload_0
     180: invokevirtual #86                 // Method includesTags:()Z
     183: ifeq          190
     186: aload_0
     187: invokevirtual #87                 // Method decodeTags:()V
     190: aload_0
     191: invokevirtual #88                 // Method includesMvcc:()Z
     194: ifeq          214
     197: aload_0
     198: getfield      #7                  // Field current:Lorg/apache/hadoop/hbase/io/encoding/RowIndexSeekerV1$SeekerState;
     201: aload_0
     202: getfield      #18                 // Field currentBuffer:Lorg/apache/hadoop/hbase/nio/ByteBuff;
     205: invokestatic  #89                 // Method org/apache/hadoop/hbase/nio/ByteBuff.readVLong:(Lorg/apache/hadoop/hbase/nio/ByteBuff;)J
     208: putfield      #90                 // Field org/apache/hadoop/hbase/io/encoding/RowIndexSeekerV1$SeekerState.memstoreTS:J
     211: goto          222
     214: aload_0
     215: getfield      #7                  // Field current:Lorg/apache/hadoop/hbase/io/encoding/RowIndexSeekerV1$SeekerState;
     218: lconst_0
     219: putfield      #90                 // Field org/apache/hadoop/hbase/io/encoding/RowIndexSeekerV1$SeekerState.memstoreTS:J
     222: aload_0
     223: getfield      #7                  // Field current:Lorg/apache/hadoop/hbase/io/encoding/RowIndexSeekerV1$SeekerState;
     226: aload_0
     227: getfield      #18                 // Field currentBuffer:Lorg/apache/hadoop/hbase/nio/ByteBuff;
     230: invokevirtual #14                 // Method org/apache/hadoop/hbase/nio/ByteBuff.position:()I
     233: putfield      #80                 // Field org/apache/hadoop/hbase/io/encoding/RowIndexSeekerV1$SeekerState.nextKvOffset:I
     236: aload_0
     237: getfield      #7                  // Field current:Lorg/apache/hadoop/hbase/io/encoding/RowIndexSeekerV1$SeekerState;
     240: invokestatic  #66                 // Method org/apache/hadoop/hbase/io/encoding/RowIndexSeekerV1$SeekerState.access$100:(Lorg/apache/hadoop/hbase/io/encoding/RowIndexSeekerV1$SeekerState;)Lorg/apache/hadoop/hbase/ByteBufferKeyOnlyKeyValue;
     243: aload_0
     244: getfield      #7                  // Field current:Lorg/apache/hadoop/hbase/io/encoding/RowIndexSeekerV1$SeekerState;
     247: getfield      #24                 // Field org/apache/hadoop/hbase/io/encoding/RowIndexSeekerV1$SeekerState.keyBuffer:Ljava/nio/ByteBuffer;
     250: aload_0
     251: getfield      #4                  // Field tmpPair:Lorg/apache/hadoop/hbase/util/ObjectIntPair;
     254: invokevirtual #39                 // Method org/apache/hadoop/hbase/util/ObjectIntPair.getSecond:()I
     257: aload_0
     258: getfield      #7                  // Field current:Lorg/apache/hadoop/hbase/io/encoding/RowIndexSeekerV1$SeekerState;
     261: getfield      #30                 // Field org/apache/hadoop/hbase/io/encoding/RowIndexSeekerV1$SeekerState.keyLength:I
     264: invokevirtual #91                 // Method org/apache/hadoop/hbase/ByteBufferKeyOnlyKeyValue.setKey:(Ljava/nio/ByteBuffer;II)V
     267: return

  protected void decodeTags();
    Code:
       0: aload_0
       1: getfield      #7                  // Field current:Lorg/apache/hadoop/hbase/io/encoding/RowIndexSeekerV1$SeekerState;
       4: aload_0
       5: getfield      #18                 // Field currentBuffer:Lorg/apache/hadoop/hbase/nio/ByteBuff;
       8: iconst_0
       9: invokevirtual #92                 // Method org/apache/hadoop/hbase/nio/ByteBuff.getShortAfterPosition:(I)S
      12: putfield      #93                 // Field org/apache/hadoop/hbase/io/encoding/RowIndexSeekerV1$SeekerState.tagsLength:I
      15: aload_0
      16: getfield      #18                 // Field currentBuffer:Lorg/apache/hadoop/hbase/nio/ByteBuff;
      19: iconst_2
      20: invokevirtual #20                 // Method org/apache/hadoop/hbase/nio/ByteBuff.skip:(I)Lorg/apache/hadoop/hbase/nio/ByteBuff;
      23: pop
      24: aload_0
      25: getfield      #7                  // Field current:Lorg/apache/hadoop/hbase/io/encoding/RowIndexSeekerV1$SeekerState;
      28: aload_0
      29: getfield      #18                 // Field currentBuffer:Lorg/apache/hadoop/hbase/nio/ByteBuff;
      32: invokevirtual #14                 // Method org/apache/hadoop/hbase/nio/ByteBuff.position:()I
      35: putfield      #94                 // Field org/apache/hadoop/hbase/io/encoding/RowIndexSeekerV1$SeekerState.tagsOffset:I
      38: aload_0
      39: getfield      #18                 // Field currentBuffer:Lorg/apache/hadoop/hbase/nio/ByteBuff;
      42: aload_0
      43: getfield      #7                  // Field current:Lorg/apache/hadoop/hbase/io/encoding/RowIndexSeekerV1$SeekerState;
      46: getfield      #93                 // Field org/apache/hadoop/hbase/io/encoding/RowIndexSeekerV1$SeekerState.tagsLength:I
      49: invokevirtual #20                 // Method org/apache/hadoop/hbase/nio/ByteBuff.skip:(I)Lorg/apache/hadoop/hbase/nio/ByteBuff;
      52: pop
      53: return
}
