Compiled from "RowIndexSeekerV1.java"
class org.apache.hadoop.hbase.io.encoding.RowIndexSeekerV1$SeekerState {
  public static final int KEY_VALUE_LEN_SIZE;

  protected org.apache.hadoop.hbase.nio.ByteBuff currentBuffer;

  protected int startOffset;

  protected int valueOffset;

  protected int keyLength;

  protected int valueLength;

  protected int tagsLength;

  protected int tagsOffset;

  protected java.nio.ByteBuffer keyBuffer;

  protected long memstoreTS;

  protected int nextKvOffset;

  final org.apache.hadoop.hbase.io.encoding.RowIndexSeekerV1 this$0;

  protected boolean isValid();
    Code:
       0: aload_0
       1: getfield      #7                  // Field valueOffset:I
       4: iconst_m1
       5: if_icmpeq     12
       8: iconst_1
       9: goto          13
      12: iconst_0
      13: ireturn

  protected void invalidate();
    Code:
       0: aload_0
       1: iconst_m1
       2: putfield      #7                  // Field valueOffset:I
       5: aload_0
       6: new           #11                 // class org/apache/hadoop/hbase/ByteBufferKeyOnlyKeyValue
       9: dup
      10: invokespecial #12                 // Method org/apache/hadoop/hbase/ByteBufferKeyOnlyKeyValue."<init>":()V
      13: putfield      #2                  // Field currentKey:Lorg/apache/hadoop/hbase/ByteBufferKeyOnlyKeyValue;
      16: aload_0
      17: aconst_null
      18: putfield      #13                 // Field currentBuffer:Lorg/apache/hadoop/hbase/nio/ByteBuff;
      21: return

  protected void copyFromNext(org.apache.hadoop.hbase.io.encoding.RowIndexSeekerV1$SeekerState);
    Code:
       0: aload_0
       1: aload_1
       2: getfield      #10                 // Field keyBuffer:Ljava/nio/ByteBuffer;
       5: putfield      #10                 // Field keyBuffer:Ljava/nio/ByteBuffer;
       8: aload_0
       9: getfield      #2                  // Field currentKey:Lorg/apache/hadoop/hbase/ByteBufferKeyOnlyKeyValue;
      12: aload_1
      13: getfield      #10                 // Field keyBuffer:Ljava/nio/ByteBuffer;
      16: aload_1
      17: getfield      #2                  // Field currentKey:Lorg/apache/hadoop/hbase/ByteBufferKeyOnlyKeyValue;
      20: invokevirtual #14                 // Method org/apache/hadoop/hbase/ByteBufferKeyOnlyKeyValue.getRowPosition:()I
      23: iconst_2
      24: isub
      25: aload_1
      26: getfield      #15                 // Field keyLength:I
      29: invokevirtual #16                 // Method org/apache/hadoop/hbase/ByteBufferKeyOnlyKeyValue.setKey:(Ljava/nio/ByteBuffer;II)V
      32: aload_0
      33: aload_1
      34: getfield      #6                  // Field startOffset:I
      37: putfield      #6                  // Field startOffset:I
      40: aload_0
      41: aload_1
      42: getfield      #7                  // Field valueOffset:I
      45: putfield      #7                  // Field valueOffset:I
      48: aload_0
      49: aload_1
      50: getfield      #15                 // Field keyLength:I
      53: putfield      #15                 // Field keyLength:I
      56: aload_0
      57: aload_1
      58: getfield      #17                 // Field valueLength:I
      61: putfield      #17                 // Field valueLength:I
      64: aload_0
      65: aload_1
      66: getfield      #18                 // Field nextKvOffset:I
      69: putfield      #18                 // Field nextKvOffset:I
      72: aload_0
      73: aload_1
      74: getfield      #19                 // Field memstoreTS:J
      77: putfield      #19                 // Field memstoreTS:J
      80: aload_0
      81: aload_1
      82: getfield      #13                 // Field currentBuffer:Lorg/apache/hadoop/hbase/nio/ByteBuff;
      85: putfield      #13                 // Field currentBuffer:Lorg/apache/hadoop/hbase/nio/ByteBuff;
      88: aload_0
      89: aload_1
      90: getfield      #9                  // Field tagsOffset:I
      93: putfield      #9                  // Field tagsOffset:I
      96: aload_0
      97: aload_1
      98: getfield      #8                  // Field tagsLength:I
     101: putfield      #8                  // Field tagsLength:I
     104: return

  public java.lang.String toString();
    Code:
       0: aload_0
       1: invokevirtual #20                 // Method toCell:()Lorg/apache/hadoop/hbase/Cell;
       4: invokestatic  #21                 // Method org/apache/hadoop/hbase/CellUtil.getCellKeyAsString:(Lorg/apache/hadoop/hbase/Cell;)Ljava/lang/String;
       7: areturn

  protected int getCellBufSize();
    Code:
       0: bipush        8
       2: aload_0
       3: getfield      #15                 // Field keyLength:I
       6: iadd
       7: aload_0
       8: getfield      #17                 // Field valueLength:I
      11: iadd
      12: istore_1
      13: aload_0
      14: getfield      #4                  // Field this$0:Lorg/apache/hadoop/hbase/io/encoding/RowIndexSeekerV1;
      17: invokevirtual #23                 // Method org/apache/hadoop/hbase/io/encoding/RowIndexSeekerV1.includesTags:()Z
      20: ifeq          39
      23: aload_0
      24: getfield      #8                  // Field tagsLength:I
      27: ifle          39
      30: iload_1
      31: iconst_2
      32: aload_0
      33: getfield      #8                  // Field tagsLength:I
      36: iadd
      37: iadd
      38: istore_1
      39: iload_1
      40: ireturn

  public org.apache.hadoop.hbase.Cell toCell();
    Code:
       0: aload_0
       1: invokevirtual #24                 // Method getCellBufSize:()I
       4: istore_2
       5: lconst_0
       6: lstore_3
       7: aload_0
       8: getfield      #4                  // Field this$0:Lorg/apache/hadoop/hbase/io/encoding/RowIndexSeekerV1;
      11: invokevirtual #25                 // Method org/apache/hadoop/hbase/io/encoding/RowIndexSeekerV1.includesMvcc:()Z
      14: ifeq          22
      17: aload_0
      18: getfield      #19                 // Field memstoreTS:J
      21: lstore_3
      22: aload_0
      23: getfield      #13                 // Field currentBuffer:Lorg/apache/hadoop/hbase/nio/ByteBuff;
      26: invokevirtual #26                 // Method org/apache/hadoop/hbase/nio/ByteBuff.hasArray:()Z
      29: ifeq          103
      32: aload_0
      33: getfield      #8                  // Field tagsLength:I
      36: ifle          71
      39: new           #27                 // class org/apache/hadoop/hbase/SizeCachedKeyValue
      42: dup
      43: aload_0
      44: getfield      #13                 // Field currentBuffer:Lorg/apache/hadoop/hbase/nio/ByteBuff;
      47: invokevirtual #28                 // Method org/apache/hadoop/hbase/nio/ByteBuff.array:()[B
      50: aload_0
      51: getfield      #13                 // Field currentBuffer:Lorg/apache/hadoop/hbase/nio/ByteBuff;
      54: invokevirtual #29                 // Method org/apache/hadoop/hbase/nio/ByteBuff.arrayOffset:()I
      57: aload_0
      58: getfield      #6                  // Field startOffset:I
      61: iadd
      62: iload_2
      63: lload_3
      64: invokespecial #30                 // Method org/apache/hadoop/hbase/SizeCachedKeyValue."<init>":([BIIJ)V
      67: astore_1
      68: goto          273
      71: new           #31                 // class org/apache/hadoop/hbase/SizeCachedNoTagsKeyValue
      74: dup
      75: aload_0
      76: getfield      #13                 // Field currentBuffer:Lorg/apache/hadoop/hbase/nio/ByteBuff;
      79: invokevirtual #28                 // Method org/apache/hadoop/hbase/nio/ByteBuff.array:()[B
      82: aload_0
      83: getfield      #13                 // Field currentBuffer:Lorg/apache/hadoop/hbase/nio/ByteBuff;
      86: invokevirtual #29                 // Method org/apache/hadoop/hbase/nio/ByteBuff.arrayOffset:()I
      89: aload_0
      90: getfield      #6                  // Field startOffset:I
      93: iadd
      94: iload_2
      95: lload_3
      96: invokespecial #32                 // Method org/apache/hadoop/hbase/SizeCachedNoTagsKeyValue."<init>":([BIIJ)V
      99: astore_1
     100: goto          273
     103: aload_0
     104: getfield      #13                 // Field currentBuffer:Lorg/apache/hadoop/hbase/nio/ByteBuff;
     107: aload_0
     108: getfield      #6                  // Field startOffset:I
     111: iload_2
     112: aload_0
     113: getfield      #4                  // Field this$0:Lorg/apache/hadoop/hbase/io/encoding/RowIndexSeekerV1;
     116: getfield      #33                 // Field org/apache/hadoop/hbase/io/encoding/RowIndexSeekerV1.tmpPair:Lorg/apache/hadoop/hbase/util/ObjectIntPair;
     119: invokevirtual #34                 // Method org/apache/hadoop/hbase/nio/ByteBuff.asSubByteBuffer:(IILorg/apache/hadoop/hbase/util/ObjectIntPair;)V
     122: aload_0
     123: getfield      #4                  // Field this$0:Lorg/apache/hadoop/hbase/io/encoding/RowIndexSeekerV1;
     126: getfield      #33                 // Field org/apache/hadoop/hbase/io/encoding/RowIndexSeekerV1.tmpPair:Lorg/apache/hadoop/hbase/util/ObjectIntPair;
     129: invokevirtual #35                 // Method org/apache/hadoop/hbase/util/ObjectIntPair.getFirst:()Ljava/lang/Object;
     132: checkcast     #36                 // class java/nio/ByteBuffer
     135: astore        5
     137: aload         5
     139: invokevirtual #37                 // Method java/nio/ByteBuffer.isDirect:()Z
     142: ifeq          201
     145: aload_0
     146: getfield      #8                  // Field tagsLength:I
     149: ifle          176
     152: new           #38                 // class org/apache/hadoop/hbase/ByteBufferKeyValue
     155: dup
     156: aload         5
     158: aload_0
     159: getfield      #4                  // Field this$0:Lorg/apache/hadoop/hbase/io/encoding/RowIndexSeekerV1;
     162: getfield      #33                 // Field org/apache/hadoop/hbase/io/encoding/RowIndexSeekerV1.tmpPair:Lorg/apache/hadoop/hbase/util/ObjectIntPair;
     165: invokevirtual #39                 // Method org/apache/hadoop/hbase/util/ObjectIntPair.getSecond:()I
     168: iload_2
     169: lload_3
     170: invokespecial #40                 // Method org/apache/hadoop/hbase/ByteBufferKeyValue."<init>":(Ljava/nio/ByteBuffer;IIJ)V
     173: goto          197
     176: new           #41                 // class org/apache/hadoop/hbase/NoTagsByteBufferKeyValue
     179: dup
     180: aload         5
     182: aload_0
     183: getfield      #4                  // Field this$0:Lorg/apache/hadoop/hbase/io/encoding/RowIndexSeekerV1;
     186: getfield      #33                 // Field org/apache/hadoop/hbase/io/encoding/RowIndexSeekerV1.tmpPair:Lorg/apache/hadoop/hbase/util/ObjectIntPair;
     189: invokevirtual #39                 // Method org/apache/hadoop/hbase/util/ObjectIntPair.getSecond:()I
     192: iload_2
     193: lload_3
     194: invokespecial #42                 // Method org/apache/hadoop/hbase/NoTagsByteBufferKeyValue."<init>":(Ljava/nio/ByteBuffer;IIJ)V
     197: astore_1
     198: goto          273
     201: aload_0
     202: getfield      #8                  // Field tagsLength:I
     205: ifle          242
     208: new           #27                 // class org/apache/hadoop/hbase/SizeCachedKeyValue
     211: dup
     212: aload         5
     214: invokevirtual #43                 // Method java/nio/ByteBuffer.array:()[B
     217: aload         5
     219: invokevirtual #44                 // Method java/nio/ByteBuffer.arrayOffset:()I
     222: aload_0
     223: getfield      #4                  // Field this$0:Lorg/apache/hadoop/hbase/io/encoding/RowIndexSeekerV1;
     226: getfield      #33                 // Field org/apache/hadoop/hbase/io/encoding/RowIndexSeekerV1.tmpPair:Lorg/apache/hadoop/hbase/util/ObjectIntPair;
     229: invokevirtual #39                 // Method org/apache/hadoop/hbase/util/ObjectIntPair.getSecond:()I
     232: iadd
     233: iload_2
     234: lload_3
     235: invokespecial #30                 // Method org/apache/hadoop/hbase/SizeCachedKeyValue."<init>":([BIIJ)V
     238: astore_1
     239: goto          273
     242: new           #31                 // class org/apache/hadoop/hbase/SizeCachedNoTagsKeyValue
     245: dup
     246: aload         5
     248: invokevirtual #43                 // Method java/nio/ByteBuffer.array:()[B
     251: aload         5
     253: invokevirtual #44                 // Method java/nio/ByteBuffer.arrayOffset:()I
     256: aload_0
     257: getfield      #4                  // Field this$0:Lorg/apache/hadoop/hbase/io/encoding/RowIndexSeekerV1;
     260: getfield      #33                 // Field org/apache/hadoop/hbase/io/encoding/RowIndexSeekerV1.tmpPair:Lorg/apache/hadoop/hbase/util/ObjectIntPair;
     263: invokevirtual #39                 // Method org/apache/hadoop/hbase/util/ObjectIntPair.getSecond:()I
     266: iadd
     267: iload_2
     268: lload_3
     269: invokespecial #32                 // Method org/apache/hadoop/hbase/SizeCachedNoTagsKeyValue."<init>":([BIIJ)V
     272: astore_1
     273: aload_1
     274: areturn

  org.apache.hadoop.hbase.io.encoding.RowIndexSeekerV1$SeekerState(org.apache.hadoop.hbase.io.encoding.RowIndexSeekerV1, org.apache.hadoop.hbase.io.encoding.RowIndexSeekerV1$1);
    Code:
       0: aload_0
       1: aload_1
       2: invokespecial #3                  // Method "<init>":(Lorg/apache/hadoop/hbase/io/encoding/RowIndexSeekerV1;)V
       5: return

  static org.apache.hadoop.hbase.ByteBufferKeyOnlyKeyValue access$100(org.apache.hadoop.hbase.io.encoding.RowIndexSeekerV1$SeekerState);
    Code:
       0: aload_0
       1: getfield      #2                  // Field currentKey:Lorg/apache/hadoop/hbase/ByteBufferKeyOnlyKeyValue;
       4: areturn
}
