Compiled from "RowIndexCodecV1.java"
public class org.apache.hadoop.hbase.io.encoding.RowIndexCodecV1 extends org.apache.hadoop.hbase.io.encoding.AbstractDataBlockEncoder {
  public org.apache.hadoop.hbase.io.encoding.RowIndexCodecV1();
    Code:
       0: aload_0
       1: invokespecial #1                  // Method org/apache/hadoop/hbase/io/encoding/AbstractDataBlockEncoder."<init>":()V
       4: return

  public void startBlockEncoding(org.apache.hadoop.hbase.io.encoding.HFileBlockEncodingContext, java.io.DataOutputStream) throws java.io.IOException;
    Code:
       0: aload_1
       1: invokevirtual #2                  // Method java/lang/Object.getClass:()Ljava/lang/Class;
       4: ldc           #3                  // class org/apache/hadoop/hbase/io/encoding/HFileBlockDefaultEncodingContext
       6: if_acmpeq     55
       9: new           #4                  // class java/io/IOException
      12: dup
      13: new           #5                  // class java/lang/StringBuilder
      16: dup
      17: invokespecial #6                  // Method java/lang/StringBuilder."<init>":()V
      20: aload_0
      21: invokevirtual #2                  // Method java/lang/Object.getClass:()Ljava/lang/Class;
      24: invokevirtual #7                  // Method java/lang/Class.getName:()Ljava/lang/String;
      27: invokevirtual #8                  // Method java/lang/StringBuilder.append:(Ljava/lang/String;)Ljava/lang/StringBuilder;
      30: ldc           #9                  // String  only accepts
      32: invokevirtual #8                  // Method java/lang/StringBuilder.append:(Ljava/lang/String;)Ljava/lang/StringBuilder;
      35: ldc           #3                  // class org/apache/hadoop/hbase/io/encoding/HFileBlockDefaultEncodingContext
      37: invokevirtual #7                  // Method java/lang/Class.getName:()Ljava/lang/String;
      40: invokevirtual #8                  // Method java/lang/StringBuilder.append:(Ljava/lang/String;)Ljava/lang/StringBuilder;
      43: ldc           #10                 // String  as the encoding context.
      45: invokevirtual #8                  // Method java/lang/StringBuilder.append:(Ljava/lang/String;)Ljava/lang/StringBuilder;
      48: invokevirtual #11                 // Method java/lang/StringBuilder.toString:()Ljava/lang/String;
      51: invokespecial #12                 // Method java/io/IOException."<init>":(Ljava/lang/String;)V
      54: athrow
      55: aload_1
      56: checkcast     #3                  // class org/apache/hadoop/hbase/io/encoding/HFileBlockDefaultEncodingContext
      59: astore_3
      60: aload_3
      61: aload_2
      62: invokevirtual #13                 // Method org/apache/hadoop/hbase/io/encoding/HFileBlockDefaultEncodingContext.prepareEncoding:(Ljava/io/DataOutputStream;)V
      65: new           #14                 // class org/apache/hadoop/hbase/io/encoding/RowIndexEncoderV1
      68: dup
      69: aload_2
      70: aload_3
      71: invokespecial #15                 // Method org/apache/hadoop/hbase/io/encoding/RowIndexEncoderV1."<init>":(Ljava/io/DataOutputStream;Lorg/apache/hadoop/hbase/io/encoding/HFileBlockDefaultEncodingContext;)V
      74: astore        4
      76: new           #16                 // class org/apache/hadoop/hbase/io/encoding/RowIndexCodecV1$RowIndexEncodingState
      79: dup
      80: aconst_null
      81: invokespecial #17                 // Method org/apache/hadoop/hbase/io/encoding/RowIndexCodecV1$RowIndexEncodingState."<init>":(Lorg/apache/hadoop/hbase/io/encoding/RowIndexCodecV1$1;)V
      84: astore        5
      86: aload         5
      88: aload         4
      90: putfield      #18                 // Field org/apache/hadoop/hbase/io/encoding/RowIndexCodecV1$RowIndexEncodingState.encoder:Lorg/apache/hadoop/hbase/io/encoding/RowIndexEncoderV1;
      93: aload_1
      94: aload         5
      96: invokeinterface #19,  2           // InterfaceMethod org/apache/hadoop/hbase/io/encoding/HFileBlockEncodingContext.setEncodingState:(Lorg/apache/hadoop/hbase/io/encoding/EncodingState;)V
     101: return

  public int encode(org.apache.hadoop.hbase.Cell, org.apache.hadoop.hbase.io.encoding.HFileBlockEncodingContext, java.io.DataOutputStream) throws java.io.IOException;
    Code:
       0: aload_2
       1: invokeinterface #20,  1           // InterfaceMethod org/apache/hadoop/hbase/io/encoding/HFileBlockEncodingContext.getEncodingState:()Lorg/apache/hadoop/hbase/io/encoding/EncodingState;
       6: checkcast     #16                 // class org/apache/hadoop/hbase/io/encoding/RowIndexCodecV1$RowIndexEncodingState
       9: astore        4
      11: aload         4
      13: getfield      #18                 // Field org/apache/hadoop/hbase/io/encoding/RowIndexCodecV1$RowIndexEncodingState.encoder:Lorg/apache/hadoop/hbase/io/encoding/RowIndexEncoderV1;
      16: astore        5
      18: aload         5
      20: aload_1
      21: invokevirtual #21                 // Method org/apache/hadoop/hbase/io/encoding/RowIndexEncoderV1.write:(Lorg/apache/hadoop/hbase/Cell;)I
      24: ireturn

  public void endBlockEncoding(org.apache.hadoop.hbase.io.encoding.HFileBlockEncodingContext, java.io.DataOutputStream, byte[]) throws java.io.IOException;
    Code:
       0: aload_1
       1: invokeinterface #20,  1           // InterfaceMethod org/apache/hadoop/hbase/io/encoding/HFileBlockEncodingContext.getEncodingState:()Lorg/apache/hadoop/hbase/io/encoding/EncodingState;
       6: checkcast     #16                 // class org/apache/hadoop/hbase/io/encoding/RowIndexCodecV1$RowIndexEncodingState
       9: astore        4
      11: aload         4
      13: getfield      #18                 // Field org/apache/hadoop/hbase/io/encoding/RowIndexCodecV1$RowIndexEncodingState.encoder:Lorg/apache/hadoop/hbase/io/encoding/RowIndexEncoderV1;
      16: astore        5
      18: aload         5
      20: invokevirtual #22                 // Method org/apache/hadoop/hbase/io/encoding/RowIndexEncoderV1.flush:()V
      23: aload_0
      24: aload_1
      25: invokevirtual #23                 // Method postEncoding:(Lorg/apache/hadoop/hbase/io/encoding/HFileBlockEncodingContext;)V
      28: return

  public java.nio.ByteBuffer decodeKeyValues(java.io.DataInputStream, org.apache.hadoop.hbase.io.encoding.HFileBlockDecodingContext) throws java.io.IOException;
    Code:
       0: aload_1
       1: invokestatic  #24                 // Method org/apache/hadoop/hbase/util/ByteBufferUtils.drainInputStreamToBuffer:(Ljava/io/InputStream;)Ljava/nio/ByteBuffer;
       4: astore_3
       5: aload_3
       6: invokevirtual #25                 // Method java/nio/ByteBuffer.mark:()Ljava/nio/Buffer;
       9: pop
      10: aload_2
      11: invokeinterface #26,  1           // InterfaceMethod org/apache/hadoop/hbase/io/encoding/HFileBlockDecodingContext.getHFileContext:()Lorg/apache/hadoop/hbase/io/hfile/HFileContext;
      16: invokevirtual #27                 // Method org/apache/hadoop/hbase/io/hfile/HFileContext.isIncludesTags:()Z
      19: ifne          79
      22: aload_3
      23: aload_3
      24: invokevirtual #28                 // Method java/nio/ByteBuffer.limit:()I
      27: iconst_4
      28: isub
      29: invokevirtual #30                 // Method java/nio/ByteBuffer.position:(I)Ljava/nio/Buffer;
      32: pop
      33: aload_3
      34: invokevirtual #31                 // Method java/nio/ByteBuffer.getInt:()I
      37: istore        4
      39: aload_3
      40: invokevirtual #32                 // Method java/nio/ByteBuffer.reset:()Ljava/nio/Buffer;
      43: pop
      44: aload_3
      45: invokevirtual #33                 // Method java/nio/ByteBuffer.duplicate:()Ljava/nio/ByteBuffer;
      48: astore        5
      50: aload         5
      52: aload_3
      53: invokevirtual #34                 // Method java/nio/ByteBuffer.position:()I
      56: invokevirtual #30                 // Method java/nio/ByteBuffer.position:(I)Ljava/nio/Buffer;
      59: pop
      60: aload         5
      62: aload_3
      63: invokevirtual #34                 // Method java/nio/ByteBuffer.position:()I
      66: iload         4
      68: iadd
      69: invokevirtual #35                 // Method java/nio/ByteBuffer.limit:(I)Ljava/nio/Buffer;
      72: pop
      73: aload         5
      75: invokevirtual #36                 // Method java/nio/ByteBuffer.slice:()Ljava/nio/ByteBuffer;
      78: areturn
      79: new           #37                 // class org/apache/hadoop/hbase/io/encoding/RowIndexSeekerV1
      82: dup
      83: getstatic     #38                 // Field org/apache/hadoop/hbase/CellComparatorImpl.COMPARATOR:Lorg/apache/hadoop/hbase/CellComparatorImpl;
      86: aload_2
      87: invokespecial #39                 // Method org/apache/hadoop/hbase/io/encoding/RowIndexSeekerV1."<init>":(Lorg/apache/hadoop/hbase/CellComparator;Lorg/apache/hadoop/hbase/io/encoding/HFileBlockDecodingContext;)V
      90: astore        4
      92: aload         4
      94: new           #40                 // class org/apache/hadoop/hbase/nio/SingleByteBuff
      97: dup
      98: aload_3
      99: invokespecial #41                 // Method org/apache/hadoop/hbase/nio/SingleByteBuff."<init>":(Ljava/nio/ByteBuffer;)V
     102: invokevirtual #42                 // Method org/apache/hadoop/hbase/io/encoding/RowIndexSeekerV1.setCurrentBuffer:(Lorg/apache/hadoop/hbase/nio/ByteBuff;)V
     105: new           #43                 // class java/util/ArrayList
     108: dup
     109: invokespecial #44                 // Method java/util/ArrayList."<init>":()V
     112: astore        5
     114: aload         5
     116: aload         4
     118: invokevirtual #45                 // Method org/apache/hadoop/hbase/io/encoding/RowIndexSeekerV1.getCell:()Lorg/apache/hadoop/hbase/Cell;
     121: invokeinterface #46,  2           // InterfaceMethod java/util/List.add:(Ljava/lang/Object;)Z
     126: pop
     127: aload         4
     129: invokevirtual #47                 // Method org/apache/hadoop/hbase/io/encoding/RowIndexSeekerV1.next:()Z
     132: ifeq          151
     135: aload         5
     137: aload         4
     139: invokevirtual #45                 // Method org/apache/hadoop/hbase/io/encoding/RowIndexSeekerV1.getCell:()Lorg/apache/hadoop/hbase/Cell;
     142: invokeinterface #46,  2           // InterfaceMethod java/util/List.add:(Ljava/lang/Object;)Z
     147: pop
     148: goto          127
     151: aload_2
     152: invokeinterface #26,  1           // InterfaceMethod org/apache/hadoop/hbase/io/encoding/HFileBlockDecodingContext.getHFileContext:()Lorg/apache/hadoop/hbase/io/hfile/HFileContext;
     157: invokevirtual #48                 // Method org/apache/hadoop/hbase/io/hfile/HFileContext.isIncludesMvcc:()Z
     160: istore        6
     162: new           #49                 // class org/apache/hadoop/hbase/io/ByteArrayOutputStream
     165: dup
     166: invokespecial #50                 // Method org/apache/hadoop/hbase/io/ByteArrayOutputStream."<init>":()V
     169: astore        7
     171: new           #51                 // class java/io/DataOutputStream
     174: dup
     175: aload         7
     177: invokespecial #52                 // Method java/io/DataOutputStream."<init>":(Ljava/io/OutputStream;)V
     180: astore        8
     182: aload         5
     184: invokeinterface #53,  1           // InterfaceMethod java/util/List.iterator:()Ljava/util/Iterator;
     189: astore        9
     191: aload         9
     193: invokeinterface #54,  1           // InterfaceMethod java/util/Iterator.hasNext:()Z
     198: ifeq          260
     201: aload         9
     203: invokeinterface #55,  1           // InterfaceMethod java/util/Iterator.next:()Ljava/lang/Object;
     208: checkcast     #56                 // class org/apache/hadoop/hbase/Cell
     211: astore        10
     213: aload         10
     215: invokestatic  #57                 // Method org/apache/hadoop/hbase/KeyValueUtil.copyToNewKeyValue:(Lorg/apache/hadoop/hbase/Cell;)Lorg/apache/hadoop/hbase/KeyValue;
     218: astore        11
     220: aload         8
     222: aload         11
     224: invokevirtual #58                 // Method org/apache/hadoop/hbase/KeyValue.getBuffer:()[B
     227: aload         11
     229: invokevirtual #59                 // Method org/apache/hadoop/hbase/KeyValue.getOffset:()I
     232: aload         11
     234: invokevirtual #60                 // Method org/apache/hadoop/hbase/KeyValue.getLength:()I
     237: invokevirtual #61                 // Method java/io/DataOutputStream.write:([BII)V
     240: iload         6
     242: ifeq          257
     245: aload         8
     247: aload         10
     249: invokeinterface #62,  1           // InterfaceMethod org/apache/hadoop/hbase/Cell.getSequenceId:()J
     254: invokestatic  #63                 // Method org/apache/hadoop/io/WritableUtils.writeVLong:(Ljava/io/DataOutput;J)V
     257: goto          191
     260: aload         8
     262: invokevirtual #64                 // Method java/io/DataOutputStream.flush:()V
     265: aload         7
     267: invokevirtual #65                 // Method org/apache/hadoop/hbase/io/ByteArrayOutputStream.getBuffer:()[B
     270: iconst_0
     271: aload         7
     273: invokevirtual #66                 // Method org/apache/hadoop/hbase/io/ByteArrayOutputStream.size:()I
     276: invokestatic  #67                 // Method java/nio/ByteBuffer.wrap:([BII)Ljava/nio/ByteBuffer;
     279: areturn

  public org.apache.hadoop.hbase.Cell getFirstKeyCellInBlock(org.apache.hadoop.hbase.nio.ByteBuff);
    Code:
       0: aload_1
       1: invokevirtual #68                 // Method org/apache/hadoop/hbase/nio/ByteBuff.mark:()Lorg/apache/hadoop/hbase/nio/ByteBuff;
       4: pop
       5: aload_1
       6: invokevirtual #69                 // Method org/apache/hadoop/hbase/nio/ByteBuff.getInt:()I
       9: istore_2
      10: aload_1
      11: invokevirtual #69                 // Method org/apache/hadoop/hbase/nio/ByteBuff.getInt:()I
      14: pop
      15: aload_1
      16: iload_2
      17: invokevirtual #70                 // Method org/apache/hadoop/hbase/nio/ByteBuff.asSubByteBuffer:(I)Ljava/nio/ByteBuffer;
      20: invokevirtual #33                 // Method java/nio/ByteBuffer.duplicate:()Ljava/nio/ByteBuffer;
      23: astore_3
      24: aload_1
      25: invokevirtual #71                 // Method org/apache/hadoop/hbase/nio/ByteBuff.reset:()Lorg/apache/hadoop/hbase/nio/ByteBuff;
      28: pop
      29: aload_0
      30: aload_3
      31: iload_2
      32: invokevirtual #72                 // Method createFirstKeyCell:(Ljava/nio/ByteBuffer;I)Lorg/apache/hadoop/hbase/Cell;
      35: areturn

  public org.apache.hadoop.hbase.io.encoding.DataBlockEncoder$EncodedSeeker createSeeker(org.apache.hadoop.hbase.CellComparator, org.apache.hadoop.hbase.io.encoding.HFileBlockDecodingContext);
    Code:
       0: new           #37                 // class org/apache/hadoop/hbase/io/encoding/RowIndexSeekerV1
       3: dup
       4: aload_1
       5: aload_2
       6: invokespecial #39                 // Method org/apache/hadoop/hbase/io/encoding/RowIndexSeekerV1."<init>":(Lorg/apache/hadoop/hbase/CellComparator;Lorg/apache/hadoop/hbase/io/encoding/HFileBlockDecodingContext;)V
       9: areturn
}
