Compiled from "RowProcessorClient.java"
public class org.apache.hadoop.hbase.client.coprocessor.RowProcessorClient {
  public org.apache.hadoop.hbase.client.coprocessor.RowProcessorClient();
    Code:
       0: aload_0
       1: invokespecial #1                  // Method java/lang/Object."<init>":()V
       4: return

  public static <S extends com.google.protobuf.Message, T extends com.google.protobuf.Message> org.apache.hadoop.hbase.protobuf.generated.RowProcessorProtos$ProcessRequest getRowProcessorPB(org.apache.hadoop.hbase.regionserver.RowProcessor<S, T>) throws java.io.IOException;
    Code:
       0: invokestatic  #2                  // Method org/apache/hadoop/hbase/protobuf/generated/RowProcessorProtos$ProcessRequest.newBuilder:()Lorg/apache/hadoop/hbase/protobuf/generated/RowProcessorProtos$ProcessRequest$Builder;
       3: astore_1
       4: aload_1
       5: aload_0
       6: invokevirtual #3                  // Method java/lang/Object.getClass:()Ljava/lang/Class;
       9: invokevirtual #4                  // Method java/lang/Class.getName:()Ljava/lang/String;
      12: invokevirtual #5                  // Method org/apache/hadoop/hbase/protobuf/generated/RowProcessorProtos$ProcessRequest$Builder.setRowProcessorClassName:(Ljava/lang/String;)Lorg/apache/hadoop/hbase/protobuf/generated/RowProcessorProtos$ProcessRequest$Builder;
      15: pop
      16: aload_0
      17: invokeinterface #6,  1            // InterfaceMethod org/apache/hadoop/hbase/regionserver/RowProcessor.getRequestData:()Lcom/google/protobuf/Message;
      22: astore_2
      23: aload_2
      24: ifnull        50
      27: aload_1
      28: aload_2
      29: invokevirtual #3                  // Method java/lang/Object.getClass:()Ljava/lang/Class;
      32: invokevirtual #4                  // Method java/lang/Class.getName:()Ljava/lang/String;
      35: invokevirtual #7                  // Method org/apache/hadoop/hbase/protobuf/generated/RowProcessorProtos$ProcessRequest$Builder.setRowProcessorInitializerMessageName:(Ljava/lang/String;)Lorg/apache/hadoop/hbase/protobuf/generated/RowProcessorProtos$ProcessRequest$Builder;
      38: pop
      39: aload_1
      40: aload_2
      41: invokeinterface #8,  1            // InterfaceMethod com/google/protobuf/Message.toByteString:()Lcom/google/protobuf/ByteString;
      46: invokevirtual #9                  // Method org/apache/hadoop/hbase/protobuf/generated/RowProcessorProtos$ProcessRequest$Builder.setRowProcessorInitializerMessage:(Lcom/google/protobuf/ByteString;)Lorg/apache/hadoop/hbase/protobuf/generated/RowProcessorProtos$ProcessRequest$Builder;
      49: pop
      50: aload_1
      51: invokevirtual #10                 // Method org/apache/hadoop/hbase/protobuf/generated/RowProcessorProtos$ProcessRequest$Builder.build:()Lorg/apache/hadoop/hbase/protobuf/generated/RowProcessorProtos$ProcessRequest;
      54: areturn
}
