Compiled from "RpcExecutor.java"
class org.apache.hadoop.hbase.ipc.RpcExecutor$RandomQueueBalancer extends org.apache.hadoop.hbase.ipc.RpcExecutor$QueueBalancer {
  public org.apache.hadoop.hbase.ipc.RpcExecutor$RandomQueueBalancer(int);
    Code:
       0: aload_0
       1: invokespecial #1                  // Method org/apache/hadoop/hbase/ipc/RpcExecutor$QueueBalancer."<init>":()V
       4: aload_0
       5: iload_1
       6: putfield      #2                  // Field queueSize:I
       9: return

  public int getNextQueue();
    Code:
       0: invokestatic  #3                  // Method java/util/concurrent/ThreadLocalRandom.current:()Ljava/util/concurrent/ThreadLocalRandom;
       3: aload_0
       4: getfield      #2                  // Field queueSize:I
       7: invokevirtual #4                  // Method java/util/concurrent/ThreadLocalRandom.nextInt:(I)I
      10: ireturn
}
