Compiled from "RpcServer.java"
public abstract class org.apache.hadoop.hbase.ipc.RpcServer implements org.apache.hadoop.hbase.ipc.RpcServerInterface,org.apache.hadoop.hbase.conf.ConfigurationObserver {
  public static final org.slf4j.Logger LOG;

  protected static final org.apache.hadoop.hbase.CallQueueTooBigException CALL_QUEUE_TOO_BIG_EXCEPTION;

  protected boolean isSecurityEnabled;

  public static final byte CURRENT_VERSION;

  public static final java.lang.String FALLBACK_TO_INSECURE_CLIENT_AUTH;

  protected static final int DEFAULT_MAX_CALLQUEUE_LENGTH_PER_HANDLER;

  protected final org.apache.hadoop.hbase.ipc.CellBlockBuilder cellBlockBuilder;

  protected static final java.lang.String AUTH_FAILED_FOR;

  protected static final java.lang.String AUTH_SUCCESSFUL_FOR;

  protected static final org.slf4j.Logger AUDITLOG;

  protected org.apache.hadoop.security.token.SecretManager<org.apache.hadoop.security.token.TokenIdentifier> secretManager;

  protected final java.util.Map<java.lang.String, java.lang.String> saslProps;

  protected org.apache.hadoop.security.authorize.ServiceAuthorizationManager authManager;

  protected static final java.lang.ThreadLocal<org.apache.hadoop.hbase.ipc.RpcCall> CurCall;

  protected static final java.lang.ThreadLocal<org.apache.hadoop.hbase.monitoring.MonitoredRPCHandler> MONITORED_RPC;

  protected final java.net.InetSocketAddress bindAddress;

  protected org.apache.hadoop.hbase.ipc.MetricsHBaseServer metrics;

  protected final org.apache.hadoop.conf.Configuration conf;

  protected final long maxQueueSizeInBytes;

  protected static final int DEFAULT_MAX_CALLQUEUE_SIZE;

  protected final java.util.concurrent.atomic.LongAdder callQueueSizeInBytes;

  protected final boolean tcpNoDelay;

  protected final boolean tcpKeepAlive;

  volatile boolean running;

  volatile boolean started;

  protected org.apache.hadoop.hbase.security.token.AuthenticationTokenSecretManager authTokenSecretMgr;

  protected org.apache.hadoop.hbase.ipc.HBaseRPCErrorHandler errorHandler;

  public static final java.lang.String MAX_REQUEST_SIZE;

  protected static final org.apache.hadoop.hbase.exceptions.RequestTooBigException REQUEST_TOO_BIG_EXCEPTION;

  protected static final java.lang.String WARN_RESPONSE_TIME;

  protected static final java.lang.String WARN_RESPONSE_SIZE;

  protected static final java.lang.String MIN_CLIENT_REQUEST_TIMEOUT;

  protected static final int DEFAULT_MIN_CLIENT_REQUEST_TIMEOUT;

  public static final int DEFAULT_MAX_REQUEST_SIZE;

  protected static final int DEFAULT_WARN_RESPONSE_TIME;

  protected static final int DEFAULT_WARN_RESPONSE_SIZE;

  protected static final int DEFAULT_TRACE_LOG_MAX_LENGTH;

  protected static final java.lang.String TRACE_LOG_MAX_LENGTH;

  protected static final java.lang.String KEY_WORD_TRUNCATED;

  protected static final org.apache.hbase.thirdparty.com.google.gson.Gson GSON;

  protected final int maxRequestSize;

  protected final int warnResponseTime;

  protected final int warnResponseSize;

  protected final int minClientRequestTimeout;

  protected final org.apache.hadoop.hbase.Server server;

  protected final java.util.List<org.apache.hadoop.hbase.ipc.RpcServer$BlockingServiceAndInterface> services;

  protected final org.apache.hadoop.hbase.ipc.RpcScheduler scheduler;

  protected org.apache.hadoop.hbase.security.UserProvider userProvider;

  protected final org.apache.hadoop.hbase.io.ByteBufferPool reservoir;

  protected final int minSizeForReservoirUse;

  protected volatile boolean allowFallbackToSimpleAuth;

  protected static final int NIO_BUFFER_LIMIT;

  public org.apache.hadoop.hbase.ipc.RpcServer(org.apache.hadoop.hbase.Server, java.lang.String, java.util.List<org.apache.hadoop.hbase.ipc.RpcServer$BlockingServiceAndInterface>, java.net.InetSocketAddress, org.apache.hadoop.conf.Configuration, org.apache.hadoop.hbase.ipc.RpcScheduler, boolean) throws java.io.IOException;
    Code:
       0: aload_0
       1: invokespecial #3                  // Method java/lang/Object."<init>":()V
       4: aload_0
       5: new           #4                  // class java/util/concurrent/atomic/LongAdder
       8: dup
       9: invokespecial #5                  // Method java/util/concurrent/atomic/LongAdder."<init>":()V
      12: putfield      #6                  // Field callQueueSizeInBytes:Ljava/util/concurrent/atomic/LongAdder;
      15: aload_0
      16: iconst_1
      17: putfield      #7                  // Field running:Z
      20: aload_0
      21: iconst_0
      22: putfield      #8                  // Field started:Z
      25: aload_0
      26: aconst_null
      27: putfield      #9                  // Field authTokenSecretMgr:Lorg/apache/hadoop/hbase/security/token/AuthenticationTokenSecretManager;
      30: aload_0
      31: aconst_null
      32: putfield      #10                 // Field errorHandler:Lorg/apache/hadoop/hbase/ipc/HBaseRPCErrorHandler;
      35: iload         7
      37: ifeq          110
      40: aload         5
      42: ldc           #12                 // String hbase.ipc.server.reservoir.initial.buffer.size
      44: ldc           #13                 // int 65536
      46: invokevirtual #14                 // Method org/apache/hadoop/conf/Configuration.getInt:(Ljava/lang/String;I)I
      49: istore        8
      51: ldc           #15                 // int 2097152
      53: iload         8
      55: idiv
      56: istore        9
      58: aload         5
      60: ldc           #16                 // String hbase.ipc.server.reservoir.initial.max
      62: aload         5
      64: ldc           #18                 // String hbase.regionserver.handler.count
      66: bipush        30
      68: invokevirtual #14                 // Method org/apache/hadoop/conf/Configuration.getInt:(Ljava/lang/String;I)I
      71: iload         9
      73: imul
      74: iconst_2
      75: imul
      76: invokevirtual #14                 // Method org/apache/hadoop/conf/Configuration.getInt:(Ljava/lang/String;I)I
      79: istore        10
      81: aload_0
      82: new           #11                 // class org/apache/hadoop/hbase/io/ByteBufferPool
      85: dup
      86: iload         8
      88: iload         10
      90: invokespecial #19                 // Method org/apache/hadoop/hbase/io/ByteBufferPool."<init>":(II)V
      93: putfield      #20                 // Field reservoir:Lorg/apache/hadoop/hbase/io/ByteBufferPool;
      96: aload_0
      97: aload_0
      98: getfield      #20                 // Field reservoir:Lorg/apache/hadoop/hbase/io/ByteBufferPool;
     101: invokestatic  #21                 // Method getMinSizeForReservoirUse:(Lorg/apache/hadoop/hbase/io/ByteBufferPool;)I
     104: putfield      #22                 // Field minSizeForReservoirUse:I
     107: goto          121
     110: aload_0
     111: aconst_null
     112: putfield      #20                 // Field reservoir:Lorg/apache/hadoop/hbase/io/ByteBufferPool;
     115: aload_0
     116: ldc           #24                 // int 2147483647
     118: putfield      #22                 // Field minSizeForReservoirUse:I
     121: aload_0
     122: aload_1
     123: putfield      #25                 // Field server:Lorg/apache/hadoop/hbase/Server;
     126: aload_0
     127: aload_3
     128: putfield      #26                 // Field services:Ljava/util/List;
     131: aload_0
     132: aload         4
     134: putfield      #27                 // Field bindAddress:Ljava/net/InetSocketAddress;
     137: aload_0
     138: aload         5
     140: putfield      #28                 // Field conf:Lorg/apache/hadoop/conf/Configuration;
     143: aload_0
     144: aload_0
     145: getfield      #28                 // Field conf:Lorg/apache/hadoop/conf/Configuration;
     148: ldc           #29                 // String hbase.ipc.server.max.callqueue.size
     150: ldc2_w        #30                 // long 1073741824l
     153: invokevirtual #32                 // Method org/apache/hadoop/conf/Configuration.getLong:(Ljava/lang/String;J)J
     156: putfield      #33                 // Field maxQueueSizeInBytes:J
     159: aload_0
     160: aload         5
     162: ldc           #34                 // String hbase.ipc.warn.response.time
     164: sipush        10000
     167: invokevirtual #14                 // Method org/apache/hadoop/conf/Configuration.getInt:(Ljava/lang/String;I)I
     170: putfield      #35                 // Field warnResponseTime:I
     173: aload_0
     174: aload         5
     176: ldc           #36                 // String hbase.ipc.warn.response.size
     178: ldc           #37                 // int 104857600
     180: invokevirtual #14                 // Method org/apache/hadoop/conf/Configuration.getInt:(Ljava/lang/String;I)I
     183: putfield      #38                 // Field warnResponseSize:I
     186: aload_0
     187: aload         5
     189: ldc           #39                 // String hbase.ipc.min.client.request.timeout
     191: bipush        20
     193: invokevirtual #14                 // Method org/apache/hadoop/conf/Configuration.getInt:(Ljava/lang/String;I)I
     196: putfield      #40                 // Field minClientRequestTimeout:I
     199: aload_0
     200: aload         5
     202: ldc           #41                 // String hbase.ipc.max.request.size
     204: ldc           #42                 // int 268435456
     206: invokevirtual #14                 // Method org/apache/hadoop/conf/Configuration.getInt:(Ljava/lang/String;I)I
     209: putfield      #43                 // Field maxRequestSize:I
     212: aload_0
     213: new           #44                 // class org/apache/hadoop/hbase/ipc/MetricsHBaseServer
     216: dup
     217: aload_2
     218: new           #45                 // class org/apache/hadoop/hbase/ipc/MetricsHBaseServerWrapperImpl
     221: dup
     222: aload_0
     223: invokespecial #46                 // Method org/apache/hadoop/hbase/ipc/MetricsHBaseServerWrapperImpl."<init>":(Lorg/apache/hadoop/hbase/ipc/RpcServer;)V
     226: invokespecial #47                 // Method org/apache/hadoop/hbase/ipc/MetricsHBaseServer."<init>":(Ljava/lang/String;Lorg/apache/hadoop/hbase/ipc/MetricsHBaseServerWrapper;)V
     229: putfield      #48                 // Field metrics:Lorg/apache/hadoop/hbase/ipc/MetricsHBaseServer;
     232: aload_0
     233: aload         5
     235: ldc           #49                 // String hbase.ipc.server.tcpnodelay
     237: iconst_1
     238: invokevirtual #50                 // Method org/apache/hadoop/conf/Configuration.getBoolean:(Ljava/lang/String;Z)Z
     241: putfield      #51                 // Field tcpNoDelay:Z
     244: aload_0
     245: aload         5
     247: ldc           #52                 // String hbase.ipc.server.tcpkeepalive
     249: iconst_1
     250: invokevirtual #50                 // Method org/apache/hadoop/conf/Configuration.getBoolean:(Ljava/lang/String;Z)Z
     253: putfield      #53                 // Field tcpKeepAlive:Z
     256: aload_0
     257: new           #54                 // class org/apache/hadoop/hbase/ipc/CellBlockBuilder
     260: dup
     261: aload         5
     263: invokespecial #55                 // Method org/apache/hadoop/hbase/ipc/CellBlockBuilder."<init>":(Lorg/apache/hadoop/conf/Configuration;)V
     266: putfield      #56                 // Field cellBlockBuilder:Lorg/apache/hadoop/hbase/ipc/CellBlockBuilder;
     269: aload_0
     270: aload         5
     272: ldc           #57                 // String hadoop.security.authorization
     274: iconst_0
     275: invokevirtual #50                 // Method org/apache/hadoop/conf/Configuration.getBoolean:(Ljava/lang/String;Z)Z
     278: putfield      #58                 // Field authorize:Z
     281: aload_0
     282: aload         5
     284: invokestatic  #59                 // Method org/apache/hadoop/hbase/security/UserProvider.instantiate:(Lorg/apache/hadoop/conf/Configuration;)Lorg/apache/hadoop/hbase/security/UserProvider;
     287: putfield      #60                 // Field userProvider:Lorg/apache/hadoop/hbase/security/UserProvider;
     290: aload_0
     291: aload_0
     292: getfield      #60                 // Field userProvider:Lorg/apache/hadoop/hbase/security/UserProvider;
     295: invokevirtual #61                 // Method org/apache/hadoop/hbase/security/UserProvider.isHBaseSecurityEnabled:()Z
     298: putfield      #62                 // Field isSecurityEnabled:Z
     301: aload_0
     302: getfield      #62                 // Field isSecurityEnabled:Z
     305: ifeq          337
     308: aload_0
     309: aload         5
     311: ldc           #63                 // String hbase.rpc.protection
     313: getstatic     #64                 // Field org/apache/hadoop/hbase/security/SaslUtil$QualityOfProtection.AUTHENTICATION:Lorg/apache/hadoop/hbase/security/SaslUtil$QualityOfProtection;
     316: invokevirtual #65                 // Method org/apache/hadoop/hbase/security/SaslUtil$QualityOfProtection.name:()Ljava/lang/String;
     319: getstatic     #66                 // Field java/util/Locale.ROOT:Ljava/util/Locale;
     322: invokevirtual #67                 // Method java/lang/String.toLowerCase:(Ljava/util/Locale;)Ljava/lang/String;
     325: invokevirtual #68                 // Method org/apache/hadoop/conf/Configuration.get:(Ljava/lang/String;Ljava/lang/String;)Ljava/lang/String;
     328: invokestatic  #69                 // Method org/apache/hadoop/hbase/security/SaslUtil.initSaslProperties:(Ljava/lang/String;)Ljava/util/Map;
     331: putfield      #70                 // Field saslProps:Ljava/util/Map;
     334: goto          344
     337: aload_0
     338: invokestatic  #71                 // Method java/util/Collections.emptyMap:()Ljava/util/Map;
     341: putfield      #70                 // Field saslProps:Ljava/util/Map;
     344: aload_0
     345: aload         6
     347: putfield      #72                 // Field scheduler:Lorg/apache/hadoop/hbase/ipc/RpcScheduler;
     350: return

  static int getMinSizeForReservoirUse(org.apache.hadoop.hbase.io.ByteBufferPool);
    Code:
       0: aload_0
       1: invokevirtual #73                 // Method org/apache/hadoop/hbase/io/ByteBufferPool.getBufferSize:()I
       4: bipush        6
       6: idiv
       7: ireturn

  public void onConfigurationChange(org.apache.hadoop.conf.Configuration);
    Code:
       0: aload_0
       1: aload_1
       2: invokevirtual #74                 // Method initReconfigurable:(Lorg/apache/hadoop/conf/Configuration;)V
       5: aload_0
       6: getfield      #72                 // Field scheduler:Lorg/apache/hadoop/hbase/ipc/RpcScheduler;
       9: instanceof    #75                 // class org/apache/hadoop/hbase/conf/ConfigurationObserver
      12: ifeq          28
      15: aload_0
      16: getfield      #72                 // Field scheduler:Lorg/apache/hadoop/hbase/ipc/RpcScheduler;
      19: checkcast     #75                 // class org/apache/hadoop/hbase/conf/ConfigurationObserver
      22: aload_1
      23: invokeinterface #76,  2           // InterfaceMethod org/apache/hadoop/hbase/conf/ConfigurationObserver.onConfigurationChange:(Lorg/apache/hadoop/conf/Configuration;)V
      28: return

  protected void initReconfigurable(org.apache.hadoop.conf.Configuration);
    Code:
       0: aload_0
       1: aload_1
       2: ldc           #77                 // String hbase.ipc.server.fallback-to-simple-auth-allowed
       4: iconst_0
       5: invokevirtual #50                 // Method org/apache/hadoop/conf/Configuration.getBoolean:(Ljava/lang/String;Z)Z
       8: putfield      #78                 // Field allowFallbackToSimpleAuth:Z
      11: aload_0
      12: getfield      #62                 // Field isSecurityEnabled:Z
      15: ifeq          105
      18: aload_0
      19: getfield      #78                 // Field allowFallbackToSimpleAuth:Z
      22: ifeq          105
      25: getstatic     #79                 // Field LOG:Lorg/slf4j/Logger;
      28: ldc           #80                 // String ********* WARNING! *********
      30: invokeinterface #81,  2           // InterfaceMethod org/slf4j/Logger.warn:(Ljava/lang/String;)V
      35: getstatic     #79                 // Field LOG:Lorg/slf4j/Logger;
      38: ldc           #82                 // String This server is configured to allow connections from INSECURE clients
      40: invokeinterface #81,  2           // InterfaceMethod org/slf4j/Logger.warn:(Ljava/lang/String;)V
      45: getstatic     #79                 // Field LOG:Lorg/slf4j/Logger;
      48: ldc           #83                 // String (hbase.ipc.server.fallback-to-simple-auth-allowed = true).
      50: invokeinterface #81,  2           // InterfaceMethod org/slf4j/Logger.warn:(Ljava/lang/String;)V
      55: getstatic     #79                 // Field LOG:Lorg/slf4j/Logger;
      58: ldc           #84                 // String While this option is enabled, client identities cannot be secured, and user
      60: invokeinterface #81,  2           // InterfaceMethod org/slf4j/Logger.warn:(Ljava/lang/String;)V
      65: getstatic     #79                 // Field LOG:Lorg/slf4j/Logger;
      68: ldc           #85                 // String impersonation is possible!
      70: invokeinterface #81,  2           // InterfaceMethod org/slf4j/Logger.warn:(Ljava/lang/String;)V
      75: getstatic     #79                 // Field LOG:Lorg/slf4j/Logger;
      78: ldc           #86                 // String For secure operation, please disable SIMPLE authentication as soon as possible,
      80: invokeinterface #81,  2           // InterfaceMethod org/slf4j/Logger.warn:(Ljava/lang/String;)V
      85: getstatic     #79                 // Field LOG:Lorg/slf4j/Logger;
      88: ldc           #87                 // String by setting hbase.ipc.server.fallback-to-simple-auth-allowed = false in hbase-site.xml
      90: invokeinterface #81,  2           // InterfaceMethod org/slf4j/Logger.warn:(Ljava/lang/String;)V
      95: getstatic     #79                 // Field LOG:Lorg/slf4j/Logger;
      98: ldc           #88                 // String ****************************
     100: invokeinterface #81,  2           // InterfaceMethod org/slf4j/Logger.warn:(Ljava/lang/String;)V
     105: return

  org.apache.hadoop.conf.Configuration getConf();
    Code:
       0: aload_0
       1: getfield      #28                 // Field conf:Lorg/apache/hadoop/conf/Configuration;
       4: areturn

  public boolean isStarted();
    Code:
       0: aload_0
       1: getfield      #8                  // Field started:Z
       4: ireturn

  public void refreshAuthManager(org.apache.hadoop.security.authorize.PolicyProvider);
    Code:
       0: aload_0
       1: getfield      #89                 // Field authManager:Lorg/apache/hadoop/security/authorize/ServiceAuthorizationManager;
       4: dup
       5: astore_2
       6: monitorenter
       7: aload_0
       8: getfield      #89                 // Field authManager:Lorg/apache/hadoop/security/authorize/ServiceAuthorizationManager;
      11: aload_0
      12: getfield      #28                 // Field conf:Lorg/apache/hadoop/conf/Configuration;
      15: aload_1
      16: invokevirtual #90                 // Method org/apache/hadoop/security/authorize/ServiceAuthorizationManager.refresh:(Lorg/apache/hadoop/conf/Configuration;Lorg/apache/hadoop/security/authorize/PolicyProvider;)V
      19: aload_2
      20: monitorexit
      21: goto          29
      24: astore_3
      25: aload_2
      26: monitorexit
      27: aload_3
      28: athrow
      29: return
    Exception table:
       from    to  target type
           7    21    24   any
          24    27    24   any

  protected org.apache.hadoop.hbase.security.token.AuthenticationTokenSecretManager createSecretManager();
    Code:
       0: aload_0
       1: getfield      #62                 // Field isSecurityEnabled:Z
       4: ifne          9
       7: aconst_null
       8: areturn
       9: aload_0
      10: getfield      #25                 // Field server:Lorg/apache/hadoop/hbase/Server;
      13: ifnonnull     18
      16: aconst_null
      17: areturn
      18: aload_0
      19: getfield      #25                 // Field server:Lorg/apache/hadoop/hbase/Server;
      22: invokeinterface #91,  1           // InterfaceMethod org/apache/hadoop/hbase/Server.getConfiguration:()Lorg/apache/hadoop/conf/Configuration;
      27: astore_1
      28: aload_1
      29: ldc           #92                 // String hbase.auth.key.update.interval
      31: ldc2_w        #93                 // long 86400000l
      34: invokevirtual #32                 // Method org/apache/hadoop/conf/Configuration.getLong:(Ljava/lang/String;J)J
      37: lstore_2
      38: aload_1
      39: ldc           #95                 // String hbase.auth.token.max.lifetime
      41: ldc2_w        #96                 // long 604800000l
      44: invokevirtual #32                 // Method org/apache/hadoop/conf/Configuration.getLong:(Ljava/lang/String;J)J
      47: lstore        4
      49: new           #98                 // class org/apache/hadoop/hbase/security/token/AuthenticationTokenSecretManager
      52: dup
      53: aload_1
      54: aload_0
      55: getfield      #25                 // Field server:Lorg/apache/hadoop/hbase/Server;
      58: invokeinterface #99,  1           // InterfaceMethod org/apache/hadoop/hbase/Server.getZooKeeper:()Lorg/apache/hadoop/hbase/zookeeper/ZKWatcher;
      63: aload_0
      64: getfield      #25                 // Field server:Lorg/apache/hadoop/hbase/Server;
      67: invokeinterface #100,  1          // InterfaceMethod org/apache/hadoop/hbase/Server.getServerName:()Lorg/apache/hadoop/hbase/ServerName;
      72: invokevirtual #101                // Method org/apache/hadoop/hbase/ServerName.toString:()Ljava/lang/String;
      75: lload_2
      76: lload         4
      78: invokespecial #102                // Method org/apache/hadoop/hbase/security/token/AuthenticationTokenSecretManager."<init>":(Lorg/apache/hadoop/conf/Configuration;Lorg/apache/hadoop/hbase/zookeeper/ZKWatcher;Ljava/lang/String;JJ)V
      81: areturn

  public org.apache.hadoop.security.token.SecretManager<? extends org.apache.hadoop.security.token.TokenIdentifier> getSecretManager();
    Code:
       0: aload_0
       1: getfield      #103                // Field secretManager:Lorg/apache/hadoop/security/token/SecretManager;
       4: areturn

  public void setSecretManager(org.apache.hadoop.security.token.SecretManager<? extends org.apache.hadoop.security.token.TokenIdentifier>);
    Code:
       0: aload_0
       1: aload_1
       2: putfield      #103                // Field secretManager:Lorg/apache/hadoop/security/token/SecretManager;
       5: return

  public org.apache.hadoop.hbase.util.Pair<org.apache.hbase.thirdparty.com.google.protobuf.Message, org.apache.hadoop.hbase.CellScanner> call(org.apache.hadoop.hbase.ipc.RpcCall, org.apache.hadoop.hbase.monitoring.MonitoredRPCHandler) throws java.io.IOException;
    Code:
       0: aload_1
       1: invokeinterface #104,  1          // InterfaceMethod org/apache/hadoop/hbase/ipc/RpcCall.getMethod:()Lorg/apache/hbase/thirdparty/com/google/protobuf/Descriptors$MethodDescriptor;
       6: astore_3
       7: aload_1
       8: invokeinterface #105,  1          // InterfaceMethod org/apache/hadoop/hbase/ipc/RpcCall.getParam:()Lorg/apache/hbase/thirdparty/com/google/protobuf/Message;
      13: astore        4
      15: aload_2
      16: aload_3
      17: invokevirtual #106                // Method org/apache/hbase/thirdparty/com/google/protobuf/Descriptors$MethodDescriptor.getName:()Ljava/lang/String;
      20: iconst_1
      21: anewarray     #107                // class java/lang/Object
      24: dup
      25: iconst_0
      26: aload         4
      28: aastore
      29: aload_1
      30: invokeinterface #108,  1          // InterfaceMethod org/apache/hadoop/hbase/ipc/RpcCall.getReceiveTime:()J
      35: invokeinterface #109,  5          // InterfaceMethod org/apache/hadoop/hbase/monitoring/MonitoredRPCHandler.setRPC:(Ljava/lang/String;[Ljava/lang/Object;J)V
      40: aload_2
      41: aload         4
      43: invokeinterface #110,  2          // InterfaceMethod org/apache/hadoop/hbase/monitoring/MonitoredRPCHandler.setRPCPacket:(Lorg/apache/hbase/thirdparty/com/google/protobuf/Message;)V
      48: aload_2
      49: ldc           #111                // String Servicing call
      51: invokeinterface #112,  2          // InterfaceMethod org/apache/hadoop/hbase/monitoring/MonitoredRPCHandler.resume:(Ljava/lang/String;)V
      56: new           #113                // class org/apache/hadoop/hbase/ipc/HBaseRpcControllerImpl
      59: dup
      60: aload_1
      61: invokeinterface #114,  1          // InterfaceMethod org/apache/hadoop/hbase/ipc/RpcCall.getCellScanner:()Lorg/apache/hadoop/hbase/CellScanner;
      66: invokespecial #115                // Method org/apache/hadoop/hbase/ipc/HBaseRpcControllerImpl."<init>":(Lorg/apache/hadoop/hbase/CellScanner;)V
      69: astore        5
      71: aload         5
      73: aload_1
      74: invokeinterface #116,  1          // InterfaceMethod org/apache/hadoop/hbase/ipc/RpcCall.getTimeout:()I
      79: invokeinterface #117,  2          // InterfaceMethod org/apache/hadoop/hbase/ipc/HBaseRpcController.setCallTimeout:(I)V
      84: aload_1
      85: invokeinterface #118,  1          // InterfaceMethod org/apache/hadoop/hbase/ipc/RpcCall.getService:()Lorg/apache/hbase/thirdparty/com/google/protobuf/BlockingService;
      90: aload_3
      91: aload         5
      93: aload         4
      95: invokeinterface #119,  4          // InterfaceMethod org/apache/hbase/thirdparty/com/google/protobuf/BlockingService.callBlockingMethod:(Lorg/apache/hbase/thirdparty/com/google/protobuf/Descriptors$MethodDescriptor;Lorg/apache/hbase/thirdparty/com/google/protobuf/RpcController;Lorg/apache/hbase/thirdparty/com/google/protobuf/Message;)Lorg/apache/hbase/thirdparty/com/google/protobuf/Message;
     100: astore        6
     102: aload_1
     103: invokeinterface #108,  1          // InterfaceMethod org/apache/hadoop/hbase/ipc/RpcCall.getReceiveTime:()J
     108: lstore        7
     110: aload_1
     111: invokeinterface #120,  1          // InterfaceMethod org/apache/hadoop/hbase/ipc/RpcCall.getStartTime:()J
     116: lstore        9
     118: invokestatic  #121                // Method java/lang/System.currentTimeMillis:()J
     121: lstore        11
     123: lload         11
     125: lload         9
     127: lsub
     128: l2i
     129: istore        13
     131: lload         9
     133: lload         7
     135: lsub
     136: l2i
     137: istore        14
     139: lload         11
     141: lload         7
     143: lsub
     144: l2i
     145: istore        15
     147: getstatic     #79                 // Field LOG:Lorg/slf4j/Logger;
     150: invokeinterface #122,  1          // InterfaceMethod org/slf4j/Logger.isTraceEnabled:()Z
     155: ifeq          234
     158: getstatic     #79                 // Field LOG:Lorg/slf4j/Logger;
     161: new           #123                // class java/lang/StringBuilder
     164: dup
     165: invokespecial #124                // Method java/lang/StringBuilder."<init>":()V
     168: getstatic     #125                // Field CurCall:Ljava/lang/ThreadLocal;
     171: invokevirtual #126                // Method java/lang/ThreadLocal.get:()Ljava/lang/Object;
     174: checkcast     #127                // class org/apache/hadoop/hbase/ipc/RpcCall
     177: invokevirtual #128                // Method java/lang/Object.toString:()Ljava/lang/String;
     180: invokevirtual #129                // Method java/lang/StringBuilder.append:(Ljava/lang/String;)Ljava/lang/StringBuilder;
     183: ldc           #130                // String , response
     185: invokevirtual #129                // Method java/lang/StringBuilder.append:(Ljava/lang/String;)Ljava/lang/StringBuilder;
     188: aload         6
     190: invokestatic  #131                // Method org/apache/hbase/thirdparty/com/google/protobuf/TextFormat.shortDebugString:(Lorg/apache/hbase/thirdparty/com/google/protobuf/MessageOrBuilder;)Ljava/lang/String;
     193: invokevirtual #129                // Method java/lang/StringBuilder.append:(Ljava/lang/String;)Ljava/lang/StringBuilder;
     196: ldc           #132                // String  queueTime:
     198: invokevirtual #129                // Method java/lang/StringBuilder.append:(Ljava/lang/String;)Ljava/lang/StringBuilder;
     201: iload         14
     203: invokevirtual #133                // Method java/lang/StringBuilder.append:(I)Ljava/lang/StringBuilder;
     206: ldc           #134                // String  processingTime:
     208: invokevirtual #129                // Method java/lang/StringBuilder.append:(Ljava/lang/String;)Ljava/lang/StringBuilder;
     211: iload         13
     213: invokevirtual #133                // Method java/lang/StringBuilder.append:(I)Ljava/lang/StringBuilder;
     216: ldc           #135                // String  totalTime:
     218: invokevirtual #129                // Method java/lang/StringBuilder.append:(Ljava/lang/String;)Ljava/lang/StringBuilder;
     221: iload         15
     223: invokevirtual #133                // Method java/lang/StringBuilder.append:(I)Ljava/lang/StringBuilder;
     226: invokevirtual #136                // Method java/lang/StringBuilder.toString:()Ljava/lang/String;
     229: invokeinterface #137,  2          // InterfaceMethod org/slf4j/Logger.trace:(Ljava/lang/String;)V
     234: aload_1
     235: invokeinterface #138,  1          // InterfaceMethod org/apache/hadoop/hbase/ipc/RpcCall.getSize:()J
     240: lstore        16
     242: aload         6
     244: invokeinterface #139,  1          // InterfaceMethod org/apache/hbase/thirdparty/com/google/protobuf/Message.getSerializedSize:()I
     249: i2l
     250: lstore        18
     252: aload_1
     253: invokeinterface #140,  1          // InterfaceMethod org/apache/hadoop/hbase/ipc/RpcCall.isClientCellBlockSupported:()Z
     258: ifeq          272
     261: lload         18
     263: aload_1
     264: invokeinterface #141,  1          // InterfaceMethod org/apache/hadoop/hbase/ipc/RpcCall.getResponseCellSize:()J
     269: ladd
     270: lstore        18
     272: aload_0
     273: getfield      #48                 // Field metrics:Lorg/apache/hadoop/hbase/ipc/MetricsHBaseServer;
     276: iload         14
     278: invokevirtual #142                // Method org/apache/hadoop/hbase/ipc/MetricsHBaseServer.dequeuedCall:(I)V
     281: aload_0
     282: getfield      #48                 // Field metrics:Lorg/apache/hadoop/hbase/ipc/MetricsHBaseServer;
     285: iload         13
     287: invokevirtual #143                // Method org/apache/hadoop/hbase/ipc/MetricsHBaseServer.processedCall:(I)V
     290: aload_0
     291: getfield      #48                 // Field metrics:Lorg/apache/hadoop/hbase/ipc/MetricsHBaseServer;
     294: iload         15
     296: invokevirtual #144                // Method org/apache/hadoop/hbase/ipc/MetricsHBaseServer.totalCall:(I)V
     299: aload_0
     300: getfield      #48                 // Field metrics:Lorg/apache/hadoop/hbase/ipc/MetricsHBaseServer;
     303: lload         16
     305: invokevirtual #145                // Method org/apache/hadoop/hbase/ipc/MetricsHBaseServer.receivedRequest:(J)V
     308: aload_0
     309: getfield      #48                 // Field metrics:Lorg/apache/hadoop/hbase/ipc/MetricsHBaseServer;
     312: lload         18
     314: invokevirtual #146                // Method org/apache/hadoop/hbase/ipc/MetricsHBaseServer.sentResponse:(J)V
     317: iload         13
     319: aload_0
     320: getfield      #35                 // Field warnResponseTime:I
     323: if_icmple     338
     326: aload_0
     327: getfield      #35                 // Field warnResponseTime:I
     330: iconst_m1
     331: if_icmple     338
     334: iconst_1
     335: goto          339
     338: iconst_0
     339: istore        20
     341: lload         18
     343: aload_0
     344: getfield      #38                 // Field warnResponseSize:I
     347: i2l
     348: lcmp
     349: ifle          364
     352: aload_0
     353: getfield      #38                 // Field warnResponseSize:I
     356: iconst_m1
     357: if_icmple     364
     360: iconst_1
     361: goto          365
     364: iconst_0
     365: istore        21
     367: iload         20
     369: ifne          377
     372: iload         21
     374: ifeq          451
     377: aload_0
     378: aload         4
     380: aload_3
     381: invokevirtual #106                // Method org/apache/hbase/thirdparty/com/google/protobuf/Descriptors$MethodDescriptor.getName:()Ljava/lang/String;
     384: new           #123                // class java/lang/StringBuilder
     387: dup
     388: invokespecial #124                // Method java/lang/StringBuilder."<init>":()V
     391: aload_3
     392: invokevirtual #106                // Method org/apache/hbase/thirdparty/com/google/protobuf/Descriptors$MethodDescriptor.getName:()Ljava/lang/String;
     395: invokevirtual #129                // Method java/lang/StringBuilder.append:(Ljava/lang/String;)Ljava/lang/StringBuilder;
     398: ldc           #147                // String (
     400: invokevirtual #129                // Method java/lang/StringBuilder.append:(Ljava/lang/String;)Ljava/lang/StringBuilder;
     403: aload         4
     405: invokevirtual #148                // Method java/lang/Object.getClass:()Ljava/lang/Class;
     408: invokevirtual #149                // Method java/lang/Class.getName:()Ljava/lang/String;
     411: invokevirtual #129                // Method java/lang/StringBuilder.append:(Ljava/lang/String;)Ljava/lang/StringBuilder;
     414: ldc           #150                // String )
     416: invokevirtual #129                // Method java/lang/StringBuilder.append:(Ljava/lang/String;)Ljava/lang/StringBuilder;
     419: invokevirtual #136                // Method java/lang/StringBuilder.toString:()Ljava/lang/String;
     422: iload         21
     424: ifeq          432
     427: ldc           #151                // String TooLarge
     429: goto          434
     432: ldc           #152                // String TooSlow
     434: aload_2
     435: invokeinterface #153,  1          // InterfaceMethod org/apache/hadoop/hbase/monitoring/MonitoredRPCHandler.getClient:()Ljava/lang/String;
     440: lload         9
     442: iload         13
     444: iload         14
     446: lload         18
     448: invokevirtual #154                // Method logResponse:(Lorg/apache/hbase/thirdparty/com/google/protobuf/Message;Ljava/lang/String;Ljava/lang/String;Ljava/lang/String;Ljava/lang/String;JIIJ)V
     451: new           #155                // class org/apache/hadoop/hbase/util/Pair
     454: dup
     455: aload         6
     457: aload         5
     459: invokeinterface #156,  1          // InterfaceMethod org/apache/hadoop/hbase/ipc/HBaseRpcController.cellScanner:()Lorg/apache/hadoop/hbase/CellScanner;
     464: invokespecial #157                // Method org/apache/hadoop/hbase/util/Pair."<init>":(Ljava/lang/Object;Ljava/lang/Object;)V
     467: areturn
     468: astore_3
     469: aload_3
     470: instanceof    #159                // class org/apache/hbase/thirdparty/com/google/protobuf/ServiceException
     473: ifeq          502
     476: aload_3
     477: invokevirtual #160                // Method java/lang/Throwable.getCause:()Ljava/lang/Throwable;
     480: ifnonnull     497
     483: getstatic     #79                 // Field LOG:Lorg/slf4j/Logger;
     486: ldc           #161                // String Caught a ServiceException with null cause
     488: aload_3
     489: invokeinterface #162,  3          // InterfaceMethod org/slf4j/Logger.debug:(Ljava/lang/String;Ljava/lang/Throwable;)V
     494: goto          502
     497: aload_3
     498: invokevirtual #160                // Method java/lang/Throwable.getCause:()Ljava/lang/Throwable;
     501: astore_3
     502: aload_0
     503: getfield      #48                 // Field metrics:Lorg/apache/hadoop/hbase/ipc/MetricsHBaseServer;
     506: aload_3
     507: invokevirtual #163                // Method org/apache/hadoop/hbase/ipc/MetricsHBaseServer.exception:(Ljava/lang/Throwable;)V
     510: aload_3
     511: instanceof    #164                // class java/lang/LinkageError
     514: ifeq          526
     517: new           #165                // class org/apache/hadoop/hbase/DoNotRetryIOException
     520: dup
     521: aload_3
     522: invokespecial #166                // Method org/apache/hadoop/hbase/DoNotRetryIOException."<init>":(Ljava/lang/Throwable;)V
     525: athrow
     526: aload_3
     527: instanceof    #167                // class java/io/IOException
     530: ifeq          538
     533: aload_3
     534: checkcast     #167                // class java/io/IOException
     537: athrow
     538: getstatic     #79                 // Field LOG:Lorg/slf4j/Logger;
     541: ldc           #168                // String Unexpected throwable object
     543: aload_3
     544: invokeinterface #169,  3          // InterfaceMethod org/slf4j/Logger.error:(Ljava/lang/String;Ljava/lang/Throwable;)V
     549: new           #167                // class java/io/IOException
     552: dup
     553: aload_3
     554: invokevirtual #170                // Method java/lang/Throwable.getMessage:()Ljava/lang/String;
     557: aload_3
     558: invokespecial #171                // Method java/io/IOException."<init>":(Ljava/lang/String;Ljava/lang/Throwable;)V
     561: athrow
    Exception table:
       from    to  target type
           0   467   468   Class java/lang/Throwable

  void logResponse(org.apache.hbase.thirdparty.com.google.protobuf.Message, java.lang.String, java.lang.String, java.lang.String, java.lang.String, long, int, int, long) throws java.io.IOException;
    Code:
       0: new           #172                // class java/util/HashMap
       3: dup
       4: invokespecial #173                // Method java/util/HashMap."<init>":()V
       7: astore        12
       9: aload         12
      11: ldc           #174                // String starttimems
      13: lload         6
      15: invokestatic  #175                // Method java/lang/Long.valueOf:(J)Ljava/lang/Long;
      18: invokeinterface #176,  3          // InterfaceMethod java/util/Map.put:(Ljava/lang/Object;Ljava/lang/Object;)Ljava/lang/Object;
      23: pop
      24: aload         12
      26: ldc           #177                // String processingtimems
      28: iload         8
      30: invokestatic  #178                // Method java/lang/Integer.valueOf:(I)Ljava/lang/Integer;
      33: invokeinterface #176,  3          // InterfaceMethod java/util/Map.put:(Ljava/lang/Object;Ljava/lang/Object;)Ljava/lang/Object;
      38: pop
      39: aload         12
      41: ldc           #179                // String queuetimems
      43: iload         9
      45: invokestatic  #178                // Method java/lang/Integer.valueOf:(I)Ljava/lang/Integer;
      48: invokeinterface #176,  3          // InterfaceMethod java/util/Map.put:(Ljava/lang/Object;Ljava/lang/Object;)Ljava/lang/Object;
      53: pop
      54: aload         12
      56: ldc           #180                // String responsesize
      58: lload         10
      60: invokestatic  #175                // Method java/lang/Long.valueOf:(J)Ljava/lang/Long;
      63: invokeinterface #176,  3          // InterfaceMethod java/util/Map.put:(Ljava/lang/Object;Ljava/lang/Object;)Ljava/lang/Object;
      68: pop
      69: aload         12
      71: ldc           #181                // String client
      73: aload         5
      75: invokeinterface #176,  3          // InterfaceMethod java/util/Map.put:(Ljava/lang/Object;Ljava/lang/Object;)Ljava/lang/Object;
      80: pop
      81: aload         12
      83: ldc           #182                // String class
      85: aload_0
      86: getfield      #25                 // Field server:Lorg/apache/hadoop/hbase/Server;
      89: ifnonnull     97
      92: ldc           #183                // String
      94: goto          107
      97: aload_0
      98: getfield      #25                 // Field server:Lorg/apache/hadoop/hbase/Server;
     101: invokevirtual #148                // Method java/lang/Object.getClass:()Ljava/lang/Class;
     104: invokevirtual #184                // Method java/lang/Class.getSimpleName:()Ljava/lang/String;
     107: invokeinterface #176,  3          // InterfaceMethod java/util/Map.put:(Ljava/lang/Object;Ljava/lang/Object;)Ljava/lang/Object;
     112: pop
     113: aload         12
     115: ldc           #185                // String method
     117: aload_2
     118: invokeinterface #176,  3          // InterfaceMethod java/util/Map.put:(Ljava/lang/Object;Ljava/lang/Object;)Ljava/lang/Object;
     123: pop
     124: aload         12
     126: ldc           #186                // String call
     128: aload_3
     129: invokeinterface #176,  3          // InterfaceMethod java/util/Map.put:(Ljava/lang/Object;Ljava/lang/Object;)Ljava/lang/Object;
     134: pop
     135: aload_1
     136: invokestatic  #187                // Method org/apache/hadoop/hbase/shaded/protobuf/ProtobufUtil.getShortTextFormat:(Lorg/apache/hbase/thirdparty/com/google/protobuf/Message;)Ljava/lang/String;
     139: astore        13
     141: aload         13
     143: invokevirtual #188                // Method java/lang/String.length:()I
     146: sipush        150
     149: if_icmple     160
     152: aload_0
     153: aload         13
     155: invokevirtual #189                // Method truncateTraceLog:(Ljava/lang/String;)Ljava/lang/String;
     158: astore        13
     160: aload         12
     162: ldc           #190                // String param
     164: aload         13
     166: invokeinterface #176,  3          // InterfaceMethod java/util/Map.put:(Ljava/lang/Object;Ljava/lang/Object;)Ljava/lang/Object;
     171: pop
     172: aload_1
     173: instanceof    #191                // class org/apache/hadoop/hbase/shaded/protobuf/generated/ClientProtos$ScanRequest
     176: ifeq          235
     179: aload_0
     180: getfield      #192                // Field rsRpcServices:Lorg/apache/hadoop/hbase/regionserver/RSRpcServices;
     183: ifnull        235
     186: aload_1
     187: checkcast     #191                // class org/apache/hadoop/hbase/shaded/protobuf/generated/ClientProtos$ScanRequest
     190: astore        14
     192: aload         14
     194: invokevirtual #193                // Method org/apache/hadoop/hbase/shaded/protobuf/generated/ClientProtos$ScanRequest.hasScannerId:()Z
     197: ifeq          235
     200: aload         14
     202: invokevirtual #194                // Method org/apache/hadoop/hbase/shaded/protobuf/generated/ClientProtos$ScanRequest.getScannerId:()J
     205: lstore        15
     207: aload_0
     208: getfield      #192                // Field rsRpcServices:Lorg/apache/hadoop/hbase/regionserver/RSRpcServices;
     211: lload         15
     213: invokevirtual #195                // Method org/apache/hadoop/hbase/regionserver/RSRpcServices.getScanDetailsWithId:(J)Ljava/lang/String;
     216: astore        17
     218: aload         17
     220: ifnull        235
     223: aload         12
     225: ldc           #196                // String scandetails
     227: aload         17
     229: invokeinterface #176,  3          // InterfaceMethod java/util/Map.put:(Ljava/lang/Object;Ljava/lang/Object;)Ljava/lang/Object;
     234: pop
     235: getstatic     #79                 // Field LOG:Lorg/slf4j/Logger;
     238: new           #123                // class java/lang/StringBuilder
     241: dup
     242: invokespecial #124                // Method java/lang/StringBuilder."<init>":()V
     245: ldc           #197                // String (response
     247: invokevirtual #129                // Method java/lang/StringBuilder.append:(Ljava/lang/String;)Ljava/lang/StringBuilder;
     250: aload         4
     252: invokevirtual #129                // Method java/lang/StringBuilder.append:(Ljava/lang/String;)Ljava/lang/StringBuilder;
     255: ldc           #198                // String ):
     257: invokevirtual #129                // Method java/lang/StringBuilder.append:(Ljava/lang/String;)Ljava/lang/StringBuilder;
     260: getstatic     #199                // Field GSON:Lorg/apache/hbase/thirdparty/com/google/gson/Gson;
     263: aload         12
     265: invokevirtual #200                // Method org/apache/hbase/thirdparty/com/google/gson/Gson.toJson:(Ljava/lang/Object;)Ljava/lang/String;
     268: invokevirtual #129                // Method java/lang/StringBuilder.append:(Ljava/lang/String;)Ljava/lang/StringBuilder;
     271: invokevirtual #136                // Method java/lang/StringBuilder.toString:()Ljava/lang/String;
     274: invokeinterface #81,  2           // InterfaceMethod org/slf4j/Logger.warn:(Ljava/lang/String;)V
     279: return

  java.lang.String truncateTraceLog(java.lang.String);
    Code:
       0: getstatic     #79                 // Field LOG:Lorg/slf4j/Logger;
       3: invokeinterface #122,  1          // InterfaceMethod org/slf4j/Logger.isTraceEnabled:()Z
       8: ifeq          83
      11: aload_0
      12: invokevirtual #201                // Method getConf:()Lorg/apache/hadoop/conf/Configuration;
      15: ldc           #202                // String hbase.ipc.trace.log.max.length
      17: sipush        1000
      20: invokevirtual #14                 // Method org/apache/hadoop/conf/Configuration.getInt:(Ljava/lang/String;I)I
      23: istore_2
      24: aload_1
      25: invokevirtual #188                // Method java/lang/String.length:()I
      28: iload_2
      29: if_icmpge     39
      32: aload_1
      33: invokevirtual #188                // Method java/lang/String.length:()I
      36: goto          40
      39: iload_2
      40: istore_3
      41: iload_3
      42: aload_1
      43: invokevirtual #188                // Method java/lang/String.length:()I
      46: if_icmpne     54
      49: ldc           #183                // String
      51: goto          56
      54: ldc           #203                // String  <TRUNCATED>
      56: astore        4
      58: new           #123                // class java/lang/StringBuilder
      61: dup
      62: invokespecial #124                // Method java/lang/StringBuilder."<init>":()V
      65: aload_1
      66: iconst_0
      67: iload_3
      68: invokevirtual #204                // Method java/lang/String.subSequence:(II)Ljava/lang/CharSequence;
      71: invokevirtual #205                // Method java/lang/StringBuilder.append:(Ljava/lang/Object;)Ljava/lang/StringBuilder;
      74: aload         4
      76: invokevirtual #129                // Method java/lang/StringBuilder.append:(Ljava/lang/String;)Ljava/lang/StringBuilder;
      79: invokevirtual #136                // Method java/lang/StringBuilder.toString:()Ljava/lang/String;
      82: areturn
      83: new           #123                // class java/lang/StringBuilder
      86: dup
      87: invokespecial #124                // Method java/lang/StringBuilder."<init>":()V
      90: aload_1
      91: iconst_0
      92: sipush        150
      95: invokevirtual #204                // Method java/lang/String.subSequence:(II)Ljava/lang/CharSequence;
      98: invokevirtual #205                // Method java/lang/StringBuilder.append:(Ljava/lang/Object;)Ljava/lang/StringBuilder;
     101: ldc           #203                // String  <TRUNCATED>
     103: invokevirtual #129                // Method java/lang/StringBuilder.append:(Ljava/lang/String;)Ljava/lang/StringBuilder;
     106: invokevirtual #136                // Method java/lang/StringBuilder.toString:()Ljava/lang/String;
     109: areturn

  public void setErrorHandler(org.apache.hadoop.hbase.ipc.HBaseRPCErrorHandler);
    Code:
       0: aload_0
       1: aload_1
       2: putfield      #10                 // Field errorHandler:Lorg/apache/hadoop/hbase/ipc/HBaseRPCErrorHandler;
       5: return

  public org.apache.hadoop.hbase.ipc.HBaseRPCErrorHandler getErrorHandler();
    Code:
       0: aload_0
       1: getfield      #10                 // Field errorHandler:Lorg/apache/hadoop/hbase/ipc/HBaseRPCErrorHandler;
       4: areturn

  public org.apache.hadoop.hbase.ipc.MetricsHBaseServer getMetrics();
    Code:
       0: aload_0
       1: getfield      #48                 // Field metrics:Lorg/apache/hadoop/hbase/ipc/MetricsHBaseServer;
       4: areturn

  public void addCallSize(long);
    Code:
       0: aload_0
       1: getfield      #6                  // Field callQueueSizeInBytes:Ljava/util/concurrent/atomic/LongAdder;
       4: lload_1
       5: invokevirtual #206                // Method java/util/concurrent/atomic/LongAdder.add:(J)V
       8: return

  public void authorize(org.apache.hadoop.security.UserGroupInformation, org.apache.hadoop.hbase.shaded.protobuf.generated.RPCProtos$ConnectionHeader, java.net.InetAddress) throws org.apache.hadoop.security.authorize.AuthorizationException;
    Code:
       0: aload_0
       1: getfield      #58                 // Field authorize:Z
       4: ifeq          57
       7: aload_0
       8: getfield      #26                 // Field services:Ljava/util/List;
      11: aload_2
      12: invokevirtual #207                // Method org/apache/hadoop/hbase/shaded/protobuf/generated/RPCProtos$ConnectionHeader.getServiceName:()Ljava/lang/String;
      15: invokestatic  #208                // Method getServiceInterface:(Ljava/util/List;Ljava/lang/String;)Ljava/lang/Class;
      18: astore        4
      20: aload_0
      21: getfield      #89                 // Field authManager:Lorg/apache/hadoop/security/authorize/ServiceAuthorizationManager;
      24: dup
      25: astore        5
      27: monitorenter
      28: aload_0
      29: getfield      #89                 // Field authManager:Lorg/apache/hadoop/security/authorize/ServiceAuthorizationManager;
      32: aload_1
      33: aload         4
      35: aload_0
      36: invokevirtual #201                // Method getConf:()Lorg/apache/hadoop/conf/Configuration;
      39: aload_3
      40: invokevirtual #209                // Method org/apache/hadoop/security/authorize/ServiceAuthorizationManager.authorize:(Lorg/apache/hadoop/security/UserGroupInformation;Ljava/lang/Class;Lorg/apache/hadoop/conf/Configuration;Ljava/net/InetAddress;)V
      43: aload         5
      45: monitorexit
      46: goto          57
      49: astore        6
      51: aload         5
      53: monitorexit
      54: aload         6
      56: athrow
      57: return
    Exception table:
       from    to  target type
          28    46    49   any
          49    54    49   any

  protected int channelRead(java.nio.channels.ReadableByteChannel, java.nio.ByteBuffer) throws java.io.IOException;
    Code:
       0: aload_2
       1: invokevirtual #210                // Method java/nio/ByteBuffer.remaining:()I
       4: ldc           #13                 // int 65536
       6: if_icmpgt     19
       9: aload_1
      10: aload_2
      11: invokeinterface #211,  2          // InterfaceMethod java/nio/channels/ReadableByteChannel.read:(Ljava/nio/ByteBuffer;)I
      16: goto          25
      19: aload_1
      20: aconst_null
      21: aload_2
      22: invokestatic  #212                // Method channelIO:(Ljava/nio/channels/ReadableByteChannel;Ljava/nio/channels/WritableByteChannel;Ljava/nio/ByteBuffer;)I
      25: istore_3
      26: iload_3
      27: ifle          38
      30: aload_0
      31: getfield      #48                 // Field metrics:Lorg/apache/hadoop/hbase/ipc/MetricsHBaseServer;
      34: iload_3
      35: invokevirtual #213                // Method org/apache/hadoop/hbase/ipc/MetricsHBaseServer.receivedBytes:(I)V
      38: iload_3
      39: ireturn

  static org.apache.hadoop.hbase.util.Pair<org.apache.hadoop.hbase.nio.ByteBuff, org.apache.hadoop.hbase.ipc.RpcServer$CallCleanup> allocateByteBuffToReadInto(org.apache.hadoop.hbase.io.ByteBufferPool, int, int);
    Code:
       0: new           #219                // class java/util/ArrayList
       3: dup
       4: iload_2
       5: aload_0
       6: invokevirtual #73                 // Method org/apache/hadoop/hbase/io/ByteBufferPool.getBufferSize:()I
       9: idiv
      10: iconst_1
      11: iadd
      12: invokespecial #220                // Method java/util/ArrayList."<init>":(I)V
      15: astore        4
      17: iload_2
      18: istore        5
      20: aconst_null
      21: astore        6
      23: iload         5
      25: iload_1
      26: if_icmplt     61
      29: aload_0
      30: invokevirtual #221                // Method org/apache/hadoop/hbase/io/ByteBufferPool.getBuffer:()Ljava/nio/ByteBuffer;
      33: dup
      34: astore        6
      36: ifnull        61
      39: aload         4
      41: aload         6
      43: invokeinterface #222,  2          // InterfaceMethod java/util/List.add:(Ljava/lang/Object;)Z
      48: pop
      49: iload         5
      51: aload_0
      52: invokevirtual #73                 // Method org/apache/hadoop/hbase/io/ByteBufferPool.getBufferSize:()I
      55: isub
      56: istore        5
      58: goto          23
      61: aconst_null
      62: astore        7
      64: aload         4
      66: invokeinterface #223,  1          // InterfaceMethod java/util/List.size:()I
      71: ifle          96
      74: aload         4
      76: invokeinterface #223,  1          // InterfaceMethod java/util/List.size:()I
      81: anewarray     #224                // class java/nio/ByteBuffer
      84: astore        7
      86: aload         4
      88: aload         7
      90: invokeinterface #225,  2          // InterfaceMethod java/util/List.toArray:([Ljava/lang/Object;)[Ljava/lang/Object;
      95: pop
      96: iload         5
      98: ifle          114
     101: aload         4
     103: iload         5
     105: invokestatic  #226                // Method java/nio/ByteBuffer.allocate:(I)Ljava/nio/ByteBuffer;
     108: invokeinterface #222,  2          // InterfaceMethod java/util/List.add:(Ljava/lang/Object;)Z
     113: pop
     114: aload         4
     116: invokeinterface #223,  1          // InterfaceMethod java/util/List.size:()I
     121: iconst_1
     122: if_icmple     160
     125: aload         4
     127: invokeinterface #223,  1          // InterfaceMethod java/util/List.size:()I
     132: anewarray     #224                // class java/nio/ByteBuffer
     135: astore        8
     137: aload         4
     139: aload         8
     141: invokeinterface #225,  2          // InterfaceMethod java/util/List.toArray:([Ljava/lang/Object;)[Ljava/lang/Object;
     146: pop
     147: new           #227                // class org/apache/hadoop/hbase/nio/MultiByteBuff
     150: dup
     151: aload         8
     153: invokespecial #228                // Method org/apache/hadoop/hbase/nio/MultiByteBuff."<init>":([Ljava/nio/ByteBuffer;)V
     156: astore_3
     157: goto          179
     160: new           #229                // class org/apache/hadoop/hbase/nio/SingleByteBuff
     163: dup
     164: aload         4
     166: iconst_0
     167: invokeinterface #230,  2          // InterfaceMethod java/util/List.get:(I)Ljava/lang/Object;
     172: checkcast     #224                // class java/nio/ByteBuffer
     175: invokespecial #231                // Method org/apache/hadoop/hbase/nio/SingleByteBuff."<init>":(Ljava/nio/ByteBuffer;)V
     178: astore_3
     179: aload_3
     180: iload_2
     181: invokevirtual #232                // Method org/apache/hadoop/hbase/nio/ByteBuff.limit:(I)Lorg/apache/hadoop/hbase/nio/ByteBuff;
     184: pop
     185: aload         7
     187: ifnull        211
     190: aload         7
     192: astore        8
     194: new           #155                // class org/apache/hadoop/hbase/util/Pair
     197: dup
     198: aload_3
     199: aload         8
     201: aload_0
     202: invokedynamic #233,  0            // InvokeDynamic #0:run:([Ljava/nio/ByteBuffer;Lorg/apache/hadoop/hbase/io/ByteBufferPool;)Lorg/apache/hadoop/hbase/ipc/RpcServer$CallCleanup;
     207: invokespecial #157                // Method org/apache/hadoop/hbase/util/Pair."<init>":(Ljava/lang/Object;Ljava/lang/Object;)V
     210: areturn
     211: new           #155                // class org/apache/hadoop/hbase/util/Pair
     214: dup
     215: aload_3
     216: aconst_null
     217: invokespecial #157                // Method org/apache/hadoop/hbase/util/Pair."<init>":(Ljava/lang/Object;Ljava/lang/Object;)V
     220: areturn

  public static java.util.Optional<org.apache.hadoop.hbase.ipc.RpcCall> getCurrentCall();
    Code:
       0: getstatic     #125                // Field CurCall:Ljava/lang/ThreadLocal;
       3: invokevirtual #126                // Method java/lang/ThreadLocal.get:()Ljava/lang/Object;
       6: invokestatic  #234                // Method java/util/Optional.ofNullable:(Ljava/lang/Object;)Ljava/util/Optional;
       9: areturn

  public static boolean isInRpcCallContext();
    Code:
       0: getstatic     #125                // Field CurCall:Ljava/lang/ThreadLocal;
       3: invokevirtual #126                // Method java/lang/ThreadLocal.get:()Ljava/lang/Object;
       6: ifnull        13
       9: iconst_1
      10: goto          14
      13: iconst_0
      14: ireturn

  public static java.util.Optional<org.apache.hadoop.hbase.security.User> getRequestUser();
    Code:
       0: invokestatic  #235                // Method getCurrentCall:()Ljava/util/Optional;
       3: astore_0
       4: aload_0
       5: invokevirtual #236                // Method java/util/Optional.isPresent:()Z
       8: ifeq          26
      11: aload_0
      12: invokevirtual #237                // Method java/util/Optional.get:()Ljava/lang/Object;
      15: checkcast     #127                // class org/apache/hadoop/hbase/ipc/RpcCall
      18: invokeinterface #238,  1          // InterfaceMethod org/apache/hadoop/hbase/ipc/RpcCall.getRequestUser:()Ljava/util/Optional;
      23: goto          29
      26: invokestatic  #239                // Method java/util/Optional.empty:()Ljava/util/Optional;
      29: areturn

  public abstract int getNumOpenConnections();

  public static java.util.Optional<java.lang.String> getRequestUserName();
    Code:
       0: invokestatic  #240                // Method getRequestUser:()Ljava/util/Optional;
       3: invokedynamic #241,  0            // InvokeDynamic #1:apply:()Ljava/util/function/Function;
       8: invokevirtual #242                // Method java/util/Optional.map:(Ljava/util/function/Function;)Ljava/util/Optional;
      11: areturn

  public static java.util.Optional<java.net.InetAddress> getRemoteAddress();
    Code:
       0: invokestatic  #235                // Method getCurrentCall:()Ljava/util/Optional;
       3: invokedynamic #243,  0            // InvokeDynamic #2:apply:()Ljava/util/function/Function;
       8: invokevirtual #242                // Method java/util/Optional.map:(Ljava/util/function/Function;)Ljava/util/Optional;
      11: areturn

  protected static org.apache.hadoop.hbase.ipc.RpcServer$BlockingServiceAndInterface getServiceAndInterface(java.util.List<org.apache.hadoop.hbase.ipc.RpcServer$BlockingServiceAndInterface>, java.lang.String);
    Code:
       0: aload_0
       1: invokeinterface #244,  1          // InterfaceMethod java/util/List.iterator:()Ljava/util/Iterator;
       6: astore_2
       7: aload_2
       8: invokeinterface #245,  1          // InterfaceMethod java/util/Iterator.hasNext:()Z
      13: ifeq          50
      16: aload_2
      17: invokeinterface #246,  1          // InterfaceMethod java/util/Iterator.next:()Ljava/lang/Object;
      22: checkcast     #247                // class org/apache/hadoop/hbase/ipc/RpcServer$BlockingServiceAndInterface
      25: astore_3
      26: aload_3
      27: invokevirtual #248                // Method org/apache/hadoop/hbase/ipc/RpcServer$BlockingServiceAndInterface.getBlockingService:()Lorg/apache/hbase/thirdparty/com/google/protobuf/BlockingService;
      30: invokeinterface #249,  1          // InterfaceMethod org/apache/hbase/thirdparty/com/google/protobuf/BlockingService.getDescriptorForType:()Lorg/apache/hbase/thirdparty/com/google/protobuf/Descriptors$ServiceDescriptor;
      35: invokevirtual #250                // Method org/apache/hbase/thirdparty/com/google/protobuf/Descriptors$ServiceDescriptor.getName:()Ljava/lang/String;
      38: aload_1
      39: invokevirtual #251                // Method java/lang/String.equals:(Ljava/lang/Object;)Z
      42: ifeq          47
      45: aload_3
      46: areturn
      47: goto          7
      50: aconst_null
      51: areturn

  protected static java.lang.Class<?> getServiceInterface(java.util.List<org.apache.hadoop.hbase.ipc.RpcServer$BlockingServiceAndInterface>, java.lang.String);
    Code:
       0: aload_0
       1: aload_1
       2: invokestatic  #252                // Method getServiceAndInterface:(Ljava/util/List;Ljava/lang/String;)Lorg/apache/hadoop/hbase/ipc/RpcServer$BlockingServiceAndInterface;
       5: astore_2
       6: aload_2
       7: ifnonnull     14
      10: aconst_null
      11: goto          18
      14: aload_2
      15: invokevirtual #253                // Method org/apache/hadoop/hbase/ipc/RpcServer$BlockingServiceAndInterface.getServiceInterface:()Ljava/lang/Class;
      18: areturn

  protected static org.apache.hbase.thirdparty.com.google.protobuf.BlockingService getService(java.util.List<org.apache.hadoop.hbase.ipc.RpcServer$BlockingServiceAndInterface>, java.lang.String);
    Code:
       0: aload_0
       1: aload_1
       2: invokestatic  #252                // Method getServiceAndInterface:(Ljava/util/List;Ljava/lang/String;)Lorg/apache/hadoop/hbase/ipc/RpcServer$BlockingServiceAndInterface;
       5: astore_2
       6: aload_2
       7: ifnonnull     14
      10: aconst_null
      11: goto          18
      14: aload_2
      15: invokevirtual #248                // Method org/apache/hadoop/hbase/ipc/RpcServer$BlockingServiceAndInterface.getBlockingService:()Lorg/apache/hbase/thirdparty/com/google/protobuf/BlockingService;
      18: areturn

  protected static org.apache.hadoop.hbase.monitoring.MonitoredRPCHandler getStatus();
    Code:
       0: getstatic     #254                // Field MONITORED_RPC:Ljava/lang/ThreadLocal;
       3: invokevirtual #126                // Method java/lang/ThreadLocal.get:()Ljava/lang/Object;
       6: checkcast     #255                // class org/apache/hadoop/hbase/monitoring/MonitoredRPCHandler
       9: astore_0
      10: aload_0
      11: ifnull        16
      14: aload_0
      15: areturn
      16: invokestatic  #256                // Method org/apache/hadoop/hbase/monitoring/TaskMonitor.get:()Lorg/apache/hadoop/hbase/monitoring/TaskMonitor;
      19: invokestatic  #257                // Method java/lang/Thread.currentThread:()Ljava/lang/Thread;
      22: invokevirtual #258                // Method java/lang/Thread.getName:()Ljava/lang/String;
      25: invokevirtual #259                // Method org/apache/hadoop/hbase/monitoring/TaskMonitor.createRPCStatus:(Ljava/lang/String;)Lorg/apache/hadoop/hbase/monitoring/MonitoredRPCHandler;
      28: astore_0
      29: aload_0
      30: ldc_w         #260                // String Waiting for a call
      33: invokeinterface #261,  2          // InterfaceMethod org/apache/hadoop/hbase/monitoring/MonitoredRPCHandler.pause:(Ljava/lang/String;)V
      38: getstatic     #254                // Field MONITORED_RPC:Ljava/lang/ThreadLocal;
      41: aload_0
      42: invokevirtual #262                // Method java/lang/ThreadLocal.set:(Ljava/lang/Object;)V
      45: aload_0
      46: areturn

  public static java.net.InetAddress getRemoteIp();
    Code:
       0: getstatic     #125                // Field CurCall:Ljava/lang/ThreadLocal;
       3: invokevirtual #126                // Method java/lang/ThreadLocal.get:()Ljava/lang/Object;
       6: checkcast     #127                // class org/apache/hadoop/hbase/ipc/RpcCall
       9: astore_0
      10: aload_0
      11: ifnull        21
      14: aload_0
      15: invokeinterface #263,  1          // InterfaceMethod org/apache/hadoop/hbase/ipc/RpcCall.getRemoteAddress:()Ljava/net/InetAddress;
      20: areturn
      21: aconst_null
      22: areturn

  public org.apache.hadoop.hbase.ipc.RpcScheduler getScheduler();
    Code:
       0: aload_0
       1: getfield      #72                 // Field scheduler:Lorg/apache/hadoop/hbase/ipc/RpcScheduler;
       4: areturn

  public void setRsRpcServices(org.apache.hadoop.hbase.regionserver.RSRpcServices);
    Code:
       0: aload_0
       1: aload_1
       2: putfield      #192                // Field rsRpcServices:Lorg/apache/hadoop/hbase/regionserver/RSRpcServices;
       5: return

  static {};
    Code:
       0: ldc           #1                  // class org/apache/hadoop/hbase/ipc/RpcServer
       2: invokestatic  #265                // Method org/slf4j/LoggerFactory.getLogger:(Ljava/lang/Class;)Lorg/slf4j/Logger;
       5: putstatic     #79                 // Field LOG:Lorg/slf4j/Logger;
       8: new           #266                // class org/apache/hadoop/hbase/CallQueueTooBigException
      11: dup
      12: invokespecial #267                // Method org/apache/hadoop/hbase/CallQueueTooBigException."<init>":()V
      15: putstatic     #268                // Field CALL_QUEUE_TOO_BIG_EXCEPTION:Lorg/apache/hadoop/hbase/CallQueueTooBigException;
      18: new           #123                // class java/lang/StringBuilder
      21: dup
      22: invokespecial #124                // Method java/lang/StringBuilder."<init>":()V
      25: ldc_w         #269                // String SecurityLogger.
      28: invokevirtual #129                // Method java/lang/StringBuilder.append:(Ljava/lang/String;)Ljava/lang/StringBuilder;
      31: ldc_w         #270                // class org/apache/hadoop/hbase/Server
      34: invokevirtual #149                // Method java/lang/Class.getName:()Ljava/lang/String;
      37: invokevirtual #129                // Method java/lang/StringBuilder.append:(Ljava/lang/String;)Ljava/lang/StringBuilder;
      40: invokevirtual #136                // Method java/lang/StringBuilder.toString:()Ljava/lang/String;
      43: invokestatic  #271                // Method org/slf4j/LoggerFactory.getLogger:(Ljava/lang/String;)Lorg/slf4j/Logger;
      46: putstatic     #272                // Field AUDITLOG:Lorg/slf4j/Logger;
      49: new           #273                // class java/lang/ThreadLocal
      52: dup
      53: invokespecial #274                // Method java/lang/ThreadLocal."<init>":()V
      56: putstatic     #125                // Field CurCall:Ljava/lang/ThreadLocal;
      59: new           #273                // class java/lang/ThreadLocal
      62: dup
      63: invokespecial #274                // Method java/lang/ThreadLocal."<init>":()V
      66: putstatic     #254                // Field MONITORED_RPC:Ljava/lang/ThreadLocal;
      69: new           #275                // class org/apache/hadoop/hbase/exceptions/RequestTooBigException
      72: dup
      73: invokespecial #276                // Method org/apache/hadoop/hbase/exceptions/RequestTooBigException."<init>":()V
      76: putstatic     #277                // Field REQUEST_TOO_BIG_EXCEPTION:Lorg/apache/hadoop/hbase/exceptions/RequestTooBigException;
      79: invokestatic  #278                // Method org/apache/hadoop/hbase/util/GsonUtil.createGson:()Lorg/apache/hbase/thirdparty/com/google/gson/GsonBuilder;
      82: invokevirtual #279                // Method org/apache/hbase/thirdparty/com/google/gson/GsonBuilder.create:()Lorg/apache/hbase/thirdparty/com/google/gson/Gson;
      85: putstatic     #199                // Field GSON:Lorg/apache/hbase/thirdparty/com/google/gson/Gson;
      88: return
}
