Compiled from "RSGroupTableAccessor.java"
public final class org.apache.hadoop.hbase.RSGroupTableAccessor {
  public static boolean isRSGroupsEnabled(org.apache.hadoop.hbase.client.Connection) throws java.io.IOException;
    Code:
       0: aload_0
       1: invokeinterface #2,  1            // InterfaceMethod org/apache/hadoop/hbase/client/Connection.getAdmin:()Lorg/apache/hadoop/hbase/client/Admin;
       6: getstatic     #3                  // Field RSGROUP_TABLE_NAME:Lorg/apache/hadoop/hbase/TableName;
       9: invokeinterface #4,  2            // InterfaceMethod org/apache/hadoop/hbase/client/Admin.tableExists:(Lorg/apache/hadoop/hbase/TableName;)Z
      14: ireturn

  public static java.util.List<org.apache.hadoop.hbase.rsgroup.RSGroupInfo> getAllRSGroupInfo(org.apache.hadoop.hbase.client.Connection) throws java.io.IOException;
    Code:
       0: aload_0
       1: getstatic     #3                  // Field RSGROUP_TABLE_NAME:Lorg/apache/hadoop/hbase/TableName;
       4: invokeinterface #5,  2            // InterfaceMethod org/apache/hadoop/hbase/client/Connection.getTable:(Lorg/apache/hadoop/hbase/TableName;)Lorg/apache/hadoop/hbase/client/Table;
       9: astore_1
      10: aconst_null
      11: astore_2
      12: new           #6                  // class java/util/ArrayList
      15: dup
      16: invokespecial #7                  // Method java/util/ArrayList."<init>":()V
      19: astore_3
      20: aload_1
      21: new           #8                  // class org/apache/hadoop/hbase/client/Scan
      24: dup
      25: invokespecial #9                  // Method org/apache/hadoop/hbase/client/Scan."<init>":()V
      28: invokeinterface #10,  2           // InterfaceMethod org/apache/hadoop/hbase/client/Table.getScanner:(Lorg/apache/hadoop/hbase/client/Scan;)Lorg/apache/hadoop/hbase/client/ResultScanner;
      33: invokeinterface #11,  1           // InterfaceMethod org/apache/hadoop/hbase/client/ResultScanner.iterator:()Ljava/util/Iterator;
      38: astore        4
      40: aload         4
      42: invokeinterface #12,  1           // InterfaceMethod java/util/Iterator.hasNext:()Z
      47: ifeq          86
      50: aload         4
      52: invokeinterface #13,  1           // InterfaceMethod java/util/Iterator.next:()Ljava/lang/Object;
      57: checkcast     #14                 // class org/apache/hadoop/hbase/client/Result
      60: astore        5
      62: aload         5
      64: invokestatic  #15                 // Method getRSGroupInfo:(Lorg/apache/hadoop/hbase/client/Result;)Lorg/apache/hadoop/hbase/rsgroup/RSGroupInfo;
      67: astore        6
      69: aload         6
      71: ifnull        83
      74: aload_3
      75: aload         6
      77: invokeinterface #16,  2           // InterfaceMethod java/util/List.add:(Ljava/lang/Object;)Z
      82: pop
      83: goto          40
      86: aload_3
      87: astore        4
      89: aload_1
      90: ifnull        123
      93: aload_2
      94: ifnull        117
      97: aload_1
      98: invokeinterface #17,  1           // InterfaceMethod org/apache/hadoop/hbase/client/Table.close:()V
     103: goto          123
     106: astore        5
     108: aload_2
     109: aload         5
     111: invokevirtual #19                 // Method java/lang/Throwable.addSuppressed:(Ljava/lang/Throwable;)V
     114: goto          123
     117: aload_1
     118: invokeinterface #17,  1           // InterfaceMethod org/apache/hadoop/hbase/client/Table.close:()V
     123: aload         4
     125: areturn
     126: astore_3
     127: aload_3
     128: astore_2
     129: aload_3
     130: athrow
     131: astore        7
     133: aload_1
     134: ifnull        167
     137: aload_2
     138: ifnull        161
     141: aload_1
     142: invokeinterface #17,  1           // InterfaceMethod org/apache/hadoop/hbase/client/Table.close:()V
     147: goto          167
     150: astore        8
     152: aload_2
     153: aload         8
     155: invokevirtual #19                 // Method java/lang/Throwable.addSuppressed:(Ljava/lang/Throwable;)V
     158: goto          167
     161: aload_1
     162: invokeinterface #17,  1           // InterfaceMethod org/apache/hadoop/hbase/client/Table.close:()V
     167: aload         7
     169: athrow
    Exception table:
       from    to  target type
          97   103   106   Class java/lang/Throwable
          12    89   126   Class java/lang/Throwable
          12    89   131   any
         141   147   150   Class java/lang/Throwable
         126   133   131   any

  public static org.apache.hadoop.hbase.rsgroup.RSGroupInfo getRSGroupInfo(org.apache.hadoop.hbase.client.Connection, byte[]) throws java.io.IOException;
    Code:
       0: aload_0
       1: getstatic     #3                  // Field RSGROUP_TABLE_NAME:Lorg/apache/hadoop/hbase/TableName;
       4: invokeinterface #5,  2            // InterfaceMethod org/apache/hadoop/hbase/client/Connection.getTable:(Lorg/apache/hadoop/hbase/TableName;)Lorg/apache/hadoop/hbase/client/Table;
       9: astore_2
      10: aconst_null
      11: astore_3
      12: aload_2
      13: new           #25                 // class org/apache/hadoop/hbase/client/Get
      16: dup
      17: aload_1
      18: invokespecial #26                 // Method org/apache/hadoop/hbase/client/Get."<init>":([B)V
      21: invokeinterface #27,  2           // InterfaceMethod org/apache/hadoop/hbase/client/Table.get:(Lorg/apache/hadoop/hbase/client/Get;)Lorg/apache/hadoop/hbase/client/Result;
      26: astore        4
      28: aload         4
      30: invokestatic  #15                 // Method getRSGroupInfo:(Lorg/apache/hadoop/hbase/client/Result;)Lorg/apache/hadoop/hbase/rsgroup/RSGroupInfo;
      33: astore        5
      35: aload_2
      36: ifnull        69
      39: aload_3
      40: ifnull        63
      43: aload_2
      44: invokeinterface #17,  1           // InterfaceMethod org/apache/hadoop/hbase/client/Table.close:()V
      49: goto          69
      52: astore        6
      54: aload_3
      55: aload         6
      57: invokevirtual #19                 // Method java/lang/Throwable.addSuppressed:(Ljava/lang/Throwable;)V
      60: goto          69
      63: aload_2
      64: invokeinterface #17,  1           // InterfaceMethod org/apache/hadoop/hbase/client/Table.close:()V
      69: aload         5
      71: areturn
      72: astore        4
      74: aload         4
      76: astore_3
      77: aload         4
      79: athrow
      80: astore        7
      82: aload_2
      83: ifnull        116
      86: aload_3
      87: ifnull        110
      90: aload_2
      91: invokeinterface #17,  1           // InterfaceMethod org/apache/hadoop/hbase/client/Table.close:()V
      96: goto          116
      99: astore        8
     101: aload_3
     102: aload         8
     104: invokevirtual #19                 // Method java/lang/Throwable.addSuppressed:(Ljava/lang/Throwable;)V
     107: goto          116
     110: aload_2
     111: invokeinterface #17,  1           // InterfaceMethod org/apache/hadoop/hbase/client/Table.close:()V
     116: aload         7
     118: athrow
    Exception table:
       from    to  target type
          43    49    52   Class java/lang/Throwable
          12    35    72   Class java/lang/Throwable
          12    35    80   any
          90    96    99   Class java/lang/Throwable
          72    82    80   any

  static {};
    Code:
       0: getstatic     #28                 // Field org/apache/hadoop/hbase/NamespaceDescriptor.SYSTEM_NAMESPACE_NAME_STR:Ljava/lang/String;
       3: ldc           #29                 // String rsgroup
       5: invokestatic  #30                 // Method org/apache/hadoop/hbase/TableName.valueOf:(Ljava/lang/String;Ljava/lang/String;)Lorg/apache/hadoop/hbase/TableName;
       8: putstatic     #3                  // Field RSGROUP_TABLE_NAME:Lorg/apache/hadoop/hbase/TableName;
      11: ldc           #31                 // String m
      13: invokestatic  #32                 // Method org/apache/hadoop/hbase/util/Bytes.toBytes:(Ljava/lang/String;)[B
      16: putstatic     #20                 // Field META_FAMILY_BYTES:[B
      19: ldc           #33                 // String i
      21: invokestatic  #32                 // Method org/apache/hadoop/hbase/util/Bytes.toBytes:(Ljava/lang/String;)[B
      24: putstatic     #21                 // Field META_QUALIFIER_BYTES:[B
      27: return
}
