Compiled from "RSProcedureDispatcher.java"
public final class org.apache.hadoop.hbase.master.procedure.RSProcedureDispatcher$ServerOperation extends org.apache.hadoop.hbase.procedure2.RemoteProcedureDispatcher$RemoteOperation {
  public org.apache.hadoop.hbase.master.procedure.RSProcedureDispatcher$ServerOperation(org.apache.hadoop.hbase.procedure2.RemoteProcedureDispatcher$RemoteProcedure, long, java.lang.Class<?>, byte[]);
    Code:
       0: aload_0
       1: aload_1
       2: invokespecial #1                  // Method org/apache/hadoop/hbase/procedure2/RemoteProcedureDispatcher$RemoteOperation."<init>":(Lorg/apache/hadoop/hbase/procedure2/RemoteProcedureDispatcher$RemoteProcedure;)V
       5: aload_0
       6: lload_2
       7: putfield      #2                  // Field procId:J
      10: aload_0
      11: aload         4
      13: putfield      #3                  // Field rsProcClass:Ljava/lang/Class;
      16: aload_0
      17: aload         5
      19: putfield      #4                  // Field rsProcData:[B
      22: return

  public org.apache.hadoop.hbase.shaded.protobuf.generated.AdminProtos$RemoteProcedureRequest buildRequest();
    Code:
       0: invokestatic  #5                  // Method org/apache/hadoop/hbase/shaded/protobuf/generated/AdminProtos$RemoteProcedureRequest.newBuilder:()Lorg/apache/hadoop/hbase/shaded/protobuf/generated/AdminProtos$RemoteProcedureRequest$Builder;
       3: aload_0
       4: getfield      #2                  // Field procId:J
       7: invokevirtual #6                  // Method org/apache/hadoop/hbase/shaded/protobuf/generated/AdminProtos$RemoteProcedureRequest$Builder.setProcId:(J)Lorg/apache/hadoop/hbase/shaded/protobuf/generated/AdminProtos$RemoteProcedureRequest$Builder;
      10: aload_0
      11: getfield      #3                  // Field rsProcClass:Ljava/lang/Class;
      14: invokevirtual #7                  // Method java/lang/Class.getName:()Ljava/lang/String;
      17: invokevirtual #8                  // Method org/apache/hadoop/hbase/shaded/protobuf/generated/AdminProtos$RemoteProcedureRequest$Builder.setProcClass:(Ljava/lang/String;)Lorg/apache/hadoop/hbase/shaded/protobuf/generated/AdminProtos$RemoteProcedureRequest$Builder;
      20: aload_0
      21: getfield      #4                  // Field rsProcData:[B
      24: invokestatic  #9                  // Method org/apache/hbase/thirdparty/com/google/protobuf/ByteString.copyFrom:([B)Lorg/apache/hbase/thirdparty/com/google/protobuf/ByteString;
      27: invokevirtual #10                 // Method org/apache/hadoop/hbase/shaded/protobuf/generated/AdminProtos$RemoteProcedureRequest$Builder.setProcData:(Lorg/apache/hbase/thirdparty/com/google/protobuf/ByteString;)Lorg/apache/hadoop/hbase/shaded/protobuf/generated/AdminProtos$RemoteProcedureRequest$Builder;
      30: invokevirtual #11                 // Method org/apache/hadoop/hbase/shaded/protobuf/generated/AdminProtos$RemoteProcedureRequest$Builder.build:()Lorg/apache/hadoop/hbase/shaded/protobuf/generated/AdminProtos$RemoteProcedureRequest;
      33: areturn
}
