Compiled from "RSProcedureDispatcher.java"
public abstract class org.apache.hadoop.hbase.master.procedure.RSProcedureDispatcher$RegionOperation extends org.apache.hadoop.hbase.procedure2.RemoteProcedureDispatcher$RemoteOperation {
  protected final org.apache.hadoop.hbase.client.RegionInfo regionInfo;

  protected final long procId;

  protected org.apache.hadoop.hbase.master.procedure.RSProcedureDispatcher$RegionOperation(org.apache.hadoop.hbase.procedure2.RemoteProcedureDispatcher$RemoteProcedure, org.apache.hadoop.hbase.client.RegionInfo, long);
    Code:
       0: aload_0
       1: aload_1
       2: invokespecial #1                  // Method org/apache/hadoop/hbase/procedure2/RemoteProcedureDispatcher$RemoteOperation."<init>":(Lorg/apache/hadoop/hbase/procedure2/RemoteProcedureDispatcher$RemoteProcedure;)V
       5: aload_0
       6: aload_2
       7: putfield      #2                  // Field regionInfo:Lorg/apache/hadoop/hbase/client/RegionInfo;
      10: aload_0
      11: lload_3
      12: putfield      #3                  // Field procId:J
      15: return
}
