Compiled from "RSRpcServices.java"
class org.apache.hadoop.hbase.regionserver.RSRpcServices$ScannerListener implements org.apache.hadoop.hbase.regionserver.LeaseListener {
  final org.apache.hadoop.hbase.regionserver.RSRpcServices this$0;

  org.apache.hadoop.hbase.regionserver.RSRpcServices$ScannerListener(org.apache.hadoop.hbase.regionserver.RSRpcServices, java.lang.String);
    Code:
       0: aload_0
       1: aload_1
       2: putfield      #1                  // Field this$0:Lorg/apache/hadoop/hbase/regionserver/RSRpcServices;
       5: aload_0
       6: invokespecial #2                  // Method java/lang/Object."<init>":()V
       9: aload_0
      10: aload_2
      11: putfield      #3                  // Field scannerName:Ljava/lang/String;
      14: return

  public void leaseExpired();
    Code:
       0: aload_0
       1: getfield      #1                  // Field this$0:Lorg/apache/hadoop/hbase/regionserver/RSRpcServices;
       4: invokestatic  #4                  // Method org/apache/hadoop/hbase/regionserver/RSRpcServices.access$000:(Lorg/apache/hadoop/hbase/regionserver/RSRpcServices;)Ljava/util/concurrent/ConcurrentMap;
       7: aload_0
       8: getfield      #3                  // Field scannerName:Ljava/lang/String;
      11: invokeinterface #5,  2            // InterfaceMethod java/util/concurrent/ConcurrentMap.remove:(Ljava/lang/Object;)Ljava/lang/Object;
      16: checkcast     #6                  // class org/apache/hadoop/hbase/regionserver/RSRpcServices$RegionScannerHolder
      19: astore_1
      20: aload_1
      21: ifnull        384
      24: aload_1
      25: invokestatic  #7                  // Method org/apache/hadoop/hbase/regionserver/RSRpcServices$RegionScannerHolder.access$100:(Lorg/apache/hadoop/hbase/regionserver/RSRpcServices$RegionScannerHolder;)Lorg/apache/hadoop/hbase/regionserver/RegionScanner;
      28: astore_2
      29: getstatic     #8                  // Field org/apache/hadoop/hbase/regionserver/RSRpcServices.LOG:Lorg/slf4j/Logger;
      32: new           #9                  // class java/lang/StringBuilder
      35: dup
      36: invokespecial #10                 // Method java/lang/StringBuilder."<init>":()V
      39: ldc           #11                 // String Scanner
      41: invokevirtual #12                 // Method java/lang/StringBuilder.append:(Ljava/lang/String;)Ljava/lang/StringBuilder;
      44: aload_0
      45: getfield      #3                  // Field scannerName:Ljava/lang/String;
      48: invokevirtual #12                 // Method java/lang/StringBuilder.append:(Ljava/lang/String;)Ljava/lang/StringBuilder;
      51: ldc           #13                 // String  lease expired on region
      53: invokevirtual #12                 // Method java/lang/StringBuilder.append:(Ljava/lang/String;)Ljava/lang/StringBuilder;
      56: aload_2
      57: invokeinterface #14,  1           // InterfaceMethod org/apache/hadoop/hbase/regionserver/RegionScanner.getRegionInfo:()Lorg/apache/hadoop/hbase/client/RegionInfo;
      62: invokeinterface #15,  1           // InterfaceMethod org/apache/hadoop/hbase/client/RegionInfo.getRegionNameAsString:()Ljava/lang/String;
      67: invokevirtual #12                 // Method java/lang/StringBuilder.append:(Ljava/lang/String;)Ljava/lang/StringBuilder;
      70: invokevirtual #16                 // Method java/lang/StringBuilder.toString:()Ljava/lang/String;
      73: invokeinterface #17,  2           // InterfaceMethod org/slf4j/Logger.info:(Ljava/lang/String;)V
      78: aconst_null
      79: astore_3
      80: aload_0
      81: getfield      #1                  // Field this$0:Lorg/apache/hadoop/hbase/regionserver/RSRpcServices;
      84: getfield      #18                 // Field org/apache/hadoop/hbase/regionserver/RSRpcServices.regionServer:Lorg/apache/hadoop/hbase/regionserver/HRegionServer;
      87: aload_2
      88: invokeinterface #14,  1           // InterfaceMethod org/apache/hadoop/hbase/regionserver/RegionScanner.getRegionInfo:()Lorg/apache/hadoop/hbase/client/RegionInfo;
      93: invokeinterface #19,  1           // InterfaceMethod org/apache/hadoop/hbase/client/RegionInfo.getRegionName:()[B
      98: invokevirtual #20                 // Method org/apache/hadoop/hbase/regionserver/HRegionServer.getRegion:([B)Lorg/apache/hadoop/hbase/regionserver/HRegion;
     101: astore_3
     102: aload_3
     103: ifnull        122
     106: aload_3
     107: invokevirtual #21                 // Method org/apache/hadoop/hbase/regionserver/HRegion.getCoprocessorHost:()Lorg/apache/hadoop/hbase/regionserver/RegionCoprocessorHost;
     110: ifnull        122
     113: aload_3
     114: invokevirtual #21                 // Method org/apache/hadoop/hbase/regionserver/HRegion.getCoprocessorHost:()Lorg/apache/hadoop/hbase/regionserver/RegionCoprocessorHost;
     117: aload_2
     118: invokevirtual #22                 // Method org/apache/hadoop/hbase/regionserver/RegionCoprocessorHost.preScannerClose:(Lorg/apache/hadoop/hbase/regionserver/InternalScanner;)Z
     121: pop
     122: aload_2
     123: invokeinterface #23,  1           // InterfaceMethod org/apache/hadoop/hbase/regionserver/RegionScanner.close:()V
     128: aload_3
     129: ifnull        147
     132: aload_3
     133: invokevirtual #21                 // Method org/apache/hadoop/hbase/regionserver/HRegion.getCoprocessorHost:()Lorg/apache/hadoop/hbase/regionserver/RegionCoprocessorHost;
     136: ifnull        147
     139: aload_3
     140: invokevirtual #21                 // Method org/apache/hadoop/hbase/regionserver/HRegion.getCoprocessorHost:()Lorg/apache/hadoop/hbase/regionserver/RegionCoprocessorHost;
     143: aload_2
     144: invokevirtual #24                 // Method org/apache/hadoop/hbase/regionserver/RegionCoprocessorHost.postScannerClose:(Lorg/apache/hadoop/hbase/regionserver/InternalScanner;)V
     147: goto          381
     150: astore        4
     152: getstatic     #8                  // Field org/apache/hadoop/hbase/regionserver/RSRpcServices.LOG:Lorg/slf4j/Logger;
     155: new           #9                  // class java/lang/StringBuilder
     158: dup
     159: invokespecial #10                 // Method java/lang/StringBuilder."<init>":()V
     162: ldc           #26                 // String Closing scanner for
     164: invokevirtual #12                 // Method java/lang/StringBuilder.append:(Ljava/lang/String;)Ljava/lang/StringBuilder;
     167: aload_2
     168: invokeinterface #14,  1           // InterfaceMethod org/apache/hadoop/hbase/regionserver/RegionScanner.getRegionInfo:()Lorg/apache/hadoop/hbase/client/RegionInfo;
     173: invokeinterface #15,  1           // InterfaceMethod org/apache/hadoop/hbase/client/RegionInfo.getRegionNameAsString:()Ljava/lang/String;
     178: invokevirtual #12                 // Method java/lang/StringBuilder.append:(Ljava/lang/String;)Ljava/lang/StringBuilder;
     181: invokevirtual #16                 // Method java/lang/StringBuilder.toString:()Ljava/lang/String;
     184: aload         4
     186: invokeinterface #27,  3           // InterfaceMethod org/slf4j/Logger.error:(Ljava/lang/String;Ljava/lang/Throwable;)V
     191: goto          381
     194: astore        4
     196: getstatic     #8                  // Field org/apache/hadoop/hbase/regionserver/RSRpcServices.LOG:Lorg/slf4j/Logger;
     199: new           #9                  // class java/lang/StringBuilder
     202: dup
     203: invokespecial #10                 // Method java/lang/StringBuilder."<init>":()V
     206: ldc           #26                 // String Closing scanner for
     208: invokevirtual #12                 // Method java/lang/StringBuilder.append:(Ljava/lang/String;)Ljava/lang/StringBuilder;
     211: aload_2
     212: invokeinterface #14,  1           // InterfaceMethod org/apache/hadoop/hbase/regionserver/RegionScanner.getRegionInfo:()Lorg/apache/hadoop/hbase/client/RegionInfo;
     217: invokeinterface #15,  1           // InterfaceMethod org/apache/hadoop/hbase/client/RegionInfo.getRegionNameAsString:()Ljava/lang/String;
     222: invokevirtual #12                 // Method java/lang/StringBuilder.append:(Ljava/lang/String;)Ljava/lang/StringBuilder;
     225: invokevirtual #16                 // Method java/lang/StringBuilder.toString:()Ljava/lang/String;
     228: aload         4
     230: invokeinterface #27,  3           // InterfaceMethod org/slf4j/Logger.error:(Ljava/lang/String;Ljava/lang/Throwable;)V
     235: aload_2
     236: invokeinterface #23,  1           // InterfaceMethod org/apache/hadoop/hbase/regionserver/RegionScanner.close:()V
     241: aload_3
     242: ifnull        260
     245: aload_3
     246: invokevirtual #21                 // Method org/apache/hadoop/hbase/regionserver/HRegion.getCoprocessorHost:()Lorg/apache/hadoop/hbase/regionserver/RegionCoprocessorHost;
     249: ifnull        260
     252: aload_3
     253: invokevirtual #21                 // Method org/apache/hadoop/hbase/regionserver/HRegion.getCoprocessorHost:()Lorg/apache/hadoop/hbase/regionserver/RegionCoprocessorHost;
     256: aload_2
     257: invokevirtual #24                 // Method org/apache/hadoop/hbase/regionserver/RegionCoprocessorHost.postScannerClose:(Lorg/apache/hadoop/hbase/regionserver/InternalScanner;)V
     260: goto          381
     263: astore        4
     265: getstatic     #8                  // Field org/apache/hadoop/hbase/regionserver/RSRpcServices.LOG:Lorg/slf4j/Logger;
     268: new           #9                  // class java/lang/StringBuilder
     271: dup
     272: invokespecial #10                 // Method java/lang/StringBuilder."<init>":()V
     275: ldc           #26                 // String Closing scanner for
     277: invokevirtual #12                 // Method java/lang/StringBuilder.append:(Ljava/lang/String;)Ljava/lang/StringBuilder;
     280: aload_2
     281: invokeinterface #14,  1           // InterfaceMethod org/apache/hadoop/hbase/regionserver/RegionScanner.getRegionInfo:()Lorg/apache/hadoop/hbase/client/RegionInfo;
     286: invokeinterface #15,  1           // InterfaceMethod org/apache/hadoop/hbase/client/RegionInfo.getRegionNameAsString:()Ljava/lang/String;
     291: invokevirtual #12                 // Method java/lang/StringBuilder.append:(Ljava/lang/String;)Ljava/lang/StringBuilder;
     294: invokevirtual #16                 // Method java/lang/StringBuilder.toString:()Ljava/lang/String;
     297: aload         4
     299: invokeinterface #27,  3           // InterfaceMethod org/slf4j/Logger.error:(Ljava/lang/String;Ljava/lang/Throwable;)V
     304: goto          381
     307: astore        5
     309: aload_2
     310: invokeinterface #23,  1           // InterfaceMethod org/apache/hadoop/hbase/regionserver/RegionScanner.close:()V
     315: aload_3
     316: ifnull        334
     319: aload_3
     320: invokevirtual #21                 // Method org/apache/hadoop/hbase/regionserver/HRegion.getCoprocessorHost:()Lorg/apache/hadoop/hbase/regionserver/RegionCoprocessorHost;
     323: ifnull        334
     326: aload_3
     327: invokevirtual #21                 // Method org/apache/hadoop/hbase/regionserver/HRegion.getCoprocessorHost:()Lorg/apache/hadoop/hbase/regionserver/RegionCoprocessorHost;
     330: aload_2
     331: invokevirtual #24                 // Method org/apache/hadoop/hbase/regionserver/RegionCoprocessorHost.postScannerClose:(Lorg/apache/hadoop/hbase/regionserver/InternalScanner;)V
     334: goto          378
     337: astore        6
     339: getstatic     #8                  // Field org/apache/hadoop/hbase/regionserver/RSRpcServices.LOG:Lorg/slf4j/Logger;
     342: new           #9                  // class java/lang/StringBuilder
     345: dup
     346: invokespecial #10                 // Method java/lang/StringBuilder."<init>":()V
     349: ldc           #26                 // String Closing scanner for
     351: invokevirtual #12                 // Method java/lang/StringBuilder.append:(Ljava/lang/String;)Ljava/lang/StringBuilder;
     354: aload_2
     355: invokeinterface #14,  1           // InterfaceMethod org/apache/hadoop/hbase/regionserver/RegionScanner.getRegionInfo:()Lorg/apache/hadoop/hbase/client/RegionInfo;
     360: invokeinterface #15,  1           // InterfaceMethod org/apache/hadoop/hbase/client/RegionInfo.getRegionNameAsString:()Ljava/lang/String;
     365: invokevirtual #12                 // Method java/lang/StringBuilder.append:(Ljava/lang/String;)Ljava/lang/StringBuilder;
     368: invokevirtual #16                 // Method java/lang/StringBuilder.toString:()Ljava/lang/String;
     371: aload         6
     373: invokeinterface #27,  3           // InterfaceMethod org/slf4j/Logger.error:(Ljava/lang/String;Ljava/lang/Throwable;)V
     378: aload         5
     380: athrow
     381: goto          419
     384: getstatic     #8                  // Field org/apache/hadoop/hbase/regionserver/RSRpcServices.LOG:Lorg/slf4j/Logger;
     387: new           #9                  // class java/lang/StringBuilder
     390: dup
     391: invokespecial #10                 // Method java/lang/StringBuilder."<init>":()V
     394: ldc           #11                 // String Scanner
     396: invokevirtual #12                 // Method java/lang/StringBuilder.append:(Ljava/lang/String;)Ljava/lang/StringBuilder;
     399: aload_0
     400: getfield      #3                  // Field scannerName:Ljava/lang/String;
     403: invokevirtual #12                 // Method java/lang/StringBuilder.append:(Ljava/lang/String;)Ljava/lang/StringBuilder;
     406: ldc           #28                 // String  lease expired, but no related scanner found, hence no chance to close that related scanner!
     408: invokevirtual #12                 // Method java/lang/StringBuilder.append:(Ljava/lang/String;)Ljava/lang/StringBuilder;
     411: invokevirtual #16                 // Method java/lang/StringBuilder.toString:()Ljava/lang/String;
     414: invokeinterface #29,  2           // InterfaceMethod org/slf4j/Logger.warn:(Ljava/lang/String;)V
     419: return
    Exception table:
       from    to  target type
         122   147   150   Class java/io/IOException
          80   122   194   Class java/io/IOException
         235   260   263   Class java/io/IOException
          80   122   307   any
         194   235   307   any
         309   334   337   Class java/io/IOException
         307   309   307   any
}
