Compiled from "RSStatusTmpl.java"
public class org.apache.hadoop.hbase.tmpl.regionserver.RSStatusTmpl extends org.jamon.AbstractTemplateProxy {
  protected java.lang.String bcn;

  protected java.lang.String bcv;

  protected java.lang.String filter;

  protected java.lang.String format;

  public org.apache.hadoop.hbase.tmpl.regionserver.RSStatusTmpl(org.jamon.TemplateManager);
    Code:
       0: aload_0
       1: aload_1
       2: invokespecial #1                  // Method org/jamon/AbstractTemplateProxy."<init>":(Lorg/jamon/TemplateManager;)V
       5: return

  protected org.apache.hadoop.hbase.tmpl.regionserver.RSStatusTmpl(java.lang.String);
    Code:
       0: aload_0
       1: aload_1
       2: invokespecial #2                  // Method org/jamon/AbstractTemplateProxy."<init>":(Ljava/lang/String;)V
       5: return

  public org.apache.hadoop.hbase.tmpl.regionserver.RSStatusTmpl();
    Code:
       0: aload_0
       1: ldc           #3                  // String /org/apache/hadoop/hbase/tmpl/regionserver/RSStatusTmpl
       3: invokespecial #2                  // Method org/jamon/AbstractTemplateProxy."<init>":(Ljava/lang/String;)V
       6: return

  protected org.jamon.AbstractTemplateProxy$ImplData makeImplData();
    Code:
       0: new           #4                  // class org/apache/hadoop/hbase/tmpl/regionserver/RSStatusTmpl$ImplData
       3: dup
       4: invokespecial #5                  // Method org/apache/hadoop/hbase/tmpl/regionserver/RSStatusTmpl$ImplData."<init>":()V
       7: areturn

  public org.apache.hadoop.hbase.tmpl.regionserver.RSStatusTmpl$ImplData getImplData();
    Code:
       0: aload_0
       1: invokespecial #6                  // Method org/jamon/AbstractTemplateProxy.getImplData:()Lorg/jamon/AbstractTemplateProxy$ImplData;
       4: checkcast     #4                  // class org/apache/hadoop/hbase/tmpl/regionserver/RSStatusTmpl$ImplData
       7: areturn

  public final org.apache.hadoop.hbase.tmpl.regionserver.RSStatusTmpl setBcn(java.lang.String);
    Code:
       0: aload_0
       1: invokevirtual #7                  // Method getImplData:()Lorg/apache/hadoop/hbase/tmpl/regionserver/RSStatusTmpl$ImplData;
       4: aload_1
       5: invokevirtual #8                  // Method org/apache/hadoop/hbase/tmpl/regionserver/RSStatusTmpl$ImplData.setBcn:(Ljava/lang/String;)V
       8: aload_0
       9: areturn

  public final org.apache.hadoop.hbase.tmpl.regionserver.RSStatusTmpl setBcv(java.lang.String);
    Code:
       0: aload_0
       1: invokevirtual #7                  // Method getImplData:()Lorg/apache/hadoop/hbase/tmpl/regionserver/RSStatusTmpl$ImplData;
       4: aload_1
       5: invokevirtual #9                  // Method org/apache/hadoop/hbase/tmpl/regionserver/RSStatusTmpl$ImplData.setBcv:(Ljava/lang/String;)V
       8: aload_0
       9: areturn

  public final org.apache.hadoop.hbase.tmpl.regionserver.RSStatusTmpl setFilter(java.lang.String);
    Code:
       0: aload_0
       1: invokevirtual #7                  // Method getImplData:()Lorg/apache/hadoop/hbase/tmpl/regionserver/RSStatusTmpl$ImplData;
       4: aload_1
       5: invokevirtual #10                 // Method org/apache/hadoop/hbase/tmpl/regionserver/RSStatusTmpl$ImplData.setFilter:(Ljava/lang/String;)V
       8: aload_0
       9: areturn

  public final org.apache.hadoop.hbase.tmpl.regionserver.RSStatusTmpl setFormat(java.lang.String);
    Code:
       0: aload_0
       1: invokevirtual #7                  // Method getImplData:()Lorg/apache/hadoop/hbase/tmpl/regionserver/RSStatusTmpl$ImplData;
       4: aload_1
       5: invokevirtual #11                 // Method org/apache/hadoop/hbase/tmpl/regionserver/RSStatusTmpl$ImplData.setFormat:(Ljava/lang/String;)V
       8: aload_0
       9: areturn

  public org.jamon.AbstractTemplateImpl constructImpl(java.lang.Class<? extends org.jamon.AbstractTemplateImpl>);
    Code:
       0: aload_1
       1: iconst_2
       2: anewarray     #12                 // class java/lang/Class
       5: dup
       6: iconst_0
       7: ldc           #13                 // class org/jamon/TemplateManager
       9: aastore
      10: dup
      11: iconst_1
      12: ldc           #4                  // class org/apache/hadoop/hbase/tmpl/regionserver/RSStatusTmpl$ImplData
      14: aastore
      15: invokevirtual #14                 // Method java/lang/Class.getConstructor:([Ljava/lang/Class;)Ljava/lang/reflect/Constructor;
      18: iconst_2
      19: anewarray     #15                 // class java/lang/Object
      22: dup
      23: iconst_0
      24: aload_0
      25: invokevirtual #16                 // Method getTemplateManager:()Lorg/jamon/TemplateManager;
      28: aastore
      29: dup
      30: iconst_1
      31: aload_0
      32: invokevirtual #7                  // Method getImplData:()Lorg/apache/hadoop/hbase/tmpl/regionserver/RSStatusTmpl$ImplData;
      35: aastore
      36: invokevirtual #17                 // Method java/lang/reflect/Constructor.newInstance:([Ljava/lang/Object;)Ljava/lang/Object;
      39: checkcast     #18                 // class org/jamon/AbstractTemplateImpl
      42: areturn
      43: astore_2
      44: aload_2
      45: athrow
      46: astore_2
      47: new           #19                 // class java/lang/RuntimeException
      50: dup
      51: aload_2
      52: invokespecial #21                 // Method java/lang/RuntimeException."<init>":(Ljava/lang/Throwable;)V
      55: athrow
    Exception table:
       from    to  target type
           0    42    43   Class java/lang/RuntimeException
           0    42    46   Class java/lang/Exception

  protected org.jamon.AbstractTemplateImpl constructImpl();
    Code:
       0: new           #22                 // class org/apache/hadoop/hbase/tmpl/regionserver/RSStatusTmplImpl
       3: dup
       4: aload_0
       5: invokevirtual #16                 // Method getTemplateManager:()Lorg/jamon/TemplateManager;
       8: aload_0
       9: invokevirtual #7                  // Method getImplData:()Lorg/apache/hadoop/hbase/tmpl/regionserver/RSStatusTmpl$ImplData;
      12: invokespecial #23                 // Method org/apache/hadoop/hbase/tmpl/regionserver/RSStatusTmplImpl."<init>":(Lorg/jamon/TemplateManager;Lorg/apache/hadoop/hbase/tmpl/regionserver/RSStatusTmpl$ImplData;)V
      15: areturn

  public org.jamon.Renderer makeRenderer(org.apache.hadoop.hbase.regionserver.HRegionServer);
    Code:
       0: new           #24                 // class org/apache/hadoop/hbase/tmpl/regionserver/RSStatusTmpl$1
       3: dup
       4: aload_0
       5: aload_1
       6: invokespecial #25                 // Method org/apache/hadoop/hbase/tmpl/regionserver/RSStatusTmpl$1."<init>":(Lorg/apache/hadoop/hbase/tmpl/regionserver/RSStatusTmpl;Lorg/apache/hadoop/hbase/regionserver/HRegionServer;)V
       9: areturn

  public void render(java.io.Writer, org.apache.hadoop.hbase.regionserver.HRegionServer) throws java.io.IOException;
    Code:
       0: aload_0
       1: aload_1
       2: aload_2
       3: invokevirtual #26                 // Method renderNoFlush:(Ljava/io/Writer;Lorg/apache/hadoop/hbase/regionserver/HRegionServer;)V
       6: aload_1
       7: invokevirtual #27                 // Method java/io/Writer.flush:()V
      10: return

  public void renderNoFlush(java.io.Writer, org.apache.hadoop.hbase.regionserver.HRegionServer) throws java.io.IOException;
    Code:
       0: aload_0
       1: invokevirtual #7                  // Method getImplData:()Lorg/apache/hadoop/hbase/tmpl/regionserver/RSStatusTmpl$ImplData;
       4: astore_3
       5: aload_3
       6: aload_2
       7: invokevirtual #28                 // Method org/apache/hadoop/hbase/tmpl/regionserver/RSStatusTmpl$ImplData.setRegionServer:(Lorg/apache/hadoop/hbase/regionserver/HRegionServer;)V
      10: aload_0
      11: invokevirtual #16                 // Method getTemplateManager:()Lorg/jamon/TemplateManager;
      14: aload_0
      15: invokeinterface #29,  2           // InterfaceMethod org/jamon/TemplateManager.constructImpl:(Lorg/jamon/AbstractTemplateProxy;)Lorg/jamon/AbstractTemplateProxy$Intf;
      20: checkcast     #30                 // class org/apache/hadoop/hbase/tmpl/regionserver/RSStatusTmpl$Intf
      23: astore        4
      25: aload         4
      27: aload_1
      28: invokeinterface #31,  2           // InterfaceMethod org/apache/hadoop/hbase/tmpl/regionserver/RSStatusTmpl$Intf.renderNoFlush:(Ljava/io/Writer;)V
      33: aload_0
      34: invokevirtual #32                 // Method reset:()V
      37: return

  public org.jamon.AbstractTemplateProxy$ImplData getImplData();
    Code:
       0: aload_0
       1: invokevirtual #7                  // Method getImplData:()Lorg/apache/hadoop/hbase/tmpl/regionserver/RSStatusTmpl$ImplData;
       4: areturn
}
