Compiled from "RSStatusTmpl.java"
public class org.apache.hadoop.hbase.tmpl.regionserver.RSStatusTmpl$ImplData extends org.jamon.AbstractTemplateProxy$ImplData {
  public org.apache.hadoop.hbase.tmpl.regionserver.RSStatusTmpl$ImplData();
    Code:
       0: aload_0
       1: invokespecial #1                  // Method org/jamon/AbstractTemplateProxy$ImplData."<init>":()V
       4: return

  public void setRegionServer(org.apache.hadoop.hbase.regionserver.HRegionServer);
    Code:
       0: aload_0
       1: aload_1
       2: putfield      #2                  // Field m_regionServer:Lorg/apache/hadoop/hbase/regionserver/HRegionServer;
       5: return

  public org.apache.hadoop.hbase.regionserver.HRegionServer getRegionServer();
    Code:
       0: aload_0
       1: getfield      #2                  // Field m_regionServer:Lorg/apache/hadoop/hbase/regionserver/HRegionServer;
       4: areturn

  public void setBcn(java.lang.String);
    Code:
       0: aload_0
       1: aload_1
       2: putfield      #3                  // Field m_bcn:Ljava/lang/String;
       5: aload_0
       6: iconst_1
       7: putfield      #4                  // Field m_bcn__IsNotDefault:Z
      10: return

  public java.lang.String getBcn();
    Code:
       0: aload_0
       1: getfield      #3                  // Field m_bcn:Ljava/lang/String;
       4: areturn

  public boolean getBcn__IsNotDefault();
    Code:
       0: aload_0
       1: getfield      #4                  // Field m_bcn__IsNotDefault:Z
       4: ireturn

  public void setBcv(java.lang.String);
    Code:
       0: aload_0
       1: aload_1
       2: putfield      #5                  // Field m_bcv:Ljava/lang/String;
       5: aload_0
       6: iconst_1
       7: putfield      #6                  // Field m_bcv__IsNotDefault:Z
      10: return

  public java.lang.String getBcv();
    Code:
       0: aload_0
       1: getfield      #5                  // Field m_bcv:Ljava/lang/String;
       4: areturn

  public boolean getBcv__IsNotDefault();
    Code:
       0: aload_0
       1: getfield      #6                  // Field m_bcv__IsNotDefault:Z
       4: ireturn

  public void setFilter(java.lang.String);
    Code:
       0: aload_0
       1: aload_1
       2: putfield      #7                  // Field m_filter:Ljava/lang/String;
       5: aload_0
       6: iconst_1
       7: putfield      #8                  // Field m_filter__IsNotDefault:Z
      10: return

  public java.lang.String getFilter();
    Code:
       0: aload_0
       1: getfield      #7                  // Field m_filter:Ljava/lang/String;
       4: areturn

  public boolean getFilter__IsNotDefault();
    Code:
       0: aload_0
       1: getfield      #8                  // Field m_filter__IsNotDefault:Z
       4: ireturn

  public void setFormat(java.lang.String);
    Code:
       0: aload_0
       1: aload_1
       2: putfield      #9                  // Field m_format:Ljava/lang/String;
       5: aload_0
       6: iconst_1
       7: putfield      #10                 // Field m_format__IsNotDefault:Z
      10: return

  public java.lang.String getFormat();
    Code:
       0: aload_0
       1: getfield      #9                  // Field m_format:Ljava/lang/String;
       4: areturn

  public boolean getFormat__IsNotDefault();
    Code:
       0: aload_0
       1: getfield      #10                 // Field m_format__IsNotDefault:Z
       4: ireturn
}
