Compiled from "RSStatusServlet.java"
public class org.apache.hadoop.hbase.regionserver.RSStatusServlet extends javax.servlet.http.HttpServlet {
  static final boolean $assertionsDisabled;

  public org.apache.hadoop.hbase.regionserver.RSStatusServlet();
    Code:
       0: aload_0
       1: invokespecial #1                  // Method javax/servlet/http/HttpServlet."<init>":()V
       4: return

  protected void doGet(javax.servlet.http.HttpServletRequest, javax.servlet.http.HttpServletResponse) throws javax.servlet.ServletException, java.io.IOException;
    Code:
       0: aload_0
       1: invokevirtual #2                  // Method getServletContext:()Ljavax/servlet/ServletContext;
       4: ldc           #4                  // String regionserver
       6: invokeinterface #5,  2            // InterfaceMethod javax/servlet/ServletContext.getAttribute:(Ljava/lang/String;)Ljava/lang/Object;
      11: checkcast     #3                  // class org/apache/hadoop/hbase/regionserver/HRegionServer
      14: astore_3
      15: getstatic     #6                  // Field $assertionsDisabled:Z
      18: ifne          35
      21: aload_3
      22: ifnonnull     35
      25: new           #7                  // class java/lang/AssertionError
      28: dup
      29: ldc           #8                  // String No RS in context!
      31: invokespecial #9                  // Method java/lang/AssertionError."<init>":(Ljava/lang/Object;)V
      34: athrow
      35: aload_2
      36: ldc           #10                 // String text/html
      38: invokeinterface #11,  2           // InterfaceMethod javax/servlet/http/HttpServletResponse.setContentType:(Ljava/lang/String;)V
      43: aload_3
      44: invokevirtual #12                 // Method org/apache/hadoop/hbase/regionserver/HRegionServer.isOnline:()Z
      47: ifne          71
      50: aload_2
      51: invokeinterface #13,  1           // InterfaceMethod javax/servlet/http/HttpServletResponse.getWriter:()Ljava/io/PrintWriter;
      56: ldc           #14                 // String The RegionServer is initializing!
      58: invokevirtual #15                 // Method java/io/PrintWriter.write:(Ljava/lang/String;)V
      61: aload_2
      62: invokeinterface #13,  1           // InterfaceMethod javax/servlet/http/HttpServletResponse.getWriter:()Ljava/io/PrintWriter;
      67: invokevirtual #16                 // Method java/io/PrintWriter.close:()V
      70: return
      71: new           #17                 // class org/apache/hadoop/hbase/tmpl/regionserver/RSStatusTmpl
      74: dup
      75: invokespecial #18                 // Method org/apache/hadoop/hbase/tmpl/regionserver/RSStatusTmpl."<init>":()V
      78: astore        4
      80: aload_1
      81: ldc           #19                 // String format
      83: invokeinterface #20,  2           // InterfaceMethod javax/servlet/http/HttpServletRequest.getParameter:(Ljava/lang/String;)Ljava/lang/String;
      88: ifnull        105
      91: aload         4
      93: aload_1
      94: ldc           #19                 // String format
      96: invokeinterface #20,  2           // InterfaceMethod javax/servlet/http/HttpServletRequest.getParameter:(Ljava/lang/String;)Ljava/lang/String;
     101: invokevirtual #21                 // Method org/apache/hadoop/hbase/tmpl/regionserver/RSStatusTmpl.setFormat:(Ljava/lang/String;)Lorg/apache/hadoop/hbase/tmpl/regionserver/RSStatusTmpl;
     104: pop
     105: aload_1
     106: ldc           #22                 // String filter
     108: invokeinterface #20,  2           // InterfaceMethod javax/servlet/http/HttpServletRequest.getParameter:(Ljava/lang/String;)Ljava/lang/String;
     113: ifnull        130
     116: aload         4
     118: aload_1
     119: ldc           #22                 // String filter
     121: invokeinterface #20,  2           // InterfaceMethod javax/servlet/http/HttpServletRequest.getParameter:(Ljava/lang/String;)Ljava/lang/String;
     126: invokevirtual #23                 // Method org/apache/hadoop/hbase/tmpl/regionserver/RSStatusTmpl.setFilter:(Ljava/lang/String;)Lorg/apache/hadoop/hbase/tmpl/regionserver/RSStatusTmpl;
     129: pop
     130: aload_1
     131: ldc           #24                 // String bcn
     133: invokeinterface #20,  2           // InterfaceMethod javax/servlet/http/HttpServletRequest.getParameter:(Ljava/lang/String;)Ljava/lang/String;
     138: ifnull        155
     141: aload         4
     143: aload_1
     144: ldc           #24                 // String bcn
     146: invokeinterface #20,  2           // InterfaceMethod javax/servlet/http/HttpServletRequest.getParameter:(Ljava/lang/String;)Ljava/lang/String;
     151: invokevirtual #25                 // Method org/apache/hadoop/hbase/tmpl/regionserver/RSStatusTmpl.setBcn:(Ljava/lang/String;)Lorg/apache/hadoop/hbase/tmpl/regionserver/RSStatusTmpl;
     154: pop
     155: aload_1
     156: ldc           #26                 // String bcv
     158: invokeinterface #20,  2           // InterfaceMethod javax/servlet/http/HttpServletRequest.getParameter:(Ljava/lang/String;)Ljava/lang/String;
     163: ifnull        180
     166: aload         4
     168: aload_1
     169: ldc           #26                 // String bcv
     171: invokeinterface #20,  2           // InterfaceMethod javax/servlet/http/HttpServletRequest.getParameter:(Ljava/lang/String;)Ljava/lang/String;
     176: invokevirtual #27                 // Method org/apache/hadoop/hbase/tmpl/regionserver/RSStatusTmpl.setBcv:(Ljava/lang/String;)Lorg/apache/hadoop/hbase/tmpl/regionserver/RSStatusTmpl;
     179: pop
     180: aload         4
     182: aload_2
     183: invokeinterface #13,  1           // InterfaceMethod javax/servlet/http/HttpServletResponse.getWriter:()Ljava/io/PrintWriter;
     188: aload_3
     189: invokevirtual #28                 // Method org/apache/hadoop/hbase/tmpl/regionserver/RSStatusTmpl.render:(Ljava/io/Writer;Lorg/apache/hadoop/hbase/regionserver/HRegionServer;)V
     192: return

  static {};
    Code:
       0: ldc           #29                 // class org/apache/hadoop/hbase/regionserver/RSStatusServlet
       2: invokevirtual #30                 // Method java/lang/Class.desiredAssertionStatus:()Z
       5: ifne          12
       8: iconst_1
       9: goto          13
      12: iconst_0
      13: putstatic     #6                  // Field $assertionsDisabled:Z
      16: return
}
