Compiled from "RuntimeFailConstraint.java"
public class org.apache.hadoop.hbase.constraint.RuntimeFailConstraint extends org.apache.hadoop.hbase.constraint.BaseConstraint {
  public org.apache.hadoop.hbase.constraint.RuntimeFailConstraint();
    Code:
       0: aload_0
       1: invokespecial #1                  // Method org/apache/hadoop/hbase/constraint/BaseConstraint."<init>":()V
       4: return

  public void check(org.apache.hadoop.hbase.client.Put) throws org.apache.hadoop.hbase.constraint.ConstraintException;
    Code:
       0: new           #2                  // class java/lang/RuntimeException
       3: dup
       4: ldc           #3                  // String RuntimeFailConstraint always throws a runtime exception
       6: invokespecial #4                  // Method java/lang/RuntimeException."<init>":(Ljava/lang/String;)V
       9: athrow
}
