Compiled from "SaslChallengeDecoder.java"
public class org.apache.hadoop.hbase.security.SaslChallengeDecoder extends org.apache.hbase.thirdparty.io.netty.handler.codec.ByteToMessageDecoder {
  public org.apache.hadoop.hbase.security.SaslChallengeDecoder();
    Code:
       0: aload_0
       1: invokespecial #1                  // Method org/apache/hbase/thirdparty/io/netty/handler/codec/ByteToMessageDecoder."<init>":()V
       4: return

  protected void decode(org.apache.hbase.thirdparty.io.netty.channel.ChannelHandlerContext, org.apache.hbase.thirdparty.io.netty.buffer.ByteBuf, java.util.List<java.lang.Object>) throws java.lang.Exception;
    Code:
       0: aload_2
       1: invokevirtual #24                 // Method org/apache/hbase/thirdparty/io/netty/buffer/ByteBuf.readableBytes:()I
       4: istore        4
       6: iload         4
       8: iconst_4
       9: if_icmpge     13
      12: return
      13: aload_2
      14: invokevirtual #25                 // Method org/apache/hbase/thirdparty/io/netty/buffer/ByteBuf.readerIndex:()I
      17: istore        5
      19: aload_2
      20: iload         5
      22: invokevirtual #2                  // Method org/apache/hbase/thirdparty/io/netty/buffer/ByteBuf.getInt:(I)I
      25: istore        6
      27: iload         6
      29: getstatic     #26                 // Field org/apache/hadoop/hbase/security/SaslStatus.SUCCESS:Lorg/apache/hadoop/hbase/security/SaslStatus;
      32: getfield      #27                 // Field org/apache/hadoop/hbase/security/SaslStatus.state:I
      35: if_icmpne     70
      38: aload_0
      39: aload_2
      40: iload         5
      42: iconst_4
      43: iadd
      44: iload         4
      46: iconst_4
      47: isub
      48: invokespecial #28                 // Method tryDecodeChallenge:(Lorg/apache/hbase/thirdparty/io/netty/buffer/ByteBuf;II)Lorg/apache/hbase/thirdparty/io/netty/buffer/ByteBuf;
      51: astore        7
      53: aload         7
      55: ifnull        67
      58: aload_3
      59: aload         7
      61: invokeinterface #29,  2           // InterfaceMethod java/util/List.add:(Ljava/lang/Object;)Z
      66: pop
      67: goto          83
      70: aload_0
      71: aload_2
      72: iload         5
      74: iconst_4
      75: iadd
      76: iload         4
      78: iconst_4
      79: isub
      80: invokespecial #30                 // Method tryDecodeError:(Lorg/apache/hbase/thirdparty/io/netty/buffer/ByteBuf;II)V
      83: return
}
