Compiled from "ScopeWALEntryFilter.java"
class org.apache.hadoop.hbase.replication.ScopeWALEntryFilter$1 implements org.apache.hbase.thirdparty.com.google.common.base.Predicate<byte[]> {
  final java.util.NavigableMap val$scopes;

  final org.apache.hadoop.hbase.replication.ScopeWALEntryFilter this$0;

  org.apache.hadoop.hbase.replication.ScopeWALEntryFilter$1(org.apache.hadoop.hbase.replication.ScopeWALEntryFilter, java.util.NavigableMap);
    Code:
       0: aload_0
       1: aload_1
       2: putfield      #1                  // Field this$0:Lorg/apache/hadoop/hbase/replication/ScopeWALEntryFilter;
       5: aload_0
       6: aload_2
       7: putfield      #2                  // Field val$scopes:Ljava/util/NavigableMap;
      10: aload_0
      11: invokespecial #3                  // Method java/lang/Object."<init>":()V
      14: return

  public boolean apply(byte[]);
    Code:
       0: aload_0
       1: getfield      #1                  // Field this$0:Lorg/apache/hadoop/hbase/replication/ScopeWALEntryFilter;
       4: aload_0
       5: getfield      #2                  // Field val$scopes:Ljava/util/NavigableMap;
       8: aload_1
       9: invokestatic  #4                  // Method org/apache/hadoop/hbase/replication/ScopeWALEntryFilter.access$000:(Lorg/apache/hadoop/hbase/replication/ScopeWALEntryFilter;Ljava/util/NavigableMap;[B)Z
      12: ifne          19
      15: iconst_1
      16: goto          20
      19: iconst_0
      20: ireturn

  public boolean apply(java.lang.Object);
    Code:
       0: aload_0
       1: aload_1
       2: checkcast     #5                  // class "[B"
       5: invokevirtual #6                  // Method apply:([B)Z
       8: ireturn
}
