Compiled from "SecureAsyncProtobufLogWriter.java"
public class org.apache.hadoop.hbase.regionserver.wal.SecureAsyncProtobufLogWriter extends org.apache.hadoop.hbase.regionserver.wal.AsyncProtobufLogWriter {
  public org.apache.hadoop.hbase.regionserver.wal.SecureAsyncProtobufLogWriter(org.apache.hbase.thirdparty.io.netty.channel.EventLoopGroup, java.lang.Class<? extends org.apache.hbase.thirdparty.io.netty.channel.Channel>);
    Code:
       0: aload_0
       1: aload_1
       2: aload_2
       3: invokespecial #1                  // Method org/apache/hadoop/hbase/regionserver/wal/AsyncProtobufLogWriter."<init>":(Lorg/apache/hbase/thirdparty/io/netty/channel/EventLoopGroup;Ljava/lang/Class;)V
       6: aload_0
       7: aconst_null
       8: putfield      #2                  // Field encryptor:Lorg/apache/hadoop/hbase/io/crypto/Encryptor;
      11: return

  protected java.lang.String getWriterClassName();
    Code:
       0: ldc           #3                  // String SecureProtobufLogWriter
       2: areturn

  protected org.apache.hadoop.hbase.shaded.protobuf.generated.WALProtos$WALHeader buildWALHeader(org.apache.hadoop.conf.Configuration, org.apache.hadoop.hbase.shaded.protobuf.generated.WALProtos$WALHeader$Builder) throws java.io.IOException;
    Code:
       0: aload_0
       1: aload_1
       2: aload_2
       3: invokespecial #4                  // Method org/apache/hadoop/hbase/regionserver/wal/AsyncProtobufLogWriter.buildSecureWALHeader:(Lorg/apache/hadoop/conf/Configuration;Lorg/apache/hadoop/hbase/shaded/protobuf/generated/WALProtos$WALHeader$Builder;)Lorg/apache/hadoop/hbase/shaded/protobuf/generated/WALProtos$WALHeader;
       6: areturn

  protected void setEncryptor(org.apache.hadoop.hbase.io.crypto.Encryptor);
    Code:
       0: aload_0
       1: aload_1
       2: putfield      #2                  // Field encryptor:Lorg/apache/hadoop/hbase/io/crypto/Encryptor;
       5: return

  protected void initAfterHeader(boolean) throws java.io.IOException;
    Code:
       0: aload_0
       1: iload_1
       2: aload_0
       3: getfield      #2                  // Field encryptor:Lorg/apache/hadoop/hbase/io/crypto/Encryptor;
       6: invokespecial #5                  // Method org/apache/hadoop/hbase/regionserver/wal/AsyncProtobufLogWriter.secureInitAfterHeader:(ZLorg/apache/hadoop/hbase/io/crypto/Encryptor;)V
       9: return
}
