Compiled from "SecureWALCellCodec.java"
public class org.apache.hadoop.hbase.regionserver.wal.SecureWALCellCodec extends org.apache.hadoop.hbase.regionserver.wal.WALCellCodec {
  public org.apache.hadoop.hbase.regionserver.wal.SecureWALCellCodec(org.apache.hadoop.conf.Configuration, org.apache.hadoop.hbase.regionserver.wal.CompressionContext);
    Code:
       0: aload_0
       1: aload_1
       2: aload_2
       3: invokespecial #1                  // Method org/apache/hadoop/hbase/regionserver/wal/WALCellCodec."<init>":(Lorg/apache/hadoop/conf/Configuration;Lorg/apache/hadoop/hbase/regionserver/wal/CompressionContext;)V
       6: return

  public org.apache.hadoop.hbase.regionserver.wal.SecureWALCellCodec(org.apache.hadoop.conf.Configuration, org.apache.hadoop.hbase.io.crypto.Encryptor);
    Code:
       0: aload_0
       1: aload_1
       2: aconst_null
       3: invokespecial #1                  // Method org/apache/hadoop/hbase/regionserver/wal/WALCellCodec."<init>":(Lorg/apache/hadoop/conf/Configuration;Lorg/apache/hadoop/hbase/regionserver/wal/CompressionContext;)V
       6: aload_0
       7: aload_2
       8: putfield      #2                  // Field encryptor:Lorg/apache/hadoop/hbase/io/crypto/Encryptor;
      11: return

  public org.apache.hadoop.hbase.regionserver.wal.SecureWALCellCodec(org.apache.hadoop.conf.Configuration, org.apache.hadoop.hbase.io.crypto.Decryptor);
    Code:
       0: aload_0
       1: aload_1
       2: aconst_null
       3: invokespecial #1                  // Method org/apache/hadoop/hbase/regionserver/wal/WALCellCodec."<init>":(Lorg/apache/hadoop/conf/Configuration;Lorg/apache/hadoop/hbase/regionserver/wal/CompressionContext;)V
       6: aload_0
       7: aload_2
       8: putfield      #3                  // Field decryptor:Lorg/apache/hadoop/hbase/io/crypto/Decryptor;
      11: return

  public org.apache.hadoop.hbase.codec.Codec$Decoder getDecoder(java.io.InputStream);
    Code:
       0: new           #4                  // class org/apache/hadoop/hbase/regionserver/wal/SecureWALCellCodec$EncryptedKvDecoder
       3: dup
       4: aload_1
       5: aload_0
       6: getfield      #3                  // Field decryptor:Lorg/apache/hadoop/hbase/io/crypto/Decryptor;
       9: invokespecial #5                  // Method org/apache/hadoop/hbase/regionserver/wal/SecureWALCellCodec$EncryptedKvDecoder."<init>":(Ljava/io/InputStream;Lorg/apache/hadoop/hbase/io/crypto/Decryptor;)V
      12: areturn

  public org.apache.hadoop.hbase.codec.Codec$Encoder getEncoder(java.io.OutputStream);
    Code:
       0: new           #6                  // class org/apache/hadoop/hbase/regionserver/wal/SecureWALCellCodec$EncryptedKvEncoder
       3: dup
       4: aload_1
       5: aload_0
       6: getfield      #2                  // Field encryptor:Lorg/apache/hadoop/hbase/io/crypto/Encryptor;
       9: invokespecial #7                  // Method org/apache/hadoop/hbase/regionserver/wal/SecureWALCellCodec$EncryptedKvEncoder."<init>":(Ljava/io/OutputStream;Lorg/apache/hadoop/hbase/io/crypto/Encryptor;)V
      12: areturn

  public static org.apache.hadoop.hbase.regionserver.wal.WALCellCodec getCodec(org.apache.hadoop.conf.Configuration, org.apache.hadoop.hbase.io.crypto.Encryptor);
    Code:
       0: new           #8                  // class org/apache/hadoop/hbase/regionserver/wal/SecureWALCellCodec
       3: dup
       4: aload_0
       5: aload_1
       6: invokespecial #9                  // Method "<init>":(Lorg/apache/hadoop/conf/Configuration;Lorg/apache/hadoop/hbase/io/crypto/Encryptor;)V
       9: areturn

  public static org.apache.hadoop.hbase.regionserver.wal.WALCellCodec getCodec(org.apache.hadoop.conf.Configuration, org.apache.hadoop.hbase.io.crypto.Decryptor);
    Code:
       0: new           #8                  // class org/apache/hadoop/hbase/regionserver/wal/SecureWALCellCodec
       3: dup
       4: aload_0
       5: aload_1
       6: invokespecial #10                 // Method "<init>":(Lorg/apache/hadoop/conf/Configuration;Lorg/apache/hadoop/hbase/io/crypto/Decryptor;)V
       9: areturn
}
