Compiled from "SendBufSizePredictor.java"
class org.apache.hadoop.hbase.io.asyncfs.SendBufSizePredictor {
  org.apache.hadoop.hbase.io.asyncfs.SendBufSizePredictor();
    Code:
       0: aload_0
       1: invokespecial #1                  // Method java/lang/Object."<init>":()V
       4: aload_0
       5: sipush        4096
       8: putfield      #2                  // Field capacity:I
      11: return

  int initialSize();
    Code:
       0: aload_0
       1: getfield      #2                  // Field capacity:I
       4: ireturn

  int guess(int);
    Code:
       0: iload_1
       1: aload_0
       2: getfield      #2                  // Field capacity:I
       5: if_icmple     32
       8: aload_0
       9: getfield      #2                  // Field capacity:I
      12: iconst_1
      13: ishl
      14: ldc           #4                  // int 134217728
      16: if_icmpgt     52
      19: aload_0
      20: aload_0
      21: getfield      #2                  // Field capacity:I
      24: iconst_1
      25: ishl
      26: putfield      #2                  // Field capacity:I
      29: goto          52
      32: aload_0
      33: getfield      #2                  // Field capacity:I
      36: iconst_1
      37: ishr
      38: iload_1
      39: if_icmplt     52
      42: aload_0
      43: aload_0
      44: getfield      #2                  // Field capacity:I
      47: iconst_1
      48: ishr
      49: putfield      #2                  // Field capacity:I
      52: aload_0
      53: getfield      #2                  // Field capacity:I
      56: ireturn
}
