Compiled from "ServerProcedureInterface.java"
public final class org.apache.hadoop.hbase.master.procedure.ServerProcedureInterface$ServerOperationType extends java.lang.Enum<org.apache.hadoop.hbase.master.procedure.ServerProcedureInterface$ServerOperationType> {
  public static final org.apache.hadoop.hbase.master.procedure.ServerProcedureInterface$ServerOperationType CRASH_HANDLER;

  public static final org.apache.hadoop.hbase.master.procedure.ServerProcedureInterface$ServerOperationType SWITCH_RPC_THROTTLE;

  public static final org.apache.hadoop.hbase.master.procedure.ServerProcedureInterface$ServerOperationType SPLIT_WAL;

  public static final org.apache.hadoop.hbase.master.procedure.ServerProcedureInterface$ServerOperationType SPLIT_WAL_REMOTE;

  public static org.apache.hadoop.hbase.master.procedure.ServerProcedureInterface$ServerOperationType[] values();
    Code:
       0: getstatic     #1                  // Field $VALUES:[Lorg/apache/hadoop/hbase/master/procedure/ServerProcedureInterface$ServerOperationType;
       3: invokevirtual #2                  // Method "[Lorg/apache/hadoop/hbase/master/procedure/ServerProcedureInterface$ServerOperationType;".clone:()Ljava/lang/Object;
       6: checkcast     #3                  // class "[Lorg/apache/hadoop/hbase/master/procedure/ServerProcedureInterface$ServerOperationType;"
       9: areturn

  public static org.apache.hadoop.hbase.master.procedure.ServerProcedureInterface$ServerOperationType valueOf(java.lang.String);
    Code:
       0: ldc           #4                  // class org/apache/hadoop/hbase/master/procedure/ServerProcedureInterface$ServerOperationType
       2: aload_0
       3: invokestatic  #5                  // Method java/lang/Enum.valueOf:(Ljava/lang/Class;Ljava/lang/String;)Ljava/lang/Enum;
       6: checkcast     #4                  // class org/apache/hadoop/hbase/master/procedure/ServerProcedureInterface$ServerOperationType
       9: areturn

  static {};
    Code:
       0: new           #4                  // class org/apache/hadoop/hbase/master/procedure/ServerProcedureInterface$ServerOperationType
       3: dup
       4: ldc           #7                  // String CRASH_HANDLER
       6: iconst_0
       7: invokespecial #8                  // Method "<init>":(Ljava/lang/String;I)V
      10: putstatic     #9                  // Field CRASH_HANDLER:Lorg/apache/hadoop/hbase/master/procedure/ServerProcedureInterface$ServerOperationType;
      13: new           #4                  // class org/apache/hadoop/hbase/master/procedure/ServerProcedureInterface$ServerOperationType
      16: dup
      17: ldc           #10                 // String SWITCH_RPC_THROTTLE
      19: iconst_1
      20: invokespecial #8                  // Method "<init>":(Ljava/lang/String;I)V
      23: putstatic     #11                 // Field SWITCH_RPC_THROTTLE:Lorg/apache/hadoop/hbase/master/procedure/ServerProcedureInterface$ServerOperationType;
      26: new           #4                  // class org/apache/hadoop/hbase/master/procedure/ServerProcedureInterface$ServerOperationType
      29: dup
      30: ldc           #12                 // String SPLIT_WAL
      32: iconst_2
      33: invokespecial #8                  // Method "<init>":(Ljava/lang/String;I)V
      36: putstatic     #13                 // Field SPLIT_WAL:Lorg/apache/hadoop/hbase/master/procedure/ServerProcedureInterface$ServerOperationType;
      39: new           #4                  // class org/apache/hadoop/hbase/master/procedure/ServerProcedureInterface$ServerOperationType
      42: dup
      43: ldc           #14                 // String SPLIT_WAL_REMOTE
      45: iconst_3
      46: invokespecial #8                  // Method "<init>":(Ljava/lang/String;I)V
      49: putstatic     #15                 // Field SPLIT_WAL_REMOTE:Lorg/apache/hadoop/hbase/master/procedure/ServerProcedureInterface$ServerOperationType;
      52: iconst_4
      53: anewarray     #4                  // class org/apache/hadoop/hbase/master/procedure/ServerProcedureInterface$ServerOperationType
      56: dup
      57: iconst_0
      58: getstatic     #9                  // Field CRASH_HANDLER:Lorg/apache/hadoop/hbase/master/procedure/ServerProcedureInterface$ServerOperationType;
      61: aastore
      62: dup
      63: iconst_1
      64: getstatic     #11                 // Field SWITCH_RPC_THROTTLE:Lorg/apache/hadoop/hbase/master/procedure/ServerProcedureInterface$ServerOperationType;
      67: aastore
      68: dup
      69: iconst_2
      70: getstatic     #13                 // Field SPLIT_WAL:Lorg/apache/hadoop/hbase/master/procedure/ServerProcedureInterface$ServerOperationType;
      73: aastore
      74: dup
      75: iconst_3
      76: getstatic     #15                 // Field SPLIT_WAL_REMOTE:Lorg/apache/hadoop/hbase/master/procedure/ServerProcedureInterface$ServerOperationType;
      79: aastore
      80: putstatic     #1                  // Field $VALUES:[Lorg/apache/hadoop/hbase/master/procedure/ServerProcedureInterface$ServerOperationType;
      83: return
}
