Compiled from "ServerStateNode.java"
public class org.apache.hadoop.hbase.master.assignment.ServerStateNode implements java.lang.Comparable<org.apache.hadoop.hbase.master.assignment.ServerStateNode> {
  public org.apache.hadoop.hbase.master.assignment.ServerStateNode(org.apache.hadoop.hbase.ServerName);
    Code:
       0: aload_0
       1: invokespecial #1                  // Method java/lang/Object."<init>":()V
       4: aload_0
       5: new           #2                  // class java/util/concurrent/locks/ReentrantReadWriteLock
       8: dup
       9: invokespecial #3                  // Method java/util/concurrent/locks/ReentrantReadWriteLock."<init>":()V
      12: putfield      #4                  // Field lock:Ljava/util/concurrent/locks/ReadWriteLock;
      15: aload_0
      16: getstatic     #5                  // Field org/apache/hadoop/hbase/master/assignment/ServerState.ONLINE:Lorg/apache/hadoop/hbase/master/assignment/ServerState;
      19: putfield      #6                  // Field state:Lorg/apache/hadoop/hbase/master/assignment/ServerState;
      22: aload_0
      23: aload_1
      24: putfield      #7                  // Field serverName:Lorg/apache/hadoop/hbase/ServerName;
      27: aload_0
      28: invokestatic  #8                  // Method java/util/concurrent/ConcurrentHashMap.newKeySet:()Ljava/util/concurrent/ConcurrentHashMap$KeySetView;
      31: putfield      #9                  // Field regions:Ljava/util/Set;
      34: return

  public org.apache.hadoop.hbase.ServerName getServerName();
    Code:
       0: aload_0
       1: getfield      #7                  // Field serverName:Lorg/apache/hadoop/hbase/ServerName;
       4: areturn

  public org.apache.hadoop.hbase.master.assignment.ServerState getState();
    Code:
       0: aload_0
       1: getfield      #6                  // Field state:Lorg/apache/hadoop/hbase/master/assignment/ServerState;
       4: areturn

  public boolean isInState(org.apache.hadoop.hbase.master.assignment.ServerState...);
    Code:
       0: iconst_0
       1: istore_2
       2: aload_1
       3: ifnull        38
       6: iconst_0
       7: istore_3
       8: iload_3
       9: aload_1
      10: arraylength
      11: if_icmpge     38
      14: iload_2
      15: aload_0
      16: getfield      #6                  // Field state:Lorg/apache/hadoop/hbase/master/assignment/ServerState;
      19: aload_1
      20: iload_3
      21: aaload
      22: if_acmpne     29
      25: iconst_1
      26: goto          30
      29: iconst_0
      30: ior
      31: istore_2
      32: iinc          3, 1
      35: goto          8
      38: iload_2
      39: ireturn

  void setState(org.apache.hadoop.hbase.master.assignment.ServerState);
    Code:
       0: aload_0
       1: aload_1
       2: putfield      #6                  // Field state:Lorg/apache/hadoop/hbase/master/assignment/ServerState;
       5: return

  public int getRegionCount();
    Code:
       0: aload_0
       1: getfield      #9                  // Field regions:Ljava/util/Set;
       4: invokeinterface #10,  1           // InterfaceMethod java/util/Set.size:()I
       9: ireturn

  public java.util.List<org.apache.hadoop.hbase.client.RegionInfo> getRegionInfoList();
    Code:
       0: aload_0
       1: getfield      #9                  // Field regions:Ljava/util/Set;
       4: invokeinterface #11,  1           // InterfaceMethod java/util/Set.stream:()Ljava/util/stream/Stream;
       9: invokedynamic #12,  0             // InvokeDynamic #0:apply:()Ljava/util/function/Function;
      14: invokeinterface #13,  2           // InterfaceMethod java/util/stream/Stream.map:(Ljava/util/function/Function;)Ljava/util/stream/Stream;
      19: invokestatic  #14                 // Method java/util/stream/Collectors.toList:()Ljava/util/stream/Collector;
      22: invokeinterface #15,  2           // InterfaceMethod java/util/stream/Stream.collect:(Ljava/util/stream/Collector;)Ljava/lang/Object;
      27: checkcast     #16                 // class java/util/List
      30: areturn

  public java.util.List<org.apache.hadoop.hbase.client.RegionInfo> getSystemRegionInfoList();
    Code:
       0: aload_0
       1: getfield      #9                  // Field regions:Ljava/util/Set;
       4: invokeinterface #11,  1           // InterfaceMethod java/util/Set.stream:()Ljava/util/stream/Stream;
       9: invokedynamic #17,  0             // InvokeDynamic #1:test:()Ljava/util/function/Predicate;
      14: invokeinterface #18,  2           // InterfaceMethod java/util/stream/Stream.filter:(Ljava/util/function/Predicate;)Ljava/util/stream/Stream;
      19: invokedynamic #12,  0             // InvokeDynamic #0:apply:()Ljava/util/function/Function;
      24: invokeinterface #13,  2           // InterfaceMethod java/util/stream/Stream.map:(Ljava/util/function/Function;)Ljava/util/stream/Stream;
      29: invokestatic  #14                 // Method java/util/stream/Collectors.toList:()Ljava/util/stream/Collector;
      32: invokeinterface #15,  2           // InterfaceMethod java/util/stream/Stream.collect:(Ljava/util/stream/Collector;)Ljava/lang/Object;
      37: checkcast     #16                 // class java/util/List
      40: areturn

  public void addRegion(org.apache.hadoop.hbase.master.assignment.RegionStateNode);
    Code:
       0: aload_0
       1: getfield      #9                  // Field regions:Ljava/util/Set;
       4: aload_1
       5: invokeinterface #19,  2           // InterfaceMethod java/util/Set.add:(Ljava/lang/Object;)Z
      10: pop
      11: return

  public void removeRegion(org.apache.hadoop.hbase.master.assignment.RegionStateNode);
    Code:
       0: aload_0
       1: getfield      #9                  // Field regions:Ljava/util/Set;
       4: aload_1
       5: invokeinterface #20,  2           // InterfaceMethod java/util/Set.remove:(Ljava/lang/Object;)Z
      10: pop
      11: return

  public java.util.concurrent.locks.Lock readLock();
    Code:
       0: aload_0
       1: getfield      #4                  // Field lock:Ljava/util/concurrent/locks/ReadWriteLock;
       4: invokeinterface #21,  1           // InterfaceMethod java/util/concurrent/locks/ReadWriteLock.readLock:()Ljava/util/concurrent/locks/Lock;
       9: areturn

  public java.util.concurrent.locks.Lock writeLock();
    Code:
       0: aload_0
       1: getfield      #4                  // Field lock:Ljava/util/concurrent/locks/ReadWriteLock;
       4: invokeinterface #22,  1           // InterfaceMethod java/util/concurrent/locks/ReadWriteLock.writeLock:()Ljava/util/concurrent/locks/Lock;
       9: areturn

  public int compareTo(org.apache.hadoop.hbase.master.assignment.ServerStateNode);
    Code:
       0: aload_0
       1: invokevirtual #23                 // Method getServerName:()Lorg/apache/hadoop/hbase/ServerName;
       4: aload_1
       5: invokevirtual #23                 // Method getServerName:()Lorg/apache/hadoop/hbase/ServerName;
       8: invokevirtual #24                 // Method org/apache/hadoop/hbase/ServerName.compareTo:(Lorg/apache/hadoop/hbase/ServerName;)I
      11: ireturn

  public int hashCode();
    Code:
       0: aload_0
       1: invokevirtual #23                 // Method getServerName:()Lorg/apache/hadoop/hbase/ServerName;
       4: invokevirtual #25                 // Method org/apache/hadoop/hbase/ServerName.hashCode:()I
       7: ireturn

  public boolean equals(java.lang.Object);
    Code:
       0: aload_0
       1: aload_1
       2: if_acmpne     7
       5: iconst_1
       6: ireturn
       7: aload_1
       8: instanceof    #26                 // class org/apache/hadoop/hbase/master/assignment/ServerStateNode
      11: ifne          16
      14: iconst_0
      15: ireturn
      16: aload_0
      17: aload_1
      18: checkcast     #26                 // class org/apache/hadoop/hbase/master/assignment/ServerStateNode
      21: invokevirtual #27                 // Method compareTo:(Lorg/apache/hadoop/hbase/master/assignment/ServerStateNode;)I
      24: ifne          31
      27: iconst_1
      28: goto          32
      31: iconst_0
      32: ireturn

  public java.lang.String toString();
    Code:
       0: ldc           #28                 // String ServerStateNode(%s)
       2: iconst_1
       3: anewarray     #29                 // class java/lang/Object
       6: dup
       7: iconst_0
       8: aload_0
       9: invokevirtual #23                 // Method getServerName:()Lorg/apache/hadoop/hbase/ServerName;
      12: aastore
      13: invokestatic  #30                 // Method java/lang/String.format:(Ljava/lang/String;[Ljava/lang/Object;)Ljava/lang/String;
      16: areturn

  public int compareTo(java.lang.Object);
    Code:
       0: aload_0
       1: aload_1
       2: checkcast     #26                 // class org/apache/hadoop/hbase/master/assignment/ServerStateNode
       5: invokevirtual #27                 // Method compareTo:(Lorg/apache/hadoop/hbase/master/assignment/ServerStateNode;)I
       8: ireturn
}
