Compiled from "ServerRpcController.java"
public class org.apache.hadoop.hbase.ipc.ServerRpcController implements com.google.protobuf.RpcController {
  public org.apache.hadoop.hbase.ipc.ServerRpcController();
    Code:
       0: aload_0
       1: invokespecial #1                  // Method java/lang/Object."<init>":()V
       4: return

  public void reset();
    Code:
       0: aload_0
       1: aconst_null
       2: putfield      #2                  // Field serviceException:Ljava/io/IOException;
       5: aload_0
       6: aconst_null
       7: putfield      #3                  // Field errorMessage:Ljava/lang/String;
      10: return

  public boolean failed();
    Code:
       0: aload_0
       1: invokevirtual #4                  // Method failedOnException:()Z
       4: ifne          14
       7: aload_0
       8: getfield      #3                  // Field errorMessage:Ljava/lang/String;
      11: ifnull        18
      14: iconst_1
      15: goto          19
      18: iconst_0
      19: ireturn

  public java.lang.String errorText();
    Code:
       0: aload_0
       1: getfield      #3                  // Field errorMessage:Ljava/lang/String;
       4: areturn

  public void startCancel();
    Code:
       0: return

  public void setFailed(java.lang.String);
    Code:
       0: aload_0
       1: aload_1
       2: putfield      #3                  // Field errorMessage:Ljava/lang/String;
       5: return

  public boolean isCanceled();
    Code:
       0: iconst_0
       1: ireturn

  public void notifyOnCancel(com.google.protobuf.RpcCallback<java.lang.Object>);
    Code:
       0: return

  public void setFailedOn(java.io.IOException);
    Code:
       0: aload_0
       1: aload_1
       2: putfield      #2                  // Field serviceException:Ljava/io/IOException;
       5: aload_0
       6: aload_1
       7: invokestatic  #5                  // Method org/apache/hadoop/util/StringUtils.stringifyException:(Ljava/lang/Throwable;)Ljava/lang/String;
      10: invokevirtual #6                  // Method setFailed:(Ljava/lang/String;)V
      13: return

  public java.io.IOException getFailedOn();
    Code:
       0: aload_0
       1: getfield      #2                  // Field serviceException:Ljava/io/IOException;
       4: areturn

  public boolean failedOnException();
    Code:
       0: aload_0
       1: getfield      #2                  // Field serviceException:Ljava/io/IOException;
       4: ifnull        11
       7: iconst_1
       8: goto          12
      11: iconst_0
      12: ireturn

  public void checkFailed() throws java.io.IOException;
    Code:
       0: aload_0
       1: invokevirtual #4                  // Method failedOnException:()Z
       4: ifeq          12
       7: aload_0
       8: invokevirtual #7                  // Method getFailedOn:()Ljava/io/IOException;
      11: athrow
      12: return
}
