Compiled from "ServerSideScanMetrics.java"
public class org.apache.hadoop.hbase.client.metrics.ServerSideScanMetrics {
  public static final java.lang.String COUNT_OF_ROWS_SCANNED_KEY_METRIC_NAME;

  public static final java.lang.String COUNT_OF_ROWS_FILTERED_KEY_METRIC_NAME;

  public final java.util.concurrent.atomic.AtomicLong countOfRowsFiltered;

  public final java.util.concurrent.atomic.AtomicLong countOfRowsScanned;

  public org.apache.hadoop.hbase.client.metrics.ServerSideScanMetrics();
    Code:
       0: aload_0
       1: invokespecial #1                  // Method java/lang/Object."<init>":()V
       4: aload_0
       5: new           #2                  // class java/util/HashMap
       8: dup
       9: invokespecial #3                  // Method java/util/HashMap."<init>":()V
      12: putfield      #4                  // Field counters:Ljava/util/Map;
      15: aload_0
      16: aload_0
      17: ldc           #6                  // String ROWS_FILTERED
      19: invokevirtual #7                  // Method createCounter:(Ljava/lang/String;)Ljava/util/concurrent/atomic/AtomicLong;
      22: putfield      #8                  // Field countOfRowsFiltered:Ljava/util/concurrent/atomic/AtomicLong;
      25: aload_0
      26: aload_0
      27: ldc           #9                  // String ROWS_SCANNED
      29: invokevirtual #7                  // Method createCounter:(Ljava/lang/String;)Ljava/util/concurrent/atomic/AtomicLong;
      32: putfield      #10                 // Field countOfRowsScanned:Ljava/util/concurrent/atomic/AtomicLong;
      35: return

  protected java.util.concurrent.atomic.AtomicLong createCounter(java.lang.String);
    Code:
       0: new           #11                 // class java/util/concurrent/atomic/AtomicLong
       3: dup
       4: lconst_0
       5: invokespecial #12                 // Method java/util/concurrent/atomic/AtomicLong."<init>":(J)V
       8: astore_2
       9: aload_0
      10: getfield      #4                  // Field counters:Ljava/util/Map;
      13: aload_1
      14: aload_2
      15: invokeinterface #13,  3           // InterfaceMethod java/util/Map.put:(Ljava/lang/Object;Ljava/lang/Object;)Ljava/lang/Object;
      20: pop
      21: aload_2
      22: areturn

  public void setCounter(java.lang.String, long);
    Code:
       0: aload_0
       1: getfield      #4                  // Field counters:Ljava/util/Map;
       4: aload_1
       5: invokeinterface #14,  2           // InterfaceMethod java/util/Map.get:(Ljava/lang/Object;)Ljava/lang/Object;
      10: checkcast     #11                 // class java/util/concurrent/atomic/AtomicLong
      13: astore        4
      15: aload         4
      17: ifnull        26
      20: aload         4
      22: lload_2
      23: invokevirtual #15                 // Method java/util/concurrent/atomic/AtomicLong.set:(J)V
      26: return

  public boolean hasCounter(java.lang.String);
    Code:
       0: aload_0
       1: getfield      #4                  // Field counters:Ljava/util/Map;
       4: aload_1
       5: invokeinterface #16,  2           // InterfaceMethod java/util/Map.containsKey:(Ljava/lang/Object;)Z
      10: ireturn

  public java.util.concurrent.atomic.AtomicLong getCounter(java.lang.String);
    Code:
       0: aload_0
       1: getfield      #4                  // Field counters:Ljava/util/Map;
       4: aload_1
       5: invokeinterface #14,  2           // InterfaceMethod java/util/Map.get:(Ljava/lang/Object;)Ljava/lang/Object;
      10: checkcast     #11                 // class java/util/concurrent/atomic/AtomicLong
      13: areturn

  public void addToCounter(java.lang.String, long);
    Code:
       0: aload_0
       1: getfield      #4                  // Field counters:Ljava/util/Map;
       4: aload_1
       5: invokeinterface #14,  2           // InterfaceMethod java/util/Map.get:(Ljava/lang/Object;)Ljava/lang/Object;
      10: checkcast     #11                 // class java/util/concurrent/atomic/AtomicLong
      13: astore        4
      15: aload         4
      17: ifnull        27
      20: aload         4
      22: lload_2
      23: invokevirtual #17                 // Method java/util/concurrent/atomic/AtomicLong.addAndGet:(J)J
      26: pop2
      27: return

  public java.util.Map<java.lang.String, java.lang.Long> getMetricsMap();
    Code:
       0: aload_0
       1: iconst_1
       2: invokevirtual #18                 // Method getMetricsMap:(Z)Ljava/util/Map;
       5: areturn

  public java.util.Map<java.lang.String, java.lang.Long> getMetricsMap(boolean);
    Code:
       0: invokestatic  #19                 // Method org/apache/hbase/thirdparty/com/google/common/collect/ImmutableMap.builder:()Lorg/apache/hbase/thirdparty/com/google/common/collect/ImmutableMap$Builder;
       3: astore_2
       4: aload_0
       5: getfield      #4                  // Field counters:Ljava/util/Map;
       8: invokeinterface #20,  1           // InterfaceMethod java/util/Map.entrySet:()Ljava/util/Set;
      13: invokeinterface #21,  1           // InterfaceMethod java/util/Set.iterator:()Ljava/util/Iterator;
      18: astore_3
      19: aload_3
      20: invokeinterface #22,  1           // InterfaceMethod java/util/Iterator.hasNext:()Z
      25: ifeq          95
      28: aload_3
      29: invokeinterface #23,  1           // InterfaceMethod java/util/Iterator.next:()Ljava/lang/Object;
      34: checkcast     #24                 // class java/util/Map$Entry
      37: astore        4
      39: iload_1
      40: ifeq          60
      43: aload         4
      45: invokeinterface #25,  1           // InterfaceMethod java/util/Map$Entry.getValue:()Ljava/lang/Object;
      50: checkcast     #11                 // class java/util/concurrent/atomic/AtomicLong
      53: lconst_0
      54: invokevirtual #26                 // Method java/util/concurrent/atomic/AtomicLong.getAndSet:(J)J
      57: goto          73
      60: aload         4
      62: invokeinterface #25,  1           // InterfaceMethod java/util/Map$Entry.getValue:()Ljava/lang/Object;
      67: checkcast     #11                 // class java/util/concurrent/atomic/AtomicLong
      70: invokevirtual #27                 // Method java/util/concurrent/atomic/AtomicLong.get:()J
      73: lstore        5
      75: aload_2
      76: aload         4
      78: invokeinterface #28,  1           // InterfaceMethod java/util/Map$Entry.getKey:()Ljava/lang/Object;
      83: lload         5
      85: invokestatic  #29                 // Method java/lang/Long.valueOf:(J)Ljava/lang/Long;
      88: invokevirtual #30                 // Method org/apache/hbase/thirdparty/com/google/common/collect/ImmutableMap$Builder.put:(Ljava/lang/Object;Ljava/lang/Object;)Lorg/apache/hbase/thirdparty/com/google/common/collect/ImmutableMap$Builder;
      91: pop
      92: goto          19
      95: aload_2
      96: invokevirtual #31                 // Method org/apache/hbase/thirdparty/com/google/common/collect/ImmutableMap$Builder.build:()Lorg/apache/hbase/thirdparty/com/google/common/collect/ImmutableMap;
      99: areturn
}
