Compiled from "ServerNonceManager.java"
public class org.apache.hadoop.hbase.regionserver.ServerNonceManager {
  public static final java.lang.String HASH_NONCE_GRACE_PERIOD_KEY;

  static final boolean $assertionsDisabled;

  public org.apache.hadoop.hbase.regionserver.ServerNonceManager(org.apache.hadoop.conf.Configuration);
    Code:
       0: aload_0
       1: invokespecial #3                  // Method java/lang/Object."<init>":()V
       4: aload_0
       5: sipush        30000
       8: putfield      #4                  // Field conflictWaitIterationMs:I
      11: aload_0
      12: new           #5                  // class java/util/concurrent/ConcurrentHashMap
      15: dup
      16: invokespecial #6                  // Method java/util/concurrent/ConcurrentHashMap."<init>":()V
      19: putfield      #7                  // Field nonces:Ljava/util/concurrent/ConcurrentHashMap;
      22: aload_0
      23: aload_1
      24: ldc           #9                  // String hbase.server.hashNonce.gracePeriod
      26: ldc           #10                 // int 1800000
      28: invokevirtual #11                 // Method org/apache/hadoop/conf/Configuration.getInt:(Ljava/lang/String;I)I
      31: putfield      #12                 // Field deleteNonceGracePeriod:I
      34: aload_0
      35: getfield      #12                 // Field deleteNonceGracePeriod:I
      38: ldc           #13                 // int 60000
      40: if_icmpge     78
      43: getstatic     #14                 // Field LOG:Lorg/slf4j/Logger;
      46: new           #15                 // class java/lang/StringBuilder
      49: dup
      50: invokespecial #16                 // Method java/lang/StringBuilder."<init>":()V
      53: ldc           #17                 // String Nonce grace period
      55: invokevirtual #18                 // Method java/lang/StringBuilder.append:(Ljava/lang/String;)Ljava/lang/StringBuilder;
      58: aload_0
      59: getfield      #12                 // Field deleteNonceGracePeriod:I
      62: invokevirtual #19                 // Method java/lang/StringBuilder.append:(I)Ljava/lang/StringBuilder;
      65: ldc           #20                 // String  is less than a minute; might be too small to be useful
      67: invokevirtual #18                 // Method java/lang/StringBuilder.append:(Ljava/lang/String;)Ljava/lang/StringBuilder;
      70: invokevirtual #21                 // Method java/lang/StringBuilder.toString:()Ljava/lang/String;
      73: invokeinterface #22,  2           // InterfaceMethod org/slf4j/Logger.warn:(Ljava/lang/String;)V
      78: return

  public void setConflictWaitIterationMs(int);
    Code:
       0: aload_0
       1: iload_1
       2: putfield      #4                  // Field conflictWaitIterationMs:I
       5: return

  public boolean startOperation(long, long, org.apache.hadoop.hbase.Stoppable) throws java.lang.InterruptedException;
    Code:
       0: lload_3
       1: lconst_0
       2: lcmp
       3: ifne          8
       6: iconst_1
       7: ireturn
       8: new           #24                 // class org/apache/hadoop/hbase/util/NonceKey
      11: dup
      12: lload_1
      13: lload_3
      14: invokespecial #25                 // Method org/apache/hadoop/hbase/util/NonceKey."<init>":(JJ)V
      17: astore        6
      19: new           #26                 // class org/apache/hadoop/hbase/regionserver/ServerNonceManager$OperationContext
      22: dup
      23: invokespecial #27                 // Method org/apache/hadoop/hbase/regionserver/ServerNonceManager$OperationContext."<init>":()V
      26: astore        7
      28: aload_0
      29: getfield      #7                  // Field nonces:Ljava/util/concurrent/ConcurrentHashMap;
      32: aload         6
      34: aload         7
      36: invokevirtual #28                 // Method java/util/concurrent/ConcurrentHashMap.putIfAbsent:(Ljava/lang/Object;Ljava/lang/Object;)Ljava/lang/Object;
      39: checkcast     #26                 // class org/apache/hadoop/hbase/regionserver/ServerNonceManager$OperationContext
      42: astore        8
      44: aload         8
      46: ifnonnull     51
      49: iconst_1
      50: ireturn
      51: aload         8
      53: dup
      54: astore        9
      56: monitorenter
      57: aload         8
      59: invokevirtual #29                 // Method org/apache/hadoop/hbase/regionserver/ServerNonceManager$OperationContext.getState:()I
      62: istore        10
      64: getstatic     #14                 // Field LOG:Lorg/slf4j/Logger;
      67: new           #15                 // class java/lang/StringBuilder
      70: dup
      71: invokespecial #16                 // Method java/lang/StringBuilder."<init>":()V
      74: ldc           #30                 // String Conflict detected by nonce:
      76: invokevirtual #18                 // Method java/lang/StringBuilder.append:(Ljava/lang/String;)Ljava/lang/StringBuilder;
      79: aload         6
      81: invokevirtual #31                 // Method java/lang/StringBuilder.append:(Ljava/lang/Object;)Ljava/lang/StringBuilder;
      84: ldc           #32                 // String ,
      86: invokevirtual #18                 // Method java/lang/StringBuilder.append:(Ljava/lang/String;)Ljava/lang/StringBuilder;
      89: aload         8
      91: invokevirtual #31                 // Method java/lang/StringBuilder.append:(Ljava/lang/Object;)Ljava/lang/StringBuilder;
      94: invokevirtual #21                 // Method java/lang/StringBuilder.toString:()Ljava/lang/String;
      97: invokeinterface #33,  2           // InterfaceMethod org/slf4j/Logger.debug:(Ljava/lang/String;)V
     102: iload         10
     104: iconst_2
     105: if_icmpeq     123
     108: iload         10
     110: iconst_1
     111: if_icmpne     118
     114: iconst_1
     115: goto          119
     118: iconst_0
     119: aload         9
     121: monitorexit
     122: ireturn
     123: aload         8
     125: invokevirtual #34                 // Method org/apache/hadoop/hbase/regionserver/ServerNonceManager$OperationContext.setHasWait:()V
     128: aload         8
     130: aload_0
     131: getfield      #4                  // Field conflictWaitIterationMs:I
     134: i2l
     135: invokevirtual #35                 // Method java/lang/Object.wait:(J)V
     138: aload         5
     140: invokeinterface #36,  1           // InterfaceMethod org/apache/hadoop/hbase/Stoppable.isStopped:()Z
     145: ifeq          158
     148: new           #37                 // class java/lang/InterruptedException
     151: dup
     152: ldc           #38                 // String Server stopped
     154: invokespecial #39                 // Method java/lang/InterruptedException."<init>":(Ljava/lang/String;)V
     157: athrow
     158: aload         9
     160: monitorexit
     161: goto          172
     164: astore        11
     166: aload         9
     168: monitorexit
     169: aload         11
     171: athrow
     172: goto          28
    Exception table:
       from    to  target type
          57   122   164   any
         123   161   164   any
         164   169   164   any

  public void endOperation(long, long, boolean);
    Code:
       0: lload_3
       1: lconst_0
       2: lcmp
       3: ifne          7
       6: return
       7: new           #24                 // class org/apache/hadoop/hbase/util/NonceKey
      10: dup
      11: lload_1
      12: lload_3
      13: invokespecial #25                 // Method org/apache/hadoop/hbase/util/NonceKey."<init>":(JJ)V
      16: astore        6
      18: aload_0
      19: getfield      #7                  // Field nonces:Ljava/util/concurrent/ConcurrentHashMap;
      22: aload         6
      24: invokevirtual #40                 // Method java/util/concurrent/ConcurrentHashMap.get:(Ljava/lang/Object;)Ljava/lang/Object;
      27: checkcast     #26                 // class org/apache/hadoop/hbase/regionserver/ServerNonceManager$OperationContext
      30: astore        7
      32: getstatic     #41                 // Field $assertionsDisabled:Z
      35: ifne          51
      38: aload         7
      40: ifnonnull     51
      43: new           #42                 // class java/lang/AssertionError
      46: dup
      47: invokespecial #43                 // Method java/lang/AssertionError."<init>":()V
      50: athrow
      51: aload         7
      53: dup
      54: astore        8
      56: monitorenter
      57: getstatic     #41                 // Field $assertionsDisabled:Z
      60: ifne          80
      63: aload         7
      65: invokevirtual #29                 // Method org/apache/hadoop/hbase/regionserver/ServerNonceManager$OperationContext.getState:()I
      68: iconst_2
      69: if_icmpeq     80
      72: new           #42                 // class java/lang/AssertionError
      75: dup
      76: invokespecial #43                 // Method java/lang/AssertionError."<init>":()V
      79: athrow
      80: aload         7
      82: iload         5
      84: ifeq          91
      87: iconst_0
      88: goto          92
      91: iconst_1
      92: invokevirtual #44                 // Method org/apache/hadoop/hbase/regionserver/ServerNonceManager$OperationContext.setState:(I)V
      95: iload         5
      97: ifeq          108
     100: aload         7
     102: invokevirtual #45                 // Method org/apache/hadoop/hbase/regionserver/ServerNonceManager$OperationContext.reportActivity:()V
     105: goto          143
     108: aload_0
     109: getfield      #7                  // Field nonces:Ljava/util/concurrent/ConcurrentHashMap;
     112: aload         6
     114: invokevirtual #46                 // Method java/util/concurrent/ConcurrentHashMap.remove:(Ljava/lang/Object;)Ljava/lang/Object;
     117: checkcast     #26                 // class org/apache/hadoop/hbase/regionserver/ServerNonceManager$OperationContext
     120: astore        9
     122: getstatic     #41                 // Field $assertionsDisabled:Z
     125: ifne          143
     128: aload         9
     130: aload         7
     132: if_acmpeq     143
     135: new           #42                 // class java/lang/AssertionError
     138: dup
     139: invokespecial #43                 // Method java/lang/AssertionError."<init>":()V
     142: athrow
     143: aload         7
     145: invokevirtual #47                 // Method org/apache/hadoop/hbase/regionserver/ServerNonceManager$OperationContext.hasWait:()Z
     148: ifeq          194
     151: getstatic     #14                 // Field LOG:Lorg/slf4j/Logger;
     154: new           #15                 // class java/lang/StringBuilder
     157: dup
     158: invokespecial #16                 // Method java/lang/StringBuilder."<init>":()V
     161: ldc           #48                 // String Conflict with running op ended:
     163: invokevirtual #18                 // Method java/lang/StringBuilder.append:(Ljava/lang/String;)Ljava/lang/StringBuilder;
     166: aload         6
     168: invokevirtual #31                 // Method java/lang/StringBuilder.append:(Ljava/lang/Object;)Ljava/lang/StringBuilder;
     171: ldc           #32                 // String ,
     173: invokevirtual #18                 // Method java/lang/StringBuilder.append:(Ljava/lang/String;)Ljava/lang/StringBuilder;
     176: aload         7
     178: invokevirtual #31                 // Method java/lang/StringBuilder.append:(Ljava/lang/Object;)Ljava/lang/StringBuilder;
     181: invokevirtual #21                 // Method java/lang/StringBuilder.toString:()Ljava/lang/String;
     184: invokeinterface #33,  2           // InterfaceMethod org/slf4j/Logger.debug:(Ljava/lang/String;)V
     189: aload         7
     191: invokevirtual #49                 // Method java/lang/Object.notifyAll:()V
     194: aload         8
     196: monitorexit
     197: goto          208
     200: astore        10
     202: aload         8
     204: monitorexit
     205: aload         10
     207: athrow
     208: return
    Exception table:
       from    to  target type
          57   197   200   any
         200   205   200   any

  public void addMvccToOperationContext(long, long, long);
    Code:
       0: lload_3
       1: lconst_0
       2: lcmp
       3: ifne          7
       6: return
       7: new           #24                 // class org/apache/hadoop/hbase/util/NonceKey
      10: dup
      11: lload_1
      12: lload_3
      13: invokespecial #25                 // Method org/apache/hadoop/hbase/util/NonceKey."<init>":(JJ)V
      16: astore        7
      18: aload_0
      19: getfield      #7                  // Field nonces:Ljava/util/concurrent/ConcurrentHashMap;
      22: aload         7
      24: invokevirtual #40                 // Method java/util/concurrent/ConcurrentHashMap.get:(Ljava/lang/Object;)Ljava/lang/Object;
      27: checkcast     #26                 // class org/apache/hadoop/hbase/regionserver/ServerNonceManager$OperationContext
      30: astore        8
      32: getstatic     #41                 // Field $assertionsDisabled:Z
      35: ifne          51
      38: aload         8
      40: ifnonnull     51
      43: new           #42                 // class java/lang/AssertionError
      46: dup
      47: invokespecial #43                 // Method java/lang/AssertionError."<init>":()V
      50: athrow
      51: aload         8
      53: dup
      54: astore        9
      56: monitorenter
      57: aload         8
      59: lload         5
      61: invokevirtual #50                 // Method org/apache/hadoop/hbase/regionserver/ServerNonceManager$OperationContext.setMvcc:(J)V
      64: aload         9
      66: monitorexit
      67: goto          78
      70: astore        10
      72: aload         9
      74: monitorexit
      75: aload         10
      77: athrow
      78: return
    Exception table:
       from    to  target type
          57    67    70   any
          70    75    70   any

  public long getMvccFromOperationContext(long, long);
    Code:
       0: lload_3
       1: lconst_0
       2: lcmp
       3: ifne          10
       6: ldc2_w        #52                 // long 9223372036854775807l
       9: lreturn
      10: new           #24                 // class org/apache/hadoop/hbase/util/NonceKey
      13: dup
      14: lload_1
      15: lload_3
      16: invokespecial #25                 // Method org/apache/hadoop/hbase/util/NonceKey."<init>":(JJ)V
      19: astore        5
      21: aload_0
      22: getfield      #7                  // Field nonces:Ljava/util/concurrent/ConcurrentHashMap;
      25: aload         5
      27: invokevirtual #40                 // Method java/util/concurrent/ConcurrentHashMap.get:(Ljava/lang/Object;)Ljava/lang/Object;
      30: checkcast     #26                 // class org/apache/hadoop/hbase/regionserver/ServerNonceManager$OperationContext
      33: astore        6
      35: aload         6
      37: ifnonnull     46
      40: ldc2_w        #52                 // long 9223372036854775807l
      43: goto          51
      46: aload         6
      48: invokevirtual #54                 // Method org/apache/hadoop/hbase/regionserver/ServerNonceManager$OperationContext.getMvcc:()J
      51: lreturn

  public void reportOperationFromWal(long, long, long);
    Code:
       0: lload_3
       1: lconst_0
       2: lcmp
       3: ifne          7
       6: return
       7: invokestatic  #55                 // Method org/apache/hadoop/hbase/util/EnvironmentEdgeManager.currentTime:()J
      10: lstore        7
      12: lload         7
      14: l2d
      15: lload         5
      17: l2d
      18: aload_0
      19: getfield      #12                 // Field deleteNonceGracePeriod:I
      22: i2d
      23: ldc2_w        #56                 // double 1.5d
      26: dmul
      27: dadd
      28: dcmpl
      29: ifle          33
      32: return
      33: new           #26                 // class org/apache/hadoop/hbase/regionserver/ServerNonceManager$OperationContext
      36: dup
      37: invokespecial #27                 // Method org/apache/hadoop/hbase/regionserver/ServerNonceManager$OperationContext."<init>":()V
      40: astore        9
      42: aload         9
      44: iconst_0
      45: invokevirtual #44                 // Method org/apache/hadoop/hbase/regionserver/ServerNonceManager$OperationContext.setState:(I)V
      48: new           #24                 // class org/apache/hadoop/hbase/util/NonceKey
      51: dup
      52: lload_1
      53: lload_3
      54: invokespecial #25                 // Method org/apache/hadoop/hbase/util/NonceKey."<init>":(JJ)V
      57: astore        10
      59: aload_0
      60: getfield      #7                  // Field nonces:Ljava/util/concurrent/ConcurrentHashMap;
      63: aload         10
      65: aload         9
      67: invokevirtual #28                 // Method java/util/concurrent/ConcurrentHashMap.putIfAbsent:(Ljava/lang/Object;Ljava/lang/Object;)Ljava/lang/Object;
      70: checkcast     #26                 // class org/apache/hadoop/hbase/regionserver/ServerNonceManager$OperationContext
      73: astore        11
      75: aload         11
      77: ifnull        128
      80: getstatic     #14                 // Field LOG:Lorg/slf4j/Logger;
      83: new           #15                 // class java/lang/StringBuilder
      86: dup
      87: invokespecial #16                 // Method java/lang/StringBuilder."<init>":()V
      90: ldc           #58                 // String Nonce collision during WAL recovery:
      92: invokevirtual #18                 // Method java/lang/StringBuilder.append:(Ljava/lang/String;)Ljava/lang/StringBuilder;
      95: aload         10
      97: invokevirtual #31                 // Method java/lang/StringBuilder.append:(Ljava/lang/Object;)Ljava/lang/StringBuilder;
     100: ldc           #32                 // String ,
     102: invokevirtual #18                 // Method java/lang/StringBuilder.append:(Ljava/lang/String;)Ljava/lang/StringBuilder;
     105: aload         11
     107: invokevirtual #31                 // Method java/lang/StringBuilder.append:(Ljava/lang/Object;)Ljava/lang/StringBuilder;
     110: ldc           #59                 // String  with
     112: invokevirtual #18                 // Method java/lang/StringBuilder.append:(Ljava/lang/String;)Ljava/lang/StringBuilder;
     115: aload         9
     117: invokevirtual #31                 // Method java/lang/StringBuilder.append:(Ljava/lang/Object;)Ljava/lang/StringBuilder;
     120: invokevirtual #21                 // Method java/lang/StringBuilder.toString:()Ljava/lang/String;
     123: invokeinterface #22,  2           // InterfaceMethod org/slf4j/Logger.warn:(Ljava/lang/String;)V
     128: return

  public org.apache.hadoop.hbase.ScheduledChore createCleanupScheduledChore(org.apache.hadoop.hbase.Stoppable);
    Code:
       0: new           #60                 // class org/apache/hadoop/hbase/regionserver/ServerNonceManager$1
       3: dup
       4: aload_0
       5: ldc           #61                 // String nonceCleaner
       7: aload_1
       8: aload_0
       9: getfield      #12                 // Field deleteNonceGracePeriod:I
      12: iconst_5
      13: idiv
      14: invokespecial #62                 // Method org/apache/hadoop/hbase/regionserver/ServerNonceManager$1."<init>":(Lorg/apache/hadoop/hbase/regionserver/ServerNonceManager;Ljava/lang/String;Lorg/apache/hadoop/hbase/Stoppable;I)V
      17: areturn

  static java.text.SimpleDateFormat access$000();
    Code:
       0: getstatic     #2                  // Field tsFormat:Ljava/text/SimpleDateFormat;
       3: areturn

  static void access$100(org.apache.hadoop.hbase.regionserver.ServerNonceManager);
    Code:
       0: aload_0
       1: invokespecial #1                  // Method cleanUpOldNonces:()V
       4: return

  static {};
    Code:
       0: ldc           #8                  // class org/apache/hadoop/hbase/regionserver/ServerNonceManager
       2: invokevirtual #71                 // Method java/lang/Class.desiredAssertionStatus:()Z
       5: ifne          12
       8: iconst_1
       9: goto          13
      12: iconst_0
      13: putstatic     #41                 // Field $assertionsDisabled:Z
      16: ldc           #8                  // class org/apache/hadoop/hbase/regionserver/ServerNonceManager
      18: invokestatic  #72                 // Method org/slf4j/LoggerFactory.getLogger:(Ljava/lang/Class;)Lorg/slf4j/Logger;
      21: putstatic     #14                 // Field LOG:Lorg/slf4j/Logger;
      24: new           #73                 // class java/text/SimpleDateFormat
      27: dup
      28: ldc           #74                 // String HH:mm:ss.SSS
      30: invokespecial #75                 // Method java/text/SimpleDateFormat."<init>":(Ljava/lang/String;)V
      33: putstatic     #2                  // Field tsFormat:Ljava/text/SimpleDateFormat;
      36: return
}
