Compiled from "ServerQueue.java"
class org.apache.hadoop.hbase.master.procedure.ServerQueue extends org.apache.hadoop.hbase.master.procedure.Queue<org.apache.hadoop.hbase.ServerName> {
  public org.apache.hadoop.hbase.master.procedure.ServerQueue(org.apache.hadoop.hbase.ServerName, int, org.apache.hadoop.hbase.procedure2.LockStatus);
    Code:
       0: aload_0
       1: aload_1
       2: iload_2
       3: aload_3
       4: invokespecial #1                  // Method org/apache/hadoop/hbase/master/procedure/Queue."<init>":(Ljava/lang/Comparable;ILorg/apache/hadoop/hbase/procedure2/LockStatus;)V
       7: return

  public boolean requireExclusiveLock(org.apache.hadoop.hbase.procedure2.Procedure<?>);
    Code:
       0: aload_1
       1: checkcast     #2                  // class org/apache/hadoop/hbase/master/procedure/ServerProcedureInterface
       4: astore_2
       5: getstatic     #3                  // Field org/apache/hadoop/hbase/master/procedure/ServerQueue$1.$SwitchMap$org$apache$hadoop$hbase$master$procedure$ServerProcedureInterface$ServerOperationType:[I
       8: aload_2
       9: invokeinterface #4,  1            // InterfaceMethod org/apache/hadoop/hbase/master/procedure/ServerProcedureInterface.getServerOperationType:()Lorg/apache/hadoop/hbase/master/procedure/ServerProcedureInterface$ServerOperationType;
      14: invokevirtual #5                  // Method org/apache/hadoop/hbase/master/procedure/ServerProcedureInterface$ServerOperationType.ordinal:()I
      17: iaload
      18: tableswitch   { // 1 to 4
                     1: 48
                     2: 50
                     3: 50
                     4: 50
               default: 52
          }
      48: iconst_1
      49: ireturn
      50: iconst_0
      51: ireturn
      52: new           #6                  // class java/lang/UnsupportedOperationException
      55: dup
      56: new           #7                  // class java/lang/StringBuilder
      59: dup
      60: invokespecial #8                  // Method java/lang/StringBuilder."<init>":()V
      63: ldc           #9                  // String unexpected type
      65: invokevirtual #10                 // Method java/lang/StringBuilder.append:(Ljava/lang/String;)Ljava/lang/StringBuilder;
      68: aload_2
      69: invokeinterface #4,  1            // InterfaceMethod org/apache/hadoop/hbase/master/procedure/ServerProcedureInterface.getServerOperationType:()Lorg/apache/hadoop/hbase/master/procedure/ServerProcedureInterface$ServerOperationType;
      74: invokevirtual #11                 // Method java/lang/StringBuilder.append:(Ljava/lang/Object;)Ljava/lang/StringBuilder;
      77: invokevirtual #12                 // Method java/lang/StringBuilder.toString:()Ljava/lang/String;
      80: invokespecial #13                 // Method java/lang/UnsupportedOperationException."<init>":(Ljava/lang/String;)V
      83: athrow
}
