Compiled from "ServerManager.java"
class org.apache.hadoop.hbase.master.ServerManager$FlushedSequenceIdFlusher extends org.apache.hadoop.hbase.ScheduledChore {
  final org.apache.hadoop.hbase.master.ServerManager this$0;

  public org.apache.hadoop.hbase.master.ServerManager$FlushedSequenceIdFlusher(org.apache.hadoop.hbase.master.ServerManager, java.lang.String, int);
    Code:
       0: aload_0
       1: aload_1
       2: putfield      #1                  // Field this$0:Lorg/apache/hadoop/hbase/master/ServerManager;
       5: aload_0
       6: aload_2
       7: aload_1
       8: invokestatic  #2                  // Method org/apache/hadoop/hbase/master/ServerManager.access$000:(Lorg/apache/hadoop/hbase/master/ServerManager;)Lorg/apache/hadoop/hbase/master/MasterServices;
      11: iload_3
      12: ldc2_w        #3                  // long 60000l
      15: invokespecial #5                  // Method org/apache/hadoop/hbase/ScheduledChore."<init>":(Ljava/lang/String;Lorg/apache/hadoop/hbase/Stoppable;IJ)V
      18: return

  protected void chore();
    Code:
       0: aload_0
       1: getfield      #1                  // Field this$0:Lorg/apache/hadoop/hbase/master/ServerManager;
       4: invokestatic  #6                  // Method org/apache/hadoop/hbase/master/ServerManager.access$100:(Lorg/apache/hadoop/hbase/master/ServerManager;)V
       7: goto          22
      10: astore_1
      11: invokestatic  #8                  // Method org/apache/hadoop/hbase/master/ServerManager.access$200:()Lorg/slf4j/Logger;
      14: ldc           #9                  // String Failed to persist last flushed sequence id of regions to file system
      16: aload_1
      17: invokeinterface #10,  3           // InterfaceMethod org/slf4j/Logger.debug:(Ljava/lang/String;Ljava/lang/Throwable;)V
      22: return
    Exception table:
       from    to  target type
           0     7    10   Class java/io/IOException
}
