Compiled from "SharedMemoryMmapIOEngine.java"
public class org.apache.hadoop.hbase.io.hfile.bucket.SharedMemoryMmapIOEngine extends org.apache.hadoop.hbase.io.hfile.bucket.FileMmapIOEngine {
  public org.apache.hadoop.hbase.io.hfile.bucket.SharedMemoryMmapIOEngine(java.lang.String, long) throws java.io.IOException;
    Code:
       0: aload_0
       1: aload_1
       2: lload_2
       3: invokespecial #1                  // Method org/apache/hadoop/hbase/io/hfile/bucket/FileMmapIOEngine."<init>":(Ljava/lang/String;J)V
       6: return

  public boolean usesSharedMemory();
    Code:
       0: iconst_1
       1: ireturn

  public org.apache.hadoop.hbase.io.hfile.Cacheable read(long, int, org.apache.hadoop.hbase.io.hfile.CacheableDeserializer<org.apache.hadoop.hbase.io.hfile.Cacheable>) throws java.io.IOException;
    Code:
       0: aload_0
       1: getfield      #2                  // Field bufferArray:Lorg/apache/hadoop/hbase/util/ByteBufferArray;
       4: lload_1
       5: iload_3
       6: invokevirtual #3                  // Method org/apache/hadoop/hbase/util/ByteBufferArray.asSubByteBuff:(JI)Lorg/apache/hadoop/hbase/nio/ByteBuff;
       9: astore        5
      11: aload         4
      13: aload         5
      15: iconst_1
      16: getstatic     #4                  // Field org/apache/hadoop/hbase/io/hfile/Cacheable$MemoryType.SHARED:Lorg/apache/hadoop/hbase/io/hfile/Cacheable$MemoryType;
      19: invokeinterface #5,  4            // InterfaceMethod org/apache/hadoop/hbase/io/hfile/CacheableDeserializer.deserialize:(Lorg/apache/hadoop/hbase/nio/ByteBuff;ZLorg/apache/hadoop/hbase/io/hfile/Cacheable$MemoryType;)Lorg/apache/hadoop/hbase/io/hfile/Cacheable;
      24: areturn
}
