Compiled from "SimpleScanLabelGenerator.java"
public class org.apache.hadoop.hbase.security.visibility.SimpleScanLabelGenerator implements org.apache.hadoop.hbase.security.visibility.ScanLabelGenerator {
  public org.apache.hadoop.hbase.security.visibility.SimpleScanLabelGenerator();
    Code:
       0: aload_0
       1: invokespecial #1                  // Method java/lang/Object."<init>":()V
       4: return

  public void setConf(org.apache.hadoop.conf.Configuration);
    Code:
       0: aload_0
       1: aload_1
       2: putfield      #2                  // Field conf:Lorg/apache/hadoop/conf/Configuration;
       5: return

  public org.apache.hadoop.conf.Configuration getConf();
    Code:
       0: aload_0
       1: getfield      #2                  // Field conf:Lorg/apache/hadoop/conf/Configuration;
       4: areturn

  public java.util.List<java.lang.String> getLabels(org.apache.hadoop.hbase.security.User, org.apache.hadoop.hbase.security.visibility.Authorizations);
    Code:
       0: aload_2
       1: ifnull        9
       4: aload_2
       5: invokevirtual #3                  // Method org/apache/hadoop/hbase/security/visibility/Authorizations.getLabels:()Ljava/util/List;
       8: areturn
       9: aconst_null
      10: areturn
}
