Compiled from "SimpleRpcServerResponder.java"
class org.apache.hadoop.hbase.ipc.SimpleRpcServerResponder extends java.lang.Thread {
  org.apache.hadoop.hbase.ipc.SimpleRpcServerResponder(org.apache.hadoop.hbase.ipc.SimpleRpcServer) throws java.io.IOException;
    Code:
       0: aload_0
       1: invokespecial #1                  // Method java/lang/Thread."<init>":()V
       4: aload_0
       5: new           #2                  // class java/util/concurrent/ConcurrentHashMap
       8: dup
       9: invokespecial #3                  // Method java/util/concurrent/ConcurrentHashMap."<init>":()V
      12: invokestatic  #4                  // Method java/util/Collections.newSetFromMap:(Ljava/util/Map;)Ljava/util/Set;
      15: putfield      #5                  // Field writingCons:Ljava/util/Set;
      18: aload_0
      19: aload_1
      20: putfield      #6                  // Field simpleRpcServer:Lorg/apache/hadoop/hbase/ipc/SimpleRpcServer;
      23: aload_0
      24: ldc           #7                  // String RpcServer.responder
      26: invokevirtual #8                  // Method setName:(Ljava/lang/String;)V
      29: aload_0
      30: iconst_1
      31: invokevirtual #9                  // Method setDaemon:(Z)V
      34: aload_0
      35: getstatic     #10                 // Field org/apache/hadoop/hbase/util/Threads.LOGGING_EXCEPTION_HANDLER:Ljava/lang/Thread$UncaughtExceptionHandler;
      38: invokevirtual #11                 // Method setUncaughtExceptionHandler:(Ljava/lang/Thread$UncaughtExceptionHandler;)V
      41: aload_0
      42: invokestatic  #12                 // Method java/nio/channels/Selector.open:()Ljava/nio/channels/Selector;
      45: putfield      #13                 // Field writeSelector:Ljava/nio/channels/Selector;
      48: return

  public void run();
    Code:
       0: getstatic     #14                 // Field org/apache/hadoop/hbase/ipc/SimpleRpcServer.LOG:Lorg/slf4j/Logger;
       3: new           #15                 // class java/lang/StringBuilder
       6: dup
       7: invokespecial #16                 // Method java/lang/StringBuilder."<init>":()V
      10: aload_0
      11: invokevirtual #17                 // Method getName:()Ljava/lang/String;
      14: invokevirtual #18                 // Method java/lang/StringBuilder.append:(Ljava/lang/String;)Ljava/lang/StringBuilder;
      17: ldc           #19                 // String : starting
      19: invokevirtual #18                 // Method java/lang/StringBuilder.append:(Ljava/lang/String;)Ljava/lang/StringBuilder;
      22: invokevirtual #20                 // Method java/lang/StringBuilder.toString:()Ljava/lang/String;
      25: invokeinterface #21,  2           // InterfaceMethod org/slf4j/Logger.debug:(Ljava/lang/String;)V
      30: aload_0
      31: invokespecial #22                 // Method doRunLoop:()V
      34: getstatic     #14                 // Field org/apache/hadoop/hbase/ipc/SimpleRpcServer.LOG:Lorg/slf4j/Logger;
      37: new           #15                 // class java/lang/StringBuilder
      40: dup
      41: invokespecial #16                 // Method java/lang/StringBuilder."<init>":()V
      44: aload_0
      45: invokevirtual #17                 // Method getName:()Ljava/lang/String;
      48: invokevirtual #18                 // Method java/lang/StringBuilder.append:(Ljava/lang/String;)Ljava/lang/StringBuilder;
      51: ldc           #23                 // String : stopping
      53: invokevirtual #18                 // Method java/lang/StringBuilder.append:(Ljava/lang/String;)Ljava/lang/StringBuilder;
      56: invokevirtual #20                 // Method java/lang/StringBuilder.toString:()Ljava/lang/String;
      59: invokeinterface #24,  2           // InterfaceMethod org/slf4j/Logger.info:(Ljava/lang/String;)V
      64: aload_0
      65: getfield      #13                 // Field writeSelector:Ljava/nio/channels/Selector;
      68: invokevirtual #25                 // Method java/nio/channels/Selector.close:()V
      71: goto          184
      74: astore_1
      75: getstatic     #14                 // Field org/apache/hadoop/hbase/ipc/SimpleRpcServer.LOG:Lorg/slf4j/Logger;
      78: new           #15                 // class java/lang/StringBuilder
      81: dup
      82: invokespecial #16                 // Method java/lang/StringBuilder."<init>":()V
      85: aload_0
      86: invokevirtual #17                 // Method getName:()Ljava/lang/String;
      89: invokevirtual #18                 // Method java/lang/StringBuilder.append:(Ljava/lang/String;)Ljava/lang/StringBuilder;
      92: ldc           #27                 // String : couldn't close write selector
      94: invokevirtual #18                 // Method java/lang/StringBuilder.append:(Ljava/lang/String;)Ljava/lang/StringBuilder;
      97: invokevirtual #20                 // Method java/lang/StringBuilder.toString:()Ljava/lang/String;
     100: aload_1
     101: invokeinterface #28,  3           // InterfaceMethod org/slf4j/Logger.error:(Ljava/lang/String;Ljava/lang/Throwable;)V
     106: goto          184
     109: astore_2
     110: getstatic     #14                 // Field org/apache/hadoop/hbase/ipc/SimpleRpcServer.LOG:Lorg/slf4j/Logger;
     113: new           #15                 // class java/lang/StringBuilder
     116: dup
     117: invokespecial #16                 // Method java/lang/StringBuilder."<init>":()V
     120: aload_0
     121: invokevirtual #17                 // Method getName:()Ljava/lang/String;
     124: invokevirtual #18                 // Method java/lang/StringBuilder.append:(Ljava/lang/String;)Ljava/lang/StringBuilder;
     127: ldc           #23                 // String : stopping
     129: invokevirtual #18                 // Method java/lang/StringBuilder.append:(Ljava/lang/String;)Ljava/lang/StringBuilder;
     132: invokevirtual #20                 // Method java/lang/StringBuilder.toString:()Ljava/lang/String;
     135: invokeinterface #24,  2           // InterfaceMethod org/slf4j/Logger.info:(Ljava/lang/String;)V
     140: aload_0
     141: getfield      #13                 // Field writeSelector:Ljava/nio/channels/Selector;
     144: invokevirtual #25                 // Method java/nio/channels/Selector.close:()V
     147: goto          182
     150: astore_3
     151: getstatic     #14                 // Field org/apache/hadoop/hbase/ipc/SimpleRpcServer.LOG:Lorg/slf4j/Logger;
     154: new           #15                 // class java/lang/StringBuilder
     157: dup
     158: invokespecial #16                 // Method java/lang/StringBuilder."<init>":()V
     161: aload_0
     162: invokevirtual #17                 // Method getName:()Ljava/lang/String;
     165: invokevirtual #18                 // Method java/lang/StringBuilder.append:(Ljava/lang/String;)Ljava/lang/StringBuilder;
     168: ldc           #27                 // String : couldn't close write selector
     170: invokevirtual #18                 // Method java/lang/StringBuilder.append:(Ljava/lang/String;)Ljava/lang/StringBuilder;
     173: invokevirtual #20                 // Method java/lang/StringBuilder.toString:()Ljava/lang/String;
     176: aload_3
     177: invokeinterface #28,  3           // InterfaceMethod org/slf4j/Logger.error:(Ljava/lang/String;Ljava/lang/Throwable;)V
     182: aload_2
     183: athrow
     184: return
    Exception table:
       from    to  target type
          64    71    74   Class java/io/IOException
          30    34   109   any
         140   147   150   Class java/io/IOException

  public void registerForWrite(org.apache.hadoop.hbase.ipc.SimpleServerRpcConnection);
    Code:
       0: aload_0
       1: getfield      #5                  // Field writingCons:Ljava/util/Set;
       4: aload_1
       5: invokeinterface #44,  2           // InterfaceMethod java/util/Set.add:(Ljava/lang/Object;)Z
      10: ifeq          21
      13: aload_0
      14: getfield      #13                 // Field writeSelector:Ljava/nio/channels/Selector;
      17: invokevirtual #45                 // Method java/nio/channels/Selector.wakeup:()Ljava/nio/channels/Selector;
      20: pop
      21: return

  void doRespond(org.apache.hadoop.hbase.ipc.SimpleServerRpcConnection, org.apache.hadoop.hbase.ipc.RpcResponse) throws java.io.IOException;
    Code:
       0: iconst_0
       1: istore_3
       2: aload_1
       3: getfield      #102                // Field org/apache/hadoop/hbase/ipc/SimpleServerRpcConnection.responseQueue:Ljava/util/concurrent/ConcurrentLinkedDeque;
       6: invokevirtual #108                // Method java/util/concurrent/ConcurrentLinkedDeque.isEmpty:()Z
       9: ifeq          89
      12: aload_1
      13: getfield      #100                // Field org/apache/hadoop/hbase/ipc/SimpleServerRpcConnection.responseWriteLock:Ljava/util/concurrent/locks/Lock;
      16: invokeinterface #109,  1          // InterfaceMethod java/util/concurrent/locks/Lock.tryLock:()Z
      21: ifeq          89
      24: aload_1
      25: getfield      #102                // Field org/apache/hadoop/hbase/ipc/SimpleServerRpcConnection.responseQueue:Ljava/util/concurrent/ConcurrentLinkedDeque;
      28: invokevirtual #108                // Method java/util/concurrent/ConcurrentLinkedDeque.isEmpty:()Z
      31: ifeq          63
      34: aload_0
      35: aload_1
      36: aload_2
      37: invokespecial #106                // Method processResponse:(Lorg/apache/hadoop/hbase/ipc/SimpleServerRpcConnection;Lorg/apache/hadoop/hbase/ipc/RpcResponse;)Z
      40: ifeq          53
      43: aload_1
      44: getfield      #100                // Field org/apache/hadoop/hbase/ipc/SimpleServerRpcConnection.responseWriteLock:Ljava/util/concurrent/locks/Lock;
      47: invokeinterface #105,  1          // InterfaceMethod java/util/concurrent/locks/Lock.unlock:()V
      52: return
      53: aload_1
      54: getfield      #102                // Field org/apache/hadoop/hbase/ipc/SimpleServerRpcConnection.responseQueue:Ljava/util/concurrent/ConcurrentLinkedDeque;
      57: aload_2
      58: invokevirtual #107                // Method java/util/concurrent/ConcurrentLinkedDeque.addFirst:(Ljava/lang/Object;)V
      61: iconst_1
      62: istore_3
      63: aload_1
      64: getfield      #100                // Field org/apache/hadoop/hbase/ipc/SimpleServerRpcConnection.responseWriteLock:Ljava/util/concurrent/locks/Lock;
      67: invokeinterface #105,  1          // InterfaceMethod java/util/concurrent/locks/Lock.unlock:()V
      72: goto          89
      75: astore        4
      77: aload_1
      78: getfield      #100                // Field org/apache/hadoop/hbase/ipc/SimpleServerRpcConnection.responseWriteLock:Ljava/util/concurrent/locks/Lock;
      81: invokeinterface #105,  1          // InterfaceMethod java/util/concurrent/locks/Lock.unlock:()V
      86: aload         4
      88: athrow
      89: iload_3
      90: ifne          101
      93: aload_1
      94: getfield      #102                // Field org/apache/hadoop/hbase/ipc/SimpleServerRpcConnection.responseQueue:Ljava/util/concurrent/ConcurrentLinkedDeque;
      97: aload_2
      98: invokevirtual #110                // Method java/util/concurrent/ConcurrentLinkedDeque.addLast:(Ljava/lang/Object;)V
     101: aload_0
     102: aload_1
     103: invokevirtual #111                // Method registerForWrite:(Lorg/apache/hadoop/hbase/ipc/SimpleServerRpcConnection;)V
     106: return
    Exception table:
       from    to  target type
          24    43    75   any
          53    63    75   any
          75    77    75   any
}
