Compiled from "SingleColumnValueFilter.java"
public class org.apache.hadoop.hbase.filter.SingleColumnValueFilter extends org.apache.hadoop.hbase.filter.FilterBase {
  protected byte[] columnFamily;

  protected byte[] columnQualifier;

  protected org.apache.hadoop.hbase.CompareOperator op;

  protected org.apache.hadoop.hbase.filter.ByteArrayComparable comparator;

  protected boolean foundColumn;

  protected boolean matchedColumn;

  protected boolean filterIfMissing;

  protected boolean latestVersionOnly;

  public org.apache.hadoop.hbase.filter.SingleColumnValueFilter(byte[], byte[], org.apache.hadoop.hbase.CompareOperator, byte[]);
    Code:
       0: aload_0
       1: aload_1
       2: aload_2
       3: aload_3
       4: new           #1                  // class org/apache/hadoop/hbase/filter/BinaryComparator
       7: dup
       8: aload         4
      10: invokespecial #2                  // Method org/apache/hadoop/hbase/filter/BinaryComparator."<init>":([B)V
      13: invokespecial #3                  // Method "<init>":([B[BLorg/apache/hadoop/hbase/CompareOperator;Lorg/apache/hadoop/hbase/filter/ByteArrayComparable;)V
      16: return

  public org.apache.hadoop.hbase.filter.SingleColumnValueFilter(byte[], byte[], org.apache.hadoop.hbase.CompareOperator, org.apache.hadoop.hbase.filter.ByteArrayComparable);
    Code:
       0: aload_0
       1: invokespecial #4                  // Method org/apache/hadoop/hbase/filter/FilterBase."<init>":()V
       4: aload_0
       5: iconst_0
       6: putfield      #5                  // Field foundColumn:Z
       9: aload_0
      10: iconst_0
      11: putfield      #6                  // Field matchedColumn:Z
      14: aload_0
      15: iconst_0
      16: putfield      #7                  // Field filterIfMissing:Z
      19: aload_0
      20: iconst_1
      21: putfield      #8                  // Field latestVersionOnly:Z
      24: aload_0
      25: aload_1
      26: putfield      #9                  // Field columnFamily:[B
      29: aload_0
      30: aload_2
      31: putfield      #10                 // Field columnQualifier:[B
      34: aload_0
      35: aload_3
      36: putfield      #11                 // Field op:Lorg/apache/hadoop/hbase/CompareOperator;
      39: aload_0
      40: aload         4
      42: putfield      #12                 // Field comparator:Lorg/apache/hadoop/hbase/filter/ByteArrayComparable;
      45: return

  protected org.apache.hadoop.hbase.filter.SingleColumnValueFilter(byte[], byte[], org.apache.hadoop.hbase.CompareOperator, org.apache.hadoop.hbase.filter.ByteArrayComparable, boolean, boolean);
    Code:
       0: aload_0
       1: aload_1
       2: aload_2
       3: aload_3
       4: aload         4
       6: invokespecial #3                  // Method "<init>":([B[BLorg/apache/hadoop/hbase/CompareOperator;Lorg/apache/hadoop/hbase/filter/ByteArrayComparable;)V
       9: aload_0
      10: iload         5
      12: putfield      #7                  // Field filterIfMissing:Z
      15: aload_0
      16: iload         6
      18: putfield      #8                  // Field latestVersionOnly:Z
      21: return

  public org.apache.hadoop.hbase.CompareOperator getOperator();
    Code:
       0: aload_0
       1: getfield      #11                 // Field op:Lorg/apache/hadoop/hbase/CompareOperator;
       4: invokevirtual #13                 // Method org/apache/hadoop/hbase/CompareOperator.name:()Ljava/lang/String;
       7: invokestatic  #14                 // Method org/apache/hadoop/hbase/CompareOperator.valueOf:(Ljava/lang/String;)Lorg/apache/hadoop/hbase/CompareOperator;
      10: areturn

  public org.apache.hadoop.hbase.CompareOperator getCompareOperator();
    Code:
       0: aload_0
       1: getfield      #11                 // Field op:Lorg/apache/hadoop/hbase/CompareOperator;
       4: areturn

  public org.apache.hadoop.hbase.filter.ByteArrayComparable getComparator();
    Code:
       0: aload_0
       1: getfield      #12                 // Field comparator:Lorg/apache/hadoop/hbase/filter/ByteArrayComparable;
       4: areturn

  public byte[] getFamily();
    Code:
       0: aload_0
       1: getfield      #9                  // Field columnFamily:[B
       4: areturn

  public byte[] getQualifier();
    Code:
       0: aload_0
       1: getfield      #10                 // Field columnQualifier:[B
       4: areturn

  public boolean filterRowKey(org.apache.hadoop.hbase.Cell) throws java.io.IOException;
    Code:
       0: iconst_0
       1: ireturn

  public org.apache.hadoop.hbase.filter.Filter$ReturnCode filterKeyValue(org.apache.hadoop.hbase.Cell);
    Code:
       0: aload_0
       1: aload_1
       2: invokevirtual #15                 // Method filterCell:(Lorg/apache/hadoop/hbase/Cell;)Lorg/apache/hadoop/hbase/filter/Filter$ReturnCode;
       5: areturn

  public org.apache.hadoop.hbase.filter.Filter$ReturnCode filterCell(org.apache.hadoop.hbase.Cell);
    Code:
       0: aload_0
       1: getfield      #6                  // Field matchedColumn:Z
       4: ifeq          11
       7: getstatic     #16                 // Field org/apache/hadoop/hbase/filter/Filter$ReturnCode.INCLUDE:Lorg/apache/hadoop/hbase/filter/Filter$ReturnCode;
      10: areturn
      11: aload_0
      12: getfield      #8                  // Field latestVersionOnly:Z
      15: ifeq          29
      18: aload_0
      19: getfield      #5                  // Field foundColumn:Z
      22: ifeq          29
      25: getstatic     #17                 // Field org/apache/hadoop/hbase/filter/Filter$ReturnCode.NEXT_ROW:Lorg/apache/hadoop/hbase/filter/Filter$ReturnCode;
      28: areturn
      29: aload_1
      30: aload_0
      31: getfield      #9                  // Field columnFamily:[B
      34: aload_0
      35: getfield      #10                 // Field columnQualifier:[B
      38: invokestatic  #18                 // Method org/apache/hadoop/hbase/CellUtil.matchingColumn:(Lorg/apache/hadoop/hbase/Cell;[B[B)Z
      41: ifne          48
      44: getstatic     #16                 // Field org/apache/hadoop/hbase/filter/Filter$ReturnCode.INCLUDE:Lorg/apache/hadoop/hbase/filter/Filter$ReturnCode;
      47: areturn
      48: aload_0
      49: iconst_1
      50: putfield      #5                  // Field foundColumn:Z
      53: aload_0
      54: aload_1
      55: invokespecial #19                 // Method filterColumnValue:(Lorg/apache/hadoop/hbase/Cell;)Z
      58: ifeq          78
      61: aload_0
      62: getfield      #8                  // Field latestVersionOnly:Z
      65: ifeq          74
      68: getstatic     #17                 // Field org/apache/hadoop/hbase/filter/Filter$ReturnCode.NEXT_ROW:Lorg/apache/hadoop/hbase/filter/Filter$ReturnCode;
      71: goto          77
      74: getstatic     #16                 // Field org/apache/hadoop/hbase/filter/Filter$ReturnCode.INCLUDE:Lorg/apache/hadoop/hbase/filter/Filter$ReturnCode;
      77: areturn
      78: aload_0
      79: iconst_1
      80: putfield      #6                  // Field matchedColumn:Z
      83: getstatic     #16                 // Field org/apache/hadoop/hbase/filter/Filter$ReturnCode.INCLUDE:Lorg/apache/hadoop/hbase/filter/Filter$ReturnCode;
      86: areturn

  public boolean filterRow();
    Code:
       0: aload_0
       1: getfield      #5                  // Field foundColumn:Z
       4: ifeq          22
       7: aload_0
       8: getfield      #6                  // Field matchedColumn:Z
      11: ifne          18
      14: iconst_1
      15: goto          26
      18: iconst_0
      19: goto          26
      22: aload_0
      23: getfield      #7                  // Field filterIfMissing:Z
      26: ireturn

  public boolean hasFilterRow();
    Code:
       0: iconst_1
       1: ireturn

  public void reset();
    Code:
       0: aload_0
       1: iconst_0
       2: putfield      #5                  // Field foundColumn:Z
       5: aload_0
       6: iconst_0
       7: putfield      #6                  // Field matchedColumn:Z
      10: return

  public boolean getFilterIfMissing();
    Code:
       0: aload_0
       1: getfield      #7                  // Field filterIfMissing:Z
       4: ireturn

  public void setFilterIfMissing(boolean);
    Code:
       0: aload_0
       1: iload_1
       2: putfield      #7                  // Field filterIfMissing:Z
       5: return

  public boolean getLatestVersionOnly();
    Code:
       0: aload_0
       1: getfield      #8                  // Field latestVersionOnly:Z
       4: ireturn

  public void setLatestVersionOnly(boolean);
    Code:
       0: aload_0
       1: iload_1
       2: putfield      #8                  // Field latestVersionOnly:Z
       5: return

  public static org.apache.hadoop.hbase.filter.Filter createFilterFromArguments(java.util.ArrayList<byte[]>);
    Code:
       0: aload_0
       1: invokevirtual #22                 // Method java/util/ArrayList.size:()I
       4: iconst_4
       5: if_icmpeq     17
       8: aload_0
       9: invokevirtual #22                 // Method java/util/ArrayList.size:()I
      12: bipush        6
      14: if_icmpne     21
      17: iconst_1
      18: goto          22
      21: iconst_0
      22: ldc           #23                 // String Expected 4 or 6 but got: %s
      24: aload_0
      25: invokevirtual #22                 // Method java/util/ArrayList.size:()I
      28: invokestatic  #24                 // Method org/apache/hbase/thirdparty/com/google/common/base/Preconditions.checkArgument:(ZLjava/lang/String;I)V
      31: aload_0
      32: iconst_0
      33: invokevirtual #25                 // Method java/util/ArrayList.get:(I)Ljava/lang/Object;
      36: checkcast     #26                 // class "[B"
      39: invokestatic  #27                 // Method org/apache/hadoop/hbase/filter/ParseFilter.removeQuotesFromByteArray:([B)[B
      42: astore_1
      43: aload_0
      44: iconst_1
      45: invokevirtual #25                 // Method java/util/ArrayList.get:(I)Ljava/lang/Object;
      48: checkcast     #26                 // class "[B"
      51: invokestatic  #27                 // Method org/apache/hadoop/hbase/filter/ParseFilter.removeQuotesFromByteArray:([B)[B
      54: astore_2
      55: aload_0
      56: iconst_2
      57: invokevirtual #25                 // Method java/util/ArrayList.get:(I)Ljava/lang/Object;
      60: checkcast     #26                 // class "[B"
      63: invokestatic  #28                 // Method org/apache/hadoop/hbase/filter/ParseFilter.createCompareOperator:([B)Lorg/apache/hadoop/hbase/CompareOperator;
      66: astore_3
      67: aload_0
      68: iconst_3
      69: invokevirtual #25                 // Method java/util/ArrayList.get:(I)Ljava/lang/Object;
      72: checkcast     #26                 // class "[B"
      75: invokestatic  #27                 // Method org/apache/hadoop/hbase/filter/ParseFilter.removeQuotesFromByteArray:([B)[B
      78: invokestatic  #29                 // Method org/apache/hadoop/hbase/filter/ParseFilter.createComparator:([B)Lorg/apache/hadoop/hbase/filter/ByteArrayComparable;
      81: astore        4
      83: aload         4
      85: instanceof    #30                 // class org/apache/hadoop/hbase/filter/RegexStringComparator
      88: ifne          99
      91: aload         4
      93: instanceof    #31                 // class org/apache/hadoop/hbase/filter/SubstringComparator
      96: ifeq          123
      99: aload_3
     100: getstatic     #32                 // Field org/apache/hadoop/hbase/CompareOperator.EQUAL:Lorg/apache/hadoop/hbase/CompareOperator;
     103: if_acmpeq     123
     106: aload_3
     107: getstatic     #33                 // Field org/apache/hadoop/hbase/CompareOperator.NOT_EQUAL:Lorg/apache/hadoop/hbase/CompareOperator;
     110: if_acmpeq     123
     113: new           #34                 // class java/lang/IllegalArgumentException
     116: dup
     117: ldc           #35                 // String A regexstring comparator and substring comparator can only be used with EQUAL and NOT_EQUAL
     119: invokespecial #36                 // Method java/lang/IllegalArgumentException."<init>":(Ljava/lang/String;)V
     122: athrow
     123: new           #37                 // class org/apache/hadoop/hbase/filter/SingleColumnValueFilter
     126: dup
     127: aload_1
     128: aload_2
     129: aload_3
     130: aload         4
     132: invokespecial #3                  // Method "<init>":([B[BLorg/apache/hadoop/hbase/CompareOperator;Lorg/apache/hadoop/hbase/filter/ByteArrayComparable;)V
     135: astore        5
     137: aload_0
     138: invokevirtual #22                 // Method java/util/ArrayList.size:()I
     141: bipush        6
     143: if_icmpne     186
     146: aload_0
     147: iconst_4
     148: invokevirtual #25                 // Method java/util/ArrayList.get:(I)Ljava/lang/Object;
     151: checkcast     #26                 // class "[B"
     154: invokestatic  #38                 // Method org/apache/hadoop/hbase/filter/ParseFilter.convertByteArrayToBoolean:([B)Z
     157: istore        6
     159: aload_0
     160: iconst_5
     161: invokevirtual #25                 // Method java/util/ArrayList.get:(I)Ljava/lang/Object;
     164: checkcast     #26                 // class "[B"
     167: invokestatic  #38                 // Method org/apache/hadoop/hbase/filter/ParseFilter.convertByteArrayToBoolean:([B)Z
     170: istore        7
     172: aload         5
     174: iload         6
     176: invokevirtual #39                 // Method setFilterIfMissing:(Z)V
     179: aload         5
     181: iload         7
     183: invokevirtual #40                 // Method setLatestVersionOnly:(Z)V
     186: aload         5
     188: areturn

  org.apache.hadoop.hbase.shaded.protobuf.generated.FilterProtos$SingleColumnValueFilter convert();
    Code:
       0: invokestatic  #41                 // Method org/apache/hadoop/hbase/shaded/protobuf/generated/FilterProtos$SingleColumnValueFilter.newBuilder:()Lorg/apache/hadoop/hbase/shaded/protobuf/generated/FilterProtos$SingleColumnValueFilter$Builder;
       3: astore_1
       4: aload_0
       5: getfield      #9                  // Field columnFamily:[B
       8: ifnull        23
      11: aload_1
      12: aload_0
      13: getfield      #9                  // Field columnFamily:[B
      16: invokestatic  #42                 // Method org/apache/hbase/thirdparty/com/google/protobuf/UnsafeByteOperations.unsafeWrap:([B)Lorg/apache/hbase/thirdparty/com/google/protobuf/ByteString;
      19: invokevirtual #43                 // Method org/apache/hadoop/hbase/shaded/protobuf/generated/FilterProtos$SingleColumnValueFilter$Builder.setColumnFamily:(Lorg/apache/hbase/thirdparty/com/google/protobuf/ByteString;)Lorg/apache/hadoop/hbase/shaded/protobuf/generated/FilterProtos$SingleColumnValueFilter$Builder;
      22: pop
      23: aload_0
      24: getfield      #10                 // Field columnQualifier:[B
      27: ifnull        42
      30: aload_1
      31: aload_0
      32: getfield      #10                 // Field columnQualifier:[B
      35: invokestatic  #42                 // Method org/apache/hbase/thirdparty/com/google/protobuf/UnsafeByteOperations.unsafeWrap:([B)Lorg/apache/hbase/thirdparty/com/google/protobuf/ByteString;
      38: invokevirtual #44                 // Method org/apache/hadoop/hbase/shaded/protobuf/generated/FilterProtos$SingleColumnValueFilter$Builder.setColumnQualifier:(Lorg/apache/hbase/thirdparty/com/google/protobuf/ByteString;)Lorg/apache/hadoop/hbase/shaded/protobuf/generated/FilterProtos$SingleColumnValueFilter$Builder;
      41: pop
      42: aload_0
      43: getfield      #11                 // Field op:Lorg/apache/hadoop/hbase/CompareOperator;
      46: invokevirtual #13                 // Method org/apache/hadoop/hbase/CompareOperator.name:()Ljava/lang/String;
      49: invokestatic  #45                 // Method org/apache/hadoop/hbase/shaded/protobuf/generated/HBaseProtos$CompareType.valueOf:(Ljava/lang/String;)Lorg/apache/hadoop/hbase/shaded/protobuf/generated/HBaseProtos$CompareType;
      52: astore_2
      53: aload_1
      54: aload_2
      55: invokevirtual #46                 // Method org/apache/hadoop/hbase/shaded/protobuf/generated/FilterProtos$SingleColumnValueFilter$Builder.setCompareOp:(Lorg/apache/hadoop/hbase/shaded/protobuf/generated/HBaseProtos$CompareType;)Lorg/apache/hadoop/hbase/shaded/protobuf/generated/FilterProtos$SingleColumnValueFilter$Builder;
      58: pop
      59: aload_1
      60: aload_0
      61: getfield      #12                 // Field comparator:Lorg/apache/hadoop/hbase/filter/ByteArrayComparable;
      64: invokestatic  #47                 // Method org/apache/hadoop/hbase/shaded/protobuf/ProtobufUtil.toComparator:(Lorg/apache/hadoop/hbase/filter/ByteArrayComparable;)Lorg/apache/hadoop/hbase/shaded/protobuf/generated/ComparatorProtos$Comparator;
      67: invokevirtual #48                 // Method org/apache/hadoop/hbase/shaded/protobuf/generated/FilterProtos$SingleColumnValueFilter$Builder.setComparator:(Lorg/apache/hadoop/hbase/shaded/protobuf/generated/ComparatorProtos$Comparator;)Lorg/apache/hadoop/hbase/shaded/protobuf/generated/FilterProtos$SingleColumnValueFilter$Builder;
      70: pop
      71: aload_1
      72: aload_0
      73: getfield      #7                  // Field filterIfMissing:Z
      76: invokevirtual #49                 // Method org/apache/hadoop/hbase/shaded/protobuf/generated/FilterProtos$SingleColumnValueFilter$Builder.setFilterIfMissing:(Z)Lorg/apache/hadoop/hbase/shaded/protobuf/generated/FilterProtos$SingleColumnValueFilter$Builder;
      79: pop
      80: aload_1
      81: aload_0
      82: getfield      #8                  // Field latestVersionOnly:Z
      85: invokevirtual #50                 // Method org/apache/hadoop/hbase/shaded/protobuf/generated/FilterProtos$SingleColumnValueFilter$Builder.setLatestVersionOnly:(Z)Lorg/apache/hadoop/hbase/shaded/protobuf/generated/FilterProtos$SingleColumnValueFilter$Builder;
      88: pop
      89: aload_1
      90: invokevirtual #51                 // Method org/apache/hadoop/hbase/shaded/protobuf/generated/FilterProtos$SingleColumnValueFilter$Builder.build:()Lorg/apache/hadoop/hbase/shaded/protobuf/generated/FilterProtos$SingleColumnValueFilter;
      93: areturn

  public byte[] toByteArray();
    Code:
       0: aload_0
       1: invokevirtual #52                 // Method convert:()Lorg/apache/hadoop/hbase/shaded/protobuf/generated/FilterProtos$SingleColumnValueFilter;
       4: invokevirtual #53                 // Method org/apache/hadoop/hbase/shaded/protobuf/generated/FilterProtos$SingleColumnValueFilter.toByteArray:()[B
       7: areturn

  public static org.apache.hadoop.hbase.filter.SingleColumnValueFilter parseFrom(byte[]) throws org.apache.hadoop.hbase.exceptions.DeserializationException;
    Code:
       0: aload_0
       1: invokestatic  #54                 // Method org/apache/hadoop/hbase/shaded/protobuf/generated/FilterProtos$SingleColumnValueFilter.parseFrom:([B)Lorg/apache/hadoop/hbase/shaded/protobuf/generated/FilterProtos$SingleColumnValueFilter;
       4: astore_1
       5: goto          18
       8: astore_2
       9: new           #56                 // class org/apache/hadoop/hbase/exceptions/DeserializationException
      12: dup
      13: aload_2
      14: invokespecial #57                 // Method org/apache/hadoop/hbase/exceptions/DeserializationException."<init>":(Ljava/lang/Throwable;)V
      17: athrow
      18: aload_1
      19: invokevirtual #58                 // Method org/apache/hadoop/hbase/shaded/protobuf/generated/FilterProtos$SingleColumnValueFilter.getCompareOp:()Lorg/apache/hadoop/hbase/shaded/protobuf/generated/HBaseProtos$CompareType;
      22: invokevirtual #59                 // Method org/apache/hadoop/hbase/shaded/protobuf/generated/HBaseProtos$CompareType.name:()Ljava/lang/String;
      25: invokestatic  #14                 // Method org/apache/hadoop/hbase/CompareOperator.valueOf:(Ljava/lang/String;)Lorg/apache/hadoop/hbase/CompareOperator;
      28: astore_2
      29: aload_1
      30: invokevirtual #60                 // Method org/apache/hadoop/hbase/shaded/protobuf/generated/FilterProtos$SingleColumnValueFilter.getComparator:()Lorg/apache/hadoop/hbase/shaded/protobuf/generated/ComparatorProtos$Comparator;
      33: invokestatic  #61                 // Method org/apache/hadoop/hbase/shaded/protobuf/ProtobufUtil.toComparator:(Lorg/apache/hadoop/hbase/shaded/protobuf/generated/ComparatorProtos$Comparator;)Lorg/apache/hadoop/hbase/filter/ByteArrayComparable;
      36: astore_3
      37: goto          52
      40: astore        4
      42: new           #56                 // class org/apache/hadoop/hbase/exceptions/DeserializationException
      45: dup
      46: aload         4
      48: invokespecial #57                 // Method org/apache/hadoop/hbase/exceptions/DeserializationException."<init>":(Ljava/lang/Throwable;)V
      51: athrow
      52: new           #37                 // class org/apache/hadoop/hbase/filter/SingleColumnValueFilter
      55: dup
      56: aload_1
      57: invokevirtual #63                 // Method org/apache/hadoop/hbase/shaded/protobuf/generated/FilterProtos$SingleColumnValueFilter.hasColumnFamily:()Z
      60: ifeq          73
      63: aload_1
      64: invokevirtual #64                 // Method org/apache/hadoop/hbase/shaded/protobuf/generated/FilterProtos$SingleColumnValueFilter.getColumnFamily:()Lorg/apache/hbase/thirdparty/com/google/protobuf/ByteString;
      67: invokevirtual #65                 // Method org/apache/hbase/thirdparty/com/google/protobuf/ByteString.toByteArray:()[B
      70: goto          74
      73: aconst_null
      74: aload_1
      75: invokevirtual #66                 // Method org/apache/hadoop/hbase/shaded/protobuf/generated/FilterProtos$SingleColumnValueFilter.hasColumnQualifier:()Z
      78: ifeq          91
      81: aload_1
      82: invokevirtual #67                 // Method org/apache/hadoop/hbase/shaded/protobuf/generated/FilterProtos$SingleColumnValueFilter.getColumnQualifier:()Lorg/apache/hbase/thirdparty/com/google/protobuf/ByteString;
      85: invokevirtual #65                 // Method org/apache/hbase/thirdparty/com/google/protobuf/ByteString.toByteArray:()[B
      88: goto          92
      91: aconst_null
      92: aload_2
      93: aload_3
      94: aload_1
      95: invokevirtual #68                 // Method org/apache/hadoop/hbase/shaded/protobuf/generated/FilterProtos$SingleColumnValueFilter.getFilterIfMissing:()Z
      98: aload_1
      99: invokevirtual #69                 // Method org/apache/hadoop/hbase/shaded/protobuf/generated/FilterProtos$SingleColumnValueFilter.getLatestVersionOnly:()Z
     102: invokespecial #70                 // Method "<init>":([B[BLorg/apache/hadoop/hbase/CompareOperator;Lorg/apache/hadoop/hbase/filter/ByteArrayComparable;ZZ)V
     105: areturn
    Exception table:
       from    to  target type
           0     5     8   Class org/apache/hbase/thirdparty/com/google/protobuf/InvalidProtocolBufferException
          29    37    40   Class java/io/IOException

  boolean areSerializedFieldsEqual(org.apache.hadoop.hbase.filter.Filter);
    Code:
       0: aload_1
       1: aload_0
       2: if_acmpne     7
       5: iconst_1
       6: ireturn
       7: aload_1
       8: instanceof    #37                 // class org/apache/hadoop/hbase/filter/SingleColumnValueFilter
      11: ifne          16
      14: iconst_0
      15: ireturn
      16: aload_1
      17: checkcast     #37                 // class org/apache/hadoop/hbase/filter/SingleColumnValueFilter
      20: astore_2
      21: aload_0
      22: invokevirtual #71                 // Method getFamily:()[B
      25: aload_2
      26: invokevirtual #71                 // Method getFamily:()[B
      29: invokestatic  #72                 // Method org/apache/hadoop/hbase/util/Bytes.equals:([B[B)Z
      32: ifeq          103
      35: aload_0
      36: invokevirtual #73                 // Method getQualifier:()[B
      39: aload_2
      40: invokevirtual #73                 // Method getQualifier:()[B
      43: invokestatic  #72                 // Method org/apache/hadoop/hbase/util/Bytes.equals:([B[B)Z
      46: ifeq          103
      49: aload_0
      50: getfield      #11                 // Field op:Lorg/apache/hadoop/hbase/CompareOperator;
      53: aload_2
      54: getfield      #11                 // Field op:Lorg/apache/hadoop/hbase/CompareOperator;
      57: invokevirtual #74                 // Method org/apache/hadoop/hbase/CompareOperator.equals:(Ljava/lang/Object;)Z
      60: ifeq          103
      63: aload_0
      64: invokevirtual #75                 // Method getComparator:()Lorg/apache/hadoop/hbase/filter/ByteArrayComparable;
      67: aload_2
      68: invokevirtual #75                 // Method getComparator:()Lorg/apache/hadoop/hbase/filter/ByteArrayComparable;
      71: invokevirtual #76                 // Method org/apache/hadoop/hbase/filter/ByteArrayComparable.areSerializedFieldsEqual:(Lorg/apache/hadoop/hbase/filter/ByteArrayComparable;)Z
      74: ifeq          103
      77: aload_0
      78: invokevirtual #77                 // Method getFilterIfMissing:()Z
      81: aload_2
      82: invokevirtual #77                 // Method getFilterIfMissing:()Z
      85: if_icmpne     103
      88: aload_0
      89: invokevirtual #78                 // Method getLatestVersionOnly:()Z
      92: aload_2
      93: invokevirtual #78                 // Method getLatestVersionOnly:()Z
      96: if_icmpne     103
      99: iconst_1
     100: goto          104
     103: iconst_0
     104: ireturn

  public boolean isFamilyEssential(byte[]);
    Code:
       0: aload_0
       1: getfield      #7                  // Field filterIfMissing:Z
       4: ifeq          18
       7: aload_1
       8: aload_0
       9: getfield      #9                  // Field columnFamily:[B
      12: invokestatic  #72                 // Method org/apache/hadoop/hbase/util/Bytes.equals:([B[B)Z
      15: ifeq          22
      18: iconst_1
      19: goto          23
      22: iconst_0
      23: ireturn

  public java.lang.String toString();
    Code:
       0: ldc           #79                 // String %s (%s, %s, %s, %s)
       2: iconst_5
       3: anewarray     #80                 // class java/lang/Object
       6: dup
       7: iconst_0
       8: aload_0
       9: invokevirtual #81                 // Method java/lang/Object.getClass:()Ljava/lang/Class;
      12: invokevirtual #82                 // Method java/lang/Class.getSimpleName:()Ljava/lang/String;
      15: aastore
      16: dup
      17: iconst_1
      18: aload_0
      19: getfield      #9                  // Field columnFamily:[B
      22: invokestatic  #83                 // Method org/apache/hadoop/hbase/util/Bytes.toStringBinary:([B)Ljava/lang/String;
      25: aastore
      26: dup
      27: iconst_2
      28: aload_0
      29: getfield      #10                 // Field columnQualifier:[B
      32: invokestatic  #83                 // Method org/apache/hadoop/hbase/util/Bytes.toStringBinary:([B)Ljava/lang/String;
      35: aastore
      36: dup
      37: iconst_3
      38: aload_0
      39: getfield      #11                 // Field op:Lorg/apache/hadoop/hbase/CompareOperator;
      42: invokevirtual #13                 // Method org/apache/hadoop/hbase/CompareOperator.name:()Ljava/lang/String;
      45: aastore
      46: dup
      47: iconst_4
      48: aload_0
      49: getfield      #12                 // Field comparator:Lorg/apache/hadoop/hbase/filter/ByteArrayComparable;
      52: invokevirtual #84                 // Method org/apache/hadoop/hbase/filter/ByteArrayComparable.getValue:()[B
      55: invokestatic  #83                 // Method org/apache/hadoop/hbase/util/Bytes.toStringBinary:([B)Ljava/lang/String;
      58: aastore
      59: invokestatic  #85                 // Method java/lang/String.format:(Ljava/lang/String;[Ljava/lang/Object;)Ljava/lang/String;
      62: areturn

  public boolean equals(java.lang.Object);
    Code:
       0: aload_1
       1: instanceof    #86                 // class org/apache/hadoop/hbase/filter/Filter
       4: ifeq          22
       7: aload_0
       8: aload_1
       9: checkcast     #86                 // class org/apache/hadoop/hbase/filter/Filter
      12: invokevirtual #87                 // Method areSerializedFieldsEqual:(Lorg/apache/hadoop/hbase/filter/Filter;)Z
      15: ifeq          22
      18: iconst_1
      19: goto          23
      22: iconst_0
      23: ireturn

  public int hashCode();
    Code:
       0: bipush        6
       2: anewarray     #80                 // class java/lang/Object
       5: dup
       6: iconst_0
       7: aload_0
       8: invokevirtual #71                 // Method getFamily:()[B
      11: invokestatic  #88                 // Method org/apache/hadoop/hbase/util/Bytes.hashCode:([B)I
      14: invokestatic  #89                 // Method java/lang/Integer.valueOf:(I)Ljava/lang/Integer;
      17: aastore
      18: dup
      19: iconst_1
      20: aload_0
      21: invokevirtual #73                 // Method getQualifier:()[B
      24: invokestatic  #88                 // Method org/apache/hadoop/hbase/util/Bytes.hashCode:([B)I
      27: invokestatic  #89                 // Method java/lang/Integer.valueOf:(I)Ljava/lang/Integer;
      30: aastore
      31: dup
      32: iconst_2
      33: aload_0
      34: getfield      #11                 // Field op:Lorg/apache/hadoop/hbase/CompareOperator;
      37: aastore
      38: dup
      39: iconst_3
      40: aload_0
      41: invokevirtual #75                 // Method getComparator:()Lorg/apache/hadoop/hbase/filter/ByteArrayComparable;
      44: aastore
      45: dup
      46: iconst_4
      47: aload_0
      48: invokevirtual #77                 // Method getFilterIfMissing:()Z
      51: invokestatic  #90                 // Method java/lang/Boolean.valueOf:(Z)Ljava/lang/Boolean;
      54: aastore
      55: dup
      56: iconst_5
      57: aload_0
      58: invokevirtual #78                 // Method getLatestVersionOnly:()Z
      61: invokestatic  #90                 // Method java/lang/Boolean.valueOf:(Z)Ljava/lang/Boolean;
      64: aastore
      65: invokestatic  #91                 // Method java/util/Objects.hash:([Ljava/lang/Object;)I
      68: ireturn
}
