Compiled from "SinusoidalFileListGenerator.java"
class org.apache.hadoop.hbase.regionserver.compactions.SinusoidalFileListGenerator extends org.apache.hadoop.hbase.regionserver.compactions.StoreFileListGenerator {
  org.apache.hadoop.hbase.regionserver.compactions.SinusoidalFileListGenerator();
    Code:
       0: aload_0
       1: ldc           #1                  // class org/apache/hadoop/hbase/regionserver/compactions/SinusoidalFileListGenerator
       3: invokespecial #2                  // Method org/apache/hadoop/hbase/regionserver/compactions/StoreFileListGenerator."<init>":(Ljava/lang/Class;)V
       6: return

  public java.util.Iterator<java.util.List<org.apache.hadoop.hbase.regionserver.HStoreFile>> iterator();
    Code:
       0: new           #3                  // class org/apache/hadoop/hbase/regionserver/compactions/SinusoidalFileListGenerator$1
       3: dup
       4: aload_0
       5: invokespecial #4                  // Method org/apache/hadoop/hbase/regionserver/compactions/SinusoidalFileListGenerator$1."<init>":(Lorg/apache/hadoop/hbase/regionserver/compactions/SinusoidalFileListGenerator;)V
       8: areturn
}
