Compiled from "SizeCachedNoTagsKeyValue.java"
public class org.apache.hadoop.hbase.SizeCachedNoTagsKeyValue extends org.apache.hadoop.hbase.SizeCachedKeyValue {
  public org.apache.hadoop.hbase.SizeCachedNoTagsKeyValue(byte[], int, int, long);
    Code:
       0: aload_0
       1: aload_1
       2: iload_2
       3: iload_3
       4: lload         4
       6: invokespecial #1                  // Method org/apache/hadoop/hbase/SizeCachedKeyValue."<init>":([BIIJ)V
       9: return

  public int getTagsLength();
    Code:
       0: iconst_0
       1: ireturn

  public int write(java.io.OutputStream, boolean) throws java.io.IOException;
    Code:
       0: aload_1
       1: aload_0
       2: getfield      #2                  // Field bytes:[B
       5: aload_0
       6: getfield      #3                  // Field offset:I
       9: aload_0
      10: getfield      #4                  // Field length:I
      13: invokevirtual #5                  // Method java/io/OutputStream.write:([BII)V
      16: aload_0
      17: getfield      #4                  // Field length:I
      20: ireturn

  public int getSerializedSize(boolean);
    Code:
       0: aload_0
       1: getfield      #4                  // Field length:I
       4: ireturn
}
