Compiled from "SnapshotReferenceUtil.java"
final class org.apache.hadoop.hbase.snapshot.SnapshotReferenceUtil$3 implements org.apache.hadoop.hbase.snapshot.SnapshotReferenceUtil$StoreFileVisitor {
  final java.util.Set val$names;

  org.apache.hadoop.hbase.snapshot.SnapshotReferenceUtil$3(java.util.Set);
    Code:
       0: aload_0
       1: aload_1
       2: putfield      #1                  // Field val$names:Ljava/util/Set;
       5: aload_0
       6: invokespecial #2                  // Method java/lang/Object."<init>":()V
       9: return

  public void storeFile(org.apache.hadoop.hbase.client.RegionInfo, java.lang.String, org.apache.hadoop.hbase.shaded.protobuf.generated.SnapshotProtos$SnapshotRegionManifest$StoreFile) throws java.io.IOException;
    Code:
       0: aload_3
       1: invokevirtual #3                  // Method org/apache/hadoop/hbase/shaded/protobuf/generated/SnapshotProtos$SnapshotRegionManifest$StoreFile.getName:()Ljava/lang/String;
       4: astore        4
       6: aload         4
       8: invokestatic  #4                  // Method org/apache/hadoop/hbase/io/HFileLink.isHFileLink:(Ljava/lang/String;)Z
      11: ifeq          32
      14: aload_0
      15: getfield      #1                  // Field val$names:Ljava/util/Set;
      18: aload         4
      20: invokestatic  #5                  // Method org/apache/hadoop/hbase/io/HFileLink.getReferencedHFileName:(Ljava/lang/String;)Ljava/lang/String;
      23: invokeinterface #6,  2            // InterfaceMethod java/util/Set.add:(Ljava/lang/Object;)Z
      28: pop
      29: goto          44
      32: aload_0
      33: getfield      #1                  // Field val$names:Ljava/util/Set;
      36: aload         4
      38: invokeinterface #6,  2            // InterfaceMethod java/util/Set.add:(Ljava/lang/Object;)Z
      43: pop
      44: return
}
