Compiled from "SnapshotInfo.java"
class org.apache.hadoop.hbase.snapshot.SnapshotInfo$1 implements org.apache.hadoop.hbase.snapshot.SnapshotReferenceUtil$SnapshotVisitor {
  final org.apache.hadoop.hbase.snapshot.SnapshotInfo$SnapshotStats val$stats;

  final boolean val$showFiles;

  final java.lang.String val$table;

  final org.apache.hadoop.hbase.snapshot.SnapshotInfo this$0;

  org.apache.hadoop.hbase.snapshot.SnapshotInfo$1(org.apache.hadoop.hbase.snapshot.SnapshotInfo, org.apache.hadoop.hbase.snapshot.SnapshotInfo$SnapshotStats, boolean, java.lang.String);
    Code:
       0: aload_0
       1: aload_1
       2: putfield      #1                  // Field this$0:Lorg/apache/hadoop/hbase/snapshot/SnapshotInfo;
       5: aload_0
       6: aload_2
       7: putfield      #2                  // Field val$stats:Lorg/apache/hadoop/hbase/snapshot/SnapshotInfo$SnapshotStats;
      10: aload_0
      11: iload_3
      12: putfield      #3                  // Field val$showFiles:Z
      15: aload_0
      16: aload         4
      18: putfield      #4                  // Field val$table:Ljava/lang/String;
      21: aload_0
      22: invokespecial #5                  // Method java/lang/Object."<init>":()V
      25: return

  public void storeFile(org.apache.hadoop.hbase.client.RegionInfo, java.lang.String, org.apache.hadoop.hbase.shaded.protobuf.generated.SnapshotProtos$SnapshotRegionManifest$StoreFile) throws java.io.IOException;
    Code:
       0: aload_3
       1: invokevirtual #6                  // Method org/apache/hadoop/hbase/shaded/protobuf/generated/SnapshotProtos$SnapshotRegionManifest$StoreFile.hasReference:()Z
       4: ifeq          8
       7: return
       8: aload_0
       9: getfield      #2                  // Field val$stats:Lorg/apache/hadoop/hbase/snapshot/SnapshotInfo$SnapshotStats;
      12: aload_1
      13: aload_2
      14: aload_3
      15: aconst_null
      16: invokevirtual #7                  // Method org/apache/hadoop/hbase/snapshot/SnapshotInfo$SnapshotStats.addStoreFile:(Lorg/apache/hadoop/hbase/client/RegionInfo;Ljava/lang/String;Lorg/apache/hadoop/hbase/shaded/protobuf/generated/SnapshotProtos$SnapshotRegionManifest$StoreFile;Ljava/util/Map;)Lorg/apache/hadoop/hbase/snapshot/SnapshotInfo$SnapshotStats$FileInfo;
      19: astore        4
      21: aload_0
      22: getfield      #3                  // Field val$showFiles:Z
      25: ifeq          142
      28: aload         4
      30: invokevirtual #8                  // Method org/apache/hadoop/hbase/snapshot/SnapshotInfo$SnapshotStats$FileInfo.getStateToString:()Ljava/lang/String;
      33: astore        5
      35: getstatic     #9                  // Field java/lang/System.out:Ljava/io/PrintStream;
      38: ldc           #10                 // String %8s %s/%s/%s/%s %s%n
      40: bipush        6
      42: anewarray     #11                 // class java/lang/Object
      45: dup
      46: iconst_0
      47: aload         4
      49: invokevirtual #12                 // Method org/apache/hadoop/hbase/snapshot/SnapshotInfo$SnapshotStats$FileInfo.isMissing:()Z
      52: ifeq          60
      55: ldc           #13                 // String -
      57: goto          72
      60: aload_0
      61: getfield      #1                  // Field this$0:Lorg/apache/hadoop/hbase/snapshot/SnapshotInfo;
      64: aload         4
      66: invokevirtual #14                 // Method org/apache/hadoop/hbase/snapshot/SnapshotInfo$SnapshotStats$FileInfo.getSize:()J
      69: invokestatic  #15                 // Method org/apache/hadoop/hbase/snapshot/SnapshotInfo.access$000:(Lorg/apache/hadoop/hbase/snapshot/SnapshotInfo;J)Ljava/lang/String;
      72: aastore
      73: dup
      74: iconst_1
      75: aload_0
      76: getfield      #4                  // Field val$table:Ljava/lang/String;
      79: aastore
      80: dup
      81: iconst_2
      82: aload_1
      83: invokeinterface #16,  1           // InterfaceMethod org/apache/hadoop/hbase/client/RegionInfo.getEncodedName:()Ljava/lang/String;
      88: aastore
      89: dup
      90: iconst_3
      91: aload_2
      92: aastore
      93: dup
      94: iconst_4
      95: aload_3
      96: invokevirtual #17                 // Method org/apache/hadoop/hbase/shaded/protobuf/generated/SnapshotProtos$SnapshotRegionManifest$StoreFile.getName:()Ljava/lang/String;
      99: aastore
     100: dup
     101: iconst_5
     102: aload         5
     104: ifnonnull     112
     107: ldc           #18                 // String
     109: goto          137
     112: new           #19                 // class java/lang/StringBuilder
     115: dup
     116: invokespecial #20                 // Method java/lang/StringBuilder."<init>":()V
     119: ldc           #21                 // String (
     121: invokevirtual #22                 // Method java/lang/StringBuilder.append:(Ljava/lang/String;)Ljava/lang/StringBuilder;
     124: aload         5
     126: invokevirtual #22                 // Method java/lang/StringBuilder.append:(Ljava/lang/String;)Ljava/lang/StringBuilder;
     129: ldc           #23                 // String )
     131: invokevirtual #22                 // Method java/lang/StringBuilder.append:(Ljava/lang/String;)Ljava/lang/StringBuilder;
     134: invokevirtual #24                 // Method java/lang/StringBuilder.toString:()Ljava/lang/String;
     137: aastore
     138: invokevirtual #25                 // Method java/io/PrintStream.printf:(Ljava/lang/String;[Ljava/lang/Object;)Ljava/io/PrintStream;
     141: pop
     142: return
}
