Compiled from "SnapshotInfo.java"
public class org.apache.hadoop.hbase.snapshot.SnapshotInfo$SnapshotStats {
  org.apache.hadoop.hbase.snapshot.SnapshotInfo$SnapshotStats(org.apache.hadoop.conf.Configuration, org.apache.hadoop.fs.FileSystem, org.apache.hadoop.hbase.client.SnapshotDescription);
    Code:
       0: aload_0
       1: invokespecial #1                  // Method java/lang/Object."<init>":()V
       4: aload_0
       5: new           #2                  // class java/util/concurrent/atomic/AtomicInteger
       8: dup
       9: invokespecial #3                  // Method java/util/concurrent/atomic/AtomicInteger."<init>":()V
      12: putfield      #4                  // Field hfilesArchiveCount:Ljava/util/concurrent/atomic/AtomicInteger;
      15: aload_0
      16: new           #2                  // class java/util/concurrent/atomic/AtomicInteger
      19: dup
      20: invokespecial #3                  // Method java/util/concurrent/atomic/AtomicInteger."<init>":()V
      23: putfield      #5                  // Field hfilesCorrupted:Ljava/util/concurrent/atomic/AtomicInteger;
      26: aload_0
      27: new           #2                  // class java/util/concurrent/atomic/AtomicInteger
      30: dup
      31: invokespecial #3                  // Method java/util/concurrent/atomic/AtomicInteger."<init>":()V
      34: putfield      #6                  // Field hfilesMissing:Ljava/util/concurrent/atomic/AtomicInteger;
      37: aload_0
      38: new           #2                  // class java/util/concurrent/atomic/AtomicInteger
      41: dup
      42: invokespecial #3                  // Method java/util/concurrent/atomic/AtomicInteger."<init>":()V
      45: putfield      #7                  // Field hfilesCount:Ljava/util/concurrent/atomic/AtomicInteger;
      48: aload_0
      49: new           #2                  // class java/util/concurrent/atomic/AtomicInteger
      52: dup
      53: invokespecial #3                  // Method java/util/concurrent/atomic/AtomicInteger."<init>":()V
      56: putfield      #8                  // Field hfilesMobCount:Ljava/util/concurrent/atomic/AtomicInteger;
      59: aload_0
      60: new           #2                  // class java/util/concurrent/atomic/AtomicInteger
      63: dup
      64: invokespecial #3                  // Method java/util/concurrent/atomic/AtomicInteger."<init>":()V
      67: putfield      #9                  // Field logsMissing:Ljava/util/concurrent/atomic/AtomicInteger;
      70: aload_0
      71: new           #2                  // class java/util/concurrent/atomic/AtomicInteger
      74: dup
      75: invokespecial #3                  // Method java/util/concurrent/atomic/AtomicInteger."<init>":()V
      78: putfield      #10                 // Field logsCount:Ljava/util/concurrent/atomic/AtomicInteger;
      81: aload_0
      82: new           #11                 // class java/util/concurrent/atomic/AtomicLong
      85: dup
      86: invokespecial #12                 // Method java/util/concurrent/atomic/AtomicLong."<init>":()V
      89: putfield      #13                 // Field hfilesArchiveSize:Ljava/util/concurrent/atomic/AtomicLong;
      92: aload_0
      93: new           #11                 // class java/util/concurrent/atomic/AtomicLong
      96: dup
      97: invokespecial #12                 // Method java/util/concurrent/atomic/AtomicLong."<init>":()V
     100: putfield      #14                 // Field hfilesSize:Ljava/util/concurrent/atomic/AtomicLong;
     103: aload_0
     104: new           #11                 // class java/util/concurrent/atomic/AtomicLong
     107: dup
     108: invokespecial #12                 // Method java/util/concurrent/atomic/AtomicLong."<init>":()V
     111: putfield      #15                 // Field hfilesMobSize:Ljava/util/concurrent/atomic/AtomicLong;
     114: aload_0
     115: new           #11                 // class java/util/concurrent/atomic/AtomicLong
     118: dup
     119: invokespecial #12                 // Method java/util/concurrent/atomic/AtomicLong."<init>":()V
     122: putfield      #16                 // Field nonSharedHfilesArchiveSize:Ljava/util/concurrent/atomic/AtomicLong;
     125: aload_0
     126: new           #11                 // class java/util/concurrent/atomic/AtomicLong
     129: dup
     130: invokespecial #12                 // Method java/util/concurrent/atomic/AtomicLong."<init>":()V
     133: putfield      #17                 // Field logSize:Ljava/util/concurrent/atomic/AtomicLong;
     136: aload_0
     137: aload_3
     138: invokestatic  #18                 // Method org/apache/hadoop/hbase/shaded/protobuf/ProtobufUtil.createHBaseProtosSnapshotDesc:(Lorg/apache/hadoop/hbase/client/SnapshotDescription;)Lorg/apache/hadoop/hbase/shaded/protobuf/generated/SnapshotProtos$SnapshotDescription;
     141: putfield      #19                 // Field snapshot:Lorg/apache/hadoop/hbase/shaded/protobuf/generated/SnapshotProtos$SnapshotDescription;
     144: aload_0
     145: aload_3
     146: invokevirtual #20                 // Method org/apache/hadoop/hbase/client/SnapshotDescription.getTableName:()Lorg/apache/hadoop/hbase/TableName;
     149: putfield      #21                 // Field snapshotTable:Lorg/apache/hadoop/hbase/TableName;
     152: aload_0
     153: aload_1
     154: putfield      #22                 // Field conf:Lorg/apache/hadoop/conf/Configuration;
     157: aload_0
     158: aload_2
     159: putfield      #23                 // Field fs:Lorg/apache/hadoop/fs/FileSystem;
     162: return

  org.apache.hadoop.hbase.snapshot.SnapshotInfo$SnapshotStats(org.apache.hadoop.conf.Configuration, org.apache.hadoop.fs.FileSystem, org.apache.hadoop.hbase.shaded.protobuf.generated.SnapshotProtos$SnapshotDescription);
    Code:
       0: aload_0
       1: invokespecial #1                  // Method java/lang/Object."<init>":()V
       4: aload_0
       5: new           #2                  // class java/util/concurrent/atomic/AtomicInteger
       8: dup
       9: invokespecial #3                  // Method java/util/concurrent/atomic/AtomicInteger."<init>":()V
      12: putfield      #4                  // Field hfilesArchiveCount:Ljava/util/concurrent/atomic/AtomicInteger;
      15: aload_0
      16: new           #2                  // class java/util/concurrent/atomic/AtomicInteger
      19: dup
      20: invokespecial #3                  // Method java/util/concurrent/atomic/AtomicInteger."<init>":()V
      23: putfield      #5                  // Field hfilesCorrupted:Ljava/util/concurrent/atomic/AtomicInteger;
      26: aload_0
      27: new           #2                  // class java/util/concurrent/atomic/AtomicInteger
      30: dup
      31: invokespecial #3                  // Method java/util/concurrent/atomic/AtomicInteger."<init>":()V
      34: putfield      #6                  // Field hfilesMissing:Ljava/util/concurrent/atomic/AtomicInteger;
      37: aload_0
      38: new           #2                  // class java/util/concurrent/atomic/AtomicInteger
      41: dup
      42: invokespecial #3                  // Method java/util/concurrent/atomic/AtomicInteger."<init>":()V
      45: putfield      #7                  // Field hfilesCount:Ljava/util/concurrent/atomic/AtomicInteger;
      48: aload_0
      49: new           #2                  // class java/util/concurrent/atomic/AtomicInteger
      52: dup
      53: invokespecial #3                  // Method java/util/concurrent/atomic/AtomicInteger."<init>":()V
      56: putfield      #8                  // Field hfilesMobCount:Ljava/util/concurrent/atomic/AtomicInteger;
      59: aload_0
      60: new           #2                  // class java/util/concurrent/atomic/AtomicInteger
      63: dup
      64: invokespecial #3                  // Method java/util/concurrent/atomic/AtomicInteger."<init>":()V
      67: putfield      #9                  // Field logsMissing:Ljava/util/concurrent/atomic/AtomicInteger;
      70: aload_0
      71: new           #2                  // class java/util/concurrent/atomic/AtomicInteger
      74: dup
      75: invokespecial #3                  // Method java/util/concurrent/atomic/AtomicInteger."<init>":()V
      78: putfield      #10                 // Field logsCount:Ljava/util/concurrent/atomic/AtomicInteger;
      81: aload_0
      82: new           #11                 // class java/util/concurrent/atomic/AtomicLong
      85: dup
      86: invokespecial #12                 // Method java/util/concurrent/atomic/AtomicLong."<init>":()V
      89: putfield      #13                 // Field hfilesArchiveSize:Ljava/util/concurrent/atomic/AtomicLong;
      92: aload_0
      93: new           #11                 // class java/util/concurrent/atomic/AtomicLong
      96: dup
      97: invokespecial #12                 // Method java/util/concurrent/atomic/AtomicLong."<init>":()V
     100: putfield      #14                 // Field hfilesSize:Ljava/util/concurrent/atomic/AtomicLong;
     103: aload_0
     104: new           #11                 // class java/util/concurrent/atomic/AtomicLong
     107: dup
     108: invokespecial #12                 // Method java/util/concurrent/atomic/AtomicLong."<init>":()V
     111: putfield      #15                 // Field hfilesMobSize:Ljava/util/concurrent/atomic/AtomicLong;
     114: aload_0
     115: new           #11                 // class java/util/concurrent/atomic/AtomicLong
     118: dup
     119: invokespecial #12                 // Method java/util/concurrent/atomic/AtomicLong."<init>":()V
     122: putfield      #16                 // Field nonSharedHfilesArchiveSize:Ljava/util/concurrent/atomic/AtomicLong;
     125: aload_0
     126: new           #11                 // class java/util/concurrent/atomic/AtomicLong
     129: dup
     130: invokespecial #12                 // Method java/util/concurrent/atomic/AtomicLong."<init>":()V
     133: putfield      #17                 // Field logSize:Ljava/util/concurrent/atomic/AtomicLong;
     136: aload_0
     137: aload_3
     138: putfield      #19                 // Field snapshot:Lorg/apache/hadoop/hbase/shaded/protobuf/generated/SnapshotProtos$SnapshotDescription;
     141: aload_0
     142: aload_3
     143: invokevirtual #24                 // Method org/apache/hadoop/hbase/shaded/protobuf/generated/SnapshotProtos$SnapshotDescription.getTable:()Ljava/lang/String;
     146: invokestatic  #25                 // Method org/apache/hadoop/hbase/TableName.valueOf:(Ljava/lang/String;)Lorg/apache/hadoop/hbase/TableName;
     149: putfield      #21                 // Field snapshotTable:Lorg/apache/hadoop/hbase/TableName;
     152: aload_0
     153: aload_1
     154: putfield      #22                 // Field conf:Lorg/apache/hadoop/conf/Configuration;
     157: aload_0
     158: aload_2
     159: putfield      #23                 // Field fs:Lorg/apache/hadoop/fs/FileSystem;
     162: return

  public org.apache.hadoop.hbase.client.SnapshotDescription getSnapshotDescription();
    Code:
       0: aload_0
       1: getfield      #19                 // Field snapshot:Lorg/apache/hadoop/hbase/shaded/protobuf/generated/SnapshotProtos$SnapshotDescription;
       4: invokestatic  #26                 // Method org/apache/hadoop/hbase/shaded/protobuf/ProtobufUtil.createSnapshotDesc:(Lorg/apache/hadoop/hbase/shaded/protobuf/generated/SnapshotProtos$SnapshotDescription;)Lorg/apache/hadoop/hbase/client/SnapshotDescription;
       7: areturn

  public boolean isSnapshotCorrupted();
    Code:
       0: aload_0
       1: getfield      #6                  // Field hfilesMissing:Ljava/util/concurrent/atomic/AtomicInteger;
       4: invokevirtual #27                 // Method java/util/concurrent/atomic/AtomicInteger.get:()I
       7: ifgt          30
      10: aload_0
      11: getfield      #9                  // Field logsMissing:Ljava/util/concurrent/atomic/AtomicInteger;
      14: invokevirtual #27                 // Method java/util/concurrent/atomic/AtomicInteger.get:()I
      17: ifgt          30
      20: aload_0
      21: getfield      #5                  // Field hfilesCorrupted:Ljava/util/concurrent/atomic/AtomicInteger;
      24: invokevirtual #27                 // Method java/util/concurrent/atomic/AtomicInteger.get:()I
      27: ifle          34
      30: iconst_1
      31: goto          35
      34: iconst_0
      35: ireturn

  public int getStoreFilesCount();
    Code:
       0: aload_0
       1: getfield      #7                  // Field hfilesCount:Ljava/util/concurrent/atomic/AtomicInteger;
       4: invokevirtual #27                 // Method java/util/concurrent/atomic/AtomicInteger.get:()I
       7: aload_0
       8: getfield      #4                  // Field hfilesArchiveCount:Ljava/util/concurrent/atomic/AtomicInteger;
      11: invokevirtual #27                 // Method java/util/concurrent/atomic/AtomicInteger.get:()I
      14: iadd
      15: aload_0
      16: getfield      #8                  // Field hfilesMobCount:Ljava/util/concurrent/atomic/AtomicInteger;
      19: invokevirtual #27                 // Method java/util/concurrent/atomic/AtomicInteger.get:()I
      22: iadd
      23: ireturn

  public int getArchivedStoreFilesCount();
    Code:
       0: aload_0
       1: getfield      #4                  // Field hfilesArchiveCount:Ljava/util/concurrent/atomic/AtomicInteger;
       4: invokevirtual #27                 // Method java/util/concurrent/atomic/AtomicInteger.get:()I
       7: ireturn

  public int getMobStoreFilesCount();
    Code:
       0: aload_0
       1: getfield      #8                  // Field hfilesMobCount:Ljava/util/concurrent/atomic/AtomicInteger;
       4: invokevirtual #27                 // Method java/util/concurrent/atomic/AtomicInteger.get:()I
       7: ireturn

  public int getLogsCount();
    Code:
       0: aload_0
       1: getfield      #10                 // Field logsCount:Ljava/util/concurrent/atomic/AtomicInteger;
       4: invokevirtual #27                 // Method java/util/concurrent/atomic/AtomicInteger.get:()I
       7: ireturn

  public int getMissingStoreFilesCount();
    Code:
       0: aload_0
       1: getfield      #6                  // Field hfilesMissing:Ljava/util/concurrent/atomic/AtomicInteger;
       4: invokevirtual #27                 // Method java/util/concurrent/atomic/AtomicInteger.get:()I
       7: ireturn

  public int getCorruptedStoreFilesCount();
    Code:
       0: aload_0
       1: getfield      #5                  // Field hfilesCorrupted:Ljava/util/concurrent/atomic/AtomicInteger;
       4: invokevirtual #27                 // Method java/util/concurrent/atomic/AtomicInteger.get:()I
       7: ireturn

  public int getMissingLogsCount();
    Code:
       0: aload_0
       1: getfield      #9                  // Field logsMissing:Ljava/util/concurrent/atomic/AtomicInteger;
       4: invokevirtual #27                 // Method java/util/concurrent/atomic/AtomicInteger.get:()I
       7: ireturn

  public long getStoreFilesSize();
    Code:
       0: aload_0
       1: getfield      #14                 // Field hfilesSize:Ljava/util/concurrent/atomic/AtomicLong;
       4: invokevirtual #28                 // Method java/util/concurrent/atomic/AtomicLong.get:()J
       7: aload_0
       8: getfield      #13                 // Field hfilesArchiveSize:Ljava/util/concurrent/atomic/AtomicLong;
      11: invokevirtual #28                 // Method java/util/concurrent/atomic/AtomicLong.get:()J
      14: ladd
      15: aload_0
      16: getfield      #15                 // Field hfilesMobSize:Ljava/util/concurrent/atomic/AtomicLong;
      19: invokevirtual #28                 // Method java/util/concurrent/atomic/AtomicLong.get:()J
      22: ladd
      23: lreturn

  public long getSharedStoreFilesSize();
    Code:
       0: aload_0
       1: getfield      #14                 // Field hfilesSize:Ljava/util/concurrent/atomic/AtomicLong;
       4: invokevirtual #28                 // Method java/util/concurrent/atomic/AtomicLong.get:()J
       7: lreturn

  public long getArchivedStoreFileSize();
    Code:
       0: aload_0
       1: getfield      #13                 // Field hfilesArchiveSize:Ljava/util/concurrent/atomic/AtomicLong;
       4: invokevirtual #28                 // Method java/util/concurrent/atomic/AtomicLong.get:()J
       7: lreturn

  public long getMobStoreFilesSize();
    Code:
       0: aload_0
       1: getfield      #15                 // Field hfilesMobSize:Ljava/util/concurrent/atomic/AtomicLong;
       4: invokevirtual #28                 // Method java/util/concurrent/atomic/AtomicLong.get:()J
       7: lreturn

  public long getNonSharedArchivedStoreFilesSize();
    Code:
       0: aload_0
       1: getfield      #16                 // Field nonSharedHfilesArchiveSize:Ljava/util/concurrent/atomic/AtomicLong;
       4: invokevirtual #28                 // Method java/util/concurrent/atomic/AtomicLong.get:()J
       7: lreturn

  public float getSharedStoreFilePercentage();
    Code:
       0: aload_0
       1: getfield      #14                 // Field hfilesSize:Ljava/util/concurrent/atomic/AtomicLong;
       4: invokevirtual #28                 // Method java/util/concurrent/atomic/AtomicLong.get:()J
       7: l2f
       8: aload_0
       9: invokevirtual #29                 // Method getStoreFilesSize:()J
      12: l2f
      13: fdiv
      14: ldc           #30                 // float 100.0f
      16: fmul
      17: freturn

  public float getMobStoreFilePercentage();
    Code:
       0: aload_0
       1: getfield      #15                 // Field hfilesMobSize:Ljava/util/concurrent/atomic/AtomicLong;
       4: invokevirtual #28                 // Method java/util/concurrent/atomic/AtomicLong.get:()J
       7: l2f
       8: aload_0
       9: invokevirtual #29                 // Method getStoreFilesSize:()J
      12: l2f
      13: fdiv
      14: ldc           #30                 // float 100.0f
      16: fmul
      17: freturn

  public long getLogsSize();
    Code:
       0: aload_0
       1: getfield      #17                 // Field logSize:Ljava/util/concurrent/atomic/AtomicLong;
       4: invokevirtual #28                 // Method java/util/concurrent/atomic/AtomicLong.get:()J
       7: lreturn

  org.apache.hadoop.hbase.snapshot.SnapshotInfo$SnapshotStats$FileInfo addStoreFile(org.apache.hadoop.hbase.client.RegionInfo, java.lang.String, org.apache.hadoop.hbase.shaded.protobuf.generated.SnapshotProtos$SnapshotRegionManifest$StoreFile, java.util.Map<org.apache.hadoop.fs.Path, java.lang.Integer>) throws java.io.IOException;
    Code:
       0: aload_0
       1: getfield      #22                 // Field conf:Lorg/apache/hadoop/conf/Configuration;
       4: aload_0
       5: getfield      #21                 // Field snapshotTable:Lorg/apache/hadoop/hbase/TableName;
       8: aload_1
       9: invokeinterface #39,  1           // InterfaceMethod org/apache/hadoop/hbase/client/RegionInfo.getEncodedName:()Ljava/lang/String;
      14: aload_2
      15: aload_3
      16: invokevirtual #40                 // Method org/apache/hadoop/hbase/shaded/protobuf/generated/SnapshotProtos$SnapshotRegionManifest$StoreFile.getName:()Ljava/lang/String;
      19: invokestatic  #41                 // Method org/apache/hadoop/hbase/io/HFileLink.build:(Lorg/apache/hadoop/conf/Configuration;Lorg/apache/hadoop/hbase/TableName;Ljava/lang/String;Ljava/lang/String;Ljava/lang/String;)Lorg/apache/hadoop/hbase/io/HFileLink;
      22: astore        5
      24: iconst_0
      25: istore        6
      27: iconst_0
      28: istore        7
      30: ldc2_w        #42                 // long -1l
      33: lstore        8
      35: aload_0
      36: getfield      #23                 // Field fs:Lorg/apache/hadoop/fs/FileSystem;
      39: aload         5
      41: invokevirtual #44                 // Method org/apache/hadoop/hbase/io/HFileLink.getArchivePath:()Lorg/apache/hadoop/fs/Path;
      44: invokevirtual #45                 // Method org/apache/hadoop/fs/FileSystem.exists:(Lorg/apache/hadoop/fs/Path;)Z
      47: ifeq          120
      50: iconst_1
      51: istore        7
      53: aload_0
      54: getfield      #23                 // Field fs:Lorg/apache/hadoop/fs/FileSystem;
      57: aload         5
      59: invokevirtual #44                 // Method org/apache/hadoop/hbase/io/HFileLink.getArchivePath:()Lorg/apache/hadoop/fs/Path;
      62: invokevirtual #46                 // Method org/apache/hadoop/fs/FileSystem.getFileStatus:(Lorg/apache/hadoop/fs/Path;)Lorg/apache/hadoop/fs/FileStatus;
      65: invokevirtual #47                 // Method org/apache/hadoop/fs/FileStatus.getLen:()J
      68: lstore        8
      70: aload_0
      71: getfield      #13                 // Field hfilesArchiveSize:Ljava/util/concurrent/atomic/AtomicLong;
      74: lload         8
      76: invokevirtual #48                 // Method java/util/concurrent/atomic/AtomicLong.addAndGet:(J)J
      79: pop2
      80: aload_0
      81: getfield      #4                  // Field hfilesArchiveCount:Ljava/util/concurrent/atomic/AtomicInteger;
      84: invokevirtual #49                 // Method java/util/concurrent/atomic/AtomicInteger.incrementAndGet:()I
      87: pop
      88: aload         4
      90: ifnull        208
      93: aload_0
      94: aload         5
      96: invokevirtual #44                 // Method org/apache/hadoop/hbase/io/HFileLink.getArchivePath:()Lorg/apache/hadoop/fs/Path;
      99: aload         4
     101: invokespecial #50                 // Method isArchivedFileStillReferenced:(Lorg/apache/hadoop/fs/Path;Ljava/util/Map;)Z
     104: ifne          208
     107: aload_0
     108: getfield      #16                 // Field nonSharedHfilesArchiveSize:Ljava/util/concurrent/atomic/AtomicLong;
     111: lload         8
     113: invokevirtual #48                 // Method java/util/concurrent/atomic/AtomicLong.addAndGet:(J)J
     116: pop2
     117: goto          208
     120: aload_0
     121: getfield      #23                 // Field fs:Lorg/apache/hadoop/fs/FileSystem;
     124: aload         5
     126: invokevirtual #51                 // Method org/apache/hadoop/hbase/io/HFileLink.getMobPath:()Lorg/apache/hadoop/fs/Path;
     129: invokevirtual #45                 // Method org/apache/hadoop/fs/FileSystem.exists:(Lorg/apache/hadoop/fs/Path;)Z
     132: ifeq          176
     135: iconst_1
     136: istore        7
     138: aload_0
     139: getfield      #23                 // Field fs:Lorg/apache/hadoop/fs/FileSystem;
     142: aload         5
     144: invokevirtual #51                 // Method org/apache/hadoop/hbase/io/HFileLink.getMobPath:()Lorg/apache/hadoop/fs/Path;
     147: invokevirtual #46                 // Method org/apache/hadoop/fs/FileSystem.getFileStatus:(Lorg/apache/hadoop/fs/Path;)Lorg/apache/hadoop/fs/FileStatus;
     150: invokevirtual #47                 // Method org/apache/hadoop/fs/FileStatus.getLen:()J
     153: lstore        8
     155: aload_0
     156: getfield      #15                 // Field hfilesMobSize:Ljava/util/concurrent/atomic/AtomicLong;
     159: lload         8
     161: invokevirtual #48                 // Method java/util/concurrent/atomic/AtomicLong.addAndGet:(J)J
     164: pop2
     165: aload_0
     166: getfield      #8                  // Field hfilesMobCount:Ljava/util/concurrent/atomic/AtomicInteger;
     169: invokevirtual #49                 // Method java/util/concurrent/atomic/AtomicInteger.incrementAndGet:()I
     172: pop
     173: goto          208
     176: aload         5
     178: aload_0
     179: getfield      #23                 // Field fs:Lorg/apache/hadoop/fs/FileSystem;
     182: invokevirtual #52                 // Method org/apache/hadoop/hbase/io/HFileLink.getFileStatus:(Lorg/apache/hadoop/fs/FileSystem;)Lorg/apache/hadoop/fs/FileStatus;
     185: invokevirtual #47                 // Method org/apache/hadoop/fs/FileStatus.getLen:()J
     188: lstore        8
     190: aload_0
     191: getfield      #14                 // Field hfilesSize:Ljava/util/concurrent/atomic/AtomicLong;
     194: lload         8
     196: invokevirtual #48                 // Method java/util/concurrent/atomic/AtomicLong.addAndGet:(J)J
     199: pop2
     200: aload_0
     201: getfield      #7                  // Field hfilesCount:Ljava/util/concurrent/atomic/AtomicInteger;
     204: invokevirtual #49                 // Method java/util/concurrent/atomic/AtomicInteger.incrementAndGet:()I
     207: pop
     208: aload_3
     209: invokevirtual #53                 // Method org/apache/hadoop/hbase/shaded/protobuf/generated/SnapshotProtos$SnapshotRegionManifest$StoreFile.hasFileSize:()Z
     212: ifeq          229
     215: aload_3
     216: invokevirtual #54                 // Method org/apache/hadoop/hbase/shaded/protobuf/generated/SnapshotProtos$SnapshotRegionManifest$StoreFile.getFileSize:()J
     219: lload         8
     221: lcmp
     222: ifeq          229
     225: iconst_1
     226: goto          230
     229: iconst_0
     230: istore        6
     232: iload         6
     234: ifeq          245
     237: aload_0
     238: getfield      #5                  // Field hfilesCorrupted:Ljava/util/concurrent/atomic/AtomicInteger;
     241: invokevirtual #49                 // Method java/util/concurrent/atomic/AtomicInteger.incrementAndGet:()I
     244: pop
     245: goto          258
     248: astore        10
     250: aload_0
     251: getfield      #6                  // Field hfilesMissing:Ljava/util/concurrent/atomic/AtomicInteger;
     254: invokevirtual #49                 // Method java/util/concurrent/atomic/AtomicInteger.incrementAndGet:()I
     257: pop
     258: new           #56                 // class org/apache/hadoop/hbase/snapshot/SnapshotInfo$SnapshotStats$FileInfo
     261: dup
     262: iload         7
     264: lload         8
     266: iload         6
     268: invokespecial #57                 // Method org/apache/hadoop/hbase/snapshot/SnapshotInfo$SnapshotStats$FileInfo."<init>":(ZJZ)V
     271: areturn
    Exception table:
       from    to  target type
          35   245   248   Class java/io/FileNotFoundException

  org.apache.hadoop.hbase.snapshot.SnapshotInfo$SnapshotStats$FileInfo addLogFile(java.lang.String, java.lang.String) throws java.io.IOException;
    Code:
       0: new           #58                 // class org/apache/hadoop/hbase/io/WALLink
       3: dup
       4: aload_0
       5: getfield      #22                 // Field conf:Lorg/apache/hadoop/conf/Configuration;
       8: aload_1
       9: aload_2
      10: invokespecial #59                 // Method org/apache/hadoop/hbase/io/WALLink."<init>":(Lorg/apache/hadoop/conf/Configuration;Ljava/lang/String;Ljava/lang/String;)V
      13: astore_3
      14: ldc2_w        #42                 // long -1l
      17: lstore        4
      19: aload_3
      20: aload_0
      21: getfield      #23                 // Field fs:Lorg/apache/hadoop/fs/FileSystem;
      24: invokevirtual #60                 // Method org/apache/hadoop/hbase/io/WALLink.getFileStatus:(Lorg/apache/hadoop/fs/FileSystem;)Lorg/apache/hadoop/fs/FileStatus;
      27: invokevirtual #47                 // Method org/apache/hadoop/fs/FileStatus.getLen:()J
      30: lstore        4
      32: aload_0
      33: getfield      #17                 // Field logSize:Ljava/util/concurrent/atomic/AtomicLong;
      36: lload         4
      38: invokevirtual #48                 // Method java/util/concurrent/atomic/AtomicLong.addAndGet:(J)J
      41: pop2
      42: aload_0
      43: getfield      #10                 // Field logsCount:Ljava/util/concurrent/atomic/AtomicInteger;
      46: invokevirtual #49                 // Method java/util/concurrent/atomic/AtomicInteger.incrementAndGet:()I
      49: pop
      50: goto          63
      53: astore        6
      55: aload_0
      56: getfield      #9                  // Field logsMissing:Ljava/util/concurrent/atomic/AtomicInteger;
      59: invokevirtual #49                 // Method java/util/concurrent/atomic/AtomicInteger.incrementAndGet:()I
      62: pop
      63: new           #56                 // class org/apache/hadoop/hbase/snapshot/SnapshotInfo$SnapshotStats$FileInfo
      66: dup
      67: iconst_0
      68: lload         4
      70: iconst_0
      71: invokespecial #57                 // Method org/apache/hadoop/hbase/snapshot/SnapshotInfo$SnapshotStats$FileInfo."<init>":(ZJZ)V
      74: areturn
    Exception table:
       from    to  target type
          19    50    53   Class java/io/FileNotFoundException
}
