Compiled from "SnapshotManifestV2.java"
class org.apache.hadoop.hbase.snapshot.SnapshotManifestV2$ManifestBuilder implements org.apache.hadoop.hbase.snapshot.SnapshotManifest$RegionVisitor<org.apache.hadoop.hbase.shaded.protobuf.generated.SnapshotProtos$SnapshotRegionManifest$Builder, org.apache.hadoop.hbase.shaded.protobuf.generated.SnapshotProtos$SnapshotRegionManifest$FamilyFiles$Builder> {
  public org.apache.hadoop.hbase.snapshot.SnapshotManifestV2$ManifestBuilder(org.apache.hadoop.conf.Configuration, org.apache.hadoop.fs.FileSystem, org.apache.hadoop.fs.Path);
    Code:
       0: aload_0
       1: invokespecial #1                  // Method java/lang/Object."<init>":()V
       4: aload_0
       5: aload_3
       6: putfield      #2                  // Field snapshotDir:Lorg/apache/hadoop/fs/Path;
       9: aload_0
      10: aload_1
      11: putfield      #3                  // Field conf:Lorg/apache/hadoop/conf/Configuration;
      14: aload_0
      15: aload_2
      16: putfield      #4                  // Field rootFs:Lorg/apache/hadoop/fs/FileSystem;
      19: return

  public org.apache.hadoop.hbase.shaded.protobuf.generated.SnapshotProtos$SnapshotRegionManifest$Builder regionOpen(org.apache.hadoop.hbase.client.RegionInfo);
    Code:
       0: invokestatic  #5                  // Method org/apache/hadoop/hbase/shaded/protobuf/generated/SnapshotProtos$SnapshotRegionManifest.newBuilder:()Lorg/apache/hadoop/hbase/shaded/protobuf/generated/SnapshotProtos$SnapshotRegionManifest$Builder;
       3: astore_2
       4: aload_2
       5: aload_1
       6: invokestatic  #6                  // Method org/apache/hadoop/hbase/shaded/protobuf/ProtobufUtil.toRegionInfo:(Lorg/apache/hadoop/hbase/client/RegionInfo;)Lorg/apache/hadoop/hbase/shaded/protobuf/generated/HBaseProtos$RegionInfo;
       9: invokevirtual #7                  // Method org/apache/hadoop/hbase/shaded/protobuf/generated/SnapshotProtos$SnapshotRegionManifest$Builder.setRegionInfo:(Lorg/apache/hadoop/hbase/shaded/protobuf/generated/HBaseProtos$RegionInfo;)Lorg/apache/hadoop/hbase/shaded/protobuf/generated/SnapshotProtos$SnapshotRegionManifest$Builder;
      12: pop
      13: aload_2
      14: areturn

  public void regionClose(org.apache.hadoop.hbase.shaded.protobuf.generated.SnapshotProtos$SnapshotRegionManifest$Builder) throws java.io.IOException;
    Code:
       0: aload_0
       1: getfield      #2                  // Field snapshotDir:Lorg/apache/hadoop/fs/Path;
       4: aload_0
       5: getfield      #3                  // Field conf:Lorg/apache/hadoop/conf/Configuration;
       8: invokevirtual #8                  // Method org/apache/hadoop/fs/Path.getFileSystem:(Lorg/apache/hadoop/conf/Configuration;)Lorg/apache/hadoop/fs/FileSystem;
      11: astore_2
      12: aload_2
      13: aload_0
      14: getfield      #2                  // Field snapshotDir:Lorg/apache/hadoop/fs/Path;
      17: invokevirtual #9                  // Method org/apache/hadoop/fs/FileSystem.exists:(Lorg/apache/hadoop/fs/Path;)Z
      20: ifeq          69
      23: aload_1
      24: invokevirtual #10                 // Method org/apache/hadoop/hbase/shaded/protobuf/generated/SnapshotProtos$SnapshotRegionManifest$Builder.build:()Lorg/apache/hadoop/hbase/shaded/protobuf/generated/SnapshotProtos$SnapshotRegionManifest;
      27: astore_3
      28: aload_2
      29: aload_0
      30: getfield      #2                  // Field snapshotDir:Lorg/apache/hadoop/fs/Path;
      33: aload_3
      34: invokestatic  #11                 // Method org/apache/hadoop/hbase/snapshot/SnapshotManifestV2.access$000:(Lorg/apache/hadoop/fs/Path;Lorg/apache/hadoop/hbase/shaded/protobuf/generated/SnapshotProtos$SnapshotRegionManifest;)Lorg/apache/hadoop/fs/Path;
      37: invokevirtual #12                 // Method org/apache/hadoop/fs/FileSystem.create:(Lorg/apache/hadoop/fs/Path;)Lorg/apache/hadoop/fs/FSDataOutputStream;
      40: astore        4
      42: aload_3
      43: aload         4
      45: invokevirtual #13                 // Method org/apache/hadoop/hbase/shaded/protobuf/generated/SnapshotProtos$SnapshotRegionManifest.writeTo:(Ljava/io/OutputStream;)V
      48: aload         4
      50: invokevirtual #14                 // Method org/apache/hadoop/fs/FSDataOutputStream.close:()V
      53: goto          66
      56: astore        5
      58: aload         4
      60: invokevirtual #14                 // Method org/apache/hadoop/fs/FSDataOutputStream.close:()V
      63: aload         5
      65: athrow
      66: goto          79
      69: invokestatic  #15                 // Method org/apache/hadoop/hbase/snapshot/SnapshotManifestV2.access$100:()Lorg/slf4j/Logger;
      72: ldc           #16                 // String can't write manifest without parent dir, maybe it has been deleted by master?
      74: invokeinterface #17,  2           // InterfaceMethod org/slf4j/Logger.warn:(Ljava/lang/String;)V
      79: return
    Exception table:
       from    to  target type
          42    48    56   any
          56    58    56   any

  public org.apache.hadoop.hbase.shaded.protobuf.generated.SnapshotProtos$SnapshotRegionManifest$FamilyFiles$Builder familyOpen(org.apache.hadoop.hbase.shaded.protobuf.generated.SnapshotProtos$SnapshotRegionManifest$Builder, byte[]);
    Code:
       0: invokestatic  #18                 // Method org/apache/hadoop/hbase/shaded/protobuf/generated/SnapshotProtos$SnapshotRegionManifest$FamilyFiles.newBuilder:()Lorg/apache/hadoop/hbase/shaded/protobuf/generated/SnapshotProtos$SnapshotRegionManifest$FamilyFiles$Builder;
       3: astore_3
       4: aload_3
       5: aload_2
       6: invokestatic  #19                 // Method org/apache/hbase/thirdparty/com/google/protobuf/UnsafeByteOperations.unsafeWrap:([B)Lorg/apache/hbase/thirdparty/com/google/protobuf/ByteString;
       9: invokevirtual #20                 // Method org/apache/hadoop/hbase/shaded/protobuf/generated/SnapshotProtos$SnapshotRegionManifest$FamilyFiles$Builder.setFamilyName:(Lorg/apache/hbase/thirdparty/com/google/protobuf/ByteString;)Lorg/apache/hadoop/hbase/shaded/protobuf/generated/SnapshotProtos$SnapshotRegionManifest$FamilyFiles$Builder;
      12: pop
      13: aload_3
      14: areturn

  public void familyClose(org.apache.hadoop.hbase.shaded.protobuf.generated.SnapshotProtos$SnapshotRegionManifest$Builder, org.apache.hadoop.hbase.shaded.protobuf.generated.SnapshotProtos$SnapshotRegionManifest$FamilyFiles$Builder);
    Code:
       0: aload_1
       1: aload_2
       2: invokevirtual #21                 // Method org/apache/hadoop/hbase/shaded/protobuf/generated/SnapshotProtos$SnapshotRegionManifest$FamilyFiles$Builder.build:()Lorg/apache/hadoop/hbase/shaded/protobuf/generated/SnapshotProtos$SnapshotRegionManifest$FamilyFiles;
       5: invokevirtual #22                 // Method org/apache/hadoop/hbase/shaded/protobuf/generated/SnapshotProtos$SnapshotRegionManifest$Builder.addFamilyFiles:(Lorg/apache/hadoop/hbase/shaded/protobuf/generated/SnapshotProtos$SnapshotRegionManifest$FamilyFiles;)Lorg/apache/hadoop/hbase/shaded/protobuf/generated/SnapshotProtos$SnapshotRegionManifest$Builder;
       8: pop
       9: return

  public void storeFile(org.apache.hadoop.hbase.shaded.protobuf.generated.SnapshotProtos$SnapshotRegionManifest$Builder, org.apache.hadoop.hbase.shaded.protobuf.generated.SnapshotProtos$SnapshotRegionManifest$FamilyFiles$Builder, org.apache.hadoop.hbase.regionserver.StoreFileInfo) throws java.io.IOException;
    Code:
       0: invokestatic  #23                 // Method org/apache/hadoop/hbase/shaded/protobuf/generated/SnapshotProtos$SnapshotRegionManifest$StoreFile.newBuilder:()Lorg/apache/hadoop/hbase/shaded/protobuf/generated/SnapshotProtos$SnapshotRegionManifest$StoreFile$Builder;
       3: astore        4
       5: aload         4
       7: aload_3
       8: invokevirtual #24                 // Method org/apache/hadoop/hbase/regionserver/StoreFileInfo.getPath:()Lorg/apache/hadoop/fs/Path;
      11: invokevirtual #25                 // Method org/apache/hadoop/fs/Path.getName:()Ljava/lang/String;
      14: invokevirtual #26                 // Method org/apache/hadoop/hbase/shaded/protobuf/generated/SnapshotProtos$SnapshotRegionManifest$StoreFile$Builder.setName:(Ljava/lang/String;)Lorg/apache/hadoop/hbase/shaded/protobuf/generated/SnapshotProtos$SnapshotRegionManifest$StoreFile$Builder;
      17: pop
      18: aload_3
      19: invokevirtual #27                 // Method org/apache/hadoop/hbase/regionserver/StoreFileInfo.isReference:()Z
      22: ifeq          38
      25: aload         4
      27: aload_3
      28: invokevirtual #28                 // Method org/apache/hadoop/hbase/regionserver/StoreFileInfo.getReference:()Lorg/apache/hadoop/hbase/io/Reference;
      31: invokevirtual #29                 // Method org/apache/hadoop/hbase/io/Reference.convert:()Lorg/apache/hadoop/hbase/shaded/protobuf/generated/FSProtos$Reference;
      34: invokevirtual #30                 // Method org/apache/hadoop/hbase/shaded/protobuf/generated/SnapshotProtos$SnapshotRegionManifest$StoreFile$Builder.setReference:(Lorg/apache/hadoop/hbase/shaded/protobuf/generated/FSProtos$Reference;)Lorg/apache/hadoop/hbase/shaded/protobuf/generated/SnapshotProtos$SnapshotRegionManifest$StoreFile$Builder;
      37: pop
      38: aload         4
      40: aload_3
      41: aload_0
      42: getfield      #4                  // Field rootFs:Lorg/apache/hadoop/fs/FileSystem;
      45: invokevirtual #31                 // Method org/apache/hadoop/hbase/regionserver/StoreFileInfo.getReferencedFileStatus:(Lorg/apache/hadoop/fs/FileSystem;)Lorg/apache/hadoop/fs/FileStatus;
      48: invokevirtual #32                 // Method org/apache/hadoop/fs/FileStatus.getLen:()J
      51: invokevirtual #33                 // Method org/apache/hadoop/hbase/shaded/protobuf/generated/SnapshotProtos$SnapshotRegionManifest$StoreFile$Builder.setFileSize:(J)Lorg/apache/hadoop/hbase/shaded/protobuf/generated/SnapshotProtos$SnapshotRegionManifest$StoreFile$Builder;
      54: pop
      55: aload_2
      56: aload         4
      58: invokevirtual #34                 // Method org/apache/hadoop/hbase/shaded/protobuf/generated/SnapshotProtos$SnapshotRegionManifest$StoreFile$Builder.build:()Lorg/apache/hadoop/hbase/shaded/protobuf/generated/SnapshotProtos$SnapshotRegionManifest$StoreFile;
      61: invokevirtual #35                 // Method org/apache/hadoop/hbase/shaded/protobuf/generated/SnapshotProtos$SnapshotRegionManifest$FamilyFiles$Builder.addStoreFiles:(Lorg/apache/hadoop/hbase/shaded/protobuf/generated/SnapshotProtos$SnapshotRegionManifest$StoreFile;)Lorg/apache/hadoop/hbase/shaded/protobuf/generated/SnapshotProtos$SnapshotRegionManifest$FamilyFiles$Builder;
      64: pop
      65: return

  public void storeFile(java.lang.Object, java.lang.Object, org.apache.hadoop.hbase.regionserver.StoreFileInfo) throws java.io.IOException;
    Code:
       0: aload_0
       1: aload_1
       2: checkcast     #36                 // class org/apache/hadoop/hbase/shaded/protobuf/generated/SnapshotProtos$SnapshotRegionManifest$Builder
       5: aload_2
       6: checkcast     #37                 // class org/apache/hadoop/hbase/shaded/protobuf/generated/SnapshotProtos$SnapshotRegionManifest$FamilyFiles$Builder
       9: aload_3
      10: invokevirtual #38                 // Method storeFile:(Lorg/apache/hadoop/hbase/shaded/protobuf/generated/SnapshotProtos$SnapshotRegionManifest$Builder;Lorg/apache/hadoop/hbase/shaded/protobuf/generated/SnapshotProtos$SnapshotRegionManifest$FamilyFiles$Builder;Lorg/apache/hadoop/hbase/regionserver/StoreFileInfo;)V
      13: return

  public void familyClose(java.lang.Object, java.lang.Object) throws java.io.IOException;
    Code:
       0: aload_0
       1: aload_1
       2: checkcast     #36                 // class org/apache/hadoop/hbase/shaded/protobuf/generated/SnapshotProtos$SnapshotRegionManifest$Builder
       5: aload_2
       6: checkcast     #37                 // class org/apache/hadoop/hbase/shaded/protobuf/generated/SnapshotProtos$SnapshotRegionManifest$FamilyFiles$Builder
       9: invokevirtual #39                 // Method familyClose:(Lorg/apache/hadoop/hbase/shaded/protobuf/generated/SnapshotProtos$SnapshotRegionManifest$Builder;Lorg/apache/hadoop/hbase/shaded/protobuf/generated/SnapshotProtos$SnapshotRegionManifest$FamilyFiles$Builder;)V
      12: return

  public java.lang.Object familyOpen(java.lang.Object, byte[]) throws java.io.IOException;
    Code:
       0: aload_0
       1: aload_1
       2: checkcast     #36                 // class org/apache/hadoop/hbase/shaded/protobuf/generated/SnapshotProtos$SnapshotRegionManifest$Builder
       5: aload_2
       6: invokevirtual #40                 // Method familyOpen:(Lorg/apache/hadoop/hbase/shaded/protobuf/generated/SnapshotProtos$SnapshotRegionManifest$Builder;[B)Lorg/apache/hadoop/hbase/shaded/protobuf/generated/SnapshotProtos$SnapshotRegionManifest$FamilyFiles$Builder;
       9: areturn

  public void regionClose(java.lang.Object) throws java.io.IOException;
    Code:
       0: aload_0
       1: aload_1
       2: checkcast     #36                 // class org/apache/hadoop/hbase/shaded/protobuf/generated/SnapshotProtos$SnapshotRegionManifest$Builder
       5: invokevirtual #41                 // Method regionClose:(Lorg/apache/hadoop/hbase/shaded/protobuf/generated/SnapshotProtos$SnapshotRegionManifest$Builder;)V
       8: return

  public java.lang.Object regionOpen(org.apache.hadoop.hbase.client.RegionInfo) throws java.io.IOException;
    Code:
       0: aload_0
       1: aload_1
       2: invokevirtual #42                 // Method regionOpen:(Lorg/apache/hadoop/hbase/client/RegionInfo;)Lorg/apache/hadoop/hbase/shaded/protobuf/generated/SnapshotProtos$SnapshotRegionManifest$Builder;
       5: areturn
}
