Compiled from "SnapshotFileCache.java"
public class org.apache.hadoop.hbase.master.snapshot.SnapshotFileCache$RefreshCacheTask extends java.util.TimerTask {
  final org.apache.hadoop.hbase.master.snapshot.SnapshotFileCache this$0;

  public org.apache.hadoop.hbase.master.snapshot.SnapshotFileCache$RefreshCacheTask(org.apache.hadoop.hbase.master.snapshot.SnapshotFileCache);
    Code:
       0: aload_0
       1: aload_1
       2: putfield      #1                  // Field this$0:Lorg/apache/hadoop/hbase/master/snapshot/SnapshotFileCache;
       5: aload_0
       6: invokespecial #2                  // Method java/util/TimerTask."<init>":()V
       9: return

  public void run();
    Code:
       0: aload_0
       1: getfield      #1                  // Field this$0:Lorg/apache/hadoop/hbase/master/snapshot/SnapshotFileCache;
       4: dup
       5: astore_1
       6: monitorenter
       7: aload_0
       8: getfield      #1                  // Field this$0:Lorg/apache/hadoop/hbase/master/snapshot/SnapshotFileCache;
      11: invokestatic  #3                  // Method org/apache/hadoop/hbase/master/snapshot/SnapshotFileCache.access$000:(Lorg/apache/hadoop/hbase/master/snapshot/SnapshotFileCache;)V
      14: goto          53
      17: astore_2
      18: invokestatic  #5                  // Method org/apache/hadoop/hbase/master/snapshot/SnapshotFileCache.access$100:()Lorg/slf4j/Logger;
      21: ldc           #6                  // String Failed to refresh snapshot hfile cache!
      23: aload_2
      24: invokeinterface #7,  3            // InterfaceMethod org/slf4j/Logger.warn:(Ljava/lang/String;Ljava/lang/Throwable;)V
      29: aload_0
      30: getfield      #1                  // Field this$0:Lorg/apache/hadoop/hbase/master/snapshot/SnapshotFileCache;
      33: invokestatic  #8                  // Method org/apache/hadoop/hbase/master/snapshot/SnapshotFileCache.access$200:(Lorg/apache/hadoop/hbase/master/snapshot/SnapshotFileCache;)Ljava/util/Set;
      36: invokeinterface #9,  1            // InterfaceMethod java/util/Set.clear:()V
      41: aload_0
      42: getfield      #1                  // Field this$0:Lorg/apache/hadoop/hbase/master/snapshot/SnapshotFileCache;
      45: invokestatic  #10                 // Method org/apache/hadoop/hbase/master/snapshot/SnapshotFileCache.access$300:(Lorg/apache/hadoop/hbase/master/snapshot/SnapshotFileCache;)Ljava/util/Map;
      48: invokeinterface #11,  1           // InterfaceMethod java/util/Map.clear:()V
      53: aload_1
      54: monitorexit
      55: goto          63
      58: astore_3
      59: aload_1
      60: monitorexit
      61: aload_3
      62: athrow
      63: return
    Exception table:
       from    to  target type
           7    14    17   Class java/io/IOException
           7    55    58   any
          58    61    58   any
}
