Compiled from "SortedCompactionPolicy.java"
public abstract class org.apache.hadoop.hbase.regionserver.compactions.SortedCompactionPolicy extends org.apache.hadoop.hbase.regionserver.compactions.CompactionPolicy {
  public org.apache.hadoop.hbase.regionserver.compactions.SortedCompactionPolicy(org.apache.hadoop.conf.Configuration, org.apache.hadoop.hbase.regionserver.StoreConfigInformation);
    Code:
       0: aload_0
       1: aload_1
       2: aload_2
       3: invokespecial #1                  // Method org/apache/hadoop/hbase/regionserver/compactions/CompactionPolicy."<init>":(Lorg/apache/hadoop/conf/Configuration;Lorg/apache/hadoop/hbase/regionserver/StoreConfigInformation;)V
       6: aload_0
       7: new           #2                  // class java/util/Random
      10: dup
      11: invokespecial #3                  // Method java/util/Random."<init>":()V
      14: putfield      #4                  // Field random:Ljava/util/Random;
      17: return

  public java.util.List<org.apache.hadoop.hbase.regionserver.HStoreFile> preSelectCompactionForCoprocessor(java.util.Collection<org.apache.hadoop.hbase.regionserver.HStoreFile>, java.util.List<org.apache.hadoop.hbase.regionserver.HStoreFile>);
    Code:
       0: aload_0
       1: new           #5                  // class java/util/ArrayList
       4: dup
       5: aload_1
       6: invokespecial #6                  // Method java/util/ArrayList."<init>":(Ljava/util/Collection;)V
       9: aload_2
      10: invokevirtual #7                  // Method getCurrentEligibleFiles:(Ljava/util/ArrayList;Ljava/util/List;)Ljava/util/ArrayList;
      13: areturn

  public org.apache.hadoop.hbase.regionserver.compactions.CompactionRequestImpl selectCompaction(java.util.Collection<org.apache.hadoop.hbase.regionserver.HStoreFile>, java.util.List<org.apache.hadoop.hbase.regionserver.HStoreFile>, boolean, boolean, boolean) throws java.io.IOException;
    Code:
       0: new           #5                  // class java/util/ArrayList
       3: dup
       4: aload_1
       5: invokespecial #6                  // Method java/util/ArrayList."<init>":(Ljava/util/Collection;)V
       8: astore        6
      10: aload_2
      11: invokeinterface #8,  1            // InterfaceMethod java/util/List.isEmpty:()Z
      16: ifeq          23
      19: iconst_0
      20: goto          24
      23: iconst_1
      24: istore        7
      26: aload_1
      27: invokeinterface #9,  1            // InterfaceMethod java/util/Collection.size:()I
      32: aload_2
      33: invokeinterface #10,  1           // InterfaceMethod java/util/List.size:()I
      38: isub
      39: iload         7
      41: iadd
      42: i2l
      43: aload_0
      44: getfield      #11                 // Field storeConfigInfo:Lorg/apache/hadoop/hbase/regionserver/StoreConfigInformation;
      47: invokeinterface #12,  1           // InterfaceMethod org/apache/hadoop/hbase/regionserver/StoreConfigInformation.getBlockingFileCount:()J
      52: lcmp
      53: iflt          60
      56: iconst_1
      57: goto          61
      60: iconst_0
      61: istore        8
      63: aload_0
      64: aload         6
      66: aload_2
      67: invokevirtual #7                  // Method getCurrentEligibleFiles:(Ljava/util/ArrayList;Ljava/util/List;)Ljava/util/ArrayList;
      70: astore        6
      72: getstatic     #13                 // Field LOG:Lorg/slf4j/Logger;
      75: new           #14                 // class java/lang/StringBuilder
      78: dup
      79: invokespecial #15                 // Method java/lang/StringBuilder."<init>":()V
      82: ldc           #16                 // String Selecting compaction from
      84: invokevirtual #17                 // Method java/lang/StringBuilder.append:(Ljava/lang/String;)Ljava/lang/StringBuilder;
      87: aload_1
      88: invokeinterface #9,  1            // InterfaceMethod java/util/Collection.size:()I
      93: invokevirtual #18                 // Method java/lang/StringBuilder.append:(I)Ljava/lang/StringBuilder;
      96: ldc           #19                 // String  store files,
      98: invokevirtual #17                 // Method java/lang/StringBuilder.append:(Ljava/lang/String;)Ljava/lang/StringBuilder;
     101: aload_2
     102: invokeinterface #10,  1           // InterfaceMethod java/util/List.size:()I
     107: invokevirtual #18                 // Method java/lang/StringBuilder.append:(I)Ljava/lang/StringBuilder;
     110: ldc           #20                 // String  compacting,
     112: invokevirtual #17                 // Method java/lang/StringBuilder.append:(Ljava/lang/String;)Ljava/lang/StringBuilder;
     115: aload         6
     117: invokevirtual #21                 // Method java/util/ArrayList.size:()I
     120: invokevirtual #18                 // Method java/lang/StringBuilder.append:(I)Ljava/lang/StringBuilder;
     123: ldc           #22                 // String  eligible,
     125: invokevirtual #17                 // Method java/lang/StringBuilder.append:(Ljava/lang/String;)Ljava/lang/StringBuilder;
     128: aload_0
     129: getfield      #11                 // Field storeConfigInfo:Lorg/apache/hadoop/hbase/regionserver/StoreConfigInformation;
     132: invokeinterface #12,  1           // InterfaceMethod org/apache/hadoop/hbase/regionserver/StoreConfigInformation.getBlockingFileCount:()J
     137: invokevirtual #23                 // Method java/lang/StringBuilder.append:(J)Ljava/lang/StringBuilder;
     140: ldc           #24                 // String  blocking
     142: invokevirtual #17                 // Method java/lang/StringBuilder.append:(Ljava/lang/String;)Ljava/lang/StringBuilder;
     145: invokevirtual #25                 // Method java/lang/StringBuilder.toString:()Ljava/lang/String;
     148: invokeinterface #26,  2           // InterfaceMethod org/slf4j/Logger.debug:(Ljava/lang/String;)V
     153: aload_1
     154: invokeinterface #9,  1            // InterfaceMethod java/util/Collection.size:()I
     159: aload         6
     161: invokevirtual #21                 // Method java/util/ArrayList.size:()I
     164: if_icmpne     171
     167: iconst_1
     168: goto          172
     171: iconst_0
     172: istore        9
     174: iload         5
     176: ifeq          184
     179: iload         9
     181: ifne          215
     184: aload_0
     185: aload         6
     187: iload         4
     189: invokevirtual #27                 // Method skipLargeFiles:(Ljava/util/ArrayList;Z)Ljava/util/ArrayList;
     192: astore        6
     194: aload_1
     195: invokeinterface #9,  1            // InterfaceMethod java/util/Collection.size:()I
     200: aload         6
     202: invokevirtual #21                 // Method java/util/ArrayList.size:()I
     205: if_icmpne     212
     208: iconst_1
     209: goto          213
     212: iconst_0
     213: istore        9
     215: iload         5
     217: ifeq          229
     220: iload         9
     222: ifeq          229
     225: iload_3
     226: ifne          263
     229: iload         5
     231: ifeq          239
     234: iload         9
     236: ifne          248
     239: aload_0
     240: aload         6
     242: invokevirtual #28                 // Method shouldPerformMajorCompaction:(Ljava/util/Collection;)Z
     245: ifeq          267
     248: aload         6
     250: invokevirtual #21                 // Method java/util/ArrayList.size:()I
     253: aload_0
     254: getfield      #29                 // Field comConf:Lorg/apache/hadoop/hbase/regionserver/compactions/CompactionConfiguration;
     257: invokevirtual #30                 // Method org/apache/hadoop/hbase/regionserver/compactions/CompactionConfiguration.getMaxFilesToCompact:()I
     260: if_icmpge     267
     263: iconst_1
     264: goto          268
     267: iconst_0
     268: istore        10
     270: aload         6
     272: invokestatic  #31                 // Method org/apache/hadoop/hbase/regionserver/StoreUtils.hasReferences:(Ljava/util/Collection;)Z
     275: istore        11
     277: aload_0
     278: aload         6
     280: iload         10
     282: ifne          290
     285: iload         11
     287: ifeq          294
     290: iconst_1
     291: goto          295
     294: iconst_0
     295: iload         4
     297: iload         8
     299: invokevirtual #32                 // Method createCompactionRequest:(Ljava/util/ArrayList;ZZZ)Lorg/apache/hadoop/hbase/regionserver/compactions/CompactionRequestImpl;
     302: astore        12
     304: aload         12
     306: invokevirtual #33                 // Method org/apache/hadoop/hbase/regionserver/compactions/CompactionRequestImpl.getFiles:()Ljava/util/Collection;
     309: invokestatic  #34                 // Method org/apache/hbase/thirdparty/com/google/common/collect/Lists.newArrayList:(Ljava/lang/Iterable;)Ljava/util/ArrayList;
     312: astore        13
     314: aload_0
     315: aload         13
     317: iload_3
     318: iload         10
     320: invokevirtual #35                 // Method removeExcessFiles:(Ljava/util/ArrayList;ZZ)V
     323: aload         12
     325: aload         13
     327: invokevirtual #36                 // Method org/apache/hadoop/hbase/regionserver/compactions/CompactionRequestImpl.updateFiles:(Ljava/util/Collection;)V
     330: aload_1
     331: invokeinterface #9,  1            // InterfaceMethod java/util/Collection.size:()I
     336: aload         13
     338: invokevirtual #21                 // Method java/util/ArrayList.size:()I
     341: if_icmpne     348
     344: iconst_1
     345: goto          349
     348: iconst_0
     349: istore        9
     351: aload         12
     353: aload         13
     355: invokevirtual #37                 // Method java/util/ArrayList.isEmpty:()Z
     358: ifne          375
     361: iload         9
     363: ifne          375
     366: iload         4
     368: ifeq          375
     371: iconst_1
     372: goto          376
     375: iconst_0
     376: invokevirtual #38                 // Method org/apache/hadoop/hbase/regionserver/compactions/CompactionRequestImpl.setOffPeak:(Z)V
     379: aload         12
     381: iload         10
     383: ifeq          395
     386: iload         9
     388: ifeq          395
     391: iconst_1
     392: goto          396
     395: iconst_0
     396: iload         9
     398: invokevirtual #39                 // Method org/apache/hadoop/hbase/regionserver/compactions/CompactionRequestImpl.setIsMajor:(ZZ)V
     401: aload         12
     403: areturn

  protected abstract org.apache.hadoop.hbase.regionserver.compactions.CompactionRequestImpl createCompactionRequest(java.util.ArrayList<org.apache.hadoop.hbase.regionserver.HStoreFile>, boolean, boolean, boolean) throws java.io.IOException;

  public abstract boolean shouldPerformMajorCompaction(java.util.Collection<org.apache.hadoop.hbase.regionserver.HStoreFile>) throws java.io.IOException;

  public long getNextMajorCompactTime(java.util.Collection<org.apache.hadoop.hbase.regionserver.HStoreFile>);
    Code:
       0: aload_0
       1: getfield      #29                 // Field comConf:Lorg/apache/hadoop/hbase/regionserver/compactions/CompactionConfiguration;
       4: invokevirtual #40                 // Method org/apache/hadoop/hbase/regionserver/compactions/CompactionConfiguration.getMajorCompactionPeriod:()J
       7: lstore_2
       8: lload_2
       9: lconst_0
      10: lcmp
      11: ifgt          16
      14: lload_2
      15: lreturn
      16: aload_0
      17: getfield      #29                 // Field comConf:Lorg/apache/hadoop/hbase/regionserver/compactions/CompactionConfiguration;
      20: invokevirtual #41                 // Method org/apache/hadoop/hbase/regionserver/compactions/CompactionConfiguration.getMajorCompactionJitter:()F
      23: f2d
      24: dstore        4
      26: dload         4
      28: dconst_0
      29: dcmpg
      30: ifgt          35
      33: lload_2
      34: lreturn
      35: aload_1
      36: invokestatic  #42                 // Method org/apache/hadoop/hbase/regionserver/StoreUtils.getDeterministicRandomSeed:(Ljava/util/Collection;)Ljava/util/OptionalInt;
      39: astore        6
      41: aload         6
      43: invokevirtual #43                 // Method java/util/OptionalInt.isPresent:()Z
      46: ifeq          119
      49: aload_0
      50: dup
      51: astore        9
      53: monitorenter
      54: aload_0
      55: getfield      #4                  // Field random:Ljava/util/Random;
      58: aload         6
      60: invokevirtual #44                 // Method java/util/OptionalInt.getAsInt:()I
      63: i2l
      64: invokevirtual #45                 // Method java/util/Random.setSeed:(J)V
      67: aload_0
      68: getfield      #4                  // Field random:Ljava/util/Random;
      71: invokevirtual #46                 // Method java/util/Random.nextDouble:()D
      74: dstore        7
      76: aload         9
      78: monitorexit
      79: goto          90
      82: astore        10
      84: aload         9
      86: monitorexit
      87: aload         10
      89: athrow
      90: lload_2
      91: l2d
      92: dload         4
      94: dmul
      95: invokestatic  #47                 // Method java/lang/Math.round:(D)J
      98: lstore        9
     100: lload_2
     101: lload         9
     103: ladd
     104: ldc2_w        #48                 // long 2l
     107: lload         9
     109: lmul
     110: l2d
     111: dload         7
     113: dmul
     114: invokestatic  #47                 // Method java/lang/Math.round:(D)J
     117: lsub
     118: lreturn
     119: lconst_0
     120: lreturn
    Exception table:
       from    to  target type
          54    79    82   any
          82    87    82   any

  public boolean throttleCompaction(long);
    Code:
       0: lload_1
       1: aload_0
       2: getfield      #29                 // Field comConf:Lorg/apache/hadoop/hbase/regionserver/compactions/CompactionConfiguration;
       5: invokevirtual #50                 // Method org/apache/hadoop/hbase/regionserver/compactions/CompactionConfiguration.getThrottlePoint:()J
       8: lcmp
       9: ifle          16
      12: iconst_1
      13: goto          17
      16: iconst_0
      17: ireturn

  public abstract boolean needsCompaction(java.util.Collection<org.apache.hadoop.hbase.regionserver.HStoreFile>, java.util.List<org.apache.hadoop.hbase.regionserver.HStoreFile>);

  protected java.util.ArrayList<org.apache.hadoop.hbase.regionserver.HStoreFile> getCurrentEligibleFiles(java.util.ArrayList<org.apache.hadoop.hbase.regionserver.HStoreFile>, java.util.List<org.apache.hadoop.hbase.regionserver.HStoreFile>);
    Code:
       0: aload_2
       1: invokeinterface #8,  1            // InterfaceMethod java/util/List.isEmpty:()Z
       6: ifne          62
       9: aload_2
      10: aload_2
      11: invokeinterface #10,  1           // InterfaceMethod java/util/List.size:()I
      16: iconst_1
      17: isub
      18: invokeinterface #51,  2           // InterfaceMethod java/util/List.get:(I)Ljava/lang/Object;
      23: checkcast     #52                 // class org/apache/hadoop/hbase/regionserver/HStoreFile
      26: astore_3
      27: aload_1
      28: aload_3
      29: invokevirtual #53                 // Method java/util/ArrayList.indexOf:(Ljava/lang/Object;)I
      32: istore        4
      34: iload         4
      36: iconst_m1
      37: if_icmpeq     44
      40: iconst_1
      41: goto          45
      44: iconst_0
      45: invokestatic  #54                 // Method org/apache/hbase/thirdparty/com/google/common/base/Preconditions.checkArgument:(Z)V
      48: aload_1
      49: iconst_0
      50: iload         4
      52: iconst_1
      53: iadd
      54: invokevirtual #55                 // Method java/util/ArrayList.subList:(II)Ljava/util/List;
      57: invokeinterface #56,  1           // InterfaceMethod java/util/List.clear:()V
      62: aload_1
      63: areturn

  protected java.util.ArrayList<org.apache.hadoop.hbase.regionserver.HStoreFile> skipLargeFiles(java.util.ArrayList<org.apache.hadoop.hbase.regionserver.HStoreFile>, boolean);
    Code:
       0: iconst_0
       1: istore_3
       2: iload_3
       3: aload_1
       4: invokevirtual #21                 // Method java/util/ArrayList.size:()I
       7: if_icmpge     56
      10: aload_1
      11: iload_3
      12: invokevirtual #57                 // Method java/util/ArrayList.get:(I)Ljava/lang/Object;
      15: checkcast     #52                 // class org/apache/hadoop/hbase/regionserver/HStoreFile
      18: invokevirtual #58                 // Method org/apache/hadoop/hbase/regionserver/HStoreFile.isReference:()Z
      21: ifne          56
      24: aload_1
      25: iload_3
      26: invokevirtual #57                 // Method java/util/ArrayList.get:(I)Ljava/lang/Object;
      29: checkcast     #52                 // class org/apache/hadoop/hbase/regionserver/HStoreFile
      32: invokevirtual #59                 // Method org/apache/hadoop/hbase/regionserver/HStoreFile.getReader:()Lorg/apache/hadoop/hbase/regionserver/StoreFileReader;
      35: invokevirtual #60                 // Method org/apache/hadoop/hbase/regionserver/StoreFileReader.length:()J
      38: aload_0
      39: getfield      #29                 // Field comConf:Lorg/apache/hadoop/hbase/regionserver/compactions/CompactionConfiguration;
      42: iload_2
      43: invokevirtual #61                 // Method org/apache/hadoop/hbase/regionserver/compactions/CompactionConfiguration.getMaxCompactSize:(Z)J
      46: lcmp
      47: ifle          56
      50: iinc          3, 1
      53: goto          2
      56: iload_3
      57: ifle          103
      60: getstatic     #13                 // Field LOG:Lorg/slf4j/Logger;
      63: new           #14                 // class java/lang/StringBuilder
      66: dup
      67: invokespecial #15                 // Method java/lang/StringBuilder."<init>":()V
      70: ldc           #62                 // String Some files are too large. Excluding
      72: invokevirtual #17                 // Method java/lang/StringBuilder.append:(Ljava/lang/String;)Ljava/lang/StringBuilder;
      75: iload_3
      76: invokevirtual #18                 // Method java/lang/StringBuilder.append:(I)Ljava/lang/StringBuilder;
      79: ldc           #63                 // String  files from compaction candidates
      81: invokevirtual #17                 // Method java/lang/StringBuilder.append:(Ljava/lang/String;)Ljava/lang/StringBuilder;
      84: invokevirtual #25                 // Method java/lang/StringBuilder.toString:()Ljava/lang/String;
      87: invokeinterface #26,  2           // InterfaceMethod org/slf4j/Logger.debug:(Ljava/lang/String;)V
      92: aload_1
      93: iconst_0
      94: iload_3
      95: invokevirtual #55                 // Method java/util/ArrayList.subList:(II)Ljava/util/List;
      98: invokeinterface #56,  1           // InterfaceMethod java/util/List.clear:()V
     103: aload_1
     104: areturn

  protected void filterBulk(java.util.ArrayList<org.apache.hadoop.hbase.regionserver.HStoreFile>);
    Code:
       0: aload_1
       1: invokedynamic #64,  0             // InvokeDynamic #0:test:()Ljava/util/function/Predicate;
       6: invokevirtual #65                 // Method java/util/ArrayList.removeIf:(Ljava/util/function/Predicate;)Z
       9: pop
      10: return

  protected void removeExcessFiles(java.util.ArrayList<org.apache.hadoop.hbase.regionserver.HStoreFile>, boolean, boolean);
    Code:
       0: aload_1
       1: invokevirtual #21                 // Method java/util/ArrayList.size:()I
       4: aload_0
       5: getfield      #29                 // Field comConf:Lorg/apache/hadoop/hbase/regionserver/compactions/CompactionConfiguration;
       8: invokevirtual #30                 // Method org/apache/hadoop/hbase/regionserver/compactions/CompactionConfiguration.getMaxFilesToCompact:()I
      11: isub
      12: istore        4
      14: iload         4
      16: ifle          121
      19: iload_3
      20: ifeq          68
      23: iload_2
      24: ifeq          68
      27: getstatic     #13                 // Field LOG:Lorg/slf4j/Logger;
      30: new           #14                 // class java/lang/StringBuilder
      33: dup
      34: invokespecial #15                 // Method java/lang/StringBuilder."<init>":()V
      37: ldc           #66                 // String Warning, compacting more than
      39: invokevirtual #17                 // Method java/lang/StringBuilder.append:(Ljava/lang/String;)Ljava/lang/StringBuilder;
      42: aload_0
      43: getfield      #29                 // Field comConf:Lorg/apache/hadoop/hbase/regionserver/compactions/CompactionConfiguration;
      46: invokevirtual #30                 // Method org/apache/hadoop/hbase/regionserver/compactions/CompactionConfiguration.getMaxFilesToCompact:()I
      49: invokevirtual #18                 // Method java/lang/StringBuilder.append:(I)Ljava/lang/StringBuilder;
      52: ldc           #67                 // String  files because of a user-requested major compaction
      54: invokevirtual #17                 // Method java/lang/StringBuilder.append:(Ljava/lang/String;)Ljava/lang/StringBuilder;
      57: invokevirtual #25                 // Method java/lang/StringBuilder.toString:()Ljava/lang/String;
      60: invokeinterface #26,  2           // InterfaceMethod org/slf4j/Logger.debug:(Ljava/lang/String;)V
      65: goto          121
      68: getstatic     #13                 // Field LOG:Lorg/slf4j/Logger;
      71: new           #14                 // class java/lang/StringBuilder
      74: dup
      75: invokespecial #15                 // Method java/lang/StringBuilder."<init>":()V
      78: ldc           #68                 // String Too many admissible files. Excluding
      80: invokevirtual #17                 // Method java/lang/StringBuilder.append:(Ljava/lang/String;)Ljava/lang/StringBuilder;
      83: iload         4
      85: invokevirtual #18                 // Method java/lang/StringBuilder.append:(I)Ljava/lang/StringBuilder;
      88: ldc           #63                 // String  files from compaction candidates
      90: invokevirtual #17                 // Method java/lang/StringBuilder.append:(Ljava/lang/String;)Ljava/lang/StringBuilder;
      93: invokevirtual #25                 // Method java/lang/StringBuilder.toString:()Ljava/lang/String;
      96: invokeinterface #26,  2           // InterfaceMethod org/slf4j/Logger.debug:(Ljava/lang/String;)V
     101: aload_1
     102: aload_0
     103: getfield      #29                 // Field comConf:Lorg/apache/hadoop/hbase/regionserver/compactions/CompactionConfiguration;
     106: invokevirtual #30                 // Method org/apache/hadoop/hbase/regionserver/compactions/CompactionConfiguration.getMaxFilesToCompact:()I
     109: aload_1
     110: invokevirtual #21                 // Method java/util/ArrayList.size:()I
     113: invokevirtual #55                 // Method java/util/ArrayList.subList:(II)Ljava/util/List;
     116: invokeinterface #56,  1           // InterfaceMethod java/util/List.clear:()V
     121: return

  protected java.util.ArrayList<org.apache.hadoop.hbase.regionserver.HStoreFile> checkMinFilesCriteria(java.util.ArrayList<org.apache.hadoop.hbase.regionserver.HStoreFile>, int);
    Code:
       0: aload_1
       1: invokevirtual #21                 // Method java/util/ArrayList.size:()I
       4: iload_2
       5: if_icmpge     67
       8: getstatic     #13                 // Field LOG:Lorg/slf4j/Logger;
      11: invokeinterface #69,  1           // InterfaceMethod org/slf4j/Logger.isDebugEnabled:()Z
      16: ifeq          63
      19: getstatic     #13                 // Field LOG:Lorg/slf4j/Logger;
      22: new           #14                 // class java/lang/StringBuilder
      25: dup
      26: invokespecial #15                 // Method java/lang/StringBuilder."<init>":()V
      29: ldc           #70                 // String Not compacting files because we only have
      31: invokevirtual #17                 // Method java/lang/StringBuilder.append:(Ljava/lang/String;)Ljava/lang/StringBuilder;
      34: aload_1
      35: invokevirtual #21                 // Method java/util/ArrayList.size:()I
      38: invokevirtual #18                 // Method java/lang/StringBuilder.append:(I)Ljava/lang/StringBuilder;
      41: ldc           #71                 // String  files ready for compaction. Need
      43: invokevirtual #17                 // Method java/lang/StringBuilder.append:(Ljava/lang/String;)Ljava/lang/StringBuilder;
      46: iload_2
      47: invokevirtual #18                 // Method java/lang/StringBuilder.append:(I)Ljava/lang/StringBuilder;
      50: ldc           #72                 // String  to initiate.
      52: invokevirtual #17                 // Method java/lang/StringBuilder.append:(Ljava/lang/String;)Ljava/lang/StringBuilder;
      55: invokevirtual #25                 // Method java/lang/StringBuilder.toString:()Ljava/lang/String;
      58: invokeinterface #26,  2           // InterfaceMethod org/slf4j/Logger.debug:(Ljava/lang/String;)V
      63: aload_1
      64: invokevirtual #73                 // Method java/util/ArrayList.clear:()V
      67: aload_1
      68: areturn

  static {};
    Code:
       0: ldc           #74                 // class org/apache/hadoop/hbase/regionserver/compactions/SortedCompactionPolicy
       2: invokestatic  #75                 // Method org/slf4j/LoggerFactory.getLogger:(Ljava/lang/Class;)Lorg/slf4j/Logger;
       5: putstatic     #13                 // Field LOG:Lorg/slf4j/Logger;
       8: return
}
