Compiled from "SpaceViolationPolicyEnforcementFactory.java"
class org.apache.hadoop.hbase.quotas.SpaceViolationPolicyEnforcementFactory$1 {
  static final int[] $SwitchMap$org$apache$hadoop$hbase$quotas$SpaceViolationPolicy;

  static {};
    Code:
       0: invokestatic  #1                  // Method org/apache/hadoop/hbase/quotas/SpaceViolationPolicy.values:()[Lorg/apache/hadoop/hbase/quotas/SpaceViolationPolicy;
       3: arraylength
       4: newarray       int
       6: putstatic     #2                  // Field $SwitchMap$org$apache$hadoop$hbase$quotas$SpaceViolationPolicy:[I
       9: getstatic     #2                  // Field $SwitchMap$org$apache$hadoop$hbase$quotas$SpaceViolationPolicy:[I
      12: getstatic     #3                  // Field org/apache/hadoop/hbase/quotas/SpaceViolationPolicy.DISABLE:Lorg/apache/hadoop/hbase/quotas/SpaceViolationPolicy;
      15: invokevirtual #4                  // Method org/apache/hadoop/hbase/quotas/SpaceViolationPolicy.ordinal:()I
      18: iconst_1
      19: iastore
      20: goto          24
      23: astore_0
      24: getstatic     #2                  // Field $SwitchMap$org$apache$hadoop$hbase$quotas$SpaceViolationPolicy:[I
      27: getstatic     #6                  // Field org/apache/hadoop/hbase/quotas/SpaceViolationPolicy.NO_WRITES_COMPACTIONS:Lorg/apache/hadoop/hbase/quotas/SpaceViolationPolicy;
      30: invokevirtual #4                  // Method org/apache/hadoop/hbase/quotas/SpaceViolationPolicy.ordinal:()I
      33: iconst_2
      34: iastore
      35: goto          39
      38: astore_0
      39: getstatic     #2                  // Field $SwitchMap$org$apache$hadoop$hbase$quotas$SpaceViolationPolicy:[I
      42: getstatic     #7                  // Field org/apache/hadoop/hbase/quotas/SpaceViolationPolicy.NO_WRITES:Lorg/apache/hadoop/hbase/quotas/SpaceViolationPolicy;
      45: invokevirtual #4                  // Method org/apache/hadoop/hbase/quotas/SpaceViolationPolicy.ordinal:()I
      48: iconst_3
      49: iastore
      50: goto          54
      53: astore_0
      54: getstatic     #2                  // Field $SwitchMap$org$apache$hadoop$hbase$quotas$SpaceViolationPolicy:[I
      57: getstatic     #8                  // Field org/apache/hadoop/hbase/quotas/SpaceViolationPolicy.NO_INSERTS:Lorg/apache/hadoop/hbase/quotas/SpaceViolationPolicy;
      60: invokevirtual #4                  // Method org/apache/hadoop/hbase/quotas/SpaceViolationPolicy.ordinal:()I
      63: iconst_4
      64: iastore
      65: goto          69
      68: astore_0
      69: return
    Exception table:
       from    to  target type
           9    20    23   Class java/lang/NoSuchFieldError
          24    35    38   Class java/lang/NoSuchFieldError
          39    50    53   Class java/lang/NoSuchFieldError
          54    65    68   Class java/lang/NoSuchFieldError
}
