Compiled from "SpaceQuotaHelperForTests.java"
class org.apache.hadoop.hbase.quotas.SpaceQuotaHelperForTests$NoFilesToDischarge implements org.apache.hadoop.hbase.Waiter$Predicate<java.lang.Exception> {
  org.apache.hadoop.hbase.quotas.SpaceQuotaHelperForTests$NoFilesToDischarge(org.apache.hadoop.hbase.MiniHBaseCluster, org.apache.hadoop.hbase.TableName);
    Code:
       0: aload_0
       1: invokespecial #1                  // Method java/lang/Object."<init>":()V
       4: aload_0
       5: aload_1
       6: putfield      #2                  // Field cluster:Lorg/apache/hadoop/hbase/MiniHBaseCluster;
       9: aload_0
      10: aload_2
      11: putfield      #3                  // Field tn:Lorg/apache/hadoop/hbase/TableName;
      14: return

  public boolean evaluate() throws java.lang.Exception;
    Code:
       0: aload_0
       1: getfield      #2                  // Field cluster:Lorg/apache/hadoop/hbase/MiniHBaseCluster;
       4: aload_0
       5: getfield      #3                  // Field tn:Lorg/apache/hadoop/hbase/TableName;
       8: invokevirtual #4                  // Method org/apache/hadoop/hbase/MiniHBaseCluster.getRegions:(Lorg/apache/hadoop/hbase/TableName;)Ljava/util/List;
      11: invokeinterface #5,  1            // InterfaceMethod java/util/List.iterator:()Ljava/util/Iterator;
      16: astore_1
      17: aload_1
      18: invokeinterface #6,  1            // InterfaceMethod java/util/Iterator.hasNext:()Z
      23: ifeq          140
      26: aload_1
      27: invokeinterface #7,  1            // InterfaceMethod java/util/Iterator.next:()Ljava/lang/Object;
      32: checkcast     #8                  // class org/apache/hadoop/hbase/regionserver/HRegion
      35: astore_2
      36: aload_2
      37: invokevirtual #9                  // Method org/apache/hadoop/hbase/regionserver/HRegion.getStores:()Ljava/util/List;
      40: invokeinterface #5,  1            // InterfaceMethod java/util/List.iterator:()Ljava/util/Iterator;
      45: astore_3
      46: aload_3
      47: invokeinterface #6,  1            // InterfaceMethod java/util/Iterator.hasNext:()Z
      52: ifeq          137
      55: aload_3
      56: invokeinterface #7,  1            // InterfaceMethod java/util/Iterator.next:()Ljava/lang/Object;
      61: checkcast     #10                 // class org/apache/hadoop/hbase/regionserver/HStore
      64: astore        4
      66: aload         4
      68: invokevirtual #11                 // Method org/apache/hadoop/hbase/regionserver/HStore.getStoreEngine:()Lorg/apache/hadoop/hbase/regionserver/StoreEngine;
      71: invokevirtual #12                 // Method org/apache/hadoop/hbase/regionserver/StoreEngine.getStoreFileManager:()Lorg/apache/hadoop/hbase/regionserver/StoreFileManager;
      74: invokeinterface #13,  1           // InterfaceMethod org/apache/hadoop/hbase/regionserver/StoreFileManager.getCompactedfiles:()Ljava/util/Collection;
      79: astore        5
      81: aconst_null
      82: aload         5
      84: if_acmpeq     134
      87: aload         5
      89: invokeinterface #14,  1           // InterfaceMethod java/util/Collection.isEmpty:()Z
      94: ifne          134
      97: invokestatic  #15                 // Method org/apache/hadoop/hbase/quotas/SpaceQuotaHelperForTests.access$000:()Lorg/slf4j/Logger;
     100: new           #16                 // class java/lang/StringBuilder
     103: dup
     104: invokespecial #17                 // Method java/lang/StringBuilder."<init>":()V
     107: aload_2
     108: invokevirtual #18                 // Method org/apache/hadoop/hbase/regionserver/HRegion.getRegionInfo:()Lorg/apache/hadoop/hbase/client/RegionInfo;
     111: invokeinterface #19,  1           // InterfaceMethod org/apache/hadoop/hbase/client/RegionInfo.getEncodedName:()Ljava/lang/String;
     116: invokevirtual #20                 // Method java/lang/StringBuilder.append:(Ljava/lang/String;)Ljava/lang/StringBuilder;
     119: ldc           #21                 // String  still has compacted files
     121: invokevirtual #20                 // Method java/lang/StringBuilder.append:(Ljava/lang/String;)Ljava/lang/StringBuilder;
     124: invokevirtual #22                 // Method java/lang/StringBuilder.toString:()Ljava/lang/String;
     127: invokeinterface #23,  2           // InterfaceMethod org/slf4j/Logger.debug:(Ljava/lang/String;)V
     132: iconst_0
     133: ireturn
     134: goto          46
     137: goto          17
     140: iconst_1
     141: ireturn
}
