Compiled from "SpaceQuotaHelperForTests.java"
class org.apache.hadoop.hbase.quotas.SpaceQuotaHelperForTests$1 implements org.apache.hadoop.hbase.Waiter$Predicate<java.io.IOException> {
  final org.apache.hadoop.hbase.client.Connection val$conn;

  final org.apache.hadoop.hbase.quotas.SpaceQuotaHelperForTests this$0;

  org.apache.hadoop.hbase.quotas.SpaceQuotaHelperForTests$1(org.apache.hadoop.hbase.quotas.SpaceQuotaHelperForTests, org.apache.hadoop.hbase.client.Connection);
    Code:
       0: aload_0
       1: aload_1
       2: putfield      #1                  // Field this$0:Lorg/apache/hadoop/hbase/quotas/SpaceQuotaHelperForTests;
       5: aload_0
       6: aload_2
       7: putfield      #2                  // Field val$conn:Lorg/apache/hadoop/hbase/client/Connection;
      10: aload_0
      11: invokespecial #3                  // Method java/lang/Object."<init>":()V
      14: return

  public boolean evaluate() throws java.io.IOException;
    Code:
       0: aload_0
       1: getfield      #2                  // Field val$conn:Lorg/apache/hadoop/hbase/client/Connection;
       4: invokeinterface #4,  1            // InterfaceMethod org/apache/hadoop/hbase/client/Connection.getAdmin:()Lorg/apache/hadoop/hbase/client/Admin;
       9: getstatic     #5                  // Field org/apache/hadoop/hbase/quotas/QuotaUtil.QUOTA_TABLE_NAME:Lorg/apache/hadoop/hbase/TableName;
      12: invokeinterface #6,  2            // InterfaceMethod org/apache/hadoop/hbase/client/Admin.tableExists:(Lorg/apache/hadoop/hbase/TableName;)Z
      17: ireturn
}
