Compiled from "SplitLogTask.java"
public class org.apache.hadoop.hbase.SplitLogTask {
  org.apache.hadoop.hbase.SplitLogTask(org.apache.hadoop.hbase.shaded.protobuf.generated.ZooKeeperProtos$SplitLogTask);
    Code:
       0: aload_0
       1: invokespecial #1                  // Method java/lang/Object."<init>":()V
       4: aload_0
       5: aload_1
       6: invokevirtual #2                  // Method org/apache/hadoop/hbase/shaded/protobuf/generated/ZooKeeperProtos$SplitLogTask.getServerName:()Lorg/apache/hadoop/hbase/shaded/protobuf/generated/HBaseProtos$ServerName;
       9: invokestatic  #3                  // Method org/apache/hadoop/hbase/shaded/protobuf/ProtobufUtil.toServerName:(Lorg/apache/hadoop/hbase/shaded/protobuf/generated/HBaseProtos$ServerName;)Lorg/apache/hadoop/hbase/ServerName;
      12: putfield      #4                  // Field originServer:Lorg/apache/hadoop/hbase/ServerName;
      15: aload_0
      16: aload_1
      17: invokevirtual #5                  // Method org/apache/hadoop/hbase/shaded/protobuf/generated/ZooKeeperProtos$SplitLogTask.getState:()Lorg/apache/hadoop/hbase/shaded/protobuf/generated/ZooKeeperProtos$SplitLogTask$State;
      20: putfield      #6                  // Field state:Lorg/apache/hadoop/hbase/shaded/protobuf/generated/ZooKeeperProtos$SplitLogTask$State;
      23: return

  org.apache.hadoop.hbase.SplitLogTask(org.apache.hadoop.hbase.ServerName, org.apache.hadoop.hbase.shaded.protobuf.generated.ZooKeeperProtos$SplitLogTask$State);
    Code:
       0: aload_0
       1: invokespecial #1                  // Method java/lang/Object."<init>":()V
       4: aload_0
       5: aload_1
       6: putfield      #4                  // Field originServer:Lorg/apache/hadoop/hbase/ServerName;
       9: aload_0
      10: aload_2
      11: putfield      #6                  // Field state:Lorg/apache/hadoop/hbase/shaded/protobuf/generated/ZooKeeperProtos$SplitLogTask$State;
      14: return

  public org.apache.hadoop.hbase.ServerName getServerName();
    Code:
       0: aload_0
       1: getfield      #4                  // Field originServer:Lorg/apache/hadoop/hbase/ServerName;
       4: areturn

  public boolean isUnassigned(org.apache.hadoop.hbase.ServerName);
    Code:
       0: aload_0
       1: getfield      #4                  // Field originServer:Lorg/apache/hadoop/hbase/ServerName;
       4: aload_1
       5: invokevirtual #7                  // Method org/apache/hadoop/hbase/ServerName.equals:(Ljava/lang/Object;)Z
       8: ifeq          22
      11: aload_0
      12: invokevirtual #8                  // Method isUnassigned:()Z
      15: ifeq          22
      18: iconst_1
      19: goto          23
      22: iconst_0
      23: ireturn

  public boolean isUnassigned();
    Code:
       0: aload_0
       1: getfield      #6                  // Field state:Lorg/apache/hadoop/hbase/shaded/protobuf/generated/ZooKeeperProtos$SplitLogTask$State;
       4: getstatic     #9                  // Field org/apache/hadoop/hbase/shaded/protobuf/generated/ZooKeeperProtos$SplitLogTask$State.UNASSIGNED:Lorg/apache/hadoop/hbase/shaded/protobuf/generated/ZooKeeperProtos$SplitLogTask$State;
       7: if_acmpne     14
      10: iconst_1
      11: goto          15
      14: iconst_0
      15: ireturn

  public boolean isOwned(org.apache.hadoop.hbase.ServerName);
    Code:
       0: aload_0
       1: getfield      #4                  // Field originServer:Lorg/apache/hadoop/hbase/ServerName;
       4: aload_1
       5: invokevirtual #7                  // Method org/apache/hadoop/hbase/ServerName.equals:(Ljava/lang/Object;)Z
       8: ifeq          22
      11: aload_0
      12: invokevirtual #10                 // Method isOwned:()Z
      15: ifeq          22
      18: iconst_1
      19: goto          23
      22: iconst_0
      23: ireturn

  public boolean isOwned();
    Code:
       0: aload_0
       1: getfield      #6                  // Field state:Lorg/apache/hadoop/hbase/shaded/protobuf/generated/ZooKeeperProtos$SplitLogTask$State;
       4: getstatic     #11                 // Field org/apache/hadoop/hbase/shaded/protobuf/generated/ZooKeeperProtos$SplitLogTask$State.OWNED:Lorg/apache/hadoop/hbase/shaded/protobuf/generated/ZooKeeperProtos$SplitLogTask$State;
       7: if_acmpne     14
      10: iconst_1
      11: goto          15
      14: iconst_0
      15: ireturn

  public boolean isResigned(org.apache.hadoop.hbase.ServerName);
    Code:
       0: aload_0
       1: getfield      #4                  // Field originServer:Lorg/apache/hadoop/hbase/ServerName;
       4: aload_1
       5: invokevirtual #7                  // Method org/apache/hadoop/hbase/ServerName.equals:(Ljava/lang/Object;)Z
       8: ifeq          22
      11: aload_0
      12: invokevirtual #12                 // Method isResigned:()Z
      15: ifeq          22
      18: iconst_1
      19: goto          23
      22: iconst_0
      23: ireturn

  public boolean isResigned();
    Code:
       0: aload_0
       1: getfield      #6                  // Field state:Lorg/apache/hadoop/hbase/shaded/protobuf/generated/ZooKeeperProtos$SplitLogTask$State;
       4: getstatic     #13                 // Field org/apache/hadoop/hbase/shaded/protobuf/generated/ZooKeeperProtos$SplitLogTask$State.RESIGNED:Lorg/apache/hadoop/hbase/shaded/protobuf/generated/ZooKeeperProtos$SplitLogTask$State;
       7: if_acmpne     14
      10: iconst_1
      11: goto          15
      14: iconst_0
      15: ireturn

  public boolean isDone(org.apache.hadoop.hbase.ServerName);
    Code:
       0: aload_0
       1: getfield      #4                  // Field originServer:Lorg/apache/hadoop/hbase/ServerName;
       4: aload_1
       5: invokevirtual #7                  // Method org/apache/hadoop/hbase/ServerName.equals:(Ljava/lang/Object;)Z
       8: ifeq          22
      11: aload_0
      12: invokevirtual #14                 // Method isDone:()Z
      15: ifeq          22
      18: iconst_1
      19: goto          23
      22: iconst_0
      23: ireturn

  public boolean isDone();
    Code:
       0: aload_0
       1: getfield      #6                  // Field state:Lorg/apache/hadoop/hbase/shaded/protobuf/generated/ZooKeeperProtos$SplitLogTask$State;
       4: getstatic     #15                 // Field org/apache/hadoop/hbase/shaded/protobuf/generated/ZooKeeperProtos$SplitLogTask$State.DONE:Lorg/apache/hadoop/hbase/shaded/protobuf/generated/ZooKeeperProtos$SplitLogTask$State;
       7: if_acmpne     14
      10: iconst_1
      11: goto          15
      14: iconst_0
      15: ireturn

  public boolean isErr(org.apache.hadoop.hbase.ServerName);
    Code:
       0: aload_0
       1: getfield      #4                  // Field originServer:Lorg/apache/hadoop/hbase/ServerName;
       4: aload_1
       5: invokevirtual #7                  // Method org/apache/hadoop/hbase/ServerName.equals:(Ljava/lang/Object;)Z
       8: ifeq          22
      11: aload_0
      12: invokevirtual #16                 // Method isErr:()Z
      15: ifeq          22
      18: iconst_1
      19: goto          23
      22: iconst_0
      23: ireturn

  public boolean isErr();
    Code:
       0: aload_0
       1: getfield      #6                  // Field state:Lorg/apache/hadoop/hbase/shaded/protobuf/generated/ZooKeeperProtos$SplitLogTask$State;
       4: getstatic     #17                 // Field org/apache/hadoop/hbase/shaded/protobuf/generated/ZooKeeperProtos$SplitLogTask$State.ERR:Lorg/apache/hadoop/hbase/shaded/protobuf/generated/ZooKeeperProtos$SplitLogTask$State;
       7: if_acmpne     14
      10: iconst_1
      11: goto          15
      14: iconst_0
      15: ireturn

  public java.lang.String toString();
    Code:
       0: new           #18                 // class java/lang/StringBuilder
       3: dup
       4: invokespecial #19                 // Method java/lang/StringBuilder."<init>":()V
       7: aload_0
       8: getfield      #6                  // Field state:Lorg/apache/hadoop/hbase/shaded/protobuf/generated/ZooKeeperProtos$SplitLogTask$State;
      11: invokevirtual #20                 // Method org/apache/hadoop/hbase/shaded/protobuf/generated/ZooKeeperProtos$SplitLogTask$State.toString:()Ljava/lang/String;
      14: invokevirtual #21                 // Method java/lang/StringBuilder.append:(Ljava/lang/String;)Ljava/lang/StringBuilder;
      17: ldc           #22                 // String
      19: invokevirtual #21                 // Method java/lang/StringBuilder.append:(Ljava/lang/String;)Ljava/lang/StringBuilder;
      22: aload_0
      23: getfield      #4                  // Field originServer:Lorg/apache/hadoop/hbase/ServerName;
      26: invokevirtual #23                 // Method org/apache/hadoop/hbase/ServerName.toString:()Ljava/lang/String;
      29: invokevirtual #21                 // Method java/lang/StringBuilder.append:(Ljava/lang/String;)Ljava/lang/StringBuilder;
      32: invokevirtual #24                 // Method java/lang/StringBuilder.toString:()Ljava/lang/String;
      35: areturn

  public boolean equals(java.lang.Object);
    Code:
       0: aload_1
       1: instanceof    #25                 // class org/apache/hadoop/hbase/SplitLogTask
       4: ifne          9
       7: iconst_0
       8: ireturn
       9: aload_1
      10: checkcast     #25                 // class org/apache/hadoop/hbase/SplitLogTask
      13: astore_2
      14: aload_2
      15: getfield      #6                  // Field state:Lorg/apache/hadoop/hbase/shaded/protobuf/generated/ZooKeeperProtos$SplitLogTask$State;
      18: aload_0
      19: getfield      #6                  // Field state:Lorg/apache/hadoop/hbase/shaded/protobuf/generated/ZooKeeperProtos$SplitLogTask$State;
      22: invokevirtual #26                 // Method org/apache/hadoop/hbase/shaded/protobuf/generated/ZooKeeperProtos$SplitLogTask$State.equals:(Ljava/lang/Object;)Z
      25: ifeq          46
      28: aload_2
      29: getfield      #4                  // Field originServer:Lorg/apache/hadoop/hbase/ServerName;
      32: aload_0
      33: getfield      #4                  // Field originServer:Lorg/apache/hadoop/hbase/ServerName;
      36: invokevirtual #7                  // Method org/apache/hadoop/hbase/ServerName.equals:(Ljava/lang/Object;)Z
      39: ifeq          46
      42: iconst_1
      43: goto          47
      46: iconst_0
      47: ireturn

  public int hashCode();
    Code:
       0: bipush        7
       2: istore_1
       3: bipush        31
       5: iload_1
       6: imul
       7: aload_0
       8: getfield      #6                  // Field state:Lorg/apache/hadoop/hbase/shaded/protobuf/generated/ZooKeeperProtos$SplitLogTask$State;
      11: invokevirtual #27                 // Method org/apache/hadoop/hbase/shaded/protobuf/generated/ZooKeeperProtos$SplitLogTask$State.hashCode:()I
      14: iadd
      15: istore_1
      16: bipush        31
      18: iload_1
      19: imul
      20: aload_0
      21: getfield      #4                  // Field originServer:Lorg/apache/hadoop/hbase/ServerName;
      24: invokevirtual #28                 // Method org/apache/hadoop/hbase/ServerName.hashCode:()I
      27: iadd
      28: ireturn

  public static org.apache.hadoop.hbase.SplitLogTask parseFrom(byte[]) throws org.apache.hadoop.hbase.exceptions.DeserializationException;
    Code:
       0: aload_0
       1: invokestatic  #29                 // Method org/apache/hadoop/hbase/shaded/protobuf/ProtobufUtil.expectPBMagicPrefix:([B)V
       4: invokestatic  #30                 // Method org/apache/hadoop/hbase/shaded/protobuf/ProtobufUtil.lengthOfPBMagic:()I
       7: istore_1
       8: invokestatic  #31                 // Method org/apache/hadoop/hbase/shaded/protobuf/generated/ZooKeeperProtos$SplitLogTask.newBuilder:()Lorg/apache/hadoop/hbase/shaded/protobuf/generated/ZooKeeperProtos$SplitLogTask$Builder;
      11: astore_2
      12: aload_2
      13: aload_0
      14: iload_1
      15: aload_0
      16: arraylength
      17: iload_1
      18: isub
      19: invokestatic  #32                 // Method org/apache/hadoop/hbase/shaded/protobuf/ProtobufUtil.mergeFrom:(Lorg/apache/hbase/thirdparty/com/google/protobuf/Message$Builder;[BII)V
      22: new           #25                 // class org/apache/hadoop/hbase/SplitLogTask
      25: dup
      26: aload_2
      27: invokevirtual #33                 // Method org/apache/hadoop/hbase/shaded/protobuf/generated/ZooKeeperProtos$SplitLogTask$Builder.build:()Lorg/apache/hadoop/hbase/shaded/protobuf/generated/ZooKeeperProtos$SplitLogTask;
      30: invokespecial #34                 // Method "<init>":(Lorg/apache/hadoop/hbase/shaded/protobuf/generated/ZooKeeperProtos$SplitLogTask;)V
      33: areturn
      34: astore_1
      35: new           #36                 // class org/apache/hadoop/hbase/exceptions/DeserializationException
      38: dup
      39: aload_0
      40: iconst_0
      41: bipush        64
      43: invokestatic  #37                 // Method org/apache/hadoop/hbase/util/Bytes.toStringBinary:([BII)Ljava/lang/String;
      46: aload_1
      47: invokespecial #38                 // Method org/apache/hadoop/hbase/exceptions/DeserializationException."<init>":(Ljava/lang/String;Ljava/lang/Throwable;)V
      50: athrow
    Exception table:
       from    to  target type
           4    33    34   Class java/io/IOException

  public byte[] toByteArray();
    Code:
       0: aload_0
       1: getfield      #4                  // Field originServer:Lorg/apache/hadoop/hbase/ServerName;
       4: invokestatic  #39                 // Method org/apache/hadoop/hbase/shaded/protobuf/ProtobufUtil.toServerName:(Lorg/apache/hadoop/hbase/ServerName;)Lorg/apache/hadoop/hbase/shaded/protobuf/generated/HBaseProtos$ServerName;
       7: astore_1
       8: invokestatic  #31                 // Method org/apache/hadoop/hbase/shaded/protobuf/generated/ZooKeeperProtos$SplitLogTask.newBuilder:()Lorg/apache/hadoop/hbase/shaded/protobuf/generated/ZooKeeperProtos$SplitLogTask$Builder;
      11: aload_1
      12: invokevirtual #40                 // Method org/apache/hadoop/hbase/shaded/protobuf/generated/ZooKeeperProtos$SplitLogTask$Builder.setServerName:(Lorg/apache/hadoop/hbase/shaded/protobuf/generated/HBaseProtos$ServerName;)Lorg/apache/hadoop/hbase/shaded/protobuf/generated/ZooKeeperProtos$SplitLogTask$Builder;
      15: aload_0
      16: getfield      #6                  // Field state:Lorg/apache/hadoop/hbase/shaded/protobuf/generated/ZooKeeperProtos$SplitLogTask$State;
      19: invokevirtual #41                 // Method org/apache/hadoop/hbase/shaded/protobuf/generated/ZooKeeperProtos$SplitLogTask$Builder.setState:(Lorg/apache/hadoop/hbase/shaded/protobuf/generated/ZooKeeperProtos$SplitLogTask$State;)Lorg/apache/hadoop/hbase/shaded/protobuf/generated/ZooKeeperProtos$SplitLogTask$Builder;
      22: invokevirtual #33                 // Method org/apache/hadoop/hbase/shaded/protobuf/generated/ZooKeeperProtos$SplitLogTask$Builder.build:()Lorg/apache/hadoop/hbase/shaded/protobuf/generated/ZooKeeperProtos$SplitLogTask;
      25: astore_2
      26: aload_2
      27: invokevirtual #42                 // Method org/apache/hadoop/hbase/shaded/protobuf/generated/ZooKeeperProtos$SplitLogTask.toByteArray:()[B
      30: invokestatic  #43                 // Method org/apache/hadoop/hbase/shaded/protobuf/ProtobufUtil.prependPBMagic:([B)[B
      33: areturn
}
