Compiled from "SplitTableRegionProcedure.java"
public class org.apache.hadoop.hbase.master.assignment.SplitTableRegionProcedure extends org.apache.hadoop.hbase.master.procedure.AbstractStateMachineRegionProcedure<org.apache.hadoop.hbase.shaded.protobuf.generated.MasterProcedureProtos$SplitTableRegionState> {
  static final boolean $assertionsDisabled;

  public org.apache.hadoop.hbase.master.assignment.SplitTableRegionProcedure();
    Code:
       0: aload_0
       1: invokespecial #2                  // Method org/apache/hadoop/hbase/master/procedure/AbstractStateMachineRegionProcedure."<init>":()V
       4: aload_0
       5: aconst_null
       6: putfield      #3                  // Field traceEnabled:Ljava/lang/Boolean;
       9: return

  public org.apache.hadoop.hbase.master.assignment.SplitTableRegionProcedure(org.apache.hadoop.hbase.master.procedure.MasterProcedureEnv, org.apache.hadoop.hbase.client.RegionInfo, byte[]) throws java.io.IOException;
    Code:
       0: aload_0
       1: aload_1
       2: aload_2
       3: invokespecial #4                  // Method org/apache/hadoop/hbase/master/procedure/AbstractStateMachineRegionProcedure."<init>":(Lorg/apache/hadoop/hbase/master/procedure/MasterProcedureEnv;Lorg/apache/hadoop/hbase/client/RegionInfo;)V
       6: aload_0
       7: aconst_null
       8: putfield      #3                  // Field traceEnabled:Ljava/lang/Boolean;
      11: aload_0
      12: aload_1
      13: iconst_1
      14: invokestatic  #5                  // Method java/lang/Boolean.valueOf:(Z)Ljava/lang/Boolean;
      17: invokevirtual #6                  // Method preflightChecks:(Lorg/apache/hadoop/hbase/master/procedure/MasterProcedureEnv;Ljava/lang/Boolean;)V
      20: aload_1
      21: aload_2
      22: invokestatic  #7                  // Method checkOnline:(Lorg/apache/hadoop/hbase/master/procedure/MasterProcedureEnv;Lorg/apache/hadoop/hbase/client/RegionInfo;)V
      25: aload_0
      26: aload_3
      27: putfield      #8                  // Field bestSplitRow:[B
      30: aload_0
      31: aload_1
      32: aload_2
      33: aload_0
      34: getfield      #8                  // Field bestSplitRow:[B
      37: invokespecial #9                  // Method checkSplittable:(Lorg/apache/hadoop/hbase/master/procedure/MasterProcedureEnv;Lorg/apache/hadoop/hbase/client/RegionInfo;[B)V
      40: aload_2
      41: invokeinterface #10,  1           // InterfaceMethod org/apache/hadoop/hbase/client/RegionInfo.getTable:()Lorg/apache/hadoop/hbase/TableName;
      46: astore        4
      48: aload_2
      49: invokestatic  #11                 // Method getDaughterRegionIdTimestamp:(Lorg/apache/hadoop/hbase/client/RegionInfo;)J
      52: lstore        5
      54: aload_0
      55: aload         4
      57: invokestatic  #12                 // Method org/apache/hadoop/hbase/client/RegionInfoBuilder.newBuilder:(Lorg/apache/hadoop/hbase/TableName;)Lorg/apache/hadoop/hbase/client/RegionInfoBuilder;
      60: aload_2
      61: invokeinterface #13,  1           // InterfaceMethod org/apache/hadoop/hbase/client/RegionInfo.getStartKey:()[B
      66: invokevirtual #14                 // Method org/apache/hadoop/hbase/client/RegionInfoBuilder.setStartKey:([B)Lorg/apache/hadoop/hbase/client/RegionInfoBuilder;
      69: aload_0
      70: getfield      #8                  // Field bestSplitRow:[B
      73: invokevirtual #15                 // Method org/apache/hadoop/hbase/client/RegionInfoBuilder.setEndKey:([B)Lorg/apache/hadoop/hbase/client/RegionInfoBuilder;
      76: iconst_0
      77: invokevirtual #16                 // Method org/apache/hadoop/hbase/client/RegionInfoBuilder.setSplit:(Z)Lorg/apache/hadoop/hbase/client/RegionInfoBuilder;
      80: lload         5
      82: invokevirtual #17                 // Method org/apache/hadoop/hbase/client/RegionInfoBuilder.setRegionId:(J)Lorg/apache/hadoop/hbase/client/RegionInfoBuilder;
      85: invokevirtual #18                 // Method org/apache/hadoop/hbase/client/RegionInfoBuilder.build:()Lorg/apache/hadoop/hbase/client/RegionInfo;
      88: putfield      #19                 // Field daughterOneRI:Lorg/apache/hadoop/hbase/client/RegionInfo;
      91: aload_0
      92: aload         4
      94: invokestatic  #12                 // Method org/apache/hadoop/hbase/client/RegionInfoBuilder.newBuilder:(Lorg/apache/hadoop/hbase/TableName;)Lorg/apache/hadoop/hbase/client/RegionInfoBuilder;
      97: aload_0
      98: getfield      #8                  // Field bestSplitRow:[B
     101: invokevirtual #14                 // Method org/apache/hadoop/hbase/client/RegionInfoBuilder.setStartKey:([B)Lorg/apache/hadoop/hbase/client/RegionInfoBuilder;
     104: aload_2
     105: invokeinterface #20,  1           // InterfaceMethod org/apache/hadoop/hbase/client/RegionInfo.getEndKey:()[B
     110: invokevirtual #15                 // Method org/apache/hadoop/hbase/client/RegionInfoBuilder.setEndKey:([B)Lorg/apache/hadoop/hbase/client/RegionInfoBuilder;
     113: iconst_0
     114: invokevirtual #16                 // Method org/apache/hadoop/hbase/client/RegionInfoBuilder.setSplit:(Z)Lorg/apache/hadoop/hbase/client/RegionInfoBuilder;
     117: lload         5
     119: invokevirtual #17                 // Method org/apache/hadoop/hbase/client/RegionInfoBuilder.setRegionId:(J)Lorg/apache/hadoop/hbase/client/RegionInfoBuilder;
     122: invokevirtual #18                 // Method org/apache/hadoop/hbase/client/RegionInfoBuilder.build:()Lorg/apache/hadoop/hbase/client/RegionInfo;
     125: putfield      #21                 // Field daughterTwoRI:Lorg/apache/hadoop/hbase/client/RegionInfo;
     128: aload_1
     129: invokevirtual #22                 // Method org/apache/hadoop/hbase/master/procedure/MasterProcedureEnv.getMasterServices:()Lorg/apache/hadoop/hbase/master/MasterServices;
     132: invokeinterface #23,  1           // InterfaceMethod org/apache/hadoop/hbase/master/MasterServices.getTableDescriptors:()Lorg/apache/hadoop/hbase/TableDescriptors;
     137: aload_0
     138: invokevirtual #24                 // Method getTableName:()Lorg/apache/hadoop/hbase/TableName;
     141: invokeinterface #25,  2           // InterfaceMethod org/apache/hadoop/hbase/TableDescriptors.get:(Lorg/apache/hadoop/hbase/TableName;)Lorg/apache/hadoop/hbase/client/TableDescriptor;
     146: astore        7
     148: aload         7
     150: invokeinterface #26,  1           // InterfaceMethod org/apache/hadoop/hbase/client/TableDescriptor.getRegionSplitPolicyClassName:()Ljava/lang/String;
     155: ifnull        185
     158: aload         7
     160: aload_1
     161: invokevirtual #27                 // Method org/apache/hadoop/hbase/master/procedure/MasterProcedureEnv.getMasterConfiguration:()Lorg/apache/hadoop/conf/Configuration;
     164: invokestatic  #28                 // Method org/apache/hadoop/hbase/regionserver/RegionSplitPolicy.getSplitPolicyClass:(Lorg/apache/hadoop/hbase/client/TableDescriptor;Lorg/apache/hadoop/conf/Configuration;)Ljava/lang/Class;
     167: astore        8
     169: aload_0
     170: aload         8
     172: aload_1
     173: invokevirtual #27                 // Method org/apache/hadoop/hbase/master/procedure/MasterProcedureEnv.getMasterConfiguration:()Lorg/apache/hadoop/conf/Configuration;
     176: invokestatic  #29                 // Method org/apache/hadoop/util/ReflectionUtils.newInstance:(Ljava/lang/Class;Lorg/apache/hadoop/conf/Configuration;)Ljava/lang/Object;
     179: checkcast     #30                 // class org/apache/hadoop/hbase/regionserver/RegionSplitPolicy
     182: putfield      #31                 // Field splitPolicy:Lorg/apache/hadoop/hbase/regionserver/RegionSplitPolicy;
     185: return

  protected org.apache.hadoop.hbase.procedure2.Procedure$LockState acquireLock(org.apache.hadoop.hbase.master.procedure.MasterProcedureEnv);
    Code:
       0: aload_1
       1: invokevirtual #32                 // Method org/apache/hadoop/hbase/master/procedure/MasterProcedureEnv.getProcedureScheduler:()Lorg/apache/hadoop/hbase/master/procedure/MasterProcedureScheduler;
       4: aload_0
       5: aload_0
       6: invokevirtual #24                 // Method getTableName:()Lorg/apache/hadoop/hbase/TableName;
       9: iconst_3
      10: anewarray     #33                 // class org/apache/hadoop/hbase/client/RegionInfo
      13: dup
      14: iconst_0
      15: aload_0
      16: invokespecial #34                 // Method getParentRegion:()Lorg/apache/hadoop/hbase/client/RegionInfo;
      19: aastore
      20: dup
      21: iconst_1
      22: aload_0
      23: getfield      #19                 // Field daughterOneRI:Lorg/apache/hadoop/hbase/client/RegionInfo;
      26: aastore
      27: dup
      28: iconst_2
      29: aload_0
      30: getfield      #21                 // Field daughterTwoRI:Lorg/apache/hadoop/hbase/client/RegionInfo;
      33: aastore
      34: invokevirtual #35                 // Method org/apache/hadoop/hbase/master/procedure/MasterProcedureScheduler.waitRegions:(Lorg/apache/hadoop/hbase/procedure2/Procedure;Lorg/apache/hadoop/hbase/TableName;[Lorg/apache/hadoop/hbase/client/RegionInfo;)Z
      37: ifeq          87
      40: getstatic     #36                 // Field LOG:Lorg/slf4j/Logger;
      43: new           #37                 // class java/lang/StringBuilder
      46: dup
      47: invokespecial #38                 // Method java/lang/StringBuilder."<init>":()V
      50: getstatic     #39                 // Field org/apache/hadoop/hbase/procedure2/Procedure$LockState.LOCK_EVENT_WAIT:Lorg/apache/hadoop/hbase/procedure2/Procedure$LockState;
      53: invokevirtual #40                 // Method java/lang/StringBuilder.append:(Ljava/lang/Object;)Ljava/lang/StringBuilder;
      56: ldc           #41                 // String
      58: invokevirtual #42                 // Method java/lang/StringBuilder.append:(Ljava/lang/String;)Ljava/lang/StringBuilder;
      61: aload_1
      62: invokevirtual #32                 // Method org/apache/hadoop/hbase/master/procedure/MasterProcedureEnv.getProcedureScheduler:()Lorg/apache/hadoop/hbase/master/procedure/MasterProcedureScheduler;
      65: invokevirtual #43                 // Method org/apache/hadoop/hbase/master/procedure/MasterProcedureScheduler.dumpLocks:()Ljava/lang/String;
      68: invokevirtual #42                 // Method java/lang/StringBuilder.append:(Ljava/lang/String;)Ljava/lang/StringBuilder;
      71: invokevirtual #44                 // Method java/lang/StringBuilder.toString:()Ljava/lang/String;
      74: invokeinterface #45,  2           // InterfaceMethod org/slf4j/Logger.debug:(Ljava/lang/String;)V
      79: goto          83
      82: astore_2
      83: getstatic     #39                 // Field org/apache/hadoop/hbase/procedure2/Procedure$LockState.LOCK_EVENT_WAIT:Lorg/apache/hadoop/hbase/procedure2/Procedure$LockState;
      86: areturn
      87: getstatic     #47                 // Field org/apache/hadoop/hbase/procedure2/Procedure$LockState.LOCK_ACQUIRED:Lorg/apache/hadoop/hbase/procedure2/Procedure$LockState;
      90: areturn
    Exception table:
       from    to  target type
          40    79    82   Class java/io/IOException

  protected void releaseLock(org.apache.hadoop.hbase.master.procedure.MasterProcedureEnv);
    Code:
       0: aload_1
       1: invokevirtual #32                 // Method org/apache/hadoop/hbase/master/procedure/MasterProcedureEnv.getProcedureScheduler:()Lorg/apache/hadoop/hbase/master/procedure/MasterProcedureScheduler;
       4: aload_0
       5: aload_0
       6: invokevirtual #24                 // Method getTableName:()Lorg/apache/hadoop/hbase/TableName;
       9: iconst_3
      10: anewarray     #33                 // class org/apache/hadoop/hbase/client/RegionInfo
      13: dup
      14: iconst_0
      15: aload_0
      16: invokespecial #34                 // Method getParentRegion:()Lorg/apache/hadoop/hbase/client/RegionInfo;
      19: aastore
      20: dup
      21: iconst_1
      22: aload_0
      23: getfield      #19                 // Field daughterOneRI:Lorg/apache/hadoop/hbase/client/RegionInfo;
      26: aastore
      27: dup
      28: iconst_2
      29: aload_0
      30: getfield      #21                 // Field daughterTwoRI:Lorg/apache/hadoop/hbase/client/RegionInfo;
      33: aastore
      34: invokevirtual #48                 // Method org/apache/hadoop/hbase/master/procedure/MasterProcedureScheduler.wakeRegions:(Lorg/apache/hadoop/hbase/procedure2/Procedure;Lorg/apache/hadoop/hbase/TableName;[Lorg/apache/hadoop/hbase/client/RegionInfo;)V
      37: return

  public org.apache.hadoop.hbase.client.RegionInfo getDaughterOneRI();
    Code:
       0: aload_0
       1: getfield      #19                 // Field daughterOneRI:Lorg/apache/hadoop/hbase/client/RegionInfo;
       4: areturn

  public org.apache.hadoop.hbase.client.RegionInfo getDaughterTwoRI();
    Code:
       0: aload_0
       1: getfield      #21                 // Field daughterTwoRI:Lorg/apache/hadoop/hbase/client/RegionInfo;
       4: areturn

  protected org.apache.hadoop.hbase.procedure2.StateMachineProcedure$Flow executeFromState(org.apache.hadoop.hbase.master.procedure.MasterProcedureEnv, org.apache.hadoop.hbase.shaded.protobuf.generated.MasterProcedureProtos$SplitTableRegionState) throws java.lang.InterruptedException;
    Code:
       0: getstatic     #36                 // Field LOG:Lorg/slf4j/Logger;
       3: ldc           #92                 // String {} execute state={}
       5: aload_0
       6: aload_2
       7: invokeinterface #93,  4           // InterfaceMethod org/slf4j/Logger.trace:(Ljava/lang/String;Ljava/lang/Object;Ljava/lang/Object;)V
      12: getstatic     #94                 // Field org/apache/hadoop/hbase/master/assignment/SplitTableRegionProcedure$1.$SwitchMap$org$apache$hadoop$hbase$shaded$protobuf$generated$MasterProcedureProtos$SplitTableRegionState:[I
      15: aload_2
      16: invokevirtual #95                 // Method org/apache/hadoop/hbase/shaded/protobuf/generated/MasterProcedureProtos$SplitTableRegionState.ordinal:()I
      19: iaload
      20: tableswitch   { // 1 to 11
                     1: 80
                     2: 102
                     3: 117
                     4: 136
                     5: 151
                     6: 171
                     7: 186
                     8: 201
                     9: 216
                    10: 231
                    11: 250
               default: 259
          }
      80: aload_0
      81: aload_1
      82: invokevirtual #96                 // Method prepareSplitRegion:(Lorg/apache/hadoop/hbase/master/procedure/MasterProcedureEnv;)Z
      85: ifeq          98
      88: aload_0
      89: getstatic     #97                 // Field org/apache/hadoop/hbase/shaded/protobuf/generated/MasterProcedureProtos$SplitTableRegionState.SPLIT_TABLE_REGION_PRE_OPERATION:Lorg/apache/hadoop/hbase/shaded/protobuf/generated/MasterProcedureProtos$SplitTableRegionState;
      92: invokevirtual #98                 // Method setNextState:(Ljava/lang/Object;)V
      95: goto          290
      98: getstatic     #99                 // Field org/apache/hadoop/hbase/procedure2/StateMachineProcedure$Flow.NO_MORE_STATE:Lorg/apache/hadoop/hbase/procedure2/StateMachineProcedure$Flow;
     101: areturn
     102: aload_0
     103: aload_1
     104: invokespecial #100                // Method preSplitRegion:(Lorg/apache/hadoop/hbase/master/procedure/MasterProcedureEnv;)V
     107: aload_0
     108: getstatic     #101                // Field org/apache/hadoop/hbase/shaded/protobuf/generated/MasterProcedureProtos$SplitTableRegionState.SPLIT_TABLE_REGION_CLOSE_PARENT_REGION:Lorg/apache/hadoop/hbase/shaded/protobuf/generated/MasterProcedureProtos$SplitTableRegionState;
     111: invokevirtual #98                 // Method setNextState:(Ljava/lang/Object;)V
     114: goto          290
     117: aload_0
     118: aload_0
     119: aload_1
     120: invokespecial #102                // Method createUnassignProcedures:(Lorg/apache/hadoop/hbase/master/procedure/MasterProcedureEnv;)[Lorg/apache/hadoop/hbase/master/assignment/TransitRegionStateProcedure;
     123: invokevirtual #103                // Method addChildProcedure:([Lorg/apache/hadoop/hbase/procedure2/Procedure;)V
     126: aload_0
     127: getstatic     #104                // Field org/apache/hadoop/hbase/shaded/protobuf/generated/MasterProcedureProtos$SplitTableRegionState.SPLIT_TABLE_REGIONS_CHECK_CLOSED_REGIONS:Lorg/apache/hadoop/hbase/shaded/protobuf/generated/MasterProcedureProtos$SplitTableRegionState;
     130: invokevirtual #98                 // Method setNextState:(Ljava/lang/Object;)V
     133: goto          290
     136: aload_0
     137: aload_1
     138: invokespecial #105                // Method checkClosedRegions:(Lorg/apache/hadoop/hbase/master/procedure/MasterProcedureEnv;)V
     141: aload_0
     142: getstatic     #106                // Field org/apache/hadoop/hbase/shaded/protobuf/generated/MasterProcedureProtos$SplitTableRegionState.SPLIT_TABLE_REGION_CREATE_DAUGHTER_REGIONS:Lorg/apache/hadoop/hbase/shaded/protobuf/generated/MasterProcedureProtos$SplitTableRegionState;
     145: invokevirtual #98                 // Method setNextState:(Ljava/lang/Object;)V
     148: goto          290
     151: aload_0
     152: aload_1
     153: invokespecial #107                // Method removeNonDefaultReplicas:(Lorg/apache/hadoop/hbase/master/procedure/MasterProcedureEnv;)V
     156: aload_0
     157: aload_1
     158: invokevirtual #108                // Method createDaughterRegions:(Lorg/apache/hadoop/hbase/master/procedure/MasterProcedureEnv;)V
     161: aload_0
     162: getstatic     #109                // Field org/apache/hadoop/hbase/shaded/protobuf/generated/MasterProcedureProtos$SplitTableRegionState.SPLIT_TABLE_REGION_WRITE_MAX_SEQUENCE_ID_FILE:Lorg/apache/hadoop/hbase/shaded/protobuf/generated/MasterProcedureProtos$SplitTableRegionState;
     165: invokevirtual #98                 // Method setNextState:(Ljava/lang/Object;)V
     168: goto          290
     171: aload_0
     172: aload_1
     173: invokespecial #110                // Method writeMaxSequenceIdFile:(Lorg/apache/hadoop/hbase/master/procedure/MasterProcedureEnv;)V
     176: aload_0
     177: getstatic     #111                // Field org/apache/hadoop/hbase/shaded/protobuf/generated/MasterProcedureProtos$SplitTableRegionState.SPLIT_TABLE_REGION_PRE_OPERATION_BEFORE_META:Lorg/apache/hadoop/hbase/shaded/protobuf/generated/MasterProcedureProtos$SplitTableRegionState;
     180: invokevirtual #98                 // Method setNextState:(Ljava/lang/Object;)V
     183: goto          290
     186: aload_0
     187: aload_1
     188: invokespecial #112                // Method preSplitRegionBeforeMETA:(Lorg/apache/hadoop/hbase/master/procedure/MasterProcedureEnv;)V
     191: aload_0
     192: getstatic     #113                // Field org/apache/hadoop/hbase/shaded/protobuf/generated/MasterProcedureProtos$SplitTableRegionState.SPLIT_TABLE_REGION_UPDATE_META:Lorg/apache/hadoop/hbase/shaded/protobuf/generated/MasterProcedureProtos$SplitTableRegionState;
     195: invokevirtual #98                 // Method setNextState:(Ljava/lang/Object;)V
     198: goto          290
     201: aload_0
     202: aload_1
     203: invokespecial #114                // Method updateMeta:(Lorg/apache/hadoop/hbase/master/procedure/MasterProcedureEnv;)V
     206: aload_0
     207: getstatic     #115                // Field org/apache/hadoop/hbase/shaded/protobuf/generated/MasterProcedureProtos$SplitTableRegionState.SPLIT_TABLE_REGION_PRE_OPERATION_AFTER_META:Lorg/apache/hadoop/hbase/shaded/protobuf/generated/MasterProcedureProtos$SplitTableRegionState;
     210: invokevirtual #98                 // Method setNextState:(Ljava/lang/Object;)V
     213: goto          290
     216: aload_0
     217: aload_1
     218: invokespecial #116                // Method preSplitRegionAfterMETA:(Lorg/apache/hadoop/hbase/master/procedure/MasterProcedureEnv;)V
     221: aload_0
     222: getstatic     #117                // Field org/apache/hadoop/hbase/shaded/protobuf/generated/MasterProcedureProtos$SplitTableRegionState.SPLIT_TABLE_REGION_OPEN_CHILD_REGIONS:Lorg/apache/hadoop/hbase/shaded/protobuf/generated/MasterProcedureProtos$SplitTableRegionState;
     225: invokevirtual #98                 // Method setNextState:(Ljava/lang/Object;)V
     228: goto          290
     231: aload_0
     232: aload_0
     233: aload_1
     234: invokespecial #118                // Method createAssignProcedures:(Lorg/apache/hadoop/hbase/master/procedure/MasterProcedureEnv;)[Lorg/apache/hadoop/hbase/master/assignment/TransitRegionStateProcedure;
     237: invokevirtual #103                // Method addChildProcedure:([Lorg/apache/hadoop/hbase/procedure2/Procedure;)V
     240: aload_0
     241: getstatic     #119                // Field org/apache/hadoop/hbase/shaded/protobuf/generated/MasterProcedureProtos$SplitTableRegionState.SPLIT_TABLE_REGION_POST_OPERATION:Lorg/apache/hadoop/hbase/shaded/protobuf/generated/MasterProcedureProtos$SplitTableRegionState;
     244: invokevirtual #98                 // Method setNextState:(Ljava/lang/Object;)V
     247: goto          290
     250: aload_0
     251: aload_1
     252: invokespecial #120                // Method postSplitRegion:(Lorg/apache/hadoop/hbase/master/procedure/MasterProcedureEnv;)V
     255: getstatic     #99                 // Field org/apache/hadoop/hbase/procedure2/StateMachineProcedure$Flow.NO_MORE_STATE:Lorg/apache/hadoop/hbase/procedure2/StateMachineProcedure$Flow;
     258: areturn
     259: new           #121                // class java/lang/UnsupportedOperationException
     262: dup
     263: new           #37                 // class java/lang/StringBuilder
     266: dup
     267: invokespecial #38                 // Method java/lang/StringBuilder."<init>":()V
     270: aload_0
     271: invokevirtual #40                 // Method java/lang/StringBuilder.append:(Ljava/lang/Object;)Ljava/lang/StringBuilder;
     274: ldc           #122                // String  unhandled state=
     276: invokevirtual #42                 // Method java/lang/StringBuilder.append:(Ljava/lang/String;)Ljava/lang/StringBuilder;
     279: aload_2
     280: invokevirtual #40                 // Method java/lang/StringBuilder.append:(Ljava/lang/Object;)Ljava/lang/StringBuilder;
     283: invokevirtual #44                 // Method java/lang/StringBuilder.toString:()Ljava/lang/String;
     286: invokespecial #123                // Method java/lang/UnsupportedOperationException."<init>":(Ljava/lang/String;)V
     289: athrow
     290: goto          372
     293: astore_3
     294: new           #37                 // class java/lang/StringBuilder
     297: dup
     298: invokespecial #38                 // Method java/lang/StringBuilder."<init>":()V
     301: ldc           #124                // String Splitting
     303: invokevirtual #42                 // Method java/lang/StringBuilder.append:(Ljava/lang/String;)Ljava/lang/StringBuilder;
     306: aload_0
     307: invokespecial #34                 // Method getParentRegion:()Lorg/apache/hadoop/hbase/client/RegionInfo;
     310: invokeinterface #125,  1          // InterfaceMethod org/apache/hadoop/hbase/client/RegionInfo.getEncodedName:()Ljava/lang/String;
     315: invokevirtual #42                 // Method java/lang/StringBuilder.append:(Ljava/lang/String;)Ljava/lang/StringBuilder;
     318: ldc           #126                // String ,
     320: invokevirtual #42                 // Method java/lang/StringBuilder.append:(Ljava/lang/String;)Ljava/lang/StringBuilder;
     323: aload_0
     324: invokevirtual #40                 // Method java/lang/StringBuilder.append:(Ljava/lang/Object;)Ljava/lang/StringBuilder;
     327: invokevirtual #44                 // Method java/lang/StringBuilder.toString:()Ljava/lang/String;
     330: astore        4
     332: aload_0
     333: aload_2
     334: invokevirtual #127                // Method isRollbackSupported:(Lorg/apache/hadoop/hbase/shaded/protobuf/generated/MasterProcedureProtos$SplitTableRegionState;)Z
     337: ifne          354
     340: getstatic     #36                 // Field LOG:Lorg/slf4j/Logger;
     343: aload         4
     345: aload_3
     346: invokeinterface #128,  3          // InterfaceMethod org/slf4j/Logger.warn:(Ljava/lang/String;Ljava/lang/Throwable;)V
     351: goto          372
     354: getstatic     #36                 // Field LOG:Lorg/slf4j/Logger;
     357: aload         4
     359: aload_3
     360: invokeinterface #129,  3          // InterfaceMethod org/slf4j/Logger.error:(Ljava/lang/String;Ljava/lang/Throwable;)V
     365: aload_0
     366: ldc           #130                // String master-split-regions
     368: aload_3
     369: invokevirtual #131                // Method setFailure:(Ljava/lang/String;Ljava/lang/Throwable;)V
     372: getstatic     #132                // Field org/apache/hadoop/hbase/procedure2/StateMachineProcedure$Flow.HAS_MORE_STATE:Lorg/apache/hadoop/hbase/procedure2/StateMachineProcedure$Flow;
     375: areturn
    Exception table:
       from    to  target type
          12   101   293   Class java/io/IOException
         102   258   293   Class java/io/IOException
         259   290   293   Class java/io/IOException

  protected void rollbackState(org.apache.hadoop.hbase.master.procedure.MasterProcedureEnv, org.apache.hadoop.hbase.shaded.protobuf.generated.MasterProcedureProtos$SplitTableRegionState) throws java.io.IOException, java.lang.InterruptedException;
    Code:
       0: aload_0
       1: invokespecial #133                // Method isTraceEnabled:()Z
       4: ifeq          38
       7: getstatic     #36                 // Field LOG:Lorg/slf4j/Logger;
      10: new           #37                 // class java/lang/StringBuilder
      13: dup
      14: invokespecial #38                 // Method java/lang/StringBuilder."<init>":()V
      17: aload_0
      18: invokevirtual #40                 // Method java/lang/StringBuilder.append:(Ljava/lang/Object;)Ljava/lang/StringBuilder;
      21: ldc           #134                // String  rollback state=
      23: invokevirtual #42                 // Method java/lang/StringBuilder.append:(Ljava/lang/String;)Ljava/lang/StringBuilder;
      26: aload_2
      27: invokevirtual #40                 // Method java/lang/StringBuilder.append:(Ljava/lang/Object;)Ljava/lang/StringBuilder;
      30: invokevirtual #44                 // Method java/lang/StringBuilder.toString:()Ljava/lang/String;
      33: invokeinterface #135,  2          // InterfaceMethod org/slf4j/Logger.trace:(Ljava/lang/String;)V
      38: getstatic     #94                 // Field org/apache/hadoop/hbase/master/assignment/SplitTableRegionProcedure$1.$SwitchMap$org$apache$hadoop$hbase$shaded$protobuf$generated$MasterProcedureProtos$SplitTableRegionState:[I
      41: aload_2
      42: invokevirtual #95                 // Method org/apache/hadoop/hbase/shaded/protobuf/generated/MasterProcedureProtos$SplitTableRegionState.ordinal:()I
      45: iaload
      46: tableswitch   { // 1 to 11
                     1: 160
                     2: 152
                     3: 144
                     4: 141
                     5: 138
                     6: 138
                     7: 135
                     8: 104
                     9: 104
                    10: 104
                    11: 104
               default: 163
          }
     104: new           #121                // class java/lang/UnsupportedOperationException
     107: dup
     108: new           #37                 // class java/lang/StringBuilder
     111: dup
     112: invokespecial #38                 // Method java/lang/StringBuilder."<init>":()V
     115: aload_0
     116: invokevirtual #40                 // Method java/lang/StringBuilder.append:(Ljava/lang/Object;)Ljava/lang/StringBuilder;
     119: ldc           #122                // String  unhandled state=
     121: invokevirtual #42                 // Method java/lang/StringBuilder.append:(Ljava/lang/String;)Ljava/lang/StringBuilder;
     124: aload_2
     125: invokevirtual #40                 // Method java/lang/StringBuilder.append:(Ljava/lang/Object;)Ljava/lang/StringBuilder;
     128: invokevirtual #44                 // Method java/lang/StringBuilder.toString:()Ljava/lang/String;
     131: invokespecial #123                // Method java/lang/UnsupportedOperationException."<init>":(Ljava/lang/String;)V
     134: athrow
     135: goto          194
     138: goto          194
     141: goto          194
     144: aload_0
     145: aload_1
     146: invokespecial #136                // Method openParentRegion:(Lorg/apache/hadoop/hbase/master/procedure/MasterProcedureEnv;)V
     149: goto          194
     152: aload_0
     153: aload_1
     154: invokespecial #137                // Method postRollBackSplitRegion:(Lorg/apache/hadoop/hbase/master/procedure/MasterProcedureEnv;)V
     157: goto          194
     160: goto          194
     163: new           #121                // class java/lang/UnsupportedOperationException
     166: dup
     167: new           #37                 // class java/lang/StringBuilder
     170: dup
     171: invokespecial #38                 // Method java/lang/StringBuilder."<init>":()V
     174: aload_0
     175: invokevirtual #40                 // Method java/lang/StringBuilder.append:(Ljava/lang/Object;)Ljava/lang/StringBuilder;
     178: ldc           #122                // String  unhandled state=
     180: invokevirtual #42                 // Method java/lang/StringBuilder.append:(Ljava/lang/String;)Ljava/lang/StringBuilder;
     183: aload_2
     184: invokevirtual #40                 // Method java/lang/StringBuilder.append:(Ljava/lang/Object;)Ljava/lang/StringBuilder;
     187: invokevirtual #44                 // Method java/lang/StringBuilder.toString:()Ljava/lang/String;
     190: invokespecial #123                // Method java/lang/UnsupportedOperationException."<init>":(Ljava/lang/String;)V
     193: athrow
     194: goto          269
     197: astore_3
     198: getstatic     #36                 // Field LOG:Lorg/slf4j/Logger;
     201: new           #37                 // class java/lang/StringBuilder
     204: dup
     205: invokespecial #38                 // Method java/lang/StringBuilder."<init>":()V
     208: ldc           #138                // String pid=
     210: invokevirtual #42                 // Method java/lang/StringBuilder.append:(Ljava/lang/String;)Ljava/lang/StringBuilder;
     213: aload_0
     214: invokevirtual #139                // Method getProcId:()J
     217: invokevirtual #85                 // Method java/lang/StringBuilder.append:(J)Ljava/lang/StringBuilder;
     220: ldc           #140                // String  failed rollback attempt step
     222: invokevirtual #42                 // Method java/lang/StringBuilder.append:(Ljava/lang/String;)Ljava/lang/StringBuilder;
     225: aload_2
     226: invokevirtual #40                 // Method java/lang/StringBuilder.append:(Ljava/lang/Object;)Ljava/lang/StringBuilder;
     229: ldc           #141                // String  for splitting the region
     231: invokevirtual #42                 // Method java/lang/StringBuilder.append:(Ljava/lang/String;)Ljava/lang/StringBuilder;
     234: aload_0
     235: invokespecial #34                 // Method getParentRegion:()Lorg/apache/hadoop/hbase/client/RegionInfo;
     238: invokeinterface #125,  1          // InterfaceMethod org/apache/hadoop/hbase/client/RegionInfo.getEncodedName:()Ljava/lang/String;
     243: invokevirtual #42                 // Method java/lang/StringBuilder.append:(Ljava/lang/String;)Ljava/lang/StringBuilder;
     246: ldc           #142                // String  in table
     248: invokevirtual #42                 // Method java/lang/StringBuilder.append:(Ljava/lang/String;)Ljava/lang/StringBuilder;
     251: aload_0
     252: invokevirtual #24                 // Method getTableName:()Lorg/apache/hadoop/hbase/TableName;
     255: invokevirtual #40                 // Method java/lang/StringBuilder.append:(Ljava/lang/Object;)Ljava/lang/StringBuilder;
     258: invokevirtual #44                 // Method java/lang/StringBuilder.toString:()Ljava/lang/String;
     261: aload_3
     262: invokeinterface #128,  3          // InterfaceMethod org/slf4j/Logger.warn:(Ljava/lang/String;Ljava/lang/Throwable;)V
     267: aload_3
     268: athrow
     269: return
    Exception table:
       from    to  target type
          38   194   197   Class java/io/IOException

  protected boolean isRollbackSupported(org.apache.hadoop.hbase.shaded.protobuf.generated.MasterProcedureProtos$SplitTableRegionState);
    Code:
       0: getstatic     #94                 // Field org/apache/hadoop/hbase/master/assignment/SplitTableRegionProcedure$1.$SwitchMap$org$apache$hadoop$hbase$shaded$protobuf$generated$MasterProcedureProtos$SplitTableRegionState:[I
       3: aload_1
       4: invokevirtual #95                 // Method org/apache/hadoop/hbase/shaded/protobuf/generated/MasterProcedureProtos$SplitTableRegionState.ordinal:()I
       7: iaload
       8: tableswitch   { // 8 to 11
                     8: 40
                     9: 40
                    10: 40
                    11: 40
               default: 42
          }
      40: iconst_0
      41: ireturn
      42: iconst_1
      43: ireturn

  protected org.apache.hadoop.hbase.shaded.protobuf.generated.MasterProcedureProtos$SplitTableRegionState getState(int);
    Code:
       0: iload_1
       1: invokestatic  #143                // Method org/apache/hadoop/hbase/shaded/protobuf/generated/MasterProcedureProtos$SplitTableRegionState.forNumber:(I)Lorg/apache/hadoop/hbase/shaded/protobuf/generated/MasterProcedureProtos$SplitTableRegionState;
       4: areturn

  protected int getStateId(org.apache.hadoop.hbase.shaded.protobuf.generated.MasterProcedureProtos$SplitTableRegionState);
    Code:
       0: aload_1
       1: invokevirtual #144                // Method org/apache/hadoop/hbase/shaded/protobuf/generated/MasterProcedureProtos$SplitTableRegionState.getNumber:()I
       4: ireturn

  protected org.apache.hadoop.hbase.shaded.protobuf.generated.MasterProcedureProtos$SplitTableRegionState getInitialState();
    Code:
       0: getstatic     #145                // Field org/apache/hadoop/hbase/shaded/protobuf/generated/MasterProcedureProtos$SplitTableRegionState.SPLIT_TABLE_REGION_PREPARE:Lorg/apache/hadoop/hbase/shaded/protobuf/generated/MasterProcedureProtos$SplitTableRegionState;
       3: areturn

  protected void serializeStateData(org.apache.hadoop.hbase.procedure2.ProcedureStateSerializer) throws java.io.IOException;
    Code:
       0: aload_0
       1: aload_1
       2: invokespecial #146                // Method org/apache/hadoop/hbase/master/procedure/AbstractStateMachineRegionProcedure.serializeStateData:(Lorg/apache/hadoop/hbase/procedure2/ProcedureStateSerializer;)V
       5: invokestatic  #147                // Method org/apache/hadoop/hbase/shaded/protobuf/generated/MasterProcedureProtos$SplitTableRegionStateData.newBuilder:()Lorg/apache/hadoop/hbase/shaded/protobuf/generated/MasterProcedureProtos$SplitTableRegionStateData$Builder;
       8: aload_0
       9: invokevirtual #148                // Method getUser:()Lorg/apache/hadoop/hbase/security/User;
      12: invokestatic  #149                // Method org/apache/hadoop/hbase/master/procedure/MasterProcedureUtil.toProtoUserInfo:(Lorg/apache/hadoop/hbase/security/User;)Lorg/apache/hadoop/hbase/shaded/protobuf/generated/RPCProtos$UserInformation;
      15: invokevirtual #150                // Method org/apache/hadoop/hbase/shaded/protobuf/generated/MasterProcedureProtos$SplitTableRegionStateData$Builder.setUserInfo:(Lorg/apache/hadoop/hbase/shaded/protobuf/generated/RPCProtos$UserInformation;)Lorg/apache/hadoop/hbase/shaded/protobuf/generated/MasterProcedureProtos$SplitTableRegionStateData$Builder;
      18: aload_0
      19: invokevirtual #151                // Method getRegion:()Lorg/apache/hadoop/hbase/client/RegionInfo;
      22: invokestatic  #152                // Method org/apache/hadoop/hbase/shaded/protobuf/ProtobufUtil.toRegionInfo:(Lorg/apache/hadoop/hbase/client/RegionInfo;)Lorg/apache/hadoop/hbase/shaded/protobuf/generated/HBaseProtos$RegionInfo;
      25: invokevirtual #153                // Method org/apache/hadoop/hbase/shaded/protobuf/generated/MasterProcedureProtos$SplitTableRegionStateData$Builder.setParentRegionInfo:(Lorg/apache/hadoop/hbase/shaded/protobuf/generated/HBaseProtos$RegionInfo;)Lorg/apache/hadoop/hbase/shaded/protobuf/generated/MasterProcedureProtos$SplitTableRegionStateData$Builder;
      28: aload_0
      29: getfield      #19                 // Field daughterOneRI:Lorg/apache/hadoop/hbase/client/RegionInfo;
      32: invokestatic  #152                // Method org/apache/hadoop/hbase/shaded/protobuf/ProtobufUtil.toRegionInfo:(Lorg/apache/hadoop/hbase/client/RegionInfo;)Lorg/apache/hadoop/hbase/shaded/protobuf/generated/HBaseProtos$RegionInfo;
      35: invokevirtual #154                // Method org/apache/hadoop/hbase/shaded/protobuf/generated/MasterProcedureProtos$SplitTableRegionStateData$Builder.addChildRegionInfo:(Lorg/apache/hadoop/hbase/shaded/protobuf/generated/HBaseProtos$RegionInfo;)Lorg/apache/hadoop/hbase/shaded/protobuf/generated/MasterProcedureProtos$SplitTableRegionStateData$Builder;
      38: aload_0
      39: getfield      #21                 // Field daughterTwoRI:Lorg/apache/hadoop/hbase/client/RegionInfo;
      42: invokestatic  #152                // Method org/apache/hadoop/hbase/shaded/protobuf/ProtobufUtil.toRegionInfo:(Lorg/apache/hadoop/hbase/client/RegionInfo;)Lorg/apache/hadoop/hbase/shaded/protobuf/generated/HBaseProtos$RegionInfo;
      45: invokevirtual #154                // Method org/apache/hadoop/hbase/shaded/protobuf/generated/MasterProcedureProtos$SplitTableRegionStateData$Builder.addChildRegionInfo:(Lorg/apache/hadoop/hbase/shaded/protobuf/generated/HBaseProtos$RegionInfo;)Lorg/apache/hadoop/hbase/shaded/protobuf/generated/MasterProcedureProtos$SplitTableRegionStateData$Builder;
      48: astore_2
      49: aload_1
      50: aload_2
      51: invokevirtual #155                // Method org/apache/hadoop/hbase/shaded/protobuf/generated/MasterProcedureProtos$SplitTableRegionStateData$Builder.build:()Lorg/apache/hadoop/hbase/shaded/protobuf/generated/MasterProcedureProtos$SplitTableRegionStateData;
      54: invokeinterface #156,  2          // InterfaceMethod org/apache/hadoop/hbase/procedure2/ProcedureStateSerializer.serialize:(Lorg/apache/hbase/thirdparty/com/google/protobuf/Message;)V
      59: return

  protected void deserializeStateData(org.apache.hadoop.hbase.procedure2.ProcedureStateSerializer) throws java.io.IOException;
    Code:
       0: aload_0
       1: aload_1
       2: invokespecial #157                // Method org/apache/hadoop/hbase/master/procedure/AbstractStateMachineRegionProcedure.deserializeStateData:(Lorg/apache/hadoop/hbase/procedure2/ProcedureStateSerializer;)V
       5: aload_1
       6: ldc           #158                // class org/apache/hadoop/hbase/shaded/protobuf/generated/MasterProcedureProtos$SplitTableRegionStateData
       8: invokeinterface #159,  2          // InterfaceMethod org/apache/hadoop/hbase/procedure2/ProcedureStateSerializer.deserialize:(Ljava/lang/Class;)Lorg/apache/hbase/thirdparty/com/google/protobuf/Message;
      13: checkcast     #158                // class org/apache/hadoop/hbase/shaded/protobuf/generated/MasterProcedureProtos$SplitTableRegionStateData
      16: astore_2
      17: aload_0
      18: aload_2
      19: invokevirtual #160                // Method org/apache/hadoop/hbase/shaded/protobuf/generated/MasterProcedureProtos$SplitTableRegionStateData.getUserInfo:()Lorg/apache/hadoop/hbase/shaded/protobuf/generated/RPCProtos$UserInformation;
      22: invokestatic  #161                // Method org/apache/hadoop/hbase/master/procedure/MasterProcedureUtil.toUserInfo:(Lorg/apache/hadoop/hbase/shaded/protobuf/generated/RPCProtos$UserInformation;)Lorg/apache/hadoop/hbase/security/User;
      25: invokevirtual #162                // Method setUser:(Lorg/apache/hadoop/hbase/security/User;)V
      28: aload_0
      29: aload_2
      30: invokevirtual #163                // Method org/apache/hadoop/hbase/shaded/protobuf/generated/MasterProcedureProtos$SplitTableRegionStateData.getParentRegionInfo:()Lorg/apache/hadoop/hbase/shaded/protobuf/generated/HBaseProtos$RegionInfo;
      33: invokestatic  #164                // Method org/apache/hadoop/hbase/shaded/protobuf/ProtobufUtil.toRegionInfo:(Lorg/apache/hadoop/hbase/shaded/protobuf/generated/HBaseProtos$RegionInfo;)Lorg/apache/hadoop/hbase/client/RegionInfo;
      36: invokevirtual #165                // Method setRegion:(Lorg/apache/hadoop/hbase/client/RegionInfo;)V
      39: getstatic     #166                // Field $assertionsDisabled:Z
      42: ifne          61
      45: aload_2
      46: invokevirtual #167                // Method org/apache/hadoop/hbase/shaded/protobuf/generated/MasterProcedureProtos$SplitTableRegionStateData.getChildRegionInfoCount:()I
      49: iconst_2
      50: if_icmpeq     61
      53: new           #168                // class java/lang/AssertionError
      56: dup
      57: invokespecial #169                // Method java/lang/AssertionError."<init>":()V
      60: athrow
      61: aload_0
      62: aload_2
      63: iconst_0
      64: invokevirtual #170                // Method org/apache/hadoop/hbase/shaded/protobuf/generated/MasterProcedureProtos$SplitTableRegionStateData.getChildRegionInfo:(I)Lorg/apache/hadoop/hbase/shaded/protobuf/generated/HBaseProtos$RegionInfo;
      67: invokestatic  #164                // Method org/apache/hadoop/hbase/shaded/protobuf/ProtobufUtil.toRegionInfo:(Lorg/apache/hadoop/hbase/shaded/protobuf/generated/HBaseProtos$RegionInfo;)Lorg/apache/hadoop/hbase/client/RegionInfo;
      70: putfield      #19                 // Field daughterOneRI:Lorg/apache/hadoop/hbase/client/RegionInfo;
      73: aload_0
      74: aload_2
      75: iconst_1
      76: invokevirtual #170                // Method org/apache/hadoop/hbase/shaded/protobuf/generated/MasterProcedureProtos$SplitTableRegionStateData.getChildRegionInfo:(I)Lorg/apache/hadoop/hbase/shaded/protobuf/generated/HBaseProtos$RegionInfo;
      79: invokestatic  #164                // Method org/apache/hadoop/hbase/shaded/protobuf/ProtobufUtil.toRegionInfo:(Lorg/apache/hadoop/hbase/shaded/protobuf/generated/HBaseProtos$RegionInfo;)Lorg/apache/hadoop/hbase/client/RegionInfo;
      82: putfield      #21                 // Field daughterTwoRI:Lorg/apache/hadoop/hbase/client/RegionInfo;
      85: return

  public void toStringClassDetails(java.lang.StringBuilder);
    Code:
       0: aload_1
       1: aload_0
       2: invokevirtual #171                // Method java/lang/Object.getClass:()Ljava/lang/Class;
       5: invokevirtual #172                // Method java/lang/Class.getSimpleName:()Ljava/lang/String;
       8: invokevirtual #42                 // Method java/lang/StringBuilder.append:(Ljava/lang/String;)Ljava/lang/StringBuilder;
      11: pop
      12: aload_1
      13: ldc           #173                // String  table=
      15: invokevirtual #42                 // Method java/lang/StringBuilder.append:(Ljava/lang/String;)Ljava/lang/StringBuilder;
      18: pop
      19: aload_1
      20: aload_0
      21: invokevirtual #24                 // Method getTableName:()Lorg/apache/hadoop/hbase/TableName;
      24: invokevirtual #40                 // Method java/lang/StringBuilder.append:(Ljava/lang/Object;)Ljava/lang/StringBuilder;
      27: pop
      28: aload_1
      29: ldc           #174                // String , parent=
      31: invokevirtual #42                 // Method java/lang/StringBuilder.append:(Ljava/lang/String;)Ljava/lang/StringBuilder;
      34: pop
      35: aload_1
      36: aload_0
      37: invokespecial #34                 // Method getParentRegion:()Lorg/apache/hadoop/hbase/client/RegionInfo;
      40: invokeinterface #71,  1           // InterfaceMethod org/apache/hadoop/hbase/client/RegionInfo.getShortNameToLog:()Ljava/lang/String;
      45: invokevirtual #42                 // Method java/lang/StringBuilder.append:(Ljava/lang/String;)Ljava/lang/StringBuilder;
      48: pop
      49: aload_1
      50: ldc           #175                // String , daughterA=
      52: invokevirtual #42                 // Method java/lang/StringBuilder.append:(Ljava/lang/String;)Ljava/lang/StringBuilder;
      55: pop
      56: aload_1
      57: aload_0
      58: getfield      #19                 // Field daughterOneRI:Lorg/apache/hadoop/hbase/client/RegionInfo;
      61: invokeinterface #71,  1           // InterfaceMethod org/apache/hadoop/hbase/client/RegionInfo.getShortNameToLog:()Ljava/lang/String;
      66: invokevirtual #42                 // Method java/lang/StringBuilder.append:(Ljava/lang/String;)Ljava/lang/StringBuilder;
      69: pop
      70: aload_1
      71: ldc           #176                // String , daughterB=
      73: invokevirtual #42                 // Method java/lang/StringBuilder.append:(Ljava/lang/String;)Ljava/lang/StringBuilder;
      76: pop
      77: aload_1
      78: aload_0
      79: getfield      #21                 // Field daughterTwoRI:Lorg/apache/hadoop/hbase/client/RegionInfo;
      82: invokeinterface #71,  1           // InterfaceMethod org/apache/hadoop/hbase/client/RegionInfo.getShortNameToLog:()Ljava/lang/String;
      87: invokevirtual #42                 // Method java/lang/StringBuilder.append:(Ljava/lang/String;)Ljava/lang/StringBuilder;
      90: pop
      91: return

  public org.apache.hadoop.hbase.master.procedure.TableProcedureInterface$TableOperationType getTableOperationType();
    Code:
       0: getstatic     #177                // Field org/apache/hadoop/hbase/master/procedure/TableProcedureInterface$TableOperationType.REGION_SPLIT:Lorg/apache/hadoop/hbase/master/procedure/TableProcedureInterface$TableOperationType;
       3: areturn

  protected org.apache.hadoop.hbase.procedure2.ProcedureMetrics getProcedureMetrics(org.apache.hadoop.hbase.master.procedure.MasterProcedureEnv);
    Code:
       0: aload_1
       1: invokevirtual #53                 // Method org/apache/hadoop/hbase/master/procedure/MasterProcedureEnv.getAssignmentManager:()Lorg/apache/hadoop/hbase/master/assignment/AssignmentManager;
       4: invokevirtual #178                // Method org/apache/hadoop/hbase/master/assignment/AssignmentManager.getAssignmentManagerMetrics:()Lorg/apache/hadoop/hbase/master/MetricsAssignmentManager;
       7: invokevirtual #179                // Method org/apache/hadoop/hbase/master/MetricsAssignmentManager.getSplitProcMetrics:()Lorg/apache/hadoop/hbase/procedure2/ProcedureMetrics;
      10: areturn

  public boolean prepareSplitRegion(org.apache.hadoop.hbase.master.procedure.MasterProcedureEnv) throws java.io.IOException;
    Code:
       0: aload_1
       1: invokevirtual #22                 // Method org/apache/hadoop/hbase/master/procedure/MasterProcedureEnv.getMasterServices:()Lorg/apache/hadoop/hbase/master/MasterServices;
       4: invokeinterface #180,  1          // InterfaceMethod org/apache/hadoop/hbase/master/MasterServices.getSnapshotManager:()Lorg/apache/hadoop/hbase/master/snapshot/SnapshotManager;
       9: aload_0
      10: invokespecial #34                 // Method getParentRegion:()Lorg/apache/hadoop/hbase/client/RegionInfo;
      13: invokeinterface #10,  1           // InterfaceMethod org/apache/hadoop/hbase/client/RegionInfo.getTable:()Lorg/apache/hadoop/hbase/TableName;
      18: invokevirtual #181                // Method org/apache/hadoop/hbase/master/snapshot/SnapshotManager.isTakingSnapshot:(Lorg/apache/hadoop/hbase/TableName;)Z
      21: ifeq          81
      24: aload_0
      25: new           #46                 // class java/io/IOException
      28: dup
      29: new           #37                 // class java/lang/StringBuilder
      32: dup
      33: invokespecial #38                 // Method java/lang/StringBuilder."<init>":()V
      36: ldc           #182                // String Skip splitting region
      38: invokevirtual #42                 // Method java/lang/StringBuilder.append:(Ljava/lang/String;)Ljava/lang/StringBuilder;
      41: aload_0
      42: invokespecial #34                 // Method getParentRegion:()Lorg/apache/hadoop/hbase/client/RegionInfo;
      45: invokeinterface #71,  1           // InterfaceMethod org/apache/hadoop/hbase/client/RegionInfo.getShortNameToLog:()Ljava/lang/String;
      50: invokevirtual #42                 // Method java/lang/StringBuilder.append:(Ljava/lang/String;)Ljava/lang/StringBuilder;
      53: ldc           #183                // String , because we are taking snapshot for the table
      55: invokevirtual #42                 // Method java/lang/StringBuilder.append:(Ljava/lang/String;)Ljava/lang/StringBuilder;
      58: aload_0
      59: invokespecial #34                 // Method getParentRegion:()Lorg/apache/hadoop/hbase/client/RegionInfo;
      62: invokeinterface #10,  1           // InterfaceMethod org/apache/hadoop/hbase/client/RegionInfo.getTable:()Lorg/apache/hadoop/hbase/TableName;
      67: invokevirtual #40                 // Method java/lang/StringBuilder.append:(Ljava/lang/Object;)Ljava/lang/StringBuilder;
      70: invokevirtual #44                 // Method java/lang/StringBuilder.toString:()Ljava/lang/String;
      73: invokespecial #184                // Method java/io/IOException."<init>":(Ljava/lang/String;)V
      76: invokevirtual #185                // Method setFailure:(Ljava/lang/Throwable;)V
      79: iconst_0
      80: ireturn
      81: aload_1
      82: invokevirtual #53                 // Method org/apache/hadoop/hbase/master/procedure/MasterProcedureEnv.getAssignmentManager:()Lorg/apache/hadoop/hbase/master/assignment/AssignmentManager;
      85: invokevirtual #54                 // Method org/apache/hadoop/hbase/master/assignment/AssignmentManager.getRegionStates:()Lorg/apache/hadoop/hbase/master/assignment/RegionStates;
      88: aload_0
      89: invokespecial #34                 // Method getParentRegion:()Lorg/apache/hadoop/hbase/client/RegionInfo;
      92: invokevirtual #55                 // Method org/apache/hadoop/hbase/master/assignment/RegionStates.getRegionStateNode:(Lorg/apache/hadoop/hbase/client/RegionInfo;)Lorg/apache/hadoop/hbase/master/assignment/RegionStateNode;
      95: astore_2
      96: aload_2
      97: ifnonnull     117
     100: new           #186                // class org/apache/hadoop/hbase/UnknownRegionException
     103: dup
     104: aload_0
     105: invokespecial #34                 // Method getParentRegion:()Lorg/apache/hadoop/hbase/client/RegionInfo;
     108: invokeinterface #187,  1          // InterfaceMethod org/apache/hadoop/hbase/client/RegionInfo.getRegionNameAsString:()Ljava/lang/String;
     113: invokespecial #188                // Method org/apache/hadoop/hbase/UnknownRegionException."<init>":(Ljava/lang/String;)V
     116: athrow
     117: aload_2
     118: invokevirtual #59                 // Method org/apache/hadoop/hbase/master/assignment/RegionStateNode.getRegionInfo:()Lorg/apache/hadoop/hbase/client/RegionInfo;
     121: astore_3
     122: aload_3
     123: ifnonnull     139
     126: getstatic     #36                 // Field LOG:Lorg/slf4j/Logger;
     129: ldc           #189                // String Unsplittable; parent region is null; node={}
     131: aload_2
     132: invokeinterface #190,  3          // InterfaceMethod org/slf4j/Logger.info:(Ljava/lang/String;Ljava/lang/Object;)V
     137: iconst_0
     138: ireturn
     139: aload_2
     140: iconst_1
     141: anewarray     #191                // class org/apache/hadoop/hbase/master/RegionState$State
     144: dup
     145: iconst_0
     146: getstatic     #192                // Field org/apache/hadoop/hbase/master/RegionState$State.SPLIT:Lorg/apache/hadoop/hbase/master/RegionState$State;
     149: aastore
     150: invokevirtual #193                // Method org/apache/hadoop/hbase/master/assignment/RegionStateNode.isInState:([Lorg/apache/hadoop/hbase/master/RegionState$State;)Z
     153: ifeq          190
     156: getstatic     #36                 // Field LOG:Lorg/slf4j/Logger;
     159: new           #37                 // class java/lang/StringBuilder
     162: dup
     163: invokespecial #38                 // Method java/lang/StringBuilder."<init>":()V
     166: ldc           #194                // String Split of
     168: invokevirtual #42                 // Method java/lang/StringBuilder.append:(Ljava/lang/String;)Ljava/lang/StringBuilder;
     171: aload_3
     172: invokevirtual #40                 // Method java/lang/StringBuilder.append:(Ljava/lang/Object;)Ljava/lang/StringBuilder;
     175: ldc           #195                // String  skipped; state is already SPLIT
     177: invokevirtual #42                 // Method java/lang/StringBuilder.append:(Ljava/lang/String;)Ljava/lang/StringBuilder;
     180: invokevirtual #44                 // Method java/lang/StringBuilder.toString:()Ljava/lang/String;
     183: invokeinterface #57,  2           // InterfaceMethod org/slf4j/Logger.info:(Ljava/lang/String;)V
     188: iconst_0
     189: ireturn
     190: aload_3
     191: invokeinterface #196,  1          // InterfaceMethod org/apache/hadoop/hbase/client/RegionInfo.isSplit:()Z
     196: ifne          208
     199: aload_3
     200: invokeinterface #197,  1          // InterfaceMethod org/apache/hadoop/hbase/client/RegionInfo.isOffline:()Z
     205: ifeq          242
     208: getstatic     #36                 // Field LOG:Lorg/slf4j/Logger;
     211: new           #37                 // class java/lang/StringBuilder
     214: dup
     215: invokespecial #38                 // Method java/lang/StringBuilder."<init>":()V
     218: ldc           #194                // String Split of
     220: invokevirtual #42                 // Method java/lang/StringBuilder.append:(Ljava/lang/String;)Ljava/lang/StringBuilder;
     223: aload_3
     224: invokevirtual #40                 // Method java/lang/StringBuilder.append:(Ljava/lang/Object;)Ljava/lang/StringBuilder;
     227: ldc           #198                // String  skipped because offline/split.
     229: invokevirtual #42                 // Method java/lang/StringBuilder.append:(Ljava/lang/String;)Ljava/lang/StringBuilder;
     232: invokevirtual #44                 // Method java/lang/StringBuilder.toString:()Ljava/lang/String;
     235: invokeinterface #57,  2           // InterfaceMethod org/slf4j/Logger.info:(Ljava/lang/String;)V
     240: iconst_0
     241: ireturn
     242: aload_2
     243: getstatic     #199                // Field EXPECTED_SPLIT_STATES:[Lorg/apache/hadoop/hbase/master/RegionState$State;
     246: invokevirtual #193                // Method org/apache/hadoop/hbase/master/assignment/RegionStateNode.isInState:([Lorg/apache/hadoop/hbase/master/RegionState$State;)Z
     249: ifne          315
     252: aload_0
     253: new           #46                 // class java/io/IOException
     256: dup
     257: new           #37                 // class java/lang/StringBuilder
     260: dup
     261: invokespecial #38                 // Method java/lang/StringBuilder."<init>":()V
     264: ldc           #200                // String Split
     266: invokevirtual #42                 // Method java/lang/StringBuilder.append:(Ljava/lang/String;)Ljava/lang/StringBuilder;
     269: aload_3
     270: invokeinterface #187,  1          // InterfaceMethod org/apache/hadoop/hbase/client/RegionInfo.getRegionNameAsString:()Ljava/lang/String;
     275: invokevirtual #42                 // Method java/lang/StringBuilder.append:(Ljava/lang/String;)Ljava/lang/StringBuilder;
     278: ldc           #201                // String  FAILED because state=
     280: invokevirtual #42                 // Method java/lang/StringBuilder.append:(Ljava/lang/String;)Ljava/lang/StringBuilder;
     283: aload_2
     284: invokevirtual #202                // Method org/apache/hadoop/hbase/master/assignment/RegionStateNode.getState:()Lorg/apache/hadoop/hbase/master/RegionState$State;
     287: invokevirtual #40                 // Method java/lang/StringBuilder.append:(Ljava/lang/Object;)Ljava/lang/StringBuilder;
     290: ldc           #203                // String ; expected
     292: invokevirtual #42                 // Method java/lang/StringBuilder.append:(Ljava/lang/String;)Ljava/lang/StringBuilder;
     295: getstatic     #199                // Field EXPECTED_SPLIT_STATES:[Lorg/apache/hadoop/hbase/master/RegionState$State;
     298: invokestatic  #204                // Method java/util/Arrays.toString:([Ljava/lang/Object;)Ljava/lang/String;
     301: invokevirtual #42                 // Method java/lang/StringBuilder.append:(Ljava/lang/String;)Ljava/lang/StringBuilder;
     304: invokevirtual #44                 // Method java/lang/StringBuilder.toString:()Ljava/lang/String;
     307: invokespecial #184                // Method java/io/IOException."<init>":(Ljava/lang/String;)V
     310: invokevirtual #185                // Method setFailure:(Ljava/lang/Throwable;)V
     313: iconst_0
     314: ireturn
     315: aload_1
     316: invokevirtual #22                 // Method org/apache/hadoop/hbase/master/procedure/MasterProcedureEnv.getMasterServices:()Lorg/apache/hadoop/hbase/master/MasterServices;
     319: getstatic     #205                // Field org/apache/hadoop/hbase/client/MasterSwitchType.SPLIT:Lorg/apache/hadoop/hbase/client/MasterSwitchType;
     322: invokeinterface #206,  2          // InterfaceMethod org/apache/hadoop/hbase/master/MasterServices.isSplitOrMergeEnabled:(Lorg/apache/hadoop/hbase/client/MasterSwitchType;)Z
     327: ifne          411
     330: getstatic     #36                 // Field LOG:Lorg/slf4j/Logger;
     333: new           #37                 // class java/lang/StringBuilder
     336: dup
     337: invokespecial #38                 // Method java/lang/StringBuilder."<init>":()V
     340: ldc           #138                // String pid=
     342: invokevirtual #42                 // Method java/lang/StringBuilder.append:(Ljava/lang/String;)Ljava/lang/StringBuilder;
     345: aload_0
     346: invokevirtual #139                // Method getProcId:()J
     349: invokevirtual #85                 // Method java/lang/StringBuilder.append:(J)Ljava/lang/StringBuilder;
     352: ldc           #207                // String  split switch is off! skip split of
     354: invokevirtual #42                 // Method java/lang/StringBuilder.append:(Ljava/lang/String;)Ljava/lang/StringBuilder;
     357: aload_3
     358: invokevirtual #40                 // Method java/lang/StringBuilder.append:(Ljava/lang/Object;)Ljava/lang/StringBuilder;
     361: invokevirtual #44                 // Method java/lang/StringBuilder.toString:()Ljava/lang/String;
     364: invokeinterface #87,  2           // InterfaceMethod org/slf4j/Logger.warn:(Ljava/lang/String;)V
     369: aload_0
     370: new           #46                 // class java/io/IOException
     373: dup
     374: new           #37                 // class java/lang/StringBuilder
     377: dup
     378: invokespecial #38                 // Method java/lang/StringBuilder."<init>":()V
     381: ldc           #208                // String Split region
     383: invokevirtual #42                 // Method java/lang/StringBuilder.append:(Ljava/lang/String;)Ljava/lang/StringBuilder;
     386: aload_3
     387: invokeinterface #187,  1          // InterfaceMethod org/apache/hadoop/hbase/client/RegionInfo.getRegionNameAsString:()Ljava/lang/String;
     392: invokevirtual #42                 // Method java/lang/StringBuilder.append:(Ljava/lang/String;)Ljava/lang/StringBuilder;
     395: ldc           #209                // String  failed due to split switch off
     397: invokevirtual #42                 // Method java/lang/StringBuilder.append:(Ljava/lang/String;)Ljava/lang/StringBuilder;
     400: invokevirtual #44                 // Method java/lang/StringBuilder.toString:()Ljava/lang/String;
     403: invokespecial #184                // Method java/io/IOException."<init>":(Ljava/lang/String;)V
     406: invokevirtual #185                // Method setFailure:(Ljava/lang/Throwable;)V
     409: iconst_0
     410: ireturn
     411: aload_1
     412: invokevirtual #22                 // Method org/apache/hadoop/hbase/master/procedure/MasterProcedureEnv.getMasterServices:()Lorg/apache/hadoop/hbase/master/MasterServices;
     415: invokeinterface #23,  1           // InterfaceMethod org/apache/hadoop/hbase/master/MasterServices.getTableDescriptors:()Lorg/apache/hadoop/hbase/TableDescriptors;
     420: aload_0
     421: invokevirtual #24                 // Method getTableName:()Lorg/apache/hadoop/hbase/TableName;
     424: invokeinterface #25,  2           // InterfaceMethod org/apache/hadoop/hbase/TableDescriptors.get:(Lorg/apache/hadoop/hbase/TableName;)Lorg/apache/hadoop/hbase/client/TableDescriptor;
     429: invokeinterface #210,  1          // InterfaceMethod org/apache/hadoop/hbase/client/TableDescriptor.isSplitEnabled:()Z
     434: ifne          497
     437: getstatic     #36                 // Field LOG:Lorg/slf4j/Logger;
     440: ldc           #211                // String pid={}, split is disabled for the table! Skipping split of {}
     442: aload_0
     443: invokevirtual #139                // Method getProcId:()J
     446: invokestatic  #212                // Method java/lang/Long.valueOf:(J)Ljava/lang/Long;
     449: aload_3
     450: invokeinterface #213,  4          // InterfaceMethod org/slf4j/Logger.warn:(Ljava/lang/String;Ljava/lang/Object;Ljava/lang/Object;)V
     455: aload_0
     456: new           #46                 // class java/io/IOException
     459: dup
     460: new           #37                 // class java/lang/StringBuilder
     463: dup
     464: invokespecial #38                 // Method java/lang/StringBuilder."<init>":()V
     467: ldc           #208                // String Split region
     469: invokevirtual #42                 // Method java/lang/StringBuilder.append:(Ljava/lang/String;)Ljava/lang/StringBuilder;
     472: aload_3
     473: invokeinterface #187,  1          // InterfaceMethod org/apache/hadoop/hbase/client/RegionInfo.getRegionNameAsString:()Ljava/lang/String;
     478: invokevirtual #42                 // Method java/lang/StringBuilder.append:(Ljava/lang/String;)Ljava/lang/StringBuilder;
     481: ldc           #214                // String  failed as region split is disabled for the table
     483: invokevirtual #42                 // Method java/lang/StringBuilder.append:(Ljava/lang/String;)Ljava/lang/StringBuilder;
     486: invokevirtual #44                 // Method java/lang/StringBuilder.toString:()Ljava/lang/String;
     489: invokespecial #184                // Method java/io/IOException."<init>":(Ljava/lang/String;)V
     492: invokevirtual #185                // Method setFailure:(Ljava/lang/Throwable;)V
     495: iconst_0
     496: ireturn
     497: aload_2
     498: getstatic     #215                // Field org/apache/hadoop/hbase/master/RegionState$State.SPLITTING:Lorg/apache/hadoop/hbase/master/RegionState$State;
     501: iconst_0
     502: anewarray     #191                // class org/apache/hadoop/hbase/master/RegionState$State
     505: invokevirtual #216                // Method org/apache/hadoop/hbase/master/assignment/RegionStateNode.setState:(Lorg/apache/hadoop/hbase/master/RegionState$State;[Lorg/apache/hadoop/hbase/master/RegionState$State;)Z
     508: pop
     509: iconst_1
     510: ireturn

  public void createDaughterRegions(org.apache.hadoop.hbase.master.procedure.MasterProcedureEnv) throws java.io.IOException;
    Code:
       0: aload_1
       1: invokevirtual #22                 // Method org/apache/hadoop/hbase/master/procedure/MasterProcedureEnv.getMasterServices:()Lorg/apache/hadoop/hbase/master/MasterServices;
       4: invokeinterface #230,  1          // InterfaceMethod org/apache/hadoop/hbase/master/MasterServices.getMasterFileSystem:()Lorg/apache/hadoop/hbase/master/MasterFileSystem;
       9: astore_2
      10: aload_2
      11: invokevirtual #231                // Method org/apache/hadoop/hbase/master/MasterFileSystem.getRootDir:()Lorg/apache/hadoop/fs/Path;
      14: aload_0
      15: invokevirtual #24                 // Method getTableName:()Lorg/apache/hadoop/hbase/TableName;
      18: invokestatic  #232                // Method org/apache/hadoop/hbase/util/FSUtils.getTableDir:(Lorg/apache/hadoop/fs/Path;Lorg/apache/hadoop/hbase/TableName;)Lorg/apache/hadoop/fs/Path;
      21: astore_3
      22: aload_2
      23: invokevirtual #233                // Method org/apache/hadoop/hbase/master/MasterFileSystem.getFileSystem:()Lorg/apache/hadoop/fs/FileSystem;
      26: astore        4
      28: aload_1
      29: invokevirtual #27                 // Method org/apache/hadoop/hbase/master/procedure/MasterProcedureEnv.getMasterConfiguration:()Lorg/apache/hadoop/conf/Configuration;
      32: aload         4
      34: aload_3
      35: aload_0
      36: invokespecial #34                 // Method getParentRegion:()Lorg/apache/hadoop/hbase/client/RegionInfo;
      39: iconst_0
      40: invokestatic  #234                // Method org/apache/hadoop/hbase/regionserver/HRegionFileSystem.openRegionFromFileSystem:(Lorg/apache/hadoop/conf/Configuration;Lorg/apache/hadoop/fs/FileSystem;Lorg/apache/hadoop/fs/Path;Lorg/apache/hadoop/hbase/client/RegionInfo;Z)Lorg/apache/hadoop/hbase/regionserver/HRegionFileSystem;
      43: astore        5
      45: aload         5
      47: invokevirtual #235                // Method org/apache/hadoop/hbase/regionserver/HRegionFileSystem.createSplitsDir:()V
      50: aload_0
      51: aload_1
      52: aload         5
      54: invokespecial #236                // Method splitStoreFiles:(Lorg/apache/hadoop/hbase/master/procedure/MasterProcedureEnv;Lorg/apache/hadoop/hbase/regionserver/HRegionFileSystem;)Lorg/apache/hadoop/hbase/util/Pair;
      57: astore        6
      59: aload_0
      60: aload         4
      62: aload         6
      64: invokevirtual #237                // Method org/apache/hadoop/hbase/util/Pair.getFirst:()Ljava/lang/Object;
      67: checkcast     #238                // class java/lang/Integer
      70: invokevirtual #239                // Method java/lang/Integer.intValue:()I
      73: aload         5
      75: aload_0
      76: getfield      #19                 // Field daughterOneRI:Lorg/apache/hadoop/hbase/client/RegionInfo;
      79: invokevirtual #240                // Method org/apache/hadoop/hbase/regionserver/HRegionFileSystem.getSplitsDir:(Lorg/apache/hadoop/hbase/client/RegionInfo;)Lorg/apache/hadoop/fs/Path;
      82: invokespecial #241                // Method assertReferenceFileCount:(Lorg/apache/hadoop/fs/FileSystem;ILorg/apache/hadoop/fs/Path;)V
      85: aload         5
      87: aload_0
      88: getfield      #19                 // Field daughterOneRI:Lorg/apache/hadoop/hbase/client/RegionInfo;
      91: invokevirtual #242                // Method org/apache/hadoop/hbase/regionserver/HRegionFileSystem.commitDaughterRegion:(Lorg/apache/hadoop/hbase/client/RegionInfo;)Lorg/apache/hadoop/fs/Path;
      94: pop
      95: aload_0
      96: aload         4
      98: aload         6
     100: invokevirtual #237                // Method org/apache/hadoop/hbase/util/Pair.getFirst:()Ljava/lang/Object;
     103: checkcast     #238                // class java/lang/Integer
     106: invokevirtual #239                // Method java/lang/Integer.intValue:()I
     109: new           #243                // class org/apache/hadoop/fs/Path
     112: dup
     113: aload_3
     114: aload_0
     115: getfield      #19                 // Field daughterOneRI:Lorg/apache/hadoop/hbase/client/RegionInfo;
     118: invokeinterface #125,  1          // InterfaceMethod org/apache/hadoop/hbase/client/RegionInfo.getEncodedName:()Ljava/lang/String;
     123: invokespecial #244                // Method org/apache/hadoop/fs/Path."<init>":(Lorg/apache/hadoop/fs/Path;Ljava/lang/String;)V
     126: invokespecial #241                // Method assertReferenceFileCount:(Lorg/apache/hadoop/fs/FileSystem;ILorg/apache/hadoop/fs/Path;)V
     129: aload_0
     130: aload         4
     132: aload         6
     134: invokevirtual #245                // Method org/apache/hadoop/hbase/util/Pair.getSecond:()Ljava/lang/Object;
     137: checkcast     #238                // class java/lang/Integer
     140: invokevirtual #239                // Method java/lang/Integer.intValue:()I
     143: aload         5
     145: aload_0
     146: getfield      #21                 // Field daughterTwoRI:Lorg/apache/hadoop/hbase/client/RegionInfo;
     149: invokevirtual #240                // Method org/apache/hadoop/hbase/regionserver/HRegionFileSystem.getSplitsDir:(Lorg/apache/hadoop/hbase/client/RegionInfo;)Lorg/apache/hadoop/fs/Path;
     152: invokespecial #241                // Method assertReferenceFileCount:(Lorg/apache/hadoop/fs/FileSystem;ILorg/apache/hadoop/fs/Path;)V
     155: aload         5
     157: aload_0
     158: getfield      #21                 // Field daughterTwoRI:Lorg/apache/hadoop/hbase/client/RegionInfo;
     161: invokevirtual #242                // Method org/apache/hadoop/hbase/regionserver/HRegionFileSystem.commitDaughterRegion:(Lorg/apache/hadoop/hbase/client/RegionInfo;)Lorg/apache/hadoop/fs/Path;
     164: pop
     165: aload_0
     166: aload         4
     168: aload         6
     170: invokevirtual #245                // Method org/apache/hadoop/hbase/util/Pair.getSecond:()Ljava/lang/Object;
     173: checkcast     #238                // class java/lang/Integer
     176: invokevirtual #239                // Method java/lang/Integer.intValue:()I
     179: new           #243                // class org/apache/hadoop/fs/Path
     182: dup
     183: aload_3
     184: aload_0
     185: getfield      #21                 // Field daughterTwoRI:Lorg/apache/hadoop/hbase/client/RegionInfo;
     188: invokeinterface #125,  1          // InterfaceMethod org/apache/hadoop/hbase/client/RegionInfo.getEncodedName:()Ljava/lang/String;
     193: invokespecial #244                // Method org/apache/hadoop/fs/Path."<init>":(Lorg/apache/hadoop/fs/Path;Ljava/lang/String;)V
     196: invokespecial #241                // Method assertReferenceFileCount:(Lorg/apache/hadoop/fs/FileSystem;ILorg/apache/hadoop/fs/Path;)V
     199: return

  protected boolean abort(org.apache.hadoop.hbase.master.procedure.MasterProcedureEnv);
    Code:
       0: aload_0
       1: aload_0
       2: invokevirtual #352                // Method getCurrentState:()Ljava/lang/Object;
       5: checkcast     #353                // class org/apache/hadoop/hbase/shaded/protobuf/generated/MasterProcedureProtos$SplitTableRegionState
       8: invokevirtual #127                // Method isRollbackSupported:(Lorg/apache/hadoop/hbase/shaded/protobuf/generated/MasterProcedureProtos$SplitTableRegionState;)Z
      11: ifeq          22
      14: aload_0
      15: aload_1
      16: invokespecial #354                // Method org/apache/hadoop/hbase/master/procedure/AbstractStateMachineRegionProcedure.abort:(Ljava/lang/Object;)Z
      19: goto          23
      22: iconst_0
      23: ireturn

  protected boolean isRollbackSupported(java.lang.Object);
    Code:
       0: aload_0
       1: aload_1
       2: checkcast     #353                // class org/apache/hadoop/hbase/shaded/protobuf/generated/MasterProcedureProtos$SplitTableRegionState
       5: invokevirtual #127                // Method isRollbackSupported:(Lorg/apache/hadoop/hbase/shaded/protobuf/generated/MasterProcedureProtos$SplitTableRegionState;)Z
       8: ireturn

  protected boolean abort(java.lang.Object);
    Code:
       0: aload_0
       1: aload_1
       2: checkcast     #355                // class org/apache/hadoop/hbase/master/procedure/MasterProcedureEnv
       5: invokevirtual #356                // Method abort:(Lorg/apache/hadoop/hbase/master/procedure/MasterProcedureEnv;)Z
       8: ireturn

  protected java.lang.Object getInitialState();
    Code:
       0: aload_0
       1: invokevirtual #357                // Method getInitialState:()Lorg/apache/hadoop/hbase/shaded/protobuf/generated/MasterProcedureProtos$SplitTableRegionState;
       4: areturn

  protected int getStateId(java.lang.Object);
    Code:
       0: aload_0
       1: aload_1
       2: checkcast     #353                // class org/apache/hadoop/hbase/shaded/protobuf/generated/MasterProcedureProtos$SplitTableRegionState
       5: invokevirtual #358                // Method getStateId:(Lorg/apache/hadoop/hbase/shaded/protobuf/generated/MasterProcedureProtos$SplitTableRegionState;)I
       8: ireturn

  protected java.lang.Object getState(int);
    Code:
       0: aload_0
       1: iload_1
       2: invokevirtual #359                // Method getState:(I)Lorg/apache/hadoop/hbase/shaded/protobuf/generated/MasterProcedureProtos$SplitTableRegionState;
       5: areturn

  protected void rollbackState(java.lang.Object, java.lang.Object) throws java.io.IOException, java.lang.InterruptedException;
    Code:
       0: aload_0
       1: aload_1
       2: checkcast     #355                // class org/apache/hadoop/hbase/master/procedure/MasterProcedureEnv
       5: aload_2
       6: checkcast     #353                // class org/apache/hadoop/hbase/shaded/protobuf/generated/MasterProcedureProtos$SplitTableRegionState
       9: invokevirtual #360                // Method rollbackState:(Lorg/apache/hadoop/hbase/master/procedure/MasterProcedureEnv;Lorg/apache/hadoop/hbase/shaded/protobuf/generated/MasterProcedureProtos$SplitTableRegionState;)V
      12: return

  protected org.apache.hadoop.hbase.procedure2.StateMachineProcedure$Flow executeFromState(java.lang.Object, java.lang.Object) throws org.apache.hadoop.hbase.procedure2.ProcedureSuspendedException, org.apache.hadoop.hbase.procedure2.ProcedureYieldException, java.lang.InterruptedException;
    Code:
       0: aload_0
       1: aload_1
       2: checkcast     #355                // class org/apache/hadoop/hbase/master/procedure/MasterProcedureEnv
       5: aload_2
       6: checkcast     #353                // class org/apache/hadoop/hbase/shaded/protobuf/generated/MasterProcedureProtos$SplitTableRegionState
       9: invokevirtual #361                // Method executeFromState:(Lorg/apache/hadoop/hbase/master/procedure/MasterProcedureEnv;Lorg/apache/hadoop/hbase/shaded/protobuf/generated/MasterProcedureProtos$SplitTableRegionState;)Lorg/apache/hadoop/hbase/procedure2/StateMachineProcedure$Flow;
      12: areturn

  protected org.apache.hadoop.hbase.procedure2.ProcedureMetrics getProcedureMetrics(java.lang.Object);
    Code:
       0: aload_0
       1: aload_1
       2: checkcast     #355                // class org/apache/hadoop/hbase/master/procedure/MasterProcedureEnv
       5: invokevirtual #362                // Method getProcedureMetrics:(Lorg/apache/hadoop/hbase/master/procedure/MasterProcedureEnv;)Lorg/apache/hadoop/hbase/procedure2/ProcedureMetrics;
       8: areturn

  protected void releaseLock(java.lang.Object);
    Code:
       0: aload_0
       1: aload_1
       2: checkcast     #355                // class org/apache/hadoop/hbase/master/procedure/MasterProcedureEnv
       5: invokevirtual #363                // Method releaseLock:(Lorg/apache/hadoop/hbase/master/procedure/MasterProcedureEnv;)V
       8: return

  protected org.apache.hadoop.hbase.procedure2.Procedure$LockState acquireLock(java.lang.Object);
    Code:
       0: aload_0
       1: aload_1
       2: checkcast     #355                // class org/apache/hadoop/hbase/master/procedure/MasterProcedureEnv
       5: invokevirtual #364                // Method acquireLock:(Lorg/apache/hadoop/hbase/master/procedure/MasterProcedureEnv;)Lorg/apache/hadoop/hbase/procedure2/Procedure$LockState;
       8: areturn

  static org.apache.hadoop.hbase.util.Pair access$000(org.apache.hadoop.hbase.master.assignment.SplitTableRegionProcedure, org.apache.hadoop.hbase.regionserver.HRegionFileSystem, byte[], org.apache.hadoop.hbase.regionserver.HStoreFile) throws java.io.IOException;
    Code:
       0: aload_0
       1: aload_1
       2: aload_2
       3: aload_3
       4: invokespecial #1                  // Method splitStoreFile:(Lorg/apache/hadoop/hbase/regionserver/HRegionFileSystem;[BLorg/apache/hadoop/hbase/regionserver/HStoreFile;)Lorg/apache/hadoop/hbase/util/Pair;
       7: areturn

  static {};
    Code:
       0: ldc_w         #365                // class org/apache/hadoop/hbase/master/assignment/SplitTableRegionProcedure
       3: invokevirtual #366                // Method java/lang/Class.desiredAssertionStatus:()Z
       6: ifne          13
       9: iconst_1
      10: goto          14
      13: iconst_0
      14: putstatic     #166                // Field $assertionsDisabled:Z
      17: ldc_w         #365                // class org/apache/hadoop/hbase/master/assignment/SplitTableRegionProcedure
      20: invokestatic  #367                // Method org/slf4j/LoggerFactory.getLogger:(Ljava/lang/Class;)Lorg/slf4j/Logger;
      23: putstatic     #36                 // Field LOG:Lorg/slf4j/Logger;
      26: iconst_2
      27: anewarray     #191                // class org/apache/hadoop/hbase/master/RegionState$State
      30: dup
      31: iconst_0
      32: getstatic     #368                // Field org/apache/hadoop/hbase/master/RegionState$State.OPEN:Lorg/apache/hadoop/hbase/master/RegionState$State;
      35: aastore
      36: dup
      37: iconst_1
      38: getstatic     #369                // Field org/apache/hadoop/hbase/master/RegionState$State.CLOSED:Lorg/apache/hadoop/hbase/master/RegionState$State;
      41: aastore
      42: putstatic     #199                // Field EXPECTED_SPLIT_STATES:[Lorg/apache/hadoop/hbase/master/RegionState$State;
      45: return
}
