Compiled from "SplitLogManager.java"
public class org.apache.hadoop.hbase.master.SplitLogManager$TaskBatch {
  public int installed;

  public int done;

  public int error;

  public volatile boolean isDead;

  public org.apache.hadoop.hbase.master.SplitLogManager$TaskBatch();
    Code:
       0: aload_0
       1: invokespecial #1                  // Method java/lang/Object."<init>":()V
       4: aload_0
       5: iconst_0
       6: putfield      #2                  // Field installed:I
       9: aload_0
      10: iconst_0
      11: putfield      #3                  // Field done:I
      14: aload_0
      15: iconst_0
      16: putfield      #4                  // Field error:I
      19: aload_0
      20: iconst_0
      21: putfield      #5                  // Field isDead:Z
      24: return

  public java.lang.String toString();
    Code:
       0: new           #6                  // class java/lang/StringBuilder
       3: dup
       4: invokespecial #7                  // Method java/lang/StringBuilder."<init>":()V
       7: ldc           #8                  // String installed =
       9: invokevirtual #9                  // Method java/lang/StringBuilder.append:(Ljava/lang/String;)Ljava/lang/StringBuilder;
      12: aload_0
      13: getfield      #2                  // Field installed:I
      16: invokevirtual #10                 // Method java/lang/StringBuilder.append:(I)Ljava/lang/StringBuilder;
      19: ldc           #11                 // String  done =
      21: invokevirtual #9                  // Method java/lang/StringBuilder.append:(Ljava/lang/String;)Ljava/lang/StringBuilder;
      24: aload_0
      25: getfield      #3                  // Field done:I
      28: invokevirtual #10                 // Method java/lang/StringBuilder.append:(I)Ljava/lang/StringBuilder;
      31: ldc           #12                 // String  error =
      33: invokevirtual #9                  // Method java/lang/StringBuilder.append:(Ljava/lang/String;)Ljava/lang/StringBuilder;
      36: aload_0
      37: getfield      #4                  // Field error:I
      40: invokevirtual #10                 // Method java/lang/StringBuilder.append:(I)Ljava/lang/StringBuilder;
      43: invokevirtual #13                 // Method java/lang/StringBuilder.toString:()Ljava/lang/String;
      46: areturn
}
