Compiled from "StealJobQueue.java"
class org.apache.hadoop.hbase.util.StealJobQueue$1 extends java.util.concurrent.PriorityBlockingQueue<T> {
  final org.apache.hadoop.hbase.util.StealJobQueue this$0;

  org.apache.hadoop.hbase.util.StealJobQueue$1(org.apache.hadoop.hbase.util.StealJobQueue, int, java.util.Comparator);
    Code:
       0: aload_0
       1: aload_1
       2: putfield      #1                  // Field this$0:Lorg/apache/hadoop/hbase/util/StealJobQueue;
       5: aload_0
       6: iload_2
       7: aload_3
       8: invokespecial #2                  // Method java/util/concurrent/PriorityBlockingQueue."<init>":(ILjava/util/Comparator;)V
      11: return

  public boolean offer(T);
    Code:
       0: aload_0
       1: getfield      #1                  // Field this$0:Lorg/apache/hadoop/hbase/util/StealJobQueue;
       4: invokestatic  #3                  // Method org/apache/hadoop/hbase/util/StealJobQueue.access$000:(Lorg/apache/hadoop/hbase/util/StealJobQueue;)Ljava/util/concurrent/locks/Lock;
       7: invokeinterface #4,  1            // InterfaceMethod java/util/concurrent/locks/Lock.lock:()V
      12: aload_0
      13: getfield      #1                  // Field this$0:Lorg/apache/hadoop/hbase/util/StealJobQueue;
      16: invokestatic  #5                  // Method org/apache/hadoop/hbase/util/StealJobQueue.access$100:(Lorg/apache/hadoop/hbase/util/StealJobQueue;)Ljava/util/concurrent/locks/Condition;
      19: invokeinterface #6,  1            // InterfaceMethod java/util/concurrent/locks/Condition.signal:()V
      24: aload_0
      25: aload_1
      26: invokespecial #7                  // Method java/util/concurrent/PriorityBlockingQueue.offer:(Ljava/lang/Object;)Z
      29: istore_2
      30: aload_0
      31: getfield      #1                  // Field this$0:Lorg/apache/hadoop/hbase/util/StealJobQueue;
      34: invokestatic  #3                  // Method org/apache/hadoop/hbase/util/StealJobQueue.access$000:(Lorg/apache/hadoop/hbase/util/StealJobQueue;)Ljava/util/concurrent/locks/Lock;
      37: invokeinterface #8,  1            // InterfaceMethod java/util/concurrent/locks/Lock.unlock:()V
      42: iload_2
      43: ireturn
      44: astore_3
      45: aload_0
      46: getfield      #1                  // Field this$0:Lorg/apache/hadoop/hbase/util/StealJobQueue;
      49: invokestatic  #3                  // Method org/apache/hadoop/hbase/util/StealJobQueue.access$000:(Lorg/apache/hadoop/hbase/util/StealJobQueue;)Ljava/util/concurrent/locks/Lock;
      52: invokeinterface #8,  1            // InterfaceMethod java/util/concurrent/locks/Lock.unlock:()V
      57: aload_3
      58: athrow
    Exception table:
       from    to  target type
          12    30    44   any
}
