Compiled from "StochasticLoadBalancer.java"
class org.apache.hadoop.hbase.master.balancer.StochasticLoadBalancer$RegionReplicaRackCandidateGenerator extends org.apache.hadoop.hbase.master.balancer.StochasticLoadBalancer$RegionReplicaCandidateGenerator {
  org.apache.hadoop.hbase.master.balancer.StochasticLoadBalancer$RegionReplicaRackCandidateGenerator();
    Code:
       0: aload_0
       1: invokespecial #1                  // Method org/apache/hadoop/hbase/master/balancer/StochasticLoadBalancer$RegionReplicaCandidateGenerator."<init>":()V
       4: return

  org.apache.hadoop.hbase.master.balancer.BaseLoadBalancer$Cluster$Action generate(org.apache.hadoop.hbase.master.balancer.BaseLoadBalancer$Cluster);
    Code:
       0: aload_0
       1: aload_1
       2: invokevirtual #2                  // Method pickRandomRack:(Lorg/apache/hadoop/hbase/master/balancer/BaseLoadBalancer$Cluster;)I
       5: istore_2
       6: aload_1
       7: getfield      #3                  // Field org/apache/hadoop/hbase/master/balancer/BaseLoadBalancer$Cluster.numRacks:I
      10: iconst_1
      11: if_icmple     19
      14: iload_2
      15: iconst_m1
      16: if_icmpne     25
      19: aload_0
      20: aload_1
      21: invokespecial #4                  // Method org/apache/hadoop/hbase/master/balancer/StochasticLoadBalancer$RegionReplicaCandidateGenerator.generate:(Lorg/apache/hadoop/hbase/master/balancer/BaseLoadBalancer$Cluster;)Lorg/apache/hadoop/hbase/master/balancer/BaseLoadBalancer$Cluster$Action;
      24: areturn
      25: aload_0
      26: aload_1
      27: getfield      #5                  // Field org/apache/hadoop/hbase/master/balancer/BaseLoadBalancer$Cluster.primariesOfRegionsPerRack:[[I
      30: iload_2
      31: aaload
      32: aload_1
      33: getfield      #6                  // Field org/apache/hadoop/hbase/master/balancer/BaseLoadBalancer$Cluster.regionsPerRack:[[I
      36: iload_2
      37: aaload
      38: aload_1
      39: getfield      #7                  // Field org/apache/hadoop/hbase/master/balancer/BaseLoadBalancer$Cluster.regionIndexToPrimaryIndex:[I
      42: invokevirtual #8                  // Method selectCoHostedRegionPerGroup:([I[I[I)I
      45: istore_3
      46: iload_3
      47: iconst_m1
      48: if_icmpne     60
      51: aload_0
      52: getfield      #9                  // Field randomGenerator:Lorg/apache/hadoop/hbase/master/balancer/StochasticLoadBalancer$RandomCandidateGenerator;
      55: aload_1
      56: invokevirtual #10                 // Method org/apache/hadoop/hbase/master/balancer/StochasticLoadBalancer$RandomCandidateGenerator.generate:(Lorg/apache/hadoop/hbase/master/balancer/BaseLoadBalancer$Cluster;)Lorg/apache/hadoop/hbase/master/balancer/BaseLoadBalancer$Cluster$Action;
      59: areturn
      60: aload_1
      61: getfield      #11                 // Field org/apache/hadoop/hbase/master/balancer/BaseLoadBalancer$Cluster.regionIndexToServerIndex:[I
      64: iload_3
      65: iaload
      66: istore        4
      68: aload_0
      69: aload_1
      70: iload_2
      71: invokevirtual #12                 // Method pickOtherRandomRack:(Lorg/apache/hadoop/hbase/master/balancer/BaseLoadBalancer$Cluster;I)I
      74: istore        5
      76: getstatic     #13                 // Field org/apache/hadoop/hbase/master/balancer/StochasticLoadBalancer.RANDOM:Ljava/util/Random;
      79: aload_1
      80: getfield      #14                 // Field org/apache/hadoop/hbase/master/balancer/BaseLoadBalancer$Cluster.serversPerRack:[[I
      83: iload         5
      85: aaload
      86: arraylength
      87: invokevirtual #15                 // Method java/util/Random.nextInt:(I)I
      90: istore        6
      92: aload_1
      93: getfield      #14                 // Field org/apache/hadoop/hbase/master/balancer/BaseLoadBalancer$Cluster.serversPerRack:[[I
      96: iload         5
      98: aaload
      99: iload         6
     101: iaload
     102: istore        7
     104: aload_0
     105: aload_1
     106: iload         7
     108: ldc2_w        #16                 // double 0.8999999761581421d
     111: invokevirtual #18                 // Method pickRandomRegion:(Lorg/apache/hadoop/hbase/master/balancer/BaseLoadBalancer$Cluster;ID)I
     114: istore        8
     116: aload_0
     117: iload         4
     119: iload_3
     120: iload         7
     122: iload         8
     124: invokevirtual #19                 // Method getAction:(IIII)Lorg/apache/hadoop/hbase/master/balancer/BaseLoadBalancer$Cluster$Action;
     127: areturn
}
