Compiled from "StochasticLoadBalancer.java"
class org.apache.hadoop.hbase.master.balancer.StochasticLoadBalancer$ReadRequestCostFunction extends org.apache.hadoop.hbase.master.balancer.StochasticLoadBalancer$CostFromRegionLoadAsRateFunction {
  org.apache.hadoop.hbase.master.balancer.StochasticLoadBalancer$ReadRequestCostFunction(org.apache.hadoop.conf.Configuration);
    Code:
       0: aload_0
       1: aload_1
       2: invokespecial #1                  // Method org/apache/hadoop/hbase/master/balancer/StochasticLoadBalancer$CostFromRegionLoadAsRateFunction."<init>":(Lorg/apache/hadoop/conf/Configuration;)V
       5: aload_0
       6: aload_1
       7: ldc           #3                  // String hbase.master.balancer.stochastic.readRequestCost
       9: ldc           #4                  // float 5.0f
      11: invokevirtual #5                  // Method org/apache/hadoop/conf/Configuration.getFloat:(Ljava/lang/String;F)F
      14: invokevirtual #6                  // Method setMultiplier:(F)V
      17: return

  protected double getCostFromRl(org.apache.hadoop.hbase.master.balancer.BalancerRegionLoad);
    Code:
       0: aload_1
       1: invokevirtual #7                  // Method org/apache/hadoop/hbase/master/balancer/BalancerRegionLoad.getReadRequestsCount:()J
       4: l2d
       5: dreturn
}
