Compiled from "StripeStoreFlusher.java"
public class org.apache.hadoop.hbase.regionserver.StripeStoreFlusher$StripeFlushRequest {
  protected final org.apache.hadoop.hbase.CellComparator comparator;

  public org.apache.hadoop.hbase.regionserver.StripeStoreFlusher$StripeFlushRequest(org.apache.hadoop.hbase.CellComparator);
    Code:
       0: aload_0
       1: invokespecial #1                  // Method java/lang/Object."<init>":()V
       4: aload_0
       5: aload_1
       6: putfield      #2                  // Field comparator:Lorg/apache/hadoop/hbase/CellComparator;
       9: return

  public org.apache.hadoop.hbase.regionserver.StripeMultiFileWriter createWriter() throws java.io.IOException;
    Code:
       0: new           #3                  // class org/apache/hadoop/hbase/regionserver/StripeMultiFileWriter$SizeMultiWriter
       3: dup
       4: aload_0
       5: getfield      #2                  // Field comparator:Lorg/apache/hadoop/hbase/CellComparator;
       8: iconst_1
       9: ldc2_w        #5                  // long 9223372036854775807l
      12: getstatic     #7                  // Field org/apache/hadoop/hbase/regionserver/StripeStoreFileManager.OPEN_KEY:[B
      15: getstatic     #7                  // Field org/apache/hadoop/hbase/regionserver/StripeStoreFileManager.OPEN_KEY:[B
      18: invokespecial #8                  // Method org/apache/hadoop/hbase/regionserver/StripeMultiFileWriter$SizeMultiWriter."<init>":(Lorg/apache/hadoop/hbase/CellComparator;IJ[B[B)V
      21: astore_1
      22: aload_1
      23: invokevirtual #9                  // Method org/apache/hadoop/hbase/regionserver/StripeMultiFileWriter.setNoStripeMetadata:()V
      26: aload_1
      27: areturn
}
