Compiled from "StripeMultiFileWriter.java"
public class org.apache.hadoop.hbase.regionserver.StripeMultiFileWriter$BoundaryMultiWriter extends org.apache.hadoop.hbase.regionserver.StripeMultiFileWriter {
  static final boolean $assertionsDisabled;

  public org.apache.hadoop.hbase.regionserver.StripeMultiFileWriter$BoundaryMultiWriter(org.apache.hadoop.hbase.CellComparator, java.util.List<byte[]>, byte[], byte[]) throws java.io.IOException;
    Code:
       0: aload_0
       1: aload_1
       2: invokespecial #1                  // Method org/apache/hadoop/hbase/regionserver/StripeMultiFileWriter."<init>":(Lorg/apache/hadoop/hbase/CellComparator;)V
       5: aload_0
       6: lconst_0
       7: putfield      #2                  // Field cellsInCurrentWriter:J
      10: aload_0
      11: iconst_m1
      12: putfield      #3                  // Field majorRangeFromIndex:I
      15: aload_0
      16: iconst_m1
      17: putfield      #4                  // Field majorRangeToIndex:I
      20: aload_0
      21: iconst_0
      22: putfield      #5                  // Field hasAnyWriter:Z
      25: aload_0
      26: aload_2
      27: putfield      #6                  // Field boundaries:Ljava/util/List;
      30: aload_0
      31: new           #7                  // class java/util/ArrayList
      34: dup
      35: aload_0
      36: getfield      #6                  // Field boundaries:Ljava/util/List;
      39: invokeinterface #8,  1            // InterfaceMethod java/util/List.size:()I
      44: iconst_1
      45: isub
      46: invokespecial #9                  // Method java/util/ArrayList."<init>":(I)V
      49: putfield      #10                 // Field existingWriters:Ljava/util/List;
      52: getstatic     #11                 // Field $assertionsDisabled:Z
      55: ifne          88
      58: aload_3
      59: ifnonnull     66
      62: iconst_1
      63: goto          67
      66: iconst_0
      67: aload         4
      69: ifnonnull     76
      72: iconst_1
      73: goto          77
      76: iconst_0
      77: if_icmpeq     88
      80: new           #12                 // class java/lang/AssertionError
      83: dup
      84: invokespecial #13                 // Method java/lang/AssertionError."<init>":()V
      87: athrow
      88: aload_3
      89: ifnull        241
      92: aload_0
      93: aload_3
      94: getstatic     #14                 // Field org/apache/hadoop/hbase/regionserver/StripeStoreFileManager.OPEN_KEY:[B
      97: invokestatic  #15                 // Method java/util/Arrays.equals:([B[B)Z
     100: ifeq          107
     103: iconst_0
     104: goto          118
     107: aload_0
     108: getfield      #6                  // Field boundaries:Ljava/util/List;
     111: aload_3
     112: getstatic     #16                 // Field org/apache/hadoop/hbase/util/Bytes.BYTES_COMPARATOR:Ljava/util/Comparator;
     115: invokestatic  #17                 // Method java/util/Collections.binarySearch:(Ljava/util/List;Ljava/lang/Object;Ljava/util/Comparator;)I
     118: putfield      #3                  // Field majorRangeFromIndex:I
     121: aload_0
     122: aload         4
     124: getstatic     #14                 // Field org/apache/hadoop/hbase/regionserver/StripeStoreFileManager.OPEN_KEY:[B
     127: invokestatic  #15                 // Method java/util/Arrays.equals:([B[B)Z
     130: ifeq          145
     133: aload_0
     134: getfield      #6                  // Field boundaries:Ljava/util/List;
     137: invokeinterface #8,  1            // InterfaceMethod java/util/List.size:()I
     142: goto          157
     145: aload_0
     146: getfield      #6                  // Field boundaries:Ljava/util/List;
     149: aload         4
     151: getstatic     #16                 // Field org/apache/hadoop/hbase/util/Bytes.BYTES_COMPARATOR:Ljava/util/Comparator;
     154: invokestatic  #17                 // Method java/util/Collections.binarySearch:(Ljava/util/List;Ljava/lang/Object;Ljava/util/Comparator;)I
     157: putfield      #4                  // Field majorRangeToIndex:I
     160: aload_0
     161: getfield      #3                  // Field majorRangeFromIndex:I
     164: iflt          174
     167: aload_0
     168: getfield      #4                  // Field majorRangeToIndex:I
     171: ifge          241
     174: new           #18                 // class java/io/IOException
     177: dup
     178: new           #19                 // class java/lang/StringBuilder
     181: dup
     182: invokespecial #20                 // Method java/lang/StringBuilder."<init>":()V
     185: ldc           #21                 // String Major range does not match writer boundaries: [
     187: invokevirtual #22                 // Method java/lang/StringBuilder.append:(Ljava/lang/String;)Ljava/lang/StringBuilder;
     190: aload_3
     191: invokestatic  #23                 // Method org/apache/hadoop/hbase/util/Bytes.toString:([B)Ljava/lang/String;
     194: invokevirtual #22                 // Method java/lang/StringBuilder.append:(Ljava/lang/String;)Ljava/lang/StringBuilder;
     197: ldc           #24                 // String ] [
     199: invokevirtual #22                 // Method java/lang/StringBuilder.append:(Ljava/lang/String;)Ljava/lang/StringBuilder;
     202: aload         4
     204: invokestatic  #23                 // Method org/apache/hadoop/hbase/util/Bytes.toString:([B)Ljava/lang/String;
     207: invokevirtual #22                 // Method java/lang/StringBuilder.append:(Ljava/lang/String;)Ljava/lang/StringBuilder;
     210: ldc           #25                 // String ]; from
     212: invokevirtual #22                 // Method java/lang/StringBuilder.append:(Ljava/lang/String;)Ljava/lang/StringBuilder;
     215: aload_0
     216: getfield      #3                  // Field majorRangeFromIndex:I
     219: invokevirtual #26                 // Method java/lang/StringBuilder.append:(I)Ljava/lang/StringBuilder;
     222: ldc           #27                 // String  to
     224: invokevirtual #22                 // Method java/lang/StringBuilder.append:(Ljava/lang/String;)Ljava/lang/StringBuilder;
     227: aload_0
     228: getfield      #4                  // Field majorRangeToIndex:I
     231: invokevirtual #26                 // Method java/lang/StringBuilder.append:(I)Ljava/lang/StringBuilder;
     234: invokevirtual #28                 // Method java/lang/StringBuilder.toString:()Ljava/lang/String;
     237: invokespecial #29                 // Method java/io/IOException."<init>":(Ljava/lang/String;)V
     240: athrow
     241: return

  public void append(org.apache.hadoop.hbase.Cell) throws java.io.IOException;
    Code:
       0: aload_0
       1: getfield      #30                 // Field currentWriter:Lorg/apache/hadoop/hbase/regionserver/StoreFileWriter;
       4: ifnonnull     37
       7: aload_0
       8: getfield      #10                 // Field existingWriters:Ljava/util/List;
      11: invokeinterface #31,  1           // InterfaceMethod java/util/List.isEmpty:()Z
      16: ifeq          37
      19: aload_0
      20: aload_0
      21: getfield      #6                  // Field boundaries:Ljava/util/List;
      24: iconst_0
      25: invokeinterface #32,  2           // InterfaceMethod java/util/List.get:(I)Ljava/lang/Object;
      30: checkcast     #33                 // class "[B"
      33: aload_1
      34: invokevirtual #34                 // Method sanityCheckLeft:([BLorg/apache/hadoop/hbase/Cell;)V
      37: aload_0
      38: aload_1
      39: invokespecial #35                 // Method prepareWriterFor:(Lorg/apache/hadoop/hbase/Cell;)V
      42: aload_0
      43: getfield      #30                 // Field currentWriter:Lorg/apache/hadoop/hbase/regionserver/StoreFileWriter;
      46: aload_1
      47: invokevirtual #36                 // Method org/apache/hadoop/hbase/regionserver/StoreFileWriter.append:(Lorg/apache/hadoop/hbase/Cell;)V
      50: aload_0
      51: aload_1
      52: putfield      #37                 // Field lastCell:Lorg/apache/hadoop/hbase/Cell;
      55: aload_0
      56: dup
      57: getfield      #2                  // Field cellsInCurrentWriter:J
      60: lconst_1
      61: ladd
      62: putfield      #2                  // Field cellsInCurrentWriter:J
      65: return

  protected void preCommitWritersInternal() throws java.io.IOException;
    Code:
       0: aload_0
       1: invokespecial #41                 // Method stopUsingCurrentWriter:()V
       4: aload_0
       5: getfield      #10                 // Field existingWriters:Ljava/util/List;
       8: invokeinterface #8,  1            // InterfaceMethod java/util/List.size:()I
      13: aload_0
      14: getfield      #6                  // Field boundaries:Ljava/util/List;
      17: invokeinterface #8,  1            // InterfaceMethod java/util/List.size:()I
      22: iconst_1
      23: isub
      24: if_icmpge     34
      27: aload_0
      28: invokespecial #42                 // Method createEmptyWriter:()V
      31: goto          4
      34: aload_0
      35: getfield      #37                 // Field lastCell:Lorg/apache/hadoop/hbase/Cell;
      38: ifnull        72
      41: aload_0
      42: aload_0
      43: getfield      #6                  // Field boundaries:Ljava/util/List;
      46: aload_0
      47: getfield      #6                  // Field boundaries:Ljava/util/List;
      50: invokeinterface #8,  1            // InterfaceMethod java/util/List.size:()I
      55: iconst_1
      56: isub
      57: invokeinterface #32,  2           // InterfaceMethod java/util/List.get:(I)Ljava/lang/Object;
      62: checkcast     #33                 // class "[B"
      65: aload_0
      66: getfield      #37                 // Field lastCell:Lorg/apache/hadoop/hbase/Cell;
      69: invokevirtual #43                 // Method sanityCheckRight:([BLorg/apache/hadoop/hbase/Cell;)V
      72: return

  static {};
    Code:
       0: ldc           #59                 // class org/apache/hadoop/hbase/regionserver/StripeMultiFileWriter
       2: invokevirtual #60                 // Method java/lang/Class.desiredAssertionStatus:()Z
       5: ifne          12
       8: iconst_1
       9: goto          13
      12: iconst_0
      13: putstatic     #11                 // Field $assertionsDisabled:Z
      16: return
}
