Compiled from "StripeCompactor.java"
public class org.apache.hadoop.hbase.regionserver.compactions.StripeCompactor extends org.apache.hadoop.hbase.regionserver.compactions.AbstractMultiOutputCompactor<org.apache.hadoop.hbase.regionserver.StripeMultiFileWriter> {
  static final boolean $assertionsDisabled;

  public org.apache.hadoop.hbase.regionserver.compactions.StripeCompactor(org.apache.hadoop.conf.Configuration, org.apache.hadoop.hbase.regionserver.HStore);
    Code:
       0: aload_0
       1: aload_1
       2: aload_2
       3: invokespecial #1                  // Method org/apache/hadoop/hbase/regionserver/compactions/AbstractMultiOutputCompactor."<init>":(Lorg/apache/hadoop/conf/Configuration;Lorg/apache/hadoop/hbase/regionserver/HStore;)V
       6: return

  public java.util.List<org.apache.hadoop.fs.Path> compact(org.apache.hadoop.hbase.regionserver.compactions.CompactionRequestImpl, java.util.List<byte[]>, byte[], byte[], org.apache.hadoop.hbase.regionserver.throttle.ThroughputController, org.apache.hadoop.hbase.security.User) throws java.io.IOException;
    Code:
       0: getstatic     #2                  // Field LOG:Lorg/slf4j/Logger;
       3: invokeinterface #3,  1            // InterfaceMethod org/slf4j/Logger.isDebugEnabled:()Z
       8: ifeq          122
      11: new           #4                  // class java/lang/StringBuilder
      14: dup
      15: invokespecial #5                  // Method java/lang/StringBuilder."<init>":()V
      18: astore        7
      20: aload         7
      22: new           #4                  // class java/lang/StringBuilder
      25: dup
      26: invokespecial #5                  // Method java/lang/StringBuilder."<init>":()V
      29: ldc           #6                  // String Executing compaction with
      31: invokevirtual #7                  // Method java/lang/StringBuilder.append:(Ljava/lang/String;)Ljava/lang/StringBuilder;
      34: aload_2
      35: invokeinterface #8,  1            // InterfaceMethod java/util/List.size:()I
      40: invokevirtual #9                  // Method java/lang/StringBuilder.append:(I)Ljava/lang/StringBuilder;
      43: ldc           #10                 // String  boundaries:
      45: invokevirtual #7                  // Method java/lang/StringBuilder.append:(Ljava/lang/String;)Ljava/lang/StringBuilder;
      48: invokevirtual #11                 // Method java/lang/StringBuilder.toString:()Ljava/lang/String;
      51: invokevirtual #7                  // Method java/lang/StringBuilder.append:(Ljava/lang/String;)Ljava/lang/StringBuilder;
      54: pop
      55: aload_2
      56: invokeinterface #12,  1           // InterfaceMethod java/util/List.iterator:()Ljava/util/Iterator;
      61: astore        8
      63: aload         8
      65: invokeinterface #13,  1           // InterfaceMethod java/util/Iterator.hasNext:()Z
      70: ifeq          109
      73: aload         8
      75: invokeinterface #14,  1           // InterfaceMethod java/util/Iterator.next:()Ljava/lang/Object;
      80: checkcast     #15                 // class "[B"
      83: astore        9
      85: aload         7
      87: ldc           #16                 // String  [
      89: invokevirtual #7                  // Method java/lang/StringBuilder.append:(Ljava/lang/String;)Ljava/lang/StringBuilder;
      92: aload         9
      94: invokestatic  #17                 // Method org/apache/hadoop/hbase/util/Bytes.toString:([B)Ljava/lang/String;
      97: invokevirtual #7                  // Method java/lang/StringBuilder.append:(Ljava/lang/String;)Ljava/lang/StringBuilder;
     100: ldc           #18                 // String ]
     102: invokevirtual #7                  // Method java/lang/StringBuilder.append:(Ljava/lang/String;)Ljava/lang/StringBuilder;
     105: pop
     106: goto          63
     109: getstatic     #2                  // Field LOG:Lorg/slf4j/Logger;
     112: aload         7
     114: invokevirtual #11                 // Method java/lang/StringBuilder.toString:()Ljava/lang/String;
     117: invokeinterface #19,  2           // InterfaceMethod org/slf4j/Logger.debug:(Ljava/lang/String;)V
     122: aload_0
     123: aload_1
     124: new           #20                 // class org/apache/hadoop/hbase/regionserver/compactions/StripeCompactor$StripeInternalScannerFactory
     127: dup
     128: aload_0
     129: aload_3
     130: aload         4
     132: invokespecial #21                 // Method org/apache/hadoop/hbase/regionserver/compactions/StripeCompactor$StripeInternalScannerFactory."<init>":(Lorg/apache/hadoop/hbase/regionserver/compactions/StripeCompactor;[B[B)V
     135: new           #22                 // class org/apache/hadoop/hbase/regionserver/compactions/StripeCompactor$1
     138: dup
     139: aload_0
     140: aload_2
     141: aload_3
     142: aload         4
     144: invokespecial #23                 // Method org/apache/hadoop/hbase/regionserver/compactions/StripeCompactor$1."<init>":(Lorg/apache/hadoop/hbase/regionserver/compactions/StripeCompactor;Ljava/util/List;[B[B)V
     147: aload         5
     149: aload         6
     151: invokevirtual #24                 // Method compact:(Lorg/apache/hadoop/hbase/regionserver/compactions/CompactionRequestImpl;Lorg/apache/hadoop/hbase/regionserver/compactions/Compactor$InternalScannerFactory;Lorg/apache/hadoop/hbase/regionserver/compactions/Compactor$CellSinkFactory;Lorg/apache/hadoop/hbase/regionserver/throttle/ThroughputController;Lorg/apache/hadoop/hbase/security/User;)Ljava/util/List;
     154: areturn

  public java.util.List<org.apache.hadoop.fs.Path> compact(org.apache.hadoop.hbase.regionserver.compactions.CompactionRequestImpl, int, long, byte[], byte[], byte[], byte[], org.apache.hadoop.hbase.regionserver.throttle.ThroughputController, org.apache.hadoop.hbase.security.User) throws java.io.IOException;
    Code:
       0: getstatic     #2                  // Field LOG:Lorg/slf4j/Logger;
       3: invokeinterface #3,  1            // InterfaceMethod org/slf4j/Logger.isDebugEnabled:()Z
       8: ifeq          78
      11: getstatic     #2                  // Field LOG:Lorg/slf4j/Logger;
      14: new           #4                  // class java/lang/StringBuilder
      17: dup
      18: invokespecial #5                  // Method java/lang/StringBuilder."<init>":()V
      21: ldc           #6                  // String Executing compaction with
      23: invokevirtual #7                  // Method java/lang/StringBuilder.append:(Ljava/lang/String;)Ljava/lang/StringBuilder;
      26: lload_3
      27: invokevirtual #25                 // Method java/lang/StringBuilder.append:(J)Ljava/lang/StringBuilder;
      30: ldc           #26                 // String  target file size, no more than
      32: invokevirtual #7                  // Method java/lang/StringBuilder.append:(Ljava/lang/String;)Ljava/lang/StringBuilder;
      35: iload_2
      36: invokevirtual #9                  // Method java/lang/StringBuilder.append:(I)Ljava/lang/StringBuilder;
      39: ldc           #27                 // String  files, in [
      41: invokevirtual #7                  // Method java/lang/StringBuilder.append:(Ljava/lang/String;)Ljava/lang/StringBuilder;
      44: aload         5
      46: invokestatic  #17                 // Method org/apache/hadoop/hbase/util/Bytes.toString:([B)Ljava/lang/String;
      49: invokevirtual #7                  // Method java/lang/StringBuilder.append:(Ljava/lang/String;)Ljava/lang/StringBuilder;
      52: ldc           #28                 // String ] [
      54: invokevirtual #7                  // Method java/lang/StringBuilder.append:(Ljava/lang/String;)Ljava/lang/StringBuilder;
      57: aload         6
      59: invokestatic  #17                 // Method org/apache/hadoop/hbase/util/Bytes.toString:([B)Ljava/lang/String;
      62: invokevirtual #7                  // Method java/lang/StringBuilder.append:(Ljava/lang/String;)Ljava/lang/StringBuilder;
      65: ldc           #29                 // String ] range
      67: invokevirtual #7                  // Method java/lang/StringBuilder.append:(Ljava/lang/String;)Ljava/lang/StringBuilder;
      70: invokevirtual #11                 // Method java/lang/StringBuilder.toString:()Ljava/lang/String;
      73: invokeinterface #19,  2           // InterfaceMethod org/slf4j/Logger.debug:(Ljava/lang/String;)V
      78: aload_0
      79: aload_1
      80: new           #20                 // class org/apache/hadoop/hbase/regionserver/compactions/StripeCompactor$StripeInternalScannerFactory
      83: dup
      84: aload_0
      85: aload         7
      87: aload         8
      89: invokespecial #21                 // Method org/apache/hadoop/hbase/regionserver/compactions/StripeCompactor$StripeInternalScannerFactory."<init>":(Lorg/apache/hadoop/hbase/regionserver/compactions/StripeCompactor;[B[B)V
      92: new           #30                 // class org/apache/hadoop/hbase/regionserver/compactions/StripeCompactor$2
      95: dup
      96: aload_0
      97: iload_2
      98: lload_3
      99: aload         5
     101: aload         6
     103: invokespecial #31                 // Method org/apache/hadoop/hbase/regionserver/compactions/StripeCompactor$2."<init>":(Lorg/apache/hadoop/hbase/regionserver/compactions/StripeCompactor;IJ[B[B)V
     106: aload         9
     108: aload         10
     110: invokevirtual #24                 // Method compact:(Lorg/apache/hadoop/hbase/regionserver/compactions/CompactionRequestImpl;Lorg/apache/hadoop/hbase/regionserver/compactions/Compactor$InternalScannerFactory;Lorg/apache/hadoop/hbase/regionserver/compactions/Compactor$CellSinkFactory;Lorg/apache/hadoop/hbase/regionserver/throttle/ThroughputController;Lorg/apache/hadoop/hbase/security/User;)Ljava/util/List;
     113: areturn

  protected java.util.List<org.apache.hadoop.fs.Path> commitWriter(org.apache.hadoop.hbase.regionserver.StripeMultiFileWriter, org.apache.hadoop.hbase.regionserver.compactions.Compactor$FileDetails, org.apache.hadoop.hbase.regionserver.compactions.CompactionRequestImpl) throws java.io.IOException;
    Code:
       0: aload_1
       1: aload_2
       2: getfield      #32                 // Field org/apache/hadoop/hbase/regionserver/compactions/Compactor$FileDetails.maxSeqId:J
       5: aload_3
       6: invokevirtual #33                 // Method org/apache/hadoop/hbase/regionserver/compactions/CompactionRequestImpl.isMajor:()Z
       9: aload_3
      10: invokevirtual #34                 // Method org/apache/hadoop/hbase/regionserver/compactions/CompactionRequestImpl.getFiles:()Ljava/util/Collection;
      13: invokevirtual #35                 // Method org/apache/hadoop/hbase/regionserver/StripeMultiFileWriter.commitWriters:(JZLjava/util/Collection;)Ljava/util/List;
      16: astore        4
      18: getstatic     #36                 // Field $assertionsDisabled:Z
      21: ifne          44
      24: aload         4
      26: invokeinterface #37,  1           // InterfaceMethod java/util/List.isEmpty:()Z
      31: ifeq          44
      34: new           #38                 // class java/lang/AssertionError
      37: dup
      38: ldc           #39                 // String Should have produced an empty file to preserve metadata.
      40: invokespecial #40                 // Method java/lang/AssertionError."<init>":(Ljava/lang/Object;)V
      43: athrow
      44: aload         4
      46: areturn

  protected java.util.List commitWriter(org.apache.hadoop.hbase.regionserver.CellSink, org.apache.hadoop.hbase.regionserver.compactions.Compactor$FileDetails, org.apache.hadoop.hbase.regionserver.compactions.CompactionRequestImpl) throws java.io.IOException;
    Code:
       0: aload_0
       1: aload_1
       2: checkcast     #41                 // class org/apache/hadoop/hbase/regionserver/StripeMultiFileWriter
       5: aload_2
       6: aload_3
       7: invokevirtual #42                 // Method commitWriter:(Lorg/apache/hadoop/hbase/regionserver/StripeMultiFileWriter;Lorg/apache/hadoop/hbase/regionserver/compactions/Compactor$FileDetails;Lorg/apache/hadoop/hbase/regionserver/compactions/CompactionRequestImpl;)Ljava/util/List;
      10: areturn

  static {};
    Code:
       0: ldc           #43                 // class org/apache/hadoop/hbase/regionserver/compactions/StripeCompactor
       2: invokevirtual #44                 // Method java/lang/Class.desiredAssertionStatus:()Z
       5: ifne          12
       8: iconst_1
       9: goto          13
      12: iconst_0
      13: putstatic     #36                 // Field $assertionsDisabled:Z
      16: ldc           #43                 // class org/apache/hadoop/hbase/regionserver/compactions/StripeCompactor
      18: invokestatic  #45                 // Method org/slf4j/LoggerFactory.getLogger:(Ljava/lang/Class;)Lorg/slf4j/Logger;
      21: putstatic     #2                  // Field LOG:Lorg/slf4j/Logger;
      24: return
}
