Compiled from "StripeStoreFileManager.java"
class org.apache.hadoop.hbase.regionserver.StripeStoreFileManager$CompactionOrFlushMergeCopy {
  static final boolean $assertionsDisabled;

  final org.apache.hadoop.hbase.regionserver.StripeStoreFileManager this$0;

  public org.apache.hadoop.hbase.regionserver.StripeStoreFileManager$CompactionOrFlushMergeCopy(org.apache.hadoop.hbase.regionserver.StripeStoreFileManager, boolean);
    Code:
       0: aload_0
       1: aload_1
       2: putfield      #3                  // Field this$0:Lorg/apache/hadoop/hbase/regionserver/StripeStoreFileManager;
       5: aload_0
       6: invokespecial #4                  // Method java/lang/Object."<init>":()V
       9: aload_0
      10: aconst_null
      11: putfield      #5                  // Field stripeFiles:Ljava/util/ArrayList;
      14: aload_0
      15: aconst_null
      16: putfield      #6                  // Field level0Files:Ljava/util/ArrayList;
      19: aload_0
      20: aconst_null
      21: putfield      #7                  // Field stripeEndRows:Ljava/util/ArrayList;
      24: aload_0
      25: aconst_null
      26: putfield      #8                  // Field compactedFiles:Ljava/util/Collection;
      29: aload_0
      30: aconst_null
      31: putfield      #9                  // Field results:Ljava/util/Collection;
      34: aload_0
      35: new           #10                 // class java/util/ArrayList
      38: dup
      39: invokespecial #11                 // Method java/util/ArrayList."<init>":()V
      42: putfield      #12                 // Field l0Results:Ljava/util/List;
      45: aload_0
      46: new           #10                 // class java/util/ArrayList
      49: dup
      50: aload_1
      51: invokestatic  #13                 // Method org/apache/hadoop/hbase/regionserver/StripeStoreFileManager.access$1600:(Lorg/apache/hadoop/hbase/regionserver/StripeStoreFileManager;)Lorg/apache/hadoop/hbase/regionserver/StripeStoreFileManager$State;
      54: getfield      #14                 // Field org/apache/hadoop/hbase/regionserver/StripeStoreFileManager$State.stripeFiles:Ljava/util/ArrayList;
      57: invokespecial #15                 // Method java/util/ArrayList."<init>":(Ljava/util/Collection;)V
      60: putfield      #5                  // Field stripeFiles:Ljava/util/ArrayList;
      63: aload_0
      64: iload_2
      65: putfield      #16                 // Field isFlush:Z
      68: return

  static void access$100(org.apache.hadoop.hbase.regionserver.StripeStoreFileManager$CompactionOrFlushMergeCopy, java.util.Collection, java.util.Collection) throws java.io.IOException;
    Code:
       0: aload_0
       1: aload_1
       2: aload_2
       3: invokespecial #2                  // Method mergeResults:(Ljava/util/Collection;Ljava/util/Collection;)V
       6: return

  static void access$400(org.apache.hadoop.hbase.regionserver.StripeStoreFileManager$CompactionOrFlushMergeCopy, java.util.Collection) throws java.io.IOException;
    Code:
       0: aload_0
       1: aload_1
       2: invokespecial #1                  // Method deleteResults:(Ljava/util/Collection;)V
       5: return

  static {};
    Code:
       0: ldc           #119                // class org/apache/hadoop/hbase/regionserver/StripeStoreFileManager
       2: invokevirtual #120                // Method java/lang/Class.desiredAssertionStatus:()Z
       5: ifne          12
       8: iconst_1
       9: goto          13
      12: iconst_0
      13: putstatic     #17                 // Field $assertionsDisabled:Z
      16: return
}
