Compiled from "StripeCompactionPolicy.java"
public class org.apache.hadoop.hbase.regionserver.compactions.StripeCompactionPolicy extends org.apache.hadoop.hbase.regionserver.compactions.CompactionPolicy {
  static final boolean $assertionsDisabled;

  public org.apache.hadoop.hbase.regionserver.compactions.StripeCompactionPolicy(org.apache.hadoop.conf.Configuration, org.apache.hadoop.hbase.regionserver.StoreConfigInformation, org.apache.hadoop.hbase.regionserver.StripeStoreConfig);
    Code:
       0: aload_0
       1: aload_1
       2: aload_2
       3: invokespecial #1                  // Method org/apache/hadoop/hbase/regionserver/compactions/CompactionPolicy."<init>":(Lorg/apache/hadoop/conf/Configuration;Lorg/apache/hadoop/hbase/regionserver/StoreConfigInformation;)V
       6: aload_0
       7: aconst_null
       8: putfield      #2                  // Field stripePolicy:Lorg/apache/hadoop/hbase/regionserver/compactions/ExploringCompactionPolicy;
      11: aload_0
      12: aload_3
      13: putfield      #3                  // Field config:Lorg/apache/hadoop/hbase/regionserver/StripeStoreConfig;
      16: aload_0
      17: new           #4                  // class org/apache/hadoop/hbase/regionserver/compactions/ExploringCompactionPolicy
      20: dup
      21: aload_1
      22: aload_2
      23: invokespecial #5                  // Method org/apache/hadoop/hbase/regionserver/compactions/ExploringCompactionPolicy."<init>":(Lorg/apache/hadoop/conf/Configuration;Lorg/apache/hadoop/hbase/regionserver/StoreConfigInformation;)V
      26: putfield      #2                  // Field stripePolicy:Lorg/apache/hadoop/hbase/regionserver/compactions/ExploringCompactionPolicy;
      29: return

  public java.util.List<org.apache.hadoop.hbase.regionserver.HStoreFile> preSelectFilesForCoprocessor(org.apache.hadoop.hbase.regionserver.compactions.StripeCompactionPolicy$StripeInformationProvider, java.util.List<org.apache.hadoop.hbase.regionserver.HStoreFile>);
    Code:
       0: new           #6                  // class java/util/ArrayList
       3: dup
       4: aload_1
       5: invokeinterface #7,  1            // InterfaceMethod org/apache/hadoop/hbase/regionserver/compactions/StripeCompactionPolicy$StripeInformationProvider.getStorefiles:()Ljava/util/Collection;
      10: invokespecial #8                  // Method java/util/ArrayList."<init>":(Ljava/util/Collection;)V
      13: astore_3
      14: aload_3
      15: aload_2
      16: invokevirtual #9                  // Method java/util/ArrayList.removeAll:(Ljava/util/Collection;)Z
      19: pop
      20: aload_3
      21: areturn

  public org.apache.hadoop.hbase.regionserver.compactions.StripeCompactionPolicy$StripeCompactionRequest createEmptyRequest(org.apache.hadoop.hbase.regionserver.compactions.StripeCompactionPolicy$StripeInformationProvider, org.apache.hadoop.hbase.regionserver.compactions.CompactionRequestImpl);
    Code:
       0: aload_1
       1: invokeinterface #10,  1           // InterfaceMethod org/apache/hadoop/hbase/regionserver/compactions/StripeCompactionPolicy$StripeInformationProvider.getStripeCount:()I
       6: ifle          24
       9: new           #11                 // class org/apache/hadoop/hbase/regionserver/compactions/StripeCompactionPolicy$BoundaryStripeCompactionRequest
      12: dup
      13: aload_2
      14: aload_1
      15: invokeinterface #12,  1           // InterfaceMethod org/apache/hadoop/hbase/regionserver/compactions/StripeCompactionPolicy$StripeInformationProvider.getStripeBoundaries:()Ljava/util/List;
      20: invokespecial #13                 // Method org/apache/hadoop/hbase/regionserver/compactions/StripeCompactionPolicy$BoundaryStripeCompactionRequest."<init>":(Lorg/apache/hadoop/hbase/regionserver/compactions/CompactionRequestImpl;Ljava/util/List;)V
      23: areturn
      24: aload_0
      25: aload_2
      26: invokevirtual #14                 // Method org/apache/hadoop/hbase/regionserver/compactions/CompactionRequestImpl.getFiles:()Ljava/util/Collection;
      29: aload_0
      30: getfield      #3                  // Field config:Lorg/apache/hadoop/hbase/regionserver/StripeStoreConfig;
      33: invokevirtual #15                 // Method org/apache/hadoop/hbase/regionserver/StripeStoreConfig.getInitialCount:()I
      36: i2d
      37: invokespecial #16                 // Method estimateTargetKvs:(Ljava/util/Collection;D)Lorg/apache/hadoop/hbase/util/Pair;
      40: astore_3
      41: new           #17                 // class org/apache/hadoop/hbase/regionserver/compactions/StripeCompactionPolicy$SplitStripeCompactionRequest
      44: dup
      45: aload_2
      46: getstatic     #18                 // Field org/apache/hadoop/hbase/regionserver/StripeStoreFileManager.OPEN_KEY:[B
      49: getstatic     #18                 // Field org/apache/hadoop/hbase/regionserver/StripeStoreFileManager.OPEN_KEY:[B
      52: aload_3
      53: invokevirtual #19                 // Method org/apache/hadoop/hbase/util/Pair.getSecond:()Ljava/lang/Object;
      56: checkcast     #20                 // class java/lang/Integer
      59: invokevirtual #21                 // Method java/lang/Integer.intValue:()I
      62: aload_3
      63: invokevirtual #22                 // Method org/apache/hadoop/hbase/util/Pair.getFirst:()Ljava/lang/Object;
      66: checkcast     #23                 // class java/lang/Long
      69: invokevirtual #24                 // Method java/lang/Long.longValue:()J
      72: invokespecial #25                 // Method org/apache/hadoop/hbase/regionserver/compactions/StripeCompactionPolicy$SplitStripeCompactionRequest."<init>":(Lorg/apache/hadoop/hbase/regionserver/compactions/CompactionRequestImpl;[B[BIJ)V
      75: areturn

  public org.apache.hadoop.hbase.regionserver.StripeStoreFlusher$StripeFlushRequest selectFlush(org.apache.hadoop.hbase.CellComparator, org.apache.hadoop.hbase.regionserver.compactions.StripeCompactionPolicy$StripeInformationProvider, int);
    Code:
       0: aload_0
       1: getfield      #3                  // Field config:Lorg/apache/hadoop/hbase/regionserver/StripeStoreConfig;
       4: invokevirtual #26                 // Method org/apache/hadoop/hbase/regionserver/StripeStoreConfig.isUsingL0Flush:()Z
       7: ifeq          19
      10: new           #27                 // class org/apache/hadoop/hbase/regionserver/StripeStoreFlusher$StripeFlushRequest
      13: dup
      14: aload_1
      15: invokespecial #28                 // Method org/apache/hadoop/hbase/regionserver/StripeStoreFlusher$StripeFlushRequest."<init>":(Lorg/apache/hadoop/hbase/CellComparator;)V
      18: areturn
      19: aload_2
      20: invokeinterface #10,  1           // InterfaceMethod org/apache/hadoop/hbase/regionserver/compactions/StripeCompactionPolicy$StripeInformationProvider.getStripeCount:()I
      25: ifne          53
      28: aload_0
      29: getfield      #3                  // Field config:Lorg/apache/hadoop/hbase/regionserver/StripeStoreConfig;
      32: invokevirtual #15                 // Method org/apache/hadoop/hbase/regionserver/StripeStoreConfig.getInitialCount:()I
      35: istore        4
      37: new           #29                 // class org/apache/hadoop/hbase/regionserver/StripeStoreFlusher$SizeStripeFlushRequest
      40: dup
      41: aload_1
      42: iload         4
      44: iload_3
      45: iload         4
      47: idiv
      48: i2l
      49: invokespecial #30                 // Method org/apache/hadoop/hbase/regionserver/StripeStoreFlusher$SizeStripeFlushRequest."<init>":(Lorg/apache/hadoop/hbase/CellComparator;IJ)V
      52: areturn
      53: new           #31                 // class org/apache/hadoop/hbase/regionserver/StripeStoreFlusher$BoundaryStripeFlushRequest
      56: dup
      57: aload_1
      58: aload_2
      59: invokeinterface #12,  1           // InterfaceMethod org/apache/hadoop/hbase/regionserver/compactions/StripeCompactionPolicy$StripeInformationProvider.getStripeBoundaries:()Ljava/util/List;
      64: invokespecial #32                 // Method org/apache/hadoop/hbase/regionserver/StripeStoreFlusher$BoundaryStripeFlushRequest."<init>":(Lorg/apache/hadoop/hbase/CellComparator;Ljava/util/List;)V
      67: areturn

  public org.apache.hadoop.hbase.regionserver.compactions.StripeCompactionPolicy$StripeCompactionRequest selectCompaction(org.apache.hadoop.hbase.regionserver.compactions.StripeCompactionPolicy$StripeInformationProvider, java.util.List<org.apache.hadoop.hbase.regionserver.HStoreFile>, boolean) throws java.io.IOException;
    Code:
       0: aload_2
       1: invokeinterface #33,  1           // InterfaceMethod java/util/List.isEmpty:()Z
       6: ifne          48
       9: getstatic     #34                 // Field LOG:Lorg/slf4j/Logger;
      12: new           #35                 // class java/lang/StringBuilder
      15: dup
      16: invokespecial #36                 // Method java/lang/StringBuilder."<init>":()V
      19: ldc           #37                 // String Not selecting compaction:
      21: invokevirtual #38                 // Method java/lang/StringBuilder.append:(Ljava/lang/String;)Ljava/lang/StringBuilder;
      24: aload_2
      25: invokeinterface #39,  1           // InterfaceMethod java/util/List.size:()I
      30: invokevirtual #40                 // Method java/lang/StringBuilder.append:(I)Ljava/lang/StringBuilder;
      33: ldc           #41                 // String  files compacting
      35: invokevirtual #38                 // Method java/lang/StringBuilder.append:(Ljava/lang/String;)Ljava/lang/StringBuilder;
      38: invokevirtual #42                 // Method java/lang/StringBuilder.toString:()Ljava/lang/String;
      41: invokeinterface #43,  2           // InterfaceMethod org/slf4j/Logger.debug:(Ljava/lang/String;)V
      46: aconst_null
      47: areturn
      48: aload_1
      49: invokeinterface #7,  1            // InterfaceMethod org/apache/hadoop/hbase/regionserver/compactions/StripeCompactionPolicy$StripeInformationProvider.getStorefiles:()Ljava/util/Collection;
      54: astore        4
      56: aload         4
      58: invokestatic  #44                 // Method org/apache/hadoop/hbase/regionserver/StoreUtils.hasReferences:(Ljava/util/Collection;)Z
      61: ifeq          126
      64: getstatic     #34                 // Field LOG:Lorg/slf4j/Logger;
      67: ldc           #45                 // String There are references in the store; compacting all files
      69: invokeinterface #43,  2           // InterfaceMethod org/slf4j/Logger.debug:(Ljava/lang/String;)V
      74: aload_0
      75: aload         4
      77: aload_0
      78: getfield      #3                  // Field config:Lorg/apache/hadoop/hbase/regionserver/StripeStoreConfig;
      81: invokevirtual #15                 // Method org/apache/hadoop/hbase/regionserver/StripeStoreConfig.getInitialCount:()I
      84: i2d
      85: invokespecial #16                 // Method estimateTargetKvs:(Ljava/util/Collection;D)Lorg/apache/hadoop/hbase/util/Pair;
      88: invokevirtual #22                 // Method org/apache/hadoop/hbase/util/Pair.getFirst:()Ljava/lang/Object;
      91: checkcast     #23                 // class java/lang/Long
      94: invokevirtual #24                 // Method java/lang/Long.longValue:()J
      97: lstore        5
      99: new           #17                 // class org/apache/hadoop/hbase/regionserver/compactions/StripeCompactionPolicy$SplitStripeCompactionRequest
     102: dup
     103: aload         4
     105: getstatic     #18                 // Field org/apache/hadoop/hbase/regionserver/StripeStoreFileManager.OPEN_KEY:[B
     108: getstatic     #18                 // Field org/apache/hadoop/hbase/regionserver/StripeStoreFileManager.OPEN_KEY:[B
     111: lload         5
     113: invokespecial #46                 // Method org/apache/hadoop/hbase/regionserver/compactions/StripeCompactionPolicy$SplitStripeCompactionRequest."<init>":(Ljava/util/Collection;[B[BJ)V
     116: astore        7
     118: aload         7
     120: invokevirtual #47                 // Method org/apache/hadoop/hbase/regionserver/compactions/StripeCompactionPolicy$SplitStripeCompactionRequest.setMajorRangeFull:()V
     123: aload         7
     125: areturn
     126: aload_1
     127: invokeinterface #10,  1           // InterfaceMethod org/apache/hadoop/hbase/regionserver/compactions/StripeCompactionPolicy$StripeInformationProvider.getStripeCount:()I
     132: istore        5
     134: aload_1
     135: invokeinterface #48,  1           // InterfaceMethod org/apache/hadoop/hbase/regionserver/compactions/StripeCompactionPolicy$StripeInformationProvider.getLevel0Files:()Ljava/util/List;
     140: astore        6
     142: aload_0
     143: getfield      #3                  // Field config:Lorg/apache/hadoop/hbase/regionserver/StripeStoreConfig;
     146: invokevirtual #49                 // Method org/apache/hadoop/hbase/regionserver/StripeStoreConfig.getLevel0MinFiles:()I
     149: aload         6
     151: invokeinterface #39,  1           // InterfaceMethod java/util/List.size:()I
     156: if_icmpgt     163
     159: iconst_1
     160: goto          164
     163: iconst_0
     164: istore        7
     166: iload         5
     168: ifne          184
     171: iload         7
     173: ifne          178
     176: aconst_null
     177: areturn
     178: aload_0
     179: aload_1
     180: invokespecial #50                 // Method selectNewStripesCompaction:(Lorg/apache/hadoop/hbase/regionserver/compactions/StripeCompactionPolicy$StripeInformationProvider;)Lorg/apache/hadoop/hbase/regionserver/compactions/StripeCompactionPolicy$StripeCompactionRequest;
     183: areturn
     184: aload         6
     186: invokeinterface #33,  1           // InterfaceMethod java/util/List.isEmpty:()Z
     191: istore        8
     193: iload         7
     195: ifeq          276
     198: iload         8
     200: ifne          222
     203: aload_0
     204: aload_1
     205: iconst_1
     206: iload         8
     208: iload_3
     209: invokevirtual #51                 // Method selectSingleStripeCompaction:(Lorg/apache/hadoop/hbase/regionserver/compactions/StripeCompactionPolicy$StripeInformationProvider;ZZZ)Lorg/apache/hadoop/hbase/regionserver/compactions/StripeCompactionPolicy$StripeCompactionRequest;
     212: astore        9
     214: aload         9
     216: ifnull        222
     219: aload         9
     221: areturn
     222: getstatic     #34                 // Field LOG:Lorg/slf4j/Logger;
     225: new           #35                 // class java/lang/StringBuilder
     228: dup
     229: invokespecial #36                 // Method java/lang/StringBuilder."<init>":()V
     232: ldc           #52                 // String Selecting L0 compaction with
     234: invokevirtual #38                 // Method java/lang/StringBuilder.append:(Ljava/lang/String;)Ljava/lang/StringBuilder;
     237: aload         6
     239: invokeinterface #39,  1           // InterfaceMethod java/util/List.size:()I
     244: invokevirtual #40                 // Method java/lang/StringBuilder.append:(I)Ljava/lang/StringBuilder;
     247: ldc           #53                 // String  files
     249: invokevirtual #38                 // Method java/lang/StringBuilder.append:(Ljava/lang/String;)Ljava/lang/StringBuilder;
     252: invokevirtual #42                 // Method java/lang/StringBuilder.toString:()Ljava/lang/String;
     255: invokeinterface #43,  2           // InterfaceMethod org/slf4j/Logger.debug:(Ljava/lang/String;)V
     260: new           #11                 // class org/apache/hadoop/hbase/regionserver/compactions/StripeCompactionPolicy$BoundaryStripeCompactionRequest
     263: dup
     264: aload         6
     266: aload_1
     267: invokeinterface #12,  1           // InterfaceMethod org/apache/hadoop/hbase/regionserver/compactions/StripeCompactionPolicy$StripeInformationProvider.getStripeBoundaries:()Ljava/util/List;
     272: invokespecial #54                 // Method org/apache/hadoop/hbase/regionserver/compactions/StripeCompactionPolicy$BoundaryStripeCompactionRequest."<init>":(Ljava/util/Collection;Ljava/util/List;)V
     275: areturn
     276: aload_0
     277: aload_1
     278: iload         8
     280: invokespecial #55                 // Method selectExpiredMergeCompaction:(Lorg/apache/hadoop/hbase/regionserver/compactions/StripeCompactionPolicy$StripeInformationProvider;Z)Lorg/apache/hadoop/hbase/regionserver/compactions/StripeCompactionPolicy$StripeCompactionRequest;
     283: astore        9
     285: aload         9
     287: ifnull        293
     290: aload         9
     292: areturn
     293: aload_0
     294: aload_1
     295: iconst_0
     296: iload         8
     298: iload_3
     299: invokevirtual #51                 // Method selectSingleStripeCompaction:(Lorg/apache/hadoop/hbase/regionserver/compactions/StripeCompactionPolicy$StripeInformationProvider;ZZZ)Lorg/apache/hadoop/hbase/regionserver/compactions/StripeCompactionPolicy$StripeCompactionRequest;
     302: areturn

  public boolean needsCompactions(org.apache.hadoop.hbase.regionserver.compactions.StripeCompactionPolicy$StripeInformationProvider, java.util.List<org.apache.hadoop.hbase.regionserver.HStoreFile>);
    Code:
       0: aload_2
       1: invokeinterface #33,  1           // InterfaceMethod java/util/List.isEmpty:()Z
       6: ifeq          54
       9: aload_1
      10: invokeinterface #7,  1            // InterfaceMethod org/apache/hadoop/hbase/regionserver/compactions/StripeCompactionPolicy$StripeInformationProvider.getStorefiles:()Ljava/util/Collection;
      15: invokestatic  #44                 // Method org/apache/hadoop/hbase/regionserver/StoreUtils.hasReferences:(Ljava/util/Collection;)Z
      18: ifne          50
      21: aload_1
      22: invokeinterface #48,  1           // InterfaceMethod org/apache/hadoop/hbase/regionserver/compactions/StripeCompactionPolicy$StripeInformationProvider.getLevel0Files:()Ljava/util/List;
      27: invokeinterface #39,  1           // InterfaceMethod java/util/List.size:()I
      32: aload_0
      33: getfield      #3                  // Field config:Lorg/apache/hadoop/hbase/regionserver/StripeStoreConfig;
      36: invokevirtual #49                 // Method org/apache/hadoop/hbase/regionserver/StripeStoreConfig.getLevel0MinFiles:()I
      39: if_icmpge     50
      42: aload_0
      43: aload_1
      44: invokevirtual #56                 // Method needsSingleStripeCompaction:(Lorg/apache/hadoop/hbase/regionserver/compactions/StripeCompactionPolicy$StripeInformationProvider;)Z
      47: ifeq          54
      50: iconst_1
      51: goto          55
      54: iconst_0
      55: ireturn

  public boolean shouldPerformMajorCompaction(java.util.Collection<org.apache.hadoop.hbase.regionserver.HStoreFile>) throws java.io.IOException;
    Code:
       0: iconst_0
       1: ireturn

  public boolean throttleCompaction(long);
    Code:
       0: lload_1
       1: aload_0
       2: getfield      #57                 // Field comConf:Lorg/apache/hadoop/hbase/regionserver/compactions/CompactionConfiguration;
       5: invokevirtual #58                 // Method org/apache/hadoop/hbase/regionserver/compactions/CompactionConfiguration.getThrottlePoint:()J
       8: lcmp
       9: ifle          16
      12: iconst_1
      13: goto          17
      16: iconst_0
      17: ireturn

  protected boolean needsSingleStripeCompaction(org.apache.hadoop.hbase.regionserver.compactions.StripeCompactionPolicy$StripeInformationProvider);
    Code:
       0: aload_0
       1: getfield      #3                  // Field config:Lorg/apache/hadoop/hbase/regionserver/StripeStoreConfig;
       4: invokevirtual #59                 // Method org/apache/hadoop/hbase/regionserver/StripeStoreConfig.getStripeCompactMinFiles:()I
       7: istore_2
       8: aload_1
       9: invokeinterface #60,  1           // InterfaceMethod org/apache/hadoop/hbase/regionserver/compactions/StripeCompactionPolicy$StripeInformationProvider.getStripes:()Ljava/util/ArrayList;
      14: invokevirtual #61                 // Method java/util/ArrayList.iterator:()Ljava/util/Iterator;
      17: astore_3
      18: aload_3
      19: invokeinterface #62,  1           // InterfaceMethod java/util/Iterator.hasNext:()Z
      24: ifeq          54
      27: aload_3
      28: invokeinterface #63,  1           // InterfaceMethod java/util/Iterator.next:()Ljava/lang/Object;
      33: checkcast     #64                 // class java/util/List
      36: astore        4
      38: aload         4
      40: invokeinterface #39,  1           // InterfaceMethod java/util/List.size:()I
      45: iload_2
      46: if_icmplt     51
      49: iconst_1
      50: ireturn
      51: goto          18
      54: iconst_0
      55: ireturn

  protected org.apache.hadoop.hbase.regionserver.compactions.StripeCompactionPolicy$StripeCompactionRequest selectSingleStripeCompaction(org.apache.hadoop.hbase.regionserver.compactions.StripeCompactionPolicy$StripeInformationProvider, boolean, boolean, boolean) throws java.io.IOException;
    Code:
       0: aload_1
       1: invokeinterface #60,  1           // InterfaceMethod org/apache/hadoop/hbase/regionserver/compactions/StripeCompactionPolicy$StripeInformationProvider.getStripes:()Ljava/util/ArrayList;
       6: astore        5
       8: iconst_m1
       9: istore        6
      11: aconst_null
      12: astore        7
      14: aload         5
      16: invokevirtual #65                 // Method java/util/ArrayList.size:()I
      19: istore        8
      21: ldc2_w        #66                 // long -1l
      24: lstore        9
      26: iconst_0
      27: istore        11
      29: iload         11
      31: iload         8
      33: if_icmpge     195
      36: aload_0
      37: aload         5
      39: iload         11
      41: invokevirtual #68                 // Method java/util/ArrayList.get:(I)Ljava/lang/Object;
      44: checkcast     #64                 // class java/util/List
      47: iload_3
      48: ifne          59
      51: iload_2
      52: ifeq          59
      55: iconst_1
      56: goto          60
      59: iconst_0
      60: iload         4
      62: invokespecial #69                 // Method selectSimpleCompaction:(Ljava/util/List;ZZ)Ljava/util/List;
      65: astore        12
      67: aload         12
      69: invokeinterface #33,  1           // InterfaceMethod java/util/List.isEmpty:()Z
      74: ifeq          80
      77: goto          189
      80: lconst_0
      81: lstore        13
      83: aload         12
      85: invokeinterface #70,  1           // InterfaceMethod java/util/List.iterator:()Ljava/util/Iterator;
      90: astore        15
      92: aload         15
      94: invokeinterface #62,  1           // InterfaceMethod java/util/Iterator.hasNext:()Z
      99: ifeq          130
     102: aload         15
     104: invokeinterface #63,  1           // InterfaceMethod java/util/Iterator.next:()Ljava/lang/Object;
     109: checkcast     #71                 // class org/apache/hadoop/hbase/regionserver/HStoreFile
     112: astore        16
     114: lload         13
     116: aload         16
     118: invokevirtual #72                 // Method org/apache/hadoop/hbase/regionserver/HStoreFile.getReader:()Lorg/apache/hadoop/hbase/regionserver/StoreFileReader;
     121: invokevirtual #73                 // Method org/apache/hadoop/hbase/regionserver/StoreFileReader.length:()J
     124: ladd
     125: lstore        13
     127: goto          92
     130: aload         7
     132: ifnull        177
     135: aload         12
     137: invokeinterface #39,  1           // InterfaceMethod java/util/List.size:()I
     142: aload         7
     144: invokeinterface #39,  1           // InterfaceMethod java/util/List.size:()I
     149: if_icmpgt     177
     152: aload         12
     154: invokeinterface #39,  1           // InterfaceMethod java/util/List.size:()I
     159: aload         7
     161: invokeinterface #39,  1           // InterfaceMethod java/util/List.size:()I
     166: if_icmpne     189
     169: lload         13
     171: lload         9
     173: lcmp
     174: ifge          189
     177: aload         12
     179: astore        7
     181: iload         11
     183: istore        6
     185: lload         13
     187: lstore        9
     189: iinc          11, 1
     192: goto          29
     195: aload         7
     197: ifnonnull     212
     200: getstatic     #34                 // Field LOG:Lorg/slf4j/Logger;
     203: ldc           #74                 // String No good compaction is possible in any stripe
     205: invokeinterface #43,  2           // InterfaceMethod org/slf4j/Logger.debug:(Ljava/lang/String;)V
     210: aconst_null
     211: areturn
     212: new           #6                  // class java/util/ArrayList
     215: dup
     216: aload         7
     218: invokespecial #8                  // Method java/util/ArrayList."<init>":(Ljava/util/Collection;)V
     221: astore        11
     223: iconst_1
     224: istore        12
     226: ldc2_w        #75                 // long 9223372036854775807l
     229: lstore        13
     231: aload         11
     233: invokeinterface #39,  1           // InterfaceMethod java/util/List.size:()I
     238: aload         5
     240: iload         6
     242: invokevirtual #68                 // Method java/util/ArrayList.get:(I)Ljava/lang/Object;
     245: checkcast     #77                 // class org/apache/hbase/thirdparty/com/google/common/collect/ImmutableList
     248: invokevirtual #78                 // Method org/apache/hbase/thirdparty/com/google/common/collect/ImmutableList.size:()I
     251: if_icmpne     258
     254: iconst_1
     255: goto          259
     258: iconst_0
     259: istore        15
     261: ldc           #79                 // String
     263: astore        16
     265: iload         15
     267: ifeq          368
     270: lload         9
     272: aload_0
     273: getfield      #3                  // Field config:Lorg/apache/hadoop/hbase/regionserver/StripeStoreConfig;
     276: invokevirtual #80                 // Method org/apache/hadoop/hbase/regionserver/StripeStoreConfig.getSplitSize:()J
     279: lcmp
     280: iflt          368
     283: iload_2
     284: ifeq          289
     287: aconst_null
     288: areturn
     289: aload_0
     290: aload         11
     292: aload_0
     293: getfield      #3                  // Field config:Lorg/apache/hadoop/hbase/regionserver/StripeStoreConfig;
     296: invokevirtual #81                 // Method org/apache/hadoop/hbase/regionserver/StripeStoreConfig.getSplitCount:()F
     299: f2d
     300: invokespecial #16                 // Method estimateTargetKvs:(Ljava/util/Collection;D)Lorg/apache/hadoop/hbase/util/Pair;
     303: astore        17
     305: aload         17
     307: invokevirtual #22                 // Method org/apache/hadoop/hbase/util/Pair.getFirst:()Ljava/lang/Object;
     310: checkcast     #23                 // class java/lang/Long
     313: invokevirtual #24                 // Method java/lang/Long.longValue:()J
     316: lstore        13
     318: aload         17
     320: invokevirtual #19                 // Method org/apache/hadoop/hbase/util/Pair.getSecond:()Ljava/lang/Object;
     323: checkcast     #20                 // class java/lang/Integer
     326: invokevirtual #21                 // Method java/lang/Integer.intValue:()I
     329: istore        12
     331: new           #35                 // class java/lang/StringBuilder
     334: dup
     335: invokespecial #36                 // Method java/lang/StringBuilder."<init>":()V
     338: ldc           #82                 // String ; the stripe will be split into at most
     340: invokevirtual #38                 // Method java/lang/StringBuilder.append:(Ljava/lang/String;)Ljava/lang/StringBuilder;
     343: iload         12
     345: invokevirtual #40                 // Method java/lang/StringBuilder.append:(I)Ljava/lang/StringBuilder;
     348: ldc           #83                 // String  stripes with
     350: invokevirtual #38                 // Method java/lang/StringBuilder.append:(Ljava/lang/String;)Ljava/lang/StringBuilder;
     353: lload         13
     355: invokevirtual #84                 // Method java/lang/StringBuilder.append:(J)Ljava/lang/StringBuilder;
     358: ldc           #85                 // String  target KVs
     360: invokevirtual #38                 // Method java/lang/StringBuilder.append:(Ljava/lang/String;)Ljava/lang/StringBuilder;
     363: invokevirtual #42                 // Method java/lang/StringBuilder.toString:()Ljava/lang/String;
     366: astore        16
     368: getstatic     #34                 // Field LOG:Lorg/slf4j/Logger;
     371: new           #35                 // class java/lang/StringBuilder
     374: dup
     375: invokespecial #36                 // Method java/lang/StringBuilder."<init>":()V
     378: ldc           #86                 // String Found compaction in a stripe with end key [
     380: invokevirtual #38                 // Method java/lang/StringBuilder.append:(Ljava/lang/String;)Ljava/lang/StringBuilder;
     383: aload_1
     384: iload         6
     386: invokeinterface #87,  2           // InterfaceMethod org/apache/hadoop/hbase/regionserver/compactions/StripeCompactionPolicy$StripeInformationProvider.getEndRow:(I)[B
     391: invokestatic  #88                 // Method org/apache/hadoop/hbase/util/Bytes.toString:([B)Ljava/lang/String;
     394: invokevirtual #38                 // Method java/lang/StringBuilder.append:(Ljava/lang/String;)Ljava/lang/StringBuilder;
     397: ldc           #89                 // String ], with
     399: invokevirtual #38                 // Method java/lang/StringBuilder.append:(Ljava/lang/String;)Ljava/lang/StringBuilder;
     402: aload         11
     404: invokeinterface #39,  1           // InterfaceMethod java/util/List.size:()I
     409: invokevirtual #40                 // Method java/lang/StringBuilder.append:(I)Ljava/lang/StringBuilder;
     412: ldc           #90                 // String  files of total size
     414: invokevirtual #38                 // Method java/lang/StringBuilder.append:(Ljava/lang/String;)Ljava/lang/StringBuilder;
     417: lload         9
     419: invokevirtual #84                 // Method java/lang/StringBuilder.append:(J)Ljava/lang/StringBuilder;
     422: aload         16
     424: invokevirtual #38                 // Method java/lang/StringBuilder.append:(Ljava/lang/String;)Ljava/lang/StringBuilder;
     427: invokevirtual #42                 // Method java/lang/StringBuilder.toString:()Ljava/lang/String;
     430: invokeinterface #43,  2           // InterfaceMethod org/slf4j/Logger.debug:(Ljava/lang/String;)V
     435: iload_2
     436: ifeq          547
     439: getstatic     #91                 // Field $assertionsDisabled:Z
     442: ifne          458
     445: iload         15
     447: ifne          458
     450: new           #92                 // class java/lang/AssertionError
     453: dup
     454: invokespecial #93                 // Method java/lang/AssertionError."<init>":()V
     457: athrow
     458: aload_1
     459: invokeinterface #48,  1           // InterfaceMethod org/apache/hadoop/hbase/regionserver/compactions/StripeCompactionPolicy$StripeInformationProvider.getLevel0Files:()Ljava/util/List;
     464: astore        18
     466: getstatic     #34                 // Field LOG:Lorg/slf4j/Logger;
     469: new           #35                 // class java/lang/StringBuilder
     472: dup
     473: invokespecial #36                 // Method java/lang/StringBuilder."<init>":()V
     476: ldc           #94                 // String Adding
     478: invokevirtual #38                 // Method java/lang/StringBuilder.append:(Ljava/lang/String;)Ljava/lang/StringBuilder;
     481: aload         18
     483: invokeinterface #39,  1           // InterfaceMethod java/util/List.size:()I
     488: invokevirtual #40                 // Method java/lang/StringBuilder.append:(I)Ljava/lang/StringBuilder;
     491: ldc           #95                 // String  files to compaction to be able to drop deletes
     493: invokevirtual #38                 // Method java/lang/StringBuilder.append:(Ljava/lang/String;)Ljava/lang/StringBuilder;
     496: invokevirtual #42                 // Method java/lang/StringBuilder.toString:()Ljava/lang/String;
     499: invokeinterface #43,  2           // InterfaceMethod org/slf4j/Logger.debug:(Ljava/lang/String;)V
     504: new           #96                 // class org/apache/hadoop/hbase/util/ConcatenatedLists
     507: dup
     508: invokespecial #97                 // Method org/apache/hadoop/hbase/util/ConcatenatedLists."<init>":()V
     511: astore        19
     513: aload         19
     515: aload         11
     517: invokevirtual #98                 // Method org/apache/hadoop/hbase/util/ConcatenatedLists.addSublist:(Ljava/util/List;)V
     520: aload         19
     522: aload         18
     524: invokevirtual #98                 // Method org/apache/hadoop/hbase/util/ConcatenatedLists.addSublist:(Ljava/util/List;)V
     527: new           #11                 // class org/apache/hadoop/hbase/regionserver/compactions/StripeCompactionPolicy$BoundaryStripeCompactionRequest
     530: dup
     531: aload         19
     533: aload_1
     534: invokeinterface #12,  1           // InterfaceMethod org/apache/hadoop/hbase/regionserver/compactions/StripeCompactionPolicy$StripeInformationProvider.getStripeBoundaries:()Ljava/util/List;
     539: invokespecial #54                 // Method org/apache/hadoop/hbase/regionserver/compactions/StripeCompactionPolicy$BoundaryStripeCompactionRequest."<init>":(Ljava/util/Collection;Ljava/util/List;)V
     542: astore        17
     544: goto          578
     547: new           #17                 // class org/apache/hadoop/hbase/regionserver/compactions/StripeCompactionPolicy$SplitStripeCompactionRequest
     550: dup
     551: aload         11
     553: aload_1
     554: iload         6
     556: invokeinterface #99,  2           // InterfaceMethod org/apache/hadoop/hbase/regionserver/compactions/StripeCompactionPolicy$StripeInformationProvider.getStartRow:(I)[B
     561: aload_1
     562: iload         6
     564: invokeinterface #87,  2           // InterfaceMethod org/apache/hadoop/hbase/regionserver/compactions/StripeCompactionPolicy$StripeInformationProvider.getEndRow:(I)[B
     569: iload         12
     571: lload         13
     573: invokespecial #100                // Method org/apache/hadoop/hbase/regionserver/compactions/StripeCompactionPolicy$SplitStripeCompactionRequest."<init>":(Ljava/util/Collection;[B[BIJ)V
     576: astore        17
     578: iload         15
     580: ifeq          612
     583: iload_3
     584: ifne          591
     587: iload_2
     588: ifeq          612
     591: aload         17
     593: aload_1
     594: iload         6
     596: invokeinterface #99,  2           // InterfaceMethod org/apache/hadoop/hbase/regionserver/compactions/StripeCompactionPolicy$StripeInformationProvider.getStartRow:(I)[B
     601: aload_1
     602: iload         6
     604: invokeinterface #87,  2           // InterfaceMethod org/apache/hadoop/hbase/regionserver/compactions/StripeCompactionPolicy$StripeInformationProvider.getEndRow:(I)[B
     609: invokevirtual #101                // Method org/apache/hadoop/hbase/regionserver/compactions/StripeCompactionPolicy$StripeCompactionRequest.setMajorRange:([B[B)V
     612: aload         17
     614: invokevirtual #102                // Method org/apache/hadoop/hbase/regionserver/compactions/StripeCompactionPolicy$StripeCompactionRequest.getRequest:()Lorg/apache/hadoop/hbase/regionserver/compactions/CompactionRequestImpl;
     617: iload         4
     619: invokevirtual #103                // Method org/apache/hadoop/hbase/regionserver/compactions/CompactionRequestImpl.setOffPeak:(Z)V
     622: aload         17
     624: areturn

  public static long getTotalFileSize(java.util.Collection<org.apache.hadoop.hbase.regionserver.HStoreFile>);
    Code:
       0: lconst_0
       1: lstore_1
       2: aload_0
       3: invokeinterface #120,  1          // InterfaceMethod java/util/Collection.iterator:()Ljava/util/Iterator;
       8: astore_3
       9: aload_3
      10: invokeinterface #62,  1           // InterfaceMethod java/util/Iterator.hasNext:()Z
      15: ifeq          43
      18: aload_3
      19: invokeinterface #63,  1           // InterfaceMethod java/util/Iterator.next:()Ljava/lang/Object;
      24: checkcast     #71                 // class org/apache/hadoop/hbase/regionserver/HStoreFile
      27: astore        4
      29: lload_1
      30: aload         4
      32: invokevirtual #72                 // Method org/apache/hadoop/hbase/regionserver/HStoreFile.getReader:()Lorg/apache/hadoop/hbase/regionserver/StoreFileReader;
      35: invokevirtual #73                 // Method org/apache/hadoop/hbase/regionserver/StoreFileReader.length:()J
      38: ladd
      39: lstore_1
      40: goto          9
      43: lload_1
      44: lreturn

  static {};
    Code:
       0: ldc           #130                // class org/apache/hadoop/hbase/regionserver/compactions/StripeCompactionPolicy
       2: invokevirtual #131                // Method java/lang/Class.desiredAssertionStatus:()Z
       5: ifne          12
       8: iconst_1
       9: goto          13
      12: iconst_0
      13: putstatic     #91                 // Field $assertionsDisabled:Z
      16: ldc           #130                // class org/apache/hadoop/hbase/regionserver/compactions/StripeCompactionPolicy
      18: invokestatic  #132                // Method org/slf4j/LoggerFactory.getLogger:(Ljava/lang/Class;)Lorg/slf4j/Logger;
      21: putstatic     #34                 // Field LOG:Lorg/slf4j/Logger;
      24: return
}
