Compiled from "SyncReplicationReplayWALManager.java"
final class org.apache.hadoop.hbase.master.replication.SyncReplicationReplayWALManager$UsedReplayWorkersForPeer {
  public org.apache.hadoop.hbase.master.replication.SyncReplicationReplayWALManager$UsedReplayWorkersForPeer(java.lang.String);
    Code:
       0: aload_0
       1: invokespecial #1                  // Method java/lang/Object."<init>":()V
       4: aload_0
       5: new           #2                  // class java/util/HashSet
       8: dup
       9: invokespecial #3                  // Method java/util/HashSet."<init>":()V
      12: putfield      #4                  // Field usedWorkers:Ljava/util/Set;
      15: aload_0
      16: new           #5                  // class org/apache/hadoop/hbase/procedure2/ProcedureEvent
      19: dup
      20: aload_1
      21: invokespecial #6                  // Method org/apache/hadoop/hbase/procedure2/ProcedureEvent."<init>":(Ljava/lang/Object;)V
      24: putfield      #7                  // Field event:Lorg/apache/hadoop/hbase/procedure2/ProcedureEvent;
      27: return

  public void used(org.apache.hadoop.hbase.ServerName);
    Code:
       0: aload_0
       1: getfield      #4                  // Field usedWorkers:Ljava/util/Set;
       4: aload_1
       5: invokeinterface #8,  2            // InterfaceMethod java/util/Set.add:(Ljava/lang/Object;)Z
      10: pop
      11: return

  public java.util.Optional<org.apache.hadoop.hbase.ServerName> acquire(org.apache.hadoop.hbase.master.ServerManager);
    Code:
       0: aload_1
       1: invokevirtual #9                  // Method org/apache/hadoop/hbase/master/ServerManager.getOnlineServers:()Ljava/util/Map;
       4: invokeinterface #10,  1           // InterfaceMethod java/util/Map.keySet:()Ljava/util/Set;
       9: invokeinterface #11,  1           // InterfaceMethod java/util/Set.stream:()Ljava/util/stream/Stream;
      14: aload_0
      15: invokedynamic #12,  0             // InvokeDynamic #0:test:(Lorg/apache/hadoop/hbase/master/replication/SyncReplicationReplayWALManager$UsedReplayWorkersForPeer;)Ljava/util/function/Predicate;
      20: invokeinterface #13,  2           // InterfaceMethod java/util/stream/Stream.filter:(Ljava/util/function/Predicate;)Ljava/util/stream/Stream;
      25: invokeinterface #14,  1           // InterfaceMethod java/util/stream/Stream.findAny:()Ljava/util/Optional;
      30: astore_2
      31: aload_2
      32: aload_0
      33: getfield      #4                  // Field usedWorkers:Ljava/util/Set;
      36: dup
      37: invokevirtual #15                 // Method java/lang/Object.getClass:()Ljava/lang/Class;
      40: pop
      41: invokedynamic #16,  0             // InvokeDynamic #1:accept:(Ljava/util/Set;)Ljava/util/function/Consumer;
      46: invokevirtual #17                 // Method java/util/Optional.ifPresent:(Ljava/util/function/Consumer;)V
      49: aload_2
      50: areturn

  public void release(org.apache.hadoop.hbase.ServerName);
    Code:
       0: aload_0
       1: getfield      #4                  // Field usedWorkers:Ljava/util/Set;
       4: aload_1
       5: invokeinterface #18,  2           // InterfaceMethod java/util/Set.remove:(Ljava/lang/Object;)Z
      10: pop
      11: return

  public void suspend(org.apache.hadoop.hbase.procedure2.Procedure<?>);
    Code:
       0: aload_0
       1: getfield      #7                  // Field event:Lorg/apache/hadoop/hbase/procedure2/ProcedureEvent;
       4: invokevirtual #19                 // Method org/apache/hadoop/hbase/procedure2/ProcedureEvent.suspend:()V
       7: aload_0
       8: getfield      #7                  // Field event:Lorg/apache/hadoop/hbase/procedure2/ProcedureEvent;
      11: aload_1
      12: invokevirtual #20                 // Method org/apache/hadoop/hbase/procedure2/ProcedureEvent.suspendIfNotReady:(Lorg/apache/hadoop/hbase/procedure2/Procedure;)Z
      15: pop
      16: return

  public void wake(org.apache.hadoop.hbase.master.procedure.MasterProcedureScheduler);
    Code:
       0: aload_0
       1: getfield      #7                  // Field event:Lorg/apache/hadoop/hbase/procedure2/ProcedureEvent;
       4: invokevirtual #21                 // Method org/apache/hadoop/hbase/procedure2/ProcedureEvent.isReady:()Z
       7: ifne          18
      10: aload_0
      11: getfield      #7                  // Field event:Lorg/apache/hadoop/hbase/procedure2/ProcedureEvent;
      14: aload_1
      15: invokevirtual #22                 // Method org/apache/hadoop/hbase/procedure2/ProcedureEvent.wake:(Lorg/apache/hadoop/hbase/procedure2/AbstractProcedureScheduler;)V
      18: return
}
