Compiled from "SystemTableWALEntryFilter.java"
public class org.apache.hadoop.hbase.replication.SystemTableWALEntryFilter implements org.apache.hadoop.hbase.replication.WALEntryFilter {
  public org.apache.hadoop.hbase.replication.SystemTableWALEntryFilter();
    Code:
       0: aload_0
       1: invokespecial #1                  // Method java/lang/Object."<init>":()V
       4: return

  public org.apache.hadoop.hbase.wal.WAL$Entry filter(org.apache.hadoop.hbase.wal.WAL$Entry);
    Code:
       0: aload_1
       1: invokevirtual #2                  // Method org/apache/hadoop/hbase/wal/WAL$Entry.getKey:()Lorg/apache/hadoop/hbase/wal/WALKeyImpl;
       4: invokevirtual #3                  // Method org/apache/hadoop/hbase/wal/WALKeyImpl.getTableName:()Lorg/apache/hadoop/hbase/TableName;
       7: invokevirtual #4                  // Method org/apache/hadoop/hbase/TableName.isSystemTable:()Z
      10: ifeq          15
      13: aconst_null
      14: areturn
      15: aload_1
      16: areturn
}
