Compiled from "TableProcedureInterface.java"
public final class org.apache.hadoop.hbase.master.procedure.TableProcedureInterface$TableOperationType extends java.lang.Enum<org.apache.hadoop.hbase.master.procedure.TableProcedureInterface$TableOperationType> {
  public static final org.apache.hadoop.hbase.master.procedure.TableProcedureInterface$TableOperationType CREATE;

  public static final org.apache.hadoop.hbase.master.procedure.TableProcedureInterface$TableOperationType DELETE;

  public static final org.apache.hadoop.hbase.master.procedure.TableProcedureInterface$TableOperationType DISABLE;

  public static final org.apache.hadoop.hbase.master.procedure.TableProcedureInterface$TableOperationType EDIT;

  public static final org.apache.hadoop.hbase.master.procedure.TableProcedureInterface$TableOperationType ENABLE;

  public static final org.apache.hadoop.hbase.master.procedure.TableProcedureInterface$TableOperationType READ;

  public static final org.apache.hadoop.hbase.master.procedure.TableProcedureInterface$TableOperationType REGION_EDIT;

  public static final org.apache.hadoop.hbase.master.procedure.TableProcedureInterface$TableOperationType REGION_SPLIT;

  public static final org.apache.hadoop.hbase.master.procedure.TableProcedureInterface$TableOperationType REGION_MERGE;

  public static final org.apache.hadoop.hbase.master.procedure.TableProcedureInterface$TableOperationType REGION_ASSIGN;

  public static final org.apache.hadoop.hbase.master.procedure.TableProcedureInterface$TableOperationType REGION_UNASSIGN;

  public static final org.apache.hadoop.hbase.master.procedure.TableProcedureInterface$TableOperationType REGION_GC;

  public static final org.apache.hadoop.hbase.master.procedure.TableProcedureInterface$TableOperationType MERGED_REGIONS_GC;

  public static org.apache.hadoop.hbase.master.procedure.TableProcedureInterface$TableOperationType[] values();
    Code:
       0: getstatic     #1                  // Field $VALUES:[Lorg/apache/hadoop/hbase/master/procedure/TableProcedureInterface$TableOperationType;
       3: invokevirtual #2                  // Method "[Lorg/apache/hadoop/hbase/master/procedure/TableProcedureInterface$TableOperationType;".clone:()Ljava/lang/Object;
       6: checkcast     #3                  // class "[Lorg/apache/hadoop/hbase/master/procedure/TableProcedureInterface$TableOperationType;"
       9: areturn

  public static org.apache.hadoop.hbase.master.procedure.TableProcedureInterface$TableOperationType valueOf(java.lang.String);
    Code:
       0: ldc           #4                  // class org/apache/hadoop/hbase/master/procedure/TableProcedureInterface$TableOperationType
       2: aload_0
       3: invokestatic  #5                  // Method java/lang/Enum.valueOf:(Ljava/lang/Class;Ljava/lang/String;)Ljava/lang/Enum;
       6: checkcast     #4                  // class org/apache/hadoop/hbase/master/procedure/TableProcedureInterface$TableOperationType
       9: areturn

  static {};
    Code:
       0: new           #4                  // class org/apache/hadoop/hbase/master/procedure/TableProcedureInterface$TableOperationType
       3: dup
       4: ldc           #7                  // String CREATE
       6: iconst_0
       7: invokespecial #8                  // Method "<init>":(Ljava/lang/String;I)V
      10: putstatic     #9                  // Field CREATE:Lorg/apache/hadoop/hbase/master/procedure/TableProcedureInterface$TableOperationType;
      13: new           #4                  // class org/apache/hadoop/hbase/master/procedure/TableProcedureInterface$TableOperationType
      16: dup
      17: ldc           #10                 // String DELETE
      19: iconst_1
      20: invokespecial #8                  // Method "<init>":(Ljava/lang/String;I)V
      23: putstatic     #11                 // Field DELETE:Lorg/apache/hadoop/hbase/master/procedure/TableProcedureInterface$TableOperationType;
      26: new           #4                  // class org/apache/hadoop/hbase/master/procedure/TableProcedureInterface$TableOperationType
      29: dup
      30: ldc           #12                 // String DISABLE
      32: iconst_2
      33: invokespecial #8                  // Method "<init>":(Ljava/lang/String;I)V
      36: putstatic     #13                 // Field DISABLE:Lorg/apache/hadoop/hbase/master/procedure/TableProcedureInterface$TableOperationType;
      39: new           #4                  // class org/apache/hadoop/hbase/master/procedure/TableProcedureInterface$TableOperationType
      42: dup
      43: ldc           #14                 // String EDIT
      45: iconst_3
      46: invokespecial #8                  // Method "<init>":(Ljava/lang/String;I)V
      49: putstatic     #15                 // Field EDIT:Lorg/apache/hadoop/hbase/master/procedure/TableProcedureInterface$TableOperationType;
      52: new           #4                  // class org/apache/hadoop/hbase/master/procedure/TableProcedureInterface$TableOperationType
      55: dup
      56: ldc           #16                 // String ENABLE
      58: iconst_4
      59: invokespecial #8                  // Method "<init>":(Ljava/lang/String;I)V
      62: putstatic     #17                 // Field ENABLE:Lorg/apache/hadoop/hbase/master/procedure/TableProcedureInterface$TableOperationType;
      65: new           #4                  // class org/apache/hadoop/hbase/master/procedure/TableProcedureInterface$TableOperationType
      68: dup
      69: ldc           #18                 // String READ
      71: iconst_5
      72: invokespecial #8                  // Method "<init>":(Ljava/lang/String;I)V
      75: putstatic     #19                 // Field READ:Lorg/apache/hadoop/hbase/master/procedure/TableProcedureInterface$TableOperationType;
      78: new           #4                  // class org/apache/hadoop/hbase/master/procedure/TableProcedureInterface$TableOperationType
      81: dup
      82: ldc           #20                 // String REGION_EDIT
      84: bipush        6
      86: invokespecial #8                  // Method "<init>":(Ljava/lang/String;I)V
      89: putstatic     #21                 // Field REGION_EDIT:Lorg/apache/hadoop/hbase/master/procedure/TableProcedureInterface$TableOperationType;
      92: new           #4                  // class org/apache/hadoop/hbase/master/procedure/TableProcedureInterface$TableOperationType
      95: dup
      96: ldc           #22                 // String REGION_SPLIT
      98: bipush        7
     100: invokespecial #8                  // Method "<init>":(Ljava/lang/String;I)V
     103: putstatic     #23                 // Field REGION_SPLIT:Lorg/apache/hadoop/hbase/master/procedure/TableProcedureInterface$TableOperationType;
     106: new           #4                  // class org/apache/hadoop/hbase/master/procedure/TableProcedureInterface$TableOperationType
     109: dup
     110: ldc           #24                 // String REGION_MERGE
     112: bipush        8
     114: invokespecial #8                  // Method "<init>":(Ljava/lang/String;I)V
     117: putstatic     #25                 // Field REGION_MERGE:Lorg/apache/hadoop/hbase/master/procedure/TableProcedureInterface$TableOperationType;
     120: new           #4                  // class org/apache/hadoop/hbase/master/procedure/TableProcedureInterface$TableOperationType
     123: dup
     124: ldc           #26                 // String REGION_ASSIGN
     126: bipush        9
     128: invokespecial #8                  // Method "<init>":(Ljava/lang/String;I)V
     131: putstatic     #27                 // Field REGION_ASSIGN:Lorg/apache/hadoop/hbase/master/procedure/TableProcedureInterface$TableOperationType;
     134: new           #4                  // class org/apache/hadoop/hbase/master/procedure/TableProcedureInterface$TableOperationType
     137: dup
     138: ldc           #28                 // String REGION_UNASSIGN
     140: bipush        10
     142: invokespecial #8                  // Method "<init>":(Ljava/lang/String;I)V
     145: putstatic     #29                 // Field REGION_UNASSIGN:Lorg/apache/hadoop/hbase/master/procedure/TableProcedureInterface$TableOperationType;
     148: new           #4                  // class org/apache/hadoop/hbase/master/procedure/TableProcedureInterface$TableOperationType
     151: dup
     152: ldc           #30                 // String REGION_GC
     154: bipush        11
     156: invokespecial #8                  // Method "<init>":(Ljava/lang/String;I)V
     159: putstatic     #31                 // Field REGION_GC:Lorg/apache/hadoop/hbase/master/procedure/TableProcedureInterface$TableOperationType;
     162: new           #4                  // class org/apache/hadoop/hbase/master/procedure/TableProcedureInterface$TableOperationType
     165: dup
     166: ldc           #32                 // String MERGED_REGIONS_GC
     168: bipush        12
     170: invokespecial #8                  // Method "<init>":(Ljava/lang/String;I)V
     173: putstatic     #33                 // Field MERGED_REGIONS_GC:Lorg/apache/hadoop/hbase/master/procedure/TableProcedureInterface$TableOperationType;
     176: bipush        13
     178: anewarray     #4                  // class org/apache/hadoop/hbase/master/procedure/TableProcedureInterface$TableOperationType
     181: dup
     182: iconst_0
     183: getstatic     #9                  // Field CREATE:Lorg/apache/hadoop/hbase/master/procedure/TableProcedureInterface$TableOperationType;
     186: aastore
     187: dup
     188: iconst_1
     189: getstatic     #11                 // Field DELETE:Lorg/apache/hadoop/hbase/master/procedure/TableProcedureInterface$TableOperationType;
     192: aastore
     193: dup
     194: iconst_2
     195: getstatic     #13                 // Field DISABLE:Lorg/apache/hadoop/hbase/master/procedure/TableProcedureInterface$TableOperationType;
     198: aastore
     199: dup
     200: iconst_3
     201: getstatic     #15                 // Field EDIT:Lorg/apache/hadoop/hbase/master/procedure/TableProcedureInterface$TableOperationType;
     204: aastore
     205: dup
     206: iconst_4
     207: getstatic     #17                 // Field ENABLE:Lorg/apache/hadoop/hbase/master/procedure/TableProcedureInterface$TableOperationType;
     210: aastore
     211: dup
     212: iconst_5
     213: getstatic     #19                 // Field READ:Lorg/apache/hadoop/hbase/master/procedure/TableProcedureInterface$TableOperationType;
     216: aastore
     217: dup
     218: bipush        6
     220: getstatic     #21                 // Field REGION_EDIT:Lorg/apache/hadoop/hbase/master/procedure/TableProcedureInterface$TableOperationType;
     223: aastore
     224: dup
     225: bipush        7
     227: getstatic     #23                 // Field REGION_SPLIT:Lorg/apache/hadoop/hbase/master/procedure/TableProcedureInterface$TableOperationType;
     230: aastore
     231: dup
     232: bipush        8
     234: getstatic     #25                 // Field REGION_MERGE:Lorg/apache/hadoop/hbase/master/procedure/TableProcedureInterface$TableOperationType;
     237: aastore
     238: dup
     239: bipush        9
     241: getstatic     #27                 // Field REGION_ASSIGN:Lorg/apache/hadoop/hbase/master/procedure/TableProcedureInterface$TableOperationType;
     244: aastore
     245: dup
     246: bipush        10
     248: getstatic     #29                 // Field REGION_UNASSIGN:Lorg/apache/hadoop/hbase/master/procedure/TableProcedureInterface$TableOperationType;
     251: aastore
     252: dup
     253: bipush        11
     255: getstatic     #31                 // Field REGION_GC:Lorg/apache/hadoop/hbase/master/procedure/TableProcedureInterface$TableOperationType;
     258: aastore
     259: dup
     260: bipush        12
     262: getstatic     #33                 // Field MERGED_REGIONS_GC:Lorg/apache/hadoop/hbase/master/procedure/TableProcedureInterface$TableOperationType;
     265: aastore
     266: putstatic     #1                  // Field $VALUES:[Lorg/apache/hadoop/hbase/master/procedure/TableProcedureInterface$TableOperationType;
     269: return
}
