Compiled from "TableNotFoundException.java"
public class org.apache.hadoop.hbase.TableNotFoundException extends org.apache.hadoop.hbase.DoNotRetryIOException {
  public org.apache.hadoop.hbase.TableNotFoundException();
    Code:
       0: aload_0
       1: invokespecial #1                  // Method org/apache/hadoop/hbase/DoNotRetryIOException."<init>":()V
       4: return

  public org.apache.hadoop.hbase.TableNotFoundException(java.lang.String);
    Code:
       0: aload_0
       1: aload_1
       2: invokespecial #2                  // Method org/apache/hadoop/hbase/DoNotRetryIOException."<init>":(Ljava/lang/String;)V
       5: return

  public org.apache.hadoop.hbase.TableNotFoundException(byte[]);
    Code:
       0: aload_0
       1: aload_1
       2: invokestatic  #3                  // Method org/apache/hadoop/hbase/util/Bytes.toString:([B)Ljava/lang/String;
       5: invokespecial #2                  // Method org/apache/hadoop/hbase/DoNotRetryIOException."<init>":(Ljava/lang/String;)V
       8: return

  public org.apache.hadoop.hbase.TableNotFoundException(org.apache.hadoop.hbase.TableName);
    Code:
       0: aload_0
       1: aload_1
       2: invokevirtual #4                  // Method org/apache/hadoop/hbase/TableName.getNameAsString:()Ljava/lang/String;
       5: invokespecial #2                  // Method org/apache/hadoop/hbase/DoNotRetryIOException."<init>":(Ljava/lang/String;)V
       8: return
}
