Compiled from "TableQueue.java"
class org.apache.hadoop.hbase.master.procedure.TableQueue extends org.apache.hadoop.hbase.master.procedure.Queue<org.apache.hadoop.hbase.TableName> {
  public org.apache.hadoop.hbase.master.procedure.TableQueue(org.apache.hadoop.hbase.TableName, int, org.apache.hadoop.hbase.procedure2.LockStatus, org.apache.hadoop.hbase.procedure2.LockStatus);
    Code:
       0: aload_0
       1: aload_1
       2: iload_2
       3: aload_3
       4: invokespecial #1                  // Method org/apache/hadoop/hbase/master/procedure/Queue."<init>":(Ljava/lang/Comparable;ILorg/apache/hadoop/hbase/procedure2/LockStatus;)V
       7: aload_0
       8: aload         4
      10: putfield      #2                  // Field namespaceLockStatus:Lorg/apache/hadoop/hbase/procedure2/LockStatus;
      13: return

  public boolean isAvailable();
    Code:
       0: aload_0
       1: invokevirtual #3                  // Method isEmpty:()Z
       4: ifne          23
       7: aload_0
       8: getfield      #2                  // Field namespaceLockStatus:Lorg/apache/hadoop/hbase/procedure2/LockStatus;
      11: invokeinterface #4,  1            // InterfaceMethod org/apache/hadoop/hbase/procedure2/LockStatus.hasExclusiveLock:()Z
      16: ifne          23
      19: iconst_1
      20: goto          24
      23: iconst_0
      24: ireturn

  public boolean requireExclusiveLock(org.apache.hadoop.hbase.procedure2.Procedure<?>);
    Code:
       0: aload_1
       1: checkcast     #5                  // class org/apache/hadoop/hbase/master/procedure/TableProcedureInterface
       4: invokestatic  #6                  // Method requireTableExclusiveLock:(Lorg/apache/hadoop/hbase/master/procedure/TableProcedureInterface;)Z
       7: ireturn
}
