Compiled from "TableStateManager.java"
class org.apache.hadoop.hbase.master.TableStateManager$2 implements org.apache.hadoop.hbase.MetaTableAccessor$Visitor {
  final java.util.Map val$states;

  final org.apache.hadoop.hbase.master.TableStateManager this$0;

  org.apache.hadoop.hbase.master.TableStateManager$2(org.apache.hadoop.hbase.master.TableStateManager, java.util.Map);
    Code:
       0: aload_0
       1: aload_1
       2: putfield      #1                  // Field this$0:Lorg/apache/hadoop/hbase/master/TableStateManager;
       5: aload_0
       6: aload_2
       7: putfield      #2                  // Field val$states:Ljava/util/Map;
      10: aload_0
      11: invokespecial #3                  // Method java/lang/Object."<init>":()V
      14: return

  public boolean visit(org.apache.hadoop.hbase.client.Result) throws java.io.IOException;
    Code:
       0: aload_1
       1: invokestatic  #4                  // Method org/apache/hadoop/hbase/MetaTableAccessor.getTableState:(Lorg/apache/hadoop/hbase/client/Result;)Lorg/apache/hadoop/hbase/client/TableState;
       4: astore_2
       5: aload_0
       6: getfield      #2                  // Field val$states:Ljava/util/Map;
       9: aload_2
      10: invokevirtual #5                  // Method org/apache/hadoop/hbase/client/TableState.getTableName:()Lorg/apache/hadoop/hbase/TableName;
      13: invokevirtual #6                  // Method org/apache/hadoop/hbase/TableName.getNameAsString:()Ljava/lang/String;
      16: aload_2
      17: invokeinterface #7,  3            // InterfaceMethod java/util/Map.put:(Ljava/lang/Object;Ljava/lang/Object;)Ljava/lang/Object;
      22: pop
      23: iconst_1
      24: ireturn
}
