Compiled from "TablePartiallyOpenException.java"
public class org.apache.hadoop.hbase.snapshot.TablePartiallyOpenException extends java.io.IOException {
  public org.apache.hadoop.hbase.snapshot.TablePartiallyOpenException();
    Code:
       0: aload_0
       1: invokespecial #1                  // Method java/io/IOException."<init>":()V
       4: return

  public org.apache.hadoop.hbase.snapshot.TablePartiallyOpenException(java.lang.String);
    Code:
       0: aload_0
       1: aload_1
       2: invokespecial #2                  // Method java/io/IOException."<init>":(Ljava/lang/String;)V
       5: return

  public org.apache.hadoop.hbase.snapshot.TablePartiallyOpenException(org.apache.hadoop.hbase.TableName);
    Code:
       0: aload_0
       1: aload_1
       2: invokevirtual #3                  // Method org/apache/hadoop/hbase/TableName.getNameAsString:()Ljava/lang/String;
       5: invokespecial #4                  // Method "<init>":(Ljava/lang/String;)V
       8: return

  public org.apache.hadoop.hbase.snapshot.TablePartiallyOpenException(byte[]);
    Code:
       0: aload_0
       1: aload_1
       2: invokestatic  #5                  // Method org/apache/hadoop/hbase/util/Bytes.toString:([B)Ljava/lang/String;
       5: invokespecial #4                  // Method "<init>":(Ljava/lang/String;)V
       8: return
}
