Compiled from "TableCFs.java"
public class org.apache.hadoop.hbase.client.replication.TableCFs {
  public org.apache.hadoop.hbase.client.replication.TableCFs(org.apache.hadoop.hbase.TableName, java.util.Map<java.lang.String, java.lang.Integer>);
    Code:
       0: aload_0
       1: invokespecial #1                  // Method java/lang/Object."<init>":()V
       4: aload_0
       5: aload_1
       6: putfield      #2                  // Field table:Lorg/apache/hadoop/hbase/TableName;
       9: aload_0
      10: aload_2
      11: putfield      #3                  // Field cfs:Ljava/util/Map;
      14: return

  public org.apache.hadoop.hbase.TableName getTable();
    Code:
       0: aload_0
       1: getfield      #2                  // Field table:Lorg/apache/hadoop/hbase/TableName;
       4: areturn

  public java.util.Map<java.lang.String, java.lang.Integer> getColumnFamilyMap();
    Code:
       0: aload_0
       1: getfield      #3                  // Field cfs:Ljava/util/Map;
       4: areturn

  public java.lang.String toString();
    Code:
       0: new           #4                  // class java/lang/StringBuilder
       3: dup
       4: invokespecial #5                  // Method java/lang/StringBuilder."<init>":()V
       7: astore_1
       8: aload_1
       9: aload_0
      10: getfield      #2                  // Field table:Lorg/apache/hadoop/hbase/TableName;
      13: invokevirtual #6                  // Method org/apache/hadoop/hbase/TableName.getNameAsString:()Ljava/lang/String;
      16: invokevirtual #7                  // Method java/lang/StringBuilder.append:(Ljava/lang/String;)Ljava/lang/StringBuilder;
      19: pop
      20: aload_0
      21: getfield      #3                  // Field cfs:Ljava/util/Map;
      24: invokeinterface #8,  1            // InterfaceMethod java/util/Map.isEmpty:()Z
      29: ifne          58
      32: aload_1
      33: ldc           #9                  // String :
      35: invokevirtual #7                  // Method java/lang/StringBuilder.append:(Ljava/lang/String;)Ljava/lang/StringBuilder;
      38: pop
      39: aload_1
      40: aload_0
      41: getfield      #3                  // Field cfs:Ljava/util/Map;
      44: invokeinterface #10,  1           // InterfaceMethod java/util/Map.keySet:()Ljava/util/Set;
      49: bipush        44
      51: invokestatic  #11                 // Method org/apache/commons/lang3/StringUtils.join:(Ljava/lang/Iterable;C)Ljava/lang/String;
      54: invokevirtual #7                  // Method java/lang/StringBuilder.append:(Ljava/lang/String;)Ljava/lang/StringBuilder;
      57: pop
      58: aload_1
      59: invokevirtual #12                 // Method java/lang/StringBuilder.toString:()Ljava/lang/String;
      62: areturn
}
