Compiled from "TablePermission.java"
public class org.apache.hadoop.hbase.security.access.TablePermission extends org.apache.hadoop.hbase.security.access.Permission {
  org.apache.hadoop.hbase.security.access.TablePermission(org.apache.hadoop.hbase.TableName, byte[], byte[], org.apache.hadoop.hbase.security.access.Permission$Action...);
    Code:
       0: aload_0
       1: aload         4
       3: invokespecial #1                  // Method org/apache/hadoop/hbase/security/access/Permission."<init>":([Lorg/apache/hadoop/hbase/security/access/Permission$Action;)V
       6: aload_0
       7: aload_1
       8: putfield      #2                  // Field table:Lorg/apache/hadoop/hbase/TableName;
      11: aload_0
      12: aload_2
      13: putfield      #3                  // Field family:[B
      16: aload_0
      17: aload_3
      18: putfield      #4                  // Field qualifier:[B
      21: aload_0
      22: getstatic     #5                  // Field org/apache/hadoop/hbase/security/access/Permission$Scope.TABLE:Lorg/apache/hadoop/hbase/security/access/Permission$Scope;
      25: putfield      #6                  // Field scope:Lorg/apache/hadoop/hbase/security/access/Permission$Scope;
      28: return

  public org.apache.hadoop.hbase.TableName getTableName();
    Code:
       0: aload_0
       1: getfield      #2                  // Field table:Lorg/apache/hadoop/hbase/TableName;
       4: areturn

  public boolean hasFamily();
    Code:
       0: aload_0
       1: getfield      #3                  // Field family:[B
       4: ifnull        11
       7: iconst_1
       8: goto          12
      11: iconst_0
      12: ireturn

  public byte[] getFamily();
    Code:
       0: aload_0
       1: getfield      #3                  // Field family:[B
       4: areturn

  public boolean hasQualifier();
    Code:
       0: aload_0
       1: getfield      #4                  // Field qualifier:[B
       4: ifnull        11
       7: iconst_1
       8: goto          12
      11: iconst_0
      12: ireturn

  public byte[] getQualifier();
    Code:
       0: aload_0
       1: getfield      #4                  // Field qualifier:[B
       4: areturn

  public java.lang.String getNamespace();
    Code:
       0: aload_0
       1: getfield      #2                  // Field table:Lorg/apache/hadoop/hbase/TableName;
       4: invokevirtual #7                  // Method org/apache/hadoop/hbase/TableName.getNamespaceAsString:()Ljava/lang/String;
       7: areturn

  public boolean implies(org.apache.hadoop.hbase.TableName, byte[], byte[], org.apache.hadoop.hbase.security.access.Permission$Action);
    Code:
       0: aload_0
       1: aload_1
       2: invokespecial #8                  // Method failCheckTable:(Lorg/apache/hadoop/hbase/TableName;)Z
       5: ifeq          10
       8: iconst_0
       9: ireturn
      10: aload_0
      11: aload_2
      12: invokespecial #9                  // Method failCheckFamily:([B)Z
      15: ifeq          20
      18: iconst_0
      19: ireturn
      20: aload_0
      21: aload_3
      22: invokespecial #10                 // Method failCheckQualifier:([B)Z
      25: ifeq          30
      28: iconst_0
      29: ireturn
      30: aload_0
      31: aload         4
      33: invokevirtual #11                 // Method implies:(Lorg/apache/hadoop/hbase/security/access/Permission$Action;)Z
      36: ireturn

  public boolean implies(org.apache.hadoop.hbase.TableName, byte[], org.apache.hadoop.hbase.security.access.Permission$Action);
    Code:
       0: aload_0
       1: aload_1
       2: invokespecial #8                  // Method failCheckTable:(Lorg/apache/hadoop/hbase/TableName;)Z
       5: ifeq          10
       8: iconst_0
       9: ireturn
      10: aload_0
      11: aload_2
      12: invokespecial #9                  // Method failCheckFamily:([B)Z
      15: ifeq          20
      18: iconst_0
      19: ireturn
      20: aload_0
      21: aload_3
      22: invokevirtual #11                 // Method implies:(Lorg/apache/hadoop/hbase/security/access/Permission$Action;)Z
      25: ireturn

  public boolean implies(org.apache.hadoop.hbase.TableName, org.apache.hadoop.hbase.KeyValue, org.apache.hadoop.hbase.security.access.Permission$Action);
    Code:
       0: aload_0
       1: aload_1
       2: invokespecial #8                  // Method failCheckTable:(Lorg/apache/hadoop/hbase/TableName;)Z
       5: ifeq          10
       8: iconst_0
       9: ireturn
      10: aload_0
      11: getfield      #3                  // Field family:[B
      14: ifnull        30
      17: aload_2
      18: aload_0
      19: getfield      #3                  // Field family:[B
      22: invokestatic  #14                 // Method org/apache/hadoop/hbase/CellUtil.matchingFamily:(Lorg/apache/hadoop/hbase/Cell;[B)Z
      25: ifne          30
      28: iconst_0
      29: ireturn
      30: aload_0
      31: getfield      #4                  // Field qualifier:[B
      34: ifnull        50
      37: aload_2
      38: aload_0
      39: getfield      #4                  // Field qualifier:[B
      42: invokestatic  #15                 // Method org/apache/hadoop/hbase/CellUtil.matchingQualifier:(Lorg/apache/hadoop/hbase/Cell;[B)Z
      45: ifne          50
      48: iconst_0
      49: ireturn
      50: aload_0
      51: aload_3
      52: invokespecial #16                 // Method org/apache/hadoop/hbase/security/access/Permission.implies:(Lorg/apache/hadoop/hbase/security/access/Permission$Action;)Z
      55: ireturn

  public boolean tableFieldsEqual(org.apache.hadoop.hbase.security.access.TablePermission);
    Code:
       0: aload_1
       1: ifnonnull     6
       4: iconst_0
       5: ireturn
       6: aload_0
       7: getfield      #2                  // Field table:Lorg/apache/hadoop/hbase/TableName;
      10: ifnonnull     20
      13: aload_1
      14: getfield      #2                  // Field table:Lorg/apache/hadoop/hbase/TableName;
      17: ifnull        41
      20: aload_0
      21: getfield      #2                  // Field table:Lorg/apache/hadoop/hbase/TableName;
      24: ifnull        45
      27: aload_0
      28: getfield      #2                  // Field table:Lorg/apache/hadoop/hbase/TableName;
      31: aload_1
      32: getfield      #2                  // Field table:Lorg/apache/hadoop/hbase/TableName;
      35: invokevirtual #12                 // Method org/apache/hadoop/hbase/TableName.equals:(Ljava/lang/Object;)Z
      38: ifeq          45
      41: iconst_1
      42: goto          46
      45: iconst_0
      46: istore_2
      47: aload_0
      48: getfield      #3                  // Field family:[B
      51: ifnonnull     61
      54: aload_1
      55: getfield      #3                  // Field family:[B
      58: ifnull        75
      61: aload_0
      62: getfield      #3                  // Field family:[B
      65: aload_1
      66: getfield      #3                  // Field family:[B
      69: invokestatic  #13                 // Method org/apache/hadoop/hbase/util/Bytes.equals:([B[B)Z
      72: ifeq          79
      75: iconst_1
      76: goto          80
      79: iconst_0
      80: istore_3
      81: aload_0
      82: getfield      #4                  // Field qualifier:[B
      85: ifnonnull     95
      88: aload_1
      89: getfield      #4                  // Field qualifier:[B
      92: ifnull        109
      95: aload_0
      96: getfield      #4                  // Field qualifier:[B
      99: aload_1
     100: getfield      #4                  // Field qualifier:[B
     103: invokestatic  #13                 // Method org/apache/hadoop/hbase/util/Bytes.equals:([B[B)Z
     106: ifeq          113
     109: iconst_1
     110: goto          114
     113: iconst_0
     114: istore        4
     116: iload_2
     117: ifeq          133
     120: iload_3
     121: ifeq          133
     124: iload         4
     126: ifeq          133
     129: iconst_1
     130: goto          134
     133: iconst_0
     134: ireturn

  public boolean equalsExceptActions(java.lang.Object);
    Code:
       0: aload_1
       1: instanceof    #17                 // class org/apache/hadoop/hbase/security/access/TablePermission
       4: ifne          9
       7: iconst_0
       8: ireturn
       9: aload_1
      10: checkcast     #17                 // class org/apache/hadoop/hbase/security/access/TablePermission
      13: astore_2
      14: aload_0
      15: aload_2
      16: invokevirtual #18                 // Method tableFieldsEqual:(Lorg/apache/hadoop/hbase/security/access/TablePermission;)Z
      19: ireturn

  public boolean equals(java.lang.Object);
    Code:
       0: aload_0
       1: aload_1
       2: invokevirtual #19                 // Method equalsExceptActions:(Ljava/lang/Object;)Z
       5: ifeq          20
       8: aload_0
       9: aload_1
      10: invokespecial #20                 // Method org/apache/hadoop/hbase/security/access/Permission.equals:(Ljava/lang/Object;)Z
      13: ifeq          20
      16: iconst_1
      17: goto          21
      20: iconst_0
      21: ireturn

  public int hashCode();
    Code:
       0: bipush        37
       2: istore_1
       3: aload_0
       4: invokespecial #21                 // Method org/apache/hadoop/hbase/security/access/Permission.hashCode:()I
       7: istore_2
       8: aload_0
       9: getfield      #2                  // Field table:Lorg/apache/hadoop/hbase/TableName;
      12: ifnull        28
      15: bipush        37
      17: iload_2
      18: imul
      19: aload_0
      20: getfield      #2                  // Field table:Lorg/apache/hadoop/hbase/TableName;
      23: invokevirtual #22                 // Method org/apache/hadoop/hbase/TableName.hashCode:()I
      26: iadd
      27: istore_2
      28: aload_0
      29: getfield      #3                  // Field family:[B
      32: ifnull        48
      35: bipush        37
      37: iload_2
      38: imul
      39: aload_0
      40: getfield      #3                  // Field family:[B
      43: invokestatic  #23                 // Method org/apache/hadoop/hbase/util/Bytes.hashCode:([B)I
      46: iadd
      47: istore_2
      48: aload_0
      49: getfield      #4                  // Field qualifier:[B
      52: ifnull        68
      55: bipush        37
      57: iload_2
      58: imul
      59: aload_0
      60: getfield      #4                  // Field qualifier:[B
      63: invokestatic  #23                 // Method org/apache/hadoop/hbase/util/Bytes.hashCode:([B)I
      66: iadd
      67: istore_2
      68: iload_2
      69: ireturn

  public java.lang.String toString();
    Code:
       0: new           #24                 // class java/lang/StringBuilder
       3: dup
       4: invokespecial #25                 // Method java/lang/StringBuilder."<init>":()V
       7: ldc           #26                 // String [TablePermission:
       9: invokevirtual #27                 // Method java/lang/StringBuilder.append:(Ljava/lang/String;)Ljava/lang/StringBuilder;
      12: aload_0
      13: invokevirtual #28                 // Method rawExpression:()Ljava/lang/String;
      16: invokevirtual #27                 // Method java/lang/StringBuilder.append:(Ljava/lang/String;)Ljava/lang/StringBuilder;
      19: ldc           #29                 // String ]
      21: invokevirtual #27                 // Method java/lang/StringBuilder.append:(Ljava/lang/String;)Ljava/lang/StringBuilder;
      24: invokevirtual #30                 // Method java/lang/StringBuilder.toString:()Ljava/lang/String;
      27: areturn

  protected java.lang.String rawExpression();
    Code:
       0: new           #24                 // class java/lang/StringBuilder
       3: dup
       4: invokespecial #25                 // Method java/lang/StringBuilder."<init>":()V
       7: astore_1
       8: aload_0
       9: getfield      #2                  // Field table:Lorg/apache/hadoop/hbase/TableName;
      12: ifnull        86
      15: aload_1
      16: ldc           #31                 // String table=
      18: invokevirtual #27                 // Method java/lang/StringBuilder.append:(Ljava/lang/String;)Ljava/lang/StringBuilder;
      21: aload_0
      22: getfield      #2                  // Field table:Lorg/apache/hadoop/hbase/TableName;
      25: invokevirtual #32                 // Method java/lang/StringBuilder.append:(Ljava/lang/Object;)Ljava/lang/StringBuilder;
      28: ldc           #33                 // String , family=
      30: invokevirtual #27                 // Method java/lang/StringBuilder.append:(Ljava/lang/String;)Ljava/lang/StringBuilder;
      33: aload_0
      34: getfield      #3                  // Field family:[B
      37: ifnonnull     44
      40: aconst_null
      41: goto          51
      44: aload_0
      45: getfield      #3                  // Field family:[B
      48: invokestatic  #34                 // Method org/apache/hadoop/hbase/util/Bytes.toString:([B)Ljava/lang/String;
      51: invokevirtual #27                 // Method java/lang/StringBuilder.append:(Ljava/lang/String;)Ljava/lang/StringBuilder;
      54: ldc           #35                 // String , qualifier=
      56: invokevirtual #27                 // Method java/lang/StringBuilder.append:(Ljava/lang/String;)Ljava/lang/StringBuilder;
      59: aload_0
      60: getfield      #4                  // Field qualifier:[B
      63: ifnonnull     70
      66: aconst_null
      67: goto          77
      70: aload_0
      71: getfield      #4                  // Field qualifier:[B
      74: invokestatic  #34                 // Method org/apache/hadoop/hbase/util/Bytes.toString:([B)Ljava/lang/String;
      77: invokevirtual #27                 // Method java/lang/StringBuilder.append:(Ljava/lang/String;)Ljava/lang/StringBuilder;
      80: ldc           #36                 // String ,
      82: invokevirtual #27                 // Method java/lang/StringBuilder.append:(Ljava/lang/String;)Ljava/lang/StringBuilder;
      85: pop
      86: new           #24                 // class java/lang/StringBuilder
      89: dup
      90: invokespecial #25                 // Method java/lang/StringBuilder."<init>":()V
      93: aload_1
      94: invokevirtual #30                 // Method java/lang/StringBuilder.toString:()Ljava/lang/String;
      97: invokevirtual #27                 // Method java/lang/StringBuilder.append:(Ljava/lang/String;)Ljava/lang/StringBuilder;
     100: aload_0
     101: invokespecial #37                 // Method org/apache/hadoop/hbase/security/access/Permission.rawExpression:()Ljava/lang/String;
     104: invokevirtual #27                 // Method java/lang/StringBuilder.append:(Ljava/lang/String;)Ljava/lang/StringBuilder;
     107: invokevirtual #30                 // Method java/lang/StringBuilder.toString:()Ljava/lang/String;
     110: areturn

  public void readFields(java.io.DataInput) throws java.io.IOException;
    Code:
       0: aload_0
       1: aload_1
       2: invokespecial #38                 // Method org/apache/hadoop/hbase/security/access/Permission.readFields:(Ljava/io/DataInput;)V
       5: aload_1
       6: invokestatic  #39                 // Method org/apache/hadoop/hbase/util/Bytes.readByteArray:(Ljava/io/DataInput;)[B
       9: astore_2
      10: aload_2
      11: arraylength
      12: ifle          23
      15: aload_0
      16: aload_2
      17: invokestatic  #40                 // Method org/apache/hadoop/hbase/TableName.valueOf:([B)Lorg/apache/hadoop/hbase/TableName;
      20: putfield      #2                  // Field table:Lorg/apache/hadoop/hbase/TableName;
      23: aload_1
      24: invokeinterface #41,  1           // InterfaceMethod java/io/DataInput.readBoolean:()Z
      29: ifeq          40
      32: aload_0
      33: aload_1
      34: invokestatic  #39                 // Method org/apache/hadoop/hbase/util/Bytes.readByteArray:(Ljava/io/DataInput;)[B
      37: putfield      #3                  // Field family:[B
      40: aload_1
      41: invokeinterface #41,  1           // InterfaceMethod java/io/DataInput.readBoolean:()Z
      46: ifeq          57
      49: aload_0
      50: aload_1
      51: invokestatic  #39                 // Method org/apache/hadoop/hbase/util/Bytes.readByteArray:(Ljava/io/DataInput;)[B
      54: putfield      #4                  // Field qualifier:[B
      57: return

  public void write(java.io.DataOutput) throws java.io.IOException;
    Code:
       0: aload_0
       1: aload_1
       2: invokespecial #42                 // Method org/apache/hadoop/hbase/security/access/Permission.write:(Ljava/io/DataOutput;)V
       5: aload_1
       6: aload_0
       7: getfield      #2                  // Field table:Lorg/apache/hadoop/hbase/TableName;
      10: ifnonnull     17
      13: aconst_null
      14: goto          24
      17: aload_0
      18: getfield      #2                  // Field table:Lorg/apache/hadoop/hbase/TableName;
      21: invokevirtual #43                 // Method org/apache/hadoop/hbase/TableName.getName:()[B
      24: invokestatic  #44                 // Method org/apache/hadoop/hbase/util/Bytes.writeByteArray:(Ljava/io/DataOutput;[B)V
      27: aload_1
      28: aload_0
      29: getfield      #3                  // Field family:[B
      32: ifnull        39
      35: iconst_1
      36: goto          40
      39: iconst_0
      40: invokeinterface #45,  2           // InterfaceMethod java/io/DataOutput.writeBoolean:(Z)V
      45: aload_0
      46: getfield      #3                  // Field family:[B
      49: ifnull        60
      52: aload_1
      53: aload_0
      54: getfield      #3                  // Field family:[B
      57: invokestatic  #44                 // Method org/apache/hadoop/hbase/util/Bytes.writeByteArray:(Ljava/io/DataOutput;[B)V
      60: aload_1
      61: aload_0
      62: getfield      #4                  // Field qualifier:[B
      65: ifnull        72
      68: iconst_1
      69: goto          73
      72: iconst_0
      73: invokeinterface #45,  2           // InterfaceMethod java/io/DataOutput.writeBoolean:(Z)V
      78: aload_0
      79: getfield      #4                  // Field qualifier:[B
      82: ifnull        93
      85: aload_1
      86: aload_0
      87: getfield      #4                  // Field qualifier:[B
      90: invokestatic  #44                 // Method org/apache/hadoop/hbase/util/Bytes.writeByteArray:(Ljava/io/DataOutput;[B)V
      93: return
}
