Compiled from "TableStateManager.java"
public class org.apache.hadoop.hbase.master.TableStateManager {
  protected final org.apache.hadoop.hbase.master.MasterServices master;

  public org.apache.hadoop.hbase.master.TableStateManager(org.apache.hadoop.hbase.master.MasterServices);
    Code:
       0: aload_0
       1: invokespecial #1                  // Method java/lang/Object."<init>":()V
       4: aload_0
       5: new           #2                  // class org/apache/hadoop/hbase/util/IdReadWriteLock
       8: dup
       9: invokespecial #3                  // Method org/apache/hadoop/hbase/util/IdReadWriteLock."<init>":()V
      12: putfield      #4                  // Field tnLock:Lorg/apache/hadoop/hbase/util/IdReadWriteLock;
      15: aload_0
      16: new           #5                  // class java/util/concurrent/ConcurrentHashMap
      19: dup
      20: invokespecial #6                  // Method java/util/concurrent/ConcurrentHashMap."<init>":()V
      23: putfield      #7                  // Field tableName2State:Ljava/util/concurrent/ConcurrentMap;
      26: aload_0
      27: aload_1
      28: putfield      #8                  // Field master:Lorg/apache/hadoop/hbase/master/MasterServices;
      31: return

  public void setTableState(org.apache.hadoop.hbase.TableName, org.apache.hadoop.hbase.client.TableState$State) throws java.io.IOException;
    Code:
       0: aload_0
       1: getfield      #4                  // Field tnLock:Lorg/apache/hadoop/hbase/util/IdReadWriteLock;
       4: aload_1
       5: invokevirtual #9                  // Method org/apache/hadoop/hbase/util/IdReadWriteLock.getLock:(Ljava/lang/Object;)Ljava/util/concurrent/locks/ReentrantReadWriteLock;
       8: astore_3
       9: aload_3
      10: invokeinterface #10,  1           // InterfaceMethod java/util/concurrent/locks/ReadWriteLock.writeLock:()Ljava/util/concurrent/locks/Lock;
      15: invokeinterface #11,  1           // InterfaceMethod java/util/concurrent/locks/Lock.lock:()V
      20: aload_0
      21: aload_1
      22: aload_2
      23: invokespecial #12                 // Method updateMetaState:(Lorg/apache/hadoop/hbase/TableName;Lorg/apache/hadoop/hbase/client/TableState$State;)V
      26: aload_3
      27: invokeinterface #10,  1           // InterfaceMethod java/util/concurrent/locks/ReadWriteLock.writeLock:()Ljava/util/concurrent/locks/Lock;
      32: invokeinterface #13,  1           // InterfaceMethod java/util/concurrent/locks/Lock.unlock:()V
      37: goto          56
      40: astore        4
      42: aload_3
      43: invokeinterface #10,  1           // InterfaceMethod java/util/concurrent/locks/ReadWriteLock.writeLock:()Ljava/util/concurrent/locks/Lock;
      48: invokeinterface #13,  1           // InterfaceMethod java/util/concurrent/locks/Lock.unlock:()V
      53: aload         4
      55: athrow
      56: return
    Exception table:
       from    to  target type
          20    26    40   any
          40    42    40   any

  public org.apache.hadoop.hbase.client.TableState setTableStateIfInStates(org.apache.hadoop.hbase.TableName, org.apache.hadoop.hbase.client.TableState$State, org.apache.hadoop.hbase.client.TableState$State...) throws java.io.IOException;
    Code:
       0: aload_0
       1: getfield      #4                  // Field tnLock:Lorg/apache/hadoop/hbase/util/IdReadWriteLock;
       4: aload_1
       5: invokevirtual #9                  // Method org/apache/hadoop/hbase/util/IdReadWriteLock.getLock:(Ljava/lang/Object;)Ljava/util/concurrent/locks/ReentrantReadWriteLock;
       8: astore        4
      10: aload         4
      12: invokeinterface #10,  1           // InterfaceMethod java/util/concurrent/locks/ReadWriteLock.writeLock:()Ljava/util/concurrent/locks/Lock;
      17: invokeinterface #11,  1           // InterfaceMethod java/util/concurrent/locks/Lock.lock:()V
      22: aload_0
      23: aload_1
      24: invokespecial #14                 // Method readMetaState:(Lorg/apache/hadoop/hbase/TableName;)Lorg/apache/hadoop/hbase/client/TableState;
      27: astore        5
      29: aload         5
      31: ifnonnull     43
      34: new           #15                 // class org/apache/hadoop/hbase/TableNotFoundException
      37: dup
      38: aload_1
      39: invokespecial #16                 // Method org/apache/hadoop/hbase/TableNotFoundException."<init>":(Lorg/apache/hadoop/hbase/TableName;)V
      42: athrow
      43: aload         5
      45: aload_3
      46: invokevirtual #17                 // Method org/apache/hadoop/hbase/client/TableState.inStates:([Lorg/apache/hadoop/hbase/client/TableState$State;)Z
      49: ifeq          76
      52: aload_0
      53: aload_1
      54: aload_2
      55: invokespecial #12                 // Method updateMetaState:(Lorg/apache/hadoop/hbase/TableName;Lorg/apache/hadoop/hbase/client/TableState$State;)V
      58: aconst_null
      59: astore        6
      61: aload         4
      63: invokeinterface #10,  1           // InterfaceMethod java/util/concurrent/locks/ReadWriteLock.writeLock:()Ljava/util/concurrent/locks/Lock;
      68: invokeinterface #13,  1           // InterfaceMethod java/util/concurrent/locks/Lock.unlock:()V
      73: aload         6
      75: areturn
      76: aload         5
      78: astore        6
      80: aload         4
      82: invokeinterface #10,  1           // InterfaceMethod java/util/concurrent/locks/ReadWriteLock.writeLock:()Ljava/util/concurrent/locks/Lock;
      87: invokeinterface #13,  1           // InterfaceMethod java/util/concurrent/locks/Lock.unlock:()V
      92: aload         6
      94: areturn
      95: astore        7
      97: aload         4
      99: invokeinterface #10,  1           // InterfaceMethod java/util/concurrent/locks/ReadWriteLock.writeLock:()Ljava/util/concurrent/locks/Lock;
     104: invokeinterface #13,  1           // InterfaceMethod java/util/concurrent/locks/Lock.unlock:()V
     109: aload         7
     111: athrow
    Exception table:
       from    to  target type
          22    61    95   any
          76    80    95   any
          95    97    95   any

  public boolean setTableStateIfNotInStates(org.apache.hadoop.hbase.TableName, org.apache.hadoop.hbase.client.TableState$State, org.apache.hadoop.hbase.client.TableState$State...) throws java.io.IOException;
    Code:
       0: aload_0
       1: getfield      #4                  // Field tnLock:Lorg/apache/hadoop/hbase/util/IdReadWriteLock;
       4: aload_1
       5: invokevirtual #9                  // Method org/apache/hadoop/hbase/util/IdReadWriteLock.getLock:(Ljava/lang/Object;)Ljava/util/concurrent/locks/ReentrantReadWriteLock;
       8: astore        4
      10: aload         4
      12: invokeinterface #10,  1           // InterfaceMethod java/util/concurrent/locks/ReadWriteLock.writeLock:()Ljava/util/concurrent/locks/Lock;
      17: invokeinterface #11,  1           // InterfaceMethod java/util/concurrent/locks/Lock.lock:()V
      22: aload_0
      23: aload_1
      24: invokespecial #14                 // Method readMetaState:(Lorg/apache/hadoop/hbase/TableName;)Lorg/apache/hadoop/hbase/client/TableState;
      27: astore        5
      29: aload         5
      31: ifnonnull     43
      34: new           #15                 // class org/apache/hadoop/hbase/TableNotFoundException
      37: dup
      38: aload_1
      39: invokespecial #16                 // Method org/apache/hadoop/hbase/TableNotFoundException."<init>":(Lorg/apache/hadoop/hbase/TableName;)V
      42: athrow
      43: aload         5
      45: aload_3
      46: invokevirtual #17                 // Method org/apache/hadoop/hbase/client/TableState.inStates:([Lorg/apache/hadoop/hbase/client/TableState$State;)Z
      49: ifne          76
      52: aload_0
      53: aload_1
      54: aload_2
      55: invokespecial #12                 // Method updateMetaState:(Lorg/apache/hadoop/hbase/TableName;Lorg/apache/hadoop/hbase/client/TableState$State;)V
      58: iconst_1
      59: istore        6
      61: aload         4
      63: invokeinterface #10,  1           // InterfaceMethod java/util/concurrent/locks/ReadWriteLock.writeLock:()Ljava/util/concurrent/locks/Lock;
      68: invokeinterface #13,  1           // InterfaceMethod java/util/concurrent/locks/Lock.unlock:()V
      73: iload         6
      75: ireturn
      76: iconst_0
      77: istore        6
      79: aload         4
      81: invokeinterface #10,  1           // InterfaceMethod java/util/concurrent/locks/ReadWriteLock.writeLock:()Ljava/util/concurrent/locks/Lock;
      86: invokeinterface #13,  1           // InterfaceMethod java/util/concurrent/locks/Lock.unlock:()V
      91: iload         6
      93: ireturn
      94: astore        7
      96: aload         4
      98: invokeinterface #10,  1           // InterfaceMethod java/util/concurrent/locks/ReadWriteLock.writeLock:()Ljava/util/concurrent/locks/Lock;
     103: invokeinterface #13,  1           // InterfaceMethod java/util/concurrent/locks/Lock.unlock:()V
     108: aload         7
     110: athrow
    Exception table:
       from    to  target type
          22    61    94   any
          76    79    94   any
          94    96    94   any

  public boolean isTableState(org.apache.hadoop.hbase.TableName, org.apache.hadoop.hbase.client.TableState$State...);
    Code:
       0: aload_0
       1: aload_1
       2: invokevirtual #18                 // Method getTableState:(Lorg/apache/hadoop/hbase/TableName;)Lorg/apache/hadoop/hbase/client/TableState;
       5: astore_3
       6: aload_3
       7: aload_2
       8: invokevirtual #19                 // Method org/apache/hadoop/hbase/client/TableState.isInStates:([Lorg/apache/hadoop/hbase/client/TableState$State;)Z
      11: ireturn
      12: astore_3
      13: getstatic     #21                 // Field LOG:Lorg/slf4j/Logger;
      16: new           #22                 // class java/lang/StringBuilder
      19: dup
      20: invokespecial #23                 // Method java/lang/StringBuilder."<init>":()V
      23: ldc           #24                 // String Unable to get table
      25: invokevirtual #25                 // Method java/lang/StringBuilder.append:(Ljava/lang/String;)Ljava/lang/StringBuilder;
      28: aload_1
      29: invokevirtual #26                 // Method java/lang/StringBuilder.append:(Ljava/lang/Object;)Ljava/lang/StringBuilder;
      32: ldc           #27                 // String  state
      34: invokevirtual #25                 // Method java/lang/StringBuilder.append:(Ljava/lang/String;)Ljava/lang/StringBuilder;
      37: invokevirtual #28                 // Method java/lang/StringBuilder.toString:()Ljava/lang/String;
      40: aload_3
      41: invokeinterface #29,  3           // InterfaceMethod org/slf4j/Logger.error:(Ljava/lang/String;Ljava/lang/Throwable;)V
      46: iconst_0
      47: ireturn
    Exception table:
       from    to  target type
           0    11    12   Class java/io/IOException

  public void setDeletedTable(org.apache.hadoop.hbase.TableName) throws java.io.IOException;
    Code:
       0: aload_1
       1: getstatic     #30                 // Field org/apache/hadoop/hbase/TableName.META_TABLE_NAME:Lorg/apache/hadoop/hbase/TableName;
       4: invokevirtual #31                 // Method org/apache/hadoop/hbase/TableName.equals:(Ljava/lang/Object;)Z
       7: ifeq          11
      10: return
      11: aload_0
      12: getfield      #4                  // Field tnLock:Lorg/apache/hadoop/hbase/util/IdReadWriteLock;
      15: aload_1
      16: invokevirtual #9                  // Method org/apache/hadoop/hbase/util/IdReadWriteLock.getLock:(Ljava/lang/Object;)Ljava/util/concurrent/locks/ReentrantReadWriteLock;
      19: astore_2
      20: aload_2
      21: invokeinterface #10,  1           // InterfaceMethod java/util/concurrent/locks/ReadWriteLock.writeLock:()Ljava/util/concurrent/locks/Lock;
      26: invokeinterface #11,  1           // InterfaceMethod java/util/concurrent/locks/Lock.lock:()V
      31: aload_0
      32: getfield      #8                  // Field master:Lorg/apache/hadoop/hbase/master/MasterServices;
      35: invokeinterface #32,  1           // InterfaceMethod org/apache/hadoop/hbase/master/MasterServices.getConnection:()Lorg/apache/hadoop/hbase/client/Connection;
      40: aload_1
      41: invokestatic  #33                 // Method org/apache/hadoop/hbase/MetaTableAccessor.deleteTableState:(Lorg/apache/hadoop/hbase/client/Connection;Lorg/apache/hadoop/hbase/TableName;)V
      44: aload_0
      45: aload_1
      46: invokevirtual #34                 // Method metaStateDeleted:(Lorg/apache/hadoop/hbase/TableName;)V
      49: aload_0
      50: getfield      #7                  // Field tableName2State:Ljava/util/concurrent/ConcurrentMap;
      53: aload_1
      54: invokeinterface #35,  2           // InterfaceMethod java/util/concurrent/ConcurrentMap.remove:(Ljava/lang/Object;)Ljava/lang/Object;
      59: pop
      60: aload_2
      61: invokeinterface #10,  1           // InterfaceMethod java/util/concurrent/locks/ReadWriteLock.writeLock:()Ljava/util/concurrent/locks/Lock;
      66: invokeinterface #13,  1           // InterfaceMethod java/util/concurrent/locks/Lock.unlock:()V
      71: goto          99
      74: astore_3
      75: aload_0
      76: getfield      #7                  // Field tableName2State:Ljava/util/concurrent/ConcurrentMap;
      79: aload_1
      80: invokeinterface #35,  2           // InterfaceMethod java/util/concurrent/ConcurrentMap.remove:(Ljava/lang/Object;)Ljava/lang/Object;
      85: pop
      86: aload_2
      87: invokeinterface #10,  1           // InterfaceMethod java/util/concurrent/locks/ReadWriteLock.writeLock:()Ljava/util/concurrent/locks/Lock;
      92: invokeinterface #13,  1           // InterfaceMethod java/util/concurrent/locks/Lock.unlock:()V
      97: aload_3
      98: athrow
      99: return
    Exception table:
       from    to  target type
          31    49    74   any

  public boolean isTablePresent(org.apache.hadoop.hbase.TableName) throws java.io.IOException;
    Code:
       0: aload_0
       1: getfield      #4                  // Field tnLock:Lorg/apache/hadoop/hbase/util/IdReadWriteLock;
       4: aload_1
       5: invokevirtual #9                  // Method org/apache/hadoop/hbase/util/IdReadWriteLock.getLock:(Ljava/lang/Object;)Ljava/util/concurrent/locks/ReentrantReadWriteLock;
       8: astore_2
       9: aload_2
      10: invokeinterface #36,  1           // InterfaceMethod java/util/concurrent/locks/ReadWriteLock.readLock:()Ljava/util/concurrent/locks/Lock;
      15: invokeinterface #11,  1           // InterfaceMethod java/util/concurrent/locks/Lock.lock:()V
      20: aload_0
      21: aload_1
      22: invokespecial #14                 // Method readMetaState:(Lorg/apache/hadoop/hbase/TableName;)Lorg/apache/hadoop/hbase/client/TableState;
      25: ifnull        32
      28: iconst_1
      29: goto          33
      32: iconst_0
      33: istore_3
      34: aload_2
      35: invokeinterface #36,  1           // InterfaceMethod java/util/concurrent/locks/ReadWriteLock.readLock:()Ljava/util/concurrent/locks/Lock;
      40: invokeinterface #13,  1           // InterfaceMethod java/util/concurrent/locks/Lock.unlock:()V
      45: iload_3
      46: ireturn
      47: astore        4
      49: aload_2
      50: invokeinterface #36,  1           // InterfaceMethod java/util/concurrent/locks/ReadWriteLock.readLock:()Ljava/util/concurrent/locks/Lock;
      55: invokeinterface #13,  1           // InterfaceMethod java/util/concurrent/locks/Lock.unlock:()V
      60: aload         4
      62: athrow
    Exception table:
       from    to  target type
          20    34    47   any
          47    49    47   any

  public java.util.Set<org.apache.hadoop.hbase.TableName> getTablesInStates(org.apache.hadoop.hbase.client.TableState$State...) throws java.io.IOException;
    Code:
       0: invokestatic  #37                 // Method org/apache/hbase/thirdparty/com/google/common/collect/Sets.newHashSet:()Ljava/util/HashSet;
       3: astore_2
       4: aload_0
       5: getfield      #8                  // Field master:Lorg/apache/hadoop/hbase/master/MasterServices;
       8: invokeinterface #32,  1           // InterfaceMethod org/apache/hadoop/hbase/master/MasterServices.getConnection:()Lorg/apache/hadoop/hbase/client/Connection;
      13: new           #38                 // class org/apache/hadoop/hbase/master/TableStateManager$1
      16: dup
      17: aload_0
      18: aload_1
      19: aload_2
      20: invokespecial #39                 // Method org/apache/hadoop/hbase/master/TableStateManager$1."<init>":(Lorg/apache/hadoop/hbase/master/TableStateManager;[Lorg/apache/hadoop/hbase/client/TableState$State;Ljava/util/Set;)V
      23: invokestatic  #40                 // Method org/apache/hadoop/hbase/MetaTableAccessor.fullScanTables:(Lorg/apache/hadoop/hbase/client/Connection;Lorg/apache/hadoop/hbase/MetaTableAccessor$Visitor;)V
      26: aload_2
      27: areturn

  public org.apache.hadoop.hbase.client.TableState getTableState(org.apache.hadoop.hbase.TableName) throws java.io.IOException;
    Code:
       0: aload_0
       1: getfield      #4                  // Field tnLock:Lorg/apache/hadoop/hbase/util/IdReadWriteLock;
       4: aload_1
       5: invokevirtual #9                  // Method org/apache/hadoop/hbase/util/IdReadWriteLock.getLock:(Ljava/lang/Object;)Ljava/util/concurrent/locks/ReentrantReadWriteLock;
       8: astore_2
       9: aload_2
      10: invokeinterface #36,  1           // InterfaceMethod java/util/concurrent/locks/ReadWriteLock.readLock:()Ljava/util/concurrent/locks/Lock;
      15: invokeinterface #11,  1           // InterfaceMethod java/util/concurrent/locks/Lock.lock:()V
      20: aload_0
      21: aload_1
      22: invokespecial #14                 // Method readMetaState:(Lorg/apache/hadoop/hbase/TableName;)Lorg/apache/hadoop/hbase/client/TableState;
      25: astore_3
      26: aload_3
      27: ifnonnull     39
      30: new           #41                 // class org/apache/hadoop/hbase/master/TableStateManager$TableStateNotFoundException
      33: dup
      34: aload_1
      35: invokespecial #42                 // Method org/apache/hadoop/hbase/master/TableStateManager$TableStateNotFoundException."<init>":(Lorg/apache/hadoop/hbase/TableName;)V
      38: athrow
      39: aload_3
      40: astore        4
      42: aload_2
      43: invokeinterface #36,  1           // InterfaceMethod java/util/concurrent/locks/ReadWriteLock.readLock:()Ljava/util/concurrent/locks/Lock;
      48: invokeinterface #13,  1           // InterfaceMethod java/util/concurrent/locks/Lock.unlock:()V
      53: aload         4
      55: areturn
      56: astore        5
      58: aload_2
      59: invokeinterface #36,  1           // InterfaceMethod java/util/concurrent/locks/ReadWriteLock.readLock:()Ljava/util/concurrent/locks/Lock;
      64: invokeinterface #13,  1           // InterfaceMethod java/util/concurrent/locks/Lock.unlock:()V
      69: aload         5
      71: athrow
    Exception table:
       from    to  target type
          20    42    56   any
          56    58    56   any

  protected void metaStateUpdated(org.apache.hadoop.hbase.TableName, org.apache.hadoop.hbase.client.TableState$State) throws java.io.IOException;
    Code:
       0: return

  protected void metaStateDeleted(org.apache.hadoop.hbase.TableName) throws java.io.IOException;
    Code:
       0: return

  public void start() throws java.io.IOException;
    Code:
       0: aload_0
       1: getfield      #8                  // Field master:Lorg/apache/hadoop/hbase/master/MasterServices;
       4: invokeinterface #59,  1           // InterfaceMethod org/apache/hadoop/hbase/master/MasterServices.getTableDescriptors:()Lorg/apache/hadoop/hbase/TableDescriptors;
       9: astore_1
      10: aload_0
      11: invokespecial #60                 // Method migrateZooKeeper:()V
      14: aload_0
      15: getfield      #8                  // Field master:Lorg/apache/hadoop/hbase/master/MasterServices;
      18: invokeinterface #32,  1           // InterfaceMethod org/apache/hadoop/hbase/master/MasterServices.getConnection:()Lorg/apache/hadoop/hbase/client/Connection;
      23: astore_2
      24: aload_0
      25: aload_1
      26: aload_2
      27: invokespecial #61                 // Method fixTableStates:(Lorg/apache/hadoop/hbase/TableDescriptors;Lorg/apache/hadoop/hbase/client/Connection;)V
      30: return

  protected void fixTableState(org.apache.hadoop.hbase.client.TableState) throws java.io.IOException;
    Code:
       0: return

  protected void deleteZooKeeper(org.apache.hadoop.hbase.TableName);
    Code:
       0: aload_0
       1: getfield      #8                  // Field master:Lorg/apache/hadoop/hbase/master/MasterServices;
       4: invokeinterface #85,  1           // InterfaceMethod org/apache/hadoop/hbase/master/MasterServices.getZooKeeper:()Lorg/apache/hadoop/hbase/zookeeper/ZKWatcher;
       9: invokevirtual #101                // Method org/apache/hadoop/hbase/zookeeper/ZKWatcher.getZNodePaths:()Lorg/apache/hadoop/hbase/zookeeper/ZNodePaths;
      12: getfield      #102                // Field org/apache/hadoop/hbase/zookeeper/ZNodePaths.tableZNode:Ljava/lang/String;
      15: aload_1
      16: invokevirtual #103                // Method org/apache/hadoop/hbase/TableName.getNameAsString:()Ljava/lang/String;
      19: invokestatic  #104                // Method org/apache/hadoop/hbase/zookeeper/ZNodePaths.joinZNode:(Ljava/lang/String;Ljava/lang/String;)Ljava/lang/String;
      22: astore_2
      23: aload_0
      24: getfield      #8                  // Field master:Lorg/apache/hadoop/hbase/master/MasterServices;
      27: invokeinterface #85,  1           // InterfaceMethod org/apache/hadoop/hbase/master/MasterServices.getZooKeeper:()Lorg/apache/hadoop/hbase/zookeeper/ZKWatcher;
      32: aload_2
      33: invokestatic  #105                // Method org/apache/hadoop/hbase/zookeeper/ZKUtil.deleteNodeFailSilent:(Lorg/apache/hadoop/hbase/zookeeper/ZKWatcher;Ljava/lang/String;)V
      36: goto          51
      39: astore_2
      40: getstatic     #21                 // Field LOG:Lorg/slf4j/Logger;
      43: ldc           #106                // String Failed deleting table state from zookeeper
      45: aload_2
      46: invokeinterface #100,  3          // InterfaceMethod org/slf4j/Logger.warn:(Ljava/lang/String;Ljava/lang/Throwable;)V
      51: return
    Exception table:
       from    to  target type
           0    36    39   Class org/apache/zookeeper/KeeperException

  static {};
    Code:
       0: ldc           #82                 // class org/apache/hadoop/hbase/master/TableStateManager
       2: invokestatic  #107                // Method org/slf4j/LoggerFactory.getLogger:(Ljava/lang/Class;)Lorg/slf4j/Logger;
       5: putstatic     #21                 // Field LOG:Lorg/slf4j/Logger;
       8: return
}
