Compiled from "Tag.java"
public interface org.apache.hadoop.hbase.Tag {
  public static final int TYPE_LENGTH_SIZE;

  public static final int TAG_LENGTH_SIZE;

  public static final int INFRASTRUCTURE_SIZE;

  public static final int MAX_TAG_LENGTH;

  public static final byte CUSTOM_TAG_TYPE_RANGE;

  public abstract byte getType();

  public abstract int getValueOffset();

  public abstract int getValueLength();

  public abstract boolean hasArray();

  public abstract byte[] getValueArray();

  public abstract java.nio.ByteBuffer getValueByteBuffer();

  public static byte[] cloneValue(org.apache.hadoop.hbase.Tag);
    Code:
       0: aload_0
       1: invokeinterface #4,  1            // InterfaceMethod getValueLength:()I
       6: istore_1
       7: iload_1
       8: newarray       byte
      10: astore_2
      11: aload_0
      12: invokeinterface #5,  1            // InterfaceMethod hasArray:()Z
      17: ifeq          42
      20: aload_2
      21: iconst_0
      22: aload_0
      23: invokeinterface #6,  1            // InterfaceMethod getValueArray:()[B
      28: aload_0
      29: invokeinterface #7,  1            // InterfaceMethod getValueOffset:()I
      34: iload_1
      35: invokestatic  #8                  // Method org/apache/hadoop/hbase/util/Bytes.putBytes:([BI[BII)I
      38: pop
      39: goto          60
      42: aload_2
      43: aload_0
      44: invokeinterface #9,  1            // InterfaceMethod getValueByteBuffer:()Ljava/nio/ByteBuffer;
      49: aload_0
      50: invokeinterface #7,  1            // InterfaceMethod getValueOffset:()I
      55: iconst_0
      56: iload_1
      57: invokestatic  #10                 // Method org/apache/hadoop/hbase/util/ByteBufferUtils.copyFromBufferToArray:([BLjava/nio/ByteBuffer;III)V
      60: aload_2
      61: areturn

  public static java.lang.String getValueAsString(org.apache.hadoop.hbase.Tag);
    Code:
       0: aload_0
       1: invokeinterface #5,  1            // InterfaceMethod hasArray:()Z
       6: ifeq          31
       9: aload_0
      10: invokeinterface #6,  1            // InterfaceMethod getValueArray:()[B
      15: aload_0
      16: invokeinterface #7,  1            // InterfaceMethod getValueOffset:()I
      21: aload_0
      22: invokeinterface #4,  1            // InterfaceMethod getValueLength:()I
      27: invokestatic  #11                 // Method org/apache/hadoop/hbase/util/Bytes.toString:([BII)Ljava/lang/String;
      30: areturn
      31: aload_0
      32: invokestatic  #12                 // InterfaceMethod cloneValue:(Lorg/apache/hadoop/hbase/Tag;)[B
      35: invokestatic  #13                 // Method org/apache/hadoop/hbase/util/Bytes.toString:([B)Ljava/lang/String;
      38: areturn

  public static boolean matchingValue(org.apache.hadoop.hbase.Tag, org.apache.hadoop.hbase.Tag);
    Code:
       0: aload_0
       1: invokeinterface #5,  1            // InterfaceMethod hasArray:()Z
       6: ifeq          58
       9: aload_1
      10: invokeinterface #5,  1            // InterfaceMethod hasArray:()Z
      15: ifeq          58
      18: aload_0
      19: invokeinterface #6,  1            // InterfaceMethod getValueArray:()[B
      24: aload_0
      25: invokeinterface #7,  1            // InterfaceMethod getValueOffset:()I
      30: aload_0
      31: invokeinterface #4,  1            // InterfaceMethod getValueLength:()I
      36: aload_1
      37: invokeinterface #6,  1            // InterfaceMethod getValueArray:()[B
      42: aload_1
      43: invokeinterface #7,  1            // InterfaceMethod getValueOffset:()I
      48: aload_1
      49: invokeinterface #4,  1            // InterfaceMethod getValueLength:()I
      54: invokestatic  #14                 // Method org/apache/hadoop/hbase/util/Bytes.equals:([BII[BII)Z
      57: ireturn
      58: aload_0
      59: invokeinterface #5,  1            // InterfaceMethod hasArray:()Z
      64: ifeq          107
      67: aload_1
      68: invokeinterface #9,  1            // InterfaceMethod getValueByteBuffer:()Ljava/nio/ByteBuffer;
      73: aload_1
      74: invokeinterface #7,  1            // InterfaceMethod getValueOffset:()I
      79: aload_1
      80: invokeinterface #4,  1            // InterfaceMethod getValueLength:()I
      85: aload_0
      86: invokeinterface #6,  1            // InterfaceMethod getValueArray:()[B
      91: aload_0
      92: invokeinterface #7,  1            // InterfaceMethod getValueOffset:()I
      97: aload_0
      98: invokeinterface #4,  1            // InterfaceMethod getValueLength:()I
     103: invokestatic  #15                 // Method org/apache/hadoop/hbase/util/ByteBufferUtils.equals:(Ljava/nio/ByteBuffer;II[BII)Z
     106: ireturn
     107: aload_1
     108: invokeinterface #5,  1            // InterfaceMethod hasArray:()Z
     113: ifeq          156
     116: aload_0
     117: invokeinterface #9,  1            // InterfaceMethod getValueByteBuffer:()Ljava/nio/ByteBuffer;
     122: aload_0
     123: invokeinterface #7,  1            // InterfaceMethod getValueOffset:()I
     128: aload_0
     129: invokeinterface #4,  1            // InterfaceMethod getValueLength:()I
     134: aload_1
     135: invokeinterface #6,  1            // InterfaceMethod getValueArray:()[B
     140: aload_1
     141: invokeinterface #7,  1            // InterfaceMethod getValueOffset:()I
     146: aload_1
     147: invokeinterface #4,  1            // InterfaceMethod getValueLength:()I
     152: invokestatic  #15                 // Method org/apache/hadoop/hbase/util/ByteBufferUtils.equals:(Ljava/nio/ByteBuffer;II[BII)Z
     155: ireturn
     156: aload_0
     157: invokeinterface #9,  1            // InterfaceMethod getValueByteBuffer:()Ljava/nio/ByteBuffer;
     162: aload_0
     163: invokeinterface #7,  1            // InterfaceMethod getValueOffset:()I
     168: aload_0
     169: invokeinterface #4,  1            // InterfaceMethod getValueLength:()I
     174: aload_1
     175: invokeinterface #9,  1            // InterfaceMethod getValueByteBuffer:()Ljava/nio/ByteBuffer;
     180: aload_1
     181: invokeinterface #7,  1            // InterfaceMethod getValueOffset:()I
     186: aload_1
     187: invokeinterface #4,  1            // InterfaceMethod getValueLength:()I
     192: invokestatic  #16                 // Method org/apache/hadoop/hbase/util/ByteBufferUtils.equals:(Ljava/nio/ByteBuffer;IILjava/nio/ByteBuffer;II)Z
     195: ireturn

  public static void copyValueTo(org.apache.hadoop.hbase.Tag, byte[], int);
    Code:
       0: aload_0
       1: invokeinterface #5,  1            // InterfaceMethod hasArray:()Z
       6: ifeq          36
       9: aload_1
      10: iload_2
      11: aload_0
      12: invokeinterface #6,  1            // InterfaceMethod getValueArray:()[B
      17: aload_0
      18: invokeinterface #7,  1            // InterfaceMethod getValueOffset:()I
      23: aload_0
      24: invokeinterface #4,  1            // InterfaceMethod getValueLength:()I
      29: invokestatic  #8                  // Method org/apache/hadoop/hbase/util/Bytes.putBytes:([BI[BII)I
      32: pop
      33: goto          59
      36: aload_1
      37: aload_0
      38: invokeinterface #9,  1            // InterfaceMethod getValueByteBuffer:()Ljava/nio/ByteBuffer;
      43: aload_0
      44: invokeinterface #7,  1            // InterfaceMethod getValueOffset:()I
      49: iload_2
      50: aload_0
      51: invokeinterface #4,  1            // InterfaceMethod getValueLength:()I
      56: invokestatic  #10                 // Method org/apache/hadoop/hbase/util/ByteBufferUtils.copyFromBufferToArray:([BLjava/nio/ByteBuffer;III)V
      59: return

  public static long getValueAsLong(org.apache.hadoop.hbase.Tag);
    Code:
       0: aload_0
       1: invokeinterface #5,  1            // InterfaceMethod hasArray:()Z
       6: ifeq          31
       9: aload_0
      10: invokeinterface #6,  1            // InterfaceMethod getValueArray:()[B
      15: aload_0
      16: invokeinterface #7,  1            // InterfaceMethod getValueOffset:()I
      21: aload_0
      22: invokeinterface #4,  1            // InterfaceMethod getValueLength:()I
      27: invokestatic  #17                 // Method org/apache/hadoop/hbase/util/Bytes.toLong:([BII)J
      30: lreturn
      31: aload_0
      32: invokeinterface #9,  1            // InterfaceMethod getValueByteBuffer:()Ljava/nio/ByteBuffer;
      37: aload_0
      38: invokeinterface #7,  1            // InterfaceMethod getValueOffset:()I
      43: invokestatic  #18                 // Method org/apache/hadoop/hbase/util/ByteBufferUtils.toLong:(Ljava/nio/ByteBuffer;I)J
      46: lreturn

  public static byte getValueAsByte(org.apache.hadoop.hbase.Tag);
    Code:
       0: aload_0
       1: invokeinterface #5,  1            // InterfaceMethod hasArray:()Z
       6: ifeq          23
       9: aload_0
      10: invokeinterface #6,  1            // InterfaceMethod getValueArray:()[B
      15: aload_0
      16: invokeinterface #7,  1            // InterfaceMethod getValueOffset:()I
      21: baload
      22: ireturn
      23: aload_0
      24: invokeinterface #9,  1            // InterfaceMethod getValueByteBuffer:()Ljava/nio/ByteBuffer;
      29: aload_0
      30: invokeinterface #7,  1            // InterfaceMethod getValueOffset:()I
      35: invokestatic  #19                 // Method org/apache/hadoop/hbase/util/ByteBufferUtils.toByte:(Ljava/nio/ByteBuffer;I)B
      38: ireturn
}
