Compiled from "TaskMonitorTmpl.java"
public class org.apache.hadoop.hbase.tmpl.common.TaskMonitorTmpl$ImplData extends org.jamon.AbstractTemplateProxy$ImplData {
  public org.apache.hadoop.hbase.tmpl.common.TaskMonitorTmpl$ImplData();
    Code:
       0: aload_0
       1: invokespecial #1                  // Method org/jamon/AbstractTemplateProxy$ImplData."<init>":()V
       4: return

  public void setFilter(java.lang.String);
    Code:
       0: aload_0
       1: aload_1
       2: putfield      #2                  // Field m_filter:Ljava/lang/String;
       5: aload_0
       6: iconst_1
       7: putfield      #3                  // Field m_filter__IsNotDefault:Z
      10: return

  public java.lang.String getFilter();
    Code:
       0: aload_0
       1: getfield      #2                  // Field m_filter:Ljava/lang/String;
       4: areturn

  public boolean getFilter__IsNotDefault();
    Code:
       0: aload_0
       1: getfield      #3                  // Field m_filter__IsNotDefault:Z
       4: ireturn

  public void setFormat(java.lang.String);
    Code:
       0: aload_0
       1: aload_1
       2: putfield      #4                  // Field m_format:Ljava/lang/String;
       5: aload_0
       6: iconst_1
       7: putfield      #5                  // Field m_format__IsNotDefault:Z
      10: return

  public java.lang.String getFormat();
    Code:
       0: aload_0
       1: getfield      #4                  // Field m_format:Ljava/lang/String;
       4: areturn

  public boolean getFormat__IsNotDefault();
    Code:
       0: aload_0
       1: getfield      #5                  // Field m_format__IsNotDefault:Z
       4: ireturn

  public void setParent(java.lang.String);
    Code:
       0: aload_0
       1: aload_1
       2: putfield      #6                  // Field m_parent:Ljava/lang/String;
       5: aload_0
       6: iconst_1
       7: putfield      #7                  // Field m_parent__IsNotDefault:Z
      10: return

  public java.lang.String getParent();
    Code:
       0: aload_0
       1: getfield      #6                  // Field m_parent:Ljava/lang/String;
       4: areturn

  public boolean getParent__IsNotDefault();
    Code:
       0: aload_0
       1: getfield      #7                  // Field m_parent__IsNotDefault:Z
       4: ireturn

  public void setTaskMonitor(org.apache.hadoop.hbase.monitoring.TaskMonitor);
    Code:
       0: aload_0
       1: aload_1
       2: putfield      #8                  // Field m_taskMonitor:Lorg/apache/hadoop/hbase/monitoring/TaskMonitor;
       5: aload_0
       6: iconst_1
       7: putfield      #9                  // Field m_taskMonitor__IsNotDefault:Z
      10: return

  public org.apache.hadoop.hbase.monitoring.TaskMonitor getTaskMonitor();
    Code:
       0: aload_0
       1: getfield      #8                  // Field m_taskMonitor:Lorg/apache/hadoop/hbase/monitoring/TaskMonitor;
       4: areturn

  public boolean getTaskMonitor__IsNotDefault();
    Code:
       0: aload_0
       1: getfield      #9                  // Field m_taskMonitor__IsNotDefault:Z
       4: ireturn
}
