Compiled from "TaskMonitor.java"
public final class org.apache.hadoop.hbase.monitoring.TaskMonitor$TaskFilter$TaskType extends java.lang.Enum<org.apache.hadoop.hbase.monitoring.TaskMonitor$TaskFilter$TaskType> {
  public static final org.apache.hadoop.hbase.monitoring.TaskMonitor$TaskFilter$TaskType GENERAL;

  public static final org.apache.hadoop.hbase.monitoring.TaskMonitor$TaskFilter$TaskType HANDLER;

  public static final org.apache.hadoop.hbase.monitoring.TaskMonitor$TaskFilter$TaskType RPC;

  public static final org.apache.hadoop.hbase.monitoring.TaskMonitor$TaskFilter$TaskType OPERATION;

  public static final org.apache.hadoop.hbase.monitoring.TaskMonitor$TaskFilter$TaskType ALL;

  public static org.apache.hadoop.hbase.monitoring.TaskMonitor$TaskFilter$TaskType[] values();
    Code:
       0: getstatic     #1                  // Field $VALUES:[Lorg/apache/hadoop/hbase/monitoring/TaskMonitor$TaskFilter$TaskType;
       3: invokevirtual #2                  // Method "[Lorg/apache/hadoop/hbase/monitoring/TaskMonitor$TaskFilter$TaskType;".clone:()Ljava/lang/Object;
       6: checkcast     #3                  // class "[Lorg/apache/hadoop/hbase/monitoring/TaskMonitor$TaskFilter$TaskType;"
       9: areturn

  public static org.apache.hadoop.hbase.monitoring.TaskMonitor$TaskFilter$TaskType valueOf(java.lang.String);
    Code:
       0: ldc           #4                  // class org/apache/hadoop/hbase/monitoring/TaskMonitor$TaskFilter$TaskType
       2: aload_0
       3: invokestatic  #5                  // Method java/lang/Enum.valueOf:(Ljava/lang/Class;Ljava/lang/String;)Ljava/lang/Enum;
       6: checkcast     #4                  // class org/apache/hadoop/hbase/monitoring/TaskMonitor$TaskFilter$TaskType
       9: areturn

  static org.apache.hadoop.hbase.monitoring.TaskMonitor$TaskFilter$TaskType getTaskType(java.lang.String);
    Code:
       0: aload_0
       1: ifnull        11
       4: aload_0
       5: invokevirtual #9                  // Method java/lang/String.isEmpty:()Z
       8: ifeq          15
      11: getstatic     #10                 // Field ALL:Lorg/apache/hadoop/hbase/monitoring/TaskMonitor$TaskFilter$TaskType;
      14: areturn
      15: aload_0
      16: invokevirtual #7                  // Method java/lang/String.toLowerCase:()Ljava/lang/String;
      19: astore_0
      20: invokestatic  #11                 // Method values:()[Lorg/apache/hadoop/hbase/monitoring/TaskMonitor$TaskFilter$TaskType;
      23: astore_1
      24: aload_1
      25: arraylength
      26: istore_2
      27: iconst_0
      28: istore_3
      29: iload_3
      30: iload_2
      31: if_icmpge     60
      34: aload_1
      35: iload_3
      36: aaload
      37: astore        4
      39: aload         4
      41: invokevirtual #12                 // Method toString:()Ljava/lang/String;
      44: aload_0
      45: invokevirtual #13                 // Method java/lang/String.equals:(Ljava/lang/Object;)Z
      48: ifeq          54
      51: aload         4
      53: areturn
      54: iinc          3, 1
      57: goto          29
      60: getstatic     #10                 // Field ALL:Lorg/apache/hadoop/hbase/monitoring/TaskMonitor$TaskFilter$TaskType;
      63: areturn

  public java.lang.String toString();
    Code:
       0: aload_0
       1: getfield      #8                  // Field type:Ljava/lang/String;
       4: areturn

  static {};
    Code:
       0: new           #4                  // class org/apache/hadoop/hbase/monitoring/TaskMonitor$TaskFilter$TaskType
       3: dup
       4: ldc           #14                 // String GENERAL
       6: iconst_0
       7: ldc           #15                 // String general
       9: invokespecial #16                 // Method "<init>":(Ljava/lang/String;ILjava/lang/String;)V
      12: putstatic     #17                 // Field GENERAL:Lorg/apache/hadoop/hbase/monitoring/TaskMonitor$TaskFilter$TaskType;
      15: new           #4                  // class org/apache/hadoop/hbase/monitoring/TaskMonitor$TaskFilter$TaskType
      18: dup
      19: ldc           #18                 // String HANDLER
      21: iconst_1
      22: ldc           #19                 // String handler
      24: invokespecial #16                 // Method "<init>":(Ljava/lang/String;ILjava/lang/String;)V
      27: putstatic     #20                 // Field HANDLER:Lorg/apache/hadoop/hbase/monitoring/TaskMonitor$TaskFilter$TaskType;
      30: new           #4                  // class org/apache/hadoop/hbase/monitoring/TaskMonitor$TaskFilter$TaskType
      33: dup
      34: ldc           #21                 // String RPC
      36: iconst_2
      37: ldc           #22                 // String rpc
      39: invokespecial #16                 // Method "<init>":(Ljava/lang/String;ILjava/lang/String;)V
      42: putstatic     #23                 // Field RPC:Lorg/apache/hadoop/hbase/monitoring/TaskMonitor$TaskFilter$TaskType;
      45: new           #4                  // class org/apache/hadoop/hbase/monitoring/TaskMonitor$TaskFilter$TaskType
      48: dup
      49: ldc           #24                 // String OPERATION
      51: iconst_3
      52: ldc           #25                 // String operation
      54: invokespecial #16                 // Method "<init>":(Ljava/lang/String;ILjava/lang/String;)V
      57: putstatic     #26                 // Field OPERATION:Lorg/apache/hadoop/hbase/monitoring/TaskMonitor$TaskFilter$TaskType;
      60: new           #4                  // class org/apache/hadoop/hbase/monitoring/TaskMonitor$TaskFilter$TaskType
      63: dup
      64: ldc           #27                 // String ALL
      66: iconst_4
      67: ldc           #28                 // String all
      69: invokespecial #16                 // Method "<init>":(Ljava/lang/String;ILjava/lang/String;)V
      72: putstatic     #10                 // Field ALL:Lorg/apache/hadoop/hbase/monitoring/TaskMonitor$TaskFilter$TaskType;
      75: iconst_5
      76: anewarray     #4                  // class org/apache/hadoop/hbase/monitoring/TaskMonitor$TaskFilter$TaskType
      79: dup
      80: iconst_0
      81: getstatic     #17                 // Field GENERAL:Lorg/apache/hadoop/hbase/monitoring/TaskMonitor$TaskFilter$TaskType;
      84: aastore
      85: dup
      86: iconst_1
      87: getstatic     #20                 // Field HANDLER:Lorg/apache/hadoop/hbase/monitoring/TaskMonitor$TaskFilter$TaskType;
      90: aastore
      91: dup
      92: iconst_2
      93: getstatic     #23                 // Field RPC:Lorg/apache/hadoop/hbase/monitoring/TaskMonitor$TaskFilter$TaskType;
      96: aastore
      97: dup
      98: iconst_3
      99: getstatic     #26                 // Field OPERATION:Lorg/apache/hadoop/hbase/monitoring/TaskMonitor$TaskFilter$TaskType;
     102: aastore
     103: dup
     104: iconst_4
     105: getstatic     #10                 // Field ALL:Lorg/apache/hadoop/hbase/monitoring/TaskMonitor$TaskFilter$TaskType;
     108: aastore
     109: putstatic     #1                  // Field $VALUES:[Lorg/apache/hadoop/hbase/monitoring/TaskMonitor$TaskFilter$TaskType;
     112: return
}
