Compiled from "TestRegionSizeImpl.java"
public class org.apache.hadoop.hbase.quotas.TestRegionSizeImpl {
  public static final org.apache.hadoop.hbase.HBaseClassTestRule CLASS_RULE;

  public org.apache.hadoop.hbase.quotas.TestRegionSizeImpl();
    Code:
       0: aload_0
       1: invokespecial #1                  // Method java/lang/Object."<init>":()V
       4: return

  public void testReportingWithSizeChanges();
    Code:
       0: ldc2_w        #2                  // long 1024l
       3: lstore_1
       4: new           #4                  // class org/apache/hadoop/hbase/quotas/RegionSizeImpl
       7: dup
       8: lload_1
       9: invokespecial #5                  // Method org/apache/hadoop/hbase/quotas/RegionSizeImpl."<init>":(J)V
      12: astore_3
      13: lload_1
      14: aload_3
      15: invokevirtual #6                  // Method org/apache/hadoop/hbase/quotas/RegionSizeImpl.getSize:()J
      18: invokestatic  #7                  // Method org/junit/Assert.assertEquals:(JJ)V
      21: lload_1
      22: ldc2_w        #8                  // long 2l
      25: lmul
      26: lstore_1
      27: aload_3
      28: lload_1
      29: invokevirtual #10                 // Method org/apache/hadoop/hbase/quotas/RegionSizeImpl.setSize:(J)Lorg/apache/hadoop/hbase/quotas/RegionSizeImpl;
      32: pop
      33: lload_1
      34: aload_3
      35: invokevirtual #6                  // Method org/apache/hadoop/hbase/quotas/RegionSizeImpl.getSize:()J
      38: invokestatic  #7                  // Method org/junit/Assert.assertEquals:(JJ)V
      41: ldc2_w        #11                 // long 512l
      44: lstore        4
      46: lload_1
      47: lload         4
      49: ladd
      50: lstore_1
      51: aload_3
      52: lload         4
      54: invokevirtual #13                 // Method org/apache/hadoop/hbase/quotas/RegionSizeImpl.incrementSize:(J)Lorg/apache/hadoop/hbase/quotas/RegionSizeImpl;
      57: pop
      58: lload_1
      59: aload_3
      60: invokevirtual #6                  // Method org/apache/hadoop/hbase/quotas/RegionSizeImpl.getSize:()J
      63: invokestatic  #7                  // Method org/junit/Assert.assertEquals:(JJ)V
      66: return

  static {};
    Code:
       0: ldc           #14                 // class org/apache/hadoop/hbase/quotas/TestRegionSizeImpl
       2: invokestatic  #15                 // Method org/apache/hadoop/hbase/HBaseClassTestRule.forClass:(Ljava/lang/Class;)Lorg/apache/hadoop/hbase/HBaseClassTestRule;
       5: putstatic     #16                 // Field CLASS_RULE:Lorg/apache/hadoop/hbase/HBaseClassTestRule;
       8: return
}
