Compiled from "TestServerNonceManager.java"
class org.apache.hadoop.hbase.regionserver.TestServerNonceManager$TestRunnable implements java.lang.Runnable {
  public final java.util.concurrent.CountDownLatch startedLatch;

  public org.apache.hadoop.hbase.regionserver.TestServerNonceManager$TestRunnable(org.apache.hadoop.hbase.regionserver.ServerNonceManager, long, java.lang.Boolean, org.apache.hadoop.hbase.Stoppable);
    Code:
       0: aload_0
       1: invokespecial #2                  // Method java/lang/Object."<init>":()V
       4: aload_0
       5: new           #3                  // class java/util/concurrent/CountDownLatch
       8: dup
       9: iconst_1
      10: invokespecial #4                  // Method java/util/concurrent/CountDownLatch."<init>":(I)V
      13: putfield      #5                  // Field startedLatch:Ljava/util/concurrent/CountDownLatch;
      16: aload_0
      17: aconst_null
      18: putfield      #6                  // Field throwable:Ljava/lang/Throwable;
      21: aload_0
      22: aload_1
      23: putfield      #7                  // Field nm:Lorg/apache/hadoop/hbase/regionserver/ServerNonceManager;
      26: aload_0
      27: lload_2
      28: putfield      #8                  // Field nonce:J
      31: aload_0
      32: aload         4
      34: putfield      #9                  // Field expected:Ljava/lang/Boolean;
      37: aload_0
      38: aload         5
      40: putfield      #10                 // Field stoppable:Lorg/apache/hadoop/hbase/Stoppable;
      43: return

  public void propagateError() throws java.lang.Exception;
    Code:
       0: aload_0
       1: getfield      #6                  // Field throwable:Ljava/lang/Throwable;
       4: ifnonnull     8
       7: return
       8: new           #11                 // class java/lang/Exception
      11: dup
      12: aload_0
      13: getfield      #6                  // Field throwable:Ljava/lang/Throwable;
      16: invokespecial #12                 // Method java/lang/Exception."<init>":(Ljava/lang/Throwable;)V
      19: athrow

  public java.lang.Thread start();
    Code:
       0: new           #13                 // class java/lang/Thread
       3: dup
       4: aload_0
       5: invokespecial #14                 // Method java/lang/Thread."<init>":(Ljava/lang/Runnable;)V
       8: astore_1
       9: aload_1
      10: invokestatic  #15                 // Method org/apache/hadoop/hbase/util/Threads.setDaemonThreadRunning:(Ljava/lang/Thread;)Ljava/lang/Thread;
      13: astore_1
      14: aload_0
      15: getfield      #5                  // Field startedLatch:Ljava/util/concurrent/CountDownLatch;
      18: invokevirtual #16                 // Method java/util/concurrent/CountDownLatch.await:()V
      21: goto          30
      24: astore_2
      25: ldc           #18                 // String Unexpected
      27: invokestatic  #19                 // Method org/junit/Assert.fail:(Ljava/lang/String;)V
      30: aload_1
      31: areturn
    Exception table:
       from    to  target type
          14    21    24   Class java/lang/InterruptedException

  public void run();
    Code:
       0: aload_0
       1: getfield      #5                  // Field startedLatch:Ljava/util/concurrent/CountDownLatch;
       4: invokevirtual #20                 // Method java/util/concurrent/CountDownLatch.countDown:()V
       7: aload_0
       8: getfield      #9                  // Field expected:Ljava/lang/Boolean;
      11: ifnonnull     18
      14: iconst_1
      15: goto          19
      18: iconst_0
      19: istore_1
      20: iconst_1
      21: istore_2
      22: aload_0
      23: getfield      #7                  // Field nm:Lorg/apache/hadoop/hbase/regionserver/ServerNonceManager;
      26: lconst_0
      27: aload_0
      28: getfield      #8                  // Field nonce:J
      31: aload_0
      32: getfield      #10                 // Field stoppable:Lorg/apache/hadoop/hbase/Stoppable;
      35: invokevirtual #21                 // Method org/apache/hadoop/hbase/regionserver/ServerNonceManager.startOperation:(JJLorg/apache/hadoop/hbase/Stoppable;)Z
      38: istore_3
      39: iconst_0
      40: istore_2
      41: iload_1
      42: ifne          62
      45: aload_0
      46: getfield      #9                  // Field expected:Ljava/lang/Boolean;
      49: invokevirtual #22                 // Method java/lang/Boolean.booleanValue:()Z
      52: invokestatic  #23                 // Method java/lang/Boolean.valueOf:(Z)Ljava/lang/Boolean;
      55: iload_3
      56: invokestatic  #23                 // Method java/lang/Boolean.valueOf:(Z)Ljava/lang/Boolean;
      59: invokestatic  #24                 // Method org/junit/Assert.assertEquals:(Ljava/lang/Object;Ljava/lang/Object;)V
      62: goto          75
      65: astore_3
      66: iload_1
      67: ifne          75
      70: aload_0
      71: aload_3
      72: putfield      #6                  // Field throwable:Ljava/lang/Throwable;
      75: iload_1
      76: ifeq          96
      79: iload_2
      80: ifne          96
      83: aload_0
      84: new           #26                 // class java/lang/AssertionError
      87: dup
      88: ldc           #27                 // String Should have thrown
      90: invokespecial #28                 // Method java/lang/AssertionError."<init>":(Ljava/lang/Object;)V
      93: putfield      #6                  // Field throwable:Ljava/lang/Throwable;
      96: return
    Exception table:
       from    to  target type
          22    62    65   Class java/lang/Throwable
}
