Compiled from "TestCompaction.java"
class org.apache.hadoop.hbase.regionserver.TestCompaction$2 implements org.mockito.stubbing.Answer<java.lang.Boolean> {
  final org.apache.hadoop.hbase.regionserver.TestCompaction this$0;

  org.apache.hadoop.hbase.regionserver.TestCompaction$2(org.apache.hadoop.hbase.regionserver.TestCompaction);
    Code:
       0: aload_0
       1: aload_1
       2: putfield      #1                  // Field this$0:Lorg/apache/hadoop/hbase/regionserver/TestCompaction;
       5: aload_0
       6: invokespecial #2                  // Method java/lang/Object."<init>":()V
       9: return

  public java.lang.Boolean answer(org.mockito.invocation.InvocationOnMock) throws java.lang.Throwable;
    Code:
       0: aload_1
       1: iconst_0
       2: invokeinterface #3,  2            // InterfaceMethod org/mockito/invocation/InvocationOnMock.getArgument:(I)Ljava/lang/Object;
       7: checkcast     #4                  // class org/apache/hadoop/hbase/regionserver/compactions/CompactionContext
      10: aload_1
      11: iconst_2
      12: invokeinterface #3,  2            // InterfaceMethod org/mockito/invocation/InvocationOnMock.getArgument:(I)Ljava/lang/Object;
      17: checkcast     #5                  // class org/apache/hadoop/hbase/regionserver/throttle/ThroughputController
      20: aconst_null
      21: invokevirtual #6                  // Method org/apache/hadoop/hbase/regionserver/compactions/CompactionContext.compact:(Lorg/apache/hadoop/hbase/regionserver/throttle/ThroughputController;Lorg/apache/hadoop/hbase/security/User;)Ljava/util/List;
      24: pop
      25: iconst_1
      26: invokestatic  #7                  // Method java/lang/Boolean.valueOf:(Z)Ljava/lang/Boolean;
      29: areturn

  public java.lang.Object answer(org.mockito.invocation.InvocationOnMock) throws java.lang.Throwable;
    Code:
       0: aload_0
       1: aload_1
       2: invokevirtual #8                  // Method answer:(Lorg/mockito/invocation/InvocationOnMock;)Ljava/lang/Boolean;
       5: areturn
}
