Compiled from "TestKeyValueCodecWithTags.java"
public class org.apache.hadoop.hbase.codec.TestKeyValueCodecWithTags {
  public static final org.apache.hadoop.hbase.HBaseClassTestRule CLASS_RULE;

  public org.apache.hadoop.hbase.codec.TestKeyValueCodecWithTags();
    Code:
       0: aload_0
       1: invokespecial #1                  // Method java/lang/Object."<init>":()V
       4: return

  public void testKeyValueWithTag() throws java.io.IOException;
    Code:
       0: new           #2                  // class java/io/ByteArrayOutputStream
       3: dup
       4: invokespecial #3                  // Method java/io/ByteArrayOutputStream."<init>":()V
       7: astore_1
       8: new           #4                  // class org/apache/hbase/thirdparty/com/google/common/io/CountingOutputStream
      11: dup
      12: aload_1
      13: invokespecial #5                  // Method org/apache/hbase/thirdparty/com/google/common/io/CountingOutputStream."<init>":(Ljava/io/OutputStream;)V
      16: astore_2
      17: new           #6                  // class java/io/DataOutputStream
      20: dup
      21: aload_2
      22: invokespecial #7                  // Method java/io/DataOutputStream."<init>":(Ljava/io/OutputStream;)V
      25: astore_3
      26: new           #8                  // class org/apache/hadoop/hbase/codec/KeyValueCodecWithTags
      29: dup
      30: invokespecial #9                  // Method org/apache/hadoop/hbase/codec/KeyValueCodecWithTags."<init>":()V
      33: astore        4
      35: aload         4
      37: aload_3
      38: invokeinterface #10,  2           // InterfaceMethod org/apache/hadoop/hbase/codec/Codec.getEncoder:(Ljava/io/OutputStream;)Lorg/apache/hadoop/hbase/codec/Codec$Encoder;
      43: astore        5
      45: new           #11                 // class org/apache/hadoop/hbase/KeyValue
      48: dup
      49: ldc           #12                 // String r
      51: invokestatic  #13                 // Method org/apache/hadoop/hbase/util/Bytes.toBytes:(Ljava/lang/String;)[B
      54: ldc           #14                 // String f
      56: invokestatic  #13                 // Method org/apache/hadoop/hbase/util/Bytes.toBytes:(Ljava/lang/String;)[B
      59: ldc           #15                 // String 1
      61: invokestatic  #13                 // Method org/apache/hadoop/hbase/util/Bytes.toBytes:(Ljava/lang/String;)[B
      64: ldc2_w        #17                 // long 9223372036854775807l
      67: ldc           #15                 // String 1
      69: invokestatic  #13                 // Method org/apache/hadoop/hbase/util/Bytes.toBytes:(Ljava/lang/String;)[B
      72: iconst_2
      73: anewarray     #19                 // class org/apache/hadoop/hbase/Tag
      76: dup
      77: iconst_0
      78: new           #20                 // class org/apache/hadoop/hbase/ArrayBackedTag
      81: dup
      82: iconst_1
      83: ldc           #21                 // String teststring1
      85: invokestatic  #13                 // Method org/apache/hadoop/hbase/util/Bytes.toBytes:(Ljava/lang/String;)[B
      88: invokespecial #22                 // Method org/apache/hadoop/hbase/ArrayBackedTag."<init>":(B[B)V
      91: aastore
      92: dup
      93: iconst_1
      94: new           #20                 // class org/apache/hadoop/hbase/ArrayBackedTag
      97: dup
      98: iconst_2
      99: ldc           #23                 // String teststring2
     101: invokestatic  #13                 // Method org/apache/hadoop/hbase/util/Bytes.toBytes:(Ljava/lang/String;)[B
     104: invokespecial #22                 // Method org/apache/hadoop/hbase/ArrayBackedTag."<init>":(B[B)V
     107: aastore
     108: invokespecial #24                 // Method org/apache/hadoop/hbase/KeyValue."<init>":([B[B[BJ[B[Lorg/apache/hadoop/hbase/Tag;)V
     111: astore        6
     113: new           #11                 // class org/apache/hadoop/hbase/KeyValue
     116: dup
     117: ldc           #12                 // String r
     119: invokestatic  #13                 // Method org/apache/hadoop/hbase/util/Bytes.toBytes:(Ljava/lang/String;)[B
     122: ldc           #14                 // String f
     124: invokestatic  #13                 // Method org/apache/hadoop/hbase/util/Bytes.toBytes:(Ljava/lang/String;)[B
     127: ldc           #25                 // String 2
     129: invokestatic  #13                 // Method org/apache/hadoop/hbase/util/Bytes.toBytes:(Ljava/lang/String;)[B
     132: ldc2_w        #17                 // long 9223372036854775807l
     135: ldc           #25                 // String 2
     137: invokestatic  #13                 // Method org/apache/hadoop/hbase/util/Bytes.toBytes:(Ljava/lang/String;)[B
     140: iconst_1
     141: anewarray     #19                 // class org/apache/hadoop/hbase/Tag
     144: dup
     145: iconst_0
     146: new           #20                 // class org/apache/hadoop/hbase/ArrayBackedTag
     149: dup
     150: iconst_1
     151: ldc           #26                 // String teststring3
     153: invokestatic  #13                 // Method org/apache/hadoop/hbase/util/Bytes.toBytes:(Ljava/lang/String;)[B
     156: invokespecial #22                 // Method org/apache/hadoop/hbase/ArrayBackedTag."<init>":(B[B)V
     159: aastore
     160: invokespecial #24                 // Method org/apache/hadoop/hbase/KeyValue."<init>":([B[B[BJ[B[Lorg/apache/hadoop/hbase/Tag;)V
     163: astore        7
     165: new           #11                 // class org/apache/hadoop/hbase/KeyValue
     168: dup
     169: ldc           #12                 // String r
     171: invokestatic  #13                 // Method org/apache/hadoop/hbase/util/Bytes.toBytes:(Ljava/lang/String;)[B
     174: ldc           #14                 // String f
     176: invokestatic  #13                 // Method org/apache/hadoop/hbase/util/Bytes.toBytes:(Ljava/lang/String;)[B
     179: ldc           #27                 // String 3
     181: invokestatic  #13                 // Method org/apache/hadoop/hbase/util/Bytes.toBytes:(Ljava/lang/String;)[B
     184: ldc2_w        #17                 // long 9223372036854775807l
     187: ldc           #27                 // String 3
     189: invokestatic  #13                 // Method org/apache/hadoop/hbase/util/Bytes.toBytes:(Ljava/lang/String;)[B
     192: iconst_3
     193: anewarray     #19                 // class org/apache/hadoop/hbase/Tag
     196: dup
     197: iconst_0
     198: new           #20                 // class org/apache/hadoop/hbase/ArrayBackedTag
     201: dup
     202: iconst_2
     203: ldc           #28                 // String teststring4
     205: invokestatic  #13                 // Method org/apache/hadoop/hbase/util/Bytes.toBytes:(Ljava/lang/String;)[B
     208: invokespecial #22                 // Method org/apache/hadoop/hbase/ArrayBackedTag."<init>":(B[B)V
     211: aastore
     212: dup
     213: iconst_1
     214: new           #20                 // class org/apache/hadoop/hbase/ArrayBackedTag
     217: dup
     218: iconst_2
     219: ldc           #29                 // String teststring5
     221: invokestatic  #13                 // Method org/apache/hadoop/hbase/util/Bytes.toBytes:(Ljava/lang/String;)[B
     224: invokespecial #22                 // Method org/apache/hadoop/hbase/ArrayBackedTag."<init>":(B[B)V
     227: aastore
     228: dup
     229: iconst_2
     230: new           #20                 // class org/apache/hadoop/hbase/ArrayBackedTag
     233: dup
     234: iconst_1
     235: ldc           #30                 // String teststring6
     237: invokestatic  #13                 // Method org/apache/hadoop/hbase/util/Bytes.toBytes:(Ljava/lang/String;)[B
     240: invokespecial #22                 // Method org/apache/hadoop/hbase/ArrayBackedTag."<init>":(B[B)V
     243: aastore
     244: invokespecial #24                 // Method org/apache/hadoop/hbase/KeyValue."<init>":([B[B[BJ[B[Lorg/apache/hadoop/hbase/Tag;)V
     247: astore        8
     249: aload         5
     251: aload         6
     253: invokeinterface #31,  2           // InterfaceMethod org/apache/hadoop/hbase/codec/Codec$Encoder.write:(Lorg/apache/hadoop/hbase/Cell;)V
     258: aload         5
     260: aload         7
     262: invokeinterface #31,  2           // InterfaceMethod org/apache/hadoop/hbase/codec/Codec$Encoder.write:(Lorg/apache/hadoop/hbase/Cell;)V
     267: aload         5
     269: aload         8
     271: invokeinterface #31,  2           // InterfaceMethod org/apache/hadoop/hbase/codec/Codec$Encoder.write:(Lorg/apache/hadoop/hbase/Cell;)V
     276: aload         5
     278: invokeinterface #32,  1           // InterfaceMethod org/apache/hadoop/hbase/codec/Codec$Encoder.flush:()V
     283: aload_3
     284: invokevirtual #33                 // Method java/io/DataOutputStream.close:()V
     287: aload_2
     288: invokevirtual #34                 // Method org/apache/hbase/thirdparty/com/google/common/io/CountingOutputStream.getCount:()J
     291: lstore        9
     293: new           #35                 // class org/apache/hbase/thirdparty/com/google/common/io/CountingInputStream
     296: dup
     297: new           #36                 // class java/io/ByteArrayInputStream
     300: dup
     301: aload_1
     302: invokevirtual #37                 // Method java/io/ByteArrayOutputStream.toByteArray:()[B
     305: invokespecial #38                 // Method java/io/ByteArrayInputStream."<init>":([B)V
     308: invokespecial #39                 // Method org/apache/hbase/thirdparty/com/google/common/io/CountingInputStream."<init>":(Ljava/io/InputStream;)V
     311: astore        11
     313: new           #40                 // class java/io/DataInputStream
     316: dup
     317: aload         11
     319: invokespecial #41                 // Method java/io/DataInputStream."<init>":(Ljava/io/InputStream;)V
     322: astore        12
     324: aload         4
     326: aload         12
     328: invokeinterface #42,  2           // InterfaceMethod org/apache/hadoop/hbase/codec/Codec.getDecoder:(Ljava/io/InputStream;)Lorg/apache/hadoop/hbase/codec/Codec$Decoder;
     333: astore        13
     335: aload         13
     337: invokeinterface #43,  1           // InterfaceMethod org/apache/hadoop/hbase/codec/Codec$Decoder.advance:()Z
     342: invokestatic  #44                 // Method org/junit/Assert.assertTrue:(Z)V
     345: aload         13
     347: invokeinterface #45,  1           // InterfaceMethod org/apache/hadoop/hbase/codec/Codec$Decoder.current:()Lorg/apache/hadoop/hbase/Cell;
     352: astore        14
     354: aload         14
     356: aload         6
     358: invokestatic  #46                 // Method org/apache/hadoop/hbase/CellUtil.equals:(Lorg/apache/hadoop/hbase/Cell;Lorg/apache/hadoop/hbase/Cell;)Z
     361: invokestatic  #44                 // Method org/junit/Assert.assertTrue:(Z)V
     364: aload         14
     366: invokestatic  #47                 // Method org/apache/hadoop/hbase/PrivateCellUtil.getTags:(Lorg/apache/hadoop/hbase/Cell;)Ljava/util/List;
     369: astore        15
     371: ldc2_w        #48                 // long 2l
     374: aload         15
     376: invokeinterface #50,  1           // InterfaceMethod java/util/List.size:()I
     381: i2l
     382: invokestatic  #51                 // Method org/junit/Assert.assertEquals:(JJ)V
     385: aload         15
     387: iconst_0
     388: invokeinterface #52,  2           // InterfaceMethod java/util/List.get:(I)Ljava/lang/Object;
     393: checkcast     #19                 // class org/apache/hadoop/hbase/Tag
     396: astore        16
     398: lconst_1
     399: aload         16
     401: invokeinterface #53,  1           // InterfaceMethod org/apache/hadoop/hbase/Tag.getType:()B
     406: i2l
     407: invokestatic  #51                 // Method org/junit/Assert.assertEquals:(JJ)V
     410: ldc           #21                 // String teststring1
     412: invokestatic  #13                 // Method org/apache/hadoop/hbase/util/Bytes.toBytes:(Ljava/lang/String;)[B
     415: aload         16
     417: invokestatic  #54                 // InterfaceMethod org/apache/hadoop/hbase/Tag.cloneValue:(Lorg/apache/hadoop/hbase/Tag;)[B
     420: invokestatic  #55                 // Method org/apache/hadoop/hbase/util/Bytes.equals:([B[B)Z
     423: invokestatic  #44                 // Method org/junit/Assert.assertTrue:(Z)V
     426: aload         15
     428: iconst_1
     429: invokeinterface #52,  2           // InterfaceMethod java/util/List.get:(I)Ljava/lang/Object;
     434: checkcast     #19                 // class org/apache/hadoop/hbase/Tag
     437: astore        16
     439: ldc2_w        #48                 // long 2l
     442: aload         16
     444: invokeinterface #53,  1           // InterfaceMethod org/apache/hadoop/hbase/Tag.getType:()B
     449: i2l
     450: invokestatic  #51                 // Method org/junit/Assert.assertEquals:(JJ)V
     453: ldc           #23                 // String teststring2
     455: invokestatic  #13                 // Method org/apache/hadoop/hbase/util/Bytes.toBytes:(Ljava/lang/String;)[B
     458: aload         16
     460: invokestatic  #54                 // InterfaceMethod org/apache/hadoop/hbase/Tag.cloneValue:(Lorg/apache/hadoop/hbase/Tag;)[B
     463: invokestatic  #55                 // Method org/apache/hadoop/hbase/util/Bytes.equals:([B[B)Z
     466: invokestatic  #44                 // Method org/junit/Assert.assertTrue:(Z)V
     469: aload         13
     471: invokeinterface #43,  1           // InterfaceMethod org/apache/hadoop/hbase/codec/Codec$Decoder.advance:()Z
     476: invokestatic  #44                 // Method org/junit/Assert.assertTrue:(Z)V
     479: aload         13
     481: invokeinterface #45,  1           // InterfaceMethod org/apache/hadoop/hbase/codec/Codec$Decoder.current:()Lorg/apache/hadoop/hbase/Cell;
     486: astore        14
     488: aload         14
     490: aload         7
     492: invokestatic  #46                 // Method org/apache/hadoop/hbase/CellUtil.equals:(Lorg/apache/hadoop/hbase/Cell;Lorg/apache/hadoop/hbase/Cell;)Z
     495: invokestatic  #44                 // Method org/junit/Assert.assertTrue:(Z)V
     498: aload         14
     500: invokestatic  #47                 // Method org/apache/hadoop/hbase/PrivateCellUtil.getTags:(Lorg/apache/hadoop/hbase/Cell;)Ljava/util/List;
     503: astore        15
     505: lconst_1
     506: aload         15
     508: invokeinterface #50,  1           // InterfaceMethod java/util/List.size:()I
     513: i2l
     514: invokestatic  #51                 // Method org/junit/Assert.assertEquals:(JJ)V
     517: aload         15
     519: iconst_0
     520: invokeinterface #52,  2           // InterfaceMethod java/util/List.get:(I)Ljava/lang/Object;
     525: checkcast     #19                 // class org/apache/hadoop/hbase/Tag
     528: astore        16
     530: lconst_1
     531: aload         16
     533: invokeinterface #53,  1           // InterfaceMethod org/apache/hadoop/hbase/Tag.getType:()B
     538: i2l
     539: invokestatic  #51                 // Method org/junit/Assert.assertEquals:(JJ)V
     542: ldc           #26                 // String teststring3
     544: invokestatic  #13                 // Method org/apache/hadoop/hbase/util/Bytes.toBytes:(Ljava/lang/String;)[B
     547: aload         16
     549: invokestatic  #54                 // InterfaceMethod org/apache/hadoop/hbase/Tag.cloneValue:(Lorg/apache/hadoop/hbase/Tag;)[B
     552: invokestatic  #55                 // Method org/apache/hadoop/hbase/util/Bytes.equals:([B[B)Z
     555: invokestatic  #44                 // Method org/junit/Assert.assertTrue:(Z)V
     558: aload         13
     560: invokeinterface #43,  1           // InterfaceMethod org/apache/hadoop/hbase/codec/Codec$Decoder.advance:()Z
     565: invokestatic  #44                 // Method org/junit/Assert.assertTrue:(Z)V
     568: aload         13
     570: invokeinterface #45,  1           // InterfaceMethod org/apache/hadoop/hbase/codec/Codec$Decoder.current:()Lorg/apache/hadoop/hbase/Cell;
     575: astore        14
     577: aload         14
     579: aload         8
     581: invokestatic  #46                 // Method org/apache/hadoop/hbase/CellUtil.equals:(Lorg/apache/hadoop/hbase/Cell;Lorg/apache/hadoop/hbase/Cell;)Z
     584: invokestatic  #44                 // Method org/junit/Assert.assertTrue:(Z)V
     587: aload         14
     589: invokestatic  #47                 // Method org/apache/hadoop/hbase/PrivateCellUtil.getTags:(Lorg/apache/hadoop/hbase/Cell;)Ljava/util/List;
     592: astore        15
     594: ldc2_w        #56                 // long 3l
     597: aload         15
     599: invokeinterface #50,  1           // InterfaceMethod java/util/List.size:()I
     604: i2l
     605: invokestatic  #51                 // Method org/junit/Assert.assertEquals:(JJ)V
     608: aload         15
     610: iconst_0
     611: invokeinterface #52,  2           // InterfaceMethod java/util/List.get:(I)Ljava/lang/Object;
     616: checkcast     #19                 // class org/apache/hadoop/hbase/Tag
     619: astore        16
     621: ldc2_w        #48                 // long 2l
     624: aload         16
     626: invokeinterface #53,  1           // InterfaceMethod org/apache/hadoop/hbase/Tag.getType:()B
     631: i2l
     632: invokestatic  #51                 // Method org/junit/Assert.assertEquals:(JJ)V
     635: ldc           #28                 // String teststring4
     637: invokestatic  #13                 // Method org/apache/hadoop/hbase/util/Bytes.toBytes:(Ljava/lang/String;)[B
     640: aload         16
     642: invokestatic  #54                 // InterfaceMethod org/apache/hadoop/hbase/Tag.cloneValue:(Lorg/apache/hadoop/hbase/Tag;)[B
     645: invokestatic  #55                 // Method org/apache/hadoop/hbase/util/Bytes.equals:([B[B)Z
     648: invokestatic  #44                 // Method org/junit/Assert.assertTrue:(Z)V
     651: aload         15
     653: iconst_1
     654: invokeinterface #52,  2           // InterfaceMethod java/util/List.get:(I)Ljava/lang/Object;
     659: checkcast     #19                 // class org/apache/hadoop/hbase/Tag
     662: astore        16
     664: ldc2_w        #48                 // long 2l
     667: aload         16
     669: invokeinterface #53,  1           // InterfaceMethod org/apache/hadoop/hbase/Tag.getType:()B
     674: i2l
     675: invokestatic  #51                 // Method org/junit/Assert.assertEquals:(JJ)V
     678: ldc           #29                 // String teststring5
     680: invokestatic  #13                 // Method org/apache/hadoop/hbase/util/Bytes.toBytes:(Ljava/lang/String;)[B
     683: aload         16
     685: invokestatic  #54                 // InterfaceMethod org/apache/hadoop/hbase/Tag.cloneValue:(Lorg/apache/hadoop/hbase/Tag;)[B
     688: invokestatic  #55                 // Method org/apache/hadoop/hbase/util/Bytes.equals:([B[B)Z
     691: invokestatic  #44                 // Method org/junit/Assert.assertTrue:(Z)V
     694: aload         15
     696: iconst_2
     697: invokeinterface #52,  2           // InterfaceMethod java/util/List.get:(I)Ljava/lang/Object;
     702: checkcast     #19                 // class org/apache/hadoop/hbase/Tag
     705: astore        16
     707: lconst_1
     708: aload         16
     710: invokeinterface #53,  1           // InterfaceMethod org/apache/hadoop/hbase/Tag.getType:()B
     715: i2l
     716: invokestatic  #51                 // Method org/junit/Assert.assertEquals:(JJ)V
     719: ldc           #30                 // String teststring6
     721: invokestatic  #13                 // Method org/apache/hadoop/hbase/util/Bytes.toBytes:(Ljava/lang/String;)[B
     724: aload         16
     726: invokestatic  #54                 // InterfaceMethod org/apache/hadoop/hbase/Tag.cloneValue:(Lorg/apache/hadoop/hbase/Tag;)[B
     729: invokestatic  #55                 // Method org/apache/hadoop/hbase/util/Bytes.equals:([B[B)Z
     732: invokestatic  #44                 // Method org/junit/Assert.assertTrue:(Z)V
     735: aload         13
     737: invokeinterface #43,  1           // InterfaceMethod org/apache/hadoop/hbase/codec/Codec$Decoder.advance:()Z
     742: invokestatic  #58                 // Method org/junit/Assert.assertFalse:(Z)V
     745: aload         12
     747: invokevirtual #59                 // Method java/io/DataInputStream.close:()V
     750: lload         9
     752: aload         11
     754: invokevirtual #60                 // Method org/apache/hbase/thirdparty/com/google/common/io/CountingInputStream.getCount:()J
     757: invokestatic  #51                 // Method org/junit/Assert.assertEquals:(JJ)V
     760: return

  static {};
    Code:
       0: ldc           #61                 // class org/apache/hadoop/hbase/codec/TestKeyValueCodecWithTags
       2: invokestatic  #62                 // Method org/apache/hadoop/hbase/HBaseClassTestRule.forClass:(Ljava/lang/Class;)Lorg/apache/hadoop/hbase/HBaseClassTestRule;
       5: putstatic     #63                 // Field CLASS_RULE:Lorg/apache/hadoop/hbase/HBaseClassTestRule;
       8: return
}
