Compiled from "TestSecureIPC.java"
class org.apache.hadoop.hbase.security.TestSecureIPC$1 implements java.lang.Thread$UncaughtExceptionHandler {
  final java.lang.Throwable[] val$exception;

  final org.apache.hadoop.hbase.security.TestSecureIPC this$0;

  org.apache.hadoop.hbase.security.TestSecureIPC$1(org.apache.hadoop.hbase.security.TestSecureIPC, java.lang.Throwable[]);
    Code:
       0: aload_0
       1: aload_1
       2: putfield      #1                  // Field this$0:Lorg/apache/hadoop/hbase/security/TestSecureIPC;
       5: aload_0
       6: aload_2
       7: putfield      #2                  // Field val$exception:[Ljava/lang/Throwable;
      10: aload_0
      11: invokespecial #3                  // Method java/lang/Object."<init>":()V
      14: return

  public void uncaughtException(java.lang.Thread, java.lang.Throwable);
    Code:
       0: aload_0
       1: getfield      #2                  // Field val$exception:[Ljava/lang/Throwable;
       4: iconst_0
       5: aload_2
       6: aastore
       7: return
}
