Compiled from "TestStripeCompactionPolicy.java"
class org.apache.hadoop.hbase.regionserver.compactions.TestStripeCompactionPolicy$3 extends org.apache.hadoop.hbase.regionserver.compactions.StripeCompactor {
  final org.apache.hadoop.hbase.regionserver.compactions.TestStripeCompactionPolicy$Scanner val$scanner;

  final org.apache.hadoop.hbase.regionserver.compactions.TestStripeCompactionPolicy this$0;

  org.apache.hadoop.hbase.regionserver.compactions.TestStripeCompactionPolicy$3(org.apache.hadoop.hbase.regionserver.compactions.TestStripeCompactionPolicy, org.apache.hadoop.conf.Configuration, org.apache.hadoop.hbase.regionserver.HStore, org.apache.hadoop.hbase.regionserver.compactions.TestStripeCompactionPolicy$Scanner);
    Code:
       0: aload_0
       1: aload_1
       2: putfield      #1                  // Field this$0:Lorg/apache/hadoop/hbase/regionserver/compactions/TestStripeCompactionPolicy;
       5: aload_0
       6: aload         4
       8: putfield      #2                  // Field val$scanner:Lorg/apache/hadoop/hbase/regionserver/compactions/TestStripeCompactionPolicy$Scanner;
      11: aload_0
      12: aload_2
      13: aload_3
      14: invokespecial #3                  // Method org/apache/hadoop/hbase/regionserver/compactions/StripeCompactor."<init>":(Lorg/apache/hadoop/conf/Configuration;Lorg/apache/hadoop/hbase/regionserver/HStore;)V
      17: return

  protected org.apache.hadoop.hbase.regionserver.InternalScanner createScanner(org.apache.hadoop.hbase.regionserver.HStore, org.apache.hadoop.hbase.regionserver.ScanInfo, java.util.List<org.apache.hadoop.hbase.regionserver.StoreFileScanner>, long, long, byte[], byte[]) throws java.io.IOException;
    Code:
       0: aload_0
       1: getfield      #2                  // Field val$scanner:Lorg/apache/hadoop/hbase/regionserver/compactions/TestStripeCompactionPolicy$Scanner;
       4: areturn

  protected org.apache.hadoop.hbase.regionserver.InternalScanner createScanner(org.apache.hadoop.hbase.regionserver.HStore, org.apache.hadoop.hbase.regionserver.ScanInfo, java.util.List<org.apache.hadoop.hbase.regionserver.StoreFileScanner>, org.apache.hadoop.hbase.regionserver.ScanType, long, long) throws java.io.IOException;
    Code:
       0: aload_0
       1: getfield      #2                  // Field val$scanner:Lorg/apache/hadoop/hbase/regionserver/compactions/TestStripeCompactionPolicy$Scanner;
       4: areturn
}
