Compiled from "TestWALSplit.java"
class org.apache.hadoop.hbase.wal.TestWALSplit$3 extends java.lang.Thread {
  final java.util.concurrent.atomic.AtomicBoolean val$stop;

  final org.apache.hadoop.hbase.wal.TestWALSplit this$0;

  org.apache.hadoop.hbase.wal.TestWALSplit$3(org.apache.hadoop.hbase.wal.TestWALSplit, java.lang.String, java.util.concurrent.atomic.AtomicBoolean);
    Code:
       0: aload_0
       1: aload_1
       2: putfield      #1                  // Field this$0:Lorg/apache/hadoop/hbase/wal/TestWALSplit;
       5: aload_0
       6: aload_3
       7: putfield      #2                  // Field val$stop:Ljava/util/concurrent/atomic/AtomicBoolean;
      10: aload_0
      11: aload_2
      12: invokespecial #3                  // Method java/lang/Thread."<init>":(Ljava/lang/String;)V
      15: return

  public void run();
    Code:
       0: aload_0
       1: getfield      #2                  // Field val$stop:Ljava/util/concurrent/atomic/AtomicBoolean;
       4: invokevirtual #4                  // Method java/util/concurrent/atomic/AtomicBoolean.get:()Z
       7: ifne          19
      10: ldc2_w        #5                  // long 10l
      13: invokestatic  #7                  // Method org/apache/hadoop/hbase/util/Threads.sleep:(J)V
      16: goto          0
      19: return
}
