Compiled from "TestReplicasClient.java"
public class org.apache.hadoop.hbase.client.TestReplicasClient {
  public static final org.apache.hadoop.hbase.HBaseClassTestRule CLASS_RULE;

  public org.apache.hadoop.hbase.client.TestReplicasClient();
    Code:
       0: aload_0
       1: invokespecial #2                  // Method java/lang/Object."<init>":()V
       4: return

  public static void beforeClass() throws java.lang.Exception;
    Code:
       0: getstatic     #3                  // Field HTU:Lorg/apache/hadoop/hbase/HBaseTestingUtility;
       3: invokevirtual #4                  // Method org/apache/hadoop/hbase/HBaseTestingUtility.getConfiguration:()Lorg/apache/hadoop/conf/Configuration;
       6: ldc           #6                  // String hbase.regionserver.storefile.refresh.period
       8: sipush        1000
      11: invokevirtual #8                  // Method org/apache/hadoop/conf/Configuration.setInt:(Ljava/lang/String;I)V
      14: getstatic     #3                  // Field HTU:Lorg/apache/hadoop/hbase/HBaseTestingUtility;
      17: invokevirtual #4                  // Method org/apache/hadoop/hbase/HBaseTestingUtility.getConfiguration:()Lorg/apache/hadoop/conf/Configuration;
      20: ldc           #9                  // String hbase.client.log.scanner.activity
      22: iconst_1
      23: invokevirtual #10                 // Method org/apache/hadoop/conf/Configuration.setBoolean:(Ljava/lang/String;Z)V
      26: getstatic     #3                  // Field HTU:Lorg/apache/hadoop/hbase/HBaseTestingUtility;
      29: invokevirtual #4                  // Method org/apache/hadoop/hbase/HBaseTestingUtility.getConfiguration:()Lorg/apache/hadoop/conf/Configuration;
      32: ldc           #12                 // String hbase.client.metrics.enable
      34: iconst_1
      35: invokevirtual #10                 // Method org/apache/hadoop/conf/Configuration.setBoolean:(Ljava/lang/String;Z)V
      38: getstatic     #3                  // Field HTU:Lorg/apache/hadoop/hbase/HBaseTestingUtility;
      41: invokevirtual #4                  // Method org/apache/hadoop/hbase/HBaseTestingUtility.getConfiguration:()Lorg/apache/hadoop/conf/Configuration;
      44: invokestatic  #13                 // Method org/apache/hadoop/hbase/client/ConnectionUtils.setupMasterlessConnection:(Lorg/apache/hadoop/conf/Configuration;)V
      47: getstatic     #3                  // Field HTU:Lorg/apache/hadoop/hbase/HBaseTestingUtility;
      50: iconst_1
      51: invokevirtual #14                 // Method org/apache/hadoop/hbase/HBaseTestingUtility.startMiniCluster:(I)Lorg/apache/hadoop/hbase/MiniHBaseCluster;
      54: pop
      55: getstatic     #3                  // Field HTU:Lorg/apache/hadoop/hbase/HBaseTestingUtility;
      58: ldc           #7                  // class org/apache/hadoop/hbase/client/TestReplicasClient
      60: invokevirtual #15                 // Method java/lang/Class.getSimpleName:()Ljava/lang/String;
      63: invokevirtual #16                 // Method org/apache/hadoop/hbase/HBaseTestingUtility.createTableDescriptor:(Ljava/lang/String;)Lorg/apache/hadoop/hbase/HTableDescriptor;
      66: astore_0
      67: aload_0
      68: ldc           #17                 // class org/apache/hadoop/hbase/client/TestReplicasClient$SlowMeCopro
      70: invokevirtual #18                 // Method java/lang/Class.getName:()Ljava/lang/String;
      73: invokevirtual #19                 // Method org/apache/hadoop/hbase/HTableDescriptor.addCoprocessor:(Ljava/lang/String;)Lorg/apache/hadoop/hbase/HTableDescriptor;
      76: pop
      77: getstatic     #3                  // Field HTU:Lorg/apache/hadoop/hbase/HBaseTestingUtility;
      80: aload_0
      81: iconst_1
      82: anewarray     #20                 // class "[B"
      85: dup
      86: iconst_0
      87: getstatic     #21                 // Field f:[B
      90: aastore
      91: aconst_null
      92: invokevirtual #22                 // Method org/apache/hadoop/hbase/HBaseTestingUtility.createTable:(Lorg/apache/hadoop/hbase/client/TableDescriptor;[[BLorg/apache/hadoop/conf/Configuration;)Lorg/apache/hadoop/hbase/client/Table;
      95: putstatic     #23                 // Field table:Lorg/apache/hadoop/hbase/client/Table;
      98: getstatic     #3                  // Field HTU:Lorg/apache/hadoop/hbase/HBaseTestingUtility;
     101: invokevirtual #24                 // Method org/apache/hadoop/hbase/HBaseTestingUtility.getConnection:()Lorg/apache/hadoop/hbase/client/Connection;
     104: aload_0
     105: invokevirtual #25                 // Method org/apache/hadoop/hbase/HTableDescriptor.getTableName:()Lorg/apache/hadoop/hbase/TableName;
     108: invokeinterface #26,  2           // InterfaceMethod org/apache/hadoop/hbase/client/Connection.getRegionLocator:(Lorg/apache/hadoop/hbase/TableName;)Lorg/apache/hadoop/hbase/client/RegionLocator;
     113: astore_1
     114: aconst_null
     115: astore_2
     116: aload_1
     117: getstatic     #27                 // Field row:[B
     120: iconst_0
     121: invokeinterface #28,  3           // InterfaceMethod org/apache/hadoop/hbase/client/RegionLocator.getRegionLocation:([BZ)Lorg/apache/hadoop/hbase/HRegionLocation;
     126: invokevirtual #29                 // Method org/apache/hadoop/hbase/HRegionLocation.getRegionInfo:()Lorg/apache/hadoop/hbase/HRegionInfo;
     129: putstatic     #30                 // Field hriPrimary:Lorg/apache/hadoop/hbase/HRegionInfo;
     132: aload_1
     133: ifnull        211
     136: aload_2
     137: ifnull        158
     140: aload_1
     141: invokeinterface #31,  1           // InterfaceMethod org/apache/hadoop/hbase/client/RegionLocator.close:()V
     146: goto          211
     149: astore_3
     150: aload_2
     151: aload_3
     152: invokevirtual #33                 // Method java/lang/Throwable.addSuppressed:(Ljava/lang/Throwable;)V
     155: goto          211
     158: aload_1
     159: invokeinterface #31,  1           // InterfaceMethod org/apache/hadoop/hbase/client/RegionLocator.close:()V
     164: goto          211
     167: astore_3
     168: aload_3
     169: astore_2
     170: aload_3
     171: athrow
     172: astore        4
     174: aload_1
     175: ifnull        208
     178: aload_2
     179: ifnull        202
     182: aload_1
     183: invokeinterface #31,  1           // InterfaceMethod org/apache/hadoop/hbase/client/RegionLocator.close:()V
     188: goto          208
     191: astore        5
     193: aload_2
     194: aload         5
     196: invokevirtual #33                 // Method java/lang/Throwable.addSuppressed:(Ljava/lang/Throwable;)V
     199: goto          208
     202: aload_1
     203: invokeinterface #31,  1           // InterfaceMethod org/apache/hadoop/hbase/client/RegionLocator.close:()V
     208: aload         4
     210: athrow
     211: new           #34                 // class org/apache/hadoop/hbase/HRegionInfo
     214: dup
     215: getstatic     #30                 // Field hriPrimary:Lorg/apache/hadoop/hbase/HRegionInfo;
     218: invokevirtual #35                 // Method org/apache/hadoop/hbase/HRegionInfo.getTable:()Lorg/apache/hadoop/hbase/TableName;
     221: getstatic     #30                 // Field hriPrimary:Lorg/apache/hadoop/hbase/HRegionInfo;
     224: invokevirtual #36                 // Method org/apache/hadoop/hbase/HRegionInfo.getStartKey:()[B
     227: getstatic     #30                 // Field hriPrimary:Lorg/apache/hadoop/hbase/HRegionInfo;
     230: invokevirtual #37                 // Method org/apache/hadoop/hbase/HRegionInfo.getEndKey:()[B
     233: getstatic     #30                 // Field hriPrimary:Lorg/apache/hadoop/hbase/HRegionInfo;
     236: invokevirtual #38                 // Method org/apache/hadoop/hbase/HRegionInfo.isSplit:()Z
     239: getstatic     #30                 // Field hriPrimary:Lorg/apache/hadoop/hbase/HRegionInfo;
     242: invokevirtual #39                 // Method org/apache/hadoop/hbase/HRegionInfo.getRegionId:()J
     245: iconst_1
     246: invokespecial #40                 // Method org/apache/hadoop/hbase/HRegionInfo."<init>":(Lorg/apache/hadoop/hbase/TableName;[B[BZJI)V
     249: putstatic     #41                 // Field hriSecondary:Lorg/apache/hadoop/hbase/HRegionInfo;
     252: getstatic     #1                  // Field LOG:Lorg/slf4j/Logger;
     255: ldc           #42                 // String Master is going to be stopped
     257: invokeinterface #43,  2           // InterfaceMethod org/slf4j/Logger.info:(Ljava/lang/String;)V
     262: getstatic     #3                  // Field HTU:Lorg/apache/hadoop/hbase/HBaseTestingUtility;
     265: invokestatic  #44                 // Method org/apache/hadoop/hbase/regionserver/TestRegionServerNoMaster.stopMasterAndAssignMeta:(Lorg/apache/hadoop/hbase/HBaseTestingUtility;)V
     268: new           #45                 // class org/apache/hadoop/conf/Configuration
     271: dup
     272: getstatic     #3                  // Field HTU:Lorg/apache/hadoop/hbase/HBaseTestingUtility;
     275: invokevirtual #4                  // Method org/apache/hadoop/hbase/HBaseTestingUtility.getConfiguration:()Lorg/apache/hadoop/conf/Configuration;
     278: invokespecial #46                 // Method org/apache/hadoop/conf/Configuration."<init>":(Lorg/apache/hadoop/conf/Configuration;)V
     281: astore_1
     282: aload_1
     283: ldc           #48                 // String hbase.client.retries.number
     285: iconst_1
     286: invokevirtual #8                  // Method org/apache/hadoop/conf/Configuration.setInt:(Ljava/lang/String;I)V
     289: getstatic     #1                  // Field LOG:Lorg/slf4j/Logger;
     292: ldc           #49                 // String Master has stopped
     294: invokeinterface #43,  2           // InterfaceMethod org/slf4j/Logger.info:(Ljava/lang/String;)V
     299: return
    Exception table:
       from    to  target type
         140   146   149   Class java/lang/Throwable
         116   132   167   Class java/lang/Throwable
         116   132   172   any
         182   188   191   Class java/lang/Throwable
         167   174   172   any

  public static void afterClass() throws java.lang.Exception;
    Code:
       0: iconst_0
       1: putstatic     #50                 // Field org/apache/hadoop/hbase/regionserver/HRegionServer.TEST_SKIP_REPORTING_TRANSITION:Z
       4: getstatic     #23                 // Field table:Lorg/apache/hadoop/hbase/client/Table;
       7: ifnull        18
      10: getstatic     #23                 // Field table:Lorg/apache/hadoop/hbase/client/Table;
      13: invokeinterface #51,  1           // InterfaceMethod org/apache/hadoop/hbase/client/Table.close:()V
      18: getstatic     #3                  // Field HTU:Lorg/apache/hadoop/hbase/HBaseTestingUtility;
      21: invokevirtual #52                 // Method org/apache/hadoop/hbase/HBaseTestingUtility.shutdownMiniCluster:()V
      24: return

  public void before() throws java.io.IOException;
    Code:
       0: getstatic     #3                  // Field HTU:Lorg/apache/hadoop/hbase/HBaseTestingUtility;
       3: invokevirtual #53                 // Method org/apache/hadoop/hbase/HBaseTestingUtility.getAdmin:()Lorg/apache/hadoop/hbase/client/Admin;
       6: invokeinterface #54,  1           // InterfaceMethod org/apache/hadoop/hbase/client/Admin.getConnection:()Lorg/apache/hadoop/hbase/client/Connection;
      11: checkcast     #55                 // class org/apache/hadoop/hbase/client/ClusterConnection
      14: invokeinterface #56,  1           // InterfaceMethod org/apache/hadoop/hbase/client/ClusterConnection.clearRegionLocationCache:()V
      19: aload_0
      20: getstatic     #30                 // Field hriPrimary:Lorg/apache/hadoop/hbase/HRegionInfo;
      23: invokespecial #57                 // Method openRegion:(Lorg/apache/hadoop/hbase/HRegionInfo;)V
      26: goto          30
      29: astore_1
      30: aload_0
      31: getstatic     #41                 // Field hriSecondary:Lorg/apache/hadoop/hbase/HRegionInfo;
      34: invokespecial #57                 // Method openRegion:(Lorg/apache/hadoop/hbase/HRegionInfo;)V
      37: goto          41
      40: astore_1
      41: return
    Exception table:
       from    to  target type
          19    26    29   Class java/lang/Exception
          30    37    40   Class java/lang/Exception

  public void after() throws java.io.IOException, org.apache.zookeeper.KeeperException;
    Code:
       0: aload_0
       1: getstatic     #41                 // Field hriSecondary:Lorg/apache/hadoop/hbase/HRegionInfo;
       4: invokespecial #59                 // Method closeRegion:(Lorg/apache/hadoop/hbase/HRegionInfo;)V
       7: goto          11
      10: astore_1
      11: aload_0
      12: getstatic     #30                 // Field hriPrimary:Lorg/apache/hadoop/hbase/HRegionInfo;
      15: invokespecial #59                 // Method closeRegion:(Lorg/apache/hadoop/hbase/HRegionInfo;)V
      18: goto          22
      21: astore_1
      22: getstatic     #3                  // Field HTU:Lorg/apache/hadoop/hbase/HBaseTestingUtility;
      25: invokevirtual #53                 // Method org/apache/hadoop/hbase/HBaseTestingUtility.getAdmin:()Lorg/apache/hadoop/hbase/client/Admin;
      28: invokeinterface #54,  1           // InterfaceMethod org/apache/hadoop/hbase/client/Admin.getConnection:()Lorg/apache/hadoop/hbase/client/Connection;
      33: checkcast     #55                 // class org/apache/hadoop/hbase/client/ClusterConnection
      36: invokeinterface #56,  1           // InterfaceMethod org/apache/hadoop/hbase/client/ClusterConnection.clearRegionLocationCache:()V
      41: return
    Exception table:
       from    to  target type
           0     7    10   Class java/lang/Exception
          11    18    21   Class java/lang/Exception

  public void testUseRegionWithoutReplica() throws java.lang.Exception;
    Code:
       0: ldc           #89                 // String testUseRegionWithoutReplica
       2: invokestatic  #90                 // Method org/apache/hadoop/hbase/util/Bytes.toBytes:(Ljava/lang/String;)[B
       5: astore_1
       6: aload_0
       7: getstatic     #41                 // Field hriSecondary:Lorg/apache/hadoop/hbase/HRegionInfo;
      10: invokespecial #57                 // Method openRegion:(Lorg/apache/hadoop/hbase/HRegionInfo;)V
      13: invokestatic  #91                 // Method org/apache/hadoop/hbase/client/TestReplicasClient$SlowMeCopro.getPrimaryCdl:()Ljava/util/concurrent/atomic/AtomicReference;
      16: new           #92                 // class java/util/concurrent/CountDownLatch
      19: dup
      20: iconst_0
      21: invokespecial #93                 // Method java/util/concurrent/CountDownLatch."<init>":(I)V
      24: invokevirtual #94                 // Method java/util/concurrent/atomic/AtomicReference.set:(Ljava/lang/Object;)V
      27: new           #95                 // class org/apache/hadoop/hbase/client/Get
      30: dup
      31: aload_1
      32: invokespecial #96                 // Method org/apache/hadoop/hbase/client/Get."<init>":([B)V
      35: astore_2
      36: getstatic     #23                 // Field table:Lorg/apache/hadoop/hbase/client/Table;
      39: aload_2
      40: invokeinterface #97,  2           // InterfaceMethod org/apache/hadoop/hbase/client/Table.get:(Lorg/apache/hadoop/hbase/client/Get;)Lorg/apache/hadoop/hbase/client/Result;
      45: astore_3
      46: aload_3
      47: invokevirtual #98                 // Method org/apache/hadoop/hbase/client/Result.isStale:()Z
      50: invokestatic  #86                 // Method org/junit/Assert.assertFalse:(Z)V
      53: aload_0
      54: getstatic     #41                 // Field hriSecondary:Lorg/apache/hadoop/hbase/HRegionInfo;
      57: invokespecial #59                 // Method closeRegion:(Lorg/apache/hadoop/hbase/HRegionInfo;)V
      60: goto          75
      63: astore        4
      65: aload_0
      66: getstatic     #41                 // Field hriSecondary:Lorg/apache/hadoop/hbase/HRegionInfo;
      69: invokespecial #59                 // Method closeRegion:(Lorg/apache/hadoop/hbase/HRegionInfo;)V
      72: aload         4
      74: athrow
      75: return
    Exception table:
       from    to  target type
          27    53    63   any
          63    65    63   any

  public void testLocations() throws java.lang.Exception;
    Code:
       0: ldc           #99                 // String testLocations
       2: invokestatic  #90                 // Method org/apache/hadoop/hbase/util/Bytes.toBytes:(Ljava/lang/String;)[B
       5: astore_1
       6: aload_0
       7: getstatic     #41                 // Field hriSecondary:Lorg/apache/hadoop/hbase/HRegionInfo;
      10: invokespecial #57                 // Method openRegion:(Lorg/apache/hadoop/hbase/HRegionInfo;)V
      13: getstatic     #3                  // Field HTU:Lorg/apache/hadoop/hbase/HBaseTestingUtility;
      16: invokevirtual #53                 // Method org/apache/hadoop/hbase/HBaseTestingUtility.getAdmin:()Lorg/apache/hadoop/hbase/client/Admin;
      19: invokeinterface #54,  1           // InterfaceMethod org/apache/hadoop/hbase/client/Admin.getConnection:()Lorg/apache/hadoop/hbase/client/Connection;
      24: checkcast     #55                 // class org/apache/hadoop/hbase/client/ClusterConnection
      27: astore_2
      28: aload_2
      29: invokeinterface #56,  1           // InterfaceMethod org/apache/hadoop/hbase/client/ClusterConnection.clearRegionLocationCache:()V
      34: aload_2
      35: getstatic     #23                 // Field table:Lorg/apache/hadoop/hbase/client/Table;
      38: invokeinterface #100,  1          // InterfaceMethod org/apache/hadoop/hbase/client/Table.getName:()Lorg/apache/hadoop/hbase/TableName;
      43: aload_1
      44: iconst_0
      45: iconst_0
      46: invokeinterface #101,  5          // InterfaceMethod org/apache/hadoop/hbase/client/ClusterConnection.locateRegion:(Lorg/apache/hadoop/hbase/TableName;[BZZ)Lorg/apache/hadoop/hbase/RegionLocations;
      51: astore_3
      52: ldc2_w        #102                // long 2l
      55: aload_3
      56: invokevirtual #104                // Method org/apache/hadoop/hbase/RegionLocations.size:()I
      59: i2l
      60: invokestatic  #69                 // Method org/junit/Assert.assertEquals:(JJ)V
      63: aload_2
      64: getstatic     #23                 // Field table:Lorg/apache/hadoop/hbase/client/Table;
      67: invokeinterface #100,  1          // InterfaceMethod org/apache/hadoop/hbase/client/Table.getName:()Lorg/apache/hadoop/hbase/TableName;
      72: aload_1
      73: iconst_1
      74: iconst_0
      75: invokeinterface #101,  5          // InterfaceMethod org/apache/hadoop/hbase/client/ClusterConnection.locateRegion:(Lorg/apache/hadoop/hbase/TableName;[BZZ)Lorg/apache/hadoop/hbase/RegionLocations;
      80: astore_3
      81: ldc2_w        #102                // long 2l
      84: aload_3
      85: invokevirtual #104                // Method org/apache/hadoop/hbase/RegionLocations.size:()I
      88: i2l
      89: invokestatic  #69                 // Method org/junit/Assert.assertEquals:(JJ)V
      92: aload_2
      93: invokeinterface #56,  1           // InterfaceMethod org/apache/hadoop/hbase/client/ClusterConnection.clearRegionLocationCache:()V
      98: aload_2
      99: getstatic     #23                 // Field table:Lorg/apache/hadoop/hbase/client/Table;
     102: invokeinterface #100,  1          // InterfaceMethod org/apache/hadoop/hbase/client/Table.getName:()Lorg/apache/hadoop/hbase/TableName;
     107: aload_1
     108: iconst_1
     109: iconst_0
     110: invokeinterface #101,  5          // InterfaceMethod org/apache/hadoop/hbase/client/ClusterConnection.locateRegion:(Lorg/apache/hadoop/hbase/TableName;[BZZ)Lorg/apache/hadoop/hbase/RegionLocations;
     115: astore_3
     116: ldc2_w        #102                // long 2l
     119: aload_3
     120: invokevirtual #104                // Method org/apache/hadoop/hbase/RegionLocations.size:()I
     123: i2l
     124: invokestatic  #69                 // Method org/junit/Assert.assertEquals:(JJ)V
     127: aload_2
     128: getstatic     #23                 // Field table:Lorg/apache/hadoop/hbase/client/Table;
     131: invokeinterface #100,  1          // InterfaceMethod org/apache/hadoop/hbase/client/Table.getName:()Lorg/apache/hadoop/hbase/TableName;
     136: aload_1
     137: iconst_0
     138: iconst_0
     139: invokeinterface #101,  5          // InterfaceMethod org/apache/hadoop/hbase/client/ClusterConnection.locateRegion:(Lorg/apache/hadoop/hbase/TableName;[BZZ)Lorg/apache/hadoop/hbase/RegionLocations;
     144: astore_3
     145: ldc2_w        #102                // long 2l
     148: aload_3
     149: invokevirtual #104                // Method org/apache/hadoop/hbase/RegionLocations.size:()I
     152: i2l
     153: invokestatic  #69                 // Method org/junit/Assert.assertEquals:(JJ)V
     156: aload_0
     157: getstatic     #41                 // Field hriSecondary:Lorg/apache/hadoop/hbase/HRegionInfo;
     160: invokespecial #59                 // Method closeRegion:(Lorg/apache/hadoop/hbase/HRegionInfo;)V
     163: goto          178
     166: astore        4
     168: aload_0
     169: getstatic     #41                 // Field hriSecondary:Lorg/apache/hadoop/hbase/HRegionInfo;
     172: invokespecial #59                 // Method closeRegion:(Lorg/apache/hadoop/hbase/HRegionInfo;)V
     175: aload         4
     177: athrow
     178: return
    Exception table:
       from    to  target type
          28   156   166   any
         166   168   166   any

  public void testGetNoResultNoStaleRegionWithReplica() throws java.lang.Exception;
    Code:
       0: ldc           #105                // String testGetNoResultNoStaleRegionWithReplica
       2: invokestatic  #90                 // Method org/apache/hadoop/hbase/util/Bytes.toBytes:(Ljava/lang/String;)[B
       5: astore_1
       6: aload_0
       7: getstatic     #41                 // Field hriSecondary:Lorg/apache/hadoop/hbase/HRegionInfo;
      10: invokespecial #57                 // Method openRegion:(Lorg/apache/hadoop/hbase/HRegionInfo;)V
      13: new           #95                 // class org/apache/hadoop/hbase/client/Get
      16: dup
      17: aload_1
      18: invokespecial #96                 // Method org/apache/hadoop/hbase/client/Get."<init>":([B)V
      21: astore_2
      22: getstatic     #23                 // Field table:Lorg/apache/hadoop/hbase/client/Table;
      25: aload_2
      26: invokeinterface #97,  2           // InterfaceMethod org/apache/hadoop/hbase/client/Table.get:(Lorg/apache/hadoop/hbase/client/Get;)Lorg/apache/hadoop/hbase/client/Result;
      31: astore_3
      32: aload_3
      33: invokevirtual #98                 // Method org/apache/hadoop/hbase/client/Result.isStale:()Z
      36: invokestatic  #86                 // Method org/junit/Assert.assertFalse:(Z)V
      39: aload_0
      40: getstatic     #41                 // Field hriSecondary:Lorg/apache/hadoop/hbase/HRegionInfo;
      43: invokespecial #59                 // Method closeRegion:(Lorg/apache/hadoop/hbase/HRegionInfo;)V
      46: goto          61
      49: astore        4
      51: aload_0
      52: getstatic     #41                 // Field hriSecondary:Lorg/apache/hadoop/hbase/HRegionInfo;
      55: invokespecial #59                 // Method closeRegion:(Lorg/apache/hadoop/hbase/HRegionInfo;)V
      58: aload         4
      60: athrow
      61: return
    Exception table:
       from    to  target type
          13    39    49   any
          49    51    49   any

  public void testGetNoResultStaleRegionWithReplica() throws java.lang.Exception;
    Code:
       0: ldc           #106                // String testGetNoResultStaleRegionWithReplica
       2: invokestatic  #90                 // Method org/apache/hadoop/hbase/util/Bytes.toBytes:(Ljava/lang/String;)[B
       5: astore_1
       6: aload_0
       7: getstatic     #41                 // Field hriSecondary:Lorg/apache/hadoop/hbase/HRegionInfo;
      10: invokespecial #57                 // Method openRegion:(Lorg/apache/hadoop/hbase/HRegionInfo;)V
      13: invokestatic  #91                 // Method org/apache/hadoop/hbase/client/TestReplicasClient$SlowMeCopro.getPrimaryCdl:()Ljava/util/concurrent/atomic/AtomicReference;
      16: new           #92                 // class java/util/concurrent/CountDownLatch
      19: dup
      20: iconst_1
      21: invokespecial #93                 // Method java/util/concurrent/CountDownLatch."<init>":(I)V
      24: invokevirtual #94                 // Method java/util/concurrent/atomic/AtomicReference.set:(Ljava/lang/Object;)V
      27: new           #95                 // class org/apache/hadoop/hbase/client/Get
      30: dup
      31: aload_1
      32: invokespecial #96                 // Method org/apache/hadoop/hbase/client/Get."<init>":([B)V
      35: astore_2
      36: aload_2
      37: getstatic     #107                // Field org/apache/hadoop/hbase/client/Consistency.TIMELINE:Lorg/apache/hadoop/hbase/client/Consistency;
      40: invokevirtual #108                // Method org/apache/hadoop/hbase/client/Get.setConsistency:(Lorg/apache/hadoop/hbase/client/Consistency;)Lorg/apache/hadoop/hbase/client/Get;
      43: pop
      44: getstatic     #23                 // Field table:Lorg/apache/hadoop/hbase/client/Table;
      47: aload_2
      48: invokeinterface #97,  2           // InterfaceMethod org/apache/hadoop/hbase/client/Table.get:(Lorg/apache/hadoop/hbase/client/Get;)Lorg/apache/hadoop/hbase/client/Result;
      53: astore_3
      54: aload_3
      55: invokevirtual #98                 // Method org/apache/hadoop/hbase/client/Result.isStale:()Z
      58: invokestatic  #78                 // Method org/junit/Assert.assertTrue:(Z)V
      61: invokestatic  #91                 // Method org/apache/hadoop/hbase/client/TestReplicasClient$SlowMeCopro.getPrimaryCdl:()Ljava/util/concurrent/atomic/AtomicReference;
      64: invokevirtual #109                // Method java/util/concurrent/atomic/AtomicReference.get:()Ljava/lang/Object;
      67: checkcast     #92                 // class java/util/concurrent/CountDownLatch
      70: invokevirtual #110                // Method java/util/concurrent/CountDownLatch.countDown:()V
      73: aload_0
      74: getstatic     #41                 // Field hriSecondary:Lorg/apache/hadoop/hbase/HRegionInfo;
      77: invokespecial #59                 // Method closeRegion:(Lorg/apache/hadoop/hbase/HRegionInfo;)V
      80: goto          107
      83: astore        4
      85: invokestatic  #91                 // Method org/apache/hadoop/hbase/client/TestReplicasClient$SlowMeCopro.getPrimaryCdl:()Ljava/util/concurrent/atomic/AtomicReference;
      88: invokevirtual #109                // Method java/util/concurrent/atomic/AtomicReference.get:()Ljava/lang/Object;
      91: checkcast     #92                 // class java/util/concurrent/CountDownLatch
      94: invokevirtual #110                // Method java/util/concurrent/CountDownLatch.countDown:()V
      97: aload_0
      98: getstatic     #41                 // Field hriSecondary:Lorg/apache/hadoop/hbase/HRegionInfo;
     101: invokespecial #59                 // Method closeRegion:(Lorg/apache/hadoop/hbase/HRegionInfo;)V
     104: aload         4
     106: athrow
     107: return
    Exception table:
       from    to  target type
          27    61    83   any
          83    85    83   any

  public void testGetNoResultNotStaleSleepRegionWithReplica() throws java.lang.Exception;
    Code:
       0: ldc           #111                // String testGetNoResultNotStaleSleepRegionWithReplica
       2: invokestatic  #90                 // Method org/apache/hadoop/hbase/util/Bytes.toBytes:(Ljava/lang/String;)[B
       5: astore_1
       6: aload_0
       7: getstatic     #41                 // Field hriSecondary:Lorg/apache/hadoop/hbase/HRegionInfo;
      10: invokespecial #57                 // Method openRegion:(Lorg/apache/hadoop/hbase/HRegionInfo;)V
      13: getstatic     #112                // Field org/apache/hadoop/hbase/client/TestReplicasClient$SlowMeCopro.sleepTime:Ljava/util/concurrent/atomic/AtomicLong;
      16: ldc2_w        #113                // long 2000l
      19: invokevirtual #115                // Method java/util/concurrent/atomic/AtomicLong.set:(J)V
      22: new           #95                 // class org/apache/hadoop/hbase/client/Get
      25: dup
      26: aload_1
      27: invokespecial #96                 // Method org/apache/hadoop/hbase/client/Get."<init>":([B)V
      30: astore_2
      31: getstatic     #23                 // Field table:Lorg/apache/hadoop/hbase/client/Table;
      34: aload_2
      35: invokeinterface #97,  2           // InterfaceMethod org/apache/hadoop/hbase/client/Table.get:(Lorg/apache/hadoop/hbase/client/Get;)Lorg/apache/hadoop/hbase/client/Result;
      40: astore_3
      41: aload_3
      42: invokevirtual #98                 // Method org/apache/hadoop/hbase/client/Result.isStale:()Z
      45: invokestatic  #86                 // Method org/junit/Assert.assertFalse:(Z)V
      48: getstatic     #112                // Field org/apache/hadoop/hbase/client/TestReplicasClient$SlowMeCopro.sleepTime:Ljava/util/concurrent/atomic/AtomicLong;
      51: lconst_0
      52: invokevirtual #115                // Method java/util/concurrent/atomic/AtomicLong.set:(J)V
      55: aload_0
      56: getstatic     #41                 // Field hriSecondary:Lorg/apache/hadoop/hbase/HRegionInfo;
      59: invokespecial #59                 // Method closeRegion:(Lorg/apache/hadoop/hbase/HRegionInfo;)V
      62: goto          84
      65: astore        4
      67: getstatic     #112                // Field org/apache/hadoop/hbase/client/TestReplicasClient$SlowMeCopro.sleepTime:Ljava/util/concurrent/atomic/AtomicLong;
      70: lconst_0
      71: invokevirtual #115                // Method java/util/concurrent/atomic/AtomicLong.set:(J)V
      74: aload_0
      75: getstatic     #41                 // Field hriSecondary:Lorg/apache/hadoop/hbase/HRegionInfo;
      78: invokespecial #59                 // Method closeRegion:(Lorg/apache/hadoop/hbase/HRegionInfo;)V
      81: aload         4
      83: athrow
      84: return
    Exception table:
       from    to  target type
          13    48    65   any
          65    67    65   any

  public void testFlushTable() throws java.lang.Exception;
    Code:
       0: aload_0
       1: getstatic     #41                 // Field hriSecondary:Lorg/apache/hadoop/hbase/HRegionInfo;
       4: invokespecial #57                 // Method openRegion:(Lorg/apache/hadoop/hbase/HRegionInfo;)V
       7: aload_0
       8: getstatic     #30                 // Field hriPrimary:Lorg/apache/hadoop/hbase/HRegionInfo;
      11: invokespecial #116                // Method flushRegion:(Lorg/apache/hadoop/hbase/HRegionInfo;)V
      14: aload_0
      15: getstatic     #41                 // Field hriSecondary:Lorg/apache/hadoop/hbase/HRegionInfo;
      18: invokespecial #116                // Method flushRegion:(Lorg/apache/hadoop/hbase/HRegionInfo;)V
      21: new           #117                // class org/apache/hadoop/hbase/client/Put
      24: dup
      25: getstatic     #27                 // Field row:[B
      28: invokespecial #118                // Method org/apache/hadoop/hbase/client/Put."<init>":([B)V
      31: astore_1
      32: aload_1
      33: getstatic     #21                 // Field f:[B
      36: getstatic     #27                 // Field row:[B
      39: getstatic     #27                 // Field row:[B
      42: invokevirtual #119                // Method org/apache/hadoop/hbase/client/Put.addColumn:([B[B[B)Lorg/apache/hadoop/hbase/client/Put;
      45: pop
      46: getstatic     #23                 // Field table:Lorg/apache/hadoop/hbase/client/Table;
      49: aload_1
      50: invokeinterface #120,  2          // InterfaceMethod org/apache/hadoop/hbase/client/Table.put:(Lorg/apache/hadoop/hbase/client/Put;)V
      55: aload_0
      56: getstatic     #30                 // Field hriPrimary:Lorg/apache/hadoop/hbase/HRegionInfo;
      59: invokespecial #116                // Method flushRegion:(Lorg/apache/hadoop/hbase/HRegionInfo;)V
      62: aload_0
      63: getstatic     #41                 // Field hriSecondary:Lorg/apache/hadoop/hbase/HRegionInfo;
      66: invokespecial #116                // Method flushRegion:(Lorg/apache/hadoop/hbase/HRegionInfo;)V
      69: new           #121                // class org/apache/hadoop/hbase/client/Delete
      72: dup
      73: getstatic     #27                 // Field row:[B
      76: invokespecial #122                // Method org/apache/hadoop/hbase/client/Delete."<init>":([B)V
      79: astore_1
      80: getstatic     #23                 // Field table:Lorg/apache/hadoop/hbase/client/Table;
      83: aload_1
      84: invokeinterface #123,  2          // InterfaceMethod org/apache/hadoop/hbase/client/Table.delete:(Lorg/apache/hadoop/hbase/client/Delete;)V
      89: aload_0
      90: getstatic     #41                 // Field hriSecondary:Lorg/apache/hadoop/hbase/HRegionInfo;
      93: invokespecial #59                 // Method closeRegion:(Lorg/apache/hadoop/hbase/HRegionInfo;)V
      96: goto          129
      99: astore_2
     100: new           #121                // class org/apache/hadoop/hbase/client/Delete
     103: dup
     104: getstatic     #27                 // Field row:[B
     107: invokespecial #122                // Method org/apache/hadoop/hbase/client/Delete."<init>":([B)V
     110: astore_3
     111: getstatic     #23                 // Field table:Lorg/apache/hadoop/hbase/client/Table;
     114: aload_3
     115: invokeinterface #123,  2          // InterfaceMethod org/apache/hadoop/hbase/client/Table.delete:(Lorg/apache/hadoop/hbase/client/Delete;)V
     120: aload_0
     121: getstatic     #41                 // Field hriSecondary:Lorg/apache/hadoop/hbase/HRegionInfo;
     124: invokespecial #59                 // Method closeRegion:(Lorg/apache/hadoop/hbase/HRegionInfo;)V
     127: aload_2
     128: athrow
     129: return
    Exception table:
       from    to  target type
           7    69    99   any

  public void testFlushPrimary() throws java.lang.Exception;
    Code:
       0: aload_0
       1: getstatic     #41                 // Field hriSecondary:Lorg/apache/hadoop/hbase/HRegionInfo;
       4: invokespecial #57                 // Method openRegion:(Lorg/apache/hadoop/hbase/HRegionInfo;)V
       7: aload_0
       8: getstatic     #30                 // Field hriPrimary:Lorg/apache/hadoop/hbase/HRegionInfo;
      11: invokespecial #116                // Method flushRegion:(Lorg/apache/hadoop/hbase/HRegionInfo;)V
      14: new           #117                // class org/apache/hadoop/hbase/client/Put
      17: dup
      18: getstatic     #27                 // Field row:[B
      21: invokespecial #118                // Method org/apache/hadoop/hbase/client/Put."<init>":([B)V
      24: astore_1
      25: aload_1
      26: getstatic     #21                 // Field f:[B
      29: getstatic     #27                 // Field row:[B
      32: getstatic     #27                 // Field row:[B
      35: invokevirtual #119                // Method org/apache/hadoop/hbase/client/Put.addColumn:([B[B[B)Lorg/apache/hadoop/hbase/client/Put;
      38: pop
      39: getstatic     #23                 // Field table:Lorg/apache/hadoop/hbase/client/Table;
      42: aload_1
      43: invokeinterface #120,  2          // InterfaceMethod org/apache/hadoop/hbase/client/Table.put:(Lorg/apache/hadoop/hbase/client/Put;)V
      48: aload_0
      49: getstatic     #30                 // Field hriPrimary:Lorg/apache/hadoop/hbase/HRegionInfo;
      52: invokespecial #116                // Method flushRegion:(Lorg/apache/hadoop/hbase/HRegionInfo;)V
      55: new           #121                // class org/apache/hadoop/hbase/client/Delete
      58: dup
      59: getstatic     #27                 // Field row:[B
      62: invokespecial #122                // Method org/apache/hadoop/hbase/client/Delete."<init>":([B)V
      65: astore_1
      66: getstatic     #23                 // Field table:Lorg/apache/hadoop/hbase/client/Table;
      69: aload_1
      70: invokeinterface #123,  2          // InterfaceMethod org/apache/hadoop/hbase/client/Table.delete:(Lorg/apache/hadoop/hbase/client/Delete;)V
      75: aload_0
      76: getstatic     #41                 // Field hriSecondary:Lorg/apache/hadoop/hbase/HRegionInfo;
      79: invokespecial #59                 // Method closeRegion:(Lorg/apache/hadoop/hbase/HRegionInfo;)V
      82: goto          115
      85: astore_2
      86: new           #121                // class org/apache/hadoop/hbase/client/Delete
      89: dup
      90: getstatic     #27                 // Field row:[B
      93: invokespecial #122                // Method org/apache/hadoop/hbase/client/Delete."<init>":([B)V
      96: astore_3
      97: getstatic     #23                 // Field table:Lorg/apache/hadoop/hbase/client/Table;
     100: aload_3
     101: invokeinterface #123,  2          // InterfaceMethod org/apache/hadoop/hbase/client/Table.delete:(Lorg/apache/hadoop/hbase/client/Delete;)V
     106: aload_0
     107: getstatic     #41                 // Field hriSecondary:Lorg/apache/hadoop/hbase/HRegionInfo;
     110: invokespecial #59                 // Method closeRegion:(Lorg/apache/hadoop/hbase/HRegionInfo;)V
     113: aload_2
     114: athrow
     115: return
    Exception table:
       from    to  target type
           7    55    85   any

  public void testFlushSecondary() throws java.lang.Exception;
    Code:
       0: aload_0
       1: getstatic     #41                 // Field hriSecondary:Lorg/apache/hadoop/hbase/HRegionInfo;
       4: invokespecial #57                 // Method openRegion:(Lorg/apache/hadoop/hbase/HRegionInfo;)V
       7: aload_0
       8: getstatic     #41                 // Field hriSecondary:Lorg/apache/hadoop/hbase/HRegionInfo;
      11: invokespecial #116                // Method flushRegion:(Lorg/apache/hadoop/hbase/HRegionInfo;)V
      14: new           #117                // class org/apache/hadoop/hbase/client/Put
      17: dup
      18: getstatic     #27                 // Field row:[B
      21: invokespecial #118                // Method org/apache/hadoop/hbase/client/Put."<init>":([B)V
      24: astore_1
      25: aload_1
      26: getstatic     #21                 // Field f:[B
      29: getstatic     #27                 // Field row:[B
      32: getstatic     #27                 // Field row:[B
      35: invokevirtual #119                // Method org/apache/hadoop/hbase/client/Put.addColumn:([B[B[B)Lorg/apache/hadoop/hbase/client/Put;
      38: pop
      39: getstatic     #23                 // Field table:Lorg/apache/hadoop/hbase/client/Table;
      42: aload_1
      43: invokeinterface #120,  2          // InterfaceMethod org/apache/hadoop/hbase/client/Table.put:(Lorg/apache/hadoop/hbase/client/Put;)V
      48: aload_0
      49: getstatic     #41                 // Field hriSecondary:Lorg/apache/hadoop/hbase/HRegionInfo;
      52: invokespecial #116                // Method flushRegion:(Lorg/apache/hadoop/hbase/HRegionInfo;)V
      55: new           #121                // class org/apache/hadoop/hbase/client/Delete
      58: dup
      59: getstatic     #27                 // Field row:[B
      62: invokespecial #122                // Method org/apache/hadoop/hbase/client/Delete."<init>":([B)V
      65: astore_1
      66: getstatic     #23                 // Field table:Lorg/apache/hadoop/hbase/client/Table;
      69: aload_1
      70: invokeinterface #123,  2          // InterfaceMethod org/apache/hadoop/hbase/client/Table.delete:(Lorg/apache/hadoop/hbase/client/Delete;)V
      75: aload_0
      76: getstatic     #41                 // Field hriSecondary:Lorg/apache/hadoop/hbase/HRegionInfo;
      79: invokespecial #59                 // Method closeRegion:(Lorg/apache/hadoop/hbase/HRegionInfo;)V
      82: goto          146
      85: astore_1
      86: new           #121                // class org/apache/hadoop/hbase/client/Delete
      89: dup
      90: getstatic     #27                 // Field row:[B
      93: invokespecial #122                // Method org/apache/hadoop/hbase/client/Delete."<init>":([B)V
      96: astore_1
      97: getstatic     #23                 // Field table:Lorg/apache/hadoop/hbase/client/Table;
     100: aload_1
     101: invokeinterface #123,  2          // InterfaceMethod org/apache/hadoop/hbase/client/Table.delete:(Lorg/apache/hadoop/hbase/client/Delete;)V
     106: aload_0
     107: getstatic     #41                 // Field hriSecondary:Lorg/apache/hadoop/hbase/HRegionInfo;
     110: invokespecial #59                 // Method closeRegion:(Lorg/apache/hadoop/hbase/HRegionInfo;)V
     113: goto          146
     116: astore_2
     117: new           #121                // class org/apache/hadoop/hbase/client/Delete
     120: dup
     121: getstatic     #27                 // Field row:[B
     124: invokespecial #122                // Method org/apache/hadoop/hbase/client/Delete."<init>":([B)V
     127: astore_3
     128: getstatic     #23                 // Field table:Lorg/apache/hadoop/hbase/client/Table;
     131: aload_3
     132: invokeinterface #123,  2          // InterfaceMethod org/apache/hadoop/hbase/client/Table.delete:(Lorg/apache/hadoop/hbase/client/Delete;)V
     137: aload_0
     138: getstatic     #41                 // Field hriSecondary:Lorg/apache/hadoop/hbase/HRegionInfo;
     141: invokespecial #59                 // Method closeRegion:(Lorg/apache/hadoop/hbase/HRegionInfo;)V
     144: aload_2
     145: athrow
     146: return
    Exception table:
       from    to  target type
           7    55    85   Class org/apache/hadoop/hbase/TableNotFoundException
           7    55   116   any

  public void testUseRegionWithReplica() throws java.lang.Exception;
    Code:
       0: ldc           #125                // String testUseRegionWithReplica
       2: invokestatic  #90                 // Method org/apache/hadoop/hbase/util/Bytes.toBytes:(Ljava/lang/String;)[B
       5: astore_1
       6: aload_0
       7: getstatic     #41                 // Field hriSecondary:Lorg/apache/hadoop/hbase/HRegionInfo;
      10: invokespecial #57                 // Method openRegion:(Lorg/apache/hadoop/hbase/HRegionInfo;)V
      13: new           #117                // class org/apache/hadoop/hbase/client/Put
      16: dup
      17: aload_1
      18: invokespecial #118                // Method org/apache/hadoop/hbase/client/Put."<init>":([B)V
      21: astore_2
      22: aload_2
      23: getstatic     #21                 // Field f:[B
      26: aload_1
      27: aload_1
      28: invokevirtual #119                // Method org/apache/hadoop/hbase/client/Put.addColumn:([B[B[B)Lorg/apache/hadoop/hbase/client/Put;
      31: pop
      32: getstatic     #23                 // Field table:Lorg/apache/hadoop/hbase/client/Table;
      35: aload_2
      36: invokeinterface #120,  2          // InterfaceMethod org/apache/hadoop/hbase/client/Table.put:(Lorg/apache/hadoop/hbase/client/Put;)V
      41: getstatic     #1                  // Field LOG:Lorg/slf4j/Logger;
      44: ldc           #126                // String Put done
      46: invokeinterface #43,  2           // InterfaceMethod org/slf4j/Logger.info:(Ljava/lang/String;)V
      51: new           #95                 // class org/apache/hadoop/hbase/client/Get
      54: dup
      55: aload_1
      56: invokespecial #96                 // Method org/apache/hadoop/hbase/client/Get."<init>":([B)V
      59: astore_3
      60: getstatic     #23                 // Field table:Lorg/apache/hadoop/hbase/client/Table;
      63: aload_3
      64: invokeinterface #97,  2           // InterfaceMethod org/apache/hadoop/hbase/client/Table.get:(Lorg/apache/hadoop/hbase/client/Get;)Lorg/apache/hadoop/hbase/client/Result;
      69: astore        4
      71: aload         4
      73: invokevirtual #98                 // Method org/apache/hadoop/hbase/client/Result.isStale:()Z
      76: invokestatic  #86                 // Method org/junit/Assert.assertFalse:(Z)V
      79: aload         4
      81: getstatic     #21                 // Field f:[B
      84: aload_1
      85: invokevirtual #127                // Method org/apache/hadoop/hbase/client/Result.getColumnCells:([B[B)Ljava/util/List;
      88: invokeinterface #128,  1          // InterfaceMethod java/util/List.isEmpty:()Z
      93: invokestatic  #86                 // Method org/junit/Assert.assertFalse:(Z)V
      96: getstatic     #1                  // Field LOG:Lorg/slf4j/Logger;
      99: ldc           #129                // String get works and is not stale done
     101: invokeinterface #43,  2           // InterfaceMethod org/slf4j/Logger.info:(Ljava/lang/String;)V
     106: getstatic     #112                // Field org/apache/hadoop/hbase/client/TestReplicasClient$SlowMeCopro.sleepTime:Ljava/util/concurrent/atomic/AtomicLong;
     109: ldc2_w        #113                // long 2000l
     112: invokevirtual #115                // Method java/util/concurrent/atomic/AtomicLong.set:(J)V
     115: new           #95                 // class org/apache/hadoop/hbase/client/Get
     118: dup
     119: aload_1
     120: invokespecial #96                 // Method org/apache/hadoop/hbase/client/Get."<init>":([B)V
     123: astore_3
     124: getstatic     #23                 // Field table:Lorg/apache/hadoop/hbase/client/Table;
     127: aload_3
     128: invokeinterface #97,  2           // InterfaceMethod org/apache/hadoop/hbase/client/Table.get:(Lorg/apache/hadoop/hbase/client/Get;)Lorg/apache/hadoop/hbase/client/Result;
     133: astore        4
     135: aload         4
     137: invokevirtual #98                 // Method org/apache/hadoop/hbase/client/Result.isStale:()Z
     140: invokestatic  #86                 // Method org/junit/Assert.assertFalse:(Z)V
     143: aload         4
     145: getstatic     #21                 // Field f:[B
     148: aload_1
     149: invokevirtual #127                // Method org/apache/hadoop/hbase/client/Result.getColumnCells:([B[B)Ljava/util/List;
     152: invokeinterface #128,  1          // InterfaceMethod java/util/List.isEmpty:()Z
     157: invokestatic  #86                 // Method org/junit/Assert.assertFalse:(Z)V
     160: getstatic     #112                // Field org/apache/hadoop/hbase/client/TestReplicasClient$SlowMeCopro.sleepTime:Ljava/util/concurrent/atomic/AtomicLong;
     163: lconst_0
     164: invokevirtual #115                // Method java/util/concurrent/atomic/AtomicLong.set:(J)V
     167: getstatic     #1                  // Field LOG:Lorg/slf4j/Logger;
     170: ldc           #130                // String sleep and is not stale done
     172: invokeinterface #43,  2           // InterfaceMethod org/slf4j/Logger.info:(Ljava/lang/String;)V
     177: invokestatic  #91                 // Method org/apache/hadoop/hbase/client/TestReplicasClient$SlowMeCopro.getPrimaryCdl:()Ljava/util/concurrent/atomic/AtomicReference;
     180: new           #92                 // class java/util/concurrent/CountDownLatch
     183: dup
     184: iconst_1
     185: invokespecial #93                 // Method java/util/concurrent/CountDownLatch."<init>":(I)V
     188: invokevirtual #94                 // Method java/util/concurrent/atomic/AtomicReference.set:(Ljava/lang/Object;)V
     191: new           #95                 // class org/apache/hadoop/hbase/client/Get
     194: dup
     195: aload_1
     196: invokespecial #96                 // Method org/apache/hadoop/hbase/client/Get."<init>":([B)V
     199: astore_3
     200: aload_3
     201: getstatic     #107                // Field org/apache/hadoop/hbase/client/Consistency.TIMELINE:Lorg/apache/hadoop/hbase/client/Consistency;
     204: invokevirtual #108                // Method org/apache/hadoop/hbase/client/Get.setConsistency:(Lorg/apache/hadoop/hbase/client/Consistency;)Lorg/apache/hadoop/hbase/client/Get;
     207: pop
     208: getstatic     #23                 // Field table:Lorg/apache/hadoop/hbase/client/Table;
     211: aload_3
     212: invokeinterface #97,  2           // InterfaceMethod org/apache/hadoop/hbase/client/Table.get:(Lorg/apache/hadoop/hbase/client/Get;)Lorg/apache/hadoop/hbase/client/Result;
     217: astore        4
     219: aload         4
     221: invokevirtual #98                 // Method org/apache/hadoop/hbase/client/Result.isStale:()Z
     224: invokestatic  #78                 // Method org/junit/Assert.assertTrue:(Z)V
     227: aload         4
     229: getstatic     #21                 // Field f:[B
     232: aload_1
     233: invokevirtual #127                // Method org/apache/hadoop/hbase/client/Result.getColumnCells:([B[B)Ljava/util/List;
     236: invokeinterface #128,  1          // InterfaceMethod java/util/List.isEmpty:()Z
     241: invokestatic  #78                 // Method org/junit/Assert.assertTrue:(Z)V
     244: invokestatic  #91                 // Method org/apache/hadoop/hbase/client/TestReplicasClient$SlowMeCopro.getPrimaryCdl:()Ljava/util/concurrent/atomic/AtomicReference;
     247: invokevirtual #109                // Method java/util/concurrent/atomic/AtomicReference.get:()Ljava/lang/Object;
     250: checkcast     #92                 // class java/util/concurrent/CountDownLatch
     253: invokevirtual #110                // Method java/util/concurrent/CountDownLatch.countDown:()V
     256: getstatic     #1                  // Field LOG:Lorg/slf4j/Logger;
     259: ldc           #131                // String stale done
     261: invokeinterface #43,  2           // InterfaceMethod org/slf4j/Logger.info:(Ljava/lang/String;)V
     266: new           #95                 // class org/apache/hadoop/hbase/client/Get
     269: dup
     270: aload_1
     271: invokespecial #96                 // Method org/apache/hadoop/hbase/client/Get."<init>":([B)V
     274: astore_3
     275: aload_3
     276: iconst_1
     277: invokevirtual #132                // Method org/apache/hadoop/hbase/client/Get.setCheckExistenceOnly:(Z)Lorg/apache/hadoop/hbase/client/Get;
     280: pop
     281: getstatic     #23                 // Field table:Lorg/apache/hadoop/hbase/client/Table;
     284: aload_3
     285: invokeinterface #97,  2           // InterfaceMethod org/apache/hadoop/hbase/client/Table.get:(Lorg/apache/hadoop/hbase/client/Get;)Lorg/apache/hadoop/hbase/client/Result;
     290: astore        4
     292: aload         4
     294: invokevirtual #98                 // Method org/apache/hadoop/hbase/client/Result.isStale:()Z
     297: invokestatic  #86                 // Method org/junit/Assert.assertFalse:(Z)V
     300: aload         4
     302: invokevirtual #133                // Method org/apache/hadoop/hbase/client/Result.getExists:()Ljava/lang/Boolean;
     305: invokevirtual #134                // Method java/lang/Boolean.booleanValue:()Z
     308: invokestatic  #78                 // Method org/junit/Assert.assertTrue:(Z)V
     311: getstatic     #1                  // Field LOG:Lorg/slf4j/Logger;
     314: ldc           #135                // String exists not stale done
     316: invokeinterface #43,  2           // InterfaceMethod org/slf4j/Logger.info:(Ljava/lang/String;)V
     321: invokestatic  #91                 // Method org/apache/hadoop/hbase/client/TestReplicasClient$SlowMeCopro.getPrimaryCdl:()Ljava/util/concurrent/atomic/AtomicReference;
     324: new           #92                 // class java/util/concurrent/CountDownLatch
     327: dup
     328: iconst_1
     329: invokespecial #93                 // Method java/util/concurrent/CountDownLatch."<init>":(I)V
     332: invokevirtual #94                 // Method java/util/concurrent/atomic/AtomicReference.set:(Ljava/lang/Object;)V
     335: new           #95                 // class org/apache/hadoop/hbase/client/Get
     338: dup
     339: aload_1
     340: invokespecial #96                 // Method org/apache/hadoop/hbase/client/Get."<init>":([B)V
     343: astore_3
     344: aload_3
     345: iconst_1
     346: invokevirtual #132                // Method org/apache/hadoop/hbase/client/Get.setCheckExistenceOnly:(Z)Lorg/apache/hadoop/hbase/client/Get;
     349: pop
     350: aload_3
     351: getstatic     #107                // Field org/apache/hadoop/hbase/client/Consistency.TIMELINE:Lorg/apache/hadoop/hbase/client/Consistency;
     354: invokevirtual #108                // Method org/apache/hadoop/hbase/client/Get.setConsistency:(Lorg/apache/hadoop/hbase/client/Consistency;)Lorg/apache/hadoop/hbase/client/Get;
     357: pop
     358: getstatic     #23                 // Field table:Lorg/apache/hadoop/hbase/client/Table;
     361: aload_3
     362: invokeinterface #97,  2           // InterfaceMethod org/apache/hadoop/hbase/client/Table.get:(Lorg/apache/hadoop/hbase/client/Get;)Lorg/apache/hadoop/hbase/client/Result;
     367: astore        4
     369: aload         4
     371: invokevirtual #98                 // Method org/apache/hadoop/hbase/client/Result.isStale:()Z
     374: invokestatic  #78                 // Method org/junit/Assert.assertTrue:(Z)V
     377: ldc           #136                // String The secondary has stale data
     379: aload         4
     381: invokevirtual #133                // Method org/apache/hadoop/hbase/client/Result.getExists:()Ljava/lang/Boolean;
     384: invokevirtual #134                // Method java/lang/Boolean.booleanValue:()Z
     387: invokestatic  #137                // Method org/junit/Assert.assertFalse:(Ljava/lang/String;Z)V
     390: invokestatic  #91                 // Method org/apache/hadoop/hbase/client/TestReplicasClient$SlowMeCopro.getPrimaryCdl:()Ljava/util/concurrent/atomic/AtomicReference;
     393: invokevirtual #109                // Method java/util/concurrent/atomic/AtomicReference.get:()Ljava/lang/Object;
     396: checkcast     #92                 // class java/util/concurrent/CountDownLatch
     399: invokevirtual #110                // Method java/util/concurrent/CountDownLatch.countDown:()V
     402: getstatic     #1                  // Field LOG:Lorg/slf4j/Logger;
     405: ldc           #138                // String exists stale before flush done
     407: invokeinterface #43,  2           // InterfaceMethod org/slf4j/Logger.info:(Ljava/lang/String;)V
     412: aload_0
     413: getstatic     #30                 // Field hriPrimary:Lorg/apache/hadoop/hbase/HRegionInfo;
     416: invokespecial #116                // Method flushRegion:(Lorg/apache/hadoop/hbase/HRegionInfo;)V
     419: aload_0
     420: getstatic     #41                 // Field hriSecondary:Lorg/apache/hadoop/hbase/HRegionInfo;
     423: invokespecial #116                // Method flushRegion:(Lorg/apache/hadoop/hbase/HRegionInfo;)V
     426: getstatic     #1                  // Field LOG:Lorg/slf4j/Logger;
     429: ldc           #139                // String flush done
     431: invokeinterface #43,  2           // InterfaceMethod org/slf4j/Logger.info:(Ljava/lang/String;)V
     436: ldc2_w        #140                // long 3000l
     439: invokestatic  #83                 // Method java/lang/Thread.sleep:(J)V
     442: invokestatic  #91                 // Method org/apache/hadoop/hbase/client/TestReplicasClient$SlowMeCopro.getPrimaryCdl:()Ljava/util/concurrent/atomic/AtomicReference;
     445: new           #92                 // class java/util/concurrent/CountDownLatch
     448: dup
     449: iconst_1
     450: invokespecial #93                 // Method java/util/concurrent/CountDownLatch."<init>":(I)V
     453: invokevirtual #94                 // Method java/util/concurrent/atomic/AtomicReference.set:(Ljava/lang/Object;)V
     456: new           #95                 // class org/apache/hadoop/hbase/client/Get
     459: dup
     460: aload_1
     461: invokespecial #96                 // Method org/apache/hadoop/hbase/client/Get."<init>":([B)V
     464: astore_3
     465: aload_3
     466: getstatic     #107                // Field org/apache/hadoop/hbase/client/Consistency.TIMELINE:Lorg/apache/hadoop/hbase/client/Consistency;
     469: invokevirtual #108                // Method org/apache/hadoop/hbase/client/Get.setConsistency:(Lorg/apache/hadoop/hbase/client/Consistency;)Lorg/apache/hadoop/hbase/client/Get;
     472: pop
     473: getstatic     #23                 // Field table:Lorg/apache/hadoop/hbase/client/Table;
     476: aload_3
     477: invokeinterface #97,  2           // InterfaceMethod org/apache/hadoop/hbase/client/Table.get:(Lorg/apache/hadoop/hbase/client/Get;)Lorg/apache/hadoop/hbase/client/Result;
     482: astore        4
     484: aload         4
     486: invokevirtual #98                 // Method org/apache/hadoop/hbase/client/Result.isStale:()Z
     489: invokestatic  #78                 // Method org/junit/Assert.assertTrue:(Z)V
     492: aload         4
     494: invokevirtual #142                // Method org/apache/hadoop/hbase/client/Result.isEmpty:()Z
     497: invokestatic  #86                 // Method org/junit/Assert.assertFalse:(Z)V
     500: invokestatic  #91                 // Method org/apache/hadoop/hbase/client/TestReplicasClient$SlowMeCopro.getPrimaryCdl:()Ljava/util/concurrent/atomic/AtomicReference;
     503: invokevirtual #109                // Method java/util/concurrent/atomic/AtomicReference.get:()Ljava/lang/Object;
     506: checkcast     #92                 // class java/util/concurrent/CountDownLatch
     509: invokevirtual #110                // Method java/util/concurrent/CountDownLatch.countDown:()V
     512: getstatic     #1                  // Field LOG:Lorg/slf4j/Logger;
     515: ldc           #131                // String stale done
     517: invokeinterface #43,  2           // InterfaceMethod org/slf4j/Logger.info:(Ljava/lang/String;)V
     522: invokestatic  #91                 // Method org/apache/hadoop/hbase/client/TestReplicasClient$SlowMeCopro.getPrimaryCdl:()Ljava/util/concurrent/atomic/AtomicReference;
     525: new           #92                 // class java/util/concurrent/CountDownLatch
     528: dup
     529: iconst_1
     530: invokespecial #93                 // Method java/util/concurrent/CountDownLatch."<init>":(I)V
     533: invokevirtual #94                 // Method java/util/concurrent/atomic/AtomicReference.set:(Ljava/lang/Object;)V
     536: new           #95                 // class org/apache/hadoop/hbase/client/Get
     539: dup
     540: aload_1
     541: invokespecial #96                 // Method org/apache/hadoop/hbase/client/Get."<init>":([B)V
     544: astore_3
     545: aload_3
     546: iconst_1
     547: invokevirtual #132                // Method org/apache/hadoop/hbase/client/Get.setCheckExistenceOnly:(Z)Lorg/apache/hadoop/hbase/client/Get;
     550: pop
     551: aload_3
     552: getstatic     #107                // Field org/apache/hadoop/hbase/client/Consistency.TIMELINE:Lorg/apache/hadoop/hbase/client/Consistency;
     555: invokevirtual #108                // Method org/apache/hadoop/hbase/client/Get.setConsistency:(Lorg/apache/hadoop/hbase/client/Consistency;)Lorg/apache/hadoop/hbase/client/Get;
     558: pop
     559: getstatic     #23                 // Field table:Lorg/apache/hadoop/hbase/client/Table;
     562: aload_3
     563: invokeinterface #97,  2           // InterfaceMethod org/apache/hadoop/hbase/client/Table.get:(Lorg/apache/hadoop/hbase/client/Get;)Lorg/apache/hadoop/hbase/client/Result;
     568: astore        4
     570: aload         4
     572: invokevirtual #98                 // Method org/apache/hadoop/hbase/client/Result.isStale:()Z
     575: invokestatic  #78                 // Method org/junit/Assert.assertTrue:(Z)V
     578: aload         4
     580: invokevirtual #133                // Method org/apache/hadoop/hbase/client/Result.getExists:()Ljava/lang/Boolean;
     583: invokevirtual #134                // Method java/lang/Boolean.booleanValue:()Z
     586: invokestatic  #78                 // Method org/junit/Assert.assertTrue:(Z)V
     589: invokestatic  #91                 // Method org/apache/hadoop/hbase/client/TestReplicasClient$SlowMeCopro.getPrimaryCdl:()Ljava/util/concurrent/atomic/AtomicReference;
     592: invokevirtual #109                // Method java/util/concurrent/atomic/AtomicReference.get:()Ljava/lang/Object;
     595: checkcast     #92                 // class java/util/concurrent/CountDownLatch
     598: invokevirtual #110                // Method java/util/concurrent/CountDownLatch.countDown:()V
     601: getstatic     #1                  // Field LOG:Lorg/slf4j/Logger;
     604: ldc           #143                // String exists stale after flush done
     606: invokeinterface #43,  2           // InterfaceMethod org/slf4j/Logger.info:(Ljava/lang/String;)V
     611: invokestatic  #91                 // Method org/apache/hadoop/hbase/client/TestReplicasClient$SlowMeCopro.getPrimaryCdl:()Ljava/util/concurrent/atomic/AtomicReference;
     614: invokevirtual #109                // Method java/util/concurrent/atomic/AtomicReference.get:()Ljava/lang/Object;
     617: checkcast     #92                 // class java/util/concurrent/CountDownLatch
     620: invokevirtual #110                // Method java/util/concurrent/CountDownLatch.countDown:()V
     623: getstatic     #112                // Field org/apache/hadoop/hbase/client/TestReplicasClient$SlowMeCopro.sleepTime:Ljava/util/concurrent/atomic/AtomicLong;
     626: lconst_0
     627: invokevirtual #115                // Method java/util/concurrent/atomic/AtomicLong.set:(J)V
     630: new           #121                // class org/apache/hadoop/hbase/client/Delete
     633: dup
     634: aload_1
     635: invokespecial #122                // Method org/apache/hadoop/hbase/client/Delete."<init>":([B)V
     638: astore_2
     639: getstatic     #23                 // Field table:Lorg/apache/hadoop/hbase/client/Table;
     642: aload_2
     643: invokeinterface #123,  2          // InterfaceMethod org/apache/hadoop/hbase/client/Table.delete:(Lorg/apache/hadoop/hbase/client/Delete;)V
     648: aload_0
     649: getstatic     #41                 // Field hriSecondary:Lorg/apache/hadoop/hbase/HRegionInfo;
     652: invokespecial #59                 // Method closeRegion:(Lorg/apache/hadoop/hbase/HRegionInfo;)V
     655: goto          709
     658: astore        5
     660: invokestatic  #91                 // Method org/apache/hadoop/hbase/client/TestReplicasClient$SlowMeCopro.getPrimaryCdl:()Ljava/util/concurrent/atomic/AtomicReference;
     663: invokevirtual #109                // Method java/util/concurrent/atomic/AtomicReference.get:()Ljava/lang/Object;
     666: checkcast     #92                 // class java/util/concurrent/CountDownLatch
     669: invokevirtual #110                // Method java/util/concurrent/CountDownLatch.countDown:()V
     672: getstatic     #112                // Field org/apache/hadoop/hbase/client/TestReplicasClient$SlowMeCopro.sleepTime:Ljava/util/concurrent/atomic/AtomicLong;
     675: lconst_0
     676: invokevirtual #115                // Method java/util/concurrent/atomic/AtomicLong.set:(J)V
     679: new           #121                // class org/apache/hadoop/hbase/client/Delete
     682: dup
     683: aload_1
     684: invokespecial #122                // Method org/apache/hadoop/hbase/client/Delete."<init>":([B)V
     687: astore        6
     689: getstatic     #23                 // Field table:Lorg/apache/hadoop/hbase/client/Table;
     692: aload         6
     694: invokeinterface #123,  2          // InterfaceMethod org/apache/hadoop/hbase/client/Table.delete:(Lorg/apache/hadoop/hbase/client/Delete;)V
     699: aload_0
     700: getstatic     #41                 // Field hriSecondary:Lorg/apache/hadoop/hbase/HRegionInfo;
     703: invokespecial #59                 // Method closeRegion:(Lorg/apache/hadoop/hbase/HRegionInfo;)V
     706: aload         5
     708: athrow
     709: return
    Exception table:
       from    to  target type
          13   611   658   any
         658   660   658   any

  public void testHedgedRead() throws java.lang.Exception;
    Code:
       0: ldc           #144                // String testHedgedRead
       2: invokestatic  #90                 // Method org/apache/hadoop/hbase/util/Bytes.toBytes:(Ljava/lang/String;)[B
       5: astore_1
       6: aload_0
       7: getstatic     #41                 // Field hriSecondary:Lorg/apache/hadoop/hbase/HRegionInfo;
      10: invokespecial #57                 // Method openRegion:(Lorg/apache/hadoop/hbase/HRegionInfo;)V
      13: new           #117                // class org/apache/hadoop/hbase/client/Put
      16: dup
      17: aload_1
      18: invokespecial #118                // Method org/apache/hadoop/hbase/client/Put."<init>":([B)V
      21: astore_2
      22: aload_2
      23: getstatic     #21                 // Field f:[B
      26: aload_1
      27: aload_1
      28: invokevirtual #119                // Method org/apache/hadoop/hbase/client/Put.addColumn:([B[B[B)Lorg/apache/hadoop/hbase/client/Put;
      31: pop
      32: getstatic     #23                 // Field table:Lorg/apache/hadoop/hbase/client/Table;
      35: aload_2
      36: invokeinterface #120,  2          // InterfaceMethod org/apache/hadoop/hbase/client/Table.put:(Lorg/apache/hadoop/hbase/client/Put;)V
      41: getstatic     #1                  // Field LOG:Lorg/slf4j/Logger;
      44: ldc           #126                // String Put done
      46: invokeinterface #43,  2           // InterfaceMethod org/slf4j/Logger.info:(Ljava/lang/String;)V
      51: new           #95                 // class org/apache/hadoop/hbase/client/Get
      54: dup
      55: aload_1
      56: invokespecial #96                 // Method org/apache/hadoop/hbase/client/Get."<init>":([B)V
      59: astore_3
      60: getstatic     #23                 // Field table:Lorg/apache/hadoop/hbase/client/Table;
      63: aload_3
      64: invokeinterface #97,  2           // InterfaceMethod org/apache/hadoop/hbase/client/Table.get:(Lorg/apache/hadoop/hbase/client/Get;)Lorg/apache/hadoop/hbase/client/Result;
      69: astore        4
      71: aload         4
      73: invokevirtual #98                 // Method org/apache/hadoop/hbase/client/Result.isStale:()Z
      76: invokestatic  #86                 // Method org/junit/Assert.assertFalse:(Z)V
      79: aload         4
      81: getstatic     #21                 // Field f:[B
      84: aload_1
      85: invokevirtual #127                // Method org/apache/hadoop/hbase/client/Result.getColumnCells:([B[B)Ljava/util/List;
      88: invokeinterface #128,  1          // InterfaceMethod java/util/List.isEmpty:()Z
      93: invokestatic  #86                 // Method org/junit/Assert.assertFalse:(Z)V
      96: getstatic     #1                  // Field LOG:Lorg/slf4j/Logger;
      99: ldc           #129                // String get works and is not stale done
     101: invokeinterface #43,  2           // InterfaceMethod org/slf4j/Logger.info:(Ljava/lang/String;)V
     106: getstatic     #3                  // Field HTU:Lorg/apache/hadoop/hbase/HBaseTestingUtility;
     109: invokevirtual #24                 // Method org/apache/hadoop/hbase/HBaseTestingUtility.getConnection:()Lorg/apache/hadoop/hbase/client/Connection;
     112: checkcast     #55                 // class org/apache/hadoop/hbase/client/ClusterConnection
     115: astore        5
     117: aload         5
     119: invokeinterface #145,  1          // InterfaceMethod org/apache/hadoop/hbase/client/ClusterConnection.getConnectionMetrics:()Lorg/apache/hadoop/hbase/client/MetricsConnection;
     124: getfield      #146                // Field org/apache/hadoop/hbase/client/MetricsConnection.hedgedReadOps:Lcom/codahale/metrics/Counter;
     127: astore        6
     129: aload         5
     131: invokeinterface #145,  1          // InterfaceMethod org/apache/hadoop/hbase/client/ClusterConnection.getConnectionMetrics:()Lorg/apache/hadoop/hbase/client/MetricsConnection;
     136: getfield      #147                // Field org/apache/hadoop/hbase/client/MetricsConnection.hedgedReadWin:Lcom/codahale/metrics/Counter;
     139: astore        7
     141: aload         6
     143: aload         6
     145: invokevirtual #148                // Method com/codahale/metrics/Counter.getCount:()J
     148: invokevirtual #149                // Method com/codahale/metrics/Counter.dec:(J)V
     151: aload         7
     153: aload         7
     155: invokevirtual #148                // Method com/codahale/metrics/Counter.getCount:()J
     158: invokevirtual #149                // Method com/codahale/metrics/Counter.dec:(J)V
     161: aload         5
     163: invokeinterface #150,  1          // InterfaceMethod org/apache/hadoop/hbase/client/ClusterConnection.getConnectionConfiguration:()Lorg/apache/hadoop/hbase/client/ConnectionConfiguration;
     168: invokevirtual #151                // Method org/apache/hadoop/hbase/client/ConnectionConfiguration.getPrimaryCallTimeoutMicroSecond:()I
     171: istore        8
     173: getstatic     #112                // Field org/apache/hadoop/hbase/client/TestReplicasClient$SlowMeCopro.sleepTime:Ljava/util/concurrent/atomic/AtomicLong;
     176: getstatic     #152                // Field java/util/concurrent/TimeUnit.MICROSECONDS:Ljava/util/concurrent/TimeUnit;
     179: iload         8
     181: i2l
     182: invokevirtual #153                // Method java/util/concurrent/TimeUnit.toMillis:(J)J
     185: invokevirtual #115                // Method java/util/concurrent/atomic/AtomicLong.set:(J)V
     188: invokestatic  #154                // Method org/apache/hadoop/hbase/client/TestReplicasClient$SlowMeCopro.getSecondaryCdl:()Ljava/util/concurrent/atomic/AtomicReference;
     191: new           #92                 // class java/util/concurrent/CountDownLatch
     194: dup
     195: iconst_1
     196: invokespecial #93                 // Method java/util/concurrent/CountDownLatch."<init>":(I)V
     199: invokevirtual #94                 // Method java/util/concurrent/atomic/AtomicReference.set:(Ljava/lang/Object;)V
     202: new           #95                 // class org/apache/hadoop/hbase/client/Get
     205: dup
     206: aload_1
     207: invokespecial #96                 // Method org/apache/hadoop/hbase/client/Get."<init>":([B)V
     210: astore_3
     211: aload_3
     212: getstatic     #107                // Field org/apache/hadoop/hbase/client/Consistency.TIMELINE:Lorg/apache/hadoop/hbase/client/Consistency;
     215: invokevirtual #108                // Method org/apache/hadoop/hbase/client/Get.setConsistency:(Lorg/apache/hadoop/hbase/client/Consistency;)Lorg/apache/hadoop/hbase/client/Get;
     218: pop
     219: getstatic     #23                 // Field table:Lorg/apache/hadoop/hbase/client/Table;
     222: aload_3
     223: invokeinterface #97,  2           // InterfaceMethod org/apache/hadoop/hbase/client/Table.get:(Lorg/apache/hadoop/hbase/client/Get;)Lorg/apache/hadoop/hbase/client/Result;
     228: astore        4
     230: aload         4
     232: invokevirtual #98                 // Method org/apache/hadoop/hbase/client/Result.isStale:()Z
     235: invokestatic  #86                 // Method org/junit/Assert.assertFalse:(Z)V
     238: aload         4
     240: getstatic     #21                 // Field f:[B
     243: aload_1
     244: invokevirtual #127                // Method org/apache/hadoop/hbase/client/Result.getColumnCells:([B[B)Ljava/util/List;
     247: invokeinterface #128,  1          // InterfaceMethod java/util/List.isEmpty:()Z
     252: invokestatic  #86                 // Method org/junit/Assert.assertFalse:(Z)V
     255: lconst_1
     256: aload         6
     258: invokevirtual #148                // Method com/codahale/metrics/Counter.getCount:()J
     261: invokestatic  #69                 // Method org/junit/Assert.assertEquals:(JJ)V
     264: lconst_0
     265: aload         7
     267: invokevirtual #148                // Method com/codahale/metrics/Counter.getCount:()J
     270: invokestatic  #69                 // Method org/junit/Assert.assertEquals:(JJ)V
     273: getstatic     #112                // Field org/apache/hadoop/hbase/client/TestReplicasClient$SlowMeCopro.sleepTime:Ljava/util/concurrent/atomic/AtomicLong;
     276: lconst_0
     277: invokevirtual #115                // Method java/util/concurrent/atomic/AtomicLong.set:(J)V
     280: invokestatic  #154                // Method org/apache/hadoop/hbase/client/TestReplicasClient$SlowMeCopro.getSecondaryCdl:()Ljava/util/concurrent/atomic/AtomicReference;
     283: invokevirtual #109                // Method java/util/concurrent/atomic/AtomicReference.get:()Ljava/lang/Object;
     286: checkcast     #92                 // class java/util/concurrent/CountDownLatch
     289: invokevirtual #110                // Method java/util/concurrent/CountDownLatch.countDown:()V
     292: getstatic     #1                  // Field LOG:Lorg/slf4j/Logger;
     295: ldc           #155                // String hedged read occurred but not faster
     297: invokeinterface #43,  2           // InterfaceMethod org/slf4j/Logger.info:(Ljava/lang/String;)V
     302: invokestatic  #91                 // Method org/apache/hadoop/hbase/client/TestReplicasClient$SlowMeCopro.getPrimaryCdl:()Ljava/util/concurrent/atomic/AtomicReference;
     305: new           #92                 // class java/util/concurrent/CountDownLatch
     308: dup
     309: iconst_1
     310: invokespecial #93                 // Method java/util/concurrent/CountDownLatch."<init>":(I)V
     313: invokevirtual #94                 // Method java/util/concurrent/atomic/AtomicReference.set:(Ljava/lang/Object;)V
     316: new           #95                 // class org/apache/hadoop/hbase/client/Get
     319: dup
     320: aload_1
     321: invokespecial #96                 // Method org/apache/hadoop/hbase/client/Get."<init>":([B)V
     324: astore_3
     325: aload_3
     326: getstatic     #107                // Field org/apache/hadoop/hbase/client/Consistency.TIMELINE:Lorg/apache/hadoop/hbase/client/Consistency;
     329: invokevirtual #108                // Method org/apache/hadoop/hbase/client/Get.setConsistency:(Lorg/apache/hadoop/hbase/client/Consistency;)Lorg/apache/hadoop/hbase/client/Get;
     332: pop
     333: getstatic     #23                 // Field table:Lorg/apache/hadoop/hbase/client/Table;
     336: aload_3
     337: invokeinterface #97,  2           // InterfaceMethod org/apache/hadoop/hbase/client/Table.get:(Lorg/apache/hadoop/hbase/client/Get;)Lorg/apache/hadoop/hbase/client/Result;
     342: astore        4
     344: aload         4
     346: invokevirtual #98                 // Method org/apache/hadoop/hbase/client/Result.isStale:()Z
     349: invokestatic  #78                 // Method org/junit/Assert.assertTrue:(Z)V
     352: aload         4
     354: getstatic     #21                 // Field f:[B
     357: aload_1
     358: invokevirtual #127                // Method org/apache/hadoop/hbase/client/Result.getColumnCells:([B[B)Ljava/util/List;
     361: invokeinterface #128,  1          // InterfaceMethod java/util/List.isEmpty:()Z
     366: invokestatic  #78                 // Method org/junit/Assert.assertTrue:(Z)V
     369: ldc2_w        #102                // long 2l
     372: aload         6
     374: invokevirtual #148                // Method com/codahale/metrics/Counter.getCount:()J
     377: invokestatic  #69                 // Method org/junit/Assert.assertEquals:(JJ)V
     380: lconst_1
     381: aload         7
     383: invokevirtual #148                // Method com/codahale/metrics/Counter.getCount:()J
     386: invokestatic  #69                 // Method org/junit/Assert.assertEquals:(JJ)V
     389: invokestatic  #91                 // Method org/apache/hadoop/hbase/client/TestReplicasClient$SlowMeCopro.getPrimaryCdl:()Ljava/util/concurrent/atomic/AtomicReference;
     392: invokevirtual #109                // Method java/util/concurrent/atomic/AtomicReference.get:()Ljava/lang/Object;
     395: checkcast     #92                 // class java/util/concurrent/CountDownLatch
     398: invokevirtual #110                // Method java/util/concurrent/CountDownLatch.countDown:()V
     401: getstatic     #1                  // Field LOG:Lorg/slf4j/Logger;
     404: ldc           #156                // String hedged read occurred and faster
     406: invokeinterface #43,  2           // InterfaceMethod org/slf4j/Logger.info:(Ljava/lang/String;)V
     411: invokestatic  #91                 // Method org/apache/hadoop/hbase/client/TestReplicasClient$SlowMeCopro.getPrimaryCdl:()Ljava/util/concurrent/atomic/AtomicReference;
     414: invokevirtual #109                // Method java/util/concurrent/atomic/AtomicReference.get:()Ljava/lang/Object;
     417: checkcast     #92                 // class java/util/concurrent/CountDownLatch
     420: invokevirtual #110                // Method java/util/concurrent/CountDownLatch.countDown:()V
     423: invokestatic  #154                // Method org/apache/hadoop/hbase/client/TestReplicasClient$SlowMeCopro.getSecondaryCdl:()Ljava/util/concurrent/atomic/AtomicReference;
     426: invokevirtual #109                // Method java/util/concurrent/atomic/AtomicReference.get:()Ljava/lang/Object;
     429: checkcast     #92                 // class java/util/concurrent/CountDownLatch
     432: invokevirtual #110                // Method java/util/concurrent/CountDownLatch.countDown:()V
     435: getstatic     #112                // Field org/apache/hadoop/hbase/client/TestReplicasClient$SlowMeCopro.sleepTime:Ljava/util/concurrent/atomic/AtomicLong;
     438: lconst_0
     439: invokevirtual #115                // Method java/util/concurrent/atomic/AtomicLong.set:(J)V
     442: new           #121                // class org/apache/hadoop/hbase/client/Delete
     445: dup
     446: aload_1
     447: invokespecial #122                // Method org/apache/hadoop/hbase/client/Delete."<init>":([B)V
     450: astore_2
     451: getstatic     #23                 // Field table:Lorg/apache/hadoop/hbase/client/Table;
     454: aload_2
     455: invokeinterface #123,  2          // InterfaceMethod org/apache/hadoop/hbase/client/Table.delete:(Lorg/apache/hadoop/hbase/client/Delete;)V
     460: aload_0
     461: getstatic     #41                 // Field hriSecondary:Lorg/apache/hadoop/hbase/HRegionInfo;
     464: invokespecial #59                 // Method closeRegion:(Lorg/apache/hadoop/hbase/HRegionInfo;)V
     467: goto          533
     470: astore        9
     472: invokestatic  #91                 // Method org/apache/hadoop/hbase/client/TestReplicasClient$SlowMeCopro.getPrimaryCdl:()Ljava/util/concurrent/atomic/AtomicReference;
     475: invokevirtual #109                // Method java/util/concurrent/atomic/AtomicReference.get:()Ljava/lang/Object;
     478: checkcast     #92                 // class java/util/concurrent/CountDownLatch
     481: invokevirtual #110                // Method java/util/concurrent/CountDownLatch.countDown:()V
     484: invokestatic  #154                // Method org/apache/hadoop/hbase/client/TestReplicasClient$SlowMeCopro.getSecondaryCdl:()Ljava/util/concurrent/atomic/AtomicReference;
     487: invokevirtual #109                // Method java/util/concurrent/atomic/AtomicReference.get:()Ljava/lang/Object;
     490: checkcast     #92                 // class java/util/concurrent/CountDownLatch
     493: invokevirtual #110                // Method java/util/concurrent/CountDownLatch.countDown:()V
     496: getstatic     #112                // Field org/apache/hadoop/hbase/client/TestReplicasClient$SlowMeCopro.sleepTime:Ljava/util/concurrent/atomic/AtomicLong;
     499: lconst_0
     500: invokevirtual #115                // Method java/util/concurrent/atomic/AtomicLong.set:(J)V
     503: new           #121                // class org/apache/hadoop/hbase/client/Delete
     506: dup
     507: aload_1
     508: invokespecial #122                // Method org/apache/hadoop/hbase/client/Delete."<init>":([B)V
     511: astore        10
     513: getstatic     #23                 // Field table:Lorg/apache/hadoop/hbase/client/Table;
     516: aload         10
     518: invokeinterface #123,  2          // InterfaceMethod org/apache/hadoop/hbase/client/Table.delete:(Lorg/apache/hadoop/hbase/client/Delete;)V
     523: aload_0
     524: getstatic     #41                 // Field hriSecondary:Lorg/apache/hadoop/hbase/HRegionInfo;
     527: invokespecial #59                 // Method closeRegion:(Lorg/apache/hadoop/hbase/HRegionInfo;)V
     530: aload         9
     532: athrow
     533: return
    Exception table:
       from    to  target type
          13   411   470   any
         470   472   470   any

  public void testCancelOfMultiGet() throws java.lang.Exception;
    Code:
       0: aload_0
       1: getstatic     #41                 // Field hriSecondary:Lorg/apache/hadoop/hbase/HRegionInfo;
       4: invokespecial #57                 // Method openRegion:(Lorg/apache/hadoop/hbase/HRegionInfo;)V
       7: new           #157                // class java/util/ArrayList
      10: dup
      11: iconst_2
      12: invokespecial #158                // Method java/util/ArrayList."<init>":(I)V
      15: astore_1
      16: ldc           #159                // String testCancelOfMultiGet0
      18: invokestatic  #90                 // Method org/apache/hadoop/hbase/util/Bytes.toBytes:(Ljava/lang/String;)[B
      21: astore_2
      22: new           #117                // class org/apache/hadoop/hbase/client/Put
      25: dup
      26: aload_2
      27: invokespecial #118                // Method org/apache/hadoop/hbase/client/Put."<init>":([B)V
      30: astore_3
      31: aload_3
      32: getstatic     #21                 // Field f:[B
      35: aload_2
      36: aload_2
      37: invokevirtual #119                // Method org/apache/hadoop/hbase/client/Put.addColumn:([B[B[B)Lorg/apache/hadoop/hbase/client/Put;
      40: pop
      41: aload_1
      42: aload_3
      43: invokeinterface #160,  2          // InterfaceMethod java/util/List.add:(Ljava/lang/Object;)Z
      48: pop
      49: ldc           #161                // String testCancelOfMultiGet1
      51: invokestatic  #90                 // Method org/apache/hadoop/hbase/util/Bytes.toBytes:(Ljava/lang/String;)[B
      54: astore        4
      56: new           #117                // class org/apache/hadoop/hbase/client/Put
      59: dup
      60: aload         4
      62: invokespecial #118                // Method org/apache/hadoop/hbase/client/Put."<init>":([B)V
      65: astore_3
      66: aload_3
      67: getstatic     #21                 // Field f:[B
      70: aload         4
      72: aload         4
      74: invokevirtual #119                // Method org/apache/hadoop/hbase/client/Put.addColumn:([B[B[B)Lorg/apache/hadoop/hbase/client/Put;
      77: pop
      78: aload_1
      79: aload_3
      80: invokeinterface #160,  2          // InterfaceMethod java/util/List.add:(Ljava/lang/Object;)Z
      85: pop
      86: getstatic     #23                 // Field table:Lorg/apache/hadoop/hbase/client/Table;
      89: aload_1
      90: invokeinterface #162,  2          // InterfaceMethod org/apache/hadoop/hbase/client/Table.put:(Ljava/util/List;)V
      95: getstatic     #1                  // Field LOG:Lorg/slf4j/Logger;
      98: ldc           #163                // String PUT done
     100: invokeinterface #164,  2          // InterfaceMethod org/slf4j/Logger.debug:(Ljava/lang/String;)V
     105: aload_0
     106: getstatic     #30                 // Field hriPrimary:Lorg/apache/hadoop/hbase/HRegionInfo;
     109: invokespecial #116                // Method flushRegion:(Lorg/apache/hadoop/hbase/HRegionInfo;)V
     112: getstatic     #1                  // Field LOG:Lorg/slf4j/Logger;
     115: ldc           #139                // String flush done
     117: invokeinterface #43,  2           // InterfaceMethod org/slf4j/Logger.info:(Ljava/lang/String;)V
     122: ldc2_w        #140                // long 3000l
     125: invokestatic  #83                 // Method java/lang/Thread.sleep:(J)V
     128: getstatic     #3                  // Field HTU:Lorg/apache/hadoop/hbase/HBaseTestingUtility;
     131: invokevirtual #24                 // Method org/apache/hadoop/hbase/HBaseTestingUtility.getConnection:()Lorg/apache/hadoop/hbase/client/Connection;
     134: checkcast     #55                 // class org/apache/hadoop/hbase/client/ClusterConnection
     137: invokeinterface #165,  1          // InterfaceMethod org/apache/hadoop/hbase/client/ClusterConnection.getAsyncProcess:()Lorg/apache/hadoop/hbase/client/AsyncProcess;
     142: astore        5
     144: invokestatic  #91                 // Method org/apache/hadoop/hbase/client/TestReplicasClient$SlowMeCopro.getPrimaryCdl:()Ljava/util/concurrent/atomic/AtomicReference;
     147: new           #92                 // class java/util/concurrent/CountDownLatch
     150: dup
     151: iconst_1
     152: invokespecial #93                 // Method java/util/concurrent/CountDownLatch."<init>":(I)V
     155: invokevirtual #94                 // Method java/util/concurrent/atomic/AtomicReference.set:(Ljava/lang/Object;)V
     158: new           #157                // class java/util/ArrayList
     161: dup
     162: invokespecial #166                // Method java/util/ArrayList."<init>":()V
     165: astore        6
     167: new           #95                 // class org/apache/hadoop/hbase/client/Get
     170: dup
     171: aload_2
     172: invokespecial #96                 // Method org/apache/hadoop/hbase/client/Get."<init>":([B)V
     175: astore        7
     177: aload         7
     179: iconst_1
     180: invokevirtual #132                // Method org/apache/hadoop/hbase/client/Get.setCheckExistenceOnly:(Z)Lorg/apache/hadoop/hbase/client/Get;
     183: pop
     184: aload         7
     186: getstatic     #107                // Field org/apache/hadoop/hbase/client/Consistency.TIMELINE:Lorg/apache/hadoop/hbase/client/Consistency;
     189: invokevirtual #108                // Method org/apache/hadoop/hbase/client/Get.setConsistency:(Lorg/apache/hadoop/hbase/client/Consistency;)Lorg/apache/hadoop/hbase/client/Get;
     192: pop
     193: aload         6
     195: aload         7
     197: invokeinterface #160,  2          // InterfaceMethod java/util/List.add:(Ljava/lang/Object;)Z
     202: pop
     203: new           #95                 // class org/apache/hadoop/hbase/client/Get
     206: dup
     207: aload         4
     209: invokespecial #96                 // Method org/apache/hadoop/hbase/client/Get."<init>":([B)V
     212: astore        7
     214: aload         7
     216: iconst_1
     217: invokevirtual #132                // Method org/apache/hadoop/hbase/client/Get.setCheckExistenceOnly:(Z)Lorg/apache/hadoop/hbase/client/Get;
     220: pop
     221: aload         7
     223: getstatic     #107                // Field org/apache/hadoop/hbase/client/Consistency.TIMELINE:Lorg/apache/hadoop/hbase/client/Consistency;
     226: invokevirtual #108                // Method org/apache/hadoop/hbase/client/Get.setConsistency:(Lorg/apache/hadoop/hbase/client/Consistency;)Lorg/apache/hadoop/hbase/client/Get;
     229: pop
     230: aload         6
     232: aload         7
     234: invokeinterface #160,  2          // InterfaceMethod java/util/List.add:(Ljava/lang/Object;)Z
     239: pop
     240: iconst_2
     241: anewarray     #167                // class java/lang/Object
     244: astore        8
     246: getstatic     #3                  // Field HTU:Lorg/apache/hadoop/hbase/HBaseTestingUtility;
     249: invokevirtual #24                 // Method org/apache/hadoop/hbase/HBaseTestingUtility.getConnection:()Lorg/apache/hadoop/hbase/client/Connection;
     252: checkcast     #55                 // class org/apache/hadoop/hbase/client/ClusterConnection
     255: invokeinterface #150,  1          // InterfaceMethod org/apache/hadoop/hbase/client/ClusterConnection.getConnectionConfiguration:()Lorg/apache/hadoop/hbase/client/ConnectionConfiguration;
     260: invokevirtual #168                // Method org/apache/hadoop/hbase/client/ConnectionConfiguration.getOperationTimeout:()I
     263: istore        9
     265: getstatic     #3                  // Field HTU:Lorg/apache/hadoop/hbase/HBaseTestingUtility;
     268: invokevirtual #24                 // Method org/apache/hadoop/hbase/HBaseTestingUtility.getConnection:()Lorg/apache/hadoop/hbase/client/Connection;
     271: checkcast     #55                 // class org/apache/hadoop/hbase/client/ClusterConnection
     274: invokeinterface #150,  1          // InterfaceMethod org/apache/hadoop/hbase/client/ClusterConnection.getConnectionConfiguration:()Lorg/apache/hadoop/hbase/client/ConnectionConfiguration;
     279: invokevirtual #169                // Method org/apache/hadoop/hbase/client/ConnectionConfiguration.getReadRpcTimeout:()I
     282: istore        10
     284: invokestatic  #170                // Method org/apache/hadoop/hbase/client/AsyncProcessTask.newBuilder:()Lorg/apache/hadoop/hbase/client/AsyncProcessTask$Builder;
     287: getstatic     #3                  // Field HTU:Lorg/apache/hadoop/hbase/HBaseTestingUtility;
     290: invokevirtual #4                  // Method org/apache/hadoop/hbase/HBaseTestingUtility.getConfiguration:()Lorg/apache/hadoop/conf/Configuration;
     293: invokestatic  #171                // Method org/apache/hadoop/hbase/client/HTable.getDefaultExecutor:(Lorg/apache/hadoop/conf/Configuration;)Ljava/util/concurrent/ThreadPoolExecutor;
     296: invokevirtual #172                // Method org/apache/hadoop/hbase/client/AsyncProcessTask$Builder.setPool:(Ljava/util/concurrent/ExecutorService;)Lorg/apache/hadoop/hbase/client/AsyncProcessTask$Builder;
     299: getstatic     #23                 // Field table:Lorg/apache/hadoop/hbase/client/Table;
     302: invokeinterface #100,  1          // InterfaceMethod org/apache/hadoop/hbase/client/Table.getName:()Lorg/apache/hadoop/hbase/TableName;
     307: invokevirtual #173                // Method org/apache/hadoop/hbase/client/AsyncProcessTask$Builder.setTableName:(Lorg/apache/hadoop/hbase/TableName;)Lorg/apache/hadoop/hbase/client/AsyncProcessTask$Builder;
     310: aload         6
     312: invokevirtual #174                // Method org/apache/hadoop/hbase/client/AsyncProcessTask$Builder.setRowAccess:(Ljava/util/List;)Lorg/apache/hadoop/hbase/client/AsyncProcessTask$Builder;
     315: aload         8
     317: invokevirtual #175                // Method org/apache/hadoop/hbase/client/AsyncProcessTask$Builder.setResults:([Ljava/lang/Object;)Lorg/apache/hadoop/hbase/client/AsyncProcessTask$Builder;
     320: iload         9
     322: invokevirtual #176                // Method org/apache/hadoop/hbase/client/AsyncProcessTask$Builder.setOperationTimeout:(I)Lorg/apache/hadoop/hbase/client/AsyncProcessTask$Builder;
     325: iload         10
     327: invokevirtual #177                // Method org/apache/hadoop/hbase/client/AsyncProcessTask$Builder.setRpcTimeout:(I)Lorg/apache/hadoop/hbase/client/AsyncProcessTask$Builder;
     330: invokevirtual #178                // Method org/apache/hadoop/hbase/client/AsyncProcessTask$Builder.build:()Lorg/apache/hadoop/hbase/client/AsyncProcessTask;
     333: astore        11
     335: aload         5
     337: aload         11
     339: invokevirtual #179                // Method org/apache/hadoop/hbase/client/AsyncProcess.submit:(Lorg/apache/hadoop/hbase/client/AsyncProcessTask;)Lorg/apache/hadoop/hbase/client/AsyncRequestFuture;
     342: astore        12
     344: aload         12
     346: invokeinterface #180,  1          // InterfaceMethod org/apache/hadoop/hbase/client/AsyncRequestFuture.waitUntilDone:()V
     351: aload         8
     353: astore        13
     355: aload         13
     357: arraylength
     358: istore        14
     360: iconst_0
     361: istore        15
     363: iload         15
     365: iload         14
     367: if_icmpge     408
     370: aload         13
     372: iload         15
     374: aaload
     375: astore        16
     377: aload         16
     379: checkcast     #181                // class org/apache/hadoop/hbase/client/Result
     382: invokevirtual #98                 // Method org/apache/hadoop/hbase/client/Result.isStale:()Z
     385: invokestatic  #78                 // Method org/junit/Assert.assertTrue:(Z)V
     388: aload         16
     390: checkcast     #181                // class org/apache/hadoop/hbase/client/Result
     393: invokevirtual #133                // Method org/apache/hadoop/hbase/client/Result.getExists:()Ljava/lang/Boolean;
     396: invokevirtual #134                // Method java/lang/Boolean.booleanValue:()Z
     399: invokestatic  #78                 // Method org/junit/Assert.assertTrue:(Z)V
     402: iinc          15, 1
     405: goto          363
     408: aload         12
     410: checkcast     #182                // class org/apache/hadoop/hbase/client/AsyncRequestFutureImpl
     413: invokevirtual #183                // Method org/apache/hadoop/hbase/client/AsyncRequestFutureImpl.getCallsInProgress:()Ljava/util/Set;
     416: astore        13
     418: aload         13
     420: invokeinterface #184,  1          // InterfaceMethod java/util/Set.isEmpty:()Z
     425: ifne          432
     428: iconst_1
     429: goto          433
     432: iconst_0
     433: invokestatic  #78                 // Method org/junit/Assert.assertTrue:(Z)V
     436: aload         13
     438: invokeinterface #185,  1          // InterfaceMethod java/util/Set.iterator:()Ljava/util/Iterator;
     443: astore        14
     445: aload         14
     447: invokeinterface #186,  1          // InterfaceMethod java/util/Iterator.hasNext:()Z
     452: ifeq          478
     455: aload         14
     457: invokeinterface #187,  1          // InterfaceMethod java/util/Iterator.next:()Ljava/lang/Object;
     462: checkcast     #188                // class org/apache/hadoop/hbase/client/CancellableRegionServerCallable
     465: astore        15
     467: aload         15
     469: invokevirtual #189                // Method org/apache/hadoop/hbase/client/CancellableRegionServerCallable.isCancelled:()Z
     472: invokestatic  #78                 // Method org/junit/Assert.assertTrue:(Z)V
     475: goto          445
     478: invokestatic  #91                 // Method org/apache/hadoop/hbase/client/TestReplicasClient$SlowMeCopro.getPrimaryCdl:()Ljava/util/concurrent/atomic/AtomicReference;
     481: invokevirtual #109                // Method java/util/concurrent/atomic/AtomicReference.get:()Ljava/lang/Object;
     484: checkcast     #92                 // class java/util/concurrent/CountDownLatch
     487: invokevirtual #110                // Method java/util/concurrent/CountDownLatch.countDown:()V
     490: getstatic     #112                // Field org/apache/hadoop/hbase/client/TestReplicasClient$SlowMeCopro.sleepTime:Ljava/util/concurrent/atomic/AtomicLong;
     493: lconst_0
     494: invokevirtual #115                // Method java/util/concurrent/atomic/AtomicLong.set:(J)V
     497: getstatic     #190                // Field org/apache/hadoop/hbase/client/TestReplicasClient$SlowMeCopro.slowDownNext:Ljava/util/concurrent/atomic/AtomicBoolean;
     500: iconst_0
     501: invokevirtual #191                // Method java/util/concurrent/atomic/AtomicBoolean.set:(Z)V
     504: getstatic     #192                // Field org/apache/hadoop/hbase/client/TestReplicasClient$SlowMeCopro.countOfNext:Ljava/util/concurrent/atomic/AtomicInteger;
     507: iconst_0
     508: invokevirtual #193                // Method java/util/concurrent/atomic/AtomicInteger.set:(I)V
     511: iconst_0
     512: istore_1
     513: iload_1
     514: iconst_2
     515: if_icmpge     565
     518: new           #194                // class java/lang/StringBuilder
     521: dup
     522: invokespecial #195                // Method java/lang/StringBuilder."<init>":()V
     525: ldc           #196                // String testCancelOfMultiGet
     527: invokevirtual #197                // Method java/lang/StringBuilder.append:(Ljava/lang/String;)Ljava/lang/StringBuilder;
     530: iload_1
     531: invokevirtual #198                // Method java/lang/StringBuilder.append:(I)Ljava/lang/StringBuilder;
     534: invokevirtual #199                // Method java/lang/StringBuilder.toString:()Ljava/lang/String;
     537: invokestatic  #90                 // Method org/apache/hadoop/hbase/util/Bytes.toBytes:(Ljava/lang/String;)[B
     540: astore_2
     541: new           #121                // class org/apache/hadoop/hbase/client/Delete
     544: dup
     545: aload_2
     546: invokespecial #122                // Method org/apache/hadoop/hbase/client/Delete."<init>":([B)V
     549: astore_3
     550: getstatic     #23                 // Field table:Lorg/apache/hadoop/hbase/client/Table;
     553: aload_3
     554: invokeinterface #123,  2          // InterfaceMethod org/apache/hadoop/hbase/client/Table.delete:(Lorg/apache/hadoop/hbase/client/Delete;)V
     559: iinc          1, 1
     562: goto          513
     565: aload_0
     566: getstatic     #41                 // Field hriSecondary:Lorg/apache/hadoop/hbase/HRegionInfo;
     569: invokespecial #59                 // Method closeRegion:(Lorg/apache/hadoop/hbase/HRegionInfo;)V
     572: goto          681
     575: astore        17
     577: invokestatic  #91                 // Method org/apache/hadoop/hbase/client/TestReplicasClient$SlowMeCopro.getPrimaryCdl:()Ljava/util/concurrent/atomic/AtomicReference;
     580: invokevirtual #109                // Method java/util/concurrent/atomic/AtomicReference.get:()Ljava/lang/Object;
     583: checkcast     #92                 // class java/util/concurrent/CountDownLatch
     586: invokevirtual #110                // Method java/util/concurrent/CountDownLatch.countDown:()V
     589: getstatic     #112                // Field org/apache/hadoop/hbase/client/TestReplicasClient$SlowMeCopro.sleepTime:Ljava/util/concurrent/atomic/AtomicLong;
     592: lconst_0
     593: invokevirtual #115                // Method java/util/concurrent/atomic/AtomicLong.set:(J)V
     596: getstatic     #190                // Field org/apache/hadoop/hbase/client/TestReplicasClient$SlowMeCopro.slowDownNext:Ljava/util/concurrent/atomic/AtomicBoolean;
     599: iconst_0
     600: invokevirtual #191                // Method java/util/concurrent/atomic/AtomicBoolean.set:(Z)V
     603: getstatic     #192                // Field org/apache/hadoop/hbase/client/TestReplicasClient$SlowMeCopro.countOfNext:Ljava/util/concurrent/atomic/AtomicInteger;
     606: iconst_0
     607: invokevirtual #193                // Method java/util/concurrent/atomic/AtomicInteger.set:(I)V
     610: iconst_0
     611: istore        18
     613: iload         18
     615: iconst_2
     616: if_icmpge     671
     619: new           #194                // class java/lang/StringBuilder
     622: dup
     623: invokespecial #195                // Method java/lang/StringBuilder."<init>":()V
     626: ldc           #196                // String testCancelOfMultiGet
     628: invokevirtual #197                // Method java/lang/StringBuilder.append:(Ljava/lang/String;)Ljava/lang/StringBuilder;
     631: iload         18
     633: invokevirtual #198                // Method java/lang/StringBuilder.append:(I)Ljava/lang/StringBuilder;
     636: invokevirtual #199                // Method java/lang/StringBuilder.toString:()Ljava/lang/String;
     639: invokestatic  #90                 // Method org/apache/hadoop/hbase/util/Bytes.toBytes:(Ljava/lang/String;)[B
     642: astore        19
     644: new           #121                // class org/apache/hadoop/hbase/client/Delete
     647: dup
     648: aload         19
     650: invokespecial #122                // Method org/apache/hadoop/hbase/client/Delete."<init>":([B)V
     653: astore        20
     655: getstatic     #23                 // Field table:Lorg/apache/hadoop/hbase/client/Table;
     658: aload         20
     660: invokeinterface #123,  2          // InterfaceMethod org/apache/hadoop/hbase/client/Table.delete:(Lorg/apache/hadoop/hbase/client/Delete;)V
     665: iinc          18, 1
     668: goto          613
     671: aload_0
     672: getstatic     #41                 // Field hriSecondary:Lorg/apache/hadoop/hbase/HRegionInfo;
     675: invokespecial #59                 // Method closeRegion:(Lorg/apache/hadoop/hbase/HRegionInfo;)V
     678: aload         17
     680: athrow
     681: return
    Exception table:
       from    to  target type
           7   478   575   any
         575   577   575   any

  public void testScanWithReplicas() throws java.lang.Exception;
    Code:
       0: aload_0
       1: iconst_0
       2: iconst_0
       3: invokespecial #200                // Method runMultipleScansOfOneType:(ZZ)V
       6: return

  public void testSmallScanWithReplicas() throws java.lang.Exception;
    Code:
       0: aload_0
       1: iconst_0
       2: iconst_1
       3: invokespecial #200                // Method runMultipleScansOfOneType:(ZZ)V
       6: return

  public void testReverseScanWithReplicas() throws java.lang.Exception;
    Code:
       0: aload_0
       1: iconst_1
       2: iconst_0
       3: invokespecial #200                // Method runMultipleScansOfOneType:(ZZ)V
       6: return

  public void testCancelOfScan() throws java.lang.Exception;
    Code:
       0: aload_0
       1: getstatic     #41                 // Field hriSecondary:Lorg/apache/hadoop/hbase/HRegionInfo;
       4: invokespecial #57                 // Method openRegion:(Lorg/apache/hadoop/hbase/HRegionInfo;)V
       7: bipush        100
       9: istore_1
      10: iconst_0
      11: istore_2
      12: iload_2
      13: iload_1
      14: if_icmpge     77
      17: new           #194                // class java/lang/StringBuilder
      20: dup
      21: invokespecial #195                // Method java/lang/StringBuilder."<init>":()V
      24: ldc           #125                // String testUseRegionWithReplica
      26: invokevirtual #197                // Method java/lang/StringBuilder.append:(Ljava/lang/String;)Ljava/lang/StringBuilder;
      29: iload_2
      30: invokevirtual #198                // Method java/lang/StringBuilder.append:(I)Ljava/lang/StringBuilder;
      33: invokevirtual #199                // Method java/lang/StringBuilder.toString:()Ljava/lang/String;
      36: invokestatic  #90                 // Method org/apache/hadoop/hbase/util/Bytes.toBytes:(Ljava/lang/String;)[B
      39: astore_3
      40: new           #117                // class org/apache/hadoop/hbase/client/Put
      43: dup
      44: aload_3
      45: invokespecial #118                // Method org/apache/hadoop/hbase/client/Put."<init>":([B)V
      48: astore        4
      50: aload         4
      52: getstatic     #21                 // Field f:[B
      55: aload_3
      56: aload_3
      57: invokevirtual #119                // Method org/apache/hadoop/hbase/client/Put.addColumn:([B[B[B)Lorg/apache/hadoop/hbase/client/Put;
      60: pop
      61: getstatic     #23                 // Field table:Lorg/apache/hadoop/hbase/client/Table;
      64: aload         4
      66: invokeinterface #120,  2          // InterfaceMethod org/apache/hadoop/hbase/client/Table.put:(Lorg/apache/hadoop/hbase/client/Put;)V
      71: iinc          2, 1
      74: goto          12
      77: getstatic     #1                  // Field LOG:Lorg/slf4j/Logger;
      80: ldc           #163                // String PUT done
      82: invokeinterface #164,  2          // InterfaceMethod org/slf4j/Logger.debug:(Ljava/lang/String;)V
      87: bipush        20
      89: istore_2
      90: ldc           #201                // String testUseRegionWithReplica0
      92: invokestatic  #90                 // Method org/apache/hadoop/hbase/util/Bytes.toBytes:(Ljava/lang/String;)[B
      95: astore_3
      96: aload_0
      97: getstatic     #30                 // Field hriPrimary:Lorg/apache/hadoop/hbase/HRegionInfo;
     100: invokespecial #116                // Method flushRegion:(Lorg/apache/hadoop/hbase/HRegionInfo;)V
     103: getstatic     #1                  // Field LOG:Lorg/slf4j/Logger;
     106: ldc           #139                // String flush done
     108: invokeinterface #43,  2           // InterfaceMethod org/slf4j/Logger.info:(Ljava/lang/String;)V
     113: ldc2_w        #140                // long 3000l
     116: invokestatic  #83                 // Method java/lang/Thread.sleep:(J)V
     119: getstatic     #190                // Field org/apache/hadoop/hbase/client/TestReplicasClient$SlowMeCopro.slowDownNext:Ljava/util/concurrent/atomic/AtomicBoolean;
     122: iconst_1
     123: invokevirtual #191                // Method java/util/concurrent/atomic/AtomicBoolean.set:(Z)V
     126: getstatic     #192                // Field org/apache/hadoop/hbase/client/TestReplicasClient$SlowMeCopro.countOfNext:Ljava/util/concurrent/atomic/AtomicInteger;
     129: iconst_0
     130: invokevirtual #193                // Method java/util/concurrent/atomic/AtomicInteger.set:(I)V
     133: getstatic     #112                // Field org/apache/hadoop/hbase/client/TestReplicasClient$SlowMeCopro.sleepTime:Ljava/util/concurrent/atomic/AtomicLong;
     136: ldc2_w        #202                // long 5000l
     139: invokevirtual #115                // Method java/util/concurrent/atomic/AtomicLong.set:(J)V
     142: new           #204                // class org/apache/hadoop/hbase/client/Scan
     145: dup
     146: aload_3
     147: invokespecial #205                // Method org/apache/hadoop/hbase/client/Scan."<init>":([B)V
     150: astore        4
     152: aload         4
     154: iload_2
     155: invokevirtual #206                // Method org/apache/hadoop/hbase/client/Scan.setCaching:(I)Lorg/apache/hadoop/hbase/client/Scan;
     158: pop
     159: aload         4
     161: getstatic     #107                // Field org/apache/hadoop/hbase/client/Consistency.TIMELINE:Lorg/apache/hadoop/hbase/client/Consistency;
     164: invokevirtual #207                // Method org/apache/hadoop/hbase/client/Scan.setConsistency:(Lorg/apache/hadoop/hbase/client/Consistency;)Lorg/apache/hadoop/hbase/client/Scan;
     167: pop
     168: getstatic     #23                 // Field table:Lorg/apache/hadoop/hbase/client/Table;
     171: aload         4
     173: invokeinterface #208,  2          // InterfaceMethod org/apache/hadoop/hbase/client/Table.getScanner:(Lorg/apache/hadoop/hbase/client/Scan;)Lorg/apache/hadoop/hbase/client/ResultScanner;
     178: astore        5
     180: aload         5
     182: invokeinterface #209,  1          // InterfaceMethod org/apache/hadoop/hbase/client/ResultScanner.iterator:()Ljava/util/Iterator;
     187: astore        6
     189: aload         6
     191: invokeinterface #187,  1          // InterfaceMethod java/util/Iterator.next:()Ljava/lang/Object;
     196: pop
     197: aload         5
     199: checkcast     #210                // class org/apache/hadoop/hbase/client/ClientScanner
     202: invokevirtual #211                // Method org/apache/hadoop/hbase/client/ClientScanner.isAnyRPCcancelled:()Z
     205: invokestatic  #78                 // Method org/junit/Assert.assertTrue:(Z)V
     208: getstatic     #190                // Field org/apache/hadoop/hbase/client/TestReplicasClient$SlowMeCopro.slowDownNext:Ljava/util/concurrent/atomic/AtomicBoolean;
     211: iconst_0
     212: invokevirtual #191                // Method java/util/concurrent/atomic/AtomicBoolean.set:(Z)V
     215: getstatic     #192                // Field org/apache/hadoop/hbase/client/TestReplicasClient$SlowMeCopro.countOfNext:Ljava/util/concurrent/atomic/AtomicInteger;
     218: iconst_0
     219: invokevirtual #193                // Method java/util/concurrent/atomic/AtomicInteger.set:(I)V
     222: invokestatic  #91                 // Method org/apache/hadoop/hbase/client/TestReplicasClient$SlowMeCopro.getPrimaryCdl:()Ljava/util/concurrent/atomic/AtomicReference;
     225: invokevirtual #109                // Method java/util/concurrent/atomic/AtomicReference.get:()Ljava/lang/Object;
     228: checkcast     #92                 // class java/util/concurrent/CountDownLatch
     231: invokevirtual #110                // Method java/util/concurrent/CountDownLatch.countDown:()V
     234: getstatic     #112                // Field org/apache/hadoop/hbase/client/TestReplicasClient$SlowMeCopro.sleepTime:Ljava/util/concurrent/atomic/AtomicLong;
     237: lconst_0
     238: invokevirtual #115                // Method java/util/concurrent/atomic/AtomicLong.set:(J)V
     241: getstatic     #190                // Field org/apache/hadoop/hbase/client/TestReplicasClient$SlowMeCopro.slowDownNext:Ljava/util/concurrent/atomic/AtomicBoolean;
     244: iconst_0
     245: invokevirtual #191                // Method java/util/concurrent/atomic/AtomicBoolean.set:(Z)V
     248: getstatic     #192                // Field org/apache/hadoop/hbase/client/TestReplicasClient$SlowMeCopro.countOfNext:Ljava/util/concurrent/atomic/AtomicInteger;
     251: iconst_0
     252: invokevirtual #193                // Method java/util/concurrent/atomic/AtomicInteger.set:(I)V
     255: iconst_0
     256: istore_2
     257: iload_2
     258: iload_1
     259: if_icmpge     311
     262: new           #194                // class java/lang/StringBuilder
     265: dup
     266: invokespecial #195                // Method java/lang/StringBuilder."<init>":()V
     269: ldc           #125                // String testUseRegionWithReplica
     271: invokevirtual #197                // Method java/lang/StringBuilder.append:(Ljava/lang/String;)Ljava/lang/StringBuilder;
     274: iload_2
     275: invokevirtual #198                // Method java/lang/StringBuilder.append:(I)Ljava/lang/StringBuilder;
     278: invokevirtual #199                // Method java/lang/StringBuilder.toString:()Ljava/lang/String;
     281: invokestatic  #90                 // Method org/apache/hadoop/hbase/util/Bytes.toBytes:(Ljava/lang/String;)[B
     284: astore_3
     285: new           #121                // class org/apache/hadoop/hbase/client/Delete
     288: dup
     289: aload_3
     290: invokespecial #122                // Method org/apache/hadoop/hbase/client/Delete."<init>":([B)V
     293: astore        4
     295: getstatic     #23                 // Field table:Lorg/apache/hadoop/hbase/client/Table;
     298: aload         4
     300: invokeinterface #123,  2          // InterfaceMethod org/apache/hadoop/hbase/client/Table.delete:(Lorg/apache/hadoop/hbase/client/Delete;)V
     305: iinc          2, 1
     308: goto          257
     311: aload_0
     312: getstatic     #41                 // Field hriSecondary:Lorg/apache/hadoop/hbase/HRegionInfo;
     315: invokespecial #59                 // Method closeRegion:(Lorg/apache/hadoop/hbase/HRegionInfo;)V
     318: goto          427
     321: astore        7
     323: invokestatic  #91                 // Method org/apache/hadoop/hbase/client/TestReplicasClient$SlowMeCopro.getPrimaryCdl:()Ljava/util/concurrent/atomic/AtomicReference;
     326: invokevirtual #109                // Method java/util/concurrent/atomic/AtomicReference.get:()Ljava/lang/Object;
     329: checkcast     #92                 // class java/util/concurrent/CountDownLatch
     332: invokevirtual #110                // Method java/util/concurrent/CountDownLatch.countDown:()V
     335: getstatic     #112                // Field org/apache/hadoop/hbase/client/TestReplicasClient$SlowMeCopro.sleepTime:Ljava/util/concurrent/atomic/AtomicLong;
     338: lconst_0
     339: invokevirtual #115                // Method java/util/concurrent/atomic/AtomicLong.set:(J)V
     342: getstatic     #190                // Field org/apache/hadoop/hbase/client/TestReplicasClient$SlowMeCopro.slowDownNext:Ljava/util/concurrent/atomic/AtomicBoolean;
     345: iconst_0
     346: invokevirtual #191                // Method java/util/concurrent/atomic/AtomicBoolean.set:(Z)V
     349: getstatic     #192                // Field org/apache/hadoop/hbase/client/TestReplicasClient$SlowMeCopro.countOfNext:Ljava/util/concurrent/atomic/AtomicInteger;
     352: iconst_0
     353: invokevirtual #193                // Method java/util/concurrent/atomic/AtomicInteger.set:(I)V
     356: iconst_0
     357: istore        8
     359: iload         8
     361: iload_1
     362: if_icmpge     417
     365: new           #194                // class java/lang/StringBuilder
     368: dup
     369: invokespecial #195                // Method java/lang/StringBuilder."<init>":()V
     372: ldc           #125                // String testUseRegionWithReplica
     374: invokevirtual #197                // Method java/lang/StringBuilder.append:(Ljava/lang/String;)Ljava/lang/StringBuilder;
     377: iload         8
     379: invokevirtual #198                // Method java/lang/StringBuilder.append:(I)Ljava/lang/StringBuilder;
     382: invokevirtual #199                // Method java/lang/StringBuilder.toString:()Ljava/lang/String;
     385: invokestatic  #90                 // Method org/apache/hadoop/hbase/util/Bytes.toBytes:(Ljava/lang/String;)[B
     388: astore        9
     390: new           #121                // class org/apache/hadoop/hbase/client/Delete
     393: dup
     394: aload         9
     396: invokespecial #122                // Method org/apache/hadoop/hbase/client/Delete."<init>":([B)V
     399: astore        10
     401: getstatic     #23                 // Field table:Lorg/apache/hadoop/hbase/client/Table;
     404: aload         10
     406: invokeinterface #123,  2          // InterfaceMethod org/apache/hadoop/hbase/client/Table.delete:(Lorg/apache/hadoop/hbase/client/Delete;)V
     411: iinc          8, 1
     414: goto          359
     417: aload_0
     418: getstatic     #41                 // Field hriSecondary:Lorg/apache/hadoop/hbase/HRegionInfo;
     421: invokespecial #59                 // Method closeRegion:(Lorg/apache/hadoop/hbase/HRegionInfo;)V
     424: aload         7
     426: athrow
     427: return
    Exception table:
       from    to  target type
          10   222   321   any
         321   323   321   any

  static org.slf4j.Logger access$000();
    Code:
       0: getstatic     #1                  // Field LOG:Lorg/slf4j/Logger;
       3: areturn

  static {};
    Code:
       0: ldc           #7                  // class org/apache/hadoop/hbase/client/TestReplicasClient
       2: invokestatic  #242                // Method org/apache/hadoop/hbase/HBaseClassTestRule.forClass:(Ljava/lang/Class;)Lorg/apache/hadoop/hbase/HBaseClassTestRule;
       5: putstatic     #243                // Field CLASS_RULE:Lorg/apache/hadoop/hbase/HBaseClassTestRule;
       8: ldc           #7                  // class org/apache/hadoop/hbase/client/TestReplicasClient
      10: invokestatic  #244                // Method org/slf4j/LoggerFactory.getLogger:(Ljava/lang/Class;)Lorg/slf4j/Logger;
      13: putstatic     #1                  // Field LOG:Lorg/slf4j/Logger;
      16: aconst_null
      17: putstatic     #23                 // Field table:Lorg/apache/hadoop/hbase/client/Table;
      20: ldc           #7                  // class org/apache/hadoop/hbase/client/TestReplicasClient
      22: invokevirtual #18                 // Method java/lang/Class.getName:()Ljava/lang/String;
      25: invokestatic  #90                 // Method org/apache/hadoop/hbase/util/Bytes.toBytes:(Ljava/lang/String;)[B
      28: putstatic     #27                 // Field row:[B
      31: new           #245                // class org/apache/hadoop/hbase/HBaseTestingUtility
      34: dup
      35: invokespecial #246                // Method org/apache/hadoop/hbase/HBaseTestingUtility."<init>":()V
      38: putstatic     #3                  // Field HTU:Lorg/apache/hadoop/hbase/HBaseTestingUtility;
      41: getstatic     #247                // Field org/apache/hadoop/hbase/HConstants.CATALOG_FAMILY:[B
      44: putstatic     #21                 // Field f:[B
      47: return
}
