Compiled from "TestAsyncAdminWithRegionReplicas.java"
public class org.apache.hadoop.hbase.client.TestAsyncAdminWithRegionReplicas extends org.apache.hadoop.hbase.client.TestAsyncAdminBase {
  public static final org.apache.hadoop.hbase.HBaseClassTestRule CLASS_RULE;

  public org.apache.hadoop.hbase.client.TestAsyncAdminWithRegionReplicas();
    Code:
       0: aload_0
       1: invokespecial #1                  // Method org/apache/hadoop/hbase/client/TestAsyncAdminBase."<init>":()V
       4: return

  public static void setUpBeforeClass() throws java.lang.Exception;
    Code:
       0: getstatic     #2                  // Field TEST_UTIL:Lorg/apache/hadoop/hbase/HBaseTestingUtility;
       3: invokevirtual #3                  // Method org/apache/hadoop/hbase/HBaseTestingUtility.getConfiguration:()Lorg/apache/hadoop/conf/Configuration;
       6: ldc           #5                  // String hbase.meta.replica.count
       8: iconst_3
       9: invokevirtual #6                  // Method org/apache/hadoop/conf/Configuration.setInt:(Ljava/lang/String;I)V
      12: invokestatic  #7                  // Method org/apache/hadoop/hbase/client/TestAsyncAdminBase.setUpBeforeClass:()V
      15: getstatic     #2                  // Field TEST_UTIL:Lorg/apache/hadoop/hbase/HBaseTestingUtility;
      18: invokevirtual #3                  // Method org/apache/hadoop/hbase/HBaseTestingUtility.getConfiguration:()Lorg/apache/hadoop/conf/Configuration;
      21: invokestatic  #8                  // Method org/apache/hadoop/hbase/client/AsyncRegistryFactory.getRegistry:(Lorg/apache/hadoop/conf/Configuration;)Lorg/apache/hadoop/hbase/client/AsyncRegistry;
      24: astore_0
      25: aconst_null
      26: astore_1
      27: getstatic     #2                  // Field TEST_UTIL:Lorg/apache/hadoop/hbase/HBaseTestingUtility;
      30: invokevirtual #3                  // Method org/apache/hadoop/hbase/HBaseTestingUtility.getConfiguration:()Lorg/apache/hadoop/conf/Configuration;
      33: aload_0
      34: iconst_3
      35: invokestatic  #9                  // Method org/apache/hadoop/hbase/client/RegionReplicaTestHelper.waitUntilAllMetaReplicasHavingRegionLocation:(Lorg/apache/hadoop/conf/Configuration;Lorg/apache/hadoop/hbase/client/AsyncRegistry;I)V
      38: aload_0
      39: ifnull        115
      42: aload_1
      43: ifnull        64
      46: aload_0
      47: invokeinterface #10,  1           // InterfaceMethod org/apache/hadoop/hbase/client/AsyncRegistry.close:()V
      52: goto          115
      55: astore_2
      56: aload_1
      57: aload_2
      58: invokevirtual #12                 // Method java/lang/Throwable.addSuppressed:(Ljava/lang/Throwable;)V
      61: goto          115
      64: aload_0
      65: invokeinterface #10,  1           // InterfaceMethod org/apache/hadoop/hbase/client/AsyncRegistry.close:()V
      70: goto          115
      73: astore_2
      74: aload_2
      75: astore_1
      76: aload_2
      77: athrow
      78: astore_3
      79: aload_0
      80: ifnull        113
      83: aload_1
      84: ifnull        107
      87: aload_0
      88: invokeinterface #10,  1           // InterfaceMethod org/apache/hadoop/hbase/client/AsyncRegistry.close:()V
      93: goto          113
      96: astore        4
      98: aload_1
      99: aload         4
     101: invokevirtual #12                 // Method java/lang/Throwable.addSuppressed:(Ljava/lang/Throwable;)V
     104: goto          113
     107: aload_0
     108: invokeinterface #10,  1           // InterfaceMethod org/apache/hadoop/hbase/client/AsyncRegistry.close:()V
     113: aload_3
     114: athrow
     115: return
    Exception table:
       from    to  target type
          46    52    55   Class java/lang/Throwable
          27    38    73   Class java/lang/Throwable
          27    38    78   any
          87    93    96   Class java/lang/Throwable
          73    79    78   any

  public void testMoveNonDefaultReplica() throws java.lang.InterruptedException, java.util.concurrent.ExecutionException, java.io.IOException;
    Code:
       0: aload_0
       1: aload_0
       2: getfield      #29                 // Field tableName:Lorg/apache/hadoop/hbase/TableName;
       5: iconst_3
       6: invokevirtual #30                 // Method createTableWithDefaultConf:(Lorg/apache/hadoop/hbase/TableName;I)V
       9: aload_0
      10: aload_0
      11: getfield      #29                 // Field tableName:Lorg/apache/hadoop/hbase/TableName;
      14: invokespecial #31                 // Method testMoveNonDefaultReplica:(Lorg/apache/hadoop/hbase/TableName;)V
      17: aload_0
      18: getstatic     #32                 // Field org/apache/hadoop/hbase/TableName.META_TABLE_NAME:Lorg/apache/hadoop/hbase/TableName;
      21: invokespecial #31                 // Method testMoveNonDefaultReplica:(Lorg/apache/hadoop/hbase/TableName;)V
      24: return

  public void testSplitNonDefaultReplica() throws java.lang.InterruptedException, java.util.concurrent.ExecutionException, java.io.IOException;
    Code:
       0: aload_0
       1: aload_0
       2: getfield      #29                 // Field tableName:Lorg/apache/hadoop/hbase/TableName;
       5: iconst_3
       6: invokevirtual #30                 // Method createTableWithDefaultConf:(Lorg/apache/hadoop/hbase/TableName;I)V
       9: getstatic     #13                 // Field ASYNC_CONN:Lorg/apache/hadoop/hbase/client/AsyncConnection;
      12: aload_0
      13: getfield      #29                 // Field tableName:Lorg/apache/hadoop/hbase/TableName;
      16: invokeinterface #14,  2           // InterfaceMethod org/apache/hadoop/hbase/client/AsyncConnection.getRegionLocator:(Lorg/apache/hadoop/hbase/TableName;)Lorg/apache/hadoop/hbase/client/AsyncTableRegionLocator;
      21: invokeinterface #15,  1           // InterfaceMethod org/apache/hadoop/hbase/client/AsyncTableRegionLocator.getAllRegionLocations:()Ljava/util/concurrent/CompletableFuture;
      26: invokevirtual #16                 // Method java/util/concurrent/CompletableFuture.get:()Ljava/lang/Object;
      29: checkcast     #17                 // class java/util/List
      32: astore_1
      33: aload_0
      34: getfield      #18                 // Field admin:Lorg/apache/hadoop/hbase/client/AsyncAdmin;
      37: aload_1
      38: iconst_1
      39: invokeinterface #19,  2           // InterfaceMethod java/util/List.get:(I)Ljava/lang/Object;
      44: checkcast     #20                 // class org/apache/hadoop/hbase/HRegionLocation
      47: invokevirtual #21                 // Method org/apache/hadoop/hbase/HRegionLocation.getRegion:()Lorg/apache/hadoop/hbase/client/RegionInfo;
      50: invokeinterface #22,  1           // InterfaceMethod org/apache/hadoop/hbase/client/RegionInfo.getRegionName:()[B
      55: invokeinterface #33,  2           // InterfaceMethod org/apache/hadoop/hbase/client/AsyncAdmin.splitRegion:([B)Ljava/util/concurrent/CompletableFuture;
      60: invokevirtual #16                 // Method java/util/concurrent/CompletableFuture.get:()Ljava/lang/Object;
      63: pop
      64: goto          80
      67: astore_2
      68: aload_2
      69: invokevirtual #35                 // Method java/util/concurrent/ExecutionException.getCause:()Ljava/lang/Throwable;
      72: ldc           #36                 // class java/lang/IllegalArgumentException
      74: invokestatic  #37                 // Method org/hamcrest/CoreMatchers.instanceOf:(Ljava/lang/Class;)Lorg/hamcrest/Matcher;
      77: invokestatic  #38                 // Method org/junit/Assert.assertThat:(Ljava/lang/Object;Lorg/hamcrest/Matcher;)V
      80: aload_0
      81: getfield      #18                 // Field admin:Lorg/apache/hadoop/hbase/client/AsyncAdmin;
      84: aload_1
      85: iconst_2
      86: invokeinterface #19,  2           // InterfaceMethod java/util/List.get:(I)Ljava/lang/Object;
      91: checkcast     #20                 // class org/apache/hadoop/hbase/HRegionLocation
      94: invokevirtual #21                 // Method org/apache/hadoop/hbase/HRegionLocation.getRegion:()Lorg/apache/hadoop/hbase/client/RegionInfo;
      97: invokeinterface #28,  1           // InterfaceMethod org/apache/hadoop/hbase/client/RegionInfo.getEncodedNameAsBytes:()[B
     102: invokeinterface #33,  2           // InterfaceMethod org/apache/hadoop/hbase/client/AsyncAdmin.splitRegion:([B)Ljava/util/concurrent/CompletableFuture;
     107: invokevirtual #16                 // Method java/util/concurrent/CompletableFuture.get:()Ljava/lang/Object;
     110: pop
     111: goto          127
     114: astore_2
     115: aload_2
     116: invokevirtual #35                 // Method java/util/concurrent/ExecutionException.getCause:()Ljava/lang/Throwable;
     119: ldc           #36                 // class java/lang/IllegalArgumentException
     121: invokestatic  #37                 // Method org/hamcrest/CoreMatchers.instanceOf:(Ljava/lang/Class;)Lorg/hamcrest/Matcher;
     124: invokestatic  #38                 // Method org/junit/Assert.assertThat:(Ljava/lang/Object;Lorg/hamcrest/Matcher;)V
     127: return
    Exception table:
       from    to  target type
          33    64    67   Class java/util/concurrent/ExecutionException
          80   111   114   Class java/util/concurrent/ExecutionException

  public void testMergeNonDefaultReplicas() throws java.lang.InterruptedException, java.util.concurrent.ExecutionException, java.io.IOException;
    Code:
       0: iconst_1
       1: anewarray     #39                 // class "[B"
       4: dup
       5: iconst_0
       6: iconst_0
       7: invokestatic  #40                 // Method org/apache/hadoop/hbase/util/Bytes.toBytes:(I)[B
      10: aastore
      11: astore_1
      12: aload_0
      13: aload_0
      14: getfield      #29                 // Field tableName:Lorg/apache/hadoop/hbase/TableName;
      17: iconst_3
      18: aload_1
      19: invokevirtual #41                 // Method createTableWithDefaultConf:(Lorg/apache/hadoop/hbase/TableName;I[[B)V
      22: getstatic     #13                 // Field ASYNC_CONN:Lorg/apache/hadoop/hbase/client/AsyncConnection;
      25: aload_0
      26: getfield      #29                 // Field tableName:Lorg/apache/hadoop/hbase/TableName;
      29: invokeinterface #14,  2           // InterfaceMethod org/apache/hadoop/hbase/client/AsyncConnection.getRegionLocator:(Lorg/apache/hadoop/hbase/TableName;)Lorg/apache/hadoop/hbase/client/AsyncTableRegionLocator;
      34: invokeinterface #15,  1           // InterfaceMethod org/apache/hadoop/hbase/client/AsyncTableRegionLocator.getAllRegionLocations:()Ljava/util/concurrent/CompletableFuture;
      39: invokevirtual #16                 // Method java/util/concurrent/CompletableFuture.get:()Ljava/lang/Object;
      42: checkcast     #17                 // class java/util/List
      45: astore_2
      46: ldc2_w        #42                 // long 6l
      49: aload_2
      50: invokeinterface #44,  1           // InterfaceMethod java/util/List.size:()I
      55: i2l
      56: invokestatic  #45                 // Method org/junit/Assert.assertEquals:(JJ)V
      59: aload_2
      60: invokeinterface #46,  1           // InterfaceMethod java/util/List.stream:()Ljava/util/stream/Stream;
      65: invokedynamic #47,  0             // InvokeDynamic #0:apply:()Ljava/util/function/Function;
      70: invokeinterface #48,  2           // InterfaceMethod java/util/stream/Stream.map:(Ljava/util/function/Function;)Ljava/util/stream/Stream;
      75: invokedynamic #49,  0             // InvokeDynamic #1:apply:()Ljava/util/function/Function;
      80: invokestatic  #50                 // Method java/util/stream/Collectors.groupingBy:(Ljava/util/function/Function;)Ljava/util/stream/Collector;
      83: invokeinterface #51,  2           // InterfaceMethod java/util/stream/Stream.collect:(Ljava/util/stream/Collector;)Ljava/lang/Object;
      88: checkcast     #52                 // class java/util/Map
      91: astore_3
      92: aload_3
      93: iconst_1
      94: invokestatic  #53                 // Method java/lang/Integer.valueOf:(I)Ljava/lang/Integer;
      97: invokeinterface #54,  2           // InterfaceMethod java/util/Map.get:(Ljava/lang/Object;)Ljava/lang/Object;
     102: checkcast     #17                 // class java/util/List
     105: astore        4
     107: aload_0
     108: getfield      #18                 // Field admin:Lorg/apache/hadoop/hbase/client/AsyncAdmin;
     111: aload         4
     113: iconst_0
     114: invokeinterface #19,  2           // InterfaceMethod java/util/List.get:(I)Ljava/lang/Object;
     119: checkcast     #55                 // class org/apache/hadoop/hbase/client/RegionInfo
     122: invokeinterface #22,  1           // InterfaceMethod org/apache/hadoop/hbase/client/RegionInfo.getRegionName:()[B
     127: aload         4
     129: iconst_1
     130: invokeinterface #19,  2           // InterfaceMethod java/util/List.get:(I)Ljava/lang/Object;
     135: checkcast     #55                 // class org/apache/hadoop/hbase/client/RegionInfo
     138: invokeinterface #22,  1           // InterfaceMethod org/apache/hadoop/hbase/client/RegionInfo.getRegionName:()[B
     143: iconst_0
     144: invokeinterface #56,  4           // InterfaceMethod org/apache/hadoop/hbase/client/AsyncAdmin.mergeRegions:([B[BZ)Ljava/util/concurrent/CompletableFuture;
     149: invokevirtual #16                 // Method java/util/concurrent/CompletableFuture.get:()Ljava/lang/Object;
     152: pop
     153: goto          171
     156: astore        5
     158: aload         5
     160: invokevirtual #35                 // Method java/util/concurrent/ExecutionException.getCause:()Ljava/lang/Throwable;
     163: ldc           #36                 // class java/lang/IllegalArgumentException
     165: invokestatic  #37                 // Method org/hamcrest/CoreMatchers.instanceOf:(Ljava/lang/Class;)Lorg/hamcrest/Matcher;
     168: invokestatic  #38                 // Method org/junit/Assert.assertThat:(Ljava/lang/Object;Lorg/hamcrest/Matcher;)V
     171: aload_3
     172: iconst_2
     173: invokestatic  #53                 // Method java/lang/Integer.valueOf:(I)Ljava/lang/Integer;
     176: invokeinterface #54,  2           // InterfaceMethod java/util/Map.get:(Ljava/lang/Object;)Ljava/lang/Object;
     181: checkcast     #17                 // class java/util/List
     184: astore        5
     186: aload_0
     187: getfield      #18                 // Field admin:Lorg/apache/hadoop/hbase/client/AsyncAdmin;
     190: aload         5
     192: iconst_0
     193: invokeinterface #19,  2           // InterfaceMethod java/util/List.get:(I)Ljava/lang/Object;
     198: checkcast     #55                 // class org/apache/hadoop/hbase/client/RegionInfo
     201: invokeinterface #22,  1           // InterfaceMethod org/apache/hadoop/hbase/client/RegionInfo.getRegionName:()[B
     206: aload         5
     208: iconst_1
     209: invokeinterface #19,  2           // InterfaceMethod java/util/List.get:(I)Ljava/lang/Object;
     214: checkcast     #55                 // class org/apache/hadoop/hbase/client/RegionInfo
     217: invokeinterface #22,  1           // InterfaceMethod org/apache/hadoop/hbase/client/RegionInfo.getRegionName:()[B
     222: iconst_0
     223: invokeinterface #56,  4           // InterfaceMethod org/apache/hadoop/hbase/client/AsyncAdmin.mergeRegions:([B[BZ)Ljava/util/concurrent/CompletableFuture;
     228: invokevirtual #16                 // Method java/util/concurrent/CompletableFuture.get:()Ljava/lang/Object;
     231: pop
     232: goto          250
     235: astore        6
     237: aload         6
     239: invokevirtual #35                 // Method java/util/concurrent/ExecutionException.getCause:()Ljava/lang/Throwable;
     242: ldc           #36                 // class java/lang/IllegalArgumentException
     244: invokestatic  #37                 // Method org/hamcrest/CoreMatchers.instanceOf:(Ljava/lang/Class;)Lorg/hamcrest/Matcher;
     247: invokestatic  #38                 // Method org/junit/Assert.assertThat:(Ljava/lang/Object;Lorg/hamcrest/Matcher;)V
     250: return
    Exception table:
       from    to  target type
         107   153   156   Class java/util/concurrent/ExecutionException
         186   232   235   Class java/util/concurrent/ExecutionException

  public void testCloneTableSchema() throws java.io.IOException, java.lang.InterruptedException, java.util.concurrent.ExecutionException;
    Code:
       0: aload_0
       1: aload_0
       2: getfield      #29                 // Field tableName:Lorg/apache/hadoop/hbase/TableName;
       5: iconst_3
       6: invokevirtual #30                 // Method createTableWithDefaultConf:(Lorg/apache/hadoop/hbase/TableName;I)V
       9: aload_0
      10: getfield      #18                 // Field admin:Lorg/apache/hadoop/hbase/client/AsyncAdmin;
      13: aload_0
      14: getfield      #29                 // Field tableName:Lorg/apache/hadoop/hbase/TableName;
      17: new           #57                 // class java/lang/StringBuilder
      20: dup
      21: invokespecial #58                 // Method java/lang/StringBuilder."<init>":()V
      24: aload_0
      25: getfield      #29                 // Field tableName:Lorg/apache/hadoop/hbase/TableName;
      28: invokevirtual #59                 // Method org/apache/hadoop/hbase/TableName.getNameAsString:()Ljava/lang/String;
      31: invokevirtual #60                 // Method java/lang/StringBuilder.append:(Ljava/lang/String;)Ljava/lang/StringBuilder;
      34: ldc           #61                 // String _new
      36: invokevirtual #60                 // Method java/lang/StringBuilder.append:(Ljava/lang/String;)Ljava/lang/StringBuilder;
      39: invokevirtual #62                 // Method java/lang/StringBuilder.toString:()Ljava/lang/String;
      42: invokestatic  #63                 // Method org/apache/hadoop/hbase/TableName.valueOf:(Ljava/lang/String;)Lorg/apache/hadoop/hbase/TableName;
      45: iconst_1
      46: invokeinterface #64,  4           // InterfaceMethod org/apache/hadoop/hbase/client/AsyncAdmin.cloneTableSchema:(Lorg/apache/hadoop/hbase/TableName;Lorg/apache/hadoop/hbase/TableName;Z)Ljava/util/concurrent/CompletableFuture;
      51: invokevirtual #16                 // Method java/util/concurrent/CompletableFuture.get:()Ljava/lang/Object;
      54: pop
      55: return

  public void testGetTableRegions() throws java.lang.InterruptedException, java.util.concurrent.ExecutionException, java.io.IOException;
    Code:
       0: aload_0
       1: getfield      #18                 // Field admin:Lorg/apache/hadoop/hbase/client/AsyncAdmin;
       4: getstatic     #32                 // Field org/apache/hadoop/hbase/TableName.META_TABLE_NAME:Lorg/apache/hadoop/hbase/TableName;
       7: invokeinterface #65,  2           // InterfaceMethod org/apache/hadoop/hbase/client/AsyncAdmin.getRegions:(Lorg/apache/hadoop/hbase/TableName;)Ljava/util/concurrent/CompletableFuture;
      12: invokevirtual #16                 // Method java/util/concurrent/CompletableFuture.get:()Ljava/lang/Object;
      15: checkcast     #17                 // class java/util/List
      18: astore_1
      19: ldc2_w        #66                 // long 3l
      22: aload_1
      23: invokeinterface #44,  1           // InterfaceMethod java/util/List.size:()I
      28: i2l
      29: invokestatic  #45                 // Method org/junit/Assert.assertEquals:(JJ)V
      32: iconst_0
      33: istore_2
      34: iload_2
      35: iconst_3
      36: if_icmpge     80
      39: aload_1
      40: iload_2
      41: invokeinterface #19,  2           // InterfaceMethod java/util/List.get:(I)Ljava/lang/Object;
      46: checkcast     #55                 // class org/apache/hadoop/hbase/client/RegionInfo
      49: astore_3
      50: getstatic     #32                 // Field org/apache/hadoop/hbase/TableName.META_TABLE_NAME:Lorg/apache/hadoop/hbase/TableName;
      53: aload_3
      54: invokeinterface #68,  1           // InterfaceMethod org/apache/hadoop/hbase/client/RegionInfo.getTable:()Lorg/apache/hadoop/hbase/TableName;
      59: invokestatic  #69                 // Method org/junit/Assert.assertEquals:(Ljava/lang/Object;Ljava/lang/Object;)V
      62: iload_2
      63: i2l
      64: aload_3
      65: invokeinterface #70,  1           // InterfaceMethod org/apache/hadoop/hbase/client/RegionInfo.getReplicaId:()I
      70: i2l
      71: invokestatic  #45                 // Method org/junit/Assert.assertEquals:(JJ)V
      74: iinc          2, 1
      77: goto          34
      80: aload_0
      81: aload_0
      82: getfield      #29                 // Field tableName:Lorg/apache/hadoop/hbase/TableName;
      85: iconst_3
      86: invokevirtual #30                 // Method createTableWithDefaultConf:(Lorg/apache/hadoop/hbase/TableName;I)V
      89: aload_0
      90: getfield      #18                 // Field admin:Lorg/apache/hadoop/hbase/client/AsyncAdmin;
      93: aload_0
      94: getfield      #29                 // Field tableName:Lorg/apache/hadoop/hbase/TableName;
      97: invokeinterface #65,  2           // InterfaceMethod org/apache/hadoop/hbase/client/AsyncAdmin.getRegions:(Lorg/apache/hadoop/hbase/TableName;)Ljava/util/concurrent/CompletableFuture;
     102: invokevirtual #16                 // Method java/util/concurrent/CompletableFuture.get:()Ljava/lang/Object;
     105: checkcast     #17                 // class java/util/List
     108: astore_2
     109: ldc2_w        #66                 // long 3l
     112: aload_1
     113: invokeinterface #44,  1           // InterfaceMethod java/util/List.size:()I
     118: i2l
     119: invokestatic  #45                 // Method org/junit/Assert.assertEquals:(JJ)V
     122: iconst_0
     123: istore_3
     124: iload_3
     125: iconst_3
     126: if_icmpge     174
     129: aload_2
     130: iload_3
     131: invokeinterface #19,  2           // InterfaceMethod java/util/List.get:(I)Ljava/lang/Object;
     136: checkcast     #55                 // class org/apache/hadoop/hbase/client/RegionInfo
     139: astore        4
     141: aload_0
     142: getfield      #29                 // Field tableName:Lorg/apache/hadoop/hbase/TableName;
     145: aload         4
     147: invokeinterface #68,  1           // InterfaceMethod org/apache/hadoop/hbase/client/RegionInfo.getTable:()Lorg/apache/hadoop/hbase/TableName;
     152: invokestatic  #69                 // Method org/junit/Assert.assertEquals:(Ljava/lang/Object;Ljava/lang/Object;)V
     155: iload_3
     156: i2l
     157: aload         4
     159: invokeinterface #70,  1           // InterfaceMethod org/apache/hadoop/hbase/client/RegionInfo.getReplicaId:()I
     164: i2l
     165: invokestatic  #45                 // Method org/junit/Assert.assertEquals:(JJ)V
     168: iinc          3, 1
     171: goto          124
     174: return

  static {};
    Code:
       0: ldc           #71                 // class org/apache/hadoop/hbase/client/TestAsyncAdminWithRegionReplicas
       2: invokestatic  #72                 // Method org/apache/hadoop/hbase/HBaseClassTestRule.forClass:(Ljava/lang/Class;)Lorg/apache/hadoop/hbase/HBaseClassTestRule;
       5: putstatic     #73                 // Field CLASS_RULE:Lorg/apache/hadoop/hbase/HBaseClassTestRule;
       8: return
}
