Compiled from "TestLruBlockCache.java"
public class org.apache.hadoop.hbase.io.hfile.TestLruBlockCache {
  public static final org.apache.hadoop.hbase.HBaseClassTestRule CLASS_RULE;

  public org.apache.hadoop.hbase.io.hfile.TestLruBlockCache();
    Code:
       0: aload_0
       1: invokespecial #1                  // Method java/lang/Object."<init>":()V
       4: return

  public void testCacheEvictionThreadSafe() throws java.lang.Exception;
    Code:
       0: ldc2_w        #2                  // long 100000l
       3: lstore_1
       4: bipush        9
       6: istore_3
       7: bipush        10
       9: istore        4
      11: aload_0
      12: lload_1
      13: iload_3
      14: invokespecial #4                  // Method calculateBlockSizeDefault:(JI)J
      17: lstore        5
      19: ldc           #5                  // String calculateBlockSize appears broken.
      21: lload         5
      23: iload_3
      24: i2l
      25: lmul
      26: lload_1
      27: lcmp
      28: ifgt          35
      31: iconst_1
      32: goto          36
      35: iconst_0
      36: invokestatic  #6                  // Method org/junit/Assert.assertTrue:(Ljava/lang/String;Z)V
      39: invokestatic  #7                  // Method org/apache/hadoop/hbase/HBaseConfiguration.create:()Lorg/apache/hadoop/conf/Configuration;
      42: astore        7
      44: new           #8                  // class org/apache/hadoop/hbase/io/hfile/LruBlockCache
      47: dup
      48: lload_1
      49: lload         5
      51: invokespecial #9                  // Method org/apache/hadoop/hbase/io/hfile/LruBlockCache."<init>":(JJ)V
      54: astore        8
      56: aload         8
      58: invokevirtual #10                 // Method org/apache/hadoop/hbase/io/hfile/LruBlockCache.getEvictionThread:()Lorg/apache/hadoop/hbase/io/hfile/LruBlockCache$EvictionThread;
      61: astore        9
      63: aload         9
      65: ifnull        72
      68: iconst_1
      69: goto          73
      72: iconst_0
      73: invokestatic  #11                 // Method org/junit/Assert.assertTrue:(Z)V
      76: aload         9
      78: invokevirtual #12                 // Method org/apache/hadoop/hbase/io/hfile/LruBlockCache$EvictionThread.isEnteringRun:()Z
      81: ifne          91
      84: lconst_1
      85: invokestatic  #13                 // Method java/lang/Thread.sleep:(J)V
      88: goto          76
      91: ldc           #14                 // String hfile
      93: astore        10
      95: bipush        10
      97: istore        11
      99: iconst_5
     100: iload_3
     101: imul
     102: istore        12
     104: iconst_0
     105: istore        13
     107: iload         13
     109: iload         4
     111: if_icmpeq     241
     114: new           #15                 // class java/util/concurrent/atomic/AtomicInteger
     117: dup
     118: iconst_0
     119: invokespecial #16                 // Method java/util/concurrent/atomic/AtomicInteger."<init>":(I)V
     122: astore        14
     124: iload         11
     126: invokestatic  #17                 // Method java/util/concurrent/Executors.newFixedThreadPool:(I)Ljava/util/concurrent/ExecutorService;
     129: astore        15
     131: iconst_0
     132: istore        16
     134: iload         16
     136: iload         11
     138: if_icmpeq     170
     141: aload         15
     143: new           #18                 // class org/apache/hadoop/hbase/io/hfile/TestLruBlockCache$1
     146: dup
     147: aload_0
     148: iload         12
     150: aload         8
     152: lload         5
     154: aload         14
     156: invokespecial #19                 // Method org/apache/hadoop/hbase/io/hfile/TestLruBlockCache$1."<init>":(Lorg/apache/hadoop/hbase/io/hfile/TestLruBlockCache;ILorg/apache/hadoop/hbase/io/hfile/LruBlockCache;JLjava/util/concurrent/atomic/AtomicInteger;)V
     159: invokeinterface #20,  2           // InterfaceMethod java/util/concurrent/ExecutorService.execute:(Ljava/lang/Runnable;)V
     164: iinc          16, 1
     167: goto          134
     170: aload         15
     172: invokeinterface #21,  1           // InterfaceMethod java/util/concurrent/ExecutorService.shutdown:()V
     177: aload         15
     179: ldc2_w        #22                 // long 10l
     182: getstatic     #24                 // Field java/util/concurrent/TimeUnit.MINUTES:Ljava/util/concurrent/TimeUnit;
     185: invokeinterface #25,  4           // InterfaceMethod java/util/concurrent/ExecutorService.awaitTermination:(JLjava/util/concurrent/TimeUnit;)Z
     190: pop
     191: aload         7
     193: ldc2_w        #26                 // long 10000l
     196: ldc2_w        #28                 // long 100l
     199: new           #30                 // class org/apache/hadoop/hbase/io/hfile/TestLruBlockCache$2
     202: dup
     203: aload_0
     204: aload         8
     206: invokespecial #31                 // Method org/apache/hadoop/hbase/io/hfile/TestLruBlockCache$2."<init>":(Lorg/apache/hadoop/hbase/io/hfile/TestLruBlockCache;Lorg/apache/hadoop/hbase/io/hfile/LruBlockCache;)V
     209: invokestatic  #32                 // Method org/apache/hadoop/hbase/Waiter.waitFor:(Lorg/apache/hadoop/conf/Configuration;JJLorg/apache/hadoop/hbase/Waiter$Predicate;)J
     212: pop2
     213: lconst_0
     214: aload         8
     216: invokevirtual #33                 // Method org/apache/hadoop/hbase/io/hfile/LruBlockCache.getBlockCount:()J
     219: invokestatic  #34                 // Method org/junit/Assert.assertEquals:(JJ)V
     222: aload         8
     224: invokevirtual #35                 // Method org/apache/hadoop/hbase/io/hfile/LruBlockCache.getOverhead:()J
     227: aload         8
     229: invokevirtual #36                 // Method org/apache/hadoop/hbase/io/hfile/LruBlockCache.getCurrentSize:()J
     232: invokestatic  #34                 // Method org/junit/Assert.assertEquals:(JJ)V
     235: iinc          13, 1
     238: goto          107
     241: return

  public void testBackgroundEvictionThread() throws java.lang.Exception;
    Code:
       0: ldc2_w        #2                  // long 100000l
       3: lstore_1
       4: bipush        9
       6: istore_3
       7: aload_0
       8: lload_1
       9: iload_3
      10: invokespecial #4                  // Method calculateBlockSizeDefault:(JI)J
      13: lstore        4
      15: ldc           #5                  // String calculateBlockSize appears broken.
      17: lload         4
      19: iload_3
      20: i2l
      21: lmul
      22: lload_1
      23: lcmp
      24: ifgt          31
      27: iconst_1
      28: goto          32
      31: iconst_0
      32: invokestatic  #6                  // Method org/junit/Assert.assertTrue:(Ljava/lang/String;Z)V
      35: new           #8                  // class org/apache/hadoop/hbase/io/hfile/LruBlockCache
      38: dup
      39: lload_1
      40: lload         4
      42: invokespecial #9                  // Method org/apache/hadoop/hbase/io/hfile/LruBlockCache."<init>":(JJ)V
      45: astore        6
      47: aload         6
      49: invokevirtual #10                 // Method org/apache/hadoop/hbase/io/hfile/LruBlockCache.getEvictionThread:()Lorg/apache/hadoop/hbase/io/hfile/LruBlockCache$EvictionThread;
      52: astore        7
      54: aload         7
      56: ifnull        63
      59: iconst_1
      60: goto          64
      63: iconst_0
      64: invokestatic  #11                 // Method org/junit/Assert.assertTrue:(Z)V
      67: aload_0
      68: iload_3
      69: iconst_1
      70: iadd
      71: lload         4
      73: ldc           #37                 // String block
      75: invokespecial #38                 // Method generateFixedBlocks:(IJLjava/lang/String;)[Lorg/apache/hadoop/hbase/io/hfile/TestLruBlockCache$CachedItem;
      78: astore        8
      80: aload         7
      82: invokevirtual #12                 // Method org/apache/hadoop/hbase/io/hfile/LruBlockCache$EvictionThread.isEnteringRun:()Z
      85: ifne          95
      88: lconst_1
      89: invokestatic  #13                 // Method java/lang/Thread.sleep:(J)V
      92: goto          80
      95: aload         8
      97: astore        9
      99: aload         9
     101: arraylength
     102: istore        10
     104: iconst_0
     105: istore        11
     107: iload         11
     109: iload         10
     111: if_icmpge     139
     114: aload         9
     116: iload         11
     118: aaload
     119: astore        12
     121: aload         6
     123: aload         12
     125: getfield      #39                 // Field org/apache/hadoop/hbase/io/hfile/TestLruBlockCache$CachedItem.cacheKey:Lorg/apache/hadoop/hbase/io/hfile/BlockCacheKey;
     128: aload         12
     130: invokevirtual #40                 // Method org/apache/hadoop/hbase/io/hfile/LruBlockCache.cacheBlock:(Lorg/apache/hadoop/hbase/io/hfile/BlockCacheKey;Lorg/apache/hadoop/hbase/io/hfile/Cacheable;)V
     133: iinc          11, 1
     136: goto          107
     139: iconst_0
     140: istore        9
     142: aload         6
     144: invokevirtual #41                 // Method org/apache/hadoop/hbase/io/hfile/LruBlockCache.getStats:()Lorg/apache/hadoop/hbase/io/hfile/CacheStats;
     147: invokevirtual #42                 // Method org/apache/hadoop/hbase/io/hfile/CacheStats.getEvictionCount:()J
     150: lconst_0
     151: lcmp
     152: ifne          184
     155: ldc2_w        #43                 // long 200l
     158: invokestatic  #13                 // Method java/lang/Thread.sleep:(J)V
     161: ldc           #45                 // String Eviction never happened.
     163: iload         9
     165: iinc          9, 1
     168: bipush        20
     170: if_icmpge     177
     173: iconst_1
     174: goto          178
     177: iconst_0
     178: invokestatic  #6                  // Method org/junit/Assert.assertTrue:(Ljava/lang/String;Z)V
     181: goto          142
     184: iconst_0
     185: istore        9
     187: lconst_0
     188: lstore        10
     190: aload         6
     192: invokevirtual #33                 // Method org/apache/hadoop/hbase/io/hfile/LruBlockCache.getBlockCount:()J
     195: lstore        12
     197: lload         10
     199: lload         12
     201: lcmp
     202: ifeq          245
     205: ldc2_w        #43                 // long 200l
     208: invokestatic  #13                 // Method java/lang/Thread.sleep:(J)V
     211: ldc           #46                 // String Cache never stabilized.
     213: iload         9
     215: iinc          9, 1
     218: bipush        20
     220: if_icmpge     227
     223: iconst_1
     224: goto          228
     227: iconst_0
     228: invokestatic  #6                  // Method org/junit/Assert.assertTrue:(Ljava/lang/String;Z)V
     231: lload         12
     233: lstore        10
     235: aload         6
     237: invokevirtual #33                 // Method org/apache/hadoop/hbase/io/hfile/LruBlockCache.getBlockCount:()J
     240: lstore        12
     242: goto          197
     245: aload         6
     247: invokevirtual #41                 // Method org/apache/hadoop/hbase/io/hfile/LruBlockCache.getStats:()Lorg/apache/hadoop/hbase/io/hfile/CacheStats;
     250: invokevirtual #42                 // Method org/apache/hadoop/hbase/io/hfile/CacheStats.getEvictionCount:()J
     253: lstore        10
     255: lload         10
     257: lconst_1
     258: lcmp
     259: iflt          266
     262: iconst_1
     263: goto          267
     266: iconst_0
     267: invokestatic  #11                 // Method org/junit/Assert.assertTrue:(Z)V
     270: getstatic     #47                 // Field java/lang/System.out:Ljava/io/PrintStream;
     273: new           #48                 // class java/lang/StringBuilder
     276: dup
     277: invokespecial #49                 // Method java/lang/StringBuilder."<init>":()V
     280: ldc           #50                 // String Background Evictions run:
     282: invokevirtual #51                 // Method java/lang/StringBuilder.append:(Ljava/lang/String;)Ljava/lang/StringBuilder;
     285: lload         10
     287: invokevirtual #52                 // Method java/lang/StringBuilder.append:(J)Ljava/lang/StringBuilder;
     290: invokevirtual #53                 // Method java/lang/StringBuilder.toString:()Ljava/lang/String;
     293: invokevirtual #54                 // Method java/io/PrintStream.println:(Ljava/lang/String;)V
     296: return

  public void testCacheSimple() throws java.lang.Exception;
    Code:
       0: ldc2_w        #55                 // long 1000000l
       3: lstore_1
       4: aload_0
       5: lload_1
       6: bipush        101
       8: invokespecial #4                  // Method calculateBlockSizeDefault:(JI)J
      11: lstore_3
      12: new           #8                  // class org/apache/hadoop/hbase/io/hfile/LruBlockCache
      15: dup
      16: lload_1
      17: lload_3
      18: invokespecial #9                  // Method org/apache/hadoop/hbase/io/hfile/LruBlockCache."<init>":(JJ)V
      21: astore        5
      23: aload_0
      24: bipush        100
      26: lload_3
      27: invokespecial #57                 // Method generateRandomBlocks:(IJ)[Lorg/apache/hadoop/hbase/io/hfile/TestLruBlockCache$CachedItem;
      30: astore        6
      32: aload         5
      34: invokevirtual #58                 // Method org/apache/hadoop/hbase/io/hfile/LruBlockCache.heapSize:()J
      37: lstore        7
      39: aload         6
      41: astore        9
      43: aload         9
      45: arraylength
      46: istore        10
      48: iconst_0
      49: istore        11
      51: iload         11
      53: iload         10
      55: if_icmpge     95
      58: aload         9
      60: iload         11
      62: aaload
      63: astore        12
      65: aload         5
      67: aload         12
      69: getfield      #39                 // Field org/apache/hadoop/hbase/io/hfile/TestLruBlockCache$CachedItem.cacheKey:Lorg/apache/hadoop/hbase/io/hfile/BlockCacheKey;
      72: iconst_1
      73: iconst_0
      74: iconst_1
      75: invokevirtual #59                 // Method org/apache/hadoop/hbase/io/hfile/LruBlockCache.getBlock:(Lorg/apache/hadoop/hbase/io/hfile/BlockCacheKey;ZZZ)Lorg/apache/hadoop/hbase/io/hfile/Cacheable;
      78: ifnonnull     85
      81: iconst_1
      82: goto          86
      85: iconst_0
      86: invokestatic  #11                 // Method org/junit/Assert.assertTrue:(Z)V
      89: iinc          11, 1
      92: goto          51
      95: aload         6
      97: astore        9
      99: aload         9
     101: arraylength
     102: istore        10
     104: iconst_0
     105: istore        11
     107: iload         11
     109: iload         10
     111: if_icmpge     149
     114: aload         9
     116: iload         11
     118: aaload
     119: astore        12
     121: aload         5
     123: aload         12
     125: getfield      #39                 // Field org/apache/hadoop/hbase/io/hfile/TestLruBlockCache$CachedItem.cacheKey:Lorg/apache/hadoop/hbase/io/hfile/BlockCacheKey;
     128: aload         12
     130: invokevirtual #40                 // Method org/apache/hadoop/hbase/io/hfile/LruBlockCache.cacheBlock:(Lorg/apache/hadoop/hbase/io/hfile/BlockCacheKey;Lorg/apache/hadoop/hbase/io/hfile/Cacheable;)V
     133: lload         7
     135: aload         12
     137: invokevirtual #60                 // Method org/apache/hadoop/hbase/io/hfile/TestLruBlockCache$CachedItem.cacheBlockHeapSize:()J
     140: ladd
     141: lstore        7
     143: iinc          11, 1
     146: goto          107
     149: lload         7
     151: aload         5
     153: invokevirtual #58                 // Method org/apache/hadoop/hbase/io/hfile/LruBlockCache.heapSize:()J
     156: invokestatic  #34                 // Method org/junit/Assert.assertEquals:(JJ)V
     159: aload         6
     161: astore        9
     163: aload         9
     165: arraylength
     166: istore        10
     168: iconst_0
     169: istore        11
     171: iload         11
     173: iload         10
     175: if_icmpge     234
     178: aload         9
     180: iload         11
     182: aaload
     183: astore        12
     185: aload         5
     187: aload         12
     189: getfield      #39                 // Field org/apache/hadoop/hbase/io/hfile/TestLruBlockCache$CachedItem.cacheKey:Lorg/apache/hadoop/hbase/io/hfile/BlockCacheKey;
     192: iconst_1
     193: iconst_0
     194: iconst_1
     195: invokevirtual #59                 // Method org/apache/hadoop/hbase/io/hfile/LruBlockCache.getBlock:(Lorg/apache/hadoop/hbase/io/hfile/BlockCacheKey;ZZZ)Lorg/apache/hadoop/hbase/io/hfile/Cacheable;
     198: astore        13
     200: aload         13
     202: ifnull        209
     205: iconst_1
     206: goto          210
     209: iconst_0
     210: invokestatic  #11                 // Method org/junit/Assert.assertTrue:(Z)V
     213: aload         13
     215: invokeinterface #61,  1           // InterfaceMethod org/apache/hadoop/hbase/io/HeapSize.heapSize:()J
     220: aload         12
     222: invokevirtual #62                 // Method org/apache/hadoop/hbase/io/hfile/TestLruBlockCache$CachedItem.heapSize:()J
     225: invokestatic  #34                 // Method org/junit/Assert.assertEquals:(JJ)V
     228: iinc          11, 1
     231: goto          171
     234: aload         5
     236: invokevirtual #33                 // Method org/apache/hadoop/hbase/io/hfile/LruBlockCache.getBlockCount:()J
     239: lstore        9
     241: aload         6
     243: astore        11
     245: aload         11
     247: arraylength
     248: istore        12
     250: iconst_0
     251: istore        13
     253: iload         13
     255: iload         12
     257: if_icmpge     285
     260: aload         11
     262: iload         13
     264: aaload
     265: astore        14
     267: aload         5
     269: aload         14
     271: getfield      #39                 // Field org/apache/hadoop/hbase/io/hfile/TestLruBlockCache$CachedItem.cacheKey:Lorg/apache/hadoop/hbase/io/hfile/BlockCacheKey;
     274: aload         14
     276: invokevirtual #40                 // Method org/apache/hadoop/hbase/io/hfile/LruBlockCache.cacheBlock:(Lorg/apache/hadoop/hbase/io/hfile/BlockCacheKey;Lorg/apache/hadoop/hbase/io/hfile/Cacheable;)V
     279: iinc          13, 1
     282: goto          253
     285: ldc           #63                 // String Cache should ignore cache requests for blocks already in cache
     287: lload         9
     289: aload         5
     291: invokevirtual #33                 // Method org/apache/hadoop/hbase/io/hfile/LruBlockCache.getBlockCount:()J
     294: invokestatic  #64                 // Method org/junit/Assert.assertEquals:(Ljava/lang/String;JJ)V
     297: lload         7
     299: aload         5
     301: invokevirtual #58                 // Method org/apache/hadoop/hbase/io/hfile/LruBlockCache.heapSize:()J
     304: invokestatic  #34                 // Method org/junit/Assert.assertEquals:(JJ)V
     307: aload         6
     309: astore        11
     311: aload         11
     313: arraylength
     314: istore        12
     316: iconst_0
     317: istore        13
     319: iload         13
     321: iload         12
     323: if_icmpge     382
     326: aload         11
     328: iload         13
     330: aaload
     331: astore        14
     333: aload         5
     335: aload         14
     337: getfield      #39                 // Field org/apache/hadoop/hbase/io/hfile/TestLruBlockCache$CachedItem.cacheKey:Lorg/apache/hadoop/hbase/io/hfile/BlockCacheKey;
     340: iconst_1
     341: iconst_0
     342: iconst_1
     343: invokevirtual #59                 // Method org/apache/hadoop/hbase/io/hfile/LruBlockCache.getBlock:(Lorg/apache/hadoop/hbase/io/hfile/BlockCacheKey;ZZZ)Lorg/apache/hadoop/hbase/io/hfile/Cacheable;
     346: astore        15
     348: aload         15
     350: ifnull        357
     353: iconst_1
     354: goto          358
     357: iconst_0
     358: invokestatic  #11                 // Method org/junit/Assert.assertTrue:(Z)V
     361: aload         15
     363: invokeinterface #61,  1           // InterfaceMethod org/apache/hadoop/hbase/io/HeapSize.heapSize:()J
     368: aload         14
     370: invokevirtual #62                 // Method org/apache/hadoop/hbase/io/hfile/TestLruBlockCache$CachedItem.heapSize:()J
     373: invokestatic  #34                 // Method org/junit/Assert.assertEquals:(JJ)V
     376: iinc          13, 1
     379: goto          319
     382: lconst_0
     383: aload         5
     385: invokevirtual #41                 // Method org/apache/hadoop/hbase/io/hfile/LruBlockCache.getStats:()Lorg/apache/hadoop/hbase/io/hfile/CacheStats;
     388: invokevirtual #42                 // Method org/apache/hadoop/hbase/io/hfile/CacheStats.getEvictionCount:()J
     391: invokestatic  #34                 // Method org/junit/Assert.assertEquals:(JJ)V
     394: new           #65                 // class org/apache/hadoop/hbase/io/hfile/LruBlockCache$StatisticsThread
     397: dup
     398: aload         5
     400: invokespecial #66                 // Method org/apache/hadoop/hbase/io/hfile/LruBlockCache$StatisticsThread."<init>":(Lorg/apache/hadoop/hbase/io/hfile/LruBlockCache;)V
     403: astore        11
     405: aload         11
     407: invokevirtual #67                 // Method java/lang/Thread.start:()V
     410: aload         11
     412: invokevirtual #68                 // Method java/lang/Thread.join:()V
     415: return

  public void testCacheEvictionSimple() throws java.lang.Exception;
    Code:
       0: ldc2_w        #2                  // long 100000l
       3: lstore_1
       4: aload_0
       5: lload_1
       6: bipush        10
       8: invokespecial #4                  // Method calculateBlockSizeDefault:(JI)J
      11: lstore_3
      12: new           #8                  // class org/apache/hadoop/hbase/io/hfile/LruBlockCache
      15: dup
      16: lload_1
      17: lload_3
      18: iconst_0
      19: invokespecial #69                 // Method org/apache/hadoop/hbase/io/hfile/LruBlockCache."<init>":(JJZ)V
      22: astore        5
      24: aload_0
      25: bipush        10
      27: lload_3
      28: ldc           #37                 // String block
      30: invokespecial #38                 // Method generateFixedBlocks:(IJLjava/lang/String;)[Lorg/apache/hadoop/hbase/io/hfile/TestLruBlockCache$CachedItem;
      33: astore        6
      35: aload         5
      37: invokevirtual #58                 // Method org/apache/hadoop/hbase/io/hfile/LruBlockCache.heapSize:()J
      40: lstore        7
      42: aload         6
      44: astore        9
      46: aload         9
      48: arraylength
      49: istore        10
      51: iconst_0
      52: istore        11
      54: iload         11
      56: iload         10
      58: if_icmpge     96
      61: aload         9
      63: iload         11
      65: aaload
      66: astore        12
      68: aload         5
      70: aload         12
      72: getfield      #39                 // Field org/apache/hadoop/hbase/io/hfile/TestLruBlockCache$CachedItem.cacheKey:Lorg/apache/hadoop/hbase/io/hfile/BlockCacheKey;
      75: aload         12
      77: invokevirtual #40                 // Method org/apache/hadoop/hbase/io/hfile/LruBlockCache.cacheBlock:(Lorg/apache/hadoop/hbase/io/hfile/BlockCacheKey;Lorg/apache/hadoop/hbase/io/hfile/Cacheable;)V
      80: lload         7
      82: aload         12
      84: invokevirtual #60                 // Method org/apache/hadoop/hbase/io/hfile/TestLruBlockCache$CachedItem.cacheBlockHeapSize:()J
      87: ladd
      88: lstore        7
      90: iinc          11, 1
      93: goto          54
      96: lconst_1
      97: aload         5
      99: invokevirtual #41                 // Method org/apache/hadoop/hbase/io/hfile/LruBlockCache.getStats:()Lorg/apache/hadoop/hbase/io/hfile/CacheStats;
     102: invokevirtual #42                 // Method org/apache/hadoop/hbase/io/hfile/CacheStats.getEvictionCount:()J
     105: invokestatic  #34                 // Method org/junit/Assert.assertEquals:(JJ)V
     108: lload         7
     110: l2f
     111: lload_1
     112: l2f
     113: ldc           #70                 // float 0.99f
     115: fmul
     116: fcmpl
     117: ifle          124
     120: iconst_1
     121: goto          125
     124: iconst_0
     125: invokestatic  #11                 // Method org/junit/Assert.assertTrue:(Z)V
     128: aload         5
     130: invokevirtual #58                 // Method org/apache/hadoop/hbase/io/hfile/LruBlockCache.heapSize:()J
     133: lload_1
     134: lcmp
     135: ifge          142
     138: iconst_1
     139: goto          143
     142: iconst_0
     143: invokestatic  #11                 // Method org/junit/Assert.assertTrue:(Z)V
     146: aload         5
     148: invokevirtual #58                 // Method org/apache/hadoop/hbase/io/hfile/LruBlockCache.heapSize:()J
     151: l2f
     152: lload_1
     153: l2f
     154: ldc           #70                 // float 0.99f
     156: fmul
     157: fcmpg
     158: ifge          165
     161: iconst_1
     162: goto          166
     165: iconst_0
     166: invokestatic  #11                 // Method org/junit/Assert.assertTrue:(Z)V
     169: aload         5
     171: aload         6
     173: iconst_0
     174: aaload
     175: getfield      #39                 // Field org/apache/hadoop/hbase/io/hfile/TestLruBlockCache$CachedItem.cacheKey:Lorg/apache/hadoop/hbase/io/hfile/BlockCacheKey;
     178: iconst_1
     179: iconst_0
     180: iconst_1
     181: invokevirtual #59                 // Method org/apache/hadoop/hbase/io/hfile/LruBlockCache.getBlock:(Lorg/apache/hadoop/hbase/io/hfile/BlockCacheKey;ZZZ)Lorg/apache/hadoop/hbase/io/hfile/Cacheable;
     184: ifnonnull     191
     187: iconst_1
     188: goto          192
     191: iconst_0
     192: invokestatic  #11                 // Method org/junit/Assert.assertTrue:(Z)V
     195: iconst_1
     196: istore        9
     198: iload         9
     200: aload         6
     202: arraylength
     203: if_icmpge     236
     206: aload         5
     208: aload         6
     210: iload         9
     212: aaload
     213: getfield      #39                 // Field org/apache/hadoop/hbase/io/hfile/TestLruBlockCache$CachedItem.cacheKey:Lorg/apache/hadoop/hbase/io/hfile/BlockCacheKey;
     216: iconst_1
     217: iconst_0
     218: iconst_1
     219: invokevirtual #59                 // Method org/apache/hadoop/hbase/io/hfile/LruBlockCache.getBlock:(Lorg/apache/hadoop/hbase/io/hfile/BlockCacheKey;ZZZ)Lorg/apache/hadoop/hbase/io/hfile/Cacheable;
     222: aload         6
     224: iload         9
     226: aaload
     227: invokestatic  #71                 // Method org/junit/Assert.assertEquals:(Ljava/lang/Object;Ljava/lang/Object;)V
     230: iinc          9, 1
     233: goto          198
     236: return

  public void testCacheEvictionTwoPriorities() throws java.lang.Exception;
    Code:
       0: ldc2_w        #2                  // long 100000l
       3: lstore_1
       4: aload_0
       5: lload_1
       6: bipush        10
       8: invokespecial #4                  // Method calculateBlockSizeDefault:(JI)J
      11: lstore_3
      12: new           #8                  // class org/apache/hadoop/hbase/io/hfile/LruBlockCache
      15: dup
      16: lload_1
      17: lload_3
      18: iconst_0
      19: invokespecial #69                 // Method org/apache/hadoop/hbase/io/hfile/LruBlockCache."<init>":(JJZ)V
      22: astore        5
      24: aload_0
      25: iconst_5
      26: sipush        10000
      29: ldc           #72                 // String single
      31: invokespecial #73                 // Method generateFixedBlocks:(IILjava/lang/String;)[Lorg/apache/hadoop/hbase/io/hfile/TestLruBlockCache$CachedItem;
      34: astore        6
      36: aload_0
      37: iconst_5
      38: sipush        10000
      41: ldc           #74                 // String multi
      43: invokespecial #73                 // Method generateFixedBlocks:(IILjava/lang/String;)[Lorg/apache/hadoop/hbase/io/hfile/TestLruBlockCache$CachedItem;
      46: astore        7
      48: aload         5
      50: invokevirtual #58                 // Method org/apache/hadoop/hbase/io/hfile/LruBlockCache.heapSize:()J
      53: lstore        8
      55: aload         7
      57: astore        10
      59: aload         10
      61: arraylength
      62: istore        11
      64: iconst_0
      65: istore        12
      67: iload         12
      69: iload         11
      71: if_icmpge     127
      74: aload         10
      76: iload         12
      78: aaload
      79: astore        13
      81: aload         5
      83: aload         13
      85: getfield      #39                 // Field org/apache/hadoop/hbase/io/hfile/TestLruBlockCache$CachedItem.cacheKey:Lorg/apache/hadoop/hbase/io/hfile/BlockCacheKey;
      88: aload         13
      90: invokevirtual #40                 // Method org/apache/hadoop/hbase/io/hfile/LruBlockCache.cacheBlock:(Lorg/apache/hadoop/hbase/io/hfile/BlockCacheKey;Lorg/apache/hadoop/hbase/io/hfile/Cacheable;)V
      93: lload         8
      95: aload         13
      97: invokevirtual #60                 // Method org/apache/hadoop/hbase/io/hfile/TestLruBlockCache$CachedItem.cacheBlockHeapSize:()J
     100: ladd
     101: lstore        8
     103: aload         5
     105: aload         13
     107: getfield      #39                 // Field org/apache/hadoop/hbase/io/hfile/TestLruBlockCache$CachedItem.cacheKey:Lorg/apache/hadoop/hbase/io/hfile/BlockCacheKey;
     110: iconst_1
     111: iconst_0
     112: iconst_1
     113: invokevirtual #59                 // Method org/apache/hadoop/hbase/io/hfile/LruBlockCache.getBlock:(Lorg/apache/hadoop/hbase/io/hfile/BlockCacheKey;ZZZ)Lorg/apache/hadoop/hbase/io/hfile/Cacheable;
     116: aload         13
     118: invokestatic  #71                 // Method org/junit/Assert.assertEquals:(Ljava/lang/Object;Ljava/lang/Object;)V
     121: iinc          12, 1
     124: goto          67
     127: aload         6
     129: astore        10
     131: aload         10
     133: arraylength
     134: istore        11
     136: iconst_0
     137: istore        12
     139: iload         12
     141: iload         11
     143: if_icmpge     181
     146: aload         10
     148: iload         12
     150: aaload
     151: astore        13
     153: aload         5
     155: aload         13
     157: getfield      #39                 // Field org/apache/hadoop/hbase/io/hfile/TestLruBlockCache$CachedItem.cacheKey:Lorg/apache/hadoop/hbase/io/hfile/BlockCacheKey;
     160: aload         13
     162: invokevirtual #40                 // Method org/apache/hadoop/hbase/io/hfile/LruBlockCache.cacheBlock:(Lorg/apache/hadoop/hbase/io/hfile/BlockCacheKey;Lorg/apache/hadoop/hbase/io/hfile/Cacheable;)V
     165: lload         8
     167: aload         13
     169: invokevirtual #62                 // Method org/apache/hadoop/hbase/io/hfile/TestLruBlockCache$CachedItem.heapSize:()J
     172: ladd
     173: lstore        8
     175: iinc          12, 1
     178: goto          139
     181: lconst_1
     182: aload         5
     184: invokevirtual #41                 // Method org/apache/hadoop/hbase/io/hfile/LruBlockCache.getStats:()Lorg/apache/hadoop/hbase/io/hfile/CacheStats;
     187: invokevirtual #42                 // Method org/apache/hadoop/hbase/io/hfile/CacheStats.getEvictionCount:()J
     190: invokestatic  #34                 // Method org/junit/Assert.assertEquals:(JJ)V
     193: ldc2_w        #75                 // long 2l
     196: aload         5
     198: invokevirtual #41                 // Method org/apache/hadoop/hbase/io/hfile/LruBlockCache.getStats:()Lorg/apache/hadoop/hbase/io/hfile/CacheStats;
     201: invokevirtual #77                 // Method org/apache/hadoop/hbase/io/hfile/CacheStats.getEvictedCount:()J
     204: invokestatic  #34                 // Method org/junit/Assert.assertEquals:(JJ)V
     207: lload         8
     209: l2f
     210: lload_1
     211: l2f
     212: ldc           #70                 // float 0.99f
     214: fmul
     215: fcmpl
     216: ifle          223
     219: iconst_1
     220: goto          224
     223: iconst_0
     224: invokestatic  #11                 // Method org/junit/Assert.assertTrue:(Z)V
     227: aload         5
     229: invokevirtual #58                 // Method org/apache/hadoop/hbase/io/hfile/LruBlockCache.heapSize:()J
     232: lload_1
     233: lcmp
     234: ifgt          241
     237: iconst_1
     238: goto          242
     241: iconst_0
     242: invokestatic  #11                 // Method org/junit/Assert.assertTrue:(Z)V
     245: aload         5
     247: invokevirtual #58                 // Method org/apache/hadoop/hbase/io/hfile/LruBlockCache.heapSize:()J
     250: l2f
     251: lload_1
     252: l2f
     253: ldc           #70                 // float 0.99f
     255: fmul
     256: fcmpg
     257: ifgt          264
     260: iconst_1
     261: goto          265
     264: iconst_0
     265: invokestatic  #11                 // Method org/junit/Assert.assertTrue:(Z)V
     268: aload         5
     270: aload         6
     272: iconst_0
     273: aaload
     274: getfield      #39                 // Field org/apache/hadoop/hbase/io/hfile/TestLruBlockCache$CachedItem.cacheKey:Lorg/apache/hadoop/hbase/io/hfile/BlockCacheKey;
     277: iconst_1
     278: iconst_0
     279: iconst_1
     280: invokevirtual #59                 // Method org/apache/hadoop/hbase/io/hfile/LruBlockCache.getBlock:(Lorg/apache/hadoop/hbase/io/hfile/BlockCacheKey;ZZZ)Lorg/apache/hadoop/hbase/io/hfile/Cacheable;
     283: ifnonnull     290
     286: iconst_1
     287: goto          291
     290: iconst_0
     291: invokestatic  #11                 // Method org/junit/Assert.assertTrue:(Z)V
     294: aload         5
     296: aload         7
     298: iconst_0
     299: aaload
     300: getfield      #39                 // Field org/apache/hadoop/hbase/io/hfile/TestLruBlockCache$CachedItem.cacheKey:Lorg/apache/hadoop/hbase/io/hfile/BlockCacheKey;
     303: iconst_1
     304: iconst_0
     305: iconst_1
     306: invokevirtual #59                 // Method org/apache/hadoop/hbase/io/hfile/LruBlockCache.getBlock:(Lorg/apache/hadoop/hbase/io/hfile/BlockCacheKey;ZZZ)Lorg/apache/hadoop/hbase/io/hfile/Cacheable;
     309: ifnonnull     316
     312: iconst_1
     313: goto          317
     316: iconst_0
     317: invokestatic  #11                 // Method org/junit/Assert.assertTrue:(Z)V
     320: iconst_1
     321: istore        10
     323: iload         10
     325: iconst_4
     326: if_icmpge     383
     329: aload         5
     331: aload         6
     333: iload         10
     335: aaload
     336: getfield      #39                 // Field org/apache/hadoop/hbase/io/hfile/TestLruBlockCache$CachedItem.cacheKey:Lorg/apache/hadoop/hbase/io/hfile/BlockCacheKey;
     339: iconst_1
     340: iconst_0
     341: iconst_1
     342: invokevirtual #59                 // Method org/apache/hadoop/hbase/io/hfile/LruBlockCache.getBlock:(Lorg/apache/hadoop/hbase/io/hfile/BlockCacheKey;ZZZ)Lorg/apache/hadoop/hbase/io/hfile/Cacheable;
     345: aload         6
     347: iload         10
     349: aaload
     350: invokestatic  #71                 // Method org/junit/Assert.assertEquals:(Ljava/lang/Object;Ljava/lang/Object;)V
     353: aload         5
     355: aload         7
     357: iload         10
     359: aaload
     360: getfield      #39                 // Field org/apache/hadoop/hbase/io/hfile/TestLruBlockCache$CachedItem.cacheKey:Lorg/apache/hadoop/hbase/io/hfile/BlockCacheKey;
     363: iconst_1
     364: iconst_0
     365: iconst_1
     366: invokevirtual #59                 // Method org/apache/hadoop/hbase/io/hfile/LruBlockCache.getBlock:(Lorg/apache/hadoop/hbase/io/hfile/BlockCacheKey;ZZZ)Lorg/apache/hadoop/hbase/io/hfile/Cacheable;
     369: aload         7
     371: iload         10
     373: aaload
     374: invokestatic  #71                 // Method org/junit/Assert.assertEquals:(Ljava/lang/Object;Ljava/lang/Object;)V
     377: iinc          10, 1
     380: goto          323
     383: return

  public void testCacheEvictionThreePriorities() throws java.lang.Exception;
    Code:
       0: ldc2_w        #2                  // long 100000l
       3: lstore_1
       4: aload_0
       5: lload_1
       6: bipush        10
       8: invokespecial #78                 // Method calculateBlockSize:(JI)J
      11: lstore_3
      12: new           #8                  // class org/apache/hadoop/hbase/io/hfile/LruBlockCache
      15: dup
      16: lload_1
      17: lload_3
      18: iconst_0
      19: ldc2_w        #79                 // double 1.2d
      22: lload_1
      23: l2d
      24: dmul
      25: lload_3
      26: l2d
      27: ddiv
      28: invokestatic  #81                 // Method java/lang/Math.ceil:(D)D
      31: d2i
      32: ldc           #82                 // float 0.75f
      34: bipush        16
      36: ldc           #83                 // float 0.98f
      38: ldc           #70                 // float 0.99f
      40: ldc           #84                 // float 0.33f
      42: ldc           #84                 // float 0.33f
      44: ldc           #85                 // float 0.34f
      46: ldc           #86                 // float 1.2f
      48: iconst_0
      49: ldc2_w        #87                 // long 16777216l
      52: invokespecial #89                 // Method org/apache/hadoop/hbase/io/hfile/LruBlockCache."<init>":(JJZIFIFFFFFFZJ)V
      55: astore        5
      57: aload_0
      58: iconst_5
      59: lload_3
      60: ldc           #72                 // String single
      62: invokespecial #38                 // Method generateFixedBlocks:(IJLjava/lang/String;)[Lorg/apache/hadoop/hbase/io/hfile/TestLruBlockCache$CachedItem;
      65: astore        6
      67: aload_0
      68: iconst_5
      69: lload_3
      70: ldc           #74                 // String multi
      72: invokespecial #38                 // Method generateFixedBlocks:(IJLjava/lang/String;)[Lorg/apache/hadoop/hbase/io/hfile/TestLruBlockCache$CachedItem;
      75: astore        7
      77: aload_0
      78: iconst_5
      79: lload_3
      80: ldc           #90                 // String memory
      82: invokespecial #38                 // Method generateFixedBlocks:(IJLjava/lang/String;)[Lorg/apache/hadoop/hbase/io/hfile/TestLruBlockCache$CachedItem;
      85: astore        8
      87: aload         5
      89: invokevirtual #58                 // Method org/apache/hadoop/hbase/io/hfile/LruBlockCache.heapSize:()J
      92: lstore        9
      94: iconst_0
      95: istore        11
      97: iload         11
      99: iconst_3
     100: if_icmpge     220
     103: aload         5
     105: aload         6
     107: iload         11
     109: aaload
     110: getfield      #39                 // Field org/apache/hadoop/hbase/io/hfile/TestLruBlockCache$CachedItem.cacheKey:Lorg/apache/hadoop/hbase/io/hfile/BlockCacheKey;
     113: aload         6
     115: iload         11
     117: aaload
     118: invokevirtual #40                 // Method org/apache/hadoop/hbase/io/hfile/LruBlockCache.cacheBlock:(Lorg/apache/hadoop/hbase/io/hfile/BlockCacheKey;Lorg/apache/hadoop/hbase/io/hfile/Cacheable;)V
     121: lload         9
     123: aload         6
     125: iload         11
     127: aaload
     128: invokevirtual #60                 // Method org/apache/hadoop/hbase/io/hfile/TestLruBlockCache$CachedItem.cacheBlockHeapSize:()J
     131: ladd
     132: lstore        9
     134: aload         5
     136: aload         7
     138: iload         11
     140: aaload
     141: getfield      #39                 // Field org/apache/hadoop/hbase/io/hfile/TestLruBlockCache$CachedItem.cacheKey:Lorg/apache/hadoop/hbase/io/hfile/BlockCacheKey;
     144: aload         7
     146: iload         11
     148: aaload
     149: invokevirtual #40                 // Method org/apache/hadoop/hbase/io/hfile/LruBlockCache.cacheBlock:(Lorg/apache/hadoop/hbase/io/hfile/BlockCacheKey;Lorg/apache/hadoop/hbase/io/hfile/Cacheable;)V
     152: lload         9
     154: aload         7
     156: iload         11
     158: aaload
     159: invokevirtual #60                 // Method org/apache/hadoop/hbase/io/hfile/TestLruBlockCache$CachedItem.cacheBlockHeapSize:()J
     162: ladd
     163: lstore        9
     165: aload         5
     167: aload         7
     169: iload         11
     171: aaload
     172: getfield      #39                 // Field org/apache/hadoop/hbase/io/hfile/TestLruBlockCache$CachedItem.cacheKey:Lorg/apache/hadoop/hbase/io/hfile/BlockCacheKey;
     175: iconst_1
     176: iconst_0
     177: iconst_1
     178: invokevirtual #59                 // Method org/apache/hadoop/hbase/io/hfile/LruBlockCache.getBlock:(Lorg/apache/hadoop/hbase/io/hfile/BlockCacheKey;ZZZ)Lorg/apache/hadoop/hbase/io/hfile/Cacheable;
     181: pop
     182: aload         5
     184: aload         8
     186: iload         11
     188: aaload
     189: getfield      #39                 // Field org/apache/hadoop/hbase/io/hfile/TestLruBlockCache$CachedItem.cacheKey:Lorg/apache/hadoop/hbase/io/hfile/BlockCacheKey;
     192: aload         8
     194: iload         11
     196: aaload
     197: iconst_1
     198: invokevirtual #91                 // Method org/apache/hadoop/hbase/io/hfile/LruBlockCache.cacheBlock:(Lorg/apache/hadoop/hbase/io/hfile/BlockCacheKey;Lorg/apache/hadoop/hbase/io/hfile/Cacheable;Z)V
     201: lload         9
     203: aload         8
     205: iload         11
     207: aaload
     208: invokevirtual #60                 // Method org/apache/hadoop/hbase/io/hfile/TestLruBlockCache$CachedItem.cacheBlockHeapSize:()J
     211: ladd
     212: lstore        9
     214: iinc          11, 1
     217: goto          97
     220: lconst_0
     221: aload         5
     223: invokevirtual #41                 // Method org/apache/hadoop/hbase/io/hfile/LruBlockCache.getStats:()Lorg/apache/hadoop/hbase/io/hfile/CacheStats;
     226: invokevirtual #42                 // Method org/apache/hadoop/hbase/io/hfile/CacheStats.getEvictionCount:()J
     229: invokestatic  #34                 // Method org/junit/Assert.assertEquals:(JJ)V
     232: lload         9
     234: aload         5
     236: invokevirtual #58                 // Method org/apache/hadoop/hbase/io/hfile/LruBlockCache.heapSize:()J
     239: invokestatic  #34                 // Method org/junit/Assert.assertEquals:(JJ)V
     242: aload         5
     244: aload         6
     246: iconst_3
     247: aaload
     248: getfield      #39                 // Field org/apache/hadoop/hbase/io/hfile/TestLruBlockCache$CachedItem.cacheKey:Lorg/apache/hadoop/hbase/io/hfile/BlockCacheKey;
     251: aload         6
     253: iconst_3
     254: aaload
     255: invokevirtual #40                 // Method org/apache/hadoop/hbase/io/hfile/LruBlockCache.cacheBlock:(Lorg/apache/hadoop/hbase/io/hfile/BlockCacheKey;Lorg/apache/hadoop/hbase/io/hfile/Cacheable;)V
     258: lconst_1
     259: aload         5
     261: invokevirtual #41                 // Method org/apache/hadoop/hbase/io/hfile/LruBlockCache.getStats:()Lorg/apache/hadoop/hbase/io/hfile/CacheStats;
     264: invokevirtual #42                 // Method org/apache/hadoop/hbase/io/hfile/CacheStats.getEvictionCount:()J
     267: invokestatic  #34                 // Method org/junit/Assert.assertEquals:(JJ)V
     270: lconst_1
     271: aload         5
     273: invokevirtual #41                 // Method org/apache/hadoop/hbase/io/hfile/LruBlockCache.getStats:()Lorg/apache/hadoop/hbase/io/hfile/CacheStats;
     276: invokevirtual #77                 // Method org/apache/hadoop/hbase/io/hfile/CacheStats.getEvictedCount:()J
     279: invokestatic  #34                 // Method org/junit/Assert.assertEquals:(JJ)V
     282: aconst_null
     283: aload         5
     285: aload         6
     287: iconst_0
     288: aaload
     289: getfield      #39                 // Field org/apache/hadoop/hbase/io/hfile/TestLruBlockCache$CachedItem.cacheKey:Lorg/apache/hadoop/hbase/io/hfile/BlockCacheKey;
     292: iconst_1
     293: iconst_0
     294: iconst_1
     295: invokevirtual #59                 // Method org/apache/hadoop/hbase/io/hfile/LruBlockCache.getBlock:(Lorg/apache/hadoop/hbase/io/hfile/BlockCacheKey;ZZZ)Lorg/apache/hadoop/hbase/io/hfile/Cacheable;
     298: invokestatic  #71                 // Method org/junit/Assert.assertEquals:(Ljava/lang/Object;Ljava/lang/Object;)V
     301: aload         5
     303: aload         6
     305: iconst_1
     306: aaload
     307: getfield      #39                 // Field org/apache/hadoop/hbase/io/hfile/TestLruBlockCache$CachedItem.cacheKey:Lorg/apache/hadoop/hbase/io/hfile/BlockCacheKey;
     310: iconst_1
     311: iconst_0
     312: iconst_1
     313: invokevirtual #59                 // Method org/apache/hadoop/hbase/io/hfile/LruBlockCache.getBlock:(Lorg/apache/hadoop/hbase/io/hfile/BlockCacheKey;ZZZ)Lorg/apache/hadoop/hbase/io/hfile/Cacheable;
     316: pop
     317: aload         5
     319: aload         6
     321: iconst_4
     322: aaload
     323: getfield      #39                 // Field org/apache/hadoop/hbase/io/hfile/TestLruBlockCache$CachedItem.cacheKey:Lorg/apache/hadoop/hbase/io/hfile/BlockCacheKey;
     326: aload         6
     328: iconst_4
     329: aaload
     330: invokevirtual #40                 // Method org/apache/hadoop/hbase/io/hfile/LruBlockCache.cacheBlock:(Lorg/apache/hadoop/hbase/io/hfile/BlockCacheKey;Lorg/apache/hadoop/hbase/io/hfile/Cacheable;)V
     333: ldc2_w        #75                 // long 2l
     336: aload         5
     338: invokevirtual #41                 // Method org/apache/hadoop/hbase/io/hfile/LruBlockCache.getStats:()Lorg/apache/hadoop/hbase/io/hfile/CacheStats;
     341: invokevirtual #42                 // Method org/apache/hadoop/hbase/io/hfile/CacheStats.getEvictionCount:()J
     344: invokestatic  #34                 // Method org/junit/Assert.assertEquals:(JJ)V
     347: ldc2_w        #75                 // long 2l
     350: aload         5
     352: invokevirtual #41                 // Method org/apache/hadoop/hbase/io/hfile/LruBlockCache.getStats:()Lorg/apache/hadoop/hbase/io/hfile/CacheStats;
     355: invokevirtual #77                 // Method org/apache/hadoop/hbase/io/hfile/CacheStats.getEvictedCount:()J
     358: invokestatic  #34                 // Method org/junit/Assert.assertEquals:(JJ)V
     361: aconst_null
     362: aload         5
     364: aload         7
     366: iconst_0
     367: aaload
     368: getfield      #39                 // Field org/apache/hadoop/hbase/io/hfile/TestLruBlockCache$CachedItem.cacheKey:Lorg/apache/hadoop/hbase/io/hfile/BlockCacheKey;
     371: iconst_1
     372: iconst_0
     373: iconst_1
     374: invokevirtual #59                 // Method org/apache/hadoop/hbase/io/hfile/LruBlockCache.getBlock:(Lorg/apache/hadoop/hbase/io/hfile/BlockCacheKey;ZZZ)Lorg/apache/hadoop/hbase/io/hfile/Cacheable;
     377: invokestatic  #71                 // Method org/junit/Assert.assertEquals:(Ljava/lang/Object;Ljava/lang/Object;)V
     380: aload         5
     382: aload         8
     384: iconst_3
     385: aaload
     386: getfield      #39                 // Field org/apache/hadoop/hbase/io/hfile/TestLruBlockCache$CachedItem.cacheKey:Lorg/apache/hadoop/hbase/io/hfile/BlockCacheKey;
     389: aload         8
     391: iconst_3
     392: aaload
     393: iconst_1
     394: invokevirtual #91                 // Method org/apache/hadoop/hbase/io/hfile/LruBlockCache.cacheBlock:(Lorg/apache/hadoop/hbase/io/hfile/BlockCacheKey;Lorg/apache/hadoop/hbase/io/hfile/Cacheable;Z)V
     397: ldc2_w        #92                 // long 3l
     400: aload         5
     402: invokevirtual #41                 // Method org/apache/hadoop/hbase/io/hfile/LruBlockCache.getStats:()Lorg/apache/hadoop/hbase/io/hfile/CacheStats;
     405: invokevirtual #42                 // Method org/apache/hadoop/hbase/io/hfile/CacheStats.getEvictionCount:()J
     408: invokestatic  #34                 // Method org/junit/Assert.assertEquals:(JJ)V
     411: ldc2_w        #92                 // long 3l
     414: aload         5
     416: invokevirtual #41                 // Method org/apache/hadoop/hbase/io/hfile/LruBlockCache.getStats:()Lorg/apache/hadoop/hbase/io/hfile/CacheStats;
     419: invokevirtual #77                 // Method org/apache/hadoop/hbase/io/hfile/CacheStats.getEvictedCount:()J
     422: invokestatic  #34                 // Method org/junit/Assert.assertEquals:(JJ)V
     425: aconst_null
     426: aload         5
     428: aload         8
     430: iconst_0
     431: aaload
     432: getfield      #39                 // Field org/apache/hadoop/hbase/io/hfile/TestLruBlockCache$CachedItem.cacheKey:Lorg/apache/hadoop/hbase/io/hfile/BlockCacheKey;
     435: iconst_1
     436: iconst_0
     437: iconst_1
     438: invokevirtual #59                 // Method org/apache/hadoop/hbase/io/hfile/LruBlockCache.getBlock:(Lorg/apache/hadoop/hbase/io/hfile/BlockCacheKey;ZZZ)Lorg/apache/hadoop/hbase/io/hfile/Cacheable;
     441: invokestatic  #71                 // Method org/junit/Assert.assertEquals:(Ljava/lang/Object;Ljava/lang/Object;)V
     444: aload_0
     445: iconst_3
     446: lload_3
     447: ldc2_w        #92                 // long 3l
     450: lmul
     451: ldc           #94                 // String big
     453: invokespecial #38                 // Method generateFixedBlocks:(IJLjava/lang/String;)[Lorg/apache/hadoop/hbase/io/hfile/TestLruBlockCache$CachedItem;
     456: astore        11
     458: aload         5
     460: aload         11
     462: iconst_0
     463: aaload
     464: getfield      #39                 // Field org/apache/hadoop/hbase/io/hfile/TestLruBlockCache$CachedItem.cacheKey:Lorg/apache/hadoop/hbase/io/hfile/BlockCacheKey;
     467: aload         11
     469: iconst_0
     470: aaload
     471: invokevirtual #40                 // Method org/apache/hadoop/hbase/io/hfile/LruBlockCache.cacheBlock:(Lorg/apache/hadoop/hbase/io/hfile/BlockCacheKey;Lorg/apache/hadoop/hbase/io/hfile/Cacheable;)V
     474: ldc2_w        #95                 // long 4l
     477: aload         5
     479: invokevirtual #41                 // Method org/apache/hadoop/hbase/io/hfile/LruBlockCache.getStats:()Lorg/apache/hadoop/hbase/io/hfile/CacheStats;
     482: invokevirtual #42                 // Method org/apache/hadoop/hbase/io/hfile/CacheStats.getEvictionCount:()J
     485: invokestatic  #34                 // Method org/junit/Assert.assertEquals:(JJ)V
     488: ldc2_w        #97                 // long 6l
     491: aload         5
     493: invokevirtual #41                 // Method org/apache/hadoop/hbase/io/hfile/LruBlockCache.getStats:()Lorg/apache/hadoop/hbase/io/hfile/CacheStats;
     496: invokevirtual #77                 // Method org/apache/hadoop/hbase/io/hfile/CacheStats.getEvictedCount:()J
     499: invokestatic  #34                 // Method org/junit/Assert.assertEquals:(JJ)V
     502: aconst_null
     503: aload         5
     505: aload         6
     507: iconst_2
     508: aaload
     509: getfield      #39                 // Field org/apache/hadoop/hbase/io/hfile/TestLruBlockCache$CachedItem.cacheKey:Lorg/apache/hadoop/hbase/io/hfile/BlockCacheKey;
     512: iconst_1
     513: iconst_0
     514: iconst_1
     515: invokevirtual #59                 // Method org/apache/hadoop/hbase/io/hfile/LruBlockCache.getBlock:(Lorg/apache/hadoop/hbase/io/hfile/BlockCacheKey;ZZZ)Lorg/apache/hadoop/hbase/io/hfile/Cacheable;
     518: invokestatic  #71                 // Method org/junit/Assert.assertEquals:(Ljava/lang/Object;Ljava/lang/Object;)V
     521: aconst_null
     522: aload         5
     524: aload         6
     526: iconst_3
     527: aaload
     528: getfield      #39                 // Field org/apache/hadoop/hbase/io/hfile/TestLruBlockCache$CachedItem.cacheKey:Lorg/apache/hadoop/hbase/io/hfile/BlockCacheKey;
     531: iconst_1
     532: iconst_0
     533: iconst_1
     534: invokevirtual #59                 // Method org/apache/hadoop/hbase/io/hfile/LruBlockCache.getBlock:(Lorg/apache/hadoop/hbase/io/hfile/BlockCacheKey;ZZZ)Lorg/apache/hadoop/hbase/io/hfile/Cacheable;
     537: invokestatic  #71                 // Method org/junit/Assert.assertEquals:(Ljava/lang/Object;Ljava/lang/Object;)V
     540: aconst_null
     541: aload         5
     543: aload         6
     545: iconst_4
     546: aaload
     547: getfield      #39                 // Field org/apache/hadoop/hbase/io/hfile/TestLruBlockCache$CachedItem.cacheKey:Lorg/apache/hadoop/hbase/io/hfile/BlockCacheKey;
     550: iconst_1
     551: iconst_0
     552: iconst_1
     553: invokevirtual #59                 // Method org/apache/hadoop/hbase/io/hfile/LruBlockCache.getBlock:(Lorg/apache/hadoop/hbase/io/hfile/BlockCacheKey;ZZZ)Lorg/apache/hadoop/hbase/io/hfile/Cacheable;
     556: invokestatic  #71                 // Method org/junit/Assert.assertEquals:(Ljava/lang/Object;Ljava/lang/Object;)V
     559: aload         5
     561: aload         11
     563: iconst_0
     564: aaload
     565: getfield      #39                 // Field org/apache/hadoop/hbase/io/hfile/TestLruBlockCache$CachedItem.cacheKey:Lorg/apache/hadoop/hbase/io/hfile/BlockCacheKey;
     568: iconst_1
     569: iconst_0
     570: iconst_1
     571: invokevirtual #59                 // Method org/apache/hadoop/hbase/io/hfile/LruBlockCache.getBlock:(Lorg/apache/hadoop/hbase/io/hfile/BlockCacheKey;ZZZ)Lorg/apache/hadoop/hbase/io/hfile/Cacheable;
     574: pop
     575: aload         5
     577: aload         11
     579: iconst_1
     580: aaload
     581: getfield      #39                 // Field org/apache/hadoop/hbase/io/hfile/TestLruBlockCache$CachedItem.cacheKey:Lorg/apache/hadoop/hbase/io/hfile/BlockCacheKey;
     584: aload         11
     586: iconst_1
     587: aaload
     588: invokevirtual #40                 // Method org/apache/hadoop/hbase/io/hfile/LruBlockCache.cacheBlock:(Lorg/apache/hadoop/hbase/io/hfile/BlockCacheKey;Lorg/apache/hadoop/hbase/io/hfile/Cacheable;)V
     591: ldc2_w        #99                 // long 5l
     594: aload         5
     596: invokevirtual #41                 // Method org/apache/hadoop/hbase/io/hfile/LruBlockCache.getStats:()Lorg/apache/hadoop/hbase/io/hfile/CacheStats;
     599: invokevirtual #42                 // Method org/apache/hadoop/hbase/io/hfile/CacheStats.getEvictionCount:()J
     602: invokestatic  #34                 // Method org/junit/Assert.assertEquals:(JJ)V
     605: ldc2_w        #101                // long 9l
     608: aload         5
     610: invokevirtual #41                 // Method org/apache/hadoop/hbase/io/hfile/LruBlockCache.getStats:()Lorg/apache/hadoop/hbase/io/hfile/CacheStats;
     613: invokevirtual #77                 // Method org/apache/hadoop/hbase/io/hfile/CacheStats.getEvictedCount:()J
     616: invokestatic  #34                 // Method org/junit/Assert.assertEquals:(JJ)V
     619: aconst_null
     620: aload         5
     622: aload         6
     624: iconst_1
     625: aaload
     626: getfield      #39                 // Field org/apache/hadoop/hbase/io/hfile/TestLruBlockCache$CachedItem.cacheKey:Lorg/apache/hadoop/hbase/io/hfile/BlockCacheKey;
     629: iconst_1
     630: iconst_0
     631: iconst_1
     632: invokevirtual #59                 // Method org/apache/hadoop/hbase/io/hfile/LruBlockCache.getBlock:(Lorg/apache/hadoop/hbase/io/hfile/BlockCacheKey;ZZZ)Lorg/apache/hadoop/hbase/io/hfile/Cacheable;
     635: invokestatic  #71                 // Method org/junit/Assert.assertEquals:(Ljava/lang/Object;Ljava/lang/Object;)V
     638: aconst_null
     639: aload         5
     641: aload         7
     643: iconst_1
     644: aaload
     645: getfield      #39                 // Field org/apache/hadoop/hbase/io/hfile/TestLruBlockCache$CachedItem.cacheKey:Lorg/apache/hadoop/hbase/io/hfile/BlockCacheKey;
     648: iconst_1
     649: iconst_0
     650: iconst_1
     651: invokevirtual #59                 // Method org/apache/hadoop/hbase/io/hfile/LruBlockCache.getBlock:(Lorg/apache/hadoop/hbase/io/hfile/BlockCacheKey;ZZZ)Lorg/apache/hadoop/hbase/io/hfile/Cacheable;
     654: invokestatic  #71                 // Method org/junit/Assert.assertEquals:(Ljava/lang/Object;Ljava/lang/Object;)V
     657: aconst_null
     658: aload         5
     660: aload         7
     662: iconst_2
     663: aaload
     664: getfield      #39                 // Field org/apache/hadoop/hbase/io/hfile/TestLruBlockCache$CachedItem.cacheKey:Lorg/apache/hadoop/hbase/io/hfile/BlockCacheKey;
     667: iconst_1
     668: iconst_0
     669: iconst_1
     670: invokevirtual #59                 // Method org/apache/hadoop/hbase/io/hfile/LruBlockCache.getBlock:(Lorg/apache/hadoop/hbase/io/hfile/BlockCacheKey;ZZZ)Lorg/apache/hadoop/hbase/io/hfile/Cacheable;
     673: invokestatic  #71                 // Method org/junit/Assert.assertEquals:(Ljava/lang/Object;Ljava/lang/Object;)V
     676: aload         5
     678: aload         11
     680: iconst_2
     681: aaload
     682: getfield      #39                 // Field org/apache/hadoop/hbase/io/hfile/TestLruBlockCache$CachedItem.cacheKey:Lorg/apache/hadoop/hbase/io/hfile/BlockCacheKey;
     685: aload         11
     687: iconst_2
     688: aaload
     689: iconst_1
     690: invokevirtual #91                 // Method org/apache/hadoop/hbase/io/hfile/LruBlockCache.cacheBlock:(Lorg/apache/hadoop/hbase/io/hfile/BlockCacheKey;Lorg/apache/hadoop/hbase/io/hfile/Cacheable;Z)V
     693: ldc2_w        #97                 // long 6l
     696: aload         5
     698: invokevirtual #41                 // Method org/apache/hadoop/hbase/io/hfile/LruBlockCache.getStats:()Lorg/apache/hadoop/hbase/io/hfile/CacheStats;
     701: invokevirtual #42                 // Method org/apache/hadoop/hbase/io/hfile/CacheStats.getEvictionCount:()J
     704: invokestatic  #34                 // Method org/junit/Assert.assertEquals:(JJ)V
     707: ldc2_w        #103                // long 12l
     710: aload         5
     712: invokevirtual #41                 // Method org/apache/hadoop/hbase/io/hfile/LruBlockCache.getStats:()Lorg/apache/hadoop/hbase/io/hfile/CacheStats;
     715: invokevirtual #77                 // Method org/apache/hadoop/hbase/io/hfile/CacheStats.getEvictedCount:()J
     718: invokestatic  #34                 // Method org/junit/Assert.assertEquals:(JJ)V
     721: aconst_null
     722: aload         5
     724: aload         8
     726: iconst_1
     727: aaload
     728: getfield      #39                 // Field org/apache/hadoop/hbase/io/hfile/TestLruBlockCache$CachedItem.cacheKey:Lorg/apache/hadoop/hbase/io/hfile/BlockCacheKey;
     731: iconst_1
     732: iconst_0
     733: iconst_1
     734: invokevirtual #59                 // Method org/apache/hadoop/hbase/io/hfile/LruBlockCache.getBlock:(Lorg/apache/hadoop/hbase/io/hfile/BlockCacheKey;ZZZ)Lorg/apache/hadoop/hbase/io/hfile/Cacheable;
     737: invokestatic  #71                 // Method org/junit/Assert.assertEquals:(Ljava/lang/Object;Ljava/lang/Object;)V
     740: aconst_null
     741: aload         5
     743: aload         8
     745: iconst_2
     746: aaload
     747: getfield      #39                 // Field org/apache/hadoop/hbase/io/hfile/TestLruBlockCache$CachedItem.cacheKey:Lorg/apache/hadoop/hbase/io/hfile/BlockCacheKey;
     750: iconst_1
     751: iconst_0
     752: iconst_1
     753: invokevirtual #59                 // Method org/apache/hadoop/hbase/io/hfile/LruBlockCache.getBlock:(Lorg/apache/hadoop/hbase/io/hfile/BlockCacheKey;ZZZ)Lorg/apache/hadoop/hbase/io/hfile/Cacheable;
     756: invokestatic  #71                 // Method org/junit/Assert.assertEquals:(Ljava/lang/Object;Ljava/lang/Object;)V
     759: aconst_null
     760: aload         5
     762: aload         8
     764: iconst_3
     765: aaload
     766: getfield      #39                 // Field org/apache/hadoop/hbase/io/hfile/TestLruBlockCache$CachedItem.cacheKey:Lorg/apache/hadoop/hbase/io/hfile/BlockCacheKey;
     769: iconst_1
     770: iconst_0
     771: iconst_1
     772: invokevirtual #59                 // Method org/apache/hadoop/hbase/io/hfile/LruBlockCache.getBlock:(Lorg/apache/hadoop/hbase/io/hfile/BlockCacheKey;ZZZ)Lorg/apache/hadoop/hbase/io/hfile/Cacheable;
     775: invokestatic  #71                 // Method org/junit/Assert.assertEquals:(Ljava/lang/Object;Ljava/lang/Object;)V
     778: return

  public void testCacheEvictionInMemoryForceMode() throws java.lang.Exception;
    Code:
       0: ldc2_w        #2                  // long 100000l
       3: lstore_1
       4: aload_0
       5: lload_1
       6: bipush        10
       8: invokespecial #78                 // Method calculateBlockSize:(JI)J
      11: lstore_3
      12: new           #8                  // class org/apache/hadoop/hbase/io/hfile/LruBlockCache
      15: dup
      16: lload_1
      17: lload_3
      18: iconst_0
      19: ldc2_w        #79                 // double 1.2d
      22: lload_1
      23: l2d
      24: dmul
      25: lload_3
      26: l2d
      27: ddiv
      28: invokestatic  #81                 // Method java/lang/Math.ceil:(D)D
      31: d2i
      32: ldc           #82                 // float 0.75f
      34: bipush        16
      36: ldc           #83                 // float 0.98f
      38: ldc           #70                 // float 0.99f
      40: ldc           #105                // float 0.2f
      42: ldc           #106                // float 0.3f
      44: ldc           #107                // float 0.5f
      46: ldc           #86                 // float 1.2f
      48: iconst_1
      49: ldc2_w        #87                 // long 16777216l
      52: invokespecial #89                 // Method org/apache/hadoop/hbase/io/hfile/LruBlockCache."<init>":(JJZIFIFFFFFFZJ)V
      55: astore        5
      57: aload_0
      58: bipush        10
      60: lload_3
      61: ldc           #72                 // String single
      63: invokespecial #38                 // Method generateFixedBlocks:(IJLjava/lang/String;)[Lorg/apache/hadoop/hbase/io/hfile/TestLruBlockCache$CachedItem;
      66: astore        6
      68: aload_0
      69: bipush        10
      71: lload_3
      72: ldc           #74                 // String multi
      74: invokespecial #38                 // Method generateFixedBlocks:(IJLjava/lang/String;)[Lorg/apache/hadoop/hbase/io/hfile/TestLruBlockCache$CachedItem;
      77: astore        7
      79: aload_0
      80: bipush        10
      82: lload_3
      83: ldc           #90                 // String memory
      85: invokespecial #38                 // Method generateFixedBlocks:(IJLjava/lang/String;)[Lorg/apache/hadoop/hbase/io/hfile/TestLruBlockCache$CachedItem;
      88: astore        8
      90: aload         5
      92: invokevirtual #58                 // Method org/apache/hadoop/hbase/io/hfile/LruBlockCache.heapSize:()J
      95: lstore        9
      97: iconst_0
      98: istore        11
     100: iload         11
     102: iconst_4
     103: if_icmpge     191
     106: aload         5
     108: aload         6
     110: iload         11
     112: aaload
     113: getfield      #39                 // Field org/apache/hadoop/hbase/io/hfile/TestLruBlockCache$CachedItem.cacheKey:Lorg/apache/hadoop/hbase/io/hfile/BlockCacheKey;
     116: aload         6
     118: iload         11
     120: aaload
     121: invokevirtual #40                 // Method org/apache/hadoop/hbase/io/hfile/LruBlockCache.cacheBlock:(Lorg/apache/hadoop/hbase/io/hfile/BlockCacheKey;Lorg/apache/hadoop/hbase/io/hfile/Cacheable;)V
     124: lload         9
     126: aload         6
     128: iload         11
     130: aaload
     131: invokevirtual #60                 // Method org/apache/hadoop/hbase/io/hfile/TestLruBlockCache$CachedItem.cacheBlockHeapSize:()J
     134: ladd
     135: lstore        9
     137: aload         5
     139: aload         7
     141: iload         11
     143: aaload
     144: getfield      #39                 // Field org/apache/hadoop/hbase/io/hfile/TestLruBlockCache$CachedItem.cacheKey:Lorg/apache/hadoop/hbase/io/hfile/BlockCacheKey;
     147: aload         7
     149: iload         11
     151: aaload
     152: invokevirtual #40                 // Method org/apache/hadoop/hbase/io/hfile/LruBlockCache.cacheBlock:(Lorg/apache/hadoop/hbase/io/hfile/BlockCacheKey;Lorg/apache/hadoop/hbase/io/hfile/Cacheable;)V
     155: lload         9
     157: aload         7
     159: iload         11
     161: aaload
     162: invokevirtual #60                 // Method org/apache/hadoop/hbase/io/hfile/TestLruBlockCache$CachedItem.cacheBlockHeapSize:()J
     165: ladd
     166: lstore        9
     168: aload         5
     170: aload         7
     172: iload         11
     174: aaload
     175: getfield      #39                 // Field org/apache/hadoop/hbase/io/hfile/TestLruBlockCache$CachedItem.cacheKey:Lorg/apache/hadoop/hbase/io/hfile/BlockCacheKey;
     178: iconst_1
     179: iconst_0
     180: iconst_1
     181: invokevirtual #59                 // Method org/apache/hadoop/hbase/io/hfile/LruBlockCache.getBlock:(Lorg/apache/hadoop/hbase/io/hfile/BlockCacheKey;ZZZ)Lorg/apache/hadoop/hbase/io/hfile/Cacheable;
     184: pop
     185: iinc          11, 1
     188: goto          100
     191: aload         5
     193: aload         6
     195: iconst_4
     196: aaload
     197: getfield      #39                 // Field org/apache/hadoop/hbase/io/hfile/TestLruBlockCache$CachedItem.cacheKey:Lorg/apache/hadoop/hbase/io/hfile/BlockCacheKey;
     200: aload         6
     202: iconst_4
     203: aaload
     204: invokevirtual #40                 // Method org/apache/hadoop/hbase/io/hfile/LruBlockCache.cacheBlock:(Lorg/apache/hadoop/hbase/io/hfile/BlockCacheKey;Lorg/apache/hadoop/hbase/io/hfile/Cacheable;)V
     207: lload         9
     209: aload         6
     211: iconst_4
     212: aaload
     213: invokevirtual #60                 // Method org/apache/hadoop/hbase/io/hfile/TestLruBlockCache$CachedItem.cacheBlockHeapSize:()J
     216: ladd
     217: lstore        9
     219: lconst_0
     220: aload         5
     222: invokevirtual #41                 // Method org/apache/hadoop/hbase/io/hfile/LruBlockCache.getStats:()Lorg/apache/hadoop/hbase/io/hfile/CacheStats;
     225: invokevirtual #42                 // Method org/apache/hadoop/hbase/io/hfile/CacheStats.getEvictionCount:()J
     228: invokestatic  #34                 // Method org/junit/Assert.assertEquals:(JJ)V
     231: lload         9
     233: aload         5
     235: invokevirtual #58                 // Method org/apache/hadoop/hbase/io/hfile/LruBlockCache.heapSize:()J
     238: invokestatic  #34                 // Method org/junit/Assert.assertEquals:(JJ)V
     241: aload         5
     243: aload         8
     245: iconst_0
     246: aaload
     247: getfield      #39                 // Field org/apache/hadoop/hbase/io/hfile/TestLruBlockCache$CachedItem.cacheKey:Lorg/apache/hadoop/hbase/io/hfile/BlockCacheKey;
     250: aload         8
     252: iconst_0
     253: aaload
     254: iconst_1
     255: invokevirtual #91                 // Method org/apache/hadoop/hbase/io/hfile/LruBlockCache.cacheBlock:(Lorg/apache/hadoop/hbase/io/hfile/BlockCacheKey;Lorg/apache/hadoop/hbase/io/hfile/Cacheable;Z)V
     258: lconst_1
     259: aload         5
     261: invokevirtual #41                 // Method org/apache/hadoop/hbase/io/hfile/LruBlockCache.getStats:()Lorg/apache/hadoop/hbase/io/hfile/CacheStats;
     264: invokevirtual #42                 // Method org/apache/hadoop/hbase/io/hfile/CacheStats.getEvictionCount:()J
     267: invokestatic  #34                 // Method org/junit/Assert.assertEquals:(JJ)V
     270: lconst_1
     271: aload         5
     273: invokevirtual #41                 // Method org/apache/hadoop/hbase/io/hfile/LruBlockCache.getStats:()Lorg/apache/hadoop/hbase/io/hfile/CacheStats;
     276: invokevirtual #77                 // Method org/apache/hadoop/hbase/io/hfile/CacheStats.getEvictedCount:()J
     279: invokestatic  #34                 // Method org/junit/Assert.assertEquals:(JJ)V
     282: aconst_null
     283: aload         5
     285: aload         6
     287: iconst_0
     288: aaload
     289: getfield      #39                 // Field org/apache/hadoop/hbase/io/hfile/TestLruBlockCache$CachedItem.cacheKey:Lorg/apache/hadoop/hbase/io/hfile/BlockCacheKey;
     292: iconst_1
     293: iconst_0
     294: iconst_1
     295: invokevirtual #59                 // Method org/apache/hadoop/hbase/io/hfile/LruBlockCache.getBlock:(Lorg/apache/hadoop/hbase/io/hfile/BlockCacheKey;ZZZ)Lorg/apache/hadoop/hbase/io/hfile/Cacheable;
     298: invokestatic  #71                 // Method org/junit/Assert.assertEquals:(Ljava/lang/Object;Ljava/lang/Object;)V
     301: aload         5
     303: aload         8
     305: iconst_1
     306: aaload
     307: getfield      #39                 // Field org/apache/hadoop/hbase/io/hfile/TestLruBlockCache$CachedItem.cacheKey:Lorg/apache/hadoop/hbase/io/hfile/BlockCacheKey;
     310: aload         8
     312: iconst_1
     313: aaload
     314: iconst_1
     315: invokevirtual #91                 // Method org/apache/hadoop/hbase/io/hfile/LruBlockCache.cacheBlock:(Lorg/apache/hadoop/hbase/io/hfile/BlockCacheKey;Lorg/apache/hadoop/hbase/io/hfile/Cacheable;Z)V
     318: ldc2_w        #75                 // long 2l
     321: aload         5
     323: invokevirtual #41                 // Method org/apache/hadoop/hbase/io/hfile/LruBlockCache.getStats:()Lorg/apache/hadoop/hbase/io/hfile/CacheStats;
     326: invokevirtual #42                 // Method org/apache/hadoop/hbase/io/hfile/CacheStats.getEvictionCount:()J
     329: invokestatic  #34                 // Method org/junit/Assert.assertEquals:(JJ)V
     332: ldc2_w        #75                 // long 2l
     335: aload         5
     337: invokevirtual #41                 // Method org/apache/hadoop/hbase/io/hfile/LruBlockCache.getStats:()Lorg/apache/hadoop/hbase/io/hfile/CacheStats;
     340: invokevirtual #77                 // Method org/apache/hadoop/hbase/io/hfile/CacheStats.getEvictedCount:()J
     343: invokestatic  #34                 // Method org/junit/Assert.assertEquals:(JJ)V
     346: aconst_null
     347: aload         5
     349: aload         6
     351: iconst_1
     352: aaload
     353: getfield      #39                 // Field org/apache/hadoop/hbase/io/hfile/TestLruBlockCache$CachedItem.cacheKey:Lorg/apache/hadoop/hbase/io/hfile/BlockCacheKey;
     356: iconst_1
     357: iconst_0
     358: iconst_1
     359: invokevirtual #59                 // Method org/apache/hadoop/hbase/io/hfile/LruBlockCache.getBlock:(Lorg/apache/hadoop/hbase/io/hfile/BlockCacheKey;ZZZ)Lorg/apache/hadoop/hbase/io/hfile/Cacheable;
     362: invokestatic  #71                 // Method org/junit/Assert.assertEquals:(Ljava/lang/Object;Ljava/lang/Object;)V
     365: aload         5
     367: aload         8
     369: iconst_2
     370: aaload
     371: getfield      #39                 // Field org/apache/hadoop/hbase/io/hfile/TestLruBlockCache$CachedItem.cacheKey:Lorg/apache/hadoop/hbase/io/hfile/BlockCacheKey;
     374: aload         8
     376: iconst_2
     377: aaload
     378: iconst_1
     379: invokevirtual #91                 // Method org/apache/hadoop/hbase/io/hfile/LruBlockCache.cacheBlock:(Lorg/apache/hadoop/hbase/io/hfile/BlockCacheKey;Lorg/apache/hadoop/hbase/io/hfile/Cacheable;Z)V
     382: aload         5
     384: aload         8
     386: iconst_3
     387: aaload
     388: getfield      #39                 // Field org/apache/hadoop/hbase/io/hfile/TestLruBlockCache$CachedItem.cacheKey:Lorg/apache/hadoop/hbase/io/hfile/BlockCacheKey;
     391: aload         8
     393: iconst_3
     394: aaload
     395: iconst_1
     396: invokevirtual #91                 // Method org/apache/hadoop/hbase/io/hfile/LruBlockCache.cacheBlock:(Lorg/apache/hadoop/hbase/io/hfile/BlockCacheKey;Lorg/apache/hadoop/hbase/io/hfile/Cacheable;Z)V
     399: aload         5
     401: aload         8
     403: iconst_4
     404: aaload
     405: getfield      #39                 // Field org/apache/hadoop/hbase/io/hfile/TestLruBlockCache$CachedItem.cacheKey:Lorg/apache/hadoop/hbase/io/hfile/BlockCacheKey;
     408: aload         8
     410: iconst_4
     411: aaload
     412: iconst_1
     413: invokevirtual #91                 // Method org/apache/hadoop/hbase/io/hfile/LruBlockCache.cacheBlock:(Lorg/apache/hadoop/hbase/io/hfile/BlockCacheKey;Lorg/apache/hadoop/hbase/io/hfile/Cacheable;Z)V
     416: aload         5
     418: aload         8
     420: iconst_5
     421: aaload
     422: getfield      #39                 // Field org/apache/hadoop/hbase/io/hfile/TestLruBlockCache$CachedItem.cacheKey:Lorg/apache/hadoop/hbase/io/hfile/BlockCacheKey;
     425: aload         8
     427: iconst_5
     428: aaload
     429: iconst_1
     430: invokevirtual #91                 // Method org/apache/hadoop/hbase/io/hfile/LruBlockCache.cacheBlock:(Lorg/apache/hadoop/hbase/io/hfile/BlockCacheKey;Lorg/apache/hadoop/hbase/io/hfile/Cacheable;Z)V
     433: ldc2_w        #97                 // long 6l
     436: aload         5
     438: invokevirtual #41                 // Method org/apache/hadoop/hbase/io/hfile/LruBlockCache.getStats:()Lorg/apache/hadoop/hbase/io/hfile/CacheStats;
     441: invokevirtual #42                 // Method org/apache/hadoop/hbase/io/hfile/CacheStats.getEvictionCount:()J
     444: invokestatic  #34                 // Method org/junit/Assert.assertEquals:(JJ)V
     447: ldc2_w        #97                 // long 6l
     450: aload         5
     452: invokevirtual #41                 // Method org/apache/hadoop/hbase/io/hfile/LruBlockCache.getStats:()Lorg/apache/hadoop/hbase/io/hfile/CacheStats;
     455: invokevirtual #77                 // Method org/apache/hadoop/hbase/io/hfile/CacheStats.getEvictedCount:()J
     458: invokestatic  #34                 // Method org/junit/Assert.assertEquals:(JJ)V
     461: aconst_null
     462: aload         5
     464: aload         6
     466: iconst_2
     467: aaload
     468: getfield      #39                 // Field org/apache/hadoop/hbase/io/hfile/TestLruBlockCache$CachedItem.cacheKey:Lorg/apache/hadoop/hbase/io/hfile/BlockCacheKey;
     471: iconst_1
     472: iconst_0
     473: iconst_1
     474: invokevirtual #59                 // Method org/apache/hadoop/hbase/io/hfile/LruBlockCache.getBlock:(Lorg/apache/hadoop/hbase/io/hfile/BlockCacheKey;ZZZ)Lorg/apache/hadoop/hbase/io/hfile/Cacheable;
     477: invokestatic  #71                 // Method org/junit/Assert.assertEquals:(Ljava/lang/Object;Ljava/lang/Object;)V
     480: aconst_null
     481: aload         5
     483: aload         6
     485: iconst_3
     486: aaload
     487: getfield      #39                 // Field org/apache/hadoop/hbase/io/hfile/TestLruBlockCache$CachedItem.cacheKey:Lorg/apache/hadoop/hbase/io/hfile/BlockCacheKey;
     490: iconst_1
     491: iconst_0
     492: iconst_1
     493: invokevirtual #59                 // Method org/apache/hadoop/hbase/io/hfile/LruBlockCache.getBlock:(Lorg/apache/hadoop/hbase/io/hfile/BlockCacheKey;ZZZ)Lorg/apache/hadoop/hbase/io/hfile/Cacheable;
     496: invokestatic  #71                 // Method org/junit/Assert.assertEquals:(Ljava/lang/Object;Ljava/lang/Object;)V
     499: aconst_null
     500: aload         5
     502: aload         7
     504: iconst_0
     505: aaload
     506: getfield      #39                 // Field org/apache/hadoop/hbase/io/hfile/TestLruBlockCache$CachedItem.cacheKey:Lorg/apache/hadoop/hbase/io/hfile/BlockCacheKey;
     509: iconst_1
     510: iconst_0
     511: iconst_1
     512: invokevirtual #59                 // Method org/apache/hadoop/hbase/io/hfile/LruBlockCache.getBlock:(Lorg/apache/hadoop/hbase/io/hfile/BlockCacheKey;ZZZ)Lorg/apache/hadoop/hbase/io/hfile/Cacheable;
     515: invokestatic  #71                 // Method org/junit/Assert.assertEquals:(Ljava/lang/Object;Ljava/lang/Object;)V
     518: aconst_null
     519: aload         5
     521: aload         7
     523: iconst_1
     524: aaload
     525: getfield      #39                 // Field org/apache/hadoop/hbase/io/hfile/TestLruBlockCache$CachedItem.cacheKey:Lorg/apache/hadoop/hbase/io/hfile/BlockCacheKey;
     528: iconst_1
     529: iconst_0
     530: iconst_1
     531: invokevirtual #59                 // Method org/apache/hadoop/hbase/io/hfile/LruBlockCache.getBlock:(Lorg/apache/hadoop/hbase/io/hfile/BlockCacheKey;ZZZ)Lorg/apache/hadoop/hbase/io/hfile/Cacheable;
     534: invokestatic  #71                 // Method org/junit/Assert.assertEquals:(Ljava/lang/Object;Ljava/lang/Object;)V
     537: aload         5
     539: aload         8
     541: bipush        6
     543: aaload
     544: getfield      #39                 // Field org/apache/hadoop/hbase/io/hfile/TestLruBlockCache$CachedItem.cacheKey:Lorg/apache/hadoop/hbase/io/hfile/BlockCacheKey;
     547: aload         8
     549: bipush        6
     551: aaload
     552: iconst_1
     553: invokevirtual #91                 // Method org/apache/hadoop/hbase/io/hfile/LruBlockCache.cacheBlock:(Lorg/apache/hadoop/hbase/io/hfile/BlockCacheKey;Lorg/apache/hadoop/hbase/io/hfile/Cacheable;Z)V
     556: aload         5
     558: aload         8
     560: bipush        7
     562: aaload
     563: getfield      #39                 // Field org/apache/hadoop/hbase/io/hfile/TestLruBlockCache$CachedItem.cacheKey:Lorg/apache/hadoop/hbase/io/hfile/BlockCacheKey;
     566: aload         8
     568: bipush        7
     570: aaload
     571: iconst_1
     572: invokevirtual #91                 // Method org/apache/hadoop/hbase/io/hfile/LruBlockCache.cacheBlock:(Lorg/apache/hadoop/hbase/io/hfile/BlockCacheKey;Lorg/apache/hadoop/hbase/io/hfile/Cacheable;Z)V
     575: aload         5
     577: aload         8
     579: bipush        8
     581: aaload
     582: getfield      #39                 // Field org/apache/hadoop/hbase/io/hfile/TestLruBlockCache$CachedItem.cacheKey:Lorg/apache/hadoop/hbase/io/hfile/BlockCacheKey;
     585: aload         8
     587: bipush        8
     589: aaload
     590: iconst_1
     591: invokevirtual #91                 // Method org/apache/hadoop/hbase/io/hfile/LruBlockCache.cacheBlock:(Lorg/apache/hadoop/hbase/io/hfile/BlockCacheKey;Lorg/apache/hadoop/hbase/io/hfile/Cacheable;Z)V
     594: ldc2_w        #101                // long 9l
     597: aload         5
     599: invokevirtual #41                 // Method org/apache/hadoop/hbase/io/hfile/LruBlockCache.getStats:()Lorg/apache/hadoop/hbase/io/hfile/CacheStats;
     602: invokevirtual #42                 // Method org/apache/hadoop/hbase/io/hfile/CacheStats.getEvictionCount:()J
     605: invokestatic  #34                 // Method org/junit/Assert.assertEquals:(JJ)V
     608: ldc2_w        #101                // long 9l
     611: aload         5
     613: invokevirtual #41                 // Method org/apache/hadoop/hbase/io/hfile/LruBlockCache.getStats:()Lorg/apache/hadoop/hbase/io/hfile/CacheStats;
     616: invokevirtual #77                 // Method org/apache/hadoop/hbase/io/hfile/CacheStats.getEvictedCount:()J
     619: invokestatic  #34                 // Method org/junit/Assert.assertEquals:(JJ)V
     622: aconst_null
     623: aload         5
     625: aload         6
     627: iconst_4
     628: aaload
     629: getfield      #39                 // Field org/apache/hadoop/hbase/io/hfile/TestLruBlockCache$CachedItem.cacheKey:Lorg/apache/hadoop/hbase/io/hfile/BlockCacheKey;
     632: iconst_1
     633: iconst_0
     634: iconst_1
     635: invokevirtual #59                 // Method org/apache/hadoop/hbase/io/hfile/LruBlockCache.getBlock:(Lorg/apache/hadoop/hbase/io/hfile/BlockCacheKey;ZZZ)Lorg/apache/hadoop/hbase/io/hfile/Cacheable;
     638: invokestatic  #71                 // Method org/junit/Assert.assertEquals:(Ljava/lang/Object;Ljava/lang/Object;)V
     641: aconst_null
     642: aload         5
     644: aload         7
     646: iconst_2
     647: aaload
     648: getfield      #39                 // Field org/apache/hadoop/hbase/io/hfile/TestLruBlockCache$CachedItem.cacheKey:Lorg/apache/hadoop/hbase/io/hfile/BlockCacheKey;
     651: iconst_1
     652: iconst_0
     653: iconst_1
     654: invokevirtual #59                 // Method org/apache/hadoop/hbase/io/hfile/LruBlockCache.getBlock:(Lorg/apache/hadoop/hbase/io/hfile/BlockCacheKey;ZZZ)Lorg/apache/hadoop/hbase/io/hfile/Cacheable;
     657: invokestatic  #71                 // Method org/junit/Assert.assertEquals:(Ljava/lang/Object;Ljava/lang/Object;)V
     660: aconst_null
     661: aload         5
     663: aload         7
     665: iconst_3
     666: aaload
     667: getfield      #39                 // Field org/apache/hadoop/hbase/io/hfile/TestLruBlockCache$CachedItem.cacheKey:Lorg/apache/hadoop/hbase/io/hfile/BlockCacheKey;
     670: iconst_1
     671: iconst_0
     672: iconst_1
     673: invokevirtual #59                 // Method org/apache/hadoop/hbase/io/hfile/LruBlockCache.getBlock:(Lorg/apache/hadoop/hbase/io/hfile/BlockCacheKey;ZZZ)Lorg/apache/hadoop/hbase/io/hfile/Cacheable;
     676: invokestatic  #71                 // Method org/junit/Assert.assertEquals:(Ljava/lang/Object;Ljava/lang/Object;)V
     679: aload         5
     681: aload         8
     683: bipush        9
     685: aaload
     686: getfield      #39                 // Field org/apache/hadoop/hbase/io/hfile/TestLruBlockCache$CachedItem.cacheKey:Lorg/apache/hadoop/hbase/io/hfile/BlockCacheKey;
     689: aload         8
     691: bipush        9
     693: aaload
     694: iconst_1
     695: invokevirtual #91                 // Method org/apache/hadoop/hbase/io/hfile/LruBlockCache.cacheBlock:(Lorg/apache/hadoop/hbase/io/hfile/BlockCacheKey;Lorg/apache/hadoop/hbase/io/hfile/Cacheable;Z)V
     698: ldc2_w        #22                 // long 10l
     701: aload         5
     703: invokevirtual #41                 // Method org/apache/hadoop/hbase/io/hfile/LruBlockCache.getStats:()Lorg/apache/hadoop/hbase/io/hfile/CacheStats;
     706: invokevirtual #42                 // Method org/apache/hadoop/hbase/io/hfile/CacheStats.getEvictionCount:()J
     709: invokestatic  #34                 // Method org/junit/Assert.assertEquals:(JJ)V
     712: ldc2_w        #22                 // long 10l
     715: aload         5
     717: invokevirtual #41                 // Method org/apache/hadoop/hbase/io/hfile/LruBlockCache.getStats:()Lorg/apache/hadoop/hbase/io/hfile/CacheStats;
     720: invokevirtual #77                 // Method org/apache/hadoop/hbase/io/hfile/CacheStats.getEvictedCount:()J
     723: invokestatic  #34                 // Method org/junit/Assert.assertEquals:(JJ)V
     726: aconst_null
     727: aload         5
     729: aload         8
     731: iconst_0
     732: aaload
     733: getfield      #39                 // Field org/apache/hadoop/hbase/io/hfile/TestLruBlockCache$CachedItem.cacheKey:Lorg/apache/hadoop/hbase/io/hfile/BlockCacheKey;
     736: iconst_1
     737: iconst_0
     738: iconst_1
     739: invokevirtual #59                 // Method org/apache/hadoop/hbase/io/hfile/LruBlockCache.getBlock:(Lorg/apache/hadoop/hbase/io/hfile/BlockCacheKey;ZZZ)Lorg/apache/hadoop/hbase/io/hfile/Cacheable;
     742: invokestatic  #71                 // Method org/junit/Assert.assertEquals:(Ljava/lang/Object;Ljava/lang/Object;)V
     745: aload         5
     747: aload         6
     749: bipush        9
     751: aaload
     752: getfield      #39                 // Field org/apache/hadoop/hbase/io/hfile/TestLruBlockCache$CachedItem.cacheKey:Lorg/apache/hadoop/hbase/io/hfile/BlockCacheKey;
     755: aload         6
     757: bipush        9
     759: aaload
     760: invokevirtual #40                 // Method org/apache/hadoop/hbase/io/hfile/LruBlockCache.cacheBlock:(Lorg/apache/hadoop/hbase/io/hfile/BlockCacheKey;Lorg/apache/hadoop/hbase/io/hfile/Cacheable;)V
     763: ldc2_w        #108                // long 11l
     766: aload         5
     768: invokevirtual #41                 // Method org/apache/hadoop/hbase/io/hfile/LruBlockCache.getStats:()Lorg/apache/hadoop/hbase/io/hfile/CacheStats;
     771: invokevirtual #42                 // Method org/apache/hadoop/hbase/io/hfile/CacheStats.getEvictionCount:()J
     774: invokestatic  #34                 // Method org/junit/Assert.assertEquals:(JJ)V
     777: ldc2_w        #108                // long 11l
     780: aload         5
     782: invokevirtual #41                 // Method org/apache/hadoop/hbase/io/hfile/LruBlockCache.getStats:()Lorg/apache/hadoop/hbase/io/hfile/CacheStats;
     785: invokevirtual #77                 // Method org/apache/hadoop/hbase/io/hfile/CacheStats.getEvictedCount:()J
     788: invokestatic  #34                 // Method org/junit/Assert.assertEquals:(JJ)V
     791: aconst_null
     792: aload         5
     794: aload         6
     796: bipush        9
     798: aaload
     799: getfield      #39                 // Field org/apache/hadoop/hbase/io/hfile/TestLruBlockCache$CachedItem.cacheKey:Lorg/apache/hadoop/hbase/io/hfile/BlockCacheKey;
     802: iconst_1
     803: iconst_0
     804: iconst_1
     805: invokevirtual #59                 // Method org/apache/hadoop/hbase/io/hfile/LruBlockCache.getBlock:(Lorg/apache/hadoop/hbase/io/hfile/BlockCacheKey;ZZZ)Lorg/apache/hadoop/hbase/io/hfile/Cacheable;
     808: invokestatic  #71                 // Method org/junit/Assert.assertEquals:(Ljava/lang/Object;Ljava/lang/Object;)V
     811: return

  public void testScanResistance() throws java.lang.Exception;
    Code:
       0: ldc2_w        #2                  // long 100000l
       3: lstore_1
       4: aload_0
       5: lload_1
       6: bipush        10
       8: invokespecial #78                 // Method calculateBlockSize:(JI)J
      11: lstore_3
      12: new           #8                  // class org/apache/hadoop/hbase/io/hfile/LruBlockCache
      15: dup
      16: lload_1
      17: lload_3
      18: iconst_0
      19: ldc2_w        #79                 // double 1.2d
      22: lload_1
      23: l2d
      24: dmul
      25: lload_3
      26: l2d
      27: ddiv
      28: invokestatic  #81                 // Method java/lang/Math.ceil:(D)D
      31: d2i
      32: ldc           #82                 // float 0.75f
      34: bipush        16
      36: ldc           #110                // float 0.66f
      38: ldc           #70                 // float 0.99f
      40: ldc           #84                 // float 0.33f
      42: ldc           #84                 // float 0.33f
      44: ldc           #85                 // float 0.34f
      46: ldc           #86                 // float 1.2f
      48: iconst_0
      49: ldc2_w        #87                 // long 16777216l
      52: invokespecial #89                 // Method org/apache/hadoop/hbase/io/hfile/LruBlockCache."<init>":(JJZIFIFFFFFFZJ)V
      55: astore        5
      57: aload_0
      58: bipush        20
      60: lload_3
      61: ldc           #72                 // String single
      63: invokespecial #38                 // Method generateFixedBlocks:(IJLjava/lang/String;)[Lorg/apache/hadoop/hbase/io/hfile/TestLruBlockCache$CachedItem;
      66: astore        6
      68: aload_0
      69: iconst_5
      70: lload_3
      71: ldc           #74                 // String multi
      73: invokespecial #38                 // Method generateFixedBlocks:(IJLjava/lang/String;)[Lorg/apache/hadoop/hbase/io/hfile/TestLruBlockCache$CachedItem;
      76: astore        7
      78: aload         7
      80: astore        8
      82: aload         8
      84: arraylength
      85: istore        9
      87: iconst_0
      88: istore        10
      90: iload         10
      92: iload         9
      94: if_icmpge     136
      97: aload         8
      99: iload         10
     101: aaload
     102: astore        11
     104: aload         5
     106: aload         11
     108: getfield      #39                 // Field org/apache/hadoop/hbase/io/hfile/TestLruBlockCache$CachedItem.cacheKey:Lorg/apache/hadoop/hbase/io/hfile/BlockCacheKey;
     111: aload         11
     113: invokevirtual #40                 // Method org/apache/hadoop/hbase/io/hfile/LruBlockCache.cacheBlock:(Lorg/apache/hadoop/hbase/io/hfile/BlockCacheKey;Lorg/apache/hadoop/hbase/io/hfile/Cacheable;)V
     116: aload         5
     118: aload         11
     120: getfield      #39                 // Field org/apache/hadoop/hbase/io/hfile/TestLruBlockCache$CachedItem.cacheKey:Lorg/apache/hadoop/hbase/io/hfile/BlockCacheKey;
     123: iconst_1
     124: iconst_0
     125: iconst_1
     126: invokevirtual #59                 // Method org/apache/hadoop/hbase/io/hfile/LruBlockCache.getBlock:(Lorg/apache/hadoop/hbase/io/hfile/BlockCacheKey;ZZZ)Lorg/apache/hadoop/hbase/io/hfile/Cacheable;
     129: pop
     130: iinc          10, 1
     133: goto          90
     136: iconst_0
     137: istore        8
     139: iload         8
     141: iconst_5
     142: if_icmpge     169
     145: aload         5
     147: aload         6
     149: iload         8
     151: aaload
     152: getfield      #39                 // Field org/apache/hadoop/hbase/io/hfile/TestLruBlockCache$CachedItem.cacheKey:Lorg/apache/hadoop/hbase/io/hfile/BlockCacheKey;
     155: aload         6
     157: iload         8
     159: aaload
     160: invokevirtual #40                 // Method org/apache/hadoop/hbase/io/hfile/LruBlockCache.cacheBlock:(Lorg/apache/hadoop/hbase/io/hfile/BlockCacheKey;Lorg/apache/hadoop/hbase/io/hfile/Cacheable;)V
     163: iinc          8, 1
     166: goto          139
     169: lconst_1
     170: aload         5
     172: invokevirtual #41                 // Method org/apache/hadoop/hbase/io/hfile/LruBlockCache.getStats:()Lorg/apache/hadoop/hbase/io/hfile/CacheStats;
     175: invokevirtual #42                 // Method org/apache/hadoop/hbase/io/hfile/CacheStats.getEvictionCount:()J
     178: invokestatic  #34                 // Method org/junit/Assert.assertEquals:(JJ)V
     181: ldc2_w        #95                 // long 4l
     184: aload         5
     186: invokevirtual #41                 // Method org/apache/hadoop/hbase/io/hfile/LruBlockCache.getStats:()Lorg/apache/hadoop/hbase/io/hfile/CacheStats;
     189: invokevirtual #77                 // Method org/apache/hadoop/hbase/io/hfile/CacheStats.getEvictedCount:()J
     192: invokestatic  #34                 // Method org/junit/Assert.assertEquals:(JJ)V
     195: aconst_null
     196: aload         5
     198: aload         6
     200: iconst_0
     201: aaload
     202: getfield      #39                 // Field org/apache/hadoop/hbase/io/hfile/TestLruBlockCache$CachedItem.cacheKey:Lorg/apache/hadoop/hbase/io/hfile/BlockCacheKey;
     205: iconst_1
     206: iconst_0
     207: iconst_1
     208: invokevirtual #59                 // Method org/apache/hadoop/hbase/io/hfile/LruBlockCache.getBlock:(Lorg/apache/hadoop/hbase/io/hfile/BlockCacheKey;ZZZ)Lorg/apache/hadoop/hbase/io/hfile/Cacheable;
     211: invokestatic  #71                 // Method org/junit/Assert.assertEquals:(Ljava/lang/Object;Ljava/lang/Object;)V
     214: aconst_null
     215: aload         5
     217: aload         6
     219: iconst_1
     220: aaload
     221: getfield      #39                 // Field org/apache/hadoop/hbase/io/hfile/TestLruBlockCache$CachedItem.cacheKey:Lorg/apache/hadoop/hbase/io/hfile/BlockCacheKey;
     224: iconst_1
     225: iconst_0
     226: iconst_1
     227: invokevirtual #59                 // Method org/apache/hadoop/hbase/io/hfile/LruBlockCache.getBlock:(Lorg/apache/hadoop/hbase/io/hfile/BlockCacheKey;ZZZ)Lorg/apache/hadoop/hbase/io/hfile/Cacheable;
     230: invokestatic  #71                 // Method org/junit/Assert.assertEquals:(Ljava/lang/Object;Ljava/lang/Object;)V
     233: aconst_null
     234: aload         5
     236: aload         7
     238: iconst_0
     239: aaload
     240: getfield      #39                 // Field org/apache/hadoop/hbase/io/hfile/TestLruBlockCache$CachedItem.cacheKey:Lorg/apache/hadoop/hbase/io/hfile/BlockCacheKey;
     243: iconst_1
     244: iconst_0
     245: iconst_1
     246: invokevirtual #59                 // Method org/apache/hadoop/hbase/io/hfile/LruBlockCache.getBlock:(Lorg/apache/hadoop/hbase/io/hfile/BlockCacheKey;ZZZ)Lorg/apache/hadoop/hbase/io/hfile/Cacheable;
     249: invokestatic  #71                 // Method org/junit/Assert.assertEquals:(Ljava/lang/Object;Ljava/lang/Object;)V
     252: aconst_null
     253: aload         5
     255: aload         7
     257: iconst_1
     258: aaload
     259: getfield      #39                 // Field org/apache/hadoop/hbase/io/hfile/TestLruBlockCache$CachedItem.cacheKey:Lorg/apache/hadoop/hbase/io/hfile/BlockCacheKey;
     262: iconst_1
     263: iconst_0
     264: iconst_1
     265: invokevirtual #59                 // Method org/apache/hadoop/hbase/io/hfile/LruBlockCache.getBlock:(Lorg/apache/hadoop/hbase/io/hfile/BlockCacheKey;ZZZ)Lorg/apache/hadoop/hbase/io/hfile/Cacheable;
     268: invokestatic  #71                 // Method org/junit/Assert.assertEquals:(Ljava/lang/Object;Ljava/lang/Object;)V
     271: iconst_5
     272: istore        8
     274: iload         8
     276: bipush        18
     278: if_icmpge     305
     281: aload         5
     283: aload         6
     285: iload         8
     287: aaload
     288: getfield      #39                 // Field org/apache/hadoop/hbase/io/hfile/TestLruBlockCache$CachedItem.cacheKey:Lorg/apache/hadoop/hbase/io/hfile/BlockCacheKey;
     291: aload         6
     293: iload         8
     295: aaload
     296: invokevirtual #40                 // Method org/apache/hadoop/hbase/io/hfile/LruBlockCache.cacheBlock:(Lorg/apache/hadoop/hbase/io/hfile/BlockCacheKey;Lorg/apache/hadoop/hbase/io/hfile/Cacheable;)V
     299: iinc          8, 1
     302: goto          274
     305: ldc2_w        #95                 // long 4l
     308: aload         5
     310: invokevirtual #41                 // Method org/apache/hadoop/hbase/io/hfile/LruBlockCache.getStats:()Lorg/apache/hadoop/hbase/io/hfile/CacheStats;
     313: invokevirtual #42                 // Method org/apache/hadoop/hbase/io/hfile/CacheStats.getEvictionCount:()J
     316: invokestatic  #34                 // Method org/junit/Assert.assertEquals:(JJ)V
     319: ldc2_w        #111                // long 16l
     322: aload         5
     324: invokevirtual #41                 // Method org/apache/hadoop/hbase/io/hfile/LruBlockCache.getStats:()Lorg/apache/hadoop/hbase/io/hfile/CacheStats;
     327: invokevirtual #77                 // Method org/apache/hadoop/hbase/io/hfile/CacheStats.getEvictedCount:()J
     330: invokestatic  #34                 // Method org/junit/Assert.assertEquals:(JJ)V
     333: ldc2_w        #113                // long 7l
     336: aload         5
     338: invokevirtual #33                 // Method org/apache/hadoop/hbase/io/hfile/LruBlockCache.getBlockCount:()J
     341: invokestatic  #34                 // Method org/junit/Assert.assertEquals:(JJ)V
     344: return

  public void testMaxBlockSize() throws java.lang.Exception;
    Code:
       0: ldc2_w        #2                  // long 100000l
       3: lstore_1
       4: aload_0
       5: lload_1
       6: bipush        10
       8: invokespecial #78                 // Method calculateBlockSize:(JI)J
      11: lstore_3
      12: new           #8                  // class org/apache/hadoop/hbase/io/hfile/LruBlockCache
      15: dup
      16: lload_1
      17: lload_3
      18: iconst_0
      19: ldc2_w        #79                 // double 1.2d
      22: lload_1
      23: l2d
      24: dmul
      25: lload_3
      26: l2d
      27: ddiv
      28: invokestatic  #81                 // Method java/lang/Math.ceil:(D)D
      31: d2i
      32: ldc           #82                 // float 0.75f
      34: bipush        16
      36: ldc           #110                // float 0.66f
      38: ldc           #70                 // float 0.99f
      40: ldc           #84                 // float 0.33f
      42: ldc           #84                 // float 0.33f
      44: ldc           #85                 // float 0.34f
      46: ldc           #86                 // float 1.2f
      48: iconst_0
      49: ldc2_w        #115                // long 1024l
      52: invokespecial #89                 // Method org/apache/hadoop/hbase/io/hfile/LruBlockCache."<init>":(JJZIFIFFFFFFZJ)V
      55: astore        5
      57: aload_0
      58: bipush        10
      60: sipush        1029
      63: ldc           #117                // String long
      65: invokespecial #73                 // Method generateFixedBlocks:(IILjava/lang/String;)[Lorg/apache/hadoop/hbase/io/hfile/TestLruBlockCache$CachedItem;
      68: astore        6
      70: aload_0
      71: bipush        15
      73: sipush        600
      76: ldc           #118                // String small
      78: invokespecial #73                 // Method generateFixedBlocks:(IILjava/lang/String;)[Lorg/apache/hadoop/hbase/io/hfile/TestLruBlockCache$CachedItem;
      81: astore        7
      83: aload         6
      85: astore        8
      87: aload         8
      89: arraylength
      90: istore        9
      92: iconst_0
      93: istore        10
      95: iload         10
      97: iload         9
      99: if_icmpge     127
     102: aload         8
     104: iload         10
     106: aaload
     107: astore        11
     109: aload         5
     111: aload         11
     113: getfield      #39                 // Field org/apache/hadoop/hbase/io/hfile/TestLruBlockCache$CachedItem.cacheKey:Lorg/apache/hadoop/hbase/io/hfile/BlockCacheKey;
     116: aload         11
     118: invokevirtual #40                 // Method org/apache/hadoop/hbase/io/hfile/LruBlockCache.cacheBlock:(Lorg/apache/hadoop/hbase/io/hfile/BlockCacheKey;Lorg/apache/hadoop/hbase/io/hfile/Cacheable;)V
     121: iinc          10, 1
     124: goto          95
     127: aload         7
     129: astore        8
     131: aload         8
     133: arraylength
     134: istore        9
     136: iconst_0
     137: istore        10
     139: iload         10
     141: iload         9
     143: if_icmpge     171
     146: aload         8
     148: iload         10
     150: aaload
     151: astore        11
     153: aload         5
     155: aload         11
     157: getfield      #39                 // Field org/apache/hadoop/hbase/io/hfile/TestLruBlockCache$CachedItem.cacheKey:Lorg/apache/hadoop/hbase/io/hfile/BlockCacheKey;
     160: aload         11
     162: invokevirtual #40                 // Method org/apache/hadoop/hbase/io/hfile/LruBlockCache.cacheBlock:(Lorg/apache/hadoop/hbase/io/hfile/BlockCacheKey;Lorg/apache/hadoop/hbase/io/hfile/Cacheable;)V
     165: iinc          10, 1
     168: goto          139
     171: ldc2_w        #119                // long 15l
     174: aload         5
     176: invokevirtual #33                 // Method org/apache/hadoop/hbase/io/hfile/LruBlockCache.getBlockCount:()J
     179: invokestatic  #34                 // Method org/junit/Assert.assertEquals:(JJ)V
     182: aload         7
     184: astore        8
     186: aload         8
     188: arraylength
     189: istore        9
     191: iconst_0
     192: istore        10
     194: iload         10
     196: iload         9
     198: if_icmpge     230
     201: aload         8
     203: iload         10
     205: aaload
     206: astore        11
     208: aload         5
     210: aload         11
     212: getfield      #39                 // Field org/apache/hadoop/hbase/io/hfile/TestLruBlockCache$CachedItem.cacheKey:Lorg/apache/hadoop/hbase/io/hfile/BlockCacheKey;
     215: iconst_1
     216: iconst_0
     217: iconst_0
     218: invokevirtual #59                 // Method org/apache/hadoop/hbase/io/hfile/LruBlockCache.getBlock:(Lorg/apache/hadoop/hbase/io/hfile/BlockCacheKey;ZZZ)Lorg/apache/hadoop/hbase/io/hfile/Cacheable;
     221: invokestatic  #121                // Method org/junit/Assert.assertNotNull:(Ljava/lang/Object;)V
     224: iinc          10, 1
     227: goto          194
     230: aload         6
     232: astore        8
     234: aload         8
     236: arraylength
     237: istore        9
     239: iconst_0
     240: istore        10
     242: iload         10
     244: iload         9
     246: if_icmpge     278
     249: aload         8
     251: iload         10
     253: aaload
     254: astore        11
     256: aload         5
     258: aload         11
     260: getfield      #39                 // Field org/apache/hadoop/hbase/io/hfile/TestLruBlockCache$CachedItem.cacheKey:Lorg/apache/hadoop/hbase/io/hfile/BlockCacheKey;
     263: iconst_1
     264: iconst_0
     265: iconst_0
     266: invokevirtual #59                 // Method org/apache/hadoop/hbase/io/hfile/LruBlockCache.getBlock:(Lorg/apache/hadoop/hbase/io/hfile/BlockCacheKey;ZZZ)Lorg/apache/hadoop/hbase/io/hfile/Cacheable;
     269: invokestatic  #122                // Method org/junit/Assert.assertNull:(Ljava/lang/Object;)V
     272: iinc          10, 1
     275: goto          242
     278: ldc2_w        #22                 // long 10l
     281: aload         5
     283: invokevirtual #41                 // Method org/apache/hadoop/hbase/io/hfile/LruBlockCache.getStats:()Lorg/apache/hadoop/hbase/io/hfile/CacheStats;
     286: invokevirtual #123                // Method org/apache/hadoop/hbase/io/hfile/CacheStats.getFailedInserts:()J
     289: invokestatic  #34                 // Method org/junit/Assert.assertEquals:(JJ)V
     292: return

  public void testResizeBlockCache() throws java.lang.Exception;
    Code:
       0: ldc2_w        #124                // long 300000l
       3: lstore_1
       4: aload_0
       5: lload_1
       6: bipush        31
       8: invokespecial #78                 // Method calculateBlockSize:(JI)J
      11: lstore_3
      12: new           #8                  // class org/apache/hadoop/hbase/io/hfile/LruBlockCache
      15: dup
      16: lload_1
      17: lload_3
      18: iconst_0
      19: ldc2_w        #79                 // double 1.2d
      22: lload_1
      23: l2d
      24: dmul
      25: lload_3
      26: l2d
      27: ddiv
      28: invokestatic  #81                 // Method java/lang/Math.ceil:(D)D
      31: d2i
      32: ldc           #82                 // float 0.75f
      34: bipush        16
      36: ldc           #83                 // float 0.98f
      38: ldc           #70                 // float 0.99f
      40: ldc           #84                 // float 0.33f
      42: ldc           #84                 // float 0.33f
      44: ldc           #85                 // float 0.34f
      46: ldc           #86                 // float 1.2f
      48: iconst_0
      49: ldc2_w        #87                 // long 16777216l
      52: invokespecial #89                 // Method org/apache/hadoop/hbase/io/hfile/LruBlockCache."<init>":(JJZIFIFFFFFFZJ)V
      55: astore        5
      57: aload_0
      58: bipush        10
      60: lload_3
      61: ldc           #72                 // String single
      63: invokespecial #38                 // Method generateFixedBlocks:(IJLjava/lang/String;)[Lorg/apache/hadoop/hbase/io/hfile/TestLruBlockCache$CachedItem;
      66: astore        6
      68: aload_0
      69: bipush        10
      71: lload_3
      72: ldc           #74                 // String multi
      74: invokespecial #38                 // Method generateFixedBlocks:(IJLjava/lang/String;)[Lorg/apache/hadoop/hbase/io/hfile/TestLruBlockCache$CachedItem;
      77: astore        7
      79: aload_0
      80: bipush        10
      82: lload_3
      83: ldc           #90                 // String memory
      85: invokespecial #38                 // Method generateFixedBlocks:(IJLjava/lang/String;)[Lorg/apache/hadoop/hbase/io/hfile/TestLruBlockCache$CachedItem;
      88: astore        8
      90: iconst_0
      91: istore        9
      93: iload         9
      95: bipush        10
      97: if_icmpge     178
     100: aload         5
     102: aload         6
     104: iload         9
     106: aaload
     107: getfield      #39                 // Field org/apache/hadoop/hbase/io/hfile/TestLruBlockCache$CachedItem.cacheKey:Lorg/apache/hadoop/hbase/io/hfile/BlockCacheKey;
     110: aload         6
     112: iload         9
     114: aaload
     115: invokevirtual #40                 // Method org/apache/hadoop/hbase/io/hfile/LruBlockCache.cacheBlock:(Lorg/apache/hadoop/hbase/io/hfile/BlockCacheKey;Lorg/apache/hadoop/hbase/io/hfile/Cacheable;)V
     118: aload         5
     120: aload         7
     122: iload         9
     124: aaload
     125: getfield      #39                 // Field org/apache/hadoop/hbase/io/hfile/TestLruBlockCache$CachedItem.cacheKey:Lorg/apache/hadoop/hbase/io/hfile/BlockCacheKey;
     128: aload         7
     130: iload         9
     132: aaload
     133: invokevirtual #40                 // Method org/apache/hadoop/hbase/io/hfile/LruBlockCache.cacheBlock:(Lorg/apache/hadoop/hbase/io/hfile/BlockCacheKey;Lorg/apache/hadoop/hbase/io/hfile/Cacheable;)V
     136: aload         5
     138: aload         7
     140: iload         9
     142: aaload
     143: getfield      #39                 // Field org/apache/hadoop/hbase/io/hfile/TestLruBlockCache$CachedItem.cacheKey:Lorg/apache/hadoop/hbase/io/hfile/BlockCacheKey;
     146: iconst_1
     147: iconst_0
     148: iconst_1
     149: invokevirtual #59                 // Method org/apache/hadoop/hbase/io/hfile/LruBlockCache.getBlock:(Lorg/apache/hadoop/hbase/io/hfile/BlockCacheKey;ZZZ)Lorg/apache/hadoop/hbase/io/hfile/Cacheable;
     152: pop
     153: aload         5
     155: aload         8
     157: iload         9
     159: aaload
     160: getfield      #39                 // Field org/apache/hadoop/hbase/io/hfile/TestLruBlockCache$CachedItem.cacheKey:Lorg/apache/hadoop/hbase/io/hfile/BlockCacheKey;
     163: aload         8
     165: iload         9
     167: aaload
     168: iconst_1
     169: invokevirtual #91                 // Method org/apache/hadoop/hbase/io/hfile/LruBlockCache.cacheBlock:(Lorg/apache/hadoop/hbase/io/hfile/BlockCacheKey;Lorg/apache/hadoop/hbase/io/hfile/Cacheable;Z)V
     172: iinc          9, 1
     175: goto          93
     178: lconst_0
     179: aload         5
     181: invokevirtual #41                 // Method org/apache/hadoop/hbase/io/hfile/LruBlockCache.getStats:()Lorg/apache/hadoop/hbase/io/hfile/CacheStats;
     184: invokevirtual #42                 // Method org/apache/hadoop/hbase/io/hfile/CacheStats.getEvictionCount:()J
     187: invokestatic  #34                 // Method org/junit/Assert.assertEquals:(JJ)V
     190: aload         5
     192: lload_1
     193: l2f
     194: ldc           #107                // float 0.5f
     196: fmul
     197: f2l
     198: invokevirtual #126                // Method org/apache/hadoop/hbase/io/hfile/LruBlockCache.setMaxSize:(J)V
     201: lconst_1
     202: aload         5
     204: invokevirtual #41                 // Method org/apache/hadoop/hbase/io/hfile/LruBlockCache.getStats:()Lorg/apache/hadoop/hbase/io/hfile/CacheStats;
     207: invokevirtual #42                 // Method org/apache/hadoop/hbase/io/hfile/CacheStats.getEvictionCount:()J
     210: invokestatic  #34                 // Method org/junit/Assert.assertEquals:(JJ)V
     213: ldc2_w        #119                // long 15l
     216: aload         5
     218: invokevirtual #41                 // Method org/apache/hadoop/hbase/io/hfile/LruBlockCache.getStats:()Lorg/apache/hadoop/hbase/io/hfile/CacheStats;
     221: invokevirtual #77                 // Method org/apache/hadoop/hbase/io/hfile/CacheStats.getEvictedCount:()J
     224: invokestatic  #34                 // Method org/junit/Assert.assertEquals:(JJ)V
     227: iconst_0
     228: istore        9
     230: iload         9
     232: iconst_5
     233: if_icmpge     302
     236: aconst_null
     237: aload         5
     239: aload         6
     241: iload         9
     243: aaload
     244: getfield      #39                 // Field org/apache/hadoop/hbase/io/hfile/TestLruBlockCache$CachedItem.cacheKey:Lorg/apache/hadoop/hbase/io/hfile/BlockCacheKey;
     247: iconst_1
     248: iconst_0
     249: iconst_1
     250: invokevirtual #59                 // Method org/apache/hadoop/hbase/io/hfile/LruBlockCache.getBlock:(Lorg/apache/hadoop/hbase/io/hfile/BlockCacheKey;ZZZ)Lorg/apache/hadoop/hbase/io/hfile/Cacheable;
     253: invokestatic  #71                 // Method org/junit/Assert.assertEquals:(Ljava/lang/Object;Ljava/lang/Object;)V
     256: aconst_null
     257: aload         5
     259: aload         7
     261: iload         9
     263: aaload
     264: getfield      #39                 // Field org/apache/hadoop/hbase/io/hfile/TestLruBlockCache$CachedItem.cacheKey:Lorg/apache/hadoop/hbase/io/hfile/BlockCacheKey;
     267: iconst_1
     268: iconst_0
     269: iconst_1
     270: invokevirtual #59                 // Method org/apache/hadoop/hbase/io/hfile/LruBlockCache.getBlock:(Lorg/apache/hadoop/hbase/io/hfile/BlockCacheKey;ZZZ)Lorg/apache/hadoop/hbase/io/hfile/Cacheable;
     273: invokestatic  #71                 // Method org/junit/Assert.assertEquals:(Ljava/lang/Object;Ljava/lang/Object;)V
     276: aconst_null
     277: aload         5
     279: aload         8
     281: iload         9
     283: aaload
     284: getfield      #39                 // Field org/apache/hadoop/hbase/io/hfile/TestLruBlockCache$CachedItem.cacheKey:Lorg/apache/hadoop/hbase/io/hfile/BlockCacheKey;
     287: iconst_1
     288: iconst_0
     289: iconst_1
     290: invokevirtual #59                 // Method org/apache/hadoop/hbase/io/hfile/LruBlockCache.getBlock:(Lorg/apache/hadoop/hbase/io/hfile/BlockCacheKey;ZZZ)Lorg/apache/hadoop/hbase/io/hfile/Cacheable;
     293: invokestatic  #71                 // Method org/junit/Assert.assertEquals:(Ljava/lang/Object;Ljava/lang/Object;)V
     296: iinc          9, 1
     299: goto          230
     302: iconst_5
     303: istore        9
     305: iload         9
     307: bipush        10
     309: if_icmpge     390
     312: aload         6
     314: iload         9
     316: aaload
     317: aload         5
     319: aload         6
     321: iload         9
     323: aaload
     324: getfield      #39                 // Field org/apache/hadoop/hbase/io/hfile/TestLruBlockCache$CachedItem.cacheKey:Lorg/apache/hadoop/hbase/io/hfile/BlockCacheKey;
     327: iconst_1
     328: iconst_0
     329: iconst_1
     330: invokevirtual #59                 // Method org/apache/hadoop/hbase/io/hfile/LruBlockCache.getBlock:(Lorg/apache/hadoop/hbase/io/hfile/BlockCacheKey;ZZZ)Lorg/apache/hadoop/hbase/io/hfile/Cacheable;
     333: invokestatic  #71                 // Method org/junit/Assert.assertEquals:(Ljava/lang/Object;Ljava/lang/Object;)V
     336: aload         7
     338: iload         9
     340: aaload
     341: aload         5
     343: aload         7
     345: iload         9
     347: aaload
     348: getfield      #39                 // Field org/apache/hadoop/hbase/io/hfile/TestLruBlockCache$CachedItem.cacheKey:Lorg/apache/hadoop/hbase/io/hfile/BlockCacheKey;
     351: iconst_1
     352: iconst_0
     353: iconst_1
     354: invokevirtual #59                 // Method org/apache/hadoop/hbase/io/hfile/LruBlockCache.getBlock:(Lorg/apache/hadoop/hbase/io/hfile/BlockCacheKey;ZZZ)Lorg/apache/hadoop/hbase/io/hfile/Cacheable;
     357: invokestatic  #71                 // Method org/junit/Assert.assertEquals:(Ljava/lang/Object;Ljava/lang/Object;)V
     360: aload         8
     362: iload         9
     364: aaload
     365: aload         5
     367: aload         8
     369: iload         9
     371: aaload
     372: getfield      #39                 // Field org/apache/hadoop/hbase/io/hfile/TestLruBlockCache$CachedItem.cacheKey:Lorg/apache/hadoop/hbase/io/hfile/BlockCacheKey;
     375: iconst_1
     376: iconst_0
     377: iconst_1
     378: invokevirtual #59                 // Method org/apache/hadoop/hbase/io/hfile/LruBlockCache.getBlock:(Lorg/apache/hadoop/hbase/io/hfile/BlockCacheKey;ZZZ)Lorg/apache/hadoop/hbase/io/hfile/Cacheable;
     381: invokestatic  #71                 // Method org/junit/Assert.assertEquals:(Ljava/lang/Object;Ljava/lang/Object;)V
     384: iinc          9, 1
     387: goto          305
     390: return

  public void testPastNPeriodsMetrics() throws java.lang.Exception;
    Code:
       0: ldc2_w        #127                // double 0.01d
       3: dstore_1
       4: new           #129                // class org/apache/hadoop/hbase/io/hfile/CacheStats
       7: dup
       8: ldc           #130                // String test
      10: iconst_3
      11: invokespecial #131                // Method org/apache/hadoop/hbase/io/hfile/CacheStats."<init>":(Ljava/lang/String;I)V
      14: astore_3
      15: aload_3
      16: invokevirtual #132                // Method org/apache/hadoop/hbase/io/hfile/CacheStats.rollMetricsPeriod:()V
      19: dconst_0
      20: aload_3
      21: invokevirtual #133                // Method org/apache/hadoop/hbase/io/hfile/CacheStats.getHitRatioPastNPeriods:()D
      24: dload_1
      25: invokestatic  #134                // Method org/junit/Assert.assertEquals:(DDD)V
      28: dconst_0
      29: aload_3
      30: invokevirtual #135                // Method org/apache/hadoop/hbase/io/hfile/CacheStats.getHitCachingRatioPastNPeriods:()D
      33: dload_1
      34: invokestatic  #134                // Method org/junit/Assert.assertEquals:(DDD)V
      37: aload_3
      38: iconst_0
      39: iconst_1
      40: getstatic     #136                // Field org/apache/hadoop/hbase/io/hfile/BlockType.DATA:Lorg/apache/hadoop/hbase/io/hfile/BlockType;
      43: invokevirtual #137                // Method org/apache/hadoop/hbase/io/hfile/CacheStats.hit:(ZZLorg/apache/hadoop/hbase/io/hfile/BlockType;)V
      46: aload_3
      47: iconst_1
      48: iconst_1
      49: getstatic     #136                // Field org/apache/hadoop/hbase/io/hfile/BlockType.DATA:Lorg/apache/hadoop/hbase/io/hfile/BlockType;
      52: invokevirtual #137                // Method org/apache/hadoop/hbase/io/hfile/CacheStats.hit:(ZZLorg/apache/hadoop/hbase/io/hfile/BlockType;)V
      55: aload_3
      56: iconst_0
      57: iconst_0
      58: getstatic     #136                // Field org/apache/hadoop/hbase/io/hfile/BlockType.DATA:Lorg/apache/hadoop/hbase/io/hfile/BlockType;
      61: invokevirtual #138                // Method org/apache/hadoop/hbase/io/hfile/CacheStats.miss:(ZZLorg/apache/hadoop/hbase/io/hfile/BlockType;)V
      64: aload_3
      65: iconst_0
      66: iconst_0
      67: getstatic     #136                // Field org/apache/hadoop/hbase/io/hfile/BlockType.DATA:Lorg/apache/hadoop/hbase/io/hfile/BlockType;
      70: invokevirtual #138                // Method org/apache/hadoop/hbase/io/hfile/CacheStats.miss:(ZZLorg/apache/hadoop/hbase/io/hfile/BlockType;)V
      73: aload_3
      74: invokevirtual #132                // Method org/apache/hadoop/hbase/io/hfile/CacheStats.rollMetricsPeriod:()V
      77: ldc2_w        #139                // double 0.5d
      80: aload_3
      81: invokevirtual #133                // Method org/apache/hadoop/hbase/io/hfile/CacheStats.getHitRatioPastNPeriods:()D
      84: dload_1
      85: invokestatic  #134                // Method org/junit/Assert.assertEquals:(DDD)V
      88: dconst_1
      89: aload_3
      90: invokevirtual #135                // Method org/apache/hadoop/hbase/io/hfile/CacheStats.getHitCachingRatioPastNPeriods:()D
      93: dload_1
      94: invokestatic  #134                // Method org/junit/Assert.assertEquals:(DDD)V
      97: aload_3
      98: iconst_1
      99: iconst_0
     100: getstatic     #136                // Field org/apache/hadoop/hbase/io/hfile/BlockType.DATA:Lorg/apache/hadoop/hbase/io/hfile/BlockType;
     103: invokevirtual #138                // Method org/apache/hadoop/hbase/io/hfile/CacheStats.miss:(ZZLorg/apache/hadoop/hbase/io/hfile/BlockType;)V
     106: aload_3
     107: iconst_0
     108: iconst_0
     109: getstatic     #136                // Field org/apache/hadoop/hbase/io/hfile/BlockType.DATA:Lorg/apache/hadoop/hbase/io/hfile/BlockType;
     112: invokevirtual #138                // Method org/apache/hadoop/hbase/io/hfile/CacheStats.miss:(ZZLorg/apache/hadoop/hbase/io/hfile/BlockType;)V
     115: aload_3
     116: iconst_0
     117: iconst_0
     118: getstatic     #136                // Field org/apache/hadoop/hbase/io/hfile/BlockType.DATA:Lorg/apache/hadoop/hbase/io/hfile/BlockType;
     121: invokevirtual #138                // Method org/apache/hadoop/hbase/io/hfile/CacheStats.miss:(ZZLorg/apache/hadoop/hbase/io/hfile/BlockType;)V
     124: aload_3
     125: iconst_0
     126: iconst_0
     127: getstatic     #136                // Field org/apache/hadoop/hbase/io/hfile/BlockType.DATA:Lorg/apache/hadoop/hbase/io/hfile/BlockType;
     130: invokevirtual #138                // Method org/apache/hadoop/hbase/io/hfile/CacheStats.miss:(ZZLorg/apache/hadoop/hbase/io/hfile/BlockType;)V
     133: aload_3
     134: invokevirtual #132                // Method org/apache/hadoop/hbase/io/hfile/CacheStats.rollMetricsPeriod:()V
     137: ldc2_w        #141                // double 0.25d
     140: aload_3
     141: invokevirtual #133                // Method org/apache/hadoop/hbase/io/hfile/CacheStats.getHitRatioPastNPeriods:()D
     144: dload_1
     145: invokestatic  #134                // Method org/junit/Assert.assertEquals:(DDD)V
     148: ldc2_w        #139                // double 0.5d
     151: aload_3
     152: invokevirtual #135                // Method org/apache/hadoop/hbase/io/hfile/CacheStats.getHitCachingRatioPastNPeriods:()D
     155: dload_1
     156: invokestatic  #134                // Method org/junit/Assert.assertEquals:(DDD)V
     159: aload_3
     160: iconst_0
     161: iconst_1
     162: getstatic     #136                // Field org/apache/hadoop/hbase/io/hfile/BlockType.DATA:Lorg/apache/hadoop/hbase/io/hfile/BlockType;
     165: invokevirtual #137                // Method org/apache/hadoop/hbase/io/hfile/CacheStats.hit:(ZZLorg/apache/hadoop/hbase/io/hfile/BlockType;)V
     168: aload_3
     169: iconst_1
     170: iconst_1
     171: getstatic     #136                // Field org/apache/hadoop/hbase/io/hfile/BlockType.DATA:Lorg/apache/hadoop/hbase/io/hfile/BlockType;
     174: invokevirtual #137                // Method org/apache/hadoop/hbase/io/hfile/CacheStats.hit:(ZZLorg/apache/hadoop/hbase/io/hfile/BlockType;)V
     177: aload_3
     178: iconst_0
     179: iconst_1
     180: getstatic     #136                // Field org/apache/hadoop/hbase/io/hfile/BlockType.DATA:Lorg/apache/hadoop/hbase/io/hfile/BlockType;
     183: invokevirtual #137                // Method org/apache/hadoop/hbase/io/hfile/CacheStats.hit:(ZZLorg/apache/hadoop/hbase/io/hfile/BlockType;)V
     186: aload_3
     187: iconst_1
     188: iconst_1
     189: getstatic     #136                // Field org/apache/hadoop/hbase/io/hfile/BlockType.DATA:Lorg/apache/hadoop/hbase/io/hfile/BlockType;
     192: invokevirtual #137                // Method org/apache/hadoop/hbase/io/hfile/CacheStats.hit:(ZZLorg/apache/hadoop/hbase/io/hfile/BlockType;)V
     195: aload_3
     196: invokevirtual #132                // Method org/apache/hadoop/hbase/io/hfile/CacheStats.rollMetricsPeriod:()V
     199: ldc2_w        #139                // double 0.5d
     202: aload_3
     203: invokevirtual #133                // Method org/apache/hadoop/hbase/io/hfile/CacheStats.getHitRatioPastNPeriods:()D
     206: dload_1
     207: invokestatic  #134                // Method org/junit/Assert.assertEquals:(DDD)V
     210: ldc2_w        #143                // double 0.75d
     213: aload_3
     214: invokevirtual #135                // Method org/apache/hadoop/hbase/io/hfile/CacheStats.getHitCachingRatioPastNPeriods:()D
     217: dload_1
     218: invokestatic  #134                // Method org/junit/Assert.assertEquals:(DDD)V
     221: aload_3
     222: iconst_1
     223: iconst_0
     224: getstatic     #136                // Field org/apache/hadoop/hbase/io/hfile/BlockType.DATA:Lorg/apache/hadoop/hbase/io/hfile/BlockType;
     227: invokevirtual #138                // Method org/apache/hadoop/hbase/io/hfile/CacheStats.miss:(ZZLorg/apache/hadoop/hbase/io/hfile/BlockType;)V
     230: aload_3
     231: iconst_1
     232: iconst_0
     233: getstatic     #136                // Field org/apache/hadoop/hbase/io/hfile/BlockType.DATA:Lorg/apache/hadoop/hbase/io/hfile/BlockType;
     236: invokevirtual #138                // Method org/apache/hadoop/hbase/io/hfile/CacheStats.miss:(ZZLorg/apache/hadoop/hbase/io/hfile/BlockType;)V
     239: aload_3
     240: invokevirtual #132                // Method org/apache/hadoop/hbase/io/hfile/CacheStats.rollMetricsPeriod:()V
     243: ldc2_w        #145                // double 0.4d
     246: aload_3
     247: invokevirtual #133                // Method org/apache/hadoop/hbase/io/hfile/CacheStats.getHitRatioPastNPeriods:()D
     250: dload_1
     251: invokestatic  #134                // Method org/junit/Assert.assertEquals:(DDD)V
     254: ldc2_w        #145                // double 0.4d
     257: aload_3
     258: invokevirtual #135                // Method org/apache/hadoop/hbase/io/hfile/CacheStats.getHitCachingRatioPastNPeriods:()D
     261: dload_1
     262: invokestatic  #134                // Method org/junit/Assert.assertEquals:(DDD)V
     265: aload_3
     266: iconst_1
     267: iconst_0
     268: getstatic     #136                // Field org/apache/hadoop/hbase/io/hfile/BlockType.DATA:Lorg/apache/hadoop/hbase/io/hfile/BlockType;
     271: invokevirtual #138                // Method org/apache/hadoop/hbase/io/hfile/CacheStats.miss:(ZZLorg/apache/hadoop/hbase/io/hfile/BlockType;)V
     274: aload_3
     275: iconst_1
     276: iconst_0
     277: getstatic     #136                // Field org/apache/hadoop/hbase/io/hfile/BlockType.DATA:Lorg/apache/hadoop/hbase/io/hfile/BlockType;
     280: invokevirtual #138                // Method org/apache/hadoop/hbase/io/hfile/CacheStats.miss:(ZZLorg/apache/hadoop/hbase/io/hfile/BlockType;)V
     283: aload_3
     284: iconst_0
     285: iconst_1
     286: getstatic     #136                // Field org/apache/hadoop/hbase/io/hfile/BlockType.DATA:Lorg/apache/hadoop/hbase/io/hfile/BlockType;
     289: invokevirtual #137                // Method org/apache/hadoop/hbase/io/hfile/CacheStats.hit:(ZZLorg/apache/hadoop/hbase/io/hfile/BlockType;)V
     292: aload_3
     293: iconst_0
     294: iconst_1
     295: getstatic     #136                // Field org/apache/hadoop/hbase/io/hfile/BlockType.DATA:Lorg/apache/hadoop/hbase/io/hfile/BlockType;
     298: invokevirtual #137                // Method org/apache/hadoop/hbase/io/hfile/CacheStats.hit:(ZZLorg/apache/hadoop/hbase/io/hfile/BlockType;)V
     301: aload_3
     302: invokevirtual #132                // Method org/apache/hadoop/hbase/io/hfile/CacheStats.rollMetricsPeriod:()V
     305: ldc2_w        #147                // double 0.6d
     308: aload_3
     309: invokevirtual #133                // Method org/apache/hadoop/hbase/io/hfile/CacheStats.getHitRatioPastNPeriods:()D
     312: dload_1
     313: invokestatic  #134                // Method org/junit/Assert.assertEquals:(DDD)V
     316: ldc2_w        #149                // double 0.3333333333333333d
     319: aload_3
     320: invokevirtual #135                // Method org/apache/hadoop/hbase/io/hfile/CacheStats.getHitCachingRatioPastNPeriods:()D
     323: dload_1
     324: invokestatic  #134                // Method org/junit/Assert.assertEquals:(DDD)V
     327: aload_3
     328: invokevirtual #132                // Method org/apache/hadoop/hbase/io/hfile/CacheStats.rollMetricsPeriod:()V
     331: ldc2_w        #149                // double 0.3333333333333333d
     334: aload_3
     335: invokevirtual #133                // Method org/apache/hadoop/hbase/io/hfile/CacheStats.getHitRatioPastNPeriods:()D
     338: dload_1
     339: invokestatic  #134                // Method org/junit/Assert.assertEquals:(DDD)V
     342: dconst_0
     343: aload_3
     344: invokevirtual #135                // Method org/apache/hadoop/hbase/io/hfile/CacheStats.getHitCachingRatioPastNPeriods:()D
     347: dload_1
     348: invokestatic  #134                // Method org/junit/Assert.assertEquals:(DDD)V
     351: aload_3
     352: invokevirtual #132                // Method org/apache/hadoop/hbase/io/hfile/CacheStats.rollMetricsPeriod:()V
     355: ldc2_w        #139                // double 0.5d
     358: aload_3
     359: invokevirtual #133                // Method org/apache/hadoop/hbase/io/hfile/CacheStats.getHitRatioPastNPeriods:()D
     362: dload_1
     363: invokestatic  #134                // Method org/junit/Assert.assertEquals:(DDD)V
     366: dconst_0
     367: aload_3
     368: invokevirtual #135                // Method org/apache/hadoop/hbase/io/hfile/CacheStats.getHitCachingRatioPastNPeriods:()D
     371: dload_1
     372: invokestatic  #134                // Method org/junit/Assert.assertEquals:(DDD)V
     375: aload_3
     376: invokevirtual #132                // Method org/apache/hadoop/hbase/io/hfile/CacheStats.rollMetricsPeriod:()V
     379: dconst_0
     380: aload_3
     381: invokevirtual #133                // Method org/apache/hadoop/hbase/io/hfile/CacheStats.getHitRatioPastNPeriods:()D
     384: dload_1
     385: invokestatic  #134                // Method org/junit/Assert.assertEquals:(DDD)V
     388: dconst_0
     389: aload_3
     390: invokevirtual #135                // Method org/apache/hadoop/hbase/io/hfile/CacheStats.getHitCachingRatioPastNPeriods:()D
     393: dload_1
     394: invokestatic  #134                // Method org/junit/Assert.assertEquals:(DDD)V
     397: aload_3
     398: iconst_1
     399: iconst_0
     400: getstatic     #136                // Field org/apache/hadoop/hbase/io/hfile/BlockType.DATA:Lorg/apache/hadoop/hbase/io/hfile/BlockType;
     403: invokevirtual #138                // Method org/apache/hadoop/hbase/io/hfile/CacheStats.miss:(ZZLorg/apache/hadoop/hbase/io/hfile/BlockType;)V
     406: aload_3
     407: iconst_0
     408: iconst_0
     409: getstatic     #136                // Field org/apache/hadoop/hbase/io/hfile/BlockType.DATA:Lorg/apache/hadoop/hbase/io/hfile/BlockType;
     412: invokevirtual #138                // Method org/apache/hadoop/hbase/io/hfile/CacheStats.miss:(ZZLorg/apache/hadoop/hbase/io/hfile/BlockType;)V
     415: aload_3
     416: iconst_1
     417: iconst_1
     418: getstatic     #136                // Field org/apache/hadoop/hbase/io/hfile/BlockType.DATA:Lorg/apache/hadoop/hbase/io/hfile/BlockType;
     421: invokevirtual #137                // Method org/apache/hadoop/hbase/io/hfile/CacheStats.hit:(ZZLorg/apache/hadoop/hbase/io/hfile/BlockType;)V
     424: aload_3
     425: iconst_0
     426: iconst_1
     427: getstatic     #136                // Field org/apache/hadoop/hbase/io/hfile/BlockType.DATA:Lorg/apache/hadoop/hbase/io/hfile/BlockType;
     430: invokevirtual #137                // Method org/apache/hadoop/hbase/io/hfile/CacheStats.hit:(ZZLorg/apache/hadoop/hbase/io/hfile/BlockType;)V
     433: aload_3
     434: invokevirtual #132                // Method org/apache/hadoop/hbase/io/hfile/CacheStats.rollMetricsPeriod:()V
     437: ldc2_w        #139                // double 0.5d
     440: aload_3
     441: invokevirtual #133                // Method org/apache/hadoop/hbase/io/hfile/CacheStats.getHitRatioPastNPeriods:()D
     444: dload_1
     445: invokestatic  #134                // Method org/junit/Assert.assertEquals:(DDD)V
     448: ldc2_w        #139                // double 0.5d
     451: aload_3
     452: invokevirtual #135                // Method org/apache/hadoop/hbase/io/hfile/CacheStats.getHitCachingRatioPastNPeriods:()D
     455: dload_1
     456: invokestatic  #134                // Method org/junit/Assert.assertEquals:(DDD)V
     459: return

  public void testCacheBlockNextBlockMetadataMissing();
    Code:
       0: ldc2_w        #2                  // long 100000l
       3: lstore_1
       4: aload_0
       5: lload_1
       6: bipush        10
       8: invokespecial #78                 // Method calculateBlockSize:(JI)J
      11: lstore_3
      12: bipush        100
      14: istore        5
      16: bipush        33
      18: iload         5
      20: iadd
      21: istore        6
      23: iload         6
      25: newarray       byte
      27: astore        7
      29: aload         7
      31: iconst_0
      32: iload         5
      34: invokestatic  #152                // Method java/nio/ByteBuffer.wrap:([BII)Ljava/nio/ByteBuffer;
      37: astore        8
      39: new           #153                // class org/apache/hadoop/hbase/io/hfile/HFileContextBuilder
      42: dup
      43: invokespecial #154                // Method org/apache/hadoop/hbase/io/hfile/HFileContextBuilder."<init>":()V
      46: invokevirtual #155                // Method org/apache/hadoop/hbase/io/hfile/HFileContextBuilder.build:()Lorg/apache/hadoop/hbase/io/hfile/HFileContext;
      49: astore        9
      51: new           #156                // class org/apache/hadoop/hbase/io/hfile/HFileBlock
      54: dup
      55: getstatic     #136                // Field org/apache/hadoop/hbase/io/hfile/BlockType.DATA:Lorg/apache/hadoop/hbase/io/hfile/BlockType;
      58: iload         5
      60: iload         5
      62: ldc2_w        #157                // long -1l
      65: aload         8
      67: iconst_1
      68: ldc2_w        #157                // long -1l
      71: bipush        52
      73: iconst_m1
      74: aload         9
      76: invokespecial #159                // Method org/apache/hadoop/hbase/io/hfile/HFileBlock."<init>":(Lorg/apache/hadoop/hbase/io/hfile/BlockType;IIJLjava/nio/ByteBuffer;ZJIILorg/apache/hadoop/hbase/io/hfile/HFileContext;)V
      79: astore        10
      81: new           #156                // class org/apache/hadoop/hbase/io/hfile/HFileBlock
      84: dup
      85: getstatic     #136                // Field org/apache/hadoop/hbase/io/hfile/BlockType.DATA:Lorg/apache/hadoop/hbase/io/hfile/BlockType;
      88: iload         5
      90: iload         5
      92: ldc2_w        #157                // long -1l
      95: aload         8
      97: iconst_1
      98: ldc2_w        #157                // long -1l
     101: iconst_m1
     102: iconst_m1
     103: aload         9
     105: invokespecial #159                // Method org/apache/hadoop/hbase/io/hfile/HFileBlock."<init>":(Lorg/apache/hadoop/hbase/io/hfile/BlockType;IIJLjava/nio/ByteBuffer;ZJIILorg/apache/hadoop/hbase/io/hfile/HFileContext;)V
     108: astore        11
     110: new           #8                  // class org/apache/hadoop/hbase/io/hfile/LruBlockCache
     113: dup
     114: lload_1
     115: lload_3
     116: iconst_0
     117: ldc2_w        #79                 // double 1.2d
     120: lload_1
     121: l2d
     122: dmul
     123: lload_3
     124: l2d
     125: ddiv
     126: invokestatic  #81                 // Method java/lang/Math.ceil:(D)D
     129: d2i
     130: ldc           #82                 // float 0.75f
     132: bipush        16
     134: ldc           #110                // float 0.66f
     136: ldc           #70                 // float 0.99f
     138: ldc           #84                 // float 0.33f
     140: ldc           #84                 // float 0.33f
     142: ldc           #85                 // float 0.34f
     144: ldc           #86                 // float 1.2f
     146: iconst_0
     147: ldc2_w        #115                // long 1024l
     150: invokespecial #89                 // Method org/apache/hadoop/hbase/io/hfile/LruBlockCache."<init>":(JJZIFIFFFFFFZJ)V
     153: astore        12
     155: new           #160                // class org/apache/hadoop/hbase/io/hfile/BlockCacheKey
     158: dup
     159: ldc           #161                // String key1
     161: lconst_0
     162: invokespecial #162                // Method org/apache/hadoop/hbase/io/hfile/BlockCacheKey."<init>":(Ljava/lang/String;J)V
     165: astore        13
     167: iload         6
     169: invokestatic  #163                // Method java/nio/ByteBuffer.allocate:(I)Ljava/nio/ByteBuffer;
     172: astore        14
     174: iload         6
     176: invokestatic  #163                // Method java/nio/ByteBuffer.allocate:(I)Ljava/nio/ByteBuffer;
     179: astore        15
     181: iload         6
     183: invokestatic  #163                // Method java/nio/ByteBuffer.allocate:(I)Ljava/nio/ByteBuffer;
     186: astore        16
     188: aload         10
     190: aload         15
     192: iconst_1
     193: invokevirtual #164                // Method org/apache/hadoop/hbase/io/hfile/HFileBlock.serialize:(Ljava/nio/ByteBuffer;Z)V
     196: aload         11
     198: aload         16
     200: iconst_1
     201: invokevirtual #164                // Method org/apache/hadoop/hbase/io/hfile/HFileBlock.serialize:(Ljava/nio/ByteBuffer;Z)V
     204: aload         12
     206: aload         13
     208: aload         10
     210: aload         14
     212: aload         15
     214: invokestatic  #165                // Method org/apache/hadoop/hbase/io/hfile/CacheTestUtils.getBlockAndAssertEquals:(Lorg/apache/hadoop/hbase/io/hfile/BlockCache;Lorg/apache/hadoop/hbase/io/hfile/BlockCacheKey;Lorg/apache/hadoop/hbase/io/hfile/Cacheable;Ljava/nio/ByteBuffer;Ljava/nio/ByteBuffer;)V
     217: aload         12
     219: aload         13
     221: aload         11
     223: aload         14
     225: aload         15
     227: invokestatic  #165                // Method org/apache/hadoop/hbase/io/hfile/CacheTestUtils.getBlockAndAssertEquals:(Lorg/apache/hadoop/hbase/io/hfile/BlockCache;Lorg/apache/hadoop/hbase/io/hfile/BlockCacheKey;Lorg/apache/hadoop/hbase/io/hfile/Cacheable;Ljava/nio/ByteBuffer;Ljava/nio/ByteBuffer;)V
     230: aload         12
     232: invokevirtual #166                // Method org/apache/hadoop/hbase/io/hfile/LruBlockCache.clearCache:()V
     235: aload         12
     237: aload         13
     239: iconst_0
     240: iconst_0
     241: iconst_0
     242: invokevirtual #59                 // Method org/apache/hadoop/hbase/io/hfile/LruBlockCache.getBlock:(Lorg/apache/hadoop/hbase/io/hfile/BlockCacheKey;ZZZ)Lorg/apache/hadoop/hbase/io/hfile/Cacheable;
     245: invokestatic  #122                // Method org/junit/Assert.assertNull:(Ljava/lang/Object;)V
     248: aload         12
     250: aload         13
     252: aload         11
     254: aload         14
     256: aload         16
     258: invokestatic  #165                // Method org/apache/hadoop/hbase/io/hfile/CacheTestUtils.getBlockAndAssertEquals:(Lorg/apache/hadoop/hbase/io/hfile/BlockCache;Lorg/apache/hadoop/hbase/io/hfile/BlockCacheKey;Lorg/apache/hadoop/hbase/io/hfile/Cacheable;Ljava/nio/ByteBuffer;Ljava/nio/ByteBuffer;)V
     261: aload         12
     263: aload         13
     265: aload         10
     267: aload         14
     269: aload         15
     271: invokestatic  #165                // Method org/apache/hadoop/hbase/io/hfile/CacheTestUtils.getBlockAndAssertEquals:(Lorg/apache/hadoop/hbase/io/hfile/BlockCache;Lorg/apache/hadoop/hbase/io/hfile/BlockCacheKey;Lorg/apache/hadoop/hbase/io/hfile/Cacheable;Ljava/nio/ByteBuffer;Ljava/nio/ByteBuffer;)V
     274: return

  static {};
    Code:
       0: ldc           #180                // class org/apache/hadoop/hbase/io/hfile/TestLruBlockCache
       2: invokestatic  #181                // Method org/apache/hadoop/hbase/HBaseClassTestRule.forClass:(Ljava/lang/Class;)Lorg/apache/hadoop/hbase/HBaseClassTestRule;
       5: putstatic     #182                // Field CLASS_RULE:Lorg/apache/hadoop/hbase/HBaseClassTestRule;
       8: return
}
