Compiled from "TestAccessController3.java"
public class org.apache.hadoop.hbase.security.access.TestAccessController3$FaultyAccessController extends org.apache.hadoop.hbase.security.access.AccessController {
  public org.apache.hadoop.hbase.security.access.TestAccessController3$FaultyAccessController();
    Code:
       0: aload_0
       1: invokespecial #1                  // Method org/apache/hadoop/hbase/security/access/AccessController."<init>":()V
       4: return

  public void stop(org.apache.hadoop.hbase.CoprocessorEnvironment);
    Code:
       0: aload_0
       1: aload_1
       2: invokespecial #2                  // Method org/apache/hadoop/hbase/security/access/AccessController.stop:(Lorg/apache/hadoop/hbase/CoprocessorEnvironment;)V
       5: invokestatic  #3                  // Method org/apache/hadoop/hbase/security/access/TestAccessController3.access$000:()Z
       8: ifeq          16
      11: aload_0
      12: aload_1
      13: invokespecial #2                  // Method org/apache/hadoop/hbase/security/access/AccessController.stop:(Lorg/apache/hadoop/hbase/CoprocessorEnvironment;)V
      16: return
}
