Compiled from "TestSerialReplicationChecker.java"
class org.apache.hadoop.hbase.replication.regionserver.TestSerialReplicationChecker$1 implements org.mockito.stubbing.Answer<org.apache.hadoop.hbase.client.Table> {
  final org.apache.hadoop.hbase.replication.regionserver.TestSerialReplicationChecker this$0;

  org.apache.hadoop.hbase.replication.regionserver.TestSerialReplicationChecker$1(org.apache.hadoop.hbase.replication.regionserver.TestSerialReplicationChecker);
    Code:
       0: aload_0
       1: aload_1
       2: putfield      #1                  // Field this$0:Lorg/apache/hadoop/hbase/replication/regionserver/TestSerialReplicationChecker;
       5: aload_0
       6: invokespecial #2                  // Method java/lang/Object."<init>":()V
       9: return

  public org.apache.hadoop.hbase.client.Table answer(org.mockito.invocation.InvocationOnMock) throws java.lang.Throwable;
    Code:
       0: invokestatic  #3                  // Method org/apache/hadoop/hbase/replication/regionserver/TestSerialReplicationChecker.access$000:()Lorg/apache/hadoop/hbase/HBaseTestingUtility;
       3: invokevirtual #4                  // Method org/apache/hadoop/hbase/HBaseTestingUtility.getConnection:()Lorg/apache/hadoop/hbase/client/Connection;
       6: aload_1
       7: iconst_0
       8: invokeinterface #5,  2            // InterfaceMethod org/mockito/invocation/InvocationOnMock.getArgument:(I)Ljava/lang/Object;
      13: checkcast     #6                  // class org/apache/hadoop/hbase/TableName
      16: invokeinterface #7,  2            // InterfaceMethod org/apache/hadoop/hbase/client/Connection.getTable:(Lorg/apache/hadoop/hbase/TableName;)Lorg/apache/hadoop/hbase/client/Table;
      21: areturn

  public java.lang.Object answer(org.mockito.invocation.InvocationOnMock) throws java.lang.Throwable;
    Code:
       0: aload_0
       1: aload_1
       2: invokevirtual #8                  // Method answer:(Lorg/mockito/invocation/InvocationOnMock;)Lorg/apache/hadoop/hbase/client/Table;
       5: areturn
}
