Compiled from "TestMasterCoprocessorServices.java"
class org.apache.hadoop.hbase.master.TestMasterCoprocessorServices$MockVisibilityController implements org.apache.hadoop.hbase.protobuf.generated.VisibilityLabelsProtos$VisibilityLabelsService$Interface,org.apache.hadoop.hbase.coprocessor.MasterCoprocessor,org.apache.hadoop.hbase.coprocessor.RegionCoprocessor,org.apache.hadoop.hbase.coprocessor.MasterObserver,org.apache.hadoop.hbase.coprocessor.RegionObserver {
  public void addLabels(com.google.protobuf.RpcController, org.apache.hadoop.hbase.protobuf.generated.VisibilityLabelsProtos$VisibilityLabelsRequest, com.google.protobuf.RpcCallback<org.apache.hadoop.hbase.protobuf.generated.VisibilityLabelsProtos$VisibilityLabelsResponse>);
    Code:
       0: return

  public void setAuths(com.google.protobuf.RpcController, org.apache.hadoop.hbase.protobuf.generated.VisibilityLabelsProtos$SetAuthsRequest, com.google.protobuf.RpcCallback<org.apache.hadoop.hbase.protobuf.generated.VisibilityLabelsProtos$VisibilityLabelsResponse>);
    Code:
       0: return

  public void clearAuths(com.google.protobuf.RpcController, org.apache.hadoop.hbase.protobuf.generated.VisibilityLabelsProtos$SetAuthsRequest, com.google.protobuf.RpcCallback<org.apache.hadoop.hbase.protobuf.generated.VisibilityLabelsProtos$VisibilityLabelsResponse>);
    Code:
       0: return

  public void getAuths(com.google.protobuf.RpcController, org.apache.hadoop.hbase.protobuf.generated.VisibilityLabelsProtos$GetAuthsRequest, com.google.protobuf.RpcCallback<org.apache.hadoop.hbase.protobuf.generated.VisibilityLabelsProtos$GetAuthsResponse>);
    Code:
       0: return

  public void listLabels(com.google.protobuf.RpcController, org.apache.hadoop.hbase.protobuf.generated.VisibilityLabelsProtos$ListLabelsRequest, com.google.protobuf.RpcCallback<org.apache.hadoop.hbase.protobuf.generated.VisibilityLabelsProtos$ListLabelsResponse>);
    Code:
       0: return

  org.apache.hadoop.hbase.master.TestMasterCoprocessorServices$MockVisibilityController(org.apache.hadoop.hbase.master.TestMasterCoprocessorServices$1);
    Code:
       0: aload_0
       1: invokespecial #1                  // Method "<init>":()V
       4: return
}
