Compiled from "TestPrefixFilter.java"
public class org.apache.hadoop.hbase.filter.TestPrefixFilter {
  public static final org.apache.hadoop.hbase.HBaseClassTestRule CLASS_RULE;

  org.apache.hadoop.hbase.filter.Filter mainFilter;

  static final char FIRST_CHAR;

  static final char LAST_CHAR;

  static final java.lang.String HOST_PREFIX;

  static final byte[] GOOD_BYTES;

  public org.apache.hadoop.hbase.filter.TestPrefixFilter();
    Code:
       0: aload_0
       1: invokespecial #1                  // Method java/lang/Object."<init>":()V
       4: return

  public void setUp() throws java.lang.Exception;
    Code:
       0: aload_0
       1: new           #2                  // class org/apache/hadoop/hbase/filter/PrefixFilter
       4: dup
       5: ldc           #4                  // String org.apache.site-
       7: invokestatic  #5                  // Method org/apache/hadoop/hbase/util/Bytes.toBytes:(Ljava/lang/String;)[B
      10: invokespecial #6                  // Method org/apache/hadoop/hbase/filter/PrefixFilter."<init>":([B)V
      13: putfield      #7                  // Field mainFilter:Lorg/apache/hadoop/hbase/filter/Filter;
      16: return

  public void testPrefixOnRow() throws java.lang.Exception;
    Code:
       0: aload_0
       1: aload_0
       2: getfield      #7                  // Field mainFilter:Lorg/apache/hadoop/hbase/filter/Filter;
       5: invokespecial #8                  // Method prefixRowTests:(Lorg/apache/hadoop/hbase/filter/Filter;)V
       8: return

  public void testPrefixOnRowInsideWhileMatchRow() throws java.lang.Exception;
    Code:
       0: aload_0
       1: new           #9                  // class org/apache/hadoop/hbase/filter/WhileMatchFilter
       4: dup
       5: aload_0
       6: getfield      #7                  // Field mainFilter:Lorg/apache/hadoop/hbase/filter/Filter;
       9: invokespecial #10                 // Method org/apache/hadoop/hbase/filter/WhileMatchFilter."<init>":(Lorg/apache/hadoop/hbase/filter/Filter;)V
      12: iconst_1
      13: invokespecial #11                 // Method prefixRowTests:(Lorg/apache/hadoop/hbase/filter/Filter;Z)V
      16: return

  public void testSerialization() throws java.lang.Exception;
    Code:
       0: aload_0
       1: getfield      #7                  // Field mainFilter:Lorg/apache/hadoop/hbase/filter/Filter;
       4: invokevirtual #12                 // Method org/apache/hadoop/hbase/filter/Filter.toByteArray:()[B
       7: astore_1
       8: aload_1
       9: invokestatic  #13                 // Method org/apache/hadoop/hbase/filter/PrefixFilter.parseFrom:([B)Lorg/apache/hadoop/hbase/filter/PrefixFilter;
      12: astore_2
      13: aload_0
      14: aload_2
      15: invokespecial #8                  // Method prefixRowTests:(Lorg/apache/hadoop/hbase/filter/Filter;)V
      18: return

  static {};
    Code:
       0: ldc           #3                  // class org/apache/hadoop/hbase/filter/TestPrefixFilter
       2: invokestatic  #31                 // Method org/apache/hadoop/hbase/HBaseClassTestRule.forClass:(Ljava/lang/Class;)Lorg/apache/hadoop/hbase/HBaseClassTestRule;
       5: putstatic     #32                 // Field CLASS_RULE:Lorg/apache/hadoop/hbase/HBaseClassTestRule;
       8: ldc           #33                 // String abc
      10: invokestatic  #5                  // Method org/apache/hadoop/hbase/util/Bytes.toBytes:(Ljava/lang/String;)[B
      13: putstatic     #34                 // Field GOOD_BYTES:[B
      16: return
}
