Compiled from "TestTimestampsFilter.java"
public class org.apache.hadoop.hbase.client.TestTimestampsFilter {
  public static final org.apache.hadoop.hbase.HBaseClassTestRule CLASS_RULE;

  public org.junit.rules.TestName name;

  public org.apache.hadoop.hbase.client.TestTimestampsFilter();
    Code:
       0: aload_0
       1: invokespecial #1                  // Method java/lang/Object."<init>":()V
       4: aload_0
       5: new           #2                  // class org/junit/rules/TestName
       8: dup
       9: invokespecial #3                  // Method org/junit/rules/TestName."<init>":()V
      12: putfield      #4                  // Field name:Lorg/junit/rules/TestName;
      15: return

  public static void setUpBeforeClass() throws java.lang.Exception;
    Code:
       0: getstatic     #5                  // Field TEST_UTIL:Lorg/apache/hadoop/hbase/HBaseTestingUtility;
       3: invokevirtual #6                  // Method org/apache/hadoop/hbase/HBaseTestingUtility.startMiniCluster:()Lorg/apache/hadoop/hbase/MiniHBaseCluster;
       6: pop
       7: return

  public static void tearDownAfterClass() throws java.lang.Exception;
    Code:
       0: getstatic     #5                  // Field TEST_UTIL:Lorg/apache/hadoop/hbase/HBaseTestingUtility;
       3: invokevirtual #7                  // Method org/apache/hadoop/hbase/HBaseTestingUtility.shutdownMiniCluster:()V
       6: return

  public void setUp() throws java.lang.Exception;
    Code:
       0: return

  public void tearDown() throws java.lang.Exception;
    Code:
       0: return

  public void testTimestampsFilter() throws java.lang.Exception;
    Code:
       0: aload_0
       1: getfield      #4                  // Field name:Lorg/junit/rules/TestName;
       4: invokevirtual #8                  // Method org/junit/rules/TestName.getMethodName:()Ljava/lang/String;
       7: invokestatic  #9                  // Method org/apache/hadoop/hbase/util/Bytes.toBytes:(Ljava/lang/String;)[B
      10: astore_1
      11: ldc           #10                 // String event_log
      13: invokestatic  #9                  // Method org/apache/hadoop/hbase/util/Bytes.toBytes:(Ljava/lang/String;)[B
      16: astore_2
      17: iconst_1
      18: anewarray     #11                 // class "[B"
      21: dup
      22: iconst_0
      23: aload_2
      24: aastore
      25: astore_3
      26: getstatic     #5                  // Field TEST_UTIL:Lorg/apache/hadoop/hbase/HBaseTestingUtility;
      29: aload_1
      30: invokestatic  #12                 // Method org/apache/hadoop/hbase/TableName.valueOf:([B)Lorg/apache/hadoop/hbase/TableName;
      33: aload_3
      34: ldc           #14                 // int 2147483647
      36: invokevirtual #15                 // Method org/apache/hadoop/hbase/HBaseTestingUtility.createTable:(Lorg/apache/hadoop/hbase/TableName;[[BI)Lorg/apache/hadoop/hbase/client/Table;
      39: astore        5
      41: iconst_0
      42: istore        6
      44: iload         6
      46: iconst_5
      47: if_icmpge     103
      50: iconst_0
      51: istore        7
      53: iload         7
      55: iconst_5
      56: if_icmpge     97
      59: aload_0
      60: aload         5
      62: aload_2
      63: iload         6
      65: iload         7
      67: ldc2_w        #16                 // long 201l
      70: ldc2_w        #18                 // long 300l
      73: invokespecial #20                 // Method putNVersions:(Lorg/apache/hadoop/hbase/client/Table;[BIIJJ)V
      76: aload_0
      77: aload         5
      79: aload_2
      80: iload         6
      82: iload         7
      84: lconst_1
      85: ldc2_w        #21                 // long 100l
      88: invokespecial #20                 // Method putNVersions:(Lorg/apache/hadoop/hbase/client/Table;[BIIJJ)V
      91: iinc          7, 1
      94: goto          53
      97: iinc          6, 1
     100: goto          44
     103: aload_0
     104: aload         5
     106: aload_2
     107: invokespecial #23                 // Method verifyInsertedValues:(Lorg/apache/hadoop/hbase/client/Table;[B)V
     110: getstatic     #5                  // Field TEST_UTIL:Lorg/apache/hadoop/hbase/HBaseTestingUtility;
     113: invokevirtual #24                 // Method org/apache/hadoop/hbase/HBaseTestingUtility.flush:()V
     116: aload_0
     117: aload         5
     119: aload_2
     120: invokespecial #23                 // Method verifyInsertedValues:(Lorg/apache/hadoop/hbase/client/Table;[B)V
     123: iconst_0
     124: istore        6
     126: iload         6
     128: iconst_5
     129: if_icmpge     187
     132: iconst_0
     133: istore        7
     135: iload         7
     137: iconst_5
     138: if_icmpge     181
     141: aload_0
     142: aload         5
     144: aload_2
     145: iload         6
     147: iload         7
     149: ldc2_w        #25                 // long 301l
     152: ldc2_w        #27                 // long 400l
     155: invokespecial #20                 // Method putNVersions:(Lorg/apache/hadoop/hbase/client/Table;[BIIJJ)V
     158: aload_0
     159: aload         5
     161: aload_2
     162: iload         6
     164: iload         7
     166: ldc2_w        #29                 // long 101l
     169: ldc2_w        #31                 // long 200l
     172: invokespecial #20                 // Method putNVersions:(Lorg/apache/hadoop/hbase/client/Table;[BIIJJ)V
     175: iinc          7, 1
     178: goto          135
     181: iinc          6, 1
     184: goto          126
     187: iconst_0
     188: istore        6
     190: iload         6
     192: iconst_5
     193: if_icmpge     356
     196: iconst_0
     197: istore        7
     199: iload         7
     201: iconst_5
     202: if_icmpge     350
     205: aload_0
     206: aload         5
     208: aload_2
     209: iload         6
     211: iload         7
     213: iconst_5
     214: anewarray     #33                 // class java/lang/Long
     217: dup
     218: iconst_0
     219: ldc2_w        #34                 // long 505l
     222: invokestatic  #36                 // Method java/lang/Long.valueOf:(J)Ljava/lang/Long;
     225: aastore
     226: dup
     227: iconst_1
     228: ldc2_w        #37                 // long 5l
     231: invokestatic  #36                 // Method java/lang/Long.valueOf:(J)Ljava/lang/Long;
     234: aastore
     235: dup
     236: iconst_2
     237: ldc2_w        #39                 // long 105l
     240: invokestatic  #36                 // Method java/lang/Long.valueOf:(J)Ljava/lang/Long;
     243: aastore
     244: dup
     245: iconst_3
     246: ldc2_w        #41                 // long 305l
     249: invokestatic  #36                 // Method java/lang/Long.valueOf:(J)Ljava/lang/Long;
     252: aastore
     253: dup
     254: iconst_4
     255: ldc2_w        #43                 // long 205l
     258: invokestatic  #36                 // Method java/lang/Long.valueOf:(J)Ljava/lang/Long;
     261: aastore
     262: invokestatic  #45                 // Method java/util/Arrays.asList:([Ljava/lang/Object;)Ljava/util/List;
     265: invokespecial #46                 // Method getNVersions:(Lorg/apache/hadoop/hbase/client/Table;[BIILjava/util/List;)[Lorg/apache/hadoop/hbase/Cell;
     268: astore        4
     270: ldc2_w        #47                 // long 4l
     273: aload         4
     275: arraylength
     276: i2l
     277: invokestatic  #49                 // Method org/junit/Assert.assertEquals:(JJ)V
     280: aload_0
     281: aload         4
     283: iconst_0
     284: aaload
     285: aload_2
     286: iload         6
     288: iload         7
     290: ldc2_w        #41                 // long 305l
     293: invokespecial #50                 // Method checkOneCell:(Lorg/apache/hadoop/hbase/Cell;[BIIJ)V
     296: aload_0
     297: aload         4
     299: iconst_1
     300: aaload
     301: aload_2
     302: iload         6
     304: iload         7
     306: ldc2_w        #43                 // long 205l
     309: invokespecial #50                 // Method checkOneCell:(Lorg/apache/hadoop/hbase/Cell;[BIIJ)V
     312: aload_0
     313: aload         4
     315: iconst_2
     316: aaload
     317: aload_2
     318: iload         6
     320: iload         7
     322: ldc2_w        #39                 // long 105l
     325: invokespecial #50                 // Method checkOneCell:(Lorg/apache/hadoop/hbase/Cell;[BIIJ)V
     328: aload_0
     329: aload         4
     331: iconst_3
     332: aaload
     333: aload_2
     334: iload         6
     336: iload         7
     338: ldc2_w        #37                 // long 5l
     341: invokespecial #50                 // Method checkOneCell:(Lorg/apache/hadoop/hbase/Cell;[BIIJ)V
     344: iinc          7, 1
     347: goto          199
     350: iinc          6, 1
     353: goto          190
     356: aload_0
     357: aload         5
     359: aload_2
     360: iconst_2
     361: iconst_2
     362: new           #51                 // class java/util/ArrayList
     365: dup
     366: invokespecial #52                 // Method java/util/ArrayList."<init>":()V
     369: invokespecial #46                 // Method getNVersions:(Lorg/apache/hadoop/hbase/client/Table;[BIILjava/util/List;)[Lorg/apache/hadoop/hbase/Cell;
     372: astore        4
     374: lconst_0
     375: aload         4
     377: ifnonnull     384
     380: lconst_0
     381: goto          388
     384: aload         4
     386: arraylength
     387: i2l
     388: invokestatic  #49                 // Method org/junit/Assert.assertEquals:(JJ)V
     391: aload_0
     392: aload         5
     394: aload_2
     395: iconst_0
     396: iconst_4
     397: iconst_3
     398: anewarray     #33                 // class java/lang/Long
     401: dup
     402: iconst_0
     403: ldc2_w        #53                 // long 6l
     406: invokestatic  #36                 // Method java/lang/Long.valueOf:(J)Ljava/lang/Long;
     409: aastore
     410: dup
     411: iconst_1
     412: ldc2_w        #55                 // long 106l
     415: invokestatic  #36                 // Method java/lang/Long.valueOf:(J)Ljava/lang/Long;
     418: aastore
     419: dup
     420: iconst_2
     421: ldc2_w        #57                 // long 306l
     424: invokestatic  #36                 // Method java/lang/Long.valueOf:(J)Ljava/lang/Long;
     427: aastore
     428: invokestatic  #45                 // Method java/util/Arrays.asList:([Ljava/lang/Object;)Ljava/util/List;
     431: invokespecial #59                 // Method scanNVersions:(Lorg/apache/hadoop/hbase/client/Table;[BIILjava/util/List;)[Lorg/apache/hadoop/hbase/client/Result;
     434: astore        6
     436: ldc           #60                 // String # of rows returned from scan
     438: ldc2_w        #37                 // long 5l
     441: aload         6
     443: arraylength
     444: i2l
     445: invokestatic  #61                 // Method org/junit/Assert.assertEquals:(Ljava/lang/String;JJ)V
     448: iconst_0
     449: istore        7
     451: iload         7
     453: iconst_5
     454: if_icmpge     581
     457: aload         6
     459: iload         7
     461: aaload
     462: invokevirtual #62                 // Method org/apache/hadoop/hbase/client/Result.rawCells:()[Lorg/apache/hadoop/hbase/Cell;
     465: astore        4
     467: new           #63                 // class java/lang/StringBuilder
     470: dup
     471: invokespecial #64                 // Method java/lang/StringBuilder."<init>":()V
     474: ldc           #65                 // String Number of KeyValues in result for row:
     476: invokevirtual #66                 // Method java/lang/StringBuilder.append:(Ljava/lang/String;)Ljava/lang/StringBuilder;
     479: iload         7
     481: invokevirtual #67                 // Method java/lang/StringBuilder.append:(I)Ljava/lang/StringBuilder;
     484: invokevirtual #68                 // Method java/lang/StringBuilder.toString:()Ljava/lang/String;
     487: ldc2_w        #69                 // long 15l
     490: aload         4
     492: arraylength
     493: i2l
     494: invokestatic  #61                 // Method org/junit/Assert.assertEquals:(Ljava/lang/String;JJ)V
     497: iconst_0
     498: istore        8
     500: iload         8
     502: iconst_5
     503: if_icmpge     575
     506: iload         8
     508: iconst_3
     509: imul
     510: istore        9
     512: aload_0
     513: aload         4
     515: iload         9
     517: iconst_0
     518: iadd
     519: aaload
     520: aload_2
     521: iload         7
     523: iload         8
     525: ldc2_w        #57                 // long 306l
     528: invokespecial #50                 // Method checkOneCell:(Lorg/apache/hadoop/hbase/Cell;[BIIJ)V
     531: aload_0
     532: aload         4
     534: iload         9
     536: iconst_1
     537: iadd
     538: aaload
     539: aload_2
     540: iload         7
     542: iload         8
     544: ldc2_w        #55                 // long 106l
     547: invokespecial #50                 // Method checkOneCell:(Lorg/apache/hadoop/hbase/Cell;[BIIJ)V
     550: aload_0
     551: aload         4
     553: iload         9
     555: iconst_2
     556: iadd
     557: aaload
     558: aload_2
     559: iload         7
     561: iload         8
     563: ldc2_w        #53                 // long 6l
     566: invokespecial #50                 // Method checkOneCell:(Lorg/apache/hadoop/hbase/Cell;[BIIJ)V
     569: iinc          8, 1
     572: goto          500
     575: iinc          7, 1
     578: goto          451
     581: aload         5
     583: invokeinterface #71,  1           // InterfaceMethod org/apache/hadoop/hbase/client/Table.close:()V
     588: return

  public void testMultiColumns() throws java.lang.Exception;
    Code:
       0: aload_0
       1: getfield      #4                  // Field name:Lorg/junit/rules/TestName;
       4: invokevirtual #8                  // Method org/junit/rules/TestName.getMethodName:()Ljava/lang/String;
       7: invokestatic  #9                  // Method org/apache/hadoop/hbase/util/Bytes.toBytes:(Ljava/lang/String;)[B
      10: astore_1
      11: ldc           #10                 // String event_log
      13: invokestatic  #9                  // Method org/apache/hadoop/hbase/util/Bytes.toBytes:(Ljava/lang/String;)[B
      16: astore_2
      17: iconst_1
      18: anewarray     #11                 // class "[B"
      21: dup
      22: iconst_0
      23: aload_2
      24: aastore
      25: astore_3
      26: getstatic     #5                  // Field TEST_UTIL:Lorg/apache/hadoop/hbase/HBaseTestingUtility;
      29: aload_1
      30: invokestatic  #12                 // Method org/apache/hadoop/hbase/TableName.valueOf:([B)Lorg/apache/hadoop/hbase/TableName;
      33: aload_3
      34: ldc           #14                 // int 2147483647
      36: invokevirtual #15                 // Method org/apache/hadoop/hbase/HBaseTestingUtility.createTable:(Lorg/apache/hadoop/hbase/TableName;[[BI)Lorg/apache/hadoop/hbase/client/Table;
      39: astore        4
      41: new           #72                 // class org/apache/hadoop/hbase/client/Put
      44: dup
      45: ldc           #73                 // String row
      47: invokestatic  #9                  // Method org/apache/hadoop/hbase/util/Bytes.toBytes:(Ljava/lang/String;)[B
      50: invokespecial #74                 // Method org/apache/hadoop/hbase/client/Put."<init>":([B)V
      53: astore        5
      55: aload         5
      57: aload_2
      58: ldc           #75                 // String column0
      60: invokestatic  #9                  // Method org/apache/hadoop/hbase/util/Bytes.toBytes:(Ljava/lang/String;)[B
      63: ldc2_w        #76                 // long 3l
      66: ldc           #78                 // String value0-3
      68: invokestatic  #9                  // Method org/apache/hadoop/hbase/util/Bytes.toBytes:(Ljava/lang/String;)[B
      71: invokevirtual #79                 // Method org/apache/hadoop/hbase/client/Put.addColumn:([B[BJ[B)Lorg/apache/hadoop/hbase/client/Put;
      74: pop
      75: aload         5
      77: aload_2
      78: ldc           #80                 // String column1
      80: invokestatic  #9                  // Method org/apache/hadoop/hbase/util/Bytes.toBytes:(Ljava/lang/String;)[B
      83: ldc2_w        #76                 // long 3l
      86: ldc           #81                 // String value1-3
      88: invokestatic  #9                  // Method org/apache/hadoop/hbase/util/Bytes.toBytes:(Ljava/lang/String;)[B
      91: invokevirtual #79                 // Method org/apache/hadoop/hbase/client/Put.addColumn:([B[BJ[B)Lorg/apache/hadoop/hbase/client/Put;
      94: pop
      95: aload         5
      97: aload_2
      98: ldc           #82                 // String column2
     100: invokestatic  #9                  // Method org/apache/hadoop/hbase/util/Bytes.toBytes:(Ljava/lang/String;)[B
     103: lconst_1
     104: ldc           #83                 // String value2-1
     106: invokestatic  #9                  // Method org/apache/hadoop/hbase/util/Bytes.toBytes:(Ljava/lang/String;)[B
     109: invokevirtual #79                 // Method org/apache/hadoop/hbase/client/Put.addColumn:([B[BJ[B)Lorg/apache/hadoop/hbase/client/Put;
     112: pop
     113: aload         5
     115: aload_2
     116: ldc           #82                 // String column2
     118: invokestatic  #9                  // Method org/apache/hadoop/hbase/util/Bytes.toBytes:(Ljava/lang/String;)[B
     121: ldc2_w        #84                 // long 2l
     124: ldc           #86                 // String value2-2
     126: invokestatic  #9                  // Method org/apache/hadoop/hbase/util/Bytes.toBytes:(Ljava/lang/String;)[B
     129: invokevirtual #79                 // Method org/apache/hadoop/hbase/client/Put.addColumn:([B[BJ[B)Lorg/apache/hadoop/hbase/client/Put;
     132: pop
     133: aload         5
     135: aload_2
     136: ldc           #82                 // String column2
     138: invokestatic  #9                  // Method org/apache/hadoop/hbase/util/Bytes.toBytes:(Ljava/lang/String;)[B
     141: ldc2_w        #76                 // long 3l
     144: ldc           #87                 // String value2-3
     146: invokestatic  #9                  // Method org/apache/hadoop/hbase/util/Bytes.toBytes:(Ljava/lang/String;)[B
     149: invokevirtual #79                 // Method org/apache/hadoop/hbase/client/Put.addColumn:([B[BJ[B)Lorg/apache/hadoop/hbase/client/Put;
     152: pop
     153: aload         5
     155: aload_2
     156: ldc           #88                 // String column3
     158: invokestatic  #9                  // Method org/apache/hadoop/hbase/util/Bytes.toBytes:(Ljava/lang/String;)[B
     161: ldc2_w        #84                 // long 2l
     164: ldc           #89                 // String value3-2
     166: invokestatic  #9                  // Method org/apache/hadoop/hbase/util/Bytes.toBytes:(Ljava/lang/String;)[B
     169: invokevirtual #79                 // Method org/apache/hadoop/hbase/client/Put.addColumn:([B[BJ[B)Lorg/apache/hadoop/hbase/client/Put;
     172: pop
     173: aload         5
     175: aload_2
     176: ldc           #90                 // String column4
     178: invokestatic  #9                  // Method org/apache/hadoop/hbase/util/Bytes.toBytes:(Ljava/lang/String;)[B
     181: lconst_1
     182: ldc           #91                 // String value4-1
     184: invokestatic  #9                  // Method org/apache/hadoop/hbase/util/Bytes.toBytes:(Ljava/lang/String;)[B
     187: invokevirtual #79                 // Method org/apache/hadoop/hbase/client/Put.addColumn:([B[BJ[B)Lorg/apache/hadoop/hbase/client/Put;
     190: pop
     191: aload         5
     193: aload_2
     194: ldc           #90                 // String column4
     196: invokestatic  #9                  // Method org/apache/hadoop/hbase/util/Bytes.toBytes:(Ljava/lang/String;)[B
     199: ldc2_w        #84                 // long 2l
     202: ldc           #92                 // String value4-2
     204: invokestatic  #9                  // Method org/apache/hadoop/hbase/util/Bytes.toBytes:(Ljava/lang/String;)[B
     207: invokevirtual #79                 // Method org/apache/hadoop/hbase/client/Put.addColumn:([B[BJ[B)Lorg/apache/hadoop/hbase/client/Put;
     210: pop
     211: aload         5
     213: aload_2
     214: ldc           #90                 // String column4
     216: invokestatic  #9                  // Method org/apache/hadoop/hbase/util/Bytes.toBytes:(Ljava/lang/String;)[B
     219: ldc2_w        #76                 // long 3l
     222: ldc           #93                 // String value4-3
     224: invokestatic  #9                  // Method org/apache/hadoop/hbase/util/Bytes.toBytes:(Ljava/lang/String;)[B
     227: invokevirtual #79                 // Method org/apache/hadoop/hbase/client/Put.addColumn:([B[BJ[B)Lorg/apache/hadoop/hbase/client/Put;
     230: pop
     231: aload         4
     233: aload         5
     235: invokeinterface #94,  2           // InterfaceMethod org/apache/hadoop/hbase/client/Table.put:(Lorg/apache/hadoop/hbase/client/Put;)V
     240: new           #51                 // class java/util/ArrayList
     243: dup
     244: invokespecial #52                 // Method java/util/ArrayList."<init>":()V
     247: astore        6
     249: aload         6
     251: new           #33                 // class java/lang/Long
     254: dup
     255: ldc2_w        #76                 // long 3l
     258: invokespecial #95                 // Method java/lang/Long."<init>":(J)V
     261: invokevirtual #96                 // Method java/util/ArrayList.add:(Ljava/lang/Object;)Z
     264: pop
     265: new           #97                 // class org/apache/hadoop/hbase/filter/TimestampsFilter
     268: dup
     269: aload         6
     271: invokespecial #98                 // Method org/apache/hadoop/hbase/filter/TimestampsFilter."<init>":(Ljava/util/List;)V
     274: astore        7
     276: new           #99                 // class org/apache/hadoop/hbase/client/Get
     279: dup
     280: ldc           #73                 // String row
     282: invokestatic  #9                  // Method org/apache/hadoop/hbase/util/Bytes.toBytes:(Ljava/lang/String;)[B
     285: invokespecial #100                // Method org/apache/hadoop/hbase/client/Get."<init>":([B)V
     288: astore        8
     290: aload         8
     292: aload         7
     294: invokevirtual #101                // Method org/apache/hadoop/hbase/client/Get.setFilter:(Lorg/apache/hadoop/hbase/filter/Filter;)Lorg/apache/hadoop/hbase/client/Get;
     297: pop
     298: aload         8
     300: invokevirtual #102                // Method org/apache/hadoop/hbase/client/Get.readAllVersions:()Lorg/apache/hadoop/hbase/client/Get;
     303: pop
     304: aload         8
     306: aload_2
     307: ldc           #82                 // String column2
     309: invokestatic  #9                  // Method org/apache/hadoop/hbase/util/Bytes.toBytes:(Ljava/lang/String;)[B
     312: invokevirtual #103                // Method org/apache/hadoop/hbase/client/Get.addColumn:([B[B)Lorg/apache/hadoop/hbase/client/Get;
     315: pop
     316: aload         8
     318: aload_2
     319: ldc           #90                 // String column4
     321: invokestatic  #9                  // Method org/apache/hadoop/hbase/util/Bytes.toBytes:(Ljava/lang/String;)[B
     324: invokevirtual #103                // Method org/apache/hadoop/hbase/client/Get.addColumn:([B[B)Lorg/apache/hadoop/hbase/client/Get;
     327: pop
     328: aload         4
     330: aload         8
     332: invokeinterface #104,  2          // InterfaceMethod org/apache/hadoop/hbase/client/Table.get:(Lorg/apache/hadoop/hbase/client/Get;)Lorg/apache/hadoop/hbase/client/Result;
     337: astore        9
     339: aload         9
     341: invokevirtual #105                // Method org/apache/hadoop/hbase/client/Result.listCells:()Ljava/util/List;
     344: invokeinterface #106,  1          // InterfaceMethod java/util/List.iterator:()Ljava/util/Iterator;
     349: astore        10
     351: aload         10
     353: invokeinterface #107,  1          // InterfaceMethod java/util/Iterator.hasNext:()Z
     358: ifeq          440
     361: aload         10
     363: invokeinterface #108,  1          // InterfaceMethod java/util/Iterator.next:()Ljava/lang/Object;
     368: checkcast     #109                // class org/apache/hadoop/hbase/Cell
     371: astore        11
     373: getstatic     #110                // Field java/lang/System.out:Ljava/io/PrintStream;
     376: new           #63                 // class java/lang/StringBuilder
     379: dup
     380: invokespecial #64                 // Method java/lang/StringBuilder."<init>":()V
     383: ldc           #111                // String found row
     385: invokevirtual #66                 // Method java/lang/StringBuilder.append:(Ljava/lang/String;)Ljava/lang/StringBuilder;
     388: aload         11
     390: invokestatic  #112                // Method org/apache/hadoop/hbase/CellUtil.cloneRow:(Lorg/apache/hadoop/hbase/Cell;)[B
     393: invokestatic  #113                // Method org/apache/hadoop/hbase/util/Bytes.toString:([B)Ljava/lang/String;
     396: invokevirtual #66                 // Method java/lang/StringBuilder.append:(Ljava/lang/String;)Ljava/lang/StringBuilder;
     399: ldc           #114                // String , column
     401: invokevirtual #66                 // Method java/lang/StringBuilder.append:(Ljava/lang/String;)Ljava/lang/StringBuilder;
     404: aload         11
     406: invokestatic  #115                // Method org/apache/hadoop/hbase/CellUtil.cloneQualifier:(Lorg/apache/hadoop/hbase/Cell;)[B
     409: invokestatic  #113                // Method org/apache/hadoop/hbase/util/Bytes.toString:([B)Ljava/lang/String;
     412: invokevirtual #66                 // Method java/lang/StringBuilder.append:(Ljava/lang/String;)Ljava/lang/StringBuilder;
     415: ldc           #116                // String , value
     417: invokevirtual #66                 // Method java/lang/StringBuilder.append:(Ljava/lang/String;)Ljava/lang/StringBuilder;
     420: aload         11
     422: invokestatic  #117                // Method org/apache/hadoop/hbase/CellUtil.cloneValue:(Lorg/apache/hadoop/hbase/Cell;)[B
     425: invokestatic  #113                // Method org/apache/hadoop/hbase/util/Bytes.toString:([B)Ljava/lang/String;
     428: invokevirtual #66                 // Method java/lang/StringBuilder.append:(Ljava/lang/String;)Ljava/lang/StringBuilder;
     431: invokevirtual #68                 // Method java/lang/StringBuilder.toString:()Ljava/lang/String;
     434: invokevirtual #118                // Method java/io/PrintStream.println:(Ljava/lang/String;)V
     437: goto          351
     440: ldc2_w        #84                 // long 2l
     443: aload         9
     445: invokevirtual #105                // Method org/apache/hadoop/hbase/client/Result.listCells:()Ljava/util/List;
     448: invokeinterface #119,  1          // InterfaceMethod java/util/List.size:()I
     453: i2l
     454: invokestatic  #49                 // Method org/junit/Assert.assertEquals:(JJ)V
     457: aload         9
     459: invokevirtual #105                // Method org/apache/hadoop/hbase/client/Result.listCells:()Ljava/util/List;
     462: iconst_0
     463: invokeinterface #120,  2          // InterfaceMethod java/util/List.get:(I)Ljava/lang/Object;
     468: checkcast     #109                // class org/apache/hadoop/hbase/Cell
     471: ldc           #87                 // String value2-3
     473: invokestatic  #9                  // Method org/apache/hadoop/hbase/util/Bytes.toBytes:(Ljava/lang/String;)[B
     476: invokestatic  #121                // Method org/apache/hadoop/hbase/CellUtil.matchingValue:(Lorg/apache/hadoop/hbase/Cell;[B)Z
     479: invokestatic  #122                // Method org/junit/Assert.assertTrue:(Z)V
     482: aload         9
     484: invokevirtual #105                // Method org/apache/hadoop/hbase/client/Result.listCells:()Ljava/util/List;
     487: iconst_1
     488: invokeinterface #120,  2          // InterfaceMethod java/util/List.get:(I)Ljava/lang/Object;
     493: checkcast     #109                // class org/apache/hadoop/hbase/Cell
     496: ldc           #93                 // String value4-3
     498: invokestatic  #9                  // Method org/apache/hadoop/hbase/util/Bytes.toBytes:(Ljava/lang/String;)[B
     501: invokestatic  #121                // Method org/apache/hadoop/hbase/CellUtil.matchingValue:(Lorg/apache/hadoop/hbase/Cell;[B)Z
     504: invokestatic  #122                // Method org/junit/Assert.assertTrue:(Z)V
     507: aload         4
     509: invokeinterface #71,  1           // InterfaceMethod org/apache/hadoop/hbase/client/Table.close:()V
     514: return

  public void testWithVersionDeletes() throws java.lang.Exception;
    Code:
       0: aload_0
       1: iconst_0
       2: invokespecial #123                // Method testWithVersionDeletes:(Z)V
       5: aload_0
       6: iconst_1
       7: invokespecial #123                // Method testWithVersionDeletes:(Z)V
      10: return

  static {};
    Code:
       0: ldc           #163                // class org/apache/hadoop/hbase/client/TestTimestampsFilter
       2: invokestatic  #164                // Method org/apache/hadoop/hbase/HBaseClassTestRule.forClass:(Ljava/lang/Class;)Lorg/apache/hadoop/hbase/HBaseClassTestRule;
       5: putstatic     #165                // Field CLASS_RULE:Lorg/apache/hadoop/hbase/HBaseClassTestRule;
       8: ldc           #163                // class org/apache/hadoop/hbase/client/TestTimestampsFilter
      10: invokestatic  #166                // Method org/slf4j/LoggerFactory.getLogger:(Ljava/lang/Class;)Lorg/slf4j/Logger;
      13: putstatic     #167                // Field LOG:Lorg/slf4j/Logger;
      16: new           #168                // class org/apache/hadoop/hbase/HBaseTestingUtility
      19: dup
      20: invokespecial #169                // Method org/apache/hadoop/hbase/HBaseTestingUtility."<init>":()V
      23: putstatic     #5                  // Field TEST_UTIL:Lorg/apache/hadoop/hbase/HBaseTestingUtility;
      26: return
}
