Compiled from "TestAsyncAdminBase.java"
public abstract class org.apache.hadoop.hbase.client.TestAsyncAdminBase {
  protected static final org.slf4j.Logger LOG;

  protected static final org.apache.hadoop.hbase.HBaseTestingUtility TEST_UTIL;

  protected static final byte[] FAMILY;

  protected static final byte[] FAMILY_0;

  protected static final byte[] FAMILY_1;

  protected static org.apache.hadoop.hbase.client.AsyncConnection ASYNC_CONN;

  protected org.apache.hadoop.hbase.client.AsyncAdmin admin;

  public java.util.function.Supplier<org.apache.hadoop.hbase.client.AsyncAdmin> getAdmin;

  public org.junit.rules.TestName testName;

  protected org.apache.hadoop.hbase.TableName tableName;

  public org.apache.hadoop.hbase.client.TestAsyncAdminBase();
    Code:
       0: aload_0
       1: invokespecial #2                  // Method java/lang/Object."<init>":()V
       4: aload_0
       5: new           #3                  // class org/junit/rules/TestName
       8: dup
       9: invokespecial #4                  // Method org/junit/rules/TestName."<init>":()V
      12: putfield      #5                  // Field testName:Lorg/junit/rules/TestName;
      15: return

  public static java.util.List<java.lang.Object[]> params();
    Code:
       0: iconst_2
       1: anewarray     #10                 // class "[Ljava/lang/Object;"
       4: dup
       5: iconst_0
       6: iconst_1
       7: anewarray     #11                 // class java/util/function/Supplier
      10: dup
      11: iconst_0
      12: invokedynamic #12,  0             // InvokeDynamic #0:get:()Ljava/util/function/Supplier;
      17: aastore
      18: aastore
      19: dup
      20: iconst_1
      21: iconst_1
      22: anewarray     #11                 // class java/util/function/Supplier
      25: dup
      26: iconst_0
      27: invokedynamic #13,  0             // InvokeDynamic #1:get:()Ljava/util/function/Supplier;
      32: aastore
      33: aastore
      34: invokestatic  #14                 // Method java/util/Arrays.asList:([Ljava/lang/Object;)Ljava/util/List;
      37: areturn

  public static void setUpBeforeClass() throws java.lang.Exception;
    Code:
       0: getstatic     #15                 // Field TEST_UTIL:Lorg/apache/hadoop/hbase/HBaseTestingUtility;
       3: invokevirtual #16                 // Method org/apache/hadoop/hbase/HBaseTestingUtility.getConfiguration:()Lorg/apache/hadoop/conf/Configuration;
       6: ldc           #18                 // String hbase.rpc.timeout
       8: ldc           #19                 // int 60000
      10: invokevirtual #20                 // Method org/apache/hadoop/conf/Configuration.setInt:(Ljava/lang/String;I)V
      13: getstatic     #15                 // Field TEST_UTIL:Lorg/apache/hadoop/hbase/HBaseTestingUtility;
      16: invokevirtual #16                 // Method org/apache/hadoop/hbase/HBaseTestingUtility.getConfiguration:()Lorg/apache/hadoop/conf/Configuration;
      19: ldc           #21                 // String hbase.client.operation.timeout
      21: ldc           #22                 // int 120000
      23: invokevirtual #20                 // Method org/apache/hadoop/conf/Configuration.setInt:(Ljava/lang/String;I)V
      26: getstatic     #15                 // Field TEST_UTIL:Lorg/apache/hadoop/hbase/HBaseTestingUtility;
      29: invokevirtual #16                 // Method org/apache/hadoop/hbase/HBaseTestingUtility.getConfiguration:()Lorg/apache/hadoop/conf/Configuration;
      32: ldc           #23                 // String hbase.client.retries.number
      34: iconst_2
      35: invokevirtual #20                 // Method org/apache/hadoop/conf/Configuration.setInt:(Ljava/lang/String;I)V
      38: getstatic     #15                 // Field TEST_UTIL:Lorg/apache/hadoop/hbase/HBaseTestingUtility;
      41: invokevirtual #16                 // Method org/apache/hadoop/hbase/HBaseTestingUtility.getConfiguration:()Lorg/apache/hadoop/conf/Configuration;
      44: ldc           #24                 // String hbase.client.start.log.errors.counter
      46: iconst_0
      47: invokevirtual #20                 // Method org/apache/hadoop/conf/Configuration.setInt:(Ljava/lang/String;I)V
      50: getstatic     #15                 // Field TEST_UTIL:Lorg/apache/hadoop/hbase/HBaseTestingUtility;
      53: iconst_2
      54: invokevirtual #25                 // Method org/apache/hadoop/hbase/HBaseTestingUtility.startMiniCluster:(I)Lorg/apache/hadoop/hbase/MiniHBaseCluster;
      57: pop
      58: getstatic     #15                 // Field TEST_UTIL:Lorg/apache/hadoop/hbase/HBaseTestingUtility;
      61: invokevirtual #16                 // Method org/apache/hadoop/hbase/HBaseTestingUtility.getConfiguration:()Lorg/apache/hadoop/conf/Configuration;
      64: invokestatic  #26                 // Method org/apache/hadoop/hbase/client/ConnectionFactory.createAsyncConnection:(Lorg/apache/hadoop/conf/Configuration;)Ljava/util/concurrent/CompletableFuture;
      67: invokevirtual #27                 // Method java/util/concurrent/CompletableFuture.get:()Ljava/lang/Object;
      70: checkcast     #28                 // class org/apache/hadoop/hbase/client/AsyncConnection
      73: putstatic     #6                  // Field ASYNC_CONN:Lorg/apache/hadoop/hbase/client/AsyncConnection;
      76: return

  public static void tearDownAfterClass() throws java.lang.Exception;
    Code:
       0: getstatic     #6                  // Field ASYNC_CONN:Lorg/apache/hadoop/hbase/client/AsyncConnection;
       3: invokestatic  #29                 // Method org/apache/commons/io/IOUtils.closeQuietly:(Ljava/io/Closeable;)V
       6: getstatic     #15                 // Field TEST_UTIL:Lorg/apache/hadoop/hbase/HBaseTestingUtility;
       9: invokevirtual #30                 // Method org/apache/hadoop/hbase/HBaseTestingUtility.shutdownMiniCluster:()V
      12: return

  public void setUp() throws java.lang.Exception;
    Code:
       0: aload_0
       1: aload_0
       2: getfield      #31                 // Field getAdmin:Ljava/util/function/Supplier;
       5: invokeinterface #32,  1           // InterfaceMethod java/util/function/Supplier.get:()Ljava/lang/Object;
      10: checkcast     #33                 // class org/apache/hadoop/hbase/client/AsyncAdmin
      13: putfield      #34                 // Field admin:Lorg/apache/hadoop/hbase/client/AsyncAdmin;
      16: aload_0
      17: getfield      #5                  // Field testName:Lorg/junit/rules/TestName;
      20: invokevirtual #35                 // Method org/junit/rules/TestName.getMethodName:()Ljava/lang/String;
      23: astore_1
      24: aload_0
      25: aload_1
      26: iconst_0
      27: aload_1
      28: invokevirtual #36                 // Method java/lang/String.length:()I
      31: iconst_3
      32: isub
      33: invokevirtual #37                 // Method java/lang/String.substring:(II)Ljava/lang/String;
      36: invokestatic  #38                 // Method org/apache/hadoop/hbase/TableName.valueOf:(Ljava/lang/String;)Lorg/apache/hadoop/hbase/TableName;
      39: putfield      #39                 // Field tableName:Lorg/apache/hadoop/hbase/TableName;
      42: return

  public void tearDown() throws java.lang.Exception;
    Code:
       0: aload_0
       1: getfield      #34                 // Field admin:Lorg/apache/hadoop/hbase/client/AsyncAdmin;
       4: new           #40                 // class java/lang/StringBuilder
       7: dup
       8: invokespecial #41                 // Method java/lang/StringBuilder."<init>":()V
      11: aload_0
      12: getfield      #39                 // Field tableName:Lorg/apache/hadoop/hbase/TableName;
      15: invokevirtual #42                 // Method org/apache/hadoop/hbase/TableName.getNameAsString:()Ljava/lang/String;
      18: invokevirtual #43                 // Method java/lang/StringBuilder.append:(Ljava/lang/String;)Ljava/lang/StringBuilder;
      21: ldc           #44                 // String .*
      23: invokevirtual #43                 // Method java/lang/StringBuilder.append:(Ljava/lang/String;)Ljava/lang/StringBuilder;
      26: invokevirtual #45                 // Method java/lang/StringBuilder.toString:()Ljava/lang/String;
      29: invokestatic  #46                 // Method java/util/regex/Pattern.compile:(Ljava/lang/String;)Ljava/util/regex/Pattern;
      32: iconst_0
      33: invokeinterface #47,  3           // InterfaceMethod org/apache/hadoop/hbase/client/AsyncAdmin.listTableNames:(Ljava/util/regex/Pattern;Z)Ljava/util/concurrent/CompletableFuture;
      38: aload_0
      39: invokedynamic #48,  0             // InvokeDynamic #2:accept:(Lorg/apache/hadoop/hbase/client/TestAsyncAdminBase;)Ljava/util/function/BiConsumer;
      44: invokestatic  #8                  // Method java/util/concurrent/ForkJoinPool.commonPool:()Ljava/util/concurrent/ForkJoinPool;
      47: invokevirtual #49                 // Method java/util/concurrent/CompletableFuture.whenCompleteAsync:(Ljava/util/function/BiConsumer;Ljava/util/concurrent/Executor;)Ljava/util/concurrent/CompletableFuture;
      50: invokevirtual #50                 // Method java/util/concurrent/CompletableFuture.join:()Ljava/lang/Object;
      53: pop
      54: aload_0
      55: getfield      #34                 // Field admin:Lorg/apache/hadoop/hbase/client/AsyncAdmin;
      58: invokeinterface #51,  1           // InterfaceMethod org/apache/hadoop/hbase/client/AsyncAdmin.isBalancerEnabled:()Ljava/util/concurrent/CompletableFuture;
      63: invokevirtual #50                 // Method java/util/concurrent/CompletableFuture.join:()Ljava/lang/Object;
      66: checkcast     #52                 // class java/lang/Boolean
      69: invokevirtual #53                 // Method java/lang/Boolean.booleanValue:()Z
      72: ifne          87
      75: aload_0
      76: getfield      #34                 // Field admin:Lorg/apache/hadoop/hbase/client/AsyncAdmin;
      79: iconst_1
      80: iconst_1
      81: invokeinterface #54,  3           // InterfaceMethod org/apache/hadoop/hbase/client/AsyncAdmin.balancerSwitch:(ZZ)Ljava/util/concurrent/CompletableFuture;
      86: pop
      87: return

  protected void createTableWithDefaultConf(org.apache.hadoop.hbase.TableName) throws java.io.IOException;
    Code:
       0: aload_0
       1: aload_1
       2: aconst_null
       3: checkcast     #55                 // class "[[B"
       6: invokevirtual #56                 // Method createTableWithDefaultConf:(Lorg/apache/hadoop/hbase/TableName;[[B)V
       9: return

  protected void createTableWithDefaultConf(org.apache.hadoop.hbase.TableName, int) throws java.io.IOException;
    Code:
       0: aload_0
       1: aload_1
       2: iload_2
       3: aconst_null
       4: checkcast     #55                 // class "[[B"
       7: iconst_1
       8: anewarray     #57                 // class "[B"
      11: dup
      12: iconst_0
      13: getstatic     #58                 // Field FAMILY:[B
      16: aastore
      17: invokevirtual #59                 // Method createTableWithDefaultConf:(Lorg/apache/hadoop/hbase/TableName;I[[B[[B)V
      20: return

  protected void createTableWithDefaultConf(org.apache.hadoop.hbase.TableName, byte[][]) throws java.io.IOException;
    Code:
       0: aload_0
       1: aload_1
       2: aload_2
       3: iconst_1
       4: anewarray     #57                 // class "[B"
       7: dup
       8: iconst_0
       9: getstatic     #58                 // Field FAMILY:[B
      12: aastore
      13: invokevirtual #60                 // Method createTableWithDefaultConf:(Lorg/apache/hadoop/hbase/TableName;[[B[[B)V
      16: return

  protected void createTableWithDefaultConf(org.apache.hadoop.hbase.TableName, int, byte[][]) throws java.io.IOException;
    Code:
       0: aload_0
       1: aload_1
       2: iload_2
       3: aload_3
       4: iconst_1
       5: anewarray     #57                 // class "[B"
       8: dup
       9: iconst_0
      10: getstatic     #58                 // Field FAMILY:[B
      13: aastore
      14: invokevirtual #59                 // Method createTableWithDefaultConf:(Lorg/apache/hadoop/hbase/TableName;I[[B[[B)V
      17: return

  protected void createTableWithDefaultConf(org.apache.hadoop.hbase.TableName, byte[][], byte[]...) throws java.io.IOException;
    Code:
       0: aload_0
       1: aload_1
       2: iconst_1
       3: aload_2
       4: aload_3
       5: invokevirtual #59                 // Method createTableWithDefaultConf:(Lorg/apache/hadoop/hbase/TableName;I[[B[[B)V
       8: return

  protected void createTableWithDefaultConf(org.apache.hadoop.hbase.TableName, int, byte[][], byte[]...) throws java.io.IOException;
    Code:
       0: aload_1
       1: invokestatic  #61                 // Method org/apache/hadoop/hbase/client/TableDescriptorBuilder.newBuilder:(Lorg/apache/hadoop/hbase/TableName;)Lorg/apache/hadoop/hbase/client/TableDescriptorBuilder;
       4: iload_2
       5: invokevirtual #62                 // Method org/apache/hadoop/hbase/client/TableDescriptorBuilder.setRegionReplication:(I)Lorg/apache/hadoop/hbase/client/TableDescriptorBuilder;
       8: astore        5
      10: aload         4
      12: astore        6
      14: aload         6
      16: arraylength
      17: istore        7
      19: iconst_0
      20: istore        8
      22: iload         8
      24: iload         7
      26: if_icmpge     53
      29: aload         6
      31: iload         8
      33: aaload
      34: astore        9
      36: aload         5
      38: aload         9
      40: invokestatic  #63                 // Method org/apache/hadoop/hbase/client/ColumnFamilyDescriptorBuilder.of:([B)Lorg/apache/hadoop/hbase/client/ColumnFamilyDescriptor;
      43: invokevirtual #64                 // Method org/apache/hadoop/hbase/client/TableDescriptorBuilder.setColumnFamily:(Lorg/apache/hadoop/hbase/client/ColumnFamilyDescriptor;)Lorg/apache/hadoop/hbase/client/TableDescriptorBuilder;
      46: pop
      47: iinc          8, 1
      50: goto          22
      53: aload_3
      54: ifnonnull     74
      57: aload_0
      58: getfield      #34                 // Field admin:Lorg/apache/hadoop/hbase/client/AsyncAdmin;
      61: aload         5
      63: invokevirtual #65                 // Method org/apache/hadoop/hbase/client/TableDescriptorBuilder.build:()Lorg/apache/hadoop/hbase/client/TableDescriptor;
      66: invokeinterface #66,  2           // InterfaceMethod org/apache/hadoop/hbase/client/AsyncAdmin.createTable:(Lorg/apache/hadoop/hbase/client/TableDescriptor;)Ljava/util/concurrent/CompletableFuture;
      71: goto          89
      74: aload_0
      75: getfield      #34                 // Field admin:Lorg/apache/hadoop/hbase/client/AsyncAdmin;
      78: aload         5
      80: invokevirtual #65                 // Method org/apache/hadoop/hbase/client/TableDescriptorBuilder.build:()Lorg/apache/hadoop/hbase/client/TableDescriptor;
      83: aload_3
      84: invokeinterface #67,  3           // InterfaceMethod org/apache/hadoop/hbase/client/AsyncAdmin.createTable:(Lorg/apache/hadoop/hbase/client/TableDescriptor;[[B)Ljava/util/concurrent/CompletableFuture;
      89: astore        6
      91: aload         6
      93: invokevirtual #50                 // Method java/util/concurrent/CompletableFuture.join:()Ljava/lang/Object;
      96: pop
      97: getstatic     #15                 // Field TEST_UTIL:Lorg/apache/hadoop/hbase/HBaseTestingUtility;
     100: aload_1
     101: invokevirtual #68                 // Method org/apache/hadoop/hbase/HBaseTestingUtility.waitUntilAllRegionsAssigned:(Lorg/apache/hadoop/hbase/TableName;)V
     104: return

  static {};
    Code:
       0: ldc           #79                 // class org/apache/hadoop/hbase/client/TestAsyncAdminBase
       2: invokestatic  #80                 // Method org/slf4j/LoggerFactory.getLogger:(Ljava/lang/Class;)Lorg/slf4j/Logger;
       5: putstatic     #73                 // Field LOG:Lorg/slf4j/Logger;
       8: new           #81                 // class org/apache/hadoop/hbase/HBaseTestingUtility
      11: dup
      12: invokespecial #82                 // Method org/apache/hadoop/hbase/HBaseTestingUtility."<init>":()V
      15: putstatic     #15                 // Field TEST_UTIL:Lorg/apache/hadoop/hbase/HBaseTestingUtility;
      18: ldc           #83                 // String testFamily
      20: invokestatic  #84                 // Method org/apache/hadoop/hbase/util/Bytes.toBytes:(Ljava/lang/String;)[B
      23: putstatic     #58                 // Field FAMILY:[B
      26: ldc           #85                 // String cf0
      28: invokestatic  #84                 // Method org/apache/hadoop/hbase/util/Bytes.toBytes:(Ljava/lang/String;)[B
      31: putstatic     #86                 // Field FAMILY_0:[B
      34: ldc           #87                 // String cf1
      36: invokestatic  #84                 // Method org/apache/hadoop/hbase/util/Bytes.toBytes:(Ljava/lang/String;)[B
      39: putstatic     #88                 // Field FAMILY_1:[B
      42: return
}
