Compiled from "TestHStore.java"
class org.apache.hadoop.hbase.regionserver.TestHStore$10 extends org.apache.hadoop.hbase.regionserver.TestHStore$MyStoreHook {
  final org.apache.hadoop.hbase.regionserver.TestHStore this$0;

  org.apache.hadoop.hbase.regionserver.TestHStore$10(org.apache.hadoop.hbase.regionserver.TestHStore);
    Code:
       0: aload_0
       1: aload_1
       2: putfield      #1                  // Field this$0:Lorg/apache/hadoop/hbase/regionserver/TestHStore;
       5: aload_0
       6: aconst_null
       7: invokespecial #2                  // Method org/apache/hadoop/hbase/regionserver/TestHStore$MyStoreHook."<init>":(Lorg/apache/hadoop/hbase/regionserver/TestHStore$1;)V
      10: return

  public void getScanners(org.apache.hadoop.hbase.regionserver.TestHStore$MyStore) throws java.io.IOException;
    Code:
       0: aload_0
       1: getfield      #1                  // Field this$0:Lorg/apache/hadoop/hbase/regionserver/TestHStore;
       4: dup
       5: getfield      #3                  // Field org/apache/hadoop/hbase/regionserver/TestHStore.id:J
       8: dup2_x1
       9: lconst_1
      10: ladd
      11: putfield      #3                  // Field org/apache/hadoop/hbase/regionserver/TestHStore.id:J
      14: lstore_2
      15: invokestatic  #4                  // Method java/util/concurrent/Executors.newSingleThreadExecutor:()Ljava/util/concurrent/ExecutorService;
      18: astore        4
      20: aload         4
      22: aload_1
      23: lload_2
      24: invokedynamic #5,  0              // InvokeDynamic #0:run:(Lorg/apache/hadoop/hbase/regionserver/TestHStore$MyStore;J)Ljava/lang/Runnable;
      29: invokeinterface #6,  2            // InterfaceMethod java/util/concurrent/ExecutorService.submit:(Ljava/lang/Runnable;)Ljava/util/concurrent/Future;
      34: pop
      35: aload         4
      37: invokeinterface #7,  1            // InterfaceMethod java/util/concurrent/ExecutorService.shutdown:()V
      42: aload         4
      44: ldc2_w        #8                  // long 3l
      47: getstatic     #10                 // Field java/util/concurrent/TimeUnit.SECONDS:Ljava/util/concurrent/TimeUnit;
      50: invokeinterface #11,  4           // InterfaceMethod java/util/concurrent/ExecutorService.awaitTermination:(JLjava/util/concurrent/TimeUnit;)Z
      55: pop
      56: goto          61
      59: astore        5
      61: return
    Exception table:
       from    to  target type
          42    56    59   Class java/lang/InterruptedException
}
