Compiled from "TestAssignmentManagerBase.java"
public class org.apache.hadoop.hbase.master.assignment.TestAssignmentManagerBase$SocketTimeoutRsExecutor extends org.apache.hadoop.hbase.master.assignment.TestAssignmentManagerBase$GoodRsExecutor {
  final org.apache.hadoop.hbase.master.assignment.TestAssignmentManagerBase this$0;

  public org.apache.hadoop.hbase.master.assignment.TestAssignmentManagerBase$SocketTimeoutRsExecutor(org.apache.hadoop.hbase.master.assignment.TestAssignmentManagerBase, int);
    Code:
       0: aload_0
       1: aload_1
       2: putfield      #1                  // Field this$0:Lorg/apache/hadoop/hbase/master/assignment/TestAssignmentManagerBase;
       5: aload_0
       6: aload_1
       7: invokespecial #2                  // Method org/apache/hadoop/hbase/master/assignment/TestAssignmentManagerBase$GoodRsExecutor."<init>":(Lorg/apache/hadoop/hbase/master/assignment/TestAssignmentManagerBase;)V
      10: aload_0
      11: iload_2
      12: putfield      #3                  // Field timeoutTimes:I
      15: return

  public org.apache.hadoop.hbase.shaded.protobuf.generated.AdminProtos$ExecuteProceduresResponse sendRequest(org.apache.hadoop.hbase.ServerName, org.apache.hadoop.hbase.shaded.protobuf.generated.AdminProtos$ExecuteProceduresRequest) throws java.io.IOException;
    Code:
       0: aload_0
       1: dup
       2: getfield      #4                  // Field retries:I
       5: iconst_1
       6: iadd
       7: putfield      #4                  // Field retries:I
      10: aload_0
      11: getfield      #4                  // Field retries:I
      14: iconst_1
      15: if_icmpne     23
      18: aload_0
      19: aload_1
      20: putfield      #5                  // Field lastServer:Lorg/apache/hadoop/hbase/ServerName;
      23: aload_0
      24: getfield      #4                  // Field retries:I
      27: aload_0
      28: getfield      #3                  // Field timeoutTimes:I
      31: if_icmpgt     181
      34: invokestatic  #6                  // Method org/apache/hadoop/hbase/master/assignment/TestAssignmentManagerBase.access$000:()Lorg/slf4j/Logger;
      37: new           #7                  // class java/lang/StringBuilder
      40: dup
      41: invokespecial #8                  // Method java/lang/StringBuilder."<init>":()V
      44: ldc           #9                  // String Socket timeout for server=
      46: invokevirtual #10                 // Method java/lang/StringBuilder.append:(Ljava/lang/String;)Ljava/lang/StringBuilder;
      49: aload_1
      50: invokevirtual #11                 // Method java/lang/StringBuilder.append:(Ljava/lang/Object;)Ljava/lang/StringBuilder;
      53: ldc           #12                 // String  retries=
      55: invokevirtual #10                 // Method java/lang/StringBuilder.append:(Ljava/lang/String;)Ljava/lang/StringBuilder;
      58: aload_0
      59: getfield      #4                  // Field retries:I
      62: invokevirtual #13                 // Method java/lang/StringBuilder.append:(I)Ljava/lang/StringBuilder;
      65: invokevirtual #14                 // Method java/lang/StringBuilder.toString:()Ljava/lang/String;
      68: invokeinterface #15,  2           // InterfaceMethod org/slf4j/Logger.debug:(Ljava/lang/String;)V
      73: aload_0
      74: getfield      #5                  // Field lastServer:Lorg/apache/hadoop/hbase/ServerName;
      77: aload_1
      78: invokestatic  #16                 // Method org/junit/Assert.assertEquals:(Ljava/lang/Object;Ljava/lang/Object;)V
      81: aload_0
      82: getfield      #4                  // Field retries:I
      85: aload_0
      86: getfield      #3                  // Field timeoutTimes:I
      89: if_icmpne     171
      92: invokestatic  #6                  // Method org/apache/hadoop/hbase/master/assignment/TestAssignmentManagerBase.access$000:()Lorg/slf4j/Logger;
      95: new           #7                  // class java/lang/StringBuilder
      98: dup
      99: invokespecial #8                  // Method java/lang/StringBuilder."<init>":()V
     102: ldc           #17                 // String Mark server=
     104: invokevirtual #10                 // Method java/lang/StringBuilder.append:(Ljava/lang/String;)Ljava/lang/StringBuilder;
     107: aload_1
     108: invokevirtual #11                 // Method java/lang/StringBuilder.append:(Ljava/lang/Object;)Ljava/lang/StringBuilder;
     111: ldc           #18                 // String  as dead. retries=
     113: invokevirtual #10                 // Method java/lang/StringBuilder.append:(Ljava/lang/String;)Ljava/lang/StringBuilder;
     116: aload_0
     117: getfield      #4                  // Field retries:I
     120: invokevirtual #13                 // Method java/lang/StringBuilder.append:(I)Ljava/lang/StringBuilder;
     123: invokevirtual #14                 // Method java/lang/StringBuilder.toString:()Ljava/lang/String;
     126: invokeinterface #19,  2           // InterfaceMethod org/slf4j/Logger.info:(Ljava/lang/String;)V
     131: aload_0
     132: getfield      #1                  // Field this$0:Lorg/apache/hadoop/hbase/master/assignment/TestAssignmentManagerBase;
     135: getfield      #20                 // Field org/apache/hadoop/hbase/master/assignment/TestAssignmentManagerBase.master:Lorg/apache/hadoop/hbase/master/assignment/MockMasterServices;
     138: invokevirtual #21                 // Method org/apache/hadoop/hbase/master/assignment/MockMasterServices.getServerManager:()Lorg/apache/hadoop/hbase/master/ServerManager;
     141: aload_1
     142: invokevirtual #22                 // Method org/apache/hadoop/hbase/master/ServerManager.moveFromOnlineToDeadServers:(Lorg/apache/hadoop/hbase/ServerName;)V
     145: aload_0
     146: getfield      #1                  // Field this$0:Lorg/apache/hadoop/hbase/master/assignment/TestAssignmentManagerBase;
     149: getfield      #23                 // Field org/apache/hadoop/hbase/master/assignment/TestAssignmentManagerBase.executor:Ljava/util/concurrent/ScheduledExecutorService;
     152: new           #24                 // class org/apache/hadoop/hbase/master/assignment/TestAssignmentManagerBase$SocketTimeoutRsExecutor$1
     155: dup
     156: aload_0
     157: aload_1
     158: invokespecial #25                 // Method org/apache/hadoop/hbase/master/assignment/TestAssignmentManagerBase$SocketTimeoutRsExecutor$1."<init>":(Lorg/apache/hadoop/hbase/master/assignment/TestAssignmentManagerBase$SocketTimeoutRsExecutor;Lorg/apache/hadoop/hbase/ServerName;)V
     161: lconst_1
     162: getstatic     #26                 // Field java/util/concurrent/TimeUnit.SECONDS:Ljava/util/concurrent/TimeUnit;
     165: invokeinterface #27,  5           // InterfaceMethod java/util/concurrent/ScheduledExecutorService.schedule:(Ljava/lang/Runnable;JLjava/util/concurrent/TimeUnit;)Ljava/util/concurrent/ScheduledFuture;
     170: pop
     171: new           #28                 // class java/net/SocketTimeoutException
     174: dup
     175: ldc           #29                 // String simulate socket timeout
     177: invokespecial #30                 // Method java/net/SocketTimeoutException."<init>":(Ljava/lang/String;)V
     180: athrow
     181: aload_0
     182: getfield      #5                  // Field lastServer:Lorg/apache/hadoop/hbase/ServerName;
     185: aload_1
     186: invokestatic  #31                 // Method org/junit/Assert.assertNotEquals:(Ljava/lang/Object;Ljava/lang/Object;)V
     189: aload_0
     190: aload_1
     191: aload_2
     192: invokespecial #32                 // Method org/apache/hadoop/hbase/master/assignment/TestAssignmentManagerBase$GoodRsExecutor.sendRequest:(Lorg/apache/hadoop/hbase/ServerName;Lorg/apache/hadoop/hbase/shaded/protobuf/generated/AdminProtos$ExecuteProceduresRequest;)Lorg/apache/hadoop/hbase/shaded/protobuf/generated/AdminProtos$ExecuteProceduresResponse;
     195: areturn
}
