Compiled from "TestSerialReplicationFailover.java"
public class org.apache.hadoop.hbase.replication.TestSerialReplicationFailover extends org.apache.hadoop.hbase.replication.SerialReplicationTestBase {
  public static final org.apache.hadoop.hbase.HBaseClassTestRule CLASS_RULE;

  public org.apache.hadoop.hbase.replication.TestSerialReplicationFailover();
    Code:
       0: aload_0
       1: invokespecial #1                  // Method org/apache/hadoop/hbase/replication/SerialReplicationTestBase."<init>":()V
       4: return

  public void setUp() throws java.io.IOException, org.apache.hadoop.hbase.util.CommonFSUtils$StreamLacksCapabilityException;
    Code:
       0: aload_0
       1: invokevirtual #2                  // Method setupWALWriter:()V
       4: aload_0
       5: iconst_0
       6: invokevirtual #3                  // Method addPeer:(Z)V
       9: return

  public void testKillRS() throws java.lang.Exception;
    Code:
       0: aload_0
       1: getfield      #4                  // Field name:Lorg/junit/rules/TestName;
       4: invokevirtual #5                  // Method org/junit/rules/TestName.getMethodName:()Ljava/lang/String;
       7: invokestatic  #6                  // Method org/apache/hadoop/hbase/TableName.valueOf:(Ljava/lang/String;)Lorg/apache/hadoop/hbase/TableName;
      10: astore_1
      11: getstatic     #7                  // Field UTIL:Lorg/apache/hadoop/hbase/HBaseTestingUtility;
      14: invokevirtual #8                  // Method org/apache/hadoop/hbase/HBaseTestingUtility.getAdmin:()Lorg/apache/hadoop/hbase/client/Admin;
      17: aload_1
      18: invokestatic  #9                  // Method org/apache/hadoop/hbase/client/TableDescriptorBuilder.newBuilder:(Lorg/apache/hadoop/hbase/TableName;)Lorg/apache/hadoop/hbase/client/TableDescriptorBuilder;
      21: getstatic     #10                 // Field CF:[B
      24: invokestatic  #11                 // Method org/apache/hadoop/hbase/client/ColumnFamilyDescriptorBuilder.newBuilder:([B)Lorg/apache/hadoop/hbase/client/ColumnFamilyDescriptorBuilder;
      27: iconst_1
      28: invokevirtual #13                 // Method org/apache/hadoop/hbase/client/ColumnFamilyDescriptorBuilder.setScope:(I)Lorg/apache/hadoop/hbase/client/ColumnFamilyDescriptorBuilder;
      31: invokevirtual #14                 // Method org/apache/hadoop/hbase/client/ColumnFamilyDescriptorBuilder.build:()Lorg/apache/hadoop/hbase/client/ColumnFamilyDescriptor;
      34: invokevirtual #15                 // Method org/apache/hadoop/hbase/client/TableDescriptorBuilder.setColumnFamily:(Lorg/apache/hadoop/hbase/client/ColumnFamilyDescriptor;)Lorg/apache/hadoop/hbase/client/TableDescriptorBuilder;
      37: invokevirtual #16                 // Method org/apache/hadoop/hbase/client/TableDescriptorBuilder.build:()Lorg/apache/hadoop/hbase/client/TableDescriptor;
      40: invokeinterface #17,  2           // InterfaceMethod org/apache/hadoop/hbase/client/Admin.createTable:(Lorg/apache/hadoop/hbase/client/TableDescriptor;)V
      45: getstatic     #7                  // Field UTIL:Lorg/apache/hadoop/hbase/HBaseTestingUtility;
      48: aload_1
      49: invokevirtual #18                 // Method org/apache/hadoop/hbase/HBaseTestingUtility.waitTableAvailable:(Lorg/apache/hadoop/hbase/TableName;)V
      52: getstatic     #7                  // Field UTIL:Lorg/apache/hadoop/hbase/HBaseTestingUtility;
      55: invokevirtual #19                 // Method org/apache/hadoop/hbase/HBaseTestingUtility.getConnection:()Lorg/apache/hadoop/hbase/client/Connection;
      58: aload_1
      59: invokeinterface #20,  2           // InterfaceMethod org/apache/hadoop/hbase/client/Connection.getTable:(Lorg/apache/hadoop/hbase/TableName;)Lorg/apache/hadoop/hbase/client/Table;
      64: astore_2
      65: aconst_null
      66: astore_3
      67: iconst_0
      68: istore        4
      70: iload         4
      72: bipush        100
      74: if_icmpge     115
      77: aload_2
      78: new           #21                 // class org/apache/hadoop/hbase/client/Put
      81: dup
      82: iload         4
      84: invokestatic  #22                 // Method org/apache/hadoop/hbase/util/Bytes.toBytes:(I)[B
      87: invokespecial #23                 // Method org/apache/hadoop/hbase/client/Put."<init>":([B)V
      90: getstatic     #10                 // Field CF:[B
      93: getstatic     #24                 // Field CQ:[B
      96: iload         4
      98: invokestatic  #22                 // Method org/apache/hadoop/hbase/util/Bytes.toBytes:(I)[B
     101: invokevirtual #25                 // Method org/apache/hadoop/hbase/client/Put.addColumn:([B[B[B)Lorg/apache/hadoop/hbase/client/Put;
     104: invokeinterface #26,  2           // InterfaceMethod org/apache/hadoop/hbase/client/Table.put:(Lorg/apache/hadoop/hbase/client/Put;)V
     109: iinc          4, 1
     112: goto          70
     115: aload_2
     116: ifnull        199
     119: aload_3
     120: ifnull        143
     123: aload_2
     124: invokeinterface #27,  1           // InterfaceMethod org/apache/hadoop/hbase/client/Table.close:()V
     129: goto          199
     132: astore        4
     134: aload_3
     135: aload         4
     137: invokevirtual #29                 // Method java/lang/Throwable.addSuppressed:(Ljava/lang/Throwable;)V
     140: goto          199
     143: aload_2
     144: invokeinterface #27,  1           // InterfaceMethod org/apache/hadoop/hbase/client/Table.close:()V
     149: goto          199
     152: astore        4
     154: aload         4
     156: astore_3
     157: aload         4
     159: athrow
     160: astore        5
     162: aload_2
     163: ifnull        196
     166: aload_3
     167: ifnull        190
     170: aload_2
     171: invokeinterface #27,  1           // InterfaceMethod org/apache/hadoop/hbase/client/Table.close:()V
     176: goto          196
     179: astore        6
     181: aload_3
     182: aload         6
     184: invokevirtual #29                 // Method java/lang/Throwable.addSuppressed:(Ljava/lang/Throwable;)V
     187: goto          196
     190: aload_2
     191: invokeinterface #27,  1           // InterfaceMethod org/apache/hadoop/hbase/client/Table.close:()V
     196: aload         5
     198: athrow
     199: getstatic     #7                  // Field UTIL:Lorg/apache/hadoop/hbase/HBaseTestingUtility;
     202: invokevirtual #30                 // Method org/apache/hadoop/hbase/HBaseTestingUtility.getMiniHBaseCluster:()Lorg/apache/hadoop/hbase/MiniHBaseCluster;
     205: invokevirtual #31                 // Method org/apache/hadoop/hbase/MiniHBaseCluster.getRegionServerThreads:()Ljava/util/List;
     208: invokeinterface #32,  1           // InterfaceMethod java/util/List.stream:()Ljava/util/stream/Stream;
     213: aload_1
     214: invokedynamic #33,  0             // InvokeDynamic #0:test:(Lorg/apache/hadoop/hbase/TableName;)Ljava/util/function/Predicate;
     219: invokeinterface #34,  2           // InterfaceMethod java/util/stream/Stream.filter:(Ljava/util/function/Predicate;)Ljava/util/stream/Stream;
     224: invokeinterface #35,  1           // InterfaceMethod java/util/stream/Stream.findFirst:()Ljava/util/Optional;
     229: invokevirtual #36                 // Method java/util/Optional.get:()Ljava/lang/Object;
     232: checkcast     #37                 // class org/apache/hadoop/hbase/util/JVMClusterUtil$RegionServerThread
     235: astore_2
     236: aload_2
     237: invokevirtual #38                 // Method org/apache/hadoop/hbase/util/JVMClusterUtil$RegionServerThread.getRegionServer:()Lorg/apache/hadoop/hbase/regionserver/HRegionServer;
     240: ldc           #39                 // String for testing
     242: invokevirtual #40                 // Method org/apache/hadoop/hbase/regionserver/HRegionServer.abort:(Ljava/lang/String;)V
     245: aload_2
     246: invokevirtual #41                 // Method org/apache/hadoop/hbase/util/JVMClusterUtil$RegionServerThread.join:()V
     249: getstatic     #7                  // Field UTIL:Lorg/apache/hadoop/hbase/HBaseTestingUtility;
     252: invokevirtual #19                 // Method org/apache/hadoop/hbase/HBaseTestingUtility.getConnection:()Lorg/apache/hadoop/hbase/client/Connection;
     255: aload_1
     256: invokeinterface #20,  2           // InterfaceMethod org/apache/hadoop/hbase/client/Connection.getTable:(Lorg/apache/hadoop/hbase/TableName;)Lorg/apache/hadoop/hbase/client/Table;
     261: astore_3
     262: aconst_null
     263: astore        4
     265: bipush        100
     267: istore        5
     269: iload         5
     271: sipush        200
     274: if_icmpge     315
     277: aload_3
     278: new           #21                 // class org/apache/hadoop/hbase/client/Put
     281: dup
     282: iload         5
     284: invokestatic  #22                 // Method org/apache/hadoop/hbase/util/Bytes.toBytes:(I)[B
     287: invokespecial #23                 // Method org/apache/hadoop/hbase/client/Put."<init>":([B)V
     290: getstatic     #10                 // Field CF:[B
     293: getstatic     #24                 // Field CQ:[B
     296: iload         5
     298: invokestatic  #22                 // Method org/apache/hadoop/hbase/util/Bytes.toBytes:(I)[B
     301: invokevirtual #25                 // Method org/apache/hadoop/hbase/client/Put.addColumn:([B[B[B)Lorg/apache/hadoop/hbase/client/Put;
     304: invokeinterface #26,  2           // InterfaceMethod org/apache/hadoop/hbase/client/Table.put:(Lorg/apache/hadoop/hbase/client/Put;)V
     309: iinc          5, 1
     312: goto          269
     315: aload_3
     316: ifnull        404
     319: aload         4
     321: ifnull        345
     324: aload_3
     325: invokeinterface #27,  1           // InterfaceMethod org/apache/hadoop/hbase/client/Table.close:()V
     330: goto          404
     333: astore        5
     335: aload         4
     337: aload         5
     339: invokevirtual #29                 // Method java/lang/Throwable.addSuppressed:(Ljava/lang/Throwable;)V
     342: goto          404
     345: aload_3
     346: invokeinterface #27,  1           // InterfaceMethod org/apache/hadoop/hbase/client/Table.close:()V
     351: goto          404
     354: astore        5
     356: aload         5
     358: astore        4
     360: aload         5
     362: athrow
     363: astore        7
     365: aload_3
     366: ifnull        401
     369: aload         4
     371: ifnull        395
     374: aload_3
     375: invokeinterface #27,  1           // InterfaceMethod org/apache/hadoop/hbase/client/Table.close:()V
     380: goto          401
     383: astore        8
     385: aload         4
     387: aload         8
     389: invokevirtual #29                 // Method java/lang/Throwable.addSuppressed:(Ljava/lang/Throwable;)V
     392: goto          401
     395: aload_3
     396: invokeinterface #27,  1           // InterfaceMethod org/apache/hadoop/hbase/client/Table.close:()V
     401: aload         7
     403: athrow
     404: aload_0
     405: sipush        200
     408: invokevirtual #42                 // Method enablePeerAndWaitUntilReplicationDone:(I)V
     411: aload_0
     412: sipush        200
     415: invokevirtual #43                 // Method checkOrder:(I)V
     418: return
    Exception table:
       from    to  target type
         123   129   132   Class java/lang/Throwable
          67   115   152   Class java/lang/Throwable
          67   115   160   any
         170   176   179   Class java/lang/Throwable
         152   162   160   any
         324   330   333   Class java/lang/Throwable
         265   315   354   Class java/lang/Throwable
         265   315   363   any
         374   380   383   Class java/lang/Throwable
         354   365   363   any

  static {};
    Code:
       0: ldc           #46                 // class org/apache/hadoop/hbase/replication/TestSerialReplicationFailover
       2: invokestatic  #47                 // Method org/apache/hadoop/hbase/HBaseClassTestRule.forClass:(Ljava/lang/Class;)Lorg/apache/hadoop/hbase/HBaseClassTestRule;
       5: putstatic     #48                 // Field CLASS_RULE:Lorg/apache/hadoop/hbase/HBaseClassTestRule;
       8: return
}
