Compiled from "TestHColumnDescriptor.java"
public class org.apache.hadoop.hbase.TestHColumnDescriptor {
  public static final org.apache.hadoop.hbase.HBaseClassTestRule CLASS_RULE;

  public org.junit.rules.ExpectedException expectedEx;

  public org.apache.hadoop.hbase.TestHColumnDescriptor();
    Code:
       0: aload_0
       1: invokespecial #1                  // Method java/lang/Object."<init>":()V
       4: aload_0
       5: invokestatic  #2                  // Method org/junit/rules/ExpectedException.none:()Lorg/junit/rules/ExpectedException;
       8: putfield      #3                  // Field expectedEx:Lorg/junit/rules/ExpectedException;
      11: return

  public void testPb() throws org.apache.hadoop.hbase.exceptions.DeserializationException;
    Code:
       0: new           #4                  // class org/apache/hadoop/hbase/HColumnDescriptor
       3: dup
       4: new           #4                  // class org/apache/hadoop/hbase/HColumnDescriptor
       7: dup
       8: getstatic     #5                  // Field org/apache/hadoop/hbase/HConstants.CATALOG_FAMILY:[B
      11: invokespecial #6                  // Method org/apache/hadoop/hbase/HColumnDescriptor."<init>":([B)V
      14: iconst_1
      15: invokevirtual #7                  // Method org/apache/hadoop/hbase/HColumnDescriptor.setInMemory:(Z)Lorg/apache/hadoop/hbase/HColumnDescriptor;
      18: iconst_0
      19: invokevirtual #9                  // Method org/apache/hadoop/hbase/HColumnDescriptor.setScope:(I)Lorg/apache/hadoop/hbase/HColumnDescriptor;
      22: getstatic     #10                 // Field org/apache/hadoop/hbase/regionserver/BloomType.NONE:Lorg/apache/hadoop/hbase/regionserver/BloomType;
      25: invokevirtual #11                 // Method org/apache/hadoop/hbase/HColumnDescriptor.setBloomFilterType:(Lorg/apache/hadoop/hbase/regionserver/BloomType;)Lorg/apache/hadoop/hbase/HColumnDescriptor;
      28: iconst_1
      29: invokevirtual #12                 // Method org/apache/hadoop/hbase/HColumnDescriptor.setCacheDataInL1:(Z)Lorg/apache/hadoop/hbase/HColumnDescriptor;
      32: invokespecial #13                 // Method org/apache/hadoop/hbase/HColumnDescriptor."<init>":(Lorg/apache/hadoop/hbase/HColumnDescriptor;)V
      35: astore_1
      36: bipush        123
      38: istore_2
      39: aload_1
      40: bipush        123
      42: invokevirtual #14                 // Method org/apache/hadoop/hbase/HColumnDescriptor.setBlocksize:(I)Lorg/apache/hadoop/hbase/HColumnDescriptor;
      45: pop
      46: aload_1
      47: bipush        123
      49: invokevirtual #15                 // Method org/apache/hadoop/hbase/HColumnDescriptor.setTimeToLive:(I)Lorg/apache/hadoop/hbase/HColumnDescriptor;
      52: pop
      53: aload_1
      54: iconst_0
      55: invokevirtual #16                 // Method org/apache/hadoop/hbase/HColumnDescriptor.setBlockCacheEnabled:(Z)Lorg/apache/hadoop/hbase/HColumnDescriptor;
      58: pop
      59: aload_1
      60: ldc           #17                 // String a
      62: ldc           #18                 // String b
      64: invokevirtual #19                 // Method org/apache/hadoop/hbase/HColumnDescriptor.setValue:(Ljava/lang/String;Ljava/lang/String;)Lorg/apache/hadoop/hbase/HColumnDescriptor;
      67: pop
      68: aload_1
      69: bipush        123
      71: invokevirtual #20                 // Method org/apache/hadoop/hbase/HColumnDescriptor.setMaxVersions:(I)Lorg/apache/hadoop/hbase/HColumnDescriptor;
      74: pop
      75: ldc2_w        #21                 // long 123l
      78: aload_1
      79: invokevirtual #23                 // Method org/apache/hadoop/hbase/HColumnDescriptor.getMaxVersions:()I
      82: i2l
      83: invokestatic  #24                 // Method org/junit/Assert.assertEquals:(JJ)V
      86: aload_1
      87: bipush        123
      89: invokevirtual #25                 // Method org/apache/hadoop/hbase/HColumnDescriptor.setMinVersions:(I)Lorg/apache/hadoop/hbase/HColumnDescriptor;
      92: pop
      93: ldc2_w        #21                 // long 123l
      96: aload_1
      97: invokevirtual #26                 // Method org/apache/hadoop/hbase/HColumnDescriptor.getMinVersions:()I
     100: i2l
     101: invokestatic  #24                 // Method org/junit/Assert.assertEquals:(JJ)V
     104: aload_1
     105: getstatic     #27                 // Field org/apache/hadoop/hbase/KeepDeletedCells.TRUE:Lorg/apache/hadoop/hbase/KeepDeletedCells;
     108: invokevirtual #28                 // Method org/apache/hadoop/hbase/HColumnDescriptor.setKeepDeletedCells:(Lorg/apache/hadoop/hbase/KeepDeletedCells;)Lorg/apache/hadoop/hbase/HColumnDescriptor;
     111: pop
     112: aload_1
     113: iconst_1
     114: invokevirtual #7                  // Method org/apache/hadoop/hbase/HColumnDescriptor.setInMemory:(Z)Lorg/apache/hadoop/hbase/HColumnDescriptor;
     117: pop
     118: aload_1
     119: invokevirtual #29                 // Method org/apache/hadoop/hbase/HColumnDescriptor.isInMemory:()Z
     122: istore_3
     123: aload_1
     124: bipush        123
     126: invokevirtual #9                  // Method org/apache/hadoop/hbase/HColumnDescriptor.setScope:(I)Lorg/apache/hadoop/hbase/HColumnDescriptor;
     129: pop
     130: aload_1
     131: getstatic     #30                 // Field org/apache/hadoop/hbase/io/encoding/DataBlockEncoding.FAST_DIFF:Lorg/apache/hadoop/hbase/io/encoding/DataBlockEncoding;
     134: invokevirtual #31                 // Method org/apache/hadoop/hbase/HColumnDescriptor.setDataBlockEncoding:(Lorg/apache/hadoop/hbase/io/encoding/DataBlockEncoding;)Lorg/apache/hadoop/hbase/HColumnDescriptor;
     137: pop
     138: aload_1
     139: getstatic     #32                 // Field org/apache/hadoop/hbase/regionserver/BloomType.ROW:Lorg/apache/hadoop/hbase/regionserver/BloomType;
     142: invokevirtual #11                 // Method org/apache/hadoop/hbase/HColumnDescriptor.setBloomFilterType:(Lorg/apache/hadoop/hbase/regionserver/BloomType;)Lorg/apache/hadoop/hbase/HColumnDescriptor;
     145: pop
     146: aload_1
     147: getstatic     #33                 // Field org/apache/hadoop/hbase/io/compress/Compression$Algorithm.SNAPPY:Lorg/apache/hadoop/hbase/io/compress/Compression$Algorithm;
     150: invokevirtual #34                 // Method org/apache/hadoop/hbase/HColumnDescriptor.setCompressionType:(Lorg/apache/hadoop/hbase/io/compress/Compression$Algorithm;)Lorg/apache/hadoop/hbase/HColumnDescriptor;
     153: pop
     154: aload_1
     155: iconst_1
     156: invokevirtual #35                 // Method org/apache/hadoop/hbase/HColumnDescriptor.setMobEnabled:(Z)Lorg/apache/hadoop/hbase/HColumnDescriptor;
     159: pop
     160: aload_1
     161: ldc2_w        #36                 // long 1000l
     164: invokevirtual #38                 // Method org/apache/hadoop/hbase/HColumnDescriptor.setMobThreshold:(J)Lorg/apache/hadoop/hbase/HColumnDescriptor;
     167: pop
     168: aload_1
     169: bipush        123
     171: invokevirtual #39                 // Method org/apache/hadoop/hbase/HColumnDescriptor.setDFSReplication:(S)Lorg/apache/hadoop/hbase/HColumnDescriptor;
     174: pop
     175: aload_1
     176: invokevirtual #40                 // Method org/apache/hadoop/hbase/HColumnDescriptor.toByteArray:()[B
     179: astore        4
     181: aload         4
     183: invokestatic  #41                 // Method org/apache/hadoop/hbase/HColumnDescriptor.parseFrom:([B)Lorg/apache/hadoop/hbase/HColumnDescriptor;
     186: astore        5
     188: aload_1
     189: aload         5
     191: invokevirtual #42                 // Method org/apache/hadoop/hbase/HColumnDescriptor.equals:(Ljava/lang/Object;)Z
     194: invokestatic  #43                 // Method org/junit/Assert.assertTrue:(Z)V
     197: ldc2_w        #21                 // long 123l
     200: aload_1
     201: invokevirtual #44                 // Method org/apache/hadoop/hbase/HColumnDescriptor.getBlocksize:()I
     204: i2l
     205: invokestatic  #24                 // Method org/junit/Assert.assertEquals:(JJ)V
     208: ldc2_w        #21                 // long 123l
     211: aload_1
     212: invokevirtual #45                 // Method org/apache/hadoop/hbase/HColumnDescriptor.getTimeToLive:()I
     215: i2l
     216: invokestatic  #24                 // Method org/junit/Assert.assertEquals:(JJ)V
     219: ldc2_w        #21                 // long 123l
     222: aload_1
     223: invokevirtual #46                 // Method org/apache/hadoop/hbase/HColumnDescriptor.getScope:()I
     226: i2l
     227: invokestatic  #24                 // Method org/junit/Assert.assertEquals:(JJ)V
     230: aload_1
     231: ldc           #17                 // String a
     233: invokevirtual #47                 // Method org/apache/hadoop/hbase/HColumnDescriptor.getValue:(Ljava/lang/String;)Ljava/lang/String;
     236: aload         5
     238: ldc           #17                 // String a
     240: invokevirtual #47                 // Method org/apache/hadoop/hbase/HColumnDescriptor.getValue:(Ljava/lang/String;)Ljava/lang/String;
     243: invokestatic  #48                 // Method org/junit/Assert.assertEquals:(Ljava/lang/Object;Ljava/lang/Object;)V
     246: aload_1
     247: invokevirtual #23                 // Method org/apache/hadoop/hbase/HColumnDescriptor.getMaxVersions:()I
     250: i2l
     251: aload         5
     253: invokevirtual #23                 // Method org/apache/hadoop/hbase/HColumnDescriptor.getMaxVersions:()I
     256: i2l
     257: invokestatic  #24                 // Method org/junit/Assert.assertEquals:(JJ)V
     260: aload_1
     261: invokevirtual #26                 // Method org/apache/hadoop/hbase/HColumnDescriptor.getMinVersions:()I
     264: i2l
     265: aload         5
     267: invokevirtual #26                 // Method org/apache/hadoop/hbase/HColumnDescriptor.getMinVersions:()I
     270: i2l
     271: invokestatic  #24                 // Method org/junit/Assert.assertEquals:(JJ)V
     274: aload_1
     275: invokevirtual #49                 // Method org/apache/hadoop/hbase/HColumnDescriptor.getKeepDeletedCells:()Lorg/apache/hadoop/hbase/KeepDeletedCells;
     278: aload         5
     280: invokevirtual #49                 // Method org/apache/hadoop/hbase/HColumnDescriptor.getKeepDeletedCells:()Lorg/apache/hadoop/hbase/KeepDeletedCells;
     283: invokestatic  #48                 // Method org/junit/Assert.assertEquals:(Ljava/lang/Object;Ljava/lang/Object;)V
     286: iload_3
     287: invokestatic  #50                 // Method java/lang/Boolean.valueOf:(Z)Ljava/lang/Boolean;
     290: aload         5
     292: invokevirtual #29                 // Method org/apache/hadoop/hbase/HColumnDescriptor.isInMemory:()Z
     295: invokestatic  #50                 // Method java/lang/Boolean.valueOf:(Z)Ljava/lang/Boolean;
     298: invokestatic  #48                 // Method org/junit/Assert.assertEquals:(Ljava/lang/Object;Ljava/lang/Object;)V
     301: aload_1
     302: invokevirtual #46                 // Method org/apache/hadoop/hbase/HColumnDescriptor.getScope:()I
     305: i2l
     306: aload         5
     308: invokevirtual #46                 // Method org/apache/hadoop/hbase/HColumnDescriptor.getScope:()I
     311: i2l
     312: invokestatic  #24                 // Method org/junit/Assert.assertEquals:(JJ)V
     315: aload         5
     317: invokevirtual #51                 // Method org/apache/hadoop/hbase/HColumnDescriptor.getCompressionType:()Lorg/apache/hadoop/hbase/io/compress/Compression$Algorithm;
     320: getstatic     #33                 // Field org/apache/hadoop/hbase/io/compress/Compression$Algorithm.SNAPPY:Lorg/apache/hadoop/hbase/io/compress/Compression$Algorithm;
     323: invokevirtual #52                 // Method org/apache/hadoop/hbase/io/compress/Compression$Algorithm.equals:(Ljava/lang/Object;)Z
     326: invokestatic  #43                 // Method org/junit/Assert.assertTrue:(Z)V
     329: aload         5
     331: invokevirtual #53                 // Method org/apache/hadoop/hbase/HColumnDescriptor.getDataBlockEncoding:()Lorg/apache/hadoop/hbase/io/encoding/DataBlockEncoding;
     334: getstatic     #30                 // Field org/apache/hadoop/hbase/io/encoding/DataBlockEncoding.FAST_DIFF:Lorg/apache/hadoop/hbase/io/encoding/DataBlockEncoding;
     337: invokevirtual #54                 // Method org/apache/hadoop/hbase/io/encoding/DataBlockEncoding.equals:(Ljava/lang/Object;)Z
     340: invokestatic  #43                 // Method org/junit/Assert.assertTrue:(Z)V
     343: aload         5
     345: invokevirtual #55                 // Method org/apache/hadoop/hbase/HColumnDescriptor.getBloomFilterType:()Lorg/apache/hadoop/hbase/regionserver/BloomType;
     348: getstatic     #32                 // Field org/apache/hadoop/hbase/regionserver/BloomType.ROW:Lorg/apache/hadoop/hbase/regionserver/BloomType;
     351: invokevirtual #56                 // Method org/apache/hadoop/hbase/regionserver/BloomType.equals:(Ljava/lang/Object;)Z
     354: invokestatic  #43                 // Method org/junit/Assert.assertTrue:(Z)V
     357: aload_1
     358: invokevirtual #57                 // Method org/apache/hadoop/hbase/HColumnDescriptor.isMobEnabled:()Z
     361: invokestatic  #50                 // Method java/lang/Boolean.valueOf:(Z)Ljava/lang/Boolean;
     364: aload         5
     366: invokevirtual #57                 // Method org/apache/hadoop/hbase/HColumnDescriptor.isMobEnabled:()Z
     369: invokestatic  #50                 // Method java/lang/Boolean.valueOf:(Z)Ljava/lang/Boolean;
     372: invokestatic  #48                 // Method org/junit/Assert.assertEquals:(Ljava/lang/Object;Ljava/lang/Object;)V
     375: aload_1
     376: invokevirtual #58                 // Method org/apache/hadoop/hbase/HColumnDescriptor.getMobThreshold:()J
     379: aload         5
     381: invokevirtual #58                 // Method org/apache/hadoop/hbase/HColumnDescriptor.getMobThreshold:()J
     384: invokestatic  #24                 // Method org/junit/Assert.assertEquals:(JJ)V
     387: ldc2_w        #21                 // long 123l
     390: aload         5
     392: invokevirtual #59                 // Method org/apache/hadoop/hbase/HColumnDescriptor.getDFSReplication:()S
     395: i2l
     396: invokestatic  #24                 // Method org/junit/Assert.assertEquals:(JJ)V
     399: return

  public void testHColumnDescriptorShouldThrowIAEWhenFamilyNameEmpty() throws java.lang.Exception;
    Code:
       0: aload_0
       1: getfield      #3                  // Field expectedEx:Lorg/junit/rules/ExpectedException;
       4: ldc           #60                 // class java/lang/IllegalArgumentException
       6: invokevirtual #61                 // Method org/junit/rules/ExpectedException.expect:(Ljava/lang/Class;)V
       9: aload_0
      10: getfield      #3                  // Field expectedEx:Lorg/junit/rules/ExpectedException;
      13: ldc           #62                 // String Column Family name can not be empty
      15: invokevirtual #63                 // Method org/junit/rules/ExpectedException.expectMessage:(Ljava/lang/String;)V
      18: new           #4                  // class org/apache/hadoop/hbase/HColumnDescriptor
      21: dup
      22: ldc           #64                 // String
      24: invokestatic  #65                 // Method org/apache/hadoop/hbase/util/Bytes.toBytes:(Ljava/lang/String;)[B
      27: invokespecial #6                  // Method org/apache/hadoop/hbase/HColumnDescriptor."<init>":([B)V
      30: pop
      31: return

  public void testAddGetRemoveConfiguration() throws java.lang.Exception;
    Code:
       0: new           #4                  // class org/apache/hadoop/hbase/HColumnDescriptor
       3: dup
       4: ldc           #66                 // String foo
       6: invokespecial #67                 // Method org/apache/hadoop/hbase/HColumnDescriptor."<init>":(Ljava/lang/String;)V
       9: astore_1
      10: ldc           #68                 // String Some
      12: astore_2
      13: ldc           #69                 // String value
      15: astore_3
      16: aload_1
      17: aload_2
      18: aload_3
      19: invokevirtual #70                 // Method org/apache/hadoop/hbase/HColumnDescriptor.setConfiguration:(Ljava/lang/String;Ljava/lang/String;)Lorg/apache/hadoop/hbase/HColumnDescriptor;
      22: pop
      23: aload_3
      24: aload_1
      25: aload_2
      26: invokevirtual #71                 // Method org/apache/hadoop/hbase/HColumnDescriptor.getConfigurationValue:(Ljava/lang/String;)Ljava/lang/String;
      29: invokestatic  #48                 // Method org/junit/Assert.assertEquals:(Ljava/lang/Object;Ljava/lang/Object;)V
      32: aload_1
      33: aload_2
      34: invokevirtual #72                 // Method org/apache/hadoop/hbase/HColumnDescriptor.removeConfiguration:(Ljava/lang/String;)V
      37: aconst_null
      38: aload_1
      39: aload_2
      40: invokevirtual #71                 // Method org/apache/hadoop/hbase/HColumnDescriptor.getConfigurationValue:(Ljava/lang/String;)Ljava/lang/String;
      43: invokestatic  #48                 // Method org/junit/Assert.assertEquals:(Ljava/lang/Object;Ljava/lang/Object;)V
      46: return

  public void testMobValuesInHColumnDescriptorShouldReadable();
    Code:
       0: iconst_1
       1: istore_1
       2: ldc2_w        #36                 // long 1000l
       5: lstore_2
       6: ldc           #73                 // String weekly
       8: astore        4
      10: iload_1
      11: invokestatic  #74                 // Method java/lang/String.valueOf:(Z)Ljava/lang/String;
      14: ldc           #75                 // String IS_MOB
      16: invokestatic  #76                 // Method org/apache/hadoop/hbase/HColumnDescriptor.getUnit:(Ljava/lang/String;)Lorg/apache/hadoop/hbase/util/PrettyPrinter$Unit;
      19: invokestatic  #77                 // Method org/apache/hadoop/hbase/util/PrettyPrinter.format:(Ljava/lang/String;Lorg/apache/hadoop/hbase/util/PrettyPrinter$Unit;)Ljava/lang/String;
      22: astore        5
      24: lload_2
      25: invokestatic  #78                 // Method java/lang/String.valueOf:(J)Ljava/lang/String;
      28: ldc           #79                 // String MOB_THRESHOLD
      30: invokestatic  #76                 // Method org/apache/hadoop/hbase/HColumnDescriptor.getUnit:(Ljava/lang/String;)Lorg/apache/hadoop/hbase/util/PrettyPrinter$Unit;
      33: invokestatic  #77                 // Method org/apache/hadoop/hbase/util/PrettyPrinter.format:(Ljava/lang/String;Lorg/apache/hadoop/hbase/util/PrettyPrinter$Unit;)Ljava/lang/String;
      36: astore        6
      38: aload         4
      40: invokestatic  #65                 // Method org/apache/hadoop/hbase/util/Bytes.toBytes:(Ljava/lang/String;)[B
      43: invokestatic  #80                 // Method org/apache/hadoop/hbase/util/Bytes.toStringBinary:([B)Ljava/lang/String;
      46: ldc           #81                 // String MOB_COMPACT_PARTITION_POLICY
      48: invokestatic  #76                 // Method org/apache/hadoop/hbase/HColumnDescriptor.getUnit:(Ljava/lang/String;)Lorg/apache/hadoop/hbase/util/PrettyPrinter$Unit;
      51: invokestatic  #77                 // Method org/apache/hadoop/hbase/util/PrettyPrinter.format:(Ljava/lang/String;Lorg/apache/hadoop/hbase/util/PrettyPrinter$Unit;)Ljava/lang/String;
      54: astore        7
      56: iload_1
      57: invokestatic  #74                 // Method java/lang/String.valueOf:(Z)Ljava/lang/String;
      60: aload         5
      62: invokestatic  #48                 // Method org/junit/Assert.assertEquals:(Ljava/lang/Object;Ljava/lang/Object;)V
      65: lload_2
      66: invokestatic  #78                 // Method java/lang/String.valueOf:(J)Ljava/lang/String;
      69: aload         6
      71: invokestatic  #48                 // Method org/junit/Assert.assertEquals:(Ljava/lang/Object;Ljava/lang/Object;)V
      74: aload         4
      76: invokestatic  #82                 // Method java/lang/String.valueOf:(Ljava/lang/Object;)Ljava/lang/String;
      79: aload         7
      81: invokestatic  #48                 // Method org/junit/Assert.assertEquals:(Ljava/lang/Object;Ljava/lang/Object;)V
      84: return

  public void testClassMethodsAreBuilderStyle();
    Code:
       0: iconst_1
       1: anewarray     #83                 // class java/lang/Class
       4: dup
       5: iconst_0
       6: ldc           #4                  // class org/apache/hadoop/hbase/HColumnDescriptor
       8: aastore
       9: invokestatic  #84                 // Method org/apache/hadoop/hbase/util/BuilderStyleTest.assertClassesAreBuilderStyle:([Ljava/lang/Class;)V
      12: return

  public void testSetTimeToLive() throws org.apache.hadoop.hbase.exceptions.HBaseException;
    Code:
       0: new           #4                  // class org/apache/hadoop/hbase/HColumnDescriptor
       3: dup
       4: ldc           #66                 // String foo
       6: invokespecial #67                 // Method org/apache/hadoop/hbase/HColumnDescriptor."<init>":(Ljava/lang/String;)V
       9: astore_2
      10: ldc           #85                 // String 50000
      12: astore_1
      13: aload_2
      14: aload_1
      15: invokevirtual #86                 // Method org/apache/hadoop/hbase/HColumnDescriptor.setTimeToLive:(Ljava/lang/String;)Lorg/apache/hadoop/hbase/HColumnDescriptor;
      18: pop
      19: ldc2_w        #87                 // long 50000l
      22: aload_2
      23: invokevirtual #45                 // Method org/apache/hadoop/hbase/HColumnDescriptor.getTimeToLive:()I
      26: i2l
      27: invokestatic  #24                 // Method org/junit/Assert.assertEquals:(JJ)V
      30: ldc           #89                 // String 50000 seconds
      32: astore_1
      33: aload_2
      34: aload_1
      35: invokevirtual #86                 // Method org/apache/hadoop/hbase/HColumnDescriptor.setTimeToLive:(Ljava/lang/String;)Lorg/apache/hadoop/hbase/HColumnDescriptor;
      38: pop
      39: ldc2_w        #87                 // long 50000l
      42: aload_2
      43: invokevirtual #45                 // Method org/apache/hadoop/hbase/HColumnDescriptor.getTimeToLive:()I
      46: i2l
      47: invokestatic  #24                 // Method org/junit/Assert.assertEquals:(JJ)V
      50: ldc           #64                 // String
      52: astore_1
      53: aload_2
      54: aload_1
      55: invokevirtual #86                 // Method org/apache/hadoop/hbase/HColumnDescriptor.setTimeToLive:(Ljava/lang/String;)Lorg/apache/hadoop/hbase/HColumnDescriptor;
      58: pop
      59: lconst_0
      60: aload_2
      61: invokevirtual #45                 // Method org/apache/hadoop/hbase/HColumnDescriptor.getTimeToLive:()I
      64: i2l
      65: invokestatic  #24                 // Method org/junit/Assert.assertEquals:(JJ)V
      68: ldc           #90                 // String FOREVER
      70: astore_1
      71: aload_2
      72: aload_1
      73: invokevirtual #86                 // Method org/apache/hadoop/hbase/HColumnDescriptor.setTimeToLive:(Ljava/lang/String;)Lorg/apache/hadoop/hbase/HColumnDescriptor;
      76: pop
      77: ldc2_w        #91                 // long 2147483647l
      80: aload_2
      81: invokevirtual #45                 // Method org/apache/hadoop/hbase/HColumnDescriptor.getTimeToLive:()I
      84: i2l
      85: invokestatic  #24                 // Method org/junit/Assert.assertEquals:(JJ)V
      88: ldc           #93                 // String 1 HOUR 10 minutes 1 second
      90: astore_1
      91: aload_2
      92: aload_1
      93: invokevirtual #86                 // Method org/apache/hadoop/hbase/HColumnDescriptor.setTimeToLive:(Ljava/lang/String;)Lorg/apache/hadoop/hbase/HColumnDescriptor;
      96: pop
      97: ldc2_w        #94                 // long 4201l
     100: aload_2
     101: invokevirtual #45                 // Method org/apache/hadoop/hbase/HColumnDescriptor.getTimeToLive:()I
     104: i2l
     105: invokestatic  #24                 // Method org/junit/Assert.assertEquals:(JJ)V
     108: ldc           #96                 // String 500 Days 23 HOURS
     110: astore_1
     111: aload_2
     112: aload_1
     113: invokevirtual #86                 // Method org/apache/hadoop/hbase/HColumnDescriptor.setTimeToLive:(Ljava/lang/String;)Lorg/apache/hadoop/hbase/HColumnDescriptor;
     116: pop
     117: ldc2_w        #97                 // long 43282800l
     120: aload_2
     121: invokevirtual #45                 // Method org/apache/hadoop/hbase/HColumnDescriptor.getTimeToLive:()I
     124: i2l
     125: invokestatic  #24                 // Method org/junit/Assert.assertEquals:(JJ)V
     128: ldc           #99                 // String 43282800 SECONDS (500 Days 23 hours)
     130: astore_1
     131: aload_2
     132: aload_1
     133: invokevirtual #86                 // Method org/apache/hadoop/hbase/HColumnDescriptor.setTimeToLive:(Ljava/lang/String;)Lorg/apache/hadoop/hbase/HColumnDescriptor;
     136: pop
     137: ldc2_w        #97                 // long 43282800l
     140: aload_2
     141: invokevirtual #45                 // Method org/apache/hadoop/hbase/HColumnDescriptor.getTimeToLive:()I
     144: i2l
     145: invokestatic  #24                 // Method org/junit/Assert.assertEquals:(JJ)V
     148: return

  static {};
    Code:
       0: ldc           #100                // class org/apache/hadoop/hbase/TestHColumnDescriptor
       2: invokestatic  #101                // Method org/apache/hadoop/hbase/HBaseClassTestRule.forClass:(Ljava/lang/Class;)Lorg/apache/hadoop/hbase/HBaseClassTestRule;
       5: putstatic     #102                // Field CLASS_RULE:Lorg/apache/hadoop/hbase/HBaseClassTestRule;
       8: return
}
