Compiled from "TestSnapshotTemporaryDirectory.java"
public class org.apache.hadoop.hbase.client.TestSnapshotTemporaryDirectory {
  public static final org.apache.hadoop.hbase.HBaseClassTestRule CLASS_RULE;

  public int manifestVersion;

  protected static final int NUM_RS;

  protected static java.lang.String TEMP_DIR;

  protected static org.apache.hadoop.hbase.client.Admin admin;

  protected static final org.apache.hadoop.hbase.HBaseTestingUtility UTIL;

  protected static final java.lang.String STRING_TABLE_NAME;

  protected static final byte[] TEST_FAM;

  protected static final org.apache.hadoop.hbase.TableName TABLE_NAME;

  public org.apache.hadoop.hbase.client.TestSnapshotTemporaryDirectory();
    Code:
       0: aload_0
       1: invokespecial #1                  // Method java/lang/Object."<init>":()V
       4: return

  public static java.lang.Iterable<java.lang.Integer> data();
    Code:
       0: iconst_2
       1: anewarray     #2                  // class java/lang/Integer
       4: dup
       5: iconst_0
       6: iconst_0
       7: invokestatic  #4                  // Method java/lang/Integer.valueOf:(I)Ljava/lang/Integer;
      10: aastore
      11: dup
      12: iconst_1
      13: iconst_2
      14: invokestatic  #4                  // Method java/lang/Integer.valueOf:(I)Ljava/lang/Integer;
      17: aastore
      18: invokestatic  #6                  // Method java/util/Arrays.asList:([Ljava/lang/Object;)Ljava/util/List;
      21: areturn

  public static void setupCluster() throws java.lang.Exception;
    Code:
       0: getstatic     #7                  // Field UTIL:Lorg/apache/hadoop/hbase/HBaseTestingUtility;
       3: invokevirtual #8                  // Method org/apache/hadoop/hbase/HBaseTestingUtility.getConfiguration:()Lorg/apache/hadoop/conf/Configuration;
       6: invokestatic  #9                  // Method setupConf:(Lorg/apache/hadoop/conf/Configuration;)V
       9: getstatic     #7                  // Field UTIL:Lorg/apache/hadoop/hbase/HBaseTestingUtility;
      12: iconst_2
      13: invokevirtual #11                 // Method org/apache/hadoop/hbase/HBaseTestingUtility.startMiniCluster:(I)Lorg/apache/hadoop/hbase/MiniHBaseCluster;
      16: pop
      17: getstatic     #7                  // Field UTIL:Lorg/apache/hadoop/hbase/HBaseTestingUtility;
      20: invokevirtual #12                 // Method org/apache/hadoop/hbase/HBaseTestingUtility.getHBaseAdmin:()Lorg/apache/hadoop/hbase/client/HBaseAdmin;
      23: putstatic     #13                 // Field admin:Lorg/apache/hadoop/hbase/client/Admin;
      26: return

  public void setup() throws java.lang.Exception;
    Code:
       0: new           #41                 // class org/apache/hadoop/hbase/HTableDescriptor
       3: dup
       4: getstatic     #42                 // Field TABLE_NAME:Lorg/apache/hadoop/hbase/TableName;
       7: invokespecial #43                 // Method org/apache/hadoop/hbase/HTableDescriptor."<init>":(Lorg/apache/hadoop/hbase/TableName;)V
      10: astore_1
      11: aload_1
      12: aload_0
      13: invokevirtual #44                 // Method getNumReplicas:()I
      16: invokevirtual #45                 // Method org/apache/hadoop/hbase/HTableDescriptor.setRegionReplication:(I)Lorg/apache/hadoop/hbase/HTableDescriptor;
      19: pop
      20: getstatic     #7                  // Field UTIL:Lorg/apache/hadoop/hbase/HBaseTestingUtility;
      23: aload_1
      24: iconst_1
      25: anewarray     #46                 // class "[B"
      28: dup
      29: iconst_0
      30: getstatic     #47                 // Field TEST_FAM:[B
      33: aastore
      34: getstatic     #7                  // Field UTIL:Lorg/apache/hadoop/hbase/HBaseTestingUtility;
      37: invokevirtual #8                  // Method org/apache/hadoop/hbase/HBaseTestingUtility.getConfiguration:()Lorg/apache/hadoop/conf/Configuration;
      40: invokevirtual #48                 // Method org/apache/hadoop/hbase/HBaseTestingUtility.createTable:(Lorg/apache/hadoop/hbase/client/TableDescriptor;[[BLorg/apache/hadoop/conf/Configuration;)Lorg/apache/hadoop/hbase/client/Table;
      43: pop
      44: return

  protected int getNumReplicas();
    Code:
       0: iconst_1
       1: ireturn

  public void tearDown() throws java.lang.Exception;
    Code:
       0: getstatic     #7                  // Field UTIL:Lorg/apache/hadoop/hbase/HBaseTestingUtility;
       3: getstatic     #42                 // Field TABLE_NAME:Lorg/apache/hadoop/hbase/TableName;
       6: invokevirtual #49                 // Method org/apache/hadoop/hbase/HBaseTestingUtility.deleteTable:(Lorg/apache/hadoop/hbase/TableName;)V
       9: getstatic     #7                  // Field UTIL:Lorg/apache/hadoop/hbase/HBaseTestingUtility;
      12: invokevirtual #12                 // Method org/apache/hadoop/hbase/HBaseTestingUtility.getHBaseAdmin:()Lorg/apache/hadoop/hbase/client/HBaseAdmin;
      15: invokestatic  #50                 // Method org/apache/hadoop/hbase/snapshot/SnapshotTestingUtils.deleteAllSnapshots:(Lorg/apache/hadoop/hbase/client/Admin;)V
      18: getstatic     #7                  // Field UTIL:Lorg/apache/hadoop/hbase/HBaseTestingUtility;
      21: invokestatic  #51                 // Method org/apache/hadoop/hbase/snapshot/SnapshotTestingUtils.deleteArchiveDirectory:(Lorg/apache/hadoop/hbase/HBaseTestingUtility;)V
      24: return

  public static void cleanupTest();
    Code:
       0: getstatic     #7                  // Field UTIL:Lorg/apache/hadoop/hbase/HBaseTestingUtility;
       3: invokevirtual #52                 // Method org/apache/hadoop/hbase/HBaseTestingUtility.shutdownMiniCluster:()V
       6: new           #53                 // class java/io/File
       9: dup
      10: getstatic     #35                 // Field TEMP_DIR:Ljava/lang/String;
      13: invokespecial #54                 // Method java/io/File."<init>":(Ljava/lang/String;)V
      16: invokestatic  #55                 // Method org/apache/commons/io/FileUtils.deleteDirectory:(Ljava/io/File;)V
      19: goto          34
      22: astore_0
      23: getstatic     #57                 // Field LOG:Lorg/slf4j/Logger;
      26: ldc           #58                 // String failure shutting down cluster
      28: aload_0
      29: invokeinterface #59,  3           // InterfaceMethod org/slf4j/Logger.warn:(Ljava/lang/String;Ljava/lang/Throwable;)V
      34: return
    Exception table:
       from    to  target type
           0    19    22   Class java/lang/Exception

  public void testRestoreDisabledSnapshot() throws java.io.IOException, java.lang.InterruptedException;
    Code:
       0: invokestatic  #60                 // Method java/lang/System.currentTimeMillis:()J
       3: lstore_1
       4: new           #30                 // class java/lang/StringBuilder
       7: dup
       8: invokespecial #31                 // Method java/lang/StringBuilder."<init>":()V
      11: ldc           #61                 // String testtb-
      13: invokevirtual #33                 // Method java/lang/StringBuilder.append:(Ljava/lang/String;)Ljava/lang/StringBuilder;
      16: lload_1
      17: invokevirtual #62                 // Method java/lang/StringBuilder.append:(J)Ljava/lang/StringBuilder;
      20: invokevirtual #40                 // Method java/lang/StringBuilder.toString:()Ljava/lang/String;
      23: invokestatic  #63                 // Method org/apache/hadoop/hbase/TableName.valueOf:(Ljava/lang/String;)Lorg/apache/hadoop/hbase/TableName;
      26: astore_3
      27: new           #30                 // class java/lang/StringBuilder
      30: dup
      31: invokespecial #31                 // Method java/lang/StringBuilder."<init>":()V
      34: ldc           #64                 // String emptySnaptb-
      36: invokevirtual #33                 // Method java/lang/StringBuilder.append:(Ljava/lang/String;)Ljava/lang/StringBuilder;
      39: lload_1
      40: invokevirtual #62                 // Method java/lang/StringBuilder.append:(J)Ljava/lang/StringBuilder;
      43: invokevirtual #40                 // Method java/lang/StringBuilder.toString:()Ljava/lang/String;
      46: astore        4
      48: new           #30                 // class java/lang/StringBuilder
      51: dup
      52: invokespecial #31                 // Method java/lang/StringBuilder."<init>":()V
      55: ldc           #65                 // String snaptb0-
      57: invokevirtual #33                 // Method java/lang/StringBuilder.append:(Ljava/lang/String;)Ljava/lang/StringBuilder;
      60: lload_1
      61: invokevirtual #62                 // Method java/lang/StringBuilder.append:(J)Ljava/lang/StringBuilder;
      64: invokevirtual #40                 // Method java/lang/StringBuilder.toString:()Ljava/lang/String;
      67: astore        5
      69: new           #30                 // class java/lang/StringBuilder
      72: dup
      73: invokespecial #31                 // Method java/lang/StringBuilder."<init>":()V
      76: ldc           #66                 // String snaptb1-
      78: invokevirtual #33                 // Method java/lang/StringBuilder.append:(Ljava/lang/String;)Ljava/lang/StringBuilder;
      81: lload_1
      82: invokevirtual #62                 // Method java/lang/StringBuilder.append:(J)Ljava/lang/StringBuilder;
      85: invokevirtual #40                 // Method java/lang/StringBuilder.toString:()Ljava/lang/String;
      88: astore        6
      90: getstatic     #7                  // Field UTIL:Lorg/apache/hadoop/hbase/HBaseTestingUtility;
      93: aload_3
      94: aload_0
      95: invokevirtual #44                 // Method getNumReplicas:()I
      98: iconst_1
      99: anewarray     #46                 // class "[B"
     102: dup
     103: iconst_0
     104: getstatic     #47                 // Field TEST_FAM:[B
     107: aastore
     108: invokestatic  #67                 // Method org/apache/hadoop/hbase/snapshot/SnapshotTestingUtils.createTable:(Lorg/apache/hadoop/hbase/HBaseTestingUtility;Lorg/apache/hadoop/hbase/TableName;I[[B)V
     111: getstatic     #13                 // Field admin:Lorg/apache/hadoop/hbase/client/Admin;
     114: aload_3
     115: invokeinterface #68,  2           // InterfaceMethod org/apache/hadoop/hbase/client/Admin.disableTable:(Lorg/apache/hadoop/hbase/TableName;)V
     120: aload_0
     121: aload_3
     122: aload         4
     124: iconst_1
     125: invokespecial #69                 // Method takeSnapshot:(Lorg/apache/hadoop/hbase/TableName;Ljava/lang/String;Z)V
     128: getstatic     #13                 // Field admin:Lorg/apache/hadoop/hbase/client/Admin;
     131: aload_3
     132: invokeinterface #70,  2           // InterfaceMethod org/apache/hadoop/hbase/client/Admin.enableTable:(Lorg/apache/hadoop/hbase/TableName;)V
     137: getstatic     #7                  // Field UTIL:Lorg/apache/hadoop/hbase/HBaseTestingUtility;
     140: aload_3
     141: sipush        500
     144: iconst_1
     145: anewarray     #46                 // class "[B"
     148: dup
     149: iconst_0
     150: getstatic     #47                 // Field TEST_FAM:[B
     153: aastore
     154: invokestatic  #71                 // Method org/apache/hadoop/hbase/snapshot/SnapshotTestingUtils.loadData:(Lorg/apache/hadoop/hbase/HBaseTestingUtility;Lorg/apache/hadoop/hbase/TableName;I[[B)V
     157: getstatic     #7                  // Field UTIL:Lorg/apache/hadoop/hbase/HBaseTestingUtility;
     160: invokevirtual #72                 // Method org/apache/hadoop/hbase/HBaseTestingUtility.getConnection:()Lorg/apache/hadoop/hbase/client/Connection;
     163: aload_3
     164: invokeinterface #73,  2           // InterfaceMethod org/apache/hadoop/hbase/client/Connection.getTable:(Lorg/apache/hadoop/hbase/TableName;)Lorg/apache/hadoop/hbase/client/Table;
     169: astore        9
     171: aconst_null
     172: astore        10
     174: getstatic     #7                  // Field UTIL:Lorg/apache/hadoop/hbase/HBaseTestingUtility;
     177: pop
     178: aload         9
     180: invokestatic  #74                 // Method org/apache/hadoop/hbase/HBaseTestingUtility.countRows:(Lorg/apache/hadoop/hbase/client/Table;)I
     183: istore        7
     185: aload         9
     187: ifnull        280
     190: aload         10
     192: ifnull        217
     195: aload         9
     197: invokeinterface #75,  1           // InterfaceMethod org/apache/hadoop/hbase/client/Table.close:()V
     202: goto          280
     205: astore        11
     207: aload         10
     209: aload         11
     211: invokevirtual #77                 // Method java/lang/Throwable.addSuppressed:(Ljava/lang/Throwable;)V
     214: goto          280
     217: aload         9
     219: invokeinterface #75,  1           // InterfaceMethod org/apache/hadoop/hbase/client/Table.close:()V
     224: goto          280
     227: astore        11
     229: aload         11
     231: astore        10
     233: aload         11
     235: athrow
     236: astore        12
     238: aload         9
     240: ifnull        277
     243: aload         10
     245: ifnull        270
     248: aload         9
     250: invokeinterface #75,  1           // InterfaceMethod org/apache/hadoop/hbase/client/Table.close:()V
     255: goto          277
     258: astore        13
     260: aload         10
     262: aload         13
     264: invokevirtual #77                 // Method java/lang/Throwable.addSuppressed:(Ljava/lang/Throwable;)V
     267: goto          277
     270: aload         9
     272: invokeinterface #75,  1           // InterfaceMethod org/apache/hadoop/hbase/client/Table.close:()V
     277: aload         12
     279: athrow
     280: getstatic     #13                 // Field admin:Lorg/apache/hadoop/hbase/client/Admin;
     283: aload_3
     284: invokeinterface #68,  2           // InterfaceMethod org/apache/hadoop/hbase/client/Admin.disableTable:(Lorg/apache/hadoop/hbase/TableName;)V
     289: aload_0
     290: aload_3
     291: aload         5
     293: iconst_1
     294: invokespecial #69                 // Method takeSnapshot:(Lorg/apache/hadoop/hbase/TableName;Ljava/lang/String;Z)V
     297: getstatic     #13                 // Field admin:Lorg/apache/hadoop/hbase/client/Admin;
     300: aload_3
     301: invokeinterface #70,  2           // InterfaceMethod org/apache/hadoop/hbase/client/Admin.enableTable:(Lorg/apache/hadoop/hbase/TableName;)V
     306: getstatic     #7                  // Field UTIL:Lorg/apache/hadoop/hbase/HBaseTestingUtility;
     309: aload_3
     310: sipush        500
     313: iconst_1
     314: anewarray     #46                 // class "[B"
     317: dup
     318: iconst_0
     319: getstatic     #47                 // Field TEST_FAM:[B
     322: aastore
     323: invokestatic  #71                 // Method org/apache/hadoop/hbase/snapshot/SnapshotTestingUtils.loadData:(Lorg/apache/hadoop/hbase/HBaseTestingUtility;Lorg/apache/hadoop/hbase/TableName;I[[B)V
     326: getstatic     #7                  // Field UTIL:Lorg/apache/hadoop/hbase/HBaseTestingUtility;
     329: invokevirtual #72                 // Method org/apache/hadoop/hbase/HBaseTestingUtility.getConnection:()Lorg/apache/hadoop/hbase/client/Connection;
     332: aload_3
     333: invokeinterface #73,  2           // InterfaceMethod org/apache/hadoop/hbase/client/Connection.getTable:(Lorg/apache/hadoop/hbase/TableName;)Lorg/apache/hadoop/hbase/client/Table;
     338: astore        9
     340: aconst_null
     341: astore        10
     343: getstatic     #7                  // Field UTIL:Lorg/apache/hadoop/hbase/HBaseTestingUtility;
     346: pop
     347: aload         9
     349: invokestatic  #74                 // Method org/apache/hadoop/hbase/HBaseTestingUtility.countRows:(Lorg/apache/hadoop/hbase/client/Table;)I
     352: istore        8
     354: aload         9
     356: ifnull        449
     359: aload         10
     361: ifnull        386
     364: aload         9
     366: invokeinterface #75,  1           // InterfaceMethod org/apache/hadoop/hbase/client/Table.close:()V
     371: goto          449
     374: astore        11
     376: aload         10
     378: aload         11
     380: invokevirtual #77                 // Method java/lang/Throwable.addSuppressed:(Ljava/lang/Throwable;)V
     383: goto          449
     386: aload         9
     388: invokeinterface #75,  1           // InterfaceMethod org/apache/hadoop/hbase/client/Table.close:()V
     393: goto          449
     396: astore        11
     398: aload         11
     400: astore        10
     402: aload         11
     404: athrow
     405: astore        14
     407: aload         9
     409: ifnull        446
     412: aload         10
     414: ifnull        439
     417: aload         9
     419: invokeinterface #75,  1           // InterfaceMethod org/apache/hadoop/hbase/client/Table.close:()V
     424: goto          446
     427: astore        15
     429: aload         10
     431: aload         15
     433: invokevirtual #77                 // Method java/lang/Throwable.addSuppressed:(Ljava/lang/Throwable;)V
     436: goto          446
     439: aload         9
     441: invokeinterface #75,  1           // InterfaceMethod org/apache/hadoop/hbase/client/Table.close:()V
     446: aload         14
     448: athrow
     449: getstatic     #7                  // Field UTIL:Lorg/apache/hadoop/hbase/HBaseTestingUtility;
     452: aload_3
     453: iload         8
     455: i2l
     456: invokestatic  #78                 // Method org/apache/hadoop/hbase/snapshot/SnapshotTestingUtils.verifyRowCount:(Lorg/apache/hadoop/hbase/HBaseTestingUtility;Lorg/apache/hadoop/hbase/TableName;J)V
     459: getstatic     #13                 // Field admin:Lorg/apache/hadoop/hbase/client/Admin;
     462: aload_3
     463: invokeinterface #68,  2           // InterfaceMethod org/apache/hadoop/hbase/client/Admin.disableTable:(Lorg/apache/hadoop/hbase/TableName;)V
     468: aload_0
     469: aload_3
     470: aload         6
     472: iconst_1
     473: invokespecial #69                 // Method takeSnapshot:(Lorg/apache/hadoop/hbase/TableName;Ljava/lang/String;Z)V
     476: getstatic     #13                 // Field admin:Lorg/apache/hadoop/hbase/client/Admin;
     479: aload         5
     481: invokeinterface #79,  2           // InterfaceMethod org/apache/hadoop/hbase/client/Admin.restoreSnapshot:(Ljava/lang/String;)V
     486: getstatic     #13                 // Field admin:Lorg/apache/hadoop/hbase/client/Admin;
     489: aload_3
     490: invokeinterface #70,  2           // InterfaceMethod org/apache/hadoop/hbase/client/Admin.enableTable:(Lorg/apache/hadoop/hbase/TableName;)V
     495: getstatic     #7                  // Field UTIL:Lorg/apache/hadoop/hbase/HBaseTestingUtility;
     498: aload_3
     499: iload         7
     501: i2l
     502: invokestatic  #78                 // Method org/apache/hadoop/hbase/snapshot/SnapshotTestingUtils.verifyRowCount:(Lorg/apache/hadoop/hbase/HBaseTestingUtility;Lorg/apache/hadoop/hbase/TableName;J)V
     505: aload_3
     506: getstatic     #13                 // Field admin:Lorg/apache/hadoop/hbase/client/Admin;
     509: aload_0
     510: invokevirtual #44                 // Method getNumReplicas:()I
     513: invokestatic  #80                 // Method org/apache/hadoop/hbase/snapshot/SnapshotTestingUtils.verifyReplicasCameOnline:(Lorg/apache/hadoop/hbase/TableName;Lorg/apache/hadoop/hbase/client/Admin;I)V
     516: getstatic     #13                 // Field admin:Lorg/apache/hadoop/hbase/client/Admin;
     519: aload_3
     520: invokeinterface #68,  2           // InterfaceMethod org/apache/hadoop/hbase/client/Admin.disableTable:(Lorg/apache/hadoop/hbase/TableName;)V
     525: getstatic     #13                 // Field admin:Lorg/apache/hadoop/hbase/client/Admin;
     528: aload         4
     530: invokeinterface #79,  2           // InterfaceMethod org/apache/hadoop/hbase/client/Admin.restoreSnapshot:(Ljava/lang/String;)V
     535: getstatic     #13                 // Field admin:Lorg/apache/hadoop/hbase/client/Admin;
     538: aload_3
     539: invokeinterface #70,  2           // InterfaceMethod org/apache/hadoop/hbase/client/Admin.enableTable:(Lorg/apache/hadoop/hbase/TableName;)V
     544: getstatic     #7                  // Field UTIL:Lorg/apache/hadoop/hbase/HBaseTestingUtility;
     547: aload_3
     548: lconst_0
     549: invokestatic  #78                 // Method org/apache/hadoop/hbase/snapshot/SnapshotTestingUtils.verifyRowCount:(Lorg/apache/hadoop/hbase/HBaseTestingUtility;Lorg/apache/hadoop/hbase/TableName;J)V
     552: aload_3
     553: getstatic     #13                 // Field admin:Lorg/apache/hadoop/hbase/client/Admin;
     556: aload_0
     557: invokevirtual #44                 // Method getNumReplicas:()I
     560: invokestatic  #80                 // Method org/apache/hadoop/hbase/snapshot/SnapshotTestingUtils.verifyReplicasCameOnline:(Lorg/apache/hadoop/hbase/TableName;Lorg/apache/hadoop/hbase/client/Admin;I)V
     563: getstatic     #13                 // Field admin:Lorg/apache/hadoop/hbase/client/Admin;
     566: aload_3
     567: invokeinterface #68,  2           // InterfaceMethod org/apache/hadoop/hbase/client/Admin.disableTable:(Lorg/apache/hadoop/hbase/TableName;)V
     572: getstatic     #13                 // Field admin:Lorg/apache/hadoop/hbase/client/Admin;
     575: aload         6
     577: invokeinterface #79,  2           // InterfaceMethod org/apache/hadoop/hbase/client/Admin.restoreSnapshot:(Ljava/lang/String;)V
     582: getstatic     #13                 // Field admin:Lorg/apache/hadoop/hbase/client/Admin;
     585: aload_3
     586: invokeinterface #70,  2           // InterfaceMethod org/apache/hadoop/hbase/client/Admin.enableTable:(Lorg/apache/hadoop/hbase/TableName;)V
     591: getstatic     #7                  // Field UTIL:Lorg/apache/hadoop/hbase/HBaseTestingUtility;
     594: aload_3
     595: iload         8
     597: i2l
     598: invokestatic  #78                 // Method org/apache/hadoop/hbase/snapshot/SnapshotTestingUtils.verifyRowCount:(Lorg/apache/hadoop/hbase/HBaseTestingUtility;Lorg/apache/hadoop/hbase/TableName;J)V
     601: aload_3
     602: getstatic     #13                 // Field admin:Lorg/apache/hadoop/hbase/client/Admin;
     605: aload_0
     606: invokevirtual #44                 // Method getNumReplicas:()I
     609: invokestatic  #80                 // Method org/apache/hadoop/hbase/snapshot/SnapshotTestingUtils.verifyReplicasCameOnline:(Lorg/apache/hadoop/hbase/TableName;Lorg/apache/hadoop/hbase/client/Admin;I)V
     612: getstatic     #7                  // Field UTIL:Lorg/apache/hadoop/hbase/HBaseTestingUtility;
     615: aload_3
     616: invokevirtual #49                 // Method org/apache/hadoop/hbase/HBaseTestingUtility.deleteTable:(Lorg/apache/hadoop/hbase/TableName;)V
     619: getstatic     #13                 // Field admin:Lorg/apache/hadoop/hbase/client/Admin;
     622: aload         6
     624: invokeinterface #79,  2           // InterfaceMethod org/apache/hadoop/hbase/client/Admin.restoreSnapshot:(Ljava/lang/String;)V
     629: getstatic     #7                  // Field UTIL:Lorg/apache/hadoop/hbase/HBaseTestingUtility;
     632: aload_3
     633: iload         8
     635: i2l
     636: invokestatic  #78                 // Method org/apache/hadoop/hbase/snapshot/SnapshotTestingUtils.verifyRowCount:(Lorg/apache/hadoop/hbase/HBaseTestingUtility;Lorg/apache/hadoop/hbase/TableName;J)V
     639: aload_3
     640: getstatic     #13                 // Field admin:Lorg/apache/hadoop/hbase/client/Admin;
     643: aload_0
     644: invokevirtual #44                 // Method getNumReplicas:()I
     647: invokestatic  #80                 // Method org/apache/hadoop/hbase/snapshot/SnapshotTestingUtils.verifyReplicasCameOnline:(Lorg/apache/hadoop/hbase/TableName;Lorg/apache/hadoop/hbase/client/Admin;I)V
     650: return
    Exception table:
       from    to  target type
         195   202   205   Class java/lang/Throwable
         174   185   227   Class java/lang/Throwable
         174   185   236   any
         248   255   258   Class java/lang/Throwable
         227   238   236   any
         364   371   374   Class java/lang/Throwable
         343   354   396   Class java/lang/Throwable
         343   354   405   any
         417   424   427   Class java/lang/Throwable
         396   407   405   any

  public void testRestoreEnabledSnapshot() throws java.io.IOException, java.lang.InterruptedException;
    Code:
       0: invokestatic  #60                 // Method java/lang/System.currentTimeMillis:()J
       3: lstore_1
       4: new           #30                 // class java/lang/StringBuilder
       7: dup
       8: invokespecial #31                 // Method java/lang/StringBuilder."<init>":()V
      11: ldc           #61                 // String testtb-
      13: invokevirtual #33                 // Method java/lang/StringBuilder.append:(Ljava/lang/String;)Ljava/lang/StringBuilder;
      16: lload_1
      17: invokevirtual #62                 // Method java/lang/StringBuilder.append:(J)Ljava/lang/StringBuilder;
      20: invokevirtual #40                 // Method java/lang/StringBuilder.toString:()Ljava/lang/String;
      23: invokestatic  #63                 // Method org/apache/hadoop/hbase/TableName.valueOf:(Ljava/lang/String;)Lorg/apache/hadoop/hbase/TableName;
      26: astore_3
      27: new           #30                 // class java/lang/StringBuilder
      30: dup
      31: invokespecial #31                 // Method java/lang/StringBuilder."<init>":()V
      34: ldc           #64                 // String emptySnaptb-
      36: invokevirtual #33                 // Method java/lang/StringBuilder.append:(Ljava/lang/String;)Ljava/lang/StringBuilder;
      39: lload_1
      40: invokevirtual #62                 // Method java/lang/StringBuilder.append:(J)Ljava/lang/StringBuilder;
      43: invokevirtual #40                 // Method java/lang/StringBuilder.toString:()Ljava/lang/String;
      46: astore        4
      48: new           #30                 // class java/lang/StringBuilder
      51: dup
      52: invokespecial #31                 // Method java/lang/StringBuilder."<init>":()V
      55: ldc           #65                 // String snaptb0-
      57: invokevirtual #33                 // Method java/lang/StringBuilder.append:(Ljava/lang/String;)Ljava/lang/StringBuilder;
      60: lload_1
      61: invokevirtual #62                 // Method java/lang/StringBuilder.append:(J)Ljava/lang/StringBuilder;
      64: invokevirtual #40                 // Method java/lang/StringBuilder.toString:()Ljava/lang/String;
      67: astore        5
      69: new           #30                 // class java/lang/StringBuilder
      72: dup
      73: invokespecial #31                 // Method java/lang/StringBuilder."<init>":()V
      76: ldc           #66                 // String snaptb1-
      78: invokevirtual #33                 // Method java/lang/StringBuilder.append:(Ljava/lang/String;)Ljava/lang/StringBuilder;
      81: lload_1
      82: invokevirtual #62                 // Method java/lang/StringBuilder.append:(J)Ljava/lang/StringBuilder;
      85: invokevirtual #40                 // Method java/lang/StringBuilder.toString:()Ljava/lang/String;
      88: astore        6
      90: getstatic     #7                  // Field UTIL:Lorg/apache/hadoop/hbase/HBaseTestingUtility;
      93: aload_3
      94: aload_0
      95: invokevirtual #44                 // Method getNumReplicas:()I
      98: iconst_1
      99: anewarray     #46                 // class "[B"
     102: dup
     103: iconst_0
     104: getstatic     #47                 // Field TEST_FAM:[B
     107: aastore
     108: invokestatic  #67                 // Method org/apache/hadoop/hbase/snapshot/SnapshotTestingUtils.createTable:(Lorg/apache/hadoop/hbase/HBaseTestingUtility;Lorg/apache/hadoop/hbase/TableName;I[[B)V
     111: aload_0
     112: aload_3
     113: aload         4
     115: iconst_0
     116: invokespecial #69                 // Method takeSnapshot:(Lorg/apache/hadoop/hbase/TableName;Ljava/lang/String;Z)V
     119: getstatic     #7                  // Field UTIL:Lorg/apache/hadoop/hbase/HBaseTestingUtility;
     122: aload_3
     123: sipush        500
     126: iconst_1
     127: anewarray     #46                 // class "[B"
     130: dup
     131: iconst_0
     132: getstatic     #47                 // Field TEST_FAM:[B
     135: aastore
     136: invokestatic  #71                 // Method org/apache/hadoop/hbase/snapshot/SnapshotTestingUtils.loadData:(Lorg/apache/hadoop/hbase/HBaseTestingUtility;Lorg/apache/hadoop/hbase/TableName;I[[B)V
     139: getstatic     #7                  // Field UTIL:Lorg/apache/hadoop/hbase/HBaseTestingUtility;
     142: invokevirtual #72                 // Method org/apache/hadoop/hbase/HBaseTestingUtility.getConnection:()Lorg/apache/hadoop/hbase/client/Connection;
     145: aload_3
     146: invokeinterface #73,  2           // InterfaceMethod org/apache/hadoop/hbase/client/Connection.getTable:(Lorg/apache/hadoop/hbase/TableName;)Lorg/apache/hadoop/hbase/client/Table;
     151: astore        9
     153: aconst_null
     154: astore        10
     156: getstatic     #7                  // Field UTIL:Lorg/apache/hadoop/hbase/HBaseTestingUtility;
     159: pop
     160: aload         9
     162: invokestatic  #74                 // Method org/apache/hadoop/hbase/HBaseTestingUtility.countRows:(Lorg/apache/hadoop/hbase/client/Table;)I
     165: istore        7
     167: aload         9
     169: ifnull        262
     172: aload         10
     174: ifnull        199
     177: aload         9
     179: invokeinterface #75,  1           // InterfaceMethod org/apache/hadoop/hbase/client/Table.close:()V
     184: goto          262
     187: astore        11
     189: aload         10
     191: aload         11
     193: invokevirtual #77                 // Method java/lang/Throwable.addSuppressed:(Ljava/lang/Throwable;)V
     196: goto          262
     199: aload         9
     201: invokeinterface #75,  1           // InterfaceMethod org/apache/hadoop/hbase/client/Table.close:()V
     206: goto          262
     209: astore        11
     211: aload         11
     213: astore        10
     215: aload         11
     217: athrow
     218: astore        12
     220: aload         9
     222: ifnull        259
     225: aload         10
     227: ifnull        252
     230: aload         9
     232: invokeinterface #75,  1           // InterfaceMethod org/apache/hadoop/hbase/client/Table.close:()V
     237: goto          259
     240: astore        13
     242: aload         10
     244: aload         13
     246: invokevirtual #77                 // Method java/lang/Throwable.addSuppressed:(Ljava/lang/Throwable;)V
     249: goto          259
     252: aload         9
     254: invokeinterface #75,  1           // InterfaceMethod org/apache/hadoop/hbase/client/Table.close:()V
     259: aload         12
     261: athrow
     262: aload_0
     263: aload_3
     264: aload         5
     266: iconst_0
     267: invokespecial #69                 // Method takeSnapshot:(Lorg/apache/hadoop/hbase/TableName;Ljava/lang/String;Z)V
     270: getstatic     #7                  // Field UTIL:Lorg/apache/hadoop/hbase/HBaseTestingUtility;
     273: aload_3
     274: sipush        500
     277: iconst_1
     278: anewarray     #46                 // class "[B"
     281: dup
     282: iconst_0
     283: getstatic     #47                 // Field TEST_FAM:[B
     286: aastore
     287: invokestatic  #71                 // Method org/apache/hadoop/hbase/snapshot/SnapshotTestingUtils.loadData:(Lorg/apache/hadoop/hbase/HBaseTestingUtility;Lorg/apache/hadoop/hbase/TableName;I[[B)V
     290: getstatic     #7                  // Field UTIL:Lorg/apache/hadoop/hbase/HBaseTestingUtility;
     293: invokevirtual #72                 // Method org/apache/hadoop/hbase/HBaseTestingUtility.getConnection:()Lorg/apache/hadoop/hbase/client/Connection;
     296: aload_3
     297: invokeinterface #73,  2           // InterfaceMethod org/apache/hadoop/hbase/client/Connection.getTable:(Lorg/apache/hadoop/hbase/TableName;)Lorg/apache/hadoop/hbase/client/Table;
     302: astore        9
     304: aconst_null
     305: astore        10
     307: getstatic     #7                  // Field UTIL:Lorg/apache/hadoop/hbase/HBaseTestingUtility;
     310: pop
     311: aload         9
     313: invokestatic  #74                 // Method org/apache/hadoop/hbase/HBaseTestingUtility.countRows:(Lorg/apache/hadoop/hbase/client/Table;)I
     316: istore        8
     318: aload         9
     320: ifnull        413
     323: aload         10
     325: ifnull        350
     328: aload         9
     330: invokeinterface #75,  1           // InterfaceMethod org/apache/hadoop/hbase/client/Table.close:()V
     335: goto          413
     338: astore        11
     340: aload         10
     342: aload         11
     344: invokevirtual #77                 // Method java/lang/Throwable.addSuppressed:(Ljava/lang/Throwable;)V
     347: goto          413
     350: aload         9
     352: invokeinterface #75,  1           // InterfaceMethod org/apache/hadoop/hbase/client/Table.close:()V
     357: goto          413
     360: astore        11
     362: aload         11
     364: astore        10
     366: aload         11
     368: athrow
     369: astore        14
     371: aload         9
     373: ifnull        410
     376: aload         10
     378: ifnull        403
     381: aload         9
     383: invokeinterface #75,  1           // InterfaceMethod org/apache/hadoop/hbase/client/Table.close:()V
     388: goto          410
     391: astore        15
     393: aload         10
     395: aload         15
     397: invokevirtual #77                 // Method java/lang/Throwable.addSuppressed:(Ljava/lang/Throwable;)V
     400: goto          410
     403: aload         9
     405: invokeinterface #75,  1           // InterfaceMethod org/apache/hadoop/hbase/client/Table.close:()V
     410: aload         14
     412: athrow
     413: getstatic     #7                  // Field UTIL:Lorg/apache/hadoop/hbase/HBaseTestingUtility;
     416: aload_3
     417: iload         8
     419: i2l
     420: invokestatic  #78                 // Method org/apache/hadoop/hbase/snapshot/SnapshotTestingUtils.verifyRowCount:(Lorg/apache/hadoop/hbase/HBaseTestingUtility;Lorg/apache/hadoop/hbase/TableName;J)V
     423: aload_0
     424: aload_3
     425: aload         6
     427: iconst_0
     428: invokespecial #69                 // Method takeSnapshot:(Lorg/apache/hadoop/hbase/TableName;Ljava/lang/String;Z)V
     431: getstatic     #13                 // Field admin:Lorg/apache/hadoop/hbase/client/Admin;
     434: aload_3
     435: invokeinterface #68,  2           // InterfaceMethod org/apache/hadoop/hbase/client/Admin.disableTable:(Lorg/apache/hadoop/hbase/TableName;)V
     440: getstatic     #13                 // Field admin:Lorg/apache/hadoop/hbase/client/Admin;
     443: aload         5
     445: invokeinterface #79,  2           // InterfaceMethod org/apache/hadoop/hbase/client/Admin.restoreSnapshot:(Ljava/lang/String;)V
     450: getstatic     #13                 // Field admin:Lorg/apache/hadoop/hbase/client/Admin;
     453: aload_3
     454: invokeinterface #70,  2           // InterfaceMethod org/apache/hadoop/hbase/client/Admin.enableTable:(Lorg/apache/hadoop/hbase/TableName;)V
     459: getstatic     #7                  // Field UTIL:Lorg/apache/hadoop/hbase/HBaseTestingUtility;
     462: aload_3
     463: iload         7
     465: i2l
     466: invokestatic  #78                 // Method org/apache/hadoop/hbase/snapshot/SnapshotTestingUtils.verifyRowCount:(Lorg/apache/hadoop/hbase/HBaseTestingUtility;Lorg/apache/hadoop/hbase/TableName;J)V
     469: aload_3
     470: getstatic     #13                 // Field admin:Lorg/apache/hadoop/hbase/client/Admin;
     473: aload_0
     474: invokevirtual #44                 // Method getNumReplicas:()I
     477: invokestatic  #80                 // Method org/apache/hadoop/hbase/snapshot/SnapshotTestingUtils.verifyReplicasCameOnline:(Lorg/apache/hadoop/hbase/TableName;Lorg/apache/hadoop/hbase/client/Admin;I)V
     480: getstatic     #13                 // Field admin:Lorg/apache/hadoop/hbase/client/Admin;
     483: aload_3
     484: invokeinterface #68,  2           // InterfaceMethod org/apache/hadoop/hbase/client/Admin.disableTable:(Lorg/apache/hadoop/hbase/TableName;)V
     489: getstatic     #13                 // Field admin:Lorg/apache/hadoop/hbase/client/Admin;
     492: aload         4
     494: invokeinterface #79,  2           // InterfaceMethod org/apache/hadoop/hbase/client/Admin.restoreSnapshot:(Ljava/lang/String;)V
     499: getstatic     #13                 // Field admin:Lorg/apache/hadoop/hbase/client/Admin;
     502: aload_3
     503: invokeinterface #70,  2           // InterfaceMethod org/apache/hadoop/hbase/client/Admin.enableTable:(Lorg/apache/hadoop/hbase/TableName;)V
     508: getstatic     #7                  // Field UTIL:Lorg/apache/hadoop/hbase/HBaseTestingUtility;
     511: aload_3
     512: lconst_0
     513: invokestatic  #78                 // Method org/apache/hadoop/hbase/snapshot/SnapshotTestingUtils.verifyRowCount:(Lorg/apache/hadoop/hbase/HBaseTestingUtility;Lorg/apache/hadoop/hbase/TableName;J)V
     516: aload_3
     517: getstatic     #13                 // Field admin:Lorg/apache/hadoop/hbase/client/Admin;
     520: aload_0
     521: invokevirtual #44                 // Method getNumReplicas:()I
     524: invokestatic  #80                 // Method org/apache/hadoop/hbase/snapshot/SnapshotTestingUtils.verifyReplicasCameOnline:(Lorg/apache/hadoop/hbase/TableName;Lorg/apache/hadoop/hbase/client/Admin;I)V
     527: getstatic     #13                 // Field admin:Lorg/apache/hadoop/hbase/client/Admin;
     530: aload_3
     531: invokeinterface #68,  2           // InterfaceMethod org/apache/hadoop/hbase/client/Admin.disableTable:(Lorg/apache/hadoop/hbase/TableName;)V
     536: getstatic     #13                 // Field admin:Lorg/apache/hadoop/hbase/client/Admin;
     539: aload         6
     541: invokeinterface #79,  2           // InterfaceMethod org/apache/hadoop/hbase/client/Admin.restoreSnapshot:(Ljava/lang/String;)V
     546: getstatic     #13                 // Field admin:Lorg/apache/hadoop/hbase/client/Admin;
     549: aload_3
     550: invokeinterface #70,  2           // InterfaceMethod org/apache/hadoop/hbase/client/Admin.enableTable:(Lorg/apache/hadoop/hbase/TableName;)V
     555: getstatic     #7                  // Field UTIL:Lorg/apache/hadoop/hbase/HBaseTestingUtility;
     558: aload_3
     559: iload         8
     561: i2l
     562: invokestatic  #78                 // Method org/apache/hadoop/hbase/snapshot/SnapshotTestingUtils.verifyRowCount:(Lorg/apache/hadoop/hbase/HBaseTestingUtility;Lorg/apache/hadoop/hbase/TableName;J)V
     565: aload_3
     566: getstatic     #13                 // Field admin:Lorg/apache/hadoop/hbase/client/Admin;
     569: aload_0
     570: invokevirtual #44                 // Method getNumReplicas:()I
     573: invokestatic  #80                 // Method org/apache/hadoop/hbase/snapshot/SnapshotTestingUtils.verifyReplicasCameOnline:(Lorg/apache/hadoop/hbase/TableName;Lorg/apache/hadoop/hbase/client/Admin;I)V
     576: getstatic     #7                  // Field UTIL:Lorg/apache/hadoop/hbase/HBaseTestingUtility;
     579: aload_3
     580: invokevirtual #49                 // Method org/apache/hadoop/hbase/HBaseTestingUtility.deleteTable:(Lorg/apache/hadoop/hbase/TableName;)V
     583: getstatic     #13                 // Field admin:Lorg/apache/hadoop/hbase/client/Admin;
     586: aload         6
     588: invokeinterface #79,  2           // InterfaceMethod org/apache/hadoop/hbase/client/Admin.restoreSnapshot:(Ljava/lang/String;)V
     593: getstatic     #7                  // Field UTIL:Lorg/apache/hadoop/hbase/HBaseTestingUtility;
     596: aload_3
     597: iload         8
     599: i2l
     600: invokestatic  #78                 // Method org/apache/hadoop/hbase/snapshot/SnapshotTestingUtils.verifyRowCount:(Lorg/apache/hadoop/hbase/HBaseTestingUtility;Lorg/apache/hadoop/hbase/TableName;J)V
     603: aload_3
     604: getstatic     #13                 // Field admin:Lorg/apache/hadoop/hbase/client/Admin;
     607: aload_0
     608: invokevirtual #44                 // Method getNumReplicas:()I
     611: invokestatic  #80                 // Method org/apache/hadoop/hbase/snapshot/SnapshotTestingUtils.verifyReplicasCameOnline:(Lorg/apache/hadoop/hbase/TableName;Lorg/apache/hadoop/hbase/client/Admin;I)V
     614: return
    Exception table:
       from    to  target type
         177   184   187   Class java/lang/Throwable
         156   167   209   Class java/lang/Throwable
         156   167   218   any
         230   237   240   Class java/lang/Throwable
         209   220   218   any
         328   335   338   Class java/lang/Throwable
         307   318   360   Class java/lang/Throwable
         307   318   369   any
         381   388   391   Class java/lang/Throwable
         360   371   369   any

  public void testOfflineTableSnapshot() throws java.lang.Exception;
    Code:
       0: getstatic     #7                  // Field UTIL:Lorg/apache/hadoop/hbase/HBaseTestingUtility;
       3: invokevirtual #12                 // Method org/apache/hadoop/hbase/HBaseTestingUtility.getHBaseAdmin:()Lorg/apache/hadoop/hbase/client/HBaseAdmin;
       6: astore_1
       7: aload_1
       8: invokestatic  #81                 // Method org/apache/hadoop/hbase/snapshot/SnapshotTestingUtils.assertNoSnapshots:(Lorg/apache/hadoop/hbase/client/Admin;)V
      11: getstatic     #7                  // Field UTIL:Lorg/apache/hadoop/hbase/HBaseTestingUtility;
      14: invokevirtual #72                 // Method org/apache/hadoop/hbase/HBaseTestingUtility.getConnection:()Lorg/apache/hadoop/hbase/client/Connection;
      17: getstatic     #42                 // Field TABLE_NAME:Lorg/apache/hadoop/hbase/TableName;
      20: invokeinterface #73,  2           // InterfaceMethod org/apache/hadoop/hbase/client/Connection.getTable:(Lorg/apache/hadoop/hbase/TableName;)Lorg/apache/hadoop/hbase/client/Table;
      25: astore_2
      26: getstatic     #7                  // Field UTIL:Lorg/apache/hadoop/hbase/HBaseTestingUtility;
      29: aload_2
      30: getstatic     #47                 // Field TEST_FAM:[B
      33: iconst_0
      34: invokevirtual #82                 // Method org/apache/hadoop/hbase/HBaseTestingUtility.loadTable:(Lorg/apache/hadoop/hbase/client/Table;[BZ)I
      37: pop
      38: getstatic     #57                 // Field LOG:Lorg/slf4j/Logger;
      41: ldc           #83                 // String FS state before disable:
      43: invokeinterface #84,  2           // InterfaceMethod org/slf4j/Logger.debug:(Ljava/lang/String;)V
      48: getstatic     #7                  // Field UTIL:Lorg/apache/hadoop/hbase/HBaseTestingUtility;
      51: invokevirtual #85                 // Method org/apache/hadoop/hbase/HBaseTestingUtility.getTestFileSystem:()Lorg/apache/hadoop/fs/FileSystem;
      54: getstatic     #7                  // Field UTIL:Lorg/apache/hadoop/hbase/HBaseTestingUtility;
      57: invokevirtual #8                  // Method org/apache/hadoop/hbase/HBaseTestingUtility.getConfiguration:()Lorg/apache/hadoop/conf/Configuration;
      60: invokestatic  #86                 // Method org/apache/hadoop/hbase/util/FSUtils.getRootDir:(Lorg/apache/hadoop/conf/Configuration;)Lorg/apache/hadoop/fs/Path;
      63: getstatic     #57                 // Field LOG:Lorg/slf4j/Logger;
      66: invokestatic  #87                 // Method org/apache/hadoop/hbase/util/FSUtils.logFileSystemState:(Lorg/apache/hadoop/fs/FileSystem;Lorg/apache/hadoop/fs/Path;Lorg/slf4j/Logger;)V
      69: aload_1
      70: getstatic     #42                 // Field TABLE_NAME:Lorg/apache/hadoop/hbase/TableName;
      73: invokeinterface #68,  2           // InterfaceMethod org/apache/hadoop/hbase/client/Admin.disableTable:(Lorg/apache/hadoop/hbase/TableName;)V
      78: getstatic     #57                 // Field LOG:Lorg/slf4j/Logger;
      81: ldc           #88                 // String FS state before snapshot:
      83: invokeinterface #84,  2           // InterfaceMethod org/slf4j/Logger.debug:(Ljava/lang/String;)V
      88: getstatic     #7                  // Field UTIL:Lorg/apache/hadoop/hbase/HBaseTestingUtility;
      91: invokevirtual #85                 // Method org/apache/hadoop/hbase/HBaseTestingUtility.getTestFileSystem:()Lorg/apache/hadoop/fs/FileSystem;
      94: getstatic     #7                  // Field UTIL:Lorg/apache/hadoop/hbase/HBaseTestingUtility;
      97: invokevirtual #8                  // Method org/apache/hadoop/hbase/HBaseTestingUtility.getConfiguration:()Lorg/apache/hadoop/conf/Configuration;
     100: invokestatic  #86                 // Method org/apache/hadoop/hbase/util/FSUtils.getRootDir:(Lorg/apache/hadoop/conf/Configuration;)Lorg/apache/hadoop/fs/Path;
     103: getstatic     #57                 // Field LOG:Lorg/slf4j/Logger;
     106: invokestatic  #87                 // Method org/apache/hadoop/hbase/util/FSUtils.logFileSystemState:(Lorg/apache/hadoop/fs/FileSystem;Lorg/apache/hadoop/fs/Path;Lorg/slf4j/Logger;)V
     109: ldc           #89                 // String offlineTableSnapshot
     111: astore_3
     112: ldc           #89                 // String offlineTableSnapshot
     114: astore        4
     116: aload_0
     117: getstatic     #42                 // Field TABLE_NAME:Lorg/apache/hadoop/hbase/TableName;
     120: ldc           #89                 // String offlineTableSnapshot
     122: iconst_1
     123: invokespecial #69                 // Method takeSnapshot:(Lorg/apache/hadoop/hbase/TableName;Ljava/lang/String;Z)V
     126: getstatic     #57                 // Field LOG:Lorg/slf4j/Logger;
     129: ldc           #90                 // String Snapshot completed.
     131: invokeinterface #84,  2           // InterfaceMethod org/slf4j/Logger.debug:(Ljava/lang/String;)V
     136: aload_1
     137: aload         4
     139: getstatic     #42                 // Field TABLE_NAME:Lorg/apache/hadoop/hbase/TableName;
     142: invokestatic  #91                 // Method org/apache/hadoop/hbase/snapshot/SnapshotTestingUtils.assertOneSnapshotThatMatches:(Lorg/apache/hadoop/hbase/client/Admin;Ljava/lang/String;Lorg/apache/hadoop/hbase/TableName;)Ljava/util/List;
     145: astore        5
     147: getstatic     #7                  // Field UTIL:Lorg/apache/hadoop/hbase/HBaseTestingUtility;
     150: invokevirtual #92                 // Method org/apache/hadoop/hbase/HBaseTestingUtility.getHBaseCluster:()Lorg/apache/hadoop/hbase/MiniHBaseCluster;
     153: invokevirtual #93                 // Method org/apache/hadoop/hbase/MiniHBaseCluster.getMaster:()Lorg/apache/hadoop/hbase/master/HMaster;
     156: invokevirtual #94                 // Method org/apache/hadoop/hbase/master/HMaster.getMasterFileSystem:()Lorg/apache/hadoop/hbase/master/MasterFileSystem;
     159: invokevirtual #95                 // Method org/apache/hadoop/hbase/master/MasterFileSystem.getFileSystem:()Lorg/apache/hadoop/fs/FileSystem;
     162: astore        6
     164: getstatic     #7                  // Field UTIL:Lorg/apache/hadoop/hbase/HBaseTestingUtility;
     167: invokevirtual #92                 // Method org/apache/hadoop/hbase/HBaseTestingUtility.getHBaseCluster:()Lorg/apache/hadoop/hbase/MiniHBaseCluster;
     170: invokevirtual #93                 // Method org/apache/hadoop/hbase/MiniHBaseCluster.getMaster:()Lorg/apache/hadoop/hbase/master/HMaster;
     173: invokevirtual #94                 // Method org/apache/hadoop/hbase/master/HMaster.getMasterFileSystem:()Lorg/apache/hadoop/hbase/master/MasterFileSystem;
     176: invokevirtual #96                 // Method org/apache/hadoop/hbase/master/MasterFileSystem.getRootDir:()Lorg/apache/hadoop/fs/Path;
     179: astore        7
     181: getstatic     #57                 // Field LOG:Lorg/slf4j/Logger;
     184: ldc           #97                 // String FS state after snapshot:
     186: invokeinterface #84,  2           // InterfaceMethod org/slf4j/Logger.debug:(Ljava/lang/String;)V
     191: getstatic     #7                  // Field UTIL:Lorg/apache/hadoop/hbase/HBaseTestingUtility;
     194: invokevirtual #85                 // Method org/apache/hadoop/hbase/HBaseTestingUtility.getTestFileSystem:()Lorg/apache/hadoop/fs/FileSystem;
     197: getstatic     #7                  // Field UTIL:Lorg/apache/hadoop/hbase/HBaseTestingUtility;
     200: invokevirtual #8                  // Method org/apache/hadoop/hbase/HBaseTestingUtility.getConfiguration:()Lorg/apache/hadoop/conf/Configuration;
     203: invokestatic  #86                 // Method org/apache/hadoop/hbase/util/FSUtils.getRootDir:(Lorg/apache/hadoop/conf/Configuration;)Lorg/apache/hadoop/fs/Path;
     206: getstatic     #57                 // Field LOG:Lorg/slf4j/Logger;
     209: invokestatic  #87                 // Method org/apache/hadoop/hbase/util/FSUtils.logFileSystemState:(Lorg/apache/hadoop/fs/FileSystem;Lorg/apache/hadoop/fs/Path;Lorg/slf4j/Logger;)V
     212: aload         5
     214: iconst_0
     215: invokeinterface #98,  2           // InterfaceMethod java/util/List.get:(I)Ljava/lang/Object;
     220: checkcast     #99                 // class org/apache/hadoop/hbase/client/SnapshotDescription
     223: invokestatic  #100                // Method org/apache/hadoop/hbase/shaded/protobuf/ProtobufUtil.createHBaseProtosSnapshotDesc:(Lorg/apache/hadoop/hbase/client/SnapshotDescription;)Lorg/apache/hadoop/hbase/shaded/protobuf/generated/SnapshotProtos$SnapshotDescription;
     226: getstatic     #42                 // Field TABLE_NAME:Lorg/apache/hadoop/hbase/TableName;
     229: getstatic     #47                 // Field TEST_FAM:[B
     232: aload         7
     234: aload_1
     235: aload         6
     237: invokestatic  #101                // Method org/apache/hadoop/hbase/snapshot/SnapshotTestingUtils.confirmSnapshotValid:(Lorg/apache/hadoop/hbase/shaded/protobuf/generated/SnapshotProtos$SnapshotDescription;Lorg/apache/hadoop/hbase/TableName;[BLorg/apache/hadoop/fs/Path;Lorg/apache/hadoop/hbase/client/Admin;Lorg/apache/hadoop/fs/FileSystem;)V
     240: aload_1
     241: aload         4
     243: invokeinterface #102,  2          // InterfaceMethod org/apache/hadoop/hbase/client/Admin.deleteSnapshot:(Ljava/lang/String;)V
     248: aload_1
     249: invokestatic  #81                 // Method org/apache/hadoop/hbase/snapshot/SnapshotTestingUtils.assertNoSnapshots:(Lorg/apache/hadoop/hbase/client/Admin;)V
     252: return

  public void testSnapshotCloneContents() throws java.lang.Exception;
    Code:
       0: getstatic     #13                 // Field admin:Lorg/apache/hadoop/hbase/client/Admin;
       3: invokestatic  #81                 // Method org/apache/hadoop/hbase/snapshot/SnapshotTestingUtils.assertNoSnapshots:(Lorg/apache/hadoop/hbase/client/Admin;)V
       6: getstatic     #7                  // Field UTIL:Lorg/apache/hadoop/hbase/HBaseTestingUtility;
       9: invokevirtual #72                 // Method org/apache/hadoop/hbase/HBaseTestingUtility.getConnection:()Lorg/apache/hadoop/hbase/client/Connection;
      12: getstatic     #42                 // Field TABLE_NAME:Lorg/apache/hadoop/hbase/TableName;
      15: invokeinterface #73,  2           // InterfaceMethod org/apache/hadoop/hbase/client/Connection.getTable:(Lorg/apache/hadoop/hbase/TableName;)Lorg/apache/hadoop/hbase/client/Table;
      20: astore_1
      21: getstatic     #7                  // Field UTIL:Lorg/apache/hadoop/hbase/HBaseTestingUtility;
      24: aload_1
      25: getstatic     #47                 // Field TEST_FAM:[B
      28: invokevirtual #103                // Method org/apache/hadoop/hbase/HBaseTestingUtility.loadTable:(Lorg/apache/hadoop/hbase/client/Table;[B)I
      31: pop
      32: aload_1
      33: invokeinterface #75,  1           // InterfaceMethod org/apache/hadoop/hbase/client/Table.close:()V
      38: ldc           #104                // String TableSnapshot1
      40: astore_2
      41: aload_0
      42: getstatic     #42                 // Field TABLE_NAME:Lorg/apache/hadoop/hbase/TableName;
      45: aload_2
      46: iconst_0
      47: invokespecial #69                 // Method takeSnapshot:(Lorg/apache/hadoop/hbase/TableName;Ljava/lang/String;Z)V
      50: getstatic     #57                 // Field LOG:Lorg/slf4j/Logger;
      53: ldc           #105                // String Snapshot1 completed.
      55: invokeinterface #84,  2           // InterfaceMethod org/slf4j/Logger.debug:(Ljava/lang/String;)V
      60: ldc           #106                // String Table1Clone
      62: invokestatic  #63                 // Method org/apache/hadoop/hbase/TableName.valueOf:(Ljava/lang/String;)Lorg/apache/hadoop/hbase/TableName;
      65: astore_3
      66: getstatic     #13                 // Field admin:Lorg/apache/hadoop/hbase/client/Admin;
      69: aload_2
      70: aload_3
      71: iconst_0
      72: invokeinterface #107,  4          // InterfaceMethod org/apache/hadoop/hbase/client/Admin.cloneSnapshot:(Ljava/lang/String;Lorg/apache/hadoop/hbase/TableName;Z)V
      77: new           #108                // class org/apache/hadoop/hbase/client/Scan
      80: dup
      81: invokespecial #109                // Method org/apache/hadoop/hbase/client/Scan."<init>":()V
      84: astore        4
      86: new           #108                // class org/apache/hadoop/hbase/client/Scan
      89: dup
      90: invokespecial #109                // Method org/apache/hadoop/hbase/client/Scan."<init>":()V
      93: astore        5
      95: getstatic     #13                 // Field admin:Lorg/apache/hadoop/hbase/client/Admin;
      98: invokeinterface #110,  1          // InterfaceMethod org/apache/hadoop/hbase/client/Admin.getConnection:()Lorg/apache/hadoop/hbase/client/Connection;
     103: getstatic     #42                 // Field TABLE_NAME:Lorg/apache/hadoop/hbase/TableName;
     106: invokeinterface #73,  2           // InterfaceMethod org/apache/hadoop/hbase/client/Connection.getTable:(Lorg/apache/hadoop/hbase/TableName;)Lorg/apache/hadoop/hbase/client/Table;
     111: aload         4
     113: invokeinterface #111,  2          // InterfaceMethod org/apache/hadoop/hbase/client/Table.getScanner:(Lorg/apache/hadoop/hbase/client/Scan;)Lorg/apache/hadoop/hbase/client/ResultScanner;
     118: astore        6
     120: getstatic     #13                 // Field admin:Lorg/apache/hadoop/hbase/client/Admin;
     123: invokeinterface #110,  1          // InterfaceMethod org/apache/hadoop/hbase/client/Admin.getConnection:()Lorg/apache/hadoop/hbase/client/Connection;
     128: ldc           #106                // String Table1Clone
     130: invokestatic  #63                 // Method org/apache/hadoop/hbase/TableName.valueOf:(Ljava/lang/String;)Lorg/apache/hadoop/hbase/TableName;
     133: invokeinterface #73,  2           // InterfaceMethod org/apache/hadoop/hbase/client/Connection.getTable:(Lorg/apache/hadoop/hbase/TableName;)Lorg/apache/hadoop/hbase/client/Table;
     138: aload         5
     140: invokeinterface #111,  2          // InterfaceMethod org/apache/hadoop/hbase/client/Table.getScanner:(Lorg/apache/hadoop/hbase/client/Scan;)Lorg/apache/hadoop/hbase/client/ResultScanner;
     145: astore        7
     147: aload         6
     149: invokeinterface #112,  1          // InterfaceMethod org/apache/hadoop/hbase/client/ResultScanner.iterator:()Ljava/util/Iterator;
     154: astore        8
     156: aload         7
     158: invokeinterface #112,  1          // InterfaceMethod org/apache/hadoop/hbase/client/ResultScanner.iterator:()Ljava/util/Iterator;
     163: astore        9
     165: aload         8
     167: invokeinterface #113,  1          // InterfaceMethod java/util/Iterator.hasNext:()Z
     172: invokestatic  #114                // Method org/junit/Assert.assertTrue:(Z)V
     175: aload         8
     177: invokeinterface #113,  1          // InterfaceMethod java/util/Iterator.hasNext:()Z
     182: ifeq          245
     185: aload         9
     187: invokeinterface #113,  1          // InterfaceMethod java/util/Iterator.hasNext:()Z
     192: invokestatic  #114                // Method org/junit/Assert.assertTrue:(Z)V
     195: aload         8
     197: invokeinterface #115,  1          // InterfaceMethod java/util/Iterator.next:()Ljava/lang/Object;
     202: checkcast     #116                // class org/apache/hadoop/hbase/client/Result
     205: getstatic     #47                 // Field TEST_FAM:[B
     208: iconst_0
     209: newarray       byte
     211: invokevirtual #117                // Method org/apache/hadoop/hbase/client/Result.getValue:([B[B)[B
     214: invokestatic  #118                // Method org/apache/hadoop/hbase/util/Bytes.toString:([B)Ljava/lang/String;
     217: aload         9
     219: invokeinterface #115,  1          // InterfaceMethod java/util/Iterator.next:()Ljava/lang/Object;
     224: checkcast     #116                // class org/apache/hadoop/hbase/client/Result
     227: getstatic     #47                 // Field TEST_FAM:[B
     230: iconst_0
     231: newarray       byte
     233: invokevirtual #117                // Method org/apache/hadoop/hbase/client/Result.getValue:([B[B)[B
     236: invokestatic  #118                // Method org/apache/hadoop/hbase/util/Bytes.toString:([B)Ljava/lang/String;
     239: invokestatic  #119                // Method org/junit/Assert.assertEquals:(Ljava/lang/Object;Ljava/lang/Object;)V
     242: goto          175
     245: aload         9
     247: invokeinterface #113,  1          // InterfaceMethod java/util/Iterator.hasNext:()Z
     252: invokestatic  #120                // Method org/junit/Assert.assertFalse:(Z)V
     255: getstatic     #13                 // Field admin:Lorg/apache/hadoop/hbase/client/Admin;
     258: aload_2
     259: invokeinterface #102,  2          // InterfaceMethod org/apache/hadoop/hbase/client/Admin.deleteSnapshot:(Ljava/lang/String;)V
     264: getstatic     #7                  // Field UTIL:Lorg/apache/hadoop/hbase/HBaseTestingUtility;
     267: aload_3
     268: invokevirtual #49                 // Method org/apache/hadoop/hbase/HBaseTestingUtility.deleteTable:(Lorg/apache/hadoop/hbase/TableName;)V
     271: getstatic     #13                 // Field admin:Lorg/apache/hadoop/hbase/client/Admin;
     274: invokeinterface #121,  1          // InterfaceMethod org/apache/hadoop/hbase/client/Admin.close:()V
     279: return

  public void testOfflineTableSnapshotWithEmptyRegion() throws java.lang.Exception;
    Code:
       0: getstatic     #13                 // Field admin:Lorg/apache/hadoop/hbase/client/Admin;
       3: invokestatic  #81                 // Method org/apache/hadoop/hbase/snapshot/SnapshotTestingUtils.assertNoSnapshots:(Lorg/apache/hadoop/hbase/client/Admin;)V
       6: getstatic     #57                 // Field LOG:Lorg/slf4j/Logger;
       9: ldc           #83                 // String FS state before disable:
      11: invokeinterface #84,  2           // InterfaceMethod org/slf4j/Logger.debug:(Ljava/lang/String;)V
      16: getstatic     #7                  // Field UTIL:Lorg/apache/hadoop/hbase/HBaseTestingUtility;
      19: invokevirtual #85                 // Method org/apache/hadoop/hbase/HBaseTestingUtility.getTestFileSystem:()Lorg/apache/hadoop/fs/FileSystem;
      22: getstatic     #7                  // Field UTIL:Lorg/apache/hadoop/hbase/HBaseTestingUtility;
      25: invokevirtual #8                  // Method org/apache/hadoop/hbase/HBaseTestingUtility.getConfiguration:()Lorg/apache/hadoop/conf/Configuration;
      28: invokestatic  #86                 // Method org/apache/hadoop/hbase/util/FSUtils.getRootDir:(Lorg/apache/hadoop/conf/Configuration;)Lorg/apache/hadoop/fs/Path;
      31: getstatic     #57                 // Field LOG:Lorg/slf4j/Logger;
      34: invokestatic  #87                 // Method org/apache/hadoop/hbase/util/FSUtils.logFileSystemState:(Lorg/apache/hadoop/fs/FileSystem;Lorg/apache/hadoop/fs/Path;Lorg/slf4j/Logger;)V
      37: getstatic     #13                 // Field admin:Lorg/apache/hadoop/hbase/client/Admin;
      40: getstatic     #42                 // Field TABLE_NAME:Lorg/apache/hadoop/hbase/TableName;
      43: invokeinterface #68,  2           // InterfaceMethod org/apache/hadoop/hbase/client/Admin.disableTable:(Lorg/apache/hadoop/hbase/TableName;)V
      48: getstatic     #57                 // Field LOG:Lorg/slf4j/Logger;
      51: ldc           #88                 // String FS state before snapshot:
      53: invokeinterface #84,  2           // InterfaceMethod org/slf4j/Logger.debug:(Ljava/lang/String;)V
      58: getstatic     #7                  // Field UTIL:Lorg/apache/hadoop/hbase/HBaseTestingUtility;
      61: invokevirtual #85                 // Method org/apache/hadoop/hbase/HBaseTestingUtility.getTestFileSystem:()Lorg/apache/hadoop/fs/FileSystem;
      64: getstatic     #7                  // Field UTIL:Lorg/apache/hadoop/hbase/HBaseTestingUtility;
      67: invokevirtual #8                  // Method org/apache/hadoop/hbase/HBaseTestingUtility.getConfiguration:()Lorg/apache/hadoop/conf/Configuration;
      70: invokestatic  #86                 // Method org/apache/hadoop/hbase/util/FSUtils.getRootDir:(Lorg/apache/hadoop/conf/Configuration;)Lorg/apache/hadoop/fs/Path;
      73: getstatic     #57                 // Field LOG:Lorg/slf4j/Logger;
      76: invokestatic  #87                 // Method org/apache/hadoop/hbase/util/FSUtils.logFileSystemState:(Lorg/apache/hadoop/fs/FileSystem;Lorg/apache/hadoop/fs/Path;Lorg/slf4j/Logger;)V
      79: ldc           #122                // String testOfflineTableSnapshotWithEmptyRegion
      81: astore_1
      82: aload_0
      83: getstatic     #42                 // Field TABLE_NAME:Lorg/apache/hadoop/hbase/TableName;
      86: aload_1
      87: iconst_1
      88: invokespecial #69                 // Method takeSnapshot:(Lorg/apache/hadoop/hbase/TableName;Ljava/lang/String;Z)V
      91: getstatic     #57                 // Field LOG:Lorg/slf4j/Logger;
      94: ldc           #90                 // String Snapshot completed.
      96: invokeinterface #84,  2           // InterfaceMethod org/slf4j/Logger.debug:(Ljava/lang/String;)V
     101: getstatic     #13                 // Field admin:Lorg/apache/hadoop/hbase/client/Admin;
     104: aload_1
     105: getstatic     #42                 // Field TABLE_NAME:Lorg/apache/hadoop/hbase/TableName;
     108: invokestatic  #91                 // Method org/apache/hadoop/hbase/snapshot/SnapshotTestingUtils.assertOneSnapshotThatMatches:(Lorg/apache/hadoop/hbase/client/Admin;Ljava/lang/String;Lorg/apache/hadoop/hbase/TableName;)Ljava/util/List;
     111: astore_2
     112: getstatic     #7                  // Field UTIL:Lorg/apache/hadoop/hbase/HBaseTestingUtility;
     115: invokevirtual #92                 // Method org/apache/hadoop/hbase/HBaseTestingUtility.getHBaseCluster:()Lorg/apache/hadoop/hbase/MiniHBaseCluster;
     118: invokevirtual #93                 // Method org/apache/hadoop/hbase/MiniHBaseCluster.getMaster:()Lorg/apache/hadoop/hbase/master/HMaster;
     121: invokevirtual #94                 // Method org/apache/hadoop/hbase/master/HMaster.getMasterFileSystem:()Lorg/apache/hadoop/hbase/master/MasterFileSystem;
     124: invokevirtual #95                 // Method org/apache/hadoop/hbase/master/MasterFileSystem.getFileSystem:()Lorg/apache/hadoop/fs/FileSystem;
     127: astore_3
     128: getstatic     #7                  // Field UTIL:Lorg/apache/hadoop/hbase/HBaseTestingUtility;
     131: invokevirtual #92                 // Method org/apache/hadoop/hbase/HBaseTestingUtility.getHBaseCluster:()Lorg/apache/hadoop/hbase/MiniHBaseCluster;
     134: invokevirtual #93                 // Method org/apache/hadoop/hbase/MiniHBaseCluster.getMaster:()Lorg/apache/hadoop/hbase/master/HMaster;
     137: invokevirtual #94                 // Method org/apache/hadoop/hbase/master/HMaster.getMasterFileSystem:()Lorg/apache/hadoop/hbase/master/MasterFileSystem;
     140: invokevirtual #96                 // Method org/apache/hadoop/hbase/master/MasterFileSystem.getRootDir:()Lorg/apache/hadoop/fs/Path;
     143: astore        4
     145: getstatic     #57                 // Field LOG:Lorg/slf4j/Logger;
     148: ldc           #97                 // String FS state after snapshot:
     150: invokeinterface #84,  2           // InterfaceMethod org/slf4j/Logger.debug:(Ljava/lang/String;)V
     155: getstatic     #7                  // Field UTIL:Lorg/apache/hadoop/hbase/HBaseTestingUtility;
     158: invokevirtual #85                 // Method org/apache/hadoop/hbase/HBaseTestingUtility.getTestFileSystem:()Lorg/apache/hadoop/fs/FileSystem;
     161: getstatic     #7                  // Field UTIL:Lorg/apache/hadoop/hbase/HBaseTestingUtility;
     164: invokevirtual #8                  // Method org/apache/hadoop/hbase/HBaseTestingUtility.getConfiguration:()Lorg/apache/hadoop/conf/Configuration;
     167: invokestatic  #86                 // Method org/apache/hadoop/hbase/util/FSUtils.getRootDir:(Lorg/apache/hadoop/conf/Configuration;)Lorg/apache/hadoop/fs/Path;
     170: getstatic     #57                 // Field LOG:Lorg/slf4j/Logger;
     173: invokestatic  #87                 // Method org/apache/hadoop/hbase/util/FSUtils.logFileSystemState:(Lorg/apache/hadoop/fs/FileSystem;Lorg/apache/hadoop/fs/Path;Lorg/slf4j/Logger;)V
     176: iconst_1
     177: anewarray     #46                 // class "[B"
     180: dup
     181: iconst_0
     182: getstatic     #47                 // Field TEST_FAM:[B
     185: aastore
     186: invokestatic  #123                // Method org/apache/hbase/thirdparty/com/google/common/collect/Lists.newArrayList:([Ljava/lang/Object;)Ljava/util/ArrayList;
     189: astore        5
     191: invokestatic  #124                // Method org/apache/hbase/thirdparty/com/google/common/collect/Lists.newArrayList:()Ljava/util/ArrayList;
     194: astore        6
     196: aload_2
     197: iconst_0
     198: invokeinterface #98,  2           // InterfaceMethod java/util/List.get:(I)Ljava/lang/Object;
     203: checkcast     #99                 // class org/apache/hadoop/hbase/client/SnapshotDescription
     206: invokestatic  #100                // Method org/apache/hadoop/hbase/shaded/protobuf/ProtobufUtil.createHBaseProtosSnapshotDesc:(Lorg/apache/hadoop/hbase/client/SnapshotDescription;)Lorg/apache/hadoop/hbase/shaded/protobuf/generated/SnapshotProtos$SnapshotDescription;
     209: getstatic     #42                 // Field TABLE_NAME:Lorg/apache/hadoop/hbase/TableName;
     212: aload         6
     214: aload         5
     216: aload         4
     218: getstatic     #13                 // Field admin:Lorg/apache/hadoop/hbase/client/Admin;
     221: aload_3
     222: invokestatic  #125                // Method org/apache/hadoop/hbase/snapshot/SnapshotTestingUtils.confirmSnapshotValid:(Lorg/apache/hadoop/hbase/shaded/protobuf/generated/SnapshotProtos$SnapshotDescription;Lorg/apache/hadoop/hbase/TableName;Ljava/util/List;Ljava/util/List;Lorg/apache/hadoop/fs/Path;Lorg/apache/hadoop/hbase/client/Admin;Lorg/apache/hadoop/fs/FileSystem;)V
     225: getstatic     #13                 // Field admin:Lorg/apache/hadoop/hbase/client/Admin;
     228: aload_1
     229: invokeinterface #102,  2          // InterfaceMethod org/apache/hadoop/hbase/client/Admin.deleteSnapshot:(Ljava/lang/String;)V
     234: getstatic     #13                 // Field admin:Lorg/apache/hadoop/hbase/client/Admin;
     237: invokestatic  #81                 // Method org/apache/hadoop/hbase/snapshot/SnapshotTestingUtils.assertNoSnapshots:(Lorg/apache/hadoop/hbase/client/Admin;)V
     240: return

  public void testEnsureTemporaryDirectoryTransfer() throws java.lang.Exception;
    Code:
       0: getstatic     #7                  // Field UTIL:Lorg/apache/hadoop/hbase/HBaseTestingUtility;
       3: invokevirtual #126                // Method org/apache/hadoop/hbase/HBaseTestingUtility.getAdmin:()Lorg/apache/hadoop/hbase/client/Admin;
       6: astore_1
       7: ldc           #127                // String testListTableSnapshots
       9: invokestatic  #63                 // Method org/apache/hadoop/hbase/TableName.valueOf:(Ljava/lang/String;)Lorg/apache/hadoop/hbase/TableName;
      12: astore_2
      13: new           #41                 // class org/apache/hadoop/hbase/HTableDescriptor
      16: dup
      17: aload_2
      18: invokespecial #43                 // Method org/apache/hadoop/hbase/HTableDescriptor."<init>":(Lorg/apache/hadoop/hbase/TableName;)V
      21: astore_3
      22: getstatic     #7                  // Field UTIL:Lorg/apache/hadoop/hbase/HBaseTestingUtility;
      25: aload_3
      26: iconst_1
      27: anewarray     #46                 // class "[B"
      30: dup
      31: iconst_0
      32: getstatic     #47                 // Field TEST_FAM:[B
      35: aastore
      36: getstatic     #7                  // Field UTIL:Lorg/apache/hadoop/hbase/HBaseTestingUtility;
      39: invokevirtual #8                  // Method org/apache/hadoop/hbase/HBaseTestingUtility.getConfiguration:()Lorg/apache/hadoop/conf/Configuration;
      42: invokevirtual #48                 // Method org/apache/hadoop/hbase/HBaseTestingUtility.createTable:(Lorg/apache/hadoop/hbase/client/TableDescriptor;[[BLorg/apache/hadoop/conf/Configuration;)Lorg/apache/hadoop/hbase/client/Table;
      45: pop
      46: ldc           #128                // String Table1Snapshot1
      48: astore        4
      50: aload_0
      51: getstatic     #42                 // Field TABLE_NAME:Lorg/apache/hadoop/hbase/TableName;
      54: aload         4
      56: iconst_0
      57: invokespecial #69                 // Method takeSnapshot:(Lorg/apache/hadoop/hbase/TableName;Ljava/lang/String;Z)V
      60: getstatic     #57                 // Field LOG:Lorg/slf4j/Logger;
      63: ldc           #105                // String Snapshot1 completed.
      65: invokeinterface #84,  2           // InterfaceMethod org/slf4j/Logger.debug:(Ljava/lang/String;)V
      70: ldc           #129                // String Table1Snapshot2
      72: astore        5
      74: aload_0
      75: getstatic     #42                 // Field TABLE_NAME:Lorg/apache/hadoop/hbase/TableName;
      78: aload         5
      80: iconst_0
      81: invokespecial #69                 // Method takeSnapshot:(Lorg/apache/hadoop/hbase/TableName;Ljava/lang/String;Z)V
      84: getstatic     #57                 // Field LOG:Lorg/slf4j/Logger;
      87: ldc           #130                // String Snapshot2 completed.
      89: invokeinterface #84,  2           // InterfaceMethod org/slf4j/Logger.debug:(Ljava/lang/String;)V
      94: ldc           #131                // String Table2Snapshot1
      96: astore        6
      98: aload_0
      99: getstatic     #42                 // Field TABLE_NAME:Lorg/apache/hadoop/hbase/TableName;
     102: aload         6
     104: iconst_0
     105: invokespecial #69                 // Method takeSnapshot:(Lorg/apache/hadoop/hbase/TableName;Ljava/lang/String;Z)V
     108: getstatic     #57                 // Field LOG:Lorg/slf4j/Logger;
     111: ldc           #132                // String Table2Snapshot1 completed.
     113: invokeinterface #84,  2           // InterfaceMethod org/slf4j/Logger.debug:(Ljava/lang/String;)V
     118: aload_1
     119: ldc           #133                // String test.*
     121: invokestatic  #134                // Method java/util/regex/Pattern.compile:(Ljava/lang/String;)Ljava/util/regex/Pattern;
     124: ldc           #135                // String .*
     126: invokestatic  #134                // Method java/util/regex/Pattern.compile:(Ljava/lang/String;)Ljava/util/regex/Pattern;
     129: invokeinterface #136,  3          // InterfaceMethod org/apache/hadoop/hbase/client/Admin.listTableSnapshots:(Ljava/util/regex/Pattern;Ljava/util/regex/Pattern;)Ljava/util/List;
     134: astore        7
     136: new           #137                // class java/util/ArrayList
     139: dup
     140: invokespecial #138                // Method java/util/ArrayList."<init>":()V
     143: astore        8
     145: ldc2_w        #139                // long 3l
     148: aload         7
     150: invokeinterface #141,  1          // InterfaceMethod java/util/List.size:()I
     155: i2l
     156: invokestatic  #142                // Method org/junit/Assert.assertEquals:(JJ)V
     159: aload         7
     161: invokeinterface #143,  1          // InterfaceMethod java/util/List.iterator:()Ljava/util/Iterator;
     166: astore        9
     168: aload         9
     170: invokeinterface #113,  1          // InterfaceMethod java/util/Iterator.hasNext:()Z
     175: ifeq          206
     178: aload         9
     180: invokeinterface #115,  1          // InterfaceMethod java/util/Iterator.next:()Ljava/lang/Object;
     185: checkcast     #99                 // class org/apache/hadoop/hbase/client/SnapshotDescription
     188: astore        10
     190: aload         8
     192: aload         10
     194: invokevirtual #144                // Method org/apache/hadoop/hbase/client/SnapshotDescription.getName:()Ljava/lang/String;
     197: invokeinterface #145,  2          // InterfaceMethod java/util/List.add:(Ljava/lang/Object;)Z
     202: pop
     203: goto          168
     206: aload         8
     208: aload         4
     210: invokeinterface #146,  2          // InterfaceMethod java/util/List.contains:(Ljava/lang/Object;)Z
     215: invokestatic  #114                // Method org/junit/Assert.assertTrue:(Z)V
     218: aload         8
     220: aload         5
     222: invokeinterface #146,  2          // InterfaceMethod java/util/List.contains:(Ljava/lang/Object;)Z
     227: invokestatic  #114                // Method org/junit/Assert.assertTrue:(Z)V
     230: aload         8
     232: aload         6
     234: invokeinterface #146,  2          // InterfaceMethod java/util/List.contains:(Ljava/lang/Object;)Z
     239: invokestatic  #114                // Method org/junit/Assert.assertTrue:(Z)V
     242: aload_1
     243: ldc           #147                // String Table.*
     245: invokestatic  #134                // Method java/util/regex/Pattern.compile:(Ljava/lang/String;)Ljava/util/regex/Pattern;
     248: invokeinterface #148,  2          // InterfaceMethod org/apache/hadoop/hbase/client/Admin.deleteSnapshots:(Ljava/util/regex/Pattern;)V
     253: goto          257
     256: astore_3
     257: aload_1
     258: aload_2
     259: invokeinterface #150,  2          // InterfaceMethod org/apache/hadoop/hbase/client/Admin.tableExists:(Lorg/apache/hadoop/hbase/TableName;)Z
     264: ifeq          274
     267: getstatic     #7                  // Field UTIL:Lorg/apache/hadoop/hbase/HBaseTestingUtility;
     270: aload_2
     271: invokevirtual #49                 // Method org/apache/hadoop/hbase/HBaseTestingUtility.deleteTable:(Lorg/apache/hadoop/hbase/TableName;)V
     274: aload_1
     275: invokeinterface #121,  1          // InterfaceMethod org/apache/hadoop/hbase/client/Admin.close:()V
     280: goto          327
     283: astore        11
     285: aload_1
     286: ldc           #147                // String Table.*
     288: invokestatic  #134                // Method java/util/regex/Pattern.compile:(Ljava/lang/String;)Ljava/util/regex/Pattern;
     291: invokeinterface #148,  2          // InterfaceMethod org/apache/hadoop/hbase/client/Admin.deleteSnapshots:(Ljava/util/regex/Pattern;)V
     296: goto          301
     299: astore        12
     301: aload_1
     302: aload_2
     303: invokeinterface #150,  2          // InterfaceMethod org/apache/hadoop/hbase/client/Admin.tableExists:(Lorg/apache/hadoop/hbase/TableName;)Z
     308: ifeq          318
     311: getstatic     #7                  // Field UTIL:Lorg/apache/hadoop/hbase/HBaseTestingUtility;
     314: aload_2
     315: invokevirtual #49                 // Method org/apache/hadoop/hbase/HBaseTestingUtility.deleteTable:(Lorg/apache/hadoop/hbase/TableName;)V
     318: aload_1
     319: invokeinterface #121,  1          // InterfaceMethod org/apache/hadoop/hbase/client/Admin.close:()V
     324: aload         11
     326: athrow
     327: return
    Exception table:
       from    to  target type
         242   253   256   Class org/apache/hadoop/hbase/snapshot/SnapshotDoesNotExistException
          13   242   283   any
         285   296   299   Class org/apache/hadoop/hbase/snapshot/SnapshotDoesNotExistException
         283   285   283   any

  static {};
    Code:
       0: ldc           #10                 // class org/apache/hadoop/hbase/client/TestSnapshotTemporaryDirectory
       2: invokestatic  #159                // Method org/apache/hadoop/hbase/HBaseClassTestRule.forClass:(Ljava/lang/Class;)Lorg/apache/hadoop/hbase/HBaseClassTestRule;
       5: putstatic     #160                // Field CLASS_RULE:Lorg/apache/hadoop/hbase/HBaseClassTestRule;
       8: ldc           #10                 // class org/apache/hadoop/hbase/client/TestSnapshotTemporaryDirectory
      10: invokestatic  #161                // Method org/slf4j/LoggerFactory.getLogger:(Ljava/lang/Class;)Lorg/slf4j/Logger;
      13: putstatic     #57                 // Field LOG:Lorg/slf4j/Logger;
      16: new           #30                 // class java/lang/StringBuilder
      19: dup
      20: invokespecial #31                 // Method java/lang/StringBuilder."<init>":()V
      23: ldc           #162                // String
      25: iconst_0
      26: anewarray     #163                // class java/lang/String
      29: invokestatic  #164                // Method java/nio/file/Paths.get:(Ljava/lang/String;[Ljava/lang/String;)Ljava/nio/file/Path;
      32: invokeinterface #165,  1          // InterfaceMethod java/nio/file/Path.toAbsolutePath:()Ljava/nio/file/Path;
      37: invokeinterface #166,  1          // InterfaceMethod java/nio/file/Path.toString:()Ljava/lang/String;
      42: invokevirtual #33                 // Method java/lang/StringBuilder.append:(Ljava/lang/String;)Ljava/lang/StringBuilder;
      45: ldc           #167                // String /
      47: invokevirtual #33                 // Method java/lang/StringBuilder.append:(Ljava/lang/String;)Ljava/lang/StringBuilder;
      50: invokestatic  #168                // Method java/util/UUID.randomUUID:()Ljava/util/UUID;
      53: invokevirtual #169                // Method java/util/UUID.toString:()Ljava/lang/String;
      56: invokevirtual #33                 // Method java/lang/StringBuilder.append:(Ljava/lang/String;)Ljava/lang/StringBuilder;
      59: invokevirtual #40                 // Method java/lang/StringBuilder.toString:()Ljava/lang/String;
      62: putstatic     #35                 // Field TEMP_DIR:Ljava/lang/String;
      65: new           #170                // class org/apache/hadoop/hbase/HBaseTestingUtility
      68: dup
      69: invokespecial #171                // Method org/apache/hadoop/hbase/HBaseTestingUtility."<init>":()V
      72: putstatic     #7                  // Field UTIL:Lorg/apache/hadoop/hbase/HBaseTestingUtility;
      75: ldc           #172                // String fam
      77: invokestatic  #173                // Method org/apache/hadoop/hbase/util/Bytes.toBytes:(Ljava/lang/String;)[B
      80: putstatic     #47                 // Field TEST_FAM:[B
      83: ldc           #174                // String test
      85: invokestatic  #63                 // Method org/apache/hadoop/hbase/TableName.valueOf:(Ljava/lang/String;)Lorg/apache/hadoop/hbase/TableName;
      88: putstatic     #42                 // Field TABLE_NAME:Lorg/apache/hadoop/hbase/TableName;
      91: return
}
