Compiled from "TestSnapshotFromAdmin.java"
public class org.apache.hadoop.hbase.client.TestSnapshotFromAdmin {
  public static final org.apache.hadoop.hbase.HBaseClassTestRule CLASS_RULE;

  public org.junit.rules.TestName name;

  public org.apache.hadoop.hbase.client.TestSnapshotFromAdmin();
    Code:
       0: aload_0
       1: invokespecial #1                  // Method java/lang/Object."<init>":()V
       4: aload_0
       5: new           #2                  // class org/junit/rules/TestName
       8: dup
       9: invokespecial #3                  // Method org/junit/rules/TestName."<init>":()V
      12: putfield      #4                  // Field name:Lorg/junit/rules/TestName;
      15: return

  public void testBackoffLogic() throws java.lang.Exception;
    Code:
       0: bipush        100
       2: istore_1
       3: getstatic     #5                  // Field org/apache/hadoop/hbase/HConstants.RETRY_BACKOFF:[I
       6: getstatic     #5                  // Field org/apache/hadoop/hbase/HConstants.RETRY_BACKOFF:[I
       9: arraylength
      10: iconst_1
      11: isub
      12: iaload
      13: bipush        100
      15: imul
      16: istore_2
      17: getstatic     #5                  // Field org/apache/hadoop/hbase/HConstants.RETRY_BACKOFF:[I
      20: arraylength
      21: istore_3
      22: lconst_0
      23: lstore        4
      25: iconst_0
      26: istore        6
      28: iload         6
      30: getstatic     #5                  // Field org/apache/hadoop/hbase/HConstants.RETRY_BACKOFF:[I
      33: arraylength
      34: if_icmpge     58
      37: lload         4
      39: getstatic     #5                  // Field org/apache/hadoop/hbase/HConstants.RETRY_BACKOFF:[I
      42: iload         6
      44: iaload
      45: bipush        100
      47: imul
      48: i2l
      49: ladd
      50: lstore        4
      52: iinc          6, 1
      55: goto          28
      58: ldc2_w        #6                  // long 300l
      61: iload_2
      62: iload_3
      63: idiv
      64: iconst_3
      65: imul
      66: i2l
      67: ladd
      68: ldc2_w        #6                  // long 300l
      71: ladd
      72: lstore        6
      74: ldc           #8                  // String Capped snapshot wait time isn't less that the uncapped backoff time - further testing won't prove anything.
      76: lload         6
      78: lload         4
      80: lcmp
      81: ifge          88
      84: iconst_1
      85: goto          89
      88: iconst_0
      89: invokestatic  #9                  // Method org/junit/Assert.assertTrue:(Ljava/lang/String;Z)V
      92: ldc           #10                 // class org/apache/hadoop/hbase/client/ConnectionImplementation
      94: invokestatic  #11                 // Method org/mockito/Mockito.mock:(Ljava/lang/Class;)Ljava/lang/Object;
      97: checkcast     #10                 // class org/apache/hadoop/hbase/client/ConnectionImplementation
     100: astore        8
     102: invokestatic  #12                 // Method org/apache/hadoop/hbase/HBaseConfiguration.create:()Lorg/apache/hadoop/conf/Configuration;
     105: astore        9
     107: aload         9
     109: ldc           #14                 // String hbase.client.retries.number
     111: iload_3
     112: invokevirtual #15                 // Method org/apache/hadoop/conf/Configuration.setInt:(Ljava/lang/String;I)V
     115: aload         9
     117: ldc           #16                 // String hbase.client.pause
     119: ldc2_w        #17                 // long 100l
     122: invokevirtual #19                 // Method org/apache/hadoop/conf/Configuration.setLong:(Ljava/lang/String;J)V
     125: ldc           #20                 // class org/apache/hadoop/hbase/client/MasterKeepAliveConnection
     127: invokestatic  #11                 // Method org/mockito/Mockito.mock:(Ljava/lang/Class;)Ljava/lang/Object;
     130: checkcast     #20                 // class org/apache/hadoop/hbase/client/MasterKeepAliveConnection
     133: astore        10
     135: aload         8
     137: invokevirtual #21                 // Method org/apache/hadoop/hbase/client/ConnectionImplementation.getConfiguration:()Lorg/apache/hadoop/conf/Configuration;
     140: invokestatic  #22                 // Method org/mockito/Mockito.when:(Ljava/lang/Object;)Lorg/mockito/stubbing/OngoingStubbing;
     143: aload         9
     145: invokeinterface #23,  2           // InterfaceMethod org/mockito/stubbing/OngoingStubbing.thenReturn:(Ljava/lang/Object;)Lorg/mockito/stubbing/OngoingStubbing;
     150: pop
     151: aload         8
     153: invokevirtual #24                 // Method org/apache/hadoop/hbase/client/ConnectionImplementation.getMaster:()Lorg/apache/hadoop/hbase/client/MasterKeepAliveConnection;
     156: invokestatic  #22                 // Method org/mockito/Mockito.when:(Ljava/lang/Object;)Lorg/mockito/stubbing/OngoingStubbing;
     159: aload         10
     161: invokeinterface #23,  2           // InterfaceMethod org/mockito/stubbing/OngoingStubbing.thenReturn:(Ljava/lang/Object;)Lorg/mockito/stubbing/OngoingStubbing;
     166: pop
     167: new           #25                 // class org/apache/hadoop/hbase/client/RpcRetryingCallerFactory
     170: dup
     171: aload         9
     173: invokespecial #26                 // Method org/apache/hadoop/hbase/client/RpcRetryingCallerFactory."<init>":(Lorg/apache/hadoop/conf/Configuration;)V
     176: astore        11
     178: ldc           #27                 // class org/apache/hadoop/hbase/ipc/RpcControllerFactory
     180: invokestatic  #11                 // Method org/mockito/Mockito.mock:(Ljava/lang/Class;)Ljava/lang/Object;
     183: checkcast     #27                 // class org/apache/hadoop/hbase/ipc/RpcControllerFactory
     186: astore        12
     188: aload         12
     190: invokevirtual #28                 // Method org/apache/hadoop/hbase/ipc/RpcControllerFactory.newController:()Lorg/apache/hadoop/hbase/ipc/HBaseRpcController;
     193: invokestatic  #22                 // Method org/mockito/Mockito.when:(Ljava/lang/Object;)Lorg/mockito/stubbing/OngoingStubbing;
     196: ldc           #29                 // class org/apache/hadoop/hbase/ipc/HBaseRpcController
     198: invokestatic  #11                 // Method org/mockito/Mockito.mock:(Ljava/lang/Class;)Ljava/lang/Object;
     201: invokeinterface #23,  2           // InterfaceMethod org/mockito/stubbing/OngoingStubbing.thenReturn:(Ljava/lang/Object;)Lorg/mockito/stubbing/OngoingStubbing;
     206: pop
     207: aload         8
     209: invokevirtual #30                 // Method org/apache/hadoop/hbase/client/ConnectionImplementation.getRpcRetryingCallerFactory:()Lorg/apache/hadoop/hbase/client/RpcRetryingCallerFactory;
     212: invokestatic  #22                 // Method org/mockito/Mockito.when:(Ljava/lang/Object;)Lorg/mockito/stubbing/OngoingStubbing;
     215: aload         11
     217: invokeinterface #23,  2           // InterfaceMethod org/mockito/stubbing/OngoingStubbing.thenReturn:(Ljava/lang/Object;)Lorg/mockito/stubbing/OngoingStubbing;
     222: pop
     223: aload         8
     225: invokevirtual #31                 // Method org/apache/hadoop/hbase/client/ConnectionImplementation.getRpcControllerFactory:()Lorg/apache/hadoop/hbase/ipc/RpcControllerFactory;
     228: invokestatic  #22                 // Method org/mockito/Mockito.when:(Ljava/lang/Object;)Lorg/mockito/stubbing/OngoingStubbing;
     231: aload         12
     233: invokeinterface #23,  2           // InterfaceMethod org/mockito/stubbing/OngoingStubbing.thenReturn:(Ljava/lang/Object;)Lorg/mockito/stubbing/OngoingStubbing;
     238: pop
     239: invokestatic  #32                 // Method org/apache/hadoop/hbase/shaded/protobuf/generated/MasterProtos$SnapshotResponse.newBuilder:()Lorg/apache/hadoop/hbase/shaded/protobuf/generated/MasterProtos$SnapshotResponse$Builder;
     242: iload_2
     243: i2l
     244: invokevirtual #33                 // Method org/apache/hadoop/hbase/shaded/protobuf/generated/MasterProtos$SnapshotResponse$Builder.setExpectedTimeout:(J)Lorg/apache/hadoop/hbase/shaded/protobuf/generated/MasterProtos$SnapshotResponse$Builder;
     247: invokevirtual #34                 // Method org/apache/hadoop/hbase/shaded/protobuf/generated/MasterProtos$SnapshotResponse$Builder.build:()Lorg/apache/hadoop/hbase/shaded/protobuf/generated/MasterProtos$SnapshotResponse;
     250: astore        13
     252: aload         10
     254: invokestatic  #35                 // Method org/mockito/Mockito.any:()Ljava/lang/Object;
     257: checkcast     #36                 // class org/apache/hbase/thirdparty/com/google/protobuf/RpcController
     260: invokestatic  #35                 // Method org/mockito/Mockito.any:()Ljava/lang/Object;
     263: checkcast     #37                 // class org/apache/hadoop/hbase/shaded/protobuf/generated/MasterProtos$SnapshotRequest
     266: invokeinterface #38,  3           // InterfaceMethod org/apache/hadoop/hbase/client/MasterKeepAliveConnection.snapshot:(Lorg/apache/hbase/thirdparty/com/google/protobuf/RpcController;Lorg/apache/hadoop/hbase/shaded/protobuf/generated/MasterProtos$SnapshotRequest;)Lorg/apache/hadoop/hbase/shaded/protobuf/generated/MasterProtos$SnapshotResponse;
     271: invokestatic  #22                 // Method org/mockito/Mockito.when:(Ljava/lang/Object;)Lorg/mockito/stubbing/OngoingStubbing;
     274: aload         13
     276: invokeinterface #23,  2           // InterfaceMethod org/mockito/stubbing/OngoingStubbing.thenReturn:(Ljava/lang/Object;)Lorg/mockito/stubbing/OngoingStubbing;
     281: pop
     282: invokestatic  #39                 // Method org/apache/hadoop/hbase/shaded/protobuf/generated/MasterProtos$IsSnapshotDoneResponse.newBuilder:()Lorg/apache/hadoop/hbase/shaded/protobuf/generated/MasterProtos$IsSnapshotDoneResponse$Builder;
     285: astore        14
     287: aload         14
     289: iconst_0
     290: invokevirtual #40                 // Method org/apache/hadoop/hbase/shaded/protobuf/generated/MasterProtos$IsSnapshotDoneResponse$Builder.setDone:(Z)Lorg/apache/hadoop/hbase/shaded/protobuf/generated/MasterProtos$IsSnapshotDoneResponse$Builder;
     293: pop
     294: aload         10
     296: invokestatic  #35                 // Method org/mockito/Mockito.any:()Ljava/lang/Object;
     299: checkcast     #36                 // class org/apache/hbase/thirdparty/com/google/protobuf/RpcController
     302: invokestatic  #35                 // Method org/mockito/Mockito.any:()Ljava/lang/Object;
     305: checkcast     #41                 // class org/apache/hadoop/hbase/shaded/protobuf/generated/MasterProtos$IsSnapshotDoneRequest
     308: invokeinterface #42,  3           // InterfaceMethod org/apache/hadoop/hbase/client/MasterKeepAliveConnection.isSnapshotDone:(Lorg/apache/hbase/thirdparty/com/google/protobuf/RpcController;Lorg/apache/hadoop/hbase/shaded/protobuf/generated/MasterProtos$IsSnapshotDoneRequest;)Lorg/apache/hadoop/hbase/shaded/protobuf/generated/MasterProtos$IsSnapshotDoneResponse;
     313: invokestatic  #22                 // Method org/mockito/Mockito.when:(Ljava/lang/Object;)Lorg/mockito/stubbing/OngoingStubbing;
     316: aload         14
     318: invokevirtual #43                 // Method org/apache/hadoop/hbase/shaded/protobuf/generated/MasterProtos$IsSnapshotDoneResponse$Builder.build:()Lorg/apache/hadoop/hbase/shaded/protobuf/generated/MasterProtos$IsSnapshotDoneResponse;
     321: iconst_5
     322: anewarray     #44                 // class org/apache/hadoop/hbase/shaded/protobuf/generated/MasterProtos$IsSnapshotDoneResponse
     325: dup
     326: iconst_0
     327: aload         14
     329: invokevirtual #43                 // Method org/apache/hadoop/hbase/shaded/protobuf/generated/MasterProtos$IsSnapshotDoneResponse$Builder.build:()Lorg/apache/hadoop/hbase/shaded/protobuf/generated/MasterProtos$IsSnapshotDoneResponse;
     332: aastore
     333: dup
     334: iconst_1
     335: aload         14
     337: invokevirtual #43                 // Method org/apache/hadoop/hbase/shaded/protobuf/generated/MasterProtos$IsSnapshotDoneResponse$Builder.build:()Lorg/apache/hadoop/hbase/shaded/protobuf/generated/MasterProtos$IsSnapshotDoneResponse;
     340: aastore
     341: dup
     342: iconst_2
     343: aload         14
     345: invokevirtual #43                 // Method org/apache/hadoop/hbase/shaded/protobuf/generated/MasterProtos$IsSnapshotDoneResponse$Builder.build:()Lorg/apache/hadoop/hbase/shaded/protobuf/generated/MasterProtos$IsSnapshotDoneResponse;
     348: aastore
     349: dup
     350: iconst_3
     351: aload         14
     353: invokevirtual #43                 // Method org/apache/hadoop/hbase/shaded/protobuf/generated/MasterProtos$IsSnapshotDoneResponse$Builder.build:()Lorg/apache/hadoop/hbase/shaded/protobuf/generated/MasterProtos$IsSnapshotDoneResponse;
     356: aastore
     357: dup
     358: iconst_4
     359: aload         14
     361: iconst_1
     362: invokevirtual #40                 // Method org/apache/hadoop/hbase/shaded/protobuf/generated/MasterProtos$IsSnapshotDoneResponse$Builder.setDone:(Z)Lorg/apache/hadoop/hbase/shaded/protobuf/generated/MasterProtos$IsSnapshotDoneResponse$Builder;
     365: invokevirtual #43                 // Method org/apache/hadoop/hbase/shaded/protobuf/generated/MasterProtos$IsSnapshotDoneResponse$Builder.build:()Lorg/apache/hadoop/hbase/shaded/protobuf/generated/MasterProtos$IsSnapshotDoneResponse;
     368: aastore
     369: invokeinterface #45,  3           // InterfaceMethod org/mockito/stubbing/OngoingStubbing.thenReturn:(Ljava/lang/Object;[Ljava/lang/Object;)Lorg/mockito/stubbing/OngoingStubbing;
     374: pop
     375: new           #46                 // class org/apache/hadoop/hbase/client/HBaseAdmin
     378: dup
     379: aload         8
     381: invokespecial #47                 // Method org/apache/hadoop/hbase/client/HBaseAdmin."<init>":(Lorg/apache/hadoop/hbase/client/ClusterConnection;)V
     384: astore        15
     386: ldc           #48                 // String snapshot
     388: astore        16
     390: aload_0
     391: getfield      #4                  // Field name:Lorg/junit/rules/TestName;
     394: invokevirtual #49                 // Method org/junit/rules/TestName.getMethodName:()Ljava/lang/String;
     397: invokestatic  #50                 // Method org/apache/hadoop/hbase/TableName.valueOf:(Ljava/lang/String;)Lorg/apache/hadoop/hbase/TableName;
     400: astore        17
     402: invokestatic  #51                 // Method java/lang/System.currentTimeMillis:()J
     405: lstore        18
     407: aload         15
     409: aload         16
     411: aload         17
     413: invokeinterface #52,  3           // InterfaceMethod org/apache/hadoop/hbase/client/Admin.snapshot:(Ljava/lang/String;Lorg/apache/hadoop/hbase/TableName;)V
     418: invokestatic  #51                 // Method java/lang/System.currentTimeMillis:()J
     421: lstore        20
     423: lload         20
     425: lload         18
     427: lsub
     428: lstore        22
     430: new           #53                 // class java/lang/StringBuilder
     433: dup
     434: invokespecial #54                 // Method java/lang/StringBuilder."<init>":()V
     437: ldc           #55                 // String Elapsed time:
     439: invokevirtual #56                 // Method java/lang/StringBuilder.append:(Ljava/lang/String;)Ljava/lang/StringBuilder;
     442: lload         22
     444: invokevirtual #57                 // Method java/lang/StringBuilder.append:(J)Ljava/lang/StringBuilder;
     447: ldc           #58                 // String  is more than expected max:
     449: invokevirtual #56                 // Method java/lang/StringBuilder.append:(Ljava/lang/String;)Ljava/lang/StringBuilder;
     452: lload         6
     454: invokevirtual #57                 // Method java/lang/StringBuilder.append:(J)Ljava/lang/StringBuilder;
     457: invokevirtual #59                 // Method java/lang/StringBuilder.toString:()Ljava/lang/String;
     460: lload         22
     462: lload         6
     464: lcmp
     465: ifgt          472
     468: iconst_1
     469: goto          473
     472: iconst_0
     473: invokestatic  #9                  // Method org/junit/Assert.assertTrue:(Ljava/lang/String;Z)V
     476: aload         15
     478: invokeinterface #60,  1           // InterfaceMethod org/apache/hadoop/hbase/client/Admin.close:()V
     483: return

  public void testValidateSnapshotName() throws java.lang.Exception;
    Code:
       0: ldc           #10                 // class org/apache/hadoop/hbase/client/ConnectionImplementation
       2: invokestatic  #11                 // Method org/mockito/Mockito.mock:(Ljava/lang/Class;)Ljava/lang/Object;
       5: checkcast     #10                 // class org/apache/hadoop/hbase/client/ConnectionImplementation
       8: astore_1
       9: invokestatic  #12                 // Method org/apache/hadoop/hbase/HBaseConfiguration.create:()Lorg/apache/hadoop/conf/Configuration;
      12: astore_2
      13: aload_1
      14: invokevirtual #21                 // Method org/apache/hadoop/hbase/client/ConnectionImplementation.getConfiguration:()Lorg/apache/hadoop/conf/Configuration;
      17: invokestatic  #22                 // Method org/mockito/Mockito.when:(Ljava/lang/Object;)Lorg/mockito/stubbing/OngoingStubbing;
      20: aload_2
      21: invokeinterface #23,  2           // InterfaceMethod org/mockito/stubbing/OngoingStubbing.thenReturn:(Ljava/lang/Object;)Lorg/mockito/stubbing/OngoingStubbing;
      26: pop
      27: new           #25                 // class org/apache/hadoop/hbase/client/RpcRetryingCallerFactory
      30: dup
      31: aload_2
      32: invokespecial #26                 // Method org/apache/hadoop/hbase/client/RpcRetryingCallerFactory."<init>":(Lorg/apache/hadoop/conf/Configuration;)V
      35: astore_3
      36: ldc           #27                 // class org/apache/hadoop/hbase/ipc/RpcControllerFactory
      38: invokestatic  #11                 // Method org/mockito/Mockito.mock:(Ljava/lang/Class;)Ljava/lang/Object;
      41: checkcast     #27                 // class org/apache/hadoop/hbase/ipc/RpcControllerFactory
      44: astore        4
      46: aload         4
      48: invokevirtual #28                 // Method org/apache/hadoop/hbase/ipc/RpcControllerFactory.newController:()Lorg/apache/hadoop/hbase/ipc/HBaseRpcController;
      51: invokestatic  #22                 // Method org/mockito/Mockito.when:(Ljava/lang/Object;)Lorg/mockito/stubbing/OngoingStubbing;
      54: ldc           #29                 // class org/apache/hadoop/hbase/ipc/HBaseRpcController
      56: invokestatic  #11                 // Method org/mockito/Mockito.mock:(Ljava/lang/Class;)Ljava/lang/Object;
      59: invokeinterface #23,  2           // InterfaceMethod org/mockito/stubbing/OngoingStubbing.thenReturn:(Ljava/lang/Object;)Lorg/mockito/stubbing/OngoingStubbing;
      64: pop
      65: aload_1
      66: invokevirtual #30                 // Method org/apache/hadoop/hbase/client/ConnectionImplementation.getRpcRetryingCallerFactory:()Lorg/apache/hadoop/hbase/client/RpcRetryingCallerFactory;
      69: invokestatic  #22                 // Method org/mockito/Mockito.when:(Ljava/lang/Object;)Lorg/mockito/stubbing/OngoingStubbing;
      72: aload_3
      73: invokeinterface #23,  2           // InterfaceMethod org/mockito/stubbing/OngoingStubbing.thenReturn:(Ljava/lang/Object;)Lorg/mockito/stubbing/OngoingStubbing;
      78: pop
      79: aload_1
      80: invokevirtual #31                 // Method org/apache/hadoop/hbase/client/ConnectionImplementation.getRpcControllerFactory:()Lorg/apache/hadoop/hbase/ipc/RpcControllerFactory;
      83: invokestatic  #22                 // Method org/mockito/Mockito.when:(Ljava/lang/Object;)Lorg/mockito/stubbing/OngoingStubbing;
      86: aload         4
      88: invokeinterface #23,  2           // InterfaceMethod org/mockito/stubbing/OngoingStubbing.thenReturn:(Ljava/lang/Object;)Lorg/mockito/stubbing/OngoingStubbing;
      93: pop
      94: new           #46                 // class org/apache/hadoop/hbase/client/HBaseAdmin
      97: dup
      98: aload_1
      99: invokespecial #47                 // Method org/apache/hadoop/hbase/client/HBaseAdmin."<init>":(Lorg/apache/hadoop/hbase/client/ClusterConnection;)V
     102: astore        5
     104: aload_0
     105: aload         5
     107: new           #61                 // class org/apache/hadoop/hbase/client/SnapshotDescription
     110: dup
     111: ldc           #62                 // String .hbase-snapshot
     113: invokespecial #63                 // Method org/apache/hadoop/hbase/client/SnapshotDescription."<init>":(Ljava/lang/String;)V
     116: invokespecial #64                 // Method failSnapshotStart:(Lorg/apache/hadoop/hbase/client/Admin;Lorg/apache/hadoop/hbase/client/SnapshotDescription;)V
     119: aload_0
     120: aload         5
     122: new           #61                 // class org/apache/hadoop/hbase/client/SnapshotDescription
     125: dup
     126: ldc           #65                 // String -snapshot
     128: invokespecial #63                 // Method org/apache/hadoop/hbase/client/SnapshotDescription."<init>":(Ljava/lang/String;)V
     131: invokespecial #64                 // Method failSnapshotStart:(Lorg/apache/hadoop/hbase/client/Admin;Lorg/apache/hadoop/hbase/client/SnapshotDescription;)V
     134: aload_0
     135: aload         5
     137: new           #61                 // class org/apache/hadoop/hbase/client/SnapshotDescription
     140: dup
     141: ldc           #66                 // String snapshot fails
     143: invokespecial #63                 // Method org/apache/hadoop/hbase/client/SnapshotDescription."<init>":(Ljava/lang/String;)V
     146: invokespecial #64                 // Method failSnapshotStart:(Lorg/apache/hadoop/hbase/client/Admin;Lorg/apache/hadoop/hbase/client/SnapshotDescription;)V
     149: aload_0
     150: aload         5
     152: new           #61                 // class org/apache/hadoop/hbase/client/SnapshotDescription
     155: dup
     156: ldc           #67                 // String snap$hot
     158: invokespecial #63                 // Method org/apache/hadoop/hbase/client/SnapshotDescription."<init>":(Ljava/lang/String;)V
     161: invokespecial #64                 // Method failSnapshotStart:(Lorg/apache/hadoop/hbase/client/Admin;Lorg/apache/hadoop/hbase/client/SnapshotDescription;)V
     164: aload_0
     165: aload         5
     167: new           #61                 // class org/apache/hadoop/hbase/client/SnapshotDescription
     170: dup
     171: ldc           #68                 // String snap:hot
     173: invokespecial #63                 // Method org/apache/hadoop/hbase/client/SnapshotDescription."<init>":(Ljava/lang/String;)V
     176: invokespecial #64                 // Method failSnapshotStart:(Lorg/apache/hadoop/hbase/client/Admin;Lorg/apache/hadoop/hbase/client/SnapshotDescription;)V
     179: aload_0
     180: ldc           #48                 // String snapshot
     182: ldc           #69                 // String .table
     184: invokespecial #70                 // Method failSnapshotDescriptorCreation:(Ljava/lang/String;Ljava/lang/String;)V
     187: aload_0
     188: ldc           #48                 // String snapshot
     190: ldc           #71                 // String -table
     192: invokespecial #70                 // Method failSnapshotDescriptorCreation:(Ljava/lang/String;Ljava/lang/String;)V
     195: aload_0
     196: ldc           #48                 // String snapshot
     198: ldc           #72                 // String table fails
     200: invokespecial #70                 // Method failSnapshotDescriptorCreation:(Ljava/lang/String;Ljava/lang/String;)V
     203: aload_0
     204: ldc           #48                 // String snapshot
     206: ldc           #73                 // String tab%le
     208: invokespecial #70                 // Method failSnapshotDescriptorCreation:(Ljava/lang/String;Ljava/lang/String;)V
     211: ldc           #20                 // class org/apache/hadoop/hbase/client/MasterKeepAliveConnection
     213: invokestatic  #11                 // Method org/mockito/Mockito.mock:(Ljava/lang/Class;)Ljava/lang/Object;
     216: checkcast     #20                 // class org/apache/hadoop/hbase/client/MasterKeepAliveConnection
     219: astore        6
     221: aload_1
     222: invokevirtual #24                 // Method org/apache/hadoop/hbase/client/ConnectionImplementation.getMaster:()Lorg/apache/hadoop/hbase/client/MasterKeepAliveConnection;
     225: invokestatic  #22                 // Method org/mockito/Mockito.when:(Ljava/lang/Object;)Lorg/mockito/stubbing/OngoingStubbing;
     228: aload         6
     230: invokeinterface #23,  2           // InterfaceMethod org/mockito/stubbing/OngoingStubbing.thenReturn:(Ljava/lang/Object;)Lorg/mockito/stubbing/OngoingStubbing;
     235: pop
     236: invokestatic  #32                 // Method org/apache/hadoop/hbase/shaded/protobuf/generated/MasterProtos$SnapshotResponse.newBuilder:()Lorg/apache/hadoop/hbase/shaded/protobuf/generated/MasterProtos$SnapshotResponse$Builder;
     239: lconst_0
     240: invokevirtual #33                 // Method org/apache/hadoop/hbase/shaded/protobuf/generated/MasterProtos$SnapshotResponse$Builder.setExpectedTimeout:(J)Lorg/apache/hadoop/hbase/shaded/protobuf/generated/MasterProtos$SnapshotResponse$Builder;
     243: invokevirtual #34                 // Method org/apache/hadoop/hbase/shaded/protobuf/generated/MasterProtos$SnapshotResponse$Builder.build:()Lorg/apache/hadoop/hbase/shaded/protobuf/generated/MasterProtos$SnapshotResponse;
     246: astore        7
     248: aload         6
     250: invokestatic  #35                 // Method org/mockito/Mockito.any:()Ljava/lang/Object;
     253: checkcast     #36                 // class org/apache/hbase/thirdparty/com/google/protobuf/RpcController
     256: invokestatic  #35                 // Method org/mockito/Mockito.any:()Ljava/lang/Object;
     259: checkcast     #37                 // class org/apache/hadoop/hbase/shaded/protobuf/generated/MasterProtos$SnapshotRequest
     262: invokeinterface #38,  3           // InterfaceMethod org/apache/hadoop/hbase/client/MasterKeepAliveConnection.snapshot:(Lorg/apache/hbase/thirdparty/com/google/protobuf/RpcController;Lorg/apache/hadoop/hbase/shaded/protobuf/generated/MasterProtos$SnapshotRequest;)Lorg/apache/hadoop/hbase/shaded/protobuf/generated/MasterProtos$SnapshotResponse;
     267: invokestatic  #22                 // Method org/mockito/Mockito.when:(Ljava/lang/Object;)Lorg/mockito/stubbing/OngoingStubbing;
     270: aload         7
     272: invokeinterface #23,  2           // InterfaceMethod org/mockito/stubbing/OngoingStubbing.thenReturn:(Ljava/lang/Object;)Lorg/mockito/stubbing/OngoingStubbing;
     277: pop
     278: invokestatic  #39                 // Method org/apache/hadoop/hbase/shaded/protobuf/generated/MasterProtos$IsSnapshotDoneResponse.newBuilder:()Lorg/apache/hadoop/hbase/shaded/protobuf/generated/MasterProtos$IsSnapshotDoneResponse$Builder;
     281: iconst_1
     282: invokevirtual #40                 // Method org/apache/hadoop/hbase/shaded/protobuf/generated/MasterProtos$IsSnapshotDoneResponse$Builder.setDone:(Z)Lorg/apache/hadoop/hbase/shaded/protobuf/generated/MasterProtos$IsSnapshotDoneResponse$Builder;
     285: invokevirtual #43                 // Method org/apache/hadoop/hbase/shaded/protobuf/generated/MasterProtos$IsSnapshotDoneResponse$Builder.build:()Lorg/apache/hadoop/hbase/shaded/protobuf/generated/MasterProtos$IsSnapshotDoneResponse;
     288: astore        8
     290: aload         6
     292: invokestatic  #35                 // Method org/mockito/Mockito.any:()Ljava/lang/Object;
     295: checkcast     #36                 // class org/apache/hbase/thirdparty/com/google/protobuf/RpcController
     298: invokestatic  #35                 // Method org/mockito/Mockito.any:()Ljava/lang/Object;
     301: checkcast     #41                 // class org/apache/hadoop/hbase/shaded/protobuf/generated/MasterProtos$IsSnapshotDoneRequest
     304: invokeinterface #42,  3           // InterfaceMethod org/apache/hadoop/hbase/client/MasterKeepAliveConnection.isSnapshotDone:(Lorg/apache/hbase/thirdparty/com/google/protobuf/RpcController;Lorg/apache/hadoop/hbase/shaded/protobuf/generated/MasterProtos$IsSnapshotDoneRequest;)Lorg/apache/hadoop/hbase/shaded/protobuf/generated/MasterProtos$IsSnapshotDoneResponse;
     309: invokestatic  #22                 // Method org/mockito/Mockito.when:(Ljava/lang/Object;)Lorg/mockito/stubbing/OngoingStubbing;
     312: aload         8
     314: invokeinterface #23,  2           // InterfaceMethod org/mockito/stubbing/OngoingStubbing.thenReturn:(Ljava/lang/Object;)Lorg/mockito/stubbing/OngoingStubbing;
     319: pop
     320: aload         5
     322: new           #61                 // class org/apache/hadoop/hbase/client/SnapshotDescription
     325: dup
     326: ldc           #48                 // String snapshot
     328: aload_0
     329: getfield      #4                  // Field name:Lorg/junit/rules/TestName;
     332: invokevirtual #49                 // Method org/junit/rules/TestName.getMethodName:()Ljava/lang/String;
     335: invokestatic  #50                 // Method org/apache/hadoop/hbase/TableName.valueOf:(Ljava/lang/String;)Lorg/apache/hadoop/hbase/TableName;
     338: invokespecial #74                 // Method org/apache/hadoop/hbase/client/SnapshotDescription."<init>":(Ljava/lang/String;Lorg/apache/hadoop/hbase/TableName;)V
     341: invokeinterface #75,  2           // InterfaceMethod org/apache/hadoop/hbase/client/Admin.snapshot:(Lorg/apache/hadoop/hbase/client/SnapshotDescription;)V
     346: return

  static {};
    Code:
       0: ldc           #87                 // class org/apache/hadoop/hbase/client/TestSnapshotFromAdmin
       2: invokestatic  #88                 // Method org/apache/hadoop/hbase/HBaseClassTestRule.forClass:(Ljava/lang/Class;)Lorg/apache/hadoop/hbase/HBaseClassTestRule;
       5: putstatic     #89                 // Field CLASS_RULE:Lorg/apache/hadoop/hbase/HBaseClassTestRule;
       8: ldc           #87                 // class org/apache/hadoop/hbase/client/TestSnapshotFromAdmin
      10: invokestatic  #90                 // Method org/slf4j/LoggerFactory.getLogger:(Ljava/lang/Class;)Lorg/slf4j/Logger;
      13: putstatic     #80                 // Field LOG:Lorg/slf4j/Logger;
      16: return
}
