Compiled from "TestSimpleRequestController.java"
final class org.apache.hadoop.hbase.client.TestSimpleRequestController$1 extends org.apache.hadoop.hbase.client.Put {
  final long val$maxHeapSizePerRequest;

  org.apache.hadoop.hbase.client.TestSimpleRequestController$1(byte[], long);
    Code:
       0: aload_0
       1: lload_2
       2: putfield      #1                  // Field val$maxHeapSizePerRequest:J
       5: aload_0
       6: aload_1
       7: invokespecial #2                  // Method org/apache/hadoop/hbase/client/Put."<init>":([B)V
      10: return

  public long heapSize();
    Code:
       0: aload_0
       1: getfield      #1                  // Field val$maxHeapSizePerRequest:J
       4: lreturn
}
