Compiled from "TestRegionObserverInterface.java"
public class org.apache.hadoop.hbase.coprocessor.TestRegionObserverInterface$EvenOnlyCompactor implements org.apache.hadoop.hbase.coprocessor.RegionCoprocessor,org.apache.hadoop.hbase.coprocessor.RegionObserver {
  long lastCompaction;

  long lastFlush;

  public org.apache.hadoop.hbase.coprocessor.TestRegionObserverInterface$EvenOnlyCompactor();
    Code:
       0: aload_0
       1: invokespecial #1                  // Method java/lang/Object."<init>":()V
       4: return

  public java.util.Optional<org.apache.hadoop.hbase.coprocessor.RegionObserver> getRegionObserver();
    Code:
       0: aload_0
       1: invokestatic  #2                  // Method java/util/Optional.of:(Ljava/lang/Object;)Ljava/util/Optional;
       4: areturn

  public org.apache.hadoop.hbase.regionserver.InternalScanner preCompact(org.apache.hadoop.hbase.coprocessor.ObserverContext<org.apache.hadoop.hbase.coprocessor.RegionCoprocessorEnvironment>, org.apache.hadoop.hbase.regionserver.Store, org.apache.hadoop.hbase.regionserver.InternalScanner, org.apache.hadoop.hbase.regionserver.ScanType, org.apache.hadoop.hbase.regionserver.compactions.CompactionLifeCycleTracker, org.apache.hadoop.hbase.regionserver.compactions.CompactionRequest);
    Code:
       0: new           #3                  // class org/apache/hadoop/hbase/coprocessor/TestRegionObserverInterface$EvenOnlyCompactor$1
       3: dup
       4: aload_0
       5: aload_3
       6: invokespecial #4                  // Method org/apache/hadoop/hbase/coprocessor/TestRegionObserverInterface$EvenOnlyCompactor$1."<init>":(Lorg/apache/hadoop/hbase/coprocessor/TestRegionObserverInterface$EvenOnlyCompactor;Lorg/apache/hadoop/hbase/regionserver/InternalScanner;)V
       9: areturn

  public void postCompact(org.apache.hadoop.hbase.coprocessor.ObserverContext<org.apache.hadoop.hbase.coprocessor.RegionCoprocessorEnvironment>, org.apache.hadoop.hbase.regionserver.Store, org.apache.hadoop.hbase.regionserver.StoreFile, org.apache.hadoop.hbase.regionserver.compactions.CompactionLifeCycleTracker, org.apache.hadoop.hbase.regionserver.compactions.CompactionRequest);
    Code:
       0: aload_0
       1: invokestatic  #5                  // Method org/apache/hadoop/hbase/util/EnvironmentEdgeManager.currentTime:()J
       4: putfield      #6                  // Field lastCompaction:J
       7: return

  public void postFlush(org.apache.hadoop.hbase.coprocessor.ObserverContext<org.apache.hadoop.hbase.coprocessor.RegionCoprocessorEnvironment>, org.apache.hadoop.hbase.regionserver.FlushLifeCycleTracker);
    Code:
       0: aload_0
       1: invokestatic  #5                  // Method org/apache/hadoop/hbase/util/EnvironmentEdgeManager.currentTime:()J
       4: putfield      #7                  // Field lastFlush:J
       7: return
}
