Compiled from "TestNamespaceAuditor.java"
public class org.apache.hadoop.hbase.namespace.TestNamespaceAuditor {
  public static final org.apache.hadoop.hbase.HBaseClassTestRule CLASS_RULE;

  public org.apache.hadoop.hbase.namespace.TestNamespaceAuditor();
    Code:
       0: aload_0
       1: invokespecial #3                  // Method java/lang/Object."<init>":()V
       4: aload_0
       5: ldc           #4                  // String TestNamespaceAuditor
       7: putfield      #5                  // Field prefix:Ljava/lang/String;
      10: return

  public static void before() throws java.lang.Exception;
    Code:
       0: getstatic     #6                  // Field UTIL:Lorg/apache/hadoop/hbase/HBaseTestingUtility;
       3: invokevirtual #7                  // Method org/apache/hadoop/hbase/HBaseTestingUtility.getConfiguration:()Lorg/apache/hadoop/conf/Configuration;
       6: astore_0
       7: aload_0
       8: ldc           #9                  // String hbase.coprocessor.region.classes
      10: ldc           #10                 // class org/apache/hadoop/hbase/namespace/TestNamespaceAuditor$CustomObserver
      12: invokevirtual #11                 // Method java/lang/Class.getName:()Ljava/lang/String;
      15: invokevirtual #12                 // Method org/apache/hadoop/conf/Configuration.set:(Ljava/lang/String;Ljava/lang/String;)V
      18: aload_0
      19: ldc           #13                 // String hbase.coprocessor.master.classes
      21: iconst_2
      22: anewarray     #14                 // class java/lang/String
      25: dup
      26: iconst_0
      27: ldc           #15                 // class org/apache/hadoop/hbase/namespace/TestNamespaceAuditor$MasterSyncObserver
      29: invokevirtual #11                 // Method java/lang/Class.getName:()Ljava/lang/String;
      32: aastore
      33: dup
      34: iconst_1
      35: ldc           #16                 // class org/apache/hadoop/hbase/namespace/TestNamespaceAuditor$CPMasterObserver
      37: invokevirtual #11                 // Method java/lang/Class.getName:()Ljava/lang/String;
      40: aastore
      41: invokevirtual #17                 // Method org/apache/hadoop/conf/Configuration.setStrings:(Ljava/lang/String;[Ljava/lang/String;)V
      44: aload_0
      45: ldc           #19                 // String hbase.client.retries.number
      47: iconst_5
      48: invokevirtual #20                 // Method org/apache/hadoop/conf/Configuration.setInt:(Ljava/lang/String;I)V
      51: aload_0
      52: ldc           #22                 // String hbase.quota.enabled
      54: iconst_1
      55: invokevirtual #23                 // Method org/apache/hadoop/conf/Configuration.setBoolean:(Ljava/lang/String;Z)V
      58: aload_0
      59: ldc           #24                 // String hbase.coprocessor.regionserver.classes
      61: ldc           #25                 // class org/apache/hadoop/hbase/namespace/TestNamespaceAuditor$CPRegionServerObserver
      63: ldc           #26                 // class org/apache/hadoop/hbase/coprocessor/RegionServerObserver
      65: invokevirtual #27                 // Method org/apache/hadoop/conf/Configuration.setClass:(Ljava/lang/String;Ljava/lang/Class;Ljava/lang/Class;)V
      68: getstatic     #6                  // Field UTIL:Lorg/apache/hadoop/hbase/HBaseTestingUtility;
      71: invokevirtual #28                 // Method org/apache/hadoop/hbase/HBaseTestingUtility.startMiniCluster:()Lorg/apache/hadoop/hbase/MiniHBaseCluster;
      74: pop
      75: getstatic     #6                  // Field UTIL:Lorg/apache/hadoop/hbase/HBaseTestingUtility;
      78: invokestatic  #29                 // Method waitForQuotaInitialize:(Lorg/apache/hadoop/hbase/HBaseTestingUtility;)V
      81: getstatic     #6                  // Field UTIL:Lorg/apache/hadoop/hbase/HBaseTestingUtility;
      84: invokevirtual #30                 // Method org/apache/hadoop/hbase/HBaseTestingUtility.getAdmin:()Lorg/apache/hadoop/hbase/client/Admin;
      87: putstatic     #2                  // Field ADMIN:Lorg/apache/hadoop/hbase/client/Admin;
      90: return

  public static void tearDown() throws java.lang.Exception;
    Code:
       0: getstatic     #6                  // Field UTIL:Lorg/apache/hadoop/hbase/HBaseTestingUtility;
       3: invokevirtual #31                 // Method org/apache/hadoop/hbase/HBaseTestingUtility.shutdownMiniCluster:()V
       6: return

  public void cleanup() throws java.lang.Exception, org.apache.zookeeper.KeeperException;
    Code:
       0: getstatic     #2                  // Field ADMIN:Lorg/apache/hadoop/hbase/client/Admin;
       3: invokeinterface #32,  1           // InterfaceMethod org/apache/hadoop/hbase/client/Admin.listTableDescriptors:()Ljava/util/List;
       8: invokeinterface #33,  1           // InterfaceMethod java/util/List.iterator:()Ljava/util/Iterator;
      13: astore_1
      14: aload_1
      15: invokeinterface #34,  1           // InterfaceMethod java/util/Iterator.hasNext:()Z
      20: ifeq          60
      23: aload_1
      24: invokeinterface #35,  1           // InterfaceMethod java/util/Iterator.next:()Ljava/lang/Object;
      29: checkcast     #36                 // class org/apache/hadoop/hbase/client/TableDescriptor
      32: astore_2
      33: getstatic     #2                  // Field ADMIN:Lorg/apache/hadoop/hbase/client/Admin;
      36: aload_2
      37: invokeinterface #37,  1           // InterfaceMethod org/apache/hadoop/hbase/client/TableDescriptor.getTableName:()Lorg/apache/hadoop/hbase/TableName;
      42: invokeinterface #38,  2           // InterfaceMethod org/apache/hadoop/hbase/client/Admin.disableTable:(Lorg/apache/hadoop/hbase/TableName;)V
      47: aload_0
      48: aload_2
      49: invokeinterface #37,  1           // InterfaceMethod org/apache/hadoop/hbase/client/TableDescriptor.getTableName:()Lorg/apache/hadoop/hbase/TableName;
      54: invokespecial #39                 // Method deleteTable:(Lorg/apache/hadoop/hbase/TableName;)V
      57: goto          14
      60: getstatic     #2                  // Field ADMIN:Lorg/apache/hadoop/hbase/client/Admin;
      63: invokeinterface #40,  1           // InterfaceMethod org/apache/hadoop/hbase/client/Admin.listNamespaceDescriptors:()[Lorg/apache/hadoop/hbase/NamespaceDescriptor;
      68: astore_1
      69: aload_1
      70: arraylength
      71: istore_2
      72: iconst_0
      73: istore_3
      74: iload_3
      75: iload_2
      76: if_icmpge     118
      79: aload_1
      80: iload_3
      81: aaload
      82: astore        4
      84: aload         4
      86: invokevirtual #41                 // Method org/apache/hadoop/hbase/NamespaceDescriptor.getName:()Ljava/lang/String;
      89: aload_0
      90: getfield      #5                  // Field prefix:Ljava/lang/String;
      93: invokevirtual #42                 // Method java/lang/String.startsWith:(Ljava/lang/String;)Z
      96: ifeq          112
      99: getstatic     #2                  // Field ADMIN:Lorg/apache/hadoop/hbase/client/Admin;
     102: aload         4
     104: invokevirtual #41                 // Method org/apache/hadoop/hbase/NamespaceDescriptor.getName:()Ljava/lang/String;
     107: invokeinterface #43,  2           // InterfaceMethod org/apache/hadoop/hbase/client/Admin.deleteNamespace:(Ljava/lang/String;)V
     112: iinc          3, 1
     115: goto          74
     118: ldc           #44                 // String Quota manager not initialized
     120: getstatic     #6                  // Field UTIL:Lorg/apache/hadoop/hbase/HBaseTestingUtility;
     123: invokevirtual #45                 // Method org/apache/hadoop/hbase/HBaseTestingUtility.getHBaseCluster:()Lorg/apache/hadoop/hbase/MiniHBaseCluster;
     126: invokevirtual #46                 // Method org/apache/hadoop/hbase/MiniHBaseCluster.getMaster:()Lorg/apache/hadoop/hbase/master/HMaster;
     129: invokevirtual #47                 // Method org/apache/hadoop/hbase/master/HMaster.getMasterQuotaManager:()Lorg/apache/hadoop/hbase/quotas/MasterQuotaManager;
     132: invokevirtual #48                 // Method org/apache/hadoop/hbase/quotas/MasterQuotaManager.isQuotaInitialized:()Z
     135: invokestatic  #49                 // Method org/junit/Assert.assertTrue:(Ljava/lang/String;Z)V
     138: return

  public void testTableOperations() throws java.lang.Exception;
    Code:
       0: new           #50                 // class java/lang/StringBuilder
       3: dup
       4: invokespecial #51                 // Method java/lang/StringBuilder."<init>":()V
       7: aload_0
       8: getfield      #5                  // Field prefix:Ljava/lang/String;
      11: invokevirtual #52                 // Method java/lang/StringBuilder.append:(Ljava/lang/String;)Ljava/lang/StringBuilder;
      14: ldc           #53                 // String _np2
      16: invokevirtual #52                 // Method java/lang/StringBuilder.append:(Ljava/lang/String;)Ljava/lang/StringBuilder;
      19: invokevirtual #54                 // Method java/lang/StringBuilder.toString:()Ljava/lang/String;
      22: astore_1
      23: aload_1
      24: invokestatic  #55                 // Method org/apache/hadoop/hbase/NamespaceDescriptor.create:(Ljava/lang/String;)Lorg/apache/hadoop/hbase/NamespaceDescriptor$Builder;
      27: ldc           #57                 // String hbase.namespace.quota.maxregions
      29: ldc           #58                 // String 5
      31: invokevirtual #59                 // Method org/apache/hadoop/hbase/NamespaceDescriptor$Builder.addConfiguration:(Ljava/lang/String;Ljava/lang/String;)Lorg/apache/hadoop/hbase/NamespaceDescriptor$Builder;
      34: ldc           #60                 // String hbase.namespace.quota.maxtables
      36: ldc           #61                 // String 2
      38: invokevirtual #59                 // Method org/apache/hadoop/hbase/NamespaceDescriptor$Builder.addConfiguration:(Ljava/lang/String;Ljava/lang/String;)Lorg/apache/hadoop/hbase/NamespaceDescriptor$Builder;
      41: invokevirtual #62                 // Method org/apache/hadoop/hbase/NamespaceDescriptor$Builder.build:()Lorg/apache/hadoop/hbase/NamespaceDescriptor;
      44: astore_2
      45: getstatic     #2                  // Field ADMIN:Lorg/apache/hadoop/hbase/client/Admin;
      48: aload_2
      49: invokeinterface #63,  2           // InterfaceMethod org/apache/hadoop/hbase/client/Admin.createNamespace:(Lorg/apache/hadoop/hbase/NamespaceDescriptor;)V
      54: ldc           #64                 // String Namespace descriptor found null.
      56: getstatic     #2                  // Field ADMIN:Lorg/apache/hadoop/hbase/client/Admin;
      59: aload_1
      60: invokeinterface #65,  2           // InterfaceMethod org/apache/hadoop/hbase/client/Admin.getNamespaceDescriptor:(Ljava/lang/String;)Lorg/apache/hadoop/hbase/NamespaceDescriptor;
      65: invokestatic  #66                 // Method org/junit/Assert.assertNotNull:(Ljava/lang/String;Ljava/lang/Object;)V
      68: ldc2_w        #67                 // long 3l
      71: getstatic     #2                  // Field ADMIN:Lorg/apache/hadoop/hbase/client/Admin;
      74: invokeinterface #40,  1           // InterfaceMethod org/apache/hadoop/hbase/client/Admin.listNamespaceDescriptors:()[Lorg/apache/hadoop/hbase/NamespaceDescriptor;
      79: arraylength
      80: i2l
      81: invokestatic  #69                 // Method org/junit/Assert.assertEquals:(JJ)V
      84: new           #70                 // class org/apache/hadoop/hbase/HColumnDescriptor
      87: dup
      88: ldc           #71                 // String fam1
      90: invokespecial #72                 // Method org/apache/hadoop/hbase/HColumnDescriptor."<init>":(Ljava/lang/String;)V
      93: astore_3
      94: new           #73                 // class org/apache/hadoop/hbase/HTableDescriptor
      97: dup
      98: new           #50                 // class java/lang/StringBuilder
     101: dup
     102: invokespecial #51                 // Method java/lang/StringBuilder."<init>":()V
     105: aload_1
     106: invokevirtual #52                 // Method java/lang/StringBuilder.append:(Ljava/lang/String;)Ljava/lang/StringBuilder;
     109: bipush        58
     111: invokevirtual #75                 // Method java/lang/StringBuilder.append:(C)Ljava/lang/StringBuilder;
     114: ldc           #76                 // String table1
     116: invokevirtual #52                 // Method java/lang/StringBuilder.append:(Ljava/lang/String;)Ljava/lang/StringBuilder;
     119: invokevirtual #54                 // Method java/lang/StringBuilder.toString:()Ljava/lang/String;
     122: invokestatic  #77                 // Method org/apache/hadoop/hbase/TableName.valueOf:(Ljava/lang/String;)Lorg/apache/hadoop/hbase/TableName;
     125: invokespecial #78                 // Method org/apache/hadoop/hbase/HTableDescriptor."<init>":(Lorg/apache/hadoop/hbase/TableName;)V
     128: astore        4
     130: aload         4
     132: aload_3
     133: invokevirtual #79                 // Method org/apache/hadoop/hbase/HTableDescriptor.addFamily:(Lorg/apache/hadoop/hbase/HColumnDescriptor;)Lorg/apache/hadoop/hbase/HTableDescriptor;
     136: pop
     137: new           #73                 // class org/apache/hadoop/hbase/HTableDescriptor
     140: dup
     141: new           #50                 // class java/lang/StringBuilder
     144: dup
     145: invokespecial #51                 // Method java/lang/StringBuilder."<init>":()V
     148: aload_1
     149: invokevirtual #52                 // Method java/lang/StringBuilder.append:(Ljava/lang/String;)Ljava/lang/StringBuilder;
     152: bipush        58
     154: invokevirtual #75                 // Method java/lang/StringBuilder.append:(C)Ljava/lang/StringBuilder;
     157: ldc           #80                 // String table2
     159: invokevirtual #52                 // Method java/lang/StringBuilder.append:(Ljava/lang/String;)Ljava/lang/StringBuilder;
     162: invokevirtual #54                 // Method java/lang/StringBuilder.toString:()Ljava/lang/String;
     165: invokestatic  #77                 // Method org/apache/hadoop/hbase/TableName.valueOf:(Ljava/lang/String;)Lorg/apache/hadoop/hbase/TableName;
     168: invokespecial #78                 // Method org/apache/hadoop/hbase/HTableDescriptor."<init>":(Lorg/apache/hadoop/hbase/TableName;)V
     171: astore        5
     173: aload         5
     175: aload_3
     176: invokevirtual #79                 // Method org/apache/hadoop/hbase/HTableDescriptor.addFamily:(Lorg/apache/hadoop/hbase/HColumnDescriptor;)Lorg/apache/hadoop/hbase/HTableDescriptor;
     179: pop
     180: new           #73                 // class org/apache/hadoop/hbase/HTableDescriptor
     183: dup
     184: new           #50                 // class java/lang/StringBuilder
     187: dup
     188: invokespecial #51                 // Method java/lang/StringBuilder."<init>":()V
     191: aload_1
     192: invokevirtual #52                 // Method java/lang/StringBuilder.append:(Ljava/lang/String;)Ljava/lang/StringBuilder;
     195: bipush        58
     197: invokevirtual #75                 // Method java/lang/StringBuilder.append:(C)Ljava/lang/StringBuilder;
     200: ldc           #81                 // String table3
     202: invokevirtual #52                 // Method java/lang/StringBuilder.append:(Ljava/lang/String;)Ljava/lang/StringBuilder;
     205: invokevirtual #54                 // Method java/lang/StringBuilder.toString:()Ljava/lang/String;
     208: invokestatic  #77                 // Method org/apache/hadoop/hbase/TableName.valueOf:(Ljava/lang/String;)Lorg/apache/hadoop/hbase/TableName;
     211: invokespecial #78                 // Method org/apache/hadoop/hbase/HTableDescriptor."<init>":(Lorg/apache/hadoop/hbase/TableName;)V
     214: astore        6
     216: aload         6
     218: aload_3
     219: invokevirtual #79                 // Method org/apache/hadoop/hbase/HTableDescriptor.addFamily:(Lorg/apache/hadoop/hbase/HColumnDescriptor;)Lorg/apache/hadoop/hbase/HTableDescriptor;
     222: pop
     223: getstatic     #2                  // Field ADMIN:Lorg/apache/hadoop/hbase/client/Admin;
     226: aload         4
     228: invokeinterface #82,  2           // InterfaceMethod org/apache/hadoop/hbase/client/Admin.createTable:(Lorg/apache/hadoop/hbase/client/TableDescriptor;)V
     233: iconst_0
     234: istore        7
     236: getstatic     #2                  // Field ADMIN:Lorg/apache/hadoop/hbase/client/Admin;
     239: aload         5
     241: ldc           #83                 // String AAA
     243: invokestatic  #84                 // Method org/apache/hadoop/hbase/util/Bytes.toBytes:(Ljava/lang/String;)[B
     246: ldc           #85                 // String ZZZ
     248: invokestatic  #84                 // Method org/apache/hadoop/hbase/util/Bytes.toBytes:(Ljava/lang/String;)[B
     251: iconst_5
     252: invokeinterface #86,  5           // InterfaceMethod org/apache/hadoop/hbase/client/Admin.createTable:(Lorg/apache/hadoop/hbase/client/TableDescriptor;[B[BI)V
     257: new           #50                 // class java/lang/StringBuilder
     260: dup
     261: invokespecial #51                 // Method java/lang/StringBuilder."<init>":()V
     264: ldc           #87                 // String Constraint not violated for table
     266: invokevirtual #52                 // Method java/lang/StringBuilder.append:(Ljava/lang/String;)Ljava/lang/StringBuilder;
     269: aload         5
     271: invokevirtual #88                 // Method org/apache/hadoop/hbase/HTableDescriptor.getTableName:()Lorg/apache/hadoop/hbase/TableName;
     274: invokevirtual #89                 // Method java/lang/StringBuilder.append:(Ljava/lang/Object;)Ljava/lang/StringBuilder;
     277: invokevirtual #54                 // Method java/lang/StringBuilder.toString:()Ljava/lang/String;
     280: iload         7
     282: invokestatic  #49                 // Method org/junit/Assert.assertTrue:(Ljava/lang/String;Z)V
     285: goto          365
     288: astore        8
     290: aload         8
     292: instanceof    #91                 // class java/io/IOException
     295: invokestatic  #92                 // Method org/junit/Assert.assertTrue:(Z)V
     298: iconst_1
     299: istore        7
     301: new           #50                 // class java/lang/StringBuilder
     304: dup
     305: invokespecial #51                 // Method java/lang/StringBuilder."<init>":()V
     308: ldc           #87                 // String Constraint not violated for table
     310: invokevirtual #52                 // Method java/lang/StringBuilder.append:(Ljava/lang/String;)Ljava/lang/StringBuilder;
     313: aload         5
     315: invokevirtual #88                 // Method org/apache/hadoop/hbase/HTableDescriptor.getTableName:()Lorg/apache/hadoop/hbase/TableName;
     318: invokevirtual #89                 // Method java/lang/StringBuilder.append:(Ljava/lang/Object;)Ljava/lang/StringBuilder;
     321: invokevirtual #54                 // Method java/lang/StringBuilder.toString:()Ljava/lang/String;
     324: iload         7
     326: invokestatic  #49                 // Method org/junit/Assert.assertTrue:(Ljava/lang/String;Z)V
     329: goto          365
     332: astore        9
     334: new           #50                 // class java/lang/StringBuilder
     337: dup
     338: invokespecial #51                 // Method java/lang/StringBuilder."<init>":()V
     341: ldc           #87                 // String Constraint not violated for table
     343: invokevirtual #52                 // Method java/lang/StringBuilder.append:(Ljava/lang/String;)Ljava/lang/StringBuilder;
     346: aload         5
     348: invokevirtual #88                 // Method org/apache/hadoop/hbase/HTableDescriptor.getTableName:()Lorg/apache/hadoop/hbase/TableName;
     351: invokevirtual #89                 // Method java/lang/StringBuilder.append:(Ljava/lang/Object;)Ljava/lang/StringBuilder;
     354: invokevirtual #54                 // Method java/lang/StringBuilder.toString:()Ljava/lang/String;
     357: iload         7
     359: invokestatic  #49                 // Method org/junit/Assert.assertTrue:(Ljava/lang/String;Z)V
     362: aload         9
     364: athrow
     365: getstatic     #2                  // Field ADMIN:Lorg/apache/hadoop/hbase/client/Admin;
     368: aload         5
     370: ldc           #83                 // String AAA
     372: invokestatic  #84                 // Method org/apache/hadoop/hbase/util/Bytes.toBytes:(Ljava/lang/String;)[B
     375: ldc           #85                 // String ZZZ
     377: invokestatic  #84                 // Method org/apache/hadoop/hbase/util/Bytes.toBytes:(Ljava/lang/String;)[B
     380: iconst_4
     381: invokeinterface #86,  5           // InterfaceMethod org/apache/hadoop/hbase/client/Admin.createTable:(Lorg/apache/hadoop/hbase/client/TableDescriptor;[B[BI)V
     386: aload_0
     387: invokespecial #93                 // Method getQuotaManager:()Lorg/apache/hadoop/hbase/namespace/NamespaceAuditor;
     390: aload_1
     391: invokevirtual #94                 // Method org/apache/hadoop/hbase/namespace/NamespaceAuditor.getState:(Ljava/lang/String;)Lorg/apache/hadoop/hbase/namespace/NamespaceTableAndRegionInfo;
     394: astore        8
     396: aload         8
     398: invokestatic  #95                 // Method org/junit/Assert.assertNotNull:(Ljava/lang/Object;)V
     401: aload         8
     403: invokevirtual #96                 // Method org/apache/hadoop/hbase/namespace/NamespaceTableAndRegionInfo.getTables:()Ljava/util/Set;
     406: invokeinterface #97,  1           // InterfaceMethod java/util/Set.size:()I
     411: iconst_2
     412: if_icmpne     419
     415: iconst_1
     416: goto          420
     419: iconst_0
     420: invokestatic  #92                 // Method org/junit/Assert.assertTrue:(Z)V
     423: aload         8
     425: invokevirtual #98                 // Method org/apache/hadoop/hbase/namespace/NamespaceTableAndRegionInfo.getRegionCount:()I
     428: iconst_5
     429: if_icmpne     436
     432: iconst_1
     433: goto          437
     436: iconst_0
     437: invokestatic  #92                 // Method org/junit/Assert.assertTrue:(Z)V
     440: iconst_0
     441: istore        7
     443: getstatic     #2                  // Field ADMIN:Lorg/apache/hadoop/hbase/client/Admin;
     446: aload         6
     448: invokeinterface #82,  2           // InterfaceMethod org/apache/hadoop/hbase/client/Admin.createTable:(Lorg/apache/hadoop/hbase/client/TableDescriptor;)V
     453: new           #50                 // class java/lang/StringBuilder
     456: dup
     457: invokespecial #51                 // Method java/lang/StringBuilder."<init>":()V
     460: ldc           #87                 // String Constraint not violated for table
     462: invokevirtual #52                 // Method java/lang/StringBuilder.append:(Ljava/lang/String;)Ljava/lang/StringBuilder;
     465: aload         6
     467: invokevirtual #88                 // Method org/apache/hadoop/hbase/HTableDescriptor.getTableName:()Lorg/apache/hadoop/hbase/TableName;
     470: invokevirtual #89                 // Method java/lang/StringBuilder.append:(Ljava/lang/Object;)Ljava/lang/StringBuilder;
     473: invokevirtual #54                 // Method java/lang/StringBuilder.toString:()Ljava/lang/String;
     476: iload         7
     478: invokestatic  #49                 // Method org/junit/Assert.assertTrue:(Ljava/lang/String;Z)V
     481: goto          561
     484: astore        9
     486: aload         9
     488: instanceof    #91                 // class java/io/IOException
     491: invokestatic  #92                 // Method org/junit/Assert.assertTrue:(Z)V
     494: iconst_1
     495: istore        7
     497: new           #50                 // class java/lang/StringBuilder
     500: dup
     501: invokespecial #51                 // Method java/lang/StringBuilder."<init>":()V
     504: ldc           #87                 // String Constraint not violated for table
     506: invokevirtual #52                 // Method java/lang/StringBuilder.append:(Ljava/lang/String;)Ljava/lang/StringBuilder;
     509: aload         6
     511: invokevirtual #88                 // Method org/apache/hadoop/hbase/HTableDescriptor.getTableName:()Lorg/apache/hadoop/hbase/TableName;
     514: invokevirtual #89                 // Method java/lang/StringBuilder.append:(Ljava/lang/Object;)Ljava/lang/StringBuilder;
     517: invokevirtual #54                 // Method java/lang/StringBuilder.toString:()Ljava/lang/String;
     520: iload         7
     522: invokestatic  #49                 // Method org/junit/Assert.assertTrue:(Ljava/lang/String;Z)V
     525: goto          561
     528: astore        10
     530: new           #50                 // class java/lang/StringBuilder
     533: dup
     534: invokespecial #51                 // Method java/lang/StringBuilder."<init>":()V
     537: ldc           #87                 // String Constraint not violated for table
     539: invokevirtual #52                 // Method java/lang/StringBuilder.append:(Ljava/lang/String;)Ljava/lang/StringBuilder;
     542: aload         6
     544: invokevirtual #88                 // Method org/apache/hadoop/hbase/HTableDescriptor.getTableName:()Lorg/apache/hadoop/hbase/TableName;
     547: invokevirtual #89                 // Method java/lang/StringBuilder.append:(Ljava/lang/Object;)Ljava/lang/StringBuilder;
     550: invokevirtual #54                 // Method java/lang/StringBuilder.toString:()Ljava/lang/String;
     553: iload         7
     555: invokestatic  #49                 // Method org/junit/Assert.assertTrue:(Ljava/lang/String;Z)V
     558: aload         10
     560: athrow
     561: return
    Exception table:
       from    to  target type
         236   257   288   Class java/lang/Exception
         236   257   332   any
         288   301   332   any
         332   334   332   any
         443   453   484   Class java/lang/Exception
         443   453   528   any
         484   497   528   any
         528   530   528   any

  public void testValidQuotas() throws java.lang.Exception;
    Code:
       0: iconst_0
       1: istore_1
       2: getstatic     #6                  // Field UTIL:Lorg/apache/hadoop/hbase/HBaseTestingUtility;
       5: invokevirtual #45                 // Method org/apache/hadoop/hbase/HBaseTestingUtility.getHBaseCluster:()Lorg/apache/hadoop/hbase/MiniHBaseCluster;
       8: invokevirtual #46                 // Method org/apache/hadoop/hbase/MiniHBaseCluster.getMaster:()Lorg/apache/hadoop/hbase/master/HMaster;
      11: invokevirtual #99                 // Method org/apache/hadoop/hbase/master/HMaster.getMasterFileSystem:()Lorg/apache/hadoop/hbase/master/MasterFileSystem;
      14: invokevirtual #100                // Method org/apache/hadoop/hbase/master/MasterFileSystem.getFileSystem:()Lorg/apache/hadoop/fs/FileSystem;
      17: astore_2
      18: getstatic     #6                  // Field UTIL:Lorg/apache/hadoop/hbase/HBaseTestingUtility;
      21: invokevirtual #45                 // Method org/apache/hadoop/hbase/HBaseTestingUtility.getHBaseCluster:()Lorg/apache/hadoop/hbase/MiniHBaseCluster;
      24: invokevirtual #46                 // Method org/apache/hadoop/hbase/MiniHBaseCluster.getMaster:()Lorg/apache/hadoop/hbase/master/HMaster;
      27: invokevirtual #99                 // Method org/apache/hadoop/hbase/master/HMaster.getMasterFileSystem:()Lorg/apache/hadoop/hbase/master/MasterFileSystem;
      30: invokevirtual #101                // Method org/apache/hadoop/hbase/master/MasterFileSystem.getRootDir:()Lorg/apache/hadoop/fs/Path;
      33: astore_3
      34: new           #50                 // class java/lang/StringBuilder
      37: dup
      38: invokespecial #51                 // Method java/lang/StringBuilder."<init>":()V
      41: aload_0
      42: getfield      #5                  // Field prefix:Ljava/lang/String;
      45: invokevirtual #52                 // Method java/lang/StringBuilder.append:(Ljava/lang/String;)Ljava/lang/StringBuilder;
      48: ldc           #102                // String vq1
      50: invokevirtual #52                 // Method java/lang/StringBuilder.append:(Ljava/lang/String;)Ljava/lang/StringBuilder;
      53: invokevirtual #54                 // Method java/lang/StringBuilder.toString:()Ljava/lang/String;
      56: invokestatic  #55                 // Method org/apache/hadoop/hbase/NamespaceDescriptor.create:(Ljava/lang/String;)Lorg/apache/hadoop/hbase/NamespaceDescriptor$Builder;
      59: ldc           #57                 // String hbase.namespace.quota.maxregions
      61: ldc           #103                // String hihdufh
      63: invokevirtual #59                 // Method org/apache/hadoop/hbase/NamespaceDescriptor$Builder.addConfiguration:(Ljava/lang/String;Ljava/lang/String;)Lorg/apache/hadoop/hbase/NamespaceDescriptor$Builder;
      66: ldc           #60                 // String hbase.namespace.quota.maxtables
      68: ldc           #61                 // String 2
      70: invokevirtual #59                 // Method org/apache/hadoop/hbase/NamespaceDescriptor$Builder.addConfiguration:(Ljava/lang/String;Ljava/lang/String;)Lorg/apache/hadoop/hbase/NamespaceDescriptor$Builder;
      73: invokevirtual #62                 // Method org/apache/hadoop/hbase/NamespaceDescriptor$Builder.build:()Lorg/apache/hadoop/hbase/NamespaceDescriptor;
      76: astore        4
      78: getstatic     #2                  // Field ADMIN:Lorg/apache/hadoop/hbase/client/Admin;
      81: aload         4
      83: invokeinterface #63,  2           // InterfaceMethod org/apache/hadoop/hbase/client/Admin.createNamespace:(Lorg/apache/hadoop/hbase/NamespaceDescriptor;)V
      88: iload_1
      89: invokestatic  #92                 // Method org/junit/Assert.assertTrue:(Z)V
      92: aload_2
      93: aload_3
      94: aload         4
      96: invokevirtual #41                 // Method org/apache/hadoop/hbase/NamespaceDescriptor.getName:()Ljava/lang/String;
      99: invokestatic  #104                // Method org/apache/hadoop/hbase/util/FSUtils.getNamespaceDir:(Lorg/apache/hadoop/fs/Path;Ljava/lang/String;)Lorg/apache/hadoop/fs/Path;
     102: invokevirtual #105                // Method org/apache/hadoop/fs/FileSystem.exists:(Lorg/apache/hadoop/fs/Path;)Z
     105: invokestatic  #106                // Method org/junit/Assert.assertFalse:(Z)V
     108: goto          178
     111: astore        5
     113: getstatic     #107                // Field LOG:Lorg/slf4j/Logger;
     116: aload         5
     118: invokevirtual #108                // Method java/lang/Exception.toString:()Ljava/lang/String;
     121: aload         5
     123: invokeinterface #109,  3          // InterfaceMethod org/slf4j/Logger.warn:(Ljava/lang/String;Ljava/lang/Throwable;)V
     128: iconst_1
     129: istore_1
     130: iload_1
     131: invokestatic  #92                 // Method org/junit/Assert.assertTrue:(Z)V
     134: aload_2
     135: aload_3
     136: aload         4
     138: invokevirtual #41                 // Method org/apache/hadoop/hbase/NamespaceDescriptor.getName:()Ljava/lang/String;
     141: invokestatic  #104                // Method org/apache/hadoop/hbase/util/FSUtils.getNamespaceDir:(Lorg/apache/hadoop/fs/Path;Ljava/lang/String;)Lorg/apache/hadoop/fs/Path;
     144: invokevirtual #105                // Method org/apache/hadoop/fs/FileSystem.exists:(Lorg/apache/hadoop/fs/Path;)Z
     147: invokestatic  #106                // Method org/junit/Assert.assertFalse:(Z)V
     150: goto          178
     153: astore        6
     155: iload_1
     156: invokestatic  #92                 // Method org/junit/Assert.assertTrue:(Z)V
     159: aload_2
     160: aload_3
     161: aload         4
     163: invokevirtual #41                 // Method org/apache/hadoop/hbase/NamespaceDescriptor.getName:()Ljava/lang/String;
     166: invokestatic  #104                // Method org/apache/hadoop/hbase/util/FSUtils.getNamespaceDir:(Lorg/apache/hadoop/fs/Path;Ljava/lang/String;)Lorg/apache/hadoop/fs/Path;
     169: invokevirtual #105                // Method org/apache/hadoop/fs/FileSystem.exists:(Lorg/apache/hadoop/fs/Path;)Z
     172: invokestatic  #106                // Method org/junit/Assert.assertFalse:(Z)V
     175: aload         6
     177: athrow
     178: new           #50                 // class java/lang/StringBuilder
     181: dup
     182: invokespecial #51                 // Method java/lang/StringBuilder."<init>":()V
     185: aload_0
     186: getfield      #5                  // Field prefix:Ljava/lang/String;
     189: invokevirtual #52                 // Method java/lang/StringBuilder.append:(Ljava/lang/String;)Ljava/lang/StringBuilder;
     192: ldc           #110                // String vq2
     194: invokevirtual #52                 // Method java/lang/StringBuilder.append:(Ljava/lang/String;)Ljava/lang/StringBuilder;
     197: invokevirtual #54                 // Method java/lang/StringBuilder.toString:()Ljava/lang/String;
     200: invokestatic  #55                 // Method org/apache/hadoop/hbase/NamespaceDescriptor.create:(Ljava/lang/String;)Lorg/apache/hadoop/hbase/NamespaceDescriptor$Builder;
     203: ldc           #57                 // String hbase.namespace.quota.maxregions
     205: ldc           #111                // String -456
     207: invokevirtual #59                 // Method org/apache/hadoop/hbase/NamespaceDescriptor$Builder.addConfiguration:(Ljava/lang/String;Ljava/lang/String;)Lorg/apache/hadoop/hbase/NamespaceDescriptor$Builder;
     210: ldc           #60                 // String hbase.namespace.quota.maxtables
     212: ldc           #61                 // String 2
     214: invokevirtual #59                 // Method org/apache/hadoop/hbase/NamespaceDescriptor$Builder.addConfiguration:(Ljava/lang/String;Ljava/lang/String;)Lorg/apache/hadoop/hbase/NamespaceDescriptor$Builder;
     217: invokevirtual #62                 // Method org/apache/hadoop/hbase/NamespaceDescriptor$Builder.build:()Lorg/apache/hadoop/hbase/NamespaceDescriptor;
     220: astore        4
     222: getstatic     #2                  // Field ADMIN:Lorg/apache/hadoop/hbase/client/Admin;
     225: aload         4
     227: invokeinterface #63,  2           // InterfaceMethod org/apache/hadoop/hbase/client/Admin.createNamespace:(Lorg/apache/hadoop/hbase/NamespaceDescriptor;)V
     232: iload_1
     233: invokestatic  #92                 // Method org/junit/Assert.assertTrue:(Z)V
     236: aload_2
     237: aload_3
     238: aload         4
     240: invokevirtual #41                 // Method org/apache/hadoop/hbase/NamespaceDescriptor.getName:()Ljava/lang/String;
     243: invokestatic  #104                // Method org/apache/hadoop/hbase/util/FSUtils.getNamespaceDir:(Lorg/apache/hadoop/fs/Path;Ljava/lang/String;)Lorg/apache/hadoop/fs/Path;
     246: invokevirtual #105                // Method org/apache/hadoop/fs/FileSystem.exists:(Lorg/apache/hadoop/fs/Path;)Z
     249: invokestatic  #106                // Method org/junit/Assert.assertFalse:(Z)V
     252: goto          322
     255: astore        5
     257: getstatic     #107                // Field LOG:Lorg/slf4j/Logger;
     260: aload         5
     262: invokevirtual #108                // Method java/lang/Exception.toString:()Ljava/lang/String;
     265: aload         5
     267: invokeinterface #109,  3          // InterfaceMethod org/slf4j/Logger.warn:(Ljava/lang/String;Ljava/lang/Throwable;)V
     272: iconst_1
     273: istore_1
     274: iload_1
     275: invokestatic  #92                 // Method org/junit/Assert.assertTrue:(Z)V
     278: aload_2
     279: aload_3
     280: aload         4
     282: invokevirtual #41                 // Method org/apache/hadoop/hbase/NamespaceDescriptor.getName:()Ljava/lang/String;
     285: invokestatic  #104                // Method org/apache/hadoop/hbase/util/FSUtils.getNamespaceDir:(Lorg/apache/hadoop/fs/Path;Ljava/lang/String;)Lorg/apache/hadoop/fs/Path;
     288: invokevirtual #105                // Method org/apache/hadoop/fs/FileSystem.exists:(Lorg/apache/hadoop/fs/Path;)Z
     291: invokestatic  #106                // Method org/junit/Assert.assertFalse:(Z)V
     294: goto          322
     297: astore        7
     299: iload_1
     300: invokestatic  #92                 // Method org/junit/Assert.assertTrue:(Z)V
     303: aload_2
     304: aload_3
     305: aload         4
     307: invokevirtual #41                 // Method org/apache/hadoop/hbase/NamespaceDescriptor.getName:()Ljava/lang/String;
     310: invokestatic  #104                // Method org/apache/hadoop/hbase/util/FSUtils.getNamespaceDir:(Lorg/apache/hadoop/fs/Path;Ljava/lang/String;)Lorg/apache/hadoop/fs/Path;
     313: invokevirtual #105                // Method org/apache/hadoop/fs/FileSystem.exists:(Lorg/apache/hadoop/fs/Path;)Z
     316: invokestatic  #106                // Method org/junit/Assert.assertFalse:(Z)V
     319: aload         7
     321: athrow
     322: new           #50                 // class java/lang/StringBuilder
     325: dup
     326: invokespecial #51                 // Method java/lang/StringBuilder."<init>":()V
     329: aload_0
     330: getfield      #5                  // Field prefix:Ljava/lang/String;
     333: invokevirtual #52                 // Method java/lang/StringBuilder.append:(Ljava/lang/String;)Ljava/lang/StringBuilder;
     336: ldc           #112                // String vq3
     338: invokevirtual #52                 // Method java/lang/StringBuilder.append:(Ljava/lang/String;)Ljava/lang/StringBuilder;
     341: invokevirtual #54                 // Method java/lang/StringBuilder.toString:()Ljava/lang/String;
     344: invokestatic  #55                 // Method org/apache/hadoop/hbase/NamespaceDescriptor.create:(Ljava/lang/String;)Lorg/apache/hadoop/hbase/NamespaceDescriptor$Builder;
     347: ldc           #57                 // String hbase.namespace.quota.maxregions
     349: ldc           #113                // String 10
     351: invokevirtual #59                 // Method org/apache/hadoop/hbase/NamespaceDescriptor$Builder.addConfiguration:(Ljava/lang/String;Ljava/lang/String;)Lorg/apache/hadoop/hbase/NamespaceDescriptor$Builder;
     354: ldc           #60                 // String hbase.namespace.quota.maxtables
     356: ldc           #114                // String sciigd
     358: invokevirtual #59                 // Method org/apache/hadoop/hbase/NamespaceDescriptor$Builder.addConfiguration:(Ljava/lang/String;Ljava/lang/String;)Lorg/apache/hadoop/hbase/NamespaceDescriptor$Builder;
     361: invokevirtual #62                 // Method org/apache/hadoop/hbase/NamespaceDescriptor$Builder.build:()Lorg/apache/hadoop/hbase/NamespaceDescriptor;
     364: astore        4
     366: getstatic     #2                  // Field ADMIN:Lorg/apache/hadoop/hbase/client/Admin;
     369: aload         4
     371: invokeinterface #63,  2           // InterfaceMethod org/apache/hadoop/hbase/client/Admin.createNamespace:(Lorg/apache/hadoop/hbase/NamespaceDescriptor;)V
     376: iload_1
     377: invokestatic  #92                 // Method org/junit/Assert.assertTrue:(Z)V
     380: aload_2
     381: aload_3
     382: aload         4
     384: invokevirtual #41                 // Method org/apache/hadoop/hbase/NamespaceDescriptor.getName:()Ljava/lang/String;
     387: invokestatic  #104                // Method org/apache/hadoop/hbase/util/FSUtils.getNamespaceDir:(Lorg/apache/hadoop/fs/Path;Ljava/lang/String;)Lorg/apache/hadoop/fs/Path;
     390: invokevirtual #105                // Method org/apache/hadoop/fs/FileSystem.exists:(Lorg/apache/hadoop/fs/Path;)Z
     393: invokestatic  #106                // Method org/junit/Assert.assertFalse:(Z)V
     396: goto          466
     399: astore        5
     401: getstatic     #107                // Field LOG:Lorg/slf4j/Logger;
     404: aload         5
     406: invokevirtual #108                // Method java/lang/Exception.toString:()Ljava/lang/String;
     409: aload         5
     411: invokeinterface #109,  3          // InterfaceMethod org/slf4j/Logger.warn:(Ljava/lang/String;Ljava/lang/Throwable;)V
     416: iconst_1
     417: istore_1
     418: iload_1
     419: invokestatic  #92                 // Method org/junit/Assert.assertTrue:(Z)V
     422: aload_2
     423: aload_3
     424: aload         4
     426: invokevirtual #41                 // Method org/apache/hadoop/hbase/NamespaceDescriptor.getName:()Ljava/lang/String;
     429: invokestatic  #104                // Method org/apache/hadoop/hbase/util/FSUtils.getNamespaceDir:(Lorg/apache/hadoop/fs/Path;Ljava/lang/String;)Lorg/apache/hadoop/fs/Path;
     432: invokevirtual #105                // Method org/apache/hadoop/fs/FileSystem.exists:(Lorg/apache/hadoop/fs/Path;)Z
     435: invokestatic  #106                // Method org/junit/Assert.assertFalse:(Z)V
     438: goto          466
     441: astore        8
     443: iload_1
     444: invokestatic  #92                 // Method org/junit/Assert.assertTrue:(Z)V
     447: aload_2
     448: aload_3
     449: aload         4
     451: invokevirtual #41                 // Method org/apache/hadoop/hbase/NamespaceDescriptor.getName:()Ljava/lang/String;
     454: invokestatic  #104                // Method org/apache/hadoop/hbase/util/FSUtils.getNamespaceDir:(Lorg/apache/hadoop/fs/Path;Ljava/lang/String;)Lorg/apache/hadoop/fs/Path;
     457: invokevirtual #105                // Method org/apache/hadoop/fs/FileSystem.exists:(Lorg/apache/hadoop/fs/Path;)Z
     460: invokestatic  #106                // Method org/junit/Assert.assertFalse:(Z)V
     463: aload         8
     465: athrow
     466: new           #50                 // class java/lang/StringBuilder
     469: dup
     470: invokespecial #51                 // Method java/lang/StringBuilder."<init>":()V
     473: aload_0
     474: getfield      #5                  // Field prefix:Ljava/lang/String;
     477: invokevirtual #52                 // Method java/lang/StringBuilder.append:(Ljava/lang/String;)Ljava/lang/StringBuilder;
     480: ldc           #115                // String vq4
     482: invokevirtual #52                 // Method java/lang/StringBuilder.append:(Ljava/lang/String;)Ljava/lang/StringBuilder;
     485: invokevirtual #54                 // Method java/lang/StringBuilder.toString:()Ljava/lang/String;
     488: invokestatic  #55                 // Method org/apache/hadoop/hbase/NamespaceDescriptor.create:(Ljava/lang/String;)Lorg/apache/hadoop/hbase/NamespaceDescriptor$Builder;
     491: ldc           #57                 // String hbase.namespace.quota.maxregions
     493: ldc           #113                // String 10
     495: invokevirtual #59                 // Method org/apache/hadoop/hbase/NamespaceDescriptor$Builder.addConfiguration:(Ljava/lang/String;Ljava/lang/String;)Lorg/apache/hadoop/hbase/NamespaceDescriptor$Builder;
     498: ldc           #60                 // String hbase.namespace.quota.maxtables
     500: ldc           #116                // String -1500
     502: invokevirtual #59                 // Method org/apache/hadoop/hbase/NamespaceDescriptor$Builder.addConfiguration:(Ljava/lang/String;Ljava/lang/String;)Lorg/apache/hadoop/hbase/NamespaceDescriptor$Builder;
     505: invokevirtual #62                 // Method org/apache/hadoop/hbase/NamespaceDescriptor$Builder.build:()Lorg/apache/hadoop/hbase/NamespaceDescriptor;
     508: astore        4
     510: getstatic     #2                  // Field ADMIN:Lorg/apache/hadoop/hbase/client/Admin;
     513: aload         4
     515: invokeinterface #63,  2           // InterfaceMethod org/apache/hadoop/hbase/client/Admin.createNamespace:(Lorg/apache/hadoop/hbase/NamespaceDescriptor;)V
     520: iload_1
     521: invokestatic  #92                 // Method org/junit/Assert.assertTrue:(Z)V
     524: aload_2
     525: aload_3
     526: aload         4
     528: invokevirtual #41                 // Method org/apache/hadoop/hbase/NamespaceDescriptor.getName:()Ljava/lang/String;
     531: invokestatic  #104                // Method org/apache/hadoop/hbase/util/FSUtils.getNamespaceDir:(Lorg/apache/hadoop/fs/Path;Ljava/lang/String;)Lorg/apache/hadoop/fs/Path;
     534: invokevirtual #105                // Method org/apache/hadoop/fs/FileSystem.exists:(Lorg/apache/hadoop/fs/Path;)Z
     537: invokestatic  #106                // Method org/junit/Assert.assertFalse:(Z)V
     540: goto          610
     543: astore        5
     545: getstatic     #107                // Field LOG:Lorg/slf4j/Logger;
     548: aload         5
     550: invokevirtual #108                // Method java/lang/Exception.toString:()Ljava/lang/String;
     553: aload         5
     555: invokeinterface #109,  3          // InterfaceMethod org/slf4j/Logger.warn:(Ljava/lang/String;Ljava/lang/Throwable;)V
     560: iconst_1
     561: istore_1
     562: iload_1
     563: invokestatic  #92                 // Method org/junit/Assert.assertTrue:(Z)V
     566: aload_2
     567: aload_3
     568: aload         4
     570: invokevirtual #41                 // Method org/apache/hadoop/hbase/NamespaceDescriptor.getName:()Ljava/lang/String;
     573: invokestatic  #104                // Method org/apache/hadoop/hbase/util/FSUtils.getNamespaceDir:(Lorg/apache/hadoop/fs/Path;Ljava/lang/String;)Lorg/apache/hadoop/fs/Path;
     576: invokevirtual #105                // Method org/apache/hadoop/fs/FileSystem.exists:(Lorg/apache/hadoop/fs/Path;)Z
     579: invokestatic  #106                // Method org/junit/Assert.assertFalse:(Z)V
     582: goto          610
     585: astore        9
     587: iload_1
     588: invokestatic  #92                 // Method org/junit/Assert.assertTrue:(Z)V
     591: aload_2
     592: aload_3
     593: aload         4
     595: invokevirtual #41                 // Method org/apache/hadoop/hbase/NamespaceDescriptor.getName:()Ljava/lang/String;
     598: invokestatic  #104                // Method org/apache/hadoop/hbase/util/FSUtils.getNamespaceDir:(Lorg/apache/hadoop/fs/Path;Ljava/lang/String;)Lorg/apache/hadoop/fs/Path;
     601: invokevirtual #105                // Method org/apache/hadoop/fs/FileSystem.exists:(Lorg/apache/hadoop/fs/Path;)Z
     604: invokestatic  #106                // Method org/junit/Assert.assertFalse:(Z)V
     607: aload         9
     609: athrow
     610: return
    Exception table:
       from    to  target type
          78    88   111   Class java/lang/Exception
          78    88   153   any
         111   130   153   any
         153   155   153   any
         222   232   255   Class java/lang/Exception
         222   232   297   any
         255   274   297   any
         297   299   297   any
         366   376   399   Class java/lang/Exception
         366   376   441   any
         399   418   441   any
         441   443   441   any
         510   520   543   Class java/lang/Exception
         510   520   585   any
         543   562   585   any
         585   587   585   any

  public void testDeleteTable() throws java.lang.Exception;
    Code:
       0: new           #50                 // class java/lang/StringBuilder
       3: dup
       4: invokespecial #51                 // Method java/lang/StringBuilder."<init>":()V
       7: aload_0
       8: getfield      #5                  // Field prefix:Ljava/lang/String;
      11: invokevirtual #52                 // Method java/lang/StringBuilder.append:(Ljava/lang/String;)Ljava/lang/StringBuilder;
      14: ldc           #117                // String _dummy
      16: invokevirtual #52                 // Method java/lang/StringBuilder.append:(Ljava/lang/String;)Ljava/lang/StringBuilder;
      19: invokevirtual #54                 // Method java/lang/StringBuilder.toString:()Ljava/lang/String;
      22: astore_1
      23: aload_1
      24: invokestatic  #55                 // Method org/apache/hadoop/hbase/NamespaceDescriptor.create:(Ljava/lang/String;)Lorg/apache/hadoop/hbase/NamespaceDescriptor$Builder;
      27: ldc           #57                 // String hbase.namespace.quota.maxregions
      29: ldc           #118                // String 100
      31: invokevirtual #59                 // Method org/apache/hadoop/hbase/NamespaceDescriptor$Builder.addConfiguration:(Ljava/lang/String;Ljava/lang/String;)Lorg/apache/hadoop/hbase/NamespaceDescriptor$Builder;
      34: ldc           #60                 // String hbase.namespace.quota.maxtables
      36: ldc           #119                // String 3
      38: invokevirtual #59                 // Method org/apache/hadoop/hbase/NamespaceDescriptor$Builder.addConfiguration:(Ljava/lang/String;Ljava/lang/String;)Lorg/apache/hadoop/hbase/NamespaceDescriptor$Builder;
      41: invokevirtual #62                 // Method org/apache/hadoop/hbase/NamespaceDescriptor$Builder.build:()Lorg/apache/hadoop/hbase/NamespaceDescriptor;
      44: astore_2
      45: getstatic     #2                  // Field ADMIN:Lorg/apache/hadoop/hbase/client/Admin;
      48: aload_2
      49: invokeinterface #63,  2           // InterfaceMethod org/apache/hadoop/hbase/client/Admin.createNamespace:(Lorg/apache/hadoop/hbase/NamespaceDescriptor;)V
      54: ldc           #64                 // String Namespace descriptor found null.
      56: getstatic     #2                  // Field ADMIN:Lorg/apache/hadoop/hbase/client/Admin;
      59: aload_1
      60: invokeinterface #65,  2           // InterfaceMethod org/apache/hadoop/hbase/client/Admin.getNamespaceDescriptor:(Ljava/lang/String;)Lorg/apache/hadoop/hbase/NamespaceDescriptor;
      65: invokestatic  #66                 // Method org/junit/Assert.assertNotNull:(Ljava/lang/String;Ljava/lang/Object;)V
      68: aload_0
      69: aload_2
      70: invokevirtual #41                 // Method org/apache/hadoop/hbase/NamespaceDescriptor.getName:()Ljava/lang/String;
      73: invokespecial #1                  // Method getNamespaceState:(Ljava/lang/String;)Lorg/apache/hadoop/hbase/namespace/NamespaceTableAndRegionInfo;
      76: astore_3
      77: new           #50                 // class java/lang/StringBuilder
      80: dup
      81: invokespecial #51                 // Method java/lang/StringBuilder."<init>":()V
      84: ldc           #120                // String Namespace state found null for
      86: invokevirtual #52                 // Method java/lang/StringBuilder.append:(Ljava/lang/String;)Ljava/lang/StringBuilder;
      89: aload_1
      90: invokevirtual #52                 // Method java/lang/StringBuilder.append:(Ljava/lang/String;)Ljava/lang/StringBuilder;
      93: invokevirtual #54                 // Method java/lang/StringBuilder.toString:()Ljava/lang/String;
      96: aload_3
      97: invokestatic  #66                 // Method org/junit/Assert.assertNotNull:(Ljava/lang/String;Ljava/lang/Object;)V
     100: new           #70                 // class org/apache/hadoop/hbase/HColumnDescriptor
     103: dup
     104: ldc           #71                 // String fam1
     106: invokespecial #72                 // Method org/apache/hadoop/hbase/HColumnDescriptor."<init>":(Ljava/lang/String;)V
     109: astore        4
     111: new           #73                 // class org/apache/hadoop/hbase/HTableDescriptor
     114: dup
     115: new           #50                 // class java/lang/StringBuilder
     118: dup
     119: invokespecial #51                 // Method java/lang/StringBuilder."<init>":()V
     122: aload_1
     123: invokevirtual #52                 // Method java/lang/StringBuilder.append:(Ljava/lang/String;)Ljava/lang/StringBuilder;
     126: bipush        58
     128: invokevirtual #75                 // Method java/lang/StringBuilder.append:(C)Ljava/lang/StringBuilder;
     131: ldc           #76                 // String table1
     133: invokevirtual #52                 // Method java/lang/StringBuilder.append:(Ljava/lang/String;)Ljava/lang/StringBuilder;
     136: invokevirtual #54                 // Method java/lang/StringBuilder.toString:()Ljava/lang/String;
     139: invokestatic  #77                 // Method org/apache/hadoop/hbase/TableName.valueOf:(Ljava/lang/String;)Lorg/apache/hadoop/hbase/TableName;
     142: invokespecial #78                 // Method org/apache/hadoop/hbase/HTableDescriptor."<init>":(Lorg/apache/hadoop/hbase/TableName;)V
     145: astore        5
     147: aload         5
     149: aload         4
     151: invokevirtual #79                 // Method org/apache/hadoop/hbase/HTableDescriptor.addFamily:(Lorg/apache/hadoop/hbase/HColumnDescriptor;)Lorg/apache/hadoop/hbase/HTableDescriptor;
     154: pop
     155: new           #73                 // class org/apache/hadoop/hbase/HTableDescriptor
     158: dup
     159: new           #50                 // class java/lang/StringBuilder
     162: dup
     163: invokespecial #51                 // Method java/lang/StringBuilder."<init>":()V
     166: aload_1
     167: invokevirtual #52                 // Method java/lang/StringBuilder.append:(Ljava/lang/String;)Ljava/lang/StringBuilder;
     170: bipush        58
     172: invokevirtual #75                 // Method java/lang/StringBuilder.append:(C)Ljava/lang/StringBuilder;
     175: ldc           #80                 // String table2
     177: invokevirtual #52                 // Method java/lang/StringBuilder.append:(Ljava/lang/String;)Ljava/lang/StringBuilder;
     180: invokevirtual #54                 // Method java/lang/StringBuilder.toString:()Ljava/lang/String;
     183: invokestatic  #77                 // Method org/apache/hadoop/hbase/TableName.valueOf:(Ljava/lang/String;)Lorg/apache/hadoop/hbase/TableName;
     186: invokespecial #78                 // Method org/apache/hadoop/hbase/HTableDescriptor."<init>":(Lorg/apache/hadoop/hbase/TableName;)V
     189: astore        6
     191: aload         6
     193: aload         4
     195: invokevirtual #79                 // Method org/apache/hadoop/hbase/HTableDescriptor.addFamily:(Lorg/apache/hadoop/hbase/HColumnDescriptor;)Lorg/apache/hadoop/hbase/HTableDescriptor;
     198: pop
     199: getstatic     #2                  // Field ADMIN:Lorg/apache/hadoop/hbase/client/Admin;
     202: aload         5
     204: invokeinterface #82,  2           // InterfaceMethod org/apache/hadoop/hbase/client/Admin.createTable:(Lorg/apache/hadoop/hbase/client/TableDescriptor;)V
     209: getstatic     #2                  // Field ADMIN:Lorg/apache/hadoop/hbase/client/Admin;
     212: aload         6
     214: ldc           #83                 // String AAA
     216: invokestatic  #84                 // Method org/apache/hadoop/hbase/util/Bytes.toBytes:(Ljava/lang/String;)[B
     219: ldc           #85                 // String ZZZ
     221: invokestatic  #84                 // Method org/apache/hadoop/hbase/util/Bytes.toBytes:(Ljava/lang/String;)[B
     224: iconst_5
     225: invokeinterface #86,  5           // InterfaceMethod org/apache/hadoop/hbase/client/Admin.createTable:(Lorg/apache/hadoop/hbase/client/TableDescriptor;[B[BI)V
     230: aload_0
     231: aload_2
     232: invokevirtual #41                 // Method org/apache/hadoop/hbase/NamespaceDescriptor.getName:()Ljava/lang/String;
     235: invokespecial #1                  // Method getNamespaceState:(Ljava/lang/String;)Lorg/apache/hadoop/hbase/namespace/NamespaceTableAndRegionInfo;
     238: astore_3
     239: ldc           #121                // String Namespace state found to be null.
     241: aload_3
     242: invokestatic  #66                 // Method org/junit/Assert.assertNotNull:(Ljava/lang/String;Ljava/lang/Object;)V
     245: ldc2_w        #122                // long 2l
     248: aload_3
     249: invokevirtual #96                 // Method org/apache/hadoop/hbase/namespace/NamespaceTableAndRegionInfo.getTables:()Ljava/util/Set;
     252: invokeinterface #97,  1           // InterfaceMethod java/util/Set.size:()I
     257: i2l
     258: invokestatic  #69                 // Method org/junit/Assert.assertEquals:(JJ)V
     261: ldc2_w        #124                // long 5l
     264: aload_3
     265: aload         6
     267: invokevirtual #88                 // Method org/apache/hadoop/hbase/HTableDescriptor.getTableName:()Lorg/apache/hadoop/hbase/TableName;
     270: invokevirtual #126                // Method org/apache/hadoop/hbase/namespace/NamespaceTableAndRegionInfo.getRegionCountOfTable:(Lorg/apache/hadoop/hbase/TableName;)I
     273: i2l
     274: invokestatic  #69                 // Method org/junit/Assert.assertEquals:(JJ)V
     277: ldc2_w        #127                // long 6l
     280: aload_3
     281: invokevirtual #98                 // Method org/apache/hadoop/hbase/namespace/NamespaceTableAndRegionInfo.getRegionCount:()I
     284: i2l
     285: invokestatic  #69                 // Method org/junit/Assert.assertEquals:(JJ)V
     288: getstatic     #2                  // Field ADMIN:Lorg/apache/hadoop/hbase/client/Admin;
     291: aload         5
     293: invokevirtual #88                 // Method org/apache/hadoop/hbase/HTableDescriptor.getTableName:()Lorg/apache/hadoop/hbase/TableName;
     296: invokeinterface #38,  2           // InterfaceMethod org/apache/hadoop/hbase/client/Admin.disableTable:(Lorg/apache/hadoop/hbase/TableName;)V
     301: aload_0
     302: aload         5
     304: invokevirtual #88                 // Method org/apache/hadoop/hbase/HTableDescriptor.getTableName:()Lorg/apache/hadoop/hbase/TableName;
     307: invokespecial #39                 // Method deleteTable:(Lorg/apache/hadoop/hbase/TableName;)V
     310: aload_0
     311: aload_2
     312: invokevirtual #41                 // Method org/apache/hadoop/hbase/NamespaceDescriptor.getName:()Ljava/lang/String;
     315: invokespecial #1                  // Method getNamespaceState:(Ljava/lang/String;)Lorg/apache/hadoop/hbase/namespace/NamespaceTableAndRegionInfo;
     318: astore_3
     319: ldc           #121                // String Namespace state found to be null.
     321: aload_3
     322: invokestatic  #66                 // Method org/junit/Assert.assertNotNull:(Ljava/lang/String;Ljava/lang/Object;)V
     325: ldc2_w        #124                // long 5l
     328: aload_3
     329: invokevirtual #98                 // Method org/apache/hadoop/hbase/namespace/NamespaceTableAndRegionInfo.getRegionCount:()I
     332: i2l
     333: invokestatic  #69                 // Method org/junit/Assert.assertEquals:(JJ)V
     336: lconst_1
     337: aload_3
     338: invokevirtual #96                 // Method org/apache/hadoop/hbase/namespace/NamespaceTableAndRegionInfo.getTables:()Ljava/util/Set;
     341: invokeinterface #97,  1           // InterfaceMethod java/util/Set.size:()I
     346: i2l
     347: invokestatic  #69                 // Method org/junit/Assert.assertEquals:(JJ)V
     350: getstatic     #2                  // Field ADMIN:Lorg/apache/hadoop/hbase/client/Admin;
     353: aload         6
     355: invokevirtual #88                 // Method org/apache/hadoop/hbase/HTableDescriptor.getTableName:()Lorg/apache/hadoop/hbase/TableName;
     358: invokeinterface #38,  2           // InterfaceMethod org/apache/hadoop/hbase/client/Admin.disableTable:(Lorg/apache/hadoop/hbase/TableName;)V
     363: aload_0
     364: aload         6
     366: invokevirtual #88                 // Method org/apache/hadoop/hbase/HTableDescriptor.getTableName:()Lorg/apache/hadoop/hbase/TableName;
     369: invokespecial #39                 // Method deleteTable:(Lorg/apache/hadoop/hbase/TableName;)V
     372: getstatic     #2                  // Field ADMIN:Lorg/apache/hadoop/hbase/client/Admin;
     375: aload_1
     376: invokeinterface #43,  2           // InterfaceMethod org/apache/hadoop/hbase/client/Admin.deleteNamespace:(Ljava/lang/String;)V
     381: aload_0
     382: aload_1
     383: invokespecial #1                  // Method getNamespaceState:(Ljava/lang/String;)Lorg/apache/hadoop/hbase/namespace/NamespaceTableAndRegionInfo;
     386: astore_3
     387: ldc           #129                // String Namespace state not found to be null.
     389: aload_3
     390: invokestatic  #130                // Method org/junit/Assert.assertNull:(Ljava/lang/String;Ljava/lang/Object;)V
     393: return

  public void testRegionMerge() throws java.lang.Exception;
    Code:
       0: new           #50                 // class java/lang/StringBuilder
       3: dup
       4: invokespecial #51                 // Method java/lang/StringBuilder."<init>":()V
       7: aload_0
       8: getfield      #5                  // Field prefix:Ljava/lang/String;
      11: invokevirtual #52                 // Method java/lang/StringBuilder.append:(Ljava/lang/String;)Ljava/lang/StringBuilder;
      14: ldc           #131                // String _regiontest
      16: invokevirtual #52                 // Method java/lang/StringBuilder.append:(Ljava/lang/String;)Ljava/lang/StringBuilder;
      19: invokevirtual #54                 // Method java/lang/StringBuilder.toString:()Ljava/lang/String;
      22: astore_1
      23: iconst_3
      24: istore_2
      25: aload_1
      26: invokestatic  #55                 // Method org/apache/hadoop/hbase/NamespaceDescriptor.create:(Ljava/lang/String;)Lorg/apache/hadoop/hbase/NamespaceDescriptor$Builder;
      29: ldc           #57                 // String hbase.namespace.quota.maxregions
      31: ldc           #119                // String 3
      33: invokevirtual #59                 // Method org/apache/hadoop/hbase/NamespaceDescriptor$Builder.addConfiguration:(Ljava/lang/String;Ljava/lang/String;)Lorg/apache/hadoop/hbase/NamespaceDescriptor$Builder;
      36: ldc           #60                 // String hbase.namespace.quota.maxtables
      38: ldc           #61                 // String 2
      40: invokevirtual #59                 // Method org/apache/hadoop/hbase/NamespaceDescriptor$Builder.addConfiguration:(Ljava/lang/String;Ljava/lang/String;)Lorg/apache/hadoop/hbase/NamespaceDescriptor$Builder;
      43: invokevirtual #62                 // Method org/apache/hadoop/hbase/NamespaceDescriptor$Builder.build:()Lorg/apache/hadoop/hbase/NamespaceDescriptor;
      46: astore_3
      47: getstatic     #2                  // Field ADMIN:Lorg/apache/hadoop/hbase/client/Admin;
      50: aload_3
      51: invokeinterface #63,  2           // InterfaceMethod org/apache/hadoop/hbase/client/Admin.createNamespace:(Lorg/apache/hadoop/hbase/NamespaceDescriptor;)V
      56: new           #50                 // class java/lang/StringBuilder
      59: dup
      60: invokespecial #51                 // Method java/lang/StringBuilder."<init>":()V
      63: aload_1
      64: invokevirtual #52                 // Method java/lang/StringBuilder.append:(Ljava/lang/String;)Ljava/lang/StringBuilder;
      67: bipush        58
      69: invokevirtual #75                 // Method java/lang/StringBuilder.append:(C)Ljava/lang/StringBuilder;
      72: ldc           #80                 // String table2
      74: invokevirtual #52                 // Method java/lang/StringBuilder.append:(Ljava/lang/String;)Ljava/lang/StringBuilder;
      77: invokevirtual #54                 // Method java/lang/StringBuilder.toString:()Ljava/lang/String;
      80: invokestatic  #77                 // Method org/apache/hadoop/hbase/TableName.valueOf:(Ljava/lang/String;)Lorg/apache/hadoop/hbase/TableName;
      83: astore        4
      85: ldc           #132                // String info
      87: invokestatic  #84                 // Method org/apache/hadoop/hbase/util/Bytes.toBytes:(Ljava/lang/String;)[B
      90: astore        5
      92: new           #73                 // class org/apache/hadoop/hbase/HTableDescriptor
      95: dup
      96: aload         4
      98: invokespecial #78                 // Method org/apache/hadoop/hbase/HTableDescriptor."<init>":(Lorg/apache/hadoop/hbase/TableName;)V
     101: astore        6
     103: aload         6
     105: new           #70                 // class org/apache/hadoop/hbase/HColumnDescriptor
     108: dup
     109: aload         5
     111: invokespecial #133                // Method org/apache/hadoop/hbase/HColumnDescriptor."<init>":([B)V
     114: invokevirtual #79                 // Method org/apache/hadoop/hbase/HTableDescriptor.addFamily:(Lorg/apache/hadoop/hbase/HColumnDescriptor;)Lorg/apache/hadoop/hbase/HTableDescriptor;
     117: pop
     118: getstatic     #2                  // Field ADMIN:Lorg/apache/hadoop/hbase/client/Admin;
     121: aload         6
     123: ldc           #134                // String 0
     125: invokestatic  #84                 // Method org/apache/hadoop/hbase/util/Bytes.toBytes:(Ljava/lang/String;)[B
     128: ldc           #135                // String 9
     130: invokestatic  #84                 // Method org/apache/hadoop/hbase/util/Bytes.toBytes:(Ljava/lang/String;)[B
     133: iconst_3
     134: invokeinterface #86,  5           // InterfaceMethod org/apache/hadoop/hbase/client/Admin.createTable:(Lorg/apache/hadoop/hbase/client/TableDescriptor;[B[BI)V
     139: getstatic     #6                  // Field UTIL:Lorg/apache/hadoop/hbase/HBaseTestingUtility;
     142: invokevirtual #7                  // Method org/apache/hadoop/hbase/HBaseTestingUtility.getConfiguration:()Lorg/apache/hadoop/conf/Configuration;
     145: invokestatic  #136                // Method org/apache/hadoop/hbase/client/ConnectionFactory.createConnection:(Lorg/apache/hadoop/conf/Configuration;)Lorg/apache/hadoop/hbase/client/Connection;
     148: astore        7
     150: aload         7
     152: aload         4
     154: invokeinterface #137,  2          // InterfaceMethod org/apache/hadoop/hbase/client/Connection.getTable:(Lorg/apache/hadoop/hbase/TableName;)Lorg/apache/hadoop/hbase/client/Table;
     159: astore        8
     161: aconst_null
     162: astore        9
     164: getstatic     #6                  // Field UTIL:Lorg/apache/hadoop/hbase/HBaseTestingUtility;
     167: aload         8
     169: ldc           #132                // String info
     171: invokestatic  #84                 // Method org/apache/hadoop/hbase/util/Bytes.toBytes:(Ljava/lang/String;)[B
     174: sipush        1000
     177: sipush        1999
     180: invokevirtual #138                // Method org/apache/hadoop/hbase/HBaseTestingUtility.loadNumericRows:(Lorg/apache/hadoop/hbase/client/Table;[BII)V
     183: aload         8
     185: ifnull        278
     188: aload         9
     190: ifnull        215
     193: aload         8
     195: invokeinterface #139,  1          // InterfaceMethod org/apache/hadoop/hbase/client/Table.close:()V
     200: goto          278
     203: astore        10
     205: aload         9
     207: aload         10
     209: invokevirtual #141                // Method java/lang/Throwable.addSuppressed:(Ljava/lang/Throwable;)V
     212: goto          278
     215: aload         8
     217: invokeinterface #139,  1          // InterfaceMethod org/apache/hadoop/hbase/client/Table.close:()V
     222: goto          278
     225: astore        10
     227: aload         10
     229: astore        9
     231: aload         10
     233: athrow
     234: astore        11
     236: aload         8
     238: ifnull        275
     241: aload         9
     243: ifnull        268
     246: aload         8
     248: invokeinterface #139,  1          // InterfaceMethod org/apache/hadoop/hbase/client/Table.close:()V
     253: goto          275
     256: astore        12
     258: aload         9
     260: aload         12
     262: invokevirtual #141                // Method java/lang/Throwable.addSuppressed:(Ljava/lang/Throwable;)V
     265: goto          275
     268: aload         8
     270: invokeinterface #139,  1          // InterfaceMethod org/apache/hadoop/hbase/client/Table.close:()V
     275: aload         11
     277: athrow
     278: getstatic     #2                  // Field ADMIN:Lorg/apache/hadoop/hbase/client/Admin;
     281: aload         4
     283: invokeinterface #142,  2          // InterfaceMethod org/apache/hadoop/hbase/client/Admin.flush:(Lorg/apache/hadoop/hbase/TableName;)V
     288: getstatic     #2                  // Field ADMIN:Lorg/apache/hadoop/hbase/client/Admin;
     291: aload         4
     293: invokeinterface #143,  2          // InterfaceMethod org/apache/hadoop/hbase/client/Admin.getRegions:(Lorg/apache/hadoop/hbase/TableName;)Ljava/util/List;
     298: astore        8
     300: ldc2_w        #67                 // long 3l
     303: aload         8
     305: invokeinterface #144,  1          // InterfaceMethod java/util/List.size:()I
     310: i2l
     311: invokestatic  #69                 // Method org/junit/Assert.assertEquals:(JJ)V
     314: aload         8
     316: getstatic     #145                // Field org/apache/hadoop/hbase/client/RegionInfo.COMPARATOR:Ljava/util/Comparator;
     319: invokestatic  #146                // Method java/util/Collections.sort:(Ljava/util/List;Ljava/util/Comparator;)V
     322: getstatic     #2                  // Field ADMIN:Lorg/apache/hadoop/hbase/client/Admin;
     325: aload         8
     327: iconst_0
     328: invokeinterface #147,  2          // InterfaceMethod java/util/List.get:(I)Ljava/lang/Object;
     333: checkcast     #148                // class org/apache/hadoop/hbase/client/RegionInfo
     336: invokeinterface #149,  1          // InterfaceMethod org/apache/hadoop/hbase/client/RegionInfo.getEncodedNameAsBytes:()[B
     341: aload         8
     343: iconst_1
     344: invokeinterface #147,  2          // InterfaceMethod java/util/List.get:(I)Ljava/lang/Object;
     349: checkcast     #148                // class org/apache/hadoop/hbase/client/RegionInfo
     352: invokeinterface #149,  1          // InterfaceMethod org/apache/hadoop/hbase/client/RegionInfo.getEncodedNameAsBytes:()[B
     357: iconst_0
     358: invokeinterface #150,  4          // InterfaceMethod org/apache/hadoop/hbase/client/Admin.mergeRegionsAsync:([B[BZ)Ljava/util/concurrent/Future;
     363: astore        9
     365: aload         9
     367: ldc2_w        #151                // long 10l
     370: getstatic     #153                // Field java/util/concurrent/TimeUnit.SECONDS:Ljava/util/concurrent/TimeUnit;
     373: invokeinterface #154,  4          // InterfaceMethod java/util/concurrent/Future.get:(JLjava/util/concurrent/TimeUnit;)Ljava/lang/Object;
     378: pop
     379: getstatic     #2                  // Field ADMIN:Lorg/apache/hadoop/hbase/client/Admin;
     382: aload         4
     384: invokeinterface #143,  2          // InterfaceMethod org/apache/hadoop/hbase/client/Admin.getRegions:(Lorg/apache/hadoop/hbase/TableName;)Ljava/util/List;
     389: astore        8
     391: ldc2_w        #122                // long 2l
     394: aload         8
     396: invokeinterface #144,  1          // InterfaceMethod java/util/List.size:()I
     401: i2l
     402: invokestatic  #69                 // Method org/junit/Assert.assertEquals:(JJ)V
     405: aload         8
     407: getstatic     #145                // Field org/apache/hadoop/hbase/client/RegionInfo.COMPARATOR:Ljava/util/Comparator;
     410: invokestatic  #146                // Method java/util/Collections.sort:(Ljava/util/List;Ljava/util/Comparator;)V
     413: ldc           #119                // String 3
     415: invokestatic  #84                 // Method org/apache/hadoop/hbase/util/Bytes.toBytes:(Ljava/lang/String;)[B
     418: astore        10
     420: getstatic     #6                  // Field UTIL:Lorg/apache/hadoop/hbase/HBaseTestingUtility;
     423: invokevirtual #155                // Method org/apache/hadoop/hbase/HBaseTestingUtility.getMiniHBaseCluster:()Lorg/apache/hadoop/hbase/MiniHBaseCluster;
     426: aload         4
     428: invokevirtual #156                // Method org/apache/hadoop/hbase/MiniHBaseCluster.getRegions:(Lorg/apache/hadoop/hbase/TableName;)Ljava/util/List;
     431: invokeinterface #157,  1          // InterfaceMethod java/util/List.stream:()Ljava/util/stream/Stream;
     436: aload         10
     438: invokedynamic #158,  0            // InvokeDynamic #0:test:([B)Ljava/util/function/Predicate;
     443: invokeinterface #159,  2          // InterfaceMethod java/util/stream/Stream.filter:(Ljava/util/function/Predicate;)Ljava/util/stream/Stream;
     448: invokeinterface #160,  1          // InterfaceMethod java/util/stream/Stream.findFirst:()Ljava/util/Optional;
     453: invokevirtual #161                // Method java/util/Optional.get:()Ljava/lang/Object;
     456: checkcast     #162                // class org/apache/hadoop/hbase/regionserver/HRegion
     459: astore        11
     461: aload         11
     463: iconst_1
     464: invokevirtual #163                // Method org/apache/hadoop/hbase/regionserver/HRegion.compact:(Z)V
     467: getstatic     #6                  // Field UTIL:Lorg/apache/hadoop/hbase/HBaseTestingUtility;
     470: ldc2_w        #164                // long 30000l
     473: new           #166                // class org/apache/hadoop/hbase/namespace/TestNamespaceAuditor$1
     476: dup
     477: aload_0
     478: aload         11
     480: invokespecial #167                // Method org/apache/hadoop/hbase/namespace/TestNamespaceAuditor$1."<init>":(Lorg/apache/hadoop/hbase/namespace/TestNamespaceAuditor;Lorg/apache/hadoop/hbase/regionserver/HRegion;)V
     483: invokevirtual #168                // Method org/apache/hadoop/hbase/HBaseTestingUtility.waitFor:(JLorg/apache/hadoop/hbase/Waiter$Predicate;)J
     486: pop2
     487: aload         11
     489: invokevirtual #169                // Method org/apache/hadoop/hbase/regionserver/HRegion.getStores:()Ljava/util/List;
     492: invokeinterface #157,  1          // InterfaceMethod java/util/List.stream:()Ljava/util/stream/Stream;
     497: invokedynamic #170,  0            // InvokeDynamic #1:accept:()Ljava/util/function/Consumer;
     502: invokeinterface #171,  2          // InterfaceMethod java/util/stream/Stream.forEach:(Ljava/util/function/Consumer;)V
     507: getstatic     #6                  // Field UTIL:Lorg/apache/hadoop/hbase/HBaseTestingUtility;
     510: ldc2_w        #172                // long 10000l
     513: aload         11
     515: dup
     516: invokevirtual #174                // Method java/lang/Object.getClass:()Ljava/lang/Class;
     519: pop
     520: invokedynamic #175,  0            // InvokeDynamic #2:evaluate:(Lorg/apache/hadoop/hbase/regionserver/HRegion;)Lorg/apache/hadoop/hbase/Waiter$Predicate;
     525: invokevirtual #168                // Method org/apache/hadoop/hbase/HBaseTestingUtility.waitFor:(JLorg/apache/hadoop/hbase/Waiter$Predicate;)J
     528: pop2
     529: getstatic     #2                  // Field ADMIN:Lorg/apache/hadoop/hbase/client/Admin;
     532: aload         11
     534: invokevirtual #176                // Method org/apache/hadoop/hbase/regionserver/HRegion.getRegionInfo:()Lorg/apache/hadoop/hbase/client/RegionInfo;
     537: invokeinterface #177,  1          // InterfaceMethod org/apache/hadoop/hbase/client/RegionInfo.getRegionName:()[B
     542: aload         10
     544: invokeinterface #178,  3          // InterfaceMethod org/apache/hadoop/hbase/client/Admin.splitRegionAsync:([B[B)Ljava/util/concurrent/Future;
     549: ldc2_w        #151                // long 10l
     552: getstatic     #153                // Field java/util/concurrent/TimeUnit.SECONDS:Ljava/util/concurrent/TimeUnit;
     555: invokeinterface #154,  4          // InterfaceMethod java/util/concurrent/Future.get:(JLjava/util/concurrent/TimeUnit;)Ljava/lang/Object;
     560: pop
     561: getstatic     #2                  // Field ADMIN:Lorg/apache/hadoop/hbase/client/Admin;
     564: aload         4
     566: invokeinterface #143,  2          // InterfaceMethod org/apache/hadoop/hbase/client/Admin.getRegions:(Lorg/apache/hadoop/hbase/TableName;)Ljava/util/List;
     571: astore        8
     573: ldc2_w        #67                 // long 3l
     576: aload         8
     578: invokeinterface #144,  1          // InterfaceMethod java/util/List.size:()I
     583: i2l
     584: invokestatic  #69                 // Method org/junit/Assert.assertEquals:(JJ)V
     587: aload         8
     589: getstatic     #145                // Field org/apache/hadoop/hbase/client/RegionInfo.COMPARATOR:Ljava/util/Comparator;
     592: invokestatic  #146                // Method java/util/Collections.sort:(Ljava/util/List;Ljava/util/Comparator;)V
     595: getstatic     #6                  // Field UTIL:Lorg/apache/hadoop/hbase/HBaseTestingUtility;
     598: invokevirtual #45                 // Method org/apache/hadoop/hbase/HBaseTestingUtility.getHBaseCluster:()Lorg/apache/hadoop/hbase/MiniHBaseCluster;
     601: astore        12
     603: aload         12
     605: invokevirtual #46                 // Method org/apache/hadoop/hbase/MiniHBaseCluster.getMaster:()Lorg/apache/hadoop/hbase/master/HMaster;
     608: invokevirtual #179                // Method org/apache/hadoop/hbase/master/HMaster.getMasterCoprocessorHost:()Lorg/apache/hadoop/hbase/master/MasterCoprocessorHost;
     611: astore        13
     613: aload         13
     615: ldc           #16                 // class org/apache/hadoop/hbase/namespace/TestNamespaceAuditor$CPMasterObserver
     617: invokevirtual #180                // Method org/apache/hadoop/hbase/master/MasterCoprocessorHost.findCoprocessor:(Ljava/lang/Class;)Lorg/apache/hadoop/hbase/Coprocessor;
     620: astore        14
     622: aload         14
     624: checkcast     #16                 // class org/apache/hadoop/hbase/namespace/TestNamespaceAuditor$CPMasterObserver
     627: astore        15
     629: aload         15
     631: iconst_1
     632: invokevirtual #181                // Method org/apache/hadoop/hbase/namespace/TestNamespaceAuditor$CPMasterObserver.failMerge:(Z)V
     635: getstatic     #2                  // Field ADMIN:Lorg/apache/hadoop/hbase/client/Admin;
     638: aload         8
     640: iconst_1
     641: invokeinterface #147,  2          // InterfaceMethod java/util/List.get:(I)Ljava/lang/Object;
     646: checkcast     #148                // class org/apache/hadoop/hbase/client/RegionInfo
     649: invokeinterface #149,  1          // InterfaceMethod org/apache/hadoop/hbase/client/RegionInfo.getEncodedNameAsBytes:()[B
     654: aload         8
     656: iconst_2
     657: invokeinterface #147,  2          // InterfaceMethod java/util/List.get:(I)Ljava/lang/Object;
     662: checkcast     #148                // class org/apache/hadoop/hbase/client/RegionInfo
     665: invokeinterface #149,  1          // InterfaceMethod org/apache/hadoop/hbase/client/RegionInfo.getEncodedNameAsBytes:()[B
     670: iconst_0
     671: invokeinterface #150,  4          // InterfaceMethod org/apache/hadoop/hbase/client/Admin.mergeRegionsAsync:([B[BZ)Ljava/util/concurrent/Future;
     676: astore        9
     678: aload         9
     680: ldc2_w        #151                // long 10l
     683: getstatic     #153                // Field java/util/concurrent/TimeUnit.SECONDS:Ljava/util/concurrent/TimeUnit;
     686: invokeinterface #154,  4          // InterfaceMethod java/util/concurrent/Future.get:(JLjava/util/concurrent/TimeUnit;)Ljava/lang/Object;
     691: pop
     692: ldc           #182                // String Merge was supposed to fail!
     694: invokestatic  #183                // Method org/junit/Assert.fail:(Ljava/lang/String;)V
     697: goto          702
     700: astore        16
     702: getstatic     #2                  // Field ADMIN:Lorg/apache/hadoop/hbase/client/Admin;
     705: aload         4
     707: invokeinterface #143,  2          // InterfaceMethod org/apache/hadoop/hbase/client/Admin.getRegions:(Lorg/apache/hadoop/hbase/TableName;)Ljava/util/List;
     712: astore        8
     714: ldc2_w        #67                 // long 3l
     717: aload         8
     719: invokeinterface #144,  1          // InterfaceMethod java/util/List.size:()I
     724: i2l
     725: invokestatic  #69                 // Method org/junit/Assert.assertEquals:(JJ)V
     728: aload         8
     730: getstatic     #145                // Field org/apache/hadoop/hbase/client/RegionInfo.COMPARATOR:Ljava/util/Comparator;
     733: invokestatic  #146                // Method java/util/Collections.sort:(Ljava/util/List;Ljava/util/Comparator;)V
     736: getstatic     #2                  // Field ADMIN:Lorg/apache/hadoop/hbase/client/Admin;
     739: aload         4
     741: ldc           #185                // String 6
     743: invokestatic  #84                 // Method org/apache/hadoop/hbase/util/Bytes.toBytes:(Ljava/lang/String;)[B
     746: invokeinterface #186,  3          // InterfaceMethod org/apache/hadoop/hbase/client/Admin.split:(Lorg/apache/hadoop/hbase/TableName;[B)V
     751: invokestatic  #187                // Method org/junit/Assert.fail:()V
     754: goto          759
     757: astore        16
     759: ldc2_w        #189                // long 2000l
     762: invokestatic  #191                // Method java/lang/Thread.sleep:(J)V
     765: ldc2_w        #67                 // long 3l
     768: getstatic     #2                  // Field ADMIN:Lorg/apache/hadoop/hbase/client/Admin;
     771: aload         4
     773: invokeinterface #143,  2          // InterfaceMethod org/apache/hadoop/hbase/client/Admin.getRegions:(Lorg/apache/hadoop/hbase/TableName;)Ljava/util/List;
     778: invokeinterface #144,  1          // InterfaceMethod java/util/List.size:()I
     783: i2l
     784: invokestatic  #69                 // Method org/junit/Assert.assertEquals:(JJ)V
     787: return
    Exception table:
       from    to  target type
         193   200   203   Class java/lang/Throwable
         164   183   225   Class java/lang/Throwable
         164   183   234   any
         246   253   256   Class java/lang/Throwable
         225   236   234   any
         678   697   700   Class java/util/concurrent/ExecutionException
         736   754   757   Class org/apache/hadoop/hbase/client/DoNotRetryRegionException

  public void testRecreateTableWithSameNameAfterFirstTimeFailure() throws java.lang.Exception;
    Code:
       0: new           #50                 // class java/lang/StringBuilder
       3: dup
       4: invokespecial #51                 // Method java/lang/StringBuilder."<init>":()V
       7: aload_0
       8: getfield      #5                  // Field prefix:Ljava/lang/String;
      11: invokevirtual #52                 // Method java/lang/StringBuilder.append:(Ljava/lang/String;)Ljava/lang/StringBuilder;
      14: ldc           #192                // String _testRecreateTable
      16: invokevirtual #52                 // Method java/lang/StringBuilder.append:(Ljava/lang/String;)Ljava/lang/StringBuilder;
      19: invokevirtual #54                 // Method java/lang/StringBuilder.toString:()Ljava/lang/String;
      22: astore_1
      23: aload_1
      24: invokestatic  #55                 // Method org/apache/hadoop/hbase/NamespaceDescriptor.create:(Ljava/lang/String;)Lorg/apache/hadoop/hbase/NamespaceDescriptor$Builder;
      27: ldc           #57                 // String hbase.namespace.quota.maxregions
      29: ldc           #193                // String 20
      31: invokevirtual #59                 // Method org/apache/hadoop/hbase/NamespaceDescriptor$Builder.addConfiguration:(Ljava/lang/String;Ljava/lang/String;)Lorg/apache/hadoop/hbase/NamespaceDescriptor$Builder;
      34: ldc           #60                 // String hbase.namespace.quota.maxtables
      36: ldc           #194                // String 1
      38: invokevirtual #59                 // Method org/apache/hadoop/hbase/NamespaceDescriptor$Builder.addConfiguration:(Ljava/lang/String;Ljava/lang/String;)Lorg/apache/hadoop/hbase/NamespaceDescriptor$Builder;
      41: invokevirtual #62                 // Method org/apache/hadoop/hbase/NamespaceDescriptor$Builder.build:()Lorg/apache/hadoop/hbase/NamespaceDescriptor;
      44: astore_2
      45: getstatic     #2                  // Field ADMIN:Lorg/apache/hadoop/hbase/client/Admin;
      48: aload_2
      49: invokeinterface #63,  2           // InterfaceMethod org/apache/hadoop/hbase/client/Admin.createNamespace:(Lorg/apache/hadoop/hbase/NamespaceDescriptor;)V
      54: new           #50                 // class java/lang/StringBuilder
      57: dup
      58: invokespecial #51                 // Method java/lang/StringBuilder."<init>":()V
      61: aload_1
      62: invokevirtual #52                 // Method java/lang/StringBuilder.append:(Ljava/lang/String;)Ljava/lang/StringBuilder;
      65: bipush        58
      67: invokevirtual #75                 // Method java/lang/StringBuilder.append:(C)Ljava/lang/StringBuilder;
      70: ldc           #76                 // String table1
      72: invokevirtual #52                 // Method java/lang/StringBuilder.append:(Ljava/lang/String;)Ljava/lang/StringBuilder;
      75: invokevirtual #54                 // Method java/lang/StringBuilder.toString:()Ljava/lang/String;
      78: invokestatic  #77                 // Method org/apache/hadoop/hbase/TableName.valueOf:(Ljava/lang/String;)Lorg/apache/hadoop/hbase/TableName;
      81: astore_3
      82: ldc           #132                // String info
      84: invokestatic  #84                 // Method org/apache/hadoop/hbase/util/Bytes.toBytes:(Ljava/lang/String;)[B
      87: astore        4
      89: new           #73                 // class org/apache/hadoop/hbase/HTableDescriptor
      92: dup
      93: aload_3
      94: invokespecial #78                 // Method org/apache/hadoop/hbase/HTableDescriptor."<init>":(Lorg/apache/hadoop/hbase/TableName;)V
      97: astore        5
      99: aload         5
     101: new           #70                 // class org/apache/hadoop/hbase/HColumnDescriptor
     104: dup
     105: aload         4
     107: invokespecial #133                // Method org/apache/hadoop/hbase/HColumnDescriptor."<init>":([B)V
     110: invokevirtual #79                 // Method org/apache/hadoop/hbase/HTableDescriptor.addFamily:(Lorg/apache/hadoop/hbase/HColumnDescriptor;)Lorg/apache/hadoop/hbase/HTableDescriptor;
     113: pop
     114: iconst_1
     115: putstatic     #195                // Field org/apache/hadoop/hbase/namespace/TestNamespaceAuditor$MasterSyncObserver.throwExceptionInPreCreateTableAction:Z
     118: getstatic     #2                  // Field ADMIN:Lorg/apache/hadoop/hbase/client/Admin;
     121: aload         5
     123: invokeinterface #82,  2           // InterfaceMethod org/apache/hadoop/hbase/client/Admin.createTable:(Lorg/apache/hadoop/hbase/client/TableDescriptor;)V
     128: new           #50                 // class java/lang/StringBuilder
     131: dup
     132: invokespecial #51                 // Method java/lang/StringBuilder."<init>":()V
     135: ldc           #196                // String Table
     137: invokevirtual #52                 // Method java/lang/StringBuilder.append:(Ljava/lang/String;)Ljava/lang/StringBuilder;
     140: aload_3
     141: invokevirtual #197                // Method org/apache/hadoop/hbase/TableName.toString:()Ljava/lang/String;
     144: invokevirtual #52                 // Method java/lang/StringBuilder.append:(Ljava/lang/String;)Ljava/lang/StringBuilder;
     147: ldc           #198                // String creation should fail.
     149: invokevirtual #52                 // Method java/lang/StringBuilder.append:(Ljava/lang/String;)Ljava/lang/StringBuilder;
     152: invokevirtual #54                 // Method java/lang/StringBuilder.toString:()Ljava/lang/String;
     155: invokestatic  #183                // Method org/junit/Assert.fail:(Ljava/lang/String;)V
     158: goto          178
     161: astore        6
     163: getstatic     #107                // Field LOG:Lorg/slf4j/Logger;
     166: aload         6
     168: invokevirtual #108                // Method java/lang/Exception.toString:()Ljava/lang/String;
     171: aload         6
     173: invokeinterface #199,  3          // InterfaceMethod org/slf4j/Logger.error:(Ljava/lang/String;Ljava/lang/Throwable;)V
     178: getstatic     #2                  // Field ADMIN:Lorg/apache/hadoop/hbase/client/Admin;
     181: aload_3
     182: invokeinterface #200,  2          // InterfaceMethod org/apache/hadoop/hbase/client/Admin.tableExists:(Lorg/apache/hadoop/hbase/TableName;)Z
     187: invokestatic  #106                // Method org/junit/Assert.assertFalse:(Z)V
     190: aload_0
     191: aload_1
     192: invokespecial #1                  // Method getNamespaceState:(Ljava/lang/String;)Lorg/apache/hadoop/hbase/namespace/NamespaceTableAndRegionInfo;
     195: astore        6
     197: ldc           #201                // String First table creation failed in namespace so number of tables in namespace should be 0.
     199: lconst_0
     200: aload         6
     202: invokevirtual #96                 // Method org/apache/hadoop/hbase/namespace/NamespaceTableAndRegionInfo.getTables:()Ljava/util/Set;
     205: invokeinterface #97,  1           // InterfaceMethod java/util/Set.size:()I
     210: i2l
     211: invokestatic  #202                // Method org/junit/Assert.assertEquals:(Ljava/lang/String;JJ)V
     214: iconst_0
     215: putstatic     #195                // Field org/apache/hadoop/hbase/namespace/TestNamespaceAuditor$MasterSyncObserver.throwExceptionInPreCreateTableAction:Z
     218: getstatic     #2                  // Field ADMIN:Lorg/apache/hadoop/hbase/client/Admin;
     221: aload         5
     223: invokeinterface #82,  2           // InterfaceMethod org/apache/hadoop/hbase/client/Admin.createTable:(Lorg/apache/hadoop/hbase/client/TableDescriptor;)V
     228: goto          278
     231: astore        7
     233: new           #50                 // class java/lang/StringBuilder
     236: dup
     237: invokespecial #51                 // Method java/lang/StringBuilder."<init>":()V
     240: ldc           #196                // String Table
     242: invokevirtual #52                 // Method java/lang/StringBuilder.append:(Ljava/lang/String;)Ljava/lang/StringBuilder;
     245: aload_3
     246: invokevirtual #197                // Method org/apache/hadoop/hbase/TableName.toString:()Ljava/lang/String;
     249: invokevirtual #52                 // Method java/lang/StringBuilder.append:(Ljava/lang/String;)Ljava/lang/StringBuilder;
     252: ldc           #203                // String creation should succeed.
     254: invokevirtual #52                 // Method java/lang/StringBuilder.append:(Ljava/lang/String;)Ljava/lang/StringBuilder;
     257: invokevirtual #54                 // Method java/lang/StringBuilder.toString:()Ljava/lang/String;
     260: invokestatic  #183                // Method org/junit/Assert.fail:(Ljava/lang/String;)V
     263: getstatic     #107                // Field LOG:Lorg/slf4j/Logger;
     266: aload         7
     268: invokevirtual #108                // Method java/lang/Exception.toString:()Ljava/lang/String;
     271: aload         7
     273: invokeinterface #199,  3          // InterfaceMethod org/slf4j/Logger.error:(Ljava/lang/String;Ljava/lang/Throwable;)V
     278: getstatic     #2                  // Field ADMIN:Lorg/apache/hadoop/hbase/client/Admin;
     281: aload_3
     282: invokeinterface #200,  2          // InterfaceMethod org/apache/hadoop/hbase/client/Admin.tableExists:(Lorg/apache/hadoop/hbase/TableName;)Z
     287: invokestatic  #92                 // Method org/junit/Assert.assertTrue:(Z)V
     290: aload_0
     291: aload_1
     292: invokespecial #1                  // Method getNamespaceState:(Ljava/lang/String;)Lorg/apache/hadoop/hbase/namespace/NamespaceTableAndRegionInfo;
     295: astore        6
     297: ldc           #204                // String First table was created successfully so table size in namespace should be one now.
     299: lconst_1
     300: aload         6
     302: invokevirtual #96                 // Method org/apache/hadoop/hbase/namespace/NamespaceTableAndRegionInfo.getTables:()Ljava/util/Set;
     305: invokeinterface #97,  1           // InterfaceMethod java/util/Set.size:()I
     310: i2l
     311: invokestatic  #202                // Method org/junit/Assert.assertEquals:(Ljava/lang/String;JJ)V
     314: iconst_0
     315: putstatic     #195                // Field org/apache/hadoop/hbase/namespace/TestNamespaceAuditor$MasterSyncObserver.throwExceptionInPreCreateTableAction:Z
     318: getstatic     #2                  // Field ADMIN:Lorg/apache/hadoop/hbase/client/Admin;
     321: aload_3
     322: invokeinterface #200,  2          // InterfaceMethod org/apache/hadoop/hbase/client/Admin.tableExists:(Lorg/apache/hadoop/hbase/TableName;)Z
     327: ifeq          344
     330: getstatic     #2                  // Field ADMIN:Lorg/apache/hadoop/hbase/client/Admin;
     333: aload_3
     334: invokeinterface #38,  2           // InterfaceMethod org/apache/hadoop/hbase/client/Admin.disableTable:(Lorg/apache/hadoop/hbase/TableName;)V
     339: aload_0
     340: aload_3
     341: invokespecial #39                 // Method deleteTable:(Lorg/apache/hadoop/hbase/TableName;)V
     344: getstatic     #2                  // Field ADMIN:Lorg/apache/hadoop/hbase/client/Admin;
     347: aload_1
     348: invokeinterface #43,  2           // InterfaceMethod org/apache/hadoop/hbase/client/Admin.deleteNamespace:(Ljava/lang/String;)V
     353: goto          400
     356: astore        8
     358: iconst_0
     359: putstatic     #195                // Field org/apache/hadoop/hbase/namespace/TestNamespaceAuditor$MasterSyncObserver.throwExceptionInPreCreateTableAction:Z
     362: getstatic     #2                  // Field ADMIN:Lorg/apache/hadoop/hbase/client/Admin;
     365: aload_3
     366: invokeinterface #200,  2          // InterfaceMethod org/apache/hadoop/hbase/client/Admin.tableExists:(Lorg/apache/hadoop/hbase/TableName;)Z
     371: ifeq          388
     374: getstatic     #2                  // Field ADMIN:Lorg/apache/hadoop/hbase/client/Admin;
     377: aload_3
     378: invokeinterface #38,  2           // InterfaceMethod org/apache/hadoop/hbase/client/Admin.disableTable:(Lorg/apache/hadoop/hbase/TableName;)V
     383: aload_0
     384: aload_3
     385: invokespecial #39                 // Method deleteTable:(Lorg/apache/hadoop/hbase/TableName;)V
     388: getstatic     #2                  // Field ADMIN:Lorg/apache/hadoop/hbase/client/Admin;
     391: aload_1
     392: invokeinterface #43,  2           // InterfaceMethod org/apache/hadoop/hbase/client/Admin.deleteNamespace:(Ljava/lang/String;)V
     397: aload         8
     399: athrow
     400: return
    Exception table:
       from    to  target type
         118   158   161   Class java/lang/Exception
         218   228   231   Class java/lang/Exception
         118   314   356   any
         356   358   356   any

  byte[] getSplitKey(byte[], byte[]);
    Code:
       0: aload_1
       1: invokestatic  #205                // Method org/apache/hadoop/hbase/util/Bytes.toString:([B)Ljava/lang/String;
       4: astore_3
       5: aload_3
       6: invokestatic  #206                // Method org/apache/commons/lang3/StringUtils.isBlank:(Ljava/lang/CharSequence;)Z
       9: ifeq          26
      12: aload_2
      13: invokestatic  #205                // Method org/apache/hadoop/hbase/util/Bytes.toString:([B)Ljava/lang/String;
      16: invokestatic  #207                // Method java/lang/Integer.parseInt:(Ljava/lang/String;)I
      19: iconst_2
      20: idiv
      21: istore        4
      23: goto          38
      26: aload_3
      27: invokestatic  #207                // Method java/lang/Integer.parseInt:(Ljava/lang/String;)I
      30: i2d
      31: ldc2_w        #208                // double 1.5d
      34: dmul
      35: d2i
      36: istore        4
      38: new           #50                 // class java/lang/StringBuilder
      41: dup
      42: invokespecial #51                 // Method java/lang/StringBuilder."<init>":()V
      45: ldc           #210                // String
      47: invokevirtual #52                 // Method java/lang/StringBuilder.append:(Ljava/lang/String;)Ljava/lang/StringBuilder;
      50: iload         4
      52: invokevirtual #211                // Method java/lang/StringBuilder.append:(I)Ljava/lang/StringBuilder;
      55: invokevirtual #54                 // Method java/lang/StringBuilder.toString:()Ljava/lang/String;
      58: invokestatic  #84                 // Method org/apache/hadoop/hbase/util/Bytes.toBytes:(Ljava/lang/String;)[B
      61: areturn

  public void testStatePreserve() throws java.lang.Exception;
    Code:
       0: new           #50                 // class java/lang/StringBuilder
       3: dup
       4: invokespecial #51                 // Method java/lang/StringBuilder."<init>":()V
       7: aload_0
       8: getfield      #5                  // Field prefix:Ljava/lang/String;
      11: invokevirtual #52                 // Method java/lang/StringBuilder.append:(Ljava/lang/String;)Ljava/lang/StringBuilder;
      14: ldc           #212                // String _testStatePreserve
      16: invokevirtual #52                 // Method java/lang/StringBuilder.append:(Ljava/lang/String;)Ljava/lang/StringBuilder;
      19: invokevirtual #54                 // Method java/lang/StringBuilder.toString:()Ljava/lang/String;
      22: astore_1
      23: aload_1
      24: invokestatic  #55                 // Method org/apache/hadoop/hbase/NamespaceDescriptor.create:(Ljava/lang/String;)Lorg/apache/hadoop/hbase/NamespaceDescriptor$Builder;
      27: ldc           #57                 // String hbase.namespace.quota.maxregions
      29: ldc           #193                // String 20
      31: invokevirtual #59                 // Method org/apache/hadoop/hbase/NamespaceDescriptor$Builder.addConfiguration:(Ljava/lang/String;Ljava/lang/String;)Lorg/apache/hadoop/hbase/NamespaceDescriptor$Builder;
      34: ldc           #60                 // String hbase.namespace.quota.maxtables
      36: ldc           #113                // String 10
      38: invokevirtual #59                 // Method org/apache/hadoop/hbase/NamespaceDescriptor$Builder.addConfiguration:(Ljava/lang/String;Ljava/lang/String;)Lorg/apache/hadoop/hbase/NamespaceDescriptor$Builder;
      41: invokevirtual #62                 // Method org/apache/hadoop/hbase/NamespaceDescriptor$Builder.build:()Lorg/apache/hadoop/hbase/NamespaceDescriptor;
      44: astore_2
      45: getstatic     #2                  // Field ADMIN:Lorg/apache/hadoop/hbase/client/Admin;
      48: aload_2
      49: invokeinterface #63,  2           // InterfaceMethod org/apache/hadoop/hbase/client/Admin.createNamespace:(Lorg/apache/hadoop/hbase/NamespaceDescriptor;)V
      54: new           #50                 // class java/lang/StringBuilder
      57: dup
      58: invokespecial #51                 // Method java/lang/StringBuilder."<init>":()V
      61: aload_1
      62: invokevirtual #52                 // Method java/lang/StringBuilder.append:(Ljava/lang/String;)Ljava/lang/StringBuilder;
      65: bipush        58
      67: invokevirtual #75                 // Method java/lang/StringBuilder.append:(C)Ljava/lang/StringBuilder;
      70: ldc           #76                 // String table1
      72: invokevirtual #52                 // Method java/lang/StringBuilder.append:(Ljava/lang/String;)Ljava/lang/StringBuilder;
      75: invokevirtual #54                 // Method java/lang/StringBuilder.toString:()Ljava/lang/String;
      78: invokestatic  #77                 // Method org/apache/hadoop/hbase/TableName.valueOf:(Ljava/lang/String;)Lorg/apache/hadoop/hbase/TableName;
      81: astore_3
      82: new           #50                 // class java/lang/StringBuilder
      85: dup
      86: invokespecial #51                 // Method java/lang/StringBuilder."<init>":()V
      89: aload_1
      90: invokevirtual #52                 // Method java/lang/StringBuilder.append:(Ljava/lang/String;)Ljava/lang/StringBuilder;
      93: bipush        58
      95: invokevirtual #75                 // Method java/lang/StringBuilder.append:(C)Ljava/lang/StringBuilder;
      98: ldc           #80                 // String table2
     100: invokevirtual #52                 // Method java/lang/StringBuilder.append:(Ljava/lang/String;)Ljava/lang/StringBuilder;
     103: invokevirtual #54                 // Method java/lang/StringBuilder.toString:()Ljava/lang/String;
     106: invokestatic  #77                 // Method org/apache/hadoop/hbase/TableName.valueOf:(Ljava/lang/String;)Lorg/apache/hadoop/hbase/TableName;
     109: astore        4
     111: new           #50                 // class java/lang/StringBuilder
     114: dup
     115: invokespecial #51                 // Method java/lang/StringBuilder."<init>":()V
     118: aload_1
     119: invokevirtual #52                 // Method java/lang/StringBuilder.append:(Ljava/lang/String;)Ljava/lang/StringBuilder;
     122: bipush        58
     124: invokevirtual #75                 // Method java/lang/StringBuilder.append:(C)Ljava/lang/StringBuilder;
     127: ldc           #81                 // String table3
     129: invokevirtual #52                 // Method java/lang/StringBuilder.append:(Ljava/lang/String;)Ljava/lang/StringBuilder;
     132: invokevirtual #54                 // Method java/lang/StringBuilder.toString:()Ljava/lang/String;
     135: invokestatic  #77                 // Method org/apache/hadoop/hbase/TableName.valueOf:(Ljava/lang/String;)Lorg/apache/hadoop/hbase/TableName;
     138: astore        5
     140: new           #70                 // class org/apache/hadoop/hbase/HColumnDescriptor
     143: dup
     144: ldc           #71                 // String fam1
     146: invokespecial #72                 // Method org/apache/hadoop/hbase/HColumnDescriptor."<init>":(Ljava/lang/String;)V
     149: astore        6
     151: new           #73                 // class org/apache/hadoop/hbase/HTableDescriptor
     154: dup
     155: aload_3
     156: invokespecial #78                 // Method org/apache/hadoop/hbase/HTableDescriptor."<init>":(Lorg/apache/hadoop/hbase/TableName;)V
     159: astore        7
     161: aload         7
     163: aload         6
     165: invokevirtual #79                 // Method org/apache/hadoop/hbase/HTableDescriptor.addFamily:(Lorg/apache/hadoop/hbase/HColumnDescriptor;)Lorg/apache/hadoop/hbase/HTableDescriptor;
     168: pop
     169: new           #73                 // class org/apache/hadoop/hbase/HTableDescriptor
     172: dup
     173: aload         4
     175: invokespecial #78                 // Method org/apache/hadoop/hbase/HTableDescriptor."<init>":(Lorg/apache/hadoop/hbase/TableName;)V
     178: astore        8
     180: aload         8
     182: aload         6
     184: invokevirtual #79                 // Method org/apache/hadoop/hbase/HTableDescriptor.addFamily:(Lorg/apache/hadoop/hbase/HColumnDescriptor;)Lorg/apache/hadoop/hbase/HTableDescriptor;
     187: pop
     188: new           #73                 // class org/apache/hadoop/hbase/HTableDescriptor
     191: dup
     192: aload         5
     194: invokespecial #78                 // Method org/apache/hadoop/hbase/HTableDescriptor."<init>":(Lorg/apache/hadoop/hbase/TableName;)V
     197: astore        9
     199: aload         9
     201: aload         6
     203: invokevirtual #79                 // Method org/apache/hadoop/hbase/HTableDescriptor.addFamily:(Lorg/apache/hadoop/hbase/HColumnDescriptor;)Lorg/apache/hadoop/hbase/HTableDescriptor;
     206: pop
     207: getstatic     #2                  // Field ADMIN:Lorg/apache/hadoop/hbase/client/Admin;
     210: aload         7
     212: ldc           #194                // String 1
     214: invokestatic  #84                 // Method org/apache/hadoop/hbase/util/Bytes.toBytes:(Ljava/lang/String;)[B
     217: ldc           #213                // String 1000
     219: invokestatic  #84                 // Method org/apache/hadoop/hbase/util/Bytes.toBytes:(Ljava/lang/String;)[B
     222: iconst_3
     223: invokeinterface #86,  5           // InterfaceMethod org/apache/hadoop/hbase/client/Admin.createTable:(Lorg/apache/hadoop/hbase/client/TableDescriptor;[B[BI)V
     228: getstatic     #2                  // Field ADMIN:Lorg/apache/hadoop/hbase/client/Admin;
     231: aload         8
     233: ldc           #194                // String 1
     235: invokestatic  #84                 // Method org/apache/hadoop/hbase/util/Bytes.toBytes:(Ljava/lang/String;)[B
     238: ldc           #213                // String 1000
     240: invokestatic  #84                 // Method org/apache/hadoop/hbase/util/Bytes.toBytes:(Ljava/lang/String;)[B
     243: iconst_3
     244: invokeinterface #86,  5           // InterfaceMethod org/apache/hadoop/hbase/client/Admin.createTable:(Lorg/apache/hadoop/hbase/client/TableDescriptor;[B[BI)V
     249: getstatic     #2                  // Field ADMIN:Lorg/apache/hadoop/hbase/client/Admin;
     252: aload         9
     254: ldc           #194                // String 1
     256: invokestatic  #84                 // Method org/apache/hadoop/hbase/util/Bytes.toBytes:(Ljava/lang/String;)[B
     259: ldc           #213                // String 1000
     261: invokestatic  #84                 // Method org/apache/hadoop/hbase/util/Bytes.toBytes:(Ljava/lang/String;)[B
     264: iconst_4
     265: invokeinterface #86,  5           // InterfaceMethod org/apache/hadoop/hbase/client/Admin.createTable:(Lorg/apache/hadoop/hbase/client/TableDescriptor;[B[BI)V
     270: getstatic     #2                  // Field ADMIN:Lorg/apache/hadoop/hbase/client/Admin;
     273: aload         5
     275: invokeinterface #38,  2           // InterfaceMethod org/apache/hadoop/hbase/client/Admin.disableTable:(Lorg/apache/hadoop/hbase/TableName;)V
     280: aload_0
     281: aload         5
     283: invokespecial #39                 // Method deleteTable:(Lorg/apache/hadoop/hbase/TableName;)V
     286: getstatic     #6                  // Field UTIL:Lorg/apache/hadoop/hbase/HBaseTestingUtility;
     289: ldc2_w        #214                // long 1000l
     292: new           #216                // class org/apache/hadoop/hbase/namespace/TestNamespaceAuditor$2
     295: dup
     296: aload_0
     297: aload_1
     298: invokespecial #217                // Method org/apache/hadoop/hbase/namespace/TestNamespaceAuditor$2."<init>":(Lorg/apache/hadoop/hbase/namespace/TestNamespaceAuditor;Ljava/lang/String;)V
     301: invokevirtual #168                // Method org/apache/hadoop/hbase/HBaseTestingUtility.waitFor:(JLorg/apache/hadoop/hbase/Waiter$Predicate;)J
     304: pop2
     305: aload_0
     306: aload_1
     307: invokespecial #1                  // Method getNamespaceState:(Ljava/lang/String;)Lorg/apache/hadoop/hbase/namespace/NamespaceTableAndRegionInfo;
     310: astore        10
     312: aload_0
     313: invokespecial #218                // Method restartMaster:()V
     316: aload_0
     317: aload_1
     318: invokespecial #1                  // Method getNamespaceState:(Ljava/lang/String;)Lorg/apache/hadoop/hbase/namespace/NamespaceTableAndRegionInfo;
     321: astore        11
     323: new           #50                 // class java/lang/StringBuilder
     326: dup
     327: invokespecial #51                 // Method java/lang/StringBuilder."<init>":()V
     330: ldc           #219                // String Expected:
     332: invokevirtual #52                 // Method java/lang/StringBuilder.append:(Ljava/lang/String;)Ljava/lang/StringBuilder;
     335: aload         10
     337: invokevirtual #96                 // Method org/apache/hadoop/hbase/namespace/NamespaceTableAndRegionInfo.getTables:()Ljava/util/Set;
     340: invokevirtual #89                 // Method java/lang/StringBuilder.append:(Ljava/lang/Object;)Ljava/lang/StringBuilder;
     343: ldc           #220                // String  Found:
     345: invokevirtual #52                 // Method java/lang/StringBuilder.append:(Ljava/lang/String;)Ljava/lang/StringBuilder;
     348: aload         11
     350: invokevirtual #96                 // Method org/apache/hadoop/hbase/namespace/NamespaceTableAndRegionInfo.getTables:()Ljava/util/Set;
     353: invokevirtual #89                 // Method java/lang/StringBuilder.append:(Ljava/lang/Object;)Ljava/lang/StringBuilder;
     356: invokevirtual #54                 // Method java/lang/StringBuilder.toString:()Ljava/lang/String;
     359: aload         10
     361: invokevirtual #96                 // Method org/apache/hadoop/hbase/namespace/NamespaceTableAndRegionInfo.getTables:()Ljava/util/Set;
     364: invokeinterface #97,  1           // InterfaceMethod java/util/Set.size:()I
     369: i2l
     370: aload         11
     372: invokevirtual #96                 // Method org/apache/hadoop/hbase/namespace/NamespaceTableAndRegionInfo.getTables:()Ljava/util/Set;
     375: invokeinterface #97,  1           // InterfaceMethod java/util/Set.size:()I
     380: i2l
     381: invokestatic  #202                // Method org/junit/Assert.assertEquals:(Ljava/lang/String;JJ)V
     384: return

  public static void waitForQuotaInitialize(org.apache.hadoop.hbase.HBaseTestingUtility) throws java.lang.Exception;
    Code:
       0: aload_0
       1: ldc2_w        #221                // long 60000l
       4: new           #223                // class org/apache/hadoop/hbase/namespace/TestNamespaceAuditor$3
       7: dup
       8: aload_0
       9: invokespecial #224                // Method org/apache/hadoop/hbase/namespace/TestNamespaceAuditor$3."<init>":(Lorg/apache/hadoop/hbase/HBaseTestingUtility;)V
      12: invokevirtual #168                // Method org/apache/hadoop/hbase/HBaseTestingUtility.waitFor:(JLorg/apache/hadoop/hbase/Waiter$Predicate;)J
      15: pop2
      16: return

  public void testExceedTableQuotaInNamespace() throws java.lang.Exception;
    Code:
       0: new           #50                 // class java/lang/StringBuilder
       3: dup
       4: invokespecial #51                 // Method java/lang/StringBuilder."<init>":()V
       7: aload_0
       8: getfield      #5                  // Field prefix:Ljava/lang/String;
      11: invokevirtual #52                 // Method java/lang/StringBuilder.append:(Ljava/lang/String;)Ljava/lang/StringBuilder;
      14: ldc           #234                // String _testExceedTableQuotaInNamespace
      16: invokevirtual #52                 // Method java/lang/StringBuilder.append:(Ljava/lang/String;)Ljava/lang/StringBuilder;
      19: invokevirtual #54                 // Method java/lang/StringBuilder.toString:()Ljava/lang/String;
      22: astore_1
      23: aload_1
      24: invokestatic  #55                 // Method org/apache/hadoop/hbase/NamespaceDescriptor.create:(Ljava/lang/String;)Lorg/apache/hadoop/hbase/NamespaceDescriptor$Builder;
      27: ldc           #60                 // String hbase.namespace.quota.maxtables
      29: ldc           #194                // String 1
      31: invokevirtual #59                 // Method org/apache/hadoop/hbase/NamespaceDescriptor$Builder.addConfiguration:(Ljava/lang/String;Ljava/lang/String;)Lorg/apache/hadoop/hbase/NamespaceDescriptor$Builder;
      34: invokevirtual #62                 // Method org/apache/hadoop/hbase/NamespaceDescriptor$Builder.build:()Lorg/apache/hadoop/hbase/NamespaceDescriptor;
      37: astore_2
      38: getstatic     #2                  // Field ADMIN:Lorg/apache/hadoop/hbase/client/Admin;
      41: aload_2
      42: invokeinterface #63,  2           // InterfaceMethod org/apache/hadoop/hbase/client/Admin.createNamespace:(Lorg/apache/hadoop/hbase/NamespaceDescriptor;)V
      47: ldc           #64                 // String Namespace descriptor found null.
      49: getstatic     #2                  // Field ADMIN:Lorg/apache/hadoop/hbase/client/Admin;
      52: aload_1
      53: invokeinterface #65,  2           // InterfaceMethod org/apache/hadoop/hbase/client/Admin.getNamespaceDescriptor:(Ljava/lang/String;)Lorg/apache/hadoop/hbase/NamespaceDescriptor;
      58: invokestatic  #66                 // Method org/junit/Assert.assertNotNull:(Ljava/lang/String;Ljava/lang/Object;)V
      61: ldc2_w        #67                 // long 3l
      64: getstatic     #2                  // Field ADMIN:Lorg/apache/hadoop/hbase/client/Admin;
      67: invokeinterface #40,  1           // InterfaceMethod org/apache/hadoop/hbase/client/Admin.listNamespaceDescriptors:()[Lorg/apache/hadoop/hbase/NamespaceDescriptor;
      72: arraylength
      73: i2l
      74: invokestatic  #69                 // Method org/junit/Assert.assertEquals:(JJ)V
      77: new           #70                 // class org/apache/hadoop/hbase/HColumnDescriptor
      80: dup
      81: ldc           #71                 // String fam1
      83: invokespecial #72                 // Method org/apache/hadoop/hbase/HColumnDescriptor."<init>":(Ljava/lang/String;)V
      86: astore_3
      87: new           #73                 // class org/apache/hadoop/hbase/HTableDescriptor
      90: dup
      91: new           #50                 // class java/lang/StringBuilder
      94: dup
      95: invokespecial #51                 // Method java/lang/StringBuilder."<init>":()V
      98: aload_1
      99: invokevirtual #52                 // Method java/lang/StringBuilder.append:(Ljava/lang/String;)Ljava/lang/StringBuilder;
     102: bipush        58
     104: invokevirtual #75                 // Method java/lang/StringBuilder.append:(C)Ljava/lang/StringBuilder;
     107: ldc           #76                 // String table1
     109: invokevirtual #52                 // Method java/lang/StringBuilder.append:(Ljava/lang/String;)Ljava/lang/StringBuilder;
     112: invokevirtual #54                 // Method java/lang/StringBuilder.toString:()Ljava/lang/String;
     115: invokestatic  #77                 // Method org/apache/hadoop/hbase/TableName.valueOf:(Ljava/lang/String;)Lorg/apache/hadoop/hbase/TableName;
     118: invokespecial #78                 // Method org/apache/hadoop/hbase/HTableDescriptor."<init>":(Lorg/apache/hadoop/hbase/TableName;)V
     121: astore        4
     123: aload         4
     125: aload_3
     126: invokevirtual #79                 // Method org/apache/hadoop/hbase/HTableDescriptor.addFamily:(Lorg/apache/hadoop/hbase/HColumnDescriptor;)Lorg/apache/hadoop/hbase/HTableDescriptor;
     129: pop
     130: new           #73                 // class org/apache/hadoop/hbase/HTableDescriptor
     133: dup
     134: new           #50                 // class java/lang/StringBuilder
     137: dup
     138: invokespecial #51                 // Method java/lang/StringBuilder."<init>":()V
     141: aload_1
     142: invokevirtual #52                 // Method java/lang/StringBuilder.append:(Ljava/lang/String;)Ljava/lang/StringBuilder;
     145: bipush        58
     147: invokevirtual #75                 // Method java/lang/StringBuilder.append:(C)Ljava/lang/StringBuilder;
     150: ldc           #80                 // String table2
     152: invokevirtual #52                 // Method java/lang/StringBuilder.append:(Ljava/lang/String;)Ljava/lang/StringBuilder;
     155: invokevirtual #54                 // Method java/lang/StringBuilder.toString:()Ljava/lang/String;
     158: invokestatic  #77                 // Method org/apache/hadoop/hbase/TableName.valueOf:(Ljava/lang/String;)Lorg/apache/hadoop/hbase/TableName;
     161: invokespecial #78                 // Method org/apache/hadoop/hbase/HTableDescriptor."<init>":(Lorg/apache/hadoop/hbase/TableName;)V
     164: astore        5
     166: aload         5
     168: aload_3
     169: invokevirtual #79                 // Method org/apache/hadoop/hbase/HTableDescriptor.addFamily:(Lorg/apache/hadoop/hbase/HColumnDescriptor;)Lorg/apache/hadoop/hbase/HTableDescriptor;
     172: pop
     173: getstatic     #2                  // Field ADMIN:Lorg/apache/hadoop/hbase/client/Admin;
     176: aload         4
     178: invokeinterface #82,  2           // InterfaceMethod org/apache/hadoop/hbase/client/Admin.createTable:(Lorg/apache/hadoop/hbase/client/TableDescriptor;)V
     183: getstatic     #2                  // Field ADMIN:Lorg/apache/hadoop/hbase/client/Admin;
     186: aload         5
     188: ldc           #83                 // String AAA
     190: invokestatic  #84                 // Method org/apache/hadoop/hbase/util/Bytes.toBytes:(Ljava/lang/String;)[B
     193: ldc           #85                 // String ZZZ
     195: invokestatic  #84                 // Method org/apache/hadoop/hbase/util/Bytes.toBytes:(Ljava/lang/String;)[B
     198: iconst_4
     199: invokeinterface #86,  5           // InterfaceMethod org/apache/hadoop/hbase/client/Admin.createTable:(Lorg/apache/hadoop/hbase/client/TableDescriptor;[B[BI)V
     204: return

  public void testCloneSnapshotQuotaExceed() throws java.lang.Exception;
    Code:
       0: new           #50                 // class java/lang/StringBuilder
       3: dup
       4: invokespecial #51                 // Method java/lang/StringBuilder."<init>":()V
       7: aload_0
       8: getfield      #5                  // Field prefix:Ljava/lang/String;
      11: invokevirtual #52                 // Method java/lang/StringBuilder.append:(Ljava/lang/String;)Ljava/lang/StringBuilder;
      14: ldc           #235                // String _testTableQuotaExceedWithCloneSnapshot
      16: invokevirtual #52                 // Method java/lang/StringBuilder.append:(Ljava/lang/String;)Ljava/lang/StringBuilder;
      19: invokevirtual #54                 // Method java/lang/StringBuilder.toString:()Ljava/lang/String;
      22: astore_1
      23: aload_1
      24: invokestatic  #55                 // Method org/apache/hadoop/hbase/NamespaceDescriptor.create:(Ljava/lang/String;)Lorg/apache/hadoop/hbase/NamespaceDescriptor$Builder;
      27: ldc           #60                 // String hbase.namespace.quota.maxtables
      29: ldc           #194                // String 1
      31: invokevirtual #59                 // Method org/apache/hadoop/hbase/NamespaceDescriptor$Builder.addConfiguration:(Ljava/lang/String;Ljava/lang/String;)Lorg/apache/hadoop/hbase/NamespaceDescriptor$Builder;
      34: invokevirtual #62                 // Method org/apache/hadoop/hbase/NamespaceDescriptor$Builder.build:()Lorg/apache/hadoop/hbase/NamespaceDescriptor;
      37: astore_2
      38: getstatic     #2                  // Field ADMIN:Lorg/apache/hadoop/hbase/client/Admin;
      41: aload_2
      42: invokeinterface #63,  2           // InterfaceMethod org/apache/hadoop/hbase/client/Admin.createNamespace:(Lorg/apache/hadoop/hbase/NamespaceDescriptor;)V
      47: ldc           #64                 // String Namespace descriptor found null.
      49: getstatic     #2                  // Field ADMIN:Lorg/apache/hadoop/hbase/client/Admin;
      52: aload_1
      53: invokeinterface #65,  2           // InterfaceMethod org/apache/hadoop/hbase/client/Admin.getNamespaceDescriptor:(Ljava/lang/String;)Lorg/apache/hadoop/hbase/NamespaceDescriptor;
      58: invokestatic  #66                 // Method org/junit/Assert.assertNotNull:(Ljava/lang/String;Ljava/lang/Object;)V
      61: new           #50                 // class java/lang/StringBuilder
      64: dup
      65: invokespecial #51                 // Method java/lang/StringBuilder."<init>":()V
      68: aload_1
      69: invokevirtual #52                 // Method java/lang/StringBuilder.append:(Ljava/lang/String;)Ljava/lang/StringBuilder;
      72: bipush        58
      74: invokevirtual #75                 // Method java/lang/StringBuilder.append:(C)Ljava/lang/StringBuilder;
      77: ldc           #76                 // String table1
      79: invokevirtual #52                 // Method java/lang/StringBuilder.append:(Ljava/lang/String;)Ljava/lang/StringBuilder;
      82: invokevirtual #54                 // Method java/lang/StringBuilder.toString:()Ljava/lang/String;
      85: invokestatic  #77                 // Method org/apache/hadoop/hbase/TableName.valueOf:(Ljava/lang/String;)Lorg/apache/hadoop/hbase/TableName;
      88: astore_3
      89: new           #50                 // class java/lang/StringBuilder
      92: dup
      93: invokespecial #51                 // Method java/lang/StringBuilder."<init>":()V
      96: aload_1
      97: invokevirtual #52                 // Method java/lang/StringBuilder.append:(Ljava/lang/String;)Ljava/lang/StringBuilder;
     100: bipush        58
     102: invokevirtual #75                 // Method java/lang/StringBuilder.append:(C)Ljava/lang/StringBuilder;
     105: ldc           #80                 // String table2
     107: invokevirtual #52                 // Method java/lang/StringBuilder.append:(Ljava/lang/String;)Ljava/lang/StringBuilder;
     110: invokevirtual #54                 // Method java/lang/StringBuilder.toString:()Ljava/lang/String;
     113: invokestatic  #77                 // Method org/apache/hadoop/hbase/TableName.valueOf:(Ljava/lang/String;)Lorg/apache/hadoop/hbase/TableName;
     116: astore        4
     118: new           #70                 // class org/apache/hadoop/hbase/HColumnDescriptor
     121: dup
     122: ldc           #71                 // String fam1
     124: invokespecial #72                 // Method org/apache/hadoop/hbase/HColumnDescriptor."<init>":(Ljava/lang/String;)V
     127: astore        5
     129: new           #73                 // class org/apache/hadoop/hbase/HTableDescriptor
     132: dup
     133: aload_3
     134: invokespecial #78                 // Method org/apache/hadoop/hbase/HTableDescriptor."<init>":(Lorg/apache/hadoop/hbase/TableName;)V
     137: astore        6
     139: aload         6
     141: aload         5
     143: invokevirtual #79                 // Method org/apache/hadoop/hbase/HTableDescriptor.addFamily:(Lorg/apache/hadoop/hbase/HColumnDescriptor;)Lorg/apache/hadoop/hbase/HTableDescriptor;
     146: pop
     147: getstatic     #2                  // Field ADMIN:Lorg/apache/hadoop/hbase/client/Admin;
     150: aload         6
     152: invokeinterface #82,  2           // InterfaceMethod org/apache/hadoop/hbase/client/Admin.createTable:(Lorg/apache/hadoop/hbase/client/TableDescriptor;)V
     157: ldc           #236                // String snapshot_testTableQuotaExceedWithCloneSnapshot
     159: astore        7
     161: getstatic     #2                  // Field ADMIN:Lorg/apache/hadoop/hbase/client/Admin;
     164: aload         7
     166: aload_3
     167: invokeinterface #237,  3          // InterfaceMethod org/apache/hadoop/hbase/client/Admin.snapshot:(Ljava/lang/String;Lorg/apache/hadoop/hbase/TableName;)V
     172: getstatic     #2                  // Field ADMIN:Lorg/apache/hadoop/hbase/client/Admin;
     175: aload         7
     177: aload         4
     179: invokeinterface #238,  3          // InterfaceMethod org/apache/hadoop/hbase/client/Admin.cloneSnapshot:(Ljava/lang/String;Lorg/apache/hadoop/hbase/TableName;)V
     184: getstatic     #2                  // Field ADMIN:Lorg/apache/hadoop/hbase/client/Admin;
     187: aload         7
     189: invokeinterface #239,  2          // InterfaceMethod org/apache/hadoop/hbase/client/Admin.deleteSnapshot:(Ljava/lang/String;)V
     194: return

  public void testCloneSnapshot() throws java.lang.Exception;
    Code:
       0: new           #50                 // class java/lang/StringBuilder
       3: dup
       4: invokespecial #51                 // Method java/lang/StringBuilder."<init>":()V
       7: aload_0
       8: getfield      #5                  // Field prefix:Ljava/lang/String;
      11: invokevirtual #52                 // Method java/lang/StringBuilder.append:(Ljava/lang/String;)Ljava/lang/StringBuilder;
      14: ldc           #240                // String _testCloneSnapshot
      16: invokevirtual #52                 // Method java/lang/StringBuilder.append:(Ljava/lang/String;)Ljava/lang/StringBuilder;
      19: invokevirtual #54                 // Method java/lang/StringBuilder.toString:()Ljava/lang/String;
      22: astore_1
      23: aload_1
      24: invokestatic  #55                 // Method org/apache/hadoop/hbase/NamespaceDescriptor.create:(Ljava/lang/String;)Lorg/apache/hadoop/hbase/NamespaceDescriptor$Builder;
      27: ldc           #60                 // String hbase.namespace.quota.maxtables
      29: ldc           #61                 // String 2
      31: invokevirtual #59                 // Method org/apache/hadoop/hbase/NamespaceDescriptor$Builder.addConfiguration:(Ljava/lang/String;Ljava/lang/String;)Lorg/apache/hadoop/hbase/NamespaceDescriptor$Builder;
      34: ldc           #57                 // String hbase.namespace.quota.maxregions
      36: ldc           #193                // String 20
      38: invokevirtual #59                 // Method org/apache/hadoop/hbase/NamespaceDescriptor$Builder.addConfiguration:(Ljava/lang/String;Ljava/lang/String;)Lorg/apache/hadoop/hbase/NamespaceDescriptor$Builder;
      41: invokevirtual #62                 // Method org/apache/hadoop/hbase/NamespaceDescriptor$Builder.build:()Lorg/apache/hadoop/hbase/NamespaceDescriptor;
      44: astore_2
      45: getstatic     #2                  // Field ADMIN:Lorg/apache/hadoop/hbase/client/Admin;
      48: aload_2
      49: invokeinterface #63,  2           // InterfaceMethod org/apache/hadoop/hbase/client/Admin.createNamespace:(Lorg/apache/hadoop/hbase/NamespaceDescriptor;)V
      54: ldc           #64                 // String Namespace descriptor found null.
      56: getstatic     #2                  // Field ADMIN:Lorg/apache/hadoop/hbase/client/Admin;
      59: aload_1
      60: invokeinterface #65,  2           // InterfaceMethod org/apache/hadoop/hbase/client/Admin.getNamespaceDescriptor:(Ljava/lang/String;)Lorg/apache/hadoop/hbase/NamespaceDescriptor;
      65: invokestatic  #66                 // Method org/junit/Assert.assertNotNull:(Ljava/lang/String;Ljava/lang/Object;)V
      68: new           #50                 // class java/lang/StringBuilder
      71: dup
      72: invokespecial #51                 // Method java/lang/StringBuilder."<init>":()V
      75: aload_1
      76: invokevirtual #52                 // Method java/lang/StringBuilder.append:(Ljava/lang/String;)Ljava/lang/StringBuilder;
      79: bipush        58
      81: invokevirtual #75                 // Method java/lang/StringBuilder.append:(C)Ljava/lang/StringBuilder;
      84: ldc           #76                 // String table1
      86: invokevirtual #52                 // Method java/lang/StringBuilder.append:(Ljava/lang/String;)Ljava/lang/StringBuilder;
      89: invokevirtual #54                 // Method java/lang/StringBuilder.toString:()Ljava/lang/String;
      92: invokestatic  #77                 // Method org/apache/hadoop/hbase/TableName.valueOf:(Ljava/lang/String;)Lorg/apache/hadoop/hbase/TableName;
      95: astore_3
      96: new           #50                 // class java/lang/StringBuilder
      99: dup
     100: invokespecial #51                 // Method java/lang/StringBuilder."<init>":()V
     103: aload_1
     104: invokevirtual #52                 // Method java/lang/StringBuilder.append:(Ljava/lang/String;)Ljava/lang/StringBuilder;
     107: bipush        58
     109: invokevirtual #75                 // Method java/lang/StringBuilder.append:(C)Ljava/lang/StringBuilder;
     112: ldc           #80                 // String table2
     114: invokevirtual #52                 // Method java/lang/StringBuilder.append:(Ljava/lang/String;)Ljava/lang/StringBuilder;
     117: invokevirtual #54                 // Method java/lang/StringBuilder.toString:()Ljava/lang/String;
     120: invokestatic  #77                 // Method org/apache/hadoop/hbase/TableName.valueOf:(Ljava/lang/String;)Lorg/apache/hadoop/hbase/TableName;
     123: astore        4
     125: new           #70                 // class org/apache/hadoop/hbase/HColumnDescriptor
     128: dup
     129: ldc           #71                 // String fam1
     131: invokespecial #72                 // Method org/apache/hadoop/hbase/HColumnDescriptor."<init>":(Ljava/lang/String;)V
     134: astore        5
     136: new           #73                 // class org/apache/hadoop/hbase/HTableDescriptor
     139: dup
     140: aload_3
     141: invokespecial #78                 // Method org/apache/hadoop/hbase/HTableDescriptor."<init>":(Lorg/apache/hadoop/hbase/TableName;)V
     144: astore        6
     146: aload         6
     148: aload         5
     150: invokevirtual #79                 // Method org/apache/hadoop/hbase/HTableDescriptor.addFamily:(Lorg/apache/hadoop/hbase/HColumnDescriptor;)Lorg/apache/hadoop/hbase/HTableDescriptor;
     153: pop
     154: getstatic     #2                  // Field ADMIN:Lorg/apache/hadoop/hbase/client/Admin;
     157: aload         6
     159: ldc           #83                 // String AAA
     161: invokestatic  #84                 // Method org/apache/hadoop/hbase/util/Bytes.toBytes:(Ljava/lang/String;)[B
     164: ldc           #85                 // String ZZZ
     166: invokestatic  #84                 // Method org/apache/hadoop/hbase/util/Bytes.toBytes:(Ljava/lang/String;)[B
     169: iconst_4
     170: invokeinterface #86,  5           // InterfaceMethod org/apache/hadoop/hbase/client/Admin.createTable:(Lorg/apache/hadoop/hbase/client/TableDescriptor;[B[BI)V
     175: ldc           #241                // String snapshot_testCloneSnapshot
     177: astore        7
     179: getstatic     #2                  // Field ADMIN:Lorg/apache/hadoop/hbase/client/Admin;
     182: aload         7
     184: aload_3
     185: invokeinterface #237,  3          // InterfaceMethod org/apache/hadoop/hbase/client/Admin.snapshot:(Ljava/lang/String;Lorg/apache/hadoop/hbase/TableName;)V
     190: getstatic     #2                  // Field ADMIN:Lorg/apache/hadoop/hbase/client/Admin;
     193: aload         7
     195: aload         4
     197: invokeinterface #238,  3          // InterfaceMethod org/apache/hadoop/hbase/client/Admin.cloneSnapshot:(Ljava/lang/String;Lorg/apache/hadoop/hbase/TableName;)V
     202: getstatic     #2                  // Field ADMIN:Lorg/apache/hadoop/hbase/client/Admin;
     205: invokeinterface #242,  1          // InterfaceMethod org/apache/hadoop/hbase/client/Admin.getConnection:()Lorg/apache/hadoop/hbase/client/Connection;
     210: aload_3
     211: invokeinterface #243,  2          // InterfaceMethod org/apache/hadoop/hbase/client/Connection.getRegionLocator:(Lorg/apache/hadoop/hbase/TableName;)Lorg/apache/hadoop/hbase/client/RegionLocator;
     216: astore        9
     218: aconst_null
     219: astore        10
     221: aload         9
     223: invokeinterface #244,  1          // InterfaceMethod org/apache/hadoop/hbase/client/RegionLocator.getStartKeys:()[[B
     228: arraylength
     229: istore        8
     231: aload         9
     233: ifnull        326
     236: aload         10
     238: ifnull        263
     241: aload         9
     243: invokeinterface #245,  1          // InterfaceMethod org/apache/hadoop/hbase/client/RegionLocator.close:()V
     248: goto          326
     251: astore        11
     253: aload         10
     255: aload         11
     257: invokevirtual #141                // Method java/lang/Throwable.addSuppressed:(Ljava/lang/Throwable;)V
     260: goto          326
     263: aload         9
     265: invokeinterface #245,  1          // InterfaceMethod org/apache/hadoop/hbase/client/RegionLocator.close:()V
     270: goto          326
     273: astore        11
     275: aload         11
     277: astore        10
     279: aload         11
     281: athrow
     282: astore        12
     284: aload         9
     286: ifnull        323
     289: aload         10
     291: ifnull        316
     294: aload         9
     296: invokeinterface #245,  1          // InterfaceMethod org/apache/hadoop/hbase/client/RegionLocator.close:()V
     301: goto          323
     304: astore        13
     306: aload         10
     308: aload         13
     310: invokevirtual #141                // Method java/lang/Throwable.addSuppressed:(Ljava/lang/Throwable;)V
     313: goto          323
     316: aload         9
     318: invokeinterface #245,  1          // InterfaceMethod org/apache/hadoop/hbase/client/RegionLocator.close:()V
     323: aload         12
     325: athrow
     326: new           #50                 // class java/lang/StringBuilder
     329: dup
     330: invokespecial #51                 // Method java/lang/StringBuilder."<init>":()V
     333: aload_3
     334: invokevirtual #246                // Method org/apache/hadoop/hbase/TableName.getNameAsString:()Ljava/lang/String;
     337: invokevirtual #52                 // Method java/lang/StringBuilder.append:(Ljava/lang/String;)Ljava/lang/StringBuilder;
     340: ldc           #247                // String  should have four regions.
     342: invokevirtual #52                 // Method java/lang/StringBuilder.append:(Ljava/lang/String;)Ljava/lang/StringBuilder;
     345: invokevirtual #54                 // Method java/lang/StringBuilder.toString:()Ljava/lang/String;
     348: ldc2_w        #248                // long 4l
     351: iload         8
     353: i2l
     354: invokestatic  #202                // Method org/junit/Assert.assertEquals:(Ljava/lang/String;JJ)V
     357: getstatic     #2                  // Field ADMIN:Lorg/apache/hadoop/hbase/client/Admin;
     360: invokeinterface #242,  1          // InterfaceMethod org/apache/hadoop/hbase/client/Admin.getConnection:()Lorg/apache/hadoop/hbase/client/Connection;
     365: aload         4
     367: invokeinterface #243,  2          // InterfaceMethod org/apache/hadoop/hbase/client/Connection.getRegionLocator:(Lorg/apache/hadoop/hbase/TableName;)Lorg/apache/hadoop/hbase/client/RegionLocator;
     372: astore        9
     374: aconst_null
     375: astore        10
     377: aload         9
     379: invokeinterface #244,  1          // InterfaceMethod org/apache/hadoop/hbase/client/RegionLocator.getStartKeys:()[[B
     384: arraylength
     385: istore        8
     387: aload         9
     389: ifnull        482
     392: aload         10
     394: ifnull        419
     397: aload         9
     399: invokeinterface #245,  1          // InterfaceMethod org/apache/hadoop/hbase/client/RegionLocator.close:()V
     404: goto          482
     407: astore        11
     409: aload         10
     411: aload         11
     413: invokevirtual #141                // Method java/lang/Throwable.addSuppressed:(Ljava/lang/Throwable;)V
     416: goto          482
     419: aload         9
     421: invokeinterface #245,  1          // InterfaceMethod org/apache/hadoop/hbase/client/RegionLocator.close:()V
     426: goto          482
     429: astore        11
     431: aload         11
     433: astore        10
     435: aload         11
     437: athrow
     438: astore        14
     440: aload         9
     442: ifnull        479
     445: aload         10
     447: ifnull        472
     450: aload         9
     452: invokeinterface #245,  1          // InterfaceMethod org/apache/hadoop/hbase/client/RegionLocator.close:()V
     457: goto          479
     460: astore        15
     462: aload         10
     464: aload         15
     466: invokevirtual #141                // Method java/lang/Throwable.addSuppressed:(Ljava/lang/Throwable;)V
     469: goto          479
     472: aload         9
     474: invokeinterface #245,  1          // InterfaceMethod org/apache/hadoop/hbase/client/RegionLocator.close:()V
     479: aload         14
     481: athrow
     482: new           #50                 // class java/lang/StringBuilder
     485: dup
     486: invokespecial #51                 // Method java/lang/StringBuilder."<init>":()V
     489: aload         4
     491: invokevirtual #246                // Method org/apache/hadoop/hbase/TableName.getNameAsString:()Ljava/lang/String;
     494: invokevirtual #52                 // Method java/lang/StringBuilder.append:(Ljava/lang/String;)Ljava/lang/StringBuilder;
     497: ldc           #247                // String  should have four regions.
     499: invokevirtual #52                 // Method java/lang/StringBuilder.append:(Ljava/lang/String;)Ljava/lang/StringBuilder;
     502: invokevirtual #54                 // Method java/lang/StringBuilder.toString:()Ljava/lang/String;
     505: ldc2_w        #248                // long 4l
     508: iload         8
     510: i2l
     511: invokestatic  #202                // Method org/junit/Assert.assertEquals:(Ljava/lang/String;JJ)V
     514: aload_0
     515: aload_1
     516: invokespecial #1                  // Method getNamespaceState:(Ljava/lang/String;)Lorg/apache/hadoop/hbase/namespace/NamespaceTableAndRegionInfo;
     519: astore        9
     521: ldc           #250                // String Total tables count should be 2.
     523: ldc2_w        #122                // long 2l
     526: aload         9
     528: invokevirtual #96                 // Method org/apache/hadoop/hbase/namespace/NamespaceTableAndRegionInfo.getTables:()Ljava/util/Set;
     531: invokeinterface #97,  1           // InterfaceMethod java/util/Set.size:()I
     536: i2l
     537: invokestatic  #202                // Method org/junit/Assert.assertEquals:(Ljava/lang/String;JJ)V
     540: ldc           #251                // String Total regions count should be.
     542: ldc2_w        #252                // long 8l
     545: aload         9
     547: invokevirtual #98                 // Method org/apache/hadoop/hbase/namespace/NamespaceTableAndRegionInfo.getRegionCount:()I
     550: i2l
     551: invokestatic  #202                // Method org/junit/Assert.assertEquals:(Ljava/lang/String;JJ)V
     554: getstatic     #2                  // Field ADMIN:Lorg/apache/hadoop/hbase/client/Admin;
     557: aload         7
     559: invokeinterface #239,  2          // InterfaceMethod org/apache/hadoop/hbase/client/Admin.deleteSnapshot:(Ljava/lang/String;)V
     564: return
    Exception table:
       from    to  target type
         241   248   251   Class java/lang/Throwable
         221   231   273   Class java/lang/Throwable
         221   231   282   any
         294   301   304   Class java/lang/Throwable
         273   284   282   any
         397   404   407   Class java/lang/Throwable
         377   387   429   Class java/lang/Throwable
         377   387   438   any
         450   457   460   Class java/lang/Throwable
         429   440   438   any

  public void testRestoreSnapshot() throws java.lang.Exception;
    Code:
       0: new           #50                 // class java/lang/StringBuilder
       3: dup
       4: invokespecial #51                 // Method java/lang/StringBuilder."<init>":()V
       7: aload_0
       8: getfield      #5                  // Field prefix:Ljava/lang/String;
      11: invokevirtual #52                 // Method java/lang/StringBuilder.append:(Ljava/lang/String;)Ljava/lang/StringBuilder;
      14: ldc           #254                // String _testRestoreSnapshot
      16: invokevirtual #52                 // Method java/lang/StringBuilder.append:(Ljava/lang/String;)Ljava/lang/StringBuilder;
      19: invokevirtual #54                 // Method java/lang/StringBuilder.toString:()Ljava/lang/String;
      22: astore_1
      23: aload_1
      24: invokestatic  #55                 // Method org/apache/hadoop/hbase/NamespaceDescriptor.create:(Ljava/lang/String;)Lorg/apache/hadoop/hbase/NamespaceDescriptor$Builder;
      27: ldc           #57                 // String hbase.namespace.quota.maxregions
      29: ldc           #113                // String 10
      31: invokevirtual #59                 // Method org/apache/hadoop/hbase/NamespaceDescriptor$Builder.addConfiguration:(Ljava/lang/String;Ljava/lang/String;)Lorg/apache/hadoop/hbase/NamespaceDescriptor$Builder;
      34: invokevirtual #62                 // Method org/apache/hadoop/hbase/NamespaceDescriptor$Builder.build:()Lorg/apache/hadoop/hbase/NamespaceDescriptor;
      37: astore_2
      38: getstatic     #2                  // Field ADMIN:Lorg/apache/hadoop/hbase/client/Admin;
      41: aload_2
      42: invokeinterface #63,  2           // InterfaceMethod org/apache/hadoop/hbase/client/Admin.createNamespace:(Lorg/apache/hadoop/hbase/NamespaceDescriptor;)V
      47: ldc           #64                 // String Namespace descriptor found null.
      49: getstatic     #2                  // Field ADMIN:Lorg/apache/hadoop/hbase/client/Admin;
      52: aload_1
      53: invokeinterface #65,  2           // InterfaceMethod org/apache/hadoop/hbase/client/Admin.getNamespaceDescriptor:(Ljava/lang/String;)Lorg/apache/hadoop/hbase/NamespaceDescriptor;
      58: invokestatic  #66                 // Method org/junit/Assert.assertNotNull:(Ljava/lang/String;Ljava/lang/Object;)V
      61: new           #50                 // class java/lang/StringBuilder
      64: dup
      65: invokespecial #51                 // Method java/lang/StringBuilder."<init>":()V
      68: aload_1
      69: invokevirtual #52                 // Method java/lang/StringBuilder.append:(Ljava/lang/String;)Ljava/lang/StringBuilder;
      72: bipush        58
      74: invokevirtual #75                 // Method java/lang/StringBuilder.append:(C)Ljava/lang/StringBuilder;
      77: ldc           #76                 // String table1
      79: invokevirtual #52                 // Method java/lang/StringBuilder.append:(Ljava/lang/String;)Ljava/lang/StringBuilder;
      82: invokevirtual #54                 // Method java/lang/StringBuilder.toString:()Ljava/lang/String;
      85: invokestatic  #77                 // Method org/apache/hadoop/hbase/TableName.valueOf:(Ljava/lang/String;)Lorg/apache/hadoop/hbase/TableName;
      88: astore_3
      89: new           #73                 // class org/apache/hadoop/hbase/HTableDescriptor
      92: dup
      93: aload_3
      94: invokespecial #78                 // Method org/apache/hadoop/hbase/HTableDescriptor."<init>":(Lorg/apache/hadoop/hbase/TableName;)V
      97: astore        4
      99: new           #70                 // class org/apache/hadoop/hbase/HColumnDescriptor
     102: dup
     103: ldc           #71                 // String fam1
     105: invokespecial #72                 // Method org/apache/hadoop/hbase/HColumnDescriptor."<init>":(Ljava/lang/String;)V
     108: astore        5
     110: aload         4
     112: aload         5
     114: invokevirtual #79                 // Method org/apache/hadoop/hbase/HTableDescriptor.addFamily:(Lorg/apache/hadoop/hbase/HColumnDescriptor;)Lorg/apache/hadoop/hbase/HTableDescriptor;
     117: pop
     118: getstatic     #2                  // Field ADMIN:Lorg/apache/hadoop/hbase/client/Admin;
     121: aload         4
     123: ldc           #83                 // String AAA
     125: invokestatic  #84                 // Method org/apache/hadoop/hbase/util/Bytes.toBytes:(Ljava/lang/String;)[B
     128: ldc           #85                 // String ZZZ
     130: invokestatic  #84                 // Method org/apache/hadoop/hbase/util/Bytes.toBytes:(Ljava/lang/String;)[B
     133: iconst_4
     134: invokeinterface #86,  5           // InterfaceMethod org/apache/hadoop/hbase/client/Admin.createTable:(Lorg/apache/hadoop/hbase/client/TableDescriptor;[B[BI)V
     139: aload_0
     140: aload_1
     141: invokespecial #1                  // Method getNamespaceState:(Ljava/lang/String;)Lorg/apache/hadoop/hbase/namespace/NamespaceTableAndRegionInfo;
     144: astore        6
     146: ldc           #255                // String Intial region count should be 4.
     148: ldc2_w        #248                // long 4l
     151: aload         6
     153: invokevirtual #98                 // Method org/apache/hadoop/hbase/namespace/NamespaceTableAndRegionInfo.getRegionCount:()I
     156: i2l
     157: invokestatic  #202                // Method org/junit/Assert.assertEquals:(Ljava/lang/String;JJ)V
     160: ldc_w         #256                // String snapshot_testRestoreSnapshot
     163: astore        7
     165: getstatic     #2                  // Field ADMIN:Lorg/apache/hadoop/hbase/client/Admin;
     168: aload         7
     170: aload_3
     171: invokeinterface #237,  3          // InterfaceMethod org/apache/hadoop/hbase/client/Admin.snapshot:(Ljava/lang/String;Lorg/apache/hadoop/hbase/TableName;)V
     176: getstatic     #2                  // Field ADMIN:Lorg/apache/hadoop/hbase/client/Admin;
     179: aload_3
     180: invokeinterface #143,  2          // InterfaceMethod org/apache/hadoop/hbase/client/Admin.getRegions:(Lorg/apache/hadoop/hbase/TableName;)Ljava/util/List;
     185: astore        8
     187: aload         8
     189: getstatic     #145                // Field org/apache/hadoop/hbase/client/RegionInfo.COMPARATOR:Ljava/util/Comparator;
     192: invokestatic  #146                // Method java/util/Collections.sort:(Ljava/util/List;Ljava/util/Comparator;)V
     195: getstatic     #2                  // Field ADMIN:Lorg/apache/hadoop/hbase/client/Admin;
     198: aload_3
     199: ldc_w         #257                // String JJJ
     202: invokestatic  #84                 // Method org/apache/hadoop/hbase/util/Bytes.toBytes:(Ljava/lang/String;)[B
     205: invokeinterface #186,  3          // InterfaceMethod org/apache/hadoop/hbase/client/Admin.split:(Lorg/apache/hadoop/hbase/TableName;[B)V
     210: ldc2_w        #189                // long 2000l
     213: invokestatic  #191                // Method java/lang/Thread.sleep:(J)V
     216: ldc_w         #258                // String Total regions count should be 5.
     219: ldc2_w        #124                // long 5l
     222: aload         6
     224: invokevirtual #98                 // Method org/apache/hadoop/hbase/namespace/NamespaceTableAndRegionInfo.getRegionCount:()I
     227: i2l
     228: invokestatic  #202                // Method org/junit/Assert.assertEquals:(Ljava/lang/String;JJ)V
     231: getstatic     #2                  // Field ADMIN:Lorg/apache/hadoop/hbase/client/Admin;
     234: aload_3
     235: invokeinterface #38,  2           // InterfaceMethod org/apache/hadoop/hbase/client/Admin.disableTable:(Lorg/apache/hadoop/hbase/TableName;)V
     240: getstatic     #2                  // Field ADMIN:Lorg/apache/hadoop/hbase/client/Admin;
     243: aload         7
     245: invokeinterface #259,  2          // InterfaceMethod org/apache/hadoop/hbase/client/Admin.restoreSnapshot:(Ljava/lang/String;)V
     250: ldc_w         #260                // String Total regions count should be 4 after restore.
     253: ldc2_w        #248                // long 4l
     256: aload         6
     258: invokevirtual #98                 // Method org/apache/hadoop/hbase/namespace/NamespaceTableAndRegionInfo.getRegionCount:()I
     261: i2l
     262: invokestatic  #202                // Method org/junit/Assert.assertEquals:(Ljava/lang/String;JJ)V
     265: getstatic     #2                  // Field ADMIN:Lorg/apache/hadoop/hbase/client/Admin;
     268: aload_3
     269: invokeinterface #261,  2          // InterfaceMethod org/apache/hadoop/hbase/client/Admin.enableTable:(Lorg/apache/hadoop/hbase/TableName;)V
     274: getstatic     #2                  // Field ADMIN:Lorg/apache/hadoop/hbase/client/Admin;
     277: aload         7
     279: invokeinterface #239,  2          // InterfaceMethod org/apache/hadoop/hbase/client/Admin.deleteSnapshot:(Ljava/lang/String;)V
     284: return

  public void testRestoreSnapshotQuotaExceed() throws java.lang.Exception;
    Code:
       0: new           #50                 // class java/lang/StringBuilder
       3: dup
       4: invokespecial #51                 // Method java/lang/StringBuilder."<init>":()V
       7: aload_0
       8: getfield      #5                  // Field prefix:Ljava/lang/String;
      11: invokevirtual #52                 // Method java/lang/StringBuilder.append:(Ljava/lang/String;)Ljava/lang/StringBuilder;
      14: ldc_w         #262                // String _testRestoreSnapshotQuotaExceed
      17: invokevirtual #52                 // Method java/lang/StringBuilder.append:(Ljava/lang/String;)Ljava/lang/StringBuilder;
      20: invokevirtual #54                 // Method java/lang/StringBuilder.toString:()Ljava/lang/String;
      23: astore_1
      24: aload_1
      25: invokestatic  #55                 // Method org/apache/hadoop/hbase/NamespaceDescriptor.create:(Ljava/lang/String;)Lorg/apache/hadoop/hbase/NamespaceDescriptor$Builder;
      28: ldc           #57                 // String hbase.namespace.quota.maxregions
      30: ldc           #113                // String 10
      32: invokevirtual #59                 // Method org/apache/hadoop/hbase/NamespaceDescriptor$Builder.addConfiguration:(Ljava/lang/String;Ljava/lang/String;)Lorg/apache/hadoop/hbase/NamespaceDescriptor$Builder;
      35: invokevirtual #62                 // Method org/apache/hadoop/hbase/NamespaceDescriptor$Builder.build:()Lorg/apache/hadoop/hbase/NamespaceDescriptor;
      38: astore_2
      39: getstatic     #2                  // Field ADMIN:Lorg/apache/hadoop/hbase/client/Admin;
      42: aload_2
      43: invokeinterface #63,  2           // InterfaceMethod org/apache/hadoop/hbase/client/Admin.createNamespace:(Lorg/apache/hadoop/hbase/NamespaceDescriptor;)V
      48: getstatic     #2                  // Field ADMIN:Lorg/apache/hadoop/hbase/client/Admin;
      51: aload_1
      52: invokeinterface #65,  2           // InterfaceMethod org/apache/hadoop/hbase/client/Admin.getNamespaceDescriptor:(Ljava/lang/String;)Lorg/apache/hadoop/hbase/NamespaceDescriptor;
      57: astore_3
      58: ldc           #64                 // String Namespace descriptor found null.
      60: aload_3
      61: invokestatic  #66                 // Method org/junit/Assert.assertNotNull:(Ljava/lang/String;Ljava/lang/Object;)V
      64: new           #50                 // class java/lang/StringBuilder
      67: dup
      68: invokespecial #51                 // Method java/lang/StringBuilder."<init>":()V
      71: aload_1
      72: invokevirtual #52                 // Method java/lang/StringBuilder.append:(Ljava/lang/String;)Ljava/lang/StringBuilder;
      75: bipush        58
      77: invokevirtual #75                 // Method java/lang/StringBuilder.append:(C)Ljava/lang/StringBuilder;
      80: ldc           #76                 // String table1
      82: invokevirtual #52                 // Method java/lang/StringBuilder.append:(Ljava/lang/String;)Ljava/lang/StringBuilder;
      85: invokevirtual #54                 // Method java/lang/StringBuilder.toString:()Ljava/lang/String;
      88: invokestatic  #77                 // Method org/apache/hadoop/hbase/TableName.valueOf:(Ljava/lang/String;)Lorg/apache/hadoop/hbase/TableName;
      91: astore        4
      93: new           #73                 // class org/apache/hadoop/hbase/HTableDescriptor
      96: dup
      97: aload         4
      99: invokespecial #78                 // Method org/apache/hadoop/hbase/HTableDescriptor."<init>":(Lorg/apache/hadoop/hbase/TableName;)V
     102: astore        5
     104: new           #70                 // class org/apache/hadoop/hbase/HColumnDescriptor
     107: dup
     108: ldc           #71                 // String fam1
     110: invokespecial #72                 // Method org/apache/hadoop/hbase/HColumnDescriptor."<init>":(Ljava/lang/String;)V
     113: astore        6
     115: aload         5
     117: aload         6
     119: invokevirtual #79                 // Method org/apache/hadoop/hbase/HTableDescriptor.addFamily:(Lorg/apache/hadoop/hbase/HColumnDescriptor;)Lorg/apache/hadoop/hbase/HTableDescriptor;
     122: pop
     123: getstatic     #2                  // Field ADMIN:Lorg/apache/hadoop/hbase/client/Admin;
     126: aload         5
     128: ldc           #83                 // String AAA
     130: invokestatic  #84                 // Method org/apache/hadoop/hbase/util/Bytes.toBytes:(Ljava/lang/String;)[B
     133: ldc           #85                 // String ZZZ
     135: invokestatic  #84                 // Method org/apache/hadoop/hbase/util/Bytes.toBytes:(Ljava/lang/String;)[B
     138: iconst_4
     139: invokeinterface #86,  5           // InterfaceMethod org/apache/hadoop/hbase/client/Admin.createTable:(Lorg/apache/hadoop/hbase/client/TableDescriptor;[B[BI)V
     144: aload_0
     145: aload_1
     146: invokespecial #1                  // Method getNamespaceState:(Ljava/lang/String;)Lorg/apache/hadoop/hbase/namespace/NamespaceTableAndRegionInfo;
     149: astore        7
     151: ldc           #255                // String Intial region count should be 4.
     153: ldc2_w        #248                // long 4l
     156: aload         7
     158: invokevirtual #98                 // Method org/apache/hadoop/hbase/namespace/NamespaceTableAndRegionInfo.getRegionCount:()I
     161: i2l
     162: invokestatic  #202                // Method org/junit/Assert.assertEquals:(Ljava/lang/String;JJ)V
     165: ldc_w         #263                // String snapshot_testRestoreSnapshotQuotaExceed
     168: astore        8
     170: getstatic     #2                  // Field ADMIN:Lorg/apache/hadoop/hbase/client/Admin;
     173: aload         8
     175: aload         4
     177: invokeinterface #237,  3          // InterfaceMethod org/apache/hadoop/hbase/client/Admin.snapshot:(Ljava/lang/String;Lorg/apache/hadoop/hbase/TableName;)V
     182: getstatic     #2                  // Field ADMIN:Lorg/apache/hadoop/hbase/client/Admin;
     185: aload         4
     187: invokeinterface #38,  2           // InterfaceMethod org/apache/hadoop/hbase/client/Admin.disableTable:(Lorg/apache/hadoop/hbase/TableName;)V
     192: getstatic     #2                  // Field ADMIN:Lorg/apache/hadoop/hbase/client/Admin;
     195: aload         4
     197: invokeinterface #231,  2          // InterfaceMethod org/apache/hadoop/hbase/client/Admin.deleteTable:(Lorg/apache/hadoop/hbase/TableName;)V
     202: getstatic     #2                  // Field ADMIN:Lorg/apache/hadoop/hbase/client/Admin;
     205: aload         5
     207: invokeinterface #82,  2           // InterfaceMethod org/apache/hadoop/hbase/client/Admin.createTable:(Lorg/apache/hadoop/hbase/client/TableDescriptor;)V
     212: aload_3
     213: ldc           #57                 // String hbase.namespace.quota.maxregions
     215: ldc           #119                // String 3
     217: invokevirtual #264                // Method org/apache/hadoop/hbase/NamespaceDescriptor.setConfiguration:(Ljava/lang/String;Ljava/lang/String;)V
     220: getstatic     #2                  // Field ADMIN:Lorg/apache/hadoop/hbase/client/Admin;
     223: aload_3
     224: invokeinterface #265,  2          // InterfaceMethod org/apache/hadoop/hbase/client/Admin.modifyNamespace:(Lorg/apache/hadoop/hbase/NamespaceDescriptor;)V
     229: getstatic     #2                  // Field ADMIN:Lorg/apache/hadoop/hbase/client/Admin;
     232: aload         4
     234: invokeinterface #38,  2           // InterfaceMethod org/apache/hadoop/hbase/client/Admin.disableTable:(Lorg/apache/hadoop/hbase/TableName;)V
     239: getstatic     #2                  // Field ADMIN:Lorg/apache/hadoop/hbase/client/Admin;
     242: aload         8
     244: invokeinterface #259,  2          // InterfaceMethod org/apache/hadoop/hbase/client/Admin.restoreSnapshot:(Ljava/lang/String;)V
     249: ldc_w         #266                // String Region quota is exceeded so QuotaExceededException should be thrown but HBaseAdmin wraps IOException into RestoreSnapshotException
     252: invokestatic  #183                // Method org/junit/Assert.fail:(Ljava/lang/String;)V
     255: goto          271
     258: astore        9
     260: aload         9
     262: invokevirtual #268                // Method org/apache/hadoop/hbase/snapshot/RestoreSnapshotException.getCause:()Ljava/lang/Throwable;
     265: instanceof    #269                // class org/apache/hadoop/hbase/quotas/QuotaExceededException
     268: invokestatic  #92                 // Method org/junit/Assert.assertTrue:(Z)V
     271: lconst_1
     272: aload_0
     273: aload_1
     274: invokespecial #1                  // Method getNamespaceState:(Ljava/lang/String;)Lorg/apache/hadoop/hbase/namespace/NamespaceTableAndRegionInfo;
     277: invokevirtual #98                 // Method org/apache/hadoop/hbase/namespace/NamespaceTableAndRegionInfo.getRegionCount:()I
     280: i2l
     281: invokestatic  #69                 // Method org/junit/Assert.assertEquals:(JJ)V
     284: getstatic     #2                  // Field ADMIN:Lorg/apache/hadoop/hbase/client/Admin;
     287: aload         4
     289: invokeinterface #261,  2          // InterfaceMethod org/apache/hadoop/hbase/client/Admin.enableTable:(Lorg/apache/hadoop/hbase/TableName;)V
     294: getstatic     #2                  // Field ADMIN:Lorg/apache/hadoop/hbase/client/Admin;
     297: aload         8
     299: invokeinterface #239,  2          // InterfaceMethod org/apache/hadoop/hbase/client/Admin.deleteSnapshot:(Ljava/lang/String;)V
     304: return
    Exception table:
       from    to  target type
         239   255   258   Class org/apache/hadoop/hbase/snapshot/RestoreSnapshotException

  static org.apache.hadoop.hbase.client.Admin access$000();
    Code:
       0: getstatic     #2                  // Field ADMIN:Lorg/apache/hadoop/hbase/client/Admin;
       3: areturn

  static org.apache.hadoop.hbase.namespace.NamespaceTableAndRegionInfo access$100(org.apache.hadoop.hbase.namespace.TestNamespaceAuditor, java.lang.String) throws org.apache.zookeeper.KeeperException, java.io.IOException;
    Code:
       0: aload_0
       1: aload_1
       2: invokespecial #1                  // Method getNamespaceState:(Ljava/lang/String;)Lorg/apache/hadoop/hbase/namespace/NamespaceTableAndRegionInfo;
       5: areturn

  static {};
    Code:
       0: ldc_w         #274                // class org/apache/hadoop/hbase/namespace/TestNamespaceAuditor
       3: invokestatic  #275                // Method org/apache/hadoop/hbase/HBaseClassTestRule.forClass:(Ljava/lang/Class;)Lorg/apache/hadoop/hbase/HBaseClassTestRule;
       6: putstatic     #276                // Field CLASS_RULE:Lorg/apache/hadoop/hbase/HBaseClassTestRule;
       9: ldc_w         #274                // class org/apache/hadoop/hbase/namespace/TestNamespaceAuditor
      12: invokestatic  #277                // Method org/slf4j/LoggerFactory.getLogger:(Ljava/lang/Class;)Lorg/slf4j/Logger;
      15: putstatic     #107                // Field LOG:Lorg/slf4j/Logger;
      18: new           #278                // class org/apache/hadoop/hbase/HBaseTestingUtility
      21: dup
      22: invokespecial #279                // Method org/apache/hadoop/hbase/HBaseTestingUtility."<init>":()V
      25: putstatic     #6                  // Field UTIL:Lorg/apache/hadoop/hbase/HBaseTestingUtility;
      28: return
}
