Compiled from "TestMultiColumnScannerWithAlgoGZAndNoDataEncoding.java"
public class org.apache.hadoop.hbase.regionserver.TestMultiColumnScannerWithAlgoGZAndNoDataEncoding extends org.apache.hadoop.hbase.regionserver.TestMultiColumnScanner {
  public static final org.apache.hadoop.hbase.HBaseClassTestRule CLASS_RULE;

  public org.apache.hadoop.hbase.regionserver.TestMultiColumnScannerWithAlgoGZAndNoDataEncoding();
    Code:
       0: aload_0
       1: invokespecial #1                  // Method org/apache/hadoop/hbase/regionserver/TestMultiColumnScanner."<init>":()V
       4: return

  public static java.util.Collection<java.lang.Object[]> parameters();
    Code:
       0: getstatic     #2                  // Field org/apache/hadoop/hbase/io/compress/Compression$Algorithm.GZ:Lorg/apache/hadoop/hbase/io/compress/Compression$Algorithm;
       3: iconst_0
       4: invokestatic  #3                  // Method org/apache/hadoop/hbase/regionserver/TestMultiColumnScanner.generateParams:(Lorg/apache/hadoop/hbase/io/compress/Compression$Algorithm;Z)Ljava/util/Collection;
       7: areturn

  static {};
    Code:
       0: ldc           #4                  // class org/apache/hadoop/hbase/regionserver/TestMultiColumnScannerWithAlgoGZAndNoDataEncoding
       2: invokestatic  #5                  // Method org/apache/hadoop/hbase/HBaseClassTestRule.forClass:(Ljava/lang/Class;)Lorg/apache/hadoop/hbase/HBaseClassTestRule;
       5: putstatic     #6                  // Field CLASS_RULE:Lorg/apache/hadoop/hbase/HBaseClassTestRule;
       8: return
}
