Compiled from "TestUser.java"
public class org.apache.hadoop.hbase.security.TestUser {
  public static final org.apache.hadoop.hbase.HBaseClassTestRule CLASS_RULE;

  public org.apache.hadoop.hbase.security.TestUser();
    Code:
       0: aload_0
       1: invokespecial #1                  // Method java/lang/Object."<init>":()V
       4: return

  public void testCreateUserForTestingGroupCache() throws java.lang.Exception;
    Code:
       0: invokestatic  #2                  // Method org/apache/hadoop/hbase/HBaseConfiguration.create:()Lorg/apache/hadoop/conf/Configuration;
       3: astore_1
       4: aload_1
       5: ldc           #3                  // String group_user
       7: iconst_1
       8: anewarray     #4                  // class java/lang/String
      11: dup
      12: iconst_0
      13: ldc           #5                  // String MYGROUP
      15: aastore
      16: invokestatic  #6                  // Method org/apache/hadoop/hbase/security/User.createUserForTesting:(Lorg/apache/hadoop/conf/Configuration;Ljava/lang/String;[Ljava/lang/String;)Lorg/apache/hadoop/hbase/security/User;
      19: astore_2
      20: aload_1
      21: invokestatic  #7                  // Method org/apache/hadoop/hbase/security/UserProvider.instantiate:(Lorg/apache/hadoop/conf/Configuration;)Lorg/apache/hadoop/hbase/security/UserProvider;
      24: astore_3
      25: aload_3
      26: ldc           #3                  // String group_user
      28: invokestatic  #8                  // Method org/apache/hadoop/security/UserGroupInformation.createRemoteUser:(Ljava/lang/String;)Lorg/apache/hadoop/security/UserGroupInformation;
      31: invokevirtual #9                  // Method org/apache/hadoop/hbase/security/UserProvider.create:(Lorg/apache/hadoop/security/UserGroupInformation;)Lorg/apache/hadoop/hbase/security/User;
      34: astore        4
      36: aload_2
      37: invokevirtual #10                 // Method org/apache/hadoop/hbase/security/User.getGroupNames:()[Ljava/lang/String;
      40: aload         4
      42: invokevirtual #10                 // Method org/apache/hadoop/hbase/security/User.getGroupNames:()[Ljava/lang/String;
      45: invokestatic  #11                 // Method org/junit/Assert.assertArrayEquals:([Ljava/lang/Object;[Ljava/lang/Object;)V
      48: return

  public void testCacheGetGroups() throws java.lang.Exception;
    Code:
       0: invokestatic  #2                  // Method org/apache/hadoop/hbase/HBaseConfiguration.create:()Lorg/apache/hadoop/conf/Configuration;
       3: astore_1
       4: aload_1
       5: invokestatic  #7                  // Method org/apache/hadoop/hbase/security/UserProvider.instantiate:(Lorg/apache/hadoop/conf/Configuration;)Lorg/apache/hadoop/hbase/security/UserProvider;
       8: astore_2
       9: ldc           #12                 // String kklvfnvhdhcenfnniilggljhdecjhidkle
      11: astore_3
      12: aload_3
      13: invokestatic  #8                  // Method org/apache/hadoop/security/UserGroupInformation.createRemoteUser:(Ljava/lang/String;)Lorg/apache/hadoop/security/UserGroupInformation;
      16: astore        4
      18: aload_3
      19: invokestatic  #8                  // Method org/apache/hadoop/security/UserGroupInformation.createRemoteUser:(Ljava/lang/String;)Lorg/apache/hadoop/security/UserGroupInformation;
      22: astore        5
      24: aload_2
      25: aload         4
      27: invokevirtual #9                  // Method org/apache/hadoop/hbase/security/UserProvider.create:(Lorg/apache/hadoop/security/UserGroupInformation;)Lorg/apache/hadoop/hbase/security/User;
      30: astore        6
      32: aload_2
      33: aload         5
      35: invokevirtual #9                  // Method org/apache/hadoop/hbase/security/UserProvider.create:(Lorg/apache/hadoop/security/UserGroupInformation;)Lorg/apache/hadoop/hbase/security/User;
      38: astore        7
      40: aload         6
      42: invokevirtual #10                 // Method org/apache/hadoop/hbase/security/User.getGroupNames:()[Ljava/lang/String;
      45: aload         7
      47: invokevirtual #10                 // Method org/apache/hadoop/hbase/security/User.getGroupNames:()[Ljava/lang/String;
      50: invokestatic  #11                 // Method org/junit/Assert.assertArrayEquals:([Ljava/lang/Object;[Ljava/lang/Object;)V
      53: aload         6
      55: invokevirtual #10                 // Method org/apache/hadoop/hbase/security/User.getGroupNames:()[Ljava/lang/String;
      58: aload         7
      60: invokevirtual #10                 // Method org/apache/hadoop/hbase/security/User.getGroupNames:()[Ljava/lang/String;
      63: if_acmpne     70
      66: iconst_1
      67: goto          71
      70: iconst_0
      71: invokestatic  #13                 // Method org/junit/Assert.assertTrue:(Z)V
      74: lconst_0
      75: aload         4
      77: invokevirtual #14                 // Method org/apache/hadoop/security/UserGroupInformation.getGroupNames:()[Ljava/lang/String;
      80: arraylength
      81: i2l
      82: invokestatic  #15                 // Method org/junit/Assert.assertEquals:(JJ)V
      85: return

  public void testCacheGetGroupsRoot() throws java.lang.Exception;
    Code:
       0: getstatic     #16                 // Field org/apache/commons/lang3/SystemUtils.IS_OS_WINDOWS:Z
       3: ifne          80
       6: invokestatic  #2                  // Method org/apache/hadoop/hbase/HBaseConfiguration.create:()Lorg/apache/hadoop/conf/Configuration;
       9: astore_1
      10: aload_1
      11: invokestatic  #7                  // Method org/apache/hadoop/hbase/security/UserProvider.instantiate:(Lorg/apache/hadoop/conf/Configuration;)Lorg/apache/hadoop/hbase/security/UserProvider;
      14: astore_2
      15: ldc           #17                 // String root
      17: astore_3
      18: aload_3
      19: invokestatic  #8                  // Method org/apache/hadoop/security/UserGroupInformation.createRemoteUser:(Ljava/lang/String;)Lorg/apache/hadoop/security/UserGroupInformation;
      22: astore        4
      24: aload_3
      25: invokestatic  #8                  // Method org/apache/hadoop/security/UserGroupInformation.createRemoteUser:(Ljava/lang/String;)Lorg/apache/hadoop/security/UserGroupInformation;
      28: astore        5
      30: aload_2
      31: aload         4
      33: invokevirtual #9                  // Method org/apache/hadoop/hbase/security/UserProvider.create:(Lorg/apache/hadoop/security/UserGroupInformation;)Lorg/apache/hadoop/hbase/security/User;
      36: astore        6
      38: aload_2
      39: aload         5
      41: invokevirtual #9                  // Method org/apache/hadoop/hbase/security/UserProvider.create:(Lorg/apache/hadoop/security/UserGroupInformation;)Lorg/apache/hadoop/hbase/security/User;
      44: astore        7
      46: aload         6
      48: invokevirtual #10                 // Method org/apache/hadoop/hbase/security/User.getGroupNames:()[Ljava/lang/String;
      51: aload         7
      53: invokevirtual #10                 // Method org/apache/hadoop/hbase/security/User.getGroupNames:()[Ljava/lang/String;
      56: invokestatic  #11                 // Method org/junit/Assert.assertArrayEquals:([Ljava/lang/Object;[Ljava/lang/Object;)V
      59: aload         4
      61: invokevirtual #14                 // Method org/apache/hadoop/security/UserGroupInformation.getGroupNames:()[Ljava/lang/String;
      64: astore        8
      66: aload         8
      68: arraylength
      69: ifle          76
      72: iconst_1
      73: goto          77
      76: iconst_0
      77: invokestatic  #13                 // Method org/junit/Assert.assertTrue:(Z)V
      80: return

  public void testBasicAttributes() throws java.lang.Exception;
    Code:
       0: invokestatic  #2                  // Method org/apache/hadoop/hbase/HBaseConfiguration.create:()Lorg/apache/hadoop/conf/Configuration;
       3: astore_1
       4: aload_1
       5: ldc           #18                 // String simple
       7: iconst_1
       8: anewarray     #4                  // class java/lang/String
      11: dup
      12: iconst_0
      13: ldc           #19                 // String foo
      15: aastore
      16: invokestatic  #6                  // Method org/apache/hadoop/hbase/security/User.createUserForTesting:(Lorg/apache/hadoop/conf/Configuration;Ljava/lang/String;[Ljava/lang/String;)Lorg/apache/hadoop/hbase/security/User;
      19: astore_2
      20: ldc           #20                 // String Username should match
      22: ldc           #18                 // String simple
      24: aload_2
      25: invokevirtual #21                 // Method org/apache/hadoop/hbase/security/User.getName:()Ljava/lang/String;
      28: invokestatic  #22                 // Method org/junit/Assert.assertEquals:(Ljava/lang/String;Ljava/lang/Object;Ljava/lang/Object;)V
      31: ldc           #23                 // String Short username should match
      33: ldc           #18                 // String simple
      35: aload_2
      36: invokevirtual #24                 // Method org/apache/hadoop/hbase/security/User.getShortName:()Ljava/lang/String;
      39: invokestatic  #22                 // Method org/junit/Assert.assertEquals:(Ljava/lang/String;Ljava/lang/Object;Ljava/lang/Object;)V
      42: return

  public void testRunAs() throws java.lang.Exception;
    Code:
       0: invokestatic  #2                  // Method org/apache/hadoop/hbase/HBaseConfiguration.create:()Lorg/apache/hadoop/conf/Configuration;
       3: astore_1
       4: aload_1
       5: ldc           #25                 // String testuser
       7: iconst_1
       8: anewarray     #4                  // class java/lang/String
      11: dup
      12: iconst_0
      13: ldc           #19                 // String foo
      15: aastore
      16: invokestatic  #6                  // Method org/apache/hadoop/hbase/security/User.createUserForTesting:(Lorg/apache/hadoop/conf/Configuration;Ljava/lang/String;[Ljava/lang/String;)Lorg/apache/hadoop/hbase/security/User;
      19: astore_2
      20: new           #26                 // class org/apache/hadoop/hbase/security/TestUser$1
      23: dup
      24: aload_0
      25: invokespecial #27                 // Method org/apache/hadoop/hbase/security/TestUser$1."<init>":(Lorg/apache/hadoop/hbase/security/TestUser;)V
      28: astore_3
      29: aload_2
      30: aload_3
      31: invokevirtual #28                 // Method org/apache/hadoop/hbase/security/User.runAs:(Ljava/security/PrivilegedExceptionAction;)Ljava/lang/Object;
      34: checkcast     #4                  // class java/lang/String
      37: astore        4
      39: ldc           #29                 // String Current user within runAs() should match
      41: ldc           #25                 // String testuser
      43: aload         4
      45: invokestatic  #22                 // Method org/junit/Assert.assertEquals:(Ljava/lang/String;Ljava/lang/Object;Ljava/lang/Object;)V
      48: aload_1
      49: ldc           #30                 // String testuser2
      51: iconst_1
      52: anewarray     #4                  // class java/lang/String
      55: dup
      56: iconst_0
      57: ldc           #19                 // String foo
      59: aastore
      60: invokestatic  #6                  // Method org/apache/hadoop/hbase/security/User.createUserForTesting:(Lorg/apache/hadoop/conf/Configuration;Ljava/lang/String;[Ljava/lang/String;)Lorg/apache/hadoop/hbase/security/User;
      63: astore        5
      65: aload         5
      67: aload_3
      68: invokevirtual #28                 // Method org/apache/hadoop/hbase/security/User.runAs:(Ljava/security/PrivilegedExceptionAction;)Ljava/lang/Object;
      71: checkcast     #4                  // class java/lang/String
      74: astore        6
      76: ldc           #31                 // String Second username should match second user
      78: ldc           #30                 // String testuser2
      80: aload         6
      82: invokestatic  #22                 // Method org/junit/Assert.assertEquals:(Ljava/lang/String;Ljava/lang/Object;Ljava/lang/Object;)V
      85: aload_2
      86: new           #32                 // class org/apache/hadoop/hbase/security/TestUser$2
      89: dup
      90: aload_0
      91: invokespecial #33                 // Method org/apache/hadoop/hbase/security/TestUser$2."<init>":(Lorg/apache/hadoop/hbase/security/TestUser;)V
      94: invokevirtual #28                 // Method org/apache/hadoop/hbase/security/User.runAs:(Ljava/security/PrivilegedExceptionAction;)Ljava/lang/Object;
      97: checkcast     #4                  // class java/lang/String
     100: astore        4
     102: ldc           #34                 // String User name in runAs() should match
     104: ldc           #25                 // String testuser
     106: aload         4
     108: invokestatic  #22                 // Method org/junit/Assert.assertEquals:(Ljava/lang/String;Ljava/lang/Object;Ljava/lang/Object;)V
     111: aload         5
     113: new           #35                 // class org/apache/hadoop/hbase/security/TestUser$3
     116: dup
     117: aload_0
     118: aload_2
     119: aload_3
     120: invokespecial #36                 // Method org/apache/hadoop/hbase/security/TestUser$3."<init>":(Lorg/apache/hadoop/hbase/security/TestUser;Lorg/apache/hadoop/hbase/security/User;Ljava/security/PrivilegedExceptionAction;)V
     123: invokevirtual #28                 // Method org/apache/hadoop/hbase/security/User.runAs:(Ljava/security/PrivilegedExceptionAction;)Ljava/lang/Object;
     126: pop
     127: aload_2
     128: new           #37                 // class org/apache/hadoop/hbase/security/TestUser$4
     131: dup
     132: aload_0
     133: invokespecial #38                 // Method org/apache/hadoop/hbase/security/TestUser$4."<init>":(Lorg/apache/hadoop/hbase/security/TestUser;)V
     136: invokevirtual #39                 // Method org/apache/hadoop/hbase/security/User.runAs:(Ljava/security/PrivilegedAction;)Ljava/lang/Object;
     139: checkcast     #4                  // class java/lang/String
     142: astore        4
     144: ldc           #29                 // String Current user within runAs() should match
     146: ldc           #25                 // String testuser
     148: aload         4
     150: invokestatic  #22                 // Method org/junit/Assert.assertEquals:(Ljava/lang/String;Ljava/lang/Object;Ljava/lang/Object;)V
     153: return

  public void testGetCurrent() throws java.lang.Exception;
    Code:
       0: invokestatic  #40                 // Method org/apache/hadoop/hbase/security/User.getCurrent:()Lorg/apache/hadoop/hbase/security/User;
       3: astore_1
       4: aload_1
       5: getfield      #41                 // Field org/apache/hadoop/hbase/security/User.ugi:Lorg/apache/hadoop/security/UserGroupInformation;
       8: invokestatic  #42                 // Method org/junit/Assert.assertNotNull:(Ljava/lang/Object;)V
      11: getstatic     #43                 // Field LOG:Lorg/slf4j/Logger;
      14: new           #44                 // class java/lang/StringBuilder
      17: dup
      18: invokespecial #45                 // Method java/lang/StringBuilder."<init>":()V
      21: ldc           #46                 // String User1 is
      23: invokevirtual #47                 // Method java/lang/StringBuilder.append:(Ljava/lang/String;)Ljava/lang/StringBuilder;
      26: aload_1
      27: invokevirtual #21                 // Method org/apache/hadoop/hbase/security/User.getName:()Ljava/lang/String;
      30: invokevirtual #47                 // Method java/lang/StringBuilder.append:(Ljava/lang/String;)Ljava/lang/StringBuilder;
      33: invokevirtual #48                 // Method java/lang/StringBuilder.toString:()Ljava/lang/String;
      36: invokeinterface #49,  2           // InterfaceMethod org/slf4j/Logger.debug:(Ljava/lang/String;)V
      41: iconst_0
      42: istore_2
      43: iload_2
      44: bipush        100
      46: if_icmpge     92
      49: invokestatic  #40                 // Method org/apache/hadoop/hbase/security/User.getCurrent:()Lorg/apache/hadoop/hbase/security/User;
      52: astore_3
      53: aload_3
      54: invokestatic  #42                 // Method org/junit/Assert.assertNotNull:(Ljava/lang/Object;)V
      57: aload_1
      58: invokevirtual #21                 // Method org/apache/hadoop/hbase/security/User.getName:()Ljava/lang/String;
      61: aload_3
      62: invokevirtual #21                 // Method org/apache/hadoop/hbase/security/User.getName:()Ljava/lang/String;
      65: invokestatic  #50                 // Method org/junit/Assert.assertEquals:(Ljava/lang/Object;Ljava/lang/Object;)V
      68: aload_1
      69: aload_3
      70: invokestatic  #50                 // Method org/junit/Assert.assertEquals:(Ljava/lang/Object;Ljava/lang/Object;)V
      73: aload_1
      74: invokevirtual #51                 // Method org/apache/hadoop/hbase/security/User.hashCode:()I
      77: i2l
      78: aload_3
      79: invokevirtual #51                 // Method org/apache/hadoop/hbase/security/User.hashCode:()I
      82: i2l
      83: invokestatic  #15                 // Method org/junit/Assert.assertEquals:(JJ)V
      86: iinc          2, 1
      89: goto          43
      92: return

  public void testUserGroupNames() throws java.lang.Exception;
    Code:
       0: ldc           #25                 // String testuser
       2: astore_1
       3: ldc           #52                 // String group
       5: invokestatic  #53                 // Method org/apache/hbase/thirdparty/com/google/common/collect/ImmutableSet.of:(Ljava/lang/Object;)Lorg/apache/hbase/thirdparty/com/google/common/collect/ImmutableSet;
       8: astore_2
       9: invokestatic  #2                  // Method org/apache/hadoop/hbase/HBaseConfiguration.create:()Lorg/apache/hadoop/conf/Configuration;
      12: astore_3
      13: aload_3
      14: ldc           #25                 // String testuser
      16: aload_2
      17: aload_2
      18: invokevirtual #54                 // Method org/apache/hbase/thirdparty/com/google/common/collect/ImmutableSet.size:()I
      21: anewarray     #4                  // class java/lang/String
      24: invokevirtual #55                 // Method org/apache/hbase/thirdparty/com/google/common/collect/ImmutableSet.toArray:([Ljava/lang/Object;)[Ljava/lang/Object;
      27: checkcast     #56                 // class "[Ljava/lang/String;"
      30: invokestatic  #6                  // Method org/apache/hadoop/hbase/security/User.createUserForTesting:(Lorg/apache/hadoop/conf/Configuration;Ljava/lang/String;[Ljava/lang/String;)Lorg/apache/hadoop/hbase/security/User;
      33: astore        4
      35: aload_0
      36: aload         4
      38: aload_2
      39: invokespecial #57                 // Method assertUserGroup:(Lorg/apache/hadoop/hbase/security/User;Lorg/apache/hbase/thirdparty/com/google/common/collect/ImmutableSet;)V
      42: ldc           #52                 // String group
      44: ldc           #58                 // String group1
      46: ldc           #59                 // String group2
      48: invokestatic  #60                 // Method org/apache/hbase/thirdparty/com/google/common/collect/ImmutableSet.of:(Ljava/lang/Object;Ljava/lang/Object;Ljava/lang/Object;)Lorg/apache/hbase/thirdparty/com/google/common/collect/ImmutableSet;
      51: astore        5
      53: aload_3
      54: ldc           #25                 // String testuser
      56: aload         5
      58: aload         5
      60: invokevirtual #54                 // Method org/apache/hbase/thirdparty/com/google/common/collect/ImmutableSet.size:()I
      63: anewarray     #4                  // class java/lang/String
      66: invokevirtual #55                 // Method org/apache/hbase/thirdparty/com/google/common/collect/ImmutableSet.toArray:([Ljava/lang/Object;)[Ljava/lang/Object;
      69: checkcast     #56                 // class "[Ljava/lang/String;"
      72: invokestatic  #6                  // Method org/apache/hadoop/hbase/security/User.createUserForTesting:(Lorg/apache/hadoop/conf/Configuration;Ljava/lang/String;[Ljava/lang/String;)Lorg/apache/hadoop/hbase/security/User;
      75: astore        4
      77: aload_0
      78: aload         4
      80: aload         5
      82: invokespecial #57                 // Method assertUserGroup:(Lorg/apache/hadoop/hbase/security/User;Lorg/apache/hbase/thirdparty/com/google/common/collect/ImmutableSet;)V
      85: return

  public void testSecurityForNonSecureHadoop();
    Code:
       0: ldc           #68                 // String Security should be disable in non-secure Hadoop
       2: invokestatic  #69                 // Method org/apache/hadoop/hbase/security/User.isSecurityEnabled:()Z
       5: invokestatic  #70                 // Method org/junit/Assert.assertFalse:(Ljava/lang/String;Z)V
       8: invokestatic  #2                  // Method org/apache/hadoop/hbase/HBaseConfiguration.create:()Lorg/apache/hadoop/conf/Configuration;
      11: astore_1
      12: aload_1
      13: ldc           #72                 // String hadoop.security.authentication
      15: ldc           #73                 // String kerberos
      17: invokevirtual #74                 // Method org/apache/hadoop/conf/Configuration.set:(Ljava/lang/String;Ljava/lang/String;)V
      20: aload_1
      21: ldc           #76                 // String hbase.security.authentication
      23: ldc           #73                 // String kerberos
      25: invokevirtual #74                 // Method org/apache/hadoop/conf/Configuration.set:(Ljava/lang/String;Ljava/lang/String;)V
      28: ldc           #77                 // String Security should be enabled
      30: aload_1
      31: invokestatic  #78                 // Method org/apache/hadoop/hbase/security/User.isHBaseSecurityEnabled:(Lorg/apache/hadoop/conf/Configuration;)Z
      34: invokestatic  #65                 // Method org/junit/Assert.assertTrue:(Ljava/lang/String;Z)V
      37: invokestatic  #2                  // Method org/apache/hadoop/hbase/HBaseConfiguration.create:()Lorg/apache/hadoop/conf/Configuration;
      40: astore_1
      41: aload_1
      42: ldc           #72                 // String hadoop.security.authentication
      44: ldc           #73                 // String kerberos
      46: invokevirtual #74                 // Method org/apache/hadoop/conf/Configuration.set:(Ljava/lang/String;Ljava/lang/String;)V
      49: ldc           #79                 // String HBase security should not be enabled if hbase.security.authentication is not set accordingly
      51: aload_1
      52: invokestatic  #78                 // Method org/apache/hadoop/hbase/security/User.isHBaseSecurityEnabled:(Lorg/apache/hadoop/conf/Configuration;)Z
      55: invokestatic  #70                 // Method org/junit/Assert.assertFalse:(Ljava/lang/String;Z)V
      58: invokestatic  #2                  // Method org/apache/hadoop/hbase/HBaseConfiguration.create:()Lorg/apache/hadoop/conf/Configuration;
      61: astore_1
      62: aload_1
      63: ldc           #76                 // String hbase.security.authentication
      65: ldc           #73                 // String kerberos
      67: invokevirtual #74                 // Method org/apache/hadoop/conf/Configuration.set:(Ljava/lang/String;Ljava/lang/String;)V
      70: ldc           #80                 // String HBase security should be enabled regardless of underlying HDFS settings
      72: aload_1
      73: invokestatic  #78                 // Method org/apache/hadoop/hbase/security/User.isHBaseSecurityEnabled:(Lorg/apache/hadoop/conf/Configuration;)Z
      76: invokestatic  #65                 // Method org/junit/Assert.assertTrue:(Ljava/lang/String;Z)V
      79: return

  static {};
    Code:
       0: ldc           #81                 // class org/apache/hadoop/hbase/security/TestUser
       2: invokestatic  #82                 // Method org/apache/hadoop/hbase/HBaseClassTestRule.forClass:(Ljava/lang/Class;)Lorg/apache/hadoop/hbase/HBaseClassTestRule;
       5: putstatic     #83                 // Field CLASS_RULE:Lorg/apache/hadoop/hbase/HBaseClassTestRule;
       8: ldc           #81                 // class org/apache/hadoop/hbase/security/TestUser
      10: invokestatic  #84                 // Method org/slf4j/LoggerFactory.getLogger:(Ljava/lang/Class;)Lorg/slf4j/Logger;
      13: putstatic     #43                 // Field LOG:Lorg/slf4j/Logger;
      16: return
}
