Compiled from "TestMultiSlaveReplication.java"
class org.apache.hadoop.hbase.replication.TestMultiSlaveReplication$1 implements org.apache.hadoop.hbase.regionserver.wal.WALActionsListener {
  final java.util.concurrent.CountDownLatch val$latch;

  final org.apache.hadoop.hbase.replication.TestMultiSlaveReplication this$0;

  org.apache.hadoop.hbase.replication.TestMultiSlaveReplication$1(org.apache.hadoop.hbase.replication.TestMultiSlaveReplication, java.util.concurrent.CountDownLatch);
    Code:
       0: aload_0
       1: aload_1
       2: putfield      #1                  // Field this$0:Lorg/apache/hadoop/hbase/replication/TestMultiSlaveReplication;
       5: aload_0
       6: aload_2
       7: putfield      #2                  // Field val$latch:Ljava/util/concurrent/CountDownLatch;
      10: aload_0
      11: invokespecial #3                  // Method java/lang/Object."<init>":()V
      14: return

  public void postLogRoll(org.apache.hadoop.fs.Path, org.apache.hadoop.fs.Path) throws java.io.IOException;
    Code:
       0: aload_0
       1: getfield      #2                  // Field val$latch:Ljava/util/concurrent/CountDownLatch;
       4: invokevirtual #4                  // Method java/util/concurrent/CountDownLatch.countDown:()V
       7: return
}
