Compiled from "TestZKConfig.java"
public class org.apache.hadoop.hbase.zookeeper.TestZKConfig {
  public static final org.apache.hadoop.hbase.HBaseClassTestRule CLASS_RULE;

  public org.apache.hadoop.hbase.zookeeper.TestZKConfig();
    Code:
       0: aload_0
       1: invokespecial #1                  // Method java/lang/Object."<init>":()V
       4: return

  public void testZKConfigLoading() throws java.lang.Exception;
    Code:
       0: invokestatic  #2                  // Method org/apache/hadoop/hbase/HBaseConfiguration.create:()Lorg/apache/hadoop/conf/Configuration;
       3: astore_1
       4: aload_1
       5: ldc           #4                  // String hbase.zookeeper.property.clientPort
       7: sipush        2181
      10: invokevirtual #5                  // Method org/apache/hadoop/conf/Configuration.setInt:(Ljava/lang/String;I)V
      13: aload_1
      14: invokestatic  #6                  // Method org/apache/hadoop/hbase/zookeeper/ZKConfig.makeZKProps:(Lorg/apache/hadoop/conf/Configuration;)Ljava/util/Properties;
      17: astore_2
      18: ldc           #7                  // String Property client port should have been default from the HBase config
      20: ldc           #8                  // String 2181
      22: aload_2
      23: ldc           #9                  // String clientPort
      25: invokevirtual #10                 // Method java/util/Properties.getProperty:(Ljava/lang/String;)Ljava/lang/String;
      28: invokestatic  #11                 // Method org/junit/Assert.assertEquals:(Ljava/lang/String;Ljava/lang/Object;Ljava/lang/Object;)V
      31: return

  public void testGetZooKeeperClusterKey();
    Code:
       0: invokestatic  #2                  // Method org/apache/hadoop/hbase/HBaseConfiguration.create:()Lorg/apache/hadoop/conf/Configuration;
       3: astore_1
       4: aload_1
       5: ldc           #12                 // String hbase.zookeeper.quorum
       7: ldc           #13                 // String \tlocalhost\n
       9: invokevirtual #14                 // Method org/apache/hadoop/conf/Configuration.set:(Ljava/lang/String;Ljava/lang/String;)V
      12: aload_1
      13: ldc           #4                  // String hbase.zookeeper.property.clientPort
      15: ldc           #15                 // String 3333
      17: invokevirtual #14                 // Method org/apache/hadoop/conf/Configuration.set:(Ljava/lang/String;Ljava/lang/String;)V
      20: aload_1
      21: ldc           #16                 // String zookeeper.znode.parent
      23: ldc           #17                 // String hbase
      25: invokevirtual #14                 // Method org/apache/hadoop/conf/Configuration.set:(Ljava/lang/String;Ljava/lang/String;)V
      28: aload_1
      29: ldc           #18                 // String test
      31: invokestatic  #19                 // Method org/apache/hadoop/hbase/zookeeper/ZKConfig.getZooKeeperClusterKey:(Lorg/apache/hadoop/conf/Configuration;Ljava/lang/String;)Ljava/lang/String;
      34: astore_2
      35: aload_2
      36: ldc           #20                 // String \t
      38: invokevirtual #21                 // Method java/lang/String.contains:(Ljava/lang/CharSequence;)Z
      41: ifne          57
      44: aload_2
      45: ldc           #22                 // String \n
      47: invokevirtual #21                 // Method java/lang/String.contains:(Ljava/lang/CharSequence;)Z
      50: ifne          57
      53: iconst_1
      54: goto          58
      57: iconst_0
      58: invokestatic  #23                 // Method org/junit/Assert.assertTrue:(Z)V
      61: ldc           #24                 // String localhost:3333:hbase,test
      63: aload_2
      64: invokestatic  #25                 // Method org/junit/Assert.assertEquals:(Ljava/lang/Object;Ljava/lang/Object;)V
      67: return

  public void testClusterKey() throws java.lang.Exception;
    Code:
       0: aload_0
       1: ldc           #26                 // String server
       3: sipush        2181
       6: ldc           #27                 // String /hbase
       8: invokespecial #28                 // Method testKey:(Ljava/lang/String;ILjava/lang/String;)V
      11: aload_0
      12: ldc           #29                 // String server1,server2,server3
      14: sipush        2181
      17: ldc           #27                 // String /hbase
      19: invokespecial #28                 // Method testKey:(Ljava/lang/String;ILjava/lang/String;)V
      22: ldc           #30                 // String 2181:/hbase
      24: invokestatic  #31                 // Method org/apache/hadoop/hbase/zookeeper/ZKConfig.validateClusterKey:(Ljava/lang/String;)V
      27: goto          31
      30: astore_1
      31: return
    Exception table:
       from    to  target type
          22    27    30   Class java/io/IOException

  public void testClusterKeyWithMultiplePorts() throws java.lang.Exception;
    Code:
       0: aload_0
       1: ldc           #33                 // String server1:2182
       3: sipush        2181
       6: ldc           #27                 // String /hbase
       8: iconst_1
       9: invokestatic  #34                 // Method java/lang/Boolean.valueOf:(Z)Ljava/lang/Boolean;
      12: invokespecial #35                 // Method testKey:(Ljava/lang/String;ILjava/lang/String;Ljava/lang/Boolean;)V
      15: aload_0
      16: ldc           #36                 // String server1:2182,server2:2183,server3:2184
      18: sipush        2181
      21: ldc           #27                 // String /hbase
      23: iconst_1
      24: invokestatic  #34                 // Method java/lang/Boolean.valueOf:(Z)Ljava/lang/Boolean;
      27: invokespecial #35                 // Method testKey:(Ljava/lang/String;ILjava/lang/String;Ljava/lang/Boolean;)V
      30: aload_0
      31: ldc           #37                 // String server1:2182,server2,server3:2184
      33: sipush        2181
      36: ldc           #27                 // String /hbase
      38: iconst_1
      39: invokestatic  #34                 // Method java/lang/Boolean.valueOf:(Z)Ljava/lang/Boolean;
      42: invokespecial #35                 // Method testKey:(Ljava/lang/String;ILjava/lang/String;Ljava/lang/Boolean;)V
      45: aload_0
      46: ldc           #38                 // String server1:2182,server2:2183,server3
      48: sipush        2181
      51: ldc           #27                 // String /hbase
      53: iconst_1
      54: invokestatic  #34                 // Method java/lang/Boolean.valueOf:(Z)Ljava/lang/Boolean;
      57: invokespecial #35                 // Method testKey:(Ljava/lang/String;ILjava/lang/String;Ljava/lang/Boolean;)V
      60: aload_0
      61: ldc           #39                 // String server1:2182,server2,server3:2184,server4
      63: sipush        2181
      66: ldc           #27                 // String /hbase
      68: iconst_1
      69: invokestatic  #34                 // Method java/lang/Boolean.valueOf:(Z)Ljava/lang/Boolean;
      72: invokespecial #35                 // Method testKey:(Ljava/lang/String;ILjava/lang/String;Ljava/lang/Boolean;)V
      75: aload_0
      76: ldc           #40                 // String server1:2182,server1:2183,server1
      78: sipush        2181
      81: ldc           #27                 // String /hbase
      83: iconst_1
      84: invokestatic  #34                 // Method java/lang/Boolean.valueOf:(Z)Ljava/lang/Boolean;
      87: invokespecial #35                 // Method testKey:(Ljava/lang/String;ILjava/lang/String;Ljava/lang/Boolean;)V
      90: aload_0
      91: ldc           #41                 // String server1:2182,server2:2183,server1
      93: sipush        2181
      96: ldc           #27                 // String /hbase
      98: iconst_1
      99: invokestatic  #34                 // Method java/lang/Boolean.valueOf:(Z)Ljava/lang/Boolean;
     102: invokespecial #35                 // Method testKey:(Ljava/lang/String;ILjava/lang/String;Ljava/lang/Boolean;)V
     105: return

  static {};
    Code:
       0: ldc           #62                 // class org/apache/hadoop/hbase/zookeeper/TestZKConfig
       2: invokestatic  #63                 // Method org/apache/hadoop/hbase/HBaseClassTestRule.forClass:(Ljava/lang/Class;)Lorg/apache/hadoop/hbase/HBaseClassTestRule;
       5: putstatic     #64                 // Field CLASS_RULE:Lorg/apache/hadoop/hbase/HBaseClassTestRule;
       8: return
}
