Compiled from "TestAccessControlFilter.java"
public class org.apache.hadoop.hbase.security.access.TestAccessControlFilter extends org.apache.hadoop.hbase.security.access.SecureTestUtil {
  public static final org.apache.hadoop.hbase.HBaseClassTestRule CLASS_RULE;

  public org.junit.rules.TestName name;

  public org.apache.hadoop.hbase.security.access.TestAccessControlFilter();
    Code:
       0: aload_0
       1: invokespecial #6                  // Method org/apache/hadoop/hbase/security/access/SecureTestUtil."<init>":()V
       4: aload_0
       5: new           #7                  // class org/junit/rules/TestName
       8: dup
       9: invokespecial #8                  // Method org/junit/rules/TestName."<init>":()V
      12: putfield      #9                  // Field name:Lorg/junit/rules/TestName;
      15: return

  public void setup();
    Code:
       0: aload_0
       1: getfield      #9                  // Field name:Lorg/junit/rules/TestName;
       4: invokevirtual #10                 // Method org/junit/rules/TestName.getMethodName:()Ljava/lang/String;
       7: invokestatic  #11                 // Method org/apache/hadoop/hbase/TableName.valueOf:(Ljava/lang/String;)Lorg/apache/hadoop/hbase/TableName;
      10: putstatic     #4                  // Field TABLE:Lorg/apache/hadoop/hbase/TableName;
      13: return

  public static void setupBeforeClass() throws java.lang.Exception;
    Code:
       0: new           #12                 // class org/apache/hadoop/hbase/HBaseTestingUtility
       3: dup
       4: invokespecial #13                 // Method org/apache/hadoop/hbase/HBaseTestingUtility."<init>":()V
       7: putstatic     #5                  // Field TEST_UTIL:Lorg/apache/hadoop/hbase/HBaseTestingUtility;
      10: getstatic     #5                  // Field TEST_UTIL:Lorg/apache/hadoop/hbase/HBaseTestingUtility;
      13: invokevirtual #14                 // Method org/apache/hadoop/hbase/HBaseTestingUtility.getConfiguration:()Lorg/apache/hadoop/conf/Configuration;
      16: astore_0
      17: aload_0
      18: ldc           #16                 // String hbase.regionserver.metahandler.count
      20: bipush        10
      22: invokevirtual #17                 // Method org/apache/hadoop/conf/Configuration.setInt:(Ljava/lang/String;I)V
      25: aload_0
      26: invokestatic  #18                 // Method enableSecurity:(Lorg/apache/hadoop/conf/Configuration;)V
      29: aload_0
      30: invokestatic  #19                 // Method verifyConfiguration:(Lorg/apache/hadoop/conf/Configuration;)V
      33: aload_0
      34: ldc           #21                 // String hbase.security.access.early_out
      36: iconst_0
      37: invokevirtual #22                 // Method org/apache/hadoop/conf/Configuration.setBoolean:(Ljava/lang/String;Z)V
      40: getstatic     #5                  // Field TEST_UTIL:Lorg/apache/hadoop/hbase/HBaseTestingUtility;
      43: invokevirtual #23                 // Method org/apache/hadoop/hbase/HBaseTestingUtility.startMiniCluster:()Lorg/apache/hadoop/hbase/MiniHBaseCluster;
      46: pop
      47: getstatic     #5                  // Field TEST_UTIL:Lorg/apache/hadoop/hbase/HBaseTestingUtility;
      50: getstatic     #24                 // Field org/apache/hadoop/hbase/security/access/PermissionStorage.ACL_TABLE_NAME:Lorg/apache/hadoop/hbase/TableName;
      53: invokevirtual #25                 // Method org/apache/hadoop/hbase/TableName.getName:()[B
      56: ldc2_w        #26                 // long 50000l
      59: invokevirtual #28                 // Method org/apache/hadoop/hbase/HBaseTestingUtility.waitTableEnabled:([BJ)V
      62: aload_0
      63: ldc           #29                 // String reader
      65: iconst_0
      66: anewarray     #30                 // class java/lang/String
      69: invokestatic  #31                 // Method org/apache/hadoop/hbase/security/User.createUserForTesting:(Lorg/apache/hadoop/conf/Configuration;Ljava/lang/String;[Ljava/lang/String;)Lorg/apache/hadoop/hbase/security/User;
      72: putstatic     #32                 // Field READER:Lorg/apache/hadoop/hbase/security/User;
      75: aload_0
      76: ldc           #33                 // String limited
      78: iconst_0
      79: anewarray     #30                 // class java/lang/String
      82: invokestatic  #31                 // Method org/apache/hadoop/hbase/security/User.createUserForTesting:(Lorg/apache/hadoop/conf/Configuration;Ljava/lang/String;[Ljava/lang/String;)Lorg/apache/hadoop/hbase/security/User;
      85: putstatic     #34                 // Field LIMITED:Lorg/apache/hadoop/hbase/security/User;
      88: aload_0
      89: ldc           #35                 // String denied
      91: iconst_0
      92: anewarray     #30                 // class java/lang/String
      95: invokestatic  #31                 // Method org/apache/hadoop/hbase/security/User.createUserForTesting:(Lorg/apache/hadoop/conf/Configuration;Ljava/lang/String;[Ljava/lang/String;)Lorg/apache/hadoop/hbase/security/User;
      98: putstatic     #36                 // Field DENIED:Lorg/apache/hadoop/hbase/security/User;
     101: return

  public static void tearDownAfterClass() throws java.lang.Exception;
    Code:
       0: getstatic     #5                  // Field TEST_UTIL:Lorg/apache/hadoop/hbase/HBaseTestingUtility;
       3: invokevirtual #37                 // Method org/apache/hadoop/hbase/HBaseTestingUtility.shutdownMiniCluster:()V
       6: return

  public void testQualifierAccess() throws java.lang.Exception;
    Code:
       0: getstatic     #5                  // Field TEST_UTIL:Lorg/apache/hadoop/hbase/HBaseTestingUtility;
       3: getstatic     #4                  // Field TABLE:Lorg/apache/hadoop/hbase/TableName;
       6: iconst_1
       7: anewarray     #38                 // class "[B"
      10: dup
      11: iconst_0
      12: getstatic     #3                  // Field FAMILY:[B
      15: aastore
      16: invokestatic  #39                 // Method createTable:(Lorg/apache/hadoop/hbase/HBaseTestingUtility;Lorg/apache/hadoop/hbase/TableName;[[B)Lorg/apache/hadoop/hbase/client/Table;
      19: astore_1
      20: aload_0
      21: aload_1
      22: invokespecial #40                 // Method doQualifierAccess:(Lorg/apache/hadoop/hbase/client/Table;)V
      25: aload_1
      26: invokeinterface #41,  1           // InterfaceMethod org/apache/hadoop/hbase/client/Table.close:()V
      31: goto          43
      34: astore_2
      35: aload_1
      36: invokeinterface #41,  1           // InterfaceMethod org/apache/hadoop/hbase/client/Table.close:()V
      41: aload_2
      42: athrow
      43: return
    Exception table:
       from    to  target type
          20    25    34   any

  static org.apache.hadoop.hbase.HBaseTestingUtility access$000();
    Code:
       0: getstatic     #5                  // Field TEST_UTIL:Lorg/apache/hadoop/hbase/HBaseTestingUtility;
       3: areturn

  static org.apache.hadoop.hbase.TableName access$100();
    Code:
       0: getstatic     #4                  // Field TABLE:Lorg/apache/hadoop/hbase/TableName;
       3: areturn

  static byte[] access$200();
    Code:
       0: getstatic     #3                  // Field FAMILY:[B
       3: areturn

  static byte[] access$300();
    Code:
       0: getstatic     #2                  // Field PRIVATE_COL:[B
       3: areturn

  static byte[] access$400();
    Code:
       0: getstatic     #1                  // Field PUBLIC_COL:[B
       3: areturn

  static {};
    Code:
       0: ldc           #69                 // class org/apache/hadoop/hbase/security/access/TestAccessControlFilter
       2: invokestatic  #70                 // Method org/apache/hadoop/hbase/HBaseClassTestRule.forClass:(Ljava/lang/Class;)Lorg/apache/hadoop/hbase/HBaseClassTestRule;
       5: putstatic     #71                 // Field CLASS_RULE:Lorg/apache/hadoop/hbase/HBaseClassTestRule;
       8: ldc           #72                 // String f1
      10: invokestatic  #57                 // Method org/apache/hadoop/hbase/util/Bytes.toBytes:(Ljava/lang/String;)[B
      13: putstatic     #3                  // Field FAMILY:[B
      16: ldc           #73                 // String private
      18: invokestatic  #57                 // Method org/apache/hadoop/hbase/util/Bytes.toBytes:(Ljava/lang/String;)[B
      21: putstatic     #2                  // Field PRIVATE_COL:[B
      24: ldc           #74                 // String public
      26: invokestatic  #57                 // Method org/apache/hadoop/hbase/util/Bytes.toBytes:(Ljava/lang/String;)[B
      29: putstatic     #1                  // Field PUBLIC_COL:[B
      32: return
}
