Compiled from "TestInclusiveStopFilter.java"
public class org.apache.hadoop.hbase.filter.TestInclusiveStopFilter {
  public static final org.apache.hadoop.hbase.HBaseClassTestRule CLASS_RULE;

  org.apache.hadoop.hbase.filter.Filter mainFilter;

  public org.apache.hadoop.hbase.filter.TestInclusiveStopFilter();
    Code:
       0: aload_0
       1: invokespecial #1                  // Method java/lang/Object."<init>":()V
       4: aload_0
       5: ldc           #2                  // String stop_row
       7: invokestatic  #3                  // Method org/apache/hadoop/hbase/util/Bytes.toBytes:(Ljava/lang/String;)[B
      10: putfield      #4                  // Field STOP_ROW:[B
      13: aload_0
      14: ldc           #5                  // String good_row
      16: invokestatic  #3                  // Method org/apache/hadoop/hbase/util/Bytes.toBytes:(Ljava/lang/String;)[B
      19: putfield      #6                  // Field GOOD_ROW:[B
      22: aload_0
      23: ldc           #7                  // String zzzzzz
      25: invokestatic  #3                  // Method org/apache/hadoop/hbase/util/Bytes.toBytes:(Ljava/lang/String;)[B
      28: putfield      #8                  // Field PAST_STOP_ROW:[B
      31: return

  public void setUp() throws java.lang.Exception;
    Code:
       0: aload_0
       1: new           #9                  // class org/apache/hadoop/hbase/filter/InclusiveStopFilter
       4: dup
       5: aload_0
       6: getfield      #4                  // Field STOP_ROW:[B
       9: invokespecial #10                 // Method org/apache/hadoop/hbase/filter/InclusiveStopFilter."<init>":([B)V
      12: putfield      #11                 // Field mainFilter:Lorg/apache/hadoop/hbase/filter/Filter;
      15: return

  public void testStopRowIdentification() throws java.lang.Exception;
    Code:
       0: aload_0
       1: aload_0
       2: getfield      #11                 // Field mainFilter:Lorg/apache/hadoop/hbase/filter/Filter;
       5: invokespecial #12                 // Method stopRowTests:(Lorg/apache/hadoop/hbase/filter/Filter;)V
       8: return

  public void testSerialization() throws java.lang.Exception;
    Code:
       0: aload_0
       1: getfield      #11                 // Field mainFilter:Lorg/apache/hadoop/hbase/filter/Filter;
       4: invokevirtual #13                 // Method org/apache/hadoop/hbase/filter/Filter.toByteArray:()[B
       7: astore_1
       8: aload_1
       9: invokestatic  #14                 // Method org/apache/hadoop/hbase/filter/InclusiveStopFilter.parseFrom:([B)Lorg/apache/hadoop/hbase/filter/InclusiveStopFilter;
      12: astore_2
      13: aload_0
      14: aload_2
      15: invokespecial #12                 // Method stopRowTests:(Lorg/apache/hadoop/hbase/filter/Filter;)V
      18: return

  static {};
    Code:
       0: ldc           #29                 // class org/apache/hadoop/hbase/filter/TestInclusiveStopFilter
       2: invokestatic  #30                 // Method org/apache/hadoop/hbase/HBaseClassTestRule.forClass:(Ljava/lang/Class;)Lorg/apache/hadoop/hbase/HBaseClassTestRule;
       5: putstatic     #31                 // Field CLASS_RULE:Lorg/apache/hadoop/hbase/HBaseClassTestRule;
       8: return
}
