Compiled from "TestHRegionFileSystem.java"
class org.apache.hadoop.hbase.regionserver.TestHRegionFileSystem$MockFileSystem extends org.apache.hadoop.fs.FileSystem {
  int retryCount;

  static final int successRetryCount;

  public org.apache.hadoop.hbase.regionserver.TestHRegionFileSystem$MockFileSystem();
    Code:
       0: aload_0
       1: invokespecial #1                  // Method org/apache/hadoop/fs/FileSystem."<init>":()V
       4: aload_0
       5: iconst_0
       6: putfield      #2                  // Field retryCount:I
       9: return

  public org.apache.hadoop.fs.FSDataOutputStream append(org.apache.hadoop.fs.Path, int, org.apache.hadoop.util.Progressable) throws java.io.IOException;
    Code:
       0: new           #3                  // class java/io/IOException
       3: dup
       4: ldc           #4                  // String
       6: invokespecial #5                  // Method java/io/IOException."<init>":(Ljava/lang/String;)V
       9: athrow

  public org.apache.hadoop.fs.FSDataOutputStream create(org.apache.hadoop.fs.Path, org.apache.hadoop.fs.permission.FsPermission, boolean, int, short, long, org.apache.hadoop.util.Progressable) throws java.io.IOException;
    Code:
       0: getstatic     #6                  // Field LOG:Lorg/apache/commons/logging/Log;
       3: new           #7                  // class java/lang/StringBuilder
       6: dup
       7: invokespecial #8                  // Method java/lang/StringBuilder."<init>":()V
      10: ldc           #9                  // String Create,
      12: invokevirtual #10                 // Method java/lang/StringBuilder.append:(Ljava/lang/String;)Ljava/lang/StringBuilder;
      15: aload_0
      16: getfield      #2                  // Field retryCount:I
      19: invokevirtual #11                 // Method java/lang/StringBuilder.append:(I)Ljava/lang/StringBuilder;
      22: invokevirtual #12                 // Method java/lang/StringBuilder.toString:()Ljava/lang/String;
      25: invokeinterface #13,  2           // InterfaceMethod org/apache/commons/logging/Log.debug:(Ljava/lang/Object;)V
      30: aload_0
      31: dup
      32: getfield      #2                  // Field retryCount:I
      35: dup_x1
      36: iconst_1
      37: iadd
      38: putfield      #2                  // Field retryCount:I
      41: iconst_3
      42: if_icmpge     55
      45: new           #3                  // class java/io/IOException
      48: dup
      49: ldc           #15                 // String Something bad happen
      51: invokespecial #5                  // Method java/io/IOException."<init>":(Ljava/lang/String;)V
      54: athrow
      55: aconst_null
      56: areturn

  public boolean delete(org.apache.hadoop.fs.Path) throws java.io.IOException;
    Code:
       0: aload_0
       1: dup
       2: getfield      #2                  // Field retryCount:I
       5: dup_x1
       6: iconst_1
       7: iadd
       8: putfield      #2                  // Field retryCount:I
      11: iconst_3
      12: if_icmpge     25
      15: new           #3                  // class java/io/IOException
      18: dup
      19: ldc           #15                 // String Something bad happen
      21: invokespecial #5                  // Method java/io/IOException."<init>":(Ljava/lang/String;)V
      24: athrow
      25: iconst_1
      26: ireturn

  public boolean delete(org.apache.hadoop.fs.Path, boolean) throws java.io.IOException;
    Code:
       0: aload_0
       1: dup
       2: getfield      #2                  // Field retryCount:I
       5: dup_x1
       6: iconst_1
       7: iadd
       8: putfield      #2                  // Field retryCount:I
      11: iconst_3
      12: if_icmpge     25
      15: new           #3                  // class java/io/IOException
      18: dup
      19: ldc           #15                 // String Something bad happen
      21: invokespecial #5                  // Method java/io/IOException."<init>":(Ljava/lang/String;)V
      24: athrow
      25: iconst_1
      26: ireturn

  public org.apache.hadoop.fs.FileStatus getFileStatus(org.apache.hadoop.fs.Path) throws java.io.IOException;
    Code:
       0: new           #16                 // class org/apache/hadoop/fs/FileStatus
       3: dup
       4: invokespecial #17                 // Method org/apache/hadoop/fs/FileStatus."<init>":()V
       7: astore_2
       8: aload_2
       9: areturn

  public boolean exists(org.apache.hadoop.fs.Path);
    Code:
       0: iconst_1
       1: ireturn

  public java.net.URI getUri();
    Code:
       0: new           #18                 // class java/lang/RuntimeException
       3: dup
       4: ldc           #15                 // String Something bad happen
       6: invokespecial #19                 // Method java/lang/RuntimeException."<init>":(Ljava/lang/String;)V
       9: athrow

  public org.apache.hadoop.fs.Path getWorkingDirectory();
    Code:
       0: new           #18                 // class java/lang/RuntimeException
       3: dup
       4: ldc           #15                 // String Something bad happen
       6: invokespecial #19                 // Method java/lang/RuntimeException."<init>":(Ljava/lang/String;)V
       9: athrow

  public org.apache.hadoop.fs.FileStatus[] listStatus(org.apache.hadoop.fs.Path) throws java.io.IOException;
    Code:
       0: new           #3                  // class java/io/IOException
       3: dup
       4: ldc           #15                 // String Something bad happen
       6: invokespecial #5                  // Method java/io/IOException."<init>":(Ljava/lang/String;)V
       9: athrow

  public boolean mkdirs(org.apache.hadoop.fs.Path, org.apache.hadoop.fs.permission.FsPermission) throws java.io.IOException;
    Code:
       0: getstatic     #6                  // Field LOG:Lorg/apache/commons/logging/Log;
       3: new           #7                  // class java/lang/StringBuilder
       6: dup
       7: invokespecial #8                  // Method java/lang/StringBuilder."<init>":()V
      10: ldc           #20                 // String mkdirs,
      12: invokevirtual #10                 // Method java/lang/StringBuilder.append:(Ljava/lang/String;)Ljava/lang/StringBuilder;
      15: aload_0
      16: getfield      #2                  // Field retryCount:I
      19: invokevirtual #11                 // Method java/lang/StringBuilder.append:(I)Ljava/lang/StringBuilder;
      22: invokevirtual #12                 // Method java/lang/StringBuilder.toString:()Ljava/lang/String;
      25: invokeinterface #13,  2           // InterfaceMethod org/apache/commons/logging/Log.debug:(Ljava/lang/Object;)V
      30: aload_0
      31: dup
      32: getfield      #2                  // Field retryCount:I
      35: dup_x1
      36: iconst_1
      37: iadd
      38: putfield      #2                  // Field retryCount:I
      41: iconst_3
      42: if_icmpge     55
      45: new           #3                  // class java/io/IOException
      48: dup
      49: ldc           #15                 // String Something bad happen
      51: invokespecial #5                  // Method java/io/IOException."<init>":(Ljava/lang/String;)V
      54: athrow
      55: iconst_1
      56: ireturn

  public org.apache.hadoop.fs.FSDataInputStream open(org.apache.hadoop.fs.Path, int) throws java.io.IOException;
    Code:
       0: new           #3                  // class java/io/IOException
       3: dup
       4: ldc           #15                 // String Something bad happen
       6: invokespecial #5                  // Method java/io/IOException."<init>":(Ljava/lang/String;)V
       9: athrow

  public boolean rename(org.apache.hadoop.fs.Path, org.apache.hadoop.fs.Path) throws java.io.IOException;
    Code:
       0: getstatic     #6                  // Field LOG:Lorg/apache/commons/logging/Log;
       3: new           #7                  // class java/lang/StringBuilder
       6: dup
       7: invokespecial #8                  // Method java/lang/StringBuilder."<init>":()V
      10: ldc           #21                 // String rename,
      12: invokevirtual #10                 // Method java/lang/StringBuilder.append:(Ljava/lang/String;)Ljava/lang/StringBuilder;
      15: aload_0
      16: getfield      #2                  // Field retryCount:I
      19: invokevirtual #11                 // Method java/lang/StringBuilder.append:(I)Ljava/lang/StringBuilder;
      22: invokevirtual #12                 // Method java/lang/StringBuilder.toString:()Ljava/lang/String;
      25: invokeinterface #13,  2           // InterfaceMethod org/apache/commons/logging/Log.debug:(Ljava/lang/Object;)V
      30: aload_0
      31: dup
      32: getfield      #2                  // Field retryCount:I
      35: dup_x1
      36: iconst_1
      37: iadd
      38: putfield      #2                  // Field retryCount:I
      41: iconst_3
      42: if_icmpge     55
      45: new           #3                  // class java/io/IOException
      48: dup
      49: ldc           #15                 // String Something bad happen
      51: invokespecial #5                  // Method java/io/IOException."<init>":(Ljava/lang/String;)V
      54: athrow
      55: iconst_1
      56: ireturn

  public void setWorkingDirectory(org.apache.hadoop.fs.Path);
    Code:
       0: new           #18                 // class java/lang/RuntimeException
       3: dup
       4: ldc           #15                 // String Something bad happen
       6: invokespecial #19                 // Method java/lang/RuntimeException."<init>":(Ljava/lang/String;)V
       9: athrow
}
