Compiled from "TestSpaceLimitSettings.java"
public class org.apache.hadoop.hbase.quotas.TestSpaceLimitSettings {
  public static final org.apache.hadoop.hbase.HBaseClassTestRule CLASS_RULE;

  public org.apache.hadoop.hbase.quotas.TestSpaceLimitSettings();
    Code:
       0: aload_0
       1: invokespecial #1                  // Method java/lang/Object."<init>":()V
       4: return

  public void testInvalidTableQuotaSizeLimit();
    Code:
       0: new           #2                  // class org/apache/hadoop/hbase/quotas/SpaceLimitSettings
       3: dup
       4: ldc           #3                  // String foo
       6: invokestatic  #4                  // Method org/apache/hadoop/hbase/TableName.valueOf:(Ljava/lang/String;)Lorg/apache/hadoop/hbase/TableName;
       9: ldc2_w        #5                  // long -1l
      12: getstatic     #7                  // Field org/apache/hadoop/hbase/quotas/SpaceViolationPolicy.NO_INSERTS:Lorg/apache/hadoop/hbase/quotas/SpaceViolationPolicy;
      15: invokespecial #8                  // Method org/apache/hadoop/hbase/quotas/SpaceLimitSettings."<init>":(Lorg/apache/hadoop/hbase/TableName;JLorg/apache/hadoop/hbase/quotas/SpaceViolationPolicy;)V
      18: pop
      19: return

  public void testNullTableName();
    Code:
       0: aconst_null
       1: astore_1
       2: new           #2                  // class org/apache/hadoop/hbase/quotas/SpaceLimitSettings
       5: dup
       6: aload_1
       7: lconst_1
       8: getstatic     #7                  // Field org/apache/hadoop/hbase/quotas/SpaceViolationPolicy.NO_INSERTS:Lorg/apache/hadoop/hbase/quotas/SpaceViolationPolicy;
      11: invokespecial #8                  // Method org/apache/hadoop/hbase/quotas/SpaceLimitSettings."<init>":(Lorg/apache/hadoop/hbase/TableName;JLorg/apache/hadoop/hbase/quotas/SpaceViolationPolicy;)V
      14: pop
      15: return

  public void testNullTableViolationPolicy();
    Code:
       0: new           #2                  // class org/apache/hadoop/hbase/quotas/SpaceLimitSettings
       3: dup
       4: ldc           #3                  // String foo
       6: invokestatic  #4                  // Method org/apache/hadoop/hbase/TableName.valueOf:(Ljava/lang/String;)Lorg/apache/hadoop/hbase/TableName;
       9: lconst_1
      10: aconst_null
      11: invokespecial #8                  // Method org/apache/hadoop/hbase/quotas/SpaceLimitSettings."<init>":(Lorg/apache/hadoop/hbase/TableName;JLorg/apache/hadoop/hbase/quotas/SpaceViolationPolicy;)V
      14: pop
      15: return

  public void testInvalidNamespaceQuotaSizeLimit();
    Code:
       0: new           #2                  // class org/apache/hadoop/hbase/quotas/SpaceLimitSettings
       3: dup
       4: ldc           #9                  // String foo_ns
       6: ldc2_w        #5                  // long -1l
       9: getstatic     #7                  // Field org/apache/hadoop/hbase/quotas/SpaceViolationPolicy.NO_INSERTS:Lorg/apache/hadoop/hbase/quotas/SpaceViolationPolicy;
      12: invokespecial #10                 // Method org/apache/hadoop/hbase/quotas/SpaceLimitSettings."<init>":(Ljava/lang/String;JLorg/apache/hadoop/hbase/quotas/SpaceViolationPolicy;)V
      15: pop
      16: return

  public void testNullNamespace();
    Code:
       0: aconst_null
       1: astore_1
       2: new           #2                  // class org/apache/hadoop/hbase/quotas/SpaceLimitSettings
       5: dup
       6: aload_1
       7: lconst_1
       8: getstatic     #7                  // Field org/apache/hadoop/hbase/quotas/SpaceViolationPolicy.NO_INSERTS:Lorg/apache/hadoop/hbase/quotas/SpaceViolationPolicy;
      11: invokespecial #10                 // Method org/apache/hadoop/hbase/quotas/SpaceLimitSettings."<init>":(Ljava/lang/String;JLorg/apache/hadoop/hbase/quotas/SpaceViolationPolicy;)V
      14: pop
      15: return

  public void testNullNamespaceViolationPolicy();
    Code:
       0: new           #2                  // class org/apache/hadoop/hbase/quotas/SpaceLimitSettings
       3: dup
       4: ldc           #9                  // String foo_ns
       6: lconst_1
       7: aconst_null
       8: invokespecial #10                 // Method org/apache/hadoop/hbase/quotas/SpaceLimitSettings."<init>":(Ljava/lang/String;JLorg/apache/hadoop/hbase/quotas/SpaceViolationPolicy;)V
      11: pop
      12: return

  public void testTableQuota();
    Code:
       0: ldc           #3                  // String foo
       2: invokestatic  #4                  // Method org/apache/hadoop/hbase/TableName.valueOf:(Ljava/lang/String;)Lorg/apache/hadoop/hbase/TableName;
       5: astore_1
       6: ldc2_w        #11                 // long 1048576l
       9: lstore_2
      10: getstatic     #13                 // Field org/apache/hadoop/hbase/quotas/SpaceViolationPolicy.NO_WRITES:Lorg/apache/hadoop/hbase/quotas/SpaceViolationPolicy;
      13: astore        4
      15: new           #2                  // class org/apache/hadoop/hbase/quotas/SpaceLimitSettings
      18: dup
      19: aload_1
      20: ldc2_w        #11                 // long 1048576l
      23: aload         4
      25: invokespecial #8                  // Method org/apache/hadoop/hbase/quotas/SpaceLimitSettings."<init>":(Lorg/apache/hadoop/hbase/TableName;JLorg/apache/hadoop/hbase/quotas/SpaceViolationPolicy;)V
      28: astore        5
      30: aload         5
      32: invokestatic  #14                 // Method org/apache/hadoop/hbase/quotas/QuotaSettings.buildSetQuotaRequestProto:(Lorg/apache/hadoop/hbase/quotas/QuotaSettings;)Lorg/apache/hadoop/hbase/shaded/protobuf/generated/MasterProtos$SetQuotaRequest;
      35: astore        6
      37: ldc           #15                 // String User should be missing
      39: aload         6
      41: invokevirtual #16                 // Method org/apache/hadoop/hbase/shaded/protobuf/generated/MasterProtos$SetQuotaRequest.hasUserName:()Z
      44: invokestatic  #17                 // Method org/junit/Assert.assertFalse:(Ljava/lang/String;Z)V
      47: ldc           #18                 // String Namespace should be missing
      49: aload         6
      51: invokevirtual #19                 // Method org/apache/hadoop/hbase/shaded/protobuf/generated/MasterProtos$SetQuotaRequest.hasNamespace:()Z
      54: invokestatic  #17                 // Method org/junit/Assert.assertFalse:(Ljava/lang/String;Z)V
      57: aload_1
      58: invokestatic  #20                 // Method org/apache/hadoop/hbase/shaded/protobuf/ProtobufUtil.toProtoTableName:(Lorg/apache/hadoop/hbase/TableName;)Lorg/apache/hadoop/hbase/shaded/protobuf/generated/HBaseProtos$TableName;
      61: aload         6
      63: invokevirtual #21                 // Method org/apache/hadoop/hbase/shaded/protobuf/generated/MasterProtos$SetQuotaRequest.getTableName:()Lorg/apache/hadoop/hbase/shaded/protobuf/generated/HBaseProtos$TableName;
      66: invokestatic  #22                 // Method org/junit/Assert.assertEquals:(Ljava/lang/Object;Ljava/lang/Object;)V
      69: aload         6
      71: invokevirtual #23                 // Method org/apache/hadoop/hbase/shaded/protobuf/generated/MasterProtos$SetQuotaRequest.getSpaceLimit:()Lorg/apache/hadoop/hbase/shaded/protobuf/generated/QuotaProtos$SpaceLimitRequest;
      74: astore        7
      76: ldc           #24                 // String SpaceLimitRequest was null
      78: aload         7
      80: invokestatic  #25                 // Method org/junit/Assert.assertNotNull:(Ljava/lang/String;Ljava/lang/Object;)V
      83: aload         7
      85: invokevirtual #26                 // Method org/apache/hadoop/hbase/shaded/protobuf/generated/QuotaProtos$SpaceLimitRequest.getQuota:()Lorg/apache/hadoop/hbase/shaded/protobuf/generated/QuotaProtos$SpaceQuota;
      88: astore        8
      90: ldc           #27                 // String SpaceQuota was null
      92: aload         8
      94: invokestatic  #25                 // Method org/junit/Assert.assertNotNull:(Ljava/lang/String;Ljava/lang/Object;)V
      97: ldc2_w        #11                 // long 1048576l
     100: aload         8
     102: invokevirtual #28                 // Method org/apache/hadoop/hbase/shaded/protobuf/generated/QuotaProtos$SpaceQuota.getSoftLimit:()J
     105: invokestatic  #29                 // Method org/junit/Assert.assertEquals:(JJ)V
     108: aload         4
     110: invokestatic  #30                 // Method org/apache/hadoop/hbase/shaded/protobuf/ProtobufUtil.toProtoViolationPolicy:(Lorg/apache/hadoop/hbase/quotas/SpaceViolationPolicy;)Lorg/apache/hadoop/hbase/shaded/protobuf/generated/QuotaProtos$SpaceViolationPolicy;
     113: aload         8
     115: invokevirtual #31                 // Method org/apache/hadoop/hbase/shaded/protobuf/generated/QuotaProtos$SpaceQuota.getViolationPolicy:()Lorg/apache/hadoop/hbase/shaded/protobuf/generated/QuotaProtos$SpaceViolationPolicy;
     118: invokestatic  #22                 // Method org/junit/Assert.assertEquals:(Ljava/lang/Object;Ljava/lang/Object;)V
     121: getstatic     #32                 // Field org/apache/hadoop/hbase/quotas/QuotaType.SPACE:Lorg/apache/hadoop/hbase/quotas/QuotaType;
     124: aload         5
     126: invokevirtual #33                 // Method org/apache/hadoop/hbase/quotas/SpaceLimitSettings.getQuotaType:()Lorg/apache/hadoop/hbase/quotas/QuotaType;
     129: invokestatic  #22                 // Method org/junit/Assert.assertEquals:(Ljava/lang/Object;Ljava/lang/Object;)V
     132: new           #2                  // class org/apache/hadoop/hbase/quotas/SpaceLimitSettings
     135: dup
     136: aload_1
     137: ldc2_w        #11                 // long 1048576l
     140: aload         4
     142: invokespecial #8                  // Method org/apache/hadoop/hbase/quotas/SpaceLimitSettings."<init>":(Lorg/apache/hadoop/hbase/TableName;JLorg/apache/hadoop/hbase/quotas/SpaceViolationPolicy;)V
     145: astore        9
     147: aload         5
     149: aload         9
     151: invokestatic  #22                 // Method org/junit/Assert.assertEquals:(Ljava/lang/Object;Ljava/lang/Object;)V
     154: aload         5
     156: invokevirtual #34                 // Method org/apache/hadoop/hbase/quotas/SpaceLimitSettings.hashCode:()I
     159: i2l
     160: aload         9
     162: invokevirtual #34                 // Method org/apache/hadoop/hbase/quotas/SpaceLimitSettings.hashCode:()I
     165: i2l
     166: invokestatic  #29                 // Method org/junit/Assert.assertEquals:(JJ)V
     169: return

  public void testNamespaceQuota();
    Code:
       0: ldc           #9                  // String foo_ns
       2: astore_1
       3: ldc2_w        #11                 // long 1048576l
       6: lstore_2
       7: getstatic     #13                 // Field org/apache/hadoop/hbase/quotas/SpaceViolationPolicy.NO_WRITES:Lorg/apache/hadoop/hbase/quotas/SpaceViolationPolicy;
      10: astore        4
      12: new           #2                  // class org/apache/hadoop/hbase/quotas/SpaceLimitSettings
      15: dup
      16: ldc           #9                  // String foo_ns
      18: ldc2_w        #11                 // long 1048576l
      21: aload         4
      23: invokespecial #10                 // Method org/apache/hadoop/hbase/quotas/SpaceLimitSettings."<init>":(Ljava/lang/String;JLorg/apache/hadoop/hbase/quotas/SpaceViolationPolicy;)V
      26: astore        5
      28: aload         5
      30: invokestatic  #14                 // Method org/apache/hadoop/hbase/quotas/QuotaSettings.buildSetQuotaRequestProto:(Lorg/apache/hadoop/hbase/quotas/QuotaSettings;)Lorg/apache/hadoop/hbase/shaded/protobuf/generated/MasterProtos$SetQuotaRequest;
      33: astore        6
      35: ldc           #15                 // String User should be missing
      37: aload         6
      39: invokevirtual #16                 // Method org/apache/hadoop/hbase/shaded/protobuf/generated/MasterProtos$SetQuotaRequest.hasUserName:()Z
      42: invokestatic  #17                 // Method org/junit/Assert.assertFalse:(Ljava/lang/String;Z)V
      45: ldc           #35                 // String TableName should be missing
      47: aload         6
      49: invokevirtual #36                 // Method org/apache/hadoop/hbase/shaded/protobuf/generated/MasterProtos$SetQuotaRequest.hasTableName:()Z
      52: invokestatic  #17                 // Method org/junit/Assert.assertFalse:(Ljava/lang/String;Z)V
      55: ldc           #9                  // String foo_ns
      57: aload         6
      59: invokevirtual #37                 // Method org/apache/hadoop/hbase/shaded/protobuf/generated/MasterProtos$SetQuotaRequest.getNamespace:()Ljava/lang/String;
      62: invokestatic  #22                 // Method org/junit/Assert.assertEquals:(Ljava/lang/Object;Ljava/lang/Object;)V
      65: aload         6
      67: invokevirtual #23                 // Method org/apache/hadoop/hbase/shaded/protobuf/generated/MasterProtos$SetQuotaRequest.getSpaceLimit:()Lorg/apache/hadoop/hbase/shaded/protobuf/generated/QuotaProtos$SpaceLimitRequest;
      70: astore        7
      72: ldc           #24                 // String SpaceLimitRequest was null
      74: aload         7
      76: invokestatic  #25                 // Method org/junit/Assert.assertNotNull:(Ljava/lang/String;Ljava/lang/Object;)V
      79: aload         7
      81: invokevirtual #26                 // Method org/apache/hadoop/hbase/shaded/protobuf/generated/QuotaProtos$SpaceLimitRequest.getQuota:()Lorg/apache/hadoop/hbase/shaded/protobuf/generated/QuotaProtos$SpaceQuota;
      84: astore        8
      86: ldc           #27                 // String SpaceQuota was null
      88: aload         8
      90: invokestatic  #25                 // Method org/junit/Assert.assertNotNull:(Ljava/lang/String;Ljava/lang/Object;)V
      93: ldc2_w        #11                 // long 1048576l
      96: aload         8
      98: invokevirtual #28                 // Method org/apache/hadoop/hbase/shaded/protobuf/generated/QuotaProtos$SpaceQuota.getSoftLimit:()J
     101: invokestatic  #29                 // Method org/junit/Assert.assertEquals:(JJ)V
     104: aload         4
     106: invokestatic  #30                 // Method org/apache/hadoop/hbase/shaded/protobuf/ProtobufUtil.toProtoViolationPolicy:(Lorg/apache/hadoop/hbase/quotas/SpaceViolationPolicy;)Lorg/apache/hadoop/hbase/shaded/protobuf/generated/QuotaProtos$SpaceViolationPolicy;
     109: aload         8
     111: invokevirtual #31                 // Method org/apache/hadoop/hbase/shaded/protobuf/generated/QuotaProtos$SpaceQuota.getViolationPolicy:()Lorg/apache/hadoop/hbase/shaded/protobuf/generated/QuotaProtos$SpaceViolationPolicy;
     114: invokestatic  #22                 // Method org/junit/Assert.assertEquals:(Ljava/lang/Object;Ljava/lang/Object;)V
     117: getstatic     #32                 // Field org/apache/hadoop/hbase/quotas/QuotaType.SPACE:Lorg/apache/hadoop/hbase/quotas/QuotaType;
     120: aload         5
     122: invokevirtual #33                 // Method org/apache/hadoop/hbase/quotas/SpaceLimitSettings.getQuotaType:()Lorg/apache/hadoop/hbase/quotas/QuotaType;
     125: invokestatic  #22                 // Method org/junit/Assert.assertEquals:(Ljava/lang/Object;Ljava/lang/Object;)V
     128: new           #2                  // class org/apache/hadoop/hbase/quotas/SpaceLimitSettings
     131: dup
     132: ldc           #9                  // String foo_ns
     134: ldc2_w        #11                 // long 1048576l
     137: aload         4
     139: invokespecial #10                 // Method org/apache/hadoop/hbase/quotas/SpaceLimitSettings."<init>":(Ljava/lang/String;JLorg/apache/hadoop/hbase/quotas/SpaceViolationPolicy;)V
     142: astore        9
     144: aload         5
     146: aload         9
     148: invokestatic  #22                 // Method org/junit/Assert.assertEquals:(Ljava/lang/Object;Ljava/lang/Object;)V
     151: aload         5
     153: invokevirtual #34                 // Method org/apache/hadoop/hbase/quotas/SpaceLimitSettings.hashCode:()I
     156: i2l
     157: aload         9
     159: invokevirtual #34                 // Method org/apache/hadoop/hbase/quotas/SpaceLimitSettings.hashCode:()I
     162: i2l
     163: invokestatic  #29                 // Method org/junit/Assert.assertEquals:(JJ)V
     166: return

  public void testQuotaMerging() throws java.io.IOException;
    Code:
       0: ldc           #3                  // String foo
       2: invokestatic  #4                  // Method org/apache/hadoop/hbase/TableName.valueOf:(Ljava/lang/String;)Lorg/apache/hadoop/hbase/TableName;
       5: astore_1
       6: aload_1
       7: ldc2_w        #11                 // long 1048576l
      10: getstatic     #38                 // Field org/apache/hadoop/hbase/quotas/SpaceViolationPolicy.DISABLE:Lorg/apache/hadoop/hbase/quotas/SpaceViolationPolicy;
      13: invokestatic  #39                 // Method org/apache/hadoop/hbase/quotas/QuotaSettingsFactory.limitTableSpace:(Lorg/apache/hadoop/hbase/TableName;JLorg/apache/hadoop/hbase/quotas/SpaceViolationPolicy;)Lorg/apache/hadoop/hbase/quotas/QuotaSettings;
      16: astore_2
      17: aload_1
      18: ldc2_w        #40                 // long 5242880l
      21: getstatic     #38                 // Field org/apache/hadoop/hbase/quotas/SpaceViolationPolicy.DISABLE:Lorg/apache/hadoop/hbase/quotas/SpaceViolationPolicy;
      24: invokestatic  #39                 // Method org/apache/hadoop/hbase/quotas/QuotaSettingsFactory.limitTableSpace:(Lorg/apache/hadoop/hbase/TableName;JLorg/apache/hadoop/hbase/quotas/SpaceViolationPolicy;)Lorg/apache/hadoop/hbase/quotas/QuotaSettings;
      27: astore_3
      28: aload_1
      29: ldc2_w        #11                 // long 1048576l
      32: getstatic     #13                 // Field org/apache/hadoop/hbase/quotas/SpaceViolationPolicy.NO_WRITES:Lorg/apache/hadoop/hbase/quotas/SpaceViolationPolicy;
      35: invokestatic  #39                 // Method org/apache/hadoop/hbase/quotas/QuotaSettingsFactory.limitTableSpace:(Lorg/apache/hadoop/hbase/TableName;JLorg/apache/hadoop/hbase/quotas/SpaceViolationPolicy;)Lorg/apache/hadoop/hbase/quotas/QuotaSettings;
      38: astore        4
      40: ldc           #42                 // String ns1
      42: ldc2_w        #40                 // long 5242880l
      45: getstatic     #13                 // Field org/apache/hadoop/hbase/quotas/SpaceViolationPolicy.NO_WRITES:Lorg/apache/hadoop/hbase/quotas/SpaceViolationPolicy;
      48: invokestatic  #43                 // Method org/apache/hadoop/hbase/quotas/QuotaSettingsFactory.limitNamespaceSpace:(Ljava/lang/String;JLorg/apache/hadoop/hbase/quotas/SpaceViolationPolicy;)Lorg/apache/hadoop/hbase/quotas/QuotaSettings;
      51: astore        5
      53: aload_2
      54: aload_3
      55: invokevirtual #44                 // Method org/apache/hadoop/hbase/quotas/QuotaSettings.merge:(Lorg/apache/hadoop/hbase/quotas/QuotaSettings;)Lorg/apache/hadoop/hbase/quotas/QuotaSettings;
      58: aload_3
      59: invokestatic  #22                 // Method org/junit/Assert.assertEquals:(Ljava/lang/Object;Ljava/lang/Object;)V
      62: aload_2
      63: aload         4
      65: invokevirtual #44                 // Method org/apache/hadoop/hbase/quotas/QuotaSettings.merge:(Lorg/apache/hadoop/hbase/quotas/QuotaSettings;)Lorg/apache/hadoop/hbase/quotas/QuotaSettings;
      68: aload         4
      70: invokestatic  #22                 // Method org/junit/Assert.assertEquals:(Ljava/lang/Object;Ljava/lang/Object;)V
      73: aload_2
      74: aload         5
      76: invokevirtual #44                 // Method org/apache/hadoop/hbase/quotas/QuotaSettings.merge:(Lorg/apache/hadoop/hbase/quotas/QuotaSettings;)Lorg/apache/hadoop/hbase/quotas/QuotaSettings;
      79: pop
      80: ldc           #45                 // String Should not be able to merge a Table space quota with a namespace space quota.
      82: invokestatic  #46                 // Method org/junit/Assert.fail:(Ljava/lang/String;)V
      85: goto          90
      88: astore        6
      90: return
    Exception table:
       from    to  target type
          73    85    88   Class java/lang/IllegalArgumentException

  static {};
    Code:
       0: ldc           #48                 // class org/apache/hadoop/hbase/quotas/TestSpaceLimitSettings
       2: invokestatic  #49                 // Method org/apache/hadoop/hbase/HBaseClassTestRule.forClass:(Ljava/lang/Class;)Lorg/apache/hadoop/hbase/HBaseClassTestRule;
       5: putstatic     #50                 // Field CLASS_RULE:Lorg/apache/hadoop/hbase/HBaseClassTestRule;
       8: return
}
