Compiled from "TestDefaultStoreEngine.java"
public class org.apache.hadoop.hbase.regionserver.TestDefaultStoreEngine {
  public static final org.apache.hadoop.hbase.HBaseClassTestRule CLASS_RULE;

  public org.apache.hadoop.hbase.regionserver.TestDefaultStoreEngine();
    Code:
       0: aload_0
       1: invokespecial #1                  // Method java/lang/Object."<init>":()V
       4: return

  public void testCustomParts() throws java.lang.Exception;
    Code:
       0: invokestatic  #2                  // Method org/apache/hadoop/hbase/HBaseConfiguration.create:()Lorg/apache/hadoop/conf/Configuration;
       3: astore_1
       4: aload_1
       5: ldc           #4                  // String hbase.hstore.defaultengine.compactor.class
       7: ldc           #5                  // class org/apache/hadoop/hbase/regionserver/TestDefaultStoreEngine$DummyCompactor
       9: invokevirtual #6                  // Method java/lang/Class.getName:()Ljava/lang/String;
      12: invokevirtual #7                  // Method org/apache/hadoop/conf/Configuration.set:(Ljava/lang/String;Ljava/lang/String;)V
      15: aload_1
      16: ldc           #8                  // String hbase.hstore.defaultengine.compactionpolicy.class
      18: ldc           #9                  // class org/apache/hadoop/hbase/regionserver/TestDefaultStoreEngine$DummyCompactionPolicy
      20: invokevirtual #6                  // Method java/lang/Class.getName:()Ljava/lang/String;
      23: invokevirtual #7                  // Method org/apache/hadoop/conf/Configuration.set:(Ljava/lang/String;Ljava/lang/String;)V
      26: aload_1
      27: ldc           #10                 // String hbase.hstore.defaultengine.storeflusher.class
      29: ldc           #11                 // class org/apache/hadoop/hbase/regionserver/TestDefaultStoreEngine$DummyStoreFlusher
      31: invokevirtual #6                  // Method java/lang/Class.getName:()Ljava/lang/String;
      34: invokevirtual #7                  // Method org/apache/hadoop/conf/Configuration.set:(Ljava/lang/String;Ljava/lang/String;)V
      37: ldc           #12                 // class org/apache/hadoop/hbase/regionserver/HStore
      39: invokestatic  #13                 // Method org/mockito/Mockito.mock:(Ljava/lang/Class;)Ljava/lang/Object;
      42: checkcast     #12                 // class org/apache/hadoop/hbase/regionserver/HStore
      45: astore_2
      46: aload_2
      47: aload_1
      48: getstatic     #14                 // Field org/apache/hadoop/hbase/CellComparatorImpl.COMPARATOR:Lorg/apache/hadoop/hbase/CellComparatorImpl;
      51: invokestatic  #15                 // Method org/apache/hadoop/hbase/regionserver/StoreEngine.create:(Lorg/apache/hadoop/hbase/regionserver/HStore;Lorg/apache/hadoop/conf/Configuration;Lorg/apache/hadoop/hbase/CellComparator;)Lorg/apache/hadoop/hbase/regionserver/StoreEngine;
      54: astore_3
      55: aload_3
      56: instanceof    #3                  // class org/apache/hadoop/hbase/regionserver/DefaultStoreEngine
      59: invokestatic  #16                 // Method org/junit/Assert.assertTrue:(Z)V
      62: aload_3
      63: invokevirtual #17                 // Method org/apache/hadoop/hbase/regionserver/StoreEngine.getCompactionPolicy:()Lorg/apache/hadoop/hbase/regionserver/compactions/CompactionPolicy;
      66: instanceof    #9                  // class org/apache/hadoop/hbase/regionserver/TestDefaultStoreEngine$DummyCompactionPolicy
      69: invokestatic  #16                 // Method org/junit/Assert.assertTrue:(Z)V
      72: aload_3
      73: invokevirtual #18                 // Method org/apache/hadoop/hbase/regionserver/StoreEngine.getStoreFlusher:()Lorg/apache/hadoop/hbase/regionserver/StoreFlusher;
      76: instanceof    #11                 // class org/apache/hadoop/hbase/regionserver/TestDefaultStoreEngine$DummyStoreFlusher
      79: invokestatic  #16                 // Method org/junit/Assert.assertTrue:(Z)V
      82: aload_3
      83: invokevirtual #19                 // Method org/apache/hadoop/hbase/regionserver/StoreEngine.getCompactor:()Lorg/apache/hadoop/hbase/regionserver/compactions/Compactor;
      86: instanceof    #5                  // class org/apache/hadoop/hbase/regionserver/TestDefaultStoreEngine$DummyCompactor
      89: invokestatic  #16                 // Method org/junit/Assert.assertTrue:(Z)V
      92: return

  static {};
    Code:
       0: ldc           #20                 // class org/apache/hadoop/hbase/regionserver/TestDefaultStoreEngine
       2: invokestatic  #21                 // Method org/apache/hadoop/hbase/HBaseClassTestRule.forClass:(Ljava/lang/Class;)Lorg/apache/hadoop/hbase/HBaseClassTestRule;
       5: putstatic     #22                 // Field CLASS_RULE:Lorg/apache/hadoop/hbase/HBaseClassTestRule;
       8: return
}
