Compiled from "TestAsyncTableBatchRetryImmediately.java"
public class org.apache.hadoop.hbase.client.TestAsyncTableBatchRetryImmediately {
  public static final org.apache.hadoop.hbase.HBaseClassTestRule CLASS_RULE;

  public org.apache.hadoop.hbase.client.TestAsyncTableBatchRetryImmediately();
    Code:
       0: aload_0
       1: invokespecial #1                  // Method java/lang/Object."<init>":()V
       4: return

  public static void setUp() throws java.lang.Exception;
    Code:
       0: ldc           #2                  // class org/apache/hadoop/hbase/client/AsyncRegionLocatorHelper
       2: invokestatic  #3                  // Method org/apache/log4j/LogManager.getLogger:(Ljava/lang/Class;)Lorg/apache/log4j/Logger;
       5: getstatic     #4                  // Field org/apache/log4j/Level.INFO:Lorg/apache/log4j/Level;
       8: invokevirtual #5                  // Method org/apache/log4j/Logger.setLevel:(Lorg/apache/log4j/Level;)V
      11: getstatic     #6                  // Field UTIL:Lorg/apache/hadoop/hbase/HBaseTestingUtility;
      14: invokevirtual #7                  // Method org/apache/hadoop/hbase/HBaseTestingUtility.getConfiguration:()Lorg/apache/hadoop/conf/Configuration;
      17: ldc           #9                  // String hbase.server.scanner.max.result.size
      19: ldc2_w        #10                 // long 1024l
      22: invokevirtual #12                 // Method org/apache/hadoop/conf/Configuration.setLong:(Ljava/lang/String;J)V
      25: getstatic     #6                  // Field UTIL:Lorg/apache/hadoop/hbase/HBaseTestingUtility;
      28: iconst_1
      29: invokevirtual #13                 // Method org/apache/hadoop/hbase/HBaseTestingUtility.startMiniCluster:(I)Lorg/apache/hadoop/hbase/MiniHBaseCluster;
      32: pop
      33: getstatic     #6                  // Field UTIL:Lorg/apache/hadoop/hbase/HBaseTestingUtility;
      36: getstatic     #14                 // Field TABLE_NAME:Lorg/apache/hadoop/hbase/TableName;
      39: getstatic     #15                 // Field FAMILY:[B
      42: invokevirtual #16                 // Method org/apache/hadoop/hbase/HBaseTestingUtility.createTable:(Lorg/apache/hadoop/hbase/TableName;[B)Lorg/apache/hadoop/hbase/client/Table;
      45: astore_0
      46: getstatic     #6                  // Field UTIL:Lorg/apache/hadoop/hbase/HBaseTestingUtility;
      49: getstatic     #14                 // Field TABLE_NAME:Lorg/apache/hadoop/hbase/TableName;
      52: invokevirtual #17                 // Method org/apache/hadoop/hbase/HBaseTestingUtility.waitTableAvailable:(Lorg/apache/hadoop/hbase/TableName;)V
      55: invokestatic  #18                 // Method java/util/concurrent/ThreadLocalRandom.current:()Ljava/util/concurrent/ThreadLocalRandom;
      58: getstatic     #19                 // Field VALUE_PREFIX:[B
      61: invokevirtual #20                 // Method java/util/concurrent/ThreadLocalRandom.nextBytes:([B)V
      64: iconst_0
      65: istore_1
      66: iload_1
      67: getstatic     #21                 // Field COUNT:I
      70: if_icmpge     115
      73: aload_0
      74: new           #22                 // class org/apache/hadoop/hbase/client/Put
      77: dup
      78: iload_1
      79: invokestatic  #23                 // Method org/apache/hadoop/hbase/util/Bytes.toBytes:(I)[B
      82: invokespecial #24                 // Method org/apache/hadoop/hbase/client/Put."<init>":([B)V
      85: getstatic     #15                 // Field FAMILY:[B
      88: getstatic     #25                 // Field QUAL:[B
      91: getstatic     #19                 // Field VALUE_PREFIX:[B
      94: iload_1
      95: invokestatic  #23                 // Method org/apache/hadoop/hbase/util/Bytes.toBytes:(I)[B
      98: invokestatic  #26                 // Method org/apache/hadoop/hbase/util/Bytes.add:([B[B)[B
     101: invokevirtual #27                 // Method org/apache/hadoop/hbase/client/Put.addColumn:([B[B[B)Lorg/apache/hadoop/hbase/client/Put;
     104: invokeinterface #28,  2           // InterfaceMethod org/apache/hadoop/hbase/client/Table.put:(Lorg/apache/hadoop/hbase/client/Put;)V
     109: iinc          1, 1
     112: goto          66
     115: getstatic     #6                  // Field UTIL:Lorg/apache/hadoop/hbase/HBaseTestingUtility;
     118: invokevirtual #7                  // Method org/apache/hadoop/hbase/HBaseTestingUtility.getConfiguration:()Lorg/apache/hadoop/conf/Configuration;
     121: invokestatic  #29                 // Method org/apache/hadoop/hbase/client/ConnectionFactory.createAsyncConnection:(Lorg/apache/hadoop/conf/Configuration;)Ljava/util/concurrent/CompletableFuture;
     124: invokevirtual #30                 // Method java/util/concurrent/CompletableFuture.get:()Ljava/lang/Object;
     127: checkcast     #31                 // class org/apache/hadoop/hbase/client/AsyncConnection
     130: putstatic     #32                 // Field CONN:Lorg/apache/hadoop/hbase/client/AsyncConnection;
     133: return

  public static void tearDown() throws java.lang.Exception;
    Code:
       0: getstatic     #32                 // Field CONN:Lorg/apache/hadoop/hbase/client/AsyncConnection;
       3: invokeinterface #33,  1           // InterfaceMethod org/apache/hadoop/hbase/client/AsyncConnection.close:()V
       8: getstatic     #6                  // Field UTIL:Lorg/apache/hadoop/hbase/HBaseTestingUtility;
      11: invokevirtual #34                 // Method org/apache/hadoop/hbase/HBaseTestingUtility.shutdownMiniCluster:()V
      14: return

  public void test();
    Code:
       0: getstatic     #32                 // Field CONN:Lorg/apache/hadoop/hbase/client/AsyncConnection;
       3: getstatic     #14                 // Field TABLE_NAME:Lorg/apache/hadoop/hbase/TableName;
       6: invokeinterface #35,  2           // InterfaceMethod org/apache/hadoop/hbase/client/AsyncConnection.getTable:(Lorg/apache/hadoop/hbase/TableName;)Lorg/apache/hadoop/hbase/client/AsyncTable;
      11: astore_1
      12: iconst_0
      13: getstatic     #21                 // Field COUNT:I
      16: invokestatic  #36                 // InterfaceMethod java/util/stream/IntStream.range:(II)Ljava/util/stream/IntStream;
      19: invokedynamic #37,  0             // InvokeDynamic #0:apply:()Ljava/util/function/IntFunction;
      24: invokeinterface #38,  2           // InterfaceMethod java/util/stream/IntStream.mapToObj:(Ljava/util/function/IntFunction;)Ljava/util/stream/Stream;
      29: invokestatic  #39                 // Method java/util/stream/Collectors.toList:()Ljava/util/stream/Collector;
      32: invokeinterface #40,  2           // InterfaceMethod java/util/stream/Stream.collect:(Ljava/util/stream/Collector;)Ljava/lang/Object;
      37: checkcast     #41                 // class java/util/List
      40: astore_2
      41: aload_1
      42: aload_2
      43: invokeinterface #42,  2           // InterfaceMethod org/apache/hadoop/hbase/client/AsyncTable.getAll:(Ljava/util/List;)Ljava/util/concurrent/CompletableFuture;
      48: invokevirtual #43                 // Method java/util/concurrent/CompletableFuture.join:()Ljava/lang/Object;
      51: checkcast     #41                 // class java/util/List
      54: astore_3
      55: iconst_0
      56: istore        4
      58: iload         4
      60: getstatic     #21                 // Field COUNT:I
      63: if_icmpge     139
      66: aload_3
      67: iload         4
      69: invokeinterface #44,  2           // InterfaceMethod java/util/List.get:(I)Ljava/lang/Object;
      74: checkcast     #45                 // class org/apache/hadoop/hbase/client/Result
      77: getstatic     #15                 // Field FAMILY:[B
      80: getstatic     #25                 // Field QUAL:[B
      83: invokevirtual #46                 // Method org/apache/hadoop/hbase/client/Result.getValue:([B[B)[B
      86: astore        5
      88: getstatic     #19                 // Field VALUE_PREFIX:[B
      91: arraylength
      92: iconst_4
      93: iadd
      94: i2l
      95: aload         5
      97: arraylength
      98: i2l
      99: invokestatic  #47                 // Method org/junit/Assert.assertEquals:(JJ)V
     102: getstatic     #19                 // Field VALUE_PREFIX:[B
     105: aload         5
     107: getstatic     #19                 // Field VALUE_PREFIX:[B
     110: arraylength
     111: invokestatic  #48                 // Method java/util/Arrays.copyOf:([BI)[B
     114: invokestatic  #49                 // Method org/junit/Assert.assertArrayEquals:([B[B)V
     117: iload         4
     119: i2l
     120: aload         5
     122: getstatic     #19                 // Field VALUE_PREFIX:[B
     125: arraylength
     126: invokestatic  #50                 // Method org/apache/hadoop/hbase/util/Bytes.toInt:([BI)I
     129: i2l
     130: invokestatic  #47                 // Method org/junit/Assert.assertEquals:(JJ)V
     133: iinc          4, 1
     136: goto          58
     139: return

  static {};
    Code:
       0: ldc           #53                 // class org/apache/hadoop/hbase/client/TestAsyncTableBatchRetryImmediately
       2: invokestatic  #54                 // Method org/apache/hadoop/hbase/HBaseClassTestRule.forClass:(Ljava/lang/Class;)Lorg/apache/hadoop/hbase/HBaseClassTestRule;
       5: putstatic     #55                 // Field CLASS_RULE:Lorg/apache/hadoop/hbase/HBaseClassTestRule;
       8: new           #56                 // class org/apache/hadoop/hbase/HBaseTestingUtility
      11: dup
      12: invokespecial #57                 // Method org/apache/hadoop/hbase/HBaseTestingUtility."<init>":()V
      15: putstatic     #6                  // Field UTIL:Lorg/apache/hadoop/hbase/HBaseTestingUtility;
      18: ldc           #58                 // String async
      20: invokestatic  #59                 // Method org/apache/hadoop/hbase/TableName.valueOf:(Ljava/lang/String;)Lorg/apache/hadoop/hbase/TableName;
      23: putstatic     #14                 // Field TABLE_NAME:Lorg/apache/hadoop/hbase/TableName;
      26: ldc           #60                 // String cf
      28: invokestatic  #61                 // Method org/apache/hadoop/hbase/util/Bytes.toBytes:(Ljava/lang/String;)[B
      31: putstatic     #15                 // Field FAMILY:[B
      34: ldc           #62                 // String cq
      36: invokestatic  #61                 // Method org/apache/hadoop/hbase/util/Bytes.toBytes:(Ljava/lang/String;)[B
      39: putstatic     #25                 // Field QUAL:[B
      42: sipush        768
      45: newarray       byte
      47: putstatic     #19                 // Field VALUE_PREFIX:[B
      50: sipush        1000
      53: putstatic     #21                 // Field COUNT:I
      56: return
}
