Compiled from "TestWALSplitCompressed.java"
public class org.apache.hadoop.hbase.wal.TestWALSplitCompressed extends org.apache.hadoop.hbase.wal.TestWALSplit {
  public static final org.apache.hadoop.hbase.HBaseClassTestRule CLASS_RULE;

  public org.apache.hadoop.hbase.wal.TestWALSplitCompressed();
    Code:
       0: aload_0
       1: invokespecial #1                  // Method org/apache/hadoop/hbase/wal/TestWALSplit."<init>":()V
       4: return

  public static void setUpBeforeClass() throws java.lang.Exception;
    Code:
       0: invokestatic  #2                  // Method org/apache/hadoop/hbase/wal/TestWALSplit.setUpBeforeClass:()V
       3: getstatic     #3                  // Field TEST_UTIL:Lorg/apache/hadoop/hbase/HBaseTestingUtility;
       6: invokevirtual #4                  // Method org/apache/hadoop/hbase/HBaseTestingUtility.getConfiguration:()Lorg/apache/hadoop/conf/Configuration;
       9: ldc           #6                  // String hbase.regionserver.wal.enablecompression
      11: iconst_1
      12: invokevirtual #7                  // Method org/apache/hadoop/conf/Configuration.setBoolean:(Ljava/lang/String;Z)V
      15: return

  static {};
    Code:
       0: ldc           #8                  // class org/apache/hadoop/hbase/wal/TestWALSplitCompressed
       2: invokestatic  #9                  // Method org/apache/hadoop/hbase/HBaseClassTestRule.forClass:(Ljava/lang/Class;)Lorg/apache/hadoop/hbase/HBaseClassTestRule;
       5: putstatic     #10                 // Field CLASS_RULE:Lorg/apache/hadoop/hbase/HBaseClassTestRule;
       8: return
}
