Compiled from "TestQuotaStatusRPCs.java"
public class org.apache.hadoop.hbase.quotas.TestQuotaStatusRPCs {
  public static final org.apache.hadoop.hbase.HBaseClassTestRule CLASS_RULE;

  public org.junit.rules.TestName testName;

  public org.apache.hadoop.hbase.quotas.TestQuotaStatusRPCs();
    Code:
       0: aload_0
       1: invokespecial #4                  // Method java/lang/Object."<init>":()V
       4: aload_0
       5: new           #5                  // class org/junit/rules/TestName
       8: dup
       9: invokespecial #6                  // Method org/junit/rules/TestName."<init>":()V
      12: putfield      #7                  // Field testName:Lorg/junit/rules/TestName;
      15: return

  public static void setUp() throws java.lang.Exception;
    Code:
       0: getstatic     #8                  // Field TEST_UTIL:Lorg/apache/hadoop/hbase/HBaseTestingUtility;
       3: invokevirtual #9                  // Method org/apache/hadoop/hbase/HBaseTestingUtility.getConfiguration:()Lorg/apache/hadoop/conf/Configuration;
       6: astore_0
       7: aload_0
       8: invokestatic  #10                 // Method org/apache/hadoop/hbase/quotas/SpaceQuotaHelperForTests.updateConfigForQuotas:(Lorg/apache/hadoop/conf/Configuration;)V
      11: getstatic     #8                  // Field TEST_UTIL:Lorg/apache/hadoop/hbase/HBaseTestingUtility;
      14: iconst_1
      15: invokevirtual #11                 // Method org/apache/hadoop/hbase/HBaseTestingUtility.startMiniCluster:(I)Lorg/apache/hadoop/hbase/MiniHBaseCluster;
      18: pop
      19: return

  public static void tearDown() throws java.lang.Exception;
    Code:
       0: getstatic     #8                  // Field TEST_UTIL:Lorg/apache/hadoop/hbase/HBaseTestingUtility;
       3: invokevirtual #12                 // Method org/apache/hadoop/hbase/HBaseTestingUtility.shutdownMiniCluster:()V
       6: return

  public void setupForTest() throws java.lang.Exception;
    Code:
       0: aload_0
       1: new           #13                 // class org/apache/hadoop/hbase/quotas/SpaceQuotaHelperForTests
       4: dup
       5: getstatic     #8                  // Field TEST_UTIL:Lorg/apache/hadoop/hbase/HBaseTestingUtility;
       8: aload_0
       9: getfield      #7                  // Field testName:Lorg/junit/rules/TestName;
      12: getstatic     #14                 // Field COUNTER:Ljava/util/concurrent/atomic/AtomicLong;
      15: invokespecial #15                 // Method org/apache/hadoop/hbase/quotas/SpaceQuotaHelperForTests."<init>":(Lorg/apache/hadoop/hbase/HBaseTestingUtility;Lorg/junit/rules/TestName;Ljava/util/concurrent/atomic/AtomicLong;)V
      18: putfield      #16                 // Field helper:Lorg/apache/hadoop/hbase/quotas/SpaceQuotaHelperForTests;
      21: return

  public void testRegionSizesFromMaster() throws java.lang.Exception;
    Code:
       0: ldc2_w        #17                 // long 10240l
       3: lstore_1
       4: bipush        10
       6: istore_3
       7: aload_0
       8: getfield      #16                 // Field helper:Lorg/apache/hadoop/hbase/quotas/SpaceQuotaHelperForTests;
      11: bipush        10
      13: invokevirtual #19                 // Method org/apache/hadoop/hbase/quotas/SpaceQuotaHelperForTests.createTableWithRegions:(I)Lorg/apache/hadoop/hbase/TableName;
      16: astore        4
      18: aload_0
      19: getfield      #16                 // Field helper:Lorg/apache/hadoop/hbase/quotas/SpaceQuotaHelperForTests;
      22: aload         4
      24: ldc2_w        #17                 // long 10240l
      27: invokevirtual #20                 // Method org/apache/hadoop/hbase/quotas/SpaceQuotaHelperForTests.writeData:(Lorg/apache/hadoop/hbase/TableName;J)V
      30: getstatic     #8                  // Field TEST_UTIL:Lorg/apache/hadoop/hbase/HBaseTestingUtility;
      33: invokevirtual #21                 // Method org/apache/hadoop/hbase/HBaseTestingUtility.getMiniHBaseCluster:()Lorg/apache/hadoop/hbase/MiniHBaseCluster;
      36: invokevirtual #22                 // Method org/apache/hadoop/hbase/MiniHBaseCluster.getMaster:()Lorg/apache/hadoop/hbase/master/HMaster;
      39: astore        5
      41: aload         5
      43: invokevirtual #23                 // Method org/apache/hadoop/hbase/master/HMaster.getMasterQuotaManager:()Lorg/apache/hadoop/hbase/quotas/MasterQuotaManager;
      46: astore        6
      48: getstatic     #8                  // Field TEST_UTIL:Lorg/apache/hadoop/hbase/HBaseTestingUtility;
      51: invokevirtual #9                  // Method org/apache/hadoop/hbase/HBaseTestingUtility.getConfiguration:()Lorg/apache/hadoop/conf/Configuration;
      54: ldc2_w        #24                 // long 30000l
      57: new           #26                 // class org/apache/hadoop/hbase/quotas/TestQuotaStatusRPCs$1
      60: dup
      61: aload_0
      62: aload         6
      64: aload         4
      66: invokespecial #27                 // Method org/apache/hadoop/hbase/quotas/TestQuotaStatusRPCs$1."<init>":(Lorg/apache/hadoop/hbase/quotas/TestQuotaStatusRPCs;Lorg/apache/hadoop/hbase/quotas/MasterQuotaManager;Lorg/apache/hadoop/hbase/TableName;)V
      69: invokestatic  #28                 // Method org/apache/hadoop/hbase/Waiter.waitFor:(Lorg/apache/hadoop/conf/Configuration;JLorg/apache/hadoop/hbase/Waiter$Predicate;)J
      72: pop2
      73: getstatic     #8                  // Field TEST_UTIL:Lorg/apache/hadoop/hbase/HBaseTestingUtility;
      76: invokevirtual #29                 // Method org/apache/hadoop/hbase/HBaseTestingUtility.getAdmin:()Lorg/apache/hadoop/hbase/client/Admin;
      79: invokeinterface #30,  1           // InterfaceMethod org/apache/hadoop/hbase/client/Admin.getSpaceQuotaTableSizes:()Ljava/util/Map;
      84: astore        7
      86: aload         7
      88: aload         4
      90: invokeinterface #31,  2           // InterfaceMethod java/util/Map.get:(Ljava/lang/Object;)Ljava/lang/Object;
      95: checkcast     #32                 // class java/lang/Long
      98: astore        8
     100: new           #33                 // class java/lang/StringBuilder
     103: dup
     104: invokespecial #34                 // Method java/lang/StringBuilder."<init>":()V
     107: ldc           #35                 // String No reported size for
     109: invokevirtual #36                 // Method java/lang/StringBuilder.append:(Ljava/lang/String;)Ljava/lang/StringBuilder;
     112: aload         4
     114: invokevirtual #37                 // Method java/lang/StringBuilder.append:(Ljava/lang/Object;)Ljava/lang/StringBuilder;
     117: invokevirtual #38                 // Method java/lang/StringBuilder.toString:()Ljava/lang/String;
     120: aload         8
     122: invokestatic  #39                 // Method org/junit/Assert.assertNotNull:(Ljava/lang/String;Ljava/lang/Object;)V
     125: new           #33                 // class java/lang/StringBuilder
     128: dup
     129: invokespecial #34                 // Method java/lang/StringBuilder."<init>":()V
     132: ldc           #40                 // String Reported table size was
     134: invokevirtual #36                 // Method java/lang/StringBuilder.append:(Ljava/lang/String;)Ljava/lang/StringBuilder;
     137: aload         8
     139: invokevirtual #37                 // Method java/lang/StringBuilder.append:(Ljava/lang/Object;)Ljava/lang/StringBuilder;
     142: invokevirtual #38                 // Method java/lang/StringBuilder.toString:()Ljava/lang/String;
     145: aload         8
     147: invokevirtual #41                 // Method java/lang/Long.longValue:()J
     150: ldc2_w        #17                 // long 10240l
     153: lcmp
     154: iflt          161
     157: iconst_1
     158: goto          162
     161: iconst_0
     162: invokestatic  #42                 // Method org/junit/Assert.assertTrue:(Ljava/lang/String;Z)V
     165: return

  public void testQuotaSnapshotsFromRS() throws java.lang.Exception;
    Code:
       0: ldc2_w        #43                 // long 1048576l
       3: lstore_1
       4: ldc2_w        #17                 // long 10240l
       7: lstore_3
       8: bipush        10
      10: istore        5
      12: aload_0
      13: getfield      #16                 // Field helper:Lorg/apache/hadoop/hbase/quotas/SpaceQuotaHelperForTests;
      16: bipush        10
      18: invokevirtual #19                 // Method org/apache/hadoop/hbase/quotas/SpaceQuotaHelperForTests.createTableWithRegions:(I)Lorg/apache/hadoop/hbase/TableName;
      21: astore        6
      23: aload         6
      25: ldc2_w        #43                 // long 1048576l
      28: getstatic     #45                 // Field org/apache/hadoop/hbase/quotas/SpaceViolationPolicy.NO_INSERTS:Lorg/apache/hadoop/hbase/quotas/SpaceViolationPolicy;
      31: invokestatic  #46                 // Method org/apache/hadoop/hbase/quotas/QuotaSettingsFactory.limitTableSpace:(Lorg/apache/hadoop/hbase/TableName;JLorg/apache/hadoop/hbase/quotas/SpaceViolationPolicy;)Lorg/apache/hadoop/hbase/quotas/QuotaSettings;
      34: astore        7
      36: getstatic     #8                  // Field TEST_UTIL:Lorg/apache/hadoop/hbase/HBaseTestingUtility;
      39: invokevirtual #29                 // Method org/apache/hadoop/hbase/HBaseTestingUtility.getAdmin:()Lorg/apache/hadoop/hbase/client/Admin;
      42: aload         7
      44: invokeinterface #47,  2           // InterfaceMethod org/apache/hadoop/hbase/client/Admin.setQuota:(Lorg/apache/hadoop/hbase/quotas/QuotaSettings;)V
      49: aload_0
      50: getfield      #16                 // Field helper:Lorg/apache/hadoop/hbase/quotas/SpaceQuotaHelperForTests;
      53: aload         6
      55: ldc2_w        #17                 // long 10240l
      58: invokevirtual #20                 // Method org/apache/hadoop/hbase/quotas/SpaceQuotaHelperForTests.writeData:(Lorg/apache/hadoop/hbase/TableName;J)V
      61: getstatic     #8                  // Field TEST_UTIL:Lorg/apache/hadoop/hbase/HBaseTestingUtility;
      64: invokevirtual #21                 // Method org/apache/hadoop/hbase/HBaseTestingUtility.getMiniHBaseCluster:()Lorg/apache/hadoop/hbase/MiniHBaseCluster;
      67: iconst_0
      68: invokevirtual #48                 // Method org/apache/hadoop/hbase/MiniHBaseCluster.getRegionServer:(I)Lorg/apache/hadoop/hbase/regionserver/HRegionServer;
      71: astore        8
      73: aload         8
      75: invokevirtual #49                 // Method org/apache/hadoop/hbase/regionserver/HRegionServer.getRegionServerSpaceQuotaManager:()Lorg/apache/hadoop/hbase/quotas/RegionServerSpaceQuotaManager;
      78: astore        9
      80: getstatic     #8                  // Field TEST_UTIL:Lorg/apache/hadoop/hbase/HBaseTestingUtility;
      83: invokevirtual #9                  // Method org/apache/hadoop/hbase/HBaseTestingUtility.getConfiguration:()Lorg/apache/hadoop/conf/Configuration;
      86: ldc2_w        #24                 // long 30000l
      89: new           #50                 // class org/apache/hadoop/hbase/quotas/TestQuotaStatusRPCs$2
      92: dup
      93: aload_0
      94: aload         9
      96: aload         6
      98: invokespecial #51                 // Method org/apache/hadoop/hbase/quotas/TestQuotaStatusRPCs$2."<init>":(Lorg/apache/hadoop/hbase/quotas/TestQuotaStatusRPCs;Lorg/apache/hadoop/hbase/quotas/RegionServerSpaceQuotaManager;Lorg/apache/hadoop/hbase/TableName;)V
     101: invokestatic  #28                 // Method org/apache/hadoop/hbase/Waiter.waitFor:(Lorg/apache/hadoop/conf/Configuration;JLorg/apache/hadoop/hbase/Waiter$Predicate;)J
     104: pop2
     105: getstatic     #8                  // Field TEST_UTIL:Lorg/apache/hadoop/hbase/HBaseTestingUtility;
     108: invokevirtual #29                 // Method org/apache/hadoop/hbase/HBaseTestingUtility.getAdmin:()Lorg/apache/hadoop/hbase/client/Admin;
     111: aload         8
     113: invokevirtual #52                 // Method org/apache/hadoop/hbase/regionserver/HRegionServer.getServerName:()Lorg/apache/hadoop/hbase/ServerName;
     116: invokeinterface #53,  2           // InterfaceMethod org/apache/hadoop/hbase/client/Admin.getRegionServerSpaceQuotaSnapshots:(Lorg/apache/hadoop/hbase/ServerName;)Ljava/util/Map;
     121: astore        10
     123: aload         10
     125: aload         6
     127: invokeinterface #31,  2           // InterfaceMethod java/util/Map.get:(Ljava/lang/Object;)Ljava/lang/Object;
     132: checkcast     #54                 // class org/apache/hadoop/hbase/quotas/SpaceQuotaSnapshot
     135: astore        11
     137: new           #33                 // class java/lang/StringBuilder
     140: dup
     141: invokespecial #34                 // Method java/lang/StringBuilder."<init>":()V
     144: ldc           #55                 // String Did not find snapshot for
     146: invokevirtual #36                 // Method java/lang/StringBuilder.append:(Ljava/lang/String;)Ljava/lang/StringBuilder;
     149: aload         6
     151: invokevirtual #37                 // Method java/lang/StringBuilder.append:(Ljava/lang/Object;)Ljava/lang/StringBuilder;
     154: invokevirtual #38                 // Method java/lang/StringBuilder.toString:()Ljava/lang/String;
     157: aload         11
     159: invokestatic  #39                 // Method org/junit/Assert.assertNotNull:(Ljava/lang/String;Ljava/lang/Object;)V
     162: new           #33                 // class java/lang/StringBuilder
     165: dup
     166: invokespecial #34                 // Method java/lang/StringBuilder."<init>":()V
     169: ldc           #56                 // String Observed table usage was
     171: invokevirtual #36                 // Method java/lang/StringBuilder.append:(Ljava/lang/String;)Ljava/lang/StringBuilder;
     174: aload         11
     176: invokevirtual #57                 // Method org/apache/hadoop/hbase/quotas/SpaceQuotaSnapshot.getUsage:()J
     179: invokevirtual #58                 // Method java/lang/StringBuilder.append:(J)Ljava/lang/StringBuilder;
     182: invokevirtual #38                 // Method java/lang/StringBuilder.toString:()Ljava/lang/String;
     185: aload         11
     187: invokevirtual #57                 // Method org/apache/hadoop/hbase/quotas/SpaceQuotaSnapshot.getUsage:()J
     190: ldc2_w        #17                 // long 10240l
     193: lcmp
     194: iflt          201
     197: iconst_1
     198: goto          202
     201: iconst_0
     202: invokestatic  #42                 // Method org/junit/Assert.assertTrue:(Ljava/lang/String;Z)V
     205: ldc2_w        #43                 // long 1048576l
     208: aload         11
     210: invokevirtual #59                 // Method org/apache/hadoop/hbase/quotas/SpaceQuotaSnapshot.getLimit:()J
     213: invokestatic  #60                 // Method org/junit/Assert.assertEquals:(JJ)V
     216: aload         11
     218: invokevirtual #61                 // Method org/apache/hadoop/hbase/quotas/SpaceQuotaSnapshot.getQuotaStatus:()Lorg/apache/hadoop/hbase/quotas/SpaceQuotaSnapshot$SpaceQuotaStatus;
     221: astore        12
     223: aload         12
     225: invokevirtual #62                 // Method org/apache/hadoop/hbase/quotas/SpaceQuotaSnapshot$SpaceQuotaStatus.isInViolation:()Z
     228: invokestatic  #63                 // Method org/junit/Assert.assertFalse:(Z)V
     231: return

  public void testQuotaEnforcementsFromRS() throws java.lang.Exception;
    Code:
       0: ldc2_w        #64                 // long 8192l
       3: lstore_1
       4: ldc2_w        #17                 // long 10240l
       7: lstore_3
       8: bipush        10
      10: istore        5
      12: aload_0
      13: getfield      #16                 // Field helper:Lorg/apache/hadoop/hbase/quotas/SpaceQuotaHelperForTests;
      16: bipush        10
      18: invokevirtual #19                 // Method org/apache/hadoop/hbase/quotas/SpaceQuotaHelperForTests.createTableWithRegions:(I)Lorg/apache/hadoop/hbase/TableName;
      21: astore        6
      23: aload         6
      25: ldc2_w        #64                 // long 8192l
      28: getstatic     #45                 // Field org/apache/hadoop/hbase/quotas/SpaceViolationPolicy.NO_INSERTS:Lorg/apache/hadoop/hbase/quotas/SpaceViolationPolicy;
      31: invokestatic  #46                 // Method org/apache/hadoop/hbase/quotas/QuotaSettingsFactory.limitTableSpace:(Lorg/apache/hadoop/hbase/TableName;JLorg/apache/hadoop/hbase/quotas/SpaceViolationPolicy;)Lorg/apache/hadoop/hbase/quotas/QuotaSettings;
      34: astore        7
      36: getstatic     #8                  // Field TEST_UTIL:Lorg/apache/hadoop/hbase/HBaseTestingUtility;
      39: invokevirtual #29                 // Method org/apache/hadoop/hbase/HBaseTestingUtility.getAdmin:()Lorg/apache/hadoop/hbase/client/Admin;
      42: aload         7
      44: invokeinterface #47,  2           // InterfaceMethod org/apache/hadoop/hbase/client/Admin.setQuota:(Lorg/apache/hadoop/hbase/quotas/QuotaSettings;)V
      49: aload_0
      50: getfield      #16                 // Field helper:Lorg/apache/hadoop/hbase/quotas/SpaceQuotaHelperForTests;
      53: aload         6
      55: ldc2_w        #17                 // long 10240l
      58: invokevirtual #20                 // Method org/apache/hadoop/hbase/quotas/SpaceQuotaHelperForTests.writeData:(Lorg/apache/hadoop/hbase/TableName;J)V
      61: goto          66
      64: astore        8
      66: getstatic     #8                  // Field TEST_UTIL:Lorg/apache/hadoop/hbase/HBaseTestingUtility;
      69: invokevirtual #21                 // Method org/apache/hadoop/hbase/HBaseTestingUtility.getMiniHBaseCluster:()Lorg/apache/hadoop/hbase/MiniHBaseCluster;
      72: iconst_0
      73: invokevirtual #48                 // Method org/apache/hadoop/hbase/MiniHBaseCluster.getRegionServer:(I)Lorg/apache/hadoop/hbase/regionserver/HRegionServer;
      76: astore        8
      78: aload         8
      80: invokevirtual #49                 // Method org/apache/hadoop/hbase/regionserver/HRegionServer.getRegionServerSpaceQuotaManager:()Lorg/apache/hadoop/hbase/quotas/RegionServerSpaceQuotaManager;
      83: astore        9
      85: getstatic     #8                  // Field TEST_UTIL:Lorg/apache/hadoop/hbase/HBaseTestingUtility;
      88: invokevirtual #9                  // Method org/apache/hadoop/hbase/HBaseTestingUtility.getConfiguration:()Lorg/apache/hadoop/conf/Configuration;
      91: ldc2_w        #24                 // long 30000l
      94: new           #68                 // class org/apache/hadoop/hbase/quotas/TestQuotaStatusRPCs$3
      97: dup
      98: aload_0
      99: aload         9
     101: aload         6
     103: invokespecial #69                 // Method org/apache/hadoop/hbase/quotas/TestQuotaStatusRPCs$3."<init>":(Lorg/apache/hadoop/hbase/quotas/TestQuotaStatusRPCs;Lorg/apache/hadoop/hbase/quotas/RegionServerSpaceQuotaManager;Lorg/apache/hadoop/hbase/TableName;)V
     106: invokestatic  #28                 // Method org/apache/hadoop/hbase/Waiter.waitFor:(Lorg/apache/hadoop/conf/Configuration;JLorg/apache/hadoop/hbase/Waiter$Predicate;)J
     109: pop2
     110: getstatic     #8                  // Field TEST_UTIL:Lorg/apache/hadoop/hbase/HBaseTestingUtility;
     113: invokevirtual #29                 // Method org/apache/hadoop/hbase/HBaseTestingUtility.getAdmin:()Lorg/apache/hadoop/hbase/client/Admin;
     116: aload         8
     118: invokevirtual #52                 // Method org/apache/hadoop/hbase/regionserver/HRegionServer.getServerName:()Lorg/apache/hadoop/hbase/ServerName;
     121: invokeinterface #53,  2           // InterfaceMethod org/apache/hadoop/hbase/client/Admin.getRegionServerSpaceQuotaSnapshots:(Lorg/apache/hadoop/hbase/ServerName;)Ljava/util/Map;
     126: astore        10
     128: aload         10
     130: aload         6
     132: invokeinterface #31,  2           // InterfaceMethod java/util/Map.get:(Ljava/lang/Object;)Ljava/lang/Object;
     137: checkcast     #54                 // class org/apache/hadoop/hbase/quotas/SpaceQuotaSnapshot
     140: astore        11
     142: new           #33                 // class java/lang/StringBuilder
     145: dup
     146: invokespecial #34                 // Method java/lang/StringBuilder."<init>":()V
     149: ldc           #55                 // String Did not find snapshot for
     151: invokevirtual #36                 // Method java/lang/StringBuilder.append:(Ljava/lang/String;)Ljava/lang/StringBuilder;
     154: aload         6
     156: invokevirtual #37                 // Method java/lang/StringBuilder.append:(Ljava/lang/Object;)Ljava/lang/StringBuilder;
     159: invokevirtual #38                 // Method java/lang/StringBuilder.toString:()Ljava/lang/String;
     162: aload         11
     164: invokestatic  #39                 // Method org/junit/Assert.assertNotNull:(Ljava/lang/String;Ljava/lang/Object;)V
     167: aload         11
     169: invokevirtual #61                 // Method org/apache/hadoop/hbase/quotas/SpaceQuotaSnapshot.getQuotaStatus:()Lorg/apache/hadoop/hbase/quotas/SpaceQuotaSnapshot$SpaceQuotaStatus;
     172: invokevirtual #62                 // Method org/apache/hadoop/hbase/quotas/SpaceQuotaSnapshot$SpaceQuotaStatus.isInViolation:()Z
     175: invokestatic  #70                 // Method org/junit/Assert.assertTrue:(Z)V
     178: getstatic     #45                 // Field org/apache/hadoop/hbase/quotas/SpaceViolationPolicy.NO_INSERTS:Lorg/apache/hadoop/hbase/quotas/SpaceViolationPolicy;
     181: aload         11
     183: invokevirtual #61                 // Method org/apache/hadoop/hbase/quotas/SpaceQuotaSnapshot.getQuotaStatus:()Lorg/apache/hadoop/hbase/quotas/SpaceQuotaSnapshot$SpaceQuotaStatus;
     186: invokevirtual #71                 // Method org/apache/hadoop/hbase/quotas/SpaceQuotaSnapshot$SpaceQuotaStatus.getPolicy:()Ljava/util/Optional;
     189: invokevirtual #72                 // Method java/util/Optional.get:()Ljava/lang/Object;
     192: invokestatic  #73                 // Method org/junit/Assert.assertEquals:(Ljava/lang/Object;Ljava/lang/Object;)V
     195: return
    Exception table:
       from    to  target type
          49    61    64   Class org/apache/hadoop/hbase/client/RetriesExhaustedWithDetailsException
          49    61    64   Class org/apache/hadoop/hbase/quotas/SpaceLimitingException

  public void testQuotaStatusFromMaster() throws java.lang.Exception;
    Code:
       0: ldc2_w        #74                 // long 25600l
       3: lstore_1
       4: ldc2_w        #76                 // long 1024l
       7: lstore_3
       8: ldc2_w        #78                 // long 9223372036854775807l
      11: lstore        5
      13: bipush        10
      15: istore        7
      17: aload_0
      18: getfield      #16                 // Field helper:Lorg/apache/hadoop/hbase/quotas/SpaceQuotaHelperForTests;
      21: bipush        10
      23: invokevirtual #19                 // Method org/apache/hadoop/hbase/quotas/SpaceQuotaHelperForTests.createTableWithRegions:(I)Lorg/apache/hadoop/hbase/TableName;
      26: astore        8
      28: aload         8
      30: ldc2_w        #74                 // long 25600l
      33: getstatic     #45                 // Field org/apache/hadoop/hbase/quotas/SpaceViolationPolicy.NO_INSERTS:Lorg/apache/hadoop/hbase/quotas/SpaceViolationPolicy;
      36: invokestatic  #46                 // Method org/apache/hadoop/hbase/quotas/QuotaSettingsFactory.limitTableSpace:(Lorg/apache/hadoop/hbase/TableName;JLorg/apache/hadoop/hbase/quotas/SpaceViolationPolicy;)Lorg/apache/hadoop/hbase/quotas/QuotaSettings;
      39: astore        9
      41: getstatic     #8                  // Field TEST_UTIL:Lorg/apache/hadoop/hbase/HBaseTestingUtility;
      44: invokevirtual #29                 // Method org/apache/hadoop/hbase/HBaseTestingUtility.getAdmin:()Lorg/apache/hadoop/hbase/client/Admin;
      47: aload         9
      49: invokeinterface #47,  2           // InterfaceMethod org/apache/hadoop/hbase/client/Admin.setQuota:(Lorg/apache/hadoop/hbase/quotas/QuotaSettings;)V
      54: aload         8
      56: invokevirtual #80                 // Method org/apache/hadoop/hbase/TableName.getNamespaceAsString:()Ljava/lang/String;
      59: ldc2_w        #78                 // long 9223372036854775807l
      62: getstatic     #45                 // Field org/apache/hadoop/hbase/quotas/SpaceViolationPolicy.NO_INSERTS:Lorg/apache/hadoop/hbase/quotas/SpaceViolationPolicy;
      65: invokestatic  #81                 // Method org/apache/hadoop/hbase/quotas/QuotaSettingsFactory.limitNamespaceSpace:(Ljava/lang/String;JLorg/apache/hadoop/hbase/quotas/SpaceViolationPolicy;)Lorg/apache/hadoop/hbase/quotas/QuotaSettings;
      68: astore        10
      70: getstatic     #8                  // Field TEST_UTIL:Lorg/apache/hadoop/hbase/HBaseTestingUtility;
      73: invokevirtual #29                 // Method org/apache/hadoop/hbase/HBaseTestingUtility.getAdmin:()Lorg/apache/hadoop/hbase/client/Admin;
      76: aload         10
      78: invokeinterface #47,  2           // InterfaceMethod org/apache/hadoop/hbase/client/Admin.setQuota:(Lorg/apache/hadoop/hbase/quotas/QuotaSettings;)V
      83: aload_0
      84: getfield      #16                 // Field helper:Lorg/apache/hadoop/hbase/quotas/SpaceQuotaHelperForTests;
      87: aload         8
      89: ldc2_w        #76                 // long 1024l
      92: invokevirtual #20                 // Method org/apache/hadoop/hbase/quotas/SpaceQuotaHelperForTests.writeData:(Lorg/apache/hadoop/hbase/TableName;J)V
      95: getstatic     #8                  // Field TEST_UTIL:Lorg/apache/hadoop/hbase/HBaseTestingUtility;
      98: invokevirtual #82                 // Method org/apache/hadoop/hbase/HBaseTestingUtility.getConnection:()Lorg/apache/hadoop/hbase/client/Connection;
     101: astore        11
     103: getstatic     #8                  // Field TEST_UTIL:Lorg/apache/hadoop/hbase/HBaseTestingUtility;
     106: invokevirtual #9                  // Method org/apache/hadoop/hbase/HBaseTestingUtility.getConfiguration:()Lorg/apache/hadoop/conf/Configuration;
     109: ldc2_w        #24                 // long 30000l
     112: new           #83                 // class org/apache/hadoop/hbase/quotas/TestQuotaStatusRPCs$4
     115: dup
     116: aload_0
     117: aload         11
     119: aload         8
     121: invokespecial #84                 // Method org/apache/hadoop/hbase/quotas/TestQuotaStatusRPCs$4."<init>":(Lorg/apache/hadoop/hbase/quotas/TestQuotaStatusRPCs;Lorg/apache/hadoop/hbase/client/Connection;Lorg/apache/hadoop/hbase/TableName;)V
     124: invokestatic  #28                 // Method org/apache/hadoop/hbase/Waiter.waitFor:(Lorg/apache/hadoop/conf/Configuration;JLorg/apache/hadoop/hbase/Waiter$Predicate;)J
     127: pop2
     128: new           #85                 // class java/util/concurrent/atomic/AtomicReference
     131: dup
     132: invokespecial #86                 // Method java/util/concurrent/atomic/AtomicReference."<init>":()V
     135: astore        12
     137: getstatic     #8                  // Field TEST_UTIL:Lorg/apache/hadoop/hbase/HBaseTestingUtility;
     140: invokevirtual #9                  // Method org/apache/hadoop/hbase/HBaseTestingUtility.getConfiguration:()Lorg/apache/hadoop/conf/Configuration;
     143: ldc2_w        #87                 // long 30000000l
     146: new           #89                 // class org/apache/hadoop/hbase/quotas/TestQuotaStatusRPCs$5
     149: dup
     150: aload_0
     151: aload         11
     153: aload         8
     155: aload         12
     157: invokespecial #90                 // Method org/apache/hadoop/hbase/quotas/TestQuotaStatusRPCs$5."<init>":(Lorg/apache/hadoop/hbase/quotas/TestQuotaStatusRPCs;Lorg/apache/hadoop/hbase/client/Connection;Lorg/apache/hadoop/hbase/TableName;Ljava/util/concurrent/atomic/AtomicReference;)V
     160: invokestatic  #28                 // Method org/apache/hadoop/hbase/Waiter.waitFor:(Lorg/apache/hadoop/conf/Configuration;JLorg/apache/hadoop/hbase/Waiter$Predicate;)J
     163: pop2
     164: aload         11
     166: invokeinterface #91,  1           // InterfaceMethod org/apache/hadoop/hbase/client/Connection.getAdmin:()Lorg/apache/hadoop/hbase/client/Admin;
     171: aload         8
     173: invokeinterface #92,  2           // InterfaceMethod org/apache/hadoop/hbase/client/Admin.getCurrentSpaceQuotaSnapshot:(Lorg/apache/hadoop/hbase/TableName;)Lorg/apache/hadoop/hbase/quotas/SpaceQuotaSnapshotView;
     178: checkcast     #54                 // class org/apache/hadoop/hbase/quotas/SpaceQuotaSnapshot
     181: astore        13
     183: new           #33                 // class java/lang/StringBuilder
     186: dup
     187: invokespecial #34                 // Method java/lang/StringBuilder."<init>":()V
     190: ldc           #93                 // String QuotaSnapshot for
     192: invokevirtual #36                 // Method java/lang/StringBuilder.append:(Ljava/lang/String;)Ljava/lang/StringBuilder;
     195: aload         8
     197: invokevirtual #37                 // Method java/lang/StringBuilder.append:(Ljava/lang/Object;)Ljava/lang/StringBuilder;
     200: ldc           #94                 // String  should be non-null and not in violation
     202: invokevirtual #36                 // Method java/lang/StringBuilder.append:(Ljava/lang/String;)Ljava/lang/StringBuilder;
     205: invokevirtual #38                 // Method java/lang/StringBuilder.toString:()Ljava/lang/String;
     208: aload         13
     210: ifnull        228
     213: aload         13
     215: invokevirtual #61                 // Method org/apache/hadoop/hbase/quotas/SpaceQuotaSnapshot.getQuotaStatus:()Lorg/apache/hadoop/hbase/quotas/SpaceQuotaSnapshot$SpaceQuotaStatus;
     218: invokevirtual #62                 // Method org/apache/hadoop/hbase/quotas/SpaceQuotaSnapshot$SpaceQuotaStatus.isInViolation:()Z
     221: ifne          228
     224: iconst_1
     225: goto          229
     228: iconst_0
     229: invokestatic  #42                 // Method org/junit/Assert.assertTrue:(Ljava/lang/String;Z)V
     232: aload_0
     233: getfield      #16                 // Field helper:Lorg/apache/hadoop/hbase/quotas/SpaceQuotaHelperForTests;
     236: aload         8
     238: ldc2_w        #95                 // long 2048l
     241: invokevirtual #20                 // Method org/apache/hadoop/hbase/quotas/SpaceQuotaHelperForTests.writeData:(Lorg/apache/hadoop/hbase/TableName;J)V
     244: goto          249
     247: astore        14
     249: getstatic     #8                  // Field TEST_UTIL:Lorg/apache/hadoop/hbase/HBaseTestingUtility;
     252: invokevirtual #9                  // Method org/apache/hadoop/hbase/HBaseTestingUtility.getConfiguration:()Lorg/apache/hadoop/conf/Configuration;
     255: ldc2_w        #24                 // long 30000l
     258: new           #97                 // class org/apache/hadoop/hbase/quotas/TestQuotaStatusRPCs$6
     261: dup
     262: aload_0
     263: aload         11
     265: aload         8
     267: invokespecial #98                 // Method org/apache/hadoop/hbase/quotas/TestQuotaStatusRPCs$6."<init>":(Lorg/apache/hadoop/hbase/quotas/TestQuotaStatusRPCs;Lorg/apache/hadoop/hbase/client/Connection;Lorg/apache/hadoop/hbase/TableName;)V
     270: invokestatic  #28                 // Method org/apache/hadoop/hbase/Waiter.waitFor:(Lorg/apache/hadoop/conf/Configuration;JLorg/apache/hadoop/hbase/Waiter$Predicate;)J
     273: pop2
     274: getstatic     #8                  // Field TEST_UTIL:Lorg/apache/hadoop/hbase/HBaseTestingUtility;
     277: invokevirtual #9                  // Method org/apache/hadoop/hbase/HBaseTestingUtility.getConfiguration:()Lorg/apache/hadoop/conf/Configuration;
     280: ldc2_w        #24                 // long 30000l
     283: new           #99                 // class org/apache/hadoop/hbase/quotas/TestQuotaStatusRPCs$7
     286: dup
     287: aload_0
     288: aload         11
     290: aload         8
     292: aload         12
     294: invokespecial #100                // Method org/apache/hadoop/hbase/quotas/TestQuotaStatusRPCs$7."<init>":(Lorg/apache/hadoop/hbase/quotas/TestQuotaStatusRPCs;Lorg/apache/hadoop/hbase/client/Connection;Lorg/apache/hadoop/hbase/TableName;Ljava/util/concurrent/atomic/AtomicReference;)V
     297: invokestatic  #28                 // Method org/apache/hadoop/hbase/Waiter.waitFor:(Lorg/apache/hadoop/conf/Configuration;JLorg/apache/hadoop/hbase/Waiter$Predicate;)J
     300: pop2
     301: return
    Exception table:
       from    to  target type
         232   244   247   Class org/apache/hadoop/hbase/client/RetriesExhaustedWithDetailsException
         232   244   247   Class org/apache/hadoop/hbase/quotas/SpaceLimitingException

  static org.slf4j.Logger access$000();
    Code:
       0: getstatic     #3                  // Field LOG:Lorg/slf4j/Logger;
       3: areturn

  static int access$100(org.apache.hadoop.hbase.quotas.TestQuotaStatusRPCs, org.apache.hadoop.hbase.TableName, java.util.Map);
    Code:
       0: aload_0
       1: aload_1
       2: aload_2
       3: invokespecial #2                  // Method countRegionsForTable:(Lorg/apache/hadoop/hbase/TableName;Ljava/util/Map;)I
       6: ireturn

  static int access$200(org.apache.hadoop.hbase.quotas.TestQuotaStatusRPCs, org.apache.hadoop.hbase.TableName, java.util.Map);
    Code:
       0: aload_0
       1: aload_1
       2: aload_2
       3: invokespecial #1                  // Method getTableSize:(Lorg/apache/hadoop/hbase/TableName;Ljava/util/Map;)I
       6: ireturn

  static {};
    Code:
       0: ldc           #112                // class org/apache/hadoop/hbase/quotas/TestQuotaStatusRPCs
       2: invokestatic  #113                // Method org/apache/hadoop/hbase/HBaseClassTestRule.forClass:(Ljava/lang/Class;)Lorg/apache/hadoop/hbase/HBaseClassTestRule;
       5: putstatic     #114                // Field CLASS_RULE:Lorg/apache/hadoop/hbase/HBaseClassTestRule;
       8: ldc           #112                // class org/apache/hadoop/hbase/quotas/TestQuotaStatusRPCs
      10: invokestatic  #115                // Method org/slf4j/LoggerFactory.getLogger:(Ljava/lang/Class;)Lorg/slf4j/Logger;
      13: putstatic     #3                  // Field LOG:Lorg/slf4j/Logger;
      16: new           #116                // class org/apache/hadoop/hbase/HBaseTestingUtility
      19: dup
      20: invokespecial #117                // Method org/apache/hadoop/hbase/HBaseTestingUtility."<init>":()V
      23: putstatic     #8                  // Field TEST_UTIL:Lorg/apache/hadoop/hbase/HBaseTestingUtility;
      26: new           #118                // class java/util/concurrent/atomic/AtomicLong
      29: dup
      30: lconst_0
      31: invokespecial #119                // Method java/util/concurrent/atomic/AtomicLong."<init>":(J)V
      34: putstatic     #14                 // Field COUNTER:Ljava/util/concurrent/atomic/AtomicLong;
      37: return
}
