Compiled from "TestRegionLocationCaching.java"
public class org.apache.hadoop.hbase.client.TestRegionLocationCaching {
  public static final org.apache.hadoop.hbase.HBaseClassTestRule CLASS_RULE;

  public org.apache.hadoop.hbase.client.TestRegionLocationCaching();
    Code:
       0: aload_0
       1: invokespecial #1                  // Method java/lang/Object."<init>":()V
       4: return

  public static void setUpBeforeClass() throws java.lang.Exception;
    Code:
       0: getstatic     #2                  // Field TEST_UTIL:Lorg/apache/hadoop/hbase/HBaseTestingUtility;
       3: getstatic     #3                  // Field SLAVES:I
       6: invokevirtual #4                  // Method org/apache/hadoop/hbase/HBaseTestingUtility.startMiniCluster:(I)Lorg/apache/hadoop/hbase/MiniHBaseCluster;
       9: pop
      10: getstatic     #2                  // Field TEST_UTIL:Lorg/apache/hadoop/hbase/HBaseTestingUtility;
      13: getstatic     #5                  // Field TABLE_NAME:Lorg/apache/hadoop/hbase/TableName;
      16: iconst_1
      17: anewarray     #6                  // class "[B"
      20: dup
      21: iconst_0
      22: getstatic     #7                  // Field FAMILY:[B
      25: aastore
      26: invokevirtual #8                  // Method org/apache/hadoop/hbase/HBaseTestingUtility.createTable:(Lorg/apache/hadoop/hbase/TableName;[[B)Lorg/apache/hadoop/hbase/client/Table;
      29: pop
      30: getstatic     #2                  // Field TEST_UTIL:Lorg/apache/hadoop/hbase/HBaseTestingUtility;
      33: getstatic     #5                  // Field TABLE_NAME:Lorg/apache/hadoop/hbase/TableName;
      36: invokevirtual #9                  // Method org/apache/hadoop/hbase/HBaseTestingUtility.waitUntilAllRegionsAssigned:(Lorg/apache/hadoop/hbase/TableName;)V
      39: return

  public static void tearDownAfterClass() throws java.lang.Exception;
    Code:
       0: getstatic     #2                  // Field TEST_UTIL:Lorg/apache/hadoop/hbase/HBaseTestingUtility;
       3: invokevirtual #10                 // Method org/apache/hadoop/hbase/HBaseTestingUtility.shutdownMiniCluster:()V
       6: return

  public void testCachingForHTableSinglePut() throws java.lang.Exception;
    Code:
       0: ldc           #11                 // String htable_single_put
       2: invokestatic  #12                 // Method org/apache/hadoop/hbase/util/Bytes.toBytes:(Ljava/lang/String;)[B
       5: astore_1
       6: ldc           #13                 // String value
       8: invokestatic  #12                 // Method org/apache/hadoop/hbase/util/Bytes.toBytes:(Ljava/lang/String;)[B
      11: astore_2
      12: new           #14                 // class org/apache/hadoop/hbase/client/Put
      15: dup
      16: aload_1
      17: invokespecial #15                 // Method org/apache/hadoop/hbase/client/Put."<init>":([B)V
      20: astore_3
      21: aload_3
      22: getstatic     #7                  // Field FAMILY:[B
      25: getstatic     #16                 // Field QUALIFIER:[B
      28: aload_2
      29: invokevirtual #17                 // Method org/apache/hadoop/hbase/client/Put.addColumn:([B[B[B)Lorg/apache/hadoop/hbase/client/Put;
      32: pop
      33: getstatic     #2                  // Field TEST_UTIL:Lorg/apache/hadoop/hbase/HBaseTestingUtility;
      36: invokevirtual #18                 // Method org/apache/hadoop/hbase/HBaseTestingUtility.getConnection:()Lorg/apache/hadoop/hbase/client/Connection;
      39: getstatic     #5                  // Field TABLE_NAME:Lorg/apache/hadoop/hbase/TableName;
      42: invokeinterface #19,  2           // InterfaceMethod org/apache/hadoop/hbase/client/Connection.getTable:(Lorg/apache/hadoop/hbase/TableName;)Lorg/apache/hadoop/hbase/client/Table;
      47: astore        4
      49: aconst_null
      50: astore        5
      52: aload         4
      54: aload_3
      55: invokeinterface #20,  2           // InterfaceMethod org/apache/hadoop/hbase/client/Table.put:(Lorg/apache/hadoop/hbase/client/Put;)V
      60: aload         4
      62: ifnull        155
      65: aload         5
      67: ifnull        92
      70: aload         4
      72: invokeinterface #21,  1           // InterfaceMethod org/apache/hadoop/hbase/client/Table.close:()V
      77: goto          155
      80: astore        6
      82: aload         5
      84: aload         6
      86: invokevirtual #23                 // Method java/lang/Throwable.addSuppressed:(Ljava/lang/Throwable;)V
      89: goto          155
      92: aload         4
      94: invokeinterface #21,  1           // InterfaceMethod org/apache/hadoop/hbase/client/Table.close:()V
      99: goto          155
     102: astore        6
     104: aload         6
     106: astore        5
     108: aload         6
     110: athrow
     111: astore        7
     113: aload         4
     115: ifnull        152
     118: aload         5
     120: ifnull        145
     123: aload         4
     125: invokeinterface #21,  1           // InterfaceMethod org/apache/hadoop/hbase/client/Table.close:()V
     130: goto          152
     133: astore        8
     135: aload         5
     137: aload         8
     139: invokevirtual #23                 // Method java/lang/Throwable.addSuppressed:(Ljava/lang/Throwable;)V
     142: goto          152
     145: aload         4
     147: invokeinterface #21,  1           // InterfaceMethod org/apache/hadoop/hbase/client/Table.close:()V
     152: aload         7
     154: athrow
     155: aload_0
     156: getstatic     #5                  // Field TABLE_NAME:Lorg/apache/hadoop/hbase/TableName;
     159: getstatic     #2                  // Field TEST_UTIL:Lorg/apache/hadoop/hbase/HBaseTestingUtility;
     162: invokevirtual #18                 // Method org/apache/hadoop/hbase/HBaseTestingUtility.getConnection:()Lorg/apache/hadoop/hbase/client/Connection;
     165: invokespecial #24                 // Method checkRegionLocationIsCached:(Lorg/apache/hadoop/hbase/TableName;Lorg/apache/hadoop/hbase/client/Connection;)V
     168: getstatic     #5                  // Field TABLE_NAME:Lorg/apache/hadoop/hbase/TableName;
     171: aload_1
     172: getstatic     #7                  // Field FAMILY:[B
     175: getstatic     #16                 // Field QUALIFIER:[B
     178: invokestatic  #25                 // Method checkExistence:(Lorg/apache/hadoop/hbase/TableName;[B[B[B)V
     181: return
    Exception table:
       from    to  target type
          70    77    80   Class java/lang/Throwable
          52    60   102   Class java/lang/Throwable
          52    60   111   any
         123   130   133   Class java/lang/Throwable
         102   113   111   any

  public void testCachingForHTableMultiPut() throws java.lang.Exception;
    Code:
       0: new           #26                 // class java/util/ArrayList
       3: dup
       4: invokespecial #27                 // Method java/util/ArrayList."<init>":()V
       7: astore_1
       8: iconst_0
       9: istore_2
      10: iload_2
      11: bipush        10
      13: if_icmpge     97
      16: new           #14                 // class org/apache/hadoop/hbase/client/Put
      19: dup
      20: new           #28                 // class java/lang/StringBuilder
      23: dup
      24: invokespecial #29                 // Method java/lang/StringBuilder."<init>":()V
      27: ldc           #30                 // String htable_multi_put
      29: invokevirtual #31                 // Method java/lang/StringBuilder.append:(Ljava/lang/String;)Ljava/lang/StringBuilder;
      32: iload_2
      33: invokevirtual #32                 // Method java/lang/StringBuilder.append:(I)Ljava/lang/StringBuilder;
      36: invokevirtual #33                 // Method java/lang/StringBuilder.toString:()Ljava/lang/String;
      39: invokestatic  #12                 // Method org/apache/hadoop/hbase/util/Bytes.toBytes:(Ljava/lang/String;)[B
      42: invokespecial #15                 // Method org/apache/hadoop/hbase/client/Put."<init>":([B)V
      45: astore_3
      46: new           #28                 // class java/lang/StringBuilder
      49: dup
      50: invokespecial #29                 // Method java/lang/StringBuilder."<init>":()V
      53: ldc           #34                 // String value_
      55: invokevirtual #31                 // Method java/lang/StringBuilder.append:(Ljava/lang/String;)Ljava/lang/StringBuilder;
      58: iload_2
      59: invokevirtual #32                 // Method java/lang/StringBuilder.append:(I)Ljava/lang/StringBuilder;
      62: invokevirtual #33                 // Method java/lang/StringBuilder.toString:()Ljava/lang/String;
      65: invokestatic  #12                 // Method org/apache/hadoop/hbase/util/Bytes.toBytes:(Ljava/lang/String;)[B
      68: astore        4
      70: aload_3
      71: getstatic     #7                  // Field FAMILY:[B
      74: getstatic     #16                 // Field QUALIFIER:[B
      77: aload         4
      79: invokevirtual #17                 // Method org/apache/hadoop/hbase/client/Put.addColumn:([B[B[B)Lorg/apache/hadoop/hbase/client/Put;
      82: pop
      83: aload_1
      84: aload_3
      85: invokeinterface #35,  2           // InterfaceMethod java/util/List.add:(Ljava/lang/Object;)Z
      90: pop
      91: iinc          2, 1
      94: goto          10
      97: getstatic     #2                  // Field TEST_UTIL:Lorg/apache/hadoop/hbase/HBaseTestingUtility;
     100: invokevirtual #18                 // Method org/apache/hadoop/hbase/HBaseTestingUtility.getConnection:()Lorg/apache/hadoop/hbase/client/Connection;
     103: getstatic     #5                  // Field TABLE_NAME:Lorg/apache/hadoop/hbase/TableName;
     106: invokeinterface #19,  2           // InterfaceMethod org/apache/hadoop/hbase/client/Connection.getTable:(Lorg/apache/hadoop/hbase/TableName;)Lorg/apache/hadoop/hbase/client/Table;
     111: astore_2
     112: aconst_null
     113: astore_3
     114: aload_2
     115: aload_1
     116: invokeinterface #36,  2           // InterfaceMethod org/apache/hadoop/hbase/client/Table.put:(Ljava/util/List;)V
     121: aload_2
     122: ifnull        205
     125: aload_3
     126: ifnull        149
     129: aload_2
     130: invokeinterface #21,  1           // InterfaceMethod org/apache/hadoop/hbase/client/Table.close:()V
     135: goto          205
     138: astore        4
     140: aload_3
     141: aload         4
     143: invokevirtual #23                 // Method java/lang/Throwable.addSuppressed:(Ljava/lang/Throwable;)V
     146: goto          205
     149: aload_2
     150: invokeinterface #21,  1           // InterfaceMethod org/apache/hadoop/hbase/client/Table.close:()V
     155: goto          205
     158: astore        4
     160: aload         4
     162: astore_3
     163: aload         4
     165: athrow
     166: astore        5
     168: aload_2
     169: ifnull        202
     172: aload_3
     173: ifnull        196
     176: aload_2
     177: invokeinterface #21,  1           // InterfaceMethod org/apache/hadoop/hbase/client/Table.close:()V
     182: goto          202
     185: astore        6
     187: aload_3
     188: aload         6
     190: invokevirtual #23                 // Method java/lang/Throwable.addSuppressed:(Ljava/lang/Throwable;)V
     193: goto          202
     196: aload_2
     197: invokeinterface #21,  1           // InterfaceMethod org/apache/hadoop/hbase/client/Table.close:()V
     202: aload         5
     204: athrow
     205: aload_0
     206: getstatic     #5                  // Field TABLE_NAME:Lorg/apache/hadoop/hbase/TableName;
     209: getstatic     #2                  // Field TEST_UTIL:Lorg/apache/hadoop/hbase/HBaseTestingUtility;
     212: invokevirtual #18                 // Method org/apache/hadoop/hbase/HBaseTestingUtility.getConnection:()Lorg/apache/hadoop/hbase/client/Connection;
     215: invokespecial #24                 // Method checkRegionLocationIsCached:(Lorg/apache/hadoop/hbase/TableName;Lorg/apache/hadoop/hbase/client/Connection;)V
     218: iconst_0
     219: istore_2
     220: iload_2
     221: bipush        10
     223: if_icmpge     266
     226: getstatic     #5                  // Field TABLE_NAME:Lorg/apache/hadoop/hbase/TableName;
     229: new           #28                 // class java/lang/StringBuilder
     232: dup
     233: invokespecial #29                 // Method java/lang/StringBuilder."<init>":()V
     236: ldc           #30                 // String htable_multi_put
     238: invokevirtual #31                 // Method java/lang/StringBuilder.append:(Ljava/lang/String;)Ljava/lang/StringBuilder;
     241: iload_2
     242: invokevirtual #32                 // Method java/lang/StringBuilder.append:(I)Ljava/lang/StringBuilder;
     245: invokevirtual #33                 // Method java/lang/StringBuilder.toString:()Ljava/lang/String;
     248: invokestatic  #12                 // Method org/apache/hadoop/hbase/util/Bytes.toBytes:(Ljava/lang/String;)[B
     251: getstatic     #7                  // Field FAMILY:[B
     254: getstatic     #16                 // Field QUALIFIER:[B
     257: invokestatic  #25                 // Method checkExistence:(Lorg/apache/hadoop/hbase/TableName;[B[B[B)V
     260: iinc          2, 1
     263: goto          220
     266: return
    Exception table:
       from    to  target type
         129   135   138   Class java/lang/Throwable
         114   121   158   Class java/lang/Throwable
         114   121   166   any
         176   182   185   Class java/lang/Throwable
         158   168   166   any

  static {};
    Code:
       0: ldc           #52                 // class org/apache/hadoop/hbase/client/TestRegionLocationCaching
       2: invokestatic  #53                 // Method org/apache/hadoop/hbase/HBaseClassTestRule.forClass:(Ljava/lang/Class;)Lorg/apache/hadoop/hbase/HBaseClassTestRule;
       5: putstatic     #54                 // Field CLASS_RULE:Lorg/apache/hadoop/hbase/HBaseClassTestRule;
       8: new           #55                 // class org/apache/hadoop/hbase/HBaseTestingUtility
      11: dup
      12: invokespecial #56                 // Method org/apache/hadoop/hbase/HBaseTestingUtility."<init>":()V
      15: putstatic     #2                  // Field TEST_UTIL:Lorg/apache/hadoop/hbase/HBaseTestingUtility;
      18: iconst_1
      19: putstatic     #3                  // Field SLAVES:I
      22: ldc           #57                 // String TestRegionLocationCaching
      24: invokestatic  #58                 // Method org/apache/hadoop/hbase/TableName.valueOf:(Ljava/lang/String;)Lorg/apache/hadoop/hbase/TableName;
      27: putstatic     #5                  // Field TABLE_NAME:Lorg/apache/hadoop/hbase/TableName;
      30: ldc           #59                 // String testFamily
      32: invokestatic  #12                 // Method org/apache/hadoop/hbase/util/Bytes.toBytes:(Ljava/lang/String;)[B
      35: putstatic     #7                  // Field FAMILY:[B
      38: ldc           #60                 // String testQualifier
      40: invokestatic  #12                 // Method org/apache/hadoop/hbase/util/Bytes.toBytes:(Ljava/lang/String;)[B
      43: putstatic     #16                 // Field QUALIFIER:[B
      46: return
}
