Compiled from "TestSplitLogWorker.java"
class org.apache.hadoop.hbase.regionserver.TestSplitLogWorker$DummyServer implements org.apache.hadoop.hbase.Server {
  public org.apache.hadoop.hbase.regionserver.TestSplitLogWorker$DummyServer(org.apache.hadoop.hbase.zookeeper.ZKWatcher, org.apache.hadoop.conf.Configuration);
    Code:
       0: aload_0
       1: invokespecial #1                  // Method java/lang/Object."<init>":()V
       4: aload_0
       5: aload_1
       6: putfield      #2                  // Field zkw:Lorg/apache/hadoop/hbase/zookeeper/ZKWatcher;
       9: aload_0
      10: aload_2
      11: putfield      #3                  // Field conf:Lorg/apache/hadoop/conf/Configuration;
      14: aload_0
      15: new           #4                  // class org/apache/hadoop/hbase/coordination/ZkCoordinatedStateManager
      18: dup
      19: aload_0
      20: invokespecial #5                  // Method org/apache/hadoop/hbase/coordination/ZkCoordinatedStateManager."<init>":(Lorg/apache/hadoop/hbase/Server;)V
      23: putfield      #6                  // Field cm:Lorg/apache/hadoop/hbase/CoordinatedStateManager;
      26: return

  public void abort(java.lang.String, java.lang.Throwable);
    Code:
       0: return

  public boolean isAborted();
    Code:
       0: iconst_0
       1: ireturn

  public void stop(java.lang.String);
    Code:
       0: return

  public boolean isStopped();
    Code:
       0: iconst_0
       1: ireturn

  public org.apache.hadoop.conf.Configuration getConfiguration();
    Code:
       0: aload_0
       1: getfield      #3                  // Field conf:Lorg/apache/hadoop/conf/Configuration;
       4: areturn

  public org.apache.hadoop.hbase.zookeeper.ZKWatcher getZooKeeper();
    Code:
       0: aload_0
       1: getfield      #2                  // Field zkw:Lorg/apache/hadoop/hbase/zookeeper/ZKWatcher;
       4: areturn

  public org.apache.hadoop.hbase.ServerName getServerName();
    Code:
       0: aconst_null
       1: areturn

  public org.apache.hadoop.hbase.CoordinatedStateManager getCoordinatedStateManager();
    Code:
       0: aload_0
       1: getfield      #6                  // Field cm:Lorg/apache/hadoop/hbase/CoordinatedStateManager;
       4: areturn

  public org.apache.hadoop.hbase.client.ClusterConnection getConnection();
    Code:
       0: aconst_null
       1: areturn

  public org.apache.hadoop.hbase.ChoreService getChoreService();
    Code:
       0: aconst_null
       1: areturn

  public org.apache.hadoop.hbase.client.ClusterConnection getClusterConnection();
    Code:
       0: aconst_null
       1: areturn

  public org.apache.hadoop.fs.FileSystem getFileSystem();
    Code:
       0: aconst_null
       1: areturn

  public boolean isStopping();
    Code:
       0: iconst_0
       1: ireturn

  public org.apache.hadoop.hbase.client.Connection createConnection(org.apache.hadoop.conf.Configuration) throws java.io.IOException;
    Code:
       0: aconst_null
       1: areturn

  public org.apache.hadoop.hbase.client.Connection getConnection();
    Code:
       0: aload_0
       1: invokevirtual #7                  // Method getConnection:()Lorg/apache/hadoop/hbase/client/ClusterConnection;
       4: areturn
}
