Compiled from "TestCompactor.java"
public class org.apache.hadoop.hbase.regionserver.compactions.TestCompactor$StoreFileWritersCapture$Writer {
  public java.util.ArrayList<org.apache.hadoop.hbase.KeyValue> kvs;

  public java.util.TreeMap<byte[], byte[]> data;

  public boolean hasMetadata;

  public org.apache.hadoop.hbase.regionserver.compactions.TestCompactor$StoreFileWritersCapture$Writer();
    Code:
       0: aload_0
       1: invokespecial #1                  // Method java/lang/Object."<init>":()V
       4: aload_0
       5: new           #2                  // class java/util/ArrayList
       8: dup
       9: invokespecial #3                  // Method java/util/ArrayList."<init>":()V
      12: putfield      #4                  // Field kvs:Ljava/util/ArrayList;
      15: aload_0
      16: new           #5                  // class java/util/TreeMap
      19: dup
      20: getstatic     #6                  // Field org/apache/hadoop/hbase/util/Bytes.BYTES_COMPARATOR:Ljava/util/Comparator;
      23: invokespecial #7                  // Method java/util/TreeMap."<init>":(Ljava/util/Comparator;)V
      26: putfield      #8                  // Field data:Ljava/util/TreeMap;
      29: return
}
