Compiled from "TestRpcServiceProtos.java"
public final class org.apache.hadoop.hbase.ipc.protobuf.generated.TestRpcServiceProtos$TestProtobufRpcProto$Stub extends org.apache.hadoop.hbase.ipc.protobuf.generated.TestRpcServiceProtos$TestProtobufRpcProto implements org.apache.hadoop.hbase.ipc.protobuf.generated.TestRpcServiceProtos$TestProtobufRpcProto$Interface {
  public com.google.protobuf.RpcChannel getChannel();
    Code:
       0: aload_0
       1: getfield      #3                  // Field channel:Lcom/google/protobuf/RpcChannel;
       4: areturn

  public void ping(com.google.protobuf.RpcController, org.apache.hadoop.hbase.ipc.protobuf.generated.TestProtos$EmptyRequestProto, com.google.protobuf.RpcCallback<org.apache.hadoop.hbase.ipc.protobuf.generated.TestProtos$EmptyResponseProto>);
    Code:
       0: aload_0
       1: getfield      #3                  // Field channel:Lcom/google/protobuf/RpcChannel;
       4: invokestatic  #4                  // Method getDescriptor:()Lcom/google/protobuf/Descriptors$ServiceDescriptor;
       7: invokevirtual #5                  // Method com/google/protobuf/Descriptors$ServiceDescriptor.getMethods:()Ljava/util/List;
      10: iconst_0
      11: invokeinterface #6,  2            // InterfaceMethod java/util/List.get:(I)Ljava/lang/Object;
      16: checkcast     #7                  // class com/google/protobuf/Descriptors$MethodDescriptor
      19: aload_1
      20: aload_2
      21: invokestatic  #8                  // Method org/apache/hadoop/hbase/ipc/protobuf/generated/TestProtos$EmptyResponseProto.getDefaultInstance:()Lorg/apache/hadoop/hbase/ipc/protobuf/generated/TestProtos$EmptyResponseProto;
      24: aload_3
      25: ldc           #9                  // class org/apache/hadoop/hbase/ipc/protobuf/generated/TestProtos$EmptyResponseProto
      27: invokestatic  #8                  // Method org/apache/hadoop/hbase/ipc/protobuf/generated/TestProtos$EmptyResponseProto.getDefaultInstance:()Lorg/apache/hadoop/hbase/ipc/protobuf/generated/TestProtos$EmptyResponseProto;
      30: invokestatic  #10                 // Method com/google/protobuf/RpcUtil.generalizeCallback:(Lcom/google/protobuf/RpcCallback;Ljava/lang/Class;Lcom/google/protobuf/Message;)Lcom/google/protobuf/RpcCallback;
      33: invokeinterface #11,  6           // InterfaceMethod com/google/protobuf/RpcChannel.callMethod:(Lcom/google/protobuf/Descriptors$MethodDescriptor;Lcom/google/protobuf/RpcController;Lcom/google/protobuf/Message;Lcom/google/protobuf/Message;Lcom/google/protobuf/RpcCallback;)V
      38: return

  public void echo(com.google.protobuf.RpcController, org.apache.hadoop.hbase.ipc.protobuf.generated.TestProtos$EchoRequestProto, com.google.protobuf.RpcCallback<org.apache.hadoop.hbase.ipc.protobuf.generated.TestProtos$EchoResponseProto>);
    Code:
       0: aload_0
       1: getfield      #3                  // Field channel:Lcom/google/protobuf/RpcChannel;
       4: invokestatic  #4                  // Method getDescriptor:()Lcom/google/protobuf/Descriptors$ServiceDescriptor;
       7: invokevirtual #5                  // Method com/google/protobuf/Descriptors$ServiceDescriptor.getMethods:()Ljava/util/List;
      10: iconst_1
      11: invokeinterface #6,  2            // InterfaceMethod java/util/List.get:(I)Ljava/lang/Object;
      16: checkcast     #7                  // class com/google/protobuf/Descriptors$MethodDescriptor
      19: aload_1
      20: aload_2
      21: invokestatic  #12                 // Method org/apache/hadoop/hbase/ipc/protobuf/generated/TestProtos$EchoResponseProto.getDefaultInstance:()Lorg/apache/hadoop/hbase/ipc/protobuf/generated/TestProtos$EchoResponseProto;
      24: aload_3
      25: ldc           #13                 // class org/apache/hadoop/hbase/ipc/protobuf/generated/TestProtos$EchoResponseProto
      27: invokestatic  #12                 // Method org/apache/hadoop/hbase/ipc/protobuf/generated/TestProtos$EchoResponseProto.getDefaultInstance:()Lorg/apache/hadoop/hbase/ipc/protobuf/generated/TestProtos$EchoResponseProto;
      30: invokestatic  #10                 // Method com/google/protobuf/RpcUtil.generalizeCallback:(Lcom/google/protobuf/RpcCallback;Ljava/lang/Class;Lcom/google/protobuf/Message;)Lcom/google/protobuf/RpcCallback;
      33: invokeinterface #11,  6           // InterfaceMethod com/google/protobuf/RpcChannel.callMethod:(Lcom/google/protobuf/Descriptors$MethodDescriptor;Lcom/google/protobuf/RpcController;Lcom/google/protobuf/Message;Lcom/google/protobuf/Message;Lcom/google/protobuf/RpcCallback;)V
      38: return

  public void error(com.google.protobuf.RpcController, org.apache.hadoop.hbase.ipc.protobuf.generated.TestProtos$EmptyRequestProto, com.google.protobuf.RpcCallback<org.apache.hadoop.hbase.ipc.protobuf.generated.TestProtos$EmptyResponseProto>);
    Code:
       0: aload_0
       1: getfield      #3                  // Field channel:Lcom/google/protobuf/RpcChannel;
       4: invokestatic  #4                  // Method getDescriptor:()Lcom/google/protobuf/Descriptors$ServiceDescriptor;
       7: invokevirtual #5                  // Method com/google/protobuf/Descriptors$ServiceDescriptor.getMethods:()Ljava/util/List;
      10: iconst_2
      11: invokeinterface #6,  2            // InterfaceMethod java/util/List.get:(I)Ljava/lang/Object;
      16: checkcast     #7                  // class com/google/protobuf/Descriptors$MethodDescriptor
      19: aload_1
      20: aload_2
      21: invokestatic  #8                  // Method org/apache/hadoop/hbase/ipc/protobuf/generated/TestProtos$EmptyResponseProto.getDefaultInstance:()Lorg/apache/hadoop/hbase/ipc/protobuf/generated/TestProtos$EmptyResponseProto;
      24: aload_3
      25: ldc           #9                  // class org/apache/hadoop/hbase/ipc/protobuf/generated/TestProtos$EmptyResponseProto
      27: invokestatic  #8                  // Method org/apache/hadoop/hbase/ipc/protobuf/generated/TestProtos$EmptyResponseProto.getDefaultInstance:()Lorg/apache/hadoop/hbase/ipc/protobuf/generated/TestProtos$EmptyResponseProto;
      30: invokestatic  #10                 // Method com/google/protobuf/RpcUtil.generalizeCallback:(Lcom/google/protobuf/RpcCallback;Ljava/lang/Class;Lcom/google/protobuf/Message;)Lcom/google/protobuf/RpcCallback;
      33: invokeinterface #11,  6           // InterfaceMethod com/google/protobuf/RpcChannel.callMethod:(Lcom/google/protobuf/Descriptors$MethodDescriptor;Lcom/google/protobuf/RpcController;Lcom/google/protobuf/Message;Lcom/google/protobuf/Message;Lcom/google/protobuf/RpcCallback;)V
      38: return

  public void pause(com.google.protobuf.RpcController, org.apache.hadoop.hbase.ipc.protobuf.generated.TestProtos$PauseRequestProto, com.google.protobuf.RpcCallback<org.apache.hadoop.hbase.ipc.protobuf.generated.TestProtos$EmptyResponseProto>);
    Code:
       0: aload_0
       1: getfield      #3                  // Field channel:Lcom/google/protobuf/RpcChannel;
       4: invokestatic  #4                  // Method getDescriptor:()Lcom/google/protobuf/Descriptors$ServiceDescriptor;
       7: invokevirtual #5                  // Method com/google/protobuf/Descriptors$ServiceDescriptor.getMethods:()Ljava/util/List;
      10: iconst_3
      11: invokeinterface #6,  2            // InterfaceMethod java/util/List.get:(I)Ljava/lang/Object;
      16: checkcast     #7                  // class com/google/protobuf/Descriptors$MethodDescriptor
      19: aload_1
      20: aload_2
      21: invokestatic  #8                  // Method org/apache/hadoop/hbase/ipc/protobuf/generated/TestProtos$EmptyResponseProto.getDefaultInstance:()Lorg/apache/hadoop/hbase/ipc/protobuf/generated/TestProtos$EmptyResponseProto;
      24: aload_3
      25: ldc           #9                  // class org/apache/hadoop/hbase/ipc/protobuf/generated/TestProtos$EmptyResponseProto
      27: invokestatic  #8                  // Method org/apache/hadoop/hbase/ipc/protobuf/generated/TestProtos$EmptyResponseProto.getDefaultInstance:()Lorg/apache/hadoop/hbase/ipc/protobuf/generated/TestProtos$EmptyResponseProto;
      30: invokestatic  #10                 // Method com/google/protobuf/RpcUtil.generalizeCallback:(Lcom/google/protobuf/RpcCallback;Ljava/lang/Class;Lcom/google/protobuf/Message;)Lcom/google/protobuf/RpcCallback;
      33: invokeinterface #11,  6           // InterfaceMethod com/google/protobuf/RpcChannel.callMethod:(Lcom/google/protobuf/Descriptors$MethodDescriptor;Lcom/google/protobuf/RpcController;Lcom/google/protobuf/Message;Lcom/google/protobuf/Message;Lcom/google/protobuf/RpcCallback;)V
      38: return

  public void addr(com.google.protobuf.RpcController, org.apache.hadoop.hbase.ipc.protobuf.generated.TestProtos$EmptyRequestProto, com.google.protobuf.RpcCallback<org.apache.hadoop.hbase.ipc.protobuf.generated.TestProtos$AddrResponseProto>);
    Code:
       0: aload_0
       1: getfield      #3                  // Field channel:Lcom/google/protobuf/RpcChannel;
       4: invokestatic  #4                  // Method getDescriptor:()Lcom/google/protobuf/Descriptors$ServiceDescriptor;
       7: invokevirtual #5                  // Method com/google/protobuf/Descriptors$ServiceDescriptor.getMethods:()Ljava/util/List;
      10: iconst_4
      11: invokeinterface #6,  2            // InterfaceMethod java/util/List.get:(I)Ljava/lang/Object;
      16: checkcast     #7                  // class com/google/protobuf/Descriptors$MethodDescriptor
      19: aload_1
      20: aload_2
      21: invokestatic  #14                 // Method org/apache/hadoop/hbase/ipc/protobuf/generated/TestProtos$AddrResponseProto.getDefaultInstance:()Lorg/apache/hadoop/hbase/ipc/protobuf/generated/TestProtos$AddrResponseProto;
      24: aload_3
      25: ldc           #15                 // class org/apache/hadoop/hbase/ipc/protobuf/generated/TestProtos$AddrResponseProto
      27: invokestatic  #14                 // Method org/apache/hadoop/hbase/ipc/protobuf/generated/TestProtos$AddrResponseProto.getDefaultInstance:()Lorg/apache/hadoop/hbase/ipc/protobuf/generated/TestProtos$AddrResponseProto;
      30: invokestatic  #10                 // Method com/google/protobuf/RpcUtil.generalizeCallback:(Lcom/google/protobuf/RpcCallback;Ljava/lang/Class;Lcom/google/protobuf/Message;)Lcom/google/protobuf/RpcCallback;
      33: invokeinterface #11,  6           // InterfaceMethod com/google/protobuf/RpcChannel.callMethod:(Lcom/google/protobuf/Descriptors$MethodDescriptor;Lcom/google/protobuf/RpcController;Lcom/google/protobuf/Message;Lcom/google/protobuf/Message;Lcom/google/protobuf/RpcCallback;)V
      38: return

  org.apache.hadoop.hbase.ipc.protobuf.generated.TestRpcServiceProtos$TestProtobufRpcProto$Stub(com.google.protobuf.RpcChannel, org.apache.hadoop.hbase.ipc.protobuf.generated.TestRpcServiceProtos$1);
    Code:
       0: aload_0
       1: aload_1
       2: invokespecial #1                  // Method "<init>":(Lcom/google/protobuf/RpcChannel;)V
       5: return
}
