Compiled from "TestVisibilityLabelsReplication.java"
public class org.apache.hadoop.hbase.security.visibility.TestVisibilityLabelsReplication$VisibilityReplicationEndPointForTest extends org.apache.hadoop.hbase.security.visibility.VisibilityReplicationEndpoint {
  static java.util.concurrent.atomic.AtomicInteger replicateCount;

  static volatile java.util.List<org.apache.hadoop.hbase.wal.WAL$Entry> lastEntries;

  public org.apache.hadoop.hbase.security.visibility.TestVisibilityLabelsReplication$VisibilityReplicationEndPointForTest(org.apache.hadoop.hbase.replication.ReplicationEndpoint, org.apache.hadoop.hbase.security.visibility.VisibilityLabelService);
    Code:
       0: aload_0
       1: aload_1
       2: aload_2
       3: invokespecial #1                  // Method org/apache/hadoop/hbase/security/visibility/VisibilityReplicationEndpoint."<init>":(Lorg/apache/hadoop/hbase/replication/ReplicationEndpoint;Lorg/apache/hadoop/hbase/security/visibility/VisibilityLabelService;)V
       6: return

  public boolean replicate(org.apache.hadoop.hbase.replication.ReplicationEndpoint$ReplicateContext);
    Code:
       0: aload_0
       1: aload_1
       2: invokespecial #2                  // Method org/apache/hadoop/hbase/security/visibility/VisibilityReplicationEndpoint.replicate:(Lorg/apache/hadoop/hbase/replication/ReplicationEndpoint$ReplicateContext;)Z
       5: istore_2
       6: aload_1
       7: invokevirtual #3                  // Method org/apache/hadoop/hbase/replication/ReplicationEndpoint$ReplicateContext.getEntries:()Ljava/util/List;
      10: putstatic     #4                  // Field lastEntries:Ljava/util/List;
      13: getstatic     #5                  // Field replicateCount:Ljava/util/concurrent/atomic/AtomicInteger;
      16: invokevirtual #6                  // Method java/util/concurrent/atomic/AtomicInteger.incrementAndGet:()I
      19: pop
      20: iload_2
      21: ireturn

  static {};
    Code:
       0: new           #7                  // class java/util/concurrent/atomic/AtomicInteger
       3: dup
       4: invokespecial #8                  // Method java/util/concurrent/atomic/AtomicInteger."<init>":()V
       7: putstatic     #5                  // Field replicateCount:Ljava/util/concurrent/atomic/AtomicInteger;
      10: aconst_null
      11: putstatic     #4                  // Field lastEntries:Ljava/util/List;
      14: return
}
