Compiled from "TestAsyncTableAdminApi3.java"
public class org.apache.hadoop.hbase.client.TestAsyncTableAdminApi3 extends org.apache.hadoop.hbase.client.TestAsyncAdminBase {
  public static final org.apache.hadoop.hbase.HBaseClassTestRule CLASS_RULE;

  public org.apache.hadoop.hbase.client.TestAsyncTableAdminApi3();
    Code:
       0: aload_0
       1: invokespecial #1                  // Method org/apache/hadoop/hbase/client/TestAsyncAdminBase."<init>":()V
       4: return

  public void testTableExist() throws java.lang.Exception;
    Code:
       0: aload_0
       1: getfield      #2                  // Field admin:Lorg/apache/hadoop/hbase/client/AsyncAdmin;
       4: aload_0
       5: getfield      #3                  // Field tableName:Lorg/apache/hadoop/hbase/TableName;
       8: invokeinterface #4,  2            // InterfaceMethod org/apache/hadoop/hbase/client/AsyncAdmin.tableExists:(Lorg/apache/hadoop/hbase/TableName;)Ljava/util/concurrent/CompletableFuture;
      13: invokevirtual #5                  // Method java/util/concurrent/CompletableFuture.get:()Ljava/lang/Object;
      16: checkcast     #6                  // class java/lang/Boolean
      19: invokevirtual #7                  // Method java/lang/Boolean.booleanValue:()Z
      22: istore_1
      23: iload_1
      24: invokestatic  #8                  // Method org/junit/Assert.assertFalse:(Z)V
      27: getstatic     #9                  // Field TEST_UTIL:Lorg/apache/hadoop/hbase/HBaseTestingUtility;
      30: aload_0
      31: getfield      #3                  // Field tableName:Lorg/apache/hadoop/hbase/TableName;
      34: getstatic     #10                 // Field FAMILY:[B
      37: invokevirtual #11                 // Method org/apache/hadoop/hbase/HBaseTestingUtility.createTable:(Lorg/apache/hadoop/hbase/TableName;[B)Lorg/apache/hadoop/hbase/client/Table;
      40: pop
      41: aload_0
      42: getfield      #2                  // Field admin:Lorg/apache/hadoop/hbase/client/AsyncAdmin;
      45: aload_0
      46: getfield      #3                  // Field tableName:Lorg/apache/hadoop/hbase/TableName;
      49: invokeinterface #4,  2            // InterfaceMethod org/apache/hadoop/hbase/client/AsyncAdmin.tableExists:(Lorg/apache/hadoop/hbase/TableName;)Ljava/util/concurrent/CompletableFuture;
      54: invokevirtual #5                  // Method java/util/concurrent/CompletableFuture.get:()Ljava/lang/Object;
      57: checkcast     #6                  // class java/lang/Boolean
      60: invokevirtual #7                  // Method java/lang/Boolean.booleanValue:()Z
      63: istore_1
      64: iload_1
      65: invokestatic  #12                 // Method org/junit/Assert.assertTrue:(Z)V
      68: aload_0
      69: getfield      #2                  // Field admin:Lorg/apache/hadoop/hbase/client/AsyncAdmin;
      72: getstatic     #13                 // Field org/apache/hadoop/hbase/TableName.META_TABLE_NAME:Lorg/apache/hadoop/hbase/TableName;
      75: invokeinterface #4,  2            // InterfaceMethod org/apache/hadoop/hbase/client/AsyncAdmin.tableExists:(Lorg/apache/hadoop/hbase/TableName;)Ljava/util/concurrent/CompletableFuture;
      80: invokevirtual #5                  // Method java/util/concurrent/CompletableFuture.get:()Ljava/lang/Object;
      83: checkcast     #6                  // class java/lang/Boolean
      86: invokevirtual #7                  // Method java/lang/Boolean.booleanValue:()Z
      89: istore_1
      90: iload_1
      91: invokestatic  #12                 // Method org/junit/Assert.assertTrue:(Z)V
      94: aload_0
      95: getfield      #2                  // Field admin:Lorg/apache/hadoop/hbase/client/AsyncAdmin;
      98: getstatic     #13                 // Field org/apache/hadoop/hbase/TableName.META_TABLE_NAME:Lorg/apache/hadoop/hbase/TableName;
     101: invokeinterface #4,  2            // InterfaceMethod org/apache/hadoop/hbase/client/AsyncAdmin.tableExists:(Lorg/apache/hadoop/hbase/TableName;)Ljava/util/concurrent/CompletableFuture;
     106: invokevirtual #5                  // Method java/util/concurrent/CompletableFuture.get:()Ljava/lang/Object;
     109: checkcast     #6                  // class java/lang/Boolean
     112: invokevirtual #7                  // Method java/lang/Boolean.booleanValue:()Z
     115: istore_1
     116: iload_1
     117: invokestatic  #12                 // Method org/junit/Assert.assertTrue:(Z)V
     120: return

  public void testListTables() throws java.lang.Exception;
    Code:
       0: aload_0
       1: getfield      #2                  // Field admin:Lorg/apache/hadoop/hbase/client/AsyncAdmin;
       4: invokeinterface #14,  1           // InterfaceMethod org/apache/hadoop/hbase/client/AsyncAdmin.listTableDescriptors:()Ljava/util/concurrent/CompletableFuture;
       9: invokevirtual #5                  // Method java/util/concurrent/CompletableFuture.get:()Ljava/lang/Object;
      12: checkcast     #15                 // class java/util/List
      15: invokeinterface #16,  1           // InterfaceMethod java/util/List.size:()I
      20: istore_1
      21: new           #17                 // class java/lang/StringBuilder
      24: dup
      25: invokespecial #18                 // Method java/lang/StringBuilder."<init>":()V
      28: aload_0
      29: getfield      #3                  // Field tableName:Lorg/apache/hadoop/hbase/TableName;
      32: invokevirtual #19                 // Method org/apache/hadoop/hbase/TableName.getNameAsString:()Ljava/lang/String;
      35: invokevirtual #20                 // Method java/lang/StringBuilder.append:(Ljava/lang/String;)Ljava/lang/StringBuilder;
      38: ldc           #21                 // String 1
      40: invokevirtual #20                 // Method java/lang/StringBuilder.append:(Ljava/lang/String;)Ljava/lang/StringBuilder;
      43: invokevirtual #22                 // Method java/lang/StringBuilder.toString:()Ljava/lang/String;
      46: invokestatic  #23                 // Method org/apache/hadoop/hbase/TableName.valueOf:(Ljava/lang/String;)Lorg/apache/hadoop/hbase/TableName;
      49: astore_2
      50: new           #17                 // class java/lang/StringBuilder
      53: dup
      54: invokespecial #18                 // Method java/lang/StringBuilder."<init>":()V
      57: aload_0
      58: getfield      #3                  // Field tableName:Lorg/apache/hadoop/hbase/TableName;
      61: invokevirtual #19                 // Method org/apache/hadoop/hbase/TableName.getNameAsString:()Ljava/lang/String;
      64: invokevirtual #20                 // Method java/lang/StringBuilder.append:(Ljava/lang/String;)Ljava/lang/StringBuilder;
      67: ldc           #24                 // String 2
      69: invokevirtual #20                 // Method java/lang/StringBuilder.append:(Ljava/lang/String;)Ljava/lang/StringBuilder;
      72: invokevirtual #22                 // Method java/lang/StringBuilder.toString:()Ljava/lang/String;
      75: invokestatic  #23                 // Method org/apache/hadoop/hbase/TableName.valueOf:(Ljava/lang/String;)Lorg/apache/hadoop/hbase/TableName;
      78: astore_3
      79: new           #17                 // class java/lang/StringBuilder
      82: dup
      83: invokespecial #18                 // Method java/lang/StringBuilder."<init>":()V
      86: aload_0
      87: getfield      #3                  // Field tableName:Lorg/apache/hadoop/hbase/TableName;
      90: invokevirtual #19                 // Method org/apache/hadoop/hbase/TableName.getNameAsString:()Ljava/lang/String;
      93: invokevirtual #20                 // Method java/lang/StringBuilder.append:(Ljava/lang/String;)Ljava/lang/StringBuilder;
      96: ldc           #25                 // String 3
      98: invokevirtual #20                 // Method java/lang/StringBuilder.append:(Ljava/lang/String;)Ljava/lang/StringBuilder;
     101: invokevirtual #22                 // Method java/lang/StringBuilder.toString:()Ljava/lang/String;
     104: invokestatic  #23                 // Method org/apache/hadoop/hbase/TableName.valueOf:(Ljava/lang/String;)Lorg/apache/hadoop/hbase/TableName;
     107: astore        4
     109: iconst_3
     110: anewarray     #26                 // class org/apache/hadoop/hbase/TableName
     113: dup
     114: iconst_0
     115: aload_2
     116: aastore
     117: dup
     118: iconst_1
     119: aload_3
     120: aastore
     121: dup
     122: iconst_2
     123: aload         4
     125: aastore
     126: astore        5
     128: iconst_0
     129: istore        6
     131: iload         6
     133: aload         5
     135: arraylength
     136: if_icmpge     154
     139: aload_0
     140: aload         5
     142: iload         6
     144: aaload
     145: invokevirtual #27                 // Method createTableWithDefaultConf:(Lorg/apache/hadoop/hbase/TableName;)V
     148: iinc          6, 1
     151: goto          131
     154: aload_0
     155: getfield      #2                  // Field admin:Lorg/apache/hadoop/hbase/client/AsyncAdmin;
     158: invokeinterface #14,  1           // InterfaceMethod org/apache/hadoop/hbase/client/AsyncAdmin.listTableDescriptors:()Ljava/util/concurrent/CompletableFuture;
     163: invokevirtual #5                  // Method java/util/concurrent/CompletableFuture.get:()Ljava/lang/Object;
     166: checkcast     #15                 // class java/util/List
     169: astore        6
     171: aload         6
     173: invokeinterface #16,  1           // InterfaceMethod java/util/List.size:()I
     178: istore        7
     180: iload         7
     182: aload         5
     184: arraylength
     185: if_icmplt     192
     188: iconst_1
     189: goto          193
     192: iconst_0
     193: invokestatic  #12                 // Method org/junit/Assert.assertTrue:(Z)V
     196: iconst_0
     197: istore        8
     199: iload         8
     201: aload         5
     203: arraylength
     204: if_icmpge     301
     207: iload         8
     209: iload         7
     211: if_icmpge     301
     214: iconst_0
     215: istore        9
     217: iconst_0
     218: istore        10
     220: iload         10
     222: iload         7
     224: if_icmpge     267
     227: aload         6
     229: iload         10
     231: invokeinterface #28,  2           // InterfaceMethod java/util/List.get:(I)Ljava/lang/Object;
     236: checkcast     #29                 // class org/apache/hadoop/hbase/client/TableDescriptor
     239: invokeinterface #30,  1           // InterfaceMethod org/apache/hadoop/hbase/client/TableDescriptor.getTableName:()Lorg/apache/hadoop/hbase/TableName;
     244: aload         5
     246: iload         8
     248: aaload
     249: invokevirtual #31                 // Method org/apache/hadoop/hbase/TableName.equals:(Ljava/lang/Object;)Z
     252: ifeq          261
     255: iconst_1
     256: istore        9
     258: goto          267
     261: iinc          10, 1
     264: goto          220
     267: new           #17                 // class java/lang/StringBuilder
     270: dup
     271: invokespecial #18                 // Method java/lang/StringBuilder."<init>":()V
     274: ldc           #32                 // String Not found:
     276: invokevirtual #20                 // Method java/lang/StringBuilder.append:(Ljava/lang/String;)Ljava/lang/StringBuilder;
     279: aload         5
     281: iload         8
     283: aaload
     284: invokevirtual #33                 // Method java/lang/StringBuilder.append:(Ljava/lang/Object;)Ljava/lang/StringBuilder;
     287: invokevirtual #22                 // Method java/lang/StringBuilder.toString:()Ljava/lang/String;
     290: iload         9
     292: invokestatic  #34                 // Method org/junit/Assert.assertTrue:(Ljava/lang/String;Z)V
     295: iinc          8, 1
     298: goto          199
     301: aload_0
     302: getfield      #2                  // Field admin:Lorg/apache/hadoop/hbase/client/AsyncAdmin;
     305: invokeinterface #35,  1           // InterfaceMethod org/apache/hadoop/hbase/client/AsyncAdmin.listTableNames:()Ljava/util/concurrent/CompletableFuture;
     310: invokevirtual #5                  // Method java/util/concurrent/CompletableFuture.get:()Ljava/lang/Object;
     313: checkcast     #15                 // class java/util/List
     316: astore        8
     318: aload         8
     320: invokeinterface #16,  1           // InterfaceMethod java/util/List.size:()I
     325: istore        7
     327: iload         7
     329: iload_1
     330: aload         5
     332: arraylength
     333: iadd
     334: if_icmpne     341
     337: iconst_1
     338: goto          342
     341: iconst_0
     342: invokestatic  #12                 // Method org/junit/Assert.assertTrue:(Z)V
     345: iconst_0
     346: istore        9
     348: iload         9
     350: aload         5
     352: arraylength
     353: if_icmpge     445
     356: iload         9
     358: iload         7
     360: if_icmpge     445
     363: iconst_0
     364: istore        10
     366: iconst_0
     367: istore        11
     369: iload         11
     371: iload         7
     373: if_icmpge     411
     376: aload         8
     378: iload         11
     380: invokeinterface #28,  2           // InterfaceMethod java/util/List.get:(I)Ljava/lang/Object;
     385: checkcast     #26                 // class org/apache/hadoop/hbase/TableName
     388: aload         5
     390: iload         9
     392: aaload
     393: invokevirtual #31                 // Method org/apache/hadoop/hbase/TableName.equals:(Ljava/lang/Object;)Z
     396: ifeq          405
     399: iconst_1
     400: istore        10
     402: goto          411
     405: iinc          11, 1
     408: goto          369
     411: new           #17                 // class java/lang/StringBuilder
     414: dup
     415: invokespecial #18                 // Method java/lang/StringBuilder."<init>":()V
     418: ldc           #32                 // String Not found:
     420: invokevirtual #20                 // Method java/lang/StringBuilder.append:(Ljava/lang/String;)Ljava/lang/StringBuilder;
     423: aload         5
     425: iload         9
     427: aaload
     428: invokevirtual #33                 // Method java/lang/StringBuilder.append:(Ljava/lang/Object;)Ljava/lang/StringBuilder;
     431: invokevirtual #22                 // Method java/lang/StringBuilder.toString:()Ljava/lang/String;
     434: iload         10
     436: invokestatic  #34                 // Method org/junit/Assert.assertTrue:(Ljava/lang/String;Z)V
     439: iinc          9, 1
     442: goto          348
     445: new           #36                 // class java/util/ArrayList
     448: dup
     449: aload         5
     451: arraylength
     452: iconst_1
     453: iadd
     454: invokespecial #37                 // Method java/util/ArrayList."<init>":(I)V
     457: astore        8
     459: aload_0
     460: getfield      #2                  // Field admin:Lorg/apache/hadoop/hbase/client/AsyncAdmin;
     463: aload         8
     465: invokeinterface #38,  2           // InterfaceMethod org/apache/hadoop/hbase/client/AsyncAdmin.listTableDescriptors:(Ljava/util/List;)Ljava/util/concurrent/CompletableFuture;
     470: invokevirtual #5                  // Method java/util/concurrent/CompletableFuture.get:()Ljava/lang/Object;
     473: checkcast     #15                 // class java/util/List
     476: astore        6
     478: aload         6
     480: invokeinterface #16,  1           // InterfaceMethod java/util/List.size:()I
     485: istore        7
     487: lconst_0
     488: iload         7
     490: i2l
     491: invokestatic  #39                 // Method org/junit/Assert.assertEquals:(JJ)V
     494: aload         8
     496: aload         5
     498: invokestatic  #40                 // Method java/util/Collections.addAll:(Ljava/util/Collection;[Ljava/lang/Object;)Z
     501: pop
     502: aload         8
     504: getstatic     #13                 // Field org/apache/hadoop/hbase/TableName.META_TABLE_NAME:Lorg/apache/hadoop/hbase/TableName;
     507: invokeinterface #41,  2           // InterfaceMethod java/util/List.add:(Ljava/lang/Object;)Z
     512: pop
     513: aload_0
     514: getfield      #2                  // Field admin:Lorg/apache/hadoop/hbase/client/AsyncAdmin;
     517: aload         8
     519: invokeinterface #38,  2           // InterfaceMethod org/apache/hadoop/hbase/client/AsyncAdmin.listTableDescriptors:(Ljava/util/List;)Ljava/util/concurrent/CompletableFuture;
     524: invokevirtual #5                  // Method java/util/concurrent/CompletableFuture.get:()Ljava/lang/Object;
     527: checkcast     #15                 // class java/util/List
     530: astore        6
     532: aload         6
     534: invokeinterface #16,  1           // InterfaceMethod java/util/List.size:()I
     539: istore        7
     541: aload         5
     543: arraylength
     544: iconst_1
     545: iadd
     546: i2l
     547: iload         7
     549: i2l
     550: invokestatic  #39                 // Method org/junit/Assert.assertEquals:(JJ)V
     553: iconst_0
     554: istore        9
     556: iconst_0
     557: istore        10
     559: iload         9
     561: aload         5
     563: arraylength
     564: if_icmpge     613
     567: iload         10
     569: iload         7
     571: if_icmpge     613
     574: ldc           #42                 // String tableName should be equal in order
     576: aload         6
     578: iload         10
     580: invokeinterface #28,  2           // InterfaceMethod java/util/List.get:(I)Ljava/lang/Object;
     585: checkcast     #29                 // class org/apache/hadoop/hbase/client/TableDescriptor
     588: invokeinterface #30,  1           // InterfaceMethod org/apache/hadoop/hbase/client/TableDescriptor.getTableName:()Lorg/apache/hadoop/hbase/TableName;
     593: aload         5
     595: iload         9
     597: aaload
     598: invokevirtual #31                 // Method org/apache/hadoop/hbase/TableName.equals:(Ljava/lang/Object;)Z
     601: invokestatic  #34                 // Method org/junit/Assert.assertTrue:(Ljava/lang/String;Z)V
     604: iinc          9, 1
     607: iinc          10, 1
     610: goto          559
     613: aload         6
     615: iload         7
     617: iconst_1
     618: isub
     619: invokeinterface #28,  2           // InterfaceMethod java/util/List.get:(I)Ljava/lang/Object;
     624: checkcast     #29                 // class org/apache/hadoop/hbase/client/TableDescriptor
     627: invokeinterface #30,  1           // InterfaceMethod org/apache/hadoop/hbase/client/TableDescriptor.getTableName:()Lorg/apache/hadoop/hbase/TableName;
     632: getstatic     #13                 // Field org/apache/hadoop/hbase/TableName.META_TABLE_NAME:Lorg/apache/hadoop/hbase/TableName;
     635: invokevirtual #31                 // Method org/apache/hadoop/hbase/TableName.equals:(Ljava/lang/Object;)Z
     638: invokestatic  #12                 // Method org/junit/Assert.assertTrue:(Z)V
     641: iconst_0
     642: istore        9
     644: iload         9
     646: aload         5
     648: arraylength
     649: if_icmpge     694
     652: aload_0
     653: getfield      #2                  // Field admin:Lorg/apache/hadoop/hbase/client/AsyncAdmin;
     656: aload         5
     658: iload         9
     660: aaload
     661: invokeinterface #43,  2           // InterfaceMethod org/apache/hadoop/hbase/client/AsyncAdmin.disableTable:(Lorg/apache/hadoop/hbase/TableName;)Ljava/util/concurrent/CompletableFuture;
     666: invokevirtual #44                 // Method java/util/concurrent/CompletableFuture.join:()Ljava/lang/Object;
     669: pop
     670: aload_0
     671: getfield      #2                  // Field admin:Lorg/apache/hadoop/hbase/client/AsyncAdmin;
     674: aload         5
     676: iload         9
     678: aaload
     679: invokeinterface #45,  2           // InterfaceMethod org/apache/hadoop/hbase/client/AsyncAdmin.deleteTable:(Lorg/apache/hadoop/hbase/TableName;)Ljava/util/concurrent/CompletableFuture;
     684: invokevirtual #44                 // Method java/util/concurrent/CompletableFuture.join:()Ljava/lang/Object;
     687: pop
     688: iinc          9, 1
     691: goto          644
     694: aload_0
     695: getfield      #2                  // Field admin:Lorg/apache/hadoop/hbase/client/AsyncAdmin;
     698: iconst_1
     699: invokeinterface #46,  2           // InterfaceMethod org/apache/hadoop/hbase/client/AsyncAdmin.listTableDescriptors:(Z)Ljava/util/concurrent/CompletableFuture;
     704: invokevirtual #5                  // Method java/util/concurrent/CompletableFuture.get:()Ljava/lang/Object;
     707: checkcast     #15                 // class java/util/List
     710: astore        6
     712: ldc           #47                 // String Not found system tables
     714: aload         6
     716: invokeinterface #16,  1           // InterfaceMethod java/util/List.size:()I
     721: ifle          728
     724: iconst_1
     725: goto          729
     728: iconst_0
     729: invokestatic  #34                 // Method org/junit/Assert.assertTrue:(Ljava/lang/String;Z)V
     732: aload_0
     733: getfield      #2                  // Field admin:Lorg/apache/hadoop/hbase/client/AsyncAdmin;
     736: iconst_1
     737: invokeinterface #48,  2           // InterfaceMethod org/apache/hadoop/hbase/client/AsyncAdmin.listTableNames:(Z)Ljava/util/concurrent/CompletableFuture;
     742: invokevirtual #5                  // Method java/util/concurrent/CompletableFuture.get:()Ljava/lang/Object;
     745: checkcast     #15                 // class java/util/List
     748: astore        8
     750: ldc           #47                 // String Not found system tables
     752: aload         8
     754: invokeinterface #16,  1           // InterfaceMethod java/util/List.size:()I
     759: ifle          766
     762: iconst_1
     763: goto          767
     766: iconst_0
     767: invokestatic  #34                 // Method org/junit/Assert.assertTrue:(Ljava/lang/String;Z)V
     770: return

  public void testGetTableDescriptor() throws java.lang.Exception;
    Code:
       0: iconst_3
       1: anewarray     #49                 // class "[B"
       4: dup
       5: iconst_0
       6: getstatic     #10                 // Field FAMILY:[B
       9: aastore
      10: dup
      11: iconst_1
      12: getstatic     #50                 // Field FAMILY_0:[B
      15: aastore
      16: dup
      17: iconst_2
      18: getstatic     #51                 // Field FAMILY_1:[B
      21: aastore
      22: astore_1
      23: aload_0
      24: getfield      #3                  // Field tableName:Lorg/apache/hadoop/hbase/TableName;
      27: invokestatic  #52                 // Method org/apache/hadoop/hbase/client/TableDescriptorBuilder.newBuilder:(Lorg/apache/hadoop/hbase/TableName;)Lorg/apache/hadoop/hbase/client/TableDescriptorBuilder;
      30: astore_2
      31: aload_1
      32: astore_3
      33: aload_3
      34: arraylength
      35: istore        4
      37: iconst_0
      38: istore        5
      40: iload         5
      42: iload         4
      44: if_icmpge     69
      47: aload_3
      48: iload         5
      50: aaload
      51: astore        6
      53: aload_2
      54: aload         6
      56: invokestatic  #53                 // Method org/apache/hadoop/hbase/client/ColumnFamilyDescriptorBuilder.of:([B)Lorg/apache/hadoop/hbase/client/ColumnFamilyDescriptor;
      59: invokevirtual #54                 // Method org/apache/hadoop/hbase/client/TableDescriptorBuilder.setColumnFamily:(Lorg/apache/hadoop/hbase/client/ColumnFamilyDescriptor;)Lorg/apache/hadoop/hbase/client/TableDescriptorBuilder;
      62: pop
      63: iinc          5, 1
      66: goto          40
      69: aload_2
      70: invokevirtual #55                 // Method org/apache/hadoop/hbase/client/TableDescriptorBuilder.build:()Lorg/apache/hadoop/hbase/client/TableDescriptor;
      73: astore_3
      74: aload_0
      75: getfield      #2                  // Field admin:Lorg/apache/hadoop/hbase/client/AsyncAdmin;
      78: aload_3
      79: invokeinterface #56,  2           // InterfaceMethod org/apache/hadoop/hbase/client/AsyncAdmin.createTable:(Lorg/apache/hadoop/hbase/client/TableDescriptor;)Ljava/util/concurrent/CompletableFuture;
      84: invokevirtual #44                 // Method java/util/concurrent/CompletableFuture.join:()Ljava/lang/Object;
      87: pop
      88: aload_3
      89: checkcast     #57                 // class org/apache/hadoop/hbase/client/TableDescriptorBuilder$ModifyableTableDescriptor
      92: astore        4
      94: aload_0
      95: getfield      #2                  // Field admin:Lorg/apache/hadoop/hbase/client/AsyncAdmin;
      98: aload_0
      99: getfield      #3                  // Field tableName:Lorg/apache/hadoop/hbase/TableName;
     102: invokeinterface #58,  2           // InterfaceMethod org/apache/hadoop/hbase/client/AsyncAdmin.getDescriptor:(Lorg/apache/hadoop/hbase/TableName;)Ljava/util/concurrent/CompletableFuture;
     107: invokevirtual #5                  // Method java/util/concurrent/CompletableFuture.get:()Ljava/lang/Object;
     110: checkcast     #29                 // class org/apache/hadoop/hbase/client/TableDescriptor
     113: astore        5
     115: lconst_0
     116: aload         4
     118: aload         5
     120: checkcast     #57                 // class org/apache/hadoop/hbase/client/TableDescriptorBuilder$ModifyableTableDescriptor
     123: invokevirtual #59                 // Method org/apache/hadoop/hbase/client/TableDescriptorBuilder$ModifyableTableDescriptor.compareTo:(Lorg/apache/hadoop/hbase/client/TableDescriptorBuilder$ModifyableTableDescriptor;)I
     126: i2l
     127: invokestatic  #39                 // Method org/junit/Assert.assertEquals:(JJ)V
     130: return

  public void testDisableAndEnableTable() throws java.lang.Exception;
    Code:
       0: aload_0
       1: aload_0
       2: getfield      #3                  // Field tableName:Lorg/apache/hadoop/hbase/TableName;
       5: invokevirtual #27                 // Method createTableWithDefaultConf:(Lorg/apache/hadoop/hbase/TableName;)V
       8: getstatic     #60                 // Field ASYNC_CONN:Lorg/apache/hadoop/hbase/client/AsyncConnection;
      11: aload_0
      12: getfield      #3                  // Field tableName:Lorg/apache/hadoop/hbase/TableName;
      15: invokeinterface #61,  2           // InterfaceMethod org/apache/hadoop/hbase/client/AsyncConnection.getTable:(Lorg/apache/hadoop/hbase/TableName;)Lorg/apache/hadoop/hbase/client/AsyncTable;
      20: astore_1
      21: ldc           #62                 // String row
      23: invokestatic  #63                 // Method org/apache/hadoop/hbase/util/Bytes.toBytes:(Ljava/lang/String;)[B
      26: astore_2
      27: ldc           #64                 // String qualifier
      29: invokestatic  #63                 // Method org/apache/hadoop/hbase/util/Bytes.toBytes:(Ljava/lang/String;)[B
      32: astore_3
      33: ldc           #65                 // String value
      35: invokestatic  #63                 // Method org/apache/hadoop/hbase/util/Bytes.toBytes:(Ljava/lang/String;)[B
      38: astore        4
      40: new           #66                 // class org/apache/hadoop/hbase/client/Put
      43: dup
      44: aload_2
      45: invokespecial #67                 // Method org/apache/hadoop/hbase/client/Put."<init>":([B)V
      48: astore        5
      50: aload         5
      52: getstatic     #10                 // Field FAMILY:[B
      55: aload_3
      56: aload         4
      58: invokevirtual #68                 // Method org/apache/hadoop/hbase/client/Put.addColumn:([B[B[B)Lorg/apache/hadoop/hbase/client/Put;
      61: pop
      62: aload_1
      63: aload         5
      65: invokeinterface #69,  2           // InterfaceMethod org/apache/hadoop/hbase/client/AsyncTable.put:(Lorg/apache/hadoop/hbase/client/Put;)Ljava/util/concurrent/CompletableFuture;
      70: invokevirtual #44                 // Method java/util/concurrent/CompletableFuture.join:()Ljava/lang/Object;
      73: pop
      74: new           #70                 // class org/apache/hadoop/hbase/client/Get
      77: dup
      78: aload_2
      79: invokespecial #71                 // Method org/apache/hadoop/hbase/client/Get."<init>":([B)V
      82: astore        6
      84: aload         6
      86: getstatic     #10                 // Field FAMILY:[B
      89: aload_3
      90: invokevirtual #72                 // Method org/apache/hadoop/hbase/client/Get.addColumn:([B[B)Lorg/apache/hadoop/hbase/client/Get;
      93: pop
      94: aload_1
      95: aload         6
      97: invokeinterface #73,  2           // InterfaceMethod org/apache/hadoop/hbase/client/AsyncTable.get:(Lorg/apache/hadoop/hbase/client/Get;)Ljava/util/concurrent/CompletableFuture;
     102: invokevirtual #5                  // Method java/util/concurrent/CompletableFuture.get:()Ljava/lang/Object;
     105: pop
     106: aload_0
     107: getfield      #2                  // Field admin:Lorg/apache/hadoop/hbase/client/AsyncAdmin;
     110: aload_0
     111: getfield      #3                  // Field tableName:Lorg/apache/hadoop/hbase/TableName;
     114: invokeinterface #43,  2           // InterfaceMethod org/apache/hadoop/hbase/client/AsyncAdmin.disableTable:(Lorg/apache/hadoop/hbase/TableName;)Ljava/util/concurrent/CompletableFuture;
     119: invokevirtual #44                 // Method java/util/concurrent/CompletableFuture.join:()Ljava/lang/Object;
     122: pop
     123: ldc           #74                 // String Table must be disabled.
     125: getstatic     #9                  // Field TEST_UTIL:Lorg/apache/hadoop/hbase/HBaseTestingUtility;
     128: invokevirtual #75                 // Method org/apache/hadoop/hbase/HBaseTestingUtility.getHBaseCluster:()Lorg/apache/hadoop/hbase/MiniHBaseCluster;
     131: invokevirtual #76                 // Method org/apache/hadoop/hbase/MiniHBaseCluster.getMaster:()Lorg/apache/hadoop/hbase/master/HMaster;
     134: invokevirtual #77                 // Method org/apache/hadoop/hbase/master/HMaster.getTableStateManager:()Lorg/apache/hadoop/hbase/master/TableStateManager;
     137: aload_0
     138: getfield      #3                  // Field tableName:Lorg/apache/hadoop/hbase/TableName;
     141: iconst_1
     142: anewarray     #78                 // class org/apache/hadoop/hbase/client/TableState$State
     145: dup
     146: iconst_0
     147: getstatic     #79                 // Field org/apache/hadoop/hbase/client/TableState$State.DISABLED:Lorg/apache/hadoop/hbase/client/TableState$State;
     150: aastore
     151: invokevirtual #80                 // Method org/apache/hadoop/hbase/master/TableStateManager.isTableState:(Lorg/apache/hadoop/hbase/TableName;[Lorg/apache/hadoop/hbase/client/TableState$State;)Z
     154: invokestatic  #34                 // Method org/junit/Assert.assertTrue:(Ljava/lang/String;Z)V
     157: getstatic     #79                 // Field org/apache/hadoop/hbase/client/TableState$State.DISABLED:Lorg/apache/hadoop/hbase/client/TableState$State;
     160: aload_0
     161: getfield      #3                  // Field tableName:Lorg/apache/hadoop/hbase/TableName;
     164: invokestatic  #81                 // Method org/apache/hadoop/hbase/client/TestAsyncTableAdminApi.getStateFromMeta:(Lorg/apache/hadoop/hbase/TableName;)Lorg/apache/hadoop/hbase/client/TableState$State;
     167: invokestatic  #82                 // Method org/junit/Assert.assertEquals:(Ljava/lang/Object;Ljava/lang/Object;)V
     170: new           #70                 // class org/apache/hadoop/hbase/client/Get
     173: dup
     174: aload_2
     175: invokespecial #71                 // Method org/apache/hadoop/hbase/client/Get."<init>":([B)V
     178: astore        6
     180: aload         6
     182: getstatic     #10                 // Field FAMILY:[B
     185: aload_3
     186: invokevirtual #72                 // Method org/apache/hadoop/hbase/client/Get.addColumn:([B[B)Lorg/apache/hadoop/hbase/client/Get;
     189: pop
     190: iconst_0
     191: istore        7
     193: aload_1
     194: aload         6
     196: invokeinterface #73,  2           // InterfaceMethod org/apache/hadoop/hbase/client/AsyncTable.get:(Lorg/apache/hadoop/hbase/client/Get;)Ljava/util/concurrent/CompletableFuture;
     201: invokevirtual #5                  // Method java/util/concurrent/CompletableFuture.get:()Ljava/lang/Object;
     204: pop
     205: goto          213
     208: astore        8
     210: iconst_1
     211: istore        7
     213: iconst_0
     214: istore        7
     216: aload_1
     217: new           #84                 // class org/apache/hadoop/hbase/client/Scan
     220: dup
     221: invokespecial #85                 // Method org/apache/hadoop/hbase/client/Scan."<init>":()V
     224: invokeinterface #86,  2           // InterfaceMethod org/apache/hadoop/hbase/client/AsyncTable.scanAll:(Lorg/apache/hadoop/hbase/client/Scan;)Ljava/util/concurrent/CompletableFuture;
     229: invokevirtual #5                  // Method java/util/concurrent/CompletableFuture.get:()Ljava/lang/Object;
     232: pop
     233: goto          241
     236: astore        8
     238: iconst_1
     239: istore        7
     241: iload         7
     243: invokestatic  #12                 // Method org/junit/Assert.assertTrue:(Z)V
     246: aload_0
     247: getfield      #2                  // Field admin:Lorg/apache/hadoop/hbase/client/AsyncAdmin;
     250: aload_0
     251: getfield      #3                  // Field tableName:Lorg/apache/hadoop/hbase/TableName;
     254: invokeinterface #87,  2           // InterfaceMethod org/apache/hadoop/hbase/client/AsyncAdmin.enableTable:(Lorg/apache/hadoop/hbase/TableName;)Ljava/util/concurrent/CompletableFuture;
     259: invokevirtual #44                 // Method java/util/concurrent/CompletableFuture.join:()Ljava/lang/Object;
     262: pop
     263: ldc           #88                 // String Table must be enabled.
     265: getstatic     #9                  // Field TEST_UTIL:Lorg/apache/hadoop/hbase/HBaseTestingUtility;
     268: invokevirtual #75                 // Method org/apache/hadoop/hbase/HBaseTestingUtility.getHBaseCluster:()Lorg/apache/hadoop/hbase/MiniHBaseCluster;
     271: invokevirtual #76                 // Method org/apache/hadoop/hbase/MiniHBaseCluster.getMaster:()Lorg/apache/hadoop/hbase/master/HMaster;
     274: invokevirtual #77                 // Method org/apache/hadoop/hbase/master/HMaster.getTableStateManager:()Lorg/apache/hadoop/hbase/master/TableStateManager;
     277: aload_0
     278: getfield      #3                  // Field tableName:Lorg/apache/hadoop/hbase/TableName;
     281: iconst_1
     282: anewarray     #78                 // class org/apache/hadoop/hbase/client/TableState$State
     285: dup
     286: iconst_0
     287: getstatic     #89                 // Field org/apache/hadoop/hbase/client/TableState$State.ENABLED:Lorg/apache/hadoop/hbase/client/TableState$State;
     290: aastore
     291: invokevirtual #80                 // Method org/apache/hadoop/hbase/master/TableStateManager.isTableState:(Lorg/apache/hadoop/hbase/TableName;[Lorg/apache/hadoop/hbase/client/TableState$State;)Z
     294: invokestatic  #34                 // Method org/junit/Assert.assertTrue:(Ljava/lang/String;Z)V
     297: getstatic     #89                 // Field org/apache/hadoop/hbase/client/TableState$State.ENABLED:Lorg/apache/hadoop/hbase/client/TableState$State;
     300: aload_0
     301: getfield      #3                  // Field tableName:Lorg/apache/hadoop/hbase/TableName;
     304: invokestatic  #81                 // Method org/apache/hadoop/hbase/client/TestAsyncTableAdminApi.getStateFromMeta:(Lorg/apache/hadoop/hbase/TableName;)Lorg/apache/hadoop/hbase/client/TableState$State;
     307: invokestatic  #82                 // Method org/junit/Assert.assertEquals:(Ljava/lang/Object;Ljava/lang/Object;)V
     310: aload_1
     311: aload         6
     313: invokeinterface #73,  2           // InterfaceMethod org/apache/hadoop/hbase/client/AsyncTable.get:(Lorg/apache/hadoop/hbase/client/Get;)Ljava/util/concurrent/CompletableFuture;
     318: invokevirtual #5                  // Method java/util/concurrent/CompletableFuture.get:()Ljava/lang/Object;
     321: pop
     322: goto          330
     325: astore        8
     327: iconst_0
     328: istore        7
     330: iload         7
     332: invokestatic  #12                 // Method org/junit/Assert.assertTrue:(Z)V
     335: aload_0
     336: getfield      #2                  // Field admin:Lorg/apache/hadoop/hbase/client/AsyncAdmin;
     339: getstatic     #13                 // Field org/apache/hadoop/hbase/TableName.META_TABLE_NAME:Lorg/apache/hadoop/hbase/TableName;
     342: invokeinterface #43,  2           // InterfaceMethod org/apache/hadoop/hbase/client/AsyncAdmin.disableTable:(Lorg/apache/hadoop/hbase/TableName;)Ljava/util/concurrent/CompletableFuture;
     347: invokevirtual #5                  // Method java/util/concurrent/CompletableFuture.get:()Ljava/lang/Object;
     350: pop
     351: ldc           #91                 // String meta table can not be disabled
     353: invokestatic  #92                 // Method org/junit/Assert.fail:(Ljava/lang/String;)V
     356: goto          378
     359: astore        8
     361: aload         8
     363: invokevirtual #93                 // Method java/util/concurrent/ExecutionException.getCause:()Ljava/lang/Throwable;
     366: astore        9
     368: aload         9
     370: ldc           #94                 // class org/apache/hadoop/hbase/DoNotRetryIOException
     372: invokestatic  #95                 // Method org/hamcrest/CoreMatchers.instanceOf:(Ljava/lang/Class;)Lorg/hamcrest/Matcher;
     375: invokestatic  #96                 // Method org/junit/Assert.assertThat:(Ljava/lang/Object;Lorg/hamcrest/Matcher;)V
     378: return
    Exception table:
       from    to  target type
         193   205   208   Class java/util/concurrent/ExecutionException
         216   233   236   Class java/util/concurrent/ExecutionException
         310   322   325   Class java/lang/Exception
         335   356   359   Class java/util/concurrent/ExecutionException

  public void testDisableAndEnableTables() throws java.lang.Exception;
    Code:
       0: new           #17                 // class java/lang/StringBuilder
       3: dup
       4: invokespecial #18                 // Method java/lang/StringBuilder."<init>":()V
       7: aload_0
       8: getfield      #3                  // Field tableName:Lorg/apache/hadoop/hbase/TableName;
      11: invokevirtual #19                 // Method org/apache/hadoop/hbase/TableName.getNameAsString:()Ljava/lang/String;
      14: invokevirtual #20                 // Method java/lang/StringBuilder.append:(Ljava/lang/String;)Ljava/lang/StringBuilder;
      17: ldc           #21                 // String 1
      19: invokevirtual #20                 // Method java/lang/StringBuilder.append:(Ljava/lang/String;)Ljava/lang/StringBuilder;
      22: invokevirtual #22                 // Method java/lang/StringBuilder.toString:()Ljava/lang/String;
      25: invokestatic  #23                 // Method org/apache/hadoop/hbase/TableName.valueOf:(Ljava/lang/String;)Lorg/apache/hadoop/hbase/TableName;
      28: astore_1
      29: new           #17                 // class java/lang/StringBuilder
      32: dup
      33: invokespecial #18                 // Method java/lang/StringBuilder."<init>":()V
      36: aload_0
      37: getfield      #3                  // Field tableName:Lorg/apache/hadoop/hbase/TableName;
      40: invokevirtual #19                 // Method org/apache/hadoop/hbase/TableName.getNameAsString:()Ljava/lang/String;
      43: invokevirtual #20                 // Method java/lang/StringBuilder.append:(Ljava/lang/String;)Ljava/lang/StringBuilder;
      46: ldc           #24                 // String 2
      48: invokevirtual #20                 // Method java/lang/StringBuilder.append:(Ljava/lang/String;)Ljava/lang/StringBuilder;
      51: invokevirtual #22                 // Method java/lang/StringBuilder.toString:()Ljava/lang/String;
      54: invokestatic  #23                 // Method org/apache/hadoop/hbase/TableName.valueOf:(Ljava/lang/String;)Lorg/apache/hadoop/hbase/TableName;
      57: astore_2
      58: aload_0
      59: aload_1
      60: invokevirtual #27                 // Method createTableWithDefaultConf:(Lorg/apache/hadoop/hbase/TableName;)V
      63: aload_0
      64: aload_2
      65: invokevirtual #27                 // Method createTableWithDefaultConf:(Lorg/apache/hadoop/hbase/TableName;)V
      68: getstatic     #60                 // Field ASYNC_CONN:Lorg/apache/hadoop/hbase/client/AsyncConnection;
      71: aload_1
      72: invokeinterface #61,  2           // InterfaceMethod org/apache/hadoop/hbase/client/AsyncConnection.getTable:(Lorg/apache/hadoop/hbase/TableName;)Lorg/apache/hadoop/hbase/client/AsyncTable;
      77: astore_3
      78: getstatic     #60                 // Field ASYNC_CONN:Lorg/apache/hadoop/hbase/client/AsyncConnection;
      81: aload_1
      82: invokeinterface #61,  2           // InterfaceMethod org/apache/hadoop/hbase/client/AsyncConnection.getTable:(Lorg/apache/hadoop/hbase/TableName;)Lorg/apache/hadoop/hbase/client/AsyncTable;
      87: astore        4
      89: ldc           #62                 // String row
      91: invokestatic  #63                 // Method org/apache/hadoop/hbase/util/Bytes.toBytes:(Ljava/lang/String;)[B
      94: astore        5
      96: ldc           #64                 // String qualifier
      98: invokestatic  #63                 // Method org/apache/hadoop/hbase/util/Bytes.toBytes:(Ljava/lang/String;)[B
     101: astore        6
     103: ldc           #65                 // String value
     105: invokestatic  #63                 // Method org/apache/hadoop/hbase/util/Bytes.toBytes:(Ljava/lang/String;)[B
     108: astore        7
     110: new           #66                 // class org/apache/hadoop/hbase/client/Put
     113: dup
     114: aload         5
     116: invokespecial #67                 // Method org/apache/hadoop/hbase/client/Put."<init>":([B)V
     119: astore        8
     121: aload         8
     123: getstatic     #10                 // Field FAMILY:[B
     126: aload         6
     128: aload         7
     130: invokevirtual #68                 // Method org/apache/hadoop/hbase/client/Put.addColumn:([B[B[B)Lorg/apache/hadoop/hbase/client/Put;
     133: pop
     134: aload_3
     135: aload         8
     137: invokeinterface #69,  2           // InterfaceMethod org/apache/hadoop/hbase/client/AsyncTable.put:(Lorg/apache/hadoop/hbase/client/Put;)Ljava/util/concurrent/CompletableFuture;
     142: invokevirtual #44                 // Method java/util/concurrent/CompletableFuture.join:()Ljava/lang/Object;
     145: pop
     146: aload         4
     148: aload         8
     150: invokeinterface #69,  2           // InterfaceMethod org/apache/hadoop/hbase/client/AsyncTable.put:(Lorg/apache/hadoop/hbase/client/Put;)Ljava/util/concurrent/CompletableFuture;
     155: invokevirtual #44                 // Method java/util/concurrent/CompletableFuture.join:()Ljava/lang/Object;
     158: pop
     159: new           #70                 // class org/apache/hadoop/hbase/client/Get
     162: dup
     163: aload         5
     165: invokespecial #71                 // Method org/apache/hadoop/hbase/client/Get."<init>":([B)V
     168: astore        9
     170: aload         9
     172: getstatic     #10                 // Field FAMILY:[B
     175: aload         6
     177: invokevirtual #72                 // Method org/apache/hadoop/hbase/client/Get.addColumn:([B[B)Lorg/apache/hadoop/hbase/client/Get;
     180: pop
     181: aload_3
     182: aload         9
     184: invokeinterface #73,  2           // InterfaceMethod org/apache/hadoop/hbase/client/AsyncTable.get:(Lorg/apache/hadoop/hbase/client/Get;)Ljava/util/concurrent/CompletableFuture;
     189: invokevirtual #5                  // Method java/util/concurrent/CompletableFuture.get:()Ljava/lang/Object;
     192: pop
     193: aload         4
     195: aload         9
     197: invokeinterface #73,  2           // InterfaceMethod org/apache/hadoop/hbase/client/AsyncTable.get:(Lorg/apache/hadoop/hbase/client/Get;)Ljava/util/concurrent/CompletableFuture;
     202: invokevirtual #5                  // Method java/util/concurrent/CompletableFuture.get:()Ljava/lang/Object;
     205: pop
     206: aload_0
     207: getfield      #2                  // Field admin:Lorg/apache/hadoop/hbase/client/AsyncAdmin;
     210: new           #17                 // class java/lang/StringBuilder
     213: dup
     214: invokespecial #18                 // Method java/lang/StringBuilder."<init>":()V
     217: aload_0
     218: getfield      #3                  // Field tableName:Lorg/apache/hadoop/hbase/TableName;
     221: invokevirtual #19                 // Method org/apache/hadoop/hbase/TableName.getNameAsString:()Ljava/lang/String;
     224: invokevirtual #20                 // Method java/lang/StringBuilder.append:(Ljava/lang/String;)Ljava/lang/StringBuilder;
     227: ldc           #97                 // String .*
     229: invokevirtual #20                 // Method java/lang/StringBuilder.append:(Ljava/lang/String;)Ljava/lang/StringBuilder;
     232: invokevirtual #22                 // Method java/lang/StringBuilder.toString:()Ljava/lang/String;
     235: invokestatic  #98                 // Method java/util/regex/Pattern.compile:(Ljava/lang/String;)Ljava/util/regex/Pattern;
     238: iconst_0
     239: invokeinterface #99,  3           // InterfaceMethod org/apache/hadoop/hbase/client/AsyncAdmin.listTableNames:(Ljava/util/regex/Pattern;Z)Ljava/util/concurrent/CompletableFuture;
     244: invokevirtual #5                  // Method java/util/concurrent/CompletableFuture.get:()Ljava/lang/Object;
     247: checkcast     #15                 // class java/util/List
     250: aload_0
     251: invokedynamic #100,  0            // InvokeDynamic #0:accept:(Lorg/apache/hadoop/hbase/client/TestAsyncTableAdminApi3;)Ljava/util/function/Consumer;
     256: invokeinterface #101,  2          // InterfaceMethod java/util/List.forEach:(Ljava/util/function/Consumer;)V
     261: new           #70                 // class org/apache/hadoop/hbase/client/Get
     264: dup
     265: aload         5
     267: invokespecial #71                 // Method org/apache/hadoop/hbase/client/Get."<init>":([B)V
     270: astore        9
     272: aload         9
     274: getstatic     #10                 // Field FAMILY:[B
     277: aload         6
     279: invokevirtual #72                 // Method org/apache/hadoop/hbase/client/Get.addColumn:([B[B)Lorg/apache/hadoop/hbase/client/Get;
     282: pop
     283: iconst_0
     284: istore        10
     286: aload_3
     287: aload         9
     289: invokeinterface #73,  2           // InterfaceMethod org/apache/hadoop/hbase/client/AsyncTable.get:(Lorg/apache/hadoop/hbase/client/Get;)Ljava/util/concurrent/CompletableFuture;
     294: invokevirtual #5                  // Method java/util/concurrent/CompletableFuture.get:()Ljava/lang/Object;
     297: pop
     298: goto          306
     301: astore        11
     303: iconst_1
     304: istore        10
     306: iload         10
     308: invokestatic  #12                 // Method org/junit/Assert.assertTrue:(Z)V
     311: iconst_0
     312: istore        10
     314: aload         4
     316: aload         9
     318: invokeinterface #73,  2           // InterfaceMethod org/apache/hadoop/hbase/client/AsyncTable.get:(Lorg/apache/hadoop/hbase/client/Get;)Ljava/util/concurrent/CompletableFuture;
     323: invokevirtual #5                  // Method java/util/concurrent/CompletableFuture.get:()Ljava/lang/Object;
     326: pop
     327: goto          335
     330: astore        11
     332: iconst_1
     333: istore        10
     335: iload         10
     337: invokestatic  #12                 // Method org/junit/Assert.assertTrue:(Z)V
     340: getstatic     #79                 // Field org/apache/hadoop/hbase/client/TableState$State.DISABLED:Lorg/apache/hadoop/hbase/client/TableState$State;
     343: aload_1
     344: invokestatic  #81                 // Method org/apache/hadoop/hbase/client/TestAsyncTableAdminApi.getStateFromMeta:(Lorg/apache/hadoop/hbase/TableName;)Lorg/apache/hadoop/hbase/client/TableState$State;
     347: invokestatic  #82                 // Method org/junit/Assert.assertEquals:(Ljava/lang/Object;Ljava/lang/Object;)V
     350: getstatic     #79                 // Field org/apache/hadoop/hbase/client/TableState$State.DISABLED:Lorg/apache/hadoop/hbase/client/TableState$State;
     353: aload_2
     354: invokestatic  #81                 // Method org/apache/hadoop/hbase/client/TestAsyncTableAdminApi.getStateFromMeta:(Lorg/apache/hadoop/hbase/TableName;)Lorg/apache/hadoop/hbase/client/TableState$State;
     357: invokestatic  #82                 // Method org/junit/Assert.assertEquals:(Ljava/lang/Object;Ljava/lang/Object;)V
     360: aload_0
     361: getfield      #2                  // Field admin:Lorg/apache/hadoop/hbase/client/AsyncAdmin;
     364: new           #17                 // class java/lang/StringBuilder
     367: dup
     368: invokespecial #18                 // Method java/lang/StringBuilder."<init>":()V
     371: aload_0
     372: getfield      #3                  // Field tableName:Lorg/apache/hadoop/hbase/TableName;
     375: invokevirtual #19                 // Method org/apache/hadoop/hbase/TableName.getNameAsString:()Ljava/lang/String;
     378: invokevirtual #20                 // Method java/lang/StringBuilder.append:(Ljava/lang/String;)Ljava/lang/StringBuilder;
     381: ldc           #97                 // String .*
     383: invokevirtual #20                 // Method java/lang/StringBuilder.append:(Ljava/lang/String;)Ljava/lang/StringBuilder;
     386: invokevirtual #22                 // Method java/lang/StringBuilder.toString:()Ljava/lang/String;
     389: invokestatic  #98                 // Method java/util/regex/Pattern.compile:(Ljava/lang/String;)Ljava/util/regex/Pattern;
     392: iconst_0
     393: invokeinterface #99,  3           // InterfaceMethod org/apache/hadoop/hbase/client/AsyncAdmin.listTableNames:(Ljava/util/regex/Pattern;Z)Ljava/util/concurrent/CompletableFuture;
     398: invokevirtual #5                  // Method java/util/concurrent/CompletableFuture.get:()Ljava/lang/Object;
     401: checkcast     #15                 // class java/util/List
     404: aload_0
     405: invokedynamic #102,  0            // InvokeDynamic #1:accept:(Lorg/apache/hadoop/hbase/client/TestAsyncTableAdminApi3;)Ljava/util/function/Consumer;
     410: invokeinterface #101,  2          // InterfaceMethod java/util/List.forEach:(Ljava/util/function/Consumer;)V
     415: aload_3
     416: aload         9
     418: invokeinterface #73,  2           // InterfaceMethod org/apache/hadoop/hbase/client/AsyncTable.get:(Lorg/apache/hadoop/hbase/client/Get;)Ljava/util/concurrent/CompletableFuture;
     423: invokevirtual #5                  // Method java/util/concurrent/CompletableFuture.get:()Ljava/lang/Object;
     426: pop
     427: goto          435
     430: astore        11
     432: iconst_0
     433: istore        10
     435: aload         4
     437: aload         9
     439: invokeinterface #73,  2           // InterfaceMethod org/apache/hadoop/hbase/client/AsyncTable.get:(Lorg/apache/hadoop/hbase/client/Get;)Ljava/util/concurrent/CompletableFuture;
     444: invokevirtual #5                  // Method java/util/concurrent/CompletableFuture.get:()Ljava/lang/Object;
     447: pop
     448: goto          456
     451: astore        11
     453: iconst_0
     454: istore        10
     456: iload         10
     458: invokestatic  #12                 // Method org/junit/Assert.assertTrue:(Z)V
     461: getstatic     #89                 // Field org/apache/hadoop/hbase/client/TableState$State.ENABLED:Lorg/apache/hadoop/hbase/client/TableState$State;
     464: aload_1
     465: invokestatic  #81                 // Method org/apache/hadoop/hbase/client/TestAsyncTableAdminApi.getStateFromMeta:(Lorg/apache/hadoop/hbase/TableName;)Lorg/apache/hadoop/hbase/client/TableState$State;
     468: invokestatic  #82                 // Method org/junit/Assert.assertEquals:(Ljava/lang/Object;Ljava/lang/Object;)V
     471: getstatic     #89                 // Field org/apache/hadoop/hbase/client/TableState$State.ENABLED:Lorg/apache/hadoop/hbase/client/TableState$State;
     474: aload_2
     475: invokestatic  #81                 // Method org/apache/hadoop/hbase/client/TestAsyncTableAdminApi.getStateFromMeta:(Lorg/apache/hadoop/hbase/TableName;)Lorg/apache/hadoop/hbase/client/TableState$State;
     478: invokestatic  #82                 // Method org/junit/Assert.assertEquals:(Ljava/lang/Object;Ljava/lang/Object;)V
     481: return
    Exception table:
       from    to  target type
         286   298   301   Class java/util/concurrent/ExecutionException
         314   327   330   Class java/util/concurrent/ExecutionException
         415   427   430   Class java/lang/Exception
         435   448   451   Class java/lang/Exception

  public void testEnableTableRetainAssignment() throws java.lang.Exception;
    Code:
       0: bipush        9
       2: anewarray     #49                 // class "[B"
       5: dup
       6: iconst_0
       7: iconst_3
       8: newarray       byte
      10: dup
      11: iconst_0
      12: iconst_1
      13: bastore
      14: dup
      15: iconst_1
      16: iconst_1
      17: bastore
      18: dup
      19: iconst_2
      20: iconst_1
      21: bastore
      22: aastore
      23: dup
      24: iconst_1
      25: iconst_3
      26: newarray       byte
      28: dup
      29: iconst_0
      30: iconst_2
      31: bastore
      32: dup
      33: iconst_1
      34: iconst_2
      35: bastore
      36: dup
      37: iconst_2
      38: iconst_2
      39: bastore
      40: aastore
      41: dup
      42: iconst_2
      43: iconst_3
      44: newarray       byte
      46: dup
      47: iconst_0
      48: iconst_3
      49: bastore
      50: dup
      51: iconst_1
      52: iconst_3
      53: bastore
      54: dup
      55: iconst_2
      56: iconst_3
      57: bastore
      58: aastore
      59: dup
      60: iconst_3
      61: iconst_3
      62: newarray       byte
      64: dup
      65: iconst_0
      66: iconst_4
      67: bastore
      68: dup
      69: iconst_1
      70: iconst_4
      71: bastore
      72: dup
      73: iconst_2
      74: iconst_4
      75: bastore
      76: aastore
      77: dup
      78: iconst_4
      79: iconst_3
      80: newarray       byte
      82: dup
      83: iconst_0
      84: iconst_5
      85: bastore
      86: dup
      87: iconst_1
      88: iconst_5
      89: bastore
      90: dup
      91: iconst_2
      92: iconst_5
      93: bastore
      94: aastore
      95: dup
      96: iconst_5
      97: iconst_3
      98: newarray       byte
     100: dup
     101: iconst_0
     102: bipush        6
     104: bastore
     105: dup
     106: iconst_1
     107: bipush        6
     109: bastore
     110: dup
     111: iconst_2
     112: bipush        6
     114: bastore
     115: aastore
     116: dup
     117: bipush        6
     119: iconst_3
     120: newarray       byte
     122: dup
     123: iconst_0
     124: bipush        7
     126: bastore
     127: dup
     128: iconst_1
     129: bipush        7
     131: bastore
     132: dup
     133: iconst_2
     134: bipush        7
     136: bastore
     137: aastore
     138: dup
     139: bipush        7
     141: iconst_3
     142: newarray       byte
     144: dup
     145: iconst_0
     146: bipush        8
     148: bastore
     149: dup
     150: iconst_1
     151: bipush        8
     153: bastore
     154: dup
     155: iconst_2
     156: bipush        8
     158: bastore
     159: aastore
     160: dup
     161: bipush        8
     163: iconst_3
     164: newarray       byte
     166: dup
     167: iconst_0
     168: bipush        9
     170: bastore
     171: dup
     172: iconst_1
     173: bipush        9
     175: bastore
     176: dup
     177: iconst_2
     178: bipush        9
     180: bastore
     181: aastore
     182: astore_1
     183: aload_1
     184: arraylength
     185: iconst_1
     186: iadd
     187: istore_2
     188: aload_0
     189: aload_0
     190: getfield      #3                  // Field tableName:Lorg/apache/hadoop/hbase/TableName;
     193: aload_1
     194: invokevirtual #103                // Method createTableWithDefaultConf:(Lorg/apache/hadoop/hbase/TableName;[[B)V
     197: getstatic     #60                 // Field ASYNC_CONN:Lorg/apache/hadoop/hbase/client/AsyncConnection;
     200: getstatic     #13                 // Field org/apache/hadoop/hbase/TableName.META_TABLE_NAME:Lorg/apache/hadoop/hbase/TableName;
     203: invokeinterface #61,  2           // InterfaceMethod org/apache/hadoop/hbase/client/AsyncConnection.getTable:(Lorg/apache/hadoop/hbase/TableName;)Lorg/apache/hadoop/hbase/client/AsyncTable;
     208: astore_3
     209: aload_3
     210: aload_0
     211: getfield      #3                  // Field tableName:Lorg/apache/hadoop/hbase/TableName;
     214: invokestatic  #104                // Method java/util/Optional.of:(Ljava/lang/Object;)Ljava/util/Optional;
     217: invokestatic  #105                // Method org/apache/hadoop/hbase/AsyncMetaTableAccessor.getTableHRegionLocations:(Lorg/apache/hadoop/hbase/client/AsyncTable;Ljava/util/Optional;)Ljava/util/concurrent/CompletableFuture;
     220: invokevirtual #5                  // Method java/util/concurrent/CompletableFuture.get:()Ljava/lang/Object;
     223: checkcast     #15                 // class java/util/List
     226: astore        4
     228: new           #17                 // class java/lang/StringBuilder
     231: dup
     232: invokespecial #18                 // Method java/lang/StringBuilder."<init>":()V
     235: ldc           #106                // String Tried to create
     237: invokevirtual #20                 // Method java/lang/StringBuilder.append:(Ljava/lang/String;)Ljava/lang/StringBuilder;
     240: iload_2
     241: invokevirtual #107                // Method java/lang/StringBuilder.append:(I)Ljava/lang/StringBuilder;
     244: ldc           #108                // String  regions but only found
     246: invokevirtual #20                 // Method java/lang/StringBuilder.append:(Ljava/lang/String;)Ljava/lang/StringBuilder;
     249: aload         4
     251: invokeinterface #16,  1           // InterfaceMethod java/util/List.size:()I
     256: invokevirtual #107                // Method java/lang/StringBuilder.append:(I)Ljava/lang/StringBuilder;
     259: invokevirtual #22                 // Method java/lang/StringBuilder.toString:()Ljava/lang/String;
     262: iload_2
     263: i2l
     264: aload         4
     266: invokeinterface #16,  1           // InterfaceMethod java/util/List.size:()I
     271: i2l
     272: invokestatic  #109                // Method org/junit/Assert.assertEquals:(Ljava/lang/String;JJ)V
     275: aload_0
     276: getfield      #2                  // Field admin:Lorg/apache/hadoop/hbase/client/AsyncAdmin;
     279: aload_0
     280: getfield      #3                  // Field tableName:Lorg/apache/hadoop/hbase/TableName;
     283: invokeinterface #43,  2           // InterfaceMethod org/apache/hadoop/hbase/client/AsyncAdmin.disableTable:(Lorg/apache/hadoop/hbase/TableName;)Ljava/util/concurrent/CompletableFuture;
     288: invokevirtual #44                 // Method java/util/concurrent/CompletableFuture.join:()Ljava/lang/Object;
     291: pop
     292: aload_0
     293: getfield      #2                  // Field admin:Lorg/apache/hadoop/hbase/client/AsyncAdmin;
     296: aload_0
     297: getfield      #3                  // Field tableName:Lorg/apache/hadoop/hbase/TableName;
     300: invokeinterface #87,  2           // InterfaceMethod org/apache/hadoop/hbase/client/AsyncAdmin.enableTable:(Lorg/apache/hadoop/hbase/TableName;)Ljava/util/concurrent/CompletableFuture;
     305: invokevirtual #44                 // Method java/util/concurrent/CompletableFuture.join:()Ljava/lang/Object;
     308: pop
     309: aload_3
     310: aload_0
     311: getfield      #3                  // Field tableName:Lorg/apache/hadoop/hbase/TableName;
     314: invokestatic  #104                // Method java/util/Optional.of:(Ljava/lang/Object;)Ljava/util/Optional;
     317: invokestatic  #105                // Method org/apache/hadoop/hbase/AsyncMetaTableAccessor.getTableHRegionLocations:(Lorg/apache/hadoop/hbase/client/AsyncTable;Ljava/util/Optional;)Ljava/util/concurrent/CompletableFuture;
     320: invokevirtual #5                  // Method java/util/concurrent/CompletableFuture.get:()Ljava/lang/Object;
     323: checkcast     #15                 // class java/util/List
     326: astore        5
     328: aload         4
     330: invokeinterface #16,  1           // InterfaceMethod java/util/List.size:()I
     335: i2l
     336: aload         5
     338: invokeinterface #16,  1           // InterfaceMethod java/util/List.size:()I
     343: i2l
     344: invokestatic  #39                 // Method org/junit/Assert.assertEquals:(JJ)V
     347: aload         5
     349: aload         4
     351: invokeinterface #110,  2          // InterfaceMethod java/util/List.containsAll:(Ljava/util/Collection;)Z
     356: invokestatic  #12                 // Method org/junit/Assert.assertTrue:(Z)V
     359: return

  public void testIsTableEnabledAndDisabled() throws java.lang.Exception;
    Code:
       0: aload_0
       1: aload_0
       2: getfield      #3                  // Field tableName:Lorg/apache/hadoop/hbase/TableName;
       5: invokevirtual #27                 // Method createTableWithDefaultConf:(Lorg/apache/hadoop/hbase/TableName;)V
       8: aload_0
       9: getfield      #2                  // Field admin:Lorg/apache/hadoop/hbase/client/AsyncAdmin;
      12: aload_0
      13: getfield      #3                  // Field tableName:Lorg/apache/hadoop/hbase/TableName;
      16: invokeinterface #111,  2          // InterfaceMethod org/apache/hadoop/hbase/client/AsyncAdmin.isTableEnabled:(Lorg/apache/hadoop/hbase/TableName;)Ljava/util/concurrent/CompletableFuture;
      21: invokevirtual #5                  // Method java/util/concurrent/CompletableFuture.get:()Ljava/lang/Object;
      24: checkcast     #6                  // class java/lang/Boolean
      27: invokevirtual #7                  // Method java/lang/Boolean.booleanValue:()Z
      30: invokestatic  #12                 // Method org/junit/Assert.assertTrue:(Z)V
      33: aload_0
      34: getfield      #2                  // Field admin:Lorg/apache/hadoop/hbase/client/AsyncAdmin;
      37: aload_0
      38: getfield      #3                  // Field tableName:Lorg/apache/hadoop/hbase/TableName;
      41: invokeinterface #112,  2          // InterfaceMethod org/apache/hadoop/hbase/client/AsyncAdmin.isTableDisabled:(Lorg/apache/hadoop/hbase/TableName;)Ljava/util/concurrent/CompletableFuture;
      46: invokevirtual #5                  // Method java/util/concurrent/CompletableFuture.get:()Ljava/lang/Object;
      49: checkcast     #6                  // class java/lang/Boolean
      52: invokevirtual #7                  // Method java/lang/Boolean.booleanValue:()Z
      55: invokestatic  #8                  // Method org/junit/Assert.assertFalse:(Z)V
      58: aload_0
      59: getfield      #2                  // Field admin:Lorg/apache/hadoop/hbase/client/AsyncAdmin;
      62: aload_0
      63: getfield      #3                  // Field tableName:Lorg/apache/hadoop/hbase/TableName;
      66: invokeinterface #43,  2           // InterfaceMethod org/apache/hadoop/hbase/client/AsyncAdmin.disableTable:(Lorg/apache/hadoop/hbase/TableName;)Ljava/util/concurrent/CompletableFuture;
      71: invokevirtual #44                 // Method java/util/concurrent/CompletableFuture.join:()Ljava/lang/Object;
      74: pop
      75: aload_0
      76: getfield      #2                  // Field admin:Lorg/apache/hadoop/hbase/client/AsyncAdmin;
      79: aload_0
      80: getfield      #3                  // Field tableName:Lorg/apache/hadoop/hbase/TableName;
      83: invokeinterface #111,  2          // InterfaceMethod org/apache/hadoop/hbase/client/AsyncAdmin.isTableEnabled:(Lorg/apache/hadoop/hbase/TableName;)Ljava/util/concurrent/CompletableFuture;
      88: invokevirtual #5                  // Method java/util/concurrent/CompletableFuture.get:()Ljava/lang/Object;
      91: checkcast     #6                  // class java/lang/Boolean
      94: invokevirtual #7                  // Method java/lang/Boolean.booleanValue:()Z
      97: invokestatic  #8                  // Method org/junit/Assert.assertFalse:(Z)V
     100: aload_0
     101: getfield      #2                  // Field admin:Lorg/apache/hadoop/hbase/client/AsyncAdmin;
     104: aload_0
     105: getfield      #3                  // Field tableName:Lorg/apache/hadoop/hbase/TableName;
     108: invokeinterface #112,  2          // InterfaceMethod org/apache/hadoop/hbase/client/AsyncAdmin.isTableDisabled:(Lorg/apache/hadoop/hbase/TableName;)Ljava/util/concurrent/CompletableFuture;
     113: invokevirtual #5                  // Method java/util/concurrent/CompletableFuture.get:()Ljava/lang/Object;
     116: checkcast     #6                  // class java/lang/Boolean
     119: invokevirtual #7                  // Method java/lang/Boolean.booleanValue:()Z
     122: invokestatic  #12                 // Method org/junit/Assert.assertTrue:(Z)V
     125: aload_0
     126: getfield      #2                  // Field admin:Lorg/apache/hadoop/hbase/client/AsyncAdmin;
     129: getstatic     #13                 // Field org/apache/hadoop/hbase/TableName.META_TABLE_NAME:Lorg/apache/hadoop/hbase/TableName;
     132: invokeinterface #111,  2          // InterfaceMethod org/apache/hadoop/hbase/client/AsyncAdmin.isTableEnabled:(Lorg/apache/hadoop/hbase/TableName;)Ljava/util/concurrent/CompletableFuture;
     137: invokevirtual #5                  // Method java/util/concurrent/CompletableFuture.get:()Ljava/lang/Object;
     140: checkcast     #6                  // class java/lang/Boolean
     143: invokevirtual #7                  // Method java/lang/Boolean.booleanValue:()Z
     146: invokestatic  #12                 // Method org/junit/Assert.assertTrue:(Z)V
     149: aload_0
     150: getfield      #2                  // Field admin:Lorg/apache/hadoop/hbase/client/AsyncAdmin;
     153: getstatic     #13                 // Field org/apache/hadoop/hbase/TableName.META_TABLE_NAME:Lorg/apache/hadoop/hbase/TableName;
     156: invokeinterface #112,  2          // InterfaceMethod org/apache/hadoop/hbase/client/AsyncAdmin.isTableDisabled:(Lorg/apache/hadoop/hbase/TableName;)Ljava/util/concurrent/CompletableFuture;
     161: invokevirtual #5                  // Method java/util/concurrent/CompletableFuture.get:()Ljava/lang/Object;
     164: checkcast     #6                  // class java/lang/Boolean
     167: invokevirtual #7                  // Method java/lang/Boolean.booleanValue:()Z
     170: invokestatic  #8                  // Method org/junit/Assert.assertFalse:(Z)V
     173: return

  public void testIsTableAvailable() throws java.lang.Exception;
    Code:
       0: aload_0
       1: aload_0
       2: getfield      #3                  // Field tableName:Lorg/apache/hadoop/hbase/TableName;
       5: invokevirtual #27                 // Method createTableWithDefaultConf:(Lorg/apache/hadoop/hbase/TableName;)V
       8: getstatic     #9                  // Field TEST_UTIL:Lorg/apache/hadoop/hbase/HBaseTestingUtility;
      11: aload_0
      12: getfield      #3                  // Field tableName:Lorg/apache/hadoop/hbase/TableName;
      15: invokevirtual #113                // Method org/apache/hadoop/hbase/HBaseTestingUtility.waitTableAvailable:(Lorg/apache/hadoop/hbase/TableName;)V
      18: aload_0
      19: getfield      #2                  // Field admin:Lorg/apache/hadoop/hbase/client/AsyncAdmin;
      22: aload_0
      23: getfield      #3                  // Field tableName:Lorg/apache/hadoop/hbase/TableName;
      26: invokeinterface #114,  2          // InterfaceMethod org/apache/hadoop/hbase/client/AsyncAdmin.isTableAvailable:(Lorg/apache/hadoop/hbase/TableName;)Ljava/util/concurrent/CompletableFuture;
      31: invokevirtual #5                  // Method java/util/concurrent/CompletableFuture.get:()Ljava/lang/Object;
      34: checkcast     #6                  // class java/lang/Boolean
      37: invokevirtual #7                  // Method java/lang/Boolean.booleanValue:()Z
      40: invokestatic  #12                 // Method org/junit/Assert.assertTrue:(Z)V
      43: aload_0
      44: getfield      #2                  // Field admin:Lorg/apache/hadoop/hbase/client/AsyncAdmin;
      47: getstatic     #13                 // Field org/apache/hadoop/hbase/TableName.META_TABLE_NAME:Lorg/apache/hadoop/hbase/TableName;
      50: invokeinterface #114,  2          // InterfaceMethod org/apache/hadoop/hbase/client/AsyncAdmin.isTableAvailable:(Lorg/apache/hadoop/hbase/TableName;)Ljava/util/concurrent/CompletableFuture;
      55: invokevirtual #5                  // Method java/util/concurrent/CompletableFuture.get:()Ljava/lang/Object;
      58: checkcast     #6                  // class java/lang/Boolean
      61: invokevirtual #7                  // Method java/lang/Boolean.booleanValue:()Z
      64: invokestatic  #12                 // Method org/junit/Assert.assertTrue:(Z)V
      67: return

  static {};
    Code:
       0: ldc           #116                // class org/apache/hadoop/hbase/client/TestAsyncTableAdminApi3
       2: invokestatic  #117                // Method org/apache/hadoop/hbase/HBaseClassTestRule.forClass:(Ljava/lang/Class;)Lorg/apache/hadoop/hbase/HBaseClassTestRule;
       5: putstatic     #118                // Field CLASS_RULE:Lorg/apache/hadoop/hbase/HBaseClassTestRule;
       8: return
}
