Compiled from "TestMultiSlaveReplication.java"
public class org.apache.hadoop.hbase.replication.TestMultiSlaveReplication {
  public static final org.apache.hadoop.hbase.HBaseClassTestRule CLASS_RULE;

  public org.apache.hadoop.hbase.replication.TestMultiSlaveReplication();
    Code:
       0: aload_0
       1: invokespecial #1                  // Method java/lang/Object."<init>":()V
       4: return

  public static void setUpBeforeClass() throws java.lang.Exception;
    Code:
       0: invokestatic  #2                  // Method org/apache/hadoop/hbase/HBaseConfiguration.create:()Lorg/apache/hadoop/conf/Configuration;
       3: putstatic     #3                  // Field conf1:Lorg/apache/hadoop/conf/Configuration;
       6: getstatic     #3                  // Field conf1:Lorg/apache/hadoop/conf/Configuration;
       9: ldc           #5                  // String zookeeper.znode.parent
      11: ldc           #6                  // String /1
      13: invokevirtual #7                  // Method org/apache/hadoop/conf/Configuration.set:(Ljava/lang/String;Ljava/lang/String;)V
      16: getstatic     #3                  // Field conf1:Lorg/apache/hadoop/conf/Configuration;
      19: ldc           #8                  // String hbase.regionserver.hlog.blocksize
      21: sipush        20480
      24: invokevirtual #9                  // Method org/apache/hadoop/conf/Configuration.setInt:(Ljava/lang/String;I)V
      27: getstatic     #3                  // Field conf1:Lorg/apache/hadoop/conf/Configuration;
      30: ldc           #10                 // String replication.source.size.capacity
      32: sipush        1024
      35: invokevirtual #9                  // Method org/apache/hadoop/conf/Configuration.setInt:(Ljava/lang/String;I)V
      38: getstatic     #3                  // Field conf1:Lorg/apache/hadoop/conf/Configuration;
      41: ldc           #11                 // String replication.source.sleepforretries
      43: ldc2_w        #12                 // long 100l
      46: invokevirtual #14                 // Method org/apache/hadoop/conf/Configuration.setLong:(Ljava/lang/String;J)V
      49: getstatic     #3                  // Field conf1:Lorg/apache/hadoop/conf/Configuration;
      52: ldc           #15                 // String hbase.regionserver.maxlogs
      54: bipush        10
      56: invokevirtual #9                  // Method org/apache/hadoop/conf/Configuration.setInt:(Ljava/lang/String;I)V
      59: getstatic     #3                  // Field conf1:Lorg/apache/hadoop/conf/Configuration;
      62: ldc           #16                 // String hbase.master.logcleaner.ttl
      64: ldc2_w        #17                 // long 10l
      67: invokevirtual #14                 // Method org/apache/hadoop/conf/Configuration.setLong:(Ljava/lang/String;J)V
      70: getstatic     #3                  // Field conf1:Lorg/apache/hadoop/conf/Configuration;
      73: ldc           #19                 // String hbase.server.thread.wakefrequency
      75: ldc2_w        #12                 // long 100l
      78: invokevirtual #14                 // Method org/apache/hadoop/conf/Configuration.setLong:(Ljava/lang/String;J)V
      81: getstatic     #3                  // Field conf1:Lorg/apache/hadoop/conf/Configuration;
      84: ldc           #21                 // String hbase.coprocessor.user.region.classes
      86: iconst_1
      87: anewarray     #22                 // class java/lang/String
      90: dup
      91: iconst_0
      92: ldc           #23                 // String org.apache.hadoop.hbase.replication.TestMasterReplication$CoprocessorCounter
      94: aastore
      95: invokevirtual #24                 // Method org/apache/hadoop/conf/Configuration.setStrings:(Ljava/lang/String;[Ljava/lang/String;)V
      98: getstatic     #3                  // Field conf1:Lorg/apache/hadoop/conf/Configuration;
     101: ldc           #25                 // String hbase.master.cleaner.interval
     103: sipush        5000
     106: invokevirtual #9                  // Method org/apache/hadoop/conf/Configuration.setInt:(Ljava/lang/String;I)V
     109: new           #26                 // class org/apache/hadoop/hbase/HBaseTestingUtility
     112: dup
     113: getstatic     #3                  // Field conf1:Lorg/apache/hadoop/conf/Configuration;
     116: invokespecial #27                 // Method org/apache/hadoop/hbase/HBaseTestingUtility."<init>":(Lorg/apache/hadoop/conf/Configuration;)V
     119: putstatic     #28                 // Field utility1:Lorg/apache/hadoop/hbase/HBaseTestingUtility;
     122: getstatic     #28                 // Field utility1:Lorg/apache/hadoop/hbase/HBaseTestingUtility;
     125: invokevirtual #29                 // Method org/apache/hadoop/hbase/HBaseTestingUtility.startMiniZKCluster:()Lorg/apache/hadoop/hbase/zookeeper/MiniZooKeeperCluster;
     128: pop
     129: getstatic     #28                 // Field utility1:Lorg/apache/hadoop/hbase/HBaseTestingUtility;
     132: invokevirtual #30                 // Method org/apache/hadoop/hbase/HBaseTestingUtility.getZkCluster:()Lorg/apache/hadoop/hbase/zookeeper/MiniZooKeeperCluster;
     135: astore_0
     136: getstatic     #28                 // Field utility1:Lorg/apache/hadoop/hbase/HBaseTestingUtility;
     139: aload_0
     140: invokevirtual #31                 // Method org/apache/hadoop/hbase/HBaseTestingUtility.setZkCluster:(Lorg/apache/hadoop/hbase/zookeeper/MiniZooKeeperCluster;)V
     143: new           #32                 // class org/apache/hadoop/hbase/zookeeper/ZKWatcher
     146: dup
     147: getstatic     #3                  // Field conf1:Lorg/apache/hadoop/conf/Configuration;
     150: ldc           #33                 // String cluster1
     152: aconst_null
     153: iconst_1
     154: invokespecial #34                 // Method org/apache/hadoop/hbase/zookeeper/ZKWatcher."<init>":(Lorg/apache/hadoop/conf/Configuration;Ljava/lang/String;Lorg/apache/hadoop/hbase/Abortable;Z)V
     157: pop
     158: new           #35                 // class org/apache/hadoop/conf/Configuration
     161: dup
     162: getstatic     #3                  // Field conf1:Lorg/apache/hadoop/conf/Configuration;
     165: invokespecial #36                 // Method org/apache/hadoop/conf/Configuration."<init>":(Lorg/apache/hadoop/conf/Configuration;)V
     168: putstatic     #37                 // Field conf2:Lorg/apache/hadoop/conf/Configuration;
     171: getstatic     #37                 // Field conf2:Lorg/apache/hadoop/conf/Configuration;
     174: ldc           #5                  // String zookeeper.znode.parent
     176: ldc           #38                 // String /2
     178: invokevirtual #7                  // Method org/apache/hadoop/conf/Configuration.set:(Ljava/lang/String;Ljava/lang/String;)V
     181: new           #35                 // class org/apache/hadoop/conf/Configuration
     184: dup
     185: getstatic     #3                  // Field conf1:Lorg/apache/hadoop/conf/Configuration;
     188: invokespecial #36                 // Method org/apache/hadoop/conf/Configuration."<init>":(Lorg/apache/hadoop/conf/Configuration;)V
     191: putstatic     #39                 // Field conf3:Lorg/apache/hadoop/conf/Configuration;
     194: getstatic     #39                 // Field conf3:Lorg/apache/hadoop/conf/Configuration;
     197: ldc           #5                  // String zookeeper.znode.parent
     199: ldc           #40                 // String /3
     201: invokevirtual #7                  // Method org/apache/hadoop/conf/Configuration.set:(Ljava/lang/String;Ljava/lang/String;)V
     204: new           #26                 // class org/apache/hadoop/hbase/HBaseTestingUtility
     207: dup
     208: getstatic     #37                 // Field conf2:Lorg/apache/hadoop/conf/Configuration;
     211: invokespecial #27                 // Method org/apache/hadoop/hbase/HBaseTestingUtility."<init>":(Lorg/apache/hadoop/conf/Configuration;)V
     214: putstatic     #41                 // Field utility2:Lorg/apache/hadoop/hbase/HBaseTestingUtility;
     217: getstatic     #41                 // Field utility2:Lorg/apache/hadoop/hbase/HBaseTestingUtility;
     220: aload_0
     221: invokevirtual #31                 // Method org/apache/hadoop/hbase/HBaseTestingUtility.setZkCluster:(Lorg/apache/hadoop/hbase/zookeeper/MiniZooKeeperCluster;)V
     224: new           #32                 // class org/apache/hadoop/hbase/zookeeper/ZKWatcher
     227: dup
     228: getstatic     #37                 // Field conf2:Lorg/apache/hadoop/conf/Configuration;
     231: ldc           #42                 // String cluster2
     233: aconst_null
     234: iconst_1
     235: invokespecial #34                 // Method org/apache/hadoop/hbase/zookeeper/ZKWatcher."<init>":(Lorg/apache/hadoop/conf/Configuration;Ljava/lang/String;Lorg/apache/hadoop/hbase/Abortable;Z)V
     238: pop
     239: new           #26                 // class org/apache/hadoop/hbase/HBaseTestingUtility
     242: dup
     243: getstatic     #39                 // Field conf3:Lorg/apache/hadoop/conf/Configuration;
     246: invokespecial #27                 // Method org/apache/hadoop/hbase/HBaseTestingUtility."<init>":(Lorg/apache/hadoop/conf/Configuration;)V
     249: putstatic     #43                 // Field utility3:Lorg/apache/hadoop/hbase/HBaseTestingUtility;
     252: getstatic     #43                 // Field utility3:Lorg/apache/hadoop/hbase/HBaseTestingUtility;
     255: aload_0
     256: invokevirtual #31                 // Method org/apache/hadoop/hbase/HBaseTestingUtility.setZkCluster:(Lorg/apache/hadoop/hbase/zookeeper/MiniZooKeeperCluster;)V
     259: new           #32                 // class org/apache/hadoop/hbase/zookeeper/ZKWatcher
     262: dup
     263: getstatic     #39                 // Field conf3:Lorg/apache/hadoop/conf/Configuration;
     266: ldc           #44                 // String cluster3
     268: aconst_null
     269: iconst_1
     270: invokespecial #34                 // Method org/apache/hadoop/hbase/zookeeper/ZKWatcher."<init>":(Lorg/apache/hadoop/conf/Configuration;Ljava/lang/String;Lorg/apache/hadoop/hbase/Abortable;Z)V
     273: pop
     274: new           #45                 // class org/apache/hadoop/hbase/HTableDescriptor
     277: dup
     278: getstatic     #46                 // Field tableName:Lorg/apache/hadoop/hbase/TableName;
     281: invokespecial #47                 // Method org/apache/hadoop/hbase/HTableDescriptor."<init>":(Lorg/apache/hadoop/hbase/TableName;)V
     284: putstatic     #48                 // Field table:Lorg/apache/hadoop/hbase/HTableDescriptor;
     287: new           #49                 // class org/apache/hadoop/hbase/HColumnDescriptor
     290: dup
     291: getstatic     #50                 // Field famName:[B
     294: invokespecial #51                 // Method org/apache/hadoop/hbase/HColumnDescriptor."<init>":([B)V
     297: astore_1
     298: aload_1
     299: iconst_1
     300: invokevirtual #52                 // Method org/apache/hadoop/hbase/HColumnDescriptor.setScope:(I)Lorg/apache/hadoop/hbase/HColumnDescriptor;
     303: pop
     304: getstatic     #48                 // Field table:Lorg/apache/hadoop/hbase/HTableDescriptor;
     307: aload_1
     308: invokevirtual #53                 // Method org/apache/hadoop/hbase/HTableDescriptor.addFamily:(Lorg/apache/hadoop/hbase/HColumnDescriptor;)Lorg/apache/hadoop/hbase/HTableDescriptor;
     311: pop
     312: new           #49                 // class org/apache/hadoop/hbase/HColumnDescriptor
     315: dup
     316: getstatic     #54                 // Field noRepfamName:[B
     319: invokespecial #51                 // Method org/apache/hadoop/hbase/HColumnDescriptor."<init>":([B)V
     322: astore_1
     323: getstatic     #48                 // Field table:Lorg/apache/hadoop/hbase/HTableDescriptor;
     326: aload_1
     327: invokevirtual #53                 // Method org/apache/hadoop/hbase/HTableDescriptor.addFamily:(Lorg/apache/hadoop/hbase/HColumnDescriptor;)Lorg/apache/hadoop/hbase/HTableDescriptor;
     330: pop
     331: return

  public void testMultiSlaveReplication() throws java.lang.Exception;
    Code:
       0: getstatic     #55                 // Field LOG:Lorg/slf4j/Logger;
       3: ldc           #56                 // String testCyclicReplication
       5: invokeinterface #57,  2           // InterfaceMethod org/slf4j/Logger.info:(Ljava/lang/String;)V
      10: getstatic     #28                 // Field utility1:Lorg/apache/hadoop/hbase/HBaseTestingUtility;
      13: invokevirtual #58                 // Method org/apache/hadoop/hbase/HBaseTestingUtility.startMiniCluster:()Lorg/apache/hadoop/hbase/MiniHBaseCluster;
      16: astore_1
      17: getstatic     #41                 // Field utility2:Lorg/apache/hadoop/hbase/HBaseTestingUtility;
      20: invokevirtual #58                 // Method org/apache/hadoop/hbase/HBaseTestingUtility.startMiniCluster:()Lorg/apache/hadoop/hbase/MiniHBaseCluster;
      23: pop
      24: getstatic     #43                 // Field utility3:Lorg/apache/hadoop/hbase/HBaseTestingUtility;
      27: invokevirtual #58                 // Method org/apache/hadoop/hbase/HBaseTestingUtility.startMiniCluster:()Lorg/apache/hadoop/hbase/MiniHBaseCluster;
      30: pop
      31: new           #59                 // class org/apache/hadoop/hbase/client/replication/ReplicationAdmin
      34: dup
      35: getstatic     #3                  // Field conf1:Lorg/apache/hadoop/conf/Configuration;
      38: invokespecial #60                 // Method org/apache/hadoop/hbase/client/replication/ReplicationAdmin."<init>":(Lorg/apache/hadoop/conf/Configuration;)V
      41: astore_2
      42: getstatic     #28                 // Field utility1:Lorg/apache/hadoop/hbase/HBaseTestingUtility;
      45: invokevirtual #61                 // Method org/apache/hadoop/hbase/HBaseTestingUtility.getAdmin:()Lorg/apache/hadoop/hbase/client/Admin;
      48: getstatic     #48                 // Field table:Lorg/apache/hadoop/hbase/HTableDescriptor;
      51: invokeinterface #62,  2           // InterfaceMethod org/apache/hadoop/hbase/client/Admin.createTable:(Lorg/apache/hadoop/hbase/client/TableDescriptor;)V
      56: getstatic     #41                 // Field utility2:Lorg/apache/hadoop/hbase/HBaseTestingUtility;
      59: invokevirtual #61                 // Method org/apache/hadoop/hbase/HBaseTestingUtility.getAdmin:()Lorg/apache/hadoop/hbase/client/Admin;
      62: getstatic     #48                 // Field table:Lorg/apache/hadoop/hbase/HTableDescriptor;
      65: invokeinterface #62,  2           // InterfaceMethod org/apache/hadoop/hbase/client/Admin.createTable:(Lorg/apache/hadoop/hbase/client/TableDescriptor;)V
      70: getstatic     #43                 // Field utility3:Lorg/apache/hadoop/hbase/HBaseTestingUtility;
      73: invokevirtual #61                 // Method org/apache/hadoop/hbase/HBaseTestingUtility.getAdmin:()Lorg/apache/hadoop/hbase/client/Admin;
      76: getstatic     #48                 // Field table:Lorg/apache/hadoop/hbase/HTableDescriptor;
      79: invokeinterface #62,  2           // InterfaceMethod org/apache/hadoop/hbase/client/Admin.createTable:(Lorg/apache/hadoop/hbase/client/TableDescriptor;)V
      84: getstatic     #28                 // Field utility1:Lorg/apache/hadoop/hbase/HBaseTestingUtility;
      87: invokevirtual #63                 // Method org/apache/hadoop/hbase/HBaseTestingUtility.getConnection:()Lorg/apache/hadoop/hbase/client/Connection;
      90: getstatic     #46                 // Field tableName:Lorg/apache/hadoop/hbase/TableName;
      93: invokeinterface #64,  2           // InterfaceMethod org/apache/hadoop/hbase/client/Connection.getTable:(Lorg/apache/hadoop/hbase/TableName;)Lorg/apache/hadoop/hbase/client/Table;
      98: astore_3
      99: getstatic     #41                 // Field utility2:Lorg/apache/hadoop/hbase/HBaseTestingUtility;
     102: invokevirtual #63                 // Method org/apache/hadoop/hbase/HBaseTestingUtility.getConnection:()Lorg/apache/hadoop/hbase/client/Connection;
     105: getstatic     #46                 // Field tableName:Lorg/apache/hadoop/hbase/TableName;
     108: invokeinterface #64,  2           // InterfaceMethod org/apache/hadoop/hbase/client/Connection.getTable:(Lorg/apache/hadoop/hbase/TableName;)Lorg/apache/hadoop/hbase/client/Table;
     113: astore        4
     115: getstatic     #43                 // Field utility3:Lorg/apache/hadoop/hbase/HBaseTestingUtility;
     118: invokevirtual #63                 // Method org/apache/hadoop/hbase/HBaseTestingUtility.getConnection:()Lorg/apache/hadoop/hbase/client/Connection;
     121: getstatic     #46                 // Field tableName:Lorg/apache/hadoop/hbase/TableName;
     124: invokeinterface #64,  2           // InterfaceMethod org/apache/hadoop/hbase/client/Connection.getTable:(Lorg/apache/hadoop/hbase/TableName;)Lorg/apache/hadoop/hbase/client/Table;
     129: astore        5
     131: new           #65                 // class org/apache/hadoop/hbase/replication/ReplicationPeerConfig
     134: dup
     135: invokespecial #66                 // Method org/apache/hadoop/hbase/replication/ReplicationPeerConfig."<init>":()V
     138: astore        6
     140: aload         6
     142: getstatic     #41                 // Field utility2:Lorg/apache/hadoop/hbase/HBaseTestingUtility;
     145: invokevirtual #67                 // Method org/apache/hadoop/hbase/HBaseTestingUtility.getClusterKey:()Ljava/lang/String;
     148: invokevirtual #68                 // Method org/apache/hadoop/hbase/replication/ReplicationPeerConfig.setClusterKey:(Ljava/lang/String;)Lorg/apache/hadoop/hbase/replication/ReplicationPeerConfig;
     151: pop
     152: aload_2
     153: ldc           #69                 // String 1
     155: aload         6
     157: aconst_null
     158: invokevirtual #70                 // Method org/apache/hadoop/hbase/client/replication/ReplicationAdmin.addPeer:(Ljava/lang/String;Lorg/apache/hadoop/hbase/replication/ReplicationPeerConfig;Ljava/util/Map;)V
     161: aload_0
     162: getstatic     #71                 // Field row:[B
     165: getstatic     #50                 // Field famName:[B
     168: aload_3
     169: iconst_1
     170: anewarray     #72                 // class org/apache/hadoop/hbase/client/Table
     173: dup
     174: iconst_0
     175: aload         4
     177: aastore
     178: invokespecial #73                 // Method putAndWait:([B[BLorg/apache/hadoop/hbase/client/Table;[Lorg/apache/hadoop/hbase/client/Table;)V
     181: aload_0
     182: getstatic     #71                 // Field row:[B
     185: aload_3
     186: iconst_1
     187: anewarray     #72                 // class org/apache/hadoop/hbase/client/Table
     190: dup
     191: iconst_0
     192: aload         4
     194: aastore
     195: invokespecial #74                 // Method deleteAndWait:([BLorg/apache/hadoop/hbase/client/Table;[Lorg/apache/hadoop/hbase/client/Table;)V
     198: aload_0
     199: getstatic     #71                 // Field row:[B
     202: iconst_0
     203: iconst_1
     204: anewarray     #72                 // class org/apache/hadoop/hbase/client/Table
     207: dup
     208: iconst_0
     209: aload         5
     211: aastore
     212: invokespecial #75                 // Method checkRow:([BI[Lorg/apache/hadoop/hbase/client/Table;)V
     215: aload_0
     216: getstatic     #76                 // Field row2:[B
     219: getstatic     #50                 // Field famName:[B
     222: aload_3
     223: iconst_1
     224: anewarray     #72                 // class org/apache/hadoop/hbase/client/Table
     227: dup
     228: iconst_0
     229: aload         4
     231: aastore
     232: invokespecial #73                 // Method putAndWait:([B[BLorg/apache/hadoop/hbase/client/Table;[Lorg/apache/hadoop/hbase/client/Table;)V
     235: aload_0
     236: getstatic     #28                 // Field utility1:Lorg/apache/hadoop/hbase/HBaseTestingUtility;
     239: aload_3
     240: invokeinterface #77,  1           // InterfaceMethod org/apache/hadoop/hbase/client/Table.getName:()Lorg/apache/hadoop/hbase/TableName;
     245: getstatic     #76                 // Field row2:[B
     248: invokespecial #78                 // Method rollWALAndWait:(Lorg/apache/hadoop/hbase/HBaseTestingUtility;Lorg/apache/hadoop/hbase/TableName;[B)V
     251: aload_0
     252: getstatic     #79                 // Field row3:[B
     255: getstatic     #50                 // Field famName:[B
     258: aload_3
     259: iconst_1
     260: anewarray     #72                 // class org/apache/hadoop/hbase/client/Table
     263: dup
     264: iconst_0
     265: aload         4
     267: aastore
     268: invokespecial #73                 // Method putAndWait:([B[BLorg/apache/hadoop/hbase/client/Table;[Lorg/apache/hadoop/hbase/client/Table;)V
     271: new           #65                 // class org/apache/hadoop/hbase/replication/ReplicationPeerConfig
     274: dup
     275: invokespecial #66                 // Method org/apache/hadoop/hbase/replication/ReplicationPeerConfig."<init>":()V
     278: astore        6
     280: aload         6
     282: getstatic     #43                 // Field utility3:Lorg/apache/hadoop/hbase/HBaseTestingUtility;
     285: invokevirtual #67                 // Method org/apache/hadoop/hbase/HBaseTestingUtility.getClusterKey:()Ljava/lang/String;
     288: invokevirtual #68                 // Method org/apache/hadoop/hbase/replication/ReplicationPeerConfig.setClusterKey:(Ljava/lang/String;)Lorg/apache/hadoop/hbase/replication/ReplicationPeerConfig;
     291: pop
     292: aload_2
     293: ldc           #80                 // String 2
     295: aload         6
     297: aconst_null
     298: invokevirtual #70                 // Method org/apache/hadoop/hbase/client/replication/ReplicationAdmin.addPeer:(Ljava/lang/String;Lorg/apache/hadoop/hbase/replication/ReplicationPeerConfig;Ljava/util/Map;)V
     301: aload_0
     302: getstatic     #81                 // Field row1:[B
     305: getstatic     #50                 // Field famName:[B
     308: aload_3
     309: iconst_2
     310: anewarray     #72                 // class org/apache/hadoop/hbase/client/Table
     313: dup
     314: iconst_0
     315: aload         4
     317: aastore
     318: dup
     319: iconst_1
     320: aload         5
     322: aastore
     323: invokespecial #73                 // Method putAndWait:([B[BLorg/apache/hadoop/hbase/client/Table;[Lorg/apache/hadoop/hbase/client/Table;)V
     326: aload_0
     327: getstatic     #81                 // Field row1:[B
     330: aload_3
     331: iconst_2
     332: anewarray     #72                 // class org/apache/hadoop/hbase/client/Table
     335: dup
     336: iconst_0
     337: aload         4
     339: aastore
     340: dup
     341: iconst_1
     342: aload         5
     344: aastore
     345: invokespecial #74                 // Method deleteAndWait:([BLorg/apache/hadoop/hbase/client/Table;[Lorg/apache/hadoop/hbase/client/Table;)V
     348: aload_0
     349: getstatic     #76                 // Field row2:[B
     352: iconst_0
     353: iconst_1
     354: anewarray     #72                 // class org/apache/hadoop/hbase/client/Table
     357: dup
     358: iconst_0
     359: aload         5
     361: aastore
     362: invokespecial #75                 // Method checkRow:([BI[Lorg/apache/hadoop/hbase/client/Table;)V
     365: aload_0
     366: getstatic     #79                 // Field row3:[B
     369: iconst_1
     370: iconst_1
     371: anewarray     #72                 // class org/apache/hadoop/hbase/client/Table
     374: dup
     375: iconst_0
     376: aload         5
     378: aastore
     379: invokespecial #75                 // Method checkRow:([BI[Lorg/apache/hadoop/hbase/client/Table;)V
     382: new           #82                 // class org/apache/hadoop/hbase/client/Put
     385: dup
     386: getstatic     #71                 // Field row:[B
     389: invokespecial #83                 // Method org/apache/hadoop/hbase/client/Put."<init>":([B)V
     392: astore        7
     394: aload         7
     396: getstatic     #50                 // Field famName:[B
     399: getstatic     #71                 // Field row:[B
     402: getstatic     #71                 // Field row:[B
     405: invokevirtual #84                 // Method org/apache/hadoop/hbase/client/Put.addColumn:([B[B[B)Lorg/apache/hadoop/hbase/client/Put;
     408: pop
     409: aload_3
     410: aload         7
     412: invokeinterface #85,  2           // InterfaceMethod org/apache/hadoop/hbase/client/Table.put:(Lorg/apache/hadoop/hbase/client/Put;)V
     417: aload_0
     418: getstatic     #28                 // Field utility1:Lorg/apache/hadoop/hbase/HBaseTestingUtility;
     421: aload_3
     422: invokeinterface #77,  1           // InterfaceMethod org/apache/hadoop/hbase/client/Table.getName:()Lorg/apache/hadoop/hbase/TableName;
     427: getstatic     #71                 // Field row:[B
     430: invokespecial #78                 // Method rollWALAndWait:(Lorg/apache/hadoop/hbase/HBaseTestingUtility;Lorg/apache/hadoop/hbase/TableName;[B)V
     433: aload_0
     434: getstatic     #76                 // Field row2:[B
     437: aload_3
     438: iconst_2
     439: anewarray     #72                 // class org/apache/hadoop/hbase/client/Table
     442: dup
     443: iconst_0
     444: aload         4
     446: aastore
     447: dup
     448: iconst_1
     449: aload         5
     451: aastore
     452: invokespecial #74                 // Method deleteAndWait:([BLorg/apache/hadoop/hbase/client/Table;[Lorg/apache/hadoop/hbase/client/Table;)V
     455: aload_0
     456: getstatic     #71                 // Field row:[B
     459: iconst_1
     460: iconst_1
     461: anewarray     #72                 // class org/apache/hadoop/hbase/client/Table
     464: dup
     465: iconst_0
     466: aload         4
     468: aastore
     469: invokespecial #75                 // Method checkRow:([BI[Lorg/apache/hadoop/hbase/client/Table;)V
     472: aload_0
     473: getstatic     #71                 // Field row:[B
     476: iconst_1
     477: aload         5
     479: invokespecial #86                 // Method checkWithWait:([BILorg/apache/hadoop/hbase/client/Table;)V
     482: aload_0
     483: getstatic     #71                 // Field row:[B
     486: aload_3
     487: iconst_2
     488: anewarray     #72                 // class org/apache/hadoop/hbase/client/Table
     491: dup
     492: iconst_0
     493: aload         4
     495: aastore
     496: dup
     497: iconst_1
     498: aload         5
     500: aastore
     501: invokespecial #74                 // Method deleteAndWait:([BLorg/apache/hadoop/hbase/client/Table;[Lorg/apache/hadoop/hbase/client/Table;)V
     504: aload_0
     505: getstatic     #79                 // Field row3:[B
     508: aload_3
     509: iconst_2
     510: anewarray     #72                 // class org/apache/hadoop/hbase/client/Table
     513: dup
     514: iconst_0
     515: aload         4
     517: aastore
     518: dup
     519: iconst_1
     520: aload         5
     522: aastore
     523: invokespecial #74                 // Method deleteAndWait:([BLorg/apache/hadoop/hbase/client/Table;[Lorg/apache/hadoop/hbase/client/Table;)V
     526: getstatic     #43                 // Field utility3:Lorg/apache/hadoop/hbase/HBaseTestingUtility;
     529: invokevirtual #87                 // Method org/apache/hadoop/hbase/HBaseTestingUtility.shutdownMiniCluster:()V
     532: getstatic     #41                 // Field utility2:Lorg/apache/hadoop/hbase/HBaseTestingUtility;
     535: invokevirtual #87                 // Method org/apache/hadoop/hbase/HBaseTestingUtility.shutdownMiniCluster:()V
     538: getstatic     #28                 // Field utility1:Lorg/apache/hadoop/hbase/HBaseTestingUtility;
     541: invokevirtual #87                 // Method org/apache/hadoop/hbase/HBaseTestingUtility.shutdownMiniCluster:()V
     544: return

  static {};
    Code:
       0: ldc           #126                // class org/apache/hadoop/hbase/replication/TestMultiSlaveReplication
       2: invokestatic  #149                // Method org/apache/hadoop/hbase/HBaseClassTestRule.forClass:(Ljava/lang/Class;)Lorg/apache/hadoop/hbase/HBaseClassTestRule;
       5: putstatic     #150                // Field CLASS_RULE:Lorg/apache/hadoop/hbase/HBaseClassTestRule;
       8: ldc           #126                // class org/apache/hadoop/hbase/replication/TestMultiSlaveReplication
      10: invokestatic  #151                // Method org/slf4j/LoggerFactory.getLogger:(Ljava/lang/Class;)Lorg/slf4j/Logger;
      13: putstatic     #55                 // Field LOG:Lorg/slf4j/Logger;
      16: ldc           #152                // String test
      18: invokestatic  #153                // Method org/apache/hadoop/hbase/TableName.valueOf:(Ljava/lang/String;)Lorg/apache/hadoop/hbase/TableName;
      21: putstatic     #46                 // Field tableName:Lorg/apache/hadoop/hbase/TableName;
      24: ldc           #154                // String f
      26: invokestatic  #155                // Method org/apache/hadoop/hbase/util/Bytes.toBytes:(Ljava/lang/String;)[B
      29: putstatic     #50                 // Field famName:[B
      32: ldc           #156                // String row
      34: invokestatic  #155                // Method org/apache/hadoop/hbase/util/Bytes.toBytes:(Ljava/lang/String;)[B
      37: putstatic     #71                 // Field row:[B
      40: ldc           #157                // String row1
      42: invokestatic  #155                // Method org/apache/hadoop/hbase/util/Bytes.toBytes:(Ljava/lang/String;)[B
      45: putstatic     #81                 // Field row1:[B
      48: ldc           #158                // String row2
      50: invokestatic  #155                // Method org/apache/hadoop/hbase/util/Bytes.toBytes:(Ljava/lang/String;)[B
      53: putstatic     #76                 // Field row2:[B
      56: ldc           #159                // String row3
      58: invokestatic  #155                // Method org/apache/hadoop/hbase/util/Bytes.toBytes:(Ljava/lang/String;)[B
      61: putstatic     #79                 // Field row3:[B
      64: ldc           #160                // String norep
      66: invokestatic  #155                // Method org/apache/hadoop/hbase/util/Bytes.toBytes:(Ljava/lang/String;)[B
      69: putstatic     #54                 // Field noRepfamName:[B
      72: return
}
