Compiled from "TestReplicationSyncUpToolBase.java"
public abstract class org.apache.hadoop.hbase.replication.TestReplicationSyncUpToolBase {
  protected static final org.apache.hadoop.hbase.HBaseTestingUtility UTIL1;

  protected static final org.apache.hadoop.hbase.HBaseTestingUtility UTIL2;

  protected static final org.apache.hadoop.hbase.TableName TN1;

  protected static final org.apache.hadoop.hbase.TableName TN2;

  protected static final byte[] FAMILY;

  protected static final byte[] QUALIFIER;

  protected static final byte[] NO_REP_FAMILY;

  protected org.apache.hadoop.hbase.client.TableDescriptor t1SyncupSource;

  protected org.apache.hadoop.hbase.client.TableDescriptor t1SyncupTarget;

  protected org.apache.hadoop.hbase.client.TableDescriptor t2SyncupSource;

  protected org.apache.hadoop.hbase.client.TableDescriptor t2SyncupTarget;

  protected org.apache.hadoop.hbase.client.Connection conn1;

  protected org.apache.hadoop.hbase.client.Connection conn2;

  protected org.apache.hadoop.hbase.client.Table ht1Source;

  protected org.apache.hadoop.hbase.client.Table ht2Source;

  protected org.apache.hadoop.hbase.client.Table ht1TargetAtPeer1;

  protected org.apache.hadoop.hbase.client.Table ht2TargetAtPeer1;

  public org.apache.hadoop.hbase.replication.TestReplicationSyncUpToolBase();
    Code:
       0: aload_0
       1: invokespecial #2                  // Method java/lang/Object."<init>":()V
       4: return

  protected void customizeClusterConf(org.apache.hadoop.conf.Configuration);
    Code:
       0: return

  public void setUp() throws java.lang.Exception;
    Code:
       0: aload_0
       1: getstatic     #3                  // Field UTIL1:Lorg/apache/hadoop/hbase/HBaseTestingUtility;
       4: invokevirtual #4                  // Method org/apache/hadoop/hbase/HBaseTestingUtility.getConfiguration:()Lorg/apache/hadoop/conf/Configuration;
       7: invokevirtual #5                  // Method customizeClusterConf:(Lorg/apache/hadoop/conf/Configuration;)V
      10: aload_0
      11: getstatic     #6                  // Field UTIL2:Lorg/apache/hadoop/hbase/HBaseTestingUtility;
      14: invokevirtual #4                  // Method org/apache/hadoop/hbase/HBaseTestingUtility.getConfiguration:()Lorg/apache/hadoop/conf/Configuration;
      17: invokevirtual #5                  // Method customizeClusterConf:(Lorg/apache/hadoop/conf/Configuration;)V
      20: getstatic     #3                  // Field UTIL1:Lorg/apache/hadoop/hbase/HBaseTestingUtility;
      23: getstatic     #6                  // Field UTIL2:Lorg/apache/hadoop/hbase/HBaseTestingUtility;
      26: invokestatic  #7                  // Method org/apache/hadoop/hbase/replication/TestReplicationBase.configureClusters:(Lorg/apache/hadoop/hbase/HBaseTestingUtility;Lorg/apache/hadoop/hbase/HBaseTestingUtility;)V
      29: getstatic     #3                  // Field UTIL1:Lorg/apache/hadoop/hbase/HBaseTestingUtility;
      32: invokevirtual #8                  // Method org/apache/hadoop/hbase/HBaseTestingUtility.startMiniZKCluster:()Lorg/apache/hadoop/hbase/zookeeper/MiniZooKeeperCluster;
      35: pop
      36: getstatic     #6                  // Field UTIL2:Lorg/apache/hadoop/hbase/HBaseTestingUtility;
      39: getstatic     #3                  // Field UTIL1:Lorg/apache/hadoop/hbase/HBaseTestingUtility;
      42: invokevirtual #9                  // Method org/apache/hadoop/hbase/HBaseTestingUtility.getZkCluster:()Lorg/apache/hadoop/hbase/zookeeper/MiniZooKeeperCluster;
      45: invokevirtual #10                 // Method org/apache/hadoop/hbase/HBaseTestingUtility.setZkCluster:(Lorg/apache/hadoop/hbase/zookeeper/MiniZooKeeperCluster;)V
      48: getstatic     #3                  // Field UTIL1:Lorg/apache/hadoop/hbase/HBaseTestingUtility;
      51: iconst_2
      52: invokevirtual #11                 // Method org/apache/hadoop/hbase/HBaseTestingUtility.startMiniCluster:(I)Lorg/apache/hadoop/hbase/MiniHBaseCluster;
      55: pop
      56: getstatic     #6                  // Field UTIL2:Lorg/apache/hadoop/hbase/HBaseTestingUtility;
      59: iconst_4
      60: invokevirtual #11                 // Method org/apache/hadoop/hbase/HBaseTestingUtility.startMiniCluster:(I)Lorg/apache/hadoop/hbase/MiniHBaseCluster;
      63: pop
      64: aload_0
      65: getstatic     #12                 // Field TN1:Lorg/apache/hadoop/hbase/TableName;
      68: invokestatic  #13                 // Method org/apache/hadoop/hbase/client/TableDescriptorBuilder.newBuilder:(Lorg/apache/hadoop/hbase/TableName;)Lorg/apache/hadoop/hbase/client/TableDescriptorBuilder;
      71: getstatic     #14                 // Field FAMILY:[B
      74: invokestatic  #15                 // Method org/apache/hadoop/hbase/client/ColumnFamilyDescriptorBuilder.newBuilder:([B)Lorg/apache/hadoop/hbase/client/ColumnFamilyDescriptorBuilder;
      77: iconst_1
      78: invokevirtual #16                 // Method org/apache/hadoop/hbase/client/ColumnFamilyDescriptorBuilder.setScope:(I)Lorg/apache/hadoop/hbase/client/ColumnFamilyDescriptorBuilder;
      81: invokevirtual #17                 // Method org/apache/hadoop/hbase/client/ColumnFamilyDescriptorBuilder.build:()Lorg/apache/hadoop/hbase/client/ColumnFamilyDescriptor;
      84: invokevirtual #18                 // Method org/apache/hadoop/hbase/client/TableDescriptorBuilder.setColumnFamily:(Lorg/apache/hadoop/hbase/client/ColumnFamilyDescriptor;)Lorg/apache/hadoop/hbase/client/TableDescriptorBuilder;
      87: getstatic     #19                 // Field NO_REP_FAMILY:[B
      90: invokestatic  #20                 // Method org/apache/hadoop/hbase/client/ColumnFamilyDescriptorBuilder.of:([B)Lorg/apache/hadoop/hbase/client/ColumnFamilyDescriptor;
      93: invokevirtual #18                 // Method org/apache/hadoop/hbase/client/TableDescriptorBuilder.setColumnFamily:(Lorg/apache/hadoop/hbase/client/ColumnFamilyDescriptor;)Lorg/apache/hadoop/hbase/client/TableDescriptorBuilder;
      96: invokevirtual #21                 // Method org/apache/hadoop/hbase/client/TableDescriptorBuilder.build:()Lorg/apache/hadoop/hbase/client/TableDescriptor;
      99: putfield      #22                 // Field t1SyncupSource:Lorg/apache/hadoop/hbase/client/TableDescriptor;
     102: aload_0
     103: getstatic     #12                 // Field TN1:Lorg/apache/hadoop/hbase/TableName;
     106: invokestatic  #13                 // Method org/apache/hadoop/hbase/client/TableDescriptorBuilder.newBuilder:(Lorg/apache/hadoop/hbase/TableName;)Lorg/apache/hadoop/hbase/client/TableDescriptorBuilder;
     109: getstatic     #14                 // Field FAMILY:[B
     112: invokestatic  #20                 // Method org/apache/hadoop/hbase/client/ColumnFamilyDescriptorBuilder.of:([B)Lorg/apache/hadoop/hbase/client/ColumnFamilyDescriptor;
     115: invokevirtual #18                 // Method org/apache/hadoop/hbase/client/TableDescriptorBuilder.setColumnFamily:(Lorg/apache/hadoop/hbase/client/ColumnFamilyDescriptor;)Lorg/apache/hadoop/hbase/client/TableDescriptorBuilder;
     118: getstatic     #19                 // Field NO_REP_FAMILY:[B
     121: invokestatic  #20                 // Method org/apache/hadoop/hbase/client/ColumnFamilyDescriptorBuilder.of:([B)Lorg/apache/hadoop/hbase/client/ColumnFamilyDescriptor;
     124: invokevirtual #18                 // Method org/apache/hadoop/hbase/client/TableDescriptorBuilder.setColumnFamily:(Lorg/apache/hadoop/hbase/client/ColumnFamilyDescriptor;)Lorg/apache/hadoop/hbase/client/TableDescriptorBuilder;
     127: invokevirtual #21                 // Method org/apache/hadoop/hbase/client/TableDescriptorBuilder.build:()Lorg/apache/hadoop/hbase/client/TableDescriptor;
     130: putfield      #23                 // Field t1SyncupTarget:Lorg/apache/hadoop/hbase/client/TableDescriptor;
     133: aload_0
     134: getstatic     #24                 // Field TN2:Lorg/apache/hadoop/hbase/TableName;
     137: invokestatic  #13                 // Method org/apache/hadoop/hbase/client/TableDescriptorBuilder.newBuilder:(Lorg/apache/hadoop/hbase/TableName;)Lorg/apache/hadoop/hbase/client/TableDescriptorBuilder;
     140: getstatic     #14                 // Field FAMILY:[B
     143: invokestatic  #15                 // Method org/apache/hadoop/hbase/client/ColumnFamilyDescriptorBuilder.newBuilder:([B)Lorg/apache/hadoop/hbase/client/ColumnFamilyDescriptorBuilder;
     146: iconst_1
     147: invokevirtual #16                 // Method org/apache/hadoop/hbase/client/ColumnFamilyDescriptorBuilder.setScope:(I)Lorg/apache/hadoop/hbase/client/ColumnFamilyDescriptorBuilder;
     150: invokevirtual #17                 // Method org/apache/hadoop/hbase/client/ColumnFamilyDescriptorBuilder.build:()Lorg/apache/hadoop/hbase/client/ColumnFamilyDescriptor;
     153: invokevirtual #18                 // Method org/apache/hadoop/hbase/client/TableDescriptorBuilder.setColumnFamily:(Lorg/apache/hadoop/hbase/client/ColumnFamilyDescriptor;)Lorg/apache/hadoop/hbase/client/TableDescriptorBuilder;
     156: getstatic     #19                 // Field NO_REP_FAMILY:[B
     159: invokestatic  #20                 // Method org/apache/hadoop/hbase/client/ColumnFamilyDescriptorBuilder.of:([B)Lorg/apache/hadoop/hbase/client/ColumnFamilyDescriptor;
     162: invokevirtual #18                 // Method org/apache/hadoop/hbase/client/TableDescriptorBuilder.setColumnFamily:(Lorg/apache/hadoop/hbase/client/ColumnFamilyDescriptor;)Lorg/apache/hadoop/hbase/client/TableDescriptorBuilder;
     165: invokevirtual #21                 // Method org/apache/hadoop/hbase/client/TableDescriptorBuilder.build:()Lorg/apache/hadoop/hbase/client/TableDescriptor;
     168: putfield      #25                 // Field t2SyncupSource:Lorg/apache/hadoop/hbase/client/TableDescriptor;
     171: aload_0
     172: getstatic     #24                 // Field TN2:Lorg/apache/hadoop/hbase/TableName;
     175: invokestatic  #13                 // Method org/apache/hadoop/hbase/client/TableDescriptorBuilder.newBuilder:(Lorg/apache/hadoop/hbase/TableName;)Lorg/apache/hadoop/hbase/client/TableDescriptorBuilder;
     178: getstatic     #14                 // Field FAMILY:[B
     181: invokestatic  #20                 // Method org/apache/hadoop/hbase/client/ColumnFamilyDescriptorBuilder.of:([B)Lorg/apache/hadoop/hbase/client/ColumnFamilyDescriptor;
     184: invokevirtual #18                 // Method org/apache/hadoop/hbase/client/TableDescriptorBuilder.setColumnFamily:(Lorg/apache/hadoop/hbase/client/ColumnFamilyDescriptor;)Lorg/apache/hadoop/hbase/client/TableDescriptorBuilder;
     187: getstatic     #19                 // Field NO_REP_FAMILY:[B
     190: invokestatic  #20                 // Method org/apache/hadoop/hbase/client/ColumnFamilyDescriptorBuilder.of:([B)Lorg/apache/hadoop/hbase/client/ColumnFamilyDescriptor;
     193: invokevirtual #18                 // Method org/apache/hadoop/hbase/client/TableDescriptorBuilder.setColumnFamily:(Lorg/apache/hadoop/hbase/client/ColumnFamilyDescriptor;)Lorg/apache/hadoop/hbase/client/TableDescriptorBuilder;
     196: invokevirtual #21                 // Method org/apache/hadoop/hbase/client/TableDescriptorBuilder.build:()Lorg/apache/hadoop/hbase/client/TableDescriptor;
     199: putfield      #26                 // Field t2SyncupTarget:Lorg/apache/hadoop/hbase/client/TableDescriptor;
     202: return

  public void tearDown() throws java.lang.Exception;
    Code:
       0: aload_0
       1: getfield      #27                 // Field ht1Source:Lorg/apache/hadoop/hbase/client/Table;
       4: iconst_1
       5: invokestatic  #28                 // Method org/apache/hbase/thirdparty/com/google/common/io/Closeables.close:(Ljava/io/Closeable;Z)V
       8: aload_0
       9: getfield      #29                 // Field ht2Source:Lorg/apache/hadoop/hbase/client/Table;
      12: iconst_1
      13: invokestatic  #28                 // Method org/apache/hbase/thirdparty/com/google/common/io/Closeables.close:(Ljava/io/Closeable;Z)V
      16: aload_0
      17: getfield      #30                 // Field ht1TargetAtPeer1:Lorg/apache/hadoop/hbase/client/Table;
      20: iconst_1
      21: invokestatic  #28                 // Method org/apache/hbase/thirdparty/com/google/common/io/Closeables.close:(Ljava/io/Closeable;Z)V
      24: aload_0
      25: getfield      #31                 // Field ht2TargetAtPeer1:Lorg/apache/hadoop/hbase/client/Table;
      28: iconst_1
      29: invokestatic  #28                 // Method org/apache/hbase/thirdparty/com/google/common/io/Closeables.close:(Ljava/io/Closeable;Z)V
      32: aload_0
      33: getfield      #32                 // Field conn1:Lorg/apache/hadoop/hbase/client/Connection;
      36: iconst_1
      37: invokestatic  #28                 // Method org/apache/hbase/thirdparty/com/google/common/io/Closeables.close:(Ljava/io/Closeable;Z)V
      40: aload_0
      41: getfield      #33                 // Field conn2:Lorg/apache/hadoop/hbase/client/Connection;
      44: iconst_1
      45: invokestatic  #28                 // Method org/apache/hbase/thirdparty/com/google/common/io/Closeables.close:(Ljava/io/Closeable;Z)V
      48: getstatic     #6                  // Field UTIL2:Lorg/apache/hadoop/hbase/HBaseTestingUtility;
      51: invokevirtual #34                 // Method org/apache/hadoop/hbase/HBaseTestingUtility.shutdownMiniCluster:()V
      54: getstatic     #3                  // Field UTIL1:Lorg/apache/hadoop/hbase/HBaseTestingUtility;
      57: invokevirtual #34                 // Method org/apache/hadoop/hbase/HBaseTestingUtility.shutdownMiniCluster:()V
      60: return

  protected final void setupReplication() throws java.lang.Exception;
    Code:
       0: getstatic     #3                  // Field UTIL1:Lorg/apache/hadoop/hbase/HBaseTestingUtility;
       3: invokevirtual #35                 // Method org/apache/hadoop/hbase/HBaseTestingUtility.getAdmin:()Lorg/apache/hadoop/hbase/client/Admin;
       6: astore_1
       7: aload_1
       8: aload_0
       9: getfield      #22                 // Field t1SyncupSource:Lorg/apache/hadoop/hbase/client/TableDescriptor;
      12: invokeinterface #36,  2           // InterfaceMethod org/apache/hadoop/hbase/client/Admin.createTable:(Lorg/apache/hadoop/hbase/client/TableDescriptor;)V
      17: aload_1
      18: aload_0
      19: getfield      #25                 // Field t2SyncupSource:Lorg/apache/hadoop/hbase/client/TableDescriptor;
      22: invokeinterface #36,  2           // InterfaceMethod org/apache/hadoop/hbase/client/Admin.createTable:(Lorg/apache/hadoop/hbase/client/TableDescriptor;)V
      27: getstatic     #6                  // Field UTIL2:Lorg/apache/hadoop/hbase/HBaseTestingUtility;
      30: invokevirtual #35                 // Method org/apache/hadoop/hbase/HBaseTestingUtility.getAdmin:()Lorg/apache/hadoop/hbase/client/Admin;
      33: astore_2
      34: aload_2
      35: aload_0
      36: getfield      #23                 // Field t1SyncupTarget:Lorg/apache/hadoop/hbase/client/TableDescriptor;
      39: invokeinterface #36,  2           // InterfaceMethod org/apache/hadoop/hbase/client/Admin.createTable:(Lorg/apache/hadoop/hbase/client/TableDescriptor;)V
      44: aload_2
      45: aload_0
      46: getfield      #26                 // Field t2SyncupTarget:Lorg/apache/hadoop/hbase/client/TableDescriptor;
      49: invokeinterface #36,  2           // InterfaceMethod org/apache/hadoop/hbase/client/Admin.createTable:(Lorg/apache/hadoop/hbase/client/TableDescriptor;)V
      54: getstatic     #3                  // Field UTIL1:Lorg/apache/hadoop/hbase/HBaseTestingUtility;
      57: invokevirtual #4                  // Method org/apache/hadoop/hbase/HBaseTestingUtility.getConfiguration:()Lorg/apache/hadoop/conf/Configuration;
      60: invokestatic  #37                 // Method org/apache/hadoop/hbase/client/ConnectionFactory.createConnection:(Lorg/apache/hadoop/conf/Configuration;)Lorg/apache/hadoop/hbase/client/Connection;
      63: astore_3
      64: aload_0
      65: aload_3
      66: getstatic     #12                 // Field TN1:Lorg/apache/hadoop/hbase/TableName;
      69: invokeinterface #38,  2           // InterfaceMethod org/apache/hadoop/hbase/client/Connection.getTable:(Lorg/apache/hadoop/hbase/TableName;)Lorg/apache/hadoop/hbase/client/Table;
      74: putfield      #27                 // Field ht1Source:Lorg/apache/hadoop/hbase/client/Table;
      77: aload_0
      78: aload_3
      79: getstatic     #24                 // Field TN2:Lorg/apache/hadoop/hbase/TableName;
      82: invokeinterface #38,  2           // InterfaceMethod org/apache/hadoop/hbase/client/Connection.getTable:(Lorg/apache/hadoop/hbase/TableName;)Lorg/apache/hadoop/hbase/client/Table;
      87: putfield      #29                 // Field ht2Source:Lorg/apache/hadoop/hbase/client/Table;
      90: getstatic     #6                  // Field UTIL2:Lorg/apache/hadoop/hbase/HBaseTestingUtility;
      93: invokevirtual #4                  // Method org/apache/hadoop/hbase/HBaseTestingUtility.getConfiguration:()Lorg/apache/hadoop/conf/Configuration;
      96: invokestatic  #37                 // Method org/apache/hadoop/hbase/client/ConnectionFactory.createConnection:(Lorg/apache/hadoop/conf/Configuration;)Lorg/apache/hadoop/hbase/client/Connection;
      99: astore        4
     101: aload_0
     102: aload         4
     104: getstatic     #12                 // Field TN1:Lorg/apache/hadoop/hbase/TableName;
     107: invokeinterface #38,  2           // InterfaceMethod org/apache/hadoop/hbase/client/Connection.getTable:(Lorg/apache/hadoop/hbase/TableName;)Lorg/apache/hadoop/hbase/client/Table;
     112: putfield      #30                 // Field ht1TargetAtPeer1:Lorg/apache/hadoop/hbase/client/Table;
     115: aload_0
     116: aload         4
     118: getstatic     #24                 // Field TN2:Lorg/apache/hadoop/hbase/TableName;
     121: invokeinterface #38,  2           // InterfaceMethod org/apache/hadoop/hbase/client/Connection.getTable:(Lorg/apache/hadoop/hbase/TableName;)Lorg/apache/hadoop/hbase/client/Table;
     126: putfield      #31                 // Field ht2TargetAtPeer1:Lorg/apache/hadoop/hbase/client/Table;
     129: invokestatic  #39                 // Method org/apache/hadoop/hbase/replication/ReplicationPeerConfig.newBuilder:()Lorg/apache/hadoop/hbase/replication/ReplicationPeerConfigBuilder;
     132: getstatic     #6                  // Field UTIL2:Lorg/apache/hadoop/hbase/HBaseTestingUtility;
     135: invokevirtual #40                 // Method org/apache/hadoop/hbase/HBaseTestingUtility.getClusterKey:()Ljava/lang/String;
     138: invokeinterface #41,  2           // InterfaceMethod org/apache/hadoop/hbase/replication/ReplicationPeerConfigBuilder.setClusterKey:(Ljava/lang/String;)Lorg/apache/hadoop/hbase/replication/ReplicationPeerConfigBuilder;
     143: invokeinterface #42,  1           // InterfaceMethod org/apache/hadoop/hbase/replication/ReplicationPeerConfigBuilder.build:()Lorg/apache/hadoop/hbase/replication/ReplicationPeerConfig;
     148: astore        5
     150: aload_1
     151: ldc           #43                 // String 1
     153: aload         5
     155: invokeinterface #44,  3           // InterfaceMethod org/apache/hadoop/hbase/client/Admin.addReplicationPeer:(Ljava/lang/String;Lorg/apache/hadoop/hbase/replication/ReplicationPeerConfig;)V
     160: return

  protected final void syncUp(org.apache.hadoop.hbase.HBaseTestingUtility) throws java.lang.Exception;
    Code:
       0: aload_1
       1: invokevirtual #4                  // Method org/apache/hadoop/hbase/HBaseTestingUtility.getConfiguration:()Lorg/apache/hadoop/conf/Configuration;
       4: new           #45                 // class org/apache/hadoop/hbase/replication/regionserver/ReplicationSyncUp
       7: dup
       8: invokespecial #46                 // Method org/apache/hadoop/hbase/replication/regionserver/ReplicationSyncUp."<init>":()V
      11: iconst_0
      12: anewarray     #47                 // class java/lang/String
      15: invokestatic  #48                 // Method org/apache/hadoop/util/ToolRunner.run:(Lorg/apache/hadoop/conf/Configuration;Lorg/apache/hadoop/util/Tool;[Ljava/lang/String;)I
      18: pop
      19: return

  static {};
    Code:
       0: new           #49                 // class org/apache/hadoop/hbase/HBaseTestingUtility
       3: dup
       4: invokespecial #50                 // Method org/apache/hadoop/hbase/HBaseTestingUtility."<init>":()V
       7: putstatic     #3                  // Field UTIL1:Lorg/apache/hadoop/hbase/HBaseTestingUtility;
      10: new           #49                 // class org/apache/hadoop/hbase/HBaseTestingUtility
      13: dup
      14: invokespecial #50                 // Method org/apache/hadoop/hbase/HBaseTestingUtility."<init>":()V
      17: putstatic     #6                  // Field UTIL2:Lorg/apache/hadoop/hbase/HBaseTestingUtility;
      20: ldc           #51                 // String t1_syncup
      22: invokestatic  #52                 // Method org/apache/hadoop/hbase/TableName.valueOf:(Ljava/lang/String;)Lorg/apache/hadoop/hbase/TableName;
      25: putstatic     #12                 // Field TN1:Lorg/apache/hadoop/hbase/TableName;
      28: ldc           #53                 // String t2_syncup
      30: invokestatic  #52                 // Method org/apache/hadoop/hbase/TableName.valueOf:(Ljava/lang/String;)Lorg/apache/hadoop/hbase/TableName;
      33: putstatic     #24                 // Field TN2:Lorg/apache/hadoop/hbase/TableName;
      36: ldc           #54                 // String cf1
      38: invokestatic  #55                 // Method org/apache/hadoop/hbase/util/Bytes.toBytes:(Ljava/lang/String;)[B
      41: putstatic     #14                 // Field FAMILY:[B
      44: ldc           #56                 // String q1
      46: invokestatic  #55                 // Method org/apache/hadoop/hbase/util/Bytes.toBytes:(Ljava/lang/String;)[B
      49: putstatic     #57                 // Field QUALIFIER:[B
      52: ldc           #58                 // String norep
      54: invokestatic  #55                 // Method org/apache/hadoop/hbase/util/Bytes.toBytes:(Ljava/lang/String;)[B
      57: putstatic     #19                 // Field NO_REP_FAMILY:[B
      60: return
}
