Compiled from "TestLocalAsyncOutput.java"
public class org.apache.hadoop.hbase.io.asyncfs.TestLocalAsyncOutput {
  public static final org.apache.hadoop.hbase.HBaseClassTestRule CLASS_RULE;

  public org.apache.hadoop.hbase.io.asyncfs.TestLocalAsyncOutput();
    Code:
       0: aload_0
       1: invokespecial #1                  // Method java/lang/Object."<init>":()V
       4: return

  public static void tearDownAfterClass() throws java.io.IOException;
    Code:
       0: getstatic     #2                  // Field TEST_UTIL:Lorg/apache/hadoop/hbase/HBaseTestingUtility;
       3: invokevirtual #3                  // Method org/apache/hadoop/hbase/HBaseTestingUtility.cleanupTestDir:()Z
       6: pop
       7: getstatic     #4                  // Field GROUP:Lorg/apache/hbase/thirdparty/io/netty/channel/EventLoopGroup;
      10: invokeinterface #5,  1            // InterfaceMethod org/apache/hbase/thirdparty/io/netty/channel/EventLoopGroup.shutdownGracefully:()Lorg/apache/hbase/thirdparty/io/netty/util/concurrent/Future;
      15: pop
      16: return

  public void test() throws java.io.IOException, java.lang.InterruptedException, java.util.concurrent.ExecutionException, org.apache.hadoop.hbase.util.CommonFSUtils$StreamLacksCapabilityException;
    Code:
       0: new           #6                  // class org/apache/hadoop/fs/Path
       3: dup
       4: getstatic     #2                  // Field TEST_UTIL:Lorg/apache/hadoop/hbase/HBaseTestingUtility;
       7: invokevirtual #7                  // Method org/apache/hadoop/hbase/HBaseTestingUtility.getDataTestDir:()Lorg/apache/hadoop/fs/Path;
      10: ldc           #8                  // String test
      12: invokespecial #9                  // Method org/apache/hadoop/fs/Path."<init>":(Lorg/apache/hadoop/fs/Path;Ljava/lang/String;)V
      15: astore_1
      16: getstatic     #2                  // Field TEST_UTIL:Lorg/apache/hadoop/hbase/HBaseTestingUtility;
      19: invokevirtual #10                 // Method org/apache/hadoop/hbase/HBaseTestingUtility.getConfiguration:()Lorg/apache/hadoop/conf/Configuration;
      22: invokestatic  #11                 // Method org/apache/hadoop/fs/FileSystem.getLocal:(Lorg/apache/hadoop/conf/Configuration;)Lorg/apache/hadoop/fs/LocalFileSystem;
      25: astore_2
      26: aload_2
      27: aload_1
      28: iconst_0
      29: iconst_1
      30: aload_2
      31: aload_1
      32: invokevirtual #12                 // Method org/apache/hadoop/fs/FileSystem.getDefaultReplication:(Lorg/apache/hadoop/fs/Path;)S
      35: aload_2
      36: aload_1
      37: invokevirtual #13                 // Method org/apache/hadoop/fs/FileSystem.getDefaultBlockSize:(Lorg/apache/hadoop/fs/Path;)J
      40: getstatic     #4                  // Field GROUP:Lorg/apache/hbase/thirdparty/io/netty/channel/EventLoopGroup;
      43: getstatic     #14                 // Field CHANNEL_CLASS:Ljava/lang/Class;
      46: invokestatic  #15                 // Method org/apache/hadoop/hbase/io/asyncfs/AsyncFSOutputHelper.createOutput:(Lorg/apache/hadoop/fs/FileSystem;Lorg/apache/hadoop/fs/Path;ZZSJLorg/apache/hbase/thirdparty/io/netty/channel/EventLoopGroup;Ljava/lang/Class;)Lorg/apache/hadoop/hbase/io/asyncfs/AsyncFSOutput;
      49: astore_3
      50: aload_2
      51: aload_1
      52: aload_3
      53: invokestatic  #16                 // Method org/apache/hadoop/hbase/io/asyncfs/TestFanOutOneBlockAsyncDFSOutput.writeAndVerify:(Lorg/apache/hadoop/fs/FileSystem;Lorg/apache/hadoop/fs/Path;Lorg/apache/hadoop/hbase/io/asyncfs/AsyncFSOutput;)V
      56: return

  static {};
    Code:
       0: ldc           #17                 // class org/apache/hadoop/hbase/io/asyncfs/TestLocalAsyncOutput
       2: invokestatic  #18                 // Method org/apache/hadoop/hbase/HBaseClassTestRule.forClass:(Ljava/lang/Class;)Lorg/apache/hadoop/hbase/HBaseClassTestRule;
       5: putstatic     #19                 // Field CLASS_RULE:Lorg/apache/hadoop/hbase/HBaseClassTestRule;
       8: new           #20                 // class org/apache/hbase/thirdparty/io/netty/channel/nio/NioEventLoopGroup
      11: dup
      12: invokespecial #21                 // Method org/apache/hbase/thirdparty/io/netty/channel/nio/NioEventLoopGroup."<init>":()V
      15: putstatic     #4                  // Field GROUP:Lorg/apache/hbase/thirdparty/io/netty/channel/EventLoopGroup;
      18: ldc           #22                 // class org/apache/hbase/thirdparty/io/netty/channel/socket/nio/NioSocketChannel
      20: putstatic     #14                 // Field CHANNEL_CLASS:Ljava/lang/Class;
      23: new           #23                 // class org/apache/hadoop/hbase/HBaseTestingUtility
      26: dup
      27: invokespecial #24                 // Method org/apache/hadoop/hbase/HBaseTestingUtility."<init>":()V
      30: putstatic     #2                  // Field TEST_UTIL:Lorg/apache/hadoop/hbase/HBaseTestingUtility;
      33: return
}
