Compiled from "TestCompactionScanQueryMatcher.java"
public class org.apache.hadoop.hbase.regionserver.querymatcher.TestCompactionScanQueryMatcher extends org.apache.hadoop.hbase.regionserver.querymatcher.AbstractTestScanQueryMatcher {
  public static final org.apache.hadoop.hbase.HBaseClassTestRule CLASS_RULE;

  public org.apache.hadoop.hbase.regionserver.querymatcher.TestCompactionScanQueryMatcher();
    Code:
       0: aload_0
       1: invokespecial #1                  // Method org/apache/hadoop/hbase/regionserver/querymatcher/AbstractTestScanQueryMatcher."<init>":()V
       4: return

  public void testMatch_PartialRangeDropDeletes() throws java.lang.Exception;
    Code:
       0: aload_0
       1: aload_0
       2: getfield      #2                  // Field row2:[B
       5: aload_0
       6: getfield      #3                  // Field row3:[B
       9: iconst_4
      10: anewarray     #4                  // class "[B"
      13: dup
      14: iconst_0
      15: aload_0
      16: getfield      #5                  // Field row1:[B
      19: aastore
      20: dup
      21: iconst_1
      22: aload_0
      23: getfield      #2                  // Field row2:[B
      26: aastore
      27: dup
      28: iconst_2
      29: aload_0
      30: getfield      #2                  // Field row2:[B
      33: aastore
      34: dup
      35: iconst_3
      36: aload_0
      37: getfield      #3                  // Field row3:[B
      40: aastore
      41: iconst_4
      42: anewarray     #6                  // class org/apache/hadoop/hbase/regionserver/querymatcher/ScanQueryMatcher$MatchCode
      45: dup
      46: iconst_0
      47: getstatic     #7                  // Field org/apache/hadoop/hbase/regionserver/querymatcher/ScanQueryMatcher$MatchCode.INCLUDE:Lorg/apache/hadoop/hbase/regionserver/querymatcher/ScanQueryMatcher$MatchCode;
      50: aastore
      51: dup
      52: iconst_1
      53: getstatic     #8                  // Field org/apache/hadoop/hbase/regionserver/querymatcher/ScanQueryMatcher$MatchCode.SKIP:Lorg/apache/hadoop/hbase/regionserver/querymatcher/ScanQueryMatcher$MatchCode;
      56: aastore
      57: dup
      58: iconst_2
      59: getstatic     #8                  // Field org/apache/hadoop/hbase/regionserver/querymatcher/ScanQueryMatcher$MatchCode.SKIP:Lorg/apache/hadoop/hbase/regionserver/querymatcher/ScanQueryMatcher$MatchCode;
      62: aastore
      63: dup
      64: iconst_3
      65: getstatic     #7                  // Field org/apache/hadoop/hbase/regionserver/querymatcher/ScanQueryMatcher$MatchCode.INCLUDE:Lorg/apache/hadoop/hbase/regionserver/querymatcher/ScanQueryMatcher$MatchCode;
      68: aastore
      69: invokespecial #9                  // Method testDropDeletes:([B[B[[B[Lorg/apache/hadoop/hbase/regionserver/querymatcher/ScanQueryMatcher$MatchCode;)V
      72: aload_0
      73: aload_0
      74: getfield      #2                  // Field row2:[B
      77: aload_0
      78: getfield      #3                  // Field row3:[B
      81: iconst_3
      82: anewarray     #4                  // class "[B"
      85: dup
      86: iconst_0
      87: aload_0
      88: getfield      #5                  // Field row1:[B
      91: aastore
      92: dup
      93: iconst_1
      94: aload_0
      95: getfield      #5                  // Field row1:[B
      98: aastore
      99: dup
     100: iconst_2
     101: aload_0
     102: getfield      #2                  // Field row2:[B
     105: aastore
     106: iconst_3
     107: anewarray     #6                  // class org/apache/hadoop/hbase/regionserver/querymatcher/ScanQueryMatcher$MatchCode
     110: dup
     111: iconst_0
     112: getstatic     #7                  // Field org/apache/hadoop/hbase/regionserver/querymatcher/ScanQueryMatcher$MatchCode.INCLUDE:Lorg/apache/hadoop/hbase/regionserver/querymatcher/ScanQueryMatcher$MatchCode;
     115: aastore
     116: dup
     117: iconst_1
     118: getstatic     #7                  // Field org/apache/hadoop/hbase/regionserver/querymatcher/ScanQueryMatcher$MatchCode.INCLUDE:Lorg/apache/hadoop/hbase/regionserver/querymatcher/ScanQueryMatcher$MatchCode;
     121: aastore
     122: dup
     123: iconst_2
     124: getstatic     #8                  // Field org/apache/hadoop/hbase/regionserver/querymatcher/ScanQueryMatcher$MatchCode.SKIP:Lorg/apache/hadoop/hbase/regionserver/querymatcher/ScanQueryMatcher$MatchCode;
     127: aastore
     128: invokespecial #9                  // Method testDropDeletes:([B[B[[B[Lorg/apache/hadoop/hbase/regionserver/querymatcher/ScanQueryMatcher$MatchCode;)V
     131: aload_0
     132: aload_0
     133: getfield      #2                  // Field row2:[B
     136: aload_0
     137: getfield      #3                  // Field row3:[B
     140: iconst_3
     141: anewarray     #4                  // class "[B"
     144: dup
     145: iconst_0
     146: aload_0
     147: getfield      #2                  // Field row2:[B
     150: aastore
     151: dup
     152: iconst_1
     153: aload_0
     154: getfield      #3                  // Field row3:[B
     157: aastore
     158: dup
     159: iconst_2
     160: aload_0
     161: getfield      #3                  // Field row3:[B
     164: aastore
     165: iconst_3
     166: anewarray     #6                  // class org/apache/hadoop/hbase/regionserver/querymatcher/ScanQueryMatcher$MatchCode
     169: dup
     170: iconst_0
     171: getstatic     #8                  // Field org/apache/hadoop/hbase/regionserver/querymatcher/ScanQueryMatcher$MatchCode.SKIP:Lorg/apache/hadoop/hbase/regionserver/querymatcher/ScanQueryMatcher$MatchCode;
     174: aastore
     175: dup
     176: iconst_1
     177: getstatic     #7                  // Field org/apache/hadoop/hbase/regionserver/querymatcher/ScanQueryMatcher$MatchCode.INCLUDE:Lorg/apache/hadoop/hbase/regionserver/querymatcher/ScanQueryMatcher$MatchCode;
     180: aastore
     181: dup
     182: iconst_2
     183: getstatic     #7                  // Field org/apache/hadoop/hbase/regionserver/querymatcher/ScanQueryMatcher$MatchCode.INCLUDE:Lorg/apache/hadoop/hbase/regionserver/querymatcher/ScanQueryMatcher$MatchCode;
     186: aastore
     187: invokespecial #9                  // Method testDropDeletes:([B[B[[B[Lorg/apache/hadoop/hbase/regionserver/querymatcher/ScanQueryMatcher$MatchCode;)V
     190: aload_0
     191: aload_0
     192: getfield      #5                  // Field row1:[B
     195: aload_0
     196: getfield      #3                  // Field row3:[B
     199: iconst_3
     200: anewarray     #4                  // class "[B"
     203: dup
     204: iconst_0
     205: aload_0
     206: getfield      #5                  // Field row1:[B
     209: aastore
     210: dup
     211: iconst_1
     212: aload_0
     213: getfield      #2                  // Field row2:[B
     216: aastore
     217: dup
     218: iconst_2
     219: aload_0
     220: getfield      #3                  // Field row3:[B
     223: aastore
     224: iconst_3
     225: anewarray     #6                  // class org/apache/hadoop/hbase/regionserver/querymatcher/ScanQueryMatcher$MatchCode
     228: dup
     229: iconst_0
     230: getstatic     #8                  // Field org/apache/hadoop/hbase/regionserver/querymatcher/ScanQueryMatcher$MatchCode.SKIP:Lorg/apache/hadoop/hbase/regionserver/querymatcher/ScanQueryMatcher$MatchCode;
     233: aastore
     234: dup
     235: iconst_1
     236: getstatic     #8                  // Field org/apache/hadoop/hbase/regionserver/querymatcher/ScanQueryMatcher$MatchCode.SKIP:Lorg/apache/hadoop/hbase/regionserver/querymatcher/ScanQueryMatcher$MatchCode;
     239: aastore
     240: dup
     241: iconst_2
     242: getstatic     #7                  // Field org/apache/hadoop/hbase/regionserver/querymatcher/ScanQueryMatcher$MatchCode.INCLUDE:Lorg/apache/hadoop/hbase/regionserver/querymatcher/ScanQueryMatcher$MatchCode;
     245: aastore
     246: invokespecial #9                  // Method testDropDeletes:([B[B[[B[Lorg/apache/hadoop/hbase/regionserver/querymatcher/ScanQueryMatcher$MatchCode;)V
     249: aload_0
     250: getstatic     #10                 // Field org/apache/hadoop/hbase/HConstants.EMPTY_START_ROW:[B
     253: aload_0
     254: getfield      #3                  // Field row3:[B
     257: iconst_3
     258: anewarray     #4                  // class "[B"
     261: dup
     262: iconst_0
     263: aload_0
     264: getfield      #5                  // Field row1:[B
     267: aastore
     268: dup
     269: iconst_1
     270: aload_0
     271: getfield      #2                  // Field row2:[B
     274: aastore
     275: dup
     276: iconst_2
     277: aload_0
     278: getfield      #3                  // Field row3:[B
     281: aastore
     282: iconst_3
     283: anewarray     #6                  // class org/apache/hadoop/hbase/regionserver/querymatcher/ScanQueryMatcher$MatchCode
     286: dup
     287: iconst_0
     288: getstatic     #8                  // Field org/apache/hadoop/hbase/regionserver/querymatcher/ScanQueryMatcher$MatchCode.SKIP:Lorg/apache/hadoop/hbase/regionserver/querymatcher/ScanQueryMatcher$MatchCode;
     291: aastore
     292: dup
     293: iconst_1
     294: getstatic     #8                  // Field org/apache/hadoop/hbase/regionserver/querymatcher/ScanQueryMatcher$MatchCode.SKIP:Lorg/apache/hadoop/hbase/regionserver/querymatcher/ScanQueryMatcher$MatchCode;
     297: aastore
     298: dup
     299: iconst_2
     300: getstatic     #7                  // Field org/apache/hadoop/hbase/regionserver/querymatcher/ScanQueryMatcher$MatchCode.INCLUDE:Lorg/apache/hadoop/hbase/regionserver/querymatcher/ScanQueryMatcher$MatchCode;
     303: aastore
     304: invokespecial #9                  // Method testDropDeletes:([B[B[[B[Lorg/apache/hadoop/hbase/regionserver/querymatcher/ScanQueryMatcher$MatchCode;)V
     307: aload_0
     308: aload_0
     309: getfield      #2                  // Field row2:[B
     312: getstatic     #11                 // Field org/apache/hadoop/hbase/HConstants.EMPTY_END_ROW:[B
     315: iconst_3
     316: anewarray     #4                  // class "[B"
     319: dup
     320: iconst_0
     321: aload_0
     322: getfield      #5                  // Field row1:[B
     325: aastore
     326: dup
     327: iconst_1
     328: aload_0
     329: getfield      #2                  // Field row2:[B
     332: aastore
     333: dup
     334: iconst_2
     335: aload_0
     336: getfield      #3                  // Field row3:[B
     339: aastore
     340: iconst_3
     341: anewarray     #6                  // class org/apache/hadoop/hbase/regionserver/querymatcher/ScanQueryMatcher$MatchCode
     344: dup
     345: iconst_0
     346: getstatic     #7                  // Field org/apache/hadoop/hbase/regionserver/querymatcher/ScanQueryMatcher$MatchCode.INCLUDE:Lorg/apache/hadoop/hbase/regionserver/querymatcher/ScanQueryMatcher$MatchCode;
     349: aastore
     350: dup
     351: iconst_1
     352: getstatic     #8                  // Field org/apache/hadoop/hbase/regionserver/querymatcher/ScanQueryMatcher$MatchCode.SKIP:Lorg/apache/hadoop/hbase/regionserver/querymatcher/ScanQueryMatcher$MatchCode;
     355: aastore
     356: dup
     357: iconst_2
     358: getstatic     #8                  // Field org/apache/hadoop/hbase/regionserver/querymatcher/ScanQueryMatcher$MatchCode.SKIP:Lorg/apache/hadoop/hbase/regionserver/querymatcher/ScanQueryMatcher$MatchCode;
     361: aastore
     362: invokespecial #9                  // Method testDropDeletes:([B[B[[B[Lorg/apache/hadoop/hbase/regionserver/querymatcher/ScanQueryMatcher$MatchCode;)V
     365: aload_0
     366: getstatic     #10                 // Field org/apache/hadoop/hbase/HConstants.EMPTY_START_ROW:[B
     369: getstatic     #11                 // Field org/apache/hadoop/hbase/HConstants.EMPTY_END_ROW:[B
     372: iconst_4
     373: anewarray     #4                  // class "[B"
     376: dup
     377: iconst_0
     378: aload_0
     379: getfield      #5                  // Field row1:[B
     382: aastore
     383: dup
     384: iconst_1
     385: aload_0
     386: getfield      #2                  // Field row2:[B
     389: aastore
     390: dup
     391: iconst_2
     392: aload_0
     393: getfield      #3                  // Field row3:[B
     396: aastore
     397: dup
     398: iconst_3
     399: aload_0
     400: getfield      #3                  // Field row3:[B
     403: aastore
     404: iconst_4
     405: anewarray     #6                  // class org/apache/hadoop/hbase/regionserver/querymatcher/ScanQueryMatcher$MatchCode
     408: dup
     409: iconst_0
     410: getstatic     #8                  // Field org/apache/hadoop/hbase/regionserver/querymatcher/ScanQueryMatcher$MatchCode.SKIP:Lorg/apache/hadoop/hbase/regionserver/querymatcher/ScanQueryMatcher$MatchCode;
     413: aastore
     414: dup
     415: iconst_1
     416: getstatic     #8                  // Field org/apache/hadoop/hbase/regionserver/querymatcher/ScanQueryMatcher$MatchCode.SKIP:Lorg/apache/hadoop/hbase/regionserver/querymatcher/ScanQueryMatcher$MatchCode;
     419: aastore
     420: dup
     421: iconst_2
     422: getstatic     #8                  // Field org/apache/hadoop/hbase/regionserver/querymatcher/ScanQueryMatcher$MatchCode.SKIP:Lorg/apache/hadoop/hbase/regionserver/querymatcher/ScanQueryMatcher$MatchCode;
     425: aastore
     426: dup
     427: iconst_3
     428: getstatic     #8                  // Field org/apache/hadoop/hbase/regionserver/querymatcher/ScanQueryMatcher$MatchCode.SKIP:Lorg/apache/hadoop/hbase/regionserver/querymatcher/ScanQueryMatcher$MatchCode;
     431: aastore
     432: invokespecial #9                  // Method testDropDeletes:([B[B[[B[Lorg/apache/hadoop/hbase/regionserver/querymatcher/ScanQueryMatcher$MatchCode;)V
     435: aload_0
     436: aload_0
     437: getfield      #2                  // Field row2:[B
     440: aload_0
     441: getfield      #3                  // Field row3:[B
     444: iconst_3
     445: anewarray     #4                  // class "[B"
     448: dup
     449: iconst_0
     450: aload_0
     451: getfield      #5                  // Field row1:[B
     454: aastore
     455: dup
     456: iconst_1
     457: aload_0
     458: getfield      #5                  // Field row1:[B
     461: aastore
     462: dup
     463: iconst_2
     464: aload_0
     465: getfield      #3                  // Field row3:[B
     468: aastore
     469: iconst_3
     470: anewarray     #6                  // class org/apache/hadoop/hbase/regionserver/querymatcher/ScanQueryMatcher$MatchCode
     473: dup
     474: iconst_0
     475: getstatic     #7                  // Field org/apache/hadoop/hbase/regionserver/querymatcher/ScanQueryMatcher$MatchCode.INCLUDE:Lorg/apache/hadoop/hbase/regionserver/querymatcher/ScanQueryMatcher$MatchCode;
     478: aastore
     479: dup
     480: iconst_1
     481: getstatic     #7                  // Field org/apache/hadoop/hbase/regionserver/querymatcher/ScanQueryMatcher$MatchCode.INCLUDE:Lorg/apache/hadoop/hbase/regionserver/querymatcher/ScanQueryMatcher$MatchCode;
     484: aastore
     485: dup
     486: iconst_2
     487: getstatic     #7                  // Field org/apache/hadoop/hbase/regionserver/querymatcher/ScanQueryMatcher$MatchCode.INCLUDE:Lorg/apache/hadoop/hbase/regionserver/querymatcher/ScanQueryMatcher$MatchCode;
     490: aastore
     491: invokespecial #9                  // Method testDropDeletes:([B[B[[B[Lorg/apache/hadoop/hbase/regionserver/querymatcher/ScanQueryMatcher$MatchCode;)V
     494: aload_0
     495: aload_0
     496: getfield      #2                  // Field row2:[B
     499: aload_0
     500: getfield      #3                  // Field row3:[B
     503: iconst_2
     504: anewarray     #4                  // class "[B"
     507: dup
     508: iconst_0
     509: aload_0
     510: getfield      #3                  // Field row3:[B
     513: aastore
     514: dup
     515: iconst_1
     516: aload_0
     517: getfield      #3                  // Field row3:[B
     520: aastore
     521: iconst_2
     522: anewarray     #6                  // class org/apache/hadoop/hbase/regionserver/querymatcher/ScanQueryMatcher$MatchCode
     525: dup
     526: iconst_0
     527: getstatic     #7                  // Field org/apache/hadoop/hbase/regionserver/querymatcher/ScanQueryMatcher$MatchCode.INCLUDE:Lorg/apache/hadoop/hbase/regionserver/querymatcher/ScanQueryMatcher$MatchCode;
     530: aastore
     531: dup
     532: iconst_1
     533: getstatic     #7                  // Field org/apache/hadoop/hbase/regionserver/querymatcher/ScanQueryMatcher$MatchCode.INCLUDE:Lorg/apache/hadoop/hbase/regionserver/querymatcher/ScanQueryMatcher$MatchCode;
     536: aastore
     537: invokespecial #9                  // Method testDropDeletes:([B[B[[B[Lorg/apache/hadoop/hbase/regionserver/querymatcher/ScanQueryMatcher$MatchCode;)V
     540: aload_0
     541: aload_0
     542: getfield      #2                  // Field row2:[B
     545: aload_0
     546: getfield      #3                  // Field row3:[B
     549: iconst_2
     550: anewarray     #4                  // class "[B"
     553: dup
     554: iconst_0
     555: aload_0
     556: getfield      #5                  // Field row1:[B
     559: aastore
     560: dup
     561: iconst_1
     562: aload_0
     563: getfield      #5                  // Field row1:[B
     566: aastore
     567: iconst_2
     568: anewarray     #6                  // class org/apache/hadoop/hbase/regionserver/querymatcher/ScanQueryMatcher$MatchCode
     571: dup
     572: iconst_0
     573: getstatic     #7                  // Field org/apache/hadoop/hbase/regionserver/querymatcher/ScanQueryMatcher$MatchCode.INCLUDE:Lorg/apache/hadoop/hbase/regionserver/querymatcher/ScanQueryMatcher$MatchCode;
     576: aastore
     577: dup
     578: iconst_1
     579: getstatic     #7                  // Field org/apache/hadoop/hbase/regionserver/querymatcher/ScanQueryMatcher$MatchCode.INCLUDE:Lorg/apache/hadoop/hbase/regionserver/querymatcher/ScanQueryMatcher$MatchCode;
     582: aastore
     583: invokespecial #9                  // Method testDropDeletes:([B[B[[B[Lorg/apache/hadoop/hbase/regionserver/querymatcher/ScanQueryMatcher$MatchCode;)V
     586: return

  static {};
    Code:
       0: ldc           #55                 // class org/apache/hadoop/hbase/regionserver/querymatcher/TestCompactionScanQueryMatcher
       2: invokestatic  #56                 // Method org/apache/hadoop/hbase/HBaseClassTestRule.forClass:(Ljava/lang/Class;)Lorg/apache/hadoop/hbase/HBaseClassTestRule;
       5: putstatic     #57                 // Field CLASS_RULE:Lorg/apache/hadoop/hbase/HBaseClassTestRule;
       8: ldc           #55                 // class org/apache/hadoop/hbase/regionserver/querymatcher/TestCompactionScanQueryMatcher
      10: invokestatic  #58                 // Method org/slf4j/LoggerFactory.getLogger:(Ljava/lang/Class;)Lorg/slf4j/Logger;
      13: putstatic     #44                 // Field LOG:Lorg/slf4j/Logger;
      16: return
}
