Compiled from "TestReplicationWALEntryFilters.java"
public class org.apache.hadoop.hbase.replication.TestReplicationWALEntryFilters {
  public static final org.apache.hadoop.hbase.HBaseClassTestRule CLASS_RULE;

  static byte[] a;

  static byte[] b;

  static byte[] c;

  static byte[] d;

  org.apache.hadoop.hbase.replication.WALEntryFilter nullFilter;

  org.apache.hadoop.hbase.replication.WALEntryFilter passFilter;

  public org.apache.hadoop.hbase.replication.TestReplicationWALEntryFilters();
    Code:
       0: aload_0
       1: invokespecial #1                  // Method java/lang/Object."<init>":()V
       4: aload_0
       5: new           #2                  // class org/apache/hadoop/hbase/replication/TestReplicationWALEntryFilters$1
       8: dup
       9: aload_0
      10: invokespecial #3                  // Method org/apache/hadoop/hbase/replication/TestReplicationWALEntryFilters$1."<init>":(Lorg/apache/hadoop/hbase/replication/TestReplicationWALEntryFilters;)V
      13: putfield      #4                  // Field nullFilter:Lorg/apache/hadoop/hbase/replication/WALEntryFilter;
      16: aload_0
      17: new           #5                  // class org/apache/hadoop/hbase/replication/TestReplicationWALEntryFilters$2
      20: dup
      21: aload_0
      22: invokespecial #6                  // Method org/apache/hadoop/hbase/replication/TestReplicationWALEntryFilters$2."<init>":(Lorg/apache/hadoop/hbase/replication/TestReplicationWALEntryFilters;)V
      25: putfield      #7                  // Field passFilter:Lorg/apache/hadoop/hbase/replication/WALEntryFilter;
      28: return

  public void testSystemTableWALEntryFilter();
    Code:
       0: new           #8                  // class org/apache/hadoop/hbase/replication/SystemTableWALEntryFilter
       3: dup
       4: invokespecial #9                  // Method org/apache/hadoop/hbase/replication/SystemTableWALEntryFilter."<init>":()V
       7: astore_1
       8: new           #10                 // class org/apache/hadoop/hbase/wal/WALKeyImpl
      11: dup
      12: getstatic     #11                 // Field org/apache/hadoop/hbase/client/RegionInfoBuilder.FIRST_META_REGIONINFO:Lorg/apache/hadoop/hbase/client/RegionInfo;
      15: invokeinterface #12,  1           // InterfaceMethod org/apache/hadoop/hbase/client/RegionInfo.getEncodedNameAsBytes:()[B
      20: getstatic     #13                 // Field org/apache/hadoop/hbase/TableName.META_TABLE_NAME:Lorg/apache/hadoop/hbase/TableName;
      23: invokestatic  #14                 // Method java/lang/System.currentTimeMillis:()J
      26: invokespecial #15                 // Method org/apache/hadoop/hbase/wal/WALKeyImpl."<init>":([BLorg/apache/hadoop/hbase/TableName;J)V
      29: astore_2
      30: new           #16                 // class org/apache/hadoop/hbase/wal/WAL$Entry
      33: dup
      34: aload_2
      35: aconst_null
      36: invokespecial #17                 // Method org/apache/hadoop/hbase/wal/WAL$Entry."<init>":(Lorg/apache/hadoop/hbase/wal/WALKeyImpl;Lorg/apache/hadoop/hbase/wal/WALEdit;)V
      39: astore_3
      40: aload_1
      41: aload_3
      42: invokevirtual #18                 // Method org/apache/hadoop/hbase/replication/SystemTableWALEntryFilter.filter:(Lorg/apache/hadoop/hbase/wal/WAL$Entry;)Lorg/apache/hadoop/hbase/wal/WAL$Entry;
      45: invokestatic  #19                 // Method org/junit/Assert.assertNull:(Ljava/lang/Object;)V
      48: new           #10                 // class org/apache/hadoop/hbase/wal/WALKeyImpl
      51: dup
      52: iconst_0
      53: newarray       byte
      55: ldc           #20                 // String foo
      57: invokestatic  #21                 // Method org/apache/hadoop/hbase/TableName.valueOf:(Ljava/lang/String;)Lorg/apache/hadoop/hbase/TableName;
      60: invokestatic  #14                 // Method java/lang/System.currentTimeMillis:()J
      63: invokespecial #15                 // Method org/apache/hadoop/hbase/wal/WALKeyImpl."<init>":([BLorg/apache/hadoop/hbase/TableName;J)V
      66: astore        4
      68: new           #16                 // class org/apache/hadoop/hbase/wal/WAL$Entry
      71: dup
      72: aload         4
      74: aconst_null
      75: invokespecial #17                 // Method org/apache/hadoop/hbase/wal/WAL$Entry."<init>":(Lorg/apache/hadoop/hbase/wal/WALKeyImpl;Lorg/apache/hadoop/hbase/wal/WALEdit;)V
      78: astore        5
      80: aload_0
      81: aload         5
      83: aload_1
      84: aload         5
      86: invokevirtual #18                 // Method org/apache/hadoop/hbase/replication/SystemTableWALEntryFilter.filter:(Lorg/apache/hadoop/hbase/wal/WAL$Entry;)Lorg/apache/hadoop/hbase/wal/WAL$Entry;
      89: invokespecial #22                 // Method assertEquals:(Lorg/apache/hadoop/hbase/wal/WAL$Entry;Lorg/apache/hadoop/hbase/wal/WAL$Entry;)V
      92: return

  public void testScopeWALEntryFilter();
    Code:
       0: new           #23                 // class org/apache/hadoop/hbase/replication/ChainWALEntryFilter
       3: dup
       4: iconst_1
       5: anewarray     #24                 // class org/apache/hadoop/hbase/replication/WALEntryFilter
       8: dup
       9: iconst_0
      10: new           #25                 // class org/apache/hadoop/hbase/replication/ScopeWALEntryFilter
      13: dup
      14: invokespecial #26                 // Method org/apache/hadoop/hbase/replication/ScopeWALEntryFilter."<init>":()V
      17: aastore
      18: invokespecial #27                 // Method org/apache/hadoop/hbase/replication/ChainWALEntryFilter."<init>":([Lorg/apache/hadoop/hbase/replication/WALEntryFilter;)V
      21: astore_1
      22: aload_0
      23: aconst_null
      24: iconst_2
      25: anewarray     #28                 // class "[B"
      28: dup
      29: iconst_0
      30: getstatic     #29                 // Field a:[B
      33: aastore
      34: dup
      35: iconst_1
      36: getstatic     #30                 // Field b:[B
      39: aastore
      40: invokespecial #31                 // Method createEntry:(Ljava/util/TreeMap;[[B)Lorg/apache/hadoop/hbase/wal/WAL$Entry;
      43: astore_2
      44: aload_0
      45: aconst_null
      46: iconst_1
      47: anewarray     #28                 // class "[B"
      50: dup
      51: iconst_0
      52: getstatic     #29                 // Field a:[B
      55: aastore
      56: invokespecial #31                 // Method createEntry:(Ljava/util/TreeMap;[[B)Lorg/apache/hadoop/hbase/wal/WAL$Entry;
      59: astore_3
      60: aload_0
      61: aconst_null
      62: iconst_1
      63: anewarray     #28                 // class "[B"
      66: dup
      67: iconst_0
      68: getstatic     #30                 // Field b:[B
      71: aastore
      72: invokespecial #31                 // Method createEntry:(Ljava/util/TreeMap;[[B)Lorg/apache/hadoop/hbase/wal/WAL$Entry;
      75: astore        4
      77: aload_0
      78: aconst_null
      79: iconst_0
      80: anewarray     #28                 // class "[B"
      83: invokespecial #31                 // Method createEntry:(Ljava/util/TreeMap;[[B)Lorg/apache/hadoop/hbase/wal/WAL$Entry;
      86: astore        5
      88: aload_1
      89: aload_2
      90: invokeinterface #32,  2           // InterfaceMethod org/apache/hadoop/hbase/replication/WALEntryFilter.filter:(Lorg/apache/hadoop/hbase/wal/WAL$Entry;)Lorg/apache/hadoop/hbase/wal/WAL$Entry;
      95: invokevirtual #33                 // Method org/apache/hadoop/hbase/wal/WAL$Entry.getEdit:()Lorg/apache/hadoop/hbase/wal/WALEdit;
      98: invokevirtual #34                 // Method org/apache/hadoop/hbase/wal/WALEdit.isEmpty:()Z
     101: invokestatic  #35                 // Method org/junit/Assert.assertTrue:(Z)V
     104: new           #36                 // class java/util/TreeMap
     107: dup
     108: getstatic     #37                 // Field org/apache/hadoop/hbase/util/Bytes.BYTES_COMPARATOR:Ljava/util/Comparator;
     111: invokespecial #38                 // Method java/util/TreeMap."<init>":(Ljava/util/Comparator;)V
     114: astore        6
     116: aload_0
     117: aload         6
     119: iconst_2
     120: anewarray     #28                 // class "[B"
     123: dup
     124: iconst_0
     125: getstatic     #29                 // Field a:[B
     128: aastore
     129: dup
     130: iconst_1
     131: getstatic     #30                 // Field b:[B
     134: aastore
     135: invokespecial #31                 // Method createEntry:(Ljava/util/TreeMap;[[B)Lorg/apache/hadoop/hbase/wal/WAL$Entry;
     138: astore_2
     139: aload_1
     140: aload_2
     141: invokeinterface #32,  2           // InterfaceMethod org/apache/hadoop/hbase/replication/WALEntryFilter.filter:(Lorg/apache/hadoop/hbase/wal/WAL$Entry;)Lorg/apache/hadoop/hbase/wal/WAL$Entry;
     146: invokevirtual #33                 // Method org/apache/hadoop/hbase/wal/WAL$Entry.getEdit:()Lorg/apache/hadoop/hbase/wal/WALEdit;
     149: invokevirtual #34                 // Method org/apache/hadoop/hbase/wal/WALEdit.isEmpty:()Z
     152: invokestatic  #35                 // Method org/junit/Assert.assertTrue:(Z)V
     155: new           #36                 // class java/util/TreeMap
     158: dup
     159: getstatic     #37                 // Field org/apache/hadoop/hbase/util/Bytes.BYTES_COMPARATOR:Ljava/util/Comparator;
     162: invokespecial #38                 // Method java/util/TreeMap."<init>":(Ljava/util/Comparator;)V
     165: astore        6
     167: aload         6
     169: getstatic     #39                 // Field c:[B
     172: iconst_1
     173: invokestatic  #41                 // Method java/lang/Integer.valueOf:(I)Ljava/lang/Integer;
     176: invokevirtual #42                 // Method java/util/TreeMap.put:(Ljava/lang/Object;Ljava/lang/Object;)Ljava/lang/Object;
     179: pop
     180: aload_0
     181: aload         6
     183: iconst_2
     184: anewarray     #28                 // class "[B"
     187: dup
     188: iconst_0
     189: getstatic     #29                 // Field a:[B
     192: aastore
     193: dup
     194: iconst_1
     195: getstatic     #30                 // Field b:[B
     198: aastore
     199: invokespecial #31                 // Method createEntry:(Ljava/util/TreeMap;[[B)Lorg/apache/hadoop/hbase/wal/WAL$Entry;
     202: astore_2
     203: aload_0
     204: aload         5
     206: aload_1
     207: aload_2
     208: invokeinterface #32,  2           // InterfaceMethod org/apache/hadoop/hbase/replication/WALEntryFilter.filter:(Lorg/apache/hadoop/hbase/wal/WAL$Entry;)Lorg/apache/hadoop/hbase/wal/WAL$Entry;
     213: invokespecial #22                 // Method assertEquals:(Lorg/apache/hadoop/hbase/wal/WAL$Entry;Lorg/apache/hadoop/hbase/wal/WAL$Entry;)V
     216: new           #36                 // class java/util/TreeMap
     219: dup
     220: getstatic     #37                 // Field org/apache/hadoop/hbase/util/Bytes.BYTES_COMPARATOR:Ljava/util/Comparator;
     223: invokespecial #38                 // Method java/util/TreeMap."<init>":(Ljava/util/Comparator;)V
     226: astore        6
     228: aload         6
     230: getstatic     #29                 // Field a:[B
     233: iconst_0
     234: invokestatic  #41                 // Method java/lang/Integer.valueOf:(I)Ljava/lang/Integer;
     237: invokevirtual #42                 // Method java/util/TreeMap.put:(Ljava/lang/Object;Ljava/lang/Object;)Ljava/lang/Object;
     240: pop
     241: aload_0
     242: aload         6
     244: iconst_2
     245: anewarray     #28                 // class "[B"
     248: dup
     249: iconst_0
     250: getstatic     #29                 // Field a:[B
     253: aastore
     254: dup
     255: iconst_1
     256: getstatic     #30                 // Field b:[B
     259: aastore
     260: invokespecial #31                 // Method createEntry:(Ljava/util/TreeMap;[[B)Lorg/apache/hadoop/hbase/wal/WAL$Entry;
     263: astore_2
     264: aload_0
     265: aload         5
     267: aload_1
     268: aload_2
     269: invokeinterface #32,  2           // InterfaceMethod org/apache/hadoop/hbase/replication/WALEntryFilter.filter:(Lorg/apache/hadoop/hbase/wal/WAL$Entry;)Lorg/apache/hadoop/hbase/wal/WAL$Entry;
     274: invokespecial #22                 // Method assertEquals:(Lorg/apache/hadoop/hbase/wal/WAL$Entry;Lorg/apache/hadoop/hbase/wal/WAL$Entry;)V
     277: aload         6
     279: getstatic     #30                 // Field b:[B
     282: iconst_0
     283: invokestatic  #41                 // Method java/lang/Integer.valueOf:(I)Ljava/lang/Integer;
     286: invokevirtual #42                 // Method java/util/TreeMap.put:(Ljava/lang/Object;Ljava/lang/Object;)Ljava/lang/Object;
     289: pop
     290: aload_0
     291: aload         5
     293: aload_1
     294: aload_2
     295: invokeinterface #32,  2           // InterfaceMethod org/apache/hadoop/hbase/replication/WALEntryFilter.filter:(Lorg/apache/hadoop/hbase/wal/WAL$Entry;)Lorg/apache/hadoop/hbase/wal/WAL$Entry;
     300: invokespecial #22                 // Method assertEquals:(Lorg/apache/hadoop/hbase/wal/WAL$Entry;Lorg/apache/hadoop/hbase/wal/WAL$Entry;)V
     303: new           #36                 // class java/util/TreeMap
     306: dup
     307: getstatic     #37                 // Field org/apache/hadoop/hbase/util/Bytes.BYTES_COMPARATOR:Ljava/util/Comparator;
     310: invokespecial #38                 // Method java/util/TreeMap."<init>":(Ljava/util/Comparator;)V
     313: astore        6
     315: aload         6
     317: getstatic     #29                 // Field a:[B
     320: iconst_1
     321: invokestatic  #41                 // Method java/lang/Integer.valueOf:(I)Ljava/lang/Integer;
     324: invokevirtual #42                 // Method java/util/TreeMap.put:(Ljava/lang/Object;Ljava/lang/Object;)Ljava/lang/Object;
     327: pop
     328: aload_0
     329: aload         6
     331: iconst_2
     332: anewarray     #28                 // class "[B"
     335: dup
     336: iconst_0
     337: getstatic     #29                 // Field a:[B
     340: aastore
     341: dup
     342: iconst_1
     343: getstatic     #30                 // Field b:[B
     346: aastore
     347: invokespecial #31                 // Method createEntry:(Ljava/util/TreeMap;[[B)Lorg/apache/hadoop/hbase/wal/WAL$Entry;
     350: astore_2
     351: aload_0
     352: aload_3
     353: aload_1
     354: aload_2
     355: invokeinterface #32,  2           // InterfaceMethod org/apache/hadoop/hbase/replication/WALEntryFilter.filter:(Lorg/apache/hadoop/hbase/wal/WAL$Entry;)Lorg/apache/hadoop/hbase/wal/WAL$Entry;
     360: invokespecial #22                 // Method assertEquals:(Lorg/apache/hadoop/hbase/wal/WAL$Entry;Lorg/apache/hadoop/hbase/wal/WAL$Entry;)V
     363: aload         6
     365: getstatic     #30                 // Field b:[B
     368: iconst_0
     369: invokestatic  #41                 // Method java/lang/Integer.valueOf:(I)Ljava/lang/Integer;
     372: invokevirtual #42                 // Method java/util/TreeMap.put:(Ljava/lang/Object;Ljava/lang/Object;)Ljava/lang/Object;
     375: pop
     376: aload_0
     377: aload_3
     378: aload_1
     379: aload_2
     380: invokeinterface #32,  2           // InterfaceMethod org/apache/hadoop/hbase/replication/WALEntryFilter.filter:(Lorg/apache/hadoop/hbase/wal/WAL$Entry;)Lorg/apache/hadoop/hbase/wal/WAL$Entry;
     385: invokespecial #22                 // Method assertEquals:(Lorg/apache/hadoop/hbase/wal/WAL$Entry;Lorg/apache/hadoop/hbase/wal/WAL$Entry;)V
     388: new           #36                 // class java/util/TreeMap
     391: dup
     392: getstatic     #37                 // Field org/apache/hadoop/hbase/util/Bytes.BYTES_COMPARATOR:Ljava/util/Comparator;
     395: invokespecial #38                 // Method java/util/TreeMap."<init>":(Ljava/util/Comparator;)V
     398: astore        6
     400: aload         6
     402: getstatic     #30                 // Field b:[B
     405: iconst_1
     406: invokestatic  #41                 // Method java/lang/Integer.valueOf:(I)Ljava/lang/Integer;
     409: invokevirtual #42                 // Method java/util/TreeMap.put:(Ljava/lang/Object;Ljava/lang/Object;)Ljava/lang/Object;
     412: pop
     413: aload_0
     414: aload         6
     416: iconst_2
     417: anewarray     #28                 // class "[B"
     420: dup
     421: iconst_0
     422: getstatic     #29                 // Field a:[B
     425: aastore
     426: dup
     427: iconst_1
     428: getstatic     #30                 // Field b:[B
     431: aastore
     432: invokespecial #31                 // Method createEntry:(Ljava/util/TreeMap;[[B)Lorg/apache/hadoop/hbase/wal/WAL$Entry;
     435: astore_2
     436: aload_0
     437: aload         4
     439: aload_1
     440: aload_2
     441: invokeinterface #32,  2           // InterfaceMethod org/apache/hadoop/hbase/replication/WALEntryFilter.filter:(Lorg/apache/hadoop/hbase/wal/WAL$Entry;)Lorg/apache/hadoop/hbase/wal/WAL$Entry;
     446: invokespecial #22                 // Method assertEquals:(Lorg/apache/hadoop/hbase/wal/WAL$Entry;Lorg/apache/hadoop/hbase/wal/WAL$Entry;)V
     449: aload         6
     451: getstatic     #29                 // Field a:[B
     454: iconst_0
     455: invokestatic  #41                 // Method java/lang/Integer.valueOf:(I)Ljava/lang/Integer;
     458: invokevirtual #42                 // Method java/util/TreeMap.put:(Ljava/lang/Object;Ljava/lang/Object;)Ljava/lang/Object;
     461: pop
     462: aload_0
     463: aload         4
     465: aload_1
     466: aload_2
     467: invokeinterface #32,  2           // InterfaceMethod org/apache/hadoop/hbase/replication/WALEntryFilter.filter:(Lorg/apache/hadoop/hbase/wal/WAL$Entry;)Lorg/apache/hadoop/hbase/wal/WAL$Entry;
     472: invokespecial #22                 // Method assertEquals:(Lorg/apache/hadoop/hbase/wal/WAL$Entry;Lorg/apache/hadoop/hbase/wal/WAL$Entry;)V
     475: new           #36                 // class java/util/TreeMap
     478: dup
     479: getstatic     #37                 // Field org/apache/hadoop/hbase/util/Bytes.BYTES_COMPARATOR:Ljava/util/Comparator;
     482: invokespecial #38                 // Method java/util/TreeMap."<init>":(Ljava/util/Comparator;)V
     485: astore        6
     487: aload         6
     489: getstatic     #30                 // Field b:[B
     492: iconst_1
     493: invokestatic  #41                 // Method java/lang/Integer.valueOf:(I)Ljava/lang/Integer;
     496: invokevirtual #42                 // Method java/util/TreeMap.put:(Ljava/lang/Object;Ljava/lang/Object;)Ljava/lang/Object;
     499: pop
     500: aload_0
     501: aload         6
     503: iconst_2
     504: anewarray     #28                 // class "[B"
     507: dup
     508: iconst_0
     509: getstatic     #29                 // Field a:[B
     512: aastore
     513: dup
     514: iconst_1
     515: getstatic     #30                 // Field b:[B
     518: aastore
     519: invokespecial #31                 // Method createEntry:(Ljava/util/TreeMap;[[B)Lorg/apache/hadoop/hbase/wal/WAL$Entry;
     522: astore_2
     523: aload_0
     524: aload         4
     526: aload_1
     527: aload_2
     528: invokeinterface #32,  2           // InterfaceMethod org/apache/hadoop/hbase/replication/WALEntryFilter.filter:(Lorg/apache/hadoop/hbase/wal/WAL$Entry;)Lorg/apache/hadoop/hbase/wal/WAL$Entry;
     533: invokespecial #22                 // Method assertEquals:(Lorg/apache/hadoop/hbase/wal/WAL$Entry;Lorg/apache/hadoop/hbase/wal/WAL$Entry;)V
     536: aload         6
     538: getstatic     #29                 // Field a:[B
     541: iconst_0
     542: invokestatic  #41                 // Method java/lang/Integer.valueOf:(I)Ljava/lang/Integer;
     545: invokevirtual #42                 // Method java/util/TreeMap.put:(Ljava/lang/Object;Ljava/lang/Object;)Ljava/lang/Object;
     548: pop
     549: aload_0
     550: aload         4
     552: aload_1
     553: aload_2
     554: invokeinterface #32,  2           // InterfaceMethod org/apache/hadoop/hbase/replication/WALEntryFilter.filter:(Lorg/apache/hadoop/hbase/wal/WAL$Entry;)Lorg/apache/hadoop/hbase/wal/WAL$Entry;
     559: invokespecial #22                 // Method assertEquals:(Lorg/apache/hadoop/hbase/wal/WAL$Entry;Lorg/apache/hadoop/hbase/wal/WAL$Entry;)V
     562: return

  public void testChainWALEntryFilter();
    Code:
       0: aload_0
       1: aconst_null
       2: iconst_3
       3: anewarray     #28                 // class "[B"
       6: dup
       7: iconst_0
       8: getstatic     #29                 // Field a:[B
      11: aastore
      12: dup
      13: iconst_1
      14: getstatic     #30                 // Field b:[B
      17: aastore
      18: dup
      19: iconst_2
      20: getstatic     #39                 // Field c:[B
      23: aastore
      24: invokespecial #31                 // Method createEntry:(Ljava/util/TreeMap;[[B)Lorg/apache/hadoop/hbase/wal/WAL$Entry;
      27: astore_1
      28: new           #23                 // class org/apache/hadoop/hbase/replication/ChainWALEntryFilter
      31: dup
      32: iconst_1
      33: anewarray     #24                 // class org/apache/hadoop/hbase/replication/WALEntryFilter
      36: dup
      37: iconst_0
      38: aload_0
      39: getfield      #7                  // Field passFilter:Lorg/apache/hadoop/hbase/replication/WALEntryFilter;
      42: aastore
      43: invokespecial #27                 // Method org/apache/hadoop/hbase/replication/ChainWALEntryFilter."<init>":([Lorg/apache/hadoop/hbase/replication/WALEntryFilter;)V
      46: astore_2
      47: aload_0
      48: aload_0
      49: aconst_null
      50: iconst_3
      51: anewarray     #28                 // class "[B"
      54: dup
      55: iconst_0
      56: getstatic     #29                 // Field a:[B
      59: aastore
      60: dup
      61: iconst_1
      62: getstatic     #30                 // Field b:[B
      65: aastore
      66: dup
      67: iconst_2
      68: getstatic     #39                 // Field c:[B
      71: aastore
      72: invokespecial #31                 // Method createEntry:(Ljava/util/TreeMap;[[B)Lorg/apache/hadoop/hbase/wal/WAL$Entry;
      75: aload_2
      76: aload_1
      77: invokevirtual #43                 // Method org/apache/hadoop/hbase/replication/ChainWALEntryFilter.filter:(Lorg/apache/hadoop/hbase/wal/WAL$Entry;)Lorg/apache/hadoop/hbase/wal/WAL$Entry;
      80: invokespecial #22                 // Method assertEquals:(Lorg/apache/hadoop/hbase/wal/WAL$Entry;Lorg/apache/hadoop/hbase/wal/WAL$Entry;)V
      83: new           #23                 // class org/apache/hadoop/hbase/replication/ChainWALEntryFilter
      86: dup
      87: iconst_2
      88: anewarray     #24                 // class org/apache/hadoop/hbase/replication/WALEntryFilter
      91: dup
      92: iconst_0
      93: aload_0
      94: getfield      #7                  // Field passFilter:Lorg/apache/hadoop/hbase/replication/WALEntryFilter;
      97: aastore
      98: dup
      99: iconst_1
     100: aload_0
     101: getfield      #7                  // Field passFilter:Lorg/apache/hadoop/hbase/replication/WALEntryFilter;
     104: aastore
     105: invokespecial #27                 // Method org/apache/hadoop/hbase/replication/ChainWALEntryFilter."<init>":([Lorg/apache/hadoop/hbase/replication/WALEntryFilter;)V
     108: astore_2
     109: aload_0
     110: aload_0
     111: aconst_null
     112: iconst_3
     113: anewarray     #28                 // class "[B"
     116: dup
     117: iconst_0
     118: getstatic     #29                 // Field a:[B
     121: aastore
     122: dup
     123: iconst_1
     124: getstatic     #30                 // Field b:[B
     127: aastore
     128: dup
     129: iconst_2
     130: getstatic     #39                 // Field c:[B
     133: aastore
     134: invokespecial #31                 // Method createEntry:(Ljava/util/TreeMap;[[B)Lorg/apache/hadoop/hbase/wal/WAL$Entry;
     137: aload_2
     138: aload_1
     139: invokevirtual #43                 // Method org/apache/hadoop/hbase/replication/ChainWALEntryFilter.filter:(Lorg/apache/hadoop/hbase/wal/WAL$Entry;)Lorg/apache/hadoop/hbase/wal/WAL$Entry;
     142: invokespecial #22                 // Method assertEquals:(Lorg/apache/hadoop/hbase/wal/WAL$Entry;Lorg/apache/hadoop/hbase/wal/WAL$Entry;)V
     145: new           #23                 // class org/apache/hadoop/hbase/replication/ChainWALEntryFilter
     148: dup
     149: iconst_3
     150: anewarray     #24                 // class org/apache/hadoop/hbase/replication/WALEntryFilter
     153: dup
     154: iconst_0
     155: aload_0
     156: getfield      #7                  // Field passFilter:Lorg/apache/hadoop/hbase/replication/WALEntryFilter;
     159: aastore
     160: dup
     161: iconst_1
     162: aload_0
     163: getfield      #7                  // Field passFilter:Lorg/apache/hadoop/hbase/replication/WALEntryFilter;
     166: aastore
     167: dup
     168: iconst_2
     169: aload_0
     170: getfield      #7                  // Field passFilter:Lorg/apache/hadoop/hbase/replication/WALEntryFilter;
     173: aastore
     174: invokespecial #27                 // Method org/apache/hadoop/hbase/replication/ChainWALEntryFilter."<init>":([Lorg/apache/hadoop/hbase/replication/WALEntryFilter;)V
     177: astore_2
     178: aload_0
     179: aload_0
     180: aconst_null
     181: iconst_3
     182: anewarray     #28                 // class "[B"
     185: dup
     186: iconst_0
     187: getstatic     #29                 // Field a:[B
     190: aastore
     191: dup
     192: iconst_1
     193: getstatic     #30                 // Field b:[B
     196: aastore
     197: dup
     198: iconst_2
     199: getstatic     #39                 // Field c:[B
     202: aastore
     203: invokespecial #31                 // Method createEntry:(Ljava/util/TreeMap;[[B)Lorg/apache/hadoop/hbase/wal/WAL$Entry;
     206: aload_2
     207: aload_1
     208: invokevirtual #43                 // Method org/apache/hadoop/hbase/replication/ChainWALEntryFilter.filter:(Lorg/apache/hadoop/hbase/wal/WAL$Entry;)Lorg/apache/hadoop/hbase/wal/WAL$Entry;
     211: invokespecial #22                 // Method assertEquals:(Lorg/apache/hadoop/hbase/wal/WAL$Entry;Lorg/apache/hadoop/hbase/wal/WAL$Entry;)V
     214: new           #23                 // class org/apache/hadoop/hbase/replication/ChainWALEntryFilter
     217: dup
     218: iconst_1
     219: anewarray     #24                 // class org/apache/hadoop/hbase/replication/WALEntryFilter
     222: dup
     223: iconst_0
     224: aload_0
     225: getfield      #4                  // Field nullFilter:Lorg/apache/hadoop/hbase/replication/WALEntryFilter;
     228: aastore
     229: invokespecial #27                 // Method org/apache/hadoop/hbase/replication/ChainWALEntryFilter."<init>":([Lorg/apache/hadoop/hbase/replication/WALEntryFilter;)V
     232: astore_2
     233: aload_0
     234: aconst_null
     235: aload_2
     236: aload_1
     237: invokevirtual #43                 // Method org/apache/hadoop/hbase/replication/ChainWALEntryFilter.filter:(Lorg/apache/hadoop/hbase/wal/WAL$Entry;)Lorg/apache/hadoop/hbase/wal/WAL$Entry;
     240: invokespecial #22                 // Method assertEquals:(Lorg/apache/hadoop/hbase/wal/WAL$Entry;Lorg/apache/hadoop/hbase/wal/WAL$Entry;)V
     243: new           #23                 // class org/apache/hadoop/hbase/replication/ChainWALEntryFilter
     246: dup
     247: iconst_2
     248: anewarray     #24                 // class org/apache/hadoop/hbase/replication/WALEntryFilter
     251: dup
     252: iconst_0
     253: aload_0
     254: getfield      #4                  // Field nullFilter:Lorg/apache/hadoop/hbase/replication/WALEntryFilter;
     257: aastore
     258: dup
     259: iconst_1
     260: aload_0
     261: getfield      #7                  // Field passFilter:Lorg/apache/hadoop/hbase/replication/WALEntryFilter;
     264: aastore
     265: invokespecial #27                 // Method org/apache/hadoop/hbase/replication/ChainWALEntryFilter."<init>":([Lorg/apache/hadoop/hbase/replication/WALEntryFilter;)V
     268: astore_2
     269: aload_0
     270: aconst_null
     271: aload_2
     272: aload_1
     273: invokevirtual #43                 // Method org/apache/hadoop/hbase/replication/ChainWALEntryFilter.filter:(Lorg/apache/hadoop/hbase/wal/WAL$Entry;)Lorg/apache/hadoop/hbase/wal/WAL$Entry;
     276: invokespecial #22                 // Method assertEquals:(Lorg/apache/hadoop/hbase/wal/WAL$Entry;Lorg/apache/hadoop/hbase/wal/WAL$Entry;)V
     279: new           #23                 // class org/apache/hadoop/hbase/replication/ChainWALEntryFilter
     282: dup
     283: iconst_2
     284: anewarray     #24                 // class org/apache/hadoop/hbase/replication/WALEntryFilter
     287: dup
     288: iconst_0
     289: aload_0
     290: getfield      #7                  // Field passFilter:Lorg/apache/hadoop/hbase/replication/WALEntryFilter;
     293: aastore
     294: dup
     295: iconst_1
     296: aload_0
     297: getfield      #4                  // Field nullFilter:Lorg/apache/hadoop/hbase/replication/WALEntryFilter;
     300: aastore
     301: invokespecial #27                 // Method org/apache/hadoop/hbase/replication/ChainWALEntryFilter."<init>":([Lorg/apache/hadoop/hbase/replication/WALEntryFilter;)V
     304: astore_2
     305: aload_0
     306: aconst_null
     307: aload_2
     308: aload_1
     309: invokevirtual #43                 // Method org/apache/hadoop/hbase/replication/ChainWALEntryFilter.filter:(Lorg/apache/hadoop/hbase/wal/WAL$Entry;)Lorg/apache/hadoop/hbase/wal/WAL$Entry;
     312: invokespecial #22                 // Method assertEquals:(Lorg/apache/hadoop/hbase/wal/WAL$Entry;Lorg/apache/hadoop/hbase/wal/WAL$Entry;)V
     315: new           #23                 // class org/apache/hadoop/hbase/replication/ChainWALEntryFilter
     318: dup
     319: iconst_3
     320: anewarray     #24                 // class org/apache/hadoop/hbase/replication/WALEntryFilter
     323: dup
     324: iconst_0
     325: aload_0
     326: getfield      #4                  // Field nullFilter:Lorg/apache/hadoop/hbase/replication/WALEntryFilter;
     329: aastore
     330: dup
     331: iconst_1
     332: aload_0
     333: getfield      #7                  // Field passFilter:Lorg/apache/hadoop/hbase/replication/WALEntryFilter;
     336: aastore
     337: dup
     338: iconst_2
     339: aload_0
     340: getfield      #4                  // Field nullFilter:Lorg/apache/hadoop/hbase/replication/WALEntryFilter;
     343: aastore
     344: invokespecial #27                 // Method org/apache/hadoop/hbase/replication/ChainWALEntryFilter."<init>":([Lorg/apache/hadoop/hbase/replication/WALEntryFilter;)V
     347: astore_2
     348: aload_0
     349: aconst_null
     350: aload_2
     351: aload_1
     352: invokevirtual #43                 // Method org/apache/hadoop/hbase/replication/ChainWALEntryFilter.filter:(Lorg/apache/hadoop/hbase/wal/WAL$Entry;)Lorg/apache/hadoop/hbase/wal/WAL$Entry;
     355: invokespecial #22                 // Method assertEquals:(Lorg/apache/hadoop/hbase/wal/WAL$Entry;Lorg/apache/hadoop/hbase/wal/WAL$Entry;)V
     358: new           #23                 // class org/apache/hadoop/hbase/replication/ChainWALEntryFilter
     361: dup
     362: iconst_2
     363: anewarray     #24                 // class org/apache/hadoop/hbase/replication/WALEntryFilter
     366: dup
     367: iconst_0
     368: aload_0
     369: getfield      #4                  // Field nullFilter:Lorg/apache/hadoop/hbase/replication/WALEntryFilter;
     372: aastore
     373: dup
     374: iconst_1
     375: aload_0
     376: getfield      #4                  // Field nullFilter:Lorg/apache/hadoop/hbase/replication/WALEntryFilter;
     379: aastore
     380: invokespecial #27                 // Method org/apache/hadoop/hbase/replication/ChainWALEntryFilter."<init>":([Lorg/apache/hadoop/hbase/replication/WALEntryFilter;)V
     383: astore_2
     384: aload_0
     385: aconst_null
     386: aload_2
     387: aload_1
     388: invokevirtual #43                 // Method org/apache/hadoop/hbase/replication/ChainWALEntryFilter.filter:(Lorg/apache/hadoop/hbase/wal/WAL$Entry;)Lorg/apache/hadoop/hbase/wal/WAL$Entry;
     391: invokespecial #22                 // Method assertEquals:(Lorg/apache/hadoop/hbase/wal/WAL$Entry;Lorg/apache/hadoop/hbase/wal/WAL$Entry;)V
     394: new           #23                 // class org/apache/hadoop/hbase/replication/ChainWALEntryFilter
     397: dup
     398: iconst_2
     399: anewarray     #24                 // class org/apache/hadoop/hbase/replication/WALEntryFilter
     402: dup
     403: iconst_0
     404: new           #23                 // class org/apache/hadoop/hbase/replication/ChainWALEntryFilter
     407: dup
     408: iconst_4
     409: anewarray     #24                 // class org/apache/hadoop/hbase/replication/WALEntryFilter
     412: dup
     413: iconst_0
     414: aload_0
     415: getfield      #7                  // Field passFilter:Lorg/apache/hadoop/hbase/replication/WALEntryFilter;
     418: aastore
     419: dup
     420: iconst_1
     421: new           #23                 // class org/apache/hadoop/hbase/replication/ChainWALEntryFilter
     424: dup
     425: iconst_2
     426: anewarray     #24                 // class org/apache/hadoop/hbase/replication/WALEntryFilter
     429: dup
     430: iconst_0
     431: aload_0
     432: getfield      #7                  // Field passFilter:Lorg/apache/hadoop/hbase/replication/WALEntryFilter;
     435: aastore
     436: dup
     437: iconst_1
     438: aload_0
     439: getfield      #7                  // Field passFilter:Lorg/apache/hadoop/hbase/replication/WALEntryFilter;
     442: aastore
     443: invokespecial #27                 // Method org/apache/hadoop/hbase/replication/ChainWALEntryFilter."<init>":([Lorg/apache/hadoop/hbase/replication/WALEntryFilter;)V
     446: aastore
     447: dup
     448: iconst_2
     449: new           #23                 // class org/apache/hadoop/hbase/replication/ChainWALEntryFilter
     452: dup
     453: iconst_1
     454: anewarray     #24                 // class org/apache/hadoop/hbase/replication/WALEntryFilter
     457: dup
     458: iconst_0
     459: aload_0
     460: getfield      #7                  // Field passFilter:Lorg/apache/hadoop/hbase/replication/WALEntryFilter;
     463: aastore
     464: invokespecial #27                 // Method org/apache/hadoop/hbase/replication/ChainWALEntryFilter."<init>":([Lorg/apache/hadoop/hbase/replication/WALEntryFilter;)V
     467: aastore
     468: dup
     469: iconst_3
     470: new           #23                 // class org/apache/hadoop/hbase/replication/ChainWALEntryFilter
     473: dup
     474: iconst_1
     475: anewarray     #24                 // class org/apache/hadoop/hbase/replication/WALEntryFilter
     478: dup
     479: iconst_0
     480: aload_0
     481: getfield      #7                  // Field passFilter:Lorg/apache/hadoop/hbase/replication/WALEntryFilter;
     484: aastore
     485: invokespecial #27                 // Method org/apache/hadoop/hbase/replication/ChainWALEntryFilter."<init>":([Lorg/apache/hadoop/hbase/replication/WALEntryFilter;)V
     488: aastore
     489: invokespecial #27                 // Method org/apache/hadoop/hbase/replication/ChainWALEntryFilter."<init>":([Lorg/apache/hadoop/hbase/replication/WALEntryFilter;)V
     492: aastore
     493: dup
     494: iconst_1
     495: new           #23                 // class org/apache/hadoop/hbase/replication/ChainWALEntryFilter
     498: dup
     499: iconst_1
     500: anewarray     #24                 // class org/apache/hadoop/hbase/replication/WALEntryFilter
     503: dup
     504: iconst_0
     505: aload_0
     506: getfield      #7                  // Field passFilter:Lorg/apache/hadoop/hbase/replication/WALEntryFilter;
     509: aastore
     510: invokespecial #27                 // Method org/apache/hadoop/hbase/replication/ChainWALEntryFilter."<init>":([Lorg/apache/hadoop/hbase/replication/WALEntryFilter;)V
     513: aastore
     514: invokespecial #27                 // Method org/apache/hadoop/hbase/replication/ChainWALEntryFilter."<init>":([Lorg/apache/hadoop/hbase/replication/WALEntryFilter;)V
     517: astore_2
     518: aload_0
     519: aload_0
     520: aconst_null
     521: iconst_3
     522: anewarray     #28                 // class "[B"
     525: dup
     526: iconst_0
     527: getstatic     #29                 // Field a:[B
     530: aastore
     531: dup
     532: iconst_1
     533: getstatic     #30                 // Field b:[B
     536: aastore
     537: dup
     538: iconst_2
     539: getstatic     #39                 // Field c:[B
     542: aastore
     543: invokespecial #31                 // Method createEntry:(Ljava/util/TreeMap;[[B)Lorg/apache/hadoop/hbase/wal/WAL$Entry;
     546: aload_2
     547: aload_1
     548: invokevirtual #43                 // Method org/apache/hadoop/hbase/replication/ChainWALEntryFilter.filter:(Lorg/apache/hadoop/hbase/wal/WAL$Entry;)Lorg/apache/hadoop/hbase/wal/WAL$Entry;
     551: invokespecial #22                 // Method assertEquals:(Lorg/apache/hadoop/hbase/wal/WAL$Entry;Lorg/apache/hadoop/hbase/wal/WAL$Entry;)V
     554: new           #23                 // class org/apache/hadoop/hbase/replication/ChainWALEntryFilter
     557: dup
     558: iconst_2
     559: anewarray     #24                 // class org/apache/hadoop/hbase/replication/WALEntryFilter
     562: dup
     563: iconst_0
     564: new           #23                 // class org/apache/hadoop/hbase/replication/ChainWALEntryFilter
     567: dup
     568: iconst_2
     569: anewarray     #24                 // class org/apache/hadoop/hbase/replication/WALEntryFilter
     572: dup
     573: iconst_0
     574: aload_0
     575: getfield      #7                  // Field passFilter:Lorg/apache/hadoop/hbase/replication/WALEntryFilter;
     578: aastore
     579: dup
     580: iconst_1
     581: new           #23                 // class org/apache/hadoop/hbase/replication/ChainWALEntryFilter
     584: dup
     585: iconst_2
     586: anewarray     #24                 // class org/apache/hadoop/hbase/replication/WALEntryFilter
     589: dup
     590: iconst_0
     591: aload_0
     592: getfield      #7                  // Field passFilter:Lorg/apache/hadoop/hbase/replication/WALEntryFilter;
     595: aastore
     596: dup
     597: iconst_1
     598: new           #23                 // class org/apache/hadoop/hbase/replication/ChainWALEntryFilter
     601: dup
     602: iconst_1
     603: anewarray     #24                 // class org/apache/hadoop/hbase/replication/WALEntryFilter
     606: dup
     607: iconst_0
     608: aload_0
     609: getfield      #4                  // Field nullFilter:Lorg/apache/hadoop/hbase/replication/WALEntryFilter;
     612: aastore
     613: invokespecial #27                 // Method org/apache/hadoop/hbase/replication/ChainWALEntryFilter."<init>":([Lorg/apache/hadoop/hbase/replication/WALEntryFilter;)V
     616: aastore
     617: invokespecial #27                 // Method org/apache/hadoop/hbase/replication/ChainWALEntryFilter."<init>":([Lorg/apache/hadoop/hbase/replication/WALEntryFilter;)V
     620: aastore
     621: invokespecial #27                 // Method org/apache/hadoop/hbase/replication/ChainWALEntryFilter."<init>":([Lorg/apache/hadoop/hbase/replication/WALEntryFilter;)V
     624: aastore
     625: dup
     626: iconst_1
     627: new           #23                 // class org/apache/hadoop/hbase/replication/ChainWALEntryFilter
     630: dup
     631: iconst_1
     632: anewarray     #24                 // class org/apache/hadoop/hbase/replication/WALEntryFilter
     635: dup
     636: iconst_0
     637: aload_0
     638: getfield      #7                  // Field passFilter:Lorg/apache/hadoop/hbase/replication/WALEntryFilter;
     641: aastore
     642: invokespecial #27                 // Method org/apache/hadoop/hbase/replication/ChainWALEntryFilter."<init>":([Lorg/apache/hadoop/hbase/replication/WALEntryFilter;)V
     645: aastore
     646: invokespecial #27                 // Method org/apache/hadoop/hbase/replication/ChainWALEntryFilter."<init>":([Lorg/apache/hadoop/hbase/replication/WALEntryFilter;)V
     649: astore_2
     650: aload_0
     651: aconst_null
     652: aload_2
     653: aload_1
     654: invokevirtual #43                 // Method org/apache/hadoop/hbase/replication/ChainWALEntryFilter.filter:(Lorg/apache/hadoop/hbase/wal/WAL$Entry;)Lorg/apache/hadoop/hbase/wal/WAL$Entry;
     657: invokespecial #22                 // Method assertEquals:(Lorg/apache/hadoop/hbase/wal/WAL$Entry;Lorg/apache/hadoop/hbase/wal/WAL$Entry;)V
     660: return

  public void testNamespaceTableCfWALEntryFilter();
    Code:
       0: ldc           #44                 // class org/apache/hadoop/hbase/replication/ReplicationPeer
       2: invokestatic  #45                 // Method org/mockito/Mockito.mock:(Ljava/lang/Class;)Ljava/lang/Object;
       5: checkcast     #44                 // class org/apache/hadoop/hbase/replication/ReplicationPeer
       8: astore_1
       9: ldc           #46                 // class org/apache/hadoop/hbase/replication/ReplicationPeerConfig
      11: invokestatic  #45                 // Method org/mockito/Mockito.mock:(Ljava/lang/Class;)Ljava/lang/Object;
      14: checkcast     #46                 // class org/apache/hadoop/hbase/replication/ReplicationPeerConfig
      17: astore_2
      18: aload_2
      19: invokevirtual #47                 // Method org/apache/hadoop/hbase/replication/ReplicationPeerConfig.replicateAllUserTables:()Z
      22: invokestatic  #48                 // Method java/lang/Boolean.valueOf:(Z)Ljava/lang/Boolean;
      25: invokestatic  #49                 // Method org/mockito/Mockito.when:(Ljava/lang/Object;)Lorg/mockito/stubbing/OngoingStubbing;
      28: iconst_0
      29: invokestatic  #48                 // Method java/lang/Boolean.valueOf:(Z)Ljava/lang/Boolean;
      32: invokeinterface #50,  2           // InterfaceMethod org/mockito/stubbing/OngoingStubbing.thenReturn:(Ljava/lang/Object;)Lorg/mockito/stubbing/OngoingStubbing;
      37: pop
      38: aload_2
      39: invokevirtual #51                 // Method org/apache/hadoop/hbase/replication/ReplicationPeerConfig.getNamespaces:()Ljava/util/Set;
      42: invokestatic  #49                 // Method org/mockito/Mockito.when:(Ljava/lang/Object;)Lorg/mockito/stubbing/OngoingStubbing;
      45: aconst_null
      46: invokeinterface #50,  2           // InterfaceMethod org/mockito/stubbing/OngoingStubbing.thenReturn:(Ljava/lang/Object;)Lorg/mockito/stubbing/OngoingStubbing;
      51: pop
      52: aload_2
      53: invokevirtual #52                 // Method org/apache/hadoop/hbase/replication/ReplicationPeerConfig.getTableCFsMap:()Ljava/util/Map;
      56: invokestatic  #49                 // Method org/mockito/Mockito.when:(Ljava/lang/Object;)Lorg/mockito/stubbing/OngoingStubbing;
      59: aconst_null
      60: invokeinterface #50,  2           // InterfaceMethod org/mockito/stubbing/OngoingStubbing.thenReturn:(Ljava/lang/Object;)Lorg/mockito/stubbing/OngoingStubbing;
      65: pop
      66: aload_1
      67: invokeinterface #53,  1           // InterfaceMethod org/apache/hadoop/hbase/replication/ReplicationPeer.getPeerConfig:()Lorg/apache/hadoop/hbase/replication/ReplicationPeerConfig;
      72: invokestatic  #49                 // Method org/mockito/Mockito.when:(Ljava/lang/Object;)Lorg/mockito/stubbing/OngoingStubbing;
      75: aload_2
      76: invokeinterface #50,  2           // InterfaceMethod org/mockito/stubbing/OngoingStubbing.thenReturn:(Ljava/lang/Object;)Lorg/mockito/stubbing/OngoingStubbing;
      81: pop
      82: aload_0
      83: aconst_null
      84: iconst_3
      85: anewarray     #28                 // class "[B"
      88: dup
      89: iconst_0
      90: getstatic     #29                 // Field a:[B
      93: aastore
      94: dup
      95: iconst_1
      96: getstatic     #30                 // Field b:[B
      99: aastore
     100: dup
     101: iconst_2
     102: getstatic     #39                 // Field c:[B
     105: aastore
     106: invokespecial #31                 // Method createEntry:(Ljava/util/TreeMap;[[B)Lorg/apache/hadoop/hbase/wal/WAL$Entry;
     109: astore_3
     110: new           #23                 // class org/apache/hadoop/hbase/replication/ChainWALEntryFilter
     113: dup
     114: iconst_1
     115: anewarray     #24                 // class org/apache/hadoop/hbase/replication/WALEntryFilter
     118: dup
     119: iconst_0
     120: new           #54                 // class org/apache/hadoop/hbase/replication/NamespaceTableCfWALEntryFilter
     123: dup
     124: aload_1
     125: invokespecial #55                 // Method org/apache/hadoop/hbase/replication/NamespaceTableCfWALEntryFilter."<init>":(Lorg/apache/hadoop/hbase/replication/ReplicationPeer;)V
     128: aastore
     129: invokespecial #27                 // Method org/apache/hadoop/hbase/replication/ChainWALEntryFilter."<init>":([Lorg/apache/hadoop/hbase/replication/WALEntryFilter;)V
     132: astore        4
     134: aload_0
     135: aconst_null
     136: aload         4
     138: aload_3
     139: invokevirtual #43                 // Method org/apache/hadoop/hbase/replication/ChainWALEntryFilter.filter:(Lorg/apache/hadoop/hbase/wal/WAL$Entry;)Lorg/apache/hadoop/hbase/wal/WAL$Entry;
     142: invokespecial #22                 // Method assertEquals:(Lorg/apache/hadoop/hbase/wal/WAL$Entry;Lorg/apache/hadoop/hbase/wal/WAL$Entry;)V
     145: aload_0
     146: aconst_null
     147: iconst_3
     148: anewarray     #28                 // class "[B"
     151: dup
     152: iconst_0
     153: getstatic     #29                 // Field a:[B
     156: aastore
     157: dup
     158: iconst_1
     159: getstatic     #30                 // Field b:[B
     162: aastore
     163: dup
     164: iconst_2
     165: getstatic     #39                 // Field c:[B
     168: aastore
     169: invokespecial #31                 // Method createEntry:(Ljava/util/TreeMap;[[B)Lorg/apache/hadoop/hbase/wal/WAL$Entry;
     172: astore_3
     173: new           #56                 // class java/util/HashMap
     176: dup
     177: invokespecial #57                 // Method java/util/HashMap."<init>":()V
     180: astore        5
     182: aload_2
     183: invokevirtual #47                 // Method org/apache/hadoop/hbase/replication/ReplicationPeerConfig.replicateAllUserTables:()Z
     186: invokestatic  #48                 // Method java/lang/Boolean.valueOf:(Z)Ljava/lang/Boolean;
     189: invokestatic  #49                 // Method org/mockito/Mockito.when:(Ljava/lang/Object;)Lorg/mockito/stubbing/OngoingStubbing;
     192: iconst_0
     193: invokestatic  #48                 // Method java/lang/Boolean.valueOf:(Z)Ljava/lang/Boolean;
     196: invokeinterface #50,  2           // InterfaceMethod org/mockito/stubbing/OngoingStubbing.thenReturn:(Ljava/lang/Object;)Lorg/mockito/stubbing/OngoingStubbing;
     201: pop
     202: aload_2
     203: invokevirtual #52                 // Method org/apache/hadoop/hbase/replication/ReplicationPeerConfig.getTableCFsMap:()Ljava/util/Map;
     206: invokestatic  #49                 // Method org/mockito/Mockito.when:(Ljava/lang/Object;)Lorg/mockito/stubbing/OngoingStubbing;
     209: aload         5
     211: invokeinterface #50,  2           // InterfaceMethod org/mockito/stubbing/OngoingStubbing.thenReturn:(Ljava/lang/Object;)Lorg/mockito/stubbing/OngoingStubbing;
     216: pop
     217: aload_1
     218: invokeinterface #53,  1           // InterfaceMethod org/apache/hadoop/hbase/replication/ReplicationPeer.getPeerConfig:()Lorg/apache/hadoop/hbase/replication/ReplicationPeerConfig;
     223: invokestatic  #49                 // Method org/mockito/Mockito.when:(Ljava/lang/Object;)Lorg/mockito/stubbing/OngoingStubbing;
     226: aload_2
     227: invokeinterface #50,  2           // InterfaceMethod org/mockito/stubbing/OngoingStubbing.thenReturn:(Ljava/lang/Object;)Lorg/mockito/stubbing/OngoingStubbing;
     232: pop
     233: new           #23                 // class org/apache/hadoop/hbase/replication/ChainWALEntryFilter
     236: dup
     237: iconst_1
     238: anewarray     #24                 // class org/apache/hadoop/hbase/replication/WALEntryFilter
     241: dup
     242: iconst_0
     243: new           #54                 // class org/apache/hadoop/hbase/replication/NamespaceTableCfWALEntryFilter
     246: dup
     247: aload_1
     248: invokespecial #55                 // Method org/apache/hadoop/hbase/replication/NamespaceTableCfWALEntryFilter."<init>":(Lorg/apache/hadoop/hbase/replication/ReplicationPeer;)V
     251: aastore
     252: invokespecial #27                 // Method org/apache/hadoop/hbase/replication/ChainWALEntryFilter."<init>":([Lorg/apache/hadoop/hbase/replication/WALEntryFilter;)V
     255: astore        4
     257: aload_0
     258: aconst_null
     259: aload         4
     261: aload_3
     262: invokevirtual #43                 // Method org/apache/hadoop/hbase/replication/ChainWALEntryFilter.filter:(Lorg/apache/hadoop/hbase/wal/WAL$Entry;)Lorg/apache/hadoop/hbase/wal/WAL$Entry;
     265: invokespecial #22                 // Method assertEquals:(Lorg/apache/hadoop/hbase/wal/WAL$Entry;Lorg/apache/hadoop/hbase/wal/WAL$Entry;)V
     268: aload_0
     269: aconst_null
     270: iconst_3
     271: anewarray     #28                 // class "[B"
     274: dup
     275: iconst_0
     276: getstatic     #29                 // Field a:[B
     279: aastore
     280: dup
     281: iconst_1
     282: getstatic     #30                 // Field b:[B
     285: aastore
     286: dup
     287: iconst_2
     288: getstatic     #39                 // Field c:[B
     291: aastore
     292: invokespecial #31                 // Method createEntry:(Ljava/util/TreeMap;[[B)Lorg/apache/hadoop/hbase/wal/WAL$Entry;
     295: astore_3
     296: new           #56                 // class java/util/HashMap
     299: dup
     300: invokespecial #57                 // Method java/util/HashMap."<init>":()V
     303: astore        5
     305: aload         5
     307: ldc           #58                 // String bar
     309: invokestatic  #21                 // Method org/apache/hadoop/hbase/TableName.valueOf:(Ljava/lang/String;)Lorg/apache/hadoop/hbase/TableName;
     312: aconst_null
     313: invokeinterface #59,  3           // InterfaceMethod java/util/Map.put:(Ljava/lang/Object;Ljava/lang/Object;)Ljava/lang/Object;
     318: pop
     319: aload_2
     320: invokevirtual #47                 // Method org/apache/hadoop/hbase/replication/ReplicationPeerConfig.replicateAllUserTables:()Z
     323: invokestatic  #48                 // Method java/lang/Boolean.valueOf:(Z)Ljava/lang/Boolean;
     326: invokestatic  #49                 // Method org/mockito/Mockito.when:(Ljava/lang/Object;)Lorg/mockito/stubbing/OngoingStubbing;
     329: iconst_0
     330: invokestatic  #48                 // Method java/lang/Boolean.valueOf:(Z)Ljava/lang/Boolean;
     333: invokeinterface #50,  2           // InterfaceMethod org/mockito/stubbing/OngoingStubbing.thenReturn:(Ljava/lang/Object;)Lorg/mockito/stubbing/OngoingStubbing;
     338: pop
     339: aload_2
     340: invokevirtual #52                 // Method org/apache/hadoop/hbase/replication/ReplicationPeerConfig.getTableCFsMap:()Ljava/util/Map;
     343: invokestatic  #49                 // Method org/mockito/Mockito.when:(Ljava/lang/Object;)Lorg/mockito/stubbing/OngoingStubbing;
     346: aload         5
     348: invokeinterface #50,  2           // InterfaceMethod org/mockito/stubbing/OngoingStubbing.thenReturn:(Ljava/lang/Object;)Lorg/mockito/stubbing/OngoingStubbing;
     353: pop
     354: aload_1
     355: invokeinterface #53,  1           // InterfaceMethod org/apache/hadoop/hbase/replication/ReplicationPeer.getPeerConfig:()Lorg/apache/hadoop/hbase/replication/ReplicationPeerConfig;
     360: invokestatic  #49                 // Method org/mockito/Mockito.when:(Ljava/lang/Object;)Lorg/mockito/stubbing/OngoingStubbing;
     363: aload_2
     364: invokeinterface #50,  2           // InterfaceMethod org/mockito/stubbing/OngoingStubbing.thenReturn:(Ljava/lang/Object;)Lorg/mockito/stubbing/OngoingStubbing;
     369: pop
     370: new           #23                 // class org/apache/hadoop/hbase/replication/ChainWALEntryFilter
     373: dup
     374: iconst_1
     375: anewarray     #24                 // class org/apache/hadoop/hbase/replication/WALEntryFilter
     378: dup
     379: iconst_0
     380: new           #54                 // class org/apache/hadoop/hbase/replication/NamespaceTableCfWALEntryFilter
     383: dup
     384: aload_1
     385: invokespecial #55                 // Method org/apache/hadoop/hbase/replication/NamespaceTableCfWALEntryFilter."<init>":(Lorg/apache/hadoop/hbase/replication/ReplicationPeer;)V
     388: aastore
     389: invokespecial #27                 // Method org/apache/hadoop/hbase/replication/ChainWALEntryFilter."<init>":([Lorg/apache/hadoop/hbase/replication/WALEntryFilter;)V
     392: astore        4
     394: aload_0
     395: aconst_null
     396: aload         4
     398: aload_3
     399: invokevirtual #43                 // Method org/apache/hadoop/hbase/replication/ChainWALEntryFilter.filter:(Lorg/apache/hadoop/hbase/wal/WAL$Entry;)Lorg/apache/hadoop/hbase/wal/WAL$Entry;
     402: invokespecial #22                 // Method assertEquals:(Lorg/apache/hadoop/hbase/wal/WAL$Entry;Lorg/apache/hadoop/hbase/wal/WAL$Entry;)V
     405: aload_0
     406: aconst_null
     407: iconst_3
     408: anewarray     #28                 // class "[B"
     411: dup
     412: iconst_0
     413: getstatic     #29                 // Field a:[B
     416: aastore
     417: dup
     418: iconst_1
     419: getstatic     #30                 // Field b:[B
     422: aastore
     423: dup
     424: iconst_2
     425: getstatic     #39                 // Field c:[B
     428: aastore
     429: invokespecial #31                 // Method createEntry:(Ljava/util/TreeMap;[[B)Lorg/apache/hadoop/hbase/wal/WAL$Entry;
     432: astore_3
     433: new           #56                 // class java/util/HashMap
     436: dup
     437: invokespecial #57                 // Method java/util/HashMap."<init>":()V
     440: astore        5
     442: aload         5
     444: ldc           #20                 // String foo
     446: invokestatic  #21                 // Method org/apache/hadoop/hbase/TableName.valueOf:(Ljava/lang/String;)Lorg/apache/hadoop/hbase/TableName;
     449: iconst_1
     450: anewarray     #60                 // class java/lang/String
     453: dup
     454: iconst_0
     455: ldc           #61                 // String a
     457: aastore
     458: invokestatic  #62                 // Method org/apache/hbase/thirdparty/com/google/common/collect/Lists.newArrayList:([Ljava/lang/Object;)Ljava/util/ArrayList;
     461: invokeinterface #59,  3           // InterfaceMethod java/util/Map.put:(Ljava/lang/Object;Ljava/lang/Object;)Ljava/lang/Object;
     466: pop
     467: aload_2
     468: invokevirtual #47                 // Method org/apache/hadoop/hbase/replication/ReplicationPeerConfig.replicateAllUserTables:()Z
     471: invokestatic  #48                 // Method java/lang/Boolean.valueOf:(Z)Ljava/lang/Boolean;
     474: invokestatic  #49                 // Method org/mockito/Mockito.when:(Ljava/lang/Object;)Lorg/mockito/stubbing/OngoingStubbing;
     477: iconst_0
     478: invokestatic  #48                 // Method java/lang/Boolean.valueOf:(Z)Ljava/lang/Boolean;
     481: invokeinterface #50,  2           // InterfaceMethod org/mockito/stubbing/OngoingStubbing.thenReturn:(Ljava/lang/Object;)Lorg/mockito/stubbing/OngoingStubbing;
     486: pop
     487: aload_2
     488: invokevirtual #52                 // Method org/apache/hadoop/hbase/replication/ReplicationPeerConfig.getTableCFsMap:()Ljava/util/Map;
     491: invokestatic  #49                 // Method org/mockito/Mockito.when:(Ljava/lang/Object;)Lorg/mockito/stubbing/OngoingStubbing;
     494: aload         5
     496: invokeinterface #50,  2           // InterfaceMethod org/mockito/stubbing/OngoingStubbing.thenReturn:(Ljava/lang/Object;)Lorg/mockito/stubbing/OngoingStubbing;
     501: pop
     502: aload_1
     503: invokeinterface #53,  1           // InterfaceMethod org/apache/hadoop/hbase/replication/ReplicationPeer.getPeerConfig:()Lorg/apache/hadoop/hbase/replication/ReplicationPeerConfig;
     508: invokestatic  #49                 // Method org/mockito/Mockito.when:(Ljava/lang/Object;)Lorg/mockito/stubbing/OngoingStubbing;
     511: aload_2
     512: invokeinterface #50,  2           // InterfaceMethod org/mockito/stubbing/OngoingStubbing.thenReturn:(Ljava/lang/Object;)Lorg/mockito/stubbing/OngoingStubbing;
     517: pop
     518: new           #23                 // class org/apache/hadoop/hbase/replication/ChainWALEntryFilter
     521: dup
     522: iconst_1
     523: anewarray     #24                 // class org/apache/hadoop/hbase/replication/WALEntryFilter
     526: dup
     527: iconst_0
     528: new           #54                 // class org/apache/hadoop/hbase/replication/NamespaceTableCfWALEntryFilter
     531: dup
     532: aload_1
     533: invokespecial #55                 // Method org/apache/hadoop/hbase/replication/NamespaceTableCfWALEntryFilter."<init>":(Lorg/apache/hadoop/hbase/replication/ReplicationPeer;)V
     536: aastore
     537: invokespecial #27                 // Method org/apache/hadoop/hbase/replication/ChainWALEntryFilter."<init>":([Lorg/apache/hadoop/hbase/replication/WALEntryFilter;)V
     540: astore        4
     542: aload_0
     543: aload_0
     544: aconst_null
     545: iconst_1
     546: anewarray     #28                 // class "[B"
     549: dup
     550: iconst_0
     551: getstatic     #29                 // Field a:[B
     554: aastore
     555: invokespecial #31                 // Method createEntry:(Ljava/util/TreeMap;[[B)Lorg/apache/hadoop/hbase/wal/WAL$Entry;
     558: aload         4
     560: aload_3
     561: invokevirtual #43                 // Method org/apache/hadoop/hbase/replication/ChainWALEntryFilter.filter:(Lorg/apache/hadoop/hbase/wal/WAL$Entry;)Lorg/apache/hadoop/hbase/wal/WAL$Entry;
     564: invokespecial #22                 // Method assertEquals:(Lorg/apache/hadoop/hbase/wal/WAL$Entry;Lorg/apache/hadoop/hbase/wal/WAL$Entry;)V
     567: aload_0
     568: aconst_null
     569: iconst_4
     570: anewarray     #28                 // class "[B"
     573: dup
     574: iconst_0
     575: getstatic     #29                 // Field a:[B
     578: aastore
     579: dup
     580: iconst_1
     581: getstatic     #30                 // Field b:[B
     584: aastore
     585: dup
     586: iconst_2
     587: getstatic     #39                 // Field c:[B
     590: aastore
     591: dup
     592: iconst_3
     593: getstatic     #63                 // Field d:[B
     596: aastore
     597: invokespecial #31                 // Method createEntry:(Ljava/util/TreeMap;[[B)Lorg/apache/hadoop/hbase/wal/WAL$Entry;
     600: astore_3
     601: new           #56                 // class java/util/HashMap
     604: dup
     605: invokespecial #57                 // Method java/util/HashMap."<init>":()V
     608: astore        5
     610: aload         5
     612: ldc           #20                 // String foo
     614: invokestatic  #21                 // Method org/apache/hadoop/hbase/TableName.valueOf:(Ljava/lang/String;)Lorg/apache/hadoop/hbase/TableName;
     617: iconst_2
     618: anewarray     #60                 // class java/lang/String
     621: dup
     622: iconst_0
     623: ldc           #61                 // String a
     625: aastore
     626: dup
     627: iconst_1
     628: ldc           #64                 // String c
     630: aastore
     631: invokestatic  #62                 // Method org/apache/hbase/thirdparty/com/google/common/collect/Lists.newArrayList:([Ljava/lang/Object;)Ljava/util/ArrayList;
     634: invokeinterface #59,  3           // InterfaceMethod java/util/Map.put:(Ljava/lang/Object;Ljava/lang/Object;)Ljava/lang/Object;
     639: pop
     640: aload_2
     641: invokevirtual #47                 // Method org/apache/hadoop/hbase/replication/ReplicationPeerConfig.replicateAllUserTables:()Z
     644: invokestatic  #48                 // Method java/lang/Boolean.valueOf:(Z)Ljava/lang/Boolean;
     647: invokestatic  #49                 // Method org/mockito/Mockito.when:(Ljava/lang/Object;)Lorg/mockito/stubbing/OngoingStubbing;
     650: iconst_0
     651: invokestatic  #48                 // Method java/lang/Boolean.valueOf:(Z)Ljava/lang/Boolean;
     654: invokeinterface #50,  2           // InterfaceMethod org/mockito/stubbing/OngoingStubbing.thenReturn:(Ljava/lang/Object;)Lorg/mockito/stubbing/OngoingStubbing;
     659: pop
     660: aload_2
     661: invokevirtual #52                 // Method org/apache/hadoop/hbase/replication/ReplicationPeerConfig.getTableCFsMap:()Ljava/util/Map;
     664: invokestatic  #49                 // Method org/mockito/Mockito.when:(Ljava/lang/Object;)Lorg/mockito/stubbing/OngoingStubbing;
     667: aload         5
     669: invokeinterface #50,  2           // InterfaceMethod org/mockito/stubbing/OngoingStubbing.thenReturn:(Ljava/lang/Object;)Lorg/mockito/stubbing/OngoingStubbing;
     674: pop
     675: aload_1
     676: invokeinterface #53,  1           // InterfaceMethod org/apache/hadoop/hbase/replication/ReplicationPeer.getPeerConfig:()Lorg/apache/hadoop/hbase/replication/ReplicationPeerConfig;
     681: invokestatic  #49                 // Method org/mockito/Mockito.when:(Ljava/lang/Object;)Lorg/mockito/stubbing/OngoingStubbing;
     684: aload_2
     685: invokeinterface #50,  2           // InterfaceMethod org/mockito/stubbing/OngoingStubbing.thenReturn:(Ljava/lang/Object;)Lorg/mockito/stubbing/OngoingStubbing;
     690: pop
     691: new           #23                 // class org/apache/hadoop/hbase/replication/ChainWALEntryFilter
     694: dup
     695: iconst_1
     696: anewarray     #24                 // class org/apache/hadoop/hbase/replication/WALEntryFilter
     699: dup
     700: iconst_0
     701: new           #54                 // class org/apache/hadoop/hbase/replication/NamespaceTableCfWALEntryFilter
     704: dup
     705: aload_1
     706: invokespecial #55                 // Method org/apache/hadoop/hbase/replication/NamespaceTableCfWALEntryFilter."<init>":(Lorg/apache/hadoop/hbase/replication/ReplicationPeer;)V
     709: aastore
     710: invokespecial #27                 // Method org/apache/hadoop/hbase/replication/ChainWALEntryFilter."<init>":([Lorg/apache/hadoop/hbase/replication/WALEntryFilter;)V
     713: astore        4
     715: aload_0
     716: aload_0
     717: aconst_null
     718: iconst_2
     719: anewarray     #28                 // class "[B"
     722: dup
     723: iconst_0
     724: getstatic     #29                 // Field a:[B
     727: aastore
     728: dup
     729: iconst_1
     730: getstatic     #39                 // Field c:[B
     733: aastore
     734: invokespecial #31                 // Method createEntry:(Ljava/util/TreeMap;[[B)Lorg/apache/hadoop/hbase/wal/WAL$Entry;
     737: aload         4
     739: aload_3
     740: invokevirtual #43                 // Method org/apache/hadoop/hbase/replication/ChainWALEntryFilter.filter:(Lorg/apache/hadoop/hbase/wal/WAL$Entry;)Lorg/apache/hadoop/hbase/wal/WAL$Entry;
     743: invokespecial #22                 // Method assertEquals:(Lorg/apache/hadoop/hbase/wal/WAL$Entry;Lorg/apache/hadoop/hbase/wal/WAL$Entry;)V
     746: aload_1
     747: invokeinterface #65,  1           // InterfaceMethod org/apache/hadoop/hbase/replication/ReplicationPeer.getTableCFs:()Ljava/util/Map;
     752: invokestatic  #49                 // Method org/mockito/Mockito.when:(Ljava/lang/Object;)Lorg/mockito/stubbing/OngoingStubbing;
     755: aconst_null
     756: invokeinterface #50,  2           // InterfaceMethod org/mockito/stubbing/OngoingStubbing.thenReturn:(Ljava/lang/Object;)Lorg/mockito/stubbing/OngoingStubbing;
     761: pop
     762: new           #66                 // class java/util/HashSet
     765: dup
     766: invokespecial #67                 // Method java/util/HashSet."<init>":()V
     769: astore        6
     771: aload_2
     772: invokevirtual #47                 // Method org/apache/hadoop/hbase/replication/ReplicationPeerConfig.replicateAllUserTables:()Z
     775: invokestatic  #48                 // Method java/lang/Boolean.valueOf:(Z)Ljava/lang/Boolean;
     778: invokestatic  #49                 // Method org/mockito/Mockito.when:(Ljava/lang/Object;)Lorg/mockito/stubbing/OngoingStubbing;
     781: iconst_0
     782: invokestatic  #48                 // Method java/lang/Boolean.valueOf:(Z)Ljava/lang/Boolean;
     785: invokeinterface #50,  2           // InterfaceMethod org/mockito/stubbing/OngoingStubbing.thenReturn:(Ljava/lang/Object;)Lorg/mockito/stubbing/OngoingStubbing;
     790: pop
     791: aload_2
     792: invokevirtual #51                 // Method org/apache/hadoop/hbase/replication/ReplicationPeerConfig.getNamespaces:()Ljava/util/Set;
     795: invokestatic  #49                 // Method org/mockito/Mockito.when:(Ljava/lang/Object;)Lorg/mockito/stubbing/OngoingStubbing;
     798: aload         6
     800: invokeinterface #50,  2           // InterfaceMethod org/mockito/stubbing/OngoingStubbing.thenReturn:(Ljava/lang/Object;)Lorg/mockito/stubbing/OngoingStubbing;
     805: pop
     806: aload_2
     807: invokevirtual #52                 // Method org/apache/hadoop/hbase/replication/ReplicationPeerConfig.getTableCFsMap:()Ljava/util/Map;
     810: invokestatic  #49                 // Method org/mockito/Mockito.when:(Ljava/lang/Object;)Lorg/mockito/stubbing/OngoingStubbing;
     813: aconst_null
     814: invokeinterface #50,  2           // InterfaceMethod org/mockito/stubbing/OngoingStubbing.thenReturn:(Ljava/lang/Object;)Lorg/mockito/stubbing/OngoingStubbing;
     819: pop
     820: aload_1
     821: invokeinterface #53,  1           // InterfaceMethod org/apache/hadoop/hbase/replication/ReplicationPeer.getPeerConfig:()Lorg/apache/hadoop/hbase/replication/ReplicationPeerConfig;
     826: invokestatic  #49                 // Method org/mockito/Mockito.when:(Ljava/lang/Object;)Lorg/mockito/stubbing/OngoingStubbing;
     829: aload_2
     830: invokeinterface #50,  2           // InterfaceMethod org/mockito/stubbing/OngoingStubbing.thenReturn:(Ljava/lang/Object;)Lorg/mockito/stubbing/OngoingStubbing;
     835: pop
     836: aload_0
     837: aconst_null
     838: iconst_3
     839: anewarray     #28                 // class "[B"
     842: dup
     843: iconst_0
     844: getstatic     #29                 // Field a:[B
     847: aastore
     848: dup
     849: iconst_1
     850: getstatic     #30                 // Field b:[B
     853: aastore
     854: dup
     855: iconst_2
     856: getstatic     #39                 // Field c:[B
     859: aastore
     860: invokespecial #31                 // Method createEntry:(Ljava/util/TreeMap;[[B)Lorg/apache/hadoop/hbase/wal/WAL$Entry;
     863: astore_3
     864: new           #23                 // class org/apache/hadoop/hbase/replication/ChainWALEntryFilter
     867: dup
     868: iconst_1
     869: anewarray     #24                 // class org/apache/hadoop/hbase/replication/WALEntryFilter
     872: dup
     873: iconst_0
     874: new           #54                 // class org/apache/hadoop/hbase/replication/NamespaceTableCfWALEntryFilter
     877: dup
     878: aload_1
     879: invokespecial #55                 // Method org/apache/hadoop/hbase/replication/NamespaceTableCfWALEntryFilter."<init>":(Lorg/apache/hadoop/hbase/replication/ReplicationPeer;)V
     882: aastore
     883: invokespecial #27                 // Method org/apache/hadoop/hbase/replication/ChainWALEntryFilter."<init>":([Lorg/apache/hadoop/hbase/replication/WALEntryFilter;)V
     886: astore        4
     888: aload_0
     889: aconst_null
     890: aload         4
     892: aload_3
     893: invokevirtual #43                 // Method org/apache/hadoop/hbase/replication/ChainWALEntryFilter.filter:(Lorg/apache/hadoop/hbase/wal/WAL$Entry;)Lorg/apache/hadoop/hbase/wal/WAL$Entry;
     896: invokespecial #22                 // Method assertEquals:(Lorg/apache/hadoop/hbase/wal/WAL$Entry;Lorg/apache/hadoop/hbase/wal/WAL$Entry;)V
     899: aload         6
     901: ldc           #68                 // String default
     903: invokeinterface #69,  2           // InterfaceMethod java/util/Set.add:(Ljava/lang/Object;)Z
     908: pop
     909: aload_2
     910: invokevirtual #47                 // Method org/apache/hadoop/hbase/replication/ReplicationPeerConfig.replicateAllUserTables:()Z
     913: invokestatic  #48                 // Method java/lang/Boolean.valueOf:(Z)Ljava/lang/Boolean;
     916: invokestatic  #49                 // Method org/mockito/Mockito.when:(Ljava/lang/Object;)Lorg/mockito/stubbing/OngoingStubbing;
     919: iconst_0
     920: invokestatic  #48                 // Method java/lang/Boolean.valueOf:(Z)Ljava/lang/Boolean;
     923: invokeinterface #50,  2           // InterfaceMethod org/mockito/stubbing/OngoingStubbing.thenReturn:(Ljava/lang/Object;)Lorg/mockito/stubbing/OngoingStubbing;
     928: pop
     929: aload_2
     930: invokevirtual #51                 // Method org/apache/hadoop/hbase/replication/ReplicationPeerConfig.getNamespaces:()Ljava/util/Set;
     933: invokestatic  #49                 // Method org/mockito/Mockito.when:(Ljava/lang/Object;)Lorg/mockito/stubbing/OngoingStubbing;
     936: aload         6
     938: invokeinterface #50,  2           // InterfaceMethod org/mockito/stubbing/OngoingStubbing.thenReturn:(Ljava/lang/Object;)Lorg/mockito/stubbing/OngoingStubbing;
     943: pop
     944: aload_1
     945: invokeinterface #53,  1           // InterfaceMethod org/apache/hadoop/hbase/replication/ReplicationPeer.getPeerConfig:()Lorg/apache/hadoop/hbase/replication/ReplicationPeerConfig;
     950: invokestatic  #49                 // Method org/mockito/Mockito.when:(Ljava/lang/Object;)Lorg/mockito/stubbing/OngoingStubbing;
     953: aload_2
     954: invokeinterface #50,  2           // InterfaceMethod org/mockito/stubbing/OngoingStubbing.thenReturn:(Ljava/lang/Object;)Lorg/mockito/stubbing/OngoingStubbing;
     959: pop
     960: aload_0
     961: aconst_null
     962: iconst_3
     963: anewarray     #28                 // class "[B"
     966: dup
     967: iconst_0
     968: getstatic     #29                 // Field a:[B
     971: aastore
     972: dup
     973: iconst_1
     974: getstatic     #30                 // Field b:[B
     977: aastore
     978: dup
     979: iconst_2
     980: getstatic     #39                 // Field c:[B
     983: aastore
     984: invokespecial #31                 // Method createEntry:(Ljava/util/TreeMap;[[B)Lorg/apache/hadoop/hbase/wal/WAL$Entry;
     987: astore_3
     988: new           #23                 // class org/apache/hadoop/hbase/replication/ChainWALEntryFilter
     991: dup
     992: iconst_1
     993: anewarray     #24                 // class org/apache/hadoop/hbase/replication/WALEntryFilter
     996: dup
     997: iconst_0
     998: new           #54                 // class org/apache/hadoop/hbase/replication/NamespaceTableCfWALEntryFilter
    1001: dup
    1002: aload_1
    1003: invokespecial #55                 // Method org/apache/hadoop/hbase/replication/NamespaceTableCfWALEntryFilter."<init>":(Lorg/apache/hadoop/hbase/replication/ReplicationPeer;)V
    1006: aastore
    1007: invokespecial #27                 // Method org/apache/hadoop/hbase/replication/ChainWALEntryFilter."<init>":([Lorg/apache/hadoop/hbase/replication/WALEntryFilter;)V
    1010: astore        4
    1012: aload_0
    1013: aload_0
    1014: aconst_null
    1015: iconst_3
    1016: anewarray     #28                 // class "[B"
    1019: dup
    1020: iconst_0
    1021: getstatic     #29                 // Field a:[B
    1024: aastore
    1025: dup
    1026: iconst_1
    1027: getstatic     #30                 // Field b:[B
    1030: aastore
    1031: dup
    1032: iconst_2
    1033: getstatic     #39                 // Field c:[B
    1036: aastore
    1037: invokespecial #31                 // Method createEntry:(Ljava/util/TreeMap;[[B)Lorg/apache/hadoop/hbase/wal/WAL$Entry;
    1040: aload         4
    1042: aload_3
    1043: invokevirtual #43                 // Method org/apache/hadoop/hbase/replication/ChainWALEntryFilter.filter:(Lorg/apache/hadoop/hbase/wal/WAL$Entry;)Lorg/apache/hadoop/hbase/wal/WAL$Entry;
    1046: invokespecial #22                 // Method assertEquals:(Lorg/apache/hadoop/hbase/wal/WAL$Entry;Lorg/apache/hadoop/hbase/wal/WAL$Entry;)V
    1049: new           #66                 // class java/util/HashSet
    1052: dup
    1053: invokespecial #67                 // Method java/util/HashSet."<init>":()V
    1056: astore        6
    1058: aload         6
    1060: ldc           #70                 // String ns1
    1062: invokeinterface #69,  2           // InterfaceMethod java/util/Set.add:(Ljava/lang/Object;)Z
    1067: pop
    1068: aload_2
    1069: invokevirtual #47                 // Method org/apache/hadoop/hbase/replication/ReplicationPeerConfig.replicateAllUserTables:()Z
    1072: invokestatic  #48                 // Method java/lang/Boolean.valueOf:(Z)Ljava/lang/Boolean;
    1075: invokestatic  #49                 // Method org/mockito/Mockito.when:(Ljava/lang/Object;)Lorg/mockito/stubbing/OngoingStubbing;
    1078: iconst_0
    1079: invokestatic  #48                 // Method java/lang/Boolean.valueOf:(Z)Ljava/lang/Boolean;
    1082: invokeinterface #50,  2           // InterfaceMethod org/mockito/stubbing/OngoingStubbing.thenReturn:(Ljava/lang/Object;)Lorg/mockito/stubbing/OngoingStubbing;
    1087: pop
    1088: aload_2
    1089: invokevirtual #51                 // Method org/apache/hadoop/hbase/replication/ReplicationPeerConfig.getNamespaces:()Ljava/util/Set;
    1092: invokestatic  #49                 // Method org/mockito/Mockito.when:(Ljava/lang/Object;)Lorg/mockito/stubbing/OngoingStubbing;
    1095: aload         6
    1097: invokeinterface #50,  2           // InterfaceMethod org/mockito/stubbing/OngoingStubbing.thenReturn:(Ljava/lang/Object;)Lorg/mockito/stubbing/OngoingStubbing;
    1102: pop
    1103: aload_1
    1104: invokeinterface #53,  1           // InterfaceMethod org/apache/hadoop/hbase/replication/ReplicationPeer.getPeerConfig:()Lorg/apache/hadoop/hbase/replication/ReplicationPeerConfig;
    1109: invokestatic  #49                 // Method org/mockito/Mockito.when:(Ljava/lang/Object;)Lorg/mockito/stubbing/OngoingStubbing;
    1112: aload_2
    1113: invokeinterface #50,  2           // InterfaceMethod org/mockito/stubbing/OngoingStubbing.thenReturn:(Ljava/lang/Object;)Lorg/mockito/stubbing/OngoingStubbing;
    1118: pop
    1119: aload_0
    1120: aconst_null
    1121: iconst_3
    1122: anewarray     #28                 // class "[B"
    1125: dup
    1126: iconst_0
    1127: getstatic     #29                 // Field a:[B
    1130: aastore
    1131: dup
    1132: iconst_1
    1133: getstatic     #30                 // Field b:[B
    1136: aastore
    1137: dup
    1138: iconst_2
    1139: getstatic     #39                 // Field c:[B
    1142: aastore
    1143: invokespecial #31                 // Method createEntry:(Ljava/util/TreeMap;[[B)Lorg/apache/hadoop/hbase/wal/WAL$Entry;
    1146: astore_3
    1147: new           #23                 // class org/apache/hadoop/hbase/replication/ChainWALEntryFilter
    1150: dup
    1151: iconst_1
    1152: anewarray     #24                 // class org/apache/hadoop/hbase/replication/WALEntryFilter
    1155: dup
    1156: iconst_0
    1157: new           #54                 // class org/apache/hadoop/hbase/replication/NamespaceTableCfWALEntryFilter
    1160: dup
    1161: aload_1
    1162: invokespecial #55                 // Method org/apache/hadoop/hbase/replication/NamespaceTableCfWALEntryFilter."<init>":(Lorg/apache/hadoop/hbase/replication/ReplicationPeer;)V
    1165: aastore
    1166: invokespecial #27                 // Method org/apache/hadoop/hbase/replication/ChainWALEntryFilter."<init>":([Lorg/apache/hadoop/hbase/replication/WALEntryFilter;)V
    1169: astore        4
    1171: aload_0
    1172: aconst_null
    1173: aload         4
    1175: aload_3
    1176: invokevirtual #43                 // Method org/apache/hadoop/hbase/replication/ChainWALEntryFilter.filter:(Lorg/apache/hadoop/hbase/wal/WAL$Entry;)Lorg/apache/hadoop/hbase/wal/WAL$Entry;
    1179: invokespecial #22                 // Method assertEquals:(Lorg/apache/hadoop/hbase/wal/WAL$Entry;Lorg/apache/hadoop/hbase/wal/WAL$Entry;)V
    1182: new           #66                 // class java/util/HashSet
    1185: dup
    1186: invokespecial #67                 // Method java/util/HashSet."<init>":()V
    1189: astore        6
    1191: new           #56                 // class java/util/HashMap
    1194: dup
    1195: invokespecial #57                 // Method java/util/HashMap."<init>":()V
    1198: astore        5
    1200: aload         6
    1202: ldc           #70                 // String ns1
    1204: invokeinterface #69,  2           // InterfaceMethod java/util/Set.add:(Ljava/lang/Object;)Z
    1209: pop
    1210: aload         5
    1212: ldc           #20                 // String foo
    1214: invokestatic  #21                 // Method org/apache/hadoop/hbase/TableName.valueOf:(Ljava/lang/String;)Lorg/apache/hadoop/hbase/TableName;
    1217: iconst_2
    1218: anewarray     #60                 // class java/lang/String
    1221: dup
    1222: iconst_0
    1223: ldc           #61                 // String a
    1225: aastore
    1226: dup
    1227: iconst_1
    1228: ldc           #64                 // String c
    1230: aastore
    1231: invokestatic  #62                 // Method org/apache/hbase/thirdparty/com/google/common/collect/Lists.newArrayList:([Ljava/lang/Object;)Ljava/util/ArrayList;
    1234: invokeinterface #59,  3           // InterfaceMethod java/util/Map.put:(Ljava/lang/Object;Ljava/lang/Object;)Ljava/lang/Object;
    1239: pop
    1240: aload_2
    1241: invokevirtual #47                 // Method org/apache/hadoop/hbase/replication/ReplicationPeerConfig.replicateAllUserTables:()Z
    1244: invokestatic  #48                 // Method java/lang/Boolean.valueOf:(Z)Ljava/lang/Boolean;
    1247: invokestatic  #49                 // Method org/mockito/Mockito.when:(Ljava/lang/Object;)Lorg/mockito/stubbing/OngoingStubbing;
    1250: iconst_0
    1251: invokestatic  #48                 // Method java/lang/Boolean.valueOf:(Z)Ljava/lang/Boolean;
    1254: invokeinterface #50,  2           // InterfaceMethod org/mockito/stubbing/OngoingStubbing.thenReturn:(Ljava/lang/Object;)Lorg/mockito/stubbing/OngoingStubbing;
    1259: pop
    1260: aload_2
    1261: invokevirtual #51                 // Method org/apache/hadoop/hbase/replication/ReplicationPeerConfig.getNamespaces:()Ljava/util/Set;
    1264: invokestatic  #49                 // Method org/mockito/Mockito.when:(Ljava/lang/Object;)Lorg/mockito/stubbing/OngoingStubbing;
    1267: aload         6
    1269: invokeinterface #50,  2           // InterfaceMethod org/mockito/stubbing/OngoingStubbing.thenReturn:(Ljava/lang/Object;)Lorg/mockito/stubbing/OngoingStubbing;
    1274: pop
    1275: aload_2
    1276: invokevirtual #52                 // Method org/apache/hadoop/hbase/replication/ReplicationPeerConfig.getTableCFsMap:()Ljava/util/Map;
    1279: invokestatic  #49                 // Method org/mockito/Mockito.when:(Ljava/lang/Object;)Lorg/mockito/stubbing/OngoingStubbing;
    1282: aload         5
    1284: invokeinterface #50,  2           // InterfaceMethod org/mockito/stubbing/OngoingStubbing.thenReturn:(Ljava/lang/Object;)Lorg/mockito/stubbing/OngoingStubbing;
    1289: pop
    1290: aload_1
    1291: invokeinterface #53,  1           // InterfaceMethod org/apache/hadoop/hbase/replication/ReplicationPeer.getPeerConfig:()Lorg/apache/hadoop/hbase/replication/ReplicationPeerConfig;
    1296: invokestatic  #49                 // Method org/mockito/Mockito.when:(Ljava/lang/Object;)Lorg/mockito/stubbing/OngoingStubbing;
    1299: aload_2
    1300: invokeinterface #50,  2           // InterfaceMethod org/mockito/stubbing/OngoingStubbing.thenReturn:(Ljava/lang/Object;)Lorg/mockito/stubbing/OngoingStubbing;
    1305: pop
    1306: aload_0
    1307: aconst_null
    1308: iconst_3
    1309: anewarray     #28                 // class "[B"
    1312: dup
    1313: iconst_0
    1314: getstatic     #29                 // Field a:[B
    1317: aastore
    1318: dup
    1319: iconst_1
    1320: getstatic     #30                 // Field b:[B
    1323: aastore
    1324: dup
    1325: iconst_2
    1326: getstatic     #39                 // Field c:[B
    1329: aastore
    1330: invokespecial #31                 // Method createEntry:(Ljava/util/TreeMap;[[B)Lorg/apache/hadoop/hbase/wal/WAL$Entry;
    1333: astore_3
    1334: new           #23                 // class org/apache/hadoop/hbase/replication/ChainWALEntryFilter
    1337: dup
    1338: iconst_1
    1339: anewarray     #24                 // class org/apache/hadoop/hbase/replication/WALEntryFilter
    1342: dup
    1343: iconst_0
    1344: new           #54                 // class org/apache/hadoop/hbase/replication/NamespaceTableCfWALEntryFilter
    1347: dup
    1348: aload_1
    1349: invokespecial #55                 // Method org/apache/hadoop/hbase/replication/NamespaceTableCfWALEntryFilter."<init>":(Lorg/apache/hadoop/hbase/replication/ReplicationPeer;)V
    1352: aastore
    1353: invokespecial #27                 // Method org/apache/hadoop/hbase/replication/ChainWALEntryFilter."<init>":([Lorg/apache/hadoop/hbase/replication/WALEntryFilter;)V
    1356: astore        4
    1358: aload_0
    1359: aload_0
    1360: aconst_null
    1361: iconst_2
    1362: anewarray     #28                 // class "[B"
    1365: dup
    1366: iconst_0
    1367: getstatic     #29                 // Field a:[B
    1370: aastore
    1371: dup
    1372: iconst_1
    1373: getstatic     #39                 // Field c:[B
    1376: aastore
    1377: invokespecial #31                 // Method createEntry:(Ljava/util/TreeMap;[[B)Lorg/apache/hadoop/hbase/wal/WAL$Entry;
    1380: aload         4
    1382: aload_3
    1383: invokevirtual #43                 // Method org/apache/hadoop/hbase/replication/ChainWALEntryFilter.filter:(Lorg/apache/hadoop/hbase/wal/WAL$Entry;)Lorg/apache/hadoop/hbase/wal/WAL$Entry;
    1386: invokespecial #22                 // Method assertEquals:(Lorg/apache/hadoop/hbase/wal/WAL$Entry;Lorg/apache/hadoop/hbase/wal/WAL$Entry;)V
    1389: new           #66                 // class java/util/HashSet
    1392: dup
    1393: invokespecial #67                 // Method java/util/HashSet."<init>":()V
    1396: astore        6
    1398: new           #56                 // class java/util/HashMap
    1401: dup
    1402: invokespecial #57                 // Method java/util/HashMap."<init>":()V
    1405: astore        5
    1407: aload         6
    1409: ldc           #68                 // String default
    1411: invokeinterface #69,  2           // InterfaceMethod java/util/Set.add:(Ljava/lang/Object;)Z
    1416: pop
    1417: aload         5
    1419: ldc           #71                 // String ns1:foo
    1421: invokestatic  #21                 // Method org/apache/hadoop/hbase/TableName.valueOf:(Ljava/lang/String;)Lorg/apache/hadoop/hbase/TableName;
    1424: iconst_2
    1425: anewarray     #60                 // class java/lang/String
    1428: dup
    1429: iconst_0
    1430: ldc           #61                 // String a
    1432: aastore
    1433: dup
    1434: iconst_1
    1435: ldc           #64                 // String c
    1437: aastore
    1438: invokestatic  #62                 // Method org/apache/hbase/thirdparty/com/google/common/collect/Lists.newArrayList:([Ljava/lang/Object;)Ljava/util/ArrayList;
    1441: invokeinterface #59,  3           // InterfaceMethod java/util/Map.put:(Ljava/lang/Object;Ljava/lang/Object;)Ljava/lang/Object;
    1446: pop
    1447: aload_2
    1448: invokevirtual #47                 // Method org/apache/hadoop/hbase/replication/ReplicationPeerConfig.replicateAllUserTables:()Z
    1451: invokestatic  #48                 // Method java/lang/Boolean.valueOf:(Z)Ljava/lang/Boolean;
    1454: invokestatic  #49                 // Method org/mockito/Mockito.when:(Ljava/lang/Object;)Lorg/mockito/stubbing/OngoingStubbing;
    1457: iconst_0
    1458: invokestatic  #48                 // Method java/lang/Boolean.valueOf:(Z)Ljava/lang/Boolean;
    1461: invokeinterface #50,  2           // InterfaceMethod org/mockito/stubbing/OngoingStubbing.thenReturn:(Ljava/lang/Object;)Lorg/mockito/stubbing/OngoingStubbing;
    1466: pop
    1467: aload_2
    1468: invokevirtual #51                 // Method org/apache/hadoop/hbase/replication/ReplicationPeerConfig.getNamespaces:()Ljava/util/Set;
    1471: invokestatic  #49                 // Method org/mockito/Mockito.when:(Ljava/lang/Object;)Lorg/mockito/stubbing/OngoingStubbing;
    1474: aload         6
    1476: invokeinterface #50,  2           // InterfaceMethod org/mockito/stubbing/OngoingStubbing.thenReturn:(Ljava/lang/Object;)Lorg/mockito/stubbing/OngoingStubbing;
    1481: pop
    1482: aload_2
    1483: invokevirtual #52                 // Method org/apache/hadoop/hbase/replication/ReplicationPeerConfig.getTableCFsMap:()Ljava/util/Map;
    1486: invokestatic  #49                 // Method org/mockito/Mockito.when:(Ljava/lang/Object;)Lorg/mockito/stubbing/OngoingStubbing;
    1489: aload         5
    1491: invokeinterface #50,  2           // InterfaceMethod org/mockito/stubbing/OngoingStubbing.thenReturn:(Ljava/lang/Object;)Lorg/mockito/stubbing/OngoingStubbing;
    1496: pop
    1497: aload_1
    1498: invokeinterface #53,  1           // InterfaceMethod org/apache/hadoop/hbase/replication/ReplicationPeer.getPeerConfig:()Lorg/apache/hadoop/hbase/replication/ReplicationPeerConfig;
    1503: invokestatic  #49                 // Method org/mockito/Mockito.when:(Ljava/lang/Object;)Lorg/mockito/stubbing/OngoingStubbing;
    1506: aload_2
    1507: invokeinterface #50,  2           // InterfaceMethod org/mockito/stubbing/OngoingStubbing.thenReturn:(Ljava/lang/Object;)Lorg/mockito/stubbing/OngoingStubbing;
    1512: pop
    1513: aload_0
    1514: aconst_null
    1515: iconst_3
    1516: anewarray     #28                 // class "[B"
    1519: dup
    1520: iconst_0
    1521: getstatic     #29                 // Field a:[B
    1524: aastore
    1525: dup
    1526: iconst_1
    1527: getstatic     #30                 // Field b:[B
    1530: aastore
    1531: dup
    1532: iconst_2
    1533: getstatic     #39                 // Field c:[B
    1536: aastore
    1537: invokespecial #31                 // Method createEntry:(Ljava/util/TreeMap;[[B)Lorg/apache/hadoop/hbase/wal/WAL$Entry;
    1540: astore_3
    1541: new           #23                 // class org/apache/hadoop/hbase/replication/ChainWALEntryFilter
    1544: dup
    1545: iconst_1
    1546: anewarray     #24                 // class org/apache/hadoop/hbase/replication/WALEntryFilter
    1549: dup
    1550: iconst_0
    1551: new           #54                 // class org/apache/hadoop/hbase/replication/NamespaceTableCfWALEntryFilter
    1554: dup
    1555: aload_1
    1556: invokespecial #55                 // Method org/apache/hadoop/hbase/replication/NamespaceTableCfWALEntryFilter."<init>":(Lorg/apache/hadoop/hbase/replication/ReplicationPeer;)V
    1559: aastore
    1560: invokespecial #27                 // Method org/apache/hadoop/hbase/replication/ChainWALEntryFilter."<init>":([Lorg/apache/hadoop/hbase/replication/WALEntryFilter;)V
    1563: astore        4
    1565: aload_0
    1566: aload_0
    1567: aconst_null
    1568: iconst_3
    1569: anewarray     #28                 // class "[B"
    1572: dup
    1573: iconst_0
    1574: getstatic     #29                 // Field a:[B
    1577: aastore
    1578: dup
    1579: iconst_1
    1580: getstatic     #30                 // Field b:[B
    1583: aastore
    1584: dup
    1585: iconst_2
    1586: getstatic     #39                 // Field c:[B
    1589: aastore
    1590: invokespecial #31                 // Method createEntry:(Ljava/util/TreeMap;[[B)Lorg/apache/hadoop/hbase/wal/WAL$Entry;
    1593: aload         4
    1595: aload_3
    1596: invokevirtual #43                 // Method org/apache/hadoop/hbase/replication/ChainWALEntryFilter.filter:(Lorg/apache/hadoop/hbase/wal/WAL$Entry;)Lorg/apache/hadoop/hbase/wal/WAL$Entry;
    1599: invokespecial #22                 // Method assertEquals:(Lorg/apache/hadoop/hbase/wal/WAL$Entry;Lorg/apache/hadoop/hbase/wal/WAL$Entry;)V
    1602: new           #66                 // class java/util/HashSet
    1605: dup
    1606: invokespecial #67                 // Method java/util/HashSet."<init>":()V
    1609: astore        6
    1611: new           #56                 // class java/util/HashMap
    1614: dup
    1615: invokespecial #57                 // Method java/util/HashMap."<init>":()V
    1618: astore        5
    1620: aload         6
    1622: ldc           #70                 // String ns1
    1624: invokeinterface #69,  2           // InterfaceMethod java/util/Set.add:(Ljava/lang/Object;)Z
    1629: pop
    1630: aload         5
    1632: ldc           #58                 // String bar
    1634: invokestatic  #21                 // Method org/apache/hadoop/hbase/TableName.valueOf:(Ljava/lang/String;)Lorg/apache/hadoop/hbase/TableName;
    1637: aconst_null
    1638: invokeinterface #59,  3           // InterfaceMethod java/util/Map.put:(Ljava/lang/Object;Ljava/lang/Object;)Ljava/lang/Object;
    1643: pop
    1644: aload_2
    1645: invokevirtual #47                 // Method org/apache/hadoop/hbase/replication/ReplicationPeerConfig.replicateAllUserTables:()Z
    1648: invokestatic  #48                 // Method java/lang/Boolean.valueOf:(Z)Ljava/lang/Boolean;
    1651: invokestatic  #49                 // Method org/mockito/Mockito.when:(Ljava/lang/Object;)Lorg/mockito/stubbing/OngoingStubbing;
    1654: iconst_0
    1655: invokestatic  #48                 // Method java/lang/Boolean.valueOf:(Z)Ljava/lang/Boolean;
    1658: invokeinterface #50,  2           // InterfaceMethod org/mockito/stubbing/OngoingStubbing.thenReturn:(Ljava/lang/Object;)Lorg/mockito/stubbing/OngoingStubbing;
    1663: pop
    1664: aload_2
    1665: invokevirtual #51                 // Method org/apache/hadoop/hbase/replication/ReplicationPeerConfig.getNamespaces:()Ljava/util/Set;
    1668: invokestatic  #49                 // Method org/mockito/Mockito.when:(Ljava/lang/Object;)Lorg/mockito/stubbing/OngoingStubbing;
    1671: aload         6
    1673: invokeinterface #50,  2           // InterfaceMethod org/mockito/stubbing/OngoingStubbing.thenReturn:(Ljava/lang/Object;)Lorg/mockito/stubbing/OngoingStubbing;
    1678: pop
    1679: aload_2
    1680: invokevirtual #52                 // Method org/apache/hadoop/hbase/replication/ReplicationPeerConfig.getTableCFsMap:()Ljava/util/Map;
    1683: invokestatic  #49                 // Method org/mockito/Mockito.when:(Ljava/lang/Object;)Lorg/mockito/stubbing/OngoingStubbing;
    1686: aload         5
    1688: invokeinterface #50,  2           // InterfaceMethod org/mockito/stubbing/OngoingStubbing.thenReturn:(Ljava/lang/Object;)Lorg/mockito/stubbing/OngoingStubbing;
    1693: pop
    1694: aload_1
    1695: invokeinterface #53,  1           // InterfaceMethod org/apache/hadoop/hbase/replication/ReplicationPeer.getPeerConfig:()Lorg/apache/hadoop/hbase/replication/ReplicationPeerConfig;
    1700: invokestatic  #49                 // Method org/mockito/Mockito.when:(Ljava/lang/Object;)Lorg/mockito/stubbing/OngoingStubbing;
    1703: aload_2
    1704: invokeinterface #50,  2           // InterfaceMethod org/mockito/stubbing/OngoingStubbing.thenReturn:(Ljava/lang/Object;)Lorg/mockito/stubbing/OngoingStubbing;
    1709: pop
    1710: aload_0
    1711: aconst_null
    1712: iconst_3
    1713: anewarray     #28                 // class "[B"
    1716: dup
    1717: iconst_0
    1718: getstatic     #29                 // Field a:[B
    1721: aastore
    1722: dup
    1723: iconst_1
    1724: getstatic     #30                 // Field b:[B
    1727: aastore
    1728: dup
    1729: iconst_2
    1730: getstatic     #39                 // Field c:[B
    1733: aastore
    1734: invokespecial #31                 // Method createEntry:(Ljava/util/TreeMap;[[B)Lorg/apache/hadoop/hbase/wal/WAL$Entry;
    1737: astore_3
    1738: new           #23                 // class org/apache/hadoop/hbase/replication/ChainWALEntryFilter
    1741: dup
    1742: iconst_1
    1743: anewarray     #24                 // class org/apache/hadoop/hbase/replication/WALEntryFilter
    1746: dup
    1747: iconst_0
    1748: new           #54                 // class org/apache/hadoop/hbase/replication/NamespaceTableCfWALEntryFilter
    1751: dup
    1752: aload_1
    1753: invokespecial #55                 // Method org/apache/hadoop/hbase/replication/NamespaceTableCfWALEntryFilter."<init>":(Lorg/apache/hadoop/hbase/replication/ReplicationPeer;)V
    1756: aastore
    1757: invokespecial #27                 // Method org/apache/hadoop/hbase/replication/ChainWALEntryFilter."<init>":([Lorg/apache/hadoop/hbase/replication/WALEntryFilter;)V
    1760: astore        4
    1762: aload_0
    1763: aconst_null
    1764: aload         4
    1766: aload_3
    1767: invokevirtual #43                 // Method org/apache/hadoop/hbase/replication/ChainWALEntryFilter.filter:(Lorg/apache/hadoop/hbase/wal/WAL$Entry;)Lorg/apache/hadoop/hbase/wal/WAL$Entry;
    1770: invokespecial #22                 // Method assertEquals:(Lorg/apache/hadoop/hbase/wal/WAL$Entry;Lorg/apache/hadoop/hbase/wal/WAL$Entry;)V
    1773: return

  public void testNamespaceTableCfWALEntryFilter2();
    Code:
       0: ldc           #44                 // class org/apache/hadoop/hbase/replication/ReplicationPeer
       2: invokestatic  #45                 // Method org/mockito/Mockito.mock:(Ljava/lang/Class;)Ljava/lang/Object;
       5: checkcast     #44                 // class org/apache/hadoop/hbase/replication/ReplicationPeer
       8: astore_1
       9: ldc           #46                 // class org/apache/hadoop/hbase/replication/ReplicationPeerConfig
      11: invokestatic  #45                 // Method org/mockito/Mockito.mock:(Ljava/lang/Class;)Ljava/lang/Object;
      14: checkcast     #46                 // class org/apache/hadoop/hbase/replication/ReplicationPeerConfig
      17: astore_2
      18: aload_2
      19: invokevirtual #47                 // Method org/apache/hadoop/hbase/replication/ReplicationPeerConfig.replicateAllUserTables:()Z
      22: invokestatic  #48                 // Method java/lang/Boolean.valueOf:(Z)Ljava/lang/Boolean;
      25: invokestatic  #49                 // Method org/mockito/Mockito.when:(Ljava/lang/Object;)Lorg/mockito/stubbing/OngoingStubbing;
      28: iconst_1
      29: invokestatic  #48                 // Method java/lang/Boolean.valueOf:(Z)Ljava/lang/Boolean;
      32: invokeinterface #50,  2           // InterfaceMethod org/mockito/stubbing/OngoingStubbing.thenReturn:(Ljava/lang/Object;)Lorg/mockito/stubbing/OngoingStubbing;
      37: pop
      38: aload_2
      39: invokevirtual #72                 // Method org/apache/hadoop/hbase/replication/ReplicationPeerConfig.getExcludeNamespaces:()Ljava/util/Set;
      42: invokestatic  #49                 // Method org/mockito/Mockito.when:(Ljava/lang/Object;)Lorg/mockito/stubbing/OngoingStubbing;
      45: aconst_null
      46: invokeinterface #50,  2           // InterfaceMethod org/mockito/stubbing/OngoingStubbing.thenReturn:(Ljava/lang/Object;)Lorg/mockito/stubbing/OngoingStubbing;
      51: pop
      52: aload_2
      53: invokevirtual #73                 // Method org/apache/hadoop/hbase/replication/ReplicationPeerConfig.getExcludeTableCFsMap:()Ljava/util/Map;
      56: invokestatic  #49                 // Method org/mockito/Mockito.when:(Ljava/lang/Object;)Lorg/mockito/stubbing/OngoingStubbing;
      59: aconst_null
      60: invokeinterface #50,  2           // InterfaceMethod org/mockito/stubbing/OngoingStubbing.thenReturn:(Ljava/lang/Object;)Lorg/mockito/stubbing/OngoingStubbing;
      65: pop
      66: aload_1
      67: invokeinterface #53,  1           // InterfaceMethod org/apache/hadoop/hbase/replication/ReplicationPeer.getPeerConfig:()Lorg/apache/hadoop/hbase/replication/ReplicationPeerConfig;
      72: invokestatic  #49                 // Method org/mockito/Mockito.when:(Ljava/lang/Object;)Lorg/mockito/stubbing/OngoingStubbing;
      75: aload_2
      76: invokeinterface #50,  2           // InterfaceMethod org/mockito/stubbing/OngoingStubbing.thenReturn:(Ljava/lang/Object;)Lorg/mockito/stubbing/OngoingStubbing;
      81: pop
      82: aload_0
      83: aconst_null
      84: iconst_3
      85: anewarray     #28                 // class "[B"
      88: dup
      89: iconst_0
      90: getstatic     #29                 // Field a:[B
      93: aastore
      94: dup
      95: iconst_1
      96: getstatic     #30                 // Field b:[B
      99: aastore
     100: dup
     101: iconst_2
     102: getstatic     #39                 // Field c:[B
     105: aastore
     106: invokespecial #31                 // Method createEntry:(Ljava/util/TreeMap;[[B)Lorg/apache/hadoop/hbase/wal/WAL$Entry;
     109: astore_3
     110: new           #23                 // class org/apache/hadoop/hbase/replication/ChainWALEntryFilter
     113: dup
     114: iconst_1
     115: anewarray     #24                 // class org/apache/hadoop/hbase/replication/WALEntryFilter
     118: dup
     119: iconst_0
     120: new           #54                 // class org/apache/hadoop/hbase/replication/NamespaceTableCfWALEntryFilter
     123: dup
     124: aload_1
     125: invokespecial #55                 // Method org/apache/hadoop/hbase/replication/NamespaceTableCfWALEntryFilter."<init>":(Lorg/apache/hadoop/hbase/replication/ReplicationPeer;)V
     128: aastore
     129: invokespecial #27                 // Method org/apache/hadoop/hbase/replication/ChainWALEntryFilter."<init>":([Lorg/apache/hadoop/hbase/replication/WALEntryFilter;)V
     132: astore        4
     134: aload_0
     135: aload_0
     136: aconst_null
     137: iconst_3
     138: anewarray     #28                 // class "[B"
     141: dup
     142: iconst_0
     143: getstatic     #29                 // Field a:[B
     146: aastore
     147: dup
     148: iconst_1
     149: getstatic     #30                 // Field b:[B
     152: aastore
     153: dup
     154: iconst_2
     155: getstatic     #39                 // Field c:[B
     158: aastore
     159: invokespecial #31                 // Method createEntry:(Ljava/util/TreeMap;[[B)Lorg/apache/hadoop/hbase/wal/WAL$Entry;
     162: aload         4
     164: aload_3
     165: invokevirtual #43                 // Method org/apache/hadoop/hbase/replication/ChainWALEntryFilter.filter:(Lorg/apache/hadoop/hbase/wal/WAL$Entry;)Lorg/apache/hadoop/hbase/wal/WAL$Entry;
     168: invokespecial #22                 // Method assertEquals:(Lorg/apache/hadoop/hbase/wal/WAL$Entry;Lorg/apache/hadoop/hbase/wal/WAL$Entry;)V
     171: new           #66                 // class java/util/HashSet
     174: dup
     175: invokespecial #67                 // Method java/util/HashSet."<init>":()V
     178: astore        5
     180: aload_2
     181: invokevirtual #72                 // Method org/apache/hadoop/hbase/replication/ReplicationPeerConfig.getExcludeNamespaces:()Ljava/util/Set;
     184: invokestatic  #49                 // Method org/mockito/Mockito.when:(Ljava/lang/Object;)Lorg/mockito/stubbing/OngoingStubbing;
     187: aload         5
     189: invokeinterface #50,  2           // InterfaceMethod org/mockito/stubbing/OngoingStubbing.thenReturn:(Ljava/lang/Object;)Lorg/mockito/stubbing/OngoingStubbing;
     194: pop
     195: aload_2
     196: invokevirtual #73                 // Method org/apache/hadoop/hbase/replication/ReplicationPeerConfig.getExcludeTableCFsMap:()Ljava/util/Map;
     199: invokestatic  #49                 // Method org/mockito/Mockito.when:(Ljava/lang/Object;)Lorg/mockito/stubbing/OngoingStubbing;
     202: aconst_null
     203: invokeinterface #50,  2           // InterfaceMethod org/mockito/stubbing/OngoingStubbing.thenReturn:(Ljava/lang/Object;)Lorg/mockito/stubbing/OngoingStubbing;
     208: pop
     209: aload_1
     210: invokeinterface #53,  1           // InterfaceMethod org/apache/hadoop/hbase/replication/ReplicationPeer.getPeerConfig:()Lorg/apache/hadoop/hbase/replication/ReplicationPeerConfig;
     215: invokestatic  #49                 // Method org/mockito/Mockito.when:(Ljava/lang/Object;)Lorg/mockito/stubbing/OngoingStubbing;
     218: aload_2
     219: invokeinterface #50,  2           // InterfaceMethod org/mockito/stubbing/OngoingStubbing.thenReturn:(Ljava/lang/Object;)Lorg/mockito/stubbing/OngoingStubbing;
     224: pop
     225: aload_0
     226: aconst_null
     227: iconst_3
     228: anewarray     #28                 // class "[B"
     231: dup
     232: iconst_0
     233: getstatic     #29                 // Field a:[B
     236: aastore
     237: dup
     238: iconst_1
     239: getstatic     #30                 // Field b:[B
     242: aastore
     243: dup
     244: iconst_2
     245: getstatic     #39                 // Field c:[B
     248: aastore
     249: invokespecial #31                 // Method createEntry:(Ljava/util/TreeMap;[[B)Lorg/apache/hadoop/hbase/wal/WAL$Entry;
     252: astore_3
     253: new           #23                 // class org/apache/hadoop/hbase/replication/ChainWALEntryFilter
     256: dup
     257: iconst_1
     258: anewarray     #24                 // class org/apache/hadoop/hbase/replication/WALEntryFilter
     261: dup
     262: iconst_0
     263: new           #54                 // class org/apache/hadoop/hbase/replication/NamespaceTableCfWALEntryFilter
     266: dup
     267: aload_1
     268: invokespecial #55                 // Method org/apache/hadoop/hbase/replication/NamespaceTableCfWALEntryFilter."<init>":(Lorg/apache/hadoop/hbase/replication/ReplicationPeer;)V
     271: aastore
     272: invokespecial #27                 // Method org/apache/hadoop/hbase/replication/ChainWALEntryFilter."<init>":([Lorg/apache/hadoop/hbase/replication/WALEntryFilter;)V
     275: astore        4
     277: aload_0
     278: aload_0
     279: aconst_null
     280: iconst_3
     281: anewarray     #28                 // class "[B"
     284: dup
     285: iconst_0
     286: getstatic     #29                 // Field a:[B
     289: aastore
     290: dup
     291: iconst_1
     292: getstatic     #30                 // Field b:[B
     295: aastore
     296: dup
     297: iconst_2
     298: getstatic     #39                 // Field c:[B
     301: aastore
     302: invokespecial #31                 // Method createEntry:(Ljava/util/TreeMap;[[B)Lorg/apache/hadoop/hbase/wal/WAL$Entry;
     305: aload         4
     307: aload_3
     308: invokevirtual #43                 // Method org/apache/hadoop/hbase/replication/ChainWALEntryFilter.filter:(Lorg/apache/hadoop/hbase/wal/WAL$Entry;)Lorg/apache/hadoop/hbase/wal/WAL$Entry;
     311: invokespecial #22                 // Method assertEquals:(Lorg/apache/hadoop/hbase/wal/WAL$Entry;Lorg/apache/hadoop/hbase/wal/WAL$Entry;)V
     314: aload         5
     316: ldc           #68                 // String default
     318: invokeinterface #69,  2           // InterfaceMethod java/util/Set.add:(Ljava/lang/Object;)Z
     323: pop
     324: aload_2
     325: invokevirtual #72                 // Method org/apache/hadoop/hbase/replication/ReplicationPeerConfig.getExcludeNamespaces:()Ljava/util/Set;
     328: invokestatic  #49                 // Method org/mockito/Mockito.when:(Ljava/lang/Object;)Lorg/mockito/stubbing/OngoingStubbing;
     331: aload         5
     333: invokeinterface #50,  2           // InterfaceMethod org/mockito/stubbing/OngoingStubbing.thenReturn:(Ljava/lang/Object;)Lorg/mockito/stubbing/OngoingStubbing;
     338: pop
     339: aload_2
     340: invokevirtual #73                 // Method org/apache/hadoop/hbase/replication/ReplicationPeerConfig.getExcludeTableCFsMap:()Ljava/util/Map;
     343: invokestatic  #49                 // Method org/mockito/Mockito.when:(Ljava/lang/Object;)Lorg/mockito/stubbing/OngoingStubbing;
     346: aconst_null
     347: invokeinterface #50,  2           // InterfaceMethod org/mockito/stubbing/OngoingStubbing.thenReturn:(Ljava/lang/Object;)Lorg/mockito/stubbing/OngoingStubbing;
     352: pop
     353: aload_1
     354: invokeinterface #53,  1           // InterfaceMethod org/apache/hadoop/hbase/replication/ReplicationPeer.getPeerConfig:()Lorg/apache/hadoop/hbase/replication/ReplicationPeerConfig;
     359: invokestatic  #49                 // Method org/mockito/Mockito.when:(Ljava/lang/Object;)Lorg/mockito/stubbing/OngoingStubbing;
     362: aload_2
     363: invokeinterface #50,  2           // InterfaceMethod org/mockito/stubbing/OngoingStubbing.thenReturn:(Ljava/lang/Object;)Lorg/mockito/stubbing/OngoingStubbing;
     368: pop
     369: aload_0
     370: aconst_null
     371: iconst_3
     372: anewarray     #28                 // class "[B"
     375: dup
     376: iconst_0
     377: getstatic     #29                 // Field a:[B
     380: aastore
     381: dup
     382: iconst_1
     383: getstatic     #30                 // Field b:[B
     386: aastore
     387: dup
     388: iconst_2
     389: getstatic     #39                 // Field c:[B
     392: aastore
     393: invokespecial #31                 // Method createEntry:(Ljava/util/TreeMap;[[B)Lorg/apache/hadoop/hbase/wal/WAL$Entry;
     396: astore_3
     397: new           #23                 // class org/apache/hadoop/hbase/replication/ChainWALEntryFilter
     400: dup
     401: iconst_1
     402: anewarray     #24                 // class org/apache/hadoop/hbase/replication/WALEntryFilter
     405: dup
     406: iconst_0
     407: new           #54                 // class org/apache/hadoop/hbase/replication/NamespaceTableCfWALEntryFilter
     410: dup
     411: aload_1
     412: invokespecial #55                 // Method org/apache/hadoop/hbase/replication/NamespaceTableCfWALEntryFilter."<init>":(Lorg/apache/hadoop/hbase/replication/ReplicationPeer;)V
     415: aastore
     416: invokespecial #27                 // Method org/apache/hadoop/hbase/replication/ChainWALEntryFilter."<init>":([Lorg/apache/hadoop/hbase/replication/WALEntryFilter;)V
     419: astore        4
     421: aload_0
     422: aconst_null
     423: aload         4
     425: aload_3
     426: invokevirtual #43                 // Method org/apache/hadoop/hbase/replication/ChainWALEntryFilter.filter:(Lorg/apache/hadoop/hbase/wal/WAL$Entry;)Lorg/apache/hadoop/hbase/wal/WAL$Entry;
     429: invokespecial #22                 // Method assertEquals:(Lorg/apache/hadoop/hbase/wal/WAL$Entry;Lorg/apache/hadoop/hbase/wal/WAL$Entry;)V
     432: new           #66                 // class java/util/HashSet
     435: dup
     436: invokespecial #67                 // Method java/util/HashSet."<init>":()V
     439: astore        5
     441: aload         5
     443: ldc           #70                 // String ns1
     445: invokeinterface #69,  2           // InterfaceMethod java/util/Set.add:(Ljava/lang/Object;)Z
     450: pop
     451: aload_2
     452: invokevirtual #72                 // Method org/apache/hadoop/hbase/replication/ReplicationPeerConfig.getExcludeNamespaces:()Ljava/util/Set;
     455: invokestatic  #49                 // Method org/mockito/Mockito.when:(Ljava/lang/Object;)Lorg/mockito/stubbing/OngoingStubbing;
     458: aload         5
     460: invokeinterface #50,  2           // InterfaceMethod org/mockito/stubbing/OngoingStubbing.thenReturn:(Ljava/lang/Object;)Lorg/mockito/stubbing/OngoingStubbing;
     465: pop
     466: aload_2
     467: invokevirtual #73                 // Method org/apache/hadoop/hbase/replication/ReplicationPeerConfig.getExcludeTableCFsMap:()Ljava/util/Map;
     470: invokestatic  #49                 // Method org/mockito/Mockito.when:(Ljava/lang/Object;)Lorg/mockito/stubbing/OngoingStubbing;
     473: aconst_null
     474: invokeinterface #50,  2           // InterfaceMethod org/mockito/stubbing/OngoingStubbing.thenReturn:(Ljava/lang/Object;)Lorg/mockito/stubbing/OngoingStubbing;
     479: pop
     480: aload_1
     481: invokeinterface #53,  1           // InterfaceMethod org/apache/hadoop/hbase/replication/ReplicationPeer.getPeerConfig:()Lorg/apache/hadoop/hbase/replication/ReplicationPeerConfig;
     486: invokestatic  #49                 // Method org/mockito/Mockito.when:(Ljava/lang/Object;)Lorg/mockito/stubbing/OngoingStubbing;
     489: aload_2
     490: invokeinterface #50,  2           // InterfaceMethod org/mockito/stubbing/OngoingStubbing.thenReturn:(Ljava/lang/Object;)Lorg/mockito/stubbing/OngoingStubbing;
     495: pop
     496: aload_0
     497: aconst_null
     498: iconst_3
     499: anewarray     #28                 // class "[B"
     502: dup
     503: iconst_0
     504: getstatic     #29                 // Field a:[B
     507: aastore
     508: dup
     509: iconst_1
     510: getstatic     #30                 // Field b:[B
     513: aastore
     514: dup
     515: iconst_2
     516: getstatic     #39                 // Field c:[B
     519: aastore
     520: invokespecial #31                 // Method createEntry:(Ljava/util/TreeMap;[[B)Lorg/apache/hadoop/hbase/wal/WAL$Entry;
     523: astore_3
     524: new           #23                 // class org/apache/hadoop/hbase/replication/ChainWALEntryFilter
     527: dup
     528: iconst_1
     529: anewarray     #24                 // class org/apache/hadoop/hbase/replication/WALEntryFilter
     532: dup
     533: iconst_0
     534: new           #54                 // class org/apache/hadoop/hbase/replication/NamespaceTableCfWALEntryFilter
     537: dup
     538: aload_1
     539: invokespecial #55                 // Method org/apache/hadoop/hbase/replication/NamespaceTableCfWALEntryFilter."<init>":(Lorg/apache/hadoop/hbase/replication/ReplicationPeer;)V
     542: aastore
     543: invokespecial #27                 // Method org/apache/hadoop/hbase/replication/ChainWALEntryFilter."<init>":([Lorg/apache/hadoop/hbase/replication/WALEntryFilter;)V
     546: astore        4
     548: aload_0
     549: aload_0
     550: aconst_null
     551: iconst_3
     552: anewarray     #28                 // class "[B"
     555: dup
     556: iconst_0
     557: getstatic     #29                 // Field a:[B
     560: aastore
     561: dup
     562: iconst_1
     563: getstatic     #30                 // Field b:[B
     566: aastore
     567: dup
     568: iconst_2
     569: getstatic     #39                 // Field c:[B
     572: aastore
     573: invokespecial #31                 // Method createEntry:(Ljava/util/TreeMap;[[B)Lorg/apache/hadoop/hbase/wal/WAL$Entry;
     576: aload         4
     578: aload_3
     579: invokevirtual #43                 // Method org/apache/hadoop/hbase/replication/ChainWALEntryFilter.filter:(Lorg/apache/hadoop/hbase/wal/WAL$Entry;)Lorg/apache/hadoop/hbase/wal/WAL$Entry;
     582: invokespecial #22                 // Method assertEquals:(Lorg/apache/hadoop/hbase/wal/WAL$Entry;Lorg/apache/hadoop/hbase/wal/WAL$Entry;)V
     585: new           #56                 // class java/util/HashMap
     588: dup
     589: invokespecial #57                 // Method java/util/HashMap."<init>":()V
     592: astore        6
     594: aload_2
     595: invokevirtual #72                 // Method org/apache/hadoop/hbase/replication/ReplicationPeerConfig.getExcludeNamespaces:()Ljava/util/Set;
     598: invokestatic  #49                 // Method org/mockito/Mockito.when:(Ljava/lang/Object;)Lorg/mockito/stubbing/OngoingStubbing;
     601: aconst_null
     602: invokeinterface #50,  2           // InterfaceMethod org/mockito/stubbing/OngoingStubbing.thenReturn:(Ljava/lang/Object;)Lorg/mockito/stubbing/OngoingStubbing;
     607: pop
     608: aload_2
     609: invokevirtual #73                 // Method org/apache/hadoop/hbase/replication/ReplicationPeerConfig.getExcludeTableCFsMap:()Ljava/util/Map;
     612: invokestatic  #49                 // Method org/mockito/Mockito.when:(Ljava/lang/Object;)Lorg/mockito/stubbing/OngoingStubbing;
     615: aload         6
     617: invokeinterface #50,  2           // InterfaceMethod org/mockito/stubbing/OngoingStubbing.thenReturn:(Ljava/lang/Object;)Lorg/mockito/stubbing/OngoingStubbing;
     622: pop
     623: aload_1
     624: invokeinterface #53,  1           // InterfaceMethod org/apache/hadoop/hbase/replication/ReplicationPeer.getPeerConfig:()Lorg/apache/hadoop/hbase/replication/ReplicationPeerConfig;
     629: invokestatic  #49                 // Method org/mockito/Mockito.when:(Ljava/lang/Object;)Lorg/mockito/stubbing/OngoingStubbing;
     632: aload_2
     633: invokeinterface #50,  2           // InterfaceMethod org/mockito/stubbing/OngoingStubbing.thenReturn:(Ljava/lang/Object;)Lorg/mockito/stubbing/OngoingStubbing;
     638: pop
     639: aload_0
     640: aconst_null
     641: iconst_3
     642: anewarray     #28                 // class "[B"
     645: dup
     646: iconst_0
     647: getstatic     #29                 // Field a:[B
     650: aastore
     651: dup
     652: iconst_1
     653: getstatic     #30                 // Field b:[B
     656: aastore
     657: dup
     658: iconst_2
     659: getstatic     #39                 // Field c:[B
     662: aastore
     663: invokespecial #31                 // Method createEntry:(Ljava/util/TreeMap;[[B)Lorg/apache/hadoop/hbase/wal/WAL$Entry;
     666: astore_3
     667: new           #23                 // class org/apache/hadoop/hbase/replication/ChainWALEntryFilter
     670: dup
     671: iconst_1
     672: anewarray     #24                 // class org/apache/hadoop/hbase/replication/WALEntryFilter
     675: dup
     676: iconst_0
     677: new           #54                 // class org/apache/hadoop/hbase/replication/NamespaceTableCfWALEntryFilter
     680: dup
     681: aload_1
     682: invokespecial #55                 // Method org/apache/hadoop/hbase/replication/NamespaceTableCfWALEntryFilter."<init>":(Lorg/apache/hadoop/hbase/replication/ReplicationPeer;)V
     685: aastore
     686: invokespecial #27                 // Method org/apache/hadoop/hbase/replication/ChainWALEntryFilter."<init>":([Lorg/apache/hadoop/hbase/replication/WALEntryFilter;)V
     689: astore        4
     691: aload_0
     692: aload_0
     693: aconst_null
     694: iconst_3
     695: anewarray     #28                 // class "[B"
     698: dup
     699: iconst_0
     700: getstatic     #29                 // Field a:[B
     703: aastore
     704: dup
     705: iconst_1
     706: getstatic     #30                 // Field b:[B
     709: aastore
     710: dup
     711: iconst_2
     712: getstatic     #39                 // Field c:[B
     715: aastore
     716: invokespecial #31                 // Method createEntry:(Ljava/util/TreeMap;[[B)Lorg/apache/hadoop/hbase/wal/WAL$Entry;
     719: aload         4
     721: aload_3
     722: invokevirtual #43                 // Method org/apache/hadoop/hbase/replication/ChainWALEntryFilter.filter:(Lorg/apache/hadoop/hbase/wal/WAL$Entry;)Lorg/apache/hadoop/hbase/wal/WAL$Entry;
     725: invokespecial #22                 // Method assertEquals:(Lorg/apache/hadoop/hbase/wal/WAL$Entry;Lorg/apache/hadoop/hbase/wal/WAL$Entry;)V
     728: new           #56                 // class java/util/HashMap
     731: dup
     732: invokespecial #57                 // Method java/util/HashMap."<init>":()V
     735: astore        6
     737: aload         6
     739: ldc           #58                 // String bar
     741: invokestatic  #21                 // Method org/apache/hadoop/hbase/TableName.valueOf:(Ljava/lang/String;)Lorg/apache/hadoop/hbase/TableName;
     744: aconst_null
     745: invokeinterface #59,  3           // InterfaceMethod java/util/Map.put:(Ljava/lang/Object;Ljava/lang/Object;)Ljava/lang/Object;
     750: pop
     751: aload_2
     752: invokevirtual #72                 // Method org/apache/hadoop/hbase/replication/ReplicationPeerConfig.getExcludeNamespaces:()Ljava/util/Set;
     755: invokestatic  #49                 // Method org/mockito/Mockito.when:(Ljava/lang/Object;)Lorg/mockito/stubbing/OngoingStubbing;
     758: aconst_null
     759: invokeinterface #50,  2           // InterfaceMethod org/mockito/stubbing/OngoingStubbing.thenReturn:(Ljava/lang/Object;)Lorg/mockito/stubbing/OngoingStubbing;
     764: pop
     765: aload_2
     766: invokevirtual #73                 // Method org/apache/hadoop/hbase/replication/ReplicationPeerConfig.getExcludeTableCFsMap:()Ljava/util/Map;
     769: invokestatic  #49                 // Method org/mockito/Mockito.when:(Ljava/lang/Object;)Lorg/mockito/stubbing/OngoingStubbing;
     772: aload         6
     774: invokeinterface #50,  2           // InterfaceMethod org/mockito/stubbing/OngoingStubbing.thenReturn:(Ljava/lang/Object;)Lorg/mockito/stubbing/OngoingStubbing;
     779: pop
     780: aload_1
     781: invokeinterface #53,  1           // InterfaceMethod org/apache/hadoop/hbase/replication/ReplicationPeer.getPeerConfig:()Lorg/apache/hadoop/hbase/replication/ReplicationPeerConfig;
     786: invokestatic  #49                 // Method org/mockito/Mockito.when:(Ljava/lang/Object;)Lorg/mockito/stubbing/OngoingStubbing;
     789: aload_2
     790: invokeinterface #50,  2           // InterfaceMethod org/mockito/stubbing/OngoingStubbing.thenReturn:(Ljava/lang/Object;)Lorg/mockito/stubbing/OngoingStubbing;
     795: pop
     796: aload_0
     797: aconst_null
     798: iconst_3
     799: anewarray     #28                 // class "[B"
     802: dup
     803: iconst_0
     804: getstatic     #29                 // Field a:[B
     807: aastore
     808: dup
     809: iconst_1
     810: getstatic     #30                 // Field b:[B
     813: aastore
     814: dup
     815: iconst_2
     816: getstatic     #39                 // Field c:[B
     819: aastore
     820: invokespecial #31                 // Method createEntry:(Ljava/util/TreeMap;[[B)Lorg/apache/hadoop/hbase/wal/WAL$Entry;
     823: astore_3
     824: new           #23                 // class org/apache/hadoop/hbase/replication/ChainWALEntryFilter
     827: dup
     828: iconst_1
     829: anewarray     #24                 // class org/apache/hadoop/hbase/replication/WALEntryFilter
     832: dup
     833: iconst_0
     834: new           #54                 // class org/apache/hadoop/hbase/replication/NamespaceTableCfWALEntryFilter
     837: dup
     838: aload_1
     839: invokespecial #55                 // Method org/apache/hadoop/hbase/replication/NamespaceTableCfWALEntryFilter."<init>":(Lorg/apache/hadoop/hbase/replication/ReplicationPeer;)V
     842: aastore
     843: invokespecial #27                 // Method org/apache/hadoop/hbase/replication/ChainWALEntryFilter."<init>":([Lorg/apache/hadoop/hbase/replication/WALEntryFilter;)V
     846: astore        4
     848: aload_0
     849: aload_0
     850: aconst_null
     851: iconst_3
     852: anewarray     #28                 // class "[B"
     855: dup
     856: iconst_0
     857: getstatic     #29                 // Field a:[B
     860: aastore
     861: dup
     862: iconst_1
     863: getstatic     #30                 // Field b:[B
     866: aastore
     867: dup
     868: iconst_2
     869: getstatic     #39                 // Field c:[B
     872: aastore
     873: invokespecial #31                 // Method createEntry:(Ljava/util/TreeMap;[[B)Lorg/apache/hadoop/hbase/wal/WAL$Entry;
     876: aload         4
     878: aload_3
     879: invokevirtual #43                 // Method org/apache/hadoop/hbase/replication/ChainWALEntryFilter.filter:(Lorg/apache/hadoop/hbase/wal/WAL$Entry;)Lorg/apache/hadoop/hbase/wal/WAL$Entry;
     882: invokespecial #22                 // Method assertEquals:(Lorg/apache/hadoop/hbase/wal/WAL$Entry;Lorg/apache/hadoop/hbase/wal/WAL$Entry;)V
     885: new           #56                 // class java/util/HashMap
     888: dup
     889: invokespecial #57                 // Method java/util/HashMap."<init>":()V
     892: astore        6
     894: aload         6
     896: ldc           #20                 // String foo
     898: invokestatic  #21                 // Method org/apache/hadoop/hbase/TableName.valueOf:(Ljava/lang/String;)Lorg/apache/hadoop/hbase/TableName;
     901: iconst_1
     902: anewarray     #60                 // class java/lang/String
     905: dup
     906: iconst_0
     907: ldc           #61                 // String a
     909: aastore
     910: invokestatic  #62                 // Method org/apache/hbase/thirdparty/com/google/common/collect/Lists.newArrayList:([Ljava/lang/Object;)Ljava/util/ArrayList;
     913: invokeinterface #59,  3           // InterfaceMethod java/util/Map.put:(Ljava/lang/Object;Ljava/lang/Object;)Ljava/lang/Object;
     918: pop
     919: aload_2
     920: invokevirtual #72                 // Method org/apache/hadoop/hbase/replication/ReplicationPeerConfig.getExcludeNamespaces:()Ljava/util/Set;
     923: invokestatic  #49                 // Method org/mockito/Mockito.when:(Ljava/lang/Object;)Lorg/mockito/stubbing/OngoingStubbing;
     926: aconst_null
     927: invokeinterface #50,  2           // InterfaceMethod org/mockito/stubbing/OngoingStubbing.thenReturn:(Ljava/lang/Object;)Lorg/mockito/stubbing/OngoingStubbing;
     932: pop
     933: aload_2
     934: invokevirtual #73                 // Method org/apache/hadoop/hbase/replication/ReplicationPeerConfig.getExcludeTableCFsMap:()Ljava/util/Map;
     937: invokestatic  #49                 // Method org/mockito/Mockito.when:(Ljava/lang/Object;)Lorg/mockito/stubbing/OngoingStubbing;
     940: aload         6
     942: invokeinterface #50,  2           // InterfaceMethod org/mockito/stubbing/OngoingStubbing.thenReturn:(Ljava/lang/Object;)Lorg/mockito/stubbing/OngoingStubbing;
     947: pop
     948: aload_1
     949: invokeinterface #53,  1           // InterfaceMethod org/apache/hadoop/hbase/replication/ReplicationPeer.getPeerConfig:()Lorg/apache/hadoop/hbase/replication/ReplicationPeerConfig;
     954: invokestatic  #49                 // Method org/mockito/Mockito.when:(Ljava/lang/Object;)Lorg/mockito/stubbing/OngoingStubbing;
     957: aload_2
     958: invokeinterface #50,  2           // InterfaceMethod org/mockito/stubbing/OngoingStubbing.thenReturn:(Ljava/lang/Object;)Lorg/mockito/stubbing/OngoingStubbing;
     963: pop
     964: aload_0
     965: aconst_null
     966: iconst_3
     967: anewarray     #28                 // class "[B"
     970: dup
     971: iconst_0
     972: getstatic     #29                 // Field a:[B
     975: aastore
     976: dup
     977: iconst_1
     978: getstatic     #30                 // Field b:[B
     981: aastore
     982: dup
     983: iconst_2
     984: getstatic     #39                 // Field c:[B
     987: aastore
     988: invokespecial #31                 // Method createEntry:(Ljava/util/TreeMap;[[B)Lorg/apache/hadoop/hbase/wal/WAL$Entry;
     991: astore_3
     992: new           #23                 // class org/apache/hadoop/hbase/replication/ChainWALEntryFilter
     995: dup
     996: iconst_1
     997: anewarray     #24                 // class org/apache/hadoop/hbase/replication/WALEntryFilter
    1000: dup
    1001: iconst_0
    1002: new           #54                 // class org/apache/hadoop/hbase/replication/NamespaceTableCfWALEntryFilter
    1005: dup
    1006: aload_1
    1007: invokespecial #55                 // Method org/apache/hadoop/hbase/replication/NamespaceTableCfWALEntryFilter."<init>":(Lorg/apache/hadoop/hbase/replication/ReplicationPeer;)V
    1010: aastore
    1011: invokespecial #27                 // Method org/apache/hadoop/hbase/replication/ChainWALEntryFilter."<init>":([Lorg/apache/hadoop/hbase/replication/WALEntryFilter;)V
    1014: astore        4
    1016: aload_0
    1017: aload_0
    1018: aconst_null
    1019: iconst_2
    1020: anewarray     #28                 // class "[B"
    1023: dup
    1024: iconst_0
    1025: getstatic     #30                 // Field b:[B
    1028: aastore
    1029: dup
    1030: iconst_1
    1031: getstatic     #39                 // Field c:[B
    1034: aastore
    1035: invokespecial #31                 // Method createEntry:(Ljava/util/TreeMap;[[B)Lorg/apache/hadoop/hbase/wal/WAL$Entry;
    1038: aload         4
    1040: aload_3
    1041: invokevirtual #43                 // Method org/apache/hadoop/hbase/replication/ChainWALEntryFilter.filter:(Lorg/apache/hadoop/hbase/wal/WAL$Entry;)Lorg/apache/hadoop/hbase/wal/WAL$Entry;
    1044: invokespecial #22                 // Method assertEquals:(Lorg/apache/hadoop/hbase/wal/WAL$Entry;Lorg/apache/hadoop/hbase/wal/WAL$Entry;)V
    1047: new           #66                 // class java/util/HashSet
    1050: dup
    1051: invokespecial #67                 // Method java/util/HashSet."<init>":()V
    1054: astore        5
    1056: new           #56                 // class java/util/HashMap
    1059: dup
    1060: invokespecial #57                 // Method java/util/HashMap."<init>":()V
    1063: astore        6
    1065: aload         5
    1067: ldc           #70                 // String ns1
    1069: invokeinterface #69,  2           // InterfaceMethod java/util/Set.add:(Ljava/lang/Object;)Z
    1074: pop
    1075: aload         6
    1077: ldc           #20                 // String foo
    1079: invokestatic  #21                 // Method org/apache/hadoop/hbase/TableName.valueOf:(Ljava/lang/String;)Lorg/apache/hadoop/hbase/TableName;
    1082: iconst_2
    1083: anewarray     #60                 // class java/lang/String
    1086: dup
    1087: iconst_0
    1088: ldc           #61                 // String a
    1090: aastore
    1091: dup
    1092: iconst_1
    1093: ldc           #64                 // String c
    1095: aastore
    1096: invokestatic  #62                 // Method org/apache/hbase/thirdparty/com/google/common/collect/Lists.newArrayList:([Ljava/lang/Object;)Ljava/util/ArrayList;
    1099: invokeinterface #59,  3           // InterfaceMethod java/util/Map.put:(Ljava/lang/Object;Ljava/lang/Object;)Ljava/lang/Object;
    1104: pop
    1105: aload_2
    1106: invokevirtual #72                 // Method org/apache/hadoop/hbase/replication/ReplicationPeerConfig.getExcludeNamespaces:()Ljava/util/Set;
    1109: invokestatic  #49                 // Method org/mockito/Mockito.when:(Ljava/lang/Object;)Lorg/mockito/stubbing/OngoingStubbing;
    1112: aload         5
    1114: invokeinterface #50,  2           // InterfaceMethod org/mockito/stubbing/OngoingStubbing.thenReturn:(Ljava/lang/Object;)Lorg/mockito/stubbing/OngoingStubbing;
    1119: pop
    1120: aload_2
    1121: invokevirtual #73                 // Method org/apache/hadoop/hbase/replication/ReplicationPeerConfig.getExcludeTableCFsMap:()Ljava/util/Map;
    1124: invokestatic  #49                 // Method org/mockito/Mockito.when:(Ljava/lang/Object;)Lorg/mockito/stubbing/OngoingStubbing;
    1127: aload         6
    1129: invokeinterface #50,  2           // InterfaceMethod org/mockito/stubbing/OngoingStubbing.thenReturn:(Ljava/lang/Object;)Lorg/mockito/stubbing/OngoingStubbing;
    1134: pop
    1135: aload_1
    1136: invokeinterface #53,  1           // InterfaceMethod org/apache/hadoop/hbase/replication/ReplicationPeer.getPeerConfig:()Lorg/apache/hadoop/hbase/replication/ReplicationPeerConfig;
    1141: invokestatic  #49                 // Method org/mockito/Mockito.when:(Ljava/lang/Object;)Lorg/mockito/stubbing/OngoingStubbing;
    1144: aload_2
    1145: invokeinterface #50,  2           // InterfaceMethod org/mockito/stubbing/OngoingStubbing.thenReturn:(Ljava/lang/Object;)Lorg/mockito/stubbing/OngoingStubbing;
    1150: pop
    1151: aload_0
    1152: aconst_null
    1153: iconst_3
    1154: anewarray     #28                 // class "[B"
    1157: dup
    1158: iconst_0
    1159: getstatic     #29                 // Field a:[B
    1162: aastore
    1163: dup
    1164: iconst_1
    1165: getstatic     #30                 // Field b:[B
    1168: aastore
    1169: dup
    1170: iconst_2
    1171: getstatic     #39                 // Field c:[B
    1174: aastore
    1175: invokespecial #31                 // Method createEntry:(Ljava/util/TreeMap;[[B)Lorg/apache/hadoop/hbase/wal/WAL$Entry;
    1178: astore_3
    1179: new           #23                 // class org/apache/hadoop/hbase/replication/ChainWALEntryFilter
    1182: dup
    1183: iconst_1
    1184: anewarray     #24                 // class org/apache/hadoop/hbase/replication/WALEntryFilter
    1187: dup
    1188: iconst_0
    1189: new           #54                 // class org/apache/hadoop/hbase/replication/NamespaceTableCfWALEntryFilter
    1192: dup
    1193: aload_1
    1194: invokespecial #55                 // Method org/apache/hadoop/hbase/replication/NamespaceTableCfWALEntryFilter."<init>":(Lorg/apache/hadoop/hbase/replication/ReplicationPeer;)V
    1197: aastore
    1198: invokespecial #27                 // Method org/apache/hadoop/hbase/replication/ChainWALEntryFilter."<init>":([Lorg/apache/hadoop/hbase/replication/WALEntryFilter;)V
    1201: astore        4
    1203: aload_0
    1204: aload_0
    1205: aconst_null
    1206: iconst_1
    1207: anewarray     #28                 // class "[B"
    1210: dup
    1211: iconst_0
    1212: getstatic     #30                 // Field b:[B
    1215: aastore
    1216: invokespecial #31                 // Method createEntry:(Ljava/util/TreeMap;[[B)Lorg/apache/hadoop/hbase/wal/WAL$Entry;
    1219: aload         4
    1221: aload_3
    1222: invokevirtual #43                 // Method org/apache/hadoop/hbase/replication/ChainWALEntryFilter.filter:(Lorg/apache/hadoop/hbase/wal/WAL$Entry;)Lorg/apache/hadoop/hbase/wal/WAL$Entry;
    1225: invokespecial #22                 // Method assertEquals:(Lorg/apache/hadoop/hbase/wal/WAL$Entry;Lorg/apache/hadoop/hbase/wal/WAL$Entry;)V
    1228: new           #66                 // class java/util/HashSet
    1231: dup
    1232: invokespecial #67                 // Method java/util/HashSet."<init>":()V
    1235: astore        5
    1237: new           #56                 // class java/util/HashMap
    1240: dup
    1241: invokespecial #57                 // Method java/util/HashMap."<init>":()V
    1244: astore        6
    1246: aload         5
    1248: ldc           #68                 // String default
    1250: invokeinterface #69,  2           // InterfaceMethod java/util/Set.add:(Ljava/lang/Object;)Z
    1255: pop
    1256: aload         6
    1258: ldc           #74                 // String ns1:bar
    1260: invokestatic  #21                 // Method org/apache/hadoop/hbase/TableName.valueOf:(Ljava/lang/String;)Lorg/apache/hadoop/hbase/TableName;
    1263: new           #75                 // class java/util/ArrayList
    1266: dup
    1267: invokespecial #76                 // Method java/util/ArrayList."<init>":()V
    1270: invokeinterface #59,  3           // InterfaceMethod java/util/Map.put:(Ljava/lang/Object;Ljava/lang/Object;)Ljava/lang/Object;
    1275: pop
    1276: aload_2
    1277: invokevirtual #72                 // Method org/apache/hadoop/hbase/replication/ReplicationPeerConfig.getExcludeNamespaces:()Ljava/util/Set;
    1280: invokestatic  #49                 // Method org/mockito/Mockito.when:(Ljava/lang/Object;)Lorg/mockito/stubbing/OngoingStubbing;
    1283: aload         5
    1285: invokeinterface #50,  2           // InterfaceMethod org/mockito/stubbing/OngoingStubbing.thenReturn:(Ljava/lang/Object;)Lorg/mockito/stubbing/OngoingStubbing;
    1290: pop
    1291: aload_2
    1292: invokevirtual #73                 // Method org/apache/hadoop/hbase/replication/ReplicationPeerConfig.getExcludeTableCFsMap:()Ljava/util/Map;
    1295: invokestatic  #49                 // Method org/mockito/Mockito.when:(Ljava/lang/Object;)Lorg/mockito/stubbing/OngoingStubbing;
    1298: aload         6
    1300: invokeinterface #50,  2           // InterfaceMethod org/mockito/stubbing/OngoingStubbing.thenReturn:(Ljava/lang/Object;)Lorg/mockito/stubbing/OngoingStubbing;
    1305: pop
    1306: aload_1
    1307: invokeinterface #53,  1           // InterfaceMethod org/apache/hadoop/hbase/replication/ReplicationPeer.getPeerConfig:()Lorg/apache/hadoop/hbase/replication/ReplicationPeerConfig;
    1312: invokestatic  #49                 // Method org/mockito/Mockito.when:(Ljava/lang/Object;)Lorg/mockito/stubbing/OngoingStubbing;
    1315: aload_2
    1316: invokeinterface #50,  2           // InterfaceMethod org/mockito/stubbing/OngoingStubbing.thenReturn:(Ljava/lang/Object;)Lorg/mockito/stubbing/OngoingStubbing;
    1321: pop
    1322: aload_0
    1323: aconst_null
    1324: iconst_3
    1325: anewarray     #28                 // class "[B"
    1328: dup
    1329: iconst_0
    1330: getstatic     #29                 // Field a:[B
    1333: aastore
    1334: dup
    1335: iconst_1
    1336: getstatic     #30                 // Field b:[B
    1339: aastore
    1340: dup
    1341: iconst_2
    1342: getstatic     #39                 // Field c:[B
    1345: aastore
    1346: invokespecial #31                 // Method createEntry:(Ljava/util/TreeMap;[[B)Lorg/apache/hadoop/hbase/wal/WAL$Entry;
    1349: astore_3
    1350: new           #23                 // class org/apache/hadoop/hbase/replication/ChainWALEntryFilter
    1353: dup
    1354: iconst_1
    1355: anewarray     #24                 // class org/apache/hadoop/hbase/replication/WALEntryFilter
    1358: dup
    1359: iconst_0
    1360: new           #54                 // class org/apache/hadoop/hbase/replication/NamespaceTableCfWALEntryFilter
    1363: dup
    1364: aload_1
    1365: invokespecial #55                 // Method org/apache/hadoop/hbase/replication/NamespaceTableCfWALEntryFilter."<init>":(Lorg/apache/hadoop/hbase/replication/ReplicationPeer;)V
    1368: aastore
    1369: invokespecial #27                 // Method org/apache/hadoop/hbase/replication/ChainWALEntryFilter."<init>":([Lorg/apache/hadoop/hbase/replication/WALEntryFilter;)V
    1372: astore        4
    1374: aload_0
    1375: aconst_null
    1376: aload         4
    1378: aload_3
    1379: invokevirtual #43                 // Method org/apache/hadoop/hbase/replication/ChainWALEntryFilter.filter:(Lorg/apache/hadoop/hbase/wal/WAL$Entry;)Lorg/apache/hadoop/hbase/wal/WAL$Entry;
    1382: invokespecial #22                 // Method assertEquals:(Lorg/apache/hadoop/hbase/wal/WAL$Entry;Lorg/apache/hadoop/hbase/wal/WAL$Entry;)V
    1385: return

  static {};
    Code:
       0: ldc           #91                 // class org/apache/hadoop/hbase/replication/TestReplicationWALEntryFilters
       2: invokestatic  #92                 // Method org/apache/hadoop/hbase/HBaseClassTestRule.forClass:(Ljava/lang/Class;)Lorg/apache/hadoop/hbase/HBaseClassTestRule;
       5: putstatic     #93                 // Field CLASS_RULE:Lorg/apache/hadoop/hbase/HBaseClassTestRule;
       8: iconst_1
       9: newarray       byte
      11: dup
      12: iconst_0
      13: bipush        97
      15: bastore
      16: putstatic     #29                 // Field a:[B
      19: iconst_1
      20: newarray       byte
      22: dup
      23: iconst_0
      24: bipush        98
      26: bastore
      27: putstatic     #30                 // Field b:[B
      30: iconst_1
      31: newarray       byte
      33: dup
      34: iconst_0
      35: bipush        99
      37: bastore
      38: putstatic     #39                 // Field c:[B
      41: iconst_1
      42: newarray       byte
      44: dup
      45: iconst_0
      46: bipush        100
      48: bastore
      49: putstatic     #63                 // Field d:[B
      52: return
}
