Compiled from "TestClientScannerRPCTimeout.java"
class org.apache.hadoop.hbase.client.TestClientScannerRPCTimeout$RegionServerWithScanTimeout extends org.apache.hadoop.hbase.MiniHBaseCluster$MiniHBaseClusterRegionServer {
  public org.apache.hadoop.hbase.client.TestClientScannerRPCTimeout$RegionServerWithScanTimeout(org.apache.hadoop.conf.Configuration) throws java.io.IOException, java.lang.InterruptedException;
    Code:
       0: aload_0
       1: aload_1
       2: invokespecial #1                  // Method org/apache/hadoop/hbase/MiniHBaseCluster$MiniHBaseClusterRegionServer."<init>":(Lorg/apache/hadoop/conf/Configuration;)V
       5: return

  protected org.apache.hadoop.hbase.regionserver.RSRpcServices createRpcServices() throws java.io.IOException;
    Code:
       0: new           #2                  // class org/apache/hadoop/hbase/client/TestClientScannerRPCTimeout$RSRpcServicesWithScanTimeout
       3: dup
       4: aload_0
       5: invokespecial #3                  // Method org/apache/hadoop/hbase/client/TestClientScannerRPCTimeout$RSRpcServicesWithScanTimeout."<init>":(Lorg/apache/hadoop/hbase/regionserver/HRegionServer;)V
       8: areturn
}
