Compiled from "TestCompactor.java"
class org.apache.hadoop.hbase.regionserver.compactions.TestCompactor$StoreFileWritersCapture$2 implements org.mockito.stubbing.Answer<java.lang.Object> {
  final org.apache.hadoop.hbase.regionserver.compactions.TestCompactor$StoreFileWritersCapture$Writer val$realWriter;

  final org.apache.hadoop.hbase.regionserver.compactions.TestCompactor$StoreFileWritersCapture this$0;

  org.apache.hadoop.hbase.regionserver.compactions.TestCompactor$StoreFileWritersCapture$2(org.apache.hadoop.hbase.regionserver.compactions.TestCompactor$StoreFileWritersCapture, org.apache.hadoop.hbase.regionserver.compactions.TestCompactor$StoreFileWritersCapture$Writer);
    Code:
       0: aload_0
       1: aload_1
       2: putfield      #1                  // Field this$0:Lorg/apache/hadoop/hbase/regionserver/compactions/TestCompactor$StoreFileWritersCapture;
       5: aload_0
       6: aload_2
       7: putfield      #2                  // Field val$realWriter:Lorg/apache/hadoop/hbase/regionserver/compactions/TestCompactor$StoreFileWritersCapture$Writer;
      10: aload_0
      11: invokespecial #3                  // Method java/lang/Object."<init>":()V
      14: return

  public java.lang.Object answer(org.mockito.invocation.InvocationOnMock);
    Code:
       0: aload_1
       1: invokeinterface #4,  1            // InterfaceMethod org/mockito/invocation/InvocationOnMock.getArguments:()[Ljava/lang/Object;
       6: astore_2
       7: aload_0
       8: getfield      #2                  // Field val$realWriter:Lorg/apache/hadoop/hbase/regionserver/compactions/TestCompactor$StoreFileWritersCapture$Writer;
      11: getfield      #5                  // Field org/apache/hadoop/hbase/regionserver/compactions/TestCompactor$StoreFileWritersCapture$Writer.data:Ljava/util/TreeMap;
      14: aload_2
      15: iconst_0
      16: aaload
      17: checkcast     #6                  // class "[B"
      20: checkcast     #6                  // class "[B"
      23: aload_2
      24: iconst_1
      25: aaload
      26: checkcast     #6                  // class "[B"
      29: checkcast     #6                  // class "[B"
      32: invokevirtual #7                  // Method java/util/TreeMap.put:(Ljava/lang/Object;Ljava/lang/Object;)Ljava/lang/Object;
      35: areturn
}
