Compiled from "TestHBaseTestingUtility.java"
class org.apache.hadoop.hbase.TestHBaseTestingUtility$1 implements org.mockito.stubbing.Answer<java.lang.Integer> {
  int[] numbers;

  int count;

  final org.apache.hadoop.hbase.TestHBaseTestingUtility this$0;

  org.apache.hadoop.hbase.TestHBaseTestingUtility$1(org.apache.hadoop.hbase.TestHBaseTestingUtility);
    Code:
       0: aload_0
       1: aload_1
       2: putfield      #1                  // Field this$0:Lorg/apache/hadoop/hbase/TestHBaseTestingUtility;
       5: aload_0
       6: invokespecial #2                  // Method java/lang/Object."<init>":()V
       9: aload_0
      10: iconst_3
      11: newarray       int
      13: dup
      14: iconst_0
      15: iconst_1
      16: iastore
      17: dup
      18: iconst_1
      19: iconst_1
      20: iastore
      21: dup
      22: iconst_2
      23: iconst_2
      24: iastore
      25: putfield      #3                  // Field numbers:[I
      28: aload_0
      29: iconst_0
      30: putfield      #4                  // Field count:I
      33: return

  public java.lang.Integer answer(org.mockito.invocation.InvocationOnMock);
    Code:
       0: aload_0
       1: getfield      #3                  // Field numbers:[I
       4: aload_0
       5: getfield      #4                  // Field count:I
       8: iaload
       9: istore_2
      10: aload_0
      11: dup
      12: getfield      #4                  // Field count:I
      15: iconst_1
      16: iadd
      17: putfield      #4                  // Field count:I
      20: iload_2
      21: invokestatic  #5                  // Method java/lang/Integer.valueOf:(I)Ljava/lang/Integer;
      24: areturn

  public java.lang.Object answer(org.mockito.invocation.InvocationOnMock) throws java.lang.Throwable;
    Code:
       0: aload_0
       1: aload_1
       2: invokevirtual #6                  // Method answer:(Lorg/mockito/invocation/InvocationOnMock;)Ljava/lang/Integer;
       5: areturn
}
