Compiled from "TestProcedureSkipPersistence.java"
public class org.apache.hadoop.hbase.procedure2.TestProcedureSkipPersistence$TestProcedure extends org.apache.hadoop.hbase.procedure2.Procedure<org.apache.hadoop.hbase.procedure2.TestProcedureSkipPersistence$ProcEnv> {
  public org.apache.hadoop.hbase.procedure2.TestProcedureSkipPersistence$TestProcedure();
    Code:
       0: aload_0
       1: invokespecial #1                  // Method org/apache/hadoop/hbase/procedure2/Procedure."<init>":()V
       4: return

  protected boolean holdLock(org.apache.hadoop.hbase.procedure2.TestProcedureSkipPersistence$ProcEnv);
    Code:
       0: iconst_1
       1: ireturn

  protected org.apache.hadoop.hbase.procedure2.Procedure<org.apache.hadoop.hbase.procedure2.TestProcedureSkipPersistence$ProcEnv>[] execute(org.apache.hadoop.hbase.procedure2.TestProcedureSkipPersistence$ProcEnv) throws org.apache.hadoop.hbase.procedure2.ProcedureYieldException, org.apache.hadoop.hbase.procedure2.ProcedureSuspendedException, java.lang.InterruptedException;
    Code:
       0: invokestatic  #2                  // Method org/apache/hadoop/hbase/procedure2/TestProcedureSkipPersistence.access$100:()I
       3: ifne          36
       6: iconst_1
       7: invokestatic  #3                  // Method org/apache/hadoop/hbase/procedure2/TestProcedureSkipPersistence.access$102:(I)I
      10: pop
      11: aload_0
      12: ldc           #4                  // int 3600000
      14: invokevirtual #5                  // Method setTimeout:(I)V
      17: aload_0
      18: getstatic     #6                  // Field org/apache/hadoop/hbase/shaded/protobuf/generated/ProcedureProtos$ProcedureState.WAITING_TIMEOUT:Lorg/apache/hadoop/hbase/shaded/protobuf/generated/ProcedureProtos$ProcedureState;
      21: invokevirtual #7                  // Method setState:(Lorg/apache/hadoop/hbase/shaded/protobuf/generated/ProcedureProtos$ProcedureState;)V
      24: aload_0
      25: invokevirtual #8                  // Method skipPersistence:()V
      28: new           #9                  // class org/apache/hadoop/hbase/procedure2/ProcedureSuspendedException
      31: dup
      32: invokespecial #10                 // Method org/apache/hadoop/hbase/procedure2/ProcedureSuspendedException."<init>":()V
      35: athrow
      36: invokestatic  #2                  // Method org/apache/hadoop/hbase/procedure2/TestProcedureSkipPersistence.access$100:()I
      39: iconst_1
      40: if_icmpne     94
      43: iconst_2
      44: invokestatic  #3                  // Method org/apache/hadoop/hbase/procedure2/TestProcedureSkipPersistence.access$102:(I)I
      47: pop
      48: aload_0
      49: invokevirtual #11                 // Method hasTimeout:()Z
      52: ifeq          72
      55: aload_0
      56: ldc           #12                 // String Should not persist the timeout value
      58: new           #13                 // class java/io/IOException
      61: dup
      62: ldc           #12                 // String Should not persist the timeout value
      64: invokespecial #14                 // Method java/io/IOException."<init>":(Ljava/lang/String;)V
      67: invokevirtual #15                 // Method setFailure:(Ljava/lang/String;Ljava/lang/Throwable;)V
      70: aconst_null
      71: areturn
      72: aload_0
      73: sipush        2000
      76: invokevirtual #5                  // Method setTimeout:(I)V
      79: aload_0
      80: getstatic     #6                  // Field org/apache/hadoop/hbase/shaded/protobuf/generated/ProcedureProtos$ProcedureState.WAITING_TIMEOUT:Lorg/apache/hadoop/hbase/shaded/protobuf/generated/ProcedureProtos$ProcedureState;
      83: invokevirtual #7                  // Method setState:(Lorg/apache/hadoop/hbase/shaded/protobuf/generated/ProcedureProtos$ProcedureState;)V
      86: new           #9                  // class org/apache/hadoop/hbase/procedure2/ProcedureSuspendedException
      89: dup
      90: invokespecial #10                 // Method org/apache/hadoop/hbase/procedure2/ProcedureSuspendedException."<init>":()V
      93: athrow
      94: aload_0
      95: invokevirtual #11                 // Method hasTimeout:()Z
      98: ifne          116
     101: aload_0
     102: ldc           #16                 // String Should have persisted the timeout value
     104: new           #13                 // class java/io/IOException
     107: dup
     108: ldc           #16                 // String Should have persisted the timeout value
     110: invokespecial #14                 // Method java/io/IOException."<init>":(Ljava/lang/String;)V
     113: invokevirtual #15                 // Method setFailure:(Ljava/lang/String;Ljava/lang/Throwable;)V
     116: aconst_null
     117: areturn

  protected synchronized boolean setTimeoutFailure(org.apache.hadoop.hbase.procedure2.TestProcedureSkipPersistence$ProcEnv);
    Code:
       0: aload_0
       1: getstatic     #17                 // Field org/apache/hadoop/hbase/shaded/protobuf/generated/ProcedureProtos$ProcedureState.RUNNABLE:Lorg/apache/hadoop/hbase/shaded/protobuf/generated/ProcedureProtos$ProcedureState;
       4: invokevirtual #7                  // Method setState:(Lorg/apache/hadoop/hbase/shaded/protobuf/generated/ProcedureProtos$ProcedureState;)V
       7: aload_1
       8: invokevirtual #18                 // Method org/apache/hadoop/hbase/procedure2/TestProcedureSkipPersistence$ProcEnv.getProcedureExecutor:()Lorg/apache/hadoop/hbase/procedure2/ProcedureExecutor;
      11: invokevirtual #19                 // Method org/apache/hadoop/hbase/procedure2/ProcedureExecutor.getProcedureScheduler:()Lorg/apache/hadoop/hbase/procedure2/ProcedureScheduler;
      14: aload_0
      15: invokeinterface #20,  2           // InterfaceMethod org/apache/hadoop/hbase/procedure2/ProcedureScheduler.addFront:(Lorg/apache/hadoop/hbase/procedure2/Procedure;)V
      20: iconst_0
      21: ireturn

  protected void rollback(org.apache.hadoop.hbase.procedure2.TestProcedureSkipPersistence$ProcEnv) throws java.io.IOException, java.lang.InterruptedException;
    Code:
       0: new           #21                 // class java/lang/UnsupportedOperationException
       3: dup
       4: invokespecial #22                 // Method java/lang/UnsupportedOperationException."<init>":()V
       7: athrow

  protected boolean abort(org.apache.hadoop.hbase.procedure2.TestProcedureSkipPersistence$ProcEnv);
    Code:
       0: iconst_0
       1: ireturn

  protected void serializeStateData(org.apache.hadoop.hbase.procedure2.ProcedureStateSerializer) throws java.io.IOException;
    Code:
       0: return

  protected void deserializeStateData(org.apache.hadoop.hbase.procedure2.ProcedureStateSerializer) throws java.io.IOException;
    Code:
       0: return

  protected boolean setTimeoutFailure(java.lang.Object);
    Code:
       0: aload_0
       1: aload_1
       2: checkcast     #23                 // class org/apache/hadoop/hbase/procedure2/TestProcedureSkipPersistence$ProcEnv
       5: invokevirtual #24                 // Method setTimeoutFailure:(Lorg/apache/hadoop/hbase/procedure2/TestProcedureSkipPersistence$ProcEnv;)Z
       8: ireturn

  protected boolean holdLock(java.lang.Object);
    Code:
       0: aload_0
       1: aload_1
       2: checkcast     #23                 // class org/apache/hadoop/hbase/procedure2/TestProcedureSkipPersistence$ProcEnv
       5: invokevirtual #25                 // Method holdLock:(Lorg/apache/hadoop/hbase/procedure2/TestProcedureSkipPersistence$ProcEnv;)Z
       8: ireturn

  protected boolean abort(java.lang.Object);
    Code:
       0: aload_0
       1: aload_1
       2: checkcast     #23                 // class org/apache/hadoop/hbase/procedure2/TestProcedureSkipPersistence$ProcEnv
       5: invokevirtual #26                 // Method abort:(Lorg/apache/hadoop/hbase/procedure2/TestProcedureSkipPersistence$ProcEnv;)Z
       8: ireturn

  protected void rollback(java.lang.Object) throws java.io.IOException, java.lang.InterruptedException;
    Code:
       0: aload_0
       1: aload_1
       2: checkcast     #23                 // class org/apache/hadoop/hbase/procedure2/TestProcedureSkipPersistence$ProcEnv
       5: invokevirtual #27                 // Method rollback:(Lorg/apache/hadoop/hbase/procedure2/TestProcedureSkipPersistence$ProcEnv;)V
       8: return

  protected org.apache.hadoop.hbase.procedure2.Procedure[] execute(java.lang.Object) throws org.apache.hadoop.hbase.procedure2.ProcedureYieldException, org.apache.hadoop.hbase.procedure2.ProcedureSuspendedException, java.lang.InterruptedException;
    Code:
       0: aload_0
       1: aload_1
       2: checkcast     #23                 // class org/apache/hadoop/hbase/procedure2/TestProcedureSkipPersistence$ProcEnv
       5: invokevirtual #28                 // Method execute:(Lorg/apache/hadoop/hbase/procedure2/TestProcedureSkipPersistence$ProcEnv;)[Lorg/apache/hadoop/hbase/procedure2/Procedure;
       8: areturn
}
