Compiled from "TestProcedureReplayOrder.java"
class org.apache.hadoop.hbase.procedure2.TestProcedureReplayOrder$1 extends java.lang.Thread {
  final int val$nprocPerThread;

  final java.lang.Class val$procClazz;

  final org.apache.hadoop.hbase.procedure2.TestProcedureReplayOrder this$0;

  org.apache.hadoop.hbase.procedure2.TestProcedureReplayOrder$1(org.apache.hadoop.hbase.procedure2.TestProcedureReplayOrder, int, java.lang.Class);
    Code:
       0: aload_0
       1: aload_1
       2: putfield      #1                  // Field this$0:Lorg/apache/hadoop/hbase/procedure2/TestProcedureReplayOrder;
       5: aload_0
       6: iload_2
       7: putfield      #2                  // Field val$nprocPerThread:I
      10: aload_0
      11: aload_3
      12: putfield      #3                  // Field val$procClazz:Ljava/lang/Class;
      15: aload_0
      16: invokespecial #4                  // Method java/lang/Thread."<init>":()V
      19: return

  public void run();
    Code:
       0: iconst_0
       1: istore_1
       2: iload_1
       3: aload_0
       4: getfield      #2                  // Field val$nprocPerThread:I
       7: if_icmpge     88
      10: aload_0
      11: getfield      #1                  // Field this$0:Lorg/apache/hadoop/hbase/procedure2/TestProcedureReplayOrder;
      14: invokestatic  #5                  // Method org/apache/hadoop/hbase/procedure2/TestProcedureReplayOrder.access$100:(Lorg/apache/hadoop/hbase/procedure2/TestProcedureReplayOrder;)Lorg/apache/hadoop/hbase/procedure2/ProcedureExecutor;
      17: aload_0
      18: getfield      #3                  // Field val$procClazz:Ljava/lang/Class;
      21: iconst_0
      22: anewarray     #6                  // class java/lang/Class
      25: invokevirtual #7                  // Method java/lang/Class.getDeclaredConstructor:([Ljava/lang/Class;)Ljava/lang/reflect/Constructor;
      28: iconst_0
      29: anewarray     #8                  // class java/lang/Object
      32: invokevirtual #9                  // Method java/lang/reflect/Constructor.newInstance:([Ljava/lang/Object;)Ljava/lang/Object;
      35: checkcast     #10                 // class org/apache/hadoop/hbase/procedure2/Procedure
      38: invokevirtual #11                 // Method org/apache/hadoop/hbase/procedure2/ProcedureExecutor.submitProcedure:(Lorg/apache/hadoop/hbase/procedure2/Procedure;)J
      41: pop2
      42: goto          82
      45: astore_2
      46: invokestatic  #13                 // Method org/apache/hadoop/hbase/procedure2/TestProcedureReplayOrder.access$200:()Lorg/slf4j/Logger;
      49: ldc           #14                 // String unable to instantiate the procedure
      51: aload_2
      52: invokeinterface #15,  3           // InterfaceMethod org/slf4j/Logger.error:(Ljava/lang/String;Ljava/lang/Throwable;)V
      57: new           #16                 // class java/lang/StringBuilder
      60: dup
      61: invokespecial #17                 // Method java/lang/StringBuilder."<init>":()V
      64: ldc           #18                 // String failure during the proc.newInstance():
      66: invokevirtual #19                 // Method java/lang/StringBuilder.append:(Ljava/lang/String;)Ljava/lang/StringBuilder;
      69: aload_2
      70: invokevirtual #20                 // Method java/lang/Exception.getMessage:()Ljava/lang/String;
      73: invokevirtual #19                 // Method java/lang/StringBuilder.append:(Ljava/lang/String;)Ljava/lang/StringBuilder;
      76: invokevirtual #21                 // Method java/lang/StringBuilder.toString:()Ljava/lang/String;
      79: invokestatic  #22                 // Method org/junit/Assert.fail:(Ljava/lang/String;)V
      82: iinc          1, 1
      85: goto          2
      88: return
    Exception table:
       from    to  target type
          10    42    45   Class java/lang/Exception
}
