Compiled from "TestClientTimeouts.java"
public class org.apache.hadoop.hbase.client.TestClientTimeouts {
  public static final org.apache.hadoop.hbase.HBaseClassTestRule CLASS_RULE;

  protected static int SLAVES;

  public org.apache.hadoop.hbase.client.TestClientTimeouts();
    Code:
       0: aload_0
       1: invokespecial #1                  // Method java/lang/Object."<init>":()V
       4: return

  public static void setUpBeforeClass() throws java.lang.Exception;
    Code:
       0: getstatic     #2                  // Field TEST_UTIL:Lorg/apache/hadoop/hbase/HBaseTestingUtility;
       3: getstatic     #3                  // Field SLAVES:I
       6: invokevirtual #4                  // Method org/apache/hadoop/hbase/HBaseTestingUtility.startMiniCluster:(I)Lorg/apache/hadoop/hbase/MiniHBaseCluster;
       9: pop
      10: getstatic     #2                  // Field TEST_UTIL:Lorg/apache/hadoop/hbase/HBaseTestingUtility;
      13: invokevirtual #5                  // Method org/apache/hadoop/hbase/HBaseTestingUtility.getConfiguration:()Lorg/apache/hadoop/conf/Configuration;
      16: ldc           #7                  // String hbase.rpc.client.impl
      18: ldc           #8                  // class org/apache/hadoop/hbase/client/TestClientTimeouts$RandomTimeoutRpcClient
      20: invokevirtual #9                  // Method java/lang/Class.getName:()Ljava/lang/String;
      23: invokevirtual #10                 // Method org/apache/hadoop/conf/Configuration.set:(Ljava/lang/String;Ljava/lang/String;)V
      26: return

  public static void tearDownAfterClass() throws java.lang.Exception;
    Code:
       0: getstatic     #2                  // Field TEST_UTIL:Lorg/apache/hadoop/hbase/HBaseTestingUtility;
       3: invokevirtual #11                 // Method org/apache/hadoop/hbase/HBaseTestingUtility.shutdownMiniCluster:()V
       6: return

  public void testAdminTimeout() throws java.lang.Exception;
    Code:
       0: iconst_0
       1: istore_1
       2: invokestatic  #12                 // Method org/apache/hadoop/hbase/client/TestClientTimeouts$RandomTimeoutBlockingRpcChannel.access$000:()Ljava/util/concurrent/atomic/AtomicInteger;
       5: invokevirtual #13                 // Method java/util/concurrent/atomic/AtomicInteger.get:()I
       8: istore_2
       9: getstatic     #2                  // Field TEST_UTIL:Lorg/apache/hadoop/hbase/HBaseTestingUtility;
      12: invokevirtual #5                  // Method org/apache/hadoop/hbase/HBaseTestingUtility.getConfiguration:()Lorg/apache/hadoop/conf/Configuration;
      15: getstatic     #2                  // Field TEST_UTIL:Lorg/apache/hadoop/hbase/HBaseTestingUtility;
      18: invokevirtual #14                 // Method org/apache/hadoop/hbase/HBaseTestingUtility.getClusterKey:()Ljava/lang/String;
      21: invokestatic  #15                 // Method org/apache/hadoop/hbase/ipc/RpcClientFactory.createClient:(Lorg/apache/hadoop/conf/Configuration;Ljava/lang/String;)Lorg/apache/hadoop/hbase/ipc/RpcClient;
      24: checkcast     #8                  // class org/apache/hadoop/hbase/client/TestClientTimeouts$RandomTimeoutRpcClient
      27: astore_3
      28: iconst_0
      29: istore        4
      31: iload         4
      33: iconst_5
      34: if_icmplt     48
      37: iload_1
      38: ifeq          304
      41: iload         4
      43: bipush        100
      45: if_icmpge     304
      48: iconst_0
      49: istore_1
      50: getstatic     #2                  // Field TEST_UTIL:Lorg/apache/hadoop/hbase/HBaseTestingUtility;
      53: invokevirtual #5                  // Method org/apache/hadoop/hbase/HBaseTestingUtility.getConfiguration:()Lorg/apache/hadoop/conf/Configuration;
      56: invokestatic  #16                 // Method org/apache/hadoop/hbase/HBaseConfiguration.create:(Lorg/apache/hadoop/conf/Configuration;)Lorg/apache/hadoop/conf/Configuration;
      59: astore        5
      61: aload         5
      63: ldc           #18                 // String hbase.client.instance.id
      65: iconst_m1
      66: invokestatic  #19                 // Method java/lang/String.valueOf:(I)Ljava/lang/String;
      69: invokevirtual #10                 // Method org/apache/hadoop/conf/Configuration.set:(Ljava/lang/String;Ljava/lang/String;)V
      72: aconst_null
      73: astore        6
      75: aconst_null
      76: astore        7
      78: aload         5
      80: invokestatic  #20                 // Method org/apache/hadoop/hbase/client/ConnectionFactory.createConnection:(Lorg/apache/hadoop/conf/Configuration;)Lorg/apache/hadoop/hbase/client/Connection;
      83: astore        7
      85: aload         7
      87: invokeinterface #21,  1           // InterfaceMethod org/apache/hadoop/hbase/client/Connection.getAdmin:()Lorg/apache/hadoop/hbase/client/Admin;
      92: astore        6
      94: aload         5
      96: invokestatic  #22                 // Method org/apache/hadoop/hbase/client/HBaseAdmin.available:(Lorg/apache/hadoop/conf/Configuration;)V
      99: aload         6
     101: iconst_0
     102: iconst_0
     103: invokeinterface #23,  3           // InterfaceMethod org/apache/hadoop/hbase/client/Admin.balancerSwitch:(ZZ)Z
     108: pop
     109: aload         6
     111: ifnull        155
     114: aload         6
     116: invokeinterface #24,  1           // InterfaceMethod org/apache/hadoop/hbase/client/Admin.close:()V
     121: aload         6
     123: invokeinterface #25,  1           // InterfaceMethod org/apache/hadoop/hbase/client/Admin.getConnection:()Lorg/apache/hadoop/hbase/client/Connection;
     128: invokeinterface #26,  1           // InterfaceMethod org/apache/hadoop/hbase/client/Connection.isClosed:()Z
     133: ifeq          155
     136: getstatic     #2                  // Field TEST_UTIL:Lorg/apache/hadoop/hbase/HBaseTestingUtility;
     139: invokevirtual #5                  // Method org/apache/hadoop/hbase/HBaseTestingUtility.getConfiguration:()Lorg/apache/hadoop/conf/Configuration;
     142: getstatic     #2                  // Field TEST_UTIL:Lorg/apache/hadoop/hbase/HBaseTestingUtility;
     145: invokevirtual #14                 // Method org/apache/hadoop/hbase/HBaseTestingUtility.getClusterKey:()Ljava/lang/String;
     148: invokestatic  #15                 // Method org/apache/hadoop/hbase/ipc/RpcClientFactory.createClient:(Lorg/apache/hadoop/conf/Configuration;Ljava/lang/String;)Lorg/apache/hadoop/hbase/ipc/RpcClient;
     151: checkcast     #8                  // class org/apache/hadoop/hbase/client/TestClientTimeouts$RandomTimeoutRpcClient
     154: astore_3
     155: aload         7
     157: ifnull        298
     160: aload         7
     162: invokeinterface #27,  1           // InterfaceMethod org/apache/hadoop/hbase/client/Connection.close:()V
     167: goto          298
     170: astore        8
     172: iconst_1
     173: istore_1
     174: aload         6
     176: ifnull        220
     179: aload         6
     181: invokeinterface #24,  1           // InterfaceMethod org/apache/hadoop/hbase/client/Admin.close:()V
     186: aload         6
     188: invokeinterface #25,  1           // InterfaceMethod org/apache/hadoop/hbase/client/Admin.getConnection:()Lorg/apache/hadoop/hbase/client/Connection;
     193: invokeinterface #26,  1           // InterfaceMethod org/apache/hadoop/hbase/client/Connection.isClosed:()Z
     198: ifeq          220
     201: getstatic     #2                  // Field TEST_UTIL:Lorg/apache/hadoop/hbase/HBaseTestingUtility;
     204: invokevirtual #5                  // Method org/apache/hadoop/hbase/HBaseTestingUtility.getConfiguration:()Lorg/apache/hadoop/conf/Configuration;
     207: getstatic     #2                  // Field TEST_UTIL:Lorg/apache/hadoop/hbase/HBaseTestingUtility;
     210: invokevirtual #14                 // Method org/apache/hadoop/hbase/HBaseTestingUtility.getClusterKey:()Ljava/lang/String;
     213: invokestatic  #15                 // Method org/apache/hadoop/hbase/ipc/RpcClientFactory.createClient:(Lorg/apache/hadoop/conf/Configuration;Ljava/lang/String;)Lorg/apache/hadoop/hbase/ipc/RpcClient;
     216: checkcast     #8                  // class org/apache/hadoop/hbase/client/TestClientTimeouts$RandomTimeoutRpcClient
     219: astore_3
     220: aload         7
     222: ifnull        298
     225: aload         7
     227: invokeinterface #27,  1           // InterfaceMethod org/apache/hadoop/hbase/client/Connection.close:()V
     232: goto          298
     235: astore        9
     237: aload         6
     239: ifnull        283
     242: aload         6
     244: invokeinterface #24,  1           // InterfaceMethod org/apache/hadoop/hbase/client/Admin.close:()V
     249: aload         6
     251: invokeinterface #25,  1           // InterfaceMethod org/apache/hadoop/hbase/client/Admin.getConnection:()Lorg/apache/hadoop/hbase/client/Connection;
     256: invokeinterface #26,  1           // InterfaceMethod org/apache/hadoop/hbase/client/Connection.isClosed:()Z
     261: ifeq          283
     264: getstatic     #2                  // Field TEST_UTIL:Lorg/apache/hadoop/hbase/HBaseTestingUtility;
     267: invokevirtual #5                  // Method org/apache/hadoop/hbase/HBaseTestingUtility.getConfiguration:()Lorg/apache/hadoop/conf/Configuration;
     270: getstatic     #2                  // Field TEST_UTIL:Lorg/apache/hadoop/hbase/HBaseTestingUtility;
     273: invokevirtual #14                 // Method org/apache/hadoop/hbase/HBaseTestingUtility.getClusterKey:()Ljava/lang/String;
     276: invokestatic  #15                 // Method org/apache/hadoop/hbase/ipc/RpcClientFactory.createClient:(Lorg/apache/hadoop/conf/Configuration;Ljava/lang/String;)Lorg/apache/hadoop/hbase/ipc/RpcClient;
     279: checkcast     #8                  // class org/apache/hadoop/hbase/client/TestClientTimeouts$RandomTimeoutRpcClient
     282: astore_3
     283: aload         7
     285: ifnull        295
     288: aload         7
     290: invokeinterface #27,  1           // InterfaceMethod org/apache/hadoop/hbase/client/Connection.close:()V
     295: aload         9
     297: athrow
     298: iinc          4, 1
     301: goto          31
     304: iload_1
     305: invokestatic  #29                 // Method org/junit/Assert.assertFalse:(Z)V
     308: invokestatic  #12                 // Method org/apache/hadoop/hbase/client/TestClientTimeouts$RandomTimeoutBlockingRpcChannel.access$000:()Ljava/util/concurrent/atomic/AtomicInteger;
     311: invokevirtual #13                 // Method java/util/concurrent/atomic/AtomicInteger.get:()I
     314: iload_2
     315: if_icmple     322
     318: iconst_1
     319: goto          323
     322: iconst_0
     323: invokestatic  #30                 // Method org/junit/Assert.assertTrue:(Z)V
     326: aload_3
     327: invokevirtual #31                 // Method org/apache/hadoop/hbase/client/TestClientTimeouts$RandomTimeoutRpcClient.close:()V
     330: goto          342
     333: astore        10
     335: aload_3
     336: invokevirtual #31                 // Method org/apache/hadoop/hbase/client/TestClientTimeouts$RandomTimeoutRpcClient.close:()V
     339: aload         10
     341: athrow
     342: return
    Exception table:
       from    to  target type
          78   109   170   Class org/apache/hadoop/hbase/MasterNotRunningException
          78   109   235   any
         170   174   235   any
         235   237   235   any
          28   326   333   any
         333   335   333   any

  static {};
    Code:
       0: ldc           #32                 // class org/apache/hadoop/hbase/client/TestClientTimeouts
       2: invokestatic  #33                 // Method org/apache/hadoop/hbase/HBaseClassTestRule.forClass:(Ljava/lang/Class;)Lorg/apache/hadoop/hbase/HBaseClassTestRule;
       5: putstatic     #34                 // Field CLASS_RULE:Lorg/apache/hadoop/hbase/HBaseClassTestRule;
       8: new           #35                 // class org/apache/hadoop/hbase/HBaseTestingUtility
      11: dup
      12: invokespecial #36                 // Method org/apache/hadoop/hbase/HBaseTestingUtility."<init>":()V
      15: putstatic     #2                  // Field TEST_UTIL:Lorg/apache/hadoop/hbase/HBaseTestingUtility;
      18: iconst_1
      19: putstatic     #3                  // Field SLAVES:I
      22: return
}
