Compiled from "TestRegionMoveAndAbandon.java"
class org.apache.hadoop.hbase.master.assignment.TestRegionMoveAndAbandon$1 implements org.apache.hadoop.hbase.Waiter$Predicate<java.lang.Exception> {
  final org.apache.hadoop.hbase.master.assignment.TestRegionMoveAndAbandon this$0;

  org.apache.hadoop.hbase.master.assignment.TestRegionMoveAndAbandon$1(org.apache.hadoop.hbase.master.assignment.TestRegionMoveAndAbandon);
    Code:
       0: aload_0
       1: aload_1
       2: putfield      #1                  // Field this$0:Lorg/apache/hadoop/hbase/master/assignment/TestRegionMoveAndAbandon;
       5: aload_0
       6: invokespecial #2                  // Method java/lang/Object."<init>":()V
       9: return

  public boolean evaluate() throws java.lang.Exception;
    Code:
       0: aload_0
       1: getfield      #1                  // Field this$0:Lorg/apache/hadoop/hbase/master/assignment/TestRegionMoveAndAbandon;
       4: invokestatic  #3                  // Method org/apache/hadoop/hbase/master/assignment/TestRegionMoveAndAbandon.access$100:(Lorg/apache/hadoop/hbase/master/assignment/TestRegionMoveAndAbandon;)Lorg/apache/hadoop/hbase/HBaseTestingUtility;
       7: invokevirtual #4                  // Method org/apache/hadoop/hbase/HBaseTestingUtility.getConnection:()Lorg/apache/hadoop/hbase/client/Connection;
      10: aload_0
      11: getfield      #1                  // Field this$0:Lorg/apache/hadoop/hbase/master/assignment/TestRegionMoveAndAbandon;
      14: invokestatic  #5                  // Method org/apache/hadoop/hbase/master/assignment/TestRegionMoveAndAbandon.access$000:(Lorg/apache/hadoop/hbase/master/assignment/TestRegionMoveAndAbandon;)Lorg/apache/hadoop/hbase/TableName;
      17: invokeinterface #6,  2            // InterfaceMethod org/apache/hadoop/hbase/client/Connection.getTable:(Lorg/apache/hadoop/hbase/TableName;)Lorg/apache/hadoop/hbase/client/Table;
      22: astore_1
      23: aconst_null
      24: astore_2
      25: aload_1
      26: new           #7                  // class org/apache/hadoop/hbase/client/Get
      29: dup
      30: ldc           #8                  // String a
      32: invokestatic  #9                  // Method org/apache/hadoop/hbase/util/Bytes.toBytes:(Ljava/lang/String;)[B
      35: invokespecial #10                 // Method org/apache/hadoop/hbase/client/Get."<init>":([B)V
      38: invokeinterface #11,  2           // InterfaceMethod org/apache/hadoop/hbase/client/Table.get:(Lorg/apache/hadoop/hbase/client/Get;)Lorg/apache/hadoop/hbase/client/Result;
      43: pop
      44: iconst_1
      45: istore_3
      46: aload_1
      47: ifnull        80
      50: aload_2
      51: ifnull        74
      54: aload_1
      55: invokeinterface #12,  1           // InterfaceMethod org/apache/hadoop/hbase/client/Table.close:()V
      60: goto          80
      63: astore        4
      65: aload_2
      66: aload         4
      68: invokevirtual #14                 // Method java/lang/Throwable.addSuppressed:(Ljava/lang/Throwable;)V
      71: goto          80
      74: aload_1
      75: invokeinterface #12,  1           // InterfaceMethod org/apache/hadoop/hbase/client/Table.close:()V
      80: iload_3
      81: ireturn
      82: astore_3
      83: aload_3
      84: astore_2
      85: aload_3
      86: athrow
      87: astore        5
      89: aload_1
      90: ifnull        123
      93: aload_2
      94: ifnull        117
      97: aload_1
      98: invokeinterface #12,  1           // InterfaceMethod org/apache/hadoop/hbase/client/Table.close:()V
     103: goto          123
     106: astore        6
     108: aload_2
     109: aload         6
     111: invokevirtual #14                 // Method java/lang/Throwable.addSuppressed:(Ljava/lang/Throwable;)V
     114: goto          123
     117: aload_1
     118: invokeinterface #12,  1           // InterfaceMethod org/apache/hadoop/hbase/client/Table.close:()V
     123: aload         5
     125: athrow
    Exception table:
       from    to  target type
          54    60    63   Class java/lang/Throwable
          25    46    82   Class java/lang/Throwable
          25    46    87   any
          97   103   106   Class java/lang/Throwable
          82    89    87   any
}
