Compiled from "TestWakeUpUnexpectedProcedure.java"
final class org.apache.hadoop.hbase.master.assignment.TestWakeUpUnexpectedProcedure$AMForTest extends org.apache.hadoop.hbase.master.assignment.AssignmentManager {
  public org.apache.hadoop.hbase.master.assignment.TestWakeUpUnexpectedProcedure$AMForTest(org.apache.hadoop.hbase.master.MasterServices);
    Code:
       0: aload_0
       1: aload_1
       2: invokespecial #1                  // Method org/apache/hadoop/hbase/master/assignment/AssignmentManager."<init>":(Lorg/apache/hadoop/hbase/master/MasterServices;)V
       5: return

  public org.apache.hadoop.hbase.shaded.protobuf.generated.RegionServerStatusProtos$ReportRegionStateTransitionResponse reportRegionStateTransition(org.apache.hadoop.hbase.shaded.protobuf.generated.RegionServerStatusProtos$ReportRegionStateTransitionRequest) throws org.apache.hadoop.hbase.PleaseHoldException;
    Code:
       0: aload_1
       1: iconst_0
       2: invokevirtual #2                  // Method org/apache/hadoop/hbase/shaded/protobuf/generated/RegionServerStatusProtos$ReportRegionStateTransitionRequest.getTransition:(I)Lorg/apache/hadoop/hbase/shaded/protobuf/generated/RegionServerStatusProtos$RegionStateTransition;
       5: astore_2
       6: aload_2
       7: invokevirtual #3                  // Method org/apache/hadoop/hbase/shaded/protobuf/generated/RegionServerStatusProtos$RegionStateTransition.getTransitionCode:()Lorg/apache/hadoop/hbase/shaded/protobuf/generated/RegionServerStatusProtos$RegionStateTransition$TransitionCode;
      10: getstatic     #4                  // Field org/apache/hadoop/hbase/shaded/protobuf/generated/RegionServerStatusProtos$RegionStateTransition$TransitionCode.OPENED:Lorg/apache/hadoop/hbase/shaded/protobuf/generated/RegionServerStatusProtos$RegionStateTransition$TransitionCode;
      13: if_acmpne     90
      16: aload_2
      17: iconst_0
      18: invokevirtual #5                  // Method org/apache/hadoop/hbase/shaded/protobuf/generated/RegionServerStatusProtos$RegionStateTransition.getRegionInfo:(I)Lorg/apache/hadoop/hbase/shaded/protobuf/generated/HBaseProtos$RegionInfo;
      21: invokevirtual #6                  // Method org/apache/hadoop/hbase/shaded/protobuf/generated/HBaseProtos$RegionInfo.getTableName:()Lorg/apache/hadoop/hbase/shaded/protobuf/generated/HBaseProtos$TableName;
      24: invokestatic  #7                  // Method org/apache/hadoop/hbase/shaded/protobuf/ProtobufUtil.toTableName:(Lorg/apache/hadoop/hbase/shaded/protobuf/generated/HBaseProtos$TableName;)Lorg/apache/hadoop/hbase/TableName;
      27: invokestatic  #8                  // Method org/apache/hadoop/hbase/master/assignment/TestWakeUpUnexpectedProcedure.access$300:()Lorg/apache/hadoop/hbase/TableName;
      30: invokevirtual #9                  // Method org/apache/hadoop/hbase/TableName.equals:(Ljava/lang/Object;)Z
      33: ifeq          90
      36: invokestatic  #10                 // Method org/apache/hadoop/hbase/master/assignment/TestWakeUpUnexpectedProcedure.access$400:()Ljava/util/concurrent/CountDownLatch;
      39: astore_3
      40: invokestatic  #10                 // Method org/apache/hadoop/hbase/master/assignment/TestWakeUpUnexpectedProcedure.access$400:()Ljava/util/concurrent/CountDownLatch;
      43: ifnull        90
      46: aconst_null
      47: invokestatic  #11                 // Method org/apache/hadoop/hbase/master/assignment/TestWakeUpUnexpectedProcedure.access$402:(Ljava/util/concurrent/CountDownLatch;)Ljava/util/concurrent/CountDownLatch;
      50: pop
      51: aload_3
      52: invokevirtual #12                 // Method java/util/concurrent/CountDownLatch.countDown:()V
      55: invokestatic  #13                 // Method org/apache/hadoop/hbase/master/assignment/TestWakeUpUnexpectedProcedure.access$500:()Ljava/util/List;
      58: aload_1
      59: invokevirtual #14                 // Method org/apache/hadoop/hbase/shaded/protobuf/generated/RegionServerStatusProtos$ReportRegionStateTransitionRequest.getServer:()Lorg/apache/hadoop/hbase/shaded/protobuf/generated/HBaseProtos$ServerName;
      62: invokestatic  #15                 // Method org/apache/hadoop/hbase/shaded/protobuf/ProtobufUtil.toServerName:(Lorg/apache/hadoop/hbase/shaded/protobuf/generated/HBaseProtos$ServerName;)Lorg/apache/hadoop/hbase/ServerName;
      65: invokeinterface #16,  2           // InterfaceMethod java/util/List.add:(Ljava/lang/Object;)Z
      70: pop
      71: invokestatic  #17                 // Method org/apache/hadoop/hbase/master/assignment/TestWakeUpUnexpectedProcedure.access$600:()Ljava/util/concurrent/CountDownLatch;
      74: invokevirtual #18                 // Method java/util/concurrent/CountDownLatch.await:()V
      77: goto          90
      80: astore        4
      82: new           #20                 // class java/lang/RuntimeException
      85: dup
      86: invokespecial #21                 // Method java/lang/RuntimeException."<init>":()V
      89: athrow
      90: aload_0
      91: aload_1
      92: invokespecial #22                 // Method org/apache/hadoop/hbase/master/assignment/AssignmentManager.reportRegionStateTransition:(Lorg/apache/hadoop/hbase/shaded/protobuf/generated/RegionServerStatusProtos$ReportRegionStateTransitionRequest;)Lorg/apache/hadoop/hbase/shaded/protobuf/generated/RegionServerStatusProtos$ReportRegionStateTransitionResponse;
      95: areturn
    Exception table:
       from    to  target type
          71    77    80   Class java/lang/InterruptedException
}
