Compiled from "TestHStore.java"
public class org.apache.hadoop.hbase.regionserver.TestHStore {
  public static final org.apache.hadoop.hbase.HBaseClassTestRule CLASS_RULE;

  public org.junit.rules.TestName name;

  org.apache.hadoop.hbase.regionserver.HRegion region;

  org.apache.hadoop.hbase.regionserver.HStore store;

  byte[] table;

  byte[] family;

  byte[] row;

  byte[] row2;

  byte[] qf1;

  byte[] qf2;

  byte[] qf3;

  byte[] qf4;

  byte[] qf5;

  byte[] qf6;

  java.util.NavigableSet<byte[]> qualifiers;

  java.util.List<org.apache.hadoop.hbase.Cell> expected;

  java.util.List<org.apache.hadoop.hbase.Cell> result;

  long id;

  org.apache.hadoop.hbase.client.Get get;

  public org.apache.hadoop.hbase.regionserver.TestHStore();
    Code:
       0: aload_0
       1: invokespecial #6                  // Method java/lang/Object."<init>":()V
       4: aload_0
       5: new           #7                  // class org/junit/rules/TestName
       8: dup
       9: invokespecial #8                  // Method org/junit/rules/TestName."<init>":()V
      12: putfield      #9                  // Field name:Lorg/junit/rules/TestName;
      15: aload_0
      16: ldc           #10                 // String table
      18: invokestatic  #11                 // Method org/apache/hadoop/hbase/util/Bytes.toBytes:(Ljava/lang/String;)[B
      21: putfield      #12                 // Field table:[B
      24: aload_0
      25: ldc           #13                 // String family
      27: invokestatic  #11                 // Method org/apache/hadoop/hbase/util/Bytes.toBytes:(Ljava/lang/String;)[B
      30: putfield      #14                 // Field family:[B
      33: aload_0
      34: ldc           #15                 // String row
      36: invokestatic  #11                 // Method org/apache/hadoop/hbase/util/Bytes.toBytes:(Ljava/lang/String;)[B
      39: putfield      #16                 // Field row:[B
      42: aload_0
      43: ldc           #17                 // String row2
      45: invokestatic  #11                 // Method org/apache/hadoop/hbase/util/Bytes.toBytes:(Ljava/lang/String;)[B
      48: putfield      #18                 // Field row2:[B
      51: aload_0
      52: ldc           #19                 // String qf1
      54: invokestatic  #11                 // Method org/apache/hadoop/hbase/util/Bytes.toBytes:(Ljava/lang/String;)[B
      57: putfield      #20                 // Field qf1:[B
      60: aload_0
      61: ldc           #21                 // String qf2
      63: invokestatic  #11                 // Method org/apache/hadoop/hbase/util/Bytes.toBytes:(Ljava/lang/String;)[B
      66: putfield      #22                 // Field qf2:[B
      69: aload_0
      70: ldc           #23                 // String qf3
      72: invokestatic  #11                 // Method org/apache/hadoop/hbase/util/Bytes.toBytes:(Ljava/lang/String;)[B
      75: putfield      #24                 // Field qf3:[B
      78: aload_0
      79: ldc           #25                 // String qf4
      81: invokestatic  #11                 // Method org/apache/hadoop/hbase/util/Bytes.toBytes:(Ljava/lang/String;)[B
      84: putfield      #26                 // Field qf4:[B
      87: aload_0
      88: ldc           #27                 // String qf5
      90: invokestatic  #11                 // Method org/apache/hadoop/hbase/util/Bytes.toBytes:(Ljava/lang/String;)[B
      93: putfield      #28                 // Field qf5:[B
      96: aload_0
      97: ldc           #29                 // String qf6
      99: invokestatic  #11                 // Method org/apache/hadoop/hbase/util/Bytes.toBytes:(Ljava/lang/String;)[B
     102: putfield      #30                 // Field qf6:[B
     105: aload_0
     106: new           #31                 // class java/util/concurrent/ConcurrentSkipListSet
     109: dup
     110: getstatic     #32                 // Field org/apache/hadoop/hbase/util/Bytes.BYTES_COMPARATOR:Ljava/util/Comparator;
     113: invokespecial #33                 // Method java/util/concurrent/ConcurrentSkipListSet."<init>":(Ljava/util/Comparator;)V
     116: putfield      #34                 // Field qualifiers:Ljava/util/NavigableSet;
     119: aload_0
     120: new           #35                 // class java/util/ArrayList
     123: dup
     124: invokespecial #36                 // Method java/util/ArrayList."<init>":()V
     127: putfield      #37                 // Field expected:Ljava/util/List;
     130: aload_0
     131: new           #35                 // class java/util/ArrayList
     134: dup
     135: invokespecial #36                 // Method java/util/ArrayList."<init>":()V
     138: putfield      #38                 // Field result:Ljava/util/List;
     141: aload_0
     142: invokestatic  #39                 // Method java/lang/System.currentTimeMillis:()J
     145: putfield      #40                 // Field id:J
     148: aload_0
     149: new           #41                 // class org/apache/hadoop/hbase/client/Get
     152: dup
     153: aload_0
     154: getfield      #16                 // Field row:[B
     157: invokespecial #42                 // Method org/apache/hadoop/hbase/client/Get."<init>":([B)V
     160: putfield      #43                 // Field get:Lorg/apache/hadoop/hbase/client/Get;
     163: return

  public void setUp() throws java.io.IOException;
    Code:
       0: aload_0
       1: getfield      #34                 // Field qualifiers:Ljava/util/NavigableSet;
       4: aload_0
       5: getfield      #20                 // Field qf1:[B
       8: invokeinterface #44,  2           // InterfaceMethod java/util/NavigableSet.add:(Ljava/lang/Object;)Z
      13: pop
      14: aload_0
      15: getfield      #34                 // Field qualifiers:Ljava/util/NavigableSet;
      18: aload_0
      19: getfield      #24                 // Field qf3:[B
      22: invokeinterface #44,  2           // InterfaceMethod java/util/NavigableSet.add:(Ljava/lang/Object;)Z
      27: pop
      28: aload_0
      29: getfield      #34                 // Field qualifiers:Ljava/util/NavigableSet;
      32: aload_0
      33: getfield      #28                 // Field qf5:[B
      36: invokeinterface #44,  2           // InterfaceMethod java/util/NavigableSet.add:(Ljava/lang/Object;)Z
      41: pop
      42: aload_0
      43: getfield      #34                 // Field qualifiers:Ljava/util/NavigableSet;
      46: invokeinterface #45,  1           // InterfaceMethod java/util/NavigableSet.iterator:()Ljava/util/Iterator;
      51: astore_1
      52: aload_1
      53: invokeinterface #46,  1           // InterfaceMethod java/util/Iterator.hasNext:()Z
      58: ifeq          118
      61: aload_1
      62: invokeinterface #47,  1           // InterfaceMethod java/util/Iterator.next:()Ljava/lang/Object;
      67: checkcast     #48                 // class "[B"
      70: astore_2
      71: aload_0
      72: getfield      #37                 // Field expected:Ljava/util/List;
      75: new           #49                 // class org/apache/hadoop/hbase/KeyValue
      78: dup
      79: aload_0
      80: getfield      #16                 // Field row:[B
      83: aload_0
      84: getfield      #14                 // Field family:[B
      87: aload_2
      88: lconst_1
      89: aconst_null
      90: checkcast     #48                 // class "[B"
      93: invokespecial #50                 // Method org/apache/hadoop/hbase/KeyValue."<init>":([B[B[BJ[B)V
      96: invokeinterface #51,  2           // InterfaceMethod java/util/List.add:(Ljava/lang/Object;)Z
     101: pop
     102: aload_0
     103: getfield      #43                 // Field get:Lorg/apache/hadoop/hbase/client/Get;
     106: aload_0
     107: getfield      #14                 // Field family:[B
     110: aload_2
     111: invokevirtual #52                 // Method org/apache/hadoop/hbase/client/Get.addColumn:([B[B)Lorg/apache/hadoop/hbase/client/Get;
     114: pop
     115: goto          52
     118: return

  public void testFlushSizeSizing() throws java.lang.Exception;
    Code:
       0: getstatic     #4                  // Field LOG:Lorg/slf4j/Logger;
       3: new           #67                 // class java/lang/StringBuilder
       6: dup
       7: invokespecial #68                 // Method java/lang/StringBuilder."<init>":()V
      10: ldc           #111                // String Setting up a faulty file system that cannot write in
      12: invokevirtual #70                 // Method java/lang/StringBuilder.append:(Ljava/lang/String;)Ljava/lang/StringBuilder;
      15: aload_0
      16: getfield      #9                  // Field name:Lorg/junit/rules/TestName;
      19: invokevirtual #112                // Method org/junit/rules/TestName.getMethodName:()Ljava/lang/String;
      22: invokevirtual #70                 // Method java/lang/StringBuilder.append:(Ljava/lang/String;)Ljava/lang/StringBuilder;
      25: invokevirtual #71                 // Method java/lang/StringBuilder.toString:()Ljava/lang/String;
      28: invokeinterface #113,  2          // InterfaceMethod org/slf4j/Logger.info:(Ljava/lang/String;)V
      33: getstatic     #53                 // Field TEST_UTIL:Lorg/apache/hadoop/hbase/HBaseTestingUtility;
      36: invokevirtual #54                 // Method org/apache/hadoop/hbase/HBaseTestingUtility.getConfiguration:()Lorg/apache/hadoop/conf/Configuration;
      39: invokestatic  #114                // Method org/apache/hadoop/hbase/HBaseConfiguration.create:(Lorg/apache/hadoop/conf/Configuration;)Lorg/apache/hadoop/conf/Configuration;
      42: astore_1
      43: aload_1
      44: ldc           #115                // String hbase.hstore.flush.retries.number
      46: iconst_1
      47: invokevirtual #116                // Method org/apache/hadoop/conf/Configuration.setInt:(Ljava/lang/String;I)V
      50: aload_1
      51: aload_0
      52: getfield      #9                  // Field name:Lorg/junit/rules/TestName;
      55: invokevirtual #112                // Method org/junit/rules/TestName.getMethodName:()Ljava/lang/String;
      58: iconst_1
      59: anewarray     #117                // class java/lang/String
      62: dup
      63: iconst_0
      64: ldc           #118                // String foo
      66: aastore
      67: invokestatic  #119                // Method org/apache/hadoop/hbase/security/User.createUserForTesting:(Lorg/apache/hadoop/conf/Configuration;Ljava/lang/String;[Ljava/lang/String;)Lorg/apache/hadoop/hbase/security/User;
      70: astore_2
      71: aload_1
      72: ldc           #120                // String fs.file.impl
      74: ldc           #121                // class org/apache/hadoop/hbase/regionserver/TestHStore$FaultyFileSystem
      76: ldc           #122                // class org/apache/hadoop/fs/FileSystem
      78: invokevirtual #123                // Method org/apache/hadoop/conf/Configuration.setClass:(Ljava/lang/String;Ljava/lang/Class;Ljava/lang/Class;)V
      81: aload_2
      82: new           #124                // class org/apache/hadoop/hbase/regionserver/TestHStore$1
      85: dup
      86: aload_0
      87: aload_1
      88: invokespecial #125                // Method org/apache/hadoop/hbase/regionserver/TestHStore$1."<init>":(Lorg/apache/hadoop/hbase/regionserver/TestHStore;Lorg/apache/hadoop/conf/Configuration;)V
      91: invokevirtual #126                // Method org/apache/hadoop/hbase/security/User.runAs:(Ljava/security/PrivilegedExceptionAction;)Ljava/lang/Object;
      94: pop
      95: return

  public void testCreateWriter() throws java.lang.Exception;
    Code:
       0: invokestatic  #127                // Method org/apache/hadoop/hbase/HBaseConfiguration.create:()Lorg/apache/hadoop/conf/Configuration;
       3: astore_1
       4: aload_1
       5: invokestatic  #77                 // Method org/apache/hadoop/fs/FileSystem.get:(Lorg/apache/hadoop/conf/Configuration;)Lorg/apache/hadoop/fs/FileSystem;
       8: astore_2
       9: aload_0
      10: getfield      #14                 // Field family:[B
      13: invokestatic  #55                 // Method org/apache/hadoop/hbase/client/ColumnFamilyDescriptorBuilder.newBuilder:([B)Lorg/apache/hadoop/hbase/client/ColumnFamilyDescriptorBuilder;
      16: getstatic     #128                // Field org/apache/hadoop/hbase/io/compress/Compression$Algorithm.GZ:Lorg/apache/hadoop/hbase/io/compress/Compression$Algorithm;
      19: invokevirtual #129                // Method org/apache/hadoop/hbase/client/ColumnFamilyDescriptorBuilder.setCompressionType:(Lorg/apache/hadoop/hbase/io/compress/Compression$Algorithm;)Lorg/apache/hadoop/hbase/client/ColumnFamilyDescriptorBuilder;
      22: getstatic     #130                // Field org/apache/hadoop/hbase/io/encoding/DataBlockEncoding.DIFF:Lorg/apache/hadoop/hbase/io/encoding/DataBlockEncoding;
      25: invokevirtual #131                // Method org/apache/hadoop/hbase/client/ColumnFamilyDescriptorBuilder.setDataBlockEncoding:(Lorg/apache/hadoop/hbase/io/encoding/DataBlockEncoding;)Lorg/apache/hadoop/hbase/client/ColumnFamilyDescriptorBuilder;
      28: invokevirtual #57                 // Method org/apache/hadoop/hbase/client/ColumnFamilyDescriptorBuilder.build:()Lorg/apache/hadoop/hbase/client/ColumnFamilyDescriptor;
      31: astore_3
      32: aload_0
      33: aload_0
      34: getfield      #9                  // Field name:Lorg/junit/rules/TestName;
      37: invokevirtual #112                // Method org/junit/rules/TestName.getMethodName:()Ljava/lang/String;
      40: aload_1
      41: aload_3
      42: invokespecial #58                 // Method init:(Ljava/lang/String;Lorg/apache/hadoop/conf/Configuration;Lorg/apache/hadoop/hbase/client/ColumnFamilyDescriptor;)Lorg/apache/hadoop/hbase/regionserver/HStore;
      45: pop
      46: aload_0
      47: getfield      #108                // Field store:Lorg/apache/hadoop/hbase/regionserver/HStore;
      50: ldc2_w        #132                // long 4l
      53: aload_3
      54: invokeinterface #134,  1          // InterfaceMethod org/apache/hadoop/hbase/client/ColumnFamilyDescriptor.getCompressionType:()Lorg/apache/hadoop/hbase/io/compress/Compression$Algorithm;
      59: iconst_0
      60: iconst_1
      61: iconst_0
      62: iconst_0
      63: invokevirtual #135                // Method org/apache/hadoop/hbase/regionserver/HStore.createWriterInTmp:(JLorg/apache/hadoop/hbase/io/compress/Compression$Algorithm;ZZZZ)Lorg/apache/hadoop/hbase/regionserver/StoreFileWriter;
      66: astore        4
      68: aload         4
      70: invokevirtual #136                // Method org/apache/hadoop/hbase/regionserver/StoreFileWriter.getPath:()Lorg/apache/hadoop/fs/Path;
      73: astore        5
      75: aload         4
      77: new           #49                 // class org/apache/hadoop/hbase/KeyValue
      80: dup
      81: aload_0
      82: getfield      #16                 // Field row:[B
      85: aload_0
      86: getfield      #14                 // Field family:[B
      89: aload_0
      90: getfield      #20                 // Field qf1:[B
      93: iconst_1
      94: invokestatic  #137                // Method org/apache/hadoop/hbase/util/Bytes.toBytes:(I)[B
      97: invokespecial #138                // Method org/apache/hadoop/hbase/KeyValue."<init>":([B[B[B[B)V
     100: invokevirtual #139                // Method org/apache/hadoop/hbase/regionserver/StoreFileWriter.append:(Lorg/apache/hadoop/hbase/Cell;)V
     103: aload         4
     105: new           #49                 // class org/apache/hadoop/hbase/KeyValue
     108: dup
     109: aload_0
     110: getfield      #16                 // Field row:[B
     113: aload_0
     114: getfield      #14                 // Field family:[B
     117: aload_0
     118: getfield      #22                 // Field qf2:[B
     121: iconst_2
     122: invokestatic  #137                // Method org/apache/hadoop/hbase/util/Bytes.toBytes:(I)[B
     125: invokespecial #138                // Method org/apache/hadoop/hbase/KeyValue."<init>":([B[B[B[B)V
     128: invokevirtual #139                // Method org/apache/hadoop/hbase/regionserver/StoreFileWriter.append:(Lorg/apache/hadoop/hbase/Cell;)V
     131: aload         4
     133: new           #49                 // class org/apache/hadoop/hbase/KeyValue
     136: dup
     137: aload_0
     138: getfield      #18                 // Field row2:[B
     141: aload_0
     142: getfield      #14                 // Field family:[B
     145: aload_0
     146: getfield      #20                 // Field qf1:[B
     149: iconst_3
     150: invokestatic  #137                // Method org/apache/hadoop/hbase/util/Bytes.toBytes:(I)[B
     153: invokespecial #138                // Method org/apache/hadoop/hbase/KeyValue."<init>":([B[B[B[B)V
     156: invokevirtual #139                // Method org/apache/hadoop/hbase/regionserver/StoreFileWriter.append:(Lorg/apache/hadoop/hbase/Cell;)V
     159: aload         4
     161: new           #49                 // class org/apache/hadoop/hbase/KeyValue
     164: dup
     165: aload_0
     166: getfield      #18                 // Field row2:[B
     169: aload_0
     170: getfield      #14                 // Field family:[B
     173: aload_0
     174: getfield      #22                 // Field qf2:[B
     177: iconst_4
     178: invokestatic  #137                // Method org/apache/hadoop/hbase/util/Bytes.toBytes:(I)[B
     181: invokespecial #138                // Method org/apache/hadoop/hbase/KeyValue."<init>":([B[B[B[B)V
     184: invokevirtual #139                // Method org/apache/hadoop/hbase/regionserver/StoreFileWriter.append:(Lorg/apache/hadoop/hbase/Cell;)V
     187: aload         4
     189: invokevirtual #140                // Method org/apache/hadoop/hbase/regionserver/StoreFileWriter.close:()V
     192: aload_2
     193: aload         5
     195: new           #141                // class org/apache/hadoop/hbase/io/hfile/CacheConfig
     198: dup
     199: aload_1
     200: invokespecial #142                // Method org/apache/hadoop/hbase/io/hfile/CacheConfig."<init>":(Lorg/apache/hadoop/conf/Configuration;)V
     203: iconst_1
     204: aload_1
     205: invokestatic  #143                // Method org/apache/hadoop/hbase/io/hfile/HFile.createReader:(Lorg/apache/hadoop/fs/FileSystem;Lorg/apache/hadoop/fs/Path;Lorg/apache/hadoop/hbase/io/hfile/CacheConfig;ZLorg/apache/hadoop/conf/Configuration;)Lorg/apache/hadoop/hbase/io/hfile/HFile$Reader;
     208: astore        6
     210: aload_3
     211: invokeinterface #134,  1          // InterfaceMethod org/apache/hadoop/hbase/client/ColumnFamilyDescriptor.getCompressionType:()Lorg/apache/hadoop/hbase/io/compress/Compression$Algorithm;
     216: aload         6
     218: invokeinterface #144,  1          // InterfaceMethod org/apache/hadoop/hbase/io/hfile/HFile$Reader.getCompressionAlgorithm:()Lorg/apache/hadoop/hbase/io/compress/Compression$Algorithm;
     223: invokestatic  #145                // Method org/junit/Assert.assertEquals:(Ljava/lang/Object;Ljava/lang/Object;)V
     226: aload_3
     227: invokeinterface #146,  1          // InterfaceMethod org/apache/hadoop/hbase/client/ColumnFamilyDescriptor.getDataBlockEncoding:()Lorg/apache/hadoop/hbase/io/encoding/DataBlockEncoding;
     232: aload         6
     234: invokeinterface #147,  1          // InterfaceMethod org/apache/hadoop/hbase/io/hfile/HFile$Reader.getDataBlockEncoding:()Lorg/apache/hadoop/hbase/io/encoding/DataBlockEncoding;
     239: invokestatic  #145                // Method org/junit/Assert.assertEquals:(Ljava/lang/Object;Ljava/lang/Object;)V
     242: aload         6
     244: invokeinterface #148,  1          // InterfaceMethod org/apache/hadoop/hbase/io/hfile/HFile$Reader.close:()V
     249: return

  public void testDeleteExpiredStoreFiles() throws java.lang.Exception;
    Code:
       0: aload_0
       1: iconst_0
       2: invokevirtual #149                // Method testDeleteExpiredStoreFiles:(I)V
       5: aload_0
       6: iconst_1
       7: invokevirtual #149                // Method testDeleteExpiredStoreFiles:(I)V
      10: return

  public void testDeleteExpiredStoreFiles(int) throws java.lang.Exception;
    Code:
       0: iconst_4
       1: istore_2
       2: iconst_4
       3: istore_3
       4: new           #150                // class org/apache/hadoop/hbase/util/IncrementingEnvironmentEdge
       7: dup
       8: invokespecial #151                // Method org/apache/hadoop/hbase/util/IncrementingEnvironmentEdge."<init>":()V
      11: astore        4
      13: aload         4
      15: invokestatic  #152                // Method org/apache/hadoop/hbase/util/EnvironmentEdgeManagerTestHelper.injectEdge:(Lorg/apache/hadoop/hbase/util/EnvironmentEdge;)V
      18: invokestatic  #127                // Method org/apache/hadoop/hbase/HBaseConfiguration.create:()Lorg/apache/hadoop/conf/Configuration;
      21: astore        5
      23: aload         5
      25: ldc           #153                // String hbase.store.delete.expired.storefile
      27: iconst_1
      28: invokevirtual #154                // Method org/apache/hadoop/conf/Configuration.setBoolean:(Ljava/lang/String;Z)V
      31: aload         5
      33: ldc           #156                // String hbase.hstore.compaction.min
      35: iconst_5
      36: invokevirtual #116                // Method org/apache/hadoop/conf/Configuration.setInt:(Ljava/lang/String;I)V
      39: aload_0
      40: new           #67                 // class java/lang/StringBuilder
      43: dup
      44: invokespecial #68                 // Method java/lang/StringBuilder."<init>":()V
      47: aload_0
      48: getfield      #9                  // Field name:Lorg/junit/rules/TestName;
      51: invokevirtual #112                // Method org/junit/rules/TestName.getMethodName:()Ljava/lang/String;
      54: invokevirtual #70                 // Method java/lang/StringBuilder.append:(Ljava/lang/String;)Ljava/lang/StringBuilder;
      57: ldc           #157                // String -
      59: invokevirtual #70                 // Method java/lang/StringBuilder.append:(Ljava/lang/String;)Ljava/lang/StringBuilder;
      62: iload_1
      63: invokevirtual #158                // Method java/lang/StringBuilder.append:(I)Ljava/lang/StringBuilder;
      66: invokevirtual #71                 // Method java/lang/StringBuilder.toString:()Ljava/lang/String;
      69: aload         5
      71: aload_0
      72: getfield      #14                 // Field family:[B
      75: invokestatic  #55                 // Method org/apache/hadoop/hbase/client/ColumnFamilyDescriptorBuilder.newBuilder:([B)Lorg/apache/hadoop/hbase/client/ColumnFamilyDescriptorBuilder;
      78: iload_1
      79: invokevirtual #159                // Method org/apache/hadoop/hbase/client/ColumnFamilyDescriptorBuilder.setMinVersions:(I)Lorg/apache/hadoop/hbase/client/ColumnFamilyDescriptorBuilder;
      82: iload_3
      83: invokevirtual #160                // Method org/apache/hadoop/hbase/client/ColumnFamilyDescriptorBuilder.setTimeToLive:(I)Lorg/apache/hadoop/hbase/client/ColumnFamilyDescriptorBuilder;
      86: invokevirtual #57                 // Method org/apache/hadoop/hbase/client/ColumnFamilyDescriptorBuilder.build:()Lorg/apache/hadoop/hbase/client/ColumnFamilyDescriptor;
      89: invokespecial #58                 // Method init:(Ljava/lang/String;Lorg/apache/hadoop/conf/Configuration;Lorg/apache/hadoop/hbase/client/ColumnFamilyDescriptor;)Lorg/apache/hadoop/hbase/regionserver/HStore;
      92: pop
      93: aload_0
      94: getfield      #108                // Field store:Lorg/apache/hadoop/hbase/regionserver/HStore;
      97: invokevirtual #161                // Method org/apache/hadoop/hbase/regionserver/HStore.getScanInfo:()Lorg/apache/hadoop/hbase/regionserver/ScanInfo;
     100: invokevirtual #162                // Method org/apache/hadoop/hbase/regionserver/ScanInfo.getTtl:()J
     103: lstore        6
     105: lload         6
     107: iload_2
     108: i2l
     109: ldiv
     110: lstore        8
     112: iconst_1
     113: istore        12
     115: iload         12
     117: iload_2
     118: if_icmpgt     273
     121: getstatic     #4                  // Field LOG:Lorg/slf4j/Logger;
     124: new           #67                 // class java/lang/StringBuilder
     127: dup
     128: invokespecial #68                 // Method java/lang/StringBuilder."<init>":()V
     131: ldc           #163                // String Adding some data for the store file #
     133: invokevirtual #70                 // Method java/lang/StringBuilder.append:(Ljava/lang/String;)Ljava/lang/StringBuilder;
     136: iload         12
     138: invokevirtual #158                // Method java/lang/StringBuilder.append:(I)Ljava/lang/StringBuilder;
     141: invokevirtual #71                 // Method java/lang/StringBuilder.toString:()Ljava/lang/String;
     144: invokeinterface #113,  2          // InterfaceMethod org/slf4j/Logger.info:(Ljava/lang/String;)V
     149: invokestatic  #164                // Method org/apache/hadoop/hbase/util/EnvironmentEdgeManager.currentTime:()J
     152: lstore        10
     154: aload_0
     155: getfield      #108                // Field store:Lorg/apache/hadoop/hbase/regionserver/HStore;
     158: new           #49                 // class org/apache/hadoop/hbase/KeyValue
     161: dup
     162: aload_0
     163: getfield      #16                 // Field row:[B
     166: aload_0
     167: getfield      #14                 // Field family:[B
     170: aload_0
     171: getfield      #20                 // Field qf1:[B
     174: lload         10
     176: aconst_null
     177: checkcast     #48                 // class "[B"
     180: invokespecial #50                 // Method org/apache/hadoop/hbase/KeyValue."<init>":([B[B[BJ[B)V
     183: aconst_null
     184: invokevirtual #165                // Method org/apache/hadoop/hbase/regionserver/HStore.add:(Lorg/apache/hadoop/hbase/Cell;Lorg/apache/hadoop/hbase/regionserver/MemStoreSizing;)V
     187: aload_0
     188: getfield      #108                // Field store:Lorg/apache/hadoop/hbase/regionserver/HStore;
     191: new           #49                 // class org/apache/hadoop/hbase/KeyValue
     194: dup
     195: aload_0
     196: getfield      #16                 // Field row:[B
     199: aload_0
     200: getfield      #14                 // Field family:[B
     203: aload_0
     204: getfield      #22                 // Field qf2:[B
     207: lload         10
     209: aconst_null
     210: checkcast     #48                 // class "[B"
     213: invokespecial #50                 // Method org/apache/hadoop/hbase/KeyValue."<init>":([B[B[BJ[B)V
     216: aconst_null
     217: invokevirtual #165                // Method org/apache/hadoop/hbase/regionserver/HStore.add:(Lorg/apache/hadoop/hbase/Cell;Lorg/apache/hadoop/hbase/regionserver/MemStoreSizing;)V
     220: aload_0
     221: getfield      #108                // Field store:Lorg/apache/hadoop/hbase/regionserver/HStore;
     224: new           #49                 // class org/apache/hadoop/hbase/KeyValue
     227: dup
     228: aload_0
     229: getfield      #16                 // Field row:[B
     232: aload_0
     233: getfield      #14                 // Field family:[B
     236: aload_0
     237: getfield      #24                 // Field qf3:[B
     240: lload         10
     242: aconst_null
     243: checkcast     #48                 // class "[B"
     246: invokespecial #50                 // Method org/apache/hadoop/hbase/KeyValue."<init>":([B[B[BJ[B)V
     249: aconst_null
     250: invokevirtual #165                // Method org/apache/hadoop/hbase/regionserver/HStore.add:(Lorg/apache/hadoop/hbase/Cell;Lorg/apache/hadoop/hbase/regionserver/MemStoreSizing;)V
     253: aload_0
     254: iload         12
     256: invokespecial #2                  // Method flush:(I)V
     259: aload         4
     261: lload         8
     263: invokevirtual #166                // Method org/apache/hadoop/hbase/util/IncrementingEnvironmentEdge.incrementTime:(J)J
     266: pop2
     267: iinc          12, 1
     270: goto          115
     273: iload_2
     274: i2l
     275: aload_0
     276: getfield      #108                // Field store:Lorg/apache/hadoop/hbase/regionserver/HStore;
     279: invokevirtual #167                // Method org/apache/hadoop/hbase/regionserver/HStore.getStorefiles:()Ljava/util/Collection;
     282: invokeinterface #168,  1          // InterfaceMethod java/util/Collection.size:()I
     287: i2l
     288: invokestatic  #169                // Method org/junit/Assert.assertEquals:(JJ)V
     291: iconst_1
     292: istore        12
     294: iload         12
     296: iload_2
     297: iconst_1
     298: isub
     299: if_icmpgt     436
     302: aload_0
     303: getfield      #108                // Field store:Lorg/apache/hadoop/hbase/regionserver/HStore;
     306: invokevirtual #170                // Method org/apache/hadoop/hbase/regionserver/HStore.requestCompaction:()Ljava/util/Optional;
     309: invokevirtual #171                // Method java/util/Optional.isPresent:()Z
     312: invokestatic  #172                // Method org/junit/Assert.assertFalse:(Z)V
     315: aload_0
     316: getfield      #108                // Field store:Lorg/apache/hadoop/hbase/regionserver/HStore;
     319: invokevirtual #167                // Method org/apache/hadoop/hbase/regionserver/HStore.getStorefiles:()Ljava/util/Collection;
     322: astore        13
     324: iload_1
     325: ifne          409
     328: iload_2
     329: iload         12
     331: isub
     332: i2l
     333: aload         13
     335: invokeinterface #168,  1          // InterfaceMethod java/util/Collection.size:()I
     340: i2l
     341: invokestatic  #169                // Method org/junit/Assert.assertEquals:(JJ)V
     344: aload         13
     346: invokeinterface #173,  1          // InterfaceMethod java/util/Collection.iterator:()Ljava/util/Iterator;
     351: astore        14
     353: aload         14
     355: invokeinterface #46,  1           // InterfaceMethod java/util/Iterator.hasNext:()Z
     360: ifeq          406
     363: aload         14
     365: invokeinterface #47,  1           // InterfaceMethod java/util/Iterator.next:()Ljava/lang/Object;
     370: checkcast     #174                // class org/apache/hadoop/hbase/regionserver/HStoreFile
     373: astore        15
     375: aload         15
     377: invokevirtual #175                // Method org/apache/hadoop/hbase/regionserver/HStoreFile.getReader:()Lorg/apache/hadoop/hbase/regionserver/StoreFileReader;
     380: invokevirtual #176                // Method org/apache/hadoop/hbase/regionserver/StoreFileReader.getMaxTimestamp:()J
     383: aload         4
     385: invokevirtual #177                // Method org/apache/hadoop/hbase/util/IncrementingEnvironmentEdge.currentTime:()J
     388: lload         6
     390: lsub
     391: lcmp
     392: iflt          399
     395: iconst_1
     396: goto          400
     399: iconst_0
     400: invokestatic  #178                // Method org/junit/Assert.assertTrue:(Z)V
     403: goto          353
     406: goto          422
     409: iload_2
     410: i2l
     411: aload         13
     413: invokeinterface #168,  1          // InterfaceMethod java/util/Collection.size:()I
     418: i2l
     419: invokestatic  #169                // Method org/junit/Assert.assertEquals:(JJ)V
     422: aload         4
     424: lload         8
     426: invokevirtual #166                // Method org/apache/hadoop/hbase/util/IncrementingEnvironmentEdge.incrementTime:(J)J
     429: pop2
     430: iinc          12, 1
     433: goto          294
     436: aload_0
     437: getfield      #108                // Field store:Lorg/apache/hadoop/hbase/regionserver/HStore;
     440: invokevirtual #170                // Method org/apache/hadoop/hbase/regionserver/HStore.requestCompaction:()Ljava/util/Optional;
     443: invokevirtual #171                // Method java/util/Optional.isPresent:()Z
     446: invokestatic  #172                // Method org/junit/Assert.assertFalse:(Z)V
     449: aload_0
     450: getfield      #108                // Field store:Lorg/apache/hadoop/hbase/regionserver/HStore;
     453: invokevirtual #167                // Method org/apache/hadoop/hbase/regionserver/HStore.getStorefiles:()Ljava/util/Collection;
     456: astore        12
     458: iload_1
     459: ifne          474
     462: lconst_1
     463: aload         12
     465: invokeinterface #168,  1          // InterfaceMethod java/util/Collection.size:()I
     470: i2l
     471: invokestatic  #169                // Method org/junit/Assert.assertEquals:(JJ)V
     474: aload         12
     476: invokeinterface #173,  1          // InterfaceMethod java/util/Collection.iterator:()Ljava/util/Iterator;
     481: invokeinterface #47,  1           // InterfaceMethod java/util/Iterator.next:()Ljava/lang/Object;
     486: checkcast     #174                // class org/apache/hadoop/hbase/regionserver/HStoreFile
     489: invokevirtual #175                // Method org/apache/hadoop/hbase/regionserver/HStoreFile.getReader:()Lorg/apache/hadoop/hbase/regionserver/StoreFileReader;
     492: invokevirtual #176                // Method org/apache/hadoop/hbase/regionserver/StoreFileReader.getMaxTimestamp:()J
     495: lstore        13
     497: lload         13
     499: aload         4
     501: invokevirtual #177                // Method org/apache/hadoop/hbase/util/IncrementingEnvironmentEdge.currentTime:()J
     504: lload         6
     506: lsub
     507: lcmp
     508: ifge          515
     511: iconst_1
     512: goto          516
     515: iconst_0
     516: invokestatic  #178                // Method org/junit/Assert.assertTrue:(Z)V
     519: aload         12
     521: invokeinterface #173,  1          // InterfaceMethod java/util/Collection.iterator:()Ljava/util/Iterator;
     526: astore        15
     528: aload         15
     530: invokeinterface #46,  1           // InterfaceMethod java/util/Iterator.hasNext:()Z
     535: ifeq          559
     538: aload         15
     540: invokeinterface #47,  1           // InterfaceMethod java/util/Iterator.next:()Ljava/lang/Object;
     545: checkcast     #174                // class org/apache/hadoop/hbase/regionserver/HStoreFile
     548: astore        16
     550: aload         16
     552: iconst_1
     553: invokevirtual #179                // Method org/apache/hadoop/hbase/regionserver/HStoreFile.closeStoreFile:(Z)V
     556: goto          528
     559: return

  public void testLowestModificationTime() throws java.lang.Exception;
    Code:
       0: invokestatic  #127                // Method org/apache/hadoop/hbase/HBaseConfiguration.create:()Lorg/apache/hadoop/conf/Configuration;
       3: astore_1
       4: aload_1
       5: invokestatic  #77                 // Method org/apache/hadoop/fs/FileSystem.get:(Lorg/apache/hadoop/conf/Configuration;)Lorg/apache/hadoop/fs/FileSystem;
       8: astore_2
       9: aload_0
      10: aload_0
      11: getfield      #9                  // Field name:Lorg/junit/rules/TestName;
      14: invokevirtual #112                // Method org/junit/rules/TestName.getMethodName:()Ljava/lang/String;
      17: aload_1
      18: invokespecial #5                  // Method init:(Ljava/lang/String;Lorg/apache/hadoop/conf/Configuration;)Lorg/apache/hadoop/hbase/regionserver/HStore;
      21: pop
      22: iconst_4
      23: istore_3
      24: iconst_1
      25: istore        4
      27: iload         4
      29: iload_3
      30: if_icmpgt     175
      33: getstatic     #4                  // Field LOG:Lorg/slf4j/Logger;
      36: new           #67                 // class java/lang/StringBuilder
      39: dup
      40: invokespecial #68                 // Method java/lang/StringBuilder."<init>":()V
      43: ldc           #163                // String Adding some data for the store file #
      45: invokevirtual #70                 // Method java/lang/StringBuilder.append:(Ljava/lang/String;)Ljava/lang/StringBuilder;
      48: iload         4
      50: invokevirtual #158                // Method java/lang/StringBuilder.append:(I)Ljava/lang/StringBuilder;
      53: invokevirtual #71                 // Method java/lang/StringBuilder.toString:()Ljava/lang/String;
      56: invokeinterface #113,  2          // InterfaceMethod org/slf4j/Logger.info:(Ljava/lang/String;)V
      61: aload_0
      62: getfield      #108                // Field store:Lorg/apache/hadoop/hbase/regionserver/HStore;
      65: new           #49                 // class org/apache/hadoop/hbase/KeyValue
      68: dup
      69: aload_0
      70: getfield      #16                 // Field row:[B
      73: aload_0
      74: getfield      #14                 // Field family:[B
      77: aload_0
      78: getfield      #20                 // Field qf1:[B
      81: iload         4
      83: i2l
      84: aconst_null
      85: checkcast     #48                 // class "[B"
      88: invokespecial #50                 // Method org/apache/hadoop/hbase/KeyValue."<init>":([B[B[BJ[B)V
      91: aconst_null
      92: invokevirtual #165                // Method org/apache/hadoop/hbase/regionserver/HStore.add:(Lorg/apache/hadoop/hbase/Cell;Lorg/apache/hadoop/hbase/regionserver/MemStoreSizing;)V
      95: aload_0
      96: getfield      #108                // Field store:Lorg/apache/hadoop/hbase/regionserver/HStore;
      99: new           #49                 // class org/apache/hadoop/hbase/KeyValue
     102: dup
     103: aload_0
     104: getfield      #16                 // Field row:[B
     107: aload_0
     108: getfield      #14                 // Field family:[B
     111: aload_0
     112: getfield      #22                 // Field qf2:[B
     115: iload         4
     117: i2l
     118: aconst_null
     119: checkcast     #48                 // class "[B"
     122: invokespecial #50                 // Method org/apache/hadoop/hbase/KeyValue."<init>":([B[B[BJ[B)V
     125: aconst_null
     126: invokevirtual #165                // Method org/apache/hadoop/hbase/regionserver/HStore.add:(Lorg/apache/hadoop/hbase/Cell;Lorg/apache/hadoop/hbase/regionserver/MemStoreSizing;)V
     129: aload_0
     130: getfield      #108                // Field store:Lorg/apache/hadoop/hbase/regionserver/HStore;
     133: new           #49                 // class org/apache/hadoop/hbase/KeyValue
     136: dup
     137: aload_0
     138: getfield      #16                 // Field row:[B
     141: aload_0
     142: getfield      #14                 // Field family:[B
     145: aload_0
     146: getfield      #24                 // Field qf3:[B
     149: iload         4
     151: i2l
     152: aconst_null
     153: checkcast     #48                 // class "[B"
     156: invokespecial #50                 // Method org/apache/hadoop/hbase/KeyValue."<init>":([B[B[BJ[B)V
     159: aconst_null
     160: invokevirtual #165                // Method org/apache/hadoop/hbase/regionserver/HStore.add:(Lorg/apache/hadoop/hbase/Cell;Lorg/apache/hadoop/hbase/regionserver/MemStoreSizing;)V
     163: aload_0
     164: iload         4
     166: invokespecial #2                  // Method flush:(I)V
     169: iinc          4, 1
     172: goto          27
     175: aload_0
     176: getfield      #108                // Field store:Lorg/apache/hadoop/hbase/regionserver/HStore;
     179: invokevirtual #167                // Method org/apache/hadoop/hbase/regionserver/HStore.getStorefiles:()Ljava/util/Collection;
     182: invokestatic  #180                // Method org/apache/hadoop/hbase/regionserver/StoreUtils.getLowestTimestamp:(Ljava/util/Collection;)J
     185: lstore        4
     187: aload_2
     188: aload_0
     189: getfield      #108                // Field store:Lorg/apache/hadoop/hbase/regionserver/HStore;
     192: invokevirtual #167                // Method org/apache/hadoop/hbase/regionserver/HStore.getStorefiles:()Ljava/util/Collection;
     195: invokestatic  #181                // Method getLowestTimeStampFromFS:(Lorg/apache/hadoop/fs/FileSystem;Ljava/util/Collection;)J
     198: lstore        6
     200: lload         4
     202: lload         6
     204: invokestatic  #169                // Method org/junit/Assert.assertEquals:(JJ)V
     207: aload_0
     208: getfield      #108                // Field store:Lorg/apache/hadoop/hbase/regionserver/HStore;
     211: aload_0
     212: getfield      #108                // Field store:Lorg/apache/hadoop/hbase/regionserver/HStore;
     215: invokevirtual #170                // Method org/apache/hadoop/hbase/regionserver/HStore.requestCompaction:()Ljava/util/Optional;
     218: invokevirtual #182                // Method java/util/Optional.get:()Ljava/lang/Object;
     221: checkcast     #183                // class org/apache/hadoop/hbase/regionserver/compactions/CompactionContext
     224: getstatic     #184                // Field org/apache/hadoop/hbase/regionserver/throttle/NoLimitThroughputController.INSTANCE:Lorg/apache/hadoop/hbase/regionserver/throttle/NoLimitThroughputController;
     227: aconst_null
     228: invokevirtual #185                // Method org/apache/hadoop/hbase/regionserver/HStore.compact:(Lorg/apache/hadoop/hbase/regionserver/compactions/CompactionContext;Lorg/apache/hadoop/hbase/regionserver/throttle/ThroughputController;Lorg/apache/hadoop/hbase/security/User;)Ljava/util/List;
     231: pop
     232: aload_0
     233: getfield      #108                // Field store:Lorg/apache/hadoop/hbase/regionserver/HStore;
     236: invokevirtual #167                // Method org/apache/hadoop/hbase/regionserver/HStore.getStorefiles:()Ljava/util/Collection;
     239: invokestatic  #180                // Method org/apache/hadoop/hbase/regionserver/StoreUtils.getLowestTimestamp:(Ljava/util/Collection;)J
     242: lstore        4
     244: aload_2
     245: aload_0
     246: getfield      #108                // Field store:Lorg/apache/hadoop/hbase/regionserver/HStore;
     249: invokevirtual #167                // Method org/apache/hadoop/hbase/regionserver/HStore.getStorefiles:()Ljava/util/Collection;
     252: invokestatic  #181                // Method getLowestTimeStampFromFS:(Lorg/apache/hadoop/fs/FileSystem;Ljava/util/Collection;)J
     255: lstore        6
     257: lload         4
     259: lload         6
     261: invokestatic  #169                // Method org/junit/Assert.assertEquals:(JJ)V
     264: return

  public void testEmptyStoreFile() throws java.io.IOException;
    Code:
       0: aload_0
       1: aload_0
       2: getfield      #9                  // Field name:Lorg/junit/rules/TestName;
       5: invokevirtual #112                // Method org/junit/rules/TestName.getMethodName:()Ljava/lang/String;
       8: invokespecial #194                // Method init:(Ljava/lang/String;)V
      11: aload_0
      12: getfield      #108                // Field store:Lorg/apache/hadoop/hbase/regionserver/HStore;
      15: new           #49                 // class org/apache/hadoop/hbase/KeyValue
      18: dup
      19: aload_0
      20: getfield      #16                 // Field row:[B
      23: aload_0
      24: getfield      #14                 // Field family:[B
      27: aload_0
      28: getfield      #20                 // Field qf1:[B
      31: lconst_1
      32: aconst_null
      33: checkcast     #48                 // class "[B"
      36: invokespecial #50                 // Method org/apache/hadoop/hbase/KeyValue."<init>":([B[B[BJ[B)V
      39: aconst_null
      40: invokevirtual #165                // Method org/apache/hadoop/hbase/regionserver/HStore.add:(Lorg/apache/hadoop/hbase/Cell;Lorg/apache/hadoop/hbase/regionserver/MemStoreSizing;)V
      43: aload_0
      44: getfield      #108                // Field store:Lorg/apache/hadoop/hbase/regionserver/HStore;
      47: new           #49                 // class org/apache/hadoop/hbase/KeyValue
      50: dup
      51: aload_0
      52: getfield      #16                 // Field row:[B
      55: aload_0
      56: getfield      #14                 // Field family:[B
      59: aload_0
      60: getfield      #22                 // Field qf2:[B
      63: lconst_1
      64: aconst_null
      65: checkcast     #48                 // class "[B"
      68: invokespecial #50                 // Method org/apache/hadoop/hbase/KeyValue."<init>":([B[B[BJ[B)V
      71: aconst_null
      72: invokevirtual #165                // Method org/apache/hadoop/hbase/regionserver/HStore.add:(Lorg/apache/hadoop/hbase/Cell;Lorg/apache/hadoop/hbase/regionserver/MemStoreSizing;)V
      75: aload_0
      76: iconst_1
      77: invokespecial #2                  // Method flush:(I)V
      80: aload_0
      81: getfield      #108                // Field store:Lorg/apache/hadoop/hbase/regionserver/HStore;
      84: invokevirtual #167                // Method org/apache/hadoop/hbase/regionserver/HStore.getStorefiles:()Ljava/util/Collection;
      87: invokeinterface #173,  1          // InterfaceMethod java/util/Collection.iterator:()Ljava/util/Iterator;
      92: invokeinterface #47,  1           // InterfaceMethod java/util/Iterator.next:()Ljava/lang/Object;
      97: checkcast     #174                // class org/apache/hadoop/hbase/regionserver/HStoreFile
     100: astore_1
     101: aload_1
     102: invokevirtual #190                // Method org/apache/hadoop/hbase/regionserver/HStoreFile.getPath:()Lorg/apache/hadoop/fs/Path;
     105: invokevirtual #195                // Method org/apache/hadoop/fs/Path.getParent:()Lorg/apache/hadoop/fs/Path;
     108: astore_2
     109: aload_1
     110: invokevirtual #196                // Method org/apache/hadoop/hbase/regionserver/HStoreFile.getMaxSequenceId:()J
     113: lstore_3
     114: invokestatic  #127                // Method org/apache/hadoop/hbase/HBaseConfiguration.create:()Lorg/apache/hadoop/conf/Configuration;
     117: astore        5
     119: aload         5
     121: invokestatic  #77                 // Method org/apache/hadoop/fs/FileSystem.get:(Lorg/apache/hadoop/conf/Configuration;)Lorg/apache/hadoop/fs/FileSystem;
     124: astore        6
     126: new           #197                // class org/apache/hadoop/hbase/io/hfile/HFileContextBuilder
     129: dup
     130: invokespecial #198                // Method org/apache/hadoop/hbase/io/hfile/HFileContextBuilder."<init>":()V
     133: sipush        8192
     136: invokevirtual #200                // Method org/apache/hadoop/hbase/io/hfile/HFileContextBuilder.withBlockSize:(I)Lorg/apache/hadoop/hbase/io/hfile/HFileContextBuilder;
     139: invokevirtual #201                // Method org/apache/hadoop/hbase/io/hfile/HFileContextBuilder.build:()Lorg/apache/hadoop/hbase/io/hfile/HFileContext;
     142: astore        7
     144: new           #202                // class org/apache/hadoop/hbase/regionserver/StoreFileWriter$Builder
     147: dup
     148: aload         5
     150: new           #141                // class org/apache/hadoop/hbase/io/hfile/CacheConfig
     153: dup
     154: aload         5
     156: invokespecial #142                // Method org/apache/hadoop/hbase/io/hfile/CacheConfig."<init>":(Lorg/apache/hadoop/conf/Configuration;)V
     159: aload         6
     161: invokespecial #203                // Method org/apache/hadoop/hbase/regionserver/StoreFileWriter$Builder."<init>":(Lorg/apache/hadoop/conf/Configuration;Lorg/apache/hadoop/hbase/io/hfile/CacheConfig;Lorg/apache/hadoop/fs/FileSystem;)V
     164: aload_2
     165: invokevirtual #204                // Method org/apache/hadoop/hbase/regionserver/StoreFileWriter$Builder.withOutputDir:(Lorg/apache/hadoop/fs/Path;)Lorg/apache/hadoop/hbase/regionserver/StoreFileWriter$Builder;
     168: aload         7
     170: invokevirtual #205                // Method org/apache/hadoop/hbase/regionserver/StoreFileWriter$Builder.withFileContext:(Lorg/apache/hadoop/hbase/io/hfile/HFileContext;)Lorg/apache/hadoop/hbase/regionserver/StoreFileWriter$Builder;
     173: invokevirtual #206                // Method org/apache/hadoop/hbase/regionserver/StoreFileWriter$Builder.build:()Lorg/apache/hadoop/hbase/regionserver/StoreFileWriter;
     176: astore        8
     178: aload         8
     180: lload_3
     181: lconst_1
     182: ladd
     183: iconst_0
     184: invokevirtual #207                // Method org/apache/hadoop/hbase/regionserver/StoreFileWriter.appendMetadata:(JZ)V
     187: aload         8
     189: invokevirtual #140                // Method org/apache/hadoop/hbase/regionserver/StoreFileWriter.close:()V
     192: aload_0
     193: getfield      #108                // Field store:Lorg/apache/hadoop/hbase/regionserver/HStore;
     196: invokevirtual #208                // Method org/apache/hadoop/hbase/regionserver/HStore.close:()Lorg/apache/hbase/thirdparty/com/google/common/collect/ImmutableCollection;
     199: pop
     200: aload_0
     201: new           #106                // class org/apache/hadoop/hbase/regionserver/HStore
     204: dup
     205: aload_0
     206: getfield      #108                // Field store:Lorg/apache/hadoop/hbase/regionserver/HStore;
     209: invokevirtual #209                // Method org/apache/hadoop/hbase/regionserver/HStore.getHRegion:()Lorg/apache/hadoop/hbase/regionserver/HRegion;
     212: aload_0
     213: getfield      #108                // Field store:Lorg/apache/hadoop/hbase/regionserver/HStore;
     216: invokevirtual #210                // Method org/apache/hadoop/hbase/regionserver/HStore.getColumnFamilyDescriptor:()Lorg/apache/hadoop/hbase/client/ColumnFamilyDescriptor;
     219: aload         5
     221: iconst_0
     222: invokespecial #107                // Method org/apache/hadoop/hbase/regionserver/HStore."<init>":(Lorg/apache/hadoop/hbase/regionserver/HRegion;Lorg/apache/hadoop/hbase/client/ColumnFamilyDescriptor;Lorg/apache/hadoop/conf/Configuration;Z)V
     225: putfield      #108                // Field store:Lorg/apache/hadoop/hbase/regionserver/HStore;
     228: ldc2_w        #211                // long 2l
     231: aload_0
     232: getfield      #108                // Field store:Lorg/apache/hadoop/hbase/regionserver/HStore;
     235: invokevirtual #213                // Method org/apache/hadoop/hbase/regionserver/HStore.getStorefilesCount:()I
     238: i2l
     239: invokestatic  #169                // Method org/junit/Assert.assertEquals:(JJ)V
     242: aload_0
     243: aload_0
     244: getfield      #108                // Field store:Lorg/apache/hadoop/hbase/regionserver/HStore;
     247: aload_0
     248: getfield      #43                 // Field get:Lorg/apache/hadoop/hbase/client/Get;
     251: invokevirtual #214                // Method org/apache/hadoop/hbase/client/Get.getRow:()[B
     254: aload_0
     255: getfield      #34                 // Field qualifiers:Ljava/util/NavigableSet;
     258: invokestatic  #215                // Method org/apache/hadoop/hbase/HBaseTestingUtility.getFromStoreFile:(Lorg/apache/hadoop/hbase/regionserver/HStore;[BLjava/util/NavigableSet;)Ljava/util/List;
     261: putfield      #38                 // Field result:Ljava/util/List;
     264: lconst_1
     265: aload_0
     266: getfield      #38                 // Field result:Ljava/util/List;
     269: invokeinterface #216,  1          // InterfaceMethod java/util/List.size:()I
     274: i2l
     275: invokestatic  #169                // Method org/junit/Assert.assertEquals:(JJ)V
     278: return

  public void testGet_FromMemStoreOnly() throws java.io.IOException;
    Code:
       0: aload_0
       1: aload_0
       2: getfield      #9                  // Field name:Lorg/junit/rules/TestName;
       5: invokevirtual #112                // Method org/junit/rules/TestName.getMethodName:()Ljava/lang/String;
       8: invokespecial #194                // Method init:(Ljava/lang/String;)V
      11: aload_0
      12: getfield      #108                // Field store:Lorg/apache/hadoop/hbase/regionserver/HStore;
      15: new           #49                 // class org/apache/hadoop/hbase/KeyValue
      18: dup
      19: aload_0
      20: getfield      #16                 // Field row:[B
      23: aload_0
      24: getfield      #14                 // Field family:[B
      27: aload_0
      28: getfield      #20                 // Field qf1:[B
      31: lconst_1
      32: aconst_null
      33: checkcast     #48                 // class "[B"
      36: invokespecial #50                 // Method org/apache/hadoop/hbase/KeyValue."<init>":([B[B[BJ[B)V
      39: aconst_null
      40: invokevirtual #165                // Method org/apache/hadoop/hbase/regionserver/HStore.add:(Lorg/apache/hadoop/hbase/Cell;Lorg/apache/hadoop/hbase/regionserver/MemStoreSizing;)V
      43: aload_0
      44: getfield      #108                // Field store:Lorg/apache/hadoop/hbase/regionserver/HStore;
      47: new           #49                 // class org/apache/hadoop/hbase/KeyValue
      50: dup
      51: aload_0
      52: getfield      #16                 // Field row:[B
      55: aload_0
      56: getfield      #14                 // Field family:[B
      59: aload_0
      60: getfield      #22                 // Field qf2:[B
      63: lconst_1
      64: aconst_null
      65: checkcast     #48                 // class "[B"
      68: invokespecial #50                 // Method org/apache/hadoop/hbase/KeyValue."<init>":([B[B[BJ[B)V
      71: aconst_null
      72: invokevirtual #165                // Method org/apache/hadoop/hbase/regionserver/HStore.add:(Lorg/apache/hadoop/hbase/Cell;Lorg/apache/hadoop/hbase/regionserver/MemStoreSizing;)V
      75: aload_0
      76: getfield      #108                // Field store:Lorg/apache/hadoop/hbase/regionserver/HStore;
      79: new           #49                 // class org/apache/hadoop/hbase/KeyValue
      82: dup
      83: aload_0
      84: getfield      #16                 // Field row:[B
      87: aload_0
      88: getfield      #14                 // Field family:[B
      91: aload_0
      92: getfield      #24                 // Field qf3:[B
      95: lconst_1
      96: aconst_null
      97: checkcast     #48                 // class "[B"
     100: invokespecial #50                 // Method org/apache/hadoop/hbase/KeyValue."<init>":([B[B[BJ[B)V
     103: aconst_null
     104: invokevirtual #165                // Method org/apache/hadoop/hbase/regionserver/HStore.add:(Lorg/apache/hadoop/hbase/Cell;Lorg/apache/hadoop/hbase/regionserver/MemStoreSizing;)V
     107: aload_0
     108: getfield      #108                // Field store:Lorg/apache/hadoop/hbase/regionserver/HStore;
     111: new           #49                 // class org/apache/hadoop/hbase/KeyValue
     114: dup
     115: aload_0
     116: getfield      #16                 // Field row:[B
     119: aload_0
     120: getfield      #14                 // Field family:[B
     123: aload_0
     124: getfield      #26                 // Field qf4:[B
     127: lconst_1
     128: aconst_null
     129: checkcast     #48                 // class "[B"
     132: invokespecial #50                 // Method org/apache/hadoop/hbase/KeyValue."<init>":([B[B[BJ[B)V
     135: aconst_null
     136: invokevirtual #165                // Method org/apache/hadoop/hbase/regionserver/HStore.add:(Lorg/apache/hadoop/hbase/Cell;Lorg/apache/hadoop/hbase/regionserver/MemStoreSizing;)V
     139: aload_0
     140: getfield      #108                // Field store:Lorg/apache/hadoop/hbase/regionserver/HStore;
     143: new           #49                 // class org/apache/hadoop/hbase/KeyValue
     146: dup
     147: aload_0
     148: getfield      #16                 // Field row:[B
     151: aload_0
     152: getfield      #14                 // Field family:[B
     155: aload_0
     156: getfield      #28                 // Field qf5:[B
     159: lconst_1
     160: aconst_null
     161: checkcast     #48                 // class "[B"
     164: invokespecial #50                 // Method org/apache/hadoop/hbase/KeyValue."<init>":([B[B[BJ[B)V
     167: aconst_null
     168: invokevirtual #165                // Method org/apache/hadoop/hbase/regionserver/HStore.add:(Lorg/apache/hadoop/hbase/Cell;Lorg/apache/hadoop/hbase/regionserver/MemStoreSizing;)V
     171: aload_0
     172: getfield      #108                // Field store:Lorg/apache/hadoop/hbase/regionserver/HStore;
     175: new           #49                 // class org/apache/hadoop/hbase/KeyValue
     178: dup
     179: aload_0
     180: getfield      #16                 // Field row:[B
     183: aload_0
     184: getfield      #14                 // Field family:[B
     187: aload_0
     188: getfield      #30                 // Field qf6:[B
     191: lconst_1
     192: aconst_null
     193: checkcast     #48                 // class "[B"
     196: invokespecial #50                 // Method org/apache/hadoop/hbase/KeyValue."<init>":([B[B[BJ[B)V
     199: aconst_null
     200: invokevirtual #165                // Method org/apache/hadoop/hbase/regionserver/HStore.add:(Lorg/apache/hadoop/hbase/Cell;Lorg/apache/hadoop/hbase/regionserver/MemStoreSizing;)V
     203: aload_0
     204: aload_0
     205: getfield      #108                // Field store:Lorg/apache/hadoop/hbase/regionserver/HStore;
     208: aload_0
     209: getfield      #43                 // Field get:Lorg/apache/hadoop/hbase/client/Get;
     212: invokevirtual #214                // Method org/apache/hadoop/hbase/client/Get.getRow:()[B
     215: aload_0
     216: getfield      #34                 // Field qualifiers:Ljava/util/NavigableSet;
     219: invokestatic  #215                // Method org/apache/hadoop/hbase/HBaseTestingUtility.getFromStoreFile:(Lorg/apache/hadoop/hbase/regionserver/HStore;[BLjava/util/NavigableSet;)Ljava/util/List;
     222: putfield      #38                 // Field result:Ljava/util/List;
     225: aload_0
     226: invokespecial #217                // Method assertCheck:()V
     229: return

  public void testTimeRangeIfSomeCellsAreDroppedInFlush() throws java.io.IOException;
    Code:
       0: aload_0
       1: iconst_1
       2: invokespecial #218                // Method testTimeRangeIfSomeCellsAreDroppedInFlush:(I)V
       5: aload_0
       6: iconst_3
       7: invokespecial #218                // Method testTimeRangeIfSomeCellsAreDroppedInFlush:(I)V
      10: aload_0
      11: iconst_5
      12: invokespecial #218                // Method testTimeRangeIfSomeCellsAreDroppedInFlush:(I)V
      15: return

  public void testGet_FromFilesOnly() throws java.io.IOException;
    Code:
       0: aload_0
       1: aload_0
       2: getfield      #9                  // Field name:Lorg/junit/rules/TestName;
       5: invokevirtual #112                // Method org/junit/rules/TestName.getMethodName:()Ljava/lang/String;
       8: invokespecial #194                // Method init:(Ljava/lang/String;)V
      11: aload_0
      12: getfield      #108                // Field store:Lorg/apache/hadoop/hbase/regionserver/HStore;
      15: new           #49                 // class org/apache/hadoop/hbase/KeyValue
      18: dup
      19: aload_0
      20: getfield      #16                 // Field row:[B
      23: aload_0
      24: getfield      #14                 // Field family:[B
      27: aload_0
      28: getfield      #20                 // Field qf1:[B
      31: lconst_1
      32: aconst_null
      33: checkcast     #48                 // class "[B"
      36: invokespecial #50                 // Method org/apache/hadoop/hbase/KeyValue."<init>":([B[B[BJ[B)V
      39: aconst_null
      40: invokevirtual #165                // Method org/apache/hadoop/hbase/regionserver/HStore.add:(Lorg/apache/hadoop/hbase/Cell;Lorg/apache/hadoop/hbase/regionserver/MemStoreSizing;)V
      43: aload_0
      44: getfield      #108                // Field store:Lorg/apache/hadoop/hbase/regionserver/HStore;
      47: new           #49                 // class org/apache/hadoop/hbase/KeyValue
      50: dup
      51: aload_0
      52: getfield      #16                 // Field row:[B
      55: aload_0
      56: getfield      #14                 // Field family:[B
      59: aload_0
      60: getfield      #22                 // Field qf2:[B
      63: lconst_1
      64: aconst_null
      65: checkcast     #48                 // class "[B"
      68: invokespecial #50                 // Method org/apache/hadoop/hbase/KeyValue."<init>":([B[B[BJ[B)V
      71: aconst_null
      72: invokevirtual #165                // Method org/apache/hadoop/hbase/regionserver/HStore.add:(Lorg/apache/hadoop/hbase/Cell;Lorg/apache/hadoop/hbase/regionserver/MemStoreSizing;)V
      75: aload_0
      76: iconst_1
      77: invokespecial #2                  // Method flush:(I)V
      80: aload_0
      81: getfield      #108                // Field store:Lorg/apache/hadoop/hbase/regionserver/HStore;
      84: new           #49                 // class org/apache/hadoop/hbase/KeyValue
      87: dup
      88: aload_0
      89: getfield      #16                 // Field row:[B
      92: aload_0
      93: getfield      #14                 // Field family:[B
      96: aload_0
      97: getfield      #24                 // Field qf3:[B
     100: lconst_1
     101: aconst_null
     102: checkcast     #48                 // class "[B"
     105: invokespecial #50                 // Method org/apache/hadoop/hbase/KeyValue."<init>":([B[B[BJ[B)V
     108: aconst_null
     109: invokevirtual #165                // Method org/apache/hadoop/hbase/regionserver/HStore.add:(Lorg/apache/hadoop/hbase/Cell;Lorg/apache/hadoop/hbase/regionserver/MemStoreSizing;)V
     112: aload_0
     113: getfield      #108                // Field store:Lorg/apache/hadoop/hbase/regionserver/HStore;
     116: new           #49                 // class org/apache/hadoop/hbase/KeyValue
     119: dup
     120: aload_0
     121: getfield      #16                 // Field row:[B
     124: aload_0
     125: getfield      #14                 // Field family:[B
     128: aload_0
     129: getfield      #26                 // Field qf4:[B
     132: lconst_1
     133: aconst_null
     134: checkcast     #48                 // class "[B"
     137: invokespecial #50                 // Method org/apache/hadoop/hbase/KeyValue."<init>":([B[B[BJ[B)V
     140: aconst_null
     141: invokevirtual #165                // Method org/apache/hadoop/hbase/regionserver/HStore.add:(Lorg/apache/hadoop/hbase/Cell;Lorg/apache/hadoop/hbase/regionserver/MemStoreSizing;)V
     144: aload_0
     145: iconst_2
     146: invokespecial #2                  // Method flush:(I)V
     149: aload_0
     150: getfield      #108                // Field store:Lorg/apache/hadoop/hbase/regionserver/HStore;
     153: new           #49                 // class org/apache/hadoop/hbase/KeyValue
     156: dup
     157: aload_0
     158: getfield      #16                 // Field row:[B
     161: aload_0
     162: getfield      #14                 // Field family:[B
     165: aload_0
     166: getfield      #28                 // Field qf5:[B
     169: lconst_1
     170: aconst_null
     171: checkcast     #48                 // class "[B"
     174: invokespecial #50                 // Method org/apache/hadoop/hbase/KeyValue."<init>":([B[B[BJ[B)V
     177: aconst_null
     178: invokevirtual #165                // Method org/apache/hadoop/hbase/regionserver/HStore.add:(Lorg/apache/hadoop/hbase/Cell;Lorg/apache/hadoop/hbase/regionserver/MemStoreSizing;)V
     181: aload_0
     182: getfield      #108                // Field store:Lorg/apache/hadoop/hbase/regionserver/HStore;
     185: new           #49                 // class org/apache/hadoop/hbase/KeyValue
     188: dup
     189: aload_0
     190: getfield      #16                 // Field row:[B
     193: aload_0
     194: getfield      #14                 // Field family:[B
     197: aload_0
     198: getfield      #30                 // Field qf6:[B
     201: lconst_1
     202: aconst_null
     203: checkcast     #48                 // class "[B"
     206: invokespecial #50                 // Method org/apache/hadoop/hbase/KeyValue."<init>":([B[B[BJ[B)V
     209: aconst_null
     210: invokevirtual #165                // Method org/apache/hadoop/hbase/regionserver/HStore.add:(Lorg/apache/hadoop/hbase/Cell;Lorg/apache/hadoop/hbase/regionserver/MemStoreSizing;)V
     213: aload_0
     214: iconst_3
     215: invokespecial #2                  // Method flush:(I)V
     218: aload_0
     219: aload_0
     220: getfield      #108                // Field store:Lorg/apache/hadoop/hbase/regionserver/HStore;
     223: aload_0
     224: getfield      #43                 // Field get:Lorg/apache/hadoop/hbase/client/Get;
     227: invokevirtual #214                // Method org/apache/hadoop/hbase/client/Get.getRow:()[B
     230: aload_0
     231: getfield      #34                 // Field qualifiers:Ljava/util/NavigableSet;
     234: invokestatic  #215                // Method org/apache/hadoop/hbase/HBaseTestingUtility.getFromStoreFile:(Lorg/apache/hadoop/hbase/regionserver/HStore;[BLjava/util/NavigableSet;)Ljava/util/List;
     237: putfield      #38                 // Field result:Ljava/util/List;
     240: aload_0
     241: getfield      #38                 // Field result:Ljava/util/List;
     244: getstatic     #225                // Field org/apache/hadoop/hbase/CellComparatorImpl.COMPARATOR:Lorg/apache/hadoop/hbase/CellComparatorImpl;
     247: invokestatic  #226                // Method java/util/Collections.sort:(Ljava/util/List;Ljava/util/Comparator;)V
     250: aload_0
     251: invokespecial #217                // Method assertCheck:()V
     254: return

  public void testGet_FromMemStoreAndFiles() throws java.io.IOException;
    Code:
       0: aload_0
       1: aload_0
       2: getfield      #9                  // Field name:Lorg/junit/rules/TestName;
       5: invokevirtual #112                // Method org/junit/rules/TestName.getMethodName:()Ljava/lang/String;
       8: invokespecial #194                // Method init:(Ljava/lang/String;)V
      11: aload_0
      12: getfield      #108                // Field store:Lorg/apache/hadoop/hbase/regionserver/HStore;
      15: new           #49                 // class org/apache/hadoop/hbase/KeyValue
      18: dup
      19: aload_0
      20: getfield      #16                 // Field row:[B
      23: aload_0
      24: getfield      #14                 // Field family:[B
      27: aload_0
      28: getfield      #20                 // Field qf1:[B
      31: lconst_1
      32: aconst_null
      33: checkcast     #48                 // class "[B"
      36: invokespecial #50                 // Method org/apache/hadoop/hbase/KeyValue."<init>":([B[B[BJ[B)V
      39: aconst_null
      40: invokevirtual #165                // Method org/apache/hadoop/hbase/regionserver/HStore.add:(Lorg/apache/hadoop/hbase/Cell;Lorg/apache/hadoop/hbase/regionserver/MemStoreSizing;)V
      43: aload_0
      44: getfield      #108                // Field store:Lorg/apache/hadoop/hbase/regionserver/HStore;
      47: new           #49                 // class org/apache/hadoop/hbase/KeyValue
      50: dup
      51: aload_0
      52: getfield      #16                 // Field row:[B
      55: aload_0
      56: getfield      #14                 // Field family:[B
      59: aload_0
      60: getfield      #22                 // Field qf2:[B
      63: lconst_1
      64: aconst_null
      65: checkcast     #48                 // class "[B"
      68: invokespecial #50                 // Method org/apache/hadoop/hbase/KeyValue."<init>":([B[B[BJ[B)V
      71: aconst_null
      72: invokevirtual #165                // Method org/apache/hadoop/hbase/regionserver/HStore.add:(Lorg/apache/hadoop/hbase/Cell;Lorg/apache/hadoop/hbase/regionserver/MemStoreSizing;)V
      75: aload_0
      76: iconst_1
      77: invokespecial #2                  // Method flush:(I)V
      80: aload_0
      81: getfield      #108                // Field store:Lorg/apache/hadoop/hbase/regionserver/HStore;
      84: new           #49                 // class org/apache/hadoop/hbase/KeyValue
      87: dup
      88: aload_0
      89: getfield      #16                 // Field row:[B
      92: aload_0
      93: getfield      #14                 // Field family:[B
      96: aload_0
      97: getfield      #24                 // Field qf3:[B
     100: lconst_1
     101: aconst_null
     102: checkcast     #48                 // class "[B"
     105: invokespecial #50                 // Method org/apache/hadoop/hbase/KeyValue."<init>":([B[B[BJ[B)V
     108: aconst_null
     109: invokevirtual #165                // Method org/apache/hadoop/hbase/regionserver/HStore.add:(Lorg/apache/hadoop/hbase/Cell;Lorg/apache/hadoop/hbase/regionserver/MemStoreSizing;)V
     112: aload_0
     113: getfield      #108                // Field store:Lorg/apache/hadoop/hbase/regionserver/HStore;
     116: new           #49                 // class org/apache/hadoop/hbase/KeyValue
     119: dup
     120: aload_0
     121: getfield      #16                 // Field row:[B
     124: aload_0
     125: getfield      #14                 // Field family:[B
     128: aload_0
     129: getfield      #26                 // Field qf4:[B
     132: lconst_1
     133: aconst_null
     134: checkcast     #48                 // class "[B"
     137: invokespecial #50                 // Method org/apache/hadoop/hbase/KeyValue."<init>":([B[B[BJ[B)V
     140: aconst_null
     141: invokevirtual #165                // Method org/apache/hadoop/hbase/regionserver/HStore.add:(Lorg/apache/hadoop/hbase/Cell;Lorg/apache/hadoop/hbase/regionserver/MemStoreSizing;)V
     144: aload_0
     145: iconst_2
     146: invokespecial #2                  // Method flush:(I)V
     149: aload_0
     150: getfield      #108                // Field store:Lorg/apache/hadoop/hbase/regionserver/HStore;
     153: new           #49                 // class org/apache/hadoop/hbase/KeyValue
     156: dup
     157: aload_0
     158: getfield      #16                 // Field row:[B
     161: aload_0
     162: getfield      #14                 // Field family:[B
     165: aload_0
     166: getfield      #28                 // Field qf5:[B
     169: lconst_1
     170: aconst_null
     171: checkcast     #48                 // class "[B"
     174: invokespecial #50                 // Method org/apache/hadoop/hbase/KeyValue."<init>":([B[B[BJ[B)V
     177: aconst_null
     178: invokevirtual #165                // Method org/apache/hadoop/hbase/regionserver/HStore.add:(Lorg/apache/hadoop/hbase/Cell;Lorg/apache/hadoop/hbase/regionserver/MemStoreSizing;)V
     181: aload_0
     182: getfield      #108                // Field store:Lorg/apache/hadoop/hbase/regionserver/HStore;
     185: new           #49                 // class org/apache/hadoop/hbase/KeyValue
     188: dup
     189: aload_0
     190: getfield      #16                 // Field row:[B
     193: aload_0
     194: getfield      #14                 // Field family:[B
     197: aload_0
     198: getfield      #30                 // Field qf6:[B
     201: lconst_1
     202: aconst_null
     203: checkcast     #48                 // class "[B"
     206: invokespecial #50                 // Method org/apache/hadoop/hbase/KeyValue."<init>":([B[B[BJ[B)V
     209: aconst_null
     210: invokevirtual #165                // Method org/apache/hadoop/hbase/regionserver/HStore.add:(Lorg/apache/hadoop/hbase/Cell;Lorg/apache/hadoop/hbase/regionserver/MemStoreSizing;)V
     213: aload_0
     214: aload_0
     215: getfield      #108                // Field store:Lorg/apache/hadoop/hbase/regionserver/HStore;
     218: aload_0
     219: getfield      #43                 // Field get:Lorg/apache/hadoop/hbase/client/Get;
     222: invokevirtual #214                // Method org/apache/hadoop/hbase/client/Get.getRow:()[B
     225: aload_0
     226: getfield      #34                 // Field qualifiers:Ljava/util/NavigableSet;
     229: invokestatic  #215                // Method org/apache/hadoop/hbase/HBaseTestingUtility.getFromStoreFile:(Lorg/apache/hadoop/hbase/regionserver/HStore;[BLjava/util/NavigableSet;)Ljava/util/List;
     232: putfield      #38                 // Field result:Ljava/util/List;
     235: aload_0
     236: getfield      #38                 // Field result:Ljava/util/List;
     239: getstatic     #225                // Field org/apache/hadoop/hbase/CellComparatorImpl.COMPARATOR:Lorg/apache/hadoop/hbase/CellComparatorImpl;
     242: invokestatic  #226                // Method java/util/Collections.sort:(Ljava/util/List;Ljava/util/Comparator;)V
     245: aload_0
     246: invokespecial #217                // Method assertCheck:()V
     249: return

  public void tearDown() throws java.lang.Exception;
    Code:
       0: invokestatic  #233                // Method org/apache/hadoop/hbase/util/EnvironmentEdgeManagerTestHelper.reset:()V
       3: aload_0
       4: getfield      #108                // Field store:Lorg/apache/hadoop/hbase/regionserver/HStore;
       7: ifnull        27
      10: aload_0
      11: getfield      #108                // Field store:Lorg/apache/hadoop/hbase/regionserver/HStore;
      14: invokevirtual #208                // Method org/apache/hadoop/hbase/regionserver/HStore.close:()Lorg/apache/hbase/thirdparty/com/google/common/collect/ImmutableCollection;
      17: pop
      18: goto          22
      21: astore_1
      22: aload_0
      23: aconst_null
      24: putfield      #108                // Field store:Lorg/apache/hadoop/hbase/regionserver/HStore;
      27: aload_0
      28: getfield      #96                 // Field region:Lorg/apache/hadoop/hbase/regionserver/HRegion;
      31: ifnull        47
      34: aload_0
      35: getfield      #96                 // Field region:Lorg/apache/hadoop/hbase/regionserver/HRegion;
      38: invokevirtual #235                // Method org/apache/hadoop/hbase/regionserver/HRegion.close:()Ljava/util/Map;
      41: pop
      42: aload_0
      43: aconst_null
      44: putfield      #96                 // Field region:Lorg/apache/hadoop/hbase/regionserver/HRegion;
      47: return
    Exception table:
       from    to  target type
          10    18    21   Class java/io/IOException

  public static void tearDownAfterClass() throws java.io.IOException;
    Code:
       0: getstatic     #53                 // Field TEST_UTIL:Lorg/apache/hadoop/hbase/HBaseTestingUtility;
       3: invokevirtual #236                // Method org/apache/hadoop/hbase/HBaseTestingUtility.cleanupTestDir:()Z
       6: pop
       7: return

  public void testHandleErrorsInFlush() throws java.lang.Exception;
    Code:
       0: getstatic     #4                  // Field LOG:Lorg/slf4j/Logger;
       3: ldc           #237                // String Setting up a faulty file system that cannot write
       5: invokeinterface #113,  2          // InterfaceMethod org/slf4j/Logger.info:(Ljava/lang/String;)V
      10: getstatic     #53                 // Field TEST_UTIL:Lorg/apache/hadoop/hbase/HBaseTestingUtility;
      13: invokevirtual #54                 // Method org/apache/hadoop/hbase/HBaseTestingUtility.getConfiguration:()Lorg/apache/hadoop/conf/Configuration;
      16: invokestatic  #114                // Method org/apache/hadoop/hbase/HBaseConfiguration.create:(Lorg/apache/hadoop/conf/Configuration;)Lorg/apache/hadoop/conf/Configuration;
      19: astore_1
      20: aload_1
      21: ldc           #238                // String testhandleerrorsinflush
      23: iconst_1
      24: anewarray     #117                // class java/lang/String
      27: dup
      28: iconst_0
      29: ldc           #118                // String foo
      31: aastore
      32: invokestatic  #119                // Method org/apache/hadoop/hbase/security/User.createUserForTesting:(Lorg/apache/hadoop/conf/Configuration;Ljava/lang/String;[Ljava/lang/String;)Lorg/apache/hadoop/hbase/security/User;
      35: astore_2
      36: aload_1
      37: ldc           #120                // String fs.file.impl
      39: ldc           #121                // class org/apache/hadoop/hbase/regionserver/TestHStore$FaultyFileSystem
      41: ldc           #122                // class org/apache/hadoop/fs/FileSystem
      43: invokevirtual #123                // Method org/apache/hadoop/conf/Configuration.setClass:(Ljava/lang/String;Ljava/lang/Class;Ljava/lang/Class;)V
      46: aload_2
      47: new           #239                // class org/apache/hadoop/hbase/regionserver/TestHStore$2
      50: dup
      51: aload_0
      52: aload_1
      53: invokespecial #240                // Method org/apache/hadoop/hbase/regionserver/TestHStore$2."<init>":(Lorg/apache/hadoop/hbase/regionserver/TestHStore;Lorg/apache/hadoop/conf/Configuration;)V
      56: invokevirtual #126                // Method org/apache/hadoop/hbase/security/User.runAs:(Ljava/security/PrivilegedExceptionAction;)Ljava/lang/Object;
      59: pop
      60: aload_2
      61: invokevirtual #241                // Method org/apache/hadoop/hbase/security/User.getUGI:()Lorg/apache/hadoop/security/UserGroupInformation;
      64: invokestatic  #242                // Method org/apache/hadoop/fs/FileSystem.closeAllForUGI:(Lorg/apache/hadoop/security/UserGroupInformation;)V
      67: return

  java.util.List<org.apache.hadoop.hbase.Cell> getKeyValueSet(long[], int, byte[], byte[]);
    Code:
       0: new           #35                 // class java/util/ArrayList
       3: dup
       4: invokespecial #36                 // Method java/util/ArrayList."<init>":()V
       7: astore        5
       9: iconst_1
      10: istore        6
      12: iload         6
      14: iload_2
      15: if_icmpgt     86
      18: iload         6
      20: invokestatic  #137                // Method org/apache/hadoop/hbase/util/Bytes.toBytes:(I)[B
      23: astore        7
      25: aload_1
      26: astore        8
      28: aload         8
      30: arraylength
      31: istore        9
      33: iconst_0
      34: istore        10
      36: iload         10
      38: iload         9
      40: if_icmpge     80
      43: aload         8
      45: iload         10
      47: laload
      48: lstore        11
      50: aload         5
      52: new           #49                 // class org/apache/hadoop/hbase/KeyValue
      55: dup
      56: aload         7
      58: aload         4
      60: aload_3
      61: lload         11
      63: aload         7
      65: invokespecial #50                 // Method org/apache/hadoop/hbase/KeyValue."<init>":([B[B[BJ[B)V
      68: invokeinterface #51,  2           // InterfaceMethod java/util/List.add:(Ljava/lang/Object;)Z
      73: pop
      74: iinc          10, 1
      77: goto          36
      80: iinc          6, 1
      83: goto          12
      86: aload         5
      88: areturn

  public void testMultipleTimestamps() throws java.io.IOException;
    Code:
       0: iconst_1
       1: istore_1
       2: iconst_4
       3: newarray       long
       5: dup
       6: iconst_0
       7: lconst_1
       8: lastore
       9: dup
      10: iconst_1
      11: ldc2_w        #250                // long 5l
      14: lastore
      15: dup
      16: iconst_2
      17: ldc2_w        #252                // long 10l
      20: lastore
      21: dup
      22: iconst_3
      23: ldc2_w        #254                // long 20l
      26: lastore
      27: astore_2
      28: iconst_2
      29: newarray       long
      31: dup
      32: iconst_0
      33: ldc2_w        #256                // long 30l
      36: lastore
      37: dup
      38: iconst_1
      39: ldc2_w        #258                // long 80l
      42: lastore
      43: astore_3
      44: aload_0
      45: aload_0
      46: getfield      #9                  // Field name:Lorg/junit/rules/TestName;
      49: invokevirtual #112                // Method org/junit/rules/TestName.getMethodName:()Ljava/lang/String;
      52: invokespecial #194                // Method init:(Ljava/lang/String;)V
      55: aload_0
      56: aload_2
      57: iload_1
      58: aload_0
      59: getfield      #20                 // Field qf1:[B
      62: aload_0
      63: getfield      #14                 // Field family:[B
      66: invokevirtual #260                // Method getKeyValueSet:([JI[B[B)Ljava/util/List;
      69: astore        4
      71: aload         4
      73: invokeinterface #261,  1          // InterfaceMethod java/util/List.iterator:()Ljava/util/Iterator;
      78: astore        5
      80: aload         5
      82: invokeinterface #46,  1           // InterfaceMethod java/util/Iterator.hasNext:()Z
      87: ifeq          115
      90: aload         5
      92: invokeinterface #47,  1           // InterfaceMethod java/util/Iterator.next:()Ljava/lang/Object;
      97: checkcast     #262                // class org/apache/hadoop/hbase/Cell
     100: astore        6
     102: aload_0
     103: getfield      #108                // Field store:Lorg/apache/hadoop/hbase/regionserver/HStore;
     106: aload         6
     108: aconst_null
     109: invokevirtual #165                // Method org/apache/hadoop/hbase/regionserver/HStore.add:(Lorg/apache/hadoop/hbase/Cell;Lorg/apache/hadoop/hbase/regionserver/MemStoreSizing;)V
     112: goto          80
     115: aload_0
     116: getfield      #108                // Field store:Lorg/apache/hadoop/hbase/regionserver/HStore;
     119: invokevirtual #227                // Method org/apache/hadoop/hbase/regionserver/HStore.snapshot:()V
     122: aload_0
     123: getfield      #108                // Field store:Lorg/apache/hadoop/hbase/regionserver/HStore;
     126: aload_0
     127: dup
     128: getfield      #40                 // Field id:J
     131: dup2_x1
     132: lconst_1
     133: ladd
     134: putfield      #40                 // Field id:J
     137: invokestatic  #3                  // Method flushStore:(Lorg/apache/hadoop/hbase/regionserver/HStore;J)V
     140: aload_0
     141: aload_3
     142: iload_1
     143: aload_0
     144: getfield      #20                 // Field qf1:[B
     147: aload_0
     148: getfield      #14                 // Field family:[B
     151: invokevirtual #260                // Method getKeyValueSet:([JI[B[B)Ljava/util/List;
     154: astore        5
     156: aload         5
     158: invokeinterface #261,  1          // InterfaceMethod java/util/List.iterator:()Ljava/util/Iterator;
     163: astore        6
     165: aload         6
     167: invokeinterface #46,  1           // InterfaceMethod java/util/Iterator.hasNext:()Z
     172: ifeq          200
     175: aload         6
     177: invokeinterface #47,  1           // InterfaceMethod java/util/Iterator.next:()Ljava/lang/Object;
     182: checkcast     #262                // class org/apache/hadoop/hbase/Cell
     185: astore        7
     187: aload_0
     188: getfield      #108                // Field store:Lorg/apache/hadoop/hbase/regionserver/HStore;
     191: aload         7
     193: aconst_null
     194: invokevirtual #165                // Method org/apache/hadoop/hbase/regionserver/HStore.add:(Lorg/apache/hadoop/hbase/Cell;Lorg/apache/hadoop/hbase/regionserver/MemStoreSizing;)V
     197: goto          165
     200: new           #41                 // class org/apache/hadoop/hbase/client/Get
     203: dup
     204: iconst_1
     205: invokestatic  #137                // Method org/apache/hadoop/hbase/util/Bytes.toBytes:(I)[B
     208: invokespecial #42                 // Method org/apache/hadoop/hbase/client/Get."<init>":([B)V
     211: astore        7
     213: aload         7
     215: aload_0
     216: getfield      #14                 // Field family:[B
     219: aload_0
     220: getfield      #20                 // Field qf1:[B
     223: invokevirtual #52                 // Method org/apache/hadoop/hbase/client/Get.addColumn:([B[B)Lorg/apache/hadoop/hbase/client/Get;
     226: pop
     227: aload         7
     229: lconst_0
     230: ldc2_w        #263                // long 15l
     233: invokevirtual #265                // Method org/apache/hadoop/hbase/client/Get.setTimeRange:(JJ)Lorg/apache/hadoop/hbase/client/Get;
     236: pop
     237: aload_0
     238: getfield      #108                // Field store:Lorg/apache/hadoop/hbase/regionserver/HStore;
     241: aload         7
     243: invokestatic  #266                // Method org/apache/hadoop/hbase/HBaseTestingUtility.getFromStoreFile:(Lorg/apache/hadoop/hbase/regionserver/HStore;Lorg/apache/hadoop/hbase/client/Get;)Ljava/util/List;
     246: astore        6
     248: aload         6
     250: invokeinterface #216,  1          // InterfaceMethod java/util/List.size:()I
     255: ifle          262
     258: iconst_1
     259: goto          263
     262: iconst_0
     263: invokestatic  #178                // Method org/junit/Assert.assertTrue:(Z)V
     266: aload         7
     268: ldc2_w        #267                // long 40l
     271: ldc2_w        #269                // long 90l
     274: invokevirtual #265                // Method org/apache/hadoop/hbase/client/Get.setTimeRange:(JJ)Lorg/apache/hadoop/hbase/client/Get;
     277: pop
     278: aload_0
     279: getfield      #108                // Field store:Lorg/apache/hadoop/hbase/regionserver/HStore;
     282: aload         7
     284: invokestatic  #266                // Method org/apache/hadoop/hbase/HBaseTestingUtility.getFromStoreFile:(Lorg/apache/hadoop/hbase/regionserver/HStore;Lorg/apache/hadoop/hbase/client/Get;)Ljava/util/List;
     287: astore        6
     289: aload         6
     291: invokeinterface #216,  1          // InterfaceMethod java/util/List.size:()I
     296: ifle          303
     299: iconst_1
     300: goto          304
     303: iconst_0
     304: invokestatic  #178                // Method org/junit/Assert.assertTrue:(Z)V
     307: aload         7
     309: ldc2_w        #252                // long 10l
     312: ldc2_w        #271                // long 45l
     315: invokevirtual #265                // Method org/apache/hadoop/hbase/client/Get.setTimeRange:(JJ)Lorg/apache/hadoop/hbase/client/Get;
     318: pop
     319: aload_0
     320: getfield      #108                // Field store:Lorg/apache/hadoop/hbase/regionserver/HStore;
     323: aload         7
     325: invokestatic  #266                // Method org/apache/hadoop/hbase/HBaseTestingUtility.getFromStoreFile:(Lorg/apache/hadoop/hbase/regionserver/HStore;Lorg/apache/hadoop/hbase/client/Get;)Ljava/util/List;
     328: astore        6
     330: aload         6
     332: invokeinterface #216,  1          // InterfaceMethod java/util/List.size:()I
     337: ifle          344
     340: iconst_1
     341: goto          345
     344: iconst_0
     345: invokestatic  #178                // Method org/junit/Assert.assertTrue:(Z)V
     348: aload         7
     350: ldc2_w        #258                // long 80l
     353: ldc2_w        #273                // long 145l
     356: invokevirtual #265                // Method org/apache/hadoop/hbase/client/Get.setTimeRange:(JJ)Lorg/apache/hadoop/hbase/client/Get;
     359: pop
     360: aload_0
     361: getfield      #108                // Field store:Lorg/apache/hadoop/hbase/regionserver/HStore;
     364: aload         7
     366: invokestatic  #266                // Method org/apache/hadoop/hbase/HBaseTestingUtility.getFromStoreFile:(Lorg/apache/hadoop/hbase/regionserver/HStore;Lorg/apache/hadoop/hbase/client/Get;)Ljava/util/List;
     369: astore        6
     371: aload         6
     373: invokeinterface #216,  1          // InterfaceMethod java/util/List.size:()I
     378: ifle          385
     381: iconst_1
     382: goto          386
     385: iconst_0
     386: invokestatic  #178                // Method org/junit/Assert.assertTrue:(Z)V
     389: aload         7
     391: lconst_1
     392: ldc2_w        #211                // long 2l
     395: invokevirtual #265                // Method org/apache/hadoop/hbase/client/Get.setTimeRange:(JJ)Lorg/apache/hadoop/hbase/client/Get;
     398: pop
     399: aload_0
     400: getfield      #108                // Field store:Lorg/apache/hadoop/hbase/regionserver/HStore;
     403: aload         7
     405: invokestatic  #266                // Method org/apache/hadoop/hbase/HBaseTestingUtility.getFromStoreFile:(Lorg/apache/hadoop/hbase/regionserver/HStore;Lorg/apache/hadoop/hbase/client/Get;)Ljava/util/List;
     408: astore        6
     410: aload         6
     412: invokeinterface #216,  1          // InterfaceMethod java/util/List.size:()I
     417: ifle          424
     420: iconst_1
     421: goto          425
     424: iconst_0
     425: invokestatic  #178                // Method org/junit/Assert.assertTrue:(Z)V
     428: aload         7
     430: ldc2_w        #269                // long 90l
     433: ldc2_w        #275                // long 200l
     436: invokevirtual #265                // Method org/apache/hadoop/hbase/client/Get.setTimeRange:(JJ)Lorg/apache/hadoop/hbase/client/Get;
     439: pop
     440: aload_0
     441: getfield      #108                // Field store:Lorg/apache/hadoop/hbase/regionserver/HStore;
     444: aload         7
     446: invokestatic  #266                // Method org/apache/hadoop/hbase/HBaseTestingUtility.getFromStoreFile:(Lorg/apache/hadoop/hbase/regionserver/HStore;Lorg/apache/hadoop/hbase/client/Get;)Ljava/util/List;
     449: astore        6
     451: aload         6
     453: invokeinterface #216,  1          // InterfaceMethod java/util/List.size:()I
     458: ifne          465
     461: iconst_1
     462: goto          466
     465: iconst_0
     466: invokestatic  #178                // Method org/junit/Assert.assertTrue:(Z)V
     469: return

  public void testSplitWithEmptyColFam() throws java.io.IOException;
    Code:
       0: aload_0
       1: aload_0
       2: getfield      #9                  // Field name:Lorg/junit/rules/TestName;
       5: invokevirtual #112                // Method org/junit/rules/TestName.getMethodName:()Ljava/lang/String;
       8: invokespecial #194                // Method init:(Ljava/lang/String;)V
      11: aload_0
      12: getfield      #108                // Field store:Lorg/apache/hadoop/hbase/regionserver/HStore;
      15: invokevirtual #277                // Method org/apache/hadoop/hbase/regionserver/HStore.getSplitPoint:()Ljava/util/Optional;
      18: invokevirtual #171                // Method java/util/Optional.isPresent:()Z
      21: invokestatic  #172                // Method org/junit/Assert.assertFalse:(Z)V
      24: aload_0
      25: getfield      #108                // Field store:Lorg/apache/hadoop/hbase/regionserver/HStore;
      28: invokevirtual #209                // Method org/apache/hadoop/hbase/regionserver/HStore.getHRegion:()Lorg/apache/hadoop/hbase/regionserver/HRegion;
      31: aconst_null
      32: invokevirtual #278                // Method org/apache/hadoop/hbase/regionserver/HRegion.forceSplit:([B)V
      35: aload_0
      36: getfield      #108                // Field store:Lorg/apache/hadoop/hbase/regionserver/HStore;
      39: invokevirtual #277                // Method org/apache/hadoop/hbase/regionserver/HStore.getSplitPoint:()Ljava/util/Optional;
      42: invokevirtual #171                // Method java/util/Optional.isPresent:()Z
      45: invokestatic  #172                // Method org/junit/Assert.assertFalse:(Z)V
      48: aload_0
      49: getfield      #108                // Field store:Lorg/apache/hadoop/hbase/regionserver/HStore;
      52: invokevirtual #209                // Method org/apache/hadoop/hbase/regionserver/HStore.getHRegion:()Lorg/apache/hadoop/hbase/regionserver/HRegion;
      55: invokevirtual #279                // Method org/apache/hadoop/hbase/regionserver/HRegion.clearSplit:()V
      58: return

  public void testStoreUsesConfigurationFromHcdAndHtd() throws java.lang.Exception;
    Code:
       0: ldc_w         #280                // String hbase.regionserver.thread.compaction.throttle
       3: astore_1
       4: ldc2_w        #252                // long 10l
       7: lstore_2
       8: invokestatic  #127                // Method org/apache/hadoop/hbase/HBaseConfiguration.create:()Lorg/apache/hadoop/conf/Configuration;
      11: astore        4
      13: aload         4
      15: ldc_w         #280                // String hbase.regionserver.thread.compaction.throttle
      18: lload_2
      19: invokevirtual #281                // Method org/apache/hadoop/conf/Configuration.setLong:(Ljava/lang/String;J)V
      22: aload_0
      23: new           #67                 // class java/lang/StringBuilder
      26: dup
      27: invokespecial #68                 // Method java/lang/StringBuilder."<init>":()V
      30: aload_0
      31: getfield      #9                  // Field name:Lorg/junit/rules/TestName;
      34: invokevirtual #112                // Method org/junit/rules/TestName.getMethodName:()Ljava/lang/String;
      37: invokevirtual #70                 // Method java/lang/StringBuilder.append:(Ljava/lang/String;)Ljava/lang/StringBuilder;
      40: ldc_w         #282                // String -xml
      43: invokevirtual #70                 // Method java/lang/StringBuilder.append:(Ljava/lang/String;)Ljava/lang/StringBuilder;
      46: invokevirtual #71                 // Method java/lang/StringBuilder.toString:()Ljava/lang/String;
      49: aload         4
      51: invokespecial #5                  // Method init:(Ljava/lang/String;Lorg/apache/hadoop/conf/Configuration;)Lorg/apache/hadoop/hbase/regionserver/HStore;
      54: pop
      55: aload_0
      56: getfield      #108                // Field store:Lorg/apache/hadoop/hbase/regionserver/HStore;
      59: lload_2
      60: lconst_1
      61: ladd
      62: invokevirtual #283                // Method org/apache/hadoop/hbase/regionserver/HStore.throttleCompaction:(J)Z
      65: invokestatic  #178                // Method org/junit/Assert.assertTrue:(Z)V
      68: aload_0
      69: getfield      #108                // Field store:Lorg/apache/hadoop/hbase/regionserver/HStore;
      72: lload_2
      73: invokevirtual #283                // Method org/apache/hadoop/hbase/regionserver/HStore.throttleCompaction:(J)Z
      76: invokestatic  #172                // Method org/junit/Assert.assertFalse:(Z)V
      79: lload_2
      80: lconst_1
      81: lsub
      82: lstore_2
      83: aload_0
      84: new           #67                 // class java/lang/StringBuilder
      87: dup
      88: invokespecial #68                 // Method java/lang/StringBuilder."<init>":()V
      91: aload_0
      92: getfield      #9                  // Field name:Lorg/junit/rules/TestName;
      95: invokevirtual #112                // Method org/junit/rules/TestName.getMethodName:()Ljava/lang/String;
      98: invokevirtual #70                 // Method java/lang/StringBuilder.append:(Ljava/lang/String;)Ljava/lang/StringBuilder;
     101: ldc_w         #284                // String -htd
     104: invokevirtual #70                 // Method java/lang/StringBuilder.append:(Ljava/lang/String;)Ljava/lang/StringBuilder;
     107: invokevirtual #71                 // Method java/lang/StringBuilder.toString:()Ljava/lang/String;
     110: aload         4
     112: aload_0
     113: getfield      #12                 // Field table:[B
     116: invokestatic  #59                 // Method org/apache/hadoop/hbase/TableName.valueOf:([B)Lorg/apache/hadoop/hbase/TableName;
     119: invokestatic  #60                 // Method org/apache/hadoop/hbase/client/TableDescriptorBuilder.newBuilder:(Lorg/apache/hadoop/hbase/TableName;)Lorg/apache/hadoop/hbase/client/TableDescriptorBuilder;
     122: ldc_w         #280                // String hbase.regionserver.thread.compaction.throttle
     125: lload_2
     126: invokestatic  #285                // Method java/lang/Long.toString:(J)Ljava/lang/String;
     129: invokevirtual #286                // Method org/apache/hadoop/hbase/client/TableDescriptorBuilder.setValue:(Ljava/lang/String;Ljava/lang/String;)Lorg/apache/hadoop/hbase/client/TableDescriptorBuilder;
     132: aload_0
     133: getfield      #14                 // Field family:[B
     136: invokestatic  #287                // Method org/apache/hadoop/hbase/client/ColumnFamilyDescriptorBuilder.of:([B)Lorg/apache/hadoop/hbase/client/ColumnFamilyDescriptor;
     139: invokespecial #61                 // Method init:(Ljava/lang/String;Lorg/apache/hadoop/conf/Configuration;Lorg/apache/hadoop/hbase/client/TableDescriptorBuilder;Lorg/apache/hadoop/hbase/client/ColumnFamilyDescriptor;)Lorg/apache/hadoop/hbase/regionserver/HStore;
     142: pop
     143: aload_0
     144: getfield      #108                // Field store:Lorg/apache/hadoop/hbase/regionserver/HStore;
     147: lload_2
     148: lconst_1
     149: ladd
     150: invokevirtual #283                // Method org/apache/hadoop/hbase/regionserver/HStore.throttleCompaction:(J)Z
     153: invokestatic  #178                // Method org/junit/Assert.assertTrue:(Z)V
     156: aload_0
     157: getfield      #108                // Field store:Lorg/apache/hadoop/hbase/regionserver/HStore;
     160: lload_2
     161: invokevirtual #283                // Method org/apache/hadoop/hbase/regionserver/HStore.throttleCompaction:(J)Z
     164: invokestatic  #172                // Method org/junit/Assert.assertFalse:(Z)V
     167: lload_2
     168: lconst_1
     169: lsub
     170: lstore_2
     171: aload_0
     172: new           #67                 // class java/lang/StringBuilder
     175: dup
     176: invokespecial #68                 // Method java/lang/StringBuilder."<init>":()V
     179: aload_0
     180: getfield      #9                  // Field name:Lorg/junit/rules/TestName;
     183: invokevirtual #112                // Method org/junit/rules/TestName.getMethodName:()Ljava/lang/String;
     186: invokevirtual #70                 // Method java/lang/StringBuilder.append:(Ljava/lang/String;)Ljava/lang/StringBuilder;
     189: ldc_w         #288                // String -hcd
     192: invokevirtual #70                 // Method java/lang/StringBuilder.append:(Ljava/lang/String;)Ljava/lang/StringBuilder;
     195: invokevirtual #71                 // Method java/lang/StringBuilder.toString:()Ljava/lang/String;
     198: aload         4
     200: aload_0
     201: getfield      #12                 // Field table:[B
     204: invokestatic  #59                 // Method org/apache/hadoop/hbase/TableName.valueOf:([B)Lorg/apache/hadoop/hbase/TableName;
     207: invokestatic  #60                 // Method org/apache/hadoop/hbase/client/TableDescriptorBuilder.newBuilder:(Lorg/apache/hadoop/hbase/TableName;)Lorg/apache/hadoop/hbase/client/TableDescriptorBuilder;
     210: ldc_w         #280                // String hbase.regionserver.thread.compaction.throttle
     213: lload_2
     214: invokestatic  #285                // Method java/lang/Long.toString:(J)Ljava/lang/String;
     217: invokevirtual #286                // Method org/apache/hadoop/hbase/client/TableDescriptorBuilder.setValue:(Ljava/lang/String;Ljava/lang/String;)Lorg/apache/hadoop/hbase/client/TableDescriptorBuilder;
     220: aload_0
     221: getfield      #14                 // Field family:[B
     224: invokestatic  #55                 // Method org/apache/hadoop/hbase/client/ColumnFamilyDescriptorBuilder.newBuilder:([B)Lorg/apache/hadoop/hbase/client/ColumnFamilyDescriptorBuilder;
     227: ldc_w         #280                // String hbase.regionserver.thread.compaction.throttle
     230: lload_2
     231: invokestatic  #285                // Method java/lang/Long.toString:(J)Ljava/lang/String;
     234: invokevirtual #289                // Method org/apache/hadoop/hbase/client/ColumnFamilyDescriptorBuilder.setValue:(Ljava/lang/String;Ljava/lang/String;)Lorg/apache/hadoop/hbase/client/ColumnFamilyDescriptorBuilder;
     237: invokevirtual #57                 // Method org/apache/hadoop/hbase/client/ColumnFamilyDescriptorBuilder.build:()Lorg/apache/hadoop/hbase/client/ColumnFamilyDescriptor;
     240: invokespecial #61                 // Method init:(Ljava/lang/String;Lorg/apache/hadoop/conf/Configuration;Lorg/apache/hadoop/hbase/client/TableDescriptorBuilder;Lorg/apache/hadoop/hbase/client/ColumnFamilyDescriptor;)Lorg/apache/hadoop/hbase/regionserver/HStore;
     243: pop
     244: aload_0
     245: getfield      #108                // Field store:Lorg/apache/hadoop/hbase/regionserver/HStore;
     248: lload_2
     249: lconst_1
     250: ladd
     251: invokevirtual #283                // Method org/apache/hadoop/hbase/regionserver/HStore.throttleCompaction:(J)Z
     254: invokestatic  #178                // Method org/junit/Assert.assertTrue:(Z)V
     257: aload_0
     258: getfield      #108                // Field store:Lorg/apache/hadoop/hbase/regionserver/HStore;
     261: lload_2
     262: invokevirtual #283                // Method org/apache/hadoop/hbase/regionserver/HStore.throttleCompaction:(J)Z
     265: invokestatic  #172                // Method org/junit/Assert.assertFalse:(Z)V
     268: return

  public void testStoreUsesSearchEngineOverride() throws java.lang.Exception;
    Code:
       0: invokestatic  #127                // Method org/apache/hadoop/hbase/HBaseConfiguration.create:()Lorg/apache/hadoop/conf/Configuration;
       3: astore_1
       4: aload_1
       5: ldc_w         #291                // String hbase.hstore.engine.class
       8: ldc_w         #292                // class org/apache/hadoop/hbase/regionserver/TestHStore$DummyStoreEngine
      11: invokevirtual #293                // Method java/lang/Class.getName:()Ljava/lang/String;
      14: invokevirtual #294                // Method org/apache/hadoop/conf/Configuration.set:(Ljava/lang/String;Ljava/lang/String;)V
      17: aload_0
      18: aload_0
      19: getfield      #9                  // Field name:Lorg/junit/rules/TestName;
      22: invokevirtual #112                // Method org/junit/rules/TestName.getMethodName:()Ljava/lang/String;
      25: aload_1
      26: invokespecial #5                  // Method init:(Ljava/lang/String;Lorg/apache/hadoop/conf/Configuration;)Lorg/apache/hadoop/hbase/regionserver/HStore;
      29: pop
      30: getstatic     #295                // Field org/apache/hadoop/hbase/regionserver/TestHStore$DummyStoreEngine.lastCreatedCompactor:Lorg/apache/hadoop/hbase/regionserver/compactions/DefaultCompactor;
      33: aload_0
      34: getfield      #108                // Field store:Lorg/apache/hadoop/hbase/regionserver/HStore;
      37: getfield      #296                // Field org/apache/hadoop/hbase/regionserver/HStore.storeEngine:Lorg/apache/hadoop/hbase/regionserver/StoreEngine;
      40: invokevirtual #297                // Method org/apache/hadoop/hbase/regionserver/StoreEngine.getCompactor:()Lorg/apache/hadoop/hbase/regionserver/compactions/Compactor;
      43: invokestatic  #145                // Method org/junit/Assert.assertEquals:(Ljava/lang/Object;Ljava/lang/Object;)V
      46: return

  public void testRefreshStoreFiles() throws java.lang.Exception;
    Code:
       0: aload_0
       1: aload_0
       2: getfield      #9                  // Field name:Lorg/junit/rules/TestName;
       5: invokevirtual #112                // Method org/junit/rules/TestName.getMethodName:()Ljava/lang/String;
       8: invokespecial #194                // Method init:(Ljava/lang/String;)V
      11: lconst_0
      12: aload_0
      13: getfield      #108                // Field store:Lorg/apache/hadoop/hbase/regionserver/HStore;
      16: invokevirtual #213                // Method org/apache/hadoop/hbase/regionserver/HStore.getStorefilesCount:()I
      19: i2l
      20: invokestatic  #169                // Method org/junit/Assert.assertEquals:(JJ)V
      23: aload_0
      24: getfield      #108                // Field store:Lorg/apache/hadoop/hbase/regionserver/HStore;
      27: invokevirtual #310                // Method org/apache/hadoop/hbase/regionserver/HStore.refreshStoreFiles:()V
      30: lconst_0
      31: aload_0
      32: getfield      #108                // Field store:Lorg/apache/hadoop/hbase/regionserver/HStore;
      35: invokevirtual #213                // Method org/apache/hadoop/hbase/regionserver/HStore.getStorefilesCount:()I
      38: i2l
      39: invokestatic  #169                // Method org/junit/Assert.assertEquals:(JJ)V
      42: aload_0
      43: getfield      #108                // Field store:Lorg/apache/hadoop/hbase/regionserver/HStore;
      46: new           #49                 // class org/apache/hadoop/hbase/KeyValue
      49: dup
      50: aload_0
      51: getfield      #16                 // Field row:[B
      54: aload_0
      55: getfield      #14                 // Field family:[B
      58: aload_0
      59: getfield      #20                 // Field qf1:[B
      62: lconst_1
      63: aconst_null
      64: checkcast     #48                 // class "[B"
      67: invokespecial #50                 // Method org/apache/hadoop/hbase/KeyValue."<init>":([B[B[BJ[B)V
      70: aconst_null
      71: invokevirtual #165                // Method org/apache/hadoop/hbase/regionserver/HStore.add:(Lorg/apache/hadoop/hbase/Cell;Lorg/apache/hadoop/hbase/regionserver/MemStoreSizing;)V
      74: aload_0
      75: iconst_1
      76: invokespecial #2                  // Method flush:(I)V
      79: lconst_1
      80: aload_0
      81: getfield      #108                // Field store:Lorg/apache/hadoop/hbase/regionserver/HStore;
      84: invokevirtual #213                // Method org/apache/hadoop/hbase/regionserver/HStore.getStorefilesCount:()I
      87: i2l
      88: invokestatic  #169                // Method org/junit/Assert.assertEquals:(JJ)V
      91: aload_0
      92: invokespecial #311                // Method addStoreFile:()V
      95: lconst_1
      96: aload_0
      97: getfield      #108                // Field store:Lorg/apache/hadoop/hbase/regionserver/HStore;
     100: invokevirtual #213                // Method org/apache/hadoop/hbase/regionserver/HStore.getStorefilesCount:()I
     103: i2l
     104: invokestatic  #169                // Method org/junit/Assert.assertEquals:(JJ)V
     107: aload_0
     108: getfield      #108                // Field store:Lorg/apache/hadoop/hbase/regionserver/HStore;
     111: invokevirtual #310                // Method org/apache/hadoop/hbase/regionserver/HStore.refreshStoreFiles:()V
     114: ldc2_w        #211                // long 2l
     117: aload_0
     118: getfield      #108                // Field store:Lorg/apache/hadoop/hbase/regionserver/HStore;
     121: invokevirtual #213                // Method org/apache/hadoop/hbase/regionserver/HStore.getStorefilesCount:()I
     124: i2l
     125: invokestatic  #169                // Method org/junit/Assert.assertEquals:(JJ)V
     128: aload_0
     129: invokespecial #311                // Method addStoreFile:()V
     132: aload_0
     133: invokespecial #311                // Method addStoreFile:()V
     136: aload_0
     137: invokespecial #311                // Method addStoreFile:()V
     140: ldc2_w        #211                // long 2l
     143: aload_0
     144: getfield      #108                // Field store:Lorg/apache/hadoop/hbase/regionserver/HStore;
     147: invokevirtual #213                // Method org/apache/hadoop/hbase/regionserver/HStore.getStorefilesCount:()I
     150: i2l
     151: invokestatic  #169                // Method org/junit/Assert.assertEquals:(JJ)V
     154: aload_0
     155: getfield      #108                // Field store:Lorg/apache/hadoop/hbase/regionserver/HStore;
     158: invokevirtual #310                // Method org/apache/hadoop/hbase/regionserver/HStore.refreshStoreFiles:()V
     161: ldc2_w        #250                // long 5l
     164: aload_0
     165: getfield      #108                // Field store:Lorg/apache/hadoop/hbase/regionserver/HStore;
     168: invokevirtual #213                // Method org/apache/hadoop/hbase/regionserver/HStore.getStorefilesCount:()I
     171: i2l
     172: invokestatic  #169                // Method org/junit/Assert.assertEquals:(JJ)V
     175: aload_0
     176: iconst_0
     177: invokespecial #312                // Method closeCompactedFile:(I)V
     180: aload_0
     181: iconst_0
     182: invokespecial #313                // Method archiveStoreFile:(I)V
     185: ldc2_w        #250                // long 5l
     188: aload_0
     189: getfield      #108                // Field store:Lorg/apache/hadoop/hbase/regionserver/HStore;
     192: invokevirtual #213                // Method org/apache/hadoop/hbase/regionserver/HStore.getStorefilesCount:()I
     195: i2l
     196: invokestatic  #169                // Method org/junit/Assert.assertEquals:(JJ)V
     199: aload_0
     200: getfield      #108                // Field store:Lorg/apache/hadoop/hbase/regionserver/HStore;
     203: invokevirtual #310                // Method org/apache/hadoop/hbase/regionserver/HStore.refreshStoreFiles:()V
     206: ldc2_w        #132                // long 4l
     209: aload_0
     210: getfield      #108                // Field store:Lorg/apache/hadoop/hbase/regionserver/HStore;
     213: invokevirtual #213                // Method org/apache/hadoop/hbase/regionserver/HStore.getStorefilesCount:()I
     216: i2l
     217: invokestatic  #169                // Method org/junit/Assert.assertEquals:(JJ)V
     220: aload_0
     221: iconst_0
     222: invokespecial #313                // Method archiveStoreFile:(I)V
     225: aload_0
     226: iconst_1
     227: invokespecial #313                // Method archiveStoreFile:(I)V
     230: aload_0
     231: iconst_2
     232: invokespecial #313                // Method archiveStoreFile:(I)V
     235: ldc2_w        #132                // long 4l
     238: aload_0
     239: getfield      #108                // Field store:Lorg/apache/hadoop/hbase/regionserver/HStore;
     242: invokevirtual #213                // Method org/apache/hadoop/hbase/regionserver/HStore.getStorefilesCount:()I
     245: i2l
     246: invokestatic  #169                // Method org/junit/Assert.assertEquals:(JJ)V
     249: aload_0
     250: getfield      #108                // Field store:Lorg/apache/hadoop/hbase/regionserver/HStore;
     253: invokevirtual #310                // Method org/apache/hadoop/hbase/regionserver/HStore.refreshStoreFiles:()V
     256: lconst_1
     257: aload_0
     258: getfield      #108                // Field store:Lorg/apache/hadoop/hbase/regionserver/HStore;
     261: invokevirtual #213                // Method org/apache/hadoop/hbase/regionserver/HStore.getStorefilesCount:()I
     264: i2l
     265: invokestatic  #169                // Method org/junit/Assert.assertEquals:(JJ)V
     268: aload_0
     269: iconst_0
     270: invokespecial #313                // Method archiveStoreFile:(I)V
     273: aload_0
     274: getfield      #108                // Field store:Lorg/apache/hadoop/hbase/regionserver/HStore;
     277: invokevirtual #310                // Method org/apache/hadoop/hbase/regionserver/HStore.refreshStoreFiles:()V
     280: lconst_0
     281: aload_0
     282: getfield      #108                // Field store:Lorg/apache/hadoop/hbase/regionserver/HStore;
     285: invokevirtual #213                // Method org/apache/hadoop/hbase/regionserver/HStore.getStorefilesCount:()I
     288: i2l
     289: invokestatic  #169                // Method org/junit/Assert.assertEquals:(JJ)V
     292: return

  public void testRefreshStoreFilesNotChanged() throws java.io.IOException;
    Code:
       0: aload_0
       1: aload_0
       2: getfield      #9                  // Field name:Lorg/junit/rules/TestName;
       5: invokevirtual #112                // Method org/junit/rules/TestName.getMethodName:()Ljava/lang/String;
       8: invokespecial #194                // Method init:(Ljava/lang/String;)V
      11: lconst_0
      12: aload_0
      13: getfield      #108                // Field store:Lorg/apache/hadoop/hbase/regionserver/HStore;
      16: invokevirtual #213                // Method org/apache/hadoop/hbase/regionserver/HStore.getStorefilesCount:()I
      19: i2l
      20: invokestatic  #169                // Method org/junit/Assert.assertEquals:(JJ)V
      23: aload_0
      24: getfield      #108                // Field store:Lorg/apache/hadoop/hbase/regionserver/HStore;
      27: new           #49                 // class org/apache/hadoop/hbase/KeyValue
      30: dup
      31: aload_0
      32: getfield      #16                 // Field row:[B
      35: aload_0
      36: getfield      #14                 // Field family:[B
      39: aload_0
      40: getfield      #20                 // Field qf1:[B
      43: lconst_1
      44: aconst_null
      45: checkcast     #48                 // class "[B"
      48: invokespecial #50                 // Method org/apache/hadoop/hbase/KeyValue."<init>":([B[B[BJ[B)V
      51: aconst_null
      52: invokevirtual #165                // Method org/apache/hadoop/hbase/regionserver/HStore.add:(Lorg/apache/hadoop/hbase/Cell;Lorg/apache/hadoop/hbase/regionserver/MemStoreSizing;)V
      55: aload_0
      56: iconst_1
      57: invokespecial #2                  // Method flush:(I)V
      60: aload_0
      61: invokespecial #311                // Method addStoreFile:()V
      64: aload_0
      65: getfield      #108                // Field store:Lorg/apache/hadoop/hbase/regionserver/HStore;
      68: invokestatic  #98                 // Method org/mockito/Mockito.spy:(Ljava/lang/Object;)Ljava/lang/Object;
      71: checkcast     #106                // class org/apache/hadoop/hbase/regionserver/HStore
      74: astore_1
      75: aload_1
      76: invokevirtual #310                // Method org/apache/hadoop/hbase/regionserver/HStore.refreshStoreFiles:()V
      79: ldc2_w        #211                // long 2l
      82: aload_0
      83: getfield      #108                // Field store:Lorg/apache/hadoop/hbase/regionserver/HStore;
      86: invokevirtual #213                // Method org/apache/hadoop/hbase/regionserver/HStore.getStorefilesCount:()I
      89: i2l
      90: invokestatic  #169                // Method org/junit/Assert.assertEquals:(JJ)V
      93: aload_1
      94: iconst_1
      95: invokestatic  #314                // Method org/mockito/Mockito.times:(I)Lorg/mockito/verification/VerificationMode;
      98: invokestatic  #315                // Method org/mockito/Mockito.verify:(Ljava/lang/Object;Lorg/mockito/verification/VerificationMode;)Ljava/lang/Object;
     101: checkcast     #106                // class org/apache/hadoop/hbase/regionserver/HStore
     104: invokestatic  #316                // Method org/mockito/ArgumentMatchers.any:()Ljava/lang/Object;
     107: checkcast     #317                // class java/util/Collection
     110: invokestatic  #316                // Method org/mockito/ArgumentMatchers.any:()Ljava/lang/Object;
     113: checkcast     #317                // class java/util/Collection
     116: invokevirtual #318                // Method org/apache/hadoop/hbase/regionserver/HStore.replaceStoreFiles:(Ljava/util/Collection;Ljava/util/Collection;)V
     119: aload_1
     120: invokevirtual #310                // Method org/apache/hadoop/hbase/regionserver/HStore.refreshStoreFiles:()V
     123: aload_1
     124: iconst_0
     125: invokestatic  #314                // Method org/mockito/Mockito.times:(I)Lorg/mockito/verification/VerificationMode;
     128: invokestatic  #315                // Method org/mockito/Mockito.verify:(Ljava/lang/Object;Lorg/mockito/verification/VerificationMode;)Ljava/lang/Object;
     131: checkcast     #106                // class org/apache/hadoop/hbase/regionserver/HStore
     134: aconst_null
     135: aconst_null
     136: invokevirtual #318                // Method org/apache/hadoop/hbase/regionserver/HStore.replaceStoreFiles:(Ljava/util/Collection;Ljava/util/Collection;)V
     139: return

  public void testNumberOfMemStoreScannersAfterFlush() throws java.io.IOException;
    Code:
       0: ldc2_w        #219                // long 100l
       3: lstore_1
       4: invokestatic  #39                 // Method java/lang/System.currentTimeMillis:()J
       7: lstore_3
       8: getstatic     #324                // Field org/apache/hadoop/hbase/CellBuilderType.DEEP_COPY:Lorg/apache/hadoop/hbase/CellBuilderType;
      11: invokestatic  #325                // Method org/apache/hadoop/hbase/CellBuilderFactory.create:(Lorg/apache/hadoop/hbase/CellBuilderType;)Lorg/apache/hadoop/hbase/CellBuilder;
      14: aload_0
      15: getfield      #16                 // Field row:[B
      18: invokeinterface #326,  2          // InterfaceMethod org/apache/hadoop/hbase/CellBuilder.setRow:([B)Lorg/apache/hadoop/hbase/CellBuilder;
      23: aload_0
      24: getfield      #14                 // Field family:[B
      27: invokeinterface #327,  2          // InterfaceMethod org/apache/hadoop/hbase/CellBuilder.setFamily:([B)Lorg/apache/hadoop/hbase/CellBuilder;
      32: aload_0
      33: getfield      #20                 // Field qf1:[B
      36: invokeinterface #328,  2          // InterfaceMethod org/apache/hadoop/hbase/CellBuilder.setQualifier:([B)Lorg/apache/hadoop/hbase/CellBuilder;
      41: lload_3
      42: invokeinterface #329,  3          // InterfaceMethod org/apache/hadoop/hbase/CellBuilder.setTimestamp:(J)Lorg/apache/hadoop/hbase/CellBuilder;
      47: getstatic     #330                // Field org/apache/hadoop/hbase/Cell$Type.Put:Lorg/apache/hadoop/hbase/Cell$Type;
      50: invokeinterface #331,  2          // InterfaceMethod org/apache/hadoop/hbase/CellBuilder.setType:(Lorg/apache/hadoop/hbase/Cell$Type;)Lorg/apache/hadoop/hbase/CellBuilder;
      55: aload_0
      56: getfield      #20                 // Field qf1:[B
      59: invokeinterface #332,  2          // InterfaceMethod org/apache/hadoop/hbase/CellBuilder.setValue:([B)Lorg/apache/hadoop/hbase/CellBuilder;
      64: invokeinterface #333,  1          // InterfaceMethod org/apache/hadoop/hbase/CellBuilder.build:()Lorg/apache/hadoop/hbase/Cell;
      69: astore        5
      71: aload         5
      73: lload_1
      74: invokestatic  #334                // Method org/apache/hadoop/hbase/PrivateCellUtil.setSequenceId:(Lorg/apache/hadoop/hbase/Cell;J)V
      77: aload_0
      78: iconst_1
      79: anewarray     #262                // class org/apache/hadoop/hbase/Cell
      82: dup
      83: iconst_0
      84: aload         5
      86: aastore
      87: invokestatic  #335                // Method java/util/Arrays.asList:([Ljava/lang/Object;)Ljava/util/List;
      90: invokestatic  #336                // Method java/util/Collections.emptyList:()Ljava/util/List;
      93: invokespecial #337                // Method testNumberOfMemStoreScannersAfterFlush:(Ljava/util/List;Ljava/util/List;)V
      96: getstatic     #324                // Field org/apache/hadoop/hbase/CellBuilderType.DEEP_COPY:Lorg/apache/hadoop/hbase/CellBuilderType;
      99: invokestatic  #325                // Method org/apache/hadoop/hbase/CellBuilderFactory.create:(Lorg/apache/hadoop/hbase/CellBuilderType;)Lorg/apache/hadoop/hbase/CellBuilder;
     102: aload_0
     103: getfield      #16                 // Field row:[B
     106: invokeinterface #326,  2          // InterfaceMethod org/apache/hadoop/hbase/CellBuilder.setRow:([B)Lorg/apache/hadoop/hbase/CellBuilder;
     111: aload_0
     112: getfield      #14                 // Field family:[B
     115: invokeinterface #327,  2          // InterfaceMethod org/apache/hadoop/hbase/CellBuilder.setFamily:([B)Lorg/apache/hadoop/hbase/CellBuilder;
     120: aload_0
     121: getfield      #22                 // Field qf2:[B
     124: invokeinterface #328,  2          // InterfaceMethod org/apache/hadoop/hbase/CellBuilder.setQualifier:([B)Lorg/apache/hadoop/hbase/CellBuilder;
     129: lload_3
     130: invokeinterface #329,  3          // InterfaceMethod org/apache/hadoop/hbase/CellBuilder.setTimestamp:(J)Lorg/apache/hadoop/hbase/CellBuilder;
     135: getstatic     #330                // Field org/apache/hadoop/hbase/Cell$Type.Put:Lorg/apache/hadoop/hbase/Cell$Type;
     138: invokeinterface #331,  2          // InterfaceMethod org/apache/hadoop/hbase/CellBuilder.setType:(Lorg/apache/hadoop/hbase/Cell$Type;)Lorg/apache/hadoop/hbase/CellBuilder;
     143: aload_0
     144: getfield      #20                 // Field qf1:[B
     147: invokeinterface #332,  2          // InterfaceMethod org/apache/hadoop/hbase/CellBuilder.setValue:([B)Lorg/apache/hadoop/hbase/CellBuilder;
     152: invokeinterface #333,  1          // InterfaceMethod org/apache/hadoop/hbase/CellBuilder.build:()Lorg/apache/hadoop/hbase/Cell;
     157: astore        6
     159: aload         6
     161: lload_1
     162: invokestatic  #334                // Method org/apache/hadoop/hbase/PrivateCellUtil.setSequenceId:(Lorg/apache/hadoop/hbase/Cell;J)V
     165: aload_0
     166: iconst_1
     167: anewarray     #262                // class org/apache/hadoop/hbase/Cell
     170: dup
     171: iconst_0
     172: aload         5
     174: aastore
     175: invokestatic  #335                // Method java/util/Arrays.asList:([Ljava/lang/Object;)Ljava/util/List;
     178: iconst_1
     179: anewarray     #262                // class org/apache/hadoop/hbase/Cell
     182: dup
     183: iconst_0
     184: aload         6
     186: aastore
     187: invokestatic  #335                // Method java/util/Arrays.asList:([Ljava/lang/Object;)Ljava/util/List;
     190: invokespecial #337                // Method testNumberOfMemStoreScannersAfterFlush:(Ljava/util/List;Ljava/util/List;)V
     193: ldc2_w        #338                // long 101l
     196: lstore_1
     197: invokestatic  #39                 // Method java/lang/System.currentTimeMillis:()J
     200: lstore_3
     201: getstatic     #324                // Field org/apache/hadoop/hbase/CellBuilderType.DEEP_COPY:Lorg/apache/hadoop/hbase/CellBuilderType;
     204: invokestatic  #325                // Method org/apache/hadoop/hbase/CellBuilderFactory.create:(Lorg/apache/hadoop/hbase/CellBuilderType;)Lorg/apache/hadoop/hbase/CellBuilder;
     207: aload_0
     208: getfield      #18                 // Field row2:[B
     211: invokeinterface #326,  2          // InterfaceMethod org/apache/hadoop/hbase/CellBuilder.setRow:([B)Lorg/apache/hadoop/hbase/CellBuilder;
     216: aload_0
     217: getfield      #14                 // Field family:[B
     220: invokeinterface #327,  2          // InterfaceMethod org/apache/hadoop/hbase/CellBuilder.setFamily:([B)Lorg/apache/hadoop/hbase/CellBuilder;
     225: aload_0
     226: getfield      #22                 // Field qf2:[B
     229: invokeinterface #328,  2          // InterfaceMethod org/apache/hadoop/hbase/CellBuilder.setQualifier:([B)Lorg/apache/hadoop/hbase/CellBuilder;
     234: lload_3
     235: invokeinterface #329,  3          // InterfaceMethod org/apache/hadoop/hbase/CellBuilder.setTimestamp:(J)Lorg/apache/hadoop/hbase/CellBuilder;
     240: getstatic     #330                // Field org/apache/hadoop/hbase/Cell$Type.Put:Lorg/apache/hadoop/hbase/Cell$Type;
     243: invokeinterface #331,  2          // InterfaceMethod org/apache/hadoop/hbase/CellBuilder.setType:(Lorg/apache/hadoop/hbase/Cell$Type;)Lorg/apache/hadoop/hbase/CellBuilder;
     248: aload_0
     249: getfield      #20                 // Field qf1:[B
     252: invokeinterface #332,  2          // InterfaceMethod org/apache/hadoop/hbase/CellBuilder.setValue:([B)Lorg/apache/hadoop/hbase/CellBuilder;
     257: invokeinterface #333,  1          // InterfaceMethod org/apache/hadoop/hbase/CellBuilder.build:()Lorg/apache/hadoop/hbase/Cell;
     262: astore        7
     264: aload         7
     266: lload_1
     267: invokestatic  #334                // Method org/apache/hadoop/hbase/PrivateCellUtil.setSequenceId:(Lorg/apache/hadoop/hbase/Cell;J)V
     270: aload_0
     271: iconst_1
     272: anewarray     #262                // class org/apache/hadoop/hbase/Cell
     275: dup
     276: iconst_0
     277: aload         5
     279: aastore
     280: invokestatic  #335                // Method java/util/Arrays.asList:([Ljava/lang/Object;)Ljava/util/List;
     283: iconst_2
     284: anewarray     #262                // class org/apache/hadoop/hbase/Cell
     287: dup
     288: iconst_0
     289: aload         6
     291: aastore
     292: dup
     293: iconst_1
     294: aload         7
     296: aastore
     297: invokestatic  #335                // Method java/util/Arrays.asList:([Ljava/lang/Object;)Ljava/util/List;
     300: invokespecial #337                // Method testNumberOfMemStoreScannersAfterFlush:(Ljava/util/List;Ljava/util/List;)V
     303: return

  public void testFlushBeforeCompletingScanWoFilter() throws java.io.IOException, java.lang.InterruptedException;
    Code:
       0: new           #365                // class java/util/concurrent/atomic/AtomicBoolean
       3: dup
       4: iconst_0
       5: invokespecial #366                // Method java/util/concurrent/atomic/AtomicBoolean."<init>":(Z)V
       8: astore_1
       9: iconst_3
      10: istore_2
      11: aload_0
      12: new           #367                // class org/apache/hadoop/hbase/regionserver/TestHStore$3
      15: dup
      16: aload_0
      17: aload_1
      18: invokespecial #368                // Method org/apache/hadoop/hbase/regionserver/TestHStore$3."<init>":(Lorg/apache/hadoop/hbase/regionserver/TestHStore;Ljava/util/concurrent/atomic/AtomicBoolean;)V
      21: new           #369                // class org/apache/hadoop/hbase/regionserver/TestHStore$4
      24: dup
      25: aload_0
      26: invokespecial #370                // Method org/apache/hadoop/hbase/regionserver/TestHStore$4."<init>":(Lorg/apache/hadoop/hbase/regionserver/TestHStore;)V
      29: iconst_3
      30: invokespecial #371                // Method testFlushBeforeCompletingScan:(Lorg/apache/hadoop/hbase/regionserver/TestHStore$MyListHook;Lorg/apache/hadoop/hbase/filter/Filter;I)V
      33: return

  public void testFlushBeforeCompletingScanWithFilter() throws java.io.IOException, java.lang.InterruptedException;
    Code:
       0: new           #365                // class java/util/concurrent/atomic/AtomicBoolean
       3: dup
       4: iconst_0
       5: invokespecial #366                // Method java/util/concurrent/atomic/AtomicBoolean."<init>":(Z)V
       8: astore_1
       9: iconst_2
      10: istore_2
      11: aload_0
      12: new           #372                // class org/apache/hadoop/hbase/regionserver/TestHStore$5
      15: dup
      16: aload_0
      17: aload_1
      18: invokespecial #373                // Method org/apache/hadoop/hbase/regionserver/TestHStore$5."<init>":(Lorg/apache/hadoop/hbase/regionserver/TestHStore;Ljava/util/concurrent/atomic/AtomicBoolean;)V
      21: new           #374                // class org/apache/hadoop/hbase/regionserver/TestHStore$6
      24: dup
      25: aload_0
      26: aload_1
      27: invokespecial #375                // Method org/apache/hadoop/hbase/regionserver/TestHStore$6."<init>":(Lorg/apache/hadoop/hbase/regionserver/TestHStore;Ljava/util/concurrent/atomic/AtomicBoolean;)V
      30: iconst_2
      31: invokespecial #371                // Method testFlushBeforeCompletingScan:(Lorg/apache/hadoop/hbase/regionserver/TestHStore$MyListHook;Lorg/apache/hadoop/hbase/filter/Filter;I)V
      34: return

  public void testFlushBeforeCompletingScanWithFilterHint() throws java.io.IOException, java.lang.InterruptedException;
    Code:
       0: new           #365                // class java/util/concurrent/atomic/AtomicBoolean
       3: dup
       4: iconst_0
       5: invokespecial #366                // Method java/util/concurrent/atomic/AtomicBoolean."<init>":(Z)V
       8: astore_1
       9: iconst_2
      10: istore_2
      11: aload_0
      12: new           #376                // class org/apache/hadoop/hbase/regionserver/TestHStore$7
      15: dup
      16: aload_0
      17: aload_1
      18: invokespecial #377                // Method org/apache/hadoop/hbase/regionserver/TestHStore$7."<init>":(Lorg/apache/hadoop/hbase/regionserver/TestHStore;Ljava/util/concurrent/atomic/AtomicBoolean;)V
      21: new           #378                // class org/apache/hadoop/hbase/regionserver/TestHStore$8
      24: dup
      25: aload_0
      26: aload_1
      27: invokespecial #379                // Method org/apache/hadoop/hbase/regionserver/TestHStore$8."<init>":(Lorg/apache/hadoop/hbase/regionserver/TestHStore;Ljava/util/concurrent/atomic/AtomicBoolean;)V
      30: iconst_2
      31: invokespecial #371                // Method testFlushBeforeCompletingScan:(Lorg/apache/hadoop/hbase/regionserver/TestHStore$MyListHook;Lorg/apache/hadoop/hbase/filter/Filter;I)V
      34: return

  public void testCreateScannerAndSnapshotConcurrently() throws java.io.IOException, java.lang.InterruptedException;
    Code:
       0: invokestatic  #127                // Method org/apache/hadoop/hbase/HBaseConfiguration.create:()Lorg/apache/hadoop/conf/Configuration;
       3: astore_1
       4: aload_1
       5: ldc_w         #405                // String hbase.regionserver.memstore.class
       8: ldc_w         #406                // class org/apache/hadoop/hbase/regionserver/TestHStore$MyCompactingMemStore
      11: invokevirtual #293                // Method java/lang/Class.getName:()Ljava/lang/String;
      14: invokevirtual #294                // Method org/apache/hadoop/conf/Configuration.set:(Ljava/lang/String;Ljava/lang/String;)V
      17: aload_0
      18: aload_0
      19: getfield      #9                  // Field name:Lorg/junit/rules/TestName;
      22: invokevirtual #112                // Method org/junit/rules/TestName.getMethodName:()Ljava/lang/String;
      25: aload_1
      26: aload_0
      27: getfield      #14                 // Field family:[B
      30: invokestatic  #55                 // Method org/apache/hadoop/hbase/client/ColumnFamilyDescriptorBuilder.newBuilder:([B)Lorg/apache/hadoop/hbase/client/ColumnFamilyDescriptorBuilder;
      33: getstatic     #407                // Field org/apache/hadoop/hbase/MemoryCompactionPolicy.BASIC:Lorg/apache/hadoop/hbase/MemoryCompactionPolicy;
      36: invokevirtual #408                // Method org/apache/hadoop/hbase/client/ColumnFamilyDescriptorBuilder.setInMemoryCompaction:(Lorg/apache/hadoop/hbase/MemoryCompactionPolicy;)Lorg/apache/hadoop/hbase/client/ColumnFamilyDescriptorBuilder;
      39: invokevirtual #57                 // Method org/apache/hadoop/hbase/client/ColumnFamilyDescriptorBuilder.build:()Lorg/apache/hadoop/hbase/client/ColumnFamilyDescriptor;
      42: invokespecial #58                 // Method init:(Ljava/lang/String;Lorg/apache/hadoop/conf/Configuration;Lorg/apache/hadoop/hbase/client/ColumnFamilyDescriptor;)Lorg/apache/hadoop/hbase/regionserver/HStore;
      45: pop
      46: ldc_w         #409                // String value
      49: invokestatic  #11                 // Method org/apache/hadoop/hbase/util/Bytes.toBytes:(Ljava/lang/String;)[B
      52: astore_2
      53: new           #385                // class org/apache/hadoop/hbase/regionserver/NonThreadSafeMemStoreSizing
      56: dup
      57: invokespecial #386                // Method org/apache/hadoop/hbase/regionserver/NonThreadSafeMemStoreSizing."<init>":()V
      60: astore_3
      61: invokestatic  #164                // Method org/apache/hadoop/hbase/util/EnvironmentEdgeManager.currentTime:()J
      64: lstore        4
      66: ldc2_w        #219                // long 100l
      69: lstore        6
      71: aload_0
      72: getfield      #108                // Field store:Lorg/apache/hadoop/hbase/regionserver/HStore;
      75: aload_0
      76: aload_0
      77: getfield      #20                 // Field qf1:[B
      80: lload         4
      82: lload         6
      84: aload_2
      85: invokespecial #410                // Method createCell:([BJJ[B)Lorg/apache/hadoop/hbase/Cell;
      88: aload_3
      89: invokevirtual #165                // Method org/apache/hadoop/hbase/regionserver/HStore.add:(Lorg/apache/hadoop/hbase/Cell;Lorg/apache/hadoop/hbase/regionserver/MemStoreSizing;)V
      92: aload_0
      93: getfield      #108                // Field store:Lorg/apache/hadoop/hbase/regionserver/HStore;
      96: aload_0
      97: aload_0
      98: getfield      #22                 // Field qf2:[B
     101: lload         4
     103: lload         6
     105: aload_2
     106: invokespecial #410                // Method createCell:([BJJ[B)Lorg/apache/hadoop/hbase/Cell;
     109: aload_3
     110: invokevirtual #165                // Method org/apache/hadoop/hbase/regionserver/HStore.add:(Lorg/apache/hadoop/hbase/Cell;Lorg/apache/hadoop/hbase/regionserver/MemStoreSizing;)V
     113: aload_0
     114: getfield      #108                // Field store:Lorg/apache/hadoop/hbase/regionserver/HStore;
     117: aload_0
     118: aload_0
     119: getfield      #24                 // Field qf3:[B
     122: lload         4
     124: lload         6
     126: aload_2
     127: invokespecial #410                // Method createCell:([BJJ[B)Lorg/apache/hadoop/hbase/Cell;
     130: aload_3
     131: invokevirtual #165                // Method org/apache/hadoop/hbase/regionserver/HStore.add:(Lorg/apache/hadoop/hbase/Cell;Lorg/apache/hadoop/hbase/regionserver/MemStoreSizing;)V
     134: new           #340                // class java/util/TreeSet
     137: dup
     138: getstatic     #32                 // Field org/apache/hadoop/hbase/util/Bytes.BYTES_COMPARATOR:Ljava/util/Comparator;
     141: invokespecial #341                // Method java/util/TreeSet."<init>":(Ljava/util/Comparator;)V
     144: astore        8
     146: aload         8
     148: aload_0
     149: getfield      #20                 // Field qf1:[B
     152: invokevirtual #345                // Method java/util/TreeSet.add:(Ljava/lang/Object;)Z
     155: pop
     156: aload         8
     158: aload_0
     159: getfield      #22                 // Field qf2:[B
     162: invokevirtual #345                // Method java/util/TreeSet.add:(Ljava/lang/Object;)Z
     165: pop
     166: aload         8
     168: aload_0
     169: getfield      #24                 // Field qf3:[B
     172: invokevirtual #345                // Method java/util/TreeSet.add:(Ljava/lang/Object;)Z
     175: pop
     176: aload_0
     177: getfield      #108                // Field store:Lorg/apache/hadoop/hbase/regionserver/HStore;
     180: aload_0
     181: dup
     182: getfield      #40                 // Field id:J
     185: dup2_x1
     186: lconst_1
     187: ladd
     188: putfield      #40                 // Field id:J
     191: getstatic     #243                // Field org/apache/hadoop/hbase/regionserver/FlushLifeCycleTracker.DUMMY:Lorg/apache/hadoop/hbase/regionserver/FlushLifeCycleTracker;
     194: invokevirtual #244                // Method org/apache/hadoop/hbase/regionserver/HStore.createFlushContext:(JLorg/apache/hadoop/hbase/regionserver/FlushLifeCycleTracker;)Lorg/apache/hadoop/hbase/regionserver/StoreFlushContext;
     197: astore        9
     199: invokestatic  #411                // Method org/apache/hadoop/hbase/regionserver/TestHStore$MyCompactingMemStore.access$500:()Ljava/util/concurrent/atomic/AtomicBoolean;
     202: iconst_1
     203: invokevirtual #412                // Method java/util/concurrent/atomic/AtomicBoolean.set:(Z)V
     206: aload         9
     208: invokedynamic #413,  0            // InvokeDynamic #3:run:(Lorg/apache/hadoop/hbase/regionserver/StoreFlushContext;)Ljava/lang/Runnable;
     213: astore        10
     215: invokestatic  #414                // Method java/util/concurrent/Executors.newSingleThreadExecutor:()Ljava/util/concurrent/ExecutorService;
     218: astore        11
     220: aload         11
     222: aload         10
     224: invokeinterface #415,  2          // InterfaceMethod java/util/concurrent/ExecutorService.submit:(Ljava/lang/Runnable;)Ljava/util/concurrent/Future;
     229: pop
     230: aload_0
     231: getfield      #108                // Field store:Lorg/apache/hadoop/hbase/regionserver/HStore;
     234: new           #352                // class org/apache/hadoop/hbase/client/Scan
     237: dup
     238: new           #41                 // class org/apache/hadoop/hbase/client/Get
     241: dup
     242: aload_0
     243: getfield      #16                 // Field row:[B
     246: invokespecial #42                 // Method org/apache/hadoop/hbase/client/Get."<init>":([B)V
     249: invokespecial #416                // Method org/apache/hadoop/hbase/client/Scan."<init>":(Lorg/apache/hadoop/hbase/client/Get;)V
     252: aload         8
     254: lload         6
     256: lconst_1
     257: ladd
     258: invokevirtual #354                // Method org/apache/hadoop/hbase/regionserver/HStore.getScanner:(Lorg/apache/hadoop/hbase/client/Scan;Ljava/util/NavigableSet;J)Lorg/apache/hadoop/hbase/regionserver/KeyValueScanner;
     261: checkcast     #395                // class org/apache/hadoop/hbase/regionserver/InternalScanner
     264: astore        12
     266: aload         11
     268: invokeinterface #417,  1          // InterfaceMethod java/util/concurrent/ExecutorService.shutdown:()V
     273: aload         11
     275: ldc2_w        #254                // long 20l
     278: getstatic     #418                // Field java/util/concurrent/TimeUnit.SECONDS:Ljava/util/concurrent/TimeUnit;
     281: invokeinterface #419,  4          // InterfaceMethod java/util/concurrent/ExecutorService.awaitTermination:(JLjava/util/concurrent/TimeUnit;)Z
     286: pop
     287: new           #35                 // class java/util/ArrayList
     290: dup
     291: invokespecial #36                 // Method java/util/ArrayList."<init>":()V
     294: astore        13
     296: aload         12
     298: aload         13
     300: invokeinterface #396,  2          // InterfaceMethod org/apache/hadoop/hbase/regionserver/InternalScanner.next:(Ljava/util/List;)Z
     305: pop
     306: ldc2_w        #389                // long 3l
     309: aload         13
     311: invokeinterface #216,  1          // InterfaceMethod java/util/List.size:()I
     316: i2l
     317: invokestatic  #169                // Method org/junit/Assert.assertEquals:(JJ)V
     320: aload         13
     322: invokeinterface #261,  1          // InterfaceMethod java/util/List.iterator:()Ljava/util/Iterator;
     327: astore        14
     329: aload         14
     331: invokeinterface #46,  1           // InterfaceMethod java/util/Iterator.hasNext:()Z
     336: ifeq          407
     339: aload         14
     341: invokeinterface #47,  1           // InterfaceMethod java/util/Iterator.next:()Ljava/lang/Object;
     346: checkcast     #262                // class org/apache/hadoop/hbase/Cell
     349: astore        15
     351: aload         15
     353: invokestatic  #397                // Method org/apache/hadoop/hbase/CellUtil.cloneValue:(Lorg/apache/hadoop/hbase/Cell;)[B
     356: astore        16
     358: new           #67                 // class java/lang/StringBuilder
     361: dup
     362: invokespecial #68                 // Method java/lang/StringBuilder."<init>":()V
     365: ldc_w         #398                // String expected:
     368: invokevirtual #70                 // Method java/lang/StringBuilder.append:(Ljava/lang/String;)Ljava/lang/StringBuilder;
     371: aload_2
     372: invokestatic  #399                // Method org/apache/hadoop/hbase/util/Bytes.toStringBinary:([B)Ljava/lang/String;
     375: invokevirtual #70                 // Method java/lang/StringBuilder.append:(Ljava/lang/String;)Ljava/lang/StringBuilder;
     378: ldc_w         #400                // String , actual:
     381: invokevirtual #70                 // Method java/lang/StringBuilder.append:(Ljava/lang/String;)Ljava/lang/StringBuilder;
     384: aload         16
     386: invokestatic  #399                // Method org/apache/hadoop/hbase/util/Bytes.toStringBinary:([B)Ljava/lang/String;
     389: invokevirtual #70                 // Method java/lang/StringBuilder.append:(Ljava/lang/String;)Ljava/lang/StringBuilder;
     392: invokevirtual #71                 // Method java/lang/StringBuilder.toString:()Ljava/lang/String;
     395: aload         16
     397: aload_2
     398: invokestatic  #401                // Method org/apache/hadoop/hbase/util/Bytes.equals:([B[B)Z
     401: invokestatic  #402                // Method org/junit/Assert.assertTrue:(Ljava/lang/String;Z)V
     404: goto          329
     407: aload         12
     409: invokeinterface #404,  1          // InterfaceMethod org/apache/hadoop/hbase/regionserver/InternalScanner.close:()V
     414: goto          429
     417: astore        17
     419: aload         12
     421: invokeinterface #404,  1          // InterfaceMethod org/apache/hadoop/hbase/regionserver/InternalScanner.close:()V
     426: aload         17
     428: athrow
     429: invokestatic  #411                // Method org/apache/hadoop/hbase/regionserver/TestHStore$MyCompactingMemStore.access$500:()Ljava/util/concurrent/atomic/AtomicBoolean;
     432: iconst_0
     433: invokevirtual #412                // Method java/util/concurrent/atomic/AtomicBoolean.set:(Z)V
     436: aload         9
     438: ldc           #246                // class org/apache/hadoop/hbase/monitoring/MonitoredTask
     440: invokestatic  #247                // Method org/mockito/Mockito.mock:(Ljava/lang/Class;)Ljava/lang/Object;
     443: checkcast     #246                // class org/apache/hadoop/hbase/monitoring/MonitoredTask
     446: invokeinterface #248,  2          // InterfaceMethod org/apache/hadoop/hbase/regionserver/StoreFlushContext.flushCache:(Lorg/apache/hadoop/hbase/monitoring/MonitoredTask;)V
     451: aload         9
     453: ldc           #246                // class org/apache/hadoop/hbase/monitoring/MonitoredTask
     455: invokestatic  #247                // Method org/mockito/Mockito.mock:(Ljava/lang/Class;)Ljava/lang/Object;
     458: checkcast     #246                // class org/apache/hadoop/hbase/monitoring/MonitoredTask
     461: invokeinterface #249,  2          // InterfaceMethod org/apache/hadoop/hbase/regionserver/StoreFlushContext.commit:(Lorg/apache/hadoop/hbase/monitoring/MonitoredTask;)Z
     466: pop
     467: goto          513
     470: astore        18
     472: invokestatic  #411                // Method org/apache/hadoop/hbase/regionserver/TestHStore$MyCompactingMemStore.access$500:()Ljava/util/concurrent/atomic/AtomicBoolean;
     475: iconst_0
     476: invokevirtual #412                // Method java/util/concurrent/atomic/AtomicBoolean.set:(Z)V
     479: aload         9
     481: ldc           #246                // class org/apache/hadoop/hbase/monitoring/MonitoredTask
     483: invokestatic  #247                // Method org/mockito/Mockito.mock:(Ljava/lang/Class;)Ljava/lang/Object;
     486: checkcast     #246                // class org/apache/hadoop/hbase/monitoring/MonitoredTask
     489: invokeinterface #248,  2          // InterfaceMethod org/apache/hadoop/hbase/regionserver/StoreFlushContext.flushCache:(Lorg/apache/hadoop/hbase/monitoring/MonitoredTask;)V
     494: aload         9
     496: ldc           #246                // class org/apache/hadoop/hbase/monitoring/MonitoredTask
     498: invokestatic  #247                // Method org/mockito/Mockito.mock:(Ljava/lang/Class;)Ljava/lang/Object;
     501: checkcast     #246                // class org/apache/hadoop/hbase/monitoring/MonitoredTask
     504: invokeinterface #249,  2          // InterfaceMethod org/apache/hadoop/hbase/regionserver/StoreFlushContext.commit:(Lorg/apache/hadoop/hbase/monitoring/MonitoredTask;)Z
     509: pop
     510: aload         18
     512: athrow
     513: return
    Exception table:
       from    to  target type
         287   407   417   any
         417   419   417   any
         287   429   470   any
         470   472   470   any

  public void testScanWithDoubleFlush() throws java.io.IOException;
    Code:
       0: invokestatic  #127                // Method org/apache/hadoop/hbase/HBaseConfiguration.create:()Lorg/apache/hadoop/conf/Configuration;
       3: astore_1
       4: aload_0
       5: aload_0
       6: getfield      #9                  // Field name:Lorg/junit/rules/TestName;
       9: invokevirtual #112                // Method org/junit/rules/TestName.getMethodName:()Ljava/lang/String;
      12: aload_1
      13: new           #420                // class org/apache/hadoop/hbase/regionserver/TestHStore$10
      16: dup
      17: aload_0
      18: invokespecial #421                // Method org/apache/hadoop/hbase/regionserver/TestHStore$10."<init>":(Lorg/apache/hadoop/hbase/regionserver/TestHStore;)V
      21: invokespecial #422                // Method initMyStore:(Ljava/lang/String;Lorg/apache/hadoop/conf/Configuration;Lorg/apache/hadoop/hbase/regionserver/TestHStore$MyStoreHook;)Lorg/apache/hadoop/hbase/regionserver/TestHStore$MyStore;
      24: astore_2
      25: ldc_w         #423                // String oldValue
      28: invokestatic  #11                 // Method org/apache/hadoop/hbase/util/Bytes.toBytes:(Ljava/lang/String;)[B
      31: astore_3
      32: ldc_w         #424                // String currentValue
      35: invokestatic  #11                 // Method org/apache/hadoop/hbase/util/Bytes.toBytes:(Ljava/lang/String;)[B
      38: astore        4
      40: new           #385                // class org/apache/hadoop/hbase/regionserver/NonThreadSafeMemStoreSizing
      43: dup
      44: invokespecial #386                // Method org/apache/hadoop/hbase/regionserver/NonThreadSafeMemStoreSizing."<init>":()V
      47: astore        5
      49: invokestatic  #164                // Method org/apache/hadoop/hbase/util/EnvironmentEdgeManager.currentTime:()J
      52: lstore        6
      54: ldc2_w        #219                // long 100l
      57: lstore        8
      59: aload_2
      60: aload_0
      61: aload_0
      62: getfield      #20                 // Field qf1:[B
      65: lload         6
      67: lload         8
      69: aload_3
      70: invokespecial #410                // Method createCell:([BJJ[B)Lorg/apache/hadoop/hbase/Cell;
      73: aload         5
      75: invokevirtual #425                // Method org/apache/hadoop/hbase/regionserver/TestHStore$MyStore.add:(Lorg/apache/hadoop/hbase/Cell;Lorg/apache/hadoop/hbase/regionserver/MemStoreSizing;)V
      78: aload_2
      79: aload_0
      80: aload_0
      81: getfield      #22                 // Field qf2:[B
      84: lload         6
      86: lload         8
      88: aload_3
      89: invokespecial #410                // Method createCell:([BJJ[B)Lorg/apache/hadoop/hbase/Cell;
      92: aload         5
      94: invokevirtual #425                // Method org/apache/hadoop/hbase/regionserver/TestHStore$MyStore.add:(Lorg/apache/hadoop/hbase/Cell;Lorg/apache/hadoop/hbase/regionserver/MemStoreSizing;)V
      97: aload_2
      98: aload_0
      99: aload_0
     100: getfield      #24                 // Field qf3:[B
     103: lload         6
     105: lload         8
     107: aload_3
     108: invokespecial #410                // Method createCell:([BJJ[B)Lorg/apache/hadoop/hbase/Cell;
     111: aload         5
     113: invokevirtual #425                // Method org/apache/hadoop/hbase/regionserver/TestHStore$MyStore.add:(Lorg/apache/hadoop/hbase/Cell;Lorg/apache/hadoop/hbase/regionserver/MemStoreSizing;)V
     116: aload_0
     117: dup
     118: getfield      #40                 // Field id:J
     121: dup2_x1
     122: lconst_1
     123: ladd
     124: putfield      #40                 // Field id:J
     127: lstore        10
     129: aload_0
     130: getfield      #108                // Field store:Lorg/apache/hadoop/hbase/regionserver/HStore;
     133: lload         10
     135: getstatic     #243                // Field org/apache/hadoop/hbase/regionserver/FlushLifeCycleTracker.DUMMY:Lorg/apache/hadoop/hbase/regionserver/FlushLifeCycleTracker;
     138: invokevirtual #244                // Method org/apache/hadoop/hbase/regionserver/HStore.createFlushContext:(JLorg/apache/hadoop/hbase/regionserver/FlushLifeCycleTracker;)Lorg/apache/hadoop/hbase/regionserver/StoreFlushContext;
     141: astore        12
     143: aload         12
     145: invokeinterface #245,  1          // InterfaceMethod org/apache/hadoop/hbase/regionserver/StoreFlushContext.prepare:()Lorg/apache/hadoop/hbase/regionserver/MemStoreSize;
     150: pop
     151: aload_2
     152: aload_0
     153: aload_0
     154: getfield      #20                 // Field qf1:[B
     157: lload         6
     159: lconst_1
     160: ladd
     161: lload         8
     163: lconst_1
     164: ladd
     165: aload         4
     167: invokespecial #410                // Method createCell:([BJJ[B)Lorg/apache/hadoop/hbase/Cell;
     170: aload         5
     172: invokevirtual #425                // Method org/apache/hadoop/hbase/regionserver/TestHStore$MyStore.add:(Lorg/apache/hadoop/hbase/Cell;Lorg/apache/hadoop/hbase/regionserver/MemStoreSizing;)V
     175: aload_2
     176: aload_0
     177: aload_0
     178: getfield      #22                 // Field qf2:[B
     181: lload         6
     183: lconst_1
     184: ladd
     185: lload         8
     187: lconst_1
     188: ladd
     189: aload         4
     191: invokespecial #410                // Method createCell:([BJJ[B)Lorg/apache/hadoop/hbase/Cell;
     194: aload         5
     196: invokevirtual #425                // Method org/apache/hadoop/hbase/regionserver/TestHStore$MyStore.add:(Lorg/apache/hadoop/hbase/Cell;Lorg/apache/hadoop/hbase/regionserver/MemStoreSizing;)V
     199: aload_2
     200: aload_0
     201: aload_0
     202: getfield      #24                 // Field qf3:[B
     205: lload         6
     207: lconst_1
     208: ladd
     209: lload         8
     211: lconst_1
     212: ladd
     213: aload         4
     215: invokespecial #410                // Method createCell:([BJJ[B)Lorg/apache/hadoop/hbase/Cell;
     218: aload         5
     220: invokevirtual #425                // Method org/apache/hadoop/hbase/regionserver/TestHStore$MyStore.add:(Lorg/apache/hadoop/hbase/Cell;Lorg/apache/hadoop/hbase/regionserver/MemStoreSizing;)V
     223: new           #340                // class java/util/TreeSet
     226: dup
     227: getstatic     #32                 // Field org/apache/hadoop/hbase/util/Bytes.BYTES_COMPARATOR:Ljava/util/Comparator;
     230: invokespecial #341                // Method java/util/TreeSet."<init>":(Ljava/util/Comparator;)V
     233: astore        13
     235: aload         13
     237: aload_0
     238: getfield      #20                 // Field qf1:[B
     241: invokevirtual #345                // Method java/util/TreeSet.add:(Ljava/lang/Object;)Z
     244: pop
     245: aload         13
     247: aload_0
     248: getfield      #22                 // Field qf2:[B
     251: invokevirtual #345                // Method java/util/TreeSet.add:(Ljava/lang/Object;)Z
     254: pop
     255: aload         13
     257: aload_0
     258: getfield      #24                 // Field qf3:[B
     261: invokevirtual #345                // Method java/util/TreeSet.add:(Ljava/lang/Object;)Z
     264: pop
     265: aload_2
     266: new           #352                // class org/apache/hadoop/hbase/client/Scan
     269: dup
     270: new           #41                 // class org/apache/hadoop/hbase/client/Get
     273: dup
     274: aload_0
     275: getfield      #16                 // Field row:[B
     278: invokespecial #42                 // Method org/apache/hadoop/hbase/client/Get."<init>":([B)V
     281: invokespecial #416                // Method org/apache/hadoop/hbase/client/Scan."<init>":(Lorg/apache/hadoop/hbase/client/Get;)V
     284: aload         13
     286: lload         8
     288: lconst_1
     289: ladd
     290: invokevirtual #426                // Method org/apache/hadoop/hbase/regionserver/TestHStore$MyStore.getScanner:(Lorg/apache/hadoop/hbase/client/Scan;Ljava/util/NavigableSet;J)Lorg/apache/hadoop/hbase/regionserver/KeyValueScanner;
     293: checkcast     #395                // class org/apache/hadoop/hbase/regionserver/InternalScanner
     296: astore        14
     298: aconst_null
     299: astore        15
     301: aload         12
     303: ldc           #246                // class org/apache/hadoop/hbase/monitoring/MonitoredTask
     305: invokestatic  #247                // Method org/mockito/Mockito.mock:(Ljava/lang/Class;)Ljava/lang/Object;
     308: checkcast     #246                // class org/apache/hadoop/hbase/monitoring/MonitoredTask
     311: invokeinterface #248,  2          // InterfaceMethod org/apache/hadoop/hbase/regionserver/StoreFlushContext.flushCache:(Lorg/apache/hadoop/hbase/monitoring/MonitoredTask;)V
     316: aload         12
     318: ldc           #246                // class org/apache/hadoop/hbase/monitoring/MonitoredTask
     320: invokestatic  #247                // Method org/mockito/Mockito.mock:(Ljava/lang/Class;)Ljava/lang/Object;
     323: checkcast     #246                // class org/apache/hadoop/hbase/monitoring/MonitoredTask
     326: invokeinterface #249,  2          // InterfaceMethod org/apache/hadoop/hbase/regionserver/StoreFlushContext.commit:(Lorg/apache/hadoop/hbase/monitoring/MonitoredTask;)Z
     331: pop
     332: new           #35                 // class java/util/ArrayList
     335: dup
     336: invokespecial #36                 // Method java/util/ArrayList."<init>":()V
     339: astore        16
     341: aload         14
     343: aload         16
     345: invokeinterface #396,  2          // InterfaceMethod org/apache/hadoop/hbase/regionserver/InternalScanner.next:(Ljava/util/List;)Z
     350: pop
     351: ldc2_w        #389                // long 3l
     354: aload         16
     356: invokeinterface #216,  1          // InterfaceMethod java/util/List.size:()I
     361: i2l
     362: invokestatic  #169                // Method org/junit/Assert.assertEquals:(JJ)V
     365: aload         16
     367: invokeinterface #261,  1          // InterfaceMethod java/util/List.iterator:()Ljava/util/Iterator;
     372: astore        17
     374: aload         17
     376: invokeinterface #46,  1           // InterfaceMethod java/util/Iterator.hasNext:()Z
     381: ifeq          454
     384: aload         17
     386: invokeinterface #47,  1           // InterfaceMethod java/util/Iterator.next:()Ljava/lang/Object;
     391: checkcast     #262                // class org/apache/hadoop/hbase/Cell
     394: astore        18
     396: aload         18
     398: invokestatic  #397                // Method org/apache/hadoop/hbase/CellUtil.cloneValue:(Lorg/apache/hadoop/hbase/Cell;)[B
     401: astore        19
     403: new           #67                 // class java/lang/StringBuilder
     406: dup
     407: invokespecial #68                 // Method java/lang/StringBuilder."<init>":()V
     410: ldc_w         #398                // String expected:
     413: invokevirtual #70                 // Method java/lang/StringBuilder.append:(Ljava/lang/String;)Ljava/lang/StringBuilder;
     416: aload         4
     418: invokestatic  #399                // Method org/apache/hadoop/hbase/util/Bytes.toStringBinary:([B)Ljava/lang/String;
     421: invokevirtual #70                 // Method java/lang/StringBuilder.append:(Ljava/lang/String;)Ljava/lang/StringBuilder;
     424: ldc_w         #400                // String , actual:
     427: invokevirtual #70                 // Method java/lang/StringBuilder.append:(Ljava/lang/String;)Ljava/lang/StringBuilder;
     430: aload         19
     432: invokestatic  #399                // Method org/apache/hadoop/hbase/util/Bytes.toStringBinary:([B)Ljava/lang/String;
     435: invokevirtual #70                 // Method java/lang/StringBuilder.append:(Ljava/lang/String;)Ljava/lang/StringBuilder;
     438: invokevirtual #71                 // Method java/lang/StringBuilder.toString:()Ljava/lang/String;
     441: aload         19
     443: aload         4
     445: invokestatic  #401                // Method org/apache/hadoop/hbase/util/Bytes.equals:([B[B)Z
     448: invokestatic  #402                // Method org/junit/Assert.assertTrue:(Ljava/lang/String;Z)V
     451: goto          374
     454: aload         14
     456: ifnull        549
     459: aload         15
     461: ifnull        486
     464: aload         14
     466: invokeinterface #404,  1          // InterfaceMethod org/apache/hadoop/hbase/regionserver/InternalScanner.close:()V
     471: goto          549
     474: astore        16
     476: aload         15
     478: aload         16
     480: invokevirtual #363                // Method java/lang/Throwable.addSuppressed:(Ljava/lang/Throwable;)V
     483: goto          549
     486: aload         14
     488: invokeinterface #404,  1          // InterfaceMethod org/apache/hadoop/hbase/regionserver/InternalScanner.close:()V
     493: goto          549
     496: astore        16
     498: aload         16
     500: astore        15
     502: aload         16
     504: athrow
     505: astore        20
     507: aload         14
     509: ifnull        546
     512: aload         15
     514: ifnull        539
     517: aload         14
     519: invokeinterface #404,  1          // InterfaceMethod org/apache/hadoop/hbase/regionserver/InternalScanner.close:()V
     524: goto          546
     527: astore        21
     529: aload         15
     531: aload         21
     533: invokevirtual #363                // Method java/lang/Throwable.addSuppressed:(Ljava/lang/Throwable;)V
     536: goto          546
     539: aload         14
     541: invokeinterface #404,  1          // InterfaceMethod org/apache/hadoop/hbase/regionserver/InternalScanner.close:()V
     546: aload         20
     548: athrow
     549: return
    Exception table:
       from    to  target type
         464   471   474   Class java/lang/Throwable
         301   454   496   Class java/lang/Throwable
         301   454   505   any
         517   524   527   Class java/lang/Throwable
         496   507   505   any

  public void testReclaimChunkWhenScaning() throws java.io.IOException;
    Code:
       0: aload_0
       1: ldc_w         #427                // String testReclaimChunkWhenScaning
       4: invokespecial #194                // Method init:(Ljava/lang/String;)V
       7: invokestatic  #164                // Method org/apache/hadoop/hbase/util/EnvironmentEdgeManager.currentTime:()J
      10: lstore_1
      11: ldc2_w        #219                // long 100l
      14: lstore_3
      15: ldc_w         #409                // String value
      18: invokestatic  #11                 // Method org/apache/hadoop/hbase/util/Bytes.toBytes:(Ljava/lang/String;)[B
      21: astore        5
      23: aload_0
      24: getfield      #108                // Field store:Lorg/apache/hadoop/hbase/regionserver/HStore;
      27: aload_0
      28: aload_0
      29: getfield      #20                 // Field qf1:[B
      32: lload_1
      33: lload_3
      34: aload         5
      36: invokespecial #410                // Method createCell:([BJJ[B)Lorg/apache/hadoop/hbase/Cell;
      39: aconst_null
      40: invokevirtual #165                // Method org/apache/hadoop/hbase/regionserver/HStore.add:(Lorg/apache/hadoop/hbase/Cell;Lorg/apache/hadoop/hbase/regionserver/MemStoreSizing;)V
      43: aload_0
      44: getfield      #108                // Field store:Lorg/apache/hadoop/hbase/regionserver/HStore;
      47: aload_0
      48: aload_0
      49: getfield      #22                 // Field qf2:[B
      52: lload_1
      53: lload_3
      54: aload         5
      56: invokespecial #410                // Method createCell:([BJJ[B)Lorg/apache/hadoop/hbase/Cell;
      59: aconst_null
      60: invokevirtual #165                // Method org/apache/hadoop/hbase/regionserver/HStore.add:(Lorg/apache/hadoop/hbase/Cell;Lorg/apache/hadoop/hbase/regionserver/MemStoreSizing;)V
      63: aload_0
      64: getfield      #108                // Field store:Lorg/apache/hadoop/hbase/regionserver/HStore;
      67: aload_0
      68: aload_0
      69: getfield      #24                 // Field qf3:[B
      72: lload_1
      73: lload_3
      74: aload         5
      76: invokespecial #410                // Method createCell:([BJJ[B)Lorg/apache/hadoop/hbase/Cell;
      79: aconst_null
      80: invokevirtual #165                // Method org/apache/hadoop/hbase/regionserver/HStore.add:(Lorg/apache/hadoop/hbase/Cell;Lorg/apache/hadoop/hbase/regionserver/MemStoreSizing;)V
      83: new           #340                // class java/util/TreeSet
      86: dup
      87: getstatic     #32                 // Field org/apache/hadoop/hbase/util/Bytes.BYTES_COMPARATOR:Ljava/util/Comparator;
      90: invokespecial #341                // Method java/util/TreeSet."<init>":(Ljava/util/Comparator;)V
      93: astore        6
      95: aload         6
      97: aload_0
      98: getfield      #20                 // Field qf1:[B
     101: invokevirtual #345                // Method java/util/TreeSet.add:(Ljava/lang/Object;)Z
     104: pop
     105: aload         6
     107: aload_0
     108: getfield      #22                 // Field qf2:[B
     111: invokevirtual #345                // Method java/util/TreeSet.add:(Ljava/lang/Object;)Z
     114: pop
     115: aload         6
     117: aload_0
     118: getfield      #24                 // Field qf3:[B
     121: invokevirtual #345                // Method java/util/TreeSet.add:(Ljava/lang/Object;)Z
     124: pop
     125: aload_0
     126: getfield      #108                // Field store:Lorg/apache/hadoop/hbase/regionserver/HStore;
     129: new           #352                // class org/apache/hadoop/hbase/client/Scan
     132: dup
     133: new           #41                 // class org/apache/hadoop/hbase/client/Get
     136: dup
     137: aload_0
     138: getfield      #16                 // Field row:[B
     141: invokespecial #42                 // Method org/apache/hadoop/hbase/client/Get."<init>":([B)V
     144: invokespecial #416                // Method org/apache/hadoop/hbase/client/Scan."<init>":(Lorg/apache/hadoop/hbase/client/Get;)V
     147: aload         6
     149: lload_3
     150: invokevirtual #354                // Method org/apache/hadoop/hbase/regionserver/HStore.getScanner:(Lorg/apache/hadoop/hbase/client/Scan;Ljava/util/NavigableSet;J)Lorg/apache/hadoop/hbase/regionserver/KeyValueScanner;
     153: checkcast     #395                // class org/apache/hadoop/hbase/regionserver/InternalScanner
     156: astore        7
     158: aconst_null
     159: astore        8
     161: new           #391                // class org/apache/hadoop/hbase/regionserver/TestHStore$MyList
     164: dup
     165: aload_0
     166: lload_1
     167: lload_3
     168: invokedynamic #428,  0            // InvokeDynamic #4:hook:(Lorg/apache/hadoop/hbase/regionserver/TestHStore;JJ)Lorg/apache/hadoop/hbase/regionserver/TestHStore$MyListHook;
     173: invokespecial #392                // Method org/apache/hadoop/hbase/regionserver/TestHStore$MyList."<init>":(Lorg/apache/hadoop/hbase/regionserver/TestHStore$MyListHook;)V
     176: astore        9
     178: aload         7
     180: aload         9
     182: invokeinterface #396,  2          // InterfaceMethod org/apache/hadoop/hbase/regionserver/InternalScanner.next:(Ljava/util/List;)Z
     187: pop
     188: ldc2_w        #389                // long 3l
     191: aload         9
     193: invokeinterface #216,  1          // InterfaceMethod java/util/List.size:()I
     198: i2l
     199: invokestatic  #169                // Method org/junit/Assert.assertEquals:(JJ)V
     202: aload         9
     204: invokeinterface #261,  1          // InterfaceMethod java/util/List.iterator:()Ljava/util/Iterator;
     209: astore        10
     211: aload         10
     213: invokeinterface #46,  1           // InterfaceMethod java/util/Iterator.hasNext:()Z
     218: ifeq          291
     221: aload         10
     223: invokeinterface #47,  1           // InterfaceMethod java/util/Iterator.next:()Ljava/lang/Object;
     228: checkcast     #262                // class org/apache/hadoop/hbase/Cell
     231: astore        11
     233: aload         11
     235: invokestatic  #397                // Method org/apache/hadoop/hbase/CellUtil.cloneValue:(Lorg/apache/hadoop/hbase/Cell;)[B
     238: astore        12
     240: new           #67                 // class java/lang/StringBuilder
     243: dup
     244: invokespecial #68                 // Method java/lang/StringBuilder."<init>":()V
     247: ldc_w         #398                // String expected:
     250: invokevirtual #70                 // Method java/lang/StringBuilder.append:(Ljava/lang/String;)Ljava/lang/StringBuilder;
     253: aload         5
     255: invokestatic  #399                // Method org/apache/hadoop/hbase/util/Bytes.toStringBinary:([B)Ljava/lang/String;
     258: invokevirtual #70                 // Method java/lang/StringBuilder.append:(Ljava/lang/String;)Ljava/lang/StringBuilder;
     261: ldc_w         #400                // String , actual:
     264: invokevirtual #70                 // Method java/lang/StringBuilder.append:(Ljava/lang/String;)Ljava/lang/StringBuilder;
     267: aload         12
     269: invokestatic  #399                // Method org/apache/hadoop/hbase/util/Bytes.toStringBinary:([B)Ljava/lang/String;
     272: invokevirtual #70                 // Method java/lang/StringBuilder.append:(Ljava/lang/String;)Ljava/lang/StringBuilder;
     275: invokevirtual #71                 // Method java/lang/StringBuilder.toString:()Ljava/lang/String;
     278: aload         12
     280: aload         5
     282: invokestatic  #401                // Method org/apache/hadoop/hbase/util/Bytes.equals:([B[B)Z
     285: invokestatic  #402                // Method org/junit/Assert.assertTrue:(Ljava/lang/String;Z)V
     288: goto          211
     291: aload         7
     293: ifnull        386
     296: aload         8
     298: ifnull        323
     301: aload         7
     303: invokeinterface #404,  1          // InterfaceMethod org/apache/hadoop/hbase/regionserver/InternalScanner.close:()V
     308: goto          386
     311: astore        9
     313: aload         8
     315: aload         9
     317: invokevirtual #363                // Method java/lang/Throwable.addSuppressed:(Ljava/lang/Throwable;)V
     320: goto          386
     323: aload         7
     325: invokeinterface #404,  1          // InterfaceMethod org/apache/hadoop/hbase/regionserver/InternalScanner.close:()V
     330: goto          386
     333: astore        9
     335: aload         9
     337: astore        8
     339: aload         9
     341: athrow
     342: astore        13
     344: aload         7
     346: ifnull        383
     349: aload         8
     351: ifnull        376
     354: aload         7
     356: invokeinterface #404,  1          // InterfaceMethod org/apache/hadoop/hbase/regionserver/InternalScanner.close:()V
     361: goto          383
     364: astore        14
     366: aload         8
     368: aload         14
     370: invokevirtual #363                // Method java/lang/Throwable.addSuppressed:(Ljava/lang/Throwable;)V
     373: goto          383
     376: aload         7
     378: invokeinterface #404,  1          // InterfaceMethod org/apache/hadoop/hbase/regionserver/InternalScanner.close:()V
     383: aload         13
     385: athrow
     386: return
    Exception table:
       from    to  target type
         301   308   311   Class java/lang/Throwable
         161   291   333   Class java/lang/Throwable
         161   291   342   any
         354   361   364   Class java/lang/Throwable
         333   344   342   any

  public void testRunDoubleMemStoreCompactors() throws java.io.IOException, java.lang.InterruptedException;
    Code:
       0: sipush        500
       3: istore_1
       4: invokestatic  #127                // Method org/apache/hadoop/hbase/HBaseConfiguration.create:()Lorg/apache/hadoop/conf/Configuration;
       7: astore_2
       8: aload_2
       9: ldc_w         #405                // String hbase.regionserver.memstore.class
      12: ldc_w         #429                // class org/apache/hadoop/hbase/regionserver/TestHStore$MyCompactingMemStoreWithCustomCompactor
      15: invokevirtual #293                // Method java/lang/Class.getName:()Ljava/lang/String;
      18: invokevirtual #294                // Method org/apache/hadoop/conf/Configuration.set:(Ljava/lang/String;Ljava/lang/String;)V
      21: aload_2
      22: ldc_w         #431                // String hbase.memstore.inmemoryflush.threshold.factor
      25: ldc2_w        #432                // double 0.25d
      28: invokevirtual #434                // Method org/apache/hadoop/conf/Configuration.setDouble:(Ljava/lang/String;D)V
      31: invokestatic  #435                // Method org/apache/hadoop/hbase/regionserver/TestHStore$MyCompactingMemStoreWithCustomCompactor.access$600:()Ljava/util/concurrent/atomic/AtomicInteger;
      34: iconst_0
      35: invokevirtual #436                // Method java/util/concurrent/atomic/AtomicInteger.set:(I)V
      38: aload_2
      39: ldc_w         #438                // String hbase.hregion.memstore.flush.size
      42: iload_1
      43: invokestatic  #439                // Method java/lang/String.valueOf:(I)Ljava/lang/String;
      46: invokevirtual #294                // Method org/apache/hadoop/conf/Configuration.set:(Ljava/lang/String;Ljava/lang/String;)V
      49: aload_2
      50: ldc_w         #441                // String hbase.hregion.compacting.pipeline.segments.limit
      53: iconst_0
      54: invokestatic  #439                // Method java/lang/String.valueOf:(I)Ljava/lang/String;
      57: invokevirtual #294                // Method org/apache/hadoop/conf/Configuration.set:(Ljava/lang/String;Ljava/lang/String;)V
      60: aload_0
      61: aload_0
      62: getfield      #9                  // Field name:Lorg/junit/rules/TestName;
      65: invokevirtual #112                // Method org/junit/rules/TestName.getMethodName:()Ljava/lang/String;
      68: aload_2
      69: aload_0
      70: getfield      #14                 // Field family:[B
      73: invokestatic  #55                 // Method org/apache/hadoop/hbase/client/ColumnFamilyDescriptorBuilder.newBuilder:([B)Lorg/apache/hadoop/hbase/client/ColumnFamilyDescriptorBuilder;
      76: getstatic     #407                // Field org/apache/hadoop/hbase/MemoryCompactionPolicy.BASIC:Lorg/apache/hadoop/hbase/MemoryCompactionPolicy;
      79: invokevirtual #408                // Method org/apache/hadoop/hbase/client/ColumnFamilyDescriptorBuilder.setInMemoryCompaction:(Lorg/apache/hadoop/hbase/MemoryCompactionPolicy;)Lorg/apache/hadoop/hbase/client/ColumnFamilyDescriptorBuilder;
      82: invokevirtual #57                 // Method org/apache/hadoop/hbase/client/ColumnFamilyDescriptorBuilder.build:()Lorg/apache/hadoop/hbase/client/ColumnFamilyDescriptor;
      85: invokespecial #58                 // Method init:(Ljava/lang/String;Lorg/apache/hadoop/conf/Configuration;Lorg/apache/hadoop/hbase/client/ColumnFamilyDescriptor;)Lorg/apache/hadoop/hbase/regionserver/HStore;
      88: pop
      89: ldc_w         #442                // String thisisavarylargevalue
      92: invokestatic  #11                 // Method org/apache/hadoop/hbase/util/Bytes.toBytes:(Ljava/lang/String;)[B
      95: astore_3
      96: new           #385                // class org/apache/hadoop/hbase/regionserver/NonThreadSafeMemStoreSizing
      99: dup
     100: invokespecial #386                // Method org/apache/hadoop/hbase/regionserver/NonThreadSafeMemStoreSizing."<init>":()V
     103: astore        4
     105: invokestatic  #164                // Method org/apache/hadoop/hbase/util/EnvironmentEdgeManager.currentTime:()J
     108: lstore        5
     110: ldc2_w        #219                // long 100l
     113: lstore        7
     115: aload_0
     116: getfield      #108                // Field store:Lorg/apache/hadoop/hbase/regionserver/HStore;
     119: aload_0
     120: aload_0
     121: getfield      #20                 // Field qf1:[B
     124: lload         5
     126: lload         7
     128: aload_3
     129: invokespecial #410                // Method createCell:([BJJ[B)Lorg/apache/hadoop/hbase/Cell;
     132: aload         4
     134: invokevirtual #165                // Method org/apache/hadoop/hbase/regionserver/HStore.add:(Lorg/apache/hadoop/hbase/Cell;Lorg/apache/hadoop/hbase/regionserver/MemStoreSizing;)V
     137: aload_0
     138: getfield      #108                // Field store:Lorg/apache/hadoop/hbase/regionserver/HStore;
     141: aload_0
     142: aload_0
     143: getfield      #22                 // Field qf2:[B
     146: lload         5
     148: lload         7
     150: aload_3
     151: invokespecial #410                // Method createCell:([BJJ[B)Lorg/apache/hadoop/hbase/Cell;
     154: aload         4
     156: invokevirtual #165                // Method org/apache/hadoop/hbase/regionserver/HStore.add:(Lorg/apache/hadoop/hbase/Cell;Lorg/apache/hadoop/hbase/regionserver/MemStoreSizing;)V
     159: aload_0
     160: getfield      #108                // Field store:Lorg/apache/hadoop/hbase/regionserver/HStore;
     163: aload_0
     164: aload_0
     165: getfield      #24                 // Field qf3:[B
     168: lload         5
     170: lload         7
     172: aload_3
     173: invokespecial #410                // Method createCell:([BJJ[B)Lorg/apache/hadoop/hbase/Cell;
     176: aload         4
     178: invokevirtual #165                // Method org/apache/hadoop/hbase/regionserver/HStore.add:(Lorg/apache/hadoop/hbase/Cell;Lorg/apache/hadoop/hbase/regionserver/MemStoreSizing;)V
     181: lconst_1
     182: invokestatic  #435                // Method org/apache/hadoop/hbase/regionserver/TestHStore$MyCompactingMemStoreWithCustomCompactor.access$600:()Ljava/util/concurrent/atomic/AtomicInteger;
     185: invokevirtual #443                // Method java/util/concurrent/atomic/AtomicInteger.get:()I
     188: i2l
     189: invokestatic  #169                // Method org/junit/Assert.assertEquals:(JJ)V
     192: aload_0
     193: getfield      #108                // Field store:Lorg/apache/hadoop/hbase/regionserver/HStore;
     196: aload_0
     197: dup
     198: getfield      #40                 // Field id:J
     201: dup2_x1
     202: lconst_1
     203: ladd
     204: putfield      #40                 // Field id:J
     207: getstatic     #243                // Field org/apache/hadoop/hbase/regionserver/FlushLifeCycleTracker.DUMMY:Lorg/apache/hadoop/hbase/regionserver/FlushLifeCycleTracker;
     210: invokevirtual #244                // Method org/apache/hadoop/hbase/regionserver/HStore.createFlushContext:(JLorg/apache/hadoop/hbase/regionserver/FlushLifeCycleTracker;)Lorg/apache/hadoop/hbase/regionserver/StoreFlushContext;
     213: astore        9
     215: aload         9
     217: invokeinterface #245,  1          // InterfaceMethod org/apache/hadoop/hbase/regionserver/StoreFlushContext.prepare:()Lorg/apache/hadoop/hbase/regionserver/MemStoreSize;
     222: pop
     223: aload_0
     224: getfield      #108                // Field store:Lorg/apache/hadoop/hbase/regionserver/HStore;
     227: aload_0
     228: aload_0
     229: getfield      #20                 // Field qf1:[B
     232: lload         5
     234: lconst_1
     235: ladd
     236: lload         7
     238: lconst_1
     239: ladd
     240: aload_3
     241: invokespecial #410                // Method createCell:([BJJ[B)Lorg/apache/hadoop/hbase/Cell;
     244: aload         4
     246: invokevirtual #165                // Method org/apache/hadoop/hbase/regionserver/HStore.add:(Lorg/apache/hadoop/hbase/Cell;Lorg/apache/hadoop/hbase/regionserver/MemStoreSizing;)V
     249: aload_0
     250: getfield      #108                // Field store:Lorg/apache/hadoop/hbase/regionserver/HStore;
     253: aload_0
     254: aload_0
     255: getfield      #20                 // Field qf1:[B
     258: lload         5
     260: lconst_1
     261: ladd
     262: lload         7
     264: lconst_1
     265: ladd
     266: aload_3
     267: invokespecial #410                // Method createCell:([BJJ[B)Lorg/apache/hadoop/hbase/Cell;
     270: aload         4
     272: invokevirtual #165                // Method org/apache/hadoop/hbase/regionserver/HStore.add:(Lorg/apache/hadoop/hbase/Cell;Lorg/apache/hadoop/hbase/regionserver/MemStoreSizing;)V
     275: aload_0
     276: getfield      #108                // Field store:Lorg/apache/hadoop/hbase/regionserver/HStore;
     279: aload_0
     280: aload_0
     281: getfield      #20                 // Field qf1:[B
     284: lload         5
     286: lconst_1
     287: ladd
     288: lload         7
     290: lconst_1
     291: ladd
     292: aload_3
     293: invokespecial #410                // Method createCell:([BJJ[B)Lorg/apache/hadoop/hbase/Cell;
     296: aload         4
     298: invokevirtual #165                // Method org/apache/hadoop/hbase/regionserver/HStore.add:(Lorg/apache/hadoop/hbase/Cell;Lorg/apache/hadoop/hbase/regionserver/MemStoreSizing;)V
     301: lconst_1
     302: invokestatic  #435                // Method org/apache/hadoop/hbase/regionserver/TestHStore$MyCompactingMemStoreWithCustomCompactor.access$600:()Ljava/util/concurrent/atomic/AtomicInteger;
     305: invokevirtual #443                // Method java/util/concurrent/atomic/AtomicInteger.get:()I
     308: i2l
     309: invokestatic  #169                // Method org/junit/Assert.assertEquals:(JJ)V
     312: invokestatic  #444                // Method org/apache/hadoop/hbase/regionserver/TestHStore$MyMemStoreCompactor.access$700:()Ljava/util/concurrent/CountDownLatch;
     315: invokevirtual #445                // Method java/util/concurrent/CountDownLatch.countDown:()V
     318: aload_0
     319: getfield      #108                // Field store:Lorg/apache/hadoop/hbase/regionserver/HStore;
     322: getfield      #228                // Field org/apache/hadoop/hbase/regionserver/HStore.memstore:Lorg/apache/hadoop/hbase/regionserver/MemStore;
     325: checkcast     #430                // class org/apache/hadoop/hbase/regionserver/CompactingMemStore
     328: astore        10
     330: aload         10
     332: invokevirtual #446                // Method org/apache/hadoop/hbase/regionserver/CompactingMemStore.isMemStoreFlushingInMemory:()Z
     335: ifeq          348
     338: getstatic     #418                // Field java/util/concurrent/TimeUnit.SECONDS:Ljava/util/concurrent/TimeUnit;
     341: lconst_1
     342: invokevirtual #447                // Method java/util/concurrent/TimeUnit.sleep:(J)V
     345: goto          330
     348: aload_0
     349: getfield      #108                // Field store:Lorg/apache/hadoop/hbase/regionserver/HStore;
     352: aload_0
     353: aload_0
     354: getfield      #20                 // Field qf1:[B
     357: lload         5
     359: ldc2_w        #211                // long 2l
     362: ladd
     363: lload         7
     365: ldc2_w        #211                // long 2l
     368: ladd
     369: aload_3
     370: invokespecial #410                // Method createCell:([BJJ[B)Lorg/apache/hadoop/hbase/Cell;
     373: aload         4
     375: invokevirtual #165                // Method org/apache/hadoop/hbase/regionserver/HStore.add:(Lorg/apache/hadoop/hbase/Cell;Lorg/apache/hadoop/hbase/regionserver/MemStoreSizing;)V
     378: aload_0
     379: getfield      #108                // Field store:Lorg/apache/hadoop/hbase/regionserver/HStore;
     382: aload_0
     383: aload_0
     384: getfield      #20                 // Field qf1:[B
     387: lload         5
     389: ldc2_w        #211                // long 2l
     392: ladd
     393: lload         7
     395: ldc2_w        #211                // long 2l
     398: ladd
     399: aload_3
     400: invokespecial #410                // Method createCell:([BJJ[B)Lorg/apache/hadoop/hbase/Cell;
     403: aload         4
     405: invokevirtual #165                // Method org/apache/hadoop/hbase/regionserver/HStore.add:(Lorg/apache/hadoop/hbase/Cell;Lorg/apache/hadoop/hbase/regionserver/MemStoreSizing;)V
     408: aload_0
     409: getfield      #108                // Field store:Lorg/apache/hadoop/hbase/regionserver/HStore;
     412: aload_0
     413: aload_0
     414: getfield      #20                 // Field qf1:[B
     417: lload         5
     419: ldc2_w        #211                // long 2l
     422: ladd
     423: lload         7
     425: ldc2_w        #211                // long 2l
     428: ladd
     429: aload_3
     430: invokespecial #410                // Method createCell:([BJJ[B)Lorg/apache/hadoop/hbase/Cell;
     433: aload         4
     435: invokevirtual #165                // Method org/apache/hadoop/hbase/regionserver/HStore.add:(Lorg/apache/hadoop/hbase/Cell;Lorg/apache/hadoop/hbase/regionserver/MemStoreSizing;)V
     438: ldc2_w        #211                // long 2l
     441: invokestatic  #435                // Method org/apache/hadoop/hbase/regionserver/TestHStore$MyCompactingMemStoreWithCustomCompactor.access$600:()Ljava/util/concurrent/atomic/AtomicInteger;
     444: invokevirtual #443                // Method java/util/concurrent/atomic/AtomicInteger.get:()I
     447: i2l
     448: invokestatic  #169                // Method org/junit/Assert.assertEquals:(JJ)V
     451: aload_2
     452: ldc_w         #438                // String hbase.hregion.memstore.flush.size
     455: ldc2_w        #449                // long 134217728l
     458: invokestatic  #451                // Method java/lang/String.valueOf:(J)Ljava/lang/String;
     461: invokevirtual #294                // Method org/apache/hadoop/conf/Configuration.set:(Ljava/lang/String;Ljava/lang/String;)V
     464: aload         9
     466: ldc           #246                // class org/apache/hadoop/hbase/monitoring/MonitoredTask
     468: invokestatic  #247                // Method org/mockito/Mockito.mock:(Ljava/lang/Class;)Ljava/lang/Object;
     471: checkcast     #246                // class org/apache/hadoop/hbase/monitoring/MonitoredTask
     474: invokeinterface #248,  2          // InterfaceMethod org/apache/hadoop/hbase/regionserver/StoreFlushContext.flushCache:(Lorg/apache/hadoop/hbase/monitoring/MonitoredTask;)V
     479: aload         9
     481: ldc           #246                // class org/apache/hadoop/hbase/monitoring/MonitoredTask
     483: invokestatic  #247                // Method org/mockito/Mockito.mock:(Ljava/lang/Class;)Ljava/lang/Object;
     486: checkcast     #246                // class org/apache/hadoop/hbase/monitoring/MonitoredTask
     489: invokeinterface #249,  2          // InterfaceMethod org/apache/hadoop/hbase/regionserver/StoreFlushContext.commit:(Lorg/apache/hadoop/hbase/monitoring/MonitoredTask;)Z
     494: pop
     495: return

  public void testAge() throws java.io.IOException;
    Code:
       0: invokestatic  #39                 // Method java/lang/System.currentTimeMillis:()J
       3: lstore_1
       4: new           #452                // class org/apache/hadoop/hbase/util/ManualEnvironmentEdge
       7: dup
       8: invokespecial #453                // Method org/apache/hadoop/hbase/util/ManualEnvironmentEdge."<init>":()V
      11: astore_3
      12: aload_3
      13: lload_1
      14: invokevirtual #454                // Method org/apache/hadoop/hbase/util/ManualEnvironmentEdge.setValue:(J)V
      17: aload_3
      18: invokestatic  #455                // Method org/apache/hadoop/hbase/util/EnvironmentEdgeManager.injectEdge:(Lorg/apache/hadoop/hbase/util/EnvironmentEdge;)V
      21: getstatic     #53                 // Field TEST_UTIL:Lorg/apache/hadoop/hbase/HBaseTestingUtility;
      24: invokevirtual #54                 // Method org/apache/hadoop/hbase/HBaseTestingUtility.getConfiguration:()Lorg/apache/hadoop/conf/Configuration;
      27: astore        4
      29: aload_0
      30: getfield      #14                 // Field family:[B
      33: invokestatic  #287                // Method org/apache/hadoop/hbase/client/ColumnFamilyDescriptorBuilder.of:([B)Lorg/apache/hadoop/hbase/client/ColumnFamilyDescriptor;
      36: astore        5
      38: aload_0
      39: aload_0
      40: getfield      #9                  // Field name:Lorg/junit/rules/TestName;
      43: invokevirtual #112                // Method org/junit/rules/TestName.getMethodName:()Ljava/lang/String;
      46: aload         4
      48: aload_0
      49: getfield      #12                 // Field table:[B
      52: invokestatic  #59                 // Method org/apache/hadoop/hbase/TableName.valueOf:([B)Lorg/apache/hadoop/hbase/TableName;
      55: invokestatic  #60                 // Method org/apache/hadoop/hbase/client/TableDescriptorBuilder.newBuilder:(Lorg/apache/hadoop/hbase/TableName;)Lorg/apache/hadoop/hbase/client/TableDescriptorBuilder;
      58: aload         5
      60: aconst_null
      61: iconst_0
      62: invokespecial #105                // Method initHRegion:(Ljava/lang/String;Lorg/apache/hadoop/conf/Configuration;Lorg/apache/hadoop/hbase/client/TableDescriptorBuilder;Lorg/apache/hadoop/hbase/client/ColumnFamilyDescriptor;Lorg/apache/hadoop/hbase/regionserver/TestHStore$MyStoreHook;Z)V
      65: new           #456                // class org/apache/hadoop/hbase/regionserver/TestHStore$11
      68: dup
      69: aload_0
      70: aload_0
      71: getfield      #96                 // Field region:Lorg/apache/hadoop/hbase/regionserver/HRegion;
      74: aload         5
      76: aload         4
      78: iconst_0
      79: lload_1
      80: invokespecial #457                // Method org/apache/hadoop/hbase/regionserver/TestHStore$11."<init>":(Lorg/apache/hadoop/hbase/regionserver/TestHStore;Lorg/apache/hadoop/hbase/regionserver/HRegion;Lorg/apache/hadoop/hbase/client/ColumnFamilyDescriptor;Lorg/apache/hadoop/conf/Configuration;ZJ)V
      83: astore        6
      85: ldc2_w        #252                // long 10l
      88: aload         6
      90: invokevirtual #458                // Method org/apache/hadoop/hbase/regionserver/HStore.getMinStoreFileAge:()Ljava/util/OptionalLong;
      93: invokevirtual #459                // Method java/util/OptionalLong.getAsLong:()J
      96: invokestatic  #169                // Method org/junit/Assert.assertEquals:(JJ)V
      99: ldc2_w        #460                // long 10000l
     102: aload         6
     104: invokevirtual #462                // Method org/apache/hadoop/hbase/regionserver/HStore.getMaxStoreFileAge:()Ljava/util/OptionalLong;
     107: invokevirtual #459                // Method java/util/OptionalLong.getAsLong:()J
     110: invokestatic  #169                // Method org/junit/Assert.assertEquals:(JJ)V
     113: ldc2_w        #463                // double 2777.5d
     116: aload         6
     118: invokevirtual #465                // Method org/apache/hadoop/hbase/regionserver/HStore.getAvgStoreFileAge:()Ljava/util/OptionalDouble;
     121: invokevirtual #466                // Method java/util/OptionalDouble.getAsDouble:()D
     124: ldc2_w        #467                // double 1.0E-4d
     127: invokestatic  #469                // Method org/junit/Assert.assertEquals:(DDD)V
     130: return

  public void testSwitchingPreadtoStreamParallelyWithCompactionDischarger() throws java.lang.Exception;
    Code:
       0: invokestatic  #127                // Method org/apache/hadoop/hbase/HBaseConfiguration.create:()Lorg/apache/hadoop/conf/Configuration;
       3: astore_1
       4: aload_1
       5: ldc_w         #291                // String hbase.hstore.engine.class
       8: ldc_w         #292                // class org/apache/hadoop/hbase/regionserver/TestHStore$DummyStoreEngine
      11: invokevirtual #293                // Method java/lang/Class.getName:()Ljava/lang/String;
      14: invokevirtual #294                // Method org/apache/hadoop/conf/Configuration.set:(Ljava/lang/String;Ljava/lang/String;)V
      17: aload_1
      18: ldc_w         #477                // String hbase.storescanner.pread.max.bytes
      21: lconst_0
      22: invokevirtual #281                // Method org/apache/hadoop/conf/Configuration.setLong:(Ljava/lang/String;J)V
      25: aload_0
      26: aload_0
      27: getfield      #9                  // Field name:Lorg/junit/rules/TestName;
      30: invokevirtual #112                // Method org/junit/rules/TestName.getMethodName:()Ljava/lang/String;
      33: aload_1
      34: new           #478                // class org/apache/hadoop/hbase/regionserver/TestHStore$12
      37: dup
      38: aload_0
      39: invokespecial #479                // Method org/apache/hadoop/hbase/regionserver/TestHStore$12."<init>":(Lorg/apache/hadoop/hbase/regionserver/TestHStore;)V
      42: invokespecial #422                // Method initMyStore:(Ljava/lang/String;Lorg/apache/hadoop/conf/Configuration;Lorg/apache/hadoop/hbase/regionserver/TestHStore$MyStoreHook;)Lorg/apache/hadoop/hbase/regionserver/TestHStore$MyStore;
      45: astore_2
      46: new           #385                // class org/apache/hadoop/hbase/regionserver/NonThreadSafeMemStoreSizing
      49: dup
      50: invokespecial #386                // Method org/apache/hadoop/hbase/regionserver/NonThreadSafeMemStoreSizing."<init>":()V
      53: astore_3
      54: invokestatic  #39                 // Method java/lang/System.currentTimeMillis:()J
      57: lstore        4
      59: lconst_1
      60: lstore        6
      62: iconst_1
      63: istore        8
      65: iload         8
      67: bipush        10
      69: if_icmpge     129
      72: aload_2
      73: aload_0
      74: new           #67                 // class java/lang/StringBuilder
      77: dup
      78: invokespecial #68                 // Method java/lang/StringBuilder."<init>":()V
      81: ldc           #15                 // String row
      83: invokevirtual #70                 // Method java/lang/StringBuilder.append:(Ljava/lang/String;)Ljava/lang/StringBuilder;
      86: iload         8
      88: invokevirtual #158                // Method java/lang/StringBuilder.append:(I)Ljava/lang/StringBuilder;
      91: invokevirtual #71                 // Method java/lang/StringBuilder.toString:()Ljava/lang/String;
      94: invokestatic  #11                 // Method org/apache/hadoop/hbase/util/Bytes.toBytes:(Ljava/lang/String;)[B
      97: aload_0
      98: getfield      #20                 // Field qf1:[B
     101: lload         4
     103: lload         6
     105: dup2
     106: lconst_1
     107: ladd
     108: lstore        6
     110: ldc_w         #480                // String
     113: invokestatic  #11                 // Method org/apache/hadoop/hbase/util/Bytes.toBytes:(Ljava/lang/String;)[B
     116: invokespecial #364                // Method createCell:([B[BJJ[B)Lorg/apache/hadoop/hbase/Cell;
     119: aload_3
     120: invokevirtual #425                // Method org/apache/hadoop/hbase/regionserver/TestHStore$MyStore.add:(Lorg/apache/hadoop/hbase/Cell;Lorg/apache/hadoop/hbase/regionserver/MemStoreSizing;)V
     123: iinc          8, 1
     126: goto          65
     129: aload_2
     130: lload         6
     132: invokestatic  #3                  // Method flushStore:(Lorg/apache/hadoop/hbase/regionserver/HStore;J)V
     135: bipush        11
     137: istore        8
     139: iload         8
     141: bipush        20
     143: if_icmpge     203
     146: aload_2
     147: aload_0
     148: new           #67                 // class java/lang/StringBuilder
     151: dup
     152: invokespecial #68                 // Method java/lang/StringBuilder."<init>":()V
     155: ldc           #15                 // String row
     157: invokevirtual #70                 // Method java/lang/StringBuilder.append:(Ljava/lang/String;)Ljava/lang/StringBuilder;
     160: iload         8
     162: invokevirtual #158                // Method java/lang/StringBuilder.append:(I)Ljava/lang/StringBuilder;
     165: invokevirtual #71                 // Method java/lang/StringBuilder.toString:()Ljava/lang/String;
     168: invokestatic  #11                 // Method org/apache/hadoop/hbase/util/Bytes.toBytes:(Ljava/lang/String;)[B
     171: aload_0
     172: getfield      #20                 // Field qf1:[B
     175: lload         4
     177: lload         6
     179: dup2
     180: lconst_1
     181: ladd
     182: lstore        6
     184: ldc_w         #480                // String
     187: invokestatic  #11                 // Method org/apache/hadoop/hbase/util/Bytes.toBytes:(Ljava/lang/String;)[B
     190: invokespecial #364                // Method createCell:([B[BJJ[B)Lorg/apache/hadoop/hbase/Cell;
     193: aload_3
     194: invokevirtual #425                // Method org/apache/hadoop/hbase/regionserver/TestHStore$MyStore.add:(Lorg/apache/hadoop/hbase/Cell;Lorg/apache/hadoop/hbase/regionserver/MemStoreSizing;)V
     197: iinc          8, 1
     200: goto          139
     203: aload_2
     204: lload         6
     206: invokestatic  #3                  // Method flushStore:(Lorg/apache/hadoop/hbase/regionserver/HStore;J)V
     209: bipush        21
     211: istore        8
     213: iload         8
     215: bipush        30
     217: if_icmpge     277
     220: aload_2
     221: aload_0
     222: new           #67                 // class java/lang/StringBuilder
     225: dup
     226: invokespecial #68                 // Method java/lang/StringBuilder."<init>":()V
     229: ldc           #15                 // String row
     231: invokevirtual #70                 // Method java/lang/StringBuilder.append:(Ljava/lang/String;)Ljava/lang/StringBuilder;
     234: iload         8
     236: invokevirtual #158                // Method java/lang/StringBuilder.append:(I)Ljava/lang/StringBuilder;
     239: invokevirtual #71                 // Method java/lang/StringBuilder.toString:()Ljava/lang/String;
     242: invokestatic  #11                 // Method org/apache/hadoop/hbase/util/Bytes.toBytes:(Ljava/lang/String;)[B
     245: aload_0
     246: getfield      #20                 // Field qf1:[B
     249: lload         4
     251: lload         6
     253: dup2
     254: lconst_1
     255: ladd
     256: lstore        6
     258: ldc_w         #480                // String
     261: invokestatic  #11                 // Method org/apache/hadoop/hbase/util/Bytes.toBytes:(Ljava/lang/String;)[B
     264: invokespecial #364                // Method createCell:([B[BJJ[B)Lorg/apache/hadoop/hbase/Cell;
     267: aload_3
     268: invokevirtual #425                // Method org/apache/hadoop/hbase/regionserver/TestHStore$MyStore.add:(Lorg/apache/hadoop/hbase/Cell;Lorg/apache/hadoop/hbase/regionserver/MemStoreSizing;)V
     271: iinc          8, 1
     274: goto          213
     277: aload_2
     278: lload         6
     280: invokestatic  #3                  // Method flushStore:(Lorg/apache/hadoop/hbase/regionserver/HStore;J)V
     283: ldc2_w        #389                // long 3l
     286: aload_2
     287: invokevirtual #481                // Method org/apache/hadoop/hbase/regionserver/TestHStore$MyStore.getStorefilesCount:()I
     290: i2l
     291: invokestatic  #169                // Method org/junit/Assert.assertEquals:(JJ)V
     294: new           #352                // class org/apache/hadoop/hbase/client/Scan
     297: dup
     298: invokespecial #353                // Method org/apache/hadoop/hbase/client/Scan."<init>":()V
     301: astore        8
     303: aload         8
     305: aload_0
     306: getfield      #14                 // Field family:[B
     309: invokevirtual #482                // Method org/apache/hadoop/hbase/client/Scan.addFamily:([B)Lorg/apache/hadoop/hbase/client/Scan;
     312: pop
     313: aload_2
     314: invokevirtual #483                // Method org/apache/hadoop/hbase/regionserver/TestHStore$MyStore.getStorefiles:()Ljava/util/Collection;
     317: astore        9
     319: aload         9
     321: invokestatic  #484                // Method org/apache/hbase/thirdparty/com/google/common/collect/Lists.newArrayList:(Ljava/lang/Iterable;)Ljava/util/ArrayList;
     324: astore        10
     326: aload_2
     327: aload         8
     329: aload         8
     331: invokevirtual #485                // Method org/apache/hadoop/hbase/client/Scan.getFamilyMap:()Ljava/util/Map;
     334: aload_0
     335: getfield      #14                 // Field family:[B
     338: invokeinterface #486,  2          // InterfaceMethod java/util/Map.get:(Ljava/lang/Object;)Ljava/lang/Object;
     343: checkcast     #487                // class java/util/NavigableSet
     346: ldc2_w        #187                // long 9223372036854775807l
     349: invokevirtual #426                // Method org/apache/hadoop/hbase/regionserver/TestHStore$MyStore.getScanner:(Lorg/apache/hadoop/hbase/client/Scan;Ljava/util/NavigableSet;J)Lorg/apache/hadoop/hbase/regionserver/KeyValueScanner;
     352: checkcast     #355                // class org/apache/hadoop/hbase/regionserver/StoreScanner
     355: astore        11
     357: aload         11
     359: getfield      #488                // Field org/apache/hadoop/hbase/regionserver/StoreScanner.heap:Lorg/apache/hadoop/hbase/regionserver/KeyValueHeap;
     362: astore        12
     364: bipush        31
     366: istore        13
     368: iload         13
     370: bipush        40
     372: if_icmpge     432
     375: aload_2
     376: aload_0
     377: new           #67                 // class java/lang/StringBuilder
     380: dup
     381: invokespecial #68                 // Method java/lang/StringBuilder."<init>":()V
     384: ldc           #15                 // String row
     386: invokevirtual #70                 // Method java/lang/StringBuilder.append:(Ljava/lang/String;)Ljava/lang/StringBuilder;
     389: iload         13
     391: invokevirtual #158                // Method java/lang/StringBuilder.append:(I)Ljava/lang/StringBuilder;
     394: invokevirtual #71                 // Method java/lang/StringBuilder.toString:()Ljava/lang/String;
     397: invokestatic  #11                 // Method org/apache/hadoop/hbase/util/Bytes.toBytes:(Ljava/lang/String;)[B
     400: aload_0
     401: getfield      #20                 // Field qf1:[B
     404: lload         4
     406: lload         6
     408: dup2
     409: lconst_1
     410: ladd
     411: lstore        6
     413: ldc_w         #480                // String
     416: invokestatic  #11                 // Method org/apache/hadoop/hbase/util/Bytes.toBytes:(Ljava/lang/String;)[B
     419: invokespecial #364                // Method createCell:([B[BJJ[B)Lorg/apache/hadoop/hbase/Cell;
     422: aload_3
     423: invokevirtual #425                // Method org/apache/hadoop/hbase/regionserver/TestHStore$MyStore.add:(Lorg/apache/hadoop/hbase/Cell;Lorg/apache/hadoop/hbase/regionserver/MemStoreSizing;)V
     426: iinc          13, 1
     429: goto          368
     432: aload_2
     433: lload         6
     435: invokestatic  #3                  // Method flushStore:(Lorg/apache/hadoop/hbase/regionserver/HStore;J)V
     438: bipush        41
     440: istore        13
     442: iload         13
     444: bipush        50
     446: if_icmpge     506
     449: aload_2
     450: aload_0
     451: new           #67                 // class java/lang/StringBuilder
     454: dup
     455: invokespecial #68                 // Method java/lang/StringBuilder."<init>":()V
     458: ldc           #15                 // String row
     460: invokevirtual #70                 // Method java/lang/StringBuilder.append:(Ljava/lang/String;)Ljava/lang/StringBuilder;
     463: iload         13
     465: invokevirtual #158                // Method java/lang/StringBuilder.append:(I)Ljava/lang/StringBuilder;
     468: invokevirtual #71                 // Method java/lang/StringBuilder.toString:()Ljava/lang/String;
     471: invokestatic  #11                 // Method org/apache/hadoop/hbase/util/Bytes.toBytes:(Ljava/lang/String;)[B
     474: aload_0
     475: getfield      #20                 // Field qf1:[B
     478: lload         4
     480: lload         6
     482: dup2
     483: lconst_1
     484: ladd
     485: lstore        6
     487: ldc_w         #480                // String
     490: invokestatic  #11                 // Method org/apache/hadoop/hbase/util/Bytes.toBytes:(Ljava/lang/String;)[B
     493: invokespecial #364                // Method createCell:([B[BJJ[B)Lorg/apache/hadoop/hbase/Cell;
     496: aload_3
     497: invokevirtual #425                // Method org/apache/hadoop/hbase/regionserver/TestHStore$MyStore.add:(Lorg/apache/hadoop/hbase/Cell;Lorg/apache/hadoop/hbase/regionserver/MemStoreSizing;)V
     500: iinc          13, 1
     503: goto          442
     506: aload_2
     507: lload         6
     509: invokestatic  #3                  // Method flushStore:(Lorg/apache/hadoop/hbase/regionserver/HStore;J)V
     512: aload_2
     513: invokevirtual #483                // Method org/apache/hadoop/hbase/regionserver/TestHStore$MyStore.getStorefiles:()Ljava/util/Collection;
     516: astore        9
     518: aload         9
     520: invokestatic  #484                // Method org/apache/hbase/thirdparty/com/google/common/collect/Lists.newArrayList:(Ljava/lang/Iterable;)Ljava/util/ArrayList;
     523: astore        13
     525: aload         13
     527: aload         10
     529: invokevirtual #489                // Method java/util/ArrayList.removeAll:(Ljava/util/Collection;)Z
     532: pop
     533: new           #490                // class org/apache/hadoop/hbase/regionserver/TestHStore$MyThread
     536: dup
     537: aload         11
     539: invokespecial #491                // Method org/apache/hadoop/hbase/regionserver/TestHStore$MyThread."<init>":(Lorg/apache/hadoop/hbase/regionserver/StoreScanner;)V
     542: astore        14
     544: aload         14
     546: invokevirtual #492                // Method org/apache/hadoop/hbase/regionserver/TestHStore$MyThread.start:()V
     549: aload_2
     550: aload         10
     552: aload         13
     554: invokevirtual #493                // Method org/apache/hadoop/hbase/regionserver/TestHStore$MyStore.replaceStoreFiles:(Ljava/util/Collection;Ljava/util/Collection;)V
     557: aload         14
     559: invokevirtual #494                // Method org/apache/hadoop/hbase/regionserver/TestHStore$MyThread.join:()V
     562: aload         14
     564: invokevirtual #495                // Method org/apache/hadoop/hbase/regionserver/TestHStore$MyThread.getHeap:()Lorg/apache/hadoop/hbase/regionserver/KeyValueHeap;
     567: astore        15
     569: aload         12
     571: aload         15
     573: invokevirtual #496                // Method java/lang/Object.equals:(Ljava/lang/Object;)Z
     576: invokestatic  #172                // Method org/junit/Assert.assertFalse:(Z)V
     579: return

  public void testSpaceQuotaChangeAfterReplacement() throws java.io.IOException;
    Code:
       0: aload_0
       1: getfield      #9                  // Field name:Lorg/junit/rules/TestName;
       4: invokevirtual #112                // Method org/junit/rules/TestName.getMethodName:()Ljava/lang/String;
       7: invokestatic  #497                // Method org/apache/hadoop/hbase/TableName.valueOf:(Ljava/lang/String;)Lorg/apache/hadoop/hbase/TableName;
      10: astore_1
      11: aload_0
      12: aload_0
      13: getfield      #9                  // Field name:Lorg/junit/rules/TestName;
      16: invokevirtual #112                // Method org/junit/rules/TestName.getMethodName:()Ljava/lang/String;
      19: invokespecial #194                // Method init:(Ljava/lang/String;)V
      22: new           #498                // class org/apache/hadoop/hbase/quotas/RegionSizeStoreImpl
      25: dup
      26: invokespecial #499                // Method org/apache/hadoop/hbase/quotas/RegionSizeStoreImpl."<init>":()V
      29: astore_2
      30: aload_0
      31: ldc2_w        #500                // long 1024l
      34: invokespecial #502                // Method mockStoreFileWithLength:(J)Lorg/apache/hadoop/hbase/regionserver/HStoreFile;
      37: astore_3
      38: aload_0
      39: ldc2_w        #503                // long 2048l
      42: invokespecial #502                // Method mockStoreFileWithLength:(J)Lorg/apache/hadoop/hbase/regionserver/HStoreFile;
      45: astore        4
      47: aload_0
      48: ldc2_w        #505                // long 4096l
      51: invokespecial #502                // Method mockStoreFileWithLength:(J)Lorg/apache/hadoop/hbase/regionserver/HStoreFile;
      54: astore        5
      56: aload_0
      57: ldc2_w        #507                // long 8192l
      60: invokespecial #502                // Method mockStoreFileWithLength:(J)Lorg/apache/hadoop/hbase/regionserver/HStoreFile;
      63: astore        6
      65: aload_1
      66: invokestatic  #84                 // Method org/apache/hadoop/hbase/client/RegionInfoBuilder.newBuilder:(Lorg/apache/hadoop/hbase/TableName;)Lorg/apache/hadoop/hbase/client/RegionInfoBuilder;
      69: ldc_w         #509                // String a
      72: invokestatic  #11                 // Method org/apache/hadoop/hbase/util/Bytes.toBytes:(Ljava/lang/String;)[B
      75: invokevirtual #510                // Method org/apache/hadoop/hbase/client/RegionInfoBuilder.setStartKey:([B)Lorg/apache/hadoop/hbase/client/RegionInfoBuilder;
      78: ldc_w         #511                // String b
      81: invokestatic  #11                 // Method org/apache/hadoop/hbase/util/Bytes.toBytes:(Ljava/lang/String;)[B
      84: invokevirtual #512                // Method org/apache/hadoop/hbase/client/RegionInfoBuilder.setEndKey:([B)Lorg/apache/hadoop/hbase/client/RegionInfoBuilder;
      87: invokevirtual #85                 // Method org/apache/hadoop/hbase/client/RegionInfoBuilder.build:()Lorg/apache/hadoop/hbase/client/RegionInfo;
      90: astore        7
      92: aload_2
      93: aload         7
      95: ldc2_w        #513                // long 5120l
      98: invokevirtual #515                // Method org/apache/hadoop/hbase/quotas/RegionSizeStoreImpl.put:(Lorg/apache/hadoop/hbase/client/RegionInfo;J)V
     101: aload_0
     102: getfield      #108                // Field store:Lorg/apache/hadoop/hbase/regionserver/HStore;
     105: aload_2
     106: aload         7
     108: iconst_2
     109: anewarray     #174                // class org/apache/hadoop/hbase/regionserver/HStoreFile
     112: dup
     113: iconst_0
     114: aload_3
     115: aastore
     116: dup
     117: iconst_1
     118: aload         5
     120: aastore
     121: invokestatic  #335                // Method java/util/Arrays.asList:([Ljava/lang/Object;)Ljava/util/List;
     124: iconst_1
     125: anewarray     #174                // class org/apache/hadoop/hbase/regionserver/HStoreFile
     128: dup
     129: iconst_0
     130: aload         4
     132: aastore
     133: invokestatic  #335                // Method java/util/Arrays.asList:([Ljava/lang/Object;)Ljava/util/List;
     136: invokevirtual #516                // Method org/apache/hadoop/hbase/regionserver/HStore.updateSpaceQuotaAfterFileReplacement:(Lorg/apache/hadoop/hbase/quotas/RegionSizeStore;Lorg/apache/hadoop/hbase/client/RegionInfo;Ljava/util/Collection;Ljava/util/Collection;)V
     139: ldc2_w        #503                // long 2048l
     142: aload_2
     143: aload         7
     145: invokevirtual #517                // Method org/apache/hadoop/hbase/quotas/RegionSizeStoreImpl.getRegionSize:(Lorg/apache/hadoop/hbase/client/RegionInfo;)Lorg/apache/hadoop/hbase/quotas/RegionSize;
     148: invokeinterface #518,  1          // InterfaceMethod org/apache/hadoop/hbase/quotas/RegionSize.getSize:()J
     153: invokestatic  #169                // Method org/junit/Assert.assertEquals:(JJ)V
     156: aload_0
     157: getfield      #108                // Field store:Lorg/apache/hadoop/hbase/regionserver/HStore;
     160: aload_2
     161: aload         7
     163: iconst_1
     164: anewarray     #174                // class org/apache/hadoop/hbase/regionserver/HStoreFile
     167: dup
     168: iconst_0
     169: aload         4
     171: aastore
     172: invokestatic  #335                // Method java/util/Arrays.asList:([Ljava/lang/Object;)Ljava/util/List;
     175: iconst_1
     176: anewarray     #174                // class org/apache/hadoop/hbase/regionserver/HStoreFile
     179: dup
     180: iconst_0
     181: aload         4
     183: aastore
     184: invokestatic  #335                // Method java/util/Arrays.asList:([Ljava/lang/Object;)Ljava/util/List;
     187: invokevirtual #516                // Method org/apache/hadoop/hbase/regionserver/HStore.updateSpaceQuotaAfterFileReplacement:(Lorg/apache/hadoop/hbase/quotas/RegionSizeStore;Lorg/apache/hadoop/hbase/client/RegionInfo;Ljava/util/Collection;Ljava/util/Collection;)V
     190: ldc2_w        #503                // long 2048l
     193: aload_2
     194: aload         7
     196: invokevirtual #517                // Method org/apache/hadoop/hbase/quotas/RegionSizeStoreImpl.getRegionSize:(Lorg/apache/hadoop/hbase/client/RegionInfo;)Lorg/apache/hadoop/hbase/quotas/RegionSize;
     199: invokeinterface #518,  1          // InterfaceMethod org/apache/hadoop/hbase/quotas/RegionSize.getSize:()J
     204: invokestatic  #169                // Method org/junit/Assert.assertEquals:(JJ)V
     207: aload_0
     208: getfield      #108                // Field store:Lorg/apache/hadoop/hbase/regionserver/HStore;
     211: aload_2
     212: aload         7
     214: iconst_1
     215: anewarray     #174                // class org/apache/hadoop/hbase/regionserver/HStoreFile
     218: dup
     219: iconst_0
     220: aload         4
     222: aastore
     223: invokestatic  #335                // Method java/util/Arrays.asList:([Ljava/lang/Object;)Ljava/util/List;
     226: iconst_1
     227: anewarray     #174                // class org/apache/hadoop/hbase/regionserver/HStoreFile
     230: dup
     231: iconst_0
     232: aload         5
     234: aastore
     235: invokestatic  #335                // Method java/util/Arrays.asList:([Ljava/lang/Object;)Ljava/util/List;
     238: invokevirtual #516                // Method org/apache/hadoop/hbase/regionserver/HStore.updateSpaceQuotaAfterFileReplacement:(Lorg/apache/hadoop/hbase/quotas/RegionSizeStore;Lorg/apache/hadoop/hbase/client/RegionInfo;Ljava/util/Collection;Ljava/util/Collection;)V
     241: ldc2_w        #505                // long 4096l
     244: aload_2
     245: aload         7
     247: invokevirtual #517                // Method org/apache/hadoop/hbase/quotas/RegionSizeStoreImpl.getRegionSize:(Lorg/apache/hadoop/hbase/client/RegionInfo;)Lorg/apache/hadoop/hbase/quotas/RegionSize;
     250: invokeinterface #518,  1          // InterfaceMethod org/apache/hadoop/hbase/quotas/RegionSize.getSize:()J
     255: invokestatic  #169                // Method org/junit/Assert.assertEquals:(JJ)V
     258: aload_1
     259: invokestatic  #84                 // Method org/apache/hadoop/hbase/client/RegionInfoBuilder.newBuilder:(Lorg/apache/hadoop/hbase/TableName;)Lorg/apache/hadoop/hbase/client/RegionInfoBuilder;
     262: ldc_w         #511                // String b
     265: invokestatic  #11                 // Method org/apache/hadoop/hbase/util/Bytes.toBytes:(Ljava/lang/String;)[B
     268: invokevirtual #510                // Method org/apache/hadoop/hbase/client/RegionInfoBuilder.setStartKey:([B)Lorg/apache/hadoop/hbase/client/RegionInfoBuilder;
     271: ldc_w         #519                // String c
     274: invokestatic  #11                 // Method org/apache/hadoop/hbase/util/Bytes.toBytes:(Ljava/lang/String;)[B
     277: invokevirtual #512                // Method org/apache/hadoop/hbase/client/RegionInfoBuilder.setEndKey:([B)Lorg/apache/hadoop/hbase/client/RegionInfoBuilder;
     280: invokevirtual #85                 // Method org/apache/hadoop/hbase/client/RegionInfoBuilder.build:()Lorg/apache/hadoop/hbase/client/RegionInfo;
     283: astore        8
     285: aload_0
     286: getfield      #108                // Field store:Lorg/apache/hadoop/hbase/regionserver/HStore;
     289: aload_2
     290: aload         8
     292: aconst_null
     293: iconst_1
     294: anewarray     #174                // class org/apache/hadoop/hbase/regionserver/HStoreFile
     297: dup
     298: iconst_0
     299: aload         6
     301: aastore
     302: invokestatic  #335                // Method java/util/Arrays.asList:([Ljava/lang/Object;)Ljava/util/List;
     305: invokevirtual #516                // Method org/apache/hadoop/hbase/regionserver/HStore.updateSpaceQuotaAfterFileReplacement:(Lorg/apache/hadoop/hbase/quotas/RegionSizeStore;Lorg/apache/hadoop/hbase/client/RegionInfo;Ljava/util/Collection;Ljava/util/Collection;)V
     308: ldc2_w        #507                // long 8192l
     311: aload_2
     312: aload         8
     314: invokevirtual #517                // Method org/apache/hadoop/hbase/quotas/RegionSizeStoreImpl.getRegionSize:(Lorg/apache/hadoop/hbase/client/RegionInfo;)Lorg/apache/hadoop/hbase/quotas/RegionSize;
     317: invokeinterface #518,  1          // InterfaceMethod org/apache/hadoop/hbase/quotas/RegionSize.getSize:()J
     322: invokestatic  #169                // Method org/junit/Assert.assertEquals:(JJ)V
     325: return

  static org.apache.hadoop.hbase.regionserver.HStore access$000(org.apache.hadoop.hbase.regionserver.TestHStore, java.lang.String, org.apache.hadoop.conf.Configuration) throws java.io.IOException;
    Code:
       0: aload_0
       1: aload_1
       2: aload_2
       3: invokespecial #5                  // Method init:(Ljava/lang/String;Lorg/apache/hadoop/conf/Configuration;)Lorg/apache/hadoop/hbase/regionserver/HStore;
       6: areturn

  static org.slf4j.Logger access$100();
    Code:
       0: getstatic     #4                  // Field LOG:Lorg/slf4j/Logger;
       3: areturn

  static void access$200(org.apache.hadoop.hbase.regionserver.HStore, long) throws java.io.IOException;
    Code:
       0: aload_0
       1: lload_1
       2: invokestatic  #3                  // Method flushStore:(Lorg/apache/hadoop/hbase/regionserver/HStore;J)V
       5: return

  static void access$300(org.apache.hadoop.hbase.regionserver.TestHStore, int) throws java.io.IOException;
    Code:
       0: aload_0
       1: iload_1
       2: invokespecial #2                  // Method flush:(I)V
       5: return

  static org.apache.hadoop.hbase.regionserver.HStoreFile access$800(org.apache.hadoop.hbase.regionserver.TestHStore, long);
    Code:
       0: aload_0
       1: lload_1
       2: invokespecial #1                  // Method mockStoreFile:(J)Lorg/apache/hadoop/hbase/regionserver/HStoreFile;
       5: areturn

  static {};
    Code:
       0: ldc           #199                // class org/apache/hadoop/hbase/regionserver/TestHStore
       2: invokestatic  #525                // Method org/apache/hadoop/hbase/HBaseClassTestRule.forClass:(Ljava/lang/Class;)Lorg/apache/hadoop/hbase/HBaseClassTestRule;
       5: putstatic     #526                // Field CLASS_RULE:Lorg/apache/hadoop/hbase/HBaseClassTestRule;
       8: ldc           #199                // class org/apache/hadoop/hbase/regionserver/TestHStore
      10: invokestatic  #527                // Method org/slf4j/LoggerFactory.getLogger:(Ljava/lang/Class;)Lorg/slf4j/Logger;
      13: putstatic     #4                  // Field LOG:Lorg/slf4j/Logger;
      16: new           #528                // class org/apache/hadoop/hbase/HBaseTestingUtility
      19: dup
      20: invokespecial #529                // Method org/apache/hadoop/hbase/HBaseTestingUtility."<init>":()V
      23: putstatic     #53                 // Field TEST_UTIL:Lorg/apache/hadoop/hbase/HBaseTestingUtility;
      26: getstatic     #53                 // Field TEST_UTIL:Lorg/apache/hadoop/hbase/HBaseTestingUtility;
      29: ldc_w         #530                // String TestStore
      32: invokevirtual #531                // Method org/apache/hadoop/hbase/HBaseTestingUtility.getDataTestDir:(Ljava/lang/String;)Lorg/apache/hadoop/fs/Path;
      35: invokevirtual #532                // Method org/apache/hadoop/fs/Path.toString:()Ljava/lang/String;
      38: putstatic     #69                 // Field DIR:Ljava/lang/String;
      41: return
}
