Compiled from "TestCommonFSUtils.java"
public class org.apache.hadoop.hbase.util.TestCommonFSUtils {
  public static final org.apache.hadoop.hbase.HBaseClassTestRule CLASS_RULE;

  public org.apache.hadoop.hbase.util.TestCommonFSUtils();
    Code:
       0: aload_0
       1: invokespecial #1                  // Method java/lang/Object."<init>":()V
       4: return

  public void setUp() throws java.io.IOException;
    Code:
       0: aload_0
       1: new           #2                  // class org/apache/hadoop/hbase/HBaseCommonTestingUtility
       4: dup
       5: invokespecial #3                  // Method org/apache/hadoop/hbase/HBaseCommonTestingUtility."<init>":()V
       8: putfield      #4                  // Field htu:Lorg/apache/hadoop/hbase/HBaseCommonTestingUtility;
      11: aload_0
      12: aload_0
      13: getfield      #4                  // Field htu:Lorg/apache/hadoop/hbase/HBaseCommonTestingUtility;
      16: invokevirtual #5                  // Method org/apache/hadoop/hbase/HBaseCommonTestingUtility.getConfiguration:()Lorg/apache/hadoop/conf/Configuration;
      19: putfield      #6                  // Field conf:Lorg/apache/hadoop/conf/Configuration;
      22: return

  public void testMatchingTail() throws java.io.IOException;
    Code:
       0: aload_0
       1: getfield      #4                  // Field htu:Lorg/apache/hadoop/hbase/HBaseCommonTestingUtility;
       4: invokevirtual #7                  // Method org/apache/hadoop/hbase/HBaseCommonTestingUtility.getDataTestDir:()Lorg/apache/hadoop/fs/Path;
       7: astore_1
       8: aload_1
       9: aload_0
      10: getfield      #6                  // Field conf:Lorg/apache/hadoop/conf/Configuration;
      13: invokevirtual #8                  // Method org/apache/hadoop/fs/Path.getFileSystem:(Lorg/apache/hadoop/conf/Configuration;)Lorg/apache/hadoop/fs/FileSystem;
      16: astore_2
      17: aload_1
      18: invokevirtual #9                  // Method org/apache/hadoop/fs/Path.depth:()I
      21: iconst_1
      22: if_icmple     29
      25: iconst_1
      26: goto          30
      29: iconst_0
      30: invokestatic  #10                 // Method org/junit/Assert.assertTrue:(Z)V
      33: new           #11                 // class org/apache/hadoop/fs/Path
      36: dup
      37: ldc           #12                 // String a
      39: ldc           #13                 // String b
      41: invokespecial #14                 // Method org/apache/hadoop/fs/Path."<init>":(Ljava/lang/String;Ljava/lang/String;)V
      44: astore_3
      45: new           #11                 // class org/apache/hadoop/fs/Path
      48: dup
      49: aload_1
      50: aload_3
      51: invokespecial #15                 // Method org/apache/hadoop/fs/Path."<init>":(Lorg/apache/hadoop/fs/Path;Lorg/apache/hadoop/fs/Path;)V
      54: astore        4
      56: aload_2
      57: aload         4
      59: invokevirtual #16                 // Method org/apache/hadoop/fs/FileSystem.makeQualified:(Lorg/apache/hadoop/fs/Path;)Lorg/apache/hadoop/fs/Path;
      62: astore        5
      64: aload         4
      66: aload_3
      67: invokestatic  #17                 // Method org/apache/hadoop/hbase/util/CommonFSUtils.isMatchingTail:(Lorg/apache/hadoop/fs/Path;Lorg/apache/hadoop/fs/Path;)Z
      70: invokestatic  #18                 // Method org/junit/Assert.assertFalse:(Z)V
      73: aload         4
      75: aload_3
      76: invokevirtual #19                 // Method org/apache/hadoop/fs/Path.toString:()Ljava/lang/String;
      79: invokestatic  #20                 // Method org/apache/hadoop/hbase/util/CommonFSUtils.isMatchingTail:(Lorg/apache/hadoop/fs/Path;Ljava/lang/String;)Z
      82: invokestatic  #18                 // Method org/junit/Assert.assertFalse:(Z)V
      85: aload_1
      86: aload         4
      88: invokevirtual #19                 // Method org/apache/hadoop/fs/Path.toString:()Ljava/lang/String;
      91: invokestatic  #21                 // Method org/apache/hadoop/hbase/util/CommonFSUtils.isStartingWithPath:(Lorg/apache/hadoop/fs/Path;Ljava/lang/String;)Z
      94: invokestatic  #10                 // Method org/junit/Assert.assertTrue:(Z)V
      97: aload         5
      99: aload         4
     101: invokevirtual #19                 // Method org/apache/hadoop/fs/Path.toString:()Ljava/lang/String;
     104: invokestatic  #21                 // Method org/apache/hadoop/hbase/util/CommonFSUtils.isStartingWithPath:(Lorg/apache/hadoop/fs/Path;Ljava/lang/String;)Z
     107: invokestatic  #10                 // Method org/junit/Assert.assertTrue:(Z)V
     110: aload_1
     111: aload_3
     112: invokevirtual #19                 // Method org/apache/hadoop/fs/Path.toString:()Ljava/lang/String;
     115: invokestatic  #21                 // Method org/apache/hadoop/hbase/util/CommonFSUtils.isStartingWithPath:(Lorg/apache/hadoop/fs/Path;Ljava/lang/String;)Z
     118: invokestatic  #18                 // Method org/junit/Assert.assertFalse:(Z)V
     121: aload         5
     123: aload_3
     124: invokestatic  #17                 // Method org/apache/hadoop/hbase/util/CommonFSUtils.isMatchingTail:(Lorg/apache/hadoop/fs/Path;Lorg/apache/hadoop/fs/Path;)Z
     127: invokestatic  #18                 // Method org/junit/Assert.assertFalse:(Z)V
     130: aload         5
     132: aload         4
     134: invokestatic  #17                 // Method org/apache/hadoop/hbase/util/CommonFSUtils.isMatchingTail:(Lorg/apache/hadoop/fs/Path;Lorg/apache/hadoop/fs/Path;)Z
     137: invokestatic  #10                 // Method org/junit/Assert.assertTrue:(Z)V
     140: aload         5
     142: aload         4
     144: invokevirtual #19                 // Method org/apache/hadoop/fs/Path.toString:()Ljava/lang/String;
     147: invokestatic  #20                 // Method org/apache/hadoop/hbase/util/CommonFSUtils.isMatchingTail:(Lorg/apache/hadoop/fs/Path;Ljava/lang/String;)Z
     150: invokestatic  #10                 // Method org/junit/Assert.assertTrue:(Z)V
     153: aload         5
     155: aload_2
     156: aload         4
     158: invokevirtual #16                 // Method org/apache/hadoop/fs/FileSystem.makeQualified:(Lorg/apache/hadoop/fs/Path;)Lorg/apache/hadoop/fs/Path;
     161: invokestatic  #17                 // Method org/apache/hadoop/hbase/util/CommonFSUtils.isMatchingTail:(Lorg/apache/hadoop/fs/Path;Lorg/apache/hadoop/fs/Path;)Z
     164: invokestatic  #10                 // Method org/junit/Assert.assertTrue:(Z)V
     167: aload_1
     168: aload         5
     170: invokevirtual #19                 // Method org/apache/hadoop/fs/Path.toString:()Ljava/lang/String;
     173: invokestatic  #21                 // Method org/apache/hadoop/hbase/util/CommonFSUtils.isStartingWithPath:(Lorg/apache/hadoop/fs/Path;Ljava/lang/String;)Z
     176: invokestatic  #10                 // Method org/junit/Assert.assertTrue:(Z)V
     179: aload         4
     181: new           #11                 // class org/apache/hadoop/fs/Path
     184: dup
     185: ldc           #22                 // String x
     187: invokespecial #23                 // Method org/apache/hadoop/fs/Path."<init>":(Ljava/lang/String;)V
     190: invokestatic  #17                 // Method org/apache/hadoop/hbase/util/CommonFSUtils.isMatchingTail:(Lorg/apache/hadoop/fs/Path;Lorg/apache/hadoop/fs/Path;)Z
     193: invokestatic  #18                 // Method org/junit/Assert.assertFalse:(Z)V
     196: new           #11                 // class org/apache/hadoop/fs/Path
     199: dup
     200: ldc           #22                 // String x
     202: invokespecial #23                 // Method org/apache/hadoop/fs/Path."<init>":(Ljava/lang/String;)V
     205: aload         4
     207: invokestatic  #17                 // Method org/apache/hadoop/hbase/util/CommonFSUtils.isMatchingTail:(Lorg/apache/hadoop/fs/Path;Lorg/apache/hadoop/fs/Path;)Z
     210: invokestatic  #18                 // Method org/junit/Assert.assertFalse:(Z)V
     213: return

  public void testSetWALRootDir() throws java.lang.Exception;
    Code:
       0: new           #11                 // class org/apache/hadoop/fs/Path
       3: dup
       4: ldc           #27                 // String file:///hbase/root
       6: invokespecial #23                 // Method org/apache/hadoop/fs/Path."<init>":(Ljava/lang/String;)V
       9: astore_1
      10: aload_0
      11: getfield      #6                  // Field conf:Lorg/apache/hadoop/conf/Configuration;
      14: aload_1
      15: invokestatic  #28                 // Method org/apache/hadoop/hbase/util/CommonFSUtils.setWALRootDir:(Lorg/apache/hadoop/conf/Configuration;Lorg/apache/hadoop/fs/Path;)V
      18: aload_1
      19: invokevirtual #19                 // Method org/apache/hadoop/fs/Path.toString:()Ljava/lang/String;
      22: aload_0
      23: getfield      #6                  // Field conf:Lorg/apache/hadoop/conf/Configuration;
      26: ldc           #30                 // String hbase.wal.dir
      28: invokevirtual #31                 // Method org/apache/hadoop/conf/Configuration.get:(Ljava/lang/String;)Ljava/lang/String;
      31: invokestatic  #32                 // Method org/junit/Assert.assertEquals:(Ljava/lang/Object;Ljava/lang/Object;)V
      34: return

  public void testGetWALRootDir() throws java.io.IOException;
    Code:
       0: new           #11                 // class org/apache/hadoop/fs/Path
       3: dup
       4: ldc           #27                 // String file:///hbase/root
       6: invokespecial #23                 // Method org/apache/hadoop/fs/Path."<init>":(Ljava/lang/String;)V
       9: astore_1
      10: new           #11                 // class org/apache/hadoop/fs/Path
      13: dup
      14: ldc           #33                 // String file:///hbase/logroot
      16: invokespecial #23                 // Method org/apache/hadoop/fs/Path."<init>":(Ljava/lang/String;)V
      19: astore_2
      20: aload_0
      21: getfield      #6                  // Field conf:Lorg/apache/hadoop/conf/Configuration;
      24: aload_1
      25: invokestatic  #34                 // Method org/apache/hadoop/hbase/util/CommonFSUtils.setRootDir:(Lorg/apache/hadoop/conf/Configuration;Lorg/apache/hadoop/fs/Path;)V
      28: aload_1
      29: aload_0
      30: getfield      #6                  // Field conf:Lorg/apache/hadoop/conf/Configuration;
      33: invokestatic  #35                 // Method org/apache/hadoop/hbase/util/CommonFSUtils.getRootDir:(Lorg/apache/hadoop/conf/Configuration;)Lorg/apache/hadoop/fs/Path;
      36: invokestatic  #32                 // Method org/junit/Assert.assertEquals:(Ljava/lang/Object;Ljava/lang/Object;)V
      39: aload_1
      40: aload_0
      41: getfield      #6                  // Field conf:Lorg/apache/hadoop/conf/Configuration;
      44: invokestatic  #36                 // Method org/apache/hadoop/hbase/util/CommonFSUtils.getWALRootDir:(Lorg/apache/hadoop/conf/Configuration;)Lorg/apache/hadoop/fs/Path;
      47: invokestatic  #32                 // Method org/junit/Assert.assertEquals:(Ljava/lang/Object;Ljava/lang/Object;)V
      50: aload_0
      51: getfield      #6                  // Field conf:Lorg/apache/hadoop/conf/Configuration;
      54: aload_2
      55: invokestatic  #28                 // Method org/apache/hadoop/hbase/util/CommonFSUtils.setWALRootDir:(Lorg/apache/hadoop/conf/Configuration;Lorg/apache/hadoop/fs/Path;)V
      58: aload_2
      59: aload_0
      60: getfield      #6                  // Field conf:Lorg/apache/hadoop/conf/Configuration;
      63: invokestatic  #36                 // Method org/apache/hadoop/hbase/util/CommonFSUtils.getWALRootDir:(Lorg/apache/hadoop/conf/Configuration;)Lorg/apache/hadoop/fs/Path;
      66: invokestatic  #32                 // Method org/junit/Assert.assertEquals:(Ljava/lang/Object;Ljava/lang/Object;)V
      69: return

  public void testGetWALRootDirIllegalWALDir() throws java.io.IOException;
    Code:
       0: new           #11                 // class org/apache/hadoop/fs/Path
       3: dup
       4: ldc           #27                 // String file:///hbase/root
       6: invokespecial #23                 // Method org/apache/hadoop/fs/Path."<init>":(Ljava/lang/String;)V
       9: astore_1
      10: new           #11                 // class org/apache/hadoop/fs/Path
      13: dup
      14: ldc           #37                 // String file:///hbase/root/logroot
      16: invokespecial #23                 // Method org/apache/hadoop/fs/Path."<init>":(Ljava/lang/String;)V
      19: astore_2
      20: aload_0
      21: getfield      #6                  // Field conf:Lorg/apache/hadoop/conf/Configuration;
      24: aload_1
      25: invokestatic  #34                 // Method org/apache/hadoop/hbase/util/CommonFSUtils.setRootDir:(Lorg/apache/hadoop/conf/Configuration;Lorg/apache/hadoop/fs/Path;)V
      28: aload_0
      29: getfield      #6                  // Field conf:Lorg/apache/hadoop/conf/Configuration;
      32: aload_2
      33: invokestatic  #28                 // Method org/apache/hadoop/hbase/util/CommonFSUtils.setWALRootDir:(Lorg/apache/hadoop/conf/Configuration;Lorg/apache/hadoop/fs/Path;)V
      36: aload_0
      37: getfield      #6                  // Field conf:Lorg/apache/hadoop/conf/Configuration;
      40: invokestatic  #36                 // Method org/apache/hadoop/hbase/util/CommonFSUtils.getWALRootDir:(Lorg/apache/hadoop/conf/Configuration;)Lorg/apache/hadoop/fs/Path;
      43: pop
      44: return

  public void testRemoveWALRootPath() throws java.lang.Exception;
    Code:
       0: aload_0
       1: getfield      #6                  // Field conf:Lorg/apache/hadoop/conf/Configuration;
       4: new           #11                 // class org/apache/hadoop/fs/Path
       7: dup
       8: ldc           #38                 // String file:///user/hbase
      10: invokespecial #23                 // Method org/apache/hadoop/fs/Path."<init>":(Ljava/lang/String;)V
      13: invokestatic  #34                 // Method org/apache/hadoop/hbase/util/CommonFSUtils.setRootDir:(Lorg/apache/hadoop/conf/Configuration;Lorg/apache/hadoop/fs/Path;)V
      16: new           #11                 // class org/apache/hadoop/fs/Path
      19: dup
      20: aload_0
      21: getfield      #6                  // Field conf:Lorg/apache/hadoop/conf/Configuration;
      24: invokestatic  #35                 // Method org/apache/hadoop/hbase/util/CommonFSUtils.getRootDir:(Lorg/apache/hadoop/conf/Configuration;)Lorg/apache/hadoop/fs/Path;
      27: ldc           #39                 // String test/testfile
      29: invokespecial #40                 // Method org/apache/hadoop/fs/Path."<init>":(Lorg/apache/hadoop/fs/Path;Ljava/lang/String;)V
      32: astore_1
      33: new           #11                 // class org/apache/hadoop/fs/Path
      36: dup
      37: ldc           #41                 // String file:///test/testfile
      39: invokespecial #23                 // Method org/apache/hadoop/fs/Path."<init>":(Ljava/lang/String;)V
      42: astore_2
      43: ldc           #39                 // String test/testfile
      45: aload_1
      46: aload_0
      47: getfield      #6                  // Field conf:Lorg/apache/hadoop/conf/Configuration;
      50: invokestatic  #42                 // Method org/apache/hadoop/hbase/util/CommonFSUtils.removeWALRootPath:(Lorg/apache/hadoop/fs/Path;Lorg/apache/hadoop/conf/Configuration;)Ljava/lang/String;
      53: invokestatic  #32                 // Method org/junit/Assert.assertEquals:(Ljava/lang/Object;Ljava/lang/Object;)V
      56: aload_2
      57: invokevirtual #19                 // Method org/apache/hadoop/fs/Path.toString:()Ljava/lang/String;
      60: aload_2
      61: aload_0
      62: getfield      #6                  // Field conf:Lorg/apache/hadoop/conf/Configuration;
      65: invokestatic  #42                 // Method org/apache/hadoop/hbase/util/CommonFSUtils.removeWALRootPath:(Lorg/apache/hadoop/fs/Path;Lorg/apache/hadoop/conf/Configuration;)Ljava/lang/String;
      68: invokestatic  #32                 // Method org/junit/Assert.assertEquals:(Ljava/lang/Object;Ljava/lang/Object;)V
      71: aload_0
      72: getfield      #6                  // Field conf:Lorg/apache/hadoop/conf/Configuration;
      75: new           #11                 // class org/apache/hadoop/fs/Path
      78: dup
      79: ldc           #43                 // String file:///user/hbaseLogDir
      81: invokespecial #23                 // Method org/apache/hadoop/fs/Path."<init>":(Ljava/lang/String;)V
      84: invokestatic  #28                 // Method org/apache/hadoop/hbase/util/CommonFSUtils.setWALRootDir:(Lorg/apache/hadoop/conf/Configuration;Lorg/apache/hadoop/fs/Path;)V
      87: aload_1
      88: invokevirtual #19                 // Method org/apache/hadoop/fs/Path.toString:()Ljava/lang/String;
      91: aload_1
      92: aload_0
      93: getfield      #6                  // Field conf:Lorg/apache/hadoop/conf/Configuration;
      96: invokestatic  #42                 // Method org/apache/hadoop/hbase/util/CommonFSUtils.removeWALRootPath:(Lorg/apache/hadoop/fs/Path;Lorg/apache/hadoop/conf/Configuration;)Ljava/lang/String;
      99: invokestatic  #32                 // Method org/junit/Assert.assertEquals:(Ljava/lang/Object;Ljava/lang/Object;)V
     102: new           #11                 // class org/apache/hadoop/fs/Path
     105: dup
     106: aload_0
     107: getfield      #6                  // Field conf:Lorg/apache/hadoop/conf/Configuration;
     110: invokestatic  #36                 // Method org/apache/hadoop/hbase/util/CommonFSUtils.getWALRootDir:(Lorg/apache/hadoop/conf/Configuration;)Lorg/apache/hadoop/fs/Path;
     113: ldc           #44                 // String test/testlog
     115: invokespecial #40                 // Method org/apache/hadoop/fs/Path."<init>":(Lorg/apache/hadoop/fs/Path;Ljava/lang/String;)V
     118: astore_3
     119: ldc           #44                 // String test/testlog
     121: aload_3
     122: aload_0
     123: getfield      #6                  // Field conf:Lorg/apache/hadoop/conf/Configuration;
     126: invokestatic  #42                 // Method org/apache/hadoop/hbase/util/CommonFSUtils.removeWALRootPath:(Lorg/apache/hadoop/fs/Path;Lorg/apache/hadoop/conf/Configuration;)Ljava/lang/String;
     129: invokestatic  #32                 // Method org/junit/Assert.assertEquals:(Ljava/lang/Object;Ljava/lang/Object;)V
     132: return

  public void streamCapabilitiesDoesNotAllowNullStream();
    Code:
       0: aconst_null
       1: ldc           #45                 // String hopefully any string
       3: invokestatic  #46                 // Method org/apache/hadoop/hbase/util/CommonFSUtils.hasCapability:(Lorg/apache/hadoop/fs/FSDataOutputStream;Ljava/lang/String;)Z
       6: pop
       7: return

  public void checkStreamCapabilitiesOnKnownNoopStream() throws java.io.IOException;
    Code:
       0: new           #47                 // class org/apache/hadoop/fs/FSDataOutputStream
       3: dup
       4: new           #48                 // class java/io/ByteArrayOutputStream
       7: dup
       8: invokespecial #49                 // Method java/io/ByteArrayOutputStream."<init>":()V
      11: aconst_null
      12: invokespecial #50                 // Method org/apache/hadoop/fs/FSDataOutputStream."<init>":(Ljava/io/OutputStream;Lorg/apache/hadoop/fs/FileSystem$Statistics;)V
      15: astore_1
      16: ldc           #51                 // String We expect our dummy FSDOS to claim capabilities iff the StreamCapabilities class is not defined.
      18: getstatic     #52                 // Field STREAM_CAPABILITIES_IS_PRESENT:Z
      21: invokestatic  #53                 // Method java/lang/Boolean.valueOf:(Z)Ljava/lang/Boolean;
      24: aload_1
      25: ldc           #54                 // String hsync
      27: invokestatic  #46                 // Method org/apache/hadoop/hbase/util/CommonFSUtils.hasCapability:(Lorg/apache/hadoop/fs/FSDataOutputStream;Ljava/lang/String;)Z
      30: invokestatic  #53                 // Method java/lang/Boolean.valueOf:(Z)Ljava/lang/Boolean;
      33: invokestatic  #55                 // Method org/junit/Assert.assertNotEquals:(Ljava/lang/String;Ljava/lang/Object;Ljava/lang/Object;)V
      36: ldc           #51                 // String We expect our dummy FSDOS to claim capabilities iff the StreamCapabilities class is not defined.
      38: getstatic     #52                 // Field STREAM_CAPABILITIES_IS_PRESENT:Z
      41: invokestatic  #53                 // Method java/lang/Boolean.valueOf:(Z)Ljava/lang/Boolean;
      44: aload_1
      45: ldc           #56                 // String hflush
      47: invokestatic  #46                 // Method org/apache/hadoop/hbase/util/CommonFSUtils.hasCapability:(Lorg/apache/hadoop/fs/FSDataOutputStream;Ljava/lang/String;)Z
      50: invokestatic  #53                 // Method java/lang/Boolean.valueOf:(Z)Ljava/lang/Boolean;
      53: invokestatic  #55                 // Method org/junit/Assert.assertNotEquals:(Ljava/lang/String;Ljava/lang/Object;Ljava/lang/Object;)V
      56: ldc           #51                 // String We expect our dummy FSDOS to claim capabilities iff the StreamCapabilities class is not defined.
      58: getstatic     #52                 // Field STREAM_CAPABILITIES_IS_PRESENT:Z
      61: invokestatic  #53                 // Method java/lang/Boolean.valueOf:(Z)Ljava/lang/Boolean;
      64: aload_1
      65: ldc           #57                 // String a capability that hopefully no filesystem will implement.
      67: invokestatic  #46                 // Method org/apache/hadoop/hbase/util/CommonFSUtils.hasCapability:(Lorg/apache/hadoop/fs/FSDataOutputStream;Ljava/lang/String;)Z
      70: invokestatic  #53                 // Method java/lang/Boolean.valueOf:(Z)Ljava/lang/Boolean;
      73: invokestatic  #55                 // Method org/junit/Assert.assertNotEquals:(Ljava/lang/String;Ljava/lang/Object;Ljava/lang/Object;)V
      76: return

  static {};
    Code:
       0: ldc           #58                 // class org/apache/hadoop/hbase/util/TestCommonFSUtils
       2: invokestatic  #59                 // Method org/apache/hadoop/hbase/HBaseClassTestRule.forClass:(Ljava/lang/Class;)Lorg/apache/hadoop/hbase/HBaseClassTestRule;
       5: putstatic     #60                 // Field CLASS_RULE:Lorg/apache/hadoop/hbase/HBaseClassTestRule;
       8: ldc           #58                 // class org/apache/hadoop/hbase/util/TestCommonFSUtils
      10: invokestatic  #61                 // Method org/slf4j/LoggerFactory.getLogger:(Ljava/lang/Class;)Lorg/slf4j/Logger;
      13: putstatic     #62                 // Field LOG:Lorg/slf4j/Logger;
      16: iconst_0
      17: istore_0
      18: ldc           #63                 // String org.apache.hadoop.fs.StreamCapabilities
      20: invokestatic  #64                 // Method java/lang/Class.forName:(Ljava/lang/String;)Ljava/lang/Class;
      23: pop
      24: iconst_1
      25: istore_0
      26: getstatic     #62                 // Field LOG:Lorg/slf4j/Logger;
      29: ldc           #65                 // String Test thought StreamCapabilities class was present.
      31: invokeinterface #66,  2           // InterfaceMethod org/slf4j/Logger.debug:(Ljava/lang/String;)V
      36: iload_0
      37: putstatic     #52                 // Field STREAM_CAPABILITIES_IS_PRESENT:Z
      40: goto          68
      43: astore_1
      44: getstatic     #62                 // Field LOG:Lorg/slf4j/Logger;
      47: ldc           #68                 // String Test didn't think StreamCapabilities class was present.
      49: invokeinterface #66,  2           // InterfaceMethod org/slf4j/Logger.debug:(Ljava/lang/String;)V
      54: iload_0
      55: putstatic     #52                 // Field STREAM_CAPABILITIES_IS_PRESENT:Z
      58: goto          68
      61: astore_2
      62: iload_0
      63: putstatic     #52                 // Field STREAM_CAPABILITIES_IS_PRESENT:Z
      66: aload_2
      67: athrow
      68: return
    Exception table:
       from    to  target type
          18    36    43   Class java/lang/ClassNotFoundException
          18    36    61   any
          43    54    61   any
}
