Compiled from "TestMasterFailoverBalancerPersistence.java"
public class org.apache.hadoop.hbase.master.TestMasterFailoverBalancerPersistence {
  public static final org.apache.hadoop.hbase.HBaseClassTestRule CLASS_RULE;

  public org.apache.hadoop.hbase.master.TestMasterFailoverBalancerPersistence();
    Code:
       0: aload_0
       1: invokespecial #1                  // Method java/lang/Object."<init>":()V
       4: return

  public void testMasterFailoverBalancerPersistence() throws java.lang.Exception;
    Code:
       0: new           #2                  // class org/apache/hadoop/hbase/HBaseTestingUtility
       3: dup
       4: invokespecial #3                  // Method org/apache/hadoop/hbase/HBaseTestingUtility."<init>":()V
       7: astore_1
       8: invokestatic  #4                  // Method org/apache/hadoop/hbase/StartMiniClusterOption.builder:()Lorg/apache/hadoop/hbase/StartMiniClusterOption$Builder;
      11: iconst_3
      12: invokevirtual #5                  // Method org/apache/hadoop/hbase/StartMiniClusterOption$Builder.numMasters:(I)Lorg/apache/hadoop/hbase/StartMiniClusterOption$Builder;
      15: invokevirtual #6                  // Method org/apache/hadoop/hbase/StartMiniClusterOption$Builder.build:()Lorg/apache/hadoop/hbase/StartMiniClusterOption;
      18: astore_2
      19: aload_1
      20: aload_2
      21: invokevirtual #7                  // Method org/apache/hadoop/hbase/HBaseTestingUtility.startMiniCluster:(Lorg/apache/hadoop/hbase/StartMiniClusterOption;)Lorg/apache/hadoop/hbase/MiniHBaseCluster;
      24: pop
      25: aload_1
      26: invokevirtual #8                  // Method org/apache/hadoop/hbase/HBaseTestingUtility.getHBaseCluster:()Lorg/apache/hadoop/hbase/MiniHBaseCluster;
      29: astore_3
      30: aload_3
      31: invokevirtual #9                  // Method org/apache/hadoop/hbase/MiniHBaseCluster.waitForActiveAndReadyMaster:()Z
      34: invokestatic  #10                 // Method org/junit/Assert.assertTrue:(Z)V
      37: aload_3
      38: invokevirtual #11                 // Method org/apache/hadoop/hbase/MiniHBaseCluster.getMaster:()Lorg/apache/hadoop/hbase/master/HMaster;
      41: astore        4
      43: aload         4
      45: invokevirtual #12                 // Method org/apache/hadoop/hbase/master/HMaster.getClusterMetrics:()Lorg/apache/hadoop/hbase/ClusterMetrics;
      48: astore        5
      50: aload         5
      52: invokeinterface #13,  1           // InterfaceMethod org/apache/hadoop/hbase/ClusterMetrics.getBalancerOn:()Ljava/lang/Boolean;
      57: invokevirtual #14                 // Method java/lang/Boolean.booleanValue:()Z
      60: invokestatic  #10                 // Method org/junit/Assert.assertTrue:(Z)V
      63: aload_0
      64: aload_3
      65: invokespecial #15                 // Method killActiveAndWaitForNewActive:(Lorg/apache/hadoop/hbase/MiniHBaseCluster;)Lorg/apache/hadoop/hbase/master/HMaster;
      68: astore        4
      70: aload         4
      72: invokevirtual #12                 // Method org/apache/hadoop/hbase/master/HMaster.getClusterMetrics:()Lorg/apache/hadoop/hbase/ClusterMetrics;
      75: astore        5
      77: aload         5
      79: invokeinterface #13,  1           // InterfaceMethod org/apache/hadoop/hbase/ClusterMetrics.getBalancerOn:()Ljava/lang/Boolean;
      84: invokevirtual #14                 // Method java/lang/Boolean.booleanValue:()Z
      87: invokestatic  #10                 // Method org/junit/Assert.assertTrue:(Z)V
      90: aload         4
      92: iconst_0
      93: invokevirtual #16                 // Method org/apache/hadoop/hbase/master/HMaster.balanceSwitch:(Z)Z
      96: pop
      97: aload_0
      98: aload_3
      99: invokespecial #15                 // Method killActiveAndWaitForNewActive:(Lorg/apache/hadoop/hbase/MiniHBaseCluster;)Lorg/apache/hadoop/hbase/master/HMaster;
     102: astore        4
     104: aload         4
     106: invokevirtual #12                 // Method org/apache/hadoop/hbase/master/HMaster.getClusterMetrics:()Lorg/apache/hadoop/hbase/ClusterMetrics;
     109: astore        5
     111: aload         5
     113: invokeinterface #13,  1           // InterfaceMethod org/apache/hadoop/hbase/ClusterMetrics.getBalancerOn:()Ljava/lang/Boolean;
     118: invokevirtual #14                 // Method java/lang/Boolean.booleanValue:()Z
     121: invokestatic  #17                 // Method org/junit/Assert.assertFalse:(Z)V
     124: aload_1
     125: invokevirtual #18                 // Method org/apache/hadoop/hbase/HBaseTestingUtility.shutdownMiniCluster:()V
     128: return

  static {};
    Code:
       0: ldc           #30                 // class org/apache/hadoop/hbase/master/TestMasterFailoverBalancerPersistence
       2: invokestatic  #31                 // Method org/apache/hadoop/hbase/HBaseClassTestRule.forClass:(Ljava/lang/Class;)Lorg/apache/hadoop/hbase/HBaseClassTestRule;
       5: putstatic     #32                 // Field CLASS_RULE:Lorg/apache/hadoop/hbase/HBaseClassTestRule;
       8: return
}
