Compiled from "TestActiveMasterManager.java"
public class org.apache.hadoop.hbase.master.TestActiveMasterManager$NodeDeletionListener extends org.apache.hadoop.hbase.zookeeper.ZKListener {
  public org.apache.hadoop.hbase.master.TestActiveMasterManager$NodeDeletionListener(org.apache.hadoop.hbase.zookeeper.ZKWatcher, java.lang.String);
    Code:
       0: aload_0
       1: aload_1
       2: invokespecial #1                  // Method org/apache/hadoop/hbase/zookeeper/ZKListener."<init>":(Lorg/apache/hadoop/hbase/zookeeper/ZKWatcher;)V
       5: aload_0
       6: new           #2                  // class java/util/concurrent/Semaphore
       9: dup
      10: iconst_0
      11: invokespecial #3                  // Method java/util/concurrent/Semaphore."<init>":(I)V
      14: putfield      #4                  // Field lock:Ljava/util/concurrent/Semaphore;
      17: aload_0
      18: aload_2
      19: putfield      #5                  // Field node:Ljava/lang/String;
      22: return

  public void nodeDeleted(java.lang.String);
    Code:
       0: aload_1
       1: aload_0
       2: getfield      #5                  // Field node:Ljava/lang/String;
       5: invokevirtual #6                  // Method java/lang/String.equals:(Ljava/lang/Object;)Z
       8: ifeq          50
      11: getstatic     #7                  // Field LOG:Lorg/slf4j/Logger;
      14: new           #8                  // class java/lang/StringBuilder
      17: dup
      18: invokespecial #9                  // Method java/lang/StringBuilder."<init>":()V
      21: ldc           #10                 // String nodeDeleted(
      23: invokevirtual #11                 // Method java/lang/StringBuilder.append:(Ljava/lang/String;)Ljava/lang/StringBuilder;
      26: aload_1
      27: invokevirtual #11                 // Method java/lang/StringBuilder.append:(Ljava/lang/String;)Ljava/lang/StringBuilder;
      30: ldc           #12                 // String )
      32: invokevirtual #11                 // Method java/lang/StringBuilder.append:(Ljava/lang/String;)Ljava/lang/StringBuilder;
      35: invokevirtual #13                 // Method java/lang/StringBuilder.toString:()Ljava/lang/String;
      38: invokeinterface #14,  2           // InterfaceMethod org/slf4j/Logger.debug:(Ljava/lang/String;)V
      43: aload_0
      44: getfield      #4                  // Field lock:Ljava/util/concurrent/Semaphore;
      47: invokevirtual #15                 // Method java/util/concurrent/Semaphore.release:()V
      50: return

  public void waitForDeletion() throws java.lang.InterruptedException;
    Code:
       0: aload_0
       1: getfield      #4                  // Field lock:Ljava/util/concurrent/Semaphore;
       4: invokevirtual #16                 // Method java/util/concurrent/Semaphore.acquire:()V
       7: return

  static {};
    Code:
       0: ldc           #17                 // class org/apache/hadoop/hbase/master/TestActiveMasterManager$NodeDeletionListener
       2: invokestatic  #18                 // Method org/slf4j/LoggerFactory.getLogger:(Ljava/lang/Class;)Lorg/slf4j/Logger;
       5: putstatic     #7                  // Field LOG:Lorg/slf4j/Logger;
       8: return
}
