Compiled from "TestByteBufferIOEngine.java"
class org.apache.hadoop.hbase.io.hfile.bucket.TestByteBufferIOEngine$BufferGrabbingDeserializer implements org.apache.hadoop.hbase.io.hfile.CacheableDeserializer<org.apache.hadoop.hbase.io.hfile.Cacheable> {
  org.apache.hadoop.hbase.io.hfile.bucket.TestByteBufferIOEngine$BufferGrabbingDeserializer();
    Code:
       0: aload_0
       1: invokespecial #2                  // Method java/lang/Object."<init>":()V
       4: return

  public org.apache.hadoop.hbase.io.hfile.Cacheable deserialize(org.apache.hadoop.hbase.nio.ByteBuff) throws java.io.IOException;
    Code:
       0: aconst_null
       1: areturn

  public org.apache.hadoop.hbase.io.hfile.Cacheable deserialize(org.apache.hadoop.hbase.nio.ByteBuff, boolean, org.apache.hadoop.hbase.io.hfile.Cacheable$MemoryType) throws java.io.IOException;
    Code:
       0: aload_0
       1: aload_1
       2: putfield      #1                  // Field buf:Lorg/apache/hadoop/hbase/nio/ByteBuff;
       5: aconst_null
       6: areturn

  public int getDeserialiserIdentifier();
    Code:
       0: iconst_0
       1: ireturn

  public org.apache.hadoop.hbase.nio.ByteBuff getDeserializedByteBuff();
    Code:
       0: aload_0
       1: getfield      #1                  // Field buf:Lorg/apache/hadoop/hbase/nio/ByteBuff;
       4: areturn

  static org.apache.hadoop.hbase.nio.ByteBuff access$000(org.apache.hadoop.hbase.io.hfile.bucket.TestByteBufferIOEngine$BufferGrabbingDeserializer);
    Code:
       0: aload_0
       1: getfield      #1                  // Field buf:Lorg/apache/hadoop/hbase/nio/ByteBuff;
       4: areturn
}
