Compiled from "TestSimplePositionedMutableByteRange.java"
public class org.apache.hadoop.hbase.util.TestSimplePositionedMutableByteRange {
  public static final org.apache.hadoop.hbase.HBaseClassTestRule CLASS_RULE;

  public org.apache.hadoop.hbase.util.TestSimplePositionedMutableByteRange();
    Code:
       0: aload_0
       1: invokespecial #1                  // Method java/lang/Object."<init>":()V
       4: return

  public void testPosition();
    Code:
       0: new           #2                  // class org/apache/hadoop/hbase/util/SimplePositionedMutableByteRange
       3: dup
       4: iconst_5
       5: newarray       byte
       7: iconst_1
       8: iconst_3
       9: invokespecial #3                  // Method org/apache/hadoop/hbase/util/SimplePositionedMutableByteRange."<init>":([BII)V
      12: astore_1
      13: aload_1
      14: ldc           #4                  // String f
      16: invokestatic  #5                  // Method org/apache/hadoop/hbase/util/Bytes.toBytes:(Ljava/lang/String;)[B
      19: iconst_0
      20: baload
      21: invokeinterface #6,  2            // InterfaceMethod org/apache/hadoop/hbase/util/PositionedByteRange.put:(B)Lorg/apache/hadoop/hbase/util/PositionedByteRange;
      26: ldc           #7                  // String o
      28: invokestatic  #5                  // Method org/apache/hadoop/hbase/util/Bytes.toBytes:(Ljava/lang/String;)[B
      31: iconst_0
      32: baload
      33: invokeinterface #6,  2            // InterfaceMethod org/apache/hadoop/hbase/util/PositionedByteRange.put:(B)Lorg/apache/hadoop/hbase/util/PositionedByteRange;
      38: ldc           #7                  // String o
      40: invokestatic  #5                  // Method org/apache/hadoop/hbase/util/Bytes.toBytes:(Ljava/lang/String;)[B
      43: iconst_0
      44: baload
      45: invokeinterface #6,  2            // InterfaceMethod org/apache/hadoop/hbase/util/PositionedByteRange.put:(B)Lorg/apache/hadoop/hbase/util/PositionedByteRange;
      50: pop
      51: ldc2_w        #8                  // long 3l
      54: aload_1
      55: invokeinterface #10,  1           // InterfaceMethod org/apache/hadoop/hbase/util/PositionedByteRange.getPosition:()I
      60: i2l
      61: invokestatic  #11                 // Method org/junit/Assert.assertEquals:(JJ)V
      64: iconst_5
      65: newarray       byte
      67: dup
      68: iconst_0
      69: iconst_0
      70: bastore
      71: dup
      72: iconst_1
      73: ldc           #4                  // String f
      75: invokestatic  #5                  // Method org/apache/hadoop/hbase/util/Bytes.toBytes:(Ljava/lang/String;)[B
      78: iconst_0
      79: baload
      80: bastore
      81: dup
      82: iconst_2
      83: ldc           #7                  // String o
      85: invokestatic  #5                  // Method org/apache/hadoop/hbase/util/Bytes.toBytes:(Ljava/lang/String;)[B
      88: iconst_0
      89: baload
      90: bastore
      91: dup
      92: iconst_3
      93: ldc           #7                  // String o
      95: invokestatic  #5                  // Method org/apache/hadoop/hbase/util/Bytes.toBytes:(Ljava/lang/String;)[B
      98: iconst_0
      99: baload
     100: bastore
     101: dup
     102: iconst_4
     103: iconst_0
     104: bastore
     105: aload_1
     106: invokeinterface #12,  1           // InterfaceMethod org/apache/hadoop/hbase/util/PositionedByteRange.getBytes:()[B
     111: invokestatic  #13                 // Method org/junit/Assert.assertArrayEquals:([B[B)V
     114: aload_1
     115: iconst_0
     116: invokeinterface #14,  2           // InterfaceMethod org/apache/hadoop/hbase/util/PositionedByteRange.setPosition:(I)Lorg/apache/hadoop/hbase/util/PositionedByteRange;
     121: pop
     122: aload_1
     123: ldc           #4                  // String f
     125: invokestatic  #5                  // Method org/apache/hadoop/hbase/util/Bytes.toBytes:(Ljava/lang/String;)[B
     128: invokeinterface #15,  2           // InterfaceMethod org/apache/hadoop/hbase/util/PositionedByteRange.put:([B)Lorg/apache/hadoop/hbase/util/PositionedByteRange;
     133: ldc           #7                  // String o
     135: invokestatic  #5                  // Method org/apache/hadoop/hbase/util/Bytes.toBytes:(Ljava/lang/String;)[B
     138: invokeinterface #15,  2           // InterfaceMethod org/apache/hadoop/hbase/util/PositionedByteRange.put:([B)Lorg/apache/hadoop/hbase/util/PositionedByteRange;
     143: ldc           #7                  // String o
     145: invokestatic  #5                  // Method org/apache/hadoop/hbase/util/Bytes.toBytes:(Ljava/lang/String;)[B
     148: invokeinterface #15,  2           // InterfaceMethod org/apache/hadoop/hbase/util/PositionedByteRange.put:([B)Lorg/apache/hadoop/hbase/util/PositionedByteRange;
     153: pop
     154: ldc2_w        #8                  // long 3l
     157: aload_1
     158: invokeinterface #10,  1           // InterfaceMethod org/apache/hadoop/hbase/util/PositionedByteRange.getPosition:()I
     163: i2l
     164: invokestatic  #11                 // Method org/junit/Assert.assertEquals:(JJ)V
     167: iconst_5
     168: newarray       byte
     170: dup
     171: iconst_0
     172: iconst_0
     173: bastore
     174: dup
     175: iconst_1
     176: ldc           #4                  // String f
     178: invokestatic  #5                  // Method org/apache/hadoop/hbase/util/Bytes.toBytes:(Ljava/lang/String;)[B
     181: iconst_0
     182: baload
     183: bastore
     184: dup
     185: iconst_2
     186: ldc           #7                  // String o
     188: invokestatic  #5                  // Method org/apache/hadoop/hbase/util/Bytes.toBytes:(Ljava/lang/String;)[B
     191: iconst_0
     192: baload
     193: bastore
     194: dup
     195: iconst_3
     196: ldc           #7                  // String o
     198: invokestatic  #5                  // Method org/apache/hadoop/hbase/util/Bytes.toBytes:(Ljava/lang/String;)[B
     201: iconst_0
     202: baload
     203: bastore
     204: dup
     205: iconst_4
     206: iconst_0
     207: bastore
     208: aload_1
     209: invokeinterface #12,  1           // InterfaceMethod org/apache/hadoop/hbase/util/PositionedByteRange.getBytes:()[B
     214: invokestatic  #13                 // Method org/junit/Assert.assertArrayEquals:([B[B)V
     217: aload_1
     218: iconst_0
     219: invokeinterface #14,  2           // InterfaceMethod org/apache/hadoop/hbase/util/PositionedByteRange.setPosition:(I)Lorg/apache/hadoop/hbase/util/PositionedByteRange;
     224: pop
     225: ldc           #4                  // String f
     227: invokestatic  #5                  // Method org/apache/hadoop/hbase/util/Bytes.toBytes:(Ljava/lang/String;)[B
     230: iconst_0
     231: baload
     232: i2l
     233: aload_1
     234: invokeinterface #16,  1           // InterfaceMethod org/apache/hadoop/hbase/util/PositionedByteRange.get:()B
     239: i2l
     240: invokestatic  #11                 // Method org/junit/Assert.assertEquals:(JJ)V
     243: ldc           #7                  // String o
     245: invokestatic  #5                  // Method org/apache/hadoop/hbase/util/Bytes.toBytes:(Ljava/lang/String;)[B
     248: iconst_0
     249: baload
     250: i2l
     251: aload_1
     252: invokeinterface #16,  1           // InterfaceMethod org/apache/hadoop/hbase/util/PositionedByteRange.get:()B
     257: i2l
     258: invokestatic  #11                 // Method org/junit/Assert.assertEquals:(JJ)V
     261: ldc           #7                  // String o
     263: invokestatic  #5                  // Method org/apache/hadoop/hbase/util/Bytes.toBytes:(Ljava/lang/String;)[B
     266: iconst_0
     267: baload
     268: i2l
     269: aload_1
     270: invokeinterface #16,  1           // InterfaceMethod org/apache/hadoop/hbase/util/PositionedByteRange.get:()B
     275: i2l
     276: invokestatic  #11                 // Method org/junit/Assert.assertEquals:(JJ)V
     279: aload_1
     280: iconst_1
     281: invokeinterface #14,  2           // InterfaceMethod org/apache/hadoop/hbase/util/PositionedByteRange.setPosition:(I)Lorg/apache/hadoop/hbase/util/PositionedByteRange;
     286: pop
     287: ldc           #7                  // String o
     289: invokestatic  #5                  // Method org/apache/hadoop/hbase/util/Bytes.toBytes:(Ljava/lang/String;)[B
     292: iconst_0
     293: baload
     294: i2l
     295: aload_1
     296: invokeinterface #16,  1           // InterfaceMethod org/apache/hadoop/hbase/util/PositionedByteRange.get:()B
     301: i2l
     302: invokestatic  #11                 // Method org/junit/Assert.assertEquals:(JJ)V
     305: aload_1
     306: iconst_0
     307: invokeinterface #14,  2           // InterfaceMethod org/apache/hadoop/hbase/util/PositionedByteRange.setPosition:(I)Lorg/apache/hadoop/hbase/util/PositionedByteRange;
     312: pop
     313: iconst_3
     314: newarray       byte
     316: astore_2
     317: aload_1
     318: aload_2
     319: invokeinterface #17,  2           // InterfaceMethod org/apache/hadoop/hbase/util/PositionedByteRange.get:([B)Lorg/apache/hadoop/hbase/util/PositionedByteRange;
     324: pop
     325: ldc           #18                 // String foo
     327: invokestatic  #5                  // Method org/apache/hadoop/hbase/util/Bytes.toBytes:(Ljava/lang/String;)[B
     330: aload_2
     331: invokestatic  #13                 // Method org/junit/Assert.assertArrayEquals:([B[B)V
     334: aload_1
     335: iconst_3
     336: invokeinterface #14,  2           // InterfaceMethod org/apache/hadoop/hbase/util/PositionedByteRange.setPosition:(I)Lorg/apache/hadoop/hbase/util/PositionedByteRange;
     341: pop
     342: return

  public void testPutAndGetPrimitiveTypes() throws java.lang.Exception;
    Code:
       0: new           #2                  // class org/apache/hadoop/hbase/util/SimplePositionedMutableByteRange
       3: dup
       4: bipush        100
       6: invokespecial #19                 // Method org/apache/hadoop/hbase/util/SimplePositionedMutableByteRange."<init>":(I)V
       9: astore_1
      10: bipush        18
      12: istore_2
      13: iconst_2
      14: istore_3
      15: iconst_0
      16: istore        4
      18: ldc2_w        #20                 // long 1234l
      21: lstore        5
      23: aload_1
      24: iload_2
      25: invokeinterface #22,  2           // InterfaceMethod org/apache/hadoop/hbase/util/PositionedByteRange.putInt:(I)Lorg/apache/hadoop/hbase/util/PositionedByteRange;
      30: pop
      31: aload_1
      32: iload_3
      33: invokeinterface #22,  2           // InterfaceMethod org/apache/hadoop/hbase/util/PositionedByteRange.putInt:(I)Lorg/apache/hadoop/hbase/util/PositionedByteRange;
      38: pop
      39: aload_1
      40: iload         4
      42: invokeinterface #23,  2           // InterfaceMethod org/apache/hadoop/hbase/util/PositionedByteRange.putShort:(S)Lorg/apache/hadoop/hbase/util/PositionedByteRange;
      47: pop
      48: aload_1
      49: lload         5
      51: invokeinterface #24,  3           // InterfaceMethod org/apache/hadoop/hbase/util/PositionedByteRange.putLong:(J)Lorg/apache/hadoop/hbase/util/PositionedByteRange;
      56: pop
      57: aload_1
      58: lconst_0
      59: invokeinterface #25,  3           // InterfaceMethod org/apache/hadoop/hbase/util/PositionedByteRange.putVLong:(J)I
      64: pop
      65: aload_1
      66: lload         5
      68: invokeinterface #25,  3           // InterfaceMethod org/apache/hadoop/hbase/util/PositionedByteRange.putVLong:(J)I
      73: pop
      74: aload_1
      75: ldc2_w        #27                 // long 9223372036854775807l
      78: invokeinterface #25,  3           // InterfaceMethod org/apache/hadoop/hbase/util/PositionedByteRange.putVLong:(J)I
      83: pop
      84: aload_1
      85: ldc2_w        #29                 // long -9223372036854775808l
      88: invokeinterface #25,  3           // InterfaceMethod org/apache/hadoop/hbase/util/PositionedByteRange.putVLong:(J)I
      93: pop
      94: aload_1
      95: iconst_0
      96: invokeinterface #14,  2           // InterfaceMethod org/apache/hadoop/hbase/util/PositionedByteRange.setPosition:(I)Lorg/apache/hadoop/hbase/util/PositionedByteRange;
     101: pop
     102: iload_2
     103: i2l
     104: aload_1
     105: invokeinterface #31,  1           // InterfaceMethod org/apache/hadoop/hbase/util/PositionedByteRange.getInt:()I
     110: i2l
     111: invokestatic  #11                 // Method org/junit/Assert.assertEquals:(JJ)V
     114: iload_3
     115: i2l
     116: aload_1
     117: invokeinterface #31,  1           // InterfaceMethod org/apache/hadoop/hbase/util/PositionedByteRange.getInt:()I
     122: i2l
     123: invokestatic  #11                 // Method org/junit/Assert.assertEquals:(JJ)V
     126: iload         4
     128: i2l
     129: aload_1
     130: invokeinterface #32,  1           // InterfaceMethod org/apache/hadoop/hbase/util/PositionedByteRange.getShort:()S
     135: i2l
     136: invokestatic  #11                 // Method org/junit/Assert.assertEquals:(JJ)V
     139: lload         5
     141: aload_1
     142: invokeinterface #33,  1           // InterfaceMethod org/apache/hadoop/hbase/util/PositionedByteRange.getLong:()J
     147: invokestatic  #11                 // Method org/junit/Assert.assertEquals:(JJ)V
     150: lconst_0
     151: aload_1
     152: invokeinterface #34,  1           // InterfaceMethod org/apache/hadoop/hbase/util/PositionedByteRange.getVLong:()J
     157: invokestatic  #11                 // Method org/junit/Assert.assertEquals:(JJ)V
     160: lload         5
     162: aload_1
     163: invokeinterface #34,  1           // InterfaceMethod org/apache/hadoop/hbase/util/PositionedByteRange.getVLong:()J
     168: invokestatic  #11                 // Method org/junit/Assert.assertEquals:(JJ)V
     171: ldc2_w        #27                 // long 9223372036854775807l
     174: aload_1
     175: invokeinterface #34,  1           // InterfaceMethod org/apache/hadoop/hbase/util/PositionedByteRange.getVLong:()J
     180: invokestatic  #11                 // Method org/junit/Assert.assertEquals:(JJ)V
     183: ldc2_w        #29                 // long -9223372036854775808l
     186: aload_1
     187: invokeinterface #34,  1           // InterfaceMethod org/apache/hadoop/hbase/util/PositionedByteRange.getVLong:()J
     192: invokestatic  #11                 // Method org/junit/Assert.assertEquals:(JJ)V
     195: return

  public void testPutGetAPIsCompareWithBBAPIs() throws java.lang.Exception;
    Code:
       0: new           #2                  // class org/apache/hadoop/hbase/util/SimplePositionedMutableByteRange
       3: dup
       4: bipush        100
       6: invokespecial #19                 // Method org/apache/hadoop/hbase/util/SimplePositionedMutableByteRange."<init>":(I)V
       9: astore_1
      10: sipush        -234
      13: istore_2
      14: iconst_2
      15: istore_3
      16: iconst_0
      17: istore        4
      19: ldc2_w        #20                 // long 1234l
      22: lstore        5
      24: aload_1
      25: iload_2
      26: invokeinterface #22,  2           // InterfaceMethod org/apache/hadoop/hbase/util/PositionedByteRange.putInt:(I)Lorg/apache/hadoop/hbase/util/PositionedByteRange;
      31: pop
      32: aload_1
      33: iload         4
      35: invokeinterface #23,  2           // InterfaceMethod org/apache/hadoop/hbase/util/PositionedByteRange.putShort:(S)Lorg/apache/hadoop/hbase/util/PositionedByteRange;
      40: pop
      41: aload_1
      42: iload_3
      43: invokeinterface #22,  2           // InterfaceMethod org/apache/hadoop/hbase/util/PositionedByteRange.putInt:(I)Lorg/apache/hadoop/hbase/util/PositionedByteRange;
      48: pop
      49: aload_1
      50: lload         5
      52: invokeinterface #24,  3           // InterfaceMethod org/apache/hadoop/hbase/util/PositionedByteRange.putLong:(J)Lorg/apache/hadoop/hbase/util/PositionedByteRange;
      57: pop
      58: aload_1
      59: iconst_0
      60: invokeinterface #14,  2           // InterfaceMethod org/apache/hadoop/hbase/util/PositionedByteRange.setPosition:(I)Lorg/apache/hadoop/hbase/util/PositionedByteRange;
      65: pop
      66: iload_2
      67: i2l
      68: aload_1
      69: invokeinterface #31,  1           // InterfaceMethod org/apache/hadoop/hbase/util/PositionedByteRange.getInt:()I
      74: i2l
      75: invokestatic  #11                 // Method org/junit/Assert.assertEquals:(JJ)V
      78: iload         4
      80: i2l
      81: aload_1
      82: invokeinterface #32,  1           // InterfaceMethod org/apache/hadoop/hbase/util/PositionedByteRange.getShort:()S
      87: i2l
      88: invokestatic  #11                 // Method org/junit/Assert.assertEquals:(JJ)V
      91: iload_3
      92: i2l
      93: aload_1
      94: invokeinterface #31,  1           // InterfaceMethod org/apache/hadoop/hbase/util/PositionedByteRange.getInt:()I
      99: i2l
     100: invokestatic  #11                 // Method org/junit/Assert.assertEquals:(JJ)V
     103: lload         5
     105: aload_1
     106: invokeinterface #33,  1           // InterfaceMethod org/apache/hadoop/hbase/util/PositionedByteRange.getLong:()J
     111: invokestatic  #11                 // Method org/junit/Assert.assertEquals:(JJ)V
     114: aload_1
     115: invokeinterface #12,  1           // InterfaceMethod org/apache/hadoop/hbase/util/PositionedByteRange.getBytes:()[B
     120: invokestatic  #35                 // Method java/nio/ByteBuffer.wrap:([B)Ljava/nio/ByteBuffer;
     123: astore        7
     125: iload_2
     126: i2l
     127: aload         7
     129: invokevirtual #36                 // Method java/nio/ByteBuffer.getInt:()I
     132: i2l
     133: invokestatic  #11                 // Method org/junit/Assert.assertEquals:(JJ)V
     136: iload         4
     138: i2l
     139: aload         7
     141: invokevirtual #37                 // Method java/nio/ByteBuffer.getShort:()S
     144: i2l
     145: invokestatic  #11                 // Method org/junit/Assert.assertEquals:(JJ)V
     148: iload_3
     149: i2l
     150: aload         7
     152: invokevirtual #36                 // Method java/nio/ByteBuffer.getInt:()I
     155: i2l
     156: invokestatic  #11                 // Method org/junit/Assert.assertEquals:(JJ)V
     159: lload         5
     161: aload         7
     163: invokevirtual #38                 // Method java/nio/ByteBuffer.getLong:()J
     166: invokestatic  #11                 // Method org/junit/Assert.assertEquals:(JJ)V
     169: return

  static {};
    Code:
       0: ldc           #39                 // class org/apache/hadoop/hbase/util/TestSimplePositionedMutableByteRange
       2: invokestatic  #40                 // Method org/apache/hadoop/hbase/HBaseClassTestRule.forClass:(Ljava/lang/Class;)Lorg/apache/hadoop/hbase/HBaseClassTestRule;
       5: putstatic     #41                 // Field CLASS_RULE:Lorg/apache/hadoop/hbase/HBaseClassTestRule;
       8: return
}
