Compiled from "TestHDFSBlocksDistribution.java"
public class org.apache.hadoop.hbase.TestHDFSBlocksDistribution$MockHDFSBlocksDistribution extends org.apache.hadoop.hbase.HDFSBlocksDistribution {
  final org.apache.hadoop.hbase.TestHDFSBlocksDistribution this$0;

  public org.apache.hadoop.hbase.TestHDFSBlocksDistribution$MockHDFSBlocksDistribution(org.apache.hadoop.hbase.TestHDFSBlocksDistribution);
    Code:
       0: aload_0
       1: aload_1
       2: putfield      #1                  // Field this$0:Lorg/apache/hadoop/hbase/TestHDFSBlocksDistribution;
       5: aload_0
       6: invokespecial #2                  // Method org/apache/hadoop/hbase/HDFSBlocksDistribution."<init>":()V
       9: return

  public java.util.Map<java.lang.String, org.apache.hadoop.hbase.HDFSBlocksDistribution$HostAndWeight> getHostAndWeights();
    Code:
       0: new           #3                  // class java/util/HashMap
       3: dup
       4: invokespecial #4                  // Method java/util/HashMap."<init>":()V
       7: astore_1
       8: aload_1
       9: ldc           #5                  // String test
      11: new           #6                  // class org/apache/hadoop/hbase/HDFSBlocksDistribution$HostAndWeight
      14: dup
      15: aconst_null
      16: ldc2_w        #7                  // long 100l
      19: invokespecial #9                  // Method org/apache/hadoop/hbase/HDFSBlocksDistribution$HostAndWeight."<init>":(Ljava/lang/String;J)V
      22: invokevirtual #10                 // Method java/util/HashMap.put:(Ljava/lang/Object;Ljava/lang/Object;)Ljava/lang/Object;
      25: pop
      26: aload_1
      27: areturn
}
