Compiled from "TestAsyncTableBatch.java"
public class org.apache.hadoop.hbase.client.TestAsyncTableBatch {
  public static final org.apache.hadoop.hbase.HBaseClassTestRule CLASS_RULE;

  public java.lang.String tableType;

  public java.util.function.Function<org.apache.hadoop.hbase.TableName, org.apache.hadoop.hbase.client.AsyncTable<?>> tableGetter;

  public org.apache.hadoop.hbase.client.TestAsyncTableBatch();
    Code:
       0: aload_0
       1: invokespecial #1                  // Method java/lang/Object."<init>":()V
       4: return

  public static java.util.List<java.lang.Object[]> params();
    Code:
       0: invokedynamic #6,  0              // InvokeDynamic #0:apply:()Ljava/util/function/Function;
       5: astore_0
       6: invokedynamic #7,  0              // InvokeDynamic #1:apply:()Ljava/util/function/Function;
      11: astore_1
      12: iconst_2
      13: anewarray     #8                  // class "[Ljava/lang/Object;"
      16: dup
      17: iconst_0
      18: iconst_2
      19: anewarray     #9                  // class java/lang/Object
      22: dup
      23: iconst_0
      24: ldc           #10                 // String raw
      26: aastore
      27: dup
      28: iconst_1
      29: aload_0
      30: aastore
      31: aastore
      32: dup
      33: iconst_1
      34: iconst_2
      35: anewarray     #9                  // class java/lang/Object
      38: dup
      39: iconst_0
      40: ldc           #11                 // String normal
      42: aastore
      43: dup
      44: iconst_1
      45: aload_1
      46: aastore
      47: aastore
      48: invokestatic  #12                 // Method java/util/Arrays.asList:([Ljava/lang/Object;)Ljava/util/List;
      51: areturn

  public static void setUp() throws java.lang.Exception;
    Code:
       0: getstatic     #13                 // Field TEST_UTIL:Lorg/apache/hadoop/hbase/HBaseTestingUtility;
       3: invokevirtual #14                 // Method org/apache/hadoop/hbase/HBaseTestingUtility.getConfiguration:()Lorg/apache/hadoop/conf/Configuration;
       6: ldc           #16                 // String hbase.client.keyvalue.maxsize
       8: getstatic     #17                 // Field MAX_KEY_VALUE_SIZE:I
      11: invokevirtual #18                 // Method org/apache/hadoop/conf/Configuration.setInt:(Ljava/lang/String;I)V
      14: getstatic     #13                 // Field TEST_UTIL:Lorg/apache/hadoop/hbase/HBaseTestingUtility;
      17: iconst_3
      18: invokevirtual #19                 // Method org/apache/hadoop/hbase/HBaseTestingUtility.startMiniCluster:(I)Lorg/apache/hadoop/hbase/MiniHBaseCluster;
      21: pop
      22: bipush        8
      24: anewarray     #20                 // class "[B"
      27: putstatic     #21                 // Field SPLIT_KEYS:[[B
      30: bipush        111
      32: istore_0
      33: iload_0
      34: sipush        999
      37: if_icmpge     75
      40: getstatic     #21                 // Field SPLIT_KEYS:[[B
      43: iload_0
      44: bipush        111
      46: idiv
      47: iconst_1
      48: isub
      49: ldc           #22                 // String %03d
      51: iconst_1
      52: anewarray     #9                  // class java/lang/Object
      55: dup
      56: iconst_0
      57: iload_0
      58: invokestatic  #23                 // Method java/lang/Integer.valueOf:(I)Ljava/lang/Integer;
      61: aastore
      62: invokestatic  #24                 // Method java/lang/String.format:(Ljava/lang/String;[Ljava/lang/Object;)Ljava/lang/String;
      65: invokestatic  #25                 // Method org/apache/hadoop/hbase/util/Bytes.toBytes:(Ljava/lang/String;)[B
      68: aastore
      69: iinc          0, 111
      72: goto          33
      75: getstatic     #13                 // Field TEST_UTIL:Lorg/apache/hadoop/hbase/HBaseTestingUtility;
      78: invokevirtual #14                 // Method org/apache/hadoop/hbase/HBaseTestingUtility.getConfiguration:()Lorg/apache/hadoop/conf/Configuration;
      81: invokestatic  #26                 // Method org/apache/hadoop/hbase/client/ConnectionFactory.createAsyncConnection:(Lorg/apache/hadoop/conf/Configuration;)Ljava/util/concurrent/CompletableFuture;
      84: invokevirtual #27                 // Method java/util/concurrent/CompletableFuture.get:()Ljava/lang/Object;
      87: checkcast     #28                 // class org/apache/hadoop/hbase/client/AsyncConnection
      90: putstatic     #2                  // Field CONN:Lorg/apache/hadoop/hbase/client/AsyncConnection;
      93: return

  public static void tearDown() throws java.lang.Exception;
    Code:
       0: getstatic     #2                  // Field CONN:Lorg/apache/hadoop/hbase/client/AsyncConnection;
       3: invokeinterface #29,  1           // InterfaceMethod org/apache/hadoop/hbase/client/AsyncConnection.close:()V
       8: getstatic     #13                 // Field TEST_UTIL:Lorg/apache/hadoop/hbase/HBaseTestingUtility;
      11: invokevirtual #30                 // Method org/apache/hadoop/hbase/HBaseTestingUtility.shutdownMiniCluster:()V
      14: return

  public void setUpBeforeTest() throws java.io.IOException, java.lang.InterruptedException;
    Code:
       0: getstatic     #13                 // Field TEST_UTIL:Lorg/apache/hadoop/hbase/HBaseTestingUtility;
       3: getstatic     #31                 // Field TABLE_NAME:Lorg/apache/hadoop/hbase/TableName;
       6: getstatic     #32                 // Field FAMILY:[B
       9: getstatic     #21                 // Field SPLIT_KEYS:[[B
      12: invokevirtual #33                 // Method org/apache/hadoop/hbase/HBaseTestingUtility.createTable:(Lorg/apache/hadoop/hbase/TableName;[B[[B)Lorg/apache/hadoop/hbase/client/Table;
      15: pop
      16: getstatic     #13                 // Field TEST_UTIL:Lorg/apache/hadoop/hbase/HBaseTestingUtility;
      19: getstatic     #31                 // Field TABLE_NAME:Lorg/apache/hadoop/hbase/TableName;
      22: invokevirtual #34                 // Method org/apache/hadoop/hbase/HBaseTestingUtility.waitTableAvailable:(Lorg/apache/hadoop/hbase/TableName;)V
      25: return

  public void tearDownAfterTest() throws java.io.IOException;
    Code:
       0: getstatic     #13                 // Field TEST_UTIL:Lorg/apache/hadoop/hbase/HBaseTestingUtility;
       3: invokevirtual #35                 // Method org/apache/hadoop/hbase/HBaseTestingUtility.getAdmin:()Lorg/apache/hadoop/hbase/client/Admin;
       6: astore_1
       7: aload_1
       8: getstatic     #31                 // Field TABLE_NAME:Lorg/apache/hadoop/hbase/TableName;
      11: invokeinterface #36,  2           // InterfaceMethod org/apache/hadoop/hbase/client/Admin.isTableEnabled:(Lorg/apache/hadoop/hbase/TableName;)Z
      16: ifeq          28
      19: aload_1
      20: getstatic     #31                 // Field TABLE_NAME:Lorg/apache/hadoop/hbase/TableName;
      23: invokeinterface #37,  2           // InterfaceMethod org/apache/hadoop/hbase/client/Admin.disableTable:(Lorg/apache/hadoop/hbase/TableName;)V
      28: aload_1
      29: getstatic     #31                 // Field TABLE_NAME:Lorg/apache/hadoop/hbase/TableName;
      32: invokeinterface #38,  2           // InterfaceMethod org/apache/hadoop/hbase/client/Admin.deleteTable:(Lorg/apache/hadoop/hbase/TableName;)V
      37: return

  public void test() throws java.lang.InterruptedException, java.util.concurrent.ExecutionException, java.io.IOException, java.util.concurrent.TimeoutException;
    Code:
       0: aload_0
       1: getfield      #39                 // Field tableGetter:Ljava/util/function/Function;
       4: getstatic     #31                 // Field TABLE_NAME:Lorg/apache/hadoop/hbase/TableName;
       7: invokeinterface #40,  2           // InterfaceMethod java/util/function/Function.apply:(Ljava/lang/Object;)Ljava/lang/Object;
      12: checkcast     #41                 // class org/apache/hadoop/hbase/client/AsyncTable
      15: astore_1
      16: aload_1
      17: iconst_0
      18: getstatic     #42                 // Field COUNT:I
      21: invokestatic  #43                 // InterfaceMethod java/util/stream/IntStream.range:(II)Ljava/util/stream/IntStream;
      24: aload_0
      25: invokedynamic #44,  0             // InvokeDynamic #2:apply:(Lorg/apache/hadoop/hbase/client/TestAsyncTableBatch;)Ljava/util/function/IntFunction;
      30: invokeinterface #45,  2           // InterfaceMethod java/util/stream/IntStream.mapToObj:(Ljava/util/function/IntFunction;)Ljava/util/stream/Stream;
      35: invokestatic  #46                 // Method java/util/stream/Collectors.toList:()Ljava/util/stream/Collector;
      38: invokeinterface #47,  2           // InterfaceMethod java/util/stream/Stream.collect:(Ljava/util/stream/Collector;)Ljava/lang/Object;
      43: checkcast     #48                 // class java/util/List
      46: invokeinterface #49,  2           // InterfaceMethod org/apache/hadoop/hbase/client/AsyncTable.putAll:(Ljava/util/List;)Ljava/util/concurrent/CompletableFuture;
      51: invokevirtual #27                 // Method java/util/concurrent/CompletableFuture.get:()Ljava/lang/Object;
      54: pop
      55: aload_1
      56: iconst_0
      57: getstatic     #42                 // Field COUNT:I
      60: invokestatic  #43                 // InterfaceMethod java/util/stream/IntStream.range:(II)Ljava/util/stream/IntStream;
      63: aload_0
      64: invokedynamic #50,  0             // InvokeDynamic #3:apply:(Lorg/apache/hadoop/hbase/client/TestAsyncTableBatch;)Ljava/util/function/IntFunction;
      69: invokeinterface #45,  2           // InterfaceMethod java/util/stream/IntStream.mapToObj:(Ljava/util/function/IntFunction;)Ljava/util/stream/Stream;
      74: invokedynamic #51,  0             // InvokeDynamic #4:apply:()Ljava/util/function/Function;
      79: invokeinterface #52,  2           // InterfaceMethod java/util/stream/Stream.flatMap:(Ljava/util/function/Function;)Ljava/util/stream/Stream;
      84: invokestatic  #46                 // Method java/util/stream/Collectors.toList:()Ljava/util/stream/Collector;
      87: invokeinterface #47,  2           // InterfaceMethod java/util/stream/Stream.collect:(Ljava/util/stream/Collector;)Ljava/lang/Object;
      92: checkcast     #48                 // class java/util/List
      95: invokeinterface #53,  2           // InterfaceMethod org/apache/hadoop/hbase/client/AsyncTable.getAll:(Ljava/util/List;)Ljava/util/concurrent/CompletableFuture;
     100: invokevirtual #27                 // Method java/util/concurrent/CompletableFuture.get:()Ljava/lang/Object;
     103: checkcast     #48                 // class java/util/List
     106: astore_2
     107: iconst_2
     108: getstatic     #42                 // Field COUNT:I
     111: imul
     112: i2l
     113: aload_2
     114: invokeinterface #54,  1           // InterfaceMethod java/util/List.size:()I
     119: i2l
     120: invokestatic  #55                 // Method org/junit/Assert.assertEquals:(JJ)V
     123: iconst_0
     124: istore_3
     125: iload_3
     126: getstatic     #42                 // Field COUNT:I
     129: if_icmpge     188
     132: iload_3
     133: i2l
     134: aload_2
     135: iconst_2
     136: iload_3
     137: imul
     138: invokeinterface #56,  2           // InterfaceMethod java/util/List.get:(I)Ljava/lang/Object;
     143: checkcast     #57                 // class org/apache/hadoop/hbase/client/Result
     146: getstatic     #32                 // Field FAMILY:[B
     149: getstatic     #58                 // Field CQ:[B
     152: invokevirtual #59                 // Method org/apache/hadoop/hbase/client/Result.getValue:([B[B)[B
     155: invokestatic  #60                 // Method org/apache/hadoop/hbase/util/Bytes.toInt:([B)I
     158: i2l
     159: invokestatic  #55                 // Method org/junit/Assert.assertEquals:(JJ)V
     162: aload_2
     163: iconst_2
     164: iload_3
     165: imul
     166: iconst_1
     167: iadd
     168: invokeinterface #56,  2           // InterfaceMethod java/util/List.get:(I)Ljava/lang/Object;
     173: checkcast     #57                 // class org/apache/hadoop/hbase/client/Result
     176: invokevirtual #61                 // Method org/apache/hadoop/hbase/client/Result.isEmpty:()Z
     179: invokestatic  #62                 // Method org/junit/Assert.assertTrue:(Z)V
     182: iinc          3, 1
     185: goto          125
     188: getstatic     #13                 // Field TEST_UTIL:Lorg/apache/hadoop/hbase/HBaseTestingUtility;
     191: invokevirtual #35                 // Method org/apache/hadoop/hbase/HBaseTestingUtility.getAdmin:()Lorg/apache/hadoop/hbase/client/Admin;
     194: astore_3
     195: aload_3
     196: getstatic     #31                 // Field TABLE_NAME:Lorg/apache/hadoop/hbase/TableName;
     199: invokeinterface #63,  2           // InterfaceMethod org/apache/hadoop/hbase/client/Admin.flush:(Lorg/apache/hadoop/hbase/TableName;)V
     204: getstatic     #13                 // Field TEST_UTIL:Lorg/apache/hadoop/hbase/HBaseTestingUtility;
     207: invokevirtual #64                 // Method org/apache/hadoop/hbase/HBaseTestingUtility.getHBaseCluster:()Lorg/apache/hadoop/hbase/MiniHBaseCluster;
     210: getstatic     #31                 // Field TABLE_NAME:Lorg/apache/hadoop/hbase/TableName;
     213: invokevirtual #65                 // Method org/apache/hadoop/hbase/MiniHBaseCluster.getRegions:(Lorg/apache/hadoop/hbase/TableName;)Ljava/util/List;
     216: invokeinterface #66,  1           // InterfaceMethod java/util/List.stream:()Ljava/util/stream/Stream;
     221: aload_3
     222: invokedynamic #67,  0             // InvokeDynamic #5:apply:(Lorg/apache/hadoop/hbase/client/Admin;)Ljava/util/function/Function;
     227: invokeinterface #68,  2           // InterfaceMethod java/util/stream/Stream.map:(Ljava/util/function/Function;)Ljava/util/stream/Stream;
     232: invokestatic  #46                 // Method java/util/stream/Collectors.toList:()Ljava/util/stream/Collector;
     235: invokeinterface #47,  2           // InterfaceMethod java/util/stream/Stream.collect:(Ljava/util/stream/Collector;)Ljava/lang/Object;
     240: checkcast     #48                 // class java/util/List
     243: astore        4
     245: aload         4
     247: invokeinterface #69,  1           // InterfaceMethod java/util/List.iterator:()Ljava/util/Iterator;
     252: astore        5
     254: aload         5
     256: invokeinterface #70,  1           // InterfaceMethod java/util/Iterator.hasNext:()Z
     261: ifeq          293
     264: aload         5
     266: invokeinterface #71,  1           // InterfaceMethod java/util/Iterator.next:()Ljava/lang/Object;
     271: checkcast     #72                 // class java/util/concurrent/Future
     274: astore        6
     276: aload         6
     278: ldc2_w        #73                 // long 30l
     281: getstatic     #75                 // Field java/util/concurrent/TimeUnit.SECONDS:Ljava/util/concurrent/TimeUnit;
     284: invokeinterface #76,  4           // InterfaceMethod java/util/concurrent/Future.get:(JLjava/util/concurrent/TimeUnit;)Ljava/lang/Object;
     289: pop
     290: goto          254
     293: aload_1
     294: iconst_0
     295: getstatic     #42                 // Field COUNT:I
     298: invokestatic  #43                 // InterfaceMethod java/util/stream/IntStream.range:(II)Ljava/util/stream/IntStream;
     301: aload_0
     302: invokedynamic #77,  0             // InvokeDynamic #6:apply:(Lorg/apache/hadoop/hbase/client/TestAsyncTableBatch;)Ljava/util/function/IntFunction;
     307: invokeinterface #45,  2           // InterfaceMethod java/util/stream/IntStream.mapToObj:(Ljava/util/function/IntFunction;)Ljava/util/stream/Stream;
     312: invokestatic  #46                 // Method java/util/stream/Collectors.toList:()Ljava/util/stream/Collector;
     315: invokeinterface #47,  2           // InterfaceMethod java/util/stream/Stream.collect:(Ljava/util/stream/Collector;)Ljava/lang/Object;
     320: checkcast     #48                 // class java/util/List
     323: invokeinterface #78,  2           // InterfaceMethod org/apache/hadoop/hbase/client/AsyncTable.deleteAll:(Ljava/util/List;)Ljava/util/concurrent/CompletableFuture;
     328: invokevirtual #27                 // Method java/util/concurrent/CompletableFuture.get:()Ljava/lang/Object;
     331: pop
     332: aload_1
     333: iconst_0
     334: getstatic     #42                 // Field COUNT:I
     337: invokestatic  #43                 // InterfaceMethod java/util/stream/IntStream.range:(II)Ljava/util/stream/IntStream;
     340: aload_0
     341: invokedynamic #79,  0             // InvokeDynamic #7:apply:(Lorg/apache/hadoop/hbase/client/TestAsyncTableBatch;)Ljava/util/function/IntFunction;
     346: invokeinterface #45,  2           // InterfaceMethod java/util/stream/IntStream.mapToObj:(Ljava/util/function/IntFunction;)Ljava/util/stream/Stream;
     351: invokestatic  #46                 // Method java/util/stream/Collectors.toList:()Ljava/util/stream/Collector;
     354: invokeinterface #47,  2           // InterfaceMethod java/util/stream/Stream.collect:(Ljava/util/stream/Collector;)Ljava/lang/Object;
     359: checkcast     #48                 // class java/util/List
     362: invokeinterface #53,  2           // InterfaceMethod org/apache/hadoop/hbase/client/AsyncTable.getAll:(Ljava/util/List;)Ljava/util/concurrent/CompletableFuture;
     367: invokevirtual #27                 // Method java/util/concurrent/CompletableFuture.get:()Ljava/lang/Object;
     370: checkcast     #48                 // class java/util/List
     373: astore_2
     374: getstatic     #42                 // Field COUNT:I
     377: i2l
     378: aload_2
     379: invokeinterface #54,  1           // InterfaceMethod java/util/List.size:()I
     384: i2l
     385: invokestatic  #55                 // Method org/junit/Assert.assertEquals:(JJ)V
     388: aload_2
     389: invokedynamic #80,  0             // InvokeDynamic #8:accept:()Ljava/util/function/Consumer;
     394: invokeinterface #81,  2           // InterfaceMethod java/util/List.forEach:(Ljava/util/function/Consumer;)V
     399: return

  public void testWithRegionServerFailover() throws java.lang.Exception;
    Code:
       0: aload_0
       1: getfield      #39                 // Field tableGetter:Ljava/util/function/Function;
       4: getstatic     #31                 // Field TABLE_NAME:Lorg/apache/hadoop/hbase/TableName;
       7: invokeinterface #40,  2           // InterfaceMethod java/util/function/Function.apply:(Ljava/lang/Object;)Ljava/lang/Object;
      12: checkcast     #41                 // class org/apache/hadoop/hbase/client/AsyncTable
      15: astore_1
      16: aload_1
      17: iconst_0
      18: getstatic     #42                 // Field COUNT:I
      21: invokestatic  #43                 // InterfaceMethod java/util/stream/IntStream.range:(II)Ljava/util/stream/IntStream;
      24: aload_0
      25: invokedynamic #82,  0             // InvokeDynamic #9:apply:(Lorg/apache/hadoop/hbase/client/TestAsyncTableBatch;)Ljava/util/function/IntFunction;
      30: invokeinterface #45,  2           // InterfaceMethod java/util/stream/IntStream.mapToObj:(Ljava/util/function/IntFunction;)Ljava/util/stream/Stream;
      35: invokestatic  #46                 // Method java/util/stream/Collectors.toList:()Ljava/util/stream/Collector;
      38: invokeinterface #47,  2           // InterfaceMethod java/util/stream/Stream.collect:(Ljava/util/stream/Collector;)Ljava/lang/Object;
      43: checkcast     #48                 // class java/util/List
      46: invokeinterface #49,  2           // InterfaceMethod org/apache/hadoop/hbase/client/AsyncTable.putAll:(Ljava/util/List;)Ljava/util/concurrent/CompletableFuture;
      51: invokevirtual #27                 // Method java/util/concurrent/CompletableFuture.get:()Ljava/lang/Object;
      54: pop
      55: getstatic     #13                 // Field TEST_UTIL:Lorg/apache/hadoop/hbase/HBaseTestingUtility;
      58: invokevirtual #83                 // Method org/apache/hadoop/hbase/HBaseTestingUtility.getMiniHBaseCluster:()Lorg/apache/hadoop/hbase/MiniHBaseCluster;
      61: iconst_0
      62: invokevirtual #84                 // Method org/apache/hadoop/hbase/MiniHBaseCluster.getRegionServer:(I)Lorg/apache/hadoop/hbase/regionserver/HRegionServer;
      65: ldc           #85                 // String Aborting for tests
      67: invokevirtual #86                 // Method org/apache/hadoop/hbase/regionserver/HRegionServer.abort:(Ljava/lang/String;)V
      70: ldc2_w        #87                 // long 100l
      73: invokestatic  #89                 // Method java/lang/Thread.sleep:(J)V
      76: aload_1
      77: getstatic     #42                 // Field COUNT:I
      80: iconst_2
      81: getstatic     #42                 // Field COUNT:I
      84: imul
      85: invokestatic  #43                 // InterfaceMethod java/util/stream/IntStream.range:(II)Ljava/util/stream/IntStream;
      88: aload_0
      89: invokedynamic #90,  0             // InvokeDynamic #10:apply:(Lorg/apache/hadoop/hbase/client/TestAsyncTableBatch;)Ljava/util/function/IntFunction;
      94: invokeinterface #45,  2           // InterfaceMethod java/util/stream/IntStream.mapToObj:(Ljava/util/function/IntFunction;)Ljava/util/stream/Stream;
      99: invokestatic  #46                 // Method java/util/stream/Collectors.toList:()Ljava/util/stream/Collector;
     102: invokeinterface #47,  2           // InterfaceMethod java/util/stream/Stream.collect:(Ljava/util/stream/Collector;)Ljava/lang/Object;
     107: checkcast     #48                 // class java/util/List
     110: invokeinterface #49,  2           // InterfaceMethod org/apache/hadoop/hbase/client/AsyncTable.putAll:(Ljava/util/List;)Ljava/util/concurrent/CompletableFuture;
     115: invokevirtual #27                 // Method java/util/concurrent/CompletableFuture.get:()Ljava/lang/Object;
     118: pop
     119: aload_1
     120: iconst_0
     121: iconst_2
     122: getstatic     #42                 // Field COUNT:I
     125: imul
     126: invokestatic  #43                 // InterfaceMethod java/util/stream/IntStream.range:(II)Ljava/util/stream/IntStream;
     129: aload_0
     130: invokedynamic #91,  0             // InvokeDynamic #11:apply:(Lorg/apache/hadoop/hbase/client/TestAsyncTableBatch;)Ljava/util/function/IntFunction;
     135: invokeinterface #45,  2           // InterfaceMethod java/util/stream/IntStream.mapToObj:(Ljava/util/function/IntFunction;)Ljava/util/stream/Stream;
     140: invokestatic  #46                 // Method java/util/stream/Collectors.toList:()Ljava/util/stream/Collector;
     143: invokeinterface #47,  2           // InterfaceMethod java/util/stream/Stream.collect:(Ljava/util/stream/Collector;)Ljava/lang/Object;
     148: checkcast     #48                 // class java/util/List
     151: invokeinterface #53,  2           // InterfaceMethod org/apache/hadoop/hbase/client/AsyncTable.getAll:(Ljava/util/List;)Ljava/util/concurrent/CompletableFuture;
     156: invokevirtual #27                 // Method java/util/concurrent/CompletableFuture.get:()Ljava/lang/Object;
     159: checkcast     #48                 // class java/util/List
     162: astore_2
     163: iconst_2
     164: getstatic     #42                 // Field COUNT:I
     167: imul
     168: i2l
     169: aload_2
     170: invokeinterface #54,  1           // InterfaceMethod java/util/List.size:()I
     175: i2l
     176: invokestatic  #55                 // Method org/junit/Assert.assertEquals:(JJ)V
     179: aload_2
     180: invokedynamic #92,  0             // InvokeDynamic #12:accept:()Ljava/util/function/Consumer;
     185: invokeinterface #81,  2           // InterfaceMethod java/util/List.forEach:(Ljava/util/function/Consumer;)V
     190: aload_1
     191: iconst_0
     192: iconst_2
     193: getstatic     #42                 // Field COUNT:I
     196: imul
     197: invokestatic  #43                 // InterfaceMethod java/util/stream/IntStream.range:(II)Ljava/util/stream/IntStream;
     200: aload_0
     201: invokedynamic #93,  0             // InvokeDynamic #13:apply:(Lorg/apache/hadoop/hbase/client/TestAsyncTableBatch;)Ljava/util/function/IntFunction;
     206: invokeinterface #45,  2           // InterfaceMethod java/util/stream/IntStream.mapToObj:(Ljava/util/function/IntFunction;)Ljava/util/stream/Stream;
     211: invokestatic  #46                 // Method java/util/stream/Collectors.toList:()Ljava/util/stream/Collector;
     214: invokeinterface #47,  2           // InterfaceMethod java/util/stream/Stream.collect:(Ljava/util/stream/Collector;)Ljava/lang/Object;
     219: checkcast     #48                 // class java/util/List
     222: invokeinterface #78,  2           // InterfaceMethod org/apache/hadoop/hbase/client/AsyncTable.deleteAll:(Ljava/util/List;)Ljava/util/concurrent/CompletableFuture;
     227: invokevirtual #27                 // Method java/util/concurrent/CompletableFuture.get:()Ljava/lang/Object;
     230: pop
     231: aload_1
     232: iconst_0
     233: iconst_2
     234: getstatic     #42                 // Field COUNT:I
     237: imul
     238: invokestatic  #43                 // InterfaceMethod java/util/stream/IntStream.range:(II)Ljava/util/stream/IntStream;
     241: aload_0
     242: invokedynamic #94,  0             // InvokeDynamic #14:apply:(Lorg/apache/hadoop/hbase/client/TestAsyncTableBatch;)Ljava/util/function/IntFunction;
     247: invokeinterface #45,  2           // InterfaceMethod java/util/stream/IntStream.mapToObj:(Ljava/util/function/IntFunction;)Ljava/util/stream/Stream;
     252: invokestatic  #46                 // Method java/util/stream/Collectors.toList:()Ljava/util/stream/Collector;
     255: invokeinterface #47,  2           // InterfaceMethod java/util/stream/Stream.collect:(Ljava/util/stream/Collector;)Ljava/lang/Object;
     260: checkcast     #48                 // class java/util/List
     263: invokeinterface #53,  2           // InterfaceMethod org/apache/hadoop/hbase/client/AsyncTable.getAll:(Ljava/util/List;)Ljava/util/concurrent/CompletableFuture;
     268: invokevirtual #27                 // Method java/util/concurrent/CompletableFuture.get:()Ljava/lang/Object;
     271: checkcast     #48                 // class java/util/List
     274: astore_2
     275: iconst_2
     276: getstatic     #42                 // Field COUNT:I
     279: imul
     280: i2l
     281: aload_2
     282: invokeinterface #54,  1           // InterfaceMethod java/util/List.size:()I
     287: i2l
     288: invokestatic  #55                 // Method org/junit/Assert.assertEquals:(JJ)V
     291: aload_2
     292: invokedynamic #95,  0             // InvokeDynamic #15:accept:()Ljava/util/function/Consumer;
     297: invokeinterface #81,  2           // InterfaceMethod java/util/List.forEach:(Ljava/util/function/Consumer;)V
     302: return

  public void testMixed() throws java.lang.InterruptedException, java.util.concurrent.ExecutionException, java.io.IOException;
    Code:
       0: aload_0
       1: getfield      #39                 // Field tableGetter:Ljava/util/function/Function;
       4: getstatic     #31                 // Field TABLE_NAME:Lorg/apache/hadoop/hbase/TableName;
       7: invokeinterface #40,  2           // InterfaceMethod java/util/function/Function.apply:(Ljava/lang/Object;)Ljava/lang/Object;
      12: checkcast     #41                 // class org/apache/hadoop/hbase/client/AsyncTable
      15: astore_1
      16: aload_1
      17: iconst_0
      18: bipush        7
      20: invokestatic  #43                 // InterfaceMethod java/util/stream/IntStream.range:(II)Ljava/util/stream/IntStream;
      23: invokedynamic #96,  0             // InvokeDynamic #16:apply:()Ljava/util/function/IntFunction;
      28: invokeinterface #45,  2           // InterfaceMethod java/util/stream/IntStream.mapToObj:(Ljava/util/function/IntFunction;)Ljava/util/stream/Stream;
      33: invokestatic  #46                 // Method java/util/stream/Collectors.toList:()Ljava/util/stream/Collector;
      36: invokeinterface #47,  2           // InterfaceMethod java/util/stream/Stream.collect:(Ljava/util/stream/Collector;)Ljava/lang/Object;
      41: checkcast     #48                 // class java/util/List
      44: invokeinterface #49,  2           // InterfaceMethod org/apache/hadoop/hbase/client/AsyncTable.putAll:(Ljava/util/List;)Ljava/util/concurrent/CompletableFuture;
      49: invokevirtual #27                 // Method java/util/concurrent/CompletableFuture.get:()Ljava/lang/Object;
      52: pop
      53: new           #97                 // class java/util/ArrayList
      56: dup
      57: invokespecial #98                 // Method java/util/ArrayList."<init>":()V
      60: astore_2
      61: aload_2
      62: new           #99                 // class org/apache/hadoop/hbase/client/Get
      65: dup
      66: iconst_0
      67: invokestatic  #100                // Method org/apache/hadoop/hbase/util/Bytes.toBytes:(I)[B
      70: invokespecial #101                // Method org/apache/hadoop/hbase/client/Get."<init>":([B)V
      73: invokeinterface #102,  2          // InterfaceMethod java/util/List.add:(Ljava/lang/Object;)Z
      78: pop
      79: aload_2
      80: new           #103                // class org/apache/hadoop/hbase/client/Put
      83: dup
      84: iconst_1
      85: invokestatic  #100                // Method org/apache/hadoop/hbase/util/Bytes.toBytes:(I)[B
      88: invokespecial #104                // Method org/apache/hadoop/hbase/client/Put."<init>":([B)V
      91: getstatic     #32                 // Field FAMILY:[B
      94: getstatic     #58                 // Field CQ:[B
      97: ldc2_w        #105                // long 2l
     100: invokestatic  #107                // Method org/apache/hadoop/hbase/util/Bytes.toBytes:(J)[B
     103: invokevirtual #108                // Method org/apache/hadoop/hbase/client/Put.addColumn:([B[B[B)Lorg/apache/hadoop/hbase/client/Put;
     106: invokeinterface #102,  2          // InterfaceMethod java/util/List.add:(Ljava/lang/Object;)Z
     111: pop
     112: aload_2
     113: new           #109                // class org/apache/hadoop/hbase/client/Delete
     116: dup
     117: iconst_2
     118: invokestatic  #100                // Method org/apache/hadoop/hbase/util/Bytes.toBytes:(I)[B
     121: invokespecial #110                // Method org/apache/hadoop/hbase/client/Delete."<init>":([B)V
     124: invokeinterface #102,  2          // InterfaceMethod java/util/List.add:(Ljava/lang/Object;)Z
     129: pop
     130: aload_2
     131: new           #111                // class org/apache/hadoop/hbase/client/Increment
     134: dup
     135: iconst_3
     136: invokestatic  #100                // Method org/apache/hadoop/hbase/util/Bytes.toBytes:(I)[B
     139: invokespecial #112                // Method org/apache/hadoop/hbase/client/Increment."<init>":([B)V
     142: getstatic     #32                 // Field FAMILY:[B
     145: getstatic     #58                 // Field CQ:[B
     148: lconst_1
     149: invokevirtual #113                // Method org/apache/hadoop/hbase/client/Increment.addColumn:([B[BJ)Lorg/apache/hadoop/hbase/client/Increment;
     152: invokeinterface #102,  2          // InterfaceMethod java/util/List.add:(Ljava/lang/Object;)Z
     157: pop
     158: aload_2
     159: new           #114                // class org/apache/hadoop/hbase/client/Append
     162: dup
     163: iconst_4
     164: invokestatic  #100                // Method org/apache/hadoop/hbase/util/Bytes.toBytes:(I)[B
     167: invokespecial #115                // Method org/apache/hadoop/hbase/client/Append."<init>":([B)V
     170: getstatic     #32                 // Field FAMILY:[B
     173: getstatic     #58                 // Field CQ:[B
     176: iconst_4
     177: invokestatic  #100                // Method org/apache/hadoop/hbase/util/Bytes.toBytes:(I)[B
     180: invokevirtual #116                // Method org/apache/hadoop/hbase/client/Append.addColumn:([B[B[B)Lorg/apache/hadoop/hbase/client/Append;
     183: invokeinterface #102,  2          // InterfaceMethod java/util/List.add:(Ljava/lang/Object;)Z
     188: pop
     189: new           #117                // class org/apache/hadoop/hbase/client/RowMutations
     192: dup
     193: iconst_5
     194: invokestatic  #100                // Method org/apache/hadoop/hbase/util/Bytes.toBytes:(I)[B
     197: invokespecial #118                // Method org/apache/hadoop/hbase/client/RowMutations."<init>":([B)V
     200: astore_3
     201: aload_3
     202: new           #103                // class org/apache/hadoop/hbase/client/Put
     205: dup
     206: iconst_5
     207: invokestatic  #100                // Method org/apache/hadoop/hbase/util/Bytes.toBytes:(I)[B
     210: invokespecial #104                // Method org/apache/hadoop/hbase/client/Put."<init>":([B)V
     213: getstatic     #32                 // Field FAMILY:[B
     216: getstatic     #58                 // Field CQ:[B
     219: ldc2_w        #87                 // long 100l
     222: invokestatic  #107                // Method org/apache/hadoop/hbase/util/Bytes.toBytes:(J)[B
     225: invokevirtual #108                // Method org/apache/hadoop/hbase/client/Put.addColumn:([B[B[B)Lorg/apache/hadoop/hbase/client/Put;
     228: invokevirtual #119                // Method org/apache/hadoop/hbase/client/RowMutations.add:(Lorg/apache/hadoop/hbase/client/Mutation;)Lorg/apache/hadoop/hbase/client/RowMutations;
     231: pop
     232: aload_3
     233: new           #103                // class org/apache/hadoop/hbase/client/Put
     236: dup
     237: iconst_5
     238: invokestatic  #100                // Method org/apache/hadoop/hbase/util/Bytes.toBytes:(I)[B
     241: invokespecial #104                // Method org/apache/hadoop/hbase/client/Put."<init>":([B)V
     244: getstatic     #32                 // Field FAMILY:[B
     247: getstatic     #120                // Field CQ1:[B
     250: ldc2_w        #121                // long 200l
     253: invokestatic  #107                // Method org/apache/hadoop/hbase/util/Bytes.toBytes:(J)[B
     256: invokevirtual #108                // Method org/apache/hadoop/hbase/client/Put.addColumn:([B[B[B)Lorg/apache/hadoop/hbase/client/Put;
     259: invokevirtual #119                // Method org/apache/hadoop/hbase/client/RowMutations.add:(Lorg/apache/hadoop/hbase/client/Mutation;)Lorg/apache/hadoop/hbase/client/RowMutations;
     262: pop
     263: aload_2
     264: aload_3
     265: invokeinterface #102,  2          // InterfaceMethod java/util/List.add:(Ljava/lang/Object;)Z
     270: pop
     271: aload_2
     272: new           #99                 // class org/apache/hadoop/hbase/client/Get
     275: dup
     276: bipush        6
     278: invokestatic  #100                // Method org/apache/hadoop/hbase/util/Bytes.toBytes:(I)[B
     281: invokespecial #101                // Method org/apache/hadoop/hbase/client/Get."<init>":([B)V
     284: invokeinterface #102,  2          // InterfaceMethod java/util/List.add:(Ljava/lang/Object;)Z
     289: pop
     290: aload_1
     291: aload_2
     292: invokeinterface #123,  2          // InterfaceMethod org/apache/hadoop/hbase/client/AsyncTable.batchAll:(Ljava/util/List;)Ljava/util/concurrent/CompletableFuture;
     297: invokevirtual #27                 // Method java/util/concurrent/CompletableFuture.get:()Ljava/lang/Object;
     300: checkcast     #48                 // class java/util/List
     303: astore        4
     305: ldc2_w        #124                // long 7l
     308: aload         4
     310: invokeinterface #54,  1           // InterfaceMethod java/util/List.size:()I
     315: i2l
     316: invokestatic  #55                 // Method org/junit/Assert.assertEquals:(JJ)V
     319: aload         4
     321: iconst_0
     322: invokeinterface #56,  2           // InterfaceMethod java/util/List.get:(I)Ljava/lang/Object;
     327: checkcast     #57                 // class org/apache/hadoop/hbase/client/Result
     330: astore        5
     332: lconst_0
     333: aload         5
     335: getstatic     #32                 // Field FAMILY:[B
     338: getstatic     #58                 // Field CQ:[B
     341: invokevirtual #59                 // Method org/apache/hadoop/hbase/client/Result.getValue:([B[B)[B
     344: invokestatic  #126                // Method org/apache/hadoop/hbase/util/Bytes.toLong:([B)J
     347: invokestatic  #55                 // Method org/junit/Assert.assertEquals:(JJ)V
     350: ldc2_w        #105                // long 2l
     353: aload_1
     354: new           #99                 // class org/apache/hadoop/hbase/client/Get
     357: dup
     358: iconst_1
     359: invokestatic  #100                // Method org/apache/hadoop/hbase/util/Bytes.toBytes:(I)[B
     362: invokespecial #101                // Method org/apache/hadoop/hbase/client/Get."<init>":([B)V
     365: invokeinterface #127,  2          // InterfaceMethod org/apache/hadoop/hbase/client/AsyncTable.get:(Lorg/apache/hadoop/hbase/client/Get;)Ljava/util/concurrent/CompletableFuture;
     370: invokevirtual #27                 // Method java/util/concurrent/CompletableFuture.get:()Ljava/lang/Object;
     373: checkcast     #57                 // class org/apache/hadoop/hbase/client/Result
     376: getstatic     #32                 // Field FAMILY:[B
     379: getstatic     #58                 // Field CQ:[B
     382: invokevirtual #59                 // Method org/apache/hadoop/hbase/client/Result.getValue:([B[B)[B
     385: invokestatic  #126                // Method org/apache/hadoop/hbase/util/Bytes.toLong:([B)J
     388: invokestatic  #55                 // Method org/junit/Assert.assertEquals:(JJ)V
     391: aload_1
     392: new           #99                 // class org/apache/hadoop/hbase/client/Get
     395: dup
     396: iconst_2
     397: invokestatic  #100                // Method org/apache/hadoop/hbase/util/Bytes.toBytes:(I)[B
     400: invokespecial #101                // Method org/apache/hadoop/hbase/client/Get."<init>":([B)V
     403: invokeinterface #127,  2          // InterfaceMethod org/apache/hadoop/hbase/client/AsyncTable.get:(Lorg/apache/hadoop/hbase/client/Get;)Ljava/util/concurrent/CompletableFuture;
     408: invokevirtual #27                 // Method java/util/concurrent/CompletableFuture.get:()Ljava/lang/Object;
     411: checkcast     #57                 // class org/apache/hadoop/hbase/client/Result
     414: invokevirtual #61                 // Method org/apache/hadoop/hbase/client/Result.isEmpty:()Z
     417: invokestatic  #62                 // Method org/junit/Assert.assertTrue:(Z)V
     420: aload         4
     422: iconst_3
     423: invokeinterface #56,  2           // InterfaceMethod java/util/List.get:(I)Ljava/lang/Object;
     428: checkcast     #57                 // class org/apache/hadoop/hbase/client/Result
     431: astore        6
     433: ldc2_w        #128                // long 4l
     436: aload         6
     438: getstatic     #32                 // Field FAMILY:[B
     441: getstatic     #58                 // Field CQ:[B
     444: invokevirtual #59                 // Method org/apache/hadoop/hbase/client/Result.getValue:([B[B)[B
     447: invokestatic  #126                // Method org/apache/hadoop/hbase/util/Bytes.toLong:([B)J
     450: invokestatic  #55                 // Method org/junit/Assert.assertEquals:(JJ)V
     453: aload         4
     455: iconst_4
     456: invokeinterface #56,  2           // InterfaceMethod java/util/List.get:(I)Ljava/lang/Object;
     461: checkcast     #57                 // class org/apache/hadoop/hbase/client/Result
     464: astore        7
     466: aload         7
     468: getstatic     #32                 // Field FAMILY:[B
     471: getstatic     #58                 // Field CQ:[B
     474: invokevirtual #59                 // Method org/apache/hadoop/hbase/client/Result.getValue:([B[B)[B
     477: astore        8
     479: ldc2_w        #130                // long 12l
     482: aload         8
     484: arraylength
     485: i2l
     486: invokestatic  #55                 // Method org/junit/Assert.assertEquals:(JJ)V
     489: ldc2_w        #128                // long 4l
     492: aload         8
     494: invokestatic  #126                // Method org/apache/hadoop/hbase/util/Bytes.toLong:([B)J
     497: invokestatic  #55                 // Method org/junit/Assert.assertEquals:(JJ)V
     500: ldc2_w        #128                // long 4l
     503: aload         8
     505: bipush        8
     507: invokestatic  #132                // Method org/apache/hadoop/hbase/util/Bytes.toInt:([BI)I
     510: i2l
     511: invokestatic  #55                 // Method org/junit/Assert.assertEquals:(JJ)V
     514: ldc2_w        #87                 // long 100l
     517: aload_1
     518: new           #99                 // class org/apache/hadoop/hbase/client/Get
     521: dup
     522: iconst_5
     523: invokestatic  #100                // Method org/apache/hadoop/hbase/util/Bytes.toBytes:(I)[B
     526: invokespecial #101                // Method org/apache/hadoop/hbase/client/Get."<init>":([B)V
     529: invokeinterface #127,  2          // InterfaceMethod org/apache/hadoop/hbase/client/AsyncTable.get:(Lorg/apache/hadoop/hbase/client/Get;)Ljava/util/concurrent/CompletableFuture;
     534: invokevirtual #27                 // Method java/util/concurrent/CompletableFuture.get:()Ljava/lang/Object;
     537: checkcast     #57                 // class org/apache/hadoop/hbase/client/Result
     540: getstatic     #32                 // Field FAMILY:[B
     543: getstatic     #58                 // Field CQ:[B
     546: invokevirtual #59                 // Method org/apache/hadoop/hbase/client/Result.getValue:([B[B)[B
     549: invokestatic  #126                // Method org/apache/hadoop/hbase/util/Bytes.toLong:([B)J
     552: invokestatic  #55                 // Method org/junit/Assert.assertEquals:(JJ)V
     555: ldc2_w        #121                // long 200l
     558: aload_1
     559: new           #99                 // class org/apache/hadoop/hbase/client/Get
     562: dup
     563: iconst_5
     564: invokestatic  #100                // Method org/apache/hadoop/hbase/util/Bytes.toBytes:(I)[B
     567: invokespecial #101                // Method org/apache/hadoop/hbase/client/Get."<init>":([B)V
     570: invokeinterface #127,  2          // InterfaceMethod org/apache/hadoop/hbase/client/AsyncTable.get:(Lorg/apache/hadoop/hbase/client/Get;)Ljava/util/concurrent/CompletableFuture;
     575: invokevirtual #27                 // Method java/util/concurrent/CompletableFuture.get:()Ljava/lang/Object;
     578: checkcast     #57                 // class org/apache/hadoop/hbase/client/Result
     581: getstatic     #32                 // Field FAMILY:[B
     584: getstatic     #120                // Field CQ1:[B
     587: invokevirtual #59                 // Method org/apache/hadoop/hbase/client/Result.getValue:([B[B)[B
     590: invokestatic  #126                // Method org/apache/hadoop/hbase/util/Bytes.toLong:([B)J
     593: invokestatic  #55                 // Method org/junit/Assert.assertEquals:(JJ)V
     596: aload         4
     598: bipush        6
     600: invokeinterface #56,  2           // InterfaceMethod java/util/List.get:(I)Ljava/lang/Object;
     605: checkcast     #57                 // class org/apache/hadoop/hbase/client/Result
     608: astore        5
     610: ldc2_w        #133                // long 6l
     613: aload         5
     615: getstatic     #32                 // Field FAMILY:[B
     618: getstatic     #58                 // Field CQ:[B
     621: invokevirtual #59                 // Method org/apache/hadoop/hbase/client/Result.getValue:([B[B)[B
     624: invokestatic  #126                // Method org/apache/hadoop/hbase/util/Bytes.toLong:([B)J
     627: invokestatic  #55                 // Method org/junit/Assert.assertEquals:(JJ)V
     630: return

  public void testPartialSuccess() throws java.io.IOException, java.lang.InterruptedException, java.util.concurrent.ExecutionException;
    Code:
       0: getstatic     #13                 // Field TEST_UTIL:Lorg/apache/hadoop/hbase/HBaseTestingUtility;
       3: invokevirtual #35                 // Method org/apache/hadoop/hbase/HBaseTestingUtility.getAdmin:()Lorg/apache/hadoop/hbase/client/Admin;
       6: astore_1
       7: aload_1
       8: getstatic     #31                 // Field TABLE_NAME:Lorg/apache/hadoop/hbase/TableName;
      11: invokeinterface #135,  2          // InterfaceMethod org/apache/hadoop/hbase/client/Admin.getDescriptor:(Lorg/apache/hadoop/hbase/TableName;)Lorg/apache/hadoop/hbase/client/TableDescriptor;
      16: invokestatic  #136                // Method org/apache/hadoop/hbase/client/TableDescriptorBuilder.newBuilder:(Lorg/apache/hadoop/hbase/client/TableDescriptor;)Lorg/apache/hadoop/hbase/client/TableDescriptorBuilder;
      19: ldc           #137                // class org/apache/hadoop/hbase/client/TestAsyncTableBatch$ErrorInjectObserver
      21: invokevirtual #138                // Method java/lang/Class.getName:()Ljava/lang/String;
      24: invokevirtual #139                // Method org/apache/hadoop/hbase/client/TableDescriptorBuilder.setCoprocessor:(Ljava/lang/String;)Lorg/apache/hadoop/hbase/client/TableDescriptorBuilder;
      27: invokevirtual #140                // Method org/apache/hadoop/hbase/client/TableDescriptorBuilder.build:()Lorg/apache/hadoop/hbase/client/TableDescriptor;
      30: astore_2
      31: aload_1
      32: aload_2
      33: invokeinterface #141,  2          // InterfaceMethod org/apache/hadoop/hbase/client/Admin.modifyTable:(Lorg/apache/hadoop/hbase/client/TableDescriptor;)V
      38: aload_0
      39: getfield      #39                 // Field tableGetter:Ljava/util/function/Function;
      42: getstatic     #31                 // Field TABLE_NAME:Lorg/apache/hadoop/hbase/TableName;
      45: invokeinterface #40,  2           // InterfaceMethod java/util/function/Function.apply:(Ljava/lang/Object;)Ljava/lang/Object;
      50: checkcast     #41                 // class org/apache/hadoop/hbase/client/AsyncTable
      53: astore_3
      54: aload_3
      55: getstatic     #21                 // Field SPLIT_KEYS:[[B
      58: invokestatic  #12                 // Method java/util/Arrays.asList:([Ljava/lang/Object;)Ljava/util/List;
      61: invokeinterface #66,  1           // InterfaceMethod java/util/List.stream:()Ljava/util/stream/Stream;
      66: invokedynamic #142,  0            // InvokeDynamic #17:apply:()Ljava/util/function/Function;
      71: invokeinterface #68,  2           // InterfaceMethod java/util/stream/Stream.map:(Ljava/util/function/Function;)Ljava/util/stream/Stream;
      76: invokestatic  #46                 // Method java/util/stream/Collectors.toList:()Ljava/util/stream/Collector;
      79: invokeinterface #47,  2           // InterfaceMethod java/util/stream/Stream.collect:(Ljava/util/stream/Collector;)Ljava/lang/Object;
      84: checkcast     #48                 // class java/util/List
      87: invokeinterface #49,  2           // InterfaceMethod org/apache/hadoop/hbase/client/AsyncTable.putAll:(Ljava/util/List;)Ljava/util/concurrent/CompletableFuture;
      92: invokevirtual #27                 // Method java/util/concurrent/CompletableFuture.get:()Ljava/lang/Object;
      95: pop
      96: aload_3
      97: getstatic     #21                 // Field SPLIT_KEYS:[[B
     100: invokestatic  #12                 // Method java/util/Arrays.asList:([Ljava/lang/Object;)Ljava/util/List;
     103: invokeinterface #66,  1           // InterfaceMethod java/util/List.stream:()Ljava/util/stream/Stream;
     108: invokedynamic #143,  0            // InvokeDynamic #18:apply:()Ljava/util/function/Function;
     113: invokeinterface #68,  2           // InterfaceMethod java/util/stream/Stream.map:(Ljava/util/function/Function;)Ljava/util/stream/Stream;
     118: invokestatic  #46                 // Method java/util/stream/Collectors.toList:()Ljava/util/stream/Collector;
     121: invokeinterface #47,  2           // InterfaceMethod java/util/stream/Stream.collect:(Ljava/util/stream/Collector;)Ljava/lang/Object;
     126: checkcast     #48                 // class java/util/List
     129: invokeinterface #144,  2          // InterfaceMethod org/apache/hadoop/hbase/client/AsyncTable.get:(Ljava/util/List;)Ljava/util/List;
     134: astore        4
     136: iconst_0
     137: istore        5
     139: iload         5
     141: getstatic     #21                 // Field SPLIT_KEYS:[[B
     144: arraylength
     145: iconst_1
     146: isub
     147: if_icmpge     192
     150: getstatic     #21                 // Field SPLIT_KEYS:[[B
     153: iload         5
     155: aaload
     156: aload         4
     158: iload         5
     160: invokeinterface #56,  2           // InterfaceMethod java/util/List.get:(I)Ljava/lang/Object;
     165: checkcast     #145                // class java/util/concurrent/CompletableFuture
     168: invokevirtual #27                 // Method java/util/concurrent/CompletableFuture.get:()Ljava/lang/Object;
     171: checkcast     #57                 // class org/apache/hadoop/hbase/client/Result
     174: getstatic     #32                 // Field FAMILY:[B
     177: getstatic     #58                 // Field CQ:[B
     180: invokevirtual #59                 // Method org/apache/hadoop/hbase/client/Result.getValue:([B[B)[B
     183: invokestatic  #146                // Method org/junit/Assert.assertArrayEquals:([B[B)V
     186: iinc          5, 1
     189: goto          139
     192: aload         4
     194: getstatic     #21                 // Field SPLIT_KEYS:[[B
     197: arraylength
     198: iconst_1
     199: isub
     200: invokeinterface #56,  2           // InterfaceMethod java/util/List.get:(I)Ljava/lang/Object;
     205: checkcast     #145                // class java/util/concurrent/CompletableFuture
     208: invokevirtual #27                 // Method java/util/concurrent/CompletableFuture.get:()Ljava/lang/Object;
     211: pop
     212: invokestatic  #147                // Method org/junit/Assert.fail:()V
     215: goto          233
     218: astore        5
     220: aload         5
     222: invokevirtual #149                // Method java/util/concurrent/ExecutionException.getCause:()Ljava/lang/Throwable;
     225: ldc           #150                // class org/apache/hadoop/hbase/client/RetriesExhaustedException
     227: invokestatic  #151                // Method org/hamcrest/CoreMatchers.instanceOf:(Ljava/lang/Class;)Lorg/hamcrest/Matcher;
     230: invokestatic  #152                // Method org/junit/Assert.assertThat:(Ljava/lang/Object;Lorg/hamcrest/Matcher;)V
     233: return
    Exception table:
       from    to  target type
         192   215   218   Class java/util/concurrent/ExecutionException

  public void testPartialSuccessOnSameRegion() throws java.lang.InterruptedException, java.util.concurrent.ExecutionException;
    Code:
       0: aload_0
       1: getfield      #39                 // Field tableGetter:Ljava/util/function/Function;
       4: getstatic     #31                 // Field TABLE_NAME:Lorg/apache/hadoop/hbase/TableName;
       7: invokeinterface #40,  2           // InterfaceMethod java/util/function/Function.apply:(Ljava/lang/Object;)Ljava/lang/Object;
      12: checkcast     #41                 // class org/apache/hadoop/hbase/client/AsyncTable
      15: astore_1
      16: aload_1
      17: iconst_3
      18: anewarray     #153                // class org/apache/hadoop/hbase/client/Mutation
      21: dup
      22: iconst_0
      23: new           #103                // class org/apache/hadoop/hbase/client/Put
      26: dup
      27: ldc           #154                // String put
      29: invokestatic  #25                 // Method org/apache/hadoop/hbase/util/Bytes.toBytes:(Ljava/lang/String;)[B
      32: invokespecial #104                // Method org/apache/hadoop/hbase/client/Put."<init>":([B)V
      35: ldc           #155                // String not-exists
      37: invokestatic  #25                 // Method org/apache/hadoop/hbase/util/Bytes.toBytes:(Ljava/lang/String;)[B
      40: getstatic     #58                 // Field CQ:[B
      43: ldc           #156                // String bad
      45: invokestatic  #25                 // Method org/apache/hadoop/hbase/util/Bytes.toBytes:(Ljava/lang/String;)[B
      48: invokevirtual #108                // Method org/apache/hadoop/hbase/client/Put.addColumn:([B[B[B)Lorg/apache/hadoop/hbase/client/Put;
      51: aastore
      52: dup
      53: iconst_1
      54: new           #111                // class org/apache/hadoop/hbase/client/Increment
      57: dup
      58: ldc           #157                // String inc
      60: invokestatic  #25                 // Method org/apache/hadoop/hbase/util/Bytes.toBytes:(Ljava/lang/String;)[B
      63: invokespecial #112                // Method org/apache/hadoop/hbase/client/Increment."<init>":([B)V
      66: getstatic     #32                 // Field FAMILY:[B
      69: getstatic     #58                 // Field CQ:[B
      72: lconst_1
      73: invokevirtual #113                // Method org/apache/hadoop/hbase/client/Increment.addColumn:([B[BJ)Lorg/apache/hadoop/hbase/client/Increment;
      76: aastore
      77: dup
      78: iconst_2
      79: new           #103                // class org/apache/hadoop/hbase/client/Put
      82: dup
      83: ldc           #154                // String put
      85: invokestatic  #25                 // Method org/apache/hadoop/hbase/util/Bytes.toBytes:(Ljava/lang/String;)[B
      88: invokespecial #104                // Method org/apache/hadoop/hbase/client/Put."<init>":([B)V
      91: getstatic     #32                 // Field FAMILY:[B
      94: getstatic     #58                 // Field CQ:[B
      97: ldc           #158                // String good
      99: invokestatic  #25                 // Method org/apache/hadoop/hbase/util/Bytes.toBytes:(Ljava/lang/String;)[B
     102: invokevirtual #108                // Method org/apache/hadoop/hbase/client/Put.addColumn:([B[B[B)Lorg/apache/hadoop/hbase/client/Put;
     105: aastore
     106: invokestatic  #12                 // Method java/util/Arrays.asList:([Ljava/lang/Object;)Ljava/util/List;
     109: invokeinterface #159,  2          // InterfaceMethod org/apache/hadoop/hbase/client/AsyncTable.batch:(Ljava/util/List;)Ljava/util/List;
     114: astore_2
     115: aload_2
     116: iconst_0
     117: invokeinterface #56,  2           // InterfaceMethod java/util/List.get:(I)Ljava/lang/Object;
     122: checkcast     #145                // class java/util/concurrent/CompletableFuture
     125: invokevirtual #27                 // Method java/util/concurrent/CompletableFuture.get:()Ljava/lang/Object;
     128: pop
     129: invokestatic  #147                // Method org/junit/Assert.fail:()V
     132: goto          163
     135: astore_3
     136: aload_3
     137: invokevirtual #149                // Method java/util/concurrent/ExecutionException.getCause:()Ljava/lang/Throwable;
     140: ldc           #150                // class org/apache/hadoop/hbase/client/RetriesExhaustedException
     142: invokestatic  #151                // Method org/hamcrest/CoreMatchers.instanceOf:(Ljava/lang/Class;)Lorg/hamcrest/Matcher;
     145: invokestatic  #152                // Method org/junit/Assert.assertThat:(Ljava/lang/Object;Lorg/hamcrest/Matcher;)V
     148: aload_3
     149: invokevirtual #149                // Method java/util/concurrent/ExecutionException.getCause:()Ljava/lang/Throwable;
     152: invokevirtual #160                // Method java/lang/Throwable.getCause:()Ljava/lang/Throwable;
     155: ldc           #161                // class org/apache/hadoop/hbase/regionserver/NoSuchColumnFamilyException
     157: invokestatic  #151                // Method org/hamcrest/CoreMatchers.instanceOf:(Ljava/lang/Class;)Lorg/hamcrest/Matcher;
     160: invokestatic  #152                // Method org/junit/Assert.assertThat:(Ljava/lang/Object;Lorg/hamcrest/Matcher;)V
     163: lconst_1
     164: aload_2
     165: iconst_1
     166: invokeinterface #56,  2           // InterfaceMethod java/util/List.get:(I)Ljava/lang/Object;
     171: checkcast     #145                // class java/util/concurrent/CompletableFuture
     174: invokevirtual #27                 // Method java/util/concurrent/CompletableFuture.get:()Ljava/lang/Object;
     177: checkcast     #57                 // class org/apache/hadoop/hbase/client/Result
     180: getstatic     #32                 // Field FAMILY:[B
     183: getstatic     #58                 // Field CQ:[B
     186: invokevirtual #59                 // Method org/apache/hadoop/hbase/client/Result.getValue:([B[B)[B
     189: invokestatic  #126                // Method org/apache/hadoop/hbase/util/Bytes.toLong:([B)J
     192: invokestatic  #55                 // Method org/junit/Assert.assertEquals:(JJ)V
     195: aload_2
     196: iconst_2
     197: invokeinterface #56,  2           // InterfaceMethod java/util/List.get:(I)Ljava/lang/Object;
     202: checkcast     #145                // class java/util/concurrent/CompletableFuture
     205: invokevirtual #27                 // Method java/util/concurrent/CompletableFuture.get:()Ljava/lang/Object;
     208: checkcast     #57                 // class org/apache/hadoop/hbase/client/Result
     211: invokevirtual #61                 // Method org/apache/hadoop/hbase/client/Result.isEmpty:()Z
     214: invokestatic  #62                 // Method org/junit/Assert.assertTrue:(Z)V
     217: ldc           #158                // String good
     219: aload_1
     220: new           #99                 // class org/apache/hadoop/hbase/client/Get
     223: dup
     224: ldc           #154                // String put
     226: invokestatic  #25                 // Method org/apache/hadoop/hbase/util/Bytes.toBytes:(Ljava/lang/String;)[B
     229: invokespecial #101                // Method org/apache/hadoop/hbase/client/Get."<init>":([B)V
     232: invokeinterface #127,  2          // InterfaceMethod org/apache/hadoop/hbase/client/AsyncTable.get:(Lorg/apache/hadoop/hbase/client/Get;)Ljava/util/concurrent/CompletableFuture;
     237: invokevirtual #27                 // Method java/util/concurrent/CompletableFuture.get:()Ljava/lang/Object;
     240: checkcast     #57                 // class org/apache/hadoop/hbase/client/Result
     243: getstatic     #32                 // Field FAMILY:[B
     246: getstatic     #58                 // Field CQ:[B
     249: invokevirtual #59                 // Method org/apache/hadoop/hbase/client/Result.getValue:([B[B)[B
     252: invokestatic  #162                // Method org/apache/hadoop/hbase/util/Bytes.toString:([B)Ljava/lang/String;
     255: invokestatic  #163                // Method org/junit/Assert.assertEquals:(Ljava/lang/Object;Ljava/lang/Object;)V
     258: return
    Exception table:
       from    to  target type
         115   132   135   Class java/util/concurrent/ExecutionException

  public void testInvalidPut();
    Code:
       0: aload_0
       1: getfield      #39                 // Field tableGetter:Ljava/util/function/Function;
       4: getstatic     #31                 // Field TABLE_NAME:Lorg/apache/hadoop/hbase/TableName;
       7: invokeinterface #40,  2           // InterfaceMethod java/util/function/Function.apply:(Ljava/lang/Object;)Ljava/lang/Object;
      12: checkcast     #41                 // class org/apache/hadoop/hbase/client/AsyncTable
      15: astore_1
      16: aload_1
      17: iconst_2
      18: anewarray     #153                // class org/apache/hadoop/hbase/client/Mutation
      21: dup
      22: iconst_0
      23: new           #109                // class org/apache/hadoop/hbase/client/Delete
      26: dup
      27: iconst_0
      28: invokestatic  #100                // Method org/apache/hadoop/hbase/util/Bytes.toBytes:(I)[B
      31: invokespecial #110                // Method org/apache/hadoop/hbase/client/Delete."<init>":([B)V
      34: aastore
      35: dup
      36: iconst_1
      37: new           #103                // class org/apache/hadoop/hbase/client/Put
      40: dup
      41: iconst_0
      42: invokestatic  #100                // Method org/apache/hadoop/hbase/util/Bytes.toBytes:(I)[B
      45: invokespecial #104                // Method org/apache/hadoop/hbase/client/Put."<init>":([B)V
      48: aastore
      49: invokestatic  #12                 // Method java/util/Arrays.asList:([Ljava/lang/Object;)Ljava/util/List;
      52: invokeinterface #159,  2          // InterfaceMethod org/apache/hadoop/hbase/client/AsyncTable.batch:(Ljava/util/List;)Ljava/util/List;
      57: pop
      58: ldc           #164                // String Should fail since the put does not contain any cells
      60: invokestatic  #165                // Method org/junit/Assert.fail:(Ljava/lang/String;)V
      63: goto          79
      66: astore_2
      67: aload_2
      68: invokevirtual #167                // Method java/lang/IllegalArgumentException.getMessage:()Ljava/lang/String;
      71: ldc           #168                // String No columns to insert
      73: invokestatic  #169                // Method org/hamcrest/CoreMatchers.containsString:(Ljava/lang/String;)Lorg/hamcrest/Matcher;
      76: invokestatic  #152                // Method org/junit/Assert.assertThat:(Ljava/lang/Object;Lorg/hamcrest/Matcher;)V
      79: aload_1
      80: iconst_2
      81: anewarray     #153                // class org/apache/hadoop/hbase/client/Mutation
      84: dup
      85: iconst_0
      86: new           #103                // class org/apache/hadoop/hbase/client/Put
      89: dup
      90: iconst_0
      91: invokestatic  #100                // Method org/apache/hadoop/hbase/util/Bytes.toBytes:(I)[B
      94: invokespecial #104                // Method org/apache/hadoop/hbase/client/Put."<init>":([B)V
      97: getstatic     #32                 // Field FAMILY:[B
     100: getstatic     #58                 // Field CQ:[B
     103: getstatic     #17                 // Field MAX_KEY_VALUE_SIZE:I
     106: newarray       byte
     108: invokevirtual #108                // Method org/apache/hadoop/hbase/client/Put.addColumn:([B[B[B)Lorg/apache/hadoop/hbase/client/Put;
     111: aastore
     112: dup
     113: iconst_1
     114: new           #109                // class org/apache/hadoop/hbase/client/Delete
     117: dup
     118: iconst_0
     119: invokestatic  #100                // Method org/apache/hadoop/hbase/util/Bytes.toBytes:(I)[B
     122: invokespecial #110                // Method org/apache/hadoop/hbase/client/Delete."<init>":([B)V
     125: aastore
     126: invokestatic  #12                 // Method java/util/Arrays.asList:([Ljava/lang/Object;)Ljava/util/List;
     129: invokeinterface #159,  2          // InterfaceMethod org/apache/hadoop/hbase/client/AsyncTable.batch:(Ljava/util/List;)Ljava/util/List;
     134: pop
     135: ldc           #170                // String Should fail since the put exceeds the max key value size
     137: invokestatic  #165                // Method org/junit/Assert.fail:(Ljava/lang/String;)V
     140: goto          156
     143: astore_2
     144: aload_2
     145: invokevirtual #167                // Method java/lang/IllegalArgumentException.getMessage:()Ljava/lang/String;
     148: ldc           #171                // String KeyValue size too large
     150: invokestatic  #169                // Method org/hamcrest/CoreMatchers.containsString:(Ljava/lang/String;)Lorg/hamcrest/Matcher;
     153: invokestatic  #152                // Method org/junit/Assert.assertThat:(Ljava/lang/Object;Lorg/hamcrest/Matcher;)V
     156: return
    Exception table:
       from    to  target type
          16    63    66   Class java/lang/IllegalArgumentException
          79   140   143   Class java/lang/IllegalArgumentException

  static {};
    Code:
       0: ldc           #183                // class org/apache/hadoop/hbase/client/TestAsyncTableBatch
       2: invokestatic  #184                // Method org/apache/hadoop/hbase/HBaseClassTestRule.forClass:(Ljava/lang/Class;)Lorg/apache/hadoop/hbase/HBaseClassTestRule;
       5: putstatic     #185                // Field CLASS_RULE:Lorg/apache/hadoop/hbase/HBaseClassTestRule;
       8: new           #186                // class org/apache/hadoop/hbase/HBaseTestingUtility
      11: dup
      12: invokespecial #187                // Method org/apache/hadoop/hbase/HBaseTestingUtility."<init>":()V
      15: putstatic     #13                 // Field TEST_UTIL:Lorg/apache/hadoop/hbase/HBaseTestingUtility;
      18: ldc           #188                // String async
      20: invokestatic  #189                // Method org/apache/hadoop/hbase/TableName.valueOf:(Ljava/lang/String;)Lorg/apache/hadoop/hbase/TableName;
      23: putstatic     #31                 // Field TABLE_NAME:Lorg/apache/hadoop/hbase/TableName;
      26: ldc           #190                // String cf
      28: invokestatic  #25                 // Method org/apache/hadoop/hbase/util/Bytes.toBytes:(Ljava/lang/String;)[B
      31: putstatic     #32                 // Field FAMILY:[B
      34: ldc           #191                // String cq
      36: invokestatic  #25                 // Method org/apache/hadoop/hbase/util/Bytes.toBytes:(Ljava/lang/String;)[B
      39: putstatic     #58                 // Field CQ:[B
      42: ldc           #192                // String cq1
      44: invokestatic  #25                 // Method org/apache/hadoop/hbase/util/Bytes.toBytes:(Ljava/lang/String;)[B
      47: putstatic     #120                // Field CQ1:[B
      50: sipush        1000
      53: putstatic     #42                 // Field COUNT:I
      56: ldc           #193                // int 65536
      58: putstatic     #17                 // Field MAX_KEY_VALUE_SIZE:I
      61: return
}
