Compiled from "TestClassFinder.java"
class org.apache.hadoop.hbase.TestClassFinder$6 implements org.apache.hadoop.hbase.ClassFinder$ResourcePathFilter {
  final org.apache.hadoop.hbase.TestClassFinder this$0;

  org.apache.hadoop.hbase.TestClassFinder$6(org.apache.hadoop.hbase.TestClassFinder);
    Code:
       0: aload_0
       1: aload_1
       2: putfield      #1                  // Field this$0:Lorg/apache/hadoop/hbase/TestClassFinder;
       5: aload_0
       6: invokespecial #2                  // Method java/lang/Object."<init>":()V
       9: return

  public boolean isCandidatePath(java.lang.String, boolean);
    Code:
       0: iload_2
       1: ifne          13
       4: aload_1
       5: ldc           #3                  // String hbase-common
       7: invokevirtual #4                  // Method java/lang/String.contains:(Ljava/lang/CharSequence;)Z
      10: ifne          17
      13: iconst_1
      14: goto          18
      17: iconst_0
      18: ireturn
}
