Compiled from "TestSnapshotWithAclAsyncAdmin.java"
public class org.apache.hadoop.hbase.client.TestSnapshotWithAclAsyncAdmin extends org.apache.hadoop.hbase.client.SnapshotWithAclTestBase {
  public static final org.apache.hadoop.hbase.HBaseClassTestRule CLASS_RULE;

  public org.apache.hadoop.hbase.client.TestSnapshotWithAclAsyncAdmin();
    Code:
       0: aload_0
       1: invokespecial #1                  // Method org/apache/hadoop/hbase/client/SnapshotWithAclTestBase."<init>":()V
       4: return

  protected void snapshot(java.lang.String, org.apache.hadoop.hbase.TableName) throws java.lang.Exception;
    Code:
       0: getstatic     #2                  // Field TEST_UTIL:Lorg/apache/hadoop/hbase/HBaseTestingUtility;
       3: invokevirtual #3                  // Method org/apache/hadoop/hbase/HBaseTestingUtility.getConfiguration:()Lorg/apache/hadoop/conf/Configuration;
       6: invokestatic  #4                  // Method org/apache/hadoop/hbase/client/ConnectionFactory.createAsyncConnection:(Lorg/apache/hadoop/conf/Configuration;)Ljava/util/concurrent/CompletableFuture;
       9: invokevirtual #5                  // Method java/util/concurrent/CompletableFuture.get:()Ljava/lang/Object;
      12: checkcast     #6                  // class org/apache/hadoop/hbase/client/AsyncConnection
      15: astore_3
      16: aconst_null
      17: astore        4
      19: aload_3
      20: invokeinterface #7,  1            // InterfaceMethod org/apache/hadoop/hbase/client/AsyncConnection.getAdmin:()Lorg/apache/hadoop/hbase/client/AsyncAdmin;
      25: aload_1
      26: aload_2
      27: invokeinterface #8,  3            // InterfaceMethod org/apache/hadoop/hbase/client/AsyncAdmin.snapshot:(Ljava/lang/String;Lorg/apache/hadoop/hbase/TableName;)Ljava/util/concurrent/CompletableFuture;
      32: invokevirtual #5                  // Method java/util/concurrent/CompletableFuture.get:()Ljava/lang/Object;
      35: pop
      36: aload_3
      37: ifnull        125
      40: aload         4
      42: ifnull        66
      45: aload_3
      46: invokeinterface #9,  1            // InterfaceMethod org/apache/hadoop/hbase/client/AsyncConnection.close:()V
      51: goto          125
      54: astore        5
      56: aload         4
      58: aload         5
      60: invokevirtual #11                 // Method java/lang/Throwable.addSuppressed:(Ljava/lang/Throwable;)V
      63: goto          125
      66: aload_3
      67: invokeinterface #9,  1            // InterfaceMethod org/apache/hadoop/hbase/client/AsyncConnection.close:()V
      72: goto          125
      75: astore        5
      77: aload         5
      79: astore        4
      81: aload         5
      83: athrow
      84: astore        6
      86: aload_3
      87: ifnull        122
      90: aload         4
      92: ifnull        116
      95: aload_3
      96: invokeinterface #9,  1            // InterfaceMethod org/apache/hadoop/hbase/client/AsyncConnection.close:()V
     101: goto          122
     104: astore        7
     106: aload         4
     108: aload         7
     110: invokevirtual #11                 // Method java/lang/Throwable.addSuppressed:(Ljava/lang/Throwable;)V
     113: goto          122
     116: aload_3
     117: invokeinterface #9,  1            // InterfaceMethod org/apache/hadoop/hbase/client/AsyncConnection.close:()V
     122: aload         6
     124: athrow
     125: return
    Exception table:
       from    to  target type
          45    51    54   Class java/lang/Throwable
          19    36    75   Class java/lang/Throwable
          19    36    84   any
          95   101   104   Class java/lang/Throwable
          75    86    84   any

  protected void cloneSnapshot(java.lang.String, org.apache.hadoop.hbase.TableName, boolean) throws java.lang.Exception;
    Code:
       0: getstatic     #2                  // Field TEST_UTIL:Lorg/apache/hadoop/hbase/HBaseTestingUtility;
       3: invokevirtual #3                  // Method org/apache/hadoop/hbase/HBaseTestingUtility.getConfiguration:()Lorg/apache/hadoop/conf/Configuration;
       6: invokestatic  #4                  // Method org/apache/hadoop/hbase/client/ConnectionFactory.createAsyncConnection:(Lorg/apache/hadoop/conf/Configuration;)Ljava/util/concurrent/CompletableFuture;
       9: invokevirtual #5                  // Method java/util/concurrent/CompletableFuture.get:()Ljava/lang/Object;
      12: checkcast     #6                  // class org/apache/hadoop/hbase/client/AsyncConnection
      15: astore        4
      17: aconst_null
      18: astore        5
      20: aload         4
      22: invokeinterface #7,  1            // InterfaceMethod org/apache/hadoop/hbase/client/AsyncConnection.getAdmin:()Lorg/apache/hadoop/hbase/client/AsyncAdmin;
      27: aload_1
      28: aload_2
      29: iload_3
      30: invokeinterface #12,  4           // InterfaceMethod org/apache/hadoop/hbase/client/AsyncAdmin.cloneSnapshot:(Ljava/lang/String;Lorg/apache/hadoop/hbase/TableName;Z)Ljava/util/concurrent/CompletableFuture;
      35: invokevirtual #5                  // Method java/util/concurrent/CompletableFuture.get:()Ljava/lang/Object;
      38: pop
      39: aload         4
      41: ifnull        134
      44: aload         5
      46: ifnull        71
      49: aload         4
      51: invokeinterface #9,  1            // InterfaceMethod org/apache/hadoop/hbase/client/AsyncConnection.close:()V
      56: goto          134
      59: astore        6
      61: aload         5
      63: aload         6
      65: invokevirtual #11                 // Method java/lang/Throwable.addSuppressed:(Ljava/lang/Throwable;)V
      68: goto          134
      71: aload         4
      73: invokeinterface #9,  1            // InterfaceMethod org/apache/hadoop/hbase/client/AsyncConnection.close:()V
      78: goto          134
      81: astore        6
      83: aload         6
      85: astore        5
      87: aload         6
      89: athrow
      90: astore        7
      92: aload         4
      94: ifnull        131
      97: aload         5
      99: ifnull        124
     102: aload         4
     104: invokeinterface #9,  1            // InterfaceMethod org/apache/hadoop/hbase/client/AsyncConnection.close:()V
     109: goto          131
     112: astore        8
     114: aload         5
     116: aload         8
     118: invokevirtual #11                 // Method java/lang/Throwable.addSuppressed:(Ljava/lang/Throwable;)V
     121: goto          131
     124: aload         4
     126: invokeinterface #9,  1            // InterfaceMethod org/apache/hadoop/hbase/client/AsyncConnection.close:()V
     131: aload         7
     133: athrow
     134: return
    Exception table:
       from    to  target type
          49    56    59   Class java/lang/Throwable
          20    39    81   Class java/lang/Throwable
          20    39    90   any
         102   109   112   Class java/lang/Throwable
          81    92    90   any

  protected void restoreSnapshot(java.lang.String, boolean) throws java.lang.Exception;
    Code:
       0: getstatic     #2                  // Field TEST_UTIL:Lorg/apache/hadoop/hbase/HBaseTestingUtility;
       3: invokevirtual #3                  // Method org/apache/hadoop/hbase/HBaseTestingUtility.getConfiguration:()Lorg/apache/hadoop/conf/Configuration;
       6: invokestatic  #4                  // Method org/apache/hadoop/hbase/client/ConnectionFactory.createAsyncConnection:(Lorg/apache/hadoop/conf/Configuration;)Ljava/util/concurrent/CompletableFuture;
       9: invokevirtual #5                  // Method java/util/concurrent/CompletableFuture.get:()Ljava/lang/Object;
      12: checkcast     #6                  // class org/apache/hadoop/hbase/client/AsyncConnection
      15: astore_3
      16: aconst_null
      17: astore        4
      19: aload_3
      20: invokeinterface #7,  1            // InterfaceMethod org/apache/hadoop/hbase/client/AsyncConnection.getAdmin:()Lorg/apache/hadoop/hbase/client/AsyncAdmin;
      25: aload_1
      26: iconst_0
      27: iload_2
      28: invokeinterface #13,  4           // InterfaceMethod org/apache/hadoop/hbase/client/AsyncAdmin.restoreSnapshot:(Ljava/lang/String;ZZ)Ljava/util/concurrent/CompletableFuture;
      33: invokevirtual #5                  // Method java/util/concurrent/CompletableFuture.get:()Ljava/lang/Object;
      36: pop
      37: aload_3
      38: ifnull        126
      41: aload         4
      43: ifnull        67
      46: aload_3
      47: invokeinterface #9,  1            // InterfaceMethod org/apache/hadoop/hbase/client/AsyncConnection.close:()V
      52: goto          126
      55: astore        5
      57: aload         4
      59: aload         5
      61: invokevirtual #11                 // Method java/lang/Throwable.addSuppressed:(Ljava/lang/Throwable;)V
      64: goto          126
      67: aload_3
      68: invokeinterface #9,  1            // InterfaceMethod org/apache/hadoop/hbase/client/AsyncConnection.close:()V
      73: goto          126
      76: astore        5
      78: aload         5
      80: astore        4
      82: aload         5
      84: athrow
      85: astore        6
      87: aload_3
      88: ifnull        123
      91: aload         4
      93: ifnull        117
      96: aload_3
      97: invokeinterface #9,  1            // InterfaceMethod org/apache/hadoop/hbase/client/AsyncConnection.close:()V
     102: goto          123
     105: astore        7
     107: aload         4
     109: aload         7
     111: invokevirtual #11                 // Method java/lang/Throwable.addSuppressed:(Ljava/lang/Throwable;)V
     114: goto          123
     117: aload_3
     118: invokeinterface #9,  1            // InterfaceMethod org/apache/hadoop/hbase/client/AsyncConnection.close:()V
     123: aload         6
     125: athrow
     126: return
    Exception table:
       from    to  target type
          46    52    55   Class java/lang/Throwable
          19    37    76   Class java/lang/Throwable
          19    37    85   any
          96   102   105   Class java/lang/Throwable
          76    87    85   any

  static {};
    Code:
       0: ldc           #14                 // class org/apache/hadoop/hbase/client/TestSnapshotWithAclAsyncAdmin
       2: invokestatic  #15                 // Method org/apache/hadoop/hbase/HBaseClassTestRule.forClass:(Ljava/lang/Class;)Lorg/apache/hadoop/hbase/HBaseClassTestRule;
       5: putstatic     #16                 // Field CLASS_RULE:Lorg/apache/hadoop/hbase/HBaseClassTestRule;
       8: return
}
