Compiled from "TestPostIncrementAndAppendBeforeWAL.java"
public class org.apache.hadoop.hbase.coprocessor.TestPostIncrementAndAppendBeforeWAL {
  public static final org.apache.hadoop.hbase.HBaseClassTestRule CLASS_RULE;

  public org.junit.rules.TestName name;

  public org.apache.hadoop.hbase.coprocessor.TestPostIncrementAndAppendBeforeWAL();
    Code:
       0: aload_0
       1: invokespecial #3                  // Method java/lang/Object."<init>":()V
       4: aload_0
       5: new           #4                  // class org/junit/rules/TestName
       8: dup
       9: invokespecial #5                  // Method org/junit/rules/TestName."<init>":()V
      12: putfield      #6                  // Field name:Lorg/junit/rules/TestName;
      15: return

  public static void setupBeforeClass() throws java.lang.Exception;
    Code:
       0: getstatic     #7                  // Field UTIL:Lorg/apache/hadoop/hbase/HBaseTestingUtility;
       3: invokevirtual #8                  // Method org/apache/hadoop/hbase/HBaseTestingUtility.startMiniCluster:()Lorg/apache/hadoop/hbase/MiniHBaseCluster;
       6: pop
       7: getstatic     #7                  // Field UTIL:Lorg/apache/hadoop/hbase/HBaseTestingUtility;
      10: invokevirtual #9                  // Method org/apache/hadoop/hbase/HBaseTestingUtility.getConnection:()Lorg/apache/hadoop/hbase/client/Connection;
      13: putstatic     #10                 // Field connection:Lorg/apache/hadoop/hbase/client/Connection;
      16: return

  public static void tearDownAfterClass() throws java.lang.Exception;
    Code:
       0: getstatic     #10                 // Field connection:Lorg/apache/hadoop/hbase/client/Connection;
       3: invokeinterface #11,  1           // InterfaceMethod org/apache/hadoop/hbase/client/Connection.close:()V
       8: getstatic     #7                  // Field UTIL:Lorg/apache/hadoop/hbase/HBaseTestingUtility;
      11: invokevirtual #12                 // Method org/apache/hadoop/hbase/HBaseTestingUtility.shutdownMiniCluster:()V
      14: return

  public void testChangeCellWithDifferntColumnFamily() throws java.lang.Exception;
    Code:
       0: aload_0
       1: getfield      #6                  // Field name:Lorg/junit/rules/TestName;
       4: invokevirtual #22                 // Method org/junit/rules/TestName.getMethodName:()Ljava/lang/String;
       7: invokestatic  #23                 // Method org/apache/hadoop/hbase/TableName.valueOf:(Ljava/lang/String;)Lorg/apache/hadoop/hbase/TableName;
      10: astore_1
      11: aload_0
      12: aload_1
      13: ldc           #24                 // class org/apache/hadoop/hbase/coprocessor/TestPostIncrementAndAppendBeforeWAL$ChangeCellWithDifferntColumnFamilyObserver
      15: invokevirtual #25                 // Method java/lang/Class.getName:()Ljava/lang/String;
      18: invokespecial #26                 // Method createTableWithCoprocessor:(Lorg/apache/hadoop/hbase/TableName;Ljava/lang/String;)V
      21: getstatic     #10                 // Field connection:Lorg/apache/hadoop/hbase/client/Connection;
      24: aload_1
      25: invokeinterface #27,  2           // InterfaceMethod org/apache/hadoop/hbase/client/Connection.getTable:(Lorg/apache/hadoop/hbase/TableName;)Lorg/apache/hadoop/hbase/client/Table;
      30: astore_2
      31: aconst_null
      32: astore_3
      33: new           #28                 // class org/apache/hadoop/hbase/client/Increment
      36: dup
      37: getstatic     #29                 // Field ROW:[B
      40: invokespecial #30                 // Method org/apache/hadoop/hbase/client/Increment."<init>":([B)V
      43: getstatic     #14                 // Field CF1_BYTES:[B
      46: getstatic     #31                 // Field CQ1:[B
      49: lconst_1
      50: invokevirtual #32                 // Method org/apache/hadoop/hbase/client/Increment.addColumn:([B[BJ)Lorg/apache/hadoop/hbase/client/Increment;
      53: astore        4
      55: aload_2
      56: aload         4
      58: invokeinterface #33,  2           // InterfaceMethod org/apache/hadoop/hbase/client/Table.increment:(Lorg/apache/hadoop/hbase/client/Increment;)Lorg/apache/hadoop/hbase/client/Result;
      63: pop
      64: new           #34                 // class org/apache/hadoop/hbase/client/Get
      67: dup
      68: getstatic     #29                 // Field ROW:[B
      71: invokespecial #35                 // Method org/apache/hadoop/hbase/client/Get."<init>":([B)V
      74: getstatic     #2                  // Field CF2_BYTES:[B
      77: getstatic     #31                 // Field CQ1:[B
      80: invokevirtual #36                 // Method org/apache/hadoop/hbase/client/Get.addColumn:([B[B)Lorg/apache/hadoop/hbase/client/Get;
      83: astore        5
      85: aload_2
      86: aload         5
      88: invokeinterface #37,  2           // InterfaceMethod org/apache/hadoop/hbase/client/Table.get:(Lorg/apache/hadoop/hbase/client/Get;)Lorg/apache/hadoop/hbase/client/Result;
      93: astore        6
      95: lconst_1
      96: aload         6
      98: invokevirtual #38                 // Method org/apache/hadoop/hbase/client/Result.size:()I
     101: i2l
     102: invokestatic  #39                 // Method org/junit/Assert.assertEquals:(JJ)V
     105: lconst_1
     106: aload         6
     108: getstatic     #2                  // Field CF2_BYTES:[B
     111: getstatic     #31                 // Field CQ1:[B
     114: invokevirtual #40                 // Method org/apache/hadoop/hbase/client/Result.getValue:([B[B)[B
     117: invokestatic  #41                 // Method org/apache/hadoop/hbase/util/Bytes.toLong:([B)J
     120: invokestatic  #39                 // Method org/junit/Assert.assertEquals:(JJ)V
     123: new           #42                 // class org/apache/hadoop/hbase/client/Append
     126: dup
     127: getstatic     #29                 // Field ROW:[B
     130: invokespecial #43                 // Method org/apache/hadoop/hbase/client/Append."<init>":([B)V
     133: getstatic     #14                 // Field CF1_BYTES:[B
     136: getstatic     #44                 // Field CQ2:[B
     139: getstatic     #45                 // Field VALUE:[B
     142: invokevirtual #46                 // Method org/apache/hadoop/hbase/client/Append.addColumn:([B[B[B)Lorg/apache/hadoop/hbase/client/Append;
     145: astore        7
     147: aload_2
     148: aload         7
     150: invokeinterface #47,  2           // InterfaceMethod org/apache/hadoop/hbase/client/Table.append:(Lorg/apache/hadoop/hbase/client/Append;)Lorg/apache/hadoop/hbase/client/Result;
     155: pop
     156: new           #34                 // class org/apache/hadoop/hbase/client/Get
     159: dup
     160: getstatic     #29                 // Field ROW:[B
     163: invokespecial #35                 // Method org/apache/hadoop/hbase/client/Get."<init>":([B)V
     166: getstatic     #2                  // Field CF2_BYTES:[B
     169: getstatic     #44                 // Field CQ2:[B
     172: invokevirtual #36                 // Method org/apache/hadoop/hbase/client/Get.addColumn:([B[B)Lorg/apache/hadoop/hbase/client/Get;
     175: astore        5
     177: aload_2
     178: aload         5
     180: invokeinterface #37,  2           // InterfaceMethod org/apache/hadoop/hbase/client/Table.get:(Lorg/apache/hadoop/hbase/client/Get;)Lorg/apache/hadoop/hbase/client/Result;
     185: astore        6
     187: lconst_1
     188: aload         6
     190: invokevirtual #38                 // Method org/apache/hadoop/hbase/client/Result.size:()I
     193: i2l
     194: invokestatic  #39                 // Method org/junit/Assert.assertEquals:(JJ)V
     197: getstatic     #45                 // Field VALUE:[B
     200: aload         6
     202: getstatic     #2                  // Field CF2_BYTES:[B
     205: getstatic     #44                 // Field CQ2:[B
     208: invokevirtual #40                 // Method org/apache/hadoop/hbase/client/Result.getValue:([B[B)[B
     211: invokestatic  #48                 // Method org/apache/hadoop/hbase/util/Bytes.equals:([B[B)Z
     214: invokestatic  #49                 // Method org/junit/Assert.assertTrue:(Z)V
     217: aload_2
     218: ifnull        301
     221: aload_3
     222: ifnull        245
     225: aload_2
     226: invokeinterface #50,  1           // InterfaceMethod org/apache/hadoop/hbase/client/Table.close:()V
     231: goto          301
     234: astore        4
     236: aload_3
     237: aload         4
     239: invokevirtual #52                 // Method java/lang/Throwable.addSuppressed:(Ljava/lang/Throwable;)V
     242: goto          301
     245: aload_2
     246: invokeinterface #50,  1           // InterfaceMethod org/apache/hadoop/hbase/client/Table.close:()V
     251: goto          301
     254: astore        4
     256: aload         4
     258: astore_3
     259: aload         4
     261: athrow
     262: astore        8
     264: aload_2
     265: ifnull        298
     268: aload_3
     269: ifnull        292
     272: aload_2
     273: invokeinterface #50,  1           // InterfaceMethod org/apache/hadoop/hbase/client/Table.close:()V
     278: goto          298
     281: astore        9
     283: aload_3
     284: aload         9
     286: invokevirtual #52                 // Method java/lang/Throwable.addSuppressed:(Ljava/lang/Throwable;)V
     289: goto          298
     292: aload_2
     293: invokeinterface #50,  1           // InterfaceMethod org/apache/hadoop/hbase/client/Table.close:()V
     298: aload         8
     300: athrow
     301: return
    Exception table:
       from    to  target type
         225   231   234   Class java/lang/Throwable
          33   217   254   Class java/lang/Throwable
          33   217   262   any
         272   278   281   Class java/lang/Throwable
         254   264   262   any

  public void testChangeCellWithNotExistColumnFamily() throws java.lang.Exception;
    Code:
       0: aload_0
       1: getfield      #6                  // Field name:Lorg/junit/rules/TestName;
       4: invokevirtual #22                 // Method org/junit/rules/TestName.getMethodName:()Ljava/lang/String;
       7: invokestatic  #23                 // Method org/apache/hadoop/hbase/TableName.valueOf:(Ljava/lang/String;)Lorg/apache/hadoop/hbase/TableName;
      10: astore_1
      11: aload_0
      12: aload_1
      13: ldc           #53                 // class org/apache/hadoop/hbase/coprocessor/TestPostIncrementAndAppendBeforeWAL$ChangeCellWithNotExistColumnFamilyObserver
      15: invokevirtual #25                 // Method java/lang/Class.getName:()Ljava/lang/String;
      18: invokespecial #26                 // Method createTableWithCoprocessor:(Lorg/apache/hadoop/hbase/TableName;Ljava/lang/String;)V
      21: getstatic     #10                 // Field connection:Lorg/apache/hadoop/hbase/client/Connection;
      24: aload_1
      25: invokeinterface #27,  2           // InterfaceMethod org/apache/hadoop/hbase/client/Connection.getTable:(Lorg/apache/hadoop/hbase/TableName;)Lorg/apache/hadoop/hbase/client/Table;
      30: astore_2
      31: aconst_null
      32: astore_3
      33: new           #28                 // class org/apache/hadoop/hbase/client/Increment
      36: dup
      37: getstatic     #29                 // Field ROW:[B
      40: invokespecial #30                 // Method org/apache/hadoop/hbase/client/Increment."<init>":([B)V
      43: getstatic     #14                 // Field CF1_BYTES:[B
      46: getstatic     #31                 // Field CQ1:[B
      49: lconst_1
      50: invokevirtual #32                 // Method org/apache/hadoop/hbase/client/Increment.addColumn:([B[BJ)Lorg/apache/hadoop/hbase/client/Increment;
      53: astore        4
      55: aload_2
      56: aload         4
      58: invokeinterface #33,  2           // InterfaceMethod org/apache/hadoop/hbase/client/Table.increment:(Lorg/apache/hadoop/hbase/client/Increment;)Lorg/apache/hadoop/hbase/client/Result;
      63: pop
      64: ldc           #54                 // String should throw NoSuchColumnFamilyException
      66: invokestatic  #55                 // Method org/junit/Assert.fail:(Ljava/lang/String;)V
      69: goto          82
      72: astore        4
      74: aload         4
      76: instanceof    #57                 // class org/apache/hadoop/hbase/regionserver/NoSuchColumnFamilyException
      79: invokestatic  #49                 // Method org/junit/Assert.assertTrue:(Z)V
      82: new           #42                 // class org/apache/hadoop/hbase/client/Append
      85: dup
      86: getstatic     #29                 // Field ROW:[B
      89: invokespecial #43                 // Method org/apache/hadoop/hbase/client/Append."<init>":([B)V
      92: getstatic     #14                 // Field CF1_BYTES:[B
      95: getstatic     #44                 // Field CQ2:[B
      98: getstatic     #45                 // Field VALUE:[B
     101: invokevirtual #46                 // Method org/apache/hadoop/hbase/client/Append.addColumn:([B[B[B)Lorg/apache/hadoop/hbase/client/Append;
     104: astore        4
     106: aload_2
     107: aload         4
     109: invokeinterface #47,  2           // InterfaceMethod org/apache/hadoop/hbase/client/Table.append:(Lorg/apache/hadoop/hbase/client/Append;)Lorg/apache/hadoop/hbase/client/Result;
     114: pop
     115: ldc           #54                 // String should throw NoSuchColumnFamilyException
     117: invokestatic  #55                 // Method org/junit/Assert.fail:(Ljava/lang/String;)V
     120: goto          133
     123: astore        4
     125: aload         4
     127: instanceof    #57                 // class org/apache/hadoop/hbase/regionserver/NoSuchColumnFamilyException
     130: invokestatic  #49                 // Method org/junit/Assert.assertTrue:(Z)V
     133: aload_2
     134: ifnull        217
     137: aload_3
     138: ifnull        161
     141: aload_2
     142: invokeinterface #50,  1           // InterfaceMethod org/apache/hadoop/hbase/client/Table.close:()V
     147: goto          217
     150: astore        4
     152: aload_3
     153: aload         4
     155: invokevirtual #52                 // Method java/lang/Throwable.addSuppressed:(Ljava/lang/Throwable;)V
     158: goto          217
     161: aload_2
     162: invokeinterface #50,  1           // InterfaceMethod org/apache/hadoop/hbase/client/Table.close:()V
     167: goto          217
     170: astore        4
     172: aload         4
     174: astore_3
     175: aload         4
     177: athrow
     178: astore        5
     180: aload_2
     181: ifnull        214
     184: aload_3
     185: ifnull        208
     188: aload_2
     189: invokeinterface #50,  1           // InterfaceMethod org/apache/hadoop/hbase/client/Table.close:()V
     194: goto          214
     197: astore        6
     199: aload_3
     200: aload         6
     202: invokevirtual #52                 // Method java/lang/Throwable.addSuppressed:(Ljava/lang/Throwable;)V
     205: goto          214
     208: aload_2
     209: invokeinterface #50,  1           // InterfaceMethod org/apache/hadoop/hbase/client/Table.close:()V
     214: aload         5
     216: athrow
     217: return
    Exception table:
       from    to  target type
          33    69    72   Class java/lang/Exception
          82   120   123   Class java/lang/Exception
         141   147   150   Class java/lang/Throwable
          33   133   170   Class java/lang/Throwable
          33   133   178   any
         188   194   197   Class java/lang/Throwable
         170   180   178   any

  static byte[] access$000();
    Code:
       0: getstatic     #2                  // Field CF2_BYTES:[B
       3: areturn

  static byte[] access$100();
    Code:
       0: getstatic     #1                  // Field CF_NOT_EXIST_BYTES:[B
       3: areturn

  static {};
    Code:
       0: ldc           #58                 // class org/apache/hadoop/hbase/coprocessor/TestPostIncrementAndAppendBeforeWAL
       2: invokestatic  #59                 // Method org/apache/hadoop/hbase/HBaseClassTestRule.forClass:(Ljava/lang/Class;)Lorg/apache/hadoop/hbase/HBaseClassTestRule;
       5: putstatic     #60                 // Field CLASS_RULE:Lorg/apache/hadoop/hbase/HBaseClassTestRule;
       8: ldc           #61                 // class org/apache/hadoop/hbase/client/TestFromClientSide
      10: invokestatic  #62                 // Method org/slf4j/LoggerFactory.getLogger:(Ljava/lang/Class;)Lorg/slf4j/Logger;
      13: putstatic     #63                 // Field LOG:Lorg/slf4j/Logger;
      16: new           #64                 // class org/apache/hadoop/hbase/HBaseTestingUtility
      19: dup
      20: invokespecial #65                 // Method org/apache/hadoop/hbase/HBaseTestingUtility."<init>":()V
      23: putstatic     #7                  // Field UTIL:Lorg/apache/hadoop/hbase/HBaseTestingUtility;
      26: ldc           #66                 // String row
      28: invokestatic  #67                 // Method org/apache/hadoop/hbase/util/Bytes.toBytes:(Ljava/lang/String;)[B
      31: putstatic     #29                 // Field ROW:[B
      34: ldc           #68                 // String cf1
      36: invokestatic  #67                 // Method org/apache/hadoop/hbase/util/Bytes.toBytes:(Ljava/lang/String;)[B
      39: putstatic     #14                 // Field CF1_BYTES:[B
      42: ldc           #69                 // String cf2
      44: invokestatic  #67                 // Method org/apache/hadoop/hbase/util/Bytes.toBytes:(Ljava/lang/String;)[B
      47: putstatic     #2                  // Field CF2_BYTES:[B
      50: ldc           #70                 // String cf_not_exist
      52: invokestatic  #67                 // Method org/apache/hadoop/hbase/util/Bytes.toBytes:(Ljava/lang/String;)[B
      55: putstatic     #1                  // Field CF_NOT_EXIST_BYTES:[B
      58: ldc           #71                 // String cq1
      60: invokestatic  #67                 // Method org/apache/hadoop/hbase/util/Bytes.toBytes:(Ljava/lang/String;)[B
      63: putstatic     #31                 // Field CQ1:[B
      66: ldc           #72                 // String cq2
      68: invokestatic  #67                 // Method org/apache/hadoop/hbase/util/Bytes.toBytes:(Ljava/lang/String;)[B
      71: putstatic     #44                 // Field CQ2:[B
      74: ldc           #73                 // String value
      76: invokestatic  #67                 // Method org/apache/hadoop/hbase/util/Bytes.toBytes:(Ljava/lang/String;)[B
      79: putstatic     #45                 // Field VALUE:[B
      82: return
}
