Compiled from "TestSplitWALManager.java"
public final class org.apache.hadoop.hbase.master.TestSplitWALManager$FakeServerProcedure extends org.apache.hadoop.hbase.procedure2.StateMachineProcedure<org.apache.hadoop.hbase.master.procedure.MasterProcedureEnv, org.apache.hadoop.hbase.shaded.protobuf.generated.MasterProcedureProtos$SplitWALState> implements org.apache.hadoop.hbase.master.procedure.ServerProcedureInterface {
  public org.apache.hadoop.hbase.master.TestSplitWALManager$FakeServerProcedure();
    Code:
       0: aload_0
       1: invokespecial #1                  // Method org/apache/hadoop/hbase/procedure2/StateMachineProcedure."<init>":()V
       4: aload_0
       5: new           #2                  // class java/util/concurrent/CountDownLatch
       8: dup
       9: iconst_1
      10: invokespecial #3                  // Method java/util/concurrent/CountDownLatch."<init>":(I)V
      13: putfield      #4                  // Field barrier:Ljava/util/concurrent/CountDownLatch;
      16: aload_0
      17: iconst_0
      18: putfield      #5                  // Field triedToAcquire:Z
      21: return

  public org.apache.hadoop.hbase.master.TestSplitWALManager$FakeServerProcedure(org.apache.hadoop.hbase.ServerName);
    Code:
       0: aload_0
       1: invokespecial #1                  // Method org/apache/hadoop/hbase/procedure2/StateMachineProcedure."<init>":()V
       4: aload_0
       5: new           #2                  // class java/util/concurrent/CountDownLatch
       8: dup
       9: iconst_1
      10: invokespecial #3                  // Method java/util/concurrent/CountDownLatch."<init>":(I)V
      13: putfield      #4                  // Field barrier:Ljava/util/concurrent/CountDownLatch;
      16: aload_0
      17: iconst_0
      18: putfield      #5                  // Field triedToAcquire:Z
      21: aload_0
      22: aload_1
      23: putfield      #6                  // Field serverName:Lorg/apache/hadoop/hbase/ServerName;
      26: return

  public org.apache.hadoop.hbase.ServerName getServerName();
    Code:
       0: aload_0
       1: getfield      #6                  // Field serverName:Lorg/apache/hadoop/hbase/ServerName;
       4: areturn

  public boolean hasMetaTableRegion();
    Code:
       0: iconst_0
       1: ireturn

  public org.apache.hadoop.hbase.master.procedure.ServerProcedureInterface$ServerOperationType getServerOperationType();
    Code:
       0: getstatic     #7                  // Field org/apache/hadoop/hbase/master/procedure/ServerProcedureInterface$ServerOperationType.SPLIT_WAL:Lorg/apache/hadoop/hbase/master/procedure/ServerProcedureInterface$ServerOperationType;
       3: areturn

  protected org.apache.hadoop.hbase.procedure2.StateMachineProcedure$Flow executeFromState(org.apache.hadoop.hbase.master.procedure.MasterProcedureEnv, org.apache.hadoop.hbase.shaded.protobuf.generated.MasterProcedureProtos$SplitWALState) throws org.apache.hadoop.hbase.procedure2.ProcedureSuspendedException, org.apache.hadoop.hbase.procedure2.ProcedureYieldException, java.lang.InterruptedException;
    Code:
       0: aload_1
       1: invokevirtual #8                  // Method org/apache/hadoop/hbase/master/procedure/MasterProcedureEnv.getMasterServices:()Lorg/apache/hadoop/hbase/master/MasterServices;
       4: invokeinterface #9,  1            // InterfaceMethod org/apache/hadoop/hbase/master/MasterServices.getSplitWALManager:()Lorg/apache/hadoop/hbase/master/SplitWALManager;
       9: astore_3
      10: getstatic     #10                 // Field org/apache/hadoop/hbase/master/TestSplitWALManager$1.$SwitchMap$org$apache$hadoop$hbase$shaded$protobuf$generated$MasterProcedureProtos$SplitWALState:[I
      13: aload_2
      14: invokevirtual #11                 // Method org/apache/hadoop/hbase/shaded/protobuf/generated/MasterProcedureProtos$SplitWALState.ordinal:()I
      17: iaload
      18: tableswitch   { // 1 to 3
                     1: 44
                     2: 69
                     3: 87
               default: 103
          }
      44: aload_0
      45: iconst_1
      46: putfield      #5                  // Field triedToAcquire:Z
      49: aload_0
      50: aload_3
      51: aload_0
      52: invokevirtual #12                 // Method org/apache/hadoop/hbase/master/SplitWALManager.acquireSplitWALWorker:(Lorg/apache/hadoop/hbase/procedure2/Procedure;)Lorg/apache/hadoop/hbase/ServerName;
      55: putfield      #13                 // Field worker:Lorg/apache/hadoop/hbase/ServerName;
      58: aload_0
      59: getstatic     #14                 // Field org/apache/hadoop/hbase/shaded/protobuf/generated/MasterProcedureProtos$SplitWALState.DISPATCH_WAL_TO_WORKER:Lorg/apache/hadoop/hbase/shaded/protobuf/generated/MasterProcedureProtos$SplitWALState;
      62: invokevirtual #15                 // Method setNextState:(Ljava/lang/Object;)V
      65: getstatic     #16                 // Field org/apache/hadoop/hbase/procedure2/StateMachineProcedure$Flow.HAS_MORE_STATE:Lorg/apache/hadoop/hbase/procedure2/StateMachineProcedure$Flow;
      68: areturn
      69: aload_0
      70: getfield      #4                  // Field barrier:Ljava/util/concurrent/CountDownLatch;
      73: invokevirtual #17                 // Method java/util/concurrent/CountDownLatch.await:()V
      76: aload_0
      77: getstatic     #18                 // Field org/apache/hadoop/hbase/shaded/protobuf/generated/MasterProcedureProtos$SplitWALState.RELEASE_SPLIT_WORKER:Lorg/apache/hadoop/hbase/shaded/protobuf/generated/MasterProcedureProtos$SplitWALState;
      80: invokevirtual #15                 // Method setNextState:(Ljava/lang/Object;)V
      83: getstatic     #16                 // Field org/apache/hadoop/hbase/procedure2/StateMachineProcedure$Flow.HAS_MORE_STATE:Lorg/apache/hadoop/hbase/procedure2/StateMachineProcedure$Flow;
      86: areturn
      87: aload_3
      88: aload_0
      89: getfield      #13                 // Field worker:Lorg/apache/hadoop/hbase/ServerName;
      92: aload_1
      93: invokevirtual #19                 // Method org/apache/hadoop/hbase/master/procedure/MasterProcedureEnv.getProcedureScheduler:()Lorg/apache/hadoop/hbase/master/procedure/MasterProcedureScheduler;
      96: invokevirtual #20                 // Method org/apache/hadoop/hbase/master/SplitWALManager.releaseSplitWALWorker:(Lorg/apache/hadoop/hbase/ServerName;Lorg/apache/hadoop/hbase/master/procedure/MasterProcedureScheduler;)V
      99: getstatic     #21                 // Field org/apache/hadoop/hbase/procedure2/StateMachineProcedure$Flow.NO_MORE_STATE:Lorg/apache/hadoop/hbase/procedure2/StateMachineProcedure$Flow;
     102: areturn
     103: new           #22                 // class java/lang/UnsupportedOperationException
     106: dup
     107: new           #23                 // class java/lang/StringBuilder
     110: dup
     111: invokespecial #24                 // Method java/lang/StringBuilder."<init>":()V
     114: ldc           #25                 // String unhandled state=
     116: invokevirtual #26                 // Method java/lang/StringBuilder.append:(Ljava/lang/String;)Ljava/lang/StringBuilder;
     119: aload_2
     120: invokevirtual #27                 // Method java/lang/StringBuilder.append:(Ljava/lang/Object;)Ljava/lang/StringBuilder;
     123: invokevirtual #28                 // Method java/lang/StringBuilder.toString:()Ljava/lang/String;
     126: invokespecial #29                 // Method java/lang/UnsupportedOperationException."<init>":(Ljava/lang/String;)V
     129: athrow

  public boolean isWorkerAcquired();
    Code:
       0: aload_0
       1: getfield      #13                 // Field worker:Lorg/apache/hadoop/hbase/ServerName;
       4: ifnull        11
       7: iconst_1
       8: goto          12
      11: iconst_0
      12: ireturn

  public boolean isTriedToAcquire();
    Code:
       0: aload_0
       1: getfield      #5                  // Field triedToAcquire:Z
       4: ireturn

  public void countDown();
    Code:
       0: aload_0
       1: getfield      #4                  // Field barrier:Ljava/util/concurrent/CountDownLatch;
       4: invokevirtual #30                 // Method java/util/concurrent/CountDownLatch.countDown:()V
       7: return

  protected void rollbackState(org.apache.hadoop.hbase.master.procedure.MasterProcedureEnv, org.apache.hadoop.hbase.shaded.protobuf.generated.MasterProcedureProtos$SplitWALState) throws java.io.IOException, java.lang.InterruptedException;
    Code:
       0: return

  protected org.apache.hadoop.hbase.shaded.protobuf.generated.MasterProcedureProtos$SplitWALState getState(int);
    Code:
       0: iload_1
       1: invokestatic  #31                 // Method org/apache/hadoop/hbase/shaded/protobuf/generated/MasterProcedureProtos$SplitWALState.forNumber:(I)Lorg/apache/hadoop/hbase/shaded/protobuf/generated/MasterProcedureProtos$SplitWALState;
       4: areturn

  protected int getStateId(org.apache.hadoop.hbase.shaded.protobuf.generated.MasterProcedureProtos$SplitWALState);
    Code:
       0: aload_1
       1: invokevirtual #32                 // Method org/apache/hadoop/hbase/shaded/protobuf/generated/MasterProcedureProtos$SplitWALState.getNumber:()I
       4: ireturn

  protected org.apache.hadoop.hbase.shaded.protobuf.generated.MasterProcedureProtos$SplitWALState getInitialState();
    Code:
       0: getstatic     #33                 // Field org/apache/hadoop/hbase/shaded/protobuf/generated/MasterProcedureProtos$SplitWALState.ACQUIRE_SPLIT_WAL_WORKER:Lorg/apache/hadoop/hbase/shaded/protobuf/generated/MasterProcedureProtos$SplitWALState;
       3: areturn

  protected boolean holdLock(org.apache.hadoop.hbase.master.procedure.MasterProcedureEnv);
    Code:
       0: iconst_1
       1: ireturn

  protected void rollback(org.apache.hadoop.hbase.master.procedure.MasterProcedureEnv) throws java.io.IOException, java.lang.InterruptedException;
    Code:
       0: return

  protected boolean abort(org.apache.hadoop.hbase.master.procedure.MasterProcedureEnv);
    Code:
       0: iconst_0
       1: ireturn

  protected void serializeStateData(org.apache.hadoop.hbase.procedure2.ProcedureStateSerializer) throws java.io.IOException;
    Code:
       0: invokestatic  #34                 // Method org/apache/hadoop/hbase/shaded/protobuf/generated/MasterProcedureProtos$SplitWALData.newBuilder:()Lorg/apache/hadoop/hbase/shaded/protobuf/generated/MasterProcedureProtos$SplitWALData$Builder;
       3: astore_2
       4: aload_2
       5: ldc           #35                 // String test
       7: invokevirtual #36                 // Method org/apache/hadoop/hbase/shaded/protobuf/generated/MasterProcedureProtos$SplitWALData$Builder.setWalPath:(Ljava/lang/String;)Lorg/apache/hadoop/hbase/shaded/protobuf/generated/MasterProcedureProtos$SplitWALData$Builder;
      10: aload_0
      11: getfield      #6                  // Field serverName:Lorg/apache/hadoop/hbase/ServerName;
      14: invokestatic  #37                 // Method org/apache/hadoop/hbase/shaded/protobuf/ProtobufUtil.toServerName:(Lorg/apache/hadoop/hbase/ServerName;)Lorg/apache/hadoop/hbase/shaded/protobuf/generated/HBaseProtos$ServerName;
      17: invokevirtual #38                 // Method org/apache/hadoop/hbase/shaded/protobuf/generated/MasterProcedureProtos$SplitWALData$Builder.setCrashedServer:(Lorg/apache/hadoop/hbase/shaded/protobuf/generated/HBaseProtos$ServerName;)Lorg/apache/hadoop/hbase/shaded/protobuf/generated/MasterProcedureProtos$SplitWALData$Builder;
      20: pop
      21: aload_1
      22: aload_2
      23: invokevirtual #39                 // Method org/apache/hadoop/hbase/shaded/protobuf/generated/MasterProcedureProtos$SplitWALData$Builder.build:()Lorg/apache/hadoop/hbase/shaded/protobuf/generated/MasterProcedureProtos$SplitWALData;
      26: invokeinterface #40,  2           // InterfaceMethod org/apache/hadoop/hbase/procedure2/ProcedureStateSerializer.serialize:(Lorg/apache/hbase/thirdparty/com/google/protobuf/Message;)V
      31: return

  protected void deserializeStateData(org.apache.hadoop.hbase.procedure2.ProcedureStateSerializer) throws java.io.IOException;
    Code:
       0: aload_1
       1: ldc           #41                 // class org/apache/hadoop/hbase/shaded/protobuf/generated/MasterProcedureProtos$SplitWALData
       3: invokeinterface #42,  2           // InterfaceMethod org/apache/hadoop/hbase/procedure2/ProcedureStateSerializer.deserialize:(Ljava/lang/Class;)Lorg/apache/hbase/thirdparty/com/google/protobuf/Message;
       8: checkcast     #41                 // class org/apache/hadoop/hbase/shaded/protobuf/generated/MasterProcedureProtos$SplitWALData
      11: astore_2
      12: aload_0
      13: aload_2
      14: invokevirtual #43                 // Method org/apache/hadoop/hbase/shaded/protobuf/generated/MasterProcedureProtos$SplitWALData.getCrashedServer:()Lorg/apache/hadoop/hbase/shaded/protobuf/generated/HBaseProtos$ServerName;
      17: invokestatic  #44                 // Method org/apache/hadoop/hbase/shaded/protobuf/ProtobufUtil.toServerName:(Lorg/apache/hadoop/hbase/shaded/protobuf/generated/HBaseProtos$ServerName;)Lorg/apache/hadoop/hbase/ServerName;
      20: putfield      #6                  // Field serverName:Lorg/apache/hadoop/hbase/ServerName;
      23: return

  protected boolean abort(java.lang.Object);
    Code:
       0: aload_0
       1: aload_1
       2: checkcast     #45                 // class org/apache/hadoop/hbase/master/procedure/MasterProcedureEnv
       5: invokevirtual #46                 // Method abort:(Lorg/apache/hadoop/hbase/master/procedure/MasterProcedureEnv;)Z
       8: ireturn

  protected void rollback(java.lang.Object) throws java.io.IOException, java.lang.InterruptedException;
    Code:
       0: aload_0
       1: aload_1
       2: checkcast     #45                 // class org/apache/hadoop/hbase/master/procedure/MasterProcedureEnv
       5: invokevirtual #47                 // Method rollback:(Lorg/apache/hadoop/hbase/master/procedure/MasterProcedureEnv;)V
       8: return

  protected java.lang.Object getInitialState();
    Code:
       0: aload_0
       1: invokevirtual #48                 // Method getInitialState:()Lorg/apache/hadoop/hbase/shaded/protobuf/generated/MasterProcedureProtos$SplitWALState;
       4: areturn

  protected int getStateId(java.lang.Object);
    Code:
       0: aload_0
       1: aload_1
       2: checkcast     #49                 // class org/apache/hadoop/hbase/shaded/protobuf/generated/MasterProcedureProtos$SplitWALState
       5: invokevirtual #50                 // Method getStateId:(Lorg/apache/hadoop/hbase/shaded/protobuf/generated/MasterProcedureProtos$SplitWALState;)I
       8: ireturn

  protected java.lang.Object getState(int);
    Code:
       0: aload_0
       1: iload_1
       2: invokevirtual #51                 // Method getState:(I)Lorg/apache/hadoop/hbase/shaded/protobuf/generated/MasterProcedureProtos$SplitWALState;
       5: areturn

  protected void rollbackState(java.lang.Object, java.lang.Object) throws java.io.IOException, java.lang.InterruptedException;
    Code:
       0: aload_0
       1: aload_1
       2: checkcast     #45                 // class org/apache/hadoop/hbase/master/procedure/MasterProcedureEnv
       5: aload_2
       6: checkcast     #49                 // class org/apache/hadoop/hbase/shaded/protobuf/generated/MasterProcedureProtos$SplitWALState
       9: invokevirtual #52                 // Method rollbackState:(Lorg/apache/hadoop/hbase/master/procedure/MasterProcedureEnv;Lorg/apache/hadoop/hbase/shaded/protobuf/generated/MasterProcedureProtos$SplitWALState;)V
      12: return

  protected org.apache.hadoop.hbase.procedure2.StateMachineProcedure$Flow executeFromState(java.lang.Object, java.lang.Object) throws org.apache.hadoop.hbase.procedure2.ProcedureSuspendedException, org.apache.hadoop.hbase.procedure2.ProcedureYieldException, java.lang.InterruptedException;
    Code:
       0: aload_0
       1: aload_1
       2: checkcast     #45                 // class org/apache/hadoop/hbase/master/procedure/MasterProcedureEnv
       5: aload_2
       6: checkcast     #49                 // class org/apache/hadoop/hbase/shaded/protobuf/generated/MasterProcedureProtos$SplitWALState
       9: invokevirtual #53                 // Method executeFromState:(Lorg/apache/hadoop/hbase/master/procedure/MasterProcedureEnv;Lorg/apache/hadoop/hbase/shaded/protobuf/generated/MasterProcedureProtos$SplitWALState;)Lorg/apache/hadoop/hbase/procedure2/StateMachineProcedure$Flow;
      12: areturn

  protected boolean holdLock(java.lang.Object);
    Code:
       0: aload_0
       1: aload_1
       2: checkcast     #45                 // class org/apache/hadoop/hbase/master/procedure/MasterProcedureEnv
       5: invokevirtual #54                 // Method holdLock:(Lorg/apache/hadoop/hbase/master/procedure/MasterProcedureEnv;)Z
       8: ireturn
}
