Compiled from "TestMetaCache.java"
public class org.apache.hadoop.hbase.client.TestMetaCache$RoundRobinExceptionInjector extends org.apache.hadoop.hbase.client.TestMetaCache$ExceptionInjector {
  public org.apache.hadoop.hbase.client.TestMetaCache$RoundRobinExceptionInjector();
    Code:
       0: aload_0
       1: invokespecial #1                  // Method org/apache/hadoop/hbase/client/TestMetaCache$ExceptionInjector."<init>":()V
       4: aload_0
       5: iconst_m1
       6: putfield      #2                  // Field numReqs:I
       9: aload_0
      10: iconst_m1
      11: putfield      #3                  // Field expCount:I
      14: aload_0
      15: invokestatic  #4                  // Method org/apache/hadoop/hbase/client/TestMetaCache.metaCachePreservingExceptions:()Ljava/util/List;
      18: putfield      #5                  // Field metaCachePreservingExceptions:Ljava/util/List;
      21: return

  public void throwOnGet(org.apache.hadoop.hbase.client.TestMetaCache$FakeRSRpcServices, org.apache.hadoop.hbase.shaded.protobuf.generated.ClientProtos$GetRequest) throws org.apache.hbase.thirdparty.com.google.protobuf.ServiceException;
    Code:
       0: aload_0
       1: aload_1
       2: aload_2
       3: invokevirtual #6                  // Method org/apache/hadoop/hbase/shaded/protobuf/generated/ClientProtos$GetRequest.getRegion:()Lorg/apache/hadoop/hbase/shaded/protobuf/generated/HBaseProtos$RegionSpecifier;
       6: invokespecial #7                  // Method throwSomeExceptions:(Lorg/apache/hadoop/hbase/client/TestMetaCache$FakeRSRpcServices;Lorg/apache/hadoop/hbase/shaded/protobuf/generated/HBaseProtos$RegionSpecifier;)V
       9: return

  public void throwOnMutate(org.apache.hadoop.hbase.client.TestMetaCache$FakeRSRpcServices, org.apache.hadoop.hbase.shaded.protobuf.generated.ClientProtos$MutateRequest) throws org.apache.hbase.thirdparty.com.google.protobuf.ServiceException;
    Code:
       0: aload_0
       1: aload_1
       2: aload_2
       3: invokevirtual #8                  // Method org/apache/hadoop/hbase/shaded/protobuf/generated/ClientProtos$MutateRequest.getRegion:()Lorg/apache/hadoop/hbase/shaded/protobuf/generated/HBaseProtos$RegionSpecifier;
       6: invokespecial #7                  // Method throwSomeExceptions:(Lorg/apache/hadoop/hbase/client/TestMetaCache$FakeRSRpcServices;Lorg/apache/hadoop/hbase/shaded/protobuf/generated/HBaseProtos$RegionSpecifier;)V
       9: return

  public void throwOnScan(org.apache.hadoop.hbase.client.TestMetaCache$FakeRSRpcServices, org.apache.hadoop.hbase.shaded.protobuf.generated.ClientProtos$ScanRequest) throws org.apache.hbase.thirdparty.com.google.protobuf.ServiceException;
    Code:
       0: aload_2
       1: invokevirtual #9                  // Method org/apache/hadoop/hbase/shaded/protobuf/generated/ClientProtos$ScanRequest.hasScannerId:()Z
       4: ifne          16
       7: aload_0
       8: aload_1
       9: aload_2
      10: invokevirtual #10                 // Method org/apache/hadoop/hbase/shaded/protobuf/generated/ClientProtos$ScanRequest.getRegion:()Lorg/apache/hadoop/hbase/shaded/protobuf/generated/HBaseProtos$RegionSpecifier;
      13: invokespecial #7                  // Method throwSomeExceptions:(Lorg/apache/hadoop/hbase/client/TestMetaCache$FakeRSRpcServices;Lorg/apache/hadoop/hbase/shaded/protobuf/generated/HBaseProtos$RegionSpecifier;)V
      16: return
}
