Compiled from "TestLockManager.java"
public class org.apache.hadoop.hbase.master.locking.TestLockManager {
  public static final org.apache.hadoop.hbase.HBaseClassTestRule CLASS_RULE;

  public org.junit.rules.TestName testName;

  protected static final org.apache.hadoop.hbase.HBaseTestingUtility UTIL;

  static final boolean $assertionsDisabled;

  public org.apache.hadoop.hbase.master.locking.TestLockManager();
    Code:
       0: aload_0
       1: invokespecial #1                  // Method java/lang/Object."<init>":()V
       4: aload_0
       5: new           #2                  // class org/junit/rules/TestName
       8: dup
       9: invokespecial #3                  // Method org/junit/rules/TestName."<init>":()V
      12: putfield      #4                  // Field testName:Lorg/junit/rules/TestName;
      15: return

  public static void setupCluster() throws java.lang.Exception;
    Code:
       0: getstatic     #13                 // Field UTIL:Lorg/apache/hadoop/hbase/HBaseTestingUtility;
       3: invokevirtual #14                 // Method org/apache/hadoop/hbase/HBaseTestingUtility.getConfiguration:()Lorg/apache/hadoop/conf/Configuration;
       6: invokestatic  #15                 // Method setupConf:(Lorg/apache/hadoop/conf/Configuration;)V
       9: getstatic     #13                 // Field UTIL:Lorg/apache/hadoop/hbase/HBaseTestingUtility;
      12: iconst_1
      13: invokevirtual #16                 // Method org/apache/hadoop/hbase/HBaseTestingUtility.startMiniCluster:(I)Lorg/apache/hadoop/hbase/MiniHBaseCluster;
      16: pop
      17: getstatic     #13                 // Field UTIL:Lorg/apache/hadoop/hbase/HBaseTestingUtility;
      20: invokevirtual #17                 // Method org/apache/hadoop/hbase/HBaseTestingUtility.getMiniHBaseCluster:()Lorg/apache/hadoop/hbase/MiniHBaseCluster;
      23: invokevirtual #18                 // Method org/apache/hadoop/hbase/MiniHBaseCluster.getMaster:()Lorg/apache/hadoop/hbase/master/HMaster;
      26: putstatic     #19                 // Field masterServices:Lorg/apache/hadoop/hbase/master/MasterServices;
      29: getstatic     #13                 // Field UTIL:Lorg/apache/hadoop/hbase/HBaseTestingUtility;
      32: invokevirtual #20                 // Method org/apache/hadoop/hbase/HBaseTestingUtility.getAdmin:()Lorg/apache/hadoop/hbase/client/Admin;
      35: getstatic     #21                 // Field namespace:Ljava/lang/String;
      38: invokestatic  #22                 // Method org/apache/hadoop/hbase/NamespaceDescriptor.create:(Ljava/lang/String;)Lorg/apache/hadoop/hbase/NamespaceDescriptor$Builder;
      41: invokevirtual #23                 // Method org/apache/hadoop/hbase/NamespaceDescriptor$Builder.build:()Lorg/apache/hadoop/hbase/NamespaceDescriptor;
      44: invokeinterface #24,  2           // InterfaceMethod org/apache/hadoop/hbase/client/Admin.createNamespace:(Lorg/apache/hadoop/hbase/NamespaceDescriptor;)V
      49: getstatic     #13                 // Field UTIL:Lorg/apache/hadoop/hbase/HBaseTestingUtility;
      52: getstatic     #25                 // Field tableName:Lorg/apache/hadoop/hbase/TableName;
      55: iconst_1
      56: anewarray     #26                 // class "[B"
      59: dup
      60: iconst_0
      61: ldc           #27                 // String fam
      63: invokestatic  #28                 // Method org/apache/hadoop/hbase/util/Bytes.toBytes:(Ljava/lang/String;)[B
      66: aastore
      67: iconst_1
      68: anewarray     #26                 // class "[B"
      71: dup
      72: iconst_0
      73: ldc           #29                 // String 1
      75: invokestatic  #28                 // Method org/apache/hadoop/hbase/util/Bytes.toBytes:(Ljava/lang/String;)[B
      78: aastore
      79: invokevirtual #30                 // Method org/apache/hadoop/hbase/HBaseTestingUtility.createTable:(Lorg/apache/hadoop/hbase/TableName;[[B[[B)Lorg/apache/hadoop/hbase/client/Table;
      82: pop
      83: getstatic     #13                 // Field UTIL:Lorg/apache/hadoop/hbase/HBaseTestingUtility;
      86: invokevirtual #20                 // Method org/apache/hadoop/hbase/HBaseTestingUtility.getAdmin:()Lorg/apache/hadoop/hbase/client/Admin;
      89: getstatic     #25                 // Field tableName:Lorg/apache/hadoop/hbase/TableName;
      92: invokeinterface #31,  2           // InterfaceMethod org/apache/hadoop/hbase/client/Admin.getRegions:(Lorg/apache/hadoop/hbase/TableName;)Ljava/util/List;
      97: astore_0
      98: getstatic     #32                 // Field $assertionsDisabled:Z
     101: ifne          121
     104: aload_0
     105: invokeinterface #33,  1           // InterfaceMethod java/util/List.size:()I
     110: ifgt          121
     113: new           #34                 // class java/lang/AssertionError
     116: dup
     117: invokespecial #35                 // Method java/lang/AssertionError."<init>":()V
     120: athrow
     121: aload_0
     122: invokeinterface #33,  1           // InterfaceMethod java/util/List.size:()I
     127: anewarray     #36                 // class org/apache/hadoop/hbase/client/RegionInfo
     130: putstatic     #37                 // Field tableRegions:[Lorg/apache/hadoop/hbase/client/RegionInfo;
     133: aload_0
     134: getstatic     #37                 // Field tableRegions:[Lorg/apache/hadoop/hbase/client/RegionInfo;
     137: invokeinterface #38,  2           // InterfaceMethod java/util/List.toArray:([Ljava/lang/Object;)[Ljava/lang/Object;
     142: pop
     143: return

  public static void cleanupTest() throws java.lang.Exception;
    Code:
       0: getstatic     #13                 // Field UTIL:Lorg/apache/hadoop/hbase/HBaseTestingUtility;
       3: invokevirtual #39                 // Method org/apache/hadoop/hbase/HBaseTestingUtility.shutdownMiniCluster:()V
       6: goto          21
       9: astore_0
      10: getstatic     #41                 // Field LOG:Lorg/slf4j/Logger;
      13: ldc           #42                 // String failure shutting down cluster
      15: aload_0
      16: invokeinterface #43,  3           // InterfaceMethod org/slf4j/Logger.warn:(Ljava/lang/String;Ljava/lang/Throwable;)V
      21: return
    Exception table:
       from    to  target type
           0     6     9   Class java/lang/Exception

  public void tearDown() throws java.lang.Exception;
    Code:
       0: aload_0
       1: invokespecial #44                 // Method getMasterProcedureExecutor:()Lorg/apache/hadoop/hbase/procedure2/ProcedureExecutor;
       4: invokevirtual #45                 // Method org/apache/hadoop/hbase/procedure2/ProcedureExecutor.getProcedures:()Ljava/util/List;
       7: invokeinterface #46,  1           // InterfaceMethod java/util/List.iterator:()Ljava/util/Iterator;
      12: astore_1
      13: aload_1
      14: invokeinterface #47,  1           // InterfaceMethod java/util/Iterator.hasNext:()Z
      19: ifeq          67
      22: aload_1
      23: invokeinterface #48,  1           // InterfaceMethod java/util/Iterator.next:()Ljava/lang/Object;
      28: checkcast     #49                 // class org/apache/hadoop/hbase/procedure2/Procedure
      31: astore_2
      32: aload_2
      33: instanceof    #10                 // class org/apache/hadoop/hbase/master/locking/LockProcedure
      36: ifeq          64
      39: aload_2
      40: checkcast     #10                 // class org/apache/hadoop/hbase/master/locking/LockProcedure
      43: aload_0
      44: invokespecial #44                 // Method getMasterProcedureExecutor:()Lorg/apache/hadoop/hbase/procedure2/ProcedureExecutor;
      47: invokevirtual #50                 // Method org/apache/hadoop/hbase/procedure2/ProcedureExecutor.getEnvironment:()Ljava/lang/Object;
      50: checkcast     #51                 // class org/apache/hadoop/hbase/master/procedure/MasterProcedureEnv
      53: invokevirtual #52                 // Method org/apache/hadoop/hbase/master/locking/LockProcedure.unlock:(Lorg/apache/hadoop/hbase/master/procedure/MasterProcedureEnv;)V
      56: aload_0
      57: invokespecial #44                 // Method getMasterProcedureExecutor:()Lorg/apache/hadoop/hbase/procedure2/ProcedureExecutor;
      60: aload_2
      61: invokestatic  #53                 // Method org/apache/hadoop/hbase/procedure2/ProcedureTestingUtility.waitProcedure:(Lorg/apache/hadoop/hbase/procedure2/ProcedureExecutor;Lorg/apache/hadoop/hbase/procedure2/Procedure;)V
      64: goto          13
      67: lconst_0
      68: aload_0
      69: invokespecial #44                 // Method getMasterProcedureExecutor:()Lorg/apache/hadoop/hbase/procedure2/ProcedureExecutor;
      72: invokevirtual #50                 // Method org/apache/hadoop/hbase/procedure2/ProcedureExecutor.getEnvironment:()Ljava/lang/Object;
      75: checkcast     #51                 // class org/apache/hadoop/hbase/master/procedure/MasterProcedureEnv
      78: invokevirtual #54                 // Method org/apache/hadoop/hbase/master/procedure/MasterProcedureEnv.getProcedureScheduler:()Lorg/apache/hadoop/hbase/master/procedure/MasterProcedureScheduler;
      81: invokevirtual #55                 // Method org/apache/hadoop/hbase/master/procedure/MasterProcedureScheduler.size:()I
      84: i2l
      85: invokestatic  #56                 // Method org/junit/Assert.assertEquals:(JJ)V
      88: return

  public void testMasterLockAcquire() throws java.lang.Exception;
    Code:
       0: getstatic     #19                 // Field masterServices:Lorg/apache/hadoop/hbase/master/MasterServices;
       3: invokeinterface #59,  1           // InterfaceMethod org/apache/hadoop/hbase/master/MasterServices.getLockManager:()Lorg/apache/hadoop/hbase/master/locking/LockManager;
       8: getstatic     #21                 // Field namespace:Ljava/lang/String;
      11: getstatic     #60                 // Field org/apache/hadoop/hbase/procedure2/LockType.EXCLUSIVE:Lorg/apache/hadoop/hbase/procedure2/LockType;
      14: ldc           #61                 // String desc
      16: invokevirtual #62                 // Method org/apache/hadoop/hbase/master/locking/LockManager.createMasterLock:(Ljava/lang/String;Lorg/apache/hadoop/hbase/procedure2/LockType;Ljava/lang/String;)Lorg/apache/hadoop/hbase/master/locking/LockManager$MasterLock;
      19: astore_1
      20: aload_1
      21: ldc2_w        #63                 // long 2000l
      24: invokevirtual #65                 // Method org/apache/hadoop/hbase/master/locking/LockManager$MasterLock.tryAcquire:(J)Z
      27: invokestatic  #66                 // Method org/junit/Assert.assertTrue:(Z)V
      30: aload_1
      31: invokevirtual #67                 // Method org/apache/hadoop/hbase/master/locking/LockManager$MasterLock.getProc:()Lorg/apache/hadoop/hbase/master/locking/LockProcedure;
      34: invokevirtual #68                 // Method org/apache/hadoop/hbase/master/locking/LockProcedure.isLocked:()Z
      37: invokestatic  #66                 // Method org/junit/Assert.assertTrue:(Z)V
      40: aload_1
      41: invokevirtual #69                 // Method org/apache/hadoop/hbase/master/locking/LockManager$MasterLock.release:()V
      44: aconst_null
      45: aload_1
      46: invokevirtual #67                 // Method org/apache/hadoop/hbase/master/locking/LockManager$MasterLock.getProc:()Lorg/apache/hadoop/hbase/master/locking/LockProcedure;
      49: invokestatic  #70                 // Method org/junit/Assert.assertEquals:(Ljava/lang/Object;Ljava/lang/Object;)V
      52: return

  public void testMasterLockAcquireTimeout() throws java.lang.Exception;
    Code:
       0: getstatic     #19                 // Field masterServices:Lorg/apache/hadoop/hbase/master/MasterServices;
       3: invokeinterface #59,  1           // InterfaceMethod org/apache/hadoop/hbase/master/MasterServices.getLockManager:()Lorg/apache/hadoop/hbase/master/locking/LockManager;
       8: getstatic     #25                 // Field tableName:Lorg/apache/hadoop/hbase/TableName;
      11: getstatic     #60                 // Field org/apache/hadoop/hbase/procedure2/LockType.EXCLUSIVE:Lorg/apache/hadoop/hbase/procedure2/LockType;
      14: ldc           #61                 // String desc
      16: invokevirtual #71                 // Method org/apache/hadoop/hbase/master/locking/LockManager.createMasterLock:(Lorg/apache/hadoop/hbase/TableName;Lorg/apache/hadoop/hbase/procedure2/LockType;Ljava/lang/String;)Lorg/apache/hadoop/hbase/master/locking/LockManager$MasterLock;
      19: astore_1
      20: getstatic     #19                 // Field masterServices:Lorg/apache/hadoop/hbase/master/MasterServices;
      23: invokeinterface #59,  1           // InterfaceMethod org/apache/hadoop/hbase/master/MasterServices.getLockManager:()Lorg/apache/hadoop/hbase/master/locking/LockManager;
      28: getstatic     #25                 // Field tableName:Lorg/apache/hadoop/hbase/TableName;
      31: getstatic     #60                 // Field org/apache/hadoop/hbase/procedure2/LockType.EXCLUSIVE:Lorg/apache/hadoop/hbase/procedure2/LockType;
      34: ldc           #61                 // String desc
      36: invokevirtual #71                 // Method org/apache/hadoop/hbase/master/locking/LockManager.createMasterLock:(Lorg/apache/hadoop/hbase/TableName;Lorg/apache/hadoop/hbase/procedure2/LockType;Ljava/lang/String;)Lorg/apache/hadoop/hbase/master/locking/LockManager$MasterLock;
      39: astore_2
      40: aload_1
      41: ldc2_w        #63                 // long 2000l
      44: invokevirtual #65                 // Method org/apache/hadoop/hbase/master/locking/LockManager$MasterLock.tryAcquire:(J)Z
      47: invokestatic  #66                 // Method org/junit/Assert.assertTrue:(Z)V
      50: aload_2
      51: ldc2_w        #72                 // long 500l
      54: invokevirtual #65                 // Method org/apache/hadoop/hbase/master/locking/LockManager$MasterLock.tryAcquire:(J)Z
      57: invokestatic  #74                 // Method org/junit/Assert.assertFalse:(Z)V
      60: aconst_null
      61: aload_2
      62: invokevirtual #67                 // Method org/apache/hadoop/hbase/master/locking/LockManager$MasterLock.getProc:()Lorg/apache/hadoop/hbase/master/locking/LockProcedure;
      65: invokestatic  #70                 // Method org/junit/Assert.assertEquals:(Ljava/lang/Object;Ljava/lang/Object;)V
      68: aload_1
      69: invokevirtual #69                 // Method org/apache/hadoop/hbase/master/locking/LockManager$MasterLock.release:()V
      72: aload_2
      73: ldc2_w        #63                 // long 2000l
      76: invokevirtual #65                 // Method org/apache/hadoop/hbase/master/locking/LockManager$MasterLock.tryAcquire:(J)Z
      79: invokestatic  #66                 // Method org/junit/Assert.assertTrue:(Z)V
      82: aload_2
      83: invokevirtual #67                 // Method org/apache/hadoop/hbase/master/locking/LockManager$MasterLock.getProc:()Lorg/apache/hadoop/hbase/master/locking/LockProcedure;
      86: invokevirtual #68                 // Method org/apache/hadoop/hbase/master/locking/LockProcedure.isLocked:()Z
      89: invokestatic  #66                 // Method org/junit/Assert.assertTrue:(Z)V
      92: aload_2
      93: invokevirtual #69                 // Method org/apache/hadoop/hbase/master/locking/LockManager$MasterLock.release:()V
      96: return

  public void testMasterLockAcquireTimeoutRegionVsTableExclusive() throws java.lang.Exception;
    Code:
       0: getstatic     #19                 // Field masterServices:Lorg/apache/hadoop/hbase/master/MasterServices;
       3: invokeinterface #59,  1           // InterfaceMethod org/apache/hadoop/hbase/master/MasterServices.getLockManager:()Lorg/apache/hadoop/hbase/master/locking/LockManager;
       8: getstatic     #37                 // Field tableRegions:[Lorg/apache/hadoop/hbase/client/RegionInfo;
      11: ldc           #61                 // String desc
      13: invokevirtual #75                 // Method org/apache/hadoop/hbase/master/locking/LockManager.createMasterLock:([Lorg/apache/hadoop/hbase/client/RegionInfo;Ljava/lang/String;)Lorg/apache/hadoop/hbase/master/locking/LockManager$MasterLock;
      16: astore_1
      17: getstatic     #19                 // Field masterServices:Lorg/apache/hadoop/hbase/master/MasterServices;
      20: invokeinterface #59,  1           // InterfaceMethod org/apache/hadoop/hbase/master/MasterServices.getLockManager:()Lorg/apache/hadoop/hbase/master/locking/LockManager;
      25: getstatic     #25                 // Field tableName:Lorg/apache/hadoop/hbase/TableName;
      28: getstatic     #60                 // Field org/apache/hadoop/hbase/procedure2/LockType.EXCLUSIVE:Lorg/apache/hadoop/hbase/procedure2/LockType;
      31: ldc           #61                 // String desc
      33: invokevirtual #71                 // Method org/apache/hadoop/hbase/master/locking/LockManager.createMasterLock:(Lorg/apache/hadoop/hbase/TableName;Lorg/apache/hadoop/hbase/procedure2/LockType;Ljava/lang/String;)Lorg/apache/hadoop/hbase/master/locking/LockManager$MasterLock;
      36: astore_2
      37: aload_1
      38: ldc2_w        #63                 // long 2000l
      41: invokevirtual #65                 // Method org/apache/hadoop/hbase/master/locking/LockManager$MasterLock.tryAcquire:(J)Z
      44: invokestatic  #66                 // Method org/junit/Assert.assertTrue:(Z)V
      47: aload_2
      48: ldc2_w        #72                 // long 500l
      51: invokevirtual #65                 // Method org/apache/hadoop/hbase/master/locking/LockManager$MasterLock.tryAcquire:(J)Z
      54: invokestatic  #74                 // Method org/junit/Assert.assertFalse:(Z)V
      57: aconst_null
      58: aload_2
      59: invokevirtual #67                 // Method org/apache/hadoop/hbase/master/locking/LockManager$MasterLock.getProc:()Lorg/apache/hadoop/hbase/master/locking/LockProcedure;
      62: invokestatic  #70                 // Method org/junit/Assert.assertEquals:(Ljava/lang/Object;Ljava/lang/Object;)V
      65: aload_1
      66: invokevirtual #69                 // Method org/apache/hadoop/hbase/master/locking/LockManager$MasterLock.release:()V
      69: aload_2
      70: ldc2_w        #63                 // long 2000l
      73: invokevirtual #65                 // Method org/apache/hadoop/hbase/master/locking/LockManager$MasterLock.tryAcquire:(J)Z
      76: invokestatic  #66                 // Method org/junit/Assert.assertTrue:(Z)V
      79: aload_2
      80: invokevirtual #67                 // Method org/apache/hadoop/hbase/master/locking/LockManager$MasterLock.getProc:()Lorg/apache/hadoop/hbase/master/locking/LockProcedure;
      83: invokevirtual #68                 // Method org/apache/hadoop/hbase/master/locking/LockProcedure.isLocked:()Z
      86: invokestatic  #66                 // Method org/junit/Assert.assertTrue:(Z)V
      89: aload_2
      90: invokevirtual #69                 // Method org/apache/hadoop/hbase/master/locking/LockManager$MasterLock.release:()V
      93: return

  static {};
    Code:
       0: ldc           #12                 // class org/apache/hadoop/hbase/master/locking/TestLockManager
       2: invokevirtual #76                 // Method java/lang/Class.desiredAssertionStatus:()Z
       5: ifne          12
       8: iconst_1
       9: goto          13
      12: iconst_0
      13: putstatic     #32                 // Field $assertionsDisabled:Z
      16: ldc           #12                 // class org/apache/hadoop/hbase/master/locking/TestLockManager
      18: invokestatic  #77                 // Method org/apache/hadoop/hbase/HBaseClassTestRule.forClass:(Ljava/lang/Class;)Lorg/apache/hadoop/hbase/HBaseClassTestRule;
      21: putstatic     #78                 // Field CLASS_RULE:Lorg/apache/hadoop/hbase/HBaseClassTestRule;
      24: ldc           #12                 // class org/apache/hadoop/hbase/master/locking/TestLockManager
      26: invokestatic  #79                 // Method org/slf4j/LoggerFactory.getLogger:(Ljava/lang/Class;)Lorg/slf4j/Logger;
      29: putstatic     #41                 // Field LOG:Lorg/slf4j/Logger;
      32: new           #80                 // class org/apache/hadoop/hbase/HBaseTestingUtility
      35: dup
      36: invokespecial #81                 // Method org/apache/hadoop/hbase/HBaseTestingUtility."<init>":()V
      39: putstatic     #13                 // Field UTIL:Lorg/apache/hadoop/hbase/HBaseTestingUtility;
      42: ldc           #82                 // String namespace
      44: putstatic     #21                 // Field namespace:Ljava/lang/String;
      47: getstatic     #21                 // Field namespace:Ljava/lang/String;
      50: ldc           #83                 // String table
      52: invokestatic  #84                 // Method org/apache/hadoop/hbase/TableName.valueOf:(Ljava/lang/String;Ljava/lang/String;)Lorg/apache/hadoop/hbase/TableName;
      55: putstatic     #25                 // Field tableName:Lorg/apache/hadoop/hbase/TableName;
      58: return
}
