Compiled from "TestSpaceQuotasWithSnapshots.java"
class org.apache.hadoop.hbase.quotas.TestSpaceQuotasWithSnapshots$6 implements org.apache.hadoop.hbase.Waiter$Predicate<java.lang.Exception> {
  final org.apache.hadoop.hbase.TableName val$tn;

  final org.apache.hadoop.hbase.quotas.TestSpaceQuotasWithSnapshots this$0;

  org.apache.hadoop.hbase.quotas.TestSpaceQuotasWithSnapshots$6(org.apache.hadoop.hbase.quotas.TestSpaceQuotasWithSnapshots, org.apache.hadoop.hbase.TableName);
    Code:
       0: aload_0
       1: aload_1
       2: putfield      #1                  // Field this$0:Lorg/apache/hadoop/hbase/quotas/TestSpaceQuotasWithSnapshots;
       5: aload_0
       6: aload_2
       7: putfield      #2                  // Field val$tn:Lorg/apache/hadoop/hbase/TableName;
      10: aload_0
      11: invokespecial #3                  // Method java/lang/Object."<init>":()V
      14: return

  public boolean evaluate() throws java.lang.Exception;
    Code:
       0: aload_0
       1: getfield      #1                  // Field this$0:Lorg/apache/hadoop/hbase/quotas/TestSpaceQuotasWithSnapshots;
       4: invokestatic  #4                  // Method org/apache/hadoop/hbase/quotas/TestSpaceQuotasWithSnapshots.access$000:(Lorg/apache/hadoop/hbase/quotas/TestSpaceQuotasWithSnapshots;)Lorg/apache/hadoop/hbase/client/Connection;
       7: invokeinterface #5,  1            // InterfaceMethod org/apache/hadoop/hbase/client/Connection.getAdmin:()Lorg/apache/hadoop/hbase/client/Admin;
      12: invokeinterface #6,  1            // InterfaceMethod org/apache/hadoop/hbase/client/Admin.getSpaceQuotaTableSizes:()Ljava/util/Map;
      17: astore_1
      18: invokestatic  #7                  // Method org/apache/hadoop/hbase/quotas/TestSpaceQuotasWithSnapshots.access$100:()Lorg/slf4j/Logger;
      21: new           #8                  // class java/lang/StringBuilder
      24: dup
      25: invokespecial #9                  // Method java/lang/StringBuilder."<init>":()V
      28: ldc           #10                 // String Master observed table sizes from region size reports:
      30: invokevirtual #11                 // Method java/lang/StringBuilder.append:(Ljava/lang/String;)Ljava/lang/StringBuilder;
      33: aload_1
      34: invokevirtual #12                 // Method java/lang/StringBuilder.append:(Ljava/lang/Object;)Ljava/lang/StringBuilder;
      37: invokevirtual #13                 // Method java/lang/StringBuilder.toString:()Ljava/lang/String;
      40: invokeinterface #14,  2           // InterfaceMethod org/slf4j/Logger.debug:(Ljava/lang/String;)V
      45: aload_1
      46: aload_0
      47: getfield      #2                  // Field val$tn:Lorg/apache/hadoop/hbase/TableName;
      50: invokeinterface #15,  2           // InterfaceMethod java/util/Map.get:(Ljava/lang/Object;)Ljava/lang/Object;
      55: checkcast     #16                 // class java/lang/Long
      58: astore_2
      59: aconst_null
      60: aload_2
      61: if_acmpne     66
      64: iconst_0
      65: ireturn
      66: aload_2
      67: invokevirtual #17                 // Method java/lang/Long.longValue:()J
      70: ldc2_w        #18                 // long 2609152l
      73: lcmp
      74: ifge          92
      77: aload_2
      78: invokevirtual #17                 // Method java/lang/Long.longValue:()J
      81: ldc2_w        #20                 // long 1585152l
      84: lcmp
      85: ifle          92
      88: iconst_1
      89: goto          93
      92: iconst_0
      93: ireturn
}
