Compiled from "TestHFile.java"
class org.apache.hadoop.hbase.io.hfile.TestHFile$1 implements org.apache.hadoop.io.Writable {
  final org.apache.hadoop.hbase.io.hfile.TestHFile this$0;

  org.apache.hadoop.hbase.io.hfile.TestHFile$1(org.apache.hadoop.hbase.io.hfile.TestHFile);
    Code:
       0: aload_0
       1: aload_1
       2: putfield      #1                  // Field this$0:Lorg/apache/hadoop/hbase/io/hfile/TestHFile;
       5: aload_0
       6: invokespecial #2                  // Method java/lang/Object."<init>":()V
       9: return

  public org.apache.hadoop.io.Writable setVal(int);
    Code:
       0: aload_0
       1: iload_1
       2: putfield      #3                  // Field val:I
       5: aload_0
       6: areturn

  public void write(java.io.DataOutput) throws java.io.IOException;
    Code:
       0: aload_1
       1: new           #4                  // class java/lang/StringBuilder
       4: dup
       5: invokespecial #5                  // Method java/lang/StringBuilder."<init>":()V
       8: ldc           #6                  // String something to test
      10: invokevirtual #7                  // Method java/lang/StringBuilder.append:(Ljava/lang/String;)Ljava/lang/StringBuilder;
      13: aload_0
      14: getfield      #3                  // Field val:I
      17: invokevirtual #8                  // Method java/lang/StringBuilder.append:(I)Ljava/lang/StringBuilder;
      20: invokevirtual #9                  // Method java/lang/StringBuilder.toString:()Ljava/lang/String;
      23: invokestatic  #10                 // Method org/apache/hadoop/hbase/util/Bytes.toBytes:(Ljava/lang/String;)[B
      26: invokeinterface #11,  2           // InterfaceMethod java/io/DataOutput.write:([B)V
      31: return

  public void readFields(java.io.DataInput) throws java.io.IOException;
    Code:
       0: return
}
