Compiled from "TestProcedureEvents.java"
public class org.apache.hadoop.hbase.procedure2.TestProcedureEvents$TestTimeoutEventProcedure extends org.apache.hadoop.hbase.procedure2.ProcedureTestingUtility$NoopProcedure<org.apache.hadoop.hbase.procedure2.TestProcedureEvents$TestProcEnv> {
  public org.apache.hadoop.hbase.procedure2.TestProcedureEvents$TestTimeoutEventProcedure();
    Code:
       0: aload_0
       1: invokespecial #1                  // Method org/apache/hadoop/hbase/procedure2/ProcedureTestingUtility$NoopProcedure."<init>":()V
       4: aload_0
       5: new           #2                  // class org/apache/hadoop/hbase/procedure2/ProcedureEvent
       8: dup
       9: ldc           #3                  // String timeout-event
      11: invokespecial #4                  // Method org/apache/hadoop/hbase/procedure2/ProcedureEvent."<init>":(Ljava/lang/Object;)V
      14: putfield      #5                  // Field event:Lorg/apache/hadoop/hbase/procedure2/ProcedureEvent;
      17: aload_0
      18: new           #6                  // class java/util/concurrent/atomic/AtomicInteger
      21: dup
      22: iconst_0
      23: invokespecial #7                  // Method java/util/concurrent/atomic/AtomicInteger."<init>":(I)V
      26: putfield      #8                  // Field ntimeouts:Ljava/util/concurrent/atomic/AtomicInteger;
      29: aload_0
      30: iconst_1
      31: putfield      #9                  // Field maxTimeouts:I
      34: return

  public org.apache.hadoop.hbase.procedure2.TestProcedureEvents$TestTimeoutEventProcedure(int, int);
    Code:
       0: aload_0
       1: invokespecial #1                  // Method org/apache/hadoop/hbase/procedure2/ProcedureTestingUtility$NoopProcedure."<init>":()V
       4: aload_0
       5: new           #2                  // class org/apache/hadoop/hbase/procedure2/ProcedureEvent
       8: dup
       9: ldc           #3                  // String timeout-event
      11: invokespecial #4                  // Method org/apache/hadoop/hbase/procedure2/ProcedureEvent."<init>":(Ljava/lang/Object;)V
      14: putfield      #5                  // Field event:Lorg/apache/hadoop/hbase/procedure2/ProcedureEvent;
      17: aload_0
      18: new           #6                  // class java/util/concurrent/atomic/AtomicInteger
      21: dup
      22: iconst_0
      23: invokespecial #7                  // Method java/util/concurrent/atomic/AtomicInteger."<init>":(I)V
      26: putfield      #8                  // Field ntimeouts:Ljava/util/concurrent/atomic/AtomicInteger;
      29: aload_0
      30: iconst_1
      31: putfield      #9                  // Field maxTimeouts:I
      34: aload_0
      35: iload_2
      36: putfield      #9                  // Field maxTimeouts:I
      39: aload_0
      40: iload_1
      41: invokevirtual #10                 // Method setTimeout:(I)V
      44: return

  public int getTimeoutsCount();
    Code:
       0: aload_0
       1: getfield      #8                  // Field ntimeouts:Ljava/util/concurrent/atomic/AtomicInteger;
       4: invokevirtual #11                 // Method java/util/concurrent/atomic/AtomicInteger.get:()I
       7: ireturn

  protected org.apache.hadoop.hbase.procedure2.Procedure[] execute(org.apache.hadoop.hbase.procedure2.TestProcedureEvents$TestProcEnv) throws org.apache.hadoop.hbase.procedure2.ProcedureSuspendedException;
    Code:
       0: invokestatic  #12                 // Method org/apache/hadoop/hbase/procedure2/TestProcedureEvents.access$100:()Lorg/slf4j/Logger;
       3: new           #13                 // class java/lang/StringBuilder
       6: dup
       7: invokespecial #14                 // Method java/lang/StringBuilder."<init>":()V
      10: ldc           #15                 // String EXECUTE
      12: invokevirtual #16                 // Method java/lang/StringBuilder.append:(Ljava/lang/String;)Ljava/lang/StringBuilder;
      15: aload_0
      16: invokevirtual #17                 // Method java/lang/StringBuilder.append:(Ljava/lang/Object;)Ljava/lang/StringBuilder;
      19: ldc           #18                 // String  ntimeouts=
      21: invokevirtual #16                 // Method java/lang/StringBuilder.append:(Ljava/lang/String;)Ljava/lang/StringBuilder;
      24: aload_0
      25: getfield      #8                  // Field ntimeouts:Ljava/util/concurrent/atomic/AtomicInteger;
      28: invokevirtual #17                 // Method java/lang/StringBuilder.append:(Ljava/lang/Object;)Ljava/lang/StringBuilder;
      31: invokevirtual #19                 // Method java/lang/StringBuilder.toString:()Ljava/lang/String;
      34: invokeinterface #20,  2           // InterfaceMethod org/slf4j/Logger.info:(Ljava/lang/String;)V
      39: aload_0
      40: getfield      #8                  // Field ntimeouts:Ljava/util/concurrent/atomic/AtomicInteger;
      43: invokevirtual #11                 // Method java/util/concurrent/atomic/AtomicInteger.get:()I
      46: aload_0
      47: getfield      #9                  // Field maxTimeouts:I
      50: if_icmple     86
      53: aload_0
      54: ldc           #21                 // String test
      56: new           #13                 // class java/lang/StringBuilder
      59: dup
      60: invokespecial #14                 // Method java/lang/StringBuilder."<init>":()V
      63: ldc           #22                 // String give up after
      65: invokevirtual #16                 // Method java/lang/StringBuilder.append:(Ljava/lang/String;)Ljava/lang/StringBuilder;
      68: aload_0
      69: getfield      #8                  // Field ntimeouts:Ljava/util/concurrent/atomic/AtomicInteger;
      72: invokevirtual #11                 // Method java/util/concurrent/atomic/AtomicInteger.get:()I
      75: invokevirtual #23                 // Method java/lang/StringBuilder.append:(I)Ljava/lang/StringBuilder;
      78: invokevirtual #19                 // Method java/lang/StringBuilder.toString:()Ljava/lang/String;
      81: invokevirtual #24                 // Method setAbortFailure:(Ljava/lang/String;Ljava/lang/String;)V
      84: aconst_null
      85: areturn
      86: aload_0
      87: getfield      #5                  // Field event:Lorg/apache/hadoop/hbase/procedure2/ProcedureEvent;
      90: invokevirtual #25                 // Method org/apache/hadoop/hbase/procedure2/ProcedureEvent.suspend:()V
      93: aload_0
      94: getfield      #5                  // Field event:Lorg/apache/hadoop/hbase/procedure2/ProcedureEvent;
      97: aload_0
      98: invokevirtual #26                 // Method org/apache/hadoop/hbase/procedure2/ProcedureEvent.suspendIfNotReady:(Lorg/apache/hadoop/hbase/procedure2/Procedure;)Z
     101: ifeq          119
     104: aload_0
     105: getstatic     #27                 // Field org/apache/hadoop/hbase/shaded/protobuf/generated/ProcedureProtos$ProcedureState.WAITING_TIMEOUT:Lorg/apache/hadoop/hbase/shaded/protobuf/generated/ProcedureProtos$ProcedureState;
     108: invokevirtual #28                 // Method setState:(Lorg/apache/hadoop/hbase/shaded/protobuf/generated/ProcedureProtos$ProcedureState;)V
     111: new           #29                 // class org/apache/hadoop/hbase/procedure2/ProcedureSuspendedException
     114: dup
     115: invokespecial #30                 // Method org/apache/hadoop/hbase/procedure2/ProcedureSuspendedException."<init>":()V
     118: athrow
     119: aconst_null
     120: areturn

  protected synchronized boolean setTimeoutFailure(org.apache.hadoop.hbase.procedure2.TestProcedureEvents$TestProcEnv);
    Code:
       0: aload_0
       1: getfield      #8                  // Field ntimeouts:Ljava/util/concurrent/atomic/AtomicInteger;
       4: invokevirtual #31                 // Method java/util/concurrent/atomic/AtomicInteger.incrementAndGet:()I
       7: istore_2
       8: invokestatic  #12                 // Method org/apache/hadoop/hbase/procedure2/TestProcedureEvents.access$100:()Lorg/slf4j/Logger;
      11: new           #13                 // class java/lang/StringBuilder
      14: dup
      15: invokespecial #14                 // Method java/lang/StringBuilder."<init>":()V
      18: ldc           #32                 // String HANDLE TIMEOUT
      20: invokevirtual #16                 // Method java/lang/StringBuilder.append:(Ljava/lang/String;)Ljava/lang/StringBuilder;
      23: aload_0
      24: invokevirtual #17                 // Method java/lang/StringBuilder.append:(Ljava/lang/Object;)Ljava/lang/StringBuilder;
      27: ldc           #18                 // String  ntimeouts=
      29: invokevirtual #16                 // Method java/lang/StringBuilder.append:(Ljava/lang/String;)Ljava/lang/StringBuilder;
      32: iload_2
      33: invokevirtual #23                 // Method java/lang/StringBuilder.append:(I)Ljava/lang/StringBuilder;
      36: invokevirtual #19                 // Method java/lang/StringBuilder.toString:()Ljava/lang/String;
      39: invokeinterface #20,  2           // InterfaceMethod org/slf4j/Logger.info:(Ljava/lang/String;)V
      44: aload_0
      45: getstatic     #33                 // Field org/apache/hadoop/hbase/shaded/protobuf/generated/ProcedureProtos$ProcedureState.RUNNABLE:Lorg/apache/hadoop/hbase/shaded/protobuf/generated/ProcedureProtos$ProcedureState;
      48: invokevirtual #28                 // Method setState:(Lorg/apache/hadoop/hbase/shaded/protobuf/generated/ProcedureProtos$ProcedureState;)V
      51: aload_0
      52: getfield      #5                  // Field event:Lorg/apache/hadoop/hbase/procedure2/ProcedureEvent;
      55: aload_1
      56: invokevirtual #34                 // Method org/apache/hadoop/hbase/procedure2/TestProcedureEvents$TestProcEnv.getProcedureScheduler:()Lorg/apache/hadoop/hbase/procedure2/ProcedureScheduler;
      59: checkcast     #35                 // class org/apache/hadoop/hbase/procedure2/AbstractProcedureScheduler
      62: invokevirtual #36                 // Method org/apache/hadoop/hbase/procedure2/ProcedureEvent.wake:(Lorg/apache/hadoop/hbase/procedure2/AbstractProcedureScheduler;)V
      65: iconst_0
      66: ireturn

  protected void afterReplay(org.apache.hadoop.hbase.procedure2.TestProcedureEvents$TestProcEnv);
    Code:
       0: aload_0
       1: invokevirtual #37                 // Method getState:()Lorg/apache/hadoop/hbase/shaded/protobuf/generated/ProcedureProtos$ProcedureState;
       4: getstatic     #27                 // Field org/apache/hadoop/hbase/shaded/protobuf/generated/ProcedureProtos$ProcedureState.WAITING_TIMEOUT:Lorg/apache/hadoop/hbase/shaded/protobuf/generated/ProcedureProtos$ProcedureState;
       7: if_acmpne     26
      10: aload_0
      11: getfield      #5                  // Field event:Lorg/apache/hadoop/hbase/procedure2/ProcedureEvent;
      14: invokevirtual #25                 // Method org/apache/hadoop/hbase/procedure2/ProcedureEvent.suspend:()V
      17: aload_0
      18: getfield      #5                  // Field event:Lorg/apache/hadoop/hbase/procedure2/ProcedureEvent;
      21: aload_0
      22: invokevirtual #26                 // Method org/apache/hadoop/hbase/procedure2/ProcedureEvent.suspendIfNotReady:(Lorg/apache/hadoop/hbase/procedure2/Procedure;)Z
      25: pop
      26: return

  protected void serializeStateData(org.apache.hadoop.hbase.procedure2.ProcedureStateSerializer) throws java.io.IOException;
    Code:
       0: invokestatic  #38                 // Method org/apache/hbase/thirdparty/com/google/protobuf/Int32Value.newBuilder:()Lorg/apache/hbase/thirdparty/com/google/protobuf/Int32Value$Builder;
       3: aload_0
       4: getfield      #8                  // Field ntimeouts:Ljava/util/concurrent/atomic/AtomicInteger;
       7: invokevirtual #11                 // Method java/util/concurrent/atomic/AtomicInteger.get:()I
      10: invokevirtual #39                 // Method org/apache/hbase/thirdparty/com/google/protobuf/Int32Value$Builder.setValue:(I)Lorg/apache/hbase/thirdparty/com/google/protobuf/Int32Value$Builder;
      13: astore_2
      14: aload_1
      15: aload_2
      16: invokevirtual #40                 // Method org/apache/hbase/thirdparty/com/google/protobuf/Int32Value$Builder.build:()Lorg/apache/hbase/thirdparty/com/google/protobuf/Int32Value;
      19: invokeinterface #41,  2           // InterfaceMethod org/apache/hadoop/hbase/procedure2/ProcedureStateSerializer.serialize:(Lorg/apache/hbase/thirdparty/com/google/protobuf/Message;)V
      24: invokestatic  #38                 // Method org/apache/hbase/thirdparty/com/google/protobuf/Int32Value.newBuilder:()Lorg/apache/hbase/thirdparty/com/google/protobuf/Int32Value$Builder;
      27: aload_0
      28: getfield      #9                  // Field maxTimeouts:I
      31: invokevirtual #39                 // Method org/apache/hbase/thirdparty/com/google/protobuf/Int32Value$Builder.setValue:(I)Lorg/apache/hbase/thirdparty/com/google/protobuf/Int32Value$Builder;
      34: astore_3
      35: aload_1
      36: aload_3
      37: invokevirtual #40                 // Method org/apache/hbase/thirdparty/com/google/protobuf/Int32Value$Builder.build:()Lorg/apache/hbase/thirdparty/com/google/protobuf/Int32Value;
      40: invokeinterface #41,  2           // InterfaceMethod org/apache/hadoop/hbase/procedure2/ProcedureStateSerializer.serialize:(Lorg/apache/hbase/thirdparty/com/google/protobuf/Message;)V
      45: return

  protected void deserializeStateData(org.apache.hadoop.hbase.procedure2.ProcedureStateSerializer) throws java.io.IOException;
    Code:
       0: aload_1
       1: ldc           #42                 // class org/apache/hbase/thirdparty/com/google/protobuf/Int32Value
       3: invokeinterface #43,  2           // InterfaceMethod org/apache/hadoop/hbase/procedure2/ProcedureStateSerializer.deserialize:(Ljava/lang/Class;)Lorg/apache/hbase/thirdparty/com/google/protobuf/Message;
       8: checkcast     #42                 // class org/apache/hbase/thirdparty/com/google/protobuf/Int32Value
      11: astore_2
      12: aload_0
      13: getfield      #8                  // Field ntimeouts:Ljava/util/concurrent/atomic/AtomicInteger;
      16: aload_2
      17: invokevirtual #44                 // Method org/apache/hbase/thirdparty/com/google/protobuf/Int32Value.getValue:()I
      20: invokevirtual #45                 // Method java/util/concurrent/atomic/AtomicInteger.set:(I)V
      23: aload_1
      24: ldc           #42                 // class org/apache/hbase/thirdparty/com/google/protobuf/Int32Value
      26: invokeinterface #43,  2           // InterfaceMethod org/apache/hadoop/hbase/procedure2/ProcedureStateSerializer.deserialize:(Ljava/lang/Class;)Lorg/apache/hbase/thirdparty/com/google/protobuf/Message;
      31: checkcast     #42                 // class org/apache/hbase/thirdparty/com/google/protobuf/Int32Value
      34: astore_3
      35: aload_0
      36: aload_3
      37: invokevirtual #44                 // Method org/apache/hbase/thirdparty/com/google/protobuf/Int32Value.getValue:()I
      40: putfield      #9                  // Field maxTimeouts:I
      43: return

  protected org.apache.hadoop.hbase.procedure2.Procedure[] execute(java.lang.Object) throws org.apache.hadoop.hbase.procedure2.ProcedureYieldException, org.apache.hadoop.hbase.procedure2.ProcedureSuspendedException, java.lang.InterruptedException;
    Code:
       0: aload_0
       1: aload_1
       2: checkcast     #46                 // class org/apache/hadoop/hbase/procedure2/TestProcedureEvents$TestProcEnv
       5: invokevirtual #47                 // Method execute:(Lorg/apache/hadoop/hbase/procedure2/TestProcedureEvents$TestProcEnv;)[Lorg/apache/hadoop/hbase/procedure2/Procedure;
       8: areturn

  protected boolean setTimeoutFailure(java.lang.Object);
    Code:
       0: aload_0
       1: aload_1
       2: checkcast     #46                 // class org/apache/hadoop/hbase/procedure2/TestProcedureEvents$TestProcEnv
       5: invokevirtual #48                 // Method setTimeoutFailure:(Lorg/apache/hadoop/hbase/procedure2/TestProcedureEvents$TestProcEnv;)Z
       8: ireturn

  protected void afterReplay(java.lang.Object);
    Code:
       0: aload_0
       1: aload_1
       2: checkcast     #46                 // class org/apache/hadoop/hbase/procedure2/TestProcedureEvents$TestProcEnv
       5: invokevirtual #49                 // Method afterReplay:(Lorg/apache/hadoop/hbase/procedure2/TestProcedureEvents$TestProcEnv;)V
       8: return
}
