Compiled from "TestRegionOpen.java"
public class org.apache.hadoop.hbase.regionserver.TestRegionOpen {
  public static final org.apache.hadoop.hbase.HBaseClassTestRule CLASS_RULE;

  public org.junit.rules.TestName name;

  public org.apache.hadoop.hbase.regionserver.TestRegionOpen();
    Code:
       0: aload_0
       1: invokespecial #1                  // Method java/lang/Object."<init>":()V
       4: aload_0
       5: new           #2                  // class org/junit/rules/TestName
       8: dup
       9: invokespecial #3                  // Method org/junit/rules/TestName."<init>":()V
      12: putfield      #4                  // Field name:Lorg/junit/rules/TestName;
      15: return

  public static void before() throws java.lang.Exception;
    Code:
       0: getstatic     #5                  // Field HTU:Lorg/apache/hadoop/hbase/HBaseTestingUtility;
       3: iconst_1
       4: invokevirtual #7                  // Method org/apache/hadoop/hbase/HBaseTestingUtility.startMiniCluster:(I)Lorg/apache/hadoop/hbase/MiniHBaseCluster;
       7: pop
       8: return

  public static void afterClass() throws java.lang.Exception;
    Code:
       0: getstatic     #5                  // Field HTU:Lorg/apache/hadoop/hbase/HBaseTestingUtility;
       3: invokevirtual #8                  // Method org/apache/hadoop/hbase/HBaseTestingUtility.shutdownMiniCluster:()V
       6: return

  public void testPriorityRegionIsOpenedWithSeparateThreadPool() throws java.lang.Exception;
    Code:
       0: ldc           #6                  // class org/apache/hadoop/hbase/regionserver/TestRegionOpen
       2: invokevirtual #14                 // Method java/lang/Class.getSimpleName:()Ljava/lang/String;
       5: invokestatic  #15                 // Method org/apache/hadoop/hbase/TableName.valueOf:(Ljava/lang/String;)Lorg/apache/hadoop/hbase/TableName;
       8: astore_1
       9: invokestatic  #16                 // Method getRS:()Lorg/apache/hadoop/hbase/regionserver/HRegionServer;
      12: invokevirtual #17                 // Method org/apache/hadoop/hbase/regionserver/HRegionServer.getExecutorService:()Lorg/apache/hadoop/hbase/executor/ExecutorService;
      15: getstatic     #18                 // Field org/apache/hadoop/hbase/executor/ExecutorType.RS_OPEN_PRIORITY_REGION:Lorg/apache/hadoop/hbase/executor/ExecutorType;
      18: invokevirtual #19                 // Method org/apache/hadoop/hbase/executor/ExecutorService.getExecutorThreadPool:(Lorg/apache/hadoop/hbase/executor/ExecutorType;)Ljava/util/concurrent/ThreadPoolExecutor;
      21: astore_2
      22: aload_2
      23: invokevirtual #20                 // Method java/util/concurrent/ThreadPoolExecutor.getCompletedTaskCount:()J
      26: lstore_3
      27: new           #21                 // class org/apache/hadoop/hbase/HTableDescriptor
      30: dup
      31: aload_1
      32: invokespecial #22                 // Method org/apache/hadoop/hbase/HTableDescriptor."<init>":(Lorg/apache/hadoop/hbase/TableName;)V
      35: astore        5
      37: aload         5
      39: sipush        200
      42: invokevirtual #24                 // Method org/apache/hadoop/hbase/HTableDescriptor.setPriority:(I)Lorg/apache/hadoop/hbase/HTableDescriptor;
      45: pop
      46: aload         5
      48: new           #25                 // class org/apache/hadoop/hbase/HColumnDescriptor
      51: dup
      52: getstatic     #26                 // Field org/apache/hadoop/hbase/HConstants.CATALOG_FAMILY:[B
      55: invokespecial #27                 // Method org/apache/hadoop/hbase/HColumnDescriptor."<init>":([B)V
      58: invokevirtual #28                 // Method org/apache/hadoop/hbase/HTableDescriptor.addFamily:(Lorg/apache/hadoop/hbase/HColumnDescriptor;)Lorg/apache/hadoop/hbase/HTableDescriptor;
      61: pop
      62: getstatic     #5                  // Field HTU:Lorg/apache/hadoop/hbase/HBaseTestingUtility;
      65: invokevirtual #29                 // Method org/apache/hadoop/hbase/HBaseTestingUtility.getConfiguration:()Lorg/apache/hadoop/conf/Configuration;
      68: invokestatic  #30                 // Method org/apache/hadoop/hbase/client/ConnectionFactory.createConnection:(Lorg/apache/hadoop/conf/Configuration;)Lorg/apache/hadoop/hbase/client/Connection;
      71: astore        6
      73: aconst_null
      74: astore        7
      76: aload         6
      78: invokeinterface #31,  1           // InterfaceMethod org/apache/hadoop/hbase/client/Connection.getAdmin:()Lorg/apache/hadoop/hbase/client/Admin;
      83: astore        8
      85: aconst_null
      86: astore        9
      88: aload         8
      90: aload         5
      92: invokeinterface #32,  2           // InterfaceMethod org/apache/hadoop/hbase/client/Admin.createTable:(Lorg/apache/hadoop/hbase/client/TableDescriptor;)V
      97: aload         8
      99: ifnull        192
     102: aload         9
     104: ifnull        129
     107: aload         8
     109: invokeinterface #33,  1           // InterfaceMethod org/apache/hadoop/hbase/client/Admin.close:()V
     114: goto          192
     117: astore        10
     119: aload         9
     121: aload         10
     123: invokevirtual #35                 // Method java/lang/Throwable.addSuppressed:(Ljava/lang/Throwable;)V
     126: goto          192
     129: aload         8
     131: invokeinterface #33,  1           // InterfaceMethod org/apache/hadoop/hbase/client/Admin.close:()V
     136: goto          192
     139: astore        10
     141: aload         10
     143: astore        9
     145: aload         10
     147: athrow
     148: astore        11
     150: aload         8
     152: ifnull        189
     155: aload         9
     157: ifnull        182
     160: aload         8
     162: invokeinterface #33,  1           // InterfaceMethod org/apache/hadoop/hbase/client/Admin.close:()V
     167: goto          189
     170: astore        12
     172: aload         9
     174: aload         12
     176: invokevirtual #35                 // Method java/lang/Throwable.addSuppressed:(Ljava/lang/Throwable;)V
     179: goto          189
     182: aload         8
     184: invokeinterface #33,  1           // InterfaceMethod org/apache/hadoop/hbase/client/Admin.close:()V
     189: aload         11
     191: athrow
     192: aload         6
     194: ifnull        287
     197: aload         7
     199: ifnull        224
     202: aload         6
     204: invokeinterface #36,  1           // InterfaceMethod org/apache/hadoop/hbase/client/Connection.close:()V
     209: goto          287
     212: astore        8
     214: aload         7
     216: aload         8
     218: invokevirtual #35                 // Method java/lang/Throwable.addSuppressed:(Ljava/lang/Throwable;)V
     221: goto          287
     224: aload         6
     226: invokeinterface #36,  1           // InterfaceMethod org/apache/hadoop/hbase/client/Connection.close:()V
     231: goto          287
     234: astore        8
     236: aload         8
     238: astore        7
     240: aload         8
     242: athrow
     243: astore        13
     245: aload         6
     247: ifnull        284
     250: aload         7
     252: ifnull        277
     255: aload         6
     257: invokeinterface #36,  1           // InterfaceMethod org/apache/hadoop/hbase/client/Connection.close:()V
     262: goto          284
     265: astore        14
     267: aload         7
     269: aload         14
     271: invokevirtual #35                 // Method java/lang/Throwable.addSuppressed:(Ljava/lang/Throwable;)V
     274: goto          284
     277: aload         6
     279: invokeinterface #36,  1           // InterfaceMethod org/apache/hadoop/hbase/client/Connection.close:()V
     284: aload         13
     286: athrow
     287: lload_3
     288: lconst_1
     289: ladd
     290: aload_2
     291: invokevirtual #20                 // Method java/util/concurrent/ThreadPoolExecutor.getCompletedTaskCount:()J
     294: invokestatic  #37                 // Method org/junit/Assert.assertEquals:(JJ)V
     297: return
    Exception table:
       from    to  target type
         107   114   117   Class java/lang/Throwable
          88    97   139   Class java/lang/Throwable
          88    97   148   any
         160   167   170   Class java/lang/Throwable
         139   150   148   any
         202   209   212   Class java/lang/Throwable
          76   192   234   Class java/lang/Throwable
          76   192   243   any
         255   262   265   Class java/lang/Throwable
         234   245   243   any

  public void testNonExistentRegionReplica() throws java.lang.Exception;
    Code:
       0: aload_0
       1: getfield      #4                  // Field name:Lorg/junit/rules/TestName;
       4: invokevirtual #38                 // Method org/junit/rules/TestName.getMethodName:()Ljava/lang/String;
       7: invokestatic  #15                 // Method org/apache/hadoop/hbase/TableName.valueOf:(Ljava/lang/String;)Lorg/apache/hadoop/hbase/TableName;
      10: astore_1
      11: ldc           #39                 // String fam
      13: invokestatic  #40                 // Method org/apache/hadoop/hbase/util/Bytes.toBytes:(Ljava/lang/String;)[B
      16: astore_2
      17: getstatic     #5                  // Field HTU:Lorg/apache/hadoop/hbase/HBaseTestingUtility;
      20: invokevirtual #41                 // Method org/apache/hadoop/hbase/HBaseTestingUtility.getTestFileSystem:()Lorg/apache/hadoop/fs/FileSystem;
      23: astore_3
      24: getstatic     #5                  // Field HTU:Lorg/apache/hadoop/hbase/HBaseTestingUtility;
      27: invokevirtual #42                 // Method org/apache/hadoop/hbase/HBaseTestingUtility.getAdmin:()Lorg/apache/hadoop/hbase/client/Admin;
      30: astore        4
      32: getstatic     #5                  // Field HTU:Lorg/apache/hadoop/hbase/HBaseTestingUtility;
      35: invokevirtual #29                 // Method org/apache/hadoop/hbase/HBaseTestingUtility.getConfiguration:()Lorg/apache/hadoop/conf/Configuration;
      38: astore        5
      40: getstatic     #5                  // Field HTU:Lorg/apache/hadoop/hbase/HBaseTestingUtility;
      43: invokevirtual #43                 // Method org/apache/hadoop/hbase/HBaseTestingUtility.getDataTestDirOnTestFS:()Lorg/apache/hadoop/fs/Path;
      46: astore        6
      48: new           #21                 // class org/apache/hadoop/hbase/HTableDescriptor
      51: dup
      52: aload_1
      53: invokespecial #22                 // Method org/apache/hadoop/hbase/HTableDescriptor."<init>":(Lorg/apache/hadoop/hbase/TableName;)V
      56: astore        7
      58: aload         7
      60: new           #25                 // class org/apache/hadoop/hbase/HColumnDescriptor
      63: dup
      64: aload_2
      65: invokespecial #27                 // Method org/apache/hadoop/hbase/HColumnDescriptor."<init>":([B)V
      68: invokevirtual #28                 // Method org/apache/hadoop/hbase/HTableDescriptor.addFamily:(Lorg/apache/hadoop/hbase/HColumnDescriptor;)Lorg/apache/hadoop/hbase/HTableDescriptor;
      71: pop
      72: aload         4
      74: aload         7
      76: invokeinterface #32,  2           // InterfaceMethod org/apache/hadoop/hbase/client/Admin.createTable:(Lorg/apache/hadoop/hbase/client/TableDescriptor;)V
      81: getstatic     #5                  // Field HTU:Lorg/apache/hadoop/hbase/HBaseTestingUtility;
      84: ldc2_w        #44                 // long 60000l
      87: invokevirtual #46                 // Method org/apache/hadoop/hbase/HBaseTestingUtility.waitUntilNoRegionsInTransition:(J)V
      90: new           #47                 // class org/apache/hadoop/hbase/HRegionInfo
      93: dup
      94: aload         7
      96: invokevirtual #48                 // Method org/apache/hadoop/hbase/HTableDescriptor.getTableName:()Lorg/apache/hadoop/hbase/TableName;
      99: ldc           #49                 // String A
     101: invokestatic  #40                 // Method org/apache/hadoop/hbase/util/Bytes.toBytes:(Ljava/lang/String;)[B
     104: ldc           #50                 // String B
     106: invokestatic  #40                 // Method org/apache/hadoop/hbase/util/Bytes.toBytes:(Ljava/lang/String;)[B
     109: iconst_0
     110: invokestatic  #51                 // Method java/lang/System.currentTimeMillis:()J
     113: iconst_2
     114: invokespecial #52                 // Method org/apache/hadoop/hbase/HRegionInfo."<init>":(Lorg/apache/hadoop/hbase/TableName;[B[BZJI)V
     117: astore        8
     119: aload         5
     121: aload_3
     122: aload         6
     124: aload         8
     126: invokevirtual #53                 // Method org/apache/hadoop/hbase/HRegionInfo.getTable:()Lorg/apache/hadoop/hbase/TableName;
     129: invokestatic  #54                 // Method org/apache/hadoop/hbase/util/FSUtils.getTableDir:(Lorg/apache/hadoop/fs/Path;Lorg/apache/hadoop/hbase/TableName;)Lorg/apache/hadoop/fs/Path;
     132: aload         8
     134: invokestatic  #55                 // Method org/apache/hadoop/hbase/regionserver/HRegionFileSystem.createRegionOnFileSystem:(Lorg/apache/hadoop/conf/Configuration;Lorg/apache/hadoop/fs/FileSystem;Lorg/apache/hadoop/fs/Path;Lorg/apache/hadoop/hbase/client/RegionInfo;)Lorg/apache/hadoop/hbase/regionserver/HRegionFileSystem;
     137: astore        9
     139: aload         9
     141: invokevirtual #56                 // Method org/apache/hadoop/hbase/regionserver/HRegionFileSystem.getRegionDir:()Lorg/apache/hadoop/fs/Path;
     144: astore        10
     146: aload_3
     147: aload         10
     149: invokestatic  #57                 // Method org/apache/hadoop/hbase/regionserver/HRegionFileSystem.loadRegionInfoFileContent:(Lorg/apache/hadoop/fs/FileSystem;Lorg/apache/hadoop/fs/Path;)Lorg/apache/hadoop/hbase/client/RegionInfo;
     152: pop
     153: goto          276
     156: astore        11
     158: getstatic     #59                 // Field LOG:Lorg/slf4j/Logger;
     161: new           #60                 // class java/lang/StringBuilder
     164: dup
     165: invokespecial #61                 // Method java/lang/StringBuilder."<init>":()V
     168: ldc           #62                 // String Caught expected IOE due missing .regioninfo file, due:
     170: invokevirtual #63                 // Method java/lang/StringBuilder.append:(Ljava/lang/String;)Ljava/lang/StringBuilder;
     173: aload         11
     175: invokevirtual #64                 // Method java/io/IOException.getMessage:()Ljava/lang/String;
     178: invokevirtual #63                 // Method java/lang/StringBuilder.append:(Ljava/lang/String;)Ljava/lang/StringBuilder;
     181: ldc           #65                 // String  skipping region open.
     183: invokevirtual #63                 // Method java/lang/StringBuilder.append:(Ljava/lang/String;)Ljava/lang/StringBuilder;
     186: invokevirtual #66                 // Method java/lang/StringBuilder.toString:()Ljava/lang/String;
     189: invokeinterface #67,  2           // InterfaceMethod org/slf4j/Logger.info:(Ljava/lang/String;)V
     194: aload         4
     196: aload_1
     197: invokeinterface #68,  2           // InterfaceMethod org/apache/hadoop/hbase/client/Admin.getRegions:(Lorg/apache/hadoop/hbase/TableName;)Ljava/util/List;
     202: astore        12
     204: getstatic     #59                 // Field LOG:Lorg/slf4j/Logger;
     207: new           #60                 // class java/lang/StringBuilder
     210: dup
     211: invokespecial #61                 // Method java/lang/StringBuilder."<init>":()V
     214: ldc           #69                 // String Regions:
     216: invokevirtual #63                 // Method java/lang/StringBuilder.append:(Ljava/lang/String;)Ljava/lang/StringBuilder;
     219: aload         12
     221: invokevirtual #70                 // Method java/lang/StringBuilder.append:(Ljava/lang/Object;)Ljava/lang/StringBuilder;
     224: invokevirtual #66                 // Method java/lang/StringBuilder.toString:()Ljava/lang/String;
     227: invokeinterface #67,  2           // InterfaceMethod org/slf4j/Logger.info:(Ljava/lang/String;)V
     232: aload         12
     234: invokeinterface #71,  1           // InterfaceMethod java/util/List.size:()I
     239: iconst_1
     240: if_icmpeq     275
     243: new           #60                 // class java/lang/StringBuilder
     246: dup
     247: invokespecial #61                 // Method java/lang/StringBuilder."<init>":()V
     250: ldc           #72                 // String Table
     252: invokevirtual #63                 // Method java/lang/StringBuilder.append:(Ljava/lang/String;)Ljava/lang/StringBuilder;
     255: aload_1
     256: invokevirtual #70                 // Method java/lang/StringBuilder.append:(Ljava/lang/Object;)Ljava/lang/StringBuilder;
     259: ldc           #73                 // String  should have only one region, but got more:
     261: invokevirtual #63                 // Method java/lang/StringBuilder.append:(Ljava/lang/String;)Ljava/lang/StringBuilder;
     264: aload         12
     266: invokevirtual #70                 // Method java/lang/StringBuilder.append:(Ljava/lang/Object;)Ljava/lang/StringBuilder;
     269: invokevirtual #66                 // Method java/lang/StringBuilder.toString:()Ljava/lang/String;
     272: invokestatic  #74                 // Method org/junit/Assert.fail:(Ljava/lang/String;)V
     275: return
     276: ldc           #75                 // String Should have thrown IOE when attempting to open a non-existing region.
     278: invokestatic  #74                 // Method org/junit/Assert.fail:(Ljava/lang/String;)V
     281: return
    Exception table:
       from    to  target type
         146   153   156   Class java/io/IOException

  static {};
    Code:
       0: ldc           #6                  // class org/apache/hadoop/hbase/regionserver/TestRegionOpen
       2: invokestatic  #76                 // Method org/apache/hadoop/hbase/HBaseClassTestRule.forClass:(Ljava/lang/Class;)Lorg/apache/hadoop/hbase/HBaseClassTestRule;
       5: putstatic     #77                 // Field CLASS_RULE:Lorg/apache/hadoop/hbase/HBaseClassTestRule;
       8: ldc           #6                  // class org/apache/hadoop/hbase/regionserver/TestRegionOpen
      10: invokestatic  #78                 // Method org/slf4j/LoggerFactory.getLogger:(Ljava/lang/Class;)Lorg/slf4j/Logger;
      13: putstatic     #59                 // Field LOG:Lorg/slf4j/Logger;
      16: new           #79                 // class org/apache/hadoop/hbase/HBaseTestingUtility
      19: dup
      20: invokespecial #80                 // Method org/apache/hadoop/hbase/HBaseTestingUtility."<init>":()V
      23: putstatic     #5                  // Field HTU:Lorg/apache/hadoop/hbase/HBaseTestingUtility;
      26: return
}
