Compiled from "TestSimpleMutableByteRange.java"
public class org.apache.hadoop.hbase.util.TestSimpleMutableByteRange {
  public static final org.apache.hadoop.hbase.HBaseClassTestRule CLASS_RULE;

  public org.apache.hadoop.hbase.util.TestSimpleMutableByteRange();
    Code:
       0: aload_0
       1: invokespecial #1                  // Method java/lang/Object."<init>":()V
       4: return

  public void testEmpty();
    Code:
       0: aconst_null
       1: invokestatic  #2                  // Method org/apache/hadoop/hbase/util/SimpleMutableByteRange.isEmpty:(Lorg/apache/hadoop/hbase/util/ByteRange;)Z
       4: invokestatic  #3                  // Method org/junit/Assert.assertTrue:(Z)V
       7: new           #4                  // class org/apache/hadoop/hbase/util/SimpleMutableByteRange
      10: dup
      11: invokespecial #5                  // Method org/apache/hadoop/hbase/util/SimpleMutableByteRange."<init>":()V
      14: astore_1
      15: aload_1
      16: invokestatic  #2                  // Method org/apache/hadoop/hbase/util/SimpleMutableByteRange.isEmpty:(Lorg/apache/hadoop/hbase/util/ByteRange;)Z
      19: invokestatic  #3                  // Method org/junit/Assert.assertTrue:(Z)V
      22: aload_1
      23: invokeinterface #6,  1            // InterfaceMethod org/apache/hadoop/hbase/util/ByteRange.isEmpty:()Z
      28: invokestatic  #3                  // Method org/junit/Assert.assertTrue:(Z)V
      31: aload_1
      32: iconst_0
      33: newarray       byte
      35: invokeinterface #7,  2            // InterfaceMethod org/apache/hadoop/hbase/util/ByteRange.set:([B)Lorg/apache/hadoop/hbase/util/ByteRange;
      40: pop
      41: lconst_0
      42: aload_1
      43: invokeinterface #8,  1            // InterfaceMethod org/apache/hadoop/hbase/util/ByteRange.getBytes:()[B
      48: arraylength
      49: i2l
      50: invokestatic  #9                  // Method org/junit/Assert.assertEquals:(JJ)V
      53: lconst_0
      54: aload_1
      55: invokeinterface #10,  1           // InterfaceMethod org/apache/hadoop/hbase/util/ByteRange.getOffset:()I
      60: i2l
      61: invokestatic  #9                  // Method org/junit/Assert.assertEquals:(JJ)V
      64: lconst_0
      65: aload_1
      66: invokeinterface #11,  1           // InterfaceMethod org/apache/hadoop/hbase/util/ByteRange.getLength:()I
      71: i2l
      72: invokestatic  #9                  // Method org/junit/Assert.assertEquals:(JJ)V
      75: iconst_0
      76: newarray       byte
      78: aload_1
      79: invokeinterface #12,  1           // InterfaceMethod org/apache/hadoop/hbase/util/ByteRange.deepCopyToNewArray:()[B
      84: invokestatic  #13                 // Method org/apache/hadoop/hbase/util/Bytes.equals:([B[B)Z
      87: invokestatic  #3                  // Method org/junit/Assert.assertTrue:(Z)V
      90: lconst_0
      91: aload_1
      92: new           #4                  // class org/apache/hadoop/hbase/util/SimpleMutableByteRange
      95: dup
      96: iconst_0
      97: newarray       byte
      99: iconst_0
     100: iconst_0
     101: invokespecial #14                 // Method org/apache/hadoop/hbase/util/SimpleMutableByteRange."<init>":([BII)V
     104: invokeinterface #15,  2           // InterfaceMethod org/apache/hadoop/hbase/util/ByteRange.compareTo:(Ljava/lang/Object;)I
     109: i2l
     110: invokestatic  #9                  // Method org/junit/Assert.assertEquals:(JJ)V
     113: lconst_0
     114: aload_1
     115: invokevirtual #16                 // Method java/lang/Object.hashCode:()I
     118: i2l
     119: invokestatic  #9                  // Method org/junit/Assert.assertEquals:(JJ)V
     122: return

  public void testBasics();
    Code:
       0: new           #4                  // class org/apache/hadoop/hbase/util/SimpleMutableByteRange
       3: dup
       4: iconst_3
       5: newarray       byte
       7: dup
       8: iconst_0
       9: iconst_1
      10: bastore
      11: dup
      12: iconst_1
      13: iconst_3
      14: bastore
      15: dup
      16: iconst_2
      17: iconst_2
      18: bastore
      19: invokespecial #17                 // Method org/apache/hadoop/hbase/util/SimpleMutableByteRange."<init>":([B)V
      22: astore_1
      23: aload_1
      24: invokestatic  #2                  // Method org/apache/hadoop/hbase/util/SimpleMutableByteRange.isEmpty:(Lorg/apache/hadoop/hbase/util/ByteRange;)Z
      27: invokestatic  #18                 // Method org/junit/Assert.assertFalse:(Z)V
      30: aload_1
      31: invokeinterface #8,  1            // InterfaceMethod org/apache/hadoop/hbase/util/ByteRange.getBytes:()[B
      36: invokestatic  #19                 // Method org/junit/Assert.assertNotNull:(Ljava/lang/Object;)V
      39: ldc2_w        #20                 // long 3l
      42: aload_1
      43: invokeinterface #8,  1            // InterfaceMethod org/apache/hadoop/hbase/util/ByteRange.getBytes:()[B
      48: arraylength
      49: i2l
      50: invokestatic  #9                  // Method org/junit/Assert.assertEquals:(JJ)V
      53: lconst_0
      54: aload_1
      55: invokeinterface #10,  1           // InterfaceMethod org/apache/hadoop/hbase/util/ByteRange.getOffset:()I
      60: i2l
      61: invokestatic  #9                  // Method org/junit/Assert.assertEquals:(JJ)V
      64: ldc2_w        #20                 // long 3l
      67: aload_1
      68: invokeinterface #11,  1           // InterfaceMethod org/apache/hadoop/hbase/util/ByteRange.getLength:()I
      73: i2l
      74: invokestatic  #9                  // Method org/junit/Assert.assertEquals:(JJ)V
      77: iconst_3
      78: newarray       byte
      80: dup
      81: iconst_0
      82: iconst_1
      83: bastore
      84: dup
      85: iconst_1
      86: iconst_3
      87: bastore
      88: dup
      89: iconst_2
      90: iconst_2
      91: bastore
      92: aload_1
      93: invokeinterface #12,  1           // InterfaceMethod org/apache/hadoop/hbase/util/ByteRange.deepCopyToNewArray:()[B
      98: invokestatic  #13                 // Method org/apache/hadoop/hbase/util/Bytes.equals:([B[B)Z
     101: invokestatic  #3                  // Method org/junit/Assert.assertTrue:(Z)V
     104: aload_1
     105: invokeinterface #8,  1            // InterfaceMethod org/apache/hadoop/hbase/util/ByteRange.getBytes:()[B
     110: aload_1
     111: invokeinterface #12,  1           // InterfaceMethod org/apache/hadoop/hbase/util/ByteRange.deepCopyToNewArray:()[B
     116: invokestatic  #22                 // Method org/junit/Assert.assertNotSame:(Ljava/lang/Object;Ljava/lang/Object;)V
     119: aload_1
     120: invokevirtual #16                 // Method java/lang/Object.hashCode:()I
     123: ifle          130
     126: iconst_1
     127: goto          131
     130: iconst_0
     131: invokestatic  #3                  // Method org/junit/Assert.assertTrue:(Z)V
     134: aload_1
     135: invokevirtual #16                 // Method java/lang/Object.hashCode:()I
     138: i2l
     139: aload_1
     140: invokeinterface #23,  1           // InterfaceMethod org/apache/hadoop/hbase/util/ByteRange.deepCopy:()Lorg/apache/hadoop/hbase/util/ByteRange;
     145: invokevirtual #16                 // Method java/lang/Object.hashCode:()I
     148: i2l
     149: invokestatic  #9                  // Method org/junit/Assert.assertEquals:(JJ)V
     152: iconst_1
     153: newarray       byte
     155: dup
     156: iconst_0
     157: bipush        -59
     159: bastore
     160: astore_2
     161: aload_1
     162: iconst_2
     163: iconst_1
     164: aload_2
     165: iconst_0
     166: invokeinterface #24,  5           // InterfaceMethod org/apache/hadoop/hbase/util/ByteRange.deepCopySubRangeTo:(II[BI)V
     171: iconst_1
     172: newarray       byte
     174: dup
     175: iconst_0
     176: iconst_2
     177: bastore
     178: aload_2
     179: invokestatic  #13                 // Method org/apache/hadoop/hbase/util/Bytes.equals:([B[B)Z
     182: invokestatic  #3                  // Method org/junit/Assert.assertTrue:(Z)V
     185: aload_1
     186: iconst_1
     187: invokeinterface #25,  2           // InterfaceMethod org/apache/hadoop/hbase/util/ByteRange.setLength:(I)Lorg/apache/hadoop/hbase/util/ByteRange;
     192: pop
     193: iconst_1
     194: newarray       byte
     196: dup
     197: iconst_0
     198: iconst_1
     199: bastore
     200: aload_1
     201: invokeinterface #12,  1           // InterfaceMethod org/apache/hadoop/hbase/util/ByteRange.deepCopyToNewArray:()[B
     206: invokestatic  #13                 // Method org/apache/hadoop/hbase/util/Bytes.equals:([B[B)Z
     209: invokestatic  #3                  // Method org/junit/Assert.assertTrue:(Z)V
     212: aload_1
     213: iconst_2
     214: invokeinterface #25,  2           // InterfaceMethod org/apache/hadoop/hbase/util/ByteRange.setLength:(I)Lorg/apache/hadoop/hbase/util/ByteRange;
     219: pop
     220: iconst_2
     221: newarray       byte
     223: dup
     224: iconst_0
     225: iconst_1
     226: bastore
     227: dup
     228: iconst_1
     229: iconst_3
     230: bastore
     231: aload_1
     232: invokeinterface #12,  1           // InterfaceMethod org/apache/hadoop/hbase/util/ByteRange.deepCopyToNewArray:()[B
     237: invokestatic  #13                 // Method org/apache/hadoop/hbase/util/Bytes.equals:([B[B)Z
     240: invokestatic  #3                  // Method org/junit/Assert.assertTrue:(Z)V
     243: return

  public void testPutandGetPrimitiveTypes() throws java.lang.Exception;
    Code:
       0: new           #4                  // class org/apache/hadoop/hbase/util/SimpleMutableByteRange
       3: dup
       4: bipush        100
       6: invokespecial #26                 // Method org/apache/hadoop/hbase/util/SimpleMutableByteRange."<init>":(I)V
       9: astore_1
      10: iconst_0
      11: istore_2
      12: bipush        18
      14: istore_3
      15: iconst_2
      16: istore        4
      18: iconst_0
      19: istore        5
      21: ldc2_w        #27                 // long 1234l
      24: lstore        6
      26: lconst_0
      27: lstore        8
      29: aload_1
      30: iload_2
      31: iload_3
      32: invokeinterface #29,  3           // InterfaceMethod org/apache/hadoop/hbase/util/ByteRange.putInt:(II)Lorg/apache/hadoop/hbase/util/ByteRange;
      37: pop
      38: iinc          2, 4
      41: aload_1
      42: iload_2
      43: iload         4
      45: invokeinterface #29,  3           // InterfaceMethod org/apache/hadoop/hbase/util/ByteRange.putInt:(II)Lorg/apache/hadoop/hbase/util/ByteRange;
      50: pop
      51: iinc          2, 4
      54: aload_1
      55: iload_2
      56: iload         5
      58: invokeinterface #30,  3           // InterfaceMethod org/apache/hadoop/hbase/util/ByteRange.putShort:(IS)Lorg/apache/hadoop/hbase/util/ByteRange;
      63: pop
      64: iinc          2, 2
      67: aload_1
      68: iload_2
      69: lload         6
      71: invokeinterface #31,  4           // InterfaceMethod org/apache/hadoop/hbase/util/ByteRange.putLong:(IJ)Lorg/apache/hadoop/hbase/util/ByteRange;
      76: pop
      77: iinc          2, 8
      80: aload_1
      81: iload_2
      82: lload         6
      84: invokeinterface #32,  4           // InterfaceMethod org/apache/hadoop/hbase/util/ByteRange.putVLong:(IJ)I
      89: istore        10
      91: iload_2
      92: iload         10
      94: iadd
      95: istore_2
      96: aload_1
      97: iload_2
      98: lload         8
     100: invokeinterface #32,  4           // InterfaceMethod org/apache/hadoop/hbase/util/ByteRange.putVLong:(IJ)I
     105: istore        10
     107: iload_2
     108: iload         10
     110: iadd
     111: istore_2
     112: aload_1
     113: iload_2
     114: ldc2_w        #34                 // long 9223372036854775807l
     117: invokeinterface #32,  4           // InterfaceMethod org/apache/hadoop/hbase/util/ByteRange.putVLong:(IJ)I
     122: istore        10
     124: iload_2
     125: iload         10
     127: iadd
     128: istore_2
     129: aload_1
     130: iload_2
     131: ldc2_w        #36                 // long -9223372036854775808l
     134: invokeinterface #32,  4           // InterfaceMethod org/apache/hadoop/hbase/util/ByteRange.putVLong:(IJ)I
     139: istore        10
     141: iconst_0
     142: istore_2
     143: iload_3
     144: i2l
     145: aload_1
     146: iload_2
     147: invokeinterface #38,  2           // InterfaceMethod org/apache/hadoop/hbase/util/ByteRange.getInt:(I)I
     152: i2l
     153: invokestatic  #9                  // Method org/junit/Assert.assertEquals:(JJ)V
     156: iinc          2, 4
     159: iload         4
     161: i2l
     162: aload_1
     163: iload_2
     164: invokeinterface #38,  2           // InterfaceMethod org/apache/hadoop/hbase/util/ByteRange.getInt:(I)I
     169: i2l
     170: invokestatic  #9                  // Method org/junit/Assert.assertEquals:(JJ)V
     173: iinc          2, 4
     176: iload         5
     178: i2l
     179: aload_1
     180: iload_2
     181: invokeinterface #39,  2           // InterfaceMethod org/apache/hadoop/hbase/util/ByteRange.getShort:(I)S
     186: i2l
     187: invokestatic  #9                  // Method org/junit/Assert.assertEquals:(JJ)V
     190: iinc          2, 2
     193: lload         6
     195: aload_1
     196: iload_2
     197: invokeinterface #40,  2           // InterfaceMethod org/apache/hadoop/hbase/util/ByteRange.getLong:(I)J
     202: invokestatic  #9                  // Method org/junit/Assert.assertEquals:(JJ)V
     205: iinc          2, 8
     208: lload         6
     210: aload_1
     211: iload_2
     212: invokeinterface #41,  2           // InterfaceMethod org/apache/hadoop/hbase/util/ByteRange.getVLong:(I)J
     217: invokestatic  #9                  // Method org/junit/Assert.assertEquals:(JJ)V
     220: iload_2
     221: lload         6
     223: invokestatic  #42                 // Method org/apache/hadoop/hbase/util/SimpleByteRange.getVLongSize:(J)I
     226: iadd
     227: istore_2
     228: lload         8
     230: aload_1
     231: iload_2
     232: invokeinterface #41,  2           // InterfaceMethod org/apache/hadoop/hbase/util/ByteRange.getVLong:(I)J
     237: invokestatic  #9                  // Method org/junit/Assert.assertEquals:(JJ)V
     240: iload_2
     241: lload         8
     243: invokestatic  #42                 // Method org/apache/hadoop/hbase/util/SimpleByteRange.getVLongSize:(J)I
     246: iadd
     247: istore_2
     248: ldc2_w        #34                 // long 9223372036854775807l
     251: aload_1
     252: iload_2
     253: invokeinterface #41,  2           // InterfaceMethod org/apache/hadoop/hbase/util/ByteRange.getVLong:(I)J
     258: invokestatic  #9                  // Method org/junit/Assert.assertEquals:(JJ)V
     261: iload_2
     262: ldc2_w        #34                 // long 9223372036854775807l
     265: invokestatic  #42                 // Method org/apache/hadoop/hbase/util/SimpleByteRange.getVLongSize:(J)I
     268: iadd
     269: istore_2
     270: ldc2_w        #36                 // long -9223372036854775808l
     273: aload_1
     274: iload_2
     275: invokeinterface #41,  2           // InterfaceMethod org/apache/hadoop/hbase/util/ByteRange.getVLong:(I)J
     280: invokestatic  #9                  // Method org/junit/Assert.assertEquals:(JJ)V
     283: return

  static {};
    Code:
       0: ldc           #43                 // class org/apache/hadoop/hbase/util/TestSimpleMutableByteRange
       2: invokestatic  #44                 // Method org/apache/hadoop/hbase/HBaseClassTestRule.forClass:(Ljava/lang/Class;)Lorg/apache/hadoop/hbase/HBaseClassTestRule;
       5: putstatic     #45                 // Field CLASS_RULE:Lorg/apache/hadoop/hbase/HBaseClassTestRule;
       8: return
}
