Compiled from "TestProcedureBypass.java"
public class org.apache.hadoop.hbase.procedure2.TestProcedureBypass$StuckProcedure extends org.apache.hadoop.hbase.procedure2.ProcedureTestingUtility$NoopProcedure<org.apache.hadoop.hbase.procedure2.TestProcedureBypass$TestProcEnv> {
  public org.apache.hadoop.hbase.procedure2.TestProcedureBypass$StuckProcedure();
    Code:
       0: aload_0
       1: invokespecial #1                  // Method org/apache/hadoop/hbase/procedure2/ProcedureTestingUtility$NoopProcedure."<init>":()V
       4: return

  protected org.apache.hadoop.hbase.procedure2.Procedure[] execute(org.apache.hadoop.hbase.procedure2.TestProcedureBypass$TestProcEnv);
    Code:
       0: ldc2_w        #3                  // long 9223372036854775807l
       3: invokestatic  #5                  // Method java/lang/Thread.sleep:(J)V
       6: goto          21
       9: astore_2
      10: invokestatic  #7                  // Method org/apache/hadoop/hbase/procedure2/TestProcedureBypass.access$100:()Lorg/slf4j/Logger;
      13: ldc           #8                  // String Sleep is interrupted.
      15: aload_2
      16: invokeinterface #9,  3            // InterfaceMethod org/slf4j/Logger.debug:(Ljava/lang/String;Ljava/lang/Throwable;)V
      21: aconst_null
      22: areturn
    Exception table:
       from    to  target type
           0     6     9   Class java/lang/Throwable

  protected org.apache.hadoop.hbase.procedure2.Procedure[] execute(java.lang.Object) throws org.apache.hadoop.hbase.procedure2.ProcedureYieldException, org.apache.hadoop.hbase.procedure2.ProcedureSuspendedException, java.lang.InterruptedException;
    Code:
       0: aload_0
       1: aload_1
       2: checkcast     #10                 // class org/apache/hadoop/hbase/procedure2/TestProcedureBypass$TestProcEnv
       5: invokevirtual #11                 // Method execute:(Lorg/apache/hadoop/hbase/procedure2/TestProcedureBypass$TestProcEnv;)[Lorg/apache/hadoop/hbase/procedure2/Procedure;
       8: areturn
}
