Compiled from "TestWithDisabledAuthorization.java"
class org.apache.hadoop.hbase.security.access.TestWithDisabledAuthorization$17 implements org.apache.hadoop.hbase.security.access.SecureTestUtil$AccessTestAction {
  final org.apache.hadoop.hbase.security.access.TestWithDisabledAuthorization this$0;

  org.apache.hadoop.hbase.security.access.TestWithDisabledAuthorization$17(org.apache.hadoop.hbase.security.access.TestWithDisabledAuthorization);
    Code:
       0: aload_0
       1: aload_1
       2: putfield      #1                  // Field this$0:Lorg/apache/hadoop/hbase/security/access/TestWithDisabledAuthorization;
       5: aload_0
       6: invokespecial #2                  // Method java/lang/Object."<init>":()V
       9: return

  public java.lang.Object run() throws java.lang.Exception;
    Code:
       0: new           #3                  // class org/apache/hadoop/hbase/HTableDescriptor
       3: dup
       4: aload_0
       5: getfield      #1                  // Field this$0:Lorg/apache/hadoop/hbase/security/access/TestWithDisabledAuthorization;
       8: getfield      #4                  // Field org/apache/hadoop/hbase/security/access/TestWithDisabledAuthorization.TEST_TABLE:Lorg/apache/hadoop/hbase/TestTableName;
      11: invokevirtual #5                  // Method org/apache/hadoop/hbase/TestTableName.getTableName:()Lorg/apache/hadoop/hbase/TableName;
      14: invokespecial #6                  // Method org/apache/hadoop/hbase/HTableDescriptor."<init>":(Lorg/apache/hadoop/hbase/TableName;)V
      17: astore_1
      18: aload_1
      19: new           #7                  // class org/apache/hadoop/hbase/HColumnDescriptor
      22: dup
      23: invokestatic  #8                  // Method org/apache/hadoop/hbase/security/access/TestWithDisabledAuthorization.access$100:()[B
      26: invokespecial #9                  // Method org/apache/hadoop/hbase/HColumnDescriptor."<init>":([B)V
      29: invokevirtual #10                 // Method org/apache/hadoop/hbase/HTableDescriptor.addFamily:(Lorg/apache/hadoop/hbase/HColumnDescriptor;)Lorg/apache/hadoop/hbase/HTableDescriptor;
      32: pop
      33: aload_1
      34: new           #7                  // class org/apache/hadoop/hbase/HColumnDescriptor
      37: dup
      38: invokestatic  #11                 // Method org/apache/hadoop/hbase/security/access/TestWithDisabledAuthorization.access$700:()[B
      41: invokespecial #9                  // Method org/apache/hadoop/hbase/HColumnDescriptor."<init>":([B)V
      44: invokevirtual #10                 // Method org/apache/hadoop/hbase/HTableDescriptor.addFamily:(Lorg/apache/hadoop/hbase/HColumnDescriptor;)Lorg/apache/hadoop/hbase/HTableDescriptor;
      47: pop
      48: invokestatic  #12                 // Method org/apache/hadoop/hbase/security/access/TestWithDisabledAuthorization.access$600:()Lorg/apache/hadoop/hbase/security/access/AccessController;
      51: invokestatic  #13                 // Method org/apache/hadoop/hbase/security/access/TestWithDisabledAuthorization.access$500:()Lorg/apache/hadoop/hbase/coprocessor/MasterCoprocessorEnvironment;
      54: invokestatic  #14                 // Method org/apache/hadoop/hbase/coprocessor/ObserverContextImpl.createAndPrepare:(Lorg/apache/hadoop/hbase/CoprocessorEnvironment;)Lorg/apache/hadoop/hbase/coprocessor/ObserverContext;
      57: aload_0
      58: getfield      #1                  // Field this$0:Lorg/apache/hadoop/hbase/security/access/TestWithDisabledAuthorization;
      61: getfield      #4                  // Field org/apache/hadoop/hbase/security/access/TestWithDisabledAuthorization.TEST_TABLE:Lorg/apache/hadoop/hbase/TestTableName;
      64: invokevirtual #5                  // Method org/apache/hadoop/hbase/TestTableName.getTableName:()Lorg/apache/hadoop/hbase/TableName;
      67: aconst_null
      68: aload_1
      69: invokevirtual #15                 // Method org/apache/hadoop/hbase/security/access/AccessController.preModifyTable:(Lorg/apache/hadoop/hbase/coprocessor/ObserverContext;Lorg/apache/hadoop/hbase/TableName;Lorg/apache/hadoop/hbase/client/TableDescriptor;Lorg/apache/hadoop/hbase/client/TableDescriptor;)Lorg/apache/hadoop/hbase/client/TableDescriptor;
      72: pop
      73: aconst_null
      74: areturn
}
