Compiled from "TestEncryptionTest.java"
public class org.apache.hadoop.hbase.util.TestEncryptionTest {
  public static final org.apache.hadoop.hbase.HBaseClassTestRule CLASS_RULE;

  public org.apache.hadoop.hbase.util.TestEncryptionTest();
    Code:
       0: aload_0
       1: invokespecial #1                  // Method java/lang/Object."<init>":()V
       4: return

  public void testTestKeyProvider();
    Code:
       0: invokestatic  #2                  // Method org/apache/hadoop/hbase/HBaseConfiguration.create:()Lorg/apache/hadoop/conf/Configuration;
       3: astore_1
       4: aload_1
       5: ldc           #4                  // String hbase.crypto.keyprovider
       7: ldc           #5                  // class org/apache/hadoop/hbase/io/crypto/KeyProviderForTesting
       9: invokevirtual #6                  // Method java/lang/Class.getName:()Ljava/lang/String;
      12: invokevirtual #7                  // Method org/apache/hadoop/conf/Configuration.set:(Ljava/lang/String;Ljava/lang/String;)V
      15: aload_1
      16: invokestatic  #8                  // Method org/apache/hadoop/hbase/util/EncryptionTest.testKeyProvider:(Lorg/apache/hadoop/conf/Configuration;)V
      19: goto          28
      22: astore_2
      23: ldc           #10                 // String Instantiation of test key provider should have passed
      25: invokestatic  #11                 // Method org/junit/Assert.fail:(Ljava/lang/String;)V
      28: aload_1
      29: ldc           #4                  // String hbase.crypto.keyprovider
      31: ldc           #12                 // class org/apache/hadoop/hbase/util/TestEncryptionTest$FailingKeyProvider
      33: invokevirtual #6                  // Method java/lang/Class.getName:()Ljava/lang/String;
      36: invokevirtual #7                  // Method org/apache/hadoop/conf/Configuration.set:(Ljava/lang/String;Ljava/lang/String;)V
      39: aload_1
      40: invokestatic  #8                  // Method org/apache/hadoop/hbase/util/EncryptionTest.testKeyProvider:(Lorg/apache/hadoop/conf/Configuration;)V
      43: ldc           #13                 // String Instantiation of bad test key provider should have failed check
      45: invokestatic  #11                 // Method org/junit/Assert.fail:(Ljava/lang/String;)V
      48: goto          52
      51: astore_2
      52: return
    Exception table:
       from    to  target type
           4    19    22   Class java/lang/Exception
          28    48    51   Class java/lang/Exception

  public void testTestCipherProvider();
    Code:
       0: invokestatic  #2                  // Method org/apache/hadoop/hbase/HBaseConfiguration.create:()Lorg/apache/hadoop/conf/Configuration;
       3: astore_1
       4: aload_1
       5: ldc           #14                 // String hbase.crypto.cipherprovider
       7: ldc           #15                 // class org/apache/hadoop/hbase/io/crypto/DefaultCipherProvider
       9: invokevirtual #6                  // Method java/lang/Class.getName:()Ljava/lang/String;
      12: invokevirtual #7                  // Method org/apache/hadoop/conf/Configuration.set:(Ljava/lang/String;Ljava/lang/String;)V
      15: aload_1
      16: invokestatic  #16                 // Method org/apache/hadoop/hbase/util/EncryptionTest.testCipherProvider:(Lorg/apache/hadoop/conf/Configuration;)V
      19: goto          28
      22: astore_2
      23: ldc           #17                 // String Instantiation of test cipher provider should have passed
      25: invokestatic  #11                 // Method org/junit/Assert.fail:(Ljava/lang/String;)V
      28: aload_1
      29: ldc           #14                 // String hbase.crypto.cipherprovider
      31: ldc           #18                 // class org/apache/hadoop/hbase/util/TestEncryptionTest$FailingCipherProvider
      33: invokevirtual #6                  // Method java/lang/Class.getName:()Ljava/lang/String;
      36: invokevirtual #7                  // Method org/apache/hadoop/conf/Configuration.set:(Ljava/lang/String;Ljava/lang/String;)V
      39: aload_1
      40: invokestatic  #16                 // Method org/apache/hadoop/hbase/util/EncryptionTest.testCipherProvider:(Lorg/apache/hadoop/conf/Configuration;)V
      43: ldc           #19                 // String Instantiation of bad test cipher provider should have failed check
      45: invokestatic  #11                 // Method org/junit/Assert.fail:(Ljava/lang/String;)V
      48: goto          52
      51: astore_2
      52: return
    Exception table:
       from    to  target type
           4    19    22   Class java/lang/Exception
          28    48    51   Class java/lang/Exception

  public void testTestCipher();
    Code:
       0: invokestatic  #2                  // Method org/apache/hadoop/hbase/HBaseConfiguration.create:()Lorg/apache/hadoop/conf/Configuration;
       3: astore_1
       4: aload_1
       5: ldc           #4                  // String hbase.crypto.keyprovider
       7: ldc           #5                  // class org/apache/hadoop/hbase/io/crypto/KeyProviderForTesting
       9: invokevirtual #6                  // Method java/lang/Class.getName:()Ljava/lang/String;
      12: invokevirtual #7                  // Method org/apache/hadoop/conf/Configuration.set:(Ljava/lang/String;Ljava/lang/String;)V
      15: aload_1
      16: ldc           #20                 // String hbase.crypto.key.algorithm
      18: ldc           #21                 // String AES
      20: invokevirtual #22                 // Method org/apache/hadoop/conf/Configuration.get:(Ljava/lang/String;Ljava/lang/String;)Ljava/lang/String;
      23: astore_2
      24: aload_1
      25: aload_2
      26: aconst_null
      27: invokestatic  #23                 // Method org/apache/hadoop/hbase/util/EncryptionTest.testEncryption:(Lorg/apache/hadoop/conf/Configuration;Ljava/lang/String;[B)V
      30: goto          61
      33: astore_3
      34: new           #24                 // class java/lang/StringBuilder
      37: dup
      38: invokespecial #25                 // Method java/lang/StringBuilder."<init>":()V
      41: ldc           #26                 // String Test for cipher
      43: invokevirtual #27                 // Method java/lang/StringBuilder.append:(Ljava/lang/String;)Ljava/lang/StringBuilder;
      46: aload_2
      47: invokevirtual #27                 // Method java/lang/StringBuilder.append:(Ljava/lang/String;)Ljava/lang/StringBuilder;
      50: ldc           #28                 // String  should have succeeded
      52: invokevirtual #27                 // Method java/lang/StringBuilder.append:(Ljava/lang/String;)Ljava/lang/StringBuilder;
      55: invokevirtual #29                 // Method java/lang/StringBuilder.toString:()Ljava/lang/String;
      58: invokestatic  #11                 // Method org/junit/Assert.fail:(Ljava/lang/String;)V
      61: aload_1
      62: ldc           #30                 // String foobar
      64: aconst_null
      65: invokestatic  #23                 // Method org/apache/hadoop/hbase/util/EncryptionTest.testEncryption:(Lorg/apache/hadoop/conf/Configuration;Ljava/lang/String;[B)V
      68: ldc           #31                 // String Test for bogus cipher should have failed
      70: invokestatic  #11                 // Method org/junit/Assert.fail:(Ljava/lang/String;)V
      73: goto          77
      76: astore_3
      77: return
    Exception table:
       from    to  target type
          24    30    33   Class java/lang/Exception
          61    73    76   Class java/lang/Exception

  static {};
    Code:
       0: ldc           #32                 // class org/apache/hadoop/hbase/util/TestEncryptionTest
       2: invokestatic  #33                 // Method org/apache/hadoop/hbase/HBaseClassTestRule.forClass:(Ljava/lang/Class;)Lorg/apache/hadoop/hbase/HBaseClassTestRule;
       5: putstatic     #34                 // Field CLASS_RULE:Lorg/apache/hadoop/hbase/HBaseClassTestRule;
       8: return
}
