Compiled from "TestTablesWithQuotas.java"
class org.apache.hadoop.hbase.quotas.TestTablesWithQuotas$2 extends org.apache.hadoop.hbase.quotas.QuotaObserverChore$TablesWithQuotas {
  final org.apache.hadoop.hbase.quotas.TestTablesWithQuotas this$0;

  org.apache.hadoop.hbase.quotas.TestTablesWithQuotas$2(org.apache.hadoop.hbase.quotas.TestTablesWithQuotas, org.apache.hadoop.hbase.client.Connection, org.apache.hadoop.conf.Configuration);
    Code:
       0: aload_0
       1: aload_1
       2: putfield      #1                  // Field this$0:Lorg/apache/hadoop/hbase/quotas/TestTablesWithQuotas;
       5: aload_0
       6: aload_2
       7: aload_3
       8: invokespecial #2                  // Method org/apache/hadoop/hbase/quotas/QuotaObserverChore$TablesWithQuotas."<init>":(Lorg/apache/hadoop/hbase/client/Connection;Lorg/apache/hadoop/conf/Configuration;)V
      11: return

  int getNumReportedRegions(org.apache.hadoop.hbase.TableName, org.apache.hadoop.hbase.quotas.QuotaSnapshotStore<org.apache.hadoop.hbase.TableName>);
    Code:
       0: new           #3                  // class java/lang/RuntimeException
       3: dup
       4: ldc           #4                  // String Should should not reach here
       6: invokespecial #5                  // Method java/lang/RuntimeException."<init>":(Ljava/lang/String;)V
       9: athrow
}
