Compiled from "TestIdReadWriteLock.java"
public class org.apache.hadoop.hbase.util.TestIdReadWriteLock {
  public static final org.apache.hadoop.hbase.HBaseClassTestRule CLASS_RULE;

  public org.apache.hadoop.hbase.util.IdReadWriteLock<java.lang.Long> idLock;

  public org.apache.hadoop.hbase.util.TestIdReadWriteLock();
    Code:
       0: aload_0
       1: invokespecial #3                  // Method java/lang/Object."<init>":()V
       4: aload_0
       5: new           #4                  // class java/util/concurrent/ConcurrentHashMap
       8: dup
       9: invokespecial #5                  // Method java/util/concurrent/ConcurrentHashMap."<init>":()V
      12: putfield      #2                  // Field idOwner:Ljava/util/Map;
      15: return

  public static java.lang.Iterable<java.lang.Object[]> data();
    Code:
       0: iconst_2
       1: anewarray     #6                  // class "[Ljava/lang/Object;"
       4: dup
       5: iconst_0
       6: iconst_1
       7: anewarray     #7                  // class java/lang/Object
      10: dup
      11: iconst_0
      12: new           #8                  // class org/apache/hadoop/hbase/util/IdReadWriteLock
      15: dup
      16: getstatic     #9                  // Field org/apache/hadoop/hbase/util/IdReadWriteLock$ReferenceType.WEAK:Lorg/apache/hadoop/hbase/util/IdReadWriteLock$ReferenceType;
      19: invokespecial #10                 // Method org/apache/hadoop/hbase/util/IdReadWriteLock."<init>":(Lorg/apache/hadoop/hbase/util/IdReadWriteLock$ReferenceType;)V
      22: aastore
      23: aastore
      24: dup
      25: iconst_1
      26: iconst_1
      27: anewarray     #7                  // class java/lang/Object
      30: dup
      31: iconst_0
      32: new           #8                  // class org/apache/hadoop/hbase/util/IdReadWriteLock
      35: dup
      36: getstatic     #11                 // Field org/apache/hadoop/hbase/util/IdReadWriteLock$ReferenceType.SOFT:Lorg/apache/hadoop/hbase/util/IdReadWriteLock$ReferenceType;
      39: invokespecial #10                 // Method org/apache/hadoop/hbase/util/IdReadWriteLock."<init>":(Lorg/apache/hadoop/hbase/util/IdReadWriteLock$ReferenceType;)V
      42: aastore
      43: aastore
      44: invokestatic  #12                 // Method java/util/Arrays.asList:([Ljava/lang/Object;)Ljava/util/List;
      47: areturn

  public void testMultipleClients() throws java.lang.Exception;
    Code:
       0: sipush        128
       3: invokestatic  #14                 // Method java/util/concurrent/Executors.newFixedThreadPool:(I)Ljava/util/concurrent/ExecutorService;
       6: astore_1
       7: new           #15                 // class java/util/concurrent/ExecutorCompletionService
      10: dup
      11: aload_1
      12: invokespecial #16                 // Method java/util/concurrent/ExecutorCompletionService."<init>":(Ljava/util/concurrent/Executor;)V
      15: astore_2
      16: iconst_0
      17: istore_3
      18: iload_3
      19: sipush        128
      22: if_icmpge     63
      25: aload_2
      26: new           #17                 // class org/apache/hadoop/hbase/util/TestIdReadWriteLock$IdLockTestThread
      29: dup
      30: aload_0
      31: new           #18                 // class java/lang/StringBuilder
      34: dup
      35: invokespecial #19                 // Method java/lang/StringBuilder."<init>":()V
      38: ldc           #20                 // String client_
      40: invokevirtual #21                 // Method java/lang/StringBuilder.append:(Ljava/lang/String;)Ljava/lang/StringBuilder;
      43: iload_3
      44: invokevirtual #22                 // Method java/lang/StringBuilder.append:(I)Ljava/lang/StringBuilder;
      47: invokevirtual #23                 // Method java/lang/StringBuilder.toString:()Ljava/lang/String;
      50: invokespecial #24                 // Method org/apache/hadoop/hbase/util/TestIdReadWriteLock$IdLockTestThread."<init>":(Lorg/apache/hadoop/hbase/util/TestIdReadWriteLock;Ljava/lang/String;)V
      53: invokevirtual #25                 // Method java/util/concurrent/ExecutorCompletionService.submit:(Ljava/util/concurrent/Callable;)Ljava/util/concurrent/Future;
      56: pop
      57: iinc          3, 1
      60: goto          18
      63: iconst_0
      64: istore_3
      65: iload_3
      66: sipush        128
      69: if_icmpge     100
      72: aload_2
      73: invokevirtual #26                 // Method java/util/concurrent/ExecutorCompletionService.take:()Ljava/util/concurrent/Future;
      76: astore        4
      78: aload         4
      80: invokeinterface #27,  1           // InterfaceMethod java/util/concurrent/Future.get:()Ljava/lang/Object;
      85: checkcast     #28                 // class java/lang/Boolean
      88: invokevirtual #29                 // Method java/lang/Boolean.booleanValue:()Z
      91: invokestatic  #30                 // Method org/junit/Assert.assertTrue:(Z)V
      94: iinc          3, 1
      97: goto          65
     100: aload_0
     101: getfield      #31                 // Field idLock:Lorg/apache/hadoop/hbase/util/IdReadWriteLock;
     104: invokevirtual #32                 // Method org/apache/hadoop/hbase/util/IdReadWriteLock.purgeAndGetEntryPoolSize:()I
     107: istore_3
     108: getstatic     #1                  // Field LOG:Lorg/slf4j/Logger;
     111: new           #18                 // class java/lang/StringBuilder
     114: dup
     115: invokespecial #19                 // Method java/lang/StringBuilder."<init>":()V
     118: ldc           #33                 // String Size of entry pool after gc and purge:
     120: invokevirtual #21                 // Method java/lang/StringBuilder.append:(Ljava/lang/String;)Ljava/lang/StringBuilder;
     123: iload_3
     124: invokevirtual #22                 // Method java/lang/StringBuilder.append:(I)Ljava/lang/StringBuilder;
     127: invokevirtual #23                 // Method java/lang/StringBuilder.toString:()Ljava/lang/String;
     130: invokeinterface #34,  2           // InterfaceMethod org/slf4j/Logger.debug:(Ljava/lang/String;)V
     135: aload_0
     136: getfield      #31                 // Field idLock:Lorg/apache/hadoop/hbase/util/IdReadWriteLock;
     139: invokevirtual #35                 // Method org/apache/hadoop/hbase/util/IdReadWriteLock.getReferenceType:()Lorg/apache/hadoop/hbase/util/IdReadWriteLock$ReferenceType;
     142: astore        4
     144: getstatic     #36                 // Field org/apache/hadoop/hbase/util/TestIdReadWriteLock$1.$SwitchMap$org$apache$hadoop$hbase$util$IdReadWriteLock$ReferenceType:[I
     147: aload         4
     149: invokevirtual #37                 // Method org/apache/hadoop/hbase/util/IdReadWriteLock$ReferenceType.ordinal:()I
     152: iaload
     153: lookupswitch  { // 2
                     1: 180
                     2: 189
               default: 200
          }
     180: lconst_0
     181: iload_3
     182: i2l
     183: invokestatic  #38                 // Method org/junit/Assert.assertEquals:(JJ)V
     186: goto          200
     189: ldc2_w        #39                 // long 16l
     192: iload_3
     193: i2l
     194: invokestatic  #38                 // Method org/junit/Assert.assertEquals:(JJ)V
     197: goto          200
     200: aload_1
     201: invokeinterface #41,  1           // InterfaceMethod java/util/concurrent/ExecutorService.shutdown:()V
     206: aload_1
     207: ldc2_w        #42                 // long 5000l
     210: getstatic     #44                 // Field java/util/concurrent/TimeUnit.MILLISECONDS:Ljava/util/concurrent/TimeUnit;
     213: invokeinterface #45,  4           // InterfaceMethod java/util/concurrent/ExecutorService.awaitTermination:(JLjava/util/concurrent/TimeUnit;)Z
     218: pop
     219: goto          246
     222: astore        5
     224: aload_1
     225: invokeinterface #41,  1           // InterfaceMethod java/util/concurrent/ExecutorService.shutdown:()V
     230: aload_1
     231: ldc2_w        #42                 // long 5000l
     234: getstatic     #44                 // Field java/util/concurrent/TimeUnit.MILLISECONDS:Ljava/util/concurrent/TimeUnit;
     237: invokeinterface #45,  4           // InterfaceMethod java/util/concurrent/ExecutorService.awaitTermination:(JLjava/util/concurrent/TimeUnit;)Z
     242: pop
     243: aload         5
     245: athrow
     246: return
    Exception table:
       from    to  target type
           7   200   222   any
         222   224   222   any

  static java.util.Map access$000(org.apache.hadoop.hbase.util.TestIdReadWriteLock);
    Code:
       0: aload_0
       1: getfield      #2                  // Field idOwner:Ljava/util/Map;
       4: areturn

  static org.slf4j.Logger access$100();
    Code:
       0: getstatic     #1                  // Field LOG:Lorg/slf4j/Logger;
       3: areturn

  static {};
    Code:
       0: ldc           #13                 // class org/apache/hadoop/hbase/util/TestIdReadWriteLock
       2: invokestatic  #46                 // Method org/apache/hadoop/hbase/HBaseClassTestRule.forClass:(Ljava/lang/Class;)Lorg/apache/hadoop/hbase/HBaseClassTestRule;
       5: putstatic     #47                 // Field CLASS_RULE:Lorg/apache/hadoop/hbase/HBaseClassTestRule;
       8: ldc           #13                 // class org/apache/hadoop/hbase/util/TestIdReadWriteLock
      10: invokestatic  #48                 // Method org/slf4j/LoggerFactory.getLogger:(Ljava/lang/Class;)Lorg/slf4j/Logger;
      13: putstatic     #1                  // Field LOG:Lorg/slf4j/Logger;
      16: return
}
