Compiled from "TestAsyncSingleRequestRpcRetryingCaller.java"
class org.apache.hadoop.hbase.client.TestAsyncSingleRequestRpcRetryingCaller$1 extends org.apache.hadoop.hbase.client.AsyncRegionLocator {
  final java.util.concurrent.atomic.AtomicInteger val$count;

  final java.util.concurrent.atomic.AtomicBoolean val$errorTriggered;

  final org.apache.hadoop.hbase.HRegionLocation val$loc;

  final org.apache.hadoop.hbase.client.TestAsyncSingleRequestRpcRetryingCaller this$0;

  org.apache.hadoop.hbase.client.TestAsyncSingleRequestRpcRetryingCaller$1(org.apache.hadoop.hbase.client.TestAsyncSingleRequestRpcRetryingCaller, org.apache.hadoop.hbase.client.AsyncConnectionImpl, org.apache.hbase.thirdparty.io.netty.util.HashedWheelTimer, java.util.concurrent.atomic.AtomicInteger, java.util.concurrent.atomic.AtomicBoolean, org.apache.hadoop.hbase.HRegionLocation);
    Code:
       0: aload_0
       1: aload_1
       2: putfield      #1                  // Field this$0:Lorg/apache/hadoop/hbase/client/TestAsyncSingleRequestRpcRetryingCaller;
       5: aload_0
       6: aload         4
       8: putfield      #2                  // Field val$count:Ljava/util/concurrent/atomic/AtomicInteger;
      11: aload_0
      12: aload         5
      14: putfield      #3                  // Field val$errorTriggered:Ljava/util/concurrent/atomic/AtomicBoolean;
      17: aload_0
      18: aload         6
      20: putfield      #4                  // Field val$loc:Lorg/apache/hadoop/hbase/HRegionLocation;
      23: aload_0
      24: aload_2
      25: aload_3
      26: invokespecial #5                  // Method org/apache/hadoop/hbase/client/AsyncRegionLocator."<init>":(Lorg/apache/hadoop/hbase/client/AsyncConnectionImpl;Lorg/apache/hbase/thirdparty/io/netty/util/HashedWheelTimer;)V
      29: return

  java.util.concurrent.CompletableFuture<org.apache.hadoop.hbase.HRegionLocation> getRegionLocation(org.apache.hadoop.hbase.TableName, byte[], int, org.apache.hadoop.hbase.client.RegionLocateType, long);
    Code:
       0: aload_1
       1: invokestatic  #6                  // Method org/apache/hadoop/hbase/client/TestAsyncSingleRequestRpcRetryingCaller.access$000:()Lorg/apache/hadoop/hbase/TableName;
       4: invokevirtual #7                  // Method org/apache/hadoop/hbase/TableName.equals:(Ljava/lang/Object;)Z
       7: ifeq          68
      10: new           #8                  // class java/util/concurrent/CompletableFuture
      13: dup
      14: invokespecial #9                  // Method java/util/concurrent/CompletableFuture."<init>":()V
      17: astore        7
      19: aload_0
      20: getfield      #2                  // Field val$count:Ljava/util/concurrent/atomic/AtomicInteger;
      23: invokevirtual #10                 // Method java/util/concurrent/atomic/AtomicInteger.getAndIncrement:()I
      26: ifne          55
      29: aload_0
      30: getfield      #3                  // Field val$errorTriggered:Ljava/util/concurrent/atomic/AtomicBoolean;
      33: iconst_1
      34: invokevirtual #11                 // Method java/util/concurrent/atomic/AtomicBoolean.set:(Z)V
      37: aload         7
      39: new           #12                 // class java/lang/RuntimeException
      42: dup
      43: ldc           #13                 // String Inject error!
      45: invokespecial #14                 // Method java/lang/RuntimeException."<init>":(Ljava/lang/String;)V
      48: invokevirtual #15                 // Method java/util/concurrent/CompletableFuture.completeExceptionally:(Ljava/lang/Throwable;)Z
      51: pop
      52: goto          65
      55: aload         7
      57: aload_0
      58: getfield      #4                  // Field val$loc:Lorg/apache/hadoop/hbase/HRegionLocation;
      61: invokevirtual #16                 // Method java/util/concurrent/CompletableFuture.complete:(Ljava/lang/Object;)Z
      64: pop
      65: aload         7
      67: areturn
      68: aload_0
      69: aload_1
      70: aload_2
      71: iload_3
      72: aload         4
      74: lload         5
      76: invokespecial #17                 // Method org/apache/hadoop/hbase/client/AsyncRegionLocator.getRegionLocation:(Lorg/apache/hadoop/hbase/TableName;[BILorg/apache/hadoop/hbase/client/RegionLocateType;J)Ljava/util/concurrent/CompletableFuture;
      79: areturn

  void updateCachedLocationOnError(org.apache.hadoop.hbase.HRegionLocation, java.lang.Throwable);
    Code:
       0: return
}
