Compiled from "TestProcedureBypass.java"
public class org.apache.hadoop.hbase.procedure2.TestProcedureBypass$StuckStateMachineProcedure extends org.apache.hadoop.hbase.procedure2.ProcedureTestingUtility$NoopStateMachineProcedure<org.apache.hadoop.hbase.procedure2.TestProcedureBypass$TestProcEnv, org.apache.hadoop.hbase.procedure2.TestProcedureBypass$StuckStateMachineState> {
  public org.apache.hadoop.hbase.procedure2.TestProcedureBypass$StuckStateMachineProcedure();
    Code:
       0: aload_0
       1: invokespecial #1                  // Method org/apache/hadoop/hbase/procedure2/ProcedureTestingUtility$NoopStateMachineProcedure."<init>":()V
       4: aload_0
       5: new           #2                  // class java/util/concurrent/atomic/AtomicBoolean
       8: dup
       9: iconst_0
      10: invokespecial #3                  // Method java/util/concurrent/atomic/AtomicBoolean."<init>":(Z)V
      13: putfield      #4                  // Field stop:Ljava/util/concurrent/atomic/AtomicBoolean;
      16: return

  public org.apache.hadoop.hbase.procedure2.TestProcedureBypass$StuckStateMachineProcedure(org.apache.hadoop.hbase.procedure2.TestProcedureBypass$TestProcEnv, org.apache.hadoop.hbase.procedure2.TestProcedureBypass$StuckStateMachineState);
    Code:
       0: aload_0
       1: aload_1
       2: aload_2
       3: invokespecial #5                  // Method org/apache/hadoop/hbase/procedure2/ProcedureTestingUtility$NoopStateMachineProcedure."<init>":(Ljava/lang/Object;Ljava/lang/Object;)V
       6: aload_0
       7: new           #2                  // class java/util/concurrent/atomic/AtomicBoolean
      10: dup
      11: iconst_0
      12: invokespecial #3                  // Method java/util/concurrent/atomic/AtomicBoolean."<init>":(Z)V
      15: putfield      #4                  // Field stop:Ljava/util/concurrent/atomic/AtomicBoolean;
      18: return

  protected org.apache.hadoop.hbase.procedure2.StateMachineProcedure$Flow executeFromState(org.apache.hadoop.hbase.procedure2.TestProcedureBypass$TestProcEnv, org.apache.hadoop.hbase.procedure2.TestProcedureBypass$StuckStateMachineState) throws org.apache.hadoop.hbase.procedure2.ProcedureSuspendedException, org.apache.hadoop.hbase.procedure2.ProcedureYieldException, java.lang.InterruptedException;
    Code:
       0: getstatic     #6                  // Field org/apache/hadoop/hbase/procedure2/TestProcedureBypass$1.$SwitchMap$org$apache$hadoop$hbase$procedure2$TestProcedureBypass$StuckStateMachineState:[I
       3: aload_2
       4: invokevirtual #7                  // Method org/apache/hadoop/hbase/procedure2/TestProcedureBypass$StuckStateMachineState.ordinal:()I
       7: iaload
       8: tableswitch   { // 1 to 3
                     1: 36
                     2: 57
                     3: 78
               default: 82
          }
      36: invokestatic  #8                  // Method org/apache/hadoop/hbase/procedure2/TestProcedureBypass.access$100:()Lorg/slf4j/Logger;
      39: ldc           #9                  // String PHASE 1: START
      41: invokeinterface #10,  2           // InterfaceMethod org/slf4j/Logger.info:(Ljava/lang/String;)V
      46: aload_0
      47: getstatic     #11                 // Field org/apache/hadoop/hbase/procedure2/TestProcedureBypass$StuckStateMachineState.THEN:Lorg/apache/hadoop/hbase/procedure2/TestProcedureBypass$StuckStateMachineState;
      50: invokevirtual #12                 // Method setNextState:(Ljava/lang/Object;)V
      53: getstatic     #13                 // Field org/apache/hadoop/hbase/procedure2/StateMachineProcedure$Flow.HAS_MORE_STATE:Lorg/apache/hadoop/hbase/procedure2/StateMachineProcedure$Flow;
      56: areturn
      57: aload_0
      58: getfield      #4                  // Field stop:Ljava/util/concurrent/atomic/AtomicBoolean;
      61: invokevirtual #14                 // Method java/util/concurrent/atomic/AtomicBoolean.get:()Z
      64: ifeq          74
      67: aload_0
      68: getstatic     #15                 // Field org/apache/hadoop/hbase/procedure2/TestProcedureBypass$StuckStateMachineState.END:Lorg/apache/hadoop/hbase/procedure2/TestProcedureBypass$StuckStateMachineState;
      71: invokevirtual #12                 // Method setNextState:(Ljava/lang/Object;)V
      74: getstatic     #13                 // Field org/apache/hadoop/hbase/procedure2/StateMachineProcedure$Flow.HAS_MORE_STATE:Lorg/apache/hadoop/hbase/procedure2/StateMachineProcedure$Flow;
      77: areturn
      78: getstatic     #16                 // Field org/apache/hadoop/hbase/procedure2/StateMachineProcedure$Flow.NO_MORE_STATE:Lorg/apache/hadoop/hbase/procedure2/StateMachineProcedure$Flow;
      81: areturn
      82: new           #17                 // class java/lang/UnsupportedOperationException
      85: dup
      86: new           #18                 // class java/lang/StringBuilder
      89: dup
      90: invokespecial #19                 // Method java/lang/StringBuilder."<init>":()V
      93: ldc           #20                 // String unhandled state=
      95: invokevirtual #21                 // Method java/lang/StringBuilder.append:(Ljava/lang/String;)Ljava/lang/StringBuilder;
      98: aload_2
      99: invokevirtual #22                 // Method java/lang/StringBuilder.append:(Ljava/lang/Object;)Ljava/lang/StringBuilder;
     102: invokevirtual #23                 // Method java/lang/StringBuilder.toString:()Ljava/lang/String;
     105: invokespecial #24                 // Method java/lang/UnsupportedOperationException."<init>":(Ljava/lang/String;)V
     108: athrow

  protected org.apache.hadoop.hbase.procedure2.TestProcedureBypass$StuckStateMachineState getState(int);
    Code:
       0: invokestatic  #25                 // Method org/apache/hadoop/hbase/procedure2/TestProcedureBypass$StuckStateMachineState.values:()[Lorg/apache/hadoop/hbase/procedure2/TestProcedureBypass$StuckStateMachineState;
       3: iload_1
       4: aaload
       5: areturn

  protected int getStateId(org.apache.hadoop.hbase.procedure2.TestProcedureBypass$StuckStateMachineState);
    Code:
       0: aload_1
       1: invokevirtual #7                  // Method org/apache/hadoop/hbase/procedure2/TestProcedureBypass$StuckStateMachineState.ordinal:()I
       4: ireturn

  protected int getStateId(java.lang.Object);
    Code:
       0: aload_0
       1: aload_1
       2: checkcast     #26                 // class org/apache/hadoop/hbase/procedure2/TestProcedureBypass$StuckStateMachineState
       5: invokevirtual #27                 // Method getStateId:(Lorg/apache/hadoop/hbase/procedure2/TestProcedureBypass$StuckStateMachineState;)I
       8: ireturn

  protected java.lang.Object getState(int);
    Code:
       0: aload_0
       1: iload_1
       2: invokevirtual #28                 // Method getState:(I)Lorg/apache/hadoop/hbase/procedure2/TestProcedureBypass$StuckStateMachineState;
       5: areturn

  protected org.apache.hadoop.hbase.procedure2.StateMachineProcedure$Flow executeFromState(java.lang.Object, java.lang.Object) throws org.apache.hadoop.hbase.procedure2.ProcedureSuspendedException, org.apache.hadoop.hbase.procedure2.ProcedureYieldException, java.lang.InterruptedException;
    Code:
       0: aload_0
       1: aload_1
       2: checkcast     #29                 // class org/apache/hadoop/hbase/procedure2/TestProcedureBypass$TestProcEnv
       5: aload_2
       6: checkcast     #26                 // class org/apache/hadoop/hbase/procedure2/TestProcedureBypass$StuckStateMachineState
       9: invokevirtual #30                 // Method executeFromState:(Lorg/apache/hadoop/hbase/procedure2/TestProcedureBypass$TestProcEnv;Lorg/apache/hadoop/hbase/procedure2/TestProcedureBypass$StuckStateMachineState;)Lorg/apache/hadoop/hbase/procedure2/StateMachineProcedure$Flow;
      12: areturn
}
