Compiled from "TestUnion2.java"
public class org.apache.hadoop.hbase.types.TestUnion2 {
  public static final org.apache.hadoop.hbase.HBaseClassTestRule CLASS_RULE;

  public org.apache.hadoop.hbase.types.TestUnion2();
    Code:
       0: aload_0
       1: invokespecial #1                  // Method java/lang/Object."<init>":()V
       4: return

  public void testEncodeDecode();
    Code:
       0: bipush        10
       2: invokestatic  #2                  // Method java/lang/Integer.valueOf:(I)Ljava/lang/Integer;
       5: astore_1
       6: ldc           #3                  // String hello
       8: astore_2
       9: new           #4                  // class org/apache/hadoop/hbase/util/SimplePositionedMutableByteRange
      12: dup
      13: bipush        10
      15: invokespecial #5                  // Method org/apache/hadoop/hbase/util/SimplePositionedMutableByteRange."<init>":(I)V
      18: astore_3
      19: new           #6                  // class org/apache/hadoop/hbase/types/TestUnion2$SampleUnion1
      22: dup
      23: invokespecial #7                  // Method org/apache/hadoop/hbase/types/TestUnion2$SampleUnion1."<init>":()V
      26: astore        4
      28: aload         4
      30: aload_3
      31: aload_1
      32: invokevirtual #8                  // Method org/apache/hadoop/hbase/types/TestUnion2$SampleUnion1.encode:(Lorg/apache/hadoop/hbase/util/PositionedByteRange;Ljava/lang/Object;)I
      35: pop
      36: aload_3
      37: iconst_0
      38: invokeinterface #9,  2            // InterfaceMethod org/apache/hadoop/hbase/util/PositionedByteRange.setPosition:(I)Lorg/apache/hadoop/hbase/util/PositionedByteRange;
      43: pop
      44: iconst_0
      45: aload_1
      46: aload         4
      48: aload_3
      49: invokevirtual #10                 // Method org/apache/hadoop/hbase/types/TestUnion2$SampleUnion1.decodeA:(Lorg/apache/hadoop/hbase/util/PositionedByteRange;)Ljava/lang/Object;
      52: checkcast     #11                 // class java/lang/Integer
      55: invokevirtual #12                 // Method java/lang/Integer.compareTo:(Ljava/lang/Integer;)I
      58: if_icmpne     65
      61: iconst_1
      62: goto          66
      65: iconst_0
      66: invokestatic  #13                 // Method org/junit/Assert.assertTrue:(Z)V
      69: aload_3
      70: iconst_0
      71: invokeinterface #9,  2            // InterfaceMethod org/apache/hadoop/hbase/util/PositionedByteRange.setPosition:(I)Lorg/apache/hadoop/hbase/util/PositionedByteRange;
      76: pop
      77: aload         4
      79: aload_3
      80: aload_2
      81: invokevirtual #8                  // Method org/apache/hadoop/hbase/types/TestUnion2$SampleUnion1.encode:(Lorg/apache/hadoop/hbase/util/PositionedByteRange;Ljava/lang/Object;)I
      84: pop
      85: aload_3
      86: iconst_0
      87: invokeinterface #9,  2            // InterfaceMethod org/apache/hadoop/hbase/util/PositionedByteRange.setPosition:(I)Lorg/apache/hadoop/hbase/util/PositionedByteRange;
      92: pop
      93: iconst_0
      94: aload_2
      95: aload         4
      97: aload_3
      98: invokevirtual #14                 // Method org/apache/hadoop/hbase/types/TestUnion2$SampleUnion1.decodeB:(Lorg/apache/hadoop/hbase/util/PositionedByteRange;)Ljava/lang/Object;
     101: checkcast     #15                 // class java/lang/String
     104: invokevirtual #16                 // Method java/lang/String.compareTo:(Ljava/lang/String;)I
     107: if_icmpne     114
     110: iconst_1
     111: goto          115
     114: iconst_0
     115: invokestatic  #13                 // Method org/junit/Assert.assertTrue:(Z)V
     118: return

  public void testSkip();
    Code:
       0: bipush        10
       2: invokestatic  #2                  // Method java/lang/Integer.valueOf:(I)Ljava/lang/Integer;
       5: astore_1
       6: ldc           #3                  // String hello
       8: astore_2
       9: new           #4                  // class org/apache/hadoop/hbase/util/SimplePositionedMutableByteRange
      12: dup
      13: bipush        10
      15: invokespecial #5                  // Method org/apache/hadoop/hbase/util/SimplePositionedMutableByteRange."<init>":(I)V
      18: astore_3
      19: new           #6                  // class org/apache/hadoop/hbase/types/TestUnion2$SampleUnion1
      22: dup
      23: invokespecial #7                  // Method org/apache/hadoop/hbase/types/TestUnion2$SampleUnion1."<init>":()V
      26: astore        4
      28: aload         4
      30: aload_3
      31: aload_1
      32: invokevirtual #8                  // Method org/apache/hadoop/hbase/types/TestUnion2$SampleUnion1.encode:(Lorg/apache/hadoop/hbase/util/PositionedByteRange;Ljava/lang/Object;)I
      35: istore        5
      37: aload_3
      38: iconst_0
      39: invokeinterface #9,  2            // InterfaceMethod org/apache/hadoop/hbase/util/PositionedByteRange.setPosition:(I)Lorg/apache/hadoop/hbase/util/PositionedByteRange;
      44: pop
      45: iload         5
      47: i2l
      48: aload         4
      50: aload_3
      51: invokevirtual #17                 // Method org/apache/hadoop/hbase/types/TestUnion2$SampleUnion1.skip:(Lorg/apache/hadoop/hbase/util/PositionedByteRange;)I
      54: i2l
      55: invokestatic  #18                 // Method org/junit/Assert.assertEquals:(JJ)V
      58: aload_3
      59: iconst_0
      60: invokeinterface #9,  2            // InterfaceMethod org/apache/hadoop/hbase/util/PositionedByteRange.setPosition:(I)Lorg/apache/hadoop/hbase/util/PositionedByteRange;
      65: pop
      66: aload         4
      68: aload_3
      69: aload_2
      70: invokevirtual #8                  // Method org/apache/hadoop/hbase/types/TestUnion2$SampleUnion1.encode:(Lorg/apache/hadoop/hbase/util/PositionedByteRange;Ljava/lang/Object;)I
      73: istore        5
      75: aload_3
      76: iconst_0
      77: invokeinterface #9,  2            // InterfaceMethod org/apache/hadoop/hbase/util/PositionedByteRange.setPosition:(I)Lorg/apache/hadoop/hbase/util/PositionedByteRange;
      82: pop
      83: iload         5
      85: i2l
      86: aload         4
      88: aload_3
      89: invokevirtual #17                 // Method org/apache/hadoop/hbase/types/TestUnion2$SampleUnion1.skip:(Lorg/apache/hadoop/hbase/util/PositionedByteRange;)I
      92: i2l
      93: invokestatic  #18                 // Method org/junit/Assert.assertEquals:(JJ)V
      96: return

  static {};
    Code:
       0: ldc           #19                 // class org/apache/hadoop/hbase/types/TestUnion2
       2: invokestatic  #20                 // Method org/apache/hadoop/hbase/HBaseClassTestRule.forClass:(Ljava/lang/Class;)Lorg/apache/hadoop/hbase/HBaseClassTestRule;
       5: putstatic     #21                 // Field CLASS_RULE:Lorg/apache/hadoop/hbase/HBaseClassTestRule;
       8: return
}
