Compiled from "TestHttpServerWebapps.java"
public class org.apache.hadoop.hbase.http.TestHttpServerWebapps extends org.apache.hadoop.hbase.http.HttpServerFunctionalTest {
  public static final org.apache.hadoop.hbase.HBaseClassTestRule CLASS_RULE;

  public org.apache.hadoop.hbase.http.TestHttpServerWebapps();
    Code:
       0: aload_0
       1: invokespecial #1                  // Method org/apache/hadoop/hbase/http/HttpServerFunctionalTest."<init>":()V
       4: return

  public void testValidServerResource() throws java.lang.Throwable;
    Code:
       0: aconst_null
       1: astore_1
       2: ldc           #2                  // String test
       4: invokestatic  #3                  // Method createServer:(Ljava/lang/String;)Lorg/apache/hadoop/hbase/http/HttpServer;
       7: astore_1
       8: aload_1
       9: invokestatic  #4                  // Method stop:(Lorg/apache/hadoop/hbase/http/HttpServer;)V
      12: goto          22
      15: astore_2
      16: aload_1
      17: invokestatic  #4                  // Method stop:(Lorg/apache/hadoop/hbase/http/HttpServer;)V
      20: aload_2
      21: athrow
      22: return
    Exception table:
       from    to  target type
           2     8    15   any

  public void testMissingServerResource() throws java.lang.Throwable;
    Code:
       0: ldc           #5                  // String NoSuchWebapp
       2: invokestatic  #3                  // Method createServer:(Ljava/lang/String;)Lorg/apache/hadoop/hbase/http/HttpServer;
       5: astore_1
       6: aload_1
       7: invokevirtual #6                  // Method org/apache/hadoop/hbase/http/HttpServer.toString:()Ljava/lang/String;
      10: astore_2
      11: aload_1
      12: invokestatic  #4                  // Method stop:(Lorg/apache/hadoop/hbase/http/HttpServer;)V
      15: new           #7                  // class java/lang/StringBuilder
      18: dup
      19: invokespecial #8                  // Method java/lang/StringBuilder."<init>":()V
      22: ldc           #9                  // String Expected an exception, got
      24: invokevirtual #10                 // Method java/lang/StringBuilder.append:(Ljava/lang/String;)Ljava/lang/StringBuilder;
      27: aload_2
      28: invokevirtual #10                 // Method java/lang/StringBuilder.append:(Ljava/lang/String;)Ljava/lang/StringBuilder;
      31: invokevirtual #11                 // Method java/lang/StringBuilder.toString:()Ljava/lang/String;
      34: invokestatic  #12                 // Method fail:(Ljava/lang/String;)V
      37: goto          69
      40: astore_1
      41: getstatic     #14                 // Field log:Lorg/slf4j/Logger;
      44: new           #7                  // class java/lang/StringBuilder
      47: dup
      48: invokespecial #8                  // Method java/lang/StringBuilder."<init>":()V
      51: ldc           #15                 // String Expected exception
      53: invokevirtual #10                 // Method java/lang/StringBuilder.append:(Ljava/lang/String;)Ljava/lang/StringBuilder;
      56: aload_1
      57: invokevirtual #16                 // Method java/lang/StringBuilder.append:(Ljava/lang/Object;)Ljava/lang/StringBuilder;
      60: invokevirtual #11                 // Method java/lang/StringBuilder.toString:()Ljava/lang/String;
      63: aload_1
      64: invokeinterface #17,  3           // InterfaceMethod org/slf4j/Logger.debug:(Ljava/lang/String;Ljava/lang/Throwable;)V
      69: return
    Exception table:
       from    to  target type
           0    37    40   Class java/io/FileNotFoundException

  static {};
    Code:
       0: ldc           #18                 // class org/apache/hadoop/hbase/http/TestHttpServerWebapps
       2: invokestatic  #19                 // Method org/apache/hadoop/hbase/HBaseClassTestRule.forClass:(Ljava/lang/Class;)Lorg/apache/hadoop/hbase/HBaseClassTestRule;
       5: putstatic     #20                 // Field CLASS_RULE:Lorg/apache/hadoop/hbase/HBaseClassTestRule;
       8: ldc           #18                 // class org/apache/hadoop/hbase/http/TestHttpServerWebapps
      10: invokestatic  #21                 // Method org/slf4j/LoggerFactory.getLogger:(Ljava/lang/Class;)Lorg/slf4j/Logger;
      13: putstatic     #14                 // Field log:Lorg/slf4j/Logger;
      16: return
}
