Compiled from "TestChoreService.java"
class org.apache.hadoop.hbase.TestChoreService$1 extends org.apache.hadoop.hbase.ScheduledChore {
  final org.apache.hadoop.hbase.TestChoreService this$0;

  org.apache.hadoop.hbase.TestChoreService$1(org.apache.hadoop.hbase.TestChoreService, java.lang.String, org.apache.hadoop.hbase.Stoppable, int, long, java.util.concurrent.TimeUnit);
    Code:
       0: aload_0
       1: aload_1
       2: putfield      #1                  // Field this$0:Lorg/apache/hadoop/hbase/TestChoreService;
       5: aload_0
       6: aload_2
       7: aload_3
       8: iload         4
      10: lload         5
      12: aload         7
      14: invokespecial #2                  // Method org/apache/hadoop/hbase/ScheduledChore."<init>":(Ljava/lang/String;Lorg/apache/hadoop/hbase/Stoppable;IJLjava/util/concurrent/TimeUnit;)V
      17: return

  protected void chore();
    Code:
       0: return
}
