Compiled from "TestClientOperationTimeout.java"
public class org.apache.hadoop.hbase.TestClientOperationTimeout$DelayedRSRpcServices extends org.apache.hadoop.hbase.regionserver.RSRpcServices {
  org.apache.hadoop.hbase.TestClientOperationTimeout$DelayedRSRpcServices(org.apache.hadoop.hbase.regionserver.HRegionServer) throws java.io.IOException;
    Code:
       0: aload_0
       1: aload_1
       2: invokespecial #1                  // Method org/apache/hadoop/hbase/regionserver/RSRpcServices."<init>":(Lorg/apache/hadoop/hbase/regionserver/HRegionServer;)V
       5: return

  public org.apache.hadoop.hbase.shaded.protobuf.generated.ClientProtos$GetResponse get(org.apache.hbase.thirdparty.com.google.protobuf.RpcController, org.apache.hadoop.hbase.shaded.protobuf.generated.ClientProtos$GetRequest) throws org.apache.hbase.thirdparty.com.google.protobuf.ServiceException;
    Code:
       0: invokestatic  #2                  // Method org/apache/hadoop/hbase/TestClientOperationTimeout.access$000:()I
       3: i2l
       4: invokestatic  #3                  // Method java/lang/Thread.sleep:(J)V
       7: goto          22
      10: astore_3
      11: getstatic     #5                  // Field LOG:Lorg/slf4j/Logger;
      14: ldc           #6                  // String Sleep interrupted during get operation
      16: aload_3
      17: invokeinterface #7,  3            // InterfaceMethod org/slf4j/Logger.error:(Ljava/lang/String;Ljava/lang/Throwable;)V
      22: aload_0
      23: aload_1
      24: aload_2
      25: invokespecial #8                  // Method org/apache/hadoop/hbase/regionserver/RSRpcServices.get:(Lorg/apache/hbase/thirdparty/com/google/protobuf/RpcController;Lorg/apache/hadoop/hbase/shaded/protobuf/generated/ClientProtos$GetRequest;)Lorg/apache/hadoop/hbase/shaded/protobuf/generated/ClientProtos$GetResponse;
      28: areturn
    Exception table:
       from    to  target type
           0     7    10   Class java/lang/InterruptedException

  public org.apache.hadoop.hbase.shaded.protobuf.generated.ClientProtos$MutateResponse mutate(org.apache.hbase.thirdparty.com.google.protobuf.RpcController, org.apache.hadoop.hbase.shaded.protobuf.generated.ClientProtos$MutateRequest) throws org.apache.hbase.thirdparty.com.google.protobuf.ServiceException;
    Code:
       0: invokestatic  #9                  // Method org/apache/hadoop/hbase/TestClientOperationTimeout.access$100:()I
       3: i2l
       4: invokestatic  #3                  // Method java/lang/Thread.sleep:(J)V
       7: goto          22
      10: astore_3
      11: getstatic     #5                  // Field LOG:Lorg/slf4j/Logger;
      14: ldc           #10                 // String Sleep interrupted during mutate operation
      16: aload_3
      17: invokeinterface #7,  3            // InterfaceMethod org/slf4j/Logger.error:(Ljava/lang/String;Ljava/lang/Throwable;)V
      22: aload_0
      23: aload_1
      24: aload_2
      25: invokespecial #11                 // Method org/apache/hadoop/hbase/regionserver/RSRpcServices.mutate:(Lorg/apache/hbase/thirdparty/com/google/protobuf/RpcController;Lorg/apache/hadoop/hbase/shaded/protobuf/generated/ClientProtos$MutateRequest;)Lorg/apache/hadoop/hbase/shaded/protobuf/generated/ClientProtos$MutateResponse;
      28: areturn
    Exception table:
       from    to  target type
           0     7    10   Class java/lang/InterruptedException

  public org.apache.hadoop.hbase.shaded.protobuf.generated.ClientProtos$ScanResponse scan(org.apache.hbase.thirdparty.com.google.protobuf.RpcController, org.apache.hadoop.hbase.shaded.protobuf.generated.ClientProtos$ScanRequest) throws org.apache.hbase.thirdparty.com.google.protobuf.ServiceException;
    Code:
       0: invokestatic  #12                 // Method org/apache/hadoop/hbase/TestClientOperationTimeout.access$200:()I
       3: i2l
       4: invokestatic  #3                  // Method java/lang/Thread.sleep:(J)V
       7: goto          22
      10: astore_3
      11: getstatic     #5                  // Field LOG:Lorg/slf4j/Logger;
      14: ldc           #13                 // String Sleep interrupted during scan operation
      16: aload_3
      17: invokeinterface #7,  3            // InterfaceMethod org/slf4j/Logger.error:(Ljava/lang/String;Ljava/lang/Throwable;)V
      22: aload_0
      23: aload_1
      24: aload_2
      25: invokespecial #14                 // Method org/apache/hadoop/hbase/regionserver/RSRpcServices.scan:(Lorg/apache/hbase/thirdparty/com/google/protobuf/RpcController;Lorg/apache/hadoop/hbase/shaded/protobuf/generated/ClientProtos$ScanRequest;)Lorg/apache/hadoop/hbase/shaded/protobuf/generated/ClientProtos$ScanResponse;
      28: areturn
    Exception table:
       from    to  target type
           0     7    10   Class java/lang/InterruptedException
}
