Compiled from "TestMetricsWAL.java"
public class org.apache.hadoop.hbase.regionserver.wal.TestMetricsWAL {
  public static final org.apache.hadoop.hbase.HBaseClassTestRule CLASS_RULE;

  public org.apache.hadoop.hbase.regionserver.wal.TestMetricsWAL();
    Code:
       0: aload_0
       1: invokespecial #1                  // Method java/lang/Object."<init>":()V
       4: return

  public void testLogRollRequested() throws java.lang.Exception;
    Code:
       0: ldc           #2                  // class org/apache/hadoop/hbase/regionserver/wal/MetricsWALSourceImpl
       2: invokestatic  #3                  // Method org/mockito/Mockito.mock:(Ljava/lang/Class;)Ljava/lang/Object;
       5: checkcast     #4                  // class org/apache/hadoop/hbase/regionserver/wal/MetricsWALSource
       8: astore_1
       9: new           #5                  // class org/apache/hadoop/hbase/regionserver/wal/MetricsWAL
      12: dup
      13: aload_1
      14: invokespecial #6                  // Method org/apache/hadoop/hbase/regionserver/wal/MetricsWAL."<init>":(Lorg/apache/hadoop/hbase/regionserver/wal/MetricsWALSource;)V
      17: astore_2
      18: aload_2
      19: getstatic     #7                  // Field org/apache/hadoop/hbase/regionserver/wal/WALActionsListener$RollRequestReason.ERROR:Lorg/apache/hadoop/hbase/regionserver/wal/WALActionsListener$RollRequestReason;
      22: invokevirtual #8                  // Method org/apache/hadoop/hbase/regionserver/wal/MetricsWAL.logRollRequested:(Lorg/apache/hadoop/hbase/regionserver/wal/WALActionsListener$RollRequestReason;)V
      25: aload_2
      26: getstatic     #9                  // Field org/apache/hadoop/hbase/regionserver/wal/WALActionsListener$RollRequestReason.LOW_REPLICATION:Lorg/apache/hadoop/hbase/regionserver/wal/WALActionsListener$RollRequestReason;
      29: invokevirtual #8                  // Method org/apache/hadoop/hbase/regionserver/wal/MetricsWAL.logRollRequested:(Lorg/apache/hadoop/hbase/regionserver/wal/WALActionsListener$RollRequestReason;)V
      32: aload_2
      33: getstatic     #10                 // Field org/apache/hadoop/hbase/regionserver/wal/WALActionsListener$RollRequestReason.SLOW_SYNC:Lorg/apache/hadoop/hbase/regionserver/wal/WALActionsListener$RollRequestReason;
      36: invokevirtual #8                  // Method org/apache/hadoop/hbase/regionserver/wal/MetricsWAL.logRollRequested:(Lorg/apache/hadoop/hbase/regionserver/wal/WALActionsListener$RollRequestReason;)V
      39: aload_2
      40: getstatic     #11                 // Field org/apache/hadoop/hbase/regionserver/wal/WALActionsListener$RollRequestReason.SIZE:Lorg/apache/hadoop/hbase/regionserver/wal/WALActionsListener$RollRequestReason;
      43: invokevirtual #8                  // Method org/apache/hadoop/hbase/regionserver/wal/MetricsWAL.logRollRequested:(Lorg/apache/hadoop/hbase/regionserver/wal/WALActionsListener$RollRequestReason;)V
      46: aload_1
      47: iconst_4
      48: invokestatic  #12                 // Method org/mockito/Mockito.times:(I)Lorg/mockito/verification/VerificationMode;
      51: invokestatic  #13                 // Method org/mockito/Mockito.verify:(Ljava/lang/Object;Lorg/mockito/verification/VerificationMode;)Ljava/lang/Object;
      54: checkcast     #4                  // class org/apache/hadoop/hbase/regionserver/wal/MetricsWALSource
      57: invokeinterface #14,  1           // InterfaceMethod org/apache/hadoop/hbase/regionserver/wal/MetricsWALSource.incrementLogRollRequested:()V
      62: aload_1
      63: iconst_1
      64: invokestatic  #12                 // Method org/mockito/Mockito.times:(I)Lorg/mockito/verification/VerificationMode;
      67: invokestatic  #13                 // Method org/mockito/Mockito.verify:(Ljava/lang/Object;Lorg/mockito/verification/VerificationMode;)Ljava/lang/Object;
      70: checkcast     #4                  // class org/apache/hadoop/hbase/regionserver/wal/MetricsWALSource
      73: invokeinterface #15,  1           // InterfaceMethod org/apache/hadoop/hbase/regionserver/wal/MetricsWALSource.incrementErrorLogRoll:()V
      78: aload_1
      79: iconst_1
      80: invokestatic  #12                 // Method org/mockito/Mockito.times:(I)Lorg/mockito/verification/VerificationMode;
      83: invokestatic  #13                 // Method org/mockito/Mockito.verify:(Ljava/lang/Object;Lorg/mockito/verification/VerificationMode;)Ljava/lang/Object;
      86: checkcast     #4                  // class org/apache/hadoop/hbase/regionserver/wal/MetricsWALSource
      89: invokeinterface #16,  1           // InterfaceMethod org/apache/hadoop/hbase/regionserver/wal/MetricsWALSource.incrementLowReplicationLogRoll:()V
      94: aload_1
      95: iconst_1
      96: invokestatic  #12                 // Method org/mockito/Mockito.times:(I)Lorg/mockito/verification/VerificationMode;
      99: invokestatic  #13                 // Method org/mockito/Mockito.verify:(Ljava/lang/Object;Lorg/mockito/verification/VerificationMode;)Ljava/lang/Object;
     102: checkcast     #4                  // class org/apache/hadoop/hbase/regionserver/wal/MetricsWALSource
     105: invokeinterface #17,  1           // InterfaceMethod org/apache/hadoop/hbase/regionserver/wal/MetricsWALSource.incrementSlowSyncLogRoll:()V
     110: aload_1
     111: iconst_1
     112: invokestatic  #12                 // Method org/mockito/Mockito.times:(I)Lorg/mockito/verification/VerificationMode;
     115: invokestatic  #13                 // Method org/mockito/Mockito.verify:(Ljava/lang/Object;Lorg/mockito/verification/VerificationMode;)Ljava/lang/Object;
     118: checkcast     #4                  // class org/apache/hadoop/hbase/regionserver/wal/MetricsWALSource
     121: invokeinterface #18,  1           // InterfaceMethod org/apache/hadoop/hbase/regionserver/wal/MetricsWALSource.incrementSizeLogRoll:()V
     126: return

  public void testPostSync() throws java.lang.Exception;
    Code:
       0: getstatic     #19                 // Field java/util/concurrent/TimeUnit.MILLISECONDS:Ljava/util/concurrent/TimeUnit;
       3: ldc2_w        #20                 // long 145l
       6: invokevirtual #22                 // Method java/util/concurrent/TimeUnit.toNanos:(J)J
       9: lstore_1
      10: ldc           #2                  // class org/apache/hadoop/hbase/regionserver/wal/MetricsWALSourceImpl
      12: invokestatic  #3                  // Method org/mockito/Mockito.mock:(Ljava/lang/Class;)Ljava/lang/Object;
      15: checkcast     #4                  // class org/apache/hadoop/hbase/regionserver/wal/MetricsWALSource
      18: astore_3
      19: new           #5                  // class org/apache/hadoop/hbase/regionserver/wal/MetricsWAL
      22: dup
      23: aload_3
      24: invokespecial #6                  // Method org/apache/hadoop/hbase/regionserver/wal/MetricsWAL."<init>":(Lorg/apache/hadoop/hbase/regionserver/wal/MetricsWALSource;)V
      27: astore        4
      29: aload         4
      31: lload_1
      32: iconst_1
      33: invokevirtual #23                 // Method org/apache/hadoop/hbase/regionserver/wal/MetricsWAL.postSync:(JI)V
      36: aload_3
      37: iconst_1
      38: invokestatic  #12                 // Method org/mockito/Mockito.times:(I)Lorg/mockito/verification/VerificationMode;
      41: invokestatic  #13                 // Method org/mockito/Mockito.verify:(Ljava/lang/Object;Lorg/mockito/verification/VerificationMode;)Ljava/lang/Object;
      44: checkcast     #4                  // class org/apache/hadoop/hbase/regionserver/wal/MetricsWALSource
      47: ldc2_w        #20                 // long 145l
      50: invokeinterface #24,  3           // InterfaceMethod org/apache/hadoop/hbase/regionserver/wal/MetricsWALSource.incrementSyncTime:(J)V
      55: return

  public void testSlowAppend() throws java.lang.Exception;
    Code:
       0: new           #2                  // class org/apache/hadoop/hbase/regionserver/wal/MetricsWALSourceImpl
       3: dup
       4: invokespecial #25                 // Method org/apache/hadoop/hbase/regionserver/wal/MetricsWALSourceImpl."<init>":()V
       7: astore_1
       8: new           #5                  // class org/apache/hadoop/hbase/regionserver/wal/MetricsWAL
      11: dup
      12: aload_1
      13: invokespecial #6                  // Method org/apache/hadoop/hbase/regionserver/wal/MetricsWAL."<init>":(Lorg/apache/hadoop/hbase/regionserver/wal/MetricsWALSource;)V
      16: astore_2
      17: aload_2
      18: lconst_1
      19: ldc2_w        #26                 // long 900l
      22: aconst_null
      23: aconst_null
      24: invokevirtual #28                 // Method org/apache/hadoop/hbase/regionserver/wal/MetricsWAL.postAppend:(JJLorg/apache/hadoop/hbase/wal/WALKey;Lorg/apache/hadoop/hbase/wal/WALEdit;)V
      27: aload_2
      28: lconst_1
      29: ldc2_w        #29                 // long 1010l
      32: aconst_null
      33: aconst_null
      34: invokevirtual #28                 // Method org/apache/hadoop/hbase/regionserver/wal/MetricsWAL.postAppend:(JJLorg/apache/hadoop/hbase/wal/WALKey;Lorg/apache/hadoop/hbase/wal/WALEdit;)V
      37: aload_2
      38: lconst_1
      39: ldc2_w        #31                 // long 2000l
      42: aconst_null
      43: aconst_null
      44: invokevirtual #28                 // Method org/apache/hadoop/hbase/regionserver/wal/MetricsWAL.postAppend:(JJLorg/apache/hadoop/hbase/wal/WALKey;Lorg/apache/hadoop/hbase/wal/WALEdit;)V
      47: ldc2_w        #33                 // long 2l
      50: aload_1
      51: invokeinterface #35,  1           // InterfaceMethod org/apache/hadoop/hbase/regionserver/wal/MetricsWALSource.getSlowAppendCount:()J
      56: invokestatic  #36                 // Method org/junit/Assert.assertEquals:(JJ)V
      59: return

  public void testWalWrittenInBytes() throws java.lang.Exception;
    Code:
       0: ldc           #2                  // class org/apache/hadoop/hbase/regionserver/wal/MetricsWALSourceImpl
       2: invokestatic  #3                  // Method org/mockito/Mockito.mock:(Ljava/lang/Class;)Ljava/lang/Object;
       5: checkcast     #4                  // class org/apache/hadoop/hbase/regionserver/wal/MetricsWALSource
       8: astore_1
       9: new           #5                  // class org/apache/hadoop/hbase/regionserver/wal/MetricsWAL
      12: dup
      13: aload_1
      14: invokespecial #6                  // Method org/apache/hadoop/hbase/regionserver/wal/MetricsWAL."<init>":(Lorg/apache/hadoop/hbase/regionserver/wal/MetricsWALSource;)V
      17: astore_2
      18: aload_2
      19: ldc2_w        #37                 // long 100l
      22: ldc2_w        #26                 // long 900l
      25: aconst_null
      26: aconst_null
      27: invokevirtual #28                 // Method org/apache/hadoop/hbase/regionserver/wal/MetricsWAL.postAppend:(JJLorg/apache/hadoop/hbase/wal/WALKey;Lorg/apache/hadoop/hbase/wal/WALEdit;)V
      30: aload_2
      31: ldc2_w        #39                 // long 200l
      34: ldc2_w        #31                 // long 2000l
      37: aconst_null
      38: aconst_null
      39: invokevirtual #28                 // Method org/apache/hadoop/hbase/regionserver/wal/MetricsWAL.postAppend:(JJLorg/apache/hadoop/hbase/wal/WALKey;Lorg/apache/hadoop/hbase/wal/WALEdit;)V
      42: aload_1
      43: iconst_1
      44: invokestatic  #12                 // Method org/mockito/Mockito.times:(I)Lorg/mockito/verification/VerificationMode;
      47: invokestatic  #13                 // Method org/mockito/Mockito.verify:(Ljava/lang/Object;Lorg/mockito/verification/VerificationMode;)Ljava/lang/Object;
      50: checkcast     #4                  // class org/apache/hadoop/hbase/regionserver/wal/MetricsWALSource
      53: ldc2_w        #37                 // long 100l
      56: invokeinterface #41,  3           // InterfaceMethod org/apache/hadoop/hbase/regionserver/wal/MetricsWALSource.incrementWrittenBytes:(J)V
      61: aload_1
      62: iconst_1
      63: invokestatic  #12                 // Method org/mockito/Mockito.times:(I)Lorg/mockito/verification/VerificationMode;
      66: invokestatic  #13                 // Method org/mockito/Mockito.verify:(Ljava/lang/Object;Lorg/mockito/verification/VerificationMode;)Ljava/lang/Object;
      69: checkcast     #4                  // class org/apache/hadoop/hbase/regionserver/wal/MetricsWALSource
      72: ldc2_w        #39                 // long 200l
      75: invokeinterface #41,  3           // InterfaceMethod org/apache/hadoop/hbase/regionserver/wal/MetricsWALSource.incrementWrittenBytes:(J)V
      80: return

  static {};
    Code:
       0: ldc           #42                 // class org/apache/hadoop/hbase/regionserver/wal/TestMetricsWAL
       2: invokestatic  #43                 // Method org/apache/hadoop/hbase/HBaseClassTestRule.forClass:(Ljava/lang/Class;)Lorg/apache/hadoop/hbase/HBaseClassTestRule;
       5: putstatic     #44                 // Field CLASS_RULE:Lorg/apache/hadoop/hbase/HBaseClassTestRule;
       8: return
}
