Compiled from "TestModifyPeerProcedureRetryBackoff.java"
public class org.apache.hadoop.hbase.master.replication.TestModifyPeerProcedureRetryBackoff {
  public static final org.apache.hadoop.hbase.HBaseClassTestRule CLASS_RULE;

  public org.apache.hadoop.hbase.master.replication.TestModifyPeerProcedureRetryBackoff();
    Code:
       0: aload_0
       1: invokespecial #2                  // Method java/lang/Object."<init>":()V
       4: return

  public static void setUp() throws java.lang.Exception;
    Code:
       0: getstatic     #3                  // Field UTIL:Lorg/apache/hadoop/hbase/HBaseTestingUtility;
       3: iconst_1
       4: invokevirtual #4                  // Method org/apache/hadoop/hbase/HBaseTestingUtility.startMiniCluster:(I)Lorg/apache/hadoop/hbase/MiniHBaseCluster;
       7: pop
       8: return

  public static void tearDown() throws java.lang.Exception;
    Code:
       0: getstatic     #3                  // Field UTIL:Lorg/apache/hadoop/hbase/HBaseTestingUtility;
       3: invokevirtual #5                  // Method org/apache/hadoop/hbase/HBaseTestingUtility.shutdownMiniCluster:()V
       6: return

  public void test() throws java.io.IOException, java.lang.InterruptedException;
    Code:
       0: getstatic     #3                  // Field UTIL:Lorg/apache/hadoop/hbase/HBaseTestingUtility;
       3: invokevirtual #14                 // Method org/apache/hadoop/hbase/HBaseTestingUtility.getMiniHBaseCluster:()Lorg/apache/hadoop/hbase/MiniHBaseCluster;
       6: invokevirtual #15                 // Method org/apache/hadoop/hbase/MiniHBaseCluster.getMaster:()Lorg/apache/hadoop/hbase/master/HMaster;
       9: invokevirtual #16                 // Method org/apache/hadoop/hbase/master/HMaster.getMasterProcedureExecutor:()Lorg/apache/hadoop/hbase/procedure2/ProcedureExecutor;
      12: astore_1
      13: aload_1
      14: new           #6                  // class org/apache/hadoop/hbase/master/replication/TestModifyPeerProcedureRetryBackoff$TestModifyPeerProcedure
      17: dup
      18: ldc           #17                 // String 1
      20: invokespecial #18                 // Method org/apache/hadoop/hbase/master/replication/TestModifyPeerProcedureRetryBackoff$TestModifyPeerProcedure."<init>":(Ljava/lang/String;)V
      23: invokevirtual #19                 // Method org/apache/hadoop/hbase/procedure2/ProcedureExecutor.submitProcedure:(Lorg/apache/hadoop/hbase/procedure2/Procedure;)J
      26: lstore_2
      27: aload_0
      28: invokespecial #20                 // Method assertBackoffIncrease:()V
      31: aload_0
      32: invokespecial #20                 // Method assertBackoffIncrease:()V
      35: aload_0
      36: invokespecial #20                 // Method assertBackoffIncrease:()V
      39: aload_0
      40: invokespecial #20                 // Method assertBackoffIncrease:()V
      43: aload_0
      44: invokespecial #20                 // Method assertBackoffIncrease:()V
      47: aload_0
      48: invokespecial #20                 // Method assertBackoffIncrease:()V
      51: getstatic     #3                  // Field UTIL:Lorg/apache/hadoop/hbase/HBaseTestingUtility;
      54: ldc2_w        #7                  // long 30000l
      57: aload_1
      58: lload_2
      59: invokedynamic #21,  0             // InvokeDynamic #1:evaluate:(Lorg/apache/hadoop/hbase/procedure2/ProcedureExecutor;J)Lorg/apache/hadoop/hbase/Waiter$Predicate;
      64: invokevirtual #13                 // Method org/apache/hadoop/hbase/HBaseTestingUtility.waitFor:(JLorg/apache/hadoop/hbase/Waiter$Predicate;)J
      67: pop2
      68: return

  static boolean access$000();
    Code:
       0: getstatic     #1                  // Field FAIL:Z
       3: ireturn

  static boolean access$002(boolean);
    Code:
       0: iload_0
       1: dup
       2: putstatic     #1                  // Field FAIL:Z
       5: ireturn

  static {};
    Code:
       0: ldc           #11                 // class org/apache/hadoop/hbase/master/replication/TestModifyPeerProcedureRetryBackoff
       2: invokestatic  #23                 // Method org/apache/hadoop/hbase/HBaseClassTestRule.forClass:(Ljava/lang/Class;)Lorg/apache/hadoop/hbase/HBaseClassTestRule;
       5: putstatic     #24                 // Field CLASS_RULE:Lorg/apache/hadoop/hbase/HBaseClassTestRule;
       8: new           #25                 // class org/apache/hadoop/hbase/HBaseTestingUtility
      11: dup
      12: invokespecial #26                 // Method org/apache/hadoop/hbase/HBaseTestingUtility."<init>":()V
      15: putstatic     #3                  // Field UTIL:Lorg/apache/hadoop/hbase/HBaseTestingUtility;
      18: iconst_1
      19: putstatic     #1                  // Field FAIL:Z
      22: return
}
