Compiled from "TestZKAsyncRegistry.java"
public class org.apache.hadoop.hbase.client.TestZKAsyncRegistry {
  public static final org.apache.hadoop.hbase.HBaseClassTestRule CLASS_RULE;

  static final org.slf4j.Logger LOG;

  static final org.apache.hadoop.hbase.HBaseTestingUtility TEST_UTIL;

  public org.apache.hadoop.hbase.client.TestZKAsyncRegistry();
    Code:
       0: aload_0
       1: invokespecial #2                  // Method java/lang/Object."<init>":()V
       4: return

  public static void setUp() throws java.lang.Exception;
    Code:
       0: getstatic     #3                  // Field TEST_UTIL:Lorg/apache/hadoop/hbase/HBaseTestingUtility;
       3: invokevirtual #4                  // Method org/apache/hadoop/hbase/HBaseTestingUtility.getConfiguration:()Lorg/apache/hadoop/conf/Configuration;
       6: ldc           #5                  // String hbase.meta.replica.count
       8: iconst_3
       9: invokevirtual #6                  // Method org/apache/hadoop/conf/Configuration.setInt:(Ljava/lang/String;I)V
      12: getstatic     #3                  // Field TEST_UTIL:Lorg/apache/hadoop/hbase/HBaseTestingUtility;
      15: iconst_3
      16: invokevirtual #7                  // Method org/apache/hadoop/hbase/HBaseTestingUtility.startMiniCluster:(I)Lorg/apache/hadoop/hbase/MiniHBaseCluster;
      19: pop
      20: new           #8                  // class org/apache/hadoop/conf/Configuration
      23: dup
      24: getstatic     #3                  // Field TEST_UTIL:Lorg/apache/hadoop/hbase/HBaseTestingUtility;
      27: invokevirtual #4                  // Method org/apache/hadoop/hbase/HBaseTestingUtility.getConfiguration:()Lorg/apache/hadoop/conf/Configuration;
      30: invokespecial #9                  // Method org/apache/hadoop/conf/Configuration."<init>":(Lorg/apache/hadoop/conf/Configuration;)V
      33: astore_0
      34: aload_0
      35: ldc           #5                  // String hbase.meta.replica.count
      37: iconst_1
      38: invokevirtual #6                  // Method org/apache/hadoop/conf/Configuration.setInt:(Ljava/lang/String;I)V
      41: new           #10                 // class org/apache/hadoop/hbase/client/ZKAsyncRegistry
      44: dup
      45: aload_0
      46: invokespecial #11                 // Method org/apache/hadoop/hbase/client/ZKAsyncRegistry."<init>":(Lorg/apache/hadoop/conf/Configuration;)V
      49: putstatic     #12                 // Field REGISTRY:Lorg/apache/hadoop/hbase/client/ZKAsyncRegistry;
      52: return

  public static void tearDown() throws java.lang.Exception;
    Code:
       0: getstatic     #12                 // Field REGISTRY:Lorg/apache/hadoop/hbase/client/ZKAsyncRegistry;
       3: invokestatic  #13                 // Method org/apache/commons/io/IOUtils.closeQuietly:(Ljava/io/Closeable;)V
       6: getstatic     #3                  // Field TEST_UTIL:Lorg/apache/hadoop/hbase/HBaseTestingUtility;
       9: invokevirtual #14                 // Method org/apache/hadoop/hbase/HBaseTestingUtility.shutdownMiniCluster:()V
      12: return

  public void test() throws java.lang.InterruptedException, java.util.concurrent.ExecutionException, java.io.IOException;
    Code:
       0: getstatic     #15                 // Field LOG:Lorg/slf4j/Logger;
       3: ldc           #16                 // String STARTED TEST
       5: invokeinterface #17,  2           // InterfaceMethod org/slf4j/Logger.info:(Ljava/lang/String;)V
      10: getstatic     #12                 // Field REGISTRY:Lorg/apache/hadoop/hbase/client/ZKAsyncRegistry;
      13: invokevirtual #18                 // Method org/apache/hadoop/hbase/client/ZKAsyncRegistry.getClusterId:()Ljava/util/concurrent/CompletableFuture;
      16: invokevirtual #19                 // Method java/util/concurrent/CompletableFuture.get:()Ljava/lang/Object;
      19: checkcast     #20                 // class java/lang/String
      22: astore_1
      23: getstatic     #3                  // Field TEST_UTIL:Lorg/apache/hadoop/hbase/HBaseTestingUtility;
      26: invokevirtual #21                 // Method org/apache/hadoop/hbase/HBaseTestingUtility.getHBaseCluster:()Lorg/apache/hadoop/hbase/MiniHBaseCluster;
      29: invokevirtual #22                 // Method org/apache/hadoop/hbase/MiniHBaseCluster.getMaster:()Lorg/apache/hadoop/hbase/master/HMaster;
      32: invokevirtual #23                 // Method org/apache/hadoop/hbase/master/HMaster.getClusterId:()Ljava/lang/String;
      35: astore_2
      36: new           #24                 // class java/lang/StringBuilder
      39: dup
      40: invokespecial #25                 // Method java/lang/StringBuilder."<init>":()V
      43: ldc           #26                 // String Expected
      45: invokevirtual #27                 // Method java/lang/StringBuilder.append:(Ljava/lang/String;)Ljava/lang/StringBuilder;
      48: aload_2
      49: invokevirtual #27                 // Method java/lang/StringBuilder.append:(Ljava/lang/String;)Ljava/lang/StringBuilder;
      52: ldc           #28                 // String , found=
      54: invokevirtual #27                 // Method java/lang/StringBuilder.append:(Ljava/lang/String;)Ljava/lang/StringBuilder;
      57: aload_1
      58: invokevirtual #27                 // Method java/lang/StringBuilder.append:(Ljava/lang/String;)Ljava/lang/StringBuilder;
      61: invokevirtual #29                 // Method java/lang/StringBuilder.toString:()Ljava/lang/String;
      64: aload_2
      65: aload_1
      66: invokestatic  #30                 // Method org/junit/Assert.assertEquals:(Ljava/lang/String;Ljava/lang/Object;Ljava/lang/Object;)V
      69: getstatic     #3                  // Field TEST_UTIL:Lorg/apache/hadoop/hbase/HBaseTestingUtility;
      72: invokevirtual #21                 // Method org/apache/hadoop/hbase/HBaseTestingUtility.getHBaseCluster:()Lorg/apache/hadoop/hbase/MiniHBaseCluster;
      75: invokevirtual #31                 // Method org/apache/hadoop/hbase/MiniHBaseCluster.getClusterMetrics:()Lorg/apache/hadoop/hbase/ClusterMetrics;
      78: invokeinterface #32,  1           // InterfaceMethod org/apache/hadoop/hbase/ClusterMetrics.getLiveServerMetrics:()Ljava/util/Map;
      83: invokeinterface #33,  1           // InterfaceMethod java/util/Map.size:()I
      88: i2l
      89: getstatic     #12                 // Field REGISTRY:Lorg/apache/hadoop/hbase/client/ZKAsyncRegistry;
      92: invokevirtual #34                 // Method org/apache/hadoop/hbase/client/ZKAsyncRegistry.getCurrentNrHRS:()Ljava/util/concurrent/CompletableFuture;
      95: invokevirtual #19                 // Method java/util/concurrent/CompletableFuture.get:()Ljava/lang/Object;
      98: checkcast     #35                 // class java/lang/Integer
     101: invokevirtual #36                 // Method java/lang/Integer.intValue:()I
     104: i2l
     105: invokestatic  #37                 // Method org/junit/Assert.assertEquals:(JJ)V
     108: getstatic     #3                  // Field TEST_UTIL:Lorg/apache/hadoop/hbase/HBaseTestingUtility;
     111: invokevirtual #21                 // Method org/apache/hadoop/hbase/HBaseTestingUtility.getHBaseCluster:()Lorg/apache/hadoop/hbase/MiniHBaseCluster;
     114: invokevirtual #22                 // Method org/apache/hadoop/hbase/MiniHBaseCluster.getMaster:()Lorg/apache/hadoop/hbase/master/HMaster;
     117: invokevirtual #38                 // Method org/apache/hadoop/hbase/master/HMaster.getServerName:()Lorg/apache/hadoop/hbase/ServerName;
     120: getstatic     #12                 // Field REGISTRY:Lorg/apache/hadoop/hbase/client/ZKAsyncRegistry;
     123: invokevirtual #39                 // Method org/apache/hadoop/hbase/client/ZKAsyncRegistry.getMasterAddress:()Ljava/util/concurrent/CompletableFuture;
     126: invokevirtual #19                 // Method java/util/concurrent/CompletableFuture.get:()Ljava/lang/Object;
     129: invokestatic  #40                 // Method org/junit/Assert.assertEquals:(Ljava/lang/Object;Ljava/lang/Object;)V
     132: ldc2_w        #41                 // long -1l
     135: getstatic     #12                 // Field REGISTRY:Lorg/apache/hadoop/hbase/client/ZKAsyncRegistry;
     138: invokevirtual #43                 // Method org/apache/hadoop/hbase/client/ZKAsyncRegistry.getMasterInfoPort:()Ljava/util/concurrent/CompletableFuture;
     141: invokevirtual #19                 // Method java/util/concurrent/CompletableFuture.get:()Ljava/lang/Object;
     144: checkcast     #35                 // class java/lang/Integer
     147: invokevirtual #36                 // Method java/lang/Integer.intValue:()I
     150: i2l
     151: invokestatic  #37                 // Method org/junit/Assert.assertEquals:(JJ)V
     154: getstatic     #3                  // Field TEST_UTIL:Lorg/apache/hadoop/hbase/HBaseTestingUtility;
     157: invokevirtual #4                  // Method org/apache/hadoop/hbase/HBaseTestingUtility.getConfiguration:()Lorg/apache/hadoop/conf/Configuration;
     160: getstatic     #12                 // Field REGISTRY:Lorg/apache/hadoop/hbase/client/ZKAsyncRegistry;
     163: iconst_3
     164: invokestatic  #44                 // Method org/apache/hadoop/hbase/client/RegionReplicaTestHelper.waitUntilAllMetaReplicasHavingRegionLocation:(Lorg/apache/hadoop/conf/Configuration;Lorg/apache/hadoop/hbase/client/AsyncRegistry;I)V
     167: getstatic     #12                 // Field REGISTRY:Lorg/apache/hadoop/hbase/client/ZKAsyncRegistry;
     170: invokevirtual #45                 // Method org/apache/hadoop/hbase/client/ZKAsyncRegistry.getMetaRegionLocation:()Ljava/util/concurrent/CompletableFuture;
     173: invokevirtual #19                 // Method java/util/concurrent/CompletableFuture.get:()Ljava/lang/Object;
     176: checkcast     #46                 // class org/apache/hadoop/hbase/RegionLocations
     179: astore_3
     180: ldc2_w        #47                 // long 3l
     183: aload_3
     184: invokevirtual #49                 // Method org/apache/hadoop/hbase/RegionLocations.getRegionLocations:()[Lorg/apache/hadoop/hbase/HRegionLocation;
     187: arraylength
     188: i2l
     189: invokestatic  #37                 // Method org/junit/Assert.assertEquals:(JJ)V
     192: iconst_0
     193: iconst_3
     194: invokestatic  #50                 // InterfaceMethod java/util/stream/IntStream.range:(II)Ljava/util/stream/IntStream;
     197: aload_3
     198: invokedynamic #51,  0             // InvokeDynamic #0:accept:(Lorg/apache/hadoop/hbase/RegionLocations;)Ljava/util/function/IntConsumer;
     203: invokeinterface #52,  2           // InterfaceMethod java/util/stream/IntStream.forEach:(Ljava/util/function/IntConsumer;)V
     208: return

  public void testIndependentZKConnections() throws java.io.IOException;
    Code:
       0: getstatic     #12                 // Field REGISTRY:Lorg/apache/hadoop/hbase/client/ZKAsyncRegistry;
       3: invokevirtual #53                 // Method org/apache/hadoop/hbase/client/ZKAsyncRegistry.getZKClient:()Lorg/apache/hadoop/hbase/zookeeper/ReadOnlyZKClient;
       6: astore_1
       7: aconst_null
       8: astore_2
       9: new           #8                  // class org/apache/hadoop/conf/Configuration
      12: dup
      13: getstatic     #3                  // Field TEST_UTIL:Lorg/apache/hadoop/hbase/HBaseTestingUtility;
      16: invokevirtual #4                  // Method org/apache/hadoop/hbase/HBaseTestingUtility.getConfiguration:()Lorg/apache/hadoop/conf/Configuration;
      19: invokespecial #9                  // Method org/apache/hadoop/conf/Configuration."<init>":(Lorg/apache/hadoop/conf/Configuration;)V
      22: astore_3
      23: aload_3
      24: ldc           #54                 // String hbase.zookeeper.quorum
      26: ldc           #55                 // String 127.0.0.1
      28: invokevirtual #56                 // Method org/apache/hadoop/conf/Configuration.set:(Ljava/lang/String;Ljava/lang/String;)V
      31: new           #10                 // class org/apache/hadoop/hbase/client/ZKAsyncRegistry
      34: dup
      35: aload_3
      36: invokespecial #11                 // Method org/apache/hadoop/hbase/client/ZKAsyncRegistry."<init>":(Lorg/apache/hadoop/conf/Configuration;)V
      39: astore        4
      41: aconst_null
      42: astore        5
      44: aload         4
      46: invokevirtual #53                 // Method org/apache/hadoop/hbase/client/ZKAsyncRegistry.getZKClient:()Lorg/apache/hadoop/hbase/zookeeper/ReadOnlyZKClient;
      49: astore        6
      51: ldc           #57                 // String Using a different configuration / quorum should result in different backing zk connection.
      53: aload_1
      54: aload         6
      56: invokestatic  #58                 // Method org/junit/Assert.assertNotSame:(Ljava/lang/String;Ljava/lang/Object;Ljava/lang/Object;)V
      59: ldc           #59                 // String Using a different configrution / quorum should be reflected in the zk connection.
      61: aload_1
      62: invokevirtual #60                 // Method org/apache/hadoop/hbase/zookeeper/ReadOnlyZKClient.getConnectString:()Ljava/lang/String;
      65: aload         6
      67: invokevirtual #60                 // Method org/apache/hadoop/hbase/zookeeper/ReadOnlyZKClient.getConnectString:()Ljava/lang/String;
      70: invokestatic  #61                 // Method org/junit/Assert.assertNotEquals:(Ljava/lang/String;Ljava/lang/Object;Ljava/lang/Object;)V
      73: aload         4
      75: ifnull        160
      78: aload         5
      80: ifnull        103
      83: aload         4
      85: invokevirtual #62                 // Method org/apache/hadoop/hbase/client/ZKAsyncRegistry.close:()V
      88: goto          160
      91: astore        6
      93: aload         5
      95: aload         6
      97: invokevirtual #64                 // Method java/lang/Throwable.addSuppressed:(Ljava/lang/Throwable;)V
     100: goto          160
     103: aload         4
     105: invokevirtual #62                 // Method org/apache/hadoop/hbase/client/ZKAsyncRegistry.close:()V
     108: goto          160
     111: astore        6
     113: aload         6
     115: astore        5
     117: aload         6
     119: athrow
     120: astore        7
     122: aload         4
     124: ifnull        157
     127: aload         5
     129: ifnull        152
     132: aload         4
     134: invokevirtual #62                 // Method org/apache/hadoop/hbase/client/ZKAsyncRegistry.close:()V
     137: goto          157
     140: astore        8
     142: aload         5
     144: aload         8
     146: invokevirtual #64                 // Method java/lang/Throwable.addSuppressed:(Ljava/lang/Throwable;)V
     149: goto          157
     152: aload         4
     154: invokevirtual #62                 // Method org/apache/hadoop/hbase/client/ZKAsyncRegistry.close:()V
     157: aload         7
     159: athrow
     160: aload_1
     161: ifnull        231
     164: aload_2
     165: ifnull        184
     168: aload_1
     169: invokevirtual #65                 // Method org/apache/hadoop/hbase/zookeeper/ReadOnlyZKClient.close:()V
     172: goto          231
     175: astore_3
     176: aload_2
     177: aload_3
     178: invokevirtual #64                 // Method java/lang/Throwable.addSuppressed:(Ljava/lang/Throwable;)V
     181: goto          231
     184: aload_1
     185: invokevirtual #65                 // Method org/apache/hadoop/hbase/zookeeper/ReadOnlyZKClient.close:()V
     188: goto          231
     191: astore_3
     192: aload_3
     193: astore_2
     194: aload_3
     195: athrow
     196: astore        9
     198: aload_1
     199: ifnull        228
     202: aload_2
     203: ifnull        224
     206: aload_1
     207: invokevirtual #65                 // Method org/apache/hadoop/hbase/zookeeper/ReadOnlyZKClient.close:()V
     210: goto          228
     213: astore        10
     215: aload_2
     216: aload         10
     218: invokevirtual #64                 // Method java/lang/Throwable.addSuppressed:(Ljava/lang/Throwable;)V
     221: goto          228
     224: aload_1
     225: invokevirtual #65                 // Method org/apache/hadoop/hbase/zookeeper/ReadOnlyZKClient.close:()V
     228: aload         9
     230: athrow
     231: getstatic     #15                 // Field LOG:Lorg/slf4j/Logger;
     234: ldc           #66                 // String DONE!
     236: invokeinterface #17,  2           // InterfaceMethod org/slf4j/Logger.info:(Ljava/lang/String;)V
     241: goto          259
     244: astore        11
     246: getstatic     #15                 // Field LOG:Lorg/slf4j/Logger;
     249: ldc           #66                 // String DONE!
     251: invokeinterface #17,  2           // InterfaceMethod org/slf4j/Logger.info:(Ljava/lang/String;)V
     256: aload         11
     258: athrow
     259: return
    Exception table:
       from    to  target type
          83    88    91   Class java/lang/Throwable
          44    73   111   Class java/lang/Throwable
          44    73   120   any
         132   137   140   Class java/lang/Throwable
         111   122   120   any
         168   172   175   Class java/lang/Throwable
           9   160   191   Class java/lang/Throwable
           9   160   196   any
         206   210   213   Class java/lang/Throwable
         191   198   196   any
           0   231   244   any
         244   246   244   any

  public void testNoMetaAvailable() throws java.lang.InterruptedException;
    Code:
       0: new           #8                  // class org/apache/hadoop/conf/Configuration
       3: dup
       4: getstatic     #3                  // Field TEST_UTIL:Lorg/apache/hadoop/hbase/HBaseTestingUtility;
       7: invokevirtual #4                  // Method org/apache/hadoop/hbase/HBaseTestingUtility.getConfiguration:()Lorg/apache/hadoop/conf/Configuration;
      10: invokespecial #9                  // Method org/apache/hadoop/conf/Configuration."<init>":(Lorg/apache/hadoop/conf/Configuration;)V
      13: astore_1
      14: aload_1
      15: ldc           #67                 // String zookeeper.znode.metaserver
      17: ldc           #68                 // String whatever
      19: invokevirtual #56                 // Method org/apache/hadoop/conf/Configuration.set:(Ljava/lang/String;Ljava/lang/String;)V
      22: new           #10                 // class org/apache/hadoop/hbase/client/ZKAsyncRegistry
      25: dup
      26: aload_1
      27: invokespecial #11                 // Method org/apache/hadoop/hbase/client/ZKAsyncRegistry."<init>":(Lorg/apache/hadoop/conf/Configuration;)V
      30: astore_2
      31: aconst_null
      32: astore_3
      33: aload_2
      34: invokevirtual #45                 // Method org/apache/hadoop/hbase/client/ZKAsyncRegistry.getMetaRegionLocation:()Ljava/util/concurrent/CompletableFuture;
      37: invokevirtual #19                 // Method java/util/concurrent/CompletableFuture.get:()Ljava/lang/Object;
      40: pop
      41: ldc           #69                 // String Should have failed since we set an incorrect meta znode prefix
      43: invokestatic  #70                 // Method org/junit/Assert.fail:(Ljava/lang/String;)V
      46: goto          64
      49: astore        4
      51: aload         4
      53: invokevirtual #72                 // Method java/util/concurrent/ExecutionException.getCause:()Ljava/lang/Throwable;
      56: ldc           #73                 // class java/io/IOException
      58: invokestatic  #74                 // Method org/hamcrest/CoreMatchers.instanceOf:(Ljava/lang/Class;)Lorg/hamcrest/Matcher;
      61: invokestatic  #75                 // Method org/junit/Assert.assertThat:(Ljava/lang/Object;Lorg/hamcrest/Matcher;)V
      64: aload_2
      65: ifnull        140
      68: aload_3
      69: ifnull        90
      72: aload_2
      73: invokevirtual #62                 // Method org/apache/hadoop/hbase/client/ZKAsyncRegistry.close:()V
      76: goto          140
      79: astore        4
      81: aload_3
      82: aload         4
      84: invokevirtual #64                 // Method java/lang/Throwable.addSuppressed:(Ljava/lang/Throwable;)V
      87: goto          140
      90: aload_2
      91: invokevirtual #62                 // Method org/apache/hadoop/hbase/client/ZKAsyncRegistry.close:()V
      94: goto          140
      97: astore        4
      99: aload         4
     101: astore_3
     102: aload         4
     104: athrow
     105: astore        5
     107: aload_2
     108: ifnull        137
     111: aload_3
     112: ifnull        133
     115: aload_2
     116: invokevirtual #62                 // Method org/apache/hadoop/hbase/client/ZKAsyncRegistry.close:()V
     119: goto          137
     122: astore        6
     124: aload_3
     125: aload         6
     127: invokevirtual #64                 // Method java/lang/Throwable.addSuppressed:(Ljava/lang/Throwable;)V
     130: goto          137
     133: aload_2
     134: invokevirtual #62                 // Method org/apache/hadoop/hbase/client/ZKAsyncRegistry.close:()V
     137: aload         5
     139: athrow
     140: return
    Exception table:
       from    to  target type
          33    46    49   Class java/util/concurrent/ExecutionException
          72    76    79   Class java/lang/Throwable
          33    64    97   Class java/lang/Throwable
          33    64   105   any
         115   119   122   Class java/lang/Throwable
          97   107   105   any

  static {};
    Code:
       0: ldc           #85                 // class org/apache/hadoop/hbase/client/TestZKAsyncRegistry
       2: invokestatic  #86                 // Method org/apache/hadoop/hbase/HBaseClassTestRule.forClass:(Ljava/lang/Class;)Lorg/apache/hadoop/hbase/HBaseClassTestRule;
       5: putstatic     #87                 // Field CLASS_RULE:Lorg/apache/hadoop/hbase/HBaseClassTestRule;
       8: ldc           #85                 // class org/apache/hadoop/hbase/client/TestZKAsyncRegistry
      10: invokestatic  #88                 // Method org/slf4j/LoggerFactory.getLogger:(Ljava/lang/Class;)Lorg/slf4j/Logger;
      13: putstatic     #15                 // Field LOG:Lorg/slf4j/Logger;
      16: new           #89                 // class org/apache/hadoop/hbase/HBaseTestingUtility
      19: dup
      20: invokespecial #90                 // Method org/apache/hadoop/hbase/HBaseTestingUtility."<init>":()V
      23: putstatic     #3                  // Field TEST_UTIL:Lorg/apache/hadoop/hbase/HBaseTestingUtility;
      26: return
}
