Compiled from "TestZooKeeper.java"
public class org.apache.hadoop.hbase.TestZooKeeper {
  public static final org.apache.hadoop.hbase.HBaseClassTestRule CLASS_RULE;

  public org.junit.rules.TestName name;

  public org.apache.hadoop.hbase.TestZooKeeper();
    Code:
       0: aload_0
       1: invokespecial #1                  // Method java/lang/Object."<init>":()V
       4: aload_0
       5: new           #2                  // class org/junit/rules/TestName
       8: dup
       9: invokespecial #3                  // Method org/junit/rules/TestName."<init>":()V
      12: putfield      #4                  // Field name:Lorg/junit/rules/TestName;
      15: return

  public static void setUpBeforeClass() throws java.lang.Exception;
    Code:
       0: getstatic     #5                  // Field TEST_UTIL:Lorg/apache/hadoop/hbase/HBaseTestingUtility;
       3: invokevirtual #6                  // Method org/apache/hadoop/hbase/HBaseTestingUtility.getConfiguration:()Lorg/apache/hadoop/conf/Configuration;
       6: astore_0
       7: getstatic     #5                  // Field TEST_UTIL:Lorg/apache/hadoop/hbase/HBaseTestingUtility;
      10: iconst_2
      11: invokevirtual #7                  // Method org/apache/hadoop/hbase/HBaseTestingUtility.startMiniDFSCluster:(I)Lorg/apache/hadoop/hdfs/MiniDFSCluster;
      14: pop
      15: getstatic     #5                  // Field TEST_UTIL:Lorg/apache/hadoop/hbase/HBaseTestingUtility;
      18: invokevirtual #8                  // Method org/apache/hadoop/hbase/HBaseTestingUtility.startMiniZKCluster:()Lorg/apache/hadoop/hbase/zookeeper/MiniZooKeeperCluster;
      21: pop
      22: aload_0
      23: ldc           #10                 // String zookeeper.session.timeout
      25: sipush        1000
      28: invokevirtual #11                 // Method org/apache/hadoop/conf/Configuration.setInt:(Ljava/lang/String;I)V
      31: aload_0
      32: ldc           #12                 // String hbase.master.loadbalancer.class
      34: ldc           #13                 // class org/apache/hadoop/hbase/TestZooKeeper$MockLoadBalancer
      36: ldc           #14                 // class org/apache/hadoop/hbase/master/LoadBalancer
      38: invokevirtual #15                 // Method org/apache/hadoop/conf/Configuration.setClass:(Ljava/lang/String;Ljava/lang/Class;Ljava/lang/Class;)V
      41: return

  public static void tearDownAfterClass() throws java.lang.Exception;
    Code:
       0: getstatic     #5                  // Field TEST_UTIL:Lorg/apache/hadoop/hbase/HBaseTestingUtility;
       3: invokevirtual #16                 // Method org/apache/hadoop/hbase/HBaseTestingUtility.shutdownMiniCluster:()V
       6: return

  public void setUp() throws java.lang.Exception;
    Code:
       0: invokestatic  #17                 // Method org/apache/hadoop/hbase/StartMiniClusterOption.builder:()Lorg/apache/hadoop/hbase/StartMiniClusterOption$Builder;
       3: iconst_2
       4: invokevirtual #18                 // Method org/apache/hadoop/hbase/StartMiniClusterOption$Builder.numMasters:(I)Lorg/apache/hadoop/hbase/StartMiniClusterOption$Builder;
       7: iconst_2
       8: invokevirtual #19                 // Method org/apache/hadoop/hbase/StartMiniClusterOption$Builder.numRegionServers:(I)Lorg/apache/hadoop/hbase/StartMiniClusterOption$Builder;
      11: invokevirtual #20                 // Method org/apache/hadoop/hbase/StartMiniClusterOption$Builder.build:()Lorg/apache/hadoop/hbase/StartMiniClusterOption;
      14: astore_1
      15: getstatic     #5                  // Field TEST_UTIL:Lorg/apache/hadoop/hbase/HBaseTestingUtility;
      18: aload_1
      19: invokevirtual #21                 // Method org/apache/hadoop/hbase/HBaseTestingUtility.startMiniHBaseCluster:(Lorg/apache/hadoop/hbase/StartMiniClusterOption;)Lorg/apache/hadoop/hbase/MiniHBaseCluster;
      22: pop
      23: return

  public void after() throws java.lang.Exception;
    Code:
       0: getstatic     #5                  // Field TEST_UTIL:Lorg/apache/hadoop/hbase/HBaseTestingUtility;
       3: invokevirtual #22                 // Method org/apache/hadoop/hbase/HBaseTestingUtility.getHBaseCluster:()Lorg/apache/hadoop/hbase/MiniHBaseCluster;
       6: ldc2_w        #23                 // long 10000l
       9: invokevirtual #25                 // Method org/apache/hadoop/hbase/MiniHBaseCluster.waitForActiveAndReadyMaster:(J)Z
      12: pop
      13: getstatic     #5                  // Field TEST_UTIL:Lorg/apache/hadoop/hbase/HBaseTestingUtility;
      16: invokevirtual #22                 // Method org/apache/hadoop/hbase/HBaseTestingUtility.getHBaseCluster:()Lorg/apache/hadoop/hbase/MiniHBaseCluster;
      19: invokevirtual #26                 // Method org/apache/hadoop/hbase/MiniHBaseCluster.killAll:()V
      22: getstatic     #5                  // Field TEST_UTIL:Lorg/apache/hadoop/hbase/HBaseTestingUtility;
      25: invokevirtual #27                 // Method org/apache/hadoop/hbase/HBaseTestingUtility.shutdownMiniHBaseCluster:()V
      28: getstatic     #5                  // Field TEST_UTIL:Lorg/apache/hadoop/hbase/HBaseTestingUtility;
      31: invokevirtual #28                 // Method org/apache/hadoop/hbase/HBaseTestingUtility.getTestFileSystem:()Lorg/apache/hadoop/fs/FileSystem;
      34: getstatic     #5                  // Field TEST_UTIL:Lorg/apache/hadoop/hbase/HBaseTestingUtility;
      37: invokevirtual #6                  // Method org/apache/hadoop/hbase/HBaseTestingUtility.getConfiguration:()Lorg/apache/hadoop/conf/Configuration;
      40: invokestatic  #29                 // Method org/apache/hadoop/hbase/util/FSUtils.getRootDir:(Lorg/apache/hadoop/conf/Configuration;)Lorg/apache/hadoop/fs/Path;
      43: iconst_1
      44: invokevirtual #30                 // Method org/apache/hadoop/fs/FileSystem.delete:(Lorg/apache/hadoop/fs/Path;Z)Z
      47: pop
      48: getstatic     #5                  // Field TEST_UTIL:Lorg/apache/hadoop/hbase/HBaseTestingUtility;
      51: invokevirtual #31                 // Method org/apache/hadoop/hbase/HBaseTestingUtility.getZooKeeperWatcher:()Lorg/apache/hadoop/hbase/zookeeper/ZKWatcher;
      54: ldc           #32                 // String /hbase
      56: invokestatic  #33                 // Method org/apache/hadoop/hbase/zookeeper/ZKUtil.deleteNodeRecursively:(Lorg/apache/hadoop/hbase/zookeeper/ZKWatcher;Ljava/lang/String;)V
      59: goto          96
      62: astore_1
      63: getstatic     #5                  // Field TEST_UTIL:Lorg/apache/hadoop/hbase/HBaseTestingUtility;
      66: invokevirtual #28                 // Method org/apache/hadoop/hbase/HBaseTestingUtility.getTestFileSystem:()Lorg/apache/hadoop/fs/FileSystem;
      69: getstatic     #5                  // Field TEST_UTIL:Lorg/apache/hadoop/hbase/HBaseTestingUtility;
      72: invokevirtual #6                  // Method org/apache/hadoop/hbase/HBaseTestingUtility.getConfiguration:()Lorg/apache/hadoop/conf/Configuration;
      75: invokestatic  #29                 // Method org/apache/hadoop/hbase/util/FSUtils.getRootDir:(Lorg/apache/hadoop/conf/Configuration;)Lorg/apache/hadoop/fs/Path;
      78: iconst_1
      79: invokevirtual #30                 // Method org/apache/hadoop/fs/FileSystem.delete:(Lorg/apache/hadoop/fs/Path;Z)Z
      82: pop
      83: getstatic     #5                  // Field TEST_UTIL:Lorg/apache/hadoop/hbase/HBaseTestingUtility;
      86: invokevirtual #31                 // Method org/apache/hadoop/hbase/HBaseTestingUtility.getZooKeeperWatcher:()Lorg/apache/hadoop/hbase/zookeeper/ZKWatcher;
      89: ldc           #32                 // String /hbase
      91: invokestatic  #33                 // Method org/apache/hadoop/hbase/zookeeper/ZKUtil.deleteNodeRecursively:(Lorg/apache/hadoop/hbase/zookeeper/ZKWatcher;Ljava/lang/String;)V
      94: aload_1
      95: athrow
      96: return
    Exception table:
       from    to  target type
           0    28    62   any

  public void testRegionServerSessionExpired() throws java.lang.Exception;
    Code:
       0: getstatic     #34                 // Field LOG:Lorg/slf4j/Logger;
       3: new           #35                 // class java/lang/StringBuilder
       6: dup
       7: invokespecial #36                 // Method java/lang/StringBuilder."<init>":()V
      10: ldc           #37                 // String Starting
      12: invokevirtual #38                 // Method java/lang/StringBuilder.append:(Ljava/lang/String;)Ljava/lang/StringBuilder;
      15: aload_0
      16: getfield      #4                  // Field name:Lorg/junit/rules/TestName;
      19: invokevirtual #39                 // Method org/junit/rules/TestName.getMethodName:()Ljava/lang/String;
      22: invokevirtual #38                 // Method java/lang/StringBuilder.append:(Ljava/lang/String;)Ljava/lang/StringBuilder;
      25: invokevirtual #40                 // Method java/lang/StringBuilder.toString:()Ljava/lang/String;
      28: invokeinterface #41,  2           // InterfaceMethod org/slf4j/Logger.info:(Ljava/lang/String;)V
      33: getstatic     #5                  // Field TEST_UTIL:Lorg/apache/hadoop/hbase/HBaseTestingUtility;
      36: iconst_0
      37: invokevirtual #42                 // Method org/apache/hadoop/hbase/HBaseTestingUtility.expireRegionServerSession:(I)V
      40: aload_0
      41: aload_0
      42: getfield      #4                  // Field name:Lorg/junit/rules/TestName;
      45: invokevirtual #39                 // Method org/junit/rules/TestName.getMethodName:()Ljava/lang/String;
      48: invokespecial #43                 // Method testSanity:(Ljava/lang/String;)V
      51: return

  public void testMasterSessionExpired() throws java.lang.Exception;
    Code:
       0: getstatic     #34                 // Field LOG:Lorg/slf4j/Logger;
       3: new           #35                 // class java/lang/StringBuilder
       6: dup
       7: invokespecial #36                 // Method java/lang/StringBuilder."<init>":()V
      10: ldc           #37                 // String Starting
      12: invokevirtual #38                 // Method java/lang/StringBuilder.append:(Ljava/lang/String;)Ljava/lang/StringBuilder;
      15: aload_0
      16: getfield      #4                  // Field name:Lorg/junit/rules/TestName;
      19: invokevirtual #39                 // Method org/junit/rules/TestName.getMethodName:()Ljava/lang/String;
      22: invokevirtual #38                 // Method java/lang/StringBuilder.append:(Ljava/lang/String;)Ljava/lang/StringBuilder;
      25: invokevirtual #40                 // Method java/lang/StringBuilder.toString:()Ljava/lang/String;
      28: invokeinterface #41,  2           // InterfaceMethod org/slf4j/Logger.info:(Ljava/lang/String;)V
      33: getstatic     #5                  // Field TEST_UTIL:Lorg/apache/hadoop/hbase/HBaseTestingUtility;
      36: invokevirtual #44                 // Method org/apache/hadoop/hbase/HBaseTestingUtility.expireMasterSession:()V
      39: aload_0
      40: aload_0
      41: getfield      #4                  // Field name:Lorg/junit/rules/TestName;
      44: invokevirtual #39                 // Method org/junit/rules/TestName.getMethodName:()Ljava/lang/String;
      47: invokespecial #43                 // Method testSanity:(Ljava/lang/String;)V
      50: return

  public void testMasterZKSessionRecoveryFailure() throws java.lang.Exception;
    Code:
       0: getstatic     #34                 // Field LOG:Lorg/slf4j/Logger;
       3: new           #35                 // class java/lang/StringBuilder
       6: dup
       7: invokespecial #36                 // Method java/lang/StringBuilder."<init>":()V
      10: ldc           #37                 // String Starting
      12: invokevirtual #38                 // Method java/lang/StringBuilder.append:(Ljava/lang/String;)Ljava/lang/StringBuilder;
      15: aload_0
      16: getfield      #4                  // Field name:Lorg/junit/rules/TestName;
      19: invokevirtual #39                 // Method org/junit/rules/TestName.getMethodName:()Ljava/lang/String;
      22: invokevirtual #38                 // Method java/lang/StringBuilder.append:(Ljava/lang/String;)Ljava/lang/StringBuilder;
      25: invokevirtual #40                 // Method java/lang/StringBuilder.toString:()Ljava/lang/String;
      28: invokeinterface #41,  2           // InterfaceMethod org/slf4j/Logger.info:(Ljava/lang/String;)V
      33: getstatic     #5                  // Field TEST_UTIL:Lorg/apache/hadoop/hbase/HBaseTestingUtility;
      36: invokevirtual #22                 // Method org/apache/hadoop/hbase/HBaseTestingUtility.getHBaseCluster:()Lorg/apache/hadoop/hbase/MiniHBaseCluster;
      39: astore_1
      40: aload_1
      41: invokevirtual #45                 // Method org/apache/hadoop/hbase/MiniHBaseCluster.getMaster:()Lorg/apache/hadoop/hbase/master/HMaster;
      44: astore_2
      45: aload_2
      46: ldc           #46                 // String Test recovery from zk session expired
      48: new           #47                 // class org/apache/zookeeper/KeeperException$SessionExpiredException
      51: dup
      52: invokespecial #48                 // Method org/apache/zookeeper/KeeperException$SessionExpiredException."<init>":()V
      55: invokevirtual #49                 // Method org/apache/hadoop/hbase/master/HMaster.abort:(Ljava/lang/String;Ljava/lang/Throwable;)V
      58: aload_2
      59: invokevirtual #50                 // Method org/apache/hadoop/hbase/master/HMaster.isStopped:()Z
      62: invokestatic  #51                 // Method org/junit/Assert.assertTrue:(Z)V
      65: aload_0
      66: aload_0
      67: getfield      #4                  // Field name:Lorg/junit/rules/TestName;
      70: invokevirtual #39                 // Method org/junit/rules/TestName.getMethodName:()Ljava/lang/String;
      73: invokespecial #43                 // Method testSanity:(Ljava/lang/String;)V
      76: return

  public void testRegionAssignmentAfterMasterRecoveryDueToZKExpiry() throws java.lang.Exception;
    Code:
       0: getstatic     #5                  // Field TEST_UTIL:Lorg/apache/hadoop/hbase/HBaseTestingUtility;
       3: invokevirtual #22                 // Method org/apache/hadoop/hbase/HBaseTestingUtility.getHBaseCluster:()Lorg/apache/hadoop/hbase/MiniHBaseCluster;
       6: astore_1
       7: aload_1
       8: invokevirtual #78                 // Method org/apache/hadoop/hbase/MiniHBaseCluster.startRegionServer:()Lorg/apache/hadoop/hbase/util/JVMClusterUtil$RegionServerThread;
      11: pop
      12: aload_1
      13: ldc2_w        #23                 // long 10000l
      16: invokevirtual #25                 // Method org/apache/hadoop/hbase/MiniHBaseCluster.waitForActiveAndReadyMaster:(J)Z
      19: pop
      20: aload_1
      21: invokevirtual #45                 // Method org/apache/hadoop/hbase/MiniHBaseCluster.getMaster:()Lorg/apache/hadoop/hbase/master/HMaster;
      24: astore_2
      25: aload_2
      26: invokevirtual #79                 // Method org/apache/hadoop/hbase/master/HMaster.getZooKeeper:()Lorg/apache/hadoop/hbase/zookeeper/ZKWatcher;
      29: astore_3
      30: getstatic     #5                  // Field TEST_UTIL:Lorg/apache/hadoop/hbase/HBaseTestingUtility;
      33: invokevirtual #62                 // Method org/apache/hadoop/hbase/HBaseTestingUtility.getAdmin:()Lorg/apache/hadoop/hbase/client/Admin;
      36: astore        4
      38: aconst_null
      39: astore        5
      41: bipush        10
      43: anewarray     #80                 // class "[B"
      46: dup
      47: iconst_0
      48: ldc           #81                 // String a
      50: invokestatic  #70                 // Method org/apache/hadoop/hbase/util/Bytes.toBytes:(Ljava/lang/String;)[B
      53: aastore
      54: dup
      55: iconst_1
      56: ldc           #82                 // String b
      58: invokestatic  #70                 // Method org/apache/hadoop/hbase/util/Bytes.toBytes:(Ljava/lang/String;)[B
      61: aastore
      62: dup
      63: iconst_2
      64: ldc           #83                 // String c
      66: invokestatic  #70                 // Method org/apache/hadoop/hbase/util/Bytes.toBytes:(Ljava/lang/String;)[B
      69: aastore
      70: dup
      71: iconst_3
      72: ldc           #84                 // String d
      74: invokestatic  #70                 // Method org/apache/hadoop/hbase/util/Bytes.toBytes:(Ljava/lang/String;)[B
      77: aastore
      78: dup
      79: iconst_4
      80: ldc           #85                 // String e
      82: invokestatic  #70                 // Method org/apache/hadoop/hbase/util/Bytes.toBytes:(Ljava/lang/String;)[B
      85: aastore
      86: dup
      87: iconst_5
      88: ldc           #86                 // String f
      90: invokestatic  #70                 // Method org/apache/hadoop/hbase/util/Bytes.toBytes:(Ljava/lang/String;)[B
      93: aastore
      94: dup
      95: bipush        6
      97: ldc           #87                 // String g
      99: invokestatic  #70                 // Method org/apache/hadoop/hbase/util/Bytes.toBytes:(Ljava/lang/String;)[B
     102: aastore
     103: dup
     104: bipush        7
     106: ldc           #88                 // String h
     108: invokestatic  #70                 // Method org/apache/hadoop/hbase/util/Bytes.toBytes:(Ljava/lang/String;)[B
     111: aastore
     112: dup
     113: bipush        8
     115: ldc           #89                 // String i
     117: invokestatic  #70                 // Method org/apache/hadoop/hbase/util/Bytes.toBytes:(Ljava/lang/String;)[B
     120: aastore
     121: dup
     122: bipush        9
     124: ldc           #90                 // String j
     126: invokestatic  #70                 // Method org/apache/hadoop/hbase/util/Bytes.toBytes:(Ljava/lang/String;)[B
     129: aastore
     130: astore        6
     132: aload_0
     133: getfield      #4                  // Field name:Lorg/junit/rules/TestName;
     136: invokevirtual #39                 // Method org/junit/rules/TestName.getMethodName:()Ljava/lang/String;
     139: invokestatic  #55                 // Method org/apache/hadoop/hbase/TableName.valueOf:(Ljava/lang/String;)Lorg/apache/hadoop/hbase/TableName;
     142: invokestatic  #56                 // Method org/apache/hadoop/hbase/client/TableDescriptorBuilder.newBuilder:(Lorg/apache/hadoop/hbase/TableName;)Lorg/apache/hadoop/hbase/client/TableDescriptorBuilder;
     145: getstatic     #91                 // Field org/apache/hadoop/hbase/HConstants.CATALOG_FAMILY:[B
     148: invokestatic  #92                 // Method org/apache/hadoop/hbase/client/ColumnFamilyDescriptorBuilder.of:([B)Lorg/apache/hadoop/hbase/client/ColumnFamilyDescriptor;
     151: invokevirtual #59                 // Method org/apache/hadoop/hbase/client/TableDescriptorBuilder.setColumnFamily:(Lorg/apache/hadoop/hbase/client/ColumnFamilyDescriptor;)Lorg/apache/hadoop/hbase/client/TableDescriptorBuilder;
     154: invokevirtual #60                 // Method org/apache/hadoop/hbase/client/TableDescriptorBuilder.build:()Lorg/apache/hadoop/hbase/client/TableDescriptor;
     157: astore        7
     159: aload         4
     161: aload         7
     163: aload         6
     165: invokeinterface #93,  3           // InterfaceMethod org/apache/hadoop/hbase/client/Admin.createTable:(Lorg/apache/hadoop/hbase/client/TableDescriptor;[[B)V
     170: getstatic     #5                  // Field TEST_UTIL:Lorg/apache/hadoop/hbase/HBaseTestingUtility;
     173: ldc2_w        #94                 // long 60000l
     176: invokevirtual #96                 // Method org/apache/hadoop/hbase/HBaseTestingUtility.waitUntilNoRegionsInTransition:(J)V
     179: aload_2
     180: invokevirtual #79                 // Method org/apache/hadoop/hbase/master/HMaster.getZooKeeper:()Lorg/apache/hadoop/hbase/zookeeper/ZKWatcher;
     183: invokevirtual #97                 // Method org/apache/hadoop/hbase/zookeeper/ZKWatcher.close:()V
     186: iconst_0
     187: putstatic     #98                 // Field org/apache/hadoop/hbase/TestZooKeeper$MockLoadBalancer.retainAssignCalled:Z
     190: aload_0
     191: aload_3
     192: invokespecial #99                 // Method countPermanentListeners:(Lorg/apache/hadoop/hbase/zookeeper/ZKWatcher;)I
     195: istore        8
     197: aload_2
     198: ldc           #46                 // String Test recovery from zk session expired
     200: new           #47                 // class org/apache/zookeeper/KeeperException$SessionExpiredException
     203: dup
     204: invokespecial #48                 // Method org/apache/zookeeper/KeeperException$SessionExpiredException."<init>":()V
     207: invokevirtual #49                 // Method org/apache/hadoop/hbase/master/HMaster.abort:(Ljava/lang/String;Ljava/lang/Throwable;)V
     210: aload_2
     211: invokevirtual #50                 // Method org/apache/hadoop/hbase/master/HMaster.isStopped:()Z
     214: invokestatic  #51                 // Method org/junit/Assert.assertTrue:(Z)V
     217: ldc           #100                // String Retain assignment should not be called
     219: getstatic     #98                 // Field org/apache/hadoop/hbase/TestZooKeeper$MockLoadBalancer.retainAssignCalled:Z
     222: invokestatic  #101                // Method org/junit/Assert.assertFalse:(Ljava/lang/String;Z)V
     225: aload_1
     226: ldc2_w        #102                // long 120000l
     229: invokevirtual #25                 // Method org/apache/hadoop/hbase/MiniHBaseCluster.waitForActiveAndReadyMaster:(J)Z
     232: pop
     233: aload_1
     234: invokevirtual #104                // Method org/apache/hadoop/hbase/MiniHBaseCluster.getMasterThread:()Lorg/apache/hadoop/hbase/util/JVMClusterUtil$MasterThread;
     237: invokevirtual #105                // Method org/apache/hadoop/hbase/util/JVMClusterUtil$MasterThread.getMaster:()Lorg/apache/hadoop/hbase/master/HMaster;
     240: astore        9
     242: iload         8
     244: i2l
     245: aload_0
     246: aload         9
     248: invokevirtual #79                 // Method org/apache/hadoop/hbase/master/HMaster.getZooKeeper:()Lorg/apache/hadoop/hbase/zookeeper/ZKWatcher;
     251: invokespecial #99                 // Method countPermanentListeners:(Lorg/apache/hadoop/hbase/zookeeper/ZKWatcher;)I
     254: i2l
     255: invokestatic  #106                // Method org/junit/Assert.assertEquals:(JJ)V
     258: aload         4
     260: ifnull        353
     263: aload         5
     265: ifnull        290
     268: aload         4
     270: invokeinterface #64,  1           // InterfaceMethod org/apache/hadoop/hbase/client/Admin.close:()V
     275: goto          353
     278: astore        6
     280: aload         5
     282: aload         6
     284: invokevirtual #108                // Method java/lang/Throwable.addSuppressed:(Ljava/lang/Throwable;)V
     287: goto          353
     290: aload         4
     292: invokeinterface #64,  1           // InterfaceMethod org/apache/hadoop/hbase/client/Admin.close:()V
     297: goto          353
     300: astore        6
     302: aload         6
     304: astore        5
     306: aload         6
     308: athrow
     309: astore        10
     311: aload         4
     313: ifnull        350
     316: aload         5
     318: ifnull        343
     321: aload         4
     323: invokeinterface #64,  1           // InterfaceMethod org/apache/hadoop/hbase/client/Admin.close:()V
     328: goto          350
     331: astore        11
     333: aload         5
     335: aload         11
     337: invokevirtual #108                // Method java/lang/Throwable.addSuppressed:(Ljava/lang/Throwable;)V
     340: goto          350
     343: aload         4
     345: invokeinterface #64,  1           // InterfaceMethod org/apache/hadoop/hbase/client/Admin.close:()V
     350: aload         10
     352: athrow
     353: return
    Exception table:
       from    to  target type
         268   275   278   Class java/lang/Throwable
          41   258   300   Class java/lang/Throwable
          41   258   309   any
         321   328   331   Class java/lang/Throwable
         300   311   309   any

  public void testLogSplittingAfterMasterRecoveryDueToZKExpiry() throws java.lang.Exception;
    Code:
       0: getstatic     #5                  // Field TEST_UTIL:Lorg/apache/hadoop/hbase/HBaseTestingUtility;
       3: invokevirtual #22                 // Method org/apache/hadoop/hbase/HBaseTestingUtility.getHBaseCluster:()Lorg/apache/hadoop/hbase/MiniHBaseCluster;
       6: astore_1
       7: aload_1
       8: invokevirtual #78                 // Method org/apache/hadoop/hbase/MiniHBaseCluster.startRegionServer:()Lorg/apache/hadoop/hbase/util/JVMClusterUtil$RegionServerThread;
      11: pop
      12: aload_0
      13: getfield      #4                  // Field name:Lorg/junit/rules/TestName;
      16: invokevirtual #39                 // Method org/junit/rules/TestName.getMethodName:()Ljava/lang/String;
      19: invokestatic  #55                 // Method org/apache/hadoop/hbase/TableName.valueOf:(Ljava/lang/String;)Lorg/apache/hadoop/hbase/TableName;
      22: astore_2
      23: ldc           #72                 // String col
      25: invokestatic  #70                 // Method org/apache/hadoop/hbase/util/Bytes.toBytes:(Ljava/lang/String;)[B
      28: astore_3
      29: getstatic     #5                  // Field TEST_UTIL:Lorg/apache/hadoop/hbase/HBaseTestingUtility;
      32: invokevirtual #62                 // Method org/apache/hadoop/hbase/HBaseTestingUtility.getAdmin:()Lorg/apache/hadoop/hbase/client/Admin;
      35: astore        4
      37: aconst_null
      38: astore        5
      40: iconst_5
      41: anewarray     #80                 // class "[B"
      44: dup
      45: iconst_0
      46: ldc           #118                // String 1
      48: invokestatic  #70                 // Method org/apache/hadoop/hbase/util/Bytes.toBytes:(Ljava/lang/String;)[B
      51: aastore
      52: dup
      53: iconst_1
      54: ldc           #119                // String 2
      56: invokestatic  #70                 // Method org/apache/hadoop/hbase/util/Bytes.toBytes:(Ljava/lang/String;)[B
      59: aastore
      60: dup
      61: iconst_2
      62: ldc           #120                // String 3
      64: invokestatic  #70                 // Method org/apache/hadoop/hbase/util/Bytes.toBytes:(Ljava/lang/String;)[B
      67: aastore
      68: dup
      69: iconst_3
      70: ldc           #121                // String 4
      72: invokestatic  #70                 // Method org/apache/hadoop/hbase/util/Bytes.toBytes:(Ljava/lang/String;)[B
      75: aastore
      76: dup
      77: iconst_4
      78: ldc           #122                // String 5
      80: invokestatic  #70                 // Method org/apache/hadoop/hbase/util/Bytes.toBytes:(Ljava/lang/String;)[B
      83: aastore
      84: astore        6
      86: aload_2
      87: invokestatic  #56                 // Method org/apache/hadoop/hbase/client/TableDescriptorBuilder.newBuilder:(Lorg/apache/hadoop/hbase/TableName;)Lorg/apache/hadoop/hbase/client/TableDescriptorBuilder;
      90: aload_3
      91: invokestatic  #92                 // Method org/apache/hadoop/hbase/client/ColumnFamilyDescriptorBuilder.of:([B)Lorg/apache/hadoop/hbase/client/ColumnFamilyDescriptor;
      94: invokevirtual #59                 // Method org/apache/hadoop/hbase/client/TableDescriptorBuilder.setColumnFamily:(Lorg/apache/hadoop/hbase/client/ColumnFamilyDescriptor;)Lorg/apache/hadoop/hbase/client/TableDescriptorBuilder;
      97: invokevirtual #60                 // Method org/apache/hadoop/hbase/client/TableDescriptorBuilder.build:()Lorg/apache/hadoop/hbase/client/TableDescriptor;
     100: astore        7
     102: aload         4
     104: aload         7
     106: aload         6
     108: invokeinterface #93,  3           // InterfaceMethod org/apache/hadoop/hbase/client/Admin.createTable:(Lorg/apache/hadoop/hbase/client/TableDescriptor;[[B)V
     113: aload         4
     115: ifnull        208
     118: aload         5
     120: ifnull        145
     123: aload         4
     125: invokeinterface #64,  1           // InterfaceMethod org/apache/hadoop/hbase/client/Admin.close:()V
     130: goto          208
     133: astore        6
     135: aload         5
     137: aload         6
     139: invokevirtual #108                // Method java/lang/Throwable.addSuppressed:(Ljava/lang/Throwable;)V
     142: goto          208
     145: aload         4
     147: invokeinterface #64,  1           // InterfaceMethod org/apache/hadoop/hbase/client/Admin.close:()V
     152: goto          208
     155: astore        6
     157: aload         6
     159: astore        5
     161: aload         6
     163: athrow
     164: astore        8
     166: aload         4
     168: ifnull        205
     171: aload         5
     173: ifnull        198
     176: aload         4
     178: invokeinterface #64,  1           // InterfaceMethod org/apache/hadoop/hbase/client/Admin.close:()V
     183: goto          205
     186: astore        9
     188: aload         5
     190: aload         9
     192: invokevirtual #108                // Method java/lang/Throwable.addSuppressed:(Ljava/lang/Throwable;)V
     195: goto          205
     198: aload         4
     200: invokeinterface #64,  1           // InterfaceMethod org/apache/hadoop/hbase/client/Admin.close:()V
     205: aload         8
     207: athrow
     208: getstatic     #5                  // Field TEST_UTIL:Lorg/apache/hadoop/hbase/HBaseTestingUtility;
     211: ldc2_w        #94                 // long 60000l
     214: invokevirtual #96                 // Method org/apache/hadoop/hbase/HBaseTestingUtility.waitUntilNoRegionsInTransition:(J)V
     217: aload_1
     218: invokevirtual #45                 // Method org/apache/hadoop/hbase/MiniHBaseCluster.getMaster:()Lorg/apache/hadoop/hbase/master/HMaster;
     221: astore        4
     223: getstatic     #5                  // Field TEST_UTIL:Lorg/apache/hadoop/hbase/HBaseTestingUtility;
     226: invokevirtual #65                 // Method org/apache/hadoop/hbase/HBaseTestingUtility.getConnection:()Lorg/apache/hadoop/hbase/client/Connection;
     229: aload_2
     230: invokeinterface #67,  2           // InterfaceMethod org/apache/hadoop/hbase/client/Connection.getTable:(Lorg/apache/hadoop/hbase/TableName;)Lorg/apache/hadoop/hbase/client/Table;
     235: astore        5
     237: aconst_null
     238: astore        6
     240: iconst_0
     241: istore        7
     243: iload         7
     245: bipush        6
     247: if_icmpge     318
     250: new           #68                 // class org/apache/hadoop/hbase/client/Put
     253: dup
     254: iload         7
     256: invokestatic  #123                // Method org/apache/hadoop/hbase/util/Bytes.toBytes:(I)[B
     259: invokespecial #71                 // Method org/apache/hadoop/hbase/client/Put."<init>":([B)V
     262: astore        8
     264: aload         8
     266: ldc           #72                 // String col
     268: invokestatic  #70                 // Method org/apache/hadoop/hbase/util/Bytes.toBytes:(Ljava/lang/String;)[B
     271: ldc           #124                // String ql
     273: invokestatic  #70                 // Method org/apache/hadoop/hbase/util/Bytes.toBytes:(Ljava/lang/String;)[B
     276: new           #35                 // class java/lang/StringBuilder
     279: dup
     280: invokespecial #36                 // Method java/lang/StringBuilder."<init>":()V
     283: ldc           #125                // String value
     285: invokevirtual #38                 // Method java/lang/StringBuilder.append:(Ljava/lang/String;)Ljava/lang/StringBuilder;
     288: iload         7
     290: invokevirtual #126                // Method java/lang/StringBuilder.append:(I)Ljava/lang/StringBuilder;
     293: invokevirtual #40                 // Method java/lang/StringBuilder.toString:()Ljava/lang/String;
     296: invokestatic  #70                 // Method org/apache/hadoop/hbase/util/Bytes.toBytes:(Ljava/lang/String;)[B
     299: invokevirtual #74                 // Method org/apache/hadoop/hbase/client/Put.addColumn:([B[B[B)Lorg/apache/hadoop/hbase/client/Put;
     302: pop
     303: aload         5
     305: aload         8
     307: invokeinterface #76,  2           // InterfaceMethod org/apache/hadoop/hbase/client/Table.put:(Lorg/apache/hadoop/hbase/client/Put;)V
     312: iinc          7, 1
     315: goto          243
     318: aload         4
     320: ldc           #46                 // String Test recovery from zk session expired
     322: new           #47                 // class org/apache/zookeeper/KeeperException$SessionExpiredException
     325: dup
     326: invokespecial #48                 // Method org/apache/zookeeper/KeeperException$SessionExpiredException."<init>":()V
     329: invokevirtual #49                 // Method org/apache/hadoop/hbase/master/HMaster.abort:(Ljava/lang/String;Ljava/lang/Throwable;)V
     332: aload         4
     334: invokevirtual #50                 // Method org/apache/hadoop/hbase/master/HMaster.isStopped:()Z
     337: invokestatic  #51                 // Method org/junit/Assert.assertTrue:(Z)V
     340: aload_1
     341: getstatic     #5                  // Field TEST_UTIL:Lorg/apache/hadoop/hbase/HBaseTestingUtility;
     344: aload_2
     345: invokevirtual #127                // Method org/apache/hadoop/hbase/HBaseTestingUtility.getRSForFirstRegionInTable:(Lorg/apache/hadoop/hbase/TableName;)Lorg/apache/hadoop/hbase/regionserver/HRegionServer;
     348: invokevirtual #128                // Method org/apache/hadoop/hbase/regionserver/HRegionServer.getServerName:()Lorg/apache/hadoop/hbase/ServerName;
     351: invokevirtual #129                // Method org/apache/hadoop/hbase/MiniHBaseCluster.killRegionServer:(Lorg/apache/hadoop/hbase/ServerName;)V
     354: iconst_0
     355: istore        8
     357: aload         5
     359: new           #130                // class org/apache/hadoop/hbase/client/Scan
     362: dup
     363: invokespecial #131                // Method org/apache/hadoop/hbase/client/Scan."<init>":()V
     366: invokeinterface #132,  2          // InterfaceMethod org/apache/hadoop/hbase/client/Table.getScanner:(Lorg/apache/hadoop/hbase/client/Scan;)Lorg/apache/hadoop/hbase/client/ResultScanner;
     371: astore        9
     373: aconst_null
     374: astore        10
     376: aload         9
     378: invokeinterface #133,  1          // InterfaceMethod org/apache/hadoop/hbase/client/ResultScanner.next:()Lorg/apache/hadoop/hbase/client/Result;
     383: ifnull        392
     386: iinc          8, 1
     389: goto          376
     392: aload         9
     394: ifnull        487
     397: aload         10
     399: ifnull        424
     402: aload         9
     404: invokeinterface #134,  1          // InterfaceMethod org/apache/hadoop/hbase/client/ResultScanner.close:()V
     409: goto          487
     412: astore        11
     414: aload         10
     416: aload         11
     418: invokevirtual #108                // Method java/lang/Throwable.addSuppressed:(Ljava/lang/Throwable;)V
     421: goto          487
     424: aload         9
     426: invokeinterface #134,  1          // InterfaceMethod org/apache/hadoop/hbase/client/ResultScanner.close:()V
     431: goto          487
     434: astore        11
     436: aload         11
     438: astore        10
     440: aload         11
     442: athrow
     443: astore        12
     445: aload         9
     447: ifnull        484
     450: aload         10
     452: ifnull        477
     455: aload         9
     457: invokeinterface #134,  1          // InterfaceMethod org/apache/hadoop/hbase/client/ResultScanner.close:()V
     462: goto          484
     465: astore        13
     467: aload         10
     469: aload         13
     471: invokevirtual #108                // Method java/lang/Throwable.addSuppressed:(Ljava/lang/Throwable;)V
     474: goto          484
     477: aload         9
     479: invokeinterface #134,  1          // InterfaceMethod org/apache/hadoop/hbase/client/ResultScanner.close:()V
     484: aload         12
     486: athrow
     487: ldc           #135                // String Number of rows should be equal to number of puts.
     489: iload         7
     491: i2l
     492: iload         8
     494: i2l
     495: invokestatic  #136                // Method org/junit/Assert.assertEquals:(Ljava/lang/String;JJ)V
     498: aload         5
     500: ifnull        593
     503: aload         6
     505: ifnull        530
     508: aload         5
     510: invokeinterface #77,  1           // InterfaceMethod org/apache/hadoop/hbase/client/Table.close:()V
     515: goto          593
     518: astore        7
     520: aload         6
     522: aload         7
     524: invokevirtual #108                // Method java/lang/Throwable.addSuppressed:(Ljava/lang/Throwable;)V
     527: goto          593
     530: aload         5
     532: invokeinterface #77,  1           // InterfaceMethod org/apache/hadoop/hbase/client/Table.close:()V
     537: goto          593
     540: astore        7
     542: aload         7
     544: astore        6
     546: aload         7
     548: athrow
     549: astore        14
     551: aload         5
     553: ifnull        590
     556: aload         6
     558: ifnull        583
     561: aload         5
     563: invokeinterface #77,  1           // InterfaceMethod org/apache/hadoop/hbase/client/Table.close:()V
     568: goto          590
     571: astore        15
     573: aload         6
     575: aload         15
     577: invokevirtual #108                // Method java/lang/Throwable.addSuppressed:(Ljava/lang/Throwable;)V
     580: goto          590
     583: aload         5
     585: invokeinterface #77,  1           // InterfaceMethod org/apache/hadoop/hbase/client/Table.close:()V
     590: aload         14
     592: athrow
     593: return
    Exception table:
       from    to  target type
         123   130   133   Class java/lang/Throwable
          40   113   155   Class java/lang/Throwable
          40   113   164   any
         176   183   186   Class java/lang/Throwable
         155   166   164   any
         402   409   412   Class java/lang/Throwable
         376   392   434   Class java/lang/Throwable
         376   392   443   any
         455   462   465   Class java/lang/Throwable
         434   445   443   any
         508   515   518   Class java/lang/Throwable
         240   498   540   Class java/lang/Throwable
         240   498   549   any
         561   568   571   Class java/lang/Throwable
         540   551   549   any

  static {};
    Code:
       0: ldc           #137                // class org/apache/hadoop/hbase/TestZooKeeper
       2: invokestatic  #138                // Method org/apache/hadoop/hbase/HBaseClassTestRule.forClass:(Ljava/lang/Class;)Lorg/apache/hadoop/hbase/HBaseClassTestRule;
       5: putstatic     #139                // Field CLASS_RULE:Lorg/apache/hadoop/hbase/HBaseClassTestRule;
       8: ldc           #137                // class org/apache/hadoop/hbase/TestZooKeeper
      10: invokestatic  #140                // Method org/slf4j/LoggerFactory.getLogger:(Ljava/lang/Class;)Lorg/slf4j/Logger;
      13: putstatic     #34                 // Field LOG:Lorg/slf4j/Logger;
      16: new           #141                // class org/apache/hadoop/hbase/HBaseTestingUtility
      19: dup
      20: invokespecial #142                // Method org/apache/hadoop/hbase/HBaseTestingUtility."<init>":()V
      23: putstatic     #5                  // Field TEST_UTIL:Lorg/apache/hadoop/hbase/HBaseTestingUtility;
      26: return
}
