Compiled from "TestHFileBlock.java"
public class org.apache.hadoop.hbase.io.hfile.TestHFileBlock {
  public static final org.apache.hadoop.hbase.HBaseClassTestRule CLASS_RULE;

  static final org.apache.hadoop.hbase.io.compress.Compression$Algorithm[] COMPRESSION_ALGORITHMS;

  public org.apache.hadoop.hbase.io.hfile.TestHFileBlock(boolean, boolean);
    Code:
       0: aload_0
       1: invokespecial #3                  // Method java/lang/Object."<init>":()V
       4: aload_0
       5: iload_1
       6: putfield      #4                  // Field includesMemstoreTS:Z
       9: aload_0
      10: iload_2
      11: putfield      #5                  // Field includesTag:Z
      14: return

  public static java.util.Collection<java.lang.Object[]> parameters();
    Code:
       0: getstatic     #6                  // Field org/apache/hadoop/hbase/HBaseTestingUtility.MEMSTORETS_TAGS_PARAMETRIZED:Ljava/util/List;
       3: areturn

  public void setUp() throws java.io.IOException;
    Code:
       0: aload_0
       1: getstatic     #7                  // Field TEST_UTIL:Lorg/apache/hadoop/hbase/HBaseTestingUtility;
       4: invokevirtual #8                  // Method org/apache/hadoop/hbase/HBaseTestingUtility.getConfiguration:()Lorg/apache/hadoop/conf/Configuration;
       7: invokestatic  #9                  // Method org/apache/hadoop/hbase/fs/HFileSystem.get:(Lorg/apache/hadoop/conf/Configuration;)Lorg/apache/hadoop/fs/FileSystem;
      10: putfield      #10                 // Field fs:Lorg/apache/hadoop/fs/FileSystem;
      13: return

  static void writeTestBlockContents(java.io.DataOutputStream) throws java.io.IOException;
    Code:
       0: iconst_0
       1: istore_1
       2: iload_1
       3: sipush        1000
       6: if_icmpge     23
       9: aload_0
      10: iload_1
      11: bipush        100
      13: idiv
      14: invokevirtual #11                 // Method java/io/DataOutputStream.writeInt:(I)V
      17: iinc          1, 1
      20: goto          2
      23: return

  static int writeTestKeyValues(org.apache.hadoop.hbase.io.hfile.HFileBlock$Writer, int, boolean, boolean) throws java.io.IOException;
    Code:
       0: new           #12                 // class java/util/ArrayList
       3: dup
       4: invokespecial #13                 // Method java/util/ArrayList."<init>":()V
       7: astore        4
       9: new           #14                 // class java/util/Random
      12: dup
      13: ldc2_w        #15                 // long 42l
      16: iload_1
      17: i2l
      18: ladd
      19: invokespecial #17                 // Method java/util/Random."<init>":(J)V
      22: astore        5
      24: iconst_0
      25: istore        6
      27: iload         6
      29: getstatic     #18                 // Field NUM_KEYVALUES:I
      32: if_icmpge     398
      35: iconst_0
      36: iload         6
      38: if_icmpge     83
      41: aload         5
      43: invokevirtual #19                 // Method java/util/Random.nextFloat:()F
      46: getstatic     #20                 // Field CHANCE_TO_REPEAT:F
      49: fcmpg
      50: ifge          83
      53: aload         4
      55: aload         5
      57: aload         4
      59: invokeinterface #21,  1           // InterfaceMethod java/util/List.size:()I
      64: invokevirtual #22                 // Method java/util/Random.nextInt:(I)I
      67: invokeinterface #23,  2           // InterfaceMethod java/util/List.get:(I)Ljava/lang/Object;
      72: checkcast     #24                 // class org/apache/hadoop/hbase/Cell
      75: invokestatic  #25                 // Method org/apache/hadoop/hbase/CellUtil.cloneRow:(Lorg/apache/hadoop/hbase/Cell;)[B
      78: astore        7
      80: goto          97
      83: getstatic     #26                 // Field FIELD_LENGTH:I
      86: newarray       byte
      88: astore        7
      90: aload         5
      92: aload         7
      94: invokevirtual #27                 // Method java/util/Random.nextBytes:([B)V
      97: iconst_0
      98: iload         6
     100: if_icmpne     120
     103: getstatic     #26                 // Field FIELD_LENGTH:I
     106: newarray       byte
     108: astore        10
     110: aload         5
     112: aload         10
     114: invokevirtual #27                 // Method java/util/Random.nextBytes:([B)V
     117: goto          136
     120: aload         4
     122: iconst_0
     123: invokeinterface #23,  2           // InterfaceMethod java/util/List.get:(I)Ljava/lang/Object;
     128: checkcast     #24                 // class org/apache/hadoop/hbase/Cell
     131: invokestatic  #28                 // Method org/apache/hadoop/hbase/CellUtil.cloneFamily:(Lorg/apache/hadoop/hbase/Cell;)[B
     134: astore        10
     136: iconst_0
     137: iload         6
     139: if_icmpge     184
     142: aload         5
     144: invokevirtual #19                 // Method java/util/Random.nextFloat:()F
     147: getstatic     #20                 // Field CHANCE_TO_REPEAT:F
     150: fcmpg
     151: ifge          184
     154: aload         4
     156: aload         5
     158: aload         4
     160: invokeinterface #21,  1           // InterfaceMethod java/util/List.size:()I
     165: invokevirtual #22                 // Method java/util/Random.nextInt:(I)I
     168: invokeinterface #23,  2           // InterfaceMethod java/util/List.get:(I)Ljava/lang/Object;
     173: checkcast     #24                 // class org/apache/hadoop/hbase/Cell
     176: invokestatic  #29                 // Method org/apache/hadoop/hbase/CellUtil.cloneQualifier:(Lorg/apache/hadoop/hbase/Cell;)[B
     179: astore        11
     181: goto          198
     184: getstatic     #26                 // Field FIELD_LENGTH:I
     187: newarray       byte
     189: astore        11
     191: aload         5
     193: aload         11
     195: invokevirtual #27                 // Method java/util/Random.nextBytes:([B)V
     198: iconst_0
     199: iload         6
     201: if_icmpge     246
     204: aload         5
     206: invokevirtual #19                 // Method java/util/Random.nextFloat:()F
     209: getstatic     #20                 // Field CHANCE_TO_REPEAT:F
     212: fcmpg
     213: ifge          246
     216: aload         4
     218: aload         5
     220: aload         4
     222: invokeinterface #21,  1           // InterfaceMethod java/util/List.size:()I
     227: invokevirtual #22                 // Method java/util/Random.nextInt:(I)I
     230: invokeinterface #23,  2           // InterfaceMethod java/util/List.get:(I)Ljava/lang/Object;
     235: checkcast     #24                 // class org/apache/hadoop/hbase/Cell
     238: invokestatic  #30                 // Method org/apache/hadoop/hbase/CellUtil.cloneValue:(Lorg/apache/hadoop/hbase/Cell;)[B
     241: astore        12
     243: goto          260
     246: getstatic     #26                 // Field FIELD_LENGTH:I
     249: newarray       byte
     251: astore        12
     253: aload         5
     255: aload         12
     257: invokevirtual #27                 // Method java/util/Random.nextBytes:([B)V
     260: iconst_0
     261: iload         6
     263: if_icmpge     308
     266: aload         5
     268: invokevirtual #19                 // Method java/util/Random.nextFloat:()F
     271: getstatic     #20                 // Field CHANCE_TO_REPEAT:F
     274: fcmpg
     275: ifge          308
     278: aload         4
     280: aload         5
     282: aload         4
     284: invokeinterface #21,  1           // InterfaceMethod java/util/List.size:()I
     289: invokevirtual #22                 // Method java/util/Random.nextInt:(I)I
     292: invokeinterface #23,  2           // InterfaceMethod java/util/List.get:(I)Ljava/lang/Object;
     297: checkcast     #31                 // class org/apache/hadoop/hbase/KeyValue
     300: invokevirtual #32                 // Method org/apache/hadoop/hbase/KeyValue.getTimestamp:()J
     303: lstore        8
     305: goto          315
     308: aload         5
     310: invokevirtual #33                 // Method java/util/Random.nextLong:()J
     313: lstore        8
     315: iload_3
     316: ifne          347
     319: aload         4
     321: new           #31                 // class org/apache/hadoop/hbase/KeyValue
     324: dup
     325: aload         7
     327: aload         10
     329: aload         11
     331: lload         8
     333: aload         12
     335: invokespecial #34                 // Method org/apache/hadoop/hbase/KeyValue."<init>":([B[B[BJ[B)V
     338: invokeinterface #35,  2           // InterfaceMethod java/util/List.add:(Ljava/lang/Object;)Z
     343: pop
     344: goto          392
     347: aload         4
     349: new           #31                 // class org/apache/hadoop/hbase/KeyValue
     352: dup
     353: aload         7
     355: aload         10
     357: aload         11
     359: lload         8
     361: aload         12
     363: iconst_1
     364: anewarray     #36                 // class org/apache/hadoop/hbase/Tag
     367: dup
     368: iconst_0
     369: new           #37                 // class org/apache/hadoop/hbase/ArrayBackedTag
     372: dup
     373: iconst_1
     374: ldc           #38                 // String myTagVal
     376: invokestatic  #39                 // Method org/apache/hadoop/hbase/util/Bytes.toBytes:(Ljava/lang/String;)[B
     379: invokespecial #40                 // Method org/apache/hadoop/hbase/ArrayBackedTag."<init>":(B[B)V
     382: aastore
     383: invokespecial #41                 // Method org/apache/hadoop/hbase/KeyValue."<init>":([B[B[BJ[B[Lorg/apache/hadoop/hbase/Tag;)V
     386: invokeinterface #35,  2           // InterfaceMethod java/util/List.add:(Ljava/lang/Object;)Z
     391: pop
     392: iinc          6, 1
     395: goto          27
     398: iconst_0
     399: istore        6
     401: aload         4
     403: getstatic     #42                 // Field org/apache/hadoop/hbase/CellComparatorImpl.COMPARATOR:Lorg/apache/hadoop/hbase/CellComparatorImpl;
     406: invokestatic  #43                 // Method java/util/Collections.sort:(Ljava/util/List;Ljava/util/Comparator;)V
     409: aload         4
     411: invokeinterface #44,  1           // InterfaceMethod java/util/List.iterator:()Ljava/util/Iterator;
     416: astore        7
     418: aload         7
     420: invokeinterface #45,  1           // InterfaceMethod java/util/Iterator.hasNext:()Z
     425: ifeq          487
     428: aload         7
     430: invokeinterface #46,  1           // InterfaceMethod java/util/Iterator.next:()Ljava/lang/Object;
     435: checkcast     #31                 // class org/apache/hadoop/hbase/KeyValue
     438: astore        8
     440: iload         6
     442: aload         8
     444: invokevirtual #47                 // Method org/apache/hadoop/hbase/KeyValue.getLength:()I
     447: iadd
     448: istore        6
     450: iload_2
     451: ifeq          478
     454: aload         5
     456: invokevirtual #33                 // Method java/util/Random.nextLong:()J
     459: lstore        9
     461: aload         8
     463: lload         9
     465: invokevirtual #48                 // Method org/apache/hadoop/hbase/KeyValue.setSequenceId:(J)V
     468: iload         6
     470: lload         9
     472: invokestatic  #49                 // Method org/apache/hadoop/io/WritableUtils.getVIntSize:(J)I
     475: iadd
     476: istore        6
     478: aload_0
     479: aload         8
     481: invokevirtual #50                 // Method org/apache/hadoop/hbase/io/hfile/HFileBlock$Writer.write:(Lorg/apache/hadoop/hbase/Cell;)V
     484: goto          418
     487: iload         6
     489: ireturn

  public byte[] createTestV1Block(org.apache.hadoop.hbase.io.compress.Compression$Algorithm) throws java.io.IOException;
    Code:
       0: aload_1
       1: invokevirtual #51                 // Method org/apache/hadoop/hbase/io/compress/Compression$Algorithm.getCompressor:()Lorg/apache/hadoop/io/compress/Compressor;
       4: astore_2
       5: new           #52                 // class java/io/ByteArrayOutputStream
       8: dup
       9: invokespecial #53                 // Method java/io/ByteArrayOutputStream."<init>":()V
      12: astore_3
      13: aload_1
      14: aload_3
      15: aload_2
      16: iconst_0
      17: invokevirtual #54                 // Method org/apache/hadoop/hbase/io/compress/Compression$Algorithm.createCompressionStream:(Ljava/io/OutputStream;Lorg/apache/hadoop/io/compress/Compressor;I)Ljava/io/OutputStream;
      20: astore        4
      22: new           #55                 // class java/io/DataOutputStream
      25: dup
      26: aload         4
      28: invokespecial #56                 // Method java/io/DataOutputStream."<init>":(Ljava/io/OutputStream;)V
      31: astore        5
      33: getstatic     #57                 // Field org/apache/hadoop/hbase/io/hfile/BlockType.META:Lorg/apache/hadoop/hbase/io/hfile/BlockType;
      36: aload         5
      38: invokevirtual #58                 // Method org/apache/hadoop/hbase/io/hfile/BlockType.write:(Ljava/io/DataOutput;)V
      41: aload         5
      43: invokestatic  #59                 // Method writeTestBlockContents:(Ljava/io/DataOutputStream;)V
      46: aload         5
      48: invokevirtual #60                 // Method java/io/DataOutputStream.flush:()V
      51: aload_1
      52: aload_2
      53: invokevirtual #61                 // Method org/apache/hadoop/hbase/io/compress/Compression$Algorithm.returnCompressor:(Lorg/apache/hadoop/io/compress/Compressor;)V
      56: aload_3
      57: invokevirtual #62                 // Method java/io/ByteArrayOutputStream.toByteArray:()[B
      60: areturn

  static org.apache.hadoop.hbase.io.hfile.HFileBlock$Writer createTestV2Block(org.apache.hadoop.hbase.io.compress.Compression$Algorithm, boolean, boolean) throws java.io.IOException;
    Code:
       0: getstatic     #63                 // Field org/apache/hadoop/hbase/io/hfile/BlockType.DATA:Lorg/apache/hadoop/hbase/io/hfile/BlockType;
       3: astore_3
       4: new           #64                 // class org/apache/hadoop/hbase/io/hfile/HFileContextBuilder
       7: dup
       8: invokespecial #65                 // Method org/apache/hadoop/hbase/io/hfile/HFileContextBuilder."<init>":()V
      11: aload_0
      12: invokevirtual #66                 // Method org/apache/hadoop/hbase/io/hfile/HFileContextBuilder.withCompression:(Lorg/apache/hadoop/hbase/io/compress/Compression$Algorithm;)Lorg/apache/hadoop/hbase/io/hfile/HFileContextBuilder;
      15: iload_1
      16: invokevirtual #67                 // Method org/apache/hadoop/hbase/io/hfile/HFileContextBuilder.withIncludesMvcc:(Z)Lorg/apache/hadoop/hbase/io/hfile/HFileContextBuilder;
      19: iload_2
      20: invokevirtual #68                 // Method org/apache/hadoop/hbase/io/hfile/HFileContextBuilder.withIncludesTags:(Z)Lorg/apache/hadoop/hbase/io/hfile/HFileContextBuilder;
      23: sipush        16384
      26: invokevirtual #70                 // Method org/apache/hadoop/hbase/io/hfile/HFileContextBuilder.withBytesPerCheckSum:(I)Lorg/apache/hadoop/hbase/io/hfile/HFileContextBuilder;
      29: invokevirtual #71                 // Method org/apache/hadoop/hbase/io/hfile/HFileContextBuilder.build:()Lorg/apache/hadoop/hbase/io/hfile/HFileContext;
      32: astore        4
      34: new           #72                 // class org/apache/hadoop/hbase/io/hfile/HFileBlock$Writer
      37: dup
      38: aconst_null
      39: aload         4
      41: invokespecial #73                 // Method org/apache/hadoop/hbase/io/hfile/HFileBlock$Writer."<init>":(Lorg/apache/hadoop/hbase/io/hfile/HFileDataBlockEncoder;Lorg/apache/hadoop/hbase/io/hfile/HFileContext;)V
      44: astore        5
      46: aload         5
      48: aload_3
      49: invokevirtual #74                 // Method org/apache/hadoop/hbase/io/hfile/HFileBlock$Writer.startWriting:(Lorg/apache/hadoop/hbase/io/hfile/BlockType;)Ljava/io/DataOutputStream;
      52: astore        6
      54: aload         6
      56: invokestatic  #59                 // Method writeTestBlockContents:(Ljava/io/DataOutputStream;)V
      59: aload         6
      61: invokevirtual #60                 // Method java/io/DataOutputStream.flush:()V
      64: aload         5
      66: invokevirtual #75                 // Method org/apache/hadoop/hbase/io/hfile/HFileBlock$Writer.ensureBlockReady:()V
      69: ldc2_w        #76                 // long 4000l
      72: aload         5
      74: invokevirtual #78                 // Method org/apache/hadoop/hbase/io/hfile/HFileBlock$Writer.getUncompressedSizeWithoutHeader:()I
      77: i2l
      78: invokestatic  #79                 // Method org/junit/Assert.assertEquals:(JJ)V
      81: aload         5
      83: invokevirtual #80                 // Method org/apache/hadoop/hbase/io/hfile/HFileBlock$Writer.release:()V
      86: aload         5
      88: areturn

  public java.lang.String createTestBlockStr(org.apache.hadoop.hbase.io.compress.Compression$Algorithm, int, boolean) throws java.io.IOException;
    Code:
       0: aload_1
       1: aload_0
       2: getfield      #4                  // Field includesMemstoreTS:Z
       5: iload_3
       6: invokestatic  #81                 // Method createTestV2Block:(Lorg/apache/hadoop/hbase/io/compress/Compression$Algorithm;ZZ)Lorg/apache/hadoop/hbase/io/hfile/HFileBlock$Writer;
       9: astore        4
      11: aload         4
      13: invokevirtual #82                 // Method org/apache/hadoop/hbase/io/hfile/HFileBlock$Writer.getHeaderAndDataForTest:()[B
      16: astore        5
      18: bipush        42
      20: istore        6
      22: aload         5
      24: arraylength
      25: iload_2
      26: if_icmpne     35
      29: aload         5
      31: iload         6
      33: iconst_3
      34: bastore
      35: aload         5
      37: invokestatic  #84                 // Method org/apache/hadoop/hbase/util/Bytes.toStringBinary:([B)Ljava/lang/String;
      40: areturn

  public void testNoCompression() throws java.io.IOException;
    Code:
       0: ldc           #85                 // class org/apache/hadoop/hbase/io/hfile/CacheConfig
       2: invokestatic  #86                 // Method org/mockito/Mockito.mock:(Ljava/lang/Class;)Ljava/lang/Object;
       5: checkcast     #85                 // class org/apache/hadoop/hbase/io/hfile/CacheConfig
       8: astore_1
       9: aload_1
      10: invokevirtual #87                 // Method org/apache/hadoop/hbase/io/hfile/CacheConfig.getBlockCache:()Ljava/util/Optional;
      13: invokestatic  #88                 // Method org/mockito/Mockito.when:(Ljava/lang/Object;)Lorg/mockito/stubbing/OngoingStubbing;
      16: invokestatic  #89                 // Method java/util/Optional.empty:()Ljava/util/Optional;
      19: invokeinterface #90,  2           // InterfaceMethod org/mockito/stubbing/OngoingStubbing.thenReturn:(Ljava/lang/Object;)Lorg/mockito/stubbing/OngoingStubbing;
      24: pop
      25: getstatic     #91                 // Field org/apache/hadoop/hbase/io/compress/Compression$Algorithm.NONE:Lorg/apache/hadoop/hbase/io/compress/Compression$Algorithm;
      28: aload_0
      29: getfield      #4                  // Field includesMemstoreTS:Z
      32: iconst_0
      33: invokestatic  #81                 // Method createTestV2Block:(Lorg/apache/hadoop/hbase/io/compress/Compression$Algorithm;ZZ)Lorg/apache/hadoop/hbase/io/hfile/HFileBlock$Writer;
      36: aload_1
      37: invokevirtual #92                 // Method org/apache/hadoop/hbase/io/hfile/HFileBlock$Writer.getBlockForCaching:(Lorg/apache/hadoop/hbase/io/hfile/CacheConfig;)Lorg/apache/hadoop/hbase/io/hfile/HFileBlock;
      40: astore_2
      41: ldc2_w        #76                 // long 4000l
      44: aload_2
      45: invokevirtual #93                 // Method org/apache/hadoop/hbase/io/hfile/HFileBlock.getUncompressedSizeWithoutHeader:()I
      48: i2l
      49: invokestatic  #79                 // Method org/junit/Assert.assertEquals:(JJ)V
      52: ldc2_w        #94                 // long 4004l
      55: aload_2
      56: invokevirtual #96                 // Method org/apache/hadoop/hbase/io/hfile/HFileBlock.getOnDiskSizeWithoutHeader:()I
      59: i2l
      60: invokestatic  #79                 // Method org/junit/Assert.assertEquals:(JJ)V
      63: aload_2
      64: invokevirtual #97                 // Method org/apache/hadoop/hbase/io/hfile/HFileBlock.isUnpacked:()Z
      67: invokestatic  #98                 // Method org/junit/Assert.assertTrue:(Z)V
      70: return

  public void testGzipCompression() throws java.io.IOException;
    Code:
       0: new           #99                 // class java/lang/StringBuilder
       3: dup
       4: invokespecial #100                // Method java/lang/StringBuilder."<init>":()V
       7: ldc           #101                // String DATABLK*\x00\x00\x00>\x00\x00\x0F\xA0\xFF\xFF\xFF\xFF\xFF\xFF\xFF\xFF\x0
       9: invokevirtual #102                // Method java/lang/StringBuilder.append:(Ljava/lang/String;)Ljava/lang/StringBuilder;
      12: invokestatic  #103                // Method org/apache/hadoop/hbase/util/ChecksumType.getDefaultChecksumType:()Lorg/apache/hadoop/hbase/util/ChecksumType;
      15: invokevirtual #104                // Method org/apache/hadoop/hbase/util/ChecksumType.getCode:()B
      18: invokevirtual #105                // Method java/lang/StringBuilder.append:(I)Ljava/lang/StringBuilder;
      21: ldc           #106                // String \x00\x00@\x00\x00\x00\x00[\x1F\x8B\x08\x00\x00\x00\x00\x00\x00\x03\xED\xC3\xC1\x11\x00 \x08\xC00DD\xDD\x7Fa\xD6\xE8\xA3\xB9K\x84`\x96Q\xD3\xA8\xDB\xA8e\xD4c\xD46\xEA5\xEA3\xEA7\xE7\x00LI\x5Cs\xA0\x0F\x00\x00\x00\x00\x00\x00
      23: invokevirtual #102                // Method java/lang/StringBuilder.append:(Ljava/lang/String;)Ljava/lang/StringBuilder;
      26: invokevirtual #107                // Method java/lang/StringBuilder.toString:()Ljava/lang/String;
      29: astore_1
      30: bipush        95
      32: istore_2
      33: aload_0
      34: getstatic     #108                // Field org/apache/hadoop/hbase/io/compress/Compression$Algorithm.GZ:Lorg/apache/hadoop/hbase/io/compress/Compression$Algorithm;
      37: bipush        95
      39: iconst_0
      40: invokevirtual #109                // Method createTestBlockStr:(Lorg/apache/hadoop/hbase/io/compress/Compression$Algorithm;IZ)Ljava/lang/String;
      43: astore_3
      44: aload_1
      45: iconst_0
      46: bipush        91
      48: invokevirtual #110                // Method java/lang/String.substring:(II)Ljava/lang/String;
      51: aload_3
      52: iconst_0
      53: bipush        91
      55: invokevirtual #110                // Method java/lang/String.substring:(II)Ljava/lang/String;
      58: invokestatic  #111                // Method org/junit/Assert.assertEquals:(Ljava/lang/Object;Ljava/lang/Object;)V
      61: return

  public void testReaderV2() throws java.io.IOException;
    Code:
       0: aload_0
       1: invokevirtual #112                // Method testReaderV2Internals:()V
       4: return

  protected void testReaderV2Internals() throws java.io.IOException;
    Code:
       0: aload_0
       1: getfield      #5                  // Field includesTag:Z
       4: ifeq          19
       7: getstatic     #7                  // Field TEST_UTIL:Lorg/apache/hadoop/hbase/HBaseTestingUtility;
      10: invokevirtual #8                  // Method org/apache/hadoop/hbase/HBaseTestingUtility.getConfiguration:()Lorg/apache/hadoop/conf/Configuration;
      13: ldc           #113                // String hfile.format.version
      15: iconst_3
      16: invokevirtual #114                // Method org/apache/hadoop/conf/Configuration.setInt:(Ljava/lang/String;I)V
      19: getstatic     #115                // Field COMPRESSION_ALGORITHMS:[Lorg/apache/hadoop/hbase/io/compress/Compression$Algorithm;
      22: astore_1
      23: aload_1
      24: arraylength
      25: istore_2
      26: iconst_0
      27: istore_3
      28: iload_3
      29: iload_2
      30: if_icmpge     593
      33: aload_1
      34: iload_3
      35: aaload
      36: astore        4
      38: iconst_2
      39: newarray       boolean
      41: dup
      42: iconst_0
      43: iconst_0
      44: bastore
      45: dup
      46: iconst_1
      47: iconst_1
      48: bastore
      49: astore        5
      51: aload         5
      53: arraylength
      54: istore        6
      56: iconst_0
      57: istore        7
      59: iload         7
      61: iload         6
      63: if_icmpge     587
      66: aload         5
      68: iload         7
      70: baload
      71: istore        8
      73: getstatic     #2                  // Field LOG:Lorg/slf4j/Logger;
      76: new           #99                 // class java/lang/StringBuilder
      79: dup
      80: invokespecial #100                // Method java/lang/StringBuilder."<init>":()V
      83: ldc           #116                // String testReaderV2: Compression algorithm:
      85: invokevirtual #102                // Method java/lang/StringBuilder.append:(Ljava/lang/String;)Ljava/lang/StringBuilder;
      88: aload         4
      90: invokevirtual #117                // Method java/lang/StringBuilder.append:(Ljava/lang/Object;)Ljava/lang/StringBuilder;
      93: ldc           #118                // String , pread=
      95: invokevirtual #102                // Method java/lang/StringBuilder.append:(Ljava/lang/String;)Ljava/lang/StringBuilder;
      98: iload         8
     100: invokevirtual #119                // Method java/lang/StringBuilder.append:(Z)Ljava/lang/StringBuilder;
     103: invokevirtual #107                // Method java/lang/StringBuilder.toString:()Ljava/lang/String;
     106: invokeinterface #120,  2          // InterfaceMethod org/slf4j/Logger.info:(Ljava/lang/String;)V
     111: new           #121                // class org/apache/hadoop/fs/Path
     114: dup
     115: getstatic     #7                  // Field TEST_UTIL:Lorg/apache/hadoop/hbase/HBaseTestingUtility;
     118: invokevirtual #122                // Method org/apache/hadoop/hbase/HBaseTestingUtility.getDataTestDir:()Lorg/apache/hadoop/fs/Path;
     121: new           #99                 // class java/lang/StringBuilder
     124: dup
     125: invokespecial #100                // Method java/lang/StringBuilder."<init>":()V
     128: ldc           #123                // String blocks_v2_
     130: invokevirtual #102                // Method java/lang/StringBuilder.append:(Ljava/lang/String;)Ljava/lang/StringBuilder;
     133: aload         4
     135: invokevirtual #117                // Method java/lang/StringBuilder.append:(Ljava/lang/Object;)Ljava/lang/StringBuilder;
     138: invokevirtual #107                // Method java/lang/StringBuilder.toString:()Ljava/lang/String;
     141: invokespecial #124                // Method org/apache/hadoop/fs/Path."<init>":(Lorg/apache/hadoop/fs/Path;Ljava/lang/String;)V
     144: astore        9
     146: aload_0
     147: getfield      #10                 // Field fs:Lorg/apache/hadoop/fs/FileSystem;
     150: aload         9
     152: invokevirtual #125                // Method org/apache/hadoop/fs/FileSystem.create:(Lorg/apache/hadoop/fs/Path;)Lorg/apache/hadoop/fs/FSDataOutputStream;
     155: astore        10
     157: new           #64                 // class org/apache/hadoop/hbase/io/hfile/HFileContextBuilder
     160: dup
     161: invokespecial #65                 // Method org/apache/hadoop/hbase/io/hfile/HFileContextBuilder."<init>":()V
     164: aload         4
     166: invokevirtual #66                 // Method org/apache/hadoop/hbase/io/hfile/HFileContextBuilder.withCompression:(Lorg/apache/hadoop/hbase/io/compress/Compression$Algorithm;)Lorg/apache/hadoop/hbase/io/hfile/HFileContextBuilder;
     169: aload_0
     170: getfield      #4                  // Field includesMemstoreTS:Z
     173: invokevirtual #67                 // Method org/apache/hadoop/hbase/io/hfile/HFileContextBuilder.withIncludesMvcc:(Z)Lorg/apache/hadoop/hbase/io/hfile/HFileContextBuilder;
     176: aload_0
     177: getfield      #5                  // Field includesTag:Z
     180: invokevirtual #68                 // Method org/apache/hadoop/hbase/io/hfile/HFileContextBuilder.withIncludesTags:(Z)Lorg/apache/hadoop/hbase/io/hfile/HFileContextBuilder;
     183: sipush        16384
     186: invokevirtual #70                 // Method org/apache/hadoop/hbase/io/hfile/HFileContextBuilder.withBytesPerCheckSum:(I)Lorg/apache/hadoop/hbase/io/hfile/HFileContextBuilder;
     189: invokevirtual #71                 // Method org/apache/hadoop/hbase/io/hfile/HFileContextBuilder.build:()Lorg/apache/hadoop/hbase/io/hfile/HFileContext;
     192: astore        11
     194: new           #72                 // class org/apache/hadoop/hbase/io/hfile/HFileBlock$Writer
     197: dup
     198: aconst_null
     199: aload         11
     201: invokespecial #73                 // Method org/apache/hadoop/hbase/io/hfile/HFileBlock$Writer."<init>":(Lorg/apache/hadoop/hbase/io/hfile/HFileDataBlockEncoder;Lorg/apache/hadoop/hbase/io/hfile/HFileContext;)V
     204: astore        12
     206: lconst_0
     207: lstore        13
     209: iconst_0
     210: istore        15
     212: iload         15
     214: iconst_2
     215: if_icmpge     276
     218: aload         12
     220: getstatic     #63                 // Field org/apache/hadoop/hbase/io/hfile/BlockType.DATA:Lorg/apache/hadoop/hbase/io/hfile/BlockType;
     223: invokevirtual #74                 // Method org/apache/hadoop/hbase/io/hfile/HFileBlock$Writer.startWriting:(Lorg/apache/hadoop/hbase/io/hfile/BlockType;)Ljava/io/DataOutputStream;
     226: astore        16
     228: iconst_0
     229: istore        17
     231: iload         17
     233: sipush        1234
     236: if_icmpge     252
     239: aload         16
     241: iload         17
     243: invokevirtual #11                 // Method java/io/DataOutputStream.writeInt:(I)V
     246: iinc          17, 1
     249: goto          231
     252: aload         12
     254: aload         10
     256: invokevirtual #126                // Method org/apache/hadoop/hbase/io/hfile/HFileBlock$Writer.writeHeaderAndData:(Lorg/apache/hadoop/fs/FSDataOutputStream;)V
     259: lload         13
     261: aload         12
     263: invokevirtual #127                // Method org/apache/hadoop/hbase/io/hfile/HFileBlock$Writer.getOnDiskSizeWithHeader:()I
     266: i2l
     267: ladd
     268: lstore        13
     270: iinc          15, 1
     273: goto          212
     276: aload         10
     278: invokevirtual #128                // Method org/apache/hadoop/fs/FSDataOutputStream.close:()V
     281: aload_0
     282: getfield      #10                 // Field fs:Lorg/apache/hadoop/fs/FileSystem;
     285: aload         9
     287: invokevirtual #129                // Method org/apache/hadoop/fs/FileSystem.open:(Lorg/apache/hadoop/fs/Path;)Lorg/apache/hadoop/fs/FSDataInputStream;
     290: astore        15
     292: new           #64                 // class org/apache/hadoop/hbase/io/hfile/HFileContextBuilder
     295: dup
     296: invokespecial #65                 // Method org/apache/hadoop/hbase/io/hfile/HFileContextBuilder."<init>":()V
     299: iconst_1
     300: invokevirtual #130                // Method org/apache/hadoop/hbase/io/hfile/HFileContextBuilder.withHBaseCheckSum:(Z)Lorg/apache/hadoop/hbase/io/hfile/HFileContextBuilder;
     303: aload_0
     304: getfield      #4                  // Field includesMemstoreTS:Z
     307: invokevirtual #67                 // Method org/apache/hadoop/hbase/io/hfile/HFileContextBuilder.withIncludesMvcc:(Z)Lorg/apache/hadoop/hbase/io/hfile/HFileContextBuilder;
     310: aload_0
     311: getfield      #5                  // Field includesTag:Z
     314: invokevirtual #68                 // Method org/apache/hadoop/hbase/io/hfile/HFileContextBuilder.withIncludesTags:(Z)Lorg/apache/hadoop/hbase/io/hfile/HFileContextBuilder;
     317: aload         4
     319: invokevirtual #66                 // Method org/apache/hadoop/hbase/io/hfile/HFileContextBuilder.withCompression:(Lorg/apache/hadoop/hbase/io/compress/Compression$Algorithm;)Lorg/apache/hadoop/hbase/io/hfile/HFileContextBuilder;
     322: invokevirtual #71                 // Method org/apache/hadoop/hbase/io/hfile/HFileContextBuilder.build:()Lorg/apache/hadoop/hbase/io/hfile/HFileContext;
     325: astore        11
     327: new           #131                // class org/apache/hadoop/hbase/io/hfile/HFileBlock$FSReaderImpl
     330: dup
     331: aload         15
     333: lload         13
     335: aload         11
     337: invokespecial #132                // Method org/apache/hadoop/hbase/io/hfile/HFileBlock$FSReaderImpl."<init>":(Lorg/apache/hadoop/fs/FSDataInputStream;JLorg/apache/hadoop/hbase/io/hfile/HFileContext;)V
     340: astore        16
     342: aload         16
     344: lconst_0
     345: ldc2_w        #133                // long -1l
     348: iload         8
     350: iconst_0
     351: invokeinterface #135,  7          // InterfaceMethod org/apache/hadoop/hbase/io/hfile/HFileBlock$FSReader.readBlockData:(JJZZ)Lorg/apache/hadoop/hbase/io/hfile/HFileBlock;
     356: astore        17
     358: aload         15
     360: invokevirtual #136                // Method org/apache/hadoop/fs/FSDataInputStream.close:()V
     363: lconst_0
     364: invokestatic  #137                // Method org/apache/hadoop/hbase/io/hfile/HFile.getAndResetChecksumFailuresCount:()J
     367: invokestatic  #79                 // Method org/junit/Assert.assertEquals:(JJ)V
     370: aload         17
     372: invokevirtual #138                // Method org/apache/hadoop/hbase/io/hfile/HFileBlock.sanityCheck:()V
     375: ldc2_w        #139                // long 4936l
     378: aload         17
     380: invokevirtual #93                 // Method org/apache/hadoop/hbase/io/hfile/HFileBlock.getUncompressedSizeWithoutHeader:()I
     383: i2l
     384: invokestatic  #79                 // Method org/junit/Assert.assertEquals:(JJ)V
     387: aload         4
     389: getstatic     #108                // Field org/apache/hadoop/hbase/io/compress/Compression$Algorithm.GZ:Lorg/apache/hadoop/hbase/io/compress/Compression$Algorithm;
     392: if_acmpne     401
     395: ldc2_w        #141                // long 2173l
     398: goto          404
     401: ldc2_w        #139                // long 4936l
     404: aload         17
     406: invokevirtual #96                 // Method org/apache/hadoop/hbase/io/hfile/HFileBlock.getOnDiskSizeWithoutHeader:()I
     409: aload         17
     411: invokevirtual #143                // Method org/apache/hadoop/hbase/io/hfile/HFileBlock.totalChecksumBytes:()I
     414: isub
     415: i2l
     416: invokestatic  #79                 // Method org/junit/Assert.assertEquals:(JJ)V
     419: aload         17
     421: astore        18
     423: aload         4
     425: getstatic     #108                // Field org/apache/hadoop/hbase/io/compress/Compression$Algorithm.GZ:Lorg/apache/hadoop/hbase/io/compress/Compression$Algorithm;
     428: if_acmpne     581
     431: aload_0
     432: getfield      #10                 // Field fs:Lorg/apache/hadoop/fs/FileSystem;
     435: aload         9
     437: invokevirtual #129                // Method org/apache/hadoop/fs/FileSystem.open:(Lorg/apache/hadoop/fs/Path;)Lorg/apache/hadoop/fs/FSDataInputStream;
     440: astore        15
     442: new           #131                // class org/apache/hadoop/hbase/io/hfile/HFileBlock$FSReaderImpl
     445: dup
     446: aload         15
     448: lload         13
     450: aload         11
     452: invokespecial #132                // Method org/apache/hadoop/hbase/io/hfile/HFileBlock$FSReaderImpl."<init>":(Lorg/apache/hadoop/fs/FSDataInputStream;JLorg/apache/hadoop/hbase/io/hfile/HFileContext;)V
     455: astore        16
     457: aload         16
     459: lconst_0
     460: sipush        2206
     463: aload         17
     465: invokevirtual #143                // Method org/apache/hadoop/hbase/io/hfile/HFileBlock.totalChecksumBytes:()I
     468: iadd
     469: i2l
     470: iload         8
     472: iconst_0
     473: invokeinterface #135,  7          // InterfaceMethod org/apache/hadoop/hbase/io/hfile/HFileBlock$FSReader.readBlockData:(JJZZ)Lorg/apache/hadoop/hbase/io/hfile/HFileBlock;
     478: astore        17
     480: aload         18
     482: aload         17
     484: invokestatic  #111                // Method org/junit/Assert.assertEquals:(Ljava/lang/Object;Ljava/lang/Object;)V
     487: sipush        2172
     490: istore        19
     492: aload         16
     494: lconst_0
     495: iload         19
     497: bipush        33
     499: iadd
     500: i2l
     501: iload         8
     503: iconst_0
     504: invokeinterface #135,  7          // InterfaceMethod org/apache/hadoop/hbase/io/hfile/HFileBlock$FSReader.readBlockData:(JJZZ)Lorg/apache/hadoop/hbase/io/hfile/HFileBlock;
     509: astore        17
     511: ldc           #144                // String Exception expected
     513: invokestatic  #145                // Method org/junit/Assert.fail:(Ljava/lang/String;)V
     516: goto          576
     519: astore        20
     521: ldc           #147                // String Passed in onDiskSizeWithHeader=
     523: astore        21
     525: new           #99                 // class java/lang/StringBuilder
     528: dup
     529: invokespecial #100                // Method java/lang/StringBuilder."<init>":()V
     532: ldc           #148                // String Invalid exception message: '
     534: invokevirtual #102                // Method java/lang/StringBuilder.append:(Ljava/lang/String;)Ljava/lang/StringBuilder;
     537: aload         20
     539: invokevirtual #149                // Method java/io/IOException.getMessage:()Ljava/lang/String;
     542: invokevirtual #102                // Method java/lang/StringBuilder.append:(Ljava/lang/String;)Ljava/lang/StringBuilder;
     545: ldc           #150                // String '.\nMessage is expected to start with: '
     547: invokevirtual #102                // Method java/lang/StringBuilder.append:(Ljava/lang/String;)Ljava/lang/StringBuilder;
     550: aload         21
     552: invokevirtual #102                // Method java/lang/StringBuilder.append:(Ljava/lang/String;)Ljava/lang/StringBuilder;
     555: ldc           #151                // String '
     557: invokevirtual #102                // Method java/lang/StringBuilder.append:(Ljava/lang/String;)Ljava/lang/StringBuilder;
     560: invokevirtual #107                // Method java/lang/StringBuilder.toString:()Ljava/lang/String;
     563: aload         20
     565: invokevirtual #149                // Method java/io/IOException.getMessage:()Ljava/lang/String;
     568: aload         21
     570: invokevirtual #152                // Method java/lang/String.startsWith:(Ljava/lang/String;)Z
     573: invokestatic  #153                // Method org/junit/Assert.assertTrue:(Ljava/lang/String;Z)V
     576: aload         15
     578: invokevirtual #136                // Method org/apache/hadoop/fs/FSDataInputStream.close:()V
     581: iinc          7, 1
     584: goto          59
     587: iinc          3, 1
     590: goto          28
     593: return
    Exception table:
       from    to  target type
         492   516   519   Class java/io/IOException

  public void testDataBlockEncoding() throws java.io.IOException;
    Code:
       0: aload_0
       1: invokespecial #154                // Method testInternals:()V
       4: return

  static java.lang.String buildMessageDetails(org.apache.hadoop.hbase.io.compress.Compression$Algorithm, org.apache.hadoop.hbase.io.encoding.DataBlockEncoding, boolean);
    Code:
       0: ldc           #211                // String compression %s, encoding %s, pread %s
       2: iconst_3
       3: anewarray     #157                // class java/lang/Object
       6: dup
       7: iconst_0
       8: aload_0
       9: aastore
      10: dup
      11: iconst_1
      12: aload_1
      13: aastore
      14: dup
      15: iconst_2
      16: iload_2
      17: invokestatic  #159                // Method java/lang/Boolean.valueOf:(Z)Ljava/lang/Boolean;
      20: aastore
      21: invokestatic  #212                // Method java/lang/String.format:(Ljava/lang/String;[Ljava/lang/Object;)Ljava/lang/String;
      24: areturn

  static void assertBuffersEqual(org.apache.hadoop.hbase.nio.ByteBuff, org.apache.hadoop.hbase.nio.ByteBuff, org.apache.hadoop.hbase.io.compress.Compression$Algorithm, org.apache.hadoop.hbase.io.encoding.DataBlockEncoding, boolean);
    Code:
       0: aload_1
       1: aload_0
       2: invokevirtual #213                // Method java/lang/Object.equals:(Ljava/lang/Object;)Z
       5: ifne          100
       8: iconst_0
       9: istore        5
      11: aload_0
      12: invokevirtual #214                // Method org/apache/hadoop/hbase/nio/ByteBuff.limit:()I
      15: aload_1
      16: invokevirtual #214                // Method org/apache/hadoop/hbase/nio/ByteBuff.limit:()I
      19: invokestatic  #215                // Method java/lang/Math.min:(II)I
      22: istore        6
      24: iload         5
      26: iload         6
      28: if_icmpge     52
      31: aload_0
      32: iload         5
      34: invokevirtual #191                // Method org/apache/hadoop/hbase/nio/ByteBuff.get:(I)B
      37: aload_1
      38: iload         5
      40: invokevirtual #191                // Method org/apache/hadoop/hbase/nio/ByteBuff.get:(I)B
      43: if_icmpne     52
      46: iinc          5, 1
      49: goto          24
      52: ldc           #216                // String Content mismatch for %s, commonPrefix %d, expected %s, got %s
      54: iconst_4
      55: anewarray     #157                // class java/lang/Object
      58: dup
      59: iconst_0
      60: aload_2
      61: aload_3
      62: iload         4
      64: invokestatic  #189                // Method buildMessageDetails:(Lorg/apache/hadoop/hbase/io/compress/Compression$Algorithm;Lorg/apache/hadoop/hbase/io/encoding/DataBlockEncoding;Z)Ljava/lang/String;
      67: aastore
      68: dup
      69: iconst_1
      70: iload         5
      72: invokestatic  #172                // Method java/lang/Integer.valueOf:(I)Ljava/lang/Integer;
      75: aastore
      76: dup
      77: iconst_2
      78: aload_0
      79: iload         5
      81: invokestatic  #217                // Method nextBytesToStr:(Lorg/apache/hadoop/hbase/nio/ByteBuff;I)Ljava/lang/String;
      84: aastore
      85: dup
      86: iconst_3
      87: aload_1
      88: iload         5
      90: invokestatic  #217                // Method nextBytesToStr:(Lorg/apache/hadoop/hbase/nio/ByteBuff;I)Ljava/lang/String;
      93: aastore
      94: invokestatic  #212                // Method java/lang/String.format:(Ljava/lang/String;[Ljava/lang/Object;)Ljava/lang/String;
      97: invokestatic  #145                // Method org/junit/Assert.fail:(Ljava/lang/String;)V
     100: return

  public void testPreviousOffset() throws java.io.IOException;
    Code:
       0: aload_0
       1: invokevirtual #223                // Method testPreviousOffsetInternals:()V
       4: return

  protected void testPreviousOffsetInternals() throws java.io.IOException;
    Code:
       0: getstatic     #115                // Field COMPRESSION_ALGORITHMS:[Lorg/apache/hadoop/hbase/io/compress/Compression$Algorithm;
       3: astore_1
       4: aload_1
       5: arraylength
       6: istore_2
       7: iconst_0
       8: istore_3
       9: iload_3
      10: iload_2
      11: if_icmpge     890
      14: aload_1
      15: iload_3
      16: aaload
      17: astore        4
      19: getstatic     #224                // Field BOOLEAN_VALUES:[Z
      22: astore        5
      24: aload         5
      26: arraylength
      27: istore        6
      29: iconst_0
      30: istore        7
      32: iload         7
      34: iload         6
      36: if_icmpge     884
      39: aload         5
      41: iload         7
      43: baload
      44: istore        8
      46: getstatic     #224                // Field BOOLEAN_VALUES:[Z
      49: astore        9
      51: aload         9
      53: arraylength
      54: istore        10
      56: iconst_0
      57: istore        11
      59: iload         11
      61: iload         10
      63: if_icmpge     878
      66: aload         9
      68: iload         11
      70: baload
      71: istore        12
      73: aload_0
      74: invokespecial #225                // Method defaultRandom:()Ljava/util/Random;
      77: astore        13
      79: getstatic     #2                  // Field LOG:Lorg/slf4j/Logger;
      82: ldc           #226                // String testPreviousOffset: Compression algorithm={}, pread={}, cacheOnWrite={}
      84: iconst_3
      85: anewarray     #157                // class java/lang/Object
      88: dup
      89: iconst_0
      90: aload         4
      92: invokevirtual #158                // Method org/apache/hadoop/hbase/io/compress/Compression$Algorithm.toString:()Ljava/lang/String;
      95: aastore
      96: dup
      97: iconst_1
      98: iload         8
     100: invokestatic  #159                // Method java/lang/Boolean.valueOf:(Z)Ljava/lang/Boolean;
     103: aastore
     104: dup
     105: iconst_2
     106: iload         12
     108: invokestatic  #159                // Method java/lang/Boolean.valueOf:(Z)Ljava/lang/Boolean;
     111: aastore
     112: invokeinterface #160,  3          // InterfaceMethod org/slf4j/Logger.info:(Ljava/lang/String;[Ljava/lang/Object;)V
     117: new           #121                // class org/apache/hadoop/fs/Path
     120: dup
     121: getstatic     #7                  // Field TEST_UTIL:Lorg/apache/hadoop/hbase/HBaseTestingUtility;
     124: invokevirtual #122                // Method org/apache/hadoop/hbase/HBaseTestingUtility.getDataTestDir:()Lorg/apache/hadoop/fs/Path;
     127: ldc           #227                // String prev_offset
     129: invokespecial #124                // Method org/apache/hadoop/fs/Path."<init>":(Lorg/apache/hadoop/fs/Path;Ljava/lang/String;)V
     132: astore        14
     134: new           #12                 // class java/util/ArrayList
     137: dup
     138: invokespecial #13                 // Method java/util/ArrayList."<init>":()V
     141: astore        15
     143: new           #12                 // class java/util/ArrayList
     146: dup
     147: invokespecial #13                 // Method java/util/ArrayList."<init>":()V
     150: astore        16
     152: new           #12                 // class java/util/ArrayList
     155: dup
     156: invokespecial #13                 // Method java/util/ArrayList."<init>":()V
     159: astore        17
     161: iload         12
     163: ifeq          176
     166: new           #12                 // class java/util/ArrayList
     169: dup
     170: invokespecial #13                 // Method java/util/ArrayList."<init>":()V
     173: goto          177
     176: aconst_null
     177: astore        18
     179: aload_0
     180: aload         13
     182: aload         4
     184: aload         14
     186: aload         15
     188: aload         16
     190: aload         17
     192: aload         18
     194: invokespecial #228                // Method writeBlocks:(Ljava/util/Random;Lorg/apache/hadoop/hbase/io/compress/Compression$Algorithm;Lorg/apache/hadoop/fs/Path;Ljava/util/List;Ljava/util/List;Ljava/util/List;Ljava/util/List;)J
     197: lstore        19
     199: aload_0
     200: getfield      #10                 // Field fs:Lorg/apache/hadoop/fs/FileSystem;
     203: aload         14
     205: invokevirtual #129                // Method org/apache/hadoop/fs/FileSystem.open:(Lorg/apache/hadoop/fs/Path;)Lorg/apache/hadoop/fs/FSDataInputStream;
     208: astore        21
     210: new           #64                 // class org/apache/hadoop/hbase/io/hfile/HFileContextBuilder
     213: dup
     214: invokespecial #65                 // Method org/apache/hadoop/hbase/io/hfile/HFileContextBuilder."<init>":()V
     217: iconst_1
     218: invokevirtual #130                // Method org/apache/hadoop/hbase/io/hfile/HFileContextBuilder.withHBaseCheckSum:(Z)Lorg/apache/hadoop/hbase/io/hfile/HFileContextBuilder;
     221: aload_0
     222: getfield      #4                  // Field includesMemstoreTS:Z
     225: invokevirtual #67                 // Method org/apache/hadoop/hbase/io/hfile/HFileContextBuilder.withIncludesMvcc:(Z)Lorg/apache/hadoop/hbase/io/hfile/HFileContextBuilder;
     228: aload_0
     229: getfield      #5                  // Field includesTag:Z
     232: invokevirtual #68                 // Method org/apache/hadoop/hbase/io/hfile/HFileContextBuilder.withIncludesTags:(Z)Lorg/apache/hadoop/hbase/io/hfile/HFileContextBuilder;
     235: aload         4
     237: invokevirtual #66                 // Method org/apache/hadoop/hbase/io/hfile/HFileContextBuilder.withCompression:(Lorg/apache/hadoop/hbase/io/compress/Compression$Algorithm;)Lorg/apache/hadoop/hbase/io/hfile/HFileContextBuilder;
     240: invokevirtual #71                 // Method org/apache/hadoop/hbase/io/hfile/HFileContextBuilder.build:()Lorg/apache/hadoop/hbase/io/hfile/HFileContext;
     243: astore        22
     245: new           #131                // class org/apache/hadoop/hbase/io/hfile/HFileBlock$FSReaderImpl
     248: dup
     249: aload         21
     251: lload         19
     253: aload         22
     255: invokespecial #132                // Method org/apache/hadoop/hbase/io/hfile/HFileBlock$FSReaderImpl."<init>":(Lorg/apache/hadoop/fs/FSDataInputStream;JLorg/apache/hadoop/hbase/io/hfile/HFileContext;)V
     258: astore        23
     260: lconst_0
     261: lstore        24
     263: iconst_0
     264: istore        26
     266: iload         26
     268: sipush        1000
     271: if_icmpge     850
     274: iload         8
     276: ifne          302
     279: aload         21
     281: invokevirtual #229                // Method org/apache/hadoop/fs/FSDataInputStream.getPos:()J
     284: lload         24
     286: iload         26
     288: ifne          295
     291: iconst_0
     292: goto          297
     295: bipush        33
     297: i2l
     298: ladd
     299: invokestatic  #79                 // Method org/junit/Assert.assertEquals:(JJ)V
     302: aload         15
     304: iload         26
     306: invokeinterface #23,  2           // InterfaceMethod java/util/List.get:(I)Ljava/lang/Object;
     311: checkcast     #230                // class java/lang/Long
     314: invokevirtual #231                // Method java/lang/Long.longValue:()J
     317: lload         24
     319: invokestatic  #79                 // Method org/junit/Assert.assertEquals:(JJ)V
     322: aload         23
     324: lload         24
     326: ldc2_w        #133                // long -1l
     329: iload         8
     331: iconst_0
     332: invokeinterface #135,  7          // InterfaceMethod org/apache/hadoop/hbase/io/hfile/HFileBlock$FSReader.readBlockData:(JJZZ)Lorg/apache/hadoop/hbase/io/hfile/HFileBlock;
     337: astore        27
     339: new           #99                 // class java/lang/StringBuilder
     342: dup
     343: invokespecial #100                // Method java/lang/StringBuilder."<init>":()V
     346: ldc           #232                // String Invalid block #
     348: invokevirtual #102                // Method java/lang/StringBuilder.append:(Ljava/lang/String;)Ljava/lang/StringBuilder;
     351: iload         26
     353: invokevirtual #105                // Method java/lang/StringBuilder.append:(I)Ljava/lang/StringBuilder;
     356: ldc           #233                // String 's type:
     358: invokevirtual #102                // Method java/lang/StringBuilder.append:(Ljava/lang/String;)Ljava/lang/StringBuilder;
     361: invokevirtual #107                // Method java/lang/StringBuilder.toString:()Ljava/lang/String;
     364: aload         17
     366: iload         26
     368: invokeinterface #23,  2           // InterfaceMethod java/util/List.get:(I)Ljava/lang/Object;
     373: aload         27
     375: invokevirtual #234                // Method org/apache/hadoop/hbase/io/hfile/HFileBlock.getBlockType:()Lorg/apache/hadoop/hbase/io/hfile/BlockType;
     378: invokestatic  #192                // Method org/junit/Assert.assertEquals:(Ljava/lang/String;Ljava/lang/Object;Ljava/lang/Object;)V
     381: new           #99                 // class java/lang/StringBuilder
     384: dup
     385: invokespecial #100                // Method java/lang/StringBuilder."<init>":()V
     388: ldc           #235                // String Invalid previous block offset for block
     390: invokevirtual #102                // Method java/lang/StringBuilder.append:(Ljava/lang/String;)Ljava/lang/StringBuilder;
     393: iload         26
     395: invokevirtual #105                // Method java/lang/StringBuilder.append:(I)Ljava/lang/StringBuilder;
     398: ldc           #236                // String  of type
     400: invokevirtual #102                // Method java/lang/StringBuilder.append:(Ljava/lang/String;)Ljava/lang/StringBuilder;
     403: aload         27
     405: invokevirtual #234                // Method org/apache/hadoop/hbase/io/hfile/HFileBlock.getBlockType:()Lorg/apache/hadoop/hbase/io/hfile/BlockType;
     408: invokevirtual #117                // Method java/lang/StringBuilder.append:(Ljava/lang/Object;)Ljava/lang/StringBuilder;
     411: ldc           #237                // String :
     413: invokevirtual #102                // Method java/lang/StringBuilder.append:(Ljava/lang/String;)Ljava/lang/StringBuilder;
     416: invokevirtual #107                // Method java/lang/StringBuilder.toString:()Ljava/lang/String;
     419: aload         16
     421: iload         26
     423: invokeinterface #23,  2           // InterfaceMethod java/util/List.get:(I)Ljava/lang/Object;
     428: checkcast     #230                // class java/lang/Long
     431: invokevirtual #231                // Method java/lang/Long.longValue:()J
     434: aload         27
     436: invokevirtual #238                // Method org/apache/hadoop/hbase/io/hfile/HFileBlock.getPrevBlockOffset:()J
     439: invokestatic  #239                // Method org/junit/Assert.assertEquals:(Ljava/lang/String;JJ)V
     442: aload         27
     444: invokevirtual #138                // Method org/apache/hadoop/hbase/io/hfile/HFileBlock.sanityCheck:()V
     447: lload         24
     449: aload         27
     451: invokevirtual #240                // Method org/apache/hadoop/hbase/io/hfile/HFileBlock.getOffset:()J
     454: invokestatic  #79                 // Method org/junit/Assert.assertEquals:(JJ)V
     457: aload         23
     459: lload         24
     461: aload         27
     463: invokevirtual #176                // Method org/apache/hadoop/hbase/io/hfile/HFileBlock.getOnDiskSizeWithHeader:()I
     466: i2l
     467: iload         8
     469: iconst_0
     470: invokeinterface #135,  7          // InterfaceMethod org/apache/hadoop/hbase/io/hfile/HFileBlock$FSReader.readBlockData:(JJZZ)Lorg/apache/hadoop/hbase/io/hfile/HFileBlock;
     475: astore        28
     477: aload         28
     479: invokevirtual #138                // Method org/apache/hadoop/hbase/io/hfile/HFileBlock.sanityCheck:()V
     482: aload         27
     484: invokevirtual #234                // Method org/apache/hadoop/hbase/io/hfile/HFileBlock.getBlockType:()Lorg/apache/hadoop/hbase/io/hfile/BlockType;
     487: aload         28
     489: invokevirtual #234                // Method org/apache/hadoop/hbase/io/hfile/HFileBlock.getBlockType:()Lorg/apache/hadoop/hbase/io/hfile/BlockType;
     492: invokestatic  #111                // Method org/junit/Assert.assertEquals:(Ljava/lang/Object;Ljava/lang/Object;)V
     495: aload         27
     497: invokevirtual #96                 // Method org/apache/hadoop/hbase/io/hfile/HFileBlock.getOnDiskSizeWithoutHeader:()I
     500: i2l
     501: aload         28
     503: invokevirtual #96                 // Method org/apache/hadoop/hbase/io/hfile/HFileBlock.getOnDiskSizeWithoutHeader:()I
     506: i2l
     507: invokestatic  #79                 // Method org/junit/Assert.assertEquals:(JJ)V
     510: aload         27
     512: invokevirtual #176                // Method org/apache/hadoop/hbase/io/hfile/HFileBlock.getOnDiskSizeWithHeader:()I
     515: i2l
     516: aload         28
     518: invokevirtual #176                // Method org/apache/hadoop/hbase/io/hfile/HFileBlock.getOnDiskSizeWithHeader:()I
     521: i2l
     522: invokestatic  #79                 // Method org/junit/Assert.assertEquals:(JJ)V
     525: aload         27
     527: invokevirtual #93                 // Method org/apache/hadoop/hbase/io/hfile/HFileBlock.getUncompressedSizeWithoutHeader:()I
     530: i2l
     531: aload         28
     533: invokevirtual #93                 // Method org/apache/hadoop/hbase/io/hfile/HFileBlock.getUncompressedSizeWithoutHeader:()I
     536: i2l
     537: invokestatic  #79                 // Method org/junit/Assert.assertEquals:(JJ)V
     540: aload         27
     542: invokevirtual #238                // Method org/apache/hadoop/hbase/io/hfile/HFileBlock.getPrevBlockOffset:()J
     545: aload         28
     547: invokevirtual #238                // Method org/apache/hadoop/hbase/io/hfile/HFileBlock.getPrevBlockOffset:()J
     550: invokestatic  #79                 // Method org/junit/Assert.assertEquals:(JJ)V
     553: lload         24
     555: aload         28
     557: invokevirtual #240                // Method org/apache/hadoop/hbase/io/hfile/HFileBlock.getOffset:()J
     560: invokestatic  #79                 // Method org/junit/Assert.assertEquals:(JJ)V
     563: aload         27
     565: invokevirtual #241                // Method org/apache/hadoop/hbase/io/hfile/HFileBlock.getBytesPerChecksum:()I
     568: i2l
     569: aload         28
     571: invokevirtual #241                // Method org/apache/hadoop/hbase/io/hfile/HFileBlock.getBytesPerChecksum:()I
     574: i2l
     575: invokestatic  #79                 // Method org/junit/Assert.assertEquals:(JJ)V
     578: aload         27
     580: invokevirtual #242                // Method org/apache/hadoop/hbase/io/hfile/HFileBlock.getOnDiskDataSizeWithHeader:()I
     583: i2l
     584: aload         28
     586: invokevirtual #242                // Method org/apache/hadoop/hbase/io/hfile/HFileBlock.getOnDiskDataSizeWithHeader:()I
     589: i2l
     590: invokestatic  #79                 // Method org/junit/Assert.assertEquals:(JJ)V
     593: lconst_0
     594: invokestatic  #137                // Method org/apache/hadoop/hbase/io/hfile/HFile.getAndResetChecksumFailuresCount:()J
     597: invokestatic  #79                 // Method org/junit/Assert.assertEquals:(JJ)V
     600: lload         24
     602: aload         27
     604: invokevirtual #176                // Method org/apache/hadoop/hbase/io/hfile/HFileBlock.getOnDiskSizeWithHeader:()I
     607: i2l
     608: ladd
     609: lstore        24
     611: iload         12
     613: ifeq          844
     616: aload         27
     618: aload         22
     620: aload         23
     622: invokevirtual #181                // Method org/apache/hadoop/hbase/io/hfile/HFileBlock.unpack:(Lorg/apache/hadoop/hbase/io/hfile/HFileContext;Lorg/apache/hadoop/hbase/io/hfile/HFileBlock$FSReader;)Lorg/apache/hadoop/hbase/io/hfile/HFileBlock;
     625: astore        27
     627: aload         27
     629: invokevirtual #243                // Method org/apache/hadoop/hbase/io/hfile/HFileBlock.getBufferReadOnly:()Lorg/apache/hadoop/hbase/nio/ByteBuff;
     632: astore        29
     634: aload         18
     636: iload         26
     638: invokeinterface #23,  2           // InterfaceMethod java/util/List.get:(I)Ljava/lang/Object;
     643: checkcast     #197                // class java/nio/ByteBuffer
     646: astore        30
     648: aload         29
     650: invokevirtual #218                // Method org/apache/hadoop/hbase/nio/ByteBuff.array:()[B
     653: aload         29
     655: invokevirtual #219                // Method org/apache/hadoop/hbase/nio/ByteBuff.arrayOffset:()I
     658: aload         29
     660: invokevirtual #214                // Method org/apache/hadoop/hbase/nio/ByteBuff.limit:()I
     663: aload         27
     665: invokevirtual #143                // Method org/apache/hadoop/hbase/io/hfile/HFileBlock.totalChecksumBytes:()I
     668: isub
     669: aload         30
     671: invokevirtual #169                // Method java/nio/ByteBuffer.array:()[B
     674: aload         30
     676: invokevirtual #244                // Method java/nio/ByteBuffer.arrayOffset:()I
     679: aload         30
     681: invokevirtual #245                // Method java/nio/ByteBuffer.limit:()I
     684: invokestatic  #246                // Method org/apache/hadoop/hbase/util/Bytes.compareTo:([BII[BII)I
     687: ifne          694
     690: iconst_1
     691: goto          695
     694: iconst_0
     695: istore        31
     697: ldc           #222                // String
     699: astore        32
     701: iload         31
     703: ifne          837
     706: new           #99                 // class java/lang/StringBuilder
     709: dup
     710: invokespecial #100                // Method java/lang/StringBuilder."<init>":()V
     713: ldc           #247                // String Expected bytes in block #
     715: invokevirtual #102                // Method java/lang/StringBuilder.append:(Ljava/lang/String;)Ljava/lang/StringBuilder;
     718: iload         26
     720: invokevirtual #105                // Method java/lang/StringBuilder.append:(I)Ljava/lang/StringBuilder;
     723: ldc           #248                // String  (algo=
     725: invokevirtual #102                // Method java/lang/StringBuilder.append:(Ljava/lang/String;)Ljava/lang/StringBuilder;
     728: aload         4
     730: invokevirtual #117                // Method java/lang/StringBuilder.append:(Ljava/lang/Object;)Ljava/lang/StringBuilder;
     733: ldc           #118                // String , pread=
     735: invokevirtual #102                // Method java/lang/StringBuilder.append:(Ljava/lang/String;)Ljava/lang/StringBuilder;
     738: iload         8
     740: invokevirtual #119                // Method java/lang/StringBuilder.append:(Z)Ljava/lang/StringBuilder;
     743: ldc           #249                // String , cacheOnWrite=
     745: invokevirtual #102                // Method java/lang/StringBuilder.append:(Ljava/lang/String;)Ljava/lang/StringBuilder;
     748: iload         12
     750: invokevirtual #119                // Method java/lang/StringBuilder.append:(Z)Ljava/lang/StringBuilder;
     753: ldc           #250                // String ):\n
     755: invokevirtual #102                // Method java/lang/StringBuilder.append:(Ljava/lang/String;)Ljava/lang/StringBuilder;
     758: invokevirtual #107                // Method java/lang/StringBuilder.toString:()Ljava/lang/String;
     761: astore        32
     763: new           #99                 // class java/lang/StringBuilder
     766: dup
     767: invokespecial #100                // Method java/lang/StringBuilder."<init>":()V
     770: aload         32
     772: invokevirtual #102                // Method java/lang/StringBuilder.append:(Ljava/lang/String;)Ljava/lang/StringBuilder;
     775: aload         30
     777: invokevirtual #169                // Method java/nio/ByteBuffer.array:()[B
     780: aload         30
     782: invokevirtual #244                // Method java/nio/ByteBuffer.arrayOffset:()I
     785: bipush        42
     787: aload         30
     789: invokevirtual #245                // Method java/nio/ByteBuffer.limit:()I
     792: invokestatic  #215                // Method java/lang/Math.min:(II)I
     795: invokestatic  #220                // Method org/apache/hadoop/hbase/util/Bytes.toStringBinary:([BII)Ljava/lang/String;
     798: invokevirtual #102                // Method java/lang/StringBuilder.append:(Ljava/lang/String;)Ljava/lang/StringBuilder;
     801: ldc           #251                // String , actual:\n
     803: invokevirtual #102                // Method java/lang/StringBuilder.append:(Ljava/lang/String;)Ljava/lang/StringBuilder;
     806: aload         29
     808: invokevirtual #218                // Method org/apache/hadoop/hbase/nio/ByteBuff.array:()[B
     811: aload         29
     813: invokevirtual #219                // Method org/apache/hadoop/hbase/nio/ByteBuff.arrayOffset:()I
     816: bipush        42
     818: aload         29
     820: invokevirtual #214                // Method org/apache/hadoop/hbase/nio/ByteBuff.limit:()I
     823: invokestatic  #215                // Method java/lang/Math.min:(II)I
     826: invokestatic  #220                // Method org/apache/hadoop/hbase/util/Bytes.toStringBinary:([BII)Ljava/lang/String;
     829: invokevirtual #102                // Method java/lang/StringBuilder.append:(Ljava/lang/String;)Ljava/lang/StringBuilder;
     832: invokevirtual #107                // Method java/lang/StringBuilder.toString:()Ljava/lang/String;
     835: astore        32
     837: aload         32
     839: iload         31
     841: invokestatic  #153                // Method org/junit/Assert.assertTrue:(Ljava/lang/String;Z)V
     844: iinc          26, 1
     847: goto          266
     850: lload         24
     852: aload_0
     853: getfield      #10                 // Field fs:Lorg/apache/hadoop/fs/FileSystem;
     856: aload         14
     858: invokevirtual #252                // Method org/apache/hadoop/fs/FileSystem.getFileStatus:(Lorg/apache/hadoop/fs/Path;)Lorg/apache/hadoop/fs/FileStatus;
     861: invokevirtual #253                // Method org/apache/hadoop/fs/FileStatus.getLen:()J
     864: invokestatic  #79                 // Method org/junit/Assert.assertEquals:(JJ)V
     867: aload         21
     869: invokevirtual #136                // Method org/apache/hadoop/fs/FSDataInputStream.close:()V
     872: iinc          11, 1
     875: goto          59
     878: iinc          7, 1
     881: goto          32
     884: iinc          3, 1
     887: goto          9
     890: return

  public void testConcurrentReading() throws java.lang.Exception;
    Code:
       0: aload_0
       1: invokevirtual #256                // Method testConcurrentReadingInternals:()V
       4: return

  protected void testConcurrentReadingInternals() throws java.io.IOException, java.lang.InterruptedException, java.util.concurrent.ExecutionException;
    Code:
       0: getstatic     #115                // Field COMPRESSION_ALGORITHMS:[Lorg/apache/hadoop/hbase/io/compress/Compression$Algorithm;
       3: astore_1
       4: aload_1
       5: arraylength
       6: istore_2
       7: iconst_0
       8: istore_3
       9: iload_3
      10: iload_2
      11: if_icmpge     284
      14: aload_1
      15: iload_3
      16: aaload
      17: astore        4
      19: new           #121                // class org/apache/hadoop/fs/Path
      22: dup
      23: getstatic     #7                  // Field TEST_UTIL:Lorg/apache/hadoop/hbase/HBaseTestingUtility;
      26: invokevirtual #122                // Method org/apache/hadoop/hbase/HBaseTestingUtility.getDataTestDir:()Lorg/apache/hadoop/fs/Path;
      29: ldc_w         #257                // String concurrent_reading
      32: invokespecial #124                // Method org/apache/hadoop/fs/Path."<init>":(Lorg/apache/hadoop/fs/Path;Ljava/lang/String;)V
      35: astore        5
      37: aload_0
      38: invokespecial #225                // Method defaultRandom:()Ljava/util/Random;
      41: astore        6
      43: new           #12                 // class java/util/ArrayList
      46: dup
      47: invokespecial #13                 // Method java/util/ArrayList."<init>":()V
      50: astore        7
      52: new           #12                 // class java/util/ArrayList
      55: dup
      56: invokespecial #13                 // Method java/util/ArrayList."<init>":()V
      59: astore        8
      61: aload_0
      62: aload         6
      64: aload         4
      66: aload         5
      68: aload         7
      70: aconst_null
      71: aload         8
      73: aconst_null
      74: invokespecial #228                // Method writeBlocks:(Ljava/util/Random;Lorg/apache/hadoop/hbase/io/compress/Compression$Algorithm;Lorg/apache/hadoop/fs/Path;Ljava/util/List;Ljava/util/List;Ljava/util/List;Ljava/util/List;)J
      77: pop2
      78: aload_0
      79: getfield      #10                 // Field fs:Lorg/apache/hadoop/fs/FileSystem;
      82: aload         5
      84: invokevirtual #129                // Method org/apache/hadoop/fs/FileSystem.open:(Lorg/apache/hadoop/fs/Path;)Lorg/apache/hadoop/fs/FSDataInputStream;
      87: astore        9
      89: aload_0
      90: getfield      #10                 // Field fs:Lorg/apache/hadoop/fs/FileSystem;
      93: aload         5
      95: invokevirtual #252                // Method org/apache/hadoop/fs/FileSystem.getFileStatus:(Lorg/apache/hadoop/fs/Path;)Lorg/apache/hadoop/fs/FileStatus;
      98: invokevirtual #253                // Method org/apache/hadoop/fs/FileStatus.getLen:()J
     101: lstore        10
     103: new           #64                 // class org/apache/hadoop/hbase/io/hfile/HFileContextBuilder
     106: dup
     107: invokespecial #65                 // Method org/apache/hadoop/hbase/io/hfile/HFileContextBuilder."<init>":()V
     110: iconst_1
     111: invokevirtual #130                // Method org/apache/hadoop/hbase/io/hfile/HFileContextBuilder.withHBaseCheckSum:(Z)Lorg/apache/hadoop/hbase/io/hfile/HFileContextBuilder;
     114: aload_0
     115: getfield      #4                  // Field includesMemstoreTS:Z
     118: invokevirtual #67                 // Method org/apache/hadoop/hbase/io/hfile/HFileContextBuilder.withIncludesMvcc:(Z)Lorg/apache/hadoop/hbase/io/hfile/HFileContextBuilder;
     121: aload_0
     122: getfield      #5                  // Field includesTag:Z
     125: invokevirtual #68                 // Method org/apache/hadoop/hbase/io/hfile/HFileContextBuilder.withIncludesTags:(Z)Lorg/apache/hadoop/hbase/io/hfile/HFileContextBuilder;
     128: aload         4
     130: invokevirtual #66                 // Method org/apache/hadoop/hbase/io/hfile/HFileContextBuilder.withCompression:(Lorg/apache/hadoop/hbase/io/compress/Compression$Algorithm;)Lorg/apache/hadoop/hbase/io/hfile/HFileContextBuilder;
     133: invokevirtual #71                 // Method org/apache/hadoop/hbase/io/hfile/HFileContextBuilder.build:()Lorg/apache/hadoop/hbase/io/hfile/HFileContext;
     136: astore        12
     138: new           #131                // class org/apache/hadoop/hbase/io/hfile/HFileBlock$FSReaderImpl
     141: dup
     142: aload         9
     144: lload         10
     146: aload         12
     148: invokespecial #132                // Method org/apache/hadoop/hbase/io/hfile/HFileBlock$FSReaderImpl."<init>":(Lorg/apache/hadoop/fs/FSDataInputStream;JLorg/apache/hadoop/hbase/io/hfile/HFileContext;)V
     151: astore        13
     153: bipush        26
     155: invokestatic  #258                // Method java/util/concurrent/Executors.newFixedThreadPool:(I)Ljava/util/concurrent/ExecutorService;
     158: astore        14
     160: new           #259                // class java/util/concurrent/ExecutorCompletionService
     163: dup
     164: aload         14
     166: invokespecial #260                // Method java/util/concurrent/ExecutorCompletionService."<init>":(Ljava/util/concurrent/Executor;)V
     169: astore        15
     171: iconst_0
     172: istore        16
     174: iload         16
     176: bipush        26
     178: if_icmpge     234
     181: aload         15
     183: new           #261                // class org/apache/hadoop/hbase/io/hfile/TestHFileBlock$BlockReaderThread
     186: dup
     187: aload_0
     188: new           #99                 // class java/lang/StringBuilder
     191: dup
     192: invokespecial #100                // Method java/lang/StringBuilder."<init>":()V
     195: ldc_w         #262                // String reader_
     198: invokevirtual #102                // Method java/lang/StringBuilder.append:(Ljava/lang/String;)Ljava/lang/StringBuilder;
     201: bipush        65
     203: iload         16
     205: iadd
     206: i2c
     207: invokevirtual #263                // Method java/lang/StringBuilder.append:(C)Ljava/lang/StringBuilder;
     210: invokevirtual #107                // Method java/lang/StringBuilder.toString:()Ljava/lang/String;
     213: aload         13
     215: aload         7
     217: aload         8
     219: lload         10
     221: invokespecial #264                // Method org/apache/hadoop/hbase/io/hfile/TestHFileBlock$BlockReaderThread."<init>":(Lorg/apache/hadoop/hbase/io/hfile/TestHFileBlock;Ljava/lang/String;Lorg/apache/hadoop/hbase/io/hfile/HFileBlock$FSReader;Ljava/util/List;Ljava/util/List;J)V
     224: invokevirtual #265                // Method java/util/concurrent/ExecutorCompletionService.submit:(Ljava/util/concurrent/Callable;)Ljava/util/concurrent/Future;
     227: pop
     228: iinc          16, 1
     231: goto          174
     234: iconst_0
     235: istore        16
     237: iload         16
     239: bipush        26
     241: if_icmpge     273
     244: aload         15
     246: invokevirtual #266                // Method java/util/concurrent/ExecutorCompletionService.take:()Ljava/util/concurrent/Future;
     249: astore        17
     251: aload         17
     253: invokeinterface #267,  1          // InterfaceMethod java/util/concurrent/Future.get:()Ljava/lang/Object;
     258: checkcast     #268                // class java/lang/Boolean
     261: invokevirtual #269                // Method java/lang/Boolean.booleanValue:()Z
     264: invokestatic  #98                 // Method org/junit/Assert.assertTrue:(Z)V
     267: iinc          16, 1
     270: goto          237
     273: aload         9
     275: invokevirtual #136                // Method org/apache/hadoop/fs/FSDataInputStream.close:()V
     278: iinc          3, 1
     281: goto          9
     284: return

  public void testBlockHeapSize();
    Code:
       0: aload_0
       1: invokevirtual #283                // Method testBlockHeapSizeInternals:()V
       4: return

  protected void testBlockHeapSizeInternals();
    Code:
       0: invokestatic  #284                // Method org/apache/hadoop/hbase/util/ClassSize.is32BitJVM:()Z
       3: ifeq          19
       6: ldc2_w        #285                // long 64l
       9: getstatic     #287                // Field org/apache/hadoop/hbase/io/hfile/HFileBlock.MULTI_BYTE_BUFFER_HEAP_SIZE:I
      12: i2l
      13: invokestatic  #79                 // Method org/junit/Assert.assertEquals:(JJ)V
      16: goto          29
      19: ldc2_w        #288                // long 72l
      22: getstatic     #287                // Field org/apache/hadoop/hbase/io/hfile/HFileBlock.MULTI_BYTE_BUFFER_HEAP_SIZE:I
      25: i2l
      26: invokestatic  #79                 // Method org/junit/Assert.assertEquals:(JJ)V
      29: iconst_3
      30: newarray       int
      32: dup
      33: iconst_0
      34: bipush        100
      36: iastore
      37: dup
      38: iconst_1
      39: sipush        256
      42: iastore
      43: dup
      44: iconst_2
      45: sipush        12345
      48: iastore
      49: astore_1
      50: aload_1
      51: arraylength
      52: istore_2
      53: iconst_0
      54: istore_3
      55: iload_3
      56: iload_2
      57: if_icmpge     295
      60: aload_1
      61: iload_3
      62: iaload
      63: istore        4
      65: bipush        33
      67: iload         4
      69: iadd
      70: newarray       byte
      72: astore        5
      74: aload         5
      76: iconst_0
      77: iload         4
      79: invokestatic  #290                // Method java/nio/ByteBuffer.wrap:([BII)Ljava/nio/ByteBuffer;
      82: astore        6
      84: new           #64                 // class org/apache/hadoop/hbase/io/hfile/HFileContextBuilder
      87: dup
      88: invokespecial #65                 // Method org/apache/hadoop/hbase/io/hfile/HFileContextBuilder."<init>":()V
      91: aload_0
      92: getfield      #4                  // Field includesMemstoreTS:Z
      95: invokevirtual #67                 // Method org/apache/hadoop/hbase/io/hfile/HFileContextBuilder.withIncludesMvcc:(Z)Lorg/apache/hadoop/hbase/io/hfile/HFileContextBuilder;
      98: aload_0
      99: getfield      #5                  // Field includesTag:Z
     102: invokevirtual #68                 // Method org/apache/hadoop/hbase/io/hfile/HFileContextBuilder.withIncludesTags:(Z)Lorg/apache/hadoop/hbase/io/hfile/HFileContextBuilder;
     105: iconst_0
     106: invokevirtual #130                // Method org/apache/hadoop/hbase/io/hfile/HFileContextBuilder.withHBaseCheckSum:(Z)Lorg/apache/hadoop/hbase/io/hfile/HFileContextBuilder;
     109: getstatic     #91                 // Field org/apache/hadoop/hbase/io/compress/Compression$Algorithm.NONE:Lorg/apache/hadoop/hbase/io/compress/Compression$Algorithm;
     112: invokevirtual #66                 // Method org/apache/hadoop/hbase/io/hfile/HFileContextBuilder.withCompression:(Lorg/apache/hadoop/hbase/io/compress/Compression$Algorithm;)Lorg/apache/hadoop/hbase/io/hfile/HFileContextBuilder;
     115: sipush        16384
     118: invokevirtual #70                 // Method org/apache/hadoop/hbase/io/hfile/HFileContextBuilder.withBytesPerCheckSum:(I)Lorg/apache/hadoop/hbase/io/hfile/HFileContextBuilder;
     121: getstatic     #291                // Field org/apache/hadoop/hbase/util/ChecksumType.NULL:Lorg/apache/hadoop/hbase/util/ChecksumType;
     124: invokevirtual #292                // Method org/apache/hadoop/hbase/io/hfile/HFileContextBuilder.withChecksumType:(Lorg/apache/hadoop/hbase/util/ChecksumType;)Lorg/apache/hadoop/hbase/io/hfile/HFileContextBuilder;
     127: invokevirtual #71                 // Method org/apache/hadoop/hbase/io/hfile/HFileContextBuilder.build:()Lorg/apache/hadoop/hbase/io/hfile/HFileContext;
     130: astore        7
     132: new           #208                // class org/apache/hadoop/hbase/io/hfile/HFileBlock
     135: dup
     136: getstatic     #63                 // Field org/apache/hadoop/hbase/io/hfile/BlockType.DATA:Lorg/apache/hadoop/hbase/io/hfile/BlockType;
     139: iload         4
     141: iload         4
     143: ldc2_w        #133                // long -1l
     146: aload         6
     148: iconst_1
     149: ldc2_w        #133                // long -1l
     152: iconst_0
     153: iconst_m1
     154: aload         7
     156: invokespecial #293                // Method org/apache/hadoop/hbase/io/hfile/HFileBlock."<init>":(Lorg/apache/hadoop/hbase/io/hfile/BlockType;IIJLjava/nio/ByteBuffer;ZJIILorg/apache/hadoop/hbase/io/hfile/HFileContext;)V
     159: astore        8
     161: new           #294                // class org/apache/hadoop/hbase/nio/MultiByteBuff
     164: dup
     165: iconst_1
     166: anewarray     #197                // class java/nio/ByteBuffer
     169: dup
     170: iconst_0
     171: aload         6
     173: aastore
     174: invokespecial #295                // Method org/apache/hadoop/hbase/nio/MultiByteBuff."<init>":([Ljava/nio/ByteBuffer;)V
     177: invokevirtual #296                // Method java/lang/Object.getClass:()Ljava/lang/Class;
     180: iconst_1
     181: invokestatic  #297                // Method org/apache/hadoop/hbase/util/ClassSize.estimateBase:(Ljava/lang/Class;Z)J
     184: ldc2_w        #298                // long 33l
     187: ladd
     188: iload         4
     190: i2l
     191: ladd
     192: invokestatic  #300                // Method org/apache/hadoop/hbase/util/ClassSize.align:(J)J
     195: lstore        9
     197: ldc_w         #301                // class org/apache/hadoop/hbase/io/hfile/HFileContext
     200: iconst_1
     201: invokestatic  #297                // Method org/apache/hadoop/hbase/util/ClassSize.estimateBase:(Ljava/lang/Class;Z)J
     204: invokestatic  #300                // Method org/apache/hadoop/hbase/util/ClassSize.align:(J)J
     207: lstore        11
     209: ldc           #208                // class org/apache/hadoop/hbase/io/hfile/HFileBlock
     211: iconst_1
     212: invokestatic  #297                // Method org/apache/hadoop/hbase/util/ClassSize.estimateBase:(Ljava/lang/Class;Z)J
     215: invokestatic  #300                // Method org/apache/hadoop/hbase/util/ClassSize.align:(J)J
     218: lstore        13
     220: lload         13
     222: lload         9
     224: ladd
     225: lload         11
     227: ladd
     228: lstore        15
     230: new           #99                 // class java/lang/StringBuilder
     233: dup
     234: invokespecial #100                // Method java/lang/StringBuilder."<init>":()V
     237: ldc_w         #302                // String Block data size:
     240: invokevirtual #102                // Method java/lang/StringBuilder.append:(Ljava/lang/String;)Ljava/lang/StringBuilder;
     243: iload         4
     245: invokevirtual #105                // Method java/lang/StringBuilder.append:(I)Ljava/lang/StringBuilder;
     248: ldc_w         #303                // String , byte buffer expected size:
     251: invokevirtual #102                // Method java/lang/StringBuilder.append:(Ljava/lang/String;)Ljava/lang/StringBuilder;
     254: lload         9
     256: invokevirtual #183                // Method java/lang/StringBuilder.append:(J)Ljava/lang/StringBuilder;
     259: ldc_w         #304                // String , HFileBlock class expected size:
     262: invokevirtual #102                // Method java/lang/StringBuilder.append:(Ljava/lang/String;)Ljava/lang/StringBuilder;
     265: lload         13
     267: invokevirtual #183                // Method java/lang/StringBuilder.append:(J)Ljava/lang/StringBuilder;
     270: ldc_w         #305                // String ;
     273: invokevirtual #102                // Method java/lang/StringBuilder.append:(Ljava/lang/String;)Ljava/lang/StringBuilder;
     276: invokevirtual #107                // Method java/lang/StringBuilder.toString:()Ljava/lang/String;
     279: lload         15
     281: aload         8
     283: invokevirtual #180                // Method org/apache/hadoop/hbase/io/hfile/HFileBlock.heapSize:()J
     286: invokestatic  #239                // Method org/junit/Assert.assertEquals:(Ljava/lang/String;JJ)V
     289: iinc          3, 1
     292: goto          55
     295: return

  public void testSerializeWithoutNextBlockMetadata();
    Code:
       0: bipush        100
       2: istore_1
       3: bipush        33
       5: iload_1
       6: iadd
       7: istore_2
       8: iload_2
       9: newarray       byte
      11: astore_3
      12: aload_3
      13: iconst_0
      14: iload_1
      15: invokestatic  #290                // Method java/nio/ByteBuffer.wrap:([BII)Ljava/nio/ByteBuffer;
      18: astore        4
      20: new           #64                 // class org/apache/hadoop/hbase/io/hfile/HFileContextBuilder
      23: dup
      24: invokespecial #65                 // Method org/apache/hadoop/hbase/io/hfile/HFileContextBuilder."<init>":()V
      27: invokevirtual #71                 // Method org/apache/hadoop/hbase/io/hfile/HFileContextBuilder.build:()Lorg/apache/hadoop/hbase/io/hfile/HFileContext;
      30: astore        5
      32: new           #208                // class org/apache/hadoop/hbase/io/hfile/HFileBlock
      35: dup
      36: getstatic     #63                 // Field org/apache/hadoop/hbase/io/hfile/BlockType.DATA:Lorg/apache/hadoop/hbase/io/hfile/BlockType;
      39: iload_1
      40: iload_1
      41: ldc2_w        #133                // long -1l
      44: aload         4
      46: iconst_1
      47: ldc2_w        #133                // long -1l
      50: bipush        52
      52: iconst_m1
      53: aload         5
      55: invokespecial #293                // Method org/apache/hadoop/hbase/io/hfile/HFileBlock."<init>":(Lorg/apache/hadoop/hbase/io/hfile/BlockType;IIJLjava/nio/ByteBuffer;ZJIILorg/apache/hadoop/hbase/io/hfile/HFileContext;)V
      58: astore        6
      60: new           #208                // class org/apache/hadoop/hbase/io/hfile/HFileBlock
      63: dup
      64: getstatic     #63                 // Field org/apache/hadoop/hbase/io/hfile/BlockType.DATA:Lorg/apache/hadoop/hbase/io/hfile/BlockType;
      67: iload_1
      68: iload_1
      69: ldc2_w        #133                // long -1l
      72: aload         4
      74: iconst_1
      75: ldc2_w        #133                // long -1l
      78: iconst_m1
      79: iconst_m1
      80: aload         5
      82: invokespecial #293                // Method org/apache/hadoop/hbase/io/hfile/HFileBlock."<init>":(Lorg/apache/hadoop/hbase/io/hfile/BlockType;IIJLjava/nio/ByteBuffer;ZJIILorg/apache/hadoop/hbase/io/hfile/HFileContext;)V
      85: astore        7
      87: iload_2
      88: invokestatic  #203                // Method java/nio/ByteBuffer.allocate:(I)Ljava/nio/ByteBuffer;
      91: astore        8
      93: iload_2
      94: invokestatic  #203                // Method java/nio/ByteBuffer.allocate:(I)Ljava/nio/ByteBuffer;
      97: astore        9
      99: aload         6
     101: aload         8
     103: iconst_1
     104: invokevirtual #204                // Method org/apache/hadoop/hbase/io/hfile/HFileBlock.serialize:(Ljava/nio/ByteBuffer;Z)V
     107: aload         7
     109: aload         9
     111: iconst_1
     112: invokevirtual #204                // Method org/apache/hadoop/hbase/io/hfile/HFileBlock.serialize:(Ljava/nio/ByteBuffer;Z)V
     115: aload         8
     117: aload         9
     119: invokestatic  #306                // Method org/junit/Assert.assertNotEquals:(Ljava/lang/Object;Ljava/lang/Object;)V
     122: aload         8
     124: invokevirtual #307                // Method java/nio/ByteBuffer.clear:()Ljava/nio/Buffer;
     127: pop
     128: aload         9
     130: invokevirtual #307                // Method java/nio/ByteBuffer.clear:()Ljava/nio/Buffer;
     133: pop
     134: aload         6
     136: aload         8
     138: iconst_0
     139: invokevirtual #204                // Method org/apache/hadoop/hbase/io/hfile/HFileBlock.serialize:(Ljava/nio/ByteBuffer;Z)V
     142: aload         7
     144: aload         9
     146: iconst_0
     147: invokevirtual #204                // Method org/apache/hadoop/hbase/io/hfile/HFileBlock.serialize:(Ljava/nio/ByteBuffer;Z)V
     150: aload         8
     152: aload         9
     154: invokestatic  #111                // Method org/junit/Assert.assertEquals:(Ljava/lang/Object;Ljava/lang/Object;)V
     157: return

  static org.slf4j.Logger access$000();
    Code:
       0: getstatic     #2                  // Field LOG:Lorg/slf4j/Logger;
       3: areturn

  static {};
    Code:
       0: ldc           #1                  // class org/apache/hadoop/hbase/io/hfile/TestHFileBlock
       2: invokestatic  #308                // Method org/apache/hadoop/hbase/HBaseClassTestRule.forClass:(Ljava/lang/Class;)Lorg/apache/hadoop/hbase/HBaseClassTestRule;
       5: putstatic     #309                // Field CLASS_RULE:Lorg/apache/hadoop/hbase/HBaseClassTestRule;
       8: iconst_2
       9: newarray       boolean
      11: dup
      12: iconst_0
      13: iconst_0
      14: bastore
      15: dup
      16: iconst_1
      17: iconst_1
      18: bastore
      19: putstatic     #224                // Field BOOLEAN_VALUES:[Z
      22: ldc           #1                  // class org/apache/hadoop/hbase/io/hfile/TestHFileBlock
      24: invokestatic  #310                // Method org/slf4j/LoggerFactory.getLogger:(Ljava/lang/Class;)Lorg/slf4j/Logger;
      27: putstatic     #2                  // Field LOG:Lorg/slf4j/Logger;
      30: iconst_2
      31: anewarray     #311                // class org/apache/hadoop/hbase/io/compress/Compression$Algorithm
      34: dup
      35: iconst_0
      36: getstatic     #91                 // Field org/apache/hadoop/hbase/io/compress/Compression$Algorithm.NONE:Lorg/apache/hadoop/hbase/io/compress/Compression$Algorithm;
      39: aastore
      40: dup
      41: iconst_1
      42: getstatic     #108                // Field org/apache/hadoop/hbase/io/compress/Compression$Algorithm.GZ:Lorg/apache/hadoop/hbase/io/compress/Compression$Algorithm;
      45: aastore
      46: putstatic     #115                // Field COMPRESSION_ALGORITHMS:[Lorg/apache/hadoop/hbase/io/compress/Compression$Algorithm;
      49: bipush        50
      51: putstatic     #18                 // Field NUM_KEYVALUES:I
      54: bipush        10
      56: putstatic     #26                 // Field FIELD_LENGTH:I
      59: ldc_w         #312                // float 0.6f
      62: putstatic     #20                 // Field CHANCE_TO_REPEAT:F
      65: new           #313                // class org/apache/hadoop/hbase/HBaseTestingUtility
      68: dup
      69: invokespecial #314                // Method org/apache/hadoop/hbase/HBaseTestingUtility."<init>":()V
      72: putstatic     #7                  // Field TEST_UTIL:Lorg/apache/hadoop/hbase/HBaseTestingUtility;
      75: return
}
