Compiled from "TestCacheConfig.java"
class org.apache.hadoop.hbase.io.hfile.TestCacheConfig$Deserializer implements org.apache.hadoop.hbase.io.hfile.CacheableDeserializer<org.apache.hadoop.hbase.io.hfile.Cacheable> {
  org.apache.hadoop.hbase.io.hfile.TestCacheConfig$Deserializer(org.apache.hadoop.hbase.io.hfile.Cacheable);
    Code:
       0: aload_0
       1: invokespecial #1                  // Method java/lang/Object."<init>":()V
       4: aload_0
       5: iconst_0
       6: putfield      #2                  // Field deserializedIdentifier:I
       9: aload_0
      10: aload_0
      11: invokestatic  #3                  // Method org/apache/hadoop/hbase/io/hfile/CacheableDeserializerIdManager.registerDeserializer:(Lorg/apache/hadoop/hbase/io/hfile/CacheableDeserializer;)I
      14: putfield      #2                  // Field deserializedIdentifier:I
      17: aload_0
      18: aload_1
      19: putfield      #4                  // Field cacheable:Lorg/apache/hadoop/hbase/io/hfile/Cacheable;
      22: return

  public int getDeserialiserIdentifier();
    Code:
       0: aload_0
       1: getfield      #2                  // Field deserializedIdentifier:I
       4: ireturn

  public org.apache.hadoop.hbase.io.hfile.Cacheable deserialize(org.apache.hadoop.hbase.nio.ByteBuff, boolean, org.apache.hadoop.hbase.io.hfile.Cacheable$MemoryType) throws java.io.IOException;
    Code:
       0: invokestatic  #5                  // Method org/apache/hadoop/hbase/io/hfile/TestCacheConfig.access$000:()Lorg/slf4j/Logger;
       3: new           #6                  // class java/lang/StringBuilder
       6: dup
       7: invokespecial #7                  // Method java/lang/StringBuilder."<init>":()V
      10: ldc           #8                  // String Deserialized
      12: invokevirtual #9                  // Method java/lang/StringBuilder.append:(Ljava/lang/String;)Ljava/lang/StringBuilder;
      15: aload_1
      16: invokevirtual #10                 // Method java/lang/StringBuilder.append:(Ljava/lang/Object;)Ljava/lang/StringBuilder;
      19: ldc           #11                 // String , reuse=
      21: invokevirtual #9                  // Method java/lang/StringBuilder.append:(Ljava/lang/String;)Ljava/lang/StringBuilder;
      24: iload_2
      25: invokevirtual #12                 // Method java/lang/StringBuilder.append:(Z)Ljava/lang/StringBuilder;
      28: invokevirtual #13                 // Method java/lang/StringBuilder.toString:()Ljava/lang/String;
      31: invokeinterface #14,  2           // InterfaceMethod org/slf4j/Logger.info:(Ljava/lang/String;)V
      36: aload_0
      37: getfield      #4                  // Field cacheable:Lorg/apache/hadoop/hbase/io/hfile/Cacheable;
      40: areturn

  public org.apache.hadoop.hbase.io.hfile.Cacheable deserialize(org.apache.hadoop.hbase.nio.ByteBuff) throws java.io.IOException;
    Code:
       0: invokestatic  #5                  // Method org/apache/hadoop/hbase/io/hfile/TestCacheConfig.access$000:()Lorg/slf4j/Logger;
       3: new           #6                  // class java/lang/StringBuilder
       6: dup
       7: invokespecial #7                  // Method java/lang/StringBuilder."<init>":()V
      10: ldc           #8                  // String Deserialized
      12: invokevirtual #9                  // Method java/lang/StringBuilder.append:(Ljava/lang/String;)Ljava/lang/StringBuilder;
      15: aload_1
      16: invokevirtual #10                 // Method java/lang/StringBuilder.append:(Ljava/lang/Object;)Ljava/lang/StringBuilder;
      19: invokevirtual #13                 // Method java/lang/StringBuilder.toString:()Ljava/lang/String;
      22: invokeinterface #14,  2           // InterfaceMethod org/slf4j/Logger.info:(Ljava/lang/String;)V
      27: aload_0
      28: getfield      #4                  // Field cacheable:Lorg/apache/hadoop/hbase/io/hfile/Cacheable;
      31: areturn
}
