Compiled from "TestDynamicClassLoader.java"
public class org.apache.hadoop.hbase.util.TestDynamicClassLoader {
  public static final org.apache.hadoop.hbase.HBaseClassTestRule CLASS_RULE;

  public org.apache.hadoop.hbase.util.TestDynamicClassLoader();
    Code:
       0: aload_0
       1: invokespecial #1                  // Method java/lang/Object."<init>":()V
       4: return

  public void initializeConfiguration();
    Code:
       0: aload_0
       1: new           #2                  // class org/apache/hadoop/conf/Configuration
       4: dup
       5: getstatic     #3                  // Field TEST_UTIL:Lorg/apache/hadoop/hbase/HBaseCommonTestingUtility;
       8: invokevirtual #4                  // Method org/apache/hadoop/hbase/HBaseCommonTestingUtility.getConfiguration:()Lorg/apache/hadoop/conf/Configuration;
      11: invokespecial #5                  // Method org/apache/hadoop/conf/Configuration."<init>":(Lorg/apache/hadoop/conf/Configuration;)V
      14: putfield      #6                  // Field conf:Lorg/apache/hadoop/conf/Configuration;
      17: return

  public void testLoadClassFromLocalPath() throws java.lang.Exception;
    Code:
       0: ldc           #7                  // class org/apache/hadoop/hbase/util/TestDynamicClassLoader
       2: invokevirtual #8                  // Method java/lang/Class.getClassLoader:()Ljava/lang/ClassLoader;
       5: astore_1
       6: new           #9                  // class org/apache/hadoop/hbase/util/DynamicClassLoader
       9: dup
      10: aload_0
      11: getfield      #6                  // Field conf:Lorg/apache/hadoop/conf/Configuration;
      14: aload_1
      15: invokespecial #10                 // Method org/apache/hadoop/hbase/util/DynamicClassLoader."<init>":(Lorg/apache/hadoop/conf/Configuration;Ljava/lang/ClassLoader;)V
      18: astore_2
      19: ldc           #11                 // String TestLoadClassFromLocalPath
      21: astore_3
      22: aload_0
      23: aload_3
      24: invokespecial #12                 // Method deleteClass:(Ljava/lang/String;)V
      27: aload_2
      28: aload_3
      29: invokevirtual #13                 // Method org/apache/hadoop/hbase/util/DynamicClassLoader.loadClass:(Ljava/lang/String;)Ljava/lang/Class;
      32: pop
      33: new           #14                 // class java/lang/StringBuilder
      36: dup
      37: invokespecial #15                 // Method java/lang/StringBuilder."<init>":()V
      40: ldc           #16                 // String Should not be able to load class
      42: invokevirtual #17                 // Method java/lang/StringBuilder.append:(Ljava/lang/String;)Ljava/lang/StringBuilder;
      45: aload_3
      46: invokevirtual #17                 // Method java/lang/StringBuilder.append:(Ljava/lang/String;)Ljava/lang/StringBuilder;
      49: invokevirtual #18                 // Method java/lang/StringBuilder.toString:()Ljava/lang/String;
      52: invokestatic  #19                 // Method org/junit/Assert.fail:(Ljava/lang/String;)V
      55: goto          60
      58: astore        4
      60: getstatic     #3                  // Field TEST_UTIL:Lorg/apache/hadoop/hbase/HBaseCommonTestingUtility;
      63: invokevirtual #21                 // Method org/apache/hadoop/hbase/HBaseCommonTestingUtility.getDataTestDir:()Lorg/apache/hadoop/fs/Path;
      66: invokevirtual #22                 // Method org/apache/hadoop/fs/Path.toString:()Ljava/lang/String;
      69: astore        4
      71: aload         4
      73: aload_3
      74: aconst_null
      75: aload_0
      76: getfield      #6                  // Field conf:Lorg/apache/hadoop/conf/Configuration;
      79: invokestatic  #23                 // Method org/apache/hadoop/hbase/util/ClassLoaderTestHelper.localDirPath:(Lorg/apache/hadoop/conf/Configuration;)Ljava/lang/String;
      82: invokestatic  #24                 // Method org/apache/hadoop/hbase/util/ClassLoaderTestHelper.buildJar:(Ljava/lang/String;Ljava/lang/String;Ljava/lang/String;Ljava/lang/String;)Ljava/io/File;
      85: pop
      86: aload_2
      87: aload_3
      88: invokevirtual #13                 // Method org/apache/hadoop/hbase/util/DynamicClassLoader.loadClass:(Ljava/lang/String;)Ljava/lang/Class;
      91: pop
      92: goto          134
      95: astore        4
      97: getstatic     #25                 // Field LOG:Lorg/slf4j/Logger;
     100: new           #14                 // class java/lang/StringBuilder
     103: dup
     104: invokespecial #15                 // Method java/lang/StringBuilder."<init>":()V
     107: ldc           #26                 // String Should be able to load class
     109: invokevirtual #17                 // Method java/lang/StringBuilder.append:(Ljava/lang/String;)Ljava/lang/StringBuilder;
     112: aload_3
     113: invokevirtual #17                 // Method java/lang/StringBuilder.append:(Ljava/lang/String;)Ljava/lang/StringBuilder;
     116: invokevirtual #18                 // Method java/lang/StringBuilder.toString:()Ljava/lang/String;
     119: aload         4
     121: invokeinterface #27,  3           // InterfaceMethod org/slf4j/Logger.error:(Ljava/lang/String;Ljava/lang/Throwable;)V
     126: aload         4
     128: invokevirtual #28                 // Method java/lang/ClassNotFoundException.getMessage:()Ljava/lang/String;
     131: invokestatic  #19                 // Method org/junit/Assert.fail:(Ljava/lang/String;)V
     134: return
    Exception table:
       from    to  target type
          27    55    58   Class java/lang/ClassNotFoundException
          60    92    95   Class java/lang/ClassNotFoundException

  public void testLoadClassFromAnotherPath() throws java.lang.Exception;
    Code:
       0: ldc           #7                  // class org/apache/hadoop/hbase/util/TestDynamicClassLoader
       2: invokevirtual #8                  // Method java/lang/Class.getClassLoader:()Ljava/lang/ClassLoader;
       5: astore_1
       6: new           #9                  // class org/apache/hadoop/hbase/util/DynamicClassLoader
       9: dup
      10: aload_0
      11: getfield      #6                  // Field conf:Lorg/apache/hadoop/conf/Configuration;
      14: aload_1
      15: invokespecial #10                 // Method org/apache/hadoop/hbase/util/DynamicClassLoader."<init>":(Lorg/apache/hadoop/conf/Configuration;Ljava/lang/ClassLoader;)V
      18: astore_2
      19: ldc           #29                 // String TestLoadClassFromAnotherPath
      21: astore_3
      22: aload_0
      23: aload_3
      24: invokespecial #12                 // Method deleteClass:(Ljava/lang/String;)V
      27: aload_2
      28: aload_3
      29: invokevirtual #13                 // Method org/apache/hadoop/hbase/util/DynamicClassLoader.loadClass:(Ljava/lang/String;)Ljava/lang/Class;
      32: pop
      33: new           #14                 // class java/lang/StringBuilder
      36: dup
      37: invokespecial #15                 // Method java/lang/StringBuilder."<init>":()V
      40: ldc           #16                 // String Should not be able to load class
      42: invokevirtual #17                 // Method java/lang/StringBuilder.append:(Ljava/lang/String;)Ljava/lang/StringBuilder;
      45: aload_3
      46: invokevirtual #17                 // Method java/lang/StringBuilder.append:(Ljava/lang/String;)Ljava/lang/StringBuilder;
      49: invokevirtual #18                 // Method java/lang/StringBuilder.toString:()Ljava/lang/String;
      52: invokestatic  #19                 // Method org/junit/Assert.fail:(Ljava/lang/String;)V
      55: goto          60
      58: astore        4
      60: getstatic     #3                  // Field TEST_UTIL:Lorg/apache/hadoop/hbase/HBaseCommonTestingUtility;
      63: invokevirtual #21                 // Method org/apache/hadoop/hbase/HBaseCommonTestingUtility.getDataTestDir:()Lorg/apache/hadoop/fs/Path;
      66: invokevirtual #22                 // Method org/apache/hadoop/fs/Path.toString:()Ljava/lang/String;
      69: astore        4
      71: aload         4
      73: aload_3
      74: aconst_null
      75: invokestatic  #30                 // Method org/apache/hadoop/hbase/util/ClassLoaderTestHelper.buildJar:(Ljava/lang/String;Ljava/lang/String;Ljava/lang/String;)Ljava/io/File;
      78: pop
      79: aload_2
      80: aload_3
      81: invokevirtual #13                 // Method org/apache/hadoop/hbase/util/DynamicClassLoader.loadClass:(Ljava/lang/String;)Ljava/lang/Class;
      84: pop
      85: goto          127
      88: astore        4
      90: getstatic     #25                 // Field LOG:Lorg/slf4j/Logger;
      93: new           #14                 // class java/lang/StringBuilder
      96: dup
      97: invokespecial #15                 // Method java/lang/StringBuilder."<init>":()V
     100: ldc           #26                 // String Should be able to load class
     102: invokevirtual #17                 // Method java/lang/StringBuilder.append:(Ljava/lang/String;)Ljava/lang/StringBuilder;
     105: aload_3
     106: invokevirtual #17                 // Method java/lang/StringBuilder.append:(Ljava/lang/String;)Ljava/lang/StringBuilder;
     109: invokevirtual #18                 // Method java/lang/StringBuilder.toString:()Ljava/lang/String;
     112: aload         4
     114: invokeinterface #27,  3           // InterfaceMethod org/slf4j/Logger.error:(Ljava/lang/String;Ljava/lang/Throwable;)V
     119: aload         4
     121: invokevirtual #28                 // Method java/lang/ClassNotFoundException.getMessage:()Ljava/lang/String;
     124: invokestatic  #19                 // Method org/junit/Assert.fail:(Ljava/lang/String;)V
     127: return
    Exception table:
       from    to  target type
          27    55    58   Class java/lang/ClassNotFoundException
          60    85    88   Class java/lang/ClassNotFoundException

  public void testLoadClassFromLocalPathWithDynamicDirOff() throws java.lang.Exception;
    Code:
       0: aload_0
       1: getfield      #6                  // Field conf:Lorg/apache/hadoop/conf/Configuration;
       4: ldc           #31                 // String hbase.use.dynamic.jars
       6: iconst_0
       7: invokevirtual #32                 // Method org/apache/hadoop/conf/Configuration.setBoolean:(Ljava/lang/String;Z)V
      10: ldc           #7                  // class org/apache/hadoop/hbase/util/TestDynamicClassLoader
      12: invokevirtual #8                  // Method java/lang/Class.getClassLoader:()Ljava/lang/ClassLoader;
      15: astore_1
      16: new           #9                  // class org/apache/hadoop/hbase/util/DynamicClassLoader
      19: dup
      20: aload_0
      21: getfield      #6                  // Field conf:Lorg/apache/hadoop/conf/Configuration;
      24: aload_1
      25: invokespecial #10                 // Method org/apache/hadoop/hbase/util/DynamicClassLoader."<init>":(Lorg/apache/hadoop/conf/Configuration;Ljava/lang/ClassLoader;)V
      28: astore_2
      29: ldc           #11                 // String TestLoadClassFromLocalPath
      31: astore_3
      32: aload_0
      33: aload_3
      34: invokespecial #12                 // Method deleteClass:(Ljava/lang/String;)V
      37: getstatic     #3                  // Field TEST_UTIL:Lorg/apache/hadoop/hbase/HBaseCommonTestingUtility;
      40: invokevirtual #21                 // Method org/apache/hadoop/hbase/HBaseCommonTestingUtility.getDataTestDir:()Lorg/apache/hadoop/fs/Path;
      43: invokevirtual #22                 // Method org/apache/hadoop/fs/Path.toString:()Ljava/lang/String;
      46: astore        4
      48: aload         4
      50: aload_3
      51: aconst_null
      52: aload_0
      53: getfield      #6                  // Field conf:Lorg/apache/hadoop/conf/Configuration;
      56: invokestatic  #23                 // Method org/apache/hadoop/hbase/util/ClassLoaderTestHelper.localDirPath:(Lorg/apache/hadoop/conf/Configuration;)Ljava/lang/String;
      59: invokestatic  #24                 // Method org/apache/hadoop/hbase/util/ClassLoaderTestHelper.buildJar:(Ljava/lang/String;Ljava/lang/String;Ljava/lang/String;Ljava/lang/String;)Ljava/io/File;
      62: pop
      63: aload_2
      64: aload_3
      65: invokevirtual #13                 // Method org/apache/hadoop/hbase/util/DynamicClassLoader.loadClass:(Ljava/lang/String;)Ljava/lang/Class;
      68: pop
      69: new           #14                 // class java/lang/StringBuilder
      72: dup
      73: invokespecial #15                 // Method java/lang/StringBuilder."<init>":()V
      76: ldc           #16                 // String Should not be able to load class
      78: invokevirtual #17                 // Method java/lang/StringBuilder.append:(Ljava/lang/String;)Ljava/lang/StringBuilder;
      81: aload_3
      82: invokevirtual #17                 // Method java/lang/StringBuilder.append:(Ljava/lang/String;)Ljava/lang/StringBuilder;
      85: invokevirtual #18                 // Method java/lang/StringBuilder.toString:()Ljava/lang/String;
      88: invokestatic  #19                 // Method org/junit/Assert.fail:(Ljava/lang/String;)V
      91: goto          96
      94: astore        4
      96: return
    Exception table:
       from    to  target type
          37    91    94   Class java/lang/ClassNotFoundException

  static {};
    Code:
       0: ldc           #7                  // class org/apache/hadoop/hbase/util/TestDynamicClassLoader
       2: invokestatic  #43                 // Method org/apache/hadoop/hbase/HBaseClassTestRule.forClass:(Ljava/lang/Class;)Lorg/apache/hadoop/hbase/HBaseClassTestRule;
       5: putstatic     #44                 // Field CLASS_RULE:Lorg/apache/hadoop/hbase/HBaseClassTestRule;
       8: ldc           #7                  // class org/apache/hadoop/hbase/util/TestDynamicClassLoader
      10: invokestatic  #45                 // Method org/slf4j/LoggerFactory.getLogger:(Ljava/lang/Class;)Lorg/slf4j/Logger;
      13: putstatic     #25                 // Field LOG:Lorg/slf4j/Logger;
      16: new           #46                 // class org/apache/hadoop/hbase/HBaseCommonTestingUtility
      19: dup
      20: invokespecial #47                 // Method org/apache/hadoop/hbase/HBaseCommonTestingUtility."<init>":()V
      23: putstatic     #3                  // Field TEST_UTIL:Lorg/apache/hadoop/hbase/HBaseCommonTestingUtility;
      26: getstatic     #3                  // Field TEST_UTIL:Lorg/apache/hadoop/hbase/HBaseCommonTestingUtility;
      29: invokevirtual #4                  // Method org/apache/hadoop/hbase/HBaseCommonTestingUtility.getConfiguration:()Lorg/apache/hadoop/conf/Configuration;
      32: ldc           #41                 // String hbase.dynamic.jars.dir
      34: getstatic     #3                  // Field TEST_UTIL:Lorg/apache/hadoop/hbase/HBaseCommonTestingUtility;
      37: invokevirtual #21                 // Method org/apache/hadoop/hbase/HBaseCommonTestingUtility.getDataTestDir:()Lorg/apache/hadoop/fs/Path;
      40: invokevirtual #22                 // Method org/apache/hadoop/fs/Path.toString:()Ljava/lang/String;
      43: invokevirtual #48                 // Method org/apache/hadoop/conf/Configuration.set:(Ljava/lang/String;Ljava/lang/String;)V
      46: return
}
