Compiled from "TestForeignExceptionSerialization.java"
public class org.apache.hadoop.hbase.errorhandling.TestForeignExceptionSerialization {
  public static final org.apache.hadoop.hbase.HBaseClassTestRule CLASS_RULE;

  public org.apache.hadoop.hbase.errorhandling.TestForeignExceptionSerialization();
    Code:
       0: aload_0
       1: invokespecial #1                  // Method java/lang/Object."<init>":()V
       4: return

  public void testSimpleException() throws java.io.IOException;
    Code:
       0: ldc           #2                  // String some bytes
       2: astore_1
       3: new           #3                  // class org/apache/hadoop/hbase/errorhandling/ForeignException
       6: dup
       7: ldc           #4                  // String SRC
       9: new           #5                  // class java/lang/IllegalArgumentException
      12: dup
      13: aload_1
      14: invokespecial #6                  // Method java/lang/IllegalArgumentException."<init>":(Ljava/lang/String;)V
      17: invokespecial #7                  // Method org/apache/hadoop/hbase/errorhandling/ForeignException."<init>":(Ljava/lang/String;Ljava/lang/Throwable;)V
      20: astore_2
      21: ldc           #9                  // String someNode
      23: aload_2
      24: invokestatic  #10                 // Method org/apache/hadoop/hbase/errorhandling/ForeignException.serialize:(Ljava/lang/String;Ljava/lang/Throwable;)[B
      27: invokestatic  #11                 // Method org/apache/hadoop/hbase/errorhandling/ForeignException.deserialize:([B)Lorg/apache/hadoop/hbase/errorhandling/ForeignException;
      30: astore_3
      31: aload_3
      32: invokestatic  #12                 // Method org/junit/Assert.assertNotNull:(Ljava/lang/Object;)V
      35: new           #13                 // class java/lang/StackTraceElement
      38: dup
      39: aload_0
      40: invokevirtual #14                 // Method java/lang/Object.getClass:()Ljava/lang/Class;
      43: invokevirtual #15                 // Method java/lang/Class.toString:()Ljava/lang/String;
      46: ldc           #16                 // String method
      48: ldc           #17                 // String file
      50: iconst_1
      51: invokespecial #18                 // Method java/lang/StackTraceElement."<init>":(Ljava/lang/String;Ljava/lang/String;Ljava/lang/String;I)V
      54: astore        4
      56: aload_2
      57: iconst_1
      58: anewarray     #13                 // class java/lang/StackTraceElement
      61: dup
      62: iconst_0
      63: aload         4
      65: aastore
      66: invokevirtual #19                 // Method org/apache/hadoop/hbase/errorhandling/ForeignException.setStackTrace:([Ljava/lang/StackTraceElement;)V
      69: ldc           #9                  // String someNode
      71: aload_2
      72: invokestatic  #10                 // Method org/apache/hadoop/hbase/errorhandling/ForeignException.serialize:(Ljava/lang/String;Ljava/lang/Throwable;)[B
      75: invokestatic  #11                 // Method org/apache/hadoop/hbase/errorhandling/ForeignException.deserialize:([B)Lorg/apache/hadoop/hbase/errorhandling/ForeignException;
      78: astore_3
      79: aload_3
      80: invokestatic  #12                 // Method org/junit/Assert.assertNotNull:(Ljava/lang/Object;)V
      83: ldc           #20                 // String Stack trace got corrupted
      85: aload         4
      87: aload_3
      88: invokevirtual #21                 // Method org/apache/hadoop/hbase/errorhandling/ForeignException.getCause:()Ljava/lang/Throwable;
      91: invokevirtual #22                 // Method java/lang/Throwable.getStackTrace:()[Ljava/lang/StackTraceElement;
      94: iconst_0
      95: aaload
      96: invokestatic  #23                 // Method org/junit/Assert.assertEquals:(Ljava/lang/String;Ljava/lang/Object;Ljava/lang/Object;)V
      99: ldc           #24                 // String Got an unexpectedly long stack trace
     101: lconst_1
     102: aload_3
     103: invokevirtual #21                 // Method org/apache/hadoop/hbase/errorhandling/ForeignException.getCause:()Ljava/lang/Throwable;
     106: invokevirtual #22                 // Method java/lang/Throwable.getStackTrace:()[Ljava/lang/StackTraceElement;
     109: arraylength
     110: i2l
     111: invokestatic  #25                 // Method org/junit/Assert.assertEquals:(Ljava/lang/String;JJ)V
     114: return

  public void testRemoteFromLocal() throws java.io.IOException;
    Code:
       0: ldc           #26                 // String some message
       2: astore_1
       3: new           #27                 // class java/lang/Exception
       6: dup
       7: aload_1
       8: invokespecial #28                 // Method java/lang/Exception."<init>":(Ljava/lang/String;)V
      11: astore_2
      12: aload_2
      13: invokevirtual #29                 // Method java/lang/Exception.printStackTrace:()V
      16: aload_2
      17: invokevirtual #30                 // Method java/lang/Exception.getMessage:()Ljava/lang/String;
      20: aload_1
      21: invokevirtual #31                 // Method java/lang/String.contains:(Ljava/lang/CharSequence;)Z
      24: invokestatic  #32                 // Method org/junit/Assert.assertTrue:(Z)V
      27: ldc           #9                  // String someNode
      29: aload_2
      30: invokestatic  #10                 // Method org/apache/hadoop/hbase/errorhandling/ForeignException.serialize:(Ljava/lang/String;Ljava/lang/Throwable;)[B
      33: invokestatic  #11                 // Method org/apache/hadoop/hbase/errorhandling/ForeignException.deserialize:([B)Lorg/apache/hadoop/hbase/errorhandling/ForeignException;
      36: astore_3
      37: ldc           #33                 // String Stacktrace lengths don't match
      39: aload_2
      40: invokevirtual #34                 // Method java/lang/Exception.getStackTrace:()[Ljava/lang/StackTraceElement;
      43: arraylength
      44: i2l
      45: aload_3
      46: invokevirtual #21                 // Method org/apache/hadoop/hbase/errorhandling/ForeignException.getCause:()Ljava/lang/Throwable;
      49: invokevirtual #22                 // Method java/lang/Throwable.getStackTrace:()[Ljava/lang/StackTraceElement;
      52: arraylength
      53: i2l
      54: invokestatic  #25                 // Method org/junit/Assert.assertEquals:(Ljava/lang/String;JJ)V
      57: iconst_0
      58: istore        4
      60: iload         4
      62: aload_2
      63: invokevirtual #34                 // Method java/lang/Exception.getStackTrace:()[Ljava/lang/StackTraceElement;
      66: arraylength
      67: if_icmpge     125
      70: new           #35                 // class java/lang/StringBuilder
      73: dup
      74: invokespecial #36                 // Method java/lang/StringBuilder."<init>":()V
      77: ldc           #37                 // String Local stack trace got corrupted at
      79: invokevirtual #38                 // Method java/lang/StringBuilder.append:(Ljava/lang/String;)Ljava/lang/StringBuilder;
      82: iload         4
      84: invokevirtual #39                 // Method java/lang/StringBuilder.append:(I)Ljava/lang/StringBuilder;
      87: ldc           #40                 // String th index
      89: invokevirtual #38                 // Method java/lang/StringBuilder.append:(Ljava/lang/String;)Ljava/lang/StringBuilder;
      92: invokevirtual #41                 // Method java/lang/StringBuilder.toString:()Ljava/lang/String;
      95: aload_0
      96: aload_2
      97: invokevirtual #34                 // Method java/lang/Exception.getStackTrace:()[Ljava/lang/StackTraceElement;
     100: iload         4
     102: aaload
     103: aload_3
     104: invokevirtual #21                 // Method org/apache/hadoop/hbase/errorhandling/ForeignException.getCause:()Ljava/lang/Throwable;
     107: invokevirtual #22                 // Method java/lang/Throwable.getStackTrace:()[Ljava/lang/StackTraceElement;
     110: iload         4
     112: aaload
     113: invokespecial #42                 // Method compareStackTraceElement:(Ljava/lang/StackTraceElement;Ljava/lang/StackTraceElement;)Z
     116: invokestatic  #43                 // Method org/junit/Assert.assertTrue:(Ljava/lang/String;Z)V
     119: iinc          4, 1
     122: goto          60
     125: aload_3
     126: invokevirtual #44                 // Method org/apache/hadoop/hbase/errorhandling/ForeignException.printStackTrace:()V
     129: aload_3
     130: invokevirtual #21                 // Method org/apache/hadoop/hbase/errorhandling/ForeignException.getCause:()Ljava/lang/Throwable;
     133: invokevirtual #45                 // Method java/lang/Throwable.getCause:()Ljava/lang/Throwable;
     136: ifnonnull     143
     139: iconst_1
     140: goto          144
     143: iconst_0
     144: invokestatic  #32                 // Method org/junit/Assert.assertTrue:(Z)V
     147: aload_3
     148: invokevirtual #21                 // Method org/apache/hadoop/hbase/errorhandling/ForeignException.getCause:()Ljava/lang/Throwable;
     151: invokevirtual #46                 // Method java/lang/Throwable.getMessage:()Ljava/lang/String;
     154: aload_1
     155: invokevirtual #31                 // Method java/lang/String.contains:(Ljava/lang/CharSequence;)Z
     158: invokestatic  #32                 // Method org/junit/Assert.assertTrue:(Z)V
     161: return

  static {};
    Code:
       0: ldc           #8                  // class org/apache/hadoop/hbase/errorhandling/TestForeignExceptionSerialization
       2: invokestatic  #53                 // Method org/apache/hadoop/hbase/HBaseClassTestRule.forClass:(Ljava/lang/Class;)Lorg/apache/hadoop/hbase/HBaseClassTestRule;
       5: putstatic     #54                 // Field CLASS_RULE:Lorg/apache/hadoop/hbase/HBaseClassTestRule;
       8: return
}
