Compiled from "TestMasterProcedureScheduler.java"
public class org.apache.hadoop.hbase.master.procedure.TestMasterProcedureScheduler$TestNamespaceProcedure extends org.apache.hadoop.hbase.procedure2.ProcedureTestingUtility$TestProcedure implements org.apache.hadoop.hbase.master.procedure.TableProcedureInterface {
  public org.apache.hadoop.hbase.master.procedure.TestMasterProcedureScheduler$TestNamespaceProcedure();
    Code:
       0: aload_0
       1: invokespecial #1                  // Method org/apache/hadoop/hbase/procedure2/ProcedureTestingUtility$TestProcedure."<init>":()V
       4: new           #2                  // class java/lang/UnsupportedOperationException
       7: dup
       8: ldc           #3                  // String recovery should not be triggered here
      10: invokespecial #4                  // Method java/lang/UnsupportedOperationException."<init>":(Ljava/lang/String;)V
      13: athrow

  public org.apache.hadoop.hbase.master.procedure.TestMasterProcedureScheduler$TestNamespaceProcedure(long, java.lang.String, org.apache.hadoop.hbase.master.procedure.TableProcedureInterface$TableOperationType);
    Code:
       0: aload_0
       1: lload_1
       2: invokespecial #5                  // Method org/apache/hadoop/hbase/procedure2/ProcedureTestingUtility$TestProcedure."<init>":(J)V
       5: aload_0
       6: aload_3
       7: putfield      #6                  // Field nsName:Ljava/lang/String;
      10: aload_0
      11: aload         4
      13: putfield      #7                  // Field opType:Lorg/apache/hadoop/hbase/master/procedure/TableProcedureInterface$TableOperationType;
      16: return

  public org.apache.hadoop.hbase.TableName getTableName();
    Code:
       0: getstatic     #8                  // Field org/apache/hadoop/hbase/master/procedure/TableProcedureInterface.DUMMY_NAMESPACE_TABLE_NAME:Lorg/apache/hadoop/hbase/TableName;
       3: areturn

  public org.apache.hadoop.hbase.master.procedure.TableProcedureInterface$TableOperationType getTableOperationType();
    Code:
       0: aload_0
       1: getfield      #7                  // Field opType:Lorg/apache/hadoop/hbase/master/procedure/TableProcedureInterface$TableOperationType;
       4: areturn

  public void toStringClassDetails(java.lang.StringBuilder);
    Code:
       0: aload_1
       1: aload_0
       2: invokevirtual #9                  // Method java/lang/Object.getClass:()Ljava/lang/Class;
       5: invokevirtual #10                 // Method java/lang/Class.getSimpleName:()Ljava/lang/String;
       8: invokevirtual #11                 // Method java/lang/StringBuilder.append:(Ljava/lang/String;)Ljava/lang/StringBuilder;
      11: pop
      12: aload_1
      13: ldc           #12                 // String (ns=
      15: invokevirtual #11                 // Method java/lang/StringBuilder.append:(Ljava/lang/String;)Ljava/lang/StringBuilder;
      18: pop
      19: aload_1
      20: aload_0
      21: getfield      #6                  // Field nsName:Ljava/lang/String;
      24: invokevirtual #11                 // Method java/lang/StringBuilder.append:(Ljava/lang/String;)Ljava/lang/StringBuilder;
      27: pop
      28: aload_1
      29: ldc           #13                 // String )
      31: invokevirtual #11                 // Method java/lang/StringBuilder.append:(Ljava/lang/String;)Ljava/lang/StringBuilder;
      34: pop
      35: return
}
