Compiled from "TestKeyOnlyFilter.java"
public class org.apache.hadoop.hbase.filter.TestKeyOnlyFilter {
  public static final org.apache.hadoop.hbase.HBaseClassTestRule CLASS_RULE;

  public boolean lenAsVal;

  public org.apache.hadoop.hbase.filter.TestKeyOnlyFilter();
    Code:
       0: aload_0
       1: invokespecial #1                  // Method java/lang/Object."<init>":()V
       4: return

  public static java.util.Collection<java.lang.Object[]> parameters();
    Code:
       0: getstatic     #2                  // Field org/apache/hadoop/hbase/HBaseCommonTestingUtility.BOOLEAN_PARAMETERIZED:Ljava/util/List;
       3: areturn

  public void testKeyOnly() throws java.lang.Exception;
    Code:
       0: ldc           #3                  // String row1
       2: invokestatic  #4                  // Method org/apache/hadoop/hbase/util/Bytes.toBytes:(Ljava/lang/String;)[B
       5: astore_1
       6: ldc           #5                  // String cf1
       8: invokestatic  #4                  // Method org/apache/hadoop/hbase/util/Bytes.toBytes:(Ljava/lang/String;)[B
      11: astore_2
      12: ldc           #6                  // String qual1
      14: invokestatic  #4                  // Method org/apache/hadoop/hbase/util/Bytes.toBytes:(Ljava/lang/String;)[B
      17: astore_3
      18: ldc           #7                  // String val1
      20: invokestatic  #4                  // Method org/apache/hadoop/hbase/util/Bytes.toBytes:(Ljava/lang/String;)[B
      23: astore        4
      25: ldc           #8                  // String tag1
      27: invokestatic  #4                  // Method org/apache/hadoop/hbase/util/Bytes.toBytes:(Ljava/lang/String;)[B
      30: astore        5
      32: new           #9                  // class org/apache/hadoop/hbase/KeyValue
      35: dup
      36: aload_1
      37: aload_2
      38: aload_3
      39: iconst_0
      40: aload_3
      41: arraylength
      42: ldc2_w        #10                 // long 1234l
      45: getstatic     #12                 // Field org/apache/hadoop/hbase/KeyValue$Type.Put:Lorg/apache/hadoop/hbase/KeyValue$Type;
      48: aload         4
      50: iconst_0
      51: aload         4
      53: arraylength
      54: aload         5
      56: invokespecial #13                 // Method org/apache/hadoop/hbase/KeyValue."<init>":([B[B[BIIJLorg/apache/hadoop/hbase/KeyValue$Type;[BII[B)V
      59: astore        6
      61: aload         6
      63: invokevirtual #14                 // Method org/apache/hadoop/hbase/KeyValue.getBuffer:()[B
      66: invokestatic  #15                 // Method java/nio/ByteBuffer.wrap:([B)Ljava/nio/ByteBuffer;
      69: astore        7
      71: new           #16                 // class org/apache/hadoop/hbase/ByteBufferKeyValue
      74: dup
      75: aload         7
      77: iconst_0
      78: aload         7
      80: invokevirtual #17                 // Method java/nio/ByteBuffer.remaining:()I
      83: invokespecial #18                 // Method org/apache/hadoop/hbase/ByteBufferKeyValue."<init>":(Ljava/nio/ByteBuffer;II)V
      86: astore        8
      88: aload_0
      89: getfield      #19                 // Field lenAsVal:Z
      92: ifeq          99
      95: iconst_4
      96: goto          100
      99: iconst_0
     100: istore        9
     102: bipush        8
     104: istore        10
     106: aload         6
     108: invokestatic  #21                 // Method org/apache/hadoop/hbase/KeyValueUtil.keyLength:(Lorg/apache/hadoop/hbase/Cell;)I
     111: istore        11
     113: iload         11
     115: iload         10
     117: iadd
     118: iload         9
     120: iadd
     121: newarray       byte
     123: astore        12
     125: aload         12
     127: iconst_0
     128: iload         11
     130: invokestatic  #22                 // Method org/apache/hadoop/hbase/util/Bytes.putInt:([BII)I
     133: pop
     134: aload         12
     136: iconst_4
     137: iload         9
     139: invokestatic  #22                 // Method org/apache/hadoop/hbase/util/Bytes.putInt:([BII)I
     142: pop
     143: aload         6
     145: aload         12
     147: iload         10
     149: invokestatic  #23                 // Method org/apache/hadoop/hbase/KeyValueUtil.appendKeyTo:(Lorg/apache/hadoop/hbase/Cell;[BI)I
     152: pop
     153: aload_0
     154: getfield      #19                 // Field lenAsVal:Z
     157: ifeq          177
     160: aload         12
     162: aload         12
     164: arraylength
     165: iload         9
     167: isub
     168: aload         6
     170: invokevirtual #24                 // Method org/apache/hadoop/hbase/KeyValue.getValueLength:()I
     173: invokestatic  #22                 // Method org/apache/hadoop/hbase/util/Bytes.putInt:([BII)I
     176: pop
     177: new           #9                  // class org/apache/hadoop/hbase/KeyValue
     180: dup
     181: aload         12
     183: invokespecial #25                 // Method org/apache/hadoop/hbase/KeyValue."<init>":([B)V
     186: astore        13
     188: new           #26                 // class org/apache/hadoop/hbase/filter/KeyOnlyFilter$KeyOnlyCell
     191: dup
     192: aload         6
     194: aload_0
     195: getfield      #19                 // Field lenAsVal:Z
     198: invokespecial #27                 // Method org/apache/hadoop/hbase/filter/KeyOnlyFilter$KeyOnlyCell."<init>":(Lorg/apache/hadoop/hbase/Cell;Z)V
     201: astore        14
     203: new           #28                 // class org/apache/hadoop/hbase/filter/KeyOnlyFilter$KeyOnlyByteBufferExtendedCell
     206: dup
     207: aload         8
     209: aload_0
     210: getfield      #19                 // Field lenAsVal:Z
     213: invokespecial #29                 // Method org/apache/hadoop/hbase/filter/KeyOnlyFilter$KeyOnlyByteBufferExtendedCell."<init>":(Lorg/apache/hadoop/hbase/ByteBufferExtendedCell;Z)V
     216: astore        15
     218: aload         13
     220: aload         14
     222: invokestatic  #30                 // Method org/apache/hadoop/hbase/CellUtil.matchingRows:(Lorg/apache/hadoop/hbase/Cell;Lorg/apache/hadoop/hbase/Cell;)Z
     225: invokestatic  #31                 // Method org/junit/Assert.assertTrue:(Z)V
     228: aload         13
     230: aload         15
     232: invokestatic  #30                 // Method org/apache/hadoop/hbase/CellUtil.matchingRows:(Lorg/apache/hadoop/hbase/Cell;Lorg/apache/hadoop/hbase/Cell;)Z
     235: invokestatic  #31                 // Method org/junit/Assert.assertTrue:(Z)V
     238: aload         13
     240: aload         14
     242: invokestatic  #32                 // Method org/apache/hadoop/hbase/CellUtil.matchingFamily:(Lorg/apache/hadoop/hbase/Cell;Lorg/apache/hadoop/hbase/Cell;)Z
     245: invokestatic  #31                 // Method org/junit/Assert.assertTrue:(Z)V
     248: aload         13
     250: aload         15
     252: invokestatic  #32                 // Method org/apache/hadoop/hbase/CellUtil.matchingFamily:(Lorg/apache/hadoop/hbase/Cell;Lorg/apache/hadoop/hbase/Cell;)Z
     255: invokestatic  #31                 // Method org/junit/Assert.assertTrue:(Z)V
     258: aload         13
     260: aload         14
     262: invokestatic  #33                 // Method org/apache/hadoop/hbase/CellUtil.matchingQualifier:(Lorg/apache/hadoop/hbase/Cell;Lorg/apache/hadoop/hbase/Cell;)Z
     265: invokestatic  #31                 // Method org/junit/Assert.assertTrue:(Z)V
     268: aload         13
     270: aload         15
     272: invokestatic  #33                 // Method org/apache/hadoop/hbase/CellUtil.matchingQualifier:(Lorg/apache/hadoop/hbase/Cell;Lorg/apache/hadoop/hbase/Cell;)Z
     275: invokestatic  #31                 // Method org/junit/Assert.assertTrue:(Z)V
     278: aload         13
     280: aload         14
     282: invokestatic  #34                 // Method org/apache/hadoop/hbase/CellUtil.matchingValue:(Lorg/apache/hadoop/hbase/Cell;Lorg/apache/hadoop/hbase/Cell;)Z
     285: invokestatic  #31                 // Method org/junit/Assert.assertTrue:(Z)V
     288: aload         13
     290: invokevirtual #24                 // Method org/apache/hadoop/hbase/KeyValue.getValueLength:()I
     293: aload         15
     295: invokevirtual #35                 // Method org/apache/hadoop/hbase/filter/KeyOnlyFilter$KeyOnlyByteBufferExtendedCell.getValueLength:()I
     298: if_icmpne     305
     301: iconst_1
     302: goto          306
     305: iconst_0
     306: invokestatic  #31                 // Method org/junit/Assert.assertTrue:(Z)V
     309: bipush        8
     311: iload         11
     313: iadd
     314: aload_0
     315: getfield      #19                 // Field lenAsVal:Z
     318: ifeq          325
     321: iconst_4
     322: goto          326
     325: iconst_0
     326: iadd
     327: i2l
     328: aload         13
     330: invokevirtual #36                 // Method org/apache/hadoop/hbase/KeyValue.getSerializedSize:()I
     333: i2l
     334: invokestatic  #37                 // Method org/junit/Assert.assertEquals:(JJ)V
     337: bipush        8
     339: iload         11
     341: iadd
     342: aload_0
     343: getfield      #19                 // Field lenAsVal:Z
     346: ifeq          353
     349: iconst_4
     350: goto          354
     353: iconst_0
     354: iadd
     355: i2l
     356: aload         14
     358: invokevirtual #38                 // Method org/apache/hadoop/hbase/filter/KeyOnlyFilter$KeyOnlyCell.getSerializedSize:()I
     361: i2l
     362: invokestatic  #37                 // Method org/junit/Assert.assertEquals:(JJ)V
     365: aload         15
     367: invokevirtual #35                 // Method org/apache/hadoop/hbase/filter/KeyOnlyFilter$KeyOnlyByteBufferExtendedCell.getValueLength:()I
     370: ifle          383
     373: aload         13
     375: aload         15
     377: invokestatic  #34                 // Method org/apache/hadoop/hbase/CellUtil.matchingValue:(Lorg/apache/hadoop/hbase/Cell;Lorg/apache/hadoop/hbase/Cell;)Z
     380: invokestatic  #31                 // Method org/junit/Assert.assertTrue:(Z)V
     383: aload         13
     385: invokevirtual #39                 // Method org/apache/hadoop/hbase/KeyValue.getTimestamp:()J
     388: aload         14
     390: invokevirtual #40                 // Method org/apache/hadoop/hbase/filter/KeyOnlyFilter$KeyOnlyCell.getTimestamp:()J
     393: lcmp
     394: ifne          401
     397: iconst_1
     398: goto          402
     401: iconst_0
     402: invokestatic  #31                 // Method org/junit/Assert.assertTrue:(Z)V
     405: aload         13
     407: invokevirtual #39                 // Method org/apache/hadoop/hbase/KeyValue.getTimestamp:()J
     410: aload         15
     412: invokevirtual #41                 // Method org/apache/hadoop/hbase/filter/KeyOnlyFilter$KeyOnlyByteBufferExtendedCell.getTimestamp:()J
     415: lcmp
     416: ifne          423
     419: iconst_1
     420: goto          424
     423: iconst_0
     424: invokestatic  #31                 // Method org/junit/Assert.assertTrue:(Z)V
     427: aload         13
     429: invokevirtual #42                 // Method org/apache/hadoop/hbase/KeyValue.getTypeByte:()B
     432: aload         14
     434: invokevirtual #43                 // Method org/apache/hadoop/hbase/filter/KeyOnlyFilter$KeyOnlyCell.getTypeByte:()B
     437: if_icmpne     444
     440: iconst_1
     441: goto          445
     444: iconst_0
     445: invokestatic  #31                 // Method org/junit/Assert.assertTrue:(Z)V
     448: aload         13
     450: invokevirtual #42                 // Method org/apache/hadoop/hbase/KeyValue.getTypeByte:()B
     453: aload         15
     455: invokevirtual #44                 // Method org/apache/hadoop/hbase/filter/KeyOnlyFilter$KeyOnlyByteBufferExtendedCell.getTypeByte:()B
     458: if_icmpne     465
     461: iconst_1
     462: goto          466
     465: iconst_0
     466: invokestatic  #31                 // Method org/junit/Assert.assertTrue:(Z)V
     469: aload         13
     471: invokevirtual #45                 // Method org/apache/hadoop/hbase/KeyValue.getTagsLength:()I
     474: aload         14
     476: invokevirtual #46                 // Method org/apache/hadoop/hbase/filter/KeyOnlyFilter$KeyOnlyCell.getTagsLength:()I
     479: if_icmpne     486
     482: iconst_1
     483: goto          487
     486: iconst_0
     487: invokestatic  #31                 // Method org/junit/Assert.assertTrue:(Z)V
     490: aload         13
     492: invokevirtual #45                 // Method org/apache/hadoop/hbase/KeyValue.getTagsLength:()I
     495: aload         15
     497: invokevirtual #47                 // Method org/apache/hadoop/hbase/filter/KeyOnlyFilter$KeyOnlyByteBufferExtendedCell.getTagsLength:()I
     500: if_icmpne     507
     503: iconst_1
     504: goto          508
     507: iconst_0
     508: invokestatic  #31                 // Method org/junit/Assert.assertTrue:(Z)V
     511: return

  static {};
    Code:
       0: ldc           #48                 // class org/apache/hadoop/hbase/filter/TestKeyOnlyFilter
       2: invokestatic  #49                 // Method org/apache/hadoop/hbase/HBaseClassTestRule.forClass:(Ljava/lang/Class;)Lorg/apache/hadoop/hbase/HBaseClassTestRule;
       5: putstatic     #50                 // Field CLASS_RULE:Lorg/apache/hadoop/hbase/HBaseClassTestRule;
       8: return
}
