Compiled from "TestReplicationEndpoint.java"
public class org.apache.hadoop.hbase.replication.TestReplicationEndpoint$ReplicationEndpointForTest extends org.apache.hadoop.hbase.replication.BaseReplicationEndpoint {
  static java.util.UUID uuid;

  static java.util.concurrent.atomic.AtomicInteger contructedCount;

  static java.util.concurrent.atomic.AtomicInteger startedCount;

  static java.util.concurrent.atomic.AtomicInteger stoppedCount;

  static java.util.concurrent.atomic.AtomicInteger replicateCount;

  static volatile java.util.List<org.apache.hadoop.hbase.wal.WAL$Entry> lastEntries;

  public org.apache.hadoop.hbase.replication.TestReplicationEndpoint$ReplicationEndpointForTest();
    Code:
       0: aload_0
       1: invokespecial #1                  // Method org/apache/hadoop/hbase/replication/BaseReplicationEndpoint."<init>":()V
       4: getstatic     #2                  // Field replicateCount:Ljava/util/concurrent/atomic/AtomicInteger;
       7: iconst_0
       8: invokevirtual #3                  // Method java/util/concurrent/atomic/AtomicInteger.set:(I)V
      11: getstatic     #4                  // Field contructedCount:Ljava/util/concurrent/atomic/AtomicInteger;
      14: invokevirtual #5                  // Method java/util/concurrent/atomic/AtomicInteger.incrementAndGet:()I
      17: pop
      18: return

  public java.util.UUID getPeerUUID();
    Code:
       0: getstatic     #6                  // Field uuid:Ljava/util/UUID;
       3: areturn

  public boolean replicate(org.apache.hadoop.hbase.replication.ReplicationEndpoint$ReplicateContext);
    Code:
       0: getstatic     #2                  // Field replicateCount:Ljava/util/concurrent/atomic/AtomicInteger;
       3: invokevirtual #5                  // Method java/util/concurrent/atomic/AtomicInteger.incrementAndGet:()I
       6: pop
       7: new           #7                  // class java/util/ArrayList
      10: dup
      11: aload_1
      12: getfield      #8                  // Field org/apache/hadoop/hbase/replication/ReplicationEndpoint$ReplicateContext.entries:Ljava/util/List;
      15: invokespecial #9                  // Method java/util/ArrayList."<init>":(Ljava/util/Collection;)V
      18: putstatic     #10                 // Field lastEntries:Ljava/util/List;
      21: iconst_1
      22: ireturn

  public void start();
    Code:
       0: aload_0
       1: invokevirtual #11                 // Method startAsync:()Lorg/apache/hbase/thirdparty/com/google/common/util/concurrent/Service;
       4: pop
       5: return

  public void stop();
    Code:
       0: aload_0
       1: invokevirtual #12                 // Method stopAsync:()Lorg/apache/hbase/thirdparty/com/google/common/util/concurrent/Service;
       4: pop
       5: return

  protected void doStart();
    Code:
       0: getstatic     #13                 // Field startedCount:Ljava/util/concurrent/atomic/AtomicInteger;
       3: invokevirtual #5                  // Method java/util/concurrent/atomic/AtomicInteger.incrementAndGet:()I
       6: pop
       7: aload_0
       8: invokevirtual #14                 // Method notifyStarted:()V
      11: return

  protected void doStop();
    Code:
       0: getstatic     #15                 // Field stoppedCount:Ljava/util/concurrent/atomic/AtomicInteger;
       3: invokevirtual #5                  // Method java/util/concurrent/atomic/AtomicInteger.incrementAndGet:()I
       6: pop
       7: aload_0
       8: invokevirtual #16                 // Method notifyStopped:()V
      11: return

  static {};
    Code:
       0: getstatic     #17                 // Field org/apache/hadoop/hbase/replication/TestReplicationBase.UTIL1:Lorg/apache/hadoop/hbase/HBaseTestingUtility;
       3: invokevirtual #18                 // Method org/apache/hadoop/hbase/HBaseTestingUtility.getRandomUUID:()Ljava/util/UUID;
       6: putstatic     #6                  // Field uuid:Ljava/util/UUID;
       9: new           #19                 // class java/util/concurrent/atomic/AtomicInteger
      12: dup
      13: invokespecial #20                 // Method java/util/concurrent/atomic/AtomicInteger."<init>":()V
      16: putstatic     #4                  // Field contructedCount:Ljava/util/concurrent/atomic/AtomicInteger;
      19: new           #19                 // class java/util/concurrent/atomic/AtomicInteger
      22: dup
      23: invokespecial #20                 // Method java/util/concurrent/atomic/AtomicInteger."<init>":()V
      26: putstatic     #13                 // Field startedCount:Ljava/util/concurrent/atomic/AtomicInteger;
      29: new           #19                 // class java/util/concurrent/atomic/AtomicInteger
      32: dup
      33: invokespecial #20                 // Method java/util/concurrent/atomic/AtomicInteger."<init>":()V
      36: putstatic     #15                 // Field stoppedCount:Ljava/util/concurrent/atomic/AtomicInteger;
      39: new           #19                 // class java/util/concurrent/atomic/AtomicInteger
      42: dup
      43: invokespecial #20                 // Method java/util/concurrent/atomic/AtomicInteger."<init>":()V
      46: putstatic     #2                  // Field replicateCount:Ljava/util/concurrent/atomic/AtomicInteger;
      49: aconst_null
      50: putstatic     #10                 // Field lastEntries:Ljava/util/List;
      53: return
}
