Compiled from "TestAsyncProcess.java"
class org.apache.hadoop.hbase.client.TestAsyncProcess$MyAsyncProcess$1 extends org.apache.hadoop.hbase.client.AsyncProcessTask {
  final org.apache.hadoop.hbase.client.TestAsyncProcess$MyAsyncProcess this$0;

  org.apache.hadoop.hbase.client.TestAsyncProcess$MyAsyncProcess$1(org.apache.hadoop.hbase.client.TestAsyncProcess$MyAsyncProcess, org.apache.hadoop.hbase.client.AsyncProcessTask);
    Code:
       0: aload_0
       1: aload_1
       2: putfield      #1                  // Field this$0:Lorg/apache/hadoop/hbase/client/TestAsyncProcess$MyAsyncProcess;
       5: aload_0
       6: aload_2
       7: invokespecial #2                  // Method org/apache/hadoop/hbase/client/AsyncProcessTask."<init>":(Lorg/apache/hadoop/hbase/client/AsyncProcessTask;)V
      10: return

  public org.apache.hadoop.hbase.TableName getTableName();
    Code:
       0: invokestatic  #3                  // Method org/apache/hadoop/hbase/client/TestAsyncProcess.access$000:()Lorg/apache/hadoop/hbase/TableName;
       3: areturn
}
