Compiled from "TestHRegion.java"
class org.apache.hadoop.hbase.regionserver.TestHRegion$5 extends org.apache.hadoop.hbase.MultithreadedTestUtil$TestThread {
  final org.apache.hadoop.hbase.regionserver.HRegion$MutationBatchOperation val$finalBatchOp;

  final java.util.concurrent.atomic.AtomicReference val$retFromThread;

  final java.util.concurrent.CountDownLatch val$finishedPuts;

  final org.apache.hadoop.hbase.regionserver.TestHRegion this$0;

  org.apache.hadoop.hbase.regionserver.TestHRegion$5(org.apache.hadoop.hbase.regionserver.TestHRegion, org.apache.hadoop.hbase.MultithreadedTestUtil$TestContext, org.apache.hadoop.hbase.regionserver.HRegion$MutationBatchOperation, java.util.concurrent.atomic.AtomicReference, java.util.concurrent.CountDownLatch);
    Code:
       0: aload_0
       1: aload_1
       2: putfield      #1                  // Field this$0:Lorg/apache/hadoop/hbase/regionserver/TestHRegion;
       5: aload_0
       6: aload_3
       7: putfield      #2                  // Field val$finalBatchOp:Lorg/apache/hadoop/hbase/regionserver/HRegion$MutationBatchOperation;
      10: aload_0
      11: aload         4
      13: putfield      #3                  // Field val$retFromThread:Ljava/util/concurrent/atomic/AtomicReference;
      16: aload_0
      17: aload         5
      19: putfield      #4                  // Field val$finishedPuts:Ljava/util/concurrent/CountDownLatch;
      22: aload_0
      23: aload_2
      24: invokespecial #5                  // Method org/apache/hadoop/hbase/MultithreadedTestUtil$TestThread."<init>":(Lorg/apache/hadoop/hbase/MultithreadedTestUtil$TestContext;)V
      27: return

  public void doWork() throws java.io.IOException;
    Code:
       0: aload_0
       1: getfield      #1                  // Field this$0:Lorg/apache/hadoop/hbase/regionserver/TestHRegion;
       4: getfield      #6                  // Field org/apache/hadoop/hbase/regionserver/TestHRegion.region:Lorg/apache/hadoop/hbase/regionserver/HRegion;
       7: aload_0
       8: getfield      #2                  // Field val$finalBatchOp:Lorg/apache/hadoop/hbase/regionserver/HRegion$MutationBatchOperation;
      11: invokevirtual #7                  // Method org/apache/hadoop/hbase/regionserver/HRegion.batchMutate:(Lorg/apache/hadoop/hbase/regionserver/HRegion$BatchOperation;)[Lorg/apache/hadoop/hbase/regionserver/OperationStatus;
      14: pop
      15: goto          38
      18: astore_1
      19: invokestatic  #9                  // Method org/apache/hadoop/hbase/regionserver/TestHRegion.access$100:()Lorg/slf4j/Logger;
      22: ldc           #10                 // String test failed!
      24: aload_1
      25: invokeinterface #11,  3           // InterfaceMethod org/slf4j/Logger.error:(Ljava/lang/String;Ljava/lang/Throwable;)V
      30: aload_0
      31: getfield      #3                  // Field val$retFromThread:Ljava/util/concurrent/atomic/AtomicReference;
      34: aload_1
      35: invokevirtual #12                 // Method java/util/concurrent/atomic/AtomicReference.set:(Ljava/lang/Object;)V
      38: aload_0
      39: getfield      #4                  // Field val$finishedPuts:Ljava/util/concurrent/CountDownLatch;
      42: invokevirtual #13                 // Method java/util/concurrent/CountDownLatch.countDown:()V
      45: return
    Exception table:
       from    to  target type
           0    15    18   Class java/io/IOException
}
