Compiled from "TestYieldProcedures.java"
class org.apache.hadoop.hbase.procedure2.TestYieldProcedures$TestScheduler extends org.apache.hadoop.hbase.procedure2.SimpleProcedureScheduler {
  public org.apache.hadoop.hbase.procedure2.TestYieldProcedures$TestScheduler();
    Code:
       0: aload_0
       1: invokespecial #6                  // Method org/apache/hadoop/hbase/procedure2/SimpleProcedureScheduler."<init>":()V
       4: return

  public void addFront(org.apache.hadoop.hbase.procedure2.Procedure);
    Code:
       0: aload_0
       1: dup
       2: getfield      #5                  // Field addFrontCalls:I
       5: iconst_1
       6: iadd
       7: putfield      #5                  // Field addFrontCalls:I
      10: aload_0
      11: aload_1
      12: invokespecial #7                  // Method org/apache/hadoop/hbase/procedure2/SimpleProcedureScheduler.addFront:(Lorg/apache/hadoop/hbase/procedure2/Procedure;)V
      15: return

  public void addBack(org.apache.hadoop.hbase.procedure2.Procedure);
    Code:
       0: aload_0
       1: dup
       2: getfield      #4                  // Field addBackCalls:I
       5: iconst_1
       6: iadd
       7: putfield      #4                  // Field addBackCalls:I
      10: aload_0
      11: aload_1
      12: invokespecial #8                  // Method org/apache/hadoop/hbase/procedure2/SimpleProcedureScheduler.addBack:(Lorg/apache/hadoop/hbase/procedure2/Procedure;)V
      15: return

  public void yield(org.apache.hadoop.hbase.procedure2.Procedure);
    Code:
       0: aload_0
       1: dup
       2: getfield      #3                  // Field yieldCalls:I
       5: iconst_1
       6: iadd
       7: putfield      #3                  // Field yieldCalls:I
      10: aload_0
      11: aload_1
      12: invokespecial #9                  // Method org/apache/hadoop/hbase/procedure2/SimpleProcedureScheduler.yield:(Lorg/apache/hadoop/hbase/procedure2/Procedure;)V
      15: return

  public org.apache.hadoop.hbase.procedure2.Procedure poll();
    Code:
       0: aload_0
       1: dup
       2: getfield      #2                  // Field pollCalls:I
       5: iconst_1
       6: iadd
       7: putfield      #2                  // Field pollCalls:I
      10: aload_0
      11: invokespecial #10                 // Method org/apache/hadoop/hbase/procedure2/SimpleProcedureScheduler.poll:()Lorg/apache/hadoop/hbase/procedure2/Procedure;
      14: areturn

  public org.apache.hadoop.hbase.procedure2.Procedure poll(long, java.util.concurrent.TimeUnit);
    Code:
       0: aload_0
       1: dup
       2: getfield      #2                  // Field pollCalls:I
       5: iconst_1
       6: iadd
       7: putfield      #2                  // Field pollCalls:I
      10: aload_0
      11: lload_1
      12: aload_3
      13: invokespecial #11                 // Method org/apache/hadoop/hbase/procedure2/SimpleProcedureScheduler.poll:(JLjava/util/concurrent/TimeUnit;)Lorg/apache/hadoop/hbase/procedure2/Procedure;
      16: areturn

  public void completionCleanup(org.apache.hadoop.hbase.procedure2.Procedure);
    Code:
       0: aload_0
       1: dup
       2: getfield      #1                  // Field completionCalls:I
       5: iconst_1
       6: iadd
       7: putfield      #1                  // Field completionCalls:I
      10: return

  static int access$100(org.apache.hadoop.hbase.procedure2.TestYieldProcedures$TestScheduler);
    Code:
       0: aload_0
       1: getfield      #5                  // Field addFrontCalls:I
       4: ireturn

  static int access$200(org.apache.hadoop.hbase.procedure2.TestYieldProcedures$TestScheduler);
    Code:
       0: aload_0
       1: getfield      #4                  // Field addBackCalls:I
       4: ireturn

  static int access$300(org.apache.hadoop.hbase.procedure2.TestYieldProcedures$TestScheduler);
    Code:
       0: aload_0
       1: getfield      #3                  // Field yieldCalls:I
       4: ireturn

  static int access$400(org.apache.hadoop.hbase.procedure2.TestYieldProcedures$TestScheduler);
    Code:
       0: aload_0
       1: getfield      #2                  // Field pollCalls:I
       4: ireturn

  static int access$500(org.apache.hadoop.hbase.procedure2.TestYieldProcedures$TestScheduler);
    Code:
       0: aload_0
       1: getfield      #1                  // Field completionCalls:I
       4: ireturn
}
