Compiled from "TestWarmupRegion.java"
public class org.apache.hadoop.hbase.master.TestWarmupRegion {
  public static final org.apache.hadoop.hbase.HBaseClassTestRule CLASS_RULE;

  protected org.apache.hadoop.hbase.TableName TABLENAME;

  protected static final org.apache.hadoop.hbase.HBaseTestingUtility TEST_UTIL;

  protected static int SLAVES;

  public org.apache.hadoop.hbase.master.TestWarmupRegion();
    Code:
       0: aload_0
       1: invokespecial #3                  // Method java/lang/Object."<init>":()V
       4: aload_0
       5: ldc           #4                  // String testPurgeFutureDeletes
       7: invokestatic  #5                  // Method org/apache/hadoop/hbase/TableName.valueOf:(Ljava/lang/String;)Lorg/apache/hadoop/hbase/TableName;
      10: putfield      #6                  // Field TABLENAME:Lorg/apache/hadoop/hbase/TableName;
      13: return

  public static void setUpBeforeClass() throws java.lang.Exception;
    Code:
       0: getstatic     #7                  // Field TEST_UTIL:Lorg/apache/hadoop/hbase/HBaseTestingUtility;
       3: invokevirtual #8                  // Method org/apache/hadoop/hbase/HBaseTestingUtility.getConfiguration:()Lorg/apache/hadoop/conf/Configuration;
       6: astore_0
       7: getstatic     #7                  // Field TEST_UTIL:Lorg/apache/hadoop/hbase/HBaseTestingUtility;
      10: getstatic     #9                  // Field SLAVES:I
      13: invokevirtual #10                 // Method org/apache/hadoop/hbase/HBaseTestingUtility.startMiniCluster:(I)Lorg/apache/hadoop/hbase/MiniHBaseCluster;
      16: pop
      17: return

  public static void tearDownAfterClass() throws java.lang.Exception;
    Code:
       0: getstatic     #7                  // Field TEST_UTIL:Lorg/apache/hadoop/hbase/HBaseTestingUtility;
       3: invokevirtual #11                 // Method org/apache/hadoop/hbase/HBaseTestingUtility.shutdownMiniCluster:()V
       6: return

  public void setUp() throws java.lang.Exception;
    Code:
       0: getstatic     #7                  // Field TEST_UTIL:Lorg/apache/hadoop/hbase/HBaseTestingUtility;
       3: aload_0
       4: getfield      #6                  // Field TABLENAME:Lorg/apache/hadoop/hbase/TableName;
       7: getstatic     #12                 // Field FAMILY:[B
      10: invokevirtual #13                 // Method org/apache/hadoop/hbase/HBaseTestingUtility.createTable:(Lorg/apache/hadoop/hbase/TableName;[B)Lorg/apache/hadoop/hbase/client/Table;
      13: putstatic     #2                  // Field table:Lorg/apache/hadoop/hbase/client/Table;
      16: iconst_0
      17: istore_1
      18: iload_1
      19: getstatic     #14                 // Field numRows:I
      22: if_icmpge     77
      25: invokestatic  #15                 // Method java/lang/System.currentTimeMillis:()J
      28: ldc2_w        #16                 // long 2l
      31: lmul
      32: lstore_2
      33: new           #18                 // class org/apache/hadoop/hbase/client/Put
      36: dup
      37: getstatic     #19                 // Field ROW:[B
      40: lload_2
      41: invokespecial #20                 // Method org/apache/hadoop/hbase/client/Put."<init>":([BJ)V
      44: astore        4
      46: aload         4
      48: getstatic     #12                 // Field FAMILY:[B
      51: getstatic     #21                 // Field COLUMN:[B
      54: getstatic     #22                 // Field VALUE:[B
      57: invokevirtual #23                 // Method org/apache/hadoop/hbase/client/Put.addColumn:([B[B[B)Lorg/apache/hadoop/hbase/client/Put;
      60: pop
      61: getstatic     #2                  // Field table:Lorg/apache/hadoop/hbase/client/Table;
      64: aload         4
      66: invokeinterface #24,  2           // InterfaceMethod org/apache/hadoop/hbase/client/Table.put:(Lorg/apache/hadoop/hbase/client/Put;)V
      71: iinc          1, 1
      74: goto          18
      77: getstatic     #7                  // Field TEST_UTIL:Lorg/apache/hadoop/hbase/HBaseTestingUtility;
      80: invokevirtual #25                 // Method org/apache/hadoop/hbase/HBaseTestingUtility.getAdmin:()Lorg/apache/hadoop/hbase/client/Admin;
      83: aload_0
      84: getfield      #6                  // Field TABLENAME:Lorg/apache/hadoop/hbase/TableName;
      87: invokeinterface #26,  2           // InterfaceMethod org/apache/hadoop/hbase/client/Admin.flush:(Lorg/apache/hadoop/hbase/TableName;)V
      92: getstatic     #7                  // Field TEST_UTIL:Lorg/apache/hadoop/hbase/HBaseTestingUtility;
      95: invokevirtual #25                 // Method org/apache/hadoop/hbase/HBaseTestingUtility.getAdmin:()Lorg/apache/hadoop/hbase/client/Admin;
      98: aload_0
      99: getfield      #6                  // Field TABLENAME:Lorg/apache/hadoop/hbase/TableName;
     102: invokeinterface #27,  2           // InterfaceMethod org/apache/hadoop/hbase/client/Admin.majorCompact:(Lorg/apache/hadoop/hbase/TableName;)V
     107: getstatic     #7                  // Field TEST_UTIL:Lorg/apache/hadoop/hbase/HBaseTestingUtility;
     110: ldc2_w        #28                 // long 6000l
     113: new           #30                 // class org/apache/hadoop/hbase/master/TestWarmupRegion$1
     116: dup
     117: aload_0
     118: invokespecial #31                 // Method org/apache/hadoop/hbase/master/TestWarmupRegion$1."<init>":(Lorg/apache/hadoop/hbase/master/TestWarmupRegion;)V
     121: invokevirtual #32                 // Method org/apache/hadoop/hbase/HBaseTestingUtility.waitFor:(JLorg/apache/hadoop/hbase/Waiter$Predicate;)J
     124: pop2
     125: getstatic     #2                  // Field table:Lorg/apache/hadoop/hbase/client/Table;
     128: invokeinterface #33,  1           // InterfaceMethod org/apache/hadoop/hbase/client/Table.close:()V
     133: return

  public void tearDown() throws java.lang.Exception;
    Code:
       0: return

  protected void runwarmup() throws java.lang.InterruptedException;
    Code:
       0: new           #34                 // class java/lang/Thread
       3: dup
       4: new           #35                 // class org/apache/hadoop/hbase/master/TestWarmupRegion$2
       7: dup
       8: aload_0
       9: invokespecial #36                 // Method org/apache/hadoop/hbase/master/TestWarmupRegion$2."<init>":(Lorg/apache/hadoop/hbase/master/TestWarmupRegion;)V
      12: invokespecial #37                 // Method java/lang/Thread."<init>":(Ljava/lang/Runnable;)V
      15: astore_1
      16: aload_1
      17: invokevirtual #38                 // Method java/lang/Thread.start:()V
      20: aload_1
      21: invokevirtual #39                 // Method java/lang/Thread.join:()V
      24: return

  public void testWarmup() throws java.lang.Exception;
    Code:
       0: iconst_0
       1: istore_1
       2: getstatic     #7                  // Field TEST_UTIL:Lorg/apache/hadoop/hbase/HBaseTestingUtility;
       5: invokevirtual #40                 // Method org/apache/hadoop/hbase/HBaseTestingUtility.getMiniHBaseCluster:()Lorg/apache/hadoop/hbase/MiniHBaseCluster;
       8: aload_0
       9: getfield      #6                  // Field TABLENAME:Lorg/apache/hadoop/hbase/TableName;
      12: invokevirtual #41                 // Method org/apache/hadoop/hbase/MiniHBaseCluster.getRegions:(Lorg/apache/hadoop/hbase/TableName;)Ljava/util/List;
      15: iconst_0
      16: invokeinterface #42,  2           // InterfaceMethod java/util/List.get:(I)Ljava/lang/Object;
      21: checkcast     #43                 // class org/apache/hadoop/hbase/regionserver/HRegion
      24: astore_2
      25: aload_2
      26: invokevirtual #44                 // Method org/apache/hadoop/hbase/regionserver/HRegion.getRegionInfo:()Lorg/apache/hadoop/hbase/client/RegionInfo;
      29: astore_3
      30: aload_0
      31: invokevirtual #45                 // Method runwarmup:()V
      34: iconst_0
      35: istore        4
      37: iload         4
      39: bipush        10
      41: if_icmpge     142
      44: getstatic     #7                  // Field TEST_UTIL:Lorg/apache/hadoop/hbase/HBaseTestingUtility;
      47: invokevirtual #40                 // Method org/apache/hadoop/hbase/HBaseTestingUtility.getMiniHBaseCluster:()Lorg/apache/hadoop/hbase/MiniHBaseCluster;
      50: iload_1
      51: invokevirtual #46                 // Method org/apache/hadoop/hbase/MiniHBaseCluster.getRegionServer:(I)Lorg/apache/hadoop/hbase/regionserver/HRegionServer;
      54: astore        5
      56: aload         5
      58: invokevirtual #47                 // Method org/apache/hadoop/hbase/regionserver/HRegionServer.getServerName:()Lorg/apache/hadoop/hbase/ServerName;
      61: invokevirtual #48                 // Method org/apache/hadoop/hbase/ServerName.toString:()Ljava/lang/String;
      64: invokestatic  #49                 // Method org/apache/hadoop/hbase/util/Bytes.toBytes:(Ljava/lang/String;)[B
      67: astore        6
      69: aload         6
      71: ifnull        78
      74: iconst_1
      75: goto          79
      78: iconst_0
      79: invokestatic  #50                 // Method org/junit/Assert.assertTrue:(Z)V
      82: getstatic     #1                  // Field LOG:Lorg/slf4j/Logger;
      85: new           #51                 // class java/lang/StringBuilder
      88: dup
      89: invokespecial #52                 // Method java/lang/StringBuilder."<init>":()V
      92: ldc           #53                 // String i=
      94: invokevirtual #54                 // Method java/lang/StringBuilder.append:(Ljava/lang/String;)Ljava/lang/StringBuilder;
      97: iload         4
      99: invokevirtual #55                 // Method java/lang/StringBuilder.append:(I)Ljava/lang/StringBuilder;
     102: invokevirtual #56                 // Method java/lang/StringBuilder.toString:()Ljava/lang/String;
     105: invokeinterface #57,  2           // InterfaceMethod org/slf4j/Logger.info:(Ljava/lang/String;)V
     110: getstatic     #7                  // Field TEST_UTIL:Lorg/apache/hadoop/hbase/HBaseTestingUtility;
     113: invokevirtual #40                 // Method org/apache/hadoop/hbase/HBaseTestingUtility.getMiniHBaseCluster:()Lorg/apache/hadoop/hbase/MiniHBaseCluster;
     116: invokevirtual #58                 // Method org/apache/hadoop/hbase/MiniHBaseCluster.getMaster:()Lorg/apache/hadoop/hbase/master/HMaster;
     119: aload_3
     120: invokeinterface #59,  1           // InterfaceMethod org/apache/hadoop/hbase/client/RegionInfo.getEncodedNameAsBytes:()[B
     125: aload         6
     127: invokevirtual #60                 // Method org/apache/hadoop/hbase/master/HMaster.move:([B[B)V
     130: iload_1
     131: iconst_1
     132: iadd
     133: iconst_2
     134: irem
     135: istore_1
     136: iinc          4, 1
     139: goto          37
     142: return

  static org.apache.hadoop.hbase.client.Table access$000();
    Code:
       0: getstatic     #2                  // Field table:Lorg/apache/hadoop/hbase/client/Table;
       3: areturn

  static org.slf4j.Logger access$100();
    Code:
       0: getstatic     #1                  // Field LOG:Lorg/slf4j/Logger;
       3: areturn

  static {};
    Code:
       0: ldc           #61                 // class org/apache/hadoop/hbase/master/TestWarmupRegion
       2: invokestatic  #62                 // Method org/apache/hadoop/hbase/HBaseClassTestRule.forClass:(Ljava/lang/Class;)Lorg/apache/hadoop/hbase/HBaseClassTestRule;
       5: putstatic     #63                 // Field CLASS_RULE:Lorg/apache/hadoop/hbase/HBaseClassTestRule;
       8: ldc           #61                 // class org/apache/hadoop/hbase/master/TestWarmupRegion
      10: invokestatic  #64                 // Method org/slf4j/LoggerFactory.getLogger:(Ljava/lang/Class;)Lorg/slf4j/Logger;
      13: putstatic     #1                  // Field LOG:Lorg/slf4j/Logger;
      16: new           #65                 // class org/apache/hadoop/hbase/HBaseTestingUtility
      19: dup
      20: invokespecial #66                 // Method org/apache/hadoop/hbase/HBaseTestingUtility."<init>":()V
      23: putstatic     #7                  // Field TEST_UTIL:Lorg/apache/hadoop/hbase/HBaseTestingUtility;
      26: ldc           #67                 // String testRow
      28: invokestatic  #49                 // Method org/apache/hadoop/hbase/util/Bytes.toBytes:(Ljava/lang/String;)[B
      31: putstatic     #19                 // Field ROW:[B
      34: ldc           #68                 // String testFamily
      36: invokestatic  #49                 // Method org/apache/hadoop/hbase/util/Bytes.toBytes:(Ljava/lang/String;)[B
      39: putstatic     #12                 // Field FAMILY:[B
      42: ldc           #69                 // String testQualifier
      44: invokestatic  #49                 // Method org/apache/hadoop/hbase/util/Bytes.toBytes:(Ljava/lang/String;)[B
      47: putstatic     #70                 // Field QUALIFIER:[B
      50: ldc           #71                 // String testValue
      52: invokestatic  #49                 // Method org/apache/hadoop/hbase/util/Bytes.toBytes:(Ljava/lang/String;)[B
      55: putstatic     #22                 // Field VALUE:[B
      58: ldc           #72                 // String column
      60: invokestatic  #49                 // Method org/apache/hadoop/hbase/util/Bytes.toBytes:(Ljava/lang/String;)[B
      63: putstatic     #21                 // Field COLUMN:[B
      66: sipush        10000
      69: putstatic     #14                 // Field numRows:I
      72: iconst_3
      73: putstatic     #9                  // Field SLAVES:I
      76: return
}
