Compiled from "TestClientNoCluster.java"
class org.apache.hadoop.hbase.client.TestClientNoCluster$SimpleRegistry extends org.apache.hadoop.hbase.client.DoNothingAsyncRegistry {
  final org.apache.hadoop.hbase.ServerName META_HOST;

  public org.apache.hadoop.hbase.client.TestClientNoCluster$SimpleRegistry(org.apache.hadoop.conf.Configuration);
    Code:
       0: aload_0
       1: aload_1
       2: invokespecial #1                  // Method org/apache/hadoop/hbase/client/DoNothingAsyncRegistry."<init>":(Lorg/apache/hadoop/conf/Configuration;)V
       5: aload_0
       6: getstatic     #2                  // Field org/apache/hadoop/hbase/client/TestClientNoCluster.META_SERVERNAME:Lorg/apache/hadoop/hbase/ServerName;
       9: putfield      #3                  // Field META_HOST:Lorg/apache/hadoop/hbase/ServerName;
      12: return

  public java.util.concurrent.CompletableFuture<org.apache.hadoop.hbase.RegionLocations> getMetaRegionLocation();
    Code:
       0: new           #4                  // class org/apache/hadoop/hbase/RegionLocations
       3: dup
       4: iconst_1
       5: anewarray     #5                  // class org/apache/hadoop/hbase/HRegionLocation
       8: dup
       9: iconst_0
      10: new           #5                  // class org/apache/hadoop/hbase/HRegionLocation
      13: dup
      14: getstatic     #6                  // Field org/apache/hadoop/hbase/client/RegionInfoBuilder.FIRST_META_REGIONINFO:Lorg/apache/hadoop/hbase/client/RegionInfo;
      17: aload_0
      18: getfield      #3                  // Field META_HOST:Lorg/apache/hadoop/hbase/ServerName;
      21: invokespecial #7                  // Method org/apache/hadoop/hbase/HRegionLocation."<init>":(Lorg/apache/hadoop/hbase/client/RegionInfo;Lorg/apache/hadoop/hbase/ServerName;)V
      24: aastore
      25: invokespecial #8                  // Method org/apache/hadoop/hbase/RegionLocations."<init>":([Lorg/apache/hadoop/hbase/HRegionLocation;)V
      28: invokestatic  #9                  // Method java/util/concurrent/CompletableFuture.completedFuture:(Ljava/lang/Object;)Ljava/util/concurrent/CompletableFuture;
      31: areturn

  public java.util.concurrent.CompletableFuture<java.lang.String> getClusterId();
    Code:
       0: ldc           #11                 // String default-cluster
       2: invokestatic  #9                  // Method java/util/concurrent/CompletableFuture.completedFuture:(Ljava/lang/Object;)Ljava/util/concurrent/CompletableFuture;
       5: areturn

  public java.util.concurrent.CompletableFuture<java.lang.Integer> getCurrentNrHRS();
    Code:
       0: iconst_1
       1: invokestatic  #12                 // Method java/lang/Integer.valueOf:(I)Ljava/lang/Integer;
       4: invokestatic  #9                  // Method java/util/concurrent/CompletableFuture.completedFuture:(Ljava/lang/Object;)Ljava/util/concurrent/CompletableFuture;
       7: areturn
}
