Compiled from "TestHRegion.java"
final class org.apache.hadoop.hbase.regionserver.TestHRegion$6 implements org.mockito.stubbing.Answer<java.lang.Void> {
  final org.apache.hadoop.hbase.client.Put val$addPut;

  org.apache.hadoop.hbase.regionserver.TestHRegion$6(org.apache.hadoop.hbase.client.Put);
    Code:
       0: aload_0
       1: aload_1
       2: putfield      #1                  // Field val$addPut:Lorg/apache/hadoop/hbase/client/Put;
       5: aload_0
       6: invokespecial #2                  // Method java/lang/Object."<init>":()V
       9: return

  public java.lang.Void answer(org.mockito.invocation.InvocationOnMock) throws java.lang.Throwable;
    Code:
       0: aload_1
       1: iconst_0
       2: invokeinterface #3,  2            // InterfaceMethod org/mockito/invocation/InvocationOnMock.getArgument:(I)Ljava/lang/Object;
       7: checkcast     #4                  // class org/apache/hadoop/hbase/regionserver/MiniBatchOperationInProgress
      10: astore_2
      11: aload_2
      12: iconst_0
      13: iconst_1
      14: anewarray     #5                  // class org/apache/hadoop/hbase/client/Mutation
      17: dup
      18: iconst_0
      19: aload_0
      20: getfield      #1                  // Field val$addPut:Lorg/apache/hadoop/hbase/client/Put;
      23: aastore
      24: invokevirtual #6                  // Method org/apache/hadoop/hbase/regionserver/MiniBatchOperationInProgress.addOperationsFromCP:(I[Lorg/apache/hadoop/hbase/client/Mutation;)V
      27: aconst_null
      28: areturn

  public java.lang.Object answer(org.mockito.invocation.InvocationOnMock) throws java.lang.Throwable;
    Code:
       0: aload_0
       1: aload_1
       2: invokevirtual #7                  // Method answer:(Lorg/mockito/invocation/InvocationOnMock;)Ljava/lang/Void;
       5: areturn
}
