Compiled from "TestMasterBalanceThrottling.java"
class org.apache.hadoop.hbase.master.TestMasterBalanceThrottling$1 implements java.lang.Runnable {
  final java.util.concurrent.atomic.AtomicBoolean val$stop;

  final java.util.concurrent.atomic.AtomicInteger val$maxCount;

  final org.apache.hadoop.hbase.master.HMaster val$master;

  final org.apache.hadoop.hbase.master.TestMasterBalanceThrottling this$0;

  org.apache.hadoop.hbase.master.TestMasterBalanceThrottling$1(org.apache.hadoop.hbase.master.TestMasterBalanceThrottling, java.util.concurrent.atomic.AtomicBoolean, java.util.concurrent.atomic.AtomicInteger, org.apache.hadoop.hbase.master.HMaster);
    Code:
       0: aload_0
       1: aload_1
       2: putfield      #1                  // Field this$0:Lorg/apache/hadoop/hbase/master/TestMasterBalanceThrottling;
       5: aload_0
       6: aload_2
       7: putfield      #2                  // Field val$stop:Ljava/util/concurrent/atomic/AtomicBoolean;
      10: aload_0
      11: aload_3
      12: putfield      #3                  // Field val$maxCount:Ljava/util/concurrent/atomic/AtomicInteger;
      15: aload_0
      16: aload         4
      18: putfield      #4                  // Field val$master:Lorg/apache/hadoop/hbase/master/HMaster;
      21: aload_0
      22: invokespecial #5                  // Method java/lang/Object."<init>":()V
      25: return

  public void run();
    Code:
       0: aload_0
       1: getfield      #2                  // Field val$stop:Ljava/util/concurrent/atomic/AtomicBoolean;
       4: invokevirtual #6                  // Method java/util/concurrent/atomic/AtomicBoolean.get:()Z
       7: ifne          57
      10: aload_0
      11: getfield      #3                  // Field val$maxCount:Ljava/util/concurrent/atomic/AtomicInteger;
      14: aload_0
      15: getfield      #3                  // Field val$maxCount:Ljava/util/concurrent/atomic/AtomicInteger;
      18: invokevirtual #7                  // Method java/util/concurrent/atomic/AtomicInteger.get:()I
      21: aload_0
      22: getfield      #4                  // Field val$master:Lorg/apache/hadoop/hbase/master/HMaster;
      25: invokevirtual #8                  // Method org/apache/hadoop/hbase/master/HMaster.getAssignmentManager:()Lorg/apache/hadoop/hbase/master/assignment/AssignmentManager;
      28: invokevirtual #9                  // Method org/apache/hadoop/hbase/master/assignment/AssignmentManager.getRegionStates:()Lorg/apache/hadoop/hbase/master/assignment/RegionStates;
      31: invokevirtual #10                 // Method org/apache/hadoop/hbase/master/assignment/RegionStates.getRegionsInTransitionCount:()I
      34: invokestatic  #11                 // Method java/lang/Math.max:(II)I
      37: invokevirtual #12                 // Method java/util/concurrent/atomic/AtomicInteger.set:(I)V
      40: ldc2_w        #13                 // long 10l
      43: invokestatic  #15                 // Method java/lang/Thread.sleep:(J)V
      46: goto          0
      49: astore_1
      50: aload_1
      51: invokevirtual #17                 // Method java/lang/InterruptedException.printStackTrace:()V
      54: goto          0
      57: return
    Exception table:
       from    to  target type
          40    46    49   Class java/lang/InterruptedException
}
