Compiled from "TestGet.java"
public class org.apache.hadoop.hbase.client.TestGet {
  public static final org.apache.hadoop.hbase.HBaseClassTestRule CLASS_RULE;

  public org.apache.hadoop.hbase.client.TestGet();
    Code:
       0: aload_0
       1: invokespecial #1                  // Method java/lang/Object."<init>":()V
       4: return

  public void testAttributesSerialization() throws java.io.IOException;
    Code:
       0: new           #2                  // class org/apache/hadoop/hbase/client/Get
       3: dup
       4: ldc           #3                  // String row
       6: invokestatic  #4                  // Method org/apache/hadoop/hbase/util/Bytes.toBytes:(Ljava/lang/String;)[B
       9: invokespecial #5                  // Method org/apache/hadoop/hbase/client/Get."<init>":([B)V
      12: astore_1
      13: aload_1
      14: ldc           #6                  // String attribute1
      16: ldc           #7                  // String value1
      18: invokestatic  #4                  // Method org/apache/hadoop/hbase/util/Bytes.toBytes:(Ljava/lang/String;)[B
      21: invokevirtual #8                  // Method org/apache/hadoop/hbase/client/Get.setAttribute:(Ljava/lang/String;[B)Lorg/apache/hadoop/hbase/client/Get;
      24: pop
      25: aload_1
      26: ldc           #9                  // String attribute2
      28: ldc           #10                 // String value2
      30: invokestatic  #4                  // Method org/apache/hadoop/hbase/util/Bytes.toBytes:(Ljava/lang/String;)[B
      33: invokevirtual #8                  // Method org/apache/hadoop/hbase/client/Get.setAttribute:(Ljava/lang/String;[B)Lorg/apache/hadoop/hbase/client/Get;
      36: pop
      37: aload_1
      38: ldc           #11                 // String attribute3
      40: ldc           #12                 // String value3
      42: invokestatic  #4                  // Method org/apache/hadoop/hbase/util/Bytes.toBytes:(Ljava/lang/String;)[B
      45: invokevirtual #8                  // Method org/apache/hadoop/hbase/client/Get.setAttribute:(Ljava/lang/String;[B)Lorg/apache/hadoop/hbase/client/Get;
      48: pop
      49: aload_1
      50: invokestatic  #13                 // Method org/apache/hadoop/hbase/shaded/protobuf/ProtobufUtil.toGet:(Lorg/apache/hadoop/hbase/client/Get;)Lorg/apache/hadoop/hbase/shaded/protobuf/generated/ClientProtos$Get;
      53: astore_2
      54: aload_2
      55: invokestatic  #14                 // Method org/apache/hadoop/hbase/shaded/protobuf/ProtobufUtil.toGet:(Lorg/apache/hadoop/hbase/shaded/protobuf/generated/ClientProtos$Get;)Lorg/apache/hadoop/hbase/client/Get;
      58: astore_3
      59: aload_3
      60: ldc           #15                 // String absent
      62: invokevirtual #16                 // Method org/apache/hadoop/hbase/client/Get.getAttribute:(Ljava/lang/String;)[B
      65: invokestatic  #17                 // Method org/junit/Assert.assertNull:(Ljava/lang/Object;)V
      68: ldc           #7                  // String value1
      70: invokestatic  #4                  // Method org/apache/hadoop/hbase/util/Bytes.toBytes:(Ljava/lang/String;)[B
      73: aload_3
      74: ldc           #6                  // String attribute1
      76: invokevirtual #16                 // Method org/apache/hadoop/hbase/client/Get.getAttribute:(Ljava/lang/String;)[B
      79: invokestatic  #18                 // Method java/util/Arrays.equals:([B[B)Z
      82: invokestatic  #19                 // Method org/junit/Assert.assertTrue:(Z)V
      85: ldc           #10                 // String value2
      87: invokestatic  #4                  // Method org/apache/hadoop/hbase/util/Bytes.toBytes:(Ljava/lang/String;)[B
      90: aload_3
      91: ldc           #9                  // String attribute2
      93: invokevirtual #16                 // Method org/apache/hadoop/hbase/client/Get.getAttribute:(Ljava/lang/String;)[B
      96: invokestatic  #18                 // Method java/util/Arrays.equals:([B[B)Z
      99: invokestatic  #19                 // Method org/junit/Assert.assertTrue:(Z)V
     102: ldc           #12                 // String value3
     104: invokestatic  #4                  // Method org/apache/hadoop/hbase/util/Bytes.toBytes:(Ljava/lang/String;)[B
     107: aload_3
     108: ldc           #11                 // String attribute3
     110: invokevirtual #16                 // Method org/apache/hadoop/hbase/client/Get.getAttribute:(Ljava/lang/String;)[B
     113: invokestatic  #18                 // Method java/util/Arrays.equals:([B[B)Z
     116: invokestatic  #19                 // Method org/junit/Assert.assertTrue:(Z)V
     119: ldc2_w        #20                 // long 3l
     122: aload_3
     123: invokevirtual #22                 // Method org/apache/hadoop/hbase/client/Get.getAttributesMap:()Ljava/util/Map;
     126: invokeinterface #23,  1           // InterfaceMethod java/util/Map.size:()I
     131: i2l
     132: invokestatic  #24                 // Method org/junit/Assert.assertEquals:(JJ)V
     135: return

  public void testGetAttributes();
    Code:
       0: new           #2                  // class org/apache/hadoop/hbase/client/Get
       3: dup
       4: getstatic     #25                 // Field ROW:[B
       7: invokespecial #5                  // Method org/apache/hadoop/hbase/client/Get."<init>":([B)V
      10: astore_1
      11: aload_1
      12: invokevirtual #22                 // Method org/apache/hadoop/hbase/client/Get.getAttributesMap:()Ljava/util/Map;
      15: invokeinterface #26,  1           // InterfaceMethod java/util/Map.isEmpty:()Z
      20: invokestatic  #19                 // Method org/junit/Assert.assertTrue:(Z)V
      23: aload_1
      24: ldc           #15                 // String absent
      26: invokevirtual #16                 // Method org/apache/hadoop/hbase/client/Get.getAttribute:(Ljava/lang/String;)[B
      29: invokestatic  #17                 // Method org/junit/Assert.assertNull:(Ljava/lang/Object;)V
      32: aload_1
      33: ldc           #15                 // String absent
      35: aconst_null
      36: invokevirtual #8                  // Method org/apache/hadoop/hbase/client/Get.setAttribute:(Ljava/lang/String;[B)Lorg/apache/hadoop/hbase/client/Get;
      39: pop
      40: aload_1
      41: invokevirtual #22                 // Method org/apache/hadoop/hbase/client/Get.getAttributesMap:()Ljava/util/Map;
      44: invokeinterface #26,  1           // InterfaceMethod java/util/Map.isEmpty:()Z
      49: invokestatic  #19                 // Method org/junit/Assert.assertTrue:(Z)V
      52: aload_1
      53: ldc           #15                 // String absent
      55: invokevirtual #16                 // Method org/apache/hadoop/hbase/client/Get.getAttribute:(Ljava/lang/String;)[B
      58: invokestatic  #17                 // Method org/junit/Assert.assertNull:(Ljava/lang/Object;)V
      61: aload_1
      62: ldc           #6                  // String attribute1
      64: ldc           #7                  // String value1
      66: invokestatic  #4                  // Method org/apache/hadoop/hbase/util/Bytes.toBytes:(Ljava/lang/String;)[B
      69: invokevirtual #8                  // Method org/apache/hadoop/hbase/client/Get.setAttribute:(Ljava/lang/String;[B)Lorg/apache/hadoop/hbase/client/Get;
      72: pop
      73: ldc           #7                  // String value1
      75: invokestatic  #4                  // Method org/apache/hadoop/hbase/util/Bytes.toBytes:(Ljava/lang/String;)[B
      78: aload_1
      79: ldc           #6                  // String attribute1
      81: invokevirtual #16                 // Method org/apache/hadoop/hbase/client/Get.getAttribute:(Ljava/lang/String;)[B
      84: invokestatic  #18                 // Method java/util/Arrays.equals:([B[B)Z
      87: invokestatic  #19                 // Method org/junit/Assert.assertTrue:(Z)V
      90: lconst_1
      91: aload_1
      92: invokevirtual #22                 // Method org/apache/hadoop/hbase/client/Get.getAttributesMap:()Ljava/util/Map;
      95: invokeinterface #23,  1           // InterfaceMethod java/util/Map.size:()I
     100: i2l
     101: invokestatic  #24                 // Method org/junit/Assert.assertEquals:(JJ)V
     104: ldc           #7                  // String value1
     106: invokestatic  #4                  // Method org/apache/hadoop/hbase/util/Bytes.toBytes:(Ljava/lang/String;)[B
     109: aload_1
     110: invokevirtual #22                 // Method org/apache/hadoop/hbase/client/Get.getAttributesMap:()Ljava/util/Map;
     113: ldc           #6                  // String attribute1
     115: invokeinterface #27,  2           // InterfaceMethod java/util/Map.get:(Ljava/lang/Object;)Ljava/lang/Object;
     120: checkcast     #28                 // class "[B"
     123: invokestatic  #18                 // Method java/util/Arrays.equals:([B[B)Z
     126: invokestatic  #19                 // Method org/junit/Assert.assertTrue:(Z)V
     129: aload_1
     130: ldc           #6                  // String attribute1
     132: ldc           #29                 // String value12
     134: invokestatic  #4                  // Method org/apache/hadoop/hbase/util/Bytes.toBytes:(Ljava/lang/String;)[B
     137: invokevirtual #8                  // Method org/apache/hadoop/hbase/client/Get.setAttribute:(Ljava/lang/String;[B)Lorg/apache/hadoop/hbase/client/Get;
     140: pop
     141: ldc           #29                 // String value12
     143: invokestatic  #4                  // Method org/apache/hadoop/hbase/util/Bytes.toBytes:(Ljava/lang/String;)[B
     146: aload_1
     147: ldc           #6                  // String attribute1
     149: invokevirtual #16                 // Method org/apache/hadoop/hbase/client/Get.getAttribute:(Ljava/lang/String;)[B
     152: invokestatic  #18                 // Method java/util/Arrays.equals:([B[B)Z
     155: invokestatic  #19                 // Method org/junit/Assert.assertTrue:(Z)V
     158: lconst_1
     159: aload_1
     160: invokevirtual #22                 // Method org/apache/hadoop/hbase/client/Get.getAttributesMap:()Ljava/util/Map;
     163: invokeinterface #23,  1           // InterfaceMethod java/util/Map.size:()I
     168: i2l
     169: invokestatic  #24                 // Method org/junit/Assert.assertEquals:(JJ)V
     172: ldc           #29                 // String value12
     174: invokestatic  #4                  // Method org/apache/hadoop/hbase/util/Bytes.toBytes:(Ljava/lang/String;)[B
     177: aload_1
     178: invokevirtual #22                 // Method org/apache/hadoop/hbase/client/Get.getAttributesMap:()Ljava/util/Map;
     181: ldc           #6                  // String attribute1
     183: invokeinterface #27,  2           // InterfaceMethod java/util/Map.get:(Ljava/lang/Object;)Ljava/lang/Object;
     188: checkcast     #28                 // class "[B"
     191: invokestatic  #18                 // Method java/util/Arrays.equals:([B[B)Z
     194: invokestatic  #19                 // Method org/junit/Assert.assertTrue:(Z)V
     197: aload_1
     198: ldc           #9                  // String attribute2
     200: ldc           #10                 // String value2
     202: invokestatic  #4                  // Method org/apache/hadoop/hbase/util/Bytes.toBytes:(Ljava/lang/String;)[B
     205: invokevirtual #8                  // Method org/apache/hadoop/hbase/client/Get.setAttribute:(Ljava/lang/String;[B)Lorg/apache/hadoop/hbase/client/Get;
     208: pop
     209: ldc           #10                 // String value2
     211: invokestatic  #4                  // Method org/apache/hadoop/hbase/util/Bytes.toBytes:(Ljava/lang/String;)[B
     214: aload_1
     215: ldc           #9                  // String attribute2
     217: invokevirtual #16                 // Method org/apache/hadoop/hbase/client/Get.getAttribute:(Ljava/lang/String;)[B
     220: invokestatic  #18                 // Method java/util/Arrays.equals:([B[B)Z
     223: invokestatic  #19                 // Method org/junit/Assert.assertTrue:(Z)V
     226: ldc2_w        #30                 // long 2l
     229: aload_1
     230: invokevirtual #22                 // Method org/apache/hadoop/hbase/client/Get.getAttributesMap:()Ljava/util/Map;
     233: invokeinterface #23,  1           // InterfaceMethod java/util/Map.size:()I
     238: i2l
     239: invokestatic  #24                 // Method org/junit/Assert.assertEquals:(JJ)V
     242: ldc           #10                 // String value2
     244: invokestatic  #4                  // Method org/apache/hadoop/hbase/util/Bytes.toBytes:(Ljava/lang/String;)[B
     247: aload_1
     248: invokevirtual #22                 // Method org/apache/hadoop/hbase/client/Get.getAttributesMap:()Ljava/util/Map;
     251: ldc           #9                  // String attribute2
     253: invokeinterface #27,  2           // InterfaceMethod java/util/Map.get:(Ljava/lang/Object;)Ljava/lang/Object;
     258: checkcast     #28                 // class "[B"
     261: invokestatic  #18                 // Method java/util/Arrays.equals:([B[B)Z
     264: invokestatic  #19                 // Method org/junit/Assert.assertTrue:(Z)V
     267: aload_1
     268: ldc           #9                  // String attribute2
     270: aconst_null
     271: invokevirtual #8                  // Method org/apache/hadoop/hbase/client/Get.setAttribute:(Ljava/lang/String;[B)Lorg/apache/hadoop/hbase/client/Get;
     274: pop
     275: aload_1
     276: ldc           #9                  // String attribute2
     278: invokevirtual #16                 // Method org/apache/hadoop/hbase/client/Get.getAttribute:(Ljava/lang/String;)[B
     281: invokestatic  #17                 // Method org/junit/Assert.assertNull:(Ljava/lang/Object;)V
     284: lconst_1
     285: aload_1
     286: invokevirtual #22                 // Method org/apache/hadoop/hbase/client/Get.getAttributesMap:()Ljava/util/Map;
     289: invokeinterface #23,  1           // InterfaceMethod java/util/Map.size:()I
     294: i2l
     295: invokestatic  #24                 // Method org/junit/Assert.assertEquals:(JJ)V
     298: aload_1
     299: invokevirtual #22                 // Method org/apache/hadoop/hbase/client/Get.getAttributesMap:()Ljava/util/Map;
     302: ldc           #9                  // String attribute2
     304: invokeinterface #27,  2           // InterfaceMethod java/util/Map.get:(Ljava/lang/Object;)Ljava/lang/Object;
     309: invokestatic  #17                 // Method org/junit/Assert.assertNull:(Ljava/lang/Object;)V
     312: aload_1
     313: ldc           #9                  // String attribute2
     315: aconst_null
     316: invokevirtual #8                  // Method org/apache/hadoop/hbase/client/Get.setAttribute:(Ljava/lang/String;[B)Lorg/apache/hadoop/hbase/client/Get;
     319: pop
     320: aload_1
     321: ldc           #9                  // String attribute2
     323: invokevirtual #16                 // Method org/apache/hadoop/hbase/client/Get.getAttribute:(Ljava/lang/String;)[B
     326: invokestatic  #17                 // Method org/junit/Assert.assertNull:(Ljava/lang/Object;)V
     329: lconst_1
     330: aload_1
     331: invokevirtual #22                 // Method org/apache/hadoop/hbase/client/Get.getAttributesMap:()Ljava/util/Map;
     334: invokeinterface #23,  1           // InterfaceMethod java/util/Map.size:()I
     339: i2l
     340: invokestatic  #24                 // Method org/junit/Assert.assertEquals:(JJ)V
     343: aload_1
     344: invokevirtual #22                 // Method org/apache/hadoop/hbase/client/Get.getAttributesMap:()Ljava/util/Map;
     347: ldc           #9                  // String attribute2
     349: invokeinterface #27,  2           // InterfaceMethod java/util/Map.get:(Ljava/lang/Object;)Ljava/lang/Object;
     354: invokestatic  #17                 // Method org/junit/Assert.assertNull:(Ljava/lang/Object;)V
     357: aload_1
     358: ldc           #6                  // String attribute1
     360: aconst_null
     361: invokevirtual #8                  // Method org/apache/hadoop/hbase/client/Get.setAttribute:(Ljava/lang/String;[B)Lorg/apache/hadoop/hbase/client/Get;
     364: pop
     365: aload_1
     366: ldc           #6                  // String attribute1
     368: invokevirtual #16                 // Method org/apache/hadoop/hbase/client/Get.getAttribute:(Ljava/lang/String;)[B
     371: invokestatic  #17                 // Method org/junit/Assert.assertNull:(Ljava/lang/Object;)V
     374: aload_1
     375: invokevirtual #22                 // Method org/apache/hadoop/hbase/client/Get.getAttributesMap:()Ljava/util/Map;
     378: invokeinterface #26,  1           // InterfaceMethod java/util/Map.isEmpty:()Z
     383: invokestatic  #19                 // Method org/junit/Assert.assertTrue:(Z)V
     386: aload_1
     387: invokevirtual #22                 // Method org/apache/hadoop/hbase/client/Get.getAttributesMap:()Ljava/util/Map;
     390: ldc           #6                  // String attribute1
     392: invokeinterface #27,  2           // InterfaceMethod java/util/Map.get:(Ljava/lang/Object;)Ljava/lang/Object;
     397: invokestatic  #17                 // Method org/junit/Assert.assertNull:(Ljava/lang/Object;)V
     400: return

  public void testNullQualifier();
    Code:
       0: new           #2                  // class org/apache/hadoop/hbase/client/Get
       3: dup
       4: getstatic     #25                 // Field ROW:[B
       7: invokespecial #5                  // Method org/apache/hadoop/hbase/client/Get."<init>":([B)V
      10: astore_1
      11: ldc           #32                 // String family
      13: invokestatic  #4                  // Method org/apache/hadoop/hbase/util/Bytes.toBytes:(Ljava/lang/String;)[B
      16: astore_2
      17: aload_1
      18: aload_2
      19: aconst_null
      20: invokevirtual #33                 // Method org/apache/hadoop/hbase/client/Get.addColumn:([B[B)Lorg/apache/hadoop/hbase/client/Get;
      23: pop
      24: aload_1
      25: invokevirtual #34                 // Method org/apache/hadoop/hbase/client/Get.getFamilyMap:()Ljava/util/Map;
      28: aload_2
      29: invokeinterface #27,  2           // InterfaceMethod java/util/Map.get:(Ljava/lang/Object;)Ljava/lang/Object;
      34: checkcast     #35                 // class java/util/Set
      37: astore_3
      38: lconst_1
      39: aload_3
      40: invokeinterface #36,  1           // InterfaceMethod java/util/Set.size:()I
      45: i2l
      46: invokestatic  #24                 // Method org/junit/Assert.assertEquals:(JJ)V
      49: return

  public void TestGetRowFromGetCopyConstructor() throws java.lang.Exception;
    Code:
       0: new           #2                  // class org/apache/hadoop/hbase/client/Get
       3: dup
       4: getstatic     #25                 // Field ROW:[B
       7: invokespecial #5                  // Method org/apache/hadoop/hbase/client/Get."<init>":([B)V
      10: astore_1
      11: aload_1
      12: aconst_null
      13: invokevirtual #37                 // Method org/apache/hadoop/hbase/client/Get.setFilter:(Lorg/apache/hadoop/hbase/filter/Filter;)Lorg/apache/hadoop/hbase/client/Get;
      16: pop
      17: aload_1
      18: new           #38                 // class org/apache/hadoop/hbase/security/visibility/Authorizations
      21: dup
      22: iconst_1
      23: anewarray     #39                 // class java/lang/String
      26: dup
      27: iconst_0
      28: ldc           #40                 // String foo
      30: aastore
      31: invokespecial #41                 // Method org/apache/hadoop/hbase/security/visibility/Authorizations."<init>":([Ljava/lang/String;)V
      34: invokevirtual #42                 // Method org/apache/hadoop/hbase/client/Get.setAuthorizations:(Lorg/apache/hadoop/hbase/security/visibility/Authorizations;)Lorg/apache/hadoop/hbase/client/Get;
      37: pop
      38: aload_1
      39: ldc           #43                 // String u
      41: new           #44                 // class org/apache/hadoop/hbase/security/access/Permission
      44: dup
      45: iconst_1
      46: anewarray     #45                 // class org/apache/hadoop/hbase/security/access/Permission$Action
      49: dup
      50: iconst_0
      51: getstatic     #46                 // Field org/apache/hadoop/hbase/security/access/Permission$Action.READ:Lorg/apache/hadoop/hbase/security/access/Permission$Action;
      54: aastore
      55: invokespecial #47                 // Method org/apache/hadoop/hbase/security/access/Permission."<init>":([Lorg/apache/hadoop/hbase/security/access/Permission$Action;)V
      58: invokevirtual #48                 // Method org/apache/hadoop/hbase/client/Get.setACL:(Ljava/lang/String;Lorg/apache/hadoop/hbase/security/access/Permission;)Lorg/apache/hadoop/hbase/client/Get;
      61: pop
      62: aload_1
      63: getstatic     #49                 // Field org/apache/hadoop/hbase/client/Consistency.TIMELINE:Lorg/apache/hadoop/hbase/client/Consistency;
      66: invokevirtual #50                 // Method org/apache/hadoop/hbase/client/Get.setConsistency:(Lorg/apache/hadoop/hbase/client/Consistency;)Lorg/apache/hadoop/hbase/client/Get;
      69: pop
      70: aload_1
      71: iconst_2
      72: invokevirtual #51                 // Method org/apache/hadoop/hbase/client/Get.setReplicaId:(I)Lorg/apache/hadoop/hbase/client/Get;
      75: pop
      76: aload_1
      77: getstatic     #52                 // Field org/apache/hadoop/hbase/client/IsolationLevel.READ_UNCOMMITTED:Lorg/apache/hadoop/hbase/client/IsolationLevel;
      80: invokevirtual #53                 // Method org/apache/hadoop/hbase/client/Get.setIsolationLevel:(Lorg/apache/hadoop/hbase/client/IsolationLevel;)Lorg/apache/hadoop/hbase/client/Get;
      83: pop
      84: aload_1
      85: iconst_1
      86: invokevirtual #54                 // Method org/apache/hadoop/hbase/client/Get.setCheckExistenceOnly:(Z)Lorg/apache/hadoop/hbase/client/Get;
      89: pop
      90: aload_1
      91: ldc2_w        #20                 // long 3l
      94: ldc2_w        #55                 // long 4l
      97: invokevirtual #57                 // Method org/apache/hadoop/hbase/client/Get.setTimeRange:(JJ)Lorg/apache/hadoop/hbase/client/Get;
     100: pop
     101: aload_1
     102: bipush        11
     104: invokevirtual #58                 // Method org/apache/hadoop/hbase/client/Get.readVersions:(I)Lorg/apache/hadoop/hbase/client/Get;
     107: pop
     108: aload_1
     109: bipush        10
     111: invokevirtual #59                 // Method org/apache/hadoop/hbase/client/Get.setMaxResultsPerColumnFamily:(I)Lorg/apache/hadoop/hbase/client/Get;
     114: pop
     115: aload_1
     116: bipush        11
     118: invokevirtual #60                 // Method org/apache/hadoop/hbase/client/Get.setRowOffsetPerColumnFamily:(I)Lorg/apache/hadoop/hbase/client/Get;
     121: pop
     122: aload_1
     123: iconst_1
     124: invokevirtual #61                 // Method org/apache/hadoop/hbase/client/Get.setCacheBlocks:(Z)Lorg/apache/hadoop/hbase/client/Get;
     127: pop
     128: new           #2                  // class org/apache/hadoop/hbase/client/Get
     131: dup
     132: aload_1
     133: invokespecial #62                 // Method org/apache/hadoop/hbase/client/Get."<init>":(Lorg/apache/hadoop/hbase/client/Get;)V
     136: astore_2
     137: lconst_0
     138: aload_1
     139: invokevirtual #63                 // Method org/apache/hadoop/hbase/client/Get.getRow:()[B
     142: aload_2
     143: invokevirtual #63                 // Method org/apache/hadoop/hbase/client/Get.getRow:()[B
     146: invokestatic  #64                 // Method org/apache/hadoop/hbase/util/Bytes.compareTo:([B[B)I
     149: i2l
     150: invokestatic  #24                 // Method org/junit/Assert.assertEquals:(JJ)V
     153: aload_1
     154: invokevirtual #65                 // Method org/apache/hadoop/hbase/client/Get.getId:()Ljava/lang/String;
     157: aload_2
     158: invokevirtual #65                 // Method org/apache/hadoop/hbase/client/Get.getId:()Ljava/lang/String;
     161: invokestatic  #66                 // Method org/junit/Assert.assertEquals:(Ljava/lang/Object;Ljava/lang/Object;)V
     164: aload_1
     165: invokevirtual #67                 // Method org/apache/hadoop/hbase/client/Get.getFilter:()Lorg/apache/hadoop/hbase/filter/Filter;
     168: aload_2
     169: invokevirtual #67                 // Method org/apache/hadoop/hbase/client/Get.getFilter:()Lorg/apache/hadoop/hbase/filter/Filter;
     172: invokestatic  #66                 // Method org/junit/Assert.assertEquals:(Ljava/lang/Object;Ljava/lang/Object;)V
     175: aload_1
     176: invokevirtual #68                 // Method org/apache/hadoop/hbase/client/Get.getAuthorizations:()Lorg/apache/hadoop/hbase/security/visibility/Authorizations;
     179: invokevirtual #69                 // Method org/apache/hadoop/hbase/security/visibility/Authorizations.toString:()Ljava/lang/String;
     182: aload_2
     183: invokevirtual #68                 // Method org/apache/hadoop/hbase/client/Get.getAuthorizations:()Lorg/apache/hadoop/hbase/security/visibility/Authorizations;
     186: invokevirtual #69                 // Method org/apache/hadoop/hbase/security/visibility/Authorizations.toString:()Ljava/lang/String;
     189: invokevirtual #70                 // Method java/lang/String.equals:(Ljava/lang/Object;)Z
     192: invokestatic  #19                 // Method org/junit/Assert.assertTrue:(Z)V
     195: aload_1
     196: invokevirtual #71                 // Method org/apache/hadoop/hbase/client/Get.getACL:()[B
     199: aload_2
     200: invokevirtual #71                 // Method org/apache/hadoop/hbase/client/Get.getACL:()[B
     203: invokestatic  #72                 // Method org/apache/hadoop/hbase/util/Bytes.equals:([B[B)Z
     206: invokestatic  #19                 // Method org/junit/Assert.assertTrue:(Z)V
     209: aload_1
     210: invokevirtual #73                 // Method org/apache/hadoop/hbase/client/Get.getConsistency:()Lorg/apache/hadoop/hbase/client/Consistency;
     213: aload_2
     214: invokevirtual #73                 // Method org/apache/hadoop/hbase/client/Get.getConsistency:()Lorg/apache/hadoop/hbase/client/Consistency;
     217: invokestatic  #66                 // Method org/junit/Assert.assertEquals:(Ljava/lang/Object;Ljava/lang/Object;)V
     220: aload_1
     221: invokevirtual #74                 // Method org/apache/hadoop/hbase/client/Get.getReplicaId:()I
     224: i2l
     225: aload_2
     226: invokevirtual #74                 // Method org/apache/hadoop/hbase/client/Get.getReplicaId:()I
     229: i2l
     230: invokestatic  #24                 // Method org/junit/Assert.assertEquals:(JJ)V
     233: aload_1
     234: invokevirtual #75                 // Method org/apache/hadoop/hbase/client/Get.getIsolationLevel:()Lorg/apache/hadoop/hbase/client/IsolationLevel;
     237: aload_2
     238: invokevirtual #75                 // Method org/apache/hadoop/hbase/client/Get.getIsolationLevel:()Lorg/apache/hadoop/hbase/client/IsolationLevel;
     241: invokestatic  #66                 // Method org/junit/Assert.assertEquals:(Ljava/lang/Object;Ljava/lang/Object;)V
     244: aload_1
     245: invokevirtual #76                 // Method org/apache/hadoop/hbase/client/Get.isCheckExistenceOnly:()Z
     248: invokestatic  #77                 // Method java/lang/Boolean.valueOf:(Z)Ljava/lang/Boolean;
     251: aload_2
     252: invokevirtual #76                 // Method org/apache/hadoop/hbase/client/Get.isCheckExistenceOnly:()Z
     255: invokestatic  #77                 // Method java/lang/Boolean.valueOf:(Z)Ljava/lang/Boolean;
     258: invokestatic  #66                 // Method org/junit/Assert.assertEquals:(Ljava/lang/Object;Ljava/lang/Object;)V
     261: aload_1
     262: invokevirtual #78                 // Method org/apache/hadoop/hbase/client/Get.getTimeRange:()Lorg/apache/hadoop/hbase/io/TimeRange;
     265: aload_2
     266: invokevirtual #78                 // Method org/apache/hadoop/hbase/client/Get.getTimeRange:()Lorg/apache/hadoop/hbase/io/TimeRange;
     269: invokevirtual #79                 // Method java/lang/Object.equals:(Ljava/lang/Object;)Z
     272: invokestatic  #19                 // Method org/junit/Assert.assertTrue:(Z)V
     275: aload_1
     276: invokevirtual #80                 // Method org/apache/hadoop/hbase/client/Get.getMaxVersions:()I
     279: i2l
     280: aload_2
     281: invokevirtual #80                 // Method org/apache/hadoop/hbase/client/Get.getMaxVersions:()I
     284: i2l
     285: invokestatic  #24                 // Method org/junit/Assert.assertEquals:(JJ)V
     288: aload_1
     289: invokevirtual #81                 // Method org/apache/hadoop/hbase/client/Get.getMaxResultsPerColumnFamily:()I
     292: i2l
     293: aload_2
     294: invokevirtual #81                 // Method org/apache/hadoop/hbase/client/Get.getMaxResultsPerColumnFamily:()I
     297: i2l
     298: invokestatic  #24                 // Method org/junit/Assert.assertEquals:(JJ)V
     301: aload_1
     302: invokevirtual #82                 // Method org/apache/hadoop/hbase/client/Get.getRowOffsetPerColumnFamily:()I
     305: i2l
     306: aload_2
     307: invokevirtual #82                 // Method org/apache/hadoop/hbase/client/Get.getRowOffsetPerColumnFamily:()I
     310: i2l
     311: invokestatic  #24                 // Method org/junit/Assert.assertEquals:(JJ)V
     314: aload_1
     315: invokevirtual #83                 // Method org/apache/hadoop/hbase/client/Get.getCacheBlocks:()Z
     318: invokestatic  #77                 // Method java/lang/Boolean.valueOf:(Z)Ljava/lang/Boolean;
     321: aload_2
     322: invokevirtual #83                 // Method org/apache/hadoop/hbase/client/Get.getCacheBlocks:()Z
     325: invokestatic  #77                 // Method java/lang/Boolean.valueOf:(Z)Ljava/lang/Boolean;
     328: invokestatic  #66                 // Method org/junit/Assert.assertEquals:(Ljava/lang/Object;Ljava/lang/Object;)V
     331: aload_1
     332: invokevirtual #65                 // Method org/apache/hadoop/hbase/client/Get.getId:()Ljava/lang/String;
     335: aload_2
     336: invokevirtual #65                 // Method org/apache/hadoop/hbase/client/Get.getId:()Ljava/lang/String;
     339: invokestatic  #66                 // Method org/junit/Assert.assertEquals:(Ljava/lang/Object;Ljava/lang/Object;)V
     342: return

  public void testDynamicFilter() throws java.lang.Exception;
    Code:
       0: invokestatic  #84                 // Method org/apache/hadoop/hbase/HBaseConfiguration.create:()Lorg/apache/hadoop/conf/Configuration;
       3: astore_1
       4: new           #85                 // class java/lang/StringBuilder
       7: dup
       8: invokespecial #86                 // Method java/lang/StringBuilder."<init>":()V
      11: aload_1
      12: ldc           #87                 // String hbase.local.dir
      14: invokevirtual #88                 // Method org/apache/hadoop/conf/Configuration.get:(Ljava/lang/String;)Ljava/lang/String;
      17: invokevirtual #89                 // Method java/lang/StringBuilder.append:(Ljava/lang/String;)Ljava/lang/StringBuilder;
      20: getstatic     #90                 // Field java/io/File.separator:Ljava/lang/String;
      23: invokevirtual #89                 // Method java/lang/StringBuilder.append:(Ljava/lang/String;)Ljava/lang/StringBuilder;
      26: ldc           #91                 // String jars
      28: invokevirtual #89                 // Method java/lang/StringBuilder.append:(Ljava/lang/String;)Ljava/lang/StringBuilder;
      31: getstatic     #90                 // Field java/io/File.separator:Ljava/lang/String;
      34: invokevirtual #89                 // Method java/lang/StringBuilder.append:(Ljava/lang/String;)Ljava/lang/StringBuilder;
      37: invokevirtual #92                 // Method java/lang/StringBuilder.toString:()Ljava/lang/String;
      40: astore_2
      41: new           #93                 // class java/io/File
      44: dup
      45: aload_2
      46: ldc           #94                 // String MockFilter.jar
      48: invokespecial #95                 // Method java/io/File."<init>":(Ljava/lang/String;Ljava/lang/String;)V
      51: astore_3
      52: aload_3
      53: invokevirtual #96                 // Method java/io/File.delete:()Z
      56: pop
      57: new           #85                 // class java/lang/StringBuilder
      60: dup
      61: invokespecial #86                 // Method java/lang/StringBuilder."<init>":()V
      64: ldc           #97                 // String Should be deleted:
      66: invokevirtual #89                 // Method java/lang/StringBuilder.append:(Ljava/lang/String;)Ljava/lang/StringBuilder;
      69: aload_3
      70: invokevirtual #98                 // Method java/io/File.getPath:()Ljava/lang/String;
      73: invokevirtual #89                 // Method java/lang/StringBuilder.append:(Ljava/lang/String;)Ljava/lang/StringBuilder;
      76: invokevirtual #92                 // Method java/lang/StringBuilder.toString:()Ljava/lang/String;
      79: aload_3
      80: invokevirtual #99                 // Method java/io/File.exists:()Z
      83: invokestatic  #100                // Method org/junit/Assert.assertFalse:(Ljava/lang/String;Z)V
      86: invokestatic  #101                // Method java/util/Base64.getDecoder:()Ljava/util/Base64$Decoder;
      89: ldc           #103                // String CgNyb3ciEwoPdGVzdC5Nb2NrRmlsdGVyEgAwATgB
      91: invokevirtual #104                // Method java/util/Base64$Decoder.decode:(Ljava/lang/String;)[B
      94: invokestatic  #105                // Method org/apache/hadoop/hbase/shaded/protobuf/generated/ClientProtos$Get.parseFrom:([B)Lorg/apache/hadoop/hbase/shaded/protobuf/generated/ClientProtos$Get;
      97: astore        4
      99: invokestatic  #101                // Method java/util/Base64.getDecoder:()Ljava/util/Base64$Decoder;
     102: ldc           #106                // String CgFyIosBCilvcmcuYXBhY2hlLmhhZG9vcC5oYmFzZS5maWx0ZXIuRmlsdGVyTGlzdBJeCAESEwoPdGVzdC5Nb2NrRmlsdGVyEgASEQoNbXkuTW9ja0ZpbHRlchIAEjIKLG9yZy5hcGFjaGUuaGFkb29wLmhiYXNlLmZpbHRlci5LZXlPbmx5RmlsdGVyEgIIADABOAE=
     104: invokevirtual #104                // Method java/util/Base64$Decoder.decode:(Ljava/lang/String;)[B
     107: invokestatic  #105                // Method org/apache/hadoop/hbase/shaded/protobuf/generated/ClientProtos$Get.parseFrom:([B)Lorg/apache/hadoop/hbase/shaded/protobuf/generated/ClientProtos$Get;
     110: astore        5
     112: aload         4
     114: invokestatic  #14                 // Method org/apache/hadoop/hbase/shaded/protobuf/ProtobufUtil.toGet:(Lorg/apache/hadoop/hbase/shaded/protobuf/generated/ClientProtos$Get;)Lorg/apache/hadoop/hbase/client/Get;
     117: pop
     118: ldc           #107                // String Should not be able to load the filter class
     120: invokestatic  #108                // Method org/junit/Assert.fail:(Ljava/lang/String;)V
     123: goto          139
     126: astore        6
     128: aload         6
     130: invokevirtual #110                // Method java/io/IOException.getCause:()Ljava/lang/Throwable;
     133: instanceof    #111                // class java/lang/ClassNotFoundException
     136: invokestatic  #19                 // Method org/junit/Assert.assertTrue:(Z)V
     139: aload         5
     141: invokestatic  #14                 // Method org/apache/hadoop/hbase/shaded/protobuf/ProtobufUtil.toGet:(Lorg/apache/hadoop/hbase/shaded/protobuf/generated/ClientProtos$Get;)Lorg/apache/hadoop/hbase/client/Get;
     144: pop
     145: ldc           #107                // String Should not be able to load the filter class
     147: invokestatic  #108                // Method org/junit/Assert.fail:(Ljava/lang/String;)V
     150: goto          187
     153: astore        6
     155: aload         6
     157: invokevirtual #110                // Method java/io/IOException.getCause:()Ljava/lang/Throwable;
     160: instanceof    #112                // class java/lang/reflect/InvocationTargetException
     163: invokestatic  #19                 // Method org/junit/Assert.assertTrue:(Z)V
     166: aload         6
     168: invokevirtual #110                // Method java/io/IOException.getCause:()Ljava/lang/Throwable;
     171: checkcast     #112                // class java/lang/reflect/InvocationTargetException
     174: astore        7
     176: aload         7
     178: invokevirtual #113                // Method java/lang/reflect/InvocationTargetException.getTargetException:()Ljava/lang/Throwable;
     181: instanceof    #114                // class org/apache/hadoop/hbase/exceptions/DeserializationException
     184: invokestatic  #19                 // Method org/junit/Assert.assertTrue:(Z)V
     187: new           #115                // class java/io/FileOutputStream
     190: dup
     191: aload_3
     192: invokespecial #116                // Method java/io/FileOutputStream."<init>":(Ljava/io/File;)V
     195: astore        6
     197: aload         6
     199: invokestatic  #101                // Method java/util/Base64.getDecoder:()Ljava/util/Base64$Decoder;
     202: ldc           #117                // String UEsDBBQACAgIANWDlEMAAAAAAAAAAAAAAAAJAAQATUVUQS1JTkYv/soAAAMAUEsHCAAAAAACAAAAAAAAAFBLAwQUAAgICADVg5RDAAAAAAAAAAAAAAAAFAAAAE1FVEEtSU5GL01BTklGRVNULk1G803My0xLLS7RDUstKs7Mz7NSMNQz4OVyLkpNLElN0XWqBAmY6xnEG1gqaPgXJSbnpCo45xcV5BcllgCVa/Jy8XIBAFBLBwgxyqRbQwAAAEQAAABQSwMEFAAICAgAUoOUQwAAAAAAAAAAAAAAABMAAABteS9Nb2NrRmlsdGVyLmNsYXNzdZHPTsJAEMa/LYVCRVFQMd68gQc38YrxUJUTetGQGE7bstrVwjbbYsSn0hOJJj6AD2WcFoP/4iYzX+bb32xmd9/en18B7GPLhY11BxsurEw3GUoHaqzSQ4ZCq91nsI/0UDLUemoszyYjX5oL4Ufk1Hs6EFFfGJXVn6adhirJ6NGUn+rgtquiVJoOQyUWJpFdo0cMjdbAa/8hnNj3pqmkbmvgMbgn94GMU6XHiYMm1ed6YgJJeDbNV+fejbgTVRRRYlj+cSZDW5trLmIRhJKHYqh1zENfJJJf5QCfcx45DJ3/WLmYgx/LRNJ1I/UgMmMxIXbo9WxkywLLZqHsUMVJGWlxdwb2lG+XKZdys4kK5eocgIsl0grVy0Q5+e9Y+V75BdblDIXHX/3b3/rLWEGNdJXCJmeNop7zjQ9QSwcI1kzyMToBAADsAQAAUEsDBBQACAgIAFKDlEMAAAAAAAAAAAAAAAAVAAAAdGVzdC9Nb2NrRmlsdGVyLmNsYXNzdVHBTsJAFJwthUJFERQx3ryBBzfxivFQlRN60ZAYTtuy2tXCNtti1K/SE4kmfoAfZXwtBg3RTd6bzOy8zezux+frO4ADbLuwsemg6cLKcIuhdKgmKj1iKLQ7Awb7WI8kQ62vJvJ8OvaluRR+REqjrwMRDYRRGf8W7TRUCUO9n8ok5Wc6uOupKJWmy1CJhUlkz+gxQ7M99Dp/eJzY9x5JZrCGHoN7+hDIOFV6kjhoEb/QUxNIsmeJfib3b8W9qKKIEslLpzJ0tLnhIhZBKHkoRlrHPPRFIvl1buBzn0cKQ/c/r1wk4ScykXTpSD2JTFhkxC69oY1sWWBZGuoOMU7ICIt7M7CXfLtMvZSLLVSoV+cGuFghrBBfJZeT/5GV75XfYF3NUHhemt/5NV/GGmqE61Q2KXWqRu7f+AJQSwcIrS5nKDoBAADyAQAAUEsBAhQAFAAICAgA1YOUQwAAAAACAAAAAAAAAAkABAAAAAAAAAAAAAAAAAAAAE1FVEEtSU5GL/7KAABQSwECFAAUAAgICADVg5RDMcqkW0MAAABEAAAAFAAAAAAAAAAAAAAAAAA9AAAATUVUQS1JTkYvTUFOSUZFU1QuTUZQSwECFAAUAAgICABSg5RD1kzyMToBAADsAQAAEwAAAAAAAAAAAAAAAADCAAAAbXkvTW9ja0ZpbHRlci5jbGFzc1BLAQIUABQACAgIAFKDlEOtLmcoOgEAAPIBAAAVAAAAAAAAAAAAAAAAAD0CAAB0ZXN0L01vY2tGaWx0ZXIuY2xhc3NQSwUGAAAAAAQABAABAQAAugMAAAAA
     204: invokevirtual #104                // Method java/util/Base64$Decoder.decode:(Ljava/lang/String;)[B
     207: invokevirtual #118                // Method java/io/FileOutputStream.write:([B)V
     210: aload         6
     212: invokevirtual #119                // Method java/io/FileOutputStream.close:()V
     215: aload         4
     217: invokestatic  #14                 // Method org/apache/hadoop/hbase/shaded/protobuf/ProtobufUtil.toGet:(Lorg/apache/hadoop/hbase/shaded/protobuf/generated/ClientProtos$Get;)Lorg/apache/hadoop/hbase/client/Get;
     220: astore        7
     222: ldc           #120                // String test.MockFilter
     224: aload         7
     226: invokevirtual #67                 // Method org/apache/hadoop/hbase/client/Get.getFilter:()Lorg/apache/hadoop/hbase/filter/Filter;
     229: invokevirtual #121                // Method java/lang/Object.getClass:()Ljava/lang/Class;
     232: invokevirtual #122                // Method java/lang/Class.getName:()Ljava/lang/String;
     235: invokestatic  #66                 // Method org/junit/Assert.assertEquals:(Ljava/lang/Object;Ljava/lang/Object;)V
     238: aload         5
     240: invokestatic  #14                 // Method org/apache/hadoop/hbase/shaded/protobuf/ProtobufUtil.toGet:(Lorg/apache/hadoop/hbase/shaded/protobuf/generated/ClientProtos$Get;)Lorg/apache/hadoop/hbase/client/Get;
     243: astore        8
     245: aload         8
     247: invokevirtual #67                 // Method org/apache/hadoop/hbase/client/Get.getFilter:()Lorg/apache/hadoop/hbase/filter/Filter;
     250: instanceof    #123                // class org/apache/hadoop/hbase/filter/FilterList
     253: invokestatic  #19                 // Method org/junit/Assert.assertTrue:(Z)V
     256: aload         8
     258: invokevirtual #67                 // Method org/apache/hadoop/hbase/client/Get.getFilter:()Lorg/apache/hadoop/hbase/filter/Filter;
     261: checkcast     #123                // class org/apache/hadoop/hbase/filter/FilterList
     264: invokevirtual #124                // Method org/apache/hadoop/hbase/filter/FilterList.getFilters:()Ljava/util/List;
     267: astore        9
     269: ldc2_w        #20                 // long 3l
     272: aload         9
     274: invokeinterface #125,  1          // InterfaceMethod java/util/List.size:()I
     279: i2l
     280: invokestatic  #24                 // Method org/junit/Assert.assertEquals:(JJ)V
     283: ldc           #120                // String test.MockFilter
     285: aload         9
     287: iconst_0
     288: invokeinterface #126,  2          // InterfaceMethod java/util/List.get:(I)Ljava/lang/Object;
     293: checkcast     #127                // class org/apache/hadoop/hbase/filter/Filter
     296: invokevirtual #121                // Method java/lang/Object.getClass:()Ljava/lang/Class;
     299: invokevirtual #122                // Method java/lang/Class.getName:()Ljava/lang/String;
     302: invokestatic  #66                 // Method org/junit/Assert.assertEquals:(Ljava/lang/Object;Ljava/lang/Object;)V
     305: ldc           #128                // String my.MockFilter
     307: aload         9
     309: iconst_1
     310: invokeinterface #126,  2          // InterfaceMethod java/util/List.get:(I)Ljava/lang/Object;
     315: checkcast     #127                // class org/apache/hadoop/hbase/filter/Filter
     318: invokevirtual #121                // Method java/lang/Object.getClass:()Ljava/lang/Class;
     321: invokevirtual #122                // Method java/lang/Class.getName:()Ljava/lang/String;
     324: invokestatic  #66                 // Method org/junit/Assert.assertEquals:(Ljava/lang/Object;Ljava/lang/Object;)V
     327: aload         9
     329: iconst_2
     330: invokeinterface #126,  2          // InterfaceMethod java/util/List.get:(I)Ljava/lang/Object;
     335: instanceof    #129                // class org/apache/hadoop/hbase/filter/KeyOnlyFilter
     338: invokestatic  #19                 // Method org/junit/Assert.assertTrue:(Z)V
     341: return
    Exception table:
       from    to  target type
         112   123   126   Class java/io/IOException
         139   150   153   Class java/io/IOException

  public void testGetRowConstructor();
    Code:
       0: ldc           #130                // String testRow
       2: invokestatic  #4                  // Method org/apache/hadoop/hbase/util/Bytes.toBytes:(Ljava/lang/String;)[B
       5: astore_1
       6: ldc           #131                // String testtestRow
       8: invokestatic  #4                  // Method org/apache/hadoop/hbase/util/Bytes.toBytes:(Ljava/lang/String;)[B
      11: astore_2
      12: bipush        16
      14: invokestatic  #132                // Method java/nio/ByteBuffer.allocate:(I)Ljava/nio/ByteBuffer;
      17: astore_3
      18: aload_1
      19: invokestatic  #133                // Method java/nio/ByteBuffer.wrap:([B)Ljava/nio/ByteBuffer;
      22: astore_3
      23: new           #2                  // class org/apache/hadoop/hbase/client/Get
      26: dup
      27: aload_3
      28: invokespecial #134                // Method org/apache/hadoop/hbase/client/Get."<init>":(Ljava/nio/ByteBuffer;)V
      31: astore        4
      33: new           #2                  // class org/apache/hadoop/hbase/client/Get
      36: dup
      37: aload_2
      38: iconst_4
      39: bipush        7
      41: invokespecial #135                // Method org/apache/hadoop/hbase/client/Get."<init>":([BII)V
      44: astore        5
      46: aload         4
      48: invokevirtual #63                 // Method org/apache/hadoop/hbase/client/Get.getRow:()[B
      51: aload         5
      53: invokevirtual #63                 // Method org/apache/hadoop/hbase/client/Get.getRow:()[B
      56: invokestatic  #136                // Method org/junit/Assert.assertArrayEquals:([B[B)V
      59: return

  static {};
    Code:
       0: ldc           #102                // class org/apache/hadoop/hbase/client/TestGet
       2: invokestatic  #137                // Method org/apache/hadoop/hbase/HBaseClassTestRule.forClass:(Ljava/lang/Class;)Lorg/apache/hadoop/hbase/HBaseClassTestRule;
       5: putstatic     #138                // Field CLASS_RULE:Lorg/apache/hadoop/hbase/HBaseClassTestRule;
       8: iconst_1
       9: newarray       byte
      11: dup
      12: iconst_0
      13: bipush        114
      15: bastore
      16: putstatic     #25                 // Field ROW:[B
      19: return
}
