Compiled from "TestReportOnlineRegionsRace.java"
public final class org.apache.hadoop.hbase.master.assignment.TestReportOnlineRegionsRace$HMasterForTest extends org.apache.hadoop.hbase.master.HMaster {
  public org.apache.hadoop.hbase.master.assignment.TestReportOnlineRegionsRace$HMasterForTest(org.apache.hadoop.conf.Configuration) throws java.io.IOException, org.apache.zookeeper.KeeperException;
    Code:
       0: aload_0
       1: aload_1
       2: invokespecial #1                  // Method org/apache/hadoop/hbase/master/HMaster."<init>":(Lorg/apache/hadoop/conf/Configuration;)V
       5: return

  protected org.apache.hadoop.hbase.master.assignment.AssignmentManager createAssignmentManager(org.apache.hadoop.hbase.master.MasterServices);
    Code:
       0: new           #2                  // class org/apache/hadoop/hbase/master/assignment/TestReportOnlineRegionsRace$AssignmentManagerForTest
       3: dup
       4: aload_1
       5: invokespecial #3                  // Method org/apache/hadoop/hbase/master/assignment/TestReportOnlineRegionsRace$AssignmentManagerForTest."<init>":(Lorg/apache/hadoop/hbase/master/MasterServices;)V
       8: areturn
}
