Compiled from "TestHBaseSaslRpcClient.java"
public class org.apache.hadoop.hbase.security.TestHBaseSaslRpcClient {
  public static final org.apache.hadoop.hbase.HBaseClassTestRule CLASS_RULE;

  static final java.lang.String DEFAULT_USER_NAME;

  static final java.lang.String DEFAULT_USER_PASSWORD;

  public org.junit.rules.ExpectedException exception;

  public org.apache.hadoop.hbase.security.TestHBaseSaslRpcClient();
    Code:
       0: aload_0
       1: invokespecial #1                  // Method java/lang/Object."<init>":()V
       4: aload_0
       5: invokestatic  #2                  // Method org/junit/rules/ExpectedException.none:()Lorg/junit/rules/ExpectedException;
       8: putfield      #3                  // Field exception:Lorg/junit/rules/ExpectedException;
      11: return

  public static void before();
    Code:
       0: invokestatic  #4                  // Method org/apache/log4j/Logger.getRootLogger:()Lorg/apache/log4j/Logger;
       3: getstatic     #5                  // Field org/apache/log4j/Level.DEBUG:Lorg/apache/log4j/Level;
       6: invokevirtual #6                  // Method org/apache/log4j/Logger.setLevel:(Lorg/apache/log4j/Level;)V
       9: return

  public void testSaslClientUsesGivenRpcProtection() throws java.lang.Exception;
    Code:
       0: aload_0
       1: ldc           #8                  // String principal
       3: ldc           #9                  // String password
       5: invokespecial #10                 // Method createTokenMockWithCredentials:(Ljava/lang/String;Ljava/lang/String;)Lorg/apache/hadoop/security/token/Token;
       8: astore_1
       9: invokestatic  #11                 // Method org/apache/hadoop/hbase/security/SaslUtil$QualityOfProtection.values:()[Lorg/apache/hadoop/hbase/security/SaslUtil$QualityOfProtection;
      12: astore_2
      13: aload_2
      14: arraylength
      15: istore_3
      16: iconst_0
      17: istore        4
      19: iload         4
      21: iload_3
      22: if_icmpge     73
      25: aload_2
      26: iload         4
      28: aaload
      29: astore        5
      31: new           #12                 // class org/apache/hadoop/hbase/security/TestHBaseSaslRpcClient$1
      34: dup
      35: aload_0
      36: getstatic     #13                 // Field org/apache/hadoop/hbase/security/AuthMethod.DIGEST:Lorg/apache/hadoop/hbase/security/AuthMethod;
      39: aload_1
      40: ldc           #14                 // String principal/host@DOMAIN.COM
      42: iconst_0
      43: aload         5
      45: invokevirtual #15                 // Method org/apache/hadoop/hbase/security/SaslUtil$QualityOfProtection.name:()Ljava/lang/String;
      48: iconst_0
      49: invokespecial #16                 // Method org/apache/hadoop/hbase/security/TestHBaseSaslRpcClient$1."<init>":(Lorg/apache/hadoop/hbase/security/TestHBaseSaslRpcClient;Lorg/apache/hadoop/hbase/security/AuthMethod;Lorg/apache/hadoop/security/token/Token;Ljava/lang/String;ZLjava/lang/String;Z)V
      52: invokevirtual #17                 // Method org/apache/hadoop/hbase/security/TestHBaseSaslRpcClient$1.getQop:()Ljava/lang/String;
      55: astore        6
      57: aload         6
      59: aload         5
      61: invokevirtual #18                 // Method org/apache/hadoop/hbase/security/SaslUtil$QualityOfProtection.getSaslQop:()Ljava/lang/String;
      64: invokestatic  #19                 // Method org/junit/Assert.assertEquals:(Ljava/lang/Object;Ljava/lang/Object;)V
      67: iinc          4, 1
      70: goto          19
      73: return

  public void testSaslClientCallbackHandler() throws javax.security.auth.callback.UnsupportedCallbackException;
    Code:
       0: aload_0
       1: invokespecial #20                 // Method createTokenMock:()Lorg/apache/hadoop/security/token/Token;
       4: astore_1
       5: aload_1
       6: invokevirtual #21                 // Method org/apache/hadoop/security/token/Token.getIdentifier:()[B
       9: invokestatic  #22                 // Method org/mockito/Mockito.when:(Ljava/lang/Object;)Lorg/mockito/stubbing/OngoingStubbing;
      12: ldc           #8                  // String principal
      14: invokestatic  #23                 // Method org/apache/hadoop/hbase/util/Bytes.toBytes:(Ljava/lang/String;)[B
      17: invokeinterface #24,  2           // InterfaceMethod org/mockito/stubbing/OngoingStubbing.thenReturn:(Ljava/lang/Object;)Lorg/mockito/stubbing/OngoingStubbing;
      22: pop
      23: aload_1
      24: invokevirtual #25                 // Method org/apache/hadoop/security/token/Token.getPassword:()[B
      27: invokestatic  #22                 // Method org/mockito/Mockito.when:(Ljava/lang/Object;)Lorg/mockito/stubbing/OngoingStubbing;
      30: ldc           #9                  // String password
      32: invokestatic  #23                 // Method org/apache/hadoop/hbase/util/Bytes.toBytes:(Ljava/lang/String;)[B
      35: invokeinterface #24,  2           // InterfaceMethod org/mockito/stubbing/OngoingStubbing.thenReturn:(Ljava/lang/Object;)Lorg/mockito/stubbing/OngoingStubbing;
      40: pop
      41: ldc           #26                 // class javax/security/auth/callback/NameCallback
      43: invokestatic  #27                 // Method org/mockito/Mockito.mock:(Ljava/lang/Class;)Ljava/lang/Object;
      46: checkcast     #26                 // class javax/security/auth/callback/NameCallback
      49: astore_2
      50: ldc           #28                 // class javax/security/auth/callback/PasswordCallback
      52: invokestatic  #27                 // Method org/mockito/Mockito.mock:(Ljava/lang/Class;)Ljava/lang/Object;
      55: checkcast     #28                 // class javax/security/auth/callback/PasswordCallback
      58: astore_3
      59: ldc           #29                 // class javax/security/sasl/RealmCallback
      61: invokestatic  #27                 // Method org/mockito/Mockito.mock:(Ljava/lang/Class;)Ljava/lang/Object;
      64: checkcast     #29                 // class javax/security/sasl/RealmCallback
      67: astore        4
      69: ldc           #30                 // class javax/security/sasl/RealmChoiceCallback
      71: invokestatic  #27                 // Method org/mockito/Mockito.mock:(Ljava/lang/Class;)Ljava/lang/Object;
      74: checkcast     #30                 // class javax/security/sasl/RealmChoiceCallback
      77: astore        5
      79: iconst_4
      80: anewarray     #31                 // class javax/security/auth/callback/Callback
      83: dup
      84: iconst_0
      85: aload_2
      86: aastore
      87: dup
      88: iconst_1
      89: aload_3
      90: aastore
      91: dup
      92: iconst_2
      93: aload         4
      95: aastore
      96: dup
      97: iconst_3
      98: aload         5
     100: aastore
     101: astore        6
     103: new           #32                 // class org/apache/hadoop/hbase/security/AbstractHBaseSaslRpcClient$SaslClientCallbackHandler
     106: dup
     107: aload_1
     108: invokespecial #33                 // Method org/apache/hadoop/hbase/security/AbstractHBaseSaslRpcClient$SaslClientCallbackHandler."<init>":(Lorg/apache/hadoop/security/token/Token;)V
     111: astore        7
     113: aload         7
     115: aload         6
     117: invokevirtual #34                 // Method org/apache/hadoop/hbase/security/AbstractHBaseSaslRpcClient$SaslClientCallbackHandler.handle:([Ljavax/security/auth/callback/Callback;)V
     120: aload_2
     121: invokestatic  #35                 // Method org/mockito/Mockito.verify:(Ljava/lang/Object;)Ljava/lang/Object;
     124: checkcast     #26                 // class javax/security/auth/callback/NameCallback
     127: invokestatic  #36                 // Method org/mockito/Matchers.anyString:()Ljava/lang/String;
     130: invokevirtual #37                 // Method javax/security/auth/callback/NameCallback.setName:(Ljava/lang/String;)V
     133: aload         4
     135: invokestatic  #35                 // Method org/mockito/Mockito.verify:(Ljava/lang/Object;)Ljava/lang/Object;
     138: checkcast     #29                 // class javax/security/sasl/RealmCallback
     141: invokestatic  #38                 // Method org/mockito/Matchers.any:()Ljava/lang/Object;
     144: checkcast     #39                 // class java/lang/String
     147: invokevirtual #40                 // Method javax/security/sasl/RealmCallback.setText:(Ljava/lang/String;)V
     150: aload_3
     151: invokestatic  #35                 // Method org/mockito/Mockito.verify:(Ljava/lang/Object;)Ljava/lang/Object;
     154: checkcast     #28                 // class javax/security/auth/callback/PasswordCallback
     157: invokestatic  #38                 // Method org/mockito/Matchers.any:()Ljava/lang/Object;
     160: checkcast     #41                 // class "[C"
     163: invokevirtual #42                 // Method javax/security/auth/callback/PasswordCallback.setPassword:([C)V
     166: return

  public void testSaslClientCallbackHandlerWithException();
    Code:
       0: aload_0
       1: invokespecial #20                 // Method createTokenMock:()Lorg/apache/hadoop/security/token/Token;
       4: astore_1
       5: aload_1
       6: invokevirtual #21                 // Method org/apache/hadoop/security/token/Token.getIdentifier:()[B
       9: invokestatic  #22                 // Method org/mockito/Mockito.when:(Ljava/lang/Object;)Lorg/mockito/stubbing/OngoingStubbing;
      12: ldc           #8                  // String principal
      14: invokestatic  #23                 // Method org/apache/hadoop/hbase/util/Bytes.toBytes:(Ljava/lang/String;)[B
      17: invokeinterface #24,  2           // InterfaceMethod org/mockito/stubbing/OngoingStubbing.thenReturn:(Ljava/lang/Object;)Lorg/mockito/stubbing/OngoingStubbing;
      22: pop
      23: aload_1
      24: invokevirtual #25                 // Method org/apache/hadoop/security/token/Token.getPassword:()[B
      27: invokestatic  #22                 // Method org/mockito/Mockito.when:(Ljava/lang/Object;)Lorg/mockito/stubbing/OngoingStubbing;
      30: ldc           #9                  // String password
      32: invokestatic  #23                 // Method org/apache/hadoop/hbase/util/Bytes.toBytes:(Ljava/lang/String;)[B
      35: invokeinterface #24,  2           // InterfaceMethod org/mockito/stubbing/OngoingStubbing.thenReturn:(Ljava/lang/Object;)Lorg/mockito/stubbing/OngoingStubbing;
      40: pop
      41: new           #32                 // class org/apache/hadoop/hbase/security/AbstractHBaseSaslRpcClient$SaslClientCallbackHandler
      44: dup
      45: aload_1
      46: invokespecial #33                 // Method org/apache/hadoop/hbase/security/AbstractHBaseSaslRpcClient$SaslClientCallbackHandler."<init>":(Lorg/apache/hadoop/security/token/Token;)V
      49: astore_2
      50: aload_2
      51: iconst_1
      52: anewarray     #31                 // class javax/security/auth/callback/Callback
      55: dup
      56: iconst_0
      57: ldc           #43                 // class javax/security/auth/callback/TextOutputCallback
      59: invokestatic  #27                 // Method org/mockito/Mockito.mock:(Ljava/lang/Class;)Ljava/lang/Object;
      62: checkcast     #31                 // class javax/security/auth/callback/Callback
      65: aastore
      66: invokevirtual #34                 // Method org/apache/hadoop/hbase/security/AbstractHBaseSaslRpcClient$SaslClientCallbackHandler.handle:([Ljavax/security/auth/callback/Callback;)V
      69: goto          102
      72: astore_3
      73: goto          102
      76: astore_3
      77: new           #46                 // class java/lang/StringBuilder
      80: dup
      81: invokespecial #47                 // Method java/lang/StringBuilder."<init>":()V
      84: ldc           #48                 // String testSaslClientCallbackHandlerWithException error :
      86: invokevirtual #49                 // Method java/lang/StringBuilder.append:(Ljava/lang/String;)Ljava/lang/StringBuilder;
      89: aload_3
      90: invokevirtual #50                 // Method java/lang/Exception.getMessage:()Ljava/lang/String;
      93: invokevirtual #49                 // Method java/lang/StringBuilder.append:(Ljava/lang/String;)Ljava/lang/StringBuilder;
      96: invokevirtual #51                 // Method java/lang/StringBuilder.toString:()Ljava/lang/String;
      99: invokestatic  #52                 // Method org/junit/Assert.fail:(Ljava/lang/String;)V
     102: return
    Exception table:
       from    to  target type
          50    69    72   Class javax/security/auth/callback/UnsupportedCallbackException
          50    69    76   Class java/lang/Exception

  public void testHBaseSaslRpcClientCreation() throws java.lang.Exception;
    Code:
       0: aload_0
       1: aconst_null
       2: invokespecial #53                 // Method assertSuccessCreationKerberosPrincipal:(Ljava/lang/String;)Z
       5: invokestatic  #54                 // Method org/junit/Assert.assertFalse:(Z)V
       8: aload_0
       9: ldc           #55                 // String DOMAIN.COM
      11: invokespecial #53                 // Method assertSuccessCreationKerberosPrincipal:(Ljava/lang/String;)Z
      14: invokestatic  #54                 // Method org/junit/Assert.assertFalse:(Z)V
      17: aload_0
      18: ldc           #56                 // String principal/DOMAIN.COM
      20: invokespecial #53                 // Method assertSuccessCreationKerberosPrincipal:(Ljava/lang/String;)Z
      23: invokestatic  #54                 // Method org/junit/Assert.assertFalse:(Z)V
      26: aload_0
      27: ldc           #57                 // String principal/localhost@DOMAIN.COM
      29: invokespecial #53                 // Method assertSuccessCreationKerberosPrincipal:(Ljava/lang/String;)Z
      32: ifne          43
      35: getstatic     #58                 // Field LOG:Lorg/apache/log4j/Logger;
      38: ldc           #59                 // String Could not create a SASL client with valid Kerberos credential
      40: invokevirtual #60                 // Method org/apache/log4j/Logger.warn:(Ljava/lang/Object;)V
      43: aload_0
      44: aconst_null
      45: aconst_null
      46: invokespecial #61                 // Method assertSuccessCreationDigestPrincipal:(Ljava/lang/String;Ljava/lang/String;)Z
      49: invokestatic  #54                 // Method org/junit/Assert.assertFalse:(Z)V
      52: aload_0
      53: ldc           #62                 // String
      55: ldc           #62                 // String
      57: invokespecial #61                 // Method assertSuccessCreationDigestPrincipal:(Ljava/lang/String;Ljava/lang/String;)Z
      60: invokestatic  #54                 // Method org/junit/Assert.assertFalse:(Z)V
      63: aload_0
      64: ldc           #62                 // String
      66: aconst_null
      67: invokespecial #61                 // Method assertSuccessCreationDigestPrincipal:(Ljava/lang/String;Ljava/lang/String;)Z
      70: invokestatic  #54                 // Method org/junit/Assert.assertFalse:(Z)V
      73: aload_0
      74: aconst_null
      75: ldc           #62                 // String
      77: invokespecial #61                 // Method assertSuccessCreationDigestPrincipal:(Ljava/lang/String;Ljava/lang/String;)Z
      80: invokestatic  #54                 // Method org/junit/Assert.assertFalse:(Z)V
      83: aload_0
      84: ldc           #8                  // String principal
      86: ldc           #9                  // String password
      88: invokespecial #61                 // Method assertSuccessCreationDigestPrincipal:(Ljava/lang/String;Ljava/lang/String;)Z
      91: invokestatic  #63                 // Method org/junit/Assert.assertTrue:(Z)V
      94: aload_0
      95: ldc           #62                 // String
      97: ldc           #62                 // String
      99: invokespecial #64                 // Method assertSuccessCreationSimplePrincipal:(Ljava/lang/String;Ljava/lang/String;)Z
     102: invokestatic  #54                 // Method org/junit/Assert.assertFalse:(Z)V
     105: aload_0
     106: aconst_null
     107: aconst_null
     108: invokespecial #64                 // Method assertSuccessCreationSimplePrincipal:(Ljava/lang/String;Ljava/lang/String;)Z
     111: invokestatic  #54                 // Method org/junit/Assert.assertFalse:(Z)V
     114: aload_0
     115: ldc           #8                  // String principal
     117: ldc           #9                  // String password
     119: invokespecial #64                 // Method assertSuccessCreationSimplePrincipal:(Ljava/lang/String;Ljava/lang/String;)Z
     122: invokestatic  #54                 // Method org/junit/Assert.assertFalse:(Z)V
     125: aload_0
     126: ldc           #8                  // String principal
     128: ldc           #9                  // String password
     130: invokespecial #65                 // Method assertIOExceptionThenSaslClientIsNull:(Ljava/lang/String;Ljava/lang/String;)Z
     133: invokestatic  #63                 // Method org/junit/Assert.assertTrue:(Z)V
     136: aload_0
     137: ldc           #8                  // String principal
     139: ldc           #9                  // String password
     141: invokespecial #66                 // Method assertIOExceptionWhenGetStreamsBeforeConnectCall:(Ljava/lang/String;Ljava/lang/String;)Z
     144: invokestatic  #63                 // Method org/junit/Assert.assertTrue:(Z)V
     147: return

  public void testAuthMethodReadWrite() throws java.io.IOException;
    Code:
       0: new           #67                 // class org/apache/hadoop/io/DataInputBuffer
       3: dup
       4: invokespecial #68                 // Method org/apache/hadoop/io/DataInputBuffer."<init>":()V
       7: astore_1
       8: new           #69                 // class org/apache/hadoop/io/DataOutputBuffer
      11: dup
      12: invokespecial #70                 // Method org/apache/hadoop/io/DataOutputBuffer."<init>":()V
      15: astore_2
      16: aload_0
      17: aload_1
      18: getstatic     #71                 // Field org/apache/hadoop/hbase/security/AuthMethod.SIMPLE:Lorg/apache/hadoop/hbase/security/AuthMethod;
      21: invokespecial #72                 // Method assertAuthMethodRead:(Lorg/apache/hadoop/io/DataInputBuffer;Lorg/apache/hadoop/hbase/security/AuthMethod;)V
      24: aload_0
      25: aload_1
      26: getstatic     #73                 // Field org/apache/hadoop/hbase/security/AuthMethod.KERBEROS:Lorg/apache/hadoop/hbase/security/AuthMethod;
      29: invokespecial #72                 // Method assertAuthMethodRead:(Lorg/apache/hadoop/io/DataInputBuffer;Lorg/apache/hadoop/hbase/security/AuthMethod;)V
      32: aload_0
      33: aload_1
      34: getstatic     #13                 // Field org/apache/hadoop/hbase/security/AuthMethod.DIGEST:Lorg/apache/hadoop/hbase/security/AuthMethod;
      37: invokespecial #72                 // Method assertAuthMethodRead:(Lorg/apache/hadoop/io/DataInputBuffer;Lorg/apache/hadoop/hbase/security/AuthMethod;)V
      40: aload_0
      41: aload_2
      42: getstatic     #71                 // Field org/apache/hadoop/hbase/security/AuthMethod.SIMPLE:Lorg/apache/hadoop/hbase/security/AuthMethod;
      45: invokespecial #74                 // Method assertAuthMethodWrite:(Lorg/apache/hadoop/io/DataOutputBuffer;Lorg/apache/hadoop/hbase/security/AuthMethod;)V
      48: aload_0
      49: aload_2
      50: getstatic     #73                 // Field org/apache/hadoop/hbase/security/AuthMethod.KERBEROS:Lorg/apache/hadoop/hbase/security/AuthMethod;
      53: invokespecial #74                 // Method assertAuthMethodWrite:(Lorg/apache/hadoop/io/DataOutputBuffer;Lorg/apache/hadoop/hbase/security/AuthMethod;)V
      56: aload_0
      57: aload_2
      58: getstatic     #13                 // Field org/apache/hadoop/hbase/security/AuthMethod.DIGEST:Lorg/apache/hadoop/hbase/security/AuthMethod;
      61: invokespecial #74                 // Method assertAuthMethodWrite:(Lorg/apache/hadoop/io/DataOutputBuffer;Lorg/apache/hadoop/hbase/security/AuthMethod;)V
      64: return

  static {};
    Code:
       0: ldc           #7                  // class org/apache/hadoop/hbase/security/TestHBaseSaslRpcClient
       2: invokestatic  #96                 // Method org/apache/hadoop/hbase/HBaseClassTestRule.forClass:(Ljava/lang/Class;)Lorg/apache/hadoop/hbase/HBaseClassTestRule;
       5: putstatic     #97                 // Field CLASS_RULE:Lorg/apache/hadoop/hbase/HBaseClassTestRule;
       8: ldc           #98                 // String java.security.krb5.realm
      10: ldc           #55                 // String DOMAIN.COM
      12: invokestatic  #99                 // Method java/lang/System.setProperty:(Ljava/lang/String;Ljava/lang/String;)Ljava/lang/String;
      15: pop
      16: ldc           #100                // String java.security.krb5.kdc
      18: ldc           #55                 // String DOMAIN.COM
      20: invokestatic  #99                 // Method java/lang/System.setProperty:(Ljava/lang/String;Ljava/lang/String;)Ljava/lang/String;
      23: pop
      24: ldc           #7                  // class org/apache/hadoop/hbase/security/TestHBaseSaslRpcClient
      26: invokestatic  #101                // Method org/apache/log4j/Logger.getLogger:(Ljava/lang/Class;)Lorg/apache/log4j/Logger;
      29: putstatic     #58                 // Field LOG:Lorg/apache/log4j/Logger;
      32: return
}
