Compiled from "TestExecutorService.java"
public class org.apache.hadoop.hbase.executor.TestExecutorService {
  public static final org.apache.hadoop.hbase.HBaseClassTestRule CLASS_RULE;

  public org.apache.hadoop.hbase.executor.TestExecutorService();
    Code:
       0: aload_0
       1: invokespecial #2                  // Method java/lang/Object."<init>":()V
       4: return

  public void testExecutorService() throws java.lang.Exception;
    Code:
       0: iconst_5
       1: istore_1
       2: bipush        10
       4: istore_2
       5: bipush        10
       7: istore_3
       8: ldc           #3                  // class org/apache/hadoop/hbase/Server
      10: invokestatic  #4                  // Method org/mockito/Mockito.mock:(Ljava/lang/Class;)Ljava/lang/Object;
      13: checkcast     #3                  // class org/apache/hadoop/hbase/Server
      16: astore        4
      18: aload         4
      20: invokeinterface #5,  1            // InterfaceMethod org/apache/hadoop/hbase/Server.getConfiguration:()Lorg/apache/hadoop/conf/Configuration;
      25: invokestatic  #6                  // Method org/mockito/Mockito.when:(Ljava/lang/Object;)Lorg/mockito/stubbing/OngoingStubbing;
      28: invokestatic  #7                  // Method org/apache/hadoop/hbase/HBaseConfiguration.create:()Lorg/apache/hadoop/conf/Configuration;
      31: invokeinterface #8,  2            // InterfaceMethod org/mockito/stubbing/OngoingStubbing.thenReturn:(Ljava/lang/Object;)Lorg/mockito/stubbing/OngoingStubbing;
      36: pop
      37: new           #9                  // class org/apache/hadoop/hbase/executor/ExecutorService
      40: dup
      41: ldc           #10                 // String unit_test
      43: invokespecial #11                 // Method org/apache/hadoop/hbase/executor/ExecutorService."<init>":(Ljava/lang/String;)V
      46: astore        5
      48: aload         5
      50: getstatic     #12                 // Field org/apache/hadoop/hbase/executor/ExecutorType.MASTER_SERVER_OPERATIONS:Lorg/apache/hadoop/hbase/executor/ExecutorType;
      53: iload_1
      54: invokevirtual #13                 // Method org/apache/hadoop/hbase/executor/ExecutorService.startExecutorService:(Lorg/apache/hadoop/hbase/executor/ExecutorType;I)V
      57: aload         5
      59: getstatic     #12                 // Field org/apache/hadoop/hbase/executor/ExecutorType.MASTER_SERVER_OPERATIONS:Lorg/apache/hadoop/hbase/executor/ExecutorType;
      62: invokevirtual #14                 // Method org/apache/hadoop/hbase/executor/ExecutorService.getExecutor:(Lorg/apache/hadoop/hbase/executor/ExecutorType;)Lorg/apache/hadoop/hbase/executor/ExecutorService$Executor;
      65: astore        6
      67: aload         6
      69: getfield      #15                 // Field org/apache/hadoop/hbase/executor/ExecutorService$Executor.threadPoolExecutor:Lorg/apache/hadoop/hbase/executor/ExecutorService$TrackingThreadPoolExecutor;
      72: astore        7
      74: lconst_0
      75: aload         7
      77: invokevirtual #16                 // Method java/util/concurrent/ThreadPoolExecutor.getPoolSize:()I
      80: i2l
      81: invokestatic  #17                 // Method org/junit/Assert.assertEquals:(JJ)V
      84: new           #18                 // class java/util/concurrent/atomic/AtomicBoolean
      87: dup
      88: iconst_1
      89: invokespecial #19                 // Method java/util/concurrent/atomic/AtomicBoolean."<init>":(Z)V
      92: astore        8
      94: new           #20                 // class java/util/concurrent/atomic/AtomicInteger
      97: dup
      98: iconst_0
      99: invokespecial #21                 // Method java/util/concurrent/atomic/AtomicInteger."<init>":(I)V
     102: astore        9
     104: iconst_0
     105: istore        10
     107: iload         10
     109: iload_1
     110: if_icmpge     140
     113: aload         5
     115: new           #22                 // class org/apache/hadoop/hbase/executor/TestExecutorService$TestEventHandler
     118: dup
     119: aload         4
     121: getstatic     #23                 // Field org/apache/hadoop/hbase/executor/EventType.M_SERVER_SHUTDOWN:Lorg/apache/hadoop/hbase/executor/EventType;
     124: aload         8
     126: aload         9
     128: invokespecial #24                 // Method org/apache/hadoop/hbase/executor/TestExecutorService$TestEventHandler."<init>":(Lorg/apache/hadoop/hbase/Server;Lorg/apache/hadoop/hbase/executor/EventType;Ljava/util/concurrent/atomic/AtomicBoolean;Ljava/util/concurrent/atomic/AtomicInteger;)V
     131: invokevirtual #25                 // Method org/apache/hadoop/hbase/executor/ExecutorService.submit:(Lorg/apache/hadoop/hbase/executor/EventHandler;)V
     134: iinc          10, 1
     137: goto          107
     140: iconst_0
     141: istore        10
     143: aload         9
     145: invokevirtual #26                 // Method java/util/concurrent/atomic/AtomicInteger.get:()I
     148: iload_1
     149: if_icmpge     179
     152: iload         10
     154: iload_2
     155: if_icmpge     179
     158: getstatic     #1                  // Field LOG:Lorg/slf4j/Logger;
     161: ldc           #27                 // String Waiting for all event handlers to start...
     163: invokeinterface #28,  2           // InterfaceMethod org/slf4j/Logger.info:(Ljava/lang/String;)V
     168: iload_3
     169: i2l
     170: invokestatic  #29                 // Method java/lang/Thread.sleep:(J)V
     173: iinc          10, 1
     176: goto          143
     179: iload_1
     180: i2l
     181: aload         9
     183: invokevirtual #26                 // Method java/util/concurrent/atomic/AtomicInteger.get:()I
     186: i2l
     187: invokestatic  #17                 // Method org/junit/Assert.assertEquals:(JJ)V
     190: iload_1
     191: i2l
     192: aload         7
     194: invokevirtual #16                 // Method java/util/concurrent/ThreadPoolExecutor.getPoolSize:()I
     197: i2l
     198: invokestatic  #17                 // Method org/junit/Assert.assertEquals:(JJ)V
     201: aload         6
     203: invokevirtual #30                 // Method org/apache/hadoop/hbase/executor/ExecutorService$Executor.getStatus:()Lorg/apache/hadoop/hbase/executor/ExecutorService$ExecutorStatus;
     206: astore        11
     208: aload         11
     210: getfield      #31                 // Field org/apache/hadoop/hbase/executor/ExecutorService$ExecutorStatus.queuedEvents:Ljava/util/List;
     213: invokeinterface #32,  1           // InterfaceMethod java/util/List.isEmpty:()Z
     218: invokestatic  #33                 // Method org/junit/Assert.assertTrue:(Z)V
     221: ldc2_w        #34                 // long 5l
     224: aload         11
     226: getfield      #36                 // Field org/apache/hadoop/hbase/executor/ExecutorService$ExecutorStatus.running:Ljava/util/List;
     229: invokeinterface #37,  1           // InterfaceMethod java/util/List.size:()I
     234: i2l
     235: invokestatic  #17                 // Method org/junit/Assert.assertEquals:(JJ)V
     238: aload_0
     239: aload         11
     241: invokespecial #38                 // Method checkStatusDump:(Lorg/apache/hadoop/hbase/executor/ExecutorService$ExecutorStatus;)V
     244: aload         8
     246: dup
     247: astore        12
     249: monitorenter
     250: aload         8
     252: iconst_0
     253: invokevirtual #39                 // Method java/util/concurrent/atomic/AtomicBoolean.set:(Z)V
     256: aload         8
     258: invokevirtual #40                 // Method java/lang/Object.notifyAll:()V
     261: aload         12
     263: monitorexit
     264: goto          275
     267: astore        13
     269: aload         12
     271: monitorexit
     272: aload         13
     274: athrow
     275: aload         9
     277: invokevirtual #26                 // Method java/util/concurrent/atomic/AtomicInteger.get:()I
     280: iload_1
     281: iconst_2
     282: imul
     283: if_icmpge     311
     286: iload         10
     288: iload_2
     289: if_icmpge     311
     292: getstatic     #41                 // Field java/lang/System.out:Ljava/io/PrintStream;
     295: ldc           #42                 // String Waiting for all event handlers to finish...
     297: invokevirtual #43                 // Method java/io/PrintStream.println:(Ljava/lang/String;)V
     300: iload_3
     301: i2l
     302: invokestatic  #29                 // Method java/lang/Thread.sleep:(J)V
     305: iinc          10, 1
     308: goto          275
     311: iload_1
     312: iconst_2
     313: imul
     314: i2l
     315: aload         9
     317: invokevirtual #26                 // Method java/util/concurrent/atomic/AtomicInteger.get:()I
     320: i2l
     321: invokestatic  #17                 // Method org/junit/Assert.assertEquals:(JJ)V
     324: iload_1
     325: i2l
     326: aload         7
     328: invokevirtual #16                 // Method java/util/concurrent/ThreadPoolExecutor.getPoolSize:()I
     331: i2l
     332: invokestatic  #17                 // Method org/junit/Assert.assertEquals:(JJ)V
     335: iconst_0
     336: istore        12
     338: iload         12
     340: iconst_2
     341: iload_1
     342: imul
     343: if_icmpge     373
     346: aload         5
     348: new           #22                 // class org/apache/hadoop/hbase/executor/TestExecutorService$TestEventHandler
     351: dup
     352: aload         4
     354: getstatic     #23                 // Field org/apache/hadoop/hbase/executor/EventType.M_SERVER_SHUTDOWN:Lorg/apache/hadoop/hbase/executor/EventType;
     357: aload         8
     359: aload         9
     361: invokespecial #24                 // Method org/apache/hadoop/hbase/executor/TestExecutorService$TestEventHandler."<init>":(Lorg/apache/hadoop/hbase/Server;Lorg/apache/hadoop/hbase/executor/EventType;Ljava/util/concurrent/atomic/AtomicBoolean;Ljava/util/concurrent/atomic/AtomicInteger;)V
     364: invokevirtual #25                 // Method org/apache/hadoop/hbase/executor/ExecutorService.submit:(Lorg/apache/hadoop/hbase/executor/EventHandler;)V
     367: iinc          12, 1
     370: goto          338
     373: aload         8
     375: dup
     376: astore        12
     378: monitorenter
     379: aload         8
     381: iconst_0
     382: invokevirtual #39                 // Method java/util/concurrent/atomic/AtomicBoolean.set:(Z)V
     385: aload         8
     387: invokevirtual #40                 // Method java/lang/Object.notifyAll:()V
     390: aload         12
     392: monitorexit
     393: goto          404
     396: astore        14
     398: aload         12
     400: monitorexit
     401: aload         14
     403: athrow
     404: ldc2_w        #45                 // long 2000l
     407: invokestatic  #29                 // Method java/lang/Thread.sleep:(J)V
     410: iload_1
     411: i2l
     412: aload         7
     414: invokevirtual #16                 // Method java/util/concurrent/ThreadPoolExecutor.getPoolSize:()I
     417: i2l
     418: invokestatic  #17                 // Method org/junit/Assert.assertEquals:(JJ)V
     421: aload         5
     423: invokevirtual #47                 // Method org/apache/hadoop/hbase/executor/ExecutorService.shutdown:()V
     426: lconst_0
     427: aload         5
     429: invokevirtual #48                 // Method org/apache/hadoop/hbase/executor/ExecutorService.getAllExecutorStatuses:()Ljava/util/Map;
     432: invokeinterface #49,  1           // InterfaceMethod java/util/Map.size:()I
     437: i2l
     438: invokestatic  #17                 // Method org/junit/Assert.assertEquals:(JJ)V
     441: aload         5
     443: new           #22                 // class org/apache/hadoop/hbase/executor/TestExecutorService$TestEventHandler
     446: dup
     447: aload         4
     449: getstatic     #23                 // Field org/apache/hadoop/hbase/executor/EventType.M_SERVER_SHUTDOWN:Lorg/apache/hadoop/hbase/executor/EventType;
     452: aload         8
     454: aload         9
     456: invokespecial #24                 // Method org/apache/hadoop/hbase/executor/TestExecutorService$TestEventHandler."<init>":(Lorg/apache/hadoop/hbase/Server;Lorg/apache/hadoop/hbase/executor/EventType;Ljava/util/concurrent/atomic/AtomicBoolean;Ljava/util/concurrent/atomic/AtomicInteger;)V
     459: invokevirtual #25                 // Method org/apache/hadoop/hbase/executor/ExecutorService.submit:(Lorg/apache/hadoop/hbase/executor/EventHandler;)V
     462: return
    Exception table:
       from    to  target type
         250   264   267   any
         267   272   267   any
         379   393   396   any
         396   401   396   any

  public void testAborting() throws java.lang.Exception;
    Code:
       0: invokestatic  #7                  // Method org/apache/hadoop/hbase/HBaseConfiguration.create:()Lorg/apache/hadoop/conf/Configuration;
       3: astore_1
       4: ldc           #3                  // class org/apache/hadoop/hbase/Server
       6: invokestatic  #4                  // Method org/mockito/Mockito.mock:(Ljava/lang/Class;)Ljava/lang/Object;
       9: checkcast     #3                  // class org/apache/hadoop/hbase/Server
      12: astore_2
      13: aload_2
      14: invokeinterface #5,  1            // InterfaceMethod org/apache/hadoop/hbase/Server.getConfiguration:()Lorg/apache/hadoop/conf/Configuration;
      19: invokestatic  #6                  // Method org/mockito/Mockito.when:(Ljava/lang/Object;)Lorg/mockito/stubbing/OngoingStubbing;
      22: aload_1
      23: invokeinterface #8,  2            // InterfaceMethod org/mockito/stubbing/OngoingStubbing.thenReturn:(Ljava/lang/Object;)Lorg/mockito/stubbing/OngoingStubbing;
      28: pop
      29: new           #9                  // class org/apache/hadoop/hbase/executor/ExecutorService
      32: dup
      33: ldc           #10                 // String unit_test
      35: invokespecial #11                 // Method org/apache/hadoop/hbase/executor/ExecutorService."<init>":(Ljava/lang/String;)V
      38: astore_3
      39: aload_3
      40: getstatic     #12                 // Field org/apache/hadoop/hbase/executor/ExecutorType.MASTER_SERVER_OPERATIONS:Lorg/apache/hadoop/hbase/executor/ExecutorType;
      43: iconst_1
      44: invokevirtual #13                 // Method org/apache/hadoop/hbase/executor/ExecutorService.startExecutorService:(Lorg/apache/hadoop/hbase/executor/ExecutorType;I)V
      47: aload_3
      48: new           #62                 // class org/apache/hadoop/hbase/executor/TestExecutorService$1
      51: dup
      52: aload_0
      53: aload_2
      54: getstatic     #23                 // Field org/apache/hadoop/hbase/executor/EventType.M_SERVER_SHUTDOWN:Lorg/apache/hadoop/hbase/executor/EventType;
      57: invokespecial #63                 // Method org/apache/hadoop/hbase/executor/TestExecutorService$1."<init>":(Lorg/apache/hadoop/hbase/executor/TestExecutorService;Lorg/apache/hadoop/hbase/Server;Lorg/apache/hadoop/hbase/executor/EventType;)V
      60: invokevirtual #25                 // Method org/apache/hadoop/hbase/executor/ExecutorService.submit:(Lorg/apache/hadoop/hbase/executor/EventHandler;)V
      63: aload_1
      64: ldc2_w        #64                 // long 30000l
      67: new           #66                 // class org/apache/hadoop/hbase/executor/TestExecutorService$2
      70: dup
      71: aload_0
      72: aload_2
      73: invokespecial #67                 // Method org/apache/hadoop/hbase/executor/TestExecutorService$2."<init>":(Lorg/apache/hadoop/hbase/executor/TestExecutorService;Lorg/apache/hadoop/hbase/Server;)V
      76: invokestatic  #68                 // Method org/apache/hadoop/hbase/Waiter.waitFor:(Lorg/apache/hadoop/conf/Configuration;JLorg/apache/hadoop/hbase/Waiter$Predicate;)J
      79: pop2
      80: aload_3
      81: invokevirtual #47                 // Method org/apache/hadoop/hbase/executor/ExecutorService.shutdown:()V
      84: return

  static org.slf4j.Logger access$000();
    Code:
       0: getstatic     #1                  // Field LOG:Lorg/slf4j/Logger;
       3: areturn

  static {};
    Code:
       0: ldc           #69                 // class org/apache/hadoop/hbase/executor/TestExecutorService
       2: invokestatic  #70                 // Method org/apache/hadoop/hbase/HBaseClassTestRule.forClass:(Ljava/lang/Class;)Lorg/apache/hadoop/hbase/HBaseClassTestRule;
       5: putstatic     #71                 // Field CLASS_RULE:Lorg/apache/hadoop/hbase/HBaseClassTestRule;
       8: ldc           #69                 // class org/apache/hadoop/hbase/executor/TestExecutorService
      10: invokestatic  #72                 // Method org/slf4j/LoggerFactory.getLogger:(Ljava/lang/Class;)Lorg/slf4j/Logger;
      13: putstatic     #1                  // Field LOG:Lorg/slf4j/Logger;
      16: return
}
