Compiled from "TestReplicationSyncUpTool.java"
public class org.apache.hadoop.hbase.replication.TestReplicationSyncUpTool extends org.apache.hadoop.hbase.replication.TestReplicationSyncUpToolBase {
  public static final org.apache.hadoop.hbase.HBaseClassTestRule CLASS_RULE;

  public org.apache.hadoop.hbase.replication.TestReplicationSyncUpTool();
    Code:
       0: aload_0
       1: invokespecial #2                  // Method org/apache/hadoop/hbase/replication/TestReplicationSyncUpToolBase."<init>":()V
       4: return

  public void testSyncUpTool() throws java.lang.Exception;
    Code:
       0: aload_0
       1: invokevirtual #3                  // Method setupReplication:()V
       4: aload_0
       5: invokespecial #4                  // Method putAndReplicateRows:()V
       8: aload_0
       9: invokespecial #5                  // Method mimicSyncUpAfterDelete:()V
      12: aload_0
      13: invokespecial #6                  // Method mimicSyncUpAfterPut:()V
      16: return

  static {};
    Code:
       0: ldc           #90                 // class org/apache/hadoop/hbase/replication/TestReplicationSyncUpTool
       2: invokestatic  #91                 // Method org/apache/hadoop/hbase/HBaseClassTestRule.forClass:(Ljava/lang/Class;)Lorg/apache/hadoop/hbase/HBaseClassTestRule;
       5: putstatic     #92                 // Field CLASS_RULE:Lorg/apache/hadoop/hbase/HBaseClassTestRule;
       8: ldc           #90                 // class org/apache/hadoop/hbase/replication/TestReplicationSyncUpTool
      10: invokestatic  #93                 // Method org/slf4j/LoggerFactory.getLogger:(Ljava/lang/Class;)Lorg/slf4j/Logger;
      13: putstatic     #7                  // Field LOG:Lorg/slf4j/Logger;
      16: return
}
