Compiled from "TestSpaceQuotasWithSnapshots.java"
class org.apache.hadoop.hbase.quotas.TestSpaceQuotasWithSnapshots$2 implements org.apache.hadoop.hbase.Waiter$Predicate<java.lang.Exception> {
  final org.apache.hadoop.hbase.TableName val$tn;

  final org.apache.hadoop.hbase.quotas.TestSpaceQuotasWithSnapshots this$0;

  org.apache.hadoop.hbase.quotas.TestSpaceQuotasWithSnapshots$2(org.apache.hadoop.hbase.quotas.TestSpaceQuotasWithSnapshots, org.apache.hadoop.hbase.TableName);
    Code:
       0: aload_0
       1: aload_1
       2: putfield      #1                  // Field this$0:Lorg/apache/hadoop/hbase/quotas/TestSpaceQuotasWithSnapshots;
       5: aload_0
       6: aload_2
       7: putfield      #2                  // Field val$tn:Lorg/apache/hadoop/hbase/TableName;
      10: aload_0
      11: invokespecial #3                  // Method java/lang/Object."<init>":()V
      14: return

  public boolean evaluate() throws java.lang.Exception;
    Code:
       0: aload_0
       1: getfield      #1                  // Field this$0:Lorg/apache/hadoop/hbase/quotas/TestSpaceQuotasWithSnapshots;
       4: aload_0
       5: getfield      #1                  // Field this$0:Lorg/apache/hadoop/hbase/quotas/TestSpaceQuotasWithSnapshots;
       8: invokestatic  #4                  // Method org/apache/hadoop/hbase/quotas/TestSpaceQuotasWithSnapshots.access$000:(Lorg/apache/hadoop/hbase/quotas/TestSpaceQuotasWithSnapshots;)Lorg/apache/hadoop/hbase/client/Connection;
      11: aload_0
      12: getfield      #2                  // Field val$tn:Lorg/apache/hadoop/hbase/TableName;
      15: invokevirtual #5                  // Method org/apache/hadoop/hbase/quotas/TestSpaceQuotasWithSnapshots.getRegionSizeReportForTable:(Lorg/apache/hadoop/hbase/client/Connection;Lorg/apache/hadoop/hbase/TableName;)J
      18: lstore_1
      19: lload_1
      20: ldc2_w        #6                  // long 2609152l
      23: lcmp
      24: ifge          39
      27: lload_1
      28: ldc2_w        #8                  // long 1585152l
      31: lcmp
      32: ifle          39
      35: iconst_1
      36: goto          40
      39: iconst_0
      40: ireturn
}
