Compiled from "TestMasterProcedureScheduler.java"
public class org.apache.hadoop.hbase.master.procedure.TestMasterProcedureScheduler {
  public static final org.apache.hadoop.hbase.HBaseClassTestRule CLASS_RULE;

  public org.junit.rules.TestName name;

  public org.apache.hadoop.hbase.master.procedure.TestMasterProcedureScheduler();
    Code:
       0: aload_0
       1: invokespecial #1                  // Method java/lang/Object."<init>":()V
       4: aload_0
       5: new           #2                  // class org/junit/rules/TestName
       8: dup
       9: invokespecial #3                  // Method org/junit/rules/TestName."<init>":()V
      12: putfield      #4                  // Field name:Lorg/junit/rules/TestName;
      15: return

  public void setUp() throws java.io.IOException;
    Code:
       0: aload_0
       1: new           #5                  // class org/apache/hadoop/hbase/master/procedure/MasterProcedureScheduler
       4: dup
       5: invokedynamic #6,  0              // InvokeDynamic #0:apply:()Ljava/util/function/Function;
      10: invokespecial #7                  // Method org/apache/hadoop/hbase/master/procedure/MasterProcedureScheduler."<init>":(Ljava/util/function/Function;)V
      13: putfield      #8                  // Field queue:Lorg/apache/hadoop/hbase/master/procedure/MasterProcedureScheduler;
      16: aload_0
      17: getfield      #8                  // Field queue:Lorg/apache/hadoop/hbase/master/procedure/MasterProcedureScheduler;
      20: invokevirtual #9                  // Method org/apache/hadoop/hbase/master/procedure/MasterProcedureScheduler.start:()V
      23: return

  public void tearDown() throws java.io.IOException;
    Code:
       0: ldc           #10                 // String proc-queue expected to be empty
       2: lconst_0
       3: aload_0
       4: getfield      #8                  // Field queue:Lorg/apache/hadoop/hbase/master/procedure/MasterProcedureScheduler;
       7: invokevirtual #11                 // Method org/apache/hadoop/hbase/master/procedure/MasterProcedureScheduler.size:()I
      10: i2l
      11: invokestatic  #12                 // Method org/junit/Assert.assertEquals:(Ljava/lang/String;JJ)V
      14: aload_0
      15: getfield      #8                  // Field queue:Lorg/apache/hadoop/hbase/master/procedure/MasterProcedureScheduler;
      18: invokevirtual #13                 // Method org/apache/hadoop/hbase/master/procedure/MasterProcedureScheduler.stop:()V
      21: aload_0
      22: getfield      #8                  // Field queue:Lorg/apache/hadoop/hbase/master/procedure/MasterProcedureScheduler;
      25: invokevirtual #14                 // Method org/apache/hadoop/hbase/master/procedure/MasterProcedureScheduler.clear:()V
      28: return

  public void testSimpleTableOpsQueues() throws java.lang.Exception;
    Code:
       0: bipush        10
       2: istore_1
       3: bipush        10
       5: istore_2
       6: iconst_0
       7: istore_3
       8: iconst_1
       9: istore        4
      11: iload         4
      13: bipush        10
      15: if_icmpgt     107
      18: ldc           #15                 // String test-%04d
      20: iconst_1
      21: anewarray     #16                 // class java/lang/Object
      24: dup
      25: iconst_0
      26: iload         4
      28: invokestatic  #17                 // Method java/lang/Integer.valueOf:(I)Ljava/lang/Integer;
      31: aastore
      32: invokestatic  #18                 // Method java/lang/String.format:(Ljava/lang/String;[Ljava/lang/Object;)Ljava/lang/String;
      35: invokestatic  #19                 // Method org/apache/hadoop/hbase/TableName.valueOf:(Ljava/lang/String;)Lorg/apache/hadoop/hbase/TableName;
      38: astore        5
      40: iconst_1
      41: istore        6
      43: iload         6
      45: bipush        10
      47: if_icmpgt     101
      50: aload_0
      51: getfield      #8                  // Field queue:Lorg/apache/hadoop/hbase/master/procedure/MasterProcedureScheduler;
      54: new           #20                 // class org/apache/hadoop/hbase/master/procedure/TestMasterProcedureScheduler$TestTableProcedure
      57: dup
      58: iload         4
      60: sipush        1000
      63: imul
      64: iload         6
      66: iadd
      67: i2l
      68: aload         5
      70: getstatic     #21                 // Field org/apache/hadoop/hbase/master/procedure/TableProcedureInterface$TableOperationType.EDIT:Lorg/apache/hadoop/hbase/master/procedure/TableProcedureInterface$TableOperationType;
      73: invokespecial #22                 // Method org/apache/hadoop/hbase/master/procedure/TestMasterProcedureScheduler$TestTableProcedure."<init>":(JLorg/apache/hadoop/hbase/TableName;Lorg/apache/hadoop/hbase/master/procedure/TableProcedureInterface$TableOperationType;)V
      76: invokevirtual #23                 // Method org/apache/hadoop/hbase/master/procedure/MasterProcedureScheduler.addBack:(Lorg/apache/hadoop/hbase/procedure2/Procedure;)V
      79: iinc          3, 1
      82: iload_3
      83: i2l
      84: aload_0
      85: getfield      #8                  // Field queue:Lorg/apache/hadoop/hbase/master/procedure/MasterProcedureScheduler;
      88: invokevirtual #11                 // Method org/apache/hadoop/hbase/master/procedure/MasterProcedureScheduler.size:()I
      91: i2l
      92: invokestatic  #24                 // Method org/junit/Assert.assertEquals:(JJ)V
      95: iinc          6, 1
      98: goto          43
     101: iinc          4, 1
     104: goto          11
     107: ldc2_w        #25                 // long 100l
     110: aload_0
     111: getfield      #8                  // Field queue:Lorg/apache/hadoop/hbase/master/procedure/MasterProcedureScheduler;
     114: invokevirtual #11                 // Method org/apache/hadoop/hbase/master/procedure/MasterProcedureScheduler.size:()I
     117: i2l
     118: invokestatic  #24                 // Method org/junit/Assert.assertEquals:(JJ)V
     121: iconst_1
     122: istore        4
     124: iload         4
     126: bipush        10
     128: if_icmpgt     251
     131: iconst_1
     132: istore        5
     134: iload         5
     136: bipush        10
     138: if_icmpgt     245
     141: aload_0
     142: getfield      #8                  // Field queue:Lorg/apache/hadoop/hbase/master/procedure/MasterProcedureScheduler;
     145: invokevirtual #27                 // Method org/apache/hadoop/hbase/master/procedure/MasterProcedureScheduler.poll:()Lorg/apache/hadoop/hbase/procedure2/Procedure;
     148: astore        6
     150: aload         6
     152: ifnull        159
     155: iconst_1
     156: goto          160
     159: iconst_0
     160: invokestatic  #28                 // Method org/junit/Assert.assertTrue:(Z)V
     163: aload         6
     165: checkcast     #20                 // class org/apache/hadoop/hbase/master/procedure/TestMasterProcedureScheduler$TestTableProcedure
     168: invokevirtual #29                 // Method org/apache/hadoop/hbase/master/procedure/TestMasterProcedureScheduler$TestTableProcedure.getTableName:()Lorg/apache/hadoop/hbase/TableName;
     171: astore        7
     173: aload_0
     174: getfield      #8                  // Field queue:Lorg/apache/hadoop/hbase/master/procedure/MasterProcedureScheduler;
     177: aload         6
     179: aload         7
     181: invokevirtual #30                 // Method org/apache/hadoop/hbase/master/procedure/MasterProcedureScheduler.waitTableExclusiveLock:(Lorg/apache/hadoop/hbase/procedure2/Procedure;Lorg/apache/hadoop/hbase/TableName;)Z
     184: pop
     185: aload_0
     186: getfield      #8                  // Field queue:Lorg/apache/hadoop/hbase/master/procedure/MasterProcedureScheduler;
     189: aload         6
     191: aload         7
     193: invokevirtual #31                 // Method org/apache/hadoop/hbase/master/procedure/MasterProcedureScheduler.wakeTableExclusiveLock:(Lorg/apache/hadoop/hbase/procedure2/Procedure;Lorg/apache/hadoop/hbase/TableName;)V
     196: aload_0
     197: getfield      #8                  // Field queue:Lorg/apache/hadoop/hbase/master/procedure/MasterProcedureScheduler;
     200: aload         6
     202: invokevirtual #32                 // Method org/apache/hadoop/hbase/master/procedure/MasterProcedureScheduler.completionCleanup:(Lorg/apache/hadoop/hbase/procedure2/Procedure;)V
     205: iinc          3, -1
     208: iload_3
     209: i2l
     210: aload_0
     211: getfield      #8                  // Field queue:Lorg/apache/hadoop/hbase/master/procedure/MasterProcedureScheduler;
     214: invokevirtual #11                 // Method org/apache/hadoop/hbase/master/procedure/MasterProcedureScheduler.size:()I
     217: i2l
     218: invokestatic  #24                 // Method org/junit/Assert.assertEquals:(JJ)V
     221: iload         5
     223: sipush        1000
     226: imul
     227: iload         4
     229: iadd
     230: i2l
     231: aload         6
     233: invokevirtual #33                 // Method org/apache/hadoop/hbase/procedure2/Procedure.getProcId:()J
     236: invokestatic  #24                 // Method org/junit/Assert.assertEquals:(JJ)V
     239: iinc          5, 1
     242: goto          134
     245: iinc          4, 1
     248: goto          124
     251: lconst_0
     252: aload_0
     253: getfield      #8                  // Field queue:Lorg/apache/hadoop/hbase/master/procedure/MasterProcedureScheduler;
     256: invokevirtual #11                 // Method org/apache/hadoop/hbase/master/procedure/MasterProcedureScheduler.size:()I
     259: i2l
     260: invokestatic  #24                 // Method org/junit/Assert.assertEquals:(JJ)V
     263: iconst_1
     264: istore        4
     266: iload         4
     268: bipush        10
     270: if_icmpgt     332
     273: ldc           #15                 // String test-%04d
     275: iconst_1
     276: anewarray     #16                 // class java/lang/Object
     279: dup
     280: iconst_0
     281: iload         4
     283: invokestatic  #17                 // Method java/lang/Integer.valueOf:(I)Ljava/lang/Integer;
     286: aastore
     287: invokestatic  #18                 // Method java/lang/String.format:(Ljava/lang/String;[Ljava/lang/Object;)Ljava/lang/String;
     290: invokestatic  #19                 // Method org/apache/hadoop/hbase/TableName.valueOf:(Ljava/lang/String;)Lorg/apache/hadoop/hbase/TableName;
     293: astore        5
     295: new           #20                 // class org/apache/hadoop/hbase/master/procedure/TestMasterProcedureScheduler$TestTableProcedure
     298: dup
     299: ldc2_w        #25                 // long 100l
     302: aload         5
     304: getstatic     #34                 // Field org/apache/hadoop/hbase/master/procedure/TableProcedureInterface$TableOperationType.DELETE:Lorg/apache/hadoop/hbase/master/procedure/TableProcedureInterface$TableOperationType;
     307: invokespecial #22                 // Method org/apache/hadoop/hbase/master/procedure/TestMasterProcedureScheduler$TestTableProcedure."<init>":(JLorg/apache/hadoop/hbase/TableName;Lorg/apache/hadoop/hbase/master/procedure/TableProcedureInterface$TableOperationType;)V
     310: astore        6
     312: aload_0
     313: getfield      #8                  // Field queue:Lorg/apache/hadoop/hbase/master/procedure/MasterProcedureScheduler;
     316: aload         5
     318: aload         6
     320: invokevirtual #35                 // Method org/apache/hadoop/hbase/master/procedure/MasterProcedureScheduler.markTableAsDeleted:(Lorg/apache/hadoop/hbase/TableName;Lorg/apache/hadoop/hbase/procedure2/Procedure;)Z
     323: invokestatic  #28                 // Method org/junit/Assert.assertTrue:(Z)V
     326: iinc          4, 1
     329: goto          266
     332: return

  public void testCreateDeleteTableOperationsWithWriteLock() throws java.lang.Exception;
    Code:
       0: aload_0
       1: getfield      #4                  // Field name:Lorg/junit/rules/TestName;
       4: invokevirtual #36                 // Method org/junit/rules/TestName.getMethodName:()Ljava/lang/String;
       7: invokestatic  #19                 // Method org/apache/hadoop/hbase/TableName.valueOf:(Ljava/lang/String;)Lorg/apache/hadoop/hbase/TableName;
      10: astore_1
      11: new           #20                 // class org/apache/hadoop/hbase/master/procedure/TestMasterProcedureScheduler$TestTableProcedure
      14: dup
      15: ldc2_w        #25                 // long 100l
      18: aload_1
      19: getstatic     #34                 // Field org/apache/hadoop/hbase/master/procedure/TableProcedureInterface$TableOperationType.DELETE:Lorg/apache/hadoop/hbase/master/procedure/TableProcedureInterface$TableOperationType;
      22: invokespecial #22                 // Method org/apache/hadoop/hbase/master/procedure/TestMasterProcedureScheduler$TestTableProcedure."<init>":(JLorg/apache/hadoop/hbase/TableName;Lorg/apache/hadoop/hbase/master/procedure/TableProcedureInterface$TableOperationType;)V
      25: astore_2
      26: aload_0
      27: getfield      #8                  // Field queue:Lorg/apache/hadoop/hbase/master/procedure/MasterProcedureScheduler;
      30: new           #20                 // class org/apache/hadoop/hbase/master/procedure/TestMasterProcedureScheduler$TestTableProcedure
      33: dup
      34: lconst_1
      35: aload_1
      36: getstatic     #21                 // Field org/apache/hadoop/hbase/master/procedure/TableProcedureInterface$TableOperationType.EDIT:Lorg/apache/hadoop/hbase/master/procedure/TableProcedureInterface$TableOperationType;
      39: invokespecial #22                 // Method org/apache/hadoop/hbase/master/procedure/TestMasterProcedureScheduler$TestTableProcedure."<init>":(JLorg/apache/hadoop/hbase/TableName;Lorg/apache/hadoop/hbase/master/procedure/TableProcedureInterface$TableOperationType;)V
      42: invokevirtual #23                 // Method org/apache/hadoop/hbase/master/procedure/MasterProcedureScheduler.addBack:(Lorg/apache/hadoop/hbase/procedure2/Procedure;)V
      45: aload_0
      46: getfield      #8                  // Field queue:Lorg/apache/hadoop/hbase/master/procedure/MasterProcedureScheduler;
      49: aload_1
      50: aload_2
      51: invokevirtual #35                 // Method org/apache/hadoop/hbase/master/procedure/MasterProcedureScheduler.markTableAsDeleted:(Lorg/apache/hadoop/hbase/TableName;Lorg/apache/hadoop/hbase/procedure2/Procedure;)Z
      54: invokestatic  #37                 // Method org/junit/Assert.assertFalse:(Z)V
      57: aload_0
      58: getfield      #8                  // Field queue:Lorg/apache/hadoop/hbase/master/procedure/MasterProcedureScheduler;
      61: invokevirtual #27                 // Method org/apache/hadoop/hbase/master/procedure/MasterProcedureScheduler.poll:()Lorg/apache/hadoop/hbase/procedure2/Procedure;
      64: astore_3
      65: lconst_1
      66: aload_3
      67: invokevirtual #33                 // Method org/apache/hadoop/hbase/procedure2/Procedure.getProcId:()J
      70: invokestatic  #24                 // Method org/junit/Assert.assertEquals:(JJ)V
      73: iconst_0
      74: invokestatic  #38                 // Method java/lang/Boolean.valueOf:(Z)Ljava/lang/Boolean;
      77: aload_0
      78: getfield      #8                  // Field queue:Lorg/apache/hadoop/hbase/master/procedure/MasterProcedureScheduler;
      81: aload_3
      82: aload_1
      83: invokevirtual #30                 // Method org/apache/hadoop/hbase/master/procedure/MasterProcedureScheduler.waitTableExclusiveLock:(Lorg/apache/hadoop/hbase/procedure2/Procedure;Lorg/apache/hadoop/hbase/TableName;)Z
      86: invokestatic  #38                 // Method java/lang/Boolean.valueOf:(Z)Ljava/lang/Boolean;
      89: invokestatic  #39                 // Method org/junit/Assert.assertEquals:(Ljava/lang/Object;Ljava/lang/Object;)V
      92: lconst_0
      93: aload_0
      94: getfield      #8                  // Field queue:Lorg/apache/hadoop/hbase/master/procedure/MasterProcedureScheduler;
      97: invokevirtual #11                 // Method org/apache/hadoop/hbase/master/procedure/MasterProcedureScheduler.size:()I
     100: i2l
     101: invokestatic  #24                 // Method org/junit/Assert.assertEquals:(JJ)V
     104: aload_0
     105: getfield      #8                  // Field queue:Lorg/apache/hadoop/hbase/master/procedure/MasterProcedureScheduler;
     108: aload_1
     109: aload_2
     110: invokevirtual #35                 // Method org/apache/hadoop/hbase/master/procedure/MasterProcedureScheduler.markTableAsDeleted:(Lorg/apache/hadoop/hbase/TableName;Lorg/apache/hadoop/hbase/procedure2/Procedure;)Z
     113: invokestatic  #37                 // Method org/junit/Assert.assertFalse:(Z)V
     116: aload_0
     117: getfield      #8                  // Field queue:Lorg/apache/hadoop/hbase/master/procedure/MasterProcedureScheduler;
     120: aload_3
     121: aload_1
     122: invokevirtual #31                 // Method org/apache/hadoop/hbase/master/procedure/MasterProcedureScheduler.wakeTableExclusiveLock:(Lorg/apache/hadoop/hbase/procedure2/Procedure;Lorg/apache/hadoop/hbase/TableName;)V
     125: aload_0
     126: getfield      #8                  // Field queue:Lorg/apache/hadoop/hbase/master/procedure/MasterProcedureScheduler;
     129: aload_1
     130: aload_3
     131: invokevirtual #35                 // Method org/apache/hadoop/hbase/master/procedure/MasterProcedureScheduler.markTableAsDeleted:(Lorg/apache/hadoop/hbase/TableName;Lorg/apache/hadoop/hbase/procedure2/Procedure;)Z
     134: invokestatic  #28                 // Method org/junit/Assert.assertTrue:(Z)V
     137: return

  public void testCreateDeleteTableOperationsWithReadLock() throws java.lang.Exception;
    Code:
       0: aload_0
       1: getfield      #4                  // Field name:Lorg/junit/rules/TestName;
       4: invokevirtual #36                 // Method org/junit/rules/TestName.getMethodName:()Ljava/lang/String;
       7: invokestatic  #19                 // Method org/apache/hadoop/hbase/TableName.valueOf:(Ljava/lang/String;)Lorg/apache/hadoop/hbase/TableName;
      10: astore_1
      11: iconst_2
      12: istore_2
      13: new           #20                 // class org/apache/hadoop/hbase/master/procedure/TestMasterProcedureScheduler$TestTableProcedure
      16: dup
      17: ldc2_w        #25                 // long 100l
      20: aload_1
      21: getstatic     #34                 // Field org/apache/hadoop/hbase/master/procedure/TableProcedureInterface$TableOperationType.DELETE:Lorg/apache/hadoop/hbase/master/procedure/TableProcedureInterface$TableOperationType;
      24: invokespecial #22                 // Method org/apache/hadoop/hbase/master/procedure/TestMasterProcedureScheduler$TestTableProcedure."<init>":(JLorg/apache/hadoop/hbase/TableName;Lorg/apache/hadoop/hbase/master/procedure/TableProcedureInterface$TableOperationType;)V
      27: astore_3
      28: iconst_1
      29: istore        4
      31: iload         4
      33: iconst_2
      34: if_icmpgt     64
      37: aload_0
      38: getfield      #8                  // Field queue:Lorg/apache/hadoop/hbase/master/procedure/MasterProcedureScheduler;
      41: new           #20                 // class org/apache/hadoop/hbase/master/procedure/TestMasterProcedureScheduler$TestTableProcedure
      44: dup
      45: iload         4
      47: i2l
      48: aload_1
      49: getstatic     #40                 // Field org/apache/hadoop/hbase/master/procedure/TableProcedureInterface$TableOperationType.READ:Lorg/apache/hadoop/hbase/master/procedure/TableProcedureInterface$TableOperationType;
      52: invokespecial #22                 // Method org/apache/hadoop/hbase/master/procedure/TestMasterProcedureScheduler$TestTableProcedure."<init>":(JLorg/apache/hadoop/hbase/TableName;Lorg/apache/hadoop/hbase/master/procedure/TableProcedureInterface$TableOperationType;)V
      55: invokevirtual #23                 // Method org/apache/hadoop/hbase/master/procedure/MasterProcedureScheduler.addBack:(Lorg/apache/hadoop/hbase/procedure2/Procedure;)V
      58: iinc          4, 1
      61: goto          31
      64: aload_0
      65: getfield      #8                  // Field queue:Lorg/apache/hadoop/hbase/master/procedure/MasterProcedureScheduler;
      68: aload_1
      69: aload_3
      70: invokevirtual #35                 // Method org/apache/hadoop/hbase/master/procedure/MasterProcedureScheduler.markTableAsDeleted:(Lorg/apache/hadoop/hbase/TableName;Lorg/apache/hadoop/hbase/procedure2/Procedure;)Z
      73: invokestatic  #37                 // Method org/junit/Assert.assertFalse:(Z)V
      76: iconst_2
      77: anewarray     #41                 // class org/apache/hadoop/hbase/procedure2/Procedure
      80: astore        4
      82: iconst_0
      83: istore        5
      85: iload         5
      87: iconst_2
      88: if_icmpge     158
      91: aload_0
      92: getfield      #8                  // Field queue:Lorg/apache/hadoop/hbase/master/procedure/MasterProcedureScheduler;
      95: invokevirtual #27                 // Method org/apache/hadoop/hbase/master/procedure/MasterProcedureScheduler.poll:()Lorg/apache/hadoop/hbase/procedure2/Procedure;
      98: astore        6
     100: aload         4
     102: iload         5
     104: aload         6
     106: aastore
     107: iload         5
     109: iconst_1
     110: iadd
     111: i2l
     112: aload         6
     114: invokevirtual #33                 // Method org/apache/hadoop/hbase/procedure2/Procedure.getProcId:()J
     117: invokestatic  #24                 // Method org/junit/Assert.assertEquals:(JJ)V
     120: iconst_0
     121: invokestatic  #38                 // Method java/lang/Boolean.valueOf:(Z)Ljava/lang/Boolean;
     124: aload_0
     125: getfield      #8                  // Field queue:Lorg/apache/hadoop/hbase/master/procedure/MasterProcedureScheduler;
     128: aload         6
     130: aload_1
     131: invokevirtual #42                 // Method org/apache/hadoop/hbase/master/procedure/MasterProcedureScheduler.waitTableSharedLock:(Lorg/apache/hadoop/hbase/procedure2/Procedure;Lorg/apache/hadoop/hbase/TableName;)Z
     134: invokestatic  #38                 // Method java/lang/Boolean.valueOf:(Z)Ljava/lang/Boolean;
     137: invokestatic  #39                 // Method org/junit/Assert.assertEquals:(Ljava/lang/Object;Ljava/lang/Object;)V
     140: aload_0
     141: getfield      #8                  // Field queue:Lorg/apache/hadoop/hbase/master/procedure/MasterProcedureScheduler;
     144: aload_1
     145: aload_3
     146: invokevirtual #35                 // Method org/apache/hadoop/hbase/master/procedure/MasterProcedureScheduler.markTableAsDeleted:(Lorg/apache/hadoop/hbase/TableName;Lorg/apache/hadoop/hbase/procedure2/Procedure;)Z
     149: invokestatic  #37                 // Method org/junit/Assert.assertFalse:(Z)V
     152: iinc          5, 1
     155: goto          85
     158: iconst_0
     159: istore        5
     161: iload         5
     163: iconst_2
     164: if_icmpge     198
     167: aload_0
     168: getfield      #8                  // Field queue:Lorg/apache/hadoop/hbase/master/procedure/MasterProcedureScheduler;
     171: aload_1
     172: aload_3
     173: invokevirtual #35                 // Method org/apache/hadoop/hbase/master/procedure/MasterProcedureScheduler.markTableAsDeleted:(Lorg/apache/hadoop/hbase/TableName;Lorg/apache/hadoop/hbase/procedure2/Procedure;)Z
     176: invokestatic  #37                 // Method org/junit/Assert.assertFalse:(Z)V
     179: aload_0
     180: getfield      #8                  // Field queue:Lorg/apache/hadoop/hbase/master/procedure/MasterProcedureScheduler;
     183: aload         4
     185: iload         5
     187: aaload
     188: aload_1
     189: invokevirtual #43                 // Method org/apache/hadoop/hbase/master/procedure/MasterProcedureScheduler.wakeTableSharedLock:(Lorg/apache/hadoop/hbase/procedure2/Procedure;Lorg/apache/hadoop/hbase/TableName;)V
     192: iinc          5, 1
     195: goto          161
     198: lconst_0
     199: aload_0
     200: getfield      #8                  // Field queue:Lorg/apache/hadoop/hbase/master/procedure/MasterProcedureScheduler;
     203: invokevirtual #11                 // Method org/apache/hadoop/hbase/master/procedure/MasterProcedureScheduler.size:()I
     206: i2l
     207: invokestatic  #24                 // Method org/junit/Assert.assertEquals:(JJ)V
     210: aload_0
     211: getfield      #8                  // Field queue:Lorg/apache/hadoop/hbase/master/procedure/MasterProcedureScheduler;
     214: aload_1
     215: aload_3
     216: invokevirtual #35                 // Method org/apache/hadoop/hbase/master/procedure/MasterProcedureScheduler.markTableAsDeleted:(Lorg/apache/hadoop/hbase/TableName;Lorg/apache/hadoop/hbase/procedure2/Procedure;)Z
     219: invokestatic  #28                 // Method org/junit/Assert.assertTrue:(Z)V
     222: return

  public void testVerifyRwLocks() throws java.lang.Exception;
    Code:
       0: aload_0
       1: getfield      #4                  // Field name:Lorg/junit/rules/TestName;
       4: invokevirtual #36                 // Method org/junit/rules/TestName.getMethodName:()Ljava/lang/String;
       7: invokestatic  #19                 // Method org/apache/hadoop/hbase/TableName.valueOf:(Ljava/lang/String;)Lorg/apache/hadoop/hbase/TableName;
      10: astore_1
      11: aload_0
      12: getfield      #8                  // Field queue:Lorg/apache/hadoop/hbase/master/procedure/MasterProcedureScheduler;
      15: new           #20                 // class org/apache/hadoop/hbase/master/procedure/TestMasterProcedureScheduler$TestTableProcedure
      18: dup
      19: lconst_1
      20: aload_1
      21: getstatic     #21                 // Field org/apache/hadoop/hbase/master/procedure/TableProcedureInterface$TableOperationType.EDIT:Lorg/apache/hadoop/hbase/master/procedure/TableProcedureInterface$TableOperationType;
      24: invokespecial #22                 // Method org/apache/hadoop/hbase/master/procedure/TestMasterProcedureScheduler$TestTableProcedure."<init>":(JLorg/apache/hadoop/hbase/TableName;Lorg/apache/hadoop/hbase/master/procedure/TableProcedureInterface$TableOperationType;)V
      27: invokevirtual #23                 // Method org/apache/hadoop/hbase/master/procedure/MasterProcedureScheduler.addBack:(Lorg/apache/hadoop/hbase/procedure2/Procedure;)V
      30: aload_0
      31: getfield      #8                  // Field queue:Lorg/apache/hadoop/hbase/master/procedure/MasterProcedureScheduler;
      34: new           #20                 // class org/apache/hadoop/hbase/master/procedure/TestMasterProcedureScheduler$TestTableProcedure
      37: dup
      38: ldc2_w        #44                 // long 2l
      41: aload_1
      42: getstatic     #40                 // Field org/apache/hadoop/hbase/master/procedure/TableProcedureInterface$TableOperationType.READ:Lorg/apache/hadoop/hbase/master/procedure/TableProcedureInterface$TableOperationType;
      45: invokespecial #22                 // Method org/apache/hadoop/hbase/master/procedure/TestMasterProcedureScheduler$TestTableProcedure."<init>":(JLorg/apache/hadoop/hbase/TableName;Lorg/apache/hadoop/hbase/master/procedure/TableProcedureInterface$TableOperationType;)V
      48: invokevirtual #23                 // Method org/apache/hadoop/hbase/master/procedure/MasterProcedureScheduler.addBack:(Lorg/apache/hadoop/hbase/procedure2/Procedure;)V
      51: aload_0
      52: getfield      #8                  // Field queue:Lorg/apache/hadoop/hbase/master/procedure/MasterProcedureScheduler;
      55: new           #20                 // class org/apache/hadoop/hbase/master/procedure/TestMasterProcedureScheduler$TestTableProcedure
      58: dup
      59: ldc2_w        #46                 // long 3l
      62: aload_1
      63: getstatic     #21                 // Field org/apache/hadoop/hbase/master/procedure/TableProcedureInterface$TableOperationType.EDIT:Lorg/apache/hadoop/hbase/master/procedure/TableProcedureInterface$TableOperationType;
      66: invokespecial #22                 // Method org/apache/hadoop/hbase/master/procedure/TestMasterProcedureScheduler$TestTableProcedure."<init>":(JLorg/apache/hadoop/hbase/TableName;Lorg/apache/hadoop/hbase/master/procedure/TableProcedureInterface$TableOperationType;)V
      69: invokevirtual #23                 // Method org/apache/hadoop/hbase/master/procedure/MasterProcedureScheduler.addBack:(Lorg/apache/hadoop/hbase/procedure2/Procedure;)V
      72: aload_0
      73: getfield      #8                  // Field queue:Lorg/apache/hadoop/hbase/master/procedure/MasterProcedureScheduler;
      76: invokevirtual #27                 // Method org/apache/hadoop/hbase/master/procedure/MasterProcedureScheduler.poll:()Lorg/apache/hadoop/hbase/procedure2/Procedure;
      79: astore_2
      80: lconst_1
      81: aload_2
      82: invokevirtual #33                 // Method org/apache/hadoop/hbase/procedure2/Procedure.getProcId:()J
      85: invokestatic  #24                 // Method org/junit/Assert.assertEquals:(JJ)V
      88: iconst_0
      89: invokestatic  #38                 // Method java/lang/Boolean.valueOf:(Z)Ljava/lang/Boolean;
      92: aload_0
      93: getfield      #8                  // Field queue:Lorg/apache/hadoop/hbase/master/procedure/MasterProcedureScheduler;
      96: aload_2
      97: aload_1
      98: invokevirtual #30                 // Method org/apache/hadoop/hbase/master/procedure/MasterProcedureScheduler.waitTableExclusiveLock:(Lorg/apache/hadoop/hbase/procedure2/Procedure;Lorg/apache/hadoop/hbase/TableName;)Z
     101: invokestatic  #38                 // Method java/lang/Boolean.valueOf:(Z)Ljava/lang/Boolean;
     104: invokestatic  #39                 // Method org/junit/Assert.assertEquals:(Ljava/lang/Object;Ljava/lang/Object;)V
     107: aconst_null
     108: aload_0
     109: getfield      #8                  // Field queue:Lorg/apache/hadoop/hbase/master/procedure/MasterProcedureScheduler;
     112: lconst_0
     113: invokevirtual #48                 // Method org/apache/hadoop/hbase/master/procedure/MasterProcedureScheduler.poll:(J)Lorg/apache/hadoop/hbase/procedure2/Procedure;
     116: invokestatic  #39                 // Method org/junit/Assert.assertEquals:(Ljava/lang/Object;Ljava/lang/Object;)V
     119: aload_0
     120: getfield      #8                  // Field queue:Lorg/apache/hadoop/hbase/master/procedure/MasterProcedureScheduler;
     123: aload_2
     124: aload_1
     125: invokevirtual #31                 // Method org/apache/hadoop/hbase/master/procedure/MasterProcedureScheduler.wakeTableExclusiveLock:(Lorg/apache/hadoop/hbase/procedure2/Procedure;Lorg/apache/hadoop/hbase/TableName;)V
     128: aload_0
     129: getfield      #8                  // Field queue:Lorg/apache/hadoop/hbase/master/procedure/MasterProcedureScheduler;
     132: invokevirtual #27                 // Method org/apache/hadoop/hbase/master/procedure/MasterProcedureScheduler.poll:()Lorg/apache/hadoop/hbase/procedure2/Procedure;
     135: astore_3
     136: ldc2_w        #44                 // long 2l
     139: aload_3
     140: invokevirtual #33                 // Method org/apache/hadoop/hbase/procedure2/Procedure.getProcId:()J
     143: invokestatic  #24                 // Method org/junit/Assert.assertEquals:(JJ)V
     146: iconst_0
     147: invokestatic  #38                 // Method java/lang/Boolean.valueOf:(Z)Ljava/lang/Boolean;
     150: aload_0
     151: getfield      #8                  // Field queue:Lorg/apache/hadoop/hbase/master/procedure/MasterProcedureScheduler;
     154: aload_3
     155: aload_1
     156: invokevirtual #42                 // Method org/apache/hadoop/hbase/master/procedure/MasterProcedureScheduler.waitTableSharedLock:(Lorg/apache/hadoop/hbase/procedure2/Procedure;Lorg/apache/hadoop/hbase/TableName;)Z
     159: invokestatic  #38                 // Method java/lang/Boolean.valueOf:(Z)Ljava/lang/Boolean;
     162: invokestatic  #39                 // Method org/junit/Assert.assertEquals:(Ljava/lang/Object;Ljava/lang/Object;)V
     165: aconst_null
     166: aload_0
     167: getfield      #8                  // Field queue:Lorg/apache/hadoop/hbase/master/procedure/MasterProcedureScheduler;
     170: lconst_0
     171: invokevirtual #48                 // Method org/apache/hadoop/hbase/master/procedure/MasterProcedureScheduler.poll:(J)Lorg/apache/hadoop/hbase/procedure2/Procedure;
     174: invokestatic  #39                 // Method org/junit/Assert.assertEquals:(Ljava/lang/Object;Ljava/lang/Object;)V
     177: aload_0
     178: getfield      #8                  // Field queue:Lorg/apache/hadoop/hbase/master/procedure/MasterProcedureScheduler;
     181: aload_3
     182: aload_1
     183: invokevirtual #43                 // Method org/apache/hadoop/hbase/master/procedure/MasterProcedureScheduler.wakeTableSharedLock:(Lorg/apache/hadoop/hbase/procedure2/Procedure;Lorg/apache/hadoop/hbase/TableName;)V
     186: aload_0
     187: getfield      #8                  // Field queue:Lorg/apache/hadoop/hbase/master/procedure/MasterProcedureScheduler;
     190: new           #20                 // class org/apache/hadoop/hbase/master/procedure/TestMasterProcedureScheduler$TestTableProcedure
     193: dup
     194: ldc2_w        #49                 // long 4l
     197: aload_1
     198: getstatic     #40                 // Field org/apache/hadoop/hbase/master/procedure/TableProcedureInterface$TableOperationType.READ:Lorg/apache/hadoop/hbase/master/procedure/TableProcedureInterface$TableOperationType;
     201: invokespecial #22                 // Method org/apache/hadoop/hbase/master/procedure/TestMasterProcedureScheduler$TestTableProcedure."<init>":(JLorg/apache/hadoop/hbase/TableName;Lorg/apache/hadoop/hbase/master/procedure/TableProcedureInterface$TableOperationType;)V
     204: invokevirtual #23                 // Method org/apache/hadoop/hbase/master/procedure/MasterProcedureScheduler.addBack:(Lorg/apache/hadoop/hbase/procedure2/Procedure;)V
     207: aload_0
     208: getfield      #8                  // Field queue:Lorg/apache/hadoop/hbase/master/procedure/MasterProcedureScheduler;
     211: new           #20                 // class org/apache/hadoop/hbase/master/procedure/TestMasterProcedureScheduler$TestTableProcedure
     214: dup
     215: ldc2_w        #51                 // long 5l
     218: aload_1
     219: getstatic     #40                 // Field org/apache/hadoop/hbase/master/procedure/TableProcedureInterface$TableOperationType.READ:Lorg/apache/hadoop/hbase/master/procedure/TableProcedureInterface$TableOperationType;
     222: invokespecial #22                 // Method org/apache/hadoop/hbase/master/procedure/TestMasterProcedureScheduler$TestTableProcedure."<init>":(JLorg/apache/hadoop/hbase/TableName;Lorg/apache/hadoop/hbase/master/procedure/TableProcedureInterface$TableOperationType;)V
     225: invokevirtual #23                 // Method org/apache/hadoop/hbase/master/procedure/MasterProcedureScheduler.addBack:(Lorg/apache/hadoop/hbase/procedure2/Procedure;)V
     228: aload_0
     229: getfield      #8                  // Field queue:Lorg/apache/hadoop/hbase/master/procedure/MasterProcedureScheduler;
     232: invokevirtual #27                 // Method org/apache/hadoop/hbase/master/procedure/MasterProcedureScheduler.poll:()Lorg/apache/hadoop/hbase/procedure2/Procedure;
     235: astore        4
     237: iconst_0
     238: invokestatic  #38                 // Method java/lang/Boolean.valueOf:(Z)Ljava/lang/Boolean;
     241: aload_0
     242: getfield      #8                  // Field queue:Lorg/apache/hadoop/hbase/master/procedure/MasterProcedureScheduler;
     245: aload         4
     247: aload_1
     248: invokevirtual #30                 // Method org/apache/hadoop/hbase/master/procedure/MasterProcedureScheduler.waitTableExclusiveLock:(Lorg/apache/hadoop/hbase/procedure2/Procedure;Lorg/apache/hadoop/hbase/TableName;)Z
     251: invokestatic  #38                 // Method java/lang/Boolean.valueOf:(Z)Ljava/lang/Boolean;
     254: invokestatic  #39                 // Method org/junit/Assert.assertEquals:(Ljava/lang/Object;Ljava/lang/Object;)V
     257: aconst_null
     258: aload_0
     259: getfield      #8                  // Field queue:Lorg/apache/hadoop/hbase/master/procedure/MasterProcedureScheduler;
     262: lconst_0
     263: invokevirtual #48                 // Method org/apache/hadoop/hbase/master/procedure/MasterProcedureScheduler.poll:(J)Lorg/apache/hadoop/hbase/procedure2/Procedure;
     266: invokestatic  #39                 // Method org/junit/Assert.assertEquals:(Ljava/lang/Object;Ljava/lang/Object;)V
     269: aload_0
     270: getfield      #8                  // Field queue:Lorg/apache/hadoop/hbase/master/procedure/MasterProcedureScheduler;
     273: aload         4
     275: aload_1
     276: invokevirtual #31                 // Method org/apache/hadoop/hbase/master/procedure/MasterProcedureScheduler.wakeTableExclusiveLock:(Lorg/apache/hadoop/hbase/procedure2/Procedure;Lorg/apache/hadoop/hbase/TableName;)V
     279: aload_0
     280: getfield      #8                  // Field queue:Lorg/apache/hadoop/hbase/master/procedure/MasterProcedureScheduler;
     283: invokevirtual #27                 // Method org/apache/hadoop/hbase/master/procedure/MasterProcedureScheduler.poll:()Lorg/apache/hadoop/hbase/procedure2/Procedure;
     286: astore_3
     287: ldc2_w        #49                 // long 4l
     290: aload_3
     291: invokevirtual #33                 // Method org/apache/hadoop/hbase/procedure2/Procedure.getProcId:()J
     294: invokestatic  #24                 // Method org/junit/Assert.assertEquals:(JJ)V
     297: iconst_0
     298: invokestatic  #38                 // Method java/lang/Boolean.valueOf:(Z)Ljava/lang/Boolean;
     301: aload_0
     302: getfield      #8                  // Field queue:Lorg/apache/hadoop/hbase/master/procedure/MasterProcedureScheduler;
     305: aload_3
     306: aload_1
     307: invokevirtual #42                 // Method org/apache/hadoop/hbase/master/procedure/MasterProcedureScheduler.waitTableSharedLock:(Lorg/apache/hadoop/hbase/procedure2/Procedure;Lorg/apache/hadoop/hbase/TableName;)Z
     310: invokestatic  #38                 // Method java/lang/Boolean.valueOf:(Z)Ljava/lang/Boolean;
     313: invokestatic  #39                 // Method org/junit/Assert.assertEquals:(Ljava/lang/Object;Ljava/lang/Object;)V
     316: aload_0
     317: getfield      #8                  // Field queue:Lorg/apache/hadoop/hbase/master/procedure/MasterProcedureScheduler;
     320: invokevirtual #27                 // Method org/apache/hadoop/hbase/master/procedure/MasterProcedureScheduler.poll:()Lorg/apache/hadoop/hbase/procedure2/Procedure;
     323: astore        5
     325: ldc2_w        #51                 // long 5l
     328: aload         5
     330: invokevirtual #33                 // Method org/apache/hadoop/hbase/procedure2/Procedure.getProcId:()J
     333: invokestatic  #24                 // Method org/junit/Assert.assertEquals:(JJ)V
     336: iconst_0
     337: invokestatic  #38                 // Method java/lang/Boolean.valueOf:(Z)Ljava/lang/Boolean;
     340: aload_0
     341: getfield      #8                  // Field queue:Lorg/apache/hadoop/hbase/master/procedure/MasterProcedureScheduler;
     344: aload         5
     346: aload_1
     347: invokevirtual #42                 // Method org/apache/hadoop/hbase/master/procedure/MasterProcedureScheduler.waitTableSharedLock:(Lorg/apache/hadoop/hbase/procedure2/Procedure;Lorg/apache/hadoop/hbase/TableName;)Z
     350: invokestatic  #38                 // Method java/lang/Boolean.valueOf:(Z)Ljava/lang/Boolean;
     353: invokestatic  #39                 // Method org/junit/Assert.assertEquals:(Ljava/lang/Object;Ljava/lang/Object;)V
     356: aload_0
     357: getfield      #8                  // Field queue:Lorg/apache/hadoop/hbase/master/procedure/MasterProcedureScheduler;
     360: aload_3
     361: aload_1
     362: invokevirtual #43                 // Method org/apache/hadoop/hbase/master/procedure/MasterProcedureScheduler.wakeTableSharedLock:(Lorg/apache/hadoop/hbase/procedure2/Procedure;Lorg/apache/hadoop/hbase/TableName;)V
     365: aload_0
     366: getfield      #8                  // Field queue:Lorg/apache/hadoop/hbase/master/procedure/MasterProcedureScheduler;
     369: aload         5
     371: aload_1
     372: invokevirtual #43                 // Method org/apache/hadoop/hbase/master/procedure/MasterProcedureScheduler.wakeTableSharedLock:(Lorg/apache/hadoop/hbase/procedure2/Procedure;Lorg/apache/hadoop/hbase/TableName;)V
     375: lconst_0
     376: aload_0
     377: getfield      #8                  // Field queue:Lorg/apache/hadoop/hbase/master/procedure/MasterProcedureScheduler;
     380: invokevirtual #11                 // Method org/apache/hadoop/hbase/master/procedure/MasterProcedureScheduler.size:()I
     383: i2l
     384: invokestatic  #24                 // Method org/junit/Assert.assertEquals:(JJ)V
     387: ldc           #53                 // String queue should be deleted
     389: aload_0
     390: getfield      #8                  // Field queue:Lorg/apache/hadoop/hbase/master/procedure/MasterProcedureScheduler;
     393: aload_1
     394: aload         4
     396: invokevirtual #35                 // Method org/apache/hadoop/hbase/master/procedure/MasterProcedureScheduler.markTableAsDeleted:(Lorg/apache/hadoop/hbase/TableName;Lorg/apache/hadoop/hbase/procedure2/Procedure;)Z
     399: invokestatic  #54                 // Method org/junit/Assert.assertTrue:(Ljava/lang/String;Z)V
     402: return

  public void testVerifyNamespaceRwLocks() throws java.lang.Exception;
    Code:
       0: ldc           #55                 // String ns1
       2: astore_1
       3: ldc           #56                 // String ns2
       5: astore_2
       6: aload_1
       7: aload_0
       8: getfield      #4                  // Field name:Lorg/junit/rules/TestName;
      11: invokevirtual #36                 // Method org/junit/rules/TestName.getMethodName:()Ljava/lang/String;
      14: invokestatic  #57                 // Method org/apache/hadoop/hbase/TableName.valueOf:(Ljava/lang/String;Ljava/lang/String;)Lorg/apache/hadoop/hbase/TableName;
      17: astore_3
      18: aload_2
      19: aload_0
      20: getfield      #4                  // Field name:Lorg/junit/rules/TestName;
      23: invokevirtual #36                 // Method org/junit/rules/TestName.getMethodName:()Ljava/lang/String;
      26: invokestatic  #57                 // Method org/apache/hadoop/hbase/TableName.valueOf:(Ljava/lang/String;Ljava/lang/String;)Lorg/apache/hadoop/hbase/TableName;
      29: astore        4
      31: aload_0
      32: getfield      #8                  // Field queue:Lorg/apache/hadoop/hbase/master/procedure/MasterProcedureScheduler;
      35: new           #58                 // class org/apache/hadoop/hbase/master/procedure/TestMasterProcedureScheduler$TestNamespaceProcedure
      38: dup
      39: lconst_1
      40: aload_1
      41: getstatic     #21                 // Field org/apache/hadoop/hbase/master/procedure/TableProcedureInterface$TableOperationType.EDIT:Lorg/apache/hadoop/hbase/master/procedure/TableProcedureInterface$TableOperationType;
      44: invokespecial #59                 // Method org/apache/hadoop/hbase/master/procedure/TestMasterProcedureScheduler$TestNamespaceProcedure."<init>":(JLjava/lang/String;Lorg/apache/hadoop/hbase/master/procedure/TableProcedureInterface$TableOperationType;)V
      47: invokevirtual #23                 // Method org/apache/hadoop/hbase/master/procedure/MasterProcedureScheduler.addBack:(Lorg/apache/hadoop/hbase/procedure2/Procedure;)V
      50: aload_0
      51: getfield      #8                  // Field queue:Lorg/apache/hadoop/hbase/master/procedure/MasterProcedureScheduler;
      54: new           #20                 // class org/apache/hadoop/hbase/master/procedure/TestMasterProcedureScheduler$TestTableProcedure
      57: dup
      58: ldc2_w        #44                 // long 2l
      61: aload_3
      62: getstatic     #21                 // Field org/apache/hadoop/hbase/master/procedure/TableProcedureInterface$TableOperationType.EDIT:Lorg/apache/hadoop/hbase/master/procedure/TableProcedureInterface$TableOperationType;
      65: invokespecial #22                 // Method org/apache/hadoop/hbase/master/procedure/TestMasterProcedureScheduler$TestTableProcedure."<init>":(JLorg/apache/hadoop/hbase/TableName;Lorg/apache/hadoop/hbase/master/procedure/TableProcedureInterface$TableOperationType;)V
      68: invokevirtual #23                 // Method org/apache/hadoop/hbase/master/procedure/MasterProcedureScheduler.addBack:(Lorg/apache/hadoop/hbase/procedure2/Procedure;)V
      71: aload_0
      72: getfield      #8                  // Field queue:Lorg/apache/hadoop/hbase/master/procedure/MasterProcedureScheduler;
      75: new           #20                 // class org/apache/hadoop/hbase/master/procedure/TestMasterProcedureScheduler$TestTableProcedure
      78: dup
      79: ldc2_w        #46                 // long 3l
      82: aload         4
      84: getstatic     #21                 // Field org/apache/hadoop/hbase/master/procedure/TableProcedureInterface$TableOperationType.EDIT:Lorg/apache/hadoop/hbase/master/procedure/TableProcedureInterface$TableOperationType;
      87: invokespecial #22                 // Method org/apache/hadoop/hbase/master/procedure/TestMasterProcedureScheduler$TestTableProcedure."<init>":(JLorg/apache/hadoop/hbase/TableName;Lorg/apache/hadoop/hbase/master/procedure/TableProcedureInterface$TableOperationType;)V
      90: invokevirtual #23                 // Method org/apache/hadoop/hbase/master/procedure/MasterProcedureScheduler.addBack:(Lorg/apache/hadoop/hbase/procedure2/Procedure;)V
      93: aload_0
      94: getfield      #8                  // Field queue:Lorg/apache/hadoop/hbase/master/procedure/MasterProcedureScheduler;
      97: new           #58                 // class org/apache/hadoop/hbase/master/procedure/TestMasterProcedureScheduler$TestNamespaceProcedure
     100: dup
     101: ldc2_w        #49                 // long 4l
     104: aload_2
     105: getstatic     #21                 // Field org/apache/hadoop/hbase/master/procedure/TableProcedureInterface$TableOperationType.EDIT:Lorg/apache/hadoop/hbase/master/procedure/TableProcedureInterface$TableOperationType;
     108: invokespecial #59                 // Method org/apache/hadoop/hbase/master/procedure/TestMasterProcedureScheduler$TestNamespaceProcedure."<init>":(JLjava/lang/String;Lorg/apache/hadoop/hbase/master/procedure/TableProcedureInterface$TableOperationType;)V
     111: invokevirtual #23                 // Method org/apache/hadoop/hbase/master/procedure/MasterProcedureScheduler.addBack:(Lorg/apache/hadoop/hbase/procedure2/Procedure;)V
     114: aload_0
     115: getfield      #8                  // Field queue:Lorg/apache/hadoop/hbase/master/procedure/MasterProcedureScheduler;
     118: invokevirtual #27                 // Method org/apache/hadoop/hbase/master/procedure/MasterProcedureScheduler.poll:()Lorg/apache/hadoop/hbase/procedure2/Procedure;
     121: astore        5
     123: lconst_1
     124: aload         5
     126: invokevirtual #33                 // Method org/apache/hadoop/hbase/procedure2/Procedure.getProcId:()J
     129: invokestatic  #24                 // Method org/junit/Assert.assertEquals:(JJ)V
     132: aload_0
     133: getfield      #8                  // Field queue:Lorg/apache/hadoop/hbase/master/procedure/MasterProcedureScheduler;
     136: aload         5
     138: aload_1
     139: invokevirtual #60                 // Method org/apache/hadoop/hbase/master/procedure/MasterProcedureScheduler.waitNamespaceExclusiveLock:(Lorg/apache/hadoop/hbase/procedure2/Procedure;Ljava/lang/String;)Z
     142: invokestatic  #37                 // Method org/junit/Assert.assertFalse:(Z)V
     145: aload_0
     146: getfield      #8                  // Field queue:Lorg/apache/hadoop/hbase/master/procedure/MasterProcedureScheduler;
     149: invokevirtual #27                 // Method org/apache/hadoop/hbase/master/procedure/MasterProcedureScheduler.poll:()Lorg/apache/hadoop/hbase/procedure2/Procedure;
     152: astore        6
     154: ldc2_w        #49                 // long 4l
     157: aload         6
     159: invokevirtual #33                 // Method org/apache/hadoop/hbase/procedure2/Procedure.getProcId:()J
     162: invokestatic  #24                 // Method org/junit/Assert.assertEquals:(JJ)V
     165: aload_0
     166: getfield      #8                  // Field queue:Lorg/apache/hadoop/hbase/master/procedure/MasterProcedureScheduler;
     169: aload         6
     171: aload_2
     172: invokevirtual #60                 // Method org/apache/hadoop/hbase/master/procedure/MasterProcedureScheduler.waitNamespaceExclusiveLock:(Lorg/apache/hadoop/hbase/procedure2/Procedure;Ljava/lang/String;)Z
     175: invokestatic  #37                 // Method org/junit/Assert.assertFalse:(Z)V
     178: aload_0
     179: getfield      #8                  // Field queue:Lorg/apache/hadoop/hbase/master/procedure/MasterProcedureScheduler;
     182: aload         6
     184: aload_2
     185: invokevirtual #61                 // Method org/apache/hadoop/hbase/master/procedure/MasterProcedureScheduler.wakeNamespaceExclusiveLock:(Lorg/apache/hadoop/hbase/procedure2/Procedure;Ljava/lang/String;)V
     188: aload_0
     189: getfield      #8                  // Field queue:Lorg/apache/hadoop/hbase/master/procedure/MasterProcedureScheduler;
     192: aload         6
     194: invokevirtual #62                 // Method org/apache/hadoop/hbase/master/procedure/MasterProcedureScheduler.yield:(Lorg/apache/hadoop/hbase/procedure2/Procedure;)V
     197: aload_0
     198: getfield      #8                  // Field queue:Lorg/apache/hadoop/hbase/master/procedure/MasterProcedureScheduler;
     201: invokevirtual #27                 // Method org/apache/hadoop/hbase/master/procedure/MasterProcedureScheduler.poll:()Lorg/apache/hadoop/hbase/procedure2/Procedure;
     204: astore        6
     206: ldc2_w        #49                 // long 4l
     209: aload         6
     211: invokevirtual #33                 // Method org/apache/hadoop/hbase/procedure2/Procedure.getProcId:()J
     214: invokestatic  #24                 // Method org/junit/Assert.assertEquals:(JJ)V
     217: aload_0
     218: getfield      #8                  // Field queue:Lorg/apache/hadoop/hbase/master/procedure/MasterProcedureScheduler;
     221: aload         6
     223: aload_2
     224: invokevirtual #60                 // Method org/apache/hadoop/hbase/master/procedure/MasterProcedureScheduler.waitNamespaceExclusiveLock:(Lorg/apache/hadoop/hbase/procedure2/Procedure;Ljava/lang/String;)Z
     227: invokestatic  #37                 // Method org/junit/Assert.assertFalse:(Z)V
     230: aload_0
     231: getfield      #8                  // Field queue:Lorg/apache/hadoop/hbase/master/procedure/MasterProcedureScheduler;
     234: invokevirtual #27                 // Method org/apache/hadoop/hbase/master/procedure/MasterProcedureScheduler.poll:()Lorg/apache/hadoop/hbase/procedure2/Procedure;
     237: invokestatic  #63                 // Method org/junit/Assert.assertNull:(Ljava/lang/Object;)V
     240: aload_0
     241: getfield      #8                  // Field queue:Lorg/apache/hadoop/hbase/master/procedure/MasterProcedureScheduler;
     244: aload         5
     246: aload_1
     247: invokevirtual #61                 // Method org/apache/hadoop/hbase/master/procedure/MasterProcedureScheduler.wakeNamespaceExclusiveLock:(Lorg/apache/hadoop/hbase/procedure2/Procedure;Ljava/lang/String;)V
     250: aload_0
     251: getfield      #8                  // Field queue:Lorg/apache/hadoop/hbase/master/procedure/MasterProcedureScheduler;
     254: invokevirtual #27                 // Method org/apache/hadoop/hbase/master/procedure/MasterProcedureScheduler.poll:()Lorg/apache/hadoop/hbase/procedure2/Procedure;
     257: invokevirtual #33                 // Method org/apache/hadoop/hbase/procedure2/Procedure.getProcId:()J
     260: lstore        7
     262: ldc2_w        #44                 // long 2l
     265: lload         7
     267: invokestatic  #24                 // Method org/junit/Assert.assertEquals:(JJ)V
     270: aload_0
     271: getfield      #8                  // Field queue:Lorg/apache/hadoop/hbase/master/procedure/MasterProcedureScheduler;
     274: aload         6
     276: aload_2
     277: invokevirtual #61                 // Method org/apache/hadoop/hbase/master/procedure/MasterProcedureScheduler.wakeNamespaceExclusiveLock:(Lorg/apache/hadoop/hbase/procedure2/Procedure;Ljava/lang/String;)V
     280: aload_0
     281: getfield      #8                  // Field queue:Lorg/apache/hadoop/hbase/master/procedure/MasterProcedureScheduler;
     284: invokevirtual #27                 // Method org/apache/hadoop/hbase/master/procedure/MasterProcedureScheduler.poll:()Lorg/apache/hadoop/hbase/procedure2/Procedure;
     287: invokevirtual #33                 // Method org/apache/hadoop/hbase/procedure2/Procedure.getProcId:()J
     290: lstore        7
     292: ldc2_w        #46                 // long 3l
     295: lload         7
     297: invokestatic  #24                 // Method org/junit/Assert.assertEquals:(JJ)V
     300: return

  public void testVerifyNamespaceXLock() throws java.lang.Exception;
    Code:
       0: ldc           #55                 // String ns1
       2: astore_1
       3: aload_1
       4: aload_0
       5: getfield      #4                  // Field name:Lorg/junit/rules/TestName;
       8: invokevirtual #36                 // Method org/junit/rules/TestName.getMethodName:()Ljava/lang/String;
      11: invokestatic  #57                 // Method org/apache/hadoop/hbase/TableName.valueOf:(Ljava/lang/String;Ljava/lang/String;)Lorg/apache/hadoop/hbase/TableName;
      14: astore_2
      15: aload_0
      16: getfield      #8                  // Field queue:Lorg/apache/hadoop/hbase/master/procedure/MasterProcedureScheduler;
      19: new           #58                 // class org/apache/hadoop/hbase/master/procedure/TestMasterProcedureScheduler$TestNamespaceProcedure
      22: dup
      23: lconst_1
      24: aload_1
      25: getstatic     #64                 // Field org/apache/hadoop/hbase/master/procedure/TableProcedureInterface$TableOperationType.CREATE:Lorg/apache/hadoop/hbase/master/procedure/TableProcedureInterface$TableOperationType;
      28: invokespecial #59                 // Method org/apache/hadoop/hbase/master/procedure/TestMasterProcedureScheduler$TestNamespaceProcedure."<init>":(JLjava/lang/String;Lorg/apache/hadoop/hbase/master/procedure/TableProcedureInterface$TableOperationType;)V
      31: invokevirtual #23                 // Method org/apache/hadoop/hbase/master/procedure/MasterProcedureScheduler.addBack:(Lorg/apache/hadoop/hbase/procedure2/Procedure;)V
      34: aload_0
      35: getfield      #8                  // Field queue:Lorg/apache/hadoop/hbase/master/procedure/MasterProcedureScheduler;
      38: new           #20                 // class org/apache/hadoop/hbase/master/procedure/TestMasterProcedureScheduler$TestTableProcedure
      41: dup
      42: ldc2_w        #44                 // long 2l
      45: aload_2
      46: getstatic     #40                 // Field org/apache/hadoop/hbase/master/procedure/TableProcedureInterface$TableOperationType.READ:Lorg/apache/hadoop/hbase/master/procedure/TableProcedureInterface$TableOperationType;
      49: invokespecial #22                 // Method org/apache/hadoop/hbase/master/procedure/TestMasterProcedureScheduler$TestTableProcedure."<init>":(JLorg/apache/hadoop/hbase/TableName;Lorg/apache/hadoop/hbase/master/procedure/TableProcedureInterface$TableOperationType;)V
      52: invokevirtual #23                 // Method org/apache/hadoop/hbase/master/procedure/MasterProcedureScheduler.addBack:(Lorg/apache/hadoop/hbase/procedure2/Procedure;)V
      55: aload_0
      56: getfield      #8                  // Field queue:Lorg/apache/hadoop/hbase/master/procedure/MasterProcedureScheduler;
      59: invokevirtual #27                 // Method org/apache/hadoop/hbase/master/procedure/MasterProcedureScheduler.poll:()Lorg/apache/hadoop/hbase/procedure2/Procedure;
      62: astore_3
      63: lconst_1
      64: aload_3
      65: invokevirtual #33                 // Method org/apache/hadoop/hbase/procedure2/Procedure.getProcId:()J
      68: invokestatic  #24                 // Method org/junit/Assert.assertEquals:(JJ)V
      71: iconst_0
      72: invokestatic  #38                 // Method java/lang/Boolean.valueOf:(Z)Ljava/lang/Boolean;
      75: aload_0
      76: getfield      #8                  // Field queue:Lorg/apache/hadoop/hbase/master/procedure/MasterProcedureScheduler;
      79: aload_3
      80: aload_1
      81: invokevirtual #60                 // Method org/apache/hadoop/hbase/master/procedure/MasterProcedureScheduler.waitNamespaceExclusiveLock:(Lorg/apache/hadoop/hbase/procedure2/Procedure;Ljava/lang/String;)Z
      84: invokestatic  #38                 // Method java/lang/Boolean.valueOf:(Z)Ljava/lang/Boolean;
      87: invokestatic  #39                 // Method org/junit/Assert.assertEquals:(Ljava/lang/Object;Ljava/lang/Object;)V
      90: aconst_null
      91: aload_0
      92: getfield      #8                  // Field queue:Lorg/apache/hadoop/hbase/master/procedure/MasterProcedureScheduler;
      95: lconst_0
      96: invokevirtual #48                 // Method org/apache/hadoop/hbase/master/procedure/MasterProcedureScheduler.poll:(J)Lorg/apache/hadoop/hbase/procedure2/Procedure;
      99: invokestatic  #39                 // Method org/junit/Assert.assertEquals:(Ljava/lang/Object;Ljava/lang/Object;)V
     102: aload_0
     103: getfield      #8                  // Field queue:Lorg/apache/hadoop/hbase/master/procedure/MasterProcedureScheduler;
     106: aload_3
     107: aload_1
     108: invokevirtual #61                 // Method org/apache/hadoop/hbase/master/procedure/MasterProcedureScheduler.wakeNamespaceExclusiveLock:(Lorg/apache/hadoop/hbase/procedure2/Procedure;Ljava/lang/String;)V
     111: aload_0
     112: getfield      #8                  // Field queue:Lorg/apache/hadoop/hbase/master/procedure/MasterProcedureScheduler;
     115: invokevirtual #27                 // Method org/apache/hadoop/hbase/master/procedure/MasterProcedureScheduler.poll:()Lorg/apache/hadoop/hbase/procedure2/Procedure;
     118: astore_3
     119: ldc2_w        #44                 // long 2l
     122: aload_3
     123: invokevirtual #33                 // Method org/apache/hadoop/hbase/procedure2/Procedure.getProcId:()J
     126: invokestatic  #24                 // Method org/junit/Assert.assertEquals:(JJ)V
     129: iconst_0
     130: invokestatic  #38                 // Method java/lang/Boolean.valueOf:(Z)Ljava/lang/Boolean;
     133: aload_0
     134: getfield      #8                  // Field queue:Lorg/apache/hadoop/hbase/master/procedure/MasterProcedureScheduler;
     137: aload_3
     138: aload_2
     139: invokevirtual #30                 // Method org/apache/hadoop/hbase/master/procedure/MasterProcedureScheduler.waitTableExclusiveLock:(Lorg/apache/hadoop/hbase/procedure2/Procedure;Lorg/apache/hadoop/hbase/TableName;)Z
     142: invokestatic  #38                 // Method java/lang/Boolean.valueOf:(Z)Ljava/lang/Boolean;
     145: invokestatic  #39                 // Method org/junit/Assert.assertEquals:(Ljava/lang/Object;Ljava/lang/Object;)V
     148: aload_0
     149: getfield      #8                  // Field queue:Lorg/apache/hadoop/hbase/master/procedure/MasterProcedureScheduler;
     152: aload_3
     153: aload_2
     154: invokevirtual #31                 // Method org/apache/hadoop/hbase/master/procedure/MasterProcedureScheduler.wakeTableExclusiveLock:(Lorg/apache/hadoop/hbase/procedure2/Procedure;Lorg/apache/hadoop/hbase/TableName;)V
     157: return

  public void testXLockWaitingForExecutingSharedLockToRelease();
    Code:
       0: aload_0
       1: getfield      #4                  // Field name:Lorg/junit/rules/TestName;
       4: invokevirtual #36                 // Method org/junit/rules/TestName.getMethodName:()Ljava/lang/String;
       7: invokestatic  #19                 // Method org/apache/hadoop/hbase/TableName.valueOf:(Ljava/lang/String;)Lorg/apache/hadoop/hbase/TableName;
      10: astore_1
      11: aload_1
      12: invokestatic  #65                 // Method org/apache/hadoop/hbase/client/RegionInfoBuilder.newBuilder:(Lorg/apache/hadoop/hbase/TableName;)Lorg/apache/hadoop/hbase/client/RegionInfoBuilder;
      15: ldc           #66                 // String a
      17: invokestatic  #67                 // Method org/apache/hadoop/hbase/util/Bytes.toBytes:(Ljava/lang/String;)[B
      20: invokevirtual #68                 // Method org/apache/hadoop/hbase/client/RegionInfoBuilder.setStartKey:([B)Lorg/apache/hadoop/hbase/client/RegionInfoBuilder;
      23: ldc           #69                 // String b
      25: invokestatic  #67                 // Method org/apache/hadoop/hbase/util/Bytes.toBytes:(Ljava/lang/String;)[B
      28: invokevirtual #70                 // Method org/apache/hadoop/hbase/client/RegionInfoBuilder.setEndKey:([B)Lorg/apache/hadoop/hbase/client/RegionInfoBuilder;
      31: invokevirtual #71                 // Method org/apache/hadoop/hbase/client/RegionInfoBuilder.build:()Lorg/apache/hadoop/hbase/client/RegionInfo;
      34: astore_2
      35: aload_0
      36: getfield      #8                  // Field queue:Lorg/apache/hadoop/hbase/master/procedure/MasterProcedureScheduler;
      39: new           #72                 // class org/apache/hadoop/hbase/master/procedure/TestMasterProcedureScheduler$TestRegionProcedure
      42: dup
      43: lconst_1
      44: aload_1
      45: getstatic     #73                 // Field org/apache/hadoop/hbase/master/procedure/TableProcedureInterface$TableOperationType.REGION_ASSIGN:Lorg/apache/hadoop/hbase/master/procedure/TableProcedureInterface$TableOperationType;
      48: iconst_1
      49: anewarray     #74                 // class org/apache/hadoop/hbase/client/RegionInfo
      52: dup
      53: iconst_0
      54: aload_2
      55: aastore
      56: invokespecial #75                 // Method org/apache/hadoop/hbase/master/procedure/TestMasterProcedureScheduler$TestRegionProcedure."<init>":(JLorg/apache/hadoop/hbase/TableName;Lorg/apache/hadoop/hbase/master/procedure/TableProcedureInterface$TableOperationType;[Lorg/apache/hadoop/hbase/client/RegionInfo;)V
      59: invokevirtual #23                 // Method org/apache/hadoop/hbase/master/procedure/MasterProcedureScheduler.addBack:(Lorg/apache/hadoop/hbase/procedure2/Procedure;)V
      62: aload_0
      63: getfield      #8                  // Field queue:Lorg/apache/hadoop/hbase/master/procedure/MasterProcedureScheduler;
      66: new           #20                 // class org/apache/hadoop/hbase/master/procedure/TestMasterProcedureScheduler$TestTableProcedure
      69: dup
      70: ldc2_w        #44                 // long 2l
      73: aload_1
      74: getstatic     #21                 // Field org/apache/hadoop/hbase/master/procedure/TableProcedureInterface$TableOperationType.EDIT:Lorg/apache/hadoop/hbase/master/procedure/TableProcedureInterface$TableOperationType;
      77: invokespecial #22                 // Method org/apache/hadoop/hbase/master/procedure/TestMasterProcedureScheduler$TestTableProcedure."<init>":(JLorg/apache/hadoop/hbase/TableName;Lorg/apache/hadoop/hbase/master/procedure/TableProcedureInterface$TableOperationType;)V
      80: invokevirtual #23                 // Method org/apache/hadoop/hbase/master/procedure/MasterProcedureScheduler.addBack:(Lorg/apache/hadoop/hbase/procedure2/Procedure;)V
      83: aload_0
      84: getfield      #8                  // Field queue:Lorg/apache/hadoop/hbase/master/procedure/MasterProcedureScheduler;
      87: invokevirtual #27                 // Method org/apache/hadoop/hbase/master/procedure/MasterProcedureScheduler.poll:()Lorg/apache/hadoop/hbase/procedure2/Procedure;
      90: astore_3
      91: lconst_1
      92: aload_3
      93: invokevirtual #33                 // Method org/apache/hadoop/hbase/procedure2/Procedure.getProcId:()J
      96: invokestatic  #24                 // Method org/junit/Assert.assertEquals:(JJ)V
      99: iconst_0
     100: invokestatic  #38                 // Method java/lang/Boolean.valueOf:(Z)Ljava/lang/Boolean;
     103: aload_0
     104: getfield      #8                  // Field queue:Lorg/apache/hadoop/hbase/master/procedure/MasterProcedureScheduler;
     107: aload_3
     108: aload_2
     109: invokevirtual #76                 // Method org/apache/hadoop/hbase/master/procedure/MasterProcedureScheduler.waitRegion:(Lorg/apache/hadoop/hbase/procedure2/Procedure;Lorg/apache/hadoop/hbase/client/RegionInfo;)Z
     112: invokestatic  #38                 // Method java/lang/Boolean.valueOf:(Z)Ljava/lang/Boolean;
     115: invokestatic  #39                 // Method org/junit/Assert.assertEquals:(Ljava/lang/Object;Ljava/lang/Object;)V
     118: aconst_null
     119: aload_0
     120: getfield      #8                  // Field queue:Lorg/apache/hadoop/hbase/master/procedure/MasterProcedureScheduler;
     123: lconst_0
     124: invokevirtual #48                 // Method org/apache/hadoop/hbase/master/procedure/MasterProcedureScheduler.poll:(J)Lorg/apache/hadoop/hbase/procedure2/Procedure;
     127: invokestatic  #39                 // Method org/junit/Assert.assertEquals:(Ljava/lang/Object;Ljava/lang/Object;)V
     130: aload_0
     131: getfield      #8                  // Field queue:Lorg/apache/hadoop/hbase/master/procedure/MasterProcedureScheduler;
     134: aload_3
     135: aload_2
     136: invokevirtual #77                 // Method org/apache/hadoop/hbase/master/procedure/MasterProcedureScheduler.wakeRegion:(Lorg/apache/hadoop/hbase/procedure2/Procedure;Lorg/apache/hadoop/hbase/client/RegionInfo;)V
     139: aload_0
     140: getfield      #8                  // Field queue:Lorg/apache/hadoop/hbase/master/procedure/MasterProcedureScheduler;
     143: invokevirtual #27                 // Method org/apache/hadoop/hbase/master/procedure/MasterProcedureScheduler.poll:()Lorg/apache/hadoop/hbase/procedure2/Procedure;
     146: astore_3
     147: ldc2_w        #44                 // long 2l
     150: aload_3
     151: invokevirtual #33                 // Method org/apache/hadoop/hbase/procedure2/Procedure.getProcId:()J
     154: invokestatic  #24                 // Method org/junit/Assert.assertEquals:(JJ)V
     157: iconst_0
     158: invokestatic  #38                 // Method java/lang/Boolean.valueOf:(Z)Ljava/lang/Boolean;
     161: aload_0
     162: getfield      #8                  // Field queue:Lorg/apache/hadoop/hbase/master/procedure/MasterProcedureScheduler;
     165: aload_3
     166: aload_1
     167: invokevirtual #30                 // Method org/apache/hadoop/hbase/master/procedure/MasterProcedureScheduler.waitTableExclusiveLock:(Lorg/apache/hadoop/hbase/procedure2/Procedure;Lorg/apache/hadoop/hbase/TableName;)Z
     170: invokestatic  #38                 // Method java/lang/Boolean.valueOf:(Z)Ljava/lang/Boolean;
     173: invokestatic  #39                 // Method org/junit/Assert.assertEquals:(Ljava/lang/Object;Ljava/lang/Object;)V
     176: aload_0
     177: getfield      #8                  // Field queue:Lorg/apache/hadoop/hbase/master/procedure/MasterProcedureScheduler;
     180: new           #72                 // class org/apache/hadoop/hbase/master/procedure/TestMasterProcedureScheduler$TestRegionProcedure
     183: dup
     184: ldc2_w        #46                 // long 3l
     187: aload_1
     188: getstatic     #78                 // Field org/apache/hadoop/hbase/master/procedure/TableProcedureInterface$TableOperationType.REGION_UNASSIGN:Lorg/apache/hadoop/hbase/master/procedure/TableProcedureInterface$TableOperationType;
     191: iconst_1
     192: anewarray     #74                 // class org/apache/hadoop/hbase/client/RegionInfo
     195: dup
     196: iconst_0
     197: aload_2
     198: aastore
     199: invokespecial #75                 // Method org/apache/hadoop/hbase/master/procedure/TestMasterProcedureScheduler$TestRegionProcedure."<init>":(JLorg/apache/hadoop/hbase/TableName;Lorg/apache/hadoop/hbase/master/procedure/TableProcedureInterface$TableOperationType;[Lorg/apache/hadoop/hbase/client/RegionInfo;)V
     202: invokevirtual #23                 // Method org/apache/hadoop/hbase/master/procedure/MasterProcedureScheduler.addBack:(Lorg/apache/hadoop/hbase/procedure2/Procedure;)V
     205: aconst_null
     206: aload_0
     207: getfield      #8                  // Field queue:Lorg/apache/hadoop/hbase/master/procedure/MasterProcedureScheduler;
     210: lconst_0
     211: invokevirtual #48                 // Method org/apache/hadoop/hbase/master/procedure/MasterProcedureScheduler.poll:(J)Lorg/apache/hadoop/hbase/procedure2/Procedure;
     214: invokestatic  #39                 // Method org/junit/Assert.assertEquals:(Ljava/lang/Object;Ljava/lang/Object;)V
     217: aload_0
     218: getfield      #8                  // Field queue:Lorg/apache/hadoop/hbase/master/procedure/MasterProcedureScheduler;
     221: aload_3
     222: aload_1
     223: invokevirtual #31                 // Method org/apache/hadoop/hbase/master/procedure/MasterProcedureScheduler.wakeTableExclusiveLock:(Lorg/apache/hadoop/hbase/procedure2/Procedure;Lorg/apache/hadoop/hbase/TableName;)V
     226: aload_0
     227: getfield      #8                  // Field queue:Lorg/apache/hadoop/hbase/master/procedure/MasterProcedureScheduler;
     230: invokevirtual #27                 // Method org/apache/hadoop/hbase/master/procedure/MasterProcedureScheduler.poll:()Lorg/apache/hadoop/hbase/procedure2/Procedure;
     233: astore_3
     234: ldc2_w        #46                 // long 3l
     237: aload_3
     238: invokevirtual #33                 // Method org/apache/hadoop/hbase/procedure2/Procedure.getProcId:()J
     241: invokestatic  #24                 // Method org/junit/Assert.assertEquals:(JJ)V
     244: iconst_0
     245: invokestatic  #38                 // Method java/lang/Boolean.valueOf:(Z)Ljava/lang/Boolean;
     248: aload_0
     249: getfield      #8                  // Field queue:Lorg/apache/hadoop/hbase/master/procedure/MasterProcedureScheduler;
     252: aload_3
     253: aload_2
     254: invokevirtual #76                 // Method org/apache/hadoop/hbase/master/procedure/MasterProcedureScheduler.waitRegion:(Lorg/apache/hadoop/hbase/procedure2/Procedure;Lorg/apache/hadoop/hbase/client/RegionInfo;)Z
     257: invokestatic  #38                 // Method java/lang/Boolean.valueOf:(Z)Ljava/lang/Boolean;
     260: invokestatic  #39                 // Method org/junit/Assert.assertEquals:(Ljava/lang/Object;Ljava/lang/Object;)V
     263: aconst_null
     264: aload_0
     265: getfield      #8                  // Field queue:Lorg/apache/hadoop/hbase/master/procedure/MasterProcedureScheduler;
     268: lconst_0
     269: invokevirtual #48                 // Method org/apache/hadoop/hbase/master/procedure/MasterProcedureScheduler.poll:(J)Lorg/apache/hadoop/hbase/procedure2/Procedure;
     272: invokestatic  #39                 // Method org/junit/Assert.assertEquals:(Ljava/lang/Object;Ljava/lang/Object;)V
     275: aload_0
     276: getfield      #8                  // Field queue:Lorg/apache/hadoop/hbase/master/procedure/MasterProcedureScheduler;
     279: aload_3
     280: aload_2
     281: invokevirtual #77                 // Method org/apache/hadoop/hbase/master/procedure/MasterProcedureScheduler.wakeRegion:(Lorg/apache/hadoop/hbase/procedure2/Procedure;Lorg/apache/hadoop/hbase/client/RegionInfo;)V
     284: return

  public void testVerifyRegionLocks() throws java.lang.Exception;
    Code:
       0: aload_0
       1: getfield      #4                  // Field name:Lorg/junit/rules/TestName;
       4: invokevirtual #36                 // Method org/junit/rules/TestName.getMethodName:()Ljava/lang/String;
       7: invokestatic  #19                 // Method org/apache/hadoop/hbase/TableName.valueOf:(Ljava/lang/String;)Lorg/apache/hadoop/hbase/TableName;
      10: astore_1
      11: aload_1
      12: invokestatic  #65                 // Method org/apache/hadoop/hbase/client/RegionInfoBuilder.newBuilder:(Lorg/apache/hadoop/hbase/TableName;)Lorg/apache/hadoop/hbase/client/RegionInfoBuilder;
      15: ldc           #66                 // String a
      17: invokestatic  #67                 // Method org/apache/hadoop/hbase/util/Bytes.toBytes:(Ljava/lang/String;)[B
      20: invokevirtual #68                 // Method org/apache/hadoop/hbase/client/RegionInfoBuilder.setStartKey:([B)Lorg/apache/hadoop/hbase/client/RegionInfoBuilder;
      23: ldc           #69                 // String b
      25: invokestatic  #67                 // Method org/apache/hadoop/hbase/util/Bytes.toBytes:(Ljava/lang/String;)[B
      28: invokevirtual #70                 // Method org/apache/hadoop/hbase/client/RegionInfoBuilder.setEndKey:([B)Lorg/apache/hadoop/hbase/client/RegionInfoBuilder;
      31: invokevirtual #71                 // Method org/apache/hadoop/hbase/client/RegionInfoBuilder.build:()Lorg/apache/hadoop/hbase/client/RegionInfo;
      34: astore_2
      35: aload_1
      36: invokestatic  #65                 // Method org/apache/hadoop/hbase/client/RegionInfoBuilder.newBuilder:(Lorg/apache/hadoop/hbase/TableName;)Lorg/apache/hadoop/hbase/client/RegionInfoBuilder;
      39: ldc           #69                 // String b
      41: invokestatic  #67                 // Method org/apache/hadoop/hbase/util/Bytes.toBytes:(Ljava/lang/String;)[B
      44: invokevirtual #68                 // Method org/apache/hadoop/hbase/client/RegionInfoBuilder.setStartKey:([B)Lorg/apache/hadoop/hbase/client/RegionInfoBuilder;
      47: ldc           #79                 // String c
      49: invokestatic  #67                 // Method org/apache/hadoop/hbase/util/Bytes.toBytes:(Ljava/lang/String;)[B
      52: invokevirtual #70                 // Method org/apache/hadoop/hbase/client/RegionInfoBuilder.setEndKey:([B)Lorg/apache/hadoop/hbase/client/RegionInfoBuilder;
      55: invokevirtual #71                 // Method org/apache/hadoop/hbase/client/RegionInfoBuilder.build:()Lorg/apache/hadoop/hbase/client/RegionInfo;
      58: astore_3
      59: aload_1
      60: invokestatic  #65                 // Method org/apache/hadoop/hbase/client/RegionInfoBuilder.newBuilder:(Lorg/apache/hadoop/hbase/TableName;)Lorg/apache/hadoop/hbase/client/RegionInfoBuilder;
      63: ldc           #79                 // String c
      65: invokestatic  #67                 // Method org/apache/hadoop/hbase/util/Bytes.toBytes:(Ljava/lang/String;)[B
      68: invokevirtual #68                 // Method org/apache/hadoop/hbase/client/RegionInfoBuilder.setStartKey:([B)Lorg/apache/hadoop/hbase/client/RegionInfoBuilder;
      71: ldc           #80                 // String d
      73: invokestatic  #67                 // Method org/apache/hadoop/hbase/util/Bytes.toBytes:(Ljava/lang/String;)[B
      76: invokevirtual #70                 // Method org/apache/hadoop/hbase/client/RegionInfoBuilder.setEndKey:([B)Lorg/apache/hadoop/hbase/client/RegionInfoBuilder;
      79: invokevirtual #71                 // Method org/apache/hadoop/hbase/client/RegionInfoBuilder.build:()Lorg/apache/hadoop/hbase/client/RegionInfo;
      82: astore        4
      84: aload_0
      85: getfield      #8                  // Field queue:Lorg/apache/hadoop/hbase/master/procedure/MasterProcedureScheduler;
      88: new           #20                 // class org/apache/hadoop/hbase/master/procedure/TestMasterProcedureScheduler$TestTableProcedure
      91: dup
      92: lconst_1
      93: aload_1
      94: getstatic     #21                 // Field org/apache/hadoop/hbase/master/procedure/TableProcedureInterface$TableOperationType.EDIT:Lorg/apache/hadoop/hbase/master/procedure/TableProcedureInterface$TableOperationType;
      97: invokespecial #22                 // Method org/apache/hadoop/hbase/master/procedure/TestMasterProcedureScheduler$TestTableProcedure."<init>":(JLorg/apache/hadoop/hbase/TableName;Lorg/apache/hadoop/hbase/master/procedure/TableProcedureInterface$TableOperationType;)V
     100: invokevirtual #23                 // Method org/apache/hadoop/hbase/master/procedure/MasterProcedureScheduler.addBack:(Lorg/apache/hadoop/hbase/procedure2/Procedure;)V
     103: aload_0
     104: getfield      #8                  // Field queue:Lorg/apache/hadoop/hbase/master/procedure/MasterProcedureScheduler;
     107: new           #72                 // class org/apache/hadoop/hbase/master/procedure/TestMasterProcedureScheduler$TestRegionProcedure
     110: dup
     111: ldc2_w        #44                 // long 2l
     114: aload_1
     115: getstatic     #81                 // Field org/apache/hadoop/hbase/master/procedure/TableProcedureInterface$TableOperationType.REGION_MERGE:Lorg/apache/hadoop/hbase/master/procedure/TableProcedureInterface$TableOperationType;
     118: iconst_2
     119: anewarray     #74                 // class org/apache/hadoop/hbase/client/RegionInfo
     122: dup
     123: iconst_0
     124: aload_2
     125: aastore
     126: dup
     127: iconst_1
     128: aload_3
     129: aastore
     130: invokespecial #75                 // Method org/apache/hadoop/hbase/master/procedure/TestMasterProcedureScheduler$TestRegionProcedure."<init>":(JLorg/apache/hadoop/hbase/TableName;Lorg/apache/hadoop/hbase/master/procedure/TableProcedureInterface$TableOperationType;[Lorg/apache/hadoop/hbase/client/RegionInfo;)V
     133: invokevirtual #23                 // Method org/apache/hadoop/hbase/master/procedure/MasterProcedureScheduler.addBack:(Lorg/apache/hadoop/hbase/procedure2/Procedure;)V
     136: aload_0
     137: getfield      #8                  // Field queue:Lorg/apache/hadoop/hbase/master/procedure/MasterProcedureScheduler;
     140: new           #72                 // class org/apache/hadoop/hbase/master/procedure/TestMasterProcedureScheduler$TestRegionProcedure
     143: dup
     144: ldc2_w        #46                 // long 3l
     147: aload_1
     148: getstatic     #82                 // Field org/apache/hadoop/hbase/master/procedure/TableProcedureInterface$TableOperationType.REGION_SPLIT:Lorg/apache/hadoop/hbase/master/procedure/TableProcedureInterface$TableOperationType;
     151: iconst_1
     152: anewarray     #74                 // class org/apache/hadoop/hbase/client/RegionInfo
     155: dup
     156: iconst_0
     157: aload_2
     158: aastore
     159: invokespecial #75                 // Method org/apache/hadoop/hbase/master/procedure/TestMasterProcedureScheduler$TestRegionProcedure."<init>":(JLorg/apache/hadoop/hbase/TableName;Lorg/apache/hadoop/hbase/master/procedure/TableProcedureInterface$TableOperationType;[Lorg/apache/hadoop/hbase/client/RegionInfo;)V
     162: invokevirtual #23                 // Method org/apache/hadoop/hbase/master/procedure/MasterProcedureScheduler.addBack:(Lorg/apache/hadoop/hbase/procedure2/Procedure;)V
     165: aload_0
     166: getfield      #8                  // Field queue:Lorg/apache/hadoop/hbase/master/procedure/MasterProcedureScheduler;
     169: new           #72                 // class org/apache/hadoop/hbase/master/procedure/TestMasterProcedureScheduler$TestRegionProcedure
     172: dup
     173: ldc2_w        #49                 // long 4l
     176: aload_1
     177: getstatic     #82                 // Field org/apache/hadoop/hbase/master/procedure/TableProcedureInterface$TableOperationType.REGION_SPLIT:Lorg/apache/hadoop/hbase/master/procedure/TableProcedureInterface$TableOperationType;
     180: iconst_1
     181: anewarray     #74                 // class org/apache/hadoop/hbase/client/RegionInfo
     184: dup
     185: iconst_0
     186: aload_3
     187: aastore
     188: invokespecial #75                 // Method org/apache/hadoop/hbase/master/procedure/TestMasterProcedureScheduler$TestRegionProcedure."<init>":(JLorg/apache/hadoop/hbase/TableName;Lorg/apache/hadoop/hbase/master/procedure/TableProcedureInterface$TableOperationType;[Lorg/apache/hadoop/hbase/client/RegionInfo;)V
     191: invokevirtual #23                 // Method org/apache/hadoop/hbase/master/procedure/MasterProcedureScheduler.addBack:(Lorg/apache/hadoop/hbase/procedure2/Procedure;)V
     194: aload_0
     195: getfield      #8                  // Field queue:Lorg/apache/hadoop/hbase/master/procedure/MasterProcedureScheduler;
     198: new           #72                 // class org/apache/hadoop/hbase/master/procedure/TestMasterProcedureScheduler$TestRegionProcedure
     201: dup
     202: ldc2_w        #51                 // long 5l
     205: aload_1
     206: getstatic     #78                 // Field org/apache/hadoop/hbase/master/procedure/TableProcedureInterface$TableOperationType.REGION_UNASSIGN:Lorg/apache/hadoop/hbase/master/procedure/TableProcedureInterface$TableOperationType;
     209: iconst_1
     210: anewarray     #74                 // class org/apache/hadoop/hbase/client/RegionInfo
     213: dup
     214: iconst_0
     215: aload         4
     217: aastore
     218: invokespecial #75                 // Method org/apache/hadoop/hbase/master/procedure/TestMasterProcedureScheduler$TestRegionProcedure."<init>":(JLorg/apache/hadoop/hbase/TableName;Lorg/apache/hadoop/hbase/master/procedure/TableProcedureInterface$TableOperationType;[Lorg/apache/hadoop/hbase/client/RegionInfo;)V
     221: invokevirtual #23                 // Method org/apache/hadoop/hbase/master/procedure/MasterProcedureScheduler.addBack:(Lorg/apache/hadoop/hbase/procedure2/Procedure;)V
     224: aload_0
     225: getfield      #8                  // Field queue:Lorg/apache/hadoop/hbase/master/procedure/MasterProcedureScheduler;
     228: invokevirtual #27                 // Method org/apache/hadoop/hbase/master/procedure/MasterProcedureScheduler.poll:()Lorg/apache/hadoop/hbase/procedure2/Procedure;
     231: astore        5
     233: lconst_1
     234: aload         5
     236: invokevirtual #33                 // Method org/apache/hadoop/hbase/procedure2/Procedure.getProcId:()J
     239: invokestatic  #24                 // Method org/junit/Assert.assertEquals:(JJ)V
     242: iconst_0
     243: invokestatic  #38                 // Method java/lang/Boolean.valueOf:(Z)Ljava/lang/Boolean;
     246: aload_0
     247: getfield      #8                  // Field queue:Lorg/apache/hadoop/hbase/master/procedure/MasterProcedureScheduler;
     250: aload         5
     252: aload_1
     253: invokevirtual #30                 // Method org/apache/hadoop/hbase/master/procedure/MasterProcedureScheduler.waitTableExclusiveLock:(Lorg/apache/hadoop/hbase/procedure2/Procedure;Lorg/apache/hadoop/hbase/TableName;)Z
     256: invokestatic  #38                 // Method java/lang/Boolean.valueOf:(Z)Ljava/lang/Boolean;
     259: invokestatic  #39                 // Method org/junit/Assert.assertEquals:(Ljava/lang/Object;Ljava/lang/Object;)V
     262: aconst_null
     263: aload_0
     264: getfield      #8                  // Field queue:Lorg/apache/hadoop/hbase/master/procedure/MasterProcedureScheduler;
     267: lconst_0
     268: invokevirtual #48                 // Method org/apache/hadoop/hbase/master/procedure/MasterProcedureScheduler.poll:(J)Lorg/apache/hadoop/hbase/procedure2/Procedure;
     271: invokestatic  #39                 // Method org/junit/Assert.assertEquals:(Ljava/lang/Object;Ljava/lang/Object;)V
     274: aload_0
     275: getfield      #8                  // Field queue:Lorg/apache/hadoop/hbase/master/procedure/MasterProcedureScheduler;
     278: aload         5
     280: aload_1
     281: invokevirtual #31                 // Method org/apache/hadoop/hbase/master/procedure/MasterProcedureScheduler.wakeTableExclusiveLock:(Lorg/apache/hadoop/hbase/procedure2/Procedure;Lorg/apache/hadoop/hbase/TableName;)V
     284: aload_0
     285: getfield      #8                  // Field queue:Lorg/apache/hadoop/hbase/master/procedure/MasterProcedureScheduler;
     288: invokevirtual #27                 // Method org/apache/hadoop/hbase/master/procedure/MasterProcedureScheduler.poll:()Lorg/apache/hadoop/hbase/procedure2/Procedure;
     291: astore        6
     293: ldc2_w        #44                 // long 2l
     296: aload         6
     298: invokevirtual #33                 // Method org/apache/hadoop/hbase/procedure2/Procedure.getProcId:()J
     301: invokestatic  #24                 // Method org/junit/Assert.assertEquals:(JJ)V
     304: iconst_0
     305: invokestatic  #38                 // Method java/lang/Boolean.valueOf:(Z)Ljava/lang/Boolean;
     308: aload_0
     309: getfield      #8                  // Field queue:Lorg/apache/hadoop/hbase/master/procedure/MasterProcedureScheduler;
     312: aload         6
     314: aload_1
     315: iconst_2
     316: anewarray     #74                 // class org/apache/hadoop/hbase/client/RegionInfo
     319: dup
     320: iconst_0
     321: aload_2
     322: aastore
     323: dup
     324: iconst_1
     325: aload_3
     326: aastore
     327: invokevirtual #83                 // Method org/apache/hadoop/hbase/master/procedure/MasterProcedureScheduler.waitRegions:(Lorg/apache/hadoop/hbase/procedure2/Procedure;Lorg/apache/hadoop/hbase/TableName;[Lorg/apache/hadoop/hbase/client/RegionInfo;)Z
     330: invokestatic  #38                 // Method java/lang/Boolean.valueOf:(Z)Ljava/lang/Boolean;
     333: invokestatic  #39                 // Method org/junit/Assert.assertEquals:(Ljava/lang/Object;Ljava/lang/Object;)V
     336: aload_0
     337: getfield      #8                  // Field queue:Lorg/apache/hadoop/hbase/master/procedure/MasterProcedureScheduler;
     340: invokevirtual #27                 // Method org/apache/hadoop/hbase/master/procedure/MasterProcedureScheduler.poll:()Lorg/apache/hadoop/hbase/procedure2/Procedure;
     343: astore        7
     345: ldc2_w        #46                 // long 3l
     348: aload         7
     350: invokevirtual #33                 // Method org/apache/hadoop/hbase/procedure2/Procedure.getProcId:()J
     353: invokestatic  #24                 // Method org/junit/Assert.assertEquals:(JJ)V
     356: iconst_1
     357: invokestatic  #38                 // Method java/lang/Boolean.valueOf:(Z)Ljava/lang/Boolean;
     360: aload_0
     361: getfield      #8                  // Field queue:Lorg/apache/hadoop/hbase/master/procedure/MasterProcedureScheduler;
     364: aload         7
     366: aload_1
     367: iconst_1
     368: anewarray     #74                 // class org/apache/hadoop/hbase/client/RegionInfo
     371: dup
     372: iconst_0
     373: aload_2
     374: aastore
     375: invokevirtual #83                 // Method org/apache/hadoop/hbase/master/procedure/MasterProcedureScheduler.waitRegions:(Lorg/apache/hadoop/hbase/procedure2/Procedure;Lorg/apache/hadoop/hbase/TableName;[Lorg/apache/hadoop/hbase/client/RegionInfo;)Z
     378: invokestatic  #38                 // Method java/lang/Boolean.valueOf:(Z)Ljava/lang/Boolean;
     381: invokestatic  #39                 // Method org/junit/Assert.assertEquals:(Ljava/lang/Object;Ljava/lang/Object;)V
     384: aload_0
     385: getfield      #8                  // Field queue:Lorg/apache/hadoop/hbase/master/procedure/MasterProcedureScheduler;
     388: invokevirtual #27                 // Method org/apache/hadoop/hbase/master/procedure/MasterProcedureScheduler.poll:()Lorg/apache/hadoop/hbase/procedure2/Procedure;
     391: astore        8
     393: ldc2_w        #49                 // long 4l
     396: aload         8
     398: invokevirtual #33                 // Method org/apache/hadoop/hbase/procedure2/Procedure.getProcId:()J
     401: invokestatic  #24                 // Method org/junit/Assert.assertEquals:(JJ)V
     404: iconst_1
     405: invokestatic  #38                 // Method java/lang/Boolean.valueOf:(Z)Ljava/lang/Boolean;
     408: aload_0
     409: getfield      #8                  // Field queue:Lorg/apache/hadoop/hbase/master/procedure/MasterProcedureScheduler;
     412: aload         8
     414: aload_1
     415: iconst_1
     416: anewarray     #74                 // class org/apache/hadoop/hbase/client/RegionInfo
     419: dup
     420: iconst_0
     421: aload_3
     422: aastore
     423: invokevirtual #83                 // Method org/apache/hadoop/hbase/master/procedure/MasterProcedureScheduler.waitRegions:(Lorg/apache/hadoop/hbase/procedure2/Procedure;Lorg/apache/hadoop/hbase/TableName;[Lorg/apache/hadoop/hbase/client/RegionInfo;)Z
     426: invokestatic  #38                 // Method java/lang/Boolean.valueOf:(Z)Ljava/lang/Boolean;
     429: invokestatic  #39                 // Method org/junit/Assert.assertEquals:(Ljava/lang/Object;Ljava/lang/Object;)V
     432: aload_0
     433: getfield      #8                  // Field queue:Lorg/apache/hadoop/hbase/master/procedure/MasterProcedureScheduler;
     436: invokevirtual #27                 // Method org/apache/hadoop/hbase/master/procedure/MasterProcedureScheduler.poll:()Lorg/apache/hadoop/hbase/procedure2/Procedure;
     439: astore        9
     441: ldc2_w        #51                 // long 5l
     444: aload         9
     446: invokevirtual #33                 // Method org/apache/hadoop/hbase/procedure2/Procedure.getProcId:()J
     449: invokestatic  #24                 // Method org/junit/Assert.assertEquals:(JJ)V
     452: iconst_0
     453: invokestatic  #38                 // Method java/lang/Boolean.valueOf:(Z)Ljava/lang/Boolean;
     456: aload_0
     457: getfield      #8                  // Field queue:Lorg/apache/hadoop/hbase/master/procedure/MasterProcedureScheduler;
     460: aload         9
     462: aload_1
     463: iconst_1
     464: anewarray     #74                 // class org/apache/hadoop/hbase/client/RegionInfo
     467: dup
     468: iconst_0
     469: aload         4
     471: aastore
     472: invokevirtual #83                 // Method org/apache/hadoop/hbase/master/procedure/MasterProcedureScheduler.waitRegions:(Lorg/apache/hadoop/hbase/procedure2/Procedure;Lorg/apache/hadoop/hbase/TableName;[Lorg/apache/hadoop/hbase/client/RegionInfo;)Z
     475: invokestatic  #38                 // Method java/lang/Boolean.valueOf:(Z)Ljava/lang/Boolean;
     478: invokestatic  #39                 // Method org/junit/Assert.assertEquals:(Ljava/lang/Object;Ljava/lang/Object;)V
     481: aconst_null
     482: aload_0
     483: getfield      #8                  // Field queue:Lorg/apache/hadoop/hbase/master/procedure/MasterProcedureScheduler;
     486: lconst_0
     487: invokevirtual #48                 // Method org/apache/hadoop/hbase/master/procedure/MasterProcedureScheduler.poll:(J)Lorg/apache/hadoop/hbase/procedure2/Procedure;
     490: invokestatic  #39                 // Method org/junit/Assert.assertEquals:(Ljava/lang/Object;Ljava/lang/Object;)V
     493: aload_0
     494: getfield      #8                  // Field queue:Lorg/apache/hadoop/hbase/master/procedure/MasterProcedureScheduler;
     497: aload         6
     499: aload_1
     500: iconst_2
     501: anewarray     #74                 // class org/apache/hadoop/hbase/client/RegionInfo
     504: dup
     505: iconst_0
     506: aload_2
     507: aastore
     508: dup
     509: iconst_1
     510: aload_3
     511: aastore
     512: invokevirtual #84                 // Method org/apache/hadoop/hbase/master/procedure/MasterProcedureScheduler.wakeRegions:(Lorg/apache/hadoop/hbase/procedure2/Procedure;Lorg/apache/hadoop/hbase/TableName;[Lorg/apache/hadoop/hbase/client/RegionInfo;)V
     515: aload_0
     516: getfield      #8                  // Field queue:Lorg/apache/hadoop/hbase/master/procedure/MasterProcedureScheduler;
     519: invokevirtual #27                 // Method org/apache/hadoop/hbase/master/procedure/MasterProcedureScheduler.poll:()Lorg/apache/hadoop/hbase/procedure2/Procedure;
     522: astore        7
     524: ldc2_w        #46                 // long 3l
     527: aload         7
     529: invokevirtual #33                 // Method org/apache/hadoop/hbase/procedure2/Procedure.getProcId:()J
     532: invokestatic  #24                 // Method org/junit/Assert.assertEquals:(JJ)V
     535: iconst_0
     536: invokestatic  #38                 // Method java/lang/Boolean.valueOf:(Z)Ljava/lang/Boolean;
     539: aload_0
     540: getfield      #8                  // Field queue:Lorg/apache/hadoop/hbase/master/procedure/MasterProcedureScheduler;
     543: aload         7
     545: aload_1
     546: iconst_1
     547: anewarray     #74                 // class org/apache/hadoop/hbase/client/RegionInfo
     550: dup
     551: iconst_0
     552: aload_2
     553: aastore
     554: invokevirtual #83                 // Method org/apache/hadoop/hbase/master/procedure/MasterProcedureScheduler.waitRegions:(Lorg/apache/hadoop/hbase/procedure2/Procedure;Lorg/apache/hadoop/hbase/TableName;[Lorg/apache/hadoop/hbase/client/RegionInfo;)Z
     557: invokestatic  #38                 // Method java/lang/Boolean.valueOf:(Z)Ljava/lang/Boolean;
     560: invokestatic  #39                 // Method org/junit/Assert.assertEquals:(Ljava/lang/Object;Ljava/lang/Object;)V
     563: aload_0
     564: getfield      #8                  // Field queue:Lorg/apache/hadoop/hbase/master/procedure/MasterProcedureScheduler;
     567: invokevirtual #27                 // Method org/apache/hadoop/hbase/master/procedure/MasterProcedureScheduler.poll:()Lorg/apache/hadoop/hbase/procedure2/Procedure;
     570: astore        8
     572: ldc2_w        #49                 // long 4l
     575: aload         8
     577: invokevirtual #33                 // Method org/apache/hadoop/hbase/procedure2/Procedure.getProcId:()J
     580: invokestatic  #24                 // Method org/junit/Assert.assertEquals:(JJ)V
     583: iconst_0
     584: invokestatic  #38                 // Method java/lang/Boolean.valueOf:(Z)Ljava/lang/Boolean;
     587: aload_0
     588: getfield      #8                  // Field queue:Lorg/apache/hadoop/hbase/master/procedure/MasterProcedureScheduler;
     591: aload         8
     593: aload_1
     594: iconst_1
     595: anewarray     #74                 // class org/apache/hadoop/hbase/client/RegionInfo
     598: dup
     599: iconst_0
     600: aload_3
     601: aastore
     602: invokevirtual #83                 // Method org/apache/hadoop/hbase/master/procedure/MasterProcedureScheduler.waitRegions:(Lorg/apache/hadoop/hbase/procedure2/Procedure;Lorg/apache/hadoop/hbase/TableName;[Lorg/apache/hadoop/hbase/client/RegionInfo;)Z
     605: invokestatic  #38                 // Method java/lang/Boolean.valueOf:(Z)Ljava/lang/Boolean;
     608: invokestatic  #39                 // Method org/junit/Assert.assertEquals:(Ljava/lang/Object;Ljava/lang/Object;)V
     611: aload_0
     612: getfield      #8                  // Field queue:Lorg/apache/hadoop/hbase/master/procedure/MasterProcedureScheduler;
     615: aload         7
     617: aload_1
     618: iconst_1
     619: anewarray     #74                 // class org/apache/hadoop/hbase/client/RegionInfo
     622: dup
     623: iconst_0
     624: aload_2
     625: aastore
     626: invokevirtual #84                 // Method org/apache/hadoop/hbase/master/procedure/MasterProcedureScheduler.wakeRegions:(Lorg/apache/hadoop/hbase/procedure2/Procedure;Lorg/apache/hadoop/hbase/TableName;[Lorg/apache/hadoop/hbase/client/RegionInfo;)V
     629: aload_0
     630: getfield      #8                  // Field queue:Lorg/apache/hadoop/hbase/master/procedure/MasterProcedureScheduler;
     633: aload         8
     635: aload_1
     636: iconst_1
     637: anewarray     #74                 // class org/apache/hadoop/hbase/client/RegionInfo
     640: dup
     641: iconst_0
     642: aload_3
     643: aastore
     644: invokevirtual #84                 // Method org/apache/hadoop/hbase/master/procedure/MasterProcedureScheduler.wakeRegions:(Lorg/apache/hadoop/hbase/procedure2/Procedure;Lorg/apache/hadoop/hbase/TableName;[Lorg/apache/hadoop/hbase/client/RegionInfo;)V
     647: aload_0
     648: getfield      #8                  // Field queue:Lorg/apache/hadoop/hbase/master/procedure/MasterProcedureScheduler;
     651: aload         9
     653: aload_1
     654: iconst_1
     655: anewarray     #74                 // class org/apache/hadoop/hbase/client/RegionInfo
     658: dup
     659: iconst_0
     660: aload         4
     662: aastore
     663: invokevirtual #84                 // Method org/apache/hadoop/hbase/master/procedure/MasterProcedureScheduler.wakeRegions:(Lorg/apache/hadoop/hbase/procedure2/Procedure;Lorg/apache/hadoop/hbase/TableName;[Lorg/apache/hadoop/hbase/client/RegionInfo;)V
     666: return

  public void testVerifySubProcRegionLocks() throws java.lang.Exception;
    Code:
       0: aload_0
       1: getfield      #4                  // Field name:Lorg/junit/rules/TestName;
       4: invokevirtual #36                 // Method org/junit/rules/TestName.getMethodName:()Ljava/lang/String;
       7: invokestatic  #19                 // Method org/apache/hadoop/hbase/TableName.valueOf:(Ljava/lang/String;)Lorg/apache/hadoop/hbase/TableName;
      10: astore_1
      11: aload_1
      12: invokestatic  #65                 // Method org/apache/hadoop/hbase/client/RegionInfoBuilder.newBuilder:(Lorg/apache/hadoop/hbase/TableName;)Lorg/apache/hadoop/hbase/client/RegionInfoBuilder;
      15: ldc           #66                 // String a
      17: invokestatic  #67                 // Method org/apache/hadoop/hbase/util/Bytes.toBytes:(Ljava/lang/String;)[B
      20: invokevirtual #68                 // Method org/apache/hadoop/hbase/client/RegionInfoBuilder.setStartKey:([B)Lorg/apache/hadoop/hbase/client/RegionInfoBuilder;
      23: ldc           #69                 // String b
      25: invokestatic  #67                 // Method org/apache/hadoop/hbase/util/Bytes.toBytes:(Ljava/lang/String;)[B
      28: invokevirtual #70                 // Method org/apache/hadoop/hbase/client/RegionInfoBuilder.setEndKey:([B)Lorg/apache/hadoop/hbase/client/RegionInfoBuilder;
      31: invokevirtual #71                 // Method org/apache/hadoop/hbase/client/RegionInfoBuilder.build:()Lorg/apache/hadoop/hbase/client/RegionInfo;
      34: astore_2
      35: aload_1
      36: invokestatic  #65                 // Method org/apache/hadoop/hbase/client/RegionInfoBuilder.newBuilder:(Lorg/apache/hadoop/hbase/TableName;)Lorg/apache/hadoop/hbase/client/RegionInfoBuilder;
      39: ldc           #69                 // String b
      41: invokestatic  #67                 // Method org/apache/hadoop/hbase/util/Bytes.toBytes:(Ljava/lang/String;)[B
      44: invokevirtual #68                 // Method org/apache/hadoop/hbase/client/RegionInfoBuilder.setStartKey:([B)Lorg/apache/hadoop/hbase/client/RegionInfoBuilder;
      47: ldc           #79                 // String c
      49: invokestatic  #67                 // Method org/apache/hadoop/hbase/util/Bytes.toBytes:(Ljava/lang/String;)[B
      52: invokevirtual #70                 // Method org/apache/hadoop/hbase/client/RegionInfoBuilder.setEndKey:([B)Lorg/apache/hadoop/hbase/client/RegionInfoBuilder;
      55: invokevirtual #71                 // Method org/apache/hadoop/hbase/client/RegionInfoBuilder.build:()Lorg/apache/hadoop/hbase/client/RegionInfo;
      58: astore_3
      59: aload_1
      60: invokestatic  #65                 // Method org/apache/hadoop/hbase/client/RegionInfoBuilder.newBuilder:(Lorg/apache/hadoop/hbase/TableName;)Lorg/apache/hadoop/hbase/client/RegionInfoBuilder;
      63: ldc           #79                 // String c
      65: invokestatic  #67                 // Method org/apache/hadoop/hbase/util/Bytes.toBytes:(Ljava/lang/String;)[B
      68: invokevirtual #68                 // Method org/apache/hadoop/hbase/client/RegionInfoBuilder.setStartKey:([B)Lorg/apache/hadoop/hbase/client/RegionInfoBuilder;
      71: ldc           #80                 // String d
      73: invokestatic  #67                 // Method org/apache/hadoop/hbase/util/Bytes.toBytes:(Ljava/lang/String;)[B
      76: invokevirtual #70                 // Method org/apache/hadoop/hbase/client/RegionInfoBuilder.setEndKey:([B)Lorg/apache/hadoop/hbase/client/RegionInfoBuilder;
      79: invokevirtual #71                 // Method org/apache/hadoop/hbase/client/RegionInfoBuilder.build:()Lorg/apache/hadoop/hbase/client/RegionInfo;
      82: astore        4
      84: aload_0
      85: getfield      #8                  // Field queue:Lorg/apache/hadoop/hbase/master/procedure/MasterProcedureScheduler;
      88: new           #20                 // class org/apache/hadoop/hbase/master/procedure/TestMasterProcedureScheduler$TestTableProcedure
      91: dup
      92: lconst_1
      93: aload_1
      94: getstatic     #85                 // Field org/apache/hadoop/hbase/master/procedure/TableProcedureInterface$TableOperationType.ENABLE:Lorg/apache/hadoop/hbase/master/procedure/TableProcedureInterface$TableOperationType;
      97: invokespecial #22                 // Method org/apache/hadoop/hbase/master/procedure/TestMasterProcedureScheduler$TestTableProcedure."<init>":(JLorg/apache/hadoop/hbase/TableName;Lorg/apache/hadoop/hbase/master/procedure/TableProcedureInterface$TableOperationType;)V
     100: invokevirtual #23                 // Method org/apache/hadoop/hbase/master/procedure/MasterProcedureScheduler.addBack:(Lorg/apache/hadoop/hbase/procedure2/Procedure;)V
     103: aload_0
     104: getfield      #8                  // Field queue:Lorg/apache/hadoop/hbase/master/procedure/MasterProcedureScheduler;
     107: invokevirtual #27                 // Method org/apache/hadoop/hbase/master/procedure/MasterProcedureScheduler.poll:()Lorg/apache/hadoop/hbase/procedure2/Procedure;
     110: astore        5
     112: lconst_1
     113: aload         5
     115: invokevirtual #33                 // Method org/apache/hadoop/hbase/procedure2/Procedure.getProcId:()J
     118: invokestatic  #24                 // Method org/junit/Assert.assertEquals:(JJ)V
     121: iconst_0
     122: invokestatic  #38                 // Method java/lang/Boolean.valueOf:(Z)Ljava/lang/Boolean;
     125: aload_0
     126: getfield      #8                  // Field queue:Lorg/apache/hadoop/hbase/master/procedure/MasterProcedureScheduler;
     129: aload         5
     131: aload_1
     132: invokevirtual #30                 // Method org/apache/hadoop/hbase/master/procedure/MasterProcedureScheduler.waitTableExclusiveLock:(Lorg/apache/hadoop/hbase/procedure2/Procedure;Lorg/apache/hadoop/hbase/TableName;)Z
     135: invokestatic  #38                 // Method java/lang/Boolean.valueOf:(Z)Ljava/lang/Boolean;
     138: invokestatic  #39                 // Method org/junit/Assert.assertEquals:(Ljava/lang/Object;Ljava/lang/Object;)V
     141: aconst_null
     142: aload_0
     143: getfield      #8                  // Field queue:Lorg/apache/hadoop/hbase/master/procedure/MasterProcedureScheduler;
     146: lconst_0
     147: invokevirtual #48                 // Method org/apache/hadoop/hbase/master/procedure/MasterProcedureScheduler.poll:(J)Lorg/apache/hadoop/hbase/procedure2/Procedure;
     150: invokestatic  #39                 // Method org/junit/Assert.assertEquals:(Ljava/lang/Object;Ljava/lang/Object;)V
     153: iconst_3
     154: anewarray     #41                 // class org/apache/hadoop/hbase/procedure2/Procedure
     157: dup
     158: iconst_0
     159: new           #72                 // class org/apache/hadoop/hbase/master/procedure/TestMasterProcedureScheduler$TestRegionProcedure
     162: dup
     163: lconst_1
     164: ldc2_w        #44                 // long 2l
     167: aload_1
     168: getstatic     #86                 // Field org/apache/hadoop/hbase/master/procedure/TableProcedureInterface$TableOperationType.REGION_EDIT:Lorg/apache/hadoop/hbase/master/procedure/TableProcedureInterface$TableOperationType;
     171: iconst_1
     172: anewarray     #74                 // class org/apache/hadoop/hbase/client/RegionInfo
     175: dup
     176: iconst_0
     177: aload_2
     178: aastore
     179: invokespecial #87                 // Method org/apache/hadoop/hbase/master/procedure/TestMasterProcedureScheduler$TestRegionProcedure."<init>":(JJLorg/apache/hadoop/hbase/TableName;Lorg/apache/hadoop/hbase/master/procedure/TableProcedureInterface$TableOperationType;[Lorg/apache/hadoop/hbase/client/RegionInfo;)V
     182: aastore
     183: dup
     184: iconst_1
     185: new           #72                 // class org/apache/hadoop/hbase/master/procedure/TestMasterProcedureScheduler$TestRegionProcedure
     188: dup
     189: lconst_1
     190: ldc2_w        #46                 // long 3l
     193: aload_1
     194: getstatic     #86                 // Field org/apache/hadoop/hbase/master/procedure/TableProcedureInterface$TableOperationType.REGION_EDIT:Lorg/apache/hadoop/hbase/master/procedure/TableProcedureInterface$TableOperationType;
     197: iconst_1
     198: anewarray     #74                 // class org/apache/hadoop/hbase/client/RegionInfo
     201: dup
     202: iconst_0
     203: aload_3
     204: aastore
     205: invokespecial #87                 // Method org/apache/hadoop/hbase/master/procedure/TestMasterProcedureScheduler$TestRegionProcedure."<init>":(JJLorg/apache/hadoop/hbase/TableName;Lorg/apache/hadoop/hbase/master/procedure/TableProcedureInterface$TableOperationType;[Lorg/apache/hadoop/hbase/client/RegionInfo;)V
     208: aastore
     209: dup
     210: iconst_2
     211: new           #72                 // class org/apache/hadoop/hbase/master/procedure/TestMasterProcedureScheduler$TestRegionProcedure
     214: dup
     215: lconst_1
     216: ldc2_w        #49                 // long 4l
     219: aload_1
     220: getstatic     #86                 // Field org/apache/hadoop/hbase/master/procedure/TableProcedureInterface$TableOperationType.REGION_EDIT:Lorg/apache/hadoop/hbase/master/procedure/TableProcedureInterface$TableOperationType;
     223: iconst_1
     224: anewarray     #74                 // class org/apache/hadoop/hbase/client/RegionInfo
     227: dup
     228: iconst_0
     229: aload         4
     231: aastore
     232: invokespecial #87                 // Method org/apache/hadoop/hbase/master/procedure/TestMasterProcedureScheduler$TestRegionProcedure."<init>":(JJLorg/apache/hadoop/hbase/TableName;Lorg/apache/hadoop/hbase/master/procedure/TableProcedureInterface$TableOperationType;[Lorg/apache/hadoop/hbase/client/RegionInfo;)V
     235: aastore
     236: astore        6
     238: aload         6
     240: arraylength
     241: iconst_1
     242: isub
     243: istore        7
     245: iload         7
     247: iflt          268
     250: aload_0
     251: getfield      #8                  // Field queue:Lorg/apache/hadoop/hbase/master/procedure/MasterProcedureScheduler;
     254: aload         6
     256: iload         7
     258: aaload
     259: invokevirtual #88                 // Method org/apache/hadoop/hbase/master/procedure/MasterProcedureScheduler.addFront:(Lorg/apache/hadoop/hbase/procedure2/Procedure;)V
     262: iinc          7, -1
     265: goto          245
     268: aload         6
     270: arraylength
     271: i2l
     272: aload_0
     273: getfield      #8                  // Field queue:Lorg/apache/hadoop/hbase/master/procedure/MasterProcedureScheduler;
     276: invokevirtual #11                 // Method org/apache/hadoop/hbase/master/procedure/MasterProcedureScheduler.size:()I
     279: i2l
     280: invokestatic  #24                 // Method org/junit/Assert.assertEquals:(JJ)V
     283: iconst_0
     284: istore        7
     286: iload         7
     288: aload         6
     290: arraylength
     291: if_icmpge     354
     294: aload_0
     295: getfield      #8                  // Field queue:Lorg/apache/hadoop/hbase/master/procedure/MasterProcedureScheduler;
     298: lconst_0
     299: invokevirtual #48                 // Method org/apache/hadoop/hbase/master/procedure/MasterProcedureScheduler.poll:(J)Lorg/apache/hadoop/hbase/procedure2/Procedure;
     302: checkcast     #72                 // class org/apache/hadoop/hbase/master/procedure/TestMasterProcedureScheduler$TestRegionProcedure
     305: astore        8
     307: aload         6
     309: iload         7
     311: aaload
     312: invokevirtual #33                 // Method org/apache/hadoop/hbase/procedure2/Procedure.getProcId:()J
     315: aload         8
     317: invokevirtual #89                 // Method org/apache/hadoop/hbase/master/procedure/TestMasterProcedureScheduler$TestRegionProcedure.getProcId:()J
     320: invokestatic  #24                 // Method org/junit/Assert.assertEquals:(JJ)V
     323: iconst_0
     324: invokestatic  #38                 // Method java/lang/Boolean.valueOf:(Z)Ljava/lang/Boolean;
     327: aload_0
     328: getfield      #8                  // Field queue:Lorg/apache/hadoop/hbase/master/procedure/MasterProcedureScheduler;
     331: aload         8
     333: aload_1
     334: aload         8
     336: invokevirtual #90                 // Method org/apache/hadoop/hbase/master/procedure/TestMasterProcedureScheduler$TestRegionProcedure.getRegionInfo:()[Lorg/apache/hadoop/hbase/client/RegionInfo;
     339: invokevirtual #83                 // Method org/apache/hadoop/hbase/master/procedure/MasterProcedureScheduler.waitRegions:(Lorg/apache/hadoop/hbase/procedure2/Procedure;Lorg/apache/hadoop/hbase/TableName;[Lorg/apache/hadoop/hbase/client/RegionInfo;)Z
     342: invokestatic  #38                 // Method java/lang/Boolean.valueOf:(Z)Ljava/lang/Boolean;
     345: invokestatic  #39                 // Method org/junit/Assert.assertEquals:(Ljava/lang/Object;Ljava/lang/Object;)V
     348: iinc          7, 1
     351: goto          286
     354: aconst_null
     355: aload_0
     356: getfield      #8                  // Field queue:Lorg/apache/hadoop/hbase/master/procedure/MasterProcedureScheduler;
     359: lconst_0
     360: invokevirtual #48                 // Method org/apache/hadoop/hbase/master/procedure/MasterProcedureScheduler.poll:(J)Lorg/apache/hadoop/hbase/procedure2/Procedure;
     363: invokestatic  #39                 // Method org/junit/Assert.assertEquals:(Ljava/lang/Object;Ljava/lang/Object;)V
     366: iconst_0
     367: istore        7
     369: iload         7
     371: aload         6
     373: arraylength
     374: if_icmpge     408
     377: aload         6
     379: iload         7
     381: aaload
     382: checkcast     #72                 // class org/apache/hadoop/hbase/master/procedure/TestMasterProcedureScheduler$TestRegionProcedure
     385: astore        8
     387: aload_0
     388: getfield      #8                  // Field queue:Lorg/apache/hadoop/hbase/master/procedure/MasterProcedureScheduler;
     391: aload         8
     393: aload_1
     394: aload         8
     396: invokevirtual #90                 // Method org/apache/hadoop/hbase/master/procedure/TestMasterProcedureScheduler$TestRegionProcedure.getRegionInfo:()[Lorg/apache/hadoop/hbase/client/RegionInfo;
     399: invokevirtual #84                 // Method org/apache/hadoop/hbase/master/procedure/MasterProcedureScheduler.wakeRegions:(Lorg/apache/hadoop/hbase/procedure2/Procedure;Lorg/apache/hadoop/hbase/TableName;[Lorg/apache/hadoop/hbase/client/RegionInfo;)V
     402: iinc          7, 1
     405: goto          369
     408: aconst_null
     409: aload_0
     410: getfield      #8                  // Field queue:Lorg/apache/hadoop/hbase/master/procedure/MasterProcedureScheduler;
     413: lconst_0
     414: invokevirtual #48                 // Method org/apache/hadoop/hbase/master/procedure/MasterProcedureScheduler.poll:(J)Lorg/apache/hadoop/hbase/procedure2/Procedure;
     417: invokestatic  #39                 // Method org/junit/Assert.assertEquals:(Ljava/lang/Object;Ljava/lang/Object;)V
     420: aload_0
     421: getfield      #8                  // Field queue:Lorg/apache/hadoop/hbase/master/procedure/MasterProcedureScheduler;
     424: aload         5
     426: aload_1
     427: invokevirtual #31                 // Method org/apache/hadoop/hbase/master/procedure/MasterProcedureScheduler.wakeTableExclusiveLock:(Lorg/apache/hadoop/hbase/procedure2/Procedure;Lorg/apache/hadoop/hbase/TableName;)V
     430: return

  public void testInheritedRegionXLock();
    Code:
       0: aload_0
       1: getfield      #4                  // Field name:Lorg/junit/rules/TestName;
       4: invokevirtual #36                 // Method org/junit/rules/TestName.getMethodName:()Ljava/lang/String;
       7: invokestatic  #19                 // Method org/apache/hadoop/hbase/TableName.valueOf:(Ljava/lang/String;)Lorg/apache/hadoop/hbase/TableName;
      10: astore_1
      11: aload_1
      12: invokestatic  #65                 // Method org/apache/hadoop/hbase/client/RegionInfoBuilder.newBuilder:(Lorg/apache/hadoop/hbase/TableName;)Lorg/apache/hadoop/hbase/client/RegionInfoBuilder;
      15: ldc           #66                 // String a
      17: invokestatic  #67                 // Method org/apache/hadoop/hbase/util/Bytes.toBytes:(Ljava/lang/String;)[B
      20: invokevirtual #68                 // Method org/apache/hadoop/hbase/client/RegionInfoBuilder.setStartKey:([B)Lorg/apache/hadoop/hbase/client/RegionInfoBuilder;
      23: ldc           #69                 // String b
      25: invokestatic  #67                 // Method org/apache/hadoop/hbase/util/Bytes.toBytes:(Ljava/lang/String;)[B
      28: invokevirtual #70                 // Method org/apache/hadoop/hbase/client/RegionInfoBuilder.setEndKey:([B)Lorg/apache/hadoop/hbase/client/RegionInfoBuilder;
      31: invokevirtual #71                 // Method org/apache/hadoop/hbase/client/RegionInfoBuilder.build:()Lorg/apache/hadoop/hbase/client/RegionInfo;
      34: astore_2
      35: aload_0
      36: getfield      #8                  // Field queue:Lorg/apache/hadoop/hbase/master/procedure/MasterProcedureScheduler;
      39: new           #72                 // class org/apache/hadoop/hbase/master/procedure/TestMasterProcedureScheduler$TestRegionProcedure
      42: dup
      43: lconst_1
      44: aload_1
      45: getstatic     #82                 // Field org/apache/hadoop/hbase/master/procedure/TableProcedureInterface$TableOperationType.REGION_SPLIT:Lorg/apache/hadoop/hbase/master/procedure/TableProcedureInterface$TableOperationType;
      48: iconst_1
      49: anewarray     #74                 // class org/apache/hadoop/hbase/client/RegionInfo
      52: dup
      53: iconst_0
      54: aload_2
      55: aastore
      56: invokespecial #75                 // Method org/apache/hadoop/hbase/master/procedure/TestMasterProcedureScheduler$TestRegionProcedure."<init>":(JLorg/apache/hadoop/hbase/TableName;Lorg/apache/hadoop/hbase/master/procedure/TableProcedureInterface$TableOperationType;[Lorg/apache/hadoop/hbase/client/RegionInfo;)V
      59: invokevirtual #23                 // Method org/apache/hadoop/hbase/master/procedure/MasterProcedureScheduler.addBack:(Lorg/apache/hadoop/hbase/procedure2/Procedure;)V
      62: aload_0
      63: getfield      #8                  // Field queue:Lorg/apache/hadoop/hbase/master/procedure/MasterProcedureScheduler;
      66: new           #72                 // class org/apache/hadoop/hbase/master/procedure/TestMasterProcedureScheduler$TestRegionProcedure
      69: dup
      70: lconst_1
      71: ldc2_w        #44                 // long 2l
      74: aload_1
      75: getstatic     #78                 // Field org/apache/hadoop/hbase/master/procedure/TableProcedureInterface$TableOperationType.REGION_UNASSIGN:Lorg/apache/hadoop/hbase/master/procedure/TableProcedureInterface$TableOperationType;
      78: iconst_1
      79: anewarray     #74                 // class org/apache/hadoop/hbase/client/RegionInfo
      82: dup
      83: iconst_0
      84: aload_2
      85: aastore
      86: invokespecial #87                 // Method org/apache/hadoop/hbase/master/procedure/TestMasterProcedureScheduler$TestRegionProcedure."<init>":(JJLorg/apache/hadoop/hbase/TableName;Lorg/apache/hadoop/hbase/master/procedure/TableProcedureInterface$TableOperationType;[Lorg/apache/hadoop/hbase/client/RegionInfo;)V
      89: invokevirtual #23                 // Method org/apache/hadoop/hbase/master/procedure/MasterProcedureScheduler.addBack:(Lorg/apache/hadoop/hbase/procedure2/Procedure;)V
      92: aload_0
      93: getfield      #8                  // Field queue:Lorg/apache/hadoop/hbase/master/procedure/MasterProcedureScheduler;
      96: new           #72                 // class org/apache/hadoop/hbase/master/procedure/TestMasterProcedureScheduler$TestRegionProcedure
      99: dup
     100: ldc2_w        #46                 // long 3l
     103: aload_1
     104: getstatic     #86                 // Field org/apache/hadoop/hbase/master/procedure/TableProcedureInterface$TableOperationType.REGION_EDIT:Lorg/apache/hadoop/hbase/master/procedure/TableProcedureInterface$TableOperationType;
     107: iconst_1
     108: anewarray     #74                 // class org/apache/hadoop/hbase/client/RegionInfo
     111: dup
     112: iconst_0
     113: aload_2
     114: aastore
     115: invokespecial #75                 // Method org/apache/hadoop/hbase/master/procedure/TestMasterProcedureScheduler$TestRegionProcedure."<init>":(JLorg/apache/hadoop/hbase/TableName;Lorg/apache/hadoop/hbase/master/procedure/TableProcedureInterface$TableOperationType;[Lorg/apache/hadoop/hbase/client/RegionInfo;)V
     118: invokevirtual #23                 // Method org/apache/hadoop/hbase/master/procedure/MasterProcedureScheduler.addBack:(Lorg/apache/hadoop/hbase/procedure2/Procedure;)V
     121: aload_0
     122: getfield      #8                  // Field queue:Lorg/apache/hadoop/hbase/master/procedure/MasterProcedureScheduler;
     125: invokevirtual #27                 // Method org/apache/hadoop/hbase/master/procedure/MasterProcedureScheduler.poll:()Lorg/apache/hadoop/hbase/procedure2/Procedure;
     128: astore_3
     129: lconst_1
     130: aload_3
     131: invokevirtual #33                 // Method org/apache/hadoop/hbase/procedure2/Procedure.getProcId:()J
     134: invokestatic  #24                 // Method org/junit/Assert.assertEquals:(JJ)V
     137: iconst_0
     138: invokestatic  #38                 // Method java/lang/Boolean.valueOf:(Z)Ljava/lang/Boolean;
     141: aload_0
     142: getfield      #8                  // Field queue:Lorg/apache/hadoop/hbase/master/procedure/MasterProcedureScheduler;
     145: aload_3
     146: aload_2
     147: invokevirtual #76                 // Method org/apache/hadoop/hbase/master/procedure/MasterProcedureScheduler.waitRegion:(Lorg/apache/hadoop/hbase/procedure2/Procedure;Lorg/apache/hadoop/hbase/client/RegionInfo;)Z
     150: invokestatic  #38                 // Method java/lang/Boolean.valueOf:(Z)Ljava/lang/Boolean;
     153: invokestatic  #39                 // Method org/junit/Assert.assertEquals:(Ljava/lang/Object;Ljava/lang/Object;)V
     156: aload_0
     157: getfield      #8                  // Field queue:Lorg/apache/hadoop/hbase/master/procedure/MasterProcedureScheduler;
     160: invokevirtual #27                 // Method org/apache/hadoop/hbase/master/procedure/MasterProcedureScheduler.poll:()Lorg/apache/hadoop/hbase/procedure2/Procedure;
     163: astore        4
     165: ldc2_w        #44                 // long 2l
     168: aload         4
     170: invokevirtual #33                 // Method org/apache/hadoop/hbase/procedure2/Procedure.getProcId:()J
     173: invokestatic  #24                 // Method org/junit/Assert.assertEquals:(JJ)V
     176: iconst_0
     177: invokestatic  #38                 // Method java/lang/Boolean.valueOf:(Z)Ljava/lang/Boolean;
     180: aload_0
     181: getfield      #8                  // Field queue:Lorg/apache/hadoop/hbase/master/procedure/MasterProcedureScheduler;
     184: aload         4
     186: aload_2
     187: invokevirtual #76                 // Method org/apache/hadoop/hbase/master/procedure/MasterProcedureScheduler.waitRegion:(Lorg/apache/hadoop/hbase/procedure2/Procedure;Lorg/apache/hadoop/hbase/client/RegionInfo;)Z
     190: invokestatic  #38                 // Method java/lang/Boolean.valueOf:(Z)Ljava/lang/Boolean;
     193: invokestatic  #39                 // Method org/junit/Assert.assertEquals:(Ljava/lang/Object;Ljava/lang/Object;)V
     196: aload_0
     197: getfield      #8                  // Field queue:Lorg/apache/hadoop/hbase/master/procedure/MasterProcedureScheduler;
     200: invokevirtual #27                 // Method org/apache/hadoop/hbase/master/procedure/MasterProcedureScheduler.poll:()Lorg/apache/hadoop/hbase/procedure2/Procedure;
     203: astore        5
     205: ldc2_w        #46                 // long 3l
     208: aload         5
     210: invokevirtual #33                 // Method org/apache/hadoop/hbase/procedure2/Procedure.getProcId:()J
     213: invokestatic  #24                 // Method org/junit/Assert.assertEquals:(JJ)V
     216: iconst_1
     217: invokestatic  #38                 // Method java/lang/Boolean.valueOf:(Z)Ljava/lang/Boolean;
     220: aload_0
     221: getfield      #8                  // Field queue:Lorg/apache/hadoop/hbase/master/procedure/MasterProcedureScheduler;
     224: aload         5
     226: aload_2
     227: invokevirtual #76                 // Method org/apache/hadoop/hbase/master/procedure/MasterProcedureScheduler.waitRegion:(Lorg/apache/hadoop/hbase/procedure2/Procedure;Lorg/apache/hadoop/hbase/client/RegionInfo;)Z
     230: invokestatic  #38                 // Method java/lang/Boolean.valueOf:(Z)Ljava/lang/Boolean;
     233: invokestatic  #39                 // Method org/junit/Assert.assertEquals:(Ljava/lang/Object;Ljava/lang/Object;)V
     236: aload_0
     237: getfield      #8                  // Field queue:Lorg/apache/hadoop/hbase/master/procedure/MasterProcedureScheduler;
     240: aload         4
     242: aload_2
     243: invokevirtual #77                 // Method org/apache/hadoop/hbase/master/procedure/MasterProcedureScheduler.wakeRegion:(Lorg/apache/hadoop/hbase/procedure2/Procedure;Lorg/apache/hadoop/hbase/client/RegionInfo;)V
     246: aconst_null
     247: aload_0
     248: getfield      #8                  // Field queue:Lorg/apache/hadoop/hbase/master/procedure/MasterProcedureScheduler;
     251: lconst_0
     252: invokevirtual #48                 // Method org/apache/hadoop/hbase/master/procedure/MasterProcedureScheduler.poll:(J)Lorg/apache/hadoop/hbase/procedure2/Procedure;
     255: invokestatic  #39                 // Method org/junit/Assert.assertEquals:(Ljava/lang/Object;Ljava/lang/Object;)V
     258: aload_0
     259: getfield      #8                  // Field queue:Lorg/apache/hadoop/hbase/master/procedure/MasterProcedureScheduler;
     262: aload_3
     263: aload_2
     264: invokevirtual #77                 // Method org/apache/hadoop/hbase/master/procedure/MasterProcedureScheduler.wakeRegion:(Lorg/apache/hadoop/hbase/procedure2/Procedure;Lorg/apache/hadoop/hbase/client/RegionInfo;)V
     267: aload_0
     268: getfield      #8                  // Field queue:Lorg/apache/hadoop/hbase/master/procedure/MasterProcedureScheduler;
     271: invokevirtual #27                 // Method org/apache/hadoop/hbase/master/procedure/MasterProcedureScheduler.poll:()Lorg/apache/hadoop/hbase/procedure2/Procedure;
     274: astore        5
     276: ldc2_w        #46                 // long 3l
     279: aload         5
     281: invokevirtual #33                 // Method org/apache/hadoop/hbase/procedure2/Procedure.getProcId:()J
     284: invokestatic  #24                 // Method org/junit/Assert.assertEquals:(JJ)V
     287: iconst_0
     288: invokestatic  #38                 // Method java/lang/Boolean.valueOf:(Z)Ljava/lang/Boolean;
     291: aload_0
     292: getfield      #8                  // Field queue:Lorg/apache/hadoop/hbase/master/procedure/MasterProcedureScheduler;
     295: aload         5
     297: aload_2
     298: invokevirtual #76                 // Method org/apache/hadoop/hbase/master/procedure/MasterProcedureScheduler.waitRegion:(Lorg/apache/hadoop/hbase/procedure2/Procedure;Lorg/apache/hadoop/hbase/client/RegionInfo;)Z
     301: invokestatic  #38                 // Method java/lang/Boolean.valueOf:(Z)Ljava/lang/Boolean;
     304: invokestatic  #39                 // Method org/junit/Assert.assertEquals:(Ljava/lang/Object;Ljava/lang/Object;)V
     307: aload_0
     308: getfield      #8                  // Field queue:Lorg/apache/hadoop/hbase/master/procedure/MasterProcedureScheduler;
     311: aload         5
     313: aload_2
     314: invokevirtual #77                 // Method org/apache/hadoop/hbase/master/procedure/MasterProcedureScheduler.wakeRegion:(Lorg/apache/hadoop/hbase/procedure2/Procedure;Lorg/apache/hadoop/hbase/client/RegionInfo;)V
     317: return

  public void testSuspendedProcedure() throws java.lang.Exception;
    Code:
       0: aload_0
       1: getfield      #4                  // Field name:Lorg/junit/rules/TestName;
       4: invokevirtual #36                 // Method org/junit/rules/TestName.getMethodName:()Ljava/lang/String;
       7: invokestatic  #19                 // Method org/apache/hadoop/hbase/TableName.valueOf:(Ljava/lang/String;)Lorg/apache/hadoop/hbase/TableName;
      10: astore_1
      11: aload_0
      12: getfield      #8                  // Field queue:Lorg/apache/hadoop/hbase/master/procedure/MasterProcedureScheduler;
      15: new           #20                 // class org/apache/hadoop/hbase/master/procedure/TestMasterProcedureScheduler$TestTableProcedure
      18: dup
      19: lconst_1
      20: aload_1
      21: getstatic     #40                 // Field org/apache/hadoop/hbase/master/procedure/TableProcedureInterface$TableOperationType.READ:Lorg/apache/hadoop/hbase/master/procedure/TableProcedureInterface$TableOperationType;
      24: invokespecial #22                 // Method org/apache/hadoop/hbase/master/procedure/TestMasterProcedureScheduler$TestTableProcedure."<init>":(JLorg/apache/hadoop/hbase/TableName;Lorg/apache/hadoop/hbase/master/procedure/TableProcedureInterface$TableOperationType;)V
      27: invokevirtual #23                 // Method org/apache/hadoop/hbase/master/procedure/MasterProcedureScheduler.addBack:(Lorg/apache/hadoop/hbase/procedure2/Procedure;)V
      30: aload_0
      31: getfield      #8                  // Field queue:Lorg/apache/hadoop/hbase/master/procedure/MasterProcedureScheduler;
      34: new           #20                 // class org/apache/hadoop/hbase/master/procedure/TestMasterProcedureScheduler$TestTableProcedure
      37: dup
      38: ldc2_w        #44                 // long 2l
      41: aload_1
      42: getstatic     #40                 // Field org/apache/hadoop/hbase/master/procedure/TableProcedureInterface$TableOperationType.READ:Lorg/apache/hadoop/hbase/master/procedure/TableProcedureInterface$TableOperationType;
      45: invokespecial #22                 // Method org/apache/hadoop/hbase/master/procedure/TestMasterProcedureScheduler$TestTableProcedure."<init>":(JLorg/apache/hadoop/hbase/TableName;Lorg/apache/hadoop/hbase/master/procedure/TableProcedureInterface$TableOperationType;)V
      48: invokevirtual #23                 // Method org/apache/hadoop/hbase/master/procedure/MasterProcedureScheduler.addBack:(Lorg/apache/hadoop/hbase/procedure2/Procedure;)V
      51: aload_0
      52: getfield      #8                  // Field queue:Lorg/apache/hadoop/hbase/master/procedure/MasterProcedureScheduler;
      55: invokevirtual #27                 // Method org/apache/hadoop/hbase/master/procedure/MasterProcedureScheduler.poll:()Lorg/apache/hadoop/hbase/procedure2/Procedure;
      58: astore_2
      59: lconst_1
      60: aload_2
      61: invokevirtual #33                 // Method org/apache/hadoop/hbase/procedure2/Procedure.getProcId:()J
      64: invokestatic  #24                 // Method org/junit/Assert.assertEquals:(JJ)V
      67: new           #91                 // class org/apache/hadoop/hbase/procedure2/ProcedureEvent
      70: dup
      71: ldc           #92                 // String testSuspendedProcedureEvent
      73: invokespecial #93                 // Method org/apache/hadoop/hbase/procedure2/ProcedureEvent."<init>":(Ljava/lang/Object;)V
      76: astore_3
      77: iconst_1
      78: invokestatic  #38                 // Method java/lang/Boolean.valueOf:(Z)Ljava/lang/Boolean;
      81: aload_3
      82: aload_2
      83: invokevirtual #94                 // Method org/apache/hadoop/hbase/procedure2/ProcedureEvent.suspendIfNotReady:(Lorg/apache/hadoop/hbase/procedure2/Procedure;)Z
      86: invokestatic  #38                 // Method java/lang/Boolean.valueOf:(Z)Ljava/lang/Boolean;
      89: invokestatic  #39                 // Method org/junit/Assert.assertEquals:(Ljava/lang/Object;Ljava/lang/Object;)V
      92: aload_0
      93: getfield      #8                  // Field queue:Lorg/apache/hadoop/hbase/master/procedure/MasterProcedureScheduler;
      96: invokevirtual #27                 // Method org/apache/hadoop/hbase/master/procedure/MasterProcedureScheduler.poll:()Lorg/apache/hadoop/hbase/procedure2/Procedure;
      99: astore_2
     100: ldc2_w        #44                 // long 2l
     103: aload_2
     104: invokevirtual #33                 // Method org/apache/hadoop/hbase/procedure2/Procedure.getProcId:()J
     107: invokestatic  #24                 // Method org/junit/Assert.assertEquals:(JJ)V
     110: aconst_null
     111: aload_0
     112: getfield      #8                  // Field queue:Lorg/apache/hadoop/hbase/master/procedure/MasterProcedureScheduler;
     115: lconst_0
     116: invokevirtual #48                 // Method org/apache/hadoop/hbase/master/procedure/MasterProcedureScheduler.poll:(J)Lorg/apache/hadoop/hbase/procedure2/Procedure;
     119: invokestatic  #39                 // Method org/junit/Assert.assertEquals:(Ljava/lang/Object;Ljava/lang/Object;)V
     122: aload_3
     123: aload_0
     124: getfield      #8                  // Field queue:Lorg/apache/hadoop/hbase/master/procedure/MasterProcedureScheduler;
     127: invokevirtual #95                 // Method org/apache/hadoop/hbase/procedure2/ProcedureEvent.wake:(Lorg/apache/hadoop/hbase/procedure2/AbstractProcedureScheduler;)V
     130: aload_0
     131: getfield      #8                  // Field queue:Lorg/apache/hadoop/hbase/master/procedure/MasterProcedureScheduler;
     134: invokevirtual #27                 // Method org/apache/hadoop/hbase/master/procedure/MasterProcedureScheduler.poll:()Lorg/apache/hadoop/hbase/procedure2/Procedure;
     137: astore_2
     138: lconst_1
     139: aload_2
     140: invokevirtual #33                 // Method org/apache/hadoop/hbase/procedure2/Procedure.getProcId:()J
     143: invokestatic  #24                 // Method org/junit/Assert.assertEquals:(JJ)V
     146: aconst_null
     147: aload_0
     148: getfield      #8                  // Field queue:Lorg/apache/hadoop/hbase/master/procedure/MasterProcedureScheduler;
     151: lconst_0
     152: invokevirtual #48                 // Method org/apache/hadoop/hbase/master/procedure/MasterProcedureScheduler.poll:(J)Lorg/apache/hadoop/hbase/procedure2/Procedure;
     155: invokestatic  #39                 // Method org/junit/Assert.assertEquals:(Ljava/lang/Object;Ljava/lang/Object;)V
     158: return

  public void testParentXLockAndChildrenSharedLock() throws java.lang.Exception;
    Code:
       0: aload_0
       1: getfield      #4                  // Field name:Lorg/junit/rules/TestName;
       4: invokevirtual #36                 // Method org/junit/rules/TestName.getMethodName:()Ljava/lang/String;
       7: invokestatic  #19                 // Method org/apache/hadoop/hbase/TableName.valueOf:(Ljava/lang/String;)Lorg/apache/hadoop/hbase/TableName;
      10: astore_1
      11: aload_1
      12: invokestatic  #96                 // Method generateRegionInfo:(Lorg/apache/hadoop/hbase/TableName;)[Lorg/apache/hadoop/hbase/client/RegionInfo;
      15: astore_2
      16: aload_2
      17: arraylength
      18: anewarray     #72                 // class org/apache/hadoop/hbase/master/procedure/TestMasterProcedureScheduler$TestRegionProcedure
      21: astore_3
      22: iconst_0
      23: istore        4
      25: iload         4
      27: aload_2
      28: arraylength
      29: if_icmpge     70
      32: aload_3
      33: iload         4
      35: new           #72                 // class org/apache/hadoop/hbase/master/procedure/TestMasterProcedureScheduler$TestRegionProcedure
      38: dup
      39: lconst_1
      40: iconst_2
      41: iload         4
      43: iadd
      44: i2l
      45: aload_1
      46: getstatic     #73                 // Field org/apache/hadoop/hbase/master/procedure/TableProcedureInterface$TableOperationType.REGION_ASSIGN:Lorg/apache/hadoop/hbase/master/procedure/TableProcedureInterface$TableOperationType;
      49: iconst_1
      50: anewarray     #74                 // class org/apache/hadoop/hbase/client/RegionInfo
      53: dup
      54: iconst_0
      55: aload_2
      56: iload         4
      58: aaload
      59: aastore
      60: invokespecial #87                 // Method org/apache/hadoop/hbase/master/procedure/TestMasterProcedureScheduler$TestRegionProcedure."<init>":(JJLorg/apache/hadoop/hbase/TableName;Lorg/apache/hadoop/hbase/master/procedure/TableProcedureInterface$TableOperationType;[Lorg/apache/hadoop/hbase/client/RegionInfo;)V
      63: aastore
      64: iinc          4, 1
      67: goto          25
      70: aload_0
      71: aload_1
      72: new           #20                 // class org/apache/hadoop/hbase/master/procedure/TestMasterProcedureScheduler$TestTableProcedure
      75: dup
      76: lconst_1
      77: aload_1
      78: getstatic     #64                 // Field org/apache/hadoop/hbase/master/procedure/TableProcedureInterface$TableOperationType.CREATE:Lorg/apache/hadoop/hbase/master/procedure/TableProcedureInterface$TableOperationType;
      81: invokespecial #22                 // Method org/apache/hadoop/hbase/master/procedure/TestMasterProcedureScheduler$TestTableProcedure."<init>":(JLorg/apache/hadoop/hbase/TableName;Lorg/apache/hadoop/hbase/master/procedure/TableProcedureInterface$TableOperationType;)V
      84: aload_3
      85: invokespecial #97                 // Method testInheritedXLockAndChildrenSharedLock:(Lorg/apache/hadoop/hbase/TableName;Lorg/apache/hadoop/hbase/master/procedure/TestMasterProcedureScheduler$TestTableProcedure;[Lorg/apache/hadoop/hbase/master/procedure/TestMasterProcedureScheduler$TestRegionProcedure;)V
      88: return

  public void testRootXLockAndChildrenSharedLock() throws java.lang.Exception;
    Code:
       0: aload_0
       1: getfield      #4                  // Field name:Lorg/junit/rules/TestName;
       4: invokevirtual #36                 // Method org/junit/rules/TestName.getMethodName:()Ljava/lang/String;
       7: invokestatic  #19                 // Method org/apache/hadoop/hbase/TableName.valueOf:(Ljava/lang/String;)Lorg/apache/hadoop/hbase/TableName;
      10: astore_1
      11: aload_1
      12: invokestatic  #96                 // Method generateRegionInfo:(Lorg/apache/hadoop/hbase/TableName;)[Lorg/apache/hadoop/hbase/client/RegionInfo;
      15: astore_2
      16: aload_2
      17: arraylength
      18: anewarray     #72                 // class org/apache/hadoop/hbase/master/procedure/TestMasterProcedureScheduler$TestRegionProcedure
      21: astore_3
      22: iconst_0
      23: istore        4
      25: iload         4
      27: aload_2
      28: arraylength
      29: if_icmpge     73
      32: aload_3
      33: iload         4
      35: new           #72                 // class org/apache/hadoop/hbase/master/procedure/TestMasterProcedureScheduler$TestRegionProcedure
      38: dup
      39: lconst_1
      40: ldc2_w        #44                 // long 2l
      43: iconst_3
      44: iload         4
      46: iadd
      47: i2l
      48: aload_1
      49: getstatic     #73                 // Field org/apache/hadoop/hbase/master/procedure/TableProcedureInterface$TableOperationType.REGION_ASSIGN:Lorg/apache/hadoop/hbase/master/procedure/TableProcedureInterface$TableOperationType;
      52: iconst_1
      53: anewarray     #74                 // class org/apache/hadoop/hbase/client/RegionInfo
      56: dup
      57: iconst_0
      58: aload_2
      59: iload         4
      61: aaload
      62: aastore
      63: invokespecial #98                 // Method org/apache/hadoop/hbase/master/procedure/TestMasterProcedureScheduler$TestRegionProcedure."<init>":(JJJLorg/apache/hadoop/hbase/TableName;Lorg/apache/hadoop/hbase/master/procedure/TableProcedureInterface$TableOperationType;[Lorg/apache/hadoop/hbase/client/RegionInfo;)V
      66: aastore
      67: iinc          4, 1
      70: goto          25
      73: aload_0
      74: aload_1
      75: new           #20                 // class org/apache/hadoop/hbase/master/procedure/TestMasterProcedureScheduler$TestTableProcedure
      78: dup
      79: lconst_1
      80: aload_1
      81: getstatic     #64                 // Field org/apache/hadoop/hbase/master/procedure/TableProcedureInterface$TableOperationType.CREATE:Lorg/apache/hadoop/hbase/master/procedure/TableProcedureInterface$TableOperationType;
      84: invokespecial #22                 // Method org/apache/hadoop/hbase/master/procedure/TestMasterProcedureScheduler$TestTableProcedure."<init>":(JLorg/apache/hadoop/hbase/TableName;Lorg/apache/hadoop/hbase/master/procedure/TableProcedureInterface$TableOperationType;)V
      87: aload_3
      88: invokespecial #97                 // Method testInheritedXLockAndChildrenSharedLock:(Lorg/apache/hadoop/hbase/TableName;Lorg/apache/hadoop/hbase/master/procedure/TestMasterProcedureScheduler$TestTableProcedure;[Lorg/apache/hadoop/hbase/master/procedure/TestMasterProcedureScheduler$TestRegionProcedure;)V
      91: return

  public void testParentXLockAndChildrenXLock() throws java.lang.Exception;
    Code:
       0: aload_0
       1: getfield      #4                  // Field name:Lorg/junit/rules/TestName;
       4: invokevirtual #36                 // Method org/junit/rules/TestName.getMethodName:()Ljava/lang/String;
       7: invokestatic  #19                 // Method org/apache/hadoop/hbase/TableName.valueOf:(Ljava/lang/String;)Lorg/apache/hadoop/hbase/TableName;
      10: astore_1
      11: aload_0
      12: aload_1
      13: new           #20                 // class org/apache/hadoop/hbase/master/procedure/TestMasterProcedureScheduler$TestTableProcedure
      16: dup
      17: lconst_1
      18: aload_1
      19: getstatic     #21                 // Field org/apache/hadoop/hbase/master/procedure/TableProcedureInterface$TableOperationType.EDIT:Lorg/apache/hadoop/hbase/master/procedure/TableProcedureInterface$TableOperationType;
      22: invokespecial #22                 // Method org/apache/hadoop/hbase/master/procedure/TestMasterProcedureScheduler$TestTableProcedure."<init>":(JLorg/apache/hadoop/hbase/TableName;Lorg/apache/hadoop/hbase/master/procedure/TableProcedureInterface$TableOperationType;)V
      25: new           #20                 // class org/apache/hadoop/hbase/master/procedure/TestMasterProcedureScheduler$TestTableProcedure
      28: dup
      29: lconst_1
      30: ldc2_w        #44                 // long 2l
      33: aload_1
      34: getstatic     #21                 // Field org/apache/hadoop/hbase/master/procedure/TableProcedureInterface$TableOperationType.EDIT:Lorg/apache/hadoop/hbase/master/procedure/TableProcedureInterface$TableOperationType;
      37: invokespecial #107                // Method org/apache/hadoop/hbase/master/procedure/TestMasterProcedureScheduler$TestTableProcedure."<init>":(JJLorg/apache/hadoop/hbase/TableName;Lorg/apache/hadoop/hbase/master/procedure/TableProcedureInterface$TableOperationType;)V
      40: invokespecial #108                // Method testInheritedXLockAndChildrenXLock:(Lorg/apache/hadoop/hbase/TableName;Lorg/apache/hadoop/hbase/master/procedure/TestMasterProcedureScheduler$TestTableProcedure;Lorg/apache/hadoop/hbase/master/procedure/TestMasterProcedureScheduler$TestTableProcedure;)V
      43: return

  public void testRootXLockAndChildrenXLock() throws java.lang.Exception;
    Code:
       0: aload_0
       1: getfield      #4                  // Field name:Lorg/junit/rules/TestName;
       4: invokevirtual #36                 // Method org/junit/rules/TestName.getMethodName:()Ljava/lang/String;
       7: invokestatic  #19                 // Method org/apache/hadoop/hbase/TableName.valueOf:(Ljava/lang/String;)Lorg/apache/hadoop/hbase/TableName;
      10: astore_1
      11: aload_0
      12: aload_1
      13: new           #20                 // class org/apache/hadoop/hbase/master/procedure/TestMasterProcedureScheduler$TestTableProcedure
      16: dup
      17: lconst_1
      18: aload_1
      19: getstatic     #21                 // Field org/apache/hadoop/hbase/master/procedure/TableProcedureInterface$TableOperationType.EDIT:Lorg/apache/hadoop/hbase/master/procedure/TableProcedureInterface$TableOperationType;
      22: invokespecial #22                 // Method org/apache/hadoop/hbase/master/procedure/TestMasterProcedureScheduler$TestTableProcedure."<init>":(JLorg/apache/hadoop/hbase/TableName;Lorg/apache/hadoop/hbase/master/procedure/TableProcedureInterface$TableOperationType;)V
      25: new           #20                 // class org/apache/hadoop/hbase/master/procedure/TestMasterProcedureScheduler$TestTableProcedure
      28: dup
      29: lconst_1
      30: ldc2_w        #44                 // long 2l
      33: ldc2_w        #46                 // long 3l
      36: aload_1
      37: getstatic     #21                 // Field org/apache/hadoop/hbase/master/procedure/TableProcedureInterface$TableOperationType.EDIT:Lorg/apache/hadoop/hbase/master/procedure/TableProcedureInterface$TableOperationType;
      40: invokespecial #109                // Method org/apache/hadoop/hbase/master/procedure/TestMasterProcedureScheduler$TestTableProcedure."<init>":(JJJLorg/apache/hadoop/hbase/TableName;Lorg/apache/hadoop/hbase/master/procedure/TableProcedureInterface$TableOperationType;)V
      43: invokespecial #108                // Method testInheritedXLockAndChildrenXLock:(Lorg/apache/hadoop/hbase/TableName;Lorg/apache/hadoop/hbase/master/procedure/TestMasterProcedureScheduler$TestTableProcedure;Lorg/apache/hadoop/hbase/master/procedure/TestMasterProcedureScheduler$TestTableProcedure;)V
      46: return

  public void testYieldWithXLockHeld() throws java.lang.Exception;
    Code:
       0: aload_0
       1: getfield      #4                  // Field name:Lorg/junit/rules/TestName;
       4: invokevirtual #36                 // Method org/junit/rules/TestName.getMethodName:()Ljava/lang/String;
       7: invokestatic  #19                 // Method org/apache/hadoop/hbase/TableName.valueOf:(Ljava/lang/String;)Lorg/apache/hadoop/hbase/TableName;
      10: astore_1
      11: aload_0
      12: getfield      #8                  // Field queue:Lorg/apache/hadoop/hbase/master/procedure/MasterProcedureScheduler;
      15: new           #20                 // class org/apache/hadoop/hbase/master/procedure/TestMasterProcedureScheduler$TestTableProcedure
      18: dup
      19: lconst_1
      20: aload_1
      21: getstatic     #21                 // Field org/apache/hadoop/hbase/master/procedure/TableProcedureInterface$TableOperationType.EDIT:Lorg/apache/hadoop/hbase/master/procedure/TableProcedureInterface$TableOperationType;
      24: invokespecial #22                 // Method org/apache/hadoop/hbase/master/procedure/TestMasterProcedureScheduler$TestTableProcedure."<init>":(JLorg/apache/hadoop/hbase/TableName;Lorg/apache/hadoop/hbase/master/procedure/TableProcedureInterface$TableOperationType;)V
      27: invokevirtual #23                 // Method org/apache/hadoop/hbase/master/procedure/MasterProcedureScheduler.addBack:(Lorg/apache/hadoop/hbase/procedure2/Procedure;)V
      30: aload_0
      31: getfield      #8                  // Field queue:Lorg/apache/hadoop/hbase/master/procedure/MasterProcedureScheduler;
      34: new           #20                 // class org/apache/hadoop/hbase/master/procedure/TestMasterProcedureScheduler$TestTableProcedure
      37: dup
      38: ldc2_w        #44                 // long 2l
      41: aload_1
      42: getstatic     #21                 // Field org/apache/hadoop/hbase/master/procedure/TableProcedureInterface$TableOperationType.EDIT:Lorg/apache/hadoop/hbase/master/procedure/TableProcedureInterface$TableOperationType;
      45: invokespecial #22                 // Method org/apache/hadoop/hbase/master/procedure/TestMasterProcedureScheduler$TestTableProcedure."<init>":(JLorg/apache/hadoop/hbase/TableName;Lorg/apache/hadoop/hbase/master/procedure/TableProcedureInterface$TableOperationType;)V
      48: invokevirtual #23                 // Method org/apache/hadoop/hbase/master/procedure/MasterProcedureScheduler.addBack:(Lorg/apache/hadoop/hbase/procedure2/Procedure;)V
      51: aload_0
      52: getfield      #8                  // Field queue:Lorg/apache/hadoop/hbase/master/procedure/MasterProcedureScheduler;
      55: invokevirtual #27                 // Method org/apache/hadoop/hbase/master/procedure/MasterProcedureScheduler.poll:()Lorg/apache/hadoop/hbase/procedure2/Procedure;
      58: astore_2
      59: lconst_1
      60: aload_2
      61: invokevirtual #33                 // Method org/apache/hadoop/hbase/procedure2/Procedure.getProcId:()J
      64: invokestatic  #24                 // Method org/junit/Assert.assertEquals:(JJ)V
      67: iconst_0
      68: invokestatic  #38                 // Method java/lang/Boolean.valueOf:(Z)Ljava/lang/Boolean;
      71: aload_0
      72: getfield      #8                  // Field queue:Lorg/apache/hadoop/hbase/master/procedure/MasterProcedureScheduler;
      75: aload_2
      76: aload_1
      77: invokevirtual #30                 // Method org/apache/hadoop/hbase/master/procedure/MasterProcedureScheduler.waitTableExclusiveLock:(Lorg/apache/hadoop/hbase/procedure2/Procedure;Lorg/apache/hadoop/hbase/TableName;)Z
      80: invokestatic  #38                 // Method java/lang/Boolean.valueOf:(Z)Ljava/lang/Boolean;
      83: invokestatic  #39                 // Method org/junit/Assert.assertEquals:(Ljava/lang/Object;Ljava/lang/Object;)V
      86: aconst_null
      87: aload_0
      88: getfield      #8                  // Field queue:Lorg/apache/hadoop/hbase/master/procedure/MasterProcedureScheduler;
      91: lconst_0
      92: invokevirtual #48                 // Method org/apache/hadoop/hbase/master/procedure/MasterProcedureScheduler.poll:(J)Lorg/apache/hadoop/hbase/procedure2/Procedure;
      95: invokestatic  #39                 // Method org/junit/Assert.assertEquals:(Ljava/lang/Object;Ljava/lang/Object;)V
      98: aload_0
      99: getfield      #8                  // Field queue:Lorg/apache/hadoop/hbase/master/procedure/MasterProcedureScheduler;
     102: aload_2
     103: invokevirtual #62                 // Method org/apache/hadoop/hbase/master/procedure/MasterProcedureScheduler.yield:(Lorg/apache/hadoop/hbase/procedure2/Procedure;)V
     106: aload_0
     107: getfield      #8                  // Field queue:Lorg/apache/hadoop/hbase/master/procedure/MasterProcedureScheduler;
     110: invokevirtual #27                 // Method org/apache/hadoop/hbase/master/procedure/MasterProcedureScheduler.poll:()Lorg/apache/hadoop/hbase/procedure2/Procedure;
     113: astore_2
     114: lconst_1
     115: aload_2
     116: invokevirtual #33                 // Method org/apache/hadoop/hbase/procedure2/Procedure.getProcId:()J
     119: invokestatic  #24                 // Method org/junit/Assert.assertEquals:(JJ)V
     122: aload_0
     123: getfield      #8                  // Field queue:Lorg/apache/hadoop/hbase/master/procedure/MasterProcedureScheduler;
     126: aload_2
     127: aload_1
     128: invokevirtual #31                 // Method org/apache/hadoop/hbase/master/procedure/MasterProcedureScheduler.wakeTableExclusiveLock:(Lorg/apache/hadoop/hbase/procedure2/Procedure;Lorg/apache/hadoop/hbase/TableName;)V
     131: aload_0
     132: getfield      #8                  // Field queue:Lorg/apache/hadoop/hbase/master/procedure/MasterProcedureScheduler;
     135: invokevirtual #27                 // Method org/apache/hadoop/hbase/master/procedure/MasterProcedureScheduler.poll:()Lorg/apache/hadoop/hbase/procedure2/Procedure;
     138: astore_2
     139: ldc2_w        #44                 // long 2l
     142: aload_2
     143: invokevirtual #33                 // Method org/apache/hadoop/hbase/procedure2/Procedure.getProcId:()J
     146: invokestatic  #24                 // Method org/junit/Assert.assertEquals:(JJ)V
     149: return

  public void testYieldWithSharedLockHeld() throws java.lang.Exception;
    Code:
       0: aload_0
       1: getfield      #4                  // Field name:Lorg/junit/rules/TestName;
       4: invokevirtual #36                 // Method org/junit/rules/TestName.getMethodName:()Ljava/lang/String;
       7: invokestatic  #19                 // Method org/apache/hadoop/hbase/TableName.valueOf:(Ljava/lang/String;)Lorg/apache/hadoop/hbase/TableName;
      10: astore_1
      11: aload_0
      12: getfield      #8                  // Field queue:Lorg/apache/hadoop/hbase/master/procedure/MasterProcedureScheduler;
      15: new           #20                 // class org/apache/hadoop/hbase/master/procedure/TestMasterProcedureScheduler$TestTableProcedure
      18: dup
      19: lconst_1
      20: aload_1
      21: getstatic     #40                 // Field org/apache/hadoop/hbase/master/procedure/TableProcedureInterface$TableOperationType.READ:Lorg/apache/hadoop/hbase/master/procedure/TableProcedureInterface$TableOperationType;
      24: invokespecial #22                 // Method org/apache/hadoop/hbase/master/procedure/TestMasterProcedureScheduler$TestTableProcedure."<init>":(JLorg/apache/hadoop/hbase/TableName;Lorg/apache/hadoop/hbase/master/procedure/TableProcedureInterface$TableOperationType;)V
      27: invokevirtual #23                 // Method org/apache/hadoop/hbase/master/procedure/MasterProcedureScheduler.addBack:(Lorg/apache/hadoop/hbase/procedure2/Procedure;)V
      30: aload_0
      31: getfield      #8                  // Field queue:Lorg/apache/hadoop/hbase/master/procedure/MasterProcedureScheduler;
      34: new           #20                 // class org/apache/hadoop/hbase/master/procedure/TestMasterProcedureScheduler$TestTableProcedure
      37: dup
      38: ldc2_w        #44                 // long 2l
      41: aload_1
      42: getstatic     #40                 // Field org/apache/hadoop/hbase/master/procedure/TableProcedureInterface$TableOperationType.READ:Lorg/apache/hadoop/hbase/master/procedure/TableProcedureInterface$TableOperationType;
      45: invokespecial #22                 // Method org/apache/hadoop/hbase/master/procedure/TestMasterProcedureScheduler$TestTableProcedure."<init>":(JLorg/apache/hadoop/hbase/TableName;Lorg/apache/hadoop/hbase/master/procedure/TableProcedureInterface$TableOperationType;)V
      48: invokevirtual #23                 // Method org/apache/hadoop/hbase/master/procedure/MasterProcedureScheduler.addBack:(Lorg/apache/hadoop/hbase/procedure2/Procedure;)V
      51: aload_0
      52: getfield      #8                  // Field queue:Lorg/apache/hadoop/hbase/master/procedure/MasterProcedureScheduler;
      55: new           #20                 // class org/apache/hadoop/hbase/master/procedure/TestMasterProcedureScheduler$TestTableProcedure
      58: dup
      59: ldc2_w        #46                 // long 3l
      62: aload_1
      63: getstatic     #21                 // Field org/apache/hadoop/hbase/master/procedure/TableProcedureInterface$TableOperationType.EDIT:Lorg/apache/hadoop/hbase/master/procedure/TableProcedureInterface$TableOperationType;
      66: invokespecial #22                 // Method org/apache/hadoop/hbase/master/procedure/TestMasterProcedureScheduler$TestTableProcedure."<init>":(JLorg/apache/hadoop/hbase/TableName;Lorg/apache/hadoop/hbase/master/procedure/TableProcedureInterface$TableOperationType;)V
      69: invokevirtual #23                 // Method org/apache/hadoop/hbase/master/procedure/MasterProcedureScheduler.addBack:(Lorg/apache/hadoop/hbase/procedure2/Procedure;)V
      72: aload_0
      73: getfield      #8                  // Field queue:Lorg/apache/hadoop/hbase/master/procedure/MasterProcedureScheduler;
      76: invokevirtual #27                 // Method org/apache/hadoop/hbase/master/procedure/MasterProcedureScheduler.poll:()Lorg/apache/hadoop/hbase/procedure2/Procedure;
      79: astore_2
      80: lconst_1
      81: aload_2
      82: invokevirtual #33                 // Method org/apache/hadoop/hbase/procedure2/Procedure.getProcId:()J
      85: invokestatic  #24                 // Method org/junit/Assert.assertEquals:(JJ)V
      88: iconst_0
      89: invokestatic  #38                 // Method java/lang/Boolean.valueOf:(Z)Ljava/lang/Boolean;
      92: aload_0
      93: getfield      #8                  // Field queue:Lorg/apache/hadoop/hbase/master/procedure/MasterProcedureScheduler;
      96: aload_2
      97: aload_1
      98: invokevirtual #42                 // Method org/apache/hadoop/hbase/master/procedure/MasterProcedureScheduler.waitTableSharedLock:(Lorg/apache/hadoop/hbase/procedure2/Procedure;Lorg/apache/hadoop/hbase/TableName;)Z
     101: invokestatic  #38                 // Method java/lang/Boolean.valueOf:(Z)Ljava/lang/Boolean;
     104: invokestatic  #39                 // Method org/junit/Assert.assertEquals:(Ljava/lang/Object;Ljava/lang/Object;)V
     107: aload_0
     108: getfield      #8                  // Field queue:Lorg/apache/hadoop/hbase/master/procedure/MasterProcedureScheduler;
     111: invokevirtual #27                 // Method org/apache/hadoop/hbase/master/procedure/MasterProcedureScheduler.poll:()Lorg/apache/hadoop/hbase/procedure2/Procedure;
     114: astore_3
     115: ldc2_w        #44                 // long 2l
     118: aload_3
     119: invokevirtual #33                 // Method org/apache/hadoop/hbase/procedure2/Procedure.getProcId:()J
     122: invokestatic  #24                 // Method org/junit/Assert.assertEquals:(JJ)V
     125: iconst_0
     126: invokestatic  #38                 // Method java/lang/Boolean.valueOf:(Z)Ljava/lang/Boolean;
     129: aload_0
     130: getfield      #8                  // Field queue:Lorg/apache/hadoop/hbase/master/procedure/MasterProcedureScheduler;
     133: aload_3
     134: aload_1
     135: invokevirtual #42                 // Method org/apache/hadoop/hbase/master/procedure/MasterProcedureScheduler.waitTableSharedLock:(Lorg/apache/hadoop/hbase/procedure2/Procedure;Lorg/apache/hadoop/hbase/TableName;)Z
     138: invokestatic  #38                 // Method java/lang/Boolean.valueOf:(Z)Ljava/lang/Boolean;
     141: invokestatic  #39                 // Method org/junit/Assert.assertEquals:(Ljava/lang/Object;Ljava/lang/Object;)V
     144: aconst_null
     145: aload_0
     146: getfield      #8                  // Field queue:Lorg/apache/hadoop/hbase/master/procedure/MasterProcedureScheduler;
     149: lconst_0
     150: invokevirtual #48                 // Method org/apache/hadoop/hbase/master/procedure/MasterProcedureScheduler.poll:(J)Lorg/apache/hadoop/hbase/procedure2/Procedure;
     153: invokestatic  #39                 // Method org/junit/Assert.assertEquals:(Ljava/lang/Object;Ljava/lang/Object;)V
     156: aload_0
     157: getfield      #8                  // Field queue:Lorg/apache/hadoop/hbase/master/procedure/MasterProcedureScheduler;
     160: aload_2
     161: invokevirtual #62                 // Method org/apache/hadoop/hbase/master/procedure/MasterProcedureScheduler.yield:(Lorg/apache/hadoop/hbase/procedure2/Procedure;)V
     164: aload_0
     165: getfield      #8                  // Field queue:Lorg/apache/hadoop/hbase/master/procedure/MasterProcedureScheduler;
     168: aload_3
     169: invokevirtual #62                 // Method org/apache/hadoop/hbase/master/procedure/MasterProcedureScheduler.yield:(Lorg/apache/hadoop/hbase/procedure2/Procedure;)V
     172: aload_0
     173: getfield      #8                  // Field queue:Lorg/apache/hadoop/hbase/master/procedure/MasterProcedureScheduler;
     176: invokevirtual #27                 // Method org/apache/hadoop/hbase/master/procedure/MasterProcedureScheduler.poll:()Lorg/apache/hadoop/hbase/procedure2/Procedure;
     179: astore_2
     180: lconst_1
     181: aload_2
     182: invokevirtual #33                 // Method org/apache/hadoop/hbase/procedure2/Procedure.getProcId:()J
     185: invokestatic  #24                 // Method org/junit/Assert.assertEquals:(JJ)V
     188: aload_0
     189: getfield      #8                  // Field queue:Lorg/apache/hadoop/hbase/master/procedure/MasterProcedureScheduler;
     192: invokevirtual #27                 // Method org/apache/hadoop/hbase/master/procedure/MasterProcedureScheduler.poll:()Lorg/apache/hadoop/hbase/procedure2/Procedure;
     195: astore_3
     196: ldc2_w        #44                 // long 2l
     199: aload_3
     200: invokevirtual #33                 // Method org/apache/hadoop/hbase/procedure2/Procedure.getProcId:()J
     203: invokestatic  #24                 // Method org/junit/Assert.assertEquals:(JJ)V
     206: aload_0
     207: getfield      #8                  // Field queue:Lorg/apache/hadoop/hbase/master/procedure/MasterProcedureScheduler;
     210: aload_2
     211: aload_1
     212: invokevirtual #43                 // Method org/apache/hadoop/hbase/master/procedure/MasterProcedureScheduler.wakeTableSharedLock:(Lorg/apache/hadoop/hbase/procedure2/Procedure;Lorg/apache/hadoop/hbase/TableName;)V
     215: aload_0
     216: getfield      #8                  // Field queue:Lorg/apache/hadoop/hbase/master/procedure/MasterProcedureScheduler;
     219: aload_3
     220: aload_1
     221: invokevirtual #43                 // Method org/apache/hadoop/hbase/master/procedure/MasterProcedureScheduler.wakeTableSharedLock:(Lorg/apache/hadoop/hbase/procedure2/Procedure;Lorg/apache/hadoop/hbase/TableName;)V
     224: aload_0
     225: getfield      #8                  // Field queue:Lorg/apache/hadoop/hbase/master/procedure/MasterProcedureScheduler;
     228: invokevirtual #27                 // Method org/apache/hadoop/hbase/master/procedure/MasterProcedureScheduler.poll:()Lorg/apache/hadoop/hbase/procedure2/Procedure;
     231: astore        4
     233: ldc2_w        #46                 // long 3l
     236: aload         4
     238: invokevirtual #33                 // Method org/apache/hadoop/hbase/procedure2/Procedure.getProcId:()J
     241: invokestatic  #24                 // Method org/junit/Assert.assertEquals:(JJ)V
     244: return

  public void testListLocksServer() throws java.lang.Exception;
    Code:
       0: lconst_0
       1: invokestatic  #131                // Method createExclusiveLockProcedure:(J)Lorg/apache/hadoop/hbase/master/locking/LockProcedure;
       4: astore_1
       5: aload_0
       6: getfield      #8                  // Field queue:Lorg/apache/hadoop/hbase/master/procedure/MasterProcedureScheduler;
       9: aload_1
      10: ldc           #132                // String server1,1234,0
      12: invokestatic  #133                // Method org/apache/hadoop/hbase/ServerName.valueOf:(Ljava/lang/String;)Lorg/apache/hadoop/hbase/ServerName;
      15: invokevirtual #134                // Method org/apache/hadoop/hbase/master/procedure/MasterProcedureScheduler.waitServerExclusiveLock:(Lorg/apache/hadoop/hbase/procedure2/Procedure;Lorg/apache/hadoop/hbase/ServerName;)Z
      18: pop
      19: aload_0
      20: getfield      #8                  // Field queue:Lorg/apache/hadoop/hbase/master/procedure/MasterProcedureScheduler;
      23: invokevirtual #135                // Method org/apache/hadoop/hbase/master/procedure/MasterProcedureScheduler.getLocks:()Ljava/util/List;
      26: astore_2
      27: lconst_1
      28: aload_2
      29: invokeinterface #136,  1          // InterfaceMethod java/util/List.size:()I
      34: i2l
      35: invokestatic  #24                 // Method org/junit/Assert.assertEquals:(JJ)V
      38: aload_2
      39: iconst_0
      40: invokeinterface #137,  2          // InterfaceMethod java/util/List.get:(I)Ljava/lang/Object;
      45: checkcast     #138                // class org/apache/hadoop/hbase/procedure2/LockedResource
      48: astore_3
      49: aload_3
      50: getstatic     #139                // Field org/apache/hadoop/hbase/procedure2/LockedResourceType.SERVER:Lorg/apache/hadoop/hbase/procedure2/LockedResourceType;
      53: ldc           #132                // String server1,1234,0
      55: invokestatic  #140                // Method assertLockResource:(Lorg/apache/hadoop/hbase/procedure2/LockedResource;Lorg/apache/hadoop/hbase/procedure2/LockedResourceType;Ljava/lang/String;)V
      58: aload_3
      59: aload_1
      60: invokestatic  #141                // Method assertExclusiveLock:(Lorg/apache/hadoop/hbase/procedure2/LockedResource;Lorg/apache/hadoop/hbase/procedure2/Procedure;)V
      63: aload_3
      64: invokevirtual #142                // Method org/apache/hadoop/hbase/procedure2/LockedResource.getWaitingProcedures:()Ljava/util/List;
      67: invokeinterface #143,  1          // InterfaceMethod java/util/List.isEmpty:()Z
      72: invokestatic  #28                 // Method org/junit/Assert.assertTrue:(Z)V
      75: return

  public void testListLocksNamespace() throws java.lang.Exception;
    Code:
       0: lconst_1
       1: invokestatic  #131                // Method createExclusiveLockProcedure:(J)Lorg/apache/hadoop/hbase/master/locking/LockProcedure;
       4: astore_1
       5: aload_0
       6: getfield      #8                  // Field queue:Lorg/apache/hadoop/hbase/master/procedure/MasterProcedureScheduler;
       9: aload_1
      10: ldc           #55                 // String ns1
      12: invokevirtual #60                 // Method org/apache/hadoop/hbase/master/procedure/MasterProcedureScheduler.waitNamespaceExclusiveLock:(Lorg/apache/hadoop/hbase/procedure2/Procedure;Ljava/lang/String;)Z
      15: pop
      16: aload_0
      17: getfield      #8                  // Field queue:Lorg/apache/hadoop/hbase/master/procedure/MasterProcedureScheduler;
      20: invokevirtual #135                // Method org/apache/hadoop/hbase/master/procedure/MasterProcedureScheduler.getLocks:()Ljava/util/List;
      23: astore_2
      24: ldc2_w        #44                 // long 2l
      27: aload_2
      28: invokeinterface #136,  1          // InterfaceMethod java/util/List.size:()I
      33: i2l
      34: invokestatic  #24                 // Method org/junit/Assert.assertEquals:(JJ)V
      37: aload_2
      38: iconst_0
      39: invokeinterface #137,  2          // InterfaceMethod java/util/List.get:(I)Ljava/lang/Object;
      44: checkcast     #138                // class org/apache/hadoop/hbase/procedure2/LockedResource
      47: astore_3
      48: aload_3
      49: getstatic     #144                // Field org/apache/hadoop/hbase/procedure2/LockedResourceType.NAMESPACE:Lorg/apache/hadoop/hbase/procedure2/LockedResourceType;
      52: ldc           #55                 // String ns1
      54: invokestatic  #140                // Method assertLockResource:(Lorg/apache/hadoop/hbase/procedure2/LockedResource;Lorg/apache/hadoop/hbase/procedure2/LockedResourceType;Ljava/lang/String;)V
      57: aload_3
      58: aload_1
      59: invokestatic  #141                // Method assertExclusiveLock:(Lorg/apache/hadoop/hbase/procedure2/LockedResource;Lorg/apache/hadoop/hbase/procedure2/Procedure;)V
      62: aload_3
      63: invokevirtual #142                // Method org/apache/hadoop/hbase/procedure2/LockedResource.getWaitingProcedures:()Ljava/util/List;
      66: invokeinterface #143,  1          // InterfaceMethod java/util/List.isEmpty:()Z
      71: invokestatic  #28                 // Method org/junit/Assert.assertTrue:(Z)V
      74: aload_2
      75: iconst_1
      76: invokeinterface #137,  2          // InterfaceMethod java/util/List.get:(I)Ljava/lang/Object;
      81: checkcast     #138                // class org/apache/hadoop/hbase/procedure2/LockedResource
      84: astore        4
      86: aload         4
      88: getstatic     #145                // Field org/apache/hadoop/hbase/procedure2/LockedResourceType.TABLE:Lorg/apache/hadoop/hbase/procedure2/LockedResourceType;
      91: getstatic     #146                // Field org/apache/hadoop/hbase/master/procedure/TableProcedureInterface.DUMMY_NAMESPACE_TABLE_NAME:Lorg/apache/hadoop/hbase/TableName;
      94: invokevirtual #147                // Method org/apache/hadoop/hbase/TableName.getNameAsString:()Ljava/lang/String;
      97: invokestatic  #140                // Method assertLockResource:(Lorg/apache/hadoop/hbase/procedure2/LockedResource;Lorg/apache/hadoop/hbase/procedure2/LockedResourceType;Ljava/lang/String;)V
     100: aload         4
     102: iconst_1
     103: invokestatic  #148                // Method assertSharedLock:(Lorg/apache/hadoop/hbase/procedure2/LockedResource;I)V
     106: aload         4
     108: invokevirtual #142                // Method org/apache/hadoop/hbase/procedure2/LockedResource.getWaitingProcedures:()Ljava/util/List;
     111: invokeinterface #143,  1          // InterfaceMethod java/util/List.isEmpty:()Z
     116: invokestatic  #28                 // Method org/junit/Assert.assertTrue:(Z)V
     119: return

  public void testListLocksTable() throws java.lang.Exception;
    Code:
       0: ldc2_w        #44                 // long 2l
       3: invokestatic  #131                // Method createExclusiveLockProcedure:(J)Lorg/apache/hadoop/hbase/master/locking/LockProcedure;
       6: astore_1
       7: aload_0
       8: getfield      #8                  // Field queue:Lorg/apache/hadoop/hbase/master/procedure/MasterProcedureScheduler;
      11: aload_1
      12: ldc           #56                 // String ns2
      14: ldc           #149                // String table2
      16: invokestatic  #57                 // Method org/apache/hadoop/hbase/TableName.valueOf:(Ljava/lang/String;Ljava/lang/String;)Lorg/apache/hadoop/hbase/TableName;
      19: invokevirtual #30                 // Method org/apache/hadoop/hbase/master/procedure/MasterProcedureScheduler.waitTableExclusiveLock:(Lorg/apache/hadoop/hbase/procedure2/Procedure;Lorg/apache/hadoop/hbase/TableName;)Z
      22: pop
      23: aload_0
      24: getfield      #8                  // Field queue:Lorg/apache/hadoop/hbase/master/procedure/MasterProcedureScheduler;
      27: invokevirtual #135                // Method org/apache/hadoop/hbase/master/procedure/MasterProcedureScheduler.getLocks:()Ljava/util/List;
      30: astore_2
      31: ldc2_w        #44                 // long 2l
      34: aload_2
      35: invokeinterface #136,  1          // InterfaceMethod java/util/List.size:()I
      40: i2l
      41: invokestatic  #24                 // Method org/junit/Assert.assertEquals:(JJ)V
      44: aload_2
      45: iconst_0
      46: invokeinterface #137,  2          // InterfaceMethod java/util/List.get:(I)Ljava/lang/Object;
      51: checkcast     #138                // class org/apache/hadoop/hbase/procedure2/LockedResource
      54: astore_3
      55: aload_3
      56: getstatic     #144                // Field org/apache/hadoop/hbase/procedure2/LockedResourceType.NAMESPACE:Lorg/apache/hadoop/hbase/procedure2/LockedResourceType;
      59: ldc           #56                 // String ns2
      61: invokestatic  #140                // Method assertLockResource:(Lorg/apache/hadoop/hbase/procedure2/LockedResource;Lorg/apache/hadoop/hbase/procedure2/LockedResourceType;Ljava/lang/String;)V
      64: aload_3
      65: iconst_1
      66: invokestatic  #148                // Method assertSharedLock:(Lorg/apache/hadoop/hbase/procedure2/LockedResource;I)V
      69: aload_3
      70: invokevirtual #142                // Method org/apache/hadoop/hbase/procedure2/LockedResource.getWaitingProcedures:()Ljava/util/List;
      73: invokeinterface #143,  1          // InterfaceMethod java/util/List.isEmpty:()Z
      78: invokestatic  #28                 // Method org/junit/Assert.assertTrue:(Z)V
      81: aload_2
      82: iconst_1
      83: invokeinterface #137,  2          // InterfaceMethod java/util/List.get:(I)Ljava/lang/Object;
      88: checkcast     #138                // class org/apache/hadoop/hbase/procedure2/LockedResource
      91: astore        4
      93: aload         4
      95: getstatic     #145                // Field org/apache/hadoop/hbase/procedure2/LockedResourceType.TABLE:Lorg/apache/hadoop/hbase/procedure2/LockedResourceType;
      98: ldc           #150                // String ns2:table2
     100: invokestatic  #140                // Method assertLockResource:(Lorg/apache/hadoop/hbase/procedure2/LockedResource;Lorg/apache/hadoop/hbase/procedure2/LockedResourceType;Ljava/lang/String;)V
     103: aload         4
     105: aload_1
     106: invokestatic  #141                // Method assertExclusiveLock:(Lorg/apache/hadoop/hbase/procedure2/LockedResource;Lorg/apache/hadoop/hbase/procedure2/Procedure;)V
     109: aload         4
     111: invokevirtual #142                // Method org/apache/hadoop/hbase/procedure2/LockedResource.getWaitingProcedures:()Ljava/util/List;
     114: invokeinterface #143,  1          // InterfaceMethod java/util/List.isEmpty:()Z
     119: invokestatic  #28                 // Method org/junit/Assert.assertTrue:(Z)V
     122: return

  public void testListLocksRegion() throws java.lang.Exception;
    Code:
       0: ldc2_w        #46                 // long 3l
       3: invokestatic  #131                // Method createExclusiveLockProcedure:(J)Lorg/apache/hadoop/hbase/master/locking/LockProcedure;
       6: astore_1
       7: ldc           #151                // String ns3
       9: ldc           #152                // String table3
      11: invokestatic  #57                 // Method org/apache/hadoop/hbase/TableName.valueOf:(Ljava/lang/String;Ljava/lang/String;)Lorg/apache/hadoop/hbase/TableName;
      14: invokestatic  #65                 // Method org/apache/hadoop/hbase/client/RegionInfoBuilder.newBuilder:(Lorg/apache/hadoop/hbase/TableName;)Lorg/apache/hadoop/hbase/client/RegionInfoBuilder;
      17: invokevirtual #71                 // Method org/apache/hadoop/hbase/client/RegionInfoBuilder.build:()Lorg/apache/hadoop/hbase/client/RegionInfo;
      20: astore_2
      21: aload_0
      22: getfield      #8                  // Field queue:Lorg/apache/hadoop/hbase/master/procedure/MasterProcedureScheduler;
      25: aload_1
      26: aload_2
      27: invokevirtual #76                 // Method org/apache/hadoop/hbase/master/procedure/MasterProcedureScheduler.waitRegion:(Lorg/apache/hadoop/hbase/procedure2/Procedure;Lorg/apache/hadoop/hbase/client/RegionInfo;)Z
      30: pop
      31: aload_0
      32: getfield      #8                  // Field queue:Lorg/apache/hadoop/hbase/master/procedure/MasterProcedureScheduler;
      35: invokevirtual #135                // Method org/apache/hadoop/hbase/master/procedure/MasterProcedureScheduler.getLocks:()Ljava/util/List;
      38: astore_3
      39: ldc2_w        #46                 // long 3l
      42: aload_3
      43: invokeinterface #136,  1          // InterfaceMethod java/util/List.size:()I
      48: i2l
      49: invokestatic  #24                 // Method org/junit/Assert.assertEquals:(JJ)V
      52: aload_3
      53: iconst_0
      54: invokeinterface #137,  2          // InterfaceMethod java/util/List.get:(I)Ljava/lang/Object;
      59: checkcast     #138                // class org/apache/hadoop/hbase/procedure2/LockedResource
      62: astore        4
      64: aload         4
      66: getstatic     #144                // Field org/apache/hadoop/hbase/procedure2/LockedResourceType.NAMESPACE:Lorg/apache/hadoop/hbase/procedure2/LockedResourceType;
      69: ldc           #151                // String ns3
      71: invokestatic  #140                // Method assertLockResource:(Lorg/apache/hadoop/hbase/procedure2/LockedResource;Lorg/apache/hadoop/hbase/procedure2/LockedResourceType;Ljava/lang/String;)V
      74: aload         4
      76: iconst_1
      77: invokestatic  #148                // Method assertSharedLock:(Lorg/apache/hadoop/hbase/procedure2/LockedResource;I)V
      80: aload         4
      82: invokevirtual #142                // Method org/apache/hadoop/hbase/procedure2/LockedResource.getWaitingProcedures:()Ljava/util/List;
      85: invokeinterface #143,  1          // InterfaceMethod java/util/List.isEmpty:()Z
      90: invokestatic  #28                 // Method org/junit/Assert.assertTrue:(Z)V
      93: aload_3
      94: iconst_1
      95: invokeinterface #137,  2          // InterfaceMethod java/util/List.get:(I)Ljava/lang/Object;
     100: checkcast     #138                // class org/apache/hadoop/hbase/procedure2/LockedResource
     103: astore        5
     105: aload         5
     107: getstatic     #145                // Field org/apache/hadoop/hbase/procedure2/LockedResourceType.TABLE:Lorg/apache/hadoop/hbase/procedure2/LockedResourceType;
     110: ldc           #153                // String ns3:table3
     112: invokestatic  #140                // Method assertLockResource:(Lorg/apache/hadoop/hbase/procedure2/LockedResource;Lorg/apache/hadoop/hbase/procedure2/LockedResourceType;Ljava/lang/String;)V
     115: aload         5
     117: iconst_1
     118: invokestatic  #148                // Method assertSharedLock:(Lorg/apache/hadoop/hbase/procedure2/LockedResource;I)V
     121: aload         5
     123: invokevirtual #142                // Method org/apache/hadoop/hbase/procedure2/LockedResource.getWaitingProcedures:()Ljava/util/List;
     126: invokeinterface #143,  1          // InterfaceMethod java/util/List.isEmpty:()Z
     131: invokestatic  #28                 // Method org/junit/Assert.assertTrue:(Z)V
     134: aload_3
     135: iconst_2
     136: invokeinterface #137,  2          // InterfaceMethod java/util/List.get:(I)Ljava/lang/Object;
     141: checkcast     #138                // class org/apache/hadoop/hbase/procedure2/LockedResource
     144: astore        6
     146: aload         6
     148: getstatic     #154                // Field org/apache/hadoop/hbase/procedure2/LockedResourceType.REGION:Lorg/apache/hadoop/hbase/procedure2/LockedResourceType;
     151: aload_2
     152: invokeinterface #155,  1          // InterfaceMethod org/apache/hadoop/hbase/client/RegionInfo.getEncodedName:()Ljava/lang/String;
     157: invokestatic  #140                // Method assertLockResource:(Lorg/apache/hadoop/hbase/procedure2/LockedResource;Lorg/apache/hadoop/hbase/procedure2/LockedResourceType;Ljava/lang/String;)V
     160: aload         6
     162: aload_1
     163: invokestatic  #141                // Method assertExclusiveLock:(Lorg/apache/hadoop/hbase/procedure2/LockedResource;Lorg/apache/hadoop/hbase/procedure2/Procedure;)V
     166: aload         6
     168: invokevirtual #142                // Method org/apache/hadoop/hbase/procedure2/LockedResource.getWaitingProcedures:()Ljava/util/List;
     171: invokeinterface #143,  1          // InterfaceMethod java/util/List.isEmpty:()Z
     176: invokestatic  #28                 // Method org/junit/Assert.assertTrue:(Z)V
     179: return

  public void testListLocksPeer() throws java.lang.Exception;
    Code:
       0: ldc           #156                // String 1
       2: astore_1
       3: ldc2_w        #49                 // long 4l
       6: invokestatic  #131                // Method createExclusiveLockProcedure:(J)Lorg/apache/hadoop/hbase/master/locking/LockProcedure;
       9: astore_2
      10: aload_0
      11: getfield      #8                  // Field queue:Lorg/apache/hadoop/hbase/master/procedure/MasterProcedureScheduler;
      14: aload_2
      15: aload_1
      16: invokevirtual #157                // Method org/apache/hadoop/hbase/master/procedure/MasterProcedureScheduler.waitPeerExclusiveLock:(Lorg/apache/hadoop/hbase/procedure2/Procedure;Ljava/lang/String;)Z
      19: pop
      20: aload_0
      21: getfield      #8                  // Field queue:Lorg/apache/hadoop/hbase/master/procedure/MasterProcedureScheduler;
      24: invokevirtual #135                // Method org/apache/hadoop/hbase/master/procedure/MasterProcedureScheduler.getLocks:()Ljava/util/List;
      27: astore_3
      28: lconst_1
      29: aload_3
      30: invokeinterface #136,  1          // InterfaceMethod java/util/List.size:()I
      35: i2l
      36: invokestatic  #24                 // Method org/junit/Assert.assertEquals:(JJ)V
      39: aload_3
      40: iconst_0
      41: invokeinterface #137,  2          // InterfaceMethod java/util/List.get:(I)Ljava/lang/Object;
      46: checkcast     #138                // class org/apache/hadoop/hbase/procedure2/LockedResource
      49: astore        4
      51: aload         4
      53: getstatic     #158                // Field org/apache/hadoop/hbase/procedure2/LockedResourceType.PEER:Lorg/apache/hadoop/hbase/procedure2/LockedResourceType;
      56: aload_1
      57: invokestatic  #140                // Method assertLockResource:(Lorg/apache/hadoop/hbase/procedure2/LockedResource;Lorg/apache/hadoop/hbase/procedure2/LockedResourceType;Ljava/lang/String;)V
      60: aload         4
      62: aload_2
      63: invokestatic  #141                // Method assertExclusiveLock:(Lorg/apache/hadoop/hbase/procedure2/LockedResource;Lorg/apache/hadoop/hbase/procedure2/Procedure;)V
      66: aload         4
      68: invokevirtual #142                // Method org/apache/hadoop/hbase/procedure2/LockedResource.getWaitingProcedures:()Ljava/util/List;
      71: invokeinterface #143,  1          // InterfaceMethod java/util/List.isEmpty:()Z
      76: invokestatic  #28                 // Method org/junit/Assert.assertTrue:(Z)V
      79: aload_0
      80: getfield      #8                  // Field queue:Lorg/apache/hadoop/hbase/master/procedure/MasterProcedureScheduler;
      83: aload_2
      84: aload_1
      85: invokevirtual #157                // Method org/apache/hadoop/hbase/master/procedure/MasterProcedureScheduler.waitPeerExclusiveLock:(Lorg/apache/hadoop/hbase/procedure2/Procedure;Ljava/lang/String;)Z
      88: invokestatic  #37                 // Method org/junit/Assert.assertFalse:(Z)V
      91: ldc2_w        #51                 // long 5l
      94: invokestatic  #131                // Method createExclusiveLockProcedure:(J)Lorg/apache/hadoop/hbase/master/locking/LockProcedure;
      97: astore        5
      99: aload_0
     100: getfield      #8                  // Field queue:Lorg/apache/hadoop/hbase/master/procedure/MasterProcedureScheduler;
     103: aload         5
     105: aload_1
     106: invokevirtual #157                // Method org/apache/hadoop/hbase/master/procedure/MasterProcedureScheduler.waitPeerExclusiveLock:(Lorg/apache/hadoop/hbase/procedure2/Procedure;Ljava/lang/String;)Z
     109: invokestatic  #28                 // Method org/junit/Assert.assertTrue:(Z)V
     112: aload_0
     113: getfield      #8                  // Field queue:Lorg/apache/hadoop/hbase/master/procedure/MasterProcedureScheduler;
     116: invokevirtual #135                // Method org/apache/hadoop/hbase/master/procedure/MasterProcedureScheduler.getLocks:()Ljava/util/List;
     119: astore_3
     120: lconst_1
     121: aload_3
     122: invokeinterface #136,  1          // InterfaceMethod java/util/List.size:()I
     127: i2l
     128: invokestatic  #24                 // Method org/junit/Assert.assertEquals:(JJ)V
     131: aload_3
     132: iconst_0
     133: invokeinterface #137,  2          // InterfaceMethod java/util/List.get:(I)Ljava/lang/Object;
     138: checkcast     #138                // class org/apache/hadoop/hbase/procedure2/LockedResource
     141: astore        4
     143: aload         4
     145: getstatic     #158                // Field org/apache/hadoop/hbase/procedure2/LockedResourceType.PEER:Lorg/apache/hadoop/hbase/procedure2/LockedResourceType;
     148: aload_1
     149: invokestatic  #140                // Method assertLockResource:(Lorg/apache/hadoop/hbase/procedure2/LockedResource;Lorg/apache/hadoop/hbase/procedure2/LockedResourceType;Ljava/lang/String;)V
     152: aload         4
     154: aload_2
     155: invokestatic  #141                // Method assertExclusiveLock:(Lorg/apache/hadoop/hbase/procedure2/LockedResource;Lorg/apache/hadoop/hbase/procedure2/Procedure;)V
     158: lconst_1
     159: aload         4
     161: invokevirtual #142                // Method org/apache/hadoop/hbase/procedure2/LockedResource.getWaitingProcedures:()Ljava/util/List;
     164: invokeinterface #136,  1          // InterfaceMethod java/util/List.size:()I
     169: i2l
     170: invokestatic  #24                 // Method org/junit/Assert.assertEquals:(JJ)V
     173: return

  public void testListLocksWaiting() throws java.lang.Exception;
    Code:
       0: lconst_1
       1: invokestatic  #131                // Method createExclusiveLockProcedure:(J)Lorg/apache/hadoop/hbase/master/locking/LockProcedure;
       4: astore_1
       5: aload_0
       6: getfield      #8                  // Field queue:Lorg/apache/hadoop/hbase/master/procedure/MasterProcedureScheduler;
       9: aload_1
      10: ldc           #159                // String ns4
      12: ldc           #160                // String table4
      14: invokestatic  #57                 // Method org/apache/hadoop/hbase/TableName.valueOf:(Ljava/lang/String;Ljava/lang/String;)Lorg/apache/hadoop/hbase/TableName;
      17: invokevirtual #30                 // Method org/apache/hadoop/hbase/master/procedure/MasterProcedureScheduler.waitTableExclusiveLock:(Lorg/apache/hadoop/hbase/procedure2/Procedure;Lorg/apache/hadoop/hbase/TableName;)Z
      20: pop
      21: ldc2_w        #44                 // long 2l
      24: invokestatic  #161                // Method createSharedLockProcedure:(J)Lorg/apache/hadoop/hbase/master/locking/LockProcedure;
      27: astore_2
      28: aload_0
      29: getfield      #8                  // Field queue:Lorg/apache/hadoop/hbase/master/procedure/MasterProcedureScheduler;
      32: aload_2
      33: ldc           #159                // String ns4
      35: ldc           #160                // String table4
      37: invokestatic  #57                 // Method org/apache/hadoop/hbase/TableName.valueOf:(Ljava/lang/String;Ljava/lang/String;)Lorg/apache/hadoop/hbase/TableName;
      40: invokevirtual #42                 // Method org/apache/hadoop/hbase/master/procedure/MasterProcedureScheduler.waitTableSharedLock:(Lorg/apache/hadoop/hbase/procedure2/Procedure;Lorg/apache/hadoop/hbase/TableName;)Z
      43: pop
      44: ldc2_w        #46                 // long 3l
      47: invokestatic  #131                // Method createExclusiveLockProcedure:(J)Lorg/apache/hadoop/hbase/master/locking/LockProcedure;
      50: astore_3
      51: aload_0
      52: getfield      #8                  // Field queue:Lorg/apache/hadoop/hbase/master/procedure/MasterProcedureScheduler;
      55: aload_3
      56: ldc           #159                // String ns4
      58: ldc           #160                // String table4
      60: invokestatic  #57                 // Method org/apache/hadoop/hbase/TableName.valueOf:(Ljava/lang/String;Ljava/lang/String;)Lorg/apache/hadoop/hbase/TableName;
      63: invokevirtual #30                 // Method org/apache/hadoop/hbase/master/procedure/MasterProcedureScheduler.waitTableExclusiveLock:(Lorg/apache/hadoop/hbase/procedure2/Procedure;Lorg/apache/hadoop/hbase/TableName;)Z
      66: pop
      67: aload_0
      68: getfield      #8                  // Field queue:Lorg/apache/hadoop/hbase/master/procedure/MasterProcedureScheduler;
      71: invokevirtual #135                // Method org/apache/hadoop/hbase/master/procedure/MasterProcedureScheduler.getLocks:()Ljava/util/List;
      74: astore        4
      76: ldc2_w        #44                 // long 2l
      79: aload         4
      81: invokeinterface #136,  1          // InterfaceMethod java/util/List.size:()I
      86: i2l
      87: invokestatic  #24                 // Method org/junit/Assert.assertEquals:(JJ)V
      90: aload         4
      92: iconst_0
      93: invokeinterface #137,  2          // InterfaceMethod java/util/List.get:(I)Ljava/lang/Object;
      98: checkcast     #138                // class org/apache/hadoop/hbase/procedure2/LockedResource
     101: astore        5
     103: aload         5
     105: getstatic     #144                // Field org/apache/hadoop/hbase/procedure2/LockedResourceType.NAMESPACE:Lorg/apache/hadoop/hbase/procedure2/LockedResourceType;
     108: ldc           #159                // String ns4
     110: invokestatic  #140                // Method assertLockResource:(Lorg/apache/hadoop/hbase/procedure2/LockedResource;Lorg/apache/hadoop/hbase/procedure2/LockedResourceType;Ljava/lang/String;)V
     113: aload         5
     115: iconst_1
     116: invokestatic  #148                // Method assertSharedLock:(Lorg/apache/hadoop/hbase/procedure2/LockedResource;I)V
     119: aload         5
     121: invokevirtual #142                // Method org/apache/hadoop/hbase/procedure2/LockedResource.getWaitingProcedures:()Ljava/util/List;
     124: invokeinterface #143,  1          // InterfaceMethod java/util/List.isEmpty:()Z
     129: invokestatic  #28                 // Method org/junit/Assert.assertTrue:(Z)V
     132: aload         4
     134: iconst_1
     135: invokeinterface #137,  2          // InterfaceMethod java/util/List.get:(I)Ljava/lang/Object;
     140: checkcast     #138                // class org/apache/hadoop/hbase/procedure2/LockedResource
     143: astore        6
     145: aload         6
     147: getstatic     #145                // Field org/apache/hadoop/hbase/procedure2/LockedResourceType.TABLE:Lorg/apache/hadoop/hbase/procedure2/LockedResourceType;
     150: ldc           #162                // String ns4:table4
     152: invokestatic  #140                // Method assertLockResource:(Lorg/apache/hadoop/hbase/procedure2/LockedResource;Lorg/apache/hadoop/hbase/procedure2/LockedResourceType;Ljava/lang/String;)V
     155: aload         6
     157: aload_1
     158: invokestatic  #141                // Method assertExclusiveLock:(Lorg/apache/hadoop/hbase/procedure2/LockedResource;Lorg/apache/hadoop/hbase/procedure2/Procedure;)V
     161: aload         6
     163: invokevirtual #142                // Method org/apache/hadoop/hbase/procedure2/LockedResource.getWaitingProcedures:()Ljava/util/List;
     166: astore        7
     168: ldc2_w        #44                 // long 2l
     171: aload         7
     173: invokeinterface #136,  1          // InterfaceMethod java/util/List.size:()I
     178: i2l
     179: invokestatic  #24                 // Method org/junit/Assert.assertEquals:(JJ)V
     182: aload         7
     184: iconst_0
     185: invokeinterface #137,  2          // InterfaceMethod java/util/List.get:(I)Ljava/lang/Object;
     190: checkcast     #110                // class org/apache/hadoop/hbase/master/locking/LockProcedure
     193: astore        8
     195: getstatic     #125                // Field org/apache/hadoop/hbase/procedure2/LockType.SHARED:Lorg/apache/hadoop/hbase/procedure2/LockType;
     198: aload         8
     200: invokevirtual #163                // Method org/apache/hadoop/hbase/master/locking/LockProcedure.getType:()Lorg/apache/hadoop/hbase/procedure2/LockType;
     203: invokestatic  #39                 // Method org/junit/Assert.assertEquals:(Ljava/lang/Object;Ljava/lang/Object;)V
     206: aload_2
     207: aload         8
     209: invokestatic  #39                 // Method org/junit/Assert.assertEquals:(Ljava/lang/Object;Ljava/lang/Object;)V
     212: aload         7
     214: iconst_1
     215: invokeinterface #137,  2          // InterfaceMethod java/util/List.get:(I)Ljava/lang/Object;
     220: checkcast     #110                // class org/apache/hadoop/hbase/master/locking/LockProcedure
     223: astore        9
     225: getstatic     #123                // Field org/apache/hadoop/hbase/procedure2/LockType.EXCLUSIVE:Lorg/apache/hadoop/hbase/procedure2/LockType;
     228: aload         9
     230: invokevirtual #163                // Method org/apache/hadoop/hbase/master/locking/LockProcedure.getType:()Lorg/apache/hadoop/hbase/procedure2/LockType;
     233: invokestatic  #39                 // Method org/junit/Assert.assertEquals:(Ljava/lang/Object;Ljava/lang/Object;)V
     236: aload_3
     237: aload         9
     239: invokestatic  #39                 // Method org/junit/Assert.assertEquals:(Ljava/lang/Object;Ljava/lang/Object;)V
     242: return

  public void testAcquireSharedLockWhileParentHoldingExclusiveLock();
    Code:
       0: aload_0
       1: getfield      #4                  // Field name:Lorg/junit/rules/TestName;
       4: invokevirtual #36                 // Method org/junit/rules/TestName.getMethodName:()Ljava/lang/String;
       7: invokestatic  #19                 // Method org/apache/hadoop/hbase/TableName.valueOf:(Ljava/lang/String;)Lorg/apache/hadoop/hbase/TableName;
      10: astore_1
      11: aload_1
      12: invokestatic  #65                 // Method org/apache/hadoop/hbase/client/RegionInfoBuilder.newBuilder:(Lorg/apache/hadoop/hbase/TableName;)Lorg/apache/hadoop/hbase/client/RegionInfoBuilder;
      15: invokevirtual #71                 // Method org/apache/hadoop/hbase/client/RegionInfoBuilder.build:()Lorg/apache/hadoop/hbase/client/RegionInfo;
      18: astore_2
      19: new           #20                 // class org/apache/hadoop/hbase/master/procedure/TestMasterProcedureScheduler$TestTableProcedure
      22: dup
      23: lconst_1
      24: aload_1
      25: getstatic     #21                 // Field org/apache/hadoop/hbase/master/procedure/TableProcedureInterface$TableOperationType.EDIT:Lorg/apache/hadoop/hbase/master/procedure/TableProcedureInterface$TableOperationType;
      28: invokespecial #22                 // Method org/apache/hadoop/hbase/master/procedure/TestMasterProcedureScheduler$TestTableProcedure."<init>":(JLorg/apache/hadoop/hbase/TableName;Lorg/apache/hadoop/hbase/master/procedure/TableProcedureInterface$TableOperationType;)V
      31: astore_3
      32: new           #72                 // class org/apache/hadoop/hbase/master/procedure/TestMasterProcedureScheduler$TestRegionProcedure
      35: dup
      36: lconst_1
      37: ldc2_w        #44                 // long 2l
      40: aload_1
      41: getstatic     #86                 // Field org/apache/hadoop/hbase/master/procedure/TableProcedureInterface$TableOperationType.REGION_EDIT:Lorg/apache/hadoop/hbase/master/procedure/TableProcedureInterface$TableOperationType;
      44: iconst_1
      45: anewarray     #74                 // class org/apache/hadoop/hbase/client/RegionInfo
      48: dup
      49: iconst_0
      50: aload_2
      51: aastore
      52: invokespecial #87                 // Method org/apache/hadoop/hbase/master/procedure/TestMasterProcedureScheduler$TestRegionProcedure."<init>":(JJLorg/apache/hadoop/hbase/TableName;Lorg/apache/hadoop/hbase/master/procedure/TableProcedureInterface$TableOperationType;[Lorg/apache/hadoop/hbase/client/RegionInfo;)V
      55: astore        4
      57: aload_0
      58: getfield      #8                  // Field queue:Lorg/apache/hadoop/hbase/master/procedure/MasterProcedureScheduler;
      61: aload_3
      62: invokevirtual #23                 // Method org/apache/hadoop/hbase/master/procedure/MasterProcedureScheduler.addBack:(Lorg/apache/hadoop/hbase/procedure2/Procedure;)V
      65: aload_3
      66: aload_0
      67: getfield      #8                  // Field queue:Lorg/apache/hadoop/hbase/master/procedure/MasterProcedureScheduler;
      70: invokevirtual #27                 // Method org/apache/hadoop/hbase/master/procedure/MasterProcedureScheduler.poll:()Lorg/apache/hadoop/hbase/procedure2/Procedure;
      73: invokestatic  #164                // Method org/junit/Assert.assertSame:(Ljava/lang/Object;Ljava/lang/Object;)V
      76: aload_0
      77: getfield      #8                  // Field queue:Lorg/apache/hadoop/hbase/master/procedure/MasterProcedureScheduler;
      80: aload_3
      81: aload_1
      82: invokevirtual #30                 // Method org/apache/hadoop/hbase/master/procedure/MasterProcedureScheduler.waitTableExclusiveLock:(Lorg/apache/hadoop/hbase/procedure2/Procedure;Lorg/apache/hadoop/hbase/TableName;)Z
      85: invokestatic  #37                 // Method org/junit/Assert.assertFalse:(Z)V
      88: aload_0
      89: getfield      #8                  // Field queue:Lorg/apache/hadoop/hbase/master/procedure/MasterProcedureScheduler;
      92: aload         4
      94: invokevirtual #88                 // Method org/apache/hadoop/hbase/master/procedure/MasterProcedureScheduler.addFront:(Lorg/apache/hadoop/hbase/procedure2/Procedure;)V
      97: aload         4
      99: aload_0
     100: getfield      #8                  // Field queue:Lorg/apache/hadoop/hbase/master/procedure/MasterProcedureScheduler;
     103: invokevirtual #27                 // Method org/apache/hadoop/hbase/master/procedure/MasterProcedureScheduler.poll:()Lorg/apache/hadoop/hbase/procedure2/Procedure;
     106: invokestatic  #164                // Method org/junit/Assert.assertSame:(Ljava/lang/Object;Ljava/lang/Object;)V
     109: aload_0
     110: getfield      #8                  // Field queue:Lorg/apache/hadoop/hbase/master/procedure/MasterProcedureScheduler;
     113: aload         4
     115: aload_2
     116: invokevirtual #76                 // Method org/apache/hadoop/hbase/master/procedure/MasterProcedureScheduler.waitRegion:(Lorg/apache/hadoop/hbase/procedure2/Procedure;Lorg/apache/hadoop/hbase/client/RegionInfo;)Z
     119: invokestatic  #37                 // Method org/junit/Assert.assertFalse:(Z)V
     122: aload_0
     123: getfield      #8                  // Field queue:Lorg/apache/hadoop/hbase/master/procedure/MasterProcedureScheduler;
     126: aload         4
     128: aload_2
     129: invokevirtual #77                 // Method org/apache/hadoop/hbase/master/procedure/MasterProcedureScheduler.wakeRegion:(Lorg/apache/hadoop/hbase/procedure2/Procedure;Lorg/apache/hadoop/hbase/client/RegionInfo;)V
     132: aload_0
     133: getfield      #8                  // Field queue:Lorg/apache/hadoop/hbase/master/procedure/MasterProcedureScheduler;
     136: aload_3
     137: aload_1
     138: invokevirtual #31                 // Method org/apache/hadoop/hbase/master/procedure/MasterProcedureScheduler.wakeTableExclusiveLock:(Lorg/apache/hadoop/hbase/procedure2/Procedure;Lorg/apache/hadoop/hbase/TableName;)V
     141: return

  static {};
    Code:
       0: ldc           #165                // class org/apache/hadoop/hbase/master/procedure/TestMasterProcedureScheduler
       2: invokestatic  #166                // Method org/apache/hadoop/hbase/HBaseClassTestRule.forClass:(Ljava/lang/Class;)Lorg/apache/hadoop/hbase/HBaseClassTestRule;
       5: putstatic     #167                // Field CLASS_RULE:Lorg/apache/hadoop/hbase/HBaseClassTestRule;
       8: ldc           #165                // class org/apache/hadoop/hbase/master/procedure/TestMasterProcedureScheduler
      10: invokestatic  #168                // Method org/slf4j/LoggerFactory.getLogger:(Ljava/lang/Class;)Lorg/slf4j/Logger;
      13: putstatic     #99                 // Field LOG:Lorg/slf4j/Logger;
      16: return
}
