Compiled from "TestCellBuilder.java"
public class org.apache.hadoop.hbase.TestCellBuilder {
  public static final org.apache.hadoop.hbase.HBaseClassTestRule CLASS_RULE;

  public org.apache.hadoop.hbase.TestCellBuilder();
    Code:
       0: aload_0
       1: invokespecial #1                  // Method java/lang/Object."<init>":()V
       4: return

  public void testCellBuilderWithDeepCopy();
    Code:
       0: iconst_1
       1: newarray       byte
       3: dup
       4: iconst_0
       5: bipush        87
       7: bastore
       8: astore_1
       9: iconst_1
      10: newarray       byte
      12: dup
      13: iconst_0
      14: bipush        87
      16: bastore
      17: astore_2
      18: iconst_1
      19: newarray       byte
      21: dup
      22: iconst_0
      23: bipush        87
      25: bastore
      26: astore_3
      27: iconst_1
      28: newarray       byte
      30: dup
      31: iconst_0
      32: bipush        87
      34: bastore
      35: astore        4
      37: getstatic     #3                  // Field org/apache/hadoop/hbase/CellBuilderType.DEEP_COPY:Lorg/apache/hadoop/hbase/CellBuilderType;
      40: invokestatic  #4                  // Method org/apache/hadoop/hbase/CellBuilderFactory.create:(Lorg/apache/hadoop/hbase/CellBuilderType;)Lorg/apache/hadoop/hbase/CellBuilder;
      43: aload_1
      44: invokeinterface #5,  2            // InterfaceMethod org/apache/hadoop/hbase/CellBuilder.setRow:([B)Lorg/apache/hadoop/hbase/CellBuilder;
      49: aload_2
      50: invokeinterface #6,  2            // InterfaceMethod org/apache/hadoop/hbase/CellBuilder.setFamily:([B)Lorg/apache/hadoop/hbase/CellBuilder;
      55: aload_3
      56: invokeinterface #7,  2            // InterfaceMethod org/apache/hadoop/hbase/CellBuilder.setQualifier:([B)Lorg/apache/hadoop/hbase/CellBuilder;
      61: getstatic     #8                  // Field org/apache/hadoop/hbase/Cell$Type.Put:Lorg/apache/hadoop/hbase/Cell$Type;
      64: invokeinterface #9,  2            // InterfaceMethod org/apache/hadoop/hbase/CellBuilder.setType:(Lorg/apache/hadoop/hbase/Cell$Type;)Lorg/apache/hadoop/hbase/CellBuilder;
      69: aload         4
      71: invokeinterface #10,  2           // InterfaceMethod org/apache/hadoop/hbase/CellBuilder.setValue:([B)Lorg/apache/hadoop/hbase/CellBuilder;
      76: invokeinterface #11,  1           // InterfaceMethod org/apache/hadoop/hbase/CellBuilder.build:()Lorg/apache/hadoop/hbase/Cell;
      81: astore        5
      83: aload_1
      84: iconst_0
      85: bipush        100
      87: bastore
      88: aload_2
      89: iconst_0
      90: bipush        100
      92: bastore
      93: aload_3
      94: iconst_0
      95: bipush        100
      97: bastore
      98: aload         4
     100: iconst_0
     101: bipush        100
     103: bastore
     104: ldc2_w        #12                 // long 87l
     107: aload         5
     109: invokeinterface #14,  1           // InterfaceMethod org/apache/hadoop/hbase/Cell.getRowArray:()[B
     114: aload         5
     116: invokeinterface #15,  1           // InterfaceMethod org/apache/hadoop/hbase/Cell.getRowOffset:()I
     121: baload
     122: i2l
     123: invokestatic  #16                 // Method org/junit/Assert.assertEquals:(JJ)V
     126: ldc2_w        #12                 // long 87l
     129: aload         5
     131: invokeinterface #17,  1           // InterfaceMethod org/apache/hadoop/hbase/Cell.getFamilyArray:()[B
     136: aload         5
     138: invokeinterface #18,  1           // InterfaceMethod org/apache/hadoop/hbase/Cell.getFamilyOffset:()I
     143: baload
     144: i2l
     145: invokestatic  #16                 // Method org/junit/Assert.assertEquals:(JJ)V
     148: ldc2_w        #12                 // long 87l
     151: aload         5
     153: invokeinterface #19,  1           // InterfaceMethod org/apache/hadoop/hbase/Cell.getQualifierArray:()[B
     158: aload         5
     160: invokeinterface #20,  1           // InterfaceMethod org/apache/hadoop/hbase/Cell.getQualifierOffset:()I
     165: baload
     166: i2l
     167: invokestatic  #16                 // Method org/junit/Assert.assertEquals:(JJ)V
     170: ldc2_w        #12                 // long 87l
     173: aload         5
     175: invokeinterface #21,  1           // InterfaceMethod org/apache/hadoop/hbase/Cell.getValueArray:()[B
     180: aload         5
     182: invokeinterface #22,  1           // InterfaceMethod org/apache/hadoop/hbase/Cell.getValueOffset:()I
     187: baload
     188: i2l
     189: invokestatic  #16                 // Method org/junit/Assert.assertEquals:(JJ)V
     192: return

  public void testCellBuilderWithShallowCopy();
    Code:
       0: iconst_1
       1: newarray       byte
       3: dup
       4: iconst_0
       5: bipush        87
       7: bastore
       8: astore_1
       9: iconst_1
      10: newarray       byte
      12: dup
      13: iconst_0
      14: bipush        87
      16: bastore
      17: astore_2
      18: iconst_1
      19: newarray       byte
      21: dup
      22: iconst_0
      23: bipush        87
      25: bastore
      26: astore_3
      27: iconst_1
      28: newarray       byte
      30: dup
      31: iconst_0
      32: bipush        87
      34: bastore
      35: astore        4
      37: getstatic     #23                 // Field org/apache/hadoop/hbase/CellBuilderType.SHALLOW_COPY:Lorg/apache/hadoop/hbase/CellBuilderType;
      40: invokestatic  #4                  // Method org/apache/hadoop/hbase/CellBuilderFactory.create:(Lorg/apache/hadoop/hbase/CellBuilderType;)Lorg/apache/hadoop/hbase/CellBuilder;
      43: aload_1
      44: invokeinterface #5,  2            // InterfaceMethod org/apache/hadoop/hbase/CellBuilder.setRow:([B)Lorg/apache/hadoop/hbase/CellBuilder;
      49: aload_2
      50: invokeinterface #6,  2            // InterfaceMethod org/apache/hadoop/hbase/CellBuilder.setFamily:([B)Lorg/apache/hadoop/hbase/CellBuilder;
      55: aload_3
      56: invokeinterface #7,  2            // InterfaceMethod org/apache/hadoop/hbase/CellBuilder.setQualifier:([B)Lorg/apache/hadoop/hbase/CellBuilder;
      61: getstatic     #8                  // Field org/apache/hadoop/hbase/Cell$Type.Put:Lorg/apache/hadoop/hbase/Cell$Type;
      64: invokeinterface #9,  2            // InterfaceMethod org/apache/hadoop/hbase/CellBuilder.setType:(Lorg/apache/hadoop/hbase/Cell$Type;)Lorg/apache/hadoop/hbase/CellBuilder;
      69: aload         4
      71: invokeinterface #10,  2           // InterfaceMethod org/apache/hadoop/hbase/CellBuilder.setValue:([B)Lorg/apache/hadoop/hbase/CellBuilder;
      76: invokeinterface #11,  1           // InterfaceMethod org/apache/hadoop/hbase/CellBuilder.build:()Lorg/apache/hadoop/hbase/Cell;
      81: astore        5
      83: aload_1
      84: iconst_0
      85: bipush        100
      87: bastore
      88: aload_2
      89: iconst_0
      90: bipush        100
      92: bastore
      93: aload_3
      94: iconst_0
      95: bipush        100
      97: bastore
      98: aload         4
     100: iconst_0
     101: bipush        100
     103: bastore
     104: ldc2_w        #24                 // long 100l
     107: aload         5
     109: invokeinterface #14,  1           // InterfaceMethod org/apache/hadoop/hbase/Cell.getRowArray:()[B
     114: aload         5
     116: invokeinterface #15,  1           // InterfaceMethod org/apache/hadoop/hbase/Cell.getRowOffset:()I
     121: baload
     122: i2l
     123: invokestatic  #16                 // Method org/junit/Assert.assertEquals:(JJ)V
     126: ldc2_w        #24                 // long 100l
     129: aload         5
     131: invokeinterface #17,  1           // InterfaceMethod org/apache/hadoop/hbase/Cell.getFamilyArray:()[B
     136: aload         5
     138: invokeinterface #18,  1           // InterfaceMethod org/apache/hadoop/hbase/Cell.getFamilyOffset:()I
     143: baload
     144: i2l
     145: invokestatic  #16                 // Method org/junit/Assert.assertEquals:(JJ)V
     148: ldc2_w        #24                 // long 100l
     151: aload         5
     153: invokeinterface #19,  1           // InterfaceMethod org/apache/hadoop/hbase/Cell.getQualifierArray:()[B
     158: aload         5
     160: invokeinterface #20,  1           // InterfaceMethod org/apache/hadoop/hbase/Cell.getQualifierOffset:()I
     165: baload
     166: i2l
     167: invokestatic  #16                 // Method org/junit/Assert.assertEquals:(JJ)V
     170: ldc2_w        #24                 // long 100l
     173: aload         5
     175: invokeinterface #21,  1           // InterfaceMethod org/apache/hadoop/hbase/Cell.getValueArray:()[B
     180: aload         5
     182: invokeinterface #22,  1           // InterfaceMethod org/apache/hadoop/hbase/Cell.getValueOffset:()I
     187: baload
     188: i2l
     189: invokestatic  #16                 // Method org/junit/Assert.assertEquals:(JJ)V
     192: return

  public void testExtendedCellBuilderWithShallowCopy();
    Code:
       0: iconst_1
       1: newarray       byte
       3: dup
       4: iconst_0
       5: bipush        87
       7: bastore
       8: astore_1
       9: iconst_1
      10: newarray       byte
      12: dup
      13: iconst_0
      14: bipush        87
      16: bastore
      17: astore_2
      18: iconst_1
      19: newarray       byte
      21: dup
      22: iconst_0
      23: bipush        87
      25: bastore
      26: astore_3
      27: iconst_1
      28: newarray       byte
      30: dup
      31: iconst_0
      32: bipush        87
      34: bastore
      35: astore        4
      37: iconst_1
      38: newarray       byte
      40: dup
      41: iconst_0
      42: bipush        87
      44: bastore
      45: astore        5
      47: ldc2_w        #26                 // long 999l
      50: lstore        6
      52: getstatic     #23                 // Field org/apache/hadoop/hbase/CellBuilderType.SHALLOW_COPY:Lorg/apache/hadoop/hbase/CellBuilderType;
      55: invokestatic  #28                 // Method org/apache/hadoop/hbase/ExtendedCellBuilderFactory.create:(Lorg/apache/hadoop/hbase/CellBuilderType;)Lorg/apache/hadoop/hbase/ExtendedCellBuilder;
      58: aload_1
      59: invokeinterface #29,  2           // InterfaceMethod org/apache/hadoop/hbase/ExtendedCellBuilder.setRow:([B)Lorg/apache/hadoop/hbase/ExtendedCellBuilder;
      64: aload_2
      65: invokeinterface #30,  2           // InterfaceMethod org/apache/hadoop/hbase/ExtendedCellBuilder.setFamily:([B)Lorg/apache/hadoop/hbase/ExtendedCellBuilder;
      70: aload_3
      71: invokeinterface #31,  2           // InterfaceMethod org/apache/hadoop/hbase/ExtendedCellBuilder.setQualifier:([B)Lorg/apache/hadoop/hbase/ExtendedCellBuilder;
      76: getstatic     #32                 // Field org/apache/hadoop/hbase/KeyValue$Type.Put:Lorg/apache/hadoop/hbase/KeyValue$Type;
      79: invokevirtual #33                 // Method org/apache/hadoop/hbase/KeyValue$Type.getCode:()B
      82: invokeinterface #34,  2           // InterfaceMethod org/apache/hadoop/hbase/ExtendedCellBuilder.setType:(B)Lorg/apache/hadoop/hbase/ExtendedCellBuilder;
      87: aload         4
      89: invokeinterface #35,  2           // InterfaceMethod org/apache/hadoop/hbase/ExtendedCellBuilder.setValue:([B)Lorg/apache/hadoop/hbase/ExtendedCellBuilder;
      94: aload         5
      96: invokeinterface #36,  2           // InterfaceMethod org/apache/hadoop/hbase/ExtendedCellBuilder.setTags:([B)Lorg/apache/hadoop/hbase/ExtendedCellBuilder;
     101: lload         6
     103: invokeinterface #37,  3           // InterfaceMethod org/apache/hadoop/hbase/ExtendedCellBuilder.setSequenceId:(J)Lorg/apache/hadoop/hbase/ExtendedCellBuilder;
     108: invokeinterface #38,  1           // InterfaceMethod org/apache/hadoop/hbase/ExtendedCellBuilder.build:()Lorg/apache/hadoop/hbase/ExtendedCell;
     113: astore        8
     115: aload_1
     116: iconst_0
     117: bipush        100
     119: bastore
     120: aload_2
     121: iconst_0
     122: bipush        100
     124: bastore
     125: aload_3
     126: iconst_0
     127: bipush        100
     129: bastore
     130: aload         4
     132: iconst_0
     133: bipush        100
     135: bastore
     136: aload         5
     138: iconst_0
     139: bipush        100
     141: bastore
     142: ldc2_w        #24                 // long 100l
     145: aload         8
     147: invokeinterface #14,  1           // InterfaceMethod org/apache/hadoop/hbase/Cell.getRowArray:()[B
     152: aload         8
     154: invokeinterface #15,  1           // InterfaceMethod org/apache/hadoop/hbase/Cell.getRowOffset:()I
     159: baload
     160: i2l
     161: invokestatic  #16                 // Method org/junit/Assert.assertEquals:(JJ)V
     164: ldc2_w        #24                 // long 100l
     167: aload         8
     169: invokeinterface #17,  1           // InterfaceMethod org/apache/hadoop/hbase/Cell.getFamilyArray:()[B
     174: aload         8
     176: invokeinterface #18,  1           // InterfaceMethod org/apache/hadoop/hbase/Cell.getFamilyOffset:()I
     181: baload
     182: i2l
     183: invokestatic  #16                 // Method org/junit/Assert.assertEquals:(JJ)V
     186: ldc2_w        #24                 // long 100l
     189: aload         8
     191: invokeinterface #19,  1           // InterfaceMethod org/apache/hadoop/hbase/Cell.getQualifierArray:()[B
     196: aload         8
     198: invokeinterface #20,  1           // InterfaceMethod org/apache/hadoop/hbase/Cell.getQualifierOffset:()I
     203: baload
     204: i2l
     205: invokestatic  #16                 // Method org/junit/Assert.assertEquals:(JJ)V
     208: ldc2_w        #24                 // long 100l
     211: aload         8
     213: invokeinterface #21,  1           // InterfaceMethod org/apache/hadoop/hbase/Cell.getValueArray:()[B
     218: aload         8
     220: invokeinterface #22,  1           // InterfaceMethod org/apache/hadoop/hbase/Cell.getValueOffset:()I
     225: baload
     226: i2l
     227: invokestatic  #16                 // Method org/junit/Assert.assertEquals:(JJ)V
     230: ldc2_w        #24                 // long 100l
     233: aload         8
     235: invokeinterface #39,  1           // InterfaceMethod org/apache/hadoop/hbase/Cell.getTagsArray:()[B
     240: aload         8
     242: invokeinterface #40,  1           // InterfaceMethod org/apache/hadoop/hbase/Cell.getTagsOffset:()I
     247: baload
     248: i2l
     249: invokestatic  #16                 // Method org/junit/Assert.assertEquals:(JJ)V
     252: lload         6
     254: aload         8
     256: invokeinterface #41,  1           // InterfaceMethod org/apache/hadoop/hbase/Cell.getSequenceId:()J
     261: invokestatic  #16                 // Method org/junit/Assert.assertEquals:(JJ)V
     264: return

  public void testExtendedCellBuilderWithDeepCopy();
    Code:
       0: iconst_1
       1: newarray       byte
       3: dup
       4: iconst_0
       5: bipush        87
       7: bastore
       8: astore_1
       9: iconst_1
      10: newarray       byte
      12: dup
      13: iconst_0
      14: bipush        87
      16: bastore
      17: astore_2
      18: iconst_1
      19: newarray       byte
      21: dup
      22: iconst_0
      23: bipush        87
      25: bastore
      26: astore_3
      27: iconst_1
      28: newarray       byte
      30: dup
      31: iconst_0
      32: bipush        87
      34: bastore
      35: astore        4
      37: iconst_1
      38: newarray       byte
      40: dup
      41: iconst_0
      42: bipush        87
      44: bastore
      45: astore        5
      47: ldc2_w        #26                 // long 999l
      50: lstore        6
      52: getstatic     #3                  // Field org/apache/hadoop/hbase/CellBuilderType.DEEP_COPY:Lorg/apache/hadoop/hbase/CellBuilderType;
      55: invokestatic  #28                 // Method org/apache/hadoop/hbase/ExtendedCellBuilderFactory.create:(Lorg/apache/hadoop/hbase/CellBuilderType;)Lorg/apache/hadoop/hbase/ExtendedCellBuilder;
      58: aload_1
      59: invokeinterface #29,  2           // InterfaceMethod org/apache/hadoop/hbase/ExtendedCellBuilder.setRow:([B)Lorg/apache/hadoop/hbase/ExtendedCellBuilder;
      64: aload_2
      65: invokeinterface #30,  2           // InterfaceMethod org/apache/hadoop/hbase/ExtendedCellBuilder.setFamily:([B)Lorg/apache/hadoop/hbase/ExtendedCellBuilder;
      70: aload_3
      71: invokeinterface #31,  2           // InterfaceMethod org/apache/hadoop/hbase/ExtendedCellBuilder.setQualifier:([B)Lorg/apache/hadoop/hbase/ExtendedCellBuilder;
      76: getstatic     #32                 // Field org/apache/hadoop/hbase/KeyValue$Type.Put:Lorg/apache/hadoop/hbase/KeyValue$Type;
      79: invokevirtual #33                 // Method org/apache/hadoop/hbase/KeyValue$Type.getCode:()B
      82: invokeinterface #34,  2           // InterfaceMethod org/apache/hadoop/hbase/ExtendedCellBuilder.setType:(B)Lorg/apache/hadoop/hbase/ExtendedCellBuilder;
      87: aload         4
      89: invokeinterface #35,  2           // InterfaceMethod org/apache/hadoop/hbase/ExtendedCellBuilder.setValue:([B)Lorg/apache/hadoop/hbase/ExtendedCellBuilder;
      94: aload         5
      96: invokeinterface #36,  2           // InterfaceMethod org/apache/hadoop/hbase/ExtendedCellBuilder.setTags:([B)Lorg/apache/hadoop/hbase/ExtendedCellBuilder;
     101: lload         6
     103: invokeinterface #37,  3           // InterfaceMethod org/apache/hadoop/hbase/ExtendedCellBuilder.setSequenceId:(J)Lorg/apache/hadoop/hbase/ExtendedCellBuilder;
     108: invokeinterface #38,  1           // InterfaceMethod org/apache/hadoop/hbase/ExtendedCellBuilder.build:()Lorg/apache/hadoop/hbase/ExtendedCell;
     113: astore        8
     115: aload_1
     116: iconst_0
     117: bipush        100
     119: bastore
     120: aload_2
     121: iconst_0
     122: bipush        100
     124: bastore
     125: aload_3
     126: iconst_0
     127: bipush        100
     129: bastore
     130: aload         4
     132: iconst_0
     133: bipush        100
     135: bastore
     136: aload         5
     138: iconst_0
     139: bipush        100
     141: bastore
     142: ldc2_w        #12                 // long 87l
     145: aload         8
     147: invokeinterface #14,  1           // InterfaceMethod org/apache/hadoop/hbase/Cell.getRowArray:()[B
     152: aload         8
     154: invokeinterface #15,  1           // InterfaceMethod org/apache/hadoop/hbase/Cell.getRowOffset:()I
     159: baload
     160: i2l
     161: invokestatic  #16                 // Method org/junit/Assert.assertEquals:(JJ)V
     164: ldc2_w        #12                 // long 87l
     167: aload         8
     169: invokeinterface #17,  1           // InterfaceMethod org/apache/hadoop/hbase/Cell.getFamilyArray:()[B
     174: aload         8
     176: invokeinterface #18,  1           // InterfaceMethod org/apache/hadoop/hbase/Cell.getFamilyOffset:()I
     181: baload
     182: i2l
     183: invokestatic  #16                 // Method org/junit/Assert.assertEquals:(JJ)V
     186: ldc2_w        #12                 // long 87l
     189: aload         8
     191: invokeinterface #19,  1           // InterfaceMethod org/apache/hadoop/hbase/Cell.getQualifierArray:()[B
     196: aload         8
     198: invokeinterface #20,  1           // InterfaceMethod org/apache/hadoop/hbase/Cell.getQualifierOffset:()I
     203: baload
     204: i2l
     205: invokestatic  #16                 // Method org/junit/Assert.assertEquals:(JJ)V
     208: ldc2_w        #12                 // long 87l
     211: aload         8
     213: invokeinterface #21,  1           // InterfaceMethod org/apache/hadoop/hbase/Cell.getValueArray:()[B
     218: aload         8
     220: invokeinterface #22,  1           // InterfaceMethod org/apache/hadoop/hbase/Cell.getValueOffset:()I
     225: baload
     226: i2l
     227: invokestatic  #16                 // Method org/junit/Assert.assertEquals:(JJ)V
     230: ldc2_w        #12                 // long 87l
     233: aload         8
     235: invokeinterface #39,  1           // InterfaceMethod org/apache/hadoop/hbase/Cell.getTagsArray:()[B
     240: aload         8
     242: invokeinterface #40,  1           // InterfaceMethod org/apache/hadoop/hbase/Cell.getTagsOffset:()I
     247: baload
     248: i2l
     249: invokestatic  #16                 // Method org/junit/Assert.assertEquals:(JJ)V
     252: lload         6
     254: aload         8
     256: invokeinterface #41,  1           // InterfaceMethod org/apache/hadoop/hbase/Cell.getSequenceId:()J
     261: invokestatic  #16                 // Method org/junit/Assert.assertEquals:(JJ)V
     264: return

  static {};
    Code:
       0: ldc           #2                  // class org/apache/hadoop/hbase/TestCellBuilder
       2: invokestatic  #42                 // Method org/apache/hadoop/hbase/HBaseClassTestRule.forClass:(Ljava/lang/Class;)Lorg/apache/hadoop/hbase/HBaseClassTestRule;
       5: putstatic     #43                 // Field CLASS_RULE:Lorg/apache/hadoop/hbase/HBaseClassTestRule;
       8: return
}
