Compiled from "TestActiveMasterManager.java"
public class org.apache.hadoop.hbase.master.TestActiveMasterManager {
  public static final org.apache.hadoop.hbase.HBaseClassTestRule CLASS_RULE;

  public org.apache.hadoop.hbase.master.TestActiveMasterManager();
    Code:
       0: aload_0
       1: invokespecial #2                  // Method java/lang/Object."<init>":()V
       4: return

  public static void setUpBeforeClass() throws java.lang.Exception;
    Code:
       0: getstatic     #3                  // Field TEST_UTIL:Lorg/apache/hadoop/hbase/HBaseTestingUtility;
       3: invokevirtual #4                  // Method org/apache/hadoop/hbase/HBaseTestingUtility.startMiniZKCluster:()Lorg/apache/hadoop/hbase/zookeeper/MiniZooKeeperCluster;
       6: pop
       7: return

  public static void tearDownAfterClass() throws java.lang.Exception;
    Code:
       0: getstatic     #3                  // Field TEST_UTIL:Lorg/apache/hadoop/hbase/HBaseTestingUtility;
       3: invokevirtual #5                  // Method org/apache/hadoop/hbase/HBaseTestingUtility.shutdownMiniZKCluster:()V
       6: return

  public void testRestartMaster() throws java.io.IOException, org.apache.zookeeper.KeeperException;
    Code:
       0: new           #6                  // class org/apache/hadoop/hbase/zookeeper/ZKWatcher
       3: dup
       4: getstatic     #3                  // Field TEST_UTIL:Lorg/apache/hadoop/hbase/HBaseTestingUtility;
       7: invokevirtual #7                  // Method org/apache/hadoop/hbase/HBaseTestingUtility.getConfiguration:()Lorg/apache/hadoop/conf/Configuration;
      10: ldc           #8                  // String testActiveMasterManagerFromZK
      12: aconst_null
      13: iconst_1
      14: invokespecial #9                  // Method org/apache/hadoop/hbase/zookeeper/ZKWatcher."<init>":(Lorg/apache/hadoop/conf/Configuration;Ljava/lang/String;Lorg/apache/hadoop/hbase/Abortable;Z)V
      17: astore_1
      18: aload_1
      19: aload_1
      20: invokevirtual #10                 // Method org/apache/hadoop/hbase/zookeeper/ZKWatcher.getZNodePaths:()Lorg/apache/hadoop/hbase/zookeeper/ZNodePaths;
      23: getfield      #11                 // Field org/apache/hadoop/hbase/zookeeper/ZNodePaths.masterAddressZNode:Ljava/lang/String;
      26: invokestatic  #12                 // Method org/apache/hadoop/hbase/zookeeper/ZKUtil.deleteNode:(Lorg/apache/hadoop/hbase/zookeeper/ZKWatcher;Ljava/lang/String;)V
      29: aload_1
      30: aload_1
      31: invokevirtual #10                 // Method org/apache/hadoop/hbase/zookeeper/ZKWatcher.getZNodePaths:()Lorg/apache/hadoop/hbase/zookeeper/ZNodePaths;
      34: getfield      #13                 // Field org/apache/hadoop/hbase/zookeeper/ZNodePaths.clusterStateZNode:Ljava/lang/String;
      37: invokestatic  #12                 // Method org/apache/hadoop/hbase/zookeeper/ZKUtil.deleteNode:(Lorg/apache/hadoop/hbase/zookeeper/ZKWatcher;Ljava/lang/String;)V
      40: goto          44
      43: astore_2
      44: ldc           #15                 // String localhost
      46: iconst_1
      47: invokestatic  #16                 // Method java/lang/System.currentTimeMillis:()J
      50: invokestatic  #17                 // Method org/apache/hadoop/hbase/ServerName.valueOf:(Ljava/lang/String;IJ)Lorg/apache/hadoop/hbase/ServerName;
      53: astore_2
      54: new           #18                 // class org/apache/hadoop/hbase/master/TestActiveMasterManager$DummyMaster
      57: dup
      58: aload_1
      59: aload_2
      60: invokespecial #19                 // Method org/apache/hadoop/hbase/master/TestActiveMasterManager$DummyMaster."<init>":(Lorg/apache/hadoop/hbase/zookeeper/ZKWatcher;Lorg/apache/hadoop/hbase/ServerName;)V
      63: astore_3
      64: aload_3
      65: invokevirtual #20                 // Method org/apache/hadoop/hbase/master/TestActiveMasterManager$DummyMaster.getClusterStatusTracker:()Lorg/apache/hadoop/hbase/zookeeper/ClusterStatusTracker;
      68: astore        4
      70: aload_3
      71: invokevirtual #21                 // Method org/apache/hadoop/hbase/master/TestActiveMasterManager$DummyMaster.getActiveMasterManager:()Lorg/apache/hadoop/hbase/master/ActiveMasterManager;
      74: astore        5
      76: aload         5
      78: getfield      #22                 // Field org/apache/hadoop/hbase/master/ActiveMasterManager.clusterHasActiveMaster:Ljava/util/concurrent/atomic/AtomicBoolean;
      81: invokevirtual #23                 // Method java/util/concurrent/atomic/AtomicBoolean.get:()Z
      84: invokestatic  #24                 // Method org/junit/Assert.assertFalse:(Z)V
      87: ldc           #25                 // class org/apache/hadoop/hbase/monitoring/MonitoredTask
      89: invokestatic  #26                 // Method org/mockito/Mockito.mock:(Ljava/lang/Class;)Ljava/lang/Object;
      92: checkcast     #25                 // class org/apache/hadoop/hbase/monitoring/MonitoredTask
      95: astore        6
      97: aload         4
      99: invokevirtual #27                 // Method org/apache/hadoop/hbase/zookeeper/ClusterStatusTracker.setClusterUp:()V
     102: aload         5
     104: bipush        100
     106: aload         6
     108: invokevirtual #28                 // Method org/apache/hadoop/hbase/master/ActiveMasterManager.blockUntilBecomingActiveMaster:(ILorg/apache/hadoop/hbase/monitoring/MonitoredTask;)Z
     111: pop
     112: aload         5
     114: getfield      #22                 // Field org/apache/hadoop/hbase/master/ActiveMasterManager.clusterHasActiveMaster:Ljava/util/concurrent/atomic/AtomicBoolean;
     117: invokevirtual #23                 // Method java/util/concurrent/atomic/AtomicBoolean.get:()Z
     120: invokestatic  #29                 // Method org/junit/Assert.assertTrue:(Z)V
     123: aload_0
     124: aload_1
     125: aload_2
     126: invokespecial #30                 // Method assertMaster:(Lorg/apache/hadoop/hbase/zookeeper/ZKWatcher;Lorg/apache/hadoop/hbase/ServerName;)V
     129: new           #18                 // class org/apache/hadoop/hbase/master/TestActiveMasterManager$DummyMaster
     132: dup
     133: aload_1
     134: aload_2
     135: invokespecial #19                 // Method org/apache/hadoop/hbase/master/TestActiveMasterManager$DummyMaster."<init>":(Lorg/apache/hadoop/hbase/zookeeper/ZKWatcher;Lorg/apache/hadoop/hbase/ServerName;)V
     138: astore        7
     140: aload         7
     142: invokevirtual #21                 // Method org/apache/hadoop/hbase/master/TestActiveMasterManager$DummyMaster.getActiveMasterManager:()Lorg/apache/hadoop/hbase/master/ActiveMasterManager;
     145: astore        8
     147: aload         8
     149: getfield      #22                 // Field org/apache/hadoop/hbase/master/ActiveMasterManager.clusterHasActiveMaster:Ljava/util/concurrent/atomic/AtomicBoolean;
     152: invokevirtual #23                 // Method java/util/concurrent/atomic/AtomicBoolean.get:()Z
     155: invokestatic  #24                 // Method org/junit/Assert.assertFalse:(Z)V
     158: aload         5
     160: bipush        100
     162: aload         6
     164: invokevirtual #28                 // Method org/apache/hadoop/hbase/master/ActiveMasterManager.blockUntilBecomingActiveMaster:(ILorg/apache/hadoop/hbase/monitoring/MonitoredTask;)Z
     167: pop
     168: aload         5
     170: getfield      #22                 // Field org/apache/hadoop/hbase/master/ActiveMasterManager.clusterHasActiveMaster:Ljava/util/concurrent/atomic/AtomicBoolean;
     173: invokevirtual #23                 // Method java/util/concurrent/atomic/AtomicBoolean.get:()Z
     176: invokestatic  #29                 // Method org/junit/Assert.assertTrue:(Z)V
     179: aload_0
     180: aload_1
     181: aload_2
     182: invokespecial #30                 // Method assertMaster:(Lorg/apache/hadoop/hbase/zookeeper/ZKWatcher;Lorg/apache/hadoop/hbase/ServerName;)V
     185: return
    Exception table:
       from    to  target type
          18    40    43   Class org/apache/zookeeper/KeeperException$NoNodeException

  public void testActiveMasterManagerFromZK() throws java.lang.Exception;
    Code:
       0: new           #6                  // class org/apache/hadoop/hbase/zookeeper/ZKWatcher
       3: dup
       4: getstatic     #3                  // Field TEST_UTIL:Lorg/apache/hadoop/hbase/HBaseTestingUtility;
       7: invokevirtual #7                  // Method org/apache/hadoop/hbase/HBaseTestingUtility.getConfiguration:()Lorg/apache/hadoop/conf/Configuration;
      10: ldc           #8                  // String testActiveMasterManagerFromZK
      12: aconst_null
      13: iconst_1
      14: invokespecial #9                  // Method org/apache/hadoop/hbase/zookeeper/ZKWatcher."<init>":(Lorg/apache/hadoop/conf/Configuration;Ljava/lang/String;Lorg/apache/hadoop/hbase/Abortable;Z)V
      17: astore_1
      18: aload_1
      19: aload_1
      20: invokevirtual #10                 // Method org/apache/hadoop/hbase/zookeeper/ZKWatcher.getZNodePaths:()Lorg/apache/hadoop/hbase/zookeeper/ZNodePaths;
      23: getfield      #11                 // Field org/apache/hadoop/hbase/zookeeper/ZNodePaths.masterAddressZNode:Ljava/lang/String;
      26: invokestatic  #12                 // Method org/apache/hadoop/hbase/zookeeper/ZKUtil.deleteNode:(Lorg/apache/hadoop/hbase/zookeeper/ZKWatcher;Ljava/lang/String;)V
      29: aload_1
      30: aload_1
      31: invokevirtual #10                 // Method org/apache/hadoop/hbase/zookeeper/ZKWatcher.getZNodePaths:()Lorg/apache/hadoop/hbase/zookeeper/ZNodePaths;
      34: getfield      #13                 // Field org/apache/hadoop/hbase/zookeeper/ZNodePaths.clusterStateZNode:Ljava/lang/String;
      37: invokestatic  #12                 // Method org/apache/hadoop/hbase/zookeeper/ZKUtil.deleteNode:(Lorg/apache/hadoop/hbase/zookeeper/ZKWatcher;Ljava/lang/String;)V
      40: goto          44
      43: astore_2
      44: ldc           #15                 // String localhost
      46: iconst_1
      47: invokestatic  #16                 // Method java/lang/System.currentTimeMillis:()J
      50: invokestatic  #17                 // Method org/apache/hadoop/hbase/ServerName.valueOf:(Ljava/lang/String;IJ)Lorg/apache/hadoop/hbase/ServerName;
      53: astore_2
      54: ldc           #15                 // String localhost
      56: iconst_2
      57: invokestatic  #16                 // Method java/lang/System.currentTimeMillis:()J
      60: invokestatic  #17                 // Method org/apache/hadoop/hbase/ServerName.valueOf:(Ljava/lang/String;IJ)Lorg/apache/hadoop/hbase/ServerName;
      63: astore_3
      64: new           #18                 // class org/apache/hadoop/hbase/master/TestActiveMasterManager$DummyMaster
      67: dup
      68: aload_1
      69: aload_2
      70: invokespecial #19                 // Method org/apache/hadoop/hbase/master/TestActiveMasterManager$DummyMaster."<init>":(Lorg/apache/hadoop/hbase/zookeeper/ZKWatcher;Lorg/apache/hadoop/hbase/ServerName;)V
      73: astore        4
      75: aload         4
      77: invokevirtual #21                 // Method org/apache/hadoop/hbase/master/TestActiveMasterManager$DummyMaster.getActiveMasterManager:()Lorg/apache/hadoop/hbase/master/ActiveMasterManager;
      80: astore        5
      82: aload         5
      84: getfield      #22                 // Field org/apache/hadoop/hbase/master/ActiveMasterManager.clusterHasActiveMaster:Ljava/util/concurrent/atomic/AtomicBoolean;
      87: invokevirtual #23                 // Method java/util/concurrent/atomic/AtomicBoolean.get:()Z
      90: invokestatic  #24                 // Method org/junit/Assert.assertFalse:(Z)V
      93: aload         4
      95: invokevirtual #20                 // Method org/apache/hadoop/hbase/master/TestActiveMasterManager$DummyMaster.getClusterStatusTracker:()Lorg/apache/hadoop/hbase/zookeeper/ClusterStatusTracker;
      98: astore        6
     100: aload         6
     102: invokevirtual #27                 // Method org/apache/hadoop/hbase/zookeeper/ClusterStatusTracker.setClusterUp:()V
     105: aload         5
     107: bipush        100
     109: ldc           #25                 // class org/apache/hadoop/hbase/monitoring/MonitoredTask
     111: invokestatic  #26                 // Method org/mockito/Mockito.mock:(Ljava/lang/Class;)Ljava/lang/Object;
     114: checkcast     #25                 // class org/apache/hadoop/hbase/monitoring/MonitoredTask
     117: invokevirtual #28                 // Method org/apache/hadoop/hbase/master/ActiveMasterManager.blockUntilBecomingActiveMaster:(ILorg/apache/hadoop/hbase/monitoring/MonitoredTask;)Z
     120: pop
     121: aload         5
     123: getfield      #22                 // Field org/apache/hadoop/hbase/master/ActiveMasterManager.clusterHasActiveMaster:Ljava/util/concurrent/atomic/AtomicBoolean;
     126: invokevirtual #23                 // Method java/util/concurrent/atomic/AtomicBoolean.get:()Z
     129: invokestatic  #29                 // Method org/junit/Assert.assertTrue:(Z)V
     132: aload_0
     133: aload_1
     134: aload_2
     135: invokespecial #30                 // Method assertMaster:(Lorg/apache/hadoop/hbase/zookeeper/ZKWatcher;Lorg/apache/hadoop/hbase/ServerName;)V
     138: new           #31                 // class org/apache/hadoop/hbase/master/TestActiveMasterManager$WaitToBeMasterThread
     141: dup
     142: aload_1
     143: aload_3
     144: invokespecial #32                 // Method org/apache/hadoop/hbase/master/TestActiveMasterManager$WaitToBeMasterThread."<init>":(Lorg/apache/hadoop/hbase/zookeeper/ZKWatcher;Lorg/apache/hadoop/hbase/ServerName;)V
     147: astore        7
     149: aload         7
     151: invokevirtual #33                 // Method org/apache/hadoop/hbase/master/TestActiveMasterManager$WaitToBeMasterThread.start:()V
     154: iconst_0
     155: istore        8
     157: aload         7
     159: getfield      #34                 // Field org/apache/hadoop/hbase/master/TestActiveMasterManager$WaitToBeMasterThread.manager:Lorg/apache/hadoop/hbase/master/ActiveMasterManager;
     162: getfield      #22                 // Field org/apache/hadoop/hbase/master/ActiveMasterManager.clusterHasActiveMaster:Ljava/util/concurrent/atomic/AtomicBoolean;
     165: invokevirtual #23                 // Method java/util/concurrent/atomic/AtomicBoolean.get:()Z
     168: ifne          190
     171: iload         8
     173: bipush        100
     175: if_icmpge     190
     178: ldc2_w        #35                 // long 10l
     181: invokestatic  #37                 // Method java/lang/Thread.sleep:(J)V
     184: iinc          8, 1
     187: goto          157
     190: aload         5
     192: getfield      #22                 // Field org/apache/hadoop/hbase/master/ActiveMasterManager.clusterHasActiveMaster:Ljava/util/concurrent/atomic/AtomicBoolean;
     195: invokevirtual #23                 // Method java/util/concurrent/atomic/AtomicBoolean.get:()Z
     198: invokestatic  #29                 // Method org/junit/Assert.assertTrue:(Z)V
     201: aload         7
     203: getfield      #34                 // Field org/apache/hadoop/hbase/master/TestActiveMasterManager$WaitToBeMasterThread.manager:Lorg/apache/hadoop/hbase/master/ActiveMasterManager;
     206: getfield      #22                 // Field org/apache/hadoop/hbase/master/ActiveMasterManager.clusterHasActiveMaster:Ljava/util/concurrent/atomic/AtomicBoolean;
     209: invokevirtual #23                 // Method java/util/concurrent/atomic/AtomicBoolean.get:()Z
     212: invokestatic  #29                 // Method org/junit/Assert.assertTrue:(Z)V
     215: aload         7
     217: getfield      #38                 // Field org/apache/hadoop/hbase/master/TestActiveMasterManager$WaitToBeMasterThread.isActiveMaster:Z
     220: invokestatic  #24                 // Method org/junit/Assert.assertFalse:(Z)V
     223: aload         4
     225: ldc           #39                 // String stopping first server
     227: invokevirtual #40                 // Method org/apache/hadoop/hbase/master/TestActiveMasterManager$DummyMaster.stop:(Ljava/lang/String;)V
     230: new           #41                 // class org/apache/hadoop/hbase/master/TestActiveMasterManager$NodeDeletionListener
     233: dup
     234: aload_1
     235: aload_1
     236: invokevirtual #10                 // Method org/apache/hadoop/hbase/zookeeper/ZKWatcher.getZNodePaths:()Lorg/apache/hadoop/hbase/zookeeper/ZNodePaths;
     239: getfield      #11                 // Field org/apache/hadoop/hbase/zookeeper/ZNodePaths.masterAddressZNode:Ljava/lang/String;
     242: invokespecial #42                 // Method org/apache/hadoop/hbase/master/TestActiveMasterManager$NodeDeletionListener."<init>":(Lorg/apache/hadoop/hbase/zookeeper/ZKWatcher;Ljava/lang/String;)V
     245: astore        9
     247: aload_1
     248: aload         9
     250: invokevirtual #43                 // Method org/apache/hadoop/hbase/zookeeper/ZKWatcher.registerListener:(Lorg/apache/hadoop/hbase/zookeeper/ZKListener;)V
     253: getstatic     #1                  // Field LOG:Lorg/slf4j/Logger;
     256: ldc           #44                 // String Deleting master node
     258: invokeinterface #45,  2           // InterfaceMethod org/slf4j/Logger.info:(Ljava/lang/String;)V
     263: aload_1
     264: aload_1
     265: invokevirtual #10                 // Method org/apache/hadoop/hbase/zookeeper/ZKWatcher.getZNodePaths:()Lorg/apache/hadoop/hbase/zookeeper/ZNodePaths;
     268: getfield      #11                 // Field org/apache/hadoop/hbase/zookeeper/ZNodePaths.masterAddressZNode:Ljava/lang/String;
     271: invokestatic  #12                 // Method org/apache/hadoop/hbase/zookeeper/ZKUtil.deleteNode:(Lorg/apache/hadoop/hbase/zookeeper/ZKWatcher;Ljava/lang/String;)V
     274: getstatic     #1                  // Field LOG:Lorg/slf4j/Logger;
     277: ldc           #46                 // String Waiting for active master manager to be notified
     279: invokeinterface #45,  2           // InterfaceMethod org/slf4j/Logger.info:(Ljava/lang/String;)V
     284: aload         9
     286: invokevirtual #47                 // Method org/apache/hadoop/hbase/master/TestActiveMasterManager$NodeDeletionListener.waitForDeletion:()V
     289: getstatic     #1                  // Field LOG:Lorg/slf4j/Logger;
     292: ldc           #48                 // String Master node deleted
     294: invokeinterface #45,  2           // InterfaceMethod org/slf4j/Logger.info:(Ljava/lang/String;)V
     299: iconst_0
     300: istore        8
     302: aload         7
     304: getfield      #38                 // Field org/apache/hadoop/hbase/master/TestActiveMasterManager$WaitToBeMasterThread.isActiveMaster:Z
     307: ifne          329
     310: iload         8
     312: bipush        100
     314: if_icmpge     329
     317: ldc2_w        #35                 // long 10l
     320: invokestatic  #37                 // Method java/lang/Thread.sleep:(J)V
     323: iinc          8, 1
     326: goto          302
     329: getstatic     #1                  // Field LOG:Lorg/slf4j/Logger;
     332: new           #49                 // class java/lang/StringBuilder
     335: dup
     336: invokespecial #50                 // Method java/lang/StringBuilder."<init>":()V
     339: ldc           #51                 // String Slept
     341: invokevirtual #52                 // Method java/lang/StringBuilder.append:(Ljava/lang/String;)Ljava/lang/StringBuilder;
     344: iload         8
     346: invokevirtual #53                 // Method java/lang/StringBuilder.append:(I)Ljava/lang/StringBuilder;
     349: ldc           #54                 // String  times
     351: invokevirtual #52                 // Method java/lang/StringBuilder.append:(Ljava/lang/String;)Ljava/lang/StringBuilder;
     354: invokevirtual #55                 // Method java/lang/StringBuilder.toString:()Ljava/lang/String;
     357: invokeinterface #56,  2           // InterfaceMethod org/slf4j/Logger.debug:(Ljava/lang/String;)V
     362: aload         7
     364: getfield      #34                 // Field org/apache/hadoop/hbase/master/TestActiveMasterManager$WaitToBeMasterThread.manager:Lorg/apache/hadoop/hbase/master/ActiveMasterManager;
     367: getfield      #22                 // Field org/apache/hadoop/hbase/master/ActiveMasterManager.clusterHasActiveMaster:Ljava/util/concurrent/atomic/AtomicBoolean;
     370: invokevirtual #23                 // Method java/util/concurrent/atomic/AtomicBoolean.get:()Z
     373: invokestatic  #29                 // Method org/junit/Assert.assertTrue:(Z)V
     376: aload         7
     378: getfield      #38                 // Field org/apache/hadoop/hbase/master/TestActiveMasterManager$WaitToBeMasterThread.isActiveMaster:Z
     381: invokestatic  #29                 // Method org/junit/Assert.assertTrue:(Z)V
     384: getstatic     #1                  // Field LOG:Lorg/slf4j/Logger;
     387: ldc           #44                 // String Deleting master node
     389: invokeinterface #45,  2           // InterfaceMethod org/slf4j/Logger.info:(Ljava/lang/String;)V
     394: aload_1
     395: aload_1
     396: invokevirtual #10                 // Method org/apache/hadoop/hbase/zookeeper/ZKWatcher.getZNodePaths:()Lorg/apache/hadoop/hbase/zookeeper/ZNodePaths;
     399: getfield      #11                 // Field org/apache/hadoop/hbase/zookeeper/ZNodePaths.masterAddressZNode:Ljava/lang/String;
     402: invokestatic  #12                 // Method org/apache/hadoop/hbase/zookeeper/ZKUtil.deleteNode:(Lorg/apache/hadoop/hbase/zookeeper/ZKWatcher;Ljava/lang/String;)V
     405: return
    Exception table:
       from    to  target type
          18    40    43   Class org/apache/zookeeper/KeeperException$NoNodeException

  static org.slf4j.Logger access$000();
    Code:
       0: getstatic     #1                  // Field LOG:Lorg/slf4j/Logger;
       3: areturn

  static {};
    Code:
       0: ldc           #60                 // class org/apache/hadoop/hbase/master/TestActiveMasterManager
       2: invokestatic  #61                 // Method org/apache/hadoop/hbase/HBaseClassTestRule.forClass:(Ljava/lang/Class;)Lorg/apache/hadoop/hbase/HBaseClassTestRule;
       5: putstatic     #62                 // Field CLASS_RULE:Lorg/apache/hadoop/hbase/HBaseClassTestRule;
       8: ldc           #60                 // class org/apache/hadoop/hbase/master/TestActiveMasterManager
      10: invokestatic  #63                 // Method org/slf4j/LoggerFactory.getLogger:(Ljava/lang/Class;)Lorg/slf4j/Logger;
      13: putstatic     #1                  // Field LOG:Lorg/slf4j/Logger;
      16: new           #64                 // class org/apache/hadoop/hbase/HBaseTestingUtility
      19: dup
      20: invokespecial #65                 // Method org/apache/hadoop/hbase/HBaseTestingUtility."<init>":()V
      23: putstatic     #3                  // Field TEST_UTIL:Lorg/apache/hadoop/hbase/HBaseTestingUtility;
      26: return
}
