Compiled from "TestAccessController.java"
class org.apache.hadoop.hbase.security.access.TestAccessController$13 implements org.apache.hadoop.hbase.security.access.SecureTestUtil$AccessTestAction {
  final org.apache.hadoop.hbase.HRegionInfo val$hri;

  final org.apache.hadoop.hbase.ServerName val$server;

  final org.apache.hadoop.hbase.security.access.TestAccessController this$0;

  org.apache.hadoop.hbase.security.access.TestAccessController$13(org.apache.hadoop.hbase.security.access.TestAccessController, org.apache.hadoop.hbase.HRegionInfo, org.apache.hadoop.hbase.ServerName);
    Code:
       0: aload_0
       1: aload_1
       2: putfield      #1                  // Field this$0:Lorg/apache/hadoop/hbase/security/access/TestAccessController;
       5: aload_0
       6: aload_2
       7: putfield      #2                  // Field val$hri:Lorg/apache/hadoop/hbase/HRegionInfo;
      10: aload_0
      11: aload_3
      12: putfield      #3                  // Field val$server:Lorg/apache/hadoop/hbase/ServerName;
      15: aload_0
      16: invokespecial #4                  // Method java/lang/Object."<init>":()V
      19: return

  public java.lang.Object run() throws java.lang.Exception;
    Code:
       0: invokestatic  #5                  // Method org/apache/hadoop/hbase/security/access/TestAccessController.access$300:()Lorg/apache/hadoop/hbase/security/access/AccessController;
       3: invokestatic  #6                  // Method org/apache/hadoop/hbase/security/access/TestAccessController.access$200:()Lorg/apache/hadoop/hbase/coprocessor/MasterCoprocessorEnvironment;
       6: invokestatic  #7                  // Method org/apache/hadoop/hbase/coprocessor/ObserverContextImpl.createAndPrepare:(Lorg/apache/hadoop/hbase/CoprocessorEnvironment;)Lorg/apache/hadoop/hbase/coprocessor/ObserverContext;
       9: aload_0
      10: getfield      #2                  // Field val$hri:Lorg/apache/hadoop/hbase/HRegionInfo;
      13: aload_0
      14: getfield      #3                  // Field val$server:Lorg/apache/hadoop/hbase/ServerName;
      17: aload_0
      18: getfield      #3                  // Field val$server:Lorg/apache/hadoop/hbase/ServerName;
      21: invokevirtual #8                  // Method org/apache/hadoop/hbase/security/access/AccessController.preMove:(Lorg/apache/hadoop/hbase/coprocessor/ObserverContext;Lorg/apache/hadoop/hbase/client/RegionInfo;Lorg/apache/hadoop/hbase/ServerName;Lorg/apache/hadoop/hbase/ServerName;)V
      24: aconst_null
      25: areturn
}
