Compiled from "TestAsyncTable.java"
public class org.apache.hadoop.hbase.client.TestAsyncTable {
  public static final org.apache.hadoop.hbase.HBaseClassTestRule CLASS_RULE;

  public org.junit.rules.TestName testName;

  public java.util.function.Supplier<org.apache.hadoop.hbase.client.AsyncTable<?>> getTable;

  public org.apache.hadoop.hbase.client.TestAsyncTable();
    Code:
       0: aload_0
       1: invokespecial #1                  // Method java/lang/Object."<init>":()V
       4: aload_0
       5: new           #2                  // class org/junit/rules/TestName
       8: dup
       9: invokespecial #3                  // Method org/junit/rules/TestName."<init>":()V
      12: putfield      #4                  // Field testName:Lorg/junit/rules/TestName;
      15: return

  public static java.util.List<java.lang.Object[]> params();
    Code:
       0: iconst_2
       1: anewarray     #10                 // class "[Ljava/lang/Object;"
       4: dup
       5: iconst_0
       6: iconst_1
       7: anewarray     #11                 // class java/util/function/Supplier
      10: dup
      11: iconst_0
      12: invokedynamic #12,  0             // InvokeDynamic #0:get:()Ljava/util/function/Supplier;
      17: aastore
      18: aastore
      19: dup
      20: iconst_1
      21: iconst_1
      22: anewarray     #11                 // class java/util/function/Supplier
      25: dup
      26: iconst_0
      27: invokedynamic #13,  0             // InvokeDynamic #1:get:()Ljava/util/function/Supplier;
      32: aastore
      33: aastore
      34: invokestatic  #14                 // Method java/util/Arrays.asList:([Ljava/lang/Object;)Ljava/util/List;
      37: areturn

  public static void setUpBeforeClass() throws java.lang.Exception;
    Code:
       0: getstatic     #15                 // Field TEST_UTIL:Lorg/apache/hadoop/hbase/HBaseTestingUtility;
       3: invokevirtual #16                 // Method org/apache/hadoop/hbase/HBaseTestingUtility.getConfiguration:()Lorg/apache/hadoop/conf/Configuration;
       6: ldc           #18                 // String hbase.client.keyvalue.maxsize
       8: getstatic     #19                 // Field MAX_KEY_VALUE_SIZE:I
      11: invokevirtual #20                 // Method org/apache/hadoop/conf/Configuration.setInt:(Ljava/lang/String;I)V
      14: getstatic     #15                 // Field TEST_UTIL:Lorg/apache/hadoop/hbase/HBaseTestingUtility;
      17: iconst_1
      18: invokevirtual #21                 // Method org/apache/hadoop/hbase/HBaseTestingUtility.startMiniCluster:(I)Lorg/apache/hadoop/hbase/MiniHBaseCluster;
      21: pop
      22: getstatic     #15                 // Field TEST_UTIL:Lorg/apache/hadoop/hbase/HBaseTestingUtility;
      25: getstatic     #6                  // Field TABLE_NAME:Lorg/apache/hadoop/hbase/TableName;
      28: getstatic     #22                 // Field FAMILY:[B
      31: invokevirtual #23                 // Method org/apache/hadoop/hbase/HBaseTestingUtility.createTable:(Lorg/apache/hadoop/hbase/TableName;[B)Lorg/apache/hadoop/hbase/client/Table;
      34: pop
      35: getstatic     #15                 // Field TEST_UTIL:Lorg/apache/hadoop/hbase/HBaseTestingUtility;
      38: getstatic     #6                  // Field TABLE_NAME:Lorg/apache/hadoop/hbase/TableName;
      41: invokevirtual #24                 // Method org/apache/hadoop/hbase/HBaseTestingUtility.waitTableAvailable:(Lorg/apache/hadoop/hbase/TableName;)V
      44: getstatic     #15                 // Field TEST_UTIL:Lorg/apache/hadoop/hbase/HBaseTestingUtility;
      47: invokevirtual #16                 // Method org/apache/hadoop/hbase/HBaseTestingUtility.getConfiguration:()Lorg/apache/hadoop/conf/Configuration;
      50: invokestatic  #25                 // Method org/apache/hadoop/hbase/client/ConnectionFactory.createAsyncConnection:(Lorg/apache/hadoop/conf/Configuration;)Ljava/util/concurrent/CompletableFuture;
      53: invokevirtual #26                 // Method java/util/concurrent/CompletableFuture.get:()Ljava/lang/Object;
      56: checkcast     #27                 // class org/apache/hadoop/hbase/client/AsyncConnection
      59: putstatic     #5                  // Field ASYNC_CONN:Lorg/apache/hadoop/hbase/client/AsyncConnection;
      62: getstatic     #5                  // Field ASYNC_CONN:Lorg/apache/hadoop/hbase/client/AsyncConnection;
      65: invokeinterface #28,  1           // InterfaceMethod org/apache/hadoop/hbase/client/AsyncConnection.isClosed:()Z
      70: invokestatic  #29                 // Method org/junit/Assert.assertFalse:(Z)V
      73: return

  public static void tearDownAfterClass() throws java.lang.Exception;
    Code:
       0: getstatic     #5                  // Field ASYNC_CONN:Lorg/apache/hadoop/hbase/client/AsyncConnection;
       3: invokestatic  #30                 // Method org/apache/commons/io/IOUtils.closeQuietly:(Ljava/io/Closeable;)V
       6: getstatic     #5                  // Field ASYNC_CONN:Lorg/apache/hadoop/hbase/client/AsyncConnection;
       9: invokeinterface #28,  1           // InterfaceMethod org/apache/hadoop/hbase/client/AsyncConnection.isClosed:()Z
      14: invokestatic  #31                 // Method org/junit/Assert.assertTrue:(Z)V
      17: getstatic     #15                 // Field TEST_UTIL:Lorg/apache/hadoop/hbase/HBaseTestingUtility;
      20: invokevirtual #32                 // Method org/apache/hadoop/hbase/HBaseTestingUtility.shutdownMiniCluster:()V
      23: return

  public void setUp() throws java.io.IOException, java.lang.InterruptedException, java.util.concurrent.ExecutionException;
    Code:
       0: aload_0
       1: aload_0
       2: getfield      #4                  // Field testName:Lorg/junit/rules/TestName;
       5: invokevirtual #33                 // Method org/junit/rules/TestName.getMethodName:()Ljava/lang/String;
       8: ldc           #34                 // String [^0-9A-Za-z]
      10: ldc           #35                 // String _
      12: invokevirtual #36                 // Method java/lang/String.replaceAll:(Ljava/lang/String;Ljava/lang/String;)Ljava/lang/String;
      15: invokestatic  #37                 // Method org/apache/hadoop/hbase/util/Bytes.toBytes:(Ljava/lang/String;)[B
      18: putfield      #38                 // Field row:[B
      21: getstatic     #5                  // Field ASYNC_CONN:Lorg/apache/hadoop/hbase/client/AsyncConnection;
      24: invokeinterface #39,  1           // InterfaceMethod org/apache/hadoop/hbase/client/AsyncConnection.getAdmin:()Lorg/apache/hadoop/hbase/client/AsyncAdmin;
      29: getstatic     #6                  // Field TABLE_NAME:Lorg/apache/hadoop/hbase/TableName;
      32: invokeinterface #40,  2           // InterfaceMethod org/apache/hadoop/hbase/client/AsyncAdmin.isTableDisabled:(Lorg/apache/hadoop/hbase/TableName;)Ljava/util/concurrent/CompletableFuture;
      37: invokevirtual #26                 // Method java/util/concurrent/CompletableFuture.get:()Ljava/lang/Object;
      40: checkcast     #41                 // class java/lang/Boolean
      43: invokevirtual #42                 // Method java/lang/Boolean.booleanValue:()Z
      46: ifeq          69
      49: getstatic     #5                  // Field ASYNC_CONN:Lorg/apache/hadoop/hbase/client/AsyncConnection;
      52: invokeinterface #39,  1           // InterfaceMethod org/apache/hadoop/hbase/client/AsyncConnection.getAdmin:()Lorg/apache/hadoop/hbase/client/AsyncAdmin;
      57: getstatic     #6                  // Field TABLE_NAME:Lorg/apache/hadoop/hbase/TableName;
      60: invokeinterface #43,  2           // InterfaceMethod org/apache/hadoop/hbase/client/AsyncAdmin.enableTable:(Lorg/apache/hadoop/hbase/TableName;)Ljava/util/concurrent/CompletableFuture;
      65: invokevirtual #26                 // Method java/util/concurrent/CompletableFuture.get:()Ljava/lang/Object;
      68: pop
      69: return

  public void testSimple() throws java.lang.Exception;
    Code:
       0: aload_0
       1: getfield      #44                 // Field getTable:Ljava/util/function/Supplier;
       4: invokeinterface #45,  1           // InterfaceMethod java/util/function/Supplier.get:()Ljava/lang/Object;
       9: checkcast     #46                 // class org/apache/hadoop/hbase/client/AsyncTable
      12: astore_1
      13: aload_1
      14: new           #47                 // class org/apache/hadoop/hbase/client/Put
      17: dup
      18: aload_0
      19: getfield      #38                 // Field row:[B
      22: invokespecial #48                 // Method org/apache/hadoop/hbase/client/Put."<init>":([B)V
      25: getstatic     #22                 // Field FAMILY:[B
      28: getstatic     #49                 // Field QUALIFIER:[B
      31: getstatic     #50                 // Field VALUE:[B
      34: invokevirtual #51                 // Method org/apache/hadoop/hbase/client/Put.addColumn:([B[B[B)Lorg/apache/hadoop/hbase/client/Put;
      37: invokeinterface #52,  2           // InterfaceMethod org/apache/hadoop/hbase/client/AsyncTable.put:(Lorg/apache/hadoop/hbase/client/Put;)Ljava/util/concurrent/CompletableFuture;
      42: invokevirtual #26                 // Method java/util/concurrent/CompletableFuture.get:()Ljava/lang/Object;
      45: pop
      46: aload_1
      47: new           #53                 // class org/apache/hadoop/hbase/client/Get
      50: dup
      51: aload_0
      52: getfield      #38                 // Field row:[B
      55: invokespecial #54                 // Method org/apache/hadoop/hbase/client/Get."<init>":([B)V
      58: getstatic     #22                 // Field FAMILY:[B
      61: getstatic     #49                 // Field QUALIFIER:[B
      64: invokevirtual #55                 // Method org/apache/hadoop/hbase/client/Get.addColumn:([B[B)Lorg/apache/hadoop/hbase/client/Get;
      67: invokeinterface #56,  2           // InterfaceMethod org/apache/hadoop/hbase/client/AsyncTable.exists:(Lorg/apache/hadoop/hbase/client/Get;)Ljava/util/concurrent/CompletableFuture;
      72: invokevirtual #26                 // Method java/util/concurrent/CompletableFuture.get:()Ljava/lang/Object;
      75: checkcast     #41                 // class java/lang/Boolean
      78: invokevirtual #42                 // Method java/lang/Boolean.booleanValue:()Z
      81: invokestatic  #31                 // Method org/junit/Assert.assertTrue:(Z)V
      84: aload_1
      85: new           #53                 // class org/apache/hadoop/hbase/client/Get
      88: dup
      89: aload_0
      90: getfield      #38                 // Field row:[B
      93: invokespecial #54                 // Method org/apache/hadoop/hbase/client/Get."<init>":([B)V
      96: getstatic     #22                 // Field FAMILY:[B
      99: getstatic     #49                 // Field QUALIFIER:[B
     102: invokevirtual #55                 // Method org/apache/hadoop/hbase/client/Get.addColumn:([B[B)Lorg/apache/hadoop/hbase/client/Get;
     105: invokeinterface #57,  2           // InterfaceMethod org/apache/hadoop/hbase/client/AsyncTable.get:(Lorg/apache/hadoop/hbase/client/Get;)Ljava/util/concurrent/CompletableFuture;
     110: invokevirtual #26                 // Method java/util/concurrent/CompletableFuture.get:()Ljava/lang/Object;
     113: checkcast     #58                 // class org/apache/hadoop/hbase/client/Result
     116: astore_2
     117: getstatic     #50                 // Field VALUE:[B
     120: aload_2
     121: getstatic     #22                 // Field FAMILY:[B
     124: getstatic     #49                 // Field QUALIFIER:[B
     127: invokevirtual #59                 // Method org/apache/hadoop/hbase/client/Result.getValue:([B[B)[B
     130: invokestatic  #60                 // Method org/junit/Assert.assertArrayEquals:([B[B)V
     133: aload_1
     134: new           #61                 // class org/apache/hadoop/hbase/client/Delete
     137: dup
     138: aload_0
     139: getfield      #38                 // Field row:[B
     142: invokespecial #62                 // Method org/apache/hadoop/hbase/client/Delete."<init>":([B)V
     145: invokeinterface #63,  2           // InterfaceMethod org/apache/hadoop/hbase/client/AsyncTable.delete:(Lorg/apache/hadoop/hbase/client/Delete;)Ljava/util/concurrent/CompletableFuture;
     150: invokevirtual #26                 // Method java/util/concurrent/CompletableFuture.get:()Ljava/lang/Object;
     153: pop
     154: aload_1
     155: new           #53                 // class org/apache/hadoop/hbase/client/Get
     158: dup
     159: aload_0
     160: getfield      #38                 // Field row:[B
     163: invokespecial #54                 // Method org/apache/hadoop/hbase/client/Get."<init>":([B)V
     166: getstatic     #22                 // Field FAMILY:[B
     169: getstatic     #49                 // Field QUALIFIER:[B
     172: invokevirtual #55                 // Method org/apache/hadoop/hbase/client/Get.addColumn:([B[B)Lorg/apache/hadoop/hbase/client/Get;
     175: invokeinterface #57,  2           // InterfaceMethod org/apache/hadoop/hbase/client/AsyncTable.get:(Lorg/apache/hadoop/hbase/client/Get;)Ljava/util/concurrent/CompletableFuture;
     180: invokevirtual #26                 // Method java/util/concurrent/CompletableFuture.get:()Ljava/lang/Object;
     183: checkcast     #58                 // class org/apache/hadoop/hbase/client/Result
     186: astore_2
     187: aload_2
     188: invokevirtual #64                 // Method org/apache/hadoop/hbase/client/Result.isEmpty:()Z
     191: invokestatic  #31                 // Method org/junit/Assert.assertTrue:(Z)V
     194: aload_1
     195: new           #53                 // class org/apache/hadoop/hbase/client/Get
     198: dup
     199: aload_0
     200: getfield      #38                 // Field row:[B
     203: invokespecial #54                 // Method org/apache/hadoop/hbase/client/Get."<init>":([B)V
     206: getstatic     #22                 // Field FAMILY:[B
     209: getstatic     #49                 // Field QUALIFIER:[B
     212: invokevirtual #55                 // Method org/apache/hadoop/hbase/client/Get.addColumn:([B[B)Lorg/apache/hadoop/hbase/client/Get;
     215: invokeinterface #56,  2           // InterfaceMethod org/apache/hadoop/hbase/client/AsyncTable.exists:(Lorg/apache/hadoop/hbase/client/Get;)Ljava/util/concurrent/CompletableFuture;
     220: invokevirtual #26                 // Method java/util/concurrent/CompletableFuture.get:()Ljava/lang/Object;
     223: checkcast     #41                 // class java/lang/Boolean
     226: invokevirtual #42                 // Method java/lang/Boolean.booleanValue:()Z
     229: invokestatic  #29                 // Method org/junit/Assert.assertFalse:(Z)V
     232: return

  public void testSimpleMultiple() throws java.lang.Exception;
    Code:
       0: aload_0
       1: getfield      #44                 // Field getTable:Ljava/util/function/Supplier;
       4: invokeinterface #45,  1           // InterfaceMethod java/util/function/Supplier.get:()Ljava/lang/Object;
       9: checkcast     #46                 // class org/apache/hadoop/hbase/client/AsyncTable
      12: astore_1
      13: bipush        100
      15: istore_2
      16: new           #72                 // class java/util/concurrent/CountDownLatch
      19: dup
      20: iload_2
      21: invokespecial #73                 // Method java/util/concurrent/CountDownLatch."<init>":(I)V
      24: astore_3
      25: iconst_0
      26: iload_2
      27: invokestatic  #74                 // InterfaceMethod java/util/stream/IntStream.range:(II)Ljava/util/stream/IntStream;
      30: aload_0
      31: aload_1
      32: aload_3
      33: invokedynamic #75,  0             // InvokeDynamic #2:accept:(Lorg/apache/hadoop/hbase/client/TestAsyncTable;Lorg/apache/hadoop/hbase/client/AsyncTable;Ljava/util/concurrent/CountDownLatch;)Ljava/util/function/IntConsumer;
      38: invokeinterface #76,  2           // InterfaceMethod java/util/stream/IntStream.forEach:(Ljava/util/function/IntConsumer;)V
      43: aload_3
      44: invokevirtual #77                 // Method java/util/concurrent/CountDownLatch.await:()V
      47: new           #78                 // class java/util/concurrent/ArrayBlockingQueue
      50: dup
      51: iload_2
      52: invokespecial #79                 // Method java/util/concurrent/ArrayBlockingQueue."<init>":(I)V
      55: astore        4
      57: iconst_0
      58: iload_2
      59: invokestatic  #74                 // InterfaceMethod java/util/stream/IntStream.range:(II)Ljava/util/stream/IntStream;
      62: aload_0
      63: aload_1
      64: aload         4
      66: invokedynamic #80,  0             // InvokeDynamic #3:accept:(Lorg/apache/hadoop/hbase/client/TestAsyncTable;Lorg/apache/hadoop/hbase/client/AsyncTable;Ljava/util/concurrent/BlockingQueue;)Ljava/util/function/IntConsumer;
      71: invokeinterface #76,  2           // InterfaceMethod java/util/stream/IntStream.forEach:(Ljava/util/function/IntConsumer;)V
      76: iconst_0
      77: istore        5
      79: iload         5
      81: iload_2
      82: if_icmpge     107
      85: aload         4
      87: invokeinterface #81,  1           // InterfaceMethod java/util/concurrent/BlockingQueue.take:()Ljava/lang/Object;
      92: checkcast     #41                 // class java/lang/Boolean
      95: invokevirtual #42                 // Method java/lang/Boolean.booleanValue:()Z
      98: invokestatic  #31                 // Method org/junit/Assert.assertTrue:(Z)V
     101: iinc          5, 1
     104: goto          79
     107: new           #78                 // class java/util/concurrent/ArrayBlockingQueue
     110: dup
     111: iload_2
     112: invokespecial #79                 // Method java/util/concurrent/ArrayBlockingQueue."<init>":(I)V
     115: astore        5
     117: iconst_0
     118: iload_2
     119: invokestatic  #74                 // InterfaceMethod java/util/stream/IntStream.range:(II)Ljava/util/stream/IntStream;
     122: aload_0
     123: aload_1
     124: aload         5
     126: invokedynamic #82,  0             // InvokeDynamic #4:accept:(Lorg/apache/hadoop/hbase/client/TestAsyncTable;Lorg/apache/hadoop/hbase/client/AsyncTable;Ljava/util/concurrent/BlockingQueue;)Ljava/util/function/IntConsumer;
     131: invokeinterface #76,  2           // InterfaceMethod java/util/stream/IntStream.forEach:(Ljava/util/function/IntConsumer;)V
     136: iconst_0
     137: istore        6
     139: iload         6
     141: iload_2
     142: if_icmpge     201
     145: aload         5
     147: invokeinterface #81,  1           // InterfaceMethod java/util/concurrent/BlockingQueue.take:()Ljava/lang/Object;
     152: checkcast     #83                 // class org/apache/hadoop/hbase/util/Pair
     155: astore        7
     157: aload_0
     158: getstatic     #50                 // Field VALUE:[B
     161: aload         7
     163: invokevirtual #84                 // Method org/apache/hadoop/hbase/util/Pair.getFirst:()Ljava/lang/Object;
     166: checkcast     #85                 // class java/lang/Integer
     169: invokevirtual #86                 // Method java/lang/Integer.intValue:()I
     172: invokespecial #87                 // Method concat:([BI)[B
     175: aload         7
     177: invokevirtual #88                 // Method org/apache/hadoop/hbase/util/Pair.getSecond:()Ljava/lang/Object;
     180: checkcast     #58                 // class org/apache/hadoop/hbase/client/Result
     183: getstatic     #22                 // Field FAMILY:[B
     186: getstatic     #49                 // Field QUALIFIER:[B
     189: invokevirtual #59                 // Method org/apache/hadoop/hbase/client/Result.getValue:([B[B)[B
     192: invokestatic  #60                 // Method org/junit/Assert.assertArrayEquals:([B[B)V
     195: iinc          6, 1
     198: goto          139
     201: new           #72                 // class java/util/concurrent/CountDownLatch
     204: dup
     205: iload_2
     206: invokespecial #73                 // Method java/util/concurrent/CountDownLatch."<init>":(I)V
     209: astore        6
     211: iconst_0
     212: iload_2
     213: invokestatic  #74                 // InterfaceMethod java/util/stream/IntStream.range:(II)Ljava/util/stream/IntStream;
     216: aload_0
     217: aload_1
     218: aload         6
     220: invokedynamic #89,  0             // InvokeDynamic #5:accept:(Lorg/apache/hadoop/hbase/client/TestAsyncTable;Lorg/apache/hadoop/hbase/client/AsyncTable;Ljava/util/concurrent/CountDownLatch;)Ljava/util/function/IntConsumer;
     225: invokeinterface #76,  2           // InterfaceMethod java/util/stream/IntStream.forEach:(Ljava/util/function/IntConsumer;)V
     230: aload         6
     232: invokevirtual #77                 // Method java/util/concurrent/CountDownLatch.await:()V
     235: iconst_0
     236: iload_2
     237: invokestatic  #74                 // InterfaceMethod java/util/stream/IntStream.range:(II)Ljava/util/stream/IntStream;
     240: aload_0
     241: aload_1
     242: aload         4
     244: invokedynamic #90,  0             // InvokeDynamic #6:accept:(Lorg/apache/hadoop/hbase/client/TestAsyncTable;Lorg/apache/hadoop/hbase/client/AsyncTable;Ljava/util/concurrent/BlockingQueue;)Ljava/util/function/IntConsumer;
     249: invokeinterface #76,  2           // InterfaceMethod java/util/stream/IntStream.forEach:(Ljava/util/function/IntConsumer;)V
     254: iconst_0
     255: istore        7
     257: iload         7
     259: iload_2
     260: if_icmpge     285
     263: aload         4
     265: invokeinterface #81,  1           // InterfaceMethod java/util/concurrent/BlockingQueue.take:()Ljava/lang/Object;
     270: checkcast     #41                 // class java/lang/Boolean
     273: invokevirtual #42                 // Method java/lang/Boolean.booleanValue:()Z
     276: invokestatic  #29                 // Method org/junit/Assert.assertFalse:(Z)V
     279: iinc          7, 1
     282: goto          257
     285: iconst_0
     286: iload_2
     287: invokestatic  #74                 // InterfaceMethod java/util/stream/IntStream.range:(II)Ljava/util/stream/IntStream;
     290: aload_0
     291: aload_1
     292: aload         5
     294: invokedynamic #91,  0             // InvokeDynamic #7:accept:(Lorg/apache/hadoop/hbase/client/TestAsyncTable;Lorg/apache/hadoop/hbase/client/AsyncTable;Ljava/util/concurrent/BlockingQueue;)Ljava/util/function/IntConsumer;
     299: invokeinterface #76,  2           // InterfaceMethod java/util/stream/IntStream.forEach:(Ljava/util/function/IntConsumer;)V
     304: iconst_0
     305: istore        7
     307: iload         7
     309: iload_2
     310: if_icmpge     345
     313: aload         5
     315: invokeinterface #81,  1           // InterfaceMethod java/util/concurrent/BlockingQueue.take:()Ljava/lang/Object;
     320: checkcast     #83                 // class org/apache/hadoop/hbase/util/Pair
     323: astore        8
     325: aload         8
     327: invokevirtual #88                 // Method org/apache/hadoop/hbase/util/Pair.getSecond:()Ljava/lang/Object;
     330: checkcast     #58                 // class org/apache/hadoop/hbase/client/Result
     333: invokevirtual #64                 // Method org/apache/hadoop/hbase/client/Result.isEmpty:()Z
     336: invokestatic  #31                 // Method org/junit/Assert.assertTrue:(Z)V
     339: iinc          7, 1
     342: goto          307
     345: return

  public void testIncrement() throws java.lang.InterruptedException, java.util.concurrent.ExecutionException;
    Code:
       0: aload_0
       1: getfield      #44                 // Field getTable:Ljava/util/function/Supplier;
       4: invokeinterface #45,  1           // InterfaceMethod java/util/function/Supplier.get:()Ljava/lang/Object;
       9: checkcast     #46                 // class org/apache/hadoop/hbase/client/AsyncTable
      12: astore_1
      13: bipush        100
      15: istore_2
      16: new           #72                 // class java/util/concurrent/CountDownLatch
      19: dup
      20: iload_2
      21: invokespecial #73                 // Method java/util/concurrent/CountDownLatch."<init>":(I)V
      24: astore_3
      25: new           #92                 // class java/util/concurrent/atomic/AtomicLong
      28: dup
      29: lconst_0
      30: invokespecial #93                 // Method java/util/concurrent/atomic/AtomicLong."<init>":(J)V
      33: astore        4
      35: iconst_0
      36: iload_2
      37: invokestatic  #74                 // InterfaceMethod java/util/stream/IntStream.range:(II)Ljava/util/stream/IntStream;
      40: aload_0
      41: aload_1
      42: aload         4
      44: aload_3
      45: invokedynamic #94,  0             // InvokeDynamic #8:accept:(Lorg/apache/hadoop/hbase/client/TestAsyncTable;Lorg/apache/hadoop/hbase/client/AsyncTable;Ljava/util/concurrent/atomic/AtomicLong;Ljava/util/concurrent/CountDownLatch;)Ljava/util/function/IntConsumer;
      50: invokeinterface #76,  2           // InterfaceMethod java/util/stream/IntStream.forEach:(Ljava/util/function/IntConsumer;)V
      55: aload_3
      56: invokevirtual #77                 // Method java/util/concurrent/CountDownLatch.await:()V
      59: iload_2
      60: i2l
      61: aload_1
      62: new           #53                 // class org/apache/hadoop/hbase/client/Get
      65: dup
      66: aload_0
      67: getfield      #38                 // Field row:[B
      70: invokespecial #54                 // Method org/apache/hadoop/hbase/client/Get."<init>":([B)V
      73: getstatic     #22                 // Field FAMILY:[B
      76: getstatic     #49                 // Field QUALIFIER:[B
      79: invokevirtual #55                 // Method org/apache/hadoop/hbase/client/Get.addColumn:([B[B)Lorg/apache/hadoop/hbase/client/Get;
      82: invokeinterface #57,  2           // InterfaceMethod org/apache/hadoop/hbase/client/AsyncTable.get:(Lorg/apache/hadoop/hbase/client/Get;)Ljava/util/concurrent/CompletableFuture;
      87: invokevirtual #26                 // Method java/util/concurrent/CompletableFuture.get:()Ljava/lang/Object;
      90: checkcast     #58                 // class org/apache/hadoop/hbase/client/Result
      93: getstatic     #22                 // Field FAMILY:[B
      96: getstatic     #49                 // Field QUALIFIER:[B
      99: invokevirtual #59                 // Method org/apache/hadoop/hbase/client/Result.getValue:([B[B)[B
     102: invokestatic  #95                 // Method org/apache/hadoop/hbase/util/Bytes.toLong:([B)J
     105: invokestatic  #96                 // Method org/junit/Assert.assertEquals:(JJ)V
     108: iconst_1
     109: iload_2
     110: iadd
     111: iload_2
     112: imul
     113: iconst_2
     114: idiv
     115: i2l
     116: aload         4
     118: invokevirtual #97                 // Method java/util/concurrent/atomic/AtomicLong.get:()J
     121: invokestatic  #96                 // Method org/junit/Assert.assertEquals:(JJ)V
     124: return

  public void testAppend() throws java.lang.InterruptedException, java.util.concurrent.ExecutionException;
    Code:
       0: aload_0
       1: getfield      #44                 // Field getTable:Ljava/util/function/Supplier;
       4: invokeinterface #45,  1           // InterfaceMethod java/util/function/Supplier.get:()Ljava/lang/Object;
       9: checkcast     #46                 // class org/apache/hadoop/hbase/client/AsyncTable
      12: astore_1
      13: bipush        10
      15: istore_2
      16: new           #72                 // class java/util/concurrent/CountDownLatch
      19: dup
      20: iload_2
      21: invokespecial #73                 // Method java/util/concurrent/CountDownLatch."<init>":(I)V
      24: astore_3
      25: bipush        58
      27: istore        4
      29: new           #92                 // class java/util/concurrent/atomic/AtomicLong
      32: dup
      33: lconst_0
      34: invokespecial #93                 // Method java/util/concurrent/atomic/AtomicLong."<init>":(J)V
      37: astore        5
      39: iconst_0
      40: iload_2
      41: invokestatic  #74                 // InterfaceMethod java/util/stream/IntStream.range:(II)Ljava/util/stream/IntStream;
      44: aload_0
      45: aload_1
      46: iload         4
      48: aload         5
      50: aload_3
      51: invokedynamic #98,  0             // InvokeDynamic #9:accept:(Lorg/apache/hadoop/hbase/client/TestAsyncTable;Lorg/apache/hadoop/hbase/client/AsyncTable;CLjava/util/concurrent/atomic/AtomicLong;Ljava/util/concurrent/CountDownLatch;)Ljava/util/function/IntConsumer;
      56: invokeinterface #99,  2           // InterfaceMethod java/util/stream/IntStream.forEachOrdered:(Ljava/util/function/IntConsumer;)V
      61: aload_3
      62: invokevirtual #77                 // Method java/util/concurrent/CountDownLatch.await:()V
      65: iconst_1
      66: iload_2
      67: iadd
      68: iload_2
      69: imul
      70: iconst_2
      71: idiv
      72: i2l
      73: aload         5
      75: invokevirtual #97                 // Method java/util/concurrent/atomic/AtomicLong.get:()J
      78: invokestatic  #96                 // Method org/junit/Assert.assertEquals:(JJ)V
      81: aload_1
      82: new           #53                 // class org/apache/hadoop/hbase/client/Get
      85: dup
      86: aload_0
      87: getfield      #38                 // Field row:[B
      90: invokespecial #54                 // Method org/apache/hadoop/hbase/client/Get."<init>":([B)V
      93: getstatic     #22                 // Field FAMILY:[B
      96: getstatic     #49                 // Field QUALIFIER:[B
      99: invokevirtual #55                 // Method org/apache/hadoop/hbase/client/Get.addColumn:([B[B)Lorg/apache/hadoop/hbase/client/Get;
     102: invokeinterface #57,  2           // InterfaceMethod org/apache/hadoop/hbase/client/AsyncTable.get:(Lorg/apache/hadoop/hbase/client/Get;)Ljava/util/concurrent/CompletableFuture;
     107: invokevirtual #26                 // Method java/util/concurrent/CompletableFuture.get:()Ljava/lang/Object;
     110: checkcast     #58                 // class org/apache/hadoop/hbase/client/Result
     113: getstatic     #22                 // Field FAMILY:[B
     116: getstatic     #49                 // Field QUALIFIER:[B
     119: invokevirtual #59                 // Method org/apache/hadoop/hbase/client/Result.getValue:([B[B)[B
     122: invokestatic  #67                 // Method org/apache/hadoop/hbase/util/Bytes.toString:([B)Ljava/lang/String;
     125: astore        6
     127: aload         6
     129: new           #65                 // class java/lang/StringBuilder
     132: dup
     133: invokespecial #66                 // Method java/lang/StringBuilder."<init>":()V
     136: ldc           #100                // String
     138: invokevirtual #68                 // Method java/lang/StringBuilder.append:(Ljava/lang/String;)Ljava/lang/StringBuilder;
     141: iload         4
     143: invokevirtual #101                // Method java/lang/StringBuilder.append:(C)Ljava/lang/StringBuilder;
     146: invokevirtual #71                 // Method java/lang/StringBuilder.toString:()Ljava/lang/String;
     149: invokevirtual #102                // Method java/lang/String.split:(Ljava/lang/String;)[Ljava/lang/String;
     152: invokestatic  #14                 // Method java/util/Arrays.asList:([Ljava/lang/Object;)Ljava/util/List;
     155: invokeinterface #103,  1          // InterfaceMethod java/util/List.stream:()Ljava/util/stream/Stream;
     160: invokedynamic #104,  0            // InvokeDynamic #10:applyAsInt:()Ljava/util/function/ToIntFunction;
     165: invokeinterface #105,  2          // InterfaceMethod java/util/stream/Stream.mapToInt:(Ljava/util/function/ToIntFunction;)Ljava/util/stream/IntStream;
     170: invokeinterface #106,  1          // InterfaceMethod java/util/stream/IntStream.sorted:()Ljava/util/stream/IntStream;
     175: invokeinterface #107,  1          // InterfaceMethod java/util/stream/IntStream.toArray:()[I
     180: astore        7
     182: iconst_0
     183: iload_2
     184: invokestatic  #74                 // InterfaceMethod java/util/stream/IntStream.range:(II)Ljava/util/stream/IntStream;
     187: invokeinterface #107,  1          // InterfaceMethod java/util/stream/IntStream.toArray:()[I
     192: aload         7
     194: invokestatic  #108                // Method org/junit/Assert.assertArrayEquals:([I[I)V
     197: return

  public void testCheckAndPut() throws java.lang.InterruptedException, java.util.concurrent.ExecutionException;
    Code:
       0: aload_0
       1: getfield      #44                 // Field getTable:Ljava/util/function/Supplier;
       4: invokeinterface #45,  1           // InterfaceMethod java/util/function/Supplier.get:()Ljava/lang/Object;
       9: checkcast     #46                 // class org/apache/hadoop/hbase/client/AsyncTable
      12: astore_1
      13: new           #109                // class java/util/concurrent/atomic/AtomicInteger
      16: dup
      17: iconst_0
      18: invokespecial #110                // Method java/util/concurrent/atomic/AtomicInteger."<init>":(I)V
      21: astore_2
      22: new           #109                // class java/util/concurrent/atomic/AtomicInteger
      25: dup
      26: iconst_m1
      27: invokespecial #110                // Method java/util/concurrent/atomic/AtomicInteger."<init>":(I)V
      30: astore_3
      31: bipush        10
      33: istore        4
      35: new           #72                 // class java/util/concurrent/CountDownLatch
      38: dup
      39: iload         4
      41: invokespecial #73                 // Method java/util/concurrent/CountDownLatch."<init>":(I)V
      44: astore        5
      46: iconst_0
      47: iload         4
      49: invokestatic  #74                 // InterfaceMethod java/util/stream/IntStream.range:(II)Ljava/util/stream/IntStream;
      52: aload_0
      53: aload_1
      54: aload_2
      55: aload_3
      56: aload         5
      58: invokedynamic #111,  0            // InvokeDynamic #11:accept:(Lorg/apache/hadoop/hbase/client/TestAsyncTable;Lorg/apache/hadoop/hbase/client/AsyncTable;Ljava/util/concurrent/atomic/AtomicInteger;Ljava/util/concurrent/atomic/AtomicInteger;Ljava/util/concurrent/CountDownLatch;)Ljava/util/function/IntConsumer;
      63: invokeinterface #76,  2           // InterfaceMethod java/util/stream/IntStream.forEach:(Ljava/util/function/IntConsumer;)V
      68: aload         5
      70: invokevirtual #77                 // Method java/util/concurrent/CountDownLatch.await:()V
      73: lconst_1
      74: aload_2
      75: invokevirtual #112                // Method java/util/concurrent/atomic/AtomicInteger.get:()I
      78: i2l
      79: invokestatic  #96                 // Method org/junit/Assert.assertEquals:(JJ)V
      82: aload_1
      83: new           #53                 // class org/apache/hadoop/hbase/client/Get
      86: dup
      87: aload_0
      88: getfield      #38                 // Field row:[B
      91: invokespecial #54                 // Method org/apache/hadoop/hbase/client/Get."<init>":([B)V
      94: invokeinterface #57,  2           // InterfaceMethod org/apache/hadoop/hbase/client/AsyncTable.get:(Lorg/apache/hadoop/hbase/client/Get;)Ljava/util/concurrent/CompletableFuture;
      99: invokevirtual #26                 // Method java/util/concurrent/CompletableFuture.get:()Ljava/lang/Object;
     102: checkcast     #58                 // class org/apache/hadoop/hbase/client/Result
     105: getstatic     #22                 // Field FAMILY:[B
     108: getstatic     #49                 // Field QUALIFIER:[B
     111: invokevirtual #59                 // Method org/apache/hadoop/hbase/client/Result.getValue:([B[B)[B
     114: invokestatic  #67                 // Method org/apache/hadoop/hbase/util/Bytes.toString:([B)Ljava/lang/String;
     117: astore        6
     119: aload         6
     121: aload_3
     122: invokevirtual #112                // Method java/util/concurrent/atomic/AtomicInteger.get:()I
     125: invokestatic  #113                // Method java/lang/Integer.toString:(I)Ljava/lang/String;
     128: invokevirtual #114                // Method java/lang/String.endsWith:(Ljava/lang/String;)Z
     131: invokestatic  #31                 // Method org/junit/Assert.assertTrue:(Z)V
     134: return

  public void testCheckAndDelete() throws java.lang.InterruptedException, java.util.concurrent.ExecutionException;
    Code:
       0: aload_0
       1: getfield      #44                 // Field getTable:Ljava/util/function/Supplier;
       4: invokeinterface #45,  1           // InterfaceMethod java/util/function/Supplier.get:()Ljava/lang/Object;
       9: checkcast     #46                 // class org/apache/hadoop/hbase/client/AsyncTable
      12: astore_1
      13: bipush        10
      15: istore_2
      16: new           #72                 // class java/util/concurrent/CountDownLatch
      19: dup
      20: iload_2
      21: iconst_1
      22: iadd
      23: invokespecial #73                 // Method java/util/concurrent/CountDownLatch."<init>":(I)V
      26: astore_3
      27: aload_1
      28: new           #47                 // class org/apache/hadoop/hbase/client/Put
      31: dup
      32: aload_0
      33: getfield      #38                 // Field row:[B
      36: invokespecial #48                 // Method org/apache/hadoop/hbase/client/Put."<init>":([B)V
      39: getstatic     #22                 // Field FAMILY:[B
      42: getstatic     #49                 // Field QUALIFIER:[B
      45: getstatic     #50                 // Field VALUE:[B
      48: invokevirtual #51                 // Method org/apache/hadoop/hbase/client/Put.addColumn:([B[B[B)Lorg/apache/hadoop/hbase/client/Put;
      51: invokeinterface #52,  2           // InterfaceMethod org/apache/hadoop/hbase/client/AsyncTable.put:(Lorg/apache/hadoop/hbase/client/Put;)Ljava/util/concurrent/CompletableFuture;
      56: aload_3
      57: invokedynamic #115,  0            // InvokeDynamic #12:run:(Ljava/util/concurrent/CountDownLatch;)Ljava/lang/Runnable;
      62: invokevirtual #116                // Method java/util/concurrent/CompletableFuture.thenRun:(Ljava/lang/Runnable;)Ljava/util/concurrent/CompletableFuture;
      65: pop
      66: iconst_0
      67: iload_2
      68: invokestatic  #74                 // InterfaceMethod java/util/stream/IntStream.range:(II)Ljava/util/stream/IntStream;
      71: aload_0
      72: aload_1
      73: aload_3
      74: invokedynamic #117,  0            // InvokeDynamic #13:accept:(Lorg/apache/hadoop/hbase/client/TestAsyncTable;Lorg/apache/hadoop/hbase/client/AsyncTable;Ljava/util/concurrent/CountDownLatch;)Ljava/util/function/IntConsumer;
      79: invokeinterface #76,  2           // InterfaceMethod java/util/stream/IntStream.forEach:(Ljava/util/function/IntConsumer;)V
      84: aload_3
      85: invokevirtual #77                 // Method java/util/concurrent/CountDownLatch.await:()V
      88: new           #109                // class java/util/concurrent/atomic/AtomicInteger
      91: dup
      92: iconst_0
      93: invokespecial #110                // Method java/util/concurrent/atomic/AtomicInteger."<init>":(I)V
      96: astore        4
      98: new           #109                // class java/util/concurrent/atomic/AtomicInteger
     101: dup
     102: iconst_m1
     103: invokespecial #110                // Method java/util/concurrent/atomic/AtomicInteger."<init>":(I)V
     106: astore        5
     108: new           #72                 // class java/util/concurrent/CountDownLatch
     111: dup
     112: iload_2
     113: invokespecial #73                 // Method java/util/concurrent/CountDownLatch."<init>":(I)V
     116: astore        6
     118: iconst_0
     119: iload_2
     120: invokestatic  #74                 // InterfaceMethod java/util/stream/IntStream.range:(II)Ljava/util/stream/IntStream;
     123: aload_0
     124: aload_1
     125: aload         4
     127: aload         5
     129: aload         6
     131: invokedynamic #118,  0            // InvokeDynamic #14:accept:(Lorg/apache/hadoop/hbase/client/TestAsyncTable;Lorg/apache/hadoop/hbase/client/AsyncTable;Ljava/util/concurrent/atomic/AtomicInteger;Ljava/util/concurrent/atomic/AtomicInteger;Ljava/util/concurrent/CountDownLatch;)Ljava/util/function/IntConsumer;
     136: invokeinterface #76,  2           // InterfaceMethod java/util/stream/IntStream.forEach:(Ljava/util/function/IntConsumer;)V
     141: aload         6
     143: invokevirtual #77                 // Method java/util/concurrent/CountDownLatch.await:()V
     146: lconst_1
     147: aload         4
     149: invokevirtual #112                // Method java/util/concurrent/atomic/AtomicInteger.get:()I
     152: i2l
     153: invokestatic  #96                 // Method org/junit/Assert.assertEquals:(JJ)V
     156: aload_1
     157: new           #53                 // class org/apache/hadoop/hbase/client/Get
     160: dup
     161: aload_0
     162: getfield      #38                 // Field row:[B
     165: invokespecial #54                 // Method org/apache/hadoop/hbase/client/Get."<init>":([B)V
     168: invokeinterface #57,  2           // InterfaceMethod org/apache/hadoop/hbase/client/AsyncTable.get:(Lorg/apache/hadoop/hbase/client/Get;)Ljava/util/concurrent/CompletableFuture;
     173: invokevirtual #26                 // Method java/util/concurrent/CompletableFuture.get:()Ljava/lang/Object;
     176: checkcast     #58                 // class org/apache/hadoop/hbase/client/Result
     179: astore        7
     181: iconst_0
     182: iload_2
     183: invokestatic  #74                 // InterfaceMethod java/util/stream/IntStream.range:(II)Ljava/util/stream/IntStream;
     186: aload_0
     187: aload         5
     189: aload         7
     191: invokedynamic #119,  0            // InvokeDynamic #15:accept:(Lorg/apache/hadoop/hbase/client/TestAsyncTable;Ljava/util/concurrent/atomic/AtomicInteger;Lorg/apache/hadoop/hbase/client/Result;)Ljava/util/function/IntConsumer;
     196: invokeinterface #76,  2           // InterfaceMethod java/util/stream/IntStream.forEach:(Ljava/util/function/IntConsumer;)V
     201: return

  public void testMutateRow() throws java.lang.InterruptedException, java.util.concurrent.ExecutionException, java.io.IOException;
    Code:
       0: aload_0
       1: getfield      #44                 // Field getTable:Ljava/util/function/Supplier;
       4: invokeinterface #45,  1           // InterfaceMethod java/util/function/Supplier.get:()Ljava/lang/Object;
       9: checkcast     #46                 // class org/apache/hadoop/hbase/client/AsyncTable
      12: astore_1
      13: new           #120                // class org/apache/hadoop/hbase/client/RowMutations
      16: dup
      17: aload_0
      18: getfield      #38                 // Field row:[B
      21: invokespecial #121                // Method org/apache/hadoop/hbase/client/RowMutations."<init>":([B)V
      24: astore_2
      25: aload_2
      26: new           #47                 // class org/apache/hadoop/hbase/client/Put
      29: dup
      30: aload_0
      31: getfield      #38                 // Field row:[B
      34: invokespecial #48                 // Method org/apache/hadoop/hbase/client/Put."<init>":([B)V
      37: getstatic     #22                 // Field FAMILY:[B
      40: aload_0
      41: getstatic     #49                 // Field QUALIFIER:[B
      44: iconst_1
      45: invokespecial #87                 // Method concat:([BI)[B
      48: getstatic     #50                 // Field VALUE:[B
      51: invokevirtual #51                 // Method org/apache/hadoop/hbase/client/Put.addColumn:([B[B[B)Lorg/apache/hadoop/hbase/client/Put;
      54: invokevirtual #122                // Method org/apache/hadoop/hbase/client/RowMutations.add:(Lorg/apache/hadoop/hbase/client/Mutation;)Lorg/apache/hadoop/hbase/client/RowMutations;
      57: pop
      58: aload_1
      59: aload_2
      60: invokeinterface #123,  2          // InterfaceMethod org/apache/hadoop/hbase/client/AsyncTable.mutateRow:(Lorg/apache/hadoop/hbase/client/RowMutations;)Ljava/util/concurrent/CompletableFuture;
      65: invokevirtual #26                 // Method java/util/concurrent/CompletableFuture.get:()Ljava/lang/Object;
      68: pop
      69: aload_1
      70: new           #53                 // class org/apache/hadoop/hbase/client/Get
      73: dup
      74: aload_0
      75: getfield      #38                 // Field row:[B
      78: invokespecial #54                 // Method org/apache/hadoop/hbase/client/Get."<init>":([B)V
      81: invokeinterface #57,  2           // InterfaceMethod org/apache/hadoop/hbase/client/AsyncTable.get:(Lorg/apache/hadoop/hbase/client/Get;)Ljava/util/concurrent/CompletableFuture;
      86: invokevirtual #26                 // Method java/util/concurrent/CompletableFuture.get:()Ljava/lang/Object;
      89: checkcast     #58                 // class org/apache/hadoop/hbase/client/Result
      92: astore_3
      93: getstatic     #50                 // Field VALUE:[B
      96: aload_3
      97: getstatic     #22                 // Field FAMILY:[B
     100: aload_0
     101: getstatic     #49                 // Field QUALIFIER:[B
     104: iconst_1
     105: invokespecial #87                 // Method concat:([BI)[B
     108: invokevirtual #59                 // Method org/apache/hadoop/hbase/client/Result.getValue:([B[B)[B
     111: invokestatic  #60                 // Method org/junit/Assert.assertArrayEquals:([B[B)V
     114: new           #120                // class org/apache/hadoop/hbase/client/RowMutations
     117: dup
     118: aload_0
     119: getfield      #38                 // Field row:[B
     122: invokespecial #121                // Method org/apache/hadoop/hbase/client/RowMutations."<init>":([B)V
     125: astore_2
     126: aload_2
     127: new           #61                 // class org/apache/hadoop/hbase/client/Delete
     130: dup
     131: aload_0
     132: getfield      #38                 // Field row:[B
     135: invokespecial #62                 // Method org/apache/hadoop/hbase/client/Delete."<init>":([B)V
     138: getstatic     #22                 // Field FAMILY:[B
     141: aload_0
     142: getstatic     #49                 // Field QUALIFIER:[B
     145: iconst_1
     146: invokespecial #87                 // Method concat:([BI)[B
     149: invokevirtual #124                // Method org/apache/hadoop/hbase/client/Delete.addColumn:([B[B)Lorg/apache/hadoop/hbase/client/Delete;
     152: invokevirtual #122                // Method org/apache/hadoop/hbase/client/RowMutations.add:(Lorg/apache/hadoop/hbase/client/Mutation;)Lorg/apache/hadoop/hbase/client/RowMutations;
     155: pop
     156: aload_2
     157: new           #47                 // class org/apache/hadoop/hbase/client/Put
     160: dup
     161: aload_0
     162: getfield      #38                 // Field row:[B
     165: invokespecial #48                 // Method org/apache/hadoop/hbase/client/Put."<init>":([B)V
     168: getstatic     #22                 // Field FAMILY:[B
     171: aload_0
     172: getstatic     #49                 // Field QUALIFIER:[B
     175: iconst_2
     176: invokespecial #87                 // Method concat:([BI)[B
     179: getstatic     #50                 // Field VALUE:[B
     182: invokevirtual #51                 // Method org/apache/hadoop/hbase/client/Put.addColumn:([B[B[B)Lorg/apache/hadoop/hbase/client/Put;
     185: invokevirtual #122                // Method org/apache/hadoop/hbase/client/RowMutations.add:(Lorg/apache/hadoop/hbase/client/Mutation;)Lorg/apache/hadoop/hbase/client/RowMutations;
     188: pop
     189: aload_1
     190: aload_2
     191: invokeinterface #123,  2          // InterfaceMethod org/apache/hadoop/hbase/client/AsyncTable.mutateRow:(Lorg/apache/hadoop/hbase/client/RowMutations;)Ljava/util/concurrent/CompletableFuture;
     196: invokevirtual #26                 // Method java/util/concurrent/CompletableFuture.get:()Ljava/lang/Object;
     199: pop
     200: aload_1
     201: new           #53                 // class org/apache/hadoop/hbase/client/Get
     204: dup
     205: aload_0
     206: getfield      #38                 // Field row:[B
     209: invokespecial #54                 // Method org/apache/hadoop/hbase/client/Get."<init>":([B)V
     212: invokeinterface #57,  2           // InterfaceMethod org/apache/hadoop/hbase/client/AsyncTable.get:(Lorg/apache/hadoop/hbase/client/Get;)Ljava/util/concurrent/CompletableFuture;
     217: invokevirtual #26                 // Method java/util/concurrent/CompletableFuture.get:()Ljava/lang/Object;
     220: checkcast     #58                 // class org/apache/hadoop/hbase/client/Result
     223: astore_3
     224: aload_3
     225: getstatic     #22                 // Field FAMILY:[B
     228: aload_0
     229: getstatic     #49                 // Field QUALIFIER:[B
     232: iconst_1
     233: invokespecial #87                 // Method concat:([BI)[B
     236: invokevirtual #59                 // Method org/apache/hadoop/hbase/client/Result.getValue:([B[B)[B
     239: invokestatic  #125                // Method org/junit/Assert.assertNull:(Ljava/lang/Object;)V
     242: getstatic     #50                 // Field VALUE:[B
     245: aload_3
     246: getstatic     #22                 // Field FAMILY:[B
     249: aload_0
     250: getstatic     #49                 // Field QUALIFIER:[B
     253: iconst_2
     254: invokespecial #87                 // Method concat:([BI)[B
     257: invokevirtual #59                 // Method org/apache/hadoop/hbase/client/Result.getValue:([B[B)[B
     260: invokestatic  #60                 // Method org/junit/Assert.assertArrayEquals:([B[B)V
     263: return

  public void testCheckAndMutate() throws java.lang.InterruptedException, java.util.concurrent.ExecutionException;
    Code:
       0: aload_0
       1: getfield      #44                 // Field getTable:Ljava/util/function/Supplier;
       4: invokeinterface #45,  1           // InterfaceMethod java/util/function/Supplier.get:()Ljava/lang/Object;
       9: checkcast     #46                 // class org/apache/hadoop/hbase/client/AsyncTable
      12: astore_1
      13: bipush        10
      15: istore_2
      16: new           #72                 // class java/util/concurrent/CountDownLatch
      19: dup
      20: iload_2
      21: iconst_1
      22: iadd
      23: invokespecial #73                 // Method java/util/concurrent/CountDownLatch."<init>":(I)V
      26: astore_3
      27: aload_1
      28: new           #47                 // class org/apache/hadoop/hbase/client/Put
      31: dup
      32: aload_0
      33: getfield      #38                 // Field row:[B
      36: invokespecial #48                 // Method org/apache/hadoop/hbase/client/Put."<init>":([B)V
      39: getstatic     #22                 // Field FAMILY:[B
      42: getstatic     #49                 // Field QUALIFIER:[B
      45: getstatic     #50                 // Field VALUE:[B
      48: invokevirtual #51                 // Method org/apache/hadoop/hbase/client/Put.addColumn:([B[B[B)Lorg/apache/hadoop/hbase/client/Put;
      51: invokeinterface #52,  2           // InterfaceMethod org/apache/hadoop/hbase/client/AsyncTable.put:(Lorg/apache/hadoop/hbase/client/Put;)Ljava/util/concurrent/CompletableFuture;
      56: aload_3
      57: invokedynamic #126,  0            // InvokeDynamic #16:run:(Ljava/util/concurrent/CountDownLatch;)Ljava/lang/Runnable;
      62: invokevirtual #116                // Method java/util/concurrent/CompletableFuture.thenRun:(Ljava/lang/Runnable;)Ljava/util/concurrent/CompletableFuture;
      65: pop
      66: iconst_0
      67: iload_2
      68: invokestatic  #74                 // InterfaceMethod java/util/stream/IntStream.range:(II)Ljava/util/stream/IntStream;
      71: aload_0
      72: aload_1
      73: aload_3
      74: invokedynamic #127,  0            // InvokeDynamic #17:accept:(Lorg/apache/hadoop/hbase/client/TestAsyncTable;Lorg/apache/hadoop/hbase/client/AsyncTable;Ljava/util/concurrent/CountDownLatch;)Ljava/util/function/IntConsumer;
      79: invokeinterface #76,  2           // InterfaceMethod java/util/stream/IntStream.forEach:(Ljava/util/function/IntConsumer;)V
      84: aload_3
      85: invokevirtual #77                 // Method java/util/concurrent/CountDownLatch.await:()V
      88: new           #109                // class java/util/concurrent/atomic/AtomicInteger
      91: dup
      92: iconst_0
      93: invokespecial #110                // Method java/util/concurrent/atomic/AtomicInteger."<init>":(I)V
      96: astore        4
      98: new           #109                // class java/util/concurrent/atomic/AtomicInteger
     101: dup
     102: iconst_m1
     103: invokespecial #110                // Method java/util/concurrent/atomic/AtomicInteger."<init>":(I)V
     106: astore        5
     108: new           #72                 // class java/util/concurrent/CountDownLatch
     111: dup
     112: iload_2
     113: invokespecial #73                 // Method java/util/concurrent/CountDownLatch."<init>":(I)V
     116: astore        6
     118: iconst_0
     119: iload_2
     120: invokestatic  #74                 // InterfaceMethod java/util/stream/IntStream.range:(II)Ljava/util/stream/IntStream;
     123: aload_0
     124: aload_1
     125: aload         4
     127: aload         5
     129: aload         6
     131: invokedynamic #128,  0            // InvokeDynamic #18:accept:(Lorg/apache/hadoop/hbase/client/TestAsyncTable;Lorg/apache/hadoop/hbase/client/AsyncTable;Ljava/util/concurrent/atomic/AtomicInteger;Ljava/util/concurrent/atomic/AtomicInteger;Ljava/util/concurrent/CountDownLatch;)Ljava/util/function/IntConsumer;
     136: invokeinterface #76,  2           // InterfaceMethod java/util/stream/IntStream.forEach:(Ljava/util/function/IntConsumer;)V
     141: aload         6
     143: invokevirtual #77                 // Method java/util/concurrent/CountDownLatch.await:()V
     146: lconst_1
     147: aload         4
     149: invokevirtual #112                // Method java/util/concurrent/atomic/AtomicInteger.get:()I
     152: i2l
     153: invokestatic  #96                 // Method org/junit/Assert.assertEquals:(JJ)V
     156: aload_1
     157: new           #53                 // class org/apache/hadoop/hbase/client/Get
     160: dup
     161: aload_0
     162: getfield      #38                 // Field row:[B
     165: invokespecial #54                 // Method org/apache/hadoop/hbase/client/Get."<init>":([B)V
     168: invokeinterface #57,  2           // InterfaceMethod org/apache/hadoop/hbase/client/AsyncTable.get:(Lorg/apache/hadoop/hbase/client/Get;)Ljava/util/concurrent/CompletableFuture;
     173: invokevirtual #26                 // Method java/util/concurrent/CompletableFuture.get:()Ljava/lang/Object;
     176: checkcast     #58                 // class org/apache/hadoop/hbase/client/Result
     179: astore        7
     181: iconst_0
     182: iload_2
     183: invokestatic  #74                 // InterfaceMethod java/util/stream/IntStream.range:(II)Ljava/util/stream/IntStream;
     186: aload_0
     187: aload         5
     189: aload         7
     191: invokedynamic #129,  0            // InvokeDynamic #19:accept:(Lorg/apache/hadoop/hbase/client/TestAsyncTable;Ljava/util/concurrent/atomic/AtomicInteger;Lorg/apache/hadoop/hbase/client/Result;)Ljava/util/function/IntConsumer;
     196: invokeinterface #76,  2           // InterfaceMethod java/util/stream/IntStream.forEach:(Ljava/util/function/IntConsumer;)V
     201: return

  public void testCheckAndMutateWithTimeRange() throws java.lang.Exception;
    Code:
       0: aload_0
       1: getfield      #44                 // Field getTable:Ljava/util/function/Supplier;
       4: invokeinterface #45,  1           // InterfaceMethod java/util/function/Supplier.get:()Ljava/lang/Object;
       9: checkcast     #46                 // class org/apache/hadoop/hbase/client/AsyncTable
      12: astore_1
      13: invokestatic  #130                // Method java/lang/System.currentTimeMillis:()J
      16: ldc2_w        #131                // long 2l
      19: ldiv
      20: lstore_2
      21: new           #47                 // class org/apache/hadoop/hbase/client/Put
      24: dup
      25: aload_0
      26: getfield      #38                 // Field row:[B
      29: invokespecial #48                 // Method org/apache/hadoop/hbase/client/Put."<init>":([B)V
      32: astore        4
      34: aload         4
      36: getstatic     #22                 // Field FAMILY:[B
      39: getstatic     #49                 // Field QUALIFIER:[B
      42: lload_2
      43: getstatic     #50                 // Field VALUE:[B
      46: invokevirtual #133                // Method org/apache/hadoop/hbase/client/Put.addColumn:([B[BJ[B)Lorg/apache/hadoop/hbase/client/Put;
      49: pop
      50: aload_1
      51: aload_0
      52: getfield      #38                 // Field row:[B
      55: getstatic     #22                 // Field FAMILY:[B
      58: invokeinterface #134,  3          // InterfaceMethod org/apache/hadoop/hbase/client/AsyncTable.checkAndMutate:([B[B)Lorg/apache/hadoop/hbase/client/AsyncTable$CheckAndMutateBuilder;
      63: getstatic     #49                 // Field QUALIFIER:[B
      66: invokeinterface #135,  2          // InterfaceMethod org/apache/hadoop/hbase/client/AsyncTable$CheckAndMutateBuilder.qualifier:([B)Lorg/apache/hadoop/hbase/client/AsyncTable$CheckAndMutateBuilder;
      71: invokeinterface #136,  1          // InterfaceMethod org/apache/hadoop/hbase/client/AsyncTable$CheckAndMutateBuilder.ifNotExists:()Lorg/apache/hadoop/hbase/client/AsyncTable$CheckAndMutateBuilder;
      76: aload         4
      78: invokeinterface #137,  2          // InterfaceMethod org/apache/hadoop/hbase/client/AsyncTable$CheckAndMutateBuilder.thenPut:(Lorg/apache/hadoop/hbase/client/Put;)Ljava/util/concurrent/CompletableFuture;
      83: invokevirtual #26                 // Method java/util/concurrent/CompletableFuture.get:()Ljava/lang/Object;
      86: checkcast     #41                 // class java/lang/Boolean
      89: invokevirtual #42                 // Method java/lang/Boolean.booleanValue:()Z
      92: istore        5
      94: iload         5
      96: invokestatic  #31                 // Method org/junit/Assert.assertTrue:(Z)V
      99: aload_1
     100: aload_0
     101: getfield      #38                 // Field row:[B
     104: getstatic     #22                 // Field FAMILY:[B
     107: invokeinterface #134,  3          // InterfaceMethod org/apache/hadoop/hbase/client/AsyncTable.checkAndMutate:([B[B)Lorg/apache/hadoop/hbase/client/AsyncTable$CheckAndMutateBuilder;
     112: getstatic     #49                 // Field QUALIFIER:[B
     115: invokeinterface #135,  2          // InterfaceMethod org/apache/hadoop/hbase/client/AsyncTable$CheckAndMutateBuilder.qualifier:([B)Lorg/apache/hadoop/hbase/client/AsyncTable$CheckAndMutateBuilder;
     120: lload_2
     121: ldc2_w        #138                // long 10000l
     124: ladd
     125: invokestatic  #140                // Method org/apache/hadoop/hbase/io/TimeRange.at:(J)Lorg/apache/hadoop/hbase/io/TimeRange;
     128: invokeinterface #141,  2          // InterfaceMethod org/apache/hadoop/hbase/client/AsyncTable$CheckAndMutateBuilder.timeRange:(Lorg/apache/hadoop/hbase/io/TimeRange;)Lorg/apache/hadoop/hbase/client/AsyncTable$CheckAndMutateBuilder;
     133: getstatic     #50                 // Field VALUE:[B
     136: invokeinterface #142,  2          // InterfaceMethod org/apache/hadoop/hbase/client/AsyncTable$CheckAndMutateBuilder.ifEquals:([B)Lorg/apache/hadoop/hbase/client/AsyncTable$CheckAndMutateBuilder;
     141: aload         4
     143: invokeinterface #137,  2          // InterfaceMethod org/apache/hadoop/hbase/client/AsyncTable$CheckAndMutateBuilder.thenPut:(Lorg/apache/hadoop/hbase/client/Put;)Ljava/util/concurrent/CompletableFuture;
     148: invokevirtual #26                 // Method java/util/concurrent/CompletableFuture.get:()Ljava/lang/Object;
     151: checkcast     #41                 // class java/lang/Boolean
     154: invokevirtual #42                 // Method java/lang/Boolean.booleanValue:()Z
     157: istore        5
     159: iload         5
     161: invokestatic  #29                 // Method org/junit/Assert.assertFalse:(Z)V
     164: aload_1
     165: aload_0
     166: getfield      #38                 // Field row:[B
     169: getstatic     #22                 // Field FAMILY:[B
     172: invokeinterface #134,  3          // InterfaceMethod org/apache/hadoop/hbase/client/AsyncTable.checkAndMutate:([B[B)Lorg/apache/hadoop/hbase/client/AsyncTable$CheckAndMutateBuilder;
     177: getstatic     #49                 // Field QUALIFIER:[B
     180: invokeinterface #135,  2          // InterfaceMethod org/apache/hadoop/hbase/client/AsyncTable$CheckAndMutateBuilder.qualifier:([B)Lorg/apache/hadoop/hbase/client/AsyncTable$CheckAndMutateBuilder;
     185: lload_2
     186: invokestatic  #140                // Method org/apache/hadoop/hbase/io/TimeRange.at:(J)Lorg/apache/hadoop/hbase/io/TimeRange;
     189: invokeinterface #141,  2          // InterfaceMethod org/apache/hadoop/hbase/client/AsyncTable$CheckAndMutateBuilder.timeRange:(Lorg/apache/hadoop/hbase/io/TimeRange;)Lorg/apache/hadoop/hbase/client/AsyncTable$CheckAndMutateBuilder;
     194: getstatic     #50                 // Field VALUE:[B
     197: invokeinterface #142,  2          // InterfaceMethod org/apache/hadoop/hbase/client/AsyncTable$CheckAndMutateBuilder.ifEquals:([B)Lorg/apache/hadoop/hbase/client/AsyncTable$CheckAndMutateBuilder;
     202: aload         4
     204: invokeinterface #137,  2          // InterfaceMethod org/apache/hadoop/hbase/client/AsyncTable$CheckAndMutateBuilder.thenPut:(Lorg/apache/hadoop/hbase/client/Put;)Ljava/util/concurrent/CompletableFuture;
     209: invokevirtual #26                 // Method java/util/concurrent/CompletableFuture.get:()Ljava/lang/Object;
     212: checkcast     #41                 // class java/lang/Boolean
     215: invokevirtual #42                 // Method java/lang/Boolean.booleanValue:()Z
     218: istore        5
     220: iload         5
     222: invokestatic  #31                 // Method org/junit/Assert.assertTrue:(Z)V
     225: new           #120                // class org/apache/hadoop/hbase/client/RowMutations
     228: dup
     229: aload_0
     230: getfield      #38                 // Field row:[B
     233: invokespecial #121                // Method org/apache/hadoop/hbase/client/RowMutations."<init>":([B)V
     236: aload         4
     238: invokevirtual #122                // Method org/apache/hadoop/hbase/client/RowMutations.add:(Lorg/apache/hadoop/hbase/client/Mutation;)Lorg/apache/hadoop/hbase/client/RowMutations;
     241: astore        6
     243: aload_1
     244: aload_0
     245: getfield      #38                 // Field row:[B
     248: getstatic     #22                 // Field FAMILY:[B
     251: invokeinterface #134,  3          // InterfaceMethod org/apache/hadoop/hbase/client/AsyncTable.checkAndMutate:([B[B)Lorg/apache/hadoop/hbase/client/AsyncTable$CheckAndMutateBuilder;
     256: getstatic     #49                 // Field QUALIFIER:[B
     259: invokeinterface #135,  2          // InterfaceMethod org/apache/hadoop/hbase/client/AsyncTable$CheckAndMutateBuilder.qualifier:([B)Lorg/apache/hadoop/hbase/client/AsyncTable$CheckAndMutateBuilder;
     264: lload_2
     265: ldc2_w        #138                // long 10000l
     268: ladd
     269: invokestatic  #140                // Method org/apache/hadoop/hbase/io/TimeRange.at:(J)Lorg/apache/hadoop/hbase/io/TimeRange;
     272: invokeinterface #141,  2          // InterfaceMethod org/apache/hadoop/hbase/client/AsyncTable$CheckAndMutateBuilder.timeRange:(Lorg/apache/hadoop/hbase/io/TimeRange;)Lorg/apache/hadoop/hbase/client/AsyncTable$CheckAndMutateBuilder;
     277: getstatic     #50                 // Field VALUE:[B
     280: invokeinterface #142,  2          // InterfaceMethod org/apache/hadoop/hbase/client/AsyncTable$CheckAndMutateBuilder.ifEquals:([B)Lorg/apache/hadoop/hbase/client/AsyncTable$CheckAndMutateBuilder;
     285: aload         6
     287: invokeinterface #143,  2          // InterfaceMethod org/apache/hadoop/hbase/client/AsyncTable$CheckAndMutateBuilder.thenMutate:(Lorg/apache/hadoop/hbase/client/RowMutations;)Ljava/util/concurrent/CompletableFuture;
     292: invokevirtual #26                 // Method java/util/concurrent/CompletableFuture.get:()Ljava/lang/Object;
     295: checkcast     #41                 // class java/lang/Boolean
     298: invokevirtual #42                 // Method java/lang/Boolean.booleanValue:()Z
     301: istore        5
     303: iload         5
     305: invokestatic  #29                 // Method org/junit/Assert.assertFalse:(Z)V
     308: aload_1
     309: aload_0
     310: getfield      #38                 // Field row:[B
     313: getstatic     #22                 // Field FAMILY:[B
     316: invokeinterface #134,  3          // InterfaceMethod org/apache/hadoop/hbase/client/AsyncTable.checkAndMutate:([B[B)Lorg/apache/hadoop/hbase/client/AsyncTable$CheckAndMutateBuilder;
     321: getstatic     #49                 // Field QUALIFIER:[B
     324: invokeinterface #135,  2          // InterfaceMethod org/apache/hadoop/hbase/client/AsyncTable$CheckAndMutateBuilder.qualifier:([B)Lorg/apache/hadoop/hbase/client/AsyncTable$CheckAndMutateBuilder;
     329: lload_2
     330: invokestatic  #140                // Method org/apache/hadoop/hbase/io/TimeRange.at:(J)Lorg/apache/hadoop/hbase/io/TimeRange;
     333: invokeinterface #141,  2          // InterfaceMethod org/apache/hadoop/hbase/client/AsyncTable$CheckAndMutateBuilder.timeRange:(Lorg/apache/hadoop/hbase/io/TimeRange;)Lorg/apache/hadoop/hbase/client/AsyncTable$CheckAndMutateBuilder;
     338: getstatic     #50                 // Field VALUE:[B
     341: invokeinterface #142,  2          // InterfaceMethod org/apache/hadoop/hbase/client/AsyncTable$CheckAndMutateBuilder.ifEquals:([B)Lorg/apache/hadoop/hbase/client/AsyncTable$CheckAndMutateBuilder;
     346: aload         6
     348: invokeinterface #143,  2          // InterfaceMethod org/apache/hadoop/hbase/client/AsyncTable$CheckAndMutateBuilder.thenMutate:(Lorg/apache/hadoop/hbase/client/RowMutations;)Ljava/util/concurrent/CompletableFuture;
     353: invokevirtual #26                 // Method java/util/concurrent/CompletableFuture.get:()Ljava/lang/Object;
     356: checkcast     #41                 // class java/lang/Boolean
     359: invokevirtual #42                 // Method java/lang/Boolean.booleanValue:()Z
     362: istore        5
     364: iload         5
     366: invokestatic  #31                 // Method org/junit/Assert.assertTrue:(Z)V
     369: new           #61                 // class org/apache/hadoop/hbase/client/Delete
     372: dup
     373: aload_0
     374: getfield      #38                 // Field row:[B
     377: invokespecial #62                 // Method org/apache/hadoop/hbase/client/Delete."<init>":([B)V
     380: getstatic     #22                 // Field FAMILY:[B
     383: getstatic     #49                 // Field QUALIFIER:[B
     386: invokevirtual #124                // Method org/apache/hadoop/hbase/client/Delete.addColumn:([B[B)Lorg/apache/hadoop/hbase/client/Delete;
     389: astore        7
     391: aload_1
     392: aload_0
     393: getfield      #38                 // Field row:[B
     396: getstatic     #22                 // Field FAMILY:[B
     399: invokeinterface #134,  3          // InterfaceMethod org/apache/hadoop/hbase/client/AsyncTable.checkAndMutate:([B[B)Lorg/apache/hadoop/hbase/client/AsyncTable$CheckAndMutateBuilder;
     404: getstatic     #49                 // Field QUALIFIER:[B
     407: invokeinterface #135,  2          // InterfaceMethod org/apache/hadoop/hbase/client/AsyncTable$CheckAndMutateBuilder.qualifier:([B)Lorg/apache/hadoop/hbase/client/AsyncTable$CheckAndMutateBuilder;
     412: lload_2
     413: ldc2_w        #138                // long 10000l
     416: ladd
     417: invokestatic  #140                // Method org/apache/hadoop/hbase/io/TimeRange.at:(J)Lorg/apache/hadoop/hbase/io/TimeRange;
     420: invokeinterface #141,  2          // InterfaceMethod org/apache/hadoop/hbase/client/AsyncTable$CheckAndMutateBuilder.timeRange:(Lorg/apache/hadoop/hbase/io/TimeRange;)Lorg/apache/hadoop/hbase/client/AsyncTable$CheckAndMutateBuilder;
     425: getstatic     #50                 // Field VALUE:[B
     428: invokeinterface #142,  2          // InterfaceMethod org/apache/hadoop/hbase/client/AsyncTable$CheckAndMutateBuilder.ifEquals:([B)Lorg/apache/hadoop/hbase/client/AsyncTable$CheckAndMutateBuilder;
     433: aload         7
     435: invokeinterface #144,  2          // InterfaceMethod org/apache/hadoop/hbase/client/AsyncTable$CheckAndMutateBuilder.thenDelete:(Lorg/apache/hadoop/hbase/client/Delete;)Ljava/util/concurrent/CompletableFuture;
     440: invokevirtual #26                 // Method java/util/concurrent/CompletableFuture.get:()Ljava/lang/Object;
     443: checkcast     #41                 // class java/lang/Boolean
     446: invokevirtual #42                 // Method java/lang/Boolean.booleanValue:()Z
     449: istore        5
     451: iload         5
     453: invokestatic  #29                 // Method org/junit/Assert.assertFalse:(Z)V
     456: aload_1
     457: aload_0
     458: getfield      #38                 // Field row:[B
     461: getstatic     #22                 // Field FAMILY:[B
     464: invokeinterface #134,  3          // InterfaceMethod org/apache/hadoop/hbase/client/AsyncTable.checkAndMutate:([B[B)Lorg/apache/hadoop/hbase/client/AsyncTable$CheckAndMutateBuilder;
     469: getstatic     #49                 // Field QUALIFIER:[B
     472: invokeinterface #135,  2          // InterfaceMethod org/apache/hadoop/hbase/client/AsyncTable$CheckAndMutateBuilder.qualifier:([B)Lorg/apache/hadoop/hbase/client/AsyncTable$CheckAndMutateBuilder;
     477: lload_2
     478: invokestatic  #140                // Method org/apache/hadoop/hbase/io/TimeRange.at:(J)Lorg/apache/hadoop/hbase/io/TimeRange;
     481: invokeinterface #141,  2          // InterfaceMethod org/apache/hadoop/hbase/client/AsyncTable$CheckAndMutateBuilder.timeRange:(Lorg/apache/hadoop/hbase/io/TimeRange;)Lorg/apache/hadoop/hbase/client/AsyncTable$CheckAndMutateBuilder;
     486: getstatic     #50                 // Field VALUE:[B
     489: invokeinterface #142,  2          // InterfaceMethod org/apache/hadoop/hbase/client/AsyncTable$CheckAndMutateBuilder.ifEquals:([B)Lorg/apache/hadoop/hbase/client/AsyncTable$CheckAndMutateBuilder;
     494: aload         7
     496: invokeinterface #144,  2          // InterfaceMethod org/apache/hadoop/hbase/client/AsyncTable$CheckAndMutateBuilder.thenDelete:(Lorg/apache/hadoop/hbase/client/Delete;)Ljava/util/concurrent/CompletableFuture;
     501: invokevirtual #26                 // Method java/util/concurrent/CompletableFuture.get:()Ljava/lang/Object;
     504: checkcast     #41                 // class java/lang/Boolean
     507: invokevirtual #42                 // Method java/lang/Boolean.booleanValue:()Z
     510: istore        5
     512: iload         5
     514: invokestatic  #31                 // Method org/junit/Assert.assertTrue:(Z)V
     517: return

  public void testDisabled() throws java.lang.InterruptedException, java.util.concurrent.ExecutionException;
    Code:
       0: getstatic     #5                  // Field ASYNC_CONN:Lorg/apache/hadoop/hbase/client/AsyncConnection;
       3: invokeinterface #39,  1           // InterfaceMethod org/apache/hadoop/hbase/client/AsyncConnection.getAdmin:()Lorg/apache/hadoop/hbase/client/AsyncAdmin;
       8: getstatic     #6                  // Field TABLE_NAME:Lorg/apache/hadoop/hbase/TableName;
      11: invokeinterface #145,  2          // InterfaceMethod org/apache/hadoop/hbase/client/AsyncAdmin.disableTable:(Lorg/apache/hadoop/hbase/TableName;)Ljava/util/concurrent/CompletableFuture;
      16: invokevirtual #26                 // Method java/util/concurrent/CompletableFuture.get:()Ljava/lang/Object;
      19: pop
      20: aload_0
      21: getfield      #44                 // Field getTable:Ljava/util/function/Supplier;
      24: invokeinterface #45,  1           // InterfaceMethod java/util/function/Supplier.get:()Ljava/lang/Object;
      29: checkcast     #46                 // class org/apache/hadoop/hbase/client/AsyncTable
      32: new           #53                 // class org/apache/hadoop/hbase/client/Get
      35: dup
      36: aload_0
      37: getfield      #38                 // Field row:[B
      40: invokespecial #54                 // Method org/apache/hadoop/hbase/client/Get."<init>":([B)V
      43: invokeinterface #57,  2           // InterfaceMethod org/apache/hadoop/hbase/client/AsyncTable.get:(Lorg/apache/hadoop/hbase/client/Get;)Ljava/util/concurrent/CompletableFuture;
      48: invokevirtual #26                 // Method java/util/concurrent/CompletableFuture.get:()Ljava/lang/Object;
      51: pop
      52: ldc           #146                // String Should fail since table has been disabled
      54: invokestatic  #147                // Method org/junit/Assert.fail:(Ljava/lang/String;)V
      57: goto          91
      60: astore_1
      61: aload_1
      62: invokevirtual #149                // Method java/util/concurrent/ExecutionException.getCause:()Ljava/lang/Throwable;
      65: astore_2
      66: aload_2
      67: ldc           #150                // class org/apache/hadoop/hbase/TableNotEnabledException
      69: invokestatic  #151                // Method org/hamcrest/CoreMatchers.instanceOf:(Ljava/lang/Class;)Lorg/hamcrest/Matcher;
      72: invokestatic  #152                // Method org/junit/Assert.assertThat:(Ljava/lang/Object;Lorg/hamcrest/Matcher;)V
      75: aload_2
      76: invokevirtual #153                // Method java/lang/Throwable.getMessage:()Ljava/lang/String;
      79: getstatic     #6                  // Field TABLE_NAME:Lorg/apache/hadoop/hbase/TableName;
      82: invokevirtual #154                // Method org/apache/hadoop/hbase/TableName.getNameAsString:()Ljava/lang/String;
      85: invokestatic  #155                // Method org/hamcrest/CoreMatchers.containsString:(Ljava/lang/String;)Lorg/hamcrest/Matcher;
      88: invokestatic  #152                // Method org/junit/Assert.assertThat:(Ljava/lang/Object;Lorg/hamcrest/Matcher;)V
      91: return
    Exception table:
       from    to  target type
          20    57    60   Class java/util/concurrent/ExecutionException

  public void testInvalidPut();
    Code:
       0: aload_0
       1: getfield      #44                 // Field getTable:Ljava/util/function/Supplier;
       4: invokeinterface #45,  1           // InterfaceMethod java/util/function/Supplier.get:()Ljava/lang/Object;
       9: checkcast     #46                 // class org/apache/hadoop/hbase/client/AsyncTable
      12: new           #47                 // class org/apache/hadoop/hbase/client/Put
      15: dup
      16: iconst_0
      17: invokestatic  #156                // Method org/apache/hadoop/hbase/util/Bytes.toBytes:(I)[B
      20: invokespecial #48                 // Method org/apache/hadoop/hbase/client/Put."<init>":([B)V
      23: invokeinterface #52,  2           // InterfaceMethod org/apache/hadoop/hbase/client/AsyncTable.put:(Lorg/apache/hadoop/hbase/client/Put;)Ljava/util/concurrent/CompletableFuture;
      28: pop
      29: ldc           #157                // String Should fail since the put does not contain any cells
      31: invokestatic  #147                // Method org/junit/Assert.fail:(Ljava/lang/String;)V
      34: goto          50
      37: astore_1
      38: aload_1
      39: invokevirtual #159                // Method java/lang/IllegalArgumentException.getMessage:()Ljava/lang/String;
      42: ldc           #160                // String No columns to insert
      44: invokestatic  #155                // Method org/hamcrest/CoreMatchers.containsString:(Ljava/lang/String;)Lorg/hamcrest/Matcher;
      47: invokestatic  #152                // Method org/junit/Assert.assertThat:(Ljava/lang/Object;Lorg/hamcrest/Matcher;)V
      50: aload_0
      51: getfield      #44                 // Field getTable:Ljava/util/function/Supplier;
      54: invokeinterface #45,  1           // InterfaceMethod java/util/function/Supplier.get:()Ljava/lang/Object;
      59: checkcast     #46                 // class org/apache/hadoop/hbase/client/AsyncTable
      62: new           #47                 // class org/apache/hadoop/hbase/client/Put
      65: dup
      66: iconst_0
      67: invokestatic  #156                // Method org/apache/hadoop/hbase/util/Bytes.toBytes:(I)[B
      70: invokespecial #48                 // Method org/apache/hadoop/hbase/client/Put."<init>":([B)V
      73: getstatic     #22                 // Field FAMILY:[B
      76: getstatic     #49                 // Field QUALIFIER:[B
      79: getstatic     #19                 // Field MAX_KEY_VALUE_SIZE:I
      82: newarray       byte
      84: invokevirtual #51                 // Method org/apache/hadoop/hbase/client/Put.addColumn:([B[B[B)Lorg/apache/hadoop/hbase/client/Put;
      87: invokeinterface #52,  2           // InterfaceMethod org/apache/hadoop/hbase/client/AsyncTable.put:(Lorg/apache/hadoop/hbase/client/Put;)Ljava/util/concurrent/CompletableFuture;
      92: pop
      93: ldc           #161                // String Should fail since the put exceeds the max key value size
      95: invokestatic  #147                // Method org/junit/Assert.fail:(Ljava/lang/String;)V
      98: goto          114
     101: astore_1
     102: aload_1
     103: invokevirtual #159                // Method java/lang/IllegalArgumentException.getMessage:()Ljava/lang/String;
     106: ldc           #162                // String KeyValue size too large
     108: invokestatic  #155                // Method org/hamcrest/CoreMatchers.containsString:(Ljava/lang/String;)Lorg/hamcrest/Matcher;
     111: invokestatic  #152                // Method org/junit/Assert.assertThat:(Ljava/lang/Object;Lorg/hamcrest/Matcher;)V
     114: return
    Exception table:
       from    to  target type
           0    34    37   Class java/lang/IllegalArgumentException
          50    98   101   Class java/lang/IllegalArgumentException

  static {};
    Code:
       0: ldc           #198                // class org/apache/hadoop/hbase/client/TestAsyncTable
       2: invokestatic  #199                // Method org/apache/hadoop/hbase/HBaseClassTestRule.forClass:(Ljava/lang/Class;)Lorg/apache/hadoop/hbase/HBaseClassTestRule;
       5: putstatic     #200                // Field CLASS_RULE:Lorg/apache/hadoop/hbase/HBaseClassTestRule;
       8: new           #201                // class org/apache/hadoop/hbase/HBaseTestingUtility
      11: dup
      12: invokespecial #202                // Method org/apache/hadoop/hbase/HBaseTestingUtility."<init>":()V
      15: putstatic     #15                 // Field TEST_UTIL:Lorg/apache/hadoop/hbase/HBaseTestingUtility;
      18: ldc           #203                // String async
      20: invokestatic  #204                // Method org/apache/hadoop/hbase/TableName.valueOf:(Ljava/lang/String;)Lorg/apache/hadoop/hbase/TableName;
      23: putstatic     #6                  // Field TABLE_NAME:Lorg/apache/hadoop/hbase/TableName;
      26: ldc           #205                // String cf
      28: invokestatic  #37                 // Method org/apache/hadoop/hbase/util/Bytes.toBytes:(Ljava/lang/String;)[B
      31: putstatic     #22                 // Field FAMILY:[B
      34: ldc           #206                // String cq
      36: invokestatic  #37                 // Method org/apache/hadoop/hbase/util/Bytes.toBytes:(Ljava/lang/String;)[B
      39: putstatic     #49                 // Field QUALIFIER:[B
      42: ldc           #207                // String value
      44: invokestatic  #37                 // Method org/apache/hadoop/hbase/util/Bytes.toBytes:(Ljava/lang/String;)[B
      47: putstatic     #50                 // Field VALUE:[B
      50: ldc           #208                // int 65536
      52: putstatic     #19                 // Field MAX_KEY_VALUE_SIZE:I
      55: return
}
