Compiled from "TestAccessController.java"
class org.apache.hadoop.hbase.security.access.TestAccessController$76 implements org.apache.hadoop.hbase.security.access.SecureTestUtil$AccessTestAction {
  final org.apache.hadoop.hbase.client.Table val$table;

  final org.apache.hadoop.hbase.security.access.TestAccessController this$0;

  org.apache.hadoop.hbase.security.access.TestAccessController$76(org.apache.hadoop.hbase.security.access.TestAccessController, org.apache.hadoop.hbase.client.Table);
    Code:
       0: aload_0
       1: aload_1
       2: putfield      #1                  // Field this$0:Lorg/apache/hadoop/hbase/security/access/TestAccessController;
       5: aload_0
       6: aload_2
       7: putfield      #2                  // Field val$table:Lorg/apache/hadoop/hbase/client/Table;
      10: aload_0
      11: invokespecial #3                  // Method java/lang/Object."<init>":()V
      14: return

  public java.lang.Object run() throws java.lang.Exception;
    Code:
       0: new           #4                  // class org/apache/hadoop/hbase/client/Put
       3: dup
       4: ldc           #5                  // String test
       6: invokestatic  #6                  // Method org/apache/hadoop/hbase/util/Bytes.toBytes:(Ljava/lang/String;)[B
       9: invokespecial #7                  // Method org/apache/hadoop/hbase/client/Put."<init>":([B)V
      12: astore_1
      13: aload_1
      14: invokestatic  #8                  // Method org/apache/hadoop/hbase/security/access/TestAccessController.access$100:()[B
      17: ldc           #9                  // String qual
      19: invokestatic  #6                  // Method org/apache/hadoop/hbase/util/Bytes.toBytes:(Ljava/lang/String;)[B
      22: ldc           #10                 // String value
      24: invokestatic  #6                  // Method org/apache/hadoop/hbase/util/Bytes.toBytes:(Ljava/lang/String;)[B
      27: invokevirtual #11                 // Method org/apache/hadoop/hbase/client/Put.addColumn:([B[B[B)Lorg/apache/hadoop/hbase/client/Put;
      30: pop
      31: aload_0
      32: getfield      #2                  // Field val$table:Lorg/apache/hadoop/hbase/client/Table;
      35: aload_1
      36: invokeinterface #12,  2           // InterfaceMethod org/apache/hadoop/hbase/client/Table.put:(Lorg/apache/hadoop/hbase/client/Put;)V
      41: aconst_null
      42: areturn
}
