Compiled from "TestHFileInlineToRootChunkConversion.java"
public class org.apache.hadoop.hbase.io.hfile.TestHFileInlineToRootChunkConversion {
  public static final org.apache.hadoop.hbase.HBaseClassTestRule CLASS_RULE;

  public org.apache.hadoop.hbase.io.hfile.TestHFileInlineToRootChunkConversion();
    Code:
       0: aload_0
       1: invokespecial #1                  // Method java/lang/Object."<init>":()V
       4: aload_0
       5: new           #2                  // class org/apache/hadoop/hbase/HBaseTestingUtility
       8: dup
       9: invokespecial #3                  // Method org/apache/hadoop/hbase/HBaseTestingUtility."<init>":()V
      12: putfield      #4                  // Field testUtil:Lorg/apache/hadoop/hbase/HBaseTestingUtility;
      15: aload_0
      16: aload_0
      17: getfield      #4                  // Field testUtil:Lorg/apache/hadoop/hbase/HBaseTestingUtility;
      20: invokevirtual #5                  // Method org/apache/hadoop/hbase/HBaseTestingUtility.getConfiguration:()Lorg/apache/hadoop/conf/Configuration;
      23: putfield      #6                  // Field conf:Lorg/apache/hadoop/conf/Configuration;
      26: return

  public void testWriteHFile() throws java.lang.Exception;
    Code:
       0: new           #7                  // class org/apache/hadoop/fs/Path
       3: dup
       4: aload_0
       5: getfield      #4                  // Field testUtil:Lorg/apache/hadoop/hbase/HBaseTestingUtility;
       8: invokevirtual #8                  // Method org/apache/hadoop/hbase/HBaseTestingUtility.getDataTestDir:()Lorg/apache/hadoop/fs/Path;
      11: new           #9                  // class java/lang/StringBuilder
      14: dup
      15: invokespecial #10                 // Method java/lang/StringBuilder."<init>":()V
      18: ldc           #11                 // class org/apache/hadoop/hbase/io/hfile/TestHFileInlineToRootChunkConversion
      20: invokevirtual #12                 // Method java/lang/Class.getSimpleName:()Ljava/lang/String;
      23: invokevirtual #13                 // Method java/lang/StringBuilder.append:(Ljava/lang/String;)Ljava/lang/StringBuilder;
      26: ldc           #14                 // String .hfile
      28: invokevirtual #13                 // Method java/lang/StringBuilder.append:(Ljava/lang/String;)Ljava/lang/StringBuilder;
      31: invokevirtual #15                 // Method java/lang/StringBuilder.toString:()Ljava/lang/String;
      34: invokespecial #16                 // Method org/apache/hadoop/fs/Path."<init>":(Lorg/apache/hadoop/fs/Path;Ljava/lang/String;)V
      37: astore_1
      38: sipush        1024
      41: istore_2
      42: aload_0
      43: getfield      #6                  // Field conf:Lorg/apache/hadoop/conf/Configuration;
      46: invokestatic  #17                 // Method org/apache/hadoop/fs/FileSystem.get:(Lorg/apache/hadoop/conf/Configuration;)Lorg/apache/hadoop/fs/FileSystem;
      49: astore_3
      50: new           #18                 // class org/apache/hadoop/hbase/io/hfile/CacheConfig
      53: dup
      54: aload_0
      55: getfield      #6                  // Field conf:Lorg/apache/hadoop/conf/Configuration;
      58: invokespecial #19                 // Method org/apache/hadoop/hbase/io/hfile/CacheConfig."<init>":(Lorg/apache/hadoop/conf/Configuration;)V
      61: astore        4
      63: aload_0
      64: getfield      #6                  // Field conf:Lorg/apache/hadoop/conf/Configuration;
      67: ldc           #21                 // String hfile.index.block.max.size
      69: iload_2
      70: invokevirtual #22                 // Method org/apache/hadoop/conf/Configuration.setInt:(Ljava/lang/String;I)V
      73: new           #23                 // class org/apache/hadoop/hbase/io/hfile/HFileContextBuilder
      76: dup
      77: invokespecial #24                 // Method org/apache/hadoop/hbase/io/hfile/HFileContextBuilder."<init>":()V
      80: bipush        16
      82: invokevirtual #25                 // Method org/apache/hadoop/hbase/io/hfile/HFileContextBuilder.withBlockSize:(I)Lorg/apache/hadoop/hbase/io/hfile/HFileContextBuilder;
      85: invokevirtual #26                 // Method org/apache/hadoop/hbase/io/hfile/HFileContextBuilder.build:()Lorg/apache/hadoop/hbase/io/hfile/HFileContext;
      88: astore        5
      90: new           #27                 // class org/apache/hadoop/hbase/io/hfile/HFile$WriterFactory
      93: dup
      94: aload_0
      95: getfield      #6                  // Field conf:Lorg/apache/hadoop/conf/Configuration;
      98: aload         4
     100: invokespecial #28                 // Method org/apache/hadoop/hbase/io/hfile/HFile$WriterFactory."<init>":(Lorg/apache/hadoop/conf/Configuration;Lorg/apache/hadoop/hbase/io/hfile/CacheConfig;)V
     103: aload         5
     105: invokevirtual #29                 // Method org/apache/hadoop/hbase/io/hfile/HFile$WriterFactory.withFileContext:(Lorg/apache/hadoop/hbase/io/hfile/HFileContext;)Lorg/apache/hadoop/hbase/io/hfile/HFile$WriterFactory;
     108: aload_3
     109: aload_1
     110: invokevirtual #30                 // Method org/apache/hadoop/hbase/io/hfile/HFile$WriterFactory.withPath:(Lorg/apache/hadoop/fs/FileSystem;Lorg/apache/hadoop/fs/Path;)Lorg/apache/hadoop/hbase/io/hfile/HFile$WriterFactory;
     113: invokevirtual #31                 // Method org/apache/hadoop/hbase/io/hfile/HFile$WriterFactory.create:()Lorg/apache/hadoop/hbase/io/hfile/HFile$Writer;
     116: astore        6
     118: new           #32                 // class java/util/ArrayList
     121: dup
     122: invokespecial #33                 // Method java/util/ArrayList."<init>":()V
     125: astore        7
     127: new           #9                  // class java/lang/StringBuilder
     130: dup
     131: invokespecial #10                 // Method java/lang/StringBuilder."<init>":()V
     134: astore        8
     136: iconst_0
     137: istore        9
     139: iload         9
     141: iconst_4
     142: if_icmpge     296
     145: aload         8
     147: new           #9                  // class java/lang/StringBuilder
     150: dup
     151: invokespecial #10                 // Method java/lang/StringBuilder."<init>":()V
     154: ldc           #34                 // String key
     156: invokevirtual #13                 // Method java/lang/StringBuilder.append:(Ljava/lang/String;)Ljava/lang/StringBuilder;
     159: ldc           #35                 // String %05d
     161: iconst_1
     162: anewarray     #36                 // class java/lang/Object
     165: dup
     166: iconst_0
     167: iload         9
     169: invokestatic  #37                 // Method java/lang/Integer.valueOf:(I)Ljava/lang/Integer;
     172: aastore
     173: invokestatic  #38                 // Method java/lang/String.format:(Ljava/lang/String;[Ljava/lang/Object;)Ljava/lang/String;
     176: invokevirtual #13                 // Method java/lang/StringBuilder.append:(Ljava/lang/String;)Ljava/lang/StringBuilder;
     179: invokevirtual #15                 // Method java/lang/StringBuilder.toString:()Ljava/lang/String;
     182: invokevirtual #13                 // Method java/lang/StringBuilder.append:(Ljava/lang/String;)Ljava/lang/StringBuilder;
     185: pop
     186: aload         8
     188: ldc           #39                 // String _
     190: invokevirtual #13                 // Method java/lang/StringBuilder.append:(Ljava/lang/String;)Ljava/lang/StringBuilder;
     193: pop
     194: iconst_0
     195: istore        10
     197: iload         10
     199: bipush        100
     201: if_icmpge     221
     204: aload         8
     206: bipush        48
     208: iload         10
     210: iadd
     211: invokevirtual #40                 // Method java/lang/StringBuilder.append:(I)Ljava/lang/StringBuilder;
     214: pop
     215: iinc          10, 1
     218: goto          197
     221: aload         8
     223: invokevirtual #15                 // Method java/lang/StringBuilder.toString:()Ljava/lang/String;
     226: astore        10
     228: aload         8
     230: iconst_0
     231: invokevirtual #41                 // Method java/lang/StringBuilder.setLength:(I)V
     234: aload         10
     236: invokestatic  #42                 // Method org/apache/hadoop/hbase/util/Bytes.toBytes:(Ljava/lang/String;)[B
     239: astore        11
     241: aload         7
     243: aload         11
     245: invokeinterface #43,  2           // InterfaceMethod java/util/List.add:(Ljava/lang/Object;)Z
     250: pop
     251: new           #9                  // class java/lang/StringBuilder
     254: dup
     255: invokespecial #10                 // Method java/lang/StringBuilder."<init>":()V
     258: ldc           #44                 // String value
     260: invokevirtual #13                 // Method java/lang/StringBuilder.append:(Ljava/lang/String;)Ljava/lang/StringBuilder;
     263: iload         9
     265: invokevirtual #40                 // Method java/lang/StringBuilder.append:(I)Ljava/lang/StringBuilder;
     268: invokevirtual #15                 // Method java/lang/StringBuilder.toString:()Ljava/lang/String;
     271: invokestatic  #42                 // Method org/apache/hadoop/hbase/util/Bytes.toBytes:(Ljava/lang/String;)[B
     274: astore        12
     276: aload         6
     278: aload         11
     280: aload         12
     282: invokestatic  #45                 // Method org/apache/hadoop/hbase/CellUtil.createCell:([B[B)Lorg/apache/hadoop/hbase/Cell;
     285: invokeinterface #46,  2           // InterfaceMethod org/apache/hadoop/hbase/io/hfile/HFile$Writer.append:(Lorg/apache/hadoop/hbase/Cell;)V
     290: iinc          9, 1
     293: goto          139
     296: aload         6
     298: invokeinterface #47,  1           // InterfaceMethod org/apache/hadoop/hbase/io/hfile/HFile$Writer.close:()V
     303: aload_3
     304: aload_1
     305: aload         4
     307: iconst_1
     308: aload_0
     309: getfield      #6                  // Field conf:Lorg/apache/hadoop/conf/Configuration;
     312: invokestatic  #48                 // Method org/apache/hadoop/hbase/io/hfile/HFile.createReader:(Lorg/apache/hadoop/fs/FileSystem;Lorg/apache/hadoop/fs/Path;Lorg/apache/hadoop/hbase/io/hfile/CacheConfig;ZLorg/apache/hadoop/conf/Configuration;)Lorg/apache/hadoop/hbase/io/hfile/HFile$Reader;
     315: astore        9
     317: aload         9
     319: iconst_1
     320: iconst_1
     321: invokeinterface #49,  3           // InterfaceMethod org/apache/hadoop/hbase/io/hfile/HFile$Reader.getScanner:(ZZ)Lorg/apache/hadoop/hbase/io/hfile/HFileScanner;
     326: astore        10
     328: iconst_0
     329: istore        11
     331: iload         11
     333: aload         7
     335: invokeinterface #50,  1           // InterfaceMethod java/util/List.size:()I
     340: if_icmpge     372
     343: aload         10
     345: aload         7
     347: iload         11
     349: invokeinterface #51,  2           // InterfaceMethod java/util/List.get:(I)Ljava/lang/Object;
     354: checkcast     #52                 // class "[B"
     357: invokestatic  #53                 // Method org/apache/hadoop/hbase/CellUtil.createCell:([B)Lorg/apache/hadoop/hbase/Cell;
     360: invokeinterface #54,  2           // InterfaceMethod org/apache/hadoop/hbase/io/hfile/HFileScanner.seekTo:(Lorg/apache/hadoop/hbase/Cell;)I
     365: pop
     366: iinc          11, 1
     369: goto          331
     372: aload         9
     374: invokeinterface #55,  1           // InterfaceMethod org/apache/hadoop/hbase/io/hfile/HFile$Reader.close:()V
     379: return

  static {};
    Code:
       0: ldc           #11                 // class org/apache/hadoop/hbase/io/hfile/TestHFileInlineToRootChunkConversion
       2: invokestatic  #56                 // Method org/apache/hadoop/hbase/HBaseClassTestRule.forClass:(Ljava/lang/Class;)Lorg/apache/hadoop/hbase/HBaseClassTestRule;
       5: putstatic     #57                 // Field CLASS_RULE:Lorg/apache/hadoop/hbase/HBaseClassTestRule;
       8: return
}
