Compiled from "TestRemoveRegionMetrics.java"
public class org.apache.hadoop.hbase.regionserver.TestRemoveRegionMetrics {
  public static final org.apache.hadoop.hbase.HBaseClassTestRule CLASS_RULE;

  public org.junit.rules.TestName name;

  public org.apache.hadoop.hbase.regionserver.TestRemoveRegionMetrics();
    Code:
       0: aload_0
       1: invokespecial #1                  // Method java/lang/Object."<init>":()V
       4: aload_0
       5: new           #2                  // class org/junit/rules/TestName
       8: dup
       9: invokespecial #3                  // Method org/junit/rules/TestName."<init>":()V
      12: putfield      #4                  // Field name:Lorg/junit/rules/TestName;
      15: return

  public static void startCluster() throws java.lang.Exception;
    Code:
       0: ldc           #5                  // class org/apache/hadoop/hbase/test/MetricsAssertHelper
       2: invokestatic  #6                  // Method org/apache/hadoop/hbase/CompatibilityFactory.getInstance:(Ljava/lang/Class;)Ljava/lang/Object;
       5: checkcast     #5                  // class org/apache/hadoop/hbase/test/MetricsAssertHelper
       8: putstatic     #7                  // Field metricsHelper:Lorg/apache/hadoop/hbase/test/MetricsAssertHelper;
      11: new           #8                  // class org/apache/hadoop/hbase/HBaseTestingUtility
      14: dup
      15: invokespecial #9                  // Method org/apache/hadoop/hbase/HBaseTestingUtility."<init>":()V
      18: putstatic     #10                 // Field TEST_UTIL:Lorg/apache/hadoop/hbase/HBaseTestingUtility;
      21: getstatic     #10                 // Field TEST_UTIL:Lorg/apache/hadoop/hbase/HBaseTestingUtility;
      24: invokevirtual #11                 // Method org/apache/hadoop/hbase/HBaseTestingUtility.getConfiguration:()Lorg/apache/hadoop/conf/Configuration;
      27: putstatic     #12                 // Field conf:Lorg/apache/hadoop/conf/Configuration;
      30: getstatic     #12                 // Field conf:Lorg/apache/hadoop/conf/Configuration;
      33: ldc           #13                 // String hbase.splitlog.max.resubmit
      35: lconst_0
      36: invokevirtual #14                 // Method org/apache/hadoop/conf/Configuration.getLong:(Ljava/lang/String;J)J
      39: pop2
      40: getstatic     #12                 // Field conf:Lorg/apache/hadoop/conf/Configuration;
      43: ldc           #15                 // String zookeeper.recovery.retry
      45: iconst_0
      46: invokevirtual #16                 // Method org/apache/hadoop/conf/Configuration.setInt:(Ljava/lang/String;I)V
      49: getstatic     #12                 // Field conf:Lorg/apache/hadoop/conf/Configuration;
      52: ldc           #18                 // String hbase.regionserver.info.port
      54: iconst_m1
      55: invokevirtual #16                 // Method org/apache/hadoop/conf/Configuration.setInt:(Ljava/lang/String;I)V
      58: getstatic     #10                 // Field TEST_UTIL:Lorg/apache/hadoop/hbase/HBaseTestingUtility;
      61: iconst_2
      62: invokevirtual #19                 // Method org/apache/hadoop/hbase/HBaseTestingUtility.startMiniCluster:(I)Lorg/apache/hadoop/hbase/MiniHBaseCluster;
      65: pop
      66: getstatic     #10                 // Field TEST_UTIL:Lorg/apache/hadoop/hbase/HBaseTestingUtility;
      69: invokevirtual #20                 // Method org/apache/hadoop/hbase/HBaseTestingUtility.getHBaseCluster:()Lorg/apache/hadoop/hbase/MiniHBaseCluster;
      72: putstatic     #21                 // Field cluster:Lorg/apache/hadoop/hbase/MiniHBaseCluster;
      75: getstatic     #21                 // Field cluster:Lorg/apache/hadoop/hbase/MiniHBaseCluster;
      78: invokevirtual #22                 // Method org/apache/hadoop/hbase/MiniHBaseCluster.waitForActiveAndReadyMaster:()Z
      81: pop
      82: getstatic     #21                 // Field cluster:Lorg/apache/hadoop/hbase/MiniHBaseCluster;
      85: invokevirtual #23                 // Method org/apache/hadoop/hbase/MiniHBaseCluster.getLiveRegionServerThreads:()Ljava/util/List;
      88: invokeinterface #24,  1           // InterfaceMethod java/util/List.size:()I
      93: iconst_2
      94: if_icmpge     106
      97: ldc2_w        #25                 // long 100l
     100: invokestatic  #27                 // Method org/apache/hadoop/hbase/util/Threads.sleep:(J)V
     103: goto          82
     106: return

  public void testMoveRegion() throws java.io.IOException, java.lang.InterruptedException;
    Code:
       0: aload_0
       1: getfield      #4                  // Field name:Lorg/junit/rules/TestName;
       4: invokevirtual #28                 // Method org/junit/rules/TestName.getMethodName:()Ljava/lang/String;
       7: astore_1
       8: aload_1
       9: invokestatic  #29                 // Method org/apache/hadoop/hbase/TableName.valueOf:(Ljava/lang/String;)Lorg/apache/hadoop/hbase/TableName;
      12: astore_2
      13: getstatic     #10                 // Field TEST_UTIL:Lorg/apache/hadoop/hbase/HBaseTestingUtility;
      16: aload_2
      17: ldc           #30                 // String D
      19: invokestatic  #31                 // Method org/apache/hadoop/hbase/util/Bytes.toBytes:(Ljava/lang/String;)[B
      22: invokevirtual #32                 // Method org/apache/hadoop/hbase/HBaseTestingUtility.createTable:(Lorg/apache/hadoop/hbase/TableName;[B)Lorg/apache/hadoop/hbase/client/Table;
      25: astore_3
      26: getstatic     #10                 // Field TEST_UTIL:Lorg/apache/hadoop/hbase/HBaseTestingUtility;
      29: aload_3
      30: invokeinterface #33,  1           // InterfaceMethod org/apache/hadoop/hbase/client/Table.getName:()Lorg/apache/hadoop/hbase/TableName;
      35: invokevirtual #34                 // Method org/apache/hadoop/hbase/HBaseTestingUtility.waitUntilAllRegionsAssigned:(Lorg/apache/hadoop/hbase/TableName;)V
      38: getstatic     #10                 // Field TEST_UTIL:Lorg/apache/hadoop/hbase/HBaseTestingUtility;
      41: invokevirtual #35                 // Method org/apache/hadoop/hbase/HBaseTestingUtility.getAdmin:()Lorg/apache/hadoop/hbase/client/Admin;
      44: astore        4
      46: ldc           #36                 // String r1
      48: invokestatic  #31                 // Method org/apache/hadoop/hbase/util/Bytes.toBytes:(Ljava/lang/String;)[B
      51: astore        6
      53: iconst_0
      54: istore        7
      56: iload         7
      58: bipush        30
      60: if_icmpge     477
      63: iconst_0
      64: istore        8
      66: getstatic     #10                 // Field TEST_UTIL:Lorg/apache/hadoop/hbase/HBaseTestingUtility;
      69: invokevirtual #37                 // Method org/apache/hadoop/hbase/HBaseTestingUtility.getConnection:()Lorg/apache/hadoop/hbase/client/Connection;
      72: aload_2
      73: invokeinterface #38,  2           // InterfaceMethod org/apache/hadoop/hbase/client/Connection.getRegionLocator:(Lorg/apache/hadoop/hbase/TableName;)Lorg/apache/hadoop/hbase/client/RegionLocator;
      78: astore        9
      80: aconst_null
      81: astore        10
      83: aload         9
      85: aload         6
      87: iconst_1
      88: invokeinterface #39,  3           // InterfaceMethod org/apache/hadoop/hbase/client/RegionLocator.getRegionLocation:([BZ)Lorg/apache/hadoop/hbase/HRegionLocation;
      93: invokevirtual #40                 // Method org/apache/hadoop/hbase/HRegionLocation.getRegionInfo:()Lorg/apache/hadoop/hbase/HRegionInfo;
      96: astore        5
      98: aload         9
     100: ifnull        193
     103: aload         10
     105: ifnull        130
     108: aload         9
     110: invokeinterface #41,  1           // InterfaceMethod org/apache/hadoop/hbase/client/RegionLocator.close:()V
     115: goto          193
     118: astore        11
     120: aload         10
     122: aload         11
     124: invokevirtual #43                 // Method java/lang/Throwable.addSuppressed:(Ljava/lang/Throwable;)V
     127: goto          193
     130: aload         9
     132: invokeinterface #41,  1           // InterfaceMethod org/apache/hadoop/hbase/client/RegionLocator.close:()V
     137: goto          193
     140: astore        11
     142: aload         11
     144: astore        10
     146: aload         11
     148: athrow
     149: astore        12
     151: aload         9
     153: ifnull        190
     156: aload         10
     158: ifnull        183
     161: aload         9
     163: invokeinterface #41,  1           // InterfaceMethod org/apache/hadoop/hbase/client/RegionLocator.close:()V
     168: goto          190
     171: astore        13
     173: aload         10
     175: aload         13
     177: invokevirtual #43                 // Method java/lang/Throwable.addSuppressed:(Ljava/lang/Throwable;)V
     180: goto          190
     183: aload         9
     185: invokeinterface #41,  1           // InterfaceMethod org/apache/hadoop/hbase/client/RegionLocator.close:()V
     190: aload         12
     192: athrow
     193: getstatic     #21                 // Field cluster:Lorg/apache/hadoop/hbase/MiniHBaseCluster;
     196: aload         5
     198: invokevirtual #44                 // Method org/apache/hadoop/hbase/HRegionInfo.getRegionName:()[B
     201: invokevirtual #45                 // Method org/apache/hadoop/hbase/MiniHBaseCluster.getServerWith:([B)I
     204: istore        9
     206: iload         9
     208: iconst_1
     209: iadd
     210: getstatic     #21                 // Field cluster:Lorg/apache/hadoop/hbase/MiniHBaseCluster;
     213: invokevirtual #23                 // Method org/apache/hadoop/hbase/MiniHBaseCluster.getLiveRegionServerThreads:()Ljava/util/List;
     216: invokeinterface #24,  1           // InterfaceMethod java/util/List.size:()I
     221: irem
     222: istore        10
     224: getstatic     #21                 // Field cluster:Lorg/apache/hadoop/hbase/MiniHBaseCluster;
     227: iload         9
     229: invokevirtual #46                 // Method org/apache/hadoop/hbase/MiniHBaseCluster.getRegionServer:(I)Lorg/apache/hadoop/hbase/regionserver/HRegionServer;
     232: astore        11
     234: getstatic     #21                 // Field cluster:Lorg/apache/hadoop/hbase/MiniHBaseCluster;
     237: iload         10
     239: invokevirtual #46                 // Method org/apache/hadoop/hbase/MiniHBaseCluster.getRegionServer:(I)Lorg/apache/hadoop/hbase/regionserver/HRegionServer;
     242: astore        12
     244: new           #47                 // class org/apache/hadoop/hbase/client/Put
     247: dup
     248: aload         6
     250: invokespecial #48                 // Method org/apache/hadoop/hbase/client/Put."<init>":([B)V
     253: astore        13
     255: aload         13
     257: ldc           #30                 // String D
     259: invokestatic  #31                 // Method org/apache/hadoop/hbase/util/Bytes.toBytes:(Ljava/lang/String;)[B
     262: ldc           #49                 // String Zero
     264: invokestatic  #31                 // Method org/apache/hadoop/hbase/util/Bytes.toBytes:(Ljava/lang/String;)[B
     267: ldc           #50                 // String VALUE
     269: invokestatic  #31                 // Method org/apache/hadoop/hbase/util/Bytes.toBytes:(Ljava/lang/String;)[B
     272: invokevirtual #51                 // Method org/apache/hadoop/hbase/client/Put.addColumn:([B[B[B)Lorg/apache/hadoop/hbase/client/Put;
     275: pop
     276: aload_3
     277: aload         13
     279: invokeinterface #52,  2           // InterfaceMethod org/apache/hadoop/hbase/client/Table.put:(Lorg/apache/hadoop/hbase/client/Put;)V
     284: aload         11
     286: aload         5
     288: invokevirtual #44                 // Method org/apache/hadoop/hbase/HRegionInfo.getRegionName:()[B
     291: invokevirtual #53                 // Method org/apache/hadoop/hbase/regionserver/HRegionServer.getRegion:([B)Lorg/apache/hadoop/hbase/regionserver/HRegion;
     294: invokevirtual #54                 // Method org/apache/hadoop/hbase/regionserver/HRegion.getMetrics:()Lorg/apache/hadoop/hbase/regionserver/MetricsRegion;
     297: invokevirtual #55                 // Method org/apache/hadoop/hbase/regionserver/MetricsRegion.getSource:()Lorg/apache/hadoop/hbase/regionserver/MetricsRegionSource;
     300: invokeinterface #56,  1           // InterfaceMethod org/apache/hadoop/hbase/regionserver/MetricsRegionSource.getAggregateSource:()Lorg/apache/hadoop/hbase/regionserver/MetricsRegionAggregateSource;
     305: astore        14
     307: new           #57                 // class java/lang/StringBuilder
     310: dup
     311: invokespecial #58                 // Method java/lang/StringBuilder."<init>":()V
     314: ldc           #59                 // String namespace_
     316: invokevirtual #60                 // Method java/lang/StringBuilder.append:(Ljava/lang/String;)Ljava/lang/StringBuilder;
     319: getstatic     #61                 // Field org/apache/hadoop/hbase/NamespaceDescriptor.DEFAULT_NAMESPACE_NAME_STR:Ljava/lang/String;
     322: invokevirtual #60                 // Method java/lang/StringBuilder.append:(Ljava/lang/String;)Ljava/lang/StringBuilder;
     325: ldc           #62                 // String _table_
     327: invokevirtual #60                 // Method java/lang/StringBuilder.append:(Ljava/lang/String;)Ljava/lang/StringBuilder;
     330: aload_1
     331: invokevirtual #60                 // Method java/lang/StringBuilder.append:(Ljava/lang/String;)Ljava/lang/StringBuilder;
     334: ldc           #63                 // String _region_
     336: invokevirtual #60                 // Method java/lang/StringBuilder.append:(Ljava/lang/String;)Ljava/lang/StringBuilder;
     339: aload         5
     341: invokevirtual #64                 // Method org/apache/hadoop/hbase/HRegionInfo.getEncodedName:()Ljava/lang/String;
     344: invokevirtual #60                 // Method java/lang/StringBuilder.append:(Ljava/lang/String;)Ljava/lang/StringBuilder;
     347: ldc           #65                 // String _metric
     349: invokevirtual #60                 // Method java/lang/StringBuilder.append:(Ljava/lang/String;)Ljava/lang/StringBuilder;
     352: invokevirtual #66                 // Method java/lang/StringBuilder.toString:()Ljava/lang/String;
     355: astore        15
     357: getstatic     #7                  // Field metricsHelper:Lorg/apache/hadoop/hbase/test/MetricsAssertHelper;
     360: new           #57                 // class java/lang/StringBuilder
     363: dup
     364: invokespecial #58                 // Method java/lang/StringBuilder."<init>":()V
     367: aload         15
     369: invokevirtual #60                 // Method java/lang/StringBuilder.append:(Ljava/lang/String;)Ljava/lang/StringBuilder;
     372: ldc           #67                 // String _putCount
     374: invokevirtual #60                 // Method java/lang/StringBuilder.append:(Ljava/lang/String;)Ljava/lang/StringBuilder;
     377: invokevirtual #66                 // Method java/lang/StringBuilder.toString:()Ljava/lang/String;
     380: lconst_1
     381: aload         14
     383: invokeinterface #68,  5           // InterfaceMethod org/apache/hadoop/hbase/test/MetricsAssertHelper.assertCounter:(Ljava/lang/String;JLorg/apache/hadoop/hbase/metrics/BaseSource;)V
     388: getstatic     #10                 // Field TEST_UTIL:Lorg/apache/hadoop/hbase/HBaseTestingUtility;
     391: aload         5
     393: aload         12
     395: invokevirtual #69                 // Method org/apache/hadoop/hbase/regionserver/HRegionServer.getServerName:()Lorg/apache/hadoop/hbase/ServerName;
     398: invokevirtual #70                 // Method org/apache/hadoop/hbase/HBaseTestingUtility.moveRegionAndWait:(Lorg/apache/hadoop/hbase/client/RegionInfo;Lorg/apache/hadoop/hbase/ServerName;)V
     401: iconst_1
     402: istore        8
     404: goto          412
     407: astore        16
     409: iconst_0
     410: istore        8
     412: iload         8
     414: ifeq          471
     417: aload         12
     419: aload         5
     421: invokevirtual #44                 // Method org/apache/hadoop/hbase/HRegionInfo.getRegionName:()[B
     424: invokevirtual #53                 // Method org/apache/hadoop/hbase/regionserver/HRegionServer.getRegion:([B)Lorg/apache/hadoop/hbase/regionserver/HRegion;
     427: invokevirtual #54                 // Method org/apache/hadoop/hbase/regionserver/HRegion.getMetrics:()Lorg/apache/hadoop/hbase/regionserver/MetricsRegion;
     430: invokevirtual #55                 // Method org/apache/hadoop/hbase/regionserver/MetricsRegion.getSource:()Lorg/apache/hadoop/hbase/regionserver/MetricsRegionSource;
     433: invokeinterface #56,  1           // InterfaceMethod org/apache/hadoop/hbase/regionserver/MetricsRegionSource.getAggregateSource:()Lorg/apache/hadoop/hbase/regionserver/MetricsRegionAggregateSource;
     438: astore        16
     440: getstatic     #7                  // Field metricsHelper:Lorg/apache/hadoop/hbase/test/MetricsAssertHelper;
     443: new           #57                 // class java/lang/StringBuilder
     446: dup
     447: invokespecial #58                 // Method java/lang/StringBuilder."<init>":()V
     450: aload         15
     452: invokevirtual #60                 // Method java/lang/StringBuilder.append:(Ljava/lang/String;)Ljava/lang/StringBuilder;
     455: ldc           #67                 // String _putCount
     457: invokevirtual #60                 // Method java/lang/StringBuilder.append:(Ljava/lang/String;)Ljava/lang/StringBuilder;
     460: invokevirtual #66                 // Method java/lang/StringBuilder.toString:()Ljava/lang/String;
     463: lconst_0
     464: aload         16
     466: invokeinterface #68,  5           // InterfaceMethod org/apache/hadoop/hbase/test/MetricsAssertHelper.assertCounter:(Ljava/lang/String;JLorg/apache/hadoop/hbase/metrics/BaseSource;)V
     471: iinc          7, 1
     474: goto          56
     477: getstatic     #10                 // Field TEST_UTIL:Lorg/apache/hadoop/hbase/HBaseTestingUtility;
     480: aload_2
     481: invokevirtual #72                 // Method org/apache/hadoop/hbase/HBaseTestingUtility.deleteTable:(Lorg/apache/hadoop/hbase/TableName;)V
     484: return
    Exception table:
       from    to  target type
         108   115   118   Class java/lang/Throwable
          83    98   140   Class java/lang/Throwable
          83    98   149   any
         161   168   171   Class java/lang/Throwable
         140   151   149   any
         388   404   407   Class java/io/IOException

  static {};
    Code:
       0: ldc           #73                 // class org/apache/hadoop/hbase/regionserver/TestRemoveRegionMetrics
       2: invokestatic  #74                 // Method org/apache/hadoop/hbase/HBaseClassTestRule.forClass:(Ljava/lang/Class;)Lorg/apache/hadoop/hbase/HBaseClassTestRule;
       5: putstatic     #75                 // Field CLASS_RULE:Lorg/apache/hadoop/hbase/HBaseClassTestRule;
       8: return
}
