Compiled from "TestReplicationWALEntryFilters.java"
class org.apache.hadoop.hbase.replication.TestReplicationWALEntryFilters$1 implements org.apache.hadoop.hbase.replication.WALEntryFilter {
  final org.apache.hadoop.hbase.replication.TestReplicationWALEntryFilters this$0;

  org.apache.hadoop.hbase.replication.TestReplicationWALEntryFilters$1(org.apache.hadoop.hbase.replication.TestReplicationWALEntryFilters);
    Code:
       0: aload_0
       1: aload_1
       2: putfield      #1                  // Field this$0:Lorg/apache/hadoop/hbase/replication/TestReplicationWALEntryFilters;
       5: aload_0
       6: invokespecial #2                  // Method java/lang/Object."<init>":()V
       9: return

  public org.apache.hadoop.hbase.wal.WAL$Entry filter(org.apache.hadoop.hbase.wal.WAL$Entry);
    Code:
       0: aconst_null
       1: areturn
}
