Compiled from "TestMultiLogThreshold.java"
public class org.apache.hadoop.hbase.regionserver.TestMultiLogThreshold {
  public static final org.apache.hadoop.hbase.HBaseClassTestRule CLASS_RULE;

  public org.apache.hadoop.hbase.regionserver.TestMultiLogThreshold();
    Code:
       0: aload_0
       1: invokespecial #1                  // Method java/lang/Object."<init>":()V
       4: return

  public static void setup() throws java.lang.Exception;
    Code:
       0: ldc           #2                  // String tableName
       2: invokestatic  #3                  // Method org/apache/hadoop/hbase/TableName.valueOf:(Ljava/lang/String;)Lorg/apache/hadoop/hbase/TableName;
       5: astore_0
       6: invokestatic  #4                  // Method org/apache/hadoop/hbase/HBaseTestingUtility.createLocalHTU:()Lorg/apache/hadoop/hbase/HBaseTestingUtility;
       9: putstatic     #5                  // Field TEST_UTIL:Lorg/apache/hadoop/hbase/HBaseTestingUtility;
      12: getstatic     #5                  // Field TEST_UTIL:Lorg/apache/hadoop/hbase/HBaseTestingUtility;
      15: invokevirtual #6                  // Method org/apache/hadoop/hbase/HBaseTestingUtility.getConfiguration:()Lorg/apache/hadoop/conf/Configuration;
      18: putstatic     #7                  // Field CONF:Lorg/apache/hadoop/conf/Configuration;
      21: getstatic     #7                  // Field CONF:Lorg/apache/hadoop/conf/Configuration;
      24: ldc           #9                  // String hbase.rpc.rows.warning.threshold
      26: sipush        5000
      29: invokevirtual #10                 // Method org/apache/hadoop/conf/Configuration.getInt:(Ljava/lang/String;I)I
      32: putstatic     #11                 // Field THRESHOLD:I
      35: getstatic     #5                  // Field TEST_UTIL:Lorg/apache/hadoop/hbase/HBaseTestingUtility;
      38: invokevirtual #12                 // Method org/apache/hadoop/hbase/HBaseTestingUtility.startMiniCluster:()Lorg/apache/hadoop/hbase/MiniHBaseCluster;
      41: pop
      42: getstatic     #5                  // Field TEST_UTIL:Lorg/apache/hadoop/hbase/HBaseTestingUtility;
      45: aload_0
      46: getstatic     #13                 // Field TEST_FAM:[B
      49: invokevirtual #14                 // Method org/apache/hadoop/hbase/HBaseTestingUtility.createTable:(Lorg/apache/hadoop/hbase/TableName;[B)Lorg/apache/hadoop/hbase/client/Table;
      52: pop
      53: getstatic     #5                  // Field TEST_UTIL:Lorg/apache/hadoop/hbase/HBaseTestingUtility;
      56: aload_0
      57: invokevirtual #15                 // Method org/apache/hadoop/hbase/HBaseTestingUtility.getRSForFirstRegionInTable:(Lorg/apache/hadoop/hbase/TableName;)Lorg/apache/hadoop/hbase/regionserver/HRegionServer;
      60: putstatic     #16                 // Field RS:Lorg/apache/hadoop/hbase/regionserver/HRegionServer;
      63: return

  public void setupTest() throws java.lang.Exception;
    Code:
       0: ldc           #17                 // class org/apache/hadoop/hbase/regionserver/RSRpcServices$LogDelegate
       2: invokestatic  #18                 // Method org/mockito/Mockito.mock:(Ljava/lang/Class;)Ljava/lang/Object;
       5: checkcast     #17                 // class org/apache/hadoop/hbase/regionserver/RSRpcServices$LogDelegate
       8: putstatic     #19                 // Field LD:Lorg/apache/hadoop/hbase/regionserver/RSRpcServices$LogDelegate;
      11: new           #8                  // class org/apache/hadoop/hbase/regionserver/RSRpcServices
      14: dup
      15: getstatic     #16                 // Field RS:Lorg/apache/hadoop/hbase/regionserver/HRegionServer;
      18: getstatic     #19                 // Field LD:Lorg/apache/hadoop/hbase/regionserver/RSRpcServices$LogDelegate;
      21: invokespecial #20                 // Method org/apache/hadoop/hbase/regionserver/RSRpcServices."<init>":(Lorg/apache/hadoop/hbase/regionserver/HRegionServer;Lorg/apache/hadoop/hbase/regionserver/RSRpcServices$LogDelegate;)V
      24: putstatic     #21                 // Field SERVICES:Lorg/apache/hadoop/hbase/regionserver/RSRpcServices;
      27: return

  public void testMultiLogThresholdRegionActions() throws org.apache.hbase.thirdparty.com.google.protobuf.ServiceException, java.io.IOException;
    Code:
       0: aload_0
       1: getstatic     #11                 // Field THRESHOLD:I
       4: iconst_1
       5: iadd
       6: getstatic     #45                 // Field org/apache/hadoop/hbase/regionserver/TestMultiLogThreshold$ActionType.REGION_ACTIONS:Lorg/apache/hadoop/hbase/regionserver/TestMultiLogThreshold$ActionType;
       9: invokespecial #46                 // Method sendMultiRequest:(ILorg/apache/hadoop/hbase/regionserver/TestMultiLogThreshold$ActionType;)V
      12: getstatic     #19                 // Field LD:Lorg/apache/hadoop/hbase/regionserver/RSRpcServices$LogDelegate;
      15: iconst_1
      16: invokestatic  #47                 // Method org/mockito/Mockito.times:(I)Lorg/mockito/verification/VerificationMode;
      19: invokestatic  #48                 // Method org/mockito/Mockito.verify:(Ljava/lang/Object;Lorg/mockito/verification/VerificationMode;)Ljava/lang/Object;
      22: checkcast     #17                 // class org/apache/hadoop/hbase/regionserver/RSRpcServices$LogDelegate
      25: invokestatic  #49                 // Method org/mockito/Mockito.anyString:()Ljava/lang/String;
      28: invokestatic  #50                 // Method org/mockito/Mockito.anyInt:()I
      31: invokestatic  #50                 // Method org/mockito/Mockito.anyInt:()I
      34: invokeinterface #51,  4           // InterfaceMethod org/apache/hadoop/hbase/regionserver/RSRpcServices$LogDelegate.logBatchWarning:(Ljava/lang/String;II)V
      39: return

  public void testMultiNoLogThresholdRegionActions() throws org.apache.hbase.thirdparty.com.google.protobuf.ServiceException, java.io.IOException;
    Code:
       0: aload_0
       1: getstatic     #11                 // Field THRESHOLD:I
       4: getstatic     #45                 // Field org/apache/hadoop/hbase/regionserver/TestMultiLogThreshold$ActionType.REGION_ACTIONS:Lorg/apache/hadoop/hbase/regionserver/TestMultiLogThreshold$ActionType;
       7: invokespecial #46                 // Method sendMultiRequest:(ILorg/apache/hadoop/hbase/regionserver/TestMultiLogThreshold$ActionType;)V
      10: getstatic     #19                 // Field LD:Lorg/apache/hadoop/hbase/regionserver/RSRpcServices$LogDelegate;
      13: invokestatic  #52                 // Method org/mockito/Mockito.never:()Lorg/mockito/verification/VerificationMode;
      16: invokestatic  #48                 // Method org/mockito/Mockito.verify:(Ljava/lang/Object;Lorg/mockito/verification/VerificationMode;)Ljava/lang/Object;
      19: checkcast     #17                 // class org/apache/hadoop/hbase/regionserver/RSRpcServices$LogDelegate
      22: invokestatic  #49                 // Method org/mockito/Mockito.anyString:()Ljava/lang/String;
      25: invokestatic  #50                 // Method org/mockito/Mockito.anyInt:()I
      28: invokestatic  #50                 // Method org/mockito/Mockito.anyInt:()I
      31: invokeinterface #51,  4           // InterfaceMethod org/apache/hadoop/hbase/regionserver/RSRpcServices$LogDelegate.logBatchWarning:(Ljava/lang/String;II)V
      36: return

  public void testMultiLogThresholdActions() throws org.apache.hbase.thirdparty.com.google.protobuf.ServiceException, java.io.IOException;
    Code:
       0: aload_0
       1: getstatic     #11                 // Field THRESHOLD:I
       4: iconst_1
       5: iadd
       6: getstatic     #53                 // Field org/apache/hadoop/hbase/regionserver/TestMultiLogThreshold$ActionType.ACTIONS:Lorg/apache/hadoop/hbase/regionserver/TestMultiLogThreshold$ActionType;
       9: invokespecial #46                 // Method sendMultiRequest:(ILorg/apache/hadoop/hbase/regionserver/TestMultiLogThreshold$ActionType;)V
      12: getstatic     #19                 // Field LD:Lorg/apache/hadoop/hbase/regionserver/RSRpcServices$LogDelegate;
      15: iconst_1
      16: invokestatic  #47                 // Method org/mockito/Mockito.times:(I)Lorg/mockito/verification/VerificationMode;
      19: invokestatic  #48                 // Method org/mockito/Mockito.verify:(Ljava/lang/Object;Lorg/mockito/verification/VerificationMode;)Ljava/lang/Object;
      22: checkcast     #17                 // class org/apache/hadoop/hbase/regionserver/RSRpcServices$LogDelegate
      25: invokestatic  #49                 // Method org/mockito/Mockito.anyString:()Ljava/lang/String;
      28: invokestatic  #50                 // Method org/mockito/Mockito.anyInt:()I
      31: invokestatic  #50                 // Method org/mockito/Mockito.anyInt:()I
      34: invokeinterface #51,  4           // InterfaceMethod org/apache/hadoop/hbase/regionserver/RSRpcServices$LogDelegate.logBatchWarning:(Ljava/lang/String;II)V
      39: return

  public void testMultiNoLogThresholdAction() throws org.apache.hbase.thirdparty.com.google.protobuf.ServiceException, java.io.IOException;
    Code:
       0: aload_0
       1: getstatic     #11                 // Field THRESHOLD:I
       4: getstatic     #53                 // Field org/apache/hadoop/hbase/regionserver/TestMultiLogThreshold$ActionType.ACTIONS:Lorg/apache/hadoop/hbase/regionserver/TestMultiLogThreshold$ActionType;
       7: invokespecial #46                 // Method sendMultiRequest:(ILorg/apache/hadoop/hbase/regionserver/TestMultiLogThreshold$ActionType;)V
      10: getstatic     #19                 // Field LD:Lorg/apache/hadoop/hbase/regionserver/RSRpcServices$LogDelegate;
      13: invokestatic  #52                 // Method org/mockito/Mockito.never:()Lorg/mockito/verification/VerificationMode;
      16: invokestatic  #48                 // Method org/mockito/Mockito.verify:(Ljava/lang/Object;Lorg/mockito/verification/VerificationMode;)Ljava/lang/Object;
      19: checkcast     #17                 // class org/apache/hadoop/hbase/regionserver/RSRpcServices$LogDelegate
      22: invokestatic  #49                 // Method org/mockito/Mockito.anyString:()Ljava/lang/String;
      25: invokestatic  #50                 // Method org/mockito/Mockito.anyInt:()I
      28: invokestatic  #50                 // Method org/mockito/Mockito.anyInt:()I
      31: invokeinterface #51,  4           // InterfaceMethod org/apache/hadoop/hbase/regionserver/RSRpcServices$LogDelegate.logBatchWarning:(Ljava/lang/String;II)V
      36: return

  static {};
    Code:
       0: ldc           #54                 // class org/apache/hadoop/hbase/regionserver/TestMultiLogThreshold
       2: invokestatic  #55                 // Method org/apache/hadoop/hbase/HBaseClassTestRule.forClass:(Ljava/lang/Class;)Lorg/apache/hadoop/hbase/HBaseClassTestRule;
       5: putstatic     #56                 // Field CLASS_RULE:Lorg/apache/hadoop/hbase/HBaseClassTestRule;
       8: ldc           #57                 // String fam
      10: invokestatic  #34                 // Method org/apache/hadoop/hbase/util/Bytes.toBytes:(Ljava/lang/String;)[B
      13: putstatic     #13                 // Field TEST_FAM:[B
      16: return
}
