Compiled from "TestClientScannerRPCTimeout.java"
public class org.apache.hadoop.hbase.client.TestClientScannerRPCTimeout {
  public static final org.apache.hadoop.hbase.HBaseClassTestRule CLASS_RULE;

  public org.junit.rules.TestName name;

  public org.apache.hadoop.hbase.client.TestClientScannerRPCTimeout();
    Code:
       0: aload_0
       1: invokespecial #1                  // Method java/lang/Object."<init>":()V
       4: aload_0
       5: new           #2                  // class org/junit/rules/TestName
       8: dup
       9: invokespecial #3                  // Method org/junit/rules/TestName."<init>":()V
      12: putfield      #4                  // Field name:Lorg/junit/rules/TestName;
      15: return

  public static void setUpBeforeClass() throws java.lang.Exception;
    Code:
       0: getstatic     #5                  // Field TEST_UTIL:Lorg/apache/hadoop/hbase/HBaseTestingUtility;
       3: invokevirtual #6                  // Method org/apache/hadoop/hbase/HBaseTestingUtility.getConfiguration:()Lorg/apache/hadoop/conf/Configuration;
       6: astore_0
       7: aload_0
       8: ldc           #7                  // String hbase.regionserver.msginterval
      10: sipush        30000
      13: invokevirtual #8                  // Method org/apache/hadoop/conf/Configuration.setInt:(Ljava/lang/String;I)V
      16: aload_0
      17: ldc           #10                 // String hbase.rpc.timeout
      19: sipush        2000
      22: invokevirtual #8                  // Method org/apache/hadoop/conf/Configuration.setInt:(Ljava/lang/String;I)V
      25: aload_0
      26: ldc           #12                 // String hbase.regionserver.impl
      28: iconst_1
      29: anewarray     #13                 // class java/lang/String
      32: dup
      33: iconst_0
      34: ldc           #14                 // class org/apache/hadoop/hbase/client/TestClientScannerRPCTimeout$RegionServerWithScanTimeout
      36: invokevirtual #15                 // Method java/lang/Class.getName:()Ljava/lang/String;
      39: aastore
      40: invokevirtual #16                 // Method org/apache/hadoop/conf/Configuration.setStrings:(Ljava/lang/String;[Ljava/lang/String;)V
      43: aload_0
      44: ldc           #17                 // String hbase.client.retries.number
      46: iconst_3
      47: invokevirtual #8                  // Method org/apache/hadoop/conf/Configuration.setInt:(Ljava/lang/String;I)V
      50: aload_0
      51: ldc           #18                 // String hbase.client.pause
      53: sipush        1000
      56: invokevirtual #8                  // Method org/apache/hadoop/conf/Configuration.setInt:(Ljava/lang/String;I)V
      59: getstatic     #5                  // Field TEST_UTIL:Lorg/apache/hadoop/hbase/HBaseTestingUtility;
      62: iconst_1
      63: invokevirtual #19                 // Method org/apache/hadoop/hbase/HBaseTestingUtility.startMiniCluster:(I)Lorg/apache/hadoop/hbase/MiniHBaseCluster;
      66: pop
      67: return

  public static void tearDownAfterClass() throws java.lang.Exception;
    Code:
       0: getstatic     #5                  // Field TEST_UTIL:Lorg/apache/hadoop/hbase/HBaseTestingUtility;
       3: invokevirtual #20                 // Method org/apache/hadoop/hbase/HBaseTestingUtility.shutdownMiniCluster:()V
       6: return

  public void testScannerNextRPCTimesout() throws java.lang.Exception;
    Code:
       0: aload_0
       1: getfield      #4                  // Field name:Lorg/junit/rules/TestName;
       4: invokevirtual #21                 // Method org/junit/rules/TestName.getMethodName:()Ljava/lang/String;
       7: invokestatic  #22                 // Method org/apache/hadoop/hbase/TableName.valueOf:(Ljava/lang/String;)Lorg/apache/hadoop/hbase/TableName;
      10: astore_1
      11: getstatic     #5                  // Field TEST_UTIL:Lorg/apache/hadoop/hbase/HBaseTestingUtility;
      14: aload_1
      15: getstatic     #23                 // Field FAMILY:[B
      18: invokevirtual #24                 // Method org/apache/hadoop/hbase/HBaseTestingUtility.createTable:(Lorg/apache/hadoop/hbase/TableName;[B)Lorg/apache/hadoop/hbase/client/Table;
      21: astore_2
      22: ldc           #25                 // String row-0
      24: invokestatic  #26                 // Method org/apache/hadoop/hbase/util/Bytes.toBytes:(Ljava/lang/String;)[B
      27: astore_3
      28: ldc           #27                 // String row-1
      30: invokestatic  #26                 // Method org/apache/hadoop/hbase/util/Bytes.toBytes:(Ljava/lang/String;)[B
      33: astore        4
      35: ldc           #28                 // String row-2
      37: invokestatic  #26                 // Method org/apache/hadoop/hbase/util/Bytes.toBytes:(Ljava/lang/String;)[B
      40: astore        5
      42: ldc           #29                 // String row-3
      44: invokestatic  #26                 // Method org/apache/hadoop/hbase/util/Bytes.toBytes:(Ljava/lang/String;)[B
      47: astore        6
      49: aload_0
      50: aload_2
      51: aload_3
      52: invokespecial #30                 // Method putToTable:(Lorg/apache/hadoop/hbase/client/Table;[B)V
      55: aload_0
      56: aload_2
      57: aload         4
      59: invokespecial #30                 // Method putToTable:(Lorg/apache/hadoop/hbase/client/Table;[B)V
      62: aload_0
      63: aload_2
      64: aload         5
      66: invokespecial #30                 // Method putToTable:(Lorg/apache/hadoop/hbase/client/Table;[B)V
      69: aload_0
      70: aload_2
      71: aload         6
      73: invokespecial #30                 // Method putToTable:(Lorg/apache/hadoop/hbase/client/Table;[B)V
      76: getstatic     #31                 // Field LOG:Lorg/slf4j/Logger;
      79: ldc           #32                 // String Wrote our three values
      81: invokeinterface #33,  2           // InterfaceMethod org/slf4j/Logger.info:(Ljava/lang/String;)V
      86: lconst_1
      87: invokestatic  #34                 // Method org/apache/hadoop/hbase/client/TestClientScannerRPCTimeout$RSRpcServicesWithScanTimeout.access$002:(J)J
      90: pop2
      91: new           #35                 // class org/apache/hadoop/hbase/client/Scan
      94: dup
      95: invokespecial #36                 // Method org/apache/hadoop/hbase/client/Scan."<init>":()V
      98: astore        7
     100: aload         7
     102: iconst_1
     103: invokevirtual #37                 // Method org/apache/hadoop/hbase/client/Scan.setCaching:(I)Lorg/apache/hadoop/hbase/client/Scan;
     106: pop
     107: aload_2
     108: aload         7
     110: invokeinterface #38,  2           // InterfaceMethod org/apache/hadoop/hbase/client/Table.getScanner:(Lorg/apache/hadoop/hbase/client/Scan;)Lorg/apache/hadoop/hbase/client/ResultScanner;
     115: astore        8
     117: aload         8
     119: invokeinterface #39,  1           // InterfaceMethod org/apache/hadoop/hbase/client/ResultScanner.next:()Lorg/apache/hadoop/hbase/client/Result;
     124: astore        9
     126: ldc           #40                 // String Expected row: row-0
     128: aload_3
     129: aload         9
     131: invokevirtual #41                 // Method org/apache/hadoop/hbase/client/Result.getRow:()[B
     134: invokestatic  #42                 // Method org/apache/hadoop/hbase/util/Bytes.equals:([B[B)Z
     137: invokestatic  #43                 // Method org/junit/Assert.assertTrue:(Ljava/lang/String;Z)V
     140: aload         8
     142: invokeinterface #39,  1           // InterfaceMethod org/apache/hadoop/hbase/client/ResultScanner.next:()Lorg/apache/hadoop/hbase/client/Result;
     147: astore        9
     149: ldc           #44                 // String Expected row: row-1
     151: aload         4
     153: aload         9
     155: invokevirtual #41                 // Method org/apache/hadoop/hbase/client/Result.getRow:()[B
     158: invokestatic  #42                 // Method org/apache/hadoop/hbase/util/Bytes.equals:([B[B)Z
     161: invokestatic  #43                 // Method org/junit/Assert.assertTrue:(Ljava/lang/String;Z)V
     164: getstatic     #31                 // Field LOG:Lorg/slf4j/Logger;
     167: ldc           #45                 // String Got expected first row
     169: invokeinterface #33,  2           // InterfaceMethod org/slf4j/Logger.info:(Ljava/lang/String;)V
     174: invokestatic  #46                 // Method java/lang/System.currentTimeMillis:()J
     177: lstore        10
     179: aload         8
     181: invokeinterface #39,  1           // InterfaceMethod org/apache/hadoop/hbase/client/ResultScanner.next:()Lorg/apache/hadoop/hbase/client/Result;
     186: astore        9
     188: invokestatic  #46                 // Method java/lang/System.currentTimeMillis:()J
     191: lload         10
     193: lsub
     194: ldc2_w        #47                 // long 2000l
     197: lcmp
     198: ifle          205
     201: iconst_1
     202: goto          206
     205: iconst_0
     206: invokestatic  #49                 // Method org/junit/Assert.assertTrue:(Z)V
     209: ldc           #50                 // String Expected row: row-2
     211: aload         5
     213: aload         9
     215: invokevirtual #41                 // Method org/apache/hadoop/hbase/client/Result.getRow:()[B
     218: invokestatic  #42                 // Method org/apache/hadoop/hbase/util/Bytes.equals:([B[B)Z
     221: invokestatic  #43                 // Method org/junit/Assert.assertTrue:(Ljava/lang/String;Z)V
     224: ldc2_w        #51                 // long -1l
     227: invokestatic  #34                 // Method org/apache/hadoop/hbase/client/TestClientScannerRPCTimeout$RSRpcServicesWithScanTimeout.access$002:(J)J
     230: pop2
     231: aload         8
     233: invokeinterface #39,  1           // InterfaceMethod org/apache/hadoop/hbase/client/ResultScanner.next:()Lorg/apache/hadoop/hbase/client/Result;
     238: astore        9
     240: ldc           #53                 // String Expected row: row-3
     242: aload         6
     244: aload         9
     246: invokevirtual #41                 // Method org/apache/hadoop/hbase/client/Result.getRow:()[B
     249: invokestatic  #42                 // Method org/apache/hadoop/hbase/util/Bytes.equals:([B[B)Z
     252: invokestatic  #43                 // Method org/junit/Assert.assertTrue:(Ljava/lang/String;Z)V
     255: aload         8
     257: invokeinterface #54,  1           // InterfaceMethod org/apache/hadoop/hbase/client/ResultScanner.close:()V
     262: aload_2
     263: aload         7
     265: invokeinterface #38,  2           // InterfaceMethod org/apache/hadoop/hbase/client/Table.getScanner:(Lorg/apache/hadoop/hbase/client/Scan;)Lorg/apache/hadoop/hbase/client/ResultScanner;
     270: astore        8
     272: iconst_1
     273: invokestatic  #55                 // Method org/apache/hadoop/hbase/client/TestClientScannerRPCTimeout$RSRpcServicesWithScanTimeout.access$102:(Z)Z
     276: pop
     277: iconst_0
     278: invokestatic  #56                 // Method org/apache/hadoop/hbase/client/TestClientScannerRPCTimeout$RSRpcServicesWithScanTimeout.access$202:(I)I
     281: pop
     282: aload         8
     284: invokeinterface #39,  1           // InterfaceMethod org/apache/hadoop/hbase/client/ResultScanner.next:()Lorg/apache/hadoop/hbase/client/Result;
     289: astore        9
     291: goto          308
     294: astore        12
     296: getstatic     #31                 // Field LOG:Lorg/slf4j/Logger;
     299: ldc           #58                 // String Failed after maximal attempts=3
     301: aload         12
     303: invokeinterface #59,  3           // InterfaceMethod org/slf4j/Logger.info:(Ljava/lang/String;Ljava/lang/Throwable;)V
     308: new           #60                 // class java/lang/StringBuilder
     311: dup
     312: invokespecial #61                 // Method java/lang/StringBuilder."<init>":()V
     315: ldc           #62                 // String Expected maximal try number=3, actual =
     317: invokevirtual #63                 // Method java/lang/StringBuilder.append:(Ljava/lang/String;)Ljava/lang/StringBuilder;
     320: invokestatic  #64                 // Method org/apache/hadoop/hbase/client/TestClientScannerRPCTimeout$RSRpcServicesWithScanTimeout.access$200:()I
     323: invokevirtual #65                 // Method java/lang/StringBuilder.append:(I)Ljava/lang/StringBuilder;
     326: invokevirtual #66                 // Method java/lang/StringBuilder.toString:()Ljava/lang/String;
     329: invokestatic  #64                 // Method org/apache/hadoop/hbase/client/TestClientScannerRPCTimeout$RSRpcServicesWithScanTimeout.access$200:()I
     332: iconst_3
     333: if_icmpgt     340
     336: iconst_1
     337: goto          341
     340: iconst_0
     341: invokestatic  #43                 // Method org/junit/Assert.assertTrue:(Ljava/lang/String;Z)V
     344: return
    Exception table:
       from    to  target type
         282   291   294   Class java/io/IOException

  static {};
    Code:
       0: ldc           #11                 // class org/apache/hadoop/hbase/client/TestClientScannerRPCTimeout
       2: invokestatic  #73                 // Method org/apache/hadoop/hbase/HBaseClassTestRule.forClass:(Ljava/lang/Class;)Lorg/apache/hadoop/hbase/HBaseClassTestRule;
       5: putstatic     #74                 // Field CLASS_RULE:Lorg/apache/hadoop/hbase/HBaseClassTestRule;
       8: ldc           #11                 // class org/apache/hadoop/hbase/client/TestClientScannerRPCTimeout
      10: invokestatic  #75                 // Method org/slf4j/LoggerFactory.getLogger:(Ljava/lang/Class;)Lorg/slf4j/Logger;
      13: putstatic     #31                 // Field LOG:Lorg/slf4j/Logger;
      16: new           #76                 // class org/apache/hadoop/hbase/HBaseTestingUtility
      19: dup
      20: invokespecial #77                 // Method org/apache/hadoop/hbase/HBaseTestingUtility."<init>":()V
      23: putstatic     #5                  // Field TEST_UTIL:Lorg/apache/hadoop/hbase/HBaseTestingUtility;
      26: ldc           #78                 // String testFamily
      28: invokestatic  #26                 // Method org/apache/hadoop/hbase/util/Bytes.toBytes:(Ljava/lang/String;)[B
      31: putstatic     #23                 // Field FAMILY:[B
      34: ldc           #79                 // String testQualifier
      36: invokestatic  #26                 // Method org/apache/hadoop/hbase/util/Bytes.toBytes:(Ljava/lang/String;)[B
      39: putstatic     #69                 // Field QUALIFIER:[B
      42: ldc           #80                 // String testValue
      44: invokestatic  #26                 // Method org/apache/hadoop/hbase/util/Bytes.toBytes:(Ljava/lang/String;)[B
      47: putstatic     #70                 // Field VALUE:[B
      50: return
}
