Compiled from "TestNewVersionBehaviorFromClientSide.java"
public class org.apache.hadoop.hbase.regionserver.TestNewVersionBehaviorFromClientSide {
  public static final org.apache.hadoop.hbase.HBaseClassTestRule CLASS_RULE;

  public org.junit.rules.TestName name;

  public org.apache.hadoop.hbase.regionserver.TestNewVersionBehaviorFromClientSide();
    Code:
       0: aload_0
       1: invokespecial #1                  // Method java/lang/Object."<init>":()V
       4: aload_0
       5: new           #2                  // class org/junit/rules/TestName
       8: dup
       9: invokespecial #3                  // Method org/junit/rules/TestName."<init>":()V
      12: putfield      #4                  // Field name:Lorg/junit/rules/TestName;
      15: return

  public static void setUpBeforeClass() throws java.lang.Exception;
    Code:
       0: getstatic     #5                  // Field TEST_UTIL:Lorg/apache/hadoop/hbase/HBaseTestingUtility;
       3: iconst_1
       4: invokevirtual #6                  // Method org/apache/hadoop/hbase/HBaseTestingUtility.startMiniCluster:(I)Lorg/apache/hadoop/hbase/MiniHBaseCluster;
       7: pop
       8: return

  public static void setDownAfterClass() throws java.lang.Exception;
    Code:
       0: getstatic     #5                  // Field TEST_UTIL:Lorg/apache/hadoop/hbase/HBaseTestingUtility;
       3: invokevirtual #7                  // Method org/apache/hadoop/hbase/HBaseTestingUtility.shutdownMiniCluster:()V
       6: return

  public void testPutAndDeleteVersions() throws java.io.IOException;
    Code:
       0: aload_0
       1: invokespecial #22                 // Method createTable:()Lorg/apache/hadoop/hbase/client/Table;
       4: astore_1
       5: aconst_null
       6: astore_2
       7: aload_1
       8: new           #23                 // class org/apache/hadoop/hbase/client/Put
      11: dup
      12: getstatic     #24                 // Field ROW:[B
      15: invokespecial #25                 // Method org/apache/hadoop/hbase/client/Put."<init>":([B)V
      18: getstatic     #13                 // Field FAMILY:[B
      21: getstatic     #26                 // Field col1:[B
      24: ldc2_w        #27                 // long 1000001l
      27: getstatic     #29                 // Field value:[B
      30: invokevirtual #30                 // Method org/apache/hadoop/hbase/client/Put.addColumn:([B[BJ[B)Lorg/apache/hadoop/hbase/client/Put;
      33: invokeinterface #31,  2           // InterfaceMethod org/apache/hadoop/hbase/client/Table.put:(Lorg/apache/hadoop/hbase/client/Put;)V
      38: aload_1
      39: new           #23                 // class org/apache/hadoop/hbase/client/Put
      42: dup
      43: getstatic     #24                 // Field ROW:[B
      46: invokespecial #25                 // Method org/apache/hadoop/hbase/client/Put."<init>":([B)V
      49: getstatic     #13                 // Field FAMILY:[B
      52: getstatic     #26                 // Field col1:[B
      55: ldc2_w        #32                 // long 1000002l
      58: getstatic     #29                 // Field value:[B
      61: invokevirtual #30                 // Method org/apache/hadoop/hbase/client/Put.addColumn:([B[BJ[B)Lorg/apache/hadoop/hbase/client/Put;
      64: invokeinterface #31,  2           // InterfaceMethod org/apache/hadoop/hbase/client/Table.put:(Lorg/apache/hadoop/hbase/client/Put;)V
      69: aload_1
      70: new           #23                 // class org/apache/hadoop/hbase/client/Put
      73: dup
      74: getstatic     #24                 // Field ROW:[B
      77: invokespecial #25                 // Method org/apache/hadoop/hbase/client/Put."<init>":([B)V
      80: getstatic     #13                 // Field FAMILY:[B
      83: getstatic     #26                 // Field col1:[B
      86: ldc2_w        #34                 // long 1000003l
      89: getstatic     #29                 // Field value:[B
      92: invokevirtual #30                 // Method org/apache/hadoop/hbase/client/Put.addColumn:([B[BJ[B)Lorg/apache/hadoop/hbase/client/Put;
      95: invokeinterface #31,  2           // InterfaceMethod org/apache/hadoop/hbase/client/Table.put:(Lorg/apache/hadoop/hbase/client/Put;)V
     100: aload_1
     101: new           #23                 // class org/apache/hadoop/hbase/client/Put
     104: dup
     105: getstatic     #24                 // Field ROW:[B
     108: invokespecial #25                 // Method org/apache/hadoop/hbase/client/Put."<init>":([B)V
     111: getstatic     #13                 // Field FAMILY:[B
     114: getstatic     #26                 // Field col1:[B
     117: ldc2_w        #36                 // long 1000004l
     120: getstatic     #29                 // Field value:[B
     123: invokevirtual #30                 // Method org/apache/hadoop/hbase/client/Put.addColumn:([B[BJ[B)Lorg/apache/hadoop/hbase/client/Put;
     126: invokeinterface #31,  2           // InterfaceMethod org/apache/hadoop/hbase/client/Table.put:(Lorg/apache/hadoop/hbase/client/Put;)V
     131: aload_1
     132: new           #38                 // class org/apache/hadoop/hbase/client/Delete
     135: dup
     136: getstatic     #24                 // Field ROW:[B
     139: invokespecial #39                 // Method org/apache/hadoop/hbase/client/Delete."<init>":([B)V
     142: getstatic     #13                 // Field FAMILY:[B
     145: getstatic     #26                 // Field col1:[B
     148: ldc2_w        #40                 // long 2000000l
     151: invokevirtual #42                 // Method org/apache/hadoop/hbase/client/Delete.addColumns:([B[BJ)Lorg/apache/hadoop/hbase/client/Delete;
     154: invokeinterface #43,  2           // InterfaceMethod org/apache/hadoop/hbase/client/Table.delete:(Lorg/apache/hadoop/hbase/client/Delete;)V
     159: aload_1
     160: new           #23                 // class org/apache/hadoop/hbase/client/Put
     163: dup
     164: getstatic     #24                 // Field ROW:[B
     167: invokespecial #25                 // Method org/apache/hadoop/hbase/client/Put."<init>":([B)V
     170: getstatic     #13                 // Field FAMILY:[B
     173: getstatic     #26                 // Field col1:[B
     176: ldc2_w        #44                 // long 1000000l
     179: getstatic     #29                 // Field value:[B
     182: invokevirtual #30                 // Method org/apache/hadoop/hbase/client/Put.addColumn:([B[BJ[B)Lorg/apache/hadoop/hbase/client/Put;
     185: invokeinterface #31,  2           // InterfaceMethod org/apache/hadoop/hbase/client/Table.put:(Lorg/apache/hadoop/hbase/client/Put;)V
     190: getstatic     #5                  // Field TEST_UTIL:Lorg/apache/hadoop/hbase/HBaseTestingUtility;
     193: invokevirtual #46                 // Method org/apache/hadoop/hbase/HBaseTestingUtility.getAdmin:()Lorg/apache/hadoop/hbase/client/Admin;
     196: aload_1
     197: invokeinterface #47,  1           // InterfaceMethod org/apache/hadoop/hbase/client/Table.getName:()Lorg/apache/hadoop/hbase/TableName;
     202: invokeinterface #48,  2           // InterfaceMethod org/apache/hadoop/hbase/client/Admin.flush:(Lorg/apache/hadoop/hbase/TableName;)V
     207: aload_1
     208: new           #49                 // class org/apache/hadoop/hbase/client/Get
     211: dup
     212: getstatic     #24                 // Field ROW:[B
     215: invokespecial #50                 // Method org/apache/hadoop/hbase/client/Get."<init>":([B)V
     218: iconst_3
     219: invokevirtual #51                 // Method org/apache/hadoop/hbase/client/Get.readVersions:(I)Lorg/apache/hadoop/hbase/client/Get;
     222: invokeinterface #52,  2           // InterfaceMethod org/apache/hadoop/hbase/client/Table.get:(Lorg/apache/hadoop/hbase/client/Get;)Lorg/apache/hadoop/hbase/client/Result;
     227: astore_3
     228: lconst_1
     229: aload_3
     230: invokevirtual #53                 // Method org/apache/hadoop/hbase/client/Result.size:()I
     233: i2l
     234: invokestatic  #54                 // Method org/junit/Assert.assertEquals:(JJ)V
     237: ldc2_w        #44                 // long 1000000l
     240: aload_3
     241: invokevirtual #55                 // Method org/apache/hadoop/hbase/client/Result.rawCells:()[Lorg/apache/hadoop/hbase/Cell;
     244: iconst_0
     245: aaload
     246: invokeinterface #56,  1           // InterfaceMethod org/apache/hadoop/hbase/Cell.getTimestamp:()J
     251: invokestatic  #54                 // Method org/junit/Assert.assertEquals:(JJ)V
     254: aload_1
     255: ifnull        333
     258: aload_2
     259: ifnull        280
     262: aload_1
     263: invokeinterface #57,  1           // InterfaceMethod org/apache/hadoop/hbase/client/Table.close:()V
     268: goto          333
     271: astore_3
     272: aload_2
     273: aload_3
     274: invokevirtual #59                 // Method java/lang/Throwable.addSuppressed:(Ljava/lang/Throwable;)V
     277: goto          333
     280: aload_1
     281: invokeinterface #57,  1           // InterfaceMethod org/apache/hadoop/hbase/client/Table.close:()V
     286: goto          333
     289: astore_3
     290: aload_3
     291: astore_2
     292: aload_3
     293: athrow
     294: astore        4
     296: aload_1
     297: ifnull        330
     300: aload_2
     301: ifnull        324
     304: aload_1
     305: invokeinterface #57,  1           // InterfaceMethod org/apache/hadoop/hbase/client/Table.close:()V
     310: goto          330
     313: astore        5
     315: aload_2
     316: aload         5
     318: invokevirtual #59                 // Method java/lang/Throwable.addSuppressed:(Ljava/lang/Throwable;)V
     321: goto          330
     324: aload_1
     325: invokeinterface #57,  1           // InterfaceMethod org/apache/hadoop/hbase/client/Table.close:()V
     330: aload         4
     332: athrow
     333: return
    Exception table:
       from    to  target type
         262   268   271   Class java/lang/Throwable
           7   254   289   Class java/lang/Throwable
           7   254   294   any
         304   310   313   Class java/lang/Throwable
         289   296   294   any

  public void testPutMasked() throws java.io.IOException;
    Code:
       0: aload_0
       1: invokespecial #22                 // Method createTable:()Lorg/apache/hadoop/hbase/client/Table;
       4: astore_1
       5: aconst_null
       6: astore_2
       7: aload_1
       8: new           #23                 // class org/apache/hadoop/hbase/client/Put
      11: dup
      12: getstatic     #24                 // Field ROW:[B
      15: invokespecial #25                 // Method org/apache/hadoop/hbase/client/Put."<init>":([B)V
      18: getstatic     #13                 // Field FAMILY:[B
      21: getstatic     #26                 // Field col1:[B
      24: ldc2_w        #27                 // long 1000001l
      27: getstatic     #29                 // Field value:[B
      30: invokevirtual #30                 // Method org/apache/hadoop/hbase/client/Put.addColumn:([B[BJ[B)Lorg/apache/hadoop/hbase/client/Put;
      33: invokeinterface #31,  2           // InterfaceMethod org/apache/hadoop/hbase/client/Table.put:(Lorg/apache/hadoop/hbase/client/Put;)V
      38: aload_1
      39: new           #23                 // class org/apache/hadoop/hbase/client/Put
      42: dup
      43: getstatic     #24                 // Field ROW:[B
      46: invokespecial #25                 // Method org/apache/hadoop/hbase/client/Put."<init>":([B)V
      49: getstatic     #13                 // Field FAMILY:[B
      52: getstatic     #26                 // Field col1:[B
      55: ldc2_w        #32                 // long 1000002l
      58: getstatic     #29                 // Field value:[B
      61: invokevirtual #30                 // Method org/apache/hadoop/hbase/client/Put.addColumn:([B[BJ[B)Lorg/apache/hadoop/hbase/client/Put;
      64: invokeinterface #31,  2           // InterfaceMethod org/apache/hadoop/hbase/client/Table.put:(Lorg/apache/hadoop/hbase/client/Put;)V
      69: aload_1
      70: new           #23                 // class org/apache/hadoop/hbase/client/Put
      73: dup
      74: getstatic     #24                 // Field ROW:[B
      77: invokespecial #25                 // Method org/apache/hadoop/hbase/client/Put."<init>":([B)V
      80: getstatic     #13                 // Field FAMILY:[B
      83: getstatic     #26                 // Field col1:[B
      86: ldc2_w        #34                 // long 1000003l
      89: getstatic     #29                 // Field value:[B
      92: invokevirtual #30                 // Method org/apache/hadoop/hbase/client/Put.addColumn:([B[BJ[B)Lorg/apache/hadoop/hbase/client/Put;
      95: invokeinterface #31,  2           // InterfaceMethod org/apache/hadoop/hbase/client/Table.put:(Lorg/apache/hadoop/hbase/client/Put;)V
     100: aload_1
     101: new           #23                 // class org/apache/hadoop/hbase/client/Put
     104: dup
     105: getstatic     #24                 // Field ROW:[B
     108: invokespecial #25                 // Method org/apache/hadoop/hbase/client/Put."<init>":([B)V
     111: getstatic     #13                 // Field FAMILY:[B
     114: getstatic     #26                 // Field col1:[B
     117: ldc2_w        #36                 // long 1000004l
     120: getstatic     #29                 // Field value:[B
     123: invokevirtual #30                 // Method org/apache/hadoop/hbase/client/Put.addColumn:([B[BJ[B)Lorg/apache/hadoop/hbase/client/Put;
     126: invokeinterface #31,  2           // InterfaceMethod org/apache/hadoop/hbase/client/Table.put:(Lorg/apache/hadoop/hbase/client/Put;)V
     131: aload_1
     132: new           #38                 // class org/apache/hadoop/hbase/client/Delete
     135: dup
     136: getstatic     #24                 // Field ROW:[B
     139: invokespecial #39                 // Method org/apache/hadoop/hbase/client/Delete."<init>":([B)V
     142: getstatic     #13                 // Field FAMILY:[B
     145: getstatic     #26                 // Field col1:[B
     148: ldc2_w        #34                 // long 1000003l
     151: invokevirtual #60                 // Method org/apache/hadoop/hbase/client/Delete.addColumn:([B[BJ)Lorg/apache/hadoop/hbase/client/Delete;
     154: invokeinterface #43,  2           // InterfaceMethod org/apache/hadoop/hbase/client/Table.delete:(Lorg/apache/hadoop/hbase/client/Delete;)V
     159: aload_1
     160: new           #49                 // class org/apache/hadoop/hbase/client/Get
     163: dup
     164: getstatic     #24                 // Field ROW:[B
     167: invokespecial #50                 // Method org/apache/hadoop/hbase/client/Get."<init>":([B)V
     170: iconst_3
     171: invokevirtual #51                 // Method org/apache/hadoop/hbase/client/Get.readVersions:(I)Lorg/apache/hadoop/hbase/client/Get;
     174: invokeinterface #52,  2           // InterfaceMethod org/apache/hadoop/hbase/client/Table.get:(Lorg/apache/hadoop/hbase/client/Get;)Lorg/apache/hadoop/hbase/client/Result;
     179: astore_3
     180: ldc2_w        #61                 // long 2l
     183: aload_3
     184: invokevirtual #53                 // Method org/apache/hadoop/hbase/client/Result.size:()I
     187: i2l
     188: invokestatic  #54                 // Method org/junit/Assert.assertEquals:(JJ)V
     191: ldc2_w        #36                 // long 1000004l
     194: aload_3
     195: invokevirtual #55                 // Method org/apache/hadoop/hbase/client/Result.rawCells:()[Lorg/apache/hadoop/hbase/Cell;
     198: iconst_0
     199: aaload
     200: invokeinterface #56,  1           // InterfaceMethod org/apache/hadoop/hbase/Cell.getTimestamp:()J
     205: invokestatic  #54                 // Method org/junit/Assert.assertEquals:(JJ)V
     208: ldc2_w        #32                 // long 1000002l
     211: aload_3
     212: invokevirtual #55                 // Method org/apache/hadoop/hbase/client/Result.rawCells:()[Lorg/apache/hadoop/hbase/Cell;
     215: iconst_1
     216: aaload
     217: invokeinterface #56,  1           // InterfaceMethod org/apache/hadoop/hbase/Cell.getTimestamp:()J
     222: invokestatic  #54                 // Method org/junit/Assert.assertEquals:(JJ)V
     225: getstatic     #5                  // Field TEST_UTIL:Lorg/apache/hadoop/hbase/HBaseTestingUtility;
     228: invokevirtual #46                 // Method org/apache/hadoop/hbase/HBaseTestingUtility.getAdmin:()Lorg/apache/hadoop/hbase/client/Admin;
     231: aload_1
     232: invokeinterface #47,  1           // InterfaceMethod org/apache/hadoop/hbase/client/Table.getName:()Lorg/apache/hadoop/hbase/TableName;
     237: invokeinterface #48,  2           // InterfaceMethod org/apache/hadoop/hbase/client/Admin.flush:(Lorg/apache/hadoop/hbase/TableName;)V
     242: aload_1
     243: new           #49                 // class org/apache/hadoop/hbase/client/Get
     246: dup
     247: getstatic     #24                 // Field ROW:[B
     250: invokespecial #50                 // Method org/apache/hadoop/hbase/client/Get."<init>":([B)V
     253: iconst_3
     254: invokevirtual #51                 // Method org/apache/hadoop/hbase/client/Get.readVersions:(I)Lorg/apache/hadoop/hbase/client/Get;
     257: invokeinterface #52,  2           // InterfaceMethod org/apache/hadoop/hbase/client/Table.get:(Lorg/apache/hadoop/hbase/client/Get;)Lorg/apache/hadoop/hbase/client/Result;
     262: astore_3
     263: ldc2_w        #61                 // long 2l
     266: aload_3
     267: invokevirtual #53                 // Method org/apache/hadoop/hbase/client/Result.size:()I
     270: i2l
     271: invokestatic  #54                 // Method org/junit/Assert.assertEquals:(JJ)V
     274: ldc2_w        #36                 // long 1000004l
     277: aload_3
     278: invokevirtual #55                 // Method org/apache/hadoop/hbase/client/Result.rawCells:()[Lorg/apache/hadoop/hbase/Cell;
     281: iconst_0
     282: aaload
     283: invokeinterface #56,  1           // InterfaceMethod org/apache/hadoop/hbase/Cell.getTimestamp:()J
     288: invokestatic  #54                 // Method org/junit/Assert.assertEquals:(JJ)V
     291: ldc2_w        #32                 // long 1000002l
     294: aload_3
     295: invokevirtual #55                 // Method org/apache/hadoop/hbase/client/Result.rawCells:()[Lorg/apache/hadoop/hbase/Cell;
     298: iconst_1
     299: aaload
     300: invokeinterface #56,  1           // InterfaceMethod org/apache/hadoop/hbase/Cell.getTimestamp:()J
     305: invokestatic  #54                 // Method org/junit/Assert.assertEquals:(JJ)V
     308: aload_1
     309: ifnull        387
     312: aload_2
     313: ifnull        334
     316: aload_1
     317: invokeinterface #57,  1           // InterfaceMethod org/apache/hadoop/hbase/client/Table.close:()V
     322: goto          387
     325: astore_3
     326: aload_2
     327: aload_3
     328: invokevirtual #59                 // Method java/lang/Throwable.addSuppressed:(Ljava/lang/Throwable;)V
     331: goto          387
     334: aload_1
     335: invokeinterface #57,  1           // InterfaceMethod org/apache/hadoop/hbase/client/Table.close:()V
     340: goto          387
     343: astore_3
     344: aload_3
     345: astore_2
     346: aload_3
     347: athrow
     348: astore        4
     350: aload_1
     351: ifnull        384
     354: aload_2
     355: ifnull        378
     358: aload_1
     359: invokeinterface #57,  1           // InterfaceMethod org/apache/hadoop/hbase/client/Table.close:()V
     364: goto          384
     367: astore        5
     369: aload_2
     370: aload         5
     372: invokevirtual #59                 // Method java/lang/Throwable.addSuppressed:(Ljava/lang/Throwable;)V
     375: goto          384
     378: aload_1
     379: invokeinterface #57,  1           // InterfaceMethod org/apache/hadoop/hbase/client/Table.close:()V
     384: aload         4
     386: athrow
     387: return
    Exception table:
       from    to  target type
         316   322   325   Class java/lang/Throwable
           7   308   343   Class java/lang/Throwable
           7   308   348   any
         358   364   367   Class java/lang/Throwable
         343   350   348   any

  public void testPutMasked2() throws java.io.IOException;
    Code:
       0: aload_0
       1: invokespecial #22                 // Method createTable:()Lorg/apache/hadoop/hbase/client/Table;
       4: astore_1
       5: aconst_null
       6: astore_2
       7: aload_1
       8: new           #23                 // class org/apache/hadoop/hbase/client/Put
      11: dup
      12: getstatic     #24                 // Field ROW:[B
      15: invokespecial #25                 // Method org/apache/hadoop/hbase/client/Put."<init>":([B)V
      18: getstatic     #13                 // Field FAMILY:[B
      21: getstatic     #26                 // Field col1:[B
      24: ldc2_w        #27                 // long 1000001l
      27: getstatic     #29                 // Field value:[B
      30: invokevirtual #30                 // Method org/apache/hadoop/hbase/client/Put.addColumn:([B[BJ[B)Lorg/apache/hadoop/hbase/client/Put;
      33: invokeinterface #31,  2           // InterfaceMethod org/apache/hadoop/hbase/client/Table.put:(Lorg/apache/hadoop/hbase/client/Put;)V
      38: aload_1
      39: new           #23                 // class org/apache/hadoop/hbase/client/Put
      42: dup
      43: getstatic     #24                 // Field ROW:[B
      46: invokespecial #25                 // Method org/apache/hadoop/hbase/client/Put."<init>":([B)V
      49: getstatic     #13                 // Field FAMILY:[B
      52: getstatic     #26                 // Field col1:[B
      55: ldc2_w        #32                 // long 1000002l
      58: getstatic     #29                 // Field value:[B
      61: invokevirtual #30                 // Method org/apache/hadoop/hbase/client/Put.addColumn:([B[BJ[B)Lorg/apache/hadoop/hbase/client/Put;
      64: invokeinterface #31,  2           // InterfaceMethod org/apache/hadoop/hbase/client/Table.put:(Lorg/apache/hadoop/hbase/client/Put;)V
      69: aload_1
      70: new           #38                 // class org/apache/hadoop/hbase/client/Delete
      73: dup
      74: getstatic     #24                 // Field ROW:[B
      77: invokespecial #39                 // Method org/apache/hadoop/hbase/client/Delete."<init>":([B)V
      80: getstatic     #13                 // Field FAMILY:[B
      83: getstatic     #26                 // Field col1:[B
      86: ldc2_w        #34                 // long 1000003l
      89: invokevirtual #60                 // Method org/apache/hadoop/hbase/client/Delete.addColumn:([B[BJ)Lorg/apache/hadoop/hbase/client/Delete;
      92: invokeinterface #43,  2           // InterfaceMethod org/apache/hadoop/hbase/client/Table.delete:(Lorg/apache/hadoop/hbase/client/Delete;)V
      97: aload_1
      98: new           #23                 // class org/apache/hadoop/hbase/client/Put
     101: dup
     102: getstatic     #24                 // Field ROW:[B
     105: invokespecial #25                 // Method org/apache/hadoop/hbase/client/Put."<init>":([B)V
     108: getstatic     #13                 // Field FAMILY:[B
     111: getstatic     #26                 // Field col1:[B
     114: ldc2_w        #34                 // long 1000003l
     117: getstatic     #29                 // Field value:[B
     120: invokevirtual #30                 // Method org/apache/hadoop/hbase/client/Put.addColumn:([B[BJ[B)Lorg/apache/hadoop/hbase/client/Put;
     123: invokeinterface #31,  2           // InterfaceMethod org/apache/hadoop/hbase/client/Table.put:(Lorg/apache/hadoop/hbase/client/Put;)V
     128: aload_1
     129: new           #23                 // class org/apache/hadoop/hbase/client/Put
     132: dup
     133: getstatic     #24                 // Field ROW:[B
     136: invokespecial #25                 // Method org/apache/hadoop/hbase/client/Put."<init>":([B)V
     139: getstatic     #13                 // Field FAMILY:[B
     142: getstatic     #26                 // Field col1:[B
     145: ldc2_w        #36                 // long 1000004l
     148: getstatic     #29                 // Field value:[B
     151: invokevirtual #30                 // Method org/apache/hadoop/hbase/client/Put.addColumn:([B[BJ[B)Lorg/apache/hadoop/hbase/client/Put;
     154: invokeinterface #31,  2           // InterfaceMethod org/apache/hadoop/hbase/client/Table.put:(Lorg/apache/hadoop/hbase/client/Put;)V
     159: aload_1
     160: new           #49                 // class org/apache/hadoop/hbase/client/Get
     163: dup
     164: getstatic     #24                 // Field ROW:[B
     167: invokespecial #50                 // Method org/apache/hadoop/hbase/client/Get."<init>":([B)V
     170: iconst_3
     171: invokevirtual #51                 // Method org/apache/hadoop/hbase/client/Get.readVersions:(I)Lorg/apache/hadoop/hbase/client/Get;
     174: invokeinterface #52,  2           // InterfaceMethod org/apache/hadoop/hbase/client/Table.get:(Lorg/apache/hadoop/hbase/client/Get;)Lorg/apache/hadoop/hbase/client/Result;
     179: astore_3
     180: ldc2_w        #63                 // long 3l
     183: aload_3
     184: invokevirtual #53                 // Method org/apache/hadoop/hbase/client/Result.size:()I
     187: i2l
     188: invokestatic  #54                 // Method org/junit/Assert.assertEquals:(JJ)V
     191: ldc2_w        #36                 // long 1000004l
     194: aload_3
     195: invokevirtual #55                 // Method org/apache/hadoop/hbase/client/Result.rawCells:()[Lorg/apache/hadoop/hbase/Cell;
     198: iconst_0
     199: aaload
     200: invokeinterface #56,  1           // InterfaceMethod org/apache/hadoop/hbase/Cell.getTimestamp:()J
     205: invokestatic  #54                 // Method org/junit/Assert.assertEquals:(JJ)V
     208: ldc2_w        #34                 // long 1000003l
     211: aload_3
     212: invokevirtual #55                 // Method org/apache/hadoop/hbase/client/Result.rawCells:()[Lorg/apache/hadoop/hbase/Cell;
     215: iconst_1
     216: aaload
     217: invokeinterface #56,  1           // InterfaceMethod org/apache/hadoop/hbase/Cell.getTimestamp:()J
     222: invokestatic  #54                 // Method org/junit/Assert.assertEquals:(JJ)V
     225: ldc2_w        #32                 // long 1000002l
     228: aload_3
     229: invokevirtual #55                 // Method org/apache/hadoop/hbase/client/Result.rawCells:()[Lorg/apache/hadoop/hbase/Cell;
     232: iconst_2
     233: aaload
     234: invokeinterface #56,  1           // InterfaceMethod org/apache/hadoop/hbase/Cell.getTimestamp:()J
     239: invokestatic  #54                 // Method org/junit/Assert.assertEquals:(JJ)V
     242: getstatic     #5                  // Field TEST_UTIL:Lorg/apache/hadoop/hbase/HBaseTestingUtility;
     245: invokevirtual #46                 // Method org/apache/hadoop/hbase/HBaseTestingUtility.getAdmin:()Lorg/apache/hadoop/hbase/client/Admin;
     248: aload_1
     249: invokeinterface #47,  1           // InterfaceMethod org/apache/hadoop/hbase/client/Table.getName:()Lorg/apache/hadoop/hbase/TableName;
     254: invokeinterface #48,  2           // InterfaceMethod org/apache/hadoop/hbase/client/Admin.flush:(Lorg/apache/hadoop/hbase/TableName;)V
     259: aload_1
     260: new           #49                 // class org/apache/hadoop/hbase/client/Get
     263: dup
     264: getstatic     #24                 // Field ROW:[B
     267: invokespecial #50                 // Method org/apache/hadoop/hbase/client/Get."<init>":([B)V
     270: iconst_3
     271: invokevirtual #51                 // Method org/apache/hadoop/hbase/client/Get.readVersions:(I)Lorg/apache/hadoop/hbase/client/Get;
     274: invokeinterface #52,  2           // InterfaceMethod org/apache/hadoop/hbase/client/Table.get:(Lorg/apache/hadoop/hbase/client/Get;)Lorg/apache/hadoop/hbase/client/Result;
     279: astore_3
     280: ldc2_w        #63                 // long 3l
     283: aload_3
     284: invokevirtual #53                 // Method org/apache/hadoop/hbase/client/Result.size:()I
     287: i2l
     288: invokestatic  #54                 // Method org/junit/Assert.assertEquals:(JJ)V
     291: ldc2_w        #36                 // long 1000004l
     294: aload_3
     295: invokevirtual #55                 // Method org/apache/hadoop/hbase/client/Result.rawCells:()[Lorg/apache/hadoop/hbase/Cell;
     298: iconst_0
     299: aaload
     300: invokeinterface #56,  1           // InterfaceMethod org/apache/hadoop/hbase/Cell.getTimestamp:()J
     305: invokestatic  #54                 // Method org/junit/Assert.assertEquals:(JJ)V
     308: ldc2_w        #34                 // long 1000003l
     311: aload_3
     312: invokevirtual #55                 // Method org/apache/hadoop/hbase/client/Result.rawCells:()[Lorg/apache/hadoop/hbase/Cell;
     315: iconst_1
     316: aaload
     317: invokeinterface #56,  1           // InterfaceMethod org/apache/hadoop/hbase/Cell.getTimestamp:()J
     322: invokestatic  #54                 // Method org/junit/Assert.assertEquals:(JJ)V
     325: ldc2_w        #32                 // long 1000002l
     328: aload_3
     329: invokevirtual #55                 // Method org/apache/hadoop/hbase/client/Result.rawCells:()[Lorg/apache/hadoop/hbase/Cell;
     332: iconst_2
     333: aaload
     334: invokeinterface #56,  1           // InterfaceMethod org/apache/hadoop/hbase/Cell.getTimestamp:()J
     339: invokestatic  #54                 // Method org/junit/Assert.assertEquals:(JJ)V
     342: aload_1
     343: ifnull        421
     346: aload_2
     347: ifnull        368
     350: aload_1
     351: invokeinterface #57,  1           // InterfaceMethod org/apache/hadoop/hbase/client/Table.close:()V
     356: goto          421
     359: astore_3
     360: aload_2
     361: aload_3
     362: invokevirtual #59                 // Method java/lang/Throwable.addSuppressed:(Ljava/lang/Throwable;)V
     365: goto          421
     368: aload_1
     369: invokeinterface #57,  1           // InterfaceMethod org/apache/hadoop/hbase/client/Table.close:()V
     374: goto          421
     377: astore_3
     378: aload_3
     379: astore_2
     380: aload_3
     381: athrow
     382: astore        4
     384: aload_1
     385: ifnull        418
     388: aload_2
     389: ifnull        412
     392: aload_1
     393: invokeinterface #57,  1           // InterfaceMethod org/apache/hadoop/hbase/client/Table.close:()V
     398: goto          418
     401: astore        5
     403: aload_2
     404: aload         5
     406: invokevirtual #59                 // Method java/lang/Throwable.addSuppressed:(Ljava/lang/Throwable;)V
     409: goto          418
     412: aload_1
     413: invokeinterface #57,  1           // InterfaceMethod org/apache/hadoop/hbase/client/Table.close:()V
     418: aload         4
     420: athrow
     421: return
    Exception table:
       from    to  target type
         350   356   359   Class java/lang/Throwable
           7   342   377   Class java/lang/Throwable
           7   342   382   any
         392   398   401   Class java/lang/Throwable
         377   384   382   any

  public void testPutMaskedAndUserMaxVersion() throws java.io.IOException;
    Code:
       0: aload_0
       1: invokespecial #22                 // Method createTable:()Lorg/apache/hadoop/hbase/client/Table;
       4: astore_1
       5: aconst_null
       6: astore_2
       7: aload_1
       8: new           #23                 // class org/apache/hadoop/hbase/client/Put
      11: dup
      12: getstatic     #24                 // Field ROW:[B
      15: invokespecial #25                 // Method org/apache/hadoop/hbase/client/Put."<init>":([B)V
      18: getstatic     #13                 // Field FAMILY:[B
      21: getstatic     #26                 // Field col1:[B
      24: ldc2_w        #27                 // long 1000001l
      27: getstatic     #29                 // Field value:[B
      30: invokevirtual #30                 // Method org/apache/hadoop/hbase/client/Put.addColumn:([B[BJ[B)Lorg/apache/hadoop/hbase/client/Put;
      33: invokeinterface #31,  2           // InterfaceMethod org/apache/hadoop/hbase/client/Table.put:(Lorg/apache/hadoop/hbase/client/Put;)V
      38: aload_1
      39: new           #23                 // class org/apache/hadoop/hbase/client/Put
      42: dup
      43: getstatic     #24                 // Field ROW:[B
      46: invokespecial #25                 // Method org/apache/hadoop/hbase/client/Put."<init>":([B)V
      49: getstatic     #13                 // Field FAMILY:[B
      52: getstatic     #26                 // Field col1:[B
      55: ldc2_w        #32                 // long 1000002l
      58: getstatic     #29                 // Field value:[B
      61: invokevirtual #30                 // Method org/apache/hadoop/hbase/client/Put.addColumn:([B[BJ[B)Lorg/apache/hadoop/hbase/client/Put;
      64: invokeinterface #31,  2           // InterfaceMethod org/apache/hadoop/hbase/client/Table.put:(Lorg/apache/hadoop/hbase/client/Put;)V
      69: aload_1
      70: new           #23                 // class org/apache/hadoop/hbase/client/Put
      73: dup
      74: getstatic     #24                 // Field ROW:[B
      77: invokespecial #25                 // Method org/apache/hadoop/hbase/client/Put."<init>":([B)V
      80: getstatic     #13                 // Field FAMILY:[B
      83: getstatic     #26                 // Field col1:[B
      86: ldc2_w        #34                 // long 1000003l
      89: getstatic     #29                 // Field value:[B
      92: invokevirtual #30                 // Method org/apache/hadoop/hbase/client/Put.addColumn:([B[BJ[B)Lorg/apache/hadoop/hbase/client/Put;
      95: invokeinterface #31,  2           // InterfaceMethod org/apache/hadoop/hbase/client/Table.put:(Lorg/apache/hadoop/hbase/client/Put;)V
     100: aload_1
     101: new           #23                 // class org/apache/hadoop/hbase/client/Put
     104: dup
     105: getstatic     #24                 // Field ROW:[B
     108: invokespecial #25                 // Method org/apache/hadoop/hbase/client/Put."<init>":([B)V
     111: getstatic     #13                 // Field FAMILY:[B
     114: getstatic     #26                 // Field col1:[B
     117: ldc2_w        #36                 // long 1000004l
     120: getstatic     #29                 // Field value:[B
     123: invokevirtual #30                 // Method org/apache/hadoop/hbase/client/Put.addColumn:([B[BJ[B)Lorg/apache/hadoop/hbase/client/Put;
     126: invokeinterface #31,  2           // InterfaceMethod org/apache/hadoop/hbase/client/Table.put:(Lorg/apache/hadoop/hbase/client/Put;)V
     131: aload_1
     132: new           #38                 // class org/apache/hadoop/hbase/client/Delete
     135: dup
     136: getstatic     #24                 // Field ROW:[B
     139: invokespecial #39                 // Method org/apache/hadoop/hbase/client/Delete."<init>":([B)V
     142: getstatic     #13                 // Field FAMILY:[B
     145: getstatic     #26                 // Field col1:[B
     148: ldc2_w        #36                 // long 1000004l
     151: invokevirtual #60                 // Method org/apache/hadoop/hbase/client/Delete.addColumn:([B[BJ)Lorg/apache/hadoop/hbase/client/Delete;
     154: invokeinterface #43,  2           // InterfaceMethod org/apache/hadoop/hbase/client/Table.delete:(Lorg/apache/hadoop/hbase/client/Delete;)V
     159: aload_1
     160: new           #38                 // class org/apache/hadoop/hbase/client/Delete
     163: dup
     164: getstatic     #24                 // Field ROW:[B
     167: invokespecial #39                 // Method org/apache/hadoop/hbase/client/Delete."<init>":([B)V
     170: getstatic     #13                 // Field FAMILY:[B
     173: getstatic     #26                 // Field col1:[B
     176: ldc2_w        #34                 // long 1000003l
     179: invokevirtual #60                 // Method org/apache/hadoop/hbase/client/Delete.addColumn:([B[BJ)Lorg/apache/hadoop/hbase/client/Delete;
     182: invokeinterface #43,  2           // InterfaceMethod org/apache/hadoop/hbase/client/Table.delete:(Lorg/apache/hadoop/hbase/client/Delete;)V
     187: aload_1
     188: new           #49                 // class org/apache/hadoop/hbase/client/Get
     191: dup
     192: getstatic     #24                 // Field ROW:[B
     195: invokespecial #50                 // Method org/apache/hadoop/hbase/client/Get."<init>":([B)V
     198: iconst_1
     199: invokevirtual #51                 // Method org/apache/hadoop/hbase/client/Get.readVersions:(I)Lorg/apache/hadoop/hbase/client/Get;
     202: invokeinterface #52,  2           // InterfaceMethod org/apache/hadoop/hbase/client/Table.get:(Lorg/apache/hadoop/hbase/client/Get;)Lorg/apache/hadoop/hbase/client/Result;
     207: astore_3
     208: lconst_1
     209: aload_3
     210: invokevirtual #53                 // Method org/apache/hadoop/hbase/client/Result.size:()I
     213: i2l
     214: invokestatic  #54                 // Method org/junit/Assert.assertEquals:(JJ)V
     217: ldc2_w        #32                 // long 1000002l
     220: aload_3
     221: invokevirtual #55                 // Method org/apache/hadoop/hbase/client/Result.rawCells:()[Lorg/apache/hadoop/hbase/Cell;
     224: iconst_0
     225: aaload
     226: invokeinterface #56,  1           // InterfaceMethod org/apache/hadoop/hbase/Cell.getTimestamp:()J
     231: invokestatic  #54                 // Method org/junit/Assert.assertEquals:(JJ)V
     234: getstatic     #5                  // Field TEST_UTIL:Lorg/apache/hadoop/hbase/HBaseTestingUtility;
     237: invokevirtual #46                 // Method org/apache/hadoop/hbase/HBaseTestingUtility.getAdmin:()Lorg/apache/hadoop/hbase/client/Admin;
     240: aload_1
     241: invokeinterface #47,  1           // InterfaceMethod org/apache/hadoop/hbase/client/Table.getName:()Lorg/apache/hadoop/hbase/TableName;
     246: invokeinterface #48,  2           // InterfaceMethod org/apache/hadoop/hbase/client/Admin.flush:(Lorg/apache/hadoop/hbase/TableName;)V
     251: aload_1
     252: new           #49                 // class org/apache/hadoop/hbase/client/Get
     255: dup
     256: getstatic     #24                 // Field ROW:[B
     259: invokespecial #50                 // Method org/apache/hadoop/hbase/client/Get."<init>":([B)V
     262: iconst_1
     263: invokevirtual #51                 // Method org/apache/hadoop/hbase/client/Get.readVersions:(I)Lorg/apache/hadoop/hbase/client/Get;
     266: invokeinterface #52,  2           // InterfaceMethod org/apache/hadoop/hbase/client/Table.get:(Lorg/apache/hadoop/hbase/client/Get;)Lorg/apache/hadoop/hbase/client/Result;
     271: astore_3
     272: lconst_1
     273: aload_3
     274: invokevirtual #53                 // Method org/apache/hadoop/hbase/client/Result.size:()I
     277: i2l
     278: invokestatic  #54                 // Method org/junit/Assert.assertEquals:(JJ)V
     281: ldc2_w        #32                 // long 1000002l
     284: aload_3
     285: invokevirtual #55                 // Method org/apache/hadoop/hbase/client/Result.rawCells:()[Lorg/apache/hadoop/hbase/Cell;
     288: iconst_0
     289: aaload
     290: invokeinterface #56,  1           // InterfaceMethod org/apache/hadoop/hbase/Cell.getTimestamp:()J
     295: invokestatic  #54                 // Method org/junit/Assert.assertEquals:(JJ)V
     298: aload_1
     299: ifnull        377
     302: aload_2
     303: ifnull        324
     306: aload_1
     307: invokeinterface #57,  1           // InterfaceMethod org/apache/hadoop/hbase/client/Table.close:()V
     312: goto          377
     315: astore_3
     316: aload_2
     317: aload_3
     318: invokevirtual #59                 // Method java/lang/Throwable.addSuppressed:(Ljava/lang/Throwable;)V
     321: goto          377
     324: aload_1
     325: invokeinterface #57,  1           // InterfaceMethod org/apache/hadoop/hbase/client/Table.close:()V
     330: goto          377
     333: astore_3
     334: aload_3
     335: astore_2
     336: aload_3
     337: athrow
     338: astore        4
     340: aload_1
     341: ifnull        374
     344: aload_2
     345: ifnull        368
     348: aload_1
     349: invokeinterface #57,  1           // InterfaceMethod org/apache/hadoop/hbase/client/Table.close:()V
     354: goto          374
     357: astore        5
     359: aload_2
     360: aload         5
     362: invokevirtual #59                 // Method java/lang/Throwable.addSuppressed:(Ljava/lang/Throwable;)V
     365: goto          374
     368: aload_1
     369: invokeinterface #57,  1           // InterfaceMethod org/apache/hadoop/hbase/client/Table.close:()V
     374: aload         4
     376: athrow
     377: return
    Exception table:
       from    to  target type
         306   312   315   Class java/lang/Throwable
           7   298   333   Class java/lang/Throwable
           7   298   338   any
         348   354   357   Class java/lang/Throwable
         333   340   338   any

  public void testSameTs() throws java.io.IOException;
    Code:
       0: aload_0
       1: invokespecial #22                 // Method createTable:()Lorg/apache/hadoop/hbase/client/Table;
       4: astore_1
       5: aconst_null
       6: astore_2
       7: aload_1
       8: new           #23                 // class org/apache/hadoop/hbase/client/Put
      11: dup
      12: getstatic     #24                 // Field ROW:[B
      15: invokespecial #25                 // Method org/apache/hadoop/hbase/client/Put."<init>":([B)V
      18: getstatic     #13                 // Field FAMILY:[B
      21: getstatic     #26                 // Field col1:[B
      24: ldc2_w        #27                 // long 1000001l
      27: getstatic     #29                 // Field value:[B
      30: invokevirtual #30                 // Method org/apache/hadoop/hbase/client/Put.addColumn:([B[BJ[B)Lorg/apache/hadoop/hbase/client/Put;
      33: invokeinterface #31,  2           // InterfaceMethod org/apache/hadoop/hbase/client/Table.put:(Lorg/apache/hadoop/hbase/client/Put;)V
      38: aload_1
      39: new           #23                 // class org/apache/hadoop/hbase/client/Put
      42: dup
      43: getstatic     #24                 // Field ROW:[B
      46: invokespecial #25                 // Method org/apache/hadoop/hbase/client/Put."<init>":([B)V
      49: getstatic     #13                 // Field FAMILY:[B
      52: getstatic     #26                 // Field col1:[B
      55: ldc2_w        #32                 // long 1000002l
      58: getstatic     #29                 // Field value:[B
      61: invokevirtual #30                 // Method org/apache/hadoop/hbase/client/Put.addColumn:([B[BJ[B)Lorg/apache/hadoop/hbase/client/Put;
      64: invokeinterface #31,  2           // InterfaceMethod org/apache/hadoop/hbase/client/Table.put:(Lorg/apache/hadoop/hbase/client/Put;)V
      69: aload_1
      70: new           #23                 // class org/apache/hadoop/hbase/client/Put
      73: dup
      74: getstatic     #24                 // Field ROW:[B
      77: invokespecial #25                 // Method org/apache/hadoop/hbase/client/Put."<init>":([B)V
      80: getstatic     #13                 // Field FAMILY:[B
      83: getstatic     #26                 // Field col1:[B
      86: ldc2_w        #34                 // long 1000003l
      89: getstatic     #29                 // Field value:[B
      92: invokevirtual #30                 // Method org/apache/hadoop/hbase/client/Put.addColumn:([B[BJ[B)Lorg/apache/hadoop/hbase/client/Put;
      95: invokeinterface #31,  2           // InterfaceMethod org/apache/hadoop/hbase/client/Table.put:(Lorg/apache/hadoop/hbase/client/Put;)V
     100: aload_1
     101: new           #23                 // class org/apache/hadoop/hbase/client/Put
     104: dup
     105: getstatic     #24                 // Field ROW:[B
     108: invokespecial #25                 // Method org/apache/hadoop/hbase/client/Put."<init>":([B)V
     111: getstatic     #13                 // Field FAMILY:[B
     114: getstatic     #26                 // Field col1:[B
     117: ldc2_w        #34                 // long 1000003l
     120: getstatic     #29                 // Field value:[B
     123: invokevirtual #30                 // Method org/apache/hadoop/hbase/client/Put.addColumn:([B[BJ[B)Lorg/apache/hadoop/hbase/client/Put;
     126: invokeinterface #31,  2           // InterfaceMethod org/apache/hadoop/hbase/client/Table.put:(Lorg/apache/hadoop/hbase/client/Put;)V
     131: aload_1
     132: new           #23                 // class org/apache/hadoop/hbase/client/Put
     135: dup
     136: getstatic     #24                 // Field ROW:[B
     139: invokespecial #25                 // Method org/apache/hadoop/hbase/client/Put."<init>":([B)V
     142: getstatic     #13                 // Field FAMILY:[B
     145: getstatic     #26                 // Field col1:[B
     148: ldc2_w        #34                 // long 1000003l
     151: getstatic     #29                 // Field value:[B
     154: invokevirtual #30                 // Method org/apache/hadoop/hbase/client/Put.addColumn:([B[BJ[B)Lorg/apache/hadoop/hbase/client/Put;
     157: invokeinterface #31,  2           // InterfaceMethod org/apache/hadoop/hbase/client/Table.put:(Lorg/apache/hadoop/hbase/client/Put;)V
     162: aload_1
     163: new           #23                 // class org/apache/hadoop/hbase/client/Put
     166: dup
     167: getstatic     #24                 // Field ROW:[B
     170: invokespecial #25                 // Method org/apache/hadoop/hbase/client/Put."<init>":([B)V
     173: getstatic     #13                 // Field FAMILY:[B
     176: getstatic     #26                 // Field col1:[B
     179: ldc2_w        #36                 // long 1000004l
     182: getstatic     #29                 // Field value:[B
     185: invokevirtual #30                 // Method org/apache/hadoop/hbase/client/Put.addColumn:([B[BJ[B)Lorg/apache/hadoop/hbase/client/Put;
     188: invokeinterface #31,  2           // InterfaceMethod org/apache/hadoop/hbase/client/Table.put:(Lorg/apache/hadoop/hbase/client/Put;)V
     193: aload_1
     194: new           #49                 // class org/apache/hadoop/hbase/client/Get
     197: dup
     198: getstatic     #24                 // Field ROW:[B
     201: invokespecial #50                 // Method org/apache/hadoop/hbase/client/Get."<init>":([B)V
     204: iconst_3
     205: invokevirtual #51                 // Method org/apache/hadoop/hbase/client/Get.readVersions:(I)Lorg/apache/hadoop/hbase/client/Get;
     208: invokeinterface #52,  2           // InterfaceMethod org/apache/hadoop/hbase/client/Table.get:(Lorg/apache/hadoop/hbase/client/Get;)Lorg/apache/hadoop/hbase/client/Result;
     213: astore_3
     214: ldc2_w        #63                 // long 3l
     217: aload_3
     218: invokevirtual #53                 // Method org/apache/hadoop/hbase/client/Result.size:()I
     221: i2l
     222: invokestatic  #54                 // Method org/junit/Assert.assertEquals:(JJ)V
     225: ldc2_w        #36                 // long 1000004l
     228: aload_3
     229: invokevirtual #55                 // Method org/apache/hadoop/hbase/client/Result.rawCells:()[Lorg/apache/hadoop/hbase/Cell;
     232: iconst_0
     233: aaload
     234: invokeinterface #56,  1           // InterfaceMethod org/apache/hadoop/hbase/Cell.getTimestamp:()J
     239: invokestatic  #54                 // Method org/junit/Assert.assertEquals:(JJ)V
     242: ldc2_w        #34                 // long 1000003l
     245: aload_3
     246: invokevirtual #55                 // Method org/apache/hadoop/hbase/client/Result.rawCells:()[Lorg/apache/hadoop/hbase/Cell;
     249: iconst_1
     250: aaload
     251: invokeinterface #56,  1           // InterfaceMethod org/apache/hadoop/hbase/Cell.getTimestamp:()J
     256: invokestatic  #54                 // Method org/junit/Assert.assertEquals:(JJ)V
     259: ldc2_w        #32                 // long 1000002l
     262: aload_3
     263: invokevirtual #55                 // Method org/apache/hadoop/hbase/client/Result.rawCells:()[Lorg/apache/hadoop/hbase/Cell;
     266: iconst_2
     267: aaload
     268: invokeinterface #56,  1           // InterfaceMethod org/apache/hadoop/hbase/Cell.getTimestamp:()J
     273: invokestatic  #54                 // Method org/junit/Assert.assertEquals:(JJ)V
     276: getstatic     #5                  // Field TEST_UTIL:Lorg/apache/hadoop/hbase/HBaseTestingUtility;
     279: invokevirtual #46                 // Method org/apache/hadoop/hbase/HBaseTestingUtility.getAdmin:()Lorg/apache/hadoop/hbase/client/Admin;
     282: aload_1
     283: invokeinterface #47,  1           // InterfaceMethod org/apache/hadoop/hbase/client/Table.getName:()Lorg/apache/hadoop/hbase/TableName;
     288: invokeinterface #48,  2           // InterfaceMethod org/apache/hadoop/hbase/client/Admin.flush:(Lorg/apache/hadoop/hbase/TableName;)V
     293: aload_1
     294: new           #49                 // class org/apache/hadoop/hbase/client/Get
     297: dup
     298: getstatic     #24                 // Field ROW:[B
     301: invokespecial #50                 // Method org/apache/hadoop/hbase/client/Get."<init>":([B)V
     304: iconst_3
     305: invokevirtual #51                 // Method org/apache/hadoop/hbase/client/Get.readVersions:(I)Lorg/apache/hadoop/hbase/client/Get;
     308: invokeinterface #52,  2           // InterfaceMethod org/apache/hadoop/hbase/client/Table.get:(Lorg/apache/hadoop/hbase/client/Get;)Lorg/apache/hadoop/hbase/client/Result;
     313: astore_3
     314: ldc2_w        #63                 // long 3l
     317: aload_3
     318: invokevirtual #53                 // Method org/apache/hadoop/hbase/client/Result.size:()I
     321: i2l
     322: invokestatic  #54                 // Method org/junit/Assert.assertEquals:(JJ)V
     325: ldc2_w        #36                 // long 1000004l
     328: aload_3
     329: invokevirtual #55                 // Method org/apache/hadoop/hbase/client/Result.rawCells:()[Lorg/apache/hadoop/hbase/Cell;
     332: iconst_0
     333: aaload
     334: invokeinterface #56,  1           // InterfaceMethod org/apache/hadoop/hbase/Cell.getTimestamp:()J
     339: invokestatic  #54                 // Method org/junit/Assert.assertEquals:(JJ)V
     342: ldc2_w        #34                 // long 1000003l
     345: aload_3
     346: invokevirtual #55                 // Method org/apache/hadoop/hbase/client/Result.rawCells:()[Lorg/apache/hadoop/hbase/Cell;
     349: iconst_1
     350: aaload
     351: invokeinterface #56,  1           // InterfaceMethod org/apache/hadoop/hbase/Cell.getTimestamp:()J
     356: invokestatic  #54                 // Method org/junit/Assert.assertEquals:(JJ)V
     359: ldc2_w        #32                 // long 1000002l
     362: aload_3
     363: invokevirtual #55                 // Method org/apache/hadoop/hbase/client/Result.rawCells:()[Lorg/apache/hadoop/hbase/Cell;
     366: iconst_2
     367: aaload
     368: invokeinterface #56,  1           // InterfaceMethod org/apache/hadoop/hbase/Cell.getTimestamp:()J
     373: invokestatic  #54                 // Method org/junit/Assert.assertEquals:(JJ)V
     376: aload_1
     377: ifnull        455
     380: aload_2
     381: ifnull        402
     384: aload_1
     385: invokeinterface #57,  1           // InterfaceMethod org/apache/hadoop/hbase/client/Table.close:()V
     390: goto          455
     393: astore_3
     394: aload_2
     395: aload_3
     396: invokevirtual #59                 // Method java/lang/Throwable.addSuppressed:(Ljava/lang/Throwable;)V
     399: goto          455
     402: aload_1
     403: invokeinterface #57,  1           // InterfaceMethod org/apache/hadoop/hbase/client/Table.close:()V
     408: goto          455
     411: astore_3
     412: aload_3
     413: astore_2
     414: aload_3
     415: athrow
     416: astore        4
     418: aload_1
     419: ifnull        452
     422: aload_2
     423: ifnull        446
     426: aload_1
     427: invokeinterface #57,  1           // InterfaceMethod org/apache/hadoop/hbase/client/Table.close:()V
     432: goto          452
     435: astore        5
     437: aload_2
     438: aload         5
     440: invokevirtual #59                 // Method java/lang/Throwable.addSuppressed:(Ljava/lang/Throwable;)V
     443: goto          452
     446: aload_1
     447: invokeinterface #57,  1           // InterfaceMethod org/apache/hadoop/hbase/client/Table.close:()V
     452: aload         4
     454: athrow
     455: return
    Exception table:
       from    to  target type
         384   390   393   Class java/lang/Throwable
           7   376   411   Class java/lang/Throwable
           7   376   416   any
         426   432   435   Class java/lang/Throwable
         411   418   416   any

  public void testSameTsAndDelete() throws java.io.IOException;
    Code:
       0: aload_0
       1: invokespecial #22                 // Method createTable:()Lorg/apache/hadoop/hbase/client/Table;
       4: astore_1
       5: aconst_null
       6: astore_2
       7: aload_1
       8: new           #23                 // class org/apache/hadoop/hbase/client/Put
      11: dup
      12: getstatic     #24                 // Field ROW:[B
      15: invokespecial #25                 // Method org/apache/hadoop/hbase/client/Put."<init>":([B)V
      18: getstatic     #13                 // Field FAMILY:[B
      21: getstatic     #26                 // Field col1:[B
      24: ldc2_w        #27                 // long 1000001l
      27: getstatic     #29                 // Field value:[B
      30: invokevirtual #30                 // Method org/apache/hadoop/hbase/client/Put.addColumn:([B[BJ[B)Lorg/apache/hadoop/hbase/client/Put;
      33: invokeinterface #31,  2           // InterfaceMethod org/apache/hadoop/hbase/client/Table.put:(Lorg/apache/hadoop/hbase/client/Put;)V
      38: aload_1
      39: new           #23                 // class org/apache/hadoop/hbase/client/Put
      42: dup
      43: getstatic     #24                 // Field ROW:[B
      46: invokespecial #25                 // Method org/apache/hadoop/hbase/client/Put."<init>":([B)V
      49: getstatic     #13                 // Field FAMILY:[B
      52: getstatic     #26                 // Field col1:[B
      55: ldc2_w        #32                 // long 1000002l
      58: getstatic     #29                 // Field value:[B
      61: invokevirtual #30                 // Method org/apache/hadoop/hbase/client/Put.addColumn:([B[BJ[B)Lorg/apache/hadoop/hbase/client/Put;
      64: invokeinterface #31,  2           // InterfaceMethod org/apache/hadoop/hbase/client/Table.put:(Lorg/apache/hadoop/hbase/client/Put;)V
      69: aload_1
      70: new           #23                 // class org/apache/hadoop/hbase/client/Put
      73: dup
      74: getstatic     #24                 // Field ROW:[B
      77: invokespecial #25                 // Method org/apache/hadoop/hbase/client/Put."<init>":([B)V
      80: getstatic     #13                 // Field FAMILY:[B
      83: getstatic     #26                 // Field col1:[B
      86: ldc2_w        #34                 // long 1000003l
      89: getstatic     #29                 // Field value:[B
      92: invokevirtual #30                 // Method org/apache/hadoop/hbase/client/Put.addColumn:([B[BJ[B)Lorg/apache/hadoop/hbase/client/Put;
      95: invokeinterface #31,  2           // InterfaceMethod org/apache/hadoop/hbase/client/Table.put:(Lorg/apache/hadoop/hbase/client/Put;)V
     100: aload_1
     101: new           #23                 // class org/apache/hadoop/hbase/client/Put
     104: dup
     105: getstatic     #24                 // Field ROW:[B
     108: invokespecial #25                 // Method org/apache/hadoop/hbase/client/Put."<init>":([B)V
     111: getstatic     #13                 // Field FAMILY:[B
     114: getstatic     #26                 // Field col1:[B
     117: ldc2_w        #34                 // long 1000003l
     120: getstatic     #29                 // Field value:[B
     123: invokevirtual #30                 // Method org/apache/hadoop/hbase/client/Put.addColumn:([B[BJ[B)Lorg/apache/hadoop/hbase/client/Put;
     126: invokeinterface #31,  2           // InterfaceMethod org/apache/hadoop/hbase/client/Table.put:(Lorg/apache/hadoop/hbase/client/Put;)V
     131: aload_1
     132: new           #23                 // class org/apache/hadoop/hbase/client/Put
     135: dup
     136: getstatic     #24                 // Field ROW:[B
     139: invokespecial #25                 // Method org/apache/hadoop/hbase/client/Put."<init>":([B)V
     142: getstatic     #13                 // Field FAMILY:[B
     145: getstatic     #26                 // Field col1:[B
     148: ldc2_w        #34                 // long 1000003l
     151: getstatic     #29                 // Field value:[B
     154: invokevirtual #30                 // Method org/apache/hadoop/hbase/client/Put.addColumn:([B[BJ[B)Lorg/apache/hadoop/hbase/client/Put;
     157: invokeinterface #31,  2           // InterfaceMethod org/apache/hadoop/hbase/client/Table.put:(Lorg/apache/hadoop/hbase/client/Put;)V
     162: aload_1
     163: new           #23                 // class org/apache/hadoop/hbase/client/Put
     166: dup
     167: getstatic     #24                 // Field ROW:[B
     170: invokespecial #25                 // Method org/apache/hadoop/hbase/client/Put."<init>":([B)V
     173: getstatic     #13                 // Field FAMILY:[B
     176: getstatic     #26                 // Field col1:[B
     179: ldc2_w        #34                 // long 1000003l
     182: getstatic     #29                 // Field value:[B
     185: invokevirtual #30                 // Method org/apache/hadoop/hbase/client/Put.addColumn:([B[BJ[B)Lorg/apache/hadoop/hbase/client/Put;
     188: invokeinterface #31,  2           // InterfaceMethod org/apache/hadoop/hbase/client/Table.put:(Lorg/apache/hadoop/hbase/client/Put;)V
     193: aload_1
     194: new           #38                 // class org/apache/hadoop/hbase/client/Delete
     197: dup
     198: getstatic     #24                 // Field ROW:[B
     201: invokespecial #39                 // Method org/apache/hadoop/hbase/client/Delete."<init>":([B)V
     204: getstatic     #13                 // Field FAMILY:[B
     207: getstatic     #26                 // Field col1:[B
     210: ldc2_w        #34                 // long 1000003l
     213: invokevirtual #60                 // Method org/apache/hadoop/hbase/client/Delete.addColumn:([B[BJ)Lorg/apache/hadoop/hbase/client/Delete;
     216: invokeinterface #43,  2           // InterfaceMethod org/apache/hadoop/hbase/client/Table.delete:(Lorg/apache/hadoop/hbase/client/Delete;)V
     221: aload_1
     222: new           #23                 // class org/apache/hadoop/hbase/client/Put
     225: dup
     226: getstatic     #24                 // Field ROW:[B
     229: invokespecial #25                 // Method org/apache/hadoop/hbase/client/Put."<init>":([B)V
     232: getstatic     #13                 // Field FAMILY:[B
     235: getstatic     #26                 // Field col1:[B
     238: ldc2_w        #36                 // long 1000004l
     241: getstatic     #29                 // Field value:[B
     244: invokevirtual #30                 // Method org/apache/hadoop/hbase/client/Put.addColumn:([B[BJ[B)Lorg/apache/hadoop/hbase/client/Put;
     247: invokeinterface #31,  2           // InterfaceMethod org/apache/hadoop/hbase/client/Table.put:(Lorg/apache/hadoop/hbase/client/Put;)V
     252: aload_1
     253: new           #49                 // class org/apache/hadoop/hbase/client/Get
     256: dup
     257: getstatic     #24                 // Field ROW:[B
     260: invokespecial #50                 // Method org/apache/hadoop/hbase/client/Get."<init>":([B)V
     263: iconst_3
     264: invokevirtual #51                 // Method org/apache/hadoop/hbase/client/Get.readVersions:(I)Lorg/apache/hadoop/hbase/client/Get;
     267: invokeinterface #52,  2           // InterfaceMethod org/apache/hadoop/hbase/client/Table.get:(Lorg/apache/hadoop/hbase/client/Get;)Lorg/apache/hadoop/hbase/client/Result;
     272: astore_3
     273: ldc2_w        #63                 // long 3l
     276: aload_3
     277: invokevirtual #53                 // Method org/apache/hadoop/hbase/client/Result.size:()I
     280: i2l
     281: invokestatic  #54                 // Method org/junit/Assert.assertEquals:(JJ)V
     284: ldc2_w        #36                 // long 1000004l
     287: aload_3
     288: invokevirtual #55                 // Method org/apache/hadoop/hbase/client/Result.rawCells:()[Lorg/apache/hadoop/hbase/Cell;
     291: iconst_0
     292: aaload
     293: invokeinterface #56,  1           // InterfaceMethod org/apache/hadoop/hbase/Cell.getTimestamp:()J
     298: invokestatic  #54                 // Method org/junit/Assert.assertEquals:(JJ)V
     301: ldc2_w        #32                 // long 1000002l
     304: aload_3
     305: invokevirtual #55                 // Method org/apache/hadoop/hbase/client/Result.rawCells:()[Lorg/apache/hadoop/hbase/Cell;
     308: iconst_1
     309: aaload
     310: invokeinterface #56,  1           // InterfaceMethod org/apache/hadoop/hbase/Cell.getTimestamp:()J
     315: invokestatic  #54                 // Method org/junit/Assert.assertEquals:(JJ)V
     318: ldc2_w        #27                 // long 1000001l
     321: aload_3
     322: invokevirtual #55                 // Method org/apache/hadoop/hbase/client/Result.rawCells:()[Lorg/apache/hadoop/hbase/Cell;
     325: iconst_2
     326: aaload
     327: invokeinterface #56,  1           // InterfaceMethod org/apache/hadoop/hbase/Cell.getTimestamp:()J
     332: invokestatic  #54                 // Method org/junit/Assert.assertEquals:(JJ)V
     335: getstatic     #5                  // Field TEST_UTIL:Lorg/apache/hadoop/hbase/HBaseTestingUtility;
     338: invokevirtual #46                 // Method org/apache/hadoop/hbase/HBaseTestingUtility.getAdmin:()Lorg/apache/hadoop/hbase/client/Admin;
     341: aload_1
     342: invokeinterface #47,  1           // InterfaceMethod org/apache/hadoop/hbase/client/Table.getName:()Lorg/apache/hadoop/hbase/TableName;
     347: invokeinterface #48,  2           // InterfaceMethod org/apache/hadoop/hbase/client/Admin.flush:(Lorg/apache/hadoop/hbase/TableName;)V
     352: aload_1
     353: new           #49                 // class org/apache/hadoop/hbase/client/Get
     356: dup
     357: getstatic     #24                 // Field ROW:[B
     360: invokespecial #50                 // Method org/apache/hadoop/hbase/client/Get."<init>":([B)V
     363: iconst_3
     364: invokevirtual #51                 // Method org/apache/hadoop/hbase/client/Get.readVersions:(I)Lorg/apache/hadoop/hbase/client/Get;
     367: invokeinterface #52,  2           // InterfaceMethod org/apache/hadoop/hbase/client/Table.get:(Lorg/apache/hadoop/hbase/client/Get;)Lorg/apache/hadoop/hbase/client/Result;
     372: astore_3
     373: ldc2_w        #63                 // long 3l
     376: aload_3
     377: invokevirtual #53                 // Method org/apache/hadoop/hbase/client/Result.size:()I
     380: i2l
     381: invokestatic  #54                 // Method org/junit/Assert.assertEquals:(JJ)V
     384: ldc2_w        #36                 // long 1000004l
     387: aload_3
     388: invokevirtual #55                 // Method org/apache/hadoop/hbase/client/Result.rawCells:()[Lorg/apache/hadoop/hbase/Cell;
     391: iconst_0
     392: aaload
     393: invokeinterface #56,  1           // InterfaceMethod org/apache/hadoop/hbase/Cell.getTimestamp:()J
     398: invokestatic  #54                 // Method org/junit/Assert.assertEquals:(JJ)V
     401: ldc2_w        #32                 // long 1000002l
     404: aload_3
     405: invokevirtual #55                 // Method org/apache/hadoop/hbase/client/Result.rawCells:()[Lorg/apache/hadoop/hbase/Cell;
     408: iconst_1
     409: aaload
     410: invokeinterface #56,  1           // InterfaceMethod org/apache/hadoop/hbase/Cell.getTimestamp:()J
     415: invokestatic  #54                 // Method org/junit/Assert.assertEquals:(JJ)V
     418: ldc2_w        #27                 // long 1000001l
     421: aload_3
     422: invokevirtual #55                 // Method org/apache/hadoop/hbase/client/Result.rawCells:()[Lorg/apache/hadoop/hbase/Cell;
     425: iconst_2
     426: aaload
     427: invokeinterface #56,  1           // InterfaceMethod org/apache/hadoop/hbase/Cell.getTimestamp:()J
     432: invokestatic  #54                 // Method org/junit/Assert.assertEquals:(JJ)V
     435: aload_1
     436: ifnull        514
     439: aload_2
     440: ifnull        461
     443: aload_1
     444: invokeinterface #57,  1           // InterfaceMethod org/apache/hadoop/hbase/client/Table.close:()V
     449: goto          514
     452: astore_3
     453: aload_2
     454: aload_3
     455: invokevirtual #59                 // Method java/lang/Throwable.addSuppressed:(Ljava/lang/Throwable;)V
     458: goto          514
     461: aload_1
     462: invokeinterface #57,  1           // InterfaceMethod org/apache/hadoop/hbase/client/Table.close:()V
     467: goto          514
     470: astore_3
     471: aload_3
     472: astore_2
     473: aload_3
     474: athrow
     475: astore        4
     477: aload_1
     478: ifnull        511
     481: aload_2
     482: ifnull        505
     485: aload_1
     486: invokeinterface #57,  1           // InterfaceMethod org/apache/hadoop/hbase/client/Table.close:()V
     491: goto          511
     494: astore        5
     496: aload_2
     497: aload         5
     499: invokevirtual #59                 // Method java/lang/Throwable.addSuppressed:(Ljava/lang/Throwable;)V
     502: goto          511
     505: aload_1
     506: invokeinterface #57,  1           // InterfaceMethod org/apache/hadoop/hbase/client/Table.close:()V
     511: aload         4
     513: athrow
     514: return
    Exception table:
       from    to  target type
         443   449   452   Class java/lang/Throwable
           7   435   470   Class java/lang/Throwable
           7   435   475   any
         485   491   494   Class java/lang/Throwable
         470   477   475   any

  public void testDeleteFamily() throws java.io.IOException;
    Code:
       0: aload_0
       1: invokespecial #22                 // Method createTable:()Lorg/apache/hadoop/hbase/client/Table;
       4: astore_1
       5: aconst_null
       6: astore_2
       7: aload_1
       8: new           #23                 // class org/apache/hadoop/hbase/client/Put
      11: dup
      12: getstatic     #24                 // Field ROW:[B
      15: invokespecial #25                 // Method org/apache/hadoop/hbase/client/Put."<init>":([B)V
      18: getstatic     #13                 // Field FAMILY:[B
      21: getstatic     #26                 // Field col1:[B
      24: ldc2_w        #27                 // long 1000001l
      27: getstatic     #29                 // Field value:[B
      30: invokevirtual #30                 // Method org/apache/hadoop/hbase/client/Put.addColumn:([B[BJ[B)Lorg/apache/hadoop/hbase/client/Put;
      33: invokeinterface #31,  2           // InterfaceMethod org/apache/hadoop/hbase/client/Table.put:(Lorg/apache/hadoop/hbase/client/Put;)V
      38: aload_1
      39: new           #23                 // class org/apache/hadoop/hbase/client/Put
      42: dup
      43: getstatic     #24                 // Field ROW:[B
      46: invokespecial #25                 // Method org/apache/hadoop/hbase/client/Put."<init>":([B)V
      49: getstatic     #13                 // Field FAMILY:[B
      52: getstatic     #26                 // Field col1:[B
      55: ldc2_w        #32                 // long 1000002l
      58: getstatic     #29                 // Field value:[B
      61: invokevirtual #30                 // Method org/apache/hadoop/hbase/client/Put.addColumn:([B[BJ[B)Lorg/apache/hadoop/hbase/client/Put;
      64: invokeinterface #31,  2           // InterfaceMethod org/apache/hadoop/hbase/client/Table.put:(Lorg/apache/hadoop/hbase/client/Put;)V
      69: aload_1
      70: new           #23                 // class org/apache/hadoop/hbase/client/Put
      73: dup
      74: getstatic     #24                 // Field ROW:[B
      77: invokespecial #25                 // Method org/apache/hadoop/hbase/client/Put."<init>":([B)V
      80: getstatic     #13                 // Field FAMILY:[B
      83: getstatic     #65                 // Field col2:[B
      86: ldc2_w        #32                 // long 1000002l
      89: getstatic     #29                 // Field value:[B
      92: invokevirtual #30                 // Method org/apache/hadoop/hbase/client/Put.addColumn:([B[BJ[B)Lorg/apache/hadoop/hbase/client/Put;
      95: invokeinterface #31,  2           // InterfaceMethod org/apache/hadoop/hbase/client/Table.put:(Lorg/apache/hadoop/hbase/client/Put;)V
     100: aload_1
     101: new           #23                 // class org/apache/hadoop/hbase/client/Put
     104: dup
     105: getstatic     #24                 // Field ROW:[B
     108: invokespecial #25                 // Method org/apache/hadoop/hbase/client/Put."<init>":([B)V
     111: getstatic     #13                 // Field FAMILY:[B
     114: getstatic     #66                 // Field col3:[B
     117: ldc2_w        #27                 // long 1000001l
     120: getstatic     #29                 // Field value:[B
     123: invokevirtual #30                 // Method org/apache/hadoop/hbase/client/Put.addColumn:([B[BJ[B)Lorg/apache/hadoop/hbase/client/Put;
     126: invokeinterface #31,  2           // InterfaceMethod org/apache/hadoop/hbase/client/Table.put:(Lorg/apache/hadoop/hbase/client/Put;)V
     131: aload_1
     132: new           #38                 // class org/apache/hadoop/hbase/client/Delete
     135: dup
     136: getstatic     #24                 // Field ROW:[B
     139: invokespecial #39                 // Method org/apache/hadoop/hbase/client/Delete."<init>":([B)V
     142: getstatic     #13                 // Field FAMILY:[B
     145: ldc2_w        #40                 // long 2000000l
     148: invokevirtual #67                 // Method org/apache/hadoop/hbase/client/Delete.addFamily:([BJ)Lorg/apache/hadoop/hbase/client/Delete;
     151: invokeinterface #43,  2           // InterfaceMethod org/apache/hadoop/hbase/client/Table.delete:(Lorg/apache/hadoop/hbase/client/Delete;)V
     156: aload_1
     157: new           #23                 // class org/apache/hadoop/hbase/client/Put
     160: dup
     161: getstatic     #24                 // Field ROW:[B
     164: invokespecial #25                 // Method org/apache/hadoop/hbase/client/Put."<init>":([B)V
     167: getstatic     #13                 // Field FAMILY:[B
     170: getstatic     #66                 // Field col3:[B
     173: ldc2_w        #68                 // long 1500002l
     176: getstatic     #29                 // Field value:[B
     179: invokevirtual #30                 // Method org/apache/hadoop/hbase/client/Put.addColumn:([B[BJ[B)Lorg/apache/hadoop/hbase/client/Put;
     182: invokeinterface #31,  2           // InterfaceMethod org/apache/hadoop/hbase/client/Table.put:(Lorg/apache/hadoop/hbase/client/Put;)V
     187: aload_1
     188: new           #23                 // class org/apache/hadoop/hbase/client/Put
     191: dup
     192: getstatic     #24                 // Field ROW:[B
     195: invokespecial #25                 // Method org/apache/hadoop/hbase/client/Put."<init>":([B)V
     198: getstatic     #13                 // Field FAMILY:[B
     201: getstatic     #65                 // Field col2:[B
     204: ldc2_w        #70                 // long 1500001l
     207: getstatic     #29                 // Field value:[B
     210: invokevirtual #30                 // Method org/apache/hadoop/hbase/client/Put.addColumn:([B[BJ[B)Lorg/apache/hadoop/hbase/client/Put;
     213: invokeinterface #31,  2           // InterfaceMethod org/apache/hadoop/hbase/client/Table.put:(Lorg/apache/hadoop/hbase/client/Put;)V
     218: aload_1
     219: new           #23                 // class org/apache/hadoop/hbase/client/Put
     222: dup
     223: getstatic     #24                 // Field ROW:[B
     226: invokespecial #25                 // Method org/apache/hadoop/hbase/client/Put."<init>":([B)V
     229: getstatic     #13                 // Field FAMILY:[B
     232: getstatic     #26                 // Field col1:[B
     235: ldc2_w        #70                 // long 1500001l
     238: getstatic     #29                 // Field value:[B
     241: invokevirtual #30                 // Method org/apache/hadoop/hbase/client/Put.addColumn:([B[BJ[B)Lorg/apache/hadoop/hbase/client/Put;
     244: invokeinterface #31,  2           // InterfaceMethod org/apache/hadoop/hbase/client/Table.put:(Lorg/apache/hadoop/hbase/client/Put;)V
     249: aload_1
     250: new           #23                 // class org/apache/hadoop/hbase/client/Put
     253: dup
     254: getstatic     #24                 // Field ROW:[B
     257: invokespecial #25                 // Method org/apache/hadoop/hbase/client/Put."<init>":([B)V
     260: getstatic     #13                 // Field FAMILY:[B
     263: getstatic     #26                 // Field col1:[B
     266: ldc2_w        #68                 // long 1500002l
     269: getstatic     #29                 // Field value:[B
     272: invokevirtual #30                 // Method org/apache/hadoop/hbase/client/Put.addColumn:([B[BJ[B)Lorg/apache/hadoop/hbase/client/Put;
     275: invokeinterface #31,  2           // InterfaceMethod org/apache/hadoop/hbase/client/Table.put:(Lorg/apache/hadoop/hbase/client/Put;)V
     280: getstatic     #5                  // Field TEST_UTIL:Lorg/apache/hadoop/hbase/HBaseTestingUtility;
     283: invokevirtual #46                 // Method org/apache/hadoop/hbase/HBaseTestingUtility.getAdmin:()Lorg/apache/hadoop/hbase/client/Admin;
     286: aload_1
     287: invokeinterface #47,  1           // InterfaceMethod org/apache/hadoop/hbase/client/Table.getName:()Lorg/apache/hadoop/hbase/TableName;
     292: invokeinterface #48,  2           // InterfaceMethod org/apache/hadoop/hbase/client/Admin.flush:(Lorg/apache/hadoop/hbase/TableName;)V
     297: aload_1
     298: new           #49                 // class org/apache/hadoop/hbase/client/Get
     301: dup
     302: getstatic     #24                 // Field ROW:[B
     305: invokespecial #50                 // Method org/apache/hadoop/hbase/client/Get."<init>":([B)V
     308: iconst_3
     309: invokevirtual #51                 // Method org/apache/hadoop/hbase/client/Get.readVersions:(I)Lorg/apache/hadoop/hbase/client/Get;
     312: invokeinterface #52,  2           // InterfaceMethod org/apache/hadoop/hbase/client/Table.get:(Lorg/apache/hadoop/hbase/client/Get;)Lorg/apache/hadoop/hbase/client/Result;
     317: astore_3
     318: ldc2_w        #72                 // long 4l
     321: aload_3
     322: invokevirtual #53                 // Method org/apache/hadoop/hbase/client/Result.size:()I
     325: i2l
     326: invokestatic  #54                 // Method org/junit/Assert.assertEquals:(JJ)V
     329: ldc2_w        #68                 // long 1500002l
     332: aload_3
     333: invokevirtual #55                 // Method org/apache/hadoop/hbase/client/Result.rawCells:()[Lorg/apache/hadoop/hbase/Cell;
     336: iconst_0
     337: aaload
     338: invokeinterface #56,  1           // InterfaceMethod org/apache/hadoop/hbase/Cell.getTimestamp:()J
     343: invokestatic  #54                 // Method org/junit/Assert.assertEquals:(JJ)V
     346: ldc2_w        #70                 // long 1500001l
     349: aload_3
     350: invokevirtual #55                 // Method org/apache/hadoop/hbase/client/Result.rawCells:()[Lorg/apache/hadoop/hbase/Cell;
     353: iconst_1
     354: aaload
     355: invokeinterface #56,  1           // InterfaceMethod org/apache/hadoop/hbase/Cell.getTimestamp:()J
     360: invokestatic  #54                 // Method org/junit/Assert.assertEquals:(JJ)V
     363: ldc2_w        #70                 // long 1500001l
     366: aload_3
     367: invokevirtual #55                 // Method org/apache/hadoop/hbase/client/Result.rawCells:()[Lorg/apache/hadoop/hbase/Cell;
     370: iconst_2
     371: aaload
     372: invokeinterface #56,  1           // InterfaceMethod org/apache/hadoop/hbase/Cell.getTimestamp:()J
     377: invokestatic  #54                 // Method org/junit/Assert.assertEquals:(JJ)V
     380: ldc2_w        #68                 // long 1500002l
     383: aload_3
     384: invokevirtual #55                 // Method org/apache/hadoop/hbase/client/Result.rawCells:()[Lorg/apache/hadoop/hbase/Cell;
     387: iconst_3
     388: aaload
     389: invokeinterface #56,  1           // InterfaceMethod org/apache/hadoop/hbase/Cell.getTimestamp:()J
     394: invokestatic  #54                 // Method org/junit/Assert.assertEquals:(JJ)V
     397: aload_1
     398: new           #38                 // class org/apache/hadoop/hbase/client/Delete
     401: dup
     402: getstatic     #24                 // Field ROW:[B
     405: invokespecial #39                 // Method org/apache/hadoop/hbase/client/Delete."<init>":([B)V
     408: getstatic     #13                 // Field FAMILY:[B
     411: ldc2_w        #70                 // long 1500001l
     414: invokevirtual #74                 // Method org/apache/hadoop/hbase/client/Delete.addFamilyVersion:([BJ)Lorg/apache/hadoop/hbase/client/Delete;
     417: invokeinterface #43,  2           // InterfaceMethod org/apache/hadoop/hbase/client/Table.delete:(Lorg/apache/hadoop/hbase/client/Delete;)V
     422: aload_1
     423: new           #49                 // class org/apache/hadoop/hbase/client/Get
     426: dup
     427: getstatic     #24                 // Field ROW:[B
     430: invokespecial #50                 // Method org/apache/hadoop/hbase/client/Get."<init>":([B)V
     433: iconst_3
     434: invokevirtual #51                 // Method org/apache/hadoop/hbase/client/Get.readVersions:(I)Lorg/apache/hadoop/hbase/client/Get;
     437: invokeinterface #52,  2           // InterfaceMethod org/apache/hadoop/hbase/client/Table.get:(Lorg/apache/hadoop/hbase/client/Get;)Lorg/apache/hadoop/hbase/client/Result;
     442: astore_3
     443: ldc2_w        #61                 // long 2l
     446: aload_3
     447: invokevirtual #53                 // Method org/apache/hadoop/hbase/client/Result.size:()I
     450: i2l
     451: invokestatic  #54                 // Method org/junit/Assert.assertEquals:(JJ)V
     454: ldc2_w        #68                 // long 1500002l
     457: aload_3
     458: invokevirtual #55                 // Method org/apache/hadoop/hbase/client/Result.rawCells:()[Lorg/apache/hadoop/hbase/Cell;
     461: iconst_0
     462: aaload
     463: invokeinterface #56,  1           // InterfaceMethod org/apache/hadoop/hbase/Cell.getTimestamp:()J
     468: invokestatic  #54                 // Method org/junit/Assert.assertEquals:(JJ)V
     471: ldc2_w        #68                 // long 1500002l
     474: aload_3
     475: invokevirtual #55                 // Method org/apache/hadoop/hbase/client/Result.rawCells:()[Lorg/apache/hadoop/hbase/Cell;
     478: iconst_1
     479: aaload
     480: invokeinterface #56,  1           // InterfaceMethod org/apache/hadoop/hbase/Cell.getTimestamp:()J
     485: invokestatic  #54                 // Method org/junit/Assert.assertEquals:(JJ)V
     488: aload_1
     489: new           #23                 // class org/apache/hadoop/hbase/client/Put
     492: dup
     493: getstatic     #24                 // Field ROW:[B
     496: invokespecial #25                 // Method org/apache/hadoop/hbase/client/Put."<init>":([B)V
     499: getstatic     #13                 // Field FAMILY:[B
     502: getstatic     #26                 // Field col1:[B
     505: ldc2_w        #27                 // long 1000001l
     508: getstatic     #29                 // Field value:[B
     511: invokevirtual #30                 // Method org/apache/hadoop/hbase/client/Put.addColumn:([B[BJ[B)Lorg/apache/hadoop/hbase/client/Put;
     514: invokeinterface #31,  2           // InterfaceMethod org/apache/hadoop/hbase/client/Table.put:(Lorg/apache/hadoop/hbase/client/Put;)V
     519: aload_1
     520: new           #23                 // class org/apache/hadoop/hbase/client/Put
     523: dup
     524: getstatic     #24                 // Field ROW:[B
     527: invokespecial #25                 // Method org/apache/hadoop/hbase/client/Put."<init>":([B)V
     530: getstatic     #13                 // Field FAMILY:[B
     533: getstatic     #26                 // Field col1:[B
     536: ldc2_w        #32                 // long 1000002l
     539: getstatic     #29                 // Field value:[B
     542: invokevirtual #30                 // Method org/apache/hadoop/hbase/client/Put.addColumn:([B[BJ[B)Lorg/apache/hadoop/hbase/client/Put;
     545: invokeinterface #31,  2           // InterfaceMethod org/apache/hadoop/hbase/client/Table.put:(Lorg/apache/hadoop/hbase/client/Put;)V
     550: aload_1
     551: new           #23                 // class org/apache/hadoop/hbase/client/Put
     554: dup
     555: getstatic     #24                 // Field ROW:[B
     558: invokespecial #25                 // Method org/apache/hadoop/hbase/client/Put."<init>":([B)V
     561: getstatic     #13                 // Field FAMILY:[B
     564: getstatic     #65                 // Field col2:[B
     567: ldc2_w        #32                 // long 1000002l
     570: getstatic     #29                 // Field value:[B
     573: invokevirtual #30                 // Method org/apache/hadoop/hbase/client/Put.addColumn:([B[BJ[B)Lorg/apache/hadoop/hbase/client/Put;
     576: invokeinterface #31,  2           // InterfaceMethod org/apache/hadoop/hbase/client/Table.put:(Lorg/apache/hadoop/hbase/client/Put;)V
     581: aload_1
     582: new           #23                 // class org/apache/hadoop/hbase/client/Put
     585: dup
     586: getstatic     #24                 // Field ROW:[B
     589: invokespecial #25                 // Method org/apache/hadoop/hbase/client/Put."<init>":([B)V
     592: getstatic     #13                 // Field FAMILY:[B
     595: getstatic     #66                 // Field col3:[B
     598: ldc2_w        #27                 // long 1000001l
     601: getstatic     #29                 // Field value:[B
     604: invokevirtual #30                 // Method org/apache/hadoop/hbase/client/Put.addColumn:([B[BJ[B)Lorg/apache/hadoop/hbase/client/Put;
     607: invokeinterface #31,  2           // InterfaceMethod org/apache/hadoop/hbase/client/Table.put:(Lorg/apache/hadoop/hbase/client/Put;)V
     612: getstatic     #5                  // Field TEST_UTIL:Lorg/apache/hadoop/hbase/HBaseTestingUtility;
     615: invokevirtual #46                 // Method org/apache/hadoop/hbase/HBaseTestingUtility.getAdmin:()Lorg/apache/hadoop/hbase/client/Admin;
     618: aload_1
     619: invokeinterface #47,  1           // InterfaceMethod org/apache/hadoop/hbase/client/Table.getName:()Lorg/apache/hadoop/hbase/TableName;
     624: invokeinterface #48,  2           // InterfaceMethod org/apache/hadoop/hbase/client/Admin.flush:(Lorg/apache/hadoop/hbase/TableName;)V
     629: aload_1
     630: new           #49                 // class org/apache/hadoop/hbase/client/Get
     633: dup
     634: getstatic     #24                 // Field ROW:[B
     637: invokespecial #50                 // Method org/apache/hadoop/hbase/client/Get."<init>":([B)V
     640: iconst_3
     641: invokevirtual #51                 // Method org/apache/hadoop/hbase/client/Get.readVersions:(I)Lorg/apache/hadoop/hbase/client/Get;
     644: invokeinterface #52,  2           // InterfaceMethod org/apache/hadoop/hbase/client/Table.get:(Lorg/apache/hadoop/hbase/client/Get;)Lorg/apache/hadoop/hbase/client/Result;
     649: astore_3
     650: ldc2_w        #75                 // long 6l
     653: aload_3
     654: invokevirtual #53                 // Method org/apache/hadoop/hbase/client/Result.size:()I
     657: i2l
     658: invokestatic  #54                 // Method org/junit/Assert.assertEquals:(JJ)V
     661: ldc2_w        #68                 // long 1500002l
     664: aload_3
     665: invokevirtual #55                 // Method org/apache/hadoop/hbase/client/Result.rawCells:()[Lorg/apache/hadoop/hbase/Cell;
     668: iconst_0
     669: aaload
     670: invokeinterface #56,  1           // InterfaceMethod org/apache/hadoop/hbase/Cell.getTimestamp:()J
     675: invokestatic  #54                 // Method org/junit/Assert.assertEquals:(JJ)V
     678: ldc2_w        #32                 // long 1000002l
     681: aload_3
     682: invokevirtual #55                 // Method org/apache/hadoop/hbase/client/Result.rawCells:()[Lorg/apache/hadoop/hbase/Cell;
     685: iconst_1
     686: aaload
     687: invokeinterface #56,  1           // InterfaceMethod org/apache/hadoop/hbase/Cell.getTimestamp:()J
     692: invokestatic  #54                 // Method org/junit/Assert.assertEquals:(JJ)V
     695: ldc2_w        #27                 // long 1000001l
     698: aload_3
     699: invokevirtual #55                 // Method org/apache/hadoop/hbase/client/Result.rawCells:()[Lorg/apache/hadoop/hbase/Cell;
     702: iconst_2
     703: aaload
     704: invokeinterface #56,  1           // InterfaceMethod org/apache/hadoop/hbase/Cell.getTimestamp:()J
     709: invokestatic  #54                 // Method org/junit/Assert.assertEquals:(JJ)V
     712: ldc2_w        #32                 // long 1000002l
     715: aload_3
     716: invokevirtual #55                 // Method org/apache/hadoop/hbase/client/Result.rawCells:()[Lorg/apache/hadoop/hbase/Cell;
     719: iconst_3
     720: aaload
     721: invokeinterface #56,  1           // InterfaceMethod org/apache/hadoop/hbase/Cell.getTimestamp:()J
     726: invokestatic  #54                 // Method org/junit/Assert.assertEquals:(JJ)V
     729: ldc2_w        #68                 // long 1500002l
     732: aload_3
     733: invokevirtual #55                 // Method org/apache/hadoop/hbase/client/Result.rawCells:()[Lorg/apache/hadoop/hbase/Cell;
     736: iconst_4
     737: aaload
     738: invokeinterface #56,  1           // InterfaceMethod org/apache/hadoop/hbase/Cell.getTimestamp:()J
     743: invokestatic  #54                 // Method org/junit/Assert.assertEquals:(JJ)V
     746: ldc2_w        #27                 // long 1000001l
     749: aload_3
     750: invokevirtual #55                 // Method org/apache/hadoop/hbase/client/Result.rawCells:()[Lorg/apache/hadoop/hbase/Cell;
     753: iconst_5
     754: aaload
     755: invokeinterface #56,  1           // InterfaceMethod org/apache/hadoop/hbase/Cell.getTimestamp:()J
     760: invokestatic  #54                 // Method org/junit/Assert.assertEquals:(JJ)V
     763: aload_1
     764: ifnull        842
     767: aload_2
     768: ifnull        789
     771: aload_1
     772: invokeinterface #57,  1           // InterfaceMethod org/apache/hadoop/hbase/client/Table.close:()V
     777: goto          842
     780: astore_3
     781: aload_2
     782: aload_3
     783: invokevirtual #59                 // Method java/lang/Throwable.addSuppressed:(Ljava/lang/Throwable;)V
     786: goto          842
     789: aload_1
     790: invokeinterface #57,  1           // InterfaceMethod org/apache/hadoop/hbase/client/Table.close:()V
     795: goto          842
     798: astore_3
     799: aload_3
     800: astore_2
     801: aload_3
     802: athrow
     803: astore        4
     805: aload_1
     806: ifnull        839
     809: aload_2
     810: ifnull        833
     813: aload_1
     814: invokeinterface #57,  1           // InterfaceMethod org/apache/hadoop/hbase/client/Table.close:()V
     819: goto          839
     822: astore        5
     824: aload_2
     825: aload         5
     827: invokevirtual #59                 // Method java/lang/Throwable.addSuppressed:(Ljava/lang/Throwable;)V
     830: goto          839
     833: aload_1
     834: invokeinterface #57,  1           // InterfaceMethod org/apache/hadoop/hbase/client/Table.close:()V
     839: aload         4
     841: athrow
     842: return
    Exception table:
       from    to  target type
         771   777   780   Class java/lang/Throwable
           7   763   798   Class java/lang/Throwable
           7   763   803   any
         813   819   822   Class java/lang/Throwable
         798   805   803   any

  public void testTimeRange() throws java.io.IOException;
    Code:
       0: aload_0
       1: invokespecial #22                 // Method createTable:()Lorg/apache/hadoop/hbase/client/Table;
       4: astore_1
       5: aconst_null
       6: astore_2
       7: aload_1
       8: new           #23                 // class org/apache/hadoop/hbase/client/Put
      11: dup
      12: getstatic     #24                 // Field ROW:[B
      15: invokespecial #25                 // Method org/apache/hadoop/hbase/client/Put."<init>":([B)V
      18: getstatic     #13                 // Field FAMILY:[B
      21: getstatic     #26                 // Field col1:[B
      24: ldc2_w        #27                 // long 1000001l
      27: getstatic     #29                 // Field value:[B
      30: invokevirtual #30                 // Method org/apache/hadoop/hbase/client/Put.addColumn:([B[BJ[B)Lorg/apache/hadoop/hbase/client/Put;
      33: invokeinterface #31,  2           // InterfaceMethod org/apache/hadoop/hbase/client/Table.put:(Lorg/apache/hadoop/hbase/client/Put;)V
      38: aload_1
      39: new           #23                 // class org/apache/hadoop/hbase/client/Put
      42: dup
      43: getstatic     #24                 // Field ROW:[B
      46: invokespecial #25                 // Method org/apache/hadoop/hbase/client/Put."<init>":([B)V
      49: getstatic     #13                 // Field FAMILY:[B
      52: getstatic     #26                 // Field col1:[B
      55: ldc2_w        #32                 // long 1000002l
      58: getstatic     #29                 // Field value:[B
      61: invokevirtual #30                 // Method org/apache/hadoop/hbase/client/Put.addColumn:([B[BJ[B)Lorg/apache/hadoop/hbase/client/Put;
      64: invokeinterface #31,  2           // InterfaceMethod org/apache/hadoop/hbase/client/Table.put:(Lorg/apache/hadoop/hbase/client/Put;)V
      69: aload_1
      70: new           #23                 // class org/apache/hadoop/hbase/client/Put
      73: dup
      74: getstatic     #24                 // Field ROW:[B
      77: invokespecial #25                 // Method org/apache/hadoop/hbase/client/Put."<init>":([B)V
      80: getstatic     #13                 // Field FAMILY:[B
      83: getstatic     #26                 // Field col1:[B
      86: ldc2_w        #34                 // long 1000003l
      89: getstatic     #29                 // Field value:[B
      92: invokevirtual #30                 // Method org/apache/hadoop/hbase/client/Put.addColumn:([B[BJ[B)Lorg/apache/hadoop/hbase/client/Put;
      95: invokeinterface #31,  2           // InterfaceMethod org/apache/hadoop/hbase/client/Table.put:(Lorg/apache/hadoop/hbase/client/Put;)V
     100: aload_1
     101: new           #23                 // class org/apache/hadoop/hbase/client/Put
     104: dup
     105: getstatic     #24                 // Field ROW:[B
     108: invokespecial #25                 // Method org/apache/hadoop/hbase/client/Put."<init>":([B)V
     111: getstatic     #13                 // Field FAMILY:[B
     114: getstatic     #26                 // Field col1:[B
     117: ldc2_w        #36                 // long 1000004l
     120: getstatic     #29                 // Field value:[B
     123: invokevirtual #30                 // Method org/apache/hadoop/hbase/client/Put.addColumn:([B[BJ[B)Lorg/apache/hadoop/hbase/client/Put;
     126: invokeinterface #31,  2           // InterfaceMethod org/apache/hadoop/hbase/client/Table.put:(Lorg/apache/hadoop/hbase/client/Put;)V
     131: aload_1
     132: new           #23                 // class org/apache/hadoop/hbase/client/Put
     135: dup
     136: getstatic     #24                 // Field ROW:[B
     139: invokespecial #25                 // Method org/apache/hadoop/hbase/client/Put."<init>":([B)V
     142: getstatic     #13                 // Field FAMILY:[B
     145: getstatic     #26                 // Field col1:[B
     148: ldc2_w        #77                 // long 1000005l
     151: getstatic     #29                 // Field value:[B
     154: invokevirtual #30                 // Method org/apache/hadoop/hbase/client/Put.addColumn:([B[BJ[B)Lorg/apache/hadoop/hbase/client/Put;
     157: invokeinterface #31,  2           // InterfaceMethod org/apache/hadoop/hbase/client/Table.put:(Lorg/apache/hadoop/hbase/client/Put;)V
     162: aload_1
     163: new           #23                 // class org/apache/hadoop/hbase/client/Put
     166: dup
     167: getstatic     #24                 // Field ROW:[B
     170: invokespecial #25                 // Method org/apache/hadoop/hbase/client/Put."<init>":([B)V
     173: getstatic     #13                 // Field FAMILY:[B
     176: getstatic     #26                 // Field col1:[B
     179: ldc2_w        #79                 // long 1000006l
     182: getstatic     #29                 // Field value:[B
     185: invokevirtual #30                 // Method org/apache/hadoop/hbase/client/Put.addColumn:([B[BJ[B)Lorg/apache/hadoop/hbase/client/Put;
     188: invokeinterface #31,  2           // InterfaceMethod org/apache/hadoop/hbase/client/Table.put:(Lorg/apache/hadoop/hbase/client/Put;)V
     193: aload_1
     194: new           #23                 // class org/apache/hadoop/hbase/client/Put
     197: dup
     198: getstatic     #24                 // Field ROW:[B
     201: invokespecial #25                 // Method org/apache/hadoop/hbase/client/Put."<init>":([B)V
     204: getstatic     #13                 // Field FAMILY:[B
     207: getstatic     #26                 // Field col1:[B
     210: ldc2_w        #81                 // long 1000007l
     213: getstatic     #29                 // Field value:[B
     216: invokevirtual #30                 // Method org/apache/hadoop/hbase/client/Put.addColumn:([B[BJ[B)Lorg/apache/hadoop/hbase/client/Put;
     219: invokeinterface #31,  2           // InterfaceMethod org/apache/hadoop/hbase/client/Table.put:(Lorg/apache/hadoop/hbase/client/Put;)V
     224: aload_1
     225: new           #23                 // class org/apache/hadoop/hbase/client/Put
     228: dup
     229: getstatic     #24                 // Field ROW:[B
     232: invokespecial #25                 // Method org/apache/hadoop/hbase/client/Put."<init>":([B)V
     235: getstatic     #13                 // Field FAMILY:[B
     238: getstatic     #26                 // Field col1:[B
     241: ldc2_w        #83                 // long 1000008l
     244: getstatic     #29                 // Field value:[B
     247: invokevirtual #30                 // Method org/apache/hadoop/hbase/client/Put.addColumn:([B[BJ[B)Lorg/apache/hadoop/hbase/client/Put;
     250: invokeinterface #31,  2           // InterfaceMethod org/apache/hadoop/hbase/client/Table.put:(Lorg/apache/hadoop/hbase/client/Put;)V
     255: aload_1
     256: new           #49                 // class org/apache/hadoop/hbase/client/Get
     259: dup
     260: getstatic     #24                 // Field ROW:[B
     263: invokespecial #50                 // Method org/apache/hadoop/hbase/client/Get."<init>":([B)V
     266: iconst_3
     267: invokevirtual #51                 // Method org/apache/hadoop/hbase/client/Get.readVersions:(I)Lorg/apache/hadoop/hbase/client/Get;
     270: lconst_0
     271: ldc2_w        #77                 // long 1000005l
     274: invokevirtual #85                 // Method org/apache/hadoop/hbase/client/Get.setTimeRange:(JJ)Lorg/apache/hadoop/hbase/client/Get;
     277: invokeinterface #52,  2           // InterfaceMethod org/apache/hadoop/hbase/client/Table.get:(Lorg/apache/hadoop/hbase/client/Get;)Lorg/apache/hadoop/hbase/client/Result;
     282: astore_3
     283: lconst_0
     284: aload_3
     285: invokevirtual #53                 // Method org/apache/hadoop/hbase/client/Result.size:()I
     288: i2l
     289: invokestatic  #54                 // Method org/junit/Assert.assertEquals:(JJ)V
     292: getstatic     #5                  // Field TEST_UTIL:Lorg/apache/hadoop/hbase/HBaseTestingUtility;
     295: invokevirtual #46                 // Method org/apache/hadoop/hbase/HBaseTestingUtility.getAdmin:()Lorg/apache/hadoop/hbase/client/Admin;
     298: aload_1
     299: invokeinterface #47,  1           // InterfaceMethod org/apache/hadoop/hbase/client/Table.getName:()Lorg/apache/hadoop/hbase/TableName;
     304: invokeinterface #48,  2           // InterfaceMethod org/apache/hadoop/hbase/client/Admin.flush:(Lorg/apache/hadoop/hbase/TableName;)V
     309: aload_1
     310: new           #49                 // class org/apache/hadoop/hbase/client/Get
     313: dup
     314: getstatic     #24                 // Field ROW:[B
     317: invokespecial #50                 // Method org/apache/hadoop/hbase/client/Get."<init>":([B)V
     320: iconst_3
     321: invokevirtual #51                 // Method org/apache/hadoop/hbase/client/Get.readVersions:(I)Lorg/apache/hadoop/hbase/client/Get;
     324: lconst_0
     325: ldc2_w        #77                 // long 1000005l
     328: invokevirtual #85                 // Method org/apache/hadoop/hbase/client/Get.setTimeRange:(JJ)Lorg/apache/hadoop/hbase/client/Get;
     331: invokeinterface #52,  2           // InterfaceMethod org/apache/hadoop/hbase/client/Table.get:(Lorg/apache/hadoop/hbase/client/Get;)Lorg/apache/hadoop/hbase/client/Result;
     336: astore_3
     337: lconst_0
     338: aload_3
     339: invokevirtual #53                 // Method org/apache/hadoop/hbase/client/Result.size:()I
     342: i2l
     343: invokestatic  #54                 // Method org/junit/Assert.assertEquals:(JJ)V
     346: aload_1
     347: ifnull        425
     350: aload_2
     351: ifnull        372
     354: aload_1
     355: invokeinterface #57,  1           // InterfaceMethod org/apache/hadoop/hbase/client/Table.close:()V
     360: goto          425
     363: astore_3
     364: aload_2
     365: aload_3
     366: invokevirtual #59                 // Method java/lang/Throwable.addSuppressed:(Ljava/lang/Throwable;)V
     369: goto          425
     372: aload_1
     373: invokeinterface #57,  1           // InterfaceMethod org/apache/hadoop/hbase/client/Table.close:()V
     378: goto          425
     381: astore_3
     382: aload_3
     383: astore_2
     384: aload_3
     385: athrow
     386: astore        4
     388: aload_1
     389: ifnull        422
     392: aload_2
     393: ifnull        416
     396: aload_1
     397: invokeinterface #57,  1           // InterfaceMethod org/apache/hadoop/hbase/client/Table.close:()V
     402: goto          422
     405: astore        5
     407: aload_2
     408: aload         5
     410: invokevirtual #59                 // Method java/lang/Throwable.addSuppressed:(Ljava/lang/Throwable;)V
     413: goto          422
     416: aload_1
     417: invokeinterface #57,  1           // InterfaceMethod org/apache/hadoop/hbase/client/Table.close:()V
     422: aload         4
     424: athrow
     425: return
    Exception table:
       from    to  target type
         354   360   363   Class java/lang/Throwable
           7   346   381   Class java/lang/Throwable
           7   346   386   any
         396   402   405   Class java/lang/Throwable
         381   388   386   any

  public void testExplicitColum() throws java.io.IOException;
    Code:
       0: aload_0
       1: invokespecial #22                 // Method createTable:()Lorg/apache/hadoop/hbase/client/Table;
       4: astore_1
       5: aconst_null
       6: astore_2
       7: aload_1
       8: new           #23                 // class org/apache/hadoop/hbase/client/Put
      11: dup
      12: getstatic     #24                 // Field ROW:[B
      15: invokespecial #25                 // Method org/apache/hadoop/hbase/client/Put."<init>":([B)V
      18: getstatic     #13                 // Field FAMILY:[B
      21: getstatic     #26                 // Field col1:[B
      24: getstatic     #29                 // Field value:[B
      27: invokevirtual #86                 // Method org/apache/hadoop/hbase/client/Put.addColumn:([B[B[B)Lorg/apache/hadoop/hbase/client/Put;
      30: invokeinterface #31,  2           // InterfaceMethod org/apache/hadoop/hbase/client/Table.put:(Lorg/apache/hadoop/hbase/client/Put;)V
      35: aload_1
      36: new           #23                 // class org/apache/hadoop/hbase/client/Put
      39: dup
      40: getstatic     #24                 // Field ROW:[B
      43: invokespecial #25                 // Method org/apache/hadoop/hbase/client/Put."<init>":([B)V
      46: getstatic     #13                 // Field FAMILY:[B
      49: getstatic     #26                 // Field col1:[B
      52: getstatic     #29                 // Field value:[B
      55: invokevirtual #86                 // Method org/apache/hadoop/hbase/client/Put.addColumn:([B[B[B)Lorg/apache/hadoop/hbase/client/Put;
      58: invokeinterface #31,  2           // InterfaceMethod org/apache/hadoop/hbase/client/Table.put:(Lorg/apache/hadoop/hbase/client/Put;)V
      63: aload_1
      64: new           #23                 // class org/apache/hadoop/hbase/client/Put
      67: dup
      68: getstatic     #24                 // Field ROW:[B
      71: invokespecial #25                 // Method org/apache/hadoop/hbase/client/Put."<init>":([B)V
      74: getstatic     #13                 // Field FAMILY:[B
      77: getstatic     #26                 // Field col1:[B
      80: getstatic     #29                 // Field value:[B
      83: invokevirtual #86                 // Method org/apache/hadoop/hbase/client/Put.addColumn:([B[B[B)Lorg/apache/hadoop/hbase/client/Put;
      86: invokeinterface #31,  2           // InterfaceMethod org/apache/hadoop/hbase/client/Table.put:(Lorg/apache/hadoop/hbase/client/Put;)V
      91: aload_1
      92: new           #23                 // class org/apache/hadoop/hbase/client/Put
      95: dup
      96: getstatic     #24                 // Field ROW:[B
      99: invokespecial #25                 // Method org/apache/hadoop/hbase/client/Put."<init>":([B)V
     102: getstatic     #13                 // Field FAMILY:[B
     105: getstatic     #26                 // Field col1:[B
     108: getstatic     #29                 // Field value:[B
     111: invokevirtual #86                 // Method org/apache/hadoop/hbase/client/Put.addColumn:([B[B[B)Lorg/apache/hadoop/hbase/client/Put;
     114: invokeinterface #31,  2           // InterfaceMethod org/apache/hadoop/hbase/client/Table.put:(Lorg/apache/hadoop/hbase/client/Put;)V
     119: aload_1
     120: new           #23                 // class org/apache/hadoop/hbase/client/Put
     123: dup
     124: getstatic     #24                 // Field ROW:[B
     127: invokespecial #25                 // Method org/apache/hadoop/hbase/client/Put."<init>":([B)V
     130: getstatic     #13                 // Field FAMILY:[B
     133: getstatic     #65                 // Field col2:[B
     136: getstatic     #29                 // Field value:[B
     139: invokevirtual #86                 // Method org/apache/hadoop/hbase/client/Put.addColumn:([B[B[B)Lorg/apache/hadoop/hbase/client/Put;
     142: invokeinterface #31,  2           // InterfaceMethod org/apache/hadoop/hbase/client/Table.put:(Lorg/apache/hadoop/hbase/client/Put;)V
     147: aload_1
     148: new           #23                 // class org/apache/hadoop/hbase/client/Put
     151: dup
     152: getstatic     #24                 // Field ROW:[B
     155: invokespecial #25                 // Method org/apache/hadoop/hbase/client/Put."<init>":([B)V
     158: getstatic     #13                 // Field FAMILY:[B
     161: getstatic     #65                 // Field col2:[B
     164: getstatic     #29                 // Field value:[B
     167: invokevirtual #86                 // Method org/apache/hadoop/hbase/client/Put.addColumn:([B[B[B)Lorg/apache/hadoop/hbase/client/Put;
     170: invokeinterface #31,  2           // InterfaceMethod org/apache/hadoop/hbase/client/Table.put:(Lorg/apache/hadoop/hbase/client/Put;)V
     175: aload_1
     176: new           #23                 // class org/apache/hadoop/hbase/client/Put
     179: dup
     180: getstatic     #24                 // Field ROW:[B
     183: invokespecial #25                 // Method org/apache/hadoop/hbase/client/Put."<init>":([B)V
     186: getstatic     #13                 // Field FAMILY:[B
     189: getstatic     #65                 // Field col2:[B
     192: getstatic     #29                 // Field value:[B
     195: invokevirtual #86                 // Method org/apache/hadoop/hbase/client/Put.addColumn:([B[B[B)Lorg/apache/hadoop/hbase/client/Put;
     198: invokeinterface #31,  2           // InterfaceMethod org/apache/hadoop/hbase/client/Table.put:(Lorg/apache/hadoop/hbase/client/Put;)V
     203: aload_1
     204: new           #23                 // class org/apache/hadoop/hbase/client/Put
     207: dup
     208: getstatic     #24                 // Field ROW:[B
     211: invokespecial #25                 // Method org/apache/hadoop/hbase/client/Put."<init>":([B)V
     214: getstatic     #13                 // Field FAMILY:[B
     217: getstatic     #65                 // Field col2:[B
     220: getstatic     #29                 // Field value:[B
     223: invokevirtual #86                 // Method org/apache/hadoop/hbase/client/Put.addColumn:([B[B[B)Lorg/apache/hadoop/hbase/client/Put;
     226: invokeinterface #31,  2           // InterfaceMethod org/apache/hadoop/hbase/client/Table.put:(Lorg/apache/hadoop/hbase/client/Put;)V
     231: aload_1
     232: new           #23                 // class org/apache/hadoop/hbase/client/Put
     235: dup
     236: getstatic     #24                 // Field ROW:[B
     239: invokespecial #25                 // Method org/apache/hadoop/hbase/client/Put."<init>":([B)V
     242: getstatic     #13                 // Field FAMILY:[B
     245: getstatic     #66                 // Field col3:[B
     248: getstatic     #29                 // Field value:[B
     251: invokevirtual #86                 // Method org/apache/hadoop/hbase/client/Put.addColumn:([B[B[B)Lorg/apache/hadoop/hbase/client/Put;
     254: invokeinterface #31,  2           // InterfaceMethod org/apache/hadoop/hbase/client/Table.put:(Lorg/apache/hadoop/hbase/client/Put;)V
     259: aload_1
     260: new           #23                 // class org/apache/hadoop/hbase/client/Put
     263: dup
     264: getstatic     #24                 // Field ROW:[B
     267: invokespecial #25                 // Method org/apache/hadoop/hbase/client/Put."<init>":([B)V
     270: getstatic     #13                 // Field FAMILY:[B
     273: getstatic     #66                 // Field col3:[B
     276: getstatic     #29                 // Field value:[B
     279: invokevirtual #86                 // Method org/apache/hadoop/hbase/client/Put.addColumn:([B[B[B)Lorg/apache/hadoop/hbase/client/Put;
     282: invokeinterface #31,  2           // InterfaceMethod org/apache/hadoop/hbase/client/Table.put:(Lorg/apache/hadoop/hbase/client/Put;)V
     287: aload_1
     288: new           #23                 // class org/apache/hadoop/hbase/client/Put
     291: dup
     292: getstatic     #24                 // Field ROW:[B
     295: invokespecial #25                 // Method org/apache/hadoop/hbase/client/Put."<init>":([B)V
     298: getstatic     #13                 // Field FAMILY:[B
     301: getstatic     #66                 // Field col3:[B
     304: getstatic     #29                 // Field value:[B
     307: invokevirtual #86                 // Method org/apache/hadoop/hbase/client/Put.addColumn:([B[B[B)Lorg/apache/hadoop/hbase/client/Put;
     310: invokeinterface #31,  2           // InterfaceMethod org/apache/hadoop/hbase/client/Table.put:(Lorg/apache/hadoop/hbase/client/Put;)V
     315: aload_1
     316: new           #23                 // class org/apache/hadoop/hbase/client/Put
     319: dup
     320: getstatic     #24                 // Field ROW:[B
     323: invokespecial #25                 // Method org/apache/hadoop/hbase/client/Put."<init>":([B)V
     326: getstatic     #13                 // Field FAMILY:[B
     329: getstatic     #66                 // Field col3:[B
     332: getstatic     #29                 // Field value:[B
     335: invokevirtual #86                 // Method org/apache/hadoop/hbase/client/Put.addColumn:([B[B[B)Lorg/apache/hadoop/hbase/client/Put;
     338: invokeinterface #31,  2           // InterfaceMethod org/apache/hadoop/hbase/client/Table.put:(Lorg/apache/hadoop/hbase/client/Put;)V
     343: aload_1
     344: new           #49                 // class org/apache/hadoop/hbase/client/Get
     347: dup
     348: getstatic     #24                 // Field ROW:[B
     351: invokespecial #50                 // Method org/apache/hadoop/hbase/client/Get."<init>":([B)V
     354: iconst_3
     355: invokevirtual #51                 // Method org/apache/hadoop/hbase/client/Get.readVersions:(I)Lorg/apache/hadoop/hbase/client/Get;
     358: getstatic     #13                 // Field FAMILY:[B
     361: getstatic     #65                 // Field col2:[B
     364: invokevirtual #87                 // Method org/apache/hadoop/hbase/client/Get.addColumn:([B[B)Lorg/apache/hadoop/hbase/client/Get;
     367: invokeinterface #52,  2           // InterfaceMethod org/apache/hadoop/hbase/client/Table.get:(Lorg/apache/hadoop/hbase/client/Get;)Lorg/apache/hadoop/hbase/client/Result;
     372: astore_3
     373: ldc2_w        #63                 // long 3l
     376: aload_3
     377: invokevirtual #53                 // Method org/apache/hadoop/hbase/client/Result.size:()I
     380: i2l
     381: invokestatic  #54                 // Method org/junit/Assert.assertEquals:(JJ)V
     384: getstatic     #5                  // Field TEST_UTIL:Lorg/apache/hadoop/hbase/HBaseTestingUtility;
     387: invokevirtual #46                 // Method org/apache/hadoop/hbase/HBaseTestingUtility.getAdmin:()Lorg/apache/hadoop/hbase/client/Admin;
     390: aload_1
     391: invokeinterface #47,  1           // InterfaceMethod org/apache/hadoop/hbase/client/Table.getName:()Lorg/apache/hadoop/hbase/TableName;
     396: invokeinterface #48,  2           // InterfaceMethod org/apache/hadoop/hbase/client/Admin.flush:(Lorg/apache/hadoop/hbase/TableName;)V
     401: aload_1
     402: new           #49                 // class org/apache/hadoop/hbase/client/Get
     405: dup
     406: getstatic     #24                 // Field ROW:[B
     409: invokespecial #50                 // Method org/apache/hadoop/hbase/client/Get."<init>":([B)V
     412: iconst_3
     413: invokevirtual #51                 // Method org/apache/hadoop/hbase/client/Get.readVersions:(I)Lorg/apache/hadoop/hbase/client/Get;
     416: getstatic     #13                 // Field FAMILY:[B
     419: getstatic     #65                 // Field col2:[B
     422: invokevirtual #87                 // Method org/apache/hadoop/hbase/client/Get.addColumn:([B[B)Lorg/apache/hadoop/hbase/client/Get;
     425: invokeinterface #52,  2           // InterfaceMethod org/apache/hadoop/hbase/client/Table.get:(Lorg/apache/hadoop/hbase/client/Get;)Lorg/apache/hadoop/hbase/client/Result;
     430: astore_3
     431: ldc2_w        #63                 // long 3l
     434: aload_3
     435: invokevirtual #53                 // Method org/apache/hadoop/hbase/client/Result.size:()I
     438: i2l
     439: invokestatic  #54                 // Method org/junit/Assert.assertEquals:(JJ)V
     442: getstatic     #5                  // Field TEST_UTIL:Lorg/apache/hadoop/hbase/HBaseTestingUtility;
     445: invokevirtual #46                 // Method org/apache/hadoop/hbase/HBaseTestingUtility.getAdmin:()Lorg/apache/hadoop/hbase/client/Admin;
     448: aload_1
     449: invokeinterface #47,  1           // InterfaceMethod org/apache/hadoop/hbase/client/Table.getName:()Lorg/apache/hadoop/hbase/TableName;
     454: invokeinterface #48,  2           // InterfaceMethod org/apache/hadoop/hbase/client/Admin.flush:(Lorg/apache/hadoop/hbase/TableName;)V
     459: aload_1
     460: ifnull        538
     463: aload_2
     464: ifnull        485
     467: aload_1
     468: invokeinterface #57,  1           // InterfaceMethod org/apache/hadoop/hbase/client/Table.close:()V
     473: goto          538
     476: astore_3
     477: aload_2
     478: aload_3
     479: invokevirtual #59                 // Method java/lang/Throwable.addSuppressed:(Ljava/lang/Throwable;)V
     482: goto          538
     485: aload_1
     486: invokeinterface #57,  1           // InterfaceMethod org/apache/hadoop/hbase/client/Table.close:()V
     491: goto          538
     494: astore_3
     495: aload_3
     496: astore_2
     497: aload_3
     498: athrow
     499: astore        4
     501: aload_1
     502: ifnull        535
     505: aload_2
     506: ifnull        529
     509: aload_1
     510: invokeinterface #57,  1           // InterfaceMethod org/apache/hadoop/hbase/client/Table.close:()V
     515: goto          535
     518: astore        5
     520: aload_2
     521: aload         5
     523: invokevirtual #59                 // Method java/lang/Throwable.addSuppressed:(Ljava/lang/Throwable;)V
     526: goto          535
     529: aload_1
     530: invokeinterface #57,  1           // InterfaceMethod org/apache/hadoop/hbase/client/Table.close:()V
     535: aload         4
     537: athrow
     538: return
    Exception table:
       from    to  target type
         467   473   476   Class java/lang/Throwable
           7   459   494   Class java/lang/Throwable
           7   459   499   any
         509   515   518   Class java/lang/Throwable
         494   501   499   any

  public void testgetColumnHint() throws java.io.IOException;
    Code:
       0: aload_0
       1: invokespecial #22                 // Method createTable:()Lorg/apache/hadoop/hbase/client/Table;
       4: astore_1
       5: aconst_null
       6: astore_2
       7: aload_1
       8: sipush        10000
      11: invokeinterface #88,  2           // InterfaceMethod org/apache/hadoop/hbase/client/Table.setOperationTimeout:(I)V
      16: aload_1
      17: sipush        10000
      20: invokeinterface #89,  2           // InterfaceMethod org/apache/hadoop/hbase/client/Table.setRpcTimeout:(I)V
      25: aload_1
      26: new           #23                 // class org/apache/hadoop/hbase/client/Put
      29: dup
      30: getstatic     #24                 // Field ROW:[B
      33: invokespecial #25                 // Method org/apache/hadoop/hbase/client/Put."<init>":([B)V
      36: getstatic     #13                 // Field FAMILY:[B
      39: getstatic     #26                 // Field col1:[B
      42: ldc2_w        #90                 // long 100l
      45: getstatic     #29                 // Field value:[B
      48: invokevirtual #30                 // Method org/apache/hadoop/hbase/client/Put.addColumn:([B[BJ[B)Lorg/apache/hadoop/hbase/client/Put;
      51: invokeinterface #31,  2           // InterfaceMethod org/apache/hadoop/hbase/client/Table.put:(Lorg/apache/hadoop/hbase/client/Put;)V
      56: aload_1
      57: new           #23                 // class org/apache/hadoop/hbase/client/Put
      60: dup
      61: getstatic     #24                 // Field ROW:[B
      64: invokespecial #25                 // Method org/apache/hadoop/hbase/client/Put."<init>":([B)V
      67: getstatic     #13                 // Field FAMILY:[B
      70: getstatic     #26                 // Field col1:[B
      73: ldc2_w        #92                 // long 101l
      76: getstatic     #29                 // Field value:[B
      79: invokevirtual #30                 // Method org/apache/hadoop/hbase/client/Put.addColumn:([B[BJ[B)Lorg/apache/hadoop/hbase/client/Put;
      82: invokeinterface #31,  2           // InterfaceMethod org/apache/hadoop/hbase/client/Table.put:(Lorg/apache/hadoop/hbase/client/Put;)V
      87: aload_1
      88: new           #23                 // class org/apache/hadoop/hbase/client/Put
      91: dup
      92: getstatic     #24                 // Field ROW:[B
      95: invokespecial #25                 // Method org/apache/hadoop/hbase/client/Put."<init>":([B)V
      98: getstatic     #13                 // Field FAMILY:[B
     101: getstatic     #26                 // Field col1:[B
     104: ldc2_w        #94                 // long 102l
     107: getstatic     #29                 // Field value:[B
     110: invokevirtual #30                 // Method org/apache/hadoop/hbase/client/Put.addColumn:([B[BJ[B)Lorg/apache/hadoop/hbase/client/Put;
     113: invokeinterface #31,  2           // InterfaceMethod org/apache/hadoop/hbase/client/Table.put:(Lorg/apache/hadoop/hbase/client/Put;)V
     118: aload_1
     119: new           #23                 // class org/apache/hadoop/hbase/client/Put
     122: dup
     123: getstatic     #24                 // Field ROW:[B
     126: invokespecial #25                 // Method org/apache/hadoop/hbase/client/Put."<init>":([B)V
     129: getstatic     #13                 // Field FAMILY:[B
     132: getstatic     #26                 // Field col1:[B
     135: ldc2_w        #96                 // long 103l
     138: getstatic     #29                 // Field value:[B
     141: invokevirtual #30                 // Method org/apache/hadoop/hbase/client/Put.addColumn:([B[BJ[B)Lorg/apache/hadoop/hbase/client/Put;
     144: invokeinterface #31,  2           // InterfaceMethod org/apache/hadoop/hbase/client/Table.put:(Lorg/apache/hadoop/hbase/client/Put;)V
     149: aload_1
     150: new           #23                 // class org/apache/hadoop/hbase/client/Put
     153: dup
     154: getstatic     #24                 // Field ROW:[B
     157: invokespecial #25                 // Method org/apache/hadoop/hbase/client/Put."<init>":([B)V
     160: getstatic     #13                 // Field FAMILY:[B
     163: getstatic     #26                 // Field col1:[B
     166: ldc2_w        #98                 // long 104l
     169: getstatic     #29                 // Field value:[B
     172: invokevirtual #30                 // Method org/apache/hadoop/hbase/client/Put.addColumn:([B[BJ[B)Lorg/apache/hadoop/hbase/client/Put;
     175: invokeinterface #31,  2           // InterfaceMethod org/apache/hadoop/hbase/client/Table.put:(Lorg/apache/hadoop/hbase/client/Put;)V
     180: aload_1
     181: new           #23                 // class org/apache/hadoop/hbase/client/Put
     184: dup
     185: getstatic     #100                // Field ROW2:[B
     188: invokespecial #25                 // Method org/apache/hadoop/hbase/client/Put."<init>":([B)V
     191: getstatic     #13                 // Field FAMILY:[B
     194: getstatic     #26                 // Field col1:[B
     197: ldc2_w        #98                 // long 104l
     200: getstatic     #29                 // Field value:[B
     203: invokevirtual #30                 // Method org/apache/hadoop/hbase/client/Put.addColumn:([B[BJ[B)Lorg/apache/hadoop/hbase/client/Put;
     206: invokeinterface #31,  2           // InterfaceMethod org/apache/hadoop/hbase/client/Table.put:(Lorg/apache/hadoop/hbase/client/Put;)V
     211: getstatic     #5                  // Field TEST_UTIL:Lorg/apache/hadoop/hbase/HBaseTestingUtility;
     214: invokevirtual #46                 // Method org/apache/hadoop/hbase/HBaseTestingUtility.getAdmin:()Lorg/apache/hadoop/hbase/client/Admin;
     217: aload_1
     218: invokeinterface #47,  1           // InterfaceMethod org/apache/hadoop/hbase/client/Table.getName:()Lorg/apache/hadoop/hbase/TableName;
     223: invokeinterface #48,  2           // InterfaceMethod org/apache/hadoop/hbase/client/Admin.flush:(Lorg/apache/hadoop/hbase/TableName;)V
     228: aload_1
     229: new           #38                 // class org/apache/hadoop/hbase/client/Delete
     232: dup
     233: getstatic     #24                 // Field ROW:[B
     236: invokespecial #39                 // Method org/apache/hadoop/hbase/client/Delete."<init>":([B)V
     239: getstatic     #13                 // Field FAMILY:[B
     242: getstatic     #26                 // Field col1:[B
     245: invokevirtual #101                // Method org/apache/hadoop/hbase/client/Delete.addColumn:([B[B)Lorg/apache/hadoop/hbase/client/Delete;
     248: invokeinterface #43,  2           // InterfaceMethod org/apache/hadoop/hbase/client/Table.delete:(Lorg/apache/hadoop/hbase/client/Delete;)V
     253: aload_1
     254: ifnull        332
     257: aload_2
     258: ifnull        279
     261: aload_1
     262: invokeinterface #57,  1           // InterfaceMethod org/apache/hadoop/hbase/client/Table.close:()V
     267: goto          332
     270: astore_3
     271: aload_2
     272: aload_3
     273: invokevirtual #59                 // Method java/lang/Throwable.addSuppressed:(Ljava/lang/Throwable;)V
     276: goto          332
     279: aload_1
     280: invokeinterface #57,  1           // InterfaceMethod org/apache/hadoop/hbase/client/Table.close:()V
     285: goto          332
     288: astore_3
     289: aload_3
     290: astore_2
     291: aload_3
     292: athrow
     293: astore        4
     295: aload_1
     296: ifnull        329
     299: aload_2
     300: ifnull        323
     303: aload_1
     304: invokeinterface #57,  1           // InterfaceMethod org/apache/hadoop/hbase/client/Table.close:()V
     309: goto          329
     312: astore        5
     314: aload_2
     315: aload         5
     317: invokevirtual #59                 // Method java/lang/Throwable.addSuppressed:(Ljava/lang/Throwable;)V
     320: goto          329
     323: aload_1
     324: invokeinterface #57,  1           // InterfaceMethod org/apache/hadoop/hbase/client/Table.close:()V
     329: aload         4
     331: athrow
     332: return
    Exception table:
       from    to  target type
         261   267   270   Class java/lang/Throwable
           7   253   288   Class java/lang/Throwable
           7   253   293   any
         303   309   312   Class java/lang/Throwable
         288   295   293   any

  public void testRawScanAndMajorCompaction() throws java.io.IOException;
    Code:
       0: aload_0
       1: invokespecial #22                 // Method createTable:()Lorg/apache/hadoop/hbase/client/Table;
       4: astore_1
       5: aconst_null
       6: astore_2
       7: aload_1
       8: new           #23                 // class org/apache/hadoop/hbase/client/Put
      11: dup
      12: getstatic     #24                 // Field ROW:[B
      15: invokespecial #25                 // Method org/apache/hadoop/hbase/client/Put."<init>":([B)V
      18: getstatic     #13                 // Field FAMILY:[B
      21: getstatic     #26                 // Field col1:[B
      24: ldc2_w        #27                 // long 1000001l
      27: getstatic     #29                 // Field value:[B
      30: invokevirtual #30                 // Method org/apache/hadoop/hbase/client/Put.addColumn:([B[BJ[B)Lorg/apache/hadoop/hbase/client/Put;
      33: invokeinterface #31,  2           // InterfaceMethod org/apache/hadoop/hbase/client/Table.put:(Lorg/apache/hadoop/hbase/client/Put;)V
      38: aload_1
      39: new           #23                 // class org/apache/hadoop/hbase/client/Put
      42: dup
      43: getstatic     #24                 // Field ROW:[B
      46: invokespecial #25                 // Method org/apache/hadoop/hbase/client/Put."<init>":([B)V
      49: getstatic     #13                 // Field FAMILY:[B
      52: getstatic     #26                 // Field col1:[B
      55: ldc2_w        #32                 // long 1000002l
      58: getstatic     #29                 // Field value:[B
      61: invokevirtual #30                 // Method org/apache/hadoop/hbase/client/Put.addColumn:([B[BJ[B)Lorg/apache/hadoop/hbase/client/Put;
      64: invokeinterface #31,  2           // InterfaceMethod org/apache/hadoop/hbase/client/Table.put:(Lorg/apache/hadoop/hbase/client/Put;)V
      69: aload_1
      70: new           #23                 // class org/apache/hadoop/hbase/client/Put
      73: dup
      74: getstatic     #24                 // Field ROW:[B
      77: invokespecial #25                 // Method org/apache/hadoop/hbase/client/Put."<init>":([B)V
      80: getstatic     #13                 // Field FAMILY:[B
      83: getstatic     #26                 // Field col1:[B
      86: ldc2_w        #34                 // long 1000003l
      89: getstatic     #29                 // Field value:[B
      92: invokevirtual #30                 // Method org/apache/hadoop/hbase/client/Put.addColumn:([B[BJ[B)Lorg/apache/hadoop/hbase/client/Put;
      95: invokeinterface #31,  2           // InterfaceMethod org/apache/hadoop/hbase/client/Table.put:(Lorg/apache/hadoop/hbase/client/Put;)V
     100: aload_1
     101: new           #23                 // class org/apache/hadoop/hbase/client/Put
     104: dup
     105: getstatic     #24                 // Field ROW:[B
     108: invokespecial #25                 // Method org/apache/hadoop/hbase/client/Put."<init>":([B)V
     111: getstatic     #13                 // Field FAMILY:[B
     114: getstatic     #26                 // Field col1:[B
     117: ldc2_w        #36                 // long 1000004l
     120: getstatic     #29                 // Field value:[B
     123: invokevirtual #30                 // Method org/apache/hadoop/hbase/client/Put.addColumn:([B[BJ[B)Lorg/apache/hadoop/hbase/client/Put;
     126: invokeinterface #31,  2           // InterfaceMethod org/apache/hadoop/hbase/client/Table.put:(Lorg/apache/hadoop/hbase/client/Put;)V
     131: aload_1
     132: new           #38                 // class org/apache/hadoop/hbase/client/Delete
     135: dup
     136: getstatic     #24                 // Field ROW:[B
     139: invokespecial #39                 // Method org/apache/hadoop/hbase/client/Delete."<init>":([B)V
     142: getstatic     #13                 // Field FAMILY:[B
     145: getstatic     #26                 // Field col1:[B
     148: ldc2_w        #36                 // long 1000004l
     151: invokevirtual #60                 // Method org/apache/hadoop/hbase/client/Delete.addColumn:([B[BJ)Lorg/apache/hadoop/hbase/client/Delete;
     154: invokeinterface #43,  2           // InterfaceMethod org/apache/hadoop/hbase/client/Table.delete:(Lorg/apache/hadoop/hbase/client/Delete;)V
     159: aload_1
     160: new           #38                 // class org/apache/hadoop/hbase/client/Delete
     163: dup
     164: getstatic     #24                 // Field ROW:[B
     167: invokespecial #39                 // Method org/apache/hadoop/hbase/client/Delete."<init>":([B)V
     170: getstatic     #13                 // Field FAMILY:[B
     173: getstatic     #26                 // Field col1:[B
     176: ldc2_w        #34                 // long 1000003l
     179: invokevirtual #60                 // Method org/apache/hadoop/hbase/client/Delete.addColumn:([B[BJ)Lorg/apache/hadoop/hbase/client/Delete;
     182: invokeinterface #43,  2           // InterfaceMethod org/apache/hadoop/hbase/client/Table.delete:(Lorg/apache/hadoop/hbase/client/Delete;)V
     187: aload_1
     188: new           #102                // class org/apache/hadoop/hbase/client/Scan
     191: dup
     192: invokespecial #103                // Method org/apache/hadoop/hbase/client/Scan."<init>":()V
     195: iconst_1
     196: invokevirtual #104                // Method org/apache/hadoop/hbase/client/Scan.setRaw:(Z)Lorg/apache/hadoop/hbase/client/Scan;
     199: invokevirtual #105                // Method org/apache/hadoop/hbase/client/Scan.setMaxVersions:()Lorg/apache/hadoop/hbase/client/Scan;
     202: invokeinterface #106,  2          // InterfaceMethod org/apache/hadoop/hbase/client/Table.getScanner:(Lorg/apache/hadoop/hbase/client/Scan;)Lorg/apache/hadoop/hbase/client/ResultScanner;
     207: astore_3
     208: aconst_null
     209: astore        4
     211: aload_3
     212: invokeinterface #107,  1          // InterfaceMethod org/apache/hadoop/hbase/client/ResultScanner.next:()Lorg/apache/hadoop/hbase/client/Result;
     217: astore        5
     219: aload_3
     220: invokeinterface #107,  1          // InterfaceMethod org/apache/hadoop/hbase/client/ResultScanner.next:()Lorg/apache/hadoop/hbase/client/Result;
     225: invokestatic  #108                // Method org/junit/Assert.assertNull:(Ljava/lang/Object;)V
     228: ldc2_w        #75                 // long 6l
     231: aload         5
     233: invokevirtual #53                 // Method org/apache/hadoop/hbase/client/Result.size:()I
     236: i2l
     237: invokestatic  #54                 // Method org/junit/Assert.assertEquals:(JJ)V
     240: aload_3
     241: ifnull        329
     244: aload         4
     246: ifnull        270
     249: aload_3
     250: invokeinterface #109,  1          // InterfaceMethod org/apache/hadoop/hbase/client/ResultScanner.close:()V
     255: goto          329
     258: astore        5
     260: aload         4
     262: aload         5
     264: invokevirtual #59                 // Method java/lang/Throwable.addSuppressed:(Ljava/lang/Throwable;)V
     267: goto          329
     270: aload_3
     271: invokeinterface #109,  1          // InterfaceMethod org/apache/hadoop/hbase/client/ResultScanner.close:()V
     276: goto          329
     279: astore        5
     281: aload         5
     283: astore        4
     285: aload         5
     287: athrow
     288: astore        6
     290: aload_3
     291: ifnull        326
     294: aload         4
     296: ifnull        320
     299: aload_3
     300: invokeinterface #109,  1          // InterfaceMethod org/apache/hadoop/hbase/client/ResultScanner.close:()V
     305: goto          326
     308: astore        7
     310: aload         4
     312: aload         7
     314: invokevirtual #59                 // Method java/lang/Throwable.addSuppressed:(Ljava/lang/Throwable;)V
     317: goto          326
     320: aload_3
     321: invokeinterface #109,  1          // InterfaceMethod org/apache/hadoop/hbase/client/ResultScanner.close:()V
     326: aload         6
     328: athrow
     329: getstatic     #5                  // Field TEST_UTIL:Lorg/apache/hadoop/hbase/HBaseTestingUtility;
     332: invokevirtual #46                 // Method org/apache/hadoop/hbase/HBaseTestingUtility.getAdmin:()Lorg/apache/hadoop/hbase/client/Admin;
     335: aload_1
     336: invokeinterface #47,  1           // InterfaceMethod org/apache/hadoop/hbase/client/Table.getName:()Lorg/apache/hadoop/hbase/TableName;
     341: invokeinterface #48,  2           // InterfaceMethod org/apache/hadoop/hbase/client/Admin.flush:(Lorg/apache/hadoop/hbase/TableName;)V
     346: aload_1
     347: new           #102                // class org/apache/hadoop/hbase/client/Scan
     350: dup
     351: invokespecial #103                // Method org/apache/hadoop/hbase/client/Scan."<init>":()V
     354: iconst_1
     355: invokevirtual #104                // Method org/apache/hadoop/hbase/client/Scan.setRaw:(Z)Lorg/apache/hadoop/hbase/client/Scan;
     358: invokevirtual #105                // Method org/apache/hadoop/hbase/client/Scan.setMaxVersions:()Lorg/apache/hadoop/hbase/client/Scan;
     361: invokeinterface #106,  2          // InterfaceMethod org/apache/hadoop/hbase/client/Table.getScanner:(Lorg/apache/hadoop/hbase/client/Scan;)Lorg/apache/hadoop/hbase/client/ResultScanner;
     366: astore_3
     367: aconst_null
     368: astore        4
     370: aload_3
     371: invokeinterface #107,  1          // InterfaceMethod org/apache/hadoop/hbase/client/ResultScanner.next:()Lorg/apache/hadoop/hbase/client/Result;
     376: astore        5
     378: aload_3
     379: invokeinterface #107,  1          // InterfaceMethod org/apache/hadoop/hbase/client/ResultScanner.next:()Lorg/apache/hadoop/hbase/client/Result;
     384: invokestatic  #108                // Method org/junit/Assert.assertNull:(Ljava/lang/Object;)V
     387: ldc2_w        #75                 // long 6l
     390: aload         5
     392: invokevirtual #53                 // Method org/apache/hadoop/hbase/client/Result.size:()I
     395: i2l
     396: invokestatic  #54                 // Method org/junit/Assert.assertEquals:(JJ)V
     399: aload_3
     400: ifnull        488
     403: aload         4
     405: ifnull        429
     408: aload_3
     409: invokeinterface #109,  1          // InterfaceMethod org/apache/hadoop/hbase/client/ResultScanner.close:()V
     414: goto          488
     417: astore        5
     419: aload         4
     421: aload         5
     423: invokevirtual #59                 // Method java/lang/Throwable.addSuppressed:(Ljava/lang/Throwable;)V
     426: goto          488
     429: aload_3
     430: invokeinterface #109,  1          // InterfaceMethod org/apache/hadoop/hbase/client/ResultScanner.close:()V
     435: goto          488
     438: astore        5
     440: aload         5
     442: astore        4
     444: aload         5
     446: athrow
     447: astore        8
     449: aload_3
     450: ifnull        485
     453: aload         4
     455: ifnull        479
     458: aload_3
     459: invokeinterface #109,  1          // InterfaceMethod org/apache/hadoop/hbase/client/ResultScanner.close:()V
     464: goto          485
     467: astore        9
     469: aload         4
     471: aload         9
     473: invokevirtual #59                 // Method java/lang/Throwable.addSuppressed:(Ljava/lang/Throwable;)V
     476: goto          485
     479: aload_3
     480: invokeinterface #109,  1          // InterfaceMethod org/apache/hadoop/hbase/client/ResultScanner.close:()V
     485: aload         8
     487: athrow
     488: getstatic     #5                  // Field TEST_UTIL:Lorg/apache/hadoop/hbase/HBaseTestingUtility;
     491: invokevirtual #46                 // Method org/apache/hadoop/hbase/HBaseTestingUtility.getAdmin:()Lorg/apache/hadoop/hbase/client/Admin;
     494: aload_1
     495: invokeinterface #47,  1           // InterfaceMethod org/apache/hadoop/hbase/client/Table.getName:()Lorg/apache/hadoop/hbase/TableName;
     500: invokeinterface #110,  2          // InterfaceMethod org/apache/hadoop/hbase/client/Admin.majorCompact:(Lorg/apache/hadoop/hbase/TableName;)V
     505: ldc2_w        #111                // long 5000l
     508: invokestatic  #113                // Method org/apache/hadoop/hbase/util/Threads.sleep:(J)V
     511: aload_1
     512: new           #102                // class org/apache/hadoop/hbase/client/Scan
     515: dup
     516: invokespecial #103                // Method org/apache/hadoop/hbase/client/Scan."<init>":()V
     519: iconst_1
     520: invokevirtual #104                // Method org/apache/hadoop/hbase/client/Scan.setRaw:(Z)Lorg/apache/hadoop/hbase/client/Scan;
     523: invokevirtual #105                // Method org/apache/hadoop/hbase/client/Scan.setMaxVersions:()Lorg/apache/hadoop/hbase/client/Scan;
     526: invokeinterface #106,  2          // InterfaceMethod org/apache/hadoop/hbase/client/Table.getScanner:(Lorg/apache/hadoop/hbase/client/Scan;)Lorg/apache/hadoop/hbase/client/ResultScanner;
     531: astore_3
     532: aconst_null
     533: astore        4
     535: aload_3
     536: invokeinterface #107,  1          // InterfaceMethod org/apache/hadoop/hbase/client/ResultScanner.next:()Lorg/apache/hadoop/hbase/client/Result;
     541: astore        5
     543: aload_3
     544: invokeinterface #107,  1          // InterfaceMethod org/apache/hadoop/hbase/client/ResultScanner.next:()Lorg/apache/hadoop/hbase/client/Result;
     549: invokestatic  #108                // Method org/junit/Assert.assertNull:(Ljava/lang/Object;)V
     552: lconst_1
     553: aload         5
     555: invokevirtual #53                 // Method org/apache/hadoop/hbase/client/Result.size:()I
     558: i2l
     559: invokestatic  #54                 // Method org/junit/Assert.assertEquals:(JJ)V
     562: ldc2_w        #32                 // long 1000002l
     565: aload         5
     567: invokevirtual #55                 // Method org/apache/hadoop/hbase/client/Result.rawCells:()[Lorg/apache/hadoop/hbase/Cell;
     570: iconst_0
     571: aaload
     572: invokeinterface #56,  1           // InterfaceMethod org/apache/hadoop/hbase/Cell.getTimestamp:()J
     577: invokestatic  #54                 // Method org/junit/Assert.assertEquals:(JJ)V
     580: aload_3
     581: ifnull        669
     584: aload         4
     586: ifnull        610
     589: aload_3
     590: invokeinterface #109,  1          // InterfaceMethod org/apache/hadoop/hbase/client/ResultScanner.close:()V
     595: goto          669
     598: astore        5
     600: aload         4
     602: aload         5
     604: invokevirtual #59                 // Method java/lang/Throwable.addSuppressed:(Ljava/lang/Throwable;)V
     607: goto          669
     610: aload_3
     611: invokeinterface #109,  1          // InterfaceMethod org/apache/hadoop/hbase/client/ResultScanner.close:()V
     616: goto          669
     619: astore        5
     621: aload         5
     623: astore        4
     625: aload         5
     627: athrow
     628: astore        10
     630: aload_3
     631: ifnull        666
     634: aload         4
     636: ifnull        660
     639: aload_3
     640: invokeinterface #109,  1          // InterfaceMethod org/apache/hadoop/hbase/client/ResultScanner.close:()V
     645: goto          666
     648: astore        11
     650: aload         4
     652: aload         11
     654: invokevirtual #59                 // Method java/lang/Throwable.addSuppressed:(Ljava/lang/Throwable;)V
     657: goto          666
     660: aload_3
     661: invokeinterface #109,  1          // InterfaceMethod org/apache/hadoop/hbase/client/ResultScanner.close:()V
     666: aload         10
     668: athrow
     669: aload_1
     670: ifnull        748
     673: aload_2
     674: ifnull        695
     677: aload_1
     678: invokeinterface #57,  1           // InterfaceMethod org/apache/hadoop/hbase/client/Table.close:()V
     683: goto          748
     686: astore_3
     687: aload_2
     688: aload_3
     689: invokevirtual #59                 // Method java/lang/Throwable.addSuppressed:(Ljava/lang/Throwable;)V
     692: goto          748
     695: aload_1
     696: invokeinterface #57,  1           // InterfaceMethod org/apache/hadoop/hbase/client/Table.close:()V
     701: goto          748
     704: astore_3
     705: aload_3
     706: astore_2
     707: aload_3
     708: athrow
     709: astore        12
     711: aload_1
     712: ifnull        745
     715: aload_2
     716: ifnull        739
     719: aload_1
     720: invokeinterface #57,  1           // InterfaceMethod org/apache/hadoop/hbase/client/Table.close:()V
     725: goto          745
     728: astore        13
     730: aload_2
     731: aload         13
     733: invokevirtual #59                 // Method java/lang/Throwable.addSuppressed:(Ljava/lang/Throwable;)V
     736: goto          745
     739: aload_1
     740: invokeinterface #57,  1           // InterfaceMethod org/apache/hadoop/hbase/client/Table.close:()V
     745: aload         12
     747: athrow
     748: return
    Exception table:
       from    to  target type
         249   255   258   Class java/lang/Throwable
         211   240   279   Class java/lang/Throwable
         211   240   288   any
         299   305   308   Class java/lang/Throwable
         279   290   288   any
         408   414   417   Class java/lang/Throwable
         370   399   438   Class java/lang/Throwable
         370   399   447   any
         458   464   467   Class java/lang/Throwable
         438   449   447   any
         589   595   598   Class java/lang/Throwable
         535   580   619   Class java/lang/Throwable
         535   580   628   any
         639   645   648   Class java/lang/Throwable
         619   630   628   any
         677   683   686   Class java/lang/Throwable
           7   669   704   Class java/lang/Throwable
           7   669   709   any
         719   725   728   Class java/lang/Throwable
         704   711   709   any

  static {};
    Code:
       0: ldc           #114                // class org/apache/hadoop/hbase/regionserver/TestNewVersionBehaviorFromClientSide
       2: invokestatic  #115                // Method org/apache/hadoop/hbase/HBaseClassTestRule.forClass:(Ljava/lang/Class;)Lorg/apache/hadoop/hbase/HBaseClassTestRule;
       5: putstatic     #116                // Field CLASS_RULE:Lorg/apache/hadoop/hbase/HBaseClassTestRule;
       8: new           #117                // class org/apache/hadoop/hbase/HBaseTestingUtility
      11: dup
      12: invokespecial #118                // Method org/apache/hadoop/hbase/HBaseTestingUtility."<init>":()V
      15: putstatic     #5                  // Field TEST_UTIL:Lorg/apache/hadoop/hbase/HBaseTestingUtility;
      18: ldc           #119                // String r1
      20: invokestatic  #120                // Method org/apache/hadoop/hbase/util/Bytes.toBytes:(Ljava/lang/String;)[B
      23: putstatic     #24                 // Field ROW:[B
      26: ldc           #121                // String r2
      28: invokestatic  #120                // Method org/apache/hadoop/hbase/util/Bytes.toBytes:(Ljava/lang/String;)[B
      31: putstatic     #100                // Field ROW2:[B
      34: ldc           #122                // String f
      36: invokestatic  #120                // Method org/apache/hadoop/hbase/util/Bytes.toBytes:(Ljava/lang/String;)[B
      39: putstatic     #13                 // Field FAMILY:[B
      42: ldc           #123                // String value
      44: invokestatic  #120                // Method org/apache/hadoop/hbase/util/Bytes.toBytes:(Ljava/lang/String;)[B
      47: putstatic     #29                 // Field value:[B
      50: ldc           #124                // String col1
      52: invokestatic  #120                // Method org/apache/hadoop/hbase/util/Bytes.toBytes:(Ljava/lang/String;)[B
      55: putstatic     #26                 // Field col1:[B
      58: ldc           #125                // String col2
      60: invokestatic  #120                // Method org/apache/hadoop/hbase/util/Bytes.toBytes:(Ljava/lang/String;)[B
      63: putstatic     #65                 // Field col2:[B
      66: ldc           #126                // String col3
      68: invokestatic  #120                // Method org/apache/hadoop/hbase/util/Bytes.toBytes:(Ljava/lang/String;)[B
      71: putstatic     #66                 // Field col3:[B
      74: return
}
