Compiled from "TestSuperUserQuotaPermissions.java"
class org.apache.hadoop.hbase.quotas.TestSuperUserQuotaPermissions$9 implements java.security.PrivilegedExceptionAction<T> {
  final java.util.concurrent.Callable val$task;

  final org.apache.hadoop.hbase.quotas.TestSuperUserQuotaPermissions this$0;

  org.apache.hadoop.hbase.quotas.TestSuperUserQuotaPermissions$9(org.apache.hadoop.hbase.quotas.TestSuperUserQuotaPermissions, java.util.concurrent.Callable);
    Code:
       0: aload_0
       1: aload_1
       2: putfield      #1                  // Field this$0:Lorg/apache/hadoop/hbase/quotas/TestSuperUserQuotaPermissions;
       5: aload_0
       6: aload_2
       7: putfield      #2                  // Field val$task:Ljava/util/concurrent/Callable;
      10: aload_0
      11: invokespecial #3                  // Method java/lang/Object."<init>":()V
      14: return

  public T run() throws java.lang.Exception;
    Code:
       0: aload_0
       1: getfield      #2                  // Field val$task:Ljava/util/concurrent/Callable;
       4: invokeinterface #4,  1            // InterfaceMethod java/util/concurrent/Callable.call:()Ljava/lang/Object;
       9: areturn
}
