Compiled from "TestIncrement.java"
public class org.apache.hadoop.hbase.client.TestIncrement {
  public static final org.apache.hadoop.hbase.HBaseClassTestRule CLASS_RULE;

  public org.apache.hadoop.hbase.client.TestIncrement();
    Code:
       0: aload_0
       1: invokespecial #1                  // Method java/lang/Object."<init>":()V
       4: return

  public void testIncrementInstance();
    Code:
       0: ldc2_w        #2                  // long 13l
       3: lstore_1
       4: new           #4                  // class org/apache/hadoop/hbase/client/Increment
       7: dup
       8: iconst_1
       9: newarray       byte
      11: dup
      12: iconst_0
      13: bipush        114
      15: bastore
      16: invokespecial #5                  // Method org/apache/hadoop/hbase/client/Increment."<init>":([B)V
      19: astore_3
      20: iconst_0
      21: istore        4
      23: iconst_0
      24: istore        5
      26: iload         5
      28: iconst_2
      29: if_icmpge     60
      32: iload         5
      34: invokestatic  #6                  // Method org/apache/hadoop/hbase/util/Bytes.toBytes:(I)[B
      37: astore        6
      39: aload_3
      40: aload         6
      42: aload         6
      44: ldc2_w        #2                  // long 13l
      47: invokevirtual #7                  // Method org/apache/hadoop/hbase/client/Increment.addColumn:([B[BJ)Lorg/apache/hadoop/hbase/client/Increment;
      50: pop
      51: iinc          4, 1
      54: iinc          5, 1
      57: goto          26
      60: aload_3
      61: invokevirtual #8                  // Method org/apache/hadoop/hbase/client/Increment.getFamilyMapOfLongs:()Ljava/util/Map;
      64: astore        5
      66: iconst_0
      67: istore        6
      69: aload         5
      71: invokeinterface #9,  1            // InterfaceMethod java/util/Map.entrySet:()Ljava/util/Set;
      76: invokeinterface #10,  1           // InterfaceMethod java/util/Set.iterator:()Ljava/util/Iterator;
      81: astore        7
      83: aload         7
      85: invokeinterface #11,  1           // InterfaceMethod java/util/Iterator.hasNext:()Z
      90: ifeq          177
      93: aload         7
      95: invokeinterface #12,  1           // InterfaceMethod java/util/Iterator.next:()Ljava/lang/Object;
     100: checkcast     #13                 // class java/util/Map$Entry
     103: astore        8
     105: aload         8
     107: invokeinterface #14,  1           // InterfaceMethod java/util/Map$Entry.getValue:()Ljava/lang/Object;
     112: checkcast     #15                 // class java/util/NavigableMap
     115: invokeinterface #16,  1           // InterfaceMethod java/util/NavigableMap.entrySet:()Ljava/util/Set;
     120: invokeinterface #10,  1           // InterfaceMethod java/util/Set.iterator:()Ljava/util/Iterator;
     125: astore        9
     127: aload         9
     129: invokeinterface #11,  1           // InterfaceMethod java/util/Iterator.hasNext:()Z
     134: ifeq          174
     137: aload         9
     139: invokeinterface #12,  1           // InterfaceMethod java/util/Iterator.next:()Ljava/lang/Object;
     144: checkcast     #13                 // class java/util/Map$Entry
     147: astore        10
     149: ldc2_w        #2                  // long 13l
     152: aload         10
     154: invokeinterface #14,  1           // InterfaceMethod java/util/Map$Entry.getValue:()Ljava/lang/Object;
     159: checkcast     #17                 // class java/lang/Long
     162: invokevirtual #18                 // Method java/lang/Long.longValue:()J
     165: invokestatic  #19                 // Method org/junit/Assert.assertEquals:(JJ)V
     168: iinc          6, 1
     171: goto          127
     174: goto          83
     177: iload         4
     179: i2l
     180: iload         6
     182: i2l
     183: invokestatic  #19                 // Method org/junit/Assert.assertEquals:(JJ)V
     186: return

  static {};
    Code:
       0: ldc           #20                 // class org/apache/hadoop/hbase/client/TestIncrement
       2: invokestatic  #21                 // Method org/apache/hadoop/hbase/HBaseClassTestRule.forClass:(Ljava/lang/Class;)Lorg/apache/hadoop/hbase/HBaseClassTestRule;
       5: putstatic     #22                 // Field CLASS_RULE:Lorg/apache/hadoop/hbase/HBaseClassTestRule;
       8: return
}
