Compiled from "TestCompactor.java"
public class org.apache.hadoop.hbase.regionserver.compactions.TestCompactor$StoreFileWritersCapture implements org.mockito.stubbing.Answer<org.apache.hadoop.hbase.regionserver.StoreFileWriter>, org.apache.hadoop.hbase.regionserver.AbstractMultiFileWriter$WriterFactory {
  public org.apache.hadoop.hbase.regionserver.compactions.TestCompactor$StoreFileWritersCapture();
    Code:
       0: aload_0
       1: invokespecial #1                  // Method java/lang/Object."<init>":()V
       4: aload_0
       5: new           #2                  // class java/util/ArrayList
       8: dup
       9: invokespecial #3                  // Method java/util/ArrayList."<init>":()V
      12: putfield      #4                  // Field writers:Ljava/util/List;
      15: return

  public org.apache.hadoop.hbase.regionserver.StoreFileWriter createWriter() throws java.io.IOException;
    Code:
       0: new           #5                  // class org/apache/hadoop/hbase/regionserver/compactions/TestCompactor$StoreFileWritersCapture$Writer
       3: dup
       4: invokespecial #6                  // Method org/apache/hadoop/hbase/regionserver/compactions/TestCompactor$StoreFileWritersCapture$Writer."<init>":()V
       7: astore_1
       8: aload_0
       9: getfield      #4                  // Field writers:Ljava/util/List;
      12: aload_1
      13: invokeinterface #7,  2            // InterfaceMethod java/util/List.add:(Ljava/lang/Object;)Z
      18: pop
      19: ldc           #8                  // class org/apache/hadoop/hbase/regionserver/StoreFileWriter
      21: invokestatic  #9                  // Method org/mockito/Mockito.mock:(Ljava/lang/Class;)Ljava/lang/Object;
      24: checkcast     #8                  // class org/apache/hadoop/hbase/regionserver/StoreFileWriter
      27: astore_2
      28: new           #10                 // class org/apache/hadoop/hbase/regionserver/compactions/TestCompactor$StoreFileWritersCapture$1
      31: dup
      32: aload_0
      33: aload_1
      34: invokespecial #11                 // Method org/apache/hadoop/hbase/regionserver/compactions/TestCompactor$StoreFileWritersCapture$1."<init>":(Lorg/apache/hadoop/hbase/regionserver/compactions/TestCompactor$StoreFileWritersCapture;Lorg/apache/hadoop/hbase/regionserver/compactions/TestCompactor$StoreFileWritersCapture$Writer;)V
      37: invokestatic  #12                 // Method org/mockito/Mockito.doAnswer:(Lorg/mockito/stubbing/Answer;)Lorg/mockito/stubbing/Stubber;
      40: aload_2
      41: invokeinterface #13,  2           // InterfaceMethod org/mockito/stubbing/Stubber.when:(Ljava/lang/Object;)Ljava/lang/Object;
      46: checkcast     #8                  // class org/apache/hadoop/hbase/regionserver/StoreFileWriter
      49: invokestatic  #14                 // Method org/mockito/Matchers.any:()Ljava/lang/Object;
      52: checkcast     #15                 // class org/apache/hadoop/hbase/Cell
      55: invokevirtual #16                 // Method org/apache/hadoop/hbase/regionserver/StoreFileWriter.append:(Lorg/apache/hadoop/hbase/Cell;)V
      58: new           #17                 // class org/apache/hadoop/hbase/regionserver/compactions/TestCompactor$StoreFileWritersCapture$2
      61: dup
      62: aload_0
      63: aload_1
      64: invokespecial #18                 // Method org/apache/hadoop/hbase/regionserver/compactions/TestCompactor$StoreFileWritersCapture$2."<init>":(Lorg/apache/hadoop/hbase/regionserver/compactions/TestCompactor$StoreFileWritersCapture;Lorg/apache/hadoop/hbase/regionserver/compactions/TestCompactor$StoreFileWritersCapture$Writer;)V
      67: invokestatic  #12                 // Method org/mockito/Mockito.doAnswer:(Lorg/mockito/stubbing/Answer;)Lorg/mockito/stubbing/Stubber;
      70: aload_2
      71: invokeinterface #13,  2           // InterfaceMethod org/mockito/stubbing/Stubber.when:(Ljava/lang/Object;)Ljava/lang/Object;
      76: checkcast     #8                  // class org/apache/hadoop/hbase/regionserver/StoreFileWriter
      79: invokestatic  #14                 // Method org/mockito/Matchers.any:()Ljava/lang/Object;
      82: checkcast     #19                 // class "[B"
      85: invokestatic  #14                 // Method org/mockito/Matchers.any:()Ljava/lang/Object;
      88: checkcast     #19                 // class "[B"
      91: invokevirtual #20                 // Method org/apache/hadoop/hbase/regionserver/StoreFileWriter.appendFileInfo:([B[B)V
      94: new           #21                 // class org/apache/hadoop/hbase/regionserver/compactions/TestCompactor$StoreFileWritersCapture$3
      97: dup
      98: aload_0
      99: aload_1
     100: invokespecial #22                 // Method org/apache/hadoop/hbase/regionserver/compactions/TestCompactor$StoreFileWritersCapture$3."<init>":(Lorg/apache/hadoop/hbase/regionserver/compactions/TestCompactor$StoreFileWritersCapture;Lorg/apache/hadoop/hbase/regionserver/compactions/TestCompactor$StoreFileWritersCapture$Writer;)V
     103: invokestatic  #12                 // Method org/mockito/Mockito.doAnswer:(Lorg/mockito/stubbing/Answer;)Lorg/mockito/stubbing/Stubber;
     106: aload_2
     107: invokeinterface #13,  2           // InterfaceMethod org/mockito/stubbing/Stubber.when:(Ljava/lang/Object;)Ljava/lang/Object;
     112: checkcast     #8                  // class org/apache/hadoop/hbase/regionserver/StoreFileWriter
     115: invokestatic  #23                 // Method org/mockito/Matchers.anyLong:()J
     118: invokestatic  #24                 // Method org/mockito/Matchers.anyBoolean:()Z
     121: invokevirtual #25                 // Method org/apache/hadoop/hbase/regionserver/StoreFileWriter.appendMetadata:(JZ)V
     124: new           #26                 // class org/apache/hadoop/hbase/regionserver/compactions/TestCompactor$StoreFileWritersCapture$4
     127: dup
     128: aload_0
     129: aload_1
     130: invokespecial #27                 // Method org/apache/hadoop/hbase/regionserver/compactions/TestCompactor$StoreFileWritersCapture$4."<init>":(Lorg/apache/hadoop/hbase/regionserver/compactions/TestCompactor$StoreFileWritersCapture;Lorg/apache/hadoop/hbase/regionserver/compactions/TestCompactor$StoreFileWritersCapture$Writer;)V
     133: invokestatic  #12                 // Method org/mockito/Mockito.doAnswer:(Lorg/mockito/stubbing/Answer;)Lorg/mockito/stubbing/Stubber;
     136: aload_2
     137: invokeinterface #13,  2           // InterfaceMethod org/mockito/stubbing/Stubber.when:(Ljava/lang/Object;)Ljava/lang/Object;
     142: checkcast     #8                  // class org/apache/hadoop/hbase/regionserver/StoreFileWriter
     145: invokestatic  #23                 // Method org/mockito/Matchers.anyLong:()J
     148: invokestatic  #24                 // Method org/mockito/Matchers.anyBoolean:()Z
     151: invokestatic  #28                 // Method org/mockito/ArgumentMatchers.anyCollection:()Ljava/util/Collection;
     154: invokevirtual #29                 // Method org/apache/hadoop/hbase/regionserver/StoreFileWriter.appendMetadata:(JZLjava/util/Collection;)V
     157: new           #30                 // class org/apache/hadoop/hbase/regionserver/compactions/TestCompactor$StoreFileWritersCapture$5
     160: dup
     161: aload_0
     162: invokespecial #31                 // Method org/apache/hadoop/hbase/regionserver/compactions/TestCompactor$StoreFileWritersCapture$5."<init>":(Lorg/apache/hadoop/hbase/regionserver/compactions/TestCompactor$StoreFileWritersCapture;)V
     165: invokestatic  #12                 // Method org/mockito/Mockito.doAnswer:(Lorg/mockito/stubbing/Answer;)Lorg/mockito/stubbing/Stubber;
     168: aload_2
     169: invokeinterface #13,  2           // InterfaceMethod org/mockito/stubbing/Stubber.when:(Ljava/lang/Object;)Ljava/lang/Object;
     174: checkcast     #8                  // class org/apache/hadoop/hbase/regionserver/StoreFileWriter
     177: invokevirtual #32                 // Method org/apache/hadoop/hbase/regionserver/StoreFileWriter.getPath:()Lorg/apache/hadoop/fs/Path;
     180: pop
     181: aload_2
     182: areturn

  public org.apache.hadoop.hbase.regionserver.StoreFileWriter answer(org.mockito.invocation.InvocationOnMock) throws java.lang.Throwable;
    Code:
       0: aload_0
       1: invokevirtual #33                 // Method createWriter:()Lorg/apache/hadoop/hbase/regionserver/StoreFileWriter;
       4: areturn

  public void verifyKvs(org.apache.hadoop.hbase.KeyValue[][], boolean, boolean);
    Code:
       0: iload_2
       1: ifeq          20
       4: aload_1
       5: arraylength
       6: i2l
       7: aload_0
       8: getfield      #4                  // Field writers:Ljava/util/List;
      11: invokeinterface #34,  1           // InterfaceMethod java/util/List.size:()I
      16: i2l
      17: invokestatic  #35                 // Method org/junit/Assert.assertEquals:(JJ)V
      20: iconst_0
      21: istore        4
      23: iconst_0
      24: istore        5
      26: iload         5
      28: aload_1
      29: arraylength
      30: if_icmpge     193
      33: aload_1
      34: iload         5
      36: aaload
      37: astore        6
      39: aload         6
      41: ifnull        180
      44: aload_0
      45: getfield      #4                  // Field writers:Ljava/util/List;
      48: iload         5
      50: iload         4
      52: isub
      53: invokeinterface #36,  2           // InterfaceMethod java/util/List.get:(I)Ljava/lang/Object;
      58: checkcast     #5                  // class org/apache/hadoop/hbase/regionserver/compactions/TestCompactor$StoreFileWritersCapture$Writer
      61: astore        7
      63: iload_3
      64: ifeq          98
      67: aload         7
      69: getfield      #37                 // Field org/apache/hadoop/hbase/regionserver/compactions/TestCompactor$StoreFileWritersCapture$Writer.data:Ljava/util/TreeMap;
      72: getstatic     #38                 // Field org/apache/hadoop/hbase/regionserver/StripeStoreFileManager.STRIPE_START_KEY:[B
      75: invokevirtual #39                 // Method java/util/TreeMap.get:(Ljava/lang/Object;)Ljava/lang/Object;
      78: invokestatic  #40                 // Method org/junit/Assert.assertNotNull:(Ljava/lang/Object;)V
      81: aload         7
      83: getfield      #37                 // Field org/apache/hadoop/hbase/regionserver/compactions/TestCompactor$StoreFileWritersCapture$Writer.data:Ljava/util/TreeMap;
      86: getstatic     #41                 // Field org/apache/hadoop/hbase/regionserver/StripeStoreFileManager.STRIPE_END_KEY:[B
      89: invokevirtual #39                 // Method java/util/TreeMap.get:(Ljava/lang/Object;)Ljava/lang/Object;
      92: invokestatic  #40                 // Method org/junit/Assert.assertNotNull:(Ljava/lang/Object;)V
      95: goto          126
      98: aload         7
     100: getfield      #37                 // Field org/apache/hadoop/hbase/regionserver/compactions/TestCompactor$StoreFileWritersCapture$Writer.data:Ljava/util/TreeMap;
     103: getstatic     #38                 // Field org/apache/hadoop/hbase/regionserver/StripeStoreFileManager.STRIPE_START_KEY:[B
     106: invokevirtual #39                 // Method java/util/TreeMap.get:(Ljava/lang/Object;)Ljava/lang/Object;
     109: invokestatic  #42                 // Method org/junit/Assert.assertNull:(Ljava/lang/Object;)V
     112: aload         7
     114: getfield      #37                 // Field org/apache/hadoop/hbase/regionserver/compactions/TestCompactor$StoreFileWritersCapture$Writer.data:Ljava/util/TreeMap;
     117: getstatic     #41                 // Field org/apache/hadoop/hbase/regionserver/StripeStoreFileManager.STRIPE_END_KEY:[B
     120: invokevirtual #39                 // Method java/util/TreeMap.get:(Ljava/lang/Object;)Ljava/lang/Object;
     123: invokestatic  #42                 // Method org/junit/Assert.assertNull:(Ljava/lang/Object;)V
     126: aload         6
     128: arraylength
     129: i2l
     130: aload         7
     132: getfield      #43                 // Field org/apache/hadoop/hbase/regionserver/compactions/TestCompactor$StoreFileWritersCapture$Writer.kvs:Ljava/util/ArrayList;
     135: invokevirtual #44                 // Method java/util/ArrayList.size:()I
     138: i2l
     139: invokestatic  #35                 // Method org/junit/Assert.assertEquals:(JJ)V
     142: iconst_0
     143: istore        8
     145: iload         8
     147: aload         6
     149: arraylength
     150: if_icmpge     177
     153: aload         6
     155: iload         8
     157: aaload
     158: aload         7
     160: getfield      #43                 // Field org/apache/hadoop/hbase/regionserver/compactions/TestCompactor$StoreFileWritersCapture$Writer.kvs:Ljava/util/ArrayList;
     163: iload         8
     165: invokevirtual #45                 // Method java/util/ArrayList.get:(I)Ljava/lang/Object;
     168: invokestatic  #46                 // Method org/junit/Assert.assertEquals:(Ljava/lang/Object;Ljava/lang/Object;)V
     171: iinc          8, 1
     174: goto          145
     177: goto          187
     180: iload_2
     181: invokestatic  #47                 // Method org/junit/Assert.assertFalse:(Z)V
     184: iinc          4, 1
     187: iinc          5, 1
     190: goto          26
     193: return

  public void verifyBoundaries(byte[][]);
    Code:
       0: aload_1
       1: arraylength
       2: iconst_1
       3: isub
       4: i2l
       5: aload_0
       6: getfield      #4                  // Field writers:Ljava/util/List;
       9: invokeinterface #34,  1           // InterfaceMethod java/util/List.size:()I
      14: i2l
      15: invokestatic  #35                 // Method org/junit/Assert.assertEquals:(JJ)V
      18: iconst_0
      19: istore_2
      20: iload_2
      21: aload_0
      22: getfield      #4                  // Field writers:Ljava/util/List;
      25: invokeinterface #34,  1           // InterfaceMethod java/util/List.size:()I
      30: if_icmpge     141
      33: new           #48                 // class java/lang/StringBuilder
      36: dup
      37: invokespecial #49                 // Method java/lang/StringBuilder."<init>":()V
      40: ldc           #50                 // String i =
      42: invokevirtual #51                 // Method java/lang/StringBuilder.append:(Ljava/lang/String;)Ljava/lang/StringBuilder;
      45: iload_2
      46: invokevirtual #52                 // Method java/lang/StringBuilder.append:(I)Ljava/lang/StringBuilder;
      49: invokevirtual #53                 // Method java/lang/StringBuilder.toString:()Ljava/lang/String;
      52: aload_1
      53: iload_2
      54: aaload
      55: aload_0
      56: getfield      #4                  // Field writers:Ljava/util/List;
      59: iload_2
      60: invokeinterface #36,  2           // InterfaceMethod java/util/List.get:(I)Ljava/lang/Object;
      65: checkcast     #5                  // class org/apache/hadoop/hbase/regionserver/compactions/TestCompactor$StoreFileWritersCapture$Writer
      68: getfield      #37                 // Field org/apache/hadoop/hbase/regionserver/compactions/TestCompactor$StoreFileWritersCapture$Writer.data:Ljava/util/TreeMap;
      71: getstatic     #38                 // Field org/apache/hadoop/hbase/regionserver/StripeStoreFileManager.STRIPE_START_KEY:[B
      74: invokevirtual #39                 // Method java/util/TreeMap.get:(Ljava/lang/Object;)Ljava/lang/Object;
      77: checkcast     #19                 // class "[B"
      80: invokestatic  #54                 // Method org/junit/Assert.assertArrayEquals:(Ljava/lang/String;[B[B)V
      83: new           #48                 // class java/lang/StringBuilder
      86: dup
      87: invokespecial #49                 // Method java/lang/StringBuilder."<init>":()V
      90: ldc           #50                 // String i =
      92: invokevirtual #51                 // Method java/lang/StringBuilder.append:(Ljava/lang/String;)Ljava/lang/StringBuilder;
      95: iload_2
      96: invokevirtual #52                 // Method java/lang/StringBuilder.append:(I)Ljava/lang/StringBuilder;
      99: invokevirtual #53                 // Method java/lang/StringBuilder.toString:()Ljava/lang/String;
     102: aload_1
     103: iload_2
     104: iconst_1
     105: iadd
     106: aaload
     107: aload_0
     108: getfield      #4                  // Field writers:Ljava/util/List;
     111: iload_2
     112: invokeinterface #36,  2           // InterfaceMethod java/util/List.get:(I)Ljava/lang/Object;
     117: checkcast     #5                  // class org/apache/hadoop/hbase/regionserver/compactions/TestCompactor$StoreFileWritersCapture$Writer
     120: getfield      #37                 // Field org/apache/hadoop/hbase/regionserver/compactions/TestCompactor$StoreFileWritersCapture$Writer.data:Ljava/util/TreeMap;
     123: getstatic     #41                 // Field org/apache/hadoop/hbase/regionserver/StripeStoreFileManager.STRIPE_END_KEY:[B
     126: invokevirtual #39                 // Method java/util/TreeMap.get:(Ljava/lang/Object;)Ljava/lang/Object;
     129: checkcast     #19                 // class "[B"
     132: invokestatic  #54                 // Method org/junit/Assert.assertArrayEquals:(Ljava/lang/String;[B[B)V
     135: iinc          2, 1
     138: goto          20
     141: return

  public void verifyKvs(org.apache.hadoop.hbase.KeyValue[][], boolean, java.util.List<java.lang.Long>);
    Code:
       0: iload_2
       1: ifeq          20
       4: aload_1
       5: arraylength
       6: i2l
       7: aload_0
       8: getfield      #4                  // Field writers:Ljava/util/List;
      11: invokeinterface #34,  1           // InterfaceMethod java/util/List.size:()I
      16: i2l
      17: invokestatic  #35                 // Method org/junit/Assert.assertEquals:(JJ)V
      20: iconst_0
      21: istore        4
      23: iconst_0
      24: istore        5
      26: iload         5
      28: aload_1
      29: arraylength
      30: if_icmpge     200
      33: aload_1
      34: iload         5
      36: aaload
      37: astore        6
      39: aload         6
      41: ifnull        187
      44: aload_0
      45: getfield      #4                  // Field writers:Ljava/util/List;
      48: iload         5
      50: iload         4
      52: isub
      53: invokeinterface #36,  2           // InterfaceMethod java/util/List.get:(I)Ljava/lang/Object;
      58: checkcast     #5                  // class org/apache/hadoop/hbase/regionserver/compactions/TestCompactor$StoreFileWritersCapture$Writer
      61: astore        7
      63: aload         6
      65: arraylength
      66: i2l
      67: aload         7
      69: getfield      #43                 // Field org/apache/hadoop/hbase/regionserver/compactions/TestCompactor$StoreFileWritersCapture$Writer.kvs:Ljava/util/ArrayList;
      72: invokevirtual #44                 // Method java/util/ArrayList.size:()I
      75: i2l
      76: invokestatic  #35                 // Method org/junit/Assert.assertEquals:(JJ)V
      79: iconst_0
      80: istore        8
      82: iload         8
      84: aload         6
      86: arraylength
      87: if_icmpge     184
      90: aload         6
      92: iload         8
      94: aaload
      95: invokevirtual #55                 // Method org/apache/hadoop/hbase/KeyValue.getTimestamp:()J
      98: aload_3
      99: iload         5
     101: invokeinterface #36,  2           // InterfaceMethod java/util/List.get:(I)Ljava/lang/Object;
     106: checkcast     #56                 // class java/lang/Long
     109: invokevirtual #57                 // Method java/lang/Long.longValue:()J
     112: lcmp
     113: iflt          120
     116: iconst_1
     117: goto          121
     120: iconst_0
     121: invokestatic  #58                 // Method org/junit/Assert.assertTrue:(Z)V
     124: aload         6
     126: iload         8
     128: aaload
     129: invokevirtual #55                 // Method org/apache/hadoop/hbase/KeyValue.getTimestamp:()J
     132: aload_3
     133: iload         5
     135: iconst_1
     136: iadd
     137: invokeinterface #36,  2           // InterfaceMethod java/util/List.get:(I)Ljava/lang/Object;
     142: checkcast     #56                 // class java/lang/Long
     145: invokevirtual #57                 // Method java/lang/Long.longValue:()J
     148: lcmp
     149: ifge          156
     152: iconst_1
     153: goto          157
     156: iconst_0
     157: invokestatic  #58                 // Method org/junit/Assert.assertTrue:(Z)V
     160: aload         6
     162: iload         8
     164: aaload
     165: aload         7
     167: getfield      #43                 // Field org/apache/hadoop/hbase/regionserver/compactions/TestCompactor$StoreFileWritersCapture$Writer.kvs:Ljava/util/ArrayList;
     170: iload         8
     172: invokevirtual #45                 // Method java/util/ArrayList.get:(I)Ljava/lang/Object;
     175: invokestatic  #46                 // Method org/junit/Assert.assertEquals:(Ljava/lang/Object;Ljava/lang/Object;)V
     178: iinc          8, 1
     181: goto          82
     184: goto          194
     187: iload_2
     188: invokestatic  #47                 // Method org/junit/Assert.assertFalse:(Z)V
     191: iinc          4, 1
     194: iinc          5, 1
     197: goto          26
     200: return

  public java.util.List<org.apache.hadoop.hbase.regionserver.compactions.TestCompactor$StoreFileWritersCapture$Writer> getWriters();
    Code:
       0: aload_0
       1: getfield      #4                  // Field writers:Ljava/util/List;
       4: areturn

  public java.lang.Object answer(org.mockito.invocation.InvocationOnMock) throws java.lang.Throwable;
    Code:
       0: aload_0
       1: aload_1
       2: invokevirtual #59                 // Method answer:(Lorg/mockito/invocation/InvocationOnMock;)Lorg/apache/hadoop/hbase/regionserver/StoreFileWriter;
       5: areturn
}
