Compiled from "TestStruct.java"
class org.apache.hadoop.hbase.types.TestStruct$Pojo1 implements java.lang.Comparable<org.apache.hadoop.hbase.types.TestStruct$Pojo1> {
  final java.lang.String stringFieldAsc;

  final int intFieldAsc;

  final double doubleFieldAsc;

  final transient java.lang.String str;

  public org.apache.hadoop.hbase.types.TestStruct$Pojo1(java.lang.Object...);
    Code:
       0: aload_0
       1: invokespecial #1                  // Method java/lang/Object."<init>":()V
       4: aload_0
       5: aload_1
       6: iconst_0
       7: aaload
       8: checkcast     #2                  // class java/lang/String
      11: putfield      #3                  // Field stringFieldAsc:Ljava/lang/String;
      14: aload_0
      15: aload_1
      16: iconst_1
      17: aaload
      18: checkcast     #4                  // class java/lang/Integer
      21: invokevirtual #5                  // Method java/lang/Integer.intValue:()I
      24: putfield      #6                  // Field intFieldAsc:I
      27: aload_0
      28: aload_1
      29: iconst_2
      30: aaload
      31: checkcast     #7                  // class java/lang/Double
      34: invokevirtual #8                  // Method java/lang/Double.doubleValue:()D
      37: putfield      #9                  // Field doubleFieldAsc:D
      40: aload_0
      41: new           #10                 // class java/lang/StringBuilder
      44: dup
      45: invokespecial #11                 // Method java/lang/StringBuilder."<init>":()V
      48: ldc           #12                 // String {
      50: invokevirtual #13                 // Method java/lang/StringBuilder.append:(Ljava/lang/String;)Ljava/lang/StringBuilder;
      53: aconst_null
      54: aload_0
      55: getfield      #3                  // Field stringFieldAsc:Ljava/lang/String;
      58: if_acmpne     66
      61: ldc           #14                 // String
      63: goto          68
      66: ldc           #15                 // String \"
      68: invokevirtual #13                 // Method java/lang/StringBuilder.append:(Ljava/lang/String;)Ljava/lang/StringBuilder;
      71: aload_0
      72: getfield      #3                  // Field stringFieldAsc:Ljava/lang/String;
      75: invokevirtual #13                 // Method java/lang/StringBuilder.append:(Ljava/lang/String;)Ljava/lang/StringBuilder;
      78: aconst_null
      79: aload_0
      80: getfield      #3                  // Field stringFieldAsc:Ljava/lang/String;
      83: if_acmpne     91
      86: ldc           #14                 // String
      88: goto          93
      91: ldc           #15                 // String \"
      93: invokevirtual #13                 // Method java/lang/StringBuilder.append:(Ljava/lang/String;)Ljava/lang/StringBuilder;
      96: ldc           #16                 // String ,
      98: invokevirtual #13                 // Method java/lang/StringBuilder.append:(Ljava/lang/String;)Ljava/lang/StringBuilder;
     101: aload_0
     102: getfield      #6                  // Field intFieldAsc:I
     105: invokevirtual #17                 // Method java/lang/StringBuilder.append:(I)Ljava/lang/StringBuilder;
     108: ldc           #16                 // String ,
     110: invokevirtual #13                 // Method java/lang/StringBuilder.append:(Ljava/lang/String;)Ljava/lang/StringBuilder;
     113: aload_0
     114: getfield      #9                  // Field doubleFieldAsc:D
     117: invokevirtual #18                 // Method java/lang/StringBuilder.append:(D)Ljava/lang/StringBuilder;
     120: ldc           #19                 // String  }
     122: invokevirtual #13                 // Method java/lang/StringBuilder.append:(Ljava/lang/String;)Ljava/lang/StringBuilder;
     125: invokevirtual #20                 // Method java/lang/StringBuilder.toString:()Ljava/lang/String;
     128: putfield      #21                 // Field str:Ljava/lang/String;
     131: return

  public java.lang.String toString();
    Code:
       0: aload_0
       1: getfield      #21                 // Field str:Ljava/lang/String;
       4: areturn

  public int compareTo(org.apache.hadoop.hbase.types.TestStruct$Pojo1);
    Code:
       0: aload_0
       1: getfield      #3                  // Field stringFieldAsc:Ljava/lang/String;
       4: aload_1
       5: getfield      #3                  // Field stringFieldAsc:Ljava/lang/String;
       8: invokevirtual #22                 // Method java/lang/String.compareTo:(Ljava/lang/String;)I
      11: istore_2
      12: iload_2
      13: ifeq          18
      16: iload_2
      17: ireturn
      18: aload_0
      19: getfield      #6                  // Field intFieldAsc:I
      22: invokestatic  #23                 // Method java/lang/Integer.valueOf:(I)Ljava/lang/Integer;
      25: aload_1
      26: getfield      #6                  // Field intFieldAsc:I
      29: invokestatic  #23                 // Method java/lang/Integer.valueOf:(I)Ljava/lang/Integer;
      32: invokevirtual #24                 // Method java/lang/Integer.compareTo:(Ljava/lang/Integer;)I
      35: istore_2
      36: iload_2
      37: ifeq          42
      40: iload_2
      41: ireturn
      42: aload_0
      43: getfield      #9                  // Field doubleFieldAsc:D
      46: aload_1
      47: getfield      #9                  // Field doubleFieldAsc:D
      50: invokestatic  #25                 // Method java/lang/Double.compare:(DD)I
      53: ireturn

  public int hashCode();
    Code:
       0: bipush        31
       2: istore_1
       3: iconst_1
       4: istore_2
       5: aload_0
       6: getfield      #9                  // Field doubleFieldAsc:D
       9: invokestatic  #26                 // Method java/lang/Double.doubleToLongBits:(D)J
      12: lstore_3
      13: bipush        31
      15: iload_2
      16: imul
      17: lload_3
      18: lload_3
      19: bipush        32
      21: lushr
      22: lxor
      23: l2i
      24: iadd
      25: istore_2
      26: bipush        31
      28: iload_2
      29: imul
      30: aload_0
      31: getfield      #6                  // Field intFieldAsc:I
      34: iadd
      35: istore_2
      36: bipush        31
      38: iload_2
      39: imul
      40: aload_0
      41: getfield      #3                  // Field stringFieldAsc:Ljava/lang/String;
      44: ifnonnull     51
      47: iconst_0
      48: goto          58
      51: aload_0
      52: getfield      #3                  // Field stringFieldAsc:Ljava/lang/String;
      55: invokevirtual #27                 // Method java/lang/String.hashCode:()I
      58: iadd
      59: istore_2
      60: iload_2
      61: ireturn

  public boolean equals(java.lang.Object);
    Code:
       0: aload_0
       1: aload_1
       2: if_acmpne     7
       5: iconst_1
       6: ireturn
       7: aload_1
       8: ifnonnull     13
      11: iconst_0
      12: ireturn
      13: aload_0
      14: invokevirtual #28                 // Method java/lang/Object.getClass:()Ljava/lang/Class;
      17: aload_1
      18: invokevirtual #28                 // Method java/lang/Object.getClass:()Ljava/lang/Class;
      21: if_acmpeq     26
      24: iconst_0
      25: ireturn
      26: aload_1
      27: checkcast     #29                 // class org/apache/hadoop/hbase/types/TestStruct$Pojo1
      30: astore_2
      31: aload_0
      32: getfield      #9                  // Field doubleFieldAsc:D
      35: invokestatic  #26                 // Method java/lang/Double.doubleToLongBits:(D)J
      38: aload_2
      39: getfield      #9                  // Field doubleFieldAsc:D
      42: invokestatic  #26                 // Method java/lang/Double.doubleToLongBits:(D)J
      45: lcmp
      46: ifeq          51
      49: iconst_0
      50: ireturn
      51: aload_0
      52: getfield      #6                  // Field intFieldAsc:I
      55: aload_2
      56: getfield      #6                  // Field intFieldAsc:I
      59: if_icmpeq     64
      62: iconst_0
      63: ireturn
      64: aload_0
      65: getfield      #3                  // Field stringFieldAsc:Ljava/lang/String;
      68: ifnonnull     80
      71: aload_2
      72: getfield      #3                  // Field stringFieldAsc:Ljava/lang/String;
      75: ifnull        96
      78: iconst_0
      79: ireturn
      80: aload_0
      81: getfield      #3                  // Field stringFieldAsc:Ljava/lang/String;
      84: aload_2
      85: getfield      #3                  // Field stringFieldAsc:Ljava/lang/String;
      88: invokevirtual #30                 // Method java/lang/String.equals:(Ljava/lang/Object;)Z
      91: ifne          96
      94: iconst_0
      95: ireturn
      96: iconst_1
      97: ireturn

  public int compareTo(java.lang.Object);
    Code:
       0: aload_0
       1: aload_1
       2: checkcast     #29                 // class org/apache/hadoop/hbase/types/TestStruct$Pojo1
       5: invokevirtual #31                 // Method compareTo:(Lorg/apache/hadoop/hbase/types/TestStruct$Pojo1;)I
       8: ireturn
}
