Compiled from "TestZKReplicationQueueStorage.java"
public class org.apache.hadoop.hbase.replication.TestZKReplicationQueueStorage {
  public static final org.apache.hadoop.hbase.HBaseClassTestRule CLASS_RULE;

  public org.apache.hadoop.hbase.replication.TestZKReplicationQueueStorage();
    Code:
       0: aload_0
       1: invokespecial #1                  // Method java/lang/Object."<init>":()V
       4: return

  public static void setUp() throws java.lang.Exception;
    Code:
       0: getstatic     #2                  // Field UTIL:Lorg/apache/hadoop/hbase/HBaseZKTestingUtility;
       3: invokevirtual #3                  // Method org/apache/hadoop/hbase/HBaseZKTestingUtility.startMiniZKCluster:()Lorg/apache/hadoop/hbase/zookeeper/MiniZooKeeperCluster;
       6: pop
       7: new           #4                  // class org/apache/hadoop/hbase/replication/ZKReplicationQueueStorage
      10: dup
      11: getstatic     #2                  // Field UTIL:Lorg/apache/hadoop/hbase/HBaseZKTestingUtility;
      14: invokevirtual #5                  // Method org/apache/hadoop/hbase/HBaseZKTestingUtility.getZooKeeperWatcher:()Lorg/apache/hadoop/hbase/zookeeper/ZKWatcher;
      17: getstatic     #2                  // Field UTIL:Lorg/apache/hadoop/hbase/HBaseZKTestingUtility;
      20: invokevirtual #6                  // Method org/apache/hadoop/hbase/HBaseZKTestingUtility.getConfiguration:()Lorg/apache/hadoop/conf/Configuration;
      23: invokespecial #7                  // Method org/apache/hadoop/hbase/replication/ZKReplicationQueueStorage."<init>":(Lorg/apache/hadoop/hbase/zookeeper/ZKWatcher;Lorg/apache/hadoop/conf/Configuration;)V
      26: putstatic     #8                  // Field STORAGE:Lorg/apache/hadoop/hbase/replication/ZKReplicationQueueStorage;
      29: return

  public static void tearDown() throws java.io.IOException;
    Code:
       0: getstatic     #2                  // Field UTIL:Lorg/apache/hadoop/hbase/HBaseZKTestingUtility;
       3: invokevirtual #9                  // Method org/apache/hadoop/hbase/HBaseZKTestingUtility.shutdownMiniZKCluster:()V
       6: return

  public void tearDownAfterTest() throws org.apache.hadoop.hbase.replication.ReplicationException, org.apache.zookeeper.KeeperException, java.io.IOException;
    Code:
       0: getstatic     #8                  // Field STORAGE:Lorg/apache/hadoop/hbase/replication/ZKReplicationQueueStorage;
       3: invokevirtual #10                 // Method org/apache/hadoop/hbase/replication/ZKReplicationQueueStorage.getListOfReplicators:()Ljava/util/List;
       6: invokeinterface #11,  1           // InterfaceMethod java/util/List.iterator:()Ljava/util/Iterator;
      11: astore_1
      12: aload_1
      13: invokeinterface #12,  1           // InterfaceMethod java/util/Iterator.hasNext:()Z
      18: ifeq          86
      21: aload_1
      22: invokeinterface #13,  1           // InterfaceMethod java/util/Iterator.next:()Ljava/lang/Object;
      27: checkcast     #14                 // class org/apache/hadoop/hbase/ServerName
      30: astore_2
      31: getstatic     #8                  // Field STORAGE:Lorg/apache/hadoop/hbase/replication/ZKReplicationQueueStorage;
      34: aload_2
      35: invokevirtual #15                 // Method org/apache/hadoop/hbase/replication/ZKReplicationQueueStorage.getAllQueues:(Lorg/apache/hadoop/hbase/ServerName;)Ljava/util/List;
      38: invokeinterface #11,  1           // InterfaceMethod java/util/List.iterator:()Ljava/util/Iterator;
      43: astore_3
      44: aload_3
      45: invokeinterface #12,  1           // InterfaceMethod java/util/Iterator.hasNext:()Z
      50: ifeq          76
      53: aload_3
      54: invokeinterface #13,  1           // InterfaceMethod java/util/Iterator.next:()Ljava/lang/Object;
      59: checkcast     #16                 // class java/lang/String
      62: astore        4
      64: getstatic     #8                  // Field STORAGE:Lorg/apache/hadoop/hbase/replication/ZKReplicationQueueStorage;
      67: aload_2
      68: aload         4
      70: invokevirtual #17                 // Method org/apache/hadoop/hbase/replication/ZKReplicationQueueStorage.removeQueue:(Lorg/apache/hadoop/hbase/ServerName;Ljava/lang/String;)V
      73: goto          44
      76: getstatic     #8                  // Field STORAGE:Lorg/apache/hadoop/hbase/replication/ZKReplicationQueueStorage;
      79: aload_2
      80: invokevirtual #18                 // Method org/apache/hadoop/hbase/replication/ZKReplicationQueueStorage.removeReplicatorIfQueueIsEmpty:(Lorg/apache/hadoop/hbase/ServerName;)V
      83: goto          12
      86: getstatic     #8                  // Field STORAGE:Lorg/apache/hadoop/hbase/replication/ZKReplicationQueueStorage;
      89: invokevirtual #19                 // Method org/apache/hadoop/hbase/replication/ZKReplicationQueueStorage.getAllPeersFromHFileRefsQueue:()Ljava/util/List;
      92: invokeinterface #11,  1           // InterfaceMethod java/util/List.iterator:()Ljava/util/Iterator;
      97: astore_1
      98: aload_1
      99: invokeinterface #12,  1           // InterfaceMethod java/util/Iterator.hasNext:()Z
     104: ifeq          127
     107: aload_1
     108: invokeinterface #13,  1           // InterfaceMethod java/util/Iterator.next:()Ljava/lang/Object;
     113: checkcast     #16                 // class java/lang/String
     116: astore_2
     117: getstatic     #8                  // Field STORAGE:Lorg/apache/hadoop/hbase/replication/ZKReplicationQueueStorage;
     120: aload_2
     121: invokevirtual #20                 // Method org/apache/hadoop/hbase/replication/ZKReplicationQueueStorage.removePeerFromHFileRefs:(Ljava/lang/String;)V
     124: goto          98
     127: return

  public void testReplicator() throws org.apache.hadoop.hbase.replication.ReplicationException;
    Code:
       0: getstatic     #8                  // Field STORAGE:Lorg/apache/hadoop/hbase/replication/ZKReplicationQueueStorage;
       3: invokevirtual #10                 // Method org/apache/hadoop/hbase/replication/ZKReplicationQueueStorage.getListOfReplicators:()Ljava/util/List;
       6: invokeinterface #23,  1           // InterfaceMethod java/util/List.isEmpty:()Z
      11: invokestatic  #24                 // Method org/junit/Assert.assertTrue:(Z)V
      14: ldc           #25                 // String 1
      16: astore_1
      17: iconst_0
      18: istore_2
      19: iload_2
      20: bipush        10
      22: if_icmpge     62
      25: getstatic     #8                  // Field STORAGE:Lorg/apache/hadoop/hbase/replication/ZKReplicationQueueStorage;
      28: aload_0
      29: iload_2
      30: invokespecial #26                 // Method getServerName:(I)Lorg/apache/hadoop/hbase/ServerName;
      33: aload_1
      34: new           #27                 // class java/lang/StringBuilder
      37: dup
      38: invokespecial #28                 // Method java/lang/StringBuilder."<init>":()V
      41: ldc           #29                 // String file
      43: invokevirtual #30                 // Method java/lang/StringBuilder.append:(Ljava/lang/String;)Ljava/lang/StringBuilder;
      46: iload_2
      47: invokevirtual #31                 // Method java/lang/StringBuilder.append:(I)Ljava/lang/StringBuilder;
      50: invokevirtual #32                 // Method java/lang/StringBuilder.toString:()Ljava/lang/String;
      53: invokevirtual #33                 // Method org/apache/hadoop/hbase/replication/ZKReplicationQueueStorage.addWAL:(Lorg/apache/hadoop/hbase/ServerName;Ljava/lang/String;Ljava/lang/String;)V
      56: iinc          2, 1
      59: goto          19
      62: getstatic     #8                  // Field STORAGE:Lorg/apache/hadoop/hbase/replication/ZKReplicationQueueStorage;
      65: invokevirtual #10                 // Method org/apache/hadoop/hbase/replication/ZKReplicationQueueStorage.getListOfReplicators:()Ljava/util/List;
      68: astore_2
      69: ldc2_w        #34                 // long 10l
      72: aload_2
      73: invokeinterface #36,  1           // InterfaceMethod java/util/List.size:()I
      78: i2l
      79: invokestatic  #37                 // Method org/junit/Assert.assertEquals:(JJ)V
      82: iconst_0
      83: istore_3
      84: iload_3
      85: bipush        10
      87: if_icmpge     115
      90: aload_2
      91: iconst_1
      92: anewarray     #14                 // class org/apache/hadoop/hbase/ServerName
      95: dup
      96: iconst_0
      97: aload_0
      98: iload_3
      99: invokespecial #26                 // Method getServerName:(I)Lorg/apache/hadoop/hbase/ServerName;
     102: aastore
     103: invokestatic  #38                 // Method org/hamcrest/CoreMatchers.hasItems:([Ljava/lang/Object;)Lorg/hamcrest/Matcher;
     106: invokestatic  #39                 // Method org/junit/Assert.assertThat:(Ljava/lang/Object;Lorg/hamcrest/Matcher;)V
     109: iinc          3, 1
     112: goto          84
     115: iconst_0
     116: istore_3
     117: iload_3
     118: iconst_5
     119: if_icmpge     140
     122: getstatic     #8                  // Field STORAGE:Lorg/apache/hadoop/hbase/replication/ZKReplicationQueueStorage;
     125: aload_0
     126: iload_3
     127: invokespecial #26                 // Method getServerName:(I)Lorg/apache/hadoop/hbase/ServerName;
     130: aload_1
     131: invokevirtual #17                 // Method org/apache/hadoop/hbase/replication/ZKReplicationQueueStorage.removeQueue:(Lorg/apache/hadoop/hbase/ServerName;Ljava/lang/String;)V
     134: iinc          3, 1
     137: goto          117
     140: iconst_0
     141: istore_3
     142: iload_3
     143: bipush        10
     145: if_icmpge     165
     148: getstatic     #8                  // Field STORAGE:Lorg/apache/hadoop/hbase/replication/ZKReplicationQueueStorage;
     151: aload_0
     152: iload_3
     153: invokespecial #26                 // Method getServerName:(I)Lorg/apache/hadoop/hbase/ServerName;
     156: invokevirtual #18                 // Method org/apache/hadoop/hbase/replication/ZKReplicationQueueStorage.removeReplicatorIfQueueIsEmpty:(Lorg/apache/hadoop/hbase/ServerName;)V
     159: iinc          3, 1
     162: goto          142
     165: getstatic     #8                  // Field STORAGE:Lorg/apache/hadoop/hbase/replication/ZKReplicationQueueStorage;
     168: invokevirtual #10                 // Method org/apache/hadoop/hbase/replication/ZKReplicationQueueStorage.getListOfReplicators:()Ljava/util/List;
     171: astore_2
     172: ldc2_w        #40                 // long 5l
     175: aload_2
     176: invokeinterface #36,  1           // InterfaceMethod java/util/List.size:()I
     181: i2l
     182: invokestatic  #37                 // Method org/junit/Assert.assertEquals:(JJ)V
     185: iconst_5
     186: istore_3
     187: iload_3
     188: bipush        10
     190: if_icmpge     218
     193: aload_2
     194: iconst_1
     195: anewarray     #14                 // class org/apache/hadoop/hbase/ServerName
     198: dup
     199: iconst_0
     200: aload_0
     201: iload_3
     202: invokespecial #26                 // Method getServerName:(I)Lorg/apache/hadoop/hbase/ServerName;
     205: aastore
     206: invokestatic  #38                 // Method org/hamcrest/CoreMatchers.hasItems:([Ljava/lang/Object;)Lorg/hamcrest/Matcher;
     209: invokestatic  #39                 // Method org/junit/Assert.assertThat:(Ljava/lang/Object;Lorg/hamcrest/Matcher;)V
     212: iinc          3, 1
     215: goto          187
     218: return

  public void testAddRemoveLog() throws org.apache.hadoop.hbase.replication.ReplicationException;
    Code:
       0: ldc           #21                 // String 127.0.0.1
       2: sipush        8000
       5: ldc2_w        #46                 // long 10000l
       8: invokestatic  #22                 // Method org/apache/hadoop/hbase/ServerName.valueOf:(Ljava/lang/String;IJ)Lorg/apache/hadoop/hbase/ServerName;
      11: astore_1
      12: getstatic     #8                  // Field STORAGE:Lorg/apache/hadoop/hbase/replication/ZKReplicationQueueStorage;
      15: aload_1
      16: invokevirtual #15                 // Method org/apache/hadoop/hbase/replication/ZKReplicationQueueStorage.getAllQueues:(Lorg/apache/hadoop/hbase/ServerName;)Ljava/util/List;
      19: invokeinterface #23,  1           // InterfaceMethod java/util/List.isEmpty:()Z
      24: invokestatic  #24                 // Method org/junit/Assert.assertTrue:(Z)V
      27: ldc           #25                 // String 1
      29: astore_2
      30: ldc           #48                 // String 2
      32: astore_3
      33: iconst_0
      34: istore        4
      36: iload         4
      38: bipush        10
      40: if_icmpge     81
      43: getstatic     #8                  // Field STORAGE:Lorg/apache/hadoop/hbase/replication/ZKReplicationQueueStorage;
      46: aload_1
      47: aload_2
      48: aload_0
      49: ldc           #49                 // String file1
      51: iload         4
      53: invokespecial #50                 // Method getFileName:(Ljava/lang/String;I)Ljava/lang/String;
      56: invokevirtual #33                 // Method org/apache/hadoop/hbase/replication/ZKReplicationQueueStorage.addWAL:(Lorg/apache/hadoop/hbase/ServerName;Ljava/lang/String;Ljava/lang/String;)V
      59: getstatic     #8                  // Field STORAGE:Lorg/apache/hadoop/hbase/replication/ZKReplicationQueueStorage;
      62: aload_1
      63: aload_3
      64: aload_0
      65: ldc           #51                 // String file2
      67: iload         4
      69: invokespecial #50                 // Method getFileName:(Ljava/lang/String;I)Ljava/lang/String;
      72: invokevirtual #33                 // Method org/apache/hadoop/hbase/replication/ZKReplicationQueueStorage.addWAL:(Lorg/apache/hadoop/hbase/ServerName;Ljava/lang/String;Ljava/lang/String;)V
      75: iinc          4, 1
      78: goto          36
      81: getstatic     #8                  // Field STORAGE:Lorg/apache/hadoop/hbase/replication/ZKReplicationQueueStorage;
      84: aload_1
      85: invokevirtual #15                 // Method org/apache/hadoop/hbase/replication/ZKReplicationQueueStorage.getAllQueues:(Lorg/apache/hadoop/hbase/ServerName;)Ljava/util/List;
      88: astore        4
      90: ldc2_w        #52                 // long 2l
      93: aload         4
      95: invokeinterface #36,  1           // InterfaceMethod java/util/List.size:()I
     100: i2l
     101: invokestatic  #37                 // Method org/junit/Assert.assertEquals:(JJ)V
     104: aload         4
     106: iconst_2
     107: anewarray     #16                 // class java/lang/String
     110: dup
     111: iconst_0
     112: ldc           #25                 // String 1
     114: aastore
     115: dup
     116: iconst_1
     117: ldc           #48                 // String 2
     119: aastore
     120: invokestatic  #38                 // Method org/hamcrest/CoreMatchers.hasItems:([Ljava/lang/Object;)Lorg/hamcrest/Matcher;
     123: invokestatic  #39                 // Method org/junit/Assert.assertThat:(Ljava/lang/Object;Lorg/hamcrest/Matcher;)V
     126: getstatic     #8                  // Field STORAGE:Lorg/apache/hadoop/hbase/replication/ZKReplicationQueueStorage;
     129: aload_1
     130: aload_2
     131: invokevirtual #54                 // Method org/apache/hadoop/hbase/replication/ZKReplicationQueueStorage.getWALsInQueue:(Lorg/apache/hadoop/hbase/ServerName;Ljava/lang/String;)Ljava/util/List;
     134: astore        5
     136: getstatic     #8                  // Field STORAGE:Lorg/apache/hadoop/hbase/replication/ZKReplicationQueueStorage;
     139: aload_1
     140: aload_3
     141: invokevirtual #54                 // Method org/apache/hadoop/hbase/replication/ZKReplicationQueueStorage.getWALsInQueue:(Lorg/apache/hadoop/hbase/ServerName;Ljava/lang/String;)Ljava/util/List;
     144: astore        6
     146: ldc2_w        #34                 // long 10l
     149: aload         5
     151: invokeinterface #36,  1           // InterfaceMethod java/util/List.size:()I
     156: i2l
     157: invokestatic  #37                 // Method org/junit/Assert.assertEquals:(JJ)V
     160: ldc2_w        #34                 // long 10l
     163: aload         6
     165: invokeinterface #36,  1           // InterfaceMethod java/util/List.size:()I
     170: i2l
     171: invokestatic  #37                 // Method org/junit/Assert.assertEquals:(JJ)V
     174: iconst_0
     175: istore        7
     177: iload         7
     179: bipush        10
     181: if_icmpge     236
     184: aload         5
     186: iconst_1
     187: anewarray     #16                 // class java/lang/String
     190: dup
     191: iconst_0
     192: aload_0
     193: ldc           #49                 // String file1
     195: iload         7
     197: invokespecial #50                 // Method getFileName:(Ljava/lang/String;I)Ljava/lang/String;
     200: aastore
     201: invokestatic  #38                 // Method org/hamcrest/CoreMatchers.hasItems:([Ljava/lang/Object;)Lorg/hamcrest/Matcher;
     204: invokestatic  #39                 // Method org/junit/Assert.assertThat:(Ljava/lang/Object;Lorg/hamcrest/Matcher;)V
     207: aload         6
     209: iconst_1
     210: anewarray     #16                 // class java/lang/String
     213: dup
     214: iconst_0
     215: aload_0
     216: ldc           #51                 // String file2
     218: iload         7
     220: invokespecial #50                 // Method getFileName:(Ljava/lang/String;I)Ljava/lang/String;
     223: aastore
     224: invokestatic  #38                 // Method org/hamcrest/CoreMatchers.hasItems:([Ljava/lang/Object;)Lorg/hamcrest/Matcher;
     227: invokestatic  #39                 // Method org/junit/Assert.assertThat:(Ljava/lang/Object;Lorg/hamcrest/Matcher;)V
     230: iinc          7, 1
     233: goto          177
     236: iconst_0
     237: istore        7
     239: iload         7
     241: bipush        10
     243: if_icmpge     349
     246: lconst_0
     247: getstatic     #8                  // Field STORAGE:Lorg/apache/hadoop/hbase/replication/ZKReplicationQueueStorage;
     250: aload_1
     251: aload_2
     252: aload_0
     253: ldc           #49                 // String file1
     255: iload         7
     257: invokespecial #50                 // Method getFileName:(Ljava/lang/String;I)Ljava/lang/String;
     260: invokevirtual #55                 // Method org/apache/hadoop/hbase/replication/ZKReplicationQueueStorage.getWALPosition:(Lorg/apache/hadoop/hbase/ServerName;Ljava/lang/String;Ljava/lang/String;)J
     263: invokestatic  #37                 // Method org/junit/Assert.assertEquals:(JJ)V
     266: lconst_0
     267: getstatic     #8                  // Field STORAGE:Lorg/apache/hadoop/hbase/replication/ZKReplicationQueueStorage;
     270: aload_1
     271: aload_3
     272: aload_0
     273: ldc           #51                 // String file2
     275: iload         7
     277: invokespecial #50                 // Method getFileName:(Ljava/lang/String;I)Ljava/lang/String;
     280: invokevirtual #55                 // Method org/apache/hadoop/hbase/replication/ZKReplicationQueueStorage.getWALPosition:(Lorg/apache/hadoop/hbase/ServerName;Ljava/lang/String;Ljava/lang/String;)J
     283: invokestatic  #37                 // Method org/junit/Assert.assertEquals:(JJ)V
     286: getstatic     #8                  // Field STORAGE:Lorg/apache/hadoop/hbase/replication/ZKReplicationQueueStorage;
     289: aload_1
     290: aload_2
     291: aload_0
     292: ldc           #49                 // String file1
     294: iload         7
     296: invokespecial #50                 // Method getFileName:(Ljava/lang/String;I)Ljava/lang/String;
     299: iload         7
     301: iconst_1
     302: iadd
     303: bipush        100
     305: imul
     306: i2l
     307: invokestatic  #56                 // Method java/util/Collections.emptyMap:()Ljava/util/Map;
     310: invokevirtual #57                 // Method org/apache/hadoop/hbase/replication/ZKReplicationQueueStorage.setWALPosition:(Lorg/apache/hadoop/hbase/ServerName;Ljava/lang/String;Ljava/lang/String;JLjava/util/Map;)V
     313: getstatic     #8                  // Field STORAGE:Lorg/apache/hadoop/hbase/replication/ZKReplicationQueueStorage;
     316: aload_1
     317: aload_3
     318: aload_0
     319: ldc           #51                 // String file2
     321: iload         7
     323: invokespecial #50                 // Method getFileName:(Ljava/lang/String;I)Ljava/lang/String;
     326: iload         7
     328: iconst_1
     329: iadd
     330: bipush        100
     332: imul
     333: bipush        10
     335: iadd
     336: i2l
     337: invokestatic  #56                 // Method java/util/Collections.emptyMap:()Ljava/util/Map;
     340: invokevirtual #57                 // Method org/apache/hadoop/hbase/replication/ZKReplicationQueueStorage.setWALPosition:(Lorg/apache/hadoop/hbase/ServerName;Ljava/lang/String;Ljava/lang/String;JLjava/util/Map;)V
     343: iinc          7, 1
     346: goto          239
     349: iconst_0
     350: istore        7
     352: iload         7
     354: bipush        10
     356: if_icmpge     422
     359: iload         7
     361: iconst_1
     362: iadd
     363: bipush        100
     365: imul
     366: i2l
     367: getstatic     #8                  // Field STORAGE:Lorg/apache/hadoop/hbase/replication/ZKReplicationQueueStorage;
     370: aload_1
     371: aload_2
     372: aload_0
     373: ldc           #49                 // String file1
     375: iload         7
     377: invokespecial #50                 // Method getFileName:(Ljava/lang/String;I)Ljava/lang/String;
     380: invokevirtual #55                 // Method org/apache/hadoop/hbase/replication/ZKReplicationQueueStorage.getWALPosition:(Lorg/apache/hadoop/hbase/ServerName;Ljava/lang/String;Ljava/lang/String;)J
     383: invokestatic  #37                 // Method org/junit/Assert.assertEquals:(JJ)V
     386: iload         7
     388: iconst_1
     389: iadd
     390: bipush        100
     392: imul
     393: bipush        10
     395: iadd
     396: i2l
     397: getstatic     #8                  // Field STORAGE:Lorg/apache/hadoop/hbase/replication/ZKReplicationQueueStorage;
     400: aload_1
     401: aload_3
     402: aload_0
     403: ldc           #51                 // String file2
     405: iload         7
     407: invokespecial #50                 // Method getFileName:(Ljava/lang/String;I)Ljava/lang/String;
     410: invokevirtual #55                 // Method org/apache/hadoop/hbase/replication/ZKReplicationQueueStorage.getWALPosition:(Lorg/apache/hadoop/hbase/ServerName;Ljava/lang/String;Ljava/lang/String;)J
     413: invokestatic  #37                 // Method org/junit/Assert.assertEquals:(JJ)V
     416: iinc          7, 1
     419: goto          352
     422: iconst_0
     423: istore        7
     425: iload         7
     427: bipush        10
     429: if_icmpge     480
     432: iload         7
     434: iconst_2
     435: irem
     436: ifne          458
     439: getstatic     #8                  // Field STORAGE:Lorg/apache/hadoop/hbase/replication/ZKReplicationQueueStorage;
     442: aload_1
     443: aload_2
     444: aload_0
     445: ldc           #49                 // String file1
     447: iload         7
     449: invokespecial #50                 // Method getFileName:(Ljava/lang/String;I)Ljava/lang/String;
     452: invokevirtual #58                 // Method org/apache/hadoop/hbase/replication/ZKReplicationQueueStorage.removeWAL:(Lorg/apache/hadoop/hbase/ServerName;Ljava/lang/String;Ljava/lang/String;)V
     455: goto          474
     458: getstatic     #8                  // Field STORAGE:Lorg/apache/hadoop/hbase/replication/ZKReplicationQueueStorage;
     461: aload_1
     462: aload_3
     463: aload_0
     464: ldc           #51                 // String file2
     466: iload         7
     468: invokespecial #50                 // Method getFileName:(Ljava/lang/String;I)Ljava/lang/String;
     471: invokevirtual #58                 // Method org/apache/hadoop/hbase/replication/ZKReplicationQueueStorage.removeWAL:(Lorg/apache/hadoop/hbase/ServerName;Ljava/lang/String;Ljava/lang/String;)V
     474: iinc          7, 1
     477: goto          425
     480: getstatic     #8                  // Field STORAGE:Lorg/apache/hadoop/hbase/replication/ZKReplicationQueueStorage;
     483: aload_1
     484: invokevirtual #15                 // Method org/apache/hadoop/hbase/replication/ZKReplicationQueueStorage.getAllQueues:(Lorg/apache/hadoop/hbase/ServerName;)Ljava/util/List;
     487: astore        4
     489: ldc2_w        #52                 // long 2l
     492: aload         4
     494: invokeinterface #36,  1           // InterfaceMethod java/util/List.size:()I
     499: i2l
     500: invokestatic  #37                 // Method org/junit/Assert.assertEquals:(JJ)V
     503: aload         4
     505: iconst_2
     506: anewarray     #16                 // class java/lang/String
     509: dup
     510: iconst_0
     511: ldc           #25                 // String 1
     513: aastore
     514: dup
     515: iconst_1
     516: ldc           #48                 // String 2
     518: aastore
     519: invokestatic  #38                 // Method org/hamcrest/CoreMatchers.hasItems:([Ljava/lang/Object;)Lorg/hamcrest/Matcher;
     522: invokestatic  #39                 // Method org/junit/Assert.assertThat:(Ljava/lang/Object;Lorg/hamcrest/Matcher;)V
     525: ldc           #21                 // String 127.0.0.1
     527: sipush        8001
     530: ldc2_w        #59                 // long 10001l
     533: invokestatic  #22                 // Method org/apache/hadoop/hbase/ServerName.valueOf:(Ljava/lang/String;IJ)Lorg/apache/hadoop/hbase/ServerName;
     536: astore        7
     538: getstatic     #8                  // Field STORAGE:Lorg/apache/hadoop/hbase/replication/ZKReplicationQueueStorage;
     541: aload_1
     542: ldc           #25                 // String 1
     544: aload         7
     546: invokevirtual #61                 // Method org/apache/hadoop/hbase/replication/ZKReplicationQueueStorage.claimQueue:(Lorg/apache/hadoop/hbase/ServerName;Ljava/lang/String;Lorg/apache/hadoop/hbase/ServerName;)Lorg/apache/hadoop/hbase/util/Pair;
     549: astore        8
     551: new           #27                 // class java/lang/StringBuilder
     554: dup
     555: invokespecial #28                 // Method java/lang/StringBuilder."<init>":()V
     558: ldc           #62                 // String 1-
     560: invokevirtual #30                 // Method java/lang/StringBuilder.append:(Ljava/lang/String;)Ljava/lang/StringBuilder;
     563: aload_1
     564: invokevirtual #63                 // Method org/apache/hadoop/hbase/ServerName.getServerName:()Ljava/lang/String;
     567: invokevirtual #30                 // Method java/lang/StringBuilder.append:(Ljava/lang/String;)Ljava/lang/StringBuilder;
     570: invokevirtual #32                 // Method java/lang/StringBuilder.toString:()Ljava/lang/String;
     573: aload         8
     575: invokevirtual #64                 // Method org/apache/hadoop/hbase/util/Pair.getFirst:()Ljava/lang/Object;
     578: invokestatic  #65                 // Method org/junit/Assert.assertEquals:(Ljava/lang/Object;Ljava/lang/Object;)V
     581: ldc2_w        #40                 // long 5l
     584: aload         8
     586: invokevirtual #66                 // Method org/apache/hadoop/hbase/util/Pair.getSecond:()Ljava/lang/Object;
     589: checkcast     #67                 // class java/util/SortedSet
     592: invokeinterface #68,  1           // InterfaceMethod java/util/SortedSet.size:()I
     597: i2l
     598: invokestatic  #37                 // Method org/junit/Assert.assertEquals:(JJ)V
     601: iconst_1
     602: istore        9
     604: aload         8
     606: invokevirtual #66                 // Method org/apache/hadoop/hbase/util/Pair.getSecond:()Ljava/lang/Object;
     609: checkcast     #67                 // class java/util/SortedSet
     612: invokeinterface #69,  1           // InterfaceMethod java/util/SortedSet.iterator:()Ljava/util/Iterator;
     617: astore        10
     619: aload         10
     621: invokeinterface #12,  1           // InterfaceMethod java/util/Iterator.hasNext:()Z
     626: ifeq          695
     629: aload         10
     631: invokeinterface #13,  1           // InterfaceMethod java/util/Iterator.next:()Ljava/lang/Object;
     636: checkcast     #16                 // class java/lang/String
     639: astore        11
     641: aload_0
     642: ldc           #49                 // String file1
     644: iload         9
     646: invokespecial #50                 // Method getFileName:(Ljava/lang/String;I)Ljava/lang/String;
     649: aload         11
     651: invokestatic  #65                 // Method org/junit/Assert.assertEquals:(Ljava/lang/Object;Ljava/lang/Object;)V
     654: iload         9
     656: iconst_1
     657: iadd
     658: bipush        100
     660: imul
     661: i2l
     662: getstatic     #8                  // Field STORAGE:Lorg/apache/hadoop/hbase/replication/ZKReplicationQueueStorage;
     665: aload         7
     667: aload         8
     669: invokevirtual #64                 // Method org/apache/hadoop/hbase/util/Pair.getFirst:()Ljava/lang/Object;
     672: checkcast     #16                 // class java/lang/String
     675: aload_0
     676: ldc           #49                 // String file1
     678: iload         9
     680: invokespecial #50                 // Method getFileName:(Ljava/lang/String;I)Ljava/lang/String;
     683: invokevirtual #55                 // Method org/apache/hadoop/hbase/replication/ZKReplicationQueueStorage.getWALPosition:(Lorg/apache/hadoop/hbase/ServerName;Ljava/lang/String;Ljava/lang/String;)J
     686: invokestatic  #37                 // Method org/junit/Assert.assertEquals:(JJ)V
     689: iinc          9, 2
     692: goto          619
     695: getstatic     #8                  // Field STORAGE:Lorg/apache/hadoop/hbase/replication/ZKReplicationQueueStorage;
     698: aload_1
     699: invokevirtual #15                 // Method org/apache/hadoop/hbase/replication/ZKReplicationQueueStorage.getAllQueues:(Lorg/apache/hadoop/hbase/ServerName;)Ljava/util/List;
     702: astore        4
     704: lconst_1
     705: aload         4
     707: invokeinterface #36,  1           // InterfaceMethod java/util/List.size:()I
     712: i2l
     713: invokestatic  #37                 // Method org/junit/Assert.assertEquals:(JJ)V
     716: aload         4
     718: iconst_1
     719: anewarray     #16                 // class java/lang/String
     722: dup
     723: iconst_0
     724: ldc           #48                 // String 2
     726: aastore
     727: invokestatic  #38                 // Method org/hamcrest/CoreMatchers.hasItems:([Ljava/lang/Object;)Lorg/hamcrest/Matcher;
     730: invokestatic  #39                 // Method org/junit/Assert.assertThat:(Ljava/lang/Object;Lorg/hamcrest/Matcher;)V
     733: getstatic     #8                  // Field STORAGE:Lorg/apache/hadoop/hbase/replication/ZKReplicationQueueStorage;
     736: aload_1
     737: aload_3
     738: invokevirtual #54                 // Method org/apache/hadoop/hbase/replication/ZKReplicationQueueStorage.getWALsInQueue:(Lorg/apache/hadoop/hbase/ServerName;Ljava/lang/String;)Ljava/util/List;
     741: astore        6
     743: ldc2_w        #40                 // long 5l
     746: aload         6
     748: invokeinterface #36,  1           // InterfaceMethod java/util/List.size:()I
     753: i2l
     754: invokestatic  #37                 // Method org/junit/Assert.assertEquals:(JJ)V
     757: iconst_0
     758: istore        9
     760: iload         9
     762: bipush        10
     764: if_icmpge     796
     767: aload         6
     769: iconst_1
     770: anewarray     #16                 // class java/lang/String
     773: dup
     774: iconst_0
     775: aload_0
     776: ldc           #51                 // String file2
     778: iload         9
     780: invokespecial #50                 // Method getFileName:(Ljava/lang/String;I)Ljava/lang/String;
     783: aastore
     784: invokestatic  #38                 // Method org/hamcrest/CoreMatchers.hasItems:([Ljava/lang/Object;)Lorg/hamcrest/Matcher;
     787: invokestatic  #39                 // Method org/junit/Assert.assertThat:(Ljava/lang/Object;Lorg/hamcrest/Matcher;)V
     790: iinc          9, 2
     793: goto          760
     796: getstatic     #8                  // Field STORAGE:Lorg/apache/hadoop/hbase/replication/ZKReplicationQueueStorage;
     799: aload         7
     801: invokevirtual #15                 // Method org/apache/hadoop/hbase/replication/ZKReplicationQueueStorage.getAllQueues:(Lorg/apache/hadoop/hbase/ServerName;)Ljava/util/List;
     804: astore        4
     806: lconst_1
     807: aload         4
     809: invokeinterface #36,  1           // InterfaceMethod java/util/List.size:()I
     814: i2l
     815: invokestatic  #37                 // Method org/junit/Assert.assertEquals:(JJ)V
     818: aload         4
     820: iconst_1
     821: anewarray     #16                 // class java/lang/String
     824: dup
     825: iconst_0
     826: aload         8
     828: invokevirtual #64                 // Method org/apache/hadoop/hbase/util/Pair.getFirst:()Ljava/lang/Object;
     831: checkcast     #16                 // class java/lang/String
     834: aastore
     835: invokestatic  #38                 // Method org/hamcrest/CoreMatchers.hasItems:([Ljava/lang/Object;)Lorg/hamcrest/Matcher;
     838: invokestatic  #39                 // Method org/junit/Assert.assertThat:(Ljava/lang/Object;Lorg/hamcrest/Matcher;)V
     841: getstatic     #8                  // Field STORAGE:Lorg/apache/hadoop/hbase/replication/ZKReplicationQueueStorage;
     844: aload         7
     846: aload         8
     848: invokevirtual #64                 // Method org/apache/hadoop/hbase/util/Pair.getFirst:()Ljava/lang/Object;
     851: checkcast     #16                 // class java/lang/String
     854: invokevirtual #54                 // Method org/apache/hadoop/hbase/replication/ZKReplicationQueueStorage.getWALsInQueue:(Lorg/apache/hadoop/hbase/ServerName;Ljava/lang/String;)Ljava/util/List;
     857: astore        5
     859: ldc2_w        #40                 // long 5l
     862: aload         5
     864: invokeinterface #36,  1           // InterfaceMethod java/util/List.size:()I
     869: i2l
     870: invokestatic  #37                 // Method org/junit/Assert.assertEquals:(JJ)V
     873: iconst_1
     874: istore        9
     876: iload         9
     878: bipush        10
     880: if_icmpge     912
     883: aload         5
     885: iconst_1
     886: anewarray     #16                 // class java/lang/String
     889: dup
     890: iconst_0
     891: aload_0
     892: ldc           #49                 // String file1
     894: iload         9
     896: invokespecial #50                 // Method getFileName:(Ljava/lang/String;I)Ljava/lang/String;
     899: aastore
     900: invokestatic  #38                 // Method org/hamcrest/CoreMatchers.hasItems:([Ljava/lang/Object;)Lorg/hamcrest/Matcher;
     903: invokestatic  #39                 // Method org/junit/Assert.assertThat:(Ljava/lang/Object;Lorg/hamcrest/Matcher;)V
     906: iinc          9, 2
     909: goto          876
     912: getstatic     #8                  // Field STORAGE:Lorg/apache/hadoop/hbase/replication/ZKReplicationQueueStorage;
     915: invokevirtual #70                 // Method org/apache/hadoop/hbase/replication/ZKReplicationQueueStorage.getAllWALs:()Ljava/util/Set;
     918: astore        10
     920: ldc2_w        #34                 // long 10l
     923: aload         10
     925: invokeinterface #71,  1           // InterfaceMethod java/util/Set.size:()I
     930: i2l
     931: invokestatic  #37                 // Method org/junit/Assert.assertEquals:(JJ)V
     934: iconst_0
     935: istore        9
     937: iload         9
     939: bipush        10
     941: if_icmpge     991
     944: aload         10
     946: iconst_1
     947: anewarray     #16                 // class java/lang/String
     950: dup
     951: iconst_0
     952: iload         9
     954: iconst_2
     955: irem
     956: ifne          970
     959: aload_0
     960: ldc           #51                 // String file2
     962: iload         9
     964: invokespecial #50                 // Method getFileName:(Ljava/lang/String;I)Ljava/lang/String;
     967: goto          978
     970: aload_0
     971: ldc           #49                 // String file1
     973: iload         9
     975: invokespecial #50                 // Method getFileName:(Ljava/lang/String;I)Ljava/lang/String;
     978: aastore
     979: invokestatic  #38                 // Method org/hamcrest/CoreMatchers.hasItems:([Ljava/lang/Object;)Lorg/hamcrest/Matcher;
     982: invokestatic  #39                 // Method org/junit/Assert.assertThat:(Ljava/lang/Object;Lorg/hamcrest/Matcher;)V
     985: iinc          9, 1
     988: goto          937
     991: return

  public void testClaimQueueChangeCversion() throws org.apache.hadoop.hbase.replication.ReplicationException, org.apache.zookeeper.KeeperException;
    Code:
       0: ldc           #21                 // String 127.0.0.1
       2: sipush        8000
       5: ldc2_w        #46                 // long 10000l
       8: invokestatic  #22                 // Method org/apache/hadoop/hbase/ServerName.valueOf:(Ljava/lang/String;IJ)Lorg/apache/hadoop/hbase/ServerName;
      11: astore_1
      12: getstatic     #8                  // Field STORAGE:Lorg/apache/hadoop/hbase/replication/ZKReplicationQueueStorage;
      15: aload_1
      16: ldc           #25                 // String 1
      18: ldc           #29                 // String file
      20: invokevirtual #33                 // Method org/apache/hadoop/hbase/replication/ZKReplicationQueueStorage.addWAL:(Lorg/apache/hadoop/hbase/ServerName;Ljava/lang/String;Ljava/lang/String;)V
      23: getstatic     #8                  // Field STORAGE:Lorg/apache/hadoop/hbase/replication/ZKReplicationQueueStorage;
      26: invokevirtual #72                 // Method org/apache/hadoop/hbase/replication/ZKReplicationQueueStorage.getQueuesZNodeCversion:()I
      29: istore_2
      30: ldc           #21                 // String 127.0.0.1
      32: sipush        8001
      35: ldc2_w        #59                 // long 10001l
      38: invokestatic  #22                 // Method org/apache/hadoop/hbase/ServerName.valueOf:(Ljava/lang/String;IJ)Lorg/apache/hadoop/hbase/ServerName;
      41: astore_3
      42: getstatic     #8                  // Field STORAGE:Lorg/apache/hadoop/hbase/replication/ZKReplicationQueueStorage;
      45: aload_1
      46: ldc           #25                 // String 1
      48: aload_3
      49: invokevirtual #61                 // Method org/apache/hadoop/hbase/replication/ZKReplicationQueueStorage.claimQueue:(Lorg/apache/hadoop/hbase/ServerName;Ljava/lang/String;Lorg/apache/hadoop/hbase/ServerName;)Lorg/apache/hadoop/hbase/util/Pair;
      52: pop
      53: getstatic     #8                  // Field STORAGE:Lorg/apache/hadoop/hbase/replication/ZKReplicationQueueStorage;
      56: invokevirtual #72                 // Method org/apache/hadoop/hbase/replication/ZKReplicationQueueStorage.getQueuesZNodeCversion:()I
      59: istore        4
      61: lconst_1
      62: iload         4
      64: iload_2
      65: isub
      66: i2l
      67: invokestatic  #37                 // Method org/junit/Assert.assertEquals:(JJ)V
      70: return

  public void testGetAllWALsCversionChange() throws java.io.IOException, org.apache.hadoop.hbase.replication.ReplicationException;
    Code:
       0: aload_0
       1: invokespecial #75                 // Method createWithUnstableVersion:()Lorg/apache/hadoop/hbase/replication/ZKReplicationQueueStorage;
       4: astore_1
       5: aload_1
       6: aload_0
       7: iconst_0
       8: invokespecial #26                 // Method getServerName:(I)Lorg/apache/hadoop/hbase/ServerName;
      11: ldc           #25                 // String 1
      13: ldc           #29                 // String file
      15: invokevirtual #33                 // Method org/apache/hadoop/hbase/replication/ZKReplicationQueueStorage.addWAL:(Lorg/apache/hadoop/hbase/ServerName;Ljava/lang/String;Ljava/lang/String;)V
      18: aload_1
      19: invokevirtual #70                 // Method org/apache/hadoop/hbase/replication/ZKReplicationQueueStorage.getAllWALs:()Ljava/util/Set;
      22: astore_2
      23: lconst_1
      24: aload_2
      25: invokeinterface #71,  1           // InterfaceMethod java/util/Set.size:()I
      30: i2l
      31: invokestatic  #37                 // Method org/junit/Assert.assertEquals:(JJ)V
      34: aload_2
      35: iconst_1
      36: anewarray     #16                 // class java/lang/String
      39: dup
      40: iconst_0
      41: ldc           #29                 // String file
      43: aastore
      44: invokestatic  #38                 // Method org/hamcrest/CoreMatchers.hasItems:([Ljava/lang/Object;)Lorg/hamcrest/Matcher;
      47: invokestatic  #39                 // Method org/junit/Assert.assertThat:(Ljava/lang/Object;Lorg/hamcrest/Matcher;)V
      50: return

  public void testGetAllHFileRefsCversionChange() throws java.io.IOException, org.apache.hadoop.hbase.replication.ReplicationException;
    Code:
       0: aload_0
       1: invokespecial #75                 // Method createWithUnstableVersion:()Lorg/apache/hadoop/hbase/replication/ZKReplicationQueueStorage;
       4: astore_1
       5: aload_1
       6: ldc           #25                 // String 1
       8: invokevirtual #76                 // Method org/apache/hadoop/hbase/replication/ZKReplicationQueueStorage.addPeerToHFileRefs:(Ljava/lang/String;)V
      11: new           #77                 // class org/apache/hadoop/fs/Path
      14: dup
      15: ldc           #78                 // String /test
      17: invokespecial #79                 // Method org/apache/hadoop/fs/Path."<init>":(Ljava/lang/String;)V
      20: astore_2
      21: aload_1
      22: ldc           #25                 // String 1
      24: iconst_1
      25: anewarray     #80                 // class org/apache/hadoop/hbase/util/Pair
      28: dup
      29: iconst_0
      30: aload_2
      31: aload_2
      32: invokestatic  #81                 // Method org/apache/hadoop/hbase/util/Pair.newPair:(Ljava/lang/Object;Ljava/lang/Object;)Lorg/apache/hadoop/hbase/util/Pair;
      35: aastore
      36: invokestatic  #82                 // Method java/util/Arrays.asList:([Ljava/lang/Object;)Ljava/util/List;
      39: invokevirtual #83                 // Method org/apache/hadoop/hbase/replication/ZKReplicationQueueStorage.addHFileRefs:(Ljava/lang/String;Ljava/util/List;)V
      42: aload_1
      43: invokevirtual #84                 // Method org/apache/hadoop/hbase/replication/ZKReplicationQueueStorage.getAllHFileRefs:()Ljava/util/Set;
      46: astore_3
      47: lconst_1
      48: aload_3
      49: invokeinterface #71,  1           // InterfaceMethod java/util/Set.size:()I
      54: i2l
      55: invokestatic  #37                 // Method org/junit/Assert.assertEquals:(JJ)V
      58: aload_3
      59: iconst_1
      60: anewarray     #16                 // class java/lang/String
      63: dup
      64: iconst_0
      65: ldc           #85                 // String test
      67: aastore
      68: invokestatic  #38                 // Method org/hamcrest/CoreMatchers.hasItems:([Ljava/lang/Object;)Lorg/hamcrest/Matcher;
      71: invokestatic  #39                 // Method org/junit/Assert.assertThat:(Ljava/lang/Object;Lorg/hamcrest/Matcher;)V
      74: return

  public void testSetWALPositionBadVersion() throws java.io.IOException, org.apache.hadoop.hbase.replication.ReplicationException;
    Code:
       0: aload_0
       1: invokespecial #75                 // Method createWithUnstableVersion:()Lorg/apache/hadoop/hbase/replication/ZKReplicationQueueStorage;
       4: astore_1
       5: ldc           #86                 // String 128.0.0.1
       7: sipush        8000
      10: ldc2_w        #46                 // long 10000l
      13: invokestatic  #22                 // Method org/apache/hadoop/hbase/ServerName.valueOf:(Ljava/lang/String;IJ)Lorg/apache/hadoop/hbase/ServerName;
      16: astore_2
      17: aload_1
      18: aload_2
      19: invokevirtual #15                 // Method org/apache/hadoop/hbase/replication/ZKReplicationQueueStorage.getAllQueues:(Lorg/apache/hadoop/hbase/ServerName;)Ljava/util/List;
      22: invokeinterface #23,  1           // InterfaceMethod java/util/List.isEmpty:()Z
      27: invokestatic  #24                 // Method org/junit/Assert.assertTrue:(Z)V
      30: ldc           #25                 // String 1
      32: astore_3
      33: aload_0
      34: ldc           #49                 // String file1
      36: iconst_0
      37: invokespecial #50                 // Method getFileName:(Ljava/lang/String;I)Ljava/lang/String;
      40: astore        4
      42: ldc           #87                 // String 31d9792f4435b99d9fb1016f6fbc8dc6
      44: astore        5
      46: aload_1
      47: aload_2
      48: aload_3
      49: aload         4
      51: invokevirtual #33                 // Method org/apache/hadoop/hbase/replication/ZKReplicationQueueStorage.addWAL:(Lorg/apache/hadoop/hbase/ServerName;Ljava/lang/String;Ljava/lang/String;)V
      54: aload_1
      55: aload_2
      56: aload_3
      57: invokevirtual #54                 // Method org/apache/hadoop/hbase/replication/ZKReplicationQueueStorage.getWALsInQueue:(Lorg/apache/hadoop/hbase/ServerName;Ljava/lang/String;)Ljava/util/List;
      60: astore        6
      62: lconst_1
      63: aload         6
      65: invokeinterface #36,  1           // InterfaceMethod java/util/List.size:()I
      70: i2l
      71: invokestatic  #37                 // Method org/junit/Assert.assertEquals:(JJ)V
      74: lconst_0
      75: aload_1
      76: aload_2
      77: aload_3
      78: aload         4
      80: invokevirtual #55                 // Method org/apache/hadoop/hbase/replication/ZKReplicationQueueStorage.getWALPosition:(Lorg/apache/hadoop/hbase/ServerName;Ljava/lang/String;Ljava/lang/String;)J
      83: invokestatic  #37                 // Method org/junit/Assert.assertEquals:(JJ)V
      86: aload_1
      87: aload_2
      88: aload_3
      89: aload         4
      91: ldc2_w        #88                 // long 100l
      94: aload         5
      96: ldc2_w        #90                 // long 120l
      99: invokestatic  #92                 // Method java/lang/Long.valueOf:(J)Ljava/lang/Long;
     102: invokestatic  #93                 // Method org/apache/hbase/thirdparty/com/google/common/collect/ImmutableMap.of:(Ljava/lang/Object;Ljava/lang/Object;)Lorg/apache/hbase/thirdparty/com/google/common/collect/ImmutableMap;
     105: invokevirtual #57                 // Method org/apache/hadoop/hbase/replication/ZKReplicationQueueStorage.setWALPosition:(Lorg/apache/hadoop/hbase/ServerName;Ljava/lang/String;Ljava/lang/String;JLjava/util/Map;)V
     108: ldc2_w        #88                 // long 100l
     111: aload_1
     112: aload_2
     113: aload_3
     114: aload         4
     116: invokevirtual #55                 // Method org/apache/hadoop/hbase/replication/ZKReplicationQueueStorage.getWALPosition:(Lorg/apache/hadoop/hbase/ServerName;Ljava/lang/String;Ljava/lang/String;)J
     119: invokestatic  #37                 // Method org/junit/Assert.assertEquals:(JJ)V
     122: ldc2_w        #90                 // long 120l
     125: aload_1
     126: aload         5
     128: aload_3
     129: invokevirtual #94                 // Method org/apache/hadoop/hbase/replication/ZKReplicationQueueStorage.getLastSequenceId:(Ljava/lang/String;Ljava/lang/String;)J
     132: invokestatic  #37                 // Method org/junit/Assert.assertEquals:(JJ)V
     135: return

  public void testRegionsZNodeLayout() throws java.lang.Exception;
    Code:
       0: ldc           #25                 // String 1
       2: astore_1
       3: ldc           #95                 // String 31d9792f4435b99d9fb1016f6fbc8dc7
       5: astore_2
       6: new           #27                 // class java/lang/StringBuilder
       9: dup
      10: invokespecial #28                 // Method java/lang/StringBuilder."<init>":()V
      13: ldc           #96                 // String /hbase/replication/regions/31/d9/792f4435b99d9fb1016f6fbc8dc7-
      15: invokevirtual #30                 // Method java/lang/StringBuilder.append:(Ljava/lang/String;)Ljava/lang/StringBuilder;
      18: aload_1
      19: invokevirtual #30                 // Method java/lang/StringBuilder.append:(Ljava/lang/String;)Ljava/lang/StringBuilder;
      22: invokevirtual #32                 // Method java/lang/StringBuilder.toString:()Ljava/lang/String;
      25: astore_3
      26: getstatic     #8                  // Field STORAGE:Lorg/apache/hadoop/hbase/replication/ZKReplicationQueueStorage;
      29: aload_2
      30: aload_1
      31: invokevirtual #97                 // Method org/apache/hadoop/hbase/replication/ZKReplicationQueueStorage.getSerialReplicationRegionPeerNode:(Ljava/lang/String;Ljava/lang/String;)Ljava/lang/String;
      34: astore        4
      36: aload_3
      37: aload         4
      39: invokestatic  #65                 // Method org/junit/Assert.assertEquals:(Ljava/lang/Object;Ljava/lang/Object;)V
      42: return

  public void testRemoveAllLastPushedSeqIdsForPeer() throws java.lang.Exception;
    Code:
       0: ldc           #25                 // String 1
       2: astore_1
       3: ldc           #48                 // String 2
       5: astore_2
       6: iconst_0
       7: istore_3
       8: iload_3
       9: bipush        100
      11: if_icmpge     63
      14: iload_3
      15: invokestatic  #98                 // Method org/apache/hadoop/hbase/util/Bytes.toBytes:(I)[B
      18: invokestatic  #99                 // Method org/apache/hadoop/hbase/util/MD5Hash.getMD5AsHex:([B)Ljava/lang/String;
      21: astore        4
      23: getstatic     #8                  // Field STORAGE:Lorg/apache/hadoop/hbase/replication/ZKReplicationQueueStorage;
      26: aload_1
      27: aload         4
      29: iload_3
      30: i2l
      31: invokestatic  #92                 // Method java/lang/Long.valueOf:(J)Ljava/lang/Long;
      34: invokestatic  #93                 // Method org/apache/hbase/thirdparty/com/google/common/collect/ImmutableMap.of:(Ljava/lang/Object;Ljava/lang/Object;)Lorg/apache/hbase/thirdparty/com/google/common/collect/ImmutableMap;
      37: invokevirtual #100                // Method org/apache/hadoop/hbase/replication/ZKReplicationQueueStorage.setLastSequenceIds:(Ljava/lang/String;Ljava/util/Map;)V
      40: getstatic     #8                  // Field STORAGE:Lorg/apache/hadoop/hbase/replication/ZKReplicationQueueStorage;
      43: aload_2
      44: aload         4
      46: iload_3
      47: i2l
      48: invokestatic  #92                 // Method java/lang/Long.valueOf:(J)Ljava/lang/Long;
      51: invokestatic  #93                 // Method org/apache/hbase/thirdparty/com/google/common/collect/ImmutableMap.of:(Ljava/lang/Object;Ljava/lang/Object;)Lorg/apache/hbase/thirdparty/com/google/common/collect/ImmutableMap;
      54: invokevirtual #100                // Method org/apache/hadoop/hbase/replication/ZKReplicationQueueStorage.setLastSequenceIds:(Ljava/lang/String;Ljava/util/Map;)V
      57: iinc          3, 1
      60: goto          8
      63: iconst_0
      64: istore_3
      65: iload_3
      66: bipush        100
      68: if_icmpge     114
      71: iload_3
      72: invokestatic  #98                 // Method org/apache/hadoop/hbase/util/Bytes.toBytes:(I)[B
      75: invokestatic  #99                 // Method org/apache/hadoop/hbase/util/MD5Hash.getMD5AsHex:([B)Ljava/lang/String;
      78: astore        4
      80: iload_3
      81: i2l
      82: getstatic     #8                  // Field STORAGE:Lorg/apache/hadoop/hbase/replication/ZKReplicationQueueStorage;
      85: aload         4
      87: aload_1
      88: invokevirtual #94                 // Method org/apache/hadoop/hbase/replication/ZKReplicationQueueStorage.getLastSequenceId:(Ljava/lang/String;Ljava/lang/String;)J
      91: invokestatic  #37                 // Method org/junit/Assert.assertEquals:(JJ)V
      94: iload_3
      95: i2l
      96: getstatic     #8                  // Field STORAGE:Lorg/apache/hadoop/hbase/replication/ZKReplicationQueueStorage;
      99: aload         4
     101: aload_2
     102: invokevirtual #94                 // Method org/apache/hadoop/hbase/replication/ZKReplicationQueueStorage.getLastSequenceId:(Ljava/lang/String;Ljava/lang/String;)J
     105: invokestatic  #37                 // Method org/junit/Assert.assertEquals:(JJ)V
     108: iinc          3, 1
     111: goto          65
     114: getstatic     #8                  // Field STORAGE:Lorg/apache/hadoop/hbase/replication/ZKReplicationQueueStorage;
     117: aload_2
     118: invokevirtual #101                // Method org/apache/hadoop/hbase/replication/ZKReplicationQueueStorage.removeLastSequenceIds:(Ljava/lang/String;)V
     121: iconst_0
     122: istore_3
     123: iload_3
     124: bipush        100
     126: if_icmpge     173
     129: iload_3
     130: invokestatic  #98                 // Method org/apache/hadoop/hbase/util/Bytes.toBytes:(I)[B
     133: invokestatic  #99                 // Method org/apache/hadoop/hbase/util/MD5Hash.getMD5AsHex:([B)Ljava/lang/String;
     136: astore        4
     138: iload_3
     139: i2l
     140: getstatic     #8                  // Field STORAGE:Lorg/apache/hadoop/hbase/replication/ZKReplicationQueueStorage;
     143: aload         4
     145: aload_1
     146: invokevirtual #94                 // Method org/apache/hadoop/hbase/replication/ZKReplicationQueueStorage.getLastSequenceId:(Ljava/lang/String;Ljava/lang/String;)J
     149: invokestatic  #37                 // Method org/junit/Assert.assertEquals:(JJ)V
     152: ldc2_w        #103                // long -1l
     155: getstatic     #8                  // Field STORAGE:Lorg/apache/hadoop/hbase/replication/ZKReplicationQueueStorage;
     158: aload         4
     160: aload_2
     161: invokevirtual #94                 // Method org/apache/hadoop/hbase/replication/ZKReplicationQueueStorage.getLastSequenceId:(Ljava/lang/String;Ljava/lang/String;)J
     164: invokestatic  #37                 // Method org/junit/Assert.assertEquals:(JJ)V
     167: iinc          3, 1
     170: goto          123
     173: return

  static {};
    Code:
       0: ldc           #105                // class org/apache/hadoop/hbase/replication/TestZKReplicationQueueStorage
       2: invokestatic  #106                // Method org/apache/hadoop/hbase/HBaseClassTestRule.forClass:(Ljava/lang/Class;)Lorg/apache/hadoop/hbase/HBaseClassTestRule;
       5: putstatic     #107                // Field CLASS_RULE:Lorg/apache/hadoop/hbase/HBaseClassTestRule;
       8: new           #108                // class org/apache/hadoop/hbase/HBaseZKTestingUtility
      11: dup
      12: invokespecial #109                // Method org/apache/hadoop/hbase/HBaseZKTestingUtility."<init>":()V
      15: putstatic     #2                  // Field UTIL:Lorg/apache/hadoop/hbase/HBaseZKTestingUtility;
      18: return
}
