Compiled from "TestHFileSeek.java"
class org.apache.hadoop.hbase.io.hfile.TestHFileSeek$MyOptions {
  int dictSize;

  int minWordLen;

  int maxWordLen;

  java.lang.String rootDir;

  java.lang.String file;

  java.lang.String compress;

  int minKeyLen;

  int maxKeyLen;

  int minValLength;

  int maxValLength;

  int minBlockSize;

  int fsOutputBufferSize;

  int fsInputBufferSize;

  long fileSize;

  long seekCount;

  long trialCount;

  long seed;

  boolean useRawFs;

  static final int OP_CREATE;

  static final int OP_READ;

  int op;

  boolean proceed;

  public org.apache.hadoop.hbase.io.hfile.TestHFileSeek$MyOptions(java.lang.String[]);
    Code:
       0: aload_0
       1: invokespecial #1                  // Method java/lang/Object."<init>":()V
       4: aload_0
       5: sipush        1000
       8: putfield      #2                  // Field dictSize:I
      11: aload_0
      12: iconst_5
      13: putfield      #3                  // Field minWordLen:I
      16: aload_0
      17: bipush        20
      19: putfield      #4                  // Field maxWordLen:I
      22: aload_0
      23: new           #5                  // class org/apache/hadoop/hbase/HBaseTestingUtility
      26: dup
      27: invokespecial #6                  // Method org/apache/hadoop/hbase/HBaseTestingUtility."<init>":()V
      30: putfield      #7                  // Field TEST_UTIL:Lorg/apache/hadoop/hbase/HBaseTestingUtility;
      33: aload_0
      34: aload_0
      35: getfield      #7                  // Field TEST_UTIL:Lorg/apache/hadoop/hbase/HBaseTestingUtility;
      38: ldc           #8                  // String TestTFileSeek
      40: invokevirtual #9                  // Method org/apache/hadoop/hbase/HBaseTestingUtility.getDataTestDir:(Ljava/lang/String;)Lorg/apache/hadoop/fs/Path;
      43: invokevirtual #10                 // Method org/apache/hadoop/fs/Path.toString:()Ljava/lang/String;
      46: putfield      #11                 // Field rootDir:Ljava/lang/String;
      49: aload_0
      50: ldc           #8                  // String TestTFileSeek
      52: putfield      #12                 // Field file:Ljava/lang/String;
      55: aload_0
      56: ldc           #13                 // String none
      58: putfield      #14                 // Field compress:Ljava/lang/String;
      61: aload_0
      62: bipush        10
      64: putfield      #15                 // Field minKeyLen:I
      67: aload_0
      68: bipush        50
      70: putfield      #16                 // Field maxKeyLen:I
      73: aload_0
      74: sipush        1024
      77: putfield      #17                 // Field minValLength:I
      80: aload_0
      81: sipush        2048
      84: putfield      #18                 // Field maxValLength:I
      87: aload_0
      88: ldc           #19                 // int 1048576
      90: putfield      #20                 // Field minBlockSize:I
      93: aload_0
      94: iconst_1
      95: putfield      #21                 // Field fsOutputBufferSize:I
      98: aload_0
      99: iconst_0
     100: putfield      #22                 // Field fsInputBufferSize:I
     103: aload_0
     104: ldc2_w        #23                 // long 10485760l
     107: putfield      #25                 // Field fileSize:J
     110: aload_0
     111: ldc2_w        #26                 // long 1000l
     114: putfield      #28                 // Field seekCount:J
     117: aload_0
     118: lconst_1
     119: putfield      #29                 // Field trialCount:J
     122: aload_0
     123: iconst_0
     124: putfield      #30                 // Field useRawFs:Z
     127: aload_0
     128: iconst_3
     129: putfield      #32                 // Field op:I
     132: aload_0
     133: iconst_0
     134: putfield      #33                 // Field proceed:Z
     137: aload_0
     138: invokestatic  #34                 // Method java/lang/System.nanoTime:()J
     141: putfield      #35                 // Field seed:J
     144: aload_0
     145: invokespecial #36                 // Method buildOptions:()Lorg/apache/hbase/thirdparty/org/apache/commons/cli/Options;
     148: astore_2
     149: new           #37                 // class org/apache/hbase/thirdparty/org/apache/commons/cli/GnuParser
     152: dup
     153: invokespecial #38                 // Method org/apache/hbase/thirdparty/org/apache/commons/cli/GnuParser."<init>":()V
     156: astore_3
     157: aload_3
     158: aload_2
     159: aload_1
     160: iconst_1
     161: invokeinterface #39,  4           // InterfaceMethod org/apache/hbase/thirdparty/org/apache/commons/cli/CommandLineParser.parse:(Lorg/apache/hbase/thirdparty/org/apache/commons/cli/Options;[Ljava/lang/String;Z)Lorg/apache/hbase/thirdparty/org/apache/commons/cli/CommandLine;
     166: astore        4
     168: aload_0
     169: aload         4
     171: aload_2
     172: invokespecial #40                 // Method processOptions:(Lorg/apache/hbase/thirdparty/org/apache/commons/cli/CommandLine;Lorg/apache/hbase/thirdparty/org/apache/commons/cli/Options;)V
     175: aload_0
     176: invokespecial #41                 // Method validateOptions:()V
     179: goto          205
     182: astore_2
     183: getstatic     #43                 // Field java/lang/System.out:Ljava/io/PrintStream;
     186: aload_2
     187: invokevirtual #44                 // Method org/apache/hbase/thirdparty/org/apache/commons/cli/ParseException.getMessage:()Ljava/lang/String;
     190: invokevirtual #45                 // Method java/io/PrintStream.println:(Ljava/lang/String;)V
     193: getstatic     #43                 // Field java/lang/System.out:Ljava/io/PrintStream;
     196: ldc           #46                 // String Try \"--help\" option for details.
     198: invokevirtual #45                 // Method java/io/PrintStream.println:(Ljava/lang/String;)V
     201: aload_0
     202: invokespecial #47                 // Method setStopProceed:()V
     205: return
    Exception table:
       from    to  target type
         144   179   182   Class org/apache/hbase/thirdparty/org/apache/commons/cli/ParseException

  public boolean proceed();
    Code:
       0: aload_0
       1: getfield      #33                 // Field proceed:Z
       4: ireturn

  public boolean doCreate();
    Code:
       0: aload_0
       1: getfield      #32                 // Field op:I
       4: iconst_1
       5: iand
       6: ifeq          13
       9: iconst_1
      10: goto          14
      13: iconst_0
      14: ireturn

  public boolean doRead();
    Code:
       0: aload_0
       1: getfield      #32                 // Field op:I
       4: iconst_2
       5: iand
       6: ifeq          13
       9: iconst_1
      10: goto          14
      13: iconst_0
      14: ireturn
}
