Compiled from "TestBufferedMutator.java"
public class org.apache.hadoop.hbase.client.TestBufferedMutator {
  public static final org.apache.hadoop.hbase.HBaseClassTestRule CLASS_RULE;

  public org.junit.rules.TestName name;

  public org.apache.hadoop.hbase.client.TestBufferedMutator();
    Code:
       0: aload_0
       1: invokespecial #1                  // Method java/lang/Object."<init>":()V
       4: aload_0
       5: new           #2                  // class org/junit/rules/TestName
       8: dup
       9: invokespecial #3                  // Method org/junit/rules/TestName."<init>":()V
      12: putfield      #4                  // Field name:Lorg/junit/rules/TestName;
      15: return

  public void testAlternateBufferedMutatorImpl() throws java.io.IOException;
    Code:
       0: new           #5                  // class org/apache/hadoop/hbase/client/BufferedMutatorParams
       3: dup
       4: aload_0
       5: getfield      #4                  // Field name:Lorg/junit/rules/TestName;
       8: invokevirtual #6                  // Method org/junit/rules/TestName.getMethodName:()Ljava/lang/String;
      11: invokestatic  #7                  // Method org/apache/hadoop/hbase/TableName.valueOf:(Ljava/lang/String;)Lorg/apache/hadoop/hbase/TableName;
      14: invokespecial #8                  // Method org/apache/hadoop/hbase/client/BufferedMutatorParams."<init>":(Lorg/apache/hadoop/hbase/TableName;)V
      17: astore_1
      18: invokestatic  #9                  // Method org/apache/hadoop/hbase/HBaseConfiguration.create:()Lorg/apache/hadoop/conf/Configuration;
      21: astore_2
      22: aload_2
      23: ldc           #11                 // String hbase.client.registry.impl
      25: ldc           #12                 // class org/apache/hadoop/hbase/client/DoNothingAsyncRegistry
      27: invokevirtual #13                 // Method java/lang/Class.getName:()Ljava/lang/String;
      30: invokevirtual #14                 // Method org/apache/hadoop/conf/Configuration.set:(Ljava/lang/String;Ljava/lang/String;)V
      33: aload_2
      34: invokestatic  #15                 // Method org/apache/hadoop/hbase/client/ConnectionFactory.createConnection:(Lorg/apache/hadoop/conf/Configuration;)Lorg/apache/hadoop/hbase/client/Connection;
      37: astore_3
      38: aconst_null
      39: astore        4
      41: aload_3
      42: aload_1
      43: invokeinterface #16,  2           // InterfaceMethod org/apache/hadoop/hbase/client/Connection.getBufferedMutator:(Lorg/apache/hadoop/hbase/client/BufferedMutatorParams;)Lorg/apache/hadoop/hbase/client/BufferedMutator;
      48: astore        5
      50: aload         5
      52: instanceof    #17                 // class org/apache/hadoop/hbase/client/BufferedMutatorImpl
      55: invokestatic  #18                 // Method org/junit/Assert.assertTrue:(Z)V
      58: aload_1
      59: ldc           #19                 // class org/apache/hadoop/hbase/client/TestBufferedMutator$MyBufferedMutator
      61: invokevirtual #13                 // Method java/lang/Class.getName:()Ljava/lang/String;
      64: invokevirtual #20                 // Method org/apache/hadoop/hbase/client/BufferedMutatorParams.implementationClassName:(Ljava/lang/String;)Lorg/apache/hadoop/hbase/client/BufferedMutatorParams;
      67: pop
      68: aload_3
      69: aload_1
      70: invokeinterface #16,  2           // InterfaceMethod org/apache/hadoop/hbase/client/Connection.getBufferedMutator:(Lorg/apache/hadoop/hbase/client/BufferedMutatorParams;)Lorg/apache/hadoop/hbase/client/BufferedMutator;
      75: astore        5
      77: aload         5
      79: instanceof    #19                 // class org/apache/hadoop/hbase/client/TestBufferedMutator$MyBufferedMutator
      82: invokestatic  #18                 // Method org/junit/Assert.assertTrue:(Z)V
      85: aload_3
      86: ifnull        174
      89: aload         4
      91: ifnull        115
      94: aload_3
      95: invokeinterface #21,  1           // InterfaceMethod org/apache/hadoop/hbase/client/Connection.close:()V
     100: goto          174
     103: astore        5
     105: aload         4
     107: aload         5
     109: invokevirtual #23                 // Method java/lang/Throwable.addSuppressed:(Ljava/lang/Throwable;)V
     112: goto          174
     115: aload_3
     116: invokeinterface #21,  1           // InterfaceMethod org/apache/hadoop/hbase/client/Connection.close:()V
     121: goto          174
     124: astore        5
     126: aload         5
     128: astore        4
     130: aload         5
     132: athrow
     133: astore        6
     135: aload_3
     136: ifnull        171
     139: aload         4
     141: ifnull        165
     144: aload_3
     145: invokeinterface #21,  1           // InterfaceMethod org/apache/hadoop/hbase/client/Connection.close:()V
     150: goto          171
     153: astore        7
     155: aload         4
     157: aload         7
     159: invokevirtual #23                 // Method java/lang/Throwable.addSuppressed:(Ljava/lang/Throwable;)V
     162: goto          171
     165: aload_3
     166: invokeinterface #21,  1           // InterfaceMethod org/apache/hadoop/hbase/client/Connection.close:()V
     171: aload         6
     173: athrow
     174: aload_2
     175: ldc           #25                 // String hbase.client.bufferedmutator.classname
     177: ldc           #19                 // class org/apache/hadoop/hbase/client/TestBufferedMutator$MyBufferedMutator
     179: invokevirtual #13                 // Method java/lang/Class.getName:()Ljava/lang/String;
     182: invokevirtual #14                 // Method org/apache/hadoop/conf/Configuration.set:(Ljava/lang/String;Ljava/lang/String;)V
     185: aload_2
     186: invokestatic  #15                 // Method org/apache/hadoop/hbase/client/ConnectionFactory.createConnection:(Lorg/apache/hadoop/conf/Configuration;)Lorg/apache/hadoop/hbase/client/Connection;
     189: astore_3
     190: aconst_null
     191: astore        4
     193: aload_3
     194: aload_1
     195: invokeinterface #16,  2           // InterfaceMethod org/apache/hadoop/hbase/client/Connection.getBufferedMutator:(Lorg/apache/hadoop/hbase/client/BufferedMutatorParams;)Lorg/apache/hadoop/hbase/client/BufferedMutator;
     200: astore        5
     202: aload         5
     204: instanceof    #19                 // class org/apache/hadoop/hbase/client/TestBufferedMutator$MyBufferedMutator
     207: invokestatic  #18                 // Method org/junit/Assert.assertTrue:(Z)V
     210: aload_3
     211: ifnull        299
     214: aload         4
     216: ifnull        240
     219: aload_3
     220: invokeinterface #21,  1           // InterfaceMethod org/apache/hadoop/hbase/client/Connection.close:()V
     225: goto          299
     228: astore        5
     230: aload         4
     232: aload         5
     234: invokevirtual #23                 // Method java/lang/Throwable.addSuppressed:(Ljava/lang/Throwable;)V
     237: goto          299
     240: aload_3
     241: invokeinterface #21,  1           // InterfaceMethod org/apache/hadoop/hbase/client/Connection.close:()V
     246: goto          299
     249: astore        5
     251: aload         5
     253: astore        4
     255: aload         5
     257: athrow
     258: astore        8
     260: aload_3
     261: ifnull        296
     264: aload         4
     266: ifnull        290
     269: aload_3
     270: invokeinterface #21,  1           // InterfaceMethod org/apache/hadoop/hbase/client/Connection.close:()V
     275: goto          296
     278: astore        9
     280: aload         4
     282: aload         9
     284: invokevirtual #23                 // Method java/lang/Throwable.addSuppressed:(Ljava/lang/Throwable;)V
     287: goto          296
     290: aload_3
     291: invokeinterface #21,  1           // InterfaceMethod org/apache/hadoop/hbase/client/Connection.close:()V
     296: aload         8
     298: athrow
     299: return
    Exception table:
       from    to  target type
          94   100   103   Class java/lang/Throwable
          41    85   124   Class java/lang/Throwable
          41    85   133   any
         144   150   153   Class java/lang/Throwable
         124   135   133   any
         219   225   228   Class java/lang/Throwable
         193   210   249   Class java/lang/Throwable
         193   210   258   any
         269   275   278   Class java/lang/Throwable
         249   260   258   any

  static {};
    Code:
       0: ldc           #26                 // class org/apache/hadoop/hbase/client/TestBufferedMutator
       2: invokestatic  #27                 // Method org/apache/hadoop/hbase/HBaseClassTestRule.forClass:(Ljava/lang/Class;)Lorg/apache/hadoop/hbase/HBaseClassTestRule;
       5: putstatic     #28                 // Field CLASS_RULE:Lorg/apache/hadoop/hbase/HBaseClassTestRule;
       8: return
}
