Compiled from "TestZKReplicationQueueStorage.java"
class org.apache.hadoop.hbase.replication.TestZKReplicationQueueStorage$1 extends org.apache.hadoop.hbase.replication.ZKReplicationQueueStorage {
  final org.apache.hadoop.hbase.replication.TestZKReplicationQueueStorage this$0;

  org.apache.hadoop.hbase.replication.TestZKReplicationQueueStorage$1(org.apache.hadoop.hbase.replication.TestZKReplicationQueueStorage, org.apache.hadoop.hbase.zookeeper.ZKWatcher, org.apache.hadoop.conf.Configuration);
    Code:
       0: aload_0
       1: aload_1
       2: putfield      #1                  // Field this$0:Lorg/apache/hadoop/hbase/replication/TestZKReplicationQueueStorage;
       5: aload_0
       6: aload_2
       7: aload_3
       8: invokespecial #2                  // Method org/apache/hadoop/hbase/replication/ZKReplicationQueueStorage."<init>":(Lorg/apache/hadoop/hbase/zookeeper/ZKWatcher;Lorg/apache/hadoop/conf/Configuration;)V
      11: aload_0
      12: iconst_0
      13: putfield      #3                  // Field called:I
      16: aload_0
      17: iconst_0
      18: putfield      #4                  // Field getLastSeqIdOpIndex:I
      21: return

  protected int getQueuesZNodeCversion() throws org.apache.zookeeper.KeeperException;
    Code:
       0: aload_0
       1: getfield      #3                  // Field called:I
       4: iconst_4
       5: if_icmpge     18
       8: aload_0
       9: dup
      10: getfield      #3                  // Field called:I
      13: iconst_1
      14: iadd
      15: putfield      #3                  // Field called:I
      18: aload_0
      19: getfield      #3                  // Field called:I
      22: ireturn

  protected org.apache.hadoop.hbase.util.Pair<java.lang.Long, java.lang.Integer> getLastSequenceIdWithVersion(java.lang.String, java.lang.String) throws org.apache.zookeeper.KeeperException;
    Code:
       0: aload_0
       1: aload_1
       2: aload_2
       3: invokespecial #5                  // Method org/apache/hadoop/hbase/replication/ZKReplicationQueueStorage.getLastSequenceIdWithVersion:(Ljava/lang/String;Ljava/lang/String;)Lorg/apache/hadoop/hbase/util/Pair;
       6: astore_3
       7: aload_0
       8: getfield      #4                  // Field getLastSeqIdOpIndex:I
      11: bipush        100
      13: if_icmpge     48
      16: aload_0
      17: aload_1
      18: aload_2
      19: invokevirtual #6                  // Method getSerialReplicationRegionPeerNode:(Ljava/lang/String;Ljava/lang/String;)Ljava/lang/String;
      22: astore        4
      24: aload_0
      25: getfield      #7                  // Field zookeeper:Lorg/apache/hadoop/hbase/zookeeper/ZKWatcher;
      28: aload         4
      30: invokestatic  #8                  // Method org/apache/hadoop/hbase/zookeeper/ZKUtil.createWithParents:(Lorg/apache/hadoop/hbase/zookeeper/ZKWatcher;Ljava/lang/String;)V
      33: aload_0
      34: getfield      #7                  // Field zookeeper:Lorg/apache/hadoop/hbase/zookeeper/ZKWatcher;
      37: aload         4
      39: ldc2_w        #9                  // long 100l
      42: invokestatic  #11                 // Method org/apache/hadoop/hbase/zookeeper/ZKUtil.positionToByteArray:(J)[B
      45: invokestatic  #12                 // Method org/apache/hadoop/hbase/zookeeper/ZKUtil.setData:(Lorg/apache/hadoop/hbase/zookeeper/ZKWatcher;Ljava/lang/String;[B)V
      48: aload_0
      49: dup
      50: getfield      #4                  // Field getLastSeqIdOpIndex:I
      53: iconst_1
      54: iadd
      55: putfield      #4                  // Field getLastSeqIdOpIndex:I
      58: aload_3
      59: areturn
}
