Compiled from "TestHttpServer.java"
class org.apache.hadoop.hbase.http.TestHttpServer$DummyServletFilter$1 extends javax.servlet.http.HttpServletRequestWrapper {
  final java.lang.String val$userName;

  final org.apache.hadoop.hbase.http.TestHttpServer$DummyServletFilter this$0;

  org.apache.hadoop.hbase.http.TestHttpServer$DummyServletFilter$1(org.apache.hadoop.hbase.http.TestHttpServer$DummyServletFilter, javax.servlet.http.HttpServletRequest, java.lang.String);
    Code:
       0: aload_0
       1: aload_1
       2: putfield      #1                  // Field this$0:Lorg/apache/hadoop/hbase/http/TestHttpServer$DummyServletFilter;
       5: aload_0
       6: aload_3
       7: putfield      #2                  // Field val$userName:Ljava/lang/String;
      10: aload_0
      11: aload_2
      12: invokespecial #3                  // Method javax/servlet/http/HttpServletRequestWrapper."<init>":(Ljavax/servlet/http/HttpServletRequest;)V
      15: return

  public java.lang.String getRemoteUser();
    Code:
       0: aload_0
       1: getfield      #2                  // Field val$userName:Ljava/lang/String;
       4: areturn
}
