Compiled from "TestIncrementingEnvironmentEdge.java"
public class org.apache.hadoop.hbase.util.TestIncrementingEnvironmentEdge {
  public static final org.apache.hadoop.hbase.HBaseClassTestRule CLASS_RULE;

  public org.apache.hadoop.hbase.util.TestIncrementingEnvironmentEdge();
    Code:
       0: aload_0
       1: invokespecial #1                  // Method java/lang/Object."<init>":()V
       4: return

  public void testGetCurrentTimeUsesSystemClock();
    Code:
       0: new           #2                  // class org/apache/hadoop/hbase/util/IncrementingEnvironmentEdge
       3: dup
       4: lconst_1
       5: invokespecial #3                  // Method org/apache/hadoop/hbase/util/IncrementingEnvironmentEdge."<init>":(J)V
       8: astore_1
       9: lconst_1
      10: aload_1
      11: invokevirtual #4                  // Method org/apache/hadoop/hbase/util/IncrementingEnvironmentEdge.currentTime:()J
      14: invokestatic  #5                  // Method junit/framework/Assert.assertEquals:(JJ)V
      17: ldc2_w        #6                  // long 2l
      20: aload_1
      21: invokevirtual #4                  // Method org/apache/hadoop/hbase/util/IncrementingEnvironmentEdge.currentTime:()J
      24: invokestatic  #5                  // Method junit/framework/Assert.assertEquals:(JJ)V
      27: ldc2_w        #8                  // long 3l
      30: aload_1
      31: invokevirtual #4                  // Method org/apache/hadoop/hbase/util/IncrementingEnvironmentEdge.currentTime:()J
      34: invokestatic  #5                  // Method junit/framework/Assert.assertEquals:(JJ)V
      37: ldc2_w        #10                 // long 4l
      40: aload_1
      41: invokevirtual #4                  // Method org/apache/hadoop/hbase/util/IncrementingEnvironmentEdge.currentTime:()J
      44: invokestatic  #5                  // Method junit/framework/Assert.assertEquals:(JJ)V
      47: return

  static {};
    Code:
       0: ldc           #12                 // class org/apache/hadoop/hbase/util/TestIncrementingEnvironmentEdge
       2: invokestatic  #13                 // Method org/apache/hadoop/hbase/HBaseClassTestRule.forClass:(Ljava/lang/Class;)Lorg/apache/hadoop/hbase/HBaseClassTestRule;
       5: putstatic     #14                 // Field CLASS_RULE:Lorg/apache/hadoop/hbase/HBaseClassTestRule;
       8: return
}
