Compiled from "TestProcedureExecution.java"
public class org.apache.hadoop.hbase.procedure2.TestProcedureExecution {
  public static final org.apache.hadoop.hbase.HBaseClassTestRule CLASS_RULE;

  public org.apache.hadoop.hbase.procedure2.TestProcedureExecution();
    Code:
       0: aload_0
       1: invokespecial #2                  // Method java/lang/Object."<init>":()V
       4: return

  public void setUp() throws java.io.IOException;
    Code:
       0: aload_0
       1: new           #3                  // class org/apache/hadoop/hbase/HBaseCommonTestingUtility
       4: dup
       5: invokespecial #4                  // Method org/apache/hadoop/hbase/HBaseCommonTestingUtility."<init>":()V
       8: putfield      #5                  // Field htu:Lorg/apache/hadoop/hbase/HBaseCommonTestingUtility;
      11: aload_0
      12: aload_0
      13: getfield      #5                  // Field htu:Lorg/apache/hadoop/hbase/HBaseCommonTestingUtility;
      16: invokevirtual #6                  // Method org/apache/hadoop/hbase/HBaseCommonTestingUtility.getDataTestDir:()Lorg/apache/hadoop/fs/Path;
      19: putfield      #7                  // Field testDir:Lorg/apache/hadoop/fs/Path;
      22: aload_0
      23: aload_0
      24: getfield      #7                  // Field testDir:Lorg/apache/hadoop/fs/Path;
      27: aload_0
      28: getfield      #5                  // Field htu:Lorg/apache/hadoop/hbase/HBaseCommonTestingUtility;
      31: invokevirtual #8                  // Method org/apache/hadoop/hbase/HBaseCommonTestingUtility.getConfiguration:()Lorg/apache/hadoop/conf/Configuration;
      34: invokevirtual #9                  // Method org/apache/hadoop/fs/Path.getFileSystem:(Lorg/apache/hadoop/conf/Configuration;)Lorg/apache/hadoop/fs/FileSystem;
      37: putfield      #10                 // Field fs:Lorg/apache/hadoop/fs/FileSystem;
      40: aload_0
      41: getfield      #7                  // Field testDir:Lorg/apache/hadoop/fs/Path;
      44: invokevirtual #11                 // Method org/apache/hadoop/fs/Path.depth:()I
      47: iconst_1
      48: if_icmple     55
      51: iconst_1
      52: goto          56
      55: iconst_0
      56: invokestatic  #12                 // Method org/junit/Assert.assertTrue:(Z)V
      59: aload_0
      60: new           #13                 // class org/apache/hadoop/fs/Path
      63: dup
      64: aload_0
      65: getfield      #7                  // Field testDir:Lorg/apache/hadoop/fs/Path;
      68: ldc           #14                 // String proc-logs
      70: invokespecial #15                 // Method org/apache/hadoop/fs/Path."<init>":(Lorg/apache/hadoop/fs/Path;Ljava/lang/String;)V
      73: putfield      #16                 // Field logDir:Lorg/apache/hadoop/fs/Path;
      76: aload_0
      77: aload_0
      78: getfield      #5                  // Field htu:Lorg/apache/hadoop/hbase/HBaseCommonTestingUtility;
      81: invokevirtual #8                  // Method org/apache/hadoop/hbase/HBaseCommonTestingUtility.getConfiguration:()Lorg/apache/hadoop/conf/Configuration;
      84: aload_0
      85: getfield      #16                 // Field logDir:Lorg/apache/hadoop/fs/Path;
      88: invokestatic  #17                 // Method org/apache/hadoop/hbase/procedure2/ProcedureTestingUtility.createWalStore:(Lorg/apache/hadoop/conf/Configuration;Lorg/apache/hadoop/fs/Path;)Lorg/apache/hadoop/hbase/procedure2/store/wal/WALProcedureStore;
      91: putfield      #18                 // Field procStore:Lorg/apache/hadoop/hbase/procedure2/store/ProcedureStore;
      94: aload_0
      95: new           #19                 // class org/apache/hadoop/hbase/procedure2/ProcedureExecutor
      98: dup
      99: aload_0
     100: getfield      #5                  // Field htu:Lorg/apache/hadoop/hbase/HBaseCommonTestingUtility;
     103: invokevirtual #8                  // Method org/apache/hadoop/hbase/HBaseCommonTestingUtility.getConfiguration:()Lorg/apache/hadoop/conf/Configuration;
     106: aconst_null
     107: aload_0
     108: getfield      #18                 // Field procStore:Lorg/apache/hadoop/hbase/procedure2/store/ProcedureStore;
     111: invokespecial #20                 // Method org/apache/hadoop/hbase/procedure2/ProcedureExecutor."<init>":(Lorg/apache/hadoop/conf/Configuration;Ljava/lang/Object;Lorg/apache/hadoop/hbase/procedure2/store/ProcedureStore;)V
     114: putfield      #21                 // Field procExecutor:Lorg/apache/hadoop/hbase/procedure2/ProcedureExecutor;
     117: aload_0
     118: getfield      #18                 // Field procStore:Lorg/apache/hadoop/hbase/procedure2/store/ProcedureStore;
     121: iconst_1
     122: invokeinterface #23,  2           // InterfaceMethod org/apache/hadoop/hbase/procedure2/store/ProcedureStore.start:(I)V
     127: aload_0
     128: getfield      #21                 // Field procExecutor:Lorg/apache/hadoop/hbase/procedure2/ProcedureExecutor;
     131: iconst_1
     132: iconst_1
     133: invokestatic  #24                 // Method org/apache/hadoop/hbase/procedure2/ProcedureTestingUtility.initAndStartWorkers:(Lorg/apache/hadoop/hbase/procedure2/ProcedureExecutor;IZ)V
     136: return

  public void tearDown() throws java.io.IOException;
    Code:
       0: aload_0
       1: getfield      #21                 // Field procExecutor:Lorg/apache/hadoop/hbase/procedure2/ProcedureExecutor;
       4: invokevirtual #25                 // Method org/apache/hadoop/hbase/procedure2/ProcedureExecutor.stop:()V
       7: aload_0
       8: getfield      #18                 // Field procStore:Lorg/apache/hadoop/hbase/procedure2/store/ProcedureStore;
      11: iconst_0
      12: invokeinterface #26,  2           // InterfaceMethod org/apache/hadoop/hbase/procedure2/store/ProcedureStore.stop:(Z)V
      17: aload_0
      18: getfield      #10                 // Field fs:Lorg/apache/hadoop/fs/FileSystem;
      21: aload_0
      22: getfield      #16                 // Field logDir:Lorg/apache/hadoop/fs/Path;
      25: iconst_1
      26: invokevirtual #27                 // Method org/apache/hadoop/fs/FileSystem.delete:(Lorg/apache/hadoop/fs/Path;Z)Z
      29: pop
      30: return

  public void testBadSubprocList();
    Code:
       0: new           #28                 // class java/util/ArrayList
       3: dup
       4: invokespecial #29                 // Method java/util/ArrayList."<init>":()V
       7: astore_1
       8: new           #30                 // class org/apache/hadoop/hbase/procedure2/TestProcedureExecution$TestSequentialProcedure
      11: dup
      12: ldc           #31                 // String subProc2
      14: aload_1
      15: iconst_0
      16: anewarray     #32                 // class org/apache/hadoop/hbase/procedure2/Procedure
      19: invokespecial #33                 // Method org/apache/hadoop/hbase/procedure2/TestProcedureExecution$TestSequentialProcedure."<init>":(Ljava/lang/String;Ljava/util/List;[Lorg/apache/hadoop/hbase/procedure2/Procedure;)V
      22: astore_2
      23: new           #30                 // class org/apache/hadoop/hbase/procedure2/TestProcedureExecution$TestSequentialProcedure
      26: dup
      27: ldc           #34                 // String subProc1
      29: aload_1
      30: iconst_2
      31: anewarray     #32                 // class org/apache/hadoop/hbase/procedure2/Procedure
      34: dup
      35: iconst_0
      36: aload_2
      37: aastore
      38: dup
      39: iconst_1
      40: getstatic     #35                 // Field NULL_PROC:Lorg/apache/hadoop/hbase/procedure2/Procedure;
      43: aastore
      44: invokespecial #33                 // Method org/apache/hadoop/hbase/procedure2/TestProcedureExecution$TestSequentialProcedure."<init>":(Ljava/lang/String;Ljava/util/List;[Lorg/apache/hadoop/hbase/procedure2/Procedure;)V
      47: astore_3
      48: new           #30                 // class org/apache/hadoop/hbase/procedure2/TestProcedureExecution$TestSequentialProcedure
      51: dup
      52: ldc           #36                 // String rootProc
      54: aload_1
      55: iconst_1
      56: anewarray     #32                 // class org/apache/hadoop/hbase/procedure2/Procedure
      59: dup
      60: iconst_0
      61: aload_3
      62: aastore
      63: invokespecial #33                 // Method org/apache/hadoop/hbase/procedure2/TestProcedureExecution$TestSequentialProcedure."<init>":(Ljava/lang/String;Ljava/util/List;[Lorg/apache/hadoop/hbase/procedure2/Procedure;)V
      66: astore        4
      68: aload_0
      69: getfield      #21                 // Field procExecutor:Lorg/apache/hadoop/hbase/procedure2/ProcedureExecutor;
      72: aload         4
      74: invokestatic  #37                 // Method org/apache/hadoop/hbase/procedure2/ProcedureTestingUtility.submitAndWait:(Lorg/apache/hadoop/hbase/procedure2/ProcedureExecutor;Lorg/apache/hadoop/hbase/procedure2/Procedure;)J
      77: lstore        5
      79: getstatic     #1                  // Field LOG:Lorg/slf4j/Logger;
      82: aload_1
      83: invokestatic  #38                 // Method java/util/Objects.toString:(Ljava/lang/Object;)Ljava/lang/String;
      86: invokeinterface #39,  2           // InterfaceMethod org/slf4j/Logger.info:(Ljava/lang/String;)V
      91: aload_0
      92: getfield      #21                 // Field procExecutor:Lorg/apache/hadoop/hbase/procedure2/ProcedureExecutor;
      95: lload         5
      97: invokevirtual #40                 // Method org/apache/hadoop/hbase/procedure2/ProcedureExecutor.getResult:(J)Lorg/apache/hadoop/hbase/procedure2/Procedure;
     100: astore        7
     102: aload_1
     103: invokevirtual #41                 // Method java/lang/Object.toString:()Ljava/lang/String;
     106: aload         7
     108: invokevirtual #42                 // Method org/apache/hadoop/hbase/procedure2/Procedure.isFailed:()Z
     111: invokestatic  #43                 // Method org/junit/Assert.assertTrue:(Ljava/lang/String;Z)V
     114: aload         7
     116: invokestatic  #44                 // Method org/apache/hadoop/hbase/procedure2/ProcedureTestingUtility.assertIsIllegalArgumentException:(Lorg/apache/hadoop/hbase/procedure2/Procedure;)V
     119: aload_1
     120: invokevirtual #41                 // Method java/lang/Object.toString:()Ljava/lang/String;
     123: ldc2_w        #45                 // long 4l
     126: aload_1
     127: invokeinterface #47,  1           // InterfaceMethod java/util/List.size:()I
     132: i2l
     133: invokestatic  #48                 // Method org/junit/Assert.assertEquals:(Ljava/lang/String;JJ)V
     136: ldc           #49                 // String rootProc-execute
     138: aload_1
     139: iconst_0
     140: invokeinterface #50,  2           // InterfaceMethod java/util/List.get:(I)Ljava/lang/Object;
     145: invokestatic  #51                 // Method org/junit/Assert.assertEquals:(Ljava/lang/Object;Ljava/lang/Object;)V
     148: ldc           #52                 // String subProc1-execute
     150: aload_1
     151: iconst_1
     152: invokeinterface #50,  2           // InterfaceMethod java/util/List.get:(I)Ljava/lang/Object;
     157: invokestatic  #51                 // Method org/junit/Assert.assertEquals:(Ljava/lang/Object;Ljava/lang/Object;)V
     160: ldc           #53                 // String subProc1-rollback
     162: aload_1
     163: iconst_2
     164: invokeinterface #50,  2           // InterfaceMethod java/util/List.get:(I)Ljava/lang/Object;
     169: invokestatic  #51                 // Method org/junit/Assert.assertEquals:(Ljava/lang/Object;Ljava/lang/Object;)V
     172: ldc           #54                 // String rootProc-rollback
     174: aload_1
     175: iconst_3
     176: invokeinterface #50,  2           // InterfaceMethod java/util/List.get:(I)Ljava/lang/Object;
     181: invokestatic  #51                 // Method org/junit/Assert.assertEquals:(Ljava/lang/Object;Ljava/lang/Object;)V
     184: return

  public void testSingleSequentialProc();
    Code:
       0: new           #28                 // class java/util/ArrayList
       3: dup
       4: invokespecial #29                 // Method java/util/ArrayList."<init>":()V
       7: astore_1
       8: new           #30                 // class org/apache/hadoop/hbase/procedure2/TestProcedureExecution$TestSequentialProcedure
      11: dup
      12: ldc           #31                 // String subProc2
      14: aload_1
      15: iconst_0
      16: anewarray     #32                 // class org/apache/hadoop/hbase/procedure2/Procedure
      19: invokespecial #33                 // Method org/apache/hadoop/hbase/procedure2/TestProcedureExecution$TestSequentialProcedure."<init>":(Ljava/lang/String;Ljava/util/List;[Lorg/apache/hadoop/hbase/procedure2/Procedure;)V
      22: astore_2
      23: new           #30                 // class org/apache/hadoop/hbase/procedure2/TestProcedureExecution$TestSequentialProcedure
      26: dup
      27: ldc           #34                 // String subProc1
      29: aload_1
      30: iconst_1
      31: anewarray     #32                 // class org/apache/hadoop/hbase/procedure2/Procedure
      34: dup
      35: iconst_0
      36: aload_2
      37: aastore
      38: invokespecial #33                 // Method org/apache/hadoop/hbase/procedure2/TestProcedureExecution$TestSequentialProcedure."<init>":(Ljava/lang/String;Ljava/util/List;[Lorg/apache/hadoop/hbase/procedure2/Procedure;)V
      41: astore_3
      42: new           #30                 // class org/apache/hadoop/hbase/procedure2/TestProcedureExecution$TestSequentialProcedure
      45: dup
      46: ldc           #36                 // String rootProc
      48: aload_1
      49: iconst_1
      50: anewarray     #32                 // class org/apache/hadoop/hbase/procedure2/Procedure
      53: dup
      54: iconst_0
      55: aload_3
      56: aastore
      57: invokespecial #33                 // Method org/apache/hadoop/hbase/procedure2/TestProcedureExecution$TestSequentialProcedure."<init>":(Ljava/lang/String;Ljava/util/List;[Lorg/apache/hadoop/hbase/procedure2/Procedure;)V
      60: astore        4
      62: aload_0
      63: getfield      #21                 // Field procExecutor:Lorg/apache/hadoop/hbase/procedure2/ProcedureExecutor;
      66: aload         4
      68: invokestatic  #37                 // Method org/apache/hadoop/hbase/procedure2/ProcedureTestingUtility.submitAndWait:(Lorg/apache/hadoop/hbase/procedure2/ProcedureExecutor;Lorg/apache/hadoop/hbase/procedure2/Procedure;)J
      71: lstore        5
      73: getstatic     #1                  // Field LOG:Lorg/slf4j/Logger;
      76: aload_1
      77: invokestatic  #38                 // Method java/util/Objects.toString:(Ljava/lang/Object;)Ljava/lang/String;
      80: invokeinterface #39,  2           // InterfaceMethod org/slf4j/Logger.info:(Ljava/lang/String;)V
      85: aload_0
      86: getfield      #21                 // Field procExecutor:Lorg/apache/hadoop/hbase/procedure2/ProcedureExecutor;
      89: lload         5
      91: invokevirtual #40                 // Method org/apache/hadoop/hbase/procedure2/ProcedureExecutor.getResult:(J)Lorg/apache/hadoop/hbase/procedure2/Procedure;
      94: astore        7
      96: aload         7
      98: invokestatic  #55                 // Method org/apache/hadoop/hbase/procedure2/ProcedureTestingUtility.assertProcNotFailed:(Lorg/apache/hadoop/hbase/procedure2/Procedure;)V
     101: aload_1
     102: invokevirtual #41                 // Method java/lang/Object.toString:()Ljava/lang/String;
     105: ldc2_w        #56                 // long 3l
     108: aload_1
     109: invokeinterface #47,  1           // InterfaceMethod java/util/List.size:()I
     114: i2l
     115: invokestatic  #48                 // Method org/junit/Assert.assertEquals:(Ljava/lang/String;JJ)V
     118: return

  public void testSingleSequentialProcRollback();
    Code:
       0: new           #28                 // class java/util/ArrayList
       3: dup
       4: invokespecial #29                 // Method java/util/ArrayList."<init>":()V
       7: astore_1
       8: new           #30                 // class org/apache/hadoop/hbase/procedure2/TestProcedureExecution$TestSequentialProcedure
      11: dup
      12: ldc           #31                 // String subProc2
      14: aload_1
      15: new           #58                 // class org/apache/hadoop/hbase/procedure2/TestProcedureExecution$TestProcedureException
      18: dup
      19: ldc           #59                 // String fail test
      21: invokespecial #60                 // Method org/apache/hadoop/hbase/procedure2/TestProcedureExecution$TestProcedureException."<init>":(Ljava/lang/String;)V
      24: invokespecial #61                 // Method org/apache/hadoop/hbase/procedure2/TestProcedureExecution$TestSequentialProcedure."<init>":(Ljava/lang/String;Ljava/util/List;Ljava/lang/Exception;)V
      27: astore_2
      28: new           #30                 // class org/apache/hadoop/hbase/procedure2/TestProcedureExecution$TestSequentialProcedure
      31: dup
      32: ldc           #34                 // String subProc1
      34: aload_1
      35: iconst_1
      36: anewarray     #32                 // class org/apache/hadoop/hbase/procedure2/Procedure
      39: dup
      40: iconst_0
      41: aload_2
      42: aastore
      43: invokespecial #33                 // Method org/apache/hadoop/hbase/procedure2/TestProcedureExecution$TestSequentialProcedure."<init>":(Ljava/lang/String;Ljava/util/List;[Lorg/apache/hadoop/hbase/procedure2/Procedure;)V
      46: astore_3
      47: new           #30                 // class org/apache/hadoop/hbase/procedure2/TestProcedureExecution$TestSequentialProcedure
      50: dup
      51: ldc           #36                 // String rootProc
      53: aload_1
      54: iconst_1
      55: anewarray     #32                 // class org/apache/hadoop/hbase/procedure2/Procedure
      58: dup
      59: iconst_0
      60: aload_3
      61: aastore
      62: invokespecial #33                 // Method org/apache/hadoop/hbase/procedure2/TestProcedureExecution$TestSequentialProcedure."<init>":(Ljava/lang/String;Ljava/util/List;[Lorg/apache/hadoop/hbase/procedure2/Procedure;)V
      65: astore        4
      67: aload_0
      68: getfield      #21                 // Field procExecutor:Lorg/apache/hadoop/hbase/procedure2/ProcedureExecutor;
      71: aload         4
      73: invokestatic  #37                 // Method org/apache/hadoop/hbase/procedure2/ProcedureTestingUtility.submitAndWait:(Lorg/apache/hadoop/hbase/procedure2/ProcedureExecutor;Lorg/apache/hadoop/hbase/procedure2/Procedure;)J
      76: lstore        5
      78: getstatic     #1                  // Field LOG:Lorg/slf4j/Logger;
      81: aload_1
      82: invokestatic  #38                 // Method java/util/Objects.toString:(Ljava/lang/Object;)Ljava/lang/String;
      85: invokeinterface #39,  2           // InterfaceMethod org/slf4j/Logger.info:(Ljava/lang/String;)V
      90: aload_0
      91: getfield      #21                 // Field procExecutor:Lorg/apache/hadoop/hbase/procedure2/ProcedureExecutor;
      94: lload         5
      96: invokevirtual #40                 // Method org/apache/hadoop/hbase/procedure2/ProcedureExecutor.getResult:(J)Lorg/apache/hadoop/hbase/procedure2/Procedure;
      99: astore        7
     101: aload_1
     102: invokevirtual #41                 // Method java/lang/Object.toString:()Ljava/lang/String;
     105: aload         7
     107: invokevirtual #42                 // Method org/apache/hadoop/hbase/procedure2/Procedure.isFailed:()Z
     110: invokestatic  #43                 // Method org/junit/Assert.assertTrue:(Ljava/lang/String;Z)V
     113: getstatic     #1                  // Field LOG:Lorg/slf4j/Logger;
     116: aload         7
     118: invokevirtual #62                 // Method org/apache/hadoop/hbase/procedure2/Procedure.getException:()Lorg/apache/hadoop/hbase/procedure2/RemoteProcedureException;
     121: invokevirtual #63                 // Method org/apache/hadoop/hbase/procedure2/RemoteProcedureException.getMessage:()Ljava/lang/String;
     124: invokeinterface #39,  2           // InterfaceMethod org/slf4j/Logger.info:(Ljava/lang/String;)V
     129: aload         7
     131: invokestatic  #64                 // Method org/apache/hadoop/hbase/procedure2/ProcedureTestingUtility.getExceptionCause:(Lorg/apache/hadoop/hbase/procedure2/Procedure;)Ljava/lang/Throwable;
     134: astore        8
     136: new           #65                 // class java/lang/StringBuilder
     139: dup
     140: invokespecial #66                 // Method java/lang/StringBuilder."<init>":()V
     143: ldc           #67                 // String expected TestProcedureException, got
     145: invokevirtual #68                 // Method java/lang/StringBuilder.append:(Ljava/lang/String;)Ljava/lang/StringBuilder;
     148: aload         8
     150: invokevirtual #69                 // Method java/lang/StringBuilder.append:(Ljava/lang/Object;)Ljava/lang/StringBuilder;
     153: invokevirtual #70                 // Method java/lang/StringBuilder.toString:()Ljava/lang/String;
     156: aload         8
     158: instanceof    #58                 // class org/apache/hadoop/hbase/procedure2/TestProcedureExecution$TestProcedureException
     161: invokestatic  #43                 // Method org/junit/Assert.assertTrue:(Ljava/lang/String;Z)V
     164: aload_1
     165: invokevirtual #41                 // Method java/lang/Object.toString:()Ljava/lang/String;
     168: ldc2_w        #71                 // long 6l
     171: aload_1
     172: invokeinterface #47,  1           // InterfaceMethod java/util/List.size:()I
     177: i2l
     178: invokestatic  #48                 // Method org/junit/Assert.assertEquals:(Ljava/lang/String;JJ)V
     181: ldc           #49                 // String rootProc-execute
     183: aload_1
     184: iconst_0
     185: invokeinterface #50,  2           // InterfaceMethod java/util/List.get:(I)Ljava/lang/Object;
     190: invokestatic  #51                 // Method org/junit/Assert.assertEquals:(Ljava/lang/Object;Ljava/lang/Object;)V
     193: ldc           #52                 // String subProc1-execute
     195: aload_1
     196: iconst_1
     197: invokeinterface #50,  2           // InterfaceMethod java/util/List.get:(I)Ljava/lang/Object;
     202: invokestatic  #51                 // Method org/junit/Assert.assertEquals:(Ljava/lang/Object;Ljava/lang/Object;)V
     205: ldc           #73                 // String subProc2-execute
     207: aload_1
     208: iconst_2
     209: invokeinterface #50,  2           // InterfaceMethod java/util/List.get:(I)Ljava/lang/Object;
     214: invokestatic  #51                 // Method org/junit/Assert.assertEquals:(Ljava/lang/Object;Ljava/lang/Object;)V
     217: ldc           #74                 // String subProc2-rollback
     219: aload_1
     220: iconst_3
     221: invokeinterface #50,  2           // InterfaceMethod java/util/List.get:(I)Ljava/lang/Object;
     226: invokestatic  #51                 // Method org/junit/Assert.assertEquals:(Ljava/lang/Object;Ljava/lang/Object;)V
     229: ldc           #53                 // String subProc1-rollback
     231: aload_1
     232: iconst_4
     233: invokeinterface #50,  2           // InterfaceMethod java/util/List.get:(I)Ljava/lang/Object;
     238: invokestatic  #51                 // Method org/junit/Assert.assertEquals:(Ljava/lang/Object;Ljava/lang/Object;)V
     241: ldc           #54                 // String rootProc-rollback
     243: aload_1
     244: iconst_5
     245: invokeinterface #50,  2           // InterfaceMethod java/util/List.get:(I)Ljava/lang/Object;
     250: invokestatic  #51                 // Method org/junit/Assert.assertEquals:(Ljava/lang/Object;Ljava/lang/Object;)V
     253: return

  public void testRollbackRetriableFailure();
    Code:
       0: aload_0
       1: getfield      #21                 // Field procExecutor:Lorg/apache/hadoop/hbase/procedure2/ProcedureExecutor;
       4: new           #75                 // class org/apache/hadoop/hbase/procedure2/TestProcedureExecution$TestFaultyRollback
       7: dup
       8: invokespecial #76                 // Method org/apache/hadoop/hbase/procedure2/TestProcedureExecution$TestFaultyRollback."<init>":()V
      11: invokestatic  #37                 // Method org/apache/hadoop/hbase/procedure2/ProcedureTestingUtility.submitAndWait:(Lorg/apache/hadoop/hbase/procedure2/ProcedureExecutor;Lorg/apache/hadoop/hbase/procedure2/Procedure;)J
      14: lstore_1
      15: aload_0
      16: getfield      #21                 // Field procExecutor:Lorg/apache/hadoop/hbase/procedure2/ProcedureExecutor;
      19: lload_1
      20: invokevirtual #40                 // Method org/apache/hadoop/hbase/procedure2/ProcedureExecutor.getResult:(J)Lorg/apache/hadoop/hbase/procedure2/Procedure;
      23: astore_3
      24: ldc           #77                 // String expected a failure
      26: aload_3
      27: invokevirtual #42                 // Method org/apache/hadoop/hbase/procedure2/Procedure.isFailed:()Z
      30: invokestatic  #43                 // Method org/junit/Assert.assertTrue:(Ljava/lang/String;Z)V
      33: getstatic     #1                  // Field LOG:Lorg/slf4j/Logger;
      36: aload_3
      37: invokevirtual #62                 // Method org/apache/hadoop/hbase/procedure2/Procedure.getException:()Lorg/apache/hadoop/hbase/procedure2/RemoteProcedureException;
      40: invokevirtual #63                 // Method org/apache/hadoop/hbase/procedure2/RemoteProcedureException.getMessage:()Ljava/lang/String;
      43: invokeinterface #39,  2           // InterfaceMethod org/slf4j/Logger.info:(Ljava/lang/String;)V
      48: aload_3
      49: invokestatic  #64                 // Method org/apache/hadoop/hbase/procedure2/ProcedureTestingUtility.getExceptionCause:(Lorg/apache/hadoop/hbase/procedure2/Procedure;)Ljava/lang/Throwable;
      52: astore        4
      54: new           #65                 // class java/lang/StringBuilder
      57: dup
      58: invokespecial #66                 // Method java/lang/StringBuilder."<init>":()V
      61: ldc           #67                 // String expected TestProcedureException, got
      63: invokevirtual #68                 // Method java/lang/StringBuilder.append:(Ljava/lang/String;)Ljava/lang/StringBuilder;
      66: aload         4
      68: invokevirtual #69                 // Method java/lang/StringBuilder.append:(Ljava/lang/Object;)Ljava/lang/StringBuilder;
      71: invokevirtual #70                 // Method java/lang/StringBuilder.toString:()Ljava/lang/String;
      74: aload         4
      76: instanceof    #58                 // class org/apache/hadoop/hbase/procedure2/TestProcedureExecution$TestProcedureException
      79: invokestatic  #43                 // Method org/junit/Assert.assertTrue:(Ljava/lang/String;Z)V
      82: return

  public void testAbortTimeout();
    Code:
       0: sipush        2500
       3: istore_1
       4: new           #28                 // class java/util/ArrayList
       7: dup
       8: invokespecial #29                 // Method java/util/ArrayList."<init>":()V
      11: astore_2
      12: new           #78                 // class org/apache/hadoop/hbase/procedure2/TestProcedureExecution$TestWaitingProcedure
      15: dup
      16: ldc           #79                 // String wproc
      18: aload_2
      19: iconst_0
      20: invokespecial #80                 // Method org/apache/hadoop/hbase/procedure2/TestProcedureExecution$TestWaitingProcedure."<init>":(Ljava/lang/String;Ljava/util/List;Z)V
      23: astore_3
      24: aload_3
      25: sipush        2500
      28: invokevirtual #81                 // Method org/apache/hadoop/hbase/procedure2/Procedure.setTimeout:(I)V
      31: invokestatic  #82                 // Method org/apache/hadoop/hbase/util/EnvironmentEdgeManager.currentTime:()J
      34: lstore        4
      36: aload_0
      37: getfield      #21                 // Field procExecutor:Lorg/apache/hadoop/hbase/procedure2/ProcedureExecutor;
      40: aload_3
      41: invokestatic  #37                 // Method org/apache/hadoop/hbase/procedure2/ProcedureTestingUtility.submitAndWait:(Lorg/apache/hadoop/hbase/procedure2/ProcedureExecutor;Lorg/apache/hadoop/hbase/procedure2/Procedure;)J
      44: lstore        6
      46: invokestatic  #82                 // Method org/apache/hadoop/hbase/util/EnvironmentEdgeManager.currentTime:()J
      49: lload         4
      51: lsub
      52: lstore        8
      54: getstatic     #1                  // Field LOG:Lorg/slf4j/Logger;
      57: aload_2
      58: invokestatic  #38                 // Method java/util/Objects.toString:(Ljava/lang/Object;)Ljava/lang/String;
      61: invokeinterface #39,  2           // InterfaceMethod org/slf4j/Logger.info:(Ljava/lang/String;)V
      66: new           #65                 // class java/lang/StringBuilder
      69: dup
      70: invokespecial #66                 // Method java/lang/StringBuilder."<init>":()V
      73: ldc           #83                 // String we didn't wait enough execTime=
      75: invokevirtual #68                 // Method java/lang/StringBuilder.append:(Ljava/lang/String;)Ljava/lang/StringBuilder;
      78: lload         8
      80: invokevirtual #84                 // Method java/lang/StringBuilder.append:(J)Ljava/lang/StringBuilder;
      83: invokevirtual #70                 // Method java/lang/StringBuilder.toString:()Ljava/lang/String;
      86: lload         8
      88: ldc2_w        #85                 // long 2500l
      91: lcmp
      92: iflt          99
      95: iconst_1
      96: goto          100
      99: iconst_0
     100: invokestatic  #43                 // Method org/junit/Assert.assertTrue:(Ljava/lang/String;Z)V
     103: aload_0
     104: getfield      #21                 // Field procExecutor:Lorg/apache/hadoop/hbase/procedure2/ProcedureExecutor;
     107: lload         6
     109: invokevirtual #40                 // Method org/apache/hadoop/hbase/procedure2/ProcedureExecutor.getResult:(J)Lorg/apache/hadoop/hbase/procedure2/Procedure;
     112: astore        10
     114: aload_2
     115: invokevirtual #41                 // Method java/lang/Object.toString:()Ljava/lang/String;
     118: aload         10
     120: invokevirtual #42                 // Method org/apache/hadoop/hbase/procedure2/Procedure.isFailed:()Z
     123: invokestatic  #43                 // Method org/junit/Assert.assertTrue:(Ljava/lang/String;Z)V
     126: aload         10
     128: invokestatic  #87                 // Method org/apache/hadoop/hbase/procedure2/ProcedureTestingUtility.assertIsTimeoutException:(Lorg/apache/hadoop/hbase/procedure2/Procedure;)V
     131: aload_2
     132: invokevirtual #41                 // Method java/lang/Object.toString:()Ljava/lang/String;
     135: ldc2_w        #88                 // long 2l
     138: aload_2
     139: invokeinterface #47,  1           // InterfaceMethod java/util/List.size:()I
     144: i2l
     145: invokestatic  #48                 // Method org/junit/Assert.assertEquals:(Ljava/lang/String;JJ)V
     148: ldc           #90                 // String wproc-execute
     150: aload_2
     151: iconst_0
     152: invokeinterface #50,  2           // InterfaceMethod java/util/List.get:(I)Ljava/lang/Object;
     157: invokestatic  #51                 // Method org/junit/Assert.assertEquals:(Ljava/lang/Object;Ljava/lang/Object;)V
     160: ldc           #91                 // String wproc-rollback
     162: aload_2
     163: iconst_1
     164: invokeinterface #50,  2           // InterfaceMethod java/util/List.get:(I)Ljava/lang/Object;
     169: invokestatic  #51                 // Method org/junit/Assert.assertEquals:(Ljava/lang/Object;Ljava/lang/Object;)V
     172: return

  public void testAbortTimeoutWithChildren();
    Code:
       0: new           #28                 // class java/util/ArrayList
       3: dup
       4: invokespecial #29                 // Method java/util/ArrayList."<init>":()V
       7: astore_1
       8: new           #78                 // class org/apache/hadoop/hbase/procedure2/TestProcedureExecution$TestWaitingProcedure
      11: dup
      12: ldc           #79                 // String wproc
      14: aload_1
      15: iconst_1
      16: invokespecial #80                 // Method org/apache/hadoop/hbase/procedure2/TestProcedureExecution$TestWaitingProcedure."<init>":(Ljava/lang/String;Ljava/util/List;Z)V
      19: astore_2
      20: aload_2
      21: sipush        2500
      24: invokevirtual #81                 // Method org/apache/hadoop/hbase/procedure2/Procedure.setTimeout:(I)V
      27: aload_0
      28: getfield      #21                 // Field procExecutor:Lorg/apache/hadoop/hbase/procedure2/ProcedureExecutor;
      31: aload_2
      32: invokestatic  #37                 // Method org/apache/hadoop/hbase/procedure2/ProcedureTestingUtility.submitAndWait:(Lorg/apache/hadoop/hbase/procedure2/ProcedureExecutor;Lorg/apache/hadoop/hbase/procedure2/Procedure;)J
      35: lstore_3
      36: getstatic     #1                  // Field LOG:Lorg/slf4j/Logger;
      39: aload_1
      40: invokestatic  #38                 // Method java/util/Objects.toString:(Ljava/lang/Object;)Ljava/lang/String;
      43: invokeinterface #39,  2           // InterfaceMethod org/slf4j/Logger.info:(Ljava/lang/String;)V
      48: aload_0
      49: getfield      #21                 // Field procExecutor:Lorg/apache/hadoop/hbase/procedure2/ProcedureExecutor;
      52: lload_3
      53: invokevirtual #40                 // Method org/apache/hadoop/hbase/procedure2/ProcedureExecutor.getResult:(J)Lorg/apache/hadoop/hbase/procedure2/Procedure;
      56: astore        5
      58: aload_1
      59: invokevirtual #41                 // Method java/lang/Object.toString:()Ljava/lang/String;
      62: aload         5
      64: invokevirtual #42                 // Method org/apache/hadoop/hbase/procedure2/Procedure.isFailed:()Z
      67: invokestatic  #43                 // Method org/junit/Assert.assertTrue:(Ljava/lang/String;Z)V
      70: aload         5
      72: invokestatic  #87                 // Method org/apache/hadoop/hbase/procedure2/ProcedureTestingUtility.assertIsTimeoutException:(Lorg/apache/hadoop/hbase/procedure2/Procedure;)V
      75: aload_1
      76: invokevirtual #41                 // Method java/lang/Object.toString:()Ljava/lang/String;
      79: ldc2_w        #56                 // long 3l
      82: aload_1
      83: invokeinterface #47,  1           // InterfaceMethod java/util/List.size:()I
      88: i2l
      89: invokestatic  #48                 // Method org/junit/Assert.assertEquals:(Ljava/lang/String;JJ)V
      92: ldc           #90                 // String wproc-execute
      94: aload_1
      95: iconst_0
      96: invokeinterface #50,  2           // InterfaceMethod java/util/List.get:(I)Ljava/lang/Object;
     101: invokestatic  #51                 // Method org/junit/Assert.assertEquals:(Ljava/lang/Object;Ljava/lang/Object;)V
     104: ldc           #92                 // String wproc-child-execute
     106: aload_1
     107: iconst_1
     108: invokeinterface #50,  2           // InterfaceMethod java/util/List.get:(I)Ljava/lang/Object;
     113: invokestatic  #51                 // Method org/junit/Assert.assertEquals:(Ljava/lang/Object;Ljava/lang/Object;)V
     116: ldc           #91                 // String wproc-rollback
     118: aload_1
     119: iconst_2
     120: invokeinterface #50,  2           // InterfaceMethod java/util/List.get:(I)Ljava/lang/Object;
     125: invokestatic  #51                 // Method org/junit/Assert.assertEquals:(Ljava/lang/Object;Ljava/lang/Object;)V
     128: return

  static org.slf4j.Logger access$000();
    Code:
       0: getstatic     #1                  // Field LOG:Lorg/slf4j/Logger;
       3: areturn

  static {};
    Code:
       0: ldc           #22                 // class org/apache/hadoop/hbase/procedure2/TestProcedureExecution
       2: invokestatic  #93                 // Method org/apache/hadoop/hbase/HBaseClassTestRule.forClass:(Ljava/lang/Class;)Lorg/apache/hadoop/hbase/HBaseClassTestRule;
       5: putstatic     #94                 // Field CLASS_RULE:Lorg/apache/hadoop/hbase/HBaseClassTestRule;
       8: ldc           #22                 // class org/apache/hadoop/hbase/procedure2/TestProcedureExecution
      10: invokestatic  #95                 // Method org/slf4j/LoggerFactory.getLogger:(Ljava/lang/Class;)Lorg/slf4j/Logger;
      13: putstatic     #1                  // Field LOG:Lorg/slf4j/Logger;
      16: aconst_null
      17: putstatic     #35                 // Field NULL_PROC:Lorg/apache/hadoop/hbase/procedure2/Procedure;
      20: return
}
