Compiled from "TestAsyncNonMetaRegionLocator.java"
class org.apache.hadoop.hbase.client.TestAsyncNonMetaRegionLocator$1 implements org.apache.hadoop.hbase.Waiter$ExplainingPredicate<java.lang.Exception> {
  final org.apache.hadoop.hbase.ServerName val$serverName;

  final org.apache.hadoop.hbase.client.RegionInfo val$region;

  final org.apache.hadoop.hbase.client.TestAsyncNonMetaRegionLocator this$0;

  org.apache.hadoop.hbase.client.TestAsyncNonMetaRegionLocator$1(org.apache.hadoop.hbase.client.TestAsyncNonMetaRegionLocator, org.apache.hadoop.hbase.ServerName, org.apache.hadoop.hbase.client.RegionInfo);
    Code:
       0: aload_0
       1: aload_1
       2: putfield      #1                  // Field this$0:Lorg/apache/hadoop/hbase/client/TestAsyncNonMetaRegionLocator;
       5: aload_0
       6: aload_2
       7: putfield      #2                  // Field val$serverName:Lorg/apache/hadoop/hbase/ServerName;
      10: aload_0
      11: aload_3
      12: putfield      #3                  // Field val$region:Lorg/apache/hadoop/hbase/client/RegionInfo;
      15: aload_0
      16: invokespecial #4                  // Method java/lang/Object."<init>":()V
      19: return

  public boolean evaluate() throws java.lang.Exception;
    Code:
       0: invokestatic  #5                  // Method org/apache/hadoop/hbase/client/TestAsyncNonMetaRegionLocator.access$100:()Lorg/apache/hadoop/hbase/HBaseTestingUtility;
       3: invokestatic  #6                  // Method org/apache/hadoop/hbase/client/TestAsyncNonMetaRegionLocator.access$000:()Lorg/apache/hadoop/hbase/TableName;
       6: invokevirtual #7                  // Method org/apache/hadoop/hbase/HBaseTestingUtility.getRSForFirstRegionInTable:(Lorg/apache/hadoop/hbase/TableName;)Lorg/apache/hadoop/hbase/regionserver/HRegionServer;
       9: invokevirtual #8                  // Method org/apache/hadoop/hbase/regionserver/HRegionServer.getServerName:()Lorg/apache/hadoop/hbase/ServerName;
      12: astore_1
      13: aload_1
      14: ifnull        32
      17: aload_1
      18: aload_0
      19: getfield      #2                  // Field val$serverName:Lorg/apache/hadoop/hbase/ServerName;
      22: invokevirtual #9                  // Method org/apache/hadoop/hbase/ServerName.equals:(Ljava/lang/Object;)Z
      25: ifne          32
      28: iconst_1
      29: goto          33
      32: iconst_0
      33: ireturn

  public java.lang.String explainFailure() throws java.lang.Exception;
    Code:
       0: new           #10                 // class java/lang/StringBuilder
       3: dup
       4: invokespecial #11                 // Method java/lang/StringBuilder."<init>":()V
       7: aload_0
       8: getfield      #3                  // Field val$region:Lorg/apache/hadoop/hbase/client/RegionInfo;
      11: invokeinterface #12,  1           // InterfaceMethod org/apache/hadoop/hbase/client/RegionInfo.getRegionNameAsString:()Ljava/lang/String;
      16: invokevirtual #13                 // Method java/lang/StringBuilder.append:(Ljava/lang/String;)Ljava/lang/StringBuilder;
      19: ldc           #14                 // String  is still on
      21: invokevirtual #13                 // Method java/lang/StringBuilder.append:(Ljava/lang/String;)Ljava/lang/StringBuilder;
      24: aload_0
      25: getfield      #2                  // Field val$serverName:Lorg/apache/hadoop/hbase/ServerName;
      28: invokevirtual #15                 // Method java/lang/StringBuilder.append:(Ljava/lang/Object;)Ljava/lang/StringBuilder;
      31: invokevirtual #16                 // Method java/lang/StringBuilder.toString:()Ljava/lang/String;
      34: areturn
}
