Compiled from "TestMetaShutdownHandler.java"
public class org.apache.hadoop.hbase.master.TestMetaShutdownHandler$MyRegionServer extends org.apache.hadoop.hbase.MiniHBaseCluster$MiniHBaseClusterRegionServer {
  public org.apache.hadoop.hbase.master.TestMetaShutdownHandler$MyRegionServer(org.apache.hadoop.conf.Configuration) throws java.io.IOException, org.apache.zookeeper.KeeperException, java.lang.InterruptedException;
    Code:
       0: aload_0
       1: aload_1
       2: invokespecial #1                  // Method org/apache/hadoop/hbase/MiniHBaseCluster$MiniHBaseClusterRegionServer."<init>":(Lorg/apache/hadoop/conf/Configuration;)V
       5: return

  public void abort(java.lang.String, java.lang.Throwable);
    Code:
       0: ldc2_w        #2                  // long 30000l
       3: invokestatic  #4                  // Method java/lang/Thread.sleep:(J)V
       6: goto          11
       9: astore_3
      10: return
      11: aload_0
      12: aload_1
      13: aload_2
      14: invokespecial #6                  // Method org/apache/hadoop/hbase/MiniHBaseCluster$MiniHBaseClusterRegionServer.abort:(Ljava/lang/String;Ljava/lang/Throwable;)V
      17: return
    Exception table:
       from    to  target type
           0     6     9   Class java/lang/InterruptedException
}
