Compiled from "TestWALSplit.java"
class org.apache.hadoop.hbase.wal.TestWALSplit$8$2 implements org.mockito.stubbing.Answer<org.apache.hadoop.hbase.wal.WAL$Entry> {
  int index;

  final org.apache.hadoop.hbase.wal.TestWALSplit$8 this$1;

  org.apache.hadoop.hbase.wal.TestWALSplit$8$2(org.apache.hadoop.hbase.wal.TestWALSplit$8);
    Code:
       0: aload_0
       1: aload_1
       2: putfield      #1                  // Field this$1:Lorg/apache/hadoop/hbase/wal/TestWALSplit$8;
       5: aload_0
       6: invokespecial #2                  // Method java/lang/Object."<init>":()V
       9: aload_0
      10: iconst_0
      11: putfield      #3                  // Field index:I
      14: return

  public org.apache.hadoop.hbase.wal.WAL$Entry answer(org.mockito.invocation.InvocationOnMock) throws java.lang.Throwable;
    Code:
       0: aload_0
       1: getfield      #3                  // Field index:I
       4: aload_0
       5: getfield      #1                  // Field this$1:Lorg/apache/hadoop/hbase/wal/TestWALSplit$8;
       8: getfield      #4                  // Field org/apache/hadoop/hbase/wal/TestWALSplit$8.val$numFakeEdits:I
      11: if_icmplt     16
      14: aconst_null
      15: areturn
      16: aload_0
      17: getfield      #3                  // Field index:I
      20: aload_0
      21: getfield      #1                  // Field this$1:Lorg/apache/hadoop/hbase/wal/TestWALSplit$8;
      24: getfield      #5                  // Field org/apache/hadoop/hbase/wal/TestWALSplit$8.val$regions:Ljava/util/List;
      27: invokeinterface #6,  1            // InterfaceMethod java/util/List.size:()I
      32: irem
      33: istore_2
      34: iconst_2
      35: newarray       byte
      37: dup
      38: iconst_0
      39: bipush        114
      41: bastore
      42: dup
      43: iconst_1
      44: bipush        48
      46: iload_2
      47: iadd
      48: i2b
      49: bastore
      50: astore_3
      51: invokestatic  #7                  // Method org/apache/hadoop/hbase/wal/TestWALSplit.access$600:()Lorg/apache/hadoop/hbase/TableName;
      54: aload_3
      55: aload_0
      56: getfield      #3                  // Field index:I
      59: aload_0
      60: getfield      #1                  // Field this$1:Lorg/apache/hadoop/hbase/wal/TestWALSplit$8;
      63: getfield      #5                  // Field org/apache/hadoop/hbase/wal/TestWALSplit$8.val$regions:Ljava/util/List;
      66: invokeinterface #6,  1            // InterfaceMethod java/util/List.size:()I
      71: idiv
      72: invokestatic  #8                  // Method org/apache/hadoop/hbase/util/Bytes.toBytes:(I)[B
      75: invokestatic  #9                  // Method org/apache/hadoop/hbase/wal/TestWALSplit.access$1600:()[B
      78: invokestatic  #10                 // Method org/apache/hadoop/hbase/wal/TestWALSplit.access$1400:()[B
      81: invokestatic  #11                 // Method org/apache/hadoop/hbase/wal/TestWALSplit.access$1500:()[B
      84: aload_0
      85: getfield      #3                  // Field index:I
      88: i2l
      89: invokestatic  #12                 // Method org/apache/hadoop/hbase/wal/TestWALSplit.access$1700:(Lorg/apache/hadoop/hbase/TableName;[B[B[B[B[BJ)Lorg/apache/hadoop/hbase/wal/WAL$Entry;
      92: astore        4
      94: aload_0
      95: dup
      96: getfield      #3                  // Field index:I
      99: iconst_1
     100: iadd
     101: putfield      #3                  // Field index:I
     104: aload         4
     106: areturn

  public java.lang.Object answer(org.mockito.invocation.InvocationOnMock) throws java.lang.Throwable;
    Code:
       0: aload_0
       1: aload_1
       2: invokevirtual #13                 // Method answer:(Lorg/mockito/invocation/InvocationOnMock;)Lorg/apache/hadoop/hbase/wal/WAL$Entry;
       5: areturn
}
