Compiled from "TestAvlUtil.java"
class org.apache.hadoop.hbase.util.TestAvlUtil$TestAvlNode extends org.apache.hadoop.hbase.util.AvlUtil$AvlNode<org.apache.hadoop.hbase.util.TestAvlUtil$TestAvlNode> {
  public org.apache.hadoop.hbase.util.TestAvlUtil$TestAvlNode(int);
    Code:
       0: aload_0
       1: invokespecial #1                  // Method org/apache/hadoop/hbase/util/AvlUtil$AvlNode."<init>":()V
       4: aload_0
       5: iload_1
       6: putfield      #2                  // Field key:I
       9: return

  public int getKey();
    Code:
       0: aload_0
       1: getfield      #2                  // Field key:I
       4: ireturn

  public int compareTo(org.apache.hadoop.hbase.util.TestAvlUtil$TestAvlNode);
    Code:
       0: aload_0
       1: getfield      #2                  // Field key:I
       4: aload_1
       5: getfield      #2                  // Field key:I
       8: isub
       9: ireturn

  public java.lang.String toString();
    Code:
       0: ldc           #3                  // String TestAvlNode(%d)
       2: iconst_1
       3: anewarray     #4                  // class java/lang/Object
       6: dup
       7: iconst_0
       8: aload_0
       9: getfield      #2                  // Field key:I
      12: invokestatic  #5                  // Method java/lang/Integer.valueOf:(I)Ljava/lang/Integer;
      15: aastore
      16: invokestatic  #6                  // Method java/lang/String.format:(Ljava/lang/String;[Ljava/lang/Object;)Ljava/lang/String;
      19: areturn

  public int compareTo(org.apache.hadoop.hbase.util.AvlUtil$AvlNode);
    Code:
       0: aload_0
       1: aload_1
       2: checkcast     #7                  // class org/apache/hadoop/hbase/util/TestAvlUtil$TestAvlNode
       5: invokevirtual #8                  // Method compareTo:(Lorg/apache/hadoop/hbase/util/TestAvlUtil$TestAvlNode;)I
       8: ireturn
}
