Compiled from "TestHFileEncryption.java"
public class org.apache.hadoop.hbase.io.hfile.TestHFileEncryption {
  public static final org.apache.hadoop.hbase.HBaseClassTestRule CLASS_RULE;

  public org.apache.hadoop.hbase.io.hfile.TestHFileEncryption();
    Code:
       0: aload_0
       1: invokespecial #1                  // Method java/lang/Object."<init>":()V
       4: return

  public static void setUp() throws java.lang.Exception;
    Code:
       0: getstatic     #2                  // Field TEST_UTIL:Lorg/apache/hadoop/hbase/HBaseTestingUtility;
       3: invokevirtual #3                  // Method org/apache/hadoop/hbase/HBaseTestingUtility.getConfiguration:()Lorg/apache/hadoop/conf/Configuration;
       6: astore_0
       7: aload_0
       8: ldc           #5                  // String hfile.block.cache.size
      10: fconst_0
      11: invokevirtual #6                  // Method org/apache/hadoop/conf/Configuration.setFloat:(Ljava/lang/String;F)V
      14: aload_0
      15: ldc           #7                  // String hbase.crypto.keyprovider
      17: ldc           #8                  // class org/apache/hadoop/hbase/io/crypto/KeyProviderForTesting
      19: invokevirtual #9                  // Method java/lang/Class.getName:()Ljava/lang/String;
      22: invokevirtual #10                 // Method org/apache/hadoop/conf/Configuration.set:(Ljava/lang/String;Ljava/lang/String;)V
      25: aload_0
      26: ldc           #11                 // String hbase.crypto.master.key.name
      28: ldc           #12                 // String hbase
      30: invokevirtual #10                 // Method org/apache/hadoop/conf/Configuration.set:(Ljava/lang/String;Ljava/lang/String;)V
      33: aload_0
      34: ldc           #13                 // String hfile.format.version
      36: iconst_3
      37: invokevirtual #14                 // Method org/apache/hadoop/conf/Configuration.setInt:(Ljava/lang/String;I)V
      40: aload_0
      41: invokestatic  #15                 // Method org/apache/hadoop/fs/FileSystem.get:(Lorg/apache/hadoop/conf/Configuration;)Lorg/apache/hadoop/fs/FileSystem;
      44: putstatic     #16                 // Field fs:Lorg/apache/hadoop/fs/FileSystem;
      47: aload_0
      48: invokestatic  #17                 // Method org/apache/hadoop/hbase/io/crypto/Encryption.newContext:(Lorg/apache/hadoop/conf/Configuration;)Lorg/apache/hadoop/hbase/io/crypto/Encryption$Context;
      51: putstatic     #18                 // Field cryptoContext:Lorg/apache/hadoop/hbase/io/crypto/Encryption$Context;
      54: aload_0
      55: ldc           #19                 // String hbase.crypto.key.algorithm
      57: ldc           #20                 // String AES
      59: invokevirtual #21                 // Method org/apache/hadoop/conf/Configuration.get:(Ljava/lang/String;Ljava/lang/String;)Ljava/lang/String;
      62: astore_1
      63: aload_0
      64: aload_1
      65: invokestatic  #22                 // Method org/apache/hadoop/hbase/io/crypto/Encryption.getCipher:(Lorg/apache/hadoop/conf/Configuration;Ljava/lang/String;)Lorg/apache/hadoop/hbase/io/crypto/Cipher;
      68: astore_2
      69: aload_2
      70: invokestatic  #23                 // Method org/junit/Assert.assertNotNull:(Ljava/lang/Object;)V
      73: getstatic     #18                 // Field cryptoContext:Lorg/apache/hadoop/hbase/io/crypto/Encryption$Context;
      76: aload_2
      77: invokevirtual #24                 // Method org/apache/hadoop/hbase/io/crypto/Encryption$Context.setCipher:(Lorg/apache/hadoop/hbase/io/crypto/Cipher;)Lorg/apache/hadoop/hbase/io/crypto/Encryption$Context;
      80: pop
      81: aload_2
      82: invokevirtual #25                 // Method org/apache/hadoop/hbase/io/crypto/Cipher.getKeyLength:()I
      85: newarray       byte
      87: astore_3
      88: getstatic     #26                 // Field RNG:Ljava/security/SecureRandom;
      91: aload_3
      92: invokevirtual #27                 // Method java/security/SecureRandom.nextBytes:([B)V
      95: getstatic     #18                 // Field cryptoContext:Lorg/apache/hadoop/hbase/io/crypto/Encryption$Context;
      98: aload_3
      99: invokevirtual #28                 // Method org/apache/hadoop/hbase/io/crypto/Encryption$Context.setKey:([B)Lorg/apache/hadoop/hbase/io/crypto/Encryption$Context;
     102: pop
     103: return

  public void testDataBlockEncryption() throws java.io.IOException;
    Code:
       0: bipush        10
       2: istore_1
       3: bipush        10
       5: newarray       int
       7: astore_2
       8: iconst_0
       9: istore_3
      10: iload_3
      11: bipush        10
      13: if_icmpge     39
      16: aload_2
      17: iload_3
      18: sipush        1024
      21: getstatic     #26                 // Field RNG:Ljava/security/SecureRandom;
      24: ldc           #67                 // int 64512
      26: invokevirtual #68                 // Method java/security/SecureRandom.nextInt:(I)I
      29: iadd
      30: iconst_4
      31: idiv
      32: iastore
      33: iinc          3, 1
      36: goto          10
      39: getstatic     #70                 // Field org/apache/hadoop/hbase/io/hfile/TestHFileBlock.COMPRESSION_ALGORITHMS:[Lorg/apache/hadoop/hbase/io/compress/Compression$Algorithm;
      42: astore_3
      43: aload_3
      44: arraylength
      45: istore        4
      47: iconst_0
      48: istore        5
      50: iload         5
      52: iload         4
      54: if_icmpge     306
      57: aload_3
      58: iload         5
      60: aaload
      61: astore        6
      63: new           #71                 // class org/apache/hadoop/fs/Path
      66: dup
      67: getstatic     #2                  // Field TEST_UTIL:Lorg/apache/hadoop/hbase/HBaseTestingUtility;
      70: invokevirtual #72                 // Method org/apache/hadoop/hbase/HBaseTestingUtility.getDataTestDir:()Lorg/apache/hadoop/fs/Path;
      73: new           #36                 // class java/lang/StringBuilder
      76: dup
      77: invokespecial #37                 // Method java/lang/StringBuilder."<init>":()V
      80: ldc           #73                 // String block_v3_
      82: invokevirtual #39                 // Method java/lang/StringBuilder.append:(Ljava/lang/String;)Ljava/lang/StringBuilder;
      85: aload         6
      87: invokevirtual #74                 // Method java/lang/StringBuilder.append:(Ljava/lang/Object;)Ljava/lang/StringBuilder;
      90: ldc           #75                 // String _AES
      92: invokevirtual #39                 // Method java/lang/StringBuilder.append:(Ljava/lang/String;)Ljava/lang/StringBuilder;
      95: invokevirtual #48                 // Method java/lang/StringBuilder.toString:()Ljava/lang/String;
      98: invokespecial #76                 // Method org/apache/hadoop/fs/Path."<init>":(Lorg/apache/hadoop/fs/Path;Ljava/lang/String;)V
     101: astore        7
     103: getstatic     #35                 // Field LOG:Lorg/slf4j/Logger;
     106: new           #36                 // class java/lang/StringBuilder
     109: dup
     110: invokespecial #37                 // Method java/lang/StringBuilder."<init>":()V
     113: ldc           #77                 // String testDataBlockEncryption: encryption=AES compression=
     115: invokevirtual #39                 // Method java/lang/StringBuilder.append:(Ljava/lang/String;)Ljava/lang/StringBuilder;
     118: aload         6
     120: invokevirtual #74                 // Method java/lang/StringBuilder.append:(Ljava/lang/Object;)Ljava/lang/StringBuilder;
     123: invokevirtual #48                 // Method java/lang/StringBuilder.toString:()Ljava/lang/String;
     126: invokeinterface #49,  2           // InterfaceMethod org/slf4j/Logger.info:(Ljava/lang/String;)V
     131: lconst_0
     132: lstore        8
     134: new           #78                 // class org/apache/hadoop/hbase/io/hfile/HFileContextBuilder
     137: dup
     138: invokespecial #79                 // Method org/apache/hadoop/hbase/io/hfile/HFileContextBuilder."<init>":()V
     141: aload         6
     143: invokevirtual #80                 // Method org/apache/hadoop/hbase/io/hfile/HFileContextBuilder.withCompression:(Lorg/apache/hadoop/hbase/io/compress/Compression$Algorithm;)Lorg/apache/hadoop/hbase/io/hfile/HFileContextBuilder;
     146: getstatic     #18                 // Field cryptoContext:Lorg/apache/hadoop/hbase/io/crypto/Encryption$Context;
     149: invokevirtual #81                 // Method org/apache/hadoop/hbase/io/hfile/HFileContextBuilder.withEncryptionContext:(Lorg/apache/hadoop/hbase/io/crypto/Encryption$Context;)Lorg/apache/hadoop/hbase/io/hfile/HFileContextBuilder;
     152: invokevirtual #82                 // Method org/apache/hadoop/hbase/io/hfile/HFileContextBuilder.build:()Lorg/apache/hadoop/hbase/io/hfile/HFileContext;
     155: astore        10
     157: getstatic     #16                 // Field fs:Lorg/apache/hadoop/fs/FileSystem;
     160: aload         7
     162: invokevirtual #83                 // Method org/apache/hadoop/fs/FileSystem.create:(Lorg/apache/hadoop/fs/Path;)Lorg/apache/hadoop/fs/FSDataOutputStream;
     165: astore        11
     167: iconst_0
     168: istore        12
     170: iload         12
     172: bipush        10
     174: if_icmpge     201
     177: lload         8
     179: aload_0
     180: aload         11
     182: aload         10
     184: aload_2
     185: iload         12
     187: iaload
     188: invokespecial #84                 // Method writeBlock:(Lorg/apache/hadoop/fs/FSDataOutputStream;Lorg/apache/hadoop/hbase/io/hfile/HFileContext;I)I
     191: i2l
     192: ladd
     193: lstore        8
     195: iinc          12, 1
     198: goto          170
     201: aload         11
     203: invokevirtual #85                 // Method org/apache/hadoop/fs/FSDataOutputStream.close:()V
     206: goto          219
     209: astore        13
     211: aload         11
     213: invokevirtual #85                 // Method org/apache/hadoop/fs/FSDataOutputStream.close:()V
     216: aload         13
     218: athrow
     219: getstatic     #16                 // Field fs:Lorg/apache/hadoop/fs/FileSystem;
     222: aload         7
     224: invokevirtual #86                 // Method org/apache/hadoop/fs/FileSystem.open:(Lorg/apache/hadoop/fs/Path;)Lorg/apache/hadoop/fs/FSDataInputStream;
     227: astore        12
     229: new           #87                 // class org/apache/hadoop/hbase/io/hfile/HFileBlock$FSReaderImpl
     232: dup
     233: aload         12
     235: lload         8
     237: aload         10
     239: invokespecial #88                 // Method org/apache/hadoop/hbase/io/hfile/HFileBlock$FSReaderImpl."<init>":(Lorg/apache/hadoop/fs/FSDataInputStream;JLorg/apache/hadoop/hbase/io/hfile/HFileContext;)V
     242: astore        13
     244: lconst_0
     245: lstore        14
     247: iconst_0
     248: istore        16
     250: iload         16
     252: bipush        10
     254: if_icmpge     282
     257: lload         14
     259: aload_0
     260: lload         14
     262: aload         10
     264: aload         13
     266: aload_2
     267: iload         16
     269: iaload
     270: invokespecial #89                 // Method readAndVerifyBlock:(JLorg/apache/hadoop/hbase/io/hfile/HFileContext;Lorg/apache/hadoop/hbase/io/hfile/HFileBlock$FSReaderImpl;I)J
     273: ladd
     274: lstore        14
     276: iinc          16, 1
     279: goto          250
     282: aload         12
     284: invokevirtual #90                 // Method org/apache/hadoop/fs/FSDataInputStream.close:()V
     287: goto          300
     290: astore        17
     292: aload         12
     294: invokevirtual #90                 // Method org/apache/hadoop/fs/FSDataInputStream.close:()V
     297: aload         17
     299: athrow
     300: iinc          5, 1
     303: goto          50
     306: return
    Exception table:
       from    to  target type
         167   201   209   any
         209   211   209   any
         229   282   290   any
         290   292   290   any

  public void testHFileEncryptionMetadata() throws java.lang.Exception;
    Code:
       0: getstatic     #2                  // Field TEST_UTIL:Lorg/apache/hadoop/hbase/HBaseTestingUtility;
       3: invokevirtual #3                  // Method org/apache/hadoop/hbase/HBaseTestingUtility.getConfiguration:()Lorg/apache/hadoop/conf/Configuration;
       6: astore_1
       7: new           #91                 // class org/apache/hadoop/hbase/io/hfile/CacheConfig
      10: dup
      11: aload_1
      12: invokespecial #92                 // Method org/apache/hadoop/hbase/io/hfile/CacheConfig."<init>":(Lorg/apache/hadoop/conf/Configuration;)V
      15: astore_2
      16: new           #78                 // class org/apache/hadoop/hbase/io/hfile/HFileContextBuilder
      19: dup
      20: invokespecial #79                 // Method org/apache/hadoop/hbase/io/hfile/HFileContextBuilder."<init>":()V
      23: getstatic     #18                 // Field cryptoContext:Lorg/apache/hadoop/hbase/io/crypto/Encryption$Context;
      26: invokevirtual #81                 // Method org/apache/hadoop/hbase/io/hfile/HFileContextBuilder.withEncryptionContext:(Lorg/apache/hadoop/hbase/io/crypto/Encryption$Context;)Lorg/apache/hadoop/hbase/io/hfile/HFileContextBuilder;
      29: invokevirtual #82                 // Method org/apache/hadoop/hbase/io/hfile/HFileContextBuilder.build:()Lorg/apache/hadoop/hbase/io/hfile/HFileContext;
      32: astore_3
      33: new           #71                 // class org/apache/hadoop/fs/Path
      36: dup
      37: getstatic     #2                  // Field TEST_UTIL:Lorg/apache/hadoop/hbase/HBaseTestingUtility;
      40: invokevirtual #72                 // Method org/apache/hadoop/hbase/HBaseTestingUtility.getDataTestDir:()Lorg/apache/hadoop/fs/Path;
      43: ldc           #93                 // String cryptometa.hfile
      45: invokespecial #76                 // Method org/apache/hadoop/fs/Path."<init>":(Lorg/apache/hadoop/fs/Path;Ljava/lang/String;)V
      48: astore        4
      50: getstatic     #16                 // Field fs:Lorg/apache/hadoop/fs/FileSystem;
      53: aload         4
      55: invokevirtual #83                 // Method org/apache/hadoop/fs/FileSystem.create:(Lorg/apache/hadoop/fs/Path;)Lorg/apache/hadoop/fs/FSDataOutputStream;
      58: astore        5
      60: aload_1
      61: aload_2
      62: invokestatic  #94                 // Method org/apache/hadoop/hbase/io/hfile/HFile.getWriterFactory:(Lorg/apache/hadoop/conf/Configuration;Lorg/apache/hadoop/hbase/io/hfile/CacheConfig;)Lorg/apache/hadoop/hbase/io/hfile/HFile$WriterFactory;
      65: aload         5
      67: invokevirtual #95                 // Method org/apache/hadoop/hbase/io/hfile/HFile$WriterFactory.withOutputStream:(Lorg/apache/hadoop/fs/FSDataOutputStream;)Lorg/apache/hadoop/hbase/io/hfile/HFile$WriterFactory;
      70: aload_3
      71: invokevirtual #96                 // Method org/apache/hadoop/hbase/io/hfile/HFile$WriterFactory.withFileContext:(Lorg/apache/hadoop/hbase/io/hfile/HFileContext;)Lorg/apache/hadoop/hbase/io/hfile/HFile$WriterFactory;
      74: invokevirtual #97                 // Method org/apache/hadoop/hbase/io/hfile/HFile$WriterFactory.create:()Lorg/apache/hadoop/hbase/io/hfile/HFile$Writer;
      77: astore        6
      79: new           #98                 // class org/apache/hadoop/hbase/KeyValue
      82: dup
      83: ldc           #99                 // String foo
      85: invokestatic  #100                // Method org/apache/hadoop/hbase/util/Bytes.toBytes:(Ljava/lang/String;)[B
      88: ldc           #101                // String f1
      90: invokestatic  #100                // Method org/apache/hadoop/hbase/util/Bytes.toBytes:(Ljava/lang/String;)[B
      93: aconst_null
      94: ldc           #102                // String value
      96: invokestatic  #100                // Method org/apache/hadoop/hbase/util/Bytes.toBytes:(Ljava/lang/String;)[B
      99: invokespecial #103                // Method org/apache/hadoop/hbase/KeyValue."<init>":([B[B[B[B)V
     102: astore        7
     104: aload         6
     106: aload         7
     108: invokeinterface #104,  2          // InterfaceMethod org/apache/hadoop/hbase/io/hfile/HFile$Writer.append:(Lorg/apache/hadoop/hbase/Cell;)V
     113: aload         6
     115: invokeinterface #105,  1          // InterfaceMethod org/apache/hadoop/hbase/io/hfile/HFile$Writer.close:()V
     120: aload         5
     122: invokevirtual #85                 // Method org/apache/hadoop/fs/FSDataOutputStream.close:()V
     125: goto          145
     128: astore        8
     130: aload         6
     132: invokeinterface #105,  1          // InterfaceMethod org/apache/hadoop/hbase/io/hfile/HFile$Writer.close:()V
     137: aload         5
     139: invokevirtual #85                 // Method org/apache/hadoop/fs/FSDataOutputStream.close:()V
     142: aload         8
     144: athrow
     145: getstatic     #16                 // Field fs:Lorg/apache/hadoop/fs/FileSystem;
     148: aload         4
     150: aload_2
     151: iconst_1
     152: aload_1
     153: invokestatic  #106                // Method org/apache/hadoop/hbase/io/hfile/HFile.createReader:(Lorg/apache/hadoop/fs/FileSystem;Lorg/apache/hadoop/fs/Path;Lorg/apache/hadoop/hbase/io/hfile/CacheConfig;ZLorg/apache/hadoop/conf/Configuration;)Lorg/apache/hadoop/hbase/io/hfile/HFile$Reader;
     156: astore        7
     158: aload         7
     160: invokeinterface #107,  1          // InterfaceMethod org/apache/hadoop/hbase/io/hfile/HFile$Reader.loadFileInfo:()Ljava/util/Map;
     165: pop
     166: aload         7
     168: invokeinterface #108,  1          // InterfaceMethod org/apache/hadoop/hbase/io/hfile/HFile$Reader.getTrailer:()Lorg/apache/hadoop/hbase/io/hfile/FixedFileTrailer;
     173: astore        8
     175: aload         8
     177: invokevirtual #109                // Method org/apache/hadoop/hbase/io/hfile/FixedFileTrailer.getEncryptionKey:()[B
     180: invokestatic  #23                 // Method org/junit/Assert.assertNotNull:(Ljava/lang/Object;)V
     183: aload         7
     185: invokeinterface #110,  1          // InterfaceMethod org/apache/hadoop/hbase/io/hfile/HFile$Reader.getFileContext:()Lorg/apache/hadoop/hbase/io/hfile/HFileContext;
     190: invokevirtual #111                // Method org/apache/hadoop/hbase/io/hfile/HFileContext.getEncryptionContext:()Lorg/apache/hadoop/hbase/io/crypto/Encryption$Context;
     193: astore        9
     195: aload         9
     197: invokevirtual #112                // Method org/apache/hadoop/hbase/io/crypto/Encryption$Context.getCipher:()Lorg/apache/hadoop/hbase/io/crypto/Cipher;
     200: invokevirtual #113                // Method org/apache/hadoop/hbase/io/crypto/Cipher.getName:()Ljava/lang/String;
     203: getstatic     #18                 // Field cryptoContext:Lorg/apache/hadoop/hbase/io/crypto/Encryption$Context;
     206: invokevirtual #112                // Method org/apache/hadoop/hbase/io/crypto/Encryption$Context.getCipher:()Lorg/apache/hadoop/hbase/io/crypto/Cipher;
     209: invokevirtual #113                // Method org/apache/hadoop/hbase/io/crypto/Cipher.getName:()Ljava/lang/String;
     212: invokestatic  #114                // Method org/junit/Assert.assertEquals:(Ljava/lang/Object;Ljava/lang/Object;)V
     215: aload         9
     217: invokevirtual #115                // Method org/apache/hadoop/hbase/io/crypto/Encryption$Context.getKeyBytes:()[B
     220: getstatic     #18                 // Field cryptoContext:Lorg/apache/hadoop/hbase/io/crypto/Encryption$Context;
     223: invokevirtual #115                // Method org/apache/hadoop/hbase/io/crypto/Encryption$Context.getKeyBytes:()[B
     226: invokestatic  #116                // Method org/apache/hadoop/hbase/util/Bytes.equals:([B[B)Z
     229: invokestatic  #117                // Method org/junit/Assert.assertTrue:(Z)V
     232: aload         7
     234: invokeinterface #118,  1          // InterfaceMethod org/apache/hadoop/hbase/io/hfile/HFile$Reader.close:()V
     239: goto          254
     242: astore        10
     244: aload         7
     246: invokeinterface #118,  1          // InterfaceMethod org/apache/hadoop/hbase/io/hfile/HFile$Reader.close:()V
     251: aload         10
     253: athrow
     254: return
    Exception table:
       from    to  target type
          79   113   128   any
         128   130   128   any
         158   232   242   any
         242   244   242   any

  public void testHFileEncryption() throws java.lang.Exception;
    Code:
       0: new           #119                // class org/apache/hadoop/hbase/util/RedundantKVGenerator
       3: dup
       4: invokespecial #120                // Method org/apache/hadoop/hbase/util/RedundantKVGenerator."<init>":()V
       7: astore_1
       8: aload_1
       9: sipush        1000
      12: invokevirtual #121                // Method org/apache/hadoop/hbase/util/RedundantKVGenerator.generateTestKeyValues:(I)Ljava/util/List;
      15: astore_2
      16: getstatic     #2                  // Field TEST_UTIL:Lorg/apache/hadoop/hbase/HBaseTestingUtility;
      19: invokevirtual #3                  // Method org/apache/hadoop/hbase/HBaseTestingUtility.getConfiguration:()Lorg/apache/hadoop/conf/Configuration;
      22: astore_3
      23: new           #91                 // class org/apache/hadoop/hbase/io/hfile/CacheConfig
      26: dup
      27: aload_3
      28: invokespecial #92                 // Method org/apache/hadoop/hbase/io/hfile/CacheConfig."<init>":(Lorg/apache/hadoop/conf/Configuration;)V
      31: astore        4
      33: invokestatic  #122                // Method org/apache/hadoop/hbase/io/encoding/DataBlockEncoding.values:()[Lorg/apache/hadoop/hbase/io/encoding/DataBlockEncoding;
      36: astore        5
      38: aload         5
      40: arraylength
      41: istore        6
      43: iconst_0
      44: istore        7
      46: iload         7
      48: iload         6
      50: if_icmpge     667
      53: aload         5
      55: iload         7
      57: aaload
      58: astore        8
      60: getstatic     #70                 // Field org/apache/hadoop/hbase/io/hfile/TestHFileBlock.COMPRESSION_ALGORITHMS:[Lorg/apache/hadoop/hbase/io/compress/Compression$Algorithm;
      63: astore        9
      65: aload         9
      67: arraylength
      68: istore        10
      70: iconst_0
      71: istore        11
      73: iload         11
      75: iload         10
      77: if_icmpge     661
      80: aload         9
      82: iload         11
      84: aaload
      85: astore        12
      87: new           #78                 // class org/apache/hadoop/hbase/io/hfile/HFileContextBuilder
      90: dup
      91: invokespecial #79                 // Method org/apache/hadoop/hbase/io/hfile/HFileContextBuilder."<init>":()V
      94: sipush        4096
      97: invokevirtual #123                // Method org/apache/hadoop/hbase/io/hfile/HFileContextBuilder.withBlockSize:(I)Lorg/apache/hadoop/hbase/io/hfile/HFileContextBuilder;
     100: getstatic     #18                 // Field cryptoContext:Lorg/apache/hadoop/hbase/io/crypto/Encryption$Context;
     103: invokevirtual #81                 // Method org/apache/hadoop/hbase/io/hfile/HFileContextBuilder.withEncryptionContext:(Lorg/apache/hadoop/hbase/io/crypto/Encryption$Context;)Lorg/apache/hadoop/hbase/io/hfile/HFileContextBuilder;
     106: aload         12
     108: invokevirtual #80                 // Method org/apache/hadoop/hbase/io/hfile/HFileContextBuilder.withCompression:(Lorg/apache/hadoop/hbase/io/compress/Compression$Algorithm;)Lorg/apache/hadoop/hbase/io/hfile/HFileContextBuilder;
     111: aload         8
     113: invokevirtual #124                // Method org/apache/hadoop/hbase/io/hfile/HFileContextBuilder.withDataBlockEncoding:(Lorg/apache/hadoop/hbase/io/encoding/DataBlockEncoding;)Lorg/apache/hadoop/hbase/io/hfile/HFileContextBuilder;
     116: invokevirtual #82                 // Method org/apache/hadoop/hbase/io/hfile/HFileContextBuilder.build:()Lorg/apache/hadoop/hbase/io/hfile/HFileContext;
     119: astore        13
     121: getstatic     #35                 // Field LOG:Lorg/slf4j/Logger;
     124: new           #36                 // class java/lang/StringBuilder
     127: dup
     128: invokespecial #37                 // Method java/lang/StringBuilder."<init>":()V
     131: ldc           #125                // String Writing with
     133: invokevirtual #39                 // Method java/lang/StringBuilder.append:(Ljava/lang/String;)Ljava/lang/StringBuilder;
     136: aload         13
     138: invokevirtual #74                 // Method java/lang/StringBuilder.append:(Ljava/lang/Object;)Ljava/lang/StringBuilder;
     141: invokevirtual #48                 // Method java/lang/StringBuilder.toString:()Ljava/lang/String;
     144: invokeinterface #49,  2           // InterfaceMethod org/slf4j/Logger.info:(Ljava/lang/String;)V
     149: new           #71                 // class org/apache/hadoop/fs/Path
     152: dup
     153: getstatic     #2                  // Field TEST_UTIL:Lorg/apache/hadoop/hbase/HBaseTestingUtility;
     156: invokevirtual #72                 // Method org/apache/hadoop/hbase/HBaseTestingUtility.getDataTestDir:()Lorg/apache/hadoop/fs/Path;
     159: new           #36                 // class java/lang/StringBuilder
     162: dup
     163: invokespecial #37                 // Method java/lang/StringBuilder."<init>":()V
     166: getstatic     #2                  // Field TEST_UTIL:Lorg/apache/hadoop/hbase/HBaseTestingUtility;
     169: invokevirtual #126                // Method org/apache/hadoop/hbase/HBaseTestingUtility.getRandomUUID:()Ljava/util/UUID;
     172: invokevirtual #127                // Method java/util/UUID.toString:()Ljava/lang/String;
     175: invokevirtual #39                 // Method java/lang/StringBuilder.append:(Ljava/lang/String;)Ljava/lang/StringBuilder;
     178: ldc           #128                // String .hfile
     180: invokevirtual #39                 // Method java/lang/StringBuilder.append:(Ljava/lang/String;)Ljava/lang/StringBuilder;
     183: invokevirtual #48                 // Method java/lang/StringBuilder.toString:()Ljava/lang/String;
     186: invokespecial #76                 // Method org/apache/hadoop/fs/Path."<init>":(Lorg/apache/hadoop/fs/Path;Ljava/lang/String;)V
     189: astore        14
     191: getstatic     #16                 // Field fs:Lorg/apache/hadoop/fs/FileSystem;
     194: aload         14
     196: invokevirtual #83                 // Method org/apache/hadoop/fs/FileSystem.create:(Lorg/apache/hadoop/fs/Path;)Lorg/apache/hadoop/fs/FSDataOutputStream;
     199: astore        15
     201: aload_3
     202: aload         4
     204: invokestatic  #94                 // Method org/apache/hadoop/hbase/io/hfile/HFile.getWriterFactory:(Lorg/apache/hadoop/conf/Configuration;Lorg/apache/hadoop/hbase/io/hfile/CacheConfig;)Lorg/apache/hadoop/hbase/io/hfile/HFile$WriterFactory;
     207: aload         15
     209: invokevirtual #95                 // Method org/apache/hadoop/hbase/io/hfile/HFile$WriterFactory.withOutputStream:(Lorg/apache/hadoop/fs/FSDataOutputStream;)Lorg/apache/hadoop/hbase/io/hfile/HFile$WriterFactory;
     212: aload         13
     214: invokevirtual #96                 // Method org/apache/hadoop/hbase/io/hfile/HFile$WriterFactory.withFileContext:(Lorg/apache/hadoop/hbase/io/hfile/HFileContext;)Lorg/apache/hadoop/hbase/io/hfile/HFile$WriterFactory;
     217: invokevirtual #97                 // Method org/apache/hadoop/hbase/io/hfile/HFile$WriterFactory.create:()Lorg/apache/hadoop/hbase/io/hfile/HFile$Writer;
     220: astore        16
     222: aload_2
     223: invokeinterface #129,  1          // InterfaceMethod java/util/List.iterator:()Ljava/util/Iterator;
     228: astore        17
     230: aload         17
     232: invokeinterface #130,  1          // InterfaceMethod java/util/Iterator.hasNext:()Z
     237: ifeq          264
     240: aload         17
     242: invokeinterface #131,  1          // InterfaceMethod java/util/Iterator.next:()Ljava/lang/Object;
     247: checkcast     #98                 // class org/apache/hadoop/hbase/KeyValue
     250: astore        18
     252: aload         16
     254: aload         18
     256: invokeinterface #104,  2          // InterfaceMethod org/apache/hadoop/hbase/io/hfile/HFile$Writer.append:(Lorg/apache/hadoop/hbase/Cell;)V
     261: goto          230
     264: aload         16
     266: invokeinterface #105,  1          // InterfaceMethod org/apache/hadoop/hbase/io/hfile/HFile$Writer.close:()V
     271: aload         15
     273: invokevirtual #85                 // Method org/apache/hadoop/fs/FSDataOutputStream.close:()V
     276: goto          296
     279: astore        19
     281: aload         16
     283: invokeinterface #105,  1          // InterfaceMethod org/apache/hadoop/hbase/io/hfile/HFile$Writer.close:()V
     288: aload         15
     290: invokevirtual #85                 // Method org/apache/hadoop/fs/FSDataOutputStream.close:()V
     293: aload         19
     295: athrow
     296: getstatic     #35                 // Field LOG:Lorg/slf4j/Logger;
     299: new           #36                 // class java/lang/StringBuilder
     302: dup
     303: invokespecial #37                 // Method java/lang/StringBuilder."<init>":()V
     306: ldc           #132                // String Reading with
     308: invokevirtual #39                 // Method java/lang/StringBuilder.append:(Ljava/lang/String;)Ljava/lang/StringBuilder;
     311: aload         13
     313: invokevirtual #74                 // Method java/lang/StringBuilder.append:(Ljava/lang/Object;)Ljava/lang/StringBuilder;
     316: invokevirtual #48                 // Method java/lang/StringBuilder.toString:()Ljava/lang/String;
     319: invokeinterface #49,  2           // InterfaceMethod org/slf4j/Logger.info:(Ljava/lang/String;)V
     324: iconst_0
     325: istore        17
     327: aconst_null
     328: astore        18
     330: getstatic     #16                 // Field fs:Lorg/apache/hadoop/fs/FileSystem;
     333: aload         14
     335: aload         4
     337: iconst_1
     338: aload_3
     339: invokestatic  #106                // Method org/apache/hadoop/hbase/io/hfile/HFile.createReader:(Lorg/apache/hadoop/fs/FileSystem;Lorg/apache/hadoop/fs/Path;Lorg/apache/hadoop/hbase/io/hfile/CacheConfig;ZLorg/apache/hadoop/conf/Configuration;)Lorg/apache/hadoop/hbase/io/hfile/HFile$Reader;
     342: astore        19
     344: aload         19
     346: invokeinterface #107,  1          // InterfaceMethod org/apache/hadoop/hbase/io/hfile/HFile$Reader.loadFileInfo:()Ljava/util/Map;
     351: pop
     352: aload         19
     354: invokeinterface #108,  1          // InterfaceMethod org/apache/hadoop/hbase/io/hfile/HFile$Reader.getTrailer:()Lorg/apache/hadoop/hbase/io/hfile/FixedFileTrailer;
     359: astore        20
     361: aload         20
     363: invokevirtual #109                // Method org/apache/hadoop/hbase/io/hfile/FixedFileTrailer.getEncryptionKey:()[B
     366: invokestatic  #23                 // Method org/junit/Assert.assertNotNull:(Ljava/lang/Object;)V
     369: aload         19
     371: iconst_0
     372: iconst_0
     373: invokeinterface #133,  3          // InterfaceMethod org/apache/hadoop/hbase/io/hfile/HFile$Reader.getScanner:(ZZ)Lorg/apache/hadoop/hbase/io/hfile/HFileScanner;
     378: astore        18
     380: ldc           #134                // String Initial seekTo failed
     382: aload         18
     384: invokeinterface #135,  1          // InterfaceMethod org/apache/hadoop/hbase/io/hfile/HFileScanner.seekTo:()Z
     389: invokestatic  #136                // Method org/junit/Assert.assertTrue:(Ljava/lang/String;Z)V
     392: aload         18
     394: invokeinterface #137,  1          // InterfaceMethod org/apache/hadoop/hbase/io/hfile/HFileScanner.getCell:()Lorg/apache/hadoop/hbase/Cell;
     399: astore        21
     401: ldc           #138                // String Read back an unexpected or invalid KV
     403: aload_2
     404: aload         21
     406: invokestatic  #139                // Method org/apache/hadoop/hbase/KeyValueUtil.ensureKeyValue:(Lorg/apache/hadoop/hbase/Cell;)Lorg/apache/hadoop/hbase/KeyValue;
     409: invokeinterface #140,  2          // InterfaceMethod java/util/List.contains:(Ljava/lang/Object;)Z
     414: invokestatic  #136                // Method org/junit/Assert.assertTrue:(Ljava/lang/String;Z)V
     417: iinc          17, 1
     420: aload         18
     422: invokeinterface #141,  1          // InterfaceMethod org/apache/hadoop/hbase/io/hfile/HFileScanner.next:()Z
     427: ifne          392
     430: aload         19
     432: invokeinterface #118,  1          // InterfaceMethod org/apache/hadoop/hbase/io/hfile/HFile$Reader.close:()V
     437: aload         18
     439: invokeinterface #142,  1          // InterfaceMethod org/apache/hadoop/hbase/io/hfile/HFileScanner.close:()V
     444: goto          466
     447: astore        22
     449: aload         19
     451: invokeinterface #118,  1          // InterfaceMethod org/apache/hadoop/hbase/io/hfile/HFile$Reader.close:()V
     456: aload         18
     458: invokeinterface #142,  1          // InterfaceMethod org/apache/hadoop/hbase/io/hfile/HFileScanner.close:()V
     463: aload         22
     465: athrow
     466: ldc           #143                // String Did not read back as many KVs as written
     468: iload         17
     470: i2l
     471: aload_2
     472: invokeinterface #144,  1          // InterfaceMethod java/util/List.size:()I
     477: i2l
     478: invokestatic  #145                // Method org/junit/Assert.assertEquals:(Ljava/lang/String;JJ)V
     481: getstatic     #35                 // Field LOG:Lorg/slf4j/Logger;
     484: new           #36                 // class java/lang/StringBuilder
     487: dup
     488: invokespecial #37                 // Method java/lang/StringBuilder."<init>":()V
     491: ldc           #146                // String Random seeking with
     493: invokevirtual #39                 // Method java/lang/StringBuilder.append:(Ljava/lang/String;)Ljava/lang/StringBuilder;
     496: aload         13
     498: invokevirtual #74                 // Method java/lang/StringBuilder.append:(Ljava/lang/Object;)Ljava/lang/StringBuilder;
     501: invokevirtual #48                 // Method java/lang/StringBuilder.toString:()Ljava/lang/String;
     504: invokeinterface #49,  2           // InterfaceMethod org/slf4j/Logger.info:(Ljava/lang/String;)V
     509: getstatic     #16                 // Field fs:Lorg/apache/hadoop/fs/FileSystem;
     512: aload         14
     514: aload         4
     516: iconst_1
     517: aload_3
     518: invokestatic  #106                // Method org/apache/hadoop/hbase/io/hfile/HFile.createReader:(Lorg/apache/hadoop/fs/FileSystem;Lorg/apache/hadoop/fs/Path;Lorg/apache/hadoop/hbase/io/hfile/CacheConfig;ZLorg/apache/hadoop/conf/Configuration;)Lorg/apache/hadoop/hbase/io/hfile/HFile$Reader;
     521: astore        19
     523: aload         19
     525: iconst_0
     526: iconst_1
     527: invokeinterface #133,  3          // InterfaceMethod org/apache/hadoop/hbase/io/hfile/HFile$Reader.getScanner:(ZZ)Lorg/apache/hadoop/hbase/io/hfile/HFileScanner;
     532: astore        18
     534: ldc           #134                // String Initial seekTo failed
     536: aload         18
     538: invokeinterface #135,  1          // InterfaceMethod org/apache/hadoop/hbase/io/hfile/HFileScanner.seekTo:()Z
     543: invokestatic  #136                // Method org/junit/Assert.assertTrue:(Ljava/lang/String;Z)V
     546: iconst_0
     547: istore        17
     549: iload         17
     551: bipush        100
     553: if_icmpge     619
     556: aload_2
     557: getstatic     #26                 // Field RNG:Ljava/security/SecureRandom;
     560: aload_2
     561: invokeinterface #144,  1          // InterfaceMethod java/util/List.size:()I
     566: invokevirtual #68                 // Method java/security/SecureRandom.nextInt:(I)I
     569: invokeinterface #147,  2          // InterfaceMethod java/util/List.get:(I)Ljava/lang/Object;
     574: checkcast     #98                 // class org/apache/hadoop/hbase/KeyValue
     577: astore        20
     579: new           #36                 // class java/lang/StringBuilder
     582: dup
     583: invokespecial #37                 // Method java/lang/StringBuilder."<init>":()V
     586: ldc           #148                // String Unable to find KV as expected:
     588: invokevirtual #39                 // Method java/lang/StringBuilder.append:(Ljava/lang/String;)Ljava/lang/StringBuilder;
     591: aload         20
     593: invokevirtual #74                 // Method java/lang/StringBuilder.append:(Ljava/lang/Object;)Ljava/lang/StringBuilder;
     596: invokevirtual #48                 // Method java/lang/StringBuilder.toString:()Ljava/lang/String;
     599: lconst_0
     600: aload         18
     602: aload         20
     604: invokeinterface #149,  2          // InterfaceMethod org/apache/hadoop/hbase/io/hfile/HFileScanner.seekTo:(Lorg/apache/hadoop/hbase/Cell;)I
     609: i2l
     610: invokestatic  #145                // Method org/junit/Assert.assertEquals:(Ljava/lang/String;JJ)V
     613: iinc          17, 1
     616: goto          549
     619: aload         18
     621: invokeinterface #142,  1          // InterfaceMethod org/apache/hadoop/hbase/io/hfile/HFileScanner.close:()V
     626: aload         19
     628: invokeinterface #118,  1          // InterfaceMethod org/apache/hadoop/hbase/io/hfile/HFile$Reader.close:()V
     633: goto          655
     636: astore        23
     638: aload         18
     640: invokeinterface #142,  1          // InterfaceMethod org/apache/hadoop/hbase/io/hfile/HFileScanner.close:()V
     645: aload         19
     647: invokeinterface #118,  1          // InterfaceMethod org/apache/hadoop/hbase/io/hfile/HFile$Reader.close:()V
     652: aload         23
     654: athrow
     655: iinc          11, 1
     658: goto          73
     661: iinc          7, 1
     664: goto          46
     667: return
    Exception table:
       from    to  target type
         222   264   279   any
         279   281   279   any
         344   430   447   any
         447   449   447   any
         523   619   636   any
         636   638   636   any

  static {};
    Code:
       0: ldc           #150                // class org/apache/hadoop/hbase/io/hfile/TestHFileEncryption
       2: invokestatic  #151                // Method org/apache/hadoop/hbase/HBaseClassTestRule.forClass:(Ljava/lang/Class;)Lorg/apache/hadoop/hbase/HBaseClassTestRule;
       5: putstatic     #152                // Field CLASS_RULE:Lorg/apache/hadoop/hbase/HBaseClassTestRule;
       8: ldc           #150                // class org/apache/hadoop/hbase/io/hfile/TestHFileEncryption
      10: invokestatic  #153                // Method org/slf4j/LoggerFactory.getLogger:(Ljava/lang/Class;)Lorg/slf4j/Logger;
      13: putstatic     #35                 // Field LOG:Lorg/slf4j/Logger;
      16: new           #154                // class org/apache/hadoop/hbase/HBaseTestingUtility
      19: dup
      20: invokespecial #155                // Method org/apache/hadoop/hbase/HBaseTestingUtility."<init>":()V
      23: putstatic     #2                  // Field TEST_UTIL:Lorg/apache/hadoop/hbase/HBaseTestingUtility;
      26: new           #156                // class java/security/SecureRandom
      29: dup
      30: invokespecial #157                // Method java/security/SecureRandom."<init>":()V
      33: putstatic     #26                 // Field RNG:Ljava/security/SecureRandom;
      36: return
}
