Compiled from "TestRecoveredEditsReplayAndAbort.java"
class org.apache.hadoop.hbase.regionserver.TestRecoveredEditsReplayAndAbort$1 implements org.apache.hadoop.hbase.util.CancelableProgressable {
  final org.apache.hadoop.hbase.regionserver.RegionServerAccounting val$rsAccounting;

  final long val$totalEdits;

  final org.apache.hadoop.hbase.regionserver.TestRecoveredEditsReplayAndAbort this$0;

  org.apache.hadoop.hbase.regionserver.TestRecoveredEditsReplayAndAbort$1(org.apache.hadoop.hbase.regionserver.TestRecoveredEditsReplayAndAbort, org.apache.hadoop.hbase.regionserver.RegionServerAccounting, long);
    Code:
       0: aload_0
       1: aload_1
       2: putfield      #1                  // Field this$0:Lorg/apache/hadoop/hbase/regionserver/TestRecoveredEditsReplayAndAbort;
       5: aload_0
       6: aload_2
       7: putfield      #2                  // Field val$rsAccounting:Lorg/apache/hadoop/hbase/regionserver/RegionServerAccounting;
      10: aload_0
      11: lload_3
      12: putfield      #3                  // Field val$totalEdits:J
      15: aload_0
      16: invokespecial #4                  // Method java/lang/Object."<init>":()V
      19: aload_0
      20: lconst_0
      21: putfield      #5                  // Field replayedEdits:J
      24: return

  public boolean progress();
    Code:
       0: aload_0
       1: dup
       2: getfield      #5                  // Field replayedEdits:J
       5: lconst_1
       6: ladd
       7: putfield      #5                  // Field replayedEdits:J
      10: aload_0
      11: getfield      #2                  // Field val$rsAccounting:Lorg/apache/hadoop/hbase/regionserver/RegionServerAccounting;
      14: invokevirtual #6                  // Method org/apache/hadoop/hbase/regionserver/RegionServerAccounting.getGlobalMemStoreDataSize:()J
      17: aload_0
      18: getfield      #1                  // Field this$0:Lorg/apache/hadoop/hbase/regionserver/TestRecoveredEditsReplayAndAbort;
      21: invokestatic  #7                  // Method org/apache/hadoop/hbase/regionserver/TestRecoveredEditsReplayAndAbort.access$000:(Lorg/apache/hadoop/hbase/regionserver/TestRecoveredEditsReplayAndAbort;)Lorg/apache/hadoop/hbase/regionserver/HRegion;
      24: invokevirtual #8                  // Method org/apache/hadoop/hbase/regionserver/HRegion.getMemStoreDataSize:()J
      27: invokestatic  #9                  // Method org/junit/Assert.assertEquals:(JJ)V
      30: aload_0
      31: getfield      #2                  // Field val$rsAccounting:Lorg/apache/hadoop/hbase/regionserver/RegionServerAccounting;
      34: invokevirtual #10                 // Method org/apache/hadoop/hbase/regionserver/RegionServerAccounting.getGlobalMemStoreHeapSize:()J
      37: aload_0
      38: getfield      #1                  // Field this$0:Lorg/apache/hadoop/hbase/regionserver/TestRecoveredEditsReplayAndAbort;
      41: invokestatic  #7                  // Method org/apache/hadoop/hbase/regionserver/TestRecoveredEditsReplayAndAbort.access$000:(Lorg/apache/hadoop/hbase/regionserver/TestRecoveredEditsReplayAndAbort;)Lorg/apache/hadoop/hbase/regionserver/HRegion;
      44: invokevirtual #11                 // Method org/apache/hadoop/hbase/regionserver/HRegion.getMemStoreHeapSize:()J
      47: invokestatic  #9                  // Method org/junit/Assert.assertEquals:(JJ)V
      50: aload_0
      51: getfield      #2                  // Field val$rsAccounting:Lorg/apache/hadoop/hbase/regionserver/RegionServerAccounting;
      54: invokevirtual #12                 // Method org/apache/hadoop/hbase/regionserver/RegionServerAccounting.getGlobalMemStoreOffHeapSize:()J
      57: aload_0
      58: getfield      #1                  // Field this$0:Lorg/apache/hadoop/hbase/regionserver/TestRecoveredEditsReplayAndAbort;
      61: invokestatic  #7                  // Method org/apache/hadoop/hbase/regionserver/TestRecoveredEditsReplayAndAbort.access$000:(Lorg/apache/hadoop/hbase/regionserver/TestRecoveredEditsReplayAndAbort;)Lorg/apache/hadoop/hbase/regionserver/HRegion;
      64: invokevirtual #13                 // Method org/apache/hadoop/hbase/regionserver/HRegion.getMemStoreOffHeapSize:()J
      67: invokestatic  #9                  // Method org/junit/Assert.assertEquals:(JJ)V
      70: aload_0
      71: getfield      #5                  // Field replayedEdits:J
      74: aload_0
      75: getfield      #3                  // Field val$totalEdits:J
      78: ldc2_w        #14                 // long 10l
      81: lsub
      82: lcmp
      83: ifge          90
      86: iconst_1
      87: goto          91
      90: iconst_0
      91: ireturn
}
