Compiled from "TestFailedAppendAndSync.java"
public class org.apache.hadoop.hbase.regionserver.TestFailedAppendAndSync {
  public static final org.apache.hadoop.hbase.HBaseClassTestRule CLASS_RULE;

  public org.junit.rules.TestName name;

  org.apache.hadoop.hbase.regionserver.HRegion region;

  public static org.apache.hadoop.conf.Configuration CONF;

  protected org.apache.hadoop.hbase.TableName tableName;

  public org.apache.hadoop.hbase.regionserver.TestFailedAppendAndSync();
    Code:
       0: aload_0
       1: invokespecial #1                  // Method java/lang/Object."<init>":()V
       4: aload_0
       5: new           #2                  // class org/junit/rules/TestName
       8: dup
       9: invokespecial #3                  // Method org/junit/rules/TestName."<init>":()V
      12: putfield      #4                  // Field name:Lorg/junit/rules/TestName;
      15: aload_0
      16: aconst_null
      17: putfield      #5                  // Field region:Lorg/apache/hadoop/hbase/regionserver/HRegion;
      20: return

  public void setup() throws java.io.IOException;
    Code:
       0: invokestatic  #6                  // Method org/apache/hadoop/hbase/HBaseTestingUtility.createLocalHTU:()Lorg/apache/hadoop/hbase/HBaseTestingUtility;
       3: putstatic     #7                  // Field TEST_UTIL:Lorg/apache/hadoop/hbase/HBaseTestingUtility;
       6: getstatic     #7                  // Field TEST_UTIL:Lorg/apache/hadoop/hbase/HBaseTestingUtility;
       9: invokevirtual #8                  // Method org/apache/hadoop/hbase/HBaseTestingUtility.getConfiguration:()Lorg/apache/hadoop/conf/Configuration;
      12: putstatic     #9                  // Field CONF:Lorg/apache/hadoop/conf/Configuration;
      15: getstatic     #9                  // Field CONF:Lorg/apache/hadoop/conf/Configuration;
      18: ldc           #11                 // String hfile.block.cache.size
      20: fconst_0
      21: invokevirtual #12                 // Method org/apache/hadoop/conf/Configuration.setFloat:(Ljava/lang/String;F)V
      24: aload_0
      25: getstatic     #7                  // Field TEST_UTIL:Lorg/apache/hadoop/hbase/HBaseTestingUtility;
      28: ldc           #13                 // String TestHRegion
      30: invokevirtual #14                 // Method org/apache/hadoop/hbase/HBaseTestingUtility.getDataTestDir:(Ljava/lang/String;)Lorg/apache/hadoop/fs/Path;
      33: invokevirtual #15                 // Method org/apache/hadoop/fs/Path.toString:()Ljava/lang/String;
      36: putfield      #16                 // Field dir:Ljava/lang/String;
      39: aload_0
      40: aload_0
      41: getfield      #4                  // Field name:Lorg/junit/rules/TestName;
      44: invokevirtual #17                 // Method org/junit/rules/TestName.getMethodName:()Ljava/lang/String;
      47: invokestatic  #18                 // Method org/apache/hadoop/hbase/TableName.valueOf:(Ljava/lang/String;)Lorg/apache/hadoop/hbase/TableName;
      50: putfield      #19                 // Field tableName:Lorg/apache/hadoop/hbase/TableName;
      53: return

  public void tearDown() throws java.lang.Exception;
    Code:
       0: invokestatic  #20                 // Method org/apache/hadoop/hbase/util/EnvironmentEdgeManagerTestHelper.reset:()V
       3: getstatic     #21                 // Field LOG:Lorg/slf4j/Logger;
       6: new           #22                 // class java/lang/StringBuilder
       9: dup
      10: invokespecial #23                 // Method java/lang/StringBuilder."<init>":()V
      13: ldc           #24                 // String Cleaning test directory:
      15: invokevirtual #25                 // Method java/lang/StringBuilder.append:(Ljava/lang/String;)Ljava/lang/StringBuilder;
      18: getstatic     #7                  // Field TEST_UTIL:Lorg/apache/hadoop/hbase/HBaseTestingUtility;
      21: invokevirtual #26                 // Method org/apache/hadoop/hbase/HBaseTestingUtility.getDataTestDir:()Lorg/apache/hadoop/fs/Path;
      24: invokevirtual #27                 // Method java/lang/StringBuilder.append:(Ljava/lang/Object;)Ljava/lang/StringBuilder;
      27: invokevirtual #28                 // Method java/lang/StringBuilder.toString:()Ljava/lang/String;
      30: invokeinterface #29,  2           // InterfaceMethod org/slf4j/Logger.info:(Ljava/lang/String;)V
      35: getstatic     #7                  // Field TEST_UTIL:Lorg/apache/hadoop/hbase/HBaseTestingUtility;
      38: invokevirtual #30                 // Method org/apache/hadoop/hbase/HBaseTestingUtility.cleanupTestDir:()Z
      41: pop
      42: return

  java.lang.String getName();
    Code:
       0: aload_0
       1: getfield      #4                  // Field name:Lorg/junit/rules/TestName;
       4: invokevirtual #17                 // Method org/junit/rules/TestName.getMethodName:()Ljava/lang/String;
       7: areturn

  public void testLockupAroundBadAssignSync() throws java.io.IOException;
    Code:
       0: ldc           #31                 // class org/apache/hadoop/hbase/Server
       2: invokestatic  #32                 // Method org/mockito/Mockito.mock:(Ljava/lang/Class;)Ljava/lang/Object;
       5: checkcast     #31                 // class org/apache/hadoop/hbase/Server
       8: astore_1
       9: aload_1
      10: invokeinterface #33,  1           // InterfaceMethod org/apache/hadoop/hbase/Server.getConfiguration:()Lorg/apache/hadoop/conf/Configuration;
      15: invokestatic  #34                 // Method org/mockito/Mockito.when:(Ljava/lang/Object;)Lorg/mockito/stubbing/OngoingStubbing;
      18: getstatic     #9                  // Field CONF:Lorg/apache/hadoop/conf/Configuration;
      21: invokeinterface #35,  2           // InterfaceMethod org/mockito/stubbing/OngoingStubbing.thenReturn:(Ljava/lang/Object;)Lorg/mockito/stubbing/OngoingStubbing;
      26: pop
      27: aload_1
      28: invokeinterface #36,  1           // InterfaceMethod org/apache/hadoop/hbase/Server.isStopped:()Z
      33: invokestatic  #37                 // Method java/lang/Boolean.valueOf:(Z)Ljava/lang/Boolean;
      36: invokestatic  #34                 // Method org/mockito/Mockito.when:(Ljava/lang/Object;)Lorg/mockito/stubbing/OngoingStubbing;
      39: iconst_0
      40: invokestatic  #37                 // Method java/lang/Boolean.valueOf:(Z)Ljava/lang/Boolean;
      43: invokeinterface #35,  2           // InterfaceMethod org/mockito/stubbing/OngoingStubbing.thenReturn:(Ljava/lang/Object;)Lorg/mockito/stubbing/OngoingStubbing;
      48: pop
      49: aload_1
      50: invokeinterface #38,  1           // InterfaceMethod org/apache/hadoop/hbase/Server.isAborted:()Z
      55: invokestatic  #37                 // Method java/lang/Boolean.valueOf:(Z)Ljava/lang/Boolean;
      58: invokestatic  #34                 // Method org/mockito/Mockito.when:(Ljava/lang/Object;)Lorg/mockito/stubbing/OngoingStubbing;
      61: iconst_0
      62: invokestatic  #37                 // Method java/lang/Boolean.valueOf:(Z)Ljava/lang/Boolean;
      65: invokeinterface #35,  2           // InterfaceMethod org/mockito/stubbing/OngoingStubbing.thenReturn:(Ljava/lang/Object;)Lorg/mockito/stubbing/OngoingStubbing;
      70: pop
      71: ldc           #39                 // class org/apache/hadoop/hbase/regionserver/RegionServerServices
      73: invokestatic  #32                 // Method org/mockito/Mockito.mock:(Ljava/lang/Class;)Ljava/lang/Object;
      76: checkcast     #39                 // class org/apache/hadoop/hbase/regionserver/RegionServerServices
      79: astore_2
      80: getstatic     #9                  // Field CONF:Lorg/apache/hadoop/conf/Configuration;
      83: invokestatic  #40                 // Method org/apache/hadoop/fs/FileSystem.get:(Lorg/apache/hadoop/conf/Configuration;)Lorg/apache/hadoop/fs/FileSystem;
      86: astore_3
      87: new           #41                 // class org/apache/hadoop/fs/Path
      90: dup
      91: new           #22                 // class java/lang/StringBuilder
      94: dup
      95: invokespecial #23                 // Method java/lang/StringBuilder."<init>":()V
      98: aload_0
      99: getfield      #16                 // Field dir:Ljava/lang/String;
     102: invokevirtual #25                 // Method java/lang/StringBuilder.append:(Ljava/lang/String;)Ljava/lang/StringBuilder;
     105: aload_0
     106: invokevirtual #42                 // Method getName:()Ljava/lang/String;
     109: invokevirtual #25                 // Method java/lang/StringBuilder.append:(Ljava/lang/String;)Ljava/lang/StringBuilder;
     112: invokevirtual #28                 // Method java/lang/StringBuilder.toString:()Ljava/lang/String;
     115: invokespecial #43                 // Method org/apache/hadoop/fs/Path."<init>":(Ljava/lang/String;)V
     118: astore        4
     120: new           #44                 // class org/apache/hadoop/hbase/regionserver/TestFailedAppendAndSync$DodgyFSLog
     123: dup
     124: aload_0
     125: aload_3
     126: aload         4
     128: aload_0
     129: invokevirtual #42                 // Method getName:()Ljava/lang/String;
     132: getstatic     #9                  // Field CONF:Lorg/apache/hadoop/conf/Configuration;
     135: invokespecial #45                 // Method org/apache/hadoop/hbase/regionserver/TestFailedAppendAndSync$DodgyFSLog."<init>":(Lorg/apache/hadoop/hbase/regionserver/TestFailedAppendAndSync;Lorg/apache/hadoop/fs/FileSystem;Lorg/apache/hadoop/fs/Path;Ljava/lang/String;Lorg/apache/hadoop/conf/Configuration;)V
     138: astore        5
     140: aload         5
     142: invokevirtual #46                 // Method org/apache/hadoop/hbase/regionserver/TestFailedAppendAndSync$DodgyFSLog.init:()V
     145: new           #47                 // class org/apache/hadoop/hbase/regionserver/LogRoller
     148: dup
     149: aload_1
     150: aload_2
     151: invokespecial #48                 // Method org/apache/hadoop/hbase/regionserver/LogRoller."<init>":(Lorg/apache/hadoop/hbase/Server;Lorg/apache/hadoop/hbase/regionserver/RegionServerServices;)V
     154: astore        6
     156: aload         6
     158: aload         5
     160: invokevirtual #49                 // Method org/apache/hadoop/hbase/regionserver/LogRoller.addWAL:(Lorg/apache/hadoop/hbase/wal/WAL;)V
     163: aload         6
     165: invokevirtual #50                 // Method org/apache/hadoop/hbase/regionserver/LogRoller.start:()V
     168: iconst_0
     169: istore        7
     171: iconst_0
     172: istore        8
     174: iconst_0
     175: istore        9
     177: aload_0
     178: getfield      #19                 // Field tableName:Lorg/apache/hadoop/hbase/TableName;
     181: aconst_null
     182: aconst_null
     183: aload         5
     185: invokestatic  #51                 // Method initHRegion:(Lorg/apache/hadoop/hbase/TableName;[B[BLorg/apache/hadoop/hbase/wal/WAL;)Lorg/apache/hadoop/hbase/regionserver/HRegion;
     188: astore        10
     190: aload_0
     191: invokevirtual #42                 // Method getName:()Ljava/lang/String;
     194: invokestatic  #52                 // Method org/apache/hadoop/hbase/util/Bytes.toBytes:(Ljava/lang/String;)[B
     197: astore        11
     199: new           #53                 // class org/apache/hadoop/hbase/client/Put
     202: dup
     203: aload         11
     205: invokespecial #54                 // Method org/apache/hadoop/hbase/client/Put."<init>":([B)V
     208: astore        12
     210: aload         12
     212: getstatic     #55                 // Field COLUMN_FAMILY_BYTES:[B
     215: ldc           #56                 // String 1
     217: invokestatic  #52                 // Method org/apache/hadoop/hbase/util/Bytes.toBytes:(Ljava/lang/String;)[B
     220: aload         11
     222: invokevirtual #57                 // Method org/apache/hadoop/hbase/client/Put.addColumn:([B[B[B)Lorg/apache/hadoop/hbase/client/Put;
     225: pop
     226: aload         10
     228: aload         12
     230: invokevirtual #58                 // Method org/apache/hadoop/hbase/regionserver/HRegion.put:(Lorg/apache/hadoop/hbase/client/Put;)V
     233: goto          241
     236: astore        12
     238: invokestatic  #60                 // Method org/junit/Assert.fail:()V
     241: aload         5
     243: getfield      #61                 // Field org/apache/hadoop/hbase/regionserver/TestFailedAppendAndSync$DodgyFSLog.rolls:Ljava/util/concurrent/atomic/AtomicLong;
     246: invokevirtual #62                 // Method java/util/concurrent/atomic/AtomicLong.get:()J
     249: lstore        12
     251: aload         5
     253: iconst_1
     254: putfield      #63                 // Field org/apache/hadoop/hbase/regionserver/TestFailedAppendAndSync$DodgyFSLog.throwAppendException:Z
     257: aload         5
     259: iconst_0
     260: putfield      #64                 // Field org/apache/hadoop/hbase/regionserver/TestFailedAppendAndSync$DodgyFSLog.throwSyncException:Z
     263: new           #53                 // class org/apache/hadoop/hbase/client/Put
     266: dup
     267: aload         11
     269: invokespecial #54                 // Method org/apache/hadoop/hbase/client/Put."<init>":([B)V
     272: astore        14
     274: aload         14
     276: getstatic     #55                 // Field COLUMN_FAMILY_BYTES:[B
     279: ldc           #65                 // String 3
     281: invokestatic  #52                 // Method org/apache/hadoop/hbase/util/Bytes.toBytes:(Ljava/lang/String;)[B
     284: aload         11
     286: invokevirtual #57                 // Method org/apache/hadoop/hbase/client/Put.addColumn:([B[B[B)Lorg/apache/hadoop/hbase/client/Put;
     289: pop
     290: aload         10
     292: aload         14
     294: invokevirtual #58                 // Method org/apache/hadoop/hbase/regionserver/HRegion.put:(Lorg/apache/hadoop/hbase/client/Put;)V
     297: goto          305
     300: astore        14
     302: iconst_1
     303: istore        8
     305: lload         12
     307: aload         5
     309: getfield      #61                 // Field org/apache/hadoop/hbase/regionserver/TestFailedAppendAndSync$DodgyFSLog.rolls:Ljava/util/concurrent/atomic/AtomicLong;
     312: invokevirtual #62                 // Method java/util/concurrent/atomic/AtomicLong.get:()J
     315: lcmp
     316: ifne          328
     319: ldc2_w        #66                 // long 100l
     322: invokestatic  #68                 // Method org/apache/hadoop/hbase/util/Threads.sleep:(J)V
     325: goto          305
     328: aload         5
     330: getfield      #61                 // Field org/apache/hadoop/hbase/regionserver/TestFailedAppendAndSync$DodgyFSLog.rolls:Ljava/util/concurrent/atomic/AtomicLong;
     333: invokevirtual #62                 // Method java/util/concurrent/atomic/AtomicLong.get:()J
     336: lstore        12
     338: aload         5
     340: iconst_1
     341: putfield      #63                 // Field org/apache/hadoop/hbase/regionserver/TestFailedAppendAndSync$DodgyFSLog.throwAppendException:Z
     344: aload         5
     346: iconst_1
     347: putfield      #64                 // Field org/apache/hadoop/hbase/regionserver/TestFailedAppendAndSync$DodgyFSLog.throwSyncException:Z
     350: new           #53                 // class org/apache/hadoop/hbase/client/Put
     353: dup
     354: aload         11
     356: invokespecial #54                 // Method org/apache/hadoop/hbase/client/Put."<init>":([B)V
     359: astore        14
     361: aload         14
     363: getstatic     #55                 // Field COLUMN_FAMILY_BYTES:[B
     366: ldc           #69                 // String 4
     368: invokestatic  #52                 // Method org/apache/hadoop/hbase/util/Bytes.toBytes:(Ljava/lang/String;)[B
     371: aload         11
     373: invokevirtual #57                 // Method org/apache/hadoop/hbase/client/Put.addColumn:([B[B[B)Lorg/apache/hadoop/hbase/client/Put;
     376: pop
     377: aload         10
     379: aload         14
     381: invokevirtual #58                 // Method org/apache/hadoop/hbase/regionserver/HRegion.put:(Lorg/apache/hadoop/hbase/client/Put;)V
     384: goto          392
     387: astore        14
     389: iconst_1
     390: istore        9
     392: lload         12
     394: aload         5
     396: getfield      #61                 // Field org/apache/hadoop/hbase/regionserver/TestFailedAppendAndSync$DodgyFSLog.rolls:Ljava/util/concurrent/atomic/AtomicLong;
     399: invokevirtual #62                 // Method java/util/concurrent/atomic/AtomicLong.get:()J
     402: lcmp
     403: ifne          415
     406: ldc2_w        #66                 // long 100l
     409: invokestatic  #68                 // Method org/apache/hadoop/hbase/util/Threads.sleep:(J)V
     412: goto          392
     415: aload_1
     416: iconst_0
     417: invokestatic  #70                 // Method org/mockito/Mockito.atLeast:(I)Lorg/mockito/verification/VerificationMode;
     420: invokestatic  #71                 // Method org/mockito/Mockito.verify:(Ljava/lang/Object;Lorg/mockito/verification/VerificationMode;)Ljava/lang/Object;
     423: checkcast     #31                 // class org/apache/hadoop/hbase/Server
     426: invokestatic  #72                 // Method org/mockito/Mockito.anyString:()Ljava/lang/String;
     429: ldc           #73                 // class java/lang/Throwable
     431: invokestatic  #74                 // Method org/mockito/Mockito.any:(Ljava/lang/Class;)Ljava/lang/Object;
     434: checkcast     #73                 // class java/lang/Throwable
     437: invokeinterface #75,  3           // InterfaceMethod org/apache/hadoop/hbase/Server.abort:(Ljava/lang/String;Ljava/lang/Throwable;)V
     442: aload         5
     444: iconst_0
     445: putfield      #63                 // Field org/apache/hadoop/hbase/regionserver/TestFailedAppendAndSync$DodgyFSLog.throwAppendException:Z
     448: aload         5
     450: iconst_1
     451: putfield      #64                 // Field org/apache/hadoop/hbase/regionserver/TestFailedAppendAndSync$DodgyFSLog.throwSyncException:Z
     454: new           #53                 // class org/apache/hadoop/hbase/client/Put
     457: dup
     458: aload         11
     460: invokespecial #54                 // Method org/apache/hadoop/hbase/client/Put."<init>":([B)V
     463: astore        14
     465: aload         14
     467: getstatic     #55                 // Field COLUMN_FAMILY_BYTES:[B
     470: ldc           #76                 // String 2
     472: invokestatic  #52                 // Method org/apache/hadoop/hbase/util/Bytes.toBytes:(Ljava/lang/String;)[B
     475: aload         11
     477: invokevirtual #57                 // Method org/apache/hadoop/hbase/client/Put.addColumn:([B[B[B)Lorg/apache/hadoop/hbase/client/Put;
     480: pop
     481: aload         10
     483: aload         14
     485: invokevirtual #58                 // Method org/apache/hadoop/hbase/regionserver/HRegion.put:(Lorg/apache/hadoop/hbase/client/Put;)V
     488: goto          496
     491: astore        14
     493: iconst_1
     494: istore        7
     496: aload_1
     497: iconst_1
     498: invokestatic  #70                 // Method org/mockito/Mockito.atLeast:(I)Lorg/mockito/verification/VerificationMode;
     501: invokestatic  #71                 // Method org/mockito/Mockito.verify:(Ljava/lang/Object;Lorg/mockito/verification/VerificationMode;)Ljava/lang/Object;
     504: checkcast     #31                 // class org/apache/hadoop/hbase/Server
     507: invokestatic  #72                 // Method org/mockito/Mockito.anyString:()Ljava/lang/String;
     510: ldc           #73                 // class java/lang/Throwable
     512: invokestatic  #74                 // Method org/mockito/Mockito.any:(Ljava/lang/Class;)Ljava/lang/Object;
     515: checkcast     #73                 // class java/lang/Throwable
     518: invokeinterface #75,  3           // InterfaceMethod org/apache/hadoop/hbase/Server.abort:(Ljava/lang/String;Ljava/lang/Throwable;)V
     523: goto          535
     526: astore        14
     528: lconst_1
     529: invokestatic  #68                 // Method org/apache/hadoop/hbase/util/Threads.sleep:(J)V
     532: goto          496
     535: aload_1
     536: invokeinterface #36,  1           // InterfaceMethod org/apache/hadoop/hbase/Server.isStopped:()Z
     541: invokestatic  #37                 // Method java/lang/Boolean.valueOf:(Z)Ljava/lang/Boolean;
     544: invokestatic  #34                 // Method org/mockito/Mockito.when:(Ljava/lang/Object;)Lorg/mockito/stubbing/OngoingStubbing;
     547: iconst_1
     548: invokestatic  #37                 // Method java/lang/Boolean.valueOf:(Z)Ljava/lang/Boolean;
     551: invokeinterface #35,  2           // InterfaceMethod org/mockito/stubbing/OngoingStubbing.thenReturn:(Ljava/lang/Object;)Lorg/mockito/stubbing/OngoingStubbing;
     556: pop
     557: aload         6
     559: ifnull        567
     562: aload         6
     564: invokevirtual #78                 // Method org/apache/hadoop/hbase/regionserver/LogRoller.close:()V
     567: aload         10
     569: ifnull        596
     572: aload         10
     574: iconst_1
     575: invokevirtual #79                 // Method org/apache/hadoop/hbase/regionserver/HRegion.close:(Z)Ljava/util/Map;
     578: pop
     579: goto          596
     582: astore        11
     584: getstatic     #21                 // Field LOG:Lorg/slf4j/Logger;
     587: ldc           #81                 // String On way out; expected!
     589: aload         11
     591: invokeinterface #82,  3           // InterfaceMethod org/slf4j/Logger.info:(Ljava/lang/String;Ljava/lang/Throwable;)V
     596: aload         5
     598: ifnull        606
     601: aload         5
     603: invokevirtual #83                 // Method org/apache/hadoop/hbase/regionserver/TestFailedAppendAndSync$DodgyFSLog.close:()V
     606: ldc           #84                 // String The regionserver should have thrown an exception
     608: iload         9
     610: invokestatic  #85                 // Method org/junit/Assert.assertTrue:(Ljava/lang/String;Z)V
     613: ldc           #84                 // String The regionserver should have thrown an exception
     615: iload         8
     617: invokestatic  #85                 // Method org/junit/Assert.assertTrue:(Ljava/lang/String;Z)V
     620: ldc           #84                 // String The regionserver should have thrown an exception
     622: iload         7
     624: invokestatic  #85                 // Method org/junit/Assert.assertTrue:(Ljava/lang/String;Z)V
     627: goto          727
     630: astore        15
     632: aload_1
     633: invokeinterface #36,  1           // InterfaceMethod org/apache/hadoop/hbase/Server.isStopped:()Z
     638: invokestatic  #37                 // Method java/lang/Boolean.valueOf:(Z)Ljava/lang/Boolean;
     641: invokestatic  #34                 // Method org/mockito/Mockito.when:(Ljava/lang/Object;)Lorg/mockito/stubbing/OngoingStubbing;
     644: iconst_1
     645: invokestatic  #37                 // Method java/lang/Boolean.valueOf:(Z)Ljava/lang/Boolean;
     648: invokeinterface #35,  2           // InterfaceMethod org/mockito/stubbing/OngoingStubbing.thenReturn:(Ljava/lang/Object;)Lorg/mockito/stubbing/OngoingStubbing;
     653: pop
     654: aload         6
     656: ifnull        664
     659: aload         6
     661: invokevirtual #78                 // Method org/apache/hadoop/hbase/regionserver/LogRoller.close:()V
     664: aload         10
     666: ifnull        693
     669: aload         10
     671: iconst_1
     672: invokevirtual #79                 // Method org/apache/hadoop/hbase/regionserver/HRegion.close:(Z)Ljava/util/Map;
     675: pop
     676: goto          693
     679: astore        16
     681: getstatic     #21                 // Field LOG:Lorg/slf4j/Logger;
     684: ldc           #81                 // String On way out; expected!
     686: aload         16
     688: invokeinterface #82,  3           // InterfaceMethod org/slf4j/Logger.info:(Ljava/lang/String;Ljava/lang/Throwable;)V
     693: aload         5
     695: ifnull        703
     698: aload         5
     700: invokevirtual #83                 // Method org/apache/hadoop/hbase/regionserver/TestFailedAppendAndSync$DodgyFSLog.close:()V
     703: ldc           #84                 // String The regionserver should have thrown an exception
     705: iload         9
     707: invokestatic  #85                 // Method org/junit/Assert.assertTrue:(Ljava/lang/String;Z)V
     710: ldc           #84                 // String The regionserver should have thrown an exception
     712: iload         8
     714: invokestatic  #85                 // Method org/junit/Assert.assertTrue:(Ljava/lang/String;Z)V
     717: ldc           #84                 // String The regionserver should have thrown an exception
     719: iload         7
     721: invokestatic  #85                 // Method org/junit/Assert.assertTrue:(Ljava/lang/String;Z)V
     724: aload         15
     726: athrow
     727: return
    Exception table:
       from    to  target type
         199   233   236   Class java/io/IOException
         251   297   300   Class java/io/IOException
         338   384   387   Class java/io/IOException
         442   488   491   Class java/io/IOException
         496   523   526   Class org/mockito/exceptions/verification/WantedButNotInvoked
         572   579   582   Class org/apache/hadoop/hbase/DroppedSnapshotException
         190   535   630   any
         669   676   679   Class org/apache/hadoop/hbase/DroppedSnapshotException
         630   632   630   any

  public static org.apache.hadoop.hbase.regionserver.HRegion initHRegion(org.apache.hadoop.hbase.TableName, byte[], byte[], org.apache.hadoop.hbase.wal.WAL) throws java.io.IOException;
    Code:
       0: ldc           #87                 // int 2097152
       2: iconst_0
       3: lconst_0
       4: fconst_0
       5: fconst_0
       6: aconst_null
       7: invokestatic  #88                 // Method org/apache/hadoop/hbase/regionserver/ChunkCreator.initialize:(IZJFFLorg/apache/hadoop/hbase/regionserver/HeapMemoryManager;)Lorg/apache/hadoop/hbase/regionserver/ChunkCreator;
      10: pop
      11: getstatic     #7                  // Field TEST_UTIL:Lorg/apache/hadoop/hbase/HBaseTestingUtility;
      14: aload_0
      15: aload_1
      16: aload_2
      17: iconst_0
      18: getstatic     #89                 // Field org/apache/hadoop/hbase/client/Durability.SYNC_WAL:Lorg/apache/hadoop/hbase/client/Durability;
      21: aload_3
      22: iconst_1
      23: anewarray     #90                 // class "[B"
      26: dup
      27: iconst_0
      28: getstatic     #55                 // Field COLUMN_FAMILY_BYTES:[B
      31: aastore
      32: invokevirtual #91                 // Method org/apache/hadoop/hbase/HBaseTestingUtility.createLocalHRegion:(Lorg/apache/hadoop/hbase/TableName;[B[BZLorg/apache/hadoop/hbase/client/Durability;Lorg/apache/hadoop/hbase/wal/WAL;[[B)Lorg/apache/hadoop/hbase/regionserver/HRegion;
      35: areturn

  static {};
    Code:
       0: ldc           #92                 // class org/apache/hadoop/hbase/regionserver/TestFailedAppendAndSync
       2: invokestatic  #93                 // Method org/apache/hadoop/hbase/HBaseClassTestRule.forClass:(Ljava/lang/Class;)Lorg/apache/hadoop/hbase/HBaseClassTestRule;
       5: putstatic     #94                 // Field CLASS_RULE:Lorg/apache/hadoop/hbase/HBaseClassTestRule;
       8: ldc           #92                 // class org/apache/hadoop/hbase/regionserver/TestFailedAppendAndSync
      10: invokestatic  #95                 // Method org/slf4j/LoggerFactory.getLogger:(Ljava/lang/Class;)Lorg/slf4j/Logger;
      13: putstatic     #21                 // Field LOG:Lorg/slf4j/Logger;
      16: ldc           #96                 // String MyCF
      18: invokestatic  #52                 // Method org/apache/hadoop/hbase/util/Bytes.toBytes:(Ljava/lang/String;)[B
      21: putstatic     #55                 // Field COLUMN_FAMILY_BYTES:[B
      24: return
}
