Compiled from "TestCoprocessorScanPolicy.java"
public class org.apache.hadoop.hbase.util.TestCoprocessorScanPolicy$ScanObserver implements org.apache.hadoop.hbase.coprocessor.RegionCoprocessor,org.apache.hadoop.hbase.coprocessor.RegionObserver {
  public org.apache.hadoop.hbase.util.TestCoprocessorScanPolicy$ScanObserver();
    Code:
       0: aload_0
       1: invokespecial #1                  // Method java/lang/Object."<init>":()V
       4: aload_0
       5: new           #2                  // class java/util/concurrent/ConcurrentHashMap
       8: dup
       9: invokespecial #3                  // Method java/util/concurrent/ConcurrentHashMap."<init>":()V
      12: putfield      #4                  // Field ttls:Ljava/util/concurrent/ConcurrentMap;
      15: aload_0
      16: new           #2                  // class java/util/concurrent/ConcurrentHashMap
      19: dup
      20: invokespecial #3                  // Method java/util/concurrent/ConcurrentHashMap."<init>":()V
      23: putfield      #5                  // Field versions:Ljava/util/concurrent/ConcurrentMap;
      26: return

  public java.util.Optional<org.apache.hadoop.hbase.coprocessor.RegionObserver> getRegionObserver();
    Code:
       0: aload_0
       1: invokestatic  #6                  // Method java/util/Optional.of:(Ljava/lang/Object;)Ljava/util/Optional;
       4: areturn

  public void prePut(org.apache.hadoop.hbase.coprocessor.ObserverContext<org.apache.hadoop.hbase.coprocessor.RegionCoprocessorEnvironment>, org.apache.hadoop.hbase.client.Put, org.apache.hadoop.hbase.wal.WALEdit, org.apache.hadoop.hbase.client.Durability) throws java.io.IOException;
    Code:
       0: aload_2
       1: ldc           #7                  // String ttl
       3: invokevirtual #8                  // Method org/apache/hadoop/hbase/client/Put.getAttribute:(Ljava/lang/String;)[B
       6: ifnull        118
       9: aload_2
      10: invokevirtual #9                  // Method org/apache/hadoop/hbase/client/Put.getFamilyCellMap:()Ljava/util/NavigableMap;
      13: invokeinterface #10,  1           // InterfaceMethod java/util/NavigableMap.values:()Ljava/util/Collection;
      18: invokeinterface #11,  1           // InterfaceMethod java/util/Collection.stream:()Ljava/util/stream/Stream;
      23: invokeinterface #12,  1           // InterfaceMethod java/util/stream/Stream.findFirst:()Ljava/util/Optional;
      28: invokevirtual #13                 // Method java/util/Optional.get:()Ljava/lang/Object;
      31: checkcast     #14                 // class java/util/List
      34: iconst_0
      35: invokeinterface #15,  2           // InterfaceMethod java/util/List.get:(I)Ljava/lang/Object;
      40: checkcast     #16                 // class org/apache/hadoop/hbase/Cell
      43: astore        5
      45: aload_0
      46: getfield      #4                  // Field ttls:Ljava/util/concurrent/ConcurrentMap;
      49: aload         5
      51: invokeinterface #17,  1           // InterfaceMethod org/apache/hadoop/hbase/Cell.getQualifierArray:()[B
      56: aload         5
      58: invokeinterface #18,  1           // InterfaceMethod org/apache/hadoop/hbase/Cell.getQualifierOffset:()I
      63: aload         5
      65: invokeinterface #19,  1           // InterfaceMethod org/apache/hadoop/hbase/Cell.getQualifierLength:()I
      70: invokestatic  #20                 // Method org/apache/hadoop/hbase/util/Bytes.toString:([BII)Ljava/lang/String;
      73: invokestatic  #21                 // Method org/apache/hadoop/hbase/TableName.valueOf:(Ljava/lang/String;)Lorg/apache/hadoop/hbase/TableName;
      76: aload         5
      78: invokeinterface #22,  1           // InterfaceMethod org/apache/hadoop/hbase/Cell.getValueArray:()[B
      83: aload         5
      85: invokeinterface #23,  1           // InterfaceMethod org/apache/hadoop/hbase/Cell.getValueOffset:()I
      90: aload         5
      92: invokeinterface #24,  1           // InterfaceMethod org/apache/hadoop/hbase/Cell.getValueLength:()I
      97: invokestatic  #25                 // Method org/apache/hadoop/hbase/util/Bytes.toLong:([BII)J
     100: invokestatic  #26                 // Method java/lang/Long.valueOf:(J)Ljava/lang/Long;
     103: invokeinterface #27,  3           // InterfaceMethod java/util/concurrent/ConcurrentMap.put:(Ljava/lang/Object;Ljava/lang/Object;)Ljava/lang/Object;
     108: pop
     109: aload_1
     110: invokeinterface #28,  1           // InterfaceMethod org/apache/hadoop/hbase/coprocessor/ObserverContext.bypass:()V
     115: goto          233
     118: aload_2
     119: ldc           #29                 // String versions
     121: invokevirtual #8                  // Method org/apache/hadoop/hbase/client/Put.getAttribute:(Ljava/lang/String;)[B
     124: ifnull        233
     127: aload_2
     128: invokevirtual #9                  // Method org/apache/hadoop/hbase/client/Put.getFamilyCellMap:()Ljava/util/NavigableMap;
     131: invokeinterface #10,  1           // InterfaceMethod java/util/NavigableMap.values:()Ljava/util/Collection;
     136: invokeinterface #11,  1           // InterfaceMethod java/util/Collection.stream:()Ljava/util/stream/Stream;
     141: invokeinterface #12,  1           // InterfaceMethod java/util/stream/Stream.findFirst:()Ljava/util/Optional;
     146: invokevirtual #13                 // Method java/util/Optional.get:()Ljava/lang/Object;
     149: checkcast     #14                 // class java/util/List
     152: iconst_0
     153: invokeinterface #15,  2           // InterfaceMethod java/util/List.get:(I)Ljava/lang/Object;
     158: checkcast     #16                 // class org/apache/hadoop/hbase/Cell
     161: astore        5
     163: aload_0
     164: getfield      #5                  // Field versions:Ljava/util/concurrent/ConcurrentMap;
     167: aload         5
     169: invokeinterface #17,  1           // InterfaceMethod org/apache/hadoop/hbase/Cell.getQualifierArray:()[B
     174: aload         5
     176: invokeinterface #18,  1           // InterfaceMethod org/apache/hadoop/hbase/Cell.getQualifierOffset:()I
     181: aload         5
     183: invokeinterface #19,  1           // InterfaceMethod org/apache/hadoop/hbase/Cell.getQualifierLength:()I
     188: invokestatic  #20                 // Method org/apache/hadoop/hbase/util/Bytes.toString:([BII)Ljava/lang/String;
     191: invokestatic  #21                 // Method org/apache/hadoop/hbase/TableName.valueOf:(Ljava/lang/String;)Lorg/apache/hadoop/hbase/TableName;
     194: aload         5
     196: invokeinterface #22,  1           // InterfaceMethod org/apache/hadoop/hbase/Cell.getValueArray:()[B
     201: aload         5
     203: invokeinterface #23,  1           // InterfaceMethod org/apache/hadoop/hbase/Cell.getValueOffset:()I
     208: aload         5
     210: invokeinterface #24,  1           // InterfaceMethod org/apache/hadoop/hbase/Cell.getValueLength:()I
     215: invokestatic  #30                 // Method org/apache/hadoop/hbase/util/Bytes.toInt:([BII)I
     218: invokestatic  #31                 // Method java/lang/Integer.valueOf:(I)Ljava/lang/Integer;
     221: invokeinterface #27,  3           // InterfaceMethod java/util/concurrent/ConcurrentMap.put:(Ljava/lang/Object;Ljava/lang/Object;)Ljava/lang/Object;
     226: pop
     227: aload_1
     228: invokeinterface #28,  1           // InterfaceMethod org/apache/hadoop/hbase/coprocessor/ObserverContext.bypass:()V
     233: return

  public org.apache.hadoop.hbase.regionserver.InternalScanner preFlush(org.apache.hadoop.hbase.coprocessor.ObserverContext<org.apache.hadoop.hbase.coprocessor.RegionCoprocessorEnvironment>, org.apache.hadoop.hbase.regionserver.Store, org.apache.hadoop.hbase.regionserver.InternalScanner, org.apache.hadoop.hbase.regionserver.FlushLifeCycleTracker) throws java.io.IOException;
    Code:
       0: aload_0
       1: aload_2
       2: aload_3
       3: invokespecial #38                 // Method wrap:(Lorg/apache/hadoop/hbase/regionserver/Store;Lorg/apache/hadoop/hbase/regionserver/InternalScanner;)Lorg/apache/hadoop/hbase/regionserver/InternalScanner;
       6: areturn

  public org.apache.hadoop.hbase.regionserver.InternalScanner preCompact(org.apache.hadoop.hbase.coprocessor.ObserverContext<org.apache.hadoop.hbase.coprocessor.RegionCoprocessorEnvironment>, org.apache.hadoop.hbase.regionserver.Store, org.apache.hadoop.hbase.regionserver.InternalScanner, org.apache.hadoop.hbase.regionserver.ScanType, org.apache.hadoop.hbase.regionserver.compactions.CompactionLifeCycleTracker, org.apache.hadoop.hbase.regionserver.compactions.CompactionRequest) throws java.io.IOException;
    Code:
       0: aload_0
       1: aload_2
       2: aload_3
       3: invokespecial #38                 // Method wrap:(Lorg/apache/hadoop/hbase/regionserver/Store;Lorg/apache/hadoop/hbase/regionserver/InternalScanner;)Lorg/apache/hadoop/hbase/regionserver/InternalScanner;
       6: areturn

  public void preGetOp(org.apache.hadoop.hbase.coprocessor.ObserverContext<org.apache.hadoop.hbase.coprocessor.RegionCoprocessorEnvironment>, org.apache.hadoop.hbase.client.Get, java.util.List<org.apache.hadoop.hbase.Cell>) throws java.io.IOException;
    Code:
       0: aload_1
       1: invokeinterface #39,  1           // InterfaceMethod org/apache/hadoop/hbase/coprocessor/ObserverContext.getEnvironment:()Lorg/apache/hadoop/hbase/CoprocessorEnvironment;
       6: checkcast     #40                 // class org/apache/hadoop/hbase/coprocessor/RegionCoprocessorEnvironment
       9: invokeinterface #41,  1           // InterfaceMethod org/apache/hadoop/hbase/coprocessor/RegionCoprocessorEnvironment.getRegion:()Lorg/apache/hadoop/hbase/regionserver/Region;
      14: invokeinterface #42,  1           // InterfaceMethod org/apache/hadoop/hbase/regionserver/Region.getTableDescriptor:()Lorg/apache/hadoop/hbase/client/TableDescriptor;
      19: invokeinterface #43,  1           // InterfaceMethod org/apache/hadoop/hbase/client/TableDescriptor.getTableName:()Lorg/apache/hadoop/hbase/TableName;
      24: astore        4
      26: aload_0
      27: getfield      #4                  // Field ttls:Ljava/util/concurrent/ConcurrentMap;
      30: aload         4
      32: invokeinterface #33,  2           // InterfaceMethod java/util/concurrent/ConcurrentMap.get:(Ljava/lang/Object;)Ljava/lang/Object;
      37: checkcast     #34                 // class java/lang/Long
      40: astore        5
      42: aload         5
      44: ifnull        68
      47: aload_2
      48: invokestatic  #44                 // Method org/apache/hadoop/hbase/util/EnvironmentEdgeManager.currentTime:()J
      51: aload         5
      53: invokevirtual #45                 // Method java/lang/Long.longValue:()J
      56: lsub
      57: aload_2
      58: invokevirtual #46                 // Method org/apache/hadoop/hbase/client/Get.getTimeRange:()Lorg/apache/hadoop/hbase/io/TimeRange;
      61: invokevirtual #47                 // Method org/apache/hadoop/hbase/io/TimeRange.getMax:()J
      64: invokevirtual #48                 // Method org/apache/hadoop/hbase/client/Get.setTimeRange:(JJ)Lorg/apache/hadoop/hbase/client/Get;
      67: pop
      68: aload_0
      69: getfield      #5                  // Field versions:Ljava/util/concurrent/ConcurrentMap;
      72: aload         4
      74: invokeinterface #33,  2           // InterfaceMethod java/util/concurrent/ConcurrentMap.get:(Ljava/lang/Object;)Ljava/lang/Object;
      79: checkcast     #35                 // class java/lang/Integer
      82: astore        6
      84: aload         6
      86: ifnull        99
      89: aload_2
      90: aload         6
      92: invokevirtual #49                 // Method java/lang/Integer.intValue:()I
      95: invokevirtual #50                 // Method org/apache/hadoop/hbase/client/Get.readVersions:(I)Lorg/apache/hadoop/hbase/client/Get;
      98: pop
      99: return

  public void preScannerOpen(org.apache.hadoop.hbase.coprocessor.ObserverContext<org.apache.hadoop.hbase.coprocessor.RegionCoprocessorEnvironment>, org.apache.hadoop.hbase.client.Scan) throws java.io.IOException;
    Code:
       0: aload_1
       1: invokeinterface #39,  1           // InterfaceMethod org/apache/hadoop/hbase/coprocessor/ObserverContext.getEnvironment:()Lorg/apache/hadoop/hbase/CoprocessorEnvironment;
       6: checkcast     #40                 // class org/apache/hadoop/hbase/coprocessor/RegionCoprocessorEnvironment
       9: invokeinterface #41,  1           // InterfaceMethod org/apache/hadoop/hbase/coprocessor/RegionCoprocessorEnvironment.getRegion:()Lorg/apache/hadoop/hbase/regionserver/Region;
      14: astore_3
      15: aload_3
      16: invokeinterface #42,  1           // InterfaceMethod org/apache/hadoop/hbase/regionserver/Region.getTableDescriptor:()Lorg/apache/hadoop/hbase/client/TableDescriptor;
      21: invokeinterface #43,  1           // InterfaceMethod org/apache/hadoop/hbase/client/TableDescriptor.getTableName:()Lorg/apache/hadoop/hbase/TableName;
      26: astore        4
      28: aload_0
      29: getfield      #4                  // Field ttls:Ljava/util/concurrent/ConcurrentMap;
      32: aload         4
      34: invokeinterface #33,  2           // InterfaceMethod java/util/concurrent/ConcurrentMap.get:(Ljava/lang/Object;)Ljava/lang/Object;
      39: checkcast     #34                 // class java/lang/Long
      42: astore        5
      44: aload         5
      46: ifnull        70
      49: aload_2
      50: invokestatic  #44                 // Method org/apache/hadoop/hbase/util/EnvironmentEdgeManager.currentTime:()J
      53: aload         5
      55: invokevirtual #45                 // Method java/lang/Long.longValue:()J
      58: lsub
      59: aload_2
      60: invokevirtual #51                 // Method org/apache/hadoop/hbase/client/Scan.getTimeRange:()Lorg/apache/hadoop/hbase/io/TimeRange;
      63: invokevirtual #47                 // Method org/apache/hadoop/hbase/io/TimeRange.getMax:()J
      66: invokevirtual #52                 // Method org/apache/hadoop/hbase/client/Scan.setTimeRange:(JJ)Lorg/apache/hadoop/hbase/client/Scan;
      69: pop
      70: aload_0
      71: getfield      #5                  // Field versions:Ljava/util/concurrent/ConcurrentMap;
      74: aload         4
      76: invokeinterface #33,  2           // InterfaceMethod java/util/concurrent/ConcurrentMap.get:(Ljava/lang/Object;)Ljava/lang/Object;
      81: checkcast     #35                 // class java/lang/Integer
      84: astore        6
      86: aload         6
      88: ifnull        101
      91: aload_2
      92: aload         6
      94: invokevirtual #49                 // Method java/lang/Integer.intValue:()I
      97: invokevirtual #53                 // Method org/apache/hadoop/hbase/client/Scan.readVersions:(I)Lorg/apache/hadoop/hbase/client/Scan;
     100: pop
     101: return
}
