Compiled from "TestTagUtil.java"
public class org.apache.hadoop.hbase.TestTagUtil {
  public static final org.apache.hadoop.hbase.HBaseClassTestRule CLASS_RULE;

  public org.apache.hadoop.hbase.TestTagUtil();
    Code:
       0: aload_0
       1: invokespecial #1                  // Method java/lang/Object."<init>":()V
       4: return

  public void testCarryForwardTTLTag() throws java.lang.Exception;
    Code:
       0: ldc2_w        #2                  // long 10000l
       3: lstore_1
       4: aconst_null
       5: lload_1
       6: invokestatic  #4                  // Method org/apache/hadoop/hbase/TagUtil.carryForwardTTLTag:(Ljava/util/List;J)Ljava/util/List;
       9: astore_3
      10: lconst_1
      11: aload_3
      12: invokeinterface #5,  1            // InterfaceMethod java/util/List.size:()I
      17: i2l
      18: invokestatic  #6                  // Method org/junit/Assert.assertEquals:(JJ)V
      21: aload_3
      22: iconst_0
      23: invokeinterface #7,  2            // InterfaceMethod java/util/List.get:(I)Ljava/lang/Object;
      28: checkcast     #8                  // class org/apache/hadoop/hbase/Tag
      31: astore        4
      33: ldc2_w        #10                 // long 8l
      36: aload         4
      38: invokeinterface #12,  1           // InterfaceMethod org/apache/hadoop/hbase/Tag.getType:()B
      43: i2l
      44: invokestatic  #6                  // Method org/junit/Assert.assertEquals:(JJ)V
      47: lload_1
      48: aload         4
      50: invokestatic  #13                 // InterfaceMethod org/apache/hadoop/hbase/Tag.getValueAsLong:(Lorg/apache/hadoop/hbase/Tag;)J
      53: invokestatic  #6                  // Method org/junit/Assert.assertEquals:(JJ)V
      56: ldc2_w        #14                 // long 30000l
      59: lstore        5
      61: aload_3
      62: lload         5
      64: invokestatic  #4                  // Method org/apache/hadoop/hbase/TagUtil.carryForwardTTLTag:(Ljava/util/List;J)Ljava/util/List;
      67: astore_3
      68: lconst_1
      69: aload_3
      70: invokeinterface #5,  1            // InterfaceMethod java/util/List.size:()I
      75: i2l
      76: invokestatic  #6                  // Method org/junit/Assert.assertEquals:(JJ)V
      79: aload_3
      80: iconst_0
      81: invokeinterface #7,  2            // InterfaceMethod java/util/List.get:(I)Ljava/lang/Object;
      86: checkcast     #8                  // class org/apache/hadoop/hbase/Tag
      89: astore        4
      91: ldc2_w        #10                 // long 8l
      94: aload         4
      96: invokeinterface #12,  1           // InterfaceMethod org/apache/hadoop/hbase/Tag.getType:()B
     101: i2l
     102: invokestatic  #6                  // Method org/junit/Assert.assertEquals:(JJ)V
     105: lload         5
     107: aload         4
     109: invokestatic  #13                 // InterfaceMethod org/apache/hadoop/hbase/Tag.getValueAsLong:(Lorg/apache/hadoop/hbase/Tag;)J
     112: invokestatic  #6                  // Method org/junit/Assert.assertEquals:(JJ)V
     115: return

  static {};
    Code:
       0: ldc           #16                 // class org/apache/hadoop/hbase/TestTagUtil
       2: invokestatic  #17                 // Method org/apache/hadoop/hbase/HBaseClassTestRule.forClass:(Ljava/lang/Class;)Lorg/apache/hadoop/hbase/HBaseClassTestRule;
       5: putstatic     #18                 // Field CLASS_RULE:Lorg/apache/hadoop/hbase/HBaseClassTestRule;
       8: return
}
