Compiled from "TestComparators.java"
public class org.apache.hadoop.hbase.filter.TestComparators {
  public static final org.apache.hadoop.hbase.HBaseClassTestRule CLASS_RULE;

  public org.apache.hadoop.hbase.filter.TestComparators();
    Code:
       0: aload_0
       1: invokespecial #1                  // Method java/lang/Object."<init>":()V
       4: return

  public void testCellFieldsCompare() throws java.lang.Exception;
    Code:
       0: ldc           #2                  // String row0
       2: invokestatic  #3                  // Method org/apache/hadoop/hbase/util/Bytes.toBytes:(Ljava/lang/String;)[B
       5: astore_1
       6: ldc           #4                  // String row1
       8: invokestatic  #3                  // Method org/apache/hadoop/hbase/util/Bytes.toBytes:(Ljava/lang/String;)[B
      11: astore_2
      12: ldc           #5                  // String row2
      14: invokestatic  #3                  // Method org/apache/hadoop/hbase/util/Bytes.toBytes:(Ljava/lang/String;)[B
      17: astore_3
      18: ldc           #6                  // String cf1
      20: invokestatic  #3                  // Method org/apache/hadoop/hbase/util/Bytes.toBytes:(Ljava/lang/String;)[B
      23: astore        4
      25: ldc           #7                  // String qual1
      27: invokestatic  #3                  // Method org/apache/hadoop/hbase/util/Bytes.toBytes:(Ljava/lang/String;)[B
      30: astore        5
      32: ldc           #8                  // String qual2
      34: invokestatic  #3                  // Method org/apache/hadoop/hbase/util/Bytes.toBytes:(Ljava/lang/String;)[B
      37: astore        6
      39: ldc           #9                  // String r
      41: invokestatic  #3                  // Method org/apache/hadoop/hbase/util/Bytes.toBytes:(Ljava/lang/String;)[B
      44: astore        7
      46: ldc2_w        #10                 // long 1234l
      49: lstore        8
      51: lload         8
      53: invokestatic  #12                 // Method org/apache/hadoop/hbase/util/Bytes.toBytes:(J)[B
      56: astore        10
      58: ldc2_w        #13                 // long 2000l
      61: lstore        11
      63: lload         11
      65: invokestatic  #12                 // Method org/apache/hadoop/hbase/util/Bytes.toBytes:(J)[B
      68: astore        13
      70: new           #15                 // class org/apache/hadoop/hbase/KeyValue
      73: dup
      74: aload_2
      75: aload         4
      77: aload         5
      79: aload         10
      81: invokespecial #16                 // Method org/apache/hadoop/hbase/KeyValue."<init>":([B[B[B[B)V
      84: astore        14
      86: aload         14
      88: invokevirtual #17                 // Method org/apache/hadoop/hbase/KeyValue.getBuffer:()[B
      91: invokestatic  #18                 // Method java/nio/ByteBuffer.wrap:([B)Ljava/nio/ByteBuffer;
      94: astore        15
      96: new           #19                 // class org/apache/hadoop/hbase/ByteBufferKeyValue
      99: dup
     100: aload         15
     102: iconst_0
     103: aload         15
     105: invokevirtual #20                 // Method java/nio/ByteBuffer.remaining:()I
     108: invokespecial #21                 // Method org/apache/hadoop/hbase/ByteBufferKeyValue."<init>":(Ljava/nio/ByteBuffer;II)V
     111: astore        16
     113: new           #22                 // class org/apache/hadoop/hbase/filter/BinaryComparator
     116: dup
     117: aload_2
     118: invokespecial #23                 // Method org/apache/hadoop/hbase/filter/BinaryComparator."<init>":([B)V
     121: astore        17
     123: lconst_0
     124: aload         16
     126: aload         17
     128: invokestatic  #24                 // Method org/apache/hadoop/hbase/PrivateCellUtil.compareRow:(Lorg/apache/hadoop/hbase/Cell;Lorg/apache/hadoop/hbase/filter/ByteArrayComparable;)I
     131: i2l
     132: invokestatic  #25                 // Method org/junit/Assert.assertEquals:(JJ)V
     135: lconst_0
     136: aload         14
     138: aload         17
     140: invokestatic  #24                 // Method org/apache/hadoop/hbase/PrivateCellUtil.compareRow:(Lorg/apache/hadoop/hbase/Cell;Lorg/apache/hadoop/hbase/filter/ByteArrayComparable;)I
     143: i2l
     144: invokestatic  #25                 // Method org/junit/Assert.assertEquals:(JJ)V
     147: new           #15                 // class org/apache/hadoop/hbase/KeyValue
     150: dup
     151: aload_1
     152: aload         4
     154: aload         5
     156: aload         10
     158: invokespecial #16                 // Method org/apache/hadoop/hbase/KeyValue."<init>":([B[B[B[B)V
     161: astore        14
     163: aload         14
     165: invokevirtual #17                 // Method org/apache/hadoop/hbase/KeyValue.getBuffer:()[B
     168: invokestatic  #18                 // Method java/nio/ByteBuffer.wrap:([B)Ljava/nio/ByteBuffer;
     171: astore        15
     173: new           #19                 // class org/apache/hadoop/hbase/ByteBufferKeyValue
     176: dup
     177: aload         15
     179: iconst_0
     180: aload         15
     182: invokevirtual #20                 // Method java/nio/ByteBuffer.remaining:()I
     185: invokespecial #21                 // Method org/apache/hadoop/hbase/ByteBufferKeyValue."<init>":(Ljava/nio/ByteBuffer;II)V
     188: astore        16
     190: aload         16
     192: aload         17
     194: invokestatic  #24                 // Method org/apache/hadoop/hbase/PrivateCellUtil.compareRow:(Lorg/apache/hadoop/hbase/Cell;Lorg/apache/hadoop/hbase/filter/ByteArrayComparable;)I
     197: ifle          204
     200: iconst_1
     201: goto          205
     204: iconst_0
     205: invokestatic  #26                 // Method org/junit/Assert.assertTrue:(Z)V
     208: aload         14
     210: aload         17
     212: invokestatic  #24                 // Method org/apache/hadoop/hbase/PrivateCellUtil.compareRow:(Lorg/apache/hadoop/hbase/Cell;Lorg/apache/hadoop/hbase/filter/ByteArrayComparable;)I
     215: ifle          222
     218: iconst_1
     219: goto          223
     222: iconst_0
     223: invokestatic  #26                 // Method org/junit/Assert.assertTrue:(Z)V
     226: new           #15                 // class org/apache/hadoop/hbase/KeyValue
     229: dup
     230: aload_3
     231: aload         4
     233: aload         5
     235: aload         10
     237: invokespecial #16                 // Method org/apache/hadoop/hbase/KeyValue."<init>":([B[B[B[B)V
     240: astore        14
     242: aload         14
     244: invokevirtual #17                 // Method org/apache/hadoop/hbase/KeyValue.getBuffer:()[B
     247: invokestatic  #18                 // Method java/nio/ByteBuffer.wrap:([B)Ljava/nio/ByteBuffer;
     250: astore        15
     252: new           #19                 // class org/apache/hadoop/hbase/ByteBufferKeyValue
     255: dup
     256: aload         15
     258: iconst_0
     259: aload         15
     261: invokevirtual #20                 // Method java/nio/ByteBuffer.remaining:()I
     264: invokespecial #21                 // Method org/apache/hadoop/hbase/ByteBufferKeyValue."<init>":(Ljava/nio/ByteBuffer;II)V
     267: astore        16
     269: aload         16
     271: aload         17
     273: invokestatic  #24                 // Method org/apache/hadoop/hbase/PrivateCellUtil.compareRow:(Lorg/apache/hadoop/hbase/Cell;Lorg/apache/hadoop/hbase/filter/ByteArrayComparable;)I
     276: ifge          283
     279: iconst_1
     280: goto          284
     283: iconst_0
     284: invokestatic  #26                 // Method org/junit/Assert.assertTrue:(Z)V
     287: aload         14
     289: aload         17
     291: invokestatic  #24                 // Method org/apache/hadoop/hbase/PrivateCellUtil.compareRow:(Lorg/apache/hadoop/hbase/Cell;Lorg/apache/hadoop/hbase/filter/ByteArrayComparable;)I
     294: ifge          301
     297: iconst_1
     298: goto          302
     301: iconst_0
     302: invokestatic  #26                 // Method org/junit/Assert.assertTrue:(Z)V
     305: new           #27                 // class org/apache/hadoop/hbase/filter/BinaryPrefixComparator
     308: dup
     309: ldc           #28                 // String qual
     311: invokestatic  #3                  // Method org/apache/hadoop/hbase/util/Bytes.toBytes:(Ljava/lang/String;)[B
     314: invokespecial #29                 // Method org/apache/hadoop/hbase/filter/BinaryPrefixComparator."<init>":([B)V
     317: astore        17
     319: lconst_0
     320: aload         16
     322: aload         17
     324: invokestatic  #30                 // Method org/apache/hadoop/hbase/PrivateCellUtil.compareQualifier:(Lorg/apache/hadoop/hbase/Cell;Lorg/apache/hadoop/hbase/filter/ByteArrayComparable;)I
     327: i2l
     328: invokestatic  #25                 // Method org/junit/Assert.assertEquals:(JJ)V
     331: lconst_0
     332: aload         14
     334: aload         17
     336: invokestatic  #30                 // Method org/apache/hadoop/hbase/PrivateCellUtil.compareQualifier:(Lorg/apache/hadoop/hbase/Cell;Lorg/apache/hadoop/hbase/filter/ByteArrayComparable;)I
     339: i2l
     340: invokestatic  #25                 // Method org/junit/Assert.assertEquals:(JJ)V
     343: new           #15                 // class org/apache/hadoop/hbase/KeyValue
     346: dup
     347: aload_3
     348: aload         4
     350: aload         6
     352: aload         10
     354: invokespecial #16                 // Method org/apache/hadoop/hbase/KeyValue."<init>":([B[B[B[B)V
     357: astore        14
     359: aload         14
     361: invokevirtual #17                 // Method org/apache/hadoop/hbase/KeyValue.getBuffer:()[B
     364: invokestatic  #18                 // Method java/nio/ByteBuffer.wrap:([B)Ljava/nio/ByteBuffer;
     367: astore        15
     369: new           #19                 // class org/apache/hadoop/hbase/ByteBufferKeyValue
     372: dup
     373: aload         15
     375: iconst_0
     376: aload         15
     378: invokevirtual #20                 // Method java/nio/ByteBuffer.remaining:()I
     381: invokespecial #21                 // Method org/apache/hadoop/hbase/ByteBufferKeyValue."<init>":(Ljava/nio/ByteBuffer;II)V
     384: astore        16
     386: lconst_0
     387: aload         16
     389: aload         17
     391: invokestatic  #30                 // Method org/apache/hadoop/hbase/PrivateCellUtil.compareQualifier:(Lorg/apache/hadoop/hbase/Cell;Lorg/apache/hadoop/hbase/filter/ByteArrayComparable;)I
     394: i2l
     395: invokestatic  #25                 // Method org/junit/Assert.assertEquals:(JJ)V
     398: lconst_0
     399: aload         14
     401: aload         17
     403: invokestatic  #30                 // Method org/apache/hadoop/hbase/PrivateCellUtil.compareQualifier:(Lorg/apache/hadoop/hbase/Cell;Lorg/apache/hadoop/hbase/filter/ByteArrayComparable;)I
     406: i2l
     407: invokestatic  #25                 // Method org/junit/Assert.assertEquals:(JJ)V
     410: new           #15                 // class org/apache/hadoop/hbase/KeyValue
     413: dup
     414: aload_3
     415: aload         4
     417: aload         7
     419: aload         10
     421: invokespecial #16                 // Method org/apache/hadoop/hbase/KeyValue."<init>":([B[B[B[B)V
     424: astore        14
     426: aload         14
     428: invokevirtual #17                 // Method org/apache/hadoop/hbase/KeyValue.getBuffer:()[B
     431: invokestatic  #18                 // Method java/nio/ByteBuffer.wrap:([B)Ljava/nio/ByteBuffer;
     434: astore        15
     436: new           #19                 // class org/apache/hadoop/hbase/ByteBufferKeyValue
     439: dup
     440: aload         15
     442: iconst_0
     443: aload         15
     445: invokevirtual #20                 // Method java/nio/ByteBuffer.remaining:()I
     448: invokespecial #21                 // Method org/apache/hadoop/hbase/ByteBufferKeyValue."<init>":(Ljava/nio/ByteBuffer;II)V
     451: astore        16
     453: aload         16
     455: aload         17
     457: invokestatic  #30                 // Method org/apache/hadoop/hbase/PrivateCellUtil.compareQualifier:(Lorg/apache/hadoop/hbase/Cell;Lorg/apache/hadoop/hbase/filter/ByteArrayComparable;)I
     460: ifge          467
     463: iconst_1
     464: goto          468
     467: iconst_0
     468: invokestatic  #26                 // Method org/junit/Assert.assertTrue:(Z)V
     471: aload         14
     473: aload         17
     475: invokestatic  #30                 // Method org/apache/hadoop/hbase/PrivateCellUtil.compareQualifier:(Lorg/apache/hadoop/hbase/Cell;Lorg/apache/hadoop/hbase/filter/ByteArrayComparable;)I
     478: ifge          485
     481: iconst_1
     482: goto          486
     485: iconst_0
     486: invokestatic  #26                 // Method org/junit/Assert.assertTrue:(Z)V
     489: new           #31                 // class org/apache/hadoop/hbase/filter/LongComparator
     492: dup
     493: lload         8
     495: invokespecial #32                 // Method org/apache/hadoop/hbase/filter/LongComparator."<init>":(J)V
     498: astore        17
     500: lconst_0
     501: aload         16
     503: aload         17
     505: invokestatic  #33                 // Method org/apache/hadoop/hbase/PrivateCellUtil.compareValue:(Lorg/apache/hadoop/hbase/Cell;Lorg/apache/hadoop/hbase/filter/ByteArrayComparable;)I
     508: i2l
     509: invokestatic  #25                 // Method org/junit/Assert.assertEquals:(JJ)V
     512: lconst_0
     513: aload         14
     515: aload         17
     517: invokestatic  #33                 // Method org/apache/hadoop/hbase/PrivateCellUtil.compareValue:(Lorg/apache/hadoop/hbase/Cell;Lorg/apache/hadoop/hbase/filter/ByteArrayComparable;)I
     520: i2l
     521: invokestatic  #25                 // Method org/junit/Assert.assertEquals:(JJ)V
     524: new           #15                 // class org/apache/hadoop/hbase/KeyValue
     527: dup
     528: aload_2
     529: aload         4
     531: aload         5
     533: aload         13
     535: invokespecial #16                 // Method org/apache/hadoop/hbase/KeyValue."<init>":([B[B[B[B)V
     538: astore        14
     540: aload         14
     542: invokevirtual #17                 // Method org/apache/hadoop/hbase/KeyValue.getBuffer:()[B
     545: invokestatic  #18                 // Method java/nio/ByteBuffer.wrap:([B)Ljava/nio/ByteBuffer;
     548: astore        15
     550: new           #19                 // class org/apache/hadoop/hbase/ByteBufferKeyValue
     553: dup
     554: aload         15
     556: iconst_0
     557: aload         15
     559: invokevirtual #20                 // Method java/nio/ByteBuffer.remaining:()I
     562: invokespecial #21                 // Method org/apache/hadoop/hbase/ByteBufferKeyValue."<init>":(Ljava/nio/ByteBuffer;II)V
     565: astore        16
     567: aload         16
     569: aload         17
     571: invokestatic  #33                 // Method org/apache/hadoop/hbase/PrivateCellUtil.compareValue:(Lorg/apache/hadoop/hbase/Cell;Lorg/apache/hadoop/hbase/filter/ByteArrayComparable;)I
     574: ifge          581
     577: iconst_1
     578: goto          582
     581: iconst_0
     582: invokestatic  #26                 // Method org/junit/Assert.assertTrue:(Z)V
     585: aload         14
     587: aload         17
     589: invokestatic  #33                 // Method org/apache/hadoop/hbase/PrivateCellUtil.compareValue:(Lorg/apache/hadoop/hbase/Cell;Lorg/apache/hadoop/hbase/filter/ByteArrayComparable;)I
     592: ifge          599
     595: iconst_1
     596: goto          600
     599: iconst_0
     600: invokestatic  #26                 // Method org/junit/Assert.assertTrue:(Z)V
     603: new           #34                 // class org/apache/hadoop/hbase/filter/SubstringComparator
     606: dup
     607: ldc           #35                 // String cf
     609: invokespecial #36                 // Method org/apache/hadoop/hbase/filter/SubstringComparator."<init>":(Ljava/lang/String;)V
     612: astore        17
     614: lconst_0
     615: aload         16
     617: aload         17
     619: invokestatic  #37                 // Method org/apache/hadoop/hbase/PrivateCellUtil.compareFamily:(Lorg/apache/hadoop/hbase/Cell;Lorg/apache/hadoop/hbase/filter/ByteArrayComparable;)I
     622: i2l
     623: invokestatic  #25                 // Method org/junit/Assert.assertEquals:(JJ)V
     626: lconst_0
     627: aload         14
     629: aload         17
     631: invokestatic  #37                 // Method org/apache/hadoop/hbase/PrivateCellUtil.compareFamily:(Lorg/apache/hadoop/hbase/Cell;Lorg/apache/hadoop/hbase/filter/ByteArrayComparable;)I
     634: i2l
     635: invokestatic  #25                 // Method org/junit/Assert.assertEquals:(JJ)V
     638: return

  static {};
    Code:
       0: ldc           #38                 // class org/apache/hadoop/hbase/filter/TestComparators
       2: invokestatic  #39                 // Method org/apache/hadoop/hbase/HBaseClassTestRule.forClass:(Ljava/lang/Class;)Lorg/apache/hadoop/hbase/HBaseClassTestRule;
       5: putstatic     #40                 // Field CLASS_RULE:Lorg/apache/hadoop/hbase/HBaseClassTestRule;
       8: return
}
