Compiled from "TestCompatibilitySingletonFactory.java"
public class org.apache.hadoop.hbase.TestCompatibilitySingletonFactory {
  public static final org.apache.hadoop.hbase.HBaseClassTestRule CLASS_RULE;

  public org.apache.hadoop.hbase.TestCompatibilitySingletonFactory();
    Code:
       0: aload_0
       1: invokespecial #2                  // Method java/lang/Object."<init>":()V
       4: return

  public void testGetInstance() throws java.lang.Exception;
    Code:
       0: new           #3                  // class java/util/ArrayList
       3: dup
       4: ldc           #5                  // int 100000
       6: invokespecial #6                  // Method java/util/ArrayList."<init>":(I)V
       9: astore_1
      10: new           #3                  // class java/util/ArrayList
      13: dup
      14: ldc           #5                  // int 100000
      16: invokespecial #6                  // Method java/util/ArrayList."<init>":(I)V
      19: astore_2
      20: iconst_0
      21: istore_3
      22: iload_3
      23: ldc           #5                  // int 100000
      25: if_icmpge     50
      28: aload_1
      29: new           #7                  // class org/apache/hadoop/hbase/TestCompatibilitySingletonFactory$TestCompatibilitySingletonFactoryCallable
      32: dup
      33: aload_0
      34: aconst_null
      35: invokespecial #8                  // Method org/apache/hadoop/hbase/TestCompatibilitySingletonFactory$TestCompatibilitySingletonFactoryCallable."<init>":(Lorg/apache/hadoop/hbase/TestCompatibilitySingletonFactory;Lorg/apache/hadoop/hbase/TestCompatibilitySingletonFactory$1;)V
      38: invokeinterface #9,  2            // InterfaceMethod java/util/List.add:(Ljava/lang/Object;)Z
      43: pop
      44: iinc          3, 1
      47: goto          22
      50: bipush        100
      52: invokestatic  #10                 // Method java/util/concurrent/Executors.newFixedThreadPool:(I)Ljava/util/concurrent/ExecutorService;
      55: astore_3
      56: aload_3
      57: aload_1
      58: invokeinterface #11,  2           // InterfaceMethod java/util/concurrent/ExecutorService.invokeAll:(Ljava/util/Collection;)Ljava/util/List;
      63: astore        4
      65: aload         4
      67: invokeinterface #12,  1           // InterfaceMethod java/util/List.iterator:()Ljava/util/Iterator;
      72: astore        5
      74: aload         5
      76: invokeinterface #13,  1           // InterfaceMethod java/util/Iterator.hasNext:()Z
      81: ifeq          113
      84: aload         5
      86: invokeinterface #14,  1           // InterfaceMethod java/util/Iterator.next:()Ljava/lang/Object;
      91: checkcast     #15                 // class java/util/concurrent/Future
      94: astore        6
      96: aload_2
      97: aload         6
      99: invokeinterface #16,  1           // InterfaceMethod java/util/concurrent/Future.get:()Ljava/lang/Object;
     104: invokeinterface #9,  2            // InterfaceMethod java/util/List.add:(Ljava/lang/Object;)Z
     109: pop
     110: goto          74
     113: aload_2
     114: iconst_0
     115: invokeinterface #17,  2           // InterfaceMethod java/util/List.get:(I)Ljava/lang/Object;
     120: checkcast     #18                 // class java/lang/String
     123: astore        5
     125: aload_2
     126: invokeinterface #12,  1           // InterfaceMethod java/util/List.iterator:()Ljava/util/Iterator;
     131: astore        6
     133: aload         6
     135: invokeinterface #13,  1           // InterfaceMethod java/util/Iterator.hasNext:()Z
     140: ifeq          165
     143: aload         6
     145: invokeinterface #14,  1           // InterfaceMethod java/util/Iterator.next:()Ljava/lang/Object;
     150: checkcast     #18                 // class java/lang/String
     153: astore        7
     155: aload         5
     157: aload         7
     159: invokestatic  #19                 // Method org/junit/Assert.assertEquals:(Ljava/lang/Object;Ljava/lang/Object;)V
     162: goto          133
     165: new           #20                 // class org/apache/hadoop/hbase/RandomStringGeneratorImpl
     168: dup
     169: invokespecial #21                 // Method org/apache/hadoop/hbase/RandomStringGeneratorImpl."<init>":()V
     172: invokevirtual #22                 // Method org/apache/hadoop/hbase/RandomStringGeneratorImpl.getRandString:()Ljava/lang/String;
     175: aload         5
     177: invokestatic  #23                 // Method org/junit/Assert.assertNotEquals:(Ljava/lang/Object;Ljava/lang/Object;)V
     180: return

  static java.util.Random access$000();
    Code:
       0: getstatic     #1                  // Field RANDOM:Ljava/util/Random;
       3: areturn

  static {};
    Code:
       0: ldc           #4                  // class org/apache/hadoop/hbase/TestCompatibilitySingletonFactory
       2: invokestatic  #24                 // Method org/apache/hadoop/hbase/HBaseClassTestRule.forClass:(Ljava/lang/Class;)Lorg/apache/hadoop/hbase/HBaseClassTestRule;
       5: putstatic     #25                 // Field CLASS_RULE:Lorg/apache/hadoop/hbase/HBaseClassTestRule;
       8: new           #26                 // class java/util/Random
      11: dup
      12: invokespecial #27                 // Method java/util/Random."<init>":()V
      15: putstatic     #1                  // Field RANDOM:Ljava/util/Random;
      18: return
}
