Compiled from "TestHRegion.java"
class org.apache.hadoop.hbase.regionserver.TestHRegion$14 implements java.util.concurrent.Callable<java.lang.Void> {
  final byte[] val$b;

  final java.util.concurrent.CountDownLatch val$obtainedRowLock;

  final org.apache.hadoop.hbase.regionserver.TestHRegion this$0;

  org.apache.hadoop.hbase.regionserver.TestHRegion$14(org.apache.hadoop.hbase.regionserver.TestHRegion, byte[], java.util.concurrent.CountDownLatch);
    Code:
       0: aload_0
       1: aload_1
       2: putfield      #1                  // Field this$0:Lorg/apache/hadoop/hbase/regionserver/TestHRegion;
       5: aload_0
       6: aload_2
       7: putfield      #2                  // Field val$b:[B
      10: aload_0
      11: aload_3
      12: putfield      #3                  // Field val$obtainedRowLock:Ljava/util/concurrent/CountDownLatch;
      15: aload_0
      16: invokespecial #4                  // Method java/lang/Object."<init>":()V
      19: return

  public java.lang.Void call() throws java.lang.Exception;
    Code:
       0: invokestatic  #5                  // Method org/apache/hadoop/hbase/regionserver/TestHRegion.access$100:()Lorg/slf4j/Logger;
       3: ldc           #6                  // String Acquiring row lock
       5: invokeinterface #7,  2            // InterfaceMethod org/slf4j/Logger.info:(Ljava/lang/String;)V
      10: aload_0
      11: getfield      #1                  // Field this$0:Lorg/apache/hadoop/hbase/regionserver/TestHRegion;
      14: getfield      #8                  // Field org/apache/hadoop/hbase/regionserver/TestHRegion.region:Lorg/apache/hadoop/hbase/regionserver/HRegion;
      17: aload_0
      18: getfield      #2                  // Field val$b:[B
      21: invokevirtual #9                  // Method org/apache/hadoop/hbase/regionserver/HRegion.getRowLock:([B)Lorg/apache/hadoop/hbase/regionserver/Region$RowLock;
      24: astore_1
      25: aload_0
      26: getfield      #3                  // Field val$obtainedRowLock:Ljava/util/concurrent/CountDownLatch;
      29: invokevirtual #10                 // Method java/util/concurrent/CountDownLatch.countDown:()V
      32: invokestatic  #5                  // Method org/apache/hadoop/hbase/regionserver/TestHRegion.access$100:()Lorg/slf4j/Logger;
      35: ldc           #11                 // String Waiting for 5 seconds before releasing lock
      37: invokeinterface #7,  2            // InterfaceMethod org/slf4j/Logger.info:(Ljava/lang/String;)V
      42: ldc2_w        #12                 // long 5000l
      45: invokestatic  #14                 // Method org/apache/hadoop/hbase/util/Threads.sleep:(J)V
      48: invokestatic  #5                  // Method org/apache/hadoop/hbase/regionserver/TestHRegion.access$100:()Lorg/slf4j/Logger;
      51: ldc           #15                 // String Releasing row lock
      53: invokeinterface #7,  2            // InterfaceMethod org/slf4j/Logger.info:(Ljava/lang/String;)V
      58: aload_1
      59: invokeinterface #16,  1           // InterfaceMethod org/apache/hadoop/hbase/regionserver/Region$RowLock.release:()V
      64: aconst_null
      65: areturn

  public java.lang.Object call() throws java.lang.Exception;
    Code:
       0: aload_0
       1: invokevirtual #17                 // Method call:()Ljava/lang/Void;
       4: areturn
}
