Compiled from "TestAvoidCellReferencesIntoShippedBlocks.java"
class org.apache.hadoop.hbase.client.TestAvoidCellReferencesIntoShippedBlocks$1 extends java.lang.Thread {
  final org.apache.hadoop.hbase.io.hfile.BlockCache val$cache;

  final org.apache.hadoop.hbase.client.Table val$table;

  final org.apache.hadoop.hbase.client.TestAvoidCellReferencesIntoShippedBlocks this$0;

  org.apache.hadoop.hbase.client.TestAvoidCellReferencesIntoShippedBlocks$1(org.apache.hadoop.hbase.client.TestAvoidCellReferencesIntoShippedBlocks, org.apache.hadoop.hbase.io.hfile.BlockCache, org.apache.hadoop.hbase.client.Table);
    Code:
       0: aload_0
       1: aload_1
       2: putfield      #1                  // Field this$0:Lorg/apache/hadoop/hbase/client/TestAvoidCellReferencesIntoShippedBlocks;
       5: aload_0
       6: aload_2
       7: putfield      #2                  // Field val$cache:Lorg/apache/hadoop/hbase/io/hfile/BlockCache;
      10: aload_0
      11: aload_3
      12: putfield      #3                  // Field val$table:Lorg/apache/hadoop/hbase/client/Table;
      15: aload_0
      16: invokespecial #4                  // Method java/lang/Thread."<init>":()V
      19: return

  public void run();
    Code:
       0: new           #5                  // class java/util/ArrayList
       3: dup
       4: invokespecial #6                  // Method java/util/ArrayList."<init>":()V
       7: astore_1
       8: aload_0
       9: getfield      #2                  // Field val$cache:Lorg/apache/hadoop/hbase/io/hfile/BlockCache;
      12: invokeinterface #7,  1            // InterfaceMethod org/apache/hadoop/hbase/io/hfile/BlockCache.iterator:()Ljava/util/Iterator;
      17: astore_2
      18: aload_2
      19: invokeinterface #8,  1            // InterfaceMethod java/util/Iterator.hasNext:()Z
      24: ifeq          82
      27: aload_2
      28: invokeinterface #9,  1            // InterfaceMethod java/util/Iterator.next:()Ljava/lang/Object;
      33: checkcast     #10                 // class org/apache/hadoop/hbase/io/hfile/CachedBlock
      36: astore_3
      37: new           #11                 // class org/apache/hadoop/hbase/io/hfile/BlockCacheKey
      40: dup
      41: aload_3
      42: invokeinterface #12,  1           // InterfaceMethod org/apache/hadoop/hbase/io/hfile/CachedBlock.getFilename:()Ljava/lang/String;
      47: aload_3
      48: invokeinterface #13,  1           // InterfaceMethod org/apache/hadoop/hbase/io/hfile/CachedBlock.getOffset:()J
      53: invokespecial #14                 // Method org/apache/hadoop/hbase/io/hfile/BlockCacheKey."<init>":(Ljava/lang/String;J)V
      56: astore        4
      58: aload_1
      59: aload         4
      61: invokeinterface #15,  2           // InterfaceMethod java/util/List.add:(Ljava/lang/Object;)Z
      66: pop
      67: aload_0
      68: getfield      #2                  // Field val$cache:Lorg/apache/hadoop/hbase/io/hfile/BlockCache;
      71: aload         4
      73: invokeinterface #16,  2           // InterfaceMethod org/apache/hadoop/hbase/io/hfile/BlockCache.evictBlock:(Lorg/apache/hadoop/hbase/io/hfile/BlockCacheKey;)Z
      78: pop
      79: goto          18
      82: lconst_1
      83: invokestatic  #17                 // Method java/lang/Thread.sleep:(J)V
      86: goto          90
      89: astore_3
      90: aload_0
      91: getfield      #2                  // Field val$cache:Lorg/apache/hadoop/hbase/io/hfile/BlockCache;
      94: invokeinterface #7,  1            // InterfaceMethod org/apache/hadoop/hbase/io/hfile/BlockCache.iterator:()Ljava/util/Iterator;
      99: astore_2
     100: iconst_0
     101: istore_3
     102: aload_2
     103: invokeinterface #8,  1            // InterfaceMethod java/util/Iterator.hasNext:()Z
     108: ifeq          124
     111: aload_2
     112: invokeinterface #9,  1            // InterfaceMethod java/util/Iterator.next:()Ljava/lang/Object;
     117: pop
     118: iinc          3, 1
     121: goto          102
     124: ldc           #19                 // String One block should be there
     126: lconst_1
     127: iload_3
     128: i2l
     129: invokestatic  #20                 // Method org/junit/Assert.assertEquals:(Ljava/lang/String;JJ)V
     132: new           #21                 // class org/apache/hadoop/hbase/client/Scan
     135: dup
     136: invokespecial #22                 // Method org/apache/hadoop/hbase/client/Scan."<init>":()V
     139: astore        4
     141: aload         4
     143: invokestatic  #23                 // Method org/apache/hadoop/hbase/client/TestAvoidCellReferencesIntoShippedBlocks.access$500:()[B
     146: invokevirtual #24                 // Method org/apache/hadoop/hbase/client/Scan.withStartRow:([B)Lorg/apache/hadoop/hbase/client/Scan;
     149: pop
     150: aload         4
     152: invokestatic  #25                 // Method org/apache/hadoop/hbase/client/TestAvoidCellReferencesIntoShippedBlocks.access$000:()[B
     155: invokevirtual #26                 // Method org/apache/hadoop/hbase/client/Scan.withStopRow:([B)Lorg/apache/hadoop/hbase/client/Scan;
     158: pop
     159: aload         4
     161: iconst_1
     162: invokevirtual #27                 // Method org/apache/hadoop/hbase/client/Scan.setCaching:(I)Lorg/apache/hadoop/hbase/client/Scan;
     165: pop
     166: aload_0
     167: getfield      #3                  // Field val$table:Lorg/apache/hadoop/hbase/client/Table;
     170: aload         4
     172: invokeinterface #28,  2           // InterfaceMethod org/apache/hadoop/hbase/client/Table.getScanner:(Lorg/apache/hadoop/hbase/client/Scan;)Lorg/apache/hadoop/hbase/client/ResultScanner;
     177: astore        5
     179: aload         5
     181: invokestatic  #29                 // Method org/apache/hbase/thirdparty/com/google/common/collect/Iterables.size:(Ljava/lang/Iterable;)I
     184: istore        6
     186: ldc           #30                 // String Count the rows
     188: ldc2_w        #31                 // long 2l
     191: iload         6
     193: i2l
     194: invokestatic  #20                 // Method org/junit/Assert.assertEquals:(Ljava/lang/String;JJ)V
     197: iconst_0
     198: istore        7
     200: new           #5                  // class java/util/ArrayList
     203: dup
     204: invokespecial #6                  // Method java/util/ArrayList."<init>":()V
     207: astore        8
     209: iconst_0
     210: istore        7
     212: aload         8
     214: invokeinterface #33,  1           // InterfaceMethod java/util/List.clear:()V
     219: aload_0
     220: getfield      #2                  // Field val$cache:Lorg/apache/hadoop/hbase/io/hfile/BlockCache;
     223: invokeinterface #7,  1            // InterfaceMethod org/apache/hadoop/hbase/io/hfile/BlockCache.iterator:()Ljava/util/Iterator;
     228: astore_2
     229: aload_2
     230: invokeinterface #8,  1            // InterfaceMethod java/util/Iterator.hasNext:()Z
     235: ifeq          285
     238: aload_2
     239: invokeinterface #9,  1            // InterfaceMethod java/util/Iterator.next:()Ljava/lang/Object;
     244: checkcast     #10                 // class org/apache/hadoop/hbase/io/hfile/CachedBlock
     247: astore        9
     249: new           #11                 // class org/apache/hadoop/hbase/io/hfile/BlockCacheKey
     252: dup
     253: aload         9
     255: invokeinterface #12,  1           // InterfaceMethod org/apache/hadoop/hbase/io/hfile/CachedBlock.getFilename:()Ljava/lang/String;
     260: aload         9
     262: invokeinterface #13,  1           // InterfaceMethod org/apache/hadoop/hbase/io/hfile/CachedBlock.getOffset:()J
     267: invokespecial #14                 // Method org/apache/hadoop/hbase/io/hfile/BlockCacheKey."<init>":(Ljava/lang/String;J)V
     270: astore        10
     272: aload         8
     274: aload         10
     276: invokeinterface #15,  2           // InterfaceMethod java/util/List.add:(Ljava/lang/Object;)Z
     281: pop
     282: goto          229
     285: aload_1
     286: invokeinterface #34,  1           // InterfaceMethod java/util/List.iterator:()Ljava/util/Iterator;
     291: astore        9
     293: aload         9
     295: invokeinterface #8,  1            // InterfaceMethod java/util/Iterator.hasNext:()Z
     300: ifeq          333
     303: aload         9
     305: invokeinterface #9,  1            // InterfaceMethod java/util/Iterator.next:()Ljava/lang/Object;
     310: checkcast     #11                 // class org/apache/hadoop/hbase/io/hfile/BlockCacheKey
     313: astore        10
     315: aload         8
     317: aload         10
     319: invokeinterface #35,  2           // InterfaceMethod java/util/List.contains:(Ljava/lang/Object;)Z
     324: ifeq          330
     327: iinc          7, 1
     330: goto          293
     333: iload         7
     335: bipush        6
     337: if_icmpne     209
     340: goto          343
     343: aload_0
     344: getfield      #1                  // Field this$0:Lorg/apache/hadoop/hbase/client/TestAvoidCellReferencesIntoShippedBlocks;
     347: invokestatic  #36                 // Method org/apache/hadoop/hbase/client/TestAvoidCellReferencesIntoShippedBlocks.access$600:(Lorg/apache/hadoop/hbase/client/TestAvoidCellReferencesIntoShippedBlocks;)Ljava/util/concurrent/CountDownLatch;
     350: invokevirtual #37                 // Method java/util/concurrent/CountDownLatch.countDown:()V
     353: goto          358
     356: astore        6
     358: return
    Exception table:
       from    to  target type
          82    86    89   Class java/lang/InterruptedException
         166   353   356   Class java/io/IOException
}
