Compiled from "TestUser.java"
class org.apache.hadoop.hbase.security.TestUser$3 implements java.security.PrivilegedExceptionAction<java.lang.Object> {
  final org.apache.hadoop.hbase.security.User val$user;

  final java.security.PrivilegedExceptionAction val$action;

  final org.apache.hadoop.hbase.security.TestUser this$0;

  org.apache.hadoop.hbase.security.TestUser$3(org.apache.hadoop.hbase.security.TestUser, org.apache.hadoop.hbase.security.User, java.security.PrivilegedExceptionAction);
    Code:
       0: aload_0
       1: aload_1
       2: putfield      #1                  // Field this$0:Lorg/apache/hadoop/hbase/security/TestUser;
       5: aload_0
       6: aload_2
       7: putfield      #2                  // Field val$user:Lorg/apache/hadoop/hbase/security/User;
      10: aload_0
      11: aload_3
      12: putfield      #3                  // Field val$action:Ljava/security/PrivilegedExceptionAction;
      15: aload_0
      16: invokespecial #4                  // Method java/lang/Object."<init>":()V
      19: return

  public java.lang.Object run() throws java.io.IOException, java.lang.InterruptedException;
    Code:
       0: aload_0
       1: getfield      #2                  // Field val$user:Lorg/apache/hadoop/hbase/security/User;
       4: aload_0
       5: getfield      #3                  // Field val$action:Ljava/security/PrivilegedExceptionAction;
       8: invokevirtual #5                  // Method org/apache/hadoop/hbase/security/User.runAs:(Ljava/security/PrivilegedExceptionAction;)Ljava/lang/Object;
      11: checkcast     #6                  // class java/lang/String
      14: astore_1
      15: ldc           #7                  // String Nest name should match nested user
      17: ldc           #8                  // String testuser
      19: aload_1
      20: invokestatic  #9                  // Method org/junit/Assert.assertEquals:(Ljava/lang/String;Ljava/lang/Object;Ljava/lang/Object;)V
      23: ldc           #10                 // String Current name should match current user
      25: ldc           #11                 // String testuser2
      27: invokestatic  #12                 // Method org/apache/hadoop/hbase/security/User.getCurrent:()Lorg/apache/hadoop/hbase/security/User;
      30: invokevirtual #13                 // Method org/apache/hadoop/hbase/security/User.getName:()Ljava/lang/String;
      33: invokestatic  #9                  // Method org/junit/Assert.assertEquals:(Ljava/lang/String;Ljava/lang/Object;Ljava/lang/Object;)V
      36: aconst_null
      37: areturn
}
