Compiled from "TestHttpServer.java"
public class org.apache.hadoop.hbase.http.TestHttpServer$MyGroupsProvider extends org.apache.hadoop.security.ShellBasedUnixGroupsMapping {
  static java.util.Map<java.lang.String, java.util.List<java.lang.String>> mapping;

  public org.apache.hadoop.hbase.http.TestHttpServer$MyGroupsProvider();
    Code:
       0: aload_0
       1: invokespecial #1                  // Method org/apache/hadoop/security/ShellBasedUnixGroupsMapping."<init>":()V
       4: return

  static void clearMapping();
    Code:
       0: getstatic     #2                  // Field mapping:Ljava/util/Map;
       3: invokeinterface #3,  1            // InterfaceMethod java/util/Map.clear:()V
       8: return

  public java.util.List<java.lang.String> getGroups(java.lang.String);
    Code:
       0: getstatic     #2                  // Field mapping:Ljava/util/Map;
       3: aload_1
       4: invokeinterface #4,  2            // InterfaceMethod java/util/Map.get:(Ljava/lang/Object;)Ljava/lang/Object;
       9: checkcast     #5                  // class java/util/List
      12: areturn

  static {};
    Code:
       0: new           #6                  // class java/util/HashMap
       3: dup
       4: invokespecial #7                  // Method java/util/HashMap."<init>":()V
       7: putstatic     #2                  // Field mapping:Ljava/util/Map;
      10: return
}
