Compiled from "TestMetaTableMetrics.java"
class org.apache.hadoop.hbase.coprocessor.TestMetaTableMetrics$PutThread extends java.lang.Thread {
  int start;

  int end;

  final org.apache.hadoop.hbase.coprocessor.TestMetaTableMetrics this$0;

  public org.apache.hadoop.hbase.coprocessor.TestMetaTableMetrics$PutThread(org.apache.hadoop.hbase.coprocessor.TestMetaTableMetrics, int, int);
    Code:
       0: aload_0
       1: aload_1
       2: putfield      #1                  // Field this$0:Lorg/apache/hadoop/hbase/coprocessor/TestMetaTableMetrics;
       5: aload_0
       6: invokespecial #2                  // Method java/lang/Thread."<init>":()V
       9: aload_0
      10: iload_2
      11: putfield      #3                  // Field start:I
      14: aload_0
      15: iload_3
      16: putfield      #4                  // Field end:I
      19: return

  public void run();
    Code:
       0: invokestatic  #5                  // Method org/apache/hadoop/hbase/coprocessor/TestMetaTableMetrics.access$000:()Lorg/apache/hadoop/hbase/HBaseTestingUtility;
       3: invokevirtual #6                  // Method org/apache/hadoop/hbase/HBaseTestingUtility.getConnection:()Lorg/apache/hadoop/hbase/client/Connection;
       6: aload_0
       7: getfield      #1                  // Field this$0:Lorg/apache/hadoop/hbase/coprocessor/TestMetaTableMetrics;
      10: getfield      #7                  // Field org/apache/hadoop/hbase/coprocessor/TestMetaTableMetrics.tablename:[B
      13: invokestatic  #8                  // Method org/apache/hadoop/hbase/TableName.valueOf:([B)Lorg/apache/hadoop/hbase/TableName;
      16: invokeinterface #9,  2            // InterfaceMethod org/apache/hadoop/hbase/client/Connection.getTable:(Lorg/apache/hadoop/hbase/TableName;)Lorg/apache/hadoop/hbase/client/Table;
      21: astore_1
      22: aconst_null
      23: astore_2
      24: aload_0
      25: getfield      #3                  // Field start:I
      28: istore_3
      29: iload_3
      30: aload_0
      31: getfield      #4                  // Field end:I
      34: if_icmpgt     128
      37: new           #10                 // class org/apache/hadoop/hbase/client/Put
      40: dup
      41: ldc           #11                 // String tableName,rowKey%d,region%d
      43: iconst_2
      44: anewarray     #12                 // class java/lang/Object
      47: dup
      48: iconst_0
      49: iload_3
      50: invokestatic  #13                 // Method java/lang/Integer.valueOf:(I)Ljava/lang/Integer;
      53: aastore
      54: dup
      55: iconst_1
      56: iload_3
      57: invokestatic  #13                 // Method java/lang/Integer.valueOf:(I)Ljava/lang/Integer;
      60: aastore
      61: invokestatic  #14                 // Method java/lang/String.format:(Ljava/lang/String;[Ljava/lang/Object;)Ljava/lang/String;
      64: invokestatic  #15                 // Method org/apache/hadoop/hbase/util/Bytes.toBytes:(Ljava/lang/String;)[B
      67: invokespecial #16                 // Method org/apache/hadoop/hbase/client/Put."<init>":([B)V
      70: astore        4
      72: aload         4
      74: aload_0
      75: getfield      #1                  // Field this$0:Lorg/apache/hadoop/hbase/coprocessor/TestMetaTableMetrics;
      78: getfield      #17                 // Field org/apache/hadoop/hbase/coprocessor/TestMetaTableMetrics.cf:[B
      81: aload_0
      82: getfield      #1                  // Field this$0:Lorg/apache/hadoop/hbase/coprocessor/TestMetaTableMetrics;
      85: getfield      #18                 // Field org/apache/hadoop/hbase/coprocessor/TestMetaTableMetrics.col:[B
      88: new           #19                 // class java/lang/StringBuilder
      91: dup
      92: invokespecial #20                 // Method java/lang/StringBuilder."<init>":()V
      95: ldc           #21                 // String Value
      97: invokevirtual #22                 // Method java/lang/StringBuilder.append:(Ljava/lang/String;)Ljava/lang/StringBuilder;
     100: iload_3
     101: invokevirtual #23                 // Method java/lang/StringBuilder.append:(I)Ljava/lang/StringBuilder;
     104: invokevirtual #24                 // Method java/lang/StringBuilder.toString:()Ljava/lang/String;
     107: invokestatic  #15                 // Method org/apache/hadoop/hbase/util/Bytes.toBytes:(Ljava/lang/String;)[B
     110: invokevirtual #25                 // Method org/apache/hadoop/hbase/client/Put.addColumn:([B[B[B)Lorg/apache/hadoop/hbase/client/Put;
     113: pop
     114: aload_1
     115: aload         4
     117: invokeinterface #26,  2           // InterfaceMethod org/apache/hadoop/hbase/client/Table.put:(Lorg/apache/hadoop/hbase/client/Put;)V
     122: iinc          3, 1
     125: goto          29
     128: aload_1
     129: ifnull        207
     132: aload_2
     133: ifnull        154
     136: aload_1
     137: invokeinterface #27,  1           // InterfaceMethod org/apache/hadoop/hbase/client/Table.close:()V
     142: goto          207
     145: astore_3
     146: aload_2
     147: aload_3
     148: invokevirtual #29                 // Method java/lang/Throwable.addSuppressed:(Ljava/lang/Throwable;)V
     151: goto          207
     154: aload_1
     155: invokeinterface #27,  1           // InterfaceMethod org/apache/hadoop/hbase/client/Table.close:()V
     160: goto          207
     163: astore_3
     164: aload_3
     165: astore_2
     166: aload_3
     167: athrow
     168: astore        5
     170: aload_1
     171: ifnull        204
     174: aload_2
     175: ifnull        198
     178: aload_1
     179: invokeinterface #27,  1           // InterfaceMethod org/apache/hadoop/hbase/client/Table.close:()V
     184: goto          204
     187: astore        6
     189: aload_2
     190: aload         6
     192: invokevirtual #29                 // Method java/lang/Throwable.addSuppressed:(Ljava/lang/Throwable;)V
     195: goto          204
     198: aload_1
     199: invokeinterface #27,  1           // InterfaceMethod org/apache/hadoop/hbase/client/Table.close:()V
     204: aload         5
     206: athrow
     207: goto          241
     210: astore_1
     211: invokestatic  #31                 // Method org/apache/hadoop/hbase/coprocessor/TestMetaTableMetrics.access$100:()Lorg/slf4j/Logger;
     214: new           #19                 // class java/lang/StringBuilder
     217: dup
     218: invokespecial #20                 // Method java/lang/StringBuilder."<init>":()V
     221: ldc           #32                 // String Caught IOException while PutThread operation:
     223: invokevirtual #22                 // Method java/lang/StringBuilder.append:(Ljava/lang/String;)Ljava/lang/StringBuilder;
     226: aload_1
     227: invokevirtual #33                 // Method java/io/IOException.getMessage:()Ljava/lang/String;
     230: invokevirtual #22                 // Method java/lang/StringBuilder.append:(Ljava/lang/String;)Ljava/lang/StringBuilder;
     233: invokevirtual #24                 // Method java/lang/StringBuilder.toString:()Ljava/lang/String;
     236: invokeinterface #34,  2           // InterfaceMethod org/slf4j/Logger.info:(Ljava/lang/String;)V
     241: return
    Exception table:
       from    to  target type
         136   142   145   Class java/lang/Throwable
          24   128   163   Class java/lang/Throwable
          24   128   168   any
         178   184   187   Class java/lang/Throwable
         163   170   168   any
           0   207   210   Class java/io/IOException
}
