Compiled from "TestMasterProcedureWalLease.java"
public class org.apache.hadoop.hbase.master.procedure.TestMasterProcedureWalLease {
  public static final org.apache.hadoop.hbase.HBaseClassTestRule CLASS_RULE;

  public org.junit.rules.TestName name;

  protected static final org.apache.hadoop.hbase.HBaseTestingUtility UTIL;

  public org.apache.hadoop.hbase.master.procedure.TestMasterProcedureWalLease();
    Code:
       0: aload_0
       1: invokespecial #2                  // Method java/lang/Object."<init>":()V
       4: aload_0
       5: new           #3                  // class org/junit/rules/TestName
       8: dup
       9: invokespecial #4                  // Method org/junit/rules/TestName."<init>":()V
      12: putfield      #5                  // Field name:Lorg/junit/rules/TestName;
      15: return

  public void setup() throws java.lang.Exception;
    Code:
       0: getstatic     #12                 // Field UTIL:Lorg/apache/hadoop/hbase/HBaseTestingUtility;
       3: invokevirtual #13                 // Method org/apache/hadoop/hbase/HBaseTestingUtility.getConfiguration:()Lorg/apache/hadoop/conf/Configuration;
       6: invokestatic  #14                 // Method setupConf:(Lorg/apache/hadoop/conf/Configuration;)V
       9: invokestatic  #15                 // Method org/apache/hadoop/hbase/StartMiniClusterOption.builder:()Lorg/apache/hadoop/hbase/StartMiniClusterOption$Builder;
      12: iconst_2
      13: invokevirtual #16                 // Method org/apache/hadoop/hbase/StartMiniClusterOption$Builder.numMasters:(I)Lorg/apache/hadoop/hbase/StartMiniClusterOption$Builder;
      16: iconst_3
      17: invokevirtual #17                 // Method org/apache/hadoop/hbase/StartMiniClusterOption$Builder.numRegionServers:(I)Lorg/apache/hadoop/hbase/StartMiniClusterOption$Builder;
      20: iconst_3
      21: invokevirtual #18                 // Method org/apache/hadoop/hbase/StartMiniClusterOption$Builder.numDataNodes:(I)Lorg/apache/hadoop/hbase/StartMiniClusterOption$Builder;
      24: invokevirtual #19                 // Method org/apache/hadoop/hbase/StartMiniClusterOption$Builder.build:()Lorg/apache/hadoop/hbase/StartMiniClusterOption;
      27: astore_1
      28: getstatic     #12                 // Field UTIL:Lorg/apache/hadoop/hbase/HBaseTestingUtility;
      31: aload_1
      32: invokevirtual #20                 // Method org/apache/hadoop/hbase/HBaseTestingUtility.startMiniCluster:(Lorg/apache/hadoop/hbase/StartMiniClusterOption;)Lorg/apache/hadoop/hbase/MiniHBaseCluster;
      35: pop
      36: return

  public void tearDown() throws java.lang.Exception;
    Code:
       0: getstatic     #12                 // Field UTIL:Lorg/apache/hadoop/hbase/HBaseTestingUtility;
       3: invokevirtual #21                 // Method org/apache/hadoop/hbase/HBaseTestingUtility.shutdownMiniCluster:()V
       6: goto          21
       9: astore_1
      10: getstatic     #1                  // Field LOG:Lorg/slf4j/Logger;
      13: ldc           #23                 // String failure shutting down cluster
      15: aload_1
      16: invokeinterface #24,  3           // InterfaceMethod org/slf4j/Logger.warn:(Ljava/lang/String;Ljava/lang/Throwable;)V
      21: return
    Exception table:
       from    to  target type
           0     6     9   Class java/lang/Exception

  public void testWalRecoverLease() throws java.lang.Exception;
    Code:
       0: aload_0
       1: invokespecial #25                 // Method getMasterProcedureExecutor:()Lorg/apache/hadoop/hbase/procedure2/ProcedureExecutor;
       4: invokevirtual #26                 // Method org/apache/hadoop/hbase/procedure2/ProcedureExecutor.getStore:()Lorg/apache/hadoop/hbase/procedure2/store/ProcedureStore;
       7: astore_1
       8: ldc           #27                 // String expected WALStore for this test
      10: aload_1
      11: instanceof    #6                  // class org/apache/hadoop/hbase/procedure2/store/wal/WALProcedureStore
      14: invokestatic  #28                 // Method org/junit/Assert.assertTrue:(Ljava/lang/String;Z)V
      17: getstatic     #12                 // Field UTIL:Lorg/apache/hadoop/hbase/HBaseTestingUtility;
      20: invokevirtual #29                 // Method org/apache/hadoop/hbase/HBaseTestingUtility.getHBaseCluster:()Lorg/apache/hadoop/hbase/MiniHBaseCluster;
      23: invokevirtual #30                 // Method org/apache/hadoop/hbase/MiniHBaseCluster.getMaster:()Lorg/apache/hadoop/hbase/master/HMaster;
      26: astore_2
      27: new           #31                 // class java/util/concurrent/CountDownLatch
      30: dup
      31: iconst_1
      32: invokespecial #32                 // Method java/util/concurrent/CountDownLatch."<init>":(I)V
      35: astore_3
      36: aload_1
      37: new           #33                 // class org/apache/hadoop/hbase/master/procedure/TestMasterProcedureWalLease$1
      40: dup
      41: aload_0
      42: aload_3
      43: invokespecial #34                 // Method org/apache/hadoop/hbase/master/procedure/TestMasterProcedureWalLease$1."<init>":(Lorg/apache/hadoop/hbase/master/procedure/TestMasterProcedureWalLease;Ljava/util/concurrent/CountDownLatch;)V
      46: invokeinterface #35,  2           // InterfaceMethod org/apache/hadoop/hbase/procedure2/store/ProcedureStore.registerListener:(Lorg/apache/hadoop/hbase/procedure2/store/ProcedureStore$ProcedureStoreListener;)V
      51: ldc           #36                 // class org/apache/hadoop/hbase/master/HMaster
      53: invokestatic  #37                 // Method org/mockito/Mockito.mock:(Ljava/lang/Class;)Ljava/lang/Object;
      56: checkcast     #36                 // class org/apache/hadoop/hbase/master/HMaster
      59: astore        4
      61: aload_2
      62: invokevirtual #38                 // Method org/apache/hadoop/hbase/master/HMaster.getConfiguration:()Lorg/apache/hadoop/conf/Configuration;
      65: invokestatic  #39                 // Method org/mockito/Mockito.doReturn:(Ljava/lang/Object;)Lorg/mockito/stubbing/Stubber;
      68: aload         4
      70: invokeinterface #40,  2           // InterfaceMethod org/mockito/stubbing/Stubber.when:(Ljava/lang/Object;)Ljava/lang/Object;
      75: checkcast     #36                 // class org/apache/hadoop/hbase/master/HMaster
      78: invokevirtual #38                 // Method org/apache/hadoop/hbase/master/HMaster.getConfiguration:()Lorg/apache/hadoop/conf/Configuration;
      81: pop
      82: iconst_1
      83: invokestatic  #41                 // Method java/lang/Boolean.valueOf:(Z)Ljava/lang/Boolean;
      86: invokestatic  #39                 // Method org/mockito/Mockito.doReturn:(Ljava/lang/Object;)Lorg/mockito/stubbing/Stubber;
      89: aload         4
      91: invokeinterface #40,  2           // InterfaceMethod org/mockito/stubbing/Stubber.when:(Ljava/lang/Object;)Ljava/lang/Object;
      96: checkcast     #36                 // class org/apache/hadoop/hbase/master/HMaster
      99: invokevirtual #42                 // Method org/apache/hadoop/hbase/master/HMaster.isActiveMaster:()Z
     102: pop
     103: new           #6                  // class org/apache/hadoop/hbase/procedure2/store/wal/WALProcedureStore
     106: dup
     107: aload_2
     108: invokevirtual #38                 // Method org/apache/hadoop/hbase/master/HMaster.getConfiguration:()Lorg/apache/hadoop/conf/Configuration;
     111: aload_1
     112: checkcast     #6                  // class org/apache/hadoop/hbase/procedure2/store/wal/WALProcedureStore
     115: invokevirtual #43                 // Method org/apache/hadoop/hbase/procedure2/store/wal/WALProcedureStore.getWALDir:()Lorg/apache/hadoop/fs/Path;
     118: aconst_null
     119: new           #44                 // class org/apache/hadoop/hbase/master/procedure/MasterProcedureEnv$WALStoreLeaseRecovery
     122: dup
     123: aload         4
     125: invokespecial #45                 // Method org/apache/hadoop/hbase/master/procedure/MasterProcedureEnv$WALStoreLeaseRecovery."<init>":(Lorg/apache/hadoop/hbase/master/MasterServices;)V
     128: invokespecial #46                 // Method org/apache/hadoop/hbase/procedure2/store/wal/WALProcedureStore."<init>":(Lorg/apache/hadoop/conf/Configuration;Lorg/apache/hadoop/fs/Path;Lorg/apache/hadoop/fs/Path;Lorg/apache/hadoop/hbase/procedure2/store/wal/WALProcedureStore$LeaseRecovery;)V
     131: astore        5
     133: new           #31                 // class java/util/concurrent/CountDownLatch
     136: dup
     137: iconst_1
     138: invokespecial #32                 // Method java/util/concurrent/CountDownLatch."<init>":(I)V
     141: astore        6
     143: aload         5
     145: new           #47                 // class org/apache/hadoop/hbase/master/procedure/TestMasterProcedureWalLease$2
     148: dup
     149: aload_0
     150: aload         6
     152: aload         5
     154: invokespecial #48                 // Method org/apache/hadoop/hbase/master/procedure/TestMasterProcedureWalLease$2."<init>":(Lorg/apache/hadoop/hbase/master/procedure/TestMasterProcedureWalLease;Ljava/util/concurrent/CountDownLatch;Lorg/apache/hadoop/hbase/procedure2/store/wal/WALProcedureStore;)V
     157: invokevirtual #49                 // Method org/apache/hadoop/hbase/procedure2/store/wal/WALProcedureStore.registerListener:(Lorg/apache/hadoop/hbase/procedure2/store/ProcedureStore$ProcedureStoreListener;)V
     160: aload         5
     162: iconst_1
     163: invokevirtual #50                 // Method org/apache/hadoop/hbase/procedure2/store/wal/WALProcedureStore.start:(I)V
     166: aload         5
     168: invokevirtual #51                 // Method org/apache/hadoop/hbase/procedure2/store/wal/WALProcedureStore.recoverLease:()V
     171: aload_0
     172: getfield      #5                  // Field name:Lorg/junit/rules/TestName;
     175: invokevirtual #52                 // Method org/junit/rules/TestName.getMethodName:()Ljava/lang/String;
     178: invokestatic  #53                 // Method org/apache/hadoop/hbase/TableName.valueOf:(Ljava/lang/String;)Lorg/apache/hadoop/hbase/TableName;
     181: iconst_1
     182: anewarray     #54                 // class java/lang/String
     185: dup
     186: iconst_0
     187: ldc           #55                 // String f
     189: aastore
     190: invokestatic  #56                 // Method org/apache/hadoop/hbase/master/procedure/MasterProcedureTestingUtility.createHTD:(Lorg/apache/hadoop/hbase/TableName;[Ljava/lang/String;)Lorg/apache/hadoop/hbase/client/TableDescriptor;
     193: astore        7
     195: aload         7
     197: aconst_null
     198: checkcast     #57                 // class "[[B"
     201: invokestatic  #58                 // Method org/apache/hadoop/hbase/util/ModifyRegionUtils.createRegionInfos:(Lorg/apache/hadoop/hbase/client/TableDescriptor;[[B)[Lorg/apache/hadoop/hbase/client/RegionInfo;
     204: astore        8
     206: getstatic     #1                  // Field LOG:Lorg/slf4j/Logger;
     209: ldc           #59                 // String submit proc
     211: invokeinterface #60,  2           // InterfaceMethod org/slf4j/Logger.debug:(Ljava/lang/String;)V
     216: aload_0
     217: invokespecial #25                 // Method getMasterProcedureExecutor:()Lorg/apache/hadoop/hbase/procedure2/ProcedureExecutor;
     220: new           #61                 // class org/apache/hadoop/hbase/master/procedure/CreateTableProcedure
     223: dup
     224: aload_0
     225: invokespecial #25                 // Method getMasterProcedureExecutor:()Lorg/apache/hadoop/hbase/procedure2/ProcedureExecutor;
     228: invokevirtual #62                 // Method org/apache/hadoop/hbase/procedure2/ProcedureExecutor.getEnvironment:()Ljava/lang/Object;
     231: checkcast     #63                 // class org/apache/hadoop/hbase/master/procedure/MasterProcedureEnv
     234: aload         7
     236: aload         8
     238: invokespecial #64                 // Method org/apache/hadoop/hbase/master/procedure/CreateTableProcedure."<init>":(Lorg/apache/hadoop/hbase/master/procedure/MasterProcedureEnv;Lorg/apache/hadoop/hbase/client/TableDescriptor;[Lorg/apache/hadoop/hbase/client/RegionInfo;)V
     241: invokevirtual #65                 // Method org/apache/hadoop/hbase/procedure2/ProcedureExecutor.submitProcedure:(Lorg/apache/hadoop/hbase/procedure2/Procedure;)J
     244: pop2
     245: ldc           #66                 // String expected RuntimeException 'sync aborted'
     247: invokestatic  #67                 // Method org/junit/Assert.fail:(Ljava/lang/String;)V
     250: goto          286
     253: astore        9
     255: getstatic     #1                  // Field LOG:Lorg/slf4j/Logger;
     258: new           #69                 // class java/lang/StringBuilder
     261: dup
     262: invokespecial #70                 // Method java/lang/StringBuilder."<init>":()V
     265: ldc           #71                 // String got
     267: invokevirtual #72                 // Method java/lang/StringBuilder.append:(Ljava/lang/String;)Ljava/lang/StringBuilder;
     270: aload         9
     272: invokevirtual #73                 // Method java/lang/RuntimeException.getMessage:()Ljava/lang/String;
     275: invokevirtual #72                 // Method java/lang/StringBuilder.append:(Ljava/lang/String;)Ljava/lang/StringBuilder;
     278: invokevirtual #74                 // Method java/lang/StringBuilder.toString:()Ljava/lang/String;
     281: invokeinterface #75,  2           // InterfaceMethod org/slf4j/Logger.info:(Ljava/lang/String;)V
     286: getstatic     #1                  // Field LOG:Lorg/slf4j/Logger;
     289: ldc           #76                 // String wait master store abort
     291: invokeinterface #60,  2           // InterfaceMethod org/slf4j/Logger.debug:(Ljava/lang/String;)V
     296: aload_3
     297: invokevirtual #77                 // Method java/util/concurrent/CountDownLatch.await:()V
     300: getstatic     #1                  // Field LOG:Lorg/slf4j/Logger;
     303: ldc           #78                 // String wait backup master to startup
     305: invokeinterface #60,  2           // InterfaceMethod org/slf4j/Logger.debug:(Ljava/lang/String;)V
     310: getstatic     #12                 // Field UTIL:Lorg/apache/hadoop/hbase/HBaseTestingUtility;
     313: aload_2
     314: invokestatic  #79                 // Method org/apache/hadoop/hbase/master/procedure/MasterProcedureTestingUtility.waitBackupMaster:(Lorg/apache/hadoop/hbase/HBaseTestingUtility;Lorg/apache/hadoop/hbase/master/HMaster;)V
     317: iconst_1
     318: invokestatic  #41                 // Method java/lang/Boolean.valueOf:(Z)Ljava/lang/Boolean;
     321: aload_2
     322: invokevirtual #80                 // Method org/apache/hadoop/hbase/master/HMaster.isStopped:()Z
     325: invokestatic  #41                 // Method java/lang/Boolean.valueOf:(Z)Ljava/lang/Boolean;
     328: invokestatic  #81                 // Method org/junit/Assert.assertEquals:(Ljava/lang/Object;Ljava/lang/Object;)V
     331: getstatic     #1                  // Field LOG:Lorg/slf4j/Logger;
     334: ldc           #82                 // String wait the store to abort
     336: invokeinterface #60,  2           // InterfaceMethod org/slf4j/Logger.debug:(Ljava/lang/String;)V
     341: aload         5
     343: invokevirtual #83                 // Method org/apache/hadoop/hbase/procedure2/store/wal/WALProcedureStore.getStoreTracker:()Lorg/apache/hadoop/hbase/procedure2/store/ProcedureStoreTracker;
     346: lconst_1
     347: iconst_0
     348: invokevirtual #84                 // Method org/apache/hadoop/hbase/procedure2/store/ProcedureStoreTracker.setDeleted:(JZ)V
     351: aload         5
     353: lconst_1
     354: invokevirtual #85                 // Method org/apache/hadoop/hbase/procedure2/store/wal/WALProcedureStore.delete:(J)V
     357: ldc           #66                 // String expected RuntimeException 'sync aborted'
     359: invokestatic  #67                 // Method org/junit/Assert.fail:(Ljava/lang/String;)V
     362: goto          398
     365: astore        9
     367: getstatic     #1                  // Field LOG:Lorg/slf4j/Logger;
     370: new           #69                 // class java/lang/StringBuilder
     373: dup
     374: invokespecial #70                 // Method java/lang/StringBuilder."<init>":()V
     377: ldc           #71                 // String got
     379: invokevirtual #72                 // Method java/lang/StringBuilder.append:(Ljava/lang/String;)Ljava/lang/StringBuilder;
     382: aload         9
     384: invokevirtual #73                 // Method java/lang/RuntimeException.getMessage:()Ljava/lang/String;
     387: invokevirtual #72                 // Method java/lang/StringBuilder.append:(Ljava/lang/String;)Ljava/lang/StringBuilder;
     390: invokevirtual #74                 // Method java/lang/StringBuilder.toString:()Ljava/lang/String;
     393: invokeinterface #75,  2           // InterfaceMethod org/slf4j/Logger.info:(Ljava/lang/String;)V
     398: aload         6
     400: invokevirtual #77                 // Method java/util/concurrent/CountDownLatch.await:()V
     403: return
    Exception table:
       from    to  target type
         216   250   253   Class java/lang/RuntimeException
         351   362   365   Class java/lang/RuntimeException

  public void testWALfencingWithoutWALRolling() throws java.io.IOException;
    Code:
       0: aload_0
       1: iconst_0
       2: invokevirtual #86                 // Method testWALfencing:(Z)V
       5: return

  public void testWALfencingWithWALRolling() throws java.io.IOException;
    Code:
       0: aload_0
       1: iconst_1
       2: invokevirtual #86                 // Method testWALfencing:(Z)V
       5: return

  public void testWALfencing(boolean) throws java.io.IOException;
    Code:
       0: aload_0
       1: invokespecial #25                 // Method getMasterProcedureExecutor:()Lorg/apache/hadoop/hbase/procedure2/ProcedureExecutor;
       4: invokevirtual #26                 // Method org/apache/hadoop/hbase/procedure2/ProcedureExecutor.getStore:()Lorg/apache/hadoop/hbase/procedure2/store/ProcedureStore;
       7: astore_2
       8: ldc           #27                 // String expected WALStore for this test
      10: aload_2
      11: instanceof    #6                  // class org/apache/hadoop/hbase/procedure2/store/wal/WALProcedureStore
      14: invokestatic  #28                 // Method org/junit/Assert.assertTrue:(Ljava/lang/String;Z)V
      17: getstatic     #12                 // Field UTIL:Lorg/apache/hadoop/hbase/HBaseTestingUtility;
      20: invokevirtual #29                 // Method org/apache/hadoop/hbase/HBaseTestingUtility.getHBaseCluster:()Lorg/apache/hadoop/hbase/MiniHBaseCluster;
      23: invokevirtual #30                 // Method org/apache/hadoop/hbase/MiniHBaseCluster.getMaster:()Lorg/apache/hadoop/hbase/master/HMaster;
      26: astore_3
      27: aload_3
      28: invokevirtual #38                 // Method org/apache/hadoop/hbase/master/HMaster.getConfiguration:()Lorg/apache/hadoop/conf/Configuration;
      31: ldc           #87                 // String hbase.procedure.store.wal.roll.threshold
      33: lconst_1
      34: invokevirtual #88                 // Method org/apache/hadoop/conf/Configuration.setLong:(Ljava/lang/String;J)V
      37: ldc           #36                 // class org/apache/hadoop/hbase/master/HMaster
      39: invokestatic  #37                 // Method org/mockito/Mockito.mock:(Ljava/lang/Class;)Ljava/lang/Object;
      42: checkcast     #36                 // class org/apache/hadoop/hbase/master/HMaster
      45: astore        4
      47: aload_3
      48: invokevirtual #38                 // Method org/apache/hadoop/hbase/master/HMaster.getConfiguration:()Lorg/apache/hadoop/conf/Configuration;
      51: invokestatic  #39                 // Method org/mockito/Mockito.doReturn:(Ljava/lang/Object;)Lorg/mockito/stubbing/Stubber;
      54: aload         4
      56: invokeinterface #40,  2           // InterfaceMethod org/mockito/stubbing/Stubber.when:(Ljava/lang/Object;)Ljava/lang/Object;
      61: checkcast     #36                 // class org/apache/hadoop/hbase/master/HMaster
      64: invokevirtual #38                 // Method org/apache/hadoop/hbase/master/HMaster.getConfiguration:()Lorg/apache/hadoop/conf/Configuration;
      67: pop
      68: iconst_1
      69: invokestatic  #41                 // Method java/lang/Boolean.valueOf:(Z)Ljava/lang/Boolean;
      72: invokestatic  #39                 // Method org/mockito/Mockito.doReturn:(Ljava/lang/Object;)Lorg/mockito/stubbing/Stubber;
      75: aload         4
      77: invokeinterface #40,  2           // InterfaceMethod org/mockito/stubbing/Stubber.when:(Ljava/lang/Object;)Ljava/lang/Object;
      82: checkcast     #36                 // class org/apache/hadoop/hbase/master/HMaster
      85: invokevirtual #42                 // Method org/apache/hadoop/hbase/master/HMaster.isActiveMaster:()Z
      88: pop
      89: new           #6                  // class org/apache/hadoop/hbase/procedure2/store/wal/WALProcedureStore
      92: dup
      93: aload_3
      94: invokevirtual #38                 // Method org/apache/hadoop/hbase/master/HMaster.getConfiguration:()Lorg/apache/hadoop/conf/Configuration;
      97: aload_2
      98: checkcast     #6                  // class org/apache/hadoop/hbase/procedure2/store/wal/WALProcedureStore
     101: invokevirtual #43                 // Method org/apache/hadoop/hbase/procedure2/store/wal/WALProcedureStore.getWALDir:()Lorg/apache/hadoop/fs/Path;
     104: aconst_null
     105: new           #44                 // class org/apache/hadoop/hbase/master/procedure/MasterProcedureEnv$WALStoreLeaseRecovery
     108: dup
     109: aload         4
     111: invokespecial #45                 // Method org/apache/hadoop/hbase/master/procedure/MasterProcedureEnv$WALStoreLeaseRecovery."<init>":(Lorg/apache/hadoop/hbase/master/MasterServices;)V
     114: invokespecial #46                 // Method org/apache/hadoop/hbase/procedure2/store/wal/WALProcedureStore."<init>":(Lorg/apache/hadoop/conf/Configuration;Lorg/apache/hadoop/fs/Path;Lorg/apache/hadoop/fs/Path;Lorg/apache/hadoop/hbase/procedure2/store/wal/WALProcedureStore$LeaseRecovery;)V
     117: astore        5
     119: getstatic     #1                  // Field LOG:Lorg/slf4j/Logger;
     122: ldc           #89                 // String Starting new WALProcedureStore
     124: invokeinterface #75,  2           // InterfaceMethod org/slf4j/Logger.info:(Ljava/lang/String;)V
     129: aload         5
     131: iconst_1
     132: invokevirtual #50                 // Method org/apache/hadoop/hbase/procedure2/store/wal/WALProcedureStore.start:(I)V
     135: aload         5
     137: invokevirtual #51                 // Method org/apache/hadoop/hbase/procedure2/store/wal/WALProcedureStore.recoverLease:()V
     140: iload_1
     141: ifeq          201
     144: getstatic     #1                  // Field LOG:Lorg/slf4j/Logger;
     147: ldc           #90                 // String Inserting into second WALProcedureStore, causing WAL rolls
     149: invokeinterface #75,  2           // InterfaceMethod org/slf4j/Logger.info:(Ljava/lang/String;)V
     154: iconst_0
     155: istore        6
     157: iload         6
     159: sipush        512
     162: if_icmpge     201
     165: new           #91                 // class org/apache/hadoop/hbase/procedure2/ProcedureTestingUtility$TestProcedure
     168: dup
     169: iload         6
     171: i2l
     172: invokespecial #92                 // Method org/apache/hadoop/hbase/procedure2/ProcedureTestingUtility$TestProcedure."<init>":(J)V
     175: astore        7
     177: aload         5
     179: aload         7
     181: aconst_null
     182: invokevirtual #93                 // Method org/apache/hadoop/hbase/procedure2/store/wal/WALProcedureStore.insert:(Lorg/apache/hadoop/hbase/procedure2/Procedure;[Lorg/apache/hadoop/hbase/procedure2/Procedure;)V
     185: aload         5
     187: aload         7
     189: invokevirtual #94                 // Method org/apache/hadoop/hbase/procedure2/Procedure.getProcId:()J
     192: invokevirtual #85                 // Method org/apache/hadoop/hbase/procedure2/store/wal/WALProcedureStore.delete:(J)V
     195: iinc          6, 1
     198: goto          157
     201: getstatic     #1                  // Field LOG:Lorg/slf4j/Logger;
     204: ldc           #95                 // String Inserting into first WALProcedureStore
     206: invokeinterface #75,  2           // InterfaceMethod org/slf4j/Logger.info:(Ljava/lang/String;)V
     211: aload_2
     212: new           #91                 // class org/apache/hadoop/hbase/procedure2/ProcedureTestingUtility$TestProcedure
     215: dup
     216: ldc2_w        #96                 // long 11l
     219: invokespecial #92                 // Method org/apache/hadoop/hbase/procedure2/ProcedureTestingUtility$TestProcedure."<init>":(J)V
     222: aconst_null
     223: invokeinterface #98,  3           // InterfaceMethod org/apache/hadoop/hbase/procedure2/store/ProcedureStore.insert:(Lorg/apache/hadoop/hbase/procedure2/Procedure;[Lorg/apache/hadoop/hbase/procedure2/Procedure;)V
     228: ldc           #99                 // String Inserting into Procedure Store should have failed
     230: invokestatic  #67                 // Method org/junit/Assert.fail:(Ljava/lang/String;)V
     233: goto          250
     236: astore        6
     238: getstatic     #1                  // Field LOG:Lorg/slf4j/Logger;
     241: ldc           #100                // String Received expected exception
     243: aload         6
     245: invokeinterface #101,  3          // InterfaceMethod org/slf4j/Logger.info:(Ljava/lang/String;Ljava/lang/Throwable;)V
     250: return
    Exception table:
       from    to  target type
         211   233   236   Class java/lang/Exception

  static org.slf4j.Logger access$000();
    Code:
       0: getstatic     #1                  // Field LOG:Lorg/slf4j/Logger;
       3: areturn

  static {};
    Code:
       0: ldc           #103                // class org/apache/hadoop/hbase/master/procedure/TestMasterProcedureWalLease
       2: invokestatic  #104                // Method org/apache/hadoop/hbase/HBaseClassTestRule.forClass:(Ljava/lang/Class;)Lorg/apache/hadoop/hbase/HBaseClassTestRule;
       5: putstatic     #105                // Field CLASS_RULE:Lorg/apache/hadoop/hbase/HBaseClassTestRule;
       8: ldc           #103                // class org/apache/hadoop/hbase/master/procedure/TestMasterProcedureWalLease
      10: invokestatic  #106                // Method org/slf4j/LoggerFactory.getLogger:(Ljava/lang/Class;)Lorg/slf4j/Logger;
      13: putstatic     #1                  // Field LOG:Lorg/slf4j/Logger;
      16: new           #107                // class org/apache/hadoop/hbase/HBaseTestingUtility
      19: dup
      20: invokespecial #108                // Method org/apache/hadoop/hbase/HBaseTestingUtility."<init>":()V
      23: putstatic     #12                 // Field UTIL:Lorg/apache/hadoop/hbase/HBaseTestingUtility;
      26: return
}
