Compiled from "TestCoprocessorDescriptor.java"
public class org.apache.hadoop.hbase.client.TestCoprocessorDescriptor {
  public static final org.apache.hadoop.hbase.HBaseClassTestRule CLASS_RULE;

  public org.junit.rules.TestName name;

  public org.apache.hadoop.hbase.client.TestCoprocessorDescriptor();
    Code:
       0: aload_0
       1: invokespecial #1                  // Method java/lang/Object."<init>":()V
       4: aload_0
       5: new           #2                  // class org/junit/rules/TestName
       8: dup
       9: invokespecial #3                  // Method org/junit/rules/TestName."<init>":()V
      12: putfield      #4                  // Field name:Lorg/junit/rules/TestName;
      15: return

  public void testBuild();
    Code:
       0: ldc           #5                  // String className
       2: astore_1
       3: ldc           #6                  // String path
       5: astore_2
       6: bipush        100
       8: istore_3
       9: ldc           #7                  // String propertyKey
      11: astore        4
      13: ldc           #8                  // String propertyValue
      15: astore        5
      17: aload_1
      18: invokestatic  #9                  // Method org/apache/hadoop/hbase/client/CoprocessorDescriptorBuilder.newBuilder:(Ljava/lang/String;)Lorg/apache/hadoop/hbase/client/CoprocessorDescriptorBuilder;
      21: aload_2
      22: invokevirtual #10                 // Method org/apache/hadoop/hbase/client/CoprocessorDescriptorBuilder.setJarPath:(Ljava/lang/String;)Lorg/apache/hadoop/hbase/client/CoprocessorDescriptorBuilder;
      25: iload_3
      26: invokevirtual #11                 // Method org/apache/hadoop/hbase/client/CoprocessorDescriptorBuilder.setPriority:(I)Lorg/apache/hadoop/hbase/client/CoprocessorDescriptorBuilder;
      29: aload         4
      31: aload         5
      33: invokevirtual #12                 // Method org/apache/hadoop/hbase/client/CoprocessorDescriptorBuilder.setProperty:(Ljava/lang/String;Ljava/lang/String;)Lorg/apache/hadoop/hbase/client/CoprocessorDescriptorBuilder;
      36: invokevirtual #13                 // Method org/apache/hadoop/hbase/client/CoprocessorDescriptorBuilder.build:()Lorg/apache/hadoop/hbase/client/CoprocessorDescriptor;
      39: astore        6
      41: aload_1
      42: aload         6
      44: invokeinterface #14,  1           // InterfaceMethod org/apache/hadoop/hbase/client/CoprocessorDescriptor.getClassName:()Ljava/lang/String;
      49: invokestatic  #15                 // Method org/junit/Assert.assertEquals:(Ljava/lang/Object;Ljava/lang/Object;)V
      52: aload_2
      53: aload         6
      55: invokeinterface #16,  1           // InterfaceMethod org/apache/hadoop/hbase/client/CoprocessorDescriptor.getJarPath:()Ljava/util/Optional;
      60: invokevirtual #17                 // Method java/util/Optional.get:()Ljava/lang/Object;
      63: invokestatic  #15                 // Method org/junit/Assert.assertEquals:(Ljava/lang/Object;Ljava/lang/Object;)V
      66: iload_3
      67: i2l
      68: aload         6
      70: invokeinterface #18,  1           // InterfaceMethod org/apache/hadoop/hbase/client/CoprocessorDescriptor.getPriority:()I
      75: i2l
      76: invokestatic  #19                 // Method org/junit/Assert.assertEquals:(JJ)V
      79: lconst_1
      80: aload         6
      82: invokeinterface #20,  1           // InterfaceMethod org/apache/hadoop/hbase/client/CoprocessorDescriptor.getProperties:()Ljava/util/Map;
      87: invokeinterface #21,  1           // InterfaceMethod java/util/Map.size:()I
      92: i2l
      93: invokestatic  #19                 // Method org/junit/Assert.assertEquals:(JJ)V
      96: aload         5
      98: aload         6
     100: invokeinterface #20,  1           // InterfaceMethod org/apache/hadoop/hbase/client/CoprocessorDescriptor.getProperties:()Ljava/util/Map;
     105: aload         4
     107: invokeinterface #22,  2           // InterfaceMethod java/util/Map.get:(Ljava/lang/Object;)Ljava/lang/Object;
     112: invokestatic  #15                 // Method org/junit/Assert.assertEquals:(Ljava/lang/Object;Ljava/lang/Object;)V
     115: return

  public void testSetCoprocessor() throws java.io.IOException;
    Code:
       0: ldc           #7                  // String propertyKey
       2: astore_1
       3: new           #23                 // class java/util/ArrayList
       6: dup
       7: invokespecial #24                 // Method java/util/ArrayList."<init>":()V
      10: astore_2
      11: iconst_3
      12: anewarray     #25                 // class java/lang/String
      15: dup
      16: iconst_0
      17: ldc           #26                 // String className0
      19: aastore
      20: dup
      21: iconst_1
      22: ldc           #27                 // String className1
      24: aastore
      25: dup
      26: iconst_2
      27: ldc           #28                 // String className2
      29: aastore
      30: invokestatic  #29                 // Method java/util/Arrays.asList:([Ljava/lang/Object;)Ljava/util/List;
      33: invokeinterface #30,  1           // InterfaceMethod java/util/List.iterator:()Ljava/util/Iterator;
      38: astore_3
      39: aload_3
      40: invokeinterface #31,  1           // InterfaceMethod java/util/Iterator.hasNext:()Z
      45: ifeq          111
      48: aload_3
      49: invokeinterface #32,  1           // InterfaceMethod java/util/Iterator.next:()Ljava/lang/Object;
      54: checkcast     #25                 // class java/lang/String
      57: astore        4
      59: ldc           #6                  // String path
      61: astore        5
      63: aload         4
      65: invokevirtual #33                 // Method java/lang/String.hashCode:()I
      68: invokestatic  #34                 // Method java/lang/Math.abs:(I)I
      71: istore        6
      73: ldc           #8                  // String propertyValue
      75: astore        7
      77: aload_2
      78: aload         4
      80: invokestatic  #9                  // Method org/apache/hadoop/hbase/client/CoprocessorDescriptorBuilder.newBuilder:(Ljava/lang/String;)Lorg/apache/hadoop/hbase/client/CoprocessorDescriptorBuilder;
      83: aload         5
      85: invokevirtual #10                 // Method org/apache/hadoop/hbase/client/CoprocessorDescriptorBuilder.setJarPath:(Ljava/lang/String;)Lorg/apache/hadoop/hbase/client/CoprocessorDescriptorBuilder;
      88: iload         6
      90: invokevirtual #11                 // Method org/apache/hadoop/hbase/client/CoprocessorDescriptorBuilder.setPriority:(I)Lorg/apache/hadoop/hbase/client/CoprocessorDescriptorBuilder;
      93: aload_1
      94: aload         7
      96: invokevirtual #12                 // Method org/apache/hadoop/hbase/client/CoprocessorDescriptorBuilder.setProperty:(Ljava/lang/String;Ljava/lang/String;)Lorg/apache/hadoop/hbase/client/CoprocessorDescriptorBuilder;
      99: invokevirtual #13                 // Method org/apache/hadoop/hbase/client/CoprocessorDescriptorBuilder.build:()Lorg/apache/hadoop/hbase/client/CoprocessorDescriptor;
     102: invokeinterface #35,  2           // InterfaceMethod java/util/List.add:(Ljava/lang/Object;)Z
     107: pop
     108: goto          39
     111: aload_0
     112: getfield      #4                  // Field name:Lorg/junit/rules/TestName;
     115: invokevirtual #36                 // Method org/junit/rules/TestName.getMethodName:()Ljava/lang/String;
     118: invokestatic  #37                 // Method org/apache/hadoop/hbase/TableName.valueOf:(Ljava/lang/String;)Lorg/apache/hadoop/hbase/TableName;
     121: invokestatic  #38                 // Method org/apache/hadoop/hbase/client/TableDescriptorBuilder.newBuilder:(Lorg/apache/hadoop/hbase/TableName;)Lorg/apache/hadoop/hbase/client/TableDescriptorBuilder;
     124: aload_2
     125: invokevirtual #39                 // Method org/apache/hadoop/hbase/client/TableDescriptorBuilder.setCoprocessors:(Ljava/util/Collection;)Lorg/apache/hadoop/hbase/client/TableDescriptorBuilder;
     128: invokevirtual #40                 // Method org/apache/hadoop/hbase/client/TableDescriptorBuilder.build:()Lorg/apache/hadoop/hbase/client/TableDescriptor;
     131: astore_3
     132: aload_2
     133: invokeinterface #30,  1           // InterfaceMethod java/util/List.iterator:()Ljava/util/Iterator;
     138: astore        4
     140: aload         4
     142: invokeinterface #31,  1           // InterfaceMethod java/util/Iterator.hasNext:()Z
     147: ifeq          374
     150: aload         4
     152: invokeinterface #32,  1           // InterfaceMethod java/util/Iterator.next:()Ljava/lang/Object;
     157: checkcast     #41                 // class org/apache/hadoop/hbase/client/CoprocessorDescriptor
     160: astore        5
     162: iconst_0
     163: istore        6
     165: aload_3
     166: invokeinterface #42,  1           // InterfaceMethod org/apache/hadoop/hbase/client/TableDescriptor.getCoprocessorDescriptors:()Ljava/util/Collection;
     171: invokeinterface #43,  1           // InterfaceMethod java/util/Collection.iterator:()Ljava/util/Iterator;
     176: astore        7
     178: aload         7
     180: invokeinterface #31,  1           // InterfaceMethod java/util/Iterator.hasNext:()Z
     185: ifeq          329
     188: aload         7
     190: invokeinterface #32,  1           // InterfaceMethod java/util/Iterator.next:()Ljava/lang/Object;
     195: checkcast     #41                 // class org/apache/hadoop/hbase/client/CoprocessorDescriptor
     198: astore        8
     200: aload         5
     202: invokeinterface #14,  1           // InterfaceMethod org/apache/hadoop/hbase/client/CoprocessorDescriptor.getClassName:()Ljava/lang/String;
     207: aload         8
     209: invokeinterface #14,  1           // InterfaceMethod org/apache/hadoop/hbase/client/CoprocessorDescriptor.getClassName:()Ljava/lang/String;
     214: invokevirtual #44                 // Method java/lang/String.equals:(Ljava/lang/Object;)Z
     217: ifeq          326
     220: aload         5
     222: invokeinterface #16,  1           // InterfaceMethod org/apache/hadoop/hbase/client/CoprocessorDescriptor.getJarPath:()Ljava/util/Optional;
     227: invokevirtual #17                 // Method java/util/Optional.get:()Ljava/lang/Object;
     230: aload         8
     232: invokeinterface #16,  1           // InterfaceMethod org/apache/hadoop/hbase/client/CoprocessorDescriptor.getJarPath:()Ljava/util/Optional;
     237: invokevirtual #17                 // Method java/util/Optional.get:()Ljava/lang/Object;
     240: invokestatic  #15                 // Method org/junit/Assert.assertEquals:(Ljava/lang/Object;Ljava/lang/Object;)V
     243: aload         5
     245: invokeinterface #18,  1           // InterfaceMethod org/apache/hadoop/hbase/client/CoprocessorDescriptor.getPriority:()I
     250: i2l
     251: aload         8
     253: invokeinterface #18,  1           // InterfaceMethod org/apache/hadoop/hbase/client/CoprocessorDescriptor.getPriority:()I
     258: i2l
     259: invokestatic  #19                 // Method org/junit/Assert.assertEquals:(JJ)V
     262: aload         5
     264: invokeinterface #20,  1           // InterfaceMethod org/apache/hadoop/hbase/client/CoprocessorDescriptor.getProperties:()Ljava/util/Map;
     269: invokeinterface #21,  1           // InterfaceMethod java/util/Map.size:()I
     274: i2l
     275: aload         8
     277: invokeinterface #20,  1           // InterfaceMethod org/apache/hadoop/hbase/client/CoprocessorDescriptor.getProperties:()Ljava/util/Map;
     282: invokeinterface #21,  1           // InterfaceMethod java/util/Map.size:()I
     287: i2l
     288: invokestatic  #19                 // Method org/junit/Assert.assertEquals:(JJ)V
     291: aload         5
     293: invokeinterface #20,  1           // InterfaceMethod org/apache/hadoop/hbase/client/CoprocessorDescriptor.getProperties:()Ljava/util/Map;
     298: aload_1
     299: invokeinterface #22,  2           // InterfaceMethod java/util/Map.get:(Ljava/lang/Object;)Ljava/lang/Object;
     304: aload         8
     306: invokeinterface #20,  1           // InterfaceMethod org/apache/hadoop/hbase/client/CoprocessorDescriptor.getProperties:()Ljava/util/Map;
     311: aload_1
     312: invokeinterface #22,  2           // InterfaceMethod java/util/Map.get:(Ljava/lang/Object;)Ljava/lang/Object;
     317: invokestatic  #15                 // Method org/junit/Assert.assertEquals:(Ljava/lang/Object;Ljava/lang/Object;)V
     320: iconst_1
     321: istore        6
     323: goto          329
     326: goto          178
     329: iload         6
     331: ifne          371
     334: new           #45                 // class java/lang/StringBuilder
     337: dup
     338: invokespecial #46                 // Method java/lang/StringBuilder."<init>":()V
     341: ldc           #47                 // String expect:
     343: invokevirtual #48                 // Method java/lang/StringBuilder.append:(Ljava/lang/String;)Ljava/lang/StringBuilder;
     346: aload         5
     348: invokevirtual #49                 // Method java/lang/StringBuilder.append:(Ljava/lang/Object;)Ljava/lang/StringBuilder;
     351: ldc           #50                 // String , actual:
     353: invokevirtual #48                 // Method java/lang/StringBuilder.append:(Ljava/lang/String;)Ljava/lang/StringBuilder;
     356: aload_3
     357: invokeinterface #42,  1           // InterfaceMethod org/apache/hadoop/hbase/client/TableDescriptor.getCoprocessorDescriptors:()Ljava/util/Collection;
     362: invokevirtual #49                 // Method java/lang/StringBuilder.append:(Ljava/lang/Object;)Ljava/lang/StringBuilder;
     365: invokevirtual #51                 // Method java/lang/StringBuilder.toString:()Ljava/lang/String;
     368: invokestatic  #52                 // Method org/junit/Assert.fail:(Ljava/lang/String;)V
     371: goto          140
     374: return

  static {};
    Code:
       0: ldc           #53                 // class org/apache/hadoop/hbase/client/TestCoprocessorDescriptor
       2: invokestatic  #54                 // Method org/apache/hadoop/hbase/HBaseClassTestRule.forClass:(Ljava/lang/Class;)Lorg/apache/hadoop/hbase/HBaseClassTestRule;
       5: putstatic     #55                 // Field CLASS_RULE:Lorg/apache/hadoop/hbase/HBaseClassTestRule;
       8: ldc           #53                 // class org/apache/hadoop/hbase/client/TestCoprocessorDescriptor
      10: invokestatic  #56                 // Method org/slf4j/LoggerFactory.getLogger:(Ljava/lang/Class;)Lorg/slf4j/Logger;
      13: putstatic     #57                 // Field LOG:Lorg/slf4j/Logger;
      16: return
}
