Compiled from "TestClientExponentialBackoff.java"
public class org.apache.hadoop.hbase.client.TestClientExponentialBackoff {
  public static final org.apache.hadoop.hbase.HBaseClassTestRule CLASS_RULE;

  org.apache.hadoop.hbase.ServerName server;

  byte[] regionname;

  public org.apache.hadoop.hbase.client.TestClientExponentialBackoff();
    Code:
       0: aload_0
       1: invokespecial #1                  // Method java/lang/Object."<init>":()V
       4: aload_0
       5: ldc           #2                  // class org/apache/hadoop/hbase/ServerName
       7: invokestatic  #3                  // Method org/mockito/Mockito.mock:(Ljava/lang/Class;)Ljava/lang/Object;
      10: checkcast     #2                  // class org/apache/hadoop/hbase/ServerName
      13: putfield      #4                  // Field server:Lorg/apache/hadoop/hbase/ServerName;
      16: aload_0
      17: ldc           #5                  // String region
      19: invokestatic  #6                  // Method org/apache/hadoop/hbase/util/Bytes.toBytes:(Ljava/lang/String;)[B
      22: putfield      #7                  // Field regionname:[B
      25: return

  public void testNulls();
    Code:
       0: new           #8                  // class org/apache/hadoop/conf/Configuration
       3: dup
       4: iconst_0
       5: invokespecial #9                  // Method org/apache/hadoop/conf/Configuration."<init>":(Z)V
       8: astore_1
       9: new           #10                 // class org/apache/hadoop/hbase/client/backoff/ExponentialClientBackoffPolicy
      12: dup
      13: aload_1
      14: invokespecial #11                 // Method org/apache/hadoop/hbase/client/backoff/ExponentialClientBackoffPolicy."<init>":(Lorg/apache/hadoop/conf/Configuration;)V
      17: astore_2
      18: lconst_0
      19: aload_2
      20: aconst_null
      21: aconst_null
      22: aconst_null
      23: invokevirtual #12                 // Method org/apache/hadoop/hbase/client/backoff/ExponentialClientBackoffPolicy.getBackoffTime:(Lorg/apache/hadoop/hbase/ServerName;[BLorg/apache/hadoop/hbase/client/backoff/ServerStatistics;)J
      26: invokestatic  #13                 // Method org/junit/Assert.assertEquals:(JJ)V
      29: lconst_0
      30: aload_2
      31: aload_0
      32: getfield      #4                  // Field server:Lorg/apache/hadoop/hbase/ServerName;
      35: aconst_null
      36: aconst_null
      37: invokevirtual #12                 // Method org/apache/hadoop/hbase/client/backoff/ExponentialClientBackoffPolicy.getBackoffTime:(Lorg/apache/hadoop/hbase/ServerName;[BLorg/apache/hadoop/hbase/client/backoff/ServerStatistics;)J
      40: invokestatic  #13                 // Method org/junit/Assert.assertEquals:(JJ)V
      43: lconst_0
      44: aload_2
      45: aload_0
      46: getfield      #4                  // Field server:Lorg/apache/hadoop/hbase/ServerName;
      49: aload_0
      50: getfield      #7                  // Field regionname:[B
      53: aconst_null
      54: invokevirtual #12                 // Method org/apache/hadoop/hbase/client/backoff/ExponentialClientBackoffPolicy.getBackoffTime:(Lorg/apache/hadoop/hbase/ServerName;[BLorg/apache/hadoop/hbase/client/backoff/ServerStatistics;)J
      57: invokestatic  #13                 // Method org/junit/Assert.assertEquals:(JJ)V
      60: new           #14                 // class org/apache/hadoop/hbase/client/backoff/ServerStatistics
      63: dup
      64: invokespecial #15                 // Method org/apache/hadoop/hbase/client/backoff/ServerStatistics."<init>":()V
      67: astore_3
      68: lconst_0
      69: aload_2
      70: aload_0
      71: getfield      #4                  // Field server:Lorg/apache/hadoop/hbase/ServerName;
      74: aload_0
      75: getfield      #7                  // Field regionname:[B
      78: aload_3
      79: invokevirtual #12                 // Method org/apache/hadoop/hbase/client/backoff/ExponentialClientBackoffPolicy.getBackoffTime:(Lorg/apache/hadoop/hbase/ServerName;[BLorg/apache/hadoop/hbase/client/backoff/ServerStatistics;)J
      82: invokestatic  #13                 // Method org/junit/Assert.assertEquals:(JJ)V
      85: return

  public void testMaxLoad();
    Code:
       0: new           #8                  // class org/apache/hadoop/conf/Configuration
       3: dup
       4: iconst_0
       5: invokespecial #9                  // Method org/apache/hadoop/conf/Configuration."<init>":(Z)V
       8: astore_1
       9: new           #10                 // class org/apache/hadoop/hbase/client/backoff/ExponentialClientBackoffPolicy
      12: dup
      13: aload_1
      14: invokespecial #11                 // Method org/apache/hadoop/hbase/client/backoff/ExponentialClientBackoffPolicy."<init>":(Lorg/apache/hadoop/conf/Configuration;)V
      17: astore_2
      18: new           #14                 // class org/apache/hadoop/hbase/client/backoff/ServerStatistics
      21: dup
      22: invokespecial #15                 // Method org/apache/hadoop/hbase/client/backoff/ServerStatistics."<init>":()V
      25: astore_3
      26: aload_0
      27: aload_3
      28: bipush        100
      30: invokespecial #16                 // Method update:(Lorg/apache/hadoop/hbase/client/backoff/ServerStatistics;I)V
      33: ldc2_w        #17                 // long 300000l
      36: aload_2
      37: aload_0
      38: getfield      #4                  // Field server:Lorg/apache/hadoop/hbase/ServerName;
      41: aload_0
      42: getfield      #7                  // Field regionname:[B
      45: aload_3
      46: invokevirtual #12                 // Method org/apache/hadoop/hbase/client/backoff/ExponentialClientBackoffPolicy.getBackoffTime:(Lorg/apache/hadoop/hbase/ServerName;[BLorg/apache/hadoop/hbase/client/backoff/ServerStatistics;)J
      49: invokestatic  #13                 // Method org/junit/Assert.assertEquals:(JJ)V
      52: ldc2_w        #19                 // long 100l
      55: lstore        4
      57: aload_1
      58: ldc           #21                 // String hbase.client.exponential-backoff.max
      60: lload         4
      62: invokevirtual #22                 // Method org/apache/hadoop/conf/Configuration.setLong:(Ljava/lang/String;J)V
      65: new           #10                 // class org/apache/hadoop/hbase/client/backoff/ExponentialClientBackoffPolicy
      68: dup
      69: aload_1
      70: invokespecial #11                 // Method org/apache/hadoop/hbase/client/backoff/ExponentialClientBackoffPolicy."<init>":(Lorg/apache/hadoop/conf/Configuration;)V
      73: astore        6
      75: lload         4
      77: aload         6
      79: aload_0
      80: getfield      #4                  // Field server:Lorg/apache/hadoop/hbase/ServerName;
      83: aload_0
      84: getfield      #7                  // Field regionname:[B
      87: aload_3
      88: invokevirtual #12                 // Method org/apache/hadoop/hbase/client/backoff/ExponentialClientBackoffPolicy.getBackoffTime:(Lorg/apache/hadoop/hbase/ServerName;[BLorg/apache/hadoop/hbase/client/backoff/ServerStatistics;)J
      91: invokestatic  #13                 // Method org/junit/Assert.assertEquals:(JJ)V
      94: aload_0
      95: aload_3
      96: bipush        101
      98: invokespecial #16                 // Method update:(Lorg/apache/hadoop/hbase/client/backoff/ServerStatistics;I)V
     101: ldc2_w        #17                 // long 300000l
     104: aload_2
     105: aload_0
     106: getfield      #4                  // Field server:Lorg/apache/hadoop/hbase/ServerName;
     109: aload_0
     110: getfield      #7                  // Field regionname:[B
     113: aload_3
     114: invokevirtual #12                 // Method org/apache/hadoop/hbase/client/backoff/ExponentialClientBackoffPolicy.getBackoffTime:(Lorg/apache/hadoop/hbase/ServerName;[BLorg/apache/hadoop/hbase/client/backoff/ServerStatistics;)J
     117: invokestatic  #13                 // Method org/junit/Assert.assertEquals:(JJ)V
     120: lload         4
     122: aload         6
     124: aload_0
     125: getfield      #4                  // Field server:Lorg/apache/hadoop/hbase/ServerName;
     128: aload_0
     129: getfield      #7                  // Field regionname:[B
     132: aload_3
     133: invokevirtual #12                 // Method org/apache/hadoop/hbase/client/backoff/ExponentialClientBackoffPolicy.getBackoffTime:(Lorg/apache/hadoop/hbase/ServerName;[BLorg/apache/hadoop/hbase/client/backoff/ServerStatistics;)J
     136: invokestatic  #13                 // Method org/junit/Assert.assertEquals:(JJ)V
     139: aload_0
     140: aload_3
     141: bipush        99
     143: invokespecial #16                 // Method update:(Lorg/apache/hadoop/hbase/client/backoff/ServerStatistics;I)V
     146: aload_2
     147: aload_0
     148: getfield      #4                  // Field server:Lorg/apache/hadoop/hbase/ServerName;
     151: aload_0
     152: getfield      #7                  // Field regionname:[B
     155: aload_3
     156: invokevirtual #12                 // Method org/apache/hadoop/hbase/client/backoff/ExponentialClientBackoffPolicy.getBackoffTime:(Lorg/apache/hadoop/hbase/ServerName;[BLorg/apache/hadoop/hbase/client/backoff/ServerStatistics;)J
     159: ldc2_w        #17                 // long 300000l
     162: lcmp
     163: ifge          170
     166: iconst_1
     167: goto          171
     170: iconst_0
     171: invokestatic  #23                 // Method org/junit/Assert.assertTrue:(Z)V
     174: aload         6
     176: aload_0
     177: getfield      #4                  // Field server:Lorg/apache/hadoop/hbase/ServerName;
     180: aload_0
     181: getfield      #7                  // Field regionname:[B
     184: aload_3
     185: invokevirtual #12                 // Method org/apache/hadoop/hbase/client/backoff/ExponentialClientBackoffPolicy.getBackoffTime:(Lorg/apache/hadoop/hbase/ServerName;[BLorg/apache/hadoop/hbase/client/backoff/ServerStatistics;)J
     188: lload         4
     190: lcmp
     191: ifge          198
     194: iconst_1
     195: goto          199
     198: iconst_0
     199: invokestatic  #23                 // Method org/junit/Assert.assertTrue:(Z)V
     202: return

  public void testResultOrdering();
    Code:
       0: new           #8                  // class org/apache/hadoop/conf/Configuration
       3: dup
       4: iconst_0
       5: invokespecial #9                  // Method org/apache/hadoop/conf/Configuration."<init>":(Z)V
       8: astore_1
       9: aload_1
      10: ldc           #21                 // String hbase.client.exponential-backoff.max
      12: ldc2_w        #25                 // long 2147483647l
      15: invokevirtual #22                 // Method org/apache/hadoop/conf/Configuration.setLong:(Ljava/lang/String;J)V
      18: new           #10                 // class org/apache/hadoop/hbase/client/backoff/ExponentialClientBackoffPolicy
      21: dup
      22: aload_1
      23: invokespecial #11                 // Method org/apache/hadoop/hbase/client/backoff/ExponentialClientBackoffPolicy."<init>":(Lorg/apache/hadoop/conf/Configuration;)V
      26: astore_2
      27: new           #14                 // class org/apache/hadoop/hbase/client/backoff/ServerStatistics
      30: dup
      31: invokespecial #15                 // Method org/apache/hadoop/hbase/client/backoff/ServerStatistics."<init>":()V
      34: astore_3
      35: aload_2
      36: aload_0
      37: getfield      #4                  // Field server:Lorg/apache/hadoop/hbase/ServerName;
      40: aload_0
      41: getfield      #7                  // Field regionname:[B
      44: aload_3
      45: invokevirtual #12                 // Method org/apache/hadoop/hbase/client/backoff/ExponentialClientBackoffPolicy.getBackoffTime:(Lorg/apache/hadoop/hbase/ServerName;[BLorg/apache/hadoop/hbase/client/backoff/ServerStatistics;)J
      48: lstore        4
      50: iconst_1
      51: istore        6
      53: iload         6
      55: bipush        100
      57: if_icmpgt     148
      60: aload_0
      61: aload_3
      62: iload         6
      64: invokespecial #16                 // Method update:(Lorg/apache/hadoop/hbase/client/backoff/ServerStatistics;I)V
      67: aload_2
      68: aload_0
      69: getfield      #4                  // Field server:Lorg/apache/hadoop/hbase/ServerName;
      72: aload_0
      73: getfield      #7                  // Field regionname:[B
      76: aload_3
      77: invokevirtual #12                 // Method org/apache/hadoop/hbase/client/backoff/ExponentialClientBackoffPolicy.getBackoffTime:(Lorg/apache/hadoop/hbase/ServerName;[BLorg/apache/hadoop/hbase/client/backoff/ServerStatistics;)J
      80: lstore        7
      82: new           #27                 // class java/lang/StringBuilder
      85: dup
      86: invokespecial #28                 // Method java/lang/StringBuilder."<init>":()V
      89: ldc           #29                 // String Previous backoff time
      91: invokevirtual #30                 // Method java/lang/StringBuilder.append:(Ljava/lang/String;)Ljava/lang/StringBuilder;
      94: lload         4
      96: invokevirtual #31                 // Method java/lang/StringBuilder.append:(J)Ljava/lang/StringBuilder;
      99: ldc           #32                 // String  >=
     101: invokevirtual #30                 // Method java/lang/StringBuilder.append:(Ljava/lang/String;)Ljava/lang/StringBuilder;
     104: lload         7
     106: invokevirtual #31                 // Method java/lang/StringBuilder.append:(J)Ljava/lang/StringBuilder;
     109: ldc           #33                 // String , the next backoff time for load
     111: invokevirtual #30                 // Method java/lang/StringBuilder.append:(Ljava/lang/String;)Ljava/lang/StringBuilder;
     114: iload         6
     116: invokevirtual #34                 // Method java/lang/StringBuilder.append:(I)Ljava/lang/StringBuilder;
     119: invokevirtual #35                 // Method java/lang/StringBuilder.toString:()Ljava/lang/String;
     122: lload         4
     124: lload         7
     126: lcmp
     127: ifge          134
     130: iconst_1
     131: goto          135
     134: iconst_0
     135: invokestatic  #36                 // Method org/junit/Assert.assertTrue:(Ljava/lang/String;Z)V
     138: lload         7
     140: lstore        4
     142: iinc          6, 1
     145: goto          53
     148: return

  public void testHeapOccupancyPolicy();
    Code:
       0: new           #8                  // class org/apache/hadoop/conf/Configuration
       3: dup
       4: iconst_0
       5: invokespecial #9                  // Method org/apache/hadoop/conf/Configuration."<init>":(Z)V
       8: astore_1
       9: new           #10                 // class org/apache/hadoop/hbase/client/backoff/ExponentialClientBackoffPolicy
      12: dup
      13: aload_1
      14: invokespecial #11                 // Method org/apache/hadoop/hbase/client/backoff/ExponentialClientBackoffPolicy."<init>":(Lorg/apache/hadoop/conf/Configuration;)V
      17: astore_2
      18: new           #14                 // class org/apache/hadoop/hbase/client/backoff/ServerStatistics
      21: dup
      22: invokespecial #15                 // Method org/apache/hadoop/hbase/client/backoff/ServerStatistics."<init>":()V
      25: astore_3
      26: aload_0
      27: aload_3
      28: iconst_0
      29: bipush        95
      31: iconst_0
      32: invokespecial #37                 // Method update:(Lorg/apache/hadoop/hbase/client/backoff/ServerStatistics;III)V
      35: aload_2
      36: aload_0
      37: getfield      #4                  // Field server:Lorg/apache/hadoop/hbase/ServerName;
      40: aload_0
      41: getfield      #7                  // Field regionname:[B
      44: aload_3
      45: invokevirtual #12                 // Method org/apache/hadoop/hbase/client/backoff/ExponentialClientBackoffPolicy.getBackoffTime:(Lorg/apache/hadoop/hbase/ServerName;[BLorg/apache/hadoop/hbase/client/backoff/ServerStatistics;)J
      48: lstore        4
      50: ldc           #38                 // String Heap occupancy at low watermark had no effect
      52: lload         4
      54: lconst_0
      55: lcmp
      56: ifle          63
      59: iconst_1
      60: goto          64
      63: iconst_0
      64: invokestatic  #36                 // Method org/junit/Assert.assertTrue:(Ljava/lang/String;Z)V
      67: lload         4
      69: lstore        6
      71: aload_0
      72: aload_3
      73: iconst_0
      74: bipush        96
      76: iconst_0
      77: invokespecial #37                 // Method update:(Lorg/apache/hadoop/hbase/client/backoff/ServerStatistics;III)V
      80: aload_2
      81: aload_0
      82: getfield      #4                  // Field server:Lorg/apache/hadoop/hbase/ServerName;
      85: aload_0
      86: getfield      #7                  // Field regionname:[B
      89: aload_3
      90: invokevirtual #12                 // Method org/apache/hadoop/hbase/client/backoff/ExponentialClientBackoffPolicy.getBackoffTime:(Lorg/apache/hadoop/hbase/ServerName;[BLorg/apache/hadoop/hbase/client/backoff/ServerStatistics;)J
      93: lstore        4
      95: ldc           #39                 // String Increase above low watermark should have increased backoff
      97: lload         4
      99: lload         6
     101: lcmp
     102: ifle          109
     105: iconst_1
     106: goto          110
     109: iconst_0
     110: invokestatic  #36                 // Method org/junit/Assert.assertTrue:(Ljava/lang/String;Z)V
     113: aload_0
     114: aload_3
     115: iconst_0
     116: bipush        98
     118: iconst_0
     119: invokespecial #37                 // Method update:(Lorg/apache/hadoop/hbase/client/backoff/ServerStatistics;III)V
     122: aload_2
     123: aload_0
     124: getfield      #4                  // Field server:Lorg/apache/hadoop/hbase/ServerName;
     127: aload_0
     128: getfield      #7                  // Field regionname:[B
     131: aload_3
     132: invokevirtual #12                 // Method org/apache/hadoop/hbase/client/backoff/ExponentialClientBackoffPolicy.getBackoffTime:(Lorg/apache/hadoop/hbase/ServerName;[BLorg/apache/hadoop/hbase/client/backoff/ServerStatistics;)J
     135: lstore        4
     137: ldc           #40                 // String We should be using max backoff when at high watermark
     139: ldc2_w        #17                 // long 300000l
     142: lload         4
     144: invokestatic  #41                 // Method org/junit/Assert.assertEquals:(Ljava/lang/String;JJ)V
     147: return

  public void testCompactionPressurePolicy();
    Code:
       0: new           #8                  // class org/apache/hadoop/conf/Configuration
       3: dup
       4: iconst_0
       5: invokespecial #9                  // Method org/apache/hadoop/conf/Configuration."<init>":(Z)V
       8: astore_1
       9: new           #10                 // class org/apache/hadoop/hbase/client/backoff/ExponentialClientBackoffPolicy
      12: dup
      13: aload_1
      14: invokespecial #11                 // Method org/apache/hadoop/hbase/client/backoff/ExponentialClientBackoffPolicy."<init>":(Lorg/apache/hadoop/conf/Configuration;)V
      17: astore_2
      18: new           #14                 // class org/apache/hadoop/hbase/client/backoff/ServerStatistics
      21: dup
      22: invokespecial #15                 // Method org/apache/hadoop/hbase/client/backoff/ServerStatistics."<init>":()V
      25: astore_3
      26: aload_0
      27: aload_3
      28: iconst_0
      29: iconst_0
      30: iconst_0
      31: invokespecial #37                 // Method update:(Lorg/apache/hadoop/hbase/client/backoff/ServerStatistics;III)V
      34: aload_2
      35: aload_0
      36: getfield      #4                  // Field server:Lorg/apache/hadoop/hbase/ServerName;
      39: aload_0
      40: getfield      #7                  // Field regionname:[B
      43: aload_3
      44: invokevirtual #12                 // Method org/apache/hadoop/hbase/client/backoff/ExponentialClientBackoffPolicy.getBackoffTime:(Lorg/apache/hadoop/hbase/ServerName;[BLorg/apache/hadoop/hbase/client/backoff/ServerStatistics;)J
      47: lstore        4
      49: ldc           #42                 // String Compaction pressure has no effect
      51: lload         4
      53: lconst_0
      54: lcmp
      55: ifne          62
      58: iconst_1
      59: goto          63
      62: iconst_0
      63: invokestatic  #36                 // Method org/junit/Assert.assertTrue:(Ljava/lang/String;Z)V
      66: lload         4
      68: lstore        6
      70: aload_0
      71: aload_3
      72: iconst_0
      73: iconst_0
      74: bipush        50
      76: invokespecial #37                 // Method update:(Lorg/apache/hadoop/hbase/client/backoff/ServerStatistics;III)V
      79: aload_2
      80: aload_0
      81: getfield      #4                  // Field server:Lorg/apache/hadoop/hbase/ServerName;
      84: aload_0
      85: getfield      #7                  // Field regionname:[B
      88: aload_3
      89: invokevirtual #12                 // Method org/apache/hadoop/hbase/client/backoff/ExponentialClientBackoffPolicy.getBackoffTime:(Lorg/apache/hadoop/hbase/ServerName;[BLorg/apache/hadoop/hbase/client/backoff/ServerStatistics;)J
      92: lstore        4
      94: ldc           #43                 // String Compaction pressure should be bigger
      96: lload         4
      98: lload         6
     100: lcmp
     101: ifle          108
     104: iconst_1
     105: goto          109
     108: iconst_0
     109: invokestatic  #36                 // Method org/junit/Assert.assertTrue:(Ljava/lang/String;Z)V
     112: aload_0
     113: aload_3
     114: iconst_0
     115: iconst_0
     116: bipush        100
     118: invokespecial #37                 // Method update:(Lorg/apache/hadoop/hbase/client/backoff/ServerStatistics;III)V
     121: aload_2
     122: aload_0
     123: getfield      #4                  // Field server:Lorg/apache/hadoop/hbase/ServerName;
     126: aload_0
     127: getfield      #7                  // Field regionname:[B
     130: aload_3
     131: invokevirtual #12                 // Method org/apache/hadoop/hbase/client/backoff/ExponentialClientBackoffPolicy.getBackoffTime:(Lorg/apache/hadoop/hbase/ServerName;[BLorg/apache/hadoop/hbase/client/backoff/ServerStatistics;)J
     134: lstore        4
     136: ldc           #44                 // String under heavy compaction pressure
     138: ldc2_w        #17                 // long 300000l
     141: lload         4
     143: invokestatic  #41                 // Method org/junit/Assert.assertEquals:(Ljava/lang/String;JJ)V
     146: return

  static {};
    Code:
       0: ldc           #52                 // class org/apache/hadoop/hbase/client/TestClientExponentialBackoff
       2: invokestatic  #53                 // Method org/apache/hadoop/hbase/HBaseClassTestRule.forClass:(Ljava/lang/Class;)Lorg/apache/hadoop/hbase/HBaseClassTestRule;
       5: putstatic     #54                 // Field CLASS_RULE:Lorg/apache/hadoop/hbase/HBaseClassTestRule;
       8: return
}
