Compiled from "TestWithDisabledAuthorization.java"
public class org.apache.hadoop.hbase.security.visibility.TestWithDisabledAuthorization {
  public static final org.apache.hadoop.hbase.HBaseClassTestRule CLASS_RULE;

  public final org.junit.rules.TestName TEST_NAME;

  public org.apache.hadoop.hbase.security.visibility.TestWithDisabledAuthorization();
    Code:
       0: aload_0
       1: invokespecial #3                  // Method java/lang/Object."<init>":()V
       4: aload_0
       5: new           #4                  // class org/junit/rules/TestName
       8: dup
       9: invokespecial #5                  // Method org/junit/rules/TestName."<init>":()V
      12: putfield      #6                  // Field TEST_NAME:Lorg/junit/rules/TestName;
      15: return

  public static void setUpBeforeClass() throws java.lang.Exception;
    Code:
       0: getstatic     #7                  // Field TEST_UTIL:Lorg/apache/hadoop/hbase/HBaseTestingUtility;
       3: invokevirtual #8                  // Method org/apache/hadoop/hbase/HBaseTestingUtility.getConfiguration:()Lorg/apache/hadoop/conf/Configuration;
       6: putstatic     #2                  // Field conf:Lorg/apache/hadoop/conf/Configuration;
       9: getstatic     #2                  // Field conf:Lorg/apache/hadoop/conf/Configuration;
      12: ldc           #10                 // String hbase.regionserver.metahandler.count
      14: bipush        10
      16: invokevirtual #11                 // Method org/apache/hadoop/conf/Configuration.setInt:(Ljava/lang/String;I)V
      19: getstatic     #2                  // Field conf:Lorg/apache/hadoop/conf/Configuration;
      22: invokestatic  #12                 // Method org/apache/hadoop/hbase/security/access/SecureTestUtil.configureSuperuser:(Lorg/apache/hadoop/conf/Configuration;)V
      25: getstatic     #2                  // Field conf:Lorg/apache/hadoop/conf/Configuration;
      28: invokestatic  #13                 // Method org/apache/hadoop/hbase/security/visibility/VisibilityTestUtil.enableVisiblityLabels:(Lorg/apache/hadoop/conf/Configuration;)V
      31: getstatic     #2                  // Field conf:Lorg/apache/hadoop/conf/Configuration;
      34: ldc           #15                 // String hbase.security.authorization
      36: iconst_0
      37: invokevirtual #16                 // Method org/apache/hadoop/conf/Configuration.setBoolean:(Ljava/lang/String;Z)V
      40: getstatic     #7                  // Field TEST_UTIL:Lorg/apache/hadoop/hbase/HBaseTestingUtility;
      43: invokevirtual #17                 // Method org/apache/hadoop/hbase/HBaseTestingUtility.startMiniCluster:()Lorg/apache/hadoop/hbase/MiniHBaseCluster;
      46: pop
      47: getstatic     #7                  // Field TEST_UTIL:Lorg/apache/hadoop/hbase/HBaseTestingUtility;
      50: getstatic     #18                 // Field org/apache/hadoop/hbase/security/visibility/VisibilityConstants.LABELS_TABLE_NAME:Lorg/apache/hadoop/hbase/TableName;
      53: invokevirtual #19                 // Method org/apache/hadoop/hbase/HBaseTestingUtility.waitUntilAllRegionsAssigned:(Lorg/apache/hadoop/hbase/TableName;)V
      56: getstatic     #2                  // Field conf:Lorg/apache/hadoop/conf/Configuration;
      59: ldc           #20                 // String admin
      61: iconst_1
      62: anewarray     #21                 // class java/lang/String
      65: dup
      66: iconst_0
      67: ldc           #22                 // String supergroup
      69: aastore
      70: invokestatic  #23                 // Method org/apache/hadoop/hbase/security/User.createUserForTesting:(Lorg/apache/hadoop/conf/Configuration;Ljava/lang/String;[Ljava/lang/String;)Lorg/apache/hadoop/hbase/security/User;
      73: putstatic     #24                 // Field SUPERUSER:Lorg/apache/hadoop/hbase/security/User;
      76: getstatic     #2                  // Field conf:Lorg/apache/hadoop/conf/Configuration;
      79: ldc           #25                 // String rwuser
      81: iconst_0
      82: anewarray     #21                 // class java/lang/String
      85: invokestatic  #23                 // Method org/apache/hadoop/hbase/security/User.createUserForTesting:(Lorg/apache/hadoop/conf/Configuration;Ljava/lang/String;[Ljava/lang/String;)Lorg/apache/hadoop/hbase/security/User;
      88: putstatic     #1                  // Field USER_RW:Lorg/apache/hadoop/hbase/security/User;
      91: getstatic     #24                 // Field SUPERUSER:Lorg/apache/hadoop/hbase/security/User;
      94: new           #26                 // class org/apache/hadoop/hbase/security/visibility/TestWithDisabledAuthorization$1
      97: dup
      98: invokespecial #27                 // Method org/apache/hadoop/hbase/security/visibility/TestWithDisabledAuthorization$1."<init>":()V
     101: invokevirtual #28                 // Method org/apache/hadoop/hbase/security/User.runAs:(Ljava/security/PrivilegedExceptionAction;)Ljava/lang/Object;
     104: pop
     105: return

  public static void tearDownAfterClass() throws java.lang.Exception;
    Code:
       0: getstatic     #7                  // Field TEST_UTIL:Lorg/apache/hadoop/hbase/HBaseTestingUtility;
       3: invokevirtual #29                 // Method org/apache/hadoop/hbase/HBaseTestingUtility.shutdownMiniCluster:()V
       6: return

  public void testManageUserAuths() throws java.lang.Throwable;
    Code:
       0: getstatic     #24                 // Field SUPERUSER:Lorg/apache/hadoop/hbase/security/User;
       3: new           #30                 // class org/apache/hadoop/hbase/security/visibility/TestWithDisabledAuthorization$2
       6: dup
       7: aload_0
       8: invokespecial #31                 // Method org/apache/hadoop/hbase/security/visibility/TestWithDisabledAuthorization$2."<init>":(Lorg/apache/hadoop/hbase/security/visibility/TestWithDisabledAuthorization;)V
      11: invokevirtual #28                 // Method org/apache/hadoop/hbase/security/User.runAs:(Ljava/security/PrivilegedExceptionAction;)Ljava/lang/Object;
      14: pop
      15: new           #32                 // class org/apache/hadoop/hbase/security/visibility/TestWithDisabledAuthorization$3
      18: dup
      19: aload_0
      20: invokespecial #33                 // Method org/apache/hadoop/hbase/security/visibility/TestWithDisabledAuthorization$3."<init>":(Lorg/apache/hadoop/hbase/security/visibility/TestWithDisabledAuthorization;)V
      23: astore_1
      24: getstatic     #24                 // Field SUPERUSER:Lorg/apache/hadoop/hbase/security/User;
      27: aload_1
      28: invokevirtual #28                 // Method org/apache/hadoop/hbase/security/User.runAs:(Ljava/security/PrivilegedExceptionAction;)Ljava/lang/Object;
      31: checkcast     #34                 // class java/util/List
      34: astore_2
      35: ldc2_w        #35                 // long 2l
      38: aload_2
      39: invokeinterface #37,  1           // InterfaceMethod java/util/List.size:()I
      44: i2l
      45: invokestatic  #38                 // Method org/junit/Assert.assertEquals:(JJ)V
      48: aload_2
      49: ldc           #40                 // String secret
      51: invokeinterface #41,  2           // InterfaceMethod java/util/List.contains:(Ljava/lang/Object;)Z
      56: invokestatic  #42                 // Method org/junit/Assert.assertTrue:(Z)V
      59: aload_2
      60: ldc           #43                 // String confidential
      62: invokeinterface #41,  2           // InterfaceMethod java/util/List.contains:(Ljava/lang/Object;)Z
      67: invokestatic  #42                 // Method org/junit/Assert.assertTrue:(Z)V
      70: getstatic     #24                 // Field SUPERUSER:Lorg/apache/hadoop/hbase/security/User;
      73: new           #44                 // class org/apache/hadoop/hbase/security/visibility/TestWithDisabledAuthorization$4
      76: dup
      77: aload_0
      78: invokespecial #45                 // Method org/apache/hadoop/hbase/security/visibility/TestWithDisabledAuthorization$4."<init>":(Lorg/apache/hadoop/hbase/security/visibility/TestWithDisabledAuthorization;)V
      81: invokevirtual #28                 // Method org/apache/hadoop/hbase/security/User.runAs:(Ljava/security/PrivilegedExceptionAction;)Ljava/lang/Object;
      84: pop
      85: getstatic     #24                 // Field SUPERUSER:Lorg/apache/hadoop/hbase/security/User;
      88: aload_1
      89: invokevirtual #28                 // Method org/apache/hadoop/hbase/security/User.runAs:(Ljava/security/PrivilegedExceptionAction;)Ljava/lang/Object;
      92: checkcast     #34                 // class java/util/List
      95: astore_2
      96: lconst_1
      97: aload_2
      98: invokeinterface #37,  1           // InterfaceMethod java/util/List.size:()I
     103: i2l
     104: invokestatic  #38                 // Method org/junit/Assert.assertEquals:(JJ)V
     107: aload_2
     108: ldc           #43                 // String confidential
     110: invokeinterface #41,  2           // InterfaceMethod java/util/List.contains:(Ljava/lang/Object;)Z
     115: invokestatic  #42                 // Method org/junit/Assert.assertTrue:(Z)V
     118: getstatic     #24                 // Field SUPERUSER:Lorg/apache/hadoop/hbase/security/User;
     121: new           #46                 // class org/apache/hadoop/hbase/security/visibility/TestWithDisabledAuthorization$5
     124: dup
     125: aload_0
     126: invokespecial #47                 // Method org/apache/hadoop/hbase/security/visibility/TestWithDisabledAuthorization$5."<init>":(Lorg/apache/hadoop/hbase/security/visibility/TestWithDisabledAuthorization;)V
     129: invokevirtual #28                 // Method org/apache/hadoop/hbase/security/User.runAs:(Ljava/security/PrivilegedExceptionAction;)Ljava/lang/Object;
     132: pop
     133: getstatic     #24                 // Field SUPERUSER:Lorg/apache/hadoop/hbase/security/User;
     136: aload_1
     137: invokevirtual #28                 // Method org/apache/hadoop/hbase/security/User.runAs:(Ljava/security/PrivilegedExceptionAction;)Ljava/lang/Object;
     140: checkcast     #34                 // class java/util/List
     143: astore_2
     144: lconst_0
     145: aload_2
     146: invokeinterface #37,  1           // InterfaceMethod java/util/List.size:()I
     151: i2l
     152: invokestatic  #38                 // Method org/junit/Assert.assertEquals:(JJ)V
     155: return

  public void testPassiveVisibility() throws java.lang.Exception;
    Code:
       0: aload_0
       1: getfield      #6                  // Field TEST_NAME:Lorg/junit/rules/TestName;
       4: invokevirtual #48                 // Method org/junit/rules/TestName.getMethodName:()Ljava/lang/String;
       7: invokestatic  #49                 // Method org/apache/hadoop/hbase/TableName.valueOf:(Ljava/lang/String;)Lorg/apache/hadoop/hbase/TableName;
      10: iconst_4
      11: anewarray     #21                 // class java/lang/String
      14: dup
      15: iconst_0
      16: ldc           #40                 // String secret
      18: aastore
      19: dup
      20: iconst_1
      21: ldc           #50                 // String private
      23: aastore
      24: dup
      25: iconst_2
      26: ldc           #51                 // String secret|confidential
      28: aastore
      29: dup
      30: iconst_3
      31: ldc           #52                 // String private|confidential
      33: aastore
      34: invokestatic  #53                 // Method createTableAndWriteDataWithLabels:(Lorg/apache/hadoop/hbase/TableName;[Ljava/lang/String;)Lorg/apache/hadoop/hbase/client/Table;
      37: astore_1
      38: aconst_null
      39: astore_2
      40: new           #54                 // class org/apache/hadoop/hbase/client/Scan
      43: dup
      44: invokespecial #55                 // Method org/apache/hadoop/hbase/client/Scan."<init>":()V
      47: astore_3
      48: aload_3
      49: new           #56                 // class org/apache/hadoop/hbase/security/visibility/Authorizations
      52: dup
      53: iconst_0
      54: anewarray     #21                 // class java/lang/String
      57: invokespecial #57                 // Method org/apache/hadoop/hbase/security/visibility/Authorizations."<init>":([Ljava/lang/String;)V
      60: invokevirtual #58                 // Method org/apache/hadoop/hbase/client/Scan.setAuthorizations:(Lorg/apache/hadoop/hbase/security/visibility/Authorizations;)Lorg/apache/hadoop/hbase/client/Scan;
      63: pop
      64: aload_1
      65: aload_3
      66: invokeinterface #59,  2           // InterfaceMethod org/apache/hadoop/hbase/client/Table.getScanner:(Lorg/apache/hadoop/hbase/client/Scan;)Lorg/apache/hadoop/hbase/client/ResultScanner;
      71: astore        4
      73: aconst_null
      74: astore        5
      76: aload         4
      78: bipush        10
      80: invokeinterface #60,  2           // InterfaceMethod org/apache/hadoop/hbase/client/ResultScanner.next:(I)[Lorg/apache/hadoop/hbase/client/Result;
      85: astore        6
      87: ldc2_w        #61                 // long 4l
      90: aload         6
      92: arraylength
      93: i2l
      94: invokestatic  #38                 // Method org/junit/Assert.assertEquals:(JJ)V
      97: aload         4
      99: ifnull        192
     102: aload         5
     104: ifnull        129
     107: aload         4
     109: invokeinterface #63,  1           // InterfaceMethod org/apache/hadoop/hbase/client/ResultScanner.close:()V
     114: goto          192
     117: astore        6
     119: aload         5
     121: aload         6
     123: invokevirtual #65                 // Method java/lang/Throwable.addSuppressed:(Ljava/lang/Throwable;)V
     126: goto          192
     129: aload         4
     131: invokeinterface #63,  1           // InterfaceMethod org/apache/hadoop/hbase/client/ResultScanner.close:()V
     136: goto          192
     139: astore        6
     141: aload         6
     143: astore        5
     145: aload         6
     147: athrow
     148: astore        7
     150: aload         4
     152: ifnull        189
     155: aload         5
     157: ifnull        182
     160: aload         4
     162: invokeinterface #63,  1           // InterfaceMethod org/apache/hadoop/hbase/client/ResultScanner.close:()V
     167: goto          189
     170: astore        8
     172: aload         5
     174: aload         8
     176: invokevirtual #65                 // Method java/lang/Throwable.addSuppressed:(Ljava/lang/Throwable;)V
     179: goto          189
     182: aload         4
     184: invokeinterface #63,  1           // InterfaceMethod org/apache/hadoop/hbase/client/ResultScanner.close:()V
     189: aload         7
     191: athrow
     192: new           #54                 // class org/apache/hadoop/hbase/client/Scan
     195: dup
     196: invokespecial #55                 // Method org/apache/hadoop/hbase/client/Scan."<init>":()V
     199: astore_3
     200: aload_3
     201: new           #56                 // class org/apache/hadoop/hbase/security/visibility/Authorizations
     204: dup
     205: iconst_1
     206: anewarray     #21                 // class java/lang/String
     209: dup
     210: iconst_0
     211: ldc           #40                 // String secret
     213: aastore
     214: invokespecial #57                 // Method org/apache/hadoop/hbase/security/visibility/Authorizations."<init>":([Ljava/lang/String;)V
     217: invokevirtual #58                 // Method org/apache/hadoop/hbase/client/Scan.setAuthorizations:(Lorg/apache/hadoop/hbase/security/visibility/Authorizations;)Lorg/apache/hadoop/hbase/client/Scan;
     220: pop
     221: aload_1
     222: aload_3
     223: invokeinterface #59,  2           // InterfaceMethod org/apache/hadoop/hbase/client/Table.getScanner:(Lorg/apache/hadoop/hbase/client/Scan;)Lorg/apache/hadoop/hbase/client/ResultScanner;
     228: astore        4
     230: aconst_null
     231: astore        5
     233: aload         4
     235: bipush        10
     237: invokeinterface #60,  2           // InterfaceMethod org/apache/hadoop/hbase/client/ResultScanner.next:(I)[Lorg/apache/hadoop/hbase/client/Result;
     242: astore        6
     244: ldc2_w        #61                 // long 4l
     247: aload         6
     249: arraylength
     250: i2l
     251: invokestatic  #38                 // Method org/junit/Assert.assertEquals:(JJ)V
     254: aload         4
     256: ifnull        349
     259: aload         5
     261: ifnull        286
     264: aload         4
     266: invokeinterface #63,  1           // InterfaceMethod org/apache/hadoop/hbase/client/ResultScanner.close:()V
     271: goto          349
     274: astore        6
     276: aload         5
     278: aload         6
     280: invokevirtual #65                 // Method java/lang/Throwable.addSuppressed:(Ljava/lang/Throwable;)V
     283: goto          349
     286: aload         4
     288: invokeinterface #63,  1           // InterfaceMethod org/apache/hadoop/hbase/client/ResultScanner.close:()V
     293: goto          349
     296: astore        6
     298: aload         6
     300: astore        5
     302: aload         6
     304: athrow
     305: astore        9
     307: aload         4
     309: ifnull        346
     312: aload         5
     314: ifnull        339
     317: aload         4
     319: invokeinterface #63,  1           // InterfaceMethod org/apache/hadoop/hbase/client/ResultScanner.close:()V
     324: goto          346
     327: astore        10
     329: aload         5
     331: aload         10
     333: invokevirtual #65                 // Method java/lang/Throwable.addSuppressed:(Ljava/lang/Throwable;)V
     336: goto          346
     339: aload         4
     341: invokeinterface #63,  1           // InterfaceMethod org/apache/hadoop/hbase/client/ResultScanner.close:()V
     346: aload         9
     348: athrow
     349: new           #54                 // class org/apache/hadoop/hbase/client/Scan
     352: dup
     353: invokespecial #55                 // Method org/apache/hadoop/hbase/client/Scan."<init>":()V
     356: astore_3
     357: aload_3
     358: new           #56                 // class org/apache/hadoop/hbase/security/visibility/Authorizations
     361: dup
     362: iconst_2
     363: anewarray     #21                 // class java/lang/String
     366: dup
     367: iconst_0
     368: ldc           #40                 // String secret
     370: aastore
     371: dup
     372: iconst_1
     373: ldc           #43                 // String confidential
     375: aastore
     376: invokespecial #57                 // Method org/apache/hadoop/hbase/security/visibility/Authorizations."<init>":([Ljava/lang/String;)V
     379: invokevirtual #58                 // Method org/apache/hadoop/hbase/client/Scan.setAuthorizations:(Lorg/apache/hadoop/hbase/security/visibility/Authorizations;)Lorg/apache/hadoop/hbase/client/Scan;
     382: pop
     383: aload_1
     384: aload_3
     385: invokeinterface #59,  2           // InterfaceMethod org/apache/hadoop/hbase/client/Table.getScanner:(Lorg/apache/hadoop/hbase/client/Scan;)Lorg/apache/hadoop/hbase/client/ResultScanner;
     390: astore        4
     392: aconst_null
     393: astore        5
     395: aload         4
     397: bipush        10
     399: invokeinterface #60,  2           // InterfaceMethod org/apache/hadoop/hbase/client/ResultScanner.next:(I)[Lorg/apache/hadoop/hbase/client/Result;
     404: astore        6
     406: ldc2_w        #61                 // long 4l
     409: aload         6
     411: arraylength
     412: i2l
     413: invokestatic  #38                 // Method org/junit/Assert.assertEquals:(JJ)V
     416: aload         4
     418: ifnull        511
     421: aload         5
     423: ifnull        448
     426: aload         4
     428: invokeinterface #63,  1           // InterfaceMethod org/apache/hadoop/hbase/client/ResultScanner.close:()V
     433: goto          511
     436: astore        6
     438: aload         5
     440: aload         6
     442: invokevirtual #65                 // Method java/lang/Throwable.addSuppressed:(Ljava/lang/Throwable;)V
     445: goto          511
     448: aload         4
     450: invokeinterface #63,  1           // InterfaceMethod org/apache/hadoop/hbase/client/ResultScanner.close:()V
     455: goto          511
     458: astore        6
     460: aload         6
     462: astore        5
     464: aload         6
     466: athrow
     467: astore        11
     469: aload         4
     471: ifnull        508
     474: aload         5
     476: ifnull        501
     479: aload         4
     481: invokeinterface #63,  1           // InterfaceMethod org/apache/hadoop/hbase/client/ResultScanner.close:()V
     486: goto          508
     489: astore        12
     491: aload         5
     493: aload         12
     495: invokevirtual #65                 // Method java/lang/Throwable.addSuppressed:(Ljava/lang/Throwable;)V
     498: goto          508
     501: aload         4
     503: invokeinterface #63,  1           // InterfaceMethod org/apache/hadoop/hbase/client/ResultScanner.close:()V
     508: aload         11
     510: athrow
     511: new           #54                 // class org/apache/hadoop/hbase/client/Scan
     514: dup
     515: invokespecial #55                 // Method org/apache/hadoop/hbase/client/Scan."<init>":()V
     518: astore_3
     519: aload_3
     520: new           #56                 // class org/apache/hadoop/hbase/security/visibility/Authorizations
     523: dup
     524: iconst_3
     525: anewarray     #21                 // class java/lang/String
     528: dup
     529: iconst_0
     530: ldc           #40                 // String secret
     532: aastore
     533: dup
     534: iconst_1
     535: ldc           #43                 // String confidential
     537: aastore
     538: dup
     539: iconst_2
     540: ldc           #50                 // String private
     542: aastore
     543: invokespecial #57                 // Method org/apache/hadoop/hbase/security/visibility/Authorizations."<init>":([Ljava/lang/String;)V
     546: invokevirtual #58                 // Method org/apache/hadoop/hbase/client/Scan.setAuthorizations:(Lorg/apache/hadoop/hbase/security/visibility/Authorizations;)Lorg/apache/hadoop/hbase/client/Scan;
     549: pop
     550: aload_1
     551: aload_3
     552: invokeinterface #59,  2           // InterfaceMethod org/apache/hadoop/hbase/client/Table.getScanner:(Lorg/apache/hadoop/hbase/client/Scan;)Lorg/apache/hadoop/hbase/client/ResultScanner;
     557: astore        4
     559: aconst_null
     560: astore        5
     562: aload         4
     564: bipush        10
     566: invokeinterface #60,  2           // InterfaceMethod org/apache/hadoop/hbase/client/ResultScanner.next:(I)[Lorg/apache/hadoop/hbase/client/Result;
     571: astore        6
     573: ldc2_w        #61                 // long 4l
     576: aload         6
     578: arraylength
     579: i2l
     580: invokestatic  #38                 // Method org/junit/Assert.assertEquals:(JJ)V
     583: aload         4
     585: ifnull        678
     588: aload         5
     590: ifnull        615
     593: aload         4
     595: invokeinterface #63,  1           // InterfaceMethod org/apache/hadoop/hbase/client/ResultScanner.close:()V
     600: goto          678
     603: astore        6
     605: aload         5
     607: aload         6
     609: invokevirtual #65                 // Method java/lang/Throwable.addSuppressed:(Ljava/lang/Throwable;)V
     612: goto          678
     615: aload         4
     617: invokeinterface #63,  1           // InterfaceMethod org/apache/hadoop/hbase/client/ResultScanner.close:()V
     622: goto          678
     625: astore        6
     627: aload         6
     629: astore        5
     631: aload         6
     633: athrow
     634: astore        13
     636: aload         4
     638: ifnull        675
     641: aload         5
     643: ifnull        668
     646: aload         4
     648: invokeinterface #63,  1           // InterfaceMethod org/apache/hadoop/hbase/client/ResultScanner.close:()V
     653: goto          675
     656: astore        14
     658: aload         5
     660: aload         14
     662: invokevirtual #65                 // Method java/lang/Throwable.addSuppressed:(Ljava/lang/Throwable;)V
     665: goto          675
     668: aload         4
     670: invokeinterface #63,  1           // InterfaceMethod org/apache/hadoop/hbase/client/ResultScanner.close:()V
     675: aload         13
     677: athrow
     678: aload_1
     679: ifnull        757
     682: aload_2
     683: ifnull        704
     686: aload_1
     687: invokeinterface #66,  1           // InterfaceMethod org/apache/hadoop/hbase/client/Table.close:()V
     692: goto          757
     695: astore_3
     696: aload_2
     697: aload_3
     698: invokevirtual #65                 // Method java/lang/Throwable.addSuppressed:(Ljava/lang/Throwable;)V
     701: goto          757
     704: aload_1
     705: invokeinterface #66,  1           // InterfaceMethod org/apache/hadoop/hbase/client/Table.close:()V
     710: goto          757
     713: astore_3
     714: aload_3
     715: astore_2
     716: aload_3
     717: athrow
     718: astore        15
     720: aload_1
     721: ifnull        754
     724: aload_2
     725: ifnull        748
     728: aload_1
     729: invokeinterface #66,  1           // InterfaceMethod org/apache/hadoop/hbase/client/Table.close:()V
     734: goto          754
     737: astore        16
     739: aload_2
     740: aload         16
     742: invokevirtual #65                 // Method java/lang/Throwable.addSuppressed:(Ljava/lang/Throwable;)V
     745: goto          754
     748: aload_1
     749: invokeinterface #66,  1           // InterfaceMethod org/apache/hadoop/hbase/client/Table.close:()V
     754: aload         15
     756: athrow
     757: return
    Exception table:
       from    to  target type
         107   114   117   Class java/lang/Throwable
          76    97   139   Class java/lang/Throwable
          76    97   148   any
         160   167   170   Class java/lang/Throwable
         139   150   148   any
         264   271   274   Class java/lang/Throwable
         233   254   296   Class java/lang/Throwable
         233   254   305   any
         317   324   327   Class java/lang/Throwable
         296   307   305   any
         426   433   436   Class java/lang/Throwable
         395   416   458   Class java/lang/Throwable
         395   416   467   any
         479   486   489   Class java/lang/Throwable
         458   469   467   any
         593   600   603   Class java/lang/Throwable
         562   583   625   Class java/lang/Throwable
         562   583   634   any
         646   653   656   Class java/lang/Throwable
         625   636   634   any
         686   692   695   Class java/lang/Throwable
          40   678   713   Class java/lang/Throwable
          40   678   718   any
         728   734   737   Class java/lang/Throwable
         713   720   718   any

  static org.apache.hadoop.hbase.client.Table createTableAndWriteDataWithLabels(org.apache.hadoop.hbase.TableName, java.lang.String...) throws java.lang.Exception;
    Code:
       0: new           #67                 // class java/util/ArrayList
       3: dup
       4: aload_1
       5: arraylength
       6: iconst_1
       7: iadd
       8: invokespecial #68                 // Method java/util/ArrayList."<init>":(I)V
      11: astore_2
      12: iconst_0
      13: istore_3
      14: iload_3
      15: aload_1
      16: arraylength
      17: if_icmpge     102
      20: new           #69                 // class org/apache/hadoop/hbase/client/Put
      23: dup
      24: new           #70                 // class java/lang/StringBuilder
      27: dup
      28: invokespecial #71                 // Method java/lang/StringBuilder."<init>":()V
      31: ldc           #72                 // String row
      33: invokevirtual #73                 // Method java/lang/StringBuilder.append:(Ljava/lang/String;)Ljava/lang/StringBuilder;
      36: iload_3
      37: iconst_1
      38: iadd
      39: invokevirtual #74                 // Method java/lang/StringBuilder.append:(I)Ljava/lang/StringBuilder;
      42: invokevirtual #75                 // Method java/lang/StringBuilder.toString:()Ljava/lang/String;
      45: invokestatic  #76                 // Method org/apache/hadoop/hbase/util/Bytes.toBytes:(Ljava/lang/String;)[B
      48: invokespecial #77                 // Method org/apache/hadoop/hbase/client/Put."<init>":([B)V
      51: astore        4
      53: aload         4
      55: getstatic     #78                 // Field TEST_FAMILY:[B
      58: getstatic     #79                 // Field TEST_QUALIFIER:[B
      61: ldc2_w        #80                 // long 9223372036854775807l
      64: getstatic     #82                 // Field ZERO:[B
      67: invokevirtual #83                 // Method org/apache/hadoop/hbase/client/Put.addColumn:([B[BJ[B)Lorg/apache/hadoop/hbase/client/Put;
      70: pop
      71: aload         4
      73: new           #84                 // class org/apache/hadoop/hbase/security/visibility/CellVisibility
      76: dup
      77: aload_1
      78: iload_3
      79: aaload
      80: invokespecial #85                 // Method org/apache/hadoop/hbase/security/visibility/CellVisibility."<init>":(Ljava/lang/String;)V
      83: invokevirtual #86                 // Method org/apache/hadoop/hbase/client/Put.setCellVisibility:(Lorg/apache/hadoop/hbase/security/visibility/CellVisibility;)Lorg/apache/hadoop/hbase/client/Put;
      86: pop
      87: aload_2
      88: aload         4
      90: invokeinterface #87,  2           // InterfaceMethod java/util/List.add:(Ljava/lang/Object;)Z
      95: pop
      96: iinc          3, 1
      99: goto          14
     102: getstatic     #7                  // Field TEST_UTIL:Lorg/apache/hadoop/hbase/HBaseTestingUtility;
     105: aload_0
     106: getstatic     #78                 // Field TEST_FAMILY:[B
     109: invokevirtual #88                 // Method org/apache/hadoop/hbase/HBaseTestingUtility.createTable:(Lorg/apache/hadoop/hbase/TableName;[B)Lorg/apache/hadoop/hbase/client/Table;
     112: astore_3
     113: aload_3
     114: aload_2
     115: invokeinterface #89,  2           // InterfaceMethod org/apache/hadoop/hbase/client/Table.put:(Ljava/util/List;)V
     120: aload_3
     121: areturn

  static org.apache.hadoop.conf.Configuration access$000();
    Code:
       0: getstatic     #2                  // Field conf:Lorg/apache/hadoop/conf/Configuration;
       3: areturn

  static org.apache.hadoop.hbase.security.User access$100();
    Code:
       0: getstatic     #1                  // Field USER_RW:Lorg/apache/hadoop/hbase/security/User;
       3: areturn

  static {};
    Code:
       0: ldc           #39                 // class org/apache/hadoop/hbase/security/visibility/TestWithDisabledAuthorization
       2: invokestatic  #90                 // Method org/apache/hadoop/hbase/HBaseClassTestRule.forClass:(Ljava/lang/Class;)Lorg/apache/hadoop/hbase/HBaseClassTestRule;
       5: putstatic     #91                 // Field CLASS_RULE:Lorg/apache/hadoop/hbase/HBaseClassTestRule;
       8: new           #92                 // class org/apache/hadoop/hbase/HBaseTestingUtility
      11: dup
      12: invokespecial #93                 // Method org/apache/hadoop/hbase/HBaseTestingUtility."<init>":()V
      15: putstatic     #7                  // Field TEST_UTIL:Lorg/apache/hadoop/hbase/HBaseTestingUtility;
      18: ldc           #94                 // String test
      20: invokestatic  #76                 // Method org/apache/hadoop/hbase/util/Bytes.toBytes:(Ljava/lang/String;)[B
      23: putstatic     #78                 // Field TEST_FAMILY:[B
      26: ldc           #95                 // String q
      28: invokestatic  #76                 // Method org/apache/hadoop/hbase/util/Bytes.toBytes:(Ljava/lang/String;)[B
      31: putstatic     #79                 // Field TEST_QUALIFIER:[B
      34: lconst_0
      35: invokestatic  #96                 // Method org/apache/hadoop/hbase/util/Bytes.toBytes:(J)[B
      38: putstatic     #82                 // Field ZERO:[B
      41: return
}
