Compiled from "TestScanDeleteTracker.java"
public class org.apache.hadoop.hbase.regionserver.querymatcher.TestScanDeleteTracker {
  public static final org.apache.hadoop.hbase.HBaseClassTestRule CLASS_RULE;

  public org.apache.hadoop.hbase.regionserver.querymatcher.TestScanDeleteTracker();
    Code:
       0: aload_0
       1: invokespecial #1                  // Method java/lang/Object."<init>":()V
       4: aload_0
       5: ldc2_w        #2                  // long 10l
       8: putfield      #4                  // Field timestamp:J
      11: return

  public void setUp() throws java.lang.Exception;
    Code:
       0: aload_0
       1: new           #5                  // class org/apache/hadoop/hbase/regionserver/querymatcher/ScanDeleteTracker
       4: dup
       5: getstatic     #6                  // Field org/apache/hadoop/hbase/CellComparatorImpl.COMPARATOR:Lorg/apache/hadoop/hbase/CellComparatorImpl;
       8: invokespecial #7                  // Method org/apache/hadoop/hbase/regionserver/querymatcher/ScanDeleteTracker."<init>":(Lorg/apache/hadoop/hbase/CellComparator;)V
      11: putfield      #8                  // Field sdt:Lorg/apache/hadoop/hbase/regionserver/querymatcher/ScanDeleteTracker;
      14: return

  public void testDeletedByDelete();
    Code:
       0: new           #9                  // class org/apache/hadoop/hbase/KeyValue
       3: dup
       4: ldc           #10                 // String row
       6: invokestatic  #11                 // Method org/apache/hadoop/hbase/util/Bytes.toBytes:(Ljava/lang/String;)[B
       9: ldc           #12                 // String f
      11: invokestatic  #11                 // Method org/apache/hadoop/hbase/util/Bytes.toBytes:(Ljava/lang/String;)[B
      14: ldc           #13                 // String qualifier
      16: invokestatic  #11                 // Method org/apache/hadoop/hbase/util/Bytes.toBytes:(Ljava/lang/String;)[B
      19: aload_0
      20: getfield      #4                  // Field timestamp:J
      23: getstatic     #14                 // Field org/apache/hadoop/hbase/KeyValue$Type.Delete:Lorg/apache/hadoop/hbase/KeyValue$Type;
      26: invokespecial #15                 // Method org/apache/hadoop/hbase/KeyValue."<init>":([B[B[BJLorg/apache/hadoop/hbase/KeyValue$Type;)V
      29: astore_1
      30: aload_0
      31: getfield      #8                  // Field sdt:Lorg/apache/hadoop/hbase/regionserver/querymatcher/ScanDeleteTracker;
      34: aload_1
      35: invokevirtual #16                 // Method org/apache/hadoop/hbase/regionserver/querymatcher/ScanDeleteTracker.add:(Lorg/apache/hadoop/hbase/Cell;)V
      38: aload_0
      39: getfield      #8                  // Field sdt:Lorg/apache/hadoop/hbase/regionserver/querymatcher/ScanDeleteTracker;
      42: aload_1
      43: invokevirtual #17                 // Method org/apache/hadoop/hbase/regionserver/querymatcher/ScanDeleteTracker.isDeleted:(Lorg/apache/hadoop/hbase/Cell;)Lorg/apache/hadoop/hbase/regionserver/querymatcher/DeleteTracker$DeleteResult;
      46: astore_2
      47: getstatic     #18                 // Field org/apache/hadoop/hbase/regionserver/querymatcher/DeleteTracker$DeleteResult.VERSION_DELETED:Lorg/apache/hadoop/hbase/regionserver/querymatcher/DeleteTracker$DeleteResult;
      50: aload_2
      51: invokestatic  #19                 // Method org/junit/Assert.assertEquals:(Ljava/lang/Object;Ljava/lang/Object;)V
      54: return

  public void testDeletedByDeleteColumn();
    Code:
       0: new           #9                  // class org/apache/hadoop/hbase/KeyValue
       3: dup
       4: ldc           #10                 // String row
       6: invokestatic  #11                 // Method org/apache/hadoop/hbase/util/Bytes.toBytes:(Ljava/lang/String;)[B
       9: ldc           #12                 // String f
      11: invokestatic  #11                 // Method org/apache/hadoop/hbase/util/Bytes.toBytes:(Ljava/lang/String;)[B
      14: ldc           #13                 // String qualifier
      16: invokestatic  #11                 // Method org/apache/hadoop/hbase/util/Bytes.toBytes:(Ljava/lang/String;)[B
      19: aload_0
      20: getfield      #4                  // Field timestamp:J
      23: getstatic     #20                 // Field org/apache/hadoop/hbase/KeyValue$Type.DeleteColumn:Lorg/apache/hadoop/hbase/KeyValue$Type;
      26: invokespecial #15                 // Method org/apache/hadoop/hbase/KeyValue."<init>":([B[B[BJLorg/apache/hadoop/hbase/KeyValue$Type;)V
      29: astore_1
      30: aload_0
      31: getfield      #8                  // Field sdt:Lorg/apache/hadoop/hbase/regionserver/querymatcher/ScanDeleteTracker;
      34: aload_1
      35: invokevirtual #16                 // Method org/apache/hadoop/hbase/regionserver/querymatcher/ScanDeleteTracker.add:(Lorg/apache/hadoop/hbase/Cell;)V
      38: aload_0
      39: dup
      40: getfield      #4                  // Field timestamp:J
      43: ldc2_w        #21                 // long 5l
      46: lsub
      47: putfield      #4                  // Field timestamp:J
      50: new           #9                  // class org/apache/hadoop/hbase/KeyValue
      53: dup
      54: ldc           #10                 // String row
      56: invokestatic  #11                 // Method org/apache/hadoop/hbase/util/Bytes.toBytes:(Ljava/lang/String;)[B
      59: ldc           #12                 // String f
      61: invokestatic  #11                 // Method org/apache/hadoop/hbase/util/Bytes.toBytes:(Ljava/lang/String;)[B
      64: ldc           #13                 // String qualifier
      66: invokestatic  #11                 // Method org/apache/hadoop/hbase/util/Bytes.toBytes:(Ljava/lang/String;)[B
      69: aload_0
      70: getfield      #4                  // Field timestamp:J
      73: getstatic     #20                 // Field org/apache/hadoop/hbase/KeyValue$Type.DeleteColumn:Lorg/apache/hadoop/hbase/KeyValue$Type;
      76: invokespecial #15                 // Method org/apache/hadoop/hbase/KeyValue."<init>":([B[B[BJLorg/apache/hadoop/hbase/KeyValue$Type;)V
      79: astore_1
      80: aload_0
      81: getfield      #8                  // Field sdt:Lorg/apache/hadoop/hbase/regionserver/querymatcher/ScanDeleteTracker;
      84: aload_1
      85: invokevirtual #17                 // Method org/apache/hadoop/hbase/regionserver/querymatcher/ScanDeleteTracker.isDeleted:(Lorg/apache/hadoop/hbase/Cell;)Lorg/apache/hadoop/hbase/regionserver/querymatcher/DeleteTracker$DeleteResult;
      88: astore_2
      89: getstatic     #23                 // Field org/apache/hadoop/hbase/regionserver/querymatcher/DeleteTracker$DeleteResult.COLUMN_DELETED:Lorg/apache/hadoop/hbase/regionserver/querymatcher/DeleteTracker$DeleteResult;
      92: aload_2
      93: invokestatic  #19                 // Method org/junit/Assert.assertEquals:(Ljava/lang/Object;Ljava/lang/Object;)V
      96: return

  public void testDeletedByDeleteFamily();
    Code:
       0: new           #9                  // class org/apache/hadoop/hbase/KeyValue
       3: dup
       4: ldc           #10                 // String row
       6: invokestatic  #11                 // Method org/apache/hadoop/hbase/util/Bytes.toBytes:(Ljava/lang/String;)[B
       9: ldc           #12                 // String f
      11: invokestatic  #11                 // Method org/apache/hadoop/hbase/util/Bytes.toBytes:(Ljava/lang/String;)[B
      14: ldc           #13                 // String qualifier
      16: invokestatic  #11                 // Method org/apache/hadoop/hbase/util/Bytes.toBytes:(Ljava/lang/String;)[B
      19: aload_0
      20: getfield      #4                  // Field timestamp:J
      23: getstatic     #24                 // Field org/apache/hadoop/hbase/KeyValue$Type.DeleteFamily:Lorg/apache/hadoop/hbase/KeyValue$Type;
      26: invokespecial #15                 // Method org/apache/hadoop/hbase/KeyValue."<init>":([B[B[BJLorg/apache/hadoop/hbase/KeyValue$Type;)V
      29: astore_1
      30: aload_0
      31: getfield      #8                  // Field sdt:Lorg/apache/hadoop/hbase/regionserver/querymatcher/ScanDeleteTracker;
      34: aload_1
      35: invokevirtual #16                 // Method org/apache/hadoop/hbase/regionserver/querymatcher/ScanDeleteTracker.add:(Lorg/apache/hadoop/hbase/Cell;)V
      38: aload_0
      39: dup
      40: getfield      #4                  // Field timestamp:J
      43: ldc2_w        #21                 // long 5l
      46: lsub
      47: putfield      #4                  // Field timestamp:J
      50: new           #9                  // class org/apache/hadoop/hbase/KeyValue
      53: dup
      54: ldc           #10                 // String row
      56: invokestatic  #11                 // Method org/apache/hadoop/hbase/util/Bytes.toBytes:(Ljava/lang/String;)[B
      59: ldc           #12                 // String f
      61: invokestatic  #11                 // Method org/apache/hadoop/hbase/util/Bytes.toBytes:(Ljava/lang/String;)[B
      64: ldc           #13                 // String qualifier
      66: invokestatic  #11                 // Method org/apache/hadoop/hbase/util/Bytes.toBytes:(Ljava/lang/String;)[B
      69: aload_0
      70: getfield      #4                  // Field timestamp:J
      73: getstatic     #20                 // Field org/apache/hadoop/hbase/KeyValue$Type.DeleteColumn:Lorg/apache/hadoop/hbase/KeyValue$Type;
      76: invokespecial #15                 // Method org/apache/hadoop/hbase/KeyValue."<init>":([B[B[BJLorg/apache/hadoop/hbase/KeyValue$Type;)V
      79: astore_1
      80: aload_0
      81: getfield      #8                  // Field sdt:Lorg/apache/hadoop/hbase/regionserver/querymatcher/ScanDeleteTracker;
      84: aload_1
      85: invokevirtual #17                 // Method org/apache/hadoop/hbase/regionserver/querymatcher/ScanDeleteTracker.isDeleted:(Lorg/apache/hadoop/hbase/Cell;)Lorg/apache/hadoop/hbase/regionserver/querymatcher/DeleteTracker$DeleteResult;
      88: astore_2
      89: getstatic     #25                 // Field org/apache/hadoop/hbase/regionserver/querymatcher/DeleteTracker$DeleteResult.FAMILY_DELETED:Lorg/apache/hadoop/hbase/regionserver/querymatcher/DeleteTracker$DeleteResult;
      92: aload_2
      93: invokestatic  #19                 // Method org/junit/Assert.assertEquals:(Ljava/lang/Object;Ljava/lang/Object;)V
      96: return

  public void testDeletedByDeleteFamilyVersion();
    Code:
       0: ldc           #26                 // String qualifier1
       2: invokestatic  #11                 // Method org/apache/hadoop/hbase/util/Bytes.toBytes:(Ljava/lang/String;)[B
       5: astore_1
       6: ldc           #27                 // String qualifier2
       8: invokestatic  #11                 // Method org/apache/hadoop/hbase/util/Bytes.toBytes:(Ljava/lang/String;)[B
      11: astore_2
      12: ldc           #28                 // String qualifier3
      14: invokestatic  #11                 // Method org/apache/hadoop/hbase/util/Bytes.toBytes:(Ljava/lang/String;)[B
      17: astore_3
      18: ldc           #29                 // String qualifier4
      20: invokestatic  #11                 // Method org/apache/hadoop/hbase/util/Bytes.toBytes:(Ljava/lang/String;)[B
      23: astore        4
      25: new           #9                  // class org/apache/hadoop/hbase/KeyValue
      28: dup
      29: ldc           #10                 // String row
      31: invokestatic  #11                 // Method org/apache/hadoop/hbase/util/Bytes.toBytes:(Ljava/lang/String;)[B
      34: ldc           #12                 // String f
      36: invokestatic  #11                 // Method org/apache/hadoop/hbase/util/Bytes.toBytes:(Ljava/lang/String;)[B
      39: aconst_null
      40: aload_0
      41: getfield      #4                  // Field timestamp:J
      44: getstatic     #30                 // Field org/apache/hadoop/hbase/KeyValue$Type.DeleteFamilyVersion:Lorg/apache/hadoop/hbase/KeyValue$Type;
      47: invokespecial #15                 // Method org/apache/hadoop/hbase/KeyValue."<init>":([B[B[BJLorg/apache/hadoop/hbase/KeyValue$Type;)V
      50: astore        5
      52: aload_0
      53: getfield      #8                  // Field sdt:Lorg/apache/hadoop/hbase/regionserver/querymatcher/ScanDeleteTracker;
      56: aload         5
      58: invokevirtual #16                 // Method org/apache/hadoop/hbase/regionserver/querymatcher/ScanDeleteTracker.add:(Lorg/apache/hadoop/hbase/Cell;)V
      61: new           #9                  // class org/apache/hadoop/hbase/KeyValue
      64: dup
      65: ldc           #10                 // String row
      67: invokestatic  #11                 // Method org/apache/hadoop/hbase/util/Bytes.toBytes:(Ljava/lang/String;)[B
      70: ldc           #12                 // String f
      72: invokestatic  #11                 // Method org/apache/hadoop/hbase/util/Bytes.toBytes:(Ljava/lang/String;)[B
      75: aload_1
      76: aload_0
      77: getfield      #4                  // Field timestamp:J
      80: getstatic     #30                 // Field org/apache/hadoop/hbase/KeyValue$Type.DeleteFamilyVersion:Lorg/apache/hadoop/hbase/KeyValue$Type;
      83: invokespecial #15                 // Method org/apache/hadoop/hbase/KeyValue."<init>":([B[B[BJLorg/apache/hadoop/hbase/KeyValue$Type;)V
      86: astore        5
      88: aload_0
      89: getfield      #8                  // Field sdt:Lorg/apache/hadoop/hbase/regionserver/querymatcher/ScanDeleteTracker;
      92: aload         5
      94: invokevirtual #17                 // Method org/apache/hadoop/hbase/regionserver/querymatcher/ScanDeleteTracker.isDeleted:(Lorg/apache/hadoop/hbase/Cell;)Lorg/apache/hadoop/hbase/regionserver/querymatcher/DeleteTracker$DeleteResult;
      97: astore        6
      99: getstatic     #31                 // Field org/apache/hadoop/hbase/regionserver/querymatcher/DeleteTracker$DeleteResult.FAMILY_VERSION_DELETED:Lorg/apache/hadoop/hbase/regionserver/querymatcher/DeleteTracker$DeleteResult;
     102: aload         6
     104: invokestatic  #19                 // Method org/junit/Assert.assertEquals:(Ljava/lang/Object;Ljava/lang/Object;)V
     107: new           #9                  // class org/apache/hadoop/hbase/KeyValue
     110: dup
     111: ldc           #10                 // String row
     113: invokestatic  #11                 // Method org/apache/hadoop/hbase/util/Bytes.toBytes:(Ljava/lang/String;)[B
     116: ldc           #12                 // String f
     118: invokestatic  #11                 // Method org/apache/hadoop/hbase/util/Bytes.toBytes:(Ljava/lang/String;)[B
     121: aload_2
     122: aload_0
     123: getfield      #4                  // Field timestamp:J
     126: getstatic     #30                 // Field org/apache/hadoop/hbase/KeyValue$Type.DeleteFamilyVersion:Lorg/apache/hadoop/hbase/KeyValue$Type;
     129: invokespecial #15                 // Method org/apache/hadoop/hbase/KeyValue."<init>":([B[B[BJLorg/apache/hadoop/hbase/KeyValue$Type;)V
     132: astore        5
     134: aload_0
     135: getfield      #8                  // Field sdt:Lorg/apache/hadoop/hbase/regionserver/querymatcher/ScanDeleteTracker;
     138: aload         5
     140: invokevirtual #17                 // Method org/apache/hadoop/hbase/regionserver/querymatcher/ScanDeleteTracker.isDeleted:(Lorg/apache/hadoop/hbase/Cell;)Lorg/apache/hadoop/hbase/regionserver/querymatcher/DeleteTracker$DeleteResult;
     143: astore        6
     145: getstatic     #31                 // Field org/apache/hadoop/hbase/regionserver/querymatcher/DeleteTracker$DeleteResult.FAMILY_VERSION_DELETED:Lorg/apache/hadoop/hbase/regionserver/querymatcher/DeleteTracker$DeleteResult;
     148: aload         6
     150: invokestatic  #19                 // Method org/junit/Assert.assertEquals:(Ljava/lang/Object;Ljava/lang/Object;)V
     153: new           #9                  // class org/apache/hadoop/hbase/KeyValue
     156: dup
     157: ldc           #10                 // String row
     159: invokestatic  #11                 // Method org/apache/hadoop/hbase/util/Bytes.toBytes:(Ljava/lang/String;)[B
     162: ldc           #12                 // String f
     164: invokestatic  #11                 // Method org/apache/hadoop/hbase/util/Bytes.toBytes:(Ljava/lang/String;)[B
     167: aload_3
     168: aload_0
     169: getfield      #4                  // Field timestamp:J
     172: getstatic     #30                 // Field org/apache/hadoop/hbase/KeyValue$Type.DeleteFamilyVersion:Lorg/apache/hadoop/hbase/KeyValue$Type;
     175: invokespecial #15                 // Method org/apache/hadoop/hbase/KeyValue."<init>":([B[B[BJLorg/apache/hadoop/hbase/KeyValue$Type;)V
     178: astore        5
     180: aload_0
     181: getfield      #8                  // Field sdt:Lorg/apache/hadoop/hbase/regionserver/querymatcher/ScanDeleteTracker;
     184: aload         5
     186: invokevirtual #17                 // Method org/apache/hadoop/hbase/regionserver/querymatcher/ScanDeleteTracker.isDeleted:(Lorg/apache/hadoop/hbase/Cell;)Lorg/apache/hadoop/hbase/regionserver/querymatcher/DeleteTracker$DeleteResult;
     189: astore        6
     191: getstatic     #31                 // Field org/apache/hadoop/hbase/regionserver/querymatcher/DeleteTracker$DeleteResult.FAMILY_VERSION_DELETED:Lorg/apache/hadoop/hbase/regionserver/querymatcher/DeleteTracker$DeleteResult;
     194: aload         6
     196: invokestatic  #19                 // Method org/junit/Assert.assertEquals:(Ljava/lang/Object;Ljava/lang/Object;)V
     199: new           #9                  // class org/apache/hadoop/hbase/KeyValue
     202: dup
     203: ldc           #10                 // String row
     205: invokestatic  #11                 // Method org/apache/hadoop/hbase/util/Bytes.toBytes:(Ljava/lang/String;)[B
     208: ldc           #12                 // String f
     210: invokestatic  #11                 // Method org/apache/hadoop/hbase/util/Bytes.toBytes:(Ljava/lang/String;)[B
     213: aload         4
     215: aload_0
     216: getfield      #4                  // Field timestamp:J
     219: getstatic     #30                 // Field org/apache/hadoop/hbase/KeyValue$Type.DeleteFamilyVersion:Lorg/apache/hadoop/hbase/KeyValue$Type;
     222: invokespecial #15                 // Method org/apache/hadoop/hbase/KeyValue."<init>":([B[B[BJLorg/apache/hadoop/hbase/KeyValue$Type;)V
     225: astore        5
     227: aload_0
     228: getfield      #8                  // Field sdt:Lorg/apache/hadoop/hbase/regionserver/querymatcher/ScanDeleteTracker;
     231: aload         5
     233: invokevirtual #17                 // Method org/apache/hadoop/hbase/regionserver/querymatcher/ScanDeleteTracker.isDeleted:(Lorg/apache/hadoop/hbase/Cell;)Lorg/apache/hadoop/hbase/regionserver/querymatcher/DeleteTracker$DeleteResult;
     236: astore        6
     238: getstatic     #31                 // Field org/apache/hadoop/hbase/regionserver/querymatcher/DeleteTracker$DeleteResult.FAMILY_VERSION_DELETED:Lorg/apache/hadoop/hbase/regionserver/querymatcher/DeleteTracker$DeleteResult;
     241: aload         6
     243: invokestatic  #19                 // Method org/junit/Assert.assertEquals:(Ljava/lang/Object;Ljava/lang/Object;)V
     246: new           #9                  // class org/apache/hadoop/hbase/KeyValue
     249: dup
     250: ldc           #10                 // String row
     252: invokestatic  #11                 // Method org/apache/hadoop/hbase/util/Bytes.toBytes:(Ljava/lang/String;)[B
     255: ldc           #12                 // String f
     257: invokestatic  #11                 // Method org/apache/hadoop/hbase/util/Bytes.toBytes:(Ljava/lang/String;)[B
     260: aload_1
     261: aload_0
     262: getfield      #4                  // Field timestamp:J
     265: ldc2_w        #32                 // long 3l
     268: ladd
     269: getstatic     #30                 // Field org/apache/hadoop/hbase/KeyValue$Type.DeleteFamilyVersion:Lorg/apache/hadoop/hbase/KeyValue$Type;
     272: invokespecial #15                 // Method org/apache/hadoop/hbase/KeyValue."<init>":([B[B[BJLorg/apache/hadoop/hbase/KeyValue$Type;)V
     275: astore        5
     277: aload_0
     278: getfield      #8                  // Field sdt:Lorg/apache/hadoop/hbase/regionserver/querymatcher/ScanDeleteTracker;
     281: aload         5
     283: invokevirtual #17                 // Method org/apache/hadoop/hbase/regionserver/querymatcher/ScanDeleteTracker.isDeleted:(Lorg/apache/hadoop/hbase/Cell;)Lorg/apache/hadoop/hbase/regionserver/querymatcher/DeleteTracker$DeleteResult;
     286: astore        6
     288: getstatic     #34                 // Field org/apache/hadoop/hbase/regionserver/querymatcher/DeleteTracker$DeleteResult.NOT_DELETED:Lorg/apache/hadoop/hbase/regionserver/querymatcher/DeleteTracker$DeleteResult;
     291: aload         6
     293: invokestatic  #19                 // Method org/junit/Assert.assertEquals:(Ljava/lang/Object;Ljava/lang/Object;)V
     296: new           #9                  // class org/apache/hadoop/hbase/KeyValue
     299: dup
     300: ldc           #10                 // String row
     302: invokestatic  #11                 // Method org/apache/hadoop/hbase/util/Bytes.toBytes:(Ljava/lang/String;)[B
     305: ldc           #12                 // String f
     307: invokestatic  #11                 // Method org/apache/hadoop/hbase/util/Bytes.toBytes:(Ljava/lang/String;)[B
     310: aload_2
     311: aload_0
     312: getfield      #4                  // Field timestamp:J
     315: ldc2_w        #35                 // long 2l
     318: lsub
     319: getstatic     #30                 // Field org/apache/hadoop/hbase/KeyValue$Type.DeleteFamilyVersion:Lorg/apache/hadoop/hbase/KeyValue$Type;
     322: invokespecial #15                 // Method org/apache/hadoop/hbase/KeyValue."<init>":([B[B[BJLorg/apache/hadoop/hbase/KeyValue$Type;)V
     325: astore        5
     327: aload_0
     328: getfield      #8                  // Field sdt:Lorg/apache/hadoop/hbase/regionserver/querymatcher/ScanDeleteTracker;
     331: aload         5
     333: invokevirtual #17                 // Method org/apache/hadoop/hbase/regionserver/querymatcher/ScanDeleteTracker.isDeleted:(Lorg/apache/hadoop/hbase/Cell;)Lorg/apache/hadoop/hbase/regionserver/querymatcher/DeleteTracker$DeleteResult;
     336: astore        6
     338: getstatic     #34                 // Field org/apache/hadoop/hbase/regionserver/querymatcher/DeleteTracker$DeleteResult.NOT_DELETED:Lorg/apache/hadoop/hbase/regionserver/querymatcher/DeleteTracker$DeleteResult;
     341: aload         6
     343: invokestatic  #19                 // Method org/junit/Assert.assertEquals:(Ljava/lang/Object;Ljava/lang/Object;)V
     346: new           #9                  // class org/apache/hadoop/hbase/KeyValue
     349: dup
     350: ldc           #10                 // String row
     352: invokestatic  #11                 // Method org/apache/hadoop/hbase/util/Bytes.toBytes:(Ljava/lang/String;)[B
     355: ldc           #12                 // String f
     357: invokestatic  #11                 // Method org/apache/hadoop/hbase/util/Bytes.toBytes:(Ljava/lang/String;)[B
     360: aload_3
     361: aload_0
     362: getfield      #4                  // Field timestamp:J
     365: ldc2_w        #21                 // long 5l
     368: lsub
     369: getstatic     #30                 // Field org/apache/hadoop/hbase/KeyValue$Type.DeleteFamilyVersion:Lorg/apache/hadoop/hbase/KeyValue$Type;
     372: invokespecial #15                 // Method org/apache/hadoop/hbase/KeyValue."<init>":([B[B[BJLorg/apache/hadoop/hbase/KeyValue$Type;)V
     375: astore        5
     377: aload_0
     378: getfield      #8                  // Field sdt:Lorg/apache/hadoop/hbase/regionserver/querymatcher/ScanDeleteTracker;
     381: aload         5
     383: invokevirtual #17                 // Method org/apache/hadoop/hbase/regionserver/querymatcher/ScanDeleteTracker.isDeleted:(Lorg/apache/hadoop/hbase/Cell;)Lorg/apache/hadoop/hbase/regionserver/querymatcher/DeleteTracker$DeleteResult;
     386: astore        6
     388: getstatic     #34                 // Field org/apache/hadoop/hbase/regionserver/querymatcher/DeleteTracker$DeleteResult.NOT_DELETED:Lorg/apache/hadoop/hbase/regionserver/querymatcher/DeleteTracker$DeleteResult;
     391: aload         6
     393: invokestatic  #19                 // Method org/junit/Assert.assertEquals:(Ljava/lang/Object;Ljava/lang/Object;)V
     396: new           #9                  // class org/apache/hadoop/hbase/KeyValue
     399: dup
     400: ldc           #10                 // String row
     402: invokestatic  #11                 // Method org/apache/hadoop/hbase/util/Bytes.toBytes:(Ljava/lang/String;)[B
     405: ldc           #12                 // String f
     407: invokestatic  #11                 // Method org/apache/hadoop/hbase/util/Bytes.toBytes:(Ljava/lang/String;)[B
     410: aload         4
     412: aload_0
     413: getfield      #4                  // Field timestamp:J
     416: ldc2_w        #37                 // long 8l
     419: ladd
     420: getstatic     #30                 // Field org/apache/hadoop/hbase/KeyValue$Type.DeleteFamilyVersion:Lorg/apache/hadoop/hbase/KeyValue$Type;
     423: invokespecial #15                 // Method org/apache/hadoop/hbase/KeyValue."<init>":([B[B[BJLorg/apache/hadoop/hbase/KeyValue$Type;)V
     426: astore        5
     428: aload_0
     429: getfield      #8                  // Field sdt:Lorg/apache/hadoop/hbase/regionserver/querymatcher/ScanDeleteTracker;
     432: aload         5
     434: invokevirtual #17                 // Method org/apache/hadoop/hbase/regionserver/querymatcher/ScanDeleteTracker.isDeleted:(Lorg/apache/hadoop/hbase/Cell;)Lorg/apache/hadoop/hbase/regionserver/querymatcher/DeleteTracker$DeleteResult;
     437: astore        6
     439: getstatic     #34                 // Field org/apache/hadoop/hbase/regionserver/querymatcher/DeleteTracker$DeleteResult.NOT_DELETED:Lorg/apache/hadoop/hbase/regionserver/querymatcher/DeleteTracker$DeleteResult;
     442: aload         6
     444: invokestatic  #19                 // Method org/junit/Assert.assertEquals:(Ljava/lang/Object;Ljava/lang/Object;)V
     447: return

  public void testDeleteDeleteColumn();
    Code:
       0: ldc           #13                 // String qualifier
       2: invokestatic  #11                 // Method org/apache/hadoop/hbase/util/Bytes.toBytes:(Ljava/lang/String;)[B
       5: astore_1
       6: new           #9                  // class org/apache/hadoop/hbase/KeyValue
       9: dup
      10: ldc           #10                 // String row
      12: invokestatic  #11                 // Method org/apache/hadoop/hbase/util/Bytes.toBytes:(Ljava/lang/String;)[B
      15: ldc           #12                 // String f
      17: invokestatic  #11                 // Method org/apache/hadoop/hbase/util/Bytes.toBytes:(Ljava/lang/String;)[B
      20: aload_1
      21: aload_0
      22: getfield      #4                  // Field timestamp:J
      25: getstatic     #14                 // Field org/apache/hadoop/hbase/KeyValue$Type.Delete:Lorg/apache/hadoop/hbase/KeyValue$Type;
      28: invokespecial #15                 // Method org/apache/hadoop/hbase/KeyValue."<init>":([B[B[BJLorg/apache/hadoop/hbase/KeyValue$Type;)V
      31: astore_2
      32: aload_0
      33: getfield      #8                  // Field sdt:Lorg/apache/hadoop/hbase/regionserver/querymatcher/ScanDeleteTracker;
      36: aload_2
      37: invokevirtual #16                 // Method org/apache/hadoop/hbase/regionserver/querymatcher/ScanDeleteTracker.add:(Lorg/apache/hadoop/hbase/Cell;)V
      40: aload_0
      41: dup
      42: getfield      #4                  // Field timestamp:J
      45: ldc2_w        #21                 // long 5l
      48: lsub
      49: putfield      #4                  // Field timestamp:J
      52: new           #9                  // class org/apache/hadoop/hbase/KeyValue
      55: dup
      56: ldc           #10                 // String row
      58: invokestatic  #11                 // Method org/apache/hadoop/hbase/util/Bytes.toBytes:(Ljava/lang/String;)[B
      61: ldc           #12                 // String f
      63: invokestatic  #11                 // Method org/apache/hadoop/hbase/util/Bytes.toBytes:(Ljava/lang/String;)[B
      66: aload_1
      67: aload_0
      68: getfield      #4                  // Field timestamp:J
      71: getstatic     #20                 // Field org/apache/hadoop/hbase/KeyValue$Type.DeleteColumn:Lorg/apache/hadoop/hbase/KeyValue$Type;
      74: invokespecial #15                 // Method org/apache/hadoop/hbase/KeyValue."<init>":([B[B[BJLorg/apache/hadoop/hbase/KeyValue$Type;)V
      77: astore_2
      78: aload_0
      79: getfield      #8                  // Field sdt:Lorg/apache/hadoop/hbase/regionserver/querymatcher/ScanDeleteTracker;
      82: aload_2
      83: invokevirtual #16                 // Method org/apache/hadoop/hbase/regionserver/querymatcher/ScanDeleteTracker.add:(Lorg/apache/hadoop/hbase/Cell;)V
      86: aload_0
      87: dup
      88: getfield      #4                  // Field timestamp:J
      91: ldc2_w        #21                 // long 5l
      94: lsub
      95: putfield      #4                  // Field timestamp:J
      98: new           #9                  // class org/apache/hadoop/hbase/KeyValue
     101: dup
     102: ldc           #10                 // String row
     104: invokestatic  #11                 // Method org/apache/hadoop/hbase/util/Bytes.toBytes:(Ljava/lang/String;)[B
     107: ldc           #12                 // String f
     109: invokestatic  #11                 // Method org/apache/hadoop/hbase/util/Bytes.toBytes:(Ljava/lang/String;)[B
     112: aload_1
     113: aload_0
     114: getfield      #4                  // Field timestamp:J
     117: getstatic     #20                 // Field org/apache/hadoop/hbase/KeyValue$Type.DeleteColumn:Lorg/apache/hadoop/hbase/KeyValue$Type;
     120: invokespecial #15                 // Method org/apache/hadoop/hbase/KeyValue."<init>":([B[B[BJLorg/apache/hadoop/hbase/KeyValue$Type;)V
     123: astore_2
     124: aload_0
     125: getfield      #8                  // Field sdt:Lorg/apache/hadoop/hbase/regionserver/querymatcher/ScanDeleteTracker;
     128: aload_2
     129: invokevirtual #17                 // Method org/apache/hadoop/hbase/regionserver/querymatcher/ScanDeleteTracker.isDeleted:(Lorg/apache/hadoop/hbase/Cell;)Lorg/apache/hadoop/hbase/regionserver/querymatcher/DeleteTracker$DeleteResult;
     132: astore_3
     133: getstatic     #23                 // Field org/apache/hadoop/hbase/regionserver/querymatcher/DeleteTracker$DeleteResult.COLUMN_DELETED:Lorg/apache/hadoop/hbase/regionserver/querymatcher/DeleteTracker$DeleteResult;
     136: aload_3
     137: invokestatic  #19                 // Method org/junit/Assert.assertEquals:(Ljava/lang/Object;Ljava/lang/Object;)V
     140: return

  public void testDeleteColumnDelete();
    Code:
       0: ldc           #13                 // String qualifier
       2: invokestatic  #11                 // Method org/apache/hadoop/hbase/util/Bytes.toBytes:(Ljava/lang/String;)[B
       5: astore_1
       6: new           #9                  // class org/apache/hadoop/hbase/KeyValue
       9: dup
      10: ldc           #10                 // String row
      12: invokestatic  #11                 // Method org/apache/hadoop/hbase/util/Bytes.toBytes:(Ljava/lang/String;)[B
      15: ldc           #12                 // String f
      17: invokestatic  #11                 // Method org/apache/hadoop/hbase/util/Bytes.toBytes:(Ljava/lang/String;)[B
      20: aload_1
      21: aload_0
      22: getfield      #4                  // Field timestamp:J
      25: getstatic     #20                 // Field org/apache/hadoop/hbase/KeyValue$Type.DeleteColumn:Lorg/apache/hadoop/hbase/KeyValue$Type;
      28: invokespecial #15                 // Method org/apache/hadoop/hbase/KeyValue."<init>":([B[B[BJLorg/apache/hadoop/hbase/KeyValue$Type;)V
      31: astore_2
      32: aload_0
      33: getfield      #8                  // Field sdt:Lorg/apache/hadoop/hbase/regionserver/querymatcher/ScanDeleteTracker;
      36: aload_2
      37: invokevirtual #16                 // Method org/apache/hadoop/hbase/regionserver/querymatcher/ScanDeleteTracker.add:(Lorg/apache/hadoop/hbase/Cell;)V
      40: ldc           #26                 // String qualifier1
      42: invokestatic  #11                 // Method org/apache/hadoop/hbase/util/Bytes.toBytes:(Ljava/lang/String;)[B
      45: astore_1
      46: new           #9                  // class org/apache/hadoop/hbase/KeyValue
      49: dup
      50: ldc           #10                 // String row
      52: invokestatic  #11                 // Method org/apache/hadoop/hbase/util/Bytes.toBytes:(Ljava/lang/String;)[B
      55: ldc           #12                 // String f
      57: invokestatic  #11                 // Method org/apache/hadoop/hbase/util/Bytes.toBytes:(Ljava/lang/String;)[B
      60: aload_1
      61: aload_0
      62: getfield      #4                  // Field timestamp:J
      65: getstatic     #14                 // Field org/apache/hadoop/hbase/KeyValue$Type.Delete:Lorg/apache/hadoop/hbase/KeyValue$Type;
      68: invokespecial #15                 // Method org/apache/hadoop/hbase/KeyValue."<init>":([B[B[BJLorg/apache/hadoop/hbase/KeyValue$Type;)V
      71: astore_2
      72: aload_0
      73: getfield      #8                  // Field sdt:Lorg/apache/hadoop/hbase/regionserver/querymatcher/ScanDeleteTracker;
      76: aload_2
      77: invokevirtual #16                 // Method org/apache/hadoop/hbase/regionserver/querymatcher/ScanDeleteTracker.add:(Lorg/apache/hadoop/hbase/Cell;)V
      80: aload_0
      81: getfield      #8                  // Field sdt:Lorg/apache/hadoop/hbase/regionserver/querymatcher/ScanDeleteTracker;
      84: aload_2
      85: invokevirtual #17                 // Method org/apache/hadoop/hbase/regionserver/querymatcher/ScanDeleteTracker.isDeleted:(Lorg/apache/hadoop/hbase/Cell;)Lorg/apache/hadoop/hbase/regionserver/querymatcher/DeleteTracker$DeleteResult;
      88: astore_3
      89: getstatic     #18                 // Field org/apache/hadoop/hbase/regionserver/querymatcher/DeleteTracker$DeleteResult.VERSION_DELETED:Lorg/apache/hadoop/hbase/regionserver/querymatcher/DeleteTracker$DeleteResult;
      92: aload_3
      93: invokestatic  #19                 // Method org/junit/Assert.assertEquals:(Ljava/lang/Object;Ljava/lang/Object;)V
      96: return

  public void testDeleteKeepDelete();
    Code:
       0: ldc           #13                 // String qualifier
       2: invokestatic  #11                 // Method org/apache/hadoop/hbase/util/Bytes.toBytes:(Ljava/lang/String;)[B
       5: astore_1
       6: new           #9                  // class org/apache/hadoop/hbase/KeyValue
       9: dup
      10: ldc           #10                 // String row
      12: invokestatic  #11                 // Method org/apache/hadoop/hbase/util/Bytes.toBytes:(Ljava/lang/String;)[B
      15: ldc           #12                 // String f
      17: invokestatic  #11                 // Method org/apache/hadoop/hbase/util/Bytes.toBytes:(Ljava/lang/String;)[B
      20: aload_1
      21: aload_0
      22: getfield      #4                  // Field timestamp:J
      25: getstatic     #14                 // Field org/apache/hadoop/hbase/KeyValue$Type.Delete:Lorg/apache/hadoop/hbase/KeyValue$Type;
      28: invokespecial #15                 // Method org/apache/hadoop/hbase/KeyValue."<init>":([B[B[BJLorg/apache/hadoop/hbase/KeyValue$Type;)V
      31: astore_2
      32: aload_0
      33: getfield      #8                  // Field sdt:Lorg/apache/hadoop/hbase/regionserver/querymatcher/ScanDeleteTracker;
      36: aload_2
      37: invokevirtual #16                 // Method org/apache/hadoop/hbase/regionserver/querymatcher/ScanDeleteTracker.add:(Lorg/apache/hadoop/hbase/Cell;)V
      40: aload_0
      41: getfield      #8                  // Field sdt:Lorg/apache/hadoop/hbase/regionserver/querymatcher/ScanDeleteTracker;
      44: aload_2
      45: invokevirtual #17                 // Method org/apache/hadoop/hbase/regionserver/querymatcher/ScanDeleteTracker.isDeleted:(Lorg/apache/hadoop/hbase/Cell;)Lorg/apache/hadoop/hbase/regionserver/querymatcher/DeleteTracker$DeleteResult;
      48: pop
      49: iconst_0
      50: invokestatic  #39                 // Method java/lang/Boolean.valueOf:(Z)Ljava/lang/Boolean;
      53: aload_0
      54: getfield      #8                  // Field sdt:Lorg/apache/hadoop/hbase/regionserver/querymatcher/ScanDeleteTracker;
      57: invokevirtual #40                 // Method org/apache/hadoop/hbase/regionserver/querymatcher/ScanDeleteTracker.isEmpty:()Z
      60: invokestatic  #39                 // Method java/lang/Boolean.valueOf:(Z)Ljava/lang/Boolean;
      63: invokestatic  #19                 // Method org/junit/Assert.assertEquals:(Ljava/lang/Object;Ljava/lang/Object;)V
      66: return

  public void testDeleteKeepVersionZero();
    Code:
       0: ldc           #13                 // String qualifier
       2: invokestatic  #11                 // Method org/apache/hadoop/hbase/util/Bytes.toBytes:(Ljava/lang/String;)[B
       5: astore_1
       6: ldc2_w        #2                  // long 10l
       9: lstore_2
      10: lconst_0
      11: lstore        4
      13: aload_0
      14: getfield      #8                  // Field sdt:Lorg/apache/hadoop/hbase/regionserver/querymatcher/ScanDeleteTracker;
      17: invokevirtual #41                 // Method org/apache/hadoop/hbase/regionserver/querymatcher/ScanDeleteTracker.reset:()V
      20: new           #9                  // class org/apache/hadoop/hbase/KeyValue
      23: dup
      24: ldc           #10                 // String row
      26: invokestatic  #11                 // Method org/apache/hadoop/hbase/util/Bytes.toBytes:(Ljava/lang/String;)[B
      29: ldc           #12                 // String f
      31: invokestatic  #11                 // Method org/apache/hadoop/hbase/util/Bytes.toBytes:(Ljava/lang/String;)[B
      34: aload_1
      35: lload_2
      36: getstatic     #14                 // Field org/apache/hadoop/hbase/KeyValue$Type.Delete:Lorg/apache/hadoop/hbase/KeyValue$Type;
      39: invokespecial #15                 // Method org/apache/hadoop/hbase/KeyValue."<init>":([B[B[BJLorg/apache/hadoop/hbase/KeyValue$Type;)V
      42: astore        6
      44: aload_0
      45: getfield      #8                  // Field sdt:Lorg/apache/hadoop/hbase/regionserver/querymatcher/ScanDeleteTracker;
      48: aload         6
      50: invokevirtual #16                 // Method org/apache/hadoop/hbase/regionserver/querymatcher/ScanDeleteTracker.add:(Lorg/apache/hadoop/hbase/Cell;)V
      53: new           #9                  // class org/apache/hadoop/hbase/KeyValue
      56: dup
      57: ldc           #10                 // String row
      59: invokestatic  #11                 // Method org/apache/hadoop/hbase/util/Bytes.toBytes:(Ljava/lang/String;)[B
      62: ldc           #12                 // String f
      64: invokestatic  #11                 // Method org/apache/hadoop/hbase/util/Bytes.toBytes:(Ljava/lang/String;)[B
      67: aload_1
      68: lload         4
      70: getstatic     #14                 // Field org/apache/hadoop/hbase/KeyValue$Type.Delete:Lorg/apache/hadoop/hbase/KeyValue$Type;
      73: invokespecial #15                 // Method org/apache/hadoop/hbase/KeyValue."<init>":([B[B[BJLorg/apache/hadoop/hbase/KeyValue$Type;)V
      76: astore        6
      78: aload_0
      79: getfield      #8                  // Field sdt:Lorg/apache/hadoop/hbase/regionserver/querymatcher/ScanDeleteTracker;
      82: aload         6
      84: invokevirtual #17                 // Method org/apache/hadoop/hbase/regionserver/querymatcher/ScanDeleteTracker.isDeleted:(Lorg/apache/hadoop/hbase/Cell;)Lorg/apache/hadoop/hbase/regionserver/querymatcher/DeleteTracker$DeleteResult;
      87: astore        7
      89: getstatic     #34                 // Field org/apache/hadoop/hbase/regionserver/querymatcher/DeleteTracker$DeleteResult.NOT_DELETED:Lorg/apache/hadoop/hbase/regionserver/querymatcher/DeleteTracker$DeleteResult;
      92: aload         7
      94: invokestatic  #19                 // Method org/junit/Assert.assertEquals:(Ljava/lang/Object;Ljava/lang/Object;)V
      97: return

  static {};
    Code:
       0: ldc           #42                 // class org/apache/hadoop/hbase/regionserver/querymatcher/TestScanDeleteTracker
       2: invokestatic  #43                 // Method org/apache/hadoop/hbase/HBaseClassTestRule.forClass:(Ljava/lang/Class;)Lorg/apache/hadoop/hbase/HBaseClassTestRule;
       5: putstatic     #44                 // Field CLASS_RULE:Lorg/apache/hadoop/hbase/HBaseClassTestRule;
       8: return
}
