Compiled from "TestRetriesExhaustedWithDetailsException.java"
public class org.apache.hadoop.hbase.client.TestRetriesExhaustedWithDetailsException {
  public static final org.apache.hadoop.hbase.HBaseClassTestRule CLASS_RULE;

  public org.junit.rules.TestName name;

  public org.apache.hadoop.hbase.client.TestRetriesExhaustedWithDetailsException();
    Code:
       0: aload_0
       1: invokespecial #1                  // Method java/lang/Object."<init>":()V
       4: aload_0
       5: new           #2                  // class org/junit/rules/TestName
       8: dup
       9: invokespecial #3                  // Method org/junit/rules/TestName."<init>":()V
      12: putfield      #4                  // Field name:Lorg/junit/rules/TestName;
      15: return

  public void testRegionTooBusyException();
    Code:
       0: new           #5                  // class java/util/ArrayList
       3: dup
       4: iconst_1
       5: invokespecial #6                  // Method java/util/ArrayList."<init>":(I)V
       8: astore_1
       9: aload_0
      10: getfield      #4                  // Field name:Lorg/junit/rules/TestName;
      13: invokevirtual #7                  // Method org/junit/rules/TestName.getMethodName:()Ljava/lang/String;
      16: astore_2
      17: aload_1
      18: new           #8                  // class org/apache/hadoop/hbase/RegionTooBusyException
      21: dup
      22: aload_2
      23: invokespecial #9                  // Method org/apache/hadoop/hbase/RegionTooBusyException."<init>":(Ljava/lang/String;)V
      26: invokeinterface #10,  2           // InterfaceMethod java/util/List.add:(Ljava/lang/Object;)Z
      31: pop
      32: new           #5                  // class java/util/ArrayList
      35: dup
      36: iconst_1
      37: invokespecial #6                  // Method java/util/ArrayList."<init>":(I)V
      40: astore_3
      41: aload_3
      42: ldc           #11                 // class org/apache/hadoop/hbase/client/Row
      44: invokestatic  #12                 // Method org/mockito/Mockito.mock:(Ljava/lang/Class;)Ljava/lang/Object;
      47: invokeinterface #10,  2           // InterfaceMethod java/util/List.add:(Ljava/lang/Object;)Z
      52: pop
      53: new           #5                  // class java/util/ArrayList
      56: dup
      57: iconst_1
      58: invokespecial #6                  // Method java/util/ArrayList."<init>":(I)V
      61: astore        4
      63: aload         4
      65: ldc           #13                 // String example.com:1234
      67: invokeinterface #10,  2           // InterfaceMethod java/util/List.add:(Ljava/lang/Object;)Z
      72: pop
      73: new           #14                 // class org/apache/hadoop/hbase/client/RetriesExhaustedWithDetailsException
      76: dup
      77: aload_1
      78: aload_3
      79: aload         4
      81: invokespecial #15                 // Method org/apache/hadoop/hbase/client/RetriesExhaustedWithDetailsException."<init>":(Ljava/util/List;Ljava/util/List;Ljava/util/List;)V
      84: astore        5
      86: aload         5
      88: invokevirtual #16                 // Method org/apache/hadoop/hbase/client/RetriesExhaustedException.toString:()Ljava/lang/String;
      91: aload_2
      92: invokevirtual #17                 // Method java/lang/String.contains:(Ljava/lang/CharSequence;)Z
      95: invokestatic  #18                 // Method org/junit/Assert.assertTrue:(Z)V
      98: return

  static {};
    Code:
       0: ldc           #19                 // class org/apache/hadoop/hbase/client/TestRetriesExhaustedWithDetailsException
       2: invokestatic  #20                 // Method org/apache/hadoop/hbase/HBaseClassTestRule.forClass:(Ljava/lang/Class;)Lorg/apache/hadoop/hbase/HBaseClassTestRule;
       5: putstatic     #21                 // Field CLASS_RULE:Lorg/apache/hadoop/hbase/HBaseClassTestRule;
       8: return
}
