Compiled from "TestAsyncProcess.java"
class org.apache.hadoop.hbase.client.TestAsyncProcess$MyConnectionImpl2 extends org.apache.hadoop.hbase.client.TestAsyncProcess$MyConnectionImpl {
  java.util.List<org.apache.hadoop.hbase.HRegionLocation> hrl;

  final boolean[] usedRegions;

  protected org.apache.hadoop.hbase.client.TestAsyncProcess$MyConnectionImpl2(java.util.List<org.apache.hadoop.hbase.HRegionLocation>, org.apache.hadoop.conf.Configuration) throws java.io.IOException;
    Code:
       0: aload_0
       1: aload_2
       2: invokespecial #1                  // Method org/apache/hadoop/hbase/client/TestAsyncProcess$MyConnectionImpl."<init>":(Lorg/apache/hadoop/conf/Configuration;)V
       5: aload_0
       6: aload_1
       7: putfield      #2                  // Field hrl:Ljava/util/List;
      10: aload_0
      11: aload_1
      12: invokeinterface #3,  1            // InterfaceMethod java/util/List.size:()I
      17: newarray       boolean
      19: putfield      #4                  // Field usedRegions:[Z
      22: return

  public org.apache.hadoop.hbase.RegionLocations locateRegion(org.apache.hadoop.hbase.TableName, byte[], boolean, boolean, int) throws java.io.IOException;
    Code:
       0: iconst_0
       1: istore        6
       3: aload_0
       4: getfield      #2                  // Field hrl:Ljava/util/List;
       7: invokeinterface #5,  1            // InterfaceMethod java/util/List.iterator:()Ljava/util/Iterator;
      12: astore        7
      14: aload         7
      16: invokeinterface #6,  1            // InterfaceMethod java/util/Iterator.hasNext:()Z
      21: ifeq          82
      24: aload         7
      26: invokeinterface #7,  1            // InterfaceMethod java/util/Iterator.next:()Ljava/lang/Object;
      31: checkcast     #8                  // class org/apache/hadoop/hbase/HRegionLocation
      34: astore        8
      36: aload_2
      37: aload         8
      39: invokevirtual #9                  // Method org/apache/hadoop/hbase/HRegionLocation.getRegionInfo:()Lorg/apache/hadoop/hbase/HRegionInfo;
      42: invokevirtual #10                 // Method org/apache/hadoop/hbase/HRegionInfo.getStartKey:()[B
      45: invokestatic  #11                 // Method java/util/Arrays.equals:([B[B)Z
      48: ifeq          76
      51: aload_0
      52: getfield      #4                  // Field usedRegions:[Z
      55: iload         6
      57: iconst_1
      58: bastore
      59: new           #12                 // class org/apache/hadoop/hbase/RegionLocations
      62: dup
      63: iconst_1
      64: anewarray     #8                  // class org/apache/hadoop/hbase/HRegionLocation
      67: dup
      68: iconst_0
      69: aload         8
      71: aastore
      72: invokespecial #13                 // Method org/apache/hadoop/hbase/RegionLocations."<init>":([Lorg/apache/hadoop/hbase/HRegionLocation;)V
      75: areturn
      76: iinc          6, 1
      79: goto          14
      82: aconst_null
      83: areturn
}
