Compiled from "TestRetainAssignmentOnRestart.java"
public class org.apache.hadoop.hbase.master.TestRetainAssignmentOnRestart extends org.apache.hadoop.hbase.master.AbstractTestRestartCluster {
  public static final org.apache.hadoop.hbase.HBaseClassTestRule CLASS_RULE;

  public org.apache.hadoop.hbase.master.TestRetainAssignmentOnRestart();
    Code:
       0: aload_0
       1: invokespecial #1                  // Method org/apache/hadoop/hbase/master/AbstractTestRestartCluster."<init>":()V
       4: return

  protected boolean splitWALCoordinatedByZk();
    Code:
       0: iconst_1
       1: ireturn

  public void test() throws java.lang.Exception;
    Code:
       0: aload_0
       1: getfield      #2                  // Field UTIL:Lorg/apache/hadoop/hbase/HBaseTestingUtility;
       4: iconst_2
       5: invokevirtual #3                  // Method org/apache/hadoop/hbase/HBaseTestingUtility.startMiniCluster:(I)Lorg/apache/hadoop/hbase/MiniHBaseCluster;
       8: pop
       9: aload_0
      10: getfield      #2                  // Field UTIL:Lorg/apache/hadoop/hbase/HBaseTestingUtility;
      13: invokevirtual #4                  // Method org/apache/hadoop/hbase/HBaseTestingUtility.getMiniHBaseCluster:()Lorg/apache/hadoop/hbase/MiniHBaseCluster;
      16: invokevirtual #5                  // Method org/apache/hadoop/hbase/MiniHBaseCluster.getMaster:()Lorg/apache/hadoop/hbase/master/HMaster;
      19: invokevirtual #6                  // Method org/apache/hadoop/hbase/master/HMaster.getMasterRpcServices:()Lorg/apache/hadoop/hbase/master/MasterRpcServices;
      22: iconst_0
      23: invokevirtual #7                  // Method org/apache/hadoop/hbase/master/MasterRpcServices.synchronousBalanceSwitch:(Z)Z
      26: pop
      27: getstatic     #8                  // Field LOG:Lorg/slf4j/Logger;
      30: ldc           #9                  // String \n\nCreating tables
      32: invokeinterface #10,  2           // InterfaceMethod org/slf4j/Logger.info:(Ljava/lang/String;)V
      37: getstatic     #11                 // Field TABLES:[Lorg/apache/hadoop/hbase/TableName;
      40: astore_1
      41: aload_1
      42: arraylength
      43: istore_2
      44: iconst_0
      45: istore_3
      46: iload_3
      47: iload_2
      48: if_icmpge     75
      51: aload_1
      52: iload_3
      53: aaload
      54: astore        4
      56: aload_0
      57: getfield      #2                  // Field UTIL:Lorg/apache/hadoop/hbase/HBaseTestingUtility;
      60: aload         4
      62: getstatic     #12                 // Field FAMILY:[B
      65: invokevirtual #13                 // Method org/apache/hadoop/hbase/HBaseTestingUtility.createTable:(Lorg/apache/hadoop/hbase/TableName;[B)Lorg/apache/hadoop/hbase/client/Table;
      68: pop
      69: iinc          3, 1
      72: goto          46
      75: getstatic     #11                 // Field TABLES:[Lorg/apache/hadoop/hbase/TableName;
      78: astore_1
      79: aload_1
      80: arraylength
      81: istore_2
      82: iconst_0
      83: istore_3
      84: iload_3
      85: iload_2
      86: if_icmpge     109
      89: aload_1
      90: iload_3
      91: aaload
      92: astore        4
      94: aload_0
      95: getfield      #2                  // Field UTIL:Lorg/apache/hadoop/hbase/HBaseTestingUtility;
      98: aload         4
     100: invokevirtual #14                 // Method org/apache/hadoop/hbase/HBaseTestingUtility.waitTableEnabled:(Lorg/apache/hadoop/hbase/TableName;)V
     103: iinc          3, 1
     106: goto          84
     109: aload_0
     110: getfield      #2                  // Field UTIL:Lorg/apache/hadoop/hbase/HBaseTestingUtility;
     113: invokevirtual #4                  // Method org/apache/hadoop/hbase/HBaseTestingUtility.getMiniHBaseCluster:()Lorg/apache/hadoop/hbase/MiniHBaseCluster;
     116: invokevirtual #5                  // Method org/apache/hadoop/hbase/MiniHBaseCluster.getMaster:()Lorg/apache/hadoop/hbase/master/HMaster;
     119: astore_1
     120: aload_0
     121: getfield      #2                  // Field UTIL:Lorg/apache/hadoop/hbase/HBaseTestingUtility;
     124: ldc2_w        #15                 // long 60000l
     127: invokevirtual #17                 // Method org/apache/hadoop/hbase/HBaseTestingUtility.waitUntilNoRegionsInTransition:(J)V
     130: new           #18                 // class org/apache/hadoop/hbase/master/SnapshotOfRegionAssignmentFromMeta
     133: dup
     134: aload_1
     135: invokevirtual #19                 // Method org/apache/hadoop/hbase/master/HMaster.getConnection:()Lorg/apache/hadoop/hbase/client/Connection;
     138: invokespecial #20                 // Method org/apache/hadoop/hbase/master/SnapshotOfRegionAssignmentFromMeta."<init>":(Lorg/apache/hadoop/hbase/client/Connection;)V
     141: astore_2
     142: aload_2
     143: invokevirtual #21                 // Method org/apache/hadoop/hbase/master/SnapshotOfRegionAssignmentFromMeta.initialize:()V
     146: aload_2
     147: invokevirtual #22                 // Method org/apache/hadoop/hbase/master/SnapshotOfRegionAssignmentFromMeta.getRegionToRegionServerMap:()Ljava/util/Map;
     150: astore_3
     151: aload_0
     152: getfield      #2                  // Field UTIL:Lorg/apache/hadoop/hbase/HBaseTestingUtility;
     155: invokevirtual #23                 // Method org/apache/hadoop/hbase/HBaseTestingUtility.getHBaseCluster:()Lorg/apache/hadoop/hbase/MiniHBaseCluster;
     158: astore        4
     160: aload         4
     162: invokevirtual #24                 // Method org/apache/hadoop/hbase/MiniHBaseCluster.getLiveRegionServerThreads:()Ljava/util/List;
     165: astore        5
     167: ldc2_w        #25                 // long 2l
     170: aload         5
     172: invokeinterface #27,  1           // InterfaceMethod java/util/List.size:()I
     177: i2l
     178: invokestatic  #28                 // Method org/junit/Assert.assertEquals:(JJ)V
     181: iconst_3
     182: newarray       int
     184: astore        6
     186: iconst_0
     187: istore        7
     189: iload         7
     191: iconst_2
     192: if_icmpge     227
     195: aload         6
     197: iload         7
     199: aload         5
     201: iload         7
     203: invokeinterface #29,  2           // InterfaceMethod java/util/List.get:(I)Ljava/lang/Object;
     208: checkcast     #30                 // class org/apache/hadoop/hbase/util/JVMClusterUtil$RegionServerThread
     211: invokevirtual #31                 // Method org/apache/hadoop/hbase/util/JVMClusterUtil$RegionServerThread.getRegionServer:()Lorg/apache/hadoop/hbase/regionserver/HRegionServer;
     214: invokevirtual #32                 // Method org/apache/hadoop/hbase/regionserver/HRegionServer.getServerName:()Lorg/apache/hadoop/hbase/ServerName;
     217: invokevirtual #33                 // Method org/apache/hadoop/hbase/ServerName.getPort:()I
     220: iastore
     221: iinc          7, 1
     224: goto          189
     227: aload         6
     229: iconst_2
     230: aload         4
     232: invokevirtual #5                  // Method org/apache/hadoop/hbase/MiniHBaseCluster.getMaster:()Lorg/apache/hadoop/hbase/master/HMaster;
     235: invokevirtual #34                 // Method org/apache/hadoop/hbase/master/HMaster.getServerName:()Lorg/apache/hadoop/hbase/ServerName;
     238: invokevirtual #33                 // Method org/apache/hadoop/hbase/ServerName.getPort:()I
     241: iastore
     242: aload_3
     243: invokeinterface #35,  1           // InterfaceMethod java/util/Map.values:()Ljava/util/Collection;
     248: invokeinterface #36,  1           // InterfaceMethod java/util/Collection.iterator:()Ljava/util/Iterator;
     253: astore        7
     255: aload         7
     257: invokeinterface #37,  1           // InterfaceMethod java/util/Iterator.hasNext:()Z
     262: ifeq          328
     265: aload         7
     267: invokeinterface #38,  1           // InterfaceMethod java/util/Iterator.next:()Ljava/lang/Object;
     272: checkcast     #39                 // class org/apache/hadoop/hbase/ServerName
     275: astore        8
     277: iconst_0
     278: istore        9
     280: iconst_0
     281: istore        10
     283: iload         10
     285: iconst_3
     286: if_icmpge     320
     289: iload         9
     291: ifne          320
     294: aload         8
     296: invokevirtual #33                 // Method org/apache/hadoop/hbase/ServerName.getPort:()I
     299: aload         6
     301: iload         10
     303: iaload
     304: if_icmpne     311
     307: iconst_1
     308: goto          312
     311: iconst_0
     312: istore        9
     314: iinc          10, 1
     317: goto          283
     320: iload         9
     322: invokestatic  #40                 // Method org/junit/Assert.assertTrue:(Z)V
     325: goto          255
     328: getstatic     #8                  // Field LOG:Lorg/slf4j/Logger;
     331: ldc           #41                 // String \n\nShutting down HBase cluster
     333: invokeinterface #10,  2           // InterfaceMethod org/slf4j/Logger.info:(Ljava/lang/String;)V
     338: aload         4
     340: iconst_0
     341: invokevirtual #42                 // Method org/apache/hadoop/hbase/MiniHBaseCluster.stopMaster:(I)Lorg/apache/hadoop/hbase/util/JVMClusterUtil$MasterThread;
     344: pop
     345: aload         4
     347: invokevirtual #43                 // Method org/apache/hadoop/hbase/MiniHBaseCluster.shutdown:()V
     350: aload         4
     352: invokevirtual #44                 // Method org/apache/hadoop/hbase/MiniHBaseCluster.waitUntilShutDown:()V
     355: getstatic     #8                  // Field LOG:Lorg/slf4j/Logger;
     358: ldc           #45                 // String \n\nSleeping a bit
     360: invokeinterface #10,  2           // InterfaceMethod org/slf4j/Logger.info:(Ljava/lang/String;)V
     365: ldc2_w        #46                 // long 2000l
     368: invokestatic  #48                 // Method java/lang/Thread.sleep:(J)V
     371: getstatic     #8                  // Field LOG:Lorg/slf4j/Logger;
     374: ldc           #49                 // String \n\nStarting cluster the second time with the same ports
     376: invokeinterface #10,  2           // InterfaceMethod org/slf4j/Logger.info:(Ljava/lang/String;)V
     381: aload         4
     383: invokevirtual #50                 // Method org/apache/hadoop/hbase/MiniHBaseCluster.getConf:()Lorg/apache/hadoop/conf/Configuration;
     386: ldc           #52                 // String hbase.master.wait.on.regionservers.mintostart
     388: iconst_3
     389: invokevirtual #53                 // Method org/apache/hadoop/conf/Configuration.setInt:(Ljava/lang/String;I)V
     392: aload         4
     394: invokevirtual #54                 // Method org/apache/hadoop/hbase/MiniHBaseCluster.startMaster:()Lorg/apache/hadoop/hbase/util/JVMClusterUtil$MasterThread;
     397: invokevirtual #55                 // Method org/apache/hadoop/hbase/util/JVMClusterUtil$MasterThread.getMaster:()Lorg/apache/hadoop/hbase/master/HMaster;
     400: astore_1
     401: iconst_0
     402: istore        7
     404: iload         7
     406: iconst_3
     407: if_icmpge     437
     410: aload         4
     412: invokevirtual #50                 // Method org/apache/hadoop/hbase/MiniHBaseCluster.getConf:()Lorg/apache/hadoop/conf/Configuration;
     415: ldc           #57                 // String hbase.regionserver.port
     417: aload         6
     419: iload         7
     421: iaload
     422: invokevirtual #53                 // Method org/apache/hadoop/conf/Configuration.setInt:(Ljava/lang/String;I)V
     425: aload         4
     427: invokevirtual #58                 // Method org/apache/hadoop/hbase/MiniHBaseCluster.startRegionServer:()Lorg/apache/hadoop/hbase/util/JVMClusterUtil$RegionServerThread;
     430: pop
     431: iinc          7, 1
     434: goto          404
     437: aload_1
     438: invokevirtual #59                 // Method org/apache/hadoop/hbase/master/HMaster.getServerManager:()Lorg/apache/hadoop/hbase/master/ServerManager;
     441: invokevirtual #60                 // Method org/apache/hadoop/hbase/master/ServerManager.getOnlineServersList:()Ljava/util/List;
     444: astore        7
     446: ldc2_w        #61                 // long 3l
     449: aload         7
     451: invokeinterface #27,  1           // InterfaceMethod java/util/List.size:()I
     456: i2l
     457: invokestatic  #28                 // Method org/junit/Assert.assertEquals:(JJ)V
     460: iconst_0
     461: istore        8
     463: iload         8
     465: iconst_3
     466: if_icmpge     536
     469: iconst_0
     470: istore        9
     472: aload         7
     474: invokeinterface #63,  1           // InterfaceMethod java/util/List.iterator:()Ljava/util/Iterator;
     479: astore        10
     481: aload         10
     483: invokeinterface #37,  1           // InterfaceMethod java/util/Iterator.hasNext:()Z
     488: ifeq          525
     491: aload         10
     493: invokeinterface #38,  1           // InterfaceMethod java/util/Iterator.next:()Ljava/lang/Object;
     498: checkcast     #39                 // class org/apache/hadoop/hbase/ServerName
     501: astore        11
     503: aload         11
     505: invokevirtual #33                 // Method org/apache/hadoop/hbase/ServerName.getPort:()I
     508: aload         6
     510: iload         8
     512: iaload
     513: if_icmpne     522
     516: iconst_1
     517: istore        9
     519: goto          525
     522: goto          481
     525: iload         9
     527: invokestatic  #40                 // Method org/junit/Assert.assertTrue:(Z)V
     530: iinc          8, 1
     533: goto          463
     536: getstatic     #11                 // Field TABLES:[Lorg/apache/hadoop/hbase/TableName;
     539: astore        8
     541: aload         8
     543: arraylength
     544: istore        9
     546: iconst_0
     547: istore        10
     549: iload         10
     551: iload         9
     553: if_icmpge     578
     556: aload         8
     558: iload         10
     560: aaload
     561: astore        11
     563: aload_0
     564: getfield      #2                  // Field UTIL:Lorg/apache/hadoop/hbase/HBaseTestingUtility;
     567: aload         11
     569: invokevirtual #64                 // Method org/apache/hadoop/hbase/HBaseTestingUtility.waitTableAvailable:(Lorg/apache/hadoop/hbase/TableName;)V
     572: iinc          10, 1
     575: goto          549
     578: aload_0
     579: getfield      #2                  // Field UTIL:Lorg/apache/hadoop/hbase/HBaseTestingUtility;
     582: ldc2_w        #15                 // long 60000l
     585: invokevirtual #17                 // Method org/apache/hadoop/hbase/HBaseTestingUtility.waitUntilNoRegionsInTransition:(J)V
     588: new           #18                 // class org/apache/hadoop/hbase/master/SnapshotOfRegionAssignmentFromMeta
     591: dup
     592: aload_1
     593: invokevirtual #19                 // Method org/apache/hadoop/hbase/master/HMaster.getConnection:()Lorg/apache/hadoop/hbase/client/Connection;
     596: invokespecial #20                 // Method org/apache/hadoop/hbase/master/SnapshotOfRegionAssignmentFromMeta."<init>":(Lorg/apache/hadoop/hbase/client/Connection;)V
     599: astore_2
     600: aload_2
     601: invokevirtual #21                 // Method org/apache/hadoop/hbase/master/SnapshotOfRegionAssignmentFromMeta.initialize:()V
     604: aload_2
     605: invokevirtual #22                 // Method org/apache/hadoop/hbase/master/SnapshotOfRegionAssignmentFromMeta.getRegionToRegionServerMap:()Ljava/util/Map;
     608: astore        8
     610: aload_3
     611: invokeinterface #65,  1           // InterfaceMethod java/util/Map.size:()I
     616: i2l
     617: aload         8
     619: invokeinterface #65,  1           // InterfaceMethod java/util/Map.size:()I
     624: i2l
     625: invokestatic  #28                 // Method org/junit/Assert.assertEquals:(JJ)V
     628: aload         8
     630: invokeinterface #66,  1           // InterfaceMethod java/util/Map.entrySet:()Ljava/util/Set;
     635: invokeinterface #67,  1           // InterfaceMethod java/util/Set.iterator:()Ljava/util/Iterator;
     640: astore        9
     642: aload         9
     644: invokeinterface #37,  1           // InterfaceMethod java/util/Iterator.hasNext:()Z
     649: ifeq          789
     652: aload         9
     654: invokeinterface #38,  1           // InterfaceMethod java/util/Iterator.next:()Ljava/lang/Object;
     659: checkcast     #68                 // class java/util/Map$Entry
     662: astore        10
     664: aload_3
     665: aload         10
     667: invokeinterface #69,  1           // InterfaceMethod java/util/Map$Entry.getKey:()Ljava/lang/Object;
     672: invokeinterface #70,  2           // InterfaceMethod java/util/Map.get:(Ljava/lang/Object;)Ljava/lang/Object;
     677: checkcast     #39                 // class org/apache/hadoop/hbase/ServerName
     680: astore        11
     682: aload         10
     684: invokeinterface #71,  1           // InterfaceMethod java/util/Map$Entry.getValue:()Ljava/lang/Object;
     689: checkcast     #39                 // class org/apache/hadoop/hbase/ServerName
     692: astore        12
     694: getstatic     #8                  // Field LOG:Lorg/slf4j/Logger;
     697: new           #72                 // class java/lang/StringBuilder
     700: dup
     701: invokespecial #73                 // Method java/lang/StringBuilder."<init>":()V
     704: ldc           #74                 // String Key=
     706: invokevirtual #75                 // Method java/lang/StringBuilder.append:(Ljava/lang/String;)Ljava/lang/StringBuilder;
     709: aload         10
     711: invokeinterface #69,  1           // InterfaceMethod java/util/Map$Entry.getKey:()Ljava/lang/Object;
     716: invokevirtual #76                 // Method java/lang/StringBuilder.append:(Ljava/lang/Object;)Ljava/lang/StringBuilder;
     719: ldc           #77                 // String  oldServer=
     721: invokevirtual #75                 // Method java/lang/StringBuilder.append:(Ljava/lang/String;)Ljava/lang/StringBuilder;
     724: aload         11
     726: invokevirtual #76                 // Method java/lang/StringBuilder.append:(Ljava/lang/Object;)Ljava/lang/StringBuilder;
     729: ldc           #78                 // String , currentServer=
     731: invokevirtual #75                 // Method java/lang/StringBuilder.append:(Ljava/lang/String;)Ljava/lang/StringBuilder;
     734: aload         12
     736: invokevirtual #76                 // Method java/lang/StringBuilder.append:(Ljava/lang/Object;)Ljava/lang/StringBuilder;
     739: invokevirtual #79                 // Method java/lang/StringBuilder.toString:()Ljava/lang/String;
     742: invokeinterface #10,  2           // InterfaceMethod org/slf4j/Logger.info:(Ljava/lang/String;)V
     747: aload         10
     749: invokeinterface #69,  1           // InterfaceMethod java/util/Map$Entry.getKey:()Ljava/lang/Object;
     754: checkcast     #80                 // class org/apache/hadoop/hbase/client/RegionInfo
     757: invokevirtual #81                 // Method java/lang/Object.toString:()Ljava/lang/String;
     760: aload         11
     762: invokevirtual #82                 // Method org/apache/hadoop/hbase/ServerName.getAddress:()Lorg/apache/hadoop/hbase/net/Address;
     765: aload         12
     767: invokevirtual #82                 // Method org/apache/hadoop/hbase/ServerName.getAddress:()Lorg/apache/hadoop/hbase/net/Address;
     770: invokestatic  #83                 // Method org/junit/Assert.assertEquals:(Ljava/lang/String;Ljava/lang/Object;Ljava/lang/Object;)V
     773: aload         11
     775: invokevirtual #84                 // Method org/apache/hadoop/hbase/ServerName.getStartcode:()J
     778: aload         12
     780: invokevirtual #84                 // Method org/apache/hadoop/hbase/ServerName.getStartcode:()J
     783: invokestatic  #85                 // Method org/junit/Assert.assertNotEquals:(JJ)V
     786: goto          642
     789: return

  static {};
    Code:
       0: ldc           #86                 // class org/apache/hadoop/hbase/master/TestRetainAssignmentOnRestart
       2: invokestatic  #87                 // Method org/apache/hadoop/hbase/HBaseClassTestRule.forClass:(Ljava/lang/Class;)Lorg/apache/hadoop/hbase/HBaseClassTestRule;
       5: putstatic     #88                 // Field CLASS_RULE:Lorg/apache/hadoop/hbase/HBaseClassTestRule;
       8: ldc           #86                 // class org/apache/hadoop/hbase/master/TestRetainAssignmentOnRestart
      10: invokestatic  #89                 // Method org/slf4j/LoggerFactory.getLogger:(Ljava/lang/Class;)Lorg/slf4j/Logger;
      13: putstatic     #8                  // Field LOG:Lorg/slf4j/Logger;
      16: return
}
