Compiled from "TestVisibilityLabelsReplication.java"
class org.apache.hadoop.hbase.security.visibility.TestVisibilityLabelsReplication$1 implements java.security.PrivilegedExceptionAction<java.lang.Void> {
  final byte[] val$row;

  final java.lang.String[] val$auths;

  final boolean val$nullExpected;

  final int val$expected;

  final java.lang.String val$visString;

  final org.apache.hadoop.hbase.security.visibility.TestVisibilityLabelsReplication this$0;

  org.apache.hadoop.hbase.security.visibility.TestVisibilityLabelsReplication$1(org.apache.hadoop.hbase.security.visibility.TestVisibilityLabelsReplication, byte[], java.lang.String[], boolean, int, java.lang.String);
    Code:
       0: aload_0
       1: aload_1
       2: putfield      #2                  // Field this$0:Lorg/apache/hadoop/hbase/security/visibility/TestVisibilityLabelsReplication;
       5: aload_0
       6: aload_2
       7: putfield      #3                  // Field val$row:[B
      10: aload_0
      11: aload_3
      12: putfield      #4                  // Field val$auths:[Ljava/lang/String;
      15: aload_0
      16: iload         4
      18: putfield      #5                  // Field val$nullExpected:Z
      21: aload_0
      22: iload         5
      24: putfield      #6                  // Field val$expected:I
      27: aload_0
      28: aload         6
      30: putfield      #7                  // Field val$visString:Ljava/lang/String;
      33: aload_0
      34: invokespecial #8                  // Method java/lang/Object."<init>":()V
      37: return

  public java.lang.Void run() throws java.lang.Exception;
    Code:
       0: getstatic     #9                  // Field org/apache/hadoop/hbase/security/visibility/TestVisibilityLabelsReplication.conf1:Lorg/apache/hadoop/conf/Configuration;
       3: invokestatic  #10                 // Method org/apache/hadoop/hbase/client/ConnectionFactory.createConnection:(Lorg/apache/hadoop/conf/Configuration;)Lorg/apache/hadoop/hbase/client/Connection;
       6: astore_1
       7: aconst_null
       8: astore_2
       9: aload_1
      10: getstatic     #11                 // Field org/apache/hadoop/hbase/security/visibility/TestVisibilityLabelsReplication.TABLE_NAME:Lorg/apache/hadoop/hbase/TableName;
      13: invokeinterface #12,  2           // InterfaceMethod org/apache/hadoop/hbase/client/Connection.getTable:(Lorg/apache/hadoop/hbase/TableName;)Lorg/apache/hadoop/hbase/client/Table;
      18: astore_3
      19: aconst_null
      20: astore        4
      22: new           #13                 // class org/apache/hadoop/hbase/client/Get
      25: dup
      26: aload_0
      27: getfield      #3                  // Field val$row:[B
      30: invokespecial #14                 // Method org/apache/hadoop/hbase/client/Get."<init>":([B)V
      33: astore        7
      35: aload         7
      37: new           #15                 // class org/apache/hadoop/hbase/security/visibility/Authorizations
      40: dup
      41: aload_0
      42: getfield      #4                  // Field val$auths:[Ljava/lang/String;
      45: invokespecial #16                 // Method org/apache/hadoop/hbase/security/visibility/Authorizations."<init>":([Ljava/lang/String;)V
      48: invokevirtual #17                 // Method org/apache/hadoop/hbase/client/Get.setAuthorizations:(Lorg/apache/hadoop/hbase/security/visibility/Authorizations;)Lorg/apache/hadoop/hbase/client/Get;
      51: pop
      52: aload_3
      53: aload         7
      55: invokeinterface #18,  2           // InterfaceMethod org/apache/hadoop/hbase/client/Table.get:(Lorg/apache/hadoop/hbase/client/Get;)Lorg/apache/hadoop/hbase/client/Result;
      60: astore        8
      62: aload         8
      64: invokevirtual #19                 // Method org/apache/hadoop/hbase/client/Result.cellScanner:()Lorg/apache/hadoop/hbase/CellScanner;
      67: astore        5
      69: aload         5
      71: invokeinterface #20,  1           // InterfaceMethod org/apache/hadoop/hbase/CellScanner.advance:()Z
      76: istore        9
      78: aload_0
      79: getfield      #5                  // Field val$nullExpected:Z
      82: ifeq          174
      85: iload         9
      87: ifne          94
      90: iconst_1
      91: goto          95
      94: iconst_0
      95: invokestatic  #21                 // Method org/junit/Assert.assertTrue:(Z)V
      98: aconst_null
      99: astore        10
     101: aload_3
     102: ifnull        137
     105: aload         4
     107: ifnull        131
     110: aload_3
     111: invokeinterface #22,  1           // InterfaceMethod org/apache/hadoop/hbase/client/Table.close:()V
     116: goto          137
     119: astore        11
     121: aload         4
     123: aload         11
     125: invokevirtual #24                 // Method java/lang/Throwable.addSuppressed:(Ljava/lang/Throwable;)V
     128: goto          137
     131: aload_3
     132: invokeinterface #22,  1           // InterfaceMethod org/apache/hadoop/hbase/client/Table.close:()V
     137: aload_1
     138: ifnull        171
     141: aload_2
     142: ifnull        165
     145: aload_1
     146: invokeinterface #25,  1           // InterfaceMethod org/apache/hadoop/hbase/client/Connection.close:()V
     151: goto          171
     154: astore        11
     156: aload_2
     157: aload         11
     159: invokevirtual #24                 // Method java/lang/Throwable.addSuppressed:(Ljava/lang/Throwable;)V
     162: goto          171
     165: aload_1
     166: invokeinterface #25,  1           // InterfaceMethod org/apache/hadoop/hbase/client/Connection.close:()V
     171: aload         10
     173: areturn
     174: aload         5
     176: invokeinterface #26,  1           // InterfaceMethod org/apache/hadoop/hbase/CellScanner.current:()Lorg/apache/hadoop/hbase/Cell;
     181: astore        6
     183: aload         6
     185: invokestatic  #27                 // Method org/apache/hadoop/hbase/CellUtil.cloneRow:(Lorg/apache/hadoop/hbase/Cell;)[B
     188: aload_0
     189: getfield      #3                  // Field val$row:[B
     192: invokestatic  #28                 // Method org/junit/Assert.assertArrayEquals:([B[B)V
     195: getstatic     #29                 // Field org/apache/hadoop/hbase/security/visibility/TestVisibilityLabelsReplication$TestCoprocessorForTagsAtSink.tags:Ljava/util/List;
     198: invokeinterface #30,  1           // InterfaceMethod java/util/List.iterator:()Ljava/util/Iterator;
     203: astore        10
     205: aload         10
     207: invokeinterface #31,  1           // InterfaceMethod java/util/Iterator.hasNext:()Z
     212: ifeq          263
     215: aload         10
     217: invokeinterface #32,  1           // InterfaceMethod java/util/Iterator.next:()Ljava/lang/Object;
     222: checkcast     #33                 // class org/apache/hadoop/hbase/Tag
     225: astore        11
     227: invokestatic  #34                 // Method org/apache/hadoop/hbase/security/visibility/TestVisibilityLabelsReplication.access$000:()Lorg/slf4j/Logger;
     230: new           #35                 // class java/lang/StringBuilder
     233: dup
     234: invokespecial #36                 // Method java/lang/StringBuilder."<init>":()V
     237: ldc           #37                 // String The tag type is
     239: invokevirtual #38                 // Method java/lang/StringBuilder.append:(Ljava/lang/String;)Ljava/lang/StringBuilder;
     242: aload         11
     244: invokeinterface #39,  1           // InterfaceMethod org/apache/hadoop/hbase/Tag.getType:()B
     249: invokevirtual #40                 // Method java/lang/StringBuilder.append:(I)Ljava/lang/StringBuilder;
     252: invokevirtual #41                 // Method java/lang/StringBuilder.toString:()Ljava/lang/String;
     255: invokeinterface #42,  2           // InterfaceMethod org/slf4j/Logger.info:(Ljava/lang/String;)V
     260: goto          205
     263: aload_0
     264: getfield      #6                  // Field val$expected:I
     267: i2l
     268: getstatic     #29                 // Field org/apache/hadoop/hbase/security/visibility/TestVisibilityLabelsReplication$TestCoprocessorForTagsAtSink.tags:Ljava/util/List;
     271: invokeinterface #43,  1           // InterfaceMethod java/util/List.size:()I
     276: i2l
     277: invokestatic  #44                 // Method org/junit/Assert.assertEquals:(JJ)V
     280: getstatic     #29                 // Field org/apache/hadoop/hbase/security/visibility/TestVisibilityLabelsReplication$TestCoprocessorForTagsAtSink.tags:Ljava/util/List;
     283: iconst_1
     284: invokeinterface #45,  2           // InterfaceMethod java/util/List.get:(I)Ljava/lang/Object;
     289: checkcast     #33                 // class org/apache/hadoop/hbase/Tag
     292: astore        10
     294: aload         10
     296: invokeinterface #39,  1           // InterfaceMethod org/apache/hadoop/hbase/Tag.getType:()B
     301: bipush        100
     303: if_icmpeq     320
     306: ldc2_w        #47                 // long 4l
     309: aload         10
     311: invokeinterface #39,  1           // InterfaceMethod org/apache/hadoop/hbase/Tag.getType:()B
     316: i2l
     317: invokestatic  #44                 // Method org/junit/Assert.assertEquals:(JJ)V
     320: getstatic     #29                 // Field org/apache/hadoop/hbase/security/visibility/TestVisibilityLabelsReplication$TestCoprocessorForTagsAtSink.tags:Ljava/util/List;
     323: iconst_0
     324: invokeinterface #45,  2           // InterfaceMethod java/util/List.get:(I)Ljava/lang/Object;
     329: checkcast     #33                 // class org/apache/hadoop/hbase/Tag
     332: astore        10
     334: iconst_0
     335: istore        11
     337: getstatic     #29                 // Field org/apache/hadoop/hbase/security/visibility/TestVisibilityLabelsReplication$TestCoprocessorForTagsAtSink.tags:Ljava/util/List;
     340: invokeinterface #30,  1           // InterfaceMethod java/util/List.iterator:()Ljava/util/Iterator;
     345: astore        12
     347: aload         12
     349: invokeinterface #31,  1           // InterfaceMethod java/util/Iterator.hasNext:()Z
     354: ifeq          400
     357: aload         12
     359: invokeinterface #32,  1           // InterfaceMethod java/util/Iterator.next:()Ljava/lang/Object;
     364: checkcast     #33                 // class org/apache/hadoop/hbase/Tag
     367: astore        13
     369: aload         13
     371: invokeinterface #39,  1           // InterfaceMethod org/apache/hadoop/hbase/Tag.getType:()B
     376: bipush        100
     378: if_icmpne     397
     381: ldc           #49                 // String temp
     383: aload         13
     385: invokestatic  #50                 // InterfaceMethod org/apache/hadoop/hbase/Tag.getValueAsString:(Lorg/apache/hadoop/hbase/Tag;)Ljava/lang/String;
     388: invokestatic  #51                 // Method org/junit/Assert.assertEquals:(Ljava/lang/Object;Ljava/lang/Object;)V
     391: iconst_1
     392: istore        11
     394: goto          400
     397: goto          347
     400: aload_0
     401: getfield      #3                  // Field val$row:[B
     404: aload_0
     405: getfield      #7                  // Field val$visString:Ljava/lang/String;
     408: invokestatic  #52                 // Method org/apache/hadoop/hbase/security/visibility/TestVisibilityLabelsReplication.doAssert:([BLjava/lang/String;)V
     411: iload         11
     413: invokestatic  #21                 // Method org/junit/Assert.assertTrue:(Z)V
     416: aconst_null
     417: astore        12
     419: aload_3
     420: ifnull        455
     423: aload         4
     425: ifnull        449
     428: aload_3
     429: invokeinterface #22,  1           // InterfaceMethod org/apache/hadoop/hbase/client/Table.close:()V
     434: goto          455
     437: astore        13
     439: aload         4
     441: aload         13
     443: invokevirtual #24                 // Method java/lang/Throwable.addSuppressed:(Ljava/lang/Throwable;)V
     446: goto          455
     449: aload_3
     450: invokeinterface #22,  1           // InterfaceMethod org/apache/hadoop/hbase/client/Table.close:()V
     455: aload_1
     456: ifnull        489
     459: aload_2
     460: ifnull        483
     463: aload_1
     464: invokeinterface #25,  1           // InterfaceMethod org/apache/hadoop/hbase/client/Connection.close:()V
     469: goto          489
     472: astore        13
     474: aload_2
     475: aload         13
     477: invokevirtual #24                 // Method java/lang/Throwable.addSuppressed:(Ljava/lang/Throwable;)V
     480: goto          489
     483: aload_1
     484: invokeinterface #25,  1           // InterfaceMethod org/apache/hadoop/hbase/client/Connection.close:()V
     489: aload         12
     491: areturn
     492: astore        5
     494: aload         5
     496: astore        4
     498: aload         5
     500: athrow
     501: astore        14
     503: aload_3
     504: ifnull        539
     507: aload         4
     509: ifnull        533
     512: aload_3
     513: invokeinterface #22,  1           // InterfaceMethod org/apache/hadoop/hbase/client/Table.close:()V
     518: goto          539
     521: astore        15
     523: aload         4
     525: aload         15
     527: invokevirtual #24                 // Method java/lang/Throwable.addSuppressed:(Ljava/lang/Throwable;)V
     530: goto          539
     533: aload_3
     534: invokeinterface #22,  1           // InterfaceMethod org/apache/hadoop/hbase/client/Table.close:()V
     539: aload         14
     541: athrow
     542: astore_3
     543: aload_3
     544: astore_2
     545: aload_3
     546: athrow
     547: astore        16
     549: aload_1
     550: ifnull        583
     553: aload_2
     554: ifnull        577
     557: aload_1
     558: invokeinterface #25,  1           // InterfaceMethod org/apache/hadoop/hbase/client/Connection.close:()V
     563: goto          583
     566: astore        17
     568: aload_2
     569: aload         17
     571: invokevirtual #24                 // Method java/lang/Throwable.addSuppressed:(Ljava/lang/Throwable;)V
     574: goto          583
     577: aload_1
     578: invokeinterface #25,  1           // InterfaceMethod org/apache/hadoop/hbase/client/Connection.close:()V
     583: aload         16
     585: athrow
    Exception table:
       from    to  target type
         110   116   119   Class java/lang/Throwable
         145   151   154   Class java/lang/Throwable
         428   434   437   Class java/lang/Throwable
         463   469   472   Class java/lang/Throwable
          22   101   492   Class java/lang/Throwable
         174   419   492   Class java/lang/Throwable
          22   101   501   any
         174   419   501   any
         512   518   521   Class java/lang/Throwable
         492   503   501   any
           9   137   542   Class java/lang/Throwable
         174   455   542   Class java/lang/Throwable
         492   542   542   Class java/lang/Throwable
           9   137   547   any
         174   455   547   any
         557   563   566   Class java/lang/Throwable
         492   549   547   any

  public java.lang.Object run() throws java.lang.Exception;
    Code:
       0: aload_0
       1: invokevirtual #53                 // Method run:()Ljava/lang/Void;
       4: areturn
}
