Compiled from "TestSaslUtil.java"
public class org.apache.hadoop.hbase.security.TestSaslUtil {
  public static final org.apache.hadoop.hbase.HBaseClassTestRule CLASS_RULE;

  public org.junit.rules.ExpectedException exception;

  public org.apache.hadoop.hbase.security.TestSaslUtil();
    Code:
       0: aload_0
       1: invokespecial #1                  // Method java/lang/Object."<init>":()V
       4: aload_0
       5: invokestatic  #2                  // Method org/junit/rules/ExpectedException.none:()Lorg/junit/rules/ExpectedException;
       8: putfield      #3                  // Field exception:Lorg/junit/rules/ExpectedException;
      11: return

  public void testInitSaslProperties();
    Code:
       0: ldc           #4                  // String integrity
       2: invokestatic  #5                  // Method org/apache/hadoop/hbase/security/SaslUtil.initSaslProperties:(Ljava/lang/String;)Ljava/util/Map;
       5: astore_1
       6: ldc           #6                  // String auth-int
       8: aload_1
       9: ldc           #8                  // String javax.security.sasl.qop
      11: invokeinterface #9,  2            // InterfaceMethod java/util/Map.get:(Ljava/lang/Object;)Ljava/lang/Object;
      16: invokestatic  #10                 // Method org/junit/Assert.assertEquals:(Ljava/lang/Object;Ljava/lang/Object;)V
      19: ldc           #11                 // String privacy,authentication
      21: invokestatic  #5                  // Method org/apache/hadoop/hbase/security/SaslUtil.initSaslProperties:(Ljava/lang/String;)Ljava/util/Map;
      24: astore_1
      25: ldc           #12                 // String auth-conf,auth
      27: aload_1
      28: ldc           #8                  // String javax.security.sasl.qop
      30: invokeinterface #9,  2            // InterfaceMethod java/util/Map.get:(Ljava/lang/Object;)Ljava/lang/Object;
      35: invokestatic  #10                 // Method org/junit/Assert.assertEquals:(Ljava/lang/Object;Ljava/lang/Object;)V
      38: ldc           #13                 // String integrity,authentication,privacy
      40: invokestatic  #5                  // Method org/apache/hadoop/hbase/security/SaslUtil.initSaslProperties:(Ljava/lang/String;)Ljava/util/Map;
      43: astore_1
      44: ldc           #14                 // String auth-int,auth,auth-conf
      46: aload_1
      47: ldc           #8                  // String javax.security.sasl.qop
      49: invokeinterface #9,  2            // InterfaceMethod java/util/Map.get:(Ljava/lang/Object;)Ljava/lang/Object;
      54: invokestatic  #10                 // Method org/junit/Assert.assertEquals:(Ljava/lang/Object;Ljava/lang/Object;)V
      57: aload_0
      58: getfield      #3                  // Field exception:Lorg/junit/rules/ExpectedException;
      61: ldc           #15                 // class java/lang/IllegalArgumentException
      63: invokevirtual #16                 // Method org/junit/rules/ExpectedException.expect:(Ljava/lang/Class;)V
      66: ldc           #17                 // String xyz
      68: invokestatic  #5                  // Method org/apache/hadoop/hbase/security/SaslUtil.initSaslProperties:(Ljava/lang/String;)Ljava/util/Map;
      71: astore_1
      72: ldc           #18                 // String auth
      74: aload_1
      75: ldc           #8                  // String javax.security.sasl.qop
      77: invokeinterface #9,  2            // InterfaceMethod java/util/Map.get:(Ljava/lang/Object;)Ljava/lang/Object;
      82: invokestatic  #10                 // Method org/junit/Assert.assertEquals:(Ljava/lang/Object;Ljava/lang/Object;)V
      85: aload_0
      86: getfield      #3                  // Field exception:Lorg/junit/rules/ExpectedException;
      89: ldc           #15                 // class java/lang/IllegalArgumentException
      91: invokevirtual #16                 // Method org/junit/rules/ExpectedException.expect:(Ljava/lang/Class;)V
      94: ldc           #19                 // String
      96: invokestatic  #5                  // Method org/apache/hadoop/hbase/security/SaslUtil.initSaslProperties:(Ljava/lang/String;)Ljava/util/Map;
      99: astore_1
     100: ldc           #18                 // String auth
     102: aload_1
     103: ldc           #8                  // String javax.security.sasl.qop
     105: invokeinterface #9,  2            // InterfaceMethod java/util/Map.get:(Ljava/lang/Object;)Ljava/lang/Object;
     110: invokestatic  #10                 // Method org/junit/Assert.assertEquals:(Ljava/lang/Object;Ljava/lang/Object;)V
     113: return

  static {};
    Code:
       0: ldc           #20                 // class org/apache/hadoop/hbase/security/TestSaslUtil
       2: invokestatic  #21                 // Method org/apache/hadoop/hbase/HBaseClassTestRule.forClass:(Ljava/lang/Class;)Lorg/apache/hadoop/hbase/HBaseClassTestRule;
       5: putstatic     #22                 // Field CLASS_RULE:Lorg/apache/hadoop/hbase/HBaseClassTestRule;
       8: return
}
