Compiled from "TestClientScanner.java"
public class org.apache.hadoop.hbase.client.TestClientScanner {
  public static final org.apache.hadoop.hbase.HBaseClassTestRule CLASS_RULE;

  org.apache.hadoop.hbase.client.Scan scan;

  java.util.concurrent.ExecutorService pool;

  org.apache.hadoop.conf.Configuration conf;

  org.apache.hadoop.hbase.client.ClusterConnection clusterConn;

  org.apache.hadoop.hbase.client.RpcRetryingCallerFactory rpcFactory;

  org.apache.hadoop.hbase.ipc.RpcControllerFactory controllerFactory;

  public org.junit.rules.TestName name;

  public org.apache.hadoop.hbase.client.TestClientScanner();
    Code:
       0: aload_0
       1: invokespecial #1                  // Method java/lang/Object."<init>":()V
       4: aload_0
       5: new           #2                  // class org/junit/rules/TestName
       8: dup
       9: invokespecial #3                  // Method org/junit/rules/TestName."<init>":()V
      12: putfield      #4                  // Field name:Lorg/junit/rules/TestName;
      15: return

  public void setup() throws java.io.IOException;
    Code:
       0: aload_0
       1: ldc           #5                  // class org/apache/hadoop/hbase/client/ClusterConnection
       3: invokestatic  #6                  // Method org/mockito/Mockito.mock:(Ljava/lang/Class;)Ljava/lang/Object;
       6: checkcast     #5                  // class org/apache/hadoop/hbase/client/ClusterConnection
       9: putfield      #7                  // Field clusterConn:Lorg/apache/hadoop/hbase/client/ClusterConnection;
      12: aload_0
      13: ldc           #8                  // class org/apache/hadoop/hbase/client/RpcRetryingCallerFactory
      15: invokestatic  #6                  // Method org/mockito/Mockito.mock:(Ljava/lang/Class;)Ljava/lang/Object;
      18: checkcast     #8                  // class org/apache/hadoop/hbase/client/RpcRetryingCallerFactory
      21: putfield      #9                  // Field rpcFactory:Lorg/apache/hadoop/hbase/client/RpcRetryingCallerFactory;
      24: aload_0
      25: ldc           #10                 // class org/apache/hadoop/hbase/ipc/RpcControllerFactory
      27: invokestatic  #6                  // Method org/mockito/Mockito.mock:(Ljava/lang/Class;)Ljava/lang/Object;
      30: checkcast     #10                 // class org/apache/hadoop/hbase/ipc/RpcControllerFactory
      33: putfield      #11                 // Field controllerFactory:Lorg/apache/hadoop/hbase/ipc/RpcControllerFactory;
      36: aload_0
      37: invokestatic  #12                 // Method java/util/concurrent/Executors.newSingleThreadExecutor:()Ljava/util/concurrent/ExecutorService;
      40: putfield      #13                 // Field pool:Ljava/util/concurrent/ExecutorService;
      43: aload_0
      44: new           #14                 // class org/apache/hadoop/hbase/client/Scan
      47: dup
      48: invokespecial #15                 // Method org/apache/hadoop/hbase/client/Scan."<init>":()V
      51: putfield      #16                 // Field scan:Lorg/apache/hadoop/hbase/client/Scan;
      54: aload_0
      55: new           #17                 // class org/apache/hadoop/conf/Configuration
      58: dup
      59: invokespecial #18                 // Method org/apache/hadoop/conf/Configuration."<init>":()V
      62: putfield      #19                 // Field conf:Lorg/apache/hadoop/conf/Configuration;
      65: aload_0
      66: getfield      #7                  // Field clusterConn:Lorg/apache/hadoop/hbase/client/ClusterConnection;
      69: invokeinterface #20,  1           // InterfaceMethod org/apache/hadoop/hbase/client/ClusterConnection.getConfiguration:()Lorg/apache/hadoop/conf/Configuration;
      74: invokestatic  #21                 // Method org/mockito/Mockito.when:(Ljava/lang/Object;)Lorg/mockito/stubbing/OngoingStubbing;
      77: aload_0
      78: getfield      #19                 // Field conf:Lorg/apache/hadoop/conf/Configuration;
      81: invokeinterface #22,  2           // InterfaceMethod org/mockito/stubbing/OngoingStubbing.thenReturn:(Ljava/lang/Object;)Lorg/mockito/stubbing/OngoingStubbing;
      86: pop
      87: return

  public void teardown();
    Code:
       0: aconst_null
       1: aload_0
       2: getfield      #13                 // Field pool:Ljava/util/concurrent/ExecutorService;
       5: if_acmpeq     18
       8: aload_0
       9: getfield      #13                 // Field pool:Ljava/util/concurrent/ExecutorService;
      12: invokeinterface #23,  1           // InterfaceMethod java/util/concurrent/ExecutorService.shutdownNow:()Ljava/util/List;
      17: pop
      18: return

  public void testNoResultsHint() throws java.io.IOException;
    Code:
       0: iconst_1
       1: anewarray     #24                 // class org/apache/hadoop/hbase/client/Result
       4: astore_1
       5: new           #25                 // class org/apache/hadoop/hbase/KeyValue
       8: dup
       9: ldc           #26                 // String row
      11: invokestatic  #27                 // Method org/apache/hadoop/hbase/util/Bytes.toBytes:(Ljava/lang/String;)[B
      14: ldc           #28                 // String cf
      16: invokestatic  #27                 // Method org/apache/hadoop/hbase/util/Bytes.toBytes:(Ljava/lang/String;)[B
      19: ldc           #29                 // String cq
      21: invokestatic  #27                 // Method org/apache/hadoop/hbase/util/Bytes.toBytes:(Ljava/lang/String;)[B
      24: lconst_1
      25: getstatic     #30                 // Field org/apache/hadoop/hbase/KeyValue$Type.Maximum:Lorg/apache/hadoop/hbase/KeyValue$Type;
      28: invokespecial #31                 // Method org/apache/hadoop/hbase/KeyValue."<init>":([B[B[BJLorg/apache/hadoop/hbase/KeyValue$Type;)V
      31: astore_2
      32: aload_1
      33: iconst_0
      34: iconst_1
      35: anewarray     #32                 // class org/apache/hadoop/hbase/Cell
      38: dup
      39: iconst_0
      40: aload_2
      41: aastore
      42: invokestatic  #33                 // Method org/apache/hadoop/hbase/client/Result.create:([Lorg/apache/hadoop/hbase/Cell;)Lorg/apache/hadoop/hbase/client/Result;
      45: aastore
      46: ldc           #34                 // class org/apache/hadoop/hbase/client/RpcRetryingCaller
      48: invokestatic  #6                  // Method org/mockito/Mockito.mock:(Ljava/lang/Class;)Ljava/lang/Object;
      51: checkcast     #34                 // class org/apache/hadoop/hbase/client/RpcRetryingCaller
      54: astore_3
      55: aload_0
      56: getfield      #9                  // Field rpcFactory:Lorg/apache/hadoop/hbase/client/RpcRetryingCallerFactory;
      59: invokevirtual #35                 // Method org/apache/hadoop/hbase/client/RpcRetryingCallerFactory.newCaller:()Lorg/apache/hadoop/hbase/client/RpcRetryingCaller;
      62: invokestatic  #21                 // Method org/mockito/Mockito.when:(Ljava/lang/Object;)Lorg/mockito/stubbing/OngoingStubbing;
      65: aload_3
      66: invokeinterface #22,  2           // InterfaceMethod org/mockito/stubbing/OngoingStubbing.thenReturn:(Ljava/lang/Object;)Lorg/mockito/stubbing/OngoingStubbing;
      71: pop
      72: aload_3
      73: invokestatic  #36                 // Method org/mockito/Mockito.any:()Ljava/lang/Object;
      76: checkcast     #37                 // class org/apache/hadoop/hbase/client/RetryingCallable
      79: invokestatic  #38                 // Method org/mockito/Mockito.anyInt:()I
      82: invokeinterface #39,  3           // InterfaceMethod org/apache/hadoop/hbase/client/RpcRetryingCaller.callWithoutRetries:(Lorg/apache/hadoop/hbase/client/RetryingCallable;I)Ljava/lang/Object;
      87: invokestatic  #21                 // Method org/mockito/Mockito.when:(Ljava/lang/Object;)Lorg/mockito/stubbing/OngoingStubbing;
      90: new           #40                 // class org/apache/hadoop/hbase/client/TestClientScanner$1
      93: dup
      94: aload_0
      95: aload_1
      96: invokespecial #41                 // Method org/apache/hadoop/hbase/client/TestClientScanner$1."<init>":(Lorg/apache/hadoop/hbase/client/TestClientScanner;[Lorg/apache/hadoop/hbase/client/Result;)V
      99: invokeinterface #42,  2           // InterfaceMethod org/mockito/stubbing/OngoingStubbing.thenAnswer:(Lorg/mockito/stubbing/Answer;)Lorg/mockito/stubbing/OngoingStubbing;
     104: pop
     105: aload_0
     106: getfield      #16                 // Field scan:Lorg/apache/hadoop/hbase/client/Scan;
     109: bipush        100
     111: invokevirtual #43                 // Method org/apache/hadoop/hbase/client/Scan.setCaching:(I)Lorg/apache/hadoop/hbase/client/Scan;
     114: pop
     115: aload_0
     116: getfield      #16                 // Field scan:Lorg/apache/hadoop/hbase/client/Scan;
     119: ldc2_w        #44                 // long 1000000l
     122: invokevirtual #46                 // Method org/apache/hadoop/hbase/client/Scan.setMaxResultSize:(J)Lorg/apache/hadoop/hbase/client/Scan;
     125: pop
     126: new           #47                 // class org/apache/hadoop/hbase/client/TestClientScanner$MockClientScanner
     129: dup
     130: aload_0
     131: getfield      #19                 // Field conf:Lorg/apache/hadoop/conf/Configuration;
     134: aload_0
     135: getfield      #16                 // Field scan:Lorg/apache/hadoop/hbase/client/Scan;
     138: aload_0
     139: getfield      #4                  // Field name:Lorg/junit/rules/TestName;
     142: invokevirtual #48                 // Method org/junit/rules/TestName.getMethodName:()Ljava/lang/String;
     145: invokestatic  #49                 // Method org/apache/hadoop/hbase/TableName.valueOf:(Ljava/lang/String;)Lorg/apache/hadoop/hbase/TableName;
     148: aload_0
     149: getfield      #7                  // Field clusterConn:Lorg/apache/hadoop/hbase/client/ClusterConnection;
     152: aload_0
     153: getfield      #9                  // Field rpcFactory:Lorg/apache/hadoop/hbase/client/RpcRetryingCallerFactory;
     156: aload_0
     157: getfield      #11                 // Field controllerFactory:Lorg/apache/hadoop/hbase/ipc/RpcControllerFactory;
     160: aload_0
     161: getfield      #13                 // Field pool:Ljava/util/concurrent/ExecutorService;
     164: ldc           #51                 // int 2147483647
     166: invokespecial #52                 // Method org/apache/hadoop/hbase/client/TestClientScanner$MockClientScanner."<init>":(Lorg/apache/hadoop/conf/Configuration;Lorg/apache/hadoop/hbase/client/Scan;Lorg/apache/hadoop/hbase/TableName;Lorg/apache/hadoop/hbase/client/ClusterConnection;Lorg/apache/hadoop/hbase/client/RpcRetryingCallerFactory;Lorg/apache/hadoop/hbase/ipc/RpcControllerFactory;Ljava/util/concurrent/ExecutorService;I)V
     169: astore        4
     171: aconst_null
     172: astore        5
     174: aload         4
     176: iconst_1
     177: invokevirtual #53                 // Method org/apache/hadoop/hbase/client/TestClientScanner$MockClientScanner.setRpcFinished:(Z)V
     180: iconst_1
     181: anewarray     #54                 // class java/lang/Object
     184: dup
     185: iconst_0
     186: aload_3
     187: aastore
     188: invokestatic  #55                 // Method org/mockito/Mockito.inOrder:([Ljava/lang/Object;)Lorg/mockito/InOrder;
     191: astore        6
     193: aload         4
     195: invokevirtual #56                 // Method org/apache/hadoop/hbase/client/TestClientScanner$MockClientScanner.loadCache:()V
     198: aload         6
     200: aload_3
     201: iconst_2
     202: invokestatic  #57                 // Method org/mockito/Mockito.times:(I)Lorg/mockito/verification/VerificationMode;
     205: invokeinterface #58,  3           // InterfaceMethod org/mockito/InOrder.verify:(Ljava/lang/Object;Lorg/mockito/verification/VerificationMode;)Ljava/lang/Object;
     210: checkcast     #34                 // class org/apache/hadoop/hbase/client/RpcRetryingCaller
     213: invokestatic  #36                 // Method org/mockito/Mockito.any:()Ljava/lang/Object;
     216: checkcast     #37                 // class org/apache/hadoop/hbase/client/RetryingCallable
     219: invokestatic  #38                 // Method org/mockito/Mockito.anyInt:()I
     222: invokeinterface #39,  3           // InterfaceMethod org/apache/hadoop/hbase/client/RpcRetryingCaller.callWithoutRetries:(Lorg/apache/hadoop/hbase/client/RetryingCallable;I)Ljava/lang/Object;
     227: pop
     228: lconst_1
     229: aload         4
     231: getfield      #59                 // Field org/apache/hadoop/hbase/client/TestClientScanner$MockClientScanner.cache:Ljava/util/Queue;
     234: invokeinterface #60,  1           // InterfaceMethod java/util/Queue.size:()I
     239: i2l
     240: invokestatic  #61                 // Method org/junit/Assert.assertEquals:(JJ)V
     243: aload         4
     245: getfield      #59                 // Field org/apache/hadoop/hbase/client/TestClientScanner$MockClientScanner.cache:Ljava/util/Queue;
     248: invokeinterface #62,  1           // InterfaceMethod java/util/Queue.poll:()Ljava/lang/Object;
     253: checkcast     #24                 // class org/apache/hadoop/hbase/client/Result
     256: astore        7
     258: aload         7
     260: invokestatic  #63                 // Method org/junit/Assert.assertNotNull:(Ljava/lang/Object;)V
     263: aload         7
     265: invokevirtual #64                 // Method org/apache/hadoop/hbase/client/Result.cellScanner:()Lorg/apache/hadoop/hbase/CellScanner;
     268: astore        8
     270: aload         8
     272: invokeinterface #65,  1           // InterfaceMethod org/apache/hadoop/hbase/CellScanner.advance:()Z
     277: invokestatic  #66                 // Method org/junit/Assert.assertTrue:(Z)V
     280: aload_2
     281: aload         8
     283: invokeinterface #67,  1           // InterfaceMethod org/apache/hadoop/hbase/CellScanner.current:()Lorg/apache/hadoop/hbase/Cell;
     288: invokestatic  #68                 // Method org/junit/Assert.assertEquals:(Ljava/lang/Object;Ljava/lang/Object;)V
     291: aload         8
     293: invokeinterface #65,  1           // InterfaceMethod org/apache/hadoop/hbase/CellScanner.advance:()Z
     298: invokestatic  #69                 // Method org/junit/Assert.assertFalse:(Z)V
     301: aload         4
     303: ifnull        388
     306: aload         5
     308: ifnull        331
     311: aload         4
     313: invokevirtual #70                 // Method org/apache/hadoop/hbase/client/TestClientScanner$MockClientScanner.close:()V
     316: goto          388
     319: astore        6
     321: aload         5
     323: aload         6
     325: invokevirtual #72                 // Method java/lang/Throwable.addSuppressed:(Ljava/lang/Throwable;)V
     328: goto          388
     331: aload         4
     333: invokevirtual #70                 // Method org/apache/hadoop/hbase/client/TestClientScanner$MockClientScanner.close:()V
     336: goto          388
     339: astore        6
     341: aload         6
     343: astore        5
     345: aload         6
     347: athrow
     348: astore        9
     350: aload         4
     352: ifnull        385
     355: aload         5
     357: ifnull        380
     360: aload         4
     362: invokevirtual #70                 // Method org/apache/hadoop/hbase/client/TestClientScanner$MockClientScanner.close:()V
     365: goto          385
     368: astore        10
     370: aload         5
     372: aload         10
     374: invokevirtual #72                 // Method java/lang/Throwable.addSuppressed:(Ljava/lang/Throwable;)V
     377: goto          385
     380: aload         4
     382: invokevirtual #70                 // Method org/apache/hadoop/hbase/client/TestClientScanner$MockClientScanner.close:()V
     385: aload         9
     387: athrow
     388: return
    Exception table:
       from    to  target type
         311   316   319   Class java/lang/Throwable
         174   301   339   Class java/lang/Throwable
         174   301   348   any
         360   365   368   Class java/lang/Throwable
         339   350   348   any

  public void testSizeLimit() throws java.io.IOException;
    Code:
       0: iconst_1
       1: anewarray     #24                 // class org/apache/hadoop/hbase/client/Result
       4: astore_1
       5: new           #25                 // class org/apache/hadoop/hbase/KeyValue
       8: dup
       9: ldc           #26                 // String row
      11: invokestatic  #27                 // Method org/apache/hadoop/hbase/util/Bytes.toBytes:(Ljava/lang/String;)[B
      14: ldc           #28                 // String cf
      16: invokestatic  #27                 // Method org/apache/hadoop/hbase/util/Bytes.toBytes:(Ljava/lang/String;)[B
      19: ldc           #29                 // String cq
      21: invokestatic  #27                 // Method org/apache/hadoop/hbase/util/Bytes.toBytes:(Ljava/lang/String;)[B
      24: lconst_1
      25: getstatic     #30                 // Field org/apache/hadoop/hbase/KeyValue$Type.Maximum:Lorg/apache/hadoop/hbase/KeyValue$Type;
      28: invokespecial #31                 // Method org/apache/hadoop/hbase/KeyValue."<init>":([B[B[BJLorg/apache/hadoop/hbase/KeyValue$Type;)V
      31: astore_2
      32: aload_1
      33: iconst_0
      34: iconst_1
      35: anewarray     #32                 // class org/apache/hadoop/hbase/Cell
      38: dup
      39: iconst_0
      40: aload_2
      41: aastore
      42: invokestatic  #33                 // Method org/apache/hadoop/hbase/client/Result.create:([Lorg/apache/hadoop/hbase/Cell;)Lorg/apache/hadoop/hbase/client/Result;
      45: aastore
      46: ldc           #34                 // class org/apache/hadoop/hbase/client/RpcRetryingCaller
      48: invokestatic  #6                  // Method org/mockito/Mockito.mock:(Ljava/lang/Class;)Ljava/lang/Object;
      51: checkcast     #34                 // class org/apache/hadoop/hbase/client/RpcRetryingCaller
      54: astore_3
      55: aload_0
      56: getfield      #9                  // Field rpcFactory:Lorg/apache/hadoop/hbase/client/RpcRetryingCallerFactory;
      59: invokevirtual #35                 // Method org/apache/hadoop/hbase/client/RpcRetryingCallerFactory.newCaller:()Lorg/apache/hadoop/hbase/client/RpcRetryingCaller;
      62: invokestatic  #21                 // Method org/mockito/Mockito.when:(Ljava/lang/Object;)Lorg/mockito/stubbing/OngoingStubbing;
      65: aload_3
      66: invokeinterface #22,  2           // InterfaceMethod org/mockito/stubbing/OngoingStubbing.thenReturn:(Ljava/lang/Object;)Lorg/mockito/stubbing/OngoingStubbing;
      71: pop
      72: aload_3
      73: invokestatic  #36                 // Method org/mockito/Mockito.any:()Ljava/lang/Object;
      76: checkcast     #37                 // class org/apache/hadoop/hbase/client/RetryingCallable
      79: invokestatic  #38                 // Method org/mockito/Mockito.anyInt:()I
      82: invokeinterface #39,  3           // InterfaceMethod org/apache/hadoop/hbase/client/RpcRetryingCaller.callWithoutRetries:(Lorg/apache/hadoop/hbase/client/RetryingCallable;I)Ljava/lang/Object;
      87: invokestatic  #21                 // Method org/mockito/Mockito.when:(Ljava/lang/Object;)Lorg/mockito/stubbing/OngoingStubbing;
      90: new           #73                 // class org/apache/hadoop/hbase/client/TestClientScanner$2
      93: dup
      94: aload_0
      95: aload_1
      96: invokespecial #74                 // Method org/apache/hadoop/hbase/client/TestClientScanner$2."<init>":(Lorg/apache/hadoop/hbase/client/TestClientScanner;[Lorg/apache/hadoop/hbase/client/Result;)V
      99: invokeinterface #42,  2           // InterfaceMethod org/mockito/stubbing/OngoingStubbing.thenAnswer:(Lorg/mockito/stubbing/Answer;)Lorg/mockito/stubbing/OngoingStubbing;
     104: pop
     105: aload_0
     106: getfield      #9                  // Field rpcFactory:Lorg/apache/hadoop/hbase/client/RpcRetryingCallerFactory;
     109: invokevirtual #35                 // Method org/apache/hadoop/hbase/client/RpcRetryingCallerFactory.newCaller:()Lorg/apache/hadoop/hbase/client/RpcRetryingCaller;
     112: invokestatic  #21                 // Method org/mockito/Mockito.when:(Ljava/lang/Object;)Lorg/mockito/stubbing/OngoingStubbing;
     115: aload_3
     116: invokeinterface #22,  2           // InterfaceMethod org/mockito/stubbing/OngoingStubbing.thenReturn:(Ljava/lang/Object;)Lorg/mockito/stubbing/OngoingStubbing;
     121: pop
     122: aload_0
     123: getfield      #16                 // Field scan:Lorg/apache/hadoop/hbase/client/Scan;
     126: bipush        100
     128: invokevirtual #43                 // Method org/apache/hadoop/hbase/client/Scan.setCaching:(I)Lorg/apache/hadoop/hbase/client/Scan;
     131: pop
     132: aload_0
     133: getfield      #16                 // Field scan:Lorg/apache/hadoop/hbase/client/Scan;
     136: lconst_1
     137: invokevirtual #46                 // Method org/apache/hadoop/hbase/client/Scan.setMaxResultSize:(J)Lorg/apache/hadoop/hbase/client/Scan;
     140: pop
     141: new           #47                 // class org/apache/hadoop/hbase/client/TestClientScanner$MockClientScanner
     144: dup
     145: aload_0
     146: getfield      #19                 // Field conf:Lorg/apache/hadoop/conf/Configuration;
     149: aload_0
     150: getfield      #16                 // Field scan:Lorg/apache/hadoop/hbase/client/Scan;
     153: aload_0
     154: getfield      #4                  // Field name:Lorg/junit/rules/TestName;
     157: invokevirtual #48                 // Method org/junit/rules/TestName.getMethodName:()Ljava/lang/String;
     160: invokestatic  #49                 // Method org/apache/hadoop/hbase/TableName.valueOf:(Ljava/lang/String;)Lorg/apache/hadoop/hbase/TableName;
     163: aload_0
     164: getfield      #7                  // Field clusterConn:Lorg/apache/hadoop/hbase/client/ClusterConnection;
     167: aload_0
     168: getfield      #9                  // Field rpcFactory:Lorg/apache/hadoop/hbase/client/RpcRetryingCallerFactory;
     171: aload_0
     172: getfield      #11                 // Field controllerFactory:Lorg/apache/hadoop/hbase/ipc/RpcControllerFactory;
     175: aload_0
     176: getfield      #13                 // Field pool:Ljava/util/concurrent/ExecutorService;
     179: ldc           #51                 // int 2147483647
     181: invokespecial #52                 // Method org/apache/hadoop/hbase/client/TestClientScanner$MockClientScanner."<init>":(Lorg/apache/hadoop/conf/Configuration;Lorg/apache/hadoop/hbase/client/Scan;Lorg/apache/hadoop/hbase/TableName;Lorg/apache/hadoop/hbase/client/ClusterConnection;Lorg/apache/hadoop/hbase/client/RpcRetryingCallerFactory;Lorg/apache/hadoop/hbase/ipc/RpcControllerFactory;Ljava/util/concurrent/ExecutorService;I)V
     184: astore        4
     186: aconst_null
     187: astore        5
     189: iconst_1
     190: anewarray     #54                 // class java/lang/Object
     193: dup
     194: iconst_0
     195: aload_3
     196: aastore
     197: invokestatic  #55                 // Method org/mockito/Mockito.inOrder:([Ljava/lang/Object;)Lorg/mockito/InOrder;
     200: astore        6
     202: aload         4
     204: invokevirtual #56                 // Method org/apache/hadoop/hbase/client/TestClientScanner$MockClientScanner.loadCache:()V
     207: aload         6
     209: aload_3
     210: iconst_1
     211: invokestatic  #57                 // Method org/mockito/Mockito.times:(I)Lorg/mockito/verification/VerificationMode;
     214: invokeinterface #58,  3           // InterfaceMethod org/mockito/InOrder.verify:(Ljava/lang/Object;Lorg/mockito/verification/VerificationMode;)Ljava/lang/Object;
     219: checkcast     #34                 // class org/apache/hadoop/hbase/client/RpcRetryingCaller
     222: invokestatic  #36                 // Method org/mockito/Mockito.any:()Ljava/lang/Object;
     225: checkcast     #37                 // class org/apache/hadoop/hbase/client/RetryingCallable
     228: invokestatic  #38                 // Method org/mockito/Mockito.anyInt:()I
     231: invokeinterface #39,  3           // InterfaceMethod org/apache/hadoop/hbase/client/RpcRetryingCaller.callWithoutRetries:(Lorg/apache/hadoop/hbase/client/RetryingCallable;I)Ljava/lang/Object;
     236: pop
     237: lconst_1
     238: aload         4
     240: getfield      #59                 // Field org/apache/hadoop/hbase/client/TestClientScanner$MockClientScanner.cache:Ljava/util/Queue;
     243: invokeinterface #60,  1           // InterfaceMethod java/util/Queue.size:()I
     248: i2l
     249: invokestatic  #61                 // Method org/junit/Assert.assertEquals:(JJ)V
     252: aload         4
     254: getfield      #59                 // Field org/apache/hadoop/hbase/client/TestClientScanner$MockClientScanner.cache:Ljava/util/Queue;
     257: invokeinterface #62,  1           // InterfaceMethod java/util/Queue.poll:()Ljava/lang/Object;
     262: checkcast     #24                 // class org/apache/hadoop/hbase/client/Result
     265: astore        7
     267: aload         7
     269: invokestatic  #63                 // Method org/junit/Assert.assertNotNull:(Ljava/lang/Object;)V
     272: aload         7
     274: invokevirtual #64                 // Method org/apache/hadoop/hbase/client/Result.cellScanner:()Lorg/apache/hadoop/hbase/CellScanner;
     277: astore        8
     279: aload         8
     281: invokeinterface #65,  1           // InterfaceMethod org/apache/hadoop/hbase/CellScanner.advance:()Z
     286: invokestatic  #66                 // Method org/junit/Assert.assertTrue:(Z)V
     289: aload_2
     290: aload         8
     292: invokeinterface #67,  1           // InterfaceMethod org/apache/hadoop/hbase/CellScanner.current:()Lorg/apache/hadoop/hbase/Cell;
     297: invokestatic  #68                 // Method org/junit/Assert.assertEquals:(Ljava/lang/Object;Ljava/lang/Object;)V
     300: aload         8
     302: invokeinterface #65,  1           // InterfaceMethod org/apache/hadoop/hbase/CellScanner.advance:()Z
     307: invokestatic  #69                 // Method org/junit/Assert.assertFalse:(Z)V
     310: aload         4
     312: ifnull        397
     315: aload         5
     317: ifnull        340
     320: aload         4
     322: invokevirtual #70                 // Method org/apache/hadoop/hbase/client/TestClientScanner$MockClientScanner.close:()V
     325: goto          397
     328: astore        6
     330: aload         5
     332: aload         6
     334: invokevirtual #72                 // Method java/lang/Throwable.addSuppressed:(Ljava/lang/Throwable;)V
     337: goto          397
     340: aload         4
     342: invokevirtual #70                 // Method org/apache/hadoop/hbase/client/TestClientScanner$MockClientScanner.close:()V
     345: goto          397
     348: astore        6
     350: aload         6
     352: astore        5
     354: aload         6
     356: athrow
     357: astore        9
     359: aload         4
     361: ifnull        394
     364: aload         5
     366: ifnull        389
     369: aload         4
     371: invokevirtual #70                 // Method org/apache/hadoop/hbase/client/TestClientScanner$MockClientScanner.close:()V
     374: goto          394
     377: astore        10
     379: aload         5
     381: aload         10
     383: invokevirtual #72                 // Method java/lang/Throwable.addSuppressed:(Ljava/lang/Throwable;)V
     386: goto          394
     389: aload         4
     391: invokevirtual #70                 // Method org/apache/hadoop/hbase/client/TestClientScanner$MockClientScanner.close:()V
     394: aload         9
     396: athrow
     397: return
    Exception table:
       from    to  target type
         320   325   328   Class java/lang/Throwable
         189   310   348   Class java/lang/Throwable
         189   310   357   any
         369   374   377   Class java/lang/Throwable
         348   359   357   any

  public void testCacheLimit() throws java.io.IOException;
    Code:
       0: new           #25                 // class org/apache/hadoop/hbase/KeyValue
       3: dup
       4: ldc           #75                 // String row1
       6: invokestatic  #27                 // Method org/apache/hadoop/hbase/util/Bytes.toBytes:(Ljava/lang/String;)[B
       9: ldc           #28                 // String cf
      11: invokestatic  #27                 // Method org/apache/hadoop/hbase/util/Bytes.toBytes:(Ljava/lang/String;)[B
      14: ldc           #29                 // String cq
      16: invokestatic  #27                 // Method org/apache/hadoop/hbase/util/Bytes.toBytes:(Ljava/lang/String;)[B
      19: lconst_1
      20: getstatic     #30                 // Field org/apache/hadoop/hbase/KeyValue$Type.Maximum:Lorg/apache/hadoop/hbase/KeyValue$Type;
      23: invokespecial #31                 // Method org/apache/hadoop/hbase/KeyValue."<init>":([B[B[BJLorg/apache/hadoop/hbase/KeyValue$Type;)V
      26: astore_1
      27: new           #25                 // class org/apache/hadoop/hbase/KeyValue
      30: dup
      31: ldc           #76                 // String row2
      33: invokestatic  #27                 // Method org/apache/hadoop/hbase/util/Bytes.toBytes:(Ljava/lang/String;)[B
      36: ldc           #28                 // String cf
      38: invokestatic  #27                 // Method org/apache/hadoop/hbase/util/Bytes.toBytes:(Ljava/lang/String;)[B
      41: ldc           #29                 // String cq
      43: invokestatic  #27                 // Method org/apache/hadoop/hbase/util/Bytes.toBytes:(Ljava/lang/String;)[B
      46: lconst_1
      47: getstatic     #30                 // Field org/apache/hadoop/hbase/KeyValue$Type.Maximum:Lorg/apache/hadoop/hbase/KeyValue$Type;
      50: invokespecial #31                 // Method org/apache/hadoop/hbase/KeyValue."<init>":([B[B[BJLorg/apache/hadoop/hbase/KeyValue$Type;)V
      53: astore_2
      54: new           #25                 // class org/apache/hadoop/hbase/KeyValue
      57: dup
      58: ldc           #77                 // String row3
      60: invokestatic  #27                 // Method org/apache/hadoop/hbase/util/Bytes.toBytes:(Ljava/lang/String;)[B
      63: ldc           #28                 // String cf
      65: invokestatic  #27                 // Method org/apache/hadoop/hbase/util/Bytes.toBytes:(Ljava/lang/String;)[B
      68: ldc           #29                 // String cq
      70: invokestatic  #27                 // Method org/apache/hadoop/hbase/util/Bytes.toBytes:(Ljava/lang/String;)[B
      73: lconst_1
      74: getstatic     #30                 // Field org/apache/hadoop/hbase/KeyValue$Type.Maximum:Lorg/apache/hadoop/hbase/KeyValue$Type;
      77: invokespecial #31                 // Method org/apache/hadoop/hbase/KeyValue."<init>":([B[B[BJLorg/apache/hadoop/hbase/KeyValue$Type;)V
      80: astore_3
      81: iconst_3
      82: anewarray     #24                 // class org/apache/hadoop/hbase/client/Result
      85: dup
      86: iconst_0
      87: iconst_1
      88: anewarray     #32                 // class org/apache/hadoop/hbase/Cell
      91: dup
      92: iconst_0
      93: aload_1
      94: aastore
      95: invokestatic  #33                 // Method org/apache/hadoop/hbase/client/Result.create:([Lorg/apache/hadoop/hbase/Cell;)Lorg/apache/hadoop/hbase/client/Result;
      98: aastore
      99: dup
     100: iconst_1
     101: iconst_1
     102: anewarray     #32                 // class org/apache/hadoop/hbase/Cell
     105: dup
     106: iconst_0
     107: aload_2
     108: aastore
     109: invokestatic  #33                 // Method org/apache/hadoop/hbase/client/Result.create:([Lorg/apache/hadoop/hbase/Cell;)Lorg/apache/hadoop/hbase/client/Result;
     112: aastore
     113: dup
     114: iconst_2
     115: iconst_1
     116: anewarray     #32                 // class org/apache/hadoop/hbase/Cell
     119: dup
     120: iconst_0
     121: aload_3
     122: aastore
     123: invokestatic  #33                 // Method org/apache/hadoop/hbase/client/Result.create:([Lorg/apache/hadoop/hbase/Cell;)Lorg/apache/hadoop/hbase/client/Result;
     126: aastore
     127: astore        4
     129: ldc           #34                 // class org/apache/hadoop/hbase/client/RpcRetryingCaller
     131: invokestatic  #6                  // Method org/mockito/Mockito.mock:(Ljava/lang/Class;)Ljava/lang/Object;
     134: checkcast     #34                 // class org/apache/hadoop/hbase/client/RpcRetryingCaller
     137: astore        5
     139: aload_0
     140: getfield      #9                  // Field rpcFactory:Lorg/apache/hadoop/hbase/client/RpcRetryingCallerFactory;
     143: invokevirtual #35                 // Method org/apache/hadoop/hbase/client/RpcRetryingCallerFactory.newCaller:()Lorg/apache/hadoop/hbase/client/RpcRetryingCaller;
     146: invokestatic  #21                 // Method org/mockito/Mockito.when:(Ljava/lang/Object;)Lorg/mockito/stubbing/OngoingStubbing;
     149: aload         5
     151: invokeinterface #22,  2           // InterfaceMethod org/mockito/stubbing/OngoingStubbing.thenReturn:(Ljava/lang/Object;)Lorg/mockito/stubbing/OngoingStubbing;
     156: pop
     157: aload         5
     159: invokestatic  #36                 // Method org/mockito/Mockito.any:()Ljava/lang/Object;
     162: checkcast     #37                 // class org/apache/hadoop/hbase/client/RetryingCallable
     165: invokestatic  #38                 // Method org/mockito/Mockito.anyInt:()I
     168: invokeinterface #39,  3           // InterfaceMethod org/apache/hadoop/hbase/client/RpcRetryingCaller.callWithoutRetries:(Lorg/apache/hadoop/hbase/client/RetryingCallable;I)Ljava/lang/Object;
     173: invokestatic  #21                 // Method org/mockito/Mockito.when:(Ljava/lang/Object;)Lorg/mockito/stubbing/OngoingStubbing;
     176: new           #78                 // class org/apache/hadoop/hbase/client/TestClientScanner$3
     179: dup
     180: aload_0
     181: aload         4
     183: invokespecial #79                 // Method org/apache/hadoop/hbase/client/TestClientScanner$3."<init>":(Lorg/apache/hadoop/hbase/client/TestClientScanner;[Lorg/apache/hadoop/hbase/client/Result;)V
     186: invokeinterface #42,  2           // InterfaceMethod org/mockito/stubbing/OngoingStubbing.thenAnswer:(Lorg/mockito/stubbing/Answer;)Lorg/mockito/stubbing/OngoingStubbing;
     191: pop
     192: aload_0
     193: getfield      #9                  // Field rpcFactory:Lorg/apache/hadoop/hbase/client/RpcRetryingCallerFactory;
     196: invokevirtual #35                 // Method org/apache/hadoop/hbase/client/RpcRetryingCallerFactory.newCaller:()Lorg/apache/hadoop/hbase/client/RpcRetryingCaller;
     199: invokestatic  #21                 // Method org/mockito/Mockito.when:(Ljava/lang/Object;)Lorg/mockito/stubbing/OngoingStubbing;
     202: aload         5
     204: invokeinterface #22,  2           // InterfaceMethod org/mockito/stubbing/OngoingStubbing.thenReturn:(Ljava/lang/Object;)Lorg/mockito/stubbing/OngoingStubbing;
     209: pop
     210: aload_0
     211: getfield      #16                 // Field scan:Lorg/apache/hadoop/hbase/client/Scan;
     214: iconst_1
     215: invokevirtual #43                 // Method org/apache/hadoop/hbase/client/Scan.setCaching:(I)Lorg/apache/hadoop/hbase/client/Scan;
     218: pop
     219: aload_0
     220: getfield      #16                 // Field scan:Lorg/apache/hadoop/hbase/client/Scan;
     223: ldc2_w        #44                 // long 1000000l
     226: invokevirtual #46                 // Method org/apache/hadoop/hbase/client/Scan.setMaxResultSize:(J)Lorg/apache/hadoop/hbase/client/Scan;
     229: pop
     230: new           #47                 // class org/apache/hadoop/hbase/client/TestClientScanner$MockClientScanner
     233: dup
     234: aload_0
     235: getfield      #19                 // Field conf:Lorg/apache/hadoop/conf/Configuration;
     238: aload_0
     239: getfield      #16                 // Field scan:Lorg/apache/hadoop/hbase/client/Scan;
     242: aload_0
     243: getfield      #4                  // Field name:Lorg/junit/rules/TestName;
     246: invokevirtual #48                 // Method org/junit/rules/TestName.getMethodName:()Ljava/lang/String;
     249: invokestatic  #49                 // Method org/apache/hadoop/hbase/TableName.valueOf:(Ljava/lang/String;)Lorg/apache/hadoop/hbase/TableName;
     252: aload_0
     253: getfield      #7                  // Field clusterConn:Lorg/apache/hadoop/hbase/client/ClusterConnection;
     256: aload_0
     257: getfield      #9                  // Field rpcFactory:Lorg/apache/hadoop/hbase/client/RpcRetryingCallerFactory;
     260: aload_0
     261: getfield      #11                 // Field controllerFactory:Lorg/apache/hadoop/hbase/ipc/RpcControllerFactory;
     264: aload_0
     265: getfield      #13                 // Field pool:Ljava/util/concurrent/ExecutorService;
     268: ldc           #51                 // int 2147483647
     270: invokespecial #52                 // Method org/apache/hadoop/hbase/client/TestClientScanner$MockClientScanner."<init>":(Lorg/apache/hadoop/conf/Configuration;Lorg/apache/hadoop/hbase/client/Scan;Lorg/apache/hadoop/hbase/TableName;Lorg/apache/hadoop/hbase/client/ClusterConnection;Lorg/apache/hadoop/hbase/client/RpcRetryingCallerFactory;Lorg/apache/hadoop/hbase/ipc/RpcControllerFactory;Ljava/util/concurrent/ExecutorService;I)V
     273: astore        6
     275: aconst_null
     276: astore        7
     278: iconst_1
     279: anewarray     #54                 // class java/lang/Object
     282: dup
     283: iconst_0
     284: aload         5
     286: aastore
     287: invokestatic  #55                 // Method org/mockito/Mockito.inOrder:([Ljava/lang/Object;)Lorg/mockito/InOrder;
     290: astore        8
     292: aload         6
     294: invokevirtual #56                 // Method org/apache/hadoop/hbase/client/TestClientScanner$MockClientScanner.loadCache:()V
     297: aload         8
     299: aload         5
     301: iconst_1
     302: invokestatic  #57                 // Method org/mockito/Mockito.times:(I)Lorg/mockito/verification/VerificationMode;
     305: invokeinterface #58,  3           // InterfaceMethod org/mockito/InOrder.verify:(Ljava/lang/Object;Lorg/mockito/verification/VerificationMode;)Ljava/lang/Object;
     310: checkcast     #34                 // class org/apache/hadoop/hbase/client/RpcRetryingCaller
     313: invokestatic  #36                 // Method org/mockito/Mockito.any:()Ljava/lang/Object;
     316: checkcast     #37                 // class org/apache/hadoop/hbase/client/RetryingCallable
     319: invokestatic  #38                 // Method org/mockito/Mockito.anyInt:()I
     322: invokeinterface #39,  3           // InterfaceMethod org/apache/hadoop/hbase/client/RpcRetryingCaller.callWithoutRetries:(Lorg/apache/hadoop/hbase/client/RetryingCallable;I)Ljava/lang/Object;
     327: pop
     328: ldc2_w        #80                 // long 3l
     331: aload         6
     333: getfield      #59                 // Field org/apache/hadoop/hbase/client/TestClientScanner$MockClientScanner.cache:Ljava/util/Queue;
     336: invokeinterface #60,  1           // InterfaceMethod java/util/Queue.size:()I
     341: i2l
     342: invokestatic  #61                 // Method org/junit/Assert.assertEquals:(JJ)V
     345: aload         6
     347: getfield      #59                 // Field org/apache/hadoop/hbase/client/TestClientScanner$MockClientScanner.cache:Ljava/util/Queue;
     350: invokeinterface #62,  1           // InterfaceMethod java/util/Queue.poll:()Ljava/lang/Object;
     355: checkcast     #24                 // class org/apache/hadoop/hbase/client/Result
     358: astore        9
     360: aload         9
     362: invokestatic  #63                 // Method org/junit/Assert.assertNotNull:(Ljava/lang/Object;)V
     365: aload         9
     367: invokevirtual #64                 // Method org/apache/hadoop/hbase/client/Result.cellScanner:()Lorg/apache/hadoop/hbase/CellScanner;
     370: astore        10
     372: aload         10
     374: invokeinterface #65,  1           // InterfaceMethod org/apache/hadoop/hbase/CellScanner.advance:()Z
     379: invokestatic  #66                 // Method org/junit/Assert.assertTrue:(Z)V
     382: aload_1
     383: aload         10
     385: invokeinterface #67,  1           // InterfaceMethod org/apache/hadoop/hbase/CellScanner.current:()Lorg/apache/hadoop/hbase/Cell;
     390: invokestatic  #68                 // Method org/junit/Assert.assertEquals:(Ljava/lang/Object;Ljava/lang/Object;)V
     393: aload         10
     395: invokeinterface #65,  1           // InterfaceMethod org/apache/hadoop/hbase/CellScanner.advance:()Z
     400: invokestatic  #69                 // Method org/junit/Assert.assertFalse:(Z)V
     403: aload         6
     405: getfield      #59                 // Field org/apache/hadoop/hbase/client/TestClientScanner$MockClientScanner.cache:Ljava/util/Queue;
     408: invokeinterface #62,  1           // InterfaceMethod java/util/Queue.poll:()Ljava/lang/Object;
     413: checkcast     #24                 // class org/apache/hadoop/hbase/client/Result
     416: astore        9
     418: aload         9
     420: invokestatic  #63                 // Method org/junit/Assert.assertNotNull:(Ljava/lang/Object;)V
     423: aload         9
     425: invokevirtual #64                 // Method org/apache/hadoop/hbase/client/Result.cellScanner:()Lorg/apache/hadoop/hbase/CellScanner;
     428: astore        10
     430: aload         10
     432: invokeinterface #65,  1           // InterfaceMethod org/apache/hadoop/hbase/CellScanner.advance:()Z
     437: invokestatic  #66                 // Method org/junit/Assert.assertTrue:(Z)V
     440: aload_2
     441: aload         10
     443: invokeinterface #67,  1           // InterfaceMethod org/apache/hadoop/hbase/CellScanner.current:()Lorg/apache/hadoop/hbase/Cell;
     448: invokestatic  #68                 // Method org/junit/Assert.assertEquals:(Ljava/lang/Object;Ljava/lang/Object;)V
     451: aload         10
     453: invokeinterface #65,  1           // InterfaceMethod org/apache/hadoop/hbase/CellScanner.advance:()Z
     458: invokestatic  #69                 // Method org/junit/Assert.assertFalse:(Z)V
     461: aload         6
     463: getfield      #59                 // Field org/apache/hadoop/hbase/client/TestClientScanner$MockClientScanner.cache:Ljava/util/Queue;
     466: invokeinterface #62,  1           // InterfaceMethod java/util/Queue.poll:()Ljava/lang/Object;
     471: checkcast     #24                 // class org/apache/hadoop/hbase/client/Result
     474: astore        9
     476: aload         9
     478: invokestatic  #63                 // Method org/junit/Assert.assertNotNull:(Ljava/lang/Object;)V
     481: aload         9
     483: invokevirtual #64                 // Method org/apache/hadoop/hbase/client/Result.cellScanner:()Lorg/apache/hadoop/hbase/CellScanner;
     486: astore        10
     488: aload         10
     490: invokeinterface #65,  1           // InterfaceMethod org/apache/hadoop/hbase/CellScanner.advance:()Z
     495: invokestatic  #66                 // Method org/junit/Assert.assertTrue:(Z)V
     498: aload_3
     499: aload         10
     501: invokeinterface #67,  1           // InterfaceMethod org/apache/hadoop/hbase/CellScanner.current:()Lorg/apache/hadoop/hbase/Cell;
     506: invokestatic  #68                 // Method org/junit/Assert.assertEquals:(Ljava/lang/Object;Ljava/lang/Object;)V
     509: aload         10
     511: invokeinterface #65,  1           // InterfaceMethod org/apache/hadoop/hbase/CellScanner.advance:()Z
     516: invokestatic  #69                 // Method org/junit/Assert.assertFalse:(Z)V
     519: aload         6
     521: ifnull        606
     524: aload         7
     526: ifnull        549
     529: aload         6
     531: invokevirtual #70                 // Method org/apache/hadoop/hbase/client/TestClientScanner$MockClientScanner.close:()V
     534: goto          606
     537: astore        8
     539: aload         7
     541: aload         8
     543: invokevirtual #72                 // Method java/lang/Throwable.addSuppressed:(Ljava/lang/Throwable;)V
     546: goto          606
     549: aload         6
     551: invokevirtual #70                 // Method org/apache/hadoop/hbase/client/TestClientScanner$MockClientScanner.close:()V
     554: goto          606
     557: astore        8
     559: aload         8
     561: astore        7
     563: aload         8
     565: athrow
     566: astore        11
     568: aload         6
     570: ifnull        603
     573: aload         7
     575: ifnull        598
     578: aload         6
     580: invokevirtual #70                 // Method org/apache/hadoop/hbase/client/TestClientScanner$MockClientScanner.close:()V
     583: goto          603
     586: astore        12
     588: aload         7
     590: aload         12
     592: invokevirtual #72                 // Method java/lang/Throwable.addSuppressed:(Ljava/lang/Throwable;)V
     595: goto          603
     598: aload         6
     600: invokevirtual #70                 // Method org/apache/hadoop/hbase/client/TestClientScanner$MockClientScanner.close:()V
     603: aload         11
     605: athrow
     606: return
    Exception table:
       from    to  target type
         529   534   537   Class java/lang/Throwable
         278   519   557   Class java/lang/Throwable
         278   519   566   any
         578   583   586   Class java/lang/Throwable
         557   568   566   any

  public void testNoMoreResults() throws java.io.IOException;
    Code:
       0: iconst_1
       1: anewarray     #24                 // class org/apache/hadoop/hbase/client/Result
       4: astore_1
       5: new           #25                 // class org/apache/hadoop/hbase/KeyValue
       8: dup
       9: ldc           #26                 // String row
      11: invokestatic  #27                 // Method org/apache/hadoop/hbase/util/Bytes.toBytes:(Ljava/lang/String;)[B
      14: ldc           #28                 // String cf
      16: invokestatic  #27                 // Method org/apache/hadoop/hbase/util/Bytes.toBytes:(Ljava/lang/String;)[B
      19: ldc           #29                 // String cq
      21: invokestatic  #27                 // Method org/apache/hadoop/hbase/util/Bytes.toBytes:(Ljava/lang/String;)[B
      24: lconst_1
      25: getstatic     #30                 // Field org/apache/hadoop/hbase/KeyValue$Type.Maximum:Lorg/apache/hadoop/hbase/KeyValue$Type;
      28: invokespecial #31                 // Method org/apache/hadoop/hbase/KeyValue."<init>":([B[B[BJLorg/apache/hadoop/hbase/KeyValue$Type;)V
      31: astore_2
      32: aload_1
      33: iconst_0
      34: iconst_1
      35: anewarray     #32                 // class org/apache/hadoop/hbase/Cell
      38: dup
      39: iconst_0
      40: aload_2
      41: aastore
      42: invokestatic  #33                 // Method org/apache/hadoop/hbase/client/Result.create:([Lorg/apache/hadoop/hbase/Cell;)Lorg/apache/hadoop/hbase/client/Result;
      45: aastore
      46: ldc           #34                 // class org/apache/hadoop/hbase/client/RpcRetryingCaller
      48: invokestatic  #6                  // Method org/mockito/Mockito.mock:(Ljava/lang/Class;)Ljava/lang/Object;
      51: checkcast     #34                 // class org/apache/hadoop/hbase/client/RpcRetryingCaller
      54: astore_3
      55: aload_0
      56: getfield      #9                  // Field rpcFactory:Lorg/apache/hadoop/hbase/client/RpcRetryingCallerFactory;
      59: invokevirtual #35                 // Method org/apache/hadoop/hbase/client/RpcRetryingCallerFactory.newCaller:()Lorg/apache/hadoop/hbase/client/RpcRetryingCaller;
      62: invokestatic  #21                 // Method org/mockito/Mockito.when:(Ljava/lang/Object;)Lorg/mockito/stubbing/OngoingStubbing;
      65: aload_3
      66: invokeinterface #22,  2           // InterfaceMethod org/mockito/stubbing/OngoingStubbing.thenReturn:(Ljava/lang/Object;)Lorg/mockito/stubbing/OngoingStubbing;
      71: pop
      72: aload_3
      73: invokestatic  #36                 // Method org/mockito/Mockito.any:()Ljava/lang/Object;
      76: checkcast     #37                 // class org/apache/hadoop/hbase/client/RetryingCallable
      79: invokestatic  #38                 // Method org/mockito/Mockito.anyInt:()I
      82: invokeinterface #39,  3           // InterfaceMethod org/apache/hadoop/hbase/client/RpcRetryingCaller.callWithoutRetries:(Lorg/apache/hadoop/hbase/client/RetryingCallable;I)Ljava/lang/Object;
      87: invokestatic  #21                 // Method org/mockito/Mockito.when:(Ljava/lang/Object;)Lorg/mockito/stubbing/OngoingStubbing;
      90: new           #82                 // class org/apache/hadoop/hbase/client/TestClientScanner$4
      93: dup
      94: aload_0
      95: aload_1
      96: invokespecial #83                 // Method org/apache/hadoop/hbase/client/TestClientScanner$4."<init>":(Lorg/apache/hadoop/hbase/client/TestClientScanner;[Lorg/apache/hadoop/hbase/client/Result;)V
      99: invokeinterface #42,  2           // InterfaceMethod org/mockito/stubbing/OngoingStubbing.thenAnswer:(Lorg/mockito/stubbing/Answer;)Lorg/mockito/stubbing/OngoingStubbing;
     104: pop
     105: aload_0
     106: getfield      #9                  // Field rpcFactory:Lorg/apache/hadoop/hbase/client/RpcRetryingCallerFactory;
     109: invokevirtual #35                 // Method org/apache/hadoop/hbase/client/RpcRetryingCallerFactory.newCaller:()Lorg/apache/hadoop/hbase/client/RpcRetryingCaller;
     112: invokestatic  #21                 // Method org/mockito/Mockito.when:(Ljava/lang/Object;)Lorg/mockito/stubbing/OngoingStubbing;
     115: aload_3
     116: invokeinterface #22,  2           // InterfaceMethod org/mockito/stubbing/OngoingStubbing.thenReturn:(Ljava/lang/Object;)Lorg/mockito/stubbing/OngoingStubbing;
     121: pop
     122: aload_0
     123: getfield      #16                 // Field scan:Lorg/apache/hadoop/hbase/client/Scan;
     126: bipush        100
     128: invokevirtual #43                 // Method org/apache/hadoop/hbase/client/Scan.setCaching:(I)Lorg/apache/hadoop/hbase/client/Scan;
     131: pop
     132: aload_0
     133: getfield      #16                 // Field scan:Lorg/apache/hadoop/hbase/client/Scan;
     136: ldc2_w        #44                 // long 1000000l
     139: invokevirtual #46                 // Method org/apache/hadoop/hbase/client/Scan.setMaxResultSize:(J)Lorg/apache/hadoop/hbase/client/Scan;
     142: pop
     143: new           #47                 // class org/apache/hadoop/hbase/client/TestClientScanner$MockClientScanner
     146: dup
     147: aload_0
     148: getfield      #19                 // Field conf:Lorg/apache/hadoop/conf/Configuration;
     151: aload_0
     152: getfield      #16                 // Field scan:Lorg/apache/hadoop/hbase/client/Scan;
     155: aload_0
     156: getfield      #4                  // Field name:Lorg/junit/rules/TestName;
     159: invokevirtual #48                 // Method org/junit/rules/TestName.getMethodName:()Ljava/lang/String;
     162: invokestatic  #49                 // Method org/apache/hadoop/hbase/TableName.valueOf:(Ljava/lang/String;)Lorg/apache/hadoop/hbase/TableName;
     165: aload_0
     166: getfield      #7                  // Field clusterConn:Lorg/apache/hadoop/hbase/client/ClusterConnection;
     169: aload_0
     170: getfield      #9                  // Field rpcFactory:Lorg/apache/hadoop/hbase/client/RpcRetryingCallerFactory;
     173: aload_0
     174: getfield      #11                 // Field controllerFactory:Lorg/apache/hadoop/hbase/ipc/RpcControllerFactory;
     177: aload_0
     178: getfield      #13                 // Field pool:Ljava/util/concurrent/ExecutorService;
     181: ldc           #51                 // int 2147483647
     183: invokespecial #52                 // Method org/apache/hadoop/hbase/client/TestClientScanner$MockClientScanner."<init>":(Lorg/apache/hadoop/conf/Configuration;Lorg/apache/hadoop/hbase/client/Scan;Lorg/apache/hadoop/hbase/TableName;Lorg/apache/hadoop/hbase/client/ClusterConnection;Lorg/apache/hadoop/hbase/client/RpcRetryingCallerFactory;Lorg/apache/hadoop/hbase/ipc/RpcControllerFactory;Ljava/util/concurrent/ExecutorService;I)V
     186: astore        4
     188: aconst_null
     189: astore        5
     191: aload         4
     193: iconst_1
     194: invokevirtual #53                 // Method org/apache/hadoop/hbase/client/TestClientScanner$MockClientScanner.setRpcFinished:(Z)V
     197: iconst_1
     198: anewarray     #54                 // class java/lang/Object
     201: dup
     202: iconst_0
     203: aload_3
     204: aastore
     205: invokestatic  #55                 // Method org/mockito/Mockito.inOrder:([Ljava/lang/Object;)Lorg/mockito/InOrder;
     208: astore        6
     210: aload         4
     212: invokevirtual #56                 // Method org/apache/hadoop/hbase/client/TestClientScanner$MockClientScanner.loadCache:()V
     215: aload         6
     217: aload_3
     218: iconst_1
     219: invokestatic  #57                 // Method org/mockito/Mockito.times:(I)Lorg/mockito/verification/VerificationMode;
     222: invokeinterface #58,  3           // InterfaceMethod org/mockito/InOrder.verify:(Ljava/lang/Object;Lorg/mockito/verification/VerificationMode;)Ljava/lang/Object;
     227: checkcast     #34                 // class org/apache/hadoop/hbase/client/RpcRetryingCaller
     230: invokestatic  #36                 // Method org/mockito/Mockito.any:()Ljava/lang/Object;
     233: checkcast     #37                 // class org/apache/hadoop/hbase/client/RetryingCallable
     236: invokestatic  #38                 // Method org/mockito/Mockito.anyInt:()I
     239: invokeinterface #39,  3           // InterfaceMethod org/apache/hadoop/hbase/client/RpcRetryingCaller.callWithoutRetries:(Lorg/apache/hadoop/hbase/client/RetryingCallable;I)Ljava/lang/Object;
     244: pop
     245: lconst_1
     246: aload         4
     248: getfield      #59                 // Field org/apache/hadoop/hbase/client/TestClientScanner$MockClientScanner.cache:Ljava/util/Queue;
     251: invokeinterface #60,  1           // InterfaceMethod java/util/Queue.size:()I
     256: i2l
     257: invokestatic  #61                 // Method org/junit/Assert.assertEquals:(JJ)V
     260: aload         4
     262: getfield      #59                 // Field org/apache/hadoop/hbase/client/TestClientScanner$MockClientScanner.cache:Ljava/util/Queue;
     265: invokeinterface #62,  1           // InterfaceMethod java/util/Queue.poll:()Ljava/lang/Object;
     270: checkcast     #24                 // class org/apache/hadoop/hbase/client/Result
     273: astore        7
     275: aload         7
     277: invokestatic  #63                 // Method org/junit/Assert.assertNotNull:(Ljava/lang/Object;)V
     280: aload         7
     282: invokevirtual #64                 // Method org/apache/hadoop/hbase/client/Result.cellScanner:()Lorg/apache/hadoop/hbase/CellScanner;
     285: astore        8
     287: aload         8
     289: invokeinterface #65,  1           // InterfaceMethod org/apache/hadoop/hbase/CellScanner.advance:()Z
     294: invokestatic  #66                 // Method org/junit/Assert.assertTrue:(Z)V
     297: aload_2
     298: aload         8
     300: invokeinterface #67,  1           // InterfaceMethod org/apache/hadoop/hbase/CellScanner.current:()Lorg/apache/hadoop/hbase/Cell;
     305: invokestatic  #68                 // Method org/junit/Assert.assertEquals:(Ljava/lang/Object;Ljava/lang/Object;)V
     308: aload         8
     310: invokeinterface #65,  1           // InterfaceMethod org/apache/hadoop/hbase/CellScanner.advance:()Z
     315: invokestatic  #69                 // Method org/junit/Assert.assertFalse:(Z)V
     318: aload         4
     320: ifnull        405
     323: aload         5
     325: ifnull        348
     328: aload         4
     330: invokevirtual #70                 // Method org/apache/hadoop/hbase/client/TestClientScanner$MockClientScanner.close:()V
     333: goto          405
     336: astore        6
     338: aload         5
     340: aload         6
     342: invokevirtual #72                 // Method java/lang/Throwable.addSuppressed:(Ljava/lang/Throwable;)V
     345: goto          405
     348: aload         4
     350: invokevirtual #70                 // Method org/apache/hadoop/hbase/client/TestClientScanner$MockClientScanner.close:()V
     353: goto          405
     356: astore        6
     358: aload         6
     360: astore        5
     362: aload         6
     364: athrow
     365: astore        9
     367: aload         4
     369: ifnull        402
     372: aload         5
     374: ifnull        397
     377: aload         4
     379: invokevirtual #70                 // Method org/apache/hadoop/hbase/client/TestClientScanner$MockClientScanner.close:()V
     382: goto          402
     385: astore        10
     387: aload         5
     389: aload         10
     391: invokevirtual #72                 // Method java/lang/Throwable.addSuppressed:(Ljava/lang/Throwable;)V
     394: goto          402
     397: aload         4
     399: invokevirtual #70                 // Method org/apache/hadoop/hbase/client/TestClientScanner$MockClientScanner.close:()V
     402: aload         9
     404: athrow
     405: return
    Exception table:
       from    to  target type
         328   333   336   Class java/lang/Throwable
         191   318   356   Class java/lang/Throwable
         191   318   365   any
         377   382   385   Class java/lang/Throwable
         356   367   365   any

  public void testMoreResults() throws java.io.IOException;
    Code:
       0: iconst_1
       1: anewarray     #24                 // class org/apache/hadoop/hbase/client/Result
       4: astore_1
       5: new           #25                 // class org/apache/hadoop/hbase/KeyValue
       8: dup
       9: ldc           #26                 // String row
      11: invokestatic  #27                 // Method org/apache/hadoop/hbase/util/Bytes.toBytes:(Ljava/lang/String;)[B
      14: ldc           #28                 // String cf
      16: invokestatic  #27                 // Method org/apache/hadoop/hbase/util/Bytes.toBytes:(Ljava/lang/String;)[B
      19: ldc           #29                 // String cq
      21: invokestatic  #27                 // Method org/apache/hadoop/hbase/util/Bytes.toBytes:(Ljava/lang/String;)[B
      24: lconst_1
      25: getstatic     #30                 // Field org/apache/hadoop/hbase/KeyValue$Type.Maximum:Lorg/apache/hadoop/hbase/KeyValue$Type;
      28: invokespecial #31                 // Method org/apache/hadoop/hbase/KeyValue."<init>":([B[B[BJLorg/apache/hadoop/hbase/KeyValue$Type;)V
      31: astore_2
      32: aload_1
      33: iconst_0
      34: iconst_1
      35: anewarray     #32                 // class org/apache/hadoop/hbase/Cell
      38: dup
      39: iconst_0
      40: aload_2
      41: aastore
      42: invokestatic  #33                 // Method org/apache/hadoop/hbase/client/Result.create:([Lorg/apache/hadoop/hbase/Cell;)Lorg/apache/hadoop/hbase/client/Result;
      45: aastore
      46: iconst_1
      47: anewarray     #24                 // class org/apache/hadoop/hbase/client/Result
      50: astore_3
      51: new           #25                 // class org/apache/hadoop/hbase/KeyValue
      54: dup
      55: ldc           #76                 // String row2
      57: invokestatic  #27                 // Method org/apache/hadoop/hbase/util/Bytes.toBytes:(Ljava/lang/String;)[B
      60: ldc           #28                 // String cf
      62: invokestatic  #27                 // Method org/apache/hadoop/hbase/util/Bytes.toBytes:(Ljava/lang/String;)[B
      65: ldc           #29                 // String cq
      67: invokestatic  #27                 // Method org/apache/hadoop/hbase/util/Bytes.toBytes:(Ljava/lang/String;)[B
      70: lconst_1
      71: getstatic     #30                 // Field org/apache/hadoop/hbase/KeyValue$Type.Maximum:Lorg/apache/hadoop/hbase/KeyValue$Type;
      74: invokespecial #31                 // Method org/apache/hadoop/hbase/KeyValue."<init>":([B[B[BJLorg/apache/hadoop/hbase/KeyValue$Type;)V
      77: astore        4
      79: aload_3
      80: iconst_0
      81: iconst_1
      82: anewarray     #32                 // class org/apache/hadoop/hbase/Cell
      85: dup
      86: iconst_0
      87: aload         4
      89: aastore
      90: invokestatic  #33                 // Method org/apache/hadoop/hbase/client/Result.create:([Lorg/apache/hadoop/hbase/Cell;)Lorg/apache/hadoop/hbase/client/Result;
      93: aastore
      94: ldc           #34                 // class org/apache/hadoop/hbase/client/RpcRetryingCaller
      96: invokestatic  #6                  // Method org/mockito/Mockito.mock:(Ljava/lang/Class;)Ljava/lang/Object;
      99: checkcast     #34                 // class org/apache/hadoop/hbase/client/RpcRetryingCaller
     102: astore        5
     104: aload_0
     105: getfield      #9                  // Field rpcFactory:Lorg/apache/hadoop/hbase/client/RpcRetryingCallerFactory;
     108: invokevirtual #35                 // Method org/apache/hadoop/hbase/client/RpcRetryingCallerFactory.newCaller:()Lorg/apache/hadoop/hbase/client/RpcRetryingCaller;
     111: invokestatic  #21                 // Method org/mockito/Mockito.when:(Ljava/lang/Object;)Lorg/mockito/stubbing/OngoingStubbing;
     114: aload         5
     116: invokeinterface #22,  2           // InterfaceMethod org/mockito/stubbing/OngoingStubbing.thenReturn:(Ljava/lang/Object;)Lorg/mockito/stubbing/OngoingStubbing;
     121: pop
     122: aload         5
     124: invokestatic  #36                 // Method org/mockito/Mockito.any:()Ljava/lang/Object;
     127: checkcast     #37                 // class org/apache/hadoop/hbase/client/RetryingCallable
     130: invokestatic  #38                 // Method org/mockito/Mockito.anyInt:()I
     133: invokeinterface #39,  3           // InterfaceMethod org/apache/hadoop/hbase/client/RpcRetryingCaller.callWithoutRetries:(Lorg/apache/hadoop/hbase/client/RetryingCallable;I)Ljava/lang/Object;
     138: invokestatic  #21                 // Method org/mockito/Mockito.when:(Ljava/lang/Object;)Lorg/mockito/stubbing/OngoingStubbing;
     141: new           #84                 // class org/apache/hadoop/hbase/client/TestClientScanner$5
     144: dup
     145: aload_0
     146: aload_1
     147: aload_3
     148: invokespecial #85                 // Method org/apache/hadoop/hbase/client/TestClientScanner$5."<init>":(Lorg/apache/hadoop/hbase/client/TestClientScanner;[Lorg/apache/hadoop/hbase/client/Result;[Lorg/apache/hadoop/hbase/client/Result;)V
     151: invokeinterface #42,  2           // InterfaceMethod org/mockito/stubbing/OngoingStubbing.thenAnswer:(Lorg/mockito/stubbing/Answer;)Lorg/mockito/stubbing/OngoingStubbing;
     156: pop
     157: aload_0
     158: getfield      #16                 // Field scan:Lorg/apache/hadoop/hbase/client/Scan;
     161: bipush        100
     163: invokevirtual #43                 // Method org/apache/hadoop/hbase/client/Scan.setCaching:(I)Lorg/apache/hadoop/hbase/client/Scan;
     166: pop
     167: aload_0
     168: getfield      #16                 // Field scan:Lorg/apache/hadoop/hbase/client/Scan;
     171: ldc2_w        #44                 // long 1000000l
     174: invokevirtual #46                 // Method org/apache/hadoop/hbase/client/Scan.setMaxResultSize:(J)Lorg/apache/hadoop/hbase/client/Scan;
     177: pop
     178: new           #47                 // class org/apache/hadoop/hbase/client/TestClientScanner$MockClientScanner
     181: dup
     182: aload_0
     183: getfield      #19                 // Field conf:Lorg/apache/hadoop/conf/Configuration;
     186: aload_0
     187: getfield      #16                 // Field scan:Lorg/apache/hadoop/hbase/client/Scan;
     190: aload_0
     191: getfield      #4                  // Field name:Lorg/junit/rules/TestName;
     194: invokevirtual #48                 // Method org/junit/rules/TestName.getMethodName:()Ljava/lang/String;
     197: invokestatic  #49                 // Method org/apache/hadoop/hbase/TableName.valueOf:(Ljava/lang/String;)Lorg/apache/hadoop/hbase/TableName;
     200: aload_0
     201: getfield      #7                  // Field clusterConn:Lorg/apache/hadoop/hbase/client/ClusterConnection;
     204: aload_0
     205: getfield      #9                  // Field rpcFactory:Lorg/apache/hadoop/hbase/client/RpcRetryingCallerFactory;
     208: aload_0
     209: getfield      #11                 // Field controllerFactory:Lorg/apache/hadoop/hbase/ipc/RpcControllerFactory;
     212: aload_0
     213: getfield      #13                 // Field pool:Ljava/util/concurrent/ExecutorService;
     216: ldc           #51                 // int 2147483647
     218: invokespecial #52                 // Method org/apache/hadoop/hbase/client/TestClientScanner$MockClientScanner."<init>":(Lorg/apache/hadoop/conf/Configuration;Lorg/apache/hadoop/hbase/client/Scan;Lorg/apache/hadoop/hbase/TableName;Lorg/apache/hadoop/hbase/client/ClusterConnection;Lorg/apache/hadoop/hbase/client/RpcRetryingCallerFactory;Lorg/apache/hadoop/hbase/ipc/RpcControllerFactory;Ljava/util/concurrent/ExecutorService;I)V
     221: astore        6
     223: aconst_null
     224: astore        7
     226: iconst_1
     227: anewarray     #54                 // class java/lang/Object
     230: dup
     231: iconst_0
     232: aload         5
     234: aastore
     235: invokestatic  #55                 // Method org/mockito/Mockito.inOrder:([Ljava/lang/Object;)Lorg/mockito/InOrder;
     238: astore        8
     240: aload         6
     242: iconst_1
     243: invokevirtual #53                 // Method org/apache/hadoop/hbase/client/TestClientScanner$MockClientScanner.setRpcFinished:(Z)V
     246: aload         6
     248: invokevirtual #56                 // Method org/apache/hadoop/hbase/client/TestClientScanner$MockClientScanner.loadCache:()V
     251: aload         8
     253: aload         5
     255: iconst_2
     256: invokestatic  #57                 // Method org/mockito/Mockito.times:(I)Lorg/mockito/verification/VerificationMode;
     259: invokeinterface #58,  3           // InterfaceMethod org/mockito/InOrder.verify:(Ljava/lang/Object;Lorg/mockito/verification/VerificationMode;)Ljava/lang/Object;
     264: checkcast     #34                 // class org/apache/hadoop/hbase/client/RpcRetryingCaller
     267: invokestatic  #36                 // Method org/mockito/Mockito.any:()Ljava/lang/Object;
     270: checkcast     #37                 // class org/apache/hadoop/hbase/client/RetryingCallable
     273: invokestatic  #38                 // Method org/mockito/Mockito.anyInt:()I
     276: invokeinterface #39,  3           // InterfaceMethod org/apache/hadoop/hbase/client/RpcRetryingCaller.callWithoutRetries:(Lorg/apache/hadoop/hbase/client/RetryingCallable;I)Ljava/lang/Object;
     281: pop
     282: ldc2_w        #86                 // long 2l
     285: aload         6
     287: getfield      #59                 // Field org/apache/hadoop/hbase/client/TestClientScanner$MockClientScanner.cache:Ljava/util/Queue;
     290: invokeinterface #60,  1           // InterfaceMethod java/util/Queue.size:()I
     295: i2l
     296: invokestatic  #61                 // Method org/junit/Assert.assertEquals:(JJ)V
     299: aload         6
     301: getfield      #59                 // Field org/apache/hadoop/hbase/client/TestClientScanner$MockClientScanner.cache:Ljava/util/Queue;
     304: invokeinterface #62,  1           // InterfaceMethod java/util/Queue.poll:()Ljava/lang/Object;
     309: checkcast     #24                 // class org/apache/hadoop/hbase/client/Result
     312: astore        9
     314: aload         9
     316: invokestatic  #63                 // Method org/junit/Assert.assertNotNull:(Ljava/lang/Object;)V
     319: aload         9
     321: invokevirtual #64                 // Method org/apache/hadoop/hbase/client/Result.cellScanner:()Lorg/apache/hadoop/hbase/CellScanner;
     324: astore        10
     326: aload         10
     328: invokeinterface #65,  1           // InterfaceMethod org/apache/hadoop/hbase/CellScanner.advance:()Z
     333: invokestatic  #66                 // Method org/junit/Assert.assertTrue:(Z)V
     336: aload_2
     337: aload         10
     339: invokeinterface #67,  1           // InterfaceMethod org/apache/hadoop/hbase/CellScanner.current:()Lorg/apache/hadoop/hbase/Cell;
     344: invokestatic  #68                 // Method org/junit/Assert.assertEquals:(Ljava/lang/Object;Ljava/lang/Object;)V
     347: aload         10
     349: invokeinterface #65,  1           // InterfaceMethod org/apache/hadoop/hbase/CellScanner.advance:()Z
     354: invokestatic  #69                 // Method org/junit/Assert.assertFalse:(Z)V
     357: aload         6
     359: getfield      #59                 // Field org/apache/hadoop/hbase/client/TestClientScanner$MockClientScanner.cache:Ljava/util/Queue;
     362: invokeinterface #62,  1           // InterfaceMethod java/util/Queue.poll:()Ljava/lang/Object;
     367: checkcast     #24                 // class org/apache/hadoop/hbase/client/Result
     370: astore        9
     372: aload         9
     374: invokestatic  #63                 // Method org/junit/Assert.assertNotNull:(Ljava/lang/Object;)V
     377: aload         9
     379: invokevirtual #64                 // Method org/apache/hadoop/hbase/client/Result.cellScanner:()Lorg/apache/hadoop/hbase/CellScanner;
     382: astore        10
     384: aload         10
     386: invokeinterface #65,  1           // InterfaceMethod org/apache/hadoop/hbase/CellScanner.advance:()Z
     391: invokestatic  #66                 // Method org/junit/Assert.assertTrue:(Z)V
     394: aload         4
     396: aload         10
     398: invokeinterface #67,  1           // InterfaceMethod org/apache/hadoop/hbase/CellScanner.current:()Lorg/apache/hadoop/hbase/Cell;
     403: invokestatic  #68                 // Method org/junit/Assert.assertEquals:(Ljava/lang/Object;Ljava/lang/Object;)V
     406: aload         10
     408: invokeinterface #65,  1           // InterfaceMethod org/apache/hadoop/hbase/CellScanner.advance:()Z
     413: invokestatic  #69                 // Method org/junit/Assert.assertFalse:(Z)V
     416: aload         6
     418: ifnull        503
     421: aload         7
     423: ifnull        446
     426: aload         6
     428: invokevirtual #70                 // Method org/apache/hadoop/hbase/client/TestClientScanner$MockClientScanner.close:()V
     431: goto          503
     434: astore        8
     436: aload         7
     438: aload         8
     440: invokevirtual #72                 // Method java/lang/Throwable.addSuppressed:(Ljava/lang/Throwable;)V
     443: goto          503
     446: aload         6
     448: invokevirtual #70                 // Method org/apache/hadoop/hbase/client/TestClientScanner$MockClientScanner.close:()V
     451: goto          503
     454: astore        8
     456: aload         8
     458: astore        7
     460: aload         8
     462: athrow
     463: astore        11
     465: aload         6
     467: ifnull        500
     470: aload         7
     472: ifnull        495
     475: aload         6
     477: invokevirtual #70                 // Method org/apache/hadoop/hbase/client/TestClientScanner$MockClientScanner.close:()V
     480: goto          500
     483: astore        12
     485: aload         7
     487: aload         12
     489: invokevirtual #72                 // Method java/lang/Throwable.addSuppressed:(Ljava/lang/Throwable;)V
     492: goto          500
     495: aload         6
     497: invokevirtual #70                 // Method org/apache/hadoop/hbase/client/TestClientScanner$MockClientScanner.close:()V
     500: aload         11
     502: athrow
     503: return
    Exception table:
       from    to  target type
         426   431   434   Class java/lang/Throwable
         226   416   454   Class java/lang/Throwable
         226   416   463   any
         475   480   483   Class java/lang/Throwable
         454   465   463   any

  public void testExceptionsFromReplicasArePropagated() throws java.io.IOException;
    Code:
       0: aload_0
       1: getfield      #16                 // Field scan:Lorg/apache/hadoop/hbase/client/Scan;
       4: getstatic     #88                 // Field org/apache/hadoop/hbase/client/Consistency.TIMELINE:Lorg/apache/hadoop/hbase/client/Consistency;
       7: invokevirtual #89                 // Method org/apache/hadoop/hbase/client/Scan.setConsistency:(Lorg/apache/hadoop/hbase/client/Consistency;)Lorg/apache/hadoop/hbase/client/Scan;
      10: pop
      11: aload_0
      12: new           #90                 // class org/apache/hadoop/hbase/client/TestClientScanner$MockRpcRetryingCallerFactory
      15: dup
      16: aload_0
      17: getfield      #19                 // Field conf:Lorg/apache/hadoop/conf/Configuration;
      20: invokespecial #91                 // Method org/apache/hadoop/hbase/client/TestClientScanner$MockRpcRetryingCallerFactory."<init>":(Lorg/apache/hadoop/conf/Configuration;)V
      23: putfield      #9                  // Field rpcFactory:Lorg/apache/hadoop/hbase/client/RpcRetryingCallerFactory;
      26: aload_0
      27: getfield      #19                 // Field conf:Lorg/apache/hadoop/conf/Configuration;
      30: ldc           #92                 // String hbase.rpc.callerfactory.class
      32: ldc           #90                 // class org/apache/hadoop/hbase/client/TestClientScanner$MockRpcRetryingCallerFactory
      34: invokevirtual #93                 // Method java/lang/Class.getName:()Ljava/lang/String;
      37: invokevirtual #94                 // Method org/apache/hadoop/conf/Configuration.set:(Ljava/lang/String;Ljava/lang/String;)V
      40: aload_0
      41: getfield      #7                  // Field clusterConn:Lorg/apache/hadoop/hbase/client/ClusterConnection;
      44: invokestatic  #95                 // Method org/mockito/Matchers.any:()Ljava/lang/Object;
      47: checkcast     #96                 // class org/apache/hadoop/hbase/TableName
      50: invokestatic  #95                 // Method org/mockito/Matchers.any:()Ljava/lang/Object;
      53: checkcast     #97                 // class "[B"
      56: checkcast     #97                 // class "[B"
      59: invokestatic  #98                 // Method org/mockito/Matchers.anyBoolean:()Z
      62: invokestatic  #98                 // Method org/mockito/Matchers.anyBoolean:()Z
      65: invokestatic  #99                 // Method org/mockito/Matchers.anyInt:()I
      68: invokeinterface #100,  6          // InterfaceMethod org/apache/hadoop/hbase/client/ClusterConnection.locateRegion:(Lorg/apache/hadoop/hbase/TableName;[BZZI)Lorg/apache/hadoop/hbase/RegionLocations;
      73: invokestatic  #21                 // Method org/mockito/Mockito.when:(Ljava/lang/Object;)Lorg/mockito/stubbing/OngoingStubbing;
      76: new           #101                // class org/apache/hadoop/hbase/RegionLocations
      79: dup
      80: iconst_3
      81: anewarray     #102                // class org/apache/hadoop/hbase/HRegionLocation
      84: dup
      85: iconst_0
      86: aconst_null
      87: aastore
      88: dup
      89: iconst_1
      90: aconst_null
      91: aastore
      92: dup
      93: iconst_2
      94: aconst_null
      95: aastore
      96: invokespecial #103                // Method org/apache/hadoop/hbase/RegionLocations."<init>":([Lorg/apache/hadoop/hbase/HRegionLocation;)V
      99: invokeinterface #22,  2           // InterfaceMethod org/mockito/stubbing/OngoingStubbing.thenReturn:(Ljava/lang/Object;)Lorg/mockito/stubbing/OngoingStubbing;
     104: pop
     105: new           #47                 // class org/apache/hadoop/hbase/client/TestClientScanner$MockClientScanner
     108: dup
     109: aload_0
     110: getfield      #19                 // Field conf:Lorg/apache/hadoop/conf/Configuration;
     113: aload_0
     114: getfield      #16                 // Field scan:Lorg/apache/hadoop/hbase/client/Scan;
     117: aload_0
     118: getfield      #4                  // Field name:Lorg/junit/rules/TestName;
     121: invokevirtual #48                 // Method org/junit/rules/TestName.getMethodName:()Ljava/lang/String;
     124: invokestatic  #49                 // Method org/apache/hadoop/hbase/TableName.valueOf:(Ljava/lang/String;)Lorg/apache/hadoop/hbase/TableName;
     127: aload_0
     128: getfield      #7                  // Field clusterConn:Lorg/apache/hadoop/hbase/client/ClusterConnection;
     131: aload_0
     132: getfield      #9                  // Field rpcFactory:Lorg/apache/hadoop/hbase/client/RpcRetryingCallerFactory;
     135: new           #10                 // class org/apache/hadoop/hbase/ipc/RpcControllerFactory
     138: dup
     139: aload_0
     140: getfield      #19                 // Field conf:Lorg/apache/hadoop/conf/Configuration;
     143: invokespecial #104                // Method org/apache/hadoop/hbase/ipc/RpcControllerFactory."<init>":(Lorg/apache/hadoop/conf/Configuration;)V
     146: aload_0
     147: getfield      #13                 // Field pool:Ljava/util/concurrent/ExecutorService;
     150: ldc           #51                 // int 2147483647
     152: invokespecial #52                 // Method org/apache/hadoop/hbase/client/TestClientScanner$MockClientScanner."<init>":(Lorg/apache/hadoop/conf/Configuration;Lorg/apache/hadoop/hbase/client/Scan;Lorg/apache/hadoop/hbase/TableName;Lorg/apache/hadoop/hbase/client/ClusterConnection;Lorg/apache/hadoop/hbase/client/RpcRetryingCallerFactory;Lorg/apache/hadoop/hbase/ipc/RpcControllerFactory;Ljava/util/concurrent/ExecutorService;I)V
     155: astore_1
     156: aconst_null
     157: astore_2
     158: aload_1
     159: invokevirtual #105                // Method org/apache/hadoop/hbase/client/TestClientScanner$MockClientScanner.iterator:()Ljava/util/Iterator;
     162: astore_3
     163: aload_3
     164: invokeinterface #106,  1          // InterfaceMethod java/util/Iterator.hasNext:()Z
     169: ifeq          182
     172: aload_3
     173: invokeinterface #107,  1          // InterfaceMethod java/util/Iterator.next:()Ljava/lang/Object;
     178: pop
     179: goto          163
     182: ldc           #108                // String Should have failed with RetriesExhaustedException
     184: invokestatic  #109                // Method org/junit/Assert.fail:(Ljava/lang/String;)V
     187: aload_1
     188: ifnull        258
     191: aload_2
     192: ifnull        211
     195: aload_1
     196: invokevirtual #70                 // Method org/apache/hadoop/hbase/client/TestClientScanner$MockClientScanner.close:()V
     199: goto          258
     202: astore_3
     203: aload_2
     204: aload_3
     205: invokevirtual #72                 // Method java/lang/Throwable.addSuppressed:(Ljava/lang/Throwable;)V
     208: goto          258
     211: aload_1
     212: invokevirtual #70                 // Method org/apache/hadoop/hbase/client/TestClientScanner$MockClientScanner.close:()V
     215: goto          258
     218: astore_3
     219: aload_3
     220: astore_2
     221: aload_3
     222: athrow
     223: astore        4
     225: aload_1
     226: ifnull        255
     229: aload_2
     230: ifnull        251
     233: aload_1
     234: invokevirtual #70                 // Method org/apache/hadoop/hbase/client/TestClientScanner$MockClientScanner.close:()V
     237: goto          255
     240: astore        5
     242: aload_2
     243: aload         5
     245: invokevirtual #72                 // Method java/lang/Throwable.addSuppressed:(Ljava/lang/Throwable;)V
     248: goto          255
     251: aload_1
     252: invokevirtual #70                 // Method org/apache/hadoop/hbase/client/TestClientScanner$MockClientScanner.close:()V
     255: aload         4
     257: athrow
     258: goto          274
     261: astore_1
     262: aload_1
     263: invokevirtual #111                // Method java/lang/RuntimeException.getCause:()Ljava/lang/Throwable;
     266: ldc           #112                // class org/apache/hadoop/hbase/client/RetriesExhaustedException
     268: invokestatic  #113                // Method org/hamcrest/CoreMatchers.instanceOf:(Ljava/lang/Class;)Lorg/hamcrest/Matcher;
     271: invokestatic  #114                // Method org/junit/Assert.assertThat:(Ljava/lang/Object;Lorg/hamcrest/Matcher;)V
     274: return
    Exception table:
       from    to  target type
         195   199   202   Class java/lang/Throwable
         158   187   218   Class java/lang/Throwable
         158   187   223   any
         233   237   240   Class java/lang/Throwable
         218   225   223   any
         105   258   261   Class java/lang/RuntimeException

  static {};
    Code:
       0: ldc           #115                // class org/apache/hadoop/hbase/client/TestClientScanner
       2: invokestatic  #116                // Method org/apache/hadoop/hbase/HBaseClassTestRule.forClass:(Ljava/lang/Class;)Lorg/apache/hadoop/hbase/HBaseClassTestRule;
       5: putstatic     #117                // Field CLASS_RULE:Lorg/apache/hadoop/hbase/HBaseClassTestRule;
       8: return
}
