Compiled from "TestClientTimeouts.java"
public class org.apache.hadoop.hbase.client.TestClientTimeouts$RandomTimeoutRpcClient extends org.apache.hadoop.hbase.ipc.BlockingRpcClient {
  public org.apache.hadoop.hbase.client.TestClientTimeouts$RandomTimeoutRpcClient(org.apache.hadoop.conf.Configuration, java.lang.String, java.net.SocketAddress, org.apache.hadoop.hbase.client.MetricsConnection);
    Code:
       0: aload_0
       1: aload_1
       2: aload_2
       3: aload_3
       4: aload         4
       6: invokespecial #1                  // Method org/apache/hadoop/hbase/ipc/BlockingRpcClient."<init>":(Lorg/apache/hadoop/conf/Configuration;Ljava/lang/String;Ljava/net/SocketAddress;Lorg/apache/hadoop/hbase/client/MetricsConnection;)V
       9: return

  public org.apache.hbase.thirdparty.com.google.protobuf.BlockingRpcChannel createBlockingRpcChannel(org.apache.hadoop.hbase.ServerName, org.apache.hadoop.hbase.security.User, int) throws java.net.UnknownHostException;
    Code:
       0: new           #2                  // class org/apache/hadoop/hbase/client/TestClientTimeouts$RandomTimeoutBlockingRpcChannel
       3: dup
       4: aload_0
       5: aload_1
       6: aload_2
       7: iload_3
       8: invokespecial #3                  // Method org/apache/hadoop/hbase/client/TestClientTimeouts$RandomTimeoutBlockingRpcChannel."<init>":(Lorg/apache/hadoop/hbase/ipc/BlockingRpcClient;Lorg/apache/hadoop/hbase/ServerName;Lorg/apache/hadoop/hbase/security/User;I)V
      11: areturn
}
