Compiled from "TestMasterCoprocessorServices.java"
class org.apache.hadoop.hbase.master.TestMasterCoprocessorServices$MockAccessController implements org.apache.hadoop.hbase.protobuf.generated.AccessControlProtos$AccessControlService$Interface,org.apache.hadoop.hbase.coprocessor.MasterCoprocessor,org.apache.hadoop.hbase.coprocessor.RegionCoprocessor,org.apache.hadoop.hbase.coprocessor.MasterObserver,org.apache.hadoop.hbase.coprocessor.RegionObserver {
  public void grant(com.google.protobuf.RpcController, org.apache.hadoop.hbase.protobuf.generated.AccessControlProtos$GrantRequest, com.google.protobuf.RpcCallback<org.apache.hadoop.hbase.protobuf.generated.AccessControlProtos$GrantResponse>);
    Code:
       0: return

  public void revoke(com.google.protobuf.RpcController, org.apache.hadoop.hbase.protobuf.generated.AccessControlProtos$RevokeRequest, com.google.protobuf.RpcCallback<org.apache.hadoop.hbase.protobuf.generated.AccessControlProtos$RevokeResponse>);
    Code:
       0: return

  public void getUserPermissions(com.google.protobuf.RpcController, org.apache.hadoop.hbase.protobuf.generated.AccessControlProtos$GetUserPermissionsRequest, com.google.protobuf.RpcCallback<org.apache.hadoop.hbase.protobuf.generated.AccessControlProtos$GetUserPermissionsResponse>);
    Code:
       0: return

  public void checkPermissions(com.google.protobuf.RpcController, org.apache.hadoop.hbase.protobuf.generated.AccessControlProtos$CheckPermissionsRequest, com.google.protobuf.RpcCallback<org.apache.hadoop.hbase.protobuf.generated.AccessControlProtos$CheckPermissionsResponse>);
    Code:
       0: return

  public void hasPermission(com.google.protobuf.RpcController, org.apache.hadoop.hbase.protobuf.generated.AccessControlProtos$HasPermissionRequest, com.google.protobuf.RpcCallback<org.apache.hadoop.hbase.protobuf.generated.AccessControlProtos$HasPermissionResponse>);
    Code:
       0: return

  org.apache.hadoop.hbase.master.TestMasterCoprocessorServices$MockAccessController(org.apache.hadoop.hbase.master.TestMasterCoprocessorServices$1);
    Code:
       0: aload_0
       1: invokespecial #1                  // Method "<init>":()V
       4: return
}
