Compiled from "TestAccessController.java"
class org.apache.hadoop.hbase.security.access.TestAccessController$4 implements org.apache.hadoop.hbase.security.access.SecureTestUtil$AccessTestAction {
  final org.apache.hadoop.hbase.security.access.TestAccessController this$0;

  org.apache.hadoop.hbase.security.access.TestAccessController$4(org.apache.hadoop.hbase.security.access.TestAccessController);
    Code:
       0: aload_0
       1: aload_1
       2: putfield      #1                  // Field this$0:Lorg/apache/hadoop/hbase/security/access/TestAccessController;
       5: aload_0
       6: invokespecial #2                  // Method java/lang/Object."<init>":()V
       9: return

  public java.lang.Object run() throws java.lang.Exception;
    Code:
       0: new           #3                  // class org/apache/hadoop/hbase/HTableDescriptor
       3: dup
       4: invokestatic  #4                  // Method org/apache/hadoop/hbase/security/access/TestAccessController.access$400:()Lorg/apache/hadoop/hbase/TableName;
       7: invokespecial #5                  // Method org/apache/hadoop/hbase/HTableDescriptor."<init>":(Lorg/apache/hadoop/hbase/TableName;)V
      10: astore_1
      11: aload_1
      12: new           #6                  // class org/apache/hadoop/hbase/HColumnDescriptor
      15: dup
      16: invokestatic  #7                  // Method org/apache/hadoop/hbase/security/access/TestAccessController.access$100:()[B
      19: invokespecial #8                  // Method org/apache/hadoop/hbase/HColumnDescriptor."<init>":([B)V
      22: invokevirtual #9                  // Method org/apache/hadoop/hbase/HTableDescriptor.addFamily:(Lorg/apache/hadoop/hbase/HColumnDescriptor;)Lorg/apache/hadoop/hbase/HTableDescriptor;
      25: pop
      26: aload_1
      27: new           #6                  // class org/apache/hadoop/hbase/HColumnDescriptor
      30: dup
      31: new           #10                 // class java/lang/StringBuilder
      34: dup
      35: invokespecial #11                 // Method java/lang/StringBuilder."<init>":()V
      38: ldc           #12                 // String fam_
      40: invokevirtual #13                 // Method java/lang/StringBuilder.append:(Ljava/lang/String;)Ljava/lang/StringBuilder;
      43: invokestatic  #14                 // Method org/apache/hadoop/hbase/security/User.getCurrent:()Lorg/apache/hadoop/hbase/security/User;
      46: invokevirtual #15                 // Method org/apache/hadoop/hbase/security/User.getShortName:()Ljava/lang/String;
      49: invokevirtual #13                 // Method java/lang/StringBuilder.append:(Ljava/lang/String;)Ljava/lang/StringBuilder;
      52: invokevirtual #16                 // Method java/lang/StringBuilder.toString:()Ljava/lang/String;
      55: invokespecial #17                 // Method org/apache/hadoop/hbase/HColumnDescriptor."<init>":(Ljava/lang/String;)V
      58: invokevirtual #9                  // Method org/apache/hadoop/hbase/HTableDescriptor.addFamily:(Lorg/apache/hadoop/hbase/HColumnDescriptor;)Lorg/apache/hadoop/hbase/HTableDescriptor;
      61: pop
      62: invokestatic  #18                 // Method org/apache/hadoop/hbase/security/access/TestAccessController.access$300:()Lorg/apache/hadoop/hbase/security/access/AccessController;
      65: invokestatic  #19                 // Method org/apache/hadoop/hbase/security/access/TestAccessController.access$200:()Lorg/apache/hadoop/hbase/coprocessor/MasterCoprocessorEnvironment;
      68: invokestatic  #20                 // Method org/apache/hadoop/hbase/coprocessor/ObserverContextImpl.createAndPrepare:(Lorg/apache/hadoop/hbase/CoprocessorEnvironment;)Lorg/apache/hadoop/hbase/coprocessor/ObserverContext;
      71: invokestatic  #4                  // Method org/apache/hadoop/hbase/security/access/TestAccessController.access$400:()Lorg/apache/hadoop/hbase/TableName;
      74: aconst_null
      75: aload_1
      76: invokevirtual #21                 // Method org/apache/hadoop/hbase/security/access/AccessController.preModifyTable:(Lorg/apache/hadoop/hbase/coprocessor/ObserverContext;Lorg/apache/hadoop/hbase/TableName;Lorg/apache/hadoop/hbase/client/TableDescriptor;Lorg/apache/hadoop/hbase/client/TableDescriptor;)Lorg/apache/hadoop/hbase/client/TableDescriptor;
      79: pop
      80: aconst_null
      81: areturn
}
