Compiled from "TestRegionReplicas.java"
class org.apache.hadoop.hbase.regionserver.TestRegionReplicas$2 implements java.lang.Runnable {
  java.util.Random random;

  final java.util.concurrent.atomic.AtomicBoolean val$running;

  final java.util.concurrent.atomic.AtomicReference[] val$exceptions;

  final org.apache.hadoop.hbase.regionserver.TestRegionReplicas this$0;

  org.apache.hadoop.hbase.regionserver.TestRegionReplicas$2(org.apache.hadoop.hbase.regionserver.TestRegionReplicas, java.util.concurrent.atomic.AtomicBoolean, java.util.concurrent.atomic.AtomicReference[]);
    Code:
       0: aload_0
       1: aload_1
       2: putfield      #1                  // Field this$0:Lorg/apache/hadoop/hbase/regionserver/TestRegionReplicas;
       5: aload_0
       6: aload_2
       7: putfield      #2                  // Field val$running:Ljava/util/concurrent/atomic/AtomicBoolean;
      10: aload_0
      11: aload_3
      12: putfield      #3                  // Field val$exceptions:[Ljava/util/concurrent/atomic/AtomicReference;
      15: aload_0
      16: invokespecial #4                  // Method java/lang/Object."<init>":()V
      19: aload_0
      20: new           #5                  // class java/util/Random
      23: dup
      24: invokespecial #6                  // Method java/util/Random."<init>":()V
      27: putfield      #7                  // Field random:Ljava/util/Random;
      30: return

  public void run();
    Code:
       0: aload_0
       1: getfield      #2                  // Field val$running:Ljava/util/concurrent/atomic/AtomicBoolean;
       4: invokevirtual #8                  // Method java/util/concurrent/atomic/AtomicBoolean.get:()Z
       7: ifeq          56
      10: aload_0
      11: getfield      #7                  // Field random:Ljava/util/Random;
      14: invokevirtual #9                  // Method java/util/Random.nextBoolean:()Z
      17: ifeq          32
      20: invokestatic  #10                 // Method org/apache/hadoop/hbase/regionserver/TestRegionReplicas.access$300:()Lorg/apache/hadoop/hbase/HBaseTestingUtility;
      23: invokestatic  #11                 // Method org/apache/hadoop/hbase/regionserver/TestRegionReplicas.access$400:()Lorg/apache/hadoop/hbase/HRegionInfo;
      26: invokestatic  #12                 // Method org/apache/hadoop/hbase/regionserver/TestRegionServerNoMaster.flushRegion:(Lorg/apache/hadoop/hbase/HBaseTestingUtility;Lorg/apache/hadoop/hbase/HRegionInfo;)V
      29: goto          0
      32: invokestatic  #10                 // Method org/apache/hadoop/hbase/regionserver/TestRegionReplicas.access$300:()Lorg/apache/hadoop/hbase/HBaseTestingUtility;
      35: invokestatic  #13                 // Method org/apache/hadoop/hbase/regionserver/TestRegionReplicas.access$100:()Lorg/apache/hadoop/hbase/client/Table;
      38: invokeinterface #14,  1           // InterfaceMethod org/apache/hadoop/hbase/client/Table.getName:()Lorg/apache/hadoop/hbase/TableName;
      43: aload_0
      44: getfield      #7                  // Field random:Ljava/util/Random;
      47: invokevirtual #9                  // Method java/util/Random.nextBoolean:()Z
      50: invokevirtual #15                 // Method org/apache/hadoop/hbase/HBaseTestingUtility.compact:(Lorg/apache/hadoop/hbase/TableName;Z)V
      53: goto          0
      56: goto          85
      59: astore_1
      60: invokestatic  #17                 // Method org/apache/hadoop/hbase/regionserver/TestRegionReplicas.access$200:()Lorg/slf4j/Logger;
      63: aload_1
      64: invokevirtual #18                 // Method java/lang/Exception.toString:()Ljava/lang/String;
      67: aload_1
      68: invokeinterface #19,  3           // InterfaceMethod org/slf4j/Logger.warn:(Ljava/lang/String;Ljava/lang/Throwable;)V
      73: aload_0
      74: getfield      #3                  // Field val$exceptions:[Ljava/util/concurrent/atomic/AtomicReference;
      77: iconst_1
      78: aaload
      79: aconst_null
      80: aload_1
      81: invokevirtual #20                 // Method java/util/concurrent/atomic/AtomicReference.compareAndSet:(Ljava/lang/Object;Ljava/lang/Object;)Z
      84: pop
      85: return
    Exception table:
       from    to  target type
           0    56    59   Class java/lang/Exception
}
