Compiled from "TestAsyncMetaRegionLocatorFailFast.java"
public class org.apache.hadoop.hbase.client.TestAsyncMetaRegionLocatorFailFast {
  public static final org.apache.hadoop.hbase.HBaseClassTestRule CLASS_RULE;

  public org.apache.hadoop.hbase.client.TestAsyncMetaRegionLocatorFailFast();
    Code:
       0: aload_0
       1: invokespecial #1                  // Method java/lang/Object."<init>":()V
       4: return

  public static void setUp();
    Code:
       0: new           #2                  // class org/apache/hadoop/hbase/client/AsyncMetaRegionLocator
       3: dup
       4: new           #3                  // class org/apache/hadoop/hbase/client/TestAsyncMetaRegionLocatorFailFast$FaultyAsyncRegistry
       7: dup
       8: getstatic     #4                  // Field CONF:Lorg/apache/hadoop/conf/Configuration;
      11: invokespecial #5                  // Method org/apache/hadoop/hbase/client/TestAsyncMetaRegionLocatorFailFast$FaultyAsyncRegistry."<init>":(Lorg/apache/hadoop/conf/Configuration;)V
      14: invokespecial #6                  // Method org/apache/hadoop/hbase/client/AsyncMetaRegionLocator."<init>":(Lorg/apache/hadoop/hbase/client/AsyncRegistry;)V
      17: putstatic     #7                  // Field LOCATOR:Lorg/apache/hadoop/hbase/client/AsyncMetaRegionLocator;
      20: return

  public void test() throws java.io.IOException;
    Code:
       0: getstatic     #7                  // Field LOCATOR:Lorg/apache/hadoop/hbase/client/AsyncMetaRegionLocator;
       3: iconst_0
       4: iconst_0
       5: invokevirtual #9                  // Method org/apache/hadoop/hbase/client/AsyncMetaRegionLocator.getRegionLocations:(IZ)Ljava/util/concurrent/CompletableFuture;
       8: invokestatic  #10                 // Method org/apache/hadoop/hbase/util/FutureUtils.get:(Ljava/util/concurrent/Future;)Ljava/lang/Object;
      11: pop
      12: return

  static {};
    Code:
       0: ldc           #11                 // class org/apache/hadoop/hbase/client/TestAsyncMetaRegionLocatorFailFast
       2: invokestatic  #12                 // Method org/apache/hadoop/hbase/HBaseClassTestRule.forClass:(Ljava/lang/Class;)Lorg/apache/hadoop/hbase/HBaseClassTestRule;
       5: putstatic     #13                 // Field CLASS_RULE:Lorg/apache/hadoop/hbase/HBaseClassTestRule;
       8: invokestatic  #14                 // Method org/apache/hadoop/hbase/HBaseConfiguration.create:()Lorg/apache/hadoop/conf/Configuration;
      11: putstatic     #4                  // Field CONF:Lorg/apache/hadoop/conf/Configuration;
      14: return
}
