Compiled from "TestRegionLoad.java"
public class org.apache.hadoop.hbase.TestRegionLoad {
  public static final org.apache.hadoop.hbase.HBaseClassTestRule CLASS_RULE;

  public org.apache.hadoop.hbase.TestRegionLoad();
    Code:
       0: aload_0
       1: invokespecial #1                  // Method java/lang/Object."<init>":()V
       4: return

  public static void beforeClass() throws java.lang.Exception;
    Code:
       0: getstatic     #2                  // Field UTIL:Lorg/apache/hadoop/hbase/HBaseTestingUtility;
       3: invokevirtual #3                  // Method org/apache/hadoop/hbase/HBaseTestingUtility.getConfiguration:()Lorg/apache/hadoop/conf/Configuration;
       6: ldc           #4                  // String hbase.regionserver.msginterval
       8: sipush        500
      11: invokevirtual #6                  // Method org/apache/hadoop/conf/Configuration.setInt:(Ljava/lang/String;I)V
      14: getstatic     #2                  // Field UTIL:Lorg/apache/hadoop/hbase/HBaseTestingUtility;
      17: iconst_4
      18: invokevirtual #7                  // Method org/apache/hadoop/hbase/HBaseTestingUtility.startMiniCluster:(I)Lorg/apache/hadoop/hbase/MiniHBaseCluster;
      21: pop
      22: getstatic     #2                  // Field UTIL:Lorg/apache/hadoop/hbase/HBaseTestingUtility;
      25: invokevirtual #8                  // Method org/apache/hadoop/hbase/HBaseTestingUtility.getAdmin:()Lorg/apache/hadoop/hbase/client/Admin;
      28: putstatic     #9                  // Field admin:Lorg/apache/hadoop/hbase/client/Admin;
      31: getstatic     #9                  // Field admin:Lorg/apache/hadoop/hbase/client/Admin;
      34: iconst_0
      35: iconst_1
      36: invokeinterface #10,  3           // InterfaceMethod org/apache/hadoop/hbase/client/Admin.balancerSwitch:(ZZ)Z
      41: pop
      42: invokestatic  #11                 // Method createTables:()V
      45: return

  public static void afterClass() throws java.lang.Exception;
    Code:
       0: getstatic     #2                  // Field UTIL:Lorg/apache/hadoop/hbase/HBaseTestingUtility;
       3: invokevirtual #12                 // Method org/apache/hadoop/hbase/HBaseTestingUtility.shutdownMiniCluster:()V
       6: return

  public void testRegionLoad() throws java.lang.Exception;
    Code:
       0: getstatic     #9                  // Field admin:Lorg/apache/hadoop/hbase/client/Admin;
       3: getstatic     #21                 // Field org/apache/hadoop/hbase/ClusterMetrics$Option.LIVE_SERVERS:Lorg/apache/hadoop/hbase/ClusterMetrics$Option;
       6: invokestatic  #22                 // Method java/util/EnumSet.of:(Ljava/lang/Enum;)Ljava/util/EnumSet;
       9: invokeinterface #23,  2           // InterfaceMethod org/apache/hadoop/hbase/client/Admin.getClusterMetrics:(Ljava/util/EnumSet;)Lorg/apache/hadoop/hbase/ClusterMetrics;
      14: invokeinterface #24,  1           // InterfaceMethod org/apache/hadoop/hbase/ClusterMetrics.getLiveServerMetrics:()Ljava/util/Map;
      19: invokeinterface #25,  1           // InterfaceMethod java/util/Map.keySet:()Ljava/util/Set;
      24: invokeinterface #26,  1           // InterfaceMethod java/util/Set.iterator:()Ljava/util/Iterator;
      29: astore_1
      30: aload_1
      31: invokeinterface #27,  1           // InterfaceMethod java/util/Iterator.hasNext:()Z
      36: ifeq          225
      39: aload_1
      40: invokeinterface #28,  1           // InterfaceMethod java/util/Iterator.next:()Ljava/lang/Object;
      45: checkcast     #29                 // class org/apache/hadoop/hbase/ServerName
      48: astore_2
      49: getstatic     #9                  // Field admin:Lorg/apache/hadoop/hbase/client/Admin;
      52: aload_2
      53: invokeinterface #30,  2           // InterfaceMethod org/apache/hadoop/hbase/client/Admin.getRegions:(Lorg/apache/hadoop/hbase/ServerName;)Ljava/util/List;
      58: astore_3
      59: getstatic     #31                 // Field LOG:Lorg/slf4j/Logger;
      62: new           #32                 // class java/lang/StringBuilder
      65: dup
      66: invokespecial #33                 // Method java/lang/StringBuilder."<init>":()V
      69: ldc           #34                 // String serverName=
      71: invokevirtual #35                 // Method java/lang/StringBuilder.append:(Ljava/lang/String;)Ljava/lang/StringBuilder;
      74: aload_2
      75: invokevirtual #36                 // Method java/lang/StringBuilder.append:(Ljava/lang/Object;)Ljava/lang/StringBuilder;
      78: ldc           #37                 // String , regions=
      80: invokevirtual #35                 // Method java/lang/StringBuilder.append:(Ljava/lang/String;)Ljava/lang/StringBuilder;
      83: aload_3
      84: invokeinterface #38,  1           // InterfaceMethod java/util/List.stream:()Ljava/util/stream/Stream;
      89: invokedynamic #39,  0             // InvokeDynamic #0:apply:()Ljava/util/function/Function;
      94: invokeinterface #40,  2           // InterfaceMethod java/util/stream/Stream.map:(Ljava/util/function/Function;)Ljava/util/stream/Stream;
      99: invokestatic  #41                 // Method java/util/stream/Collectors.toList:()Ljava/util/stream/Collector;
     102: invokeinterface #42,  2           // InterfaceMethod java/util/stream/Stream.collect:(Ljava/util/stream/Collector;)Ljava/lang/Object;
     107: invokevirtual #36                 // Method java/lang/StringBuilder.append:(Ljava/lang/Object;)Ljava/lang/StringBuilder;
     110: invokevirtual #43                 // Method java/lang/StringBuilder.toString:()Ljava/lang/String;
     113: invokeinterface #44,  2           // InterfaceMethod org/slf4j/Logger.info:(Ljava/lang/String;)V
     118: getstatic     #9                  // Field admin:Lorg/apache/hadoop/hbase/client/Admin;
     121: aload_2
     122: invokeinterface #45,  2           // InterfaceMethod org/apache/hadoop/hbase/client/Admin.getRegionMetrics:(Lorg/apache/hadoop/hbase/ServerName;)Ljava/util/List;
     127: invokeinterface #38,  1           // InterfaceMethod java/util/List.stream:()Ljava/util/stream/Stream;
     132: invokedynamic #46,  0             // InvokeDynamic #1:apply:()Ljava/util/function/Function;
     137: invokeinterface #40,  2           // InterfaceMethod java/util/stream/Stream.map:(Ljava/util/function/Function;)Ljava/util/stream/Stream;
     142: invokestatic  #41                 // Method java/util/stream/Collectors.toList:()Ljava/util/stream/Collector;
     145: invokeinterface #42,  2           // InterfaceMethod java/util/stream/Stream.collect:(Ljava/util/stream/Collector;)Ljava/lang/Object;
     150: checkcast     #47                 // class java/util/Collection
     153: astore        4
     155: getstatic     #31                 // Field LOG:Lorg/slf4j/Logger;
     158: new           #32                 // class java/lang/StringBuilder
     161: dup
     162: invokespecial #33                 // Method java/lang/StringBuilder."<init>":()V
     165: ldc           #34                 // String serverName=
     167: invokevirtual #35                 // Method java/lang/StringBuilder.append:(Ljava/lang/String;)Ljava/lang/StringBuilder;
     170: aload_2
     171: invokevirtual #36                 // Method java/lang/StringBuilder.append:(Ljava/lang/Object;)Ljava/lang/StringBuilder;
     174: ldc           #48                 // String , regionLoads=
     176: invokevirtual #35                 // Method java/lang/StringBuilder.append:(Ljava/lang/String;)Ljava/lang/StringBuilder;
     179: aload         4
     181: invokeinterface #49,  1           // InterfaceMethod java/util/Collection.stream:()Ljava/util/stream/Stream;
     186: invokedynamic #50,  0             // InvokeDynamic #2:apply:()Ljava/util/function/Function;
     191: invokeinterface #40,  2           // InterfaceMethod java/util/stream/Stream.map:(Ljava/util/function/Function;)Ljava/util/stream/Stream;
     196: invokestatic  #41                 // Method java/util/stream/Collectors.toList:()Ljava/util/stream/Collector;
     199: invokeinterface #42,  2           // InterfaceMethod java/util/stream/Stream.collect:(Ljava/util/stream/Collector;)Ljava/lang/Object;
     204: invokevirtual #36                 // Method java/lang/StringBuilder.append:(Ljava/lang/Object;)Ljava/lang/StringBuilder;
     207: invokevirtual #43                 // Method java/lang/StringBuilder.toString:()Ljava/lang/String;
     210: invokeinterface #44,  2           // InterfaceMethod org/slf4j/Logger.info:(Ljava/lang/String;)V
     215: aload_0
     216: aload_3
     217: aload         4
     219: invokespecial #51                 // Method checkRegionsAndRegionLoads:(Ljava/util/Collection;Ljava/util/Collection;)V
     222: goto          30
     225: iconst_3
     226: anewarray     #52                 // class org/apache/hadoop/hbase/TableName
     229: dup
     230: iconst_0
     231: getstatic     #53                 // Field TABLE_1:Lorg/apache/hadoop/hbase/TableName;
     234: aastore
     235: dup
     236: iconst_1
     237: getstatic     #54                 // Field TABLE_2:Lorg/apache/hadoop/hbase/TableName;
     240: aastore
     241: dup
     242: iconst_2
     243: getstatic     #55                 // Field TABLE_3:Lorg/apache/hadoop/hbase/TableName;
     246: aastore
     247: astore_1
     248: aload_1
     249: arraylength
     250: istore_2
     251: iconst_0
     252: istore_3
     253: iload_3
     254: iload_2
     255: if_icmpge     396
     258: aload_1
     259: iload_3
     260: aaload
     261: astore        4
     263: getstatic     #9                  // Field admin:Lorg/apache/hadoop/hbase/client/Admin;
     266: aload         4
     268: invokeinterface #56,  2           // InterfaceMethod org/apache/hadoop/hbase/client/Admin.getRegions:(Lorg/apache/hadoop/hbase/TableName;)Ljava/util/List;
     273: astore        5
     275: invokestatic  #57                 // Method org/apache/hbase/thirdparty/com/google/common/collect/Lists.newArrayList:()Ljava/util/ArrayList;
     278: astore        6
     280: getstatic     #9                  // Field admin:Lorg/apache/hadoop/hbase/client/Admin;
     283: getstatic     #21                 // Field org/apache/hadoop/hbase/ClusterMetrics$Option.LIVE_SERVERS:Lorg/apache/hadoop/hbase/ClusterMetrics$Option;
     286: invokestatic  #22                 // Method java/util/EnumSet.of:(Ljava/lang/Enum;)Ljava/util/EnumSet;
     289: invokeinterface #23,  2           // InterfaceMethod org/apache/hadoop/hbase/client/Admin.getClusterMetrics:(Ljava/util/EnumSet;)Lorg/apache/hadoop/hbase/ClusterMetrics;
     294: invokeinterface #24,  1           // InterfaceMethod org/apache/hadoop/hbase/ClusterMetrics.getLiveServerMetrics:()Ljava/util/Map;
     299: invokeinterface #25,  1           // InterfaceMethod java/util/Map.keySet:()Ljava/util/Set;
     304: invokeinterface #26,  1           // InterfaceMethod java/util/Set.iterator:()Ljava/util/Iterator;
     309: astore        7
     311: aload         7
     313: invokeinterface #27,  1           // InterfaceMethod java/util/Iterator.hasNext:()Z
     318: ifeq          382
     321: aload         7
     323: invokeinterface #28,  1           // InterfaceMethod java/util/Iterator.next:()Ljava/lang/Object;
     328: checkcast     #29                 // class org/apache/hadoop/hbase/ServerName
     331: astore        8
     333: aload         6
     335: getstatic     #9                  // Field admin:Lorg/apache/hadoop/hbase/client/Admin;
     338: aload         8
     340: aload         4
     342: invokeinterface #58,  3           // InterfaceMethod org/apache/hadoop/hbase/client/Admin.getRegionMetrics:(Lorg/apache/hadoop/hbase/ServerName;Lorg/apache/hadoop/hbase/TableName;)Ljava/util/List;
     347: invokeinterface #38,  1           // InterfaceMethod java/util/List.stream:()Ljava/util/stream/Stream;
     352: invokedynamic #59,  0             // InvokeDynamic #3:apply:()Ljava/util/function/Function;
     357: invokeinterface #40,  2           // InterfaceMethod java/util/stream/Stream.map:(Ljava/util/function/Function;)Ljava/util/stream/Stream;
     362: invokestatic  #41                 // Method java/util/stream/Collectors.toList:()Ljava/util/stream/Collector;
     365: invokeinterface #42,  2           // InterfaceMethod java/util/stream/Stream.collect:(Ljava/util/stream/Collector;)Ljava/lang/Object;
     370: checkcast     #47                 // class java/util/Collection
     373: invokeinterface #60,  2           // InterfaceMethod java/util/List.addAll:(Ljava/util/Collection;)Z
     378: pop
     379: goto          311
     382: aload_0
     383: aload         5
     385: aload         6
     387: invokespecial #51                 // Method checkRegionsAndRegionLoads:(Ljava/util/Collection;Ljava/util/Collection;)V
     390: iinc          3, 1
     393: goto          253
     396: getstatic     #61                 // Field java/util/concurrent/TimeUnit.MILLISECONDS:Ljava/util/concurrent/TimeUnit;
     399: ldc2_w        #62                 // long 1500l
     402: invokevirtual #64                 // Method java/util/concurrent/TimeUnit.sleep:(J)V
     405: new           #65                 // class org/apache/hadoop/hbase/ClusterStatus
     408: dup
     409: getstatic     #9                  // Field admin:Lorg/apache/hadoop/hbase/client/Admin;
     412: getstatic     #21                 // Field org/apache/hadoop/hbase/ClusterMetrics$Option.LIVE_SERVERS:Lorg/apache/hadoop/hbase/ClusterMetrics$Option;
     415: invokestatic  #22                 // Method java/util/EnumSet.of:(Ljava/lang/Enum;)Ljava/util/EnumSet;
     418: invokeinterface #23,  2           // InterfaceMethod org/apache/hadoop/hbase/client/Admin.getClusterMetrics:(Ljava/util/EnumSet;)Lorg/apache/hadoop/hbase/ClusterMetrics;
     423: invokespecial #66                 // Method org/apache/hadoop/hbase/ClusterStatus."<init>":(Lorg/apache/hadoop/hbase/ClusterMetrics;)V
     426: astore_1
     427: aload_1
     428: invokevirtual #67                 // Method org/apache/hadoop/hbase/ClusterStatus.getServers:()Ljava/util/Collection;
     431: invokeinterface #68,  1           // InterfaceMethod java/util/Collection.iterator:()Ljava/util/Iterator;
     436: astore_2
     437: aload_2
     438: invokeinterface #27,  1           // InterfaceMethod java/util/Iterator.hasNext:()Z
     443: ifeq          657
     446: aload_2
     447: invokeinterface #28,  1           // InterfaceMethod java/util/Iterator.next:()Ljava/lang/Object;
     452: checkcast     #29                 // class org/apache/hadoop/hbase/ServerName
     455: astore_3
     456: aload_1
     457: aload_3
     458: invokevirtual #69                 // Method org/apache/hadoop/hbase/ClusterStatus.getLoad:(Lorg/apache/hadoop/hbase/ServerName;)Lorg/apache/hadoop/hbase/ServerLoad;
     461: astore        4
     463: getstatic     #9                  // Field admin:Lorg/apache/hadoop/hbase/client/Admin;
     466: aload_3
     467: invokeinterface #45,  2           // InterfaceMethod org/apache/hadoop/hbase/client/Admin.getRegionMetrics:(Lorg/apache/hadoop/hbase/ServerName;)Ljava/util/List;
     472: invokeinterface #38,  1           // InterfaceMethod java/util/List.stream:()Ljava/util/stream/Stream;
     477: invokedynamic #70,  0             // InvokeDynamic #4:apply:()Ljava/util/function/Function;
     482: invokedynamic #71,  0             // InvokeDynamic #5:apply:()Ljava/util/function/Function;
     487: invokedynamic #72,  0             // InvokeDynamic #6:apply:()Ljava/util/function/BinaryOperator;
     492: invokedynamic #73,  0             // InvokeDynamic #7:get:()Ljava/util/function/Supplier;
     497: invokestatic  #74                 // Method java/util/stream/Collectors.toMap:(Ljava/util/function/Function;Ljava/util/function/Function;Ljava/util/function/BinaryOperator;Ljava/util/function/Supplier;)Ljava/util/stream/Collector;
     500: invokeinterface #42,  2           // InterfaceMethod java/util/stream/Stream.collect:(Ljava/util/stream/Collector;)Ljava/lang/Object;
     505: checkcast     #75                 // class java/util/Map
     508: astore        5
     510: getstatic     #31                 // Field LOG:Lorg/slf4j/Logger;
     513: new           #32                 // class java/lang/StringBuilder
     516: dup
     517: invokespecial #33                 // Method java/lang/StringBuilder."<init>":()V
     520: ldc           #34                 // String serverName=
     522: invokevirtual #35                 // Method java/lang/StringBuilder.append:(Ljava/lang/String;)Ljava/lang/StringBuilder;
     525: aload_3
     526: invokevirtual #36                 // Method java/lang/StringBuilder.append:(Ljava/lang/Object;)Ljava/lang/StringBuilder;
     529: ldc           #76                 // String , getRegionLoads=
     531: invokevirtual #35                 // Method java/lang/StringBuilder.append:(Ljava/lang/String;)Ljava/lang/StringBuilder;
     534: aload         4
     536: invokevirtual #77                 // Method org/apache/hadoop/hbase/ServerLoad.getRegionsLoad:()Ljava/util/Map;
     539: invokeinterface #25,  1           // InterfaceMethod java/util/Map.keySet:()Ljava/util/Set;
     544: invokeinterface #78,  1           // InterfaceMethod java/util/Set.stream:()Ljava/util/stream/Stream;
     549: invokedynamic #79,  0             // InvokeDynamic #8:apply:()Ljava/util/function/Function;
     554: invokeinterface #40,  2           // InterfaceMethod java/util/stream/Stream.map:(Ljava/util/function/Function;)Ljava/util/stream/Stream;
     559: invokestatic  #41                 // Method java/util/stream/Collectors.toList:()Ljava/util/stream/Collector;
     562: invokeinterface #42,  2           // InterfaceMethod java/util/stream/Stream.collect:(Ljava/util/stream/Collector;)Ljava/lang/Object;
     567: invokevirtual #36                 // Method java/lang/StringBuilder.append:(Ljava/lang/Object;)Ljava/lang/StringBuilder;
     570: invokevirtual #43                 // Method java/lang/StringBuilder.toString:()Ljava/lang/String;
     573: invokeinterface #80,  2           // InterfaceMethod org/slf4j/Logger.debug:(Ljava/lang/String;)V
     578: getstatic     #31                 // Field LOG:Lorg/slf4j/Logger;
     581: new           #32                 // class java/lang/StringBuilder
     584: dup
     585: invokespecial #33                 // Method java/lang/StringBuilder."<init>":()V
     588: ldc           #34                 // String serverName=
     590: invokevirtual #35                 // Method java/lang/StringBuilder.append:(Ljava/lang/String;)Ljava/lang/StringBuilder;
     593: aload_3
     594: invokevirtual #36                 // Method java/lang/StringBuilder.append:(Ljava/lang/Object;)Ljava/lang/StringBuilder;
     597: ldc           #48                 // String , regionLoads=
     599: invokevirtual #35                 // Method java/lang/StringBuilder.append:(Ljava/lang/String;)Ljava/lang/StringBuilder;
     602: aload         5
     604: invokeinterface #25,  1           // InterfaceMethod java/util/Map.keySet:()Ljava/util/Set;
     609: invokeinterface #78,  1           // InterfaceMethod java/util/Set.stream:()Ljava/util/stream/Stream;
     614: invokedynamic #81,  0             // InvokeDynamic #9:apply:()Ljava/util/function/Function;
     619: invokeinterface #40,  2           // InterfaceMethod java/util/stream/Stream.map:(Ljava/util/function/Function;)Ljava/util/stream/Stream;
     624: invokestatic  #41                 // Method java/util/stream/Collectors.toList:()Ljava/util/stream/Collector;
     627: invokeinterface #42,  2           // InterfaceMethod java/util/stream/Stream.collect:(Ljava/util/stream/Collector;)Ljava/lang/Object;
     632: invokevirtual #36                 // Method java/lang/StringBuilder.append:(Ljava/lang/Object;)Ljava/lang/StringBuilder;
     635: invokevirtual #43                 // Method java/lang/StringBuilder.toString:()Ljava/lang/String;
     638: invokeinterface #80,  2           // InterfaceMethod org/slf4j/Logger.debug:(Ljava/lang/String;)V
     643: aload_0
     644: aload         4
     646: invokevirtual #77                 // Method org/apache/hadoop/hbase/ServerLoad.getRegionsLoad:()Ljava/util/Map;
     649: aload         5
     651: invokespecial #82                 // Method compareRegionLoads:(Ljava/util/Map;Ljava/util/Map;)V
     654: goto          437
     657: return

  static {};
    Code:
       0: ldc           #5                  // class org/apache/hadoop/hbase/TestRegionLoad
       2: invokestatic  #113                // Method org/apache/hadoop/hbase/HBaseClassTestRule.forClass:(Ljava/lang/Class;)Lorg/apache/hadoop/hbase/HBaseClassTestRule;
       5: putstatic     #114                // Field CLASS_RULE:Lorg/apache/hadoop/hbase/HBaseClassTestRule;
       8: ldc           #5                  // class org/apache/hadoop/hbase/TestRegionLoad
      10: invokestatic  #115                // Method org/slf4j/LoggerFactory.getLogger:(Ljava/lang/Class;)Lorg/slf4j/Logger;
      13: putstatic     #31                 // Field LOG:Lorg/slf4j/Logger;
      16: new           #116                // class org/apache/hadoop/hbase/HBaseTestingUtility
      19: dup
      20: invokespecial #117                // Method org/apache/hadoop/hbase/HBaseTestingUtility."<init>":()V
      23: putstatic     #2                  // Field UTIL:Lorg/apache/hadoop/hbase/HBaseTestingUtility;
      26: ldc           #118                // String table_1
      28: invokestatic  #119                // Method org/apache/hadoop/hbase/TableName.valueOf:(Ljava/lang/String;)Lorg/apache/hadoop/hbase/TableName;
      31: putstatic     #53                 // Field TABLE_1:Lorg/apache/hadoop/hbase/TableName;
      34: ldc           #120                // String table_2
      36: invokestatic  #119                // Method org/apache/hadoop/hbase/TableName.valueOf:(Ljava/lang/String;)Lorg/apache/hadoop/hbase/TableName;
      39: putstatic     #54                 // Field TABLE_2:Lorg/apache/hadoop/hbase/TableName;
      42: ldc           #121                // String table_3
      44: invokestatic  #119                // Method org/apache/hadoop/hbase/TableName.valueOf:(Ljava/lang/String;)Lorg/apache/hadoop/hbase/TableName;
      47: putstatic     #55                 // Field TABLE_3:Lorg/apache/hadoop/hbase/TableName;
      50: iconst_3
      51: anewarray     #52                 // class org/apache/hadoop/hbase/TableName
      54: dup
      55: iconst_0
      56: getstatic     #53                 // Field TABLE_1:Lorg/apache/hadoop/hbase/TableName;
      59: aastore
      60: dup
      61: iconst_1
      62: getstatic     #54                 // Field TABLE_2:Lorg/apache/hadoop/hbase/TableName;
      65: aastore
      66: dup
      67: iconst_2
      68: getstatic     #55                 // Field TABLE_3:Lorg/apache/hadoop/hbase/TableName;
      71: aastore
      72: putstatic     #16                 // Field tables:[Lorg/apache/hadoop/hbase/TableName;
      75: return
}
