Compiled from "TestFSHLog.java"
class org.apache.hadoop.hbase.regionserver.wal.TestFSHLog$1 extends org.apache.hadoop.hbase.regionserver.wal.FSHLog {
  final java.lang.Runnable val$action;

  final org.apache.hadoop.hbase.regionserver.wal.TestFSHLog this$0;

  org.apache.hadoop.hbase.regionserver.wal.TestFSHLog$1(org.apache.hadoop.hbase.regionserver.wal.TestFSHLog, org.apache.hadoop.fs.FileSystem, org.apache.hadoop.fs.Path, java.lang.String, java.lang.String, org.apache.hadoop.conf.Configuration, java.util.List, boolean, java.lang.String, java.lang.String, java.lang.Runnable);
    Code:
       0: aload_0
       1: aload_1
       2: putfield      #1                  // Field this$0:Lorg/apache/hadoop/hbase/regionserver/wal/TestFSHLog;
       5: aload_0
       6: aload         11
       8: putfield      #2                  // Field val$action:Ljava/lang/Runnable;
      11: aload_0
      12: aload_2
      13: aload_3
      14: aload         4
      16: aload         5
      18: aload         6
      20: aload         7
      22: iload         8
      24: aload         9
      26: aload         10
      28: invokespecial #3                  // Method org/apache/hadoop/hbase/regionserver/wal/FSHLog."<init>":(Lorg/apache/hadoop/fs/FileSystem;Lorg/apache/hadoop/fs/Path;Ljava/lang/String;Ljava/lang/String;Lorg/apache/hadoop/conf/Configuration;Ljava/util/List;ZLjava/lang/String;Ljava/lang/String;)V
      31: return

  void atHeadOfRingBufferEventHandlerAppend();
    Code:
       0: aload_0
       1: getfield      #2                  // Field val$action:Ljava/lang/Runnable;
       4: invokeinterface #4,  1            // InterfaceMethod java/lang/Runnable.run:()V
       9: aload_0
      10: invokespecial #5                  // Method org/apache/hadoop/hbase/regionserver/wal/FSHLog.atHeadOfRingBufferEventHandlerAppend:()V
      13: return
}
