Compiled from "TestWALSplit.java"
class org.apache.hadoop.hbase.wal.TestWALSplit$4 extends java.lang.Thread {
  final java.lang.Thread val$someOldThread;

  final org.apache.hadoop.hbase.wal.TestWALSplit this$0;

  org.apache.hadoop.hbase.wal.TestWALSplit$4(org.apache.hadoop.hbase.wal.TestWALSplit, java.lang.String, java.lang.Thread);
    Code:
       0: aload_0
       1: aload_1
       2: putfield      #1                  // Field this$0:Lorg/apache/hadoop/hbase/wal/TestWALSplit;
       5: aload_0
       6: aload_3
       7: putfield      #2                  // Field val$someOldThread:Ljava/lang/Thread;
      10: aload_0
      11: aload_2
      12: invokespecial #3                  // Method java/lang/Thread."<init>":(Ljava/lang/String;)V
      15: return

  public void run();
    Code:
       0: aload_0
       1: getfield      #2                  // Field val$someOldThread:Ljava/lang/Thread;
       4: invokestatic  #4                  // Method org/apache/hadoop/hbase/util/Threads.threadDumpingIsAlive:(Ljava/lang/Thread;)V
       7: goto          15
      10: astore_1
      11: aload_1
      12: invokevirtual #6                  // Method java/lang/InterruptedException.printStackTrace:()V
      15: return
    Exception table:
       from    to  target type
           0     7    10   Class java/lang/InterruptedException
}
