Compiled from "TestRawAsyncTableLimitedScanWithFilter.java"
public class org.apache.hadoop.hbase.client.TestRawAsyncTableLimitedScanWithFilter {
  public static final org.apache.hadoop.hbase.HBaseClassTestRule CLASS_RULE;

  public org.apache.hadoop.hbase.client.TestRawAsyncTableLimitedScanWithFilter();
    Code:
       0: aload_0
       1: invokespecial #1                  // Method java/lang/Object."<init>":()V
       4: return

  public static void setUp() throws java.lang.Exception;
    Code:
       0: getstatic     #2                  // Field UTIL:Lorg/apache/hadoop/hbase/HBaseTestingUtility;
       3: iconst_1
       4: invokevirtual #3                  // Method org/apache/hadoop/hbase/HBaseTestingUtility.startMiniCluster:(I)Lorg/apache/hadoop/hbase/MiniHBaseCluster;
       7: pop
       8: getstatic     #2                  // Field UTIL:Lorg/apache/hadoop/hbase/HBaseTestingUtility;
      11: getstatic     #4                  // Field TABLE_NAME:Lorg/apache/hadoop/hbase/TableName;
      14: getstatic     #5                  // Field FAMILY:[B
      17: invokevirtual #6                  // Method org/apache/hadoop/hbase/HBaseTestingUtility.createTable:(Lorg/apache/hadoop/hbase/TableName;[B)Lorg/apache/hadoop/hbase/client/Table;
      20: pop
      21: getstatic     #2                  // Field UTIL:Lorg/apache/hadoop/hbase/HBaseTestingUtility;
      24: invokevirtual #7                  // Method org/apache/hadoop/hbase/HBaseTestingUtility.getConfiguration:()Lorg/apache/hadoop/conf/Configuration;
      27: invokestatic  #8                  // Method org/apache/hadoop/hbase/client/ConnectionFactory.createAsyncConnection:(Lorg/apache/hadoop/conf/Configuration;)Ljava/util/concurrent/CompletableFuture;
      30: invokevirtual #9                  // Method java/util/concurrent/CompletableFuture.get:()Ljava/lang/Object;
      33: checkcast     #10                 // class org/apache/hadoop/hbase/client/AsyncConnection
      36: putstatic     #11                 // Field CONN:Lorg/apache/hadoop/hbase/client/AsyncConnection;
      39: getstatic     #11                 // Field CONN:Lorg/apache/hadoop/hbase/client/AsyncConnection;
      42: getstatic     #4                  // Field TABLE_NAME:Lorg/apache/hadoop/hbase/TableName;
      45: invokeinterface #12,  2           // InterfaceMethod org/apache/hadoop/hbase/client/AsyncConnection.getTable:(Lorg/apache/hadoop/hbase/TableName;)Lorg/apache/hadoop/hbase/client/AsyncTable;
      50: putstatic     #13                 // Field TABLE:Lorg/apache/hadoop/hbase/client/AsyncTable;
      53: getstatic     #13                 // Field TABLE:Lorg/apache/hadoop/hbase/client/AsyncTable;
      56: iconst_0
      57: getstatic     #14                 // Field ROW_COUNT:I
      60: invokestatic  #15                 // InterfaceMethod java/util/stream/IntStream.range:(II)Ljava/util/stream/IntStream;
      63: invokedynamic #16,  0             // InvokeDynamic #0:apply:()Ljava/util/function/IntFunction;
      68: invokeinterface #17,  2           // InterfaceMethod java/util/stream/IntStream.mapToObj:(Ljava/util/function/IntFunction;)Ljava/util/stream/Stream;
      73: invokestatic  #18                 // Method java/util/stream/Collectors.toList:()Ljava/util/stream/Collector;
      76: invokeinterface #19,  2           // InterfaceMethod java/util/stream/Stream.collect:(Ljava/util/stream/Collector;)Ljava/lang/Object;
      81: checkcast     #20                 // class java/util/List
      84: invokeinterface #21,  2           // InterfaceMethod org/apache/hadoop/hbase/client/AsyncTable.putAll:(Ljava/util/List;)Ljava/util/concurrent/CompletableFuture;
      89: invokevirtual #9                  // Method java/util/concurrent/CompletableFuture.get:()Ljava/lang/Object;
      92: pop
      93: return

  public static void tearDown() throws java.lang.Exception;
    Code:
       0: getstatic     #11                 // Field CONN:Lorg/apache/hadoop/hbase/client/AsyncConnection;
       3: invokeinterface #22,  1           // InterfaceMethod org/apache/hadoop/hbase/client/AsyncConnection.close:()V
       8: getstatic     #2                  // Field UTIL:Lorg/apache/hadoop/hbase/HBaseTestingUtility;
      11: invokevirtual #23                 // Method org/apache/hadoop/hbase/HBaseTestingUtility.shutdownMiniCluster:()V
      14: return

  public void testCompleteResult() throws java.lang.InterruptedException, java.util.concurrent.ExecutionException;
    Code:
       0: iconst_5
       1: istore_1
       2: new           #24                 // class org/apache/hadoop/hbase/client/Scan
       5: dup
       6: invokespecial #25                 // Method org/apache/hadoop/hbase/client/Scan."<init>":()V
       9: new           #26                 // class org/apache/hadoop/hbase/client/ColumnCountOnRowFilter
      12: dup
      13: iconst_2
      14: invokespecial #27                 // Method org/apache/hadoop/hbase/client/ColumnCountOnRowFilter."<init>":(I)V
      17: invokevirtual #28                 // Method org/apache/hadoop/hbase/client/Scan.setFilter:(Lorg/apache/hadoop/hbase/filter/Filter;)Lorg/apache/hadoop/hbase/client/Scan;
      20: lconst_1
      21: invokevirtual #29                 // Method org/apache/hadoop/hbase/client/Scan.setMaxResultSize:(J)Lorg/apache/hadoop/hbase/client/Scan;
      24: iload_1
      25: invokevirtual #30                 // Method org/apache/hadoop/hbase/client/Scan.setLimit:(I)Lorg/apache/hadoop/hbase/client/Scan;
      28: astore_2
      29: getstatic     #13                 // Field TABLE:Lorg/apache/hadoop/hbase/client/AsyncTable;
      32: aload_2
      33: invokeinterface #31,  2           // InterfaceMethod org/apache/hadoop/hbase/client/AsyncTable.scanAll:(Lorg/apache/hadoop/hbase/client/Scan;)Ljava/util/concurrent/CompletableFuture;
      38: invokevirtual #9                  // Method java/util/concurrent/CompletableFuture.get:()Ljava/lang/Object;
      41: checkcast     #20                 // class java/util/List
      44: astore_3
      45: iload_1
      46: i2l
      47: aload_3
      48: invokeinterface #32,  1           // InterfaceMethod java/util/List.size:()I
      53: i2l
      54: invokestatic  #33                 // Method org/junit/Assert.assertEquals:(JJ)V
      57: iconst_0
      58: iload_1
      59: invokestatic  #15                 // InterfaceMethod java/util/stream/IntStream.range:(II)Ljava/util/stream/IntStream;
      62: aload_3
      63: invokedynamic #34,  0             // InvokeDynamic #1:accept:(Ljava/util/List;)Ljava/util/function/IntConsumer;
      68: invokeinterface #35,  2           // InterfaceMethod java/util/stream/IntStream.forEach:(Ljava/util/function/IntConsumer;)V
      73: return

  public void testAllowPartial() throws java.lang.InterruptedException, java.util.concurrent.ExecutionException;
    Code:
       0: iconst_5
       1: istore_1
       2: new           #24                 // class org/apache/hadoop/hbase/client/Scan
       5: dup
       6: invokespecial #25                 // Method org/apache/hadoop/hbase/client/Scan."<init>":()V
       9: new           #26                 // class org/apache/hadoop/hbase/client/ColumnCountOnRowFilter
      12: dup
      13: iconst_2
      14: invokespecial #27                 // Method org/apache/hadoop/hbase/client/ColumnCountOnRowFilter."<init>":(I)V
      17: invokevirtual #28                 // Method org/apache/hadoop/hbase/client/Scan.setFilter:(Lorg/apache/hadoop/hbase/filter/Filter;)Lorg/apache/hadoop/hbase/client/Scan;
      20: lconst_1
      21: invokevirtual #29                 // Method org/apache/hadoop/hbase/client/Scan.setMaxResultSize:(J)Lorg/apache/hadoop/hbase/client/Scan;
      24: iconst_1
      25: invokevirtual #36                 // Method org/apache/hadoop/hbase/client/Scan.setAllowPartialResults:(Z)Lorg/apache/hadoop/hbase/client/Scan;
      28: iload_1
      29: invokevirtual #30                 // Method org/apache/hadoop/hbase/client/Scan.setLimit:(I)Lorg/apache/hadoop/hbase/client/Scan;
      32: astore_2
      33: getstatic     #13                 // Field TABLE:Lorg/apache/hadoop/hbase/client/AsyncTable;
      36: aload_2
      37: invokeinterface #31,  2           // InterfaceMethod org/apache/hadoop/hbase/client/AsyncTable.scanAll:(Lorg/apache/hadoop/hbase/client/Scan;)Ljava/util/concurrent/CompletableFuture;
      42: invokevirtual #9                  // Method java/util/concurrent/CompletableFuture.get:()Ljava/lang/Object;
      45: checkcast     #20                 // class java/util/List
      48: astore_3
      49: iconst_2
      50: iload_1
      51: imul
      52: i2l
      53: aload_3
      54: invokeinterface #32,  1           // InterfaceMethod java/util/List.size:()I
      59: i2l
      60: invokestatic  #33                 // Method org/junit/Assert.assertEquals:(JJ)V
      63: iconst_0
      64: iconst_2
      65: iload_1
      66: imul
      67: invokestatic  #15                 // InterfaceMethod java/util/stream/IntStream.range:(II)Ljava/util/stream/IntStream;
      70: aload_3
      71: invokedynamic #37,  0             // InvokeDynamic #2:accept:(Ljava/util/List;)Ljava/util/function/IntConsumer;
      76: invokeinterface #35,  2           // InterfaceMethod java/util/stream/IntStream.forEach:(Ljava/util/function/IntConsumer;)V
      81: return

  public void testBatchAllowPartial() throws java.lang.InterruptedException, java.util.concurrent.ExecutionException;
    Code:
       0: iconst_5
       1: istore_1
       2: new           #24                 // class org/apache/hadoop/hbase/client/Scan
       5: dup
       6: invokespecial #25                 // Method org/apache/hadoop/hbase/client/Scan."<init>":()V
       9: new           #26                 // class org/apache/hadoop/hbase/client/ColumnCountOnRowFilter
      12: dup
      13: iconst_3
      14: invokespecial #27                 // Method org/apache/hadoop/hbase/client/ColumnCountOnRowFilter."<init>":(I)V
      17: invokevirtual #28                 // Method org/apache/hadoop/hbase/client/Scan.setFilter:(Lorg/apache/hadoop/hbase/filter/Filter;)Lorg/apache/hadoop/hbase/client/Scan;
      20: iconst_2
      21: invokevirtual #38                 // Method org/apache/hadoop/hbase/client/Scan.setBatch:(I)Lorg/apache/hadoop/hbase/client/Scan;
      24: lconst_1
      25: invokevirtual #29                 // Method org/apache/hadoop/hbase/client/Scan.setMaxResultSize:(J)Lorg/apache/hadoop/hbase/client/Scan;
      28: iconst_1
      29: invokevirtual #36                 // Method org/apache/hadoop/hbase/client/Scan.setAllowPartialResults:(Z)Lorg/apache/hadoop/hbase/client/Scan;
      32: iload_1
      33: invokevirtual #30                 // Method org/apache/hadoop/hbase/client/Scan.setLimit:(I)Lorg/apache/hadoop/hbase/client/Scan;
      36: astore_2
      37: getstatic     #13                 // Field TABLE:Lorg/apache/hadoop/hbase/client/AsyncTable;
      40: aload_2
      41: invokeinterface #31,  2           // InterfaceMethod org/apache/hadoop/hbase/client/AsyncTable.scanAll:(Lorg/apache/hadoop/hbase/client/Scan;)Ljava/util/concurrent/CompletableFuture;
      46: invokevirtual #9                  // Method java/util/concurrent/CompletableFuture.get:()Ljava/lang/Object;
      49: checkcast     #20                 // class java/util/List
      52: astore_3
      53: iconst_3
      54: iload_1
      55: imul
      56: i2l
      57: aload_3
      58: invokeinterface #32,  1           // InterfaceMethod java/util/List.size:()I
      63: i2l
      64: invokestatic  #33                 // Method org/junit/Assert.assertEquals:(JJ)V
      67: iconst_0
      68: iconst_3
      69: iload_1
      70: imul
      71: invokestatic  #15                 // InterfaceMethod java/util/stream/IntStream.range:(II)Ljava/util/stream/IntStream;
      74: aload_3
      75: invokedynamic #39,  0             // InvokeDynamic #3:accept:(Ljava/util/List;)Ljava/util/function/IntConsumer;
      80: invokeinterface #35,  2           // InterfaceMethod java/util/stream/IntStream.forEach:(Ljava/util/function/IntConsumer;)V
      85: return

  public void testBatch() throws java.lang.InterruptedException, java.util.concurrent.ExecutionException;
    Code:
       0: iconst_5
       1: istore_1
       2: new           #24                 // class org/apache/hadoop/hbase/client/Scan
       5: dup
       6: invokespecial #25                 // Method org/apache/hadoop/hbase/client/Scan."<init>":()V
       9: new           #26                 // class org/apache/hadoop/hbase/client/ColumnCountOnRowFilter
      12: dup
      13: iconst_2
      14: invokespecial #27                 // Method org/apache/hadoop/hbase/client/ColumnCountOnRowFilter."<init>":(I)V
      17: invokevirtual #28                 // Method org/apache/hadoop/hbase/client/Scan.setFilter:(Lorg/apache/hadoop/hbase/filter/Filter;)Lorg/apache/hadoop/hbase/client/Scan;
      20: iconst_2
      21: invokevirtual #38                 // Method org/apache/hadoop/hbase/client/Scan.setBatch:(I)Lorg/apache/hadoop/hbase/client/Scan;
      24: lconst_1
      25: invokevirtual #29                 // Method org/apache/hadoop/hbase/client/Scan.setMaxResultSize:(J)Lorg/apache/hadoop/hbase/client/Scan;
      28: iload_1
      29: invokevirtual #30                 // Method org/apache/hadoop/hbase/client/Scan.setLimit:(I)Lorg/apache/hadoop/hbase/client/Scan;
      32: astore_2
      33: getstatic     #13                 // Field TABLE:Lorg/apache/hadoop/hbase/client/AsyncTable;
      36: aload_2
      37: invokeinterface #31,  2           // InterfaceMethod org/apache/hadoop/hbase/client/AsyncTable.scanAll:(Lorg/apache/hadoop/hbase/client/Scan;)Ljava/util/concurrent/CompletableFuture;
      42: invokevirtual #9                  // Method java/util/concurrent/CompletableFuture.get:()Ljava/lang/Object;
      45: checkcast     #20                 // class java/util/List
      48: astore_3
      49: iload_1
      50: i2l
      51: aload_3
      52: invokeinterface #32,  1           // InterfaceMethod java/util/List.size:()I
      57: i2l
      58: invokestatic  #33                 // Method org/junit/Assert.assertEquals:(JJ)V
      61: iconst_0
      62: iload_1
      63: invokestatic  #15                 // InterfaceMethod java/util/stream/IntStream.range:(II)Ljava/util/stream/IntStream;
      66: aload_3
      67: invokedynamic #40,  0             // InvokeDynamic #4:accept:(Ljava/util/List;)Ljava/util/function/IntConsumer;
      72: invokeinterface #35,  2           // InterfaceMethod java/util/stream/IntStream.forEach:(Ljava/util/function/IntConsumer;)V
      77: return

  public void testBatchAndFilterDiffer() throws java.lang.InterruptedException, java.util.concurrent.ExecutionException;
    Code:
       0: iconst_5
       1: istore_1
       2: new           #24                 // class org/apache/hadoop/hbase/client/Scan
       5: dup
       6: invokespecial #25                 // Method org/apache/hadoop/hbase/client/Scan."<init>":()V
       9: new           #26                 // class org/apache/hadoop/hbase/client/ColumnCountOnRowFilter
      12: dup
      13: iconst_3
      14: invokespecial #27                 // Method org/apache/hadoop/hbase/client/ColumnCountOnRowFilter."<init>":(I)V
      17: invokevirtual #28                 // Method org/apache/hadoop/hbase/client/Scan.setFilter:(Lorg/apache/hadoop/hbase/filter/Filter;)Lorg/apache/hadoop/hbase/client/Scan;
      20: iconst_2
      21: invokevirtual #38                 // Method org/apache/hadoop/hbase/client/Scan.setBatch:(I)Lorg/apache/hadoop/hbase/client/Scan;
      24: lconst_1
      25: invokevirtual #29                 // Method org/apache/hadoop/hbase/client/Scan.setMaxResultSize:(J)Lorg/apache/hadoop/hbase/client/Scan;
      28: iload_1
      29: invokevirtual #30                 // Method org/apache/hadoop/hbase/client/Scan.setLimit:(I)Lorg/apache/hadoop/hbase/client/Scan;
      32: astore_2
      33: getstatic     #13                 // Field TABLE:Lorg/apache/hadoop/hbase/client/AsyncTable;
      36: aload_2
      37: invokeinterface #31,  2           // InterfaceMethod org/apache/hadoop/hbase/client/AsyncTable.scanAll:(Lorg/apache/hadoop/hbase/client/Scan;)Ljava/util/concurrent/CompletableFuture;
      42: invokevirtual #9                  // Method java/util/concurrent/CompletableFuture.get:()Ljava/lang/Object;
      45: checkcast     #20                 // class java/util/List
      48: astore_3
      49: iconst_2
      50: iload_1
      51: imul
      52: i2l
      53: aload_3
      54: invokeinterface #32,  1           // InterfaceMethod java/util/List.size:()I
      59: i2l
      60: invokestatic  #33                 // Method org/junit/Assert.assertEquals:(JJ)V
      63: iconst_0
      64: iload_1
      65: invokestatic  #15                 // InterfaceMethod java/util/stream/IntStream.range:(II)Ljava/util/stream/IntStream;
      68: aload_3
      69: invokedynamic #41,  0             // InvokeDynamic #5:accept:(Ljava/util/List;)Ljava/util/function/IntConsumer;
      74: invokeinterface #35,  2           // InterfaceMethod java/util/stream/IntStream.forEach:(Ljava/util/function/IntConsumer;)V
      79: return

  static {};
    Code:
       0: ldc           #59                 // class org/apache/hadoop/hbase/client/TestRawAsyncTableLimitedScanWithFilter
       2: invokestatic  #60                 // Method org/apache/hadoop/hbase/HBaseClassTestRule.forClass:(Ljava/lang/Class;)Lorg/apache/hadoop/hbase/HBaseClassTestRule;
       5: putstatic     #61                 // Field CLASS_RULE:Lorg/apache/hadoop/hbase/HBaseClassTestRule;
       8: new           #62                 // class org/apache/hadoop/hbase/HBaseTestingUtility
      11: dup
      12: invokespecial #63                 // Method org/apache/hadoop/hbase/HBaseTestingUtility."<init>":()V
      15: putstatic     #2                  // Field UTIL:Lorg/apache/hadoop/hbase/HBaseTestingUtility;
      18: ldc           #64                 // String TestRegionScanner
      20: invokestatic  #65                 // Method org/apache/hadoop/hbase/TableName.valueOf:(Ljava/lang/String;)Lorg/apache/hadoop/hbase/TableName;
      23: putstatic     #4                  // Field TABLE_NAME:Lorg/apache/hadoop/hbase/TableName;
      26: ldc           #66                 // String cf
      28: invokestatic  #67                 // Method org/apache/hadoop/hbase/util/Bytes.toBytes:(Ljava/lang/String;)[B
      31: putstatic     #5                  // Field FAMILY:[B
      34: iconst_4
      35: anewarray     #68                 // class "[B"
      38: dup
      39: iconst_0
      40: ldc           #69                 // String cq1
      42: invokestatic  #67                 // Method org/apache/hadoop/hbase/util/Bytes.toBytes:(Ljava/lang/String;)[B
      45: aastore
      46: dup
      47: iconst_1
      48: ldc           #70                 // String cq2
      50: invokestatic  #67                 // Method org/apache/hadoop/hbase/util/Bytes.toBytes:(Ljava/lang/String;)[B
      53: aastore
      54: dup
      55: iconst_2
      56: ldc           #71                 // String cq3
      58: invokestatic  #67                 // Method org/apache/hadoop/hbase/util/Bytes.toBytes:(Ljava/lang/String;)[B
      61: aastore
      62: dup
      63: iconst_3
      64: ldc           #72                 // String cq4
      66: invokestatic  #67                 // Method org/apache/hadoop/hbase/util/Bytes.toBytes:(Ljava/lang/String;)[B
      69: aastore
      70: putstatic     #51                 // Field CQS:[[B
      73: bipush        10
      75: putstatic     #14                 // Field ROW_COUNT:I
      78: return
}
