Compiled from "TestReplicationEndpoint.java"
class org.apache.hadoop.hbase.replication.TestReplicationEndpoint$3 implements org.apache.hadoop.hbase.Waiter$Predicate<java.lang.Exception> {
  final org.apache.hadoop.hbase.replication.TestReplicationEndpoint this$0;

  org.apache.hadoop.hbase.replication.TestReplicationEndpoint$3(org.apache.hadoop.hbase.replication.TestReplicationEndpoint);
    Code:
       0: aload_0
       1: aload_1
       2: putfield      #1                  // Field this$0:Lorg/apache/hadoop/hbase/replication/TestReplicationEndpoint;
       5: aload_0
       6: invokespecial #2                  // Method java/lang/Object."<init>":()V
       9: return

  public boolean evaluate() throws java.lang.Exception;
    Code:
       0: getstatic     #3                  // Field org/apache/hadoop/hbase/replication/TestReplicationEndpoint$ReplicationEndpointForTest.startedCount:Ljava/util/concurrent/atomic/AtomicInteger;
       3: invokevirtual #4                  // Method java/util/concurrent/atomic/AtomicInteger.get:()I
       6: getstatic     #5                  // Field org/apache/hadoop/hbase/replication/TestReplicationEndpoint.numRegionServers:I
       9: if_icmplt     16
      12: iconst_1
      13: goto          17
      16: iconst_0
      17: ireturn
}
