Compiled from "TestClearRegionBlockCache.java"
public class org.apache.hadoop.hbase.regionserver.TestClearRegionBlockCache {
  public static final org.apache.hadoop.hbase.HBaseClassTestRule CLASS_RULE;

  public java.lang.String cacheType;

  public org.apache.hadoop.hbase.regionserver.TestClearRegionBlockCache();
    Code:
       0: aload_0
       1: invokespecial #1                  // Method java/lang/Object."<init>":()V
       4: aload_0
       5: new           #2                  // class org/apache/hadoop/hbase/HBaseTestingUtility
       8: dup
       9: invokespecial #3                  // Method org/apache/hadoop/hbase/HBaseTestingUtility."<init>":()V
      12: putfield      #4                  // Field HTU:Lorg/apache/hadoop/hbase/HBaseTestingUtility;
      15: aload_0
      16: aload_0
      17: getfield      #4                  // Field HTU:Lorg/apache/hadoop/hbase/HBaseTestingUtility;
      20: invokevirtual #5                  // Method org/apache/hadoop/hbase/HBaseTestingUtility.getConfiguration:()Lorg/apache/hadoop/conf/Configuration;
      23: putfield      #6                  // Field CONF:Lorg/apache/hadoop/conf/Configuration;
      26: return

  public static java.lang.Object[] data();
    Code:
       0: iconst_2
       1: anewarray     #7                  // class java/lang/Object
       4: dup
       5: iconst_0
       6: ldc           #8                  // String lru
       8: aastore
       9: dup
      10: iconst_1
      11: ldc           #9                  // String bucket
      13: aastore
      14: areturn

  public void setup() throws java.lang.Exception;
    Code:
       0: aload_0
       1: getfield      #10                 // Field cacheType:Ljava/lang/String;
       4: ldc           #9                  // String bucket
       6: invokevirtual #11                 // Method java/lang/String.equals:(Ljava/lang/Object;)Z
       9: ifeq          34
      12: aload_0
      13: getfield      #6                  // Field CONF:Lorg/apache/hadoop/conf/Configuration;
      16: ldc           #13                 // String hbase.bucketcache.ioengine
      18: ldc           #14                 // String offheap
      20: invokevirtual #15                 // Method org/apache/hadoop/conf/Configuration.set:(Ljava/lang/String;Ljava/lang/String;)V
      23: aload_0
      24: getfield      #6                  // Field CONF:Lorg/apache/hadoop/conf/Configuration;
      27: ldc           #16                 // String hbase.bucketcache.size
      29: bipush        30
      31: invokevirtual #17                 // Method org/apache/hadoop/conf/Configuration.setInt:(Ljava/lang/String;I)V
      34: aload_0
      35: aload_0
      36: getfield      #4                  // Field HTU:Lorg/apache/hadoop/hbase/HBaseTestingUtility;
      39: iconst_2
      40: invokevirtual #19                 // Method org/apache/hadoop/hbase/HBaseTestingUtility.startMiniCluster:(I)Lorg/apache/hadoop/hbase/MiniHBaseCluster;
      43: putfield      #20                 // Field cluster:Lorg/apache/hadoop/hbase/MiniHBaseCluster;
      46: aload_0
      47: aload_0
      48: getfield      #20                 // Field cluster:Lorg/apache/hadoop/hbase/MiniHBaseCluster;
      51: iconst_0
      52: invokevirtual #21                 // Method org/apache/hadoop/hbase/MiniHBaseCluster.getRegionServer:(I)Lorg/apache/hadoop/hbase/regionserver/HRegionServer;
      55: putfield      #22                 // Field rs1:Lorg/apache/hadoop/hbase/regionserver/HRegionServer;
      58: aload_0
      59: aload_0
      60: getfield      #20                 // Field cluster:Lorg/apache/hadoop/hbase/MiniHBaseCluster;
      63: iconst_1
      64: invokevirtual #21                 // Method org/apache/hadoop/hbase/MiniHBaseCluster.getRegionServer:(I)Lorg/apache/hadoop/hbase/regionserver/HRegionServer;
      67: putfield      #23                 // Field rs2:Lorg/apache/hadoop/hbase/regionserver/HRegionServer;
      70: aload_0
      71: aload_0
      72: getfield      #4                  // Field HTU:Lorg/apache/hadoop/hbase/HBaseTestingUtility;
      75: getstatic     #24                 // Field TABLE_NAME:Lorg/apache/hadoop/hbase/TableName;
      78: getstatic     #25                 // Field FAMILY:[B
      81: getstatic     #26                 // Field SPLIT_KEY:[[B
      84: invokevirtual #27                 // Method org/apache/hadoop/hbase/HBaseTestingUtility.createTable:(Lorg/apache/hadoop/hbase/TableName;[B[[B)Lorg/apache/hadoop/hbase/client/Table;
      87: putfield      #28                 // Field table:Lorg/apache/hadoop/hbase/client/Table;
      90: aload_0
      91: getfield      #4                  // Field HTU:Lorg/apache/hadoop/hbase/HBaseTestingUtility;
      94: aload_0
      95: getfield      #28                 // Field table:Lorg/apache/hadoop/hbase/client/Table;
      98: getstatic     #25                 // Field FAMILY:[B
     101: iconst_1
     102: bipush        10
     104: invokevirtual #29                 // Method org/apache/hadoop/hbase/HBaseTestingUtility.loadNumericRows:(Lorg/apache/hadoop/hbase/client/Table;[BII)V
     107: aload_0
     108: getfield      #4                  // Field HTU:Lorg/apache/hadoop/hbase/HBaseTestingUtility;
     111: getstatic     #24                 // Field TABLE_NAME:Lorg/apache/hadoop/hbase/TableName;
     114: invokevirtual #30                 // Method org/apache/hadoop/hbase/HBaseTestingUtility.flush:(Lorg/apache/hadoop/hbase/TableName;)V
     117: return

  public void teardown() throws java.lang.Exception;
    Code:
       0: aload_0
       1: getfield      #4                  // Field HTU:Lorg/apache/hadoop/hbase/HBaseTestingUtility;
       4: invokevirtual #31                 // Method org/apache/hadoop/hbase/HBaseTestingUtility.shutdownMiniCluster:()V
       7: return

  public void testClearBlockCache() throws java.lang.Exception;
    Code:
       0: aload_0
       1: getfield      #22                 // Field rs1:Lorg/apache/hadoop/hbase/regionserver/HRegionServer;
       4: invokevirtual #32                 // Method org/apache/hadoop/hbase/regionserver/HRegionServer.getBlockCache:()Ljava/util/Optional;
       7: invokevirtual #33                 // Method java/util/Optional.get:()Ljava/lang/Object;
      10: checkcast     #34                 // class org/apache/hadoop/hbase/io/hfile/BlockCache
      13: astore_1
      14: aload_0
      15: getfield      #23                 // Field rs2:Lorg/apache/hadoop/hbase/regionserver/HRegionServer;
      18: invokevirtual #32                 // Method org/apache/hadoop/hbase/regionserver/HRegionServer.getBlockCache:()Ljava/util/Optional;
      21: invokevirtual #33                 // Method java/util/Optional.get:()Ljava/lang/Object;
      24: checkcast     #34                 // class org/apache/hadoop/hbase/io/hfile/BlockCache
      27: astore_2
      28: aload_1
      29: invokeinterface #35,  1           // InterfaceMethod org/apache/hadoop/hbase/io/hfile/BlockCache.getBlockCount:()J
      34: lstore_3
      35: aload_2
      36: invokeinterface #35,  1           // InterfaceMethod org/apache/hadoop/hbase/io/hfile/BlockCache.getBlockCount:()J
      41: lstore        5
      43: aload_0
      44: aload_0
      45: getfield      #22                 // Field rs1:Lorg/apache/hadoop/hbase/regionserver/HRegionServer;
      48: invokespecial #36                 // Method scanAllRegionsForRS:(Lorg/apache/hadoop/hbase/regionserver/HRegionServer;)V
      51: aload_1
      52: invokeinterface #35,  1           // InterfaceMethod org/apache/hadoop/hbase/io/hfile/BlockCache.getBlockCount:()J
      57: lload_3
      58: lsub
      59: aload_0
      60: getfield      #4                  // Field HTU:Lorg/apache/hadoop/hbase/HBaseTestingUtility;
      63: aload_0
      64: getfield      #22                 // Field rs1:Lorg/apache/hadoop/hbase/regionserver/HRegionServer;
      67: getstatic     #24                 // Field TABLE_NAME:Lorg/apache/hadoop/hbase/TableName;
      70: getstatic     #25                 // Field FAMILY:[B
      73: invokevirtual #37                 // Method org/apache/hadoop/hbase/HBaseTestingUtility.getNumHFilesForRS:(Lorg/apache/hadoop/hbase/regionserver/HRegionServer;Lorg/apache/hadoop/hbase/TableName;[B)I
      76: i2l
      77: invokestatic  #38                 // Method org/junit/Assert.assertEquals:(JJ)V
      80: aload_0
      81: aload_0
      82: getfield      #22                 // Field rs1:Lorg/apache/hadoop/hbase/regionserver/HRegionServer;
      85: invokespecial #39                 // Method clearRegionBlockCache:(Lorg/apache/hadoop/hbase/regionserver/HRegionServer;)V
      88: aload_0
      89: aload_0
      90: getfield      #23                 // Field rs2:Lorg/apache/hadoop/hbase/regionserver/HRegionServer;
      93: invokespecial #36                 // Method scanAllRegionsForRS:(Lorg/apache/hadoop/hbase/regionserver/HRegionServer;)V
      96: aload_2
      97: invokeinterface #35,  1           // InterfaceMethod org/apache/hadoop/hbase/io/hfile/BlockCache.getBlockCount:()J
     102: lload         5
     104: lsub
     105: aload_0
     106: getfield      #4                  // Field HTU:Lorg/apache/hadoop/hbase/HBaseTestingUtility;
     109: aload_0
     110: getfield      #23                 // Field rs2:Lorg/apache/hadoop/hbase/regionserver/HRegionServer;
     113: getstatic     #24                 // Field TABLE_NAME:Lorg/apache/hadoop/hbase/TableName;
     116: getstatic     #25                 // Field FAMILY:[B
     119: invokevirtual #37                 // Method org/apache/hadoop/hbase/HBaseTestingUtility.getNumHFilesForRS:(Lorg/apache/hadoop/hbase/regionserver/HRegionServer;Lorg/apache/hadoop/hbase/TableName;[B)I
     122: i2l
     123: invokestatic  #38                 // Method org/junit/Assert.assertEquals:(JJ)V
     126: aload_0
     127: aload_0
     128: getfield      #23                 // Field rs2:Lorg/apache/hadoop/hbase/regionserver/HRegionServer;
     131: invokespecial #39                 // Method clearRegionBlockCache:(Lorg/apache/hadoop/hbase/regionserver/HRegionServer;)V
     134: lload_3
     135: aload_1
     136: invokeinterface #35,  1           // InterfaceMethod org/apache/hadoop/hbase/io/hfile/BlockCache.getBlockCount:()J
     141: invokestatic  #38                 // Method org/junit/Assert.assertEquals:(JJ)V
     144: lload         5
     146: aload_2
     147: invokeinterface #35,  1           // InterfaceMethod org/apache/hadoop/hbase/io/hfile/BlockCache.getBlockCount:()J
     152: invokestatic  #38                 // Method org/junit/Assert.assertEquals:(JJ)V
     155: return

  public void testClearBlockCacheFromAdmin() throws java.lang.Exception;
    Code:
       0: aload_0
       1: getfield      #4                  // Field HTU:Lorg/apache/hadoop/hbase/HBaseTestingUtility;
       4: invokevirtual #40                 // Method org/apache/hadoop/hbase/HBaseTestingUtility.getAdmin:()Lorg/apache/hadoop/hbase/client/Admin;
       7: astore_1
       8: aload_0
       9: getfield      #22                 // Field rs1:Lorg/apache/hadoop/hbase/regionserver/HRegionServer;
      12: invokevirtual #32                 // Method org/apache/hadoop/hbase/regionserver/HRegionServer.getBlockCache:()Ljava/util/Optional;
      15: invokevirtual #33                 // Method java/util/Optional.get:()Ljava/lang/Object;
      18: checkcast     #34                 // class org/apache/hadoop/hbase/io/hfile/BlockCache
      21: astore_2
      22: aload_0
      23: getfield      #23                 // Field rs2:Lorg/apache/hadoop/hbase/regionserver/HRegionServer;
      26: invokevirtual #32                 // Method org/apache/hadoop/hbase/regionserver/HRegionServer.getBlockCache:()Ljava/util/Optional;
      29: invokevirtual #33                 // Method java/util/Optional.get:()Ljava/lang/Object;
      32: checkcast     #34                 // class org/apache/hadoop/hbase/io/hfile/BlockCache
      35: astore_3
      36: aload_2
      37: invokeinterface #35,  1           // InterfaceMethod org/apache/hadoop/hbase/io/hfile/BlockCache.getBlockCount:()J
      42: lstore        4
      44: aload_3
      45: invokeinterface #35,  1           // InterfaceMethod org/apache/hadoop/hbase/io/hfile/BlockCache.getBlockCount:()J
      50: lstore        6
      52: aload_0
      53: aload_0
      54: getfield      #22                 // Field rs1:Lorg/apache/hadoop/hbase/regionserver/HRegionServer;
      57: invokespecial #36                 // Method scanAllRegionsForRS:(Lorg/apache/hadoop/hbase/regionserver/HRegionServer;)V
      60: aload_2
      61: invokeinterface #35,  1           // InterfaceMethod org/apache/hadoop/hbase/io/hfile/BlockCache.getBlockCount:()J
      66: lload         4
      68: lsub
      69: aload_0
      70: getfield      #4                  // Field HTU:Lorg/apache/hadoop/hbase/HBaseTestingUtility;
      73: aload_0
      74: getfield      #22                 // Field rs1:Lorg/apache/hadoop/hbase/regionserver/HRegionServer;
      77: getstatic     #24                 // Field TABLE_NAME:Lorg/apache/hadoop/hbase/TableName;
      80: getstatic     #25                 // Field FAMILY:[B
      83: invokevirtual #37                 // Method org/apache/hadoop/hbase/HBaseTestingUtility.getNumHFilesForRS:(Lorg/apache/hadoop/hbase/regionserver/HRegionServer;Lorg/apache/hadoop/hbase/TableName;[B)I
      86: i2l
      87: invokestatic  #38                 // Method org/junit/Assert.assertEquals:(JJ)V
      90: aload_0
      91: aload_0
      92: getfield      #23                 // Field rs2:Lorg/apache/hadoop/hbase/regionserver/HRegionServer;
      95: invokespecial #36                 // Method scanAllRegionsForRS:(Lorg/apache/hadoop/hbase/regionserver/HRegionServer;)V
      98: aload_3
      99: invokeinterface #35,  1           // InterfaceMethod org/apache/hadoop/hbase/io/hfile/BlockCache.getBlockCount:()J
     104: lload         6
     106: lsub
     107: aload_0
     108: getfield      #4                  // Field HTU:Lorg/apache/hadoop/hbase/HBaseTestingUtility;
     111: aload_0
     112: getfield      #23                 // Field rs2:Lorg/apache/hadoop/hbase/regionserver/HRegionServer;
     115: getstatic     #24                 // Field TABLE_NAME:Lorg/apache/hadoop/hbase/TableName;
     118: getstatic     #25                 // Field FAMILY:[B
     121: invokevirtual #37                 // Method org/apache/hadoop/hbase/HBaseTestingUtility.getNumHFilesForRS:(Lorg/apache/hadoop/hbase/regionserver/HRegionServer;Lorg/apache/hadoop/hbase/TableName;[B)I
     124: i2l
     125: invokestatic  #38                 // Method org/junit/Assert.assertEquals:(JJ)V
     128: aload_1
     129: getstatic     #24                 // Field TABLE_NAME:Lorg/apache/hadoop/hbase/TableName;
     132: invokeinterface #41,  2           // InterfaceMethod org/apache/hadoop/hbase/client/Admin.clearBlockCache:(Lorg/apache/hadoop/hbase/TableName;)Lorg/apache/hadoop/hbase/CacheEvictionStats;
     137: astore        8
     139: aload         8
     141: invokevirtual #42                 // Method org/apache/hadoop/hbase/CacheEvictionStats.getEvictedBlocks:()J
     144: aload_0
     145: getfield      #4                  // Field HTU:Lorg/apache/hadoop/hbase/HBaseTestingUtility;
     148: aload_0
     149: getfield      #22                 // Field rs1:Lorg/apache/hadoop/hbase/regionserver/HRegionServer;
     152: getstatic     #24                 // Field TABLE_NAME:Lorg/apache/hadoop/hbase/TableName;
     155: getstatic     #25                 // Field FAMILY:[B
     158: invokevirtual #37                 // Method org/apache/hadoop/hbase/HBaseTestingUtility.getNumHFilesForRS:(Lorg/apache/hadoop/hbase/regionserver/HRegionServer;Lorg/apache/hadoop/hbase/TableName;[B)I
     161: aload_0
     162: getfield      #4                  // Field HTU:Lorg/apache/hadoop/hbase/HBaseTestingUtility;
     165: aload_0
     166: getfield      #23                 // Field rs2:Lorg/apache/hadoop/hbase/regionserver/HRegionServer;
     169: getstatic     #24                 // Field TABLE_NAME:Lorg/apache/hadoop/hbase/TableName;
     172: getstatic     #25                 // Field FAMILY:[B
     175: invokevirtual #37                 // Method org/apache/hadoop/hbase/HBaseTestingUtility.getNumHFilesForRS:(Lorg/apache/hadoop/hbase/regionserver/HRegionServer;Lorg/apache/hadoop/hbase/TableName;[B)I
     178: iadd
     179: i2l
     180: invokestatic  #38                 // Method org/junit/Assert.assertEquals:(JJ)V
     183: lload         4
     185: aload_2
     186: invokeinterface #35,  1           // InterfaceMethod org/apache/hadoop/hbase/io/hfile/BlockCache.getBlockCount:()J
     191: invokestatic  #38                 // Method org/junit/Assert.assertEquals:(JJ)V
     194: lload         6
     196: aload_3
     197: invokeinterface #35,  1           // InterfaceMethod org/apache/hadoop/hbase/io/hfile/BlockCache.getBlockCount:()J
     202: invokestatic  #38                 // Method org/junit/Assert.assertEquals:(JJ)V
     205: return

  public void testClearBlockCacheFromAsyncAdmin() throws java.lang.Exception;
    Code:
       0: aload_0
       1: getfield      #4                  // Field HTU:Lorg/apache/hadoop/hbase/HBaseTestingUtility;
       4: invokevirtual #5                  // Method org/apache/hadoop/hbase/HBaseTestingUtility.getConfiguration:()Lorg/apache/hadoop/conf/Configuration;
       7: invokestatic  #43                 // Method org/apache/hadoop/hbase/client/ConnectionFactory.createAsyncConnection:(Lorg/apache/hadoop/conf/Configuration;)Ljava/util/concurrent/CompletableFuture;
      10: invokevirtual #44                 // Method java/util/concurrent/CompletableFuture.get:()Ljava/lang/Object;
      13: checkcast     #45                 // class org/apache/hadoop/hbase/client/AsyncConnection
      16: invokeinterface #46,  1           // InterfaceMethod org/apache/hadoop/hbase/client/AsyncConnection.getAdmin:()Lorg/apache/hadoop/hbase/client/AsyncAdmin;
      21: astore_1
      22: aload_0
      23: getfield      #22                 // Field rs1:Lorg/apache/hadoop/hbase/regionserver/HRegionServer;
      26: invokevirtual #32                 // Method org/apache/hadoop/hbase/regionserver/HRegionServer.getBlockCache:()Ljava/util/Optional;
      29: invokevirtual #33                 // Method java/util/Optional.get:()Ljava/lang/Object;
      32: checkcast     #34                 // class org/apache/hadoop/hbase/io/hfile/BlockCache
      35: astore_2
      36: aload_0
      37: getfield      #23                 // Field rs2:Lorg/apache/hadoop/hbase/regionserver/HRegionServer;
      40: invokevirtual #32                 // Method org/apache/hadoop/hbase/regionserver/HRegionServer.getBlockCache:()Ljava/util/Optional;
      43: invokevirtual #33                 // Method java/util/Optional.get:()Ljava/lang/Object;
      46: checkcast     #34                 // class org/apache/hadoop/hbase/io/hfile/BlockCache
      49: astore_3
      50: aload_2
      51: invokeinterface #35,  1           // InterfaceMethod org/apache/hadoop/hbase/io/hfile/BlockCache.getBlockCount:()J
      56: lstore        4
      58: aload_3
      59: invokeinterface #35,  1           // InterfaceMethod org/apache/hadoop/hbase/io/hfile/BlockCache.getBlockCount:()J
      64: lstore        6
      66: aload_0
      67: aload_0
      68: getfield      #22                 // Field rs1:Lorg/apache/hadoop/hbase/regionserver/HRegionServer;
      71: invokespecial #36                 // Method scanAllRegionsForRS:(Lorg/apache/hadoop/hbase/regionserver/HRegionServer;)V
      74: aload_2
      75: invokeinterface #35,  1           // InterfaceMethod org/apache/hadoop/hbase/io/hfile/BlockCache.getBlockCount:()J
      80: lload         4
      82: lsub
      83: aload_0
      84: getfield      #4                  // Field HTU:Lorg/apache/hadoop/hbase/HBaseTestingUtility;
      87: aload_0
      88: getfield      #22                 // Field rs1:Lorg/apache/hadoop/hbase/regionserver/HRegionServer;
      91: getstatic     #24                 // Field TABLE_NAME:Lorg/apache/hadoop/hbase/TableName;
      94: getstatic     #25                 // Field FAMILY:[B
      97: invokevirtual #37                 // Method org/apache/hadoop/hbase/HBaseTestingUtility.getNumHFilesForRS:(Lorg/apache/hadoop/hbase/regionserver/HRegionServer;Lorg/apache/hadoop/hbase/TableName;[B)I
     100: i2l
     101: invokestatic  #38                 // Method org/junit/Assert.assertEquals:(JJ)V
     104: aload_0
     105: aload_0
     106: getfield      #23                 // Field rs2:Lorg/apache/hadoop/hbase/regionserver/HRegionServer;
     109: invokespecial #36                 // Method scanAllRegionsForRS:(Lorg/apache/hadoop/hbase/regionserver/HRegionServer;)V
     112: aload_3
     113: invokeinterface #35,  1           // InterfaceMethod org/apache/hadoop/hbase/io/hfile/BlockCache.getBlockCount:()J
     118: lload         6
     120: lsub
     121: aload_0
     122: getfield      #4                  // Field HTU:Lorg/apache/hadoop/hbase/HBaseTestingUtility;
     125: aload_0
     126: getfield      #23                 // Field rs2:Lorg/apache/hadoop/hbase/regionserver/HRegionServer;
     129: getstatic     #24                 // Field TABLE_NAME:Lorg/apache/hadoop/hbase/TableName;
     132: getstatic     #25                 // Field FAMILY:[B
     135: invokevirtual #37                 // Method org/apache/hadoop/hbase/HBaseTestingUtility.getNumHFilesForRS:(Lorg/apache/hadoop/hbase/regionserver/HRegionServer;Lorg/apache/hadoop/hbase/TableName;[B)I
     138: i2l
     139: invokestatic  #38                 // Method org/junit/Assert.assertEquals:(JJ)V
     142: aload_1
     143: getstatic     #24                 // Field TABLE_NAME:Lorg/apache/hadoop/hbase/TableName;
     146: invokeinterface #47,  2           // InterfaceMethod org/apache/hadoop/hbase/client/AsyncAdmin.clearBlockCache:(Lorg/apache/hadoop/hbase/TableName;)Ljava/util/concurrent/CompletableFuture;
     151: invokevirtual #44                 // Method java/util/concurrent/CompletableFuture.get:()Ljava/lang/Object;
     154: checkcast     #48                 // class org/apache/hadoop/hbase/CacheEvictionStats
     157: astore        8
     159: aload         8
     161: invokevirtual #42                 // Method org/apache/hadoop/hbase/CacheEvictionStats.getEvictedBlocks:()J
     164: aload_0
     165: getfield      #4                  // Field HTU:Lorg/apache/hadoop/hbase/HBaseTestingUtility;
     168: aload_0
     169: getfield      #22                 // Field rs1:Lorg/apache/hadoop/hbase/regionserver/HRegionServer;
     172: getstatic     #24                 // Field TABLE_NAME:Lorg/apache/hadoop/hbase/TableName;
     175: getstatic     #25                 // Field FAMILY:[B
     178: invokevirtual #37                 // Method org/apache/hadoop/hbase/HBaseTestingUtility.getNumHFilesForRS:(Lorg/apache/hadoop/hbase/regionserver/HRegionServer;Lorg/apache/hadoop/hbase/TableName;[B)I
     181: aload_0
     182: getfield      #4                  // Field HTU:Lorg/apache/hadoop/hbase/HBaseTestingUtility;
     185: aload_0
     186: getfield      #23                 // Field rs2:Lorg/apache/hadoop/hbase/regionserver/HRegionServer;
     189: getstatic     #24                 // Field TABLE_NAME:Lorg/apache/hadoop/hbase/TableName;
     192: getstatic     #25                 // Field FAMILY:[B
     195: invokevirtual #37                 // Method org/apache/hadoop/hbase/HBaseTestingUtility.getNumHFilesForRS:(Lorg/apache/hadoop/hbase/regionserver/HRegionServer;Lorg/apache/hadoop/hbase/TableName;[B)I
     198: iadd
     199: i2l
     200: invokestatic  #38                 // Method org/junit/Assert.assertEquals:(JJ)V
     203: lload         4
     205: aload_2
     206: invokeinterface #35,  1           // InterfaceMethod org/apache/hadoop/hbase/io/hfile/BlockCache.getBlockCount:()J
     211: invokestatic  #38                 // Method org/junit/Assert.assertEquals:(JJ)V
     214: lload         6
     216: aload_3
     217: invokeinterface #35,  1           // InterfaceMethod org/apache/hadoop/hbase/io/hfile/BlockCache.getBlockCount:()J
     222: invokestatic  #38                 // Method org/junit/Assert.assertEquals:(JJ)V
     225: return

  static {};
    Code:
       0: ldc           #18                 // class org/apache/hadoop/hbase/regionserver/TestClearRegionBlockCache
       2: invokestatic  #61                 // Method org/apache/hadoop/hbase/HBaseClassTestRule.forClass:(Ljava/lang/Class;)Lorg/apache/hadoop/hbase/HBaseClassTestRule;
       5: putstatic     #62                 // Field CLASS_RULE:Lorg/apache/hadoop/hbase/HBaseClassTestRule;
       8: ldc           #18                 // class org/apache/hadoop/hbase/regionserver/TestClearRegionBlockCache
      10: invokestatic  #63                 // Method org/slf4j/LoggerFactory.getLogger:(Ljava/lang/Class;)Lorg/slf4j/Logger;
      13: putstatic     #64                 // Field LOG:Lorg/slf4j/Logger;
      16: ldc           #65                 // String testClearRegionBlockCache
      18: invokestatic  #66                 // Method org/apache/hadoop/hbase/TableName.valueOf:(Ljava/lang/String;)Lorg/apache/hadoop/hbase/TableName;
      21: putstatic     #24                 // Field TABLE_NAME:Lorg/apache/hadoop/hbase/TableName;
      24: ldc           #67                 // String family
      26: invokestatic  #68                 // Method org/apache/hadoop/hbase/util/Bytes.toBytes:(Ljava/lang/String;)[B
      29: putstatic     #25                 // Field FAMILY:[B
      32: iconst_1
      33: anewarray     #69                 // class "[B"
      36: dup
      37: iconst_0
      38: ldc           #70                 // String 5
      40: invokestatic  #68                 // Method org/apache/hadoop/hbase/util/Bytes.toBytes:(Ljava/lang/String;)[B
      43: aastore
      44: putstatic     #26                 // Field SPLIT_KEY:[[B
      47: return
}
