Compiled from "TestRegionServerCoprocessorExceptionWithAbort.java"
class org.apache.hadoop.hbase.coprocessor.TestRegionServerCoprocessorExceptionWithAbort$1 implements org.apache.hadoop.hbase.Waiter$Predicate<java.lang.Exception> {
  final org.apache.hadoop.hbase.regionserver.HRegionServer val$regionServer;

  final org.apache.hadoop.hbase.coprocessor.TestRegionServerCoprocessorExceptionWithAbort this$0;

  org.apache.hadoop.hbase.coprocessor.TestRegionServerCoprocessorExceptionWithAbort$1(org.apache.hadoop.hbase.coprocessor.TestRegionServerCoprocessorExceptionWithAbort, org.apache.hadoop.hbase.regionserver.HRegionServer);
    Code:
       0: aload_0
       1: aload_1
       2: putfield      #1                  // Field this$0:Lorg/apache/hadoop/hbase/coprocessor/TestRegionServerCoprocessorExceptionWithAbort;
       5: aload_0
       6: aload_2
       7: putfield      #2                  // Field val$regionServer:Lorg/apache/hadoop/hbase/regionserver/HRegionServer;
      10: aload_0
      11: invokespecial #3                  // Method java/lang/Object."<init>":()V
      14: return

  public boolean evaluate() throws java.lang.Exception;
    Code:
       0: aload_0
       1: getfield      #2                  // Field val$regionServer:Lorg/apache/hadoop/hbase/regionserver/HRegionServer;
       4: invokevirtual #4                  // Method org/apache/hadoop/hbase/regionserver/HRegionServer.isAborted:()Z
       7: ireturn
}
