Compiled from "TestCommonsAES.java"
class org.apache.hadoop.hbase.io.crypto.aes.TestCommonsAES$TestProvider$1 implements java.security.PrivilegedAction<java.lang.Object> {
  final org.apache.hadoop.hbase.io.crypto.aes.TestCommonsAES$TestProvider this$0;

  org.apache.hadoop.hbase.io.crypto.aes.TestCommonsAES$TestProvider$1(org.apache.hadoop.hbase.io.crypto.aes.TestCommonsAES$TestProvider);
    Code:
       0: aload_0
       1: aload_1
       2: putfield      #1                  // Field this$0:Lorg/apache/hadoop/hbase/io/crypto/aes/TestCommonsAES$TestProvider;
       5: aload_0
       6: invokespecial #2                  // Method java/lang/Object."<init>":()V
       9: return

  public java.lang.Object run();
    Code:
       0: aload_0
       1: getfield      #1                  // Field this$0:Lorg/apache/hadoop/hbase/io/crypto/aes/TestCommonsAES$TestProvider;
       4: ldc           #3                  // String SecureRandom.TestRNG
       6: new           #4                  // class java/lang/StringBuilder
       9: dup
      10: invokespecial #5                  // Method java/lang/StringBuilder."<init>":()V
      13: ldc           #6                  // class org/apache/hadoop/hbase/io/crypto/aes/TestCommonsAES
      15: invokevirtual #7                  // Method java/lang/Class.getName:()Ljava/lang/String;
      18: invokevirtual #8                  // Method java/lang/StringBuilder.append:(Ljava/lang/String;)Ljava/lang/StringBuilder;
      21: ldc           #9                  // String $TestRNG
      23: invokevirtual #8                  // Method java/lang/StringBuilder.append:(Ljava/lang/String;)Ljava/lang/StringBuilder;
      26: invokevirtual #10                 // Method java/lang/StringBuilder.toString:()Ljava/lang/String;
      29: invokevirtual #11                 // Method org/apache/hadoop/hbase/io/crypto/aes/TestCommonsAES$TestProvider.put:(Ljava/lang/Object;Ljava/lang/Object;)Ljava/lang/Object;
      32: pop
      33: aconst_null
      34: areturn
}
