Compiled from "TestAsyncProcess.java"
class org.apache.hadoop.hbase.client.TestAsyncProcess$MyAsyncProcessWithReplicas$2 extends org.apache.hadoop.hbase.client.RpcRetryingCallerImpl<org.apache.hadoop.hbase.client.AbstractResponse> {
  final boolean val$isDefault;

  final org.apache.hadoop.hbase.ServerName val$server;

  final org.apache.hadoop.hbase.client.MultiResponse val$mr;

  final org.apache.hadoop.hbase.client.TestAsyncProcess$MyAsyncProcessWithReplicas this$0;

  org.apache.hadoop.hbase.client.TestAsyncProcess$MyAsyncProcessWithReplicas$2(org.apache.hadoop.hbase.client.TestAsyncProcess$MyAsyncProcessWithReplicas, long, long, int, int, boolean, org.apache.hadoop.hbase.ServerName, org.apache.hadoop.hbase.client.MultiResponse);
    Code:
       0: aload_0
       1: aload_1
       2: putfield      #1                  // Field this$0:Lorg/apache/hadoop/hbase/client/TestAsyncProcess$MyAsyncProcessWithReplicas;
       5: aload_0
       6: iload         8
       8: putfield      #2                  // Field val$isDefault:Z
      11: aload_0
      12: aload         9
      14: putfield      #3                  // Field val$server:Lorg/apache/hadoop/hbase/ServerName;
      17: aload_0
      18: aload         10
      20: putfield      #4                  // Field val$mr:Lorg/apache/hadoop/hbase/client/MultiResponse;
      23: aload_0
      24: lload_2
      25: lload         4
      27: iload         6
      29: iload         7
      31: invokespecial #5                  // Method org/apache/hadoop/hbase/client/RpcRetryingCallerImpl."<init>":(JJII)V
      34: return

  public org.apache.hadoop.hbase.client.MultiResponse callWithoutRetries(org.apache.hadoop.hbase.client.RetryingCallable<org.apache.hadoop.hbase.client.AbstractResponse>, int) throws java.io.IOException, java.lang.RuntimeException;
    Code:
       0: ldc2_w        #6                  // long -1l
       3: lstore_3
       4: aload_0
       5: getfield      #2                  // Field val$isDefault:Z
       8: ifeq          56
      11: aload_0
      12: getfield      #1                  // Field this$0:Lorg/apache/hadoop/hbase/client/TestAsyncProcess$MyAsyncProcessWithReplicas;
      15: invokestatic  #8                  // Method org/apache/hadoop/hbase/client/TestAsyncProcess$MyAsyncProcessWithReplicas.access$500:(Lorg/apache/hadoop/hbase/client/TestAsyncProcess$MyAsyncProcessWithReplicas;)Ljava/util/Map;
      18: aload_0
      19: getfield      #3                  // Field val$server:Lorg/apache/hadoop/hbase/ServerName;
      22: invokeinterface #9,  2            // InterfaceMethod java/util/Map.get:(Ljava/lang/Object;)Ljava/lang/Object;
      27: checkcast     #10                 // class java/lang/Long
      30: astore        5
      32: aload         5
      34: ifnonnull     47
      37: aload_0
      38: getfield      #1                  // Field this$0:Lorg/apache/hadoop/hbase/client/TestAsyncProcess$MyAsyncProcessWithReplicas;
      41: invokestatic  #11                 // Method org/apache/hadoop/hbase/client/TestAsyncProcess$MyAsyncProcessWithReplicas.access$600:(Lorg/apache/hadoop/hbase/client/TestAsyncProcess$MyAsyncProcessWithReplicas;)J
      44: goto          52
      47: aload         5
      49: invokevirtual #12                 // Method java/lang/Long.longValue:()J
      52: lstore_3
      53: goto          64
      56: aload_0
      57: getfield      #1                  // Field this$0:Lorg/apache/hadoop/hbase/client/TestAsyncProcess$MyAsyncProcessWithReplicas;
      60: invokestatic  #13                 // Method org/apache/hadoop/hbase/client/TestAsyncProcess$MyAsyncProcessWithReplicas.access$700:(Lorg/apache/hadoop/hbase/client/TestAsyncProcess$MyAsyncProcessWithReplicas;)J
      63: lstore_3
      64: lload_3
      65: lconst_0
      66: lcmp
      67: ifeq          79
      70: lload_3
      71: invokestatic  #14                 // Method java/lang/Thread.sleep:(J)V
      74: goto          79
      77: astore        5
      79: aload_0
      80: getfield      #4                  // Field val$mr:Lorg/apache/hadoop/hbase/client/MultiResponse;
      83: areturn
    Exception table:
       from    to  target type
          70    74    77   Class java/lang/InterruptedException

  public java.lang.Object callWithoutRetries(org.apache.hadoop.hbase.client.RetryingCallable, int) throws java.io.IOException, java.lang.RuntimeException;
    Code:
       0: aload_0
       1: aload_1
       2: iload_2
       3: invokevirtual #16                 // Method callWithoutRetries:(Lorg/apache/hadoop/hbase/client/RetryingCallable;I)Lorg/apache/hadoop/hbase/client/MultiResponse;
       6: areturn
}
