Compiled from "TestClientTimeouts.java"
class org.apache.hadoop.hbase.client.TestClientTimeouts$RandomTimeoutBlockingRpcChannel extends org.apache.hadoop.hbase.ipc.AbstractRpcClient$BlockingRpcChannelImplementation {
  public static final double CHANCE_OF_TIMEOUT;

  org.apache.hadoop.hbase.client.TestClientTimeouts$RandomTimeoutBlockingRpcChannel(org.apache.hadoop.hbase.ipc.BlockingRpcClient, org.apache.hadoop.hbase.ServerName, org.apache.hadoop.hbase.security.User, int);
    Code:
       0: aload_0
       1: aload_1
       2: new           #2                  // class java/net/InetSocketAddress
       5: dup
       6: aload_2
       7: invokevirtual #3                  // Method org/apache/hadoop/hbase/ServerName.getHostname:()Ljava/lang/String;
      10: aload_2
      11: invokevirtual #4                  // Method org/apache/hadoop/hbase/ServerName.getPort:()I
      14: invokespecial #5                  // Method java/net/InetSocketAddress."<init>":(Ljava/lang/String;I)V
      17: aload_3
      18: iload         4
      20: invokespecial #6                  // Method org/apache/hadoop/hbase/ipc/AbstractRpcClient$BlockingRpcChannelImplementation."<init>":(Lorg/apache/hadoop/hbase/ipc/AbstractRpcClient;Ljava/net/InetSocketAddress;Lorg/apache/hadoop/hbase/security/User;I)V
      23: return

  public org.apache.hbase.thirdparty.com.google.protobuf.Message callBlockingMethod(org.apache.hbase.thirdparty.com.google.protobuf.Descriptors$MethodDescriptor, org.apache.hbase.thirdparty.com.google.protobuf.RpcController, org.apache.hbase.thirdparty.com.google.protobuf.Message, org.apache.hbase.thirdparty.com.google.protobuf.Message) throws org.apache.hbase.thirdparty.com.google.protobuf.ServiceException;
    Code:
       0: getstatic     #1                  // Field invokations:Ljava/util/concurrent/atomic/AtomicInteger;
       3: invokevirtual #7                  // Method java/util/concurrent/atomic/AtomicInteger.getAndIncrement:()I
       6: pop
       7: getstatic     #8                  // Field RANDOM:Ljava/util/Random;
      10: invokevirtual #9                  // Method java/util/Random.nextFloat:()F
      13: f2d
      14: ldc2_w        #11                 // double 0.3d
      17: dcmpg
      18: ifge          38
      21: new           #13                 // class org/apache/hbase/thirdparty/com/google/protobuf/ServiceException
      24: dup
      25: new           #14                 // class java/net/SocketTimeoutException
      28: dup
      29: ldc           #15                 // String fake timeout
      31: invokespecial #16                 // Method java/net/SocketTimeoutException."<init>":(Ljava/lang/String;)V
      34: invokespecial #17                 // Method org/apache/hbase/thirdparty/com/google/protobuf/ServiceException."<init>":(Ljava/lang/Throwable;)V
      37: athrow
      38: aload_0
      39: aload_1
      40: aload_2
      41: aload_3
      42: aload         4
      44: invokespecial #18                 // Method org/apache/hadoop/hbase/ipc/AbstractRpcClient$BlockingRpcChannelImplementation.callBlockingMethod:(Lorg/apache/hbase/thirdparty/com/google/protobuf/Descriptors$MethodDescriptor;Lorg/apache/hbase/thirdparty/com/google/protobuf/RpcController;Lorg/apache/hbase/thirdparty/com/google/protobuf/Message;Lorg/apache/hbase/thirdparty/com/google/protobuf/Message;)Lorg/apache/hbase/thirdparty/com/google/protobuf/Message;
      47: areturn

  static java.util.concurrent.atomic.AtomicInteger access$000();
    Code:
       0: getstatic     #1                  // Field invokations:Ljava/util/concurrent/atomic/AtomicInteger;
       3: areturn

  static {};
    Code:
       0: new           #19                 // class java/util/Random
       3: dup
       4: invokestatic  #20                 // Method java/lang/System.currentTimeMillis:()J
       7: invokespecial #21                 // Method java/util/Random."<init>":(J)V
      10: putstatic     #8                  // Field RANDOM:Ljava/util/Random;
      13: new           #22                 // class java/util/concurrent/atomic/AtomicInteger
      16: dup
      17: invokespecial #23                 // Method java/util/concurrent/atomic/AtomicInteger."<init>":()V
      20: putstatic     #1                  // Field invokations:Ljava/util/concurrent/atomic/AtomicInteger;
      23: return
}
