Compiled from "TestNettyIPC.java"
class org.apache.hadoop.hbase.ipc.TestNettyIPC$2 extends org.apache.hadoop.hbase.ipc.NettyRpcClient {
  final org.apache.hadoop.hbase.ipc.TestNettyIPC this$0;

  org.apache.hadoop.hbase.ipc.TestNettyIPC$2(org.apache.hadoop.hbase.ipc.TestNettyIPC, org.apache.hadoop.conf.Configuration);
    Code:
       0: aload_0
       1: aload_1
       2: putfield      #1                  // Field this$0:Lorg/apache/hadoop/hbase/ipc/TestNettyIPC;
       5: aload_0
       6: aload_2
       7: invokespecial #2                  // Method org/apache/hadoop/hbase/ipc/NettyRpcClient."<init>":(Lorg/apache/hadoop/conf/Configuration;)V
      10: return

  boolean isTcpNoDelay();
    Code:
       0: new           #3                  // class java/lang/RuntimeException
       3: dup
       4: ldc           #4                  // String Injected fault
       6: invokespecial #5                  // Method java/lang/RuntimeException."<init>":(Ljava/lang/String;)V
       9: athrow
}
