Compiled from "TestMajorCompactionTTLRequest.java"
public class org.apache.hadoop.hbase.util.compaction.TestMajorCompactionTTLRequest extends org.apache.hadoop.hbase.util.compaction.TestMajorCompactionRequest {
  public static final org.apache.hadoop.hbase.HBaseClassTestRule CLASS_RULE;

  public org.apache.hadoop.hbase.util.compaction.TestMajorCompactionTTLRequest();
    Code:
       0: aload_0
       1: invokespecial #1                  // Method org/apache/hadoop/hbase/util/compaction/TestMajorCompactionRequest."<init>":()V
       4: return

  public void setUp() throws java.lang.Exception;
    Code:
       0: aload_0
       1: getstatic     #2                  // Field UTILITY:Lorg/apache/hadoop/hbase/HBaseTestingUtility;
       4: ldc           #3                  // String TestMajorCompactionTTLRequest
       6: invokevirtual #4                  // Method org/apache/hadoop/hbase/HBaseTestingUtility.getDataTestDirOnTestFS:(Ljava/lang/String;)Lorg/apache/hadoop/fs/Path;
       9: putfield      #5                  // Field rootRegionDir:Lorg/apache/hadoop/fs/Path;
      12: aload_0
      13: new           #6                  // class org/apache/hadoop/fs/Path
      16: dup
      17: aload_0
      18: getfield      #5                  // Field rootRegionDir:Lorg/apache/hadoop/fs/Path;
      21: ldc           #8                  // String a
      23: invokespecial #9                  // Method org/apache/hadoop/fs/Path."<init>":(Lorg/apache/hadoop/fs/Path;Ljava/lang/String;)V
      26: putfield      #10                 // Field regionStoreDir:Lorg/apache/hadoop/fs/Path;
      29: return

  public void testStoresNeedingCompaction() throws java.lang.Exception;
    Code:
       0: aload_0
       1: aload_0
       2: getfield      #10                 // Field regionStoreDir:Lorg/apache/hadoop/fs/Path;
       5: iconst_5
       6: ldc2_w        #11                 // long 10l
       9: invokevirtual #13                 // Method mockStoreFiles:(Lorg/apache/hadoop/fs/Path;IJ)Ljava/util/List;
      12: astore_1
      13: aload_0
      14: aload_0
      15: getfield      #10                 // Field regionStoreDir:Lorg/apache/hadoop/fs/Path;
      18: iconst_5
      19: ldc2_w        #14                 // long 100l
      22: invokevirtual #13                 // Method mockStoreFiles:(Lorg/apache/hadoop/fs/Path;IJ)Ljava/util/List;
      25: astore_2
      26: aload_1
      27: invokestatic  #16                 // Method org/apache/hbase/thirdparty/com/google/common/collect/Lists.newArrayList:(Ljava/lang/Iterable;)Ljava/util/ArrayList;
      30: astore_3
      31: aload_3
      32: aload_2
      33: invokeinterface #17,  2           // InterfaceMethod java/util/List.addAll:(Ljava/util/Collection;)Z
      38: pop
      39: aload_0
      40: aload_3
      41: invokespecial #18                 // Method makeMockRequest:(Ljava/util/List;)Lorg/apache/hadoop/hbase/util/compaction/MajorCompactionTTLRequest;
      44: astore        4
      46: aload         4
      48: ldc           #19                 // class org/apache/hadoop/conf/Configuration
      50: invokestatic  #20                 // Method org/mockito/Mockito.mock:(Ljava/lang/Class;)Ljava/lang/Object;
      53: checkcast     #19                 // class org/apache/hadoop/conf/Configuration
      56: iconst_1
      57: anewarray     #21                 // class java/lang/String
      60: dup
      61: iconst_0
      62: ldc           #8                  // String a
      64: aastore
      65: invokestatic  #22                 // Method org/apache/hbase/thirdparty/com/google/common/collect/Sets.newHashSet:([Ljava/lang/Object;)Ljava/util/HashSet;
      68: ldc2_w        #11                 // long 10l
      71: invokevirtual #23                 // Method org/apache/hadoop/hbase/util/compaction/MajorCompactionTTLRequest.createRequest:(Lorg/apache/hadoop/conf/Configuration;Ljava/util/Set;J)Ljava/util/Optional;
      74: astore        5
      76: aload         5
      78: invokevirtual #24                 // Method java/util/Optional.isPresent:()Z
      81: invokestatic  #25                 // Method org/junit/Assert.assertFalse:(Z)V
      84: aload         4
      86: ldc           #19                 // class org/apache/hadoop/conf/Configuration
      88: invokestatic  #20                 // Method org/mockito/Mockito.mock:(Ljava/lang/Class;)Ljava/lang/Object;
      91: checkcast     #19                 // class org/apache/hadoop/conf/Configuration
      94: iconst_1
      95: anewarray     #21                 // class java/lang/String
      98: dup
      99: iconst_0
     100: ldc           #8                  // String a
     102: aastore
     103: invokestatic  #22                 // Method org/apache/hbase/thirdparty/com/google/common/collect/Sets.newHashSet:([Ljava/lang/Object;)Ljava/util/HashSet;
     106: ldc2_w        #14                 // long 100l
     109: invokevirtual #23                 // Method org/apache/hadoop/hbase/util/compaction/MajorCompactionTTLRequest.createRequest:(Lorg/apache/hadoop/conf/Configuration;Ljava/util/Set;J)Ljava/util/Optional;
     112: astore        5
     114: aload         5
     116: invokevirtual #24                 // Method java/util/Optional.isPresent:()Z
     119: invokestatic  #25                 // Method org/junit/Assert.assertFalse:(Z)V
     122: aload         4
     124: ldc           #19                 // class org/apache/hadoop/conf/Configuration
     126: invokestatic  #20                 // Method org/mockito/Mockito.mock:(Ljava/lang/Class;)Ljava/lang/Object;
     129: checkcast     #19                 // class org/apache/hadoop/conf/Configuration
     132: iconst_1
     133: anewarray     #21                 // class java/lang/String
     136: dup
     137: iconst_0
     138: ldc           #8                  // String a
     140: aastore
     141: invokestatic  #22                 // Method org/apache/hbase/thirdparty/com/google/common/collect/Sets.newHashSet:([Ljava/lang/Object;)Ljava/util/HashSet;
     144: ldc2_w        #26                 // long 101l
     147: invokevirtual #23                 // Method org/apache/hadoop/hbase/util/compaction/MajorCompactionTTLRequest.createRequest:(Lorg/apache/hadoop/conf/Configuration;Ljava/util/Set;J)Ljava/util/Optional;
     150: astore        5
     152: aload         5
     154: invokevirtual #24                 // Method java/util/Optional.isPresent:()Z
     157: invokestatic  #28                 // Method org/junit/Assert.assertTrue:(Z)V
     160: return

  static {};
    Code:
       0: ldc           #48                 // class org/apache/hadoop/hbase/util/compaction/TestMajorCompactionTTLRequest
       2: invokestatic  #49                 // Method org/apache/hadoop/hbase/HBaseClassTestRule.forClass:(Ljava/lang/Class;)Lorg/apache/hadoop/hbase/HBaseClassTestRule;
       5: putstatic     #50                 // Field CLASS_RULE:Lorg/apache/hadoop/hbase/HBaseClassTestRule;
       8: return
}
