Compiled from "TestPassCustomCellViaRegionObserver.java"
public class org.apache.hadoop.hbase.coprocessor.TestPassCustomCellViaRegionObserver {
  public static final org.apache.hadoop.hbase.HBaseClassTestRule CLASS_RULE;

  public org.junit.rules.TestName testName;

  public org.apache.hadoop.hbase.coprocessor.TestPassCustomCellViaRegionObserver();
    Code:
       0: aload_0
       1: invokespecial #5                  // Method java/lang/Object."<init>":()V
       4: aload_0
       5: new           #6                  // class org/junit/rules/TestName
       8: dup
       9: invokespecial #7                  // Method org/junit/rules/TestName."<init>":()V
      12: putfield      #8                  // Field testName:Lorg/junit/rules/TestName;
      15: aload_0
      16: aconst_null
      17: putfield      #9                  // Field table:Lorg/apache/hadoop/hbase/client/Table;
      20: return

  public static void setupBeforeClass() throws java.lang.Exception;
    Code:
       0: getstatic     #10                 // Field UTIL:Lorg/apache/hadoop/hbase/HBaseTestingUtility;
       3: invokevirtual #11                 // Method org/apache/hadoop/hbase/HBaseTestingUtility.getConfiguration:()Lorg/apache/hadoop/conf/Configuration;
       6: ldc           #13                 // String hbase.client.retries.number
       8: iconst_2
       9: invokevirtual #14                 // Method org/apache/hadoop/conf/Configuration.setInt:(Ljava/lang/String;I)V
      12: getstatic     #10                 // Field UTIL:Lorg/apache/hadoop/hbase/HBaseTestingUtility;
      15: invokevirtual #15                 // Method org/apache/hadoop/hbase/HBaseTestingUtility.startMiniCluster:()Lorg/apache/hadoop/hbase/MiniHBaseCluster;
      18: pop
      19: return

  public static void tearDownAfterClass() throws java.lang.Exception;
    Code:
       0: getstatic     #10                 // Field UTIL:Lorg/apache/hadoop/hbase/HBaseTestingUtility;
       3: invokevirtual #16                 // Method org/apache/hadoop/hbase/HBaseTestingUtility.shutdownMiniCluster:()V
       6: return

  public void clearTable() throws java.io.IOException;
    Code:
       0: getstatic     #17                 // Field org/apache/hadoop/hbase/coprocessor/TestPassCustomCellViaRegionObserver$RegionObserverImpl.COUNT:Ljava/util/concurrent/atomic/AtomicInteger;
       3: iconst_0
       4: invokevirtual #18                 // Method java/util/concurrent/atomic/AtomicInteger.set:(I)V
       7: aload_0
       8: aload_0
       9: getfield      #8                  // Field testName:Lorg/junit/rules/TestName;
      12: invokevirtual #19                 // Method org/junit/rules/TestName.getMethodName:()Ljava/lang/String;
      15: invokestatic  #20                 // Method org/apache/hadoop/hbase/TableName.valueOf:(Ljava/lang/String;)Lorg/apache/hadoop/hbase/TableName;
      18: putfield      #21                 // Field tableName:Lorg/apache/hadoop/hbase/TableName;
      21: aload_0
      22: getfield      #9                  // Field table:Lorg/apache/hadoop/hbase/client/Table;
      25: ifnull        37
      28: aload_0
      29: getfield      #9                  // Field table:Lorg/apache/hadoop/hbase/client/Table;
      32: invokeinterface #22,  1           // InterfaceMethod org/apache/hadoop/hbase/client/Table.close:()V
      37: getstatic     #10                 // Field UTIL:Lorg/apache/hadoop/hbase/HBaseTestingUtility;
      40: invokevirtual #23                 // Method org/apache/hadoop/hbase/HBaseTestingUtility.getAdmin:()Lorg/apache/hadoop/hbase/client/Admin;
      43: astore_1
      44: aconst_null
      45: astore_2
      46: aload_1
      47: invokeinterface #24,  1           // InterfaceMethod org/apache/hadoop/hbase/client/Admin.listTableNames:()[Lorg/apache/hadoop/hbase/TableName;
      52: astore_3
      53: aload_3
      54: arraylength
      55: istore        4
      57: iconst_0
      58: istore        5
      60: iload         5
      62: iload         4
      64: if_icmpge     100
      67: aload_3
      68: iload         5
      70: aaload
      71: astore        6
      73: aload_1
      74: aload         6
      76: invokeinterface #25,  2           // InterfaceMethod org/apache/hadoop/hbase/client/Admin.disableTable:(Lorg/apache/hadoop/hbase/TableName;)V
      81: goto          86
      84: astore        7
      86: aload_1
      87: aload         6
      89: invokeinterface #27,  2           // InterfaceMethod org/apache/hadoop/hbase/client/Admin.deleteTable:(Lorg/apache/hadoop/hbase/TableName;)V
      94: iinc          5, 1
      97: goto          60
     100: aload_0
     101: getstatic     #10                 // Field UTIL:Lorg/apache/hadoop/hbase/HBaseTestingUtility;
     104: aload_0
     105: getfield      #21                 // Field tableName:Lorg/apache/hadoop/hbase/TableName;
     108: invokestatic  #28                 // Method org/apache/hadoop/hbase/client/TableDescriptorBuilder.newBuilder:(Lorg/apache/hadoop/hbase/TableName;)Lorg/apache/hadoop/hbase/client/TableDescriptorBuilder;
     111: getstatic     #29                 // Field FAMILY:[B
     114: invokestatic  #30                 // Method org/apache/hadoop/hbase/client/ColumnFamilyDescriptorBuilder.of:([B)Lorg/apache/hadoop/hbase/client/ColumnFamilyDescriptor;
     117: invokevirtual #31                 // Method org/apache/hadoop/hbase/client/TableDescriptorBuilder.setColumnFamily:(Lorg/apache/hadoop/hbase/client/ColumnFamilyDescriptor;)Lorg/apache/hadoop/hbase/client/TableDescriptorBuilder;
     120: ldc           #32                 // class org/apache/hadoop/hbase/coprocessor/TestPassCustomCellViaRegionObserver$RegionObserverImpl
     122: invokevirtual #33                 // Method java/lang/Class.getName:()Ljava/lang/String;
     125: invokevirtual #34                 // Method org/apache/hadoop/hbase/client/TableDescriptorBuilder.setCoprocessor:(Ljava/lang/String;)Lorg/apache/hadoop/hbase/client/TableDescriptorBuilder;
     128: invokevirtual #35                 // Method org/apache/hadoop/hbase/client/TableDescriptorBuilder.build:()Lorg/apache/hadoop/hbase/client/TableDescriptor;
     131: aconst_null
     132: checkcast     #36                 // class "[[B"
     135: invokevirtual #37                 // Method org/apache/hadoop/hbase/HBaseTestingUtility.createTable:(Lorg/apache/hadoop/hbase/client/TableDescriptor;[[B)Lorg/apache/hadoop/hbase/client/Table;
     138: putfield      #9                  // Field table:Lorg/apache/hadoop/hbase/client/Table;
     141: aload_1
     142: ifnull        220
     145: aload_2
     146: ifnull        167
     149: aload_1
     150: invokeinterface #38,  1           // InterfaceMethod org/apache/hadoop/hbase/client/Admin.close:()V
     155: goto          220
     158: astore_3
     159: aload_2
     160: aload_3
     161: invokevirtual #40                 // Method java/lang/Throwable.addSuppressed:(Ljava/lang/Throwable;)V
     164: goto          220
     167: aload_1
     168: invokeinterface #38,  1           // InterfaceMethod org/apache/hadoop/hbase/client/Admin.close:()V
     173: goto          220
     176: astore_3
     177: aload_3
     178: astore_2
     179: aload_3
     180: athrow
     181: astore        8
     183: aload_1
     184: ifnull        217
     187: aload_2
     188: ifnull        211
     191: aload_1
     192: invokeinterface #38,  1           // InterfaceMethod org/apache/hadoop/hbase/client/Admin.close:()V
     197: goto          217
     200: astore        9
     202: aload_2
     203: aload         9
     205: invokevirtual #40                 // Method java/lang/Throwable.addSuppressed:(Ljava/lang/Throwable;)V
     208: goto          217
     211: aload_1
     212: invokeinterface #38,  1           // InterfaceMethod org/apache/hadoop/hbase/client/Admin.close:()V
     217: aload         8
     219: athrow
     220: return
    Exception table:
       from    to  target type
          73    81    84   Class java/io/IOException
         149   155   158   Class java/lang/Throwable
          46   141   176   Class java/lang/Throwable
          46   141   181   any
         191   197   200   Class java/lang/Throwable
         176   183   181   any

  public void testMutation() throws java.lang.Exception;
    Code:
       0: new           #41                 // class org/apache/hadoop/hbase/client/Put
       3: dup
       4: getstatic     #42                 // Field ROW:[B
       7: invokespecial #43                 // Method org/apache/hadoop/hbase/client/Put."<init>":([B)V
      10: astore_1
      11: aload_1
      12: getstatic     #29                 // Field FAMILY:[B
      15: getstatic     #44                 // Field QUALIFIER:[B
      18: getstatic     #45                 // Field VALUE:[B
      21: invokevirtual #46                 // Method org/apache/hadoop/hbase/client/Put.addColumn:([B[B[B)Lorg/apache/hadoop/hbase/client/Put;
      24: pop
      25: aload_0
      26: getfield      #9                  // Field table:Lorg/apache/hadoop/hbase/client/Table;
      29: aload_1
      30: invokeinterface #47,  2           // InterfaceMethod org/apache/hadoop/hbase/client/Table.put:(Lorg/apache/hadoop/hbase/client/Put;)V
      35: getstatic     #45                 // Field VALUE:[B
      38: astore_2
      39: aload_0
      40: getfield      #9                  // Field table:Lorg/apache/hadoop/hbase/client/Table;
      43: new           #48                 // class org/apache/hadoop/hbase/client/Get
      46: dup
      47: getstatic     #42                 // Field ROW:[B
      50: invokespecial #49                 // Method org/apache/hadoop/hbase/client/Get."<init>":([B)V
      53: invokeinterface #50,  2           // InterfaceMethod org/apache/hadoop/hbase/client/Table.get:(Lorg/apache/hadoop/hbase/client/Get;)Lorg/apache/hadoop/hbase/client/Result;
      58: aload_2
      59: aload_2
      60: invokestatic  #51                 // Method assertResult:(Lorg/apache/hadoop/hbase/client/Result;[B[B)V
      63: invokestatic  #52                 // Method assertObserverHasExecuted:()V
      66: new           #53                 // class org/apache/hadoop/hbase/client/Increment
      69: dup
      70: getstatic     #42                 // Field ROW:[B
      73: invokespecial #54                 // Method org/apache/hadoop/hbase/client/Increment."<init>":([B)V
      76: astore_3
      77: aload_3
      78: getstatic     #29                 // Field FAMILY:[B
      81: getstatic     #44                 // Field QUALIFIER:[B
      84: ldc2_w        #55                 // long 10l
      87: invokevirtual #57                 // Method org/apache/hadoop/hbase/client/Increment.addColumn:([B[BJ)Lorg/apache/hadoop/hbase/client/Increment;
      90: pop
      91: aload_0
      92: getfield      #9                  // Field table:Lorg/apache/hadoop/hbase/client/Table;
      95: aload_3
      96: invokeinterface #58,  2           // InterfaceMethod org/apache/hadoop/hbase/client/Table.increment:(Lorg/apache/hadoop/hbase/client/Increment;)Lorg/apache/hadoop/hbase/client/Result;
     101: pop
     102: ldc2_w        #59                 // long 20l
     105: invokestatic  #61                 // Method org/apache/hadoop/hbase/util/Bytes.toBytes:(J)[B
     108: astore_2
     109: aload_0
     110: getfield      #9                  // Field table:Lorg/apache/hadoop/hbase/client/Table;
     113: new           #48                 // class org/apache/hadoop/hbase/client/Get
     116: dup
     117: getstatic     #42                 // Field ROW:[B
     120: invokespecial #49                 // Method org/apache/hadoop/hbase/client/Get."<init>":([B)V
     123: invokeinterface #50,  2           // InterfaceMethod org/apache/hadoop/hbase/client/Table.get:(Lorg/apache/hadoop/hbase/client/Get;)Lorg/apache/hadoop/hbase/client/Result;
     128: aload_2
     129: aload_2
     130: invokestatic  #51                 // Method assertResult:(Lorg/apache/hadoop/hbase/client/Result;[B[B)V
     133: invokestatic  #52                 // Method assertObserverHasExecuted:()V
     136: new           #62                 // class org/apache/hadoop/hbase/client/Append
     139: dup
     140: getstatic     #42                 // Field ROW:[B
     143: invokespecial #63                 // Method org/apache/hadoop/hbase/client/Append."<init>":([B)V
     146: astore        4
     148: aload         4
     150: getstatic     #29                 // Field FAMILY:[B
     153: getstatic     #44                 // Field QUALIFIER:[B
     156: getstatic     #64                 // Field APPEND_VALUE:[B
     159: invokevirtual #65                 // Method org/apache/hadoop/hbase/client/Append.addColumn:([B[B[B)Lorg/apache/hadoop/hbase/client/Append;
     162: pop
     163: aload_0
     164: getfield      #9                  // Field table:Lorg/apache/hadoop/hbase/client/Table;
     167: aload         4
     169: invokeinterface #66,  2           // InterfaceMethod org/apache/hadoop/hbase/client/Table.append:(Lorg/apache/hadoop/hbase/client/Append;)Lorg/apache/hadoop/hbase/client/Result;
     174: pop
     175: aload_2
     176: arraylength
     177: getstatic     #64                 // Field APPEND_VALUE:[B
     180: arraylength
     181: iadd
     182: newarray       byte
     184: invokestatic  #67                 // Method java/nio/ByteBuffer.wrap:([B)Ljava/nio/ByteBuffer;
     187: aload_2
     188: invokevirtual #68                 // Method java/nio/ByteBuffer.put:([B)Ljava/nio/ByteBuffer;
     191: getstatic     #64                 // Field APPEND_VALUE:[B
     194: invokevirtual #68                 // Method java/nio/ByteBuffer.put:([B)Ljava/nio/ByteBuffer;
     197: invokevirtual #69                 // Method java/nio/ByteBuffer.array:()[B
     200: astore_2
     201: aload_0
     202: getfield      #9                  // Field table:Lorg/apache/hadoop/hbase/client/Table;
     205: new           #48                 // class org/apache/hadoop/hbase/client/Get
     208: dup
     209: getstatic     #42                 // Field ROW:[B
     212: invokespecial #49                 // Method org/apache/hadoop/hbase/client/Get."<init>":([B)V
     215: invokeinterface #50,  2           // InterfaceMethod org/apache/hadoop/hbase/client/Table.get:(Lorg/apache/hadoop/hbase/client/Get;)Lorg/apache/hadoop/hbase/client/Result;
     220: aload_2
     221: aload_2
     222: invokestatic  #51                 // Method assertResult:(Lorg/apache/hadoop/hbase/client/Result;[B[B)V
     225: invokestatic  #52                 // Method assertObserverHasExecuted:()V
     228: new           #70                 // class org/apache/hadoop/hbase/client/Delete
     231: dup
     232: getstatic     #42                 // Field ROW:[B
     235: invokespecial #71                 // Method org/apache/hadoop/hbase/client/Delete."<init>":([B)V
     238: astore        5
     240: aload         5
     242: getstatic     #29                 // Field FAMILY:[B
     245: getstatic     #44                 // Field QUALIFIER:[B
     248: invokevirtual #72                 // Method org/apache/hadoop/hbase/client/Delete.addColumns:([B[B)Lorg/apache/hadoop/hbase/client/Delete;
     251: pop
     252: aload_0
     253: getfield      #9                  // Field table:Lorg/apache/hadoop/hbase/client/Table;
     256: aload         5
     258: invokeinterface #73,  2           // InterfaceMethod org/apache/hadoop/hbase/client/Table.delete:(Lorg/apache/hadoop/hbase/client/Delete;)V
     263: aload_0
     264: getfield      #9                  // Field table:Lorg/apache/hadoop/hbase/client/Table;
     267: new           #48                 // class org/apache/hadoop/hbase/client/Get
     270: dup
     271: getstatic     #42                 // Field ROW:[B
     274: invokespecial #49                 // Method org/apache/hadoop/hbase/client/Get."<init>":([B)V
     277: invokeinterface #50,  2           // InterfaceMethod org/apache/hadoop/hbase/client/Table.get:(Lorg/apache/hadoop/hbase/client/Get;)Lorg/apache/hadoop/hbase/client/Result;
     282: invokevirtual #74                 // Method org/apache/hadoop/hbase/client/Result.rawCells:()[Lorg/apache/hadoop/hbase/Cell;
     285: invokestatic  #75                 // Method java/util/Arrays.asList:([Ljava/lang/Object;)Ljava/util/List;
     288: invokevirtual #76                 // Method java/lang/Object.toString:()Ljava/lang/String;
     291: aload_0
     292: getfield      #9                  // Field table:Lorg/apache/hadoop/hbase/client/Table;
     295: new           #48                 // class org/apache/hadoop/hbase/client/Get
     298: dup
     299: getstatic     #42                 // Field ROW:[B
     302: invokespecial #49                 // Method org/apache/hadoop/hbase/client/Get."<init>":([B)V
     305: invokeinterface #50,  2           // InterfaceMethod org/apache/hadoop/hbase/client/Table.get:(Lorg/apache/hadoop/hbase/client/Get;)Lorg/apache/hadoop/hbase/client/Result;
     310: invokevirtual #77                 // Method org/apache/hadoop/hbase/client/Result.isEmpty:()Z
     313: invokestatic  #78                 // Method org/junit/Assert.assertTrue:(Ljava/lang/String;Z)V
     316: invokestatic  #52                 // Method assertObserverHasExecuted:()V
     319: aload_0
     320: getfield      #9                  // Field table:Lorg/apache/hadoop/hbase/client/Table;
     323: getstatic     #42                 // Field ROW:[B
     326: getstatic     #29                 // Field FAMILY:[B
     329: getstatic     #44                 // Field QUALIFIER:[B
     332: aconst_null
     333: aload_1
     334: invokeinterface #79,  6           // InterfaceMethod org/apache/hadoop/hbase/client/Table.checkAndPut:([B[B[B[BLorg/apache/hadoop/hbase/client/Put;)Z
     339: invokestatic  #80                 // Method org/junit/Assert.assertTrue:(Z)V
     342: invokestatic  #52                 // Method assertObserverHasExecuted:()V
     345: aload_0
     346: getfield      #9                  // Field table:Lorg/apache/hadoop/hbase/client/Table;
     349: getstatic     #42                 // Field ROW:[B
     352: getstatic     #29                 // Field FAMILY:[B
     355: getstatic     #44                 // Field QUALIFIER:[B
     358: getstatic     #45                 // Field VALUE:[B
     361: aload         5
     363: invokeinterface #81,  6           // InterfaceMethod org/apache/hadoop/hbase/client/Table.checkAndDelete:([B[B[B[BLorg/apache/hadoop/hbase/client/Delete;)Z
     368: invokestatic  #80                 // Method org/junit/Assert.assertTrue:(Z)V
     371: invokestatic  #52                 // Method assertObserverHasExecuted:()V
     374: aload_0
     375: getfield      #9                  // Field table:Lorg/apache/hadoop/hbase/client/Table;
     378: new           #48                 // class org/apache/hadoop/hbase/client/Get
     381: dup
     382: getstatic     #42                 // Field ROW:[B
     385: invokespecial #49                 // Method org/apache/hadoop/hbase/client/Get."<init>":([B)V
     388: invokeinterface #50,  2           // InterfaceMethod org/apache/hadoop/hbase/client/Table.get:(Lorg/apache/hadoop/hbase/client/Get;)Lorg/apache/hadoop/hbase/client/Result;
     393: invokevirtual #77                 // Method org/apache/hadoop/hbase/client/Result.isEmpty:()Z
     396: invokestatic  #80                 // Method org/junit/Assert.assertTrue:(Z)V
     399: return

  public void testMultiPut() throws java.lang.Exception;
    Code:
       0: iconst_0
       1: bipush        10
       3: invokestatic  #82                 // InterfaceMethod java/util/stream/IntStream.range:(II)Ljava/util/stream/IntStream;
       6: invokedynamic #83,  0             // InvokeDynamic #0:apply:()Ljava/util/function/IntFunction;
      11: invokeinterface #84,  2           // InterfaceMethod java/util/stream/IntStream.mapToObj:(Ljava/util/function/IntFunction;)Ljava/util/stream/Stream;
      16: invokestatic  #85                 // Method java/util/stream/Collectors.toList:()Ljava/util/stream/Collector;
      19: invokeinterface #86,  2           // InterfaceMethod java/util/stream/Stream.collect:(Ljava/util/stream/Collector;)Ljava/lang/Object;
      24: checkcast     #87                 // class java/util/List
      27: astore_1
      28: aload_0
      29: getfield      #9                  // Field table:Lorg/apache/hadoop/hbase/client/Table;
      32: aload_1
      33: invokeinterface #88,  2           // InterfaceMethod org/apache/hadoop/hbase/client/Table.put:(Ljava/util/List;)V
      38: aload_0
      39: getfield      #9                  // Field table:Lorg/apache/hadoop/hbase/client/Table;
      42: new           #48                 // class org/apache/hadoop/hbase/client/Get
      45: dup
      46: getstatic     #42                 // Field ROW:[B
      49: invokespecial #49                 // Method org/apache/hadoop/hbase/client/Get."<init>":([B)V
      52: invokeinterface #50,  2           // InterfaceMethod org/apache/hadoop/hbase/client/Table.get:(Lorg/apache/hadoop/hbase/client/Get;)Lorg/apache/hadoop/hbase/client/Result;
      57: getstatic     #45                 // Field VALUE:[B
      60: invokestatic  #89                 // Method assertResult:(Lorg/apache/hadoop/hbase/client/Result;[B)V
      63: invokestatic  #52                 // Method assertObserverHasExecuted:()V
      66: iconst_0
      67: bipush        10
      69: invokestatic  #82                 // InterfaceMethod java/util/stream/IntStream.range:(II)Ljava/util/stream/IntStream;
      72: invokedynamic #90,  0             // InvokeDynamic #1:apply:()Ljava/util/function/IntFunction;
      77: invokeinterface #84,  2           // InterfaceMethod java/util/stream/IntStream.mapToObj:(Ljava/util/function/IntFunction;)Ljava/util/stream/Stream;
      82: invokestatic  #85                 // Method java/util/stream/Collectors.toList:()Ljava/util/stream/Collector;
      85: invokeinterface #86,  2           // InterfaceMethod java/util/stream/Stream.collect:(Ljava/util/stream/Collector;)Ljava/lang/Object;
      90: checkcast     #87                 // class java/util/List
      93: astore_2
      94: aload_0
      95: getfield      #9                  // Field table:Lorg/apache/hadoop/hbase/client/Table;
      98: aload_2
      99: invokeinterface #91,  2           // InterfaceMethod org/apache/hadoop/hbase/client/Table.delete:(Ljava/util/List;)V
     104: aload_0
     105: getfield      #9                  // Field table:Lorg/apache/hadoop/hbase/client/Table;
     108: new           #48                 // class org/apache/hadoop/hbase/client/Get
     111: dup
     112: getstatic     #42                 // Field ROW:[B
     115: invokespecial #49                 // Method org/apache/hadoop/hbase/client/Get."<init>":([B)V
     118: invokeinterface #50,  2           // InterfaceMethod org/apache/hadoop/hbase/client/Table.get:(Lorg/apache/hadoop/hbase/client/Get;)Lorg/apache/hadoop/hbase/client/Result;
     123: invokevirtual #77                 // Method org/apache/hadoop/hbase/client/Result.isEmpty:()Z
     126: invokestatic  #80                 // Method org/junit/Assert.assertTrue:(Z)V
     129: invokestatic  #52                 // Method assertObserverHasExecuted:()V
     132: return

  static org.apache.hadoop.hbase.Cell access$000(org.apache.hadoop.hbase.client.Put);
    Code:
       0: aload_0
       1: invokestatic  #4                  // Method createCustomCell:(Lorg/apache/hadoop/hbase/client/Put;)Lorg/apache/hadoop/hbase/Cell;
       4: areturn

  static org.apache.hadoop.hbase.Cell access$100(org.apache.hadoop.hbase.client.Delete);
    Code:
       0: aload_0
       1: invokestatic  #3                  // Method createCustomCell:(Lorg/apache/hadoop/hbase/client/Delete;)Lorg/apache/hadoop/hbase/Cell;
       4: areturn

  static org.apache.hadoop.hbase.Cell access$200(org.apache.hadoop.hbase.client.Append);
    Code:
       0: aload_0
       1: invokestatic  #2                  // Method createCustomCell:(Lorg/apache/hadoop/hbase/client/Append;)Lorg/apache/hadoop/hbase/Cell;
       4: areturn

  static org.apache.hadoop.hbase.Cell access$300(org.apache.hadoop.hbase.client.Increment);
    Code:
       0: aload_0
       1: invokestatic  #1                  // Method createCustomCell:(Lorg/apache/hadoop/hbase/client/Increment;)Lorg/apache/hadoop/hbase/Cell;
       4: areturn

  static {};
    Code:
       0: ldc           #113                // class org/apache/hadoop/hbase/coprocessor/TestPassCustomCellViaRegionObserver
       2: invokestatic  #114                // Method org/apache/hadoop/hbase/HBaseClassTestRule.forClass:(Ljava/lang/Class;)Lorg/apache/hadoop/hbase/HBaseClassTestRule;
       5: putstatic     #115                // Field CLASS_RULE:Lorg/apache/hadoop/hbase/HBaseClassTestRule;
       8: new           #116                // class org/apache/hadoop/hbase/HBaseTestingUtility
      11: dup
      12: invokespecial #117                // Method org/apache/hadoop/hbase/HBaseTestingUtility."<init>":()V
      15: putstatic     #10                 // Field UTIL:Lorg/apache/hadoop/hbase/HBaseTestingUtility;
      18: ldc           #118                // String ROW
      20: invokestatic  #119                // Method org/apache/hadoop/hbase/util/Bytes.toBytes:(Ljava/lang/String;)[B
      23: putstatic     #42                 // Field ROW:[B
      26: ldc           #120                // String FAMILY
      28: invokestatic  #119                // Method org/apache/hadoop/hbase/util/Bytes.toBytes:(Ljava/lang/String;)[B
      31: putstatic     #29                 // Field FAMILY:[B
      34: ldc           #121                // String QUALIFIER
      36: invokestatic  #119                // Method org/apache/hadoop/hbase/util/Bytes.toBytes:(Ljava/lang/String;)[B
      39: putstatic     #44                 // Field QUALIFIER:[B
      42: ldc2_w        #55                 // long 10l
      45: invokestatic  #61                 // Method org/apache/hadoop/hbase/util/Bytes.toBytes:(J)[B
      48: putstatic     #45                 // Field VALUE:[B
      51: ldc           #122                // String MB
      53: invokestatic  #119                // Method org/apache/hadoop/hbase/util/Bytes.toBytes:(Ljava/lang/String;)[B
      56: putstatic     #64                 // Field APPEND_VALUE:[B
      59: ldc           #123                // String QUALIFIER_FROM_CP
      61: invokestatic  #119                // Method org/apache/hadoop/hbase/util/Bytes.toBytes:(Ljava/lang/String;)[B
      64: putstatic     #99                 // Field QUALIFIER_FROM_CP:[B
      67: return
}
