Compiled from "TestAsyncTableRpcPriority.java"
class org.apache.hadoop.hbase.client.TestAsyncTableRpcPriority$3 implements org.mockito.stubbing.Answer<java.lang.Void> {
  final org.apache.hadoop.hbase.client.TestAsyncTableRpcPriority this$0;

  org.apache.hadoop.hbase.client.TestAsyncTableRpcPriority$3(org.apache.hadoop.hbase.client.TestAsyncTableRpcPriority);
    Code:
       0: aload_0
       1: aload_1
       2: putfield      #1                  // Field this$0:Lorg/apache/hadoop/hbase/client/TestAsyncTableRpcPriority;
       5: aload_0
       6: invokespecial #2                  // Method java/lang/Object."<init>":()V
       9: return

  public java.lang.Void answer(org.mockito.invocation.InvocationOnMock) throws java.lang.Throwable;
    Code:
       0: aload_1
       1: iconst_1
       2: invokeinterface #3,  2            // InterfaceMethod org/mockito/invocation/InvocationOnMock.getArgument:(I)Ljava/lang/Object;
       7: checkcast     #4                  // class org/apache/hadoop/hbase/shaded/protobuf/generated/ClientProtos$MutateRequest
      10: invokevirtual #5                  // Method org/apache/hadoop/hbase/shaded/protobuf/generated/ClientProtos$MutateRequest.getMutation:()Lorg/apache/hadoop/hbase/shaded/protobuf/generated/ClientProtos$MutationProto;
      13: astore_2
      14: getstatic     #6                  // Field org/apache/hadoop/hbase/client/TestAsyncTableRpcPriority$7.$SwitchMap$org$apache$hadoop$hbase$shaded$protobuf$generated$ClientProtos$MutationProto$MutationType:[I
      17: aload_2
      18: invokevirtual #7                  // Method org/apache/hadoop/hbase/shaded/protobuf/generated/ClientProtos$MutationProto.getMutateType:()Lorg/apache/hadoop/hbase/shaded/protobuf/generated/ClientProtos$MutationProto$MutationType;
      21: invokevirtual #8                  // Method org/apache/hadoop/hbase/shaded/protobuf/generated/ClientProtos$MutationProto$MutationType.ordinal:()I
      24: iaload
      25: lookupswitch  { // 1
                     1: 44
               default: 162
          }
      44: aload_2
      45: iconst_0
      46: invokevirtual #9                  // Method org/apache/hadoop/hbase/shaded/protobuf/generated/ClientProtos$MutationProto.getColumnValue:(I)Lorg/apache/hadoop/hbase/shaded/protobuf/generated/ClientProtos$MutationProto$ColumnValue;
      49: astore        4
      51: aload         4
      53: iconst_0
      54: invokevirtual #10                 // Method org/apache/hadoop/hbase/shaded/protobuf/generated/ClientProtos$MutationProto$ColumnValue.getQualifierValue:(I)Lorg/apache/hadoop/hbase/shaded/protobuf/generated/ClientProtos$MutationProto$ColumnValue$QualifierValue;
      57: astore        5
      59: getstatic     #11                 // Field org/apache/hadoop/hbase/CellBuilderType.SHALLOW_COPY:Lorg/apache/hadoop/hbase/CellBuilderType;
      62: invokestatic  #12                 // Method org/apache/hadoop/hbase/CellBuilderFactory.create:(Lorg/apache/hadoop/hbase/CellBuilderType;)Lorg/apache/hadoop/hbase/CellBuilder;
      65: getstatic     #13                 // Field org/apache/hadoop/hbase/Cell$Type.Put:Lorg/apache/hadoop/hbase/Cell$Type;
      68: invokeinterface #14,  2           // InterfaceMethod org/apache/hadoop/hbase/CellBuilder.setType:(Lorg/apache/hadoop/hbase/Cell$Type;)Lorg/apache/hadoop/hbase/CellBuilder;
      73: aload_2
      74: invokevirtual #15                 // Method org/apache/hadoop/hbase/shaded/protobuf/generated/ClientProtos$MutationProto.getRow:()Lorg/apache/hbase/thirdparty/com/google/protobuf/ByteString;
      77: invokevirtual #16                 // Method org/apache/hbase/thirdparty/com/google/protobuf/ByteString.toByteArray:()[B
      80: invokeinterface #17,  2           // InterfaceMethod org/apache/hadoop/hbase/CellBuilder.setRow:([B)Lorg/apache/hadoop/hbase/CellBuilder;
      85: aload         4
      87: invokevirtual #18                 // Method org/apache/hadoop/hbase/shaded/protobuf/generated/ClientProtos$MutationProto$ColumnValue.getFamily:()Lorg/apache/hbase/thirdparty/com/google/protobuf/ByteString;
      90: invokevirtual #16                 // Method org/apache/hbase/thirdparty/com/google/protobuf/ByteString.toByteArray:()[B
      93: invokeinterface #19,  2           // InterfaceMethod org/apache/hadoop/hbase/CellBuilder.setFamily:([B)Lorg/apache/hadoop/hbase/CellBuilder;
      98: aload         5
     100: invokevirtual #20                 // Method org/apache/hadoop/hbase/shaded/protobuf/generated/ClientProtos$MutationProto$ColumnValue$QualifierValue.getQualifier:()Lorg/apache/hbase/thirdparty/com/google/protobuf/ByteString;
     103: invokevirtual #16                 // Method org/apache/hbase/thirdparty/com/google/protobuf/ByteString.toByteArray:()[B
     106: invokeinterface #21,  2           // InterfaceMethod org/apache/hadoop/hbase/CellBuilder.setQualifier:([B)Lorg/apache/hadoop/hbase/CellBuilder;
     111: aload         5
     113: invokevirtual #22                 // Method org/apache/hadoop/hbase/shaded/protobuf/generated/ClientProtos$MutationProto$ColumnValue$QualifierValue.getValue:()Lorg/apache/hbase/thirdparty/com/google/protobuf/ByteString;
     116: invokevirtual #16                 // Method org/apache/hbase/thirdparty/com/google/protobuf/ByteString.toByteArray:()[B
     119: invokeinterface #23,  2           // InterfaceMethod org/apache/hadoop/hbase/CellBuilder.setValue:([B)Lorg/apache/hadoop/hbase/CellBuilder;
     124: invokeinterface #24,  1           // InterfaceMethod org/apache/hadoop/hbase/CellBuilder.build:()Lorg/apache/hadoop/hbase/Cell;
     129: astore        6
     131: invokestatic  #25                 // Method org/apache/hadoop/hbase/shaded/protobuf/generated/ClientProtos$MutateResponse.newBuilder:()Lorg/apache/hadoop/hbase/shaded/protobuf/generated/ClientProtos$MutateResponse$Builder;
     134: iconst_1
     135: anewarray     #26                 // class org/apache/hadoop/hbase/Cell
     138: dup
     139: iconst_0
     140: aload         6
     142: aastore
     143: invokestatic  #27                 // Method java/util/Arrays.asList:([Ljava/lang/Object;)Ljava/util/List;
     146: invokestatic  #28                 // Method org/apache/hadoop/hbase/client/Result.create:(Ljava/util/List;)Lorg/apache/hadoop/hbase/client/Result;
     149: invokestatic  #29                 // Method org/apache/hadoop/hbase/shaded/protobuf/ProtobufUtil.toResult:(Lorg/apache/hadoop/hbase/client/Result;)Lorg/apache/hadoop/hbase/shaded/protobuf/generated/ClientProtos$Result;
     152: invokevirtual #30                 // Method org/apache/hadoop/hbase/shaded/protobuf/generated/ClientProtos$MutateResponse$Builder.setResult:(Lorg/apache/hadoop/hbase/shaded/protobuf/generated/ClientProtos$Result;)Lorg/apache/hadoop/hbase/shaded/protobuf/generated/ClientProtos$MutateResponse$Builder;
     155: invokevirtual #31                 // Method org/apache/hadoop/hbase/shaded/protobuf/generated/ClientProtos$MutateResponse$Builder.build:()Lorg/apache/hadoop/hbase/shaded/protobuf/generated/ClientProtos$MutateResponse;
     158: astore_3
     159: goto          166
     162: invokestatic  #32                 // Method org/apache/hadoop/hbase/shaded/protobuf/generated/ClientProtos$MutateResponse.getDefaultInstance:()Lorg/apache/hadoop/hbase/shaded/protobuf/generated/ClientProtos$MutateResponse;
     165: astore_3
     166: aload_1
     167: iconst_2
     168: invokeinterface #3,  2            // InterfaceMethod org/mockito/invocation/InvocationOnMock.getArgument:(I)Ljava/lang/Object;
     173: checkcast     #33                 // class org/apache/hbase/thirdparty/com/google/protobuf/RpcCallback
     176: astore        4
     178: aload         4
     180: aload_3
     181: invokeinterface #34,  2           // InterfaceMethod org/apache/hbase/thirdparty/com/google/protobuf/RpcCallback.run:(Ljava/lang/Object;)V
     186: aconst_null
     187: areturn

  public java.lang.Object answer(org.mockito.invocation.InvocationOnMock) throws java.lang.Throwable;
    Code:
       0: aload_0
       1: aload_1
       2: invokevirtual #35                 // Method answer:(Lorg/mockito/invocation/InvocationOnMock;)Ljava/lang/Void;
       5: areturn
}
