Compiled from "TestMetricsRegionSourceImpl.java"
public class org.apache.hadoop.hbase.regionserver.TestMetricsRegionSourceImpl {
  public static final org.apache.hadoop.hbase.HBaseClassTestRule CLASS_RULE;

  public org.apache.hadoop.hbase.regionserver.TestMetricsRegionSourceImpl();
    Code:
       0: aload_0
       1: invokespecial #1                  // Method java/lang/Object."<init>":()V
       4: return

  public void testCompareToHashCodeEquals();
    Code:
       0: ldc           #2                  // class org/apache/hadoop/hbase/regionserver/MetricsRegionServerSourceFactory
       2: invokestatic  #3                  // Method org/apache/hadoop/hbase/CompatibilitySingletonFactory.getInstance:(Ljava/lang/Class;)Ljava/lang/Object;
       5: checkcast     #2                  // class org/apache/hadoop/hbase/regionserver/MetricsRegionServerSourceFactory
       8: astore_1
       9: aload_1
      10: new           #4                  // class org/apache/hadoop/hbase/regionserver/TestMetricsRegionSourceImpl$RegionWrapperStub
      13: dup
      14: ldc           #5                  // String TEST
      16: invokespecial #6                  // Method org/apache/hadoop/hbase/regionserver/TestMetricsRegionSourceImpl$RegionWrapperStub."<init>":(Ljava/lang/String;)V
      19: invokeinterface #7,  2            // InterfaceMethod org/apache/hadoop/hbase/regionserver/MetricsRegionServerSourceFactory.createRegion:(Lorg/apache/hadoop/hbase/regionserver/MetricsRegionWrapper;)Lorg/apache/hadoop/hbase/regionserver/MetricsRegionSource;
      24: astore_2
      25: aload_1
      26: new           #4                  // class org/apache/hadoop/hbase/regionserver/TestMetricsRegionSourceImpl$RegionWrapperStub
      29: dup
      30: ldc           #5                  // String TEST
      32: invokespecial #6                  // Method org/apache/hadoop/hbase/regionserver/TestMetricsRegionSourceImpl$RegionWrapperStub."<init>":(Ljava/lang/String;)V
      35: invokeinterface #7,  2            // InterfaceMethod org/apache/hadoop/hbase/regionserver/MetricsRegionServerSourceFactory.createRegion:(Lorg/apache/hadoop/hbase/regionserver/MetricsRegionWrapper;)Lorg/apache/hadoop/hbase/regionserver/MetricsRegionSource;
      40: astore_3
      41: aload_1
      42: new           #4                  // class org/apache/hadoop/hbase/regionserver/TestMetricsRegionSourceImpl$RegionWrapperStub
      45: dup
      46: ldc           #8                  // String TWO
      48: invokespecial #6                  // Method org/apache/hadoop/hbase/regionserver/TestMetricsRegionSourceImpl$RegionWrapperStub."<init>":(Ljava/lang/String;)V
      51: invokeinterface #7,  2            // InterfaceMethod org/apache/hadoop/hbase/regionserver/MetricsRegionServerSourceFactory.createRegion:(Lorg/apache/hadoop/hbase/regionserver/MetricsRegionWrapper;)Lorg/apache/hadoop/hbase/regionserver/MetricsRegionSource;
      56: astore        4
      58: lconst_0
      59: aload_2
      60: aload_3
      61: invokeinterface #9,  2            // InterfaceMethod org/apache/hadoop/hbase/regionserver/MetricsRegionSource.compareTo:(Ljava/lang/Object;)I
      66: i2l
      67: invokestatic  #10                 // Method org/junit/Assert.assertEquals:(JJ)V
      70: aload_2
      71: invokevirtual #11                 // Method java/lang/Object.hashCode:()I
      74: i2l
      75: aload_3
      76: invokevirtual #11                 // Method java/lang/Object.hashCode:()I
      79: i2l
      80: invokestatic  #10                 // Method org/junit/Assert.assertEquals:(JJ)V
      83: aload_2
      84: aload         4
      86: invokestatic  #12                 // Method org/junit/Assert.assertNotEquals:(Ljava/lang/Object;Ljava/lang/Object;)V
      89: lconst_0
      90: aload_2
      91: aload         4
      93: invokeinterface #9,  2            // InterfaceMethod org/apache/hadoop/hbase/regionserver/MetricsRegionSource.compareTo:(Ljava/lang/Object;)I
      98: i2l
      99: invokestatic  #13                 // Method org/junit/Assert.assertNotEquals:(JJ)V
     102: lconst_0
     103: aload         4
     105: aload_2
     106: invokeinterface #9,  2            // InterfaceMethod org/apache/hadoop/hbase/regionserver/MetricsRegionSource.compareTo:(Ljava/lang/Object;)I
     111: i2l
     112: invokestatic  #13                 // Method org/junit/Assert.assertNotEquals:(JJ)V
     115: aload_2
     116: aload         4
     118: invokeinterface #9,  2            // InterfaceMethod org/apache/hadoop/hbase/regionserver/MetricsRegionSource.compareTo:(Ljava/lang/Object;)I
     123: i2l
     124: aload         4
     126: aload_2
     127: invokeinterface #9,  2            // InterfaceMethod org/apache/hadoop/hbase/regionserver/MetricsRegionSource.compareTo:(Ljava/lang/Object;)I
     132: i2l
     133: invokestatic  #13                 // Method org/junit/Assert.assertNotEquals:(JJ)V
     136: lconst_0
     137: aload         4
     139: aload         4
     141: invokeinterface #9,  2            // InterfaceMethod org/apache/hadoop/hbase/regionserver/MetricsRegionSource.compareTo:(Ljava/lang/Object;)I
     146: i2l
     147: invokestatic  #10                 // Method org/junit/Assert.assertEquals:(JJ)V
     150: return

  public void testNoGetRegionServerMetricsSourceImpl();
    Code:
       0: ldc           #14                 // class org/apache/hadoop/hbase/regionserver/MetricsRegionSource
       2: invokestatic  #3                  // Method org/apache/hadoop/hbase/CompatibilitySingletonFactory.getInstance:(Ljava/lang/Class;)Ljava/lang/Object;
       5: pop
       6: return

  static {};
    Code:
       0: ldc           #15                 // class org/apache/hadoop/hbase/regionserver/TestMetricsRegionSourceImpl
       2: invokestatic  #16                 // Method org/apache/hadoop/hbase/HBaseClassTestRule.forClass:(Ljava/lang/Class;)Lorg/apache/hadoop/hbase/HBaseClassTestRule;
       5: putstatic     #17                 // Field CLASS_RULE:Lorg/apache/hadoop/hbase/HBaseClassTestRule;
       8: return
}
