Compiled from "TestMasterOperationsForRegionReplicas.java"
public class org.apache.hadoop.hbase.master.TestMasterOperationsForRegionReplicas {
  public static final org.apache.hadoop.hbase.HBaseClassTestRule CLASS_RULE;

  public org.junit.rules.TestName name;

  static final boolean $assertionsDisabled;

  public org.apache.hadoop.hbase.master.TestMasterOperationsForRegionReplicas();
    Code:
       0: aload_0
       1: invokespecial #1                  // Method java/lang/Object."<init>":()V
       4: aload_0
       5: new           #2                  // class org/junit/rules/TestName
       8: dup
       9: invokespecial #3                  // Method org/junit/rules/TestName."<init>":()V
      12: putfield      #4                  // Field name:Lorg/junit/rules/TestName;
      15: return

  public static void setupBeforeClass() throws java.lang.Exception;
    Code:
       0: getstatic     #5                  // Field TEST_UTIL:Lorg/apache/hadoop/hbase/HBaseTestingUtility;
       3: invokevirtual #6                  // Method org/apache/hadoop/hbase/HBaseTestingUtility.getConfiguration:()Lorg/apache/hadoop/conf/Configuration;
       6: putstatic     #7                  // Field conf:Lorg/apache/hadoop/conf/Configuration;
       9: getstatic     #7                  // Field conf:Lorg/apache/hadoop/conf/Configuration;
      12: ldc           #8                  // String hbase.tests.use.shortcircuit.reads
      14: iconst_0
      15: invokevirtual #9                  // Method org/apache/hadoop/conf/Configuration.setBoolean:(Ljava/lang/String;Z)V
      18: getstatic     #5                  // Field TEST_UTIL:Lorg/apache/hadoop/hbase/HBaseTestingUtility;
      21: getstatic     #10                 // Field numSlaves:I
      24: invokevirtual #11                 // Method org/apache/hadoop/hbase/HBaseTestingUtility.startMiniCluster:(I)Lorg/apache/hadoop/hbase/MiniHBaseCluster;
      27: pop
      28: getstatic     #5                  // Field TEST_UTIL:Lorg/apache/hadoop/hbase/HBaseTestingUtility;
      31: invokevirtual #6                  // Method org/apache/hadoop/hbase/HBaseTestingUtility.getConfiguration:()Lorg/apache/hadoop/conf/Configuration;
      34: invokestatic  #12                 // Method org/apache/hadoop/hbase/client/ConnectionFactory.createConnection:(Lorg/apache/hadoop/conf/Configuration;)Lorg/apache/hadoop/hbase/client/Connection;
      37: putstatic     #13                 // Field CONNECTION:Lorg/apache/hadoop/hbase/client/Connection;
      40: getstatic     #13                 // Field CONNECTION:Lorg/apache/hadoop/hbase/client/Connection;
      43: invokeinterface #14,  1           // InterfaceMethod org/apache/hadoop/hbase/client/Connection.getAdmin:()Lorg/apache/hadoop/hbase/client/Admin;
      48: putstatic     #15                 // Field ADMIN:Lorg/apache/hadoop/hbase/client/Admin;
      51: getstatic     #15                 // Field ADMIN:Lorg/apache/hadoop/hbase/client/Admin;
      54: getstatic     #16                 // Field org/apache/hadoop/hbase/ClusterMetrics$Option.LIVE_SERVERS:Lorg/apache/hadoop/hbase/ClusterMetrics$Option;
      57: invokestatic  #17                 // Method java/util/EnumSet.of:(Ljava/lang/Enum;)Ljava/util/EnumSet;
      60: invokeinterface #18,  2           // InterfaceMethod org/apache/hadoop/hbase/client/Admin.getClusterMetrics:(Ljava/util/EnumSet;)Lorg/apache/hadoop/hbase/ClusterMetrics;
      65: invokeinterface #19,  1           // InterfaceMethod org/apache/hadoop/hbase/ClusterMetrics.getLiveServerMetrics:()Ljava/util/Map;
      70: invokeinterface #20,  1           // InterfaceMethod java/util/Map.size:()I
      75: getstatic     #10                 // Field numSlaves:I
      78: if_icmpge     90
      81: ldc2_w        #21                 // long 100l
      84: invokestatic  #23                 // Method java/lang/Thread.sleep:(J)V
      87: goto          51
      90: return

  public static void tearDownAfterClass() throws java.lang.Exception;
    Code:
       0: getstatic     #15                 // Field ADMIN:Lorg/apache/hadoop/hbase/client/Admin;
       3: ifnull        14
       6: getstatic     #15                 // Field ADMIN:Lorg/apache/hadoop/hbase/client/Admin;
       9: invokeinterface #24,  1           // InterfaceMethod org/apache/hadoop/hbase/client/Admin.close:()V
      14: getstatic     #13                 // Field CONNECTION:Lorg/apache/hadoop/hbase/client/Connection;
      17: ifnull        39
      20: getstatic     #13                 // Field CONNECTION:Lorg/apache/hadoop/hbase/client/Connection;
      23: invokeinterface #25,  1           // InterfaceMethod org/apache/hadoop/hbase/client/Connection.isClosed:()Z
      28: ifne          39
      31: getstatic     #13                 // Field CONNECTION:Lorg/apache/hadoop/hbase/client/Connection;
      34: invokeinterface #26,  1           // InterfaceMethod org/apache/hadoop/hbase/client/Connection.close:()V
      39: getstatic     #5                  // Field TEST_UTIL:Lorg/apache/hadoop/hbase/HBaseTestingUtility;
      42: invokevirtual #27                 // Method org/apache/hadoop/hbase/HBaseTestingUtility.shutdownMiniCluster:()V
      45: return

  public void testCreateTableWithSingleReplica() throws java.lang.Exception;
    Code:
       0: iconst_3
       1: istore_1
       2: iconst_1
       3: istore_2
       4: aload_0
       5: getfield      #4                  // Field name:Lorg/junit/rules/TestName;
       8: invokevirtual #28                 // Method org/junit/rules/TestName.getMethodName:()Ljava/lang/String;
      11: invokestatic  #29                 // Method org/apache/hadoop/hbase/TableName.valueOf:(Ljava/lang/String;)Lorg/apache/hadoop/hbase/TableName;
      14: astore_3
      15: new           #30                 // class org/apache/hadoop/hbase/HTableDescriptor
      18: dup
      19: aload_3
      20: invokespecial #31                 // Method org/apache/hadoop/hbase/HTableDescriptor."<init>":(Lorg/apache/hadoop/hbase/TableName;)V
      23: astore        4
      25: aload         4
      27: iconst_1
      28: invokevirtual #32                 // Method org/apache/hadoop/hbase/HTableDescriptor.setRegionReplication:(I)Lorg/apache/hadoop/hbase/HTableDescriptor;
      31: pop
      32: aload         4
      34: new           #33                 // class org/apache/hadoop/hbase/HColumnDescriptor
      37: dup
      38: ldc           #34                 // String family
      40: invokespecial #35                 // Method org/apache/hadoop/hbase/HColumnDescriptor."<init>":(Ljava/lang/String;)V
      43: invokevirtual #36                 // Method org/apache/hadoop/hbase/HTableDescriptor.addFamily:(Lorg/apache/hadoop/hbase/HColumnDescriptor;)Lorg/apache/hadoop/hbase/HTableDescriptor;
      46: pop
      47: getstatic     #15                 // Field ADMIN:Lorg/apache/hadoop/hbase/client/Admin;
      50: aload         4
      52: ldc           #37                 // String A
      54: invokestatic  #38                 // Method org/apache/hadoop/hbase/util/Bytes.toBytes:(Ljava/lang/String;)[B
      57: ldc           #39                 // String Z
      59: invokestatic  #38                 // Method org/apache/hadoop/hbase/util/Bytes.toBytes:(Ljava/lang/String;)[B
      62: iconst_3
      63: invokeinterface #40,  5           // InterfaceMethod org/apache/hadoop/hbase/client/Admin.createTable:(Lorg/apache/hadoop/hbase/client/TableDescriptor;[B[BI)V
      68: aload_0
      69: aload_3
      70: iconst_3
      71: getstatic     #15                 // Field ADMIN:Lorg/apache/hadoop/hbase/client/Admin;
      74: invokeinterface #41,  1           // InterfaceMethod org/apache/hadoop/hbase/client/Admin.getConnection:()Lorg/apache/hadoop/hbase/client/Connection;
      79: invokespecial #42                 // Method validateNumberOfRowsInMeta:(Lorg/apache/hadoop/hbase/TableName;ILorg/apache/hadoop/hbase/client/Connection;)V
      82: getstatic     #15                 // Field ADMIN:Lorg/apache/hadoop/hbase/client/Admin;
      85: invokeinterface #41,  1           // InterfaceMethod org/apache/hadoop/hbase/client/Admin.getConnection:()Lorg/apache/hadoop/hbase/client/Connection;
      90: aload_3
      91: invokestatic  #43                 // Method org/apache/hadoop/hbase/MetaTableAccessor.getTableRegions:(Lorg/apache/hadoop/hbase/client/Connection;Lorg/apache/hadoop/hbase/TableName;)Ljava/util/List;
      94: astore        5
      96: getstatic     #44                 // Field $assertionsDisabled:Z
      99: ifne          121
     102: aload         5
     104: invokeinterface #45,  1           // InterfaceMethod java/util/List.size:()I
     109: iconst_3
     110: if_icmpeq     121
     113: new           #46                 // class java/lang/AssertionError
     116: dup
     117: invokespecial #47                 // Method java/lang/AssertionError."<init>":()V
     120: athrow
     121: getstatic     #15                 // Field ADMIN:Lorg/apache/hadoop/hbase/client/Admin;
     124: aload_3
     125: invokeinterface #48,  2           // InterfaceMethod org/apache/hadoop/hbase/client/Admin.disableTable:(Lorg/apache/hadoop/hbase/TableName;)V
     130: getstatic     #15                 // Field ADMIN:Lorg/apache/hadoop/hbase/client/Admin;
     133: aload_3
     134: invokeinterface #49,  2           // InterfaceMethod org/apache/hadoop/hbase/client/Admin.deleteTable:(Lorg/apache/hadoop/hbase/TableName;)V
     139: goto          165
     142: astore        6
     144: getstatic     #15                 // Field ADMIN:Lorg/apache/hadoop/hbase/client/Admin;
     147: aload_3
     148: invokeinterface #48,  2           // InterfaceMethod org/apache/hadoop/hbase/client/Admin.disableTable:(Lorg/apache/hadoop/hbase/TableName;)V
     153: getstatic     #15                 // Field ADMIN:Lorg/apache/hadoop/hbase/client/Admin;
     156: aload_3
     157: invokeinterface #49,  2           // InterfaceMethod org/apache/hadoop/hbase/client/Admin.deleteTable:(Lorg/apache/hadoop/hbase/TableName;)V
     162: aload         6
     164: athrow
     165: return
    Exception table:
       from    to  target type
          15   121   142   any
         142   144   142   any

  public void testCreateTableWithMultipleReplicas() throws java.lang.Exception;
    Code:
       0: aload_0
       1: getfield      #4                  // Field name:Lorg/junit/rules/TestName;
       4: invokevirtual #28                 // Method org/junit/rules/TestName.getMethodName:()Ljava/lang/String;
       7: invokestatic  #29                 // Method org/apache/hadoop/hbase/TableName.valueOf:(Ljava/lang/String;)Lorg/apache/hadoop/hbase/TableName;
      10: astore_1
      11: iconst_3
      12: istore_2
      13: iconst_2
      14: istore_3
      15: new           #30                 // class org/apache/hadoop/hbase/HTableDescriptor
      18: dup
      19: aload_1
      20: invokespecial #31                 // Method org/apache/hadoop/hbase/HTableDescriptor."<init>":(Lorg/apache/hadoop/hbase/TableName;)V
      23: astore        4
      25: aload         4
      27: iconst_2
      28: invokevirtual #32                 // Method org/apache/hadoop/hbase/HTableDescriptor.setRegionReplication:(I)Lorg/apache/hadoop/hbase/HTableDescriptor;
      31: pop
      32: aload         4
      34: new           #33                 // class org/apache/hadoop/hbase/HColumnDescriptor
      37: dup
      38: ldc           #34                 // String family
      40: invokespecial #35                 // Method org/apache/hadoop/hbase/HColumnDescriptor."<init>":(Ljava/lang/String;)V
      43: invokevirtual #36                 // Method org/apache/hadoop/hbase/HTableDescriptor.addFamily:(Lorg/apache/hadoop/hbase/HColumnDescriptor;)Lorg/apache/hadoop/hbase/HTableDescriptor;
      46: pop
      47: getstatic     #15                 // Field ADMIN:Lorg/apache/hadoop/hbase/client/Admin;
      50: aload         4
      52: ldc           #37                 // String A
      54: invokestatic  #38                 // Method org/apache/hadoop/hbase/util/Bytes.toBytes:(Ljava/lang/String;)[B
      57: ldc           #39                 // String Z
      59: invokestatic  #38                 // Method org/apache/hadoop/hbase/util/Bytes.toBytes:(Ljava/lang/String;)[B
      62: iconst_3
      63: invokeinterface #40,  5           // InterfaceMethod org/apache/hadoop/hbase/client/Admin.createTable:(Lorg/apache/hadoop/hbase/client/TableDescriptor;[B[BI)V
      68: getstatic     #5                  // Field TEST_UTIL:Lorg/apache/hadoop/hbase/HBaseTestingUtility;
      71: aload_1
      72: invokevirtual #50                 // Method org/apache/hadoop/hbase/HBaseTestingUtility.waitTableEnabled:(Lorg/apache/hadoop/hbase/TableName;)V
      75: aload_0
      76: aload_1
      77: iconst_3
      78: getstatic     #15                 // Field ADMIN:Lorg/apache/hadoop/hbase/client/Admin;
      81: invokeinterface #41,  1           // InterfaceMethod org/apache/hadoop/hbase/client/Admin.getConnection:()Lorg/apache/hadoop/hbase/client/Connection;
      86: invokespecial #42                 // Method validateNumberOfRowsInMeta:(Lorg/apache/hadoop/hbase/TableName;ILorg/apache/hadoop/hbase/client/Connection;)V
      89: getstatic     #15                 // Field ADMIN:Lorg/apache/hadoop/hbase/client/Admin;
      92: invokeinterface #41,  1           // InterfaceMethod org/apache/hadoop/hbase/client/Admin.getConnection:()Lorg/apache/hadoop/hbase/client/Connection;
      97: aload_1
      98: invokestatic  #43                 // Method org/apache/hadoop/hbase/MetaTableAccessor.getTableRegions:(Lorg/apache/hadoop/hbase/client/Connection;Lorg/apache/hadoop/hbase/TableName;)Ljava/util/List;
     101: astore        5
     103: getstatic     #44                 // Field $assertionsDisabled:Z
     106: ifne          129
     109: aload         5
     111: invokeinterface #45,  1           // InterfaceMethod java/util/List.size:()I
     116: bipush        6
     118: if_icmpeq     129
     121: new           #46                 // class java/lang/AssertionError
     124: dup
     125: invokespecial #47                 // Method java/lang/AssertionError."<init>":()V
     128: athrow
     129: iconst_0
     130: istore        6
     132: iload         6
     134: iconst_3
     135: if_icmpge     219
     138: iconst_0
     139: istore        7
     141: iload         7
     143: iconst_2
     144: if_icmpge     213
     147: aload         5
     149: iload         6
     151: invokeinterface #51,  2           // InterfaceMethod java/util/List.get:(I)Ljava/lang/Object;
     156: checkcast     #52                 // class org/apache/hadoop/hbase/client/RegionInfo
     159: iload         7
     161: invokestatic  #53                 // Method org/apache/hadoop/hbase/client/RegionReplicaUtil.getRegionInfoForReplica:(Lorg/apache/hadoop/hbase/client/RegionInfo;I)Lorg/apache/hadoop/hbase/client/RegionInfo;
     164: astore        8
     166: getstatic     #5                  // Field TEST_UTIL:Lorg/apache/hadoop/hbase/HBaseTestingUtility;
     169: invokevirtual #54                 // Method org/apache/hadoop/hbase/HBaseTestingUtility.getHBaseCluster:()Lorg/apache/hadoop/hbase/MiniHBaseCluster;
     172: invokevirtual #55                 // Method org/apache/hadoop/hbase/MiniHBaseCluster.getMaster:()Lorg/apache/hadoop/hbase/master/HMaster;
     175: invokevirtual #56                 // Method org/apache/hadoop/hbase/master/HMaster.getAssignmentManager:()Lorg/apache/hadoop/hbase/master/assignment/AssignmentManager;
     178: invokevirtual #57                 // Method org/apache/hadoop/hbase/master/assignment/AssignmentManager.getRegionStates:()Lorg/apache/hadoop/hbase/master/assignment/RegionStates;
     181: aload         8
     183: invokevirtual #58                 // Method org/apache/hadoop/hbase/master/assignment/RegionStates.getRegionState:(Lorg/apache/hadoop/hbase/client/RegionInfo;)Lorg/apache/hadoop/hbase/master/RegionState;
     186: astore        9
     188: getstatic     #44                 // Field $assertionsDisabled:Z
     191: ifne          207
     194: aload         9
     196: ifnonnull     207
     199: new           #46                 // class java/lang/AssertionError
     202: dup
     203: invokespecial #47                 // Method java/lang/AssertionError."<init>":()V
     206: athrow
     207: iinc          7, 1
     210: goto          141
     213: iinc          6, 1
     216: goto          132
     219: getstatic     #15                 // Field ADMIN:Lorg/apache/hadoop/hbase/client/Admin;
     222: invokeinterface #41,  1           // InterfaceMethod org/apache/hadoop/hbase/client/Admin.getConnection:()Lorg/apache/hadoop/hbase/client/Connection;
     227: invokestatic  #59                 // Method org/apache/hadoop/hbase/MetaTableAccessor.fullScanRegions:(Lorg/apache/hadoop/hbase/client/Connection;)Ljava/util/List;
     230: astore        6
     232: iconst_0
     233: istore        7
     235: aload         6
     237: invokeinterface #60,  1           // InterfaceMethod java/util/List.iterator:()Ljava/util/Iterator;
     242: astore        8
     244: aload         8
     246: invokeinterface #61,  1           // InterfaceMethod java/util/Iterator.hasNext:()Z
     251: ifeq          362
     254: aload         8
     256: invokeinterface #62,  1           // InterfaceMethod java/util/Iterator.next:()Ljava/lang/Object;
     261: checkcast     #63                 // class org/apache/hadoop/hbase/client/Result
     264: astore        9
     266: aload         9
     268: invokestatic  #64                 // Method org/apache/hadoop/hbase/MetaTableAccessor.getRegionLocations:(Lorg/apache/hadoop/hbase/client/Result;)Lorg/apache/hadoop/hbase/RegionLocations;
     271: astore        10
     273: aload         10
     275: invokevirtual #65                 // Method org/apache/hadoop/hbase/RegionLocations.getRegionLocation:()Lorg/apache/hadoop/hbase/HRegionLocation;
     278: invokevirtual #66                 // Method org/apache/hadoop/hbase/HRegionLocation.getRegionInfo:()Lorg/apache/hadoop/hbase/HRegionInfo;
     281: astore        11
     283: aload         11
     285: invokeinterface #67,  1           // InterfaceMethod org/apache/hadoop/hbase/client/RegionInfo.getTable:()Lorg/apache/hadoop/hbase/TableName;
     290: aload_1
     291: invokevirtual #68                 // Method org/apache/hadoop/hbase/TableName.equals:(Ljava/lang/Object;)Z
     294: ifne          300
     297: goto          244
     300: iinc          7, 1
     303: aload         10
     305: invokevirtual #69                 // Method org/apache/hadoop/hbase/RegionLocations.getRegionLocations:()[Lorg/apache/hadoop/hbase/HRegionLocation;
     308: astore        12
     310: getstatic     #44                 // Field $assertionsDisabled:Z
     313: ifne          331
     316: aload         12
     318: arraylength
     319: iconst_2
     320: if_icmpeq     331
     323: new           #46                 // class java/lang/AssertionError
     326: dup
     327: invokespecial #47                 // Method java/lang/AssertionError."<init>":()V
     330: athrow
     331: getstatic     #44                 // Field $assertionsDisabled:Z
     334: ifne          359
     337: aload         12
     339: iconst_0
     340: aaload
     341: aload         12
     343: iconst_1
     344: aaload
     345: invokevirtual #70                 // Method org/apache/hadoop/hbase/HRegionLocation.equals:(Ljava/lang/Object;)Z
     348: ifeq          359
     351: new           #46                 // class java/lang/AssertionError
     354: dup
     355: invokespecial #47                 // Method java/lang/AssertionError."<init>":()V
     358: athrow
     359: goto          244
     362: getstatic     #44                 // Field $assertionsDisabled:Z
     365: ifne          382
     368: iload         7
     370: iconst_3
     371: if_icmpeq     382
     374: new           #46                 // class java/lang/AssertionError
     377: dup
     378: invokespecial #47                 // Method java/lang/AssertionError."<init>":()V
     381: athrow
     382: aload_0
     383: getstatic     #5                  // Field TEST_UTIL:Lorg/apache/hadoop/hbase/HBaseTestingUtility;
     386: aload_1
     387: iconst_3
     388: iconst_2
     389: getstatic     #15                 // Field ADMIN:Lorg/apache/hadoop/hbase/client/Admin;
     392: invokeinterface #41,  1           // InterfaceMethod org/apache/hadoop/hbase/client/Admin.getConnection:()Lorg/apache/hadoop/hbase/client/Connection;
     397: invokespecial #71                 // Method validateFromSnapshotFromMeta:(Lorg/apache/hadoop/hbase/HBaseTestingUtility;Lorg/apache/hadoop/hbase/TableName;IILorg/apache/hadoop/hbase/client/Connection;)V
     400: getstatic     #5                  // Field TEST_UTIL:Lorg/apache/hadoop/hbase/HBaseTestingUtility;
     403: invokevirtual #72                 // Method org/apache/hadoop/hbase/HBaseTestingUtility.getHBaseClusterInterface:()Lorg/apache/hadoop/hbase/HBaseCluster;
     406: invokevirtual #73                 // Method org/apache/hadoop/hbase/HBaseCluster.getClusterMetrics:()Lorg/apache/hadoop/hbase/ClusterMetrics;
     409: invokeinterface #74,  1           // InterfaceMethod org/apache/hadoop/hbase/ClusterMetrics.getMasterName:()Lorg/apache/hadoop/hbase/ServerName;
     414: astore        8
     416: getstatic     #5                  // Field TEST_UTIL:Lorg/apache/hadoop/hbase/HBaseTestingUtility;
     419: invokevirtual #72                 // Method org/apache/hadoop/hbase/HBaseTestingUtility.getHBaseClusterInterface:()Lorg/apache/hadoop/hbase/HBaseCluster;
     422: aload         8
     424: invokevirtual #75                 // Method org/apache/hadoop/hbase/HBaseCluster.stopMaster:(Lorg/apache/hadoop/hbase/ServerName;)V
     427: getstatic     #5                  // Field TEST_UTIL:Lorg/apache/hadoop/hbase/HBaseTestingUtility;
     430: invokevirtual #72                 // Method org/apache/hadoop/hbase/HBaseTestingUtility.getHBaseClusterInterface:()Lorg/apache/hadoop/hbase/HBaseCluster;
     433: aload         8
     435: ldc2_w        #76                 // long 30000l
     438: invokevirtual #78                 // Method org/apache/hadoop/hbase/HBaseCluster.waitForMasterToStop:(Lorg/apache/hadoop/hbase/ServerName;J)V
     441: getstatic     #5                  // Field TEST_UTIL:Lorg/apache/hadoop/hbase/HBaseTestingUtility;
     444: invokevirtual #72                 // Method org/apache/hadoop/hbase/HBaseTestingUtility.getHBaseClusterInterface:()Lorg/apache/hadoop/hbase/HBaseCluster;
     447: aload         8
     449: invokevirtual #79                 // Method org/apache/hadoop/hbase/ServerName.getHostname:()Ljava/lang/String;
     452: aload         8
     454: invokevirtual #80                 // Method org/apache/hadoop/hbase/ServerName.getPort:()I
     457: invokevirtual #81                 // Method org/apache/hadoop/hbase/HBaseCluster.startMaster:(Ljava/lang/String;I)V
     460: getstatic     #5                  // Field TEST_UTIL:Lorg/apache/hadoop/hbase/HBaseTestingUtility;
     463: invokevirtual #72                 // Method org/apache/hadoop/hbase/HBaseTestingUtility.getHBaseClusterInterface:()Lorg/apache/hadoop/hbase/HBaseCluster;
     466: invokevirtual #82                 // Method org/apache/hadoop/hbase/HBaseCluster.waitForActiveAndReadyMaster:()Z
     469: pop
     470: iconst_0
     471: istore        9
     473: iload         9
     475: iconst_3
     476: if_icmpge     560
     479: iconst_0
     480: istore        10
     482: iload         10
     484: iconst_2
     485: if_icmpge     554
     488: aload         5
     490: iload         9
     492: invokeinterface #51,  2           // InterfaceMethod java/util/List.get:(I)Ljava/lang/Object;
     497: checkcast     #52                 // class org/apache/hadoop/hbase/client/RegionInfo
     500: iload         10
     502: invokestatic  #53                 // Method org/apache/hadoop/hbase/client/RegionReplicaUtil.getRegionInfoForReplica:(Lorg/apache/hadoop/hbase/client/RegionInfo;I)Lorg/apache/hadoop/hbase/client/RegionInfo;
     505: astore        11
     507: getstatic     #5                  // Field TEST_UTIL:Lorg/apache/hadoop/hbase/HBaseTestingUtility;
     510: invokevirtual #54                 // Method org/apache/hadoop/hbase/HBaseTestingUtility.getHBaseCluster:()Lorg/apache/hadoop/hbase/MiniHBaseCluster;
     513: invokevirtual #55                 // Method org/apache/hadoop/hbase/MiniHBaseCluster.getMaster:()Lorg/apache/hadoop/hbase/master/HMaster;
     516: invokevirtual #56                 // Method org/apache/hadoop/hbase/master/HMaster.getAssignmentManager:()Lorg/apache/hadoop/hbase/master/assignment/AssignmentManager;
     519: invokevirtual #57                 // Method org/apache/hadoop/hbase/master/assignment/AssignmentManager.getRegionStates:()Lorg/apache/hadoop/hbase/master/assignment/RegionStates;
     522: aload         11
     524: invokevirtual #58                 // Method org/apache/hadoop/hbase/master/assignment/RegionStates.getRegionState:(Lorg/apache/hadoop/hbase/client/RegionInfo;)Lorg/apache/hadoop/hbase/master/RegionState;
     527: astore        12
     529: getstatic     #44                 // Field $assertionsDisabled:Z
     532: ifne          548
     535: aload         12
     537: ifnonnull     548
     540: new           #46                 // class java/lang/AssertionError
     543: dup
     544: invokespecial #47                 // Method java/lang/AssertionError."<init>":()V
     547: athrow
     548: iinc          10, 1
     551: goto          482
     554: iinc          9, 1
     557: goto          473
     560: aload_0
     561: getstatic     #5                  // Field TEST_UTIL:Lorg/apache/hadoop/hbase/HBaseTestingUtility;
     564: aload_1
     565: iconst_3
     566: iconst_2
     567: getstatic     #15                 // Field ADMIN:Lorg/apache/hadoop/hbase/client/Admin;
     570: invokeinterface #41,  1           // InterfaceMethod org/apache/hadoop/hbase/client/Admin.getConnection:()Lorg/apache/hadoop/hbase/client/Connection;
     575: invokespecial #71                 // Method validateFromSnapshotFromMeta:(Lorg/apache/hadoop/hbase/HBaseTestingUtility;Lorg/apache/hadoop/hbase/TableName;IILorg/apache/hadoop/hbase/client/Connection;)V
     578: new           #83                 // class java/util/ArrayList
     581: dup
     582: invokespecial #84                 // Method java/util/ArrayList."<init>":()V
     585: astore        9
     587: getstatic     #5                  // Field TEST_UTIL:Lorg/apache/hadoop/hbase/HBaseTestingUtility;
     590: invokevirtual #54                 // Method org/apache/hadoop/hbase/HBaseTestingUtility.getHBaseCluster:()Lorg/apache/hadoop/hbase/MiniHBaseCluster;
     593: invokevirtual #85                 // Method org/apache/hadoop/hbase/MiniHBaseCluster.getLiveRegionServerThreads:()Ljava/util/List;
     596: invokeinterface #60,  1           // InterfaceMethod java/util/List.iterator:()Ljava/util/Iterator;
     601: astore        10
     603: aload         10
     605: invokeinterface #61,  1           // InterfaceMethod java/util/Iterator.hasNext:()Z
     610: ifeq          655
     613: aload         10
     615: invokeinterface #62,  1           // InterfaceMethod java/util/Iterator.next:()Ljava/lang/Object;
     620: checkcast     #86                 // class org/apache/hadoop/hbase/util/JVMClusterUtil$RegionServerThread
     623: astore        11
     625: aload         9
     627: aload         11
     629: invokevirtual #87                 // Method org/apache/hadoop/hbase/util/JVMClusterUtil$RegionServerThread.getRegionServer:()Lorg/apache/hadoop/hbase/regionserver/HRegionServer;
     632: invokevirtual #88                 // Method org/apache/hadoop/hbase/regionserver/HRegionServer.getRpcServer:()Lorg/apache/hadoop/hbase/ipc/RpcServerInterface;
     635: invokeinterface #89,  1           // InterfaceMethod org/apache/hadoop/hbase/ipc/RpcServerInterface.getListenerAddress:()Ljava/net/InetSocketAddress;
     640: invokevirtual #90                 // Method java/net/InetSocketAddress.getPort:()I
     643: invokestatic  #91                 // Method java/lang/Integer.valueOf:(I)Ljava/lang/Integer;
     646: invokeinterface #92,  2           // InterfaceMethod java/util/List.add:(Ljava/lang/Object;)Z
     651: pop
     652: goto          603
     655: getstatic     #5                  // Field TEST_UTIL:Lorg/apache/hadoop/hbase/HBaseTestingUtility;
     658: invokevirtual #93                 // Method org/apache/hadoop/hbase/HBaseTestingUtility.shutdownMiniHBaseCluster:()V
     661: invokestatic  #94                 // Method org/apache/hadoop/hbase/StartMiniClusterOption.builder:()Lorg/apache/hadoop/hbase/StartMiniClusterOption$Builder;
     664: getstatic     #10                 // Field numSlaves:I
     667: invokevirtual #95                 // Method org/apache/hadoop/hbase/StartMiniClusterOption$Builder.numRegionServers:(I)Lorg/apache/hadoop/hbase/StartMiniClusterOption$Builder;
     670: aload         9
     672: invokevirtual #96                 // Method org/apache/hadoop/hbase/StartMiniClusterOption$Builder.rsPorts:(Ljava/util/List;)Lorg/apache/hadoop/hbase/StartMiniClusterOption$Builder;
     675: invokevirtual #97                 // Method org/apache/hadoop/hbase/StartMiniClusterOption$Builder.build:()Lorg/apache/hadoop/hbase/StartMiniClusterOption;
     678: astore        10
     680: getstatic     #5                  // Field TEST_UTIL:Lorg/apache/hadoop/hbase/HBaseTestingUtility;
     683: aload         10
     685: invokevirtual #98                 // Method org/apache/hadoop/hbase/HBaseTestingUtility.startMiniHBaseCluster:(Lorg/apache/hadoop/hbase/StartMiniClusterOption;)Lorg/apache/hadoop/hbase/MiniHBaseCluster;
     688: pop
     689: getstatic     #5                  // Field TEST_UTIL:Lorg/apache/hadoop/hbase/HBaseTestingUtility;
     692: aload_1
     693: invokevirtual #99                 // Method org/apache/hadoop/hbase/HBaseTestingUtility.waitTableAvailable:(Lorg/apache/hadoop/hbase/TableName;)V
     696: aload_0
     697: getstatic     #5                  // Field TEST_UTIL:Lorg/apache/hadoop/hbase/HBaseTestingUtility;
     700: aload_1
     701: iconst_3
     702: iconst_2
     703: getstatic     #15                 // Field ADMIN:Lorg/apache/hadoop/hbase/client/Admin;
     706: invokeinterface #41,  1           // InterfaceMethod org/apache/hadoop/hbase/client/Admin.getConnection:()Lorg/apache/hadoop/hbase/client/Connection;
     711: invokespecial #71                 // Method validateFromSnapshotFromMeta:(Lorg/apache/hadoop/hbase/HBaseTestingUtility;Lorg/apache/hadoop/hbase/TableName;IILorg/apache/hadoop/hbase/client/Connection;)V
     714: getstatic     #5                  // Field TEST_UTIL:Lorg/apache/hadoop/hbase/HBaseTestingUtility;
     717: invokevirtual #93                 // Method org/apache/hadoop/hbase/HBaseTestingUtility.shutdownMiniHBaseCluster:()V
     720: getstatic     #5                  // Field TEST_UTIL:Lorg/apache/hadoop/hbase/HBaseTestingUtility;
     723: invokevirtual #100                // Method org/apache/hadoop/hbase/HBaseTestingUtility.startMiniHBaseCluster:()Lorg/apache/hadoop/hbase/MiniHBaseCluster;
     726: pop
     727: getstatic     #5                  // Field TEST_UTIL:Lorg/apache/hadoop/hbase/HBaseTestingUtility;
     730: aload_1
     731: invokevirtual #99                 // Method org/apache/hadoop/hbase/HBaseTestingUtility.waitTableAvailable:(Lorg/apache/hadoop/hbase/TableName;)V
     734: aload_0
     735: getstatic     #15                 // Field ADMIN:Lorg/apache/hadoop/hbase/client/Admin;
     738: invokeinterface #41,  1           // InterfaceMethod org/apache/hadoop/hbase/client/Admin.getConnection:()Lorg/apache/hadoop/hbase/client/Connection;
     743: iconst_3
     744: iconst_2
     745: invokespecial #101                // Method validateSingleRegionServerAssignment:(Lorg/apache/hadoop/hbase/client/Connection;II)V
     748: iconst_1
     749: istore        11
     751: iload         11
     753: getstatic     #10                 // Field numSlaves:I
     756: if_icmpge     775
     759: getstatic     #5                  // Field TEST_UTIL:Lorg/apache/hadoop/hbase/HBaseTestingUtility;
     762: invokevirtual #102                // Method org/apache/hadoop/hbase/HBaseTestingUtility.getMiniHBaseCluster:()Lorg/apache/hadoop/hbase/MiniHBaseCluster;
     765: invokevirtual #103                // Method org/apache/hadoop/hbase/MiniHBaseCluster.startRegionServer:()Lorg/apache/hadoop/hbase/util/JVMClusterUtil$RegionServerThread;
     768: pop
     769: iinc          11, 1
     772: goto          751
     775: getstatic     #15                 // Field ADMIN:Lorg/apache/hadoop/hbase/client/Admin;
     778: aload_1
     779: invokeinterface #48,  2           // InterfaceMethod org/apache/hadoop/hbase/client/Admin.disableTable:(Lorg/apache/hadoop/hbase/TableName;)V
     784: getstatic     #44                 // Field $assertionsDisabled:Z
     787: ifne          810
     790: getstatic     #15                 // Field ADMIN:Lorg/apache/hadoop/hbase/client/Admin;
     793: aload_1
     794: invokeinterface #104,  2          // InterfaceMethod org/apache/hadoop/hbase/client/Admin.isTableDisabled:(Lorg/apache/hadoop/hbase/TableName;)Z
     799: ifne          810
     802: new           #46                 // class java/lang/AssertionError
     805: dup
     806: invokespecial #47                 // Method java/lang/AssertionError."<init>":()V
     809: athrow
     810: aload         4
     812: iconst_3
     813: invokevirtual #32                 // Method org/apache/hadoop/hbase/HTableDescriptor.setRegionReplication:(I)Lorg/apache/hadoop/hbase/HTableDescriptor;
     816: pop
     817: getstatic     #15                 // Field ADMIN:Lorg/apache/hadoop/hbase/client/Admin;
     820: aload         4
     822: invokeinterface #105,  2          // InterfaceMethod org/apache/hadoop/hbase/client/Admin.modifyTable:(Lorg/apache/hadoop/hbase/client/TableDescriptor;)V
     827: getstatic     #15                 // Field ADMIN:Lorg/apache/hadoop/hbase/client/Admin;
     830: aload_1
     831: invokeinterface #106,  2          // InterfaceMethod org/apache/hadoop/hbase/client/Admin.enableTable:(Lorg/apache/hadoop/hbase/TableName;)V
     836: getstatic     #107                // Field LOG:Lorg/slf4j/Logger;
     839: getstatic     #15                 // Field ADMIN:Lorg/apache/hadoop/hbase/client/Admin;
     842: aload_1
     843: invokeinterface #108,  2          // InterfaceMethod org/apache/hadoop/hbase/client/Admin.getDescriptor:(Lorg/apache/hadoop/hbase/TableName;)Lorg/apache/hadoop/hbase/client/TableDescriptor;
     848: invokevirtual #109                // Method java/lang/Object.toString:()Ljava/lang/String;
     851: invokeinterface #110,  2          // InterfaceMethod org/slf4j/Logger.info:(Ljava/lang/String;)V
     856: getstatic     #44                 // Field $assertionsDisabled:Z
     859: ifne          882
     862: getstatic     #15                 // Field ADMIN:Lorg/apache/hadoop/hbase/client/Admin;
     865: aload_1
     866: invokeinterface #111,  2          // InterfaceMethod org/apache/hadoop/hbase/client/Admin.isTableEnabled:(Lorg/apache/hadoop/hbase/TableName;)Z
     871: ifne          882
     874: new           #46                 // class java/lang/AssertionError
     877: dup
     878: invokespecial #47                 // Method java/lang/AssertionError."<init>":()V
     881: athrow
     882: getstatic     #5                  // Field TEST_UTIL:Lorg/apache/hadoop/hbase/HBaseTestingUtility;
     885: invokevirtual #102                // Method org/apache/hadoop/hbase/HBaseTestingUtility.getMiniHBaseCluster:()Lorg/apache/hadoop/hbase/MiniHBaseCluster;
     888: invokevirtual #55                 // Method org/apache/hadoop/hbase/MiniHBaseCluster.getMaster:()Lorg/apache/hadoop/hbase/master/HMaster;
     891: invokevirtual #56                 // Method org/apache/hadoop/hbase/master/HMaster.getAssignmentManager:()Lorg/apache/hadoop/hbase/master/assignment/AssignmentManager;
     894: invokevirtual #57                 // Method org/apache/hadoop/hbase/master/assignment/AssignmentManager.getRegionStates:()Lorg/apache/hadoop/hbase/master/assignment/RegionStates;
     897: aload_1
     898: invokevirtual #112                // Method org/apache/hadoop/hbase/master/assignment/RegionStates.getRegionsOfTable:(Lorg/apache/hadoop/hbase/TableName;)Ljava/util/List;
     901: astore        11
     903: new           #113                // class java/lang/StringBuilder
     906: dup
     907: invokespecial #114                // Method java/lang/StringBuilder."<init>":()V
     910: ldc           #115                // String regions.size=
     912: invokevirtual #116                // Method java/lang/StringBuilder.append:(Ljava/lang/String;)Ljava/lang/StringBuilder;
     915: aload         11
     917: invokeinterface #45,  1           // InterfaceMethod java/util/List.size:()I
     922: invokevirtual #117                // Method java/lang/StringBuilder.append:(I)Ljava/lang/StringBuilder;
     925: ldc           #118                // String , numRegions=
     927: invokevirtual #116                // Method java/lang/StringBuilder.append:(Ljava/lang/String;)Ljava/lang/StringBuilder;
     930: iconst_3
     931: invokevirtual #117                // Method java/lang/StringBuilder.append:(I)Ljava/lang/StringBuilder;
     934: ldc           #119                // String , numReplica=
     936: invokevirtual #116                // Method java/lang/StringBuilder.append:(Ljava/lang/String;)Ljava/lang/StringBuilder;
     939: iconst_2
     940: invokevirtual #117                // Method java/lang/StringBuilder.append:(I)Ljava/lang/StringBuilder;
     943: invokevirtual #120                // Method java/lang/StringBuilder.toString:()Ljava/lang/String;
     946: aload         11
     948: invokeinterface #45,  1           // InterfaceMethod java/util/List.size:()I
     953: bipush        9
     955: if_icmpne     962
     958: iconst_1
     959: goto          963
     962: iconst_0
     963: invokestatic  #121                // Method org/junit/Assert.assertTrue:(Ljava/lang/String;Z)V
     966: getstatic     #15                 // Field ADMIN:Lorg/apache/hadoop/hbase/client/Admin;
     969: aload_1
     970: invokeinterface #48,  2           // InterfaceMethod org/apache/hadoop/hbase/client/Admin.disableTable:(Lorg/apache/hadoop/hbase/TableName;)V
     975: aload         4
     977: iconst_2
     978: invokevirtual #32                 // Method org/apache/hadoop/hbase/HTableDescriptor.setRegionReplication:(I)Lorg/apache/hadoop/hbase/HTableDescriptor;
     981: pop
     982: getstatic     #15                 // Field ADMIN:Lorg/apache/hadoop/hbase/client/Admin;
     985: aload         4
     987: invokeinterface #105,  2          // InterfaceMethod org/apache/hadoop/hbase/client/Admin.modifyTable:(Lorg/apache/hadoop/hbase/client/TableDescriptor;)V
     992: getstatic     #15                 // Field ADMIN:Lorg/apache/hadoop/hbase/client/Admin;
     995: aload_1
     996: invokeinterface #106,  2          // InterfaceMethod org/apache/hadoop/hbase/client/Admin.enableTable:(Lorg/apache/hadoop/hbase/TableName;)V
    1001: getstatic     #44                 // Field $assertionsDisabled:Z
    1004: ifne          1027
    1007: getstatic     #15                 // Field ADMIN:Lorg/apache/hadoop/hbase/client/Admin;
    1010: aload_1
    1011: invokeinterface #111,  2          // InterfaceMethod org/apache/hadoop/hbase/client/Admin.isTableEnabled:(Lorg/apache/hadoop/hbase/TableName;)Z
    1016: ifne          1027
    1019: new           #46                 // class java/lang/AssertionError
    1022: dup
    1023: invokespecial #47                 // Method java/lang/AssertionError."<init>":()V
    1026: athrow
    1027: getstatic     #5                  // Field TEST_UTIL:Lorg/apache/hadoop/hbase/HBaseTestingUtility;
    1030: invokevirtual #102                // Method org/apache/hadoop/hbase/HBaseTestingUtility.getMiniHBaseCluster:()Lorg/apache/hadoop/hbase/MiniHBaseCluster;
    1033: invokevirtual #55                 // Method org/apache/hadoop/hbase/MiniHBaseCluster.getMaster:()Lorg/apache/hadoop/hbase/master/HMaster;
    1036: invokevirtual #56                 // Method org/apache/hadoop/hbase/master/HMaster.getAssignmentManager:()Lorg/apache/hadoop/hbase/master/assignment/AssignmentManager;
    1039: invokevirtual #57                 // Method org/apache/hadoop/hbase/master/assignment/AssignmentManager.getRegionStates:()Lorg/apache/hadoop/hbase/master/assignment/RegionStates;
    1042: aload_1
    1043: invokevirtual #112                // Method org/apache/hadoop/hbase/master/assignment/RegionStates.getRegionsOfTable:(Lorg/apache/hadoop/hbase/TableName;)Ljava/util/List;
    1046: astore        11
    1048: getstatic     #44                 // Field $assertionsDisabled:Z
    1051: ifne          1074
    1054: aload         11
    1056: invokeinterface #45,  1           // InterfaceMethod java/util/List.size:()I
    1061: bipush        6
    1063: if_icmpeq     1074
    1066: new           #46                 // class java/lang/AssertionError
    1069: dup
    1070: invokespecial #47                 // Method java/lang/AssertionError."<init>":()V
    1073: athrow
    1074: getstatic     #15                 // Field ADMIN:Lorg/apache/hadoop/hbase/client/Admin;
    1077: invokeinterface #41,  1           // InterfaceMethod org/apache/hadoop/hbase/client/Admin.getConnection:()Lorg/apache/hadoop/hbase/client/Connection;
    1082: aload_1
    1083: invokestatic  #43                 // Method org/apache/hadoop/hbase/MetaTableAccessor.getTableRegions:(Lorg/apache/hadoop/hbase/client/Connection;Lorg/apache/hadoop/hbase/TableName;)Ljava/util/List;
    1086: astore        5
    1088: getstatic     #44                 // Field $assertionsDisabled:Z
    1091: ifne          1114
    1094: aload         5
    1096: invokeinterface #45,  1           // InterfaceMethod java/util/List.size:()I
    1101: bipush        6
    1103: if_icmpeq     1114
    1106: new           #46                 // class java/lang/AssertionError
    1109: dup
    1110: invokespecial #47                 // Method java/lang/AssertionError."<init>":()V
    1113: athrow
    1114: new           #122                // class java/util/HashMap
    1117: dup
    1118: invokespecial #123                // Method java/util/HashMap."<init>":()V
    1121: astore        12
    1123: aload         5
    1125: invokeinterface #60,  1           // InterfaceMethod java/util/List.iterator:()Ljava/util/Iterator;
    1130: astore        13
    1132: aload         13
    1134: invokeinterface #61,  1           // InterfaceMethod java/util/Iterator.hasNext:()Z
    1139: ifeq          1206
    1142: aload         13
    1144: invokeinterface #62,  1           // InterfaceMethod java/util/Iterator.next:()Ljava/lang/Object;
    1149: checkcast     #52                 // class org/apache/hadoop/hbase/client/RegionInfo
    1152: astore        14
    1154: aload         14
    1156: invokestatic  #124                // Method org/apache/hadoop/hbase/client/RegionReplicaUtil.getRegionInfoForDefaultReplica:(Lorg/apache/hadoop/hbase/client/RegionInfo;)Lorg/apache/hadoop/hbase/client/RegionInfo;
    1159: astore        16
    1161: aload         12
    1163: aload         16
    1165: aload         12
    1167: aload         16
    1169: invokeinterface #125,  2          // InterfaceMethod java/util/Map.get:(Ljava/lang/Object;)Ljava/lang/Object;
    1174: checkcast     #126                // class java/lang/Integer
    1177: dup
    1178: astore        15
    1180: ifnonnull     1187
    1183: iconst_1
    1184: goto          1194
    1187: aload         15
    1189: invokevirtual #127                // Method java/lang/Integer.intValue:()I
    1192: iconst_1
    1193: iadd
    1194: invokestatic  #91                 // Method java/lang/Integer.valueOf:(I)Ljava/lang/Integer;
    1197: invokeinterface #128,  3          // InterfaceMethod java/util/Map.put:(Ljava/lang/Object;Ljava/lang/Object;)Ljava/lang/Object;
    1202: pop
    1203: goto          1132
    1206: getstatic     #44                 // Field $assertionsDisabled:Z
    1209: ifne          1231
    1212: aload         12
    1214: invokeinterface #20,  1           // InterfaceMethod java/util/Map.size:()I
    1219: iconst_3
    1220: if_icmpeq     1231
    1223: new           #46                 // class java/lang/AssertionError
    1226: dup
    1227: invokespecial #47                 // Method java/lang/AssertionError."<init>":()V
    1230: athrow
    1231: new           #129                // class java/util/HashSet
    1234: dup
    1235: aload         12
    1237: invokeinterface #130,  1          // InterfaceMethod java/util/Map.values:()Ljava/util/Collection;
    1242: invokespecial #131                // Method java/util/HashSet."<init>":(Ljava/util/Collection;)V
    1245: astore        13
    1247: getstatic     #44                 // Field $assertionsDisabled:Z
    1250: ifne          1286
    1253: aload         13
    1255: invokeinterface #132,  1          // InterfaceMethod java/util/Collection.size:()I
    1260: iconst_1
    1261: if_icmpne     1278
    1264: aload         13
    1266: iconst_2
    1267: invokestatic  #91                 // Method java/lang/Integer.valueOf:(I)Ljava/lang/Integer;
    1270: invokeinterface #133,  2          // InterfaceMethod java/util/Collection.contains:(Ljava/lang/Object;)Z
    1275: ifne          1286
    1278: new           #46                 // class java/lang/AssertionError
    1281: dup
    1282: invokespecial #47                 // Method java/lang/AssertionError."<init>":()V
    1285: athrow
    1286: getstatic     #15                 // Field ADMIN:Lorg/apache/hadoop/hbase/client/Admin;
    1289: aload_1
    1290: invokeinterface #48,  2           // InterfaceMethod org/apache/hadoop/hbase/client/Admin.disableTable:(Lorg/apache/hadoop/hbase/TableName;)V
    1295: getstatic     #15                 // Field ADMIN:Lorg/apache/hadoop/hbase/client/Admin;
    1298: aload_1
    1299: invokeinterface #49,  2           // InterfaceMethod org/apache/hadoop/hbase/client/Admin.deleteTable:(Lorg/apache/hadoop/hbase/TableName;)V
    1304: goto          1330
    1307: astore        17
    1309: getstatic     #15                 // Field ADMIN:Lorg/apache/hadoop/hbase/client/Admin;
    1312: aload_1
    1313: invokeinterface #48,  2           // InterfaceMethod org/apache/hadoop/hbase/client/Admin.disableTable:(Lorg/apache/hadoop/hbase/TableName;)V
    1318: getstatic     #15                 // Field ADMIN:Lorg/apache/hadoop/hbase/client/Admin;
    1321: aload_1
    1322: invokeinterface #49,  2           // InterfaceMethod org/apache/hadoop/hbase/client/Admin.deleteTable:(Lorg/apache/hadoop/hbase/TableName;)V
    1327: aload         17
    1329: athrow
    1330: return
    Exception table:
       from    to  target type
          15  1286  1307   any
        1307  1309  1307   any

  public void testIncompleteMetaTableReplicaInformation() throws java.lang.Exception;
    Code:
       0: aload_0
       1: getfield      #4                  // Field name:Lorg/junit/rules/TestName;
       4: invokevirtual #28                 // Method org/junit/rules/TestName.getMethodName:()Ljava/lang/String;
       7: invokestatic  #29                 // Method org/apache/hadoop/hbase/TableName.valueOf:(Ljava/lang/String;)Lorg/apache/hadoop/hbase/TableName;
      10: astore_1
      11: iconst_3
      12: istore_2
      13: iconst_2
      14: istore_3
      15: new           #30                 // class org/apache/hadoop/hbase/HTableDescriptor
      18: dup
      19: aload_1
      20: invokespecial #31                 // Method org/apache/hadoop/hbase/HTableDescriptor."<init>":(Lorg/apache/hadoop/hbase/TableName;)V
      23: astore        4
      25: aload         4
      27: iconst_2
      28: invokevirtual #32                 // Method org/apache/hadoop/hbase/HTableDescriptor.setRegionReplication:(I)Lorg/apache/hadoop/hbase/HTableDescriptor;
      31: pop
      32: aload         4
      34: new           #33                 // class org/apache/hadoop/hbase/HColumnDescriptor
      37: dup
      38: ldc           #34                 // String family
      40: invokespecial #35                 // Method org/apache/hadoop/hbase/HColumnDescriptor."<init>":(Ljava/lang/String;)V
      43: invokevirtual #36                 // Method org/apache/hadoop/hbase/HTableDescriptor.addFamily:(Lorg/apache/hadoop/hbase/HColumnDescriptor;)Lorg/apache/hadoop/hbase/HTableDescriptor;
      46: pop
      47: getstatic     #15                 // Field ADMIN:Lorg/apache/hadoop/hbase/client/Admin;
      50: aload         4
      52: ldc           #37                 // String A
      54: invokestatic  #38                 // Method org/apache/hadoop/hbase/util/Bytes.toBytes:(Ljava/lang/String;)[B
      57: ldc           #39                 // String Z
      59: invokestatic  #38                 // Method org/apache/hadoop/hbase/util/Bytes.toBytes:(Ljava/lang/String;)[B
      62: iconst_3
      63: invokeinterface #40,  5           // InterfaceMethod org/apache/hadoop/hbase/client/Admin.createTable:(Lorg/apache/hadoop/hbase/client/TableDescriptor;[B[BI)V
      68: getstatic     #5                  // Field TEST_UTIL:Lorg/apache/hadoop/hbase/HBaseTestingUtility;
      71: aload_1
      72: invokevirtual #50                 // Method org/apache/hadoop/hbase/HBaseTestingUtility.waitTableEnabled:(Lorg/apache/hadoop/hbase/TableName;)V
      75: new           #129                // class java/util/HashSet
      78: dup
      79: invokespecial #134                // Method java/util/HashSet."<init>":()V
      82: astore        5
      84: getstatic     #15                 // Field ADMIN:Lorg/apache/hadoop/hbase/client/Admin;
      87: invokeinterface #41,  1           // InterfaceMethod org/apache/hadoop/hbase/client/Admin.getConnection:()Lorg/apache/hadoop/hbase/client/Connection;
      92: aload_1
      93: invokestatic  #43                 // Method org/apache/hadoop/hbase/MetaTableAccessor.getTableRegions:(Lorg/apache/hadoop/hbase/client/Connection;Lorg/apache/hadoop/hbase/TableName;)Ljava/util/List;
      96: astore        6
      98: aload         6
     100: invokeinterface #60,  1           // InterfaceMethod java/util/List.iterator:()Ljava/util/Iterator;
     105: astore        7
     107: aload         7
     109: invokeinterface #61,  1           // InterfaceMethod java/util/Iterator.hasNext:()Z
     114: ifeq          147
     117: aload         7
     119: invokeinterface #62,  1           // InterfaceMethod java/util/Iterator.next:()Ljava/lang/Object;
     124: checkcast     #52                 // class org/apache/hadoop/hbase/client/RegionInfo
     127: astore        8
     129: aload         5
     131: aload         8
     133: invokeinterface #135,  1          // InterfaceMethod org/apache/hadoop/hbase/client/RegionInfo.getRegionName:()[B
     138: invokeinterface #136,  2          // InterfaceMethod java/util/Set.add:(Ljava/lang/Object;)Z
     143: pop
     144: goto          107
     147: getstatic     #15                 // Field ADMIN:Lorg/apache/hadoop/hbase/client/Admin;
     150: aload_1
     151: invokeinterface #48,  2           // InterfaceMethod org/apache/hadoop/hbase/client/Admin.disableTable:(Lorg/apache/hadoop/hbase/TableName;)V
     156: getstatic     #15                 // Field ADMIN:Lorg/apache/hadoop/hbase/client/Admin;
     159: invokeinterface #41,  1           // InterfaceMethod org/apache/hadoop/hbase/client/Admin.getConnection:()Lorg/apache/hadoop/hbase/client/Connection;
     164: getstatic     #137                // Field org/apache/hadoop/hbase/TableName.META_TABLE_NAME:Lorg/apache/hadoop/hbase/TableName;
     167: invokeinterface #138,  2          // InterfaceMethod org/apache/hadoop/hbase/client/Connection.getTable:(Lorg/apache/hadoop/hbase/TableName;)Lorg/apache/hadoop/hbase/client/Table;
     172: astore        7
     174: aload         5
     176: invokeinterface #139,  1          // InterfaceMethod java/util/Set.iterator:()Ljava/util/Iterator;
     181: astore        8
     183: aload         8
     185: invokeinterface #61,  1           // InterfaceMethod java/util/Iterator.hasNext:()Z
     190: ifeq          267
     193: aload         8
     195: invokeinterface #62,  1           // InterfaceMethod java/util/Iterator.next:()Ljava/lang/Object;
     200: checkcast     #140                // class "[B"
     203: astore        9
     205: new           #141                // class org/apache/hadoop/hbase/client/Delete
     208: dup
     209: aload         9
     211: invokespecial #142                // Method org/apache/hadoop/hbase/client/Delete."<init>":([B)V
     214: astore        10
     216: aload         10
     218: getstatic     #143                // Field org/apache/hadoop/hbase/HConstants.CATALOG_FAMILY:[B
     221: iconst_1
     222: invokestatic  #144                // Method org/apache/hadoop/hbase/MetaTableAccessor.getServerColumn:(I)[B
     225: invokevirtual #145                // Method org/apache/hadoop/hbase/client/Delete.addColumns:([B[B)Lorg/apache/hadoop/hbase/client/Delete;
     228: pop
     229: aload         10
     231: getstatic     #143                // Field org/apache/hadoop/hbase/HConstants.CATALOG_FAMILY:[B
     234: iconst_1
     235: invokestatic  #146                // Method org/apache/hadoop/hbase/MetaTableAccessor.getSeqNumColumn:(I)[B
     238: invokevirtual #145                // Method org/apache/hadoop/hbase/client/Delete.addColumns:([B[B)Lorg/apache/hadoop/hbase/client/Delete;
     241: pop
     242: aload         10
     244: getstatic     #143                // Field org/apache/hadoop/hbase/HConstants.CATALOG_FAMILY:[B
     247: iconst_1
     248: invokestatic  #147                // Method org/apache/hadoop/hbase/MetaTableAccessor.getStartCodeColumn:(I)[B
     251: invokevirtual #145                // Method org/apache/hadoop/hbase/client/Delete.addColumns:([B[B)Lorg/apache/hadoop/hbase/client/Delete;
     254: pop
     255: aload         7
     257: aload         10
     259: invokeinterface #148,  2          // InterfaceMethod org/apache/hadoop/hbase/client/Table.delete:(Lorg/apache/hadoop/hbase/client/Delete;)V
     264: goto          183
     267: aload         7
     269: invokeinterface #149,  1          // InterfaceMethod org/apache/hadoop/hbase/client/Table.close:()V
     274: getstatic     #15                 // Field ADMIN:Lorg/apache/hadoop/hbase/client/Admin;
     277: aload_1
     278: invokeinterface #106,  2          // InterfaceMethod org/apache/hadoop/hbase/client/Admin.enableTable:(Lorg/apache/hadoop/hbase/TableName;)V
     283: getstatic     #44                 // Field $assertionsDisabled:Z
     286: ifne          309
     289: getstatic     #15                 // Field ADMIN:Lorg/apache/hadoop/hbase/client/Admin;
     292: aload_1
     293: invokeinterface #111,  2          // InterfaceMethod org/apache/hadoop/hbase/client/Admin.isTableEnabled:(Lorg/apache/hadoop/hbase/TableName;)Z
     298: ifne          309
     301: new           #46                 // class java/lang/AssertionError
     304: dup
     305: invokespecial #47                 // Method java/lang/AssertionError."<init>":()V
     308: athrow
     309: getstatic     #5                  // Field TEST_UTIL:Lorg/apache/hadoop/hbase/HBaseTestingUtility;
     312: invokevirtual #102                // Method org/apache/hadoop/hbase/HBaseTestingUtility.getMiniHBaseCluster:()Lorg/apache/hadoop/hbase/MiniHBaseCluster;
     315: invokevirtual #55                 // Method org/apache/hadoop/hbase/MiniHBaseCluster.getMaster:()Lorg/apache/hadoop/hbase/master/HMaster;
     318: invokevirtual #56                 // Method org/apache/hadoop/hbase/master/HMaster.getAssignmentManager:()Lorg/apache/hadoop/hbase/master/assignment/AssignmentManager;
     321: invokevirtual #57                 // Method org/apache/hadoop/hbase/master/assignment/AssignmentManager.getRegionStates:()Lorg/apache/hadoop/hbase/master/assignment/RegionStates;
     324: aload_1
     325: invokevirtual #112                // Method org/apache/hadoop/hbase/master/assignment/RegionStates.getRegionsOfTable:(Lorg/apache/hadoop/hbase/TableName;)Ljava/util/List;
     328: astore        8
     330: getstatic     #44                 // Field $assertionsDisabled:Z
     333: ifne          356
     336: aload         8
     338: invokeinterface #45,  1           // InterfaceMethod java/util/List.size:()I
     343: bipush        6
     345: if_icmpeq     356
     348: new           #46                 // class java/lang/AssertionError
     351: dup
     352: invokespecial #47                 // Method java/lang/AssertionError."<init>":()V
     355: athrow
     356: getstatic     #15                 // Field ADMIN:Lorg/apache/hadoop/hbase/client/Admin;
     359: aload_1
     360: invokeinterface #48,  2           // InterfaceMethod org/apache/hadoop/hbase/client/Admin.disableTable:(Lorg/apache/hadoop/hbase/TableName;)V
     365: getstatic     #15                 // Field ADMIN:Lorg/apache/hadoop/hbase/client/Admin;
     368: aload_1
     369: invokeinterface #49,  2           // InterfaceMethod org/apache/hadoop/hbase/client/Admin.deleteTable:(Lorg/apache/hadoop/hbase/TableName;)V
     374: goto          400
     377: astore        11
     379: getstatic     #15                 // Field ADMIN:Lorg/apache/hadoop/hbase/client/Admin;
     382: aload_1
     383: invokeinterface #48,  2           // InterfaceMethod org/apache/hadoop/hbase/client/Admin.disableTable:(Lorg/apache/hadoop/hbase/TableName;)V
     388: getstatic     #15                 // Field ADMIN:Lorg/apache/hadoop/hbase/client/Admin;
     391: aload_1
     392: invokeinterface #49,  2           // InterfaceMethod org/apache/hadoop/hbase/client/Admin.deleteTable:(Lorg/apache/hadoop/hbase/TableName;)V
     397: aload         11
     399: athrow
     400: return
    Exception table:
       from    to  target type
          15   356   377   any
         377   379   377   any

  static {};
    Code:
       0: ldc           #182                // class org/apache/hadoop/hbase/master/TestMasterOperationsForRegionReplicas
       2: invokevirtual #183                // Method java/lang/Class.desiredAssertionStatus:()Z
       5: ifne          12
       8: iconst_1
       9: goto          13
      12: iconst_0
      13: putstatic     #44                 // Field $assertionsDisabled:Z
      16: ldc           #182                // class org/apache/hadoop/hbase/master/TestMasterOperationsForRegionReplicas
      18: invokestatic  #184                // Method org/apache/hadoop/hbase/HBaseClassTestRule.forClass:(Ljava/lang/Class;)Lorg/apache/hadoop/hbase/HBaseClassTestRule;
      21: putstatic     #185                // Field CLASS_RULE:Lorg/apache/hadoop/hbase/HBaseClassTestRule;
      24: ldc           #186                // class org/apache/hadoop/hbase/master/TestRegionPlacement
      26: invokestatic  #187                // Method org/slf4j/LoggerFactory.getLogger:(Ljava/lang/Class;)Lorg/slf4j/Logger;
      29: putstatic     #107                // Field LOG:Lorg/slf4j/Logger;
      32: new           #188                // class org/apache/hadoop/hbase/HBaseTestingUtility
      35: dup
      36: invokespecial #189                // Method org/apache/hadoop/hbase/HBaseTestingUtility."<init>":()V
      39: putstatic     #5                  // Field TEST_UTIL:Lorg/apache/hadoop/hbase/HBaseTestingUtility;
      42: aconst_null
      43: putstatic     #13                 // Field CONNECTION:Lorg/apache/hadoop/hbase/client/Connection;
      46: iconst_2
      47: putstatic     #10                 // Field numSlaves:I
      50: return
}
