Compiled from "TestAsyncProcess.java"
class org.apache.hadoop.hbase.client.TestAsyncProcess$1 implements org.apache.hadoop.hbase.client.coprocessor.Batch$Callback<java.lang.Object> {
  final java.util.concurrent.atomic.AtomicInteger val$updateCalled;

  final org.apache.hadoop.hbase.client.TestAsyncProcess this$0;

  org.apache.hadoop.hbase.client.TestAsyncProcess$1(org.apache.hadoop.hbase.client.TestAsyncProcess, java.util.concurrent.atomic.AtomicInteger);
    Code:
       0: aload_0
       1: aload_1
       2: putfield      #1                  // Field this$0:Lorg/apache/hadoop/hbase/client/TestAsyncProcess;
       5: aload_0
       6: aload_2
       7: putfield      #2                  // Field val$updateCalled:Ljava/util/concurrent/atomic/AtomicInteger;
      10: aload_0
      11: invokespecial #3                  // Method java/lang/Object."<init>":()V
      14: return

  public void update(byte[], byte[], java.lang.Object);
    Code:
       0: aload_0
       1: getfield      #2                  // Field val$updateCalled:Ljava/util/concurrent/atomic/AtomicInteger;
       4: invokevirtual #4                  // Method java/util/concurrent/atomic/AtomicInteger.incrementAndGet:()I
       7: pop
       8: return
}
