Compiled from "TestSimpleTimeRangeTracker.java"
public class org.apache.hadoop.hbase.regionserver.TestSimpleTimeRangeTracker {
  public static final org.apache.hadoop.hbase.HBaseClassTestRule CLASS_RULE;

  public org.apache.hadoop.hbase.regionserver.TestSimpleTimeRangeTracker();
    Code:
       0: aload_0
       1: invokespecial #1                  // Method java/lang/Object."<init>":()V
       4: return

  protected org.apache.hadoop.hbase.regionserver.TimeRangeTracker getTimeRangeTracker();
    Code:
       0: getstatic     #2                  // Field org/apache/hadoop/hbase/regionserver/TimeRangeTracker$Type.NON_SYNC:Lorg/apache/hadoop/hbase/regionserver/TimeRangeTracker$Type;
       3: invokestatic  #3                  // Method org/apache/hadoop/hbase/regionserver/TimeRangeTracker.create:(Lorg/apache/hadoop/hbase/regionserver/TimeRangeTracker$Type;)Lorg/apache/hadoop/hbase/regionserver/TimeRangeTracker;
       6: areturn

  protected org.apache.hadoop.hbase.regionserver.TimeRangeTracker getTimeRangeTracker(long, long);
    Code:
       0: getstatic     #2                  // Field org/apache/hadoop/hbase/regionserver/TimeRangeTracker$Type.NON_SYNC:Lorg/apache/hadoop/hbase/regionserver/TimeRangeTracker$Type;
       3: lload_1
       4: lload_3
       5: invokestatic  #4                  // Method org/apache/hadoop/hbase/regionserver/TimeRangeTracker.create:(Lorg/apache/hadoop/hbase/regionserver/TimeRangeTracker$Type;JJ)Lorg/apache/hadoop/hbase/regionserver/TimeRangeTracker;
       8: areturn

  public void testExtreme();
    Code:
       0: invokestatic  #5                  // Method org/apache/hadoop/hbase/io/TimeRange.allTime:()Lorg/apache/hadoop/hbase/io/TimeRange;
       3: astore_1
       4: aload_1
       5: invokestatic  #5                  // Method org/apache/hadoop/hbase/io/TimeRange.allTime:()Lorg/apache/hadoop/hbase/io/TimeRange;
       8: invokevirtual #6                  // Method org/apache/hadoop/hbase/io/TimeRange.includesTimeRange:(Lorg/apache/hadoop/hbase/io/TimeRange;)Z
      11: invokestatic  #7                  // Method org/junit/Assert.assertTrue:(Z)V
      14: aload_0
      15: invokevirtual #8                  // Method getTimeRangeTracker:()Lorg/apache/hadoop/hbase/regionserver/TimeRangeTracker;
      18: astore_2
      19: aload_2
      20: invokestatic  #5                  // Method org/apache/hadoop/hbase/io/TimeRange.allTime:()Lorg/apache/hadoop/hbase/io/TimeRange;
      23: invokevirtual #9                  // Method org/apache/hadoop/hbase/regionserver/TimeRangeTracker.includesTimeRange:(Lorg/apache/hadoop/hbase/io/TimeRange;)Z
      26: invokestatic  #10                 // Method org/junit/Assert.assertFalse:(Z)V
      29: aload_2
      30: lconst_1
      31: invokevirtual #11                 // Method org/apache/hadoop/hbase/regionserver/TimeRangeTracker.includeTimestamp:(J)V
      34: aload_2
      35: ldc2_w        #12                 // long 10l
      38: invokevirtual #11                 // Method org/apache/hadoop/hbase/regionserver/TimeRangeTracker.includeTimestamp:(J)V
      41: aload_2
      42: invokestatic  #5                  // Method org/apache/hadoop/hbase/io/TimeRange.allTime:()Lorg/apache/hadoop/hbase/io/TimeRange;
      45: invokevirtual #9                  // Method org/apache/hadoop/hbase/regionserver/TimeRangeTracker.includesTimeRange:(Lorg/apache/hadoop/hbase/io/TimeRange;)Z
      48: invokestatic  #7                  // Method org/junit/Assert.assertTrue:(Z)V
      51: return

  public void testTimeRangeInitialized();
    Code:
       0: aload_0
       1: invokevirtual #8                  // Method getTimeRangeTracker:()Lorg/apache/hadoop/hbase/regionserver/TimeRangeTracker;
       4: astore_1
       5: new           #14                 // class org/apache/hadoop/hbase/io/TimeRange
       8: dup
       9: invokestatic  #15                 // Method java/lang/System.currentTimeMillis:()J
      12: invokespecial #16                 // Method org/apache/hadoop/hbase/io/TimeRange."<init>":(J)V
      15: astore_2
      16: aload_1
      17: aload_2
      18: invokevirtual #9                  // Method org/apache/hadoop/hbase/regionserver/TimeRangeTracker.includesTimeRange:(Lorg/apache/hadoop/hbase/io/TimeRange;)Z
      21: invokestatic  #10                 // Method org/junit/Assert.assertFalse:(Z)V
      24: return

  public void testTimeRangeTrackerNullIsSameAsTimeRangeNull() throws java.io.IOException;
    Code:
       0: aload_0
       1: lconst_1
       2: ldc2_w        #17                 // long 2l
       5: invokevirtual #19                 // Method getTimeRangeTracker:(JJ)Lorg/apache/hadoop/hbase/regionserver/TimeRangeTracker;
       8: astore_1
       9: aload_1
      10: invokestatic  #20                 // Method org/apache/hadoop/hbase/regionserver/TimeRangeTracker.toByteArray:(Lorg/apache/hadoop/hbase/regionserver/TimeRangeTracker;)[B
      13: astore_2
      14: aload_2
      15: invokestatic  #21                 // Method org/apache/hadoop/hbase/regionserver/TimeRangeTracker.parseFrom:([B)Lorg/apache/hadoop/hbase/regionserver/TimeRangeTracker;
      18: invokevirtual #22                 // Method org/apache/hadoop/hbase/regionserver/TimeRangeTracker.toTimeRange:()Lorg/apache/hadoop/hbase/io/TimeRange;
      21: astore_3
      22: aload_1
      23: invokevirtual #23                 // Method org/apache/hadoop/hbase/regionserver/TimeRangeTracker.getMin:()J
      26: aload_3
      27: invokevirtual #24                 // Method org/apache/hadoop/hbase/io/TimeRange.getMin:()J
      30: invokestatic  #25                 // Method org/junit/Assert.assertEquals:(JJ)V
      33: aload_1
      34: invokevirtual #26                 // Method org/apache/hadoop/hbase/regionserver/TimeRangeTracker.getMax:()J
      37: aload_3
      38: invokevirtual #27                 // Method org/apache/hadoop/hbase/io/TimeRange.getMax:()J
      41: invokestatic  #25                 // Method org/junit/Assert.assertEquals:(JJ)V
      44: return

  public void testSerialization() throws java.io.IOException;
    Code:
       0: aload_0
       1: lconst_1
       2: ldc2_w        #17                 // long 2l
       5: invokevirtual #19                 // Method getTimeRangeTracker:(JJ)Lorg/apache/hadoop/hbase/regionserver/TimeRangeTracker;
       8: astore_1
       9: aload_1
      10: invokestatic  #20                 // Method org/apache/hadoop/hbase/regionserver/TimeRangeTracker.toByteArray:(Lorg/apache/hadoop/hbase/regionserver/TimeRangeTracker;)[B
      13: invokestatic  #21                 // Method org/apache/hadoop/hbase/regionserver/TimeRangeTracker.parseFrom:([B)Lorg/apache/hadoop/hbase/regionserver/TimeRangeTracker;
      16: astore_2
      17: aload_1
      18: invokevirtual #23                 // Method org/apache/hadoop/hbase/regionserver/TimeRangeTracker.getMin:()J
      21: aload_2
      22: invokevirtual #23                 // Method org/apache/hadoop/hbase/regionserver/TimeRangeTracker.getMin:()J
      25: invokestatic  #25                 // Method org/junit/Assert.assertEquals:(JJ)V
      28: aload_1
      29: invokevirtual #26                 // Method org/apache/hadoop/hbase/regionserver/TimeRangeTracker.getMax:()J
      32: aload_2
      33: invokevirtual #26                 // Method org/apache/hadoop/hbase/regionserver/TimeRangeTracker.getMax:()J
      36: invokestatic  #25                 // Method org/junit/Assert.assertEquals:(JJ)V
      39: return

  public void testLegacySerialization() throws java.io.IOException;
    Code:
       0: new           #28                 // class org/apache/hadoop/hbase/io/ByteArrayOutputStream
       3: dup
       4: invokespecial #29                 // Method org/apache/hadoop/hbase/io/ByteArrayOutputStream."<init>":()V
       7: astore_1
       8: new           #30                 // class java/io/DataOutputStream
      11: dup
      12: aload_1
      13: invokespecial #31                 // Method java/io/DataOutputStream."<init>":(Ljava/io/OutputStream;)V
      16: astore_2
      17: aload_2
      18: ldc2_w        #32                 // long 100l
      21: invokevirtual #34                 // Method java/io/DataOutputStream.writeLong:(J)V
      24: aload_2
      25: ldc2_w        #35                 // long 200l
      28: invokevirtual #34                 // Method java/io/DataOutputStream.writeLong:(J)V
      31: aload_1
      32: invokevirtual #37                 // Method org/apache/hadoop/hbase/io/ByteArrayOutputStream.toByteArray:()[B
      35: invokestatic  #21                 // Method org/apache/hadoop/hbase/regionserver/TimeRangeTracker.parseFrom:([B)Lorg/apache/hadoop/hbase/regionserver/TimeRangeTracker;
      38: astore_3
      39: ldc2_w        #32                 // long 100l
      42: aload_3
      43: invokevirtual #23                 // Method org/apache/hadoop/hbase/regionserver/TimeRangeTracker.getMin:()J
      46: invokestatic  #25                 // Method org/junit/Assert.assertEquals:(JJ)V
      49: ldc2_w        #35                 // long 200l
      52: aload_3
      53: invokevirtual #26                 // Method org/apache/hadoop/hbase/regionserver/TimeRangeTracker.getMax:()J
      56: invokestatic  #25                 // Method org/junit/Assert.assertEquals:(JJ)V
      59: return

  public void testAlwaysDecrementingSetsMaximum();
    Code:
       0: aload_0
       1: invokevirtual #8                  // Method getTimeRangeTracker:()Lorg/apache/hadoop/hbase/regionserver/TimeRangeTracker;
       4: astore_1
       5: aload_1
       6: ldc2_w        #38                 // long 3l
       9: invokevirtual #11                 // Method org/apache/hadoop/hbase/regionserver/TimeRangeTracker.includeTimestamp:(J)V
      12: aload_1
      13: ldc2_w        #17                 // long 2l
      16: invokevirtual #11                 // Method org/apache/hadoop/hbase/regionserver/TimeRangeTracker.includeTimestamp:(J)V
      19: aload_1
      20: lconst_1
      21: invokevirtual #11                 // Method org/apache/hadoop/hbase/regionserver/TimeRangeTracker.includeTimestamp:(J)V
      24: aload_1
      25: invokevirtual #23                 // Method org/apache/hadoop/hbase/regionserver/TimeRangeTracker.getMin:()J
      28: ldc2_w        #41                 // long 9223372036854775807l
      31: lcmp
      32: ifeq          39
      35: iconst_1
      36: goto          40
      39: iconst_0
      40: invokestatic  #7                  // Method org/junit/Assert.assertTrue:(Z)V
      43: aload_1
      44: invokevirtual #26                 // Method org/apache/hadoop/hbase/regionserver/TimeRangeTracker.getMax:()J
      47: ldc2_w        #43                 // long -1l
      50: lcmp
      51: ifeq          58
      54: iconst_1
      55: goto          59
      58: iconst_0
      59: invokestatic  #7                  // Method org/junit/Assert.assertTrue:(Z)V
      62: return

  public void testSimpleInRange();
    Code:
       0: aload_0
       1: invokevirtual #8                  // Method getTimeRangeTracker:()Lorg/apache/hadoop/hbase/regionserver/TimeRangeTracker;
       4: astore_1
       5: aload_1
       6: lconst_0
       7: invokevirtual #11                 // Method org/apache/hadoop/hbase/regionserver/TimeRangeTracker.includeTimestamp:(J)V
      10: aload_1
      11: ldc2_w        #17                 // long 2l
      14: invokevirtual #11                 // Method org/apache/hadoop/hbase/regionserver/TimeRangeTracker.includeTimestamp:(J)V
      17: aload_1
      18: new           #14                 // class org/apache/hadoop/hbase/io/TimeRange
      21: dup
      22: lconst_1
      23: invokespecial #16                 // Method org/apache/hadoop/hbase/io/TimeRange."<init>":(J)V
      26: invokevirtual #9                  // Method org/apache/hadoop/hbase/regionserver/TimeRangeTracker.includesTimeRange:(Lorg/apache/hadoop/hbase/io/TimeRange;)Z
      29: invokestatic  #7                  // Method org/junit/Assert.assertTrue:(Z)V
      32: return

  public void testRangeConstruction() throws java.io.IOException;
    Code:
       0: invokestatic  #5                  // Method org/apache/hadoop/hbase/io/TimeRange.allTime:()Lorg/apache/hadoop/hbase/io/TimeRange;
       3: astore_1
       4: lconst_0
       5: aload_1
       6: invokevirtual #24                 // Method org/apache/hadoop/hbase/io/TimeRange.getMin:()J
       9: invokestatic  #25                 // Method org/junit/Assert.assertEquals:(JJ)V
      12: ldc2_w        #41                 // long 9223372036854775807l
      15: aload_1
      16: invokevirtual #27                 // Method org/apache/hadoop/hbase/io/TimeRange.getMax:()J
      19: invokestatic  #25                 // Method org/junit/Assert.assertEquals:(JJ)V
      22: aload_1
      23: invokevirtual #46                 // Method org/apache/hadoop/hbase/io/TimeRange.isAllTime:()Z
      26: invokestatic  #7                  // Method org/junit/Assert.assertTrue:(Z)V
      29: new           #14                 // class org/apache/hadoop/hbase/io/TimeRange
      32: dup
      33: lconst_0
      34: invokespecial #16                 // Method org/apache/hadoop/hbase/io/TimeRange."<init>":(J)V
      37: astore_2
      38: lconst_0
      39: aload_2
      40: invokevirtual #24                 // Method org/apache/hadoop/hbase/io/TimeRange.getMin:()J
      43: invokestatic  #25                 // Method org/junit/Assert.assertEquals:(JJ)V
      46: ldc2_w        #41                 // long 9223372036854775807l
      49: aload_2
      50: invokevirtual #27                 // Method org/apache/hadoop/hbase/io/TimeRange.getMax:()J
      53: invokestatic  #25                 // Method org/junit/Assert.assertEquals:(JJ)V
      56: aload_2
      57: invokevirtual #46                 // Method org/apache/hadoop/hbase/io/TimeRange.isAllTime:()Z
      60: invokestatic  #7                  // Method org/junit/Assert.assertTrue:(Z)V
      63: new           #14                 // class org/apache/hadoop/hbase/io/TimeRange
      66: dup
      67: lconst_1
      68: invokespecial #16                 // Method org/apache/hadoop/hbase/io/TimeRange."<init>":(J)V
      71: astore_3
      72: lconst_1
      73: aload_3
      74: invokevirtual #24                 // Method org/apache/hadoop/hbase/io/TimeRange.getMin:()J
      77: invokestatic  #25                 // Method org/junit/Assert.assertEquals:(JJ)V
      80: ldc2_w        #41                 // long 9223372036854775807l
      83: aload_3
      84: invokevirtual #27                 // Method org/apache/hadoop/hbase/io/TimeRange.getMax:()J
      87: invokestatic  #25                 // Method org/junit/Assert.assertEquals:(JJ)V
      90: aload_3
      91: invokevirtual #46                 // Method org/apache/hadoop/hbase/io/TimeRange.isAllTime:()Z
      94: invokestatic  #10                 // Method org/junit/Assert.assertFalse:(Z)V
      97: new           #14                 // class org/apache/hadoop/hbase/io/TimeRange
     100: dup
     101: lconst_0
     102: ldc2_w        #41                 // long 9223372036854775807l
     105: invokespecial #47                 // Method org/apache/hadoop/hbase/io/TimeRange."<init>":(JJ)V
     108: astore        4
     110: lconst_0
     111: aload         4
     113: invokevirtual #24                 // Method org/apache/hadoop/hbase/io/TimeRange.getMin:()J
     116: invokestatic  #25                 // Method org/junit/Assert.assertEquals:(JJ)V
     119: ldc2_w        #41                 // long 9223372036854775807l
     122: aload         4
     124: invokevirtual #27                 // Method org/apache/hadoop/hbase/io/TimeRange.getMax:()J
     127: invokestatic  #25                 // Method org/junit/Assert.assertEquals:(JJ)V
     130: aload         4
     132: invokevirtual #46                 // Method org/apache/hadoop/hbase/io/TimeRange.isAllTime:()Z
     135: invokestatic  #7                  // Method org/junit/Assert.assertTrue:(Z)V
     138: new           #14                 // class org/apache/hadoop/hbase/io/TimeRange
     141: dup
     142: lconst_0
     143: ldc2_w        #48                 // long 9223372036854775806l
     146: invokespecial #47                 // Method org/apache/hadoop/hbase/io/TimeRange."<init>":(JJ)V
     149: astore        5
     151: lconst_0
     152: aload         5
     154: invokevirtual #24                 // Method org/apache/hadoop/hbase/io/TimeRange.getMin:()J
     157: invokestatic  #25                 // Method org/junit/Assert.assertEquals:(JJ)V
     160: ldc2_w        #48                 // long 9223372036854775806l
     163: aload         5
     165: invokevirtual #27                 // Method org/apache/hadoop/hbase/io/TimeRange.getMax:()J
     168: invokestatic  #25                 // Method org/junit/Assert.assertEquals:(JJ)V
     171: aload         5
     173: invokevirtual #46                 // Method org/apache/hadoop/hbase/io/TimeRange.isAllTime:()Z
     176: invokestatic  #10                 // Method org/junit/Assert.assertFalse:(Z)V
     179: new           #14                 // class org/apache/hadoop/hbase/io/TimeRange
     182: dup
     183: lconst_1
     184: ldc2_w        #41                 // long 9223372036854775807l
     187: invokespecial #47                 // Method org/apache/hadoop/hbase/io/TimeRange."<init>":(JJ)V
     190: astore        6
     192: lconst_1
     193: aload         6
     195: invokevirtual #24                 // Method org/apache/hadoop/hbase/io/TimeRange.getMin:()J
     198: invokestatic  #25                 // Method org/junit/Assert.assertEquals:(JJ)V
     201: ldc2_w        #41                 // long 9223372036854775807l
     204: aload         6
     206: invokevirtual #27                 // Method org/apache/hadoop/hbase/io/TimeRange.getMax:()J
     209: invokestatic  #25                 // Method org/junit/Assert.assertEquals:(JJ)V
     212: aload         6
     214: invokevirtual #46                 // Method org/apache/hadoop/hbase/io/TimeRange.isAllTime:()Z
     217: invokestatic  #10                 // Method org/junit/Assert.assertFalse:(Z)V
     220: return

  static {};
    Code:
       0: ldc           #50                 // class org/apache/hadoop/hbase/regionserver/TestSimpleTimeRangeTracker
       2: invokestatic  #51                 // Method org/apache/hadoop/hbase/HBaseClassTestRule.forClass:(Ljava/lang/Class;)Lorg/apache/hadoop/hbase/HBaseClassTestRule;
       5: putstatic     #52                 // Field CLASS_RULE:Lorg/apache/hadoop/hbase/HBaseClassTestRule;
       8: return
}
