Compiled from "TestStateMachineProcedure.java"
public class org.apache.hadoop.hbase.procedure2.TestStateMachineProcedure$TestSMProcedureBadRollback extends org.apache.hadoop.hbase.procedure2.StateMachineProcedure<org.apache.hadoop.hbase.procedure2.TestStateMachineProcedure$TestProcEnv, org.apache.hadoop.hbase.procedure2.TestStateMachineProcedure$TestSMProcedureState> {
  public org.apache.hadoop.hbase.procedure2.TestStateMachineProcedure$TestSMProcedureBadRollback();
    Code:
       0: aload_0
       1: invokespecial #1                  // Method org/apache/hadoop/hbase/procedure2/StateMachineProcedure."<init>":()V
       4: return

  protected org.apache.hadoop.hbase.procedure2.StateMachineProcedure$Flow executeFromState(org.apache.hadoop.hbase.procedure2.TestStateMachineProcedure$TestProcEnv, org.apache.hadoop.hbase.procedure2.TestStateMachineProcedure$TestSMProcedureState);
    Code:
       0: invokestatic  #2                  // Method org/apache/hadoop/hbase/procedure2/TestStateMachineProcedure.access$000:()Lorg/slf4j/Logger;
       3: new           #3                  // class java/lang/StringBuilder
       6: dup
       7: invokespecial #4                  // Method java/lang/StringBuilder."<init>":()V
      10: ldc           #5                  // String EXEC
      12: invokevirtual #6                  // Method java/lang/StringBuilder.append:(Ljava/lang/String;)Ljava/lang/StringBuilder;
      15: aload_2
      16: invokevirtual #7                  // Method java/lang/StringBuilder.append:(Ljava/lang/Object;)Ljava/lang/StringBuilder;
      19: ldc           #8                  // String
      21: invokevirtual #6                  // Method java/lang/StringBuilder.append:(Ljava/lang/String;)Ljava/lang/StringBuilder;
      24: aload_0
      25: invokevirtual #7                  // Method java/lang/StringBuilder.append:(Ljava/lang/Object;)Ljava/lang/StringBuilder;
      28: invokevirtual #9                  // Method java/lang/StringBuilder.toString:()Ljava/lang/String;
      31: invokeinterface #10,  2           // InterfaceMethod org/slf4j/Logger.info:(Ljava/lang/String;)V
      36: aload_1
      37: getfield      #11                 // Field org/apache/hadoop/hbase/procedure2/TestStateMachineProcedure$TestProcEnv.execCount:Ljava/util/concurrent/atomic/AtomicInteger;
      40: invokevirtual #12                 // Method java/util/concurrent/atomic/AtomicInteger.incrementAndGet:()I
      43: pop
      44: getstatic     #13                 // Field org/apache/hadoop/hbase/procedure2/TestStateMachineProcedure$2.$SwitchMap$org$apache$hadoop$hbase$procedure2$TestStateMachineProcedure$TestSMProcedureState:[I
      47: aload_2
      48: invokevirtual #14                 // Method org/apache/hadoop/hbase/procedure2/TestStateMachineProcedure$TestSMProcedureState.ordinal:()I
      51: iaload
      52: lookupswitch  { // 2
                     1: 80
                     2: 97
               default: 119
          }
      80: aload_1
      81: getfield      #15                 // Field org/apache/hadoop/hbase/procedure2/TestStateMachineProcedure$TestProcEnv.loop:Z
      84: ifne          119
      87: aload_0
      88: getstatic     #16                 // Field org/apache/hadoop/hbase/procedure2/TestStateMachineProcedure$TestSMProcedureState.STEP_2:Lorg/apache/hadoop/hbase/procedure2/TestStateMachineProcedure$TestSMProcedureState;
      91: invokevirtual #17                 // Method setNextState:(Ljava/lang/Object;)V
      94: goto          119
      97: aload_0
      98: iconst_1
      99: anewarray     #18                 // class org/apache/hadoop/hbase/procedure2/TestStateMachineProcedure$SimpleChildProcedure
     102: dup
     103: iconst_0
     104: new           #18                 // class org/apache/hadoop/hbase/procedure2/TestStateMachineProcedure$SimpleChildProcedure
     107: dup
     108: invokespecial #19                 // Method org/apache/hadoop/hbase/procedure2/TestStateMachineProcedure$SimpleChildProcedure."<init>":()V
     111: aastore
     112: invokevirtual #20                 // Method addChildProcedure:([Lorg/apache/hadoop/hbase/procedure2/Procedure;)V
     115: getstatic     #21                 // Field org/apache/hadoop/hbase/procedure2/StateMachineProcedure$Flow.NO_MORE_STATE:Lorg/apache/hadoop/hbase/procedure2/StateMachineProcedure$Flow;
     118: areturn
     119: getstatic     #22                 // Field org/apache/hadoop/hbase/procedure2/StateMachineProcedure$Flow.HAS_MORE_STATE:Lorg/apache/hadoop/hbase/procedure2/StateMachineProcedure$Flow;
     122: areturn

  protected void rollbackState(org.apache.hadoop.hbase.procedure2.TestStateMachineProcedure$TestProcEnv, org.apache.hadoop.hbase.procedure2.TestStateMachineProcedure$TestSMProcedureState);
    Code:
       0: invokestatic  #2                  // Method org/apache/hadoop/hbase/procedure2/TestStateMachineProcedure.access$000:()Lorg/slf4j/Logger;
       3: new           #3                  // class java/lang/StringBuilder
       6: dup
       7: invokespecial #4                  // Method java/lang/StringBuilder."<init>":()V
      10: ldc           #23                 // String ROLLBACK
      12: invokevirtual #6                  // Method java/lang/StringBuilder.append:(Ljava/lang/String;)Ljava/lang/StringBuilder;
      15: aload_2
      16: invokevirtual #7                  // Method java/lang/StringBuilder.append:(Ljava/lang/Object;)Ljava/lang/StringBuilder;
      19: ldc           #8                  // String
      21: invokevirtual #6                  // Method java/lang/StringBuilder.append:(Ljava/lang/String;)Ljava/lang/StringBuilder;
      24: aload_0
      25: invokevirtual #7                  // Method java/lang/StringBuilder.append:(Ljava/lang/Object;)Ljava/lang/StringBuilder;
      28: invokevirtual #9                  // Method java/lang/StringBuilder.toString:()Ljava/lang/String;
      31: invokeinterface #10,  2           // InterfaceMethod org/slf4j/Logger.info:(Ljava/lang/String;)V
      36: aload_1
      37: getfield      #24                 // Field org/apache/hadoop/hbase/procedure2/TestStateMachineProcedure$TestProcEnv.rollbackCount:Ljava/util/concurrent/atomic/AtomicInteger;
      40: invokevirtual #12                 // Method java/util/concurrent/atomic/AtomicInteger.incrementAndGet:()I
      43: pop
      44: return

  protected org.apache.hadoop.hbase.procedure2.TestStateMachineProcedure$TestSMProcedureState getState(int);
    Code:
       0: invokestatic  #25                 // Method org/apache/hadoop/hbase/procedure2/TestStateMachineProcedure$TestSMProcedureState.values:()[Lorg/apache/hadoop/hbase/procedure2/TestStateMachineProcedure$TestSMProcedureState;
       3: iload_1
       4: aaload
       5: areturn

  protected int getStateId(org.apache.hadoop.hbase.procedure2.TestStateMachineProcedure$TestSMProcedureState);
    Code:
       0: aload_1
       1: invokevirtual #14                 // Method org/apache/hadoop/hbase/procedure2/TestStateMachineProcedure$TestSMProcedureState.ordinal:()I
       4: ireturn

  protected org.apache.hadoop.hbase.procedure2.TestStateMachineProcedure$TestSMProcedureState getInitialState();
    Code:
       0: getstatic     #26                 // Field org/apache/hadoop/hbase/procedure2/TestStateMachineProcedure$TestSMProcedureState.STEP_1:Lorg/apache/hadoop/hbase/procedure2/TestStateMachineProcedure$TestSMProcedureState;
       3: areturn

  protected void rollback(org.apache.hadoop.hbase.procedure2.TestStateMachineProcedure$TestProcEnv) throws java.io.IOException, java.lang.InterruptedException;
    Code:
       0: aload_0
       1: invokevirtual #27                 // Method isEofState:()Z
       4: ifeq          17
       7: aload_0
       8: dup
       9: getfield      #28                 // Field stateCount:I
      12: iconst_1
      13: isub
      14: putfield      #28                 // Field stateCount:I
      17: aload_0
      18: invokevirtual #29                 // Method updateTimestamp:()V
      21: aload_0
      22: aload_1
      23: aload_0
      24: invokevirtual #30                 // Method getCurrentState:()Ljava/lang/Object;
      27: checkcast     #31                 // class org/apache/hadoop/hbase/procedure2/TestStateMachineProcedure$TestSMProcedureState
      30: invokevirtual #32                 // Method rollbackState:(Lorg/apache/hadoop/hbase/procedure2/TestStateMachineProcedure$TestProcEnv;Lorg/apache/hadoop/hbase/procedure2/TestStateMachineProcedure$TestSMProcedureState;)V
      33: new           #33                 // class java/io/IOException
      36: dup
      37: invokespecial #34                 // Method java/io/IOException."<init>":()V
      40: athrow
      41: astore_2
      42: aload_0
      43: dup
      44: getfield      #28                 // Field stateCount:I
      47: iconst_1
      48: isub
      49: putfield      #28                 // Field stateCount:I
      52: aload_0
      53: invokevirtual #29                 // Method updateTimestamp:()V
      56: goto          76
      59: astore_3
      60: aload_0
      61: dup
      62: getfield      #28                 // Field stateCount:I
      65: iconst_1
      66: isub
      67: putfield      #28                 // Field stateCount:I
      70: aload_0
      71: invokevirtual #29                 // Method updateTimestamp:()V
      74: aload_3
      75: athrow
      76: return
    Exception table:
       from    to  target type
          17    41    41   Class java/io/IOException
          17    42    59   any

  protected void rollback(java.lang.Object) throws java.io.IOException, java.lang.InterruptedException;
    Code:
       0: aload_0
       1: aload_1
       2: checkcast     #35                 // class org/apache/hadoop/hbase/procedure2/TestStateMachineProcedure$TestProcEnv
       5: invokevirtual #36                 // Method rollback:(Lorg/apache/hadoop/hbase/procedure2/TestStateMachineProcedure$TestProcEnv;)V
       8: return

  protected java.lang.Object getInitialState();
    Code:
       0: aload_0
       1: invokevirtual #37                 // Method getInitialState:()Lorg/apache/hadoop/hbase/procedure2/TestStateMachineProcedure$TestSMProcedureState;
       4: areturn

  protected int getStateId(java.lang.Object);
    Code:
       0: aload_0
       1: aload_1
       2: checkcast     #31                 // class org/apache/hadoop/hbase/procedure2/TestStateMachineProcedure$TestSMProcedureState
       5: invokevirtual #38                 // Method getStateId:(Lorg/apache/hadoop/hbase/procedure2/TestStateMachineProcedure$TestSMProcedureState;)I
       8: ireturn

  protected java.lang.Object getState(int);
    Code:
       0: aload_0
       1: iload_1
       2: invokevirtual #39                 // Method getState:(I)Lorg/apache/hadoop/hbase/procedure2/TestStateMachineProcedure$TestSMProcedureState;
       5: areturn

  protected void rollbackState(java.lang.Object, java.lang.Object) throws java.io.IOException, java.lang.InterruptedException;
    Code:
       0: aload_0
       1: aload_1
       2: checkcast     #35                 // class org/apache/hadoop/hbase/procedure2/TestStateMachineProcedure$TestProcEnv
       5: aload_2
       6: checkcast     #31                 // class org/apache/hadoop/hbase/procedure2/TestStateMachineProcedure$TestSMProcedureState
       9: invokevirtual #32                 // Method rollbackState:(Lorg/apache/hadoop/hbase/procedure2/TestStateMachineProcedure$TestProcEnv;Lorg/apache/hadoop/hbase/procedure2/TestStateMachineProcedure$TestSMProcedureState;)V
      12: return

  protected org.apache.hadoop.hbase.procedure2.StateMachineProcedure$Flow executeFromState(java.lang.Object, java.lang.Object) throws org.apache.hadoop.hbase.procedure2.ProcedureSuspendedException, org.apache.hadoop.hbase.procedure2.ProcedureYieldException, java.lang.InterruptedException;
    Code:
       0: aload_0
       1: aload_1
       2: checkcast     #35                 // class org/apache/hadoop/hbase/procedure2/TestStateMachineProcedure$TestProcEnv
       5: aload_2
       6: checkcast     #31                 // class org/apache/hadoop/hbase/procedure2/TestStateMachineProcedure$TestSMProcedureState
       9: invokevirtual #40                 // Method executeFromState:(Lorg/apache/hadoop/hbase/procedure2/TestStateMachineProcedure$TestProcEnv;Lorg/apache/hadoop/hbase/procedure2/TestStateMachineProcedure$TestSMProcedureState;)Lorg/apache/hadoop/hbase/procedure2/StateMachineProcedure$Flow;
      12: areturn
}
