Compiled from "TestMultiActionMetricsFromClient.java"
public class org.apache.hadoop.hbase.client.TestMultiActionMetricsFromClient {
  public static final org.apache.hadoop.hbase.HBaseClassTestRule CLASS_RULE;

  public org.apache.hadoop.hbase.client.TestMultiActionMetricsFromClient();
    Code:
       0: aload_0
       1: invokespecial #1                  // Method java/lang/Object."<init>":()V
       4: return

  public static void setUpBeforeClass() throws java.lang.Exception;
    Code:
       0: getstatic     #2                  // Field TEST_UTIL:Lorg/apache/hadoop/hbase/HBaseTestingUtility;
       3: iconst_1
       4: invokevirtual #3                  // Method org/apache/hadoop/hbase/HBaseTestingUtility.startMiniCluster:(I)Lorg/apache/hadoop/hbase/MiniHBaseCluster;
       7: pop
       8: getstatic     #2                  // Field TEST_UTIL:Lorg/apache/hadoop/hbase/HBaseTestingUtility;
      11: invokevirtual #4                  // Method org/apache/hadoop/hbase/HBaseTestingUtility.getHBaseCluster:()Lorg/apache/hadoop/hbase/MiniHBaseCluster;
      14: invokevirtual #5                  // Method org/apache/hadoop/hbase/MiniHBaseCluster.waitForActiveAndReadyMaster:()Z
      17: pop
      18: getstatic     #2                  // Field TEST_UTIL:Lorg/apache/hadoop/hbase/HBaseTestingUtility;
      21: getstatic     #6                  // Field TABLE_NAME:Lorg/apache/hadoop/hbase/TableName;
      24: pop
      25: getstatic     #7                  // Field org/apache/hadoop/hbase/TableName.META_TABLE_NAME:Lorg/apache/hadoop/hbase/TableName;
      28: invokevirtual #8                  // Method org/apache/hadoop/hbase/HBaseTestingUtility.waitUntilAllRegionsAssigned:(Lorg/apache/hadoop/hbase/TableName;)V
      31: getstatic     #2                  // Field TEST_UTIL:Lorg/apache/hadoop/hbase/HBaseTestingUtility;
      34: getstatic     #6                  // Field TABLE_NAME:Lorg/apache/hadoop/hbase/TableName;
      37: getstatic     #9                  // Field FAMILY:[B
      40: invokevirtual #10                 // Method org/apache/hadoop/hbase/HBaseTestingUtility.createTable:(Lorg/apache/hadoop/hbase/TableName;[B)Lorg/apache/hadoop/hbase/client/Table;
      43: pop
      44: return

  public static void tearDownAfterClass() throws java.lang.Exception;
    Code:
       0: getstatic     #2                  // Field TEST_UTIL:Lorg/apache/hadoop/hbase/HBaseTestingUtility;
       3: invokevirtual #11                 // Method org/apache/hadoop/hbase/HBaseTestingUtility.shutdownMiniCluster:()V
       6: return

  public void testMultiMetrics() throws java.lang.Exception;
    Code:
       0: new           #12                 // class org/apache/hadoop/conf/Configuration
       3: dup
       4: getstatic     #2                  // Field TEST_UTIL:Lorg/apache/hadoop/hbase/HBaseTestingUtility;
       7: invokevirtual #13                 // Method org/apache/hadoop/hbase/HBaseTestingUtility.getConfiguration:()Lorg/apache/hadoop/conf/Configuration;
      10: invokespecial #14                 // Method org/apache/hadoop/conf/Configuration."<init>":(Lorg/apache/hadoop/conf/Configuration;)V
      13: astore_1
      14: aload_1
      15: ldc           #16                 // String hbase.client.metrics.enable
      17: ldc           #17                 // String true
      19: invokevirtual #18                 // Method org/apache/hadoop/conf/Configuration.set:(Ljava/lang/String;Ljava/lang/String;)V
      22: aload_1
      23: invokestatic  #19                 // Method org/apache/hadoop/hbase/client/ConnectionFactory.createConnection:(Lorg/apache/hadoop/conf/Configuration;)Lorg/apache/hadoop/hbase/client/Connection;
      26: checkcast     #20                 // class org/apache/hadoop/hbase/client/ConnectionImplementation
      29: astore_2
      30: aload_2
      31: getstatic     #6                  // Field TABLE_NAME:Lorg/apache/hadoop/hbase/TableName;
      34: invokevirtual #21                 // Method org/apache/hadoop/hbase/client/ConnectionImplementation.getBufferedMutator:(Lorg/apache/hadoop/hbase/TableName;)Lorg/apache/hadoop/hbase/client/BufferedMutator;
      37: astore_3
      38: iconst_3
      39: anewarray     #22                 // class "[B"
      42: dup
      43: iconst_0
      44: ldc           #23                 // String aaa
      46: invokestatic  #24                 // Method org/apache/hadoop/hbase/util/Bytes.toBytes:(Ljava/lang/String;)[B
      49: aastore
      50: dup
      51: iconst_1
      52: ldc           #25                 // String mmm
      54: invokestatic  #24                 // Method org/apache/hadoop/hbase/util/Bytes.toBytes:(Ljava/lang/String;)[B
      57: aastore
      58: dup
      59: iconst_2
      60: ldc           #26                 // String zzz
      62: invokestatic  #24                 // Method org/apache/hadoop/hbase/util/Bytes.toBytes:(Ljava/lang/String;)[B
      65: aastore
      66: astore        4
      68: aload         4
      70: astore        5
      72: aload         5
      74: arraylength
      75: istore        6
      77: iconst_0
      78: istore        7
      80: iload         7
      82: iload         6
      84: if_icmpge     136
      87: aload         5
      89: iload         7
      91: aaload
      92: astore        8
      94: new           #27                 // class org/apache/hadoop/hbase/client/Put
      97: dup
      98: aload         8
     100: invokespecial #28                 // Method org/apache/hadoop/hbase/client/Put."<init>":([B)V
     103: astore        9
     105: aload         9
     107: getstatic     #9                  // Field FAMILY:[B
     110: getstatic     #29                 // Field QUALIFIER:[B
     113: bipush        10
     115: invokestatic  #30                 // Method org/apache/hadoop/hbase/util/Bytes.toBytes:(I)[B
     118: invokevirtual #31                 // Method org/apache/hadoop/hbase/client/Put.addColumn:([B[B[B)Lorg/apache/hadoop/hbase/client/Put;
     121: pop
     122: aload_3
     123: aload         9
     125: invokeinterface #32,  2           // InterfaceMethod org/apache/hadoop/hbase/client/BufferedMutator.mutate:(Lorg/apache/hadoop/hbase/client/Mutation;)V
     130: iinc          7, 1
     133: goto          80
     136: aload_3
     137: invokeinterface #33,  1           // InterfaceMethod org/apache/hadoop/hbase/client/BufferedMutator.flush:()V
     142: aload_3
     143: invokeinterface #34,  1           // InterfaceMethod org/apache/hadoop/hbase/client/BufferedMutator.close:()V
     148: aload_2
     149: invokevirtual #35                 // Method org/apache/hadoop/hbase/client/ConnectionImplementation.getConnectionMetrics:()Lorg/apache/hadoop/hbase/client/MetricsConnection;
     152: astore        5
     154: lconst_1
     155: aload         5
     157: getfield      #36                 // Field org/apache/hadoop/hbase/client/MetricsConnection.multiTracker:Lorg/apache/hadoop/hbase/client/MetricsConnection$CallTracker;
     160: getfield      #37                 // Field org/apache/hadoop/hbase/client/MetricsConnection$CallTracker.reqHist:Lcom/codahale/metrics/Histogram;
     163: invokevirtual #38                 // Method com/codahale/metrics/Histogram.getCount:()J
     166: invokestatic  #39                 // Method org/junit/Assert.assertEquals:(JJ)V
     169: ldc2_w        #40                 // double 3.0d
     172: aload         5
     174: getfield      #42                 // Field org/apache/hadoop/hbase/client/MetricsConnection.numActionsPerServerHist:Lcom/codahale/metrics/Histogram;
     177: invokevirtual #43                 // Method com/codahale/metrics/Histogram.getSnapshot:()Lcom/codahale/metrics/Snapshot;
     180: invokevirtual #44                 // Method com/codahale/metrics/Snapshot.getMean:()D
     183: ldc2_w        #45                 // double 1.0E-15d
     186: invokestatic  #47                 // Method org/junit/Assert.assertEquals:(DDD)V
     189: lconst_1
     190: aload         5
     192: getfield      #42                 // Field org/apache/hadoop/hbase/client/MetricsConnection.numActionsPerServerHist:Lcom/codahale/metrics/Histogram;
     195: invokevirtual #38                 // Method com/codahale/metrics/Histogram.getCount:()J
     198: invokestatic  #39                 // Method org/junit/Assert.assertEquals:(JJ)V
     201: aload_2
     202: invokevirtual #48                 // Method org/apache/hadoop/hbase/client/ConnectionImplementation.close:()V
     205: goto          217
     208: astore        10
     210: aload_2
     211: invokevirtual #48                 // Method org/apache/hadoop/hbase/client/ConnectionImplementation.close:()V
     214: aload         10
     216: athrow
     217: return
    Exception table:
       from    to  target type
          30   201   208   any
         208   210   208   any

  static {};
    Code:
       0: ldc           #49                 // class org/apache/hadoop/hbase/client/TestMultiActionMetricsFromClient
       2: invokestatic  #50                 // Method org/apache/hadoop/hbase/HBaseClassTestRule.forClass:(Ljava/lang/Class;)Lorg/apache/hadoop/hbase/HBaseClassTestRule;
       5: putstatic     #51                 // Field CLASS_RULE:Lorg/apache/hadoop/hbase/HBaseClassTestRule;
       8: new           #52                 // class org/apache/hadoop/hbase/HBaseTestingUtility
      11: dup
      12: invokespecial #53                 // Method org/apache/hadoop/hbase/HBaseTestingUtility."<init>":()V
      15: putstatic     #2                  // Field TEST_UTIL:Lorg/apache/hadoop/hbase/HBaseTestingUtility;
      18: ldc           #54                 // String test_table
      20: invokestatic  #55                 // Method org/apache/hadoop/hbase/TableName.valueOf:(Ljava/lang/String;)Lorg/apache/hadoop/hbase/TableName;
      23: putstatic     #6                  // Field TABLE_NAME:Lorg/apache/hadoop/hbase/TableName;
      26: ldc           #56                 // String fam1
      28: invokestatic  #24                 // Method org/apache/hadoop/hbase/util/Bytes.toBytes:(Ljava/lang/String;)[B
      31: putstatic     #9                  // Field FAMILY:[B
      34: ldc           #57                 // String qual
      36: invokestatic  #24                 // Method org/apache/hadoop/hbase/util/Bytes.toBytes:(Ljava/lang/String;)[B
      39: putstatic     #29                 // Field QUALIFIER:[B
      42: return
}
