Compiled from "TestMultiByteBuff.java"
public class org.apache.hadoop.hbase.nio.TestMultiByteBuff {
  public static final org.apache.hadoop.hbase.HBaseClassTestRule CLASS_RULE;

  public org.apache.hadoop.hbase.nio.TestMultiByteBuff();
    Code:
       0: aload_0
       1: invokespecial #1                  // Method java/lang/Object."<init>":()V
       4: return

  public void testGetShort();
    Code:
       0: iconst_1
       1: invokestatic  #2                  // Method java/nio/ByteBuffer.allocate:(I)Ljava/nio/ByteBuffer;
       4: astore_1
       5: aload_1
       6: iconst_1
       7: invokevirtual #3                  // Method java/nio/ByteBuffer.put:(B)Ljava/nio/ByteBuffer;
      10: pop
      11: iconst_1
      12: invokestatic  #2                  // Method java/nio/ByteBuffer.allocate:(I)Ljava/nio/ByteBuffer;
      15: astore_2
      16: aload_2
      17: iconst_0
      18: invokevirtual #3                  // Method java/nio/ByteBuffer.put:(B)Ljava/nio/ByteBuffer;
      21: pop
      22: iconst_1
      23: invokestatic  #2                  // Method java/nio/ByteBuffer.allocate:(I)Ljava/nio/ByteBuffer;
      26: astore_3
      27: aload_3
      28: iconst_2
      29: invokevirtual #3                  // Method java/nio/ByteBuffer.put:(B)Ljava/nio/ByteBuffer;
      32: pop
      33: iconst_1
      34: invokestatic  #2                  // Method java/nio/ByteBuffer.allocate:(I)Ljava/nio/ByteBuffer;
      37: astore        4
      39: aload         4
      41: iconst_3
      42: invokevirtual #3                  // Method java/nio/ByteBuffer.put:(B)Ljava/nio/ByteBuffer;
      45: pop
      46: new           #4                  // class org/apache/hadoop/hbase/nio/MultiByteBuff
      49: dup
      50: iconst_4
      51: anewarray     #5                  // class java/nio/ByteBuffer
      54: dup
      55: iconst_0
      56: aload_1
      57: aastore
      58: dup
      59: iconst_1
      60: aload_2
      61: aastore
      62: dup
      63: iconst_2
      64: aload_3
      65: aastore
      66: dup
      67: iconst_3
      68: aload         4
      70: aastore
      71: invokespecial #6                  // Method org/apache/hadoop/hbase/nio/MultiByteBuff."<init>":([Ljava/nio/ByteBuffer;)V
      74: astore        5
      76: ldc2_w        #7                  // long 256l
      79: aload         5
      81: iconst_0
      82: invokevirtual #9                  // Method org/apache/hadoop/hbase/nio/MultiByteBuff.getShortAfterPosition:(I)S
      85: i2l
      86: invokestatic  #10                 // Method org/junit/Assert.assertEquals:(JJ)V
      89: ldc2_w        #11                 // long 2l
      92: aload         5
      94: iconst_1
      95: invokevirtual #9                  // Method org/apache/hadoop/hbase/nio/MultiByteBuff.getShortAfterPosition:(I)S
      98: i2l
      99: invokestatic  #10                 // Method org/junit/Assert.assertEquals:(JJ)V
     102: ldc2_w        #13                 // long 515l
     105: aload         5
     107: iconst_2
     108: invokevirtual #9                  // Method org/apache/hadoop/hbase/nio/MultiByteBuff.getShortAfterPosition:(I)S
     111: i2l
     112: invokestatic  #10                 // Method org/junit/Assert.assertEquals:(JJ)V
     115: return

  public void testWritesAndReads();
    Code:
       0: bipush        15
       2: invokestatic  #2                  // Method java/nio/ByteBuffer.allocate:(I)Ljava/nio/ByteBuffer;
       5: astore_1
       6: bipush        15
       8: invokestatic  #2                  // Method java/nio/ByteBuffer.allocate:(I)Ljava/nio/ByteBuffer;
      11: astore_2
      12: iconst_4
      13: istore_3
      14: aload_1
      15: iload_3
      16: invokevirtual #15                 // Method java/nio/ByteBuffer.putInt:(I)Ljava/nio/ByteBuffer;
      19: pop
      20: ldc2_w        #16                 // long 45l
      23: lstore        4
      25: ldc2_w        #18                 // long 100l
      28: lstore        6
      30: ldc2_w        #20                 // long 12345l
      33: lstore        8
      35: aload_1
      36: lload         4
      38: invokevirtual #22                 // Method java/nio/ByteBuffer.putLong:(J)Ljava/nio/ByteBuffer;
      41: pop
      42: iconst_2
      43: istore        10
      45: aload_1
      46: iload         10
      48: invokevirtual #23                 // Method java/nio/ByteBuffer.putShort:(S)Ljava/nio/ByteBuffer;
      51: pop
      52: lload         6
      54: invokestatic  #24                 // Method org/apache/hadoop/hbase/util/Bytes.toBytes:(J)[B
      57: astore        11
      59: aload_1
      60: aload         11
      62: iconst_0
      63: iconst_1
      64: invokevirtual #25                 // Method java/nio/ByteBuffer.put:([BII)Ljava/nio/ByteBuffer;
      67: pop
      68: aload_2
      69: aload         11
      71: iconst_1
      72: bipush        7
      74: invokevirtual #25                 // Method java/nio/ByteBuffer.put:([BII)Ljava/nio/ByteBuffer;
      77: pop
      78: aload_2
      79: lload         8
      81: invokevirtual #22                 // Method java/nio/ByteBuffer.putLong:(J)Ljava/nio/ByteBuffer;
      84: pop
      85: new           #4                  // class org/apache/hadoop/hbase/nio/MultiByteBuff
      88: dup
      89: iconst_2
      90: anewarray     #5                  // class java/nio/ByteBuffer
      93: dup
      94: iconst_0
      95: aload_1
      96: aastore
      97: dup
      98: iconst_1
      99: aload_2
     100: aastore
     101: invokespecial #6                  // Method org/apache/hadoop/hbase/nio/MultiByteBuff."<init>":([Ljava/nio/ByteBuffer;)V
     104: astore        12
     106: lload         4
     108: aload         12
     110: iconst_4
     111: invokevirtual #26                 // Method org/apache/hadoop/hbase/nio/MultiByteBuff.getLong:(I)J
     114: invokestatic  #10                 // Method org/junit/Assert.assertEquals:(JJ)V
     117: lload         6
     119: aload         12
     121: bipush        14
     123: invokevirtual #26                 // Method org/apache/hadoop/hbase/nio/MultiByteBuff.getLong:(I)J
     126: invokestatic  #10                 // Method org/junit/Assert.assertEquals:(JJ)V
     129: lload         8
     131: aload         12
     133: bipush        22
     135: invokevirtual #26                 // Method org/apache/hadoop/hbase/nio/MultiByteBuff.getLong:(I)J
     138: invokestatic  #10                 // Method org/junit/Assert.assertEquals:(JJ)V
     141: iload_3
     142: i2l
     143: aload         12
     145: iconst_0
     146: invokevirtual #27                 // Method org/apache/hadoop/hbase/nio/MultiByteBuff.getInt:(I)I
     149: i2l
     150: invokestatic  #10                 // Method org/junit/Assert.assertEquals:(JJ)V
     153: iload         10
     155: i2l
     156: aload         12
     158: bipush        12
     160: invokevirtual #28                 // Method org/apache/hadoop/hbase/nio/MultiByteBuff.getShort:(I)S
     163: i2l
     164: invokestatic  #10                 // Method org/junit/Assert.assertEquals:(JJ)V
     167: iload_3
     168: i2l
     169: aload         12
     171: invokevirtual #29                 // Method org/apache/hadoop/hbase/nio/MultiByteBuff.getInt:()I
     174: i2l
     175: invokestatic  #10                 // Method org/junit/Assert.assertEquals:(JJ)V
     178: lload         4
     180: aload         12
     182: invokevirtual #30                 // Method org/apache/hadoop/hbase/nio/MultiByteBuff.getLong:()J
     185: invokestatic  #10                 // Method org/junit/Assert.assertEquals:(JJ)V
     188: iload         10
     190: i2l
     191: aload         12
     193: invokevirtual #31                 // Method org/apache/hadoop/hbase/nio/MultiByteBuff.getShort:()S
     196: i2l
     197: invokestatic  #10                 // Method org/junit/Assert.assertEquals:(JJ)V
     200: lload         6
     202: aload         12
     204: invokevirtual #30                 // Method org/apache/hadoop/hbase/nio/MultiByteBuff.getLong:()J
     207: invokestatic  #10                 // Method org/junit/Assert.assertEquals:(JJ)V
     210: lload         8
     212: aload         12
     214: invokevirtual #30                 // Method org/apache/hadoop/hbase/nio/MultiByteBuff.getLong:()J
     217: invokestatic  #10                 // Method org/junit/Assert.assertEquals:(JJ)V
     220: bipush        15
     222: invokestatic  #2                  // Method java/nio/ByteBuffer.allocate:(I)Ljava/nio/ByteBuffer;
     225: astore_1
     226: bipush        15
     228: invokestatic  #2                  // Method java/nio/ByteBuffer.allocate:(I)Ljava/nio/ByteBuffer;
     231: astore_2
     232: new           #4                  // class org/apache/hadoop/hbase/nio/MultiByteBuff
     235: dup
     236: iconst_2
     237: anewarray     #5                  // class java/nio/ByteBuffer
     240: dup
     241: iconst_0
     242: aload_1
     243: aastore
     244: dup
     245: iconst_1
     246: aload_2
     247: aastore
     248: invokespecial #6                  // Method org/apache/hadoop/hbase/nio/MultiByteBuff."<init>":([Ljava/nio/ByteBuffer;)V
     251: astore        12
     253: iconst_5
     254: istore        13
     256: bipush        31
     258: istore        14
     260: aload         12
     262: iload         13
     264: invokevirtual #32                 // Method org/apache/hadoop/hbase/nio/MultiByteBuff.put:(B)Lorg/apache/hadoop/hbase/nio/MultiByteBuff;
     267: pop
     268: aload         12
     270: lload         4
     272: invokevirtual #33                 // Method org/apache/hadoop/hbase/nio/MultiByteBuff.putLong:(J)Lorg/apache/hadoop/hbase/nio/MultiByteBuff;
     275: pop
     276: aload         12
     278: iload_3
     279: invokevirtual #34                 // Method org/apache/hadoop/hbase/nio/MultiByteBuff.putInt:(I)Lorg/apache/hadoop/hbase/nio/MultiByteBuff;
     282: pop
     283: aload         12
     285: lload         6
     287: invokevirtual #33                 // Method org/apache/hadoop/hbase/nio/MultiByteBuff.putLong:(J)Lorg/apache/hadoop/hbase/nio/MultiByteBuff;
     290: pop
     291: aload         12
     293: iload         14
     295: invokevirtual #32                 // Method org/apache/hadoop/hbase/nio/MultiByteBuff.put:(B)Lorg/apache/hadoop/hbase/nio/MultiByteBuff;
     298: pop
     299: aload         12
     301: aload         12
     303: invokevirtual #35                 // Method org/apache/hadoop/hbase/nio/MultiByteBuff.position:()I
     306: iconst_2
     307: iadd
     308: invokevirtual #36                 // Method org/apache/hadoop/hbase/nio/MultiByteBuff.position:(I)Lorg/apache/hadoop/hbase/nio/MultiByteBuff;
     311: pop
     312: aload         12
     314: lload         8
     316: invokevirtual #33                 // Method org/apache/hadoop/hbase/nio/MultiByteBuff.putLong:(J)Lorg/apache/hadoop/hbase/nio/MultiByteBuff;
     319: pop
     320: ldc           #37                 // String 'Should have thrown BufferOverflowException
     322: invokestatic  #38                 // Method org/junit/Assert.fail:(Ljava/lang/String;)V
     325: goto          330
     328: astore        15
     330: aload         12
     332: aload         12
     334: invokevirtual #35                 // Method org/apache/hadoop/hbase/nio/MultiByteBuff.position:()I
     337: iconst_2
     338: isub
     339: invokevirtual #36                 // Method org/apache/hadoop/hbase/nio/MultiByteBuff.position:(I)Lorg/apache/hadoop/hbase/nio/MultiByteBuff;
     342: pop
     343: aload         12
     345: lload         8
     347: invokevirtual #33                 // Method org/apache/hadoop/hbase/nio/MultiByteBuff.putLong:(J)Lorg/apache/hadoop/hbase/nio/MultiByteBuff;
     350: pop
     351: aload         12
     353: invokevirtual #40                 // Method org/apache/hadoop/hbase/nio/MultiByteBuff.rewind:()Lorg/apache/hadoop/hbase/nio/MultiByteBuff;
     356: pop
     357: iload         13
     359: i2l
     360: aload         12
     362: invokevirtual #41                 // Method org/apache/hadoop/hbase/nio/MultiByteBuff.get:()B
     365: i2l
     366: invokestatic  #10                 // Method org/junit/Assert.assertEquals:(JJ)V
     369: lload         4
     371: aload         12
     373: invokevirtual #30                 // Method org/apache/hadoop/hbase/nio/MultiByteBuff.getLong:()J
     376: invokestatic  #10                 // Method org/junit/Assert.assertEquals:(JJ)V
     379: iload_3
     380: i2l
     381: aload         12
     383: invokevirtual #29                 // Method org/apache/hadoop/hbase/nio/MultiByteBuff.getInt:()I
     386: i2l
     387: invokestatic  #10                 // Method org/junit/Assert.assertEquals:(JJ)V
     390: lload         6
     392: aload         12
     394: invokevirtual #30                 // Method org/apache/hadoop/hbase/nio/MultiByteBuff.getLong:()J
     397: invokestatic  #10                 // Method org/junit/Assert.assertEquals:(JJ)V
     400: iload         14
     402: i2l
     403: aload         12
     405: invokevirtual #41                 // Method org/apache/hadoop/hbase/nio/MultiByteBuff.get:()B
     408: i2l
     409: invokestatic  #10                 // Method org/junit/Assert.assertEquals:(JJ)V
     412: lload         8
     414: aload         12
     416: invokevirtual #30                 // Method org/apache/hadoop/hbase/nio/MultiByteBuff.getLong:()J
     419: invokestatic  #10                 // Method org/junit/Assert.assertEquals:(JJ)V
     422: aload         12
     424: bipush        21
     426: iload         13
     428: invokevirtual #42                 // Method org/apache/hadoop/hbase/nio/MultiByteBuff.put:(IB)Lorg/apache/hadoop/hbase/nio/MultiByteBuff;
     431: pop
     432: aload         12
     434: bipush        21
     436: invokevirtual #36                 // Method org/apache/hadoop/hbase/nio/MultiByteBuff.position:(I)Lorg/apache/hadoop/hbase/nio/MultiByteBuff;
     439: pop
     440: iload         13
     442: i2l
     443: aload         12
     445: invokevirtual #41                 // Method org/apache/hadoop/hbase/nio/MultiByteBuff.get:()B
     448: i2l
     449: invokestatic  #10                 // Method org/junit/Assert.assertEquals:(JJ)V
     452: aload         12
     454: aload         11
     456: invokevirtual #43                 // Method org/apache/hadoop/hbase/nio/MultiByteBuff.put:([B)Lorg/apache/hadoop/hbase/nio/MultiByteBuff;
     459: pop
     460: lload         6
     462: aload         12
     464: bipush        22
     466: invokevirtual #26                 // Method org/apache/hadoop/hbase/nio/MultiByteBuff.getLong:(I)J
     469: invokestatic  #10                 // Method org/junit/Assert.assertEquals:(JJ)V
     472: return
    Exception table:
       from    to  target type
         312   325   328   Class java/nio/BufferOverflowException

  public void testPutPrimitives();
    Code:
       0: bipush        10
       2: invokestatic  #2                  // Method java/nio/ByteBuffer.allocate:(I)Ljava/nio/ByteBuffer;
       5: astore_1
       6: new           #44                 // class org/apache/hadoop/hbase/nio/SingleByteBuff
       9: dup
      10: aload_1
      11: invokespecial #45                 // Method org/apache/hadoop/hbase/nio/SingleByteBuff."<init>":(Ljava/nio/ByteBuffer;)V
      14: astore_2
      15: aload_2
      16: ldc2_w        #46                 // long -4465109508325701663l
      19: invokevirtual #48                 // Method org/apache/hadoop/hbase/nio/SingleByteBuff.putLong:(J)Lorg/apache/hadoop/hbase/nio/SingleByteBuff;
      22: pop
      23: aload_1
      24: invokevirtual #49                 // Method java/nio/ByteBuffer.rewind:()Ljava/nio/Buffer;
      27: pop
      28: aload_1
      29: invokevirtual #50                 // Method java/nio/ByteBuffer.getLong:()J
      32: lstore_3
      33: ldc2_w        #46                 // long -4465109508325701663l
      36: lload_3
      37: invokestatic  #10                 // Method org/junit/Assert.assertEquals:(JJ)V
      40: aload_2
      41: bipush        8
      43: invokevirtual #51                 // Method org/apache/hadoop/hbase/nio/SingleByteBuff.position:(I)Lorg/apache/hadoop/hbase/nio/SingleByteBuff;
      46: pop
      47: return

  public void testArrayBasedMethods();
    Code:
       0: bipush        15
       2: newarray       byte
       4: astore_1
       5: aload_1
       6: iconst_1
       7: bipush        10
       9: invokestatic  #52                 // Method java/nio/ByteBuffer.wrap:([BII)Ljava/nio/ByteBuffer;
      12: invokevirtual #53                 // Method java/nio/ByteBuffer.slice:()Ljava/nio/ByteBuffer;
      15: astore_2
      16: bipush        15
      18: invokestatic  #2                  // Method java/nio/ByteBuffer.allocate:(I)Ljava/nio/ByteBuffer;
      21: astore_3
      22: new           #4                  // class org/apache/hadoop/hbase/nio/MultiByteBuff
      25: dup
      26: iconst_2
      27: anewarray     #5                  // class java/nio/ByteBuffer
      30: dup
      31: iconst_0
      32: aload_2
      33: aastore
      34: dup
      35: iconst_1
      36: aload_3
      37: aastore
      38: invokespecial #6                  // Method org/apache/hadoop/hbase/nio/MultiByteBuff."<init>":([Ljava/nio/ByteBuffer;)V
      41: astore        4
      43: aload         4
      45: invokevirtual #54                 // Method org/apache/hadoop/hbase/nio/ByteBuff.hasArray:()Z
      48: invokestatic  #55                 // Method org/junit/Assert.assertFalse:(Z)V
      51: aload         4
      53: invokevirtual #56                 // Method org/apache/hadoop/hbase/nio/ByteBuff.array:()[B
      56: pop
      57: invokestatic  #57                 // Method org/junit/Assert.fail:()V
      60: goto          65
      63: astore        5
      65: aload         4
      67: invokevirtual #59                 // Method org/apache/hadoop/hbase/nio/ByteBuff.arrayOffset:()I
      70: pop
      71: invokestatic  #57                 // Method org/junit/Assert.fail:()V
      74: goto          79
      77: astore        5
      79: new           #44                 // class org/apache/hadoop/hbase/nio/SingleByteBuff
      82: dup
      83: aload_2
      84: invokespecial #45                 // Method org/apache/hadoop/hbase/nio/SingleByteBuff."<init>":(Ljava/nio/ByteBuffer;)V
      87: astore        4
      89: aload         4
      91: invokevirtual #54                 // Method org/apache/hadoop/hbase/nio/ByteBuff.hasArray:()Z
      94: invokestatic  #60                 // Method org/junit/Assert.assertTrue:(Z)V
      97: lconst_1
      98: aload         4
     100: invokevirtual #59                 // Method org/apache/hadoop/hbase/nio/ByteBuff.arrayOffset:()I
     103: i2l
     104: invokestatic  #10                 // Method org/junit/Assert.assertEquals:(JJ)V
     107: aload_1
     108: aload         4
     110: invokevirtual #56                 // Method org/apache/hadoop/hbase/nio/ByteBuff.array:()[B
     113: invokestatic  #61                 // Method org/junit/Assert.assertEquals:(Ljava/lang/Object;Ljava/lang/Object;)V
     116: new           #44                 // class org/apache/hadoop/hbase/nio/SingleByteBuff
     119: dup
     120: bipush        10
     122: invokestatic  #62                 // Method java/nio/ByteBuffer.allocateDirect:(I)Ljava/nio/ByteBuffer;
     125: invokespecial #45                 // Method org/apache/hadoop/hbase/nio/SingleByteBuff."<init>":(Ljava/nio/ByteBuffer;)V
     128: astore        4
     130: aload         4
     132: invokevirtual #54                 // Method org/apache/hadoop/hbase/nio/ByteBuff.hasArray:()Z
     135: invokestatic  #55                 // Method org/junit/Assert.assertFalse:(Z)V
     138: aload         4
     140: invokevirtual #56                 // Method org/apache/hadoop/hbase/nio/ByteBuff.array:()[B
     143: pop
     144: invokestatic  #57                 // Method org/junit/Assert.fail:()V
     147: goto          152
     150: astore        5
     152: aload         4
     154: invokevirtual #59                 // Method org/apache/hadoop/hbase/nio/ByteBuff.arrayOffset:()I
     157: pop
     158: invokestatic  #57                 // Method org/junit/Assert.fail:()V
     161: goto          166
     164: astore        5
     166: return
    Exception table:
       from    to  target type
          51    60    63   Class java/lang/UnsupportedOperationException
          65    74    77   Class java/lang/UnsupportedOperationException
         138   147   150   Class java/lang/UnsupportedOperationException
         152   161   164   Class java/lang/UnsupportedOperationException

  public void testMarkAndResetWithMBB();
    Code:
       0: bipush        15
       2: invokestatic  #62                 // Method java/nio/ByteBuffer.allocateDirect:(I)Ljava/nio/ByteBuffer;
       5: astore_1
       6: bipush        15
       8: invokestatic  #62                 // Method java/nio/ByteBuffer.allocateDirect:(I)Ljava/nio/ByteBuffer;
      11: astore_2
      12: aload_1
      13: iconst_4
      14: invokevirtual #15                 // Method java/nio/ByteBuffer.putInt:(I)Ljava/nio/ByteBuffer;
      17: pop
      18: ldc2_w        #16                 // long 45l
      21: lstore_3
      22: ldc2_w        #18                 // long 100l
      25: lstore        5
      27: ldc2_w        #20                 // long 12345l
      30: lstore        7
      32: aload_1
      33: lload_3
      34: invokevirtual #22                 // Method java/nio/ByteBuffer.putLong:(J)Ljava/nio/ByteBuffer;
      37: pop
      38: aload_1
      39: iconst_2
      40: invokevirtual #23                 // Method java/nio/ByteBuffer.putShort:(S)Ljava/nio/ByteBuffer;
      43: pop
      44: lload         5
      46: invokestatic  #24                 // Method org/apache/hadoop/hbase/util/Bytes.toBytes:(J)[B
      49: astore        9
      51: aload_1
      52: aload         9
      54: iconst_0
      55: iconst_1
      56: invokevirtual #25                 // Method java/nio/ByteBuffer.put:([BII)Ljava/nio/ByteBuffer;
      59: pop
      60: aload_2
      61: aload         9
      63: iconst_1
      64: bipush        7
      66: invokevirtual #25                 // Method java/nio/ByteBuffer.put:([BII)Ljava/nio/ByteBuffer;
      69: pop
      70: aload_2
      71: lload         7
      73: invokevirtual #22                 // Method java/nio/ByteBuffer.putLong:(J)Ljava/nio/ByteBuffer;
      76: pop
      77: new           #4                  // class org/apache/hadoop/hbase/nio/MultiByteBuff
      80: dup
      81: iconst_2
      82: anewarray     #5                  // class java/nio/ByteBuffer
      85: dup
      86: iconst_0
      87: aload_1
      88: aastore
      89: dup
      90: iconst_1
      91: aload_2
      92: aastore
      93: invokespecial #6                  // Method org/apache/hadoop/hbase/nio/MultiByteBuff."<init>":([Ljava/nio/ByteBuffer;)V
      96: astore        10
      98: ldc2_w        #63                 // long 4l
     101: aload         10
     103: invokevirtual #65                 // Method org/apache/hadoop/hbase/nio/ByteBuff.getInt:()I
     106: i2l
     107: invokestatic  #10                 // Method org/junit/Assert.assertEquals:(JJ)V
     110: lload_3
     111: aload         10
     113: invokevirtual #66                 // Method org/apache/hadoop/hbase/nio/ByteBuff.getLong:()J
     116: invokestatic  #10                 // Method org/junit/Assert.assertEquals:(JJ)V
     119: aload         10
     121: invokevirtual #67                 // Method org/apache/hadoop/hbase/nio/ByteBuff.mark:()Lorg/apache/hadoop/hbase/nio/ByteBuff;
     124: pop
     125: ldc2_w        #11                 // long 2l
     128: aload         10
     130: invokevirtual #68                 // Method org/apache/hadoop/hbase/nio/ByteBuff.getShort:()S
     133: i2l
     134: invokestatic  #10                 // Method org/junit/Assert.assertEquals:(JJ)V
     137: aload         10
     139: invokevirtual #69                 // Method org/apache/hadoop/hbase/nio/ByteBuff.reset:()Lorg/apache/hadoop/hbase/nio/ByteBuff;
     142: pop
     143: ldc2_w        #11                 // long 2l
     146: aload         10
     148: invokevirtual #68                 // Method org/apache/hadoop/hbase/nio/ByteBuff.getShort:()S
     151: i2l
     152: invokestatic  #10                 // Method org/junit/Assert.assertEquals:(JJ)V
     155: aload         10
     157: invokevirtual #67                 // Method org/apache/hadoop/hbase/nio/ByteBuff.mark:()Lorg/apache/hadoop/hbase/nio/ByteBuff;
     160: pop
     161: lload         5
     163: aload         10
     165: invokevirtual #66                 // Method org/apache/hadoop/hbase/nio/ByteBuff.getLong:()J
     168: invokestatic  #10                 // Method org/junit/Assert.assertEquals:(JJ)V
     171: aload         10
     173: invokevirtual #69                 // Method org/apache/hadoop/hbase/nio/ByteBuff.reset:()Lorg/apache/hadoop/hbase/nio/ByteBuff;
     176: pop
     177: lload         5
     179: aload         10
     181: invokevirtual #66                 // Method org/apache/hadoop/hbase/nio/ByteBuff.getLong:()J
     184: invokestatic  #10                 // Method org/junit/Assert.assertEquals:(JJ)V
     187: aload         10
     189: invokevirtual #67                 // Method org/apache/hadoop/hbase/nio/ByteBuff.mark:()Lorg/apache/hadoop/hbase/nio/ByteBuff;
     192: pop
     193: lload         7
     195: aload         10
     197: invokevirtual #66                 // Method org/apache/hadoop/hbase/nio/ByteBuff.getLong:()J
     200: invokestatic  #10                 // Method org/junit/Assert.assertEquals:(JJ)V
     203: aload         10
     205: invokevirtual #69                 // Method org/apache/hadoop/hbase/nio/ByteBuff.reset:()Lorg/apache/hadoop/hbase/nio/ByteBuff;
     208: pop
     209: lload         7
     211: aload         10
     213: invokevirtual #66                 // Method org/apache/hadoop/hbase/nio/ByteBuff.getLong:()J
     216: invokestatic  #10                 // Method org/junit/Assert.assertEquals:(JJ)V
     219: aload         10
     221: invokevirtual #67                 // Method org/apache/hadoop/hbase/nio/ByteBuff.mark:()Lorg/apache/hadoop/hbase/nio/ByteBuff;
     224: pop
     225: lload         5
     227: aload         10
     229: bipush        14
     231: invokevirtual #70                 // Method org/apache/hadoop/hbase/nio/ByteBuff.getLong:(I)J
     234: invokestatic  #10                 // Method org/junit/Assert.assertEquals:(JJ)V
     237: aload         10
     239: invokevirtual #69                 // Method org/apache/hadoop/hbase/nio/ByteBuff.reset:()Lorg/apache/hadoop/hbase/nio/ByteBuff;
     242: pop
     243: lload         7
     245: aload         10
     247: bipush        22
     249: invokevirtual #70                 // Method org/apache/hadoop/hbase/nio/ByteBuff.getLong:(I)J
     252: invokestatic  #10                 // Method org/junit/Assert.assertEquals:(JJ)V
     255: aload         10
     257: invokevirtual #69                 // Method org/apache/hadoop/hbase/nio/ByteBuff.reset:()Lorg/apache/hadoop/hbase/nio/ByteBuff;
     260: pop
     261: lload         5
     263: aload         10
     265: bipush        14
     267: invokevirtual #70                 // Method org/apache/hadoop/hbase/nio/ByteBuff.getLong:(I)J
     270: invokestatic  #10                 // Method org/junit/Assert.assertEquals:(JJ)V
     273: aload         10
     275: invokevirtual #67                 // Method org/apache/hadoop/hbase/nio/ByteBuff.mark:()Lorg/apache/hadoop/hbase/nio/ByteBuff;
     278: pop
     279: lload         7
     281: aload         10
     283: bipush        22
     285: invokevirtual #70                 // Method org/apache/hadoop/hbase/nio/ByteBuff.getLong:(I)J
     288: invokestatic  #10                 // Method org/junit/Assert.assertEquals:(JJ)V
     291: aload         10
     293: invokevirtual #69                 // Method org/apache/hadoop/hbase/nio/ByteBuff.reset:()Lorg/apache/hadoop/hbase/nio/ByteBuff;
     296: pop
     297: return

  public void testSkipNBytes();
    Code:
       0: bipush        15
       2: invokestatic  #2                  // Method java/nio/ByteBuffer.allocate:(I)Ljava/nio/ByteBuffer;
       5: astore_1
       6: bipush        15
       8: invokestatic  #2                  // Method java/nio/ByteBuffer.allocate:(I)Ljava/nio/ByteBuffer;
      11: astore_2
      12: aload_1
      13: iconst_4
      14: invokevirtual #15                 // Method java/nio/ByteBuffer.putInt:(I)Ljava/nio/ByteBuffer;
      17: pop
      18: ldc2_w        #16                 // long 45l
      21: lstore_3
      22: ldc2_w        #18                 // long 100l
      25: lstore        5
      27: ldc2_w        #20                 // long 12345l
      30: lstore        7
      32: aload_1
      33: lload_3
      34: invokevirtual #22                 // Method java/nio/ByteBuffer.putLong:(J)Ljava/nio/ByteBuffer;
      37: pop
      38: aload_1
      39: iconst_2
      40: invokevirtual #23                 // Method java/nio/ByteBuffer.putShort:(S)Ljava/nio/ByteBuffer;
      43: pop
      44: lload         5
      46: invokestatic  #24                 // Method org/apache/hadoop/hbase/util/Bytes.toBytes:(J)[B
      49: astore        9
      51: aload_1
      52: aload         9
      54: iconst_0
      55: iconst_1
      56: invokevirtual #25                 // Method java/nio/ByteBuffer.put:([BII)Ljava/nio/ByteBuffer;
      59: pop
      60: aload_2
      61: aload         9
      63: iconst_1
      64: bipush        7
      66: invokevirtual #25                 // Method java/nio/ByteBuffer.put:([BII)Ljava/nio/ByteBuffer;
      69: pop
      70: aload_2
      71: lload         7
      73: invokevirtual #22                 // Method java/nio/ByteBuffer.putLong:(J)Ljava/nio/ByteBuffer;
      76: pop
      77: new           #4                  // class org/apache/hadoop/hbase/nio/MultiByteBuff
      80: dup
      81: iconst_2
      82: anewarray     #5                  // class java/nio/ByteBuffer
      85: dup
      86: iconst_0
      87: aload_1
      88: aastore
      89: dup
      90: iconst_1
      91: aload_2
      92: aastore
      93: invokespecial #6                  // Method org/apache/hadoop/hbase/nio/MultiByteBuff."<init>":([Ljava/nio/ByteBuffer;)V
      96: astore        10
      98: ldc2_w        #63                 // long 4l
     101: aload         10
     103: invokevirtual #29                 // Method org/apache/hadoop/hbase/nio/MultiByteBuff.getInt:()I
     106: i2l
     107: invokestatic  #10                 // Method org/junit/Assert.assertEquals:(JJ)V
     110: lload_3
     111: aload         10
     113: invokevirtual #30                 // Method org/apache/hadoop/hbase/nio/MultiByteBuff.getLong:()J
     116: invokestatic  #10                 // Method org/junit/Assert.assertEquals:(JJ)V
     119: aload         10
     121: bipush        10
     123: invokevirtual #71                 // Method org/apache/hadoop/hbase/nio/MultiByteBuff.skip:(I)Lorg/apache/hadoop/hbase/nio/MultiByteBuff;
     126: pop
     127: lload         7
     129: aload         10
     131: invokevirtual #30                 // Method org/apache/hadoop/hbase/nio/MultiByteBuff.getLong:()J
     134: invokestatic  #10                 // Method org/junit/Assert.assertEquals:(JJ)V
     137: return

  public void testMoveBack();
    Code:
       0: bipush        15
       2: invokestatic  #2                  // Method java/nio/ByteBuffer.allocate:(I)Ljava/nio/ByteBuffer;
       5: astore_1
       6: bipush        15
       8: invokestatic  #2                  // Method java/nio/ByteBuffer.allocate:(I)Ljava/nio/ByteBuffer;
      11: astore_2
      12: aload_1
      13: iconst_4
      14: invokevirtual #15                 // Method java/nio/ByteBuffer.putInt:(I)Ljava/nio/ByteBuffer;
      17: pop
      18: ldc2_w        #16                 // long 45l
      21: lstore_3
      22: ldc2_w        #18                 // long 100l
      25: lstore        5
      27: ldc2_w        #20                 // long 12345l
      30: lstore        7
      32: aload_1
      33: lload_3
      34: invokevirtual #22                 // Method java/nio/ByteBuffer.putLong:(J)Ljava/nio/ByteBuffer;
      37: pop
      38: aload_1
      39: iconst_2
      40: invokevirtual #23                 // Method java/nio/ByteBuffer.putShort:(S)Ljava/nio/ByteBuffer;
      43: pop
      44: lload         5
      46: invokestatic  #24                 // Method org/apache/hadoop/hbase/util/Bytes.toBytes:(J)[B
      49: astore        9
      51: aload_1
      52: aload         9
      54: iconst_0
      55: iconst_1
      56: invokevirtual #25                 // Method java/nio/ByteBuffer.put:([BII)Ljava/nio/ByteBuffer;
      59: pop
      60: aload_2
      61: aload         9
      63: iconst_1
      64: bipush        7
      66: invokevirtual #25                 // Method java/nio/ByteBuffer.put:([BII)Ljava/nio/ByteBuffer;
      69: pop
      70: aload_2
      71: lload         7
      73: invokevirtual #22                 // Method java/nio/ByteBuffer.putLong:(J)Ljava/nio/ByteBuffer;
      76: pop
      77: new           #4                  // class org/apache/hadoop/hbase/nio/MultiByteBuff
      80: dup
      81: iconst_2
      82: anewarray     #5                  // class java/nio/ByteBuffer
      85: dup
      86: iconst_0
      87: aload_1
      88: aastore
      89: dup
      90: iconst_1
      91: aload_2
      92: aastore
      93: invokespecial #6                  // Method org/apache/hadoop/hbase/nio/MultiByteBuff."<init>":([Ljava/nio/ByteBuffer;)V
      96: astore        10
      98: ldc2_w        #63                 // long 4l
     101: aload         10
     103: invokevirtual #29                 // Method org/apache/hadoop/hbase/nio/MultiByteBuff.getInt:()I
     106: i2l
     107: invokestatic  #10                 // Method org/junit/Assert.assertEquals:(JJ)V
     110: lload_3
     111: aload         10
     113: invokevirtual #30                 // Method org/apache/hadoop/hbase/nio/MultiByteBuff.getLong:()J
     116: invokestatic  #10                 // Method org/junit/Assert.assertEquals:(JJ)V
     119: aload         10
     121: bipush        10
     123: invokevirtual #71                 // Method org/apache/hadoop/hbase/nio/MultiByteBuff.skip:(I)Lorg/apache/hadoop/hbase/nio/MultiByteBuff;
     126: pop
     127: aload         10
     129: iconst_4
     130: invokevirtual #72                 // Method org/apache/hadoop/hbase/nio/MultiByteBuff.moveBack:(I)Lorg/apache/hadoop/hbase/nio/MultiByteBuff;
     133: pop
     134: aload         10
     136: bipush        6
     138: invokevirtual #72                 // Method org/apache/hadoop/hbase/nio/MultiByteBuff.moveBack:(I)Lorg/apache/hadoop/hbase/nio/MultiByteBuff;
     141: pop
     142: aload         10
     144: bipush        8
     146: invokevirtual #72                 // Method org/apache/hadoop/hbase/nio/MultiByteBuff.moveBack:(I)Lorg/apache/hadoop/hbase/nio/MultiByteBuff;
     149: pop
     150: lload_3
     151: aload         10
     153: invokevirtual #30                 // Method org/apache/hadoop/hbase/nio/MultiByteBuff.getLong:()J
     156: invokestatic  #10                 // Method org/junit/Assert.assertEquals:(JJ)V
     159: return

  public void testSubBuffer();
    Code:
       0: bipush        10
       2: invokestatic  #62                 // Method java/nio/ByteBuffer.allocateDirect:(I)Ljava/nio/ByteBuffer;
       5: astore_1
       6: bipush        10
       8: invokestatic  #62                 // Method java/nio/ByteBuffer.allocateDirect:(I)Ljava/nio/ByteBuffer;
      11: astore_2
      12: new           #4                  // class org/apache/hadoop/hbase/nio/MultiByteBuff
      15: dup
      16: iconst_2
      17: anewarray     #5                  // class java/nio/ByteBuffer
      20: dup
      21: iconst_0
      22: aload_1
      23: aastore
      24: dup
      25: iconst_1
      26: aload_2
      27: aastore
      28: invokespecial #6                  // Method org/apache/hadoop/hbase/nio/MultiByteBuff."<init>":([Ljava/nio/ByteBuffer;)V
      31: astore_3
      32: ldc2_w        #73                 // long 1234l
      35: lstore        4
      37: ldc2_w        #18                 // long 100l
      40: lstore        6
      42: aload_3
      43: lload         4
      45: invokevirtual #33                 // Method org/apache/hadoop/hbase/nio/MultiByteBuff.putLong:(J)Lorg/apache/hadoop/hbase/nio/MultiByteBuff;
      48: pop
      49: aload_3
      50: lload         6
      52: invokevirtual #33                 // Method org/apache/hadoop/hbase/nio/MultiByteBuff.putLong:(J)Lorg/apache/hadoop/hbase/nio/MultiByteBuff;
      55: pop
      56: aload_3
      57: invokevirtual #40                 // Method org/apache/hadoop/hbase/nio/MultiByteBuff.rewind:()Lorg/apache/hadoop/hbase/nio/MultiByteBuff;
      60: pop
      61: aload_3
      62: bipush        8
      64: invokevirtual #76                 // Method org/apache/hadoop/hbase/nio/MultiByteBuff.asSubByteBuffer:(I)Ljava/nio/ByteBuffer;
      67: astore        8
      69: aload_1
      70: aload         8
      72: invokestatic  #61                 // Method org/junit/Assert.assertEquals:(Ljava/lang/Object;Ljava/lang/Object;)V
      75: lload         4
      77: aload         8
      79: aload         8
      81: invokevirtual #77                 // Method java/nio/ByteBuffer.position:()I
      84: invokestatic  #78                 // Method org/apache/hadoop/hbase/util/ByteBufferUtils.toLong:(Ljava/nio/ByteBuffer;I)J
      87: invokestatic  #10                 // Method org/junit/Assert.assertEquals:(JJ)V
      90: aload_3
      91: bipush        8
      93: invokevirtual #71                 // Method org/apache/hadoop/hbase/nio/MultiByteBuff.skip:(I)Lorg/apache/hadoop/hbase/nio/MultiByteBuff;
      96: pop
      97: aload_3
      98: bipush        8
     100: invokevirtual #76                 // Method org/apache/hadoop/hbase/nio/MultiByteBuff.asSubByteBuffer:(I)Ljava/nio/ByteBuffer;
     103: astore        8
     105: aload_1
     106: aload         8
     108: invokestatic  #79                 // Method org/junit/Assert.assertNotEquals:(Ljava/lang/Object;Ljava/lang/Object;)V
     111: aload_2
     112: aload         8
     114: invokestatic  #79                 // Method org/junit/Assert.assertNotEquals:(Ljava/lang/Object;Ljava/lang/Object;)V
     117: lload         6
     119: aload         8
     121: aload         8
     123: invokevirtual #77                 // Method java/nio/ByteBuffer.position:()I
     126: invokestatic  #78                 // Method org/apache/hadoop/hbase/util/ByteBufferUtils.toLong:(Ljava/nio/ByteBuffer;I)J
     129: invokestatic  #10                 // Method org/junit/Assert.assertEquals:(JJ)V
     132: aload_3
     133: invokevirtual #40                 // Method org/apache/hadoop/hbase/nio/MultiByteBuff.rewind:()Lorg/apache/hadoop/hbase/nio/MultiByteBuff;
     136: pop
     137: new           #80                 // class org/apache/hadoop/hbase/util/ObjectIntPair
     140: dup
     141: invokespecial #81                 // Method org/apache/hadoop/hbase/util/ObjectIntPair."<init>":()V
     144: astore        9
     146: aload_3
     147: bipush        8
     149: bipush        8
     151: aload         9
     153: invokevirtual #82                 // Method org/apache/hadoop/hbase/nio/MultiByteBuff.asSubByteBuffer:(IILorg/apache/hadoop/hbase/util/ObjectIntPair;)V
     156: aload_1
     157: aload         9
     159: invokevirtual #83                 // Method org/apache/hadoop/hbase/util/ObjectIntPair.getFirst:()Ljava/lang/Object;
     162: invokestatic  #79                 // Method org/junit/Assert.assertNotEquals:(Ljava/lang/Object;Ljava/lang/Object;)V
     165: aload_2
     166: aload         9
     168: invokevirtual #83                 // Method org/apache/hadoop/hbase/util/ObjectIntPair.getFirst:()Ljava/lang/Object;
     171: invokestatic  #79                 // Method org/junit/Assert.assertNotEquals:(Ljava/lang/Object;Ljava/lang/Object;)V
     174: lconst_0
     175: aload         9
     177: invokevirtual #84                 // Method org/apache/hadoop/hbase/util/ObjectIntPair.getSecond:()I
     180: i2l
     181: invokestatic  #10                 // Method org/junit/Assert.assertEquals:(JJ)V
     184: lload         6
     186: aload         8
     188: aload         9
     190: invokevirtual #84                 // Method org/apache/hadoop/hbase/util/ObjectIntPair.getSecond:()I
     193: invokestatic  #78                 // Method org/apache/hadoop/hbase/util/ByteBufferUtils.toLong:(Ljava/nio/ByteBuffer;I)J
     196: invokestatic  #10                 // Method org/junit/Assert.assertEquals:(JJ)V
     199: return

  public void testSliceDuplicateMethods() throws java.lang.Exception;
    Code:
       0: bipush        10
       2: invokestatic  #62                 // Method java/nio/ByteBuffer.allocateDirect:(I)Ljava/nio/ByteBuffer;
       5: astore_1
       6: bipush        15
       8: invokestatic  #62                 // Method java/nio/ByteBuffer.allocateDirect:(I)Ljava/nio/ByteBuffer;
      11: astore_2
      12: new           #4                  // class org/apache/hadoop/hbase/nio/MultiByteBuff
      15: dup
      16: iconst_2
      17: anewarray     #5                  // class java/nio/ByteBuffer
      20: dup
      21: iconst_0
      22: aload_1
      23: aastore
      24: dup
      25: iconst_1
      26: aload_2
      27: aastore
      28: invokespecial #6                  // Method org/apache/hadoop/hbase/nio/MultiByteBuff."<init>":([Ljava/nio/ByteBuffer;)V
      31: astore_3
      32: ldc2_w        #73                 // long 1234l
      35: lstore        4
      37: ldc2_w        #18                 // long 100l
      40: lstore        6
      42: aload_3
      43: iconst_2
      44: invokevirtual #32                 // Method org/apache/hadoop/hbase/nio/MultiByteBuff.put:(B)Lorg/apache/hadoop/hbase/nio/MultiByteBuff;
      47: pop
      48: aload_3
      49: lload         4
      51: invokevirtual #33                 // Method org/apache/hadoop/hbase/nio/MultiByteBuff.putLong:(J)Lorg/apache/hadoop/hbase/nio/MultiByteBuff;
      54: pop
      55: aload_3
      56: lload         6
      58: invokevirtual #33                 // Method org/apache/hadoop/hbase/nio/MultiByteBuff.putLong:(J)Lorg/apache/hadoop/hbase/nio/MultiByteBuff;
      61: pop
      62: aload_3
      63: bipush        45
      65: invokevirtual #34                 // Method org/apache/hadoop/hbase/nio/MultiByteBuff.putInt:(I)Lorg/apache/hadoop/hbase/nio/MultiByteBuff;
      68: pop
      69: aload_3
      70: iconst_1
      71: invokevirtual #36                 // Method org/apache/hadoop/hbase/nio/MultiByteBuff.position:(I)Lorg/apache/hadoop/hbase/nio/MultiByteBuff;
      74: pop
      75: aload_3
      76: aload_3
      77: invokevirtual #35                 // Method org/apache/hadoop/hbase/nio/MultiByteBuff.position:()I
      80: bipush        16
      82: iadd
      83: invokevirtual #85                 // Method org/apache/hadoop/hbase/nio/MultiByteBuff.limit:(I)Lorg/apache/hadoop/hbase/nio/MultiByteBuff;
      86: pop
      87: aload_3
      88: invokevirtual #86                 // Method org/apache/hadoop/hbase/nio/MultiByteBuff.slice:()Lorg/apache/hadoop/hbase/nio/MultiByteBuff;
      91: astore        8
      93: lconst_0
      94: aload         8
      96: invokevirtual #35                 // Method org/apache/hadoop/hbase/nio/MultiByteBuff.position:()I
      99: i2l
     100: invokestatic  #10                 // Method org/junit/Assert.assertEquals:(JJ)V
     103: ldc2_w        #87                 // long 16l
     106: aload         8
     108: invokevirtual #89                 // Method org/apache/hadoop/hbase/nio/MultiByteBuff.limit:()I
     111: i2l
     112: invokestatic  #10                 // Method org/junit/Assert.assertEquals:(JJ)V
     115: lload         4
     117: aload         8
     119: invokevirtual #30                 // Method org/apache/hadoop/hbase/nio/MultiByteBuff.getLong:()J
     122: invokestatic  #10                 // Method org/junit/Assert.assertEquals:(JJ)V
     125: lload         6
     127: aload         8
     129: invokevirtual #30                 // Method org/apache/hadoop/hbase/nio/MultiByteBuff.getLong:()J
     132: invokestatic  #10                 // Method org/junit/Assert.assertEquals:(JJ)V
     135: aload_3
     136: invokevirtual #90                 // Method org/apache/hadoop/hbase/nio/MultiByteBuff.duplicate:()Lorg/apache/hadoop/hbase/nio/MultiByteBuff;
     139: astore        9
     141: lconst_1
     142: aload         9
     144: invokevirtual #35                 // Method org/apache/hadoop/hbase/nio/MultiByteBuff.position:()I
     147: i2l
     148: invokestatic  #10                 // Method org/junit/Assert.assertEquals:(JJ)V
     151: aload         9
     153: invokevirtual #35                 // Method org/apache/hadoop/hbase/nio/MultiByteBuff.position:()I
     156: bipush        16
     158: iadd
     159: i2l
     160: aload         9
     162: invokevirtual #89                 // Method org/apache/hadoop/hbase/nio/MultiByteBuff.limit:()I
     165: i2l
     166: invokestatic  #10                 // Method org/junit/Assert.assertEquals:(JJ)V
     169: lload         4
     171: aload         9
     173: invokevirtual #30                 // Method org/apache/hadoop/hbase/nio/MultiByteBuff.getLong:()J
     176: invokestatic  #10                 // Method org/junit/Assert.assertEquals:(JJ)V
     179: lload         6
     181: aload         9
     183: invokevirtual #30                 // Method org/apache/hadoop/hbase/nio/MultiByteBuff.getLong:()J
     186: invokestatic  #10                 // Method org/junit/Assert.assertEquals:(JJ)V
     189: return

  public void testGetWithPosOnMultiBuffers() throws java.io.IOException;
    Code:
       0: iconst_4
       1: newarray       byte
       3: astore_1
       4: iconst_4
       5: newarray       byte
       7: astore_2
       8: aload_1
       9: invokestatic  #91                 // Method java/nio/ByteBuffer.wrap:([B)Ljava/nio/ByteBuffer;
      12: astore_3
      13: aload_2
      14: invokestatic  #91                 // Method java/nio/ByteBuffer.wrap:([B)Ljava/nio/ByteBuffer;
      17: astore        4
      19: new           #4                  // class org/apache/hadoop/hbase/nio/MultiByteBuff
      22: dup
      23: iconst_2
      24: anewarray     #5                  // class java/nio/ByteBuffer
      27: dup
      28: iconst_0
      29: aload_3
      30: aastore
      31: dup
      32: iconst_1
      33: aload         4
      35: aastore
      36: invokespecial #6                  // Method org/apache/hadoop/hbase/nio/MultiByteBuff."<init>":([Ljava/nio/ByteBuffer;)V
      39: astore        5
      41: aload         5
      43: iconst_2
      44: invokevirtual #36                 // Method org/apache/hadoop/hbase/nio/MultiByteBuff.position:(I)Lorg/apache/hadoop/hbase/nio/MultiByteBuff;
      47: pop
      48: aload         5
      50: iconst_4
      51: invokevirtual #34                 // Method org/apache/hadoop/hbase/nio/MultiByteBuff.putInt:(I)Lorg/apache/hadoop/hbase/nio/MultiByteBuff;
      54: pop
      55: aload         5
      57: iconst_2
      58: invokevirtual #27                 // Method org/apache/hadoop/hbase/nio/MultiByteBuff.getInt:(I)I
      61: istore        6
      63: iconst_4
      64: newarray       byte
      66: astore        7
      68: aload         7
      70: iconst_0
      71: aload         5
      73: iconst_2
      74: invokevirtual #92                 // Method org/apache/hadoop/hbase/nio/MultiByteBuff.get:(I)B
      77: bastore
      78: aload         7
      80: iconst_1
      81: aload         5
      83: iconst_3
      84: invokevirtual #92                 // Method org/apache/hadoop/hbase/nio/MultiByteBuff.get:(I)B
      87: bastore
      88: aload         7
      90: iconst_2
      91: aload         5
      93: iconst_4
      94: invokevirtual #92                 // Method org/apache/hadoop/hbase/nio/MultiByteBuff.get:(I)B
      97: bastore
      98: aload         7
     100: iconst_3
     101: aload         5
     103: iconst_5
     104: invokevirtual #92                 // Method org/apache/hadoop/hbase/nio/MultiByteBuff.get:(I)B
     107: bastore
     108: aload         7
     110: invokestatic  #93                 // Method org/apache/hadoop/hbase/util/Bytes.toInt:([B)I
     113: istore        8
     115: iload         8
     117: i2l
     118: iload         6
     120: i2l
     121: invokestatic  #10                 // Method org/junit/Assert.assertEquals:(JJ)V
     124: return

  public void testGetIntStrictlyForwardWithPosOnMultiBuffers() throws java.io.IOException;
    Code:
       0: iconst_4
       1: newarray       byte
       3: astore_1
       4: bipush        8
       6: newarray       byte
       8: astore_2
       9: aload_1
      10: invokestatic  #91                 // Method java/nio/ByteBuffer.wrap:([B)Ljava/nio/ByteBuffer;
      13: astore_3
      14: aload_2
      15: invokestatic  #91                 // Method java/nio/ByteBuffer.wrap:([B)Ljava/nio/ByteBuffer;
      18: astore        4
      20: new           #4                  // class org/apache/hadoop/hbase/nio/MultiByteBuff
      23: dup
      24: iconst_2
      25: anewarray     #5                  // class java/nio/ByteBuffer
      28: dup
      29: iconst_0
      30: aload_3
      31: aastore
      32: dup
      33: iconst_1
      34: aload         4
      36: aastore
      37: invokespecial #6                  // Method org/apache/hadoop/hbase/nio/MultiByteBuff."<init>":([Ljava/nio/ByteBuffer;)V
      40: astore        5
      42: aload         5
      44: iconst_2
      45: invokevirtual #36                 // Method org/apache/hadoop/hbase/nio/MultiByteBuff.position:(I)Lorg/apache/hadoop/hbase/nio/MultiByteBuff;
      48: pop
      49: aload         5
      51: iconst_4
      52: invokevirtual #34                 // Method org/apache/hadoop/hbase/nio/MultiByteBuff.putInt:(I)Lorg/apache/hadoop/hbase/nio/MultiByteBuff;
      55: pop
      56: aload         5
      58: bipush        7
      60: invokevirtual #36                 // Method org/apache/hadoop/hbase/nio/MultiByteBuff.position:(I)Lorg/apache/hadoop/hbase/nio/MultiByteBuff;
      63: pop
      64: aload         5
      66: iconst_2
      67: invokevirtual #32                 // Method org/apache/hadoop/hbase/nio/MultiByteBuff.put:(B)Lorg/apache/hadoop/hbase/nio/MultiByteBuff;
      70: pop
      71: aload         5
      73: iconst_3
      74: invokevirtual #34                 // Method org/apache/hadoop/hbase/nio/MultiByteBuff.putInt:(I)Lorg/apache/hadoop/hbase/nio/MultiByteBuff;
      77: pop
      78: aload         5
      80: invokevirtual #40                 // Method org/apache/hadoop/hbase/nio/MultiByteBuff.rewind:()Lorg/apache/hadoop/hbase/nio/MultiByteBuff;
      83: pop
      84: aload         5
      86: iconst_4
      87: invokevirtual #94                 // Method org/apache/hadoop/hbase/nio/MultiByteBuff.getIntAfterPosition:(I)I
      90: pop
      91: aload         5
      93: bipush        7
      95: invokevirtual #92                 // Method org/apache/hadoop/hbase/nio/MultiByteBuff.get:(I)B
      98: istore        6
     100: ldc2_w        #11                 // long 2l
     103: iload         6
     105: i2l
     106: invokestatic  #10                 // Method org/junit/Assert.assertEquals:(JJ)V
     109: aload         5
     111: bipush        7
     113: invokevirtual #36                 // Method org/apache/hadoop/hbase/nio/MultiByteBuff.position:(I)Lorg/apache/hadoop/hbase/nio/MultiByteBuff;
     116: pop
     117: aload         5
     119: iconst_1
     120: invokevirtual #94                 // Method org/apache/hadoop/hbase/nio/MultiByteBuff.getIntAfterPosition:(I)I
     123: istore        7
     125: ldc2_w        #95                 // long 3l
     128: iload         7
     130: i2l
     131: invokestatic  #10                 // Method org/junit/Assert.assertEquals:(JJ)V
     134: return

  public void testPositonalCopyToByteArray() throws java.lang.Exception;
    Code:
       0: iconst_4
       1: newarray       byte
       3: astore_1
       4: bipush        8
       6: newarray       byte
       8: astore_2
       9: aload_1
      10: invokestatic  #91                 // Method java/nio/ByteBuffer.wrap:([B)Ljava/nio/ByteBuffer;
      13: astore_3
      14: aload_2
      15: invokestatic  #91                 // Method java/nio/ByteBuffer.wrap:([B)Ljava/nio/ByteBuffer;
      18: astore        4
      20: new           #4                  // class org/apache/hadoop/hbase/nio/MultiByteBuff
      23: dup
      24: iconst_2
      25: anewarray     #5                  // class java/nio/ByteBuffer
      28: dup
      29: iconst_0
      30: aload_3
      31: aastore
      32: dup
      33: iconst_1
      34: aload         4
      36: aastore
      37: invokespecial #6                  // Method org/apache/hadoop/hbase/nio/MultiByteBuff."<init>":([Ljava/nio/ByteBuffer;)V
      40: astore        5
      42: aload         5
      44: iconst_2
      45: invokevirtual #36                 // Method org/apache/hadoop/hbase/nio/MultiByteBuff.position:(I)Lorg/apache/hadoop/hbase/nio/MultiByteBuff;
      48: pop
      49: aload         5
      51: iconst_4
      52: invokevirtual #34                 // Method org/apache/hadoop/hbase/nio/MultiByteBuff.putInt:(I)Lorg/apache/hadoop/hbase/nio/MultiByteBuff;
      55: pop
      56: aload         5
      58: bipush        7
      60: invokevirtual #36                 // Method org/apache/hadoop/hbase/nio/MultiByteBuff.position:(I)Lorg/apache/hadoop/hbase/nio/MultiByteBuff;
      63: pop
      64: aload         5
      66: iconst_2
      67: invokevirtual #32                 // Method org/apache/hadoop/hbase/nio/MultiByteBuff.put:(B)Lorg/apache/hadoop/hbase/nio/MultiByteBuff;
      70: pop
      71: aload         5
      73: iconst_3
      74: invokevirtual #34                 // Method org/apache/hadoop/hbase/nio/MultiByteBuff.putInt:(I)Lorg/apache/hadoop/hbase/nio/MultiByteBuff;
      77: pop
      78: iconst_4
      79: newarray       byte
      81: astore        6
      83: aload         5
      85: iconst_2
      86: aload         6
      88: iconst_0
      89: iconst_4
      90: invokevirtual #97                 // Method org/apache/hadoop/hbase/nio/MultiByteBuff.get:(I[BII)V
      93: ldc2_w        #63                 // long 4l
      96: aload         6
      98: invokestatic  #93                 // Method org/apache/hadoop/hbase/util/Bytes.toInt:([B)I
     101: i2l
     102: invokestatic  #10                 // Method org/junit/Assert.assertEquals:(JJ)V
     105: ldc2_w        #98                 // long 12l
     108: aload         5
     110: invokevirtual #35                 // Method org/apache/hadoop/hbase/nio/MultiByteBuff.position:()I
     113: i2l
     114: invokestatic  #10                 // Method org/junit/Assert.assertEquals:(JJ)V
     117: aload         5
     119: iconst_1
     120: invokevirtual #36                 // Method org/apache/hadoop/hbase/nio/MultiByteBuff.position:(I)Lorg/apache/hadoop/hbase/nio/MultiByteBuff;
     123: pop
     124: iconst_4
     125: newarray       byte
     127: astore        6
     129: aload         5
     131: bipush        8
     133: aload         6
     135: iconst_0
     136: iconst_4
     137: invokevirtual #97                 // Method org/apache/hadoop/hbase/nio/MultiByteBuff.get:(I[BII)V
     140: ldc2_w        #95                 // long 3l
     143: aload         6
     145: invokestatic  #93                 // Method org/apache/hadoop/hbase/util/Bytes.toInt:([B)I
     148: i2l
     149: invokestatic  #10                 // Method org/junit/Assert.assertEquals:(JJ)V
     152: lconst_1
     153: aload         5
     155: invokevirtual #35                 // Method org/apache/hadoop/hbase/nio/MultiByteBuff.position:()I
     158: i2l
     159: invokestatic  #10                 // Method org/junit/Assert.assertEquals:(JJ)V
     162: aload         5
     164: bipush        12
     166: invokevirtual #36                 // Method org/apache/hadoop/hbase/nio/MultiByteBuff.position:(I)Lorg/apache/hadoop/hbase/nio/MultiByteBuff;
     169: pop
     170: iconst_1
     171: newarray       byte
     173: astore        6
     175: aload         5
     177: bipush        7
     179: aload         6
     181: iconst_0
     182: iconst_1
     183: invokevirtual #97                 // Method org/apache/hadoop/hbase/nio/MultiByteBuff.get:(I[BII)V
     186: ldc2_w        #11                 // long 2l
     189: aload         6
     191: iconst_0
     192: baload
     193: i2l
     194: invokestatic  #10                 // Method org/junit/Assert.assertEquals:(JJ)V
     197: ldc2_w        #98                 // long 12l
     200: aload         5
     202: invokevirtual #35                 // Method org/apache/hadoop/hbase/nio/MultiByteBuff.position:()I
     205: i2l
     206: invokestatic  #10                 // Method org/junit/Assert.assertEquals:(JJ)V
     209: return

  public void testToBytes() throws java.lang.Exception;
    Code:
       0: iconst_4
       1: newarray       byte
       3: astore_1
       4: bipush        8
       6: newarray       byte
       8: astore_2
       9: iconst_0
      10: istore_3
      11: iload_3
      12: aload_1
      13: arraylength
      14: if_icmpge     28
      17: aload_1
      18: iload_3
      19: iload_3
      20: i2b
      21: bastore
      22: iinc          3, 1
      25: goto          11
      28: iconst_0
      29: istore_3
      30: iload_3
      31: aload_2
      32: arraylength
      33: if_icmpge     50
      36: aload_2
      37: iload_3
      38: aload_2
      39: arraylength
      40: iload_3
      41: iadd
      42: i2b
      43: bastore
      44: iinc          3, 1
      47: goto          30
      50: aload_1
      51: invokestatic  #91                 // Method java/nio/ByteBuffer.wrap:([B)Ljava/nio/ByteBuffer;
      54: astore_3
      55: aload_2
      56: invokestatic  #91                 // Method java/nio/ByteBuffer.wrap:([B)Ljava/nio/ByteBuffer;
      59: astore        4
      61: new           #4                  // class org/apache/hadoop/hbase/nio/MultiByteBuff
      64: dup
      65: iconst_2
      66: anewarray     #5                  // class java/nio/ByteBuffer
      69: dup
      70: iconst_0
      71: aload_3
      72: aastore
      73: dup
      74: iconst_1
      75: aload         4
      77: aastore
      78: invokespecial #6                  // Method org/apache/hadoop/hbase/nio/MultiByteBuff."<init>":([Ljava/nio/ByteBuffer;)V
      81: astore        5
      83: aload         5
      85: bipush        6
      87: iconst_4
      88: invokevirtual #100                // Method org/apache/hadoop/hbase/nio/MultiByteBuff.toBytes:(II)[B
      91: astore        6
      93: aload         6
      95: iconst_0
      96: aload         6
      98: arraylength
      99: aload_2
     100: iconst_2
     101: iconst_4
     102: invokestatic  #101                // Method org/apache/hadoop/hbase/util/Bytes.equals:([BII[BII)Z
     105: invokestatic  #60                 // Method org/junit/Assert.assertTrue:(Z)V
     108: aload         5
     110: iconst_5
     111: bipush        7
     113: invokevirtual #100                // Method org/apache/hadoop/hbase/nio/MultiByteBuff.toBytes:(II)[B
     116: astore        6
     118: aload         6
     120: iconst_0
     121: aload         6
     123: arraylength
     124: aload_2
     125: iconst_1
     126: bipush        7
     128: invokestatic  #101                // Method org/apache/hadoop/hbase/util/Bytes.equals:([BII[BII)Z
     131: invokestatic  #60                 // Method org/junit/Assert.assertTrue:(Z)V
     134: aload         5
     136: iconst_2
     137: bipush        7
     139: invokevirtual #100                // Method org/apache/hadoop/hbase/nio/MultiByteBuff.toBytes:(II)[B
     142: astore        6
     144: bipush        7
     146: newarray       byte
     148: astore        7
     150: aload_1
     151: iconst_2
     152: aload         7
     154: iconst_0
     155: iconst_2
     156: invokestatic  #102                // Method java/lang/System.arraycopy:(Ljava/lang/Object;ILjava/lang/Object;II)V
     159: aload_2
     160: iconst_0
     161: aload         7
     163: iconst_2
     164: iconst_5
     165: invokestatic  #102                // Method java/lang/System.arraycopy:(Ljava/lang/Object;ILjava/lang/Object;II)V
     168: aload         6
     170: aload         7
     172: invokestatic  #103                // Method org/apache/hadoop/hbase/util/Bytes.equals:([B[B)Z
     175: invokestatic  #60                 // Method org/junit/Assert.assertTrue:(Z)V
     178: aload         5
     180: iconst_1
     181: iconst_3
     182: invokevirtual #100                // Method org/apache/hadoop/hbase/nio/MultiByteBuff.toBytes:(II)[B
     185: astore        6
     187: aload         6
     189: iconst_0
     190: aload         6
     192: arraylength
     193: aload_1
     194: iconst_1
     195: iconst_3
     196: invokestatic  #101                // Method org/apache/hadoop/hbase/util/Bytes.equals:([BII[BII)Z
     199: invokestatic  #60                 // Method org/junit/Assert.assertTrue:(Z)V
     202: return

  public void testHasRemaining();
    Code:
       0: bipush        8
       2: invokestatic  #2                  // Method java/nio/ByteBuffer.allocate:(I)Ljava/nio/ByteBuffer;
       5: astore_1
       6: bipush        8
       8: invokestatic  #2                  // Method java/nio/ByteBuffer.allocate:(I)Ljava/nio/ByteBuffer;
      11: astore_2
      12: bipush        8
      14: invokestatic  #2                  // Method java/nio/ByteBuffer.allocate:(I)Ljava/nio/ByteBuffer;
      17: astore_3
      18: new           #4                  // class org/apache/hadoop/hbase/nio/MultiByteBuff
      21: dup
      22: iconst_3
      23: anewarray     #5                  // class java/nio/ByteBuffer
      26: dup
      27: iconst_0
      28: aload_1
      29: aastore
      30: dup
      31: iconst_1
      32: aload_2
      33: aastore
      34: dup
      35: iconst_2
      36: aload_3
      37: aastore
      38: invokespecial #6                  // Method org/apache/hadoop/hbase/nio/MultiByteBuff."<init>":([Ljava/nio/ByteBuffer;)V
      41: astore        4
      43: aload         4
      45: invokevirtual #104                // Method org/apache/hadoop/hbase/nio/MultiByteBuff.hasRemaining:()Z
      48: invokestatic  #60                 // Method org/junit/Assert.assertTrue:(Z)V
      51: aload         4
      53: bipush        20
      55: invokevirtual #85                 // Method org/apache/hadoop/hbase/nio/MultiByteBuff.limit:(I)Lorg/apache/hadoop/hbase/nio/MultiByteBuff;
      58: pop
      59: aload         4
      61: bipush        15
      63: invokevirtual #36                 // Method org/apache/hadoop/hbase/nio/MultiByteBuff.position:(I)Lorg/apache/hadoop/hbase/nio/MultiByteBuff;
      66: pop
      67: aload         4
      69: invokevirtual #41                 // Method org/apache/hadoop/hbase/nio/MultiByteBuff.get:()B
      72: pop
      73: aload         4
      75: invokevirtual #104                // Method org/apache/hadoop/hbase/nio/MultiByteBuff.hasRemaining:()Z
      78: invokestatic  #60                 // Method org/junit/Assert.assertTrue:(Z)V
      81: aload         4
      83: bipush        20
      85: invokevirtual #36                 // Method org/apache/hadoop/hbase/nio/MultiByteBuff.position:(I)Lorg/apache/hadoop/hbase/nio/MultiByteBuff;
      88: pop
      89: aload         4
      91: invokevirtual #104                // Method org/apache/hadoop/hbase/nio/MultiByteBuff.hasRemaining:()Z
      94: invokestatic  #55                 // Method org/junit/Assert.assertFalse:(Z)V
      97: aload         4
      99: bipush        12
     101: invokevirtual #85                 // Method org/apache/hadoop/hbase/nio/MultiByteBuff.limit:(I)Lorg/apache/hadoop/hbase/nio/MultiByteBuff;
     104: pop
     105: aload         4
     107: bipush        11
     109: invokevirtual #36                 // Method org/apache/hadoop/hbase/nio/MultiByteBuff.position:(I)Lorg/apache/hadoop/hbase/nio/MultiByteBuff;
     112: pop
     113: aload         4
     115: invokevirtual #104                // Method org/apache/hadoop/hbase/nio/MultiByteBuff.hasRemaining:()Z
     118: invokestatic  #60                 // Method org/junit/Assert.assertTrue:(Z)V
     121: aload         4
     123: invokevirtual #41                 // Method org/apache/hadoop/hbase/nio/MultiByteBuff.get:()B
     126: pop
     127: aload         4
     129: invokevirtual #104                // Method org/apache/hadoop/hbase/nio/MultiByteBuff.hasRemaining:()Z
     132: invokestatic  #55                 // Method org/junit/Assert.assertFalse:(Z)V
     135: aload         4
     137: bipush        16
     139: invokevirtual #85                 // Method org/apache/hadoop/hbase/nio/MultiByteBuff.limit:(I)Lorg/apache/hadoop/hbase/nio/MultiByteBuff;
     142: pop
     143: aload         4
     145: bipush        15
     147: invokevirtual #36                 // Method org/apache/hadoop/hbase/nio/MultiByteBuff.position:(I)Lorg/apache/hadoop/hbase/nio/MultiByteBuff;
     150: pop
     151: aload         4
     153: invokevirtual #104                // Method org/apache/hadoop/hbase/nio/MultiByteBuff.hasRemaining:()Z
     156: invokestatic  #60                 // Method org/junit/Assert.assertTrue:(Z)V
     159: aload         4
     161: invokevirtual #41                 // Method org/apache/hadoop/hbase/nio/MultiByteBuff.get:()B
     164: pop
     165: aload         4
     167: invokevirtual #104                // Method org/apache/hadoop/hbase/nio/MultiByteBuff.hasRemaining:()Z
     170: invokestatic  #55                 // Method org/junit/Assert.assertFalse:(Z)V
     173: return

  public void testGetPrimitivesWithSmallIndividualBBs();
    Code:
       0: bipush        45
       2: istore_1
       3: sipush        2345
       6: istore_2
       7: ldc2_w        #105                // long 75681526l
      10: lstore_3
      11: bipush        14
      13: invokestatic  #2                  // Method java/nio/ByteBuffer.allocate:(I)Ljava/nio/ByteBuffer;
      16: astore        5
      18: aload         5
      20: iload_1
      21: invokevirtual #23                 // Method java/nio/ByteBuffer.putShort:(S)Ljava/nio/ByteBuffer;
      24: pop
      25: aload         5
      27: iload_2
      28: invokevirtual #15                 // Method java/nio/ByteBuffer.putInt:(I)Ljava/nio/ByteBuffer;
      31: pop
      32: aload         5
      34: lload_3
      35: invokevirtual #22                 // Method java/nio/ByteBuffer.putLong:(J)Ljava/nio/ByteBuffer;
      38: pop
      39: aload         5
      41: invokevirtual #107                // Method java/nio/ByteBuffer.duplicate:()Ljava/nio/ByteBuffer;
      44: iconst_0
      45: invokevirtual #108                // Method java/nio/ByteBuffer.position:(I)Ljava/nio/Buffer;
      48: iconst_1
      49: invokevirtual #109                // Method java/nio/Buffer.limit:(I)Ljava/nio/Buffer;
      52: checkcast     #5                  // class java/nio/ByteBuffer
      55: invokevirtual #53                 // Method java/nio/ByteBuffer.slice:()Ljava/nio/ByteBuffer;
      58: astore        6
      60: aload         5
      62: invokevirtual #107                // Method java/nio/ByteBuffer.duplicate:()Ljava/nio/ByteBuffer;
      65: iconst_1
      66: invokevirtual #108                // Method java/nio/ByteBuffer.position:(I)Ljava/nio/Buffer;
      69: iconst_3
      70: invokevirtual #109                // Method java/nio/Buffer.limit:(I)Ljava/nio/Buffer;
      73: checkcast     #5                  // class java/nio/ByteBuffer
      76: invokevirtual #53                 // Method java/nio/ByteBuffer.slice:()Ljava/nio/ByteBuffer;
      79: astore        7
      81: aload         5
      83: invokevirtual #107                // Method java/nio/ByteBuffer.duplicate:()Ljava/nio/ByteBuffer;
      86: iconst_3
      87: invokevirtual #108                // Method java/nio/ByteBuffer.position:(I)Ljava/nio/Buffer;
      90: iconst_5
      91: invokevirtual #109                // Method java/nio/Buffer.limit:(I)Ljava/nio/Buffer;
      94: checkcast     #5                  // class java/nio/ByteBuffer
      97: invokevirtual #53                 // Method java/nio/ByteBuffer.slice:()Ljava/nio/ByteBuffer;
     100: astore        8
     102: aload         5
     104: invokevirtual #107                // Method java/nio/ByteBuffer.duplicate:()Ljava/nio/ByteBuffer;
     107: iconst_5
     108: invokevirtual #108                // Method java/nio/ByteBuffer.position:(I)Ljava/nio/Buffer;
     111: bipush        11
     113: invokevirtual #109                // Method java/nio/Buffer.limit:(I)Ljava/nio/Buffer;
     116: checkcast     #5                  // class java/nio/ByteBuffer
     119: invokevirtual #53                 // Method java/nio/ByteBuffer.slice:()Ljava/nio/ByteBuffer;
     122: astore        9
     124: aload         5
     126: invokevirtual #107                // Method java/nio/ByteBuffer.duplicate:()Ljava/nio/ByteBuffer;
     129: bipush        11
     131: invokevirtual #108                // Method java/nio/ByteBuffer.position:(I)Ljava/nio/Buffer;
     134: bipush        12
     136: invokevirtual #109                // Method java/nio/Buffer.limit:(I)Ljava/nio/Buffer;
     139: checkcast     #5                  // class java/nio/ByteBuffer
     142: invokevirtual #53                 // Method java/nio/ByteBuffer.slice:()Ljava/nio/ByteBuffer;
     145: astore        10
     147: aload         5
     149: invokevirtual #107                // Method java/nio/ByteBuffer.duplicate:()Ljava/nio/ByteBuffer;
     152: bipush        12
     154: invokevirtual #108                // Method java/nio/ByteBuffer.position:(I)Ljava/nio/Buffer;
     157: bipush        14
     159: invokevirtual #109                // Method java/nio/Buffer.limit:(I)Ljava/nio/Buffer;
     162: checkcast     #5                  // class java/nio/ByteBuffer
     165: invokevirtual #53                 // Method java/nio/ByteBuffer.slice:()Ljava/nio/ByteBuffer;
     168: astore        11
     170: new           #4                  // class org/apache/hadoop/hbase/nio/MultiByteBuff
     173: dup
     174: bipush        6
     176: anewarray     #5                  // class java/nio/ByteBuffer
     179: dup
     180: iconst_0
     181: aload         6
     183: aastore
     184: dup
     185: iconst_1
     186: aload         7
     188: aastore
     189: dup
     190: iconst_2
     191: aload         8
     193: aastore
     194: dup
     195: iconst_3
     196: aload         9
     198: aastore
     199: dup
     200: iconst_4
     201: aload         10
     203: aastore
     204: dup
     205: iconst_5
     206: aload         11
     208: aastore
     209: invokespecial #6                  // Method org/apache/hadoop/hbase/nio/MultiByteBuff."<init>":([Ljava/nio/ByteBuffer;)V
     212: astore        12
     214: iload_1
     215: i2l
     216: aload         12
     218: iconst_0
     219: invokevirtual #9                  // Method org/apache/hadoop/hbase/nio/MultiByteBuff.getShortAfterPosition:(I)S
     222: i2l
     223: invokestatic  #10                 // Method org/junit/Assert.assertEquals:(JJ)V
     226: iload_2
     227: i2l
     228: aload         12
     230: iconst_2
     231: invokevirtual #94                 // Method org/apache/hadoop/hbase/nio/MultiByteBuff.getIntAfterPosition:(I)I
     234: i2l
     235: invokestatic  #10                 // Method org/junit/Assert.assertEquals:(JJ)V
     238: lload_3
     239: aload         12
     241: bipush        6
     243: invokevirtual #110                // Method org/apache/hadoop/hbase/nio/MultiByteBuff.getLongAfterPosition:(I)J
     246: invokestatic  #10                 // Method org/junit/Assert.assertEquals:(JJ)V
     249: iload_1
     250: i2l
     251: aload         12
     253: iconst_0
     254: invokevirtual #28                 // Method org/apache/hadoop/hbase/nio/MultiByteBuff.getShort:(I)S
     257: i2l
     258: invokestatic  #10                 // Method org/junit/Assert.assertEquals:(JJ)V
     261: iload_2
     262: i2l
     263: aload         12
     265: iconst_2
     266: invokevirtual #27                 // Method org/apache/hadoop/hbase/nio/MultiByteBuff.getInt:(I)I
     269: i2l
     270: invokestatic  #10                 // Method org/junit/Assert.assertEquals:(JJ)V
     273: lload_3
     274: aload         12
     276: bipush        6
     278: invokevirtual #26                 // Method org/apache/hadoop/hbase/nio/MultiByteBuff.getLong:(I)J
     281: invokestatic  #10                 // Method org/junit/Assert.assertEquals:(JJ)V
     284: aload         12
     286: iconst_0
     287: invokevirtual #36                 // Method org/apache/hadoop/hbase/nio/MultiByteBuff.position:(I)Lorg/apache/hadoop/hbase/nio/MultiByteBuff;
     290: pop
     291: iload_1
     292: i2l
     293: aload         12
     295: invokevirtual #31                 // Method org/apache/hadoop/hbase/nio/MultiByteBuff.getShort:()S
     298: i2l
     299: invokestatic  #10                 // Method org/junit/Assert.assertEquals:(JJ)V
     302: iload_2
     303: i2l
     304: aload         12
     306: invokevirtual #29                 // Method org/apache/hadoop/hbase/nio/MultiByteBuff.getInt:()I
     309: i2l
     310: invokestatic  #10                 // Method org/junit/Assert.assertEquals:(JJ)V
     313: lload_3
     314: aload         12
     316: invokevirtual #30                 // Method org/apache/hadoop/hbase/nio/MultiByteBuff.getLong:()J
     319: invokestatic  #10                 // Method org/junit/Assert.assertEquals:(JJ)V
     322: return

  static {};
    Code:
       0: ldc           #111                // class org/apache/hadoop/hbase/nio/TestMultiByteBuff
       2: invokestatic  #112                // Method org/apache/hadoop/hbase/HBaseClassTestRule.forClass:(Ljava/lang/Class;)Lorg/apache/hadoop/hbase/HBaseClassTestRule;
       5: putstatic     #113                // Field CLASS_RULE:Lorg/apache/hadoop/hbase/HBaseClassTestRule;
       8: return
}
