Compiled from "TestMasterObserverToModifyTableSchema.java"
public class org.apache.hadoop.hbase.coprocessor.TestMasterObserverToModifyTableSchema$OnlyOneVersionAllowedMasterObserver implements org.apache.hadoop.hbase.coprocessor.MasterCoprocessor,org.apache.hadoop.hbase.coprocessor.MasterObserver {
  public org.apache.hadoop.hbase.coprocessor.TestMasterObserverToModifyTableSchema$OnlyOneVersionAllowedMasterObserver();
    Code:
       0: aload_0
       1: invokespecial #1                  // Method java/lang/Object."<init>":()V
       4: return

  public java.util.Optional<org.apache.hadoop.hbase.coprocessor.MasterObserver> getMasterObserver();
    Code:
       0: aload_0
       1: invokestatic  #2                  // Method java/util/Optional.of:(Ljava/lang/Object;)Ljava/util/Optional;
       4: areturn

  public org.apache.hadoop.hbase.client.TableDescriptor preCreateTableRegionsInfos(org.apache.hadoop.hbase.coprocessor.ObserverContext<org.apache.hadoop.hbase.coprocessor.MasterCoprocessorEnvironment>, org.apache.hadoop.hbase.client.TableDescriptor) throws java.io.IOException;
    Code:
       0: aload_2
       1: invokestatic  #3                  // Method org/apache/hadoop/hbase/client/TableDescriptorBuilder.newBuilder:(Lorg/apache/hadoop/hbase/client/TableDescriptor;)Lorg/apache/hadoop/hbase/client/TableDescriptorBuilder;
       4: astore_3
       5: aload_2
       6: invokeinterface #4,  1            // InterfaceMethod org/apache/hadoop/hbase/client/TableDescriptor.getColumnFamilies:()[Lorg/apache/hadoop/hbase/client/ColumnFamilyDescriptor;
      11: astore        4
      13: aload         4
      15: arraylength
      16: istore        5
      18: iconst_0
      19: istore        6
      21: iload         6
      23: iload         5
      25: if_icmpge     58
      28: aload         4
      30: iload         6
      32: aaload
      33: astore        7
      35: aload_3
      36: aload         7
      38: invokestatic  #5                  // Method org/apache/hadoop/hbase/client/ColumnFamilyDescriptorBuilder.newBuilder:(Lorg/apache/hadoop/hbase/client/ColumnFamilyDescriptor;)Lorg/apache/hadoop/hbase/client/ColumnFamilyDescriptorBuilder;
      41: iconst_1
      42: invokevirtual #6                  // Method org/apache/hadoop/hbase/client/ColumnFamilyDescriptorBuilder.setMaxVersions:(I)Lorg/apache/hadoop/hbase/client/ColumnFamilyDescriptorBuilder;
      45: invokevirtual #7                  // Method org/apache/hadoop/hbase/client/ColumnFamilyDescriptorBuilder.build:()Lorg/apache/hadoop/hbase/client/ColumnFamilyDescriptor;
      48: invokevirtual #8                  // Method org/apache/hadoop/hbase/client/TableDescriptorBuilder.modifyColumnFamily:(Lorg/apache/hadoop/hbase/client/ColumnFamilyDescriptor;)Lorg/apache/hadoop/hbase/client/TableDescriptorBuilder;
      51: pop
      52: iinc          6, 1
      55: goto          21
      58: aload_3
      59: invokevirtual #9                  // Method org/apache/hadoop/hbase/client/TableDescriptorBuilder.build:()Lorg/apache/hadoop/hbase/client/TableDescriptor;
      62: areturn

  public org.apache.hadoop.hbase.client.TableDescriptor preModifyTable(org.apache.hadoop.hbase.coprocessor.ObserverContext<org.apache.hadoop.hbase.coprocessor.MasterCoprocessorEnvironment>, org.apache.hadoop.hbase.TableName, org.apache.hadoop.hbase.client.TableDescriptor, org.apache.hadoop.hbase.client.TableDescriptor) throws java.io.IOException;
    Code:
       0: aload         4
       2: invokestatic  #3                  // Method org/apache/hadoop/hbase/client/TableDescriptorBuilder.newBuilder:(Lorg/apache/hadoop/hbase/client/TableDescriptor;)Lorg/apache/hadoop/hbase/client/TableDescriptorBuilder;
       5: astore        5
       7: aload         4
       9: invokeinterface #4,  1            // InterfaceMethod org/apache/hadoop/hbase/client/TableDescriptor.getColumnFamilies:()[Lorg/apache/hadoop/hbase/client/ColumnFamilyDescriptor;
      14: astore        6
      16: aload         6
      18: arraylength
      19: istore        7
      21: iconst_0
      22: istore        8
      24: iload         8
      26: iload         7
      28: if_icmpge     62
      31: aload         6
      33: iload         8
      35: aaload
      36: astore        9
      38: aload         5
      40: aload         9
      42: invokestatic  #5                  // Method org/apache/hadoop/hbase/client/ColumnFamilyDescriptorBuilder.newBuilder:(Lorg/apache/hadoop/hbase/client/ColumnFamilyDescriptor;)Lorg/apache/hadoop/hbase/client/ColumnFamilyDescriptorBuilder;
      45: iconst_1
      46: invokevirtual #6                  // Method org/apache/hadoop/hbase/client/ColumnFamilyDescriptorBuilder.setMaxVersions:(I)Lorg/apache/hadoop/hbase/client/ColumnFamilyDescriptorBuilder;
      49: invokevirtual #7                  // Method org/apache/hadoop/hbase/client/ColumnFamilyDescriptorBuilder.build:()Lorg/apache/hadoop/hbase/client/ColumnFamilyDescriptor;
      52: invokevirtual #8                  // Method org/apache/hadoop/hbase/client/TableDescriptorBuilder.modifyColumnFamily:(Lorg/apache/hadoop/hbase/client/ColumnFamilyDescriptor;)Lorg/apache/hadoop/hbase/client/TableDescriptorBuilder;
      55: pop
      56: iinc          8, 1
      59: goto          24
      62: aload         5
      64: invokevirtual #9                  // Method org/apache/hadoop/hbase/client/TableDescriptorBuilder.build:()Lorg/apache/hadoop/hbase/client/TableDescriptor;
      67: areturn
}
