Compiled from "TestFromClientSideScanExcpetion.java"
public class org.apache.hadoop.hbase.client.TestFromClientSideScanExcpetion {
  public static final org.apache.hadoop.hbase.HBaseClassTestRule CLASS_RULE;

  protected static final org.apache.hadoop.hbase.HBaseTestingUtility TEST_UTIL;

  public org.junit.rules.TestName name;

  public org.apache.hadoop.hbase.client.TestFromClientSideScanExcpetion();
    Code:
       0: aload_0
       1: invokespecial #5                  // Method java/lang/Object."<init>":()V
       4: aload_0
       5: new           #6                  // class org/junit/rules/TestName
       8: dup
       9: invokespecial #7                  // Method org/junit/rules/TestName."<init>":()V
      12: putfield      #8                  // Field name:Lorg/junit/rules/TestName;
      15: return

  public static void setUpBeforeClass() throws java.lang.Exception;
    Code:
       0: getstatic     #9                  // Field TEST_UTIL:Lorg/apache/hadoop/hbase/HBaseTestingUtility;
       3: invokevirtual #10                 // Method org/apache/hadoop/hbase/HBaseTestingUtility.getConfiguration:()Lorg/apache/hadoop/conf/Configuration;
       6: astore_0
       7: aload_0
       8: ldc           #12                 // String hbase.client.scanner.timeout.period
      10: ldc2_w        #13                 // long 6000000l
      13: invokevirtual #15                 // Method org/apache/hadoop/conf/Configuration.setLong:(Ljava/lang/String;J)V
      16: aload_0
      17: ldc           #16                 // String hbase.hregion.impl
      19: ldc           #17                 // class org/apache/hadoop/hbase/client/TestFromClientSideScanExcpetion$MyHRegion
      21: ldc           #18                 // class org/apache/hadoop/hbase/regionserver/HRegion
      23: invokevirtual #19                 // Method org/apache/hadoop/conf/Configuration.setClass:(Ljava/lang/String;Ljava/lang/Class;Ljava/lang/Class;)V
      26: aload_0
      27: ldc           #20                 // String hbase.client.log.scanner.activity
      29: iconst_1
      30: invokevirtual #21                 // Method org/apache/hadoop/conf/Configuration.setBoolean:(Ljava/lang/String;Z)V
      33: getstatic     #9                  // Field TEST_UTIL:Lorg/apache/hadoop/hbase/HBaseTestingUtility;
      36: getstatic     #22                 // Field SLAVES:I
      39: invokevirtual #23                 // Method org/apache/hadoop/hbase/HBaseTestingUtility.startMiniCluster:(I)Lorg/apache/hadoop/hbase/MiniHBaseCluster;
      42: pop
      43: return

  public static void tearDownAfterClass() throws java.lang.Exception;
    Code:
       0: getstatic     #9                  // Field TEST_UTIL:Lorg/apache/hadoop/hbase/HBaseTestingUtility;
       3: invokevirtual #24                 // Method org/apache/hadoop/hbase/HBaseTestingUtility.shutdownMiniCluster:()V
       6: return

  public void testClientScannerIsResetWhenScanThrowsIOException() throws java.io.IOException, java.lang.InterruptedException;
    Code:
       0: invokestatic  #27                 // Method reset:()V
       3: getstatic     #2                  // Field THROW_ONCE:Ljava/util/concurrent/atomic/AtomicBoolean;
       6: iconst_1
       7: invokevirtual #25                 // Method java/util/concurrent/atomic/AtomicBoolean.set:(Z)V
      10: aload_0
      11: getfield      #8                  // Field name:Lorg/junit/rules/TestName;
      14: invokevirtual #28                 // Method org/junit/rules/TestName.getMethodName:()Ljava/lang/String;
      17: invokestatic  #29                 // Method org/apache/hadoop/hbase/TableName.valueOf:(Ljava/lang/String;)Lorg/apache/hadoop/hbase/TableName;
      20: astore_1
      21: getstatic     #9                  // Field TEST_UTIL:Lorg/apache/hadoop/hbase/HBaseTestingUtility;
      24: aload_1
      25: getstatic     #30                 // Field FAMILY:[B
      28: invokevirtual #31                 // Method org/apache/hadoop/hbase/HBaseTestingUtility.createTable:(Lorg/apache/hadoop/hbase/TableName;[B)Lorg/apache/hadoop/hbase/client/Table;
      31: astore_2
      32: aconst_null
      33: astore_3
      34: getstatic     #9                  // Field TEST_UTIL:Lorg/apache/hadoop/hbase/HBaseTestingUtility;
      37: aload_2
      38: getstatic     #30                 // Field FAMILY:[B
      41: iconst_0
      42: invokevirtual #32                 // Method org/apache/hadoop/hbase/HBaseTestingUtility.loadTable:(Lorg/apache/hadoop/hbase/client/Table;[BZ)I
      45: istore        4
      47: getstatic     #9                  // Field TEST_UTIL:Lorg/apache/hadoop/hbase/HBaseTestingUtility;
      50: invokevirtual #33                 // Method org/apache/hadoop/hbase/HBaseTestingUtility.getAdmin:()Lorg/apache/hadoop/hbase/client/Admin;
      53: aload_1
      54: invokeinterface #34,  2           // InterfaceMethod org/apache/hadoop/hbase/client/Admin.flush:(Lorg/apache/hadoop/hbase/TableName;)V
      59: invokestatic  #35                 // Method inject:()V
      62: getstatic     #9                  // Field TEST_UTIL:Lorg/apache/hadoop/hbase/HBaseTestingUtility;
      65: pop
      66: aload_2
      67: new           #36                 // class org/apache/hadoop/hbase/client/Scan
      70: dup
      71: invokespecial #37                 // Method org/apache/hadoop/hbase/client/Scan."<init>":()V
      74: getstatic     #30                 // Field FAMILY:[B
      77: getstatic     #30                 // Field FAMILY:[B
      80: invokevirtual #38                 // Method org/apache/hadoop/hbase/client/Scan.addColumn:([B[B)Lorg/apache/hadoop/hbase/client/Scan;
      83: invokestatic  #39                 // Method org/apache/hadoop/hbase/HBaseTestingUtility.countRows:(Lorg/apache/hadoop/hbase/client/Table;Lorg/apache/hadoop/hbase/client/Scan;)I
      86: istore        5
      88: iload         4
      90: i2l
      91: iload         5
      93: i2l
      94: invokestatic  #40                 // Method org/junit/Assert.assertEquals:(JJ)V
      97: aload_2
      98: ifnull        181
     101: aload_3
     102: ifnull        125
     105: aload_2
     106: invokeinterface #41,  1           // InterfaceMethod org/apache/hadoop/hbase/client/Table.close:()V
     111: goto          181
     114: astore        4
     116: aload_3
     117: aload         4
     119: invokevirtual #43                 // Method java/lang/Throwable.addSuppressed:(Ljava/lang/Throwable;)V
     122: goto          181
     125: aload_2
     126: invokeinterface #41,  1           // InterfaceMethod org/apache/hadoop/hbase/client/Table.close:()V
     131: goto          181
     134: astore        4
     136: aload         4
     138: astore_3
     139: aload         4
     141: athrow
     142: astore        6
     144: aload_2
     145: ifnull        178
     148: aload_3
     149: ifnull        172
     152: aload_2
     153: invokeinterface #41,  1           // InterfaceMethod org/apache/hadoop/hbase/client/Table.close:()V
     158: goto          178
     161: astore        7
     163: aload_3
     164: aload         7
     166: invokevirtual #43                 // Method java/lang/Throwable.addSuppressed:(Ljava/lang/Throwable;)V
     169: goto          178
     172: aload_2
     173: invokeinterface #41,  1           // InterfaceMethod org/apache/hadoop/hbase/client/Table.close:()V
     178: aload         6
     180: athrow
     181: getstatic     #3                  // Field REQ_COUNT:Ljava/util/concurrent/atomic/AtomicLong;
     184: invokevirtual #44                 // Method java/util/concurrent/atomic/AtomicLong.get:()J
     187: lconst_0
     188: lcmp
     189: ifle          196
     192: iconst_1
     193: goto          197
     196: iconst_0
     197: invokestatic  #45                 // Method org/junit/Assert.assertTrue:(Z)V
     200: return
    Exception table:
       from    to  target type
         105   111   114   Class java/lang/Throwable
          34    97   134   Class java/lang/Throwable
          34    97   142   any
         152   158   161   Class java/lang/Throwable
         134   144   142   any

  public void testScannerThrowsExceptionWhenCoprocessorThrowsDNRIOE() throws java.io.IOException, java.lang.InterruptedException;
    Code:
       0: invokestatic  #27                 // Method reset:()V
       3: getstatic     #1                  // Field IS_DO_NOT_RETRY:Ljava/util/concurrent/atomic/AtomicBoolean;
       6: iconst_1
       7: invokevirtual #25                 // Method java/util/concurrent/atomic/AtomicBoolean.set:(Z)V
      10: aload_0
      11: getfield      #8                  // Field name:Lorg/junit/rules/TestName;
      14: invokevirtual #28                 // Method org/junit/rules/TestName.getMethodName:()Ljava/lang/String;
      17: invokestatic  #29                 // Method org/apache/hadoop/hbase/TableName.valueOf:(Ljava/lang/String;)Lorg/apache/hadoop/hbase/TableName;
      20: astore_1
      21: getstatic     #9                  // Field TEST_UTIL:Lorg/apache/hadoop/hbase/HBaseTestingUtility;
      24: aload_1
      25: getstatic     #30                 // Field FAMILY:[B
      28: invokevirtual #31                 // Method org/apache/hadoop/hbase/HBaseTestingUtility.createTable:(Lorg/apache/hadoop/hbase/TableName;[B)Lorg/apache/hadoop/hbase/client/Table;
      31: astore_2
      32: aconst_null
      33: astore_3
      34: getstatic     #9                  // Field TEST_UTIL:Lorg/apache/hadoop/hbase/HBaseTestingUtility;
      37: aload_2
      38: getstatic     #30                 // Field FAMILY:[B
      41: iconst_0
      42: invokevirtual #32                 // Method org/apache/hadoop/hbase/HBaseTestingUtility.loadTable:(Lorg/apache/hadoop/hbase/client/Table;[BZ)I
      45: pop
      46: getstatic     #9                  // Field TEST_UTIL:Lorg/apache/hadoop/hbase/HBaseTestingUtility;
      49: invokevirtual #33                 // Method org/apache/hadoop/hbase/HBaseTestingUtility.getAdmin:()Lorg/apache/hadoop/hbase/client/Admin;
      52: aload_1
      53: invokeinterface #34,  2           // InterfaceMethod org/apache/hadoop/hbase/client/Admin.flush:(Lorg/apache/hadoop/hbase/TableName;)V
      58: invokestatic  #35                 // Method inject:()V
      61: getstatic     #9                  // Field TEST_UTIL:Lorg/apache/hadoop/hbase/HBaseTestingUtility;
      64: pop
      65: aload_2
      66: new           #36                 // class org/apache/hadoop/hbase/client/Scan
      69: dup
      70: invokespecial #37                 // Method org/apache/hadoop/hbase/client/Scan."<init>":()V
      73: getstatic     #30                 // Field FAMILY:[B
      76: getstatic     #30                 // Field FAMILY:[B
      79: invokevirtual #38                 // Method org/apache/hadoop/hbase/client/Scan.addColumn:([B[B)Lorg/apache/hadoop/hbase/client/Scan;
      82: invokestatic  #39                 // Method org/apache/hadoop/hbase/HBaseTestingUtility.countRows:(Lorg/apache/hadoop/hbase/client/Table;Lorg/apache/hadoop/hbase/client/Scan;)I
      85: pop
      86: ldc           #46                 // String Should have thrown an exception
      88: invokestatic  #47                 // Method org/junit/Assert.fail:(Ljava/lang/String;)V
      91: aload_2
      92: ifnull        175
      95: aload_3
      96: ifnull        119
      99: aload_2
     100: invokeinterface #41,  1           // InterfaceMethod org/apache/hadoop/hbase/client/Table.close:()V
     105: goto          175
     108: astore        4
     110: aload_3
     111: aload         4
     113: invokevirtual #43                 // Method java/lang/Throwable.addSuppressed:(Ljava/lang/Throwable;)V
     116: goto          175
     119: aload_2
     120: invokeinterface #41,  1           // InterfaceMethod org/apache/hadoop/hbase/client/Table.close:()V
     125: goto          175
     128: astore        4
     130: aload         4
     132: astore_3
     133: aload         4
     135: athrow
     136: astore        5
     138: aload_2
     139: ifnull        172
     142: aload_3
     143: ifnull        166
     146: aload_2
     147: invokeinterface #41,  1           // InterfaceMethod org/apache/hadoop/hbase/client/Table.close:()V
     152: goto          172
     155: astore        6
     157: aload_3
     158: aload         6
     160: invokevirtual #43                 // Method java/lang/Throwable.addSuppressed:(Ljava/lang/Throwable;)V
     163: goto          172
     166: aload_2
     167: invokeinterface #41,  1           // InterfaceMethod org/apache/hadoop/hbase/client/Table.close:()V
     172: aload         5
     174: athrow
     175: goto          179
     178: astore_2
     179: getstatic     #3                  // Field REQ_COUNT:Ljava/util/concurrent/atomic/AtomicLong;
     182: invokevirtual #44                 // Method java/util/concurrent/atomic/AtomicLong.get:()J
     185: lconst_0
     186: lcmp
     187: ifle          194
     190: iconst_1
     191: goto          195
     194: iconst_0
     195: invokestatic  #45                 // Method org/junit/Assert.assertTrue:(Z)V
     198: return
    Exception table:
       from    to  target type
          99   105   108   Class java/lang/Throwable
          34    91   128   Class java/lang/Throwable
          34    91   136   any
         146   152   155   Class java/lang/Throwable
         128   138   136   any
          21   175   178   Class org/apache/hadoop/hbase/DoNotRetryIOException

  public void testScannerFailsAfterRetriesWhenCoprocessorThrowsIOE() throws java.io.IOException, java.lang.InterruptedException;
    Code:
       0: getstatic     #9                  // Field TEST_UTIL:Lorg/apache/hadoop/hbase/HBaseTestingUtility;
       3: invokevirtual #10                 // Method org/apache/hadoop/hbase/HBaseTestingUtility.getConfiguration:()Lorg/apache/hadoop/conf/Configuration;
       6: ldc           #49                 // String hbase.client.retries.number
       8: iconst_3
       9: invokevirtual #50                 // Method org/apache/hadoop/conf/Configuration.setInt:(Ljava/lang/String;I)V
      12: aload_0
      13: getfield      #8                  // Field name:Lorg/junit/rules/TestName;
      16: invokevirtual #28                 // Method org/junit/rules/TestName.getMethodName:()Ljava/lang/String;
      19: invokestatic  #29                 // Method org/apache/hadoop/hbase/TableName.valueOf:(Ljava/lang/String;)Lorg/apache/hadoop/hbase/TableName;
      22: astore_1
      23: invokestatic  #27                 // Method reset:()V
      26: getstatic     #2                  // Field THROW_ONCE:Ljava/util/concurrent/atomic/AtomicBoolean;
      29: iconst_0
      30: invokevirtual #25                 // Method java/util/concurrent/atomic/AtomicBoolean.set:(Z)V
      33: getstatic     #9                  // Field TEST_UTIL:Lorg/apache/hadoop/hbase/HBaseTestingUtility;
      36: aload_1
      37: getstatic     #30                 // Field FAMILY:[B
      40: invokevirtual #31                 // Method org/apache/hadoop/hbase/HBaseTestingUtility.createTable:(Lorg/apache/hadoop/hbase/TableName;[B)Lorg/apache/hadoop/hbase/client/Table;
      43: astore_2
      44: aconst_null
      45: astore_3
      46: getstatic     #9                  // Field TEST_UTIL:Lorg/apache/hadoop/hbase/HBaseTestingUtility;
      49: aload_2
      50: getstatic     #30                 // Field FAMILY:[B
      53: iconst_0
      54: invokevirtual #32                 // Method org/apache/hadoop/hbase/HBaseTestingUtility.loadTable:(Lorg/apache/hadoop/hbase/client/Table;[BZ)I
      57: pop
      58: getstatic     #9                  // Field TEST_UTIL:Lorg/apache/hadoop/hbase/HBaseTestingUtility;
      61: invokevirtual #33                 // Method org/apache/hadoop/hbase/HBaseTestingUtility.getAdmin:()Lorg/apache/hadoop/hbase/client/Admin;
      64: aload_1
      65: invokeinterface #34,  2           // InterfaceMethod org/apache/hadoop/hbase/client/Admin.flush:(Lorg/apache/hadoop/hbase/TableName;)V
      70: invokestatic  #35                 // Method inject:()V
      73: getstatic     #9                  // Field TEST_UTIL:Lorg/apache/hadoop/hbase/HBaseTestingUtility;
      76: pop
      77: aload_2
      78: new           #36                 // class org/apache/hadoop/hbase/client/Scan
      81: dup
      82: invokespecial #37                 // Method org/apache/hadoop/hbase/client/Scan."<init>":()V
      85: getstatic     #30                 // Field FAMILY:[B
      88: getstatic     #30                 // Field FAMILY:[B
      91: invokevirtual #38                 // Method org/apache/hadoop/hbase/client/Scan.addColumn:([B[B)Lorg/apache/hadoop/hbase/client/Scan;
      94: invokestatic  #39                 // Method org/apache/hadoop/hbase/HBaseTestingUtility.countRows:(Lorg/apache/hadoop/hbase/client/Table;Lorg/apache/hadoop/hbase/client/Scan;)I
      97: pop
      98: ldc           #46                 // String Should have thrown an exception
     100: invokestatic  #47                 // Method org/junit/Assert.fail:(Ljava/lang/String;)V
     103: aload_2
     104: ifnull        187
     107: aload_3
     108: ifnull        131
     111: aload_2
     112: invokeinterface #41,  1           // InterfaceMethod org/apache/hadoop/hbase/client/Table.close:()V
     117: goto          187
     120: astore        4
     122: aload_3
     123: aload         4
     125: invokevirtual #43                 // Method java/lang/Throwable.addSuppressed:(Ljava/lang/Throwable;)V
     128: goto          187
     131: aload_2
     132: invokeinterface #41,  1           // InterfaceMethod org/apache/hadoop/hbase/client/Table.close:()V
     137: goto          187
     140: astore        4
     142: aload         4
     144: astore_3
     145: aload         4
     147: athrow
     148: astore        5
     150: aload_2
     151: ifnull        184
     154: aload_3
     155: ifnull        178
     158: aload_2
     159: invokeinterface #41,  1           // InterfaceMethod org/apache/hadoop/hbase/client/Table.close:()V
     164: goto          184
     167: astore        6
     169: aload_3
     170: aload         6
     172: invokevirtual #43                 // Method java/lang/Throwable.addSuppressed:(Ljava/lang/Throwable;)V
     175: goto          184
     178: aload_2
     179: invokeinterface #41,  1           // InterfaceMethod org/apache/hadoop/hbase/client/Table.close:()V
     184: aload         5
     186: athrow
     187: goto          200
     190: astore_2
     191: aload_2
     192: ldc           #51                 // class org/apache/hadoop/hbase/exceptions/ScannerResetException
     194: invokestatic  #52                 // Method org/hamcrest/CoreMatchers.instanceOf:(Ljava/lang/Class;)Lorg/hamcrest/Matcher;
     197: invokestatic  #53                 // Method org/junit/Assert.assertThat:(Ljava/lang/Object;Lorg/hamcrest/Matcher;)V
     200: getstatic     #3                  // Field REQ_COUNT:Ljava/util/concurrent/atomic/AtomicLong;
     203: invokevirtual #44                 // Method java/util/concurrent/atomic/AtomicLong.get:()J
     206: ldc2_w        #54                 // long 3l
     209: lcmp
     210: iflt          217
     213: iconst_1
     214: goto          218
     217: iconst_0
     218: invokestatic  #45                 // Method org/junit/Assert.assertTrue:(Z)V
     221: return
    Exception table:
       from    to  target type
         111   117   120   Class java/lang/Throwable
          46   103   140   Class java/lang/Throwable
          46   103   148   any
         158   164   167   Class java/lang/Throwable
         140   150   148   any
          33   187   190   Class org/apache/hadoop/hbase/DoNotRetryIOException

  static java.util.concurrent.atomic.AtomicBoolean access$000();
    Code:
       0: getstatic     #4                  // Field ON:Ljava/util/concurrent/atomic/AtomicBoolean;
       3: areturn

  static java.util.concurrent.atomic.AtomicLong access$100();
    Code:
       0: getstatic     #3                  // Field REQ_COUNT:Ljava/util/concurrent/atomic/AtomicLong;
       3: areturn

  static java.util.concurrent.atomic.AtomicBoolean access$200();
    Code:
       0: getstatic     #2                  // Field THROW_ONCE:Ljava/util/concurrent/atomic/AtomicBoolean;
       3: areturn

  static java.util.concurrent.atomic.AtomicBoolean access$300();
    Code:
       0: getstatic     #1                  // Field IS_DO_NOT_RETRY:Ljava/util/concurrent/atomic/AtomicBoolean;
       3: areturn

  static {};
    Code:
       0: ldc           #56                 // class org/apache/hadoop/hbase/client/TestFromClientSideScanExcpetion
       2: invokestatic  #57                 // Method org/apache/hadoop/hbase/HBaseClassTestRule.forClass:(Ljava/lang/Class;)Lorg/apache/hadoop/hbase/HBaseClassTestRule;
       5: putstatic     #58                 // Field CLASS_RULE:Lorg/apache/hadoop/hbase/HBaseClassTestRule;
       8: new           #59                 // class org/apache/hadoop/hbase/HBaseTestingUtility
      11: dup
      12: invokespecial #60                 // Method org/apache/hadoop/hbase/HBaseTestingUtility."<init>":()V
      15: putstatic     #9                  // Field TEST_UTIL:Lorg/apache/hadoop/hbase/HBaseTestingUtility;
      18: ldc           #61                 // String testFamily
      20: invokestatic  #62                 // Method org/apache/hadoop/hbase/util/Bytes.toBytes:(Ljava/lang/String;)[B
      23: putstatic     #30                 // Field FAMILY:[B
      26: iconst_3
      27: putstatic     #22                 // Field SLAVES:I
      30: new           #63                 // class java/util/concurrent/atomic/AtomicBoolean
      33: dup
      34: iconst_0
      35: invokespecial #64                 // Method java/util/concurrent/atomic/AtomicBoolean."<init>":(Z)V
      38: putstatic     #4                  // Field ON:Ljava/util/concurrent/atomic/AtomicBoolean;
      41: new           #65                 // class java/util/concurrent/atomic/AtomicLong
      44: dup
      45: lconst_0
      46: invokespecial #66                 // Method java/util/concurrent/atomic/AtomicLong."<init>":(J)V
      49: putstatic     #3                  // Field REQ_COUNT:Ljava/util/concurrent/atomic/AtomicLong;
      52: new           #63                 // class java/util/concurrent/atomic/AtomicBoolean
      55: dup
      56: iconst_0
      57: invokespecial #64                 // Method java/util/concurrent/atomic/AtomicBoolean."<init>":(Z)V
      60: putstatic     #1                  // Field IS_DO_NOT_RETRY:Ljava/util/concurrent/atomic/AtomicBoolean;
      63: new           #63                 // class java/util/concurrent/atomic/AtomicBoolean
      66: dup
      67: iconst_1
      68: invokespecial #64                 // Method java/util/concurrent/atomic/AtomicBoolean."<init>":(Z)V
      71: putstatic     #2                  // Field THROW_ONCE:Ljava/util/concurrent/atomic/AtomicBoolean;
      74: return
}
