Compiled from "TestAsyncAdminRpcPriority.java"
public class org.apache.hadoop.hbase.client.TestAsyncAdminRpcPriority {
  public static final org.apache.hadoop.hbase.HBaseClassTestRule CLASS_RULE;

  public org.junit.rules.TestName name;

  public org.apache.hadoop.hbase.client.TestAsyncAdminRpcPriority();
    Code:
       0: aload_0
       1: invokespecial #4                  // Method java/lang/Object."<init>":()V
       4: aload_0
       5: new           #5                  // class org/junit/rules/TestName
       8: dup
       9: invokespecial #6                  // Method org/junit/rules/TestName."<init>":()V
      12: putfield      #7                  // Field name:Lorg/junit/rules/TestName;
      15: return

  public void setUp() throws java.io.IOException;
    Code:
       0: aload_0
       1: ldc           #8                  // class org/apache/hadoop/hbase/shaded/protobuf/generated/MasterProtos$MasterService$Interface
       3: invokestatic  #9                  // Method org/mockito/Mockito.mock:(Ljava/lang/Class;)Ljava/lang/Object;
       6: checkcast     #8                  // class org/apache/hadoop/hbase/shaded/protobuf/generated/MasterProtos$MasterService$Interface
       9: putfield      #3                  // Field masterStub:Lorg/apache/hadoop/hbase/shaded/protobuf/generated/MasterProtos$MasterService$Interface;
      12: aload_0
      13: ldc           #10                 // class org/apache/hadoop/hbase/shaded/protobuf/generated/AdminProtos$AdminService$Interface
      15: invokestatic  #9                  // Method org/mockito/Mockito.mock:(Ljava/lang/Class;)Ljava/lang/Object;
      18: checkcast     #10                 // class org/apache/hadoop/hbase/shaded/protobuf/generated/AdminProtos$AdminService$Interface
      21: putfield      #2                  // Field adminStub:Lorg/apache/hadoop/hbase/shaded/protobuf/generated/AdminProtos$AdminService$Interface;
      24: new           #11                 // class org/apache/hadoop/hbase/client/TestAsyncAdminRpcPriority$1
      27: dup
      28: aload_0
      29: invokespecial #12                 // Method org/apache/hadoop/hbase/client/TestAsyncAdminRpcPriority$1."<init>":(Lorg/apache/hadoop/hbase/client/TestAsyncAdminRpcPriority;)V
      32: invokestatic  #13                 // Method org/mockito/Mockito.doAnswer:(Lorg/mockito/stubbing/Answer;)Lorg/mockito/stubbing/Stubber;
      35: aload_0
      36: getfield      #3                  // Field masterStub:Lorg/apache/hadoop/hbase/shaded/protobuf/generated/MasterProtos$MasterService$Interface;
      39: invokeinterface #14,  2           // InterfaceMethod org/mockito/stubbing/Stubber.when:(Ljava/lang/Object;)Ljava/lang/Object;
      44: checkcast     #8                  // class org/apache/hadoop/hbase/shaded/protobuf/generated/MasterProtos$MasterService$Interface
      47: ldc           #15                 // class org/apache/hadoop/hbase/ipc/HBaseRpcController
      49: invokestatic  #16                 // Method org/mockito/ArgumentMatchers.any:(Ljava/lang/Class;)Ljava/lang/Object;
      52: checkcast     #17                 // class org/apache/hbase/thirdparty/com/google/protobuf/RpcController
      55: ldc           #18                 // class org/apache/hadoop/hbase/shaded/protobuf/generated/MasterProtos$GetProcedureResultRequest
      57: invokestatic  #16                 // Method org/mockito/ArgumentMatchers.any:(Ljava/lang/Class;)Ljava/lang/Object;
      60: checkcast     #18                 // class org/apache/hadoop/hbase/shaded/protobuf/generated/MasterProtos$GetProcedureResultRequest
      63: invokestatic  #19                 // Method org/mockito/ArgumentMatchers.any:()Ljava/lang/Object;
      66: checkcast     #20                 // class org/apache/hbase/thirdparty/com/google/protobuf/RpcCallback
      69: invokeinterface #21,  4           // InterfaceMethod org/apache/hadoop/hbase/shaded/protobuf/generated/MasterProtos$MasterService$Interface.getProcedureResult:(Lorg/apache/hbase/thirdparty/com/google/protobuf/RpcController;Lorg/apache/hadoop/hbase/shaded/protobuf/generated/MasterProtos$GetProcedureResultRequest;Lorg/apache/hbase/thirdparty/com/google/protobuf/RpcCallback;)V
      74: new           #22                 // class org/apache/hadoop/hbase/client/TestAsyncAdminRpcPriority$2
      77: dup
      78: aload_0
      79: invokespecial #23                 // Method org/apache/hadoop/hbase/client/TestAsyncAdminRpcPriority$2."<init>":(Lorg/apache/hadoop/hbase/client/TestAsyncAdminRpcPriority;)V
      82: invokestatic  #13                 // Method org/mockito/Mockito.doAnswer:(Lorg/mockito/stubbing/Answer;)Lorg/mockito/stubbing/Stubber;
      85: aload_0
      86: getfield      #3                  // Field masterStub:Lorg/apache/hadoop/hbase/shaded/protobuf/generated/MasterProtos$MasterService$Interface;
      89: invokeinterface #14,  2           // InterfaceMethod org/mockito/stubbing/Stubber.when:(Ljava/lang/Object;)Ljava/lang/Object;
      94: checkcast     #8                  // class org/apache/hadoop/hbase/shaded/protobuf/generated/MasterProtos$MasterService$Interface
      97: ldc           #15                 // class org/apache/hadoop/hbase/ipc/HBaseRpcController
      99: invokestatic  #16                 // Method org/mockito/ArgumentMatchers.any:(Ljava/lang/Class;)Ljava/lang/Object;
     102: checkcast     #17                 // class org/apache/hbase/thirdparty/com/google/protobuf/RpcController
     105: ldc           #24                 // class org/apache/hadoop/hbase/shaded/protobuf/generated/MasterProtos$CreateTableRequest
     107: invokestatic  #16                 // Method org/mockito/ArgumentMatchers.any:(Ljava/lang/Class;)Ljava/lang/Object;
     110: checkcast     #24                 // class org/apache/hadoop/hbase/shaded/protobuf/generated/MasterProtos$CreateTableRequest
     113: invokestatic  #19                 // Method org/mockito/ArgumentMatchers.any:()Ljava/lang/Object;
     116: checkcast     #20                 // class org/apache/hbase/thirdparty/com/google/protobuf/RpcCallback
     119: invokeinterface #25,  4           // InterfaceMethod org/apache/hadoop/hbase/shaded/protobuf/generated/MasterProtos$MasterService$Interface.createTable:(Lorg/apache/hbase/thirdparty/com/google/protobuf/RpcController;Lorg/apache/hadoop/hbase/shaded/protobuf/generated/MasterProtos$CreateTableRequest;Lorg/apache/hbase/thirdparty/com/google/protobuf/RpcCallback;)V
     124: new           #26                 // class org/apache/hadoop/hbase/client/TestAsyncAdminRpcPriority$3
     127: dup
     128: aload_0
     129: invokespecial #27                 // Method org/apache/hadoop/hbase/client/TestAsyncAdminRpcPriority$3."<init>":(Lorg/apache/hadoop/hbase/client/TestAsyncAdminRpcPriority;)V
     132: invokestatic  #13                 // Method org/mockito/Mockito.doAnswer:(Lorg/mockito/stubbing/Answer;)Lorg/mockito/stubbing/Stubber;
     135: aload_0
     136: getfield      #3                  // Field masterStub:Lorg/apache/hadoop/hbase/shaded/protobuf/generated/MasterProtos$MasterService$Interface;
     139: invokeinterface #14,  2           // InterfaceMethod org/mockito/stubbing/Stubber.when:(Ljava/lang/Object;)Ljava/lang/Object;
     144: checkcast     #8                  // class org/apache/hadoop/hbase/shaded/protobuf/generated/MasterProtos$MasterService$Interface
     147: ldc           #15                 // class org/apache/hadoop/hbase/ipc/HBaseRpcController
     149: invokestatic  #16                 // Method org/mockito/ArgumentMatchers.any:(Ljava/lang/Class;)Ljava/lang/Object;
     152: checkcast     #17                 // class org/apache/hbase/thirdparty/com/google/protobuf/RpcController
     155: ldc           #28                 // class org/apache/hadoop/hbase/shaded/protobuf/generated/MasterProtos$ShutdownRequest
     157: invokestatic  #16                 // Method org/mockito/ArgumentMatchers.any:(Ljava/lang/Class;)Ljava/lang/Object;
     160: checkcast     #28                 // class org/apache/hadoop/hbase/shaded/protobuf/generated/MasterProtos$ShutdownRequest
     163: invokestatic  #19                 // Method org/mockito/ArgumentMatchers.any:()Ljava/lang/Object;
     166: checkcast     #20                 // class org/apache/hbase/thirdparty/com/google/protobuf/RpcCallback
     169: invokeinterface #29,  4           // InterfaceMethod org/apache/hadoop/hbase/shaded/protobuf/generated/MasterProtos$MasterService$Interface.shutdown:(Lorg/apache/hbase/thirdparty/com/google/protobuf/RpcController;Lorg/apache/hadoop/hbase/shaded/protobuf/generated/MasterProtos$ShutdownRequest;Lorg/apache/hbase/thirdparty/com/google/protobuf/RpcCallback;)V
     174: new           #30                 // class org/apache/hadoop/hbase/client/TestAsyncAdminRpcPriority$4
     177: dup
     178: aload_0
     179: invokespecial #31                 // Method org/apache/hadoop/hbase/client/TestAsyncAdminRpcPriority$4."<init>":(Lorg/apache/hadoop/hbase/client/TestAsyncAdminRpcPriority;)V
     182: invokestatic  #13                 // Method org/mockito/Mockito.doAnswer:(Lorg/mockito/stubbing/Answer;)Lorg/mockito/stubbing/Stubber;
     185: aload_0
     186: getfield      #3                  // Field masterStub:Lorg/apache/hadoop/hbase/shaded/protobuf/generated/MasterProtos$MasterService$Interface;
     189: invokeinterface #14,  2           // InterfaceMethod org/mockito/stubbing/Stubber.when:(Ljava/lang/Object;)Ljava/lang/Object;
     194: checkcast     #8                  // class org/apache/hadoop/hbase/shaded/protobuf/generated/MasterProtos$MasterService$Interface
     197: ldc           #15                 // class org/apache/hadoop/hbase/ipc/HBaseRpcController
     199: invokestatic  #16                 // Method org/mockito/ArgumentMatchers.any:(Ljava/lang/Class;)Ljava/lang/Object;
     202: checkcast     #17                 // class org/apache/hbase/thirdparty/com/google/protobuf/RpcController
     205: ldc           #32                 // class org/apache/hadoop/hbase/shaded/protobuf/generated/MasterProtos$StopMasterRequest
     207: invokestatic  #16                 // Method org/mockito/ArgumentMatchers.any:(Ljava/lang/Class;)Ljava/lang/Object;
     210: checkcast     #32                 // class org/apache/hadoop/hbase/shaded/protobuf/generated/MasterProtos$StopMasterRequest
     213: invokestatic  #19                 // Method org/mockito/ArgumentMatchers.any:()Ljava/lang/Object;
     216: checkcast     #20                 // class org/apache/hbase/thirdparty/com/google/protobuf/RpcCallback
     219: invokeinterface #33,  4           // InterfaceMethod org/apache/hadoop/hbase/shaded/protobuf/generated/MasterProtos$MasterService$Interface.stopMaster:(Lorg/apache/hbase/thirdparty/com/google/protobuf/RpcController;Lorg/apache/hadoop/hbase/shaded/protobuf/generated/MasterProtos$StopMasterRequest;Lorg/apache/hbase/thirdparty/com/google/protobuf/RpcCallback;)V
     224: new           #34                 // class org/apache/hadoop/hbase/client/TestAsyncAdminRpcPriority$5
     227: dup
     228: aload_0
     229: invokespecial #35                 // Method org/apache/hadoop/hbase/client/TestAsyncAdminRpcPriority$5."<init>":(Lorg/apache/hadoop/hbase/client/TestAsyncAdminRpcPriority;)V
     232: invokestatic  #13                 // Method org/mockito/Mockito.doAnswer:(Lorg/mockito/stubbing/Answer;)Lorg/mockito/stubbing/Stubber;
     235: aload_0
     236: getfield      #2                  // Field adminStub:Lorg/apache/hadoop/hbase/shaded/protobuf/generated/AdminProtos$AdminService$Interface;
     239: invokeinterface #14,  2           // InterfaceMethod org/mockito/stubbing/Stubber.when:(Ljava/lang/Object;)Ljava/lang/Object;
     244: checkcast     #10                 // class org/apache/hadoop/hbase/shaded/protobuf/generated/AdminProtos$AdminService$Interface
     247: ldc           #15                 // class org/apache/hadoop/hbase/ipc/HBaseRpcController
     249: invokestatic  #16                 // Method org/mockito/ArgumentMatchers.any:(Ljava/lang/Class;)Ljava/lang/Object;
     252: checkcast     #17                 // class org/apache/hbase/thirdparty/com/google/protobuf/RpcController
     255: ldc           #36                 // class org/apache/hadoop/hbase/shaded/protobuf/generated/AdminProtos$StopServerRequest
     257: invokestatic  #16                 // Method org/mockito/ArgumentMatchers.any:(Ljava/lang/Class;)Ljava/lang/Object;
     260: checkcast     #36                 // class org/apache/hadoop/hbase/shaded/protobuf/generated/AdminProtos$StopServerRequest
     263: invokestatic  #19                 // Method org/mockito/ArgumentMatchers.any:()Ljava/lang/Object;
     266: checkcast     #20                 // class org/apache/hbase/thirdparty/com/google/protobuf/RpcCallback
     269: invokeinterface #37,  4           // InterfaceMethod org/apache/hadoop/hbase/shaded/protobuf/generated/AdminProtos$AdminService$Interface.stopServer:(Lorg/apache/hbase/thirdparty/com/google/protobuf/RpcController;Lorg/apache/hadoop/hbase/shaded/protobuf/generated/AdminProtos$StopServerRequest;Lorg/apache/hbase/thirdparty/com/google/protobuf/RpcCallback;)V
     274: aload_0
     275: new           #38                 // class org/apache/hadoop/hbase/client/TestAsyncAdminRpcPriority$6
     278: dup
     279: aload_0
     280: getstatic     #39                 // Field CONF:Lorg/apache/hadoop/conf/Configuration;
     283: new           #40                 // class org/apache/hadoop/hbase/client/DoNothingAsyncRegistry
     286: dup
     287: getstatic     #39                 // Field CONF:Lorg/apache/hadoop/conf/Configuration;
     290: invokespecial #41                 // Method org/apache/hadoop/hbase/client/DoNothingAsyncRegistry."<init>":(Lorg/apache/hadoop/conf/Configuration;)V
     293: ldc           #42                 // String test
     295: getstatic     #39                 // Field CONF:Lorg/apache/hadoop/conf/Configuration;
     298: invokestatic  #43                 // Method org/apache/hadoop/hbase/security/UserProvider.instantiate:(Lorg/apache/hadoop/conf/Configuration;)Lorg/apache/hadoop/hbase/security/UserProvider;
     301: invokevirtual #44                 // Method org/apache/hadoop/hbase/security/UserProvider.getCurrent:()Lorg/apache/hadoop/hbase/security/User;
     304: invokespecial #45                 // Method org/apache/hadoop/hbase/client/TestAsyncAdminRpcPriority$6."<init>":(Lorg/apache/hadoop/hbase/client/TestAsyncAdminRpcPriority;Lorg/apache/hadoop/conf/Configuration;Lorg/apache/hadoop/hbase/client/AsyncRegistry;Ljava/lang/String;Lorg/apache/hadoop/hbase/security/User;)V
     307: putfield      #46                 // Field conn:Lorg/apache/hadoop/hbase/client/AsyncConnection;
     310: return

  public void testCreateNormalTable();
    Code:
       0: aload_0
       1: getfield      #46                 // Field conn:Lorg/apache/hadoop/hbase/client/AsyncConnection;
       4: invokeinterface #50,  1           // InterfaceMethod org/apache/hadoop/hbase/client/AsyncConnection.getAdmin:()Lorg/apache/hadoop/hbase/client/AsyncAdmin;
       9: aload_0
      10: getfield      #7                  // Field name:Lorg/junit/rules/TestName;
      13: invokevirtual #51                 // Method org/junit/rules/TestName.getMethodName:()Ljava/lang/String;
      16: invokestatic  #52                 // Method org/apache/hadoop/hbase/TableName.valueOf:(Ljava/lang/String;)Lorg/apache/hadoop/hbase/TableName;
      19: invokestatic  #53                 // Method org/apache/hadoop/hbase/client/TableDescriptorBuilder.newBuilder:(Lorg/apache/hadoop/hbase/TableName;)Lorg/apache/hadoop/hbase/client/TableDescriptorBuilder;
      22: ldc           #54                 // String cf
      24: invokestatic  #55                 // Method org/apache/hadoop/hbase/client/ColumnFamilyDescriptorBuilder.of:(Ljava/lang/String;)Lorg/apache/hadoop/hbase/client/ColumnFamilyDescriptor;
      27: invokevirtual #56                 // Method org/apache/hadoop/hbase/client/TableDescriptorBuilder.setColumnFamily:(Lorg/apache/hadoop/hbase/client/ColumnFamilyDescriptor;)Lorg/apache/hadoop/hbase/client/TableDescriptorBuilder;
      30: invokevirtual #57                 // Method org/apache/hadoop/hbase/client/TableDescriptorBuilder.build:()Lorg/apache/hadoop/hbase/client/TableDescriptor;
      33: invokeinterface #58,  2           // InterfaceMethod org/apache/hadoop/hbase/client/AsyncAdmin.createTable:(Lorg/apache/hadoop/hbase/client/TableDescriptor;)Ljava/util/concurrent/CompletableFuture;
      38: invokevirtual #59                 // Method java/util/concurrent/CompletableFuture.join:()Ljava/lang/Object;
      41: pop
      42: aload_0
      43: getfield      #3                  // Field masterStub:Lorg/apache/hadoop/hbase/shaded/protobuf/generated/MasterProtos$MasterService$Interface;
      46: iconst_1
      47: invokestatic  #60                 // Method org/mockito/Mockito.times:(I)Lorg/mockito/verification/VerificationMode;
      50: invokestatic  #61                 // Method org/mockito/Mockito.verify:(Ljava/lang/Object;Lorg/mockito/verification/VerificationMode;)Ljava/lang/Object;
      53: checkcast     #8                  // class org/apache/hadoop/hbase/shaded/protobuf/generated/MasterProtos$MasterService$Interface
      56: aload_0
      57: iconst_0
      58: invokespecial #62                 // Method assertPriority:(I)Lorg/apache/hadoop/hbase/ipc/HBaseRpcController;
      61: ldc           #24                 // class org/apache/hadoop/hbase/shaded/protobuf/generated/MasterProtos$CreateTableRequest
      63: invokestatic  #16                 // Method org/mockito/ArgumentMatchers.any:(Ljava/lang/Class;)Ljava/lang/Object;
      66: checkcast     #24                 // class org/apache/hadoop/hbase/shaded/protobuf/generated/MasterProtos$CreateTableRequest
      69: invokestatic  #19                 // Method org/mockito/ArgumentMatchers.any:()Ljava/lang/Object;
      72: checkcast     #20                 // class org/apache/hbase/thirdparty/com/google/protobuf/RpcCallback
      75: invokeinterface #25,  4           // InterfaceMethod org/apache/hadoop/hbase/shaded/protobuf/generated/MasterProtos$MasterService$Interface.createTable:(Lorg/apache/hbase/thirdparty/com/google/protobuf/RpcController;Lorg/apache/hadoop/hbase/shaded/protobuf/generated/MasterProtos$CreateTableRequest;Lorg/apache/hbase/thirdparty/com/google/protobuf/RpcCallback;)V
      80: return

  public void testCreateSystemTable();
    Code:
       0: aload_0
       1: getfield      #46                 // Field conn:Lorg/apache/hadoop/hbase/client/AsyncConnection;
       4: invokeinterface #50,  1           // InterfaceMethod org/apache/hadoop/hbase/client/AsyncConnection.getAdmin:()Lorg/apache/hadoop/hbase/client/AsyncAdmin;
       9: getstatic     #63                 // Field org/apache/hadoop/hbase/NamespaceDescriptor.SYSTEM_NAMESPACE_NAME_STR:Ljava/lang/String;
      12: aload_0
      13: getfield      #7                  // Field name:Lorg/junit/rules/TestName;
      16: invokevirtual #51                 // Method org/junit/rules/TestName.getMethodName:()Ljava/lang/String;
      19: invokestatic  #64                 // Method org/apache/hadoop/hbase/TableName.valueOf:(Ljava/lang/String;Ljava/lang/String;)Lorg/apache/hadoop/hbase/TableName;
      22: invokestatic  #53                 // Method org/apache/hadoop/hbase/client/TableDescriptorBuilder.newBuilder:(Lorg/apache/hadoop/hbase/TableName;)Lorg/apache/hadoop/hbase/client/TableDescriptorBuilder;
      25: ldc           #54                 // String cf
      27: invokestatic  #55                 // Method org/apache/hadoop/hbase/client/ColumnFamilyDescriptorBuilder.of:(Ljava/lang/String;)Lorg/apache/hadoop/hbase/client/ColumnFamilyDescriptor;
      30: invokevirtual #56                 // Method org/apache/hadoop/hbase/client/TableDescriptorBuilder.setColumnFamily:(Lorg/apache/hadoop/hbase/client/ColumnFamilyDescriptor;)Lorg/apache/hadoop/hbase/client/TableDescriptorBuilder;
      33: invokevirtual #57                 // Method org/apache/hadoop/hbase/client/TableDescriptorBuilder.build:()Lorg/apache/hadoop/hbase/client/TableDescriptor;
      36: invokeinterface #58,  2           // InterfaceMethod org/apache/hadoop/hbase/client/AsyncAdmin.createTable:(Lorg/apache/hadoop/hbase/client/TableDescriptor;)Ljava/util/concurrent/CompletableFuture;
      41: invokevirtual #59                 // Method java/util/concurrent/CompletableFuture.join:()Ljava/lang/Object;
      44: pop
      45: aload_0
      46: getfield      #3                  // Field masterStub:Lorg/apache/hadoop/hbase/shaded/protobuf/generated/MasterProtos$MasterService$Interface;
      49: iconst_1
      50: invokestatic  #60                 // Method org/mockito/Mockito.times:(I)Lorg/mockito/verification/VerificationMode;
      53: invokestatic  #61                 // Method org/mockito/Mockito.verify:(Ljava/lang/Object;Lorg/mockito/verification/VerificationMode;)Ljava/lang/Object;
      56: checkcast     #8                  // class org/apache/hadoop/hbase/shaded/protobuf/generated/MasterProtos$MasterService$Interface
      59: aload_0
      60: sipush        200
      63: invokespecial #62                 // Method assertPriority:(I)Lorg/apache/hadoop/hbase/ipc/HBaseRpcController;
      66: ldc           #24                 // class org/apache/hadoop/hbase/shaded/protobuf/generated/MasterProtos$CreateTableRequest
      68: invokestatic  #16                 // Method org/mockito/ArgumentMatchers.any:(Ljava/lang/Class;)Ljava/lang/Object;
      71: checkcast     #24                 // class org/apache/hadoop/hbase/shaded/protobuf/generated/MasterProtos$CreateTableRequest
      74: invokestatic  #19                 // Method org/mockito/ArgumentMatchers.any:()Ljava/lang/Object;
      77: checkcast     #20                 // class org/apache/hbase/thirdparty/com/google/protobuf/RpcCallback
      80: invokeinterface #25,  4           // InterfaceMethod org/apache/hadoop/hbase/shaded/protobuf/generated/MasterProtos$MasterService$Interface.createTable:(Lorg/apache/hbase/thirdparty/com/google/protobuf/RpcController;Lorg/apache/hadoop/hbase/shaded/protobuf/generated/MasterProtos$CreateTableRequest;Lorg/apache/hbase/thirdparty/com/google/protobuf/RpcCallback;)V
      85: return

  public void testCreateMetaTable();
    Code:
       0: aload_0
       1: getfield      #46                 // Field conn:Lorg/apache/hadoop/hbase/client/AsyncConnection;
       4: invokeinterface #50,  1           // InterfaceMethod org/apache/hadoop/hbase/client/AsyncConnection.getAdmin:()Lorg/apache/hadoop/hbase/client/AsyncAdmin;
       9: getstatic     #65                 // Field org/apache/hadoop/hbase/TableName.META_TABLE_NAME:Lorg/apache/hadoop/hbase/TableName;
      12: invokestatic  #53                 // Method org/apache/hadoop/hbase/client/TableDescriptorBuilder.newBuilder:(Lorg/apache/hadoop/hbase/TableName;)Lorg/apache/hadoop/hbase/client/TableDescriptorBuilder;
      15: ldc           #54                 // String cf
      17: invokestatic  #55                 // Method org/apache/hadoop/hbase/client/ColumnFamilyDescriptorBuilder.of:(Ljava/lang/String;)Lorg/apache/hadoop/hbase/client/ColumnFamilyDescriptor;
      20: invokevirtual #56                 // Method org/apache/hadoop/hbase/client/TableDescriptorBuilder.setColumnFamily:(Lorg/apache/hadoop/hbase/client/ColumnFamilyDescriptor;)Lorg/apache/hadoop/hbase/client/TableDescriptorBuilder;
      23: invokevirtual #57                 // Method org/apache/hadoop/hbase/client/TableDescriptorBuilder.build:()Lorg/apache/hadoop/hbase/client/TableDescriptor;
      26: invokeinterface #58,  2           // InterfaceMethod org/apache/hadoop/hbase/client/AsyncAdmin.createTable:(Lorg/apache/hadoop/hbase/client/TableDescriptor;)Ljava/util/concurrent/CompletableFuture;
      31: invokevirtual #59                 // Method java/util/concurrent/CompletableFuture.join:()Ljava/lang/Object;
      34: pop
      35: aload_0
      36: getfield      #3                  // Field masterStub:Lorg/apache/hadoop/hbase/shaded/protobuf/generated/MasterProtos$MasterService$Interface;
      39: iconst_1
      40: invokestatic  #60                 // Method org/mockito/Mockito.times:(I)Lorg/mockito/verification/VerificationMode;
      43: invokestatic  #61                 // Method org/mockito/Mockito.verify:(Ljava/lang/Object;Lorg/mockito/verification/VerificationMode;)Ljava/lang/Object;
      46: checkcast     #8                  // class org/apache/hadoop/hbase/shaded/protobuf/generated/MasterProtos$MasterService$Interface
      49: aload_0
      50: sipush        200
      53: invokespecial #62                 // Method assertPriority:(I)Lorg/apache/hadoop/hbase/ipc/HBaseRpcController;
      56: ldc           #24                 // class org/apache/hadoop/hbase/shaded/protobuf/generated/MasterProtos$CreateTableRequest
      58: invokestatic  #16                 // Method org/mockito/ArgumentMatchers.any:(Ljava/lang/Class;)Ljava/lang/Object;
      61: checkcast     #24                 // class org/apache/hadoop/hbase/shaded/protobuf/generated/MasterProtos$CreateTableRequest
      64: invokestatic  #19                 // Method org/mockito/ArgumentMatchers.any:()Ljava/lang/Object;
      67: checkcast     #20                 // class org/apache/hbase/thirdparty/com/google/protobuf/RpcCallback
      70: invokeinterface #25,  4           // InterfaceMethod org/apache/hadoop/hbase/shaded/protobuf/generated/MasterProtos$MasterService$Interface.createTable:(Lorg/apache/hbase/thirdparty/com/google/protobuf/RpcController;Lorg/apache/hadoop/hbase/shaded/protobuf/generated/MasterProtos$CreateTableRequest;Lorg/apache/hbase/thirdparty/com/google/protobuf/RpcCallback;)V
      75: return

  public void testShutdown();
    Code:
       0: aload_0
       1: getfield      #46                 // Field conn:Lorg/apache/hadoop/hbase/client/AsyncConnection;
       4: invokeinterface #50,  1           // InterfaceMethod org/apache/hadoop/hbase/client/AsyncConnection.getAdmin:()Lorg/apache/hadoop/hbase/client/AsyncAdmin;
       9: invokeinterface #66,  1           // InterfaceMethod org/apache/hadoop/hbase/client/AsyncAdmin.shutdown:()Ljava/util/concurrent/CompletableFuture;
      14: invokevirtual #59                 // Method java/util/concurrent/CompletableFuture.join:()Ljava/lang/Object;
      17: pop
      18: aload_0
      19: getfield      #3                  // Field masterStub:Lorg/apache/hadoop/hbase/shaded/protobuf/generated/MasterProtos$MasterService$Interface;
      22: iconst_1
      23: invokestatic  #60                 // Method org/mockito/Mockito.times:(I)Lorg/mockito/verification/VerificationMode;
      26: invokestatic  #61                 // Method org/mockito/Mockito.verify:(Ljava/lang/Object;Lorg/mockito/verification/VerificationMode;)Ljava/lang/Object;
      29: checkcast     #8                  // class org/apache/hadoop/hbase/shaded/protobuf/generated/MasterProtos$MasterService$Interface
      32: aload_0
      33: sipush        200
      36: invokespecial #62                 // Method assertPriority:(I)Lorg/apache/hadoop/hbase/ipc/HBaseRpcController;
      39: ldc           #28                 // class org/apache/hadoop/hbase/shaded/protobuf/generated/MasterProtos$ShutdownRequest
      41: invokestatic  #16                 // Method org/mockito/ArgumentMatchers.any:(Ljava/lang/Class;)Ljava/lang/Object;
      44: checkcast     #28                 // class org/apache/hadoop/hbase/shaded/protobuf/generated/MasterProtos$ShutdownRequest
      47: invokestatic  #19                 // Method org/mockito/ArgumentMatchers.any:()Ljava/lang/Object;
      50: checkcast     #20                 // class org/apache/hbase/thirdparty/com/google/protobuf/RpcCallback
      53: invokeinterface #29,  4           // InterfaceMethod org/apache/hadoop/hbase/shaded/protobuf/generated/MasterProtos$MasterService$Interface.shutdown:(Lorg/apache/hbase/thirdparty/com/google/protobuf/RpcController;Lorg/apache/hadoop/hbase/shaded/protobuf/generated/MasterProtos$ShutdownRequest;Lorg/apache/hbase/thirdparty/com/google/protobuf/RpcCallback;)V
      58: return

  public void testStopMaster();
    Code:
       0: aload_0
       1: getfield      #46                 // Field conn:Lorg/apache/hadoop/hbase/client/AsyncConnection;
       4: invokeinterface #50,  1           // InterfaceMethod org/apache/hadoop/hbase/client/AsyncConnection.getAdmin:()Lorg/apache/hadoop/hbase/client/AsyncAdmin;
       9: invokeinterface #67,  1           // InterfaceMethod org/apache/hadoop/hbase/client/AsyncAdmin.stopMaster:()Ljava/util/concurrent/CompletableFuture;
      14: invokevirtual #59                 // Method java/util/concurrent/CompletableFuture.join:()Ljava/lang/Object;
      17: pop
      18: aload_0
      19: getfield      #3                  // Field masterStub:Lorg/apache/hadoop/hbase/shaded/protobuf/generated/MasterProtos$MasterService$Interface;
      22: iconst_1
      23: invokestatic  #60                 // Method org/mockito/Mockito.times:(I)Lorg/mockito/verification/VerificationMode;
      26: invokestatic  #61                 // Method org/mockito/Mockito.verify:(Ljava/lang/Object;Lorg/mockito/verification/VerificationMode;)Ljava/lang/Object;
      29: checkcast     #8                  // class org/apache/hadoop/hbase/shaded/protobuf/generated/MasterProtos$MasterService$Interface
      32: aload_0
      33: sipush        200
      36: invokespecial #62                 // Method assertPriority:(I)Lorg/apache/hadoop/hbase/ipc/HBaseRpcController;
      39: ldc           #32                 // class org/apache/hadoop/hbase/shaded/protobuf/generated/MasterProtos$StopMasterRequest
      41: invokestatic  #16                 // Method org/mockito/ArgumentMatchers.any:(Ljava/lang/Class;)Ljava/lang/Object;
      44: checkcast     #32                 // class org/apache/hadoop/hbase/shaded/protobuf/generated/MasterProtos$StopMasterRequest
      47: invokestatic  #19                 // Method org/mockito/ArgumentMatchers.any:()Ljava/lang/Object;
      50: checkcast     #20                 // class org/apache/hbase/thirdparty/com/google/protobuf/RpcCallback
      53: invokeinterface #33,  4           // InterfaceMethod org/apache/hadoop/hbase/shaded/protobuf/generated/MasterProtos$MasterService$Interface.stopMaster:(Lorg/apache/hbase/thirdparty/com/google/protobuf/RpcController;Lorg/apache/hadoop/hbase/shaded/protobuf/generated/MasterProtos$StopMasterRequest;Lorg/apache/hbase/thirdparty/com/google/protobuf/RpcCallback;)V
      58: return

  public void testStopRegionServer();
    Code:
       0: aload_0
       1: getfield      #46                 // Field conn:Lorg/apache/hadoop/hbase/client/AsyncConnection;
       4: invokeinterface #50,  1           // InterfaceMethod org/apache/hadoop/hbase/client/AsyncConnection.getAdmin:()Lorg/apache/hadoop/hbase/client/AsyncAdmin;
       9: ldc           #68                 // String rs
      11: sipush        16010
      14: ldc2_w        #69                 // long 12345l
      17: invokestatic  #71                 // Method org/apache/hadoop/hbase/ServerName.valueOf:(Ljava/lang/String;IJ)Lorg/apache/hadoop/hbase/ServerName;
      20: invokeinterface #72,  2           // InterfaceMethod org/apache/hadoop/hbase/client/AsyncAdmin.stopRegionServer:(Lorg/apache/hadoop/hbase/ServerName;)Ljava/util/concurrent/CompletableFuture;
      25: invokevirtual #59                 // Method java/util/concurrent/CompletableFuture.join:()Ljava/lang/Object;
      28: pop
      29: aload_0
      30: getfield      #2                  // Field adminStub:Lorg/apache/hadoop/hbase/shaded/protobuf/generated/AdminProtos$AdminService$Interface;
      33: iconst_1
      34: invokestatic  #60                 // Method org/mockito/Mockito.times:(I)Lorg/mockito/verification/VerificationMode;
      37: invokestatic  #61                 // Method org/mockito/Mockito.verify:(Ljava/lang/Object;Lorg/mockito/verification/VerificationMode;)Ljava/lang/Object;
      40: checkcast     #10                 // class org/apache/hadoop/hbase/shaded/protobuf/generated/AdminProtos$AdminService$Interface
      43: aload_0
      44: sipush        200
      47: invokespecial #62                 // Method assertPriority:(I)Lorg/apache/hadoop/hbase/ipc/HBaseRpcController;
      50: ldc           #36                 // class org/apache/hadoop/hbase/shaded/protobuf/generated/AdminProtos$StopServerRequest
      52: invokestatic  #16                 // Method org/mockito/ArgumentMatchers.any:(Ljava/lang/Class;)Ljava/lang/Object;
      55: checkcast     #36                 // class org/apache/hadoop/hbase/shaded/protobuf/generated/AdminProtos$StopServerRequest
      58: invokestatic  #19                 // Method org/mockito/ArgumentMatchers.any:()Ljava/lang/Object;
      61: checkcast     #20                 // class org/apache/hbase/thirdparty/com/google/protobuf/RpcCallback
      64: invokeinterface #37,  4           // InterfaceMethod org/apache/hadoop/hbase/shaded/protobuf/generated/AdminProtos$AdminService$Interface.stopServer:(Lorg/apache/hbase/thirdparty/com/google/protobuf/RpcController;Lorg/apache/hadoop/hbase/shaded/protobuf/generated/AdminProtos$StopServerRequest;Lorg/apache/hbase/thirdparty/com/google/protobuf/RpcCallback;)V
      69: return

  static org.apache.hadoop.hbase.shaded.protobuf.generated.MasterProtos$MasterService$Interface access$000(org.apache.hadoop.hbase.client.TestAsyncAdminRpcPriority);
    Code:
       0: aload_0
       1: getfield      #3                  // Field masterStub:Lorg/apache/hadoop/hbase/shaded/protobuf/generated/MasterProtos$MasterService$Interface;
       4: areturn

  static org.apache.hadoop.hbase.shaded.protobuf.generated.AdminProtos$AdminService$Interface access$100(org.apache.hadoop.hbase.client.TestAsyncAdminRpcPriority);
    Code:
       0: aload_0
       1: getfield      #2                  // Field adminStub:Lorg/apache/hadoop/hbase/shaded/protobuf/generated/AdminProtos$AdminService$Interface;
       4: areturn

  static {};
    Code:
       0: ldc           #73                 // class org/apache/hadoop/hbase/client/TestAsyncAdminRpcPriority
       2: invokestatic  #74                 // Method org/apache/hadoop/hbase/HBaseClassTestRule.forClass:(Ljava/lang/Class;)Lorg/apache/hadoop/hbase/HBaseClassTestRule;
       5: putstatic     #75                 // Field CLASS_RULE:Lorg/apache/hadoop/hbase/HBaseClassTestRule;
       8: invokestatic  #76                 // Method org/apache/hadoop/hbase/HBaseConfiguration.create:()Lorg/apache/hadoop/conf/Configuration;
      11: putstatic     #39                 // Field CONF:Lorg/apache/hadoop/conf/Configuration;
      14: return
}
