Compiled from "TestAtomicOperation.java"
final class org.apache.hadoop.hbase.regionserver.TestAtomicOperation$TestStep extends java.lang.Enum<org.apache.hadoop.hbase.regionserver.TestAtomicOperation$TestStep> {
  public static final org.apache.hadoop.hbase.regionserver.TestAtomicOperation$TestStep INIT;

  public static final org.apache.hadoop.hbase.regionserver.TestAtomicOperation$TestStep PUT_STARTED;

  public static final org.apache.hadoop.hbase.regionserver.TestAtomicOperation$TestStep PUT_COMPLETED;

  public static final org.apache.hadoop.hbase.regionserver.TestAtomicOperation$TestStep CHECKANDPUT_STARTED;

  public static final org.apache.hadoop.hbase.regionserver.TestAtomicOperation$TestStep CHECKANDPUT_COMPLETED;

  public static org.apache.hadoop.hbase.regionserver.TestAtomicOperation$TestStep[] values();
    Code:
       0: getstatic     #1                  // Field $VALUES:[Lorg/apache/hadoop/hbase/regionserver/TestAtomicOperation$TestStep;
       3: invokevirtual #2                  // Method "[Lorg/apache/hadoop/hbase/regionserver/TestAtomicOperation$TestStep;".clone:()Ljava/lang/Object;
       6: checkcast     #3                  // class "[Lorg/apache/hadoop/hbase/regionserver/TestAtomicOperation$TestStep;"
       9: areturn

  public static org.apache.hadoop.hbase.regionserver.TestAtomicOperation$TestStep valueOf(java.lang.String);
    Code:
       0: ldc           #4                  // class org/apache/hadoop/hbase/regionserver/TestAtomicOperation$TestStep
       2: aload_0
       3: invokestatic  #5                  // Method java/lang/Enum.valueOf:(Ljava/lang/Class;Ljava/lang/String;)Ljava/lang/Enum;
       6: checkcast     #4                  // class org/apache/hadoop/hbase/regionserver/TestAtomicOperation$TestStep
       9: areturn

  static {};
    Code:
       0: new           #4                  // class org/apache/hadoop/hbase/regionserver/TestAtomicOperation$TestStep
       3: dup
       4: ldc           #7                  // String INIT
       6: iconst_0
       7: invokespecial #8                  // Method "<init>":(Ljava/lang/String;I)V
      10: putstatic     #9                  // Field INIT:Lorg/apache/hadoop/hbase/regionserver/TestAtomicOperation$TestStep;
      13: new           #4                  // class org/apache/hadoop/hbase/regionserver/TestAtomicOperation$TestStep
      16: dup
      17: ldc           #10                 // String PUT_STARTED
      19: iconst_1
      20: invokespecial #8                  // Method "<init>":(Ljava/lang/String;I)V
      23: putstatic     #11                 // Field PUT_STARTED:Lorg/apache/hadoop/hbase/regionserver/TestAtomicOperation$TestStep;
      26: new           #4                  // class org/apache/hadoop/hbase/regionserver/TestAtomicOperation$TestStep
      29: dup
      30: ldc           #12                 // String PUT_COMPLETED
      32: iconst_2
      33: invokespecial #8                  // Method "<init>":(Ljava/lang/String;I)V
      36: putstatic     #13                 // Field PUT_COMPLETED:Lorg/apache/hadoop/hbase/regionserver/TestAtomicOperation$TestStep;
      39: new           #4                  // class org/apache/hadoop/hbase/regionserver/TestAtomicOperation$TestStep
      42: dup
      43: ldc           #14                 // String CHECKANDPUT_STARTED
      45: iconst_3
      46: invokespecial #8                  // Method "<init>":(Ljava/lang/String;I)V
      49: putstatic     #15                 // Field CHECKANDPUT_STARTED:Lorg/apache/hadoop/hbase/regionserver/TestAtomicOperation$TestStep;
      52: new           #4                  // class org/apache/hadoop/hbase/regionserver/TestAtomicOperation$TestStep
      55: dup
      56: ldc           #16                 // String CHECKANDPUT_COMPLETED
      58: iconst_4
      59: invokespecial #8                  // Method "<init>":(Ljava/lang/String;I)V
      62: putstatic     #17                 // Field CHECKANDPUT_COMPLETED:Lorg/apache/hadoop/hbase/regionserver/TestAtomicOperation$TestStep;
      65: iconst_5
      66: anewarray     #4                  // class org/apache/hadoop/hbase/regionserver/TestAtomicOperation$TestStep
      69: dup
      70: iconst_0
      71: getstatic     #9                  // Field INIT:Lorg/apache/hadoop/hbase/regionserver/TestAtomicOperation$TestStep;
      74: aastore
      75: dup
      76: iconst_1
      77: getstatic     #11                 // Field PUT_STARTED:Lorg/apache/hadoop/hbase/regionserver/TestAtomicOperation$TestStep;
      80: aastore
      81: dup
      82: iconst_2
      83: getstatic     #13                 // Field PUT_COMPLETED:Lorg/apache/hadoop/hbase/regionserver/TestAtomicOperation$TestStep;
      86: aastore
      87: dup
      88: iconst_3
      89: getstatic     #15                 // Field CHECKANDPUT_STARTED:Lorg/apache/hadoop/hbase/regionserver/TestAtomicOperation$TestStep;
      92: aastore
      93: dup
      94: iconst_4
      95: getstatic     #17                 // Field CHECKANDPUT_COMPLETED:Lorg/apache/hadoop/hbase/regionserver/TestAtomicOperation$TestStep;
      98: aastore
      99: putstatic     #1                  // Field $VALUES:[Lorg/apache/hadoop/hbase/regionserver/TestAtomicOperation$TestStep;
     102: return
}
