Compiled from "TestRegionServerMetrics.java"
public class org.apache.hadoop.hbase.regionserver.TestRegionServerMetrics {
  public static final org.apache.hadoop.hbase.HBaseClassTestRule CLASS_RULE;

  public org.junit.rules.TestName testName;

  org.apache.hadoop.hbase.TableName tableName;

  org.apache.hadoop.hbase.client.Table table;

  public org.apache.hadoop.hbase.regionserver.TestRegionServerMetrics();
    Code:
       0: aload_0
       1: invokespecial #1                  // Method java/lang/Object."<init>":()V
       4: aload_0
       5: new           #2                  // class org/junit/rules/TestName
       8: dup
       9: invokespecial #3                  // Method org/junit/rules/TestName."<init>":()V
      12: putfield      #4                  // Field testName:Lorg/junit/rules/TestName;
      15: return

  public static void startCluster() throws java.lang.Exception;
    Code:
       0: ldc           #5                  // class org/apache/hadoop/hbase/test/MetricsAssertHelper
       2: invokestatic  #6                  // Method org/apache/hadoop/hbase/CompatibilityFactory.getInstance:(Ljava/lang/Class;)Ljava/lang/Object;
       5: checkcast     #5                  // class org/apache/hadoop/hbase/test/MetricsAssertHelper
       8: putstatic     #7                  // Field metricsHelper:Lorg/apache/hadoop/hbase/test/MetricsAssertHelper;
      11: new           #8                  // class org/apache/hadoop/hbase/HBaseTestingUtility
      14: dup
      15: invokespecial #9                  // Method org/apache/hadoop/hbase/HBaseTestingUtility."<init>":()V
      18: putstatic     #10                 // Field TEST_UTIL:Lorg/apache/hadoop/hbase/HBaseTestingUtility;
      21: getstatic     #10                 // Field TEST_UTIL:Lorg/apache/hadoop/hbase/HBaseTestingUtility;
      24: invokevirtual #11                 // Method org/apache/hadoop/hbase/HBaseTestingUtility.getConfiguration:()Lorg/apache/hadoop/conf/Configuration;
      27: invokestatic  #12                 // InterfaceMethod org/apache/hadoop/hbase/master/LoadBalancer.isTablesOnMaster:(Lorg/apache/hadoop/conf/Configuration;)Z
      30: putstatic     #13                 // Field TABLES_ON_MASTER:Z
      33: getstatic     #10                 // Field TEST_UTIL:Lorg/apache/hadoop/hbase/HBaseTestingUtility;
      36: invokevirtual #11                 // Method org/apache/hadoop/hbase/HBaseTestingUtility.getConfiguration:()Lorg/apache/hadoop/conf/Configuration;
      39: putstatic     #14                 // Field conf:Lorg/apache/hadoop/conf/Configuration;
      42: getstatic     #14                 // Field conf:Lorg/apache/hadoop/conf/Configuration;
      45: ldc           #15                 // String hbase.splitlog.max.resubmit
      47: lconst_0
      48: invokevirtual #16                 // Method org/apache/hadoop/conf/Configuration.getLong:(Ljava/lang/String;J)J
      51: pop2
      52: getstatic     #14                 // Field conf:Lorg/apache/hadoop/conf/Configuration;
      55: ldc           #17                 // String zookeeper.recovery.retry
      57: iconst_0
      58: invokevirtual #18                 // Method org/apache/hadoop/conf/Configuration.setInt:(Ljava/lang/String;I)V
      61: getstatic     #14                 // Field conf:Lorg/apache/hadoop/conf/Configuration;
      64: ldc           #19                 // String hbase.hstore.compactionThreshold
      66: bipush        100
      68: invokevirtual #18                 // Method org/apache/hadoop/conf/Configuration.setInt:(Ljava/lang/String;I)V
      71: getstatic     #14                 // Field conf:Lorg/apache/hadoop/conf/Configuration;
      74: ldc           #20                 // String hbase.hstore.compaction.max
      76: bipush        100
      78: invokevirtual #18                 // Method org/apache/hadoop/conf/Configuration.setInt:(Ljava/lang/String;I)V
      81: getstatic     #14                 // Field conf:Lorg/apache/hadoop/conf/Configuration;
      84: ldc           #21                 // String hbase.regionserver.periodicmemstoreflusher.rangeofdelayseconds
      86: sipush        240
      89: invokevirtual #18                 // Method org/apache/hadoop/conf/Configuration.setInt:(Ljava/lang/String;I)V
      92: getstatic     #14                 // Field conf:Lorg/apache/hadoop/conf/Configuration;
      95: ldc           #23                 // String hbase.regionserver.info.port
      97: iconst_m1
      98: invokevirtual #18                 // Method org/apache/hadoop/conf/Configuration.setInt:(Ljava/lang/String;I)V
     101: getstatic     #10                 // Field TEST_UTIL:Lorg/apache/hadoop/hbase/HBaseTestingUtility;
     104: invokevirtual #24                 // Method org/apache/hadoop/hbase/HBaseTestingUtility.startMiniCluster:()Lorg/apache/hadoop/hbase/MiniHBaseCluster;
     107: pop
     108: getstatic     #10                 // Field TEST_UTIL:Lorg/apache/hadoop/hbase/HBaseTestingUtility;
     111: invokevirtual #25                 // Method org/apache/hadoop/hbase/HBaseTestingUtility.getHBaseCluster:()Lorg/apache/hadoop/hbase/MiniHBaseCluster;
     114: putstatic     #26                 // Field cluster:Lorg/apache/hadoop/hbase/MiniHBaseCluster;
     117: getstatic     #26                 // Field cluster:Lorg/apache/hadoop/hbase/MiniHBaseCluster;
     120: invokevirtual #27                 // Method org/apache/hadoop/hbase/MiniHBaseCluster.waitForActiveAndReadyMaster:()Z
     123: pop
     124: getstatic     #10                 // Field TEST_UTIL:Lorg/apache/hadoop/hbase/HBaseTestingUtility;
     127: invokevirtual #28                 // Method org/apache/hadoop/hbase/HBaseTestingUtility.getAdmin:()Lorg/apache/hadoop/hbase/client/Admin;
     130: putstatic     #29                 // Field admin:Lorg/apache/hadoop/hbase/client/Admin;
     133: getstatic     #10                 // Field TEST_UTIL:Lorg/apache/hadoop/hbase/HBaseTestingUtility;
     136: invokevirtual #30                 // Method org/apache/hadoop/hbase/HBaseTestingUtility.getConnection:()Lorg/apache/hadoop/hbase/client/Connection;
     139: putstatic     #31                 // Field connection:Lorg/apache/hadoop/hbase/client/Connection;
     142: getstatic     #26                 // Field cluster:Lorg/apache/hadoop/hbase/MiniHBaseCluster;
     145: invokevirtual #32                 // Method org/apache/hadoop/hbase/MiniHBaseCluster.getLiveRegionServerThreads:()Ljava/util/List;
     148: invokeinterface #33,  1           // InterfaceMethod java/util/List.isEmpty:()Z
     153: ifeq          184
     156: getstatic     #26                 // Field cluster:Lorg/apache/hadoop/hbase/MiniHBaseCluster;
     159: iconst_0
     160: invokevirtual #34                 // Method org/apache/hadoop/hbase/MiniHBaseCluster.getRegionServer:(I)Lorg/apache/hadoop/hbase/regionserver/HRegionServer;
     163: ifnonnull     184
     166: getstatic     #35                 // Field rs:Lorg/apache/hadoop/hbase/regionserver/HRegionServer;
     169: invokevirtual #36                 // Method org/apache/hadoop/hbase/regionserver/HRegionServer.getRegionServerMetrics:()Lorg/apache/hadoop/hbase/regionserver/MetricsRegionServer;
     172: ifnonnull     184
     175: ldc2_w        #37                 // long 100l
     178: invokestatic  #39                 // Method org/apache/hadoop/hbase/util/Threads.sleep:(J)V
     181: goto          142
     184: getstatic     #26                 // Field cluster:Lorg/apache/hadoop/hbase/MiniHBaseCluster;
     187: iconst_0
     188: invokevirtual #34                 // Method org/apache/hadoop/hbase/MiniHBaseCluster.getRegionServer:(I)Lorg/apache/hadoop/hbase/regionserver/HRegionServer;
     191: putstatic     #35                 // Field rs:Lorg/apache/hadoop/hbase/regionserver/HRegionServer;
     194: getstatic     #35                 // Field rs:Lorg/apache/hadoop/hbase/regionserver/HRegionServer;
     197: invokevirtual #36                 // Method org/apache/hadoop/hbase/regionserver/HRegionServer.getRegionServerMetrics:()Lorg/apache/hadoop/hbase/regionserver/MetricsRegionServer;
     200: putstatic     #40                 // Field metricsRegionServer:Lorg/apache/hadoop/hbase/regionserver/MetricsRegionServer;
     203: getstatic     #40                 // Field metricsRegionServer:Lorg/apache/hadoop/hbase/regionserver/MetricsRegionServer;
     206: invokevirtual #41                 // Method org/apache/hadoop/hbase/regionserver/MetricsRegionServer.getMetricsSource:()Lorg/apache/hadoop/hbase/regionserver/MetricsRegionServerSource;
     209: putstatic     #42                 // Field serverSource:Lorg/apache/hadoop/hbase/regionserver/MetricsRegionServerSource;
     212: return

  public static void after() throws java.lang.Exception;
    Code:
       0: getstatic     #10                 // Field TEST_UTIL:Lorg/apache/hadoop/hbase/HBaseTestingUtility;
       3: ifnull        12
       6: getstatic     #10                 // Field TEST_UTIL:Lorg/apache/hadoop/hbase/HBaseTestingUtility;
       9: invokevirtual #43                 // Method org/apache/hadoop/hbase/HBaseTestingUtility.shutdownMiniCluster:()V
      12: return

  public void beforeTestMethod() throws java.lang.Exception;
    Code:
       0: getstatic     #40                 // Field metricsRegionServer:Lorg/apache/hadoop/hbase/regionserver/MetricsRegionServer;
       3: invokevirtual #44                 // Method org/apache/hadoop/hbase/regionserver/MetricsRegionServer.getRegionServerWrapper:()Lorg/apache/hadoop/hbase/regionserver/MetricsRegionServerWrapper;
       6: invokeinterface #45,  1           // InterfaceMethod org/apache/hadoop/hbase/regionserver/MetricsRegionServerWrapper.forceRecompute:()V
      11: aload_0
      12: aload_0
      13: getfield      #4                  // Field testName:Lorg/junit/rules/TestName;
      16: invokevirtual #46                 // Method org/junit/rules/TestName.getMethodName:()Ljava/lang/String;
      19: invokestatic  #47                 // Method org/apache/hadoop/hbase/TableName.valueOf:(Ljava/lang/String;)Lorg/apache/hadoop/hbase/TableName;
      22: putfield      #48                 // Field tableName:Lorg/apache/hadoop/hbase/TableName;
      25: aload_0
      26: getstatic     #10                 // Field TEST_UTIL:Lorg/apache/hadoop/hbase/HBaseTestingUtility;
      29: aload_0
      30: getfield      #48                 // Field tableName:Lorg/apache/hadoop/hbase/TableName;
      33: getstatic     #49                 // Field cf:[B
      36: invokevirtual #50                 // Method org/apache/hadoop/hbase/HBaseTestingUtility.createTable:(Lorg/apache/hadoop/hbase/TableName;[B)Lorg/apache/hadoop/hbase/client/Table;
      39: putfield      #51                 // Field table:Lorg/apache/hadoop/hbase/client/Table;
      42: return

  public void afterTestMethod() throws java.lang.Exception;
    Code:
       0: getstatic     #29                 // Field admin:Lorg/apache/hadoop/hbase/client/Admin;
       3: aload_0
       4: getfield      #48                 // Field tableName:Lorg/apache/hadoop/hbase/TableName;
       7: invokeinterface #52,  2           // InterfaceMethod org/apache/hadoop/hbase/client/Admin.disableTable:(Lorg/apache/hadoop/hbase/TableName;)V
      12: getstatic     #29                 // Field admin:Lorg/apache/hadoop/hbase/client/Admin;
      15: aload_0
      16: getfield      #48                 // Field tableName:Lorg/apache/hadoop/hbase/TableName;
      19: invokeinterface #53,  2           // InterfaceMethod org/apache/hadoop/hbase/client/Admin.deleteTable:(Lorg/apache/hadoop/hbase/TableName;)V
      24: return

  public void assertCounter(java.lang.String, long);
    Code:
       0: getstatic     #7                  // Field metricsHelper:Lorg/apache/hadoop/hbase/test/MetricsAssertHelper;
       3: aload_1
       4: lload_2
       5: getstatic     #42                 // Field serverSource:Lorg/apache/hadoop/hbase/regionserver/MetricsRegionServerSource;
       8: invokeinterface #54,  5           // InterfaceMethod org/apache/hadoop/hbase/test/MetricsAssertHelper.assertCounter:(Ljava/lang/String;JLorg/apache/hadoop/hbase/metrics/BaseSource;)V
      13: return

  public void assertGauge(java.lang.String, long);
    Code:
       0: getstatic     #7                  // Field metricsHelper:Lorg/apache/hadoop/hbase/test/MetricsAssertHelper;
       3: aload_1
       4: lload_2
       5: getstatic     #42                 // Field serverSource:Lorg/apache/hadoop/hbase/regionserver/MetricsRegionServerSource;
       8: invokeinterface #55,  5           // InterfaceMethod org/apache/hadoop/hbase/test/MetricsAssertHelper.assertGauge:(Ljava/lang/String;JLorg/apache/hadoop/hbase/metrics/BaseSource;)V
      13: return

  public void assertRegionMetrics(java.lang.String, long) throws java.lang.Exception;
    Code:
       0: getstatic     #31                 // Field connection:Lorg/apache/hadoop/hbase/client/Connection;
       3: aload_0
       4: getfield      #48                 // Field tableName:Lorg/apache/hadoop/hbase/TableName;
       7: invokeinterface #56,  2           // InterfaceMethod org/apache/hadoop/hbase/client/Connection.getRegionLocator:(Lorg/apache/hadoop/hbase/TableName;)Lorg/apache/hadoop/hbase/client/RegionLocator;
      12: astore        4
      14: aconst_null
      15: astore        5
      17: aload         4
      19: invokeinterface #57,  1           // InterfaceMethod org/apache/hadoop/hbase/client/RegionLocator.getAllRegionLocations:()Ljava/util/List;
      24: invokeinterface #58,  1           // InterfaceMethod java/util/List.iterator:()Ljava/util/Iterator;
      29: astore        6
      31: aload         6
      33: invokeinterface #59,  1           // InterfaceMethod java/util/Iterator.hasNext:()Z
      38: ifeq          173
      41: aload         6
      43: invokeinterface #60,  1           // InterfaceMethod java/util/Iterator.next:()Ljava/lang/Object;
      48: checkcast     #61                 // class org/apache/hadoop/hbase/HRegionLocation
      51: astore        7
      53: aload         7
      55: invokevirtual #62                 // Method org/apache/hadoop/hbase/HRegionLocation.getRegionInfo:()Lorg/apache/hadoop/hbase/HRegionInfo;
      58: astore        8
      60: getstatic     #35                 // Field rs:Lorg/apache/hadoop/hbase/regionserver/HRegionServer;
      63: aload         8
      65: invokevirtual #63                 // Method org/apache/hadoop/hbase/HRegionInfo.getRegionName:()[B
      68: invokevirtual #64                 // Method org/apache/hadoop/hbase/regionserver/HRegionServer.getRegion:([B)Lorg/apache/hadoop/hbase/regionserver/HRegion;
      71: invokevirtual #65                 // Method org/apache/hadoop/hbase/regionserver/HRegion.getMetrics:()Lorg/apache/hadoop/hbase/regionserver/MetricsRegion;
      74: invokevirtual #66                 // Method org/apache/hadoop/hbase/regionserver/MetricsRegion.getSource:()Lorg/apache/hadoop/hbase/regionserver/MetricsRegionSource;
      77: invokeinterface #67,  1           // InterfaceMethod org/apache/hadoop/hbase/regionserver/MetricsRegionSource.getAggregateSource:()Lorg/apache/hadoop/hbase/regionserver/MetricsRegionAggregateSource;
      82: astore        9
      84: new           #68                 // class java/lang/StringBuilder
      87: dup
      88: invokespecial #69                 // Method java/lang/StringBuilder."<init>":()V
      91: ldc           #70                 // String namespace_
      93: invokevirtual #71                 // Method java/lang/StringBuilder.append:(Ljava/lang/String;)Ljava/lang/StringBuilder;
      96: getstatic     #72                 // Field org/apache/hadoop/hbase/NamespaceDescriptor.DEFAULT_NAMESPACE_NAME_STR:Ljava/lang/String;
      99: invokevirtual #71                 // Method java/lang/StringBuilder.append:(Ljava/lang/String;)Ljava/lang/StringBuilder;
     102: ldc           #73                 // String _table_
     104: invokevirtual #71                 // Method java/lang/StringBuilder.append:(Ljava/lang/String;)Ljava/lang/StringBuilder;
     107: aload_0
     108: getfield      #48                 // Field tableName:Lorg/apache/hadoop/hbase/TableName;
     111: invokevirtual #74                 // Method org/apache/hadoop/hbase/TableName.getNameAsString:()Ljava/lang/String;
     114: invokevirtual #71                 // Method java/lang/StringBuilder.append:(Ljava/lang/String;)Ljava/lang/StringBuilder;
     117: ldc           #75                 // String _region_
     119: invokevirtual #71                 // Method java/lang/StringBuilder.append:(Ljava/lang/String;)Ljava/lang/StringBuilder;
     122: aload         8
     124: invokevirtual #76                 // Method org/apache/hadoop/hbase/HRegionInfo.getEncodedName:()Ljava/lang/String;
     127: invokevirtual #71                 // Method java/lang/StringBuilder.append:(Ljava/lang/String;)Ljava/lang/StringBuilder;
     130: ldc           #77                 // String _metric_
     132: invokevirtual #71                 // Method java/lang/StringBuilder.append:(Ljava/lang/String;)Ljava/lang/StringBuilder;
     135: invokevirtual #78                 // Method java/lang/StringBuilder.toString:()Ljava/lang/String;
     138: astore        10
     140: getstatic     #7                  // Field metricsHelper:Lorg/apache/hadoop/hbase/test/MetricsAssertHelper;
     143: new           #68                 // class java/lang/StringBuilder
     146: dup
     147: invokespecial #69                 // Method java/lang/StringBuilder."<init>":()V
     150: aload         10
     152: invokevirtual #71                 // Method java/lang/StringBuilder.append:(Ljava/lang/String;)Ljava/lang/StringBuilder;
     155: aload_1
     156: invokevirtual #71                 // Method java/lang/StringBuilder.append:(Ljava/lang/String;)Ljava/lang/StringBuilder;
     159: invokevirtual #78                 // Method java/lang/StringBuilder.toString:()Ljava/lang/String;
     162: lload_2
     163: aload         9
     165: invokeinterface #54,  5           // InterfaceMethod org/apache/hadoop/hbase/test/MetricsAssertHelper.assertCounter:(Ljava/lang/String;JLorg/apache/hadoop/hbase/metrics/BaseSource;)V
     170: goto          31
     173: aload         4
     175: ifnull        268
     178: aload         5
     180: ifnull        205
     183: aload         4
     185: invokeinterface #79,  1           // InterfaceMethod org/apache/hadoop/hbase/client/RegionLocator.close:()V
     190: goto          268
     193: astore        6
     195: aload         5
     197: aload         6
     199: invokevirtual #81                 // Method java/lang/Throwable.addSuppressed:(Ljava/lang/Throwable;)V
     202: goto          268
     205: aload         4
     207: invokeinterface #79,  1           // InterfaceMethod org/apache/hadoop/hbase/client/RegionLocator.close:()V
     212: goto          268
     215: astore        6
     217: aload         6
     219: astore        5
     221: aload         6
     223: athrow
     224: astore        11
     226: aload         4
     228: ifnull        265
     231: aload         5
     233: ifnull        258
     236: aload         4
     238: invokeinterface #79,  1           // InterfaceMethod org/apache/hadoop/hbase/client/RegionLocator.close:()V
     243: goto          265
     246: astore        12
     248: aload         5
     250: aload         12
     252: invokevirtual #81                 // Method java/lang/Throwable.addSuppressed:(Ljava/lang/Throwable;)V
     255: goto          265
     258: aload         4
     260: invokeinterface #79,  1           // InterfaceMethod org/apache/hadoop/hbase/client/RegionLocator.close:()V
     265: aload         11
     267: athrow
     268: return
    Exception table:
       from    to  target type
         183   190   193   Class java/lang/Throwable
          17   173   215   Class java/lang/Throwable
          17   173   224   any
         236   243   246   Class java/lang/Throwable
         215   226   224   any

  public void doNPuts(int, boolean) throws java.lang.Exception;
    Code:
       0: iload_2
       1: ifeq          98
       4: new           #82                 // class java/util/ArrayList
       7: dup
       8: invokespecial #83                 // Method java/util/ArrayList."<init>":()V
      11: astore_3
      12: iconst_0
      13: istore        4
      15: iload         4
      17: iload_1
      18: if_icmpge     85
      21: new           #84                 // class org/apache/hadoop/hbase/client/Put
      24: dup
      25: new           #68                 // class java/lang/StringBuilder
      28: dup
      29: invokespecial #69                 // Method java/lang/StringBuilder."<init>":()V
      32: ldc           #85                 // String
      34: invokevirtual #71                 // Method java/lang/StringBuilder.append:(Ljava/lang/String;)Ljava/lang/StringBuilder;
      37: iload         4
      39: invokevirtual #86                 // Method java/lang/StringBuilder.append:(I)Ljava/lang/StringBuilder;
      42: ldc           #87                 // String row
      44: invokevirtual #71                 // Method java/lang/StringBuilder.append:(Ljava/lang/String;)Ljava/lang/StringBuilder;
      47: invokevirtual #78                 // Method java/lang/StringBuilder.toString:()Ljava/lang/String;
      50: invokestatic  #88                 // Method org/apache/hadoop/hbase/util/Bytes.toBytes:(Ljava/lang/String;)[B
      53: invokespecial #89                 // Method org/apache/hadoop/hbase/client/Put."<init>":([B)V
      56: getstatic     #49                 // Field cf:[B
      59: getstatic     #90                 // Field qualifier:[B
      62: getstatic     #91                 // Field val:[B
      65: invokevirtual #92                 // Method org/apache/hadoop/hbase/client/Put.addColumn:([B[B[B)Lorg/apache/hadoop/hbase/client/Put;
      68: astore        5
      70: aload_3
      71: aload         5
      73: invokeinterface #93,  2           // InterfaceMethod java/util/List.add:(Ljava/lang/Object;)Z
      78: pop
      79: iinc          4, 1
      82: goto          15
      85: aload_0
      86: getfield      #51                 // Field table:Lorg/apache/hadoop/hbase/client/Table;
      89: aload_3
      90: invokeinterface #94,  2           // InterfaceMethod org/apache/hadoop/hbase/client/Table.put:(Ljava/util/List;)V
      95: goto          146
      98: iconst_0
      99: istore_3
     100: iload_3
     101: iload_1
     102: if_icmpge     146
     105: new           #84                 // class org/apache/hadoop/hbase/client/Put
     108: dup
     109: getstatic     #95                 // Field row:[B
     112: invokespecial #89                 // Method org/apache/hadoop/hbase/client/Put."<init>":([B)V
     115: getstatic     #49                 // Field cf:[B
     118: getstatic     #90                 // Field qualifier:[B
     121: getstatic     #91                 // Field val:[B
     124: invokevirtual #92                 // Method org/apache/hadoop/hbase/client/Put.addColumn:([B[B[B)Lorg/apache/hadoop/hbase/client/Put;
     127: astore        4
     129: aload_0
     130: getfield      #51                 // Field table:Lorg/apache/hadoop/hbase/client/Table;
     133: aload         4
     135: invokeinterface #96,  2           // InterfaceMethod org/apache/hadoop/hbase/client/Table.put:(Lorg/apache/hadoop/hbase/client/Put;)V
     140: iinc          3, 1
     143: goto          100
     146: return

  public void doNGets(int, boolean) throws java.lang.Exception;
    Code:
       0: iload_2
       1: ifeq          58
       4: new           #82                 // class java/util/ArrayList
       7: dup
       8: invokespecial #83                 // Method java/util/ArrayList."<init>":()V
      11: astore_3
      12: iconst_0
      13: istore        4
      15: iload         4
      17: iload_1
      18: if_icmpge     44
      21: aload_3
      22: new           #97                 // class org/apache/hadoop/hbase/client/Get
      25: dup
      26: getstatic     #95                 // Field row:[B
      29: invokespecial #98                 // Method org/apache/hadoop/hbase/client/Get."<init>":([B)V
      32: invokeinterface #93,  2           // InterfaceMethod java/util/List.add:(Ljava/lang/Object;)Z
      37: pop
      38: iinc          4, 1
      41: goto          15
      44: aload_0
      45: getfield      #51                 // Field table:Lorg/apache/hadoop/hbase/client/Table;
      48: aload_3
      49: invokeinterface #99,  2           // InterfaceMethod org/apache/hadoop/hbase/client/Table.get:(Ljava/util/List;)[Lorg/apache/hadoop/hbase/client/Result;
      54: pop
      55: goto          91
      58: iconst_0
      59: istore_3
      60: iload_3
      61: iload_1
      62: if_icmpge     91
      65: aload_0
      66: getfield      #51                 // Field table:Lorg/apache/hadoop/hbase/client/Table;
      69: new           #97                 // class org/apache/hadoop/hbase/client/Get
      72: dup
      73: getstatic     #95                 // Field row:[B
      76: invokespecial #98                 // Method org/apache/hadoop/hbase/client/Get."<init>":([B)V
      79: invokeinterface #100,  2          // InterfaceMethod org/apache/hadoop/hbase/client/Table.get:(Lorg/apache/hadoop/hbase/client/Get;)Lorg/apache/hadoop/hbase/client/Result;
      84: pop
      85: iinc          3, 1
      88: goto          60
      91: return

  public void doScan(int, boolean) throws java.io.IOException;
    Code:
       0: new           #101                // class org/apache/hadoop/hbase/client/Scan
       3: dup
       4: invokespecial #102                // Method org/apache/hadoop/hbase/client/Scan."<init>":()V
       7: astore_3
       8: iload_2
       9: ifeq          21
      12: aload_3
      13: iload_1
      14: invokevirtual #103                // Method org/apache/hadoop/hbase/client/Scan.setCaching:(I)Lorg/apache/hadoop/hbase/client/Scan;
      17: pop
      18: goto          27
      21: aload_3
      22: iconst_1
      23: invokevirtual #103                // Method org/apache/hadoop/hbase/client/Scan.setCaching:(I)Lorg/apache/hadoop/hbase/client/Scan;
      26: pop
      27: aload_0
      28: getfield      #51                 // Field table:Lorg/apache/hadoop/hbase/client/Table;
      31: aload_3
      32: invokeinterface #104,  2          // InterfaceMethod org/apache/hadoop/hbase/client/Table.getScanner:(Lorg/apache/hadoop/hbase/client/Scan;)Lorg/apache/hadoop/hbase/client/ResultScanner;
      37: astore        4
      39: iconst_0
      40: istore        5
      42: iload         5
      44: iload_1
      45: if_icmpge     119
      48: aload         4
      50: invokeinterface #105,  1          // InterfaceMethod org/apache/hadoop/hbase/client/ResultScanner.next:()Lorg/apache/hadoop/hbase/client/Result;
      55: astore        6
      57: getstatic     #106                // Field LOG:Lorg/slf4j/Logger;
      60: new           #68                 // class java/lang/StringBuilder
      63: dup
      64: invokespecial #69                 // Method java/lang/StringBuilder."<init>":()V
      67: ldc           #107                // String Result row:
      69: invokevirtual #71                 // Method java/lang/StringBuilder.append:(Ljava/lang/String;)Ljava/lang/StringBuilder;
      72: aload         6
      74: invokevirtual #108                // Method org/apache/hadoop/hbase/client/Result.getRow:()[B
      77: invokestatic  #109                // Method org/apache/hadoop/hbase/util/Bytes.toString:([B)Ljava/lang/String;
      80: invokevirtual #71                 // Method java/lang/StringBuilder.append:(Ljava/lang/String;)Ljava/lang/StringBuilder;
      83: ldc           #110                // String , value:
      85: invokevirtual #71                 // Method java/lang/StringBuilder.append:(Ljava/lang/String;)Ljava/lang/StringBuilder;
      88: aload         6
      90: getstatic     #49                 // Field cf:[B
      93: getstatic     #90                 // Field qualifier:[B
      96: invokevirtual #111                // Method org/apache/hadoop/hbase/client/Result.getValue:([B[B)[B
      99: invokestatic  #109                // Method org/apache/hadoop/hbase/util/Bytes.toString:([B)Ljava/lang/String;
     102: invokevirtual #71                 // Method java/lang/StringBuilder.append:(Ljava/lang/String;)Ljava/lang/StringBuilder;
     105: invokevirtual #78                 // Method java/lang/StringBuilder.toString:()Ljava/lang/String;
     108: invokeinterface #112,  2          // InterfaceMethod org/slf4j/Logger.debug:(Ljava/lang/String;)V
     113: iinc          5, 1
     116: goto          42
     119: return

  public void testRegionCount() throws java.lang.Exception;
    Code:
       0: getstatic     #7                  // Field metricsHelper:Lorg/apache/hadoop/hbase/test/MetricsAssertHelper;
       3: ldc           #113                // String regionCount
       5: getstatic     #13                 // Field TABLES_ON_MASTER:Z
       8: ifeq          15
      11: lconst_1
      12: goto          18
      15: ldc2_w        #114                // long 2l
      18: getstatic     #42                 // Field serverSource:Lorg/apache/hadoop/hbase/regionserver/MetricsRegionServerSource;
      21: invokeinterface #55,  5           // InterfaceMethod org/apache/hadoop/hbase/test/MetricsAssertHelper.assertGauge:(Ljava/lang/String;JLorg/apache/hadoop/hbase/metrics/BaseSource;)V
      26: return

  public void testLocalFiles() throws java.lang.Exception;
    Code:
       0: aload_0
       1: ldc           #116                // String percentFilesLocal
       3: lconst_0
       4: invokevirtual #117                // Method assertGauge:(Ljava/lang/String;J)V
       7: aload_0
       8: ldc           #118                // String percentFilesLocalSecondaryRegions
      10: lconst_0
      11: invokevirtual #117                // Method assertGauge:(Ljava/lang/String;J)V
      14: return

  public void testRequestCount() throws java.lang.Exception;
    Code:
       0: aload_0
       1: iconst_1
       2: iconst_0
       3: invokevirtual #119                // Method doNPuts:(IZ)V
       6: getstatic     #40                 // Field metricsRegionServer:Lorg/apache/hadoop/hbase/regionserver/MetricsRegionServer;
       9: invokevirtual #44                 // Method org/apache/hadoop/hbase/regionserver/MetricsRegionServer.getRegionServerWrapper:()Lorg/apache/hadoop/hbase/regionserver/MetricsRegionServerWrapper;
      12: invokeinterface #45,  1           // InterfaceMethod org/apache/hadoop/hbase/regionserver/MetricsRegionServerWrapper.forceRecompute:()V
      17: getstatic     #7                  // Field metricsHelper:Lorg/apache/hadoop/hbase/test/MetricsAssertHelper;
      20: ldc           #120                // String totalRequestCount
      22: getstatic     #42                 // Field serverSource:Lorg/apache/hadoop/hbase/regionserver/MetricsRegionServerSource;
      25: invokeinterface #121,  3          // InterfaceMethod org/apache/hadoop/hbase/test/MetricsAssertHelper.getCounter:(Ljava/lang/String;Lorg/apache/hadoop/hbase/metrics/BaseSource;)J
      30: lstore_1
      31: getstatic     #7                  // Field metricsHelper:Lorg/apache/hadoop/hbase/test/MetricsAssertHelper;
      34: ldc           #122                // String totalRowActionRequestCount
      36: getstatic     #42                 // Field serverSource:Lorg/apache/hadoop/hbase/regionserver/MetricsRegionServerSource;
      39: invokeinterface #121,  3          // InterfaceMethod org/apache/hadoop/hbase/test/MetricsAssertHelper.getCounter:(Ljava/lang/String;Lorg/apache/hadoop/hbase/metrics/BaseSource;)J
      44: lstore_3
      45: getstatic     #7                  // Field metricsHelper:Lorg/apache/hadoop/hbase/test/MetricsAssertHelper;
      48: ldc           #123                // String readRequestCount
      50: getstatic     #42                 // Field serverSource:Lorg/apache/hadoop/hbase/regionserver/MetricsRegionServerSource;
      53: invokeinterface #121,  3          // InterfaceMethod org/apache/hadoop/hbase/test/MetricsAssertHelper.getCounter:(Ljava/lang/String;Lorg/apache/hadoop/hbase/metrics/BaseSource;)J
      58: lstore        5
      60: getstatic     #7                  // Field metricsHelper:Lorg/apache/hadoop/hbase/test/MetricsAssertHelper;
      63: ldc           #124                // String writeRequestCount
      65: getstatic     #42                 // Field serverSource:Lorg/apache/hadoop/hbase/regionserver/MetricsRegionServerSource;
      68: invokeinterface #121,  3          // InterfaceMethod org/apache/hadoop/hbase/test/MetricsAssertHelper.getCounter:(Ljava/lang/String;Lorg/apache/hadoop/hbase/metrics/BaseSource;)J
      73: lstore        7
      75: aload_0
      76: bipush        30
      78: iconst_0
      79: invokevirtual #119                // Method doNPuts:(IZ)V
      82: getstatic     #40                 // Field metricsRegionServer:Lorg/apache/hadoop/hbase/regionserver/MetricsRegionServer;
      85: invokevirtual #44                 // Method org/apache/hadoop/hbase/regionserver/MetricsRegionServer.getRegionServerWrapper:()Lorg/apache/hadoop/hbase/regionserver/MetricsRegionServerWrapper;
      88: invokeinterface #45,  1           // InterfaceMethod org/apache/hadoop/hbase/regionserver/MetricsRegionServerWrapper.forceRecompute:()V
      93: aload_0
      94: ldc           #120                // String totalRequestCount
      96: lload_1
      97: ldc2_w        #125                // long 30l
     100: ladd
     101: invokevirtual #127                // Method assertCounter:(Ljava/lang/String;J)V
     104: aload_0
     105: ldc           #122                // String totalRowActionRequestCount
     107: lload_3
     108: ldc2_w        #125                // long 30l
     111: ladd
     112: invokevirtual #127                // Method assertCounter:(Ljava/lang/String;J)V
     115: aload_0
     116: ldc           #123                // String readRequestCount
     118: lload         5
     120: invokevirtual #127                // Method assertCounter:(Ljava/lang/String;J)V
     123: aload_0
     124: ldc           #124                // String writeRequestCount
     126: lload         7
     128: ldc2_w        #125                // long 30l
     131: ladd
     132: invokevirtual #127                // Method assertCounter:(Ljava/lang/String;J)V
     135: aload_0
     136: bipush        10
     138: iconst_0
     139: invokevirtual #128                // Method doNGets:(IZ)V
     142: getstatic     #40                 // Field metricsRegionServer:Lorg/apache/hadoop/hbase/regionserver/MetricsRegionServer;
     145: invokevirtual #44                 // Method org/apache/hadoop/hbase/regionserver/MetricsRegionServer.getRegionServerWrapper:()Lorg/apache/hadoop/hbase/regionserver/MetricsRegionServerWrapper;
     148: invokeinterface #45,  1           // InterfaceMethod org/apache/hadoop/hbase/regionserver/MetricsRegionServerWrapper.forceRecompute:()V
     153: aload_0
     154: ldc           #120                // String totalRequestCount
     156: lload_1
     157: ldc2_w        #129                // long 40l
     160: ladd
     161: invokevirtual #127                // Method assertCounter:(Ljava/lang/String;J)V
     164: aload_0
     165: ldc           #122                // String totalRowActionRequestCount
     167: lload_3
     168: ldc2_w        #129                // long 40l
     171: ladd
     172: invokevirtual #127                // Method assertCounter:(Ljava/lang/String;J)V
     175: aload_0
     176: ldc           #123                // String readRequestCount
     178: lload         5
     180: ldc2_w        #131                // long 10l
     183: ladd
     184: invokevirtual #127                // Method assertCounter:(Ljava/lang/String;J)V
     187: aload_0
     188: ldc           #124                // String writeRequestCount
     190: lload         7
     192: ldc2_w        #125                // long 30l
     195: ladd
     196: invokevirtual #127                // Method assertCounter:(Ljava/lang/String;J)V
     199: aload_0
     200: ldc           #133                // String getCount
     202: ldc2_w        #131                // long 10l
     205: invokevirtual #134                // Method assertRegionMetrics:(Ljava/lang/String;J)V
     208: aload_0
     209: ldc           #135                // String putCount
     211: ldc2_w        #136                // long 31l
     214: invokevirtual #134                // Method assertRegionMetrics:(Ljava/lang/String;J)V
     217: aload_0
     218: bipush        10
     220: iconst_1
     221: invokevirtual #128                // Method doNGets:(IZ)V
     224: getstatic     #40                 // Field metricsRegionServer:Lorg/apache/hadoop/hbase/regionserver/MetricsRegionServer;
     227: invokevirtual #44                 // Method org/apache/hadoop/hbase/regionserver/MetricsRegionServer.getRegionServerWrapper:()Lorg/apache/hadoop/hbase/regionserver/MetricsRegionServerWrapper;
     230: invokeinterface #45,  1           // InterfaceMethod org/apache/hadoop/hbase/regionserver/MetricsRegionServerWrapper.forceRecompute:()V
     235: getstatic     #13                 // Field TABLES_ON_MASTER:Z
     238: ifeq          275
     241: aload_0
     242: ldc           #120                // String totalRequestCount
     244: lload_1
     245: ldc2_w        #138                // long 41l
     248: ladd
     249: invokevirtual #127                // Method assertCounter:(Ljava/lang/String;J)V
     252: aload_0
     253: ldc           #122                // String totalRowActionRequestCount
     255: lload_3
     256: ldc2_w        #140                // long 50l
     259: ladd
     260: invokevirtual #127                // Method assertCounter:(Ljava/lang/String;J)V
     263: aload_0
     264: ldc           #123                // String readRequestCount
     266: lload         5
     268: ldc2_w        #142                // long 20l
     271: ladd
     272: invokevirtual #127                // Method assertCounter:(Ljava/lang/String;J)V
     275: aload_0
     276: ldc           #124                // String writeRequestCount
     278: lload         7
     280: ldc2_w        #125                // long 30l
     283: ladd
     284: invokevirtual #127                // Method assertCounter:(Ljava/lang/String;J)V
     287: aload_0
     288: bipush        30
     290: iconst_1
     291: invokevirtual #119                // Method doNPuts:(IZ)V
     294: getstatic     #40                 // Field metricsRegionServer:Lorg/apache/hadoop/hbase/regionserver/MetricsRegionServer;
     297: invokevirtual #44                 // Method org/apache/hadoop/hbase/regionserver/MetricsRegionServer.getRegionServerWrapper:()Lorg/apache/hadoop/hbase/regionserver/MetricsRegionServerWrapper;
     300: invokeinterface #45,  1           // InterfaceMethod org/apache/hadoop/hbase/regionserver/MetricsRegionServerWrapper.forceRecompute:()V
     305: getstatic     #13                 // Field TABLES_ON_MASTER:Z
     308: ifeq          345
     311: aload_0
     312: ldc           #120                // String totalRequestCount
     314: lload_1
     315: ldc2_w        #144                // long 42l
     318: ladd
     319: invokevirtual #127                // Method assertCounter:(Ljava/lang/String;J)V
     322: aload_0
     323: ldc           #122                // String totalRowActionRequestCount
     325: lload_3
     326: ldc2_w        #146                // long 80l
     329: ladd
     330: invokevirtual #127                // Method assertCounter:(Ljava/lang/String;J)V
     333: aload_0
     334: ldc           #123                // String readRequestCount
     336: lload         5
     338: ldc2_w        #142                // long 20l
     341: ladd
     342: invokevirtual #127                // Method assertCounter:(Ljava/lang/String;J)V
     345: aload_0
     346: ldc           #124                // String writeRequestCount
     348: lload         7
     350: ldc2_w        #148                // long 60l
     353: ladd
     354: invokevirtual #127                // Method assertCounter:(Ljava/lang/String;J)V
     357: aload_0
     358: bipush        10
     360: iconst_0
     361: invokevirtual #150                // Method doScan:(IZ)V
     364: getstatic     #40                 // Field metricsRegionServer:Lorg/apache/hadoop/hbase/regionserver/MetricsRegionServer;
     367: invokevirtual #44                 // Method org/apache/hadoop/hbase/regionserver/MetricsRegionServer.getRegionServerWrapper:()Lorg/apache/hadoop/hbase/regionserver/MetricsRegionServerWrapper;
     370: invokeinterface #45,  1           // InterfaceMethod org/apache/hadoop/hbase/regionserver/MetricsRegionServerWrapper.forceRecompute:()V
     375: getstatic     #13                 // Field TABLES_ON_MASTER:Z
     378: ifeq          415
     381: aload_0
     382: ldc           #120                // String totalRequestCount
     384: lload_1
     385: ldc2_w        #151                // long 52l
     388: ladd
     389: invokevirtual #127                // Method assertCounter:(Ljava/lang/String;J)V
     392: aload_0
     393: ldc           #122                // String totalRowActionRequestCount
     395: lload_3
     396: ldc2_w        #153                // long 90l
     399: ladd
     400: invokevirtual #127                // Method assertCounter:(Ljava/lang/String;J)V
     403: aload_0
     404: ldc           #123                // String readRequestCount
     406: lload         5
     408: ldc2_w        #125                // long 30l
     411: ladd
     412: invokevirtual #127                // Method assertCounter:(Ljava/lang/String;J)V
     415: aload_0
     416: ldc           #124                // String writeRequestCount
     418: lload         7
     420: ldc2_w        #148                // long 60l
     423: ladd
     424: invokevirtual #127                // Method assertCounter:(Ljava/lang/String;J)V
     427: getstatic     #155                // Field numScanNext:I
     430: bipush        10
     432: iadd
     433: putstatic     #155                // Field numScanNext:I
     436: aload_0
     437: bipush        10
     439: iconst_1
     440: invokevirtual #150                // Method doScan:(IZ)V
     443: getstatic     #40                 // Field metricsRegionServer:Lorg/apache/hadoop/hbase/regionserver/MetricsRegionServer;
     446: invokevirtual #44                 // Method org/apache/hadoop/hbase/regionserver/MetricsRegionServer.getRegionServerWrapper:()Lorg/apache/hadoop/hbase/regionserver/MetricsRegionServerWrapper;
     449: invokeinterface #45,  1           // InterfaceMethod org/apache/hadoop/hbase/regionserver/MetricsRegionServerWrapper.forceRecompute:()V
     454: getstatic     #13                 // Field TABLES_ON_MASTER:Z
     457: ifeq          494
     460: aload_0
     461: ldc           #120                // String totalRequestCount
     463: lload_1
     464: ldc2_w        #156                // long 53l
     467: ladd
     468: invokevirtual #127                // Method assertCounter:(Ljava/lang/String;J)V
     471: aload_0
     472: ldc           #122                // String totalRowActionRequestCount
     474: lload_3
     475: ldc2_w        #37                 // long 100l
     478: ladd
     479: invokevirtual #127                // Method assertCounter:(Ljava/lang/String;J)V
     482: aload_0
     483: ldc           #123                // String readRequestCount
     485: lload         5
     487: ldc2_w        #129                // long 40l
     490: ladd
     491: invokevirtual #127                // Method assertCounter:(Ljava/lang/String;J)V
     494: aload_0
     495: ldc           #124                // String writeRequestCount
     497: lload         7
     499: ldc2_w        #148                // long 60l
     502: ladd
     503: invokevirtual #127                // Method assertCounter:(Ljava/lang/String;J)V
     506: getstatic     #155                // Field numScanNext:I
     509: iconst_1
     510: iadd
     511: putstatic     #155                // Field numScanNext:I
     514: return

  public void testGet() throws java.lang.Exception;
    Code:
       0: aload_0
       1: iconst_1
       2: iconst_0
       3: invokevirtual #119                // Method doNPuts:(IZ)V
       6: aload_0
       7: bipush        10
       9: iconst_0
      10: invokevirtual #128                // Method doNGets:(IZ)V
      13: aload_0
      14: ldc           #133                // String getCount
      16: ldc2_w        #131                // long 10l
      19: invokevirtual #134                // Method assertRegionMetrics:(Ljava/lang/String;J)V
      22: getstatic     #7                  // Field metricsHelper:Lorg/apache/hadoop/hbase/test/MetricsAssertHelper;
      25: ldc           #158                // String Get_num_ops
      27: ldc2_w        #131                // long 10l
      30: getstatic     #42                 // Field serverSource:Lorg/apache/hadoop/hbase/regionserver/MetricsRegionServerSource;
      33: invokeinterface #159,  5          // InterfaceMethod org/apache/hadoop/hbase/test/MetricsAssertHelper.assertCounterGt:(Ljava/lang/String;JLorg/apache/hadoop/hbase/metrics/BaseSource;)V
      38: return

  public void testMutationsWithoutWal() throws java.lang.Exception;
    Code:
       0: new           #84                 // class org/apache/hadoop/hbase/client/Put
       3: dup
       4: getstatic     #95                 // Field row:[B
       7: invokespecial #89                 // Method org/apache/hadoop/hbase/client/Put."<init>":([B)V
      10: getstatic     #49                 // Field cf:[B
      13: getstatic     #90                 // Field qualifier:[B
      16: getstatic     #91                 // Field val:[B
      19: invokevirtual #92                 // Method org/apache/hadoop/hbase/client/Put.addColumn:([B[B[B)Lorg/apache/hadoop/hbase/client/Put;
      22: getstatic     #160                // Field org/apache/hadoop/hbase/client/Durability.SKIP_WAL:Lorg/apache/hadoop/hbase/client/Durability;
      25: invokevirtual #161                // Method org/apache/hadoop/hbase/client/Put.setDurability:(Lorg/apache/hadoop/hbase/client/Durability;)Lorg/apache/hadoop/hbase/client/Put;
      28: astore_1
      29: aload_0
      30: getfield      #51                 // Field table:Lorg/apache/hadoop/hbase/client/Table;
      33: aload_1
      34: invokeinterface #96,  2           // InterfaceMethod org/apache/hadoop/hbase/client/Table.put:(Lorg/apache/hadoop/hbase/client/Put;)V
      39: getstatic     #40                 // Field metricsRegionServer:Lorg/apache/hadoop/hbase/regionserver/MetricsRegionServer;
      42: invokevirtual #44                 // Method org/apache/hadoop/hbase/regionserver/MetricsRegionServer.getRegionServerWrapper:()Lorg/apache/hadoop/hbase/regionserver/MetricsRegionServerWrapper;
      45: invokeinterface #45,  1           // InterfaceMethod org/apache/hadoop/hbase/regionserver/MetricsRegionServerWrapper.forceRecompute:()V
      50: aload_0
      51: ldc           #162                // String mutationsWithoutWALCount
      53: lconst_1
      54: invokevirtual #117                // Method assertGauge:(Ljava/lang/String;J)V
      57: getstatic     #95                 // Field row:[B
      60: arraylength
      61: getstatic     #49                 // Field cf:[B
      64: arraylength
      65: iadd
      66: getstatic     #90                 // Field qualifier:[B
      69: arraylength
      70: iadd
      71: getstatic     #91                 // Field val:[B
      74: arraylength
      75: iadd
      76: i2l
      77: lstore_2
      78: getstatic     #7                  // Field metricsHelper:Lorg/apache/hadoop/hbase/test/MetricsAssertHelper;
      81: ldc           #163                // String mutationsWithoutWALSize
      83: lload_2
      84: getstatic     #42                 // Field serverSource:Lorg/apache/hadoop/hbase/regionserver/MetricsRegionServerSource;
      87: invokeinterface #164,  5          // InterfaceMethod org/apache/hadoop/hbase/test/MetricsAssertHelper.assertGaugeGt:(Ljava/lang/String;JLorg/apache/hadoop/hbase/metrics/BaseSource;)V
      92: return

  public void testStoreCount() throws java.lang.Exception;
    Code:
       0: aload_0
       1: iconst_1
       2: iconst_0
       3: invokevirtual #119                // Method doNPuts:(IZ)V
       6: getstatic     #10                 // Field TEST_UTIL:Lorg/apache/hadoop/hbase/HBaseTestingUtility;
       9: invokevirtual #28                 // Method org/apache/hadoop/hbase/HBaseTestingUtility.getAdmin:()Lorg/apache/hadoop/hbase/client/Admin;
      12: aload_0
      13: getfield      #48                 // Field tableName:Lorg/apache/hadoop/hbase/TableName;
      16: invokeinterface #165,  2          // InterfaceMethod org/apache/hadoop/hbase/client/Admin.flush:(Lorg/apache/hadoop/hbase/TableName;)V
      21: getstatic     #40                 // Field metricsRegionServer:Lorg/apache/hadoop/hbase/regionserver/MetricsRegionServer;
      24: invokevirtual #44                 // Method org/apache/hadoop/hbase/regionserver/MetricsRegionServer.getRegionServerWrapper:()Lorg/apache/hadoop/hbase/regionserver/MetricsRegionServerWrapper;
      27: invokeinterface #45,  1           // InterfaceMethod org/apache/hadoop/hbase/regionserver/MetricsRegionServerWrapper.forceRecompute:()V
      32: aload_0
      33: ldc           #166                // String storeCount
      35: getstatic     #13                 // Field TABLES_ON_MASTER:Z
      38: ifeq          45
      41: lconst_1
      42: goto          48
      45: ldc2_w        #167                // long 5l
      48: invokevirtual #117                // Method assertGauge:(Ljava/lang/String;J)V
      51: aload_0
      52: ldc           #169                // String storeFileCount
      54: lconst_1
      55: invokevirtual #117                // Method assertGauge:(Ljava/lang/String;J)V
      58: return

  public void testStoreFileAge() throws java.lang.Exception;
    Code:
       0: aload_0
       1: iconst_1
       2: iconst_0
       3: invokevirtual #119                // Method doNPuts:(IZ)V
       6: getstatic     #10                 // Field TEST_UTIL:Lorg/apache/hadoop/hbase/HBaseTestingUtility;
       9: invokevirtual #28                 // Method org/apache/hadoop/hbase/HBaseTestingUtility.getAdmin:()Lorg/apache/hadoop/hbase/client/Admin;
      12: aload_0
      13: getfield      #48                 // Field tableName:Lorg/apache/hadoop/hbase/TableName;
      16: invokeinterface #165,  2          // InterfaceMethod org/apache/hadoop/hbase/client/Admin.flush:(Lorg/apache/hadoop/hbase/TableName;)V
      21: getstatic     #40                 // Field metricsRegionServer:Lorg/apache/hadoop/hbase/regionserver/MetricsRegionServer;
      24: invokevirtual #44                 // Method org/apache/hadoop/hbase/regionserver/MetricsRegionServer.getRegionServerWrapper:()Lorg/apache/hadoop/hbase/regionserver/MetricsRegionServerWrapper;
      27: invokeinterface #45,  1           // InterfaceMethod org/apache/hadoop/hbase/regionserver/MetricsRegionServerWrapper.forceRecompute:()V
      32: getstatic     #7                  // Field metricsHelper:Lorg/apache/hadoop/hbase/test/MetricsAssertHelper;
      35: ldc           #170                // String maxStoreFileAge
      37: getstatic     #42                 // Field serverSource:Lorg/apache/hadoop/hbase/regionserver/MetricsRegionServerSource;
      40: invokeinterface #171,  3          // InterfaceMethod org/apache/hadoop/hbase/test/MetricsAssertHelper.getGaugeLong:(Ljava/lang/String;Lorg/apache/hadoop/hbase/metrics/BaseSource;)J
      45: lconst_0
      46: lcmp
      47: ifle          54
      50: iconst_1
      51: goto          55
      54: iconst_0
      55: invokestatic  #172                // Method org/junit/Assert.assertTrue:(Z)V
      58: getstatic     #7                  // Field metricsHelper:Lorg/apache/hadoop/hbase/test/MetricsAssertHelper;
      61: ldc           #173                // String minStoreFileAge
      63: getstatic     #42                 // Field serverSource:Lorg/apache/hadoop/hbase/regionserver/MetricsRegionServerSource;
      66: invokeinterface #171,  3          // InterfaceMethod org/apache/hadoop/hbase/test/MetricsAssertHelper.getGaugeLong:(Ljava/lang/String;Lorg/apache/hadoop/hbase/metrics/BaseSource;)J
      71: lconst_0
      72: lcmp
      73: ifle          80
      76: iconst_1
      77: goto          81
      80: iconst_0
      81: invokestatic  #172                // Method org/junit/Assert.assertTrue:(Z)V
      84: getstatic     #7                  // Field metricsHelper:Lorg/apache/hadoop/hbase/test/MetricsAssertHelper;
      87: ldc           #174                // String avgStoreFileAge
      89: getstatic     #42                 // Field serverSource:Lorg/apache/hadoop/hbase/regionserver/MetricsRegionServerSource;
      92: invokeinterface #171,  3          // InterfaceMethod org/apache/hadoop/hbase/test/MetricsAssertHelper.getGaugeLong:(Ljava/lang/String;Lorg/apache/hadoop/hbase/metrics/BaseSource;)J
      97: lconst_0
      98: lcmp
      99: ifle          106
     102: iconst_1
     103: goto          107
     106: iconst_0
     107: invokestatic  #172                // Method org/junit/Assert.assertTrue:(Z)V
     110: return

  public void testCheckAndPutCount() throws java.lang.Exception;
    Code:
       0: ldc           #175                // String Value
       2: invokestatic  #88                 // Method org/apache/hadoop/hbase/util/Bytes.toBytes:(Ljava/lang/String;)[B
       5: astore_1
       6: ldc           #176                // String ValueTwo
       8: invokestatic  #88                 // Method org/apache/hadoop/hbase/util/Bytes.toBytes:(Ljava/lang/String;)[B
      11: astore_2
      12: ldc           #177                // String ValueThree
      14: invokestatic  #88                 // Method org/apache/hadoop/hbase/util/Bytes.toBytes:(Ljava/lang/String;)[B
      17: astore_3
      18: new           #84                 // class org/apache/hadoop/hbase/client/Put
      21: dup
      22: getstatic     #95                 // Field row:[B
      25: invokespecial #89                 // Method org/apache/hadoop/hbase/client/Put."<init>":([B)V
      28: astore        4
      30: aload         4
      32: getstatic     #49                 // Field cf:[B
      35: getstatic     #90                 // Field qualifier:[B
      38: aload_1
      39: invokevirtual #92                 // Method org/apache/hadoop/hbase/client/Put.addColumn:([B[B[B)Lorg/apache/hadoop/hbase/client/Put;
      42: pop
      43: aload_0
      44: getfield      #51                 // Field table:Lorg/apache/hadoop/hbase/client/Table;
      47: aload         4
      49: invokeinterface #96,  2           // InterfaceMethod org/apache/hadoop/hbase/client/Table.put:(Lorg/apache/hadoop/hbase/client/Put;)V
      54: new           #84                 // class org/apache/hadoop/hbase/client/Put
      57: dup
      58: getstatic     #95                 // Field row:[B
      61: invokespecial #89                 // Method org/apache/hadoop/hbase/client/Put."<init>":([B)V
      64: astore        5
      66: aload         5
      68: getstatic     #49                 // Field cf:[B
      71: getstatic     #90                 // Field qualifier:[B
      74: aload_2
      75: invokevirtual #92                 // Method org/apache/hadoop/hbase/client/Put.addColumn:([B[B[B)Lorg/apache/hadoop/hbase/client/Put;
      78: pop
      79: aload_0
      80: getfield      #51                 // Field table:Lorg/apache/hadoop/hbase/client/Table;
      83: getstatic     #95                 // Field row:[B
      86: getstatic     #49                 // Field cf:[B
      89: invokeinterface #178,  3          // InterfaceMethod org/apache/hadoop/hbase/client/Table.checkAndMutate:([B[B)Lorg/apache/hadoop/hbase/client/Table$CheckAndMutateBuilder;
      94: getstatic     #90                 // Field qualifier:[B
      97: invokeinterface #179,  2          // InterfaceMethod org/apache/hadoop/hbase/client/Table$CheckAndMutateBuilder.qualifier:([B)Lorg/apache/hadoop/hbase/client/Table$CheckAndMutateBuilder;
     102: aload_1
     103: invokeinterface #180,  2          // InterfaceMethod org/apache/hadoop/hbase/client/Table$CheckAndMutateBuilder.ifEquals:([B)Lorg/apache/hadoop/hbase/client/Table$CheckAndMutateBuilder;
     108: aload         5
     110: invokeinterface #181,  2          // InterfaceMethod org/apache/hadoop/hbase/client/Table$CheckAndMutateBuilder.thenPut:(Lorg/apache/hadoop/hbase/client/Put;)Z
     115: pop
     116: new           #84                 // class org/apache/hadoop/hbase/client/Put
     119: dup
     120: getstatic     #95                 // Field row:[B
     123: invokespecial #89                 // Method org/apache/hadoop/hbase/client/Put."<init>":([B)V
     126: astore        6
     128: aload         6
     130: getstatic     #49                 // Field cf:[B
     133: getstatic     #90                 // Field qualifier:[B
     136: aload_3
     137: invokevirtual #92                 // Method org/apache/hadoop/hbase/client/Put.addColumn:([B[B[B)Lorg/apache/hadoop/hbase/client/Put;
     140: pop
     141: aload_0
     142: getfield      #51                 // Field table:Lorg/apache/hadoop/hbase/client/Table;
     145: getstatic     #95                 // Field row:[B
     148: getstatic     #49                 // Field cf:[B
     151: invokeinterface #178,  3          // InterfaceMethod org/apache/hadoop/hbase/client/Table.checkAndMutate:([B[B)Lorg/apache/hadoop/hbase/client/Table$CheckAndMutateBuilder;
     156: getstatic     #90                 // Field qualifier:[B
     159: invokeinterface #179,  2          // InterfaceMethod org/apache/hadoop/hbase/client/Table$CheckAndMutateBuilder.qualifier:([B)Lorg/apache/hadoop/hbase/client/Table$CheckAndMutateBuilder;
     164: aload_1
     165: invokeinterface #180,  2          // InterfaceMethod org/apache/hadoop/hbase/client/Table$CheckAndMutateBuilder.ifEquals:([B)Lorg/apache/hadoop/hbase/client/Table$CheckAndMutateBuilder;
     170: aload         6
     172: invokeinterface #181,  2          // InterfaceMethod org/apache/hadoop/hbase/client/Table$CheckAndMutateBuilder.thenPut:(Lorg/apache/hadoop/hbase/client/Put;)Z
     177: pop
     178: getstatic     #40                 // Field metricsRegionServer:Lorg/apache/hadoop/hbase/regionserver/MetricsRegionServer;
     181: invokevirtual #44                 // Method org/apache/hadoop/hbase/regionserver/MetricsRegionServer.getRegionServerWrapper:()Lorg/apache/hadoop/hbase/regionserver/MetricsRegionServerWrapper;
     184: invokeinterface #45,  1           // InterfaceMethod org/apache/hadoop/hbase/regionserver/MetricsRegionServerWrapper.forceRecompute:()V
     189: aload_0
     190: ldc           #182                // String checkMutateFailedCount
     192: lconst_1
     193: invokevirtual #127                // Method assertCounter:(Ljava/lang/String;J)V
     196: aload_0
     197: ldc           #183                // String checkMutatePassedCount
     199: lconst_1
     200: invokevirtual #127                // Method assertCounter:(Ljava/lang/String;J)V
     203: return

  public void testIncrement() throws java.lang.Exception;
    Code:
       0: new           #84                 // class org/apache/hadoop/hbase/client/Put
       3: dup
       4: getstatic     #95                 // Field row:[B
       7: invokespecial #89                 // Method org/apache/hadoop/hbase/client/Put."<init>":([B)V
      10: getstatic     #49                 // Field cf:[B
      13: getstatic     #90                 // Field qualifier:[B
      16: lconst_0
      17: invokestatic  #184                // Method org/apache/hadoop/hbase/util/Bytes.toBytes:(J)[B
      20: invokevirtual #92                 // Method org/apache/hadoop/hbase/client/Put.addColumn:([B[B[B)Lorg/apache/hadoop/hbase/client/Put;
      23: astore_1
      24: aload_0
      25: getfield      #51                 // Field table:Lorg/apache/hadoop/hbase/client/Table;
      28: aload_1
      29: invokeinterface #96,  2           // InterfaceMethod org/apache/hadoop/hbase/client/Table.put:(Lorg/apache/hadoop/hbase/client/Put;)V
      34: iconst_0
      35: istore_2
      36: iload_2
      37: bipush        13
      39: if_icmpge     84
      42: new           #185                // class org/apache/hadoop/hbase/client/Increment
      45: dup
      46: getstatic     #95                 // Field row:[B
      49: invokespecial #186                // Method org/apache/hadoop/hbase/client/Increment."<init>":([B)V
      52: astore_3
      53: aload_3
      54: getstatic     #49                 // Field cf:[B
      57: getstatic     #90                 // Field qualifier:[B
      60: ldc2_w        #37                 // long 100l
      63: invokevirtual #187                // Method org/apache/hadoop/hbase/client/Increment.addColumn:([B[BJ)Lorg/apache/hadoop/hbase/client/Increment;
      66: pop
      67: aload_0
      68: getfield      #51                 // Field table:Lorg/apache/hadoop/hbase/client/Table;
      71: aload_3
      72: invokeinterface #188,  2          // InterfaceMethod org/apache/hadoop/hbase/client/Table.increment:(Lorg/apache/hadoop/hbase/client/Increment;)Lorg/apache/hadoop/hbase/client/Result;
      77: pop
      78: iinc          2, 1
      81: goto          36
      84: getstatic     #40                 // Field metricsRegionServer:Lorg/apache/hadoop/hbase/regionserver/MetricsRegionServer;
      87: invokevirtual #44                 // Method org/apache/hadoop/hbase/regionserver/MetricsRegionServer.getRegionServerWrapper:()Lorg/apache/hadoop/hbase/regionserver/MetricsRegionServerWrapper;
      90: invokeinterface #45,  1           // InterfaceMethod org/apache/hadoop/hbase/regionserver/MetricsRegionServerWrapper.forceRecompute:()V
      95: aload_0
      96: ldc           #189                // String incrementNumOps
      98: ldc2_w        #190                // long 13l
     101: invokevirtual #127                // Method assertCounter:(Ljava/lang/String;J)V
     104: return

  public void testAppend() throws java.lang.Exception;
    Code:
       0: aload_0
       1: iconst_1
       2: iconst_0
       3: invokevirtual #119                // Method doNPuts:(IZ)V
       6: iconst_0
       7: istore_1
       8: iload_1
       9: bipush        73
      11: if_icmpge     58
      14: new           #192                // class org/apache/hadoop/hbase/client/Append
      17: dup
      18: getstatic     #95                 // Field row:[B
      21: invokespecial #193                // Method org/apache/hadoop/hbase/client/Append."<init>":([B)V
      24: astore_2
      25: aload_2
      26: getstatic     #49                 // Field cf:[B
      29: getstatic     #90                 // Field qualifier:[B
      32: ldc           #194                // String ,Test
      34: invokestatic  #88                 // Method org/apache/hadoop/hbase/util/Bytes.toBytes:(Ljava/lang/String;)[B
      37: invokevirtual #195                // Method org/apache/hadoop/hbase/client/Append.addColumn:([B[B[B)Lorg/apache/hadoop/hbase/client/Append;
      40: pop
      41: aload_0
      42: getfield      #51                 // Field table:Lorg/apache/hadoop/hbase/client/Table;
      45: aload_2
      46: invokeinterface #196,  2          // InterfaceMethod org/apache/hadoop/hbase/client/Table.append:(Lorg/apache/hadoop/hbase/client/Append;)Lorg/apache/hadoop/hbase/client/Result;
      51: pop
      52: iinc          1, 1
      55: goto          8
      58: getstatic     #40                 // Field metricsRegionServer:Lorg/apache/hadoop/hbase/regionserver/MetricsRegionServer;
      61: invokevirtual #44                 // Method org/apache/hadoop/hbase/regionserver/MetricsRegionServer.getRegionServerWrapper:()Lorg/apache/hadoop/hbase/regionserver/MetricsRegionServerWrapper;
      64: invokeinterface #45,  1           // InterfaceMethod org/apache/hadoop/hbase/regionserver/MetricsRegionServerWrapper.forceRecompute:()V
      69: aload_0
      70: ldc           #197                // String appendNumOps
      72: ldc2_w        #198                // long 73l
      75: invokevirtual #127                // Method assertCounter:(Ljava/lang/String;J)V
      78: return

  public void testScanSize() throws java.lang.Exception;
    Code:
       0: aload_0
       1: bipush        100
       3: iconst_1
       4: invokevirtual #119                // Method doNPuts:(IZ)V
       7: new           #101                // class org/apache/hadoop/hbase/client/Scan
      10: dup
      11: invokespecial #102                // Method org/apache/hadoop/hbase/client/Scan."<init>":()V
      14: astore_1
      15: aload_1
      16: iconst_1
      17: invokevirtual #200                // Method org/apache/hadoop/hbase/client/Scan.setBatch:(I)Lorg/apache/hadoop/hbase/client/Scan;
      20: pop
      21: aload_1
      22: iconst_1
      23: invokevirtual #103                // Method org/apache/hadoop/hbase/client/Scan.setCaching:(I)Lorg/apache/hadoop/hbase/client/Scan;
      26: pop
      27: aload_0
      28: getfield      #51                 // Field table:Lorg/apache/hadoop/hbase/client/Table;
      31: aload_1
      32: invokeinterface #104,  2          // InterfaceMethod org/apache/hadoop/hbase/client/Table.getScanner:(Lorg/apache/hadoop/hbase/client/Scan;)Lorg/apache/hadoop/hbase/client/ResultScanner;
      37: astore_2
      38: iconst_0
      39: istore_3
      40: iload_3
      41: bipush        30
      43: if_icmpge     75
      46: aload_2
      47: invokeinterface #105,  1          // InterfaceMethod org/apache/hadoop/hbase/client/ResultScanner.next:()Lorg/apache/hadoop/hbase/client/Result;
      52: astore        4
      54: aload         4
      56: invokestatic  #202                // Method org/junit/Assert.assertNotNull:(Ljava/lang/Object;)V
      59: lconst_1
      60: aload         4
      62: invokevirtual #203                // Method org/apache/hadoop/hbase/client/Result.size:()I
      65: i2l
      66: invokestatic  #204                // Method org/junit/Assert.assertEquals:(JJ)V
      69: iinc          3, 1
      72: goto          40
      75: getstatic     #155                // Field numScanNext:I
      78: bipush        30
      80: iadd
      81: putstatic     #155                // Field numScanNext:I
      84: aload_0
      85: ldc           #205                // String scanCount
      87: ldc2_w        #125                // long 30l
      90: invokevirtual #134                // Method assertRegionMetrics:(Ljava/lang/String;J)V
      93: getstatic     #13                 // Field TABLES_ON_MASTER:Z
      96: ifeq          109
      99: aload_0
     100: ldc           #206                // String ScanSize_num_ops
     102: getstatic     #155                // Field numScanNext:I
     105: i2l
     106: invokevirtual #127                // Method assertCounter:(Ljava/lang/String;J)V
     109: return

  public void testScanTime() throws java.lang.Exception;
    Code:
       0: aload_0
       1: bipush        100
       3: iconst_1
       4: invokevirtual #119                // Method doNPuts:(IZ)V
       7: new           #101                // class org/apache/hadoop/hbase/client/Scan
      10: dup
      11: invokespecial #102                // Method org/apache/hadoop/hbase/client/Scan."<init>":()V
      14: astore_1
      15: aload_1
      16: iconst_1
      17: invokevirtual #200                // Method org/apache/hadoop/hbase/client/Scan.setBatch:(I)Lorg/apache/hadoop/hbase/client/Scan;
      20: pop
      21: aload_1
      22: iconst_1
      23: invokevirtual #103                // Method org/apache/hadoop/hbase/client/Scan.setCaching:(I)Lorg/apache/hadoop/hbase/client/Scan;
      26: pop
      27: aload_0
      28: getfield      #51                 // Field table:Lorg/apache/hadoop/hbase/client/Table;
      31: aload_1
      32: invokeinterface #104,  2          // InterfaceMethod org/apache/hadoop/hbase/client/Table.getScanner:(Lorg/apache/hadoop/hbase/client/Scan;)Lorg/apache/hadoop/hbase/client/ResultScanner;
      37: astore_2
      38: iconst_0
      39: istore_3
      40: iload_3
      41: bipush        30
      43: if_icmpge     75
      46: aload_2
      47: invokeinterface #105,  1          // InterfaceMethod org/apache/hadoop/hbase/client/ResultScanner.next:()Lorg/apache/hadoop/hbase/client/Result;
      52: astore        4
      54: aload         4
      56: invokestatic  #202                // Method org/junit/Assert.assertNotNull:(Ljava/lang/Object;)V
      59: lconst_1
      60: aload         4
      62: invokevirtual #203                // Method org/apache/hadoop/hbase/client/Result.size:()I
      65: i2l
      66: invokestatic  #204                // Method org/junit/Assert.assertEquals:(JJ)V
      69: iinc          3, 1
      72: goto          40
      75: getstatic     #155                // Field numScanNext:I
      78: bipush        30
      80: iadd
      81: putstatic     #155                // Field numScanNext:I
      84: aload_0
      85: ldc           #205                // String scanCount
      87: ldc2_w        #125                // long 30l
      90: invokevirtual #134                // Method assertRegionMetrics:(Ljava/lang/String;J)V
      93: getstatic     #13                 // Field TABLES_ON_MASTER:Z
      96: ifeq          109
      99: aload_0
     100: ldc           #207                // String ScanTime_num_ops
     102: getstatic     #155                // Field numScanNext:I
     105: i2l
     106: invokevirtual #127                // Method assertCounter:(Ljava/lang/String;J)V
     109: return

  public void testScanSizeForSmallScan() throws java.lang.Exception;
    Code:
       0: aload_0
       1: bipush        100
       3: iconst_1
       4: invokevirtual #119                // Method doNPuts:(IZ)V
       7: new           #101                // class org/apache/hadoop/hbase/client/Scan
      10: dup
      11: invokespecial #102                // Method org/apache/hadoop/hbase/client/Scan."<init>":()V
      14: astore_1
      15: aload_1
      16: iconst_1
      17: invokevirtual #208                // Method org/apache/hadoop/hbase/client/Scan.setSmall:(Z)Lorg/apache/hadoop/hbase/client/Scan;
      20: pop
      21: aload_1
      22: iconst_1
      23: invokevirtual #103                // Method org/apache/hadoop/hbase/client/Scan.setCaching:(I)Lorg/apache/hadoop/hbase/client/Scan;
      26: pop
      27: aload_0
      28: getfield      #51                 // Field table:Lorg/apache/hadoop/hbase/client/Table;
      31: aload_1
      32: invokeinterface #104,  2          // InterfaceMethod org/apache/hadoop/hbase/client/Table.getScanner:(Lorg/apache/hadoop/hbase/client/Scan;)Lorg/apache/hadoop/hbase/client/ResultScanner;
      37: astore_2
      38: iconst_0
      39: istore_3
      40: iload_3
      41: bipush        30
      43: if_icmpge     81
      46: aload_2
      47: invokeinterface #105,  1          // InterfaceMethod org/apache/hadoop/hbase/client/ResultScanner.next:()Lorg/apache/hadoop/hbase/client/Result;
      52: astore        4
      54: aload         4
      56: invokestatic  #202                // Method org/junit/Assert.assertNotNull:(Ljava/lang/Object;)V
      59: getstatic     #13                 // Field TABLES_ON_MASTER:Z
      62: ifeq          75
      65: lconst_1
      66: aload         4
      68: invokevirtual #203                // Method org/apache/hadoop/hbase/client/Result.size:()I
      71: i2l
      72: invokestatic  #204                // Method org/junit/Assert.assertEquals:(JJ)V
      75: iinc          3, 1
      78: goto          40
      81: getstatic     #155                // Field numScanNext:I
      84: bipush        30
      86: iadd
      87: putstatic     #155                // Field numScanNext:I
      90: aload_0
      91: ldc           #205                // String scanCount
      93: ldc2_w        #125                // long 30l
      96: invokevirtual #134                // Method assertRegionMetrics:(Ljava/lang/String;J)V
      99: getstatic     #13                 // Field TABLES_ON_MASTER:Z
     102: ifeq          115
     105: aload_0
     106: ldc           #206                // String ScanSize_num_ops
     108: getstatic     #155                // Field numScanNext:I
     111: i2l
     112: invokevirtual #127                // Method assertCounter:(Ljava/lang/String;J)V
     115: return

  public void testMobMetrics() throws java.io.IOException, java.lang.InterruptedException;
    Code:
       0: ldc           #209                // String testMobMetricsLocal
       2: invokestatic  #47                 // Method org/apache/hadoop/hbase/TableName.valueOf:(Ljava/lang/String;)Lorg/apache/hadoop/hbase/TableName;
       5: astore_1
       6: iconst_5
       7: istore_2
       8: new           #210                // class org/apache/hadoop/hbase/HTableDescriptor
      11: dup
      12: aload_1
      13: invokespecial #211                // Method org/apache/hadoop/hbase/HTableDescriptor."<init>":(Lorg/apache/hadoop/hbase/TableName;)V
      16: astore_3
      17: new           #212                // class org/apache/hadoop/hbase/HColumnDescriptor
      20: dup
      21: getstatic     #49                 // Field cf:[B
      24: invokespecial #213                // Method org/apache/hadoop/hbase/HColumnDescriptor."<init>":([B)V
      27: astore        4
      29: aload         4
      31: iconst_1
      32: invokevirtual #214                // Method org/apache/hadoop/hbase/HColumnDescriptor.setMobEnabled:(Z)Lorg/apache/hadoop/hbase/HColumnDescriptor;
      35: pop
      36: aload         4
      38: lconst_0
      39: invokevirtual #215                // Method org/apache/hadoop/hbase/HColumnDescriptor.setMobThreshold:(J)Lorg/apache/hadoop/hbase/HColumnDescriptor;
      42: pop
      43: aload_3
      44: aload         4
      46: invokevirtual #216                // Method org/apache/hadoop/hbase/HTableDescriptor.addFamily:(Lorg/apache/hadoop/hbase/HColumnDescriptor;)Lorg/apache/hadoop/hbase/HTableDescriptor;
      49: pop
      50: ldc           #217                // String mobdata
      52: invokestatic  #88                 // Method org/apache/hadoop/hbase/util/Bytes.toBytes:(Ljava/lang/String;)[B
      55: astore        5
      57: getstatic     #10                 // Field TEST_UTIL:Lorg/apache/hadoop/hbase/HBaseTestingUtility;
      60: aload_3
      61: iconst_0
      62: iconst_0
      63: multianewarray #218,  2           // class "[[B"
      67: getstatic     #14                 // Field conf:Lorg/apache/hadoop/conf/Configuration;
      70: invokevirtual #219                // Method org/apache/hadoop/hbase/HBaseTestingUtility.createTable:(Lorg/apache/hadoop/hbase/client/TableDescriptor;[[BLorg/apache/hadoop/conf/Configuration;)Lorg/apache/hadoop/hbase/client/Table;
      73: astore        6
      75: getstatic     #35                 // Field rs:Lorg/apache/hadoop/hbase/regionserver/HRegionServer;
      78: aload_1
      79: invokevirtual #220                // Method org/apache/hadoop/hbase/regionserver/HRegionServer.getRegions:(Lorg/apache/hadoop/hbase/TableName;)Ljava/util/List;
      82: iconst_0
      83: invokeinterface #221,  2          // InterfaceMethod java/util/List.get:(I)Ljava/lang/Object;
      88: checkcast     #222                // class org/apache/hadoop/hbase/regionserver/HRegion
      91: astore        7
      93: iconst_0
      94: istore        8
      96: iload         8
      98: iload_2
      99: if_icmpge     154
     102: new           #84                 // class org/apache/hadoop/hbase/client/Put
     105: dup
     106: iload         8
     108: invokestatic  #223                // Method org/apache/hadoop/hbase/util/Bytes.toBytes:(I)[B
     111: invokespecial #89                 // Method org/apache/hadoop/hbase/client/Put."<init>":([B)V
     114: astore        9
     116: aload         9
     118: getstatic     #49                 // Field cf:[B
     121: getstatic     #90                 // Field qualifier:[B
     124: aload         5
     126: invokevirtual #92                 // Method org/apache/hadoop/hbase/client/Put.addColumn:([B[B[B)Lorg/apache/hadoop/hbase/client/Put;
     129: pop
     130: aload         6
     132: aload         9
     134: invokeinterface #96,  2           // InterfaceMethod org/apache/hadoop/hbase/client/Table.put:(Lorg/apache/hadoop/hbase/client/Put;)V
     139: getstatic     #29                 // Field admin:Lorg/apache/hadoop/hbase/client/Admin;
     142: aload_1
     143: invokeinterface #165,  2          // InterfaceMethod org/apache/hadoop/hbase/client/Admin.flush:(Lorg/apache/hadoop/hbase/TableName;)V
     148: iinc          8, 1
     151: goto          96
     154: getstatic     #40                 // Field metricsRegionServer:Lorg/apache/hadoop/hbase/regionserver/MetricsRegionServer;
     157: invokevirtual #44                 // Method org/apache/hadoop/hbase/regionserver/MetricsRegionServer.getRegionServerWrapper:()Lorg/apache/hadoop/hbase/regionserver/MetricsRegionServerWrapper;
     160: invokeinterface #45,  1           // InterfaceMethod org/apache/hadoop/hbase/regionserver/MetricsRegionServerWrapper.forceRecompute:()V
     165: aload_0
     166: ldc           #224                // String mobFlushCount
     168: iload_2
     169: i2l
     170: invokevirtual #127                // Method assertCounter:(Ljava/lang/String;J)V
     173: new           #101                // class org/apache/hadoop/hbase/client/Scan
     176: dup
     177: iconst_0
     178: invokestatic  #223                // Method org/apache/hadoop/hbase/util/Bytes.toBytes:(I)[B
     181: iload_2
     182: invokestatic  #223                // Method org/apache/hadoop/hbase/util/Bytes.toBytes:(I)[B
     185: invokespecial #225                // Method org/apache/hadoop/hbase/client/Scan."<init>":([B[B)V
     188: astore        8
     190: aload         6
     192: aload         8
     194: invokeinterface #104,  2          // InterfaceMethod org/apache/hadoop/hbase/client/Table.getScanner:(Lorg/apache/hadoop/hbase/client/Scan;)Lorg/apache/hadoop/hbase/client/ResultScanner;
     199: astore        9
     201: aload         9
     203: bipush        100
     205: invokeinterface #226,  2          // InterfaceMethod org/apache/hadoop/hbase/client/ResultScanner.next:(I)[Lorg/apache/hadoop/hbase/client/Result;
     210: pop
     211: getstatic     #155                // Field numScanNext:I
     214: iconst_1
     215: iadd
     216: putstatic     #155                // Field numScanNext:I
     219: aload         9
     221: invokeinterface #227,  1          // InterfaceMethod org/apache/hadoop/hbase/client/ResultScanner.close:()V
     226: getstatic     #40                 // Field metricsRegionServer:Lorg/apache/hadoop/hbase/regionserver/MetricsRegionServer;
     229: invokevirtual #44                 // Method org/apache/hadoop/hbase/regionserver/MetricsRegionServer.getRegionServerWrapper:()Lorg/apache/hadoop/hbase/regionserver/MetricsRegionServerWrapper;
     232: invokeinterface #45,  1           // InterfaceMethod org/apache/hadoop/hbase/regionserver/MetricsRegionServerWrapper.forceRecompute:()V
     237: aload_0
     238: ldc           #228                // String mobScanCellsCount
     240: iload_2
     241: i2l
     242: invokevirtual #127                // Method assertCounter:(Ljava/lang/String;J)V
     245: aload         7
     247: getstatic     #49                 // Field cf:[B
     250: ldc2_w        #37                 // long 100l
     253: invokestatic  #229                // Method setMobThreshold:(Lorg/apache/hadoop/hbase/regionserver/Region;[BJ)Lorg/apache/hadoop/hbase/regionserver/Region;
     256: pop
     257: aload         7
     259: invokevirtual #230                // Method org/apache/hadoop/hbase/regionserver/HRegion.initialize:()J
     262: pop2
     263: aload         7
     265: iconst_1
     266: invokevirtual #231                // Method org/apache/hadoop/hbase/regionserver/HRegion.compact:(Z)V
     269: getstatic     #40                 // Field metricsRegionServer:Lorg/apache/hadoop/hbase/regionserver/MetricsRegionServer;
     272: invokevirtual #44                 // Method org/apache/hadoop/hbase/regionserver/MetricsRegionServer.getRegionServerWrapper:()Lorg/apache/hadoop/hbase/regionserver/MetricsRegionServerWrapper;
     275: invokeinterface #45,  1           // InterfaceMethod org/apache/hadoop/hbase/regionserver/MetricsRegionServerWrapper.forceRecompute:()V
     280: aload_0
     281: ldc           #232                // String cellsCountCompactedFromMob
     283: iload_2
     284: i2l
     285: invokevirtual #127                // Method assertCounter:(Ljava/lang/String;J)V
     288: aload_0
     289: ldc           #233                // String cellsCountCompactedToMob
     291: lconst_0
     292: invokevirtual #127                // Method assertCounter:(Ljava/lang/String;J)V
     295: aload         6
     297: aload         8
     299: invokeinterface #104,  2          // InterfaceMethod org/apache/hadoop/hbase/client/Table.getScanner:(Lorg/apache/hadoop/hbase/client/Scan;)Lorg/apache/hadoop/hbase/client/ResultScanner;
     304: astore        9
     306: aload         9
     308: bipush        100
     310: invokeinterface #226,  2          // InterfaceMethod org/apache/hadoop/hbase/client/ResultScanner.next:(I)[Lorg/apache/hadoop/hbase/client/Result;
     315: pop
     316: getstatic     #155                // Field numScanNext:I
     319: iconst_1
     320: iadd
     321: putstatic     #155                // Field numScanNext:I
     324: getstatic     #40                 // Field metricsRegionServer:Lorg/apache/hadoop/hbase/regionserver/MetricsRegionServer;
     327: invokevirtual #44                 // Method org/apache/hadoop/hbase/regionserver/MetricsRegionServer.getRegionServerWrapper:()Lorg/apache/hadoop/hbase/regionserver/MetricsRegionServerWrapper;
     330: invokeinterface #45,  1           // InterfaceMethod org/apache/hadoop/hbase/regionserver/MetricsRegionServerWrapper.forceRecompute:()V
     335: aload_0
     336: ldc           #228                // String mobScanCellsCount
     338: lconst_0
     339: invokevirtual #127                // Method assertCounter:(Ljava/lang/String;J)V
     342: iload_2
     343: istore        10
     345: iload         10
     347: iconst_2
     348: iload_2
     349: imul
     350: if_icmpge     405
     353: new           #84                 // class org/apache/hadoop/hbase/client/Put
     356: dup
     357: iload         10
     359: invokestatic  #223                // Method org/apache/hadoop/hbase/util/Bytes.toBytes:(I)[B
     362: invokespecial #89                 // Method org/apache/hadoop/hbase/client/Put."<init>":([B)V
     365: astore        11
     367: aload         11
     369: getstatic     #49                 // Field cf:[B
     372: getstatic     #90                 // Field qualifier:[B
     375: aload         5
     377: invokevirtual #92                 // Method org/apache/hadoop/hbase/client/Put.addColumn:([B[B[B)Lorg/apache/hadoop/hbase/client/Put;
     380: pop
     381: aload         6
     383: aload         11
     385: invokeinterface #96,  2           // InterfaceMethod org/apache/hadoop/hbase/client/Table.put:(Lorg/apache/hadoop/hbase/client/Put;)V
     390: getstatic     #29                 // Field admin:Lorg/apache/hadoop/hbase/client/Admin;
     393: aload_1
     394: invokeinterface #165,  2          // InterfaceMethod org/apache/hadoop/hbase/client/Admin.flush:(Lorg/apache/hadoop/hbase/TableName;)V
     399: iinc          10, 1
     402: goto          345
     405: aload         7
     407: getstatic     #49                 // Field cf:[B
     410: lconst_0
     411: invokestatic  #229                // Method setMobThreshold:(Lorg/apache/hadoop/hbase/regionserver/Region;[BJ)Lorg/apache/hadoop/hbase/regionserver/Region;
     414: pop
     415: aload         7
     417: invokevirtual #234                // Method org/apache/hadoop/hbase/regionserver/HRegion.close:()Ljava/util/Map;
     420: pop
     421: aload         7
     423: invokevirtual #230                // Method org/apache/hadoop/hbase/regionserver/HRegion.initialize:()J
     426: pop2
     427: aload         7
     429: iconst_1
     430: invokevirtual #231                // Method org/apache/hadoop/hbase/regionserver/HRegion.compact:(Z)V
     433: getstatic     #40                 // Field metricsRegionServer:Lorg/apache/hadoop/hbase/regionserver/MetricsRegionServer;
     436: invokevirtual #44                 // Method org/apache/hadoop/hbase/regionserver/MetricsRegionServer.getRegionServerWrapper:()Lorg/apache/hadoop/hbase/regionserver/MetricsRegionServerWrapper;
     439: invokeinterface #45,  1           // InterfaceMethod org/apache/hadoop/hbase/regionserver/MetricsRegionServerWrapper.forceRecompute:()V
     444: aload_0
     445: ldc           #232                // String cellsCountCompactedFromMob
     447: lconst_0
     448: invokevirtual #127                // Method assertCounter:(Ljava/lang/String;J)V
     451: aload_0
     452: ldc           #233                // String cellsCountCompactedToMob
     454: iconst_2
     455: iload_2
     456: imul
     457: i2l
     458: invokevirtual #127                // Method assertCounter:(Ljava/lang/String;J)V
     461: getstatic     #29                 // Field admin:Lorg/apache/hadoop/hbase/client/Admin;
     464: aload_1
     465: invokeinterface #52,  2           // InterfaceMethod org/apache/hadoop/hbase/client/Admin.disableTable:(Lorg/apache/hadoop/hbase/TableName;)V
     470: getstatic     #29                 // Field admin:Lorg/apache/hadoop/hbase/client/Admin;
     473: aload_1
     474: invokeinterface #53,  2           // InterfaceMethod org/apache/hadoop/hbase/client/Admin.deleteTable:(Lorg/apache/hadoop/hbase/TableName;)V
     479: goto          505
     482: astore        12
     484: getstatic     #29                 // Field admin:Lorg/apache/hadoop/hbase/client/Admin;
     487: aload_1
     488: invokeinterface #52,  2           // InterfaceMethod org/apache/hadoop/hbase/client/Admin.disableTable:(Lorg/apache/hadoop/hbase/TableName;)V
     493: getstatic     #29                 // Field admin:Lorg/apache/hadoop/hbase/client/Admin;
     496: aload_1
     497: invokeinterface #53,  2           // InterfaceMethod org/apache/hadoop/hbase/client/Admin.deleteTable:(Lorg/apache/hadoop/hbase/TableName;)V
     502: aload         12
     504: athrow
     505: return
    Exception table:
       from    to  target type
          57   461   482   any
         482   484   482   any

  public void testRangeCountMetrics() throws java.lang.Exception;
    Code:
       0: bipush        14
       2: newarray       long
       4: dup
       5: iconst_0
       6: lconst_1
       7: lastore
       8: dup
       9: iconst_1
      10: ldc2_w        #245                // long 3l
      13: lastore
      14: dup
      15: iconst_2
      16: ldc2_w        #131                // long 10l
      19: lastore
      20: dup
      21: iconst_3
      22: ldc2_w        #125                // long 30l
      25: lastore
      26: dup
      27: iconst_4
      28: ldc2_w        #37                 // long 100l
      31: lastore
      32: dup
      33: iconst_5
      34: ldc2_w        #247                // long 300l
      37: lastore
      38: dup
      39: bipush        6
      41: ldc2_w        #249                // long 1000l
      44: lastore
      45: dup
      46: bipush        7
      48: ldc2_w        #251                // long 3000l
      51: lastore
      52: dup
      53: bipush        8
      55: ldc2_w        #253                // long 10000l
      58: lastore
      59: dup
      60: bipush        9
      62: ldc2_w        #255                // long 30000l
      65: lastore
      66: dup
      67: bipush        10
      69: ldc2_w        #257                // long 60000l
      72: lastore
      73: dup
      74: bipush        11
      76: ldc2_w        #259                // long 120000l
      79: lastore
      80: dup
      81: bipush        12
      83: ldc2_w        #261                // long 300000l
      86: lastore
      87: dup
      88: bipush        13
      90: ldc2_w        #263                // long 600000l
      93: lastore
      94: astore_1
      95: ldc_w         #265                // String TimeRangeCount
      98: astore_2
      99: ldc_w         #266                // String Mutate
     102: astore_3
     103: iconst_0
     104: istore        4
     106: new           #84                 // class org/apache/hadoop/hbase/client/Put
     109: dup
     110: getstatic     #95                 // Field row:[B
     113: invokespecial #89                 // Method org/apache/hadoop/hbase/client/Put."<init>":([B)V
     116: astore        5
     118: aload         5
     120: getstatic     #49                 // Field cf:[B
     123: getstatic     #90                 // Field qualifier:[B
     126: getstatic     #91                 // Field val:[B
     129: invokevirtual #92                 // Method org/apache/hadoop/hbase/client/Put.addColumn:([B[B[B)Lorg/apache/hadoop/hbase/client/Put;
     132: pop
     133: aload_0
     134: getfield      #51                 // Field table:Lorg/apache/hadoop/hbase/client/Table;
     137: aload         5
     139: invokeinterface #96,  2           // InterfaceMethod org/apache/hadoop/hbase/client/Table.put:(Lorg/apache/hadoop/hbase/client/Put;)V
     144: iconst_0
     145: istore        6
     147: iload         6
     149: bipush        10
     151: if_icmpge     171
     154: aload_0
     155: getfield      #51                 // Field table:Lorg/apache/hadoop/hbase/client/Table;
     158: aload         5
     160: invokeinterface #96,  2           // InterfaceMethod org/apache/hadoop/hbase/client/Table.put:(Lorg/apache/hadoop/hbase/client/Put;)V
     165: iinc          6, 1
     168: goto          147
     171: new           #97                 // class org/apache/hadoop/hbase/client/Get
     174: dup
     175: getstatic     #95                 // Field row:[B
     178: invokespecial #98                 // Method org/apache/hadoop/hbase/client/Get."<init>":([B)V
     181: astore        6
     183: iconst_0
     184: istore        7
     186: iload         7
     188: bipush        10
     190: if_icmpge     211
     193: aload_0
     194: getfield      #51                 // Field table:Lorg/apache/hadoop/hbase/client/Table;
     197: aload         6
     199: invokeinterface #100,  2          // InterfaceMethod org/apache/hadoop/hbase/client/Table.get:(Lorg/apache/hadoop/hbase/client/Get;)Lorg/apache/hadoop/hbase/client/Result;
     204: pop
     205: iinc          7, 1
     208: goto          186
     211: getstatic     #40                 // Field metricsRegionServer:Lorg/apache/hadoop/hbase/regionserver/MetricsRegionServer;
     214: invokevirtual #44                 // Method org/apache/hadoop/hbase/regionserver/MetricsRegionServer.getRegionServerWrapper:()Lorg/apache/hadoop/hbase/regionserver/MetricsRegionServerWrapper;
     217: invokeinterface #45,  1           // InterfaceMethod org/apache/hadoop/hbase/regionserver/MetricsRegionServerWrapper.forceRecompute:()V
     222: lconst_0
     223: lstore        7
     225: iconst_0
     226: istore        10
     228: iload         10
     230: aload_1
     231: arraylength
     232: if_icmpge     327
     235: new           #68                 // class java/lang/StringBuilder
     238: dup
     239: invokespecial #69                 // Method java/lang/StringBuilder."<init>":()V
     242: ldc_w         #267                // String Mutate_TimeRangeCount_
     245: invokevirtual #71                 // Method java/lang/StringBuilder.append:(Ljava/lang/String;)Ljava/lang/StringBuilder;
     248: lload         7
     250: invokevirtual #268                // Method java/lang/StringBuilder.append:(J)Ljava/lang/StringBuilder;
     253: ldc_w         #269                // String -
     256: invokevirtual #71                 // Method java/lang/StringBuilder.append:(Ljava/lang/String;)Ljava/lang/StringBuilder;
     259: aload_1
     260: iload         10
     262: laload
     263: invokevirtual #268                // Method java/lang/StringBuilder.append:(J)Ljava/lang/StringBuilder;
     266: invokevirtual #78                 // Method java/lang/StringBuilder.toString:()Ljava/lang/String;
     269: astore        9
     271: getstatic     #7                  // Field metricsHelper:Lorg/apache/hadoop/hbase/test/MetricsAssertHelper;
     274: aload         9
     276: getstatic     #42                 // Field serverSource:Lorg/apache/hadoop/hbase/regionserver/MetricsRegionServerSource;
     279: invokeinterface #270,  3          // InterfaceMethod org/apache/hadoop/hbase/test/MetricsAssertHelper.checkCounterExists:(Ljava/lang/String;Lorg/apache/hadoop/hbase/metrics/BaseSource;)Z
     284: ifeq          315
     287: getstatic     #7                  // Field metricsHelper:Lorg/apache/hadoop/hbase/test/MetricsAssertHelper;
     290: aload         9
     292: getstatic     #42                 // Field serverSource:Lorg/apache/hadoop/hbase/regionserver/MetricsRegionServerSource;
     295: invokeinterface #171,  3          // InterfaceMethod org/apache/hadoop/hbase/test/MetricsAssertHelper.getGaugeLong:(Ljava/lang/String;Lorg/apache/hadoop/hbase/metrics/BaseSource;)J
     300: lstore        11
     302: lload         11
     304: lconst_0
     305: lcmp
     306: ifle          315
     309: iconst_1
     310: istore        4
     312: goto          327
     315: aload_1
     316: iload         10
     318: laload
     319: lstore        7
     321: iinc          10, 1
     324: goto          228
     327: new           #68                 // class java/lang/StringBuilder
     330: dup
     331: invokespecial #69                 // Method java/lang/StringBuilder."<init>":()V
     334: ldc_w         #267                // String Mutate_TimeRangeCount_
     337: invokevirtual #71                 // Method java/lang/StringBuilder.append:(Ljava/lang/String;)Ljava/lang/StringBuilder;
     340: aload_1
     341: aload_1
     342: arraylength
     343: iconst_1
     344: isub
     345: laload
     346: invokevirtual #268                // Method java/lang/StringBuilder.append:(J)Ljava/lang/StringBuilder;
     349: ldc_w         #271                // String -inf
     352: invokevirtual #71                 // Method java/lang/StringBuilder.append:(Ljava/lang/String;)Ljava/lang/StringBuilder;
     355: invokevirtual #78                 // Method java/lang/StringBuilder.toString:()Ljava/lang/String;
     358: astore        9
     360: getstatic     #7                  // Field metricsHelper:Lorg/apache/hadoop/hbase/test/MetricsAssertHelper;
     363: aload         9
     365: getstatic     #42                 // Field serverSource:Lorg/apache/hadoop/hbase/regionserver/MetricsRegionServerSource;
     368: invokeinterface #270,  3          // InterfaceMethod org/apache/hadoop/hbase/test/MetricsAssertHelper.checkCounterExists:(Ljava/lang/String;Lorg/apache/hadoop/hbase/metrics/BaseSource;)Z
     373: ifeq          401
     376: getstatic     #7                  // Field metricsHelper:Lorg/apache/hadoop/hbase/test/MetricsAssertHelper;
     379: aload         9
     381: getstatic     #42                 // Field serverSource:Lorg/apache/hadoop/hbase/regionserver/MetricsRegionServerSource;
     384: invokeinterface #121,  3          // InterfaceMethod org/apache/hadoop/hbase/test/MetricsAssertHelper.getCounter:(Ljava/lang/String;Lorg/apache/hadoop/hbase/metrics/BaseSource;)J
     389: lstore        10
     391: lload         10
     393: lconst_0
     394: lcmp
     395: ifle          401
     398: iconst_1
     399: istore        4
     401: iconst_1
     402: invokestatic  #272                // Method java/lang/Boolean.valueOf:(Z)Ljava/lang/Boolean;
     405: iload         4
     407: invokestatic  #272                // Method java/lang/Boolean.valueOf:(Z)Ljava/lang/Boolean;
     410: invokestatic  #273                // Method org/junit/Assert.assertEquals:(Ljava/lang/Object;Ljava/lang/Object;)V
     413: return

  public void testAverageRegionSize() throws java.lang.Exception;
    Code:
       0: aload_0
       1: iconst_1
       2: iconst_0
       3: invokevirtual #119                // Method doNPuts:(IZ)V
       6: getstatic     #10                 // Field TEST_UTIL:Lorg/apache/hadoop/hbase/HBaseTestingUtility;
       9: invokevirtual #28                 // Method org/apache/hadoop/hbase/HBaseTestingUtility.getAdmin:()Lorg/apache/hadoop/hbase/client/Admin;
      12: aload_0
      13: getfield      #48                 // Field tableName:Lorg/apache/hadoop/hbase/TableName;
      16: invokeinterface #165,  2          // InterfaceMethod org/apache/hadoop/hbase/client/Admin.flush:(Lorg/apache/hadoop/hbase/TableName;)V
      21: getstatic     #40                 // Field metricsRegionServer:Lorg/apache/hadoop/hbase/regionserver/MetricsRegionServer;
      24: invokevirtual #44                 // Method org/apache/hadoop/hbase/regionserver/MetricsRegionServer.getRegionServerWrapper:()Lorg/apache/hadoop/hbase/regionserver/MetricsRegionServerWrapper;
      27: invokeinterface #45,  1           // InterfaceMethod org/apache/hadoop/hbase/regionserver/MetricsRegionServerWrapper.forceRecompute:()V
      32: getstatic     #7                  // Field metricsHelper:Lorg/apache/hadoop/hbase/test/MetricsAssertHelper;
      35: ldc_w         #274                // String averageRegionSize
      38: getstatic     #42                 // Field serverSource:Lorg/apache/hadoop/hbase/regionserver/MetricsRegionServerSource;
      41: invokeinterface #275,  3          // InterfaceMethod org/apache/hadoop/hbase/test/MetricsAssertHelper.getGaugeDouble:(Ljava/lang/String;Lorg/apache/hadoop/hbase/metrics/BaseSource;)D
      46: dconst_0
      47: dcmpl
      48: ifle          55
      51: iconst_1
      52: goto          56
      55: iconst_0
      56: invokestatic  #172                // Method org/junit/Assert.assertTrue:(Z)V
      59: return

  static {};
    Code:
       0: ldc           #201                // class org/apache/hadoop/hbase/regionserver/TestRegionServerMetrics
       2: invokestatic  #276                // Method org/apache/hadoop/hbase/HBaseClassTestRule.forClass:(Ljava/lang/Class;)Lorg/apache/hadoop/hbase/HBaseClassTestRule;
       5: putstatic     #277                // Field CLASS_RULE:Lorg/apache/hadoop/hbase/HBaseClassTestRule;
       8: ldc           #201                // class org/apache/hadoop/hbase/regionserver/TestRegionServerMetrics
      10: invokestatic  #278                // Method org/slf4j/LoggerFactory.getLogger:(Ljava/lang/Class;)Lorg/slf4j/Logger;
      13: putstatic     #106                // Field LOG:Lorg/slf4j/Logger;
      16: iconst_0
      17: putstatic     #155                // Field numScanNext:I
      20: ldc_w         #279                // String cf
      23: invokestatic  #88                 // Method org/apache/hadoop/hbase/util/Bytes.toBytes:(Ljava/lang/String;)[B
      26: putstatic     #49                 // Field cf:[B
      29: ldc           #87                 // String row
      31: invokestatic  #88                 // Method org/apache/hadoop/hbase/util/Bytes.toBytes:(Ljava/lang/String;)[B
      34: putstatic     #95                 // Field row:[B
      37: ldc_w         #280                // String qual
      40: invokestatic  #88                 // Method org/apache/hadoop/hbase/util/Bytes.toBytes:(Ljava/lang/String;)[B
      43: putstatic     #90                 // Field qualifier:[B
      46: ldc_w         #281                // String val
      49: invokestatic  #88                 // Method org/apache/hadoop/hbase/util/Bytes.toBytes:(Ljava/lang/String;)[B
      52: putstatic     #91                 // Field val:[B
      55: return
}
