Compiled from "TestSCPBase.java"
public class org.apache.hadoop.hbase.master.procedure.TestSCPBase {
  protected org.apache.hadoop.hbase.HBaseTestingUtility util;

  public org.apache.hadoop.hbase.master.procedure.TestSCPBase();
    Code:
       0: aload_0
       1: invokespecial #1                  // Method java/lang/Object."<init>":()V
       4: return

  protected void setupConf(org.apache.hadoop.conf.Configuration);
    Code:
       0: aload_1
       1: ldc           #3                  // String hbase.master.procedure.threads
       3: iconst_1
       4: invokevirtual #4                  // Method org/apache/hadoop/conf/Configuration.setInt:(Ljava/lang/String;I)V
       7: aload_1
       8: ldc           #5                  // String hbase.balancer.tablesOnMaster
      10: ldc           #6                  // String none
      12: invokevirtual #7                  // Method org/apache/hadoop/conf/Configuration.set:(Ljava/lang/String;Ljava/lang/String;)V
      15: aload_1
      16: ldc           #9                  // String hbase.client.retries.number
      18: iconst_3
      19: invokevirtual #4                  // Method org/apache/hadoop/conf/Configuration.setInt:(Ljava/lang/String;I)V
      22: aload_1
      23: ldc           #10                 // String hbase.client.serverside.retries.multiplier
      25: iconst_3
      26: invokevirtual #4                  // Method org/apache/hadoop/conf/Configuration.setInt:(Ljava/lang/String;I)V
      29: aload_1
      30: ldc           #11                 // String hbase.split.writer.creation.bounded
      32: iconst_1
      33: invokevirtual #12                 // Method org/apache/hadoop/conf/Configuration.setBoolean:(Ljava/lang/String;Z)V
      36: aload_1
      37: ldc           #13                 // String hbase.regionserver.hlog.splitlog.writer.threads
      39: bipush        8
      41: invokevirtual #4                  // Method org/apache/hadoop/conf/Configuration.setInt:(Ljava/lang/String;I)V
      44: aload_1
      45: ldc           #14                 // String hbase.split.wal.zk.coordinated
      47: iconst_1
      48: invokevirtual #12                 // Method org/apache/hadoop/conf/Configuration.setBoolean:(Ljava/lang/String;Z)V
      51: return

  public void setup() throws java.lang.Exception;
    Code:
       0: aload_0
       1: new           #15                 // class org/apache/hadoop/hbase/HBaseTestingUtility
       4: dup
       5: invokespecial #16                 // Method org/apache/hadoop/hbase/HBaseTestingUtility."<init>":()V
       8: putfield      #17                 // Field util:Lorg/apache/hadoop/hbase/HBaseTestingUtility;
      11: aload_0
      12: aload_0
      13: getfield      #17                 // Field util:Lorg/apache/hadoop/hbase/HBaseTestingUtility;
      16: invokevirtual #18                 // Method org/apache/hadoop/hbase/HBaseTestingUtility.getConfiguration:()Lorg/apache/hadoop/conf/Configuration;
      19: invokevirtual #19                 // Method setupConf:(Lorg/apache/hadoop/conf/Configuration;)V
      22: aload_0
      23: invokevirtual #20                 // Method startMiniCluster:()V
      26: aload_0
      27: getfield      #17                 // Field util:Lorg/apache/hadoop/hbase/HBaseTestingUtility;
      30: invokevirtual #21                 // Method org/apache/hadoop/hbase/HBaseTestingUtility.getHBaseCluster:()Lorg/apache/hadoop/hbase/MiniHBaseCluster;
      33: invokevirtual #22                 // Method org/apache/hadoop/hbase/MiniHBaseCluster.getMaster:()Lorg/apache/hadoop/hbase/master/HMaster;
      36: invokevirtual #23                 // Method org/apache/hadoop/hbase/master/HMaster.getMasterProcedureExecutor:()Lorg/apache/hadoop/hbase/procedure2/ProcedureExecutor;
      39: iconst_0
      40: invokestatic  #24                 // Method org/apache/hadoop/hbase/procedure2/ProcedureTestingUtility.setKillAndToggleBeforeStoreUpdate:(Lorg/apache/hadoop/hbase/procedure2/ProcedureExecutor;Z)V
      43: return

  protected void startMiniCluster() throws java.lang.Exception;
    Code:
       0: aload_0
       1: getfield      #17                 // Field util:Lorg/apache/hadoop/hbase/HBaseTestingUtility;
       4: iconst_3
       5: invokevirtual #25                 // Method org/apache/hadoop/hbase/HBaseTestingUtility.startMiniCluster:(I)Lorg/apache/hadoop/hbase/MiniHBaseCluster;
       8: pop
       9: return

  public void tearDown() throws java.lang.Exception;
    Code:
       0: aload_0
       1: getfield      #17                 // Field util:Lorg/apache/hadoop/hbase/HBaseTestingUtility;
       4: invokevirtual #21                 // Method org/apache/hadoop/hbase/HBaseTestingUtility.getHBaseCluster:()Lorg/apache/hadoop/hbase/MiniHBaseCluster;
       7: astore_1
       8: aload_1
       9: ifnonnull     16
      12: aconst_null
      13: goto          20
      16: aload_1
      17: invokevirtual #22                 // Method org/apache/hadoop/hbase/MiniHBaseCluster.getMaster:()Lorg/apache/hadoop/hbase/master/HMaster;
      20: astore_2
      21: aload_2
      22: ifnull        40
      25: aload_2
      26: invokevirtual #23                 // Method org/apache/hadoop/hbase/master/HMaster.getMasterProcedureExecutor:()Lorg/apache/hadoop/hbase/procedure2/ProcedureExecutor;
      29: ifnull        40
      32: aload_2
      33: invokevirtual #23                 // Method org/apache/hadoop/hbase/master/HMaster.getMasterProcedureExecutor:()Lorg/apache/hadoop/hbase/procedure2/ProcedureExecutor;
      36: iconst_0
      37: invokestatic  #24                 // Method org/apache/hadoop/hbase/procedure2/ProcedureTestingUtility.setKillAndToggleBeforeStoreUpdate:(Lorg/apache/hadoop/hbase/procedure2/ProcedureExecutor;Z)V
      40: aload_0
      41: getfield      #17                 // Field util:Lorg/apache/hadoop/hbase/HBaseTestingUtility;
      44: invokevirtual #26                 // Method org/apache/hadoop/hbase/HBaseTestingUtility.shutdownMiniCluster:()V
      47: return

  protected void testRecoveryAndDoubleExecution(boolean, boolean) throws java.lang.Exception;
    Code:
       0: new           #27                 // class java/lang/StringBuilder
       3: dup
       4: invokespecial #28                 // Method java/lang/StringBuilder."<init>":()V
       7: ldc           #29                 // String testRecoveryAndDoubleExecution-carryingMeta-
       9: invokevirtual #30                 // Method java/lang/StringBuilder.append:(Ljava/lang/String;)Ljava/lang/StringBuilder;
      12: iload_1
      13: invokevirtual #31                 // Method java/lang/StringBuilder.append:(Z)Ljava/lang/StringBuilder;
      16: ldc           #32                 // String -doubleExecution-
      18: invokevirtual #30                 // Method java/lang/StringBuilder.append:(Ljava/lang/String;)Ljava/lang/StringBuilder;
      21: iload_2
      22: invokevirtual #31                 // Method java/lang/StringBuilder.append:(Z)Ljava/lang/StringBuilder;
      25: invokevirtual #33                 // Method java/lang/StringBuilder.toString:()Ljava/lang/String;
      28: invokestatic  #34                 // Method org/apache/hadoop/hbase/TableName.valueOf:(Ljava/lang/String;)Lorg/apache/hadoop/hbase/TableName;
      31: astore_3
      32: aload_0
      33: aload_3
      34: invokevirtual #35                 // Method createTable:(Lorg/apache/hadoop/hbase/TableName;)Lorg/apache/hadoop/hbase/client/Table;
      37: astore        4
      39: aconst_null
      40: astore        5
      42: aload_0
      43: getfield      #17                 // Field util:Lorg/apache/hadoop/hbase/HBaseTestingUtility;
      46: aload         4
      48: getstatic     #36                 // Field org/apache/hadoop/hbase/HBaseTestingUtility.COLUMNS:[[B
      51: iconst_0
      52: aaload
      53: invokevirtual #37                 // Method org/apache/hadoop/hbase/HBaseTestingUtility.loadTable:(Lorg/apache/hadoop/hbase/client/Table;[B)I
      56: pop
      57: aload         4
      59: invokestatic  #38                 // Method org/apache/hadoop/hbase/HBaseTestingUtility.countRows:(Lorg/apache/hadoop/hbase/client/Table;)I
      62: istore        6
      64: ldc           #39                 // String expected some rows
      66: iload         6
      68: ifle          75
      71: iconst_1
      72: goto          76
      75: iconst_0
      76: invokestatic  #40                 // Method org/junit/Assert.assertTrue:(Ljava/lang/String;Z)V
      79: aload_0
      80: getfield      #17                 // Field util:Lorg/apache/hadoop/hbase/HBaseTestingUtility;
      83: aload         4
      85: invokevirtual #41                 // Method org/apache/hadoop/hbase/HBaseTestingUtility.checksumRows:(Lorg/apache/hadoop/hbase/client/Table;)Ljava/lang/String;
      88: astore        7
      90: aload_0
      91: getfield      #17                 // Field util:Lorg/apache/hadoop/hbase/HBaseTestingUtility;
      94: invokevirtual #21                 // Method org/apache/hadoop/hbase/HBaseTestingUtility.getHBaseCluster:()Lorg/apache/hadoop/hbase/MiniHBaseCluster;
      97: invokevirtual #22                 // Method org/apache/hadoop/hbase/MiniHBaseCluster.getMaster:()Lorg/apache/hadoop/hbase/master/HMaster;
     100: astore        8
     102: aload         8
     104: invokevirtual #23                 // Method org/apache/hadoop/hbase/master/HMaster.getMasterProcedureExecutor:()Lorg/apache/hadoop/hbase/procedure2/ProcedureExecutor;
     107: astore        9
     109: aconst_null
     110: astore        10
     112: aload_0
     113: getfield      #17                 // Field util:Lorg/apache/hadoop/hbase/HBaseTestingUtility;
     116: invokevirtual #42                 // Method org/apache/hadoop/hbase/HBaseTestingUtility.getAdmin:()Lorg/apache/hadoop/hbase/client/Admin;
     119: aload_3
     120: invokeinterface #43,  2           // InterfaceMethod org/apache/hadoop/hbase/client/Admin.getRegions:(Lorg/apache/hadoop/hbase/TableName;)Ljava/util/List;
     125: invokeinterface #44,  1           // InterfaceMethod java/util/List.iterator:()Ljava/util/Iterator;
     130: astore        11
     132: aload         11
     134: invokeinterface #45,  1           // InterfaceMethod java/util/Iterator.hasNext:()Z
     139: ifeq          188
     142: aload         11
     144: invokeinterface #46,  1           // InterfaceMethod java/util/Iterator.next:()Ljava/lang/Object;
     149: checkcast     #47                 // class org/apache/hadoop/hbase/client/RegionInfo
     152: astore        12
     154: aload_0
     155: getfield      #17                 // Field util:Lorg/apache/hadoop/hbase/HBaseTestingUtility;
     158: aload         12
     160: invokestatic  #48                 // Method org/apache/hadoop/hbase/master/assignment/AssignmentTestingUtil.getServerHoldingRegion:(Lorg/apache/hadoop/hbase/HBaseTestingUtility;Lorg/apache/hadoop/hbase/client/RegionInfo;)Lorg/apache/hadoop/hbase/ServerName;
     163: astore        13
     165: aload_0
     166: getfield      #17                 // Field util:Lorg/apache/hadoop/hbase/HBaseTestingUtility;
     169: aload         13
     171: invokestatic  #49                 // Method org/apache/hadoop/hbase/master/assignment/AssignmentTestingUtil.isServerHoldingMeta:(Lorg/apache/hadoop/hbase/HBaseTestingUtility;Lorg/apache/hadoop/hbase/ServerName;)Z
     174: iload_1
     175: if_icmpne     185
     178: aload         13
     180: astore        10
     182: goto          188
     185: goto          132
     188: aload         9
     190: invokestatic  #50                 // Method org/apache/hadoop/hbase/procedure2/ProcedureTestingUtility.waitNoProcedureRunning:(Lorg/apache/hadoop/hbase/procedure2/ProcedureExecutor;)V
     193: iload_2
     194: ifeq          236
     197: aload         9
     199: iconst_0
     200: invokestatic  #51                 // Method org/apache/hadoop/hbase/procedure2/ProcedureTestingUtility.setKillIfHasParent:(Lorg/apache/hadoop/hbase/procedure2/ProcedureExecutor;Z)V
     203: aload         9
     205: iconst_1
     206: invokestatic  #24                 // Method org/apache/hadoop/hbase/procedure2/ProcedureTestingUtility.setKillAndToggleBeforeStoreUpdate:(Lorg/apache/hadoop/hbase/procedure2/ProcedureExecutor;Z)V
     209: aload_0
     210: getfield      #17                 // Field util:Lorg/apache/hadoop/hbase/HBaseTestingUtility;
     213: aload         10
     215: invokestatic  #52                 // Method org/apache/hadoop/hbase/master/assignment/AssignmentTestingUtil.killRs:(Lorg/apache/hadoop/hbase/HBaseTestingUtility;Lorg/apache/hadoop/hbase/ServerName;)V
     218: aload_0
     219: aload         9
     221: invokevirtual #53                 // Method getSCPProcId:(Lorg/apache/hadoop/hbase/procedure2/ProcedureExecutor;)J
     224: lstore        11
     226: aload         9
     228: lload         11
     230: invokestatic  #54                 // Method org/apache/hadoop/hbase/master/procedure/MasterProcedureTestingUtility.testRecoveryAndDoubleExecution:(Lorg/apache/hadoop/hbase/procedure2/ProcedureExecutor;J)V
     233: goto          260
     236: aload_0
     237: getfield      #17                 // Field util:Lorg/apache/hadoop/hbase/HBaseTestingUtility;
     240: aload         10
     242: invokestatic  #52                 // Method org/apache/hadoop/hbase/master/assignment/AssignmentTestingUtil.killRs:(Lorg/apache/hadoop/hbase/HBaseTestingUtility;Lorg/apache/hadoop/hbase/ServerName;)V
     245: aload_0
     246: aload         9
     248: invokevirtual #53                 // Method getSCPProcId:(Lorg/apache/hadoop/hbase/procedure2/ProcedureExecutor;)J
     251: lstore        11
     253: aload         9
     255: lload         11
     257: invokestatic  #55                 // Method org/apache/hadoop/hbase/procedure2/ProcedureTestingUtility.waitProcedure:(Lorg/apache/hadoop/hbase/procedure2/ProcedureExecutor;J)V
     260: aload_0
     261: aload         4
     263: invokespecial #56                 // Method assertReplicaDistributed:(Lorg/apache/hadoop/hbase/client/Table;)V
     266: iload         6
     268: i2l
     269: aload         4
     271: invokestatic  #38                 // Method org/apache/hadoop/hbase/HBaseTestingUtility.countRows:(Lorg/apache/hadoop/hbase/client/Table;)I
     274: i2l
     275: invokestatic  #57                 // Method org/junit/Assert.assertEquals:(JJ)V
     278: aload         7
     280: aload_0
     281: getfield      #17                 // Field util:Lorg/apache/hadoop/hbase/HBaseTestingUtility;
     284: aload         4
     286: invokevirtual #41                 // Method org/apache/hadoop/hbase/HBaseTestingUtility.checksumRows:(Lorg/apache/hadoop/hbase/client/Table;)Ljava/lang/String;
     289: invokestatic  #58                 // Method org/junit/Assert.assertEquals:(Ljava/lang/Object;Ljava/lang/Object;)V
     292: aload         4
     294: ifnull        387
     297: aload         5
     299: ifnull        324
     302: aload         4
     304: invokeinterface #59,  1           // InterfaceMethod org/apache/hadoop/hbase/client/Table.close:()V
     309: goto          387
     312: astore        6
     314: aload         5
     316: aload         6
     318: invokevirtual #61                 // Method java/lang/Throwable.addSuppressed:(Ljava/lang/Throwable;)V
     321: goto          387
     324: aload         4
     326: invokeinterface #59,  1           // InterfaceMethod org/apache/hadoop/hbase/client/Table.close:()V
     331: goto          387
     334: astore        6
     336: aload         6
     338: astore        5
     340: aload         6
     342: athrow
     343: astore        14
     345: aload         4
     347: ifnull        384
     350: aload         5
     352: ifnull        377
     355: aload         4
     357: invokeinterface #59,  1           // InterfaceMethod org/apache/hadoop/hbase/client/Table.close:()V
     362: goto          384
     365: astore        15
     367: aload         5
     369: aload         15
     371: invokevirtual #61                 // Method java/lang/Throwable.addSuppressed:(Ljava/lang/Throwable;)V
     374: goto          384
     377: aload         4
     379: invokeinterface #59,  1           // InterfaceMethod org/apache/hadoop/hbase/client/Table.close:()V
     384: aload         14
     386: athrow
     387: return
    Exception table:
       from    to  target type
         302   309   312   Class java/lang/Throwable
          42   292   334   Class java/lang/Throwable
          42   292   343   any
         355   362   365   Class java/lang/Throwable
         334   345   343   any

  protected long getSCPProcId(org.apache.hadoop.hbase.procedure2.ProcedureExecutor<?>);
    Code:
       0: aload_0
       1: getfield      #17                 // Field util:Lorg/apache/hadoop/hbase/HBaseTestingUtility;
       4: ldc2_w        #62                 // long 30000l
       7: aload_1
       8: invokedynamic #64,  0             // InvokeDynamic #0:evaluate:(Lorg/apache/hadoop/hbase/procedure2/ProcedureExecutor;)Lorg/apache/hadoop/hbase/Waiter$Predicate;
      13: invokevirtual #65                 // Method org/apache/hadoop/hbase/HBaseTestingUtility.waitFor:(JLorg/apache/hadoop/hbase/Waiter$Predicate;)J
      16: pop2
      17: aload_1
      18: invokevirtual #66                 // Method org/apache/hadoop/hbase/procedure2/ProcedureExecutor.getActiveProcIds:()Ljava/util/Set;
      21: invokeinterface #67,  1           // InterfaceMethod java/util/Set.stream:()Ljava/util/stream/Stream;
      26: invokedynamic #68,  0             // InvokeDynamic #1:applyAsLong:()Ljava/util/function/ToLongFunction;
      31: invokeinterface #69,  2           // InterfaceMethod java/util/stream/Stream.mapToLong:(Ljava/util/function/ToLongFunction;)Ljava/util/stream/LongStream;
      36: invokeinterface #70,  1           // InterfaceMethod java/util/stream/LongStream.min:()Ljava/util/OptionalLong;
      41: invokevirtual #71                 // Method java/util/OptionalLong.getAsLong:()J
      44: lreturn

  protected org.apache.hadoop.hbase.client.Table createTable(org.apache.hadoop.hbase.TableName) throws java.io.IOException;
    Code:
       0: aload_0
       1: getfield      #17                 // Field util:Lorg/apache/hadoop/hbase/HBaseTestingUtility;
       4: aload_1
       5: getstatic     #36                 // Field org/apache/hadoop/hbase/HBaseTestingUtility.COLUMNS:[[B
       8: getstatic     #98                 // Field org/apache/hadoop/hbase/HBaseTestingUtility.KEYS_FOR_HBA_CREATE_TABLE:[[B
      11: aload_0
      12: invokevirtual #99                 // Method getRegionReplication:()I
      15: invokevirtual #100                // Method org/apache/hadoop/hbase/HBaseTestingUtility.createTable:(Lorg/apache/hadoop/hbase/TableName;[[B[[BI)Lorg/apache/hadoop/hbase/client/Table;
      18: astore_2
      19: aload_2
      20: areturn

  protected int getRegionReplication();
    Code:
       0: iconst_1
       1: ireturn

  static {};
    Code:
       0: ldc           #103                // class org/apache/hadoop/hbase/master/procedure/TestSCPBase
       2: invokestatic  #104                // Method org/slf4j/LoggerFactory.getLogger:(Ljava/lang/Class;)Lorg/slf4j/Logger;
       5: putstatic     #84                 // Field LOG:Lorg/slf4j/Logger;
       8: return
}
