Compiled from "TestYieldProcedures.java"
public class org.apache.hadoop.hbase.procedure2.TestYieldProcedures$TestYieldProcedure extends org.apache.hadoop.hbase.procedure2.Procedure<org.apache.hadoop.hbase.procedure2.TestYieldProcedures$TestProcEnv> {
  public org.apache.hadoop.hbase.procedure2.TestYieldProcedures$TestYieldProcedure();
    Code:
       0: aload_0
       1: invokespecial #2                  // Method org/apache/hadoop/hbase/procedure2/Procedure."<init>":()V
       4: aload_0
       5: iconst_0
       6: putfield      #1                  // Field step:I
       9: return

  protected org.apache.hadoop.hbase.procedure2.Procedure[] execute(org.apache.hadoop.hbase.procedure2.TestYieldProcedures$TestProcEnv) throws org.apache.hadoop.hbase.procedure2.ProcedureYieldException;
    Code:
       0: invokestatic  #3                  // Method org/apache/hadoop/hbase/procedure2/TestYieldProcedures.access$700:()Lorg/slf4j/Logger;
       3: new           #4                  // class java/lang/StringBuilder
       6: dup
       7: invokespecial #5                  // Method java/lang/StringBuilder."<init>":()V
      10: ldc           #6                  // String execute step
      12: invokevirtual #7                  // Method java/lang/StringBuilder.append:(Ljava/lang/String;)Ljava/lang/StringBuilder;
      15: aload_0
      16: getfield      #1                  // Field step:I
      19: invokevirtual #8                  // Method java/lang/StringBuilder.append:(I)Ljava/lang/StringBuilder;
      22: invokevirtual #9                  // Method java/lang/StringBuilder.toString:()Ljava/lang/String;
      25: invokeinterface #10,  2           // InterfaceMethod org/slf4j/Logger.info:(Ljava/lang/String;)V
      30: aload_0
      31: dup
      32: getfield      #1                  // Field step:I
      35: dup_x1
      36: iconst_1
      37: iadd
      38: putfield      #1                  // Field step:I
      41: iconst_5
      42: if_icmpge     53
      45: new           #11                 // class org/apache/hadoop/hbase/procedure2/ProcedureYieldException
      48: dup
      49: invokespecial #12                 // Method org/apache/hadoop/hbase/procedure2/ProcedureYieldException."<init>":()V
      52: athrow
      53: aconst_null
      54: areturn

  protected void rollback(org.apache.hadoop.hbase.procedure2.TestYieldProcedures$TestProcEnv);
    Code:
       0: return

  protected boolean abort(org.apache.hadoop.hbase.procedure2.TestYieldProcedures$TestProcEnv);
    Code:
       0: iconst_0
       1: ireturn

  protected boolean isYieldAfterExecutionStep(org.apache.hadoop.hbase.procedure2.TestYieldProcedures$TestProcEnv);
    Code:
       0: iconst_1
       1: ireturn

  protected void serializeStateData(org.apache.hadoop.hbase.procedure2.ProcedureStateSerializer) throws java.io.IOException;
    Code:
       0: return

  protected void deserializeStateData(org.apache.hadoop.hbase.procedure2.ProcedureStateSerializer) throws java.io.IOException;
    Code:
       0: return

  protected boolean isYieldAfterExecutionStep(java.lang.Object);
    Code:
       0: aload_0
       1: aload_1
       2: checkcast     #13                 // class org/apache/hadoop/hbase/procedure2/TestYieldProcedures$TestProcEnv
       5: invokevirtual #14                 // Method isYieldAfterExecutionStep:(Lorg/apache/hadoop/hbase/procedure2/TestYieldProcedures$TestProcEnv;)Z
       8: ireturn

  protected boolean abort(java.lang.Object);
    Code:
       0: aload_0
       1: aload_1
       2: checkcast     #13                 // class org/apache/hadoop/hbase/procedure2/TestYieldProcedures$TestProcEnv
       5: invokevirtual #15                 // Method abort:(Lorg/apache/hadoop/hbase/procedure2/TestYieldProcedures$TestProcEnv;)Z
       8: ireturn

  protected void rollback(java.lang.Object) throws java.io.IOException, java.lang.InterruptedException;
    Code:
       0: aload_0
       1: aload_1
       2: checkcast     #13                 // class org/apache/hadoop/hbase/procedure2/TestYieldProcedures$TestProcEnv
       5: invokevirtual #16                 // Method rollback:(Lorg/apache/hadoop/hbase/procedure2/TestYieldProcedures$TestProcEnv;)V
       8: return

  protected org.apache.hadoop.hbase.procedure2.Procedure[] execute(java.lang.Object) throws org.apache.hadoop.hbase.procedure2.ProcedureYieldException, org.apache.hadoop.hbase.procedure2.ProcedureSuspendedException, java.lang.InterruptedException;
    Code:
       0: aload_0
       1: aload_1
       2: checkcast     #13                 // class org/apache/hadoop/hbase/procedure2/TestYieldProcedures$TestProcEnv
       5: invokevirtual #17                 // Method execute:(Lorg/apache/hadoop/hbase/procedure2/TestYieldProcedures$TestProcEnv;)[Lorg/apache/hadoop/hbase/procedure2/Procedure;
       8: areturn

  static int access$600(org.apache.hadoop.hbase.procedure2.TestYieldProcedures$TestYieldProcedure);
    Code:
       0: aload_0
       1: getfield      #1                  // Field step:I
       4: ireturn
}
