Compiled from "TestCompaction.java"
public class org.apache.hadoop.hbase.regionserver.TestCompaction$DummyCompactor extends org.apache.hadoop.hbase.regionserver.compactions.DefaultCompactor {
  public org.apache.hadoop.hbase.regionserver.TestCompaction$DummyCompactor(org.apache.hadoop.conf.Configuration, org.apache.hadoop.hbase.regionserver.HStore);
    Code:
       0: aload_0
       1: aload_1
       2: aload_2
       3: invokespecial #1                  // Method org/apache/hadoop/hbase/regionserver/compactions/DefaultCompactor."<init>":(Lorg/apache/hadoop/conf/Configuration;Lorg/apache/hadoop/hbase/regionserver/HStore;)V
       6: aload_0
       7: iconst_0
       8: putfield      #2                  // Field keepSeqIdPeriod:I
      11: return
}
