Compiled from "TestSnapshotManifest.java"
public class org.apache.hadoop.hbase.snapshot.TestSnapshotManifest {
  public static final org.apache.hadoop.hbase.HBaseClassTestRule CLASS_RULE;

  public org.apache.hadoop.hbase.snapshot.TestSnapshotManifest();
    Code:
       0: aload_0
       1: invokespecial #1                  // Method java/lang/Object."<init>":()V
       4: aload_0
       5: aload_0
       6: invokevirtual #2                  // Method java/lang/Object.getClass:()Ljava/lang/Class;
       9: invokestatic  #3                  // Method org/slf4j/LoggerFactory.getLogger:(Ljava/lang/Class;)Lorg/slf4j/Logger;
      12: putfield      #4                  // Field LOG:Lorg/slf4j/Logger;
      15: return

  public void setup() throws java.lang.Exception;
    Code:
       0: invokestatic  #5                  // Method org/apache/hadoop/hbase/HBaseTestingUtility.createLocalHTU:()Lorg/apache/hadoop/hbase/HBaseTestingUtility;
       3: putstatic     #6                  // Field TEST_UTIL:Lorg/apache/hadoop/hbase/HBaseTestingUtility;
       6: aload_0
       7: getstatic     #6                  // Field TEST_UTIL:Lorg/apache/hadoop/hbase/HBaseTestingUtility;
      10: ldc           #8                  // String testSnapshotManifest
      12: invokevirtual #9                  // Method org/apache/hadoop/hbase/HBaseTestingUtility.getDataTestDir:(Ljava/lang/String;)Lorg/apache/hadoop/fs/Path;
      15: putfield      #10                 // Field rootDir:Lorg/apache/hadoop/fs/Path;
      18: aload_0
      19: getstatic     #6                  // Field TEST_UTIL:Lorg/apache/hadoop/hbase/HBaseTestingUtility;
      22: invokevirtual #11                 // Method org/apache/hadoop/hbase/HBaseTestingUtility.getTestFileSystem:()Lorg/apache/hadoop/fs/FileSystem;
      25: putfield      #12                 // Field fs:Lorg/apache/hadoop/fs/FileSystem;
      28: aload_0
      29: getstatic     #6                  // Field TEST_UTIL:Lorg/apache/hadoop/hbase/HBaseTestingUtility;
      32: invokevirtual #13                 // Method org/apache/hadoop/hbase/HBaseTestingUtility.getConfiguration:()Lorg/apache/hadoop/conf/Configuration;
      35: putfield      #14                 // Field conf:Lorg/apache/hadoop/conf/Configuration;
      38: new           #15                 // class org/apache/hadoop/hbase/snapshot/SnapshotTestingUtils$SnapshotMock
      41: dup
      42: aload_0
      43: getfield      #14                 // Field conf:Lorg/apache/hadoop/conf/Configuration;
      46: aload_0
      47: getfield      #12                 // Field fs:Lorg/apache/hadoop/fs/FileSystem;
      50: aload_0
      51: getfield      #10                 // Field rootDir:Lorg/apache/hadoop/fs/Path;
      54: invokespecial #16                 // Method org/apache/hadoop/hbase/snapshot/SnapshotTestingUtils$SnapshotMock."<init>":(Lorg/apache/hadoop/conf/Configuration;Lorg/apache/hadoop/fs/FileSystem;Lorg/apache/hadoop/fs/Path;)V
      57: astore_1
      58: aload_0
      59: aload_1
      60: ldc           #17                 // String snapshot
      62: ldc           #8                  // String testSnapshotManifest
      64: iconst_0
      65: invokevirtual #18                 // Method org/apache/hadoop/hbase/snapshot/SnapshotTestingUtils$SnapshotMock.createSnapshotV2:(Ljava/lang/String;Ljava/lang/String;I)Lorg/apache/hadoop/hbase/snapshot/SnapshotTestingUtils$SnapshotMock$SnapshotBuilder;
      68: putfield      #19                 // Field builder:Lorg/apache/hadoop/hbase/snapshot/SnapshotTestingUtils$SnapshotMock$SnapshotBuilder;
      71: aload_0
      72: aload_0
      73: getfield      #19                 // Field builder:Lorg/apache/hadoop/hbase/snapshot/SnapshotTestingUtils$SnapshotMock$SnapshotBuilder;
      76: invokevirtual #20                 // Method org/apache/hadoop/hbase/snapshot/SnapshotTestingUtils$SnapshotMock$SnapshotBuilder.commit:()Lorg/apache/hadoop/fs/Path;
      79: putfield      #21                 // Field snapshotDir:Lorg/apache/hadoop/fs/Path;
      82: aload_0
      83: aload_0
      84: getfield      #19                 // Field builder:Lorg/apache/hadoop/hbase/snapshot/SnapshotTestingUtils$SnapshotMock$SnapshotBuilder;
      87: invokevirtual #22                 // Method org/apache/hadoop/hbase/snapshot/SnapshotTestingUtils$SnapshotMock$SnapshotBuilder.getSnapshotDescription:()Lorg/apache/hadoop/hbase/shaded/protobuf/generated/SnapshotProtos$SnapshotDescription;
      90: putfield      #23                 // Field snapshotDesc:Lorg/apache/hadoop/hbase/shaded/protobuf/generated/SnapshotProtos$SnapshotDescription;
      93: return

  public void tearDown() throws java.lang.Exception;
    Code:
       0: aload_0
       1: getfield      #12                 // Field fs:Lorg/apache/hadoop/fs/FileSystem;
       4: aload_0
       5: getfield      #10                 // Field rootDir:Lorg/apache/hadoop/fs/Path;
       8: iconst_1
       9: invokevirtual #24                 // Method org/apache/hadoop/fs/FileSystem.delete:(Lorg/apache/hadoop/fs/Path;Z)Z
      12: pop
      13: return

  public void testReadSnapshotManifest() throws java.io.IOException;
    Code:
       0: aload_0
       1: invokespecial #25                 // Method createDataManifest:()Lorg/apache/hadoop/fs/Path;
       4: astore_1
       5: aload_0
       6: getfield      #14                 // Field conf:Lorg/apache/hadoop/conf/Configuration;
       9: aload_0
      10: getfield      #12                 // Field fs:Lorg/apache/hadoop/fs/FileSystem;
      13: aload_0
      14: getfield      #21                 // Field snapshotDir:Lorg/apache/hadoop/fs/Path;
      17: aload_0
      18: getfield      #23                 // Field snapshotDesc:Lorg/apache/hadoop/hbase/shaded/protobuf/generated/SnapshotProtos$SnapshotDescription;
      21: invokestatic  #26                 // Method org/apache/hadoop/hbase/snapshot/SnapshotManifest.open:(Lorg/apache/hadoop/conf/Configuration;Lorg/apache/hadoop/fs/FileSystem;Lorg/apache/hadoop/fs/Path;Lorg/apache/hadoop/hbase/shaded/protobuf/generated/SnapshotProtos$SnapshotDescription;)Lorg/apache/hadoop/hbase/snapshot/SnapshotManifest;
      24: pop
      25: ldc           #27                 // String fail to test snapshot manifest because message size is too small.
      27: invokestatic  #28                 // Method org/junit/Assert.fail:(Ljava/lang/String;)V
      30: aload_0
      31: getfield      #12                 // Field fs:Lorg/apache/hadoop/fs/FileSystem;
      34: aload_1
      35: iconst_0
      36: invokevirtual #24                 // Method org/apache/hadoop/fs/FileSystem.delete:(Lorg/apache/hadoop/fs/Path;Z)Z
      39: pop
      40: goto          123
      43: astore_2
      44: aload_0
      45: getfield      #14                 // Field conf:Lorg/apache/hadoop/conf/Configuration;
      48: ldc           #31                 // String snapshot.manifest.size.limit
      50: ldc           #32                 // int 134217728
      52: invokevirtual #33                 // Method org/apache/hadoop/conf/Configuration.setInt:(Ljava/lang/String;I)V
      55: aload_0
      56: getfield      #14                 // Field conf:Lorg/apache/hadoop/conf/Configuration;
      59: aload_0
      60: getfield      #12                 // Field fs:Lorg/apache/hadoop/fs/FileSystem;
      63: aload_0
      64: getfield      #21                 // Field snapshotDir:Lorg/apache/hadoop/fs/Path;
      67: aload_0
      68: getfield      #23                 // Field snapshotDesc:Lorg/apache/hadoop/hbase/shaded/protobuf/generated/SnapshotProtos$SnapshotDescription;
      71: invokestatic  #26                 // Method org/apache/hadoop/hbase/snapshot/SnapshotManifest.open:(Lorg/apache/hadoop/conf/Configuration;Lorg/apache/hadoop/fs/FileSystem;Lorg/apache/hadoop/fs/Path;Lorg/apache/hadoop/hbase/shaded/protobuf/generated/SnapshotProtos$SnapshotDescription;)Lorg/apache/hadoop/hbase/snapshot/SnapshotManifest;
      74: pop
      75: aload_0
      76: getfield      #4                  // Field LOG:Lorg/slf4j/Logger;
      79: ldc           #34                 // String open snapshot manifest succeed.
      81: invokeinterface #35,  2           // InterfaceMethod org/slf4j/Logger.info:(Ljava/lang/String;)V
      86: goto          95
      89: astore_3
      90: ldc           #36                 // String fail to take snapshot because Manifest proto-message too large.
      92: invokestatic  #28                 // Method org/junit/Assert.fail:(Ljava/lang/String;)V
      95: aload_0
      96: getfield      #12                 // Field fs:Lorg/apache/hadoop/fs/FileSystem;
      99: aload_1
     100: iconst_0
     101: invokevirtual #24                 // Method org/apache/hadoop/fs/FileSystem.delete:(Lorg/apache/hadoop/fs/Path;Z)Z
     104: pop
     105: goto          123
     108: astore        4
     110: aload_0
     111: getfield      #12                 // Field fs:Lorg/apache/hadoop/fs/FileSystem;
     114: aload_1
     115: iconst_0
     116: invokevirtual #24                 // Method org/apache/hadoop/fs/FileSystem.delete:(Lorg/apache/hadoop/fs/Path;Z)Z
     119: pop
     120: aload         4
     122: athrow
     123: return
    Exception table:
       from    to  target type
           5    30    43   Class org/apache/hadoop/hbase/snapshot/CorruptedSnapshotException
          44    86    89   Class org/apache/hadoop/hbase/snapshot/CorruptedSnapshotException
           5    30   108   any
          43    95   108   any
         108   110   108   any

  public void testReadSnapshotRegionManifest() throws java.io.IOException;
    Code:
       0: aload_0
       1: getfield      #12                 // Field fs:Lorg/apache/hadoop/fs/FileSystem;
       4: new           #37                 // class org/apache/hadoop/fs/Path
       7: dup
       8: aload_0
       9: getfield      #21                 // Field snapshotDir:Lorg/apache/hadoop/fs/Path;
      12: ldc           #38                 // String data.manifest
      14: invokespecial #39                 // Method org/apache/hadoop/fs/Path."<init>":(Lorg/apache/hadoop/fs/Path;Ljava/lang/String;)V
      17: iconst_1
      18: invokevirtual #24                 // Method org/apache/hadoop/fs/FileSystem.delete:(Lorg/apache/hadoop/fs/Path;Z)Z
      21: pop
      22: aload_0
      23: invokespecial #40                 // Method createRegionManifest:()Lorg/apache/hadoop/fs/Path;
      26: astore_1
      27: aload_0
      28: getfield      #14                 // Field conf:Lorg/apache/hadoop/conf/Configuration;
      31: ldc           #31                 // String snapshot.manifest.size.limit
      33: ldc           #32                 // int 134217728
      35: invokevirtual #33                 // Method org/apache/hadoop/conf/Configuration.setInt:(Ljava/lang/String;I)V
      38: aload_0
      39: getfield      #14                 // Field conf:Lorg/apache/hadoop/conf/Configuration;
      42: aload_0
      43: getfield      #12                 // Field fs:Lorg/apache/hadoop/fs/FileSystem;
      46: aload_0
      47: getfield      #21                 // Field snapshotDir:Lorg/apache/hadoop/fs/Path;
      50: aload_0
      51: getfield      #23                 // Field snapshotDesc:Lorg/apache/hadoop/hbase/shaded/protobuf/generated/SnapshotProtos$SnapshotDescription;
      54: invokestatic  #26                 // Method org/apache/hadoop/hbase/snapshot/SnapshotManifest.open:(Lorg/apache/hadoop/conf/Configuration;Lorg/apache/hadoop/fs/FileSystem;Lorg/apache/hadoop/fs/Path;Lorg/apache/hadoop/hbase/shaded/protobuf/generated/SnapshotProtos$SnapshotDescription;)Lorg/apache/hadoop/hbase/snapshot/SnapshotManifest;
      57: pop
      58: aload_0
      59: getfield      #12                 // Field fs:Lorg/apache/hadoop/fs/FileSystem;
      62: aload_1
      63: iconst_0
      64: invokevirtual #24                 // Method org/apache/hadoop/fs/FileSystem.delete:(Lorg/apache/hadoop/fs/Path;Z)Z
      67: pop
      68: goto          103
      71: astore_2
      72: ldc           #41                 // String fail to test snapshot manifest because region message size is too small.
      74: invokestatic  #28                 // Method org/junit/Assert.fail:(Ljava/lang/String;)V
      77: aload_0
      78: getfield      #12                 // Field fs:Lorg/apache/hadoop/fs/FileSystem;
      81: aload_1
      82: iconst_0
      83: invokevirtual #24                 // Method org/apache/hadoop/fs/FileSystem.delete:(Lorg/apache/hadoop/fs/Path;Z)Z
      86: pop
      87: goto          103
      90: astore_3
      91: aload_0
      92: getfield      #12                 // Field fs:Lorg/apache/hadoop/fs/FileSystem;
      95: aload_1
      96: iconst_0
      97: invokevirtual #24                 // Method org/apache/hadoop/fs/FileSystem.delete:(Lorg/apache/hadoop/fs/Path;Z)Z
     100: pop
     101: aload_3
     102: athrow
     103: return
    Exception table:
       from    to  target type
          27    58    71   Class org/apache/hadoop/hbase/snapshot/CorruptedSnapshotException
          27    58    90   any
          71    77    90   any

  static {};
    Code:
       0: ldc           #7                  // class org/apache/hadoop/hbase/snapshot/TestSnapshotManifest
       2: invokestatic  #89                 // Method org/apache/hadoop/hbase/HBaseClassTestRule.forClass:(Ljava/lang/Class;)Lorg/apache/hadoop/hbase/HBaseClassTestRule;
       5: putstatic     #90                 // Field CLASS_RULE:Lorg/apache/hadoop/hbase/HBaseClassTestRule;
       8: ldc           #8                  // String testSnapshotManifest
      10: invokestatic  #91                 // Method org/apache/hadoop/hbase/TableName.valueOf:(Ljava/lang/String;)Lorg/apache/hadoop/hbase/TableName;
      13: putstatic     #49                 // Field TABLE_NAME:Lorg/apache/hadoop/hbase/TableName;
      16: return
}
