Compiled from "TestAssignmentManagerBase.java"
public class org.apache.hadoop.hbase.master.assignment.TestAssignmentManagerBase$RandRsExecutor extends org.apache.hadoop.hbase.master.assignment.TestAssignmentManagerBase$NoopRsExecutor {
  final org.apache.hadoop.hbase.master.assignment.TestAssignmentManagerBase this$0;

  protected org.apache.hadoop.hbase.master.assignment.TestAssignmentManagerBase$RandRsExecutor(org.apache.hadoop.hbase.master.assignment.TestAssignmentManagerBase);
    Code:
       0: aload_0
       1: aload_1
       2: putfield      #1                  // Field this$0:Lorg/apache/hadoop/hbase/master/assignment/TestAssignmentManagerBase;
       5: aload_0
       6: aload_1
       7: invokespecial #2                  // Method org/apache/hadoop/hbase/master/assignment/TestAssignmentManagerBase$NoopRsExecutor."<init>":(Lorg/apache/hadoop/hbase/master/assignment/TestAssignmentManagerBase;)V
      10: aload_0
      11: new           #3                  // class java/util/Random
      14: dup
      15: invokespecial #4                  // Method java/util/Random."<init>":()V
      18: putfield      #5                  // Field rand:Ljava/util/Random;
      21: return

  public org.apache.hadoop.hbase.shaded.protobuf.generated.AdminProtos$ExecuteProceduresResponse sendRequest(org.apache.hadoop.hbase.ServerName, org.apache.hadoop.hbase.shaded.protobuf.generated.AdminProtos$ExecuteProceduresRequest) throws java.io.IOException;
    Code:
       0: aload_0
       1: getfield      #5                  // Field rand:Ljava/util/Random;
       4: iconst_5
       5: invokevirtual #6                  // Method java/util/Random.nextInt:(I)I
       8: tableswitch   { // 0 to 2
                     0: 36
                     1: 46
                     2: 56
               default: 68
          }
      36: new           #7                  // class org/apache/hadoop/hbase/ipc/ServerNotRunningYetException
      39: dup
      40: ldc           #8                  // String wait on server startup
      42: invokespecial #9                  // Method org/apache/hadoop/hbase/ipc/ServerNotRunningYetException."<init>":(Ljava/lang/String;)V
      45: athrow
      46: new           #10                 // class java/net/SocketTimeoutException
      49: dup
      50: ldc           #11                 // String simulate socket timeout
      52: invokespecial #12                 // Method java/net/SocketTimeoutException."<init>":(Ljava/lang/String;)V
      55: athrow
      56: new           #13                 // class org/apache/hadoop/ipc/RemoteException
      59: dup
      60: ldc           #14                 // String java.io.IOException
      62: ldc           #15                 // String unexpected exception
      64: invokespecial #16                 // Method org/apache/hadoop/ipc/RemoteException."<init>":(Ljava/lang/String;Ljava/lang/String;)V
      67: athrow
      68: aload_0
      69: aload_1
      70: aload_2
      71: invokespecial #17                 // Method org/apache/hadoop/hbase/master/assignment/TestAssignmentManagerBase$NoopRsExecutor.sendRequest:(Lorg/apache/hadoop/hbase/ServerName;Lorg/apache/hadoop/hbase/shaded/protobuf/generated/AdminProtos$ExecuteProceduresRequest;)Lorg/apache/hadoop/hbase/shaded/protobuf/generated/AdminProtos$ExecuteProceduresResponse;
      74: areturn

  protected org.apache.hadoop.hbase.shaded.protobuf.generated.AdminProtos$OpenRegionResponse$RegionOpeningState execOpenRegion(org.apache.hadoop.hbase.ServerName, org.apache.hadoop.hbase.shaded.protobuf.generated.AdminProtos$OpenRegionRequest$RegionOpenInfo) throws java.io.IOException;
    Code:
       0: aload_2
       1: invokevirtual #18                 // Method org/apache/hadoop/hbase/shaded/protobuf/generated/AdminProtos$OpenRegionRequest$RegionOpenInfo.getRegion:()Lorg/apache/hadoop/hbase/shaded/protobuf/generated/HBaseProtos$RegionInfo;
       4: invokestatic  #19                 // Method org/apache/hadoop/hbase/shaded/protobuf/ProtobufUtil.toRegionInfo:(Lorg/apache/hadoop/hbase/shaded/protobuf/generated/HBaseProtos$RegionInfo;)Lorg/apache/hadoop/hbase/client/RegionInfo;
       7: astore_3
       8: aload_0
       9: getfield      #1                  // Field this$0:Lorg/apache/hadoop/hbase/master/assignment/TestAssignmentManagerBase;
      12: getfield      #20                 // Field org/apache/hadoop/hbase/master/assignment/TestAssignmentManagerBase.am:Lorg/apache/hadoop/hbase/master/assignment/AssignmentManager;
      15: invokevirtual #21                 // Method org/apache/hadoop/hbase/master/assignment/AssignmentManager.getRegionStates:()Lorg/apache/hadoop/hbase/master/assignment/RegionStates;
      18: aload_3
      19: invokevirtual #22                 // Method org/apache/hadoop/hbase/master/assignment/RegionStates.getOrCreateRegionStateNode:(Lorg/apache/hadoop/hbase/client/RegionInfo;)Lorg/apache/hadoop/hbase/master/assignment/RegionStateNode;
      22: invokevirtual #23                 // Method org/apache/hadoop/hbase/master/assignment/RegionStateNode.getOpenSeqNum:()J
      25: lstore        4
      27: aload_0
      28: getfield      #5                  // Field rand:Ljava/util/Random;
      31: iconst_3
      32: invokevirtual #6                  // Method java/util/Random.nextInt:(I)I
      35: lookupswitch  { // 2
                     0: 60
                     1: 95
               default: 127
          }
      60: invokestatic  #24                 // Method org/apache/hadoop/hbase/master/assignment/TestAssignmentManagerBase.access$000:()Lorg/slf4j/Logger;
      63: ldc           #25                 // String Return OPENED response
      65: invokeinterface #26,  2           // InterfaceMethod org/slf4j/Logger.info:(Ljava/lang/String;)V
      70: aload_0
      71: getfield      #1                  // Field this$0:Lorg/apache/hadoop/hbase/master/assignment/TestAssignmentManagerBase;
      74: aload_1
      75: aload_2
      76: invokevirtual #18                 // Method org/apache/hadoop/hbase/shaded/protobuf/generated/AdminProtos$OpenRegionRequest$RegionOpenInfo.getRegion:()Lorg/apache/hadoop/hbase/shaded/protobuf/generated/HBaseProtos$RegionInfo;
      79: getstatic     #27                 // Field org/apache/hadoop/hbase/shaded/protobuf/generated/RegionServerStatusProtos$RegionStateTransition$TransitionCode.OPENED:Lorg/apache/hadoop/hbase/shaded/protobuf/generated/RegionServerStatusProtos$RegionStateTransition$TransitionCode;
      82: lload         4
      84: ldc2_w        #28                 // long 2l
      87: ladd
      88: invokevirtual #30                 // Method org/apache/hadoop/hbase/master/assignment/TestAssignmentManagerBase.sendTransitionReport:(Lorg/apache/hadoop/hbase/ServerName;Lorg/apache/hadoop/hbase/shaded/protobuf/generated/HBaseProtos$RegionInfo;Lorg/apache/hadoop/hbase/shaded/protobuf/generated/RegionServerStatusProtos$RegionStateTransition$TransitionCode;J)V
      91: getstatic     #31                 // Field org/apache/hadoop/hbase/shaded/protobuf/generated/AdminProtos$OpenRegionResponse$RegionOpeningState.OPENED:Lorg/apache/hadoop/hbase/shaded/protobuf/generated/AdminProtos$OpenRegionResponse$RegionOpeningState;
      94: areturn
      95: invokestatic  #24                 // Method org/apache/hadoop/hbase/master/assignment/TestAssignmentManagerBase.access$000:()Lorg/slf4j/Logger;
      98: ldc           #32                 // String Return transition report that FAILED_OPEN/FAILED_OPENING response
     100: invokeinterface #26,  2           // InterfaceMethod org/slf4j/Logger.info:(Ljava/lang/String;)V
     105: aload_0
     106: getfield      #1                  // Field this$0:Lorg/apache/hadoop/hbase/master/assignment/TestAssignmentManagerBase;
     109: aload_1
     110: aload_2
     111: invokevirtual #18                 // Method org/apache/hadoop/hbase/shaded/protobuf/generated/AdminProtos$OpenRegionRequest$RegionOpenInfo.getRegion:()Lorg/apache/hadoop/hbase/shaded/protobuf/generated/HBaseProtos$RegionInfo;
     114: getstatic     #33                 // Field org/apache/hadoop/hbase/shaded/protobuf/generated/RegionServerStatusProtos$RegionStateTransition$TransitionCode.FAILED_OPEN:Lorg/apache/hadoop/hbase/shaded/protobuf/generated/RegionServerStatusProtos$RegionStateTransition$TransitionCode;
     117: ldc2_w        #34                 // long -1l
     120: invokevirtual #30                 // Method org/apache/hadoop/hbase/master/assignment/TestAssignmentManagerBase.sendTransitionReport:(Lorg/apache/hadoop/hbase/ServerName;Lorg/apache/hadoop/hbase/shaded/protobuf/generated/HBaseProtos$RegionInfo;Lorg/apache/hadoop/hbase/shaded/protobuf/generated/RegionServerStatusProtos$RegionStateTransition$TransitionCode;J)V
     123: getstatic     #36                 // Field org/apache/hadoop/hbase/shaded/protobuf/generated/AdminProtos$OpenRegionResponse$RegionOpeningState.FAILED_OPENING:Lorg/apache/hadoop/hbase/shaded/protobuf/generated/AdminProtos$OpenRegionResponse$RegionOpeningState;
     126: areturn
     127: invokestatic  #24                 // Method org/apache/hadoop/hbase/master/assignment/TestAssignmentManagerBase.access$000:()Lorg/slf4j/Logger;
     130: ldc           #37                 // String Return null as response; means proc stuck so we send in a crash report after a few seconds...
     132: invokeinterface #26,  2           // InterfaceMethod org/slf4j/Logger.info:(Ljava/lang/String;)V
     137: aload_0
     138: getfield      #1                  // Field this$0:Lorg/apache/hadoop/hbase/master/assignment/TestAssignmentManagerBase;
     141: getfield      #38                 // Field org/apache/hadoop/hbase/master/assignment/TestAssignmentManagerBase.executor:Ljava/util/concurrent/ScheduledExecutorService;
     144: new           #39                 // class org/apache/hadoop/hbase/master/assignment/TestAssignmentManagerBase$RandRsExecutor$1
     147: dup
     148: aload_0
     149: aload_1
     150: invokespecial #40                 // Method org/apache/hadoop/hbase/master/assignment/TestAssignmentManagerBase$RandRsExecutor$1."<init>":(Lorg/apache/hadoop/hbase/master/assignment/TestAssignmentManagerBase$RandRsExecutor;Lorg/apache/hadoop/hbase/ServerName;)V
     153: ldc2_w        #41                 // long 5l
     156: getstatic     #43                 // Field java/util/concurrent/TimeUnit.SECONDS:Ljava/util/concurrent/TimeUnit;
     159: invokeinterface #44,  5           // InterfaceMethod java/util/concurrent/ScheduledExecutorService.schedule:(Ljava/lang/Runnable;JLjava/util/concurrent/TimeUnit;)Ljava/util/concurrent/ScheduledFuture;
     164: pop
     165: aconst_null
     166: areturn

  protected org.apache.hadoop.hbase.shaded.protobuf.generated.AdminProtos$CloseRegionResponse execCloseRegion(org.apache.hadoop.hbase.ServerName, byte[]) throws java.io.IOException;
    Code:
       0: invokestatic  #45                 // Method org/apache/hadoop/hbase/shaded/protobuf/generated/AdminProtos$CloseRegionResponse.newBuilder:()Lorg/apache/hadoop/hbase/shaded/protobuf/generated/AdminProtos$CloseRegionResponse$Builder;
       3: astore_3
       4: aload_0
       5: getfield      #5                  // Field rand:Ljava/util/Random;
       8: invokevirtual #46                 // Method java/util/Random.nextBoolean:()Z
      11: istore        4
      13: iload         4
      15: ifeq          50
      18: aload_0
      19: getfield      #1                  // Field this$0:Lorg/apache/hadoop/hbase/master/assignment/TestAssignmentManagerBase;
      22: getfield      #20                 // Field org/apache/hadoop/hbase/master/assignment/TestAssignmentManagerBase.am:Lorg/apache/hadoop/hbase/master/assignment/AssignmentManager;
      25: aload_2
      26: invokevirtual #47                 // Method org/apache/hadoop/hbase/master/assignment/AssignmentManager.getRegionInfo:([B)Lorg/apache/hadoop/hbase/client/RegionInfo;
      29: astore        5
      31: aload_0
      32: getfield      #1                  // Field this$0:Lorg/apache/hadoop/hbase/master/assignment/TestAssignmentManagerBase;
      35: aload_1
      36: aload         5
      38: invokestatic  #48                 // Method org/apache/hadoop/hbase/shaded/protobuf/ProtobufUtil.toRegionInfo:(Lorg/apache/hadoop/hbase/client/RegionInfo;)Lorg/apache/hadoop/hbase/shaded/protobuf/generated/HBaseProtos$RegionInfo;
      41: getstatic     #49                 // Field org/apache/hadoop/hbase/shaded/protobuf/generated/RegionServerStatusProtos$RegionStateTransition$TransitionCode.CLOSED:Lorg/apache/hadoop/hbase/shaded/protobuf/generated/RegionServerStatusProtos$RegionStateTransition$TransitionCode;
      44: ldc2_w        #34                 // long -1l
      47: invokevirtual #30                 // Method org/apache/hadoop/hbase/master/assignment/TestAssignmentManagerBase.sendTransitionReport:(Lorg/apache/hadoop/hbase/ServerName;Lorg/apache/hadoop/hbase/shaded/protobuf/generated/HBaseProtos$RegionInfo;Lorg/apache/hadoop/hbase/shaded/protobuf/generated/RegionServerStatusProtos$RegionStateTransition$TransitionCode;J)V
      50: aload_3
      51: iload         4
      53: invokevirtual #50                 // Method org/apache/hadoop/hbase/shaded/protobuf/generated/AdminProtos$CloseRegionResponse$Builder.setClosed:(Z)Lorg/apache/hadoop/hbase/shaded/protobuf/generated/AdminProtos$CloseRegionResponse$Builder;
      56: pop
      57: aload_3
      58: invokevirtual #51                 // Method org/apache/hadoop/hbase/shaded/protobuf/generated/AdminProtos$CloseRegionResponse$Builder.build:()Lorg/apache/hadoop/hbase/shaded/protobuf/generated/AdminProtos$CloseRegionResponse;
      61: areturn
}
