Compiled from "TestVisibilityLabelsWithACL.java"
public class org.apache.hadoop.hbase.security.visibility.TestVisibilityLabelsWithACL {
  public static final org.apache.hadoop.hbase.HBaseClassTestRule CLASS_RULE;

  public final org.junit.rules.TestName TEST_NAME;

  public org.apache.hadoop.hbase.security.visibility.TestVisibilityLabelsWithACL();
    Code:
       0: aload_0
       1: invokespecial #3                  // Method java/lang/Object."<init>":()V
       4: aload_0
       5: new           #4                  // class org/junit/rules/TestName
       8: dup
       9: invokespecial #5                  // Method org/junit/rules/TestName."<init>":()V
      12: putfield      #6                  // Field TEST_NAME:Lorg/junit/rules/TestName;
      15: return

  public static void setupBeforeClass() throws java.lang.Exception;
    Code:
       0: getstatic     #7                  // Field TEST_UTIL:Lorg/apache/hadoop/hbase/HBaseTestingUtility;
       3: invokevirtual #8                  // Method org/apache/hadoop/hbase/HBaseTestingUtility.getConfiguration:()Lorg/apache/hadoop/conf/Configuration;
       6: putstatic     #2                  // Field conf:Lorg/apache/hadoop/conf/Configuration;
       9: getstatic     #2                  // Field conf:Lorg/apache/hadoop/conf/Configuration;
      12: invokestatic  #9                  // Method org/apache/hadoop/hbase/security/access/SecureTestUtil.enableSecurity:(Lorg/apache/hadoop/conf/Configuration;)V
      15: getstatic     #2                  // Field conf:Lorg/apache/hadoop/conf/Configuration;
      18: ldc           #10                 // String hbase.coprocessor.master.classes
      20: new           #11                 // class java/lang/StringBuilder
      23: dup
      24: invokespecial #12                 // Method java/lang/StringBuilder."<init>":()V
      27: ldc           #13                 // class org/apache/hadoop/hbase/security/access/AccessController
      29: invokevirtual #14                 // Method java/lang/Class.getName:()Ljava/lang/String;
      32: invokevirtual #15                 // Method java/lang/StringBuilder.append:(Ljava/lang/String;)Ljava/lang/StringBuilder;
      35: ldc           #16                 // String ,
      37: invokevirtual #15                 // Method java/lang/StringBuilder.append:(Ljava/lang/String;)Ljava/lang/StringBuilder;
      40: ldc           #17                 // class org/apache/hadoop/hbase/security/visibility/VisibilityController
      42: invokevirtual #14                 // Method java/lang/Class.getName:()Ljava/lang/String;
      45: invokevirtual #15                 // Method java/lang/StringBuilder.append:(Ljava/lang/String;)Ljava/lang/StringBuilder;
      48: invokevirtual #18                 // Method java/lang/StringBuilder.toString:()Ljava/lang/String;
      51: invokevirtual #19                 // Method org/apache/hadoop/conf/Configuration.set:(Ljava/lang/String;Ljava/lang/String;)V
      54: getstatic     #2                  // Field conf:Lorg/apache/hadoop/conf/Configuration;
      57: ldc           #20                 // String hbase.coprocessor.region.classes
      59: new           #11                 // class java/lang/StringBuilder
      62: dup
      63: invokespecial #12                 // Method java/lang/StringBuilder."<init>":()V
      66: ldc           #13                 // class org/apache/hadoop/hbase/security/access/AccessController
      68: invokevirtual #14                 // Method java/lang/Class.getName:()Ljava/lang/String;
      71: invokevirtual #15                 // Method java/lang/StringBuilder.append:(Ljava/lang/String;)Ljava/lang/StringBuilder;
      74: ldc           #16                 // String ,
      76: invokevirtual #15                 // Method java/lang/StringBuilder.append:(Ljava/lang/String;)Ljava/lang/StringBuilder;
      79: ldc           #17                 // class org/apache/hadoop/hbase/security/visibility/VisibilityController
      81: invokevirtual #14                 // Method java/lang/Class.getName:()Ljava/lang/String;
      84: invokevirtual #15                 // Method java/lang/StringBuilder.append:(Ljava/lang/String;)Ljava/lang/StringBuilder;
      87: invokevirtual #18                 // Method java/lang/StringBuilder.toString:()Ljava/lang/String;
      90: invokevirtual #19                 // Method org/apache/hadoop/conf/Configuration.set:(Ljava/lang/String;Ljava/lang/String;)V
      93: getstatic     #7                  // Field TEST_UTIL:Lorg/apache/hadoop/hbase/HBaseTestingUtility;
      96: iconst_2
      97: invokevirtual #21                 // Method org/apache/hadoop/hbase/HBaseTestingUtility.startMiniCluster:(I)Lorg/apache/hadoop/hbase/MiniHBaseCluster;
     100: pop
     101: getstatic     #7                  // Field TEST_UTIL:Lorg/apache/hadoop/hbase/HBaseTestingUtility;
     104: getstatic     #22                 // Field org/apache/hadoop/hbase/security/access/PermissionStorage.ACL_TABLE_NAME:Lorg/apache/hadoop/hbase/TableName;
     107: invokevirtual #23                 // Method org/apache/hadoop/hbase/TableName.getName:()[B
     110: ldc2_w        #24                 // long 50000l
     113: invokevirtual #26                 // Method org/apache/hadoop/hbase/HBaseTestingUtility.waitTableEnabled:([BJ)V
     116: getstatic     #7                  // Field TEST_UTIL:Lorg/apache/hadoop/hbase/HBaseTestingUtility;
     119: getstatic     #27                 // Field org/apache/hadoop/hbase/security/visibility/VisibilityConstants.LABELS_TABLE_NAME:Lorg/apache/hadoop/hbase/TableName;
     122: invokevirtual #23                 // Method org/apache/hadoop/hbase/TableName.getName:()[B
     125: ldc2_w        #24                 // long 50000l
     128: invokevirtual #26                 // Method org/apache/hadoop/hbase/HBaseTestingUtility.waitTableEnabled:([BJ)V
     131: invokestatic  #28                 // Method addLabels:()V
     134: getstatic     #2                  // Field conf:Lorg/apache/hadoop/conf/Configuration;
     137: ldc           #29                 // String admin
     139: iconst_1
     140: anewarray     #30                 // class java/lang/String
     143: dup
     144: iconst_0
     145: ldc           #31                 // String supergroup
     147: aastore
     148: invokestatic  #32                 // Method org/apache/hadoop/hbase/security/User.createUserForTesting:(Lorg/apache/hadoop/conf/Configuration;Ljava/lang/String;[Ljava/lang/String;)Lorg/apache/hadoop/hbase/security/User;
     151: putstatic     #33                 // Field SUPERUSER:Lorg/apache/hadoop/hbase/security/User;
     154: getstatic     #2                  // Field conf:Lorg/apache/hadoop/conf/Configuration;
     157: ldc           #34                 // String user1
     159: iconst_0
     160: anewarray     #30                 // class java/lang/String
     163: invokestatic  #32                 // Method org/apache/hadoop/hbase/security/User.createUserForTesting:(Lorg/apache/hadoop/conf/Configuration;Ljava/lang/String;[Ljava/lang/String;)Lorg/apache/hadoop/hbase/security/User;
     166: putstatic     #35                 // Field NORMAL_USER1:Lorg/apache/hadoop/hbase/security/User;
     169: getstatic     #2                  // Field conf:Lorg/apache/hadoop/conf/Configuration;
     172: ldc           #36                 // String user2
     174: iconst_0
     175: anewarray     #30                 // class java/lang/String
     178: invokestatic  #32                 // Method org/apache/hadoop/hbase/security/User.createUserForTesting:(Lorg/apache/hadoop/conf/Configuration;Ljava/lang/String;[Ljava/lang/String;)Lorg/apache/hadoop/hbase/security/User;
     181: putstatic     #37                 // Field NORMAL_USER2:Lorg/apache/hadoop/hbase/security/User;
     184: getstatic     #7                  // Field TEST_UTIL:Lorg/apache/hadoop/hbase/HBaseTestingUtility;
     187: getstatic     #35                 // Field NORMAL_USER1:Lorg/apache/hadoop/hbase/security/User;
     190: invokevirtual #38                 // Method org/apache/hadoop/hbase/security/User.getShortName:()Ljava/lang/String;
     193: getstatic     #27                 // Field org/apache/hadoop/hbase/security/visibility/VisibilityConstants.LABELS_TABLE_NAME:Lorg/apache/hadoop/hbase/TableName;
     196: aconst_null
     197: aconst_null
     198: iconst_1
     199: anewarray     #39                 // class org/apache/hadoop/hbase/security/access/Permission$Action
     202: dup
     203: iconst_0
     204: getstatic     #40                 // Field org/apache/hadoop/hbase/security/access/Permission$Action.EXEC:Lorg/apache/hadoop/hbase/security/access/Permission$Action;
     207: aastore
     208: invokestatic  #41                 // Method org/apache/hadoop/hbase/security/access/SecureTestUtil.grantOnTable:(Lorg/apache/hadoop/hbase/HBaseTestingUtility;Ljava/lang/String;Lorg/apache/hadoop/hbase/TableName;[B[B[Lorg/apache/hadoop/hbase/security/access/Permission$Action;)V
     211: getstatic     #7                  // Field TEST_UTIL:Lorg/apache/hadoop/hbase/HBaseTestingUtility;
     214: getstatic     #37                 // Field NORMAL_USER2:Lorg/apache/hadoop/hbase/security/User;
     217: invokevirtual #38                 // Method org/apache/hadoop/hbase/security/User.getShortName:()Ljava/lang/String;
     220: getstatic     #27                 // Field org/apache/hadoop/hbase/security/visibility/VisibilityConstants.LABELS_TABLE_NAME:Lorg/apache/hadoop/hbase/TableName;
     223: aconst_null
     224: aconst_null
     225: iconst_1
     226: anewarray     #39                 // class org/apache/hadoop/hbase/security/access/Permission$Action
     229: dup
     230: iconst_0
     231: getstatic     #40                 // Field org/apache/hadoop/hbase/security/access/Permission$Action.EXEC:Lorg/apache/hadoop/hbase/security/access/Permission$Action;
     234: aastore
     235: invokestatic  #41                 // Method org/apache/hadoop/hbase/security/access/SecureTestUtil.grantOnTable:(Lorg/apache/hadoop/hbase/HBaseTestingUtility;Ljava/lang/String;Lorg/apache/hadoop/hbase/TableName;[B[B[Lorg/apache/hadoop/hbase/security/access/Permission$Action;)V
     238: return

  public static void tearDownAfterClass() throws java.lang.Exception;
    Code:
       0: getstatic     #7                  // Field TEST_UTIL:Lorg/apache/hadoop/hbase/HBaseTestingUtility;
       3: invokevirtual #42                 // Method org/apache/hadoop/hbase/HBaseTestingUtility.shutdownMiniCluster:()V
       6: return

  public void testScanForUserWithFewerLabelAuthsThanLabelsInScanAuthorizations() throws java.lang.Throwable;
    Code:
       0: iconst_1
       1: anewarray     #30                 // class java/lang/String
       4: dup
       5: iconst_0
       6: ldc           #44                 // String secret
       8: aastore
       9: astore_1
      10: ldc           #36                 // String user2
      12: astore_2
      13: getstatic     #7                  // Field TEST_UTIL:Lorg/apache/hadoop/hbase/HBaseTestingUtility;
      16: invokevirtual #45                 // Method org/apache/hadoop/hbase/HBaseTestingUtility.getConnection:()Lorg/apache/hadoop/hbase/client/Connection;
      19: aload_1
      20: aload_2
      21: invokestatic  #46                 // Method org/apache/hadoop/hbase/security/visibility/VisibilityClient.setAuths:(Lorg/apache/hadoop/hbase/client/Connection;[Ljava/lang/String;Ljava/lang/String;)Lorg/apache/hadoop/hbase/protobuf/generated/VisibilityLabelsProtos$VisibilityLabelsResponse;
      24: pop
      25: aload_0
      26: getfield      #6                  // Field TEST_NAME:Lorg/junit/rules/TestName;
      29: invokevirtual #47                 // Method org/junit/rules/TestName.getMethodName:()Ljava/lang/String;
      32: invokestatic  #48                 // Method org/apache/hadoop/hbase/TableName.valueOf:(Ljava/lang/String;)Lorg/apache/hadoop/hbase/TableName;
      35: astore_3
      36: aload_3
      37: iconst_2
      38: anewarray     #30                 // class java/lang/String
      41: dup
      42: iconst_0
      43: ldc           #49                 // String secret&confidential&!private
      45: aastore
      46: dup
      47: iconst_1
      48: ldc           #50                 // String secret&!private
      50: aastore
      51: invokestatic  #51                 // Method createTableAndWriteDataWithLabels:(Lorg/apache/hadoop/hbase/TableName;[Ljava/lang/String;)Lorg/apache/hadoop/hbase/client/Table;
      54: astore        4
      56: getstatic     #7                  // Field TEST_UTIL:Lorg/apache/hadoop/hbase/HBaseTestingUtility;
      59: getstatic     #37                 // Field NORMAL_USER2:Lorg/apache/hadoop/hbase/security/User;
      62: invokevirtual #38                 // Method org/apache/hadoop/hbase/security/User.getShortName:()Ljava/lang/String;
      65: aload_3
      66: aconst_null
      67: aconst_null
      68: iconst_1
      69: anewarray     #39                 // class org/apache/hadoop/hbase/security/access/Permission$Action
      72: dup
      73: iconst_0
      74: getstatic     #52                 // Field org/apache/hadoop/hbase/security/access/Permission$Action.READ:Lorg/apache/hadoop/hbase/security/access/Permission$Action;
      77: aastore
      78: invokestatic  #41                 // Method org/apache/hadoop/hbase/security/access/SecureTestUtil.grantOnTable:(Lorg/apache/hadoop/hbase/HBaseTestingUtility;Ljava/lang/String;Lorg/apache/hadoop/hbase/TableName;[B[B[Lorg/apache/hadoop/hbase/security/access/Permission$Action;)V
      81: new           #53                 // class org/apache/hadoop/hbase/security/visibility/TestVisibilityLabelsWithACL$1
      84: dup
      85: aload_0
      86: aload         4
      88: invokespecial #54                 // Method org/apache/hadoop/hbase/security/visibility/TestVisibilityLabelsWithACL$1."<init>":(Lorg/apache/hadoop/hbase/security/visibility/TestVisibilityLabelsWithACL;Lorg/apache/hadoop/hbase/client/Table;)V
      91: astore        5
      93: getstatic     #37                 // Field NORMAL_USER2:Lorg/apache/hadoop/hbase/security/User;
      96: aload         5
      98: invokevirtual #55                 // Method org/apache/hadoop/hbase/security/User.runAs:(Ljava/security/PrivilegedExceptionAction;)Ljava/lang/Object;
     101: pop
     102: return

  public void testScanForSuperUserWithFewerLabelAuths() throws java.lang.Throwable;
    Code:
       0: iconst_1
       1: anewarray     #30                 // class java/lang/String
       4: dup
       5: iconst_0
       6: ldc           #44                 // String secret
       8: aastore
       9: astore_1
      10: ldc           #29                 // String admin
      12: astore_2
      13: getstatic     #2                  // Field conf:Lorg/apache/hadoop/conf/Configuration;
      16: invokestatic  #56                 // Method org/apache/hadoop/hbase/client/ConnectionFactory.createConnection:(Lorg/apache/hadoop/conf/Configuration;)Lorg/apache/hadoop/hbase/client/Connection;
      19: astore_3
      20: aconst_null
      21: astore        4
      23: aload_3
      24: aload_1
      25: aload_2
      26: invokestatic  #46                 // Method org/apache/hadoop/hbase/security/visibility/VisibilityClient.setAuths:(Lorg/apache/hadoop/hbase/client/Connection;[Ljava/lang/String;Ljava/lang/String;)Lorg/apache/hadoop/hbase/protobuf/generated/VisibilityLabelsProtos$VisibilityLabelsResponse;
      29: pop
      30: aload_3
      31: ifnull        119
      34: aload         4
      36: ifnull        60
      39: aload_3
      40: invokeinterface #57,  1           // InterfaceMethod org/apache/hadoop/hbase/client/Connection.close:()V
      45: goto          119
      48: astore        5
      50: aload         4
      52: aload         5
      54: invokevirtual #59                 // Method java/lang/Throwable.addSuppressed:(Ljava/lang/Throwable;)V
      57: goto          119
      60: aload_3
      61: invokeinterface #57,  1           // InterfaceMethod org/apache/hadoop/hbase/client/Connection.close:()V
      66: goto          119
      69: astore        5
      71: aload         5
      73: astore        4
      75: aload         5
      77: athrow
      78: astore        6
      80: aload_3
      81: ifnull        116
      84: aload         4
      86: ifnull        110
      89: aload_3
      90: invokeinterface #57,  1           // InterfaceMethod org/apache/hadoop/hbase/client/Connection.close:()V
      95: goto          116
      98: astore        7
     100: aload         4
     102: aload         7
     104: invokevirtual #59                 // Method java/lang/Throwable.addSuppressed:(Ljava/lang/Throwable;)V
     107: goto          116
     110: aload_3
     111: invokeinterface #57,  1           // InterfaceMethod org/apache/hadoop/hbase/client/Connection.close:()V
     116: aload         6
     118: athrow
     119: aload_0
     120: getfield      #6                  // Field TEST_NAME:Lorg/junit/rules/TestName;
     123: invokevirtual #47                 // Method org/junit/rules/TestName.getMethodName:()Ljava/lang/String;
     126: invokestatic  #48                 // Method org/apache/hadoop/hbase/TableName.valueOf:(Ljava/lang/String;)Lorg/apache/hadoop/hbase/TableName;
     129: astore_3
     130: aload_3
     131: iconst_2
     132: anewarray     #30                 // class java/lang/String
     135: dup
     136: iconst_0
     137: ldc           #49                 // String secret&confidential&!private
     139: aastore
     140: dup
     141: iconst_1
     142: ldc           #50                 // String secret&!private
     144: aastore
     145: invokestatic  #51                 // Method createTableAndWriteDataWithLabels:(Lorg/apache/hadoop/hbase/TableName;[Ljava/lang/String;)Lorg/apache/hadoop/hbase/client/Table;
     148: astore        4
     150: new           #60                 // class org/apache/hadoop/hbase/security/visibility/TestVisibilityLabelsWithACL$2
     153: dup
     154: aload_0
     155: aload         4
     157: invokespecial #61                 // Method org/apache/hadoop/hbase/security/visibility/TestVisibilityLabelsWithACL$2."<init>":(Lorg/apache/hadoop/hbase/security/visibility/TestVisibilityLabelsWithACL;Lorg/apache/hadoop/hbase/client/Table;)V
     160: astore        5
     162: getstatic     #33                 // Field SUPERUSER:Lorg/apache/hadoop/hbase/security/User;
     165: aload         5
     167: invokevirtual #55                 // Method org/apache/hadoop/hbase/security/User.runAs:(Ljava/security/PrivilegedExceptionAction;)Ljava/lang/Object;
     170: pop
     171: return
    Exception table:
       from    to  target type
          39    45    48   Class java/lang/Throwable
          23    30    69   Class java/lang/Throwable
          23    30    78   any
          89    95    98   Class java/lang/Throwable
          69    80    78   any

  public void testGetForSuperUserWithFewerLabelAuths() throws java.lang.Throwable;
    Code:
       0: iconst_1
       1: anewarray     #30                 // class java/lang/String
       4: dup
       5: iconst_0
       6: ldc           #44                 // String secret
       8: aastore
       9: astore_1
      10: ldc           #29                 // String admin
      12: astore_2
      13: getstatic     #7                  // Field TEST_UTIL:Lorg/apache/hadoop/hbase/HBaseTestingUtility;
      16: invokevirtual #45                 // Method org/apache/hadoop/hbase/HBaseTestingUtility.getConnection:()Lorg/apache/hadoop/hbase/client/Connection;
      19: aload_1
      20: aload_2
      21: invokestatic  #46                 // Method org/apache/hadoop/hbase/security/visibility/VisibilityClient.setAuths:(Lorg/apache/hadoop/hbase/client/Connection;[Ljava/lang/String;Ljava/lang/String;)Lorg/apache/hadoop/hbase/protobuf/generated/VisibilityLabelsProtos$VisibilityLabelsResponse;
      24: pop
      25: aload_0
      26: getfield      #6                  // Field TEST_NAME:Lorg/junit/rules/TestName;
      29: invokevirtual #47                 // Method org/junit/rules/TestName.getMethodName:()Ljava/lang/String;
      32: invokestatic  #48                 // Method org/apache/hadoop/hbase/TableName.valueOf:(Ljava/lang/String;)Lorg/apache/hadoop/hbase/TableName;
      35: astore_3
      36: aload_3
      37: iconst_2
      38: anewarray     #30                 // class java/lang/String
      41: dup
      42: iconst_0
      43: ldc           #49                 // String secret&confidential&!private
      45: aastore
      46: dup
      47: iconst_1
      48: ldc           #50                 // String secret&!private
      50: aastore
      51: invokestatic  #51                 // Method createTableAndWriteDataWithLabels:(Lorg/apache/hadoop/hbase/TableName;[Ljava/lang/String;)Lorg/apache/hadoop/hbase/client/Table;
      54: astore        4
      56: new           #62                 // class org/apache/hadoop/hbase/security/visibility/TestVisibilityLabelsWithACL$3
      59: dup
      60: aload_0
      61: aload         4
      63: invokespecial #63                 // Method org/apache/hadoop/hbase/security/visibility/TestVisibilityLabelsWithACL$3."<init>":(Lorg/apache/hadoop/hbase/security/visibility/TestVisibilityLabelsWithACL;Lorg/apache/hadoop/hbase/client/Table;)V
      66: astore        5
      68: getstatic     #33                 // Field SUPERUSER:Lorg/apache/hadoop/hbase/security/User;
      71: aload         5
      73: invokevirtual #55                 // Method org/apache/hadoop/hbase/security/User.runAs:(Ljava/security/PrivilegedExceptionAction;)Ljava/lang/Object;
      76: pop
      77: return

  public void testVisibilityLabelsForUserWithNoAuths() throws java.lang.Throwable;
    Code:
       0: ldc           #29                 // String admin
       2: astore_1
       3: iconst_1
       4: anewarray     #30                 // class java/lang/String
       7: dup
       8: iconst_0
       9: ldc           #44                 // String secret
      11: aastore
      12: astore_2
      13: getstatic     #2                  // Field conf:Lorg/apache/hadoop/conf/Configuration;
      16: invokestatic  #56                 // Method org/apache/hadoop/hbase/client/ConnectionFactory.createConnection:(Lorg/apache/hadoop/conf/Configuration;)Lorg/apache/hadoop/hbase/client/Connection;
      19: astore_3
      20: aconst_null
      21: astore        4
      23: aload_3
      24: aload_2
      25: aload_1
      26: invokestatic  #64                 // Method org/apache/hadoop/hbase/security/visibility/VisibilityClient.clearAuths:(Lorg/apache/hadoop/hbase/client/Connection;[Ljava/lang/String;Ljava/lang/String;)Lorg/apache/hadoop/hbase/protobuf/generated/VisibilityLabelsProtos$VisibilityLabelsResponse;
      29: pop
      30: aload_3
      31: aload_2
      32: ldc           #34                 // String user1
      34: invokestatic  #46                 // Method org/apache/hadoop/hbase/security/visibility/VisibilityClient.setAuths:(Lorg/apache/hadoop/hbase/client/Connection;[Ljava/lang/String;Ljava/lang/String;)Lorg/apache/hadoop/hbase/protobuf/generated/VisibilityLabelsProtos$VisibilityLabelsResponse;
      37: pop
      38: aload_3
      39: ifnull        127
      42: aload         4
      44: ifnull        68
      47: aload_3
      48: invokeinterface #57,  1           // InterfaceMethod org/apache/hadoop/hbase/client/Connection.close:()V
      53: goto          127
      56: astore        5
      58: aload         4
      60: aload         5
      62: invokevirtual #59                 // Method java/lang/Throwable.addSuppressed:(Ljava/lang/Throwable;)V
      65: goto          127
      68: aload_3
      69: invokeinterface #57,  1           // InterfaceMethod org/apache/hadoop/hbase/client/Connection.close:()V
      74: goto          127
      77: astore        5
      79: aload         5
      81: astore        4
      83: aload         5
      85: athrow
      86: astore        6
      88: aload_3
      89: ifnull        124
      92: aload         4
      94: ifnull        118
      97: aload_3
      98: invokeinterface #57,  1           // InterfaceMethod org/apache/hadoop/hbase/client/Connection.close:()V
     103: goto          124
     106: astore        7
     108: aload         4
     110: aload         7
     112: invokevirtual #59                 // Method java/lang/Throwable.addSuppressed:(Ljava/lang/Throwable;)V
     115: goto          124
     118: aload_3
     119: invokeinterface #57,  1           // InterfaceMethod org/apache/hadoop/hbase/client/Connection.close:()V
     124: aload         6
     126: athrow
     127: aload_0
     128: getfield      #6                  // Field TEST_NAME:Lorg/junit/rules/TestName;
     131: invokevirtual #47                 // Method org/junit/rules/TestName.getMethodName:()Ljava/lang/String;
     134: invokestatic  #48                 // Method org/apache/hadoop/hbase/TableName.valueOf:(Ljava/lang/String;)Lorg/apache/hadoop/hbase/TableName;
     137: astore_3
     138: aload_3
     139: iconst_1
     140: anewarray     #30                 // class java/lang/String
     143: dup
     144: iconst_0
     145: ldc           #44                 // String secret
     147: aastore
     148: invokestatic  #51                 // Method createTableAndWriteDataWithLabels:(Lorg/apache/hadoop/hbase/TableName;[Ljava/lang/String;)Lorg/apache/hadoop/hbase/client/Table;
     151: astore        4
     153: getstatic     #7                  // Field TEST_UTIL:Lorg/apache/hadoop/hbase/HBaseTestingUtility;
     156: getstatic     #35                 // Field NORMAL_USER1:Lorg/apache/hadoop/hbase/security/User;
     159: invokevirtual #38                 // Method org/apache/hadoop/hbase/security/User.getShortName:()Ljava/lang/String;
     162: aload_3
     163: aconst_null
     164: aconst_null
     165: iconst_1
     166: anewarray     #39                 // class org/apache/hadoop/hbase/security/access/Permission$Action
     169: dup
     170: iconst_0
     171: getstatic     #52                 // Field org/apache/hadoop/hbase/security/access/Permission$Action.READ:Lorg/apache/hadoop/hbase/security/access/Permission$Action;
     174: aastore
     175: invokestatic  #41                 // Method org/apache/hadoop/hbase/security/access/SecureTestUtil.grantOnTable:(Lorg/apache/hadoop/hbase/HBaseTestingUtility;Ljava/lang/String;Lorg/apache/hadoop/hbase/TableName;[B[B[Lorg/apache/hadoop/hbase/security/access/Permission$Action;)V
     178: getstatic     #7                  // Field TEST_UTIL:Lorg/apache/hadoop/hbase/HBaseTestingUtility;
     181: getstatic     #37                 // Field NORMAL_USER2:Lorg/apache/hadoop/hbase/security/User;
     184: invokevirtual #38                 // Method org/apache/hadoop/hbase/security/User.getShortName:()Ljava/lang/String;
     187: aload_3
     188: aconst_null
     189: aconst_null
     190: iconst_1
     191: anewarray     #39                 // class org/apache/hadoop/hbase/security/access/Permission$Action
     194: dup
     195: iconst_0
     196: getstatic     #52                 // Field org/apache/hadoop/hbase/security/access/Permission$Action.READ:Lorg/apache/hadoop/hbase/security/access/Permission$Action;
     199: aastore
     200: invokestatic  #41                 // Method org/apache/hadoop/hbase/security/access/SecureTestUtil.grantOnTable:(Lorg/apache/hadoop/hbase/HBaseTestingUtility;Ljava/lang/String;Lorg/apache/hadoop/hbase/TableName;[B[B[Lorg/apache/hadoop/hbase/security/access/Permission$Action;)V
     203: new           #65                 // class org/apache/hadoop/hbase/security/visibility/TestVisibilityLabelsWithACL$4
     206: dup
     207: aload_0
     208: aload         4
     210: invokespecial #66                 // Method org/apache/hadoop/hbase/security/visibility/TestVisibilityLabelsWithACL$4."<init>":(Lorg/apache/hadoop/hbase/security/visibility/TestVisibilityLabelsWithACL;Lorg/apache/hadoop/hbase/client/Table;)V
     213: astore        5
     215: getstatic     #37                 // Field NORMAL_USER2:Lorg/apache/hadoop/hbase/security/User;
     218: aload         5
     220: invokevirtual #55                 // Method org/apache/hadoop/hbase/security/User.runAs:(Ljava/security/PrivilegedExceptionAction;)Ljava/lang/Object;
     223: pop
     224: return
    Exception table:
       from    to  target type
          47    53    56   Class java/lang/Throwable
          23    38    77   Class java/lang/Throwable
          23    38    86   any
          97   103   106   Class java/lang/Throwable
          77    88    86   any

  public void testLabelsTableOpsWithDifferentUsers() throws java.lang.Throwable;
    Code:
       0: new           #67                 // class org/apache/hadoop/hbase/security/visibility/TestVisibilityLabelsWithACL$5
       3: dup
       4: aload_0
       5: invokespecial #68                 // Method org/apache/hadoop/hbase/security/visibility/TestVisibilityLabelsWithACL$5."<init>":(Lorg/apache/hadoop/hbase/security/visibility/TestVisibilityLabelsWithACL;)V
       8: astore_1
       9: getstatic     #35                 // Field NORMAL_USER1:Lorg/apache/hadoop/hbase/security/User;
      12: aload_1
      13: invokevirtual #55                 // Method org/apache/hadoop/hbase/security/User.runAs:(Ljava/security/PrivilegedExceptionAction;)Ljava/lang/Object;
      16: checkcast     #69                 // class org/apache/hadoop/hbase/protobuf/generated/VisibilityLabelsProtos$VisibilityLabelsResponse
      19: astore_2
      20: ldc           #70                 // String org.apache.hadoop.hbase.security.AccessDeniedException
      22: aload_2
      23: iconst_0
      24: invokevirtual #71                 // Method org/apache/hadoop/hbase/protobuf/generated/VisibilityLabelsProtos$VisibilityLabelsResponse.getResult:(I)Lorg/apache/hadoop/hbase/protobuf/generated/ClientProtos$RegionActionResult;
      27: invokevirtual #72                 // Method org/apache/hadoop/hbase/protobuf/generated/ClientProtos$RegionActionResult.getException:()Lorg/apache/hadoop/hbase/protobuf/generated/HBaseProtos$NameBytesPair;
      30: invokevirtual #73                 // Method org/apache/hadoop/hbase/protobuf/generated/HBaseProtos$NameBytesPair.getName:()Ljava/lang/String;
      33: invokestatic  #74                 // Method org/junit/Assert.assertEquals:(Ljava/lang/Object;Ljava/lang/Object;)V
      36: ldc           #70                 // String org.apache.hadoop.hbase.security.AccessDeniedException
      38: aload_2
      39: iconst_1
      40: invokevirtual #71                 // Method org/apache/hadoop/hbase/protobuf/generated/VisibilityLabelsProtos$VisibilityLabelsResponse.getResult:(I)Lorg/apache/hadoop/hbase/protobuf/generated/ClientProtos$RegionActionResult;
      43: invokevirtual #72                 // Method org/apache/hadoop/hbase/protobuf/generated/ClientProtos$RegionActionResult.getException:()Lorg/apache/hadoop/hbase/protobuf/generated/HBaseProtos$NameBytesPair;
      46: invokevirtual #73                 // Method org/apache/hadoop/hbase/protobuf/generated/HBaseProtos$NameBytesPair.getName:()Ljava/lang/String;
      49: invokestatic  #74                 // Method org/junit/Assert.assertEquals:(Ljava/lang/Object;Ljava/lang/Object;)V
      52: new           #75                 // class org/apache/hadoop/hbase/security/visibility/TestVisibilityLabelsWithACL$6
      55: dup
      56: aload_0
      57: invokespecial #76                 // Method org/apache/hadoop/hbase/security/visibility/TestVisibilityLabelsWithACL$6."<init>":(Lorg/apache/hadoop/hbase/security/visibility/TestVisibilityLabelsWithACL;)V
      60: astore_1
      61: getstatic     #35                 // Field NORMAL_USER1:Lorg/apache/hadoop/hbase/security/User;
      64: aload_1
      65: invokevirtual #55                 // Method org/apache/hadoop/hbase/security/User.runAs:(Ljava/security/PrivilegedExceptionAction;)Ljava/lang/Object;
      68: checkcast     #69                 // class org/apache/hadoop/hbase/protobuf/generated/VisibilityLabelsProtos$VisibilityLabelsResponse
      71: astore_2
      72: ldc           #70                 // String org.apache.hadoop.hbase.security.AccessDeniedException
      74: aload_2
      75: iconst_0
      76: invokevirtual #71                 // Method org/apache/hadoop/hbase/protobuf/generated/VisibilityLabelsProtos$VisibilityLabelsResponse.getResult:(I)Lorg/apache/hadoop/hbase/protobuf/generated/ClientProtos$RegionActionResult;
      79: invokevirtual #72                 // Method org/apache/hadoop/hbase/protobuf/generated/ClientProtos$RegionActionResult.getException:()Lorg/apache/hadoop/hbase/protobuf/generated/HBaseProtos$NameBytesPair;
      82: invokevirtual #73                 // Method org/apache/hadoop/hbase/protobuf/generated/HBaseProtos$NameBytesPair.getName:()Ljava/lang/String;
      85: invokestatic  #74                 // Method org/junit/Assert.assertEquals:(Ljava/lang/Object;Ljava/lang/Object;)V
      88: ldc           #70                 // String org.apache.hadoop.hbase.security.AccessDeniedException
      90: aload_2
      91: iconst_1
      92: invokevirtual #71                 // Method org/apache/hadoop/hbase/protobuf/generated/VisibilityLabelsProtos$VisibilityLabelsResponse.getResult:(I)Lorg/apache/hadoop/hbase/protobuf/generated/ClientProtos$RegionActionResult;
      95: invokevirtual #72                 // Method org/apache/hadoop/hbase/protobuf/generated/ClientProtos$RegionActionResult.getException:()Lorg/apache/hadoop/hbase/protobuf/generated/HBaseProtos$NameBytesPair;
      98: invokevirtual #73                 // Method org/apache/hadoop/hbase/protobuf/generated/HBaseProtos$NameBytesPair.getName:()Ljava/lang/String;
     101: invokestatic  #74                 // Method org/junit/Assert.assertEquals:(Ljava/lang/Object;Ljava/lang/Object;)V
     104: new           #77                 // class org/apache/hadoop/hbase/security/visibility/TestVisibilityLabelsWithACL$7
     107: dup
     108: aload_0
     109: invokespecial #78                 // Method org/apache/hadoop/hbase/security/visibility/TestVisibilityLabelsWithACL$7."<init>":(Lorg/apache/hadoop/hbase/security/visibility/TestVisibilityLabelsWithACL;)V
     112: astore_1
     113: getstatic     #33                 // Field SUPERUSER:Lorg/apache/hadoop/hbase/security/User;
     116: aload_1
     117: invokevirtual #55                 // Method org/apache/hadoop/hbase/security/User.runAs:(Ljava/security/PrivilegedExceptionAction;)Ljava/lang/Object;
     120: checkcast     #69                 // class org/apache/hadoop/hbase/protobuf/generated/VisibilityLabelsProtos$VisibilityLabelsResponse
     123: astore_2
     124: aload_2
     125: iconst_0
     126: invokevirtual #71                 // Method org/apache/hadoop/hbase/protobuf/generated/VisibilityLabelsProtos$VisibilityLabelsResponse.getResult:(I)Lorg/apache/hadoop/hbase/protobuf/generated/ClientProtos$RegionActionResult;
     129: invokevirtual #72                 // Method org/apache/hadoop/hbase/protobuf/generated/ClientProtos$RegionActionResult.getException:()Lorg/apache/hadoop/hbase/protobuf/generated/HBaseProtos$NameBytesPair;
     132: invokevirtual #79                 // Method org/apache/hadoop/hbase/protobuf/generated/HBaseProtos$NameBytesPair.getValue:()Lcom/google/protobuf/ByteString;
     135: invokevirtual #80                 // Method com/google/protobuf/ByteString.isEmpty:()Z
     138: invokestatic  #81                 // Method org/junit/Assert.assertTrue:(Z)V
     141: aload_2
     142: iconst_1
     143: invokevirtual #71                 // Method org/apache/hadoop/hbase/protobuf/generated/VisibilityLabelsProtos$VisibilityLabelsResponse.getResult:(I)Lorg/apache/hadoop/hbase/protobuf/generated/ClientProtos$RegionActionResult;
     146: invokevirtual #72                 // Method org/apache/hadoop/hbase/protobuf/generated/ClientProtos$RegionActionResult.getException:()Lorg/apache/hadoop/hbase/protobuf/generated/HBaseProtos$NameBytesPair;
     149: invokevirtual #79                 // Method org/apache/hadoop/hbase/protobuf/generated/HBaseProtos$NameBytesPair.getValue:()Lcom/google/protobuf/ByteString;
     152: invokevirtual #80                 // Method com/google/protobuf/ByteString.isEmpty:()Z
     155: invokestatic  #81                 // Method org/junit/Assert.assertTrue:(Z)V
     158: new           #82                 // class org/apache/hadoop/hbase/security/visibility/TestVisibilityLabelsWithACL$8
     161: dup
     162: aload_0
     163: invokespecial #83                 // Method org/apache/hadoop/hbase/security/visibility/TestVisibilityLabelsWithACL$8."<init>":(Lorg/apache/hadoop/hbase/security/visibility/TestVisibilityLabelsWithACL;)V
     166: astore_1
     167: getstatic     #35                 // Field NORMAL_USER1:Lorg/apache/hadoop/hbase/security/User;
     170: aload_1
     171: invokevirtual #55                 // Method org/apache/hadoop/hbase/security/User.runAs:(Ljava/security/PrivilegedExceptionAction;)Ljava/lang/Object;
     174: checkcast     #69                 // class org/apache/hadoop/hbase/protobuf/generated/VisibilityLabelsProtos$VisibilityLabelsResponse
     177: astore_2
     178: ldc           #70                 // String org.apache.hadoop.hbase.security.AccessDeniedException
     180: aload_2
     181: iconst_0
     182: invokevirtual #71                 // Method org/apache/hadoop/hbase/protobuf/generated/VisibilityLabelsProtos$VisibilityLabelsResponse.getResult:(I)Lorg/apache/hadoop/hbase/protobuf/generated/ClientProtos$RegionActionResult;
     185: invokevirtual #72                 // Method org/apache/hadoop/hbase/protobuf/generated/ClientProtos$RegionActionResult.getException:()Lorg/apache/hadoop/hbase/protobuf/generated/HBaseProtos$NameBytesPair;
     188: invokevirtual #73                 // Method org/apache/hadoop/hbase/protobuf/generated/HBaseProtos$NameBytesPair.getName:()Ljava/lang/String;
     191: invokestatic  #74                 // Method org/junit/Assert.assertEquals:(Ljava/lang/Object;Ljava/lang/Object;)V
     194: ldc           #70                 // String org.apache.hadoop.hbase.security.AccessDeniedException
     196: aload_2
     197: iconst_1
     198: invokevirtual #71                 // Method org/apache/hadoop/hbase/protobuf/generated/VisibilityLabelsProtos$VisibilityLabelsResponse.getResult:(I)Lorg/apache/hadoop/hbase/protobuf/generated/ClientProtos$RegionActionResult;
     201: invokevirtual #72                 // Method org/apache/hadoop/hbase/protobuf/generated/ClientProtos$RegionActionResult.getException:()Lorg/apache/hadoop/hbase/protobuf/generated/HBaseProtos$NameBytesPair;
     204: invokevirtual #73                 // Method org/apache/hadoop/hbase/protobuf/generated/HBaseProtos$NameBytesPair.getName:()Ljava/lang/String;
     207: invokestatic  #74                 // Method org/junit/Assert.assertEquals:(Ljava/lang/Object;Ljava/lang/Object;)V
     210: getstatic     #7                  // Field TEST_UTIL:Lorg/apache/hadoop/hbase/HBaseTestingUtility;
     213: invokevirtual #45                 // Method org/apache/hadoop/hbase/HBaseTestingUtility.getConnection:()Lorg/apache/hadoop/hbase/client/Connection;
     216: iconst_2
     217: anewarray     #30                 // class java/lang/String
     220: dup
     221: iconst_0
     222: ldc           #84                 // String confidential
     224: aastore
     225: dup
     226: iconst_1
     227: ldc           #85                 // String private
     229: aastore
     230: ldc           #34                 // String user1
     232: invokestatic  #64                 // Method org/apache/hadoop/hbase/security/visibility/VisibilityClient.clearAuths:(Lorg/apache/hadoop/hbase/client/Connection;[Ljava/lang/String;Ljava/lang/String;)Lorg/apache/hadoop/hbase/protobuf/generated/VisibilityLabelsProtos$VisibilityLabelsResponse;
     235: astore_2
     236: aload_2
     237: iconst_0
     238: invokevirtual #71                 // Method org/apache/hadoop/hbase/protobuf/generated/VisibilityLabelsProtos$VisibilityLabelsResponse.getResult:(I)Lorg/apache/hadoop/hbase/protobuf/generated/ClientProtos$RegionActionResult;
     241: invokevirtual #72                 // Method org/apache/hadoop/hbase/protobuf/generated/ClientProtos$RegionActionResult.getException:()Lorg/apache/hadoop/hbase/protobuf/generated/HBaseProtos$NameBytesPair;
     244: invokevirtual #79                 // Method org/apache/hadoop/hbase/protobuf/generated/HBaseProtos$NameBytesPair.getValue:()Lcom/google/protobuf/ByteString;
     247: invokevirtual #80                 // Method com/google/protobuf/ByteString.isEmpty:()Z
     250: invokestatic  #81                 // Method org/junit/Assert.assertTrue:(Z)V
     253: aload_2
     254: iconst_1
     255: invokevirtual #71                 // Method org/apache/hadoop/hbase/protobuf/generated/VisibilityLabelsProtos$VisibilityLabelsResponse.getResult:(I)Lorg/apache/hadoop/hbase/protobuf/generated/ClientProtos$RegionActionResult;
     258: invokevirtual #72                 // Method org/apache/hadoop/hbase/protobuf/generated/ClientProtos$RegionActionResult.getException:()Lorg/apache/hadoop/hbase/protobuf/generated/HBaseProtos$NameBytesPair;
     261: invokevirtual #79                 // Method org/apache/hadoop/hbase/protobuf/generated/HBaseProtos$NameBytesPair.getValue:()Lcom/google/protobuf/ByteString;
     264: invokevirtual #80                 // Method com/google/protobuf/ByteString.isEmpty:()Z
     267: invokestatic  #81                 // Method org/junit/Assert.assertTrue:(Z)V
     270: getstatic     #7                  // Field TEST_UTIL:Lorg/apache/hadoop/hbase/HBaseTestingUtility;
     273: invokevirtual #45                 // Method org/apache/hadoop/hbase/HBaseTestingUtility.getConnection:()Lorg/apache/hadoop/hbase/client/Connection;
     276: iconst_2
     277: anewarray     #30                 // class java/lang/String
     280: dup
     281: iconst_0
     282: ldc           #84                 // String confidential
     284: aastore
     285: dup
     286: iconst_1
     287: ldc           #85                 // String private
     289: aastore
     290: ldc           #86                 // String user3
     292: invokestatic  #46                 // Method org/apache/hadoop/hbase/security/visibility/VisibilityClient.setAuths:(Lorg/apache/hadoop/hbase/client/Connection;[Ljava/lang/String;Ljava/lang/String;)Lorg/apache/hadoop/hbase/protobuf/generated/VisibilityLabelsProtos$VisibilityLabelsResponse;
     295: pop
     296: new           #87                 // class org/apache/hadoop/hbase/security/visibility/TestVisibilityLabelsWithACL$9
     299: dup
     300: aload_0
     301: invokespecial #88                 // Method org/apache/hadoop/hbase/security/visibility/TestVisibilityLabelsWithACL$9."<init>":(Lorg/apache/hadoop/hbase/security/visibility/TestVisibilityLabelsWithACL;)V
     304: astore_3
     305: getstatic     #35                 // Field NORMAL_USER1:Lorg/apache/hadoop/hbase/security/User;
     308: aload_3
     309: invokevirtual #55                 // Method org/apache/hadoop/hbase/security/User.runAs:(Ljava/security/PrivilegedExceptionAction;)Ljava/lang/Object;
     312: checkcast     #89                 // class org/apache/hadoop/hbase/protobuf/generated/VisibilityLabelsProtos$GetAuthsResponse
     315: astore        4
     317: aload         4
     319: invokestatic  #90                 // Method org/junit/Assert.assertNull:(Ljava/lang/Object;)V
     322: getstatic     #33                 // Field SUPERUSER:Lorg/apache/hadoop/hbase/security/User;
     325: aload_3
     326: invokevirtual #55                 // Method org/apache/hadoop/hbase/security/User.runAs:(Ljava/security/PrivilegedExceptionAction;)Ljava/lang/Object;
     329: checkcast     #89                 // class org/apache/hadoop/hbase/protobuf/generated/VisibilityLabelsProtos$GetAuthsResponse
     332: astore        4
     334: new           #91                 // class java/util/ArrayList
     337: dup
     338: aload         4
     340: invokevirtual #92                 // Method org/apache/hadoop/hbase/protobuf/generated/VisibilityLabelsProtos$GetAuthsResponse.getAuthList:()Ljava/util/List;
     343: invokeinterface #93,  1           // InterfaceMethod java/util/List.size:()I
     348: invokespecial #94                 // Method java/util/ArrayList."<init>":(I)V
     351: astore        5
     353: aload         4
     355: invokevirtual #92                 // Method org/apache/hadoop/hbase/protobuf/generated/VisibilityLabelsProtos$GetAuthsResponse.getAuthList:()Ljava/util/List;
     358: invokeinterface #95,  1           // InterfaceMethod java/util/List.iterator:()Ljava/util/Iterator;
     363: astore        6
     365: aload         6
     367: invokeinterface #96,  1           // InterfaceMethod java/util/Iterator.hasNext:()Z
     372: ifeq          406
     375: aload         6
     377: invokeinterface #97,  1           // InterfaceMethod java/util/Iterator.next:()Ljava/lang/Object;
     382: checkcast     #98                 // class com/google/protobuf/ByteString
     385: astore        7
     387: aload         5
     389: aload         7
     391: invokevirtual #99                 // Method com/google/protobuf/ByteString.toByteArray:()[B
     394: invokestatic  #100                // Method org/apache/hadoop/hbase/util/Bytes.toString:([B)Ljava/lang/String;
     397: invokeinterface #101,  2          // InterfaceMethod java/util/List.add:(Ljava/lang/Object;)Z
     402: pop
     403: goto          365
     406: ldc2_w        #102                // long 2l
     409: aload         5
     411: invokeinterface #93,  1           // InterfaceMethod java/util/List.size:()I
     416: i2l
     417: invokestatic  #104                // Method org/junit/Assert.assertEquals:(JJ)V
     420: aload         5
     422: ldc           #84                 // String confidential
     424: invokeinterface #105,  2          // InterfaceMethod java/util/List.contains:(Ljava/lang/Object;)Z
     429: invokestatic  #81                 // Method org/junit/Assert.assertTrue:(Z)V
     432: aload         5
     434: ldc           #85                 // String private
     436: invokeinterface #105,  2          // InterfaceMethod java/util/List.contains:(Ljava/lang/Object;)Z
     441: invokestatic  #81                 // Method org/junit/Assert.assertTrue:(Z)V
     444: return

  static org.apache.hadoop.conf.Configuration access$000();
    Code:
       0: getstatic     #2                  // Field conf:Lorg/apache/hadoop/conf/Configuration;
       3: areturn

  static byte[] access$100();
    Code:
       0: getstatic     #1                  // Field row1:[B
       3: areturn

  static {};
    Code:
       0: ldc           #43                 // class org/apache/hadoop/hbase/security/visibility/TestVisibilityLabelsWithACL
       2: invokestatic  #127                // Method org/apache/hadoop/hbase/HBaseClassTestRule.forClass:(Ljava/lang/Class;)Lorg/apache/hadoop/hbase/HBaseClassTestRule;
       5: putstatic     #128                // Field CLASS_RULE:Lorg/apache/hadoop/hbase/HBaseClassTestRule;
       8: new           #129                // class org/apache/hadoop/hbase/HBaseTestingUtility
      11: dup
      12: invokespecial #130                // Method org/apache/hadoop/hbase/HBaseTestingUtility."<init>":()V
      15: putstatic     #7                  // Field TEST_UTIL:Lorg/apache/hadoop/hbase/HBaseTestingUtility;
      18: ldc           #131                // String row1
      20: invokestatic  #111                // Method org/apache/hadoop/hbase/util/Bytes.toBytes:(Ljava/lang/String;)[B
      23: putstatic     #1                  // Field row1:[B
      26: ldc           #132                // String info
      28: invokestatic  #111                // Method org/apache/hadoop/hbase/util/Bytes.toBytes:(Ljava/lang/String;)[B
      31: putstatic     #106                // Field fam:[B
      34: ldc           #133                // String qual
      36: invokestatic  #111                // Method org/apache/hadoop/hbase/util/Bytes.toBytes:(Ljava/lang/String;)[B
      39: putstatic     #113                // Field qual:[B
      42: ldc           #134                // String value
      44: invokestatic  #111                // Method org/apache/hadoop/hbase/util/Bytes.toBytes:(Ljava/lang/String;)[B
      47: putstatic     #117                // Field value:[B
      50: return
}
