Compiled from "TestRegionServerReadRequestMetrics.java"
public class org.apache.hadoop.hbase.regionserver.TestRegionServerReadRequestMetrics {
  public static final org.apache.hadoop.hbase.HBaseClassTestRule CLASS_RULE;

  public org.apache.hadoop.hbase.regionserver.TestRegionServerReadRequestMetrics();
    Code:
       0: aload_0
       1: invokespecial #8                  // Method java/lang/Object."<init>":()V
       4: return

  public static void setUpOnce() throws java.lang.Exception;
    Code:
       0: getstatic     #9                  // Field TEST_UTIL:Lorg/apache/hadoop/hbase/HBaseTestingUtility;
       3: invokevirtual #10                 // Method org/apache/hadoop/hbase/HBaseTestingUtility.getConfiguration:()Lorg/apache/hadoop/conf/Configuration;
       6: ldc           #12                 // String hbase.balancer.tablesOnMaster
       8: iconst_1
       9: invokevirtual #13                 // Method org/apache/hadoop/conf/Configuration.setBoolean:(Ljava/lang/String;Z)V
      12: getstatic     #9                  // Field TEST_UTIL:Lorg/apache/hadoop/hbase/HBaseTestingUtility;
      15: invokevirtual #14                 // Method org/apache/hadoop/hbase/HBaseTestingUtility.startMiniCluster:()Lorg/apache/hadoop/hbase/MiniHBaseCluster;
      18: pop
      19: getstatic     #9                  // Field TEST_UTIL:Lorg/apache/hadoop/hbase/HBaseTestingUtility;
      22: invokevirtual #15                 // Method org/apache/hadoop/hbase/HBaseTestingUtility.getAdmin:()Lorg/apache/hadoop/hbase/client/Admin;
      25: putstatic     #16                 // Field admin:Lorg/apache/hadoop/hbase/client/Admin;
      28: getstatic     #16                 // Field admin:Lorg/apache/hadoop/hbase/client/Admin;
      31: getstatic     #17                 // Field org/apache/hadoop/hbase/ClusterMetrics$Option.LIVE_SERVERS:Lorg/apache/hadoop/hbase/ClusterMetrics$Option;
      34: invokestatic  #18                 // Method java/util/EnumSet.of:(Ljava/lang/Enum;)Ljava/util/EnumSet;
      37: invokeinterface #19,  2           // InterfaceMethod org/apache/hadoop/hbase/client/Admin.getClusterMetrics:(Ljava/util/EnumSet;)Lorg/apache/hadoop/hbase/ClusterMetrics;
      42: invokeinterface #20,  1           // InterfaceMethod org/apache/hadoop/hbase/ClusterMetrics.getLiveServerMetrics:()Ljava/util/Map;
      47: invokeinterface #21,  1           // InterfaceMethod java/util/Map.keySet:()Ljava/util/Set;
      52: putstatic     #22                 // Field serverNames:Ljava/util/Collection;
      55: invokestatic  #23                 // Method createTable:()Lorg/apache/hadoop/hbase/client/Table;
      58: putstatic     #24                 // Field table:Lorg/apache/hadoop/hbase/client/Table;
      61: invokestatic  #25                 // Method putData:()V
      64: getstatic     #16                 // Field admin:Lorg/apache/hadoop/hbase/client/Admin;
      67: getstatic     #26                 // Field TABLE_NAME:Lorg/apache/hadoop/hbase/TableName;
      70: invokeinterface #27,  2           // InterfaceMethod org/apache/hadoop/hbase/client/Admin.getRegions:(Lorg/apache/hadoop/hbase/TableName;)Ljava/util/List;
      75: astore_0
      76: new           #28                 // class java/lang/StringBuilder
      79: dup
      80: invokespecial #29                 // Method java/lang/StringBuilder."<init>":()V
      83: ldc           #30                 // String Table
      85: invokevirtual #31                 // Method java/lang/StringBuilder.append:(Ljava/lang/String;)Ljava/lang/StringBuilder;
      88: getstatic     #26                 // Field TABLE_NAME:Lorg/apache/hadoop/hbase/TableName;
      91: invokevirtual #32                 // Method java/lang/StringBuilder.append:(Ljava/lang/Object;)Ljava/lang/StringBuilder;
      94: ldc           #33                 // String  should have 1 region
      96: invokevirtual #31                 // Method java/lang/StringBuilder.append:(Ljava/lang/String;)Ljava/lang/StringBuilder;
      99: invokevirtual #34                 // Method java/lang/StringBuilder.toString:()Ljava/lang/String;
     102: lconst_1
     103: aload_0
     104: invokeinterface #35,  1           // InterfaceMethod java/util/List.size:()I
     109: i2l
     110: invokestatic  #36                 // Method org/junit/Assert.assertEquals:(Ljava/lang/String;JJ)V
     113: aload_0
     114: iconst_0
     115: invokeinterface #37,  2           // InterfaceMethod java/util/List.get:(I)Ljava/lang/Object;
     120: checkcast     #38                 // class org/apache/hadoop/hbase/client/RegionInfo
     123: putstatic     #39                 // Field regionInfo:Lorg/apache/hadoop/hbase/client/RegionInfo;
     126: invokestatic  #40                 // Method org/apache/hadoop/hbase/regionserver/TestRegionServerReadRequestMetrics$Metric.values:()[Lorg/apache/hadoop/hbase/regionserver/TestRegionServerReadRequestMetrics$Metric;
     129: astore_1
     130: aload_1
     131: arraylength
     132: istore_2
     133: iconst_0
     134: istore_3
     135: iload_3
     136: iload_2
     137: if_icmpge     181
     140: aload_1
     141: iload_3
     142: aaload
     143: astore        4
     145: getstatic     #41                 // Field requestsMap:Ljava/util/Map;
     148: aload         4
     150: lconst_0
     151: invokestatic  #42                 // Method java/lang/Long.valueOf:(J)Ljava/lang/Long;
     154: invokeinterface #43,  3           // InterfaceMethod java/util/Map.put:(Ljava/lang/Object;Ljava/lang/Object;)Ljava/lang/Object;
     159: pop
     160: getstatic     #44                 // Field requestsMapPrev:Ljava/util/Map;
     163: aload         4
     165: lconst_0
     166: invokestatic  #42                 // Method java/lang/Long.valueOf:(J)Ljava/lang/Long;
     169: invokeinterface #43,  3           // InterfaceMethod java/util/Map.put:(Ljava/lang/Object;Ljava/lang/Object;)Ljava/lang/Object;
     174: pop
     175: iinc          3, 1
     178: goto          135
     181: return

  public static void tearDownOnce() throws java.lang.Exception;
    Code:
       0: getstatic     #9                  // Field TEST_UTIL:Lorg/apache/hadoop/hbase/HBaseTestingUtility;
       3: invokevirtual #103                // Method org/apache/hadoop/hbase/HBaseTestingUtility.shutdownMiniCluster:()V
       6: return

  public void testReadRequestsCountNotFiltered() throws java.lang.Exception;
    Code:
       0: new           #104                // class org/apache/hadoop/hbase/client/Scan
       3: dup
       4: invokespecial #105                // Method org/apache/hadoop/hbase/client/Scan."<init>":()V
       7: astore_2
       8: getstatic     #24                 // Field table:Lorg/apache/hadoop/hbase/client/Table;
      11: aload_2
      12: invokeinterface #106,  2          // InterfaceMethod org/apache/hadoop/hbase/client/Table.getScanner:(Lorg/apache/hadoop/hbase/client/Scan;)Lorg/apache/hadoop/hbase/client/ResultScanner;
      17: astore        7
      19: aconst_null
      20: astore        8
      22: iconst_0
      23: istore_1
      24: aload         7
      26: invokeinterface #107,  1          // InterfaceMethod org/apache/hadoop/hbase/client/ResultScanner.iterator:()Ljava/util/Iterator;
      31: astore        9
      33: aload         9
      35: invokeinterface #72,  1           // InterfaceMethod java/util/Iterator.hasNext:()Z
      40: ifeq          61
      43: aload         9
      45: invokeinterface #73,  1           // InterfaceMethod java/util/Iterator.next:()Ljava/lang/Object;
      50: checkcast     #108                // class org/apache/hadoop/hbase/client/Result
      53: astore        10
      55: iinc          1, 1
      58: goto          33
      61: iload_1
      62: i2l
      63: ldc2_w        #109                // long 3l
      66: lconst_0
      67: invokestatic  #111                // Method testReadRequests:(JJJ)V
      70: aload         7
      72: ifnull        165
      75: aload         8
      77: ifnull        102
      80: aload         7
      82: invokeinterface #112,  1          // InterfaceMethod org/apache/hadoop/hbase/client/ResultScanner.close:()V
      87: goto          165
      90: astore        9
      92: aload         8
      94: aload         9
      96: invokevirtual #114                // Method java/lang/Throwable.addSuppressed:(Ljava/lang/Throwable;)V
      99: goto          165
     102: aload         7
     104: invokeinterface #112,  1          // InterfaceMethod org/apache/hadoop/hbase/client/ResultScanner.close:()V
     109: goto          165
     112: astore        9
     114: aload         9
     116: astore        8
     118: aload         9
     120: athrow
     121: astore        11
     123: aload         7
     125: ifnull        162
     128: aload         8
     130: ifnull        155
     133: aload         7
     135: invokeinterface #112,  1          // InterfaceMethod org/apache/hadoop/hbase/client/ResultScanner.close:()V
     140: goto          162
     143: astore        12
     145: aload         8
     147: aload         12
     149: invokevirtual #114                // Method java/lang/Throwable.addSuppressed:(Ljava/lang/Throwable;)V
     152: goto          162
     155: aload         7
     157: invokeinterface #112,  1          // InterfaceMethod org/apache/hadoop/hbase/client/ResultScanner.close:()V
     162: aload         11
     164: athrow
     165: new           #104                // class org/apache/hadoop/hbase/client/Scan
     168: dup
     169: getstatic     #2                  // Field ROW2:[B
     172: getstatic     #1                  // Field ROW3:[B
     175: invokespecial #115                // Method org/apache/hadoop/hbase/client/Scan."<init>":([B[B)V
     178: astore_2
     179: getstatic     #24                 // Field table:Lorg/apache/hadoop/hbase/client/Table;
     182: aload_2
     183: invokeinterface #106,  2          // InterfaceMethod org/apache/hadoop/hbase/client/Table.getScanner:(Lorg/apache/hadoop/hbase/client/Scan;)Lorg/apache/hadoop/hbase/client/ResultScanner;
     188: astore        7
     190: aconst_null
     191: astore        8
     193: iconst_0
     194: istore_1
     195: aload         7
     197: invokeinterface #107,  1          // InterfaceMethod org/apache/hadoop/hbase/client/ResultScanner.iterator:()Ljava/util/Iterator;
     202: astore        9
     204: aload         9
     206: invokeinterface #72,  1           // InterfaceMethod java/util/Iterator.hasNext:()Z
     211: ifeq          232
     214: aload         9
     216: invokeinterface #73,  1           // InterfaceMethod java/util/Iterator.next:()Ljava/lang/Object;
     221: checkcast     #108                // class org/apache/hadoop/hbase/client/Result
     224: astore        10
     226: iinc          1, 1
     229: goto          204
     232: iload_1
     233: i2l
     234: lconst_1
     235: lconst_0
     236: invokestatic  #111                // Method testReadRequests:(JJJ)V
     239: aload         7
     241: ifnull        334
     244: aload         8
     246: ifnull        271
     249: aload         7
     251: invokeinterface #112,  1          // InterfaceMethod org/apache/hadoop/hbase/client/ResultScanner.close:()V
     256: goto          334
     259: astore        9
     261: aload         8
     263: aload         9
     265: invokevirtual #114                // Method java/lang/Throwable.addSuppressed:(Ljava/lang/Throwable;)V
     268: goto          334
     271: aload         7
     273: invokeinterface #112,  1          // InterfaceMethod org/apache/hadoop/hbase/client/ResultScanner.close:()V
     278: goto          334
     281: astore        9
     283: aload         9
     285: astore        8
     287: aload         9
     289: athrow
     290: astore        13
     292: aload         7
     294: ifnull        331
     297: aload         8
     299: ifnull        324
     302: aload         7
     304: invokeinterface #112,  1          // InterfaceMethod org/apache/hadoop/hbase/client/ResultScanner.close:()V
     309: goto          331
     312: astore        14
     314: aload         8
     316: aload         14
     318: invokevirtual #114                // Method java/lang/Throwable.addSuppressed:(Ljava/lang/Throwable;)V
     321: goto          331
     324: aload         7
     326: invokeinterface #112,  1          // InterfaceMethod org/apache/hadoop/hbase/client/ResultScanner.close:()V
     331: aload         13
     333: athrow
     334: new           #116                // class org/apache/hadoop/hbase/client/Get
     337: dup
     338: getstatic     #2                  // Field ROW2:[B
     341: invokespecial #117                // Method org/apache/hadoop/hbase/client/Get."<init>":([B)V
     344: astore        6
     346: getstatic     #24                 // Field table:Lorg/apache/hadoop/hbase/client/Table;
     349: aload         6
     351: invokeinterface #118,  2          // InterfaceMethod org/apache/hadoop/hbase/client/Table.get:(Lorg/apache/hadoop/hbase/client/Get;)Lorg/apache/hadoop/hbase/client/Result;
     356: astore        7
     358: aload         7
     360: invokevirtual #119                // Method org/apache/hadoop/hbase/client/Result.isEmpty:()Z
     363: ifeq          370
     366: iconst_0
     367: goto          371
     370: iconst_1
     371: istore_1
     372: iload_1
     373: i2l
     374: lconst_1
     375: lconst_0
     376: invokestatic  #111                // Method testReadRequests:(JJJ)V
     379: new           #120                // class org/apache/hadoop/hbase/client/Increment
     382: dup
     383: getstatic     #6                  // Field ROW1:[B
     386: invokespecial #121                // Method org/apache/hadoop/hbase/client/Increment."<init>":([B)V
     389: astore        5
     391: aload         5
     393: getstatic     #5                  // Field CF1:[B
     396: getstatic     #98                 // Field COL3:[B
     399: lconst_1
     400: invokevirtual #122                // Method org/apache/hadoop/hbase/client/Increment.addColumn:([B[BJ)Lorg/apache/hadoop/hbase/client/Increment;
     403: pop
     404: getstatic     #24                 // Field table:Lorg/apache/hadoop/hbase/client/Table;
     407: aload         5
     409: invokeinterface #123,  2          // InterfaceMethod org/apache/hadoop/hbase/client/Table.increment:(Lorg/apache/hadoop/hbase/client/Increment;)Lorg/apache/hadoop/hbase/client/Result;
     414: astore        7
     416: aload         7
     418: invokevirtual #119                // Method org/apache/hadoop/hbase/client/Result.isEmpty:()Z
     421: ifeq          428
     424: iconst_0
     425: goto          429
     428: iconst_1
     429: istore_1
     430: iload_1
     431: i2l
     432: lconst_1
     433: lconst_0
     434: invokestatic  #111                // Method testReadRequests:(JJJ)V
     437: new           #93                 // class org/apache/hadoop/hbase/client/Put
     440: dup
     441: getstatic     #6                  // Field ROW1:[B
     444: invokespecial #94                 // Method org/apache/hadoop/hbase/client/Put."<init>":([B)V
     447: astore        4
     449: aload         4
     451: getstatic     #5                  // Field CF1:[B
     454: getstatic     #96                 // Field COL2:[B
     457: getstatic     #97                 // Field VAL2:[B
     460: invokevirtual #95                 // Method org/apache/hadoop/hbase/client/Put.addColumn:([B[B[B)Lorg/apache/hadoop/hbase/client/Put;
     463: pop
     464: getstatic     #24                 // Field table:Lorg/apache/hadoop/hbase/client/Table;
     467: getstatic     #6                  // Field ROW1:[B
     470: getstatic     #5                  // Field CF1:[B
     473: invokeinterface #124,  3          // InterfaceMethod org/apache/hadoop/hbase/client/Table.checkAndMutate:([B[B)Lorg/apache/hadoop/hbase/client/Table$CheckAndMutateBuilder;
     478: getstatic     #96                 // Field COL2:[B
     481: invokeinterface #125,  2          // InterfaceMethod org/apache/hadoop/hbase/client/Table$CheckAndMutateBuilder.qualifier:([B)Lorg/apache/hadoop/hbase/client/Table$CheckAndMutateBuilder;
     486: getstatic     #97                 // Field VAL2:[B
     489: invokeinterface #126,  2          // InterfaceMethod org/apache/hadoop/hbase/client/Table$CheckAndMutateBuilder.ifEquals:([B)Lorg/apache/hadoop/hbase/client/Table$CheckAndMutateBuilder;
     494: aload         4
     496: invokeinterface #127,  2          // InterfaceMethod org/apache/hadoop/hbase/client/Table$CheckAndMutateBuilder.thenPut:(Lorg/apache/hadoop/hbase/client/Put;)Z
     501: istore        8
     503: iload         8
     505: ifeq          512
     508: iconst_1
     509: goto          513
     512: iconst_0
     513: istore_1
     514: iload_1
     515: i2l
     516: lconst_1
     517: lconst_0
     518: invokestatic  #111                // Method testReadRequests:(JJJ)V
     521: new           #128                // class org/apache/hadoop/hbase/client/Append
     524: dup
     525: getstatic     #6                  // Field ROW1:[B
     528: invokespecial #129                // Method org/apache/hadoop/hbase/client/Append."<init>":([B)V
     531: astore_3
     532: aload_3
     533: getstatic     #5                  // Field CF1:[B
     536: getstatic     #96                 // Field COL2:[B
     539: getstatic     #97                 // Field VAL2:[B
     542: invokevirtual #130                // Method org/apache/hadoop/hbase/client/Append.addColumn:([B[B[B)Lorg/apache/hadoop/hbase/client/Append;
     545: pop
     546: getstatic     #24                 // Field table:Lorg/apache/hadoop/hbase/client/Table;
     549: aload_3
     550: invokeinterface #131,  2          // InterfaceMethod org/apache/hadoop/hbase/client/Table.append:(Lorg/apache/hadoop/hbase/client/Append;)Lorg/apache/hadoop/hbase/client/Result;
     555: astore        7
     557: aload         7
     559: invokevirtual #119                // Method org/apache/hadoop/hbase/client/Result.isEmpty:()Z
     562: ifeq          569
     565: iconst_0
     566: goto          570
     569: iconst_1
     570: istore_1
     571: iload_1
     572: i2l
     573: lconst_1
     574: lconst_0
     575: invokestatic  #111                // Method testReadRequests:(JJJ)V
     578: new           #93                 // class org/apache/hadoop/hbase/client/Put
     581: dup
     582: getstatic     #6                  // Field ROW1:[B
     585: invokespecial #94                 // Method org/apache/hadoop/hbase/client/Put."<init>":([B)V
     588: astore        4
     590: aload         4
     592: getstatic     #5                  // Field CF1:[B
     595: getstatic     #4                  // Field COL1:[B
     598: getstatic     #3                  // Field VAL1:[B
     601: invokevirtual #95                 // Method org/apache/hadoop/hbase/client/Put.addColumn:([B[B[B)Lorg/apache/hadoop/hbase/client/Put;
     604: pop
     605: new           #132                // class org/apache/hadoop/hbase/client/RowMutations
     608: dup
     609: getstatic     #6                  // Field ROW1:[B
     612: invokespecial #133                // Method org/apache/hadoop/hbase/client/RowMutations."<init>":([B)V
     615: astore        9
     617: aload         9
     619: aload         4
     621: invokevirtual #134                // Method org/apache/hadoop/hbase/client/RowMutations.add:(Lorg/apache/hadoop/hbase/client/Put;)V
     624: getstatic     #24                 // Field table:Lorg/apache/hadoop/hbase/client/Table;
     627: getstatic     #6                  // Field ROW1:[B
     630: getstatic     #5                  // Field CF1:[B
     633: invokeinterface #124,  3          // InterfaceMethod org/apache/hadoop/hbase/client/Table.checkAndMutate:([B[B)Lorg/apache/hadoop/hbase/client/Table$CheckAndMutateBuilder;
     638: getstatic     #4                  // Field COL1:[B
     641: invokeinterface #125,  2          // InterfaceMethod org/apache/hadoop/hbase/client/Table$CheckAndMutateBuilder.qualifier:([B)Lorg/apache/hadoop/hbase/client/Table$CheckAndMutateBuilder;
     646: getstatic     #3                  // Field VAL1:[B
     649: invokeinterface #126,  2          // InterfaceMethod org/apache/hadoop/hbase/client/Table$CheckAndMutateBuilder.ifEquals:([B)Lorg/apache/hadoop/hbase/client/Table$CheckAndMutateBuilder;
     654: aload         9
     656: invokeinterface #135,  2          // InterfaceMethod org/apache/hadoop/hbase/client/Table$CheckAndMutateBuilder.thenMutate:(Lorg/apache/hadoop/hbase/client/RowMutations;)Z
     661: istore        10
     663: iload         10
     665: ifeq          672
     668: iconst_1
     669: goto          673
     672: iconst_0
     673: istore_1
     674: iload_1
     675: i2l
     676: lconst_1
     677: lconst_0
     678: invokestatic  #111                // Method testReadRequests:(JJJ)V
     681: return
    Exception table:
       from    to  target type
          80    87    90   Class java/lang/Throwable
          22    70   112   Class java/lang/Throwable
          22    70   121   any
         133   140   143   Class java/lang/Throwable
         112   123   121   any
         249   256   259   Class java/lang/Throwable
         193   239   281   Class java/lang/Throwable
         193   239   290   any
         302   309   312   Class java/lang/Throwable
         281   292   290   any

  public void testReadRequestsCountWithFilter() throws java.lang.Exception;
    Code:
       0: new           #104                // class org/apache/hadoop/hbase/client/Scan
       3: dup
       4: invokespecial #105                // Method org/apache/hadoop/hbase/client/Scan."<init>":()V
       7: astore_2
       8: aload_2
       9: new           #136                // class org/apache/hadoop/hbase/filter/SingleColumnValueFilter
      12: dup
      13: getstatic     #5                  // Field CF1:[B
      16: getstatic     #4                  // Field COL1:[B
      19: getstatic     #137                // Field org/apache/hadoop/hbase/CompareOperator.EQUAL:Lorg/apache/hadoop/hbase/CompareOperator;
      22: getstatic     #3                  // Field VAL1:[B
      25: invokespecial #138                // Method org/apache/hadoop/hbase/filter/SingleColumnValueFilter."<init>":([B[BLorg/apache/hadoop/hbase/CompareOperator;[B)V
      28: invokevirtual #139                // Method org/apache/hadoop/hbase/client/Scan.setFilter:(Lorg/apache/hadoop/hbase/filter/Filter;)Lorg/apache/hadoop/hbase/client/Scan;
      31: pop
      32: getstatic     #24                 // Field table:Lorg/apache/hadoop/hbase/client/Table;
      35: aload_2
      36: invokeinterface #106,  2          // InterfaceMethod org/apache/hadoop/hbase/client/Table.getScanner:(Lorg/apache/hadoop/hbase/client/Scan;)Lorg/apache/hadoop/hbase/client/ResultScanner;
      41: astore_3
      42: aconst_null
      43: astore        4
      45: iconst_0
      46: istore_1
      47: aload_3
      48: invokeinterface #107,  1          // InterfaceMethod org/apache/hadoop/hbase/client/ResultScanner.iterator:()Ljava/util/Iterator;
      53: astore        5
      55: aload         5
      57: invokeinterface #72,  1           // InterfaceMethod java/util/Iterator.hasNext:()Z
      62: ifeq          83
      65: aload         5
      67: invokeinterface #73,  1           // InterfaceMethod java/util/Iterator.next:()Ljava/lang/Object;
      72: checkcast     #108                // class org/apache/hadoop/hbase/client/Result
      75: astore        6
      77: iinc          1, 1
      80: goto          55
      83: iload_1
      84: i2l
      85: ldc2_w        #140                // long 2l
      88: lconst_1
      89: invokestatic  #111                // Method testReadRequests:(JJJ)V
      92: aload_3
      93: ifnull        181
      96: aload         4
      98: ifnull        122
     101: aload_3
     102: invokeinterface #112,  1          // InterfaceMethod org/apache/hadoop/hbase/client/ResultScanner.close:()V
     107: goto          181
     110: astore        5
     112: aload         4
     114: aload         5
     116: invokevirtual #114                // Method java/lang/Throwable.addSuppressed:(Ljava/lang/Throwable;)V
     119: goto          181
     122: aload_3
     123: invokeinterface #112,  1          // InterfaceMethod org/apache/hadoop/hbase/client/ResultScanner.close:()V
     128: goto          181
     131: astore        5
     133: aload         5
     135: astore        4
     137: aload         5
     139: athrow
     140: astore        7
     142: aload_3
     143: ifnull        178
     146: aload         4
     148: ifnull        172
     151: aload_3
     152: invokeinterface #112,  1          // InterfaceMethod org/apache/hadoop/hbase/client/ResultScanner.close:()V
     157: goto          178
     160: astore        8
     162: aload         4
     164: aload         8
     166: invokevirtual #114                // Method java/lang/Throwable.addSuppressed:(Ljava/lang/Throwable;)V
     169: goto          178
     172: aload_3
     173: invokeinterface #112,  1          // InterfaceMethod org/apache/hadoop/hbase/client/ResultScanner.close:()V
     178: aload         7
     180: athrow
     181: new           #104                // class org/apache/hadoop/hbase/client/Scan
     184: dup
     185: invokespecial #105                // Method org/apache/hadoop/hbase/client/Scan."<init>":()V
     188: astore_2
     189: aload_2
     190: new           #142                // class org/apache/hadoop/hbase/filter/RowFilter
     193: dup
     194: getstatic     #137                // Field org/apache/hadoop/hbase/CompareOperator.EQUAL:Lorg/apache/hadoop/hbase/CompareOperator;
     197: new           #143                // class org/apache/hadoop/hbase/filter/BinaryComparator
     200: dup
     201: getstatic     #6                  // Field ROW1:[B
     204: invokespecial #144                // Method org/apache/hadoop/hbase/filter/BinaryComparator."<init>":([B)V
     207: invokespecial #145                // Method org/apache/hadoop/hbase/filter/RowFilter."<init>":(Lorg/apache/hadoop/hbase/CompareOperator;Lorg/apache/hadoop/hbase/filter/ByteArrayComparable;)V
     210: invokevirtual #139                // Method org/apache/hadoop/hbase/client/Scan.setFilter:(Lorg/apache/hadoop/hbase/filter/Filter;)Lorg/apache/hadoop/hbase/client/Scan;
     213: pop
     214: getstatic     #24                 // Field table:Lorg/apache/hadoop/hbase/client/Table;
     217: aload_2
     218: invokeinterface #106,  2          // InterfaceMethod org/apache/hadoop/hbase/client/Table.getScanner:(Lorg/apache/hadoop/hbase/client/Scan;)Lorg/apache/hadoop/hbase/client/ResultScanner;
     223: astore_3
     224: aconst_null
     225: astore        4
     227: iconst_0
     228: istore_1
     229: aload_3
     230: invokeinterface #107,  1          // InterfaceMethod org/apache/hadoop/hbase/client/ResultScanner.iterator:()Ljava/util/Iterator;
     235: astore        5
     237: aload         5
     239: invokeinterface #72,  1           // InterfaceMethod java/util/Iterator.hasNext:()Z
     244: ifeq          265
     247: aload         5
     249: invokeinterface #73,  1           // InterfaceMethod java/util/Iterator.next:()Ljava/lang/Object;
     254: checkcast     #108                // class org/apache/hadoop/hbase/client/Result
     257: astore        6
     259: iinc          1, 1
     262: goto          237
     265: iload_1
     266: i2l
     267: lconst_1
     268: ldc2_w        #140                // long 2l
     271: invokestatic  #111                // Method testReadRequests:(JJJ)V
     274: aload_3
     275: ifnull        363
     278: aload         4
     280: ifnull        304
     283: aload_3
     284: invokeinterface #112,  1          // InterfaceMethod org/apache/hadoop/hbase/client/ResultScanner.close:()V
     289: goto          363
     292: astore        5
     294: aload         4
     296: aload         5
     298: invokevirtual #114                // Method java/lang/Throwable.addSuppressed:(Ljava/lang/Throwable;)V
     301: goto          363
     304: aload_3
     305: invokeinterface #112,  1          // InterfaceMethod org/apache/hadoop/hbase/client/ResultScanner.close:()V
     310: goto          363
     313: astore        5
     315: aload         5
     317: astore        4
     319: aload         5
     321: athrow
     322: astore        9
     324: aload_3
     325: ifnull        360
     328: aload         4
     330: ifnull        354
     333: aload_3
     334: invokeinterface #112,  1          // InterfaceMethod org/apache/hadoop/hbase/client/ResultScanner.close:()V
     339: goto          360
     342: astore        10
     344: aload         4
     346: aload         10
     348: invokevirtual #114                // Method java/lang/Throwable.addSuppressed:(Ljava/lang/Throwable;)V
     351: goto          360
     354: aload_3
     355: invokeinterface #112,  1          // InterfaceMethod org/apache/hadoop/hbase/client/ResultScanner.close:()V
     360: aload         9
     362: athrow
     363: new           #104                // class org/apache/hadoop/hbase/client/Scan
     366: dup
     367: getstatic     #2                  // Field ROW2:[B
     370: getstatic     #1                  // Field ROW3:[B
     373: invokespecial #115                // Method org/apache/hadoop/hbase/client/Scan."<init>":([B[B)V
     376: astore_2
     377: aload_2
     378: new           #142                // class org/apache/hadoop/hbase/filter/RowFilter
     381: dup
     382: getstatic     #137                // Field org/apache/hadoop/hbase/CompareOperator.EQUAL:Lorg/apache/hadoop/hbase/CompareOperator;
     385: new           #143                // class org/apache/hadoop/hbase/filter/BinaryComparator
     388: dup
     389: getstatic     #6                  // Field ROW1:[B
     392: invokespecial #144                // Method org/apache/hadoop/hbase/filter/BinaryComparator."<init>":([B)V
     395: invokespecial #145                // Method org/apache/hadoop/hbase/filter/RowFilter."<init>":(Lorg/apache/hadoop/hbase/CompareOperator;Lorg/apache/hadoop/hbase/filter/ByteArrayComparable;)V
     398: invokevirtual #139                // Method org/apache/hadoop/hbase/client/Scan.setFilter:(Lorg/apache/hadoop/hbase/filter/Filter;)Lorg/apache/hadoop/hbase/client/Scan;
     401: pop
     402: getstatic     #24                 // Field table:Lorg/apache/hadoop/hbase/client/Table;
     405: aload_2
     406: invokeinterface #106,  2          // InterfaceMethod org/apache/hadoop/hbase/client/Table.getScanner:(Lorg/apache/hadoop/hbase/client/Scan;)Lorg/apache/hadoop/hbase/client/ResultScanner;
     411: astore_3
     412: aconst_null
     413: astore        4
     415: iconst_0
     416: istore_1
     417: aload_3
     418: invokeinterface #107,  1          // InterfaceMethod org/apache/hadoop/hbase/client/ResultScanner.iterator:()Ljava/util/Iterator;
     423: astore        5
     425: aload         5
     427: invokeinterface #72,  1           // InterfaceMethod java/util/Iterator.hasNext:()Z
     432: ifeq          453
     435: aload         5
     437: invokeinterface #73,  1           // InterfaceMethod java/util/Iterator.next:()Ljava/lang/Object;
     442: checkcast     #108                // class org/apache/hadoop/hbase/client/Result
     445: astore        6
     447: iinc          1, 1
     450: goto          425
     453: iload_1
     454: i2l
     455: lconst_0
     456: lconst_1
     457: invokestatic  #111                // Method testReadRequests:(JJJ)V
     460: aload_3
     461: ifnull        549
     464: aload         4
     466: ifnull        490
     469: aload_3
     470: invokeinterface #112,  1          // InterfaceMethod org/apache/hadoop/hbase/client/ResultScanner.close:()V
     475: goto          549
     478: astore        5
     480: aload         4
     482: aload         5
     484: invokevirtual #114                // Method java/lang/Throwable.addSuppressed:(Ljava/lang/Throwable;)V
     487: goto          549
     490: aload_3
     491: invokeinterface #112,  1          // InterfaceMethod org/apache/hadoop/hbase/client/ResultScanner.close:()V
     496: goto          549
     499: astore        5
     501: aload         5
     503: astore        4
     505: aload         5
     507: athrow
     508: astore        11
     510: aload_3
     511: ifnull        546
     514: aload         4
     516: ifnull        540
     519: aload_3
     520: invokeinterface #112,  1          // InterfaceMethod org/apache/hadoop/hbase/client/ResultScanner.close:()V
     525: goto          546
     528: astore        12
     530: aload         4
     532: aload         12
     534: invokevirtual #114                // Method java/lang/Throwable.addSuppressed:(Ljava/lang/Throwable;)V
     537: goto          546
     540: aload_3
     541: invokeinterface #112,  1          // InterfaceMethod org/apache/hadoop/hbase/client/ResultScanner.close:()V
     546: aload         11
     548: athrow
     549: return
    Exception table:
       from    to  target type
         101   107   110   Class java/lang/Throwable
          45    92   131   Class java/lang/Throwable
          45    92   140   any
         151   157   160   Class java/lang/Throwable
         131   142   140   any
         283   289   292   Class java/lang/Throwable
         227   274   313   Class java/lang/Throwable
         227   274   322   any
         333   339   342   Class java/lang/Throwable
         313   324   322   any
         469   475   478   Class java/lang/Throwable
         415   460   499   Class java/lang/Throwable
         415   460   508   any
         519   525   528   Class java/lang/Throwable
         499   510   508   any

  public void testReadRequestsCountWithDeletedRow() throws java.lang.Exception;
    Code:
       0: new           #146                // class org/apache/hadoop/hbase/client/Delete
       3: dup
       4: getstatic     #1                  // Field ROW3:[B
       7: invokespecial #147                // Method org/apache/hadoop/hbase/client/Delete."<init>":([B)V
      10: astore_1
      11: getstatic     #24                 // Field table:Lorg/apache/hadoop/hbase/client/Table;
      14: aload_1
      15: invokeinterface #148,  2          // InterfaceMethod org/apache/hadoop/hbase/client/Table.delete:(Lorg/apache/hadoop/hbase/client/Delete;)V
      20: new           #104                // class org/apache/hadoop/hbase/client/Scan
      23: dup
      24: invokespecial #105                // Method org/apache/hadoop/hbase/client/Scan."<init>":()V
      27: astore_2
      28: getstatic     #24                 // Field table:Lorg/apache/hadoop/hbase/client/Table;
      31: aload_2
      32: invokeinterface #106,  2          // InterfaceMethod org/apache/hadoop/hbase/client/Table.getScanner:(Lorg/apache/hadoop/hbase/client/Scan;)Lorg/apache/hadoop/hbase/client/ResultScanner;
      37: astore_3
      38: aconst_null
      39: astore        4
      41: iconst_0
      42: istore        5
      44: aload_3
      45: invokeinterface #107,  1          // InterfaceMethod org/apache/hadoop/hbase/client/ResultScanner.iterator:()Ljava/util/Iterator;
      50: astore        6
      52: aload         6
      54: invokeinterface #72,  1           // InterfaceMethod java/util/Iterator.hasNext:()Z
      59: ifeq          80
      62: aload         6
      64: invokeinterface #73,  1           // InterfaceMethod java/util/Iterator.next:()Ljava/lang/Object;
      69: checkcast     #108                // class org/apache/hadoop/hbase/client/Result
      72: astore        7
      74: iinc          5, 1
      77: goto          52
      80: iload         5
      82: i2l
      83: ldc2_w        #140                // long 2l
      86: lconst_1
      87: invokestatic  #111                // Method testReadRequests:(JJJ)V
      90: aload_3
      91: ifnull        179
      94: aload         4
      96: ifnull        120
      99: aload_3
     100: invokeinterface #112,  1          // InterfaceMethod org/apache/hadoop/hbase/client/ResultScanner.close:()V
     105: goto          179
     108: astore        5
     110: aload         4
     112: aload         5
     114: invokevirtual #114                // Method java/lang/Throwable.addSuppressed:(Ljava/lang/Throwable;)V
     117: goto          179
     120: aload_3
     121: invokeinterface #112,  1          // InterfaceMethod org/apache/hadoop/hbase/client/ResultScanner.close:()V
     126: goto          179
     129: astore        5
     131: aload         5
     133: astore        4
     135: aload         5
     137: athrow
     138: astore        8
     140: aload_3
     141: ifnull        176
     144: aload         4
     146: ifnull        170
     149: aload_3
     150: invokeinterface #112,  1          // InterfaceMethod org/apache/hadoop/hbase/client/ResultScanner.close:()V
     155: goto          176
     158: astore        9
     160: aload         4
     162: aload         9
     164: invokevirtual #114                // Method java/lang/Throwable.addSuppressed:(Ljava/lang/Throwable;)V
     167: goto          176
     170: aload_3
     171: invokeinterface #112,  1          // InterfaceMethod org/apache/hadoop/hbase/client/ResultScanner.close:()V
     176: aload         8
     178: athrow
     179: new           #93                 // class org/apache/hadoop/hbase/client/Put
     182: dup
     183: getstatic     #1                  // Field ROW3:[B
     186: invokespecial #94                 // Method org/apache/hadoop/hbase/client/Put."<init>":([B)V
     189: astore_1
     190: aload_1
     191: getstatic     #5                  // Field CF1:[B
     194: getstatic     #4                  // Field COL1:[B
     197: getstatic     #3                  // Field VAL1:[B
     200: invokevirtual #95                 // Method org/apache/hadoop/hbase/client/Put.addColumn:([B[B[B)Lorg/apache/hadoop/hbase/client/Put;
     203: pop
     204: aload_1
     205: getstatic     #5                  // Field CF1:[B
     208: getstatic     #96                 // Field COL2:[B
     211: getstatic     #97                 // Field VAL2:[B
     214: invokevirtual #95                 // Method org/apache/hadoop/hbase/client/Put.addColumn:([B[B[B)Lorg/apache/hadoop/hbase/client/Put;
     217: pop
     218: getstatic     #24                 // Field table:Lorg/apache/hadoop/hbase/client/Table;
     221: aload_1
     222: invokeinterface #100,  2          // InterfaceMethod org/apache/hadoop/hbase/client/Table.put:(Lorg/apache/hadoop/hbase/client/Put;)V
     227: goto          287
     230: astore        10
     232: new           #93                 // class org/apache/hadoop/hbase/client/Put
     235: dup
     236: getstatic     #1                  // Field ROW3:[B
     239: invokespecial #94                 // Method org/apache/hadoop/hbase/client/Put."<init>":([B)V
     242: astore        11
     244: aload         11
     246: getstatic     #5                  // Field CF1:[B
     249: getstatic     #4                  // Field COL1:[B
     252: getstatic     #3                  // Field VAL1:[B
     255: invokevirtual #95                 // Method org/apache/hadoop/hbase/client/Put.addColumn:([B[B[B)Lorg/apache/hadoop/hbase/client/Put;
     258: pop
     259: aload         11
     261: getstatic     #5                  // Field CF1:[B
     264: getstatic     #96                 // Field COL2:[B
     267: getstatic     #97                 // Field VAL2:[B
     270: invokevirtual #95                 // Method org/apache/hadoop/hbase/client/Put.addColumn:([B[B[B)Lorg/apache/hadoop/hbase/client/Put;
     273: pop
     274: getstatic     #24                 // Field table:Lorg/apache/hadoop/hbase/client/Table;
     277: aload         11
     279: invokeinterface #100,  2          // InterfaceMethod org/apache/hadoop/hbase/client/Table.put:(Lorg/apache/hadoop/hbase/client/Put;)V
     284: aload         10
     286: athrow
     287: return
    Exception table:
       from    to  target type
          99   105   108   Class java/lang/Throwable
          41    90   129   Class java/lang/Throwable
          41    90   138   any
         149   155   158   Class java/lang/Throwable
         129   140   138   any
           0   179   230   any
         230   232   230   any

  public void testReadRequestsCountWithTTLExpiration() throws java.lang.Exception;
    Code:
       0: invokestatic  #149                // Method putTTLExpiredData:()V
       3: new           #104                // class org/apache/hadoop/hbase/client/Scan
       6: dup
       7: invokespecial #105                // Method org/apache/hadoop/hbase/client/Scan."<init>":()V
      10: astore_1
      11: aload_1
      12: getstatic     #48                 // Field CF2:[B
      15: invokevirtual #150                // Method org/apache/hadoop/hbase/client/Scan.addFamily:([B)Lorg/apache/hadoop/hbase/client/Scan;
      18: pop
      19: getstatic     #24                 // Field table:Lorg/apache/hadoop/hbase/client/Table;
      22: aload_1
      23: invokeinterface #106,  2          // InterfaceMethod org/apache/hadoop/hbase/client/Table.getScanner:(Lorg/apache/hadoop/hbase/client/Scan;)Lorg/apache/hadoop/hbase/client/ResultScanner;
      28: astore_2
      29: aconst_null
      30: astore_3
      31: iconst_0
      32: istore        4
      34: aload_2
      35: invokeinterface #107,  1          // InterfaceMethod org/apache/hadoop/hbase/client/ResultScanner.iterator:()Ljava/util/Iterator;
      40: astore        5
      42: aload         5
      44: invokeinterface #72,  1           // InterfaceMethod java/util/Iterator.hasNext:()Z
      49: ifeq          70
      52: aload         5
      54: invokeinterface #73,  1           // InterfaceMethod java/util/Iterator.next:()Ljava/lang/Object;
      59: checkcast     #108                // class org/apache/hadoop/hbase/client/Result
      62: astore        6
      64: iinc          4, 1
      67: goto          42
      70: iload         4
      72: i2l
      73: ldc2_w        #140                // long 2l
      76: lconst_1
      77: invokestatic  #111                // Method testReadRequests:(JJJ)V
      80: aload_2
      81: ifnull        164
      84: aload_3
      85: ifnull        108
      88: aload_2
      89: invokeinterface #112,  1          // InterfaceMethod org/apache/hadoop/hbase/client/ResultScanner.close:()V
      94: goto          164
      97: astore        4
      99: aload_3
     100: aload         4
     102: invokevirtual #114                // Method java/lang/Throwable.addSuppressed:(Ljava/lang/Throwable;)V
     105: goto          164
     108: aload_2
     109: invokeinterface #112,  1          // InterfaceMethod org/apache/hadoop/hbase/client/ResultScanner.close:()V
     114: goto          164
     117: astore        4
     119: aload         4
     121: astore_3
     122: aload         4
     124: athrow
     125: astore        7
     127: aload_2
     128: ifnull        161
     131: aload_3
     132: ifnull        155
     135: aload_2
     136: invokeinterface #112,  1          // InterfaceMethod org/apache/hadoop/hbase/client/ResultScanner.close:()V
     141: goto          161
     144: astore        8
     146: aload_3
     147: aload         8
     149: invokevirtual #114                // Method java/lang/Throwable.addSuppressed:(Ljava/lang/Throwable;)V
     152: goto          161
     155: aload_2
     156: invokeinterface #112,  1          // InterfaceMethod org/apache/hadoop/hbase/client/ResultScanner.close:()V
     161: aload         7
     163: athrow
     164: return
    Exception table:
       from    to  target type
          88    94    97   Class java/lang/Throwable
          31    80   117   Class java/lang/Throwable
          31    80   125   any
         135   141   144   Class java/lang/Throwable
         117   127   125   any

  public void testReadRequestsWithCoprocessor() throws java.lang.Exception;
    Code:
       0: ldc           #151                // String testReadRequestsWithCoprocessor
       2: invokestatic  #152                // Method org/apache/hadoop/hbase/TableName.valueOf:(Ljava/lang/String;)Lorg/apache/hadoop/hbase/TableName;
       5: astore_1
       6: aload_1
       7: invokestatic  #45                 // Method org/apache/hadoop/hbase/client/TableDescriptorBuilder.newBuilder:(Lorg/apache/hadoop/hbase/TableName;)Lorg/apache/hadoop/hbase/client/TableDescriptorBuilder;
      10: astore_2
      11: aload_2
      12: getstatic     #5                  // Field CF1:[B
      15: invokestatic  #46                 // Method org/apache/hadoop/hbase/client/ColumnFamilyDescriptorBuilder.of:([B)Lorg/apache/hadoop/hbase/client/ColumnFamilyDescriptor;
      18: invokevirtual #47                 // Method org/apache/hadoop/hbase/client/TableDescriptorBuilder.setColumnFamily:(Lorg/apache/hadoop/hbase/client/ColumnFamilyDescriptor;)Lorg/apache/hadoop/hbase/client/TableDescriptorBuilder;
      21: pop
      22: aload_2
      23: ldc           #153                // class org/apache/hadoop/hbase/regionserver/TestRegionServerReadRequestMetrics$ScanRegionCoprocessor
      25: invokevirtual #154                // Method java/lang/Class.getName:()Ljava/lang/String;
      28: invokevirtual #155                // Method org/apache/hadoop/hbase/client/TableDescriptorBuilder.setCoprocessor:(Ljava/lang/String;)Lorg/apache/hadoop/hbase/client/TableDescriptorBuilder;
      31: pop
      32: getstatic     #16                 // Field admin:Lorg/apache/hadoop/hbase/client/Admin;
      35: aload_2
      36: invokevirtual #53                 // Method org/apache/hadoop/hbase/client/TableDescriptorBuilder.build:()Lorg/apache/hadoop/hbase/client/TableDescriptor;
      39: invokeinterface #54,  2           // InterfaceMethod org/apache/hadoop/hbase/client/Admin.createTable:(Lorg/apache/hadoop/hbase/client/TableDescriptor;)V
      44: getstatic     #9                  // Field TEST_UTIL:Lorg/apache/hadoop/hbase/HBaseTestingUtility;
      47: aload_1
      48: invokevirtual #156                // Method org/apache/hadoop/hbase/HBaseTestingUtility.waitTableAvailable:(Lorg/apache/hadoop/hbase/TableName;)V
      51: getstatic     #16                 // Field admin:Lorg/apache/hadoop/hbase/client/Admin;
      54: aload_1
      55: invokeinterface #27,  2           // InterfaceMethod org/apache/hadoop/hbase/client/Admin.getRegions:(Lorg/apache/hadoop/hbase/TableName;)Ljava/util/List;
      60: astore_3
      61: new           #28                 // class java/lang/StringBuilder
      64: dup
      65: invokespecial #29                 // Method java/lang/StringBuilder."<init>":()V
      68: ldc           #30                 // String Table
      70: invokevirtual #31                 // Method java/lang/StringBuilder.append:(Ljava/lang/String;)Ljava/lang/StringBuilder;
      73: getstatic     #26                 // Field TABLE_NAME:Lorg/apache/hadoop/hbase/TableName;
      76: invokevirtual #32                 // Method java/lang/StringBuilder.append:(Ljava/lang/Object;)Ljava/lang/StringBuilder;
      79: ldc           #33                 // String  should have 1 region
      81: invokevirtual #31                 // Method java/lang/StringBuilder.append:(Ljava/lang/String;)Ljava/lang/StringBuilder;
      84: invokevirtual #34                 // Method java/lang/StringBuilder.toString:()Ljava/lang/String;
      87: lconst_1
      88: aload_3
      89: invokeinterface #35,  1           // InterfaceMethod java/util/List.size:()I
      94: i2l
      95: invokestatic  #36                 // Method org/junit/Assert.assertEquals:(Ljava/lang/String;JJ)V
      98: iconst_1
      99: istore        4
     101: iconst_0
     102: istore        5
     104: iload         5
     106: bipush        20
     108: if_icmpge     194
     111: aload_0
     112: aload_3
     113: iconst_0
     114: invokeinterface #37,  2           // InterfaceMethod java/util/List.get:(I)Ljava/lang/Object;
     119: checkcast     #38                 // class org/apache/hadoop/hbase/client/RegionInfo
     122: invokeinterface #79,  1           // InterfaceMethod org/apache/hadoop/hbase/client/RegionInfo.getRegionName:()[B
     127: iconst_3
     128: invokespecial #157                // Method testReadRequests:([BI)V
     131: goto          180
     134: astore        6
     136: getstatic     #7                  // Field LOG:Lorg/slf4j/Logger;
     139: new           #28                 // class java/lang/StringBuilder
     142: dup
     143: invokespecial #29                 // Method java/lang/StringBuilder."<init>":()V
     146: ldc           #158                // String Got exception when try
     148: invokevirtual #31                 // Method java/lang/StringBuilder.append:(Ljava/lang/String;)Ljava/lang/StringBuilder;
     151: iload         5
     153: invokevirtual #159                // Method java/lang/StringBuilder.append:(I)Ljava/lang/StringBuilder;
     156: ldc           #160                // String  times
     158: invokevirtual #31                 // Method java/lang/StringBuilder.append:(Ljava/lang/String;)Ljava/lang/StringBuilder;
     161: invokevirtual #34                 // Method java/lang/StringBuilder.toString:()Ljava/lang/String;
     164: aload         6
     166: invokeinterface #161,  3          // InterfaceMethod org/slf4j/Logger.warn:(Ljava/lang/String;Ljava/lang/Throwable;)V
     171: ldc2_w        #82                 // long 100l
     174: invokestatic  #84                 // Method java/lang/Thread.sleep:(J)V
     177: iconst_0
     178: istore        4
     180: iload         4
     182: ifeq          188
     185: goto          194
     188: iinc          5, 1
     191: goto          104
     194: iload         5
     196: bipush        20
     198: if_icmpne     229
     201: new           #28                 // class java/lang/StringBuilder
     204: dup
     205: invokespecial #29                 // Method java/lang/StringBuilder."<init>":()V
     208: ldc           #162                // String Failed to get right read requests metric after try
     210: invokevirtual #31                 // Method java/lang/StringBuilder.append:(Ljava/lang/String;)Ljava/lang/StringBuilder;
     213: iload         5
     215: invokevirtual #159                // Method java/lang/StringBuilder.append:(I)Ljava/lang/StringBuilder;
     218: ldc           #160                // String  times
     220: invokevirtual #31                 // Method java/lang/StringBuilder.append:(Ljava/lang/String;)Ljava/lang/StringBuilder;
     223: invokevirtual #34                 // Method java/lang/StringBuilder.toString:()Ljava/lang/String;
     226: invokestatic  #163                // Method org/junit/Assert.fail:(Ljava/lang/String;)V
     229: getstatic     #16                 // Field admin:Lorg/apache/hadoop/hbase/client/Admin;
     232: aload_1
     233: invokeinterface #164,  2          // InterfaceMethod org/apache/hadoop/hbase/client/Admin.disableTable:(Lorg/apache/hadoop/hbase/TableName;)V
     238: getstatic     #16                 // Field admin:Lorg/apache/hadoop/hbase/client/Admin;
     241: aload_1
     242: invokeinterface #165,  2          // InterfaceMethod org/apache/hadoop/hbase/client/Admin.deleteTable:(Lorg/apache/hadoop/hbase/TableName;)V
     247: goto          273
     250: astore        7
     252: getstatic     #16                 // Field admin:Lorg/apache/hadoop/hbase/client/Admin;
     255: aload_1
     256: invokeinterface #164,  2          // InterfaceMethod org/apache/hadoop/hbase/client/Admin.disableTable:(Lorg/apache/hadoop/hbase/TableName;)V
     261: getstatic     #16                 // Field admin:Lorg/apache/hadoop/hbase/client/Admin;
     264: aload_1
     265: invokeinterface #165,  2          // InterfaceMethod org/apache/hadoop/hbase/client/Admin.deleteTable:(Lorg/apache/hadoop/hbase/TableName;)V
     270: aload         7
     272: athrow
     273: return
    Exception table:
       from    to  target type
         111   131   134   Class java/lang/Throwable
          44   229   250   any
         250   252   250   any

  static org.slf4j.Logger access$000();
    Code:
       0: getstatic     #7                  // Field LOG:Lorg/slf4j/Logger;
       3: areturn

  static byte[] access$100();
    Code:
       0: getstatic     #6                  // Field ROW1:[B
       3: areturn

  static byte[] access$200();
    Code:
       0: getstatic     #5                  // Field CF1:[B
       3: areturn

  static byte[] access$300();
    Code:
       0: getstatic     #4                  // Field COL1:[B
       3: areturn

  static byte[] access$400();
    Code:
       0: getstatic     #3                  // Field VAL1:[B
       3: areturn

  static byte[] access$500();
    Code:
       0: getstatic     #2                  // Field ROW2:[B
       3: areturn

  static byte[] access$600();
    Code:
       0: getstatic     #1                  // Field ROW3:[B
       3: areturn

  static {};
    Code:
       0: ldc           #50                 // class org/apache/hadoop/hbase/regionserver/TestRegionServerReadRequestMetrics
       2: invokestatic  #170                // Method org/apache/hadoop/hbase/HBaseClassTestRule.forClass:(Ljava/lang/Class;)Lorg/apache/hadoop/hbase/HBaseClassTestRule;
       5: putstatic     #171                // Field CLASS_RULE:Lorg/apache/hadoop/hbase/HBaseClassTestRule;
       8: ldc           #50                 // class org/apache/hadoop/hbase/regionserver/TestRegionServerReadRequestMetrics
      10: invokestatic  #172                // Method org/slf4j/LoggerFactory.getLogger:(Ljava/lang/Class;)Lorg/slf4j/Logger;
      13: putstatic     #7                  // Field LOG:Lorg/slf4j/Logger;
      16: new           #173                // class org/apache/hadoop/hbase/HBaseTestingUtility
      19: dup
      20: invokespecial #174                // Method org/apache/hadoop/hbase/HBaseTestingUtility."<init>":()V
      23: putstatic     #9                  // Field TEST_UTIL:Lorg/apache/hadoop/hbase/HBaseTestingUtility;
      26: ldc           #175                // String test
      28: invokestatic  #152                // Method org/apache/hadoop/hbase/TableName.valueOf:(Ljava/lang/String;)Lorg/apache/hadoop/hbase/TableName;
      31: putstatic     #26                 // Field TABLE_NAME:Lorg/apache/hadoop/hbase/TableName;
      34: ldc           #176                // String c1
      36: invokestatic  #177                // Method org/apache/hadoop/hbase/util/Bytes.toBytes:(Ljava/lang/String;)[B
      39: putstatic     #5                  // Field CF1:[B
      42: ldc           #178                // String c2
      44: invokestatic  #177                // Method org/apache/hadoop/hbase/util/Bytes.toBytes:(Ljava/lang/String;)[B
      47: putstatic     #48                 // Field CF2:[B
      50: ldc           #179                // String a
      52: invokestatic  #177                // Method org/apache/hadoop/hbase/util/Bytes.toBytes:(Ljava/lang/String;)[B
      55: putstatic     #6                  // Field ROW1:[B
      58: ldc           #180                // String b
      60: invokestatic  #177                // Method org/apache/hadoop/hbase/util/Bytes.toBytes:(Ljava/lang/String;)[B
      63: putstatic     #2                  // Field ROW2:[B
      66: ldc           #181                // String c
      68: invokestatic  #177                // Method org/apache/hadoop/hbase/util/Bytes.toBytes:(Ljava/lang/String;)[B
      71: putstatic     #1                  // Field ROW3:[B
      74: ldc           #182                // String q1
      76: invokestatic  #177                // Method org/apache/hadoop/hbase/util/Bytes.toBytes:(Ljava/lang/String;)[B
      79: putstatic     #4                  // Field COL1:[B
      82: ldc           #183                // String q2
      84: invokestatic  #177                // Method org/apache/hadoop/hbase/util/Bytes.toBytes:(Ljava/lang/String;)[B
      87: putstatic     #96                 // Field COL2:[B
      90: ldc           #184                // String q3
      92: invokestatic  #177                // Method org/apache/hadoop/hbase/util/Bytes.toBytes:(Ljava/lang/String;)[B
      95: putstatic     #98                 // Field COL3:[B
      98: ldc           #185                // String v1
     100: invokestatic  #177                // Method org/apache/hadoop/hbase/util/Bytes.toBytes:(Ljava/lang/String;)[B
     103: putstatic     #3                  // Field VAL1:[B
     106: ldc           #186                // String v2
     108: invokestatic  #177                // Method org/apache/hadoop/hbase/util/Bytes.toBytes:(Ljava/lang/String;)[B
     111: putstatic     #97                 // Field VAL2:[B
     114: lconst_0
     115: invokestatic  #187                // Method org/apache/hadoop/hbase/util/Bytes.toBytes:(J)[B
     118: putstatic     #99                 // Field VAL3:[B
     121: new           #188                // class java/util/HashMap
     124: dup
     125: invokespecial #189                // Method java/util/HashMap."<init>":()V
     128: putstatic     #41                 // Field requestsMap:Ljava/util/Map;
     131: new           #188                // class java/util/HashMap
     134: dup
     135: invokespecial #189                // Method java/util/HashMap."<init>":()V
     138: putstatic     #44                 // Field requestsMapPrev:Ljava/util/Map;
     141: return
}
