Compiled from "TestFromClientSide3.java"
public class org.apache.hadoop.hbase.client.TestFromClientSide3$WaitingForMultiMutationsObserver implements org.apache.hadoop.hbase.coprocessor.RegionCoprocessor,org.apache.hadoop.hbase.coprocessor.RegionObserver {
  final java.util.concurrent.CountDownLatch latch;

  public org.apache.hadoop.hbase.client.TestFromClientSide3$WaitingForMultiMutationsObserver();
    Code:
       0: aload_0
       1: invokespecial #1                  // Method java/lang/Object."<init>":()V
       4: aload_0
       5: new           #2                  // class java/util/concurrent/CountDownLatch
       8: dup
       9: iconst_1
      10: invokespecial #3                  // Method java/util/concurrent/CountDownLatch."<init>":(I)V
      13: putfield      #4                  // Field latch:Ljava/util/concurrent/CountDownLatch;
      16: return

  public java.util.Optional<org.apache.hadoop.hbase.coprocessor.RegionObserver> getRegionObserver();
    Code:
       0: aload_0
       1: invokestatic  #5                  // Method java/util/Optional.of:(Ljava/lang/Object;)Ljava/util/Optional;
       4: areturn

  public void postBatchMutate(org.apache.hadoop.hbase.coprocessor.ObserverContext<org.apache.hadoop.hbase.coprocessor.RegionCoprocessorEnvironment>, org.apache.hadoop.hbase.regionserver.MiniBatchOperationInProgress<org.apache.hadoop.hbase.client.Mutation>) throws java.io.IOException;
    Code:
       0: aload_0
       1: getfield      #4                  // Field latch:Ljava/util/concurrent/CountDownLatch;
       4: invokevirtual #6                  // Method java/util/concurrent/CountDownLatch.await:()V
       7: goto          20
      10: astore_3
      11: new           #8                  // class java/io/IOException
      14: dup
      15: aload_3
      16: invokespecial #9                  // Method java/io/IOException."<init>":(Ljava/lang/Throwable;)V
      19: athrow
      20: return
    Exception table:
       from    to  target type
           0     7    10   Class java/lang/InterruptedException
}
