Compiled from "TestCustomWALCellCodec.java"
public class org.apache.hadoop.hbase.regionserver.wal.TestCustomWALCellCodec {
  public static final org.apache.hadoop.hbase.HBaseClassTestRule CLASS_RULE;

  public org.apache.hadoop.hbase.regionserver.wal.TestCustomWALCellCodec();
    Code:
       0: aload_0
       1: invokespecial #1                  // Method java/lang/Object."<init>":()V
       4: return

  public void testCreatePreparesCodec() throws java.lang.Exception;
    Code:
       0: new           #2                  // class org/apache/hadoop/conf/Configuration
       3: dup
       4: iconst_0
       5: invokespecial #3                  // Method org/apache/hadoop/conf/Configuration."<init>":(Z)V
       8: astore_1
       9: aload_1
      10: ldc           #5                  // String hbase.regionserver.wal.codec
      12: ldc           #6                  // class org/apache/hadoop/hbase/regionserver/wal/TestCustomWALCellCodec$CustomWALCellCodec
      14: ldc           #4                  // class org/apache/hadoop/hbase/regionserver/wal/WALCellCodec
      16: invokevirtual #7                  // Method org/apache/hadoop/conf/Configuration.setClass:(Ljava/lang/String;Ljava/lang/Class;Ljava/lang/Class;)V
      19: aload_1
      20: aconst_null
      21: aconst_null
      22: invokestatic  #8                  // Method org/apache/hadoop/hbase/regionserver/wal/WALCellCodec.create:(Lorg/apache/hadoop/conf/Configuration;Ljava/lang/String;Lorg/apache/hadoop/hbase/regionserver/wal/CompressionContext;)Lorg/apache/hadoop/hbase/regionserver/wal/WALCellCodec;
      25: checkcast     #6                  // class org/apache/hadoop/hbase/regionserver/wal/TestCustomWALCellCodec$CustomWALCellCodec
      28: astore_2
      29: ldc           #9                  // String Custom codec didn't get initialized with the right configuration!
      31: aload_1
      32: aload_2
      33: getfield      #10                 // Field org/apache/hadoop/hbase/regionserver/wal/TestCustomWALCellCodec$CustomWALCellCodec.conf:Lorg/apache/hadoop/conf/Configuration;
      36: invokestatic  #11                 // Method org/junit/Assert.assertEquals:(Ljava/lang/String;Ljava/lang/Object;Ljava/lang/Object;)V
      39: ldc           #12                 // String Custom codec didn't get initialized with the right compression context!
      41: aconst_null
      42: aload_2
      43: getfield      #13                 // Field org/apache/hadoop/hbase/regionserver/wal/TestCustomWALCellCodec$CustomWALCellCodec.context:Lorg/apache/hadoop/hbase/regionserver/wal/CompressionContext;
      46: invokestatic  #11                 // Method org/junit/Assert.assertEquals:(Ljava/lang/String;Ljava/lang/Object;Ljava/lang/Object;)V
      49: return

  public void testCreatePreparesCodecInvalidClass() throws java.lang.Exception;
    Code:
       0: new           #2                  // class org/apache/hadoop/conf/Configuration
       3: dup
       4: iconst_0
       5: invokespecial #3                  // Method org/apache/hadoop/conf/Configuration."<init>":(Z)V
       8: astore_1
       9: aload_1
      10: ldc           #5                  // String hbase.regionserver.wal.codec
      12: iconst_1
      13: anewarray     #14                 // class java/lang/String
      16: dup
      17: iconst_0
      18: ldc           #15                 // String org.apache.hbase.wal.NoSuchClass
      20: aastore
      21: invokevirtual #16                 // Method org/apache/hadoop/conf/Configuration.setStrings:(Ljava/lang/String;[Ljava/lang/String;)V
      24: aload_1
      25: aconst_null
      26: aconst_null
      27: invokestatic  #8                  // Method org/apache/hadoop/hbase/regionserver/wal/WALCellCodec.create:(Lorg/apache/hadoop/conf/Configuration;Ljava/lang/String;Lorg/apache/hadoop/hbase/regionserver/wal/CompressionContext;)Lorg/apache/hadoop/hbase/regionserver/wal/WALCellCodec;
      30: pop
      31: return

  static {};
    Code:
       0: ldc           #17                 // class org/apache/hadoop/hbase/regionserver/wal/TestCustomWALCellCodec
       2: invokestatic  #18                 // Method org/apache/hadoop/hbase/HBaseClassTestRule.forClass:(Ljava/lang/Class;)Lorg/apache/hadoop/hbase/HBaseClassTestRule;
       5: putstatic     #19                 // Field CLASS_RULE:Lorg/apache/hadoop/hbase/HBaseClassTestRule;
       8: return
}
