Compiled from "TestClientNoCluster.java"
class org.apache.hadoop.hbase.client.TestClientNoCluster$RegionServerStoppedOnScannerOpenConnection extends org.apache.hadoop.hbase.client.ConnectionImplementation {
  final org.apache.hadoop.hbase.shaded.protobuf.generated.ClientProtos$ClientService$BlockingInterface stub;

  org.apache.hadoop.hbase.client.TestClientNoCluster$RegionServerStoppedOnScannerOpenConnection(org.apache.hadoop.conf.Configuration, java.util.concurrent.ExecutorService, org.apache.hadoop.hbase.security.User) throws java.io.IOException;
    Code:
       0: aload_0
       1: aload_1
       2: aload_2
       3: aload_3
       4: invokespecial #1                  // Method org/apache/hadoop/hbase/client/ConnectionImplementation."<init>":(Lorg/apache/hadoop/conf/Configuration;Ljava/util/concurrent/ExecutorService;Lorg/apache/hadoop/hbase/security/User;)V
       7: aload_0
       8: ldc           #2                  // class org/apache/hadoop/hbase/shaded/protobuf/generated/ClientProtos$ClientService$BlockingInterface
      10: invokestatic  #3                  // Method org/mockito/Mockito.mock:(Ljava/lang/Class;)Ljava/lang/Object;
      13: checkcast     #2                  // class org/apache/hadoop/hbase/shaded/protobuf/generated/ClientProtos$ClientService$BlockingInterface
      16: putfield      #4                  // Field stub:Lorg/apache/hadoop/hbase/shaded/protobuf/generated/ClientProtos$ClientService$BlockingInterface;
      19: ldc2_w        #5                  // long 12345l
      22: lstore        4
      24: aload_0
      25: getfield      #4                  // Field stub:Lorg/apache/hadoop/hbase/shaded/protobuf/generated/ClientProtos$ClientService$BlockingInterface;
      28: invokestatic  #7                  // Method org/mockito/Mockito.any:()Ljava/lang/Object;
      31: checkcast     #8                  // class org/apache/hbase/thirdparty/com/google/protobuf/RpcController
      34: invokestatic  #7                  // Method org/mockito/Mockito.any:()Ljava/lang/Object;
      37: checkcast     #9                  // class org/apache/hadoop/hbase/shaded/protobuf/generated/ClientProtos$ScanRequest
      40: invokeinterface #10,  3           // InterfaceMethod org/apache/hadoop/hbase/shaded/protobuf/generated/ClientProtos$ClientService$BlockingInterface.scan:(Lorg/apache/hbase/thirdparty/com/google/protobuf/RpcController;Lorg/apache/hadoop/hbase/shaded/protobuf/generated/ClientProtos$ScanRequest;)Lorg/apache/hadoop/hbase/shaded/protobuf/generated/ClientProtos$ScanResponse;
      45: invokestatic  #11                 // Method org/mockito/Mockito.when:(Ljava/lang/Object;)Lorg/mockito/stubbing/OngoingStubbing;
      48: invokestatic  #12                 // Method org/apache/hadoop/hbase/shaded/protobuf/generated/ClientProtos$ScanResponse.newBuilder:()Lorg/apache/hadoop/hbase/shaded/protobuf/generated/ClientProtos$ScanResponse$Builder;
      51: lload         4
      53: invokevirtual #13                 // Method org/apache/hadoop/hbase/shaded/protobuf/generated/ClientProtos$ScanResponse$Builder.setScannerId:(J)Lorg/apache/hadoop/hbase/shaded/protobuf/generated/ClientProtos$ScanResponse$Builder;
      56: invokevirtual #14                 // Method org/apache/hadoop/hbase/shaded/protobuf/generated/ClientProtos$ScanResponse$Builder.build:()Lorg/apache/hadoop/hbase/shaded/protobuf/generated/ClientProtos$ScanResponse;
      59: invokeinterface #15,  2           // InterfaceMethod org/mockito/stubbing/OngoingStubbing.thenReturn:(Ljava/lang/Object;)Lorg/mockito/stubbing/OngoingStubbing;
      64: iconst_1
      65: anewarray     #16                 // class java/lang/Throwable
      68: dup
      69: iconst_0
      70: new           #17                 // class org/apache/hbase/thirdparty/com/google/protobuf/ServiceException
      73: dup
      74: new           #18                 // class org/apache/hadoop/hbase/regionserver/RegionServerStoppedException
      77: dup
      78: ldc           #19                 // String From Mockito
      80: invokespecial #20                 // Method org/apache/hadoop/hbase/regionserver/RegionServerStoppedException."<init>":(Ljava/lang/String;)V
      83: invokespecial #21                 // Method org/apache/hbase/thirdparty/com/google/protobuf/ServiceException."<init>":(Ljava/lang/Throwable;)V
      86: aastore
      87: invokeinterface #22,  2           // InterfaceMethod org/mockito/stubbing/OngoingStubbing.thenThrow:([Ljava/lang/Throwable;)Lorg/mockito/stubbing/OngoingStubbing;
      92: invokestatic  #12                 // Method org/apache/hadoop/hbase/shaded/protobuf/generated/ClientProtos$ScanResponse.newBuilder:()Lorg/apache/hadoop/hbase/shaded/protobuf/generated/ClientProtos$ScanResponse$Builder;
      95: lload         4
      97: invokevirtual #13                 // Method org/apache/hadoop/hbase/shaded/protobuf/generated/ClientProtos$ScanResponse$Builder.setScannerId:(J)Lorg/apache/hadoop/hbase/shaded/protobuf/generated/ClientProtos$ScanResponse$Builder;
     100: iconst_0
     101: invokevirtual #23                 // Method org/apache/hadoop/hbase/shaded/protobuf/generated/ClientProtos$ScanResponse$Builder.setMoreResults:(Z)Lorg/apache/hadoop/hbase/shaded/protobuf/generated/ClientProtos$ScanResponse$Builder;
     104: invokevirtual #14                 // Method org/apache/hadoop/hbase/shaded/protobuf/generated/ClientProtos$ScanResponse$Builder.build:()Lorg/apache/hadoop/hbase/shaded/protobuf/generated/ClientProtos$ScanResponse;
     107: invokeinterface #15,  2           // InterfaceMethod org/mockito/stubbing/OngoingStubbing.thenReturn:(Ljava/lang/Object;)Lorg/mockito/stubbing/OngoingStubbing;
     112: pop
     113: goto          128
     116: astore        6
     118: new           #24                 // class java/io/IOException
     121: dup
     122: aload         6
     124: invokespecial #25                 // Method java/io/IOException."<init>":(Ljava/lang/Throwable;)V
     127: athrow
     128: return
    Exception table:
       from    to  target type
          24   113   116   Class org/apache/hbase/thirdparty/com/google/protobuf/ServiceException

  public org.apache.hadoop.hbase.shaded.protobuf.generated.ClientProtos$ClientService$BlockingInterface getClient(org.apache.hadoop.hbase.ServerName) throws java.io.IOException;
    Code:
       0: aload_0
       1: getfield      #4                  // Field stub:Lorg/apache/hadoop/hbase/shaded/protobuf/generated/ClientProtos$ClientService$BlockingInterface;
       4: areturn
}
