Compiled from "TestWithDisabledAuthorization.java"
class org.apache.hadoop.hbase.security.access.TestWithDisabledAuthorization$22 implements org.apache.hadoop.hbase.security.access.SecureTestUtil$AccessTestAction {
  final org.apache.hadoop.hbase.security.access.TestWithDisabledAuthorization this$0;

  org.apache.hadoop.hbase.security.access.TestWithDisabledAuthorization$22(org.apache.hadoop.hbase.security.access.TestWithDisabledAuthorization);
    Code:
       0: aload_0
       1: aload_1
       2: putfield      #1                  // Field this$0:Lorg/apache/hadoop/hbase/security/access/TestWithDisabledAuthorization;
       5: aload_0
       6: invokespecial #2                  // Method java/lang/Object."<init>":()V
       9: return

  public java.lang.Object run() throws java.lang.Exception;
    Code:
       0: new           #3                  // class org/apache/hadoop/hbase/HRegionInfo
       3: dup
       4: aload_0
       5: getfield      #1                  // Field this$0:Lorg/apache/hadoop/hbase/security/access/TestWithDisabledAuthorization;
       8: getfield      #4                  // Field org/apache/hadoop/hbase/security/access/TestWithDisabledAuthorization.TEST_TABLE:Lorg/apache/hadoop/hbase/TestTableName;
      11: invokevirtual #5                  // Method org/apache/hadoop/hbase/TestTableName.getTableName:()Lorg/apache/hadoop/hbase/TableName;
      14: invokespecial #6                  // Method org/apache/hadoop/hbase/HRegionInfo."<init>":(Lorg/apache/hadoop/hbase/TableName;)V
      17: astore_1
      18: ldc           #7                  // String 1.1.1.1
      20: iconst_1
      21: lconst_0
      22: invokestatic  #8                  // Method org/apache/hadoop/hbase/ServerName.valueOf:(Ljava/lang/String;IJ)Lorg/apache/hadoop/hbase/ServerName;
      25: astore_2
      26: ldc           #9                  // String 2.2.2.2
      28: iconst_2
      29: lconst_0
      30: invokestatic  #8                  // Method org/apache/hadoop/hbase/ServerName.valueOf:(Ljava/lang/String;IJ)Lorg/apache/hadoop/hbase/ServerName;
      33: astore_3
      34: invokestatic  #10                 // Method org/apache/hadoop/hbase/security/access/TestWithDisabledAuthorization.access$600:()Lorg/apache/hadoop/hbase/security/access/AccessController;
      37: invokestatic  #11                 // Method org/apache/hadoop/hbase/security/access/TestWithDisabledAuthorization.access$500:()Lorg/apache/hadoop/hbase/coprocessor/MasterCoprocessorEnvironment;
      40: invokestatic  #12                 // Method org/apache/hadoop/hbase/coprocessor/ObserverContextImpl.createAndPrepare:(Lorg/apache/hadoop/hbase/CoprocessorEnvironment;)Lorg/apache/hadoop/hbase/coprocessor/ObserverContext;
      43: aload_1
      44: aload_2
      45: aload_3
      46: invokevirtual #13                 // Method org/apache/hadoop/hbase/security/access/AccessController.preMove:(Lorg/apache/hadoop/hbase/coprocessor/ObserverContext;Lorg/apache/hadoop/hbase/client/RegionInfo;Lorg/apache/hadoop/hbase/ServerName;Lorg/apache/hadoop/hbase/ServerName;)V
      49: aconst_null
      50: areturn
}
