Compiled from "TestMetaTableAccessor.java"
public class org.apache.hadoop.hbase.TestMetaTableAccessor$SpyingRpcSchedulerFactory extends org.apache.hadoop.hbase.regionserver.SimpleRpcSchedulerFactory {
  public org.apache.hadoop.hbase.TestMetaTableAccessor$SpyingRpcSchedulerFactory();
    Code:
       0: aload_0
       1: invokespecial #1                  // Method org/apache/hadoop/hbase/regionserver/SimpleRpcSchedulerFactory."<init>":()V
       4: return

  public org.apache.hadoop.hbase.ipc.RpcScheduler create(org.apache.hadoop.conf.Configuration, org.apache.hadoop.hbase.ipc.PriorityFunction, org.apache.hadoop.hbase.Abortable);
    Code:
       0: aload_0
       1: aload_1
       2: aload_2
       3: aload_3
       4: invokespecial #2                  // Method org/apache/hadoop/hbase/regionserver/SimpleRpcSchedulerFactory.create:(Lorg/apache/hadoop/conf/Configuration;Lorg/apache/hadoop/hbase/ipc/PriorityFunction;Lorg/apache/hadoop/hbase/Abortable;)Lorg/apache/hadoop/hbase/ipc/RpcScheduler;
       7: astore        4
       9: new           #3                  // class org/apache/hadoop/hbase/TestMetaTableAccessor$SpyingRpcScheduler
      12: dup
      13: aload         4
      15: invokespecial #4                  // Method org/apache/hadoop/hbase/TestMetaTableAccessor$SpyingRpcScheduler."<init>":(Lorg/apache/hadoop/hbase/ipc/RpcScheduler;)V
      18: areturn
}
