Compiled from "TestRpcClientDeprecatedNameMapping.java"
public class org.apache.hadoop.hbase.ipc.TestRpcClientDeprecatedNameMapping {
  public static final org.apache.hadoop.hbase.HBaseClassTestRule CLASS_RULE;

  public org.apache.hadoop.hbase.ipc.TestRpcClientDeprecatedNameMapping();
    Code:
       0: aload_0
       1: invokespecial #1                  // Method java/lang/Object."<init>":()V
       4: return

  public void test();
    Code:
       0: invokestatic  #2                  // Method org/apache/hadoop/hbase/HBaseConfiguration.create:()Lorg/apache/hadoop/conf/Configuration;
       3: astore_1
       4: aload_1
       5: ldc           #4                  // String hbase.rpc.client.impl
       7: ldc           #5                  // class org/apache/hadoop/hbase/ipc/BlockingRpcClient
       9: invokevirtual #6                  // Method java/lang/Class.getName:()Ljava/lang/String;
      12: invokevirtual #7                  // Method org/apache/hadoop/conf/Configuration.set:(Ljava/lang/String;Ljava/lang/String;)V
      15: aload_1
      16: ldc           #9                  // String default-cluster
      18: invokestatic  #10                 // Method org/apache/hadoop/hbase/ipc/RpcClientFactory.createClient:(Lorg/apache/hadoop/conf/Configuration;Ljava/lang/String;)Lorg/apache/hadoop/hbase/ipc/RpcClient;
      21: astore_2
      22: aconst_null
      23: astore_3
      24: aload_2
      25: ldc           #5                  // class org/apache/hadoop/hbase/ipc/BlockingRpcClient
      27: invokestatic  #11                 // Method org/hamcrest/CoreMatchers.instanceOf:(Ljava/lang/Class;)Lorg/hamcrest/Matcher;
      30: invokestatic  #12                 // Method org/junit/Assert.assertThat:(Ljava/lang/Object;Lorg/hamcrest/Matcher;)V
      33: aload_2
      34: ifnull        117
      37: aload_3
      38: ifnull        61
      41: aload_2
      42: invokeinterface #13,  1           // InterfaceMethod org/apache/hadoop/hbase/ipc/RpcClient.close:()V
      47: goto          117
      50: astore        4
      52: aload_3
      53: aload         4
      55: invokevirtual #15                 // Method java/lang/Throwable.addSuppressed:(Ljava/lang/Throwable;)V
      58: goto          117
      61: aload_2
      62: invokeinterface #13,  1           // InterfaceMethod org/apache/hadoop/hbase/ipc/RpcClient.close:()V
      67: goto          117
      70: astore        4
      72: aload         4
      74: astore_3
      75: aload         4
      77: athrow
      78: astore        5
      80: aload_2
      81: ifnull        114
      84: aload_3
      85: ifnull        108
      88: aload_2
      89: invokeinterface #13,  1           // InterfaceMethod org/apache/hadoop/hbase/ipc/RpcClient.close:()V
      94: goto          114
      97: astore        6
      99: aload_3
     100: aload         6
     102: invokevirtual #15                 // Method java/lang/Throwable.addSuppressed:(Ljava/lang/Throwable;)V
     105: goto          114
     108: aload_2
     109: invokeinterface #13,  1           // InterfaceMethod org/apache/hadoop/hbase/ipc/RpcClient.close:()V
     114: aload         5
     116: athrow
     117: aload_1
     118: ldc           #4                  // String hbase.rpc.client.impl
     120: ldc           #16                 // String org.apache.hadoop.hbase.ipc.RpcClientImpl
     122: invokevirtual #7                  // Method org/apache/hadoop/conf/Configuration.set:(Ljava/lang/String;Ljava/lang/String;)V
     125: aload_1
     126: ldc           #9                  // String default-cluster
     128: invokestatic  #10                 // Method org/apache/hadoop/hbase/ipc/RpcClientFactory.createClient:(Lorg/apache/hadoop/conf/Configuration;Ljava/lang/String;)Lorg/apache/hadoop/hbase/ipc/RpcClient;
     131: astore_2
     132: aconst_null
     133: astore_3
     134: aload_2
     135: ldc           #5                  // class org/apache/hadoop/hbase/ipc/BlockingRpcClient
     137: invokestatic  #11                 // Method org/hamcrest/CoreMatchers.instanceOf:(Ljava/lang/Class;)Lorg/hamcrest/Matcher;
     140: invokestatic  #12                 // Method org/junit/Assert.assertThat:(Ljava/lang/Object;Lorg/hamcrest/Matcher;)V
     143: aload_2
     144: ifnull        227
     147: aload_3
     148: ifnull        171
     151: aload_2
     152: invokeinterface #13,  1           // InterfaceMethod org/apache/hadoop/hbase/ipc/RpcClient.close:()V
     157: goto          227
     160: astore        4
     162: aload_3
     163: aload         4
     165: invokevirtual #15                 // Method java/lang/Throwable.addSuppressed:(Ljava/lang/Throwable;)V
     168: goto          227
     171: aload_2
     172: invokeinterface #13,  1           // InterfaceMethod org/apache/hadoop/hbase/ipc/RpcClient.close:()V
     177: goto          227
     180: astore        4
     182: aload         4
     184: astore_3
     185: aload         4
     187: athrow
     188: astore        7
     190: aload_2
     191: ifnull        224
     194: aload_3
     195: ifnull        218
     198: aload_2
     199: invokeinterface #13,  1           // InterfaceMethod org/apache/hadoop/hbase/ipc/RpcClient.close:()V
     204: goto          224
     207: astore        8
     209: aload_3
     210: aload         8
     212: invokevirtual #15                 // Method java/lang/Throwable.addSuppressed:(Ljava/lang/Throwable;)V
     215: goto          224
     218: aload_2
     219: invokeinterface #13,  1           // InterfaceMethod org/apache/hadoop/hbase/ipc/RpcClient.close:()V
     224: aload         7
     226: athrow
     227: aload_1
     228: ldc           #4                  // String hbase.rpc.client.impl
     230: ldc           #17                 // class org/apache/hadoop/hbase/ipc/NettyRpcClient
     232: invokevirtual #6                  // Method java/lang/Class.getName:()Ljava/lang/String;
     235: invokevirtual #7                  // Method org/apache/hadoop/conf/Configuration.set:(Ljava/lang/String;Ljava/lang/String;)V
     238: aload_1
     239: ldc           #9                  // String default-cluster
     241: invokestatic  #10                 // Method org/apache/hadoop/hbase/ipc/RpcClientFactory.createClient:(Lorg/apache/hadoop/conf/Configuration;Ljava/lang/String;)Lorg/apache/hadoop/hbase/ipc/RpcClient;
     244: astore_2
     245: aconst_null
     246: astore_3
     247: aload_2
     248: ldc           #17                 // class org/apache/hadoop/hbase/ipc/NettyRpcClient
     250: invokestatic  #11                 // Method org/hamcrest/CoreMatchers.instanceOf:(Ljava/lang/Class;)Lorg/hamcrest/Matcher;
     253: invokestatic  #12                 // Method org/junit/Assert.assertThat:(Ljava/lang/Object;Lorg/hamcrest/Matcher;)V
     256: aload_2
     257: ifnull        340
     260: aload_3
     261: ifnull        284
     264: aload_2
     265: invokeinterface #13,  1           // InterfaceMethod org/apache/hadoop/hbase/ipc/RpcClient.close:()V
     270: goto          340
     273: astore        4
     275: aload_3
     276: aload         4
     278: invokevirtual #15                 // Method java/lang/Throwable.addSuppressed:(Ljava/lang/Throwable;)V
     281: goto          340
     284: aload_2
     285: invokeinterface #13,  1           // InterfaceMethod org/apache/hadoop/hbase/ipc/RpcClient.close:()V
     290: goto          340
     293: astore        4
     295: aload         4
     297: astore_3
     298: aload         4
     300: athrow
     301: astore        9
     303: aload_2
     304: ifnull        337
     307: aload_3
     308: ifnull        331
     311: aload_2
     312: invokeinterface #13,  1           // InterfaceMethod org/apache/hadoop/hbase/ipc/RpcClient.close:()V
     317: goto          337
     320: astore        10
     322: aload_3
     323: aload         10
     325: invokevirtual #15                 // Method java/lang/Throwable.addSuppressed:(Ljava/lang/Throwable;)V
     328: goto          337
     331: aload_2
     332: invokeinterface #13,  1           // InterfaceMethod org/apache/hadoop/hbase/ipc/RpcClient.close:()V
     337: aload         9
     339: athrow
     340: aload_1
     341: ldc           #4                  // String hbase.rpc.client.impl
     343: ldc           #18                 // String org.apache.hadoop.hbase.ipc.AsyncRpcClient
     345: invokevirtual #7                  // Method org/apache/hadoop/conf/Configuration.set:(Ljava/lang/String;Ljava/lang/String;)V
     348: aload_1
     349: ldc           #9                  // String default-cluster
     351: invokestatic  #10                 // Method org/apache/hadoop/hbase/ipc/RpcClientFactory.createClient:(Lorg/apache/hadoop/conf/Configuration;Ljava/lang/String;)Lorg/apache/hadoop/hbase/ipc/RpcClient;
     354: astore_2
     355: aconst_null
     356: astore_3
     357: aload_2
     358: ldc           #17                 // class org/apache/hadoop/hbase/ipc/NettyRpcClient
     360: invokestatic  #11                 // Method org/hamcrest/CoreMatchers.instanceOf:(Ljava/lang/Class;)Lorg/hamcrest/Matcher;
     363: invokestatic  #12                 // Method org/junit/Assert.assertThat:(Ljava/lang/Object;Lorg/hamcrest/Matcher;)V
     366: aload_2
     367: ifnull        450
     370: aload_3
     371: ifnull        394
     374: aload_2
     375: invokeinterface #13,  1           // InterfaceMethod org/apache/hadoop/hbase/ipc/RpcClient.close:()V
     380: goto          450
     383: astore        4
     385: aload_3
     386: aload         4
     388: invokevirtual #15                 // Method java/lang/Throwable.addSuppressed:(Ljava/lang/Throwable;)V
     391: goto          450
     394: aload_2
     395: invokeinterface #13,  1           // InterfaceMethod org/apache/hadoop/hbase/ipc/RpcClient.close:()V
     400: goto          450
     403: astore        4
     405: aload         4
     407: astore_3
     408: aload         4
     410: athrow
     411: astore        11
     413: aload_2
     414: ifnull        447
     417: aload_3
     418: ifnull        441
     421: aload_2
     422: invokeinterface #13,  1           // InterfaceMethod org/apache/hadoop/hbase/ipc/RpcClient.close:()V
     427: goto          447
     430: astore        12
     432: aload_3
     433: aload         12
     435: invokevirtual #15                 // Method java/lang/Throwable.addSuppressed:(Ljava/lang/Throwable;)V
     438: goto          447
     441: aload_2
     442: invokeinterface #13,  1           // InterfaceMethod org/apache/hadoop/hbase/ipc/RpcClient.close:()V
     447: aload         11
     449: athrow
     450: return
    Exception table:
       from    to  target type
          41    47    50   Class java/lang/Throwable
          24    33    70   Class java/lang/Throwable
          24    33    78   any
          88    94    97   Class java/lang/Throwable
          70    80    78   any
         151   157   160   Class java/lang/Throwable
         134   143   180   Class java/lang/Throwable
         134   143   188   any
         198   204   207   Class java/lang/Throwable
         180   190   188   any
         264   270   273   Class java/lang/Throwable
         247   256   293   Class java/lang/Throwable
         247   256   301   any
         311   317   320   Class java/lang/Throwable
         293   303   301   any
         374   380   383   Class java/lang/Throwable
         357   366   403   Class java/lang/Throwable
         357   366   411   any
         421   427   430   Class java/lang/Throwable
         403   413   411   any

  static {};
    Code:
       0: ldc           #19                 // class org/apache/hadoop/hbase/ipc/TestRpcClientDeprecatedNameMapping
       2: invokestatic  #20                 // Method org/apache/hadoop/hbase/HBaseClassTestRule.forClass:(Ljava/lang/Class;)Lorg/apache/hadoop/hbase/HBaseClassTestRule;
       5: putstatic     #21                 // Field CLASS_RULE:Lorg/apache/hadoop/hbase/HBaseClassTestRule;
       8: return
}
