Compiled from "TestStoreFileRefresherChore.java"
public class org.apache.hadoop.hbase.regionserver.TestStoreFileRefresherChore {
  public static final org.apache.hadoop.hbase.HBaseClassTestRule CLASS_RULE;

  public org.junit.rules.TestName name;

  public org.apache.hadoop.hbase.regionserver.TestStoreFileRefresherChore();
    Code:
       0: aload_0
       1: invokespecial #1                  // Method java/lang/Object."<init>":()V
       4: aload_0
       5: new           #2                  // class org/junit/rules/TestName
       8: dup
       9: invokespecial #3                  // Method org/junit/rules/TestName."<init>":()V
      12: putfield      #4                  // Field name:Lorg/junit/rules/TestName;
      15: return

  public void setUp() throws java.io.IOException;
    Code:
       0: aload_0
       1: new           #5                  // class org/apache/hadoop/hbase/HBaseTestingUtility
       4: dup
       5: invokespecial #6                  // Method org/apache/hadoop/hbase/HBaseTestingUtility."<init>":()V
       8: putfield      #7                  // Field TEST_UTIL:Lorg/apache/hadoop/hbase/HBaseTestingUtility;
      11: aload_0
      12: aload_0
      13: getfield      #7                  // Field TEST_UTIL:Lorg/apache/hadoop/hbase/HBaseTestingUtility;
      16: ldc           #8                  // String TestStoreFileRefresherChore
      18: invokevirtual #9                  // Method org/apache/hadoop/hbase/HBaseTestingUtility.getDataTestDir:(Ljava/lang/String;)Lorg/apache/hadoop/fs/Path;
      21: putfield      #10                 // Field testDir:Lorg/apache/hadoop/fs/Path;
      24: aload_0
      25: getfield      #7                  // Field TEST_UTIL:Lorg/apache/hadoop/hbase/HBaseTestingUtility;
      28: invokevirtual #11                 // Method org/apache/hadoop/hbase/HBaseTestingUtility.getConfiguration:()Lorg/apache/hadoop/conf/Configuration;
      31: aload_0
      32: getfield      #10                 // Field testDir:Lorg/apache/hadoop/fs/Path;
      35: invokestatic  #12                 // Method org/apache/hadoop/hbase/util/FSUtils.setRootDir:(Lorg/apache/hadoop/conf/Configuration;Lorg/apache/hadoop/fs/Path;)V
      38: return

  public void testIsStale() throws java.io.IOException;
    Code:
       0: iconst_0
       1: istore_1
       2: iconst_1
       3: anewarray     #73                 // class "[B"
       6: dup
       7: iconst_0
       8: ldc           #74                 // String cf
      10: invokestatic  #52                 // Method org/apache/hadoop/hbase/util/Bytes.toBytes:(Ljava/lang/String;)[B
      13: aastore
      14: astore_2
      15: ldc           #75                 // String cq
      17: invokestatic  #52                 // Method org/apache/hadoop/hbase/util/Bytes.toBytes:(Ljava/lang/String;)[B
      20: astore_3
      21: ldc           #76                 // class org/apache/hadoop/hbase/regionserver/HRegionServer
      23: invokestatic  #77                 // Method org/mockito/Mockito.mock:(Ljava/lang/Class;)Ljava/lang/Object;
      26: checkcast     #76                 // class org/apache/hadoop/hbase/regionserver/HRegionServer
      29: astore        4
      31: new           #78                 // class java/util/ArrayList
      34: dup
      35: invokespecial #79                 // Method java/util/ArrayList."<init>":()V
      38: astore        5
      40: aload         4
      42: invokevirtual #80                 // Method org/apache/hadoop/hbase/regionserver/HRegionServer.getOnlineRegionsLocalContext:()Ljava/util/Collection;
      45: invokestatic  #81                 // Method org/mockito/Mockito.when:(Ljava/lang/Object;)Lorg/mockito/stubbing/OngoingStubbing;
      48: aload         5
      50: invokeinterface #82,  2           // InterfaceMethod org/mockito/stubbing/OngoingStubbing.thenReturn:(Ljava/lang/Object;)Lorg/mockito/stubbing/OngoingStubbing;
      55: pop
      56: aload         4
      58: invokevirtual #83                 // Method org/apache/hadoop/hbase/regionserver/HRegionServer.getConfiguration:()Lorg/apache/hadoop/conf/Configuration;
      61: invokestatic  #81                 // Method org/mockito/Mockito.when:(Ljava/lang/Object;)Lorg/mockito/stubbing/OngoingStubbing;
      64: aload_0
      65: getfield      #7                  // Field TEST_UTIL:Lorg/apache/hadoop/hbase/HBaseTestingUtility;
      68: invokevirtual #11                 // Method org/apache/hadoop/hbase/HBaseTestingUtility.getConfiguration:()Lorg/apache/hadoop/conf/Configuration;
      71: invokeinterface #82,  2           // InterfaceMethod org/mockito/stubbing/OngoingStubbing.thenReturn:(Ljava/lang/Object;)Lorg/mockito/stubbing/OngoingStubbing;
      76: pop
      77: aload_0
      78: aload_0
      79: getfield      #4                  // Field name:Lorg/junit/rules/TestName;
      82: invokevirtual #84                 // Method org/junit/rules/TestName.getMethodName:()Ljava/lang/String;
      85: invokestatic  #85                 // Method org/apache/hadoop/hbase/TableName.valueOf:(Ljava/lang/String;)Lorg/apache/hadoop/hbase/TableName;
      88: iconst_2
      89: aload_2
      90: invokespecial #86                 // Method getTableDesc:(Lorg/apache/hadoop/hbase/TableName;I[[B)Lorg/apache/hadoop/hbase/client/TableDescriptor;
      93: astore        6
      95: aload_0
      96: aload         6
      98: getstatic     #87                 // Field org/apache/hadoop/hbase/HConstants.EMPTY_START_ROW:[B
     101: getstatic     #88                 // Field org/apache/hadoop/hbase/HConstants.EMPTY_END_ROW:[B
     104: iconst_0
     105: invokespecial #89                 // Method initHRegion:(Lorg/apache/hadoop/hbase/client/TableDescriptor;[B[BI)Lorg/apache/hadoop/hbase/regionserver/HRegion;
     108: astore        7
     110: aload_0
     111: aload         6
     113: getstatic     #87                 // Field org/apache/hadoop/hbase/HConstants.EMPTY_START_ROW:[B
     116: getstatic     #88                 // Field org/apache/hadoop/hbase/HConstants.EMPTY_END_ROW:[B
     119: iconst_1
     120: invokespecial #89                 // Method initHRegion:(Lorg/apache/hadoop/hbase/client/TableDescriptor;[B[BI)Lorg/apache/hadoop/hbase/regionserver/HRegion;
     123: astore        8
     125: aload         5
     127: aload         7
     129: invokeinterface #90,  2           // InterfaceMethod java/util/List.add:(Ljava/lang/Object;)Z
     134: pop
     135: aload         5
     137: aload         8
     139: invokeinterface #90,  2           // InterfaceMethod java/util/List.add:(Ljava/lang/Object;)Z
     144: pop
     145: new           #91                 // class org/apache/hadoop/hbase/regionserver/TestStoreFileRefresherChore$StaleStorefileRefresherChore
     148: dup
     149: iload_1
     150: aload         4
     152: new           #92                 // class org/apache/hadoop/hbase/util/StoppableImplementation
     155: dup
     156: invokespecial #93                 // Method org/apache/hadoop/hbase/util/StoppableImplementation."<init>":()V
     159: invokespecial #94                 // Method org/apache/hadoop/hbase/regionserver/TestStoreFileRefresherChore$StaleStorefileRefresherChore."<init>":(ILorg/apache/hadoop/hbase/regionserver/HRegionServer;Lorg/apache/hadoop/hbase/Stoppable;)V
     162: astore        9
     164: aload_0
     165: aload         7
     167: iconst_0
     168: bipush        100
     170: aload_3
     171: aload_2
     172: invokespecial #95                 // Method putData:(Lorg/apache/hadoop/hbase/regionserver/Region;II[B[[B)V
     175: aload         7
     177: iconst_1
     178: invokevirtual #96                 // Method org/apache/hadoop/hbase/regionserver/HRegion.flush:(Z)Lorg/apache/hadoop/hbase/regionserver/HRegion$FlushResult;
     181: pop
     182: aload_0
     183: aload         7
     185: iconst_0
     186: bipush        100
     188: aload_3
     189: aload_2
     190: invokespecial #58                 // Method verifyData:(Lorg/apache/hadoop/hbase/regionserver/Region;II[B[[B)V
     193: aload_0
     194: aload         8
     196: iconst_0
     197: bipush        100
     199: aload_3
     200: aload_2
     201: invokespecial #97                 // Method verifyDataExpectFail:(Lorg/apache/hadoop/hbase/regionserver/Region;II[B[[B)V
     204: aload         9
     206: invokevirtual #98                 // Method org/apache/hadoop/hbase/regionserver/TestStoreFileRefresherChore$StaleStorefileRefresherChore.chore:()V
     209: aload_0
     210: aload         8
     212: iconst_0
     213: bipush        100
     215: aload_3
     216: aload_2
     217: invokespecial #58                 // Method verifyData:(Lorg/apache/hadoop/hbase/regionserver/Region;II[B[[B)V
     220: aload         8
     222: invokevirtual #99                 // Method org/apache/hadoop/hbase/regionserver/HRegion.getRegionFileSystem:()Lorg/apache/hadoop/hbase/regionserver/HRegionFileSystem;
     225: checkcast     #30                 // class org/apache/hadoop/hbase/regionserver/TestStoreFileRefresherChore$FailingHRegionFileSystem
     228: iconst_1
     229: putfield      #100                // Field org/apache/hadoop/hbase/regionserver/TestStoreFileRefresherChore$FailingHRegionFileSystem.fail:Z
     232: aload_0
     233: aload         7
     235: bipush        100
     237: bipush        100
     239: aload_3
     240: aload_2
     241: invokespecial #95                 // Method putData:(Lorg/apache/hadoop/hbase/regionserver/Region;II[B[[B)V
     244: aload         7
     246: iconst_1
     247: invokevirtual #96                 // Method org/apache/hadoop/hbase/regionserver/HRegion.flush:(Z)Lorg/apache/hadoop/hbase/regionserver/HRegion$FlushResult;
     250: pop
     251: aload_0
     252: aload         7
     254: iconst_0
     255: sipush        200
     258: aload_3
     259: aload_2
     260: invokespecial #58                 // Method verifyData:(Lorg/apache/hadoop/hbase/regionserver/Region;II[B[[B)V
     263: aload         9
     265: invokevirtual #98                 // Method org/apache/hadoop/hbase/regionserver/TestStoreFileRefresherChore$StaleStorefileRefresherChore.chore:()V
     268: aload_0
     269: aload         8
     271: iconst_0
     272: bipush        100
     274: aload_3
     275: aload_2
     276: invokespecial #58                 // Method verifyData:(Lorg/apache/hadoop/hbase/regionserver/Region;II[B[[B)V
     279: aload_0
     280: aload         8
     282: bipush        100
     284: bipush        100
     286: aload_3
     287: aload_2
     288: invokespecial #97                 // Method verifyDataExpectFail:(Lorg/apache/hadoop/hbase/regionserver/Region;II[B[[B)V
     291: aload         9
     293: iconst_1
     294: putfield      #101                // Field org/apache/hadoop/hbase/regionserver/TestStoreFileRefresherChore$StaleStorefileRefresherChore.isStale:Z
     297: aload         9
     299: invokevirtual #98                 // Method org/apache/hadoop/hbase/regionserver/TestStoreFileRefresherChore$StaleStorefileRefresherChore.chore:()V
     302: aload_0
     303: aload         8
     305: iconst_0
     306: bipush        100
     308: aload_3
     309: aload_2
     310: invokespecial #58                 // Method verifyData:(Lorg/apache/hadoop/hbase/regionserver/Region;II[B[[B)V
     313: ldc           #102                // String should have failed with IOException
     315: invokestatic  #61                 // Method org/junit/Assert.fail:(Ljava/lang/String;)V
     318: goto          323
     321: astore        10
     323: return
    Exception table:
       from    to  target type
         302   318   321   Class java/io/IOException

  static {};
    Code:
       0: ldc           #109                // class org/apache/hadoop/hbase/regionserver/TestStoreFileRefresherChore
       2: invokestatic  #110                // Method org/apache/hadoop/hbase/HBaseClassTestRule.forClass:(Ljava/lang/Class;)Lorg/apache/hadoop/hbase/HBaseClassTestRule;
       5: putstatic     #111                // Field CLASS_RULE:Lorg/apache/hadoop/hbase/HBaseClassTestRule;
       8: return
}
