Compiled from "Threads.java"
final class org.apache.hadoop.hbase.util.Threads$1 implements java.lang.Thread$UncaughtExceptionHandler {
  org.apache.hadoop.hbase.util.Threads$1();
    Code:
       0: aload_0
       1: invokespecial #1                  // Method java/lang/Object."<init>":()V
       4: return

  public void uncaughtException(java.lang.Thread, java.lang.Throwable);
    Code:
       0: invokestatic  #2                  // Method org/apache/hadoop/hbase/util/Threads.access$000:()Lorg/slf4j/Logger;
       3: new           #3                  // class java/lang/StringBuilder
       6: dup
       7: invokespecial #4                  // Method java/lang/StringBuilder."<init>":()V
      10: ldc           #5                  // String Thread:
      12: invokevirtual #6                  // Method java/lang/StringBuilder.append:(Ljava/lang/String;)Ljava/lang/StringBuilder;
      15: aload_1
      16: invokevirtual #7                  // Method java/lang/StringBuilder.append:(Ljava/lang/Object;)Ljava/lang/StringBuilder;
      19: ldc           #8                  // String  exited with Exception:
      21: invokevirtual #6                  // Method java/lang/StringBuilder.append:(Ljava/lang/String;)Ljava/lang/StringBuilder;
      24: aload_2
      25: invokestatic  #9                  // Method org/apache/hadoop/util/StringUtils.stringifyException:(Ljava/lang/Throwable;)Ljava/lang/String;
      28: invokevirtual #6                  // Method java/lang/StringBuilder.append:(Ljava/lang/String;)Ljava/lang/StringBuilder;
      31: invokevirtual #10                 // Method java/lang/StringBuilder.toString:()Ljava/lang/String;
      34: invokeinterface #11,  2           // InterfaceMethod org/slf4j/Logger.warn:(Ljava/lang/String;)V
      39: return
}
