Compiled from "TimeRangeTracker.java"
public abstract class org.apache.hadoop.hbase.regionserver.TimeRangeTracker {
  static final long INITIAL_MIN_TIMESTAMP;

  static final long INITIAL_MAX_TIMESTAMP;

  public org.apache.hadoop.hbase.regionserver.TimeRangeTracker();
    Code:
       0: aload_0
       1: invokespecial #2                  // Method java/lang/Object."<init>":()V
       4: return

  public static org.apache.hadoop.hbase.regionserver.TimeRangeTracker create(org.apache.hadoop.hbase.regionserver.TimeRangeTracker$Type);
    Code:
       0: getstatic     #3                  // Field org/apache/hadoop/hbase/regionserver/TimeRangeTracker$1.$SwitchMap$org$apache$hadoop$hbase$regionserver$TimeRangeTracker$Type:[I
       3: aload_0
       4: invokevirtual #4                  // Method org/apache/hadoop/hbase/regionserver/TimeRangeTracker$Type.ordinal:()I
       7: iaload
       8: lookupswitch  { // 2
                     1: 36
                     2: 44
               default: 53
          }
      36: new           #5                  // class org/apache/hadoop/hbase/regionserver/TimeRangeTracker$NonSyncTimeRangeTracker
      39: dup
      40: invokespecial #6                  // Method org/apache/hadoop/hbase/regionserver/TimeRangeTracker$NonSyncTimeRangeTracker."<init>":()V
      43: areturn
      44: new           #7                  // class org/apache/hadoop/hbase/regionserver/TimeRangeTracker$SyncTimeRangeTracker
      47: dup
      48: aconst_null
      49: invokespecial #8                  // Method org/apache/hadoop/hbase/regionserver/TimeRangeTracker$SyncTimeRangeTracker."<init>":(Lorg/apache/hadoop/hbase/regionserver/TimeRangeTracker$1;)V
      52: areturn
      53: new           #9                  // class java/lang/UnsupportedOperationException
      56: dup
      57: new           #10                 // class java/lang/StringBuilder
      60: dup
      61: invokespecial #11                 // Method java/lang/StringBuilder."<init>":()V
      64: ldc           #12                 // String The type:
      66: invokevirtual #13                 // Method java/lang/StringBuilder.append:(Ljava/lang/String;)Ljava/lang/StringBuilder;
      69: aload_0
      70: invokevirtual #14                 // Method java/lang/StringBuilder.append:(Ljava/lang/Object;)Ljava/lang/StringBuilder;
      73: ldc           #15                 // String  is unsupported
      75: invokevirtual #13                 // Method java/lang/StringBuilder.append:(Ljava/lang/String;)Ljava/lang/StringBuilder;
      78: invokevirtual #16                 // Method java/lang/StringBuilder.toString:()Ljava/lang/String;
      81: invokespecial #17                 // Method java/lang/UnsupportedOperationException."<init>":(Ljava/lang/String;)V
      84: athrow

  public static org.apache.hadoop.hbase.regionserver.TimeRangeTracker create(org.apache.hadoop.hbase.regionserver.TimeRangeTracker$Type, org.apache.hadoop.hbase.regionserver.TimeRangeTracker);
    Code:
       0: getstatic     #3                  // Field org/apache/hadoop/hbase/regionserver/TimeRangeTracker$1.$SwitchMap$org$apache$hadoop$hbase$regionserver$TimeRangeTracker$Type:[I
       3: aload_0
       4: invokevirtual #4                  // Method org/apache/hadoop/hbase/regionserver/TimeRangeTracker$Type.ordinal:()I
       7: iaload
       8: lookupswitch  { // 2
                     1: 36
                     2: 45
               default: 54
          }
      36: new           #5                  // class org/apache/hadoop/hbase/regionserver/TimeRangeTracker$NonSyncTimeRangeTracker
      39: dup
      40: aload_1
      41: invokespecial #18                 // Method org/apache/hadoop/hbase/regionserver/TimeRangeTracker$NonSyncTimeRangeTracker."<init>":(Lorg/apache/hadoop/hbase/regionserver/TimeRangeTracker;)V
      44: areturn
      45: new           #7                  // class org/apache/hadoop/hbase/regionserver/TimeRangeTracker$SyncTimeRangeTracker
      48: dup
      49: aload_1
      50: invokespecial #19                 // Method org/apache/hadoop/hbase/regionserver/TimeRangeTracker$SyncTimeRangeTracker."<init>":(Lorg/apache/hadoop/hbase/regionserver/TimeRangeTracker;)V
      53: areturn
      54: new           #9                  // class java/lang/UnsupportedOperationException
      57: dup
      58: new           #10                 // class java/lang/StringBuilder
      61: dup
      62: invokespecial #11                 // Method java/lang/StringBuilder."<init>":()V
      65: ldc           #12                 // String The type:
      67: invokevirtual #13                 // Method java/lang/StringBuilder.append:(Ljava/lang/String;)Ljava/lang/StringBuilder;
      70: aload_0
      71: invokevirtual #14                 // Method java/lang/StringBuilder.append:(Ljava/lang/Object;)Ljava/lang/StringBuilder;
      74: ldc           #15                 // String  is unsupported
      76: invokevirtual #13                 // Method java/lang/StringBuilder.append:(Ljava/lang/String;)Ljava/lang/StringBuilder;
      79: invokevirtual #16                 // Method java/lang/StringBuilder.toString:()Ljava/lang/String;
      82: invokespecial #17                 // Method java/lang/UnsupportedOperationException."<init>":(Ljava/lang/String;)V
      85: athrow

  public static org.apache.hadoop.hbase.regionserver.TimeRangeTracker create(org.apache.hadoop.hbase.regionserver.TimeRangeTracker$Type, long, long);
    Code:
       0: getstatic     #3                  // Field org/apache/hadoop/hbase/regionserver/TimeRangeTracker$1.$SwitchMap$org$apache$hadoop$hbase$regionserver$TimeRangeTracker$Type:[I
       3: aload_0
       4: invokevirtual #4                  // Method org/apache/hadoop/hbase/regionserver/TimeRangeTracker$Type.ordinal:()I
       7: iaload
       8: lookupswitch  { // 2
                     1: 36
                     2: 46
               default: 56
          }
      36: new           #5                  // class org/apache/hadoop/hbase/regionserver/TimeRangeTracker$NonSyncTimeRangeTracker
      39: dup
      40: lload_1
      41: lload_3
      42: invokespecial #20                 // Method org/apache/hadoop/hbase/regionserver/TimeRangeTracker$NonSyncTimeRangeTracker."<init>":(JJ)V
      45: areturn
      46: new           #7                  // class org/apache/hadoop/hbase/regionserver/TimeRangeTracker$SyncTimeRangeTracker
      49: dup
      50: lload_1
      51: lload_3
      52: invokespecial #21                 // Method org/apache/hadoop/hbase/regionserver/TimeRangeTracker$SyncTimeRangeTracker."<init>":(JJ)V
      55: areturn
      56: new           #9                  // class java/lang/UnsupportedOperationException
      59: dup
      60: new           #10                 // class java/lang/StringBuilder
      63: dup
      64: invokespecial #11                 // Method java/lang/StringBuilder."<init>":()V
      67: ldc           #12                 // String The type:
      69: invokevirtual #13                 // Method java/lang/StringBuilder.append:(Ljava/lang/String;)Ljava/lang/StringBuilder;
      72: aload_0
      73: invokevirtual #14                 // Method java/lang/StringBuilder.append:(Ljava/lang/Object;)Ljava/lang/StringBuilder;
      76: ldc           #15                 // String  is unsupported
      78: invokevirtual #13                 // Method java/lang/StringBuilder.append:(Ljava/lang/String;)Ljava/lang/StringBuilder;
      81: invokevirtual #16                 // Method java/lang/StringBuilder.toString:()Ljava/lang/String;
      84: invokespecial #17                 // Method java/lang/UnsupportedOperationException."<init>":(Ljava/lang/String;)V
      87: athrow

  protected abstract void setMax(long);

  protected abstract void setMin(long);

  protected abstract boolean compareAndSetMin(long, long);

  protected abstract boolean compareAndSetMax(long, long);

  public void includeTimestamp(org.apache.hadoop.hbase.Cell);
    Code:
       0: aload_0
       1: aload_1
       2: invokeinterface #22,  1           // InterfaceMethod org/apache/hadoop/hbase/Cell.getTimestamp:()J
       7: invokevirtual #23                 // Method includeTimestamp:(J)V
      10: aload_1
      11: invokestatic  #24                 // Method org/apache/hadoop/hbase/PrivateCellUtil.isDeleteColumnOrFamily:(Lorg/apache/hadoop/hbase/Cell;)Z
      14: ifeq          22
      17: aload_0
      18: lconst_0
      19: invokevirtual #23                 // Method includeTimestamp:(J)V
      22: return

  void includeTimestamp(long);
    Code:
       0: aload_0
       1: invokevirtual #25                 // Method getMin:()J
       4: lstore_3
       5: lload_1
       6: lload_3
       7: lcmp
       8: ifge          49
      11: lload_3
      12: lstore        5
      14: lload_1
      15: lload         5
      17: lcmp
      18: ifge          40
      21: aload_0
      22: lload         5
      24: lload_1
      25: invokevirtual #26                 // Method compareAndSetMin:(JJ)Z
      28: ifne          40
      31: aload_0
      32: invokevirtual #25                 // Method getMin:()J
      35: lstore        5
      37: goto          14
      40: lload_3
      41: ldc2_w        #28                 // long 9223372036854775807l
      44: lcmp
      45: ifeq          49
      48: return
      49: aload_0
      50: invokevirtual #30                 // Method getMax:()J
      53: lstore        5
      55: lload_1
      56: lload         5
      58: lcmp
      59: ifle          88
      62: lload_1
      63: lload         5
      65: lcmp
      66: ifle          88
      69: aload_0
      70: lload         5
      72: lload_1
      73: invokevirtual #31                 // Method compareAndSetMax:(JJ)Z
      76: ifne          88
      79: aload_0
      80: invokevirtual #30                 // Method getMax:()J
      83: lstore        5
      85: goto          62
      88: return

  public boolean includesTimeRange(org.apache.hadoop.hbase.io.TimeRange);
    Code:
       0: aload_0
       1: invokevirtual #25                 // Method getMin:()J
       4: aload_1
       5: invokevirtual #32                 // Method org/apache/hadoop/hbase/io/TimeRange.getMax:()J
       8: lcmp
       9: ifge          28
      12: aload_0
      13: invokevirtual #30                 // Method getMax:()J
      16: aload_1
      17: invokevirtual #33                 // Method org/apache/hadoop/hbase/io/TimeRange.getMin:()J
      20: lcmp
      21: iflt          28
      24: iconst_1
      25: goto          29
      28: iconst_0
      29: ireturn

  public abstract long getMin();

  public abstract long getMax();

  public java.lang.String toString();
    Code:
       0: new           #10                 // class java/lang/StringBuilder
       3: dup
       4: invokespecial #11                 // Method java/lang/StringBuilder."<init>":()V
       7: ldc           #34                 // String [
       9: invokevirtual #13                 // Method java/lang/StringBuilder.append:(Ljava/lang/String;)Ljava/lang/StringBuilder;
      12: aload_0
      13: invokevirtual #25                 // Method getMin:()J
      16: invokevirtual #35                 // Method java/lang/StringBuilder.append:(J)Ljava/lang/StringBuilder;
      19: ldc           #36                 // String ,
      21: invokevirtual #13                 // Method java/lang/StringBuilder.append:(Ljava/lang/String;)Ljava/lang/StringBuilder;
      24: aload_0
      25: invokevirtual #30                 // Method getMax:()J
      28: invokevirtual #35                 // Method java/lang/StringBuilder.append:(J)Ljava/lang/StringBuilder;
      31: ldc           #37                 // String ]
      33: invokevirtual #13                 // Method java/lang/StringBuilder.append:(Ljava/lang/String;)Ljava/lang/StringBuilder;
      36: invokevirtual #16                 // Method java/lang/StringBuilder.toString:()Ljava/lang/String;
      39: areturn

  public static org.apache.hadoop.hbase.regionserver.TimeRangeTracker parseFrom(byte[]) throws java.io.IOException;
    Code:
       0: aload_0
       1: getstatic     #38                 // Field org/apache/hadoop/hbase/regionserver/TimeRangeTracker$Type.NON_SYNC:Lorg/apache/hadoop/hbase/regionserver/TimeRangeTracker$Type;
       4: invokestatic  #39                 // Method parseFrom:([BLorg/apache/hadoop/hbase/regionserver/TimeRangeTracker$Type;)Lorg/apache/hadoop/hbase/regionserver/TimeRangeTracker;
       7: areturn

  public static org.apache.hadoop.hbase.regionserver.TimeRangeTracker parseFrom(byte[], org.apache.hadoop.hbase.regionserver.TimeRangeTracker$Type) throws java.io.IOException;
    Code:
       0: aload_0
       1: ldc           #40                 // String input data is null!
       3: invokestatic  #41                 // Method org/apache/hbase/thirdparty/com/google/common/base/Preconditions.checkNotNull:(Ljava/lang/Object;Ljava/lang/Object;)Ljava/lang/Object;
       6: pop
       7: aload_0
       8: invokestatic  #42                 // Method org/apache/hadoop/hbase/shaded/protobuf/ProtobufUtil.isPBMagicPrefix:([B)Z
      11: ifeq          45
      14: invokestatic  #43                 // Method org/apache/hadoop/hbase/shaded/protobuf/ProtobufUtil.lengthOfPBMagic:()I
      17: istore_2
      18: invokestatic  #44                 // Method org/apache/hadoop/hbase/shaded/protobuf/generated/HBaseProtos$TimeRangeTracker.newBuilder:()Lorg/apache/hadoop/hbase/shaded/protobuf/generated/HBaseProtos$TimeRangeTracker$Builder;
      21: astore_3
      22: aload_3
      23: aload_0
      24: iload_2
      25: aload_0
      26: arraylength
      27: iload_2
      28: isub
      29: invokestatic  #45                 // Method org/apache/hadoop/hbase/shaded/protobuf/ProtobufUtil.mergeFrom:(Lorg/apache/hbase/thirdparty/com/google/protobuf/Message$Builder;[BII)V
      32: aload_1
      33: aload_3
      34: invokevirtual #46                 // Method org/apache/hadoop/hbase/shaded/protobuf/generated/HBaseProtos$TimeRangeTracker$Builder.getFrom:()J
      37: aload_3
      38: invokevirtual #47                 // Method org/apache/hadoop/hbase/shaded/protobuf/generated/HBaseProtos$TimeRangeTracker$Builder.getTo:()J
      41: invokestatic  #48                 // Method create:(Lorg/apache/hadoop/hbase/regionserver/TimeRangeTracker$Type;JJ)Lorg/apache/hadoop/hbase/regionserver/TimeRangeTracker;
      44: areturn
      45: new           #49                 // class java/io/DataInputStream
      48: dup
      49: new           #50                 // class java/io/ByteArrayInputStream
      52: dup
      53: aload_0
      54: invokespecial #51                 // Method java/io/ByteArrayInputStream."<init>":([B)V
      57: invokespecial #52                 // Method java/io/DataInputStream."<init>":(Ljava/io/InputStream;)V
      60: astore_2
      61: aconst_null
      62: astore_3
      63: aload_1
      64: aload_2
      65: invokevirtual #53                 // Method java/io/DataInputStream.readLong:()J
      68: aload_2
      69: invokevirtual #53                 // Method java/io/DataInputStream.readLong:()J
      72: invokestatic  #48                 // Method create:(Lorg/apache/hadoop/hbase/regionserver/TimeRangeTracker$Type;JJ)Lorg/apache/hadoop/hbase/regionserver/TimeRangeTracker;
      75: astore        4
      77: aload_2
      78: ifnull        107
      81: aload_3
      82: ifnull        103
      85: aload_2
      86: invokevirtual #54                 // Method java/io/DataInputStream.close:()V
      89: goto          107
      92: astore        5
      94: aload_3
      95: aload         5
      97: invokevirtual #56                 // Method java/lang/Throwable.addSuppressed:(Ljava/lang/Throwable;)V
     100: goto          107
     103: aload_2
     104: invokevirtual #54                 // Method java/io/DataInputStream.close:()V
     107: aload         4
     109: areturn
     110: astore        4
     112: aload         4
     114: astore_3
     115: aload         4
     117: athrow
     118: astore        6
     120: aload_2
     121: ifnull        150
     124: aload_3
     125: ifnull        146
     128: aload_2
     129: invokevirtual #54                 // Method java/io/DataInputStream.close:()V
     132: goto          150
     135: astore        7
     137: aload_3
     138: aload         7
     140: invokevirtual #56                 // Method java/lang/Throwable.addSuppressed:(Ljava/lang/Throwable;)V
     143: goto          150
     146: aload_2
     147: invokevirtual #54                 // Method java/io/DataInputStream.close:()V
     150: aload         6
     152: athrow
    Exception table:
       from    to  target type
          85    89    92   Class java/lang/Throwable
          63    77   110   Class java/lang/Throwable
          63    77   118   any
         128   132   135   Class java/lang/Throwable
         110   120   118   any

  public static byte[] toByteArray(org.apache.hadoop.hbase.regionserver.TimeRangeTracker) throws java.io.IOException;
    Code:
       0: new           #57                 // class java/io/ByteArrayOutputStream
       3: dup
       4: invokespecial #58                 // Method java/io/ByteArrayOutputStream."<init>":()V
       7: astore_1
       8: aconst_null
       9: astore_2
      10: new           #59                 // class java/io/DataOutputStream
      13: dup
      14: aload_1
      15: invokespecial #60                 // Method java/io/DataOutputStream."<init>":(Ljava/io/OutputStream;)V
      18: astore_3
      19: aconst_null
      20: astore        4
      22: aload_3
      23: aload_0
      24: invokevirtual #25                 // Method getMin:()J
      27: invokevirtual #61                 // Method java/io/DataOutputStream.writeLong:(J)V
      30: aload_3
      31: aload_0
      32: invokevirtual #30                 // Method getMax:()J
      35: invokevirtual #61                 // Method java/io/DataOutputStream.writeLong:(J)V
      38: aload_1
      39: invokevirtual #62                 // Method java/io/ByteArrayOutputStream.toByteArray:()[B
      42: astore        5
      44: aload_3
      45: ifnull        76
      48: aload         4
      50: ifnull        72
      53: aload_3
      54: invokevirtual #63                 // Method java/io/DataOutputStream.close:()V
      57: goto          76
      60: astore        6
      62: aload         4
      64: aload         6
      66: invokevirtual #56                 // Method java/lang/Throwable.addSuppressed:(Ljava/lang/Throwable;)V
      69: goto          76
      72: aload_3
      73: invokevirtual #63                 // Method java/io/DataOutputStream.close:()V
      76: aload_1
      77: ifnull        106
      80: aload_2
      81: ifnull        102
      84: aload_1
      85: invokevirtual #64                 // Method java/io/ByteArrayOutputStream.close:()V
      88: goto          106
      91: astore        6
      93: aload_2
      94: aload         6
      96: invokevirtual #56                 // Method java/lang/Throwable.addSuppressed:(Ljava/lang/Throwable;)V
      99: goto          106
     102: aload_1
     103: invokevirtual #64                 // Method java/io/ByteArrayOutputStream.close:()V
     106: aload         5
     108: areturn
     109: astore        5
     111: aload         5
     113: astore        4
     115: aload         5
     117: athrow
     118: astore        7
     120: aload_3
     121: ifnull        152
     124: aload         4
     126: ifnull        148
     129: aload_3
     130: invokevirtual #63                 // Method java/io/DataOutputStream.close:()V
     133: goto          152
     136: astore        8
     138: aload         4
     140: aload         8
     142: invokevirtual #56                 // Method java/lang/Throwable.addSuppressed:(Ljava/lang/Throwable;)V
     145: goto          152
     148: aload_3
     149: invokevirtual #63                 // Method java/io/DataOutputStream.close:()V
     152: aload         7
     154: athrow
     155: astore_3
     156: aload_3
     157: astore_2
     158: aload_3
     159: athrow
     160: astore        9
     162: aload_1
     163: ifnull        192
     166: aload_2
     167: ifnull        188
     170: aload_1
     171: invokevirtual #64                 // Method java/io/ByteArrayOutputStream.close:()V
     174: goto          192
     177: astore        10
     179: aload_2
     180: aload         10
     182: invokevirtual #56                 // Method java/lang/Throwable.addSuppressed:(Ljava/lang/Throwable;)V
     185: goto          192
     188: aload_1
     189: invokevirtual #64                 // Method java/io/ByteArrayOutputStream.close:()V
     192: aload         9
     194: athrow
    Exception table:
       from    to  target type
          53    57    60   Class java/lang/Throwable
          84    88    91   Class java/lang/Throwable
          22    44   109   Class java/lang/Throwable
          22    44   118   any
         129   133   136   Class java/lang/Throwable
         109   120   118   any
          10    76   155   Class java/lang/Throwable
         109   155   155   Class java/lang/Throwable
          10    76   160   any
         170   174   177   Class java/lang/Throwable
         109   162   160   any

  org.apache.hadoop.hbase.io.TimeRange toTimeRange();
    Code:
       0: aload_0
       1: invokevirtual #25                 // Method getMin:()J
       4: lstore_1
       5: aload_0
       6: invokevirtual #30                 // Method getMax:()J
       9: lstore_3
      10: lload_1
      11: ldc2_w        #28                 // long 9223372036854775807l
      14: lcmp
      15: ifne          20
      18: lconst_0
      19: lstore_1
      20: lload_3
      21: ldc2_w        #66                 // long -1l
      24: lcmp
      25: ifne          32
      28: ldc2_w        #28                 // long 9223372036854775807l
      31: lstore_3
      32: new           #65                 // class org/apache/hadoop/hbase/io/TimeRange
      35: dup
      36: lload_1
      37: lload_3
      38: invokespecial #68                 // Method org/apache/hadoop/hbase/io/TimeRange."<init>":(JJ)V
      41: areturn
}
