Compiled from "Timer.java"
public interface org.apache.hadoop.hbase.metrics.Timer extends org.apache.hadoop.hbase.metrics.Metric {
  public abstract void update(long, java.util.concurrent.TimeUnit);

  public void updateMillis(long);
    Code:
       0: aload_0
       1: lload_1
       2: getstatic     #1                  // Field java/util/concurrent/TimeUnit.NANOSECONDS:Ljava/util/concurrent/TimeUnit;
       5: invokeinterface #2,  4            // InterfaceMethod update:(JLjava/util/concurrent/TimeUnit;)V
      10: return

  public void updateMicros(long);
    Code:
       0: aload_0
       1: lload_1
       2: getstatic     #3                  // Field java/util/concurrent/TimeUnit.MICROSECONDS:Ljava/util/concurrent/TimeUnit;
       5: invokeinterface #2,  4            // InterfaceMethod update:(JLjava/util/concurrent/TimeUnit;)V
      10: return

  public void updateNanos(long);
    Code:
       0: aload_0
       1: lload_1
       2: getstatic     #1                  // Field java/util/concurrent/TimeUnit.NANOSECONDS:Ljava/util/concurrent/TimeUnit;
       5: invokeinterface #2,  4            // InterfaceMethod update:(JLjava/util/concurrent/TimeUnit;)V
      10: return

  public abstract org.apache.hadoop.hbase.metrics.Histogram getHistogram();

  public abstract org.apache.hadoop.hbase.metrics.Meter getMeter();
}
