Compiled from "TimerImpl.java"
public class org.apache.hadoop.hbase.metrics.impl.TimerImpl implements org.apache.hadoop.hbase.metrics.Timer {
  public org.apache.hadoop.hbase.metrics.impl.TimerImpl();
    Code:
       0: aload_0
       1: invokespecial #1                  // Method java/lang/Object."<init>":()V
       4: aload_0
       5: new           #2                  // class org/apache/hadoop/hbase/metrics/impl/HistogramImpl
       8: dup
       9: invokespecial #3                  // Method org/apache/hadoop/hbase/metrics/impl/HistogramImpl."<init>":()V
      12: putfield      #4                  // Field histogram:Lorg/apache/hadoop/hbase/metrics/impl/HistogramImpl;
      15: aload_0
      16: new           #5                  // class org/apache/hadoop/hbase/metrics/impl/DropwizardMeter
      19: dup
      20: invokespecial #6                  // Method org/apache/hadoop/hbase/metrics/impl/DropwizardMeter."<init>":()V
      23: putfield      #7                  // Field meter:Lorg/apache/hadoop/hbase/metrics/impl/DropwizardMeter;
      26: return

  public void update(long, java.util.concurrent.TimeUnit);
    Code:
       0: lload_1
       1: lconst_0
       2: lcmp
       3: iflt          28
       6: aload_0
       7: getfield      #4                  // Field histogram:Lorg/apache/hadoop/hbase/metrics/impl/HistogramImpl;
      10: getstatic     #8                  // Field DEFAULT_UNIT:Ljava/util/concurrent/TimeUnit;
      13: lload_1
      14: aload_3
      15: invokevirtual #9                  // Method java/util/concurrent/TimeUnit.convert:(JLjava/util/concurrent/TimeUnit;)J
      18: invokevirtual #10                 // Method org/apache/hadoop/hbase/metrics/impl/HistogramImpl.update:(J)V
      21: aload_0
      22: getfield      #7                  // Field meter:Lorg/apache/hadoop/hbase/metrics/impl/DropwizardMeter;
      25: invokevirtual #11                 // Method org/apache/hadoop/hbase/metrics/impl/DropwizardMeter.mark:()V
      28: return

  public org.apache.hadoop.hbase.metrics.impl.HistogramImpl getHistogram();
    Code:
       0: aload_0
       1: getfield      #4                  // Field histogram:Lorg/apache/hadoop/hbase/metrics/impl/HistogramImpl;
       4: areturn

  public org.apache.hadoop.hbase.metrics.impl.DropwizardMeter getMeter();
    Code:
       0: aload_0
       1: getfield      #7                  // Field meter:Lorg/apache/hadoop/hbase/metrics/impl/DropwizardMeter;
       4: areturn

  public org.apache.hadoop.hbase.metrics.Meter getMeter();
    Code:
       0: aload_0
       1: invokevirtual #12                 // Method getMeter:()Lorg/apache/hadoop/hbase/metrics/impl/DropwizardMeter;
       4: areturn

  public org.apache.hadoop.hbase.metrics.Histogram getHistogram();
    Code:
       0: aload_0
       1: invokevirtual #13                 // Method getHistogram:()Lorg/apache/hadoop/hbase/metrics/impl/HistogramImpl;
       4: areturn

  static {};
    Code:
       0: getstatic     #14                 // Field java/util/concurrent/TimeUnit.MICROSECONDS:Ljava/util/concurrent/TimeUnit;
       3: putstatic     #8                  // Field DEFAULT_UNIT:Ljava/util/concurrent/TimeUnit;
       6: return
}
