Compiled from "TokenUtil.java"
final class org.apache.hadoop.hbase.security.token.TokenUtil$1 implements java.security.PrivilegedExceptionAction<org.apache.hadoop.security.token.Token<org.apache.hadoop.hbase.security.token.AuthenticationTokenIdentifier>> {
  final org.apache.hadoop.hbase.client.Connection val$conn;

  org.apache.hadoop.hbase.security.token.TokenUtil$1(org.apache.hadoop.hbase.client.Connection);
    Code:
       0: aload_0
       1: aload_1
       2: putfield      #1                  // Field val$conn:Lorg/apache/hadoop/hbase/client/Connection;
       5: aload_0
       6: invokespecial #2                  // Method java/lang/Object."<init>":()V
       9: return

  public org.apache.hadoop.security.token.Token<org.apache.hadoop.hbase.security.token.AuthenticationTokenIdentifier> run() throws java.lang.Exception;
    Code:
       0: aload_0
       1: getfield      #1                  // Field val$conn:Lorg/apache/hadoop/hbase/client/Connection;
       4: invokestatic  #3                  // Method org/apache/hadoop/hbase/security/token/TokenUtil.obtainToken:(Lorg/apache/hadoop/hbase/client/Connection;)Lorg/apache/hadoop/security/token/Token;
       7: areturn

  public java.lang.Object run() throws java.lang.Exception;
    Code:
       0: aload_0
       1: invokevirtual #4                  // Method run:()Lorg/apache/hadoop/security/token/Token;
       4: areturn
}
