Compiled from "TransitRegionStateProcedure.java"
public class org.apache.hadoop.hbase.master.assignment.TransitRegionStateProcedure extends org.apache.hadoop.hbase.master.procedure.AbstractStateMachineRegionProcedure<org.apache.hadoop.hbase.shaded.protobuf.generated.MasterProcedureProtos$RegionStateTransitionState> {
  static final boolean $assertionsDisabled;

  public org.apache.hadoop.hbase.master.assignment.TransitRegionStateProcedure();
    Code:
       0: aload_0
       1: invokespecial #1                  // Method org/apache/hadoop/hbase/master/procedure/AbstractStateMachineRegionProcedure."<init>":()V
       4: return

  protected org.apache.hadoop.hbase.master.assignment.TransitRegionStateProcedure(org.apache.hadoop.hbase.master.procedure.MasterProcedureEnv, org.apache.hadoop.hbase.client.RegionInfo, org.apache.hadoop.hbase.ServerName, boolean, org.apache.hadoop.hbase.master.assignment.TransitRegionStateProcedure$TransitionType);
    Code:
       0: aload_0
       1: aload_1
       2: aload_2
       3: invokespecial #19                 // Method org/apache/hadoop/hbase/master/procedure/AbstractStateMachineRegionProcedure."<init>":(Lorg/apache/hadoop/hbase/master/procedure/MasterProcedureEnv;Lorg/apache/hadoop/hbase/client/RegionInfo;)V
       6: aload_0
       7: aload_3
       8: putfield      #20                 // Field assignCandidate:Lorg/apache/hadoop/hbase/ServerName;
      11: aload_0
      12: iload         4
      14: putfield      #21                 // Field forceNewPlan:Z
      17: aload_0
      18: aload         5
      20: putfield      #3                  // Field type:Lorg/apache/hadoop/hbase/master/assignment/TransitRegionStateProcedure$TransitionType;
      23: aload_0
      24: invokespecial #22                 // Method setInitalAndLastState:()V
      27: return

  public org.apache.hadoop.hbase.master.procedure.TableProcedureInterface$TableOperationType getTableOperationType();
    Code:
       0: getstatic     #23                 // Field org/apache/hadoop/hbase/master/procedure/TableProcedureInterface$TableOperationType.REGION_EDIT:Lorg/apache/hadoop/hbase/master/procedure/TableProcedureInterface$TableOperationType;
       3: areturn

  protected boolean waitInitialized(org.apache.hadoop.hbase.master.procedure.MasterProcedureEnv);
    Code:
       0: aload_0
       1: invokevirtual #24                 // Method getTableName:()Lorg/apache/hadoop/hbase/TableName;
       4: invokestatic  #25                 // Method org/apache/hadoop/hbase/TableName.isMetaTableName:(Lorg/apache/hadoop/hbase/TableName;)Z
       7: ifeq          12
      10: iconst_0
      11: ireturn
      12: aload_1
      13: invokevirtual #26                 // Method org/apache/hadoop/hbase/master/procedure/MasterProcedureEnv.getAssignmentManager:()Lorg/apache/hadoop/hbase/master/assignment/AssignmentManager;
      16: astore_2
      17: aload_2
      18: aload_0
      19: invokevirtual #27                 // Method org/apache/hadoop/hbase/master/assignment/AssignmentManager.waitMetaLoaded:(Lorg/apache/hadoop/hbase/procedure2/Procedure;)Z
      22: ifne          37
      25: aload_2
      26: aload_0
      27: aload_0
      28: invokevirtual #28                 // Method getRegion:()Lorg/apache/hadoop/hbase/client/RegionInfo;
      31: invokevirtual #29                 // Method org/apache/hadoop/hbase/master/assignment/AssignmentManager.waitMetaAssigned:(Lorg/apache/hadoop/hbase/procedure2/Procedure;Lorg/apache/hadoop/hbase/client/RegionInfo;)Z
      34: ifeq          41
      37: iconst_1
      38: goto          42
      41: iconst_0
      42: ireturn

  protected org.apache.hadoop.hbase.procedure2.Procedure[] execute(org.apache.hadoop.hbase.master.procedure.MasterProcedureEnv) throws org.apache.hadoop.hbase.procedure2.ProcedureSuspendedException, org.apache.hadoop.hbase.procedure2.ProcedureYieldException, java.lang.InterruptedException;
    Code:
       0: aload_1
       1: invokevirtual #26                 // Method org/apache/hadoop/hbase/master/procedure/MasterProcedureEnv.getAssignmentManager:()Lorg/apache/hadoop/hbase/master/assignment/AssignmentManager;
       4: invokevirtual #64                 // Method org/apache/hadoop/hbase/master/assignment/AssignmentManager.getRegionStates:()Lorg/apache/hadoop/hbase/master/assignment/RegionStates;
       7: aload_0
       8: invokevirtual #28                 // Method getRegion:()Lorg/apache/hadoop/hbase/client/RegionInfo;
      11: invokevirtual #96                 // Method org/apache/hadoop/hbase/master/assignment/RegionStates.getOrCreateRegionStateNode:(Lorg/apache/hadoop/hbase/client/RegionInfo;)Lorg/apache/hadoop/hbase/master/assignment/RegionStateNode;
      14: astore_2
      15: aload_2
      16: invokevirtual #97                 // Method org/apache/hadoop/hbase/master/assignment/RegionStateNode.lock:()V
      19: aload_0
      20: aload_1
      21: invokespecial #98                 // Method org/apache/hadoop/hbase/master/procedure/AbstractStateMachineRegionProcedure.execute:(Ljava/lang/Object;)[Lorg/apache/hadoop/hbase/procedure2/Procedure;
      24: astore_3
      25: aload_2
      26: invokevirtual #99                 // Method org/apache/hadoop/hbase/master/assignment/RegionStateNode.unlock:()V
      29: aload_3
      30: areturn
      31: astore        4
      33: aload_2
      34: invokevirtual #99                 // Method org/apache/hadoop/hbase/master/assignment/RegionStateNode.unlock:()V
      37: aload         4
      39: athrow
    Exception table:
       from    to  target type
          19    25    31   any
          31    33    31   any

  protected org.apache.hadoop.hbase.procedure2.StateMachineProcedure$Flow executeFromState(org.apache.hadoop.hbase.master.procedure.MasterProcedureEnv, org.apache.hadoop.hbase.shaded.protobuf.generated.MasterProcedureProtos$RegionStateTransitionState) throws org.apache.hadoop.hbase.procedure2.ProcedureSuspendedException, org.apache.hadoop.hbase.procedure2.ProcedureYieldException, java.lang.InterruptedException;
    Code:
       0: aload_0
       1: aload_1
       2: invokespecial #100                // Method getRegionStateNode:(Lorg/apache/hadoop/hbase/master/procedure/MasterProcedureEnv;)Lorg/apache/hadoop/hbase/master/assignment/RegionStateNode;
       5: astore_3
       6: getstatic     #101                // Field org/apache/hadoop/hbase/master/assignment/TransitRegionStateProcedure$1.$SwitchMap$org$apache$hadoop$hbase$shaded$protobuf$generated$MasterProcedureProtos$RegionStateTransitionState:[I
       9: aload_2
      10: invokevirtual #102                // Method org/apache/hadoop/hbase/shaded/protobuf/generated/MasterProcedureProtos$RegionStateTransitionState.ordinal:()I
      13: iaload
      14: tableswitch   { // 1 to 5
                     1: 48
                     2: 58
                     3: 68
                     4: 75
                     5: 85
               default: 92
          }
      48: aload_0
      49: aload_1
      50: aload_3
      51: invokespecial #103                // Method queueAssign:(Lorg/apache/hadoop/hbase/master/procedure/MasterProcedureEnv;Lorg/apache/hadoop/hbase/master/assignment/RegionStateNode;)V
      54: getstatic     #63                 // Field org/apache/hadoop/hbase/procedure2/StateMachineProcedure$Flow.HAS_MORE_STATE:Lorg/apache/hadoop/hbase/procedure2/StateMachineProcedure$Flow;
      57: areturn
      58: aload_0
      59: aload_1
      60: aload_3
      61: invokespecial #104                // Method openRegion:(Lorg/apache/hadoop/hbase/master/procedure/MasterProcedureEnv;Lorg/apache/hadoop/hbase/master/assignment/RegionStateNode;)V
      64: getstatic     #63                 // Field org/apache/hadoop/hbase/procedure2/StateMachineProcedure$Flow.HAS_MORE_STATE:Lorg/apache/hadoop/hbase/procedure2/StateMachineProcedure$Flow;
      67: areturn
      68: aload_0
      69: aload_1
      70: aload_3
      71: invokespecial #105                // Method confirmOpened:(Lorg/apache/hadoop/hbase/master/procedure/MasterProcedureEnv;Lorg/apache/hadoop/hbase/master/assignment/RegionStateNode;)Lorg/apache/hadoop/hbase/procedure2/StateMachineProcedure$Flow;
      74: areturn
      75: aload_0
      76: aload_1
      77: aload_3
      78: invokespecial #106                // Method closeRegion:(Lorg/apache/hadoop/hbase/master/procedure/MasterProcedureEnv;Lorg/apache/hadoop/hbase/master/assignment/RegionStateNode;)V
      81: getstatic     #63                 // Field org/apache/hadoop/hbase/procedure2/StateMachineProcedure$Flow.HAS_MORE_STATE:Lorg/apache/hadoop/hbase/procedure2/StateMachineProcedure$Flow;
      84: areturn
      85: aload_0
      86: aload_1
      87: aload_3
      88: invokespecial #107                // Method confirmClosed:(Lorg/apache/hadoop/hbase/master/procedure/MasterProcedureEnv;Lorg/apache/hadoop/hbase/master/assignment/RegionStateNode;)Lorg/apache/hadoop/hbase/procedure2/StateMachineProcedure$Flow;
      91: areturn
      92: new           #108                // class java/lang/UnsupportedOperationException
      95: dup
      96: new           #12                 // class java/lang/StringBuilder
      99: dup
     100: invokespecial #13                 // Method java/lang/StringBuilder."<init>":()V
     103: ldc           #109                // String unhandled state=
     105: invokevirtual #15                 // Method java/lang/StringBuilder.append:(Ljava/lang/String;)Ljava/lang/StringBuilder;
     108: aload_2
     109: invokevirtual #16                 // Method java/lang/StringBuilder.append:(Ljava/lang/Object;)Ljava/lang/StringBuilder;
     112: invokevirtual #17                 // Method java/lang/StringBuilder.toString:()Ljava/lang/String;
     115: invokespecial #110                // Method java/lang/UnsupportedOperationException."<init>":(Ljava/lang/String;)V
     118: athrow
     119: astore        4
     121: aload_0
     122: getfield      #58                 // Field retryCounter:Lorg/apache/hadoop/hbase/util/RetryCounter;
     125: ifnonnull     139
     128: aload_0
     129: aload_1
     130: invokevirtual #112                // Method org/apache/hadoop/hbase/master/procedure/MasterProcedureEnv.getMasterConfiguration:()Lorg/apache/hadoop/conf/Configuration;
     133: invokestatic  #113                // Method org/apache/hadoop/hbase/procedure2/ProcedureUtil.createRetryCounter:(Lorg/apache/hadoop/conf/Configuration;)Lorg/apache/hadoop/hbase/util/RetryCounter;
     136: putfield      #58                 // Field retryCounter:Lorg/apache/hadoop/hbase/util/RetryCounter;
     139: aload_0
     140: getfield      #58                 // Field retryCounter:Lorg/apache/hadoop/hbase/util/RetryCounter;
     143: invokevirtual #114                // Method org/apache/hadoop/hbase/util/RetryCounter.getBackoffTimeAndIncrementAttempts:()J
     146: lstore        5
     148: getstatic     #33                 // Field LOG:Lorg/slf4j/Logger;
     151: ldc           #115                // String Failed transition, suspend {}secs {}; {}; waiting on rectified condition fixed by other Procedure or operator intervention
     153: iconst_4
     154: anewarray     #37                 // class java/lang/Object
     157: dup
     158: iconst_0
     159: lload         5
     161: ldc2_w        #116                // long 1000l
     164: ldiv
     165: invokestatic  #118                // Method java/lang/Long.valueOf:(J)Ljava/lang/Long;
     168: aastore
     169: dup
     170: iconst_1
     171: aload_0
     172: aastore
     173: dup
     174: iconst_2
     175: aload_3
     176: invokevirtual #38                 // Method org/apache/hadoop/hbase/master/assignment/RegionStateNode.toShortString:()Ljava/lang/String;
     179: aastore
     180: dup
     181: iconst_3
     182: aload         4
     184: aastore
     185: invokeinterface #119,  3          // InterfaceMethod org/slf4j/Logger.warn:(Ljava/lang/String;[Ljava/lang/Object;)V
     190: aload_0
     191: lload         5
     193: invokestatic  #120                // Method java/lang/Math.toIntExact:(J)I
     196: invokevirtual #121                // Method setTimeout:(I)V
     199: aload_0
     200: getstatic     #122                // Field org/apache/hadoop/hbase/shaded/protobuf/generated/ProcedureProtos$ProcedureState.WAITING_TIMEOUT:Lorg/apache/hadoop/hbase/shaded/protobuf/generated/ProcedureProtos$ProcedureState;
     203: invokevirtual #123                // Method setState:(Lorg/apache/hadoop/hbase/shaded/protobuf/generated/ProcedureProtos$ProcedureState;)V
     206: aload_0
     207: invokevirtual #124                // Method skipPersistence:()V
     210: new           #46                 // class org/apache/hadoop/hbase/procedure2/ProcedureSuspendedException
     213: dup
     214: invokespecial #47                 // Method org/apache/hadoop/hbase/procedure2/ProcedureSuspendedException."<init>":()V
     217: athrow
    Exception table:
       from    to  target type
           6    57   119   Class java/io/IOException
          58    67   119   Class java/io/IOException
          68    74   119   Class java/io/IOException
          75    84   119   Class java/io/IOException
          85    91   119   Class java/io/IOException
          92   119   119   Class java/io/IOException

  protected synchronized boolean setTimeoutFailure(org.apache.hadoop.hbase.master.procedure.MasterProcedureEnv);
    Code:
       0: aload_0
       1: getstatic     #125                // Field org/apache/hadoop/hbase/shaded/protobuf/generated/ProcedureProtos$ProcedureState.RUNNABLE:Lorg/apache/hadoop/hbase/shaded/protobuf/generated/ProcedureProtos$ProcedureState;
       4: invokevirtual #123                // Method setState:(Lorg/apache/hadoop/hbase/shaded/protobuf/generated/ProcedureProtos$ProcedureState;)V
       7: aload_1
       8: invokevirtual #126                // Method org/apache/hadoop/hbase/master/procedure/MasterProcedureEnv.getProcedureScheduler:()Lorg/apache/hadoop/hbase/master/procedure/MasterProcedureScheduler;
      11: aload_0
      12: invokevirtual #127                // Method org/apache/hadoop/hbase/master/procedure/MasterProcedureScheduler.addFront:(Lorg/apache/hadoop/hbase/procedure2/Procedure;)V
      15: iconst_0
      16: ireturn

  public void reportTransition(org.apache.hadoop.hbase.master.procedure.MasterProcedureEnv, org.apache.hadoop.hbase.master.assignment.RegionStateNode, org.apache.hadoop.hbase.ServerName, org.apache.hadoop.hbase.shaded.protobuf.generated.RegionServerStatusProtos$RegionStateTransition$TransitionCode, long, long) throws java.io.IOException;
    Code:
       0: aload_0
       1: getfield      #128                // Field remoteProc:Lorg/apache/hadoop/hbase/master/assignment/RegionRemoteProcedureBase;
       4: ifnonnull     47
       7: getstatic     #33                 // Field LOG:Lorg/slf4j/Logger;
      10: ldc           #129                // String There is no outstanding remote region procedure for {}, serverName={}, code={}, seqId={}, proc={}, should be a retry, ignore
      12: iconst_5
      13: anewarray     #37                 // class java/lang/Object
      16: dup
      17: iconst_0
      18: aload_2
      19: aastore
      20: dup
      21: iconst_1
      22: aload_3
      23: aastore
      24: dup
      25: iconst_2
      26: aload         4
      28: aastore
      29: dup
      30: iconst_3
      31: lload         5
      33: invokestatic  #118                // Method java/lang/Long.valueOf:(J)Ljava/lang/Long;
      36: aastore
      37: dup
      38: iconst_4
      39: aload_0
      40: aastore
      41: invokeinterface #119,  3          // InterfaceMethod org/slf4j/Logger.warn:(Ljava/lang/String;[Ljava/lang/Object;)V
      46: return
      47: lload         7
      49: lconst_0
      50: lcmp
      51: iflt          130
      54: aload_0
      55: getfield      #128                // Field remoteProc:Lorg/apache/hadoop/hbase/master/assignment/RegionRemoteProcedureBase;
      58: invokevirtual #130                // Method org/apache/hadoop/hbase/master/assignment/RegionRemoteProcedureBase.getProcId:()J
      61: lload         7
      63: lcmp
      64: ifeq          130
      67: getstatic     #33                 // Field LOG:Lorg/slf4j/Logger;
      70: ldc           #131                // String The pid of remote region procedure for {} is {}, the reported pid={}, serverName={}, code={}, seqId={}, proc={}, should be a retry, ignore
      72: bipush        7
      74: anewarray     #37                 // class java/lang/Object
      77: dup
      78: iconst_0
      79: aload_2
      80: aastore
      81: dup
      82: iconst_1
      83: aload_0
      84: getfield      #128                // Field remoteProc:Lorg/apache/hadoop/hbase/master/assignment/RegionRemoteProcedureBase;
      87: invokevirtual #130                // Method org/apache/hadoop/hbase/master/assignment/RegionRemoteProcedureBase.getProcId:()J
      90: invokestatic  #118                // Method java/lang/Long.valueOf:(J)Ljava/lang/Long;
      93: aastore
      94: dup
      95: iconst_2
      96: lload         7
      98: invokestatic  #118                // Method java/lang/Long.valueOf:(J)Ljava/lang/Long;
     101: aastore
     102: dup
     103: iconst_3
     104: aload_3
     105: aastore
     106: dup
     107: iconst_4
     108: aload         4
     110: aastore
     111: dup
     112: iconst_5
     113: lload         5
     115: invokestatic  #118                // Method java/lang/Long.valueOf:(J)Ljava/lang/Long;
     118: aastore
     119: dup
     120: bipush        6
     122: aload_0
     123: aastore
     124: invokeinterface #119,  3          // InterfaceMethod org/slf4j/Logger.warn:(Ljava/lang/String;[Ljava/lang/Object;)V
     129: return
     130: aload_0
     131: getfield      #128                // Field remoteProc:Lorg/apache/hadoop/hbase/master/assignment/RegionRemoteProcedureBase;
     134: aload_1
     135: aload_2
     136: aload_3
     137: aload         4
     139: lload         5
     141: invokevirtual #132                // Method org/apache/hadoop/hbase/master/assignment/RegionRemoteProcedureBase.reportTransition:(Lorg/apache/hadoop/hbase/master/procedure/MasterProcedureEnv;Lorg/apache/hadoop/hbase/master/assignment/RegionStateNode;Lorg/apache/hadoop/hbase/ServerName;Lorg/apache/hadoop/hbase/shaded/protobuf/generated/RegionServerStatusProtos$RegionStateTransition$TransitionCode;J)V
     144: return

  public void serverCrashed(org.apache.hadoop.hbase.master.procedure.MasterProcedureEnv, org.apache.hadoop.hbase.master.assignment.RegionStateNode, org.apache.hadoop.hbase.ServerName) throws java.io.IOException;
    Code:
       0: aload_0
       1: getfield      #128                // Field remoteProc:Lorg/apache/hadoop/hbase/master/assignment/RegionRemoteProcedureBase;
       4: ifnull        20
       7: aload_0
       8: getfield      #128                // Field remoteProc:Lorg/apache/hadoop/hbase/master/assignment/RegionRemoteProcedureBase;
      11: aload_1
      12: aload_2
      13: aload_3
      14: invokevirtual #133                // Method org/apache/hadoop/hbase/master/assignment/RegionRemoteProcedureBase.serverCrashed:(Lorg/apache/hadoop/hbase/master/procedure/MasterProcedureEnv;Lorg/apache/hadoop/hbase/master/assignment/RegionStateNode;Lorg/apache/hadoop/hbase/ServerName;)V
      17: goto          28
      20: aload_1
      21: invokevirtual #26                 // Method org/apache/hadoop/hbase/master/procedure/MasterProcedureEnv.getAssignmentManager:()Lorg/apache/hadoop/hbase/master/assignment/AssignmentManager;
      24: aload_2
      25: invokevirtual #134                // Method org/apache/hadoop/hbase/master/assignment/AssignmentManager.regionClosedAbnormally:(Lorg/apache/hadoop/hbase/master/assignment/RegionStateNode;)V
      28: return

  void attachRemoteProc(org.apache.hadoop.hbase.master.assignment.RegionRemoteProcedureBase);
    Code:
       0: aload_0
       1: aload_1
       2: putfield      #128                // Field remoteProc:Lorg/apache/hadoop/hbase/master/assignment/RegionRemoteProcedureBase;
       5: return

  void unattachRemoteProc(org.apache.hadoop.hbase.master.assignment.RegionRemoteProcedureBase);
    Code:
       0: getstatic     #91                 // Field $assertionsDisabled:Z
       3: ifne          22
       6: aload_0
       7: getfield      #128                // Field remoteProc:Lorg/apache/hadoop/hbase/master/assignment/RegionRemoteProcedureBase;
      10: aload_1
      11: if_acmpeq     22
      14: new           #93                 // class java/lang/AssertionError
      17: dup
      18: invokespecial #94                 // Method java/lang/AssertionError."<init>":()V
      21: athrow
      22: aload_0
      23: aconst_null
      24: putfield      #128                // Field remoteProc:Lorg/apache/hadoop/hbase/master/assignment/RegionRemoteProcedureBase;
      27: return

  void stateLoaded(org.apache.hadoop.hbase.master.assignment.AssignmentManager, org.apache.hadoop.hbase.master.assignment.RegionStateNode);
    Code:
       0: aload_0
       1: getfield      #128                // Field remoteProc:Lorg/apache/hadoop/hbase/master/assignment/RegionRemoteProcedureBase;
       4: ifnull        16
       7: aload_0
       8: getfield      #128                // Field remoteProc:Lorg/apache/hadoop/hbase/master/assignment/RegionRemoteProcedureBase;
      11: aload_1
      12: aload_2
      13: invokevirtual #135                // Method org/apache/hadoop/hbase/master/assignment/RegionRemoteProcedureBase.stateLoaded:(Lorg/apache/hadoop/hbase/master/assignment/AssignmentManager;Lorg/apache/hadoop/hbase/master/assignment/RegionStateNode;)V
      16: return

  protected void rollbackState(org.apache.hadoop.hbase.master.procedure.MasterProcedureEnv, org.apache.hadoop.hbase.shaded.protobuf.generated.MasterProcedureProtos$RegionStateTransitionState) throws java.io.IOException, java.lang.InterruptedException;
    Code:
       0: new           #108                // class java/lang/UnsupportedOperationException
       3: dup
       4: invokespecial #136                // Method java/lang/UnsupportedOperationException."<init>":()V
       7: athrow

  protected org.apache.hadoop.hbase.shaded.protobuf.generated.MasterProcedureProtos$RegionStateTransitionState getState(int);
    Code:
       0: iload_1
       1: invokestatic  #137                // Method org/apache/hadoop/hbase/shaded/protobuf/generated/MasterProcedureProtos$RegionStateTransitionState.forNumber:(I)Lorg/apache/hadoop/hbase/shaded/protobuf/generated/MasterProcedureProtos$RegionStateTransitionState;
       4: areturn

  protected int getStateId(org.apache.hadoop.hbase.shaded.protobuf.generated.MasterProcedureProtos$RegionStateTransitionState);
    Code:
       0: aload_1
       1: invokevirtual #138                // Method org/apache/hadoop/hbase/shaded/protobuf/generated/MasterProcedureProtos$RegionStateTransitionState.getNumber:()I
       4: ireturn

  protected org.apache.hadoop.hbase.shaded.protobuf.generated.MasterProcedureProtos$RegionStateTransitionState getInitialState();
    Code:
       0: aload_0
       1: getfield      #6                  // Field initialState:Lorg/apache/hadoop/hbase/shaded/protobuf/generated/MasterProcedureProtos$RegionStateTransitionState;
       4: areturn

  protected void serializeStateData(org.apache.hadoop.hbase.procedure2.ProcedureStateSerializer) throws java.io.IOException;
    Code:
       0: aload_0
       1: aload_1
       2: invokespecial #150                // Method org/apache/hadoop/hbase/master/procedure/AbstractStateMachineRegionProcedure.serializeStateData:(Lorg/apache/hadoop/hbase/procedure2/ProcedureStateSerializer;)V
       5: invokestatic  #151                // Method org/apache/hadoop/hbase/shaded/protobuf/generated/MasterProcedureProtos$RegionStateTransitionStateData.newBuilder:()Lorg/apache/hadoop/hbase/shaded/protobuf/generated/MasterProcedureProtos$RegionStateTransitionStateData$Builder;
       8: aload_0
       9: getfield      #3                  // Field type:Lorg/apache/hadoop/hbase/master/assignment/TransitRegionStateProcedure$TransitionType;
      12: invokestatic  #152                // Method convert:(Lorg/apache/hadoop/hbase/master/assignment/TransitRegionStateProcedure$TransitionType;)Lorg/apache/hadoop/hbase/shaded/protobuf/generated/MasterProcedureProtos$RegionTransitionType;
      15: invokevirtual #153                // Method org/apache/hadoop/hbase/shaded/protobuf/generated/MasterProcedureProtos$RegionStateTransitionStateData$Builder.setType:(Lorg/apache/hadoop/hbase/shaded/protobuf/generated/MasterProcedureProtos$RegionTransitionType;)Lorg/apache/hadoop/hbase/shaded/protobuf/generated/MasterProcedureProtos$RegionStateTransitionStateData$Builder;
      18: aload_0
      19: getfield      #21                 // Field forceNewPlan:Z
      22: invokevirtual #154                // Method org/apache/hadoop/hbase/shaded/protobuf/generated/MasterProcedureProtos$RegionStateTransitionStateData$Builder.setForceNewPlan:(Z)Lorg/apache/hadoop/hbase/shaded/protobuf/generated/MasterProcedureProtos$RegionStateTransitionStateData$Builder;
      25: astore_2
      26: aload_0
      27: getfield      #20                 // Field assignCandidate:Lorg/apache/hadoop/hbase/ServerName;
      30: ifnull        45
      33: aload_2
      34: aload_0
      35: getfield      #20                 // Field assignCandidate:Lorg/apache/hadoop/hbase/ServerName;
      38: invokestatic  #155                // Method org/apache/hadoop/hbase/shaded/protobuf/ProtobufUtil.toServerName:(Lorg/apache/hadoop/hbase/ServerName;)Lorg/apache/hadoop/hbase/shaded/protobuf/generated/HBaseProtos$ServerName;
      41: invokevirtual #156                // Method org/apache/hadoop/hbase/shaded/protobuf/generated/MasterProcedureProtos$RegionStateTransitionStateData$Builder.setAssignCandidate:(Lorg/apache/hadoop/hbase/shaded/protobuf/generated/HBaseProtos$ServerName;)Lorg/apache/hadoop/hbase/shaded/protobuf/generated/MasterProcedureProtos$RegionStateTransitionStateData$Builder;
      44: pop
      45: aload_1
      46: aload_2
      47: invokevirtual #157                // Method org/apache/hadoop/hbase/shaded/protobuf/generated/MasterProcedureProtos$RegionStateTransitionStateData$Builder.build:()Lorg/apache/hadoop/hbase/shaded/protobuf/generated/MasterProcedureProtos$RegionStateTransitionStateData;
      50: invokeinterface #158,  2          // InterfaceMethod org/apache/hadoop/hbase/procedure2/ProcedureStateSerializer.serialize:(Lorg/apache/hbase/thirdparty/com/google/protobuf/Message;)V
      55: return

  protected void deserializeStateData(org.apache.hadoop.hbase.procedure2.ProcedureStateSerializer) throws java.io.IOException;
    Code:
       0: aload_0
       1: aload_1
       2: invokespecial #159                // Method org/apache/hadoop/hbase/master/procedure/AbstractStateMachineRegionProcedure.deserializeStateData:(Lorg/apache/hadoop/hbase/procedure2/ProcedureStateSerializer;)V
       5: aload_1
       6: ldc           #160                // class org/apache/hadoop/hbase/shaded/protobuf/generated/MasterProcedureProtos$RegionStateTransitionStateData
       8: invokeinterface #161,  2          // InterfaceMethod org/apache/hadoop/hbase/procedure2/ProcedureStateSerializer.deserialize:(Ljava/lang/Class;)Lorg/apache/hbase/thirdparty/com/google/protobuf/Message;
      13: checkcast     #160                // class org/apache/hadoop/hbase/shaded/protobuf/generated/MasterProcedureProtos$RegionStateTransitionStateData
      16: astore_2
      17: aload_0
      18: aload_2
      19: invokevirtual #162                // Method org/apache/hadoop/hbase/shaded/protobuf/generated/MasterProcedureProtos$RegionStateTransitionStateData.getType:()Lorg/apache/hadoop/hbase/shaded/protobuf/generated/MasterProcedureProtos$RegionTransitionType;
      22: invokestatic  #163                // Method convert:(Lorg/apache/hadoop/hbase/shaded/protobuf/generated/MasterProcedureProtos$RegionTransitionType;)Lorg/apache/hadoop/hbase/master/assignment/TransitRegionStateProcedure$TransitionType;
      25: putfield      #3                  // Field type:Lorg/apache/hadoop/hbase/master/assignment/TransitRegionStateProcedure$TransitionType;
      28: aload_0
      29: invokespecial #22                 // Method setInitalAndLastState:()V
      32: aload_0
      33: aload_2
      34: invokevirtual #164                // Method org/apache/hadoop/hbase/shaded/protobuf/generated/MasterProcedureProtos$RegionStateTransitionStateData.getForceNewPlan:()Z
      37: putfield      #21                 // Field forceNewPlan:Z
      40: aload_2
      41: invokevirtual #165                // Method org/apache/hadoop/hbase/shaded/protobuf/generated/MasterProcedureProtos$RegionStateTransitionStateData.hasAssignCandidate:()Z
      44: ifeq          58
      47: aload_0
      48: aload_2
      49: invokevirtual #166                // Method org/apache/hadoop/hbase/shaded/protobuf/generated/MasterProcedureProtos$RegionStateTransitionStateData.getAssignCandidate:()Lorg/apache/hadoop/hbase/shaded/protobuf/generated/HBaseProtos$ServerName;
      52: invokestatic  #167                // Method org/apache/hadoop/hbase/shaded/protobuf/ProtobufUtil.toServerName:(Lorg/apache/hadoop/hbase/shaded/protobuf/generated/HBaseProtos$ServerName;)Lorg/apache/hadoop/hbase/ServerName;
      55: putfield      #20                 // Field assignCandidate:Lorg/apache/hadoop/hbase/ServerName;
      58: return

  protected org.apache.hadoop.hbase.procedure2.ProcedureMetrics getProcedureMetrics(org.apache.hadoop.hbase.master.procedure.MasterProcedureEnv);
    Code:
       0: aload_1
       1: invokevirtual #26                 // Method org/apache/hadoop/hbase/master/procedure/MasterProcedureEnv.getAssignmentManager:()Lorg/apache/hadoop/hbase/master/assignment/AssignmentManager;
       4: invokevirtual #168                // Method org/apache/hadoop/hbase/master/assignment/AssignmentManager.getAssignmentManagerMetrics:()Lorg/apache/hadoop/hbase/master/MetricsAssignmentManager;
       7: astore_2
       8: getstatic     #2                  // Field org/apache/hadoop/hbase/master/assignment/TransitRegionStateProcedure$1.$SwitchMap$org$apache$hadoop$hbase$master$assignment$TransitRegionStateProcedure$TransitionType:[I
      11: aload_0
      12: getfield      #3                  // Field type:Lorg/apache/hadoop/hbase/master/assignment/TransitRegionStateProcedure$TransitionType;
      15: invokevirtual #4                  // Method org/apache/hadoop/hbase/master/assignment/TransitRegionStateProcedure$TransitionType.ordinal:()I
      18: iaload
      19: tableswitch   { // 1 to 4
                     1: 48
                     2: 53
                     3: 58
                     4: 63
               default: 68
          }
      48: aload_2
      49: invokevirtual #169                // Method org/apache/hadoop/hbase/master/MetricsAssignmentManager.getAssignProcMetrics:()Lorg/apache/hadoop/hbase/procedure2/ProcedureMetrics;
      52: areturn
      53: aload_2
      54: invokevirtual #170                // Method org/apache/hadoop/hbase/master/MetricsAssignmentManager.getUnassignProcMetrics:()Lorg/apache/hadoop/hbase/procedure2/ProcedureMetrics;
      57: areturn
      58: aload_2
      59: invokevirtual #171                // Method org/apache/hadoop/hbase/master/MetricsAssignmentManager.getMoveProcMetrics:()Lorg/apache/hadoop/hbase/procedure2/ProcedureMetrics;
      62: areturn
      63: aload_2
      64: invokevirtual #172                // Method org/apache/hadoop/hbase/master/MetricsAssignmentManager.getReopenProcMetrics:()Lorg/apache/hadoop/hbase/procedure2/ProcedureMetrics;
      67: areturn
      68: new           #11                 // class java/lang/IllegalArgumentException
      71: dup
      72: new           #12                 // class java/lang/StringBuilder
      75: dup
      76: invokespecial #13                 // Method java/lang/StringBuilder."<init>":()V
      79: ldc           #173                // String Unknown transition type:
      81: invokevirtual #15                 // Method java/lang/StringBuilder.append:(Ljava/lang/String;)Ljava/lang/StringBuilder;
      84: aload_0
      85: getfield      #3                  // Field type:Lorg/apache/hadoop/hbase/master/assignment/TransitRegionStateProcedure$TransitionType;
      88: invokevirtual #16                 // Method java/lang/StringBuilder.append:(Ljava/lang/Object;)Ljava/lang/StringBuilder;
      91: invokevirtual #17                 // Method java/lang/StringBuilder.toString:()Ljava/lang/String;
      94: invokespecial #18                 // Method java/lang/IllegalArgumentException."<init>":(Ljava/lang/String;)V
      97: athrow

  public void toStringClassDetails(java.lang.StringBuilder);
    Code:
       0: aload_0
       1: aload_1
       2: invokespecial #174                // Method org/apache/hadoop/hbase/master/procedure/AbstractStateMachineRegionProcedure.toStringClassDetails:(Ljava/lang/StringBuilder;)V
       5: aload_0
       6: getfield      #6                  // Field initialState:Lorg/apache/hadoop/hbase/shaded/protobuf/generated/MasterProcedureProtos$RegionStateTransitionState;
       9: getstatic     #5                  // Field org/apache/hadoop/hbase/shaded/protobuf/generated/MasterProcedureProtos$RegionStateTransitionState.REGION_STATE_TRANSITION_GET_ASSIGN_CANDIDATE:Lorg/apache/hadoop/hbase/shaded/protobuf/generated/MasterProcedureProtos$RegionStateTransitionState;
      12: if_acmpne     25
      15: aload_1
      16: ldc           #175                // String , ASSIGN
      18: invokevirtual #15                 // Method java/lang/StringBuilder.append:(Ljava/lang/String;)Ljava/lang/StringBuilder;
      21: pop
      22: goto          52
      25: aload_0
      26: getfield      #8                  // Field lastState:Lorg/apache/hadoop/hbase/shaded/protobuf/generated/MasterProcedureProtos$RegionStateTransitionState;
      29: getstatic     #10                 // Field org/apache/hadoop/hbase/shaded/protobuf/generated/MasterProcedureProtos$RegionStateTransitionState.REGION_STATE_TRANSITION_CONFIRM_CLOSED:Lorg/apache/hadoop/hbase/shaded/protobuf/generated/MasterProcedureProtos$RegionStateTransitionState;
      32: if_acmpne     45
      35: aload_1
      36: ldc           #176                // String , UNASSIGN
      38: invokevirtual #15                 // Method java/lang/StringBuilder.append:(Ljava/lang/String;)Ljava/lang/StringBuilder;
      41: pop
      42: goto          52
      45: aload_1
      46: ldc           #177                // String , REOPEN/MOVE
      48: invokevirtual #15                 // Method java/lang/StringBuilder.append:(Ljava/lang/String;)Ljava/lang/StringBuilder;
      51: pop
      52: return

  public static org.apache.hadoop.hbase.master.assignment.TransitRegionStateProcedure assign(org.apache.hadoop.hbase.master.procedure.MasterProcedureEnv, org.apache.hadoop.hbase.client.RegionInfo, org.apache.hadoop.hbase.ServerName);
    Code:
       0: aload_0
       1: new           #181                // class org/apache/hadoop/hbase/master/assignment/TransitRegionStateProcedure
       4: dup
       5: aload_0
       6: aload_1
       7: aload_2
       8: iconst_0
       9: getstatic     #141                // Field org/apache/hadoop/hbase/master/assignment/TransitRegionStateProcedure$TransitionType.ASSIGN:Lorg/apache/hadoop/hbase/master/assignment/TransitRegionStateProcedure$TransitionType;
      12: invokespecial #182                // Method "<init>":(Lorg/apache/hadoop/hbase/master/procedure/MasterProcedureEnv;Lorg/apache/hadoop/hbase/client/RegionInfo;Lorg/apache/hadoop/hbase/ServerName;ZLorg/apache/hadoop/hbase/master/assignment/TransitRegionStateProcedure$TransitionType;)V
      15: invokestatic  #183                // Method setOwner:(Lorg/apache/hadoop/hbase/master/procedure/MasterProcedureEnv;Lorg/apache/hadoop/hbase/master/assignment/TransitRegionStateProcedure;)Lorg/apache/hadoop/hbase/master/assignment/TransitRegionStateProcedure;
      18: areturn

  public static org.apache.hadoop.hbase.master.assignment.TransitRegionStateProcedure unassign(org.apache.hadoop.hbase.master.procedure.MasterProcedureEnv, org.apache.hadoop.hbase.client.RegionInfo);
    Code:
       0: aload_0
       1: new           #181                // class org/apache/hadoop/hbase/master/assignment/TransitRegionStateProcedure
       4: dup
       5: aload_0
       6: aload_1
       7: aconst_null
       8: iconst_0
       9: getstatic     #142                // Field org/apache/hadoop/hbase/master/assignment/TransitRegionStateProcedure$TransitionType.UNASSIGN:Lorg/apache/hadoop/hbase/master/assignment/TransitRegionStateProcedure$TransitionType;
      12: invokespecial #182                // Method "<init>":(Lorg/apache/hadoop/hbase/master/procedure/MasterProcedureEnv;Lorg/apache/hadoop/hbase/client/RegionInfo;Lorg/apache/hadoop/hbase/ServerName;ZLorg/apache/hadoop/hbase/master/assignment/TransitRegionStateProcedure$TransitionType;)V
      15: invokestatic  #183                // Method setOwner:(Lorg/apache/hadoop/hbase/master/procedure/MasterProcedureEnv;Lorg/apache/hadoop/hbase/master/assignment/TransitRegionStateProcedure;)Lorg/apache/hadoop/hbase/master/assignment/TransitRegionStateProcedure;
      18: areturn

  public static org.apache.hadoop.hbase.master.assignment.TransitRegionStateProcedure reopen(org.apache.hadoop.hbase.master.procedure.MasterProcedureEnv, org.apache.hadoop.hbase.client.RegionInfo);
    Code:
       0: aload_0
       1: new           #181                // class org/apache/hadoop/hbase/master/assignment/TransitRegionStateProcedure
       4: dup
       5: aload_0
       6: aload_1
       7: aconst_null
       8: iconst_0
       9: getstatic     #144                // Field org/apache/hadoop/hbase/master/assignment/TransitRegionStateProcedure$TransitionType.REOPEN:Lorg/apache/hadoop/hbase/master/assignment/TransitRegionStateProcedure$TransitionType;
      12: invokespecial #182                // Method "<init>":(Lorg/apache/hadoop/hbase/master/procedure/MasterProcedureEnv;Lorg/apache/hadoop/hbase/client/RegionInfo;Lorg/apache/hadoop/hbase/ServerName;ZLorg/apache/hadoop/hbase/master/assignment/TransitRegionStateProcedure$TransitionType;)V
      15: invokestatic  #183                // Method setOwner:(Lorg/apache/hadoop/hbase/master/procedure/MasterProcedureEnv;Lorg/apache/hadoop/hbase/master/assignment/TransitRegionStateProcedure;)Lorg/apache/hadoop/hbase/master/assignment/TransitRegionStateProcedure;
      18: areturn

  public static org.apache.hadoop.hbase.master.assignment.TransitRegionStateProcedure move(org.apache.hadoop.hbase.master.procedure.MasterProcedureEnv, org.apache.hadoop.hbase.client.RegionInfo, org.apache.hadoop.hbase.ServerName);
    Code:
       0: aload_0
       1: new           #181                // class org/apache/hadoop/hbase/master/assignment/TransitRegionStateProcedure
       4: dup
       5: aload_0
       6: aload_1
       7: aload_2
       8: aload_2
       9: ifnonnull     16
      12: iconst_1
      13: goto          17
      16: iconst_0
      17: getstatic     #143                // Field org/apache/hadoop/hbase/master/assignment/TransitRegionStateProcedure$TransitionType.MOVE:Lorg/apache/hadoop/hbase/master/assignment/TransitRegionStateProcedure$TransitionType;
      20: invokespecial #182                // Method "<init>":(Lorg/apache/hadoop/hbase/master/procedure/MasterProcedureEnv;Lorg/apache/hadoop/hbase/client/RegionInfo;Lorg/apache/hadoop/hbase/ServerName;ZLorg/apache/hadoop/hbase/master/assignment/TransitRegionStateProcedure$TransitionType;)V
      23: invokestatic  #183                // Method setOwner:(Lorg/apache/hadoop/hbase/master/procedure/MasterProcedureEnv;Lorg/apache/hadoop/hbase/master/assignment/TransitRegionStateProcedure;)Lorg/apache/hadoop/hbase/master/assignment/TransitRegionStateProcedure;
      26: areturn

  protected org.apache.hadoop.hbase.procedure2.Procedure[] execute(java.lang.Object) throws org.apache.hadoop.hbase.procedure2.ProcedureSuspendedException, org.apache.hadoop.hbase.procedure2.ProcedureYieldException, java.lang.InterruptedException;
    Code:
       0: aload_0
       1: aload_1
       2: checkcast     #184                // class org/apache/hadoop/hbase/master/procedure/MasterProcedureEnv
       5: invokevirtual #185                // Method execute:(Lorg/apache/hadoop/hbase/master/procedure/MasterProcedureEnv;)[Lorg/apache/hadoop/hbase/procedure2/Procedure;
       8: areturn

  protected java.lang.Object getInitialState();
    Code:
       0: aload_0
       1: invokevirtual #186                // Method getInitialState:()Lorg/apache/hadoop/hbase/shaded/protobuf/generated/MasterProcedureProtos$RegionStateTransitionState;
       4: areturn

  protected int getStateId(java.lang.Object);
    Code:
       0: aload_0
       1: aload_1
       2: checkcast     #187                // class org/apache/hadoop/hbase/shaded/protobuf/generated/MasterProcedureProtos$RegionStateTransitionState
       5: invokevirtual #188                // Method getStateId:(Lorg/apache/hadoop/hbase/shaded/protobuf/generated/MasterProcedureProtos$RegionStateTransitionState;)I
       8: ireturn

  protected java.lang.Object getState(int);
    Code:
       0: aload_0
       1: iload_1
       2: invokevirtual #189                // Method getState:(I)Lorg/apache/hadoop/hbase/shaded/protobuf/generated/MasterProcedureProtos$RegionStateTransitionState;
       5: areturn

  protected void rollbackState(java.lang.Object, java.lang.Object) throws java.io.IOException, java.lang.InterruptedException;
    Code:
       0: aload_0
       1: aload_1
       2: checkcast     #184                // class org/apache/hadoop/hbase/master/procedure/MasterProcedureEnv
       5: aload_2
       6: checkcast     #187                // class org/apache/hadoop/hbase/shaded/protobuf/generated/MasterProcedureProtos$RegionStateTransitionState
       9: invokevirtual #190                // Method rollbackState:(Lorg/apache/hadoop/hbase/master/procedure/MasterProcedureEnv;Lorg/apache/hadoop/hbase/shaded/protobuf/generated/MasterProcedureProtos$RegionStateTransitionState;)V
      12: return

  protected org.apache.hadoop.hbase.procedure2.StateMachineProcedure$Flow executeFromState(java.lang.Object, java.lang.Object) throws org.apache.hadoop.hbase.procedure2.ProcedureSuspendedException, org.apache.hadoop.hbase.procedure2.ProcedureYieldException, java.lang.InterruptedException;
    Code:
       0: aload_0
       1: aload_1
       2: checkcast     #184                // class org/apache/hadoop/hbase/master/procedure/MasterProcedureEnv
       5: aload_2
       6: checkcast     #187                // class org/apache/hadoop/hbase/shaded/protobuf/generated/MasterProcedureProtos$RegionStateTransitionState
       9: invokevirtual #191                // Method executeFromState:(Lorg/apache/hadoop/hbase/master/procedure/MasterProcedureEnv;Lorg/apache/hadoop/hbase/shaded/protobuf/generated/MasterProcedureProtos$RegionStateTransitionState;)Lorg/apache/hadoop/hbase/procedure2/StateMachineProcedure$Flow;
      12: areturn

  protected boolean setTimeoutFailure(java.lang.Object);
    Code:
       0: aload_0
       1: aload_1
       2: checkcast     #184                // class org/apache/hadoop/hbase/master/procedure/MasterProcedureEnv
       5: invokevirtual #192                // Method setTimeoutFailure:(Lorg/apache/hadoop/hbase/master/procedure/MasterProcedureEnv;)Z
       8: ireturn

  protected org.apache.hadoop.hbase.procedure2.ProcedureMetrics getProcedureMetrics(java.lang.Object);
    Code:
       0: aload_0
       1: aload_1
       2: checkcast     #184                // class org/apache/hadoop/hbase/master/procedure/MasterProcedureEnv
       5: invokevirtual #193                // Method getProcedureMetrics:(Lorg/apache/hadoop/hbase/master/procedure/MasterProcedureEnv;)Lorg/apache/hadoop/hbase/procedure2/ProcedureMetrics;
       8: areturn

  protected boolean waitInitialized(java.lang.Object);
    Code:
       0: aload_0
       1: aload_1
       2: checkcast     #184                // class org/apache/hadoop/hbase/master/procedure/MasterProcedureEnv
       5: invokevirtual #194                // Method waitInitialized:(Lorg/apache/hadoop/hbase/master/procedure/MasterProcedureEnv;)Z
       8: ireturn

  static {};
    Code:
       0: ldc           #181                // class org/apache/hadoop/hbase/master/assignment/TransitRegionStateProcedure
       2: invokevirtual #195                // Method java/lang/Class.desiredAssertionStatus:()Z
       5: ifne          12
       8: iconst_1
       9: goto          13
      12: iconst_0
      13: putstatic     #91                 // Field $assertionsDisabled:Z
      16: ldc           #181                // class org/apache/hadoop/hbase/master/assignment/TransitRegionStateProcedure
      18: invokestatic  #196                // Method org/slf4j/LoggerFactory.getLogger:(Ljava/lang/Class;)Lorg/slf4j/Logger;
      21: putstatic     #33                 // Field LOG:Lorg/slf4j/Logger;
      24: return
}
