Compiled from "UnsafeAccess.java"
final class org.apache.hadoop.hbase.util.UnsafeAccess$1 implements java.security.PrivilegedAction<java.lang.Object> {
  org.apache.hadoop.hbase.util.UnsafeAccess$1();
    Code:
       0: aload_0
       1: invokespecial #1                  // Method java/lang/Object."<init>":()V
       4: return

  public java.lang.Object run();
    Code:
       0: ldc           #2                  // class sun/misc/Unsafe
       2: ldc           #3                  // String theUnsafe
       4: invokevirtual #4                  // Method java/lang/Class.getDeclaredField:(Ljava/lang/String;)Ljava/lang/reflect/Field;
       7: astore_1
       8: aload_1
       9: iconst_1
      10: invokevirtual #5                  // Method java/lang/reflect/Field.setAccessible:(Z)V
      13: aload_1
      14: aconst_null
      15: invokevirtual #6                  // Method java/lang/reflect/Field.get:(Ljava/lang/Object;)Ljava/lang/Object;
      18: areturn
      19: astore_1
      20: invokestatic  #8                  // Method org/apache/hadoop/hbase/util/UnsafeAccess.access$000:()Lorg/slf4j/Logger;
      23: ldc           #9                  // String sun.misc.Unsafe is not accessible
      25: aload_1
      26: invokeinterface #10,  3           // InterfaceMethod org/slf4j/Logger.warn:(Ljava/lang/String;Ljava/lang/Throwable;)V
      31: aconst_null
      32: areturn
    Exception table:
       from    to  target type
           0    18    19   Class java/lang/Throwable
}
