Compiled from "UpdatePeerConfigProcedure.java"
public class org.apache.hadoop.hbase.master.replication.UpdatePeerConfigProcedure extends org.apache.hadoop.hbase.master.replication.ModifyPeerProcedure {
  static final boolean $assertionsDisabled;

  public org.apache.hadoop.hbase.master.replication.UpdatePeerConfigProcedure();
    Code:
       0: aload_0
       1: invokespecial #1                  // Method org/apache/hadoop/hbase/master/replication/ModifyPeerProcedure."<init>":()V
       4: return

  public org.apache.hadoop.hbase.master.replication.UpdatePeerConfigProcedure(java.lang.String, org.apache.hadoop.hbase.replication.ReplicationPeerConfig);
    Code:
       0: aload_0
       1: aload_1
       2: invokespecial #2                  // Method org/apache/hadoop/hbase/master/replication/ModifyPeerProcedure."<init>":(Ljava/lang/String;)V
       5: aload_0
       6: aload_2
       7: putfield      #3                  // Field peerConfig:Lorg/apache/hadoop/hbase/replication/ReplicationPeerConfig;
      10: return

  public org.apache.hadoop.hbase.master.procedure.PeerProcedureInterface$PeerOperationType getPeerOperationType();
    Code:
       0: getstatic     #4                  // Field org/apache/hadoop/hbase/master/procedure/PeerProcedureInterface$PeerOperationType.UPDATE_CONFIG:Lorg/apache/hadoop/hbase/master/procedure/PeerProcedureInterface$PeerOperationType;
       3: areturn

  protected org.apache.hadoop.hbase.shaded.protobuf.generated.MasterProcedureProtos$PeerModificationState nextStateAfterRefresh();
    Code:
       0: aload_0
       1: getfield      #3                  // Field peerConfig:Lorg/apache/hadoop/hbase/replication/ReplicationPeerConfig;
       4: invokevirtual #11                 // Method org/apache/hadoop/hbase/replication/ReplicationPeerConfig.isSerial:()Z
       7: ifeq          49
      10: aload_0
      11: getfield      #12                 // Field oldPeerConfig:Lorg/apache/hadoop/hbase/replication/ReplicationPeerConfig;
      14: invokevirtual #11                 // Method org/apache/hadoop/hbase/replication/ReplicationPeerConfig.isSerial:()Z
      17: ifeq          45
      20: aload_0
      21: getfield      #3                  // Field peerConfig:Lorg/apache/hadoop/hbase/replication/ReplicationPeerConfig;
      24: aload_0
      25: getfield      #12                 // Field oldPeerConfig:Lorg/apache/hadoop/hbase/replication/ReplicationPeerConfig;
      28: invokestatic  #13                 // Method org/apache/hadoop/hbase/replication/ReplicationUtils.isNamespacesAndTableCFsEqual:(Lorg/apache/hadoop/hbase/replication/ReplicationPeerConfig;Lorg/apache/hadoop/hbase/replication/ReplicationPeerConfig;)Z
      31: ifeq          41
      34: aload_0
      35: invokespecial #14                 // Method org/apache/hadoop/hbase/master/replication/ModifyPeerProcedure.nextStateAfterRefresh:()Lorg/apache/hadoop/hbase/shaded/protobuf/generated/MasterProcedureProtos$PeerModificationState;
      38: goto          44
      41: getstatic     #15                 // Field org/apache/hadoop/hbase/shaded/protobuf/generated/MasterProcedureProtos$PeerModificationState.SERIAL_PEER_REOPEN_REGIONS:Lorg/apache/hadoop/hbase/shaded/protobuf/generated/MasterProcedureProtos$PeerModificationState;
      44: areturn
      45: getstatic     #15                 // Field org/apache/hadoop/hbase/shaded/protobuf/generated/MasterProcedureProtos$PeerModificationState.SERIAL_PEER_REOPEN_REGIONS:Lorg/apache/hadoop/hbase/shaded/protobuf/generated/MasterProcedureProtos$PeerModificationState;
      48: areturn
      49: aload_0
      50: getfield      #12                 // Field oldPeerConfig:Lorg/apache/hadoop/hbase/replication/ReplicationPeerConfig;
      53: invokevirtual #11                 // Method org/apache/hadoop/hbase/replication/ReplicationPeerConfig.isSerial:()Z
      56: ifeq          63
      59: getstatic     #16                 // Field org/apache/hadoop/hbase/shaded/protobuf/generated/MasterProcedureProtos$PeerModificationState.SERIAL_PEER_UPDATE_LAST_PUSHED_SEQ_ID:Lorg/apache/hadoop/hbase/shaded/protobuf/generated/MasterProcedureProtos$PeerModificationState;
      62: areturn
      63: aload_0
      64: invokespecial #14                 // Method org/apache/hadoop/hbase/master/replication/ModifyPeerProcedure.nextStateAfterRefresh:()Lorg/apache/hadoop/hbase/shaded/protobuf/generated/MasterProcedureProtos$PeerModificationState;
      67: areturn

  protected void updateLastPushedSequenceIdForSerialPeer(org.apache.hadoop.hbase.master.procedure.MasterProcedureEnv) throws java.io.IOException, org.apache.hadoop.hbase.replication.ReplicationException;
    Code:
       0: aload_0
       1: getfield      #12                 // Field oldPeerConfig:Lorg/apache/hadoop/hbase/replication/ReplicationPeerConfig;
       4: invokevirtual #11                 // Method org/apache/hadoop/hbase/replication/ReplicationPeerConfig.isSerial:()Z
       7: ifne          44
      10: getstatic     #17                 // Field $assertionsDisabled:Z
      13: ifne          34
      16: aload_0
      17: getfield      #3                  // Field peerConfig:Lorg/apache/hadoop/hbase/replication/ReplicationPeerConfig;
      20: invokevirtual #11                 // Method org/apache/hadoop/hbase/replication/ReplicationPeerConfig.isSerial:()Z
      23: ifne          34
      26: new           #18                 // class java/lang/AssertionError
      29: dup
      30: invokespecial #19                 // Method java/lang/AssertionError."<init>":()V
      33: athrow
      34: aload_0
      35: aload_1
      36: aload_0
      37: getfield      #3                  // Field peerConfig:Lorg/apache/hadoop/hbase/replication/ReplicationPeerConfig;
      40: invokevirtual #20                 // Method setLastPushedSequenceId:(Lorg/apache/hadoop/hbase/master/procedure/MasterProcedureEnv;Lorg/apache/hadoop/hbase/replication/ReplicationPeerConfig;)V
      43: return
      44: aload_0
      45: getfield      #3                  // Field peerConfig:Lorg/apache/hadoop/hbase/replication/ReplicationPeerConfig;
      48: invokevirtual #11                 // Method org/apache/hadoop/hbase/replication/ReplicationPeerConfig.isSerial:()Z
      51: ifne          66
      54: aload_1
      55: invokevirtual #21                 // Method org/apache/hadoop/hbase/master/procedure/MasterProcedureEnv.getReplicationPeerManager:()Lorg/apache/hadoop/hbase/master/replication/ReplicationPeerManager;
      58: aload_0
      59: getfield      #8                  // Field peerId:Ljava/lang/String;
      62: invokevirtual #22                 // Method org/apache/hadoop/hbase/master/replication/ReplicationPeerManager.removeAllLastPushedSeqIds:(Ljava/lang/String;)V
      65: return
      66: aload_1
      67: invokevirtual #21                 // Method org/apache/hadoop/hbase/master/procedure/MasterProcedureEnv.getReplicationPeerManager:()Lorg/apache/hadoop/hbase/master/replication/ReplicationPeerManager;
      70: invokevirtual #23                 // Method org/apache/hadoop/hbase/master/replication/ReplicationPeerManager.getQueueStorage:()Lorg/apache/hadoop/hbase/replication/ReplicationQueueStorage;
      73: astore_2
      74: aload_1
      75: invokevirtual #24                 // Method org/apache/hadoop/hbase/master/procedure/MasterProcedureEnv.getMasterServices:()Lorg/apache/hadoop/hbase/master/MasterServices;
      78: invokeinterface #25,  1           // InterfaceMethod org/apache/hadoop/hbase/master/MasterServices.getConnection:()Lorg/apache/hadoop/hbase/client/Connection;
      83: astore_3
      84: new           #26                 // class java/util/HashMap
      87: dup
      88: invokespecial #27                 // Method java/util/HashMap."<init>":()V
      91: astore        4
      93: new           #28                 // class java/util/ArrayList
      96: dup
      97: invokespecial #29                 // Method java/util/ArrayList."<init>":()V
     100: astore        5
     102: aload_1
     103: invokevirtual #24                 // Method org/apache/hadoop/hbase/master/procedure/MasterProcedureEnv.getMasterServices:()Lorg/apache/hadoop/hbase/master/MasterServices;
     106: invokeinterface #30,  1           // InterfaceMethod org/apache/hadoop/hbase/master/MasterServices.getTableDescriptors:()Lorg/apache/hadoop/hbase/TableDescriptors;
     111: invokeinterface #31,  1           // InterfaceMethod org/apache/hadoop/hbase/TableDescriptors.getAll:()Ljava/util/Map;
     116: invokeinterface #32,  1           // InterfaceMethod java/util/Map.values:()Ljava/util/Collection;
     121: invokeinterface #33,  1           // InterfaceMethod java/util/Collection.iterator:()Ljava/util/Iterator;
     126: astore        6
     128: aload         6
     130: invokeinterface #34,  1           // InterfaceMethod java/util/Iterator.hasNext:()Z
     135: ifeq          270
     138: aload         6
     140: invokeinterface #35,  1           // InterfaceMethod java/util/Iterator.next:()Ljava/lang/Object;
     145: checkcast     #36                 // class org/apache/hadoop/hbase/client/TableDescriptor
     148: astore        7
     150: aload         7
     152: invokeinterface #37,  1           // InterfaceMethod org/apache/hadoop/hbase/client/TableDescriptor.hasGlobalReplicationScope:()Z
     157: ifne          163
     160: goto          128
     163: aload         7
     165: invokeinterface #38,  1           // InterfaceMethod org/apache/hadoop/hbase/client/TableDescriptor.getTableName:()Lorg/apache/hadoop/hbase/TableName;
     170: astore        8
     172: aload_0
     173: getfield      #12                 // Field oldPeerConfig:Lorg/apache/hadoop/hbase/replication/ReplicationPeerConfig;
     176: aload         8
     178: invokestatic  #39                 // Method org/apache/hadoop/hbase/replication/ReplicationUtils.contains:(Lorg/apache/hadoop/hbase/replication/ReplicationPeerConfig;Lorg/apache/hadoop/hbase/TableName;)Z
     181: ifeq          246
     184: aload_0
     185: getfield      #3                  // Field peerConfig:Lorg/apache/hadoop/hbase/replication/ReplicationPeerConfig;
     188: aload         8
     190: invokestatic  #39                 // Method org/apache/hadoop/hbase/replication/ReplicationUtils.contains:(Lorg/apache/hadoop/hbase/replication/ReplicationPeerConfig;Lorg/apache/hadoop/hbase/TableName;)Z
     193: ifne          267
     196: aload_3
     197: aload         8
     199: invokestatic  #40                 // Method org/apache/hadoop/hbase/MetaTableAccessor.getTableEncodedRegionNamesForSerialReplication:(Lorg/apache/hadoop/hbase/client/Connection;Lorg/apache/hadoop/hbase/TableName;)Ljava/util/List;
     202: invokeinterface #41,  1           // InterfaceMethod java/util/List.iterator:()Ljava/util/Iterator;
     207: astore        9
     209: aload         9
     211: invokeinterface #34,  1           // InterfaceMethod java/util/Iterator.hasNext:()Z
     216: ifeq          243
     219: aload         9
     221: invokeinterface #35,  1           // InterfaceMethod java/util/Iterator.next:()Ljava/lang/Object;
     226: checkcast     #42                 // class java/lang/String
     229: astore        10
     231: aload_0
     232: aload         5
     234: aload         10
     236: aload_2
     237: invokespecial #43                 // Method addToList:(Ljava/util/List;Ljava/lang/String;Lorg/apache/hadoop/hbase/replication/ReplicationQueueStorage;)V
     240: goto          209
     243: goto          267
     246: aload_0
     247: getfield      #3                  // Field peerConfig:Lorg/apache/hadoop/hbase/replication/ReplicationPeerConfig;
     250: aload         8
     252: invokestatic  #39                 // Method org/apache/hadoop/hbase/replication/ReplicationUtils.contains:(Lorg/apache/hadoop/hbase/replication/ReplicationPeerConfig;Lorg/apache/hadoop/hbase/TableName;)Z
     255: ifeq          267
     258: aload_0
     259: aload_1
     260: aload         8
     262: aload         4
     264: invokevirtual #44                 // Method setLastPushedSequenceIdForTable:(Lorg/apache/hadoop/hbase/master/procedure/MasterProcedureEnv;Lorg/apache/hadoop/hbase/TableName;Ljava/util/Map;)V
     267: goto          128
     270: aload         5
     272: invokeinterface #45,  1           // InterfaceMethod java/util/List.isEmpty:()Z
     277: ifne          292
     280: aload_2
     281: aload_0
     282: getfield      #8                  // Field peerId:Ljava/lang/String;
     285: aload         5
     287: invokeinterface #9,  3            // InterfaceMethod org/apache/hadoop/hbase/replication/ReplicationQueueStorage.removeLastSequenceIds:(Ljava/lang/String;Ljava/util/List;)V
     292: aload         4
     294: invokeinterface #46,  1           // InterfaceMethod java/util/Map.isEmpty:()Z
     299: ifne          314
     302: aload_2
     303: aload_0
     304: getfield      #8                  // Field peerId:Ljava/lang/String;
     307: aload         4
     309: invokeinterface #47,  3           // InterfaceMethod org/apache/hadoop/hbase/replication/ReplicationQueueStorage.setLastSequenceIds:(Ljava/lang/String;Ljava/util/Map;)V
     314: return

  protected boolean enablePeerBeforeFinish();
    Code:
       0: aload_0
       1: getfield      #48                 // Field enabled:Z
       4: ireturn

  protected org.apache.hadoop.hbase.replication.ReplicationPeerConfig getOldPeerConfig();
    Code:
       0: aload_0
       1: getfield      #12                 // Field oldPeerConfig:Lorg/apache/hadoop/hbase/replication/ReplicationPeerConfig;
       4: areturn

  protected org.apache.hadoop.hbase.replication.ReplicationPeerConfig getNewPeerConfig();
    Code:
       0: aload_0
       1: getfield      #3                  // Field peerConfig:Lorg/apache/hadoop/hbase/replication/ReplicationPeerConfig;
       4: areturn

  protected void prePeerModification(org.apache.hadoop.hbase.master.procedure.MasterProcedureEnv) throws java.io.IOException;
    Code:
       0: aload_1
       1: invokevirtual #49                 // Method org/apache/hadoop/hbase/master/procedure/MasterProcedureEnv.getMasterCoprocessorHost:()Lorg/apache/hadoop/hbase/master/MasterCoprocessorHost;
       4: astore_2
       5: aload_2
       6: ifnull        21
       9: aload_2
      10: aload_0
      11: getfield      #8                  // Field peerId:Ljava/lang/String;
      14: aload_0
      15: getfield      #3                  // Field peerConfig:Lorg/apache/hadoop/hbase/replication/ReplicationPeerConfig;
      18: invokevirtual #50                 // Method org/apache/hadoop/hbase/master/MasterCoprocessorHost.preUpdateReplicationPeerConfig:(Ljava/lang/String;Lorg/apache/hadoop/hbase/replication/ReplicationPeerConfig;)V
      21: aload_1
      22: invokevirtual #21                 // Method org/apache/hadoop/hbase/master/procedure/MasterProcedureEnv.getReplicationPeerManager:()Lorg/apache/hadoop/hbase/master/replication/ReplicationPeerManager;
      25: aload_0
      26: getfield      #8                  // Field peerId:Ljava/lang/String;
      29: aload_0
      30: getfield      #3                  // Field peerConfig:Lorg/apache/hadoop/hbase/replication/ReplicationPeerConfig;
      33: invokevirtual #51                 // Method org/apache/hadoop/hbase/master/replication/ReplicationPeerManager.preUpdatePeerConfig:(Ljava/lang/String;Lorg/apache/hadoop/hbase/replication/ReplicationPeerConfig;)Lorg/apache/hadoop/hbase/replication/ReplicationPeerDescription;
      36: astore_3
      37: aload_0
      38: aload_3
      39: invokevirtual #52                 // Method org/apache/hadoop/hbase/replication/ReplicationPeerDescription.getPeerConfig:()Lorg/apache/hadoop/hbase/replication/ReplicationPeerConfig;
      42: putfield      #12                 // Field oldPeerConfig:Lorg/apache/hadoop/hbase/replication/ReplicationPeerConfig;
      45: aload_0
      46: aload_3
      47: invokevirtual #53                 // Method org/apache/hadoop/hbase/replication/ReplicationPeerDescription.isEnabled:()Z
      50: putfield      #48                 // Field enabled:Z
      53: return

  protected void updatePeerStorage(org.apache.hadoop.hbase.master.procedure.MasterProcedureEnv) throws org.apache.hadoop.hbase.replication.ReplicationException;
    Code:
       0: aload_1
       1: invokevirtual #21                 // Method org/apache/hadoop/hbase/master/procedure/MasterProcedureEnv.getReplicationPeerManager:()Lorg/apache/hadoop/hbase/master/replication/ReplicationPeerManager;
       4: aload_0
       5: getfield      #8                  // Field peerId:Ljava/lang/String;
       8: aload_0
       9: getfield      #3                  // Field peerConfig:Lorg/apache/hadoop/hbase/replication/ReplicationPeerConfig;
      12: invokevirtual #54                 // Method org/apache/hadoop/hbase/master/replication/ReplicationPeerManager.updatePeerConfig:(Ljava/lang/String;Lorg/apache/hadoop/hbase/replication/ReplicationPeerConfig;)V
      15: aload_0
      16: getfield      #48                 // Field enabled:Z
      19: ifeq          44
      22: aload_0
      23: invokevirtual #55                 // Method nextStateAfterRefresh:()Lorg/apache/hadoop/hbase/shaded/protobuf/generated/MasterProcedureProtos$PeerModificationState;
      26: aload_0
      27: invokespecial #14                 // Method org/apache/hadoop/hbase/master/replication/ModifyPeerProcedure.nextStateAfterRefresh:()Lorg/apache/hadoop/hbase/shaded/protobuf/generated/MasterProcedureProtos$PeerModificationState;
      30: if_acmpeq     44
      33: aload_1
      34: invokevirtual #21                 // Method org/apache/hadoop/hbase/master/procedure/MasterProcedureEnv.getReplicationPeerManager:()Lorg/apache/hadoop/hbase/master/replication/ReplicationPeerManager;
      37: aload_0
      38: getfield      #8                  // Field peerId:Ljava/lang/String;
      41: invokevirtual #56                 // Method org/apache/hadoop/hbase/master/replication/ReplicationPeerManager.disablePeer:(Ljava/lang/String;)V
      44: return

  protected void postPeerModification(org.apache.hadoop.hbase.master.procedure.MasterProcedureEnv) throws java.io.IOException, org.apache.hadoop.hbase.replication.ReplicationException;
    Code:
       0: aload_0
       1: getfield      #12                 // Field oldPeerConfig:Lorg/apache/hadoop/hbase/replication/ReplicationPeerConfig;
       4: invokevirtual #11                 // Method org/apache/hadoop/hbase/replication/ReplicationPeerConfig.isSerial:()Z
       7: ifeq          31
      10: aload_0
      11: getfield      #3                  // Field peerConfig:Lorg/apache/hadoop/hbase/replication/ReplicationPeerConfig;
      14: invokevirtual #11                 // Method org/apache/hadoop/hbase/replication/ReplicationPeerConfig.isSerial:()Z
      17: ifne          31
      20: aload_1
      21: invokevirtual #21                 // Method org/apache/hadoop/hbase/master/procedure/MasterProcedureEnv.getReplicationPeerManager:()Lorg/apache/hadoop/hbase/master/replication/ReplicationPeerManager;
      24: aload_0
      25: getfield      #8                  // Field peerId:Ljava/lang/String;
      28: invokevirtual #22                 // Method org/apache/hadoop/hbase/master/replication/ReplicationPeerManager.removeAllLastPushedSeqIds:(Ljava/lang/String;)V
      31: getstatic     #57                 // Field LOG:Lorg/slf4j/Logger;
      34: ldc           #58                 // String Successfully updated peer config of {} to {}
      36: aload_0
      37: getfield      #8                  // Field peerId:Ljava/lang/String;
      40: aload_0
      41: getfield      #3                  // Field peerConfig:Lorg/apache/hadoop/hbase/replication/ReplicationPeerConfig;
      44: invokeinterface #59,  4           // InterfaceMethod org/slf4j/Logger.info:(Ljava/lang/String;Ljava/lang/Object;Ljava/lang/Object;)V
      49: aload_1
      50: invokevirtual #49                 // Method org/apache/hadoop/hbase/master/procedure/MasterProcedureEnv.getMasterCoprocessorHost:()Lorg/apache/hadoop/hbase/master/MasterCoprocessorHost;
      53: astore_2
      54: aload_2
      55: ifnull        70
      58: aload_2
      59: aload_0
      60: getfield      #8                  // Field peerId:Ljava/lang/String;
      63: aload_0
      64: getfield      #3                  // Field peerConfig:Lorg/apache/hadoop/hbase/replication/ReplicationPeerConfig;
      67: invokevirtual #60                 // Method org/apache/hadoop/hbase/master/MasterCoprocessorHost.postUpdateReplicationPeerConfig:(Ljava/lang/String;Lorg/apache/hadoop/hbase/replication/ReplicationPeerConfig;)V
      70: return

  protected void serializeStateData(org.apache.hadoop.hbase.procedure2.ProcedureStateSerializer) throws java.io.IOException;
    Code:
       0: aload_0
       1: aload_1
       2: invokespecial #61                 // Method org/apache/hadoop/hbase/master/replication/ModifyPeerProcedure.serializeStateData:(Lorg/apache/hadoop/hbase/procedure2/ProcedureStateSerializer;)V
       5: invokestatic  #62                 // Method org/apache/hadoop/hbase/shaded/protobuf/generated/MasterProcedureProtos$UpdatePeerConfigStateData.newBuilder:()Lorg/apache/hadoop/hbase/shaded/protobuf/generated/MasterProcedureProtos$UpdatePeerConfigStateData$Builder;
       8: aload_0
       9: getfield      #3                  // Field peerConfig:Lorg/apache/hadoop/hbase/replication/ReplicationPeerConfig;
      12: invokestatic  #63                 // Method org/apache/hadoop/hbase/client/replication/ReplicationPeerConfigUtil.convert:(Lorg/apache/hadoop/hbase/replication/ReplicationPeerConfig;)Lorg/apache/hadoop/hbase/shaded/protobuf/generated/ReplicationProtos$ReplicationPeer;
      15: invokevirtual #64                 // Method org/apache/hadoop/hbase/shaded/protobuf/generated/MasterProcedureProtos$UpdatePeerConfigStateData$Builder.setPeerConfig:(Lorg/apache/hadoop/hbase/shaded/protobuf/generated/ReplicationProtos$ReplicationPeer;)Lorg/apache/hadoop/hbase/shaded/protobuf/generated/MasterProcedureProtos$UpdatePeerConfigStateData$Builder;
      18: astore_2
      19: aload_0
      20: getfield      #12                 // Field oldPeerConfig:Lorg/apache/hadoop/hbase/replication/ReplicationPeerConfig;
      23: ifnull        38
      26: aload_2
      27: aload_0
      28: getfield      #12                 // Field oldPeerConfig:Lorg/apache/hadoop/hbase/replication/ReplicationPeerConfig;
      31: invokestatic  #63                 // Method org/apache/hadoop/hbase/client/replication/ReplicationPeerConfigUtil.convert:(Lorg/apache/hadoop/hbase/replication/ReplicationPeerConfig;)Lorg/apache/hadoop/hbase/shaded/protobuf/generated/ReplicationProtos$ReplicationPeer;
      34: invokevirtual #65                 // Method org/apache/hadoop/hbase/shaded/protobuf/generated/MasterProcedureProtos$UpdatePeerConfigStateData$Builder.setOldPeerConfig:(Lorg/apache/hadoop/hbase/shaded/protobuf/generated/ReplicationProtos$ReplicationPeer;)Lorg/apache/hadoop/hbase/shaded/protobuf/generated/MasterProcedureProtos$UpdatePeerConfigStateData$Builder;
      37: pop
      38: aload_2
      39: aload_0
      40: getfield      #48                 // Field enabled:Z
      43: invokevirtual #66                 // Method org/apache/hadoop/hbase/shaded/protobuf/generated/MasterProcedureProtos$UpdatePeerConfigStateData$Builder.setEnabled:(Z)Lorg/apache/hadoop/hbase/shaded/protobuf/generated/MasterProcedureProtos$UpdatePeerConfigStateData$Builder;
      46: pop
      47: aload_1
      48: aload_2
      49: invokevirtual #67                 // Method org/apache/hadoop/hbase/shaded/protobuf/generated/MasterProcedureProtos$UpdatePeerConfigStateData$Builder.build:()Lorg/apache/hadoop/hbase/shaded/protobuf/generated/MasterProcedureProtos$UpdatePeerConfigStateData;
      52: invokeinterface #68,  2           // InterfaceMethod org/apache/hadoop/hbase/procedure2/ProcedureStateSerializer.serialize:(Lorg/apache/hbase/thirdparty/com/google/protobuf/Message;)V
      57: return

  protected void deserializeStateData(org.apache.hadoop.hbase.procedure2.ProcedureStateSerializer) throws java.io.IOException;
    Code:
       0: aload_0
       1: aload_1
       2: invokespecial #69                 // Method org/apache/hadoop/hbase/master/replication/ModifyPeerProcedure.deserializeStateData:(Lorg/apache/hadoop/hbase/procedure2/ProcedureStateSerializer;)V
       5: aload_1
       6: ldc           #70                 // class org/apache/hadoop/hbase/shaded/protobuf/generated/MasterProcedureProtos$UpdatePeerConfigStateData
       8: invokeinterface #71,  2           // InterfaceMethod org/apache/hadoop/hbase/procedure2/ProcedureStateSerializer.deserialize:(Ljava/lang/Class;)Lorg/apache/hbase/thirdparty/com/google/protobuf/Message;
      13: checkcast     #70                 // class org/apache/hadoop/hbase/shaded/protobuf/generated/MasterProcedureProtos$UpdatePeerConfigStateData
      16: astore_2
      17: aload_0
      18: aload_2
      19: invokevirtual #72                 // Method org/apache/hadoop/hbase/shaded/protobuf/generated/MasterProcedureProtos$UpdatePeerConfigStateData.getPeerConfig:()Lorg/apache/hadoop/hbase/shaded/protobuf/generated/ReplicationProtos$ReplicationPeer;
      22: invokestatic  #73                 // Method org/apache/hadoop/hbase/client/replication/ReplicationPeerConfigUtil.convert:(Lorg/apache/hadoop/hbase/shaded/protobuf/generated/ReplicationProtos$ReplicationPeer;)Lorg/apache/hadoop/hbase/replication/ReplicationPeerConfig;
      25: putfield      #3                  // Field peerConfig:Lorg/apache/hadoop/hbase/replication/ReplicationPeerConfig;
      28: aload_2
      29: invokevirtual #74                 // Method org/apache/hadoop/hbase/shaded/protobuf/generated/MasterProcedureProtos$UpdatePeerConfigStateData.hasOldPeerConfig:()Z
      32: ifeq          49
      35: aload_0
      36: aload_2
      37: invokevirtual #75                 // Method org/apache/hadoop/hbase/shaded/protobuf/generated/MasterProcedureProtos$UpdatePeerConfigStateData.getOldPeerConfig:()Lorg/apache/hadoop/hbase/shaded/protobuf/generated/ReplicationProtos$ReplicationPeer;
      40: invokestatic  #73                 // Method org/apache/hadoop/hbase/client/replication/ReplicationPeerConfigUtil.convert:(Lorg/apache/hadoop/hbase/shaded/protobuf/generated/ReplicationProtos$ReplicationPeer;)Lorg/apache/hadoop/hbase/replication/ReplicationPeerConfig;
      43: putfield      #12                 // Field oldPeerConfig:Lorg/apache/hadoop/hbase/replication/ReplicationPeerConfig;
      46: goto          54
      49: aload_0
      50: aconst_null
      51: putfield      #12                 // Field oldPeerConfig:Lorg/apache/hadoop/hbase/replication/ReplicationPeerConfig;
      54: aload_0
      55: aload_2
      56: invokevirtual #76                 // Method org/apache/hadoop/hbase/shaded/protobuf/generated/MasterProcedureProtos$UpdatePeerConfigStateData.getEnabled:()Z
      59: putfield      #48                 // Field enabled:Z
      62: return

  static {};
    Code:
       0: ldc           #77                 // class org/apache/hadoop/hbase/master/replication/UpdatePeerConfigProcedure
       2: invokevirtual #78                 // Method java/lang/Class.desiredAssertionStatus:()Z
       5: ifne          12
       8: iconst_1
       9: goto          13
      12: iconst_0
      13: putstatic     #17                 // Field $assertionsDisabled:Z
      16: ldc           #77                 // class org/apache/hadoop/hbase/master/replication/UpdatePeerConfigProcedure
      18: invokestatic  #79                 // Method org/slf4j/LoggerFactory.getLogger:(Ljava/lang/Class;)Lorg/slf4j/Logger;
      21: putstatic     #57                 // Field LOG:Lorg/slf4j/Logger;
      24: return
}
