Compiled from "User.java"
public final class org.apache.hadoop.hbase.security.User$SecureHadoopUser extends org.apache.hadoop.hbase.security.User {
  public org.apache.hadoop.hbase.security.User$SecureHadoopUser() throws java.io.IOException;
    Code:
       0: aload_0
       1: invokespecial #1                  // Method org/apache/hadoop/hbase/security/User."<init>":()V
       4: aload_0
       5: invokestatic  #2                  // Method org/apache/hadoop/security/UserGroupInformation.getCurrentUser:()Lorg/apache/hadoop/security/UserGroupInformation;
       8: putfield      #3                  // Field ugi:Lorg/apache/hadoop/security/UserGroupInformation;
      11: aload_0
      12: aconst_null
      13: putfield      #4                  // Field cache:Lorg/apache/hbase/thirdparty/com/google/common/cache/LoadingCache;
      16: return

  public org.apache.hadoop.hbase.security.User$SecureHadoopUser(org.apache.hadoop.security.UserGroupInformation);
    Code:
       0: aload_0
       1: invokespecial #1                  // Method org/apache/hadoop/hbase/security/User."<init>":()V
       4: aload_0
       5: aload_1
       6: putfield      #3                  // Field ugi:Lorg/apache/hadoop/security/UserGroupInformation;
       9: aload_0
      10: aconst_null
      11: putfield      #4                  // Field cache:Lorg/apache/hbase/thirdparty/com/google/common/cache/LoadingCache;
      14: return

  public org.apache.hadoop.hbase.security.User$SecureHadoopUser(org.apache.hadoop.security.UserGroupInformation, org.apache.hbase.thirdparty.com.google.common.cache.LoadingCache<java.lang.String, java.lang.String[]>);
    Code:
       0: aload_0
       1: invokespecial #1                  // Method org/apache/hadoop/hbase/security/User."<init>":()V
       4: aload_0
       5: aload_1
       6: putfield      #3                  // Field ugi:Lorg/apache/hadoop/security/UserGroupInformation;
       9: aload_0
      10: aload_2
      11: putfield      #4                  // Field cache:Lorg/apache/hbase/thirdparty/com/google/common/cache/LoadingCache;
      14: return

  public java.lang.String getShortName();
    Code:
       0: aload_0
       1: getfield      #5                  // Field shortName:Ljava/lang/String;
       4: ifnull        12
       7: aload_0
       8: getfield      #5                  // Field shortName:Ljava/lang/String;
      11: areturn
      12: aload_0
      13: aload_0
      14: getfield      #3                  // Field ugi:Lorg/apache/hadoop/security/UserGroupInformation;
      17: invokevirtual #6                  // Method org/apache/hadoop/security/UserGroupInformation.getShortUserName:()Ljava/lang/String;
      20: putfield      #5                  // Field shortName:Ljava/lang/String;
      23: aload_0
      24: getfield      #5                  // Field shortName:Ljava/lang/String;
      27: areturn
      28: astore_1
      29: new           #8                  // class java/lang/RuntimeException
      32: dup
      33: ldc           #9                  // String Unexpected error getting user short name
      35: aload_1
      36: invokespecial #10                 // Method java/lang/RuntimeException."<init>":(Ljava/lang/String;Ljava/lang/Throwable;)V
      39: athrow
    Exception table:
       from    to  target type
          12    27    28   Class java/lang/Exception

  public java.lang.String[] getGroupNames();
    Code:
       0: aload_0
       1: getfield      #4                  // Field cache:Lorg/apache/hbase/thirdparty/com/google/common/cache/LoadingCache;
       4: ifnull        30
       7: aload_0
       8: getfield      #4                  // Field cache:Lorg/apache/hbase/thirdparty/com/google/common/cache/LoadingCache;
      11: aload_0
      12: invokevirtual #11                 // Method getShortName:()Ljava/lang/String;
      15: invokeinterface #12,  2           // InterfaceMethod org/apache/hbase/thirdparty/com/google/common/cache/LoadingCache.get:(Ljava/lang/Object;)Ljava/lang/Object;
      20: checkcast     #13                 // class "[Ljava/lang/String;"
      23: areturn
      24: astore_1
      25: iconst_0
      26: anewarray     #15                 // class java/lang/String
      29: areturn
      30: aload_0
      31: getfield      #3                  // Field ugi:Lorg/apache/hadoop/security/UserGroupInformation;
      34: invokevirtual #16                 // Method org/apache/hadoop/security/UserGroupInformation.getGroupNames:()[Ljava/lang/String;
      37: areturn
    Exception table:
       from    to  target type
           7    23    24   Class java/util/concurrent/ExecutionException

  public <T> T runAs(java.security.PrivilegedAction<T>);
    Code:
       0: aload_0
       1: getfield      #3                  // Field ugi:Lorg/apache/hadoop/security/UserGroupInformation;
       4: aload_1
       5: invokevirtual #17                 // Method org/apache/hadoop/security/UserGroupInformation.doAs:(Ljava/security/PrivilegedAction;)Ljava/lang/Object;
       8: areturn

  public <T> T runAs(java.security.PrivilegedExceptionAction<T>) throws java.io.IOException, java.lang.InterruptedException;
    Code:
       0: aload_0
       1: getfield      #3                  // Field ugi:Lorg/apache/hadoop/security/UserGroupInformation;
       4: aload_1
       5: invokevirtual #18                 // Method org/apache/hadoop/security/UserGroupInformation.doAs:(Ljava/security/PrivilegedExceptionAction;)Ljava/lang/Object;
       8: areturn

  public static org.apache.hadoop.hbase.security.User createUserForTesting(org.apache.hadoop.conf.Configuration, java.lang.String, java.lang.String[]);
    Code:
       0: ldc           #19                 // class org/apache/hadoop/hbase/security/UserProvider
       2: dup
       3: astore_3
       4: monitorenter
       5: getstatic     #20                 // Field org/apache/hadoop/hbase/security/UserProvider.groups:Lorg/apache/hadoop/security/Groups;
       8: instanceof    #21                 // class org/apache/hadoop/hbase/security/User$TestingGroups
      11: ifeq          24
      14: aload_0
      15: ldc           #22                 // String hbase.group.service.for.test.only
      17: iconst_0
      18: invokevirtual #23                 // Method org/apache/hadoop/conf/Configuration.getBoolean:(Ljava/lang/String;Z)Z
      21: ifeq          37
      24: new           #21                 // class org/apache/hadoop/hbase/security/User$TestingGroups
      27: dup
      28: getstatic     #20                 // Field org/apache/hadoop/hbase/security/UserProvider.groups:Lorg/apache/hadoop/security/Groups;
      31: invokespecial #24                 // Method org/apache/hadoop/hbase/security/User$TestingGroups."<init>":(Lorg/apache/hadoop/security/Groups;)V
      34: putstatic     #20                 // Field org/apache/hadoop/hbase/security/UserProvider.groups:Lorg/apache/hadoop/security/Groups;
      37: aload_3
      38: monitorexit
      39: goto          49
      42: astore        4
      44: aload_3
      45: monitorexit
      46: aload         4
      48: athrow
      49: getstatic     #20                 // Field org/apache/hadoop/hbase/security/UserProvider.groups:Lorg/apache/hadoop/security/Groups;
      52: checkcast     #21                 // class org/apache/hadoop/hbase/security/User$TestingGroups
      55: aload_1
      56: aload_2
      57: invokestatic  #25                 // Method org/apache/hadoop/hbase/security/User$TestingGroups.access$000:(Lorg/apache/hadoop/hbase/security/User$TestingGroups;Ljava/lang/String;[Ljava/lang/String;)V
      60: new           #26                 // class org/apache/hadoop/hbase/security/User$SecureHadoopUser
      63: dup
      64: aload_1
      65: aload_2
      66: invokestatic  #27                 // Method org/apache/hadoop/security/UserGroupInformation.createUserForTesting:(Ljava/lang/String;[Ljava/lang/String;)Lorg/apache/hadoop/security/UserGroupInformation;
      69: invokespecial #28                 // Method "<init>":(Lorg/apache/hadoop/security/UserGroupInformation;)V
      72: areturn
    Exception table:
       from    to  target type
           5    39    42   any
          42    46    42   any

  public static void login(org.apache.hadoop.conf.Configuration, java.lang.String, java.lang.String, java.lang.String) throws java.io.IOException;
    Code:
       0: invokestatic  #29                 // Method isSecurityEnabled:()Z
       3: ifeq          13
       6: aload_0
       7: aload_1
       8: aload_2
       9: aload_3
      10: invokestatic  #30                 // Method org/apache/hadoop/security/SecurityUtil.login:(Lorg/apache/hadoop/conf/Configuration;Ljava/lang/String;Ljava/lang/String;Ljava/lang/String;)V
      13: return

  public static void login(java.lang.String, java.lang.String) throws java.io.IOException;
    Code:
       0: invokestatic  #29                 // Method isSecurityEnabled:()Z
       3: ifeq          11
       6: aload_1
       7: aload_0
       8: invokestatic  #31                 // Method org/apache/hadoop/security/UserGroupInformation.loginUserFromKeytab:(Ljava/lang/String;Ljava/lang/String;)V
      11: return

  public static boolean isSecurityEnabled();
    Code:
       0: invokestatic  #32                 // Method org/apache/hadoop/security/UserGroupInformation.isSecurityEnabled:()Z
       3: ireturn
}
