Compiled from "VersionInfoUtil.java"
public final class org.apache.hadoop.hbase.client.VersionInfoUtil {
  public static boolean currentClientHasMinimumVersion(int, int);
    Code:
       0: invokestatic  #2                  // Method getCurrentClientVersionInfo:()Lorg/apache/hadoop/hbase/shaded/protobuf/generated/HBaseProtos$VersionInfo;
       3: iload_0
       4: iload_1
       5: invokestatic  #3                  // Method hasMinimumVersion:(Lorg/apache/hadoop/hbase/shaded/protobuf/generated/HBaseProtos$VersionInfo;II)Z
       8: ireturn

  public static boolean hasMinimumVersion(org.apache.hadoop.hbase.shaded.protobuf.generated.HBaseProtos$VersionInfo, int, int);
    Code:
       0: aload_0
       1: ifnull        130
       4: aload_0
       5: invokevirtual #4                  // Method org/apache/hadoop/hbase/shaded/protobuf/generated/HBaseProtos$VersionInfo.hasVersionMajor:()Z
       8: ifeq          57
      11: aload_0
      12: invokevirtual #5                  // Method org/apache/hadoop/hbase/shaded/protobuf/generated/HBaseProtos$VersionInfo.hasVersionMinor:()Z
      15: ifeq          57
      18: aload_0
      19: invokevirtual #6                  // Method org/apache/hadoop/hbase/shaded/protobuf/generated/HBaseProtos$VersionInfo.getVersionMajor:()I
      22: istore_3
      23: iload_3
      24: iload_1
      25: if_icmpeq     39
      28: iload_3
      29: iload_1
      30: if_icmple     37
      33: iconst_1
      34: goto          38
      37: iconst_0
      38: ireturn
      39: aload_0
      40: invokevirtual #7                  // Method org/apache/hadoop/hbase/shaded/protobuf/generated/HBaseProtos$VersionInfo.getVersionMinor:()I
      43: istore        4
      45: iload         4
      47: iload_2
      48: if_icmplt     55
      51: iconst_1
      52: goto          56
      55: iconst_0
      56: ireturn
      57: aload_0
      58: invokestatic  #8                  // Method getVersionComponents:(Lorg/apache/hadoop/hbase/shaded/protobuf/generated/HBaseProtos$VersionInfo;)[Ljava/lang/String;
      61: astore_3
      62: aload_3
      63: arraylength
      64: ifle          76
      67: aload_3
      68: iconst_0
      69: aaload
      70: invokestatic  #9                  // Method java/lang/Integer.parseInt:(Ljava/lang/String;)I
      73: goto          77
      76: iconst_0
      77: istore        4
      79: iload         4
      81: iload_1
      82: if_icmpeq     97
      85: iload         4
      87: iload_1
      88: if_icmple     95
      91: iconst_1
      92: goto          96
      95: iconst_0
      96: ireturn
      97: aload_3
      98: arraylength
      99: iconst_1
     100: if_icmple     112
     103: aload_3
     104: iconst_1
     105: aaload
     106: invokestatic  #9                  // Method java/lang/Integer.parseInt:(Ljava/lang/String;)I
     109: goto          113
     112: iconst_0
     113: istore        5
     115: iload         5
     117: iload_2
     118: if_icmplt     125
     121: iconst_1
     122: goto          126
     125: iconst_0
     126: ireturn
     127: astore_3
     128: iconst_0
     129: ireturn
     130: iconst_0
     131: ireturn
    Exception table:
       from    to  target type
          57    96   127   Class java/lang/NumberFormatException
          97   126   127   Class java/lang/NumberFormatException

  public static <T1, T2, R, E extends java.lang.Throwable> R callWithVersion(org.apache.hadoop.hbase.client.VersionInfoUtil$ServiceCallFunction<T1, T2, R, E>, T1, T2) throws E;
    Code:
       0: getstatic     #11                 // Field NonCallVersion:Ljava/lang/ThreadLocal;
       3: invokestatic  #12                 // Method org/apache/hadoop/hbase/shaded/protobuf/ProtobufUtil.getVersionInfo:()Lorg/apache/hadoop/hbase/shaded/protobuf/generated/HBaseProtos$VersionInfo;
       6: invokevirtual #13                 // Method java/lang/ThreadLocal.set:(Ljava/lang/Object;)V
       9: aload_0
      10: aload_1
      11: aload_2
      12: invokeinterface #14,  3           // InterfaceMethod org/apache/hadoop/hbase/client/VersionInfoUtil$ServiceCallFunction.apply:(Ljava/lang/Object;Ljava/lang/Object;)Ljava/lang/Object;
      17: astore_3
      18: getstatic     #11                 // Field NonCallVersion:Ljava/lang/ThreadLocal;
      21: invokevirtual #15                 // Method java/lang/ThreadLocal.remove:()V
      24: aload_3
      25: areturn
      26: astore        4
      28: getstatic     #11                 // Field NonCallVersion:Ljava/lang/ThreadLocal;
      31: invokevirtual #15                 // Method java/lang/ThreadLocal.remove:()V
      34: aload         4
      36: athrow
    Exception table:
       from    to  target type
           9    18    26   any
          26    28    26   any

  public static org.apache.hadoop.hbase.shaded.protobuf.generated.HBaseProtos$VersionInfo getCurrentClientVersionInfo();
    Code:
       0: invokestatic  #16                 // Method org/apache/hadoop/hbase/ipc/RpcServer.getCurrentCall:()Ljava/util/Optional;
       3: invokedynamic #17,  0             // InvokeDynamic #0:apply:()Ljava/util/function/Function;
       8: invokevirtual #18                 // Method java/util/Optional.map:(Ljava/util/function/Function;)Ljava/util/Optional;
      11: getstatic     #11                 // Field NonCallVersion:Ljava/lang/ThreadLocal;
      14: invokevirtual #19                 // Method java/lang/ThreadLocal.get:()Ljava/lang/Object;
      17: invokevirtual #20                 // Method java/util/Optional.orElse:(Ljava/lang/Object;)Ljava/lang/Object;
      20: checkcast     #21                 // class org/apache/hadoop/hbase/shaded/protobuf/generated/HBaseProtos$VersionInfo
      23: areturn

  public static java.lang.String versionNumberToString(int);
    Code:
       0: ldc           #22                 // String %d.%d.%d
       2: iconst_3
       3: anewarray     #23                 // class java/lang/Object
       6: dup
       7: iconst_0
       8: iload_0
       9: bipush        20
      11: ishr
      12: sipush        255
      15: iand
      16: invokestatic  #24                 // Method java/lang/Integer.valueOf:(I)Ljava/lang/Integer;
      19: aastore
      20: dup
      21: iconst_1
      22: iload_0
      23: bipush        12
      25: ishr
      26: sipush        255
      29: iand
      30: invokestatic  #24                 // Method java/lang/Integer.valueOf:(I)Ljava/lang/Integer;
      33: aastore
      34: dup
      35: iconst_2
      36: iload_0
      37: sipush        4095
      40: iand
      41: invokestatic  #24                 // Method java/lang/Integer.valueOf:(I)Ljava/lang/Integer;
      44: aastore
      45: invokestatic  #25                 // Method java/lang/String.format:(Ljava/lang/String;[Ljava/lang/Object;)Ljava/lang/String;
      48: areturn

  public static int getVersionNumber(org.apache.hadoop.hbase.shaded.protobuf.generated.HBaseProtos$VersionInfo);
    Code:
       0: aload_0
       1: ifnull        108
       4: aload_0
       5: invokestatic  #8                  // Method getVersionComponents:(Lorg/apache/hadoop/hbase/shaded/protobuf/generated/HBaseProtos$VersionInfo;)[Ljava/lang/String;
       8: astore_1
       9: aload_1
      10: arraylength
      11: ifle          23
      14: aload_1
      15: iconst_0
      16: aaload
      17: invokestatic  #9                  // Method java/lang/Integer.parseInt:(Ljava/lang/String;)I
      20: goto          24
      23: iconst_0
      24: istore_2
      25: aload_1
      26: arraylength
      27: iconst_1
      28: if_icmple     40
      31: aload_1
      32: iconst_1
      33: aaload
      34: invokestatic  #9                  // Method java/lang/Integer.parseInt:(Ljava/lang/String;)I
      37: goto          41
      40: iconst_0
      41: istore_3
      42: aload_1
      43: arraylength
      44: iconst_2
      45: if_icmple     57
      48: aload_1
      49: iconst_2
      50: aaload
      51: invokestatic  #9                  // Method java/lang/Integer.parseInt:(Ljava/lang/String;)I
      54: goto          58
      57: iconst_0
      58: istore        4
      60: iload_2
      61: iload_3
      62: iload         4
      64: invokestatic  #26                 // Method buildVersionNumber:(III)I
      67: ireturn
      68: astore_1
      69: aload_0
      70: invokevirtual #4                  // Method org/apache/hadoop/hbase/shaded/protobuf/generated/HBaseProtos$VersionInfo.hasVersionMajor:()Z
      73: ifeq          83
      76: aload_0
      77: invokevirtual #6                  // Method org/apache/hadoop/hbase/shaded/protobuf/generated/HBaseProtos$VersionInfo.getVersionMajor:()I
      80: goto          84
      83: iconst_0
      84: istore_2
      85: aload_0
      86: invokevirtual #5                  // Method org/apache/hadoop/hbase/shaded/protobuf/generated/HBaseProtos$VersionInfo.hasVersionMinor:()Z
      89: ifeq          99
      92: aload_0
      93: invokevirtual #7                  // Method org/apache/hadoop/hbase/shaded/protobuf/generated/HBaseProtos$VersionInfo.getVersionMinor:()I
      96: goto          100
      99: iconst_0
     100: istore_3
     101: iload_2
     102: iload_3
     103: iconst_0
     104: invokestatic  #26                 // Method buildVersionNumber:(III)I
     107: ireturn
     108: iconst_0
     109: ireturn
    Exception table:
       from    to  target type
           4    67    68   Class java/lang/NumberFormatException

  static {};
    Code:
       0: new           #30                 // class java/lang/ThreadLocal
       3: dup
       4: invokespecial #31                 // Method java/lang/ThreadLocal."<init>":()V
       7: putstatic     #11                 // Field NonCallVersion:Ljava/lang/ThreadLocal;
      10: return
}
