Compiled from "VisibilityClient.java"
public class org.apache.hadoop.hbase.security.visibility.VisibilityClient {
  public org.apache.hadoop.hbase.security.visibility.VisibilityClient();
    Code:
       0: aload_0
       1: invokespecial #1                  // Method java/lang/Object."<init>":()V
       4: return

  public static boolean isCellVisibilityEnabled(org.apache.hadoop.hbase.client.Connection) throws java.io.IOException;
    Code:
       0: aload_0
       1: invokeinterface #2,  1            // InterfaceMethod org/apache/hadoop/hbase/client/Connection.getAdmin:()Lorg/apache/hadoop/hbase/client/Admin;
       6: invokeinterface #3,  1            // InterfaceMethod org/apache/hadoop/hbase/client/Admin.getSecurityCapabilities:()Ljava/util/List;
      11: getstatic     #4                  // Field org/apache/hadoop/hbase/client/security/SecurityCapability.CELL_VISIBILITY:Lorg/apache/hadoop/hbase/client/security/SecurityCapability;
      14: invokeinterface #5,  2            // InterfaceMethod java/util/List.contains:(Ljava/lang/Object;)Z
      19: ireturn

  public static org.apache.hadoop.hbase.protobuf.generated.VisibilityLabelsProtos$VisibilityLabelsResponse addLabel(org.apache.hadoop.hbase.client.Connection, java.lang.String) throws java.lang.Throwable;
    Code:
       0: aload_0
       1: iconst_1
       2: anewarray     #6                  // class java/lang/String
       5: dup
       6: iconst_0
       7: aload_1
       8: aastore
       9: invokestatic  #7                  // Method addLabels:(Lorg/apache/hadoop/hbase/client/Connection;[Ljava/lang/String;)Lorg/apache/hadoop/hbase/protobuf/generated/VisibilityLabelsProtos$VisibilityLabelsResponse;
      12: areturn

  public static org.apache.hadoop.hbase.protobuf.generated.VisibilityLabelsProtos$VisibilityLabelsResponse addLabels(org.apache.hadoop.hbase.client.Connection, java.lang.String[]) throws java.lang.Throwable;
    Code:
       0: aload_0
       1: getstatic     #8                  // Field org/apache/hadoop/hbase/security/visibility/VisibilityConstants.LABELS_TABLE_NAME:Lorg/apache/hadoop/hbase/TableName;
       4: invokeinterface #9,  2            // InterfaceMethod org/apache/hadoop/hbase/client/Connection.getTable:(Lorg/apache/hadoop/hbase/TableName;)Lorg/apache/hadoop/hbase/client/Table;
       9: astore_2
      10: aconst_null
      11: astore_3
      12: new           #10                 // class org/apache/hadoop/hbase/security/visibility/VisibilityClient$1
      15: dup
      16: aload_1
      17: invokespecial #11                 // Method org/apache/hadoop/hbase/security/visibility/VisibilityClient$1."<init>":([Ljava/lang/String;)V
      20: astore        4
      22: aload_2
      23: ldc           #12                 // class org/apache/hadoop/hbase/protobuf/generated/VisibilityLabelsProtos$VisibilityLabelsService
      25: getstatic     #13                 // Field org/apache/hadoop/hbase/HConstants.EMPTY_BYTE_ARRAY:[B
      28: getstatic     #13                 // Field org/apache/hadoop/hbase/HConstants.EMPTY_BYTE_ARRAY:[B
      31: aload         4
      33: invokeinterface #14,  5           // InterfaceMethod org/apache/hadoop/hbase/client/Table.coprocessorService:(Ljava/lang/Class;[B[BLorg/apache/hadoop/hbase/client/coprocessor/Batch$Call;)Ljava/util/Map;
      38: astore        5
      40: aload         5
      42: invokeinterface #15,  1           // InterfaceMethod java/util/Map.values:()Ljava/util/Collection;
      47: invokeinterface #16,  1           // InterfaceMethod java/util/Collection.iterator:()Ljava/util/Iterator;
      52: invokeinterface #17,  1           // InterfaceMethod java/util/Iterator.next:()Ljava/lang/Object;
      57: checkcast     #18                 // class org/apache/hadoop/hbase/protobuf/generated/VisibilityLabelsProtos$VisibilityLabelsResponse
      60: astore        6
      62: aload_2
      63: ifnull        96
      66: aload_3
      67: ifnull        90
      70: aload_2
      71: invokeinterface #19,  1           // InterfaceMethod org/apache/hadoop/hbase/client/Table.close:()V
      76: goto          96
      79: astore        7
      81: aload_3
      82: aload         7
      84: invokevirtual #21                 // Method java/lang/Throwable.addSuppressed:(Ljava/lang/Throwable;)V
      87: goto          96
      90: aload_2
      91: invokeinterface #19,  1           // InterfaceMethod org/apache/hadoop/hbase/client/Table.close:()V
      96: aload         6
      98: areturn
      99: astore        4
     101: aload         4
     103: astore_3
     104: aload         4
     106: athrow
     107: astore        8
     109: aload_2
     110: ifnull        143
     113: aload_3
     114: ifnull        137
     117: aload_2
     118: invokeinterface #19,  1           // InterfaceMethod org/apache/hadoop/hbase/client/Table.close:()V
     123: goto          143
     126: astore        9
     128: aload_3
     129: aload         9
     131: invokevirtual #21                 // Method java/lang/Throwable.addSuppressed:(Ljava/lang/Throwable;)V
     134: goto          143
     137: aload_2
     138: invokeinterface #19,  1           // InterfaceMethod org/apache/hadoop/hbase/client/Table.close:()V
     143: aload         8
     145: athrow
    Exception table:
       from    to  target type
          70    76    79   Class java/lang/Throwable
          12    62    99   Class java/lang/Throwable
          12    62   107   any
         117   123   126   Class java/lang/Throwable
          99   109   107   any

  public static org.apache.hadoop.hbase.protobuf.generated.VisibilityLabelsProtos$VisibilityLabelsResponse setAuths(org.apache.hadoop.hbase.client.Connection, java.lang.String[], java.lang.String) throws java.lang.Throwable;
    Code:
       0: aload_0
       1: aload_1
       2: aload_2
       3: iconst_1
       4: invokestatic  #22                 // Method setOrClearAuths:(Lorg/apache/hadoop/hbase/client/Connection;[Ljava/lang/String;Ljava/lang/String;Z)Lorg/apache/hadoop/hbase/protobuf/generated/VisibilityLabelsProtos$VisibilityLabelsResponse;
       7: areturn

  public static org.apache.hadoop.hbase.protobuf.generated.VisibilityLabelsProtos$GetAuthsResponse getAuths(org.apache.hadoop.hbase.client.Connection, java.lang.String) throws java.lang.Throwable;
    Code:
       0: aload_0
       1: getstatic     #8                  // Field org/apache/hadoop/hbase/security/visibility/VisibilityConstants.LABELS_TABLE_NAME:Lorg/apache/hadoop/hbase/TableName;
       4: invokeinterface #9,  2            // InterfaceMethod org/apache/hadoop/hbase/client/Connection.getTable:(Lorg/apache/hadoop/hbase/TableName;)Lorg/apache/hadoop/hbase/client/Table;
       9: astore_2
      10: aconst_null
      11: astore_3
      12: new           #23                 // class org/apache/hadoop/hbase/security/visibility/VisibilityClient$2
      15: dup
      16: aload_1
      17: invokespecial #24                 // Method org/apache/hadoop/hbase/security/visibility/VisibilityClient$2."<init>":(Ljava/lang/String;)V
      20: astore        4
      22: aload_2
      23: ldc           #12                 // class org/apache/hadoop/hbase/protobuf/generated/VisibilityLabelsProtos$VisibilityLabelsService
      25: getstatic     #13                 // Field org/apache/hadoop/hbase/HConstants.EMPTY_BYTE_ARRAY:[B
      28: getstatic     #13                 // Field org/apache/hadoop/hbase/HConstants.EMPTY_BYTE_ARRAY:[B
      31: aload         4
      33: invokeinterface #14,  5           // InterfaceMethod org/apache/hadoop/hbase/client/Table.coprocessorService:(Ljava/lang/Class;[B[BLorg/apache/hadoop/hbase/client/coprocessor/Batch$Call;)Ljava/util/Map;
      38: astore        5
      40: aload         5
      42: invokeinterface #15,  1           // InterfaceMethod java/util/Map.values:()Ljava/util/Collection;
      47: invokeinterface #16,  1           // InterfaceMethod java/util/Collection.iterator:()Ljava/util/Iterator;
      52: invokeinterface #17,  1           // InterfaceMethod java/util/Iterator.next:()Ljava/lang/Object;
      57: checkcast     #25                 // class org/apache/hadoop/hbase/protobuf/generated/VisibilityLabelsProtos$GetAuthsResponse
      60: astore        6
      62: aload_2
      63: ifnull        96
      66: aload_3
      67: ifnull        90
      70: aload_2
      71: invokeinterface #19,  1           // InterfaceMethod org/apache/hadoop/hbase/client/Table.close:()V
      76: goto          96
      79: astore        7
      81: aload_3
      82: aload         7
      84: invokevirtual #21                 // Method java/lang/Throwable.addSuppressed:(Ljava/lang/Throwable;)V
      87: goto          96
      90: aload_2
      91: invokeinterface #19,  1           // InterfaceMethod org/apache/hadoop/hbase/client/Table.close:()V
      96: aload         6
      98: areturn
      99: astore        4
     101: aload         4
     103: astore_3
     104: aload         4
     106: athrow
     107: astore        8
     109: aload_2
     110: ifnull        143
     113: aload_3
     114: ifnull        137
     117: aload_2
     118: invokeinterface #19,  1           // InterfaceMethod org/apache/hadoop/hbase/client/Table.close:()V
     123: goto          143
     126: astore        9
     128: aload_3
     129: aload         9
     131: invokevirtual #21                 // Method java/lang/Throwable.addSuppressed:(Ljava/lang/Throwable;)V
     134: goto          143
     137: aload_2
     138: invokeinterface #19,  1           // InterfaceMethod org/apache/hadoop/hbase/client/Table.close:()V
     143: aload         8
     145: athrow
    Exception table:
       from    to  target type
          70    76    79   Class java/lang/Throwable
          12    62    99   Class java/lang/Throwable
          12    62   107   any
         117   123   126   Class java/lang/Throwable
          99   109   107   any

  public static org.apache.hadoop.hbase.protobuf.generated.VisibilityLabelsProtos$ListLabelsResponse listLabels(org.apache.hadoop.hbase.client.Connection, java.lang.String) throws java.lang.Throwable;
    Code:
       0: aload_0
       1: getstatic     #8                  // Field org/apache/hadoop/hbase/security/visibility/VisibilityConstants.LABELS_TABLE_NAME:Lorg/apache/hadoop/hbase/TableName;
       4: invokeinterface #9,  2            // InterfaceMethod org/apache/hadoop/hbase/client/Connection.getTable:(Lorg/apache/hadoop/hbase/TableName;)Lorg/apache/hadoop/hbase/client/Table;
       9: astore_2
      10: aconst_null
      11: astore_3
      12: new           #26                 // class org/apache/hadoop/hbase/security/visibility/VisibilityClient$3
      15: dup
      16: aload_1
      17: invokespecial #27                 // Method org/apache/hadoop/hbase/security/visibility/VisibilityClient$3."<init>":(Ljava/lang/String;)V
      20: astore        4
      22: aload_2
      23: ldc           #12                 // class org/apache/hadoop/hbase/protobuf/generated/VisibilityLabelsProtos$VisibilityLabelsService
      25: getstatic     #13                 // Field org/apache/hadoop/hbase/HConstants.EMPTY_BYTE_ARRAY:[B
      28: getstatic     #13                 // Field org/apache/hadoop/hbase/HConstants.EMPTY_BYTE_ARRAY:[B
      31: aload         4
      33: invokeinterface #14,  5           // InterfaceMethod org/apache/hadoop/hbase/client/Table.coprocessorService:(Ljava/lang/Class;[B[BLorg/apache/hadoop/hbase/client/coprocessor/Batch$Call;)Ljava/util/Map;
      38: astore        5
      40: aload         5
      42: invokeinterface #15,  1           // InterfaceMethod java/util/Map.values:()Ljava/util/Collection;
      47: invokeinterface #16,  1           // InterfaceMethod java/util/Collection.iterator:()Ljava/util/Iterator;
      52: invokeinterface #17,  1           // InterfaceMethod java/util/Iterator.next:()Ljava/lang/Object;
      57: checkcast     #28                 // class org/apache/hadoop/hbase/protobuf/generated/VisibilityLabelsProtos$ListLabelsResponse
      60: astore        6
      62: aload_2
      63: ifnull        96
      66: aload_3
      67: ifnull        90
      70: aload_2
      71: invokeinterface #19,  1           // InterfaceMethod org/apache/hadoop/hbase/client/Table.close:()V
      76: goto          96
      79: astore        7
      81: aload_3
      82: aload         7
      84: invokevirtual #21                 // Method java/lang/Throwable.addSuppressed:(Ljava/lang/Throwable;)V
      87: goto          96
      90: aload_2
      91: invokeinterface #19,  1           // InterfaceMethod org/apache/hadoop/hbase/client/Table.close:()V
      96: aload         6
      98: areturn
      99: astore        4
     101: aload         4
     103: astore_3
     104: aload         4
     106: athrow
     107: astore        8
     109: aload_2
     110: ifnull        143
     113: aload_3
     114: ifnull        137
     117: aload_2
     118: invokeinterface #19,  1           // InterfaceMethod org/apache/hadoop/hbase/client/Table.close:()V
     123: goto          143
     126: astore        9
     128: aload_3
     129: aload         9
     131: invokevirtual #21                 // Method java/lang/Throwable.addSuppressed:(Ljava/lang/Throwable;)V
     134: goto          143
     137: aload_2
     138: invokeinterface #19,  1           // InterfaceMethod org/apache/hadoop/hbase/client/Table.close:()V
     143: aload         8
     145: athrow
    Exception table:
       from    to  target type
          70    76    79   Class java/lang/Throwable
          12    62    99   Class java/lang/Throwable
          12    62   107   any
         117   123   126   Class java/lang/Throwable
          99   109   107   any

  public static org.apache.hadoop.hbase.protobuf.generated.VisibilityLabelsProtos$VisibilityLabelsResponse clearAuths(org.apache.hadoop.hbase.client.Connection, java.lang.String[], java.lang.String) throws java.lang.Throwable;
    Code:
       0: aload_0
       1: aload_1
       2: aload_2
       3: iconst_0
       4: invokestatic  #22                 // Method setOrClearAuths:(Lorg/apache/hadoop/hbase/client/Connection;[Ljava/lang/String;Ljava/lang/String;Z)Lorg/apache/hadoop/hbase/protobuf/generated/VisibilityLabelsProtos$VisibilityLabelsResponse;
       7: areturn
}
