Compiled from "VisibilityLabelsWithDeletesTestBase.java"
public abstract class org.apache.hadoop.hbase.security.visibility.VisibilityLabelsWithDeletesTestBase {
  protected static final java.lang.String TOPSECRET;

  protected static final java.lang.String PUBLIC;

  protected static final java.lang.String PRIVATE;

  protected static final java.lang.String CONFIDENTIAL;

  protected static final java.lang.String SECRET;

  protected static final org.apache.hadoop.hbase.HBaseTestingUtility TEST_UTIL;

  protected static final byte[] row1;

  protected static final byte[] row2;

  protected static final byte[] fam;

  protected static final byte[] qual;

  protected static final byte[] qual1;

  protected static final byte[] qual2;

  protected static final byte[] value;

  protected static final byte[] value1;

  protected static org.apache.hadoop.conf.Configuration conf;

  public final org.junit.rules.TestName testName;

  protected static org.apache.hadoop.hbase.security.User SUPERUSER;

  public org.apache.hadoop.hbase.security.visibility.VisibilityLabelsWithDeletesTestBase();
    Code:
       0: aload_0
       1: invokespecial #1                  // Method java/lang/Object."<init>":()V
       4: aload_0
       5: new           #2                  // class org/junit/rules/TestName
       8: dup
       9: invokespecial #3                  // Method org/junit/rules/TestName."<init>":()V
      12: putfield      #4                  // Field testName:Lorg/junit/rules/TestName;
      15: return

  public static void setupBeforeClass() throws java.lang.Exception;
    Code:
       0: getstatic     #5                  // Field TEST_UTIL:Lorg/apache/hadoop/hbase/HBaseTestingUtility;
       3: invokevirtual #6                  // Method org/apache/hadoop/hbase/HBaseTestingUtility.getConfiguration:()Lorg/apache/hadoop/conf/Configuration;
       6: putstatic     #7                  // Field conf:Lorg/apache/hadoop/conf/Configuration;
       9: getstatic     #7                  // Field conf:Lorg/apache/hadoop/conf/Configuration;
      12: invokestatic  #8                  // Method org/apache/hadoop/hbase/security/visibility/VisibilityTestUtil.enableVisiblityLabels:(Lorg/apache/hadoop/conf/Configuration;)V
      15: getstatic     #7                  // Field conf:Lorg/apache/hadoop/conf/Configuration;
      18: ldc           #10                 // String hbase.regionserver.scan.visibility.label.generator.class
      20: ldc           #11                 // class org/apache/hadoop/hbase/security/visibility/SimpleScanLabelGenerator
      22: ldc           #12                 // class org/apache/hadoop/hbase/security/visibility/ScanLabelGenerator
      24: invokevirtual #13                 // Method org/apache/hadoop/conf/Configuration.setClass:(Ljava/lang/String;Ljava/lang/Class;Ljava/lang/Class;)V
      27: getstatic     #7                  // Field conf:Lorg/apache/hadoop/conf/Configuration;
      30: ldc           #14                 // String hbase.superuser
      32: ldc           #15                 // String admin
      34: invokevirtual #16                 // Method org/apache/hadoop/conf/Configuration.set:(Ljava/lang/String;Ljava/lang/String;)V
      37: getstatic     #5                  // Field TEST_UTIL:Lorg/apache/hadoop/hbase/HBaseTestingUtility;
      40: iconst_2
      41: invokevirtual #17                 // Method org/apache/hadoop/hbase/HBaseTestingUtility.startMiniCluster:(I)Lorg/apache/hadoop/hbase/MiniHBaseCluster;
      44: pop
      45: getstatic     #7                  // Field conf:Lorg/apache/hadoop/conf/Configuration;
      48: ldc           #15                 // String admin
      50: iconst_1
      51: anewarray     #18                 // class java/lang/String
      54: dup
      55: iconst_0
      56: ldc           #19                 // String supergroup
      58: aastore
      59: invokestatic  #20                 // Method org/apache/hadoop/hbase/security/User.createUserForTesting:(Lorg/apache/hadoop/conf/Configuration;Ljava/lang/String;[Ljava/lang/String;)Lorg/apache/hadoop/hbase/security/User;
      62: putstatic     #21                 // Field SUPERUSER:Lorg/apache/hadoop/hbase/security/User;
      65: getstatic     #5                  // Field TEST_UTIL:Lorg/apache/hadoop/hbase/HBaseTestingUtility;
      68: getstatic     #22                 // Field org/apache/hadoop/hbase/security/visibility/VisibilityConstants.LABELS_TABLE_NAME:Lorg/apache/hadoop/hbase/TableName;
      71: invokevirtual #23                 // Method org/apache/hadoop/hbase/TableName.getName:()[B
      74: ldc2_w        #24                 // long 50000l
      77: invokevirtual #26                 // Method org/apache/hadoop/hbase/HBaseTestingUtility.waitTableEnabled:([BJ)V
      80: invokestatic  #27                 // Method addLabels:()V
      83: return

  public static void tearDownAfterClass() throws java.lang.Exception;
    Code:
       0: getstatic     #5                  // Field TEST_UTIL:Lorg/apache/hadoop/hbase/HBaseTestingUtility;
       3: invokevirtual #28                 // Method org/apache/hadoop/hbase/HBaseTestingUtility.shutdownMiniCluster:()V
       6: return

  public static void addLabels() throws java.lang.Exception;
    Code:
       0: new           #29                 // class org/apache/hadoop/hbase/security/visibility/VisibilityLabelsWithDeletesTestBase$1
       3: dup
       4: invokespecial #30                 // Method org/apache/hadoop/hbase/security/visibility/VisibilityLabelsWithDeletesTestBase$1."<init>":()V
       7: astore_0
       8: getstatic     #21                 // Field SUPERUSER:Lorg/apache/hadoop/hbase/security/User;
      11: aload_0
      12: invokevirtual #31                 // Method org/apache/hadoop/hbase/security/User.runAs:(Ljava/security/PrivilegedExceptionAction;)Ljava/lang/Object;
      15: pop
      16: return

  protected abstract org.apache.hadoop.hbase.client.Table createTable(byte[]) throws java.io.IOException;

  protected final void setAuths() throws java.io.IOException, java.lang.InterruptedException;
    Code:
       0: new           #32                 // class org/apache/hadoop/hbase/security/visibility/VisibilityLabelsWithDeletesTestBase$2
       3: dup
       4: aload_0
       5: invokespecial #33                 // Method org/apache/hadoop/hbase/security/visibility/VisibilityLabelsWithDeletesTestBase$2."<init>":(Lorg/apache/hadoop/hbase/security/visibility/VisibilityLabelsWithDeletesTestBase;)V
       8: astore_1
       9: getstatic     #21                 // Field SUPERUSER:Lorg/apache/hadoop/hbase/security/User;
      12: aload_1
      13: invokevirtual #31                 // Method org/apache/hadoop/hbase/security/User.runAs:(Ljava/security/PrivilegedExceptionAction;)Ljava/lang/Object;
      16: pop
      17: return

  public void testVisibilityLabelsWithDeleteColumns() throws java.lang.Throwable;
    Code:
       0: aload_0
       1: invokevirtual #61                 // Method setAuths:()V
       4: aload_0
       5: getfield      #4                  // Field testName:Lorg/junit/rules/TestName;
       8: invokevirtual #62                 // Method org/junit/rules/TestName.getMethodName:()Ljava/lang/String;
      11: invokestatic  #63                 // Method org/apache/hadoop/hbase/TableName.valueOf:(Ljava/lang/String;)Lorg/apache/hadoop/hbase/TableName;
      14: astore_1
      15: aload_0
      16: iconst_2
      17: anewarray     #18                 // class java/lang/String
      20: dup
      21: iconst_0
      22: ldc           #65                 // String SECRET&TOPSECRET
      24: aastore
      25: dup
      26: iconst_1
      27: ldc           #66                 // String SECRET
      29: aastore
      30: invokespecial #67                 // Method createTableAndWriteDataWithLabels:([Ljava/lang/String;)Lorg/apache/hadoop/hbase/client/Table;
      33: astore_2
      34: aconst_null
      35: astore_3
      36: new           #68                 // class org/apache/hadoop/hbase/security/visibility/VisibilityLabelsWithDeletesTestBase$3
      39: dup
      40: aload_0
      41: aload_1
      42: invokespecial #69                 // Method org/apache/hadoop/hbase/security/visibility/VisibilityLabelsWithDeletesTestBase$3."<init>":(Lorg/apache/hadoop/hbase/security/visibility/VisibilityLabelsWithDeletesTestBase;Lorg/apache/hadoop/hbase/TableName;)V
      45: astore        4
      47: getstatic     #21                 // Field SUPERUSER:Lorg/apache/hadoop/hbase/security/User;
      50: aload         4
      52: invokevirtual #31                 // Method org/apache/hadoop/hbase/security/User.runAs:(Ljava/security/PrivilegedExceptionAction;)Ljava/lang/Object;
      55: pop
      56: getstatic     #5                  // Field TEST_UTIL:Lorg/apache/hadoop/hbase/HBaseTestingUtility;
      59: invokevirtual #58                 // Method org/apache/hadoop/hbase/HBaseTestingUtility.getAdmin:()Lorg/apache/hadoop/hbase/client/Admin;
      62: aload_1
      63: invokeinterface #60,  2           // InterfaceMethod org/apache/hadoop/hbase/client/Admin.flush:(Lorg/apache/hadoop/hbase/TableName;)V
      68: new           #70                 // class org/apache/hadoop/hbase/client/Scan
      71: dup
      72: invokespecial #71                 // Method org/apache/hadoop/hbase/client/Scan."<init>":()V
      75: astore        5
      77: aload         5
      79: new           #72                 // class org/apache/hadoop/hbase/security/visibility/Authorizations
      82: dup
      83: iconst_3
      84: anewarray     #18                 // class java/lang/String
      87: dup
      88: iconst_0
      89: ldc           #66                 // String SECRET
      91: aastore
      92: dup
      93: iconst_1
      94: ldc           #73                 // String PRIVATE
      96: aastore
      97: dup
      98: iconst_2
      99: ldc           #74                 // String CONFIDENTIAL
     101: aastore
     102: invokespecial #75                 // Method org/apache/hadoop/hbase/security/visibility/Authorizations."<init>":([Ljava/lang/String;)V
     105: invokevirtual #76                 // Method org/apache/hadoop/hbase/client/Scan.setAuthorizations:(Lorg/apache/hadoop/hbase/security/visibility/Authorizations;)Lorg/apache/hadoop/hbase/client/Scan;
     108: pop
     109: aload_2
     110: aload         5
     112: invokeinterface #77,  2           // InterfaceMethod org/apache/hadoop/hbase/client/Table.getScanner:(Lorg/apache/hadoop/hbase/client/Scan;)Lorg/apache/hadoop/hbase/client/ResultScanner;
     117: astore        6
     119: aload         6
     121: iconst_3
     122: invokeinterface #78,  2           // InterfaceMethod org/apache/hadoop/hbase/client/ResultScanner.next:(I)[Lorg/apache/hadoop/hbase/client/Result;
     127: astore        7
     129: aload         7
     131: arraylength
     132: iconst_1
     133: if_icmpne     140
     136: iconst_1
     137: goto          141
     140: iconst_0
     141: invokestatic  #79                 // Method org/junit/Assert.assertTrue:(Z)V
     144: aload         7
     146: iconst_0
     147: aaload
     148: invokevirtual #80                 // Method org/apache/hadoop/hbase/client/Result.cellScanner:()Lorg/apache/hadoop/hbase/CellScanner;
     151: astore        8
     153: aload         8
     155: invokeinterface #81,  1           // InterfaceMethod org/apache/hadoop/hbase/CellScanner.advance:()Z
     160: pop
     161: aload         8
     163: invokeinterface #82,  1           // InterfaceMethod org/apache/hadoop/hbase/CellScanner.current:()Lorg/apache/hadoop/hbase/Cell;
     168: astore        9
     170: aload         9
     172: invokeinterface #83,  1           // InterfaceMethod org/apache/hadoop/hbase/Cell.getRowArray:()[B
     177: aload         9
     179: invokeinterface #84,  1           // InterfaceMethod org/apache/hadoop/hbase/Cell.getRowOffset:()I
     184: aload         9
     186: invokeinterface #85,  1           // InterfaceMethod org/apache/hadoop/hbase/Cell.getRowLength:()S
     191: getstatic     #86                 // Field row2:[B
     194: iconst_0
     195: getstatic     #86                 // Field row2:[B
     198: arraylength
     199: invokestatic  #87                 // Method org/apache/hadoop/hbase/util/Bytes.equals:([BII[BII)Z
     202: invokestatic  #79                 // Method org/junit/Assert.assertTrue:(Z)V
     205: aload_2
     206: ifnull        289
     209: aload_3
     210: ifnull        233
     213: aload_2
     214: invokeinterface #88,  1           // InterfaceMethod org/apache/hadoop/hbase/client/Table.close:()V
     219: goto          289
     222: astore        4
     224: aload_3
     225: aload         4
     227: invokevirtual #90                 // Method java/lang/Throwable.addSuppressed:(Ljava/lang/Throwable;)V
     230: goto          289
     233: aload_2
     234: invokeinterface #88,  1           // InterfaceMethod org/apache/hadoop/hbase/client/Table.close:()V
     239: goto          289
     242: astore        4
     244: aload         4
     246: astore_3
     247: aload         4
     249: athrow
     250: astore        10
     252: aload_2
     253: ifnull        286
     256: aload_3
     257: ifnull        280
     260: aload_2
     261: invokeinterface #88,  1           // InterfaceMethod org/apache/hadoop/hbase/client/Table.close:()V
     266: goto          286
     269: astore        11
     271: aload_3
     272: aload         11
     274: invokevirtual #90                 // Method java/lang/Throwable.addSuppressed:(Ljava/lang/Throwable;)V
     277: goto          286
     280: aload_2
     281: invokeinterface #88,  1           // InterfaceMethod org/apache/hadoop/hbase/client/Table.close:()V
     286: aload         10
     288: athrow
     289: return
    Exception table:
       from    to  target type
         213   219   222   Class java/lang/Throwable
          36   205   242   Class java/lang/Throwable
          36   205   250   any
         260   266   269   Class java/lang/Throwable
         242   252   250   any

  public void testVisibilityLabelsWithDeleteFamily() throws java.lang.Exception;
    Code:
       0: aload_0
       1: invokevirtual #61                 // Method setAuths:()V
       4: aload_0
       5: getfield      #4                  // Field testName:Lorg/junit/rules/TestName;
       8: invokevirtual #62                 // Method org/junit/rules/TestName.getMethodName:()Ljava/lang/String;
      11: invokestatic  #63                 // Method org/apache/hadoop/hbase/TableName.valueOf:(Ljava/lang/String;)Lorg/apache/hadoop/hbase/TableName;
      14: astore_1
      15: aload_0
      16: iconst_2
      17: anewarray     #18                 // class java/lang/String
      20: dup
      21: iconst_0
      22: ldc           #66                 // String SECRET
      24: aastore
      25: dup
      26: iconst_1
      27: ldc           #91                 // String CONFIDENTIAL|TOPSECRET
      29: aastore
      30: invokespecial #67                 // Method createTableAndWriteDataWithLabels:([Ljava/lang/String;)Lorg/apache/hadoop/hbase/client/Table;
      33: astore_2
      34: aconst_null
      35: astore_3
      36: new           #92                 // class org/apache/hadoop/hbase/security/visibility/VisibilityLabelsWithDeletesTestBase$4
      39: dup
      40: aload_0
      41: aload_1
      42: invokespecial #93                 // Method org/apache/hadoop/hbase/security/visibility/VisibilityLabelsWithDeletesTestBase$4."<init>":(Lorg/apache/hadoop/hbase/security/visibility/VisibilityLabelsWithDeletesTestBase;Lorg/apache/hadoop/hbase/TableName;)V
      45: astore        4
      47: getstatic     #21                 // Field SUPERUSER:Lorg/apache/hadoop/hbase/security/User;
      50: aload         4
      52: invokevirtual #31                 // Method org/apache/hadoop/hbase/security/User.runAs:(Ljava/security/PrivilegedExceptionAction;)Ljava/lang/Object;
      55: pop
      56: getstatic     #5                  // Field TEST_UTIL:Lorg/apache/hadoop/hbase/HBaseTestingUtility;
      59: invokevirtual #58                 // Method org/apache/hadoop/hbase/HBaseTestingUtility.getAdmin:()Lorg/apache/hadoop/hbase/client/Admin;
      62: aload_1
      63: invokeinterface #60,  2           // InterfaceMethod org/apache/hadoop/hbase/client/Admin.flush:(Lorg/apache/hadoop/hbase/TableName;)V
      68: new           #70                 // class org/apache/hadoop/hbase/client/Scan
      71: dup
      72: invokespecial #71                 // Method org/apache/hadoop/hbase/client/Scan."<init>":()V
      75: astore        5
      77: aload         5
      79: new           #72                 // class org/apache/hadoop/hbase/security/visibility/Authorizations
      82: dup
      83: iconst_3
      84: anewarray     #18                 // class java/lang/String
      87: dup
      88: iconst_0
      89: ldc           #66                 // String SECRET
      91: aastore
      92: dup
      93: iconst_1
      94: ldc           #73                 // String PRIVATE
      96: aastore
      97: dup
      98: iconst_2
      99: ldc           #74                 // String CONFIDENTIAL
     101: aastore
     102: invokespecial #75                 // Method org/apache/hadoop/hbase/security/visibility/Authorizations."<init>":([Ljava/lang/String;)V
     105: invokevirtual #76                 // Method org/apache/hadoop/hbase/client/Scan.setAuthorizations:(Lorg/apache/hadoop/hbase/security/visibility/Authorizations;)Lorg/apache/hadoop/hbase/client/Scan;
     108: pop
     109: aload_2
     110: aload         5
     112: invokeinterface #77,  2           // InterfaceMethod org/apache/hadoop/hbase/client/Table.getScanner:(Lorg/apache/hadoop/hbase/client/Scan;)Lorg/apache/hadoop/hbase/client/ResultScanner;
     117: astore        6
     119: aload         6
     121: iconst_3
     122: invokeinterface #78,  2           // InterfaceMethod org/apache/hadoop/hbase/client/ResultScanner.next:(I)[Lorg/apache/hadoop/hbase/client/Result;
     127: astore        7
     129: aload         7
     131: arraylength
     132: iconst_1
     133: if_icmpne     140
     136: iconst_1
     137: goto          141
     140: iconst_0
     141: invokestatic  #79                 // Method org/junit/Assert.assertTrue:(Z)V
     144: aload         7
     146: iconst_0
     147: aaload
     148: invokevirtual #80                 // Method org/apache/hadoop/hbase/client/Result.cellScanner:()Lorg/apache/hadoop/hbase/CellScanner;
     151: astore        8
     153: aload         8
     155: invokeinterface #81,  1           // InterfaceMethod org/apache/hadoop/hbase/CellScanner.advance:()Z
     160: pop
     161: aload         8
     163: invokeinterface #82,  1           // InterfaceMethod org/apache/hadoop/hbase/CellScanner.current:()Lorg/apache/hadoop/hbase/Cell;
     168: astore        9
     170: aload         9
     172: invokeinterface #83,  1           // InterfaceMethod org/apache/hadoop/hbase/Cell.getRowArray:()[B
     177: aload         9
     179: invokeinterface #84,  1           // InterfaceMethod org/apache/hadoop/hbase/Cell.getRowOffset:()I
     184: aload         9
     186: invokeinterface #85,  1           // InterfaceMethod org/apache/hadoop/hbase/Cell.getRowLength:()S
     191: getstatic     #94                 // Field row1:[B
     194: iconst_0
     195: getstatic     #94                 // Field row1:[B
     198: arraylength
     199: invokestatic  #87                 // Method org/apache/hadoop/hbase/util/Bytes.equals:([BII[BII)Z
     202: invokestatic  #79                 // Method org/junit/Assert.assertTrue:(Z)V
     205: aload_2
     206: ifnull        289
     209: aload_3
     210: ifnull        233
     213: aload_2
     214: invokeinterface #88,  1           // InterfaceMethod org/apache/hadoop/hbase/client/Table.close:()V
     219: goto          289
     222: astore        4
     224: aload_3
     225: aload         4
     227: invokevirtual #90                 // Method java/lang/Throwable.addSuppressed:(Ljava/lang/Throwable;)V
     230: goto          289
     233: aload_2
     234: invokeinterface #88,  1           // InterfaceMethod org/apache/hadoop/hbase/client/Table.close:()V
     239: goto          289
     242: astore        4
     244: aload         4
     246: astore_3
     247: aload         4
     249: athrow
     250: astore        10
     252: aload_2
     253: ifnull        286
     256: aload_3
     257: ifnull        280
     260: aload_2
     261: invokeinterface #88,  1           // InterfaceMethod org/apache/hadoop/hbase/client/Table.close:()V
     266: goto          286
     269: astore        11
     271: aload_3
     272: aload         11
     274: invokevirtual #90                 // Method java/lang/Throwable.addSuppressed:(Ljava/lang/Throwable;)V
     277: goto          286
     280: aload_2
     281: invokeinterface #88,  1           // InterfaceMethod org/apache/hadoop/hbase/client/Table.close:()V
     286: aload         10
     288: athrow
     289: return
    Exception table:
       from    to  target type
         213   219   222   Class java/lang/Throwable
          36   205   242   Class java/lang/Throwable
          36   205   250   any
         260   266   269   Class java/lang/Throwable
         242   252   250   any

  public void testVisibilityLabelsWithDeleteFamilyVersion() throws java.lang.Exception;
    Code:
       0: aload_0
       1: invokevirtual #61                 // Method setAuths:()V
       4: aload_0
       5: getfield      #4                  // Field testName:Lorg/junit/rules/TestName;
       8: invokevirtual #62                 // Method org/junit/rules/TestName.getMethodName:()Ljava/lang/String;
      11: invokestatic  #63                 // Method org/apache/hadoop/hbase/TableName.valueOf:(Ljava/lang/String;)Lorg/apache/hadoop/hbase/TableName;
      14: astore_1
      15: iconst_2
      16: newarray       long
      18: dup
      19: iconst_0
      20: ldc2_w        #95                 // long 123l
      23: lastore
      24: dup
      25: iconst_1
      26: ldc2_w        #97                 // long 125l
      29: lastore
      30: astore_2
      31: aload_0
      32: aload_2
      33: iconst_2
      34: anewarray     #18                 // class java/lang/String
      37: dup
      38: iconst_0
      39: ldc           #91                 // String CONFIDENTIAL|TOPSECRET
      41: aastore
      42: dup
      43: iconst_1
      44: ldc           #66                 // String SECRET
      46: aastore
      47: invokespecial #99                 // Method createTableAndWriteDataWithLabels:([J[Ljava/lang/String;)Lorg/apache/hadoop/hbase/client/Table;
      50: astore_3
      51: aconst_null
      52: astore        4
      54: new           #100                // class org/apache/hadoop/hbase/security/visibility/VisibilityLabelsWithDeletesTestBase$5
      57: dup
      58: aload_0
      59: aload_1
      60: invokespecial #101                // Method org/apache/hadoop/hbase/security/visibility/VisibilityLabelsWithDeletesTestBase$5."<init>":(Lorg/apache/hadoop/hbase/security/visibility/VisibilityLabelsWithDeletesTestBase;Lorg/apache/hadoop/hbase/TableName;)V
      63: astore        5
      65: getstatic     #21                 // Field SUPERUSER:Lorg/apache/hadoop/hbase/security/User;
      68: aload         5
      70: invokevirtual #31                 // Method org/apache/hadoop/hbase/security/User.runAs:(Ljava/security/PrivilegedExceptionAction;)Ljava/lang/Object;
      73: pop
      74: getstatic     #5                  // Field TEST_UTIL:Lorg/apache/hadoop/hbase/HBaseTestingUtility;
      77: invokevirtual #58                 // Method org/apache/hadoop/hbase/HBaseTestingUtility.getAdmin:()Lorg/apache/hadoop/hbase/client/Admin;
      80: aload_1
      81: invokeinterface #60,  2           // InterfaceMethod org/apache/hadoop/hbase/client/Admin.flush:(Lorg/apache/hadoop/hbase/TableName;)V
      86: new           #70                 // class org/apache/hadoop/hbase/client/Scan
      89: dup
      90: invokespecial #71                 // Method org/apache/hadoop/hbase/client/Scan."<init>":()V
      93: astore        6
      95: aload         6
      97: new           #72                 // class org/apache/hadoop/hbase/security/visibility/Authorizations
     100: dup
     101: iconst_3
     102: anewarray     #18                 // class java/lang/String
     105: dup
     106: iconst_0
     107: ldc           #66                 // String SECRET
     109: aastore
     110: dup
     111: iconst_1
     112: ldc           #73                 // String PRIVATE
     114: aastore
     115: dup
     116: iconst_2
     117: ldc           #74                 // String CONFIDENTIAL
     119: aastore
     120: invokespecial #75                 // Method org/apache/hadoop/hbase/security/visibility/Authorizations."<init>":([Ljava/lang/String;)V
     123: invokevirtual #76                 // Method org/apache/hadoop/hbase/client/Scan.setAuthorizations:(Lorg/apache/hadoop/hbase/security/visibility/Authorizations;)Lorg/apache/hadoop/hbase/client/Scan;
     126: pop
     127: aload_3
     128: aload         6
     130: invokeinterface #77,  2           // InterfaceMethod org/apache/hadoop/hbase/client/Table.getScanner:(Lorg/apache/hadoop/hbase/client/Scan;)Lorg/apache/hadoop/hbase/client/ResultScanner;
     135: astore        7
     137: aload         7
     139: iconst_3
     140: invokeinterface #78,  2           // InterfaceMethod org/apache/hadoop/hbase/client/ResultScanner.next:(I)[Lorg/apache/hadoop/hbase/client/Result;
     145: astore        8
     147: aload         8
     149: arraylength
     150: iconst_1
     151: if_icmpne     158
     154: iconst_1
     155: goto          159
     158: iconst_0
     159: invokestatic  #79                 // Method org/junit/Assert.assertTrue:(Z)V
     162: aload         8
     164: iconst_0
     165: aaload
     166: invokevirtual #80                 // Method org/apache/hadoop/hbase/client/Result.cellScanner:()Lorg/apache/hadoop/hbase/CellScanner;
     169: astore        9
     171: aload         9
     173: invokeinterface #81,  1           // InterfaceMethod org/apache/hadoop/hbase/CellScanner.advance:()Z
     178: pop
     179: aload         9
     181: invokeinterface #82,  1           // InterfaceMethod org/apache/hadoop/hbase/CellScanner.current:()Lorg/apache/hadoop/hbase/Cell;
     186: astore        10
     188: aload         10
     190: invokeinterface #83,  1           // InterfaceMethod org/apache/hadoop/hbase/Cell.getRowArray:()[B
     195: aload         10
     197: invokeinterface #84,  1           // InterfaceMethod org/apache/hadoop/hbase/Cell.getRowOffset:()I
     202: aload         10
     204: invokeinterface #85,  1           // InterfaceMethod org/apache/hadoop/hbase/Cell.getRowLength:()S
     209: getstatic     #86                 // Field row2:[B
     212: iconst_0
     213: getstatic     #86                 // Field row2:[B
     216: arraylength
     217: invokestatic  #87                 // Method org/apache/hadoop/hbase/util/Bytes.equals:([BII[BII)Z
     220: invokestatic  #79                 // Method org/junit/Assert.assertTrue:(Z)V
     223: aload_3
     224: ifnull        312
     227: aload         4
     229: ifnull        253
     232: aload_3
     233: invokeinterface #88,  1           // InterfaceMethod org/apache/hadoop/hbase/client/Table.close:()V
     238: goto          312
     241: astore        5
     243: aload         4
     245: aload         5
     247: invokevirtual #90                 // Method java/lang/Throwable.addSuppressed:(Ljava/lang/Throwable;)V
     250: goto          312
     253: aload_3
     254: invokeinterface #88,  1           // InterfaceMethod org/apache/hadoop/hbase/client/Table.close:()V
     259: goto          312
     262: astore        5
     264: aload         5
     266: astore        4
     268: aload         5
     270: athrow
     271: astore        11
     273: aload_3
     274: ifnull        309
     277: aload         4
     279: ifnull        303
     282: aload_3
     283: invokeinterface #88,  1           // InterfaceMethod org/apache/hadoop/hbase/client/Table.close:()V
     288: goto          309
     291: astore        12
     293: aload         4
     295: aload         12
     297: invokevirtual #90                 // Method java/lang/Throwable.addSuppressed:(Ljava/lang/Throwable;)V
     300: goto          309
     303: aload_3
     304: invokeinterface #88,  1           // InterfaceMethod org/apache/hadoop/hbase/client/Table.close:()V
     309: aload         11
     311: athrow
     312: return
    Exception table:
       from    to  target type
         232   238   241   Class java/lang/Throwable
          54   223   262   Class java/lang/Throwable
          54   223   271   any
         282   288   291   Class java/lang/Throwable
         262   273   271   any

  public void testVisibilityLabelsWithDeleteColumnExactVersion() throws java.lang.Exception;
    Code:
       0: aload_0
       1: invokevirtual #61                 // Method setAuths:()V
       4: aload_0
       5: getfield      #4                  // Field testName:Lorg/junit/rules/TestName;
       8: invokevirtual #62                 // Method org/junit/rules/TestName.getMethodName:()Ljava/lang/String;
      11: invokestatic  #63                 // Method org/apache/hadoop/hbase/TableName.valueOf:(Ljava/lang/String;)Lorg/apache/hadoop/hbase/TableName;
      14: astore_1
      15: iconst_2
      16: newarray       long
      18: dup
      19: iconst_0
      20: ldc2_w        #95                 // long 123l
      23: lastore
      24: dup
      25: iconst_1
      26: ldc2_w        #97                 // long 125l
      29: lastore
      30: astore_2
      31: aload_0
      32: aload_2
      33: iconst_2
      34: anewarray     #18                 // class java/lang/String
      37: dup
      38: iconst_0
      39: ldc           #91                 // String CONFIDENTIAL|TOPSECRET
      41: aastore
      42: dup
      43: iconst_1
      44: ldc           #66                 // String SECRET
      46: aastore
      47: invokespecial #99                 // Method createTableAndWriteDataWithLabels:([J[Ljava/lang/String;)Lorg/apache/hadoop/hbase/client/Table;
      50: astore_3
      51: aconst_null
      52: astore        4
      54: new           #102                // class org/apache/hadoop/hbase/security/visibility/VisibilityLabelsWithDeletesTestBase$6
      57: dup
      58: aload_0
      59: aload_1
      60: invokespecial #103                // Method org/apache/hadoop/hbase/security/visibility/VisibilityLabelsWithDeletesTestBase$6."<init>":(Lorg/apache/hadoop/hbase/security/visibility/VisibilityLabelsWithDeletesTestBase;Lorg/apache/hadoop/hbase/TableName;)V
      63: astore        5
      65: getstatic     #21                 // Field SUPERUSER:Lorg/apache/hadoop/hbase/security/User;
      68: aload         5
      70: invokevirtual #31                 // Method org/apache/hadoop/hbase/security/User.runAs:(Ljava/security/PrivilegedExceptionAction;)Ljava/lang/Object;
      73: pop
      74: getstatic     #5                  // Field TEST_UTIL:Lorg/apache/hadoop/hbase/HBaseTestingUtility;
      77: invokevirtual #58                 // Method org/apache/hadoop/hbase/HBaseTestingUtility.getAdmin:()Lorg/apache/hadoop/hbase/client/Admin;
      80: aload_1
      81: invokeinterface #60,  2           // InterfaceMethod org/apache/hadoop/hbase/client/Admin.flush:(Lorg/apache/hadoop/hbase/TableName;)V
      86: new           #70                 // class org/apache/hadoop/hbase/client/Scan
      89: dup
      90: invokespecial #71                 // Method org/apache/hadoop/hbase/client/Scan."<init>":()V
      93: astore        6
      95: aload         6
      97: new           #72                 // class org/apache/hadoop/hbase/security/visibility/Authorizations
     100: dup
     101: iconst_3
     102: anewarray     #18                 // class java/lang/String
     105: dup
     106: iconst_0
     107: ldc           #66                 // String SECRET
     109: aastore
     110: dup
     111: iconst_1
     112: ldc           #73                 // String PRIVATE
     114: aastore
     115: dup
     116: iconst_2
     117: ldc           #74                 // String CONFIDENTIAL
     119: aastore
     120: invokespecial #75                 // Method org/apache/hadoop/hbase/security/visibility/Authorizations."<init>":([Ljava/lang/String;)V
     123: invokevirtual #76                 // Method org/apache/hadoop/hbase/client/Scan.setAuthorizations:(Lorg/apache/hadoop/hbase/security/visibility/Authorizations;)Lorg/apache/hadoop/hbase/client/Scan;
     126: pop
     127: aload_3
     128: aload         6
     130: invokeinterface #77,  2           // InterfaceMethod org/apache/hadoop/hbase/client/Table.getScanner:(Lorg/apache/hadoop/hbase/client/Scan;)Lorg/apache/hadoop/hbase/client/ResultScanner;
     135: astore        7
     137: aload         7
     139: iconst_3
     140: invokeinterface #78,  2           // InterfaceMethod org/apache/hadoop/hbase/client/ResultScanner.next:(I)[Lorg/apache/hadoop/hbase/client/Result;
     145: astore        8
     147: aload         8
     149: arraylength
     150: iconst_1
     151: if_icmpne     158
     154: iconst_1
     155: goto          159
     158: iconst_0
     159: invokestatic  #79                 // Method org/junit/Assert.assertTrue:(Z)V
     162: aload         8
     164: iconst_0
     165: aaload
     166: invokevirtual #80                 // Method org/apache/hadoop/hbase/client/Result.cellScanner:()Lorg/apache/hadoop/hbase/CellScanner;
     169: astore        9
     171: aload         9
     173: invokeinterface #81,  1           // InterfaceMethod org/apache/hadoop/hbase/CellScanner.advance:()Z
     178: pop
     179: aload         9
     181: invokeinterface #82,  1           // InterfaceMethod org/apache/hadoop/hbase/CellScanner.current:()Lorg/apache/hadoop/hbase/Cell;
     186: astore        10
     188: aload         10
     190: invokeinterface #83,  1           // InterfaceMethod org/apache/hadoop/hbase/Cell.getRowArray:()[B
     195: aload         10
     197: invokeinterface #84,  1           // InterfaceMethod org/apache/hadoop/hbase/Cell.getRowOffset:()I
     202: aload         10
     204: invokeinterface #85,  1           // InterfaceMethod org/apache/hadoop/hbase/Cell.getRowLength:()S
     209: getstatic     #86                 // Field row2:[B
     212: iconst_0
     213: getstatic     #86                 // Field row2:[B
     216: arraylength
     217: invokestatic  #87                 // Method org/apache/hadoop/hbase/util/Bytes.equals:([BII[BII)Z
     220: invokestatic  #79                 // Method org/junit/Assert.assertTrue:(Z)V
     223: aload_3
     224: ifnull        312
     227: aload         4
     229: ifnull        253
     232: aload_3
     233: invokeinterface #88,  1           // InterfaceMethod org/apache/hadoop/hbase/client/Table.close:()V
     238: goto          312
     241: astore        5
     243: aload         4
     245: aload         5
     247: invokevirtual #90                 // Method java/lang/Throwable.addSuppressed:(Ljava/lang/Throwable;)V
     250: goto          312
     253: aload_3
     254: invokeinterface #88,  1           // InterfaceMethod org/apache/hadoop/hbase/client/Table.close:()V
     259: goto          312
     262: astore        5
     264: aload         5
     266: astore        4
     268: aload         5
     270: athrow
     271: astore        11
     273: aload_3
     274: ifnull        309
     277: aload         4
     279: ifnull        303
     282: aload_3
     283: invokeinterface #88,  1           // InterfaceMethod org/apache/hadoop/hbase/client/Table.close:()V
     288: goto          309
     291: astore        12
     293: aload         4
     295: aload         12
     297: invokevirtual #90                 // Method java/lang/Throwable.addSuppressed:(Ljava/lang/Throwable;)V
     300: goto          309
     303: aload_3
     304: invokeinterface #88,  1           // InterfaceMethod org/apache/hadoop/hbase/client/Table.close:()V
     309: aload         11
     311: athrow
     312: return
    Exception table:
       from    to  target type
         232   238   241   Class java/lang/Throwable
          54   223   262   Class java/lang/Throwable
          54   223   271   any
         282   288   291   Class java/lang/Throwable
         262   273   271   any

  static {};
    Code:
       0: new           #104                // class org/apache/hadoop/hbase/HBaseTestingUtility
       3: dup
       4: invokespecial #105                // Method org/apache/hadoop/hbase/HBaseTestingUtility."<init>":()V
       7: putstatic     #5                  // Field TEST_UTIL:Lorg/apache/hadoop/hbase/HBaseTestingUtility;
      10: ldc           #106                // String row1
      12: invokestatic  #45                 // Method org/apache/hadoop/hbase/util/Bytes.toBytes:(Ljava/lang/String;)[B
      15: putstatic     #94                 // Field row1:[B
      18: ldc           #107                // String row2
      20: invokestatic  #45                 // Method org/apache/hadoop/hbase/util/Bytes.toBytes:(Ljava/lang/String;)[B
      23: putstatic     #86                 // Field row2:[B
      26: ldc           #108                // String info
      28: invokestatic  #45                 // Method org/apache/hadoop/hbase/util/Bytes.toBytes:(Ljava/lang/String;)[B
      31: putstatic     #34                 // Field fam:[B
      34: ldc           #109                // String qual
      36: invokestatic  #45                 // Method org/apache/hadoop/hbase/util/Bytes.toBytes:(Ljava/lang/String;)[B
      39: putstatic     #47                 // Field qual:[B
      42: ldc           #110                // String qual1
      44: invokestatic  #45                 // Method org/apache/hadoop/hbase/util/Bytes.toBytes:(Ljava/lang/String;)[B
      47: putstatic     #111                // Field qual1:[B
      50: ldc           #112                // String qual2
      52: invokestatic  #45                 // Method org/apache/hadoop/hbase/util/Bytes.toBytes:(Ljava/lang/String;)[B
      55: putstatic     #113                // Field qual2:[B
      58: ldc           #114                // String value
      60: invokestatic  #45                 // Method org/apache/hadoop/hbase/util/Bytes.toBytes:(Ljava/lang/String;)[B
      63: putstatic     #51                 // Field value:[B
      66: ldc           #115                // String value1
      68: invokestatic  #45                 // Method org/apache/hadoop/hbase/util/Bytes.toBytes:(Ljava/lang/String;)[B
      71: putstatic     #116                // Field value1:[B
      74: return
}
