Compiled from "VisibilityScanDeleteTracker.java"
public class org.apache.hadoop.hbase.security.visibility.VisibilityScanDeleteTracker extends org.apache.hadoop.hbase.regionserver.querymatcher.ScanDeleteTracker {
  public org.apache.hadoop.hbase.security.visibility.VisibilityScanDeleteTracker(org.apache.hadoop.hbase.CellComparator);
    Code:
       0: aload_0
       1: aload_1
       2: invokespecial #1                  // Method org/apache/hadoop/hbase/regionserver/querymatcher/ScanDeleteTracker."<init>":(Lorg/apache/hadoop/hbase/CellComparator;)V
       5: aload_0
       6: new           #2                  // class java/util/ArrayList
       9: dup
      10: invokespecial #3                  // Method java/util/ArrayList."<init>":()V
      13: putfield      #4                  // Field visibilityTagsDeleteFamily:Ljava/util/List;
      16: aload_0
      17: new           #2                  // class java/util/ArrayList
      20: dup
      21: invokespecial #3                  // Method java/util/ArrayList."<init>":()V
      24: putfield      #5                  // Field visibilityTagsDeleteFamilyVersion:Ljava/util/List;
      27: aload_0
      28: new           #2                  // class java/util/ArrayList
      31: dup
      32: invokespecial #3                  // Method java/util/ArrayList."<init>":()V
      35: putfield      #6                  // Field visiblityTagsDeleteColumnVersion:Ljava/util/List;
      38: return

  public void add(org.apache.hadoop.hbase.Cell);
    Code:
       0: aload_1
       1: invokeinterface #7,  1            // InterfaceMethod org/apache/hadoop/hbase/Cell.getTimestamp:()J
       6: lstore_2
       7: aload_1
       8: invokeinterface #8,  1            // InterfaceMethod org/apache/hadoop/hbase/Cell.getTypeByte:()B
      13: istore        4
      15: iload         4
      17: getstatic     #9                  // Field org/apache/hadoop/hbase/KeyValue$Type.DeleteFamily:Lorg/apache/hadoop/hbase/KeyValue$Type;
      20: invokevirtual #10                 // Method org/apache/hadoop/hbase/KeyValue$Type.getCode:()B
      23: if_icmpne     61
      26: aload_0
      27: iconst_1
      28: putfield      #11                 // Field hasFamilyStamp:Z
      31: aload_0
      32: aload_1
      33: getstatic     #9                  // Field org/apache/hadoop/hbase/KeyValue$Type.DeleteFamily:Lorg/apache/hadoop/hbase/KeyValue$Type;
      36: invokespecial #12                 // Method extractDeleteCellVisTags:(Lorg/apache/hadoop/hbase/Cell;Lorg/apache/hadoop/hbase/KeyValue$Type;)Z
      39: istore        5
      41: iload         5
      43: ifne          60
      46: lload_2
      47: aload_0
      48: getfield      #13                 // Field familyStamp:J
      51: lcmp
      52: ifle          60
      55: aload_0
      56: lload_2
      57: putfield      #13                 // Field familyStamp:J
      60: return
      61: iload         4
      63: getstatic     #14                 // Field org/apache/hadoop/hbase/KeyValue$Type.DeleteFamilyVersion:Lorg/apache/hadoop/hbase/KeyValue$Type;
      66: invokevirtual #10                 // Method org/apache/hadoop/hbase/KeyValue$Type.getCode:()B
      69: if_icmpne     96
      72: aload_0
      73: getfield      #15                 // Field familyVersionStamps:Ljava/util/SortedSet;
      76: lload_2
      77: invokestatic  #16                 // Method java/lang/Long.valueOf:(J)Ljava/lang/Long;
      80: invokeinterface #17,  2           // InterfaceMethod java/util/SortedSet.add:(Ljava/lang/Object;)Z
      85: pop
      86: aload_0
      87: aload_1
      88: getstatic     #14                 // Field org/apache/hadoop/hbase/KeyValue$Type.DeleteFamilyVersion:Lorg/apache/hadoop/hbase/KeyValue$Type;
      91: invokespecial #12                 // Method extractDeleteCellVisTags:(Lorg/apache/hadoop/hbase/Cell;Lorg/apache/hadoop/hbase/KeyValue$Type;)Z
      94: pop
      95: return
      96: aload_0
      97: getfield      #18                 // Field deleteCell:Lorg/apache/hadoop/hbase/Cell;
     100: ifnull        152
     103: aload_1
     104: aload_0
     105: getfield      #18                 // Field deleteCell:Lorg/apache/hadoop/hbase/Cell;
     108: invokestatic  #19                 // Method org/apache/hadoop/hbase/CellUtil.matchingQualifier:(Lorg/apache/hadoop/hbase/Cell;Lorg/apache/hadoop/hbase/Cell;)Z
     111: ifne          127
     114: aload_0
     115: aconst_null
     116: putfield      #20                 // Field visibilityTagsDeleteColumns:Ljava/util/List;
     119: aload_0
     120: aconst_null
     121: putfield      #6                  // Field visiblityTagsDeleteColumnVersion:Ljava/util/List;
     124: goto          152
     127: iload         4
     129: getstatic     #21                 // Field org/apache/hadoop/hbase/KeyValue$Type.Delete:Lorg/apache/hadoop/hbase/KeyValue$Type;
     132: invokevirtual #10                 // Method org/apache/hadoop/hbase/KeyValue$Type.getCode:()B
     135: if_icmpne     152
     138: aload_0
     139: getfield      #22                 // Field deleteTimestamp:J
     142: lload_2
     143: lcmp
     144: ifeq          152
     147: aload_0
     148: aconst_null
     149: putfield      #6                  // Field visiblityTagsDeleteColumnVersion:Ljava/util/List;
     152: aload_0
     153: aload_1
     154: putfield      #18                 // Field deleteCell:Lorg/apache/hadoop/hbase/Cell;
     157: aload_0
     158: iload         4
     160: putfield      #23                 // Field deleteType:B
     163: aload_0
     164: lload_2
     165: putfield      #22                 // Field deleteTimestamp:J
     168: aload_0
     169: aload_1
     170: iload         4
     172: invokestatic  #24                 // Method org/apache/hadoop/hbase/KeyValue$Type.codeToType:(B)Lorg/apache/hadoop/hbase/KeyValue$Type;
     175: invokespecial #12                 // Method extractDeleteCellVisTags:(Lorg/apache/hadoop/hbase/Cell;Lorg/apache/hadoop/hbase/KeyValue$Type;)Z
     178: pop
     179: return

  public org.apache.hadoop.hbase.regionserver.querymatcher.DeleteTracker$DeleteResult isDeleted(org.apache.hadoop.hbase.Cell);
    Code:
       0: aload_1
       1: invokeinterface #7,  1            // InterfaceMethod org/apache/hadoop/hbase/Cell.getTimestamp:()J
       6: lstore_2
       7: aload_0
       8: getfield      #11                 // Field hasFamilyStamp:Z
      11: ifeq          190
      14: aload_0
      15: getfield      #4                  // Field visibilityTagsDeleteFamily:Ljava/util/List;
      18: ifnull        170
      21: aload_0
      22: getfield      #4                  // Field visibilityTagsDeleteFamily:Ljava/util/List;
      25: invokeinterface #28,  1           // InterfaceMethod java/util/List.isEmpty:()Z
      30: ifne          150
      33: iconst_0
      34: istore        4
      36: iload         4
      38: aload_0
      39: getfield      #4                  // Field visibilityTagsDeleteFamily:Ljava/util/List;
      42: invokeinterface #38,  1           // InterfaceMethod java/util/List.size:()I
      47: if_icmpge     147
      50: aload_0
      51: getfield      #4                  // Field visibilityTagsDeleteFamily:Ljava/util/List;
      54: iload         4
      56: invokeinterface #39,  2           // InterfaceMethod java/util/List.get:(I)Ljava/lang/Object;
      61: checkcast     #29                 // class org/apache/hadoop/hbase/util/Triple
      64: astore        5
      66: lload_2
      67: aload         5
      69: invokevirtual #40                 // Method org/apache/hadoop/hbase/util/Triple.getThird:()Ljava/lang/Object;
      72: checkcast     #41                 // class java/lang/Long
      75: invokevirtual #42                 // Method java/lang/Long.longValue:()J
      78: lcmp
      79: ifgt          141
      82: new           #2                  // class java/util/ArrayList
      85: dup
      86: invokespecial #3                  // Method java/util/ArrayList."<init>":()V
      89: astore        6
      91: aload_1
      92: aload         6
      94: invokestatic  #27                 // Method org/apache/hadoop/hbase/security/visibility/VisibilityUtils.extractVisibilityTags:(Lorg/apache/hadoop/hbase/Cell;Ljava/util/List;)Ljava/lang/Byte;
      97: astore        7
      99: invokestatic  #43                 // Method org/apache/hadoop/hbase/security/visibility/VisibilityLabelServiceManager.getInstance:()Lorg/apache/hadoop/hbase/security/visibility/VisibilityLabelServiceManager;
     102: invokevirtual #44                 // Method org/apache/hadoop/hbase/security/visibility/VisibilityLabelServiceManager.getVisibilityLabelService:()Lorg/apache/hadoop/hbase/security/visibility/VisibilityLabelService;
     105: aload         6
     107: aload         7
     109: aload         5
     111: invokevirtual #45                 // Method org/apache/hadoop/hbase/util/Triple.getFirst:()Ljava/lang/Object;
     114: checkcast     #46                 // class java/util/List
     117: aload         5
     119: invokevirtual #47                 // Method org/apache/hadoop/hbase/util/Triple.getSecond:()Ljava/lang/Object;
     122: checkcast     #48                 // class java/lang/Byte
     125: invokeinterface #49,  5           // InterfaceMethod org/apache/hadoop/hbase/security/visibility/VisibilityLabelService.matchVisibility:(Ljava/util/List;Ljava/lang/Byte;Ljava/util/List;Ljava/lang/Byte;)Z
     130: istore        8
     132: iload         8
     134: ifeq          141
     137: getstatic     #50                 // Field org/apache/hadoop/hbase/regionserver/querymatcher/DeleteTracker$DeleteResult.FAMILY_VERSION_DELETED:Lorg/apache/hadoop/hbase/regionserver/querymatcher/DeleteTracker$DeleteResult;
     140: areturn
     141: iinc          4, 1
     144: goto          36
     147: goto          190
     150: aload_1
     151: invokestatic  #51                 // Method org/apache/hadoop/hbase/security/visibility/VisibilityUtils.isVisibilityTagsPresent:(Lorg/apache/hadoop/hbase/Cell;)Z
     154: ifne          190
     157: lload_2
     158: aload_0
     159: getfield      #13                 // Field familyStamp:J
     162: lcmp
     163: ifgt          190
     166: getstatic     #50                 // Field org/apache/hadoop/hbase/regionserver/querymatcher/DeleteTracker$DeleteResult.FAMILY_VERSION_DELETED:Lorg/apache/hadoop/hbase/regionserver/querymatcher/DeleteTracker$DeleteResult;
     169: areturn
     170: aload_1
     171: invokestatic  #51                 // Method org/apache/hadoop/hbase/security/visibility/VisibilityUtils.isVisibilityTagsPresent:(Lorg/apache/hadoop/hbase/Cell;)Z
     174: ifne          190
     177: lload_2
     178: aload_0
     179: getfield      #13                 // Field familyStamp:J
     182: lcmp
     183: ifgt          190
     186: getstatic     #50                 // Field org/apache/hadoop/hbase/regionserver/querymatcher/DeleteTracker$DeleteResult.FAMILY_VERSION_DELETED:Lorg/apache/hadoop/hbase/regionserver/querymatcher/DeleteTracker$DeleteResult;
     189: areturn
     190: aload_0
     191: getfield      #15                 // Field familyVersionStamps:Ljava/util/SortedSet;
     194: lload_2
     195: invokestatic  #16                 // Method java/lang/Long.valueOf:(J)Ljava/lang/Long;
     198: invokeinterface #52,  2           // InterfaceMethod java/util/SortedSet.contains:(Ljava/lang/Object;)Z
     203: ifeq          364
     206: aload_0
     207: getfield      #5                  // Field visibilityTagsDeleteFamilyVersion:Ljava/util/List;
     210: ifnull        353
     213: aload_0
     214: getfield      #5                  // Field visibilityTagsDeleteFamilyVersion:Ljava/util/List;
     217: invokeinterface #28,  1           // InterfaceMethod java/util/List.isEmpty:()Z
     222: ifne          342
     225: iconst_0
     226: istore        4
     228: iload         4
     230: aload_0
     231: getfield      #5                  // Field visibilityTagsDeleteFamilyVersion:Ljava/util/List;
     234: invokeinterface #38,  1           // InterfaceMethod java/util/List.size:()I
     239: if_icmpge     339
     242: aload_0
     243: getfield      #5                  // Field visibilityTagsDeleteFamilyVersion:Ljava/util/List;
     246: iload         4
     248: invokeinterface #39,  2           // InterfaceMethod java/util/List.get:(I)Ljava/lang/Object;
     253: checkcast     #29                 // class org/apache/hadoop/hbase/util/Triple
     256: astore        5
     258: lload_2
     259: aload         5
     261: invokevirtual #40                 // Method org/apache/hadoop/hbase/util/Triple.getThird:()Ljava/lang/Object;
     264: checkcast     #41                 // class java/lang/Long
     267: invokevirtual #42                 // Method java/lang/Long.longValue:()J
     270: lcmp
     271: ifne          333
     274: new           #2                  // class java/util/ArrayList
     277: dup
     278: invokespecial #3                  // Method java/util/ArrayList."<init>":()V
     281: astore        6
     283: aload_1
     284: aload         6
     286: invokestatic  #27                 // Method org/apache/hadoop/hbase/security/visibility/VisibilityUtils.extractVisibilityTags:(Lorg/apache/hadoop/hbase/Cell;Ljava/util/List;)Ljava/lang/Byte;
     289: astore        7
     291: invokestatic  #43                 // Method org/apache/hadoop/hbase/security/visibility/VisibilityLabelServiceManager.getInstance:()Lorg/apache/hadoop/hbase/security/visibility/VisibilityLabelServiceManager;
     294: invokevirtual #44                 // Method org/apache/hadoop/hbase/security/visibility/VisibilityLabelServiceManager.getVisibilityLabelService:()Lorg/apache/hadoop/hbase/security/visibility/VisibilityLabelService;
     297: aload         6
     299: aload         7
     301: aload         5
     303: invokevirtual #45                 // Method org/apache/hadoop/hbase/util/Triple.getFirst:()Ljava/lang/Object;
     306: checkcast     #46                 // class java/util/List
     309: aload         5
     311: invokevirtual #47                 // Method org/apache/hadoop/hbase/util/Triple.getSecond:()Ljava/lang/Object;
     314: checkcast     #48                 // class java/lang/Byte
     317: invokeinterface #49,  5           // InterfaceMethod org/apache/hadoop/hbase/security/visibility/VisibilityLabelService.matchVisibility:(Ljava/util/List;Ljava/lang/Byte;Ljava/util/List;Ljava/lang/Byte;)Z
     322: istore        8
     324: iload         8
     326: ifeq          333
     329: getstatic     #50                 // Field org/apache/hadoop/hbase/regionserver/querymatcher/DeleteTracker$DeleteResult.FAMILY_VERSION_DELETED:Lorg/apache/hadoop/hbase/regionserver/querymatcher/DeleteTracker$DeleteResult;
     332: areturn
     333: iinc          4, 1
     336: goto          228
     339: goto          364
     342: aload_1
     343: invokestatic  #51                 // Method org/apache/hadoop/hbase/security/visibility/VisibilityUtils.isVisibilityTagsPresent:(Lorg/apache/hadoop/hbase/Cell;)Z
     346: ifne          364
     349: getstatic     #50                 // Field org/apache/hadoop/hbase/regionserver/querymatcher/DeleteTracker$DeleteResult.FAMILY_VERSION_DELETED:Lorg/apache/hadoop/hbase/regionserver/querymatcher/DeleteTracker$DeleteResult;
     352: areturn
     353: aload_1
     354: invokestatic  #51                 // Method org/apache/hadoop/hbase/security/visibility/VisibilityUtils.isVisibilityTagsPresent:(Lorg/apache/hadoop/hbase/Cell;)Z
     357: ifne          364
     360: getstatic     #50                 // Field org/apache/hadoop/hbase/regionserver/querymatcher/DeleteTracker$DeleteResult.FAMILY_VERSION_DELETED:Lorg/apache/hadoop/hbase/regionserver/querymatcher/DeleteTracker$DeleteResult;
     363: areturn
     364: aload_0
     365: getfield      #18                 // Field deleteCell:Lorg/apache/hadoop/hbase/Cell;
     368: ifnull        819
     371: aload_0
     372: getfield      #53                 // Field comparator:Lorg/apache/hadoop/hbase/CellComparator;
     375: aload_1
     376: aload_0
     377: getfield      #18                 // Field deleteCell:Lorg/apache/hadoop/hbase/Cell;
     380: invokeinterface #54,  3           // InterfaceMethod org/apache/hadoop/hbase/CellComparator.compareQualifiers:(Lorg/apache/hadoop/hbase/Cell;Lorg/apache/hadoop/hbase/Cell;)I
     385: istore        4
     387: iload         4
     389: ifne          692
     392: aload_0
     393: getfield      #23                 // Field deleteType:B
     396: getstatic     #55                 // Field org/apache/hadoop/hbase/KeyValue$Type.DeleteColumn:Lorg/apache/hadoop/hbase/KeyValue$Type;
     399: invokevirtual #10                 // Method org/apache/hadoop/hbase/KeyValue$Type.getCode:()B
     402: if_icmpne     544
     405: aload_0
     406: getfield      #20                 // Field visibilityTagsDeleteColumns:Ljava/util/List;
     409: ifnull        533
     412: aload_0
     413: getfield      #20                 // Field visibilityTagsDeleteColumns:Ljava/util/List;
     416: invokeinterface #28,  1           // InterfaceMethod java/util/List.isEmpty:()Z
     421: ifne          522
     424: aload_0
     425: getfield      #20                 // Field visibilityTagsDeleteColumns:Ljava/util/List;
     428: invokeinterface #56,  1           // InterfaceMethod java/util/List.iterator:()Ljava/util/Iterator;
     433: astore        5
     435: aload         5
     437: invokeinterface #57,  1           // InterfaceMethod java/util/Iterator.hasNext:()Z
     442: ifeq          519
     445: aload         5
     447: invokeinterface #58,  1           // InterfaceMethod java/util/Iterator.next:()Ljava/lang/Object;
     452: checkcast     #33                 // class org/apache/hadoop/hbase/util/Pair
     455: astore        6
     457: new           #2                  // class java/util/ArrayList
     460: dup
     461: invokespecial #3                  // Method java/util/ArrayList."<init>":()V
     464: astore        7
     466: aload_1
     467: aload         7
     469: invokestatic  #27                 // Method org/apache/hadoop/hbase/security/visibility/VisibilityUtils.extractVisibilityTags:(Lorg/apache/hadoop/hbase/Cell;Ljava/util/List;)Ljava/lang/Byte;
     472: astore        8
     474: invokestatic  #43                 // Method org/apache/hadoop/hbase/security/visibility/VisibilityLabelServiceManager.getInstance:()Lorg/apache/hadoop/hbase/security/visibility/VisibilityLabelServiceManager;
     477: invokevirtual #44                 // Method org/apache/hadoop/hbase/security/visibility/VisibilityLabelServiceManager.getVisibilityLabelService:()Lorg/apache/hadoop/hbase/security/visibility/VisibilityLabelService;
     480: aload         7
     482: aload         8
     484: aload         6
     486: invokevirtual #59                 // Method org/apache/hadoop/hbase/util/Pair.getFirst:()Ljava/lang/Object;
     489: checkcast     #46                 // class java/util/List
     492: aload         6
     494: invokevirtual #60                 // Method org/apache/hadoop/hbase/util/Pair.getSecond:()Ljava/lang/Object;
     497: checkcast     #48                 // class java/lang/Byte
     500: invokeinterface #49,  5           // InterfaceMethod org/apache/hadoop/hbase/security/visibility/VisibilityLabelService.matchVisibility:(Ljava/util/List;Ljava/lang/Byte;Ljava/util/List;Ljava/lang/Byte;)Z
     505: istore        9
     507: iload         9
     509: ifeq          516
     512: getstatic     #61                 // Field org/apache/hadoop/hbase/regionserver/querymatcher/DeleteTracker$DeleteResult.VERSION_DELETED:Lorg/apache/hadoop/hbase/regionserver/querymatcher/DeleteTracker$DeleteResult;
     515: areturn
     516: goto          435
     519: goto          544
     522: aload_1
     523: invokestatic  #51                 // Method org/apache/hadoop/hbase/security/visibility/VisibilityUtils.isVisibilityTagsPresent:(Lorg/apache/hadoop/hbase/Cell;)Z
     526: ifne          544
     529: getstatic     #61                 // Field org/apache/hadoop/hbase/regionserver/querymatcher/DeleteTracker$DeleteResult.VERSION_DELETED:Lorg/apache/hadoop/hbase/regionserver/querymatcher/DeleteTracker$DeleteResult;
     532: areturn
     533: aload_1
     534: invokestatic  #51                 // Method org/apache/hadoop/hbase/security/visibility/VisibilityUtils.isVisibilityTagsPresent:(Lorg/apache/hadoop/hbase/Cell;)Z
     537: ifne          544
     540: getstatic     #61                 // Field org/apache/hadoop/hbase/regionserver/querymatcher/DeleteTracker$DeleteResult.VERSION_DELETED:Lorg/apache/hadoop/hbase/regionserver/querymatcher/DeleteTracker$DeleteResult;
     543: areturn
     544: lload_2
     545: aload_0
     546: getfield      #22                 // Field deleteTimestamp:J
     549: lcmp
     550: ifne          819
     553: aload_0
     554: getfield      #6                  // Field visiblityTagsDeleteColumnVersion:Ljava/util/List;
     557: ifnull        681
     560: aload_0
     561: getfield      #6                  // Field visiblityTagsDeleteColumnVersion:Ljava/util/List;
     564: invokeinterface #28,  1           // InterfaceMethod java/util/List.isEmpty:()Z
     569: ifne          670
     572: aload_0
     573: getfield      #6                  // Field visiblityTagsDeleteColumnVersion:Ljava/util/List;
     576: invokeinterface #56,  1           // InterfaceMethod java/util/List.iterator:()Ljava/util/Iterator;
     581: astore        5
     583: aload         5
     585: invokeinterface #57,  1           // InterfaceMethod java/util/Iterator.hasNext:()Z
     590: ifeq          667
     593: aload         5
     595: invokeinterface #58,  1           // InterfaceMethod java/util/Iterator.next:()Ljava/lang/Object;
     600: checkcast     #33                 // class org/apache/hadoop/hbase/util/Pair
     603: astore        6
     605: new           #2                  // class java/util/ArrayList
     608: dup
     609: invokespecial #3                  // Method java/util/ArrayList."<init>":()V
     612: astore        7
     614: aload_1
     615: aload         7
     617: invokestatic  #27                 // Method org/apache/hadoop/hbase/security/visibility/VisibilityUtils.extractVisibilityTags:(Lorg/apache/hadoop/hbase/Cell;Ljava/util/List;)Ljava/lang/Byte;
     620: astore        8
     622: invokestatic  #43                 // Method org/apache/hadoop/hbase/security/visibility/VisibilityLabelServiceManager.getInstance:()Lorg/apache/hadoop/hbase/security/visibility/VisibilityLabelServiceManager;
     625: invokevirtual #44                 // Method org/apache/hadoop/hbase/security/visibility/VisibilityLabelServiceManager.getVisibilityLabelService:()Lorg/apache/hadoop/hbase/security/visibility/VisibilityLabelService;
     628: aload         7
     630: aload         8
     632: aload         6
     634: invokevirtual #59                 // Method org/apache/hadoop/hbase/util/Pair.getFirst:()Ljava/lang/Object;
     637: checkcast     #46                 // class java/util/List
     640: aload         6
     642: invokevirtual #60                 // Method org/apache/hadoop/hbase/util/Pair.getSecond:()Ljava/lang/Object;
     645: checkcast     #48                 // class java/lang/Byte
     648: invokeinterface #49,  5           // InterfaceMethod org/apache/hadoop/hbase/security/visibility/VisibilityLabelService.matchVisibility:(Ljava/util/List;Ljava/lang/Byte;Ljava/util/List;Ljava/lang/Byte;)Z
     653: istore        9
     655: iload         9
     657: ifeq          664
     660: getstatic     #61                 // Field org/apache/hadoop/hbase/regionserver/querymatcher/DeleteTracker$DeleteResult.VERSION_DELETED:Lorg/apache/hadoop/hbase/regionserver/querymatcher/DeleteTracker$DeleteResult;
     663: areturn
     664: goto          583
     667: goto          819
     670: aload_1
     671: invokestatic  #51                 // Method org/apache/hadoop/hbase/security/visibility/VisibilityUtils.isVisibilityTagsPresent:(Lorg/apache/hadoop/hbase/Cell;)Z
     674: ifne          819
     677: getstatic     #61                 // Field org/apache/hadoop/hbase/regionserver/querymatcher/DeleteTracker$DeleteResult.VERSION_DELETED:Lorg/apache/hadoop/hbase/regionserver/querymatcher/DeleteTracker$DeleteResult;
     680: areturn
     681: aload_1
     682: invokestatic  #51                 // Method org/apache/hadoop/hbase/security/visibility/VisibilityUtils.isVisibilityTagsPresent:(Lorg/apache/hadoop/hbase/Cell;)Z
     685: ifne          819
     688: getstatic     #61                 // Field org/apache/hadoop/hbase/regionserver/querymatcher/DeleteTracker$DeleteResult.VERSION_DELETED:Lorg/apache/hadoop/hbase/regionserver/querymatcher/DeleteTracker$DeleteResult;
     691: areturn
     692: iload         4
     694: ifle          715
     697: aload_0
     698: aconst_null
     699: putfield      #18                 // Field deleteCell:Lorg/apache/hadoop/hbase/Cell;
     702: aload_0
     703: aconst_null
     704: putfield      #20                 // Field visibilityTagsDeleteColumns:Ljava/util/List;
     707: aload_0
     708: aconst_null
     709: putfield      #6                  // Field visiblityTagsDeleteColumnVersion:Ljava/util/List;
     712: goto          819
     715: new           #62                 // class java/lang/IllegalStateException
     718: dup
     719: new           #63                 // class java/lang/StringBuilder
     722: dup
     723: invokespecial #64                 // Method java/lang/StringBuilder."<init>":()V
     726: ldc           #65                 // String isDeleted failed: deleteBuffer=
     728: invokevirtual #66                 // Method java/lang/StringBuilder.append:(Ljava/lang/String;)Ljava/lang/StringBuilder;
     731: aload_0
     732: getfield      #18                 // Field deleteCell:Lorg/apache/hadoop/hbase/Cell;
     735: invokeinterface #67,  1           // InterfaceMethod org/apache/hadoop/hbase/Cell.getQualifierArray:()[B
     740: aload_0
     741: getfield      #18                 // Field deleteCell:Lorg/apache/hadoop/hbase/Cell;
     744: invokeinterface #68,  1           // InterfaceMethod org/apache/hadoop/hbase/Cell.getQualifierOffset:()I
     749: aload_0
     750: getfield      #18                 // Field deleteCell:Lorg/apache/hadoop/hbase/Cell;
     753: invokeinterface #69,  1           // InterfaceMethod org/apache/hadoop/hbase/Cell.getQualifierLength:()I
     758: invokestatic  #70                 // Method org/apache/hadoop/hbase/util/Bytes.toStringBinary:([BII)Ljava/lang/String;
     761: invokevirtual #66                 // Method java/lang/StringBuilder.append:(Ljava/lang/String;)Ljava/lang/StringBuilder;
     764: ldc           #71                 // String , qualifier=
     766: invokevirtual #66                 // Method java/lang/StringBuilder.append:(Ljava/lang/String;)Ljava/lang/StringBuilder;
     769: aload_1
     770: invokeinterface #67,  1           // InterfaceMethod org/apache/hadoop/hbase/Cell.getQualifierArray:()[B
     775: aload_1
     776: invokeinterface #68,  1           // InterfaceMethod org/apache/hadoop/hbase/Cell.getQualifierOffset:()I
     781: aload_1
     782: invokeinterface #69,  1           // InterfaceMethod org/apache/hadoop/hbase/Cell.getQualifierLength:()I
     787: invokestatic  #70                 // Method org/apache/hadoop/hbase/util/Bytes.toStringBinary:([BII)Ljava/lang/String;
     790: invokevirtual #66                 // Method java/lang/StringBuilder.append:(Ljava/lang/String;)Ljava/lang/StringBuilder;
     793: ldc           #72                 // String , timestamp=
     795: invokevirtual #66                 // Method java/lang/StringBuilder.append:(Ljava/lang/String;)Ljava/lang/StringBuilder;
     798: lload_2
     799: invokevirtual #73                 // Method java/lang/StringBuilder.append:(J)Ljava/lang/StringBuilder;
     802: ldc           #74                 // String , comparison result:
     804: invokevirtual #66                 // Method java/lang/StringBuilder.append:(Ljava/lang/String;)Ljava/lang/StringBuilder;
     807: iload         4
     809: invokevirtual #75                 // Method java/lang/StringBuilder.append:(I)Ljava/lang/StringBuilder;
     812: invokevirtual #76                 // Method java/lang/StringBuilder.toString:()Ljava/lang/String;
     815: invokespecial #77                 // Method java/lang/IllegalStateException."<init>":(Ljava/lang/String;)V
     818: athrow
     819: goto          836
     822: astore        4
     824: getstatic     #79                 // Field LOG:Lorg/slf4j/Logger;
     827: ldc           #80                 // String Error in isDeleted() check! Will treat cell as not deleted
     829: aload         4
     831: invokeinterface #81,  3           // InterfaceMethod org/slf4j/Logger.error:(Ljava/lang/String;Ljava/lang/Throwable;)V
     836: getstatic     #82                 // Field org/apache/hadoop/hbase/regionserver/querymatcher/DeleteTracker$DeleteResult.NOT_DELETED:Lorg/apache/hadoop/hbase/regionserver/querymatcher/DeleteTracker$DeleteResult;
     839: areturn
    Exception table:
       from    to  target type
           7   140   822   Class java/io/IOException
         141   169   822   Class java/io/IOException
         170   189   822   Class java/io/IOException
         190   332   822   Class java/io/IOException
         333   352   822   Class java/io/IOException
         353   363   822   Class java/io/IOException
         364   515   822   Class java/io/IOException
         516   532   822   Class java/io/IOException
         533   543   822   Class java/io/IOException
         544   663   822   Class java/io/IOException
         664   680   822   Class java/io/IOException
         681   691   822   Class java/io/IOException
         692   819   822   Class java/io/IOException

  public void reset();
    Code:
       0: aload_0
       1: invokespecial #83                 // Method org/apache/hadoop/hbase/regionserver/querymatcher/ScanDeleteTracker.reset:()V
       4: aload_0
       5: aconst_null
       6: putfield      #20                 // Field visibilityTagsDeleteColumns:Ljava/util/List;
       9: aload_0
      10: aconst_null
      11: putfield      #4                  // Field visibilityTagsDeleteFamily:Ljava/util/List;
      14: aload_0
      15: aconst_null
      16: putfield      #5                  // Field visibilityTagsDeleteFamilyVersion:Ljava/util/List;
      19: aload_0
      20: aconst_null
      21: putfield      #6                  // Field visiblityTagsDeleteColumnVersion:Ljava/util/List;
      24: return

  static {};
    Code:
       0: ldc           #84                 // class org/apache/hadoop/hbase/security/visibility/VisibilityScanDeleteTracker
       2: invokestatic  #85                 // Method org/slf4j/LoggerFactory.getLogger:(Ljava/lang/Class;)Lorg/slf4j/Logger;
       5: putstatic     #79                 // Field LOG:Lorg/slf4j/Logger;
       8: getstatic     #86                 // Field java/util/Collections.EMPTY_LIST:Ljava/util/List;
      11: putstatic     #32                 // Field EMPTY_TAG:Ljava/util/List;
      14: return
}
