Compiled from "VisibilityUtils.java"
public class org.apache.hadoop.hbase.security.visibility.VisibilityUtils {
  public static final java.lang.String VISIBILITY_LABEL_GENERATOR_CLASS;

  public static final java.lang.String SYSTEM_LABEL;

  public static final org.apache.hadoop.hbase.Tag SORTED_ORDINAL_SERIALIZATION_FORMAT_TAG;

  public org.apache.hadoop.hbase.security.visibility.VisibilityUtils();
    Code:
       0: aload_0
       1: invokespecial #2                  // Method java/lang/Object."<init>":()V
       4: return

  public static byte[] getDataToWriteToZooKeeper(java.util.Map<java.lang.String, java.lang.Integer>);
    Code:
       0: invokestatic  #3                  // Method org/apache/hadoop/hbase/protobuf/generated/VisibilityLabelsProtos$VisibilityLabelsRequest.newBuilder:()Lorg/apache/hadoop/hbase/protobuf/generated/VisibilityLabelsProtos$VisibilityLabelsRequest$Builder;
       3: astore_1
       4: aload_0
       5: invokeinterface #4,  1            // InterfaceMethod java/util/Map.entrySet:()Ljava/util/Set;
      10: invokeinterface #5,  1            // InterfaceMethod java/util/Set.iterator:()Ljava/util/Iterator;
      15: astore_2
      16: aload_2
      17: invokeinterface #6,  1            // InterfaceMethod java/util/Iterator.hasNext:()Z
      22: ifeq          92
      25: aload_2
      26: invokeinterface #7,  1            // InterfaceMethod java/util/Iterator.next:()Ljava/lang/Object;
      31: checkcast     #8                  // class java/util/Map$Entry
      34: astore_3
      35: invokestatic  #9                  // Method org/apache/hadoop/hbase/protobuf/generated/VisibilityLabelsProtos$VisibilityLabel.newBuilder:()Lorg/apache/hadoop/hbase/protobuf/generated/VisibilityLabelsProtos$VisibilityLabel$Builder;
      38: astore        4
      40: aload         4
      42: aload_3
      43: invokeinterface #10,  1           // InterfaceMethod java/util/Map$Entry.getKey:()Ljava/lang/Object;
      48: checkcast     #11                 // class java/lang/String
      51: invokestatic  #12                 // Method org/apache/hadoop/hbase/util/Bytes.toBytes:(Ljava/lang/String;)[B
      54: invokestatic  #13                 // Method com/google/protobuf/ByteString.copyFrom:([B)Lcom/google/protobuf/ByteString;
      57: invokevirtual #14                 // Method org/apache/hadoop/hbase/protobuf/generated/VisibilityLabelsProtos$VisibilityLabel$Builder.setLabel:(Lcom/google/protobuf/ByteString;)Lorg/apache/hadoop/hbase/protobuf/generated/VisibilityLabelsProtos$VisibilityLabel$Builder;
      60: pop
      61: aload         4
      63: aload_3
      64: invokeinterface #15,  1           // InterfaceMethod java/util/Map$Entry.getValue:()Ljava/lang/Object;
      69: checkcast     #16                 // class java/lang/Integer
      72: invokevirtual #17                 // Method java/lang/Integer.intValue:()I
      75: invokevirtual #18                 // Method org/apache/hadoop/hbase/protobuf/generated/VisibilityLabelsProtos$VisibilityLabel$Builder.setOrdinal:(I)Lorg/apache/hadoop/hbase/protobuf/generated/VisibilityLabelsProtos$VisibilityLabel$Builder;
      78: pop
      79: aload_1
      80: aload         4
      82: invokevirtual #19                 // Method org/apache/hadoop/hbase/protobuf/generated/VisibilityLabelsProtos$VisibilityLabel$Builder.build:()Lorg/apache/hadoop/hbase/protobuf/generated/VisibilityLabelsProtos$VisibilityLabel;
      85: invokevirtual #20                 // Method org/apache/hadoop/hbase/protobuf/generated/VisibilityLabelsProtos$VisibilityLabelsRequest$Builder.addVisLabel:(Lorg/apache/hadoop/hbase/protobuf/generated/VisibilityLabelsProtos$VisibilityLabel;)Lorg/apache/hadoop/hbase/protobuf/generated/VisibilityLabelsProtos$VisibilityLabelsRequest$Builder;
      88: pop
      89: goto          16
      92: aload_1
      93: invokevirtual #21                 // Method org/apache/hadoop/hbase/protobuf/generated/VisibilityLabelsProtos$VisibilityLabelsRequest$Builder.build:()Lorg/apache/hadoop/hbase/protobuf/generated/VisibilityLabelsProtos$VisibilityLabelsRequest;
      96: invokevirtual #22                 // Method org/apache/hadoop/hbase/protobuf/generated/VisibilityLabelsProtos$VisibilityLabelsRequest.toByteArray:()[B
      99: invokestatic  #23                 // Method org/apache/hadoop/hbase/protobuf/ProtobufUtil.prependPBMagic:([B)[B
     102: areturn

  public static byte[] getUserAuthsDataToWriteToZooKeeper(java.util.Map<java.lang.String, java.util.List<java.lang.Integer>>);
    Code:
       0: invokestatic  #24                 // Method org/apache/hadoop/hbase/protobuf/generated/VisibilityLabelsProtos$MultiUserAuthorizations.newBuilder:()Lorg/apache/hadoop/hbase/protobuf/generated/VisibilityLabelsProtos$MultiUserAuthorizations$Builder;
       3: astore_1
       4: aload_0
       5: invokeinterface #4,  1            // InterfaceMethod java/util/Map.entrySet:()Ljava/util/Set;
      10: invokeinterface #5,  1            // InterfaceMethod java/util/Set.iterator:()Ljava/util/Iterator;
      15: astore_2
      16: aload_2
      17: invokeinterface #6,  1            // InterfaceMethod java/util/Iterator.hasNext:()Z
      22: ifeq          126
      25: aload_2
      26: invokeinterface #7,  1            // InterfaceMethod java/util/Iterator.next:()Ljava/lang/Object;
      31: checkcast     #8                  // class java/util/Map$Entry
      34: astore_3
      35: invokestatic  #25                 // Method org/apache/hadoop/hbase/protobuf/generated/VisibilityLabelsProtos$UserAuthorizations.newBuilder:()Lorg/apache/hadoop/hbase/protobuf/generated/VisibilityLabelsProtos$UserAuthorizations$Builder;
      38: astore        4
      40: aload         4
      42: aload_3
      43: invokeinterface #10,  1           // InterfaceMethod java/util/Map$Entry.getKey:()Ljava/lang/Object;
      48: checkcast     #11                 // class java/lang/String
      51: invokestatic  #12                 // Method org/apache/hadoop/hbase/util/Bytes.toBytes:(Ljava/lang/String;)[B
      54: invokestatic  #13                 // Method com/google/protobuf/ByteString.copyFrom:([B)Lcom/google/protobuf/ByteString;
      57: invokevirtual #26                 // Method org/apache/hadoop/hbase/protobuf/generated/VisibilityLabelsProtos$UserAuthorizations$Builder.setUser:(Lcom/google/protobuf/ByteString;)Lorg/apache/hadoop/hbase/protobuf/generated/VisibilityLabelsProtos$UserAuthorizations$Builder;
      60: pop
      61: aload_3
      62: invokeinterface #15,  1           // InterfaceMethod java/util/Map$Entry.getValue:()Ljava/lang/Object;
      67: checkcast     #27                 // class java/util/List
      70: invokeinterface #28,  1           // InterfaceMethod java/util/List.iterator:()Ljava/util/Iterator;
      75: astore        5
      77: aload         5
      79: invokeinterface #6,  1            // InterfaceMethod java/util/Iterator.hasNext:()Z
      84: ifeq          113
      87: aload         5
      89: invokeinterface #7,  1            // InterfaceMethod java/util/Iterator.next:()Ljava/lang/Object;
      94: checkcast     #16                 // class java/lang/Integer
      97: astore        6
      99: aload         4
     101: aload         6
     103: invokevirtual #17                 // Method java/lang/Integer.intValue:()I
     106: invokevirtual #29                 // Method org/apache/hadoop/hbase/protobuf/generated/VisibilityLabelsProtos$UserAuthorizations$Builder.addAuth:(I)Lorg/apache/hadoop/hbase/protobuf/generated/VisibilityLabelsProtos$UserAuthorizations$Builder;
     109: pop
     110: goto          77
     113: aload_1
     114: aload         4
     116: invokevirtual #30                 // Method org/apache/hadoop/hbase/protobuf/generated/VisibilityLabelsProtos$UserAuthorizations$Builder.build:()Lorg/apache/hadoop/hbase/protobuf/generated/VisibilityLabelsProtos$UserAuthorizations;
     119: invokevirtual #31                 // Method org/apache/hadoop/hbase/protobuf/generated/VisibilityLabelsProtos$MultiUserAuthorizations$Builder.addUserAuths:(Lorg/apache/hadoop/hbase/protobuf/generated/VisibilityLabelsProtos$UserAuthorizations;)Lorg/apache/hadoop/hbase/protobuf/generated/VisibilityLabelsProtos$MultiUserAuthorizations$Builder;
     122: pop
     123: goto          16
     126: aload_1
     127: invokevirtual #32                 // Method org/apache/hadoop/hbase/protobuf/generated/VisibilityLabelsProtos$MultiUserAuthorizations$Builder.build:()Lorg/apache/hadoop/hbase/protobuf/generated/VisibilityLabelsProtos$MultiUserAuthorizations;
     130: invokevirtual #33                 // Method org/apache/hadoop/hbase/protobuf/generated/VisibilityLabelsProtos$MultiUserAuthorizations.toByteArray:()[B
     133: invokestatic  #23                 // Method org/apache/hadoop/hbase/protobuf/ProtobufUtil.prependPBMagic:([B)[B
     136: areturn

  public static java.util.List<org.apache.hadoop.hbase.protobuf.generated.VisibilityLabelsProtos$VisibilityLabel> readLabelsFromZKData(byte[]) throws org.apache.hadoop.hbase.exceptions.DeserializationException;
    Code:
       0: aload_0
       1: invokestatic  #34                 // Method org/apache/hadoop/hbase/protobuf/ProtobufUtil.isPBMagicPrefix:([B)Z
       4: ifeq          40
       7: invokestatic  #35                 // Method org/apache/hadoop/hbase/protobuf/ProtobufUtil.lengthOfPBMagic:()I
      10: istore_1
      11: invokestatic  #3                  // Method org/apache/hadoop/hbase/protobuf/generated/VisibilityLabelsProtos$VisibilityLabelsRequest.newBuilder:()Lorg/apache/hadoop/hbase/protobuf/generated/VisibilityLabelsProtos$VisibilityLabelsRequest$Builder;
      14: astore_2
      15: aload_2
      16: aload_0
      17: iload_1
      18: aload_0
      19: arraylength
      20: iload_1
      21: isub
      22: invokestatic  #36                 // Method org/apache/hadoop/hbase/protobuf/ProtobufUtil.mergeFrom:(Lcom/google/protobuf/Message$Builder;[BII)V
      25: aload_2
      26: invokevirtual #37                 // Method org/apache/hadoop/hbase/protobuf/generated/VisibilityLabelsProtos$VisibilityLabelsRequest$Builder.getVisLabelList:()Ljava/util/List;
      29: areturn
      30: astore_2
      31: new           #39                 // class org/apache/hadoop/hbase/exceptions/DeserializationException
      34: dup
      35: aload_2
      36: invokespecial #40                 // Method org/apache/hadoop/hbase/exceptions/DeserializationException."<init>":(Ljava/lang/Throwable;)V
      39: athrow
      40: aconst_null
      41: areturn
    Exception table:
       from    to  target type
          11    29    30   Class java/io/IOException

  public static org.apache.hadoop.hbase.protobuf.generated.VisibilityLabelsProtos$MultiUserAuthorizations readUserAuthsFromZKData(byte[]) throws org.apache.hadoop.hbase.exceptions.DeserializationException;
    Code:
       0: aload_0
       1: invokestatic  #34                 // Method org/apache/hadoop/hbase/protobuf/ProtobufUtil.isPBMagicPrefix:([B)Z
       4: ifeq          40
       7: invokestatic  #35                 // Method org/apache/hadoop/hbase/protobuf/ProtobufUtil.lengthOfPBMagic:()I
      10: istore_1
      11: invokestatic  #24                 // Method org/apache/hadoop/hbase/protobuf/generated/VisibilityLabelsProtos$MultiUserAuthorizations.newBuilder:()Lorg/apache/hadoop/hbase/protobuf/generated/VisibilityLabelsProtos$MultiUserAuthorizations$Builder;
      14: astore_2
      15: aload_2
      16: aload_0
      17: iload_1
      18: aload_0
      19: arraylength
      20: iload_1
      21: isub
      22: invokestatic  #36                 // Method org/apache/hadoop/hbase/protobuf/ProtobufUtil.mergeFrom:(Lcom/google/protobuf/Message$Builder;[BII)V
      25: aload_2
      26: invokevirtual #32                 // Method org/apache/hadoop/hbase/protobuf/generated/VisibilityLabelsProtos$MultiUserAuthorizations$Builder.build:()Lorg/apache/hadoop/hbase/protobuf/generated/VisibilityLabelsProtos$MultiUserAuthorizations;
      29: areturn
      30: astore_2
      31: new           #39                 // class org/apache/hadoop/hbase/exceptions/DeserializationException
      34: dup
      35: aload_2
      36: invokespecial #40                 // Method org/apache/hadoop/hbase/exceptions/DeserializationException."<init>":(Ljava/lang/Throwable;)V
      39: athrow
      40: aconst_null
      41: areturn
    Exception table:
       from    to  target type
          11    29    30   Class java/io/IOException

  public static java.util.List<org.apache.hadoop.hbase.security.visibility.ScanLabelGenerator> getScanLabelGenerators(org.apache.hadoop.conf.Configuration);
    Code:
       0: aload_0
       1: ldc           #42                 // String hbase.regionserver.scan.visibility.label.generator.class
       3: invokevirtual #43                 // Method org/apache/hadoop/conf/Configuration.get:(Ljava/lang/String;)Ljava/lang/String;
       6: astore_1
       7: new           #44                 // class java/util/ArrayList
      10: dup
      11: invokespecial #45                 // Method java/util/ArrayList."<init>":()V
      14: astore_2
      15: aload_1
      16: invokestatic  #46                 // Method org/apache/commons/lang3/StringUtils.isNotEmpty:(Ljava/lang/CharSequence;)Z
      19: ifeq          119
      22: aload_1
      23: ldc           #47                 // String ,
      25: invokevirtual #48                 // Method java/lang/String.split:(Ljava/lang/String;)[Ljava/lang/String;
      28: astore_3
      29: aload_3
      30: astore        4
      32: aload         4
      34: arraylength
      35: istore        5
      37: iconst_0
      38: istore        6
      40: iload         6
      42: iload         5
      44: if_icmpge     119
      47: aload         4
      49: iload         6
      51: aaload
      52: astore        7
      54: aload_0
      55: aload         7
      57: invokevirtual #49                 // Method java/lang/String.trim:()Ljava/lang/String;
      60: invokevirtual #50                 // Method org/apache/hadoop/conf/Configuration.getClassByName:(Ljava/lang/String;)Ljava/lang/Class;
      63: astore        8
      65: aload_2
      66: aload         8
      68: aload_0
      69: invokestatic  #51                 // Method org/apache/hadoop/util/ReflectionUtils.newInstance:(Ljava/lang/Class;Lorg/apache/hadoop/conf/Configuration;)Ljava/lang/Object;
      72: invokeinterface #52,  2           // InterfaceMethod java/util/List.add:(Ljava/lang/Object;)Z
      77: pop
      78: goto          113
      81: astore        9
      83: new           #54                 // class java/lang/IllegalArgumentException
      86: dup
      87: new           #55                 // class java/lang/StringBuilder
      90: dup
      91: invokespecial #56                 // Method java/lang/StringBuilder."<init>":()V
      94: ldc           #57                 // String Unable to find
      96: invokevirtual #58                 // Method java/lang/StringBuilder.append:(Ljava/lang/String;)Ljava/lang/StringBuilder;
      99: aload         7
     101: invokevirtual #58                 // Method java/lang/StringBuilder.append:(Ljava/lang/String;)Ljava/lang/StringBuilder;
     104: invokevirtual #59                 // Method java/lang/StringBuilder.toString:()Ljava/lang/String;
     107: aload         9
     109: invokespecial #60                 // Method java/lang/IllegalArgumentException."<init>":(Ljava/lang/String;Ljava/lang/Throwable;)V
     112: athrow
     113: iinc          6, 1
     116: goto          40
     119: aload_2
     120: invokeinterface #61,  1           // InterfaceMethod java/util/List.isEmpty:()Z
     125: ifeq          154
     128: aload_2
     129: ldc           #62                 // class org/apache/hadoop/hbase/security/visibility/FeedUserAuthScanLabelGenerator
     131: aload_0
     132: invokestatic  #51                 // Method org/apache/hadoop/util/ReflectionUtils.newInstance:(Ljava/lang/Class;Lorg/apache/hadoop/conf/Configuration;)Ljava/lang/Object;
     135: invokeinterface #52,  2           // InterfaceMethod java/util/List.add:(Ljava/lang/Object;)Z
     140: pop
     141: aload_2
     142: ldc           #63                 // class org/apache/hadoop/hbase/security/visibility/DefinedSetFilterScanLabelGenerator
     144: aload_0
     145: invokestatic  #51                 // Method org/apache/hadoop/util/ReflectionUtils.newInstance:(Ljava/lang/Class;Lorg/apache/hadoop/conf/Configuration;)Ljava/lang/Object;
     148: invokeinterface #52,  2           // InterfaceMethod java/util/List.add:(Ljava/lang/Object;)Z
     153: pop
     154: aload_2
     155: areturn
    Exception table:
       from    to  target type
          54    78    81   Class java/lang/ClassNotFoundException

  public static java.lang.Byte extractVisibilityTags(org.apache.hadoop.hbase.Cell, java.util.List<org.apache.hadoop.hbase.Tag>);
    Code:
       0: aconst_null
       1: astore_2
       2: aload_0
       3: invokestatic  #64                 // Method org/apache/hadoop/hbase/PrivateCellUtil.tagsIterator:(Lorg/apache/hadoop/hbase/Cell;)Ljava/util/Iterator;
       6: astore_3
       7: aload_3
       8: invokeinterface #6,  1            // InterfaceMethod java/util/Iterator.hasNext:()Z
      13: ifeq          73
      16: aload_3
      17: invokeinterface #7,  1            // InterfaceMethod java/util/Iterator.next:()Ljava/lang/Object;
      22: checkcast     #65                 // class org/apache/hadoop/hbase/Tag
      25: astore        4
      27: aload         4
      29: invokeinterface #66,  1           // InterfaceMethod org/apache/hadoop/hbase/Tag.getType:()B
      34: iconst_4
      35: if_icmpne     50
      38: aload         4
      40: invokestatic  #67                 // InterfaceMethod org/apache/hadoop/hbase/Tag.getValueAsByte:(Lorg/apache/hadoop/hbase/Tag;)B
      43: invokestatic  #68                 // Method java/lang/Byte.valueOf:(B)Ljava/lang/Byte;
      46: astore_2
      47: goto          70
      50: aload         4
      52: invokeinterface #66,  1           // InterfaceMethod org/apache/hadoop/hbase/Tag.getType:()B
      57: iconst_2
      58: if_icmpne     70
      61: aload_1
      62: aload         4
      64: invokeinterface #52,  2           // InterfaceMethod java/util/List.add:(Ljava/lang/Object;)Z
      69: pop
      70: goto          7
      73: aload_2
      74: areturn

  public static java.lang.Byte extractAndPartitionTags(org.apache.hadoop.hbase.Cell, java.util.List<org.apache.hadoop.hbase.Tag>, java.util.List<org.apache.hadoop.hbase.Tag>);
    Code:
       0: aconst_null
       1: astore_3
       2: aload_0
       3: invokestatic  #64                 // Method org/apache/hadoop/hbase/PrivateCellUtil.tagsIterator:(Lorg/apache/hadoop/hbase/Cell;)Ljava/util/Iterator;
       6: astore        4
       8: aload         4
      10: invokeinterface #6,  1            // InterfaceMethod java/util/Iterator.hasNext:()Z
      15: ifeq          88
      18: aload         4
      20: invokeinterface #7,  1            // InterfaceMethod java/util/Iterator.next:()Ljava/lang/Object;
      25: checkcast     #65                 // class org/apache/hadoop/hbase/Tag
      28: astore        5
      30: aload         5
      32: invokeinterface #66,  1           // InterfaceMethod org/apache/hadoop/hbase/Tag.getType:()B
      37: iconst_4
      38: if_icmpne     53
      41: aload         5
      43: invokestatic  #67                 // InterfaceMethod org/apache/hadoop/hbase/Tag.getValueAsByte:(Lorg/apache/hadoop/hbase/Tag;)B
      46: invokestatic  #68                 // Method java/lang/Byte.valueOf:(B)Ljava/lang/Byte;
      49: astore_3
      50: goto          85
      53: aload         5
      55: invokeinterface #66,  1           // InterfaceMethod org/apache/hadoop/hbase/Tag.getType:()B
      60: iconst_2
      61: if_icmpne     76
      64: aload_1
      65: aload         5
      67: invokeinterface #52,  2           // InterfaceMethod java/util/List.add:(Ljava/lang/Object;)Z
      72: pop
      73: goto          85
      76: aload_2
      77: aload         5
      79: invokeinterface #52,  2           // InterfaceMethod java/util/List.add:(Ljava/lang/Object;)Z
      84: pop
      85: goto          8
      88: aload_3
      89: areturn

  public static boolean isVisibilityTagsPresent(org.apache.hadoop.hbase.Cell);
    Code:
       0: aload_0
       1: invokestatic  #64                 // Method org/apache/hadoop/hbase/PrivateCellUtil.tagsIterator:(Lorg/apache/hadoop/hbase/Cell;)Ljava/util/Iterator;
       4: astore_1
       5: aload_1
       6: invokeinterface #6,  1            // InterfaceMethod java/util/Iterator.hasNext:()Z
      11: ifeq          39
      14: aload_1
      15: invokeinterface #7,  1            // InterfaceMethod java/util/Iterator.next:()Ljava/lang/Object;
      20: checkcast     #65                 // class org/apache/hadoop/hbase/Tag
      23: astore_2
      24: aload_2
      25: invokeinterface #66,  1           // InterfaceMethod org/apache/hadoop/hbase/Tag.getType:()B
      30: iconst_2
      31: if_icmpne     36
      34: iconst_1
      35: ireturn
      36: goto          5
      39: iconst_0
      40: ireturn

  public static org.apache.hadoop.hbase.filter.Filter createVisibilityLabelFilter(org.apache.hadoop.hbase.regionserver.Region, org.apache.hadoop.hbase.security.visibility.Authorizations) throws java.io.IOException;
    Code:
       0: new           #69                 // class java/util/HashMap
       3: dup
       4: invokespecial #70                 // Method java/util/HashMap."<init>":()V
       7: astore_2
       8: aload_0
       9: invokeinterface #71,  1           // InterfaceMethod org/apache/hadoop/hbase/regionserver/Region.getTableDescriptor:()Lorg/apache/hadoop/hbase/client/TableDescriptor;
      14: invokeinterface #72,  1           // InterfaceMethod org/apache/hadoop/hbase/client/TableDescriptor.getColumnFamilies:()[Lorg/apache/hadoop/hbase/client/ColumnFamilyDescriptor;
      19: astore_3
      20: aload_3
      21: arraylength
      22: istore        4
      24: iconst_0
      25: istore        5
      27: iload         5
      29: iload         4
      31: if_icmpge     77
      34: aload_3
      35: iload         5
      37: aaload
      38: astore        6
      40: aload_2
      41: new           #73                 // class org/apache/hadoop/hbase/util/SimpleMutableByteRange
      44: dup
      45: aload         6
      47: invokeinterface #74,  1           // InterfaceMethod org/apache/hadoop/hbase/client/ColumnFamilyDescriptor.getName:()[B
      52: invokespecial #75                 // Method org/apache/hadoop/hbase/util/SimpleMutableByteRange."<init>":([B)V
      55: aload         6
      57: invokeinterface #76,  1           // InterfaceMethod org/apache/hadoop/hbase/client/ColumnFamilyDescriptor.getMaxVersions:()I
      62: invokestatic  #77                 // Method java/lang/Integer.valueOf:(I)Ljava/lang/Integer;
      65: invokeinterface #78,  3           // InterfaceMethod java/util/Map.put:(Ljava/lang/Object;Ljava/lang/Object;)Ljava/lang/Object;
      70: pop
      71: iinc          5, 1
      74: goto          27
      77: invokestatic  #79                 // Method org/apache/hadoop/hbase/security/visibility/VisibilityLabelServiceManager.getInstance:()Lorg/apache/hadoop/hbase/security/visibility/VisibilityLabelServiceManager;
      80: invokevirtual #80                 // Method org/apache/hadoop/hbase/security/visibility/VisibilityLabelServiceManager.getVisibilityLabelService:()Lorg/apache/hadoop/hbase/security/visibility/VisibilityLabelService;
      83: astore_3
      84: new           #81                 // class org/apache/hadoop/hbase/security/visibility/VisibilityLabelFilter
      87: dup
      88: aload_3
      89: aload_1
      90: invokeinterface #82,  2           // InterfaceMethod org/apache/hadoop/hbase/security/visibility/VisibilityLabelService.getVisibilityExpEvaluator:(Lorg/apache/hadoop/hbase/security/visibility/Authorizations;)Lorg/apache/hadoop/hbase/security/visibility/VisibilityExpEvaluator;
      95: aload_2
      96: invokespecial #83                 // Method org/apache/hadoop/hbase/security/visibility/VisibilityLabelFilter."<init>":(Lorg/apache/hadoop/hbase/security/visibility/VisibilityExpEvaluator;Ljava/util/Map;)V
      99: astore        4
     101: aload         4
     103: areturn

  public static org.apache.hadoop.hbase.security.User getActiveUser() throws java.io.IOException;
    Code:
       0: invokestatic  #84                 // Method org/apache/hadoop/hbase/ipc/RpcServer.getRequestUser:()Ljava/util/Optional;
       3: astore_0
       4: aload_0
       5: invokevirtual #85                 // Method java/util/Optional.isPresent:()Z
       8: ifeq          22
      11: aload_0
      12: invokevirtual #86                 // Method java/util/Optional.get:()Ljava/lang/Object;
      15: checkcast     #87                 // class org/apache/hadoop/hbase/security/User
      18: astore_1
      19: goto          26
      22: invokestatic  #88                 // Method org/apache/hadoop/hbase/security/User.getCurrent:()Lorg/apache/hadoop/hbase/security/User;
      25: astore_1
      26: getstatic     #89                 // Field LOG:Lorg/slf4j/Logger;
      29: invokeinterface #90,  1           // InterfaceMethod org/slf4j/Logger.isTraceEnabled:()Z
      34: ifeq          67
      37: getstatic     #89                 // Field LOG:Lorg/slf4j/Logger;
      40: new           #55                 // class java/lang/StringBuilder
      43: dup
      44: invokespecial #56                 // Method java/lang/StringBuilder."<init>":()V
      47: ldc           #91                 // String Current active user name is
      49: invokevirtual #58                 // Method java/lang/StringBuilder.append:(Ljava/lang/String;)Ljava/lang/StringBuilder;
      52: aload_1
      53: invokevirtual #92                 // Method org/apache/hadoop/hbase/security/User.getShortName:()Ljava/lang/String;
      56: invokevirtual #58                 // Method java/lang/StringBuilder.append:(Ljava/lang/String;)Ljava/lang/StringBuilder;
      59: invokevirtual #59                 // Method java/lang/StringBuilder.toString:()Ljava/lang/String;
      62: invokeinterface #93,  2           // InterfaceMethod org/slf4j/Logger.trace:(Ljava/lang/String;)V
      67: aload_1
      68: areturn

  public static java.util.List<org.apache.hadoop.hbase.Tag> createVisibilityExpTags(java.lang.String, boolean, boolean, java.util.Set<java.lang.Integer>, org.apache.hadoop.hbase.security.visibility.VisibilityLabelOrdinalProvider) throws java.io.IOException;
    Code:
       0: aconst_null
       1: astore        5
       3: getstatic     #94                 // Field EXP_PARSER:Lorg/apache/hadoop/hbase/security/visibility/ExpressionParser;
       6: aload_0
       7: invokevirtual #95                 // Method org/apache/hadoop/hbase/security/visibility/ExpressionParser.parse:(Ljava/lang/String;)Lorg/apache/hadoop/hbase/security/visibility/expression/ExpressionNode;
      10: astore        5
      12: goto          27
      15: astore        6
      17: new           #38                 // class java/io/IOException
      20: dup
      21: aload         6
      23: invokespecial #97                 // Method java/io/IOException."<init>":(Ljava/lang/Throwable;)V
      26: athrow
      27: getstatic     #98                 // Field EXP_EXPANDER:Lorg/apache/hadoop/hbase/security/visibility/ExpressionExpander;
      30: aload         5
      32: invokevirtual #99                 // Method org/apache/hadoop/hbase/security/visibility/ExpressionExpander.expand:(Lorg/apache/hadoop/hbase/security/visibility/expression/ExpressionNode;)Lorg/apache/hadoop/hbase/security/visibility/expression/ExpressionNode;
      35: astore        5
      37: new           #44                 // class java/util/ArrayList
      40: dup
      41: invokespecial #45                 // Method java/util/ArrayList."<init>":()V
      44: astore        6
      46: new           #100                // class java/io/ByteArrayOutputStream
      49: dup
      50: invokespecial #101                // Method java/io/ByteArrayOutputStream."<init>":()V
      53: astore        7
      55: new           #102                // class java/io/DataOutputStream
      58: dup
      59: aload         7
      61: invokespecial #103                // Method java/io/DataOutputStream."<init>":(Ljava/io/OutputStream;)V
      64: astore        8
      66: new           #44                 // class java/util/ArrayList
      69: dup
      70: invokespecial #45                 // Method java/util/ArrayList."<init>":()V
      73: astore        9
      75: iload_1
      76: ifeq          90
      79: aload         6
      81: getstatic     #104                // Field SORTED_ORDINAL_SERIALIZATION_FORMAT_TAG:Lorg/apache/hadoop/hbase/Tag;
      84: invokeinterface #52,  2           // InterfaceMethod java/util/List.add:(Ljava/lang/Object;)Z
      89: pop
      90: aload         5
      92: invokeinterface #105,  1          // InterfaceMethod org/apache/hadoop/hbase/security/visibility/expression/ExpressionNode.isSingleNode:()Z
      97: ifeq          147
     100: aload         5
     102: aload         9
     104: aload_3
     105: iload_2
     106: aload         4
     108: invokestatic  #106                // Method getLabelOrdinals:(Lorg/apache/hadoop/hbase/security/visibility/expression/ExpressionNode;Ljava/util/List;Ljava/util/Set;ZLorg/apache/hadoop/hbase/security/visibility/VisibilityLabelOrdinalProvider;)V
     111: aload         9
     113: aload         8
     115: invokestatic  #107                // Method writeLabelOrdinalsToStream:(Ljava/util/List;Ljava/io/DataOutputStream;)V
     118: aload         6
     120: new           #108                // class org/apache/hadoop/hbase/ArrayBackedTag
     123: dup
     124: iconst_2
     125: aload         7
     127: invokevirtual #109                // Method java/io/ByteArrayOutputStream.toByteArray:()[B
     130: invokespecial #110                // Method org/apache/hadoop/hbase/ArrayBackedTag."<init>":(B[B)V
     133: invokeinterface #52,  2           // InterfaceMethod java/util/List.add:(Ljava/lang/Object;)Z
     138: pop
     139: aload         7
     141: invokevirtual #111                // Method java/io/ByteArrayOutputStream.reset:()V
     144: goto          300
     147: aload         5
     149: checkcast     #112                // class org/apache/hadoop/hbase/security/visibility/expression/NonLeafExpressionNode
     152: astore        10
     154: aload         10
     156: invokevirtual #113                // Method org/apache/hadoop/hbase/security/visibility/expression/NonLeafExpressionNode.getOperator:()Lorg/apache/hadoop/hbase/security/visibility/expression/Operator;
     159: getstatic     #114                // Field org/apache/hadoop/hbase/security/visibility/expression/Operator.OR:Lorg/apache/hadoop/hbase/security/visibility/expression/Operator;
     162: if_acmpne     256
     165: aload         10
     167: invokevirtual #115                // Method org/apache/hadoop/hbase/security/visibility/expression/NonLeafExpressionNode.getChildExps:()Ljava/util/List;
     170: invokeinterface #28,  1           // InterfaceMethod java/util/List.iterator:()Ljava/util/Iterator;
     175: astore        11
     177: aload         11
     179: invokeinterface #6,  1            // InterfaceMethod java/util/Iterator.hasNext:()Z
     184: ifeq          253
     187: aload         11
     189: invokeinterface #7,  1            // InterfaceMethod java/util/Iterator.next:()Ljava/lang/Object;
     194: checkcast     #116                // class org/apache/hadoop/hbase/security/visibility/expression/ExpressionNode
     197: astore        12
     199: aload         12
     201: aload         9
     203: aload_3
     204: iload_2
     205: aload         4
     207: invokestatic  #106                // Method getLabelOrdinals:(Lorg/apache/hadoop/hbase/security/visibility/expression/ExpressionNode;Ljava/util/List;Ljava/util/Set;ZLorg/apache/hadoop/hbase/security/visibility/VisibilityLabelOrdinalProvider;)V
     210: aload         9
     212: aload         8
     214: invokestatic  #107                // Method writeLabelOrdinalsToStream:(Ljava/util/List;Ljava/io/DataOutputStream;)V
     217: aload         6
     219: new           #108                // class org/apache/hadoop/hbase/ArrayBackedTag
     222: dup
     223: iconst_2
     224: aload         7
     226: invokevirtual #109                // Method java/io/ByteArrayOutputStream.toByteArray:()[B
     229: invokespecial #110                // Method org/apache/hadoop/hbase/ArrayBackedTag."<init>":(B[B)V
     232: invokeinterface #52,  2           // InterfaceMethod java/util/List.add:(Ljava/lang/Object;)Z
     237: pop
     238: aload         7
     240: invokevirtual #111                // Method java/io/ByteArrayOutputStream.reset:()V
     243: aload         9
     245: invokeinterface #117,  1          // InterfaceMethod java/util/List.clear:()V
     250: goto          177
     253: goto          300
     256: aload         10
     258: aload         9
     260: aload_3
     261: iload_2
     262: aload         4
     264: invokestatic  #106                // Method getLabelOrdinals:(Lorg/apache/hadoop/hbase/security/visibility/expression/ExpressionNode;Ljava/util/List;Ljava/util/Set;ZLorg/apache/hadoop/hbase/security/visibility/VisibilityLabelOrdinalProvider;)V
     267: aload         9
     269: aload         8
     271: invokestatic  #107                // Method writeLabelOrdinalsToStream:(Ljava/util/List;Ljava/io/DataOutputStream;)V
     274: aload         6
     276: new           #108                // class org/apache/hadoop/hbase/ArrayBackedTag
     279: dup
     280: iconst_2
     281: aload         7
     283: invokevirtual #109                // Method java/io/ByteArrayOutputStream.toByteArray:()[B
     286: invokespecial #110                // Method org/apache/hadoop/hbase/ArrayBackedTag."<init>":(B[B)V
     289: invokeinterface #52,  2           // InterfaceMethod java/util/List.add:(Ljava/lang/Object;)Z
     294: pop
     295: aload         7
     297: invokevirtual #111                // Method java/io/ByteArrayOutputStream.reset:()V
     300: aload         6
     302: areturn
    Exception table:
       from    to  target type
           3    12    15   Class org/apache/hadoop/hbase/security/visibility/ParseException

  static {};
    Code:
       0: ldc           #41                 // class org/apache/hadoop/hbase/security/visibility/VisibilityUtils
       2: invokestatic  #135                // Method org/slf4j/LoggerFactory.getLogger:(Ljava/lang/Class;)Lorg/slf4j/Logger;
       5: putstatic     #89                 // Field LOG:Lorg/slf4j/Logger;
       8: new           #108                // class org/apache/hadoop/hbase/ArrayBackedTag
      11: dup
      12: iconst_4
      13: getstatic     #136                // Field org/apache/hadoop/hbase/security/visibility/VisibilityConstants.SORTED_ORDINAL_SERIALIZATION_FORMAT_TAG_VAL:[B
      16: invokespecial #110                // Method org/apache/hadoop/hbase/ArrayBackedTag."<init>":(B[B)V
      19: putstatic     #104                // Field SORTED_ORDINAL_SERIALIZATION_FORMAT_TAG:Lorg/apache/hadoop/hbase/Tag;
      22: new           #137                // class org/apache/hadoop/hbase/security/visibility/ExpressionParser
      25: dup
      26: invokespecial #138                // Method org/apache/hadoop/hbase/security/visibility/ExpressionParser."<init>":()V
      29: putstatic     #94                 // Field EXP_PARSER:Lorg/apache/hadoop/hbase/security/visibility/ExpressionParser;
      32: new           #139                // class org/apache/hadoop/hbase/security/visibility/ExpressionExpander
      35: dup
      36: invokespecial #140                // Method org/apache/hadoop/hbase/security/visibility/ExpressionExpander."<init>":()V
      39: putstatic     #98                 // Field EXP_EXPANDER:Lorg/apache/hadoop/hbase/security/visibility/ExpressionExpander;
      42: return
}
