Compiled from "WALCoprocessorHost.java"
abstract class org.apache.hadoop.hbase.regionserver.wal.WALCoprocessorHost$WALObserverOperation extends org.apache.hadoop.hbase.coprocessor.CoprocessorHost<org.apache.hadoop.hbase.coprocessor.WALCoprocessor, org.apache.hadoop.hbase.coprocessor.WALCoprocessorEnvironment>.ObserverOperationWithoutResult<org.apache.hadoop.hbase.coprocessor.WALObserver> {
  final org.apache.hadoop.hbase.regionserver.wal.WALCoprocessorHost this$0;

  public org.apache.hadoop.hbase.regionserver.wal.WALCoprocessorHost$WALObserverOperation(org.apache.hadoop.hbase.regionserver.wal.WALCoprocessorHost);
    Code:
       0: aload_0
       1: aload_1
       2: putfield      #1                  // Field this$0:Lorg/apache/hadoop/hbase/regionserver/wal/WALCoprocessorHost;
       5: aload_0
       6: aload_1
       7: aload_1
       8: invokestatic  #2                  // Method org/apache/hadoop/hbase/regionserver/wal/WALCoprocessorHost.access$100:(Lorg/apache/hadoop/hbase/regionserver/wal/WALCoprocessorHost;)Lorg/apache/hadoop/hbase/coprocessor/CoprocessorHost$ObserverGetter;
      11: invokespecial #3                  // Method org/apache/hadoop/hbase/coprocessor/CoprocessorHost$ObserverOperationWithoutResult."<init>":(Lorg/apache/hadoop/hbase/coprocessor/CoprocessorHost;Lorg/apache/hadoop/hbase/coprocessor/CoprocessorHost$ObserverGetter;)V
      14: return
}
