Compiled from "WALCoprocessorHost.java"
class org.apache.hadoop.hbase.regionserver.wal.WALCoprocessorHost$2 extends org.apache.hadoop.hbase.regionserver.wal.WALCoprocessorHost$WALObserverOperation {
  final org.apache.hadoop.hbase.client.RegionInfo val$info;

  final org.apache.hadoop.hbase.wal.WALKey val$logKey;

  final org.apache.hadoop.hbase.wal.WALEdit val$logEdit;

  final org.apache.hadoop.hbase.regionserver.wal.WALCoprocessorHost this$0;

  org.apache.hadoop.hbase.regionserver.wal.WALCoprocessorHost$2(org.apache.hadoop.hbase.regionserver.wal.WALCoprocessorHost, org.apache.hadoop.hbase.client.RegionInfo, org.apache.hadoop.hbase.wal.WALKey, org.apache.hadoop.hbase.wal.WALEdit);
    Code:
       0: aload_0
       1: aload_1
       2: putfield      #1                  // Field this$0:Lorg/apache/hadoop/hbase/regionserver/wal/WALCoprocessorHost;
       5: aload_0
       6: aload_2
       7: putfield      #2                  // Field val$info:Lorg/apache/hadoop/hbase/client/RegionInfo;
      10: aload_0
      11: aload_3
      12: putfield      #3                  // Field val$logKey:Lorg/apache/hadoop/hbase/wal/WALKey;
      15: aload_0
      16: aload         4
      18: putfield      #4                  // Field val$logEdit:Lorg/apache/hadoop/hbase/wal/WALEdit;
      21: aload_0
      22: aload_1
      23: invokespecial #5                  // Method org/apache/hadoop/hbase/regionserver/wal/WALCoprocessorHost$WALObserverOperation."<init>":(Lorg/apache/hadoop/hbase/regionserver/wal/WALCoprocessorHost;)V
      26: return

  protected void call(org.apache.hadoop.hbase.coprocessor.WALObserver) throws java.io.IOException;
    Code:
       0: aload_1
       1: aload_0
       2: aload_0
       3: getfield      #2                  // Field val$info:Lorg/apache/hadoop/hbase/client/RegionInfo;
       6: aload_0
       7: getfield      #3                  // Field val$logKey:Lorg/apache/hadoop/hbase/wal/WALKey;
      10: aload_0
      11: getfield      #4                  // Field val$logEdit:Lorg/apache/hadoop/hbase/wal/WALEdit;
      14: invokeinterface #6,  5            // InterfaceMethod org/apache/hadoop/hbase/coprocessor/WALObserver.postWALWrite:(Lorg/apache/hadoop/hbase/coprocessor/ObserverContext;Lorg/apache/hadoop/hbase/client/RegionInfo;Lorg/apache/hadoop/hbase/wal/WALKey;Lorg/apache/hadoop/hbase/wal/WALEdit;)V
      19: return

  protected void call(java.lang.Object) throws java.io.IOException;
    Code:
       0: aload_0
       1: aload_1
       2: checkcast     #7                  // class org/apache/hadoop/hbase/coprocessor/WALObserver
       5: invokevirtual #8                  // Method call:(Lorg/apache/hadoop/hbase/coprocessor/WALObserver;)V
       8: return
}
