Compiled from "WALSplitter.java"
public abstract class org.apache.hadoop.hbase.wal.WALSplitter$SinkWriter {
  long editsWritten;

  long editsSkipped;

  long nanosSpent;

  public org.apache.hadoop.hbase.wal.WALSplitter$SinkWriter();
    Code:
       0: aload_0
       1: invokespecial #1                  // Method java/lang/Object."<init>":()V
       4: aload_0
       5: lconst_0
       6: putfield      #2                  // Field editsWritten:J
       9: aload_0
      10: lconst_0
      11: putfield      #3                  // Field editsSkipped:J
      14: aload_0
      15: lconst_0
      16: putfield      #4                  // Field nanosSpent:J
      19: return

  void incrementEdits(int);
    Code:
       0: aload_0
       1: dup
       2: getfield      #2                  // Field editsWritten:J
       5: iload_1
       6: i2l
       7: ladd
       8: putfield      #2                  // Field editsWritten:J
      11: return

  void incrementSkippedEdits(int);
    Code:
       0: aload_0
       1: dup
       2: getfield      #3                  // Field editsSkipped:J
       5: iload_1
       6: i2l
       7: ladd
       8: putfield      #3                  // Field editsSkipped:J
      11: return

  void incrementNanoTime(long);
    Code:
       0: aload_0
       1: dup
       2: getfield      #4                  // Field nanosSpent:J
       5: lload_1
       6: ladd
       7: putfield      #4                  // Field nanosSpent:J
      10: return
}
