Compiled from "WALSplitUtil.java"
public final class org.apache.hadoop.hbase.wal.WALSplitUtil {
  public static void finishSplitLogFile(java.lang.String, org.apache.hadoop.conf.Configuration) throws java.io.IOException;
    Code:
       0: aload_1
       1: invokestatic  #4                  // Method org/apache/hadoop/hbase/util/FSUtils.getWALRootDir:(Lorg/apache/hadoop/conf/Configuration;)Lorg/apache/hadoop/fs/Path;
       4: astore_2
       5: new           #5                  // class org/apache/hadoop/fs/Path
       8: dup
       9: aload_2
      10: ldc           #7                  // String oldWALs
      12: invokespecial #8                  // Method org/apache/hadoop/fs/Path."<init>":(Lorg/apache/hadoop/fs/Path;Ljava/lang/String;)V
      15: astore_3
      16: aload_2
      17: aload_0
      18: invokestatic  #9                  // Method org/apache/hadoop/hbase/util/FSUtils.isStartingWithPath:(Lorg/apache/hadoop/fs/Path;Ljava/lang/String;)Z
      21: ifeq          37
      24: new           #5                  // class org/apache/hadoop/fs/Path
      27: dup
      28: aload_0
      29: invokespecial #10                 // Method org/apache/hadoop/fs/Path."<init>":(Ljava/lang/String;)V
      32: astore        4
      34: goto          48
      37: new           #5                  // class org/apache/hadoop/fs/Path
      40: dup
      41: aload_2
      42: aload_0
      43: invokespecial #8                  // Method org/apache/hadoop/fs/Path."<init>":(Lorg/apache/hadoop/fs/Path;Ljava/lang/String;)V
      46: astore        4
      48: aload_2
      49: aload_3
      50: aload         4
      52: aload_1
      53: invokestatic  #11                 // Method finishSplitLogFile:(Lorg/apache/hadoop/fs/Path;Lorg/apache/hadoop/fs/Path;Lorg/apache/hadoop/fs/Path;Lorg/apache/hadoop/conf/Configuration;)V
      56: return

  static void finishSplitLogFile(org.apache.hadoop.fs.Path, org.apache.hadoop.fs.Path, org.apache.hadoop.fs.Path, org.apache.hadoop.conf.Configuration) throws java.io.IOException;
    Code:
       0: new           #12                 // class java/util/ArrayList
       3: dup
       4: invokespecial #13                 // Method java/util/ArrayList."<init>":()V
       7: astore        4
       9: new           #12                 // class java/util/ArrayList
      12: dup
      13: invokespecial #13                 // Method java/util/ArrayList."<init>":()V
      16: astore        5
      18: aload_0
      19: aload_3
      20: invokevirtual #14                 // Method org/apache/hadoop/fs/Path.getFileSystem:(Lorg/apache/hadoop/conf/Configuration;)Lorg/apache/hadoop/fs/FileSystem;
      23: astore        6
      25: aload_0
      26: aload_2
      27: invokevirtual #15                 // Method org/apache/hadoop/fs/Path.getName:()Ljava/lang/String;
      30: aload         6
      32: invokestatic  #16                 // Method org/apache/hadoop/hbase/zookeeper/ZKSplitLog.isCorrupted:(Lorg/apache/hadoop/fs/Path;Ljava/lang/String;Lorg/apache/hadoop/fs/FileSystem;)Z
      35: ifeq          50
      38: aload         5
      40: aload_2
      41: invokeinterface #17,  2           // InterfaceMethod java/util/List.add:(Ljava/lang/Object;)Z
      46: pop
      47: goto          59
      50: aload         4
      52: aload_2
      53: invokeinterface #17,  2           // InterfaceMethod java/util/List.add:(Ljava/lang/Object;)Z
      58: pop
      59: aload         5
      61: aload         4
      63: aload_1
      64: aload         6
      66: aload_3
      67: invokestatic  #18                 // Method archiveWALs:(Ljava/util/List;Ljava/util/List;Lorg/apache/hadoop/fs/Path;Lorg/apache/hadoop/fs/FileSystem;Lorg/apache/hadoop/conf/Configuration;)V
      70: aload_0
      71: aload_2
      72: invokevirtual #15                 // Method org/apache/hadoop/fs/Path.getName:()Ljava/lang/String;
      75: invokestatic  #19                 // Method org/apache/hadoop/hbase/zookeeper/ZKSplitLog.getSplitLogDir:(Lorg/apache/hadoop/fs/Path;Ljava/lang/String;)Lorg/apache/hadoop/fs/Path;
      78: astore        7
      80: aload         6
      82: aload         7
      84: iconst_1
      85: invokevirtual #20                 // Method org/apache/hadoop/fs/FileSystem.delete:(Lorg/apache/hadoop/fs/Path;Z)Z
      88: pop
      89: return

  static org.apache.hadoop.fs.Path getRegionSplitEditsPath(org.apache.hadoop.hbase.wal.WAL$Entry, java.lang.String, java.lang.String, org.apache.hadoop.conf.Configuration) throws java.io.IOException;
    Code:
       0: aload_3
       1: invokestatic  #42                 // Method org/apache/hadoop/hbase/util/FSUtils.getWALFileSystem:(Lorg/apache/hadoop/conf/Configuration;)Lorg/apache/hadoop/fs/FileSystem;
       4: astore        4
       6: aload_3
       7: aload_0
       8: invokevirtual #43                 // Method org/apache/hadoop/hbase/wal/WAL$Entry.getKey:()Lorg/apache/hadoop/hbase/wal/WALKeyImpl;
      11: invokevirtual #44                 // Method org/apache/hadoop/hbase/wal/WALKeyImpl.getTableName:()Lorg/apache/hadoop/hbase/TableName;
      14: invokestatic  #45                 // Method org/apache/hadoop/hbase/util/FSUtils.getWALTableDir:(Lorg/apache/hadoop/conf/Configuration;Lorg/apache/hadoop/hbase/TableName;)Lorg/apache/hadoop/fs/Path;
      17: astore        5
      19: aload_0
      20: invokevirtual #43                 // Method org/apache/hadoop/hbase/wal/WAL$Entry.getKey:()Lorg/apache/hadoop/hbase/wal/WALKeyImpl;
      23: invokevirtual #46                 // Method org/apache/hadoop/hbase/wal/WALKeyImpl.getEncodedRegionName:()[B
      26: invokestatic  #47                 // Method org/apache/hadoop/hbase/util/Bytes.toString:([B)Ljava/lang/String;
      29: astore        6
      31: aload         5
      33: aload         6
      35: invokestatic  #48                 // Method org/apache/hadoop/hbase/regionserver/HRegion.getRegionDir:(Lorg/apache/hadoop/fs/Path;Ljava/lang/String;)Lorg/apache/hadoop/fs/Path;
      38: astore        7
      40: aload         7
      42: invokestatic  #49                 // Method getRegionDirRecoveredEditsDir:(Lorg/apache/hadoop/fs/Path;)Lorg/apache/hadoop/fs/Path;
      45: astore        8
      47: aload         4
      49: aload         8
      51: invokevirtual #32                 // Method org/apache/hadoop/fs/FileSystem.exists:(Lorg/apache/hadoop/fs/Path;)Z
      54: ifeq          164
      57: aload         4
      59: aload         8
      61: invokevirtual #50                 // Method org/apache/hadoop/fs/FileSystem.isFile:(Lorg/apache/hadoop/fs/Path;)Z
      64: ifeq          164
      67: new           #5                  // class org/apache/hadoop/fs/Path
      70: dup
      71: aload_2
      72: invokespecial #10                 // Method org/apache/hadoop/fs/Path."<init>":(Ljava/lang/String;)V
      75: astore        9
      77: aload         4
      79: aload         9
      81: invokevirtual #32                 // Method org/apache/hadoop/fs/FileSystem.exists:(Lorg/apache/hadoop/fs/Path;)Z
      84: ifne          95
      87: aload         4
      89: aload         9
      91: invokevirtual #26                 // Method org/apache/hadoop/fs/FileSystem.mkdirs:(Lorg/apache/hadoop/fs/Path;)Z
      94: pop
      95: new           #5                  // class org/apache/hadoop/fs/Path
      98: dup
      99: aload         9
     101: new           #51                 // class java/lang/StringBuilder
     104: dup
     105: invokespecial #52                 // Method java/lang/StringBuilder."<init>":()V
     108: ldc           #53                 // String recovered.edits_
     110: invokevirtual #54                 // Method java/lang/StringBuilder.append:(Ljava/lang/String;)Ljava/lang/StringBuilder;
     113: aload         6
     115: invokevirtual #54                 // Method java/lang/StringBuilder.append:(Ljava/lang/String;)Ljava/lang/StringBuilder;
     118: invokevirtual #55                 // Method java/lang/StringBuilder.toString:()Ljava/lang/String;
     121: invokespecial #8                  // Method org/apache/hadoop/fs/Path."<init>":(Lorg/apache/hadoop/fs/Path;Ljava/lang/String;)V
     124: astore        9
     126: getstatic     #1                  // Field LOG:Lorg/slf4j/Logger;
     129: ldc           #56                 // String Found existing old file: {}. It could be some leftover of an old installation. It should be a folder instead. So moving it to {}
     131: aload         8
     133: aload         9
     135: invokeinterface #35,  4           // InterfaceMethod org/slf4j/Logger.warn:(Ljava/lang/String;Ljava/lang/Object;Ljava/lang/Object;)V
     140: aload         4
     142: aload         8
     144: aload         9
     146: invokevirtual #33                 // Method org/apache/hadoop/fs/FileSystem.rename:(Lorg/apache/hadoop/fs/Path;Lorg/apache/hadoop/fs/Path;)Z
     149: ifne          164
     152: getstatic     #1                  // Field LOG:Lorg/slf4j/Logger;
     155: ldc           #57                 // String Failed to sideline old file {}
     157: aload         8
     159: invokeinterface #25,  3           // InterfaceMethod org/slf4j/Logger.warn:(Ljava/lang/String;Ljava/lang/Object;)V
     164: aload         4
     166: aload         8
     168: invokevirtual #32                 // Method org/apache/hadoop/fs/FileSystem.exists:(Lorg/apache/hadoop/fs/Path;)Z
     171: ifne          196
     174: aload         4
     176: aload         8
     178: invokevirtual #26                 // Method org/apache/hadoop/fs/FileSystem.mkdirs:(Lorg/apache/hadoop/fs/Path;)Z
     181: ifne          196
     184: getstatic     #1                  // Field LOG:Lorg/slf4j/Logger;
     187: ldc           #58                 // String mkdir failed on {}
     189: aload         8
     191: invokeinterface #25,  3           // InterfaceMethod org/slf4j/Logger.warn:(Ljava/lang/String;Ljava/lang/Object;)V
     196: aload_0
     197: invokevirtual #43                 // Method org/apache/hadoop/hbase/wal/WAL$Entry.getKey:()Lorg/apache/hadoop/hbase/wal/WALKeyImpl;
     200: invokevirtual #59                 // Method org/apache/hadoop/hbase/wal/WALKeyImpl.getSequenceId:()J
     203: invokestatic  #60                 // Method formatRecoveredEditsFileName:(J)Ljava/lang/String;
     206: astore        9
     208: new           #51                 // class java/lang/StringBuilder
     211: dup
     212: invokespecial #52                 // Method java/lang/StringBuilder."<init>":()V
     215: aload         9
     217: invokevirtual #54                 // Method java/lang/StringBuilder.append:(Ljava/lang/String;)Ljava/lang/StringBuilder;
     220: ldc           #61                 // String -
     222: invokevirtual #54                 // Method java/lang/StringBuilder.append:(Ljava/lang/String;)Ljava/lang/StringBuilder;
     225: aload_1
     226: invokevirtual #54                 // Method java/lang/StringBuilder.append:(Ljava/lang/String;)Ljava/lang/StringBuilder;
     229: invokevirtual #55                 // Method java/lang/StringBuilder.toString:()Ljava/lang/String;
     232: invokestatic  #62                 // Method getTmpRecoveredEditsFileName:(Ljava/lang/String;)Ljava/lang/String;
     235: astore        9
     237: new           #5                  // class org/apache/hadoop/fs/Path
     240: dup
     241: aload         8
     243: aload         9
     245: invokespecial #8                  // Method org/apache/hadoop/fs/Path."<init>":(Lorg/apache/hadoop/fs/Path;Ljava/lang/String;)V
     248: areturn

  static org.apache.hadoop.fs.Path getCompletedRecoveredEditsFilePath(org.apache.hadoop.fs.Path, long);
    Code:
       0: lload_1
       1: invokestatic  #60                 // Method formatRecoveredEditsFileName:(J)Ljava/lang/String;
       4: astore_3
       5: new           #5                  // class org/apache/hadoop/fs/Path
       8: dup
       9: aload_0
      10: invokevirtual #65                 // Method org/apache/hadoop/fs/Path.getParent:()Lorg/apache/hadoop/fs/Path;
      13: aload_3
      14: invokespecial #8                  // Method org/apache/hadoop/fs/Path."<init>":(Lorg/apache/hadoop/fs/Path;Ljava/lang/String;)V
      17: areturn

  static java.lang.String formatRecoveredEditsFileName(long);
    Code:
       0: ldc           #66                 // String %019d
       2: iconst_1
       3: anewarray     #67                 // class java/lang/Object
       6: dup
       7: iconst_0
       8: lload_0
       9: invokestatic  #68                 // Method java/lang/Long.valueOf:(J)Ljava/lang/Long;
      12: aastore
      13: invokestatic  #69                 // Method java/lang/String.format:(Ljava/lang/String;[Ljava/lang/Object;)Ljava/lang/String;
      16: areturn

  public static org.apache.hadoop.fs.Path getRegionDirRecoveredEditsDir(org.apache.hadoop.fs.Path);
    Code:
       0: new           #5                  // class org/apache/hadoop/fs/Path
       3: dup
       4: aload_0
       5: ldc           #70                 // String recovered.edits
       7: invokespecial #8                  // Method org/apache/hadoop/fs/Path."<init>":(Lorg/apache/hadoop/fs/Path;Ljava/lang/String;)V
      10: areturn

  public static boolean hasRecoveredEdits(org.apache.hadoop.conf.Configuration, org.apache.hadoop.hbase.client.RegionInfo) throws java.io.IOException;
    Code:
       0: aload_1
       1: invokeinterface #71,  1           // InterfaceMethod org/apache/hadoop/hbase/client/RegionInfo.getReplicaId:()I
       6: ifeq          11
       9: iconst_0
      10: ireturn
      11: aload_0
      12: aload_1
      13: invokeinterface #72,  1           // InterfaceMethod org/apache/hadoop/hbase/client/RegionInfo.getTable:()Lorg/apache/hadoop/hbase/TableName;
      18: aload_1
      19: invokeinterface #73,  1           // InterfaceMethod org/apache/hadoop/hbase/client/RegionInfo.getEncodedName:()Ljava/lang/String;
      24: invokestatic  #74                 // Method org/apache/hadoop/hbase/util/FSUtils.getWALRegionDir:(Lorg/apache/hadoop/conf/Configuration;Lorg/apache/hadoop/hbase/TableName;Ljava/lang/String;)Lorg/apache/hadoop/fs/Path;
      27: astore_2
      28: aload_0
      29: invokestatic  #42                 // Method org/apache/hadoop/hbase/util/FSUtils.getWALFileSystem:(Lorg/apache/hadoop/conf/Configuration;)Lorg/apache/hadoop/fs/FileSystem;
      32: aload_2
      33: invokestatic  #75                 // Method getSplitEditFilesSorted:(Lorg/apache/hadoop/fs/FileSystem;Lorg/apache/hadoop/fs/Path;)Ljava/util/NavigableSet;
      36: astore_3
      37: aload_3
      38: ifnull        54
      41: aload_3
      42: invokeinterface #76,  1           // InterfaceMethod java/util/NavigableSet.isEmpty:()Z
      47: ifne          54
      50: iconst_1
      51: goto          55
      54: iconst_0
      55: ireturn

  public static java.util.NavigableSet<org.apache.hadoop.fs.Path> getSplitEditFilesSorted(org.apache.hadoop.fs.FileSystem, org.apache.hadoop.fs.Path) throws java.io.IOException;
    Code:
       0: new           #77                 // class java/util/TreeSet
       3: dup
       4: invokespecial #78                 // Method java/util/TreeSet."<init>":()V
       7: astore_2
       8: aload_1
       9: invokestatic  #49                 // Method getRegionDirRecoveredEditsDir:(Lorg/apache/hadoop/fs/Path;)Lorg/apache/hadoop/fs/Path;
      12: astore_3
      13: aload_0
      14: aload_3
      15: invokevirtual #32                 // Method org/apache/hadoop/fs/FileSystem.exists:(Lorg/apache/hadoop/fs/Path;)Z
      18: ifne          23
      21: aload_2
      22: areturn
      23: aload_0
      24: aload_3
      25: new           #79                 // class org/apache/hadoop/hbase/wal/WALSplitUtil$1
      28: dup
      29: aload_0
      30: invokespecial #80                 // Method org/apache/hadoop/hbase/wal/WALSplitUtil$1."<init>":(Lorg/apache/hadoop/fs/FileSystem;)V
      33: invokestatic  #81                 // Method org/apache/hadoop/hbase/util/FSUtils.listStatus:(Lorg/apache/hadoop/fs/FileSystem;Lorg/apache/hadoop/fs/Path;Lorg/apache/hadoop/fs/PathFilter;)[Lorg/apache/hadoop/fs/FileStatus;
      36: astore        4
      38: aload         4
      40: invokestatic  #82                 // Method org/apache/commons/lang3/ArrayUtils.isNotEmpty:([Ljava/lang/Object;)Z
      43: ifeq          62
      46: aload         4
      48: invokestatic  #83                 // Method java/util/Arrays.asList:([Ljava/lang/Object;)Ljava/util/List;
      51: aload_2
      52: invokedynamic #84,  0             // InvokeDynamic #0:accept:(Ljava/util/NavigableSet;)Ljava/util/function/Consumer;
      57: invokeinterface #85,  2           // InterfaceMethod java/util/List.forEach:(Ljava/util/function/Consumer;)V
      62: aload_2
      63: areturn

  public static org.apache.hadoop.fs.Path moveAsideBadEditsFile(org.apache.hadoop.fs.FileSystem, org.apache.hadoop.fs.Path) throws java.io.IOException;
    Code:
       0: new           #5                  // class org/apache/hadoop/fs/Path
       3: dup
       4: aload_1
       5: invokevirtual #65                 // Method org/apache/hadoop/fs/Path.getParent:()Lorg/apache/hadoop/fs/Path;
       8: new           #51                 // class java/lang/StringBuilder
      11: dup
      12: invokespecial #52                 // Method java/lang/StringBuilder."<init>":()V
      15: aload_1
      16: invokevirtual #15                 // Method org/apache/hadoop/fs/Path.getName:()Ljava/lang/String;
      19: invokevirtual #54                 // Method java/lang/StringBuilder.append:(Ljava/lang/String;)Ljava/lang/StringBuilder;
      22: ldc           #86                 // String .
      24: invokevirtual #54                 // Method java/lang/StringBuilder.append:(Ljava/lang/String;)Ljava/lang/StringBuilder;
      27: invokestatic  #87                 // Method java/lang/System.currentTimeMillis:()J
      30: invokevirtual #88                 // Method java/lang/StringBuilder.append:(J)Ljava/lang/StringBuilder;
      33: invokevirtual #55                 // Method java/lang/StringBuilder.toString:()Ljava/lang/String;
      36: invokespecial #8                  // Method org/apache/hadoop/fs/Path."<init>":(Lorg/apache/hadoop/fs/Path;Ljava/lang/String;)V
      39: astore_2
      40: aload_0
      41: aload_1
      42: aload_2
      43: invokevirtual #33                 // Method org/apache/hadoop/fs/FileSystem.rename:(Lorg/apache/hadoop/fs/Path;Lorg/apache/hadoop/fs/Path;)Z
      46: ifne          61
      49: getstatic     #1                  // Field LOG:Lorg/slf4j/Logger;
      52: ldc           #89                 // String Rename failed from {} to {}
      54: aload_1
      55: aload_2
      56: invokeinterface #35,  4           // InterfaceMethod org/slf4j/Logger.warn:(Ljava/lang/String;Ljava/lang/Object;Ljava/lang/Object;)V
      61: aload_2
      62: areturn

  public static boolean isSequenceIdFile(org.apache.hadoop.fs.Path);
    Code:
       0: aload_0
       1: invokevirtual #15                 // Method org/apache/hadoop/fs/Path.getName:()Ljava/lang/String;
       4: ldc           #90                 // String .seqid
       6: invokevirtual #91                 // Method java/lang/String.endsWith:(Ljava/lang/String;)Z
       9: ifne          24
      12: aload_0
      13: invokevirtual #15                 // Method org/apache/hadoop/fs/Path.getName:()Ljava/lang/String;
      16: ldc           #92                 // String _seqid
      18: invokevirtual #91                 // Method java/lang/String.endsWith:(Ljava/lang/String;)Z
      21: ifeq          28
      24: iconst_1
      25: goto          29
      28: iconst_0
      29: ireturn

  public static long getMaxRegionSequenceId(org.apache.hadoop.fs.FileSystem, org.apache.hadoop.fs.Path) throws java.io.IOException;
    Code:
       0: aload_0
       1: aload_1
       2: invokestatic  #107                // Method getSequenceIdFiles:(Lorg/apache/hadoop/fs/FileSystem;Lorg/apache/hadoop/fs/Path;)[Lorg/apache/hadoop/fs/FileStatus;
       5: invokestatic  #108                // Method getMaxSequenceId:([Lorg/apache/hadoop/fs/FileStatus;)J
       8: lreturn

  public static void writeRegionSequenceIdFile(org.apache.hadoop.fs.FileSystem, org.apache.hadoop.fs.Path, long) throws java.io.IOException;
    Code:
       0: aload_0
       1: aload_1
       2: invokestatic  #107                // Method getSequenceIdFiles:(Lorg/apache/hadoop/fs/FileSystem;Lorg/apache/hadoop/fs/Path;)[Lorg/apache/hadoop/fs/FileStatus;
       5: astore        4
       7: aload         4
       9: invokestatic  #108                // Method getMaxSequenceId:([Lorg/apache/hadoop/fs/FileStatus;)J
      12: lstore        5
      14: lload         5
      16: lload_2
      17: lcmp
      18: ifle          58
      21: new           #109                // class java/io/IOException
      24: dup
      25: new           #51                 // class java/lang/StringBuilder
      28: dup
      29: invokespecial #52                 // Method java/lang/StringBuilder."<init>":()V
      32: ldc           #110                // String The new max sequence id
      34: invokevirtual #54                 // Method java/lang/StringBuilder.append:(Ljava/lang/String;)Ljava/lang/StringBuilder;
      37: lload_2
      38: invokevirtual #88                 // Method java/lang/StringBuilder.append:(J)Ljava/lang/StringBuilder;
      41: ldc           #111                // String  is less than the old max sequence id
      43: invokevirtual #54                 // Method java/lang/StringBuilder.append:(Ljava/lang/String;)Ljava/lang/StringBuilder;
      46: lload         5
      48: invokevirtual #88                 // Method java/lang/StringBuilder.append:(J)Ljava/lang/StringBuilder;
      51: invokevirtual #55                 // Method java/lang/StringBuilder.toString:()Ljava/lang/String;
      54: invokespecial #112                // Method java/io/IOException."<init>":(Ljava/lang/String;)V
      57: athrow
      58: new           #5                  // class org/apache/hadoop/fs/Path
      61: dup
      62: aload_1
      63: invokestatic  #49                 // Method getRegionDirRecoveredEditsDir:(Lorg/apache/hadoop/fs/Path;)Lorg/apache/hadoop/fs/Path;
      66: new           #51                 // class java/lang/StringBuilder
      69: dup
      70: invokespecial #52                 // Method java/lang/StringBuilder."<init>":()V
      73: lload_2
      74: invokevirtual #88                 // Method java/lang/StringBuilder.append:(J)Ljava/lang/StringBuilder;
      77: ldc           #90                 // String .seqid
      79: invokevirtual #54                 // Method java/lang/StringBuilder.append:(Ljava/lang/String;)Ljava/lang/StringBuilder;
      82: invokevirtual #55                 // Method java/lang/StringBuilder.toString:()Ljava/lang/String;
      85: invokespecial #8                  // Method org/apache/hadoop/fs/Path."<init>":(Lorg/apache/hadoop/fs/Path;Ljava/lang/String;)V
      88: astore        7
      90: lload_2
      91: lload         5
      93: lcmp
      94: ifeq          182
      97: aload_0
      98: aload         7
     100: invokevirtual #113                // Method org/apache/hadoop/fs/FileSystem.createNewFile:(Lorg/apache/hadoop/fs/Path;)Z
     103: ifne          143
     106: aload_0
     107: aload         7
     109: invokevirtual #32                 // Method org/apache/hadoop/fs/FileSystem.exists:(Lorg/apache/hadoop/fs/Path;)Z
     112: ifne          143
     115: new           #109                // class java/io/IOException
     118: dup
     119: new           #51                 // class java/lang/StringBuilder
     122: dup
     123: invokespecial #52                 // Method java/lang/StringBuilder."<init>":()V
     126: ldc           #114                // String Failed to create SeqId file:
     128: invokevirtual #54                 // Method java/lang/StringBuilder.append:(Ljava/lang/String;)Ljava/lang/StringBuilder;
     131: aload         7
     133: invokevirtual #115                // Method java/lang/StringBuilder.append:(Ljava/lang/Object;)Ljava/lang/StringBuilder;
     136: invokevirtual #55                 // Method java/lang/StringBuilder.toString:()Ljava/lang/String;
     139: invokespecial #112                // Method java/io/IOException."<init>":(Ljava/lang/String;)V
     142: athrow
     143: getstatic     #1                  // Field LOG:Lorg/slf4j/Logger;
     146: ldc           #116                // String Wrote file={}, newMaxSeqId={}, maxSeqId={}
     148: iconst_3
     149: anewarray     #67                 // class java/lang/Object
     152: dup
     153: iconst_0
     154: aload         7
     156: aastore
     157: dup
     158: iconst_1
     159: lload_2
     160: invokestatic  #68                 // Method java/lang/Long.valueOf:(J)Ljava/lang/Long;
     163: aastore
     164: dup
     165: iconst_2
     166: lload         5
     168: invokestatic  #68                 // Method java/lang/Long.valueOf:(J)Ljava/lang/Long;
     171: aastore
     172: invokeinterface #117,  3          // InterfaceMethod org/slf4j/Logger.debug:(Ljava/lang/String;[Ljava/lang/Object;)V
     177: goto          182
     180: astore        8
     182: aload         4
     184: astore        8
     186: aload         8
     188: arraylength
     189: istore        9
     191: iconst_0
     192: istore        10
     194: iload         10
     196: iload         9
     198: if_icmpge     238
     201: aload         8
     203: iload         10
     205: aaload
     206: astore        11
     208: aload         7
     210: aload         11
     212: invokevirtual #99                 // Method org/apache/hadoop/fs/FileStatus.getPath:()Lorg/apache/hadoop/fs/Path;
     215: invokevirtual #119                // Method org/apache/hadoop/fs/Path.equals:(Ljava/lang/Object;)Z
     218: ifne          232
     221: aload_0
     222: aload         11
     224: invokevirtual #99                 // Method org/apache/hadoop/fs/FileStatus.getPath:()Lorg/apache/hadoop/fs/Path;
     227: iconst_0
     228: invokevirtual #20                 // Method org/apache/hadoop/fs/FileSystem.delete:(Lorg/apache/hadoop/fs/Path;Z)Z
     231: pop
     232: iinc          10, 1
     235: goto          194
     238: return
    Exception table:
       from    to  target type
          97   177   180   Class org/apache/hadoop/fs/FileAlreadyExistsException

  public static java.util.List<org.apache.hadoop.hbase.wal.WALSplitUtil$MutationReplay> getMutationsFromWALEntry(org.apache.hadoop.hbase.shaded.protobuf.generated.AdminProtos$WALEntry, org.apache.hadoop.hbase.CellScanner, org.apache.hadoop.hbase.util.Pair<org.apache.hadoop.hbase.wal.WALKey, org.apache.hadoop.hbase.wal.WALEdit>, org.apache.hadoop.hbase.client.Durability) throws java.io.IOException;
    Code:
       0: aload_0
       1: ifnonnull     8
       4: invokestatic  #120                // Method java/util/Collections.emptyList:()Ljava/util/List;
       7: areturn
       8: aload_0
       9: invokevirtual #121                // Method org/apache/hadoop/hbase/shaded/protobuf/generated/AdminProtos$WALEntry.getKey:()Lorg/apache/hadoop/hbase/shaded/protobuf/generated/WALProtos$WALKey;
      12: invokevirtual #122                // Method org/apache/hadoop/hbase/shaded/protobuf/generated/WALProtos$WALKey.hasOrigSequenceNumber:()Z
      15: ifeq          28
      18: aload_0
      19: invokevirtual #121                // Method org/apache/hadoop/hbase/shaded/protobuf/generated/AdminProtos$WALEntry.getKey:()Lorg/apache/hadoop/hbase/shaded/protobuf/generated/WALProtos$WALKey;
      22: invokevirtual #123                // Method org/apache/hadoop/hbase/shaded/protobuf/generated/WALProtos$WALKey.getOrigSequenceNumber:()J
      25: goto          35
      28: aload_0
      29: invokevirtual #121                // Method org/apache/hadoop/hbase/shaded/protobuf/generated/AdminProtos$WALEntry.getKey:()Lorg/apache/hadoop/hbase/shaded/protobuf/generated/WALProtos$WALKey;
      32: invokevirtual #124                // Method org/apache/hadoop/hbase/shaded/protobuf/generated/WALProtos$WALKey.getLogSequenceNumber:()J
      35: lstore        4
      37: aload_0
      38: invokevirtual #125                // Method org/apache/hadoop/hbase/shaded/protobuf/generated/AdminProtos$WALEntry.getAssociatedCellCount:()I
      41: istore        6
      43: new           #12                 // class java/util/ArrayList
      46: dup
      47: invokespecial #13                 // Method java/util/ArrayList."<init>":()V
      50: astore        7
      52: aconst_null
      53: astore        8
      55: aconst_null
      56: astore        9
      58: aconst_null
      59: astore        10
      61: aconst_null
      62: astore        11
      64: aload_2
      65: ifnull        77
      68: new           #126                // class org/apache/hadoop/hbase/wal/WALEdit
      71: dup
      72: invokespecial #127                // Method org/apache/hadoop/hbase/wal/WALEdit."<init>":()V
      75: astore        11
      77: iconst_0
      78: istore        12
      80: iload         12
      82: iload         6
      84: if_icmpge     412
      87: aload_1
      88: invokeinterface #128,  1          // InterfaceMethod org/apache/hadoop/hbase/CellScanner.advance:()Z
      93: ifne          134
      96: new           #129                // class java/lang/ArrayIndexOutOfBoundsException
      99: dup
     100: new           #51                 // class java/lang/StringBuilder
     103: dup
     104: invokespecial #52                 // Method java/lang/StringBuilder."<init>":()V
     107: ldc           #130                // String Expected=
     109: invokevirtual #54                 // Method java/lang/StringBuilder.append:(Ljava/lang/String;)Ljava/lang/StringBuilder;
     112: iload         6
     114: invokevirtual #131                // Method java/lang/StringBuilder.append:(I)Ljava/lang/StringBuilder;
     117: ldc           #132                // String , index=
     119: invokevirtual #54                 // Method java/lang/StringBuilder.append:(Ljava/lang/String;)Ljava/lang/StringBuilder;
     122: iload         12
     124: invokevirtual #131                // Method java/lang/StringBuilder.append:(I)Ljava/lang/StringBuilder;
     127: invokevirtual #55                 // Method java/lang/StringBuilder.toString:()Ljava/lang/String;
     130: invokespecial #133                // Method java/lang/ArrayIndexOutOfBoundsException."<init>":(Ljava/lang/String;)V
     133: athrow
     134: aload_1
     135: invokeinterface #134,  1          // InterfaceMethod org/apache/hadoop/hbase/CellScanner.current:()Lorg/apache/hadoop/hbase/Cell;
     140: astore        13
     142: aload         11
     144: ifnull        155
     147: aload         11
     149: aload         13
     151: invokevirtual #135                // Method org/apache/hadoop/hbase/wal/WALEdit.add:(Lorg/apache/hadoop/hbase/Cell;)Lorg/apache/hadoop/hbase/wal/WALEdit;
     154: pop
     155: aload         8
     157: ifnull        187
     160: aload         8
     162: invokeinterface #136,  1          // InterfaceMethod org/apache/hadoop/hbase/Cell.getTypeByte:()B
     167: aload         13
     169: invokeinterface #136,  1          // InterfaceMethod org/apache/hadoop/hbase/Cell.getTypeByte:()B
     174: if_icmpne     187
     177: aload         8
     179: aload         13
     181: invokestatic  #137                // Method org/apache/hadoop/hbase/CellUtil.matchingRows:(Lorg/apache/hadoop/hbase/Cell;Lorg/apache/hadoop/hbase/Cell;)Z
     184: ifne          191
     187: iconst_1
     188: goto          192
     191: iconst_0
     192: istore        14
     194: iload         14
     196: ifeq          362
     199: aload         13
     201: invokestatic  #138                // Method org/apache/hadoop/hbase/CellUtil.isDelete:(Lorg/apache/hadoop/hbase/Cell;)Z
     204: ifeq          262
     207: new           #139                // class org/apache/hadoop/hbase/client/Delete
     210: dup
     211: aload         13
     213: invokeinterface #140,  1          // InterfaceMethod org/apache/hadoop/hbase/Cell.getRowArray:()[B
     218: aload         13
     220: invokeinterface #141,  1          // InterfaceMethod org/apache/hadoop/hbase/Cell.getRowOffset:()I
     225: aload         13
     227: invokeinterface #142,  1          // InterfaceMethod org/apache/hadoop/hbase/Cell.getRowLength:()S
     232: invokespecial #143                // Method org/apache/hadoop/hbase/client/Delete."<init>":([BII)V
     235: astore        9
     237: aload         7
     239: new           #144                // class org/apache/hadoop/hbase/wal/WALSplitUtil$MutationReplay
     242: dup
     243: getstatic     #145                // Field org/apache/hadoop/hbase/shaded/protobuf/generated/ClientProtos$MutationProto$MutationType.DELETE:Lorg/apache/hadoop/hbase/shaded/protobuf/generated/ClientProtos$MutationProto$MutationType;
     246: aload         9
     248: lconst_0
     249: lconst_0
     250: invokespecial #146                // Method org/apache/hadoop/hbase/wal/WALSplitUtil$MutationReplay."<init>":(Lorg/apache/hadoop/hbase/shaded/protobuf/generated/ClientProtos$MutationProto$MutationType;Lorg/apache/hadoop/hbase/client/Mutation;JJ)V
     253: invokeinterface #17,  2           // InterfaceMethod java/util/List.add:(Ljava/lang/Object;)Z
     258: pop
     259: goto          362
     262: new           #147                // class org/apache/hadoop/hbase/client/Put
     265: dup
     266: aload         13
     268: invokeinterface #140,  1          // InterfaceMethod org/apache/hadoop/hbase/Cell.getRowArray:()[B
     273: aload         13
     275: invokeinterface #141,  1          // InterfaceMethod org/apache/hadoop/hbase/Cell.getRowOffset:()I
     280: aload         13
     282: invokeinterface #142,  1          // InterfaceMethod org/apache/hadoop/hbase/Cell.getRowLength:()S
     287: invokespecial #148                // Method org/apache/hadoop/hbase/client/Put."<init>":([BII)V
     290: astore        9
     292: aload_0
     293: invokevirtual #121                // Method org/apache/hadoop/hbase/shaded/protobuf/generated/AdminProtos$WALEntry.getKey:()Lorg/apache/hadoop/hbase/shaded/protobuf/generated/WALProtos$WALKey;
     296: invokevirtual #149                // Method org/apache/hadoop/hbase/shaded/protobuf/generated/WALProtos$WALKey.hasNonceGroup:()Z
     299: ifeq          312
     302: aload_0
     303: invokevirtual #121                // Method org/apache/hadoop/hbase/shaded/protobuf/generated/AdminProtos$WALEntry.getKey:()Lorg/apache/hadoop/hbase/shaded/protobuf/generated/WALProtos$WALKey;
     306: invokevirtual #150                // Method org/apache/hadoop/hbase/shaded/protobuf/generated/WALProtos$WALKey.getNonceGroup:()J
     309: goto          313
     312: lconst_0
     313: lstore        15
     315: aload_0
     316: invokevirtual #121                // Method org/apache/hadoop/hbase/shaded/protobuf/generated/AdminProtos$WALEntry.getKey:()Lorg/apache/hadoop/hbase/shaded/protobuf/generated/WALProtos$WALKey;
     319: invokevirtual #151                // Method org/apache/hadoop/hbase/shaded/protobuf/generated/WALProtos$WALKey.hasNonce:()Z
     322: ifeq          335
     325: aload_0
     326: invokevirtual #121                // Method org/apache/hadoop/hbase/shaded/protobuf/generated/AdminProtos$WALEntry.getKey:()Lorg/apache/hadoop/hbase/shaded/protobuf/generated/WALProtos$WALKey;
     329: invokevirtual #152                // Method org/apache/hadoop/hbase/shaded/protobuf/generated/WALProtos$WALKey.getNonce:()J
     332: goto          336
     335: lconst_0
     336: lstore        17
     338: aload         7
     340: new           #144                // class org/apache/hadoop/hbase/wal/WALSplitUtil$MutationReplay
     343: dup
     344: getstatic     #153                // Field org/apache/hadoop/hbase/shaded/protobuf/generated/ClientProtos$MutationProto$MutationType.PUT:Lorg/apache/hadoop/hbase/shaded/protobuf/generated/ClientProtos$MutationProto$MutationType;
     347: aload         9
     349: lload         15
     351: lload         17
     353: invokespecial #146                // Method org/apache/hadoop/hbase/wal/WALSplitUtil$MutationReplay."<init>":(Lorg/apache/hadoop/hbase/shaded/protobuf/generated/ClientProtos$MutationProto$MutationType;Lorg/apache/hadoop/hbase/client/Mutation;JJ)V
     356: invokeinterface #17,  2           // InterfaceMethod java/util/List.add:(Ljava/lang/Object;)Z
     361: pop
     362: aload         13
     364: invokestatic  #138                // Method org/apache/hadoop/hbase/CellUtil.isDelete:(Lorg/apache/hadoop/hbase/Cell;)Z
     367: ifeq          384
     370: aload         9
     372: checkcast     #139                // class org/apache/hadoop/hbase/client/Delete
     375: aload         13
     377: invokevirtual #154                // Method org/apache/hadoop/hbase/client/Delete.add:(Lorg/apache/hadoop/hbase/Cell;)Lorg/apache/hadoop/hbase/client/Delete;
     380: pop
     381: goto          395
     384: aload         9
     386: checkcast     #147                // class org/apache/hadoop/hbase/client/Put
     389: aload         13
     391: invokevirtual #155                // Method org/apache/hadoop/hbase/client/Put.add:(Lorg/apache/hadoop/hbase/Cell;)Lorg/apache/hadoop/hbase/client/Put;
     394: pop
     395: aload         9
     397: aload_3
     398: invokevirtual #156                // Method org/apache/hadoop/hbase/client/Mutation.setDurability:(Lorg/apache/hadoop/hbase/client/Durability;)Lorg/apache/hadoop/hbase/client/Mutation;
     401: pop
     402: aload         13
     404: astore        8
     406: iinc          12, 1
     409: goto          80
     412: aload_2
     413: ifnull        560
     416: aload_0
     417: invokevirtual #121                // Method org/apache/hadoop/hbase/shaded/protobuf/generated/AdminProtos$WALEntry.getKey:()Lorg/apache/hadoop/hbase/shaded/protobuf/generated/WALProtos$WALKey;
     420: astore        12
     422: new           #12                 // class java/util/ArrayList
     425: dup
     426: aload         12
     428: invokevirtual #157                // Method org/apache/hadoop/hbase/shaded/protobuf/generated/WALProtos$WALKey.getClusterIdsCount:()I
     431: invokespecial #158                // Method java/util/ArrayList."<init>":(I)V
     434: astore        13
     436: aload_0
     437: invokevirtual #121                // Method org/apache/hadoop/hbase/shaded/protobuf/generated/AdminProtos$WALEntry.getKey:()Lorg/apache/hadoop/hbase/shaded/protobuf/generated/WALProtos$WALKey;
     440: invokevirtual #159                // Method org/apache/hadoop/hbase/shaded/protobuf/generated/WALProtos$WALKey.getClusterIdsList:()Ljava/util/List;
     443: invokeinterface #29,  1           // InterfaceMethod java/util/List.iterator:()Ljava/util/Iterator;
     448: astore        14
     450: aload         14
     452: invokeinterface #30,  1           // InterfaceMethod java/util/Iterator.hasNext:()Z
     457: ifeq          500
     460: aload         14
     462: invokeinterface #31,  1           // InterfaceMethod java/util/Iterator.next:()Ljava/lang/Object;
     467: checkcast     #160                // class org/apache/hadoop/hbase/shaded/protobuf/generated/HBaseProtos$UUID
     470: astore        15
     472: aload         13
     474: new           #161                // class java/util/UUID
     477: dup
     478: aload         15
     480: invokevirtual #162                // Method org/apache/hadoop/hbase/shaded/protobuf/generated/HBaseProtos$UUID.getMostSigBits:()J
     483: aload         15
     485: invokevirtual #163                // Method org/apache/hadoop/hbase/shaded/protobuf/generated/HBaseProtos$UUID.getLeastSigBits:()J
     488: invokespecial #164                // Method java/util/UUID."<init>":(JJ)V
     491: invokeinterface #17,  2           // InterfaceMethod java/util/List.add:(Ljava/lang/Object;)Z
     496: pop
     497: goto          450
     500: new           #165                // class org/apache/hadoop/hbase/wal/WALKeyImpl
     503: dup
     504: aload         12
     506: invokevirtual #166                // Method org/apache/hadoop/hbase/shaded/protobuf/generated/WALProtos$WALKey.getEncodedRegionName:()Lorg/apache/hbase/thirdparty/com/google/protobuf/ByteString;
     509: invokevirtual #167                // Method org/apache/hbase/thirdparty/com/google/protobuf/ByteString.toByteArray:()[B
     512: aload         12
     514: invokevirtual #168                // Method org/apache/hadoop/hbase/shaded/protobuf/generated/WALProtos$WALKey.getTableName:()Lorg/apache/hbase/thirdparty/com/google/protobuf/ByteString;
     517: invokevirtual #167                // Method org/apache/hbase/thirdparty/com/google/protobuf/ByteString.toByteArray:()[B
     520: invokestatic  #169                // Method org/apache/hadoop/hbase/TableName.valueOf:([B)Lorg/apache/hadoop/hbase/TableName;
     523: lload         4
     525: aload         12
     527: invokevirtual #170                // Method org/apache/hadoop/hbase/shaded/protobuf/generated/WALProtos$WALKey.getWriteTime:()J
     530: aload         13
     532: aload         12
     534: invokevirtual #150                // Method org/apache/hadoop/hbase/shaded/protobuf/generated/WALProtos$WALKey.getNonceGroup:()J
     537: aload         12
     539: invokevirtual #152                // Method org/apache/hadoop/hbase/shaded/protobuf/generated/WALProtos$WALKey.getNonce:()J
     542: aconst_null
     543: invokespecial #171                // Method org/apache/hadoop/hbase/wal/WALKeyImpl."<init>":([BLorg/apache/hadoop/hbase/TableName;JJLjava/util/List;JJLorg/apache/hadoop/hbase/regionserver/MultiVersionConcurrencyControl;)V
     546: astore        10
     548: aload_2
     549: aload         10
     551: invokevirtual #172                // Method org/apache/hadoop/hbase/util/Pair.setFirst:(Ljava/lang/Object;)V
     554: aload_2
     555: aload         11
     557: invokevirtual #173                // Method org/apache/hadoop/hbase/util/Pair.setSecond:(Ljava/lang/Object;)V
     560: aload         7
     562: areturn

  static java.util.regex.Pattern access$000();
    Code:
       0: getstatic     #2                  // Field EDITFILES_NAME_PATTERN:Ljava/util/regex/Pattern;
       3: areturn

  static org.slf4j.Logger access$100();
    Code:
       0: getstatic     #1                  // Field LOG:Lorg/slf4j/Logger;
       3: areturn

  static {};
    Code:
       0: ldc           #63                 // class org/apache/hadoop/hbase/wal/WALSplitUtil
       2: invokestatic  #175                // Method org/slf4j/LoggerFactory.getLogger:(Ljava/lang/Class;)Lorg/slf4j/Logger;
       5: putstatic     #1                  // Field LOG:Lorg/slf4j/Logger;
       8: ldc           #176                // String -?[0-9]+
      10: invokestatic  #177                // Method java/util/regex/Pattern.compile:(Ljava/lang/String;)Ljava/util/regex/Pattern;
      13: putstatic     #2                  // Field EDITFILES_NAME_PATTERN:Ljava/util/regex/Pattern;
      16: ldc           #90                 // String .seqid
      18: invokevirtual #100                // Method java/lang/String.length:()I
      21: putstatic     #101                // Field SEQUENCE_ID_FILE_SUFFIX_LENGTH:I
      24: return
}
