Compiled from "WALUtil.java"
public class org.apache.hadoop.hbase.regionserver.wal.WALUtil {
  public static org.apache.hadoop.hbase.wal.WALKeyImpl writeCompactionMarker(org.apache.hadoop.hbase.wal.WAL, java.util.NavigableMap<byte[], java.lang.Integer>, org.apache.hadoop.hbase.client.RegionInfo, org.apache.hadoop.hbase.shaded.protobuf.generated.WALProtos$CompactionDescriptor, org.apache.hadoop.hbase.regionserver.MultiVersionConcurrencyControl) throws java.io.IOException;
    Code:
       0: aload_0
       1: aload_1
       2: aload_2
       3: aload_2
       4: aload_3
       5: invokestatic  #2                  // Method org/apache/hadoop/hbase/wal/WALEdit.createCompaction:(Lorg/apache/hadoop/hbase/client/RegionInfo;Lorg/apache/hadoop/hbase/shaded/protobuf/generated/WALProtos$CompactionDescriptor;)Lorg/apache/hadoop/hbase/wal/WALEdit;
       8: aload         4
      10: invokestatic  #3                  // Method writeMarker:(Lorg/apache/hadoop/hbase/wal/WAL;Ljava/util/NavigableMap;Lorg/apache/hadoop/hbase/client/RegionInfo;Lorg/apache/hadoop/hbase/wal/WALEdit;Lorg/apache/hadoop/hbase/regionserver/MultiVersionConcurrencyControl;)Lorg/apache/hadoop/hbase/wal/WALKeyImpl;
      13: astore        5
      15: getstatic     #4                  // Field LOG:Lorg/slf4j/Logger;
      18: invokeinterface #5,  1            // InterfaceMethod org/slf4j/Logger.isTraceEnabled:()Z
      23: ifeq          56
      26: getstatic     #4                  // Field LOG:Lorg/slf4j/Logger;
      29: new           #6                  // class java/lang/StringBuilder
      32: dup
      33: invokespecial #7                  // Method java/lang/StringBuilder."<init>":()V
      36: ldc           #8                  // String Appended compaction marker
      38: invokevirtual #9                  // Method java/lang/StringBuilder.append:(Ljava/lang/String;)Ljava/lang/StringBuilder;
      41: aload_3
      42: invokestatic  #10                 // Method org/apache/hbase/thirdparty/com/google/protobuf/TextFormat.shortDebugString:(Lorg/apache/hbase/thirdparty/com/google/protobuf/MessageOrBuilder;)Ljava/lang/String;
      45: invokevirtual #9                  // Method java/lang/StringBuilder.append:(Ljava/lang/String;)Ljava/lang/StringBuilder;
      48: invokevirtual #11                 // Method java/lang/StringBuilder.toString:()Ljava/lang/String;
      51: invokeinterface #12,  2           // InterfaceMethod org/slf4j/Logger.trace:(Ljava/lang/String;)V
      56: aload         5
      58: areturn

  public static org.apache.hadoop.hbase.wal.WALKeyImpl writeFlushMarker(org.apache.hadoop.hbase.wal.WAL, java.util.NavigableMap<byte[], java.lang.Integer>, org.apache.hadoop.hbase.client.RegionInfo, org.apache.hadoop.hbase.shaded.protobuf.generated.WALProtos$FlushDescriptor, boolean, org.apache.hadoop.hbase.regionserver.MultiVersionConcurrencyControl) throws java.io.IOException;
    Code:
       0: aload_0
       1: aload_1
       2: aload_2
       3: aload_2
       4: aload_3
       5: invokestatic  #13                 // Method org/apache/hadoop/hbase/wal/WALEdit.createFlushWALEdit:(Lorg/apache/hadoop/hbase/client/RegionInfo;Lorg/apache/hadoop/hbase/shaded/protobuf/generated/WALProtos$FlushDescriptor;)Lorg/apache/hadoop/hbase/wal/WALEdit;
       8: aload         5
      10: iload         4
      12: invokestatic  #14                 // Method doFullAppendTransaction:(Lorg/apache/hadoop/hbase/wal/WAL;Ljava/util/NavigableMap;Lorg/apache/hadoop/hbase/client/RegionInfo;Lorg/apache/hadoop/hbase/wal/WALEdit;Lorg/apache/hadoop/hbase/regionserver/MultiVersionConcurrencyControl;Z)Lorg/apache/hadoop/hbase/wal/WALKeyImpl;
      15: astore        6
      17: getstatic     #4                  // Field LOG:Lorg/slf4j/Logger;
      20: invokeinterface #5,  1            // InterfaceMethod org/slf4j/Logger.isTraceEnabled:()Z
      25: ifeq          58
      28: getstatic     #4                  // Field LOG:Lorg/slf4j/Logger;
      31: new           #6                  // class java/lang/StringBuilder
      34: dup
      35: invokespecial #7                  // Method java/lang/StringBuilder."<init>":()V
      38: ldc           #15                 // String Appended flush marker
      40: invokevirtual #9                  // Method java/lang/StringBuilder.append:(Ljava/lang/String;)Ljava/lang/StringBuilder;
      43: aload_3
      44: invokestatic  #10                 // Method org/apache/hbase/thirdparty/com/google/protobuf/TextFormat.shortDebugString:(Lorg/apache/hbase/thirdparty/com/google/protobuf/MessageOrBuilder;)Ljava/lang/String;
      47: invokevirtual #9                  // Method java/lang/StringBuilder.append:(Ljava/lang/String;)Ljava/lang/StringBuilder;
      50: invokevirtual #11                 // Method java/lang/StringBuilder.toString:()Ljava/lang/String;
      53: invokeinterface #12,  2           // InterfaceMethod org/slf4j/Logger.trace:(Ljava/lang/String;)V
      58: aload         6
      60: areturn

  public static org.apache.hadoop.hbase.wal.WALKeyImpl writeRegionEventMarker(org.apache.hadoop.hbase.wal.WAL, java.util.NavigableMap<byte[], java.lang.Integer>, org.apache.hadoop.hbase.client.RegionInfo, org.apache.hadoop.hbase.shaded.protobuf.generated.WALProtos$RegionEventDescriptor, org.apache.hadoop.hbase.regionserver.MultiVersionConcurrencyControl) throws java.io.IOException;
    Code:
       0: aload_0
       1: aload_1
       2: aload_2
       3: aload_2
       4: aload_3
       5: invokestatic  #16                 // Method org/apache/hadoop/hbase/wal/WALEdit.createRegionEventWALEdit:(Lorg/apache/hadoop/hbase/client/RegionInfo;Lorg/apache/hadoop/hbase/shaded/protobuf/generated/WALProtos$RegionEventDescriptor;)Lorg/apache/hadoop/hbase/wal/WALEdit;
       8: aload         4
      10: invokestatic  #3                  // Method writeMarker:(Lorg/apache/hadoop/hbase/wal/WAL;Ljava/util/NavigableMap;Lorg/apache/hadoop/hbase/client/RegionInfo;Lorg/apache/hadoop/hbase/wal/WALEdit;Lorg/apache/hadoop/hbase/regionserver/MultiVersionConcurrencyControl;)Lorg/apache/hadoop/hbase/wal/WALKeyImpl;
      13: astore        5
      15: getstatic     #4                  // Field LOG:Lorg/slf4j/Logger;
      18: invokeinterface #5,  1            // InterfaceMethod org/slf4j/Logger.isTraceEnabled:()Z
      23: ifeq          56
      26: getstatic     #4                  // Field LOG:Lorg/slf4j/Logger;
      29: new           #6                  // class java/lang/StringBuilder
      32: dup
      33: invokespecial #7                  // Method java/lang/StringBuilder."<init>":()V
      36: ldc           #17                 // String Appended region event marker
      38: invokevirtual #9                  // Method java/lang/StringBuilder.append:(Ljava/lang/String;)Ljava/lang/StringBuilder;
      41: aload_3
      42: invokestatic  #10                 // Method org/apache/hbase/thirdparty/com/google/protobuf/TextFormat.shortDebugString:(Lorg/apache/hbase/thirdparty/com/google/protobuf/MessageOrBuilder;)Ljava/lang/String;
      45: invokevirtual #9                  // Method java/lang/StringBuilder.append:(Ljava/lang/String;)Ljava/lang/StringBuilder;
      48: invokevirtual #11                 // Method java/lang/StringBuilder.toString:()Ljava/lang/String;
      51: invokeinterface #12,  2           // InterfaceMethod org/slf4j/Logger.trace:(Ljava/lang/String;)V
      56: aload         5
      58: areturn

  public static org.apache.hadoop.hbase.wal.WALKeyImpl writeBulkLoadMarkerAndSync(org.apache.hadoop.hbase.wal.WAL, java.util.NavigableMap<byte[], java.lang.Integer>, org.apache.hadoop.hbase.client.RegionInfo, org.apache.hadoop.hbase.shaded.protobuf.generated.WALProtos$BulkLoadDescriptor, org.apache.hadoop.hbase.regionserver.MultiVersionConcurrencyControl) throws java.io.IOException;
    Code:
       0: aload_0
       1: aload_1
       2: aload_2
       3: aload_2
       4: aload_3
       5: invokestatic  #18                 // Method org/apache/hadoop/hbase/wal/WALEdit.createBulkLoadEvent:(Lorg/apache/hadoop/hbase/client/RegionInfo;Lorg/apache/hadoop/hbase/shaded/protobuf/generated/WALProtos$BulkLoadDescriptor;)Lorg/apache/hadoop/hbase/wal/WALEdit;
       8: aload         4
      10: invokestatic  #3                  // Method writeMarker:(Lorg/apache/hadoop/hbase/wal/WAL;Ljava/util/NavigableMap;Lorg/apache/hadoop/hbase/client/RegionInfo;Lorg/apache/hadoop/hbase/wal/WALEdit;Lorg/apache/hadoop/hbase/regionserver/MultiVersionConcurrencyControl;)Lorg/apache/hadoop/hbase/wal/WALKeyImpl;
      13: astore        5
      15: getstatic     #4                  // Field LOG:Lorg/slf4j/Logger;
      18: invokeinterface #5,  1            // InterfaceMethod org/slf4j/Logger.isTraceEnabled:()Z
      23: ifeq          56
      26: getstatic     #4                  // Field LOG:Lorg/slf4j/Logger;
      29: new           #6                  // class java/lang/StringBuilder
      32: dup
      33: invokespecial #7                  // Method java/lang/StringBuilder."<init>":()V
      36: ldc           #19                 // String Appended Bulk Load marker
      38: invokevirtual #9                  // Method java/lang/StringBuilder.append:(Ljava/lang/String;)Ljava/lang/StringBuilder;
      41: aload_3
      42: invokestatic  #10                 // Method org/apache/hbase/thirdparty/com/google/protobuf/TextFormat.shortDebugString:(Lorg/apache/hbase/thirdparty/com/google/protobuf/MessageOrBuilder;)Ljava/lang/String;
      45: invokevirtual #9                  // Method java/lang/StringBuilder.append:(Ljava/lang/String;)Ljava/lang/StringBuilder;
      48: invokevirtual #11                 // Method java/lang/StringBuilder.toString:()Ljava/lang/String;
      51: invokeinterface #12,  2           // InterfaceMethod org/slf4j/Logger.trace:(Ljava/lang/String;)V
      56: aload         5
      58: areturn

  public static org.apache.hadoop.hbase.wal.WALKeyImpl doFullAppendTransaction(org.apache.hadoop.hbase.wal.WAL, java.util.NavigableMap<byte[], java.lang.Integer>, org.apache.hadoop.hbase.client.RegionInfo, org.apache.hadoop.hbase.wal.WALEdit, org.apache.hadoop.hbase.regionserver.MultiVersionConcurrencyControl, boolean) throws java.io.IOException;
    Code:
       0: new           #20                 // class org/apache/hadoop/hbase/wal/WALKeyImpl
       3: dup
       4: aload_2
       5: invokeinterface #21,  1           // InterfaceMethod org/apache/hadoop/hbase/client/RegionInfo.getEncodedNameAsBytes:()[B
      10: aload_2
      11: invokeinterface #22,  1           // InterfaceMethod org/apache/hadoop/hbase/client/RegionInfo.getTable:()Lorg/apache/hadoop/hbase/TableName;
      16: invokestatic  #23                 // Method java/lang/System.currentTimeMillis:()J
      19: aload         4
      21: aload_1
      22: invokespecial #24                 // Method org/apache/hadoop/hbase/wal/WALKeyImpl."<init>":([BLorg/apache/hadoop/hbase/TableName;JLorg/apache/hadoop/hbase/regionserver/MultiVersionConcurrencyControl;Ljava/util/NavigableMap;)V
      25: astore        6
      27: ldc2_w        #26                 // long -1l
      30: lstore        7
      32: aload_0
      33: aload_2
      34: aload         6
      36: aload_3
      37: iconst_0
      38: invokeinterface #28,  5           // InterfaceMethod org/apache/hadoop/hbase/wal/WAL.append:(Lorg/apache/hadoop/hbase/client/RegionInfo;Lorg/apache/hadoop/hbase/wal/WALKeyImpl;Lorg/apache/hadoop/hbase/wal/WALEdit;Z)J
      43: lstore        7
      45: iload         5
      47: ifeq          58
      50: aload_0
      51: lload         7
      53: invokeinterface #29,  3           // InterfaceMethod org/apache/hadoop/hbase/wal/WAL.sync:(J)V
      58: aload         4
      60: aload         6
      62: invokevirtual #30                 // Method org/apache/hadoop/hbase/wal/WALKeyImpl.getWriteEntry:()Lorg/apache/hadoop/hbase/regionserver/MultiVersionConcurrencyControl$WriteEntry;
      65: invokevirtual #31                 // Method org/apache/hadoop/hbase/regionserver/MultiVersionConcurrencyControl.complete:(Lorg/apache/hadoop/hbase/regionserver/MultiVersionConcurrencyControl$WriteEntry;)Z
      68: pop
      69: goto          96
      72: astore        9
      74: aload         6
      76: invokevirtual #30                 // Method org/apache/hadoop/hbase/wal/WALKeyImpl.getWriteEntry:()Lorg/apache/hadoop/hbase/regionserver/MultiVersionConcurrencyControl$WriteEntry;
      79: ifnull        93
      82: aload         4
      84: aload         6
      86: invokevirtual #30                 // Method org/apache/hadoop/hbase/wal/WALKeyImpl.getWriteEntry:()Lorg/apache/hadoop/hbase/regionserver/MultiVersionConcurrencyControl$WriteEntry;
      89: invokevirtual #31                 // Method org/apache/hadoop/hbase/regionserver/MultiVersionConcurrencyControl.complete:(Lorg/apache/hadoop/hbase/regionserver/MultiVersionConcurrencyControl$WriteEntry;)Z
      92: pop
      93: aload         9
      95: athrow
      96: aload         6
      98: areturn
    Exception table:
       from    to  target type
          32    69    72   Class java/io/IOException

  public static long getWALBlockSize(org.apache.hadoop.conf.Configuration, org.apache.hadoop.fs.FileSystem, org.apache.hadoop.fs.Path) throws java.io.IOException;
    Code:
       0: aload_0
       1: aload_1
       2: aload_2
       3: iconst_0
       4: invokestatic  #33                 // Method getWALBlockSize:(Lorg/apache/hadoop/conf/Configuration;Lorg/apache/hadoop/fs/FileSystem;Lorg/apache/hadoop/fs/Path;Z)J
       7: lreturn

  public static long getWALBlockSize(org.apache.hadoop.conf.Configuration, org.apache.hadoop.fs.FileSystem, org.apache.hadoop.fs.Path, boolean) throws java.io.IOException;
    Code:
       0: aload_1
       1: aload_2
       2: invokestatic  #34                 // Method org/apache/hadoop/hbase/util/CommonFSUtils.getDefaultBlockSize:(Lorg/apache/hadoop/fs/FileSystem;Lorg/apache/hadoop/fs/Path;)J
       5: ldc2_w        #35                 // long 2l
       8: lmul
       9: lstore        4
      11: iload_3
      12: ifeq          24
      15: aload_0
      16: ldc           #37                 // String hbase.regionserver.recoverededits.blocksize
      18: lload         4
      20: invokevirtual #38                 // Method org/apache/hadoop/conf/Configuration.getLong:(Ljava/lang/String;J)J
      23: lreturn
      24: aload_0
      25: ldc           #39                 // String hbase.regionserver.hlog.blocksize
      27: lload         4
      29: invokevirtual #38                 // Method org/apache/hadoop/conf/Configuration.getLong:(Ljava/lang/String;J)J
      32: lreturn

  public static void filterCells(org.apache.hadoop.hbase.wal.WALEdit, java.util.function.Function<org.apache.hadoop.hbase.Cell, org.apache.hadoop.hbase.Cell>);
    Code:
       0: aload_0
       1: invokevirtual #40                 // Method org/apache/hadoop/hbase/wal/WALEdit.getCells:()Ljava/util/ArrayList;
       4: astore_2
       5: aload_2
       6: invokevirtual #41                 // Method java/util/ArrayList.size:()I
       9: istore_3
      10: iconst_0
      11: istore        4
      13: iconst_0
      14: istore        5
      16: iload         5
      18: iload_3
      19: if_icmpge     62
      22: aload_1
      23: aload_2
      24: iload         5
      26: invokevirtual #42                 // Method java/util/ArrayList.get:(I)Ljava/lang/Object;
      29: invokeinterface #43,  2           // InterfaceMethod java/util/function/Function.apply:(Ljava/lang/Object;)Ljava/lang/Object;
      34: checkcast     #44                 // class org/apache/hadoop/hbase/Cell
      37: astore        6
      39: aload         6
      41: ifnull        56
      44: aload_2
      45: iload         4
      47: aload         6
      49: invokevirtual #45                 // Method java/util/ArrayList.set:(ILjava/lang/Object;)Ljava/lang/Object;
      52: pop
      53: iinc          4, 1
      56: iinc          5, 1
      59: goto          16
      62: iload_3
      63: iconst_1
      64: isub
      65: istore        5
      67: iload         5
      69: iload         4
      71: if_icmplt     87
      74: aload_2
      75: iload         5
      77: invokevirtual #46                 // Method java/util/ArrayList.remove:(I)Ljava/lang/Object;
      80: pop
      81: iinc          5, -1
      84: goto          67
      87: iload         4
      89: iload_3
      90: iconst_2
      91: idiv
      92: if_icmpge     99
      95: aload_2
      96: invokevirtual #47                 // Method java/util/ArrayList.trimToSize:()V
      99: return

  static {};
    Code:
       0: ldc           #48                 // class org/apache/hadoop/hbase/regionserver/wal/WALUtil
       2: invokestatic  #49                 // Method org/slf4j/LoggerFactory.getLogger:(Ljava/lang/Class;)Lorg/slf4j/Logger;
       5: putstatic     #4                  // Field LOG:Lorg/slf4j/Logger;
       8: return
}
