Compiled from "YammerHistogramUtils.java"
public final class org.apache.hadoop.hbase.util.YammerHistogramUtils {
  public static com.codahale.metrics.Histogram newHistogram(com.codahale.metrics.Reservoir);
    Code:
       0: ldc           #2                  // class com/codahale/metrics/Histogram
       2: iconst_1
       3: anewarray     #3                  // class java/lang/Class
       6: dup
       7: iconst_0
       8: ldc           #4                  // class com/codahale/metrics/Reservoir
      10: aastore
      11: invokevirtual #5                  // Method java/lang/Class.getDeclaredConstructor:([Ljava/lang/Class;)Ljava/lang/reflect/Constructor;
      14: astore_1
      15: aload_1
      16: iconst_1
      17: invokevirtual #6                  // Method java/lang/reflect/Constructor.setAccessible:(Z)V
      20: aload_1
      21: iconst_1
      22: anewarray     #7                  // class java/lang/Object
      25: dup
      26: iconst_0
      27: aload_0
      28: aastore
      29: invokevirtual #8                  // Method java/lang/reflect/Constructor.newInstance:([Ljava/lang/Object;)Ljava/lang/Object;
      32: checkcast     #2                  // class com/codahale/metrics/Histogram
      35: areturn
      36: astore_1
      37: new           #10                 // class java/lang/RuntimeException
      40: dup
      41: aload_1
      42: invokespecial #11                 // Method java/lang/RuntimeException."<init>":(Ljava/lang/Throwable;)V
      45: athrow
    Exception table:
       from    to  target type
           0    35    36   Class java/lang/Exception

  public static java.lang.String getShortHistogramReport(com.codahale.metrics.Histogram);
    Code:
       0: aload_0
       1: invokevirtual #12                 // Method com/codahale/metrics/Histogram.getSnapshot:()Lcom/codahale/metrics/Snapshot;
       4: astore_1
       5: new           #13                 // class java/lang/StringBuilder
       8: dup
       9: invokespecial #14                 // Method java/lang/StringBuilder."<init>":()V
      12: ldc           #15                 // String mean=
      14: invokevirtual #16                 // Method java/lang/StringBuilder.append:(Ljava/lang/String;)Ljava/lang/StringBuilder;
      17: getstatic     #17                 // Field DOUBLE_FORMAT:Ljava/text/DecimalFormat;
      20: aload_1
      21: invokevirtual #18                 // Method com/codahale/metrics/Snapshot.getMean:()D
      24: invokevirtual #19                 // Method java/text/DecimalFormat.format:(D)Ljava/lang/String;
      27: invokevirtual #16                 // Method java/lang/StringBuilder.append:(Ljava/lang/String;)Ljava/lang/StringBuilder;
      30: ldc           #20                 // String , min=
      32: invokevirtual #16                 // Method java/lang/StringBuilder.append:(Ljava/lang/String;)Ljava/lang/StringBuilder;
      35: getstatic     #17                 // Field DOUBLE_FORMAT:Ljava/text/DecimalFormat;
      38: aload_1
      39: invokevirtual #21                 // Method com/codahale/metrics/Snapshot.getMin:()J
      42: invokevirtual #22                 // Method java/text/DecimalFormat.format:(J)Ljava/lang/String;
      45: invokevirtual #16                 // Method java/lang/StringBuilder.append:(Ljava/lang/String;)Ljava/lang/StringBuilder;
      48: ldc           #23                 // String , max=
      50: invokevirtual #16                 // Method java/lang/StringBuilder.append:(Ljava/lang/String;)Ljava/lang/StringBuilder;
      53: getstatic     #17                 // Field DOUBLE_FORMAT:Ljava/text/DecimalFormat;
      56: aload_1
      57: invokevirtual #24                 // Method com/codahale/metrics/Snapshot.getMax:()J
      60: invokevirtual #22                 // Method java/text/DecimalFormat.format:(J)Ljava/lang/String;
      63: invokevirtual #16                 // Method java/lang/StringBuilder.append:(Ljava/lang/String;)Ljava/lang/StringBuilder;
      66: ldc           #25                 // String , stdDev=
      68: invokevirtual #16                 // Method java/lang/StringBuilder.append:(Ljava/lang/String;)Ljava/lang/StringBuilder;
      71: getstatic     #17                 // Field DOUBLE_FORMAT:Ljava/text/DecimalFormat;
      74: aload_1
      75: invokevirtual #26                 // Method com/codahale/metrics/Snapshot.getStdDev:()D
      78: invokevirtual #19                 // Method java/text/DecimalFormat.format:(D)Ljava/lang/String;
      81: invokevirtual #16                 // Method java/lang/StringBuilder.append:(Ljava/lang/String;)Ljava/lang/StringBuilder;
      84: ldc           #27                 // String , 95th=
      86: invokevirtual #16                 // Method java/lang/StringBuilder.append:(Ljava/lang/String;)Ljava/lang/StringBuilder;
      89: getstatic     #17                 // Field DOUBLE_FORMAT:Ljava/text/DecimalFormat;
      92: aload_1
      93: invokevirtual #28                 // Method com/codahale/metrics/Snapshot.get95thPercentile:()D
      96: invokevirtual #19                 // Method java/text/DecimalFormat.format:(D)Ljava/lang/String;
      99: invokevirtual #16                 // Method java/lang/StringBuilder.append:(Ljava/lang/String;)Ljava/lang/StringBuilder;
     102: ldc           #29                 // String , 99th=
     104: invokevirtual #16                 // Method java/lang/StringBuilder.append:(Ljava/lang/String;)Ljava/lang/StringBuilder;
     107: getstatic     #17                 // Field DOUBLE_FORMAT:Ljava/text/DecimalFormat;
     110: aload_1
     111: invokevirtual #30                 // Method com/codahale/metrics/Snapshot.get99thPercentile:()D
     114: invokevirtual #19                 // Method java/text/DecimalFormat.format:(D)Ljava/lang/String;
     117: invokevirtual #16                 // Method java/lang/StringBuilder.append:(Ljava/lang/String;)Ljava/lang/StringBuilder;
     120: invokevirtual #31                 // Method java/lang/StringBuilder.toString:()Ljava/lang/String;
     123: areturn

  public static java.lang.String getHistogramReport(com.codahale.metrics.Histogram);
    Code:
       0: aload_0
       1: invokevirtual #12                 // Method com/codahale/metrics/Histogram.getSnapshot:()Lcom/codahale/metrics/Snapshot;
       4: astore_1
       5: new           #13                 // class java/lang/StringBuilder
       8: dup
       9: invokespecial #14                 // Method java/lang/StringBuilder."<init>":()V
      12: ldc           #15                 // String mean=
      14: invokevirtual #16                 // Method java/lang/StringBuilder.append:(Ljava/lang/String;)Ljava/lang/StringBuilder;
      17: getstatic     #17                 // Field DOUBLE_FORMAT:Ljava/text/DecimalFormat;
      20: aload_1
      21: invokevirtual #18                 // Method com/codahale/metrics/Snapshot.getMean:()D
      24: invokevirtual #19                 // Method java/text/DecimalFormat.format:(D)Ljava/lang/String;
      27: invokevirtual #16                 // Method java/lang/StringBuilder.append:(Ljava/lang/String;)Ljava/lang/StringBuilder;
      30: ldc           #20                 // String , min=
      32: invokevirtual #16                 // Method java/lang/StringBuilder.append:(Ljava/lang/String;)Ljava/lang/StringBuilder;
      35: getstatic     #17                 // Field DOUBLE_FORMAT:Ljava/text/DecimalFormat;
      38: aload_1
      39: invokevirtual #21                 // Method com/codahale/metrics/Snapshot.getMin:()J
      42: invokevirtual #22                 // Method java/text/DecimalFormat.format:(J)Ljava/lang/String;
      45: invokevirtual #16                 // Method java/lang/StringBuilder.append:(Ljava/lang/String;)Ljava/lang/StringBuilder;
      48: ldc           #23                 // String , max=
      50: invokevirtual #16                 // Method java/lang/StringBuilder.append:(Ljava/lang/String;)Ljava/lang/StringBuilder;
      53: getstatic     #17                 // Field DOUBLE_FORMAT:Ljava/text/DecimalFormat;
      56: aload_1
      57: invokevirtual #24                 // Method com/codahale/metrics/Snapshot.getMax:()J
      60: invokevirtual #22                 // Method java/text/DecimalFormat.format:(J)Ljava/lang/String;
      63: invokevirtual #16                 // Method java/lang/StringBuilder.append:(Ljava/lang/String;)Ljava/lang/StringBuilder;
      66: ldc           #25                 // String , stdDev=
      68: invokevirtual #16                 // Method java/lang/StringBuilder.append:(Ljava/lang/String;)Ljava/lang/StringBuilder;
      71: getstatic     #17                 // Field DOUBLE_FORMAT:Ljava/text/DecimalFormat;
      74: aload_1
      75: invokevirtual #26                 // Method com/codahale/metrics/Snapshot.getStdDev:()D
      78: invokevirtual #19                 // Method java/text/DecimalFormat.format:(D)Ljava/lang/String;
      81: invokevirtual #16                 // Method java/lang/StringBuilder.append:(Ljava/lang/String;)Ljava/lang/StringBuilder;
      84: ldc           #32                 // String , 50th=
      86: invokevirtual #16                 // Method java/lang/StringBuilder.append:(Ljava/lang/String;)Ljava/lang/StringBuilder;
      89: getstatic     #17                 // Field DOUBLE_FORMAT:Ljava/text/DecimalFormat;
      92: aload_1
      93: invokevirtual #33                 // Method com/codahale/metrics/Snapshot.getMedian:()D
      96: invokevirtual #19                 // Method java/text/DecimalFormat.format:(D)Ljava/lang/String;
      99: invokevirtual #16                 // Method java/lang/StringBuilder.append:(Ljava/lang/String;)Ljava/lang/StringBuilder;
     102: ldc           #34                 // String , 75th=
     104: invokevirtual #16                 // Method java/lang/StringBuilder.append:(Ljava/lang/String;)Ljava/lang/StringBuilder;
     107: getstatic     #17                 // Field DOUBLE_FORMAT:Ljava/text/DecimalFormat;
     110: aload_1
     111: invokevirtual #35                 // Method com/codahale/metrics/Snapshot.get75thPercentile:()D
     114: invokevirtual #19                 // Method java/text/DecimalFormat.format:(D)Ljava/lang/String;
     117: invokevirtual #16                 // Method java/lang/StringBuilder.append:(Ljava/lang/String;)Ljava/lang/StringBuilder;
     120: ldc           #27                 // String , 95th=
     122: invokevirtual #16                 // Method java/lang/StringBuilder.append:(Ljava/lang/String;)Ljava/lang/StringBuilder;
     125: getstatic     #17                 // Field DOUBLE_FORMAT:Ljava/text/DecimalFormat;
     128: aload_1
     129: invokevirtual #28                 // Method com/codahale/metrics/Snapshot.get95thPercentile:()D
     132: invokevirtual #19                 // Method java/text/DecimalFormat.format:(D)Ljava/lang/String;
     135: invokevirtual #16                 // Method java/lang/StringBuilder.append:(Ljava/lang/String;)Ljava/lang/StringBuilder;
     138: ldc           #29                 // String , 99th=
     140: invokevirtual #16                 // Method java/lang/StringBuilder.append:(Ljava/lang/String;)Ljava/lang/StringBuilder;
     143: getstatic     #17                 // Field DOUBLE_FORMAT:Ljava/text/DecimalFormat;
     146: aload_1
     147: invokevirtual #30                 // Method com/codahale/metrics/Snapshot.get99thPercentile:()D
     150: invokevirtual #19                 // Method java/text/DecimalFormat.format:(D)Ljava/lang/String;
     153: invokevirtual #16                 // Method java/lang/StringBuilder.append:(Ljava/lang/String;)Ljava/lang/StringBuilder;
     156: ldc           #36                 // String , 99.9th=
     158: invokevirtual #16                 // Method java/lang/StringBuilder.append:(Ljava/lang/String;)Ljava/lang/StringBuilder;
     161: getstatic     #17                 // Field DOUBLE_FORMAT:Ljava/text/DecimalFormat;
     164: aload_1
     165: invokevirtual #37                 // Method com/codahale/metrics/Snapshot.get999thPercentile:()D
     168: invokevirtual #19                 // Method java/text/DecimalFormat.format:(D)Ljava/lang/String;
     171: invokevirtual #16                 // Method java/lang/StringBuilder.append:(Ljava/lang/String;)Ljava/lang/StringBuilder;
     174: ldc           #38                 // String , 99.99th=
     176: invokevirtual #16                 // Method java/lang/StringBuilder.append:(Ljava/lang/String;)Ljava/lang/StringBuilder;
     179: getstatic     #17                 // Field DOUBLE_FORMAT:Ljava/text/DecimalFormat;
     182: aload_1
     183: ldc2_w        #39                 // double 0.9999d
     186: invokevirtual #41                 // Method com/codahale/metrics/Snapshot.getValue:(D)D
     189: invokevirtual #19                 // Method java/text/DecimalFormat.format:(D)Ljava/lang/String;
     192: invokevirtual #16                 // Method java/lang/StringBuilder.append:(Ljava/lang/String;)Ljava/lang/StringBuilder;
     195: ldc           #42                 // String , 99.999th=
     197: invokevirtual #16                 // Method java/lang/StringBuilder.append:(Ljava/lang/String;)Ljava/lang/StringBuilder;
     200: getstatic     #17                 // Field DOUBLE_FORMAT:Ljava/text/DecimalFormat;
     203: aload_1
     204: ldc2_w        #43                 // double 0.99999d
     207: invokevirtual #41                 // Method com/codahale/metrics/Snapshot.getValue:(D)D
     210: invokevirtual #19                 // Method java/text/DecimalFormat.format:(D)Ljava/lang/String;
     213: invokevirtual #16                 // Method java/lang/StringBuilder.append:(Ljava/lang/String;)Ljava/lang/StringBuilder;
     216: invokevirtual #31                 // Method java/lang/StringBuilder.toString:()Ljava/lang/String;
     219: areturn

  public static java.lang.String getPrettyHistogramReport(com.codahale.metrics.Histogram);
    Code:
       0: aload_0
       1: invokevirtual #12                 // Method com/codahale/metrics/Histogram.getSnapshot:()Lcom/codahale/metrics/Snapshot;
       4: astore_1
       5: new           #13                 // class java/lang/StringBuilder
       8: dup
       9: invokespecial #14                 // Method java/lang/StringBuilder."<init>":()V
      12: ldc           #45                 // String Mean      =
      14: invokevirtual #16                 // Method java/lang/StringBuilder.append:(Ljava/lang/String;)Ljava/lang/StringBuilder;
      17: getstatic     #17                 // Field DOUBLE_FORMAT:Ljava/text/DecimalFormat;
      20: aload_1
      21: invokevirtual #18                 // Method com/codahale/metrics/Snapshot.getMean:()D
      24: invokevirtual #19                 // Method java/text/DecimalFormat.format:(D)Ljava/lang/String;
      27: invokevirtual #16                 // Method java/lang/StringBuilder.append:(Ljava/lang/String;)Ljava/lang/StringBuilder;
      30: ldc           #46                 // String \nMin       =
      32: invokevirtual #16                 // Method java/lang/StringBuilder.append:(Ljava/lang/String;)Ljava/lang/StringBuilder;
      35: getstatic     #17                 // Field DOUBLE_FORMAT:Ljava/text/DecimalFormat;
      38: aload_1
      39: invokevirtual #21                 // Method com/codahale/metrics/Snapshot.getMin:()J
      42: invokevirtual #22                 // Method java/text/DecimalFormat.format:(J)Ljava/lang/String;
      45: invokevirtual #16                 // Method java/lang/StringBuilder.append:(Ljava/lang/String;)Ljava/lang/StringBuilder;
      48: ldc           #47                 // String \nMax       =
      50: invokevirtual #16                 // Method java/lang/StringBuilder.append:(Ljava/lang/String;)Ljava/lang/StringBuilder;
      53: getstatic     #17                 // Field DOUBLE_FORMAT:Ljava/text/DecimalFormat;
      56: aload_1
      57: invokevirtual #24                 // Method com/codahale/metrics/Snapshot.getMax:()J
      60: invokevirtual #22                 // Method java/text/DecimalFormat.format:(J)Ljava/lang/String;
      63: invokevirtual #16                 // Method java/lang/StringBuilder.append:(Ljava/lang/String;)Ljava/lang/StringBuilder;
      66: ldc           #48                 // String \nStdDev    =
      68: invokevirtual #16                 // Method java/lang/StringBuilder.append:(Ljava/lang/String;)Ljava/lang/StringBuilder;
      71: getstatic     #17                 // Field DOUBLE_FORMAT:Ljava/text/DecimalFormat;
      74: aload_1
      75: invokevirtual #26                 // Method com/codahale/metrics/Snapshot.getStdDev:()D
      78: invokevirtual #19                 // Method java/text/DecimalFormat.format:(D)Ljava/lang/String;
      81: invokevirtual #16                 // Method java/lang/StringBuilder.append:(Ljava/lang/String;)Ljava/lang/StringBuilder;
      84: ldc           #49                 // String \n50th      =
      86: invokevirtual #16                 // Method java/lang/StringBuilder.append:(Ljava/lang/String;)Ljava/lang/StringBuilder;
      89: getstatic     #17                 // Field DOUBLE_FORMAT:Ljava/text/DecimalFormat;
      92: aload_1
      93: invokevirtual #33                 // Method com/codahale/metrics/Snapshot.getMedian:()D
      96: invokevirtual #19                 // Method java/text/DecimalFormat.format:(D)Ljava/lang/String;
      99: invokevirtual #16                 // Method java/lang/StringBuilder.append:(Ljava/lang/String;)Ljava/lang/StringBuilder;
     102: ldc           #50                 // String \n75th      =
     104: invokevirtual #16                 // Method java/lang/StringBuilder.append:(Ljava/lang/String;)Ljava/lang/StringBuilder;
     107: getstatic     #17                 // Field DOUBLE_FORMAT:Ljava/text/DecimalFormat;
     110: aload_1
     111: invokevirtual #35                 // Method com/codahale/metrics/Snapshot.get75thPercentile:()D
     114: invokevirtual #19                 // Method java/text/DecimalFormat.format:(D)Ljava/lang/String;
     117: invokevirtual #16                 // Method java/lang/StringBuilder.append:(Ljava/lang/String;)Ljava/lang/StringBuilder;
     120: ldc           #51                 // String \n95th      =
     122: invokevirtual #16                 // Method java/lang/StringBuilder.append:(Ljava/lang/String;)Ljava/lang/StringBuilder;
     125: getstatic     #17                 // Field DOUBLE_FORMAT:Ljava/text/DecimalFormat;
     128: aload_1
     129: invokevirtual #28                 // Method com/codahale/metrics/Snapshot.get95thPercentile:()D
     132: invokevirtual #19                 // Method java/text/DecimalFormat.format:(D)Ljava/lang/String;
     135: invokevirtual #16                 // Method java/lang/StringBuilder.append:(Ljava/lang/String;)Ljava/lang/StringBuilder;
     138: ldc           #52                 // String \n99th      =
     140: invokevirtual #16                 // Method java/lang/StringBuilder.append:(Ljava/lang/String;)Ljava/lang/StringBuilder;
     143: getstatic     #17                 // Field DOUBLE_FORMAT:Ljava/text/DecimalFormat;
     146: aload_1
     147: invokevirtual #30                 // Method com/codahale/metrics/Snapshot.get99thPercentile:()D
     150: invokevirtual #19                 // Method java/text/DecimalFormat.format:(D)Ljava/lang/String;
     153: invokevirtual #16                 // Method java/lang/StringBuilder.append:(Ljava/lang/String;)Ljava/lang/StringBuilder;
     156: ldc           #53                 // String \n99.9th    =
     158: invokevirtual #16                 // Method java/lang/StringBuilder.append:(Ljava/lang/String;)Ljava/lang/StringBuilder;
     161: getstatic     #17                 // Field DOUBLE_FORMAT:Ljava/text/DecimalFormat;
     164: aload_1
     165: invokevirtual #37                 // Method com/codahale/metrics/Snapshot.get999thPercentile:()D
     168: invokevirtual #19                 // Method java/text/DecimalFormat.format:(D)Ljava/lang/String;
     171: invokevirtual #16                 // Method java/lang/StringBuilder.append:(Ljava/lang/String;)Ljava/lang/StringBuilder;
     174: ldc           #54                 // String \n99.99th   =
     176: invokevirtual #16                 // Method java/lang/StringBuilder.append:(Ljava/lang/String;)Ljava/lang/StringBuilder;
     179: getstatic     #17                 // Field DOUBLE_FORMAT:Ljava/text/DecimalFormat;
     182: aload_1
     183: ldc2_w        #39                 // double 0.9999d
     186: invokevirtual #41                 // Method com/codahale/metrics/Snapshot.getValue:(D)D
     189: invokevirtual #19                 // Method java/text/DecimalFormat.format:(D)Ljava/lang/String;
     192: invokevirtual #16                 // Method java/lang/StringBuilder.append:(Ljava/lang/String;)Ljava/lang/StringBuilder;
     195: ldc           #55                 // String \n99.999th  =
     197: invokevirtual #16                 // Method java/lang/StringBuilder.append:(Ljava/lang/String;)Ljava/lang/StringBuilder;
     200: getstatic     #17                 // Field DOUBLE_FORMAT:Ljava/text/DecimalFormat;
     203: aload_1
     204: ldc2_w        #43                 // double 0.99999d
     207: invokevirtual #41                 // Method com/codahale/metrics/Snapshot.getValue:(D)D
     210: invokevirtual #19                 // Method java/text/DecimalFormat.format:(D)Ljava/lang/String;
     213: invokevirtual #16                 // Method java/lang/StringBuilder.append:(Ljava/lang/String;)Ljava/lang/StringBuilder;
     216: invokevirtual #31                 // Method java/lang/StringBuilder.toString:()Ljava/lang/String;
     219: areturn

  static {};
    Code:
       0: new           #56                 // class java/text/DecimalFormat
       3: dup
       4: ldc           #57                 // String #0.00
       6: invokespecial #58                 // Method java/text/DecimalFormat."<init>":(Ljava/lang/String;)V
       9: putstatic     #17                 // Field DOUBLE_FORMAT:Ljava/text/DecimalFormat;
      12: return
}
