Compiled from "ZKAsyncRegistry.java"
class org.apache.hadoop.hbase.client.ZKAsyncRegistry implements org.apache.hadoop.hbase.client.AsyncRegistry {
  org.apache.hadoop.hbase.client.ZKAsyncRegistry(org.apache.hadoop.conf.Configuration);
    Code:
       0: aload_0
       1: invokespecial #2                  // Method java/lang/Object."<init>":()V
       4: aload_0
       5: new           #3                  // class org/apache/hadoop/hbase/zookeeper/ZNodePaths
       8: dup
       9: aload_1
      10: invokespecial #4                  // Method org/apache/hadoop/hbase/zookeeper/ZNodePaths."<init>":(Lorg/apache/hadoop/conf/Configuration;)V
      13: putfield      #5                  // Field znodePaths:Lorg/apache/hadoop/hbase/zookeeper/ZNodePaths;
      16: aload_0
      17: new           #6                  // class org/apache/hadoop/hbase/zookeeper/ReadOnlyZKClient
      20: dup
      21: aload_1
      22: invokespecial #7                  // Method org/apache/hadoop/hbase/zookeeper/ReadOnlyZKClient."<init>":(Lorg/apache/hadoop/conf/Configuration;)V
      25: putfield      #8                  // Field zk:Lorg/apache/hadoop/hbase/zookeeper/ReadOnlyZKClient;
      28: return

  public java.util.concurrent.CompletableFuture<java.lang.String> getClusterId();
    Code:
       0: aload_0
       1: aload_0
       2: getfield      #5                  // Field znodePaths:Lorg/apache/hadoop/hbase/zookeeper/ZNodePaths;
       5: getfield      #17                 // Field org/apache/hadoop/hbase/zookeeper/ZNodePaths.clusterIdZNode:Ljava/lang/String;
       8: invokedynamic #18,  0             // InvokeDynamic #1:convert:()Lorg/apache/hadoop/hbase/client/ZKAsyncRegistry$Converter;
      13: invokespecial #19                 // Method getAndConvert:(Ljava/lang/String;Lorg/apache/hadoop/hbase/client/ZKAsyncRegistry$Converter;)Ljava/util/concurrent/CompletableFuture;
      16: areturn

  org.apache.hadoop.hbase.zookeeper.ReadOnlyZKClient getZKClient();
    Code:
       0: aload_0
       1: getfield      #8                  // Field zk:Lorg/apache/hadoop/hbase/zookeeper/ReadOnlyZKClient;
       4: areturn

  public java.util.concurrent.CompletableFuture<org.apache.hadoop.hbase.RegionLocations> getMetaRegionLocation();
    Code:
       0: new           #9                  // class java/util/concurrent/CompletableFuture
       3: dup
       4: invokespecial #10                 // Method java/util/concurrent/CompletableFuture."<init>":()V
       7: astore_1
       8: aload_0
       9: getfield      #8                  // Field zk:Lorg/apache/hadoop/hbase/zookeeper/ReadOnlyZKClient;
      12: aload_0
      13: getfield      #5                  // Field znodePaths:Lorg/apache/hadoop/hbase/zookeeper/ZNodePaths;
      16: getfield      #53                 // Field org/apache/hadoop/hbase/zookeeper/ZNodePaths.baseZNode:Ljava/lang/String;
      19: invokevirtual #58                 // Method org/apache/hadoop/hbase/zookeeper/ReadOnlyZKClient.list:(Ljava/lang/String;)Ljava/util/concurrent/CompletableFuture;
      22: aload_0
      23: invokedynamic #59,  0             // InvokeDynamic #5:apply:(Lorg/apache/hadoop/hbase/client/ZKAsyncRegistry;)Ljava/util/function/Function;
      28: invokevirtual #60                 // Method java/util/concurrent/CompletableFuture.thenApply:(Ljava/util/function/Function;)Ljava/util/concurrent/CompletableFuture;
      31: aload_0
      32: aload_1
      33: invokedynamic #61,  0             // InvokeDynamic #6:accept:(Lorg/apache/hadoop/hbase/client/ZKAsyncRegistry;Ljava/util/concurrent/CompletableFuture;)Ljava/util/function/BiConsumer;
      38: invokestatic  #13                 // Method org/apache/hadoop/hbase/util/FutureUtils.addListener:(Ljava/util/concurrent/CompletableFuture;Ljava/util/function/BiConsumer;)V
      41: aload_1
      42: areturn

  public java.util.concurrent.CompletableFuture<java.lang.Integer> getCurrentNrHRS();
    Code:
       0: aload_0
       1: getfield      #8                  // Field zk:Lorg/apache/hadoop/hbase/zookeeper/ReadOnlyZKClient;
       4: aload_0
       5: getfield      #5                  // Field znodePaths:Lorg/apache/hadoop/hbase/zookeeper/ZNodePaths;
       8: getfield      #62                 // Field org/apache/hadoop/hbase/zookeeper/ZNodePaths.rsZNode:Ljava/lang/String;
      11: invokevirtual #63                 // Method org/apache/hadoop/hbase/zookeeper/ReadOnlyZKClient.exists:(Ljava/lang/String;)Ljava/util/concurrent/CompletableFuture;
      14: invokedynamic #64,  0             // InvokeDynamic #7:apply:()Ljava/util/function/Function;
      19: invokevirtual #60                 // Method java/util/concurrent/CompletableFuture.thenApply:(Ljava/util/function/Function;)Ljava/util/concurrent/CompletableFuture;
      22: areturn

  public java.util.concurrent.CompletableFuture<org.apache.hadoop.hbase.ServerName> getMasterAddress();
    Code:
       0: aload_0
       1: aload_0
       2: getfield      #5                  // Field znodePaths:Lorg/apache/hadoop/hbase/zookeeper/ZNodePaths;
       5: getfield      #67                 // Field org/apache/hadoop/hbase/zookeeper/ZNodePaths.masterAddressZNode:Ljava/lang/String;
       8: invokedynamic #68,  0             // InvokeDynamic #8:convert:()Lorg/apache/hadoop/hbase/client/ZKAsyncRegistry$Converter;
      13: invokespecial #19                 // Method getAndConvert:(Ljava/lang/String;Lorg/apache/hadoop/hbase/client/ZKAsyncRegistry$Converter;)Ljava/util/concurrent/CompletableFuture;
      16: invokedynamic #69,  0             // InvokeDynamic #9:apply:()Ljava/util/function/Function;
      21: invokevirtual #60                 // Method java/util/concurrent/CompletableFuture.thenApply:(Ljava/util/function/Function;)Ljava/util/concurrent/CompletableFuture;
      24: areturn

  public java.util.concurrent.CompletableFuture<java.lang.Integer> getMasterInfoPort();
    Code:
       0: aload_0
       1: aload_0
       2: getfield      #5                  // Field znodePaths:Lorg/apache/hadoop/hbase/zookeeper/ZNodePaths;
       5: getfield      #67                 // Field org/apache/hadoop/hbase/zookeeper/ZNodePaths.masterAddressZNode:Ljava/lang/String;
       8: invokedynamic #68,  0             // InvokeDynamic #8:convert:()Lorg/apache/hadoop/hbase/client/ZKAsyncRegistry$Converter;
      13: invokespecial #19                 // Method getAndConvert:(Ljava/lang/String;Lorg/apache/hadoop/hbase/client/ZKAsyncRegistry$Converter;)Ljava/util/concurrent/CompletableFuture;
      16: invokedynamic #70,  0             // InvokeDynamic #10:apply:()Ljava/util/function/Function;
      21: invokevirtual #60                 // Method java/util/concurrent/CompletableFuture.thenApply:(Ljava/util/function/Function;)Ljava/util/concurrent/CompletableFuture;
      24: areturn

  public void close();
    Code:
       0: aload_0
       1: getfield      #8                  // Field zk:Lorg/apache/hadoop/hbase/zookeeper/ReadOnlyZKClient;
       4: invokevirtual #71                 // Method org/apache/hadoop/hbase/zookeeper/ReadOnlyZKClient.close:()V
       7: return

  static {};
    Code:
       0: ldc           #113                // class org/apache/hadoop/hbase/client/ZKAsyncRegistry
       2: invokestatic  #114                // Method org/slf4j/LoggerFactory.getLogger:(Ljava/lang/Class;)Lorg/slf4j/Logger;
       5: putstatic     #86                 // Field LOG:Lorg/slf4j/Logger;
       8: return
}
