Compiled from "ZKMainServer.java"
class org.apache.hadoop.hbase.zookeeper.ZKMainServer$HACK_UNTIL_ZOOKEEPER_1897_ZooKeeperMain extends org.apache.zookeeper.ZooKeeperMain {
  public org.apache.hadoop.hbase.zookeeper.ZKMainServer$HACK_UNTIL_ZOOKEEPER_1897_ZooKeeperMain(java.lang.String[]) throws java.io.IOException, java.lang.InterruptedException;
    Code:
       0: aload_0
       1: aload_1
       2: invokespecial #1                  // Method org/apache/zookeeper/ZooKeeperMain."<init>":([Ljava/lang/String;)V
       5: aload_0
       6: getfield      #2                  // Field zk:Lorg/apache/zookeeper/ZooKeeper;
       9: sipush        30000
      12: invokestatic  #3                  // Method org/apache/hadoop/hbase/zookeeper/ZooKeeperHelper.ensureConnectedZooKeeper:(Lorg/apache/zookeeper/ZooKeeper;I)Lorg/apache/zookeeper/ZooKeeper;
      15: pop
      16: return

  void runCmdLine() throws org.apache.zookeeper.KeeperException, java.io.IOException, java.lang.InterruptedException;
    Code:
       0: aload_0
       1: aload_0
       2: getfield      #4                  // Field cl:Lorg/apache/zookeeper/ZooKeeperMain$MyCommandOptions;
       5: invokevirtual #5                  // Method processCmd:(Lorg/apache/zookeeper/ZooKeeperMain$MyCommandOptions;)Z
       8: pop
       9: iconst_0
      10: invokestatic  #6                  // Method java/lang/System.exit:(I)V
      13: return
}
