Compiled from "ZKMetadata.java"
public class org.apache.hadoop.hbase.zookeeper.ZKMetadata {
  public static byte[] appendMetaData(byte[], byte[]);
    Code:
       0: aload_1
       1: ifnull        9
       4: aload_1
       5: arraylength
       6: ifne          11
       9: aload_1
      10: areturn
      11: invokestatic  #4                  // Method java/util/concurrent/ThreadLocalRandom.current:()Ljava/util/concurrent/ThreadLocalRandom;
      14: invokevirtual #5                  // Method java/util/concurrent/ThreadLocalRandom.nextLong:()J
      17: invokestatic  #6                  // Method org/apache/hadoop/hbase/util/Bytes.toBytes:(J)[B
      20: astore_2
      21: aload_0
      22: arraylength
      23: aload_2
      24: arraylength
      25: iadd
      26: istore_3
      27: iconst_5
      28: iload_3
      29: iadd
      30: aload_1
      31: arraylength
      32: iadd
      33: newarray       byte
      35: astore        4
      37: iconst_0
      38: istore        5
      40: aload         4
      42: iload         5
      44: iconst_m1
      45: invokestatic  #7                  // Method org/apache/hadoop/hbase/util/Bytes.putByte:([BIB)I
      48: istore        5
      50: aload         4
      52: iload         5
      54: iload_3
      55: invokestatic  #8                  // Method org/apache/hadoop/hbase/util/Bytes.putInt:([BII)I
      58: istore        5
      60: aload         4
      62: iload         5
      64: aload_0
      65: iconst_0
      66: aload_0
      67: arraylength
      68: invokestatic  #9                  // Method org/apache/hadoop/hbase/util/Bytes.putBytes:([BI[BII)I
      71: istore        5
      73: aload         4
      75: iload         5
      77: aload_2
      78: iconst_0
      79: aload_2
      80: arraylength
      81: invokestatic  #9                  // Method org/apache/hadoop/hbase/util/Bytes.putBytes:([BI[BII)I
      84: istore        5
      86: aload         4
      88: iload         5
      90: aload_1
      91: iconst_0
      92: aload_1
      93: arraylength
      94: invokestatic  #9                  // Method org/apache/hadoop/hbase/util/Bytes.putBytes:([BI[BII)I
      97: istore        5
      99: aload         4
     101: areturn

  public static byte[] removeMetaData(byte[]);
    Code:
       0: aload_0
       1: ifnull        9
       4: aload_0
       5: arraylength
       6: ifne          11
       9: aload_0
      10: areturn
      11: aload_0
      12: iconst_0
      13: baload
      14: istore_1
      15: iload_1
      16: iconst_m1
      17: if_icmpeq     22
      20: aload_0
      21: areturn
      22: aload_0
      23: iconst_1
      24: invokestatic  #10                 // Method org/apache/hadoop/hbase/util/Bytes.toInt:([BI)I
      27: istore_2
      28: aload_0
      29: arraylength
      30: iconst_1
      31: isub
      32: iconst_4
      33: isub
      34: iload_2
      35: isub
      36: istore_3
      37: iconst_5
      38: iload_2
      39: iadd
      40: istore        4
      42: iload_3
      43: newarray       byte
      45: astore        5
      47: aload_0
      48: iload         4
      50: aload         5
      52: iconst_0
      53: iload_3
      54: invokestatic  #11                 // Method java/lang/System.arraycopy:(Ljava/lang/Object;ILjava/lang/Object;II)V
      57: aload         5
      59: areturn
}
