Compiled from "ZKPermissionWatcher.java"
class org.apache.hadoop.hbase.security.access.ZKPermissionWatcher$1 implements java.util.concurrent.Callable<java.lang.Void> {
  final org.apache.hadoop.hbase.security.access.ZKPermissionWatcher this$0;

  org.apache.hadoop.hbase.security.access.ZKPermissionWatcher$1(org.apache.hadoop.hbase.security.access.ZKPermissionWatcher);
    Code:
       0: aload_0
       1: aload_1
       2: putfield      #1                  // Field this$0:Lorg/apache/hadoop/hbase/security/access/ZKPermissionWatcher;
       5: aload_0
       6: invokespecial #2                  // Method java/lang/Object."<init>":()V
       9: return

  public java.lang.Void call() throws org.apache.zookeeper.KeeperException;
    Code:
       0: aload_0
       1: getfield      #1                  // Field this$0:Lorg/apache/hadoop/hbase/security/access/ZKPermissionWatcher;
       4: invokestatic  #3                  // Method org/apache/hadoop/hbase/security/access/ZKPermissionWatcher.access$000:(Lorg/apache/hadoop/hbase/security/access/ZKPermissionWatcher;)Lorg/apache/hadoop/hbase/zookeeper/ZKWatcher;
       7: aload_0
       8: getfield      #1                  // Field this$0:Lorg/apache/hadoop/hbase/security/access/ZKPermissionWatcher;
      11: invokestatic  #4                  // Method org/apache/hadoop/hbase/security/access/ZKPermissionWatcher.access$100:(Lorg/apache/hadoop/hbase/security/access/ZKPermissionWatcher;)Ljava/lang/String;
      14: invokestatic  #5                  // Method org/apache/hadoop/hbase/zookeeper/ZKUtil.getChildDataAndWatchForNewChildren:(Lorg/apache/hadoop/hbase/zookeeper/ZKWatcher;Ljava/lang/String;)Ljava/util/List;
      17: astore_1
      18: aload_1
      19: ifnull        30
      22: aload_0
      23: getfield      #1                  // Field this$0:Lorg/apache/hadoop/hbase/security/access/ZKPermissionWatcher;
      26: aload_1
      27: invokestatic  #6                  // Method org/apache/hadoop/hbase/security/access/ZKPermissionWatcher.access$200:(Lorg/apache/hadoop/hbase/security/access/ZKPermissionWatcher;Ljava/util/List;)V
      30: aconst_null
      31: areturn

  public java.lang.Object call() throws java.lang.Exception;
    Code:
       0: aload_0
       1: invokevirtual #7                  // Method call:()Ljava/lang/Void;
       4: areturn
}
