Compiled from "ZKPermissionWatcher.java"
class org.apache.hadoop.hbase.security.access.ZKPermissionWatcher$3 implements java.lang.Runnable {
  final java.lang.String val$path;

  final org.apache.hadoop.hbase.security.access.ZKPermissionWatcher this$0;

  org.apache.hadoop.hbase.security.access.ZKPermissionWatcher$3(org.apache.hadoop.hbase.security.access.ZKPermissionWatcher, java.lang.String);
    Code:
       0: aload_0
       1: aload_1
       2: putfield      #1                  // Field this$0:Lorg/apache/hadoop/hbase/security/access/ZKPermissionWatcher;
       5: aload_0
       6: aload_2
       7: putfield      #2                  // Field val$path:Ljava/lang/String;
      10: aload_0
      11: invokespecial #3                  // Method java/lang/Object."<init>":()V
      14: return

  public void run();
    Code:
       0: aload_0
       1: getfield      #2                  // Field val$path:Ljava/lang/String;
       4: invokestatic  #4                  // Method org/apache/hadoop/hbase/zookeeper/ZKUtil.getNodeName:(Ljava/lang/String;)Ljava/lang/String;
       7: astore_1
       8: aload_1
       9: invokestatic  #5                  // Method org/apache/hadoop/hbase/security/access/PermissionStorage.isNamespaceEntry:(Ljava/lang/String;)Z
      12: ifeq          32
      15: aload_0
      16: getfield      #1                  // Field this$0:Lorg/apache/hadoop/hbase/security/access/ZKPermissionWatcher;
      19: invokestatic  #6                  // Method org/apache/hadoop/hbase/security/access/ZKPermissionWatcher.access$600:(Lorg/apache/hadoop/hbase/security/access/ZKPermissionWatcher;)Lorg/apache/hadoop/hbase/security/access/AuthManager;
      22: aload_1
      23: invokestatic  #7                  // Method org/apache/hadoop/hbase/util/Bytes.toBytes:(Ljava/lang/String;)[B
      26: invokevirtual #8                  // Method org/apache/hadoop/hbase/security/access/AuthManager.removeNamespace:([B)V
      29: goto          46
      32: aload_0
      33: getfield      #1                  // Field this$0:Lorg/apache/hadoop/hbase/security/access/ZKPermissionWatcher;
      36: invokestatic  #6                  // Method org/apache/hadoop/hbase/security/access/ZKPermissionWatcher.access$600:(Lorg/apache/hadoop/hbase/security/access/ZKPermissionWatcher;)Lorg/apache/hadoop/hbase/security/access/AuthManager;
      39: aload_1
      40: invokestatic  #9                  // Method org/apache/hadoop/hbase/TableName.valueOf:(Ljava/lang/String;)Lorg/apache/hadoop/hbase/TableName;
      43: invokevirtual #10                 // Method org/apache/hadoop/hbase/security/access/AuthManager.removeTable:(Lorg/apache/hadoop/hbase/TableName;)V
      46: return
}
