Compiled from "ZKProcedureMemberRpcs.java"
class org.apache.hadoop.hbase.procedure.ZKProcedureMemberRpcs$1 extends org.apache.hadoop.hbase.procedure.ZKProcedureUtil {
  final org.apache.hadoop.hbase.procedure.ZKProcedureMemberRpcs this$0;

  org.apache.hadoop.hbase.procedure.ZKProcedureMemberRpcs$1(org.apache.hadoop.hbase.procedure.ZKProcedureMemberRpcs, org.apache.hadoop.hbase.zookeeper.ZKWatcher, java.lang.String);
    Code:
       0: aload_0
       1: aload_1
       2: putfield      #1                  // Field this$0:Lorg/apache/hadoop/hbase/procedure/ZKProcedureMemberRpcs;
       5: aload_0
       6: aload_2
       7: aload_3
       8: invokespecial #2                  // Method org/apache/hadoop/hbase/procedure/ZKProcedureUtil."<init>":(Lorg/apache/hadoop/hbase/zookeeper/ZKWatcher;Ljava/lang/String;)V
      11: return

  public void nodeCreated(java.lang.String);
    Code:
       0: aload_0
       1: aload_1
       2: invokevirtual #3                  // Method isInProcedurePath:(Ljava/lang/String;)Z
       5: ifne          9
       8: return
       9: invokestatic  #4                  // Method org/apache/hadoop/hbase/procedure/ZKProcedureMemberRpcs.access$000:()Lorg/slf4j/Logger;
      12: new           #5                  // class java/lang/StringBuilder
      15: dup
      16: invokespecial #6                  // Method java/lang/StringBuilder."<init>":()V
      19: ldc           #7                  // String Received created event:
      21: invokevirtual #8                  // Method java/lang/StringBuilder.append:(Ljava/lang/String;)Ljava/lang/StringBuilder;
      24: aload_1
      25: invokevirtual #8                  // Method java/lang/StringBuilder.append:(Ljava/lang/String;)Ljava/lang/StringBuilder;
      28: invokevirtual #9                  // Method java/lang/StringBuilder.toString:()Ljava/lang/String;
      31: invokeinterface #10,  2           // InterfaceMethod org/slf4j/Logger.info:(Ljava/lang/String;)V
      36: aload_0
      37: aload_1
      38: invokevirtual #11                 // Method isAcquiredNode:(Ljava/lang/String;)Z
      41: ifeq          52
      44: aload_0
      45: getfield      #1                  // Field this$0:Lorg/apache/hadoop/hbase/procedure/ZKProcedureMemberRpcs;
      48: invokestatic  #12                 // Method org/apache/hadoop/hbase/procedure/ZKProcedureMemberRpcs.access$100:(Lorg/apache/hadoop/hbase/procedure/ZKProcedureMemberRpcs;)V
      51: return
      52: aload_0
      53: aload_1
      54: invokevirtual #13                 // Method isAbortNode:(Ljava/lang/String;)Z
      57: ifeq          68
      60: aload_0
      61: getfield      #1                  // Field this$0:Lorg/apache/hadoop/hbase/procedure/ZKProcedureMemberRpcs;
      64: invokestatic  #14                 // Method org/apache/hadoop/hbase/procedure/ZKProcedureMemberRpcs.access$200:(Lorg/apache/hadoop/hbase/procedure/ZKProcedureMemberRpcs;)V
      67: return
      68: aload_1
      69: invokestatic  #15                 // Method org/apache/hadoop/hbase/zookeeper/ZKUtil.getParent:(Ljava/lang/String;)Ljava/lang/String;
      72: astore_2
      73: aload_0
      74: aload_2
      75: invokevirtual #16                 // Method isReachedNode:(Ljava/lang/String;)Z
      78: ifeq          90
      81: aload_0
      82: getfield      #1                  // Field this$0:Lorg/apache/hadoop/hbase/procedure/ZKProcedureMemberRpcs;
      85: aload_1
      86: invokestatic  #17                 // Method org/apache/hadoop/hbase/procedure/ZKProcedureMemberRpcs.access$300:(Lorg/apache/hadoop/hbase/procedure/ZKProcedureMemberRpcs;Ljava/lang/String;)V
      89: return
      90: aload_0
      91: aload_2
      92: invokevirtual #13                 // Method isAbortNode:(Ljava/lang/String;)Z
      95: ifeq          107
      98: aload_0
      99: getfield      #1                  // Field this$0:Lorg/apache/hadoop/hbase/procedure/ZKProcedureMemberRpcs;
     102: aload_1
     103: invokevirtual #18                 // Method org/apache/hadoop/hbase/procedure/ZKProcedureMemberRpcs.abort:(Ljava/lang/String;)V
     106: return
     107: aload_0
     108: aload_2
     109: invokevirtual #11                 // Method isAcquiredNode:(Ljava/lang/String;)Z
     112: ifeq          126
     115: aload_0
     116: getfield      #1                  // Field this$0:Lorg/apache/hadoop/hbase/procedure/ZKProcedureMemberRpcs;
     119: aload_1
     120: invokestatic  #19                 // Method org/apache/hadoop/hbase/procedure/ZKProcedureMemberRpcs.access$400:(Lorg/apache/hadoop/hbase/procedure/ZKProcedureMemberRpcs;Ljava/lang/String;)V
     123: goto          153
     126: invokestatic  #4                  // Method org/apache/hadoop/hbase/procedure/ZKProcedureMemberRpcs.access$000:()Lorg/slf4j/Logger;
     129: new           #5                  // class java/lang/StringBuilder
     132: dup
     133: invokespecial #6                  // Method java/lang/StringBuilder."<init>":()V
     136: ldc           #20                 // String Ignoring created notification for node:
     138: invokevirtual #8                  // Method java/lang/StringBuilder.append:(Ljava/lang/String;)Ljava/lang/StringBuilder;
     141: aload_1
     142: invokevirtual #8                  // Method java/lang/StringBuilder.append:(Ljava/lang/String;)Ljava/lang/StringBuilder;
     145: invokevirtual #9                  // Method java/lang/StringBuilder.toString:()Ljava/lang/String;
     148: invokeinterface #21,  2           // InterfaceMethod org/slf4j/Logger.debug:(Ljava/lang/String;)V
     153: return

  public void nodeChildrenChanged(java.lang.String);
    Code:
       0: aload_1
       1: aload_0
       2: getfield      #22                 // Field acquiredZnode:Ljava/lang/String;
       5: invokevirtual #23                 // Method java/lang/String.equals:(Ljava/lang/Object;)Z
       8: ifeq          48
      11: invokestatic  #4                  // Method org/apache/hadoop/hbase/procedure/ZKProcedureMemberRpcs.access$000:()Lorg/slf4j/Logger;
      14: new           #5                  // class java/lang/StringBuilder
      17: dup
      18: invokespecial #6                  // Method java/lang/StringBuilder."<init>":()V
      21: ldc           #24                 // String Received procedure start children changed event:
      23: invokevirtual #8                  // Method java/lang/StringBuilder.append:(Ljava/lang/String;)Ljava/lang/StringBuilder;
      26: aload_1
      27: invokevirtual #8                  // Method java/lang/StringBuilder.append:(Ljava/lang/String;)Ljava/lang/StringBuilder;
      30: invokevirtual #9                  // Method java/lang/StringBuilder.toString:()Ljava/lang/String;
      33: invokeinterface #10,  2           // InterfaceMethod org/slf4j/Logger.info:(Ljava/lang/String;)V
      38: aload_0
      39: getfield      #1                  // Field this$0:Lorg/apache/hadoop/hbase/procedure/ZKProcedureMemberRpcs;
      42: invokestatic  #12                 // Method org/apache/hadoop/hbase/procedure/ZKProcedureMemberRpcs.access$100:(Lorg/apache/hadoop/hbase/procedure/ZKProcedureMemberRpcs;)V
      45: goto          93
      48: aload_1
      49: aload_0
      50: getfield      #25                 // Field abortZnode:Ljava/lang/String;
      53: invokevirtual #23                 // Method java/lang/String.equals:(Ljava/lang/Object;)Z
      56: ifeq          93
      59: invokestatic  #4                  // Method org/apache/hadoop/hbase/procedure/ZKProcedureMemberRpcs.access$000:()Lorg/slf4j/Logger;
      62: new           #5                  // class java/lang/StringBuilder
      65: dup
      66: invokespecial #6                  // Method java/lang/StringBuilder."<init>":()V
      69: ldc           #26                 // String Received procedure abort children changed event:
      71: invokevirtual #8                  // Method java/lang/StringBuilder.append:(Ljava/lang/String;)Ljava/lang/StringBuilder;
      74: aload_1
      75: invokevirtual #8                  // Method java/lang/StringBuilder.append:(Ljava/lang/String;)Ljava/lang/StringBuilder;
      78: invokevirtual #9                  // Method java/lang/StringBuilder.toString:()Ljava/lang/String;
      81: invokeinterface #10,  2           // InterfaceMethod org/slf4j/Logger.info:(Ljava/lang/String;)V
      86: aload_0
      87: getfield      #1                  // Field this$0:Lorg/apache/hadoop/hbase/procedure/ZKProcedureMemberRpcs;
      90: invokestatic  #14                 // Method org/apache/hadoop/hbase/procedure/ZKProcedureMemberRpcs.access$200:(Lorg/apache/hadoop/hbase/procedure/ZKProcedureMemberRpcs;)V
      93: return
}
