Compiled from "ZKSplitLogManagerCoordination.java"
public final class org.apache.hadoop.hbase.coordination.ZKSplitLogManagerCoordination$TaskFinisher$Status extends java.lang.Enum<org.apache.hadoop.hbase.coordination.ZKSplitLogManagerCoordination$TaskFinisher$Status> {
  public static final org.apache.hadoop.hbase.coordination.ZKSplitLogManagerCoordination$TaskFinisher$Status DONE;

  public static final org.apache.hadoop.hbase.coordination.ZKSplitLogManagerCoordination$TaskFinisher$Status ERR;

  public static org.apache.hadoop.hbase.coordination.ZKSplitLogManagerCoordination$TaskFinisher$Status[] values();
    Code:
       0: getstatic     #1                  // Field $VALUES:[Lorg/apache/hadoop/hbase/coordination/ZKSplitLogManagerCoordination$TaskFinisher$Status;
       3: invokevirtual #2                  // Method "[Lorg/apache/hadoop/hbase/coordination/ZKSplitLogManagerCoordination$TaskFinisher$Status;".clone:()Ljava/lang/Object;
       6: checkcast     #3                  // class "[Lorg/apache/hadoop/hbase/coordination/ZKSplitLogManagerCoordination$TaskFinisher$Status;"
       9: areturn

  public static org.apache.hadoop.hbase.coordination.ZKSplitLogManagerCoordination$TaskFinisher$Status valueOf(java.lang.String);
    Code:
       0: ldc           #4                  // class org/apache/hadoop/hbase/coordination/ZKSplitLogManagerCoordination$TaskFinisher$Status
       2: aload_0
       3: invokestatic  #5                  // Method java/lang/Enum.valueOf:(Ljava/lang/Class;Ljava/lang/String;)Ljava/lang/Enum;
       6: checkcast     #4                  // class org/apache/hadoop/hbase/coordination/ZKSplitLogManagerCoordination$TaskFinisher$Status
       9: areturn

  static {};
    Code:
       0: new           #4                  // class org/apache/hadoop/hbase/coordination/ZKSplitLogManagerCoordination$TaskFinisher$Status
       3: dup
       4: ldc           #7                  // String DONE
       6: iconst_0
       7: invokespecial #8                  // Method "<init>":(Ljava/lang/String;I)V
      10: putstatic     #9                  // Field DONE:Lorg/apache/hadoop/hbase/coordination/ZKSplitLogManagerCoordination$TaskFinisher$Status;
      13: new           #4                  // class org/apache/hadoop/hbase/coordination/ZKSplitLogManagerCoordination$TaskFinisher$Status
      16: dup
      17: ldc           #10                 // String ERR
      19: iconst_1
      20: invokespecial #8                  // Method "<init>":(Ljava/lang/String;I)V
      23: putstatic     #11                 // Field ERR:Lorg/apache/hadoop/hbase/coordination/ZKSplitLogManagerCoordination$TaskFinisher$Status;
      26: iconst_2
      27: anewarray     #4                  // class org/apache/hadoop/hbase/coordination/ZKSplitLogManagerCoordination$TaskFinisher$Status
      30: dup
      31: iconst_0
      32: getstatic     #9                  // Field DONE:Lorg/apache/hadoop/hbase/coordination/ZKSplitLogManagerCoordination$TaskFinisher$Status;
      35: aastore
      36: dup
      37: iconst_1
      38: getstatic     #11                 // Field ERR:Lorg/apache/hadoop/hbase/coordination/ZKSplitLogManagerCoordination$TaskFinisher$Status;
      41: aastore
      42: putstatic     #1                  // Field $VALUES:[Lorg/apache/hadoop/hbase/coordination/ZKSplitLogManagerCoordination$TaskFinisher$Status;
      45: return
}
