Compiled from "ZNodeClearer.java"
public final class org.apache.hadoop.hbase.ZNodeClearer {
  public static void writeMyEphemeralNodeOnDisk(java.lang.String);
    Code:
       0: invokestatic  #2                  // Method getMyEphemeralNodeFileName:()Ljava/lang/String;
       3: astore_1
       4: aload_1
       5: ifnonnull     19
       8: getstatic     #3                  // Field LOG:Lorg/slf4j/Logger;
      11: ldc           #4                  // String Environment variable HBASE_ZNODE_FILE not set; znodes will not be cleared on crash by start scripts (Longer MTTR!)
      13: invokeinterface #5,  2            // InterfaceMethod org/slf4j/Logger.warn:(Ljava/lang/String;)V
      18: return
      19: new           #6                  // class java/io/FileWriter
      22: dup
      23: aload_1
      24: invokespecial #7                  // Method java/io/FileWriter."<init>":(Ljava/lang/String;)V
      27: astore_2
      28: goto          61
      31: astore_3
      32: getstatic     #3                  // Field LOG:Lorg/slf4j/Logger;
      35: new           #9                  // class java/lang/StringBuilder
      38: dup
      39: invokespecial #10                 // Method java/lang/StringBuilder."<init>":()V
      42: ldc           #11                 // String Can't write znode file
      44: invokevirtual #12                 // Method java/lang/StringBuilder.append:(Ljava/lang/String;)Ljava/lang/StringBuilder;
      47: aload_1
      48: invokevirtual #12                 // Method java/lang/StringBuilder.append:(Ljava/lang/String;)Ljava/lang/StringBuilder;
      51: invokevirtual #13                 // Method java/lang/StringBuilder.toString:()Ljava/lang/String;
      54: aload_3
      55: invokeinterface #14,  3           // InterfaceMethod org/slf4j/Logger.warn:(Ljava/lang/String;Ljava/lang/Throwable;)V
      60: return
      61: new           #15                 // class java/io/BufferedWriter
      64: dup
      65: aload_2
      66: invokespecial #16                 // Method java/io/BufferedWriter."<init>":(Ljava/io/Writer;)V
      69: astore_3
      70: aload_3
      71: new           #9                  // class java/lang/StringBuilder
      74: dup
      75: invokespecial #10                 // Method java/lang/StringBuilder."<init>":()V
      78: aload_0
      79: invokevirtual #12                 // Method java/lang/StringBuilder.append:(Ljava/lang/String;)Ljava/lang/StringBuilder;
      82: ldc           #17                 // String \n
      84: invokevirtual #12                 // Method java/lang/StringBuilder.append:(Ljava/lang/String;)Ljava/lang/StringBuilder;
      87: invokevirtual #13                 // Method java/lang/StringBuilder.toString:()Ljava/lang/String;
      90: invokevirtual #18                 // Method java/io/BufferedWriter.write:(Ljava/lang/String;)V
      93: aload_3
      94: invokevirtual #19                 // Method java/io/BufferedWriter.close:()V
      97: aload_2
      98: invokevirtual #20                 // Method java/io/FileWriter.close:()V
     101: goto          113
     104: astore        4
     106: aload_2
     107: invokevirtual #20                 // Method java/io/FileWriter.close:()V
     110: aload         4
     112: athrow
     113: goto          141
     116: astore        5
     118: aload_3
     119: invokevirtual #19                 // Method java/io/BufferedWriter.close:()V
     122: aload_2
     123: invokevirtual #20                 // Method java/io/FileWriter.close:()V
     126: goto          138
     129: astore        6
     131: aload_2
     132: invokevirtual #20                 // Method java/io/FileWriter.close:()V
     135: aload         6
     137: athrow
     138: aload         5
     140: athrow
     141: goto          175
     144: astore        4
     146: getstatic     #3                  // Field LOG:Lorg/slf4j/Logger;
     149: new           #9                  // class java/lang/StringBuilder
     152: dup
     153: invokespecial #10                 // Method java/lang/StringBuilder."<init>":()V
     156: ldc           #11                 // String Can't write znode file
     158: invokevirtual #12                 // Method java/lang/StringBuilder.append:(Ljava/lang/String;)Ljava/lang/StringBuilder;
     161: aload_1
     162: invokevirtual #12                 // Method java/lang/StringBuilder.append:(Ljava/lang/String;)Ljava/lang/StringBuilder;
     165: invokevirtual #13                 // Method java/lang/StringBuilder.toString:()Ljava/lang/String;
     168: aload         4
     170: invokeinterface #14,  3           // InterfaceMethod org/slf4j/Logger.warn:(Ljava/lang/String;Ljava/lang/Throwable;)V
     175: return
    Exception table:
       from    to  target type
          19    28    31   Class java/io/IOException
          93    97   104   any
         104   106   104   any
          70    93   116   any
         118   122   129   any
         129   131   129   any
         116   118   116   any
          70   141   144   Class java/io/IOException

  public static java.lang.String readMyEphemeralNodeOnDisk() throws java.io.IOException;
    Code:
       0: invokestatic  #2                  // Method getMyEphemeralNodeFileName:()Ljava/lang/String;
       3: astore_0
       4: aload_0
       5: ifnonnull     18
       8: new           #21                 // class java/io/FileNotFoundException
      11: dup
      12: ldc           #22                 // String No filename; set environment variable HBASE_ZNODE_FILE
      14: invokespecial #23                 // Method java/io/FileNotFoundException."<init>":(Ljava/lang/String;)V
      17: athrow
      18: new           #24                 // class java/io/FileReader
      21: dup
      22: aload_0
      23: invokespecial #25                 // Method java/io/FileReader."<init>":(Ljava/lang/String;)V
      26: astore_1
      27: aconst_null
      28: astore_2
      29: new           #26                 // class java/io/BufferedReader
      32: dup
      33: aload_1
      34: invokespecial #27                 // Method java/io/BufferedReader."<init>":(Ljava/io/Reader;)V
      37: astore_2
      38: aload_2
      39: invokevirtual #28                 // Method java/io/BufferedReader.readLine:()Ljava/lang/String;
      42: astore_3
      43: aload_3
      44: astore        4
      46: aload_2
      47: ifnull        54
      50: aload_2
      51: invokevirtual #29                 // Method java/io/BufferedReader.close:()V
      54: aload         4
      56: areturn
      57: astore        5
      59: aload_2
      60: ifnull        67
      63: aload_2
      64: invokevirtual #29                 // Method java/io/BufferedReader.close:()V
      67: aload         5
      69: athrow
    Exception table:
       from    to  target type
          29    46    57   any
          57    59    57   any

  public static java.lang.String getMyEphemeralNodeFileName();
    Code:
       0: invokestatic  #30                 // Method java/lang/System.getenv:()Ljava/util/Map;
       3: ldc           #31                 // String HBASE_ZNODE_FILE
       5: invokeinterface #32,  2           // InterfaceMethod java/util/Map.get:(Ljava/lang/Object;)Ljava/lang/Object;
      10: checkcast     #33                 // class java/lang/String
      13: areturn

  public static void deleteMyEphemeralNodeOnDisk();
    Code:
       0: invokestatic  #2                  // Method getMyEphemeralNodeFileName:()Ljava/lang/String;
       3: astore_0
       4: aload_0
       5: ifnull        20
       8: new           #34                 // class java/io/File
      11: dup
      12: aload_0
      13: invokespecial #35                 // Method java/io/File."<init>":(Ljava/lang/String;)V
      16: invokevirtual #36                 // Method java/io/File.delete:()Z
      19: pop
      20: return

  public static java.lang.String parseMasterServerName(java.lang.String);
    Code:
       0: aconst_null
       1: astore_1
       2: aload_0
       3: ldc           #37                 // String /
       5: invokevirtual #38                 // Method java/lang/String.split:(Ljava/lang/String;)[Ljava/lang/String;
       8: astore_2
       9: aload_2
      10: aload_2
      11: arraylength
      12: iconst_1
      13: isub
      14: aaload
      15: astore_1
      16: goto          53
      19: astore_2
      20: getstatic     #3                  // Field LOG:Lorg/slf4j/Logger;
      23: new           #9                  // class java/lang/StringBuilder
      26: dup
      27: invokespecial #10                 // Method java/lang/StringBuilder."<init>":()V
      30: ldc           #40                 // String String
      32: invokevirtual #12                 // Method java/lang/StringBuilder.append:(Ljava/lang/String;)Ljava/lang/StringBuilder;
      35: aload_0
      36: invokevirtual #12                 // Method java/lang/StringBuilder.append:(Ljava/lang/String;)Ljava/lang/StringBuilder;
      39: ldc           #41                 // String  has wrong format
      41: invokevirtual #12                 // Method java/lang/StringBuilder.append:(Ljava/lang/String;)Ljava/lang/StringBuilder;
      44: invokevirtual #13                 // Method java/lang/StringBuilder.toString:()Ljava/lang/String;
      47: aload_2
      48: invokeinterface #14,  3           // InterfaceMethod org/slf4j/Logger.warn:(Ljava/lang/String;Ljava/lang/Throwable;)V
      53: aload_1
      54: areturn
    Exception table:
       from    to  target type
           2    16    19   Class java/lang/IndexOutOfBoundsException

  public static boolean clear(org.apache.hadoop.conf.Configuration);
    Code:
       0: new           #47                 // class org/apache/hadoop/conf/Configuration
       3: dup
       4: aload_0
       5: invokespecial #48                 // Method org/apache/hadoop/conf/Configuration."<init>":(Lorg/apache/hadoop/conf/Configuration;)V
       8: astore_1
       9: aload_1
      10: ldc           #49                 // String zookeeper.recovery.retry
      12: iconst_0
      13: invokevirtual #50                 // Method org/apache/hadoop/conf/Configuration.setInt:(Ljava/lang/String;I)V
      16: new           #51                 // class org/apache/hadoop/hbase/zookeeper/ZKWatcher
      19: dup
      20: aload_1
      21: ldc           #52                 // String clean znode for master
      23: new           #53                 // class org/apache/hadoop/hbase/ZNodeClearer$1
      26: dup
      27: invokespecial #54                 // Method org/apache/hadoop/hbase/ZNodeClearer$1."<init>":()V
      30: invokespecial #55                 // Method org/apache/hadoop/hbase/zookeeper/ZKWatcher."<init>":(Lorg/apache/hadoop/conf/Configuration;Ljava/lang/String;Lorg/apache/hadoop/hbase/Abortable;)V
      33: astore_2
      34: goto          51
      37: astore_3
      38: getstatic     #3                  // Field LOG:Lorg/slf4j/Logger;
      41: ldc           #56                 // String Can't connect to zookeeper to read the master znode
      43: aload_3
      44: invokeinterface #14,  3           // InterfaceMethod org/slf4j/Logger.warn:(Ljava/lang/String;Ljava/lang/Throwable;)V
      49: iconst_0
      50: ireturn
      51: invokestatic  #57                 // Method readMyEphemeralNodeOnDisk:()Ljava/lang/String;
      54: astore_3
      55: aload_0
      56: invokestatic  #58                 // Method tablesOnMaster:(Lorg/apache/hadoop/conf/Configuration;)Z
      59: ifeq          94
      62: aload_2
      63: aload_2
      64: invokevirtual #59                 // Method org/apache/hadoop/hbase/zookeeper/ZKWatcher.getZNodePaths:()Lorg/apache/hadoop/hbase/zookeeper/ZNodePaths;
      67: getfield      #60                 // Field org/apache/hadoop/hbase/zookeeper/ZNodePaths.rsZNode:Ljava/lang/String;
      70: aload_3
      71: invokestatic  #61                 // Method org/apache/hadoop/hbase/zookeeper/ZNodePaths.joinZNode:(Ljava/lang/String;Ljava/lang/String;)Ljava/lang/String;
      74: invokestatic  #62                 // Method org/apache/hadoop/hbase/zookeeper/ZKUtil.deleteNodeFailSilent:(Lorg/apache/hadoop/hbase/zookeeper/ZKWatcher;Ljava/lang/String;)V
      77: aload_2
      78: aload_3
      79: invokestatic  #63                 // Method parseMasterServerName:(Ljava/lang/String;)Ljava/lang/String;
      82: invokestatic  #64                 // Method org/apache/hadoop/hbase/zookeeper/MasterAddressTracker.deleteIfEquals:(Lorg/apache/hadoop/hbase/zookeeper/ZKWatcher;Ljava/lang/String;)Z
      85: istore        4
      87: aload_2
      88: invokevirtual #65                 // Method org/apache/hadoop/hbase/zookeeper/ZKWatcher.close:()V
      91: iload         4
      93: ireturn
      94: aload_2
      95: aload_3
      96: invokestatic  #64                 // Method org/apache/hadoop/hbase/zookeeper/MasterAddressTracker.deleteIfEquals:(Lorg/apache/hadoop/hbase/zookeeper/ZKWatcher;Ljava/lang/String;)Z
      99: istore        4
     101: aload_2
     102: invokevirtual #65                 // Method org/apache/hadoop/hbase/zookeeper/ZKWatcher.close:()V
     105: iload         4
     107: ireturn
     108: astore        4
     110: getstatic     #3                  // Field LOG:Lorg/slf4j/Logger;
     113: ldc           #66                 // String Can't find the znode file; presume non-fatal
     115: aload         4
     117: invokeinterface #14,  3           // InterfaceMethod org/slf4j/Logger.warn:(Ljava/lang/String;Ljava/lang/Throwable;)V
     122: iconst_1
     123: istore        5
     125: aload_2
     126: invokevirtual #65                 // Method org/apache/hadoop/hbase/zookeeper/ZKWatcher.close:()V
     129: iload         5
     131: ireturn
     132: astore        4
     134: getstatic     #3                  // Field LOG:Lorg/slf4j/Logger;
     137: ldc           #67                 // String Can't read the content of the znode file
     139: aload         4
     141: invokeinterface #14,  3           // InterfaceMethod org/slf4j/Logger.warn:(Ljava/lang/String;Ljava/lang/Throwable;)V
     146: iconst_0
     147: istore        5
     149: aload_2
     150: invokevirtual #65                 // Method org/apache/hadoop/hbase/zookeeper/ZKWatcher.close:()V
     153: iload         5
     155: ireturn
     156: astore        4
     158: getstatic     #3                  // Field LOG:Lorg/slf4j/Logger;
     161: ldc           #69                 // String ZooKeeper exception deleting znode
     163: aload         4
     165: invokeinterface #14,  3           // InterfaceMethod org/slf4j/Logger.warn:(Ljava/lang/String;Ljava/lang/Throwable;)V
     170: iconst_0
     171: istore        5
     173: aload_2
     174: invokevirtual #65                 // Method org/apache/hadoop/hbase/zookeeper/ZKWatcher.close:()V
     177: iload         5
     179: ireturn
     180: astore        6
     182: aload_2
     183: invokevirtual #65                 // Method org/apache/hadoop/hbase/zookeeper/ZKWatcher.close:()V
     186: aload         6
     188: athrow
    Exception table:
       from    to  target type
          16    34    37   Class java/io/IOException
          51    87   108   Class java/io/FileNotFoundException
          94   101   108   Class java/io/FileNotFoundException
          51    87   132   Class java/io/IOException
          94   101   132   Class java/io/IOException
          51    87   156   Class org/apache/zookeeper/KeeperException
          94   101   156   Class org/apache/zookeeper/KeeperException
          51    87   180   any
          94   101   180   any
         108   125   180   any
         132   149   180   any
         156   173   180   any
         180   182   180   any

  static {};
    Code:
       0: ldc           #70                 // class org/apache/hadoop/hbase/ZNodeClearer
       2: invokestatic  #71                 // Method org/slf4j/LoggerFactory.getLogger:(Ljava/lang/Class;)Lorg/slf4j/Logger;
       5: putstatic     #3                  // Field LOG:Lorg/slf4j/Logger;
       8: return
}
