Compiled from "java30.java"
public class test.java30 {
  public test.java30();
    Code:
       0: aload_0
       1: invokespecial #1                  // Method java/lang/Object."<init>":()V
       4: return

  public static void main(java.lang.String[]);
    Code:
       0: new           #2                  // class test/Test
       3: dup
       4: invokespecial #3                  // Method test/Test."<init>":()V
       7: astore_1
       8: aload_1
       9: ldc           #4                  // String 1
      11: ldc           #5                  // String a
      13: invokevirtual #6                  // Method test/Test.test:(Ljava/lang/String;Ljava/lang/String;)V
      16: goto          28
      19: astore_2
      20: getstatic     #8                  // Field java/lang/System.out:Ljava/io/PrintStream;
      23: ldc           #9                  // String input is not number...
      25: invokevirtual #10                 // Method java/io/PrintStream.println:(Ljava/lang/String;)V
      28: return
    Exception table:
       from    to  target type
           8    16    19   Class java/lang/NumberFormatException
}
