Compiled from "LoggerExample.java"
public class LoggerExample {
  public LoggerExample();
    Code:
       0: aload_0
       1: invokespecial #1                  // Method java/lang/Object."<init>":()V
       4: return

  public static void main(java.lang.String[]) throws java.lang.SecurityException, java.io.IOException;
    Code:
       0: getstatic     #2                  // Field LOGGER:Ljava/util/logging/Logger;
       3: new           #3                  // class java/lang/StringBuilder
       6: dup
       7: invokespecial #4                  // Method java/lang/StringBuilder."<init>":()V
      10: ldc           #5                  // String Logger Name:
      12: invokevirtual #6                  // Method java/lang/StringBuilder.append:(Ljava/lang/String;)Ljava/lang/StringBuilder;
      15: getstatic     #2                  // Field LOGGER:Ljava/util/logging/Logger;
      18: invokevirtual #7                  // Method java/util/logging/Logger.getName:()Ljava/lang/String;
      21: invokevirtual #6                  // Method java/lang/StringBuilder.append:(Ljava/lang/String;)Ljava/lang/StringBuilder;
      24: invokevirtual #8                  // Method java/lang/StringBuilder.toString:()Ljava/lang/String;
      27: invokevirtual #9                  // Method java/util/logging/Logger.info:(Ljava/lang/String;)V
      30: getstatic     #2                  // Field LOGGER:Ljava/util/logging/Logger;
      33: ldc           #10                 // String Can cause ArrayIndexOutOfBoundsException
      35: invokevirtual #11                 // Method java/util/logging/Logger.warning:(Ljava/lang/String;)V
      38: iconst_3
      39: newarray       int
      41: dup
      42: iconst_0
      43: iconst_1
      44: iastore
      45: dup
      46: iconst_1
      47: iconst_2
      48: iastore
      49: dup
      50: iconst_2
      51: iconst_3
      52: iastore
      53: astore_1
      54: iconst_4
      55: istore_2
      56: getstatic     #2                  // Field LOGGER:Ljava/util/logging/Logger;
      59: new           #3                  // class java/lang/StringBuilder
      62: dup
      63: invokespecial #4                  // Method java/lang/StringBuilder."<init>":()V
      66: ldc           #12                 // String index is set to
      68: invokevirtual #6                  // Method java/lang/StringBuilder.append:(Ljava/lang/String;)Ljava/lang/StringBuilder;
      71: iload_2
      72: invokevirtual #13                 // Method java/lang/StringBuilder.append:(I)Ljava/lang/StringBuilder;
      75: invokevirtual #8                  // Method java/lang/StringBuilder.toString:()Ljava/lang/String;
      78: invokevirtual #14                 // Method java/util/logging/Logger.config:(Ljava/lang/String;)V
      81: getstatic     #15                 // Field java/lang/System.out:Ljava/io/PrintStream;
      84: aload_1
      85: iload_2
      86: iaload
      87: invokevirtual #16                 // Method java/io/PrintStream.println:(I)V
      90: goto          106
      93: astore_3
      94: getstatic     #2                  // Field LOGGER:Ljava/util/logging/Logger;
      97: getstatic     #18                 // Field java/util/logging/Level.SEVERE:Ljava/util/logging/Level;
     100: ldc           #19                 // String Exception occur
     102: aload_3
     103: invokevirtual #20                 // Method java/util/logging/Logger.log:(Ljava/util/logging/Level;Ljava/lang/String;Ljava/lang/Throwable;)V
     106: return
    Exception table:
       from    to  target type
          81    90    93   Class java/lang/ArrayIndexOutOfBoundsException

  static {};
    Code:
       0: ldc           #21                 // class LoggerExample
       2: invokevirtual #22                 // Method java/lang/Class.getName:()Ljava/lang/String;
       5: invokestatic  #23                 // Method java/util/logging/Logger.getLogger:(Ljava/lang/String;)Ljava/util/logging/Logger;
       8: putstatic     #2                  // Field LOGGER:Ljava/util/logging/Logger;
      11: return
}
