Compiled from "AbstractHBaseSaslRpcClient.java"
public abstract class org.apache.hadoop.hbase.security.AbstractHBaseSaslRpcClient {
  protected final javax.security.sasl.SaslClient saslClient;

  protected final boolean fallbackAllowed;

  protected final java.util.Map<java.lang.String, java.lang.String> saslProps;

  protected org.apache.hadoop.hbase.security.AbstractHBaseSaslRpcClient(org.apache.hadoop.hbase.security.AuthMethod, org.apache.hadoop.security.token.Token<? extends org.apache.hadoop.security.token.TokenIdentifier>, java.lang.String, boolean) throws java.io.IOException;
    Code:
       0: aload_0
       1: aload_1
       2: aload_2
       3: aload_3
       4: iload         4
       6: ldc           #2                  // String authentication
       8: invokespecial #3                  // Method "<init>":(Lorg/apache/hadoop/hbase/security/AuthMethod;Lorg/apache/hadoop/security/token/Token;Ljava/lang/String;ZLjava/lang/String;)V
      11: return

  protected org.apache.hadoop.hbase.security.AbstractHBaseSaslRpcClient(org.apache.hadoop.hbase.security.AuthMethod, org.apache.hadoop.security.token.Token<? extends org.apache.hadoop.security.token.TokenIdentifier>, java.lang.String, boolean, java.lang.String) throws java.io.IOException;
    Code:
       0: aload_0
       1: invokespecial #4                  // Method java/lang/Object."<init>":()V
       4: aload_0
       5: iload         4
       7: putfield      #5                  // Field fallbackAllowed:Z
      10: aload_0
      11: aload         5
      13: invokestatic  #6                  // Method org/apache/hadoop/hbase/security/SaslUtil.initSaslProperties:(Ljava/lang/String;)Ljava/util/Map;
      16: putfield      #7                  // Field saslProps:Ljava/util/Map;
      19: getstatic     #8                  // Field org/apache/hadoop/hbase/security/AbstractHBaseSaslRpcClient$1.$SwitchMap$org$apache$hadoop$hbase$security$AuthMethod:[I
      22: aload_1
      23: invokevirtual #9                  // Method org/apache/hadoop/hbase/security/AuthMethod.ordinal:()I
      26: iaload
      27: lookupswitch  { // 2
                     1: 52
                     2: 141
               default: 286
          }
      52: getstatic     #1                  // Field LOG:Lorg/slf4j/Logger;
      55: invokeinterface #10,  1           // InterfaceMethod org/slf4j/Logger.isDebugEnabled:()Z
      60: ifeq          107
      63: getstatic     #1                  // Field LOG:Lorg/slf4j/Logger;
      66: new           #11                 // class java/lang/StringBuilder
      69: dup
      70: invokespecial #12                 // Method java/lang/StringBuilder."<init>":()V
      73: ldc           #13                 // String Creating SASL
      75: invokevirtual #14                 // Method java/lang/StringBuilder.append:(Ljava/lang/String;)Ljava/lang/StringBuilder;
      78: getstatic     #15                 // Field org/apache/hadoop/hbase/security/AuthMethod.DIGEST:Lorg/apache/hadoop/hbase/security/AuthMethod;
      81: invokevirtual #16                 // Method org/apache/hadoop/hbase/security/AuthMethod.getMechanismName:()Ljava/lang/String;
      84: invokevirtual #14                 // Method java/lang/StringBuilder.append:(Ljava/lang/String;)Ljava/lang/StringBuilder;
      87: ldc           #17                 // String  client to authenticate to service at
      89: invokevirtual #14                 // Method java/lang/StringBuilder.append:(Ljava/lang/String;)Ljava/lang/StringBuilder;
      92: aload_2
      93: invokevirtual #18                 // Method org/apache/hadoop/security/token/Token.getService:()Lorg/apache/hadoop/io/Text;
      96: invokevirtual #19                 // Method java/lang/StringBuilder.append:(Ljava/lang/Object;)Ljava/lang/StringBuilder;
      99: invokevirtual #20                 // Method java/lang/StringBuilder.toString:()Ljava/lang/String;
     102: invokeinterface #21,  2           // InterfaceMethod org/slf4j/Logger.debug:(Ljava/lang/String;)V
     107: aload_0
     108: aload_0
     109: iconst_1
     110: anewarray     #22                 // class java/lang/String
     113: dup
     114: iconst_0
     115: getstatic     #15                 // Field org/apache/hadoop/hbase/security/AuthMethod.DIGEST:Lorg/apache/hadoop/hbase/security/AuthMethod;
     118: invokevirtual #16                 // Method org/apache/hadoop/hbase/security/AuthMethod.getMechanismName:()Ljava/lang/String;
     121: aastore
     122: ldc           #24                 // String default
     124: new           #25                 // class org/apache/hadoop/hbase/security/AbstractHBaseSaslRpcClient$SaslClientCallbackHandler
     127: dup
     128: aload_2
     129: invokespecial #26                 // Method org/apache/hadoop/hbase/security/AbstractHBaseSaslRpcClient$SaslClientCallbackHandler."<init>":(Lorg/apache/hadoop/security/token/Token;)V
     132: invokevirtual #27                 // Method createDigestSaslClient:([Ljava/lang/String;Ljava/lang/String;Ljavax/security/auth/callback/CallbackHandler;)Ljavax/security/sasl/SaslClient;
     135: putfield      #28                 // Field saslClient:Ljavax/security/sasl/SaslClient;
     138: goto          313
     141: getstatic     #1                  // Field LOG:Lorg/slf4j/Logger;
     144: invokeinterface #10,  1           // InterfaceMethod org/slf4j/Logger.isDebugEnabled:()Z
     149: ifeq          193
     152: getstatic     #1                  // Field LOG:Lorg/slf4j/Logger;
     155: new           #11                 // class java/lang/StringBuilder
     158: dup
     159: invokespecial #12                 // Method java/lang/StringBuilder."<init>":()V
     162: ldc           #13                 // String Creating SASL
     164: invokevirtual #14                 // Method java/lang/StringBuilder.append:(Ljava/lang/String;)Ljava/lang/StringBuilder;
     167: getstatic     #29                 // Field org/apache/hadoop/hbase/security/AuthMethod.KERBEROS:Lorg/apache/hadoop/hbase/security/AuthMethod;
     170: invokevirtual #16                 // Method org/apache/hadoop/hbase/security/AuthMethod.getMechanismName:()Ljava/lang/String;
     173: invokevirtual #14                 // Method java/lang/StringBuilder.append:(Ljava/lang/String;)Ljava/lang/StringBuilder;
     176: ldc           #30                 // String  client. Server's Kerberos principal name is
     178: invokevirtual #14                 // Method java/lang/StringBuilder.append:(Ljava/lang/String;)Ljava/lang/StringBuilder;
     181: aload_3
     182: invokevirtual #14                 // Method java/lang/StringBuilder.append:(Ljava/lang/String;)Ljava/lang/StringBuilder;
     185: invokevirtual #20                 // Method java/lang/StringBuilder.toString:()Ljava/lang/String;
     188: invokeinterface #21,  2           // InterfaceMethod org/slf4j/Logger.debug:(Ljava/lang/String;)V
     193: aload_3
     194: ifnull        204
     197: aload_3
     198: invokevirtual #31                 // Method java/lang/String.length:()I
     201: ifne          214
     204: new           #32                 // class java/io/IOException
     207: dup
     208: ldc           #33                 // String Failed to specify server's Kerberos principal name
     210: invokespecial #34                 // Method java/io/IOException."<init>":(Ljava/lang/String;)V
     213: athrow
     214: aload_3
     215: invokestatic  #35                 // Method org/apache/hadoop/hbase/security/SaslUtil.splitKerberosName:(Ljava/lang/String;)[Ljava/lang/String;
     218: astore        6
     220: aload         6
     222: arraylength
     223: iconst_3
     224: if_icmpeq     254
     227: new           #32                 // class java/io/IOException
     230: dup
     231: new           #11                 // class java/lang/StringBuilder
     234: dup
     235: invokespecial #12                 // Method java/lang/StringBuilder."<init>":()V
     238: ldc           #36                 // String Kerberos principal does not have the expected format:
     240: invokevirtual #14                 // Method java/lang/StringBuilder.append:(Ljava/lang/String;)Ljava/lang/StringBuilder;
     243: aload_3
     244: invokevirtual #14                 // Method java/lang/StringBuilder.append:(Ljava/lang/String;)Ljava/lang/StringBuilder;
     247: invokevirtual #20                 // Method java/lang/StringBuilder.toString:()Ljava/lang/String;
     250: invokespecial #34                 // Method java/io/IOException."<init>":(Ljava/lang/String;)V
     253: athrow
     254: aload_0
     255: aload_0
     256: iconst_1
     257: anewarray     #22                 // class java/lang/String
     260: dup
     261: iconst_0
     262: getstatic     #29                 // Field org/apache/hadoop/hbase/security/AuthMethod.KERBEROS:Lorg/apache/hadoop/hbase/security/AuthMethod;
     265: invokevirtual #16                 // Method org/apache/hadoop/hbase/security/AuthMethod.getMechanismName:()Ljava/lang/String;
     268: aastore
     269: aload         6
     271: iconst_0
     272: aaload
     273: aload         6
     275: iconst_1
     276: aaload
     277: invokevirtual #37                 // Method createKerberosSaslClient:([Ljava/lang/String;Ljava/lang/String;Ljava/lang/String;)Ljavax/security/sasl/SaslClient;
     280: putfield      #28                 // Field saslClient:Ljavax/security/sasl/SaslClient;
     283: goto          313
     286: new           #32                 // class java/io/IOException
     289: dup
     290: new           #11                 // class java/lang/StringBuilder
     293: dup
     294: invokespecial #12                 // Method java/lang/StringBuilder."<init>":()V
     297: ldc           #38                 // String Unknown authentication method
     299: invokevirtual #14                 // Method java/lang/StringBuilder.append:(Ljava/lang/String;)Ljava/lang/StringBuilder;
     302: aload_1
     303: invokevirtual #19                 // Method java/lang/StringBuilder.append:(Ljava/lang/Object;)Ljava/lang/StringBuilder;
     306: invokevirtual #20                 // Method java/lang/StringBuilder.toString:()Ljava/lang/String;
     309: invokespecial #34                 // Method java/io/IOException."<init>":(Ljava/lang/String;)V
     312: athrow
     313: aload_0
     314: getfield      #28                 // Field saslClient:Ljavax/security/sasl/SaslClient;
     317: ifnonnull     330
     320: new           #32                 // class java/io/IOException
     323: dup
     324: ldc           #39                 // String Unable to find SASL client implementation
     326: invokespecial #34                 // Method java/io/IOException."<init>":(Ljava/lang/String;)V
     329: athrow
     330: return

  protected javax.security.sasl.SaslClient createDigestSaslClient(java.lang.String[], java.lang.String, javax.security.auth.callback.CallbackHandler) throws java.io.IOException;
    Code:
       0: aload_1
       1: aconst_null
       2: aconst_null
       3: aload_2
       4: aload_0
       5: getfield      #7                  // Field saslProps:Ljava/util/Map;
       8: aload_3
       9: invokestatic  #40                 // Method javax/security/sasl/Sasl.createSaslClient:([Ljava/lang/String;Ljava/lang/String;Ljava/lang/String;Ljava/lang/String;Ljava/util/Map;Ljavax/security/auth/callback/CallbackHandler;)Ljavax/security/sasl/SaslClient;
      12: areturn

  protected javax.security.sasl.SaslClient createKerberosSaslClient(java.lang.String[], java.lang.String, java.lang.String) throws java.io.IOException;
    Code:
       0: aload_1
       1: aconst_null
       2: aload_2
       3: aload_3
       4: aload_0
       5: getfield      #7                  // Field saslProps:Ljava/util/Map;
       8: aconst_null
       9: invokestatic  #40                 // Method javax/security/sasl/Sasl.createSaslClient:([Ljava/lang/String;Ljava/lang/String;Ljava/lang/String;Ljava/lang/String;Ljava/util/Map;Ljavax/security/auth/callback/CallbackHandler;)Ljavax/security/sasl/SaslClient;
      12: areturn

  public byte[] getInitialResponse() throws javax.security.sasl.SaslException;
    Code:
       0: aload_0
       1: getfield      #28                 // Field saslClient:Ljavax/security/sasl/SaslClient;
       4: invokeinterface #41,  1           // InterfaceMethod javax/security/sasl/SaslClient.hasInitialResponse:()Z
       9: ifeq          25
      12: aload_0
      13: getfield      #28                 // Field saslClient:Ljavax/security/sasl/SaslClient;
      16: getstatic     #42                 // Field EMPTY_TOKEN:[B
      19: invokeinterface #43,  2           // InterfaceMethod javax/security/sasl/SaslClient.evaluateChallenge:([B)[B
      24: areturn
      25: getstatic     #42                 // Field EMPTY_TOKEN:[B
      28: areturn

  public boolean isComplete();
    Code:
       0: aload_0
       1: getfield      #28                 // Field saslClient:Ljavax/security/sasl/SaslClient;
       4: invokeinterface #44,  1           // InterfaceMethod javax/security/sasl/SaslClient.isComplete:()Z
       9: ireturn

  public byte[] evaluateChallenge(byte[]) throws javax.security.sasl.SaslException;
    Code:
       0: aload_0
       1: getfield      #28                 // Field saslClient:Ljavax/security/sasl/SaslClient;
       4: aload_1
       5: invokeinterface #43,  2           // InterfaceMethod javax/security/sasl/SaslClient.evaluateChallenge:([B)[B
      10: areturn

  public void dispose();
    Code:
       0: aload_0
       1: getfield      #28                 // Field saslClient:Ljavax/security/sasl/SaslClient;
       4: invokestatic  #45                 // Method org/apache/hadoop/hbase/security/SaslUtil.safeDispose:(Ljavax/security/sasl/SaslClient;)V
       7: return

  static org.slf4j.Logger access$000();
    Code:
       0: getstatic     #1                  // Field LOG:Lorg/slf4j/Logger;
       3: areturn

  static {};
    Code:
       0: ldc           #46                 // class org/apache/hadoop/hbase/security/AbstractHBaseSaslRpcClient
       2: invokestatic  #47                 // Method org/slf4j/LoggerFactory.getLogger:(Ljava/lang/Class;)Lorg/slf4j/Logger;
       5: putstatic     #1                  // Field LOG:Lorg/slf4j/Logger;
       8: iconst_0
       9: newarray       byte
      11: putstatic     #42                 // Field EMPTY_TOKEN:[B
      14: return
}
