Compiled from "AbstractStateMachineNamespaceProcedure.java"
public abstract class org.apache.hadoop.hbase.master.procedure.AbstractStateMachineNamespaceProcedure<TState> extends org.apache.hadoop.hbase.procedure2.StateMachineProcedure<org.apache.hadoop.hbase.master.procedure.MasterProcedureEnv, TState> implements org.apache.hadoop.hbase.master.procedure.TableProcedureInterface {
  protected org.apache.hadoop.hbase.master.procedure.AbstractStateMachineNamespaceProcedure();
    Code:
       0: aload_0
       1: invokespecial #1                  // Method org/apache/hadoop/hbase/procedure2/StateMachineProcedure."<init>":()V
       4: aload_0
       5: aconst_null
       6: putfield      #2                  // Field syncLatch:Lorg/apache/hadoop/hbase/master/procedure/ProcedurePrepareLatch;
       9: return

  protected org.apache.hadoop.hbase.master.procedure.AbstractStateMachineNamespaceProcedure(org.apache.hadoop.hbase.master.procedure.MasterProcedureEnv);
    Code:
       0: aload_0
       1: aload_1
       2: aconst_null
       3: invokespecial #3                  // Method "<init>":(Lorg/apache/hadoop/hbase/master/procedure/MasterProcedureEnv;Lorg/apache/hadoop/hbase/master/procedure/ProcedurePrepareLatch;)V
       6: return

  protected org.apache.hadoop.hbase.master.procedure.AbstractStateMachineNamespaceProcedure(org.apache.hadoop.hbase.master.procedure.MasterProcedureEnv, org.apache.hadoop.hbase.master.procedure.ProcedurePrepareLatch);
    Code:
       0: aload_0
       1: invokespecial #1                  // Method org/apache/hadoop/hbase/procedure2/StateMachineProcedure."<init>":()V
       4: aload_0
       5: aload_1
       6: invokevirtual #4                  // Method org/apache/hadoop/hbase/master/procedure/MasterProcedureEnv.getRequestUser:()Lorg/apache/hadoop/hbase/security/User;
       9: invokevirtual #5                  // Method setOwner:(Lorg/apache/hadoop/hbase/security/User;)V
      12: aload_0
      13: aload_2
      14: putfield      #2                  // Field syncLatch:Lorg/apache/hadoop/hbase/master/procedure/ProcedurePrepareLatch;
      17: return

  protected abstract java.lang.String getNamespaceName();

  public org.apache.hadoop.hbase.TableName getTableName();
    Code:
       0: getstatic     #6                  // Field DUMMY_NAMESPACE_TABLE_NAME:Lorg/apache/hadoop/hbase/TableName;
       3: areturn

  public abstract org.apache.hadoop.hbase.master.procedure.TableProcedureInterface$TableOperationType getTableOperationType();

  public void toStringClassDetails(java.lang.StringBuilder);
    Code:
       0: aload_1
       1: aload_0
       2: invokevirtual #7                  // Method java/lang/Object.getClass:()Ljava/lang/Class;
       5: invokevirtual #8                  // Method java/lang/Class.getSimpleName:()Ljava/lang/String;
       8: invokevirtual #9                  // Method java/lang/StringBuilder.append:(Ljava/lang/String;)Ljava/lang/StringBuilder;
      11: pop
      12: aload_1
      13: ldc           #10                 // String , namespace=
      15: invokevirtual #9                  // Method java/lang/StringBuilder.append:(Ljava/lang/String;)Ljava/lang/StringBuilder;
      18: pop
      19: aload_1
      20: aload_0
      21: invokevirtual #11                 // Method getNamespaceName:()Ljava/lang/String;
      24: invokevirtual #9                  // Method java/lang/StringBuilder.append:(Ljava/lang/String;)Ljava/lang/StringBuilder;
      27: pop
      28: return

  protected boolean waitInitialized(org.apache.hadoop.hbase.master.procedure.MasterProcedureEnv);
    Code:
       0: aload_1
       1: aload_0
       2: invokevirtual #12                 // Method org/apache/hadoop/hbase/master/procedure/MasterProcedureEnv.waitInitialized:(Lorg/apache/hadoop/hbase/procedure2/Procedure;)Z
       5: ireturn

  protected org.apache.hadoop.hbase.procedure2.Procedure$LockState acquireLock(org.apache.hadoop.hbase.master.procedure.MasterProcedureEnv);
    Code:
       0: aload_1
       1: invokevirtual #13                 // Method org/apache/hadoop/hbase/master/procedure/MasterProcedureEnv.getProcedureScheduler:()Lorg/apache/hadoop/hbase/master/procedure/MasterProcedureScheduler;
       4: aload_0
       5: aload_0
       6: invokevirtual #11                 // Method getNamespaceName:()Ljava/lang/String;
       9: invokevirtual #14                 // Method org/apache/hadoop/hbase/master/procedure/MasterProcedureScheduler.waitNamespaceExclusiveLock:(Lorg/apache/hadoop/hbase/procedure2/Procedure;Ljava/lang/String;)Z
      12: ifeq          19
      15: getstatic     #15                 // Field org/apache/hadoop/hbase/procedure2/Procedure$LockState.LOCK_EVENT_WAIT:Lorg/apache/hadoop/hbase/procedure2/Procedure$LockState;
      18: areturn
      19: getstatic     #16                 // Field org/apache/hadoop/hbase/procedure2/Procedure$LockState.LOCK_ACQUIRED:Lorg/apache/hadoop/hbase/procedure2/Procedure$LockState;
      22: areturn

  protected void releaseLock(org.apache.hadoop.hbase.master.procedure.MasterProcedureEnv);
    Code:
       0: aload_1
       1: invokevirtual #13                 // Method org/apache/hadoop/hbase/master/procedure/MasterProcedureEnv.getProcedureScheduler:()Lorg/apache/hadoop/hbase/master/procedure/MasterProcedureScheduler;
       4: aload_0
       5: aload_0
       6: invokevirtual #11                 // Method getNamespaceName:()Ljava/lang/String;
       9: invokevirtual #17                 // Method org/apache/hadoop/hbase/master/procedure/MasterProcedureScheduler.wakeNamespaceExclusiveLock:(Lorg/apache/hadoop/hbase/procedure2/Procedure;Ljava/lang/String;)V
      12: return

  protected static void addOrUpdateNamespace(org.apache.hadoop.hbase.master.procedure.MasterProcedureEnv, org.apache.hadoop.hbase.NamespaceDescriptor) throws java.io.IOException;
    Code:
       0: aload_0
       1: invokestatic  #18                 // Method getTableNamespaceManager:(Lorg/apache/hadoop/hbase/master/procedure/MasterProcedureEnv;)Lorg/apache/hadoop/hbase/master/TableNamespaceManager;
       4: aload_1
       5: invokevirtual #19                 // Method org/apache/hadoop/hbase/master/TableNamespaceManager.addOrUpdateNamespace:(Lorg/apache/hadoop/hbase/NamespaceDescriptor;)V
       8: return

  protected static org.apache.hadoop.hbase.master.TableNamespaceManager getTableNamespaceManager(org.apache.hadoop.hbase.master.procedure.MasterProcedureEnv);
    Code:
       0: aload_0
       1: invokevirtual #20                 // Method org/apache/hadoop/hbase/master/procedure/MasterProcedureEnv.getMasterServices:()Lorg/apache/hadoop/hbase/master/MasterServices;
       4: invokeinterface #21,  1           // InterfaceMethod org/apache/hadoop/hbase/master/MasterServices.getClusterSchema:()Lorg/apache/hadoop/hbase/master/ClusterSchema;
       9: invokeinterface #22,  1           // InterfaceMethod org/apache/hadoop/hbase/master/ClusterSchema.getTableNamespaceManager:()Lorg/apache/hadoop/hbase/master/TableNamespaceManager;
      14: areturn

  protected static void createDirectory(org.apache.hadoop.hbase.master.procedure.MasterProcedureEnv, org.apache.hadoop.hbase.NamespaceDescriptor) throws java.io.IOException;
    Code:
       0: aload_0
       1: invokevirtual #20                 // Method org/apache/hadoop/hbase/master/procedure/MasterProcedureEnv.getMasterServices:()Lorg/apache/hadoop/hbase/master/MasterServices;
       4: invokeinterface #23,  1           // InterfaceMethod org/apache/hadoop/hbase/master/MasterServices.getMasterFileSystem:()Lorg/apache/hadoop/hbase/master/MasterFileSystem;
       9: aload_1
      10: invokestatic  #24                 // Method createDirectory:(Lorg/apache/hadoop/hbase/master/MasterFileSystem;Lorg/apache/hadoop/hbase/NamespaceDescriptor;)V
      13: return

  public static void createDirectory(org.apache.hadoop.hbase.master.MasterFileSystem, org.apache.hadoop.hbase.NamespaceDescriptor) throws java.io.IOException;
    Code:
       0: aload_0
       1: invokevirtual #25                 // Method org/apache/hadoop/hbase/master/MasterFileSystem.getFileSystem:()Lorg/apache/hadoop/fs/FileSystem;
       4: aload_0
       5: invokevirtual #26                 // Method org/apache/hadoop/hbase/master/MasterFileSystem.getRootDir:()Lorg/apache/hadoop/fs/Path;
       8: aload_1
       9: invokevirtual #27                 // Method org/apache/hadoop/hbase/NamespaceDescriptor.getName:()Ljava/lang/String;
      12: invokestatic  #28                 // Method org/apache/hadoop/hbase/util/FSUtils.getNamespaceDir:(Lorg/apache/hadoop/fs/Path;Ljava/lang/String;)Lorg/apache/hadoop/fs/Path;
      15: invokevirtual #29                 // Method org/apache/hadoop/fs/FileSystem.mkdirs:(Lorg/apache/hadoop/fs/Path;)Z
      18: pop
      19: return

  protected void releaseSyncLatch();
    Code:
       0: aload_0
       1: getfield      #2                  // Field syncLatch:Lorg/apache/hadoop/hbase/master/procedure/ProcedurePrepareLatch;
       4: aload_0
       5: invokestatic  #30                 // Method org/apache/hadoop/hbase/master/procedure/ProcedurePrepareLatch.releaseLatch:(Lorg/apache/hadoop/hbase/master/procedure/ProcedurePrepareLatch;Lorg/apache/hadoop/hbase/procedure2/Procedure;)V
       8: return

  protected void releaseLock(java.lang.Object);
    Code:
       0: aload_0
       1: aload_1
       2: checkcast     #31                 // class org/apache/hadoop/hbase/master/procedure/MasterProcedureEnv
       5: invokevirtual #32                 // Method releaseLock:(Lorg/apache/hadoop/hbase/master/procedure/MasterProcedureEnv;)V
       8: return

  protected org.apache.hadoop.hbase.procedure2.Procedure$LockState acquireLock(java.lang.Object);
    Code:
       0: aload_0
       1: aload_1
       2: checkcast     #31                 // class org/apache/hadoop/hbase/master/procedure/MasterProcedureEnv
       5: invokevirtual #33                 // Method acquireLock:(Lorg/apache/hadoop/hbase/master/procedure/MasterProcedureEnv;)Lorg/apache/hadoop/hbase/procedure2/Procedure$LockState;
       8: areturn

  protected boolean waitInitialized(java.lang.Object);
    Code:
       0: aload_0
       1: aload_1
       2: checkcast     #31                 // class org/apache/hadoop/hbase/master/procedure/MasterProcedureEnv
       5: invokevirtual #34                 // Method waitInitialized:(Lorg/apache/hadoop/hbase/master/procedure/MasterProcedureEnv;)Z
       8: ireturn
}
