Compiled from "AbstractHBaseToolTest.java"
final class org.apache.hadoop.hbase.util.AbstractHBaseToolTest$Options {
  static final org.apache.hbase.thirdparty.org.apache.commons.cli.Option REQUIRED;

  static final org.apache.hbase.thirdparty.org.apache.commons.cli.Option OPTIONAL;

  static final org.apache.hbase.thirdparty.org.apache.commons.cli.Option BOOLEAN;

  org.apache.hadoop.hbase.util.AbstractHBaseToolTest$Options();
    Code:
       0: aload_0
       1: invokespecial #1                  // Method java/lang/Object."<init>":()V
       4: return

  static {};
    Code:
       0: new           #2                  // class org/apache/hbase/thirdparty/org/apache/commons/cli/Option
       3: dup
       4: aconst_null
       5: ldc           #3                  // String required
       7: iconst_1
       8: ldc           #4                  // String
      10: invokespecial #5                  // Method org/apache/hbase/thirdparty/org/apache/commons/cli/Option."<init>":(Ljava/lang/String;Ljava/lang/String;ZLjava/lang/String;)V
      13: putstatic     #6                  // Field REQUIRED:Lorg/apache/hbase/thirdparty/org/apache/commons/cli/Option;
      16: new           #2                  // class org/apache/hbase/thirdparty/org/apache/commons/cli/Option
      19: dup
      20: aconst_null
      21: ldc           #7                  // String optional
      23: iconst_1
      24: ldc           #4                  // String
      26: invokespecial #5                  // Method org/apache/hbase/thirdparty/org/apache/commons/cli/Option."<init>":(Ljava/lang/String;Ljava/lang/String;ZLjava/lang/String;)V
      29: putstatic     #8                  // Field OPTIONAL:Lorg/apache/hbase/thirdparty/org/apache/commons/cli/Option;
      32: new           #2                  // class org/apache/hbase/thirdparty/org/apache/commons/cli/Option
      35: dup
      36: aconst_null
      37: ldc           #9                  // String boolean
      39: iconst_0
      40: ldc           #4                  // String
      42: invokespecial #5                  // Method org/apache/hbase/thirdparty/org/apache/commons/cli/Option."<init>":(Ljava/lang/String;Ljava/lang/String;ZLjava/lang/String;)V
      45: putstatic     #10                 // Field BOOLEAN:Lorg/apache/hbase/thirdparty/org/apache/commons/cli/Option;
      48: return
}
