Compiled from "AbstractTestWALReplay.java"
class org.apache.hadoop.hbase.regionserver.wal.AbstractTestWALReplay$5 implements org.apache.hadoop.fs.PathFilter {
  final org.apache.hadoop.hbase.regionserver.wal.AbstractTestWALReplay this$0;

  org.apache.hadoop.hbase.regionserver.wal.AbstractTestWALReplay$5(org.apache.hadoop.hbase.regionserver.wal.AbstractTestWALReplay);
    Code:
       0: aload_0
       1: aload_1
       2: putfield      #1                  // Field this$0:Lorg/apache/hadoop/hbase/regionserver/wal/AbstractTestWALReplay;
       5: aload_0
       6: invokespecial #2                  // Method java/lang/Object."<init>":()V
       9: return

  public boolean accept(org.apache.hadoop.fs.Path);
    Code:
       0: aload_1
       1: invokestatic  #3                  // Method org/apache/hadoop/hbase/wal/WALSplitUtil.isSequenceIdFile:(Lorg/apache/hadoop/fs/Path;)Z
       4: ifne          11
       7: iconst_1
       8: goto          12
      11: iconst_0
      12: ireturn
}
