Compiled from "AbstractRpcClient.java"
class org.apache.hadoop.hbase.ipc.AbstractRpcClient$3 implements org.apache.hbase.thirdparty.com.google.protobuf.RpcCallback<org.apache.hadoop.hbase.ipc.Call> {
  final java.util.concurrent.atomic.AtomicInteger val$counter;

  final org.apache.hadoop.hbase.ipc.HBaseRpcController val$hrc;

  final java.net.InetSocketAddress val$addr;

  final org.apache.hbase.thirdparty.com.google.protobuf.RpcCallback val$callback;

  final org.apache.hadoop.hbase.ipc.AbstractRpcClient this$0;

  org.apache.hadoop.hbase.ipc.AbstractRpcClient$3(org.apache.hadoop.hbase.ipc.AbstractRpcClient, java.util.concurrent.atomic.AtomicInteger, org.apache.hadoop.hbase.ipc.HBaseRpcController, java.net.InetSocketAddress, org.apache.hbase.thirdparty.com.google.protobuf.RpcCallback);
    Code:
       0: aload_0
       1: aload_1
       2: putfield      #1                  // Field this$0:Lorg/apache/hadoop/hbase/ipc/AbstractRpcClient;
       5: aload_0
       6: aload_2
       7: putfield      #2                  // Field val$counter:Ljava/util/concurrent/atomic/AtomicInteger;
      10: aload_0
      11: aload_3
      12: putfield      #3                  // Field val$hrc:Lorg/apache/hadoop/hbase/ipc/HBaseRpcController;
      15: aload_0
      16: aload         4
      18: putfield      #4                  // Field val$addr:Ljava/net/InetSocketAddress;
      21: aload_0
      22: aload         5
      24: putfield      #5                  // Field val$callback:Lorg/apache/hbase/thirdparty/com/google/protobuf/RpcCallback;
      27: aload_0
      28: invokespecial #6                  // Method java/lang/Object."<init>":()V
      31: return

  public void run(org.apache.hadoop.hbase.ipc.Call);
    Code:
       0: aload_0
       1: getfield      #2                  // Field val$counter:Ljava/util/concurrent/atomic/AtomicInteger;
       4: invokevirtual #7                  // Method java/util/concurrent/atomic/AtomicInteger.decrementAndGet:()I
       7: pop
       8: aload_0
       9: getfield      #1                  // Field this$0:Lorg/apache/hadoop/hbase/ipc/AbstractRpcClient;
      12: aload_1
      13: aload_0
      14: getfield      #3                  // Field val$hrc:Lorg/apache/hadoop/hbase/ipc/HBaseRpcController;
      17: aload_0
      18: getfield      #4                  // Field val$addr:Ljava/net/InetSocketAddress;
      21: aload_0
      22: getfield      #5                  // Field val$callback:Lorg/apache/hbase/thirdparty/com/google/protobuf/RpcCallback;
      25: invokestatic  #8                  // Method org/apache/hadoop/hbase/ipc/AbstractRpcClient.access$100:(Lorg/apache/hadoop/hbase/ipc/AbstractRpcClient;Lorg/apache/hadoop/hbase/ipc/Call;Lorg/apache/hadoop/hbase/ipc/HBaseRpcController;Ljava/net/InetSocketAddress;Lorg/apache/hbase/thirdparty/com/google/protobuf/RpcCallback;)V
      28: return

  public void run(java.lang.Object);
    Code:
       0: aload_0
       1: aload_1
       2: checkcast     #9                  // class org/apache/hadoop/hbase/ipc/Call
       5: invokevirtual #10                 // Method run:(Lorg/apache/hadoop/hbase/ipc/Call;)V
       8: return
}
