Compiled from "AbstractTestWALReplay.java"
class org.apache.hadoop.hbase.regionserver.wal.AbstractTestWALReplay$4$1 extends org.apache.hadoop.hbase.regionserver.HRegion {
  final java.util.concurrent.atomic.AtomicInteger val$flushcount;

  final org.apache.hadoop.hbase.regionserver.wal.AbstractTestWALReplay$4 this$1;

  org.apache.hadoop.hbase.regionserver.wal.AbstractTestWALReplay$4$1(org.apache.hadoop.hbase.regionserver.wal.AbstractTestWALReplay$4, org.apache.hadoop.fs.Path, org.apache.hadoop.hbase.wal.WAL, org.apache.hadoop.fs.FileSystem, org.apache.hadoop.conf.Configuration, org.apache.hadoop.hbase.client.RegionInfo, org.apache.hadoop.hbase.client.TableDescriptor, org.apache.hadoop.hbase.regionserver.RegionServerServices, java.util.concurrent.atomic.AtomicInteger);
    Code:
       0: aload_0
       1: aload_1
       2: putfield      #1                  // Field this$1:Lorg/apache/hadoop/hbase/regionserver/wal/AbstractTestWALReplay$4;
       5: aload_0
       6: aload         9
       8: putfield      #2                  // Field val$flushcount:Ljava/util/concurrent/atomic/AtomicInteger;
      11: aload_0
      12: aload_2
      13: aload_3
      14: aload         4
      16: aload         5
      18: aload         6
      20: aload         7
      22: aload         8
      24: invokespecial #3                  // Method org/apache/hadoop/hbase/regionserver/HRegion."<init>":(Lorg/apache/hadoop/fs/Path;Lorg/apache/hadoop/hbase/wal/WAL;Lorg/apache/hadoop/fs/FileSystem;Lorg/apache/hadoop/conf/Configuration;Lorg/apache/hadoop/hbase/client/RegionInfo;Lorg/apache/hadoop/hbase/client/TableDescriptor;Lorg/apache/hadoop/hbase/regionserver/RegionServerServices;)V
      27: return

  protected org.apache.hadoop.hbase.regionserver.HRegion$FlushResultImpl internalFlushcache(org.apache.hadoop.hbase.wal.WAL, long, java.util.Collection<org.apache.hadoop.hbase.regionserver.HStore>, org.apache.hadoop.hbase.monitoring.MonitoredTask, boolean, org.apache.hadoop.hbase.regionserver.FlushLifeCycleTracker) throws java.io.IOException;
    Code:
       0: invokestatic  #4                  // Method org/apache/hadoop/hbase/regionserver/wal/AbstractTestWALReplay.access$400:()Lorg/slf4j/Logger;
       3: ldc           #5                  // String InternalFlushCache Invoked
       5: invokeinterface #6,  2            // InterfaceMethod org/slf4j/Logger.info:(Ljava/lang/String;)V
      10: aload_0
      11: aload_1
      12: lload_2
      13: aload         4
      15: ldc           #7                  // class org/apache/hadoop/hbase/monitoring/MonitoredTask
      17: invokestatic  #8                  // Method org/mockito/Mockito.mock:(Ljava/lang/Class;)Ljava/lang/Object;
      20: checkcast     #7                  // class org/apache/hadoop/hbase/monitoring/MonitoredTask
      23: iload         6
      25: aload         7
      27: invokespecial #9                  // Method org/apache/hadoop/hbase/regionserver/HRegion.internalFlushcache:(Lorg/apache/hadoop/hbase/wal/WAL;JLjava/util/Collection;Lorg/apache/hadoop/hbase/monitoring/MonitoredTask;ZLorg/apache/hadoop/hbase/regionserver/FlushLifeCycleTracker;)Lorg/apache/hadoop/hbase/regionserver/HRegion$FlushResultImpl;
      30: astore        8
      32: aload_0
      33: getfield      #2                  // Field val$flushcount:Ljava/util/concurrent/atomic/AtomicInteger;
      36: invokevirtual #10                 // Method java/util/concurrent/atomic/AtomicInteger.incrementAndGet:()I
      39: pop
      40: aload         8
      42: areturn
}
