Compiled from "AbstractTestResultScannerCursor.java"
public abstract class org.apache.hadoop.hbase.client.AbstractTestResultScannerCursor extends org.apache.hadoop.hbase.client.AbstractTestScanCursor {
  public org.apache.hadoop.hbase.client.AbstractTestResultScannerCursor();
    Code:
       0: aload_0
       1: invokespecial #1                  // Method org/apache/hadoop/hbase/client/AbstractTestScanCursor."<init>":()V
       4: return

  protected abstract org.apache.hadoop.hbase.client.ResultScanner getScanner(org.apache.hadoop.hbase.client.Scan) throws java.lang.Exception;

  public void testHeartbeatWithSparseFilter() throws java.lang.Exception;
    Code:
       0: aload_0
       1: aload_0
       2: invokevirtual #2                  // Method createScanWithSparseFilter:()Lorg/apache/hadoop/hbase/client/Scan;
       5: invokevirtual #3                  // Method getScanner:(Lorg/apache/hadoop/hbase/client/Scan;)Lorg/apache/hadoop/hbase/client/ResultScanner;
       8: astore_1
       9: aconst_null
      10: astore_2
      11: iconst_0
      12: istore_3
      13: aload_1
      14: invokeinterface #4,  1            // InterfaceMethod org/apache/hadoop/hbase/client/ResultScanner.next:()Lorg/apache/hadoop/hbase/client/Result;
      19: dup
      20: astore        4
      22: ifnull        112
      25: iload_3
      26: getstatic     #5                  // Field NUM_ROWS:I
      29: iconst_1
      30: isub
      31: getstatic     #6                  // Field NUM_FAMILIES:I
      34: imul
      35: getstatic     #7                  // Field NUM_QUALIFIERS:I
      38: imul
      39: if_icmpge     77
      42: aload         4
      44: invokevirtual #8                  // Method org/apache/hadoop/hbase/client/Result.isCursor:()Z
      47: invokestatic  #9                  // Method org/junit/Assert.assertTrue:(Z)V
      50: getstatic     #10                 // Field ROWS:[[B
      53: iload_3
      54: getstatic     #6                  // Field NUM_FAMILIES:I
      57: idiv
      58: getstatic     #7                  // Field NUM_QUALIFIERS:I
      61: idiv
      62: aaload
      63: aload         4
      65: invokevirtual #11                 // Method org/apache/hadoop/hbase/client/Result.getCursor:()Lorg/apache/hadoop/hbase/client/Cursor;
      68: invokevirtual #12                 // Method org/apache/hadoop/hbase/client/Cursor.getRow:()[B
      71: invokestatic  #13                 // Method org/junit/Assert.assertArrayEquals:([B[B)V
      74: goto          106
      77: aload         4
      79: invokevirtual #8                  // Method org/apache/hadoop/hbase/client/Result.isCursor:()Z
      82: invokestatic  #14                 // Method org/junit/Assert.assertFalse:(Z)V
      85: getstatic     #10                 // Field ROWS:[[B
      88: iload_3
      89: getstatic     #6                  // Field NUM_FAMILIES:I
      92: idiv
      93: getstatic     #7                  // Field NUM_QUALIFIERS:I
      96: idiv
      97: aaload
      98: aload         4
     100: invokevirtual #15                 // Method org/apache/hadoop/hbase/client/Result.getRow:()[B
     103: invokestatic  #13                 // Method org/junit/Assert.assertArrayEquals:([B[B)V
     106: iinc          3, 1
     109: goto          13
     112: aload_1
     113: ifnull        191
     116: aload_2
     117: ifnull        138
     120: aload_1
     121: invokeinterface #16,  1           // InterfaceMethod org/apache/hadoop/hbase/client/ResultScanner.close:()V
     126: goto          191
     129: astore_3
     130: aload_2
     131: aload_3
     132: invokevirtual #18                 // Method java/lang/Throwable.addSuppressed:(Ljava/lang/Throwable;)V
     135: goto          191
     138: aload_1
     139: invokeinterface #16,  1           // InterfaceMethod org/apache/hadoop/hbase/client/ResultScanner.close:()V
     144: goto          191
     147: astore_3
     148: aload_3
     149: astore_2
     150: aload_3
     151: athrow
     152: astore        5
     154: aload_1
     155: ifnull        188
     158: aload_2
     159: ifnull        182
     162: aload_1
     163: invokeinterface #16,  1           // InterfaceMethod org/apache/hadoop/hbase/client/ResultScanner.close:()V
     168: goto          188
     171: astore        6
     173: aload_2
     174: aload         6
     176: invokevirtual #18                 // Method java/lang/Throwable.addSuppressed:(Ljava/lang/Throwable;)V
     179: goto          188
     182: aload_1
     183: invokeinterface #16,  1           // InterfaceMethod org/apache/hadoop/hbase/client/ResultScanner.close:()V
     188: aload         5
     190: athrow
     191: return
    Exception table:
       from    to  target type
         120   126   129   Class java/lang/Throwable
          11   112   147   Class java/lang/Throwable
          11   112   152   any
         162   168   171   Class java/lang/Throwable
         147   154   152   any

  public void testHeartbeatWithSparseFilterReversed() throws java.lang.Exception;
    Code:
       0: aload_0
       1: aload_0
       2: invokevirtual #19                 // Method createReversedScanWithSparseFilter:()Lorg/apache/hadoop/hbase/client/Scan;
       5: invokevirtual #3                  // Method getScanner:(Lorg/apache/hadoop/hbase/client/Scan;)Lorg/apache/hadoop/hbase/client/ResultScanner;
       8: astore_1
       9: aconst_null
      10: astore_2
      11: iconst_0
      12: istore_3
      13: aload_1
      14: invokeinterface #4,  1            // InterfaceMethod org/apache/hadoop/hbase/client/ResultScanner.next:()Lorg/apache/hadoop/hbase/client/Result;
      19: dup
      20: astore        4
      22: ifnull        110
      25: iload_3
      26: getstatic     #5                  // Field NUM_ROWS:I
      29: iconst_1
      30: isub
      31: getstatic     #6                  // Field NUM_FAMILIES:I
      34: imul
      35: getstatic     #7                  // Field NUM_QUALIFIERS:I
      38: imul
      39: if_icmpge     83
      42: aload         4
      44: invokevirtual #8                  // Method org/apache/hadoop/hbase/client/Result.isCursor:()Z
      47: invokestatic  #9                  // Method org/junit/Assert.assertTrue:(Z)V
      50: getstatic     #10                 // Field ROWS:[[B
      53: getstatic     #5                  // Field NUM_ROWS:I
      56: iconst_1
      57: isub
      58: iload_3
      59: getstatic     #6                  // Field NUM_FAMILIES:I
      62: idiv
      63: getstatic     #7                  // Field NUM_QUALIFIERS:I
      66: idiv
      67: isub
      68: aaload
      69: aload         4
      71: invokevirtual #11                 // Method org/apache/hadoop/hbase/client/Result.getCursor:()Lorg/apache/hadoop/hbase/client/Cursor;
      74: invokevirtual #12                 // Method org/apache/hadoop/hbase/client/Cursor.getRow:()[B
      77: invokestatic  #13                 // Method org/junit/Assert.assertArrayEquals:([B[B)V
      80: goto          104
      83: aload         4
      85: invokevirtual #8                  // Method org/apache/hadoop/hbase/client/Result.isCursor:()Z
      88: invokestatic  #14                 // Method org/junit/Assert.assertFalse:(Z)V
      91: getstatic     #10                 // Field ROWS:[[B
      94: iconst_0
      95: aaload
      96: aload         4
      98: invokevirtual #15                 // Method org/apache/hadoop/hbase/client/Result.getRow:()[B
     101: invokestatic  #13                 // Method org/junit/Assert.assertArrayEquals:([B[B)V
     104: iinc          3, 1
     107: goto          13
     110: aload_1
     111: ifnull        189
     114: aload_2
     115: ifnull        136
     118: aload_1
     119: invokeinterface #16,  1           // InterfaceMethod org/apache/hadoop/hbase/client/ResultScanner.close:()V
     124: goto          189
     127: astore_3
     128: aload_2
     129: aload_3
     130: invokevirtual #18                 // Method java/lang/Throwable.addSuppressed:(Ljava/lang/Throwable;)V
     133: goto          189
     136: aload_1
     137: invokeinterface #16,  1           // InterfaceMethod org/apache/hadoop/hbase/client/ResultScanner.close:()V
     142: goto          189
     145: astore_3
     146: aload_3
     147: astore_2
     148: aload_3
     149: athrow
     150: astore        5
     152: aload_1
     153: ifnull        186
     156: aload_2
     157: ifnull        180
     160: aload_1
     161: invokeinterface #16,  1           // InterfaceMethod org/apache/hadoop/hbase/client/ResultScanner.close:()V
     166: goto          186
     169: astore        6
     171: aload_2
     172: aload         6
     174: invokevirtual #18                 // Method java/lang/Throwable.addSuppressed:(Ljava/lang/Throwable;)V
     177: goto          186
     180: aload_1
     181: invokeinterface #16,  1           // InterfaceMethod org/apache/hadoop/hbase/client/ResultScanner.close:()V
     186: aload         5
     188: athrow
     189: return
    Exception table:
       from    to  target type
         118   124   127   Class java/lang/Throwable
          11   110   145   Class java/lang/Throwable
          11   110   150   any
         160   166   169   Class java/lang/Throwable
         145   152   150   any

  public void testSizeLimit() throws java.io.IOException;
    Code:
       0: getstatic     #20                 // Field TEST_UTIL:Lorg/apache/hadoop/hbase/HBaseTestingUtility;
       3: invokevirtual #21                 // Method org/apache/hadoop/hbase/HBaseTestingUtility.getConnection:()Lorg/apache/hadoop/hbase/client/Connection;
       6: getstatic     #22                 // Field TABLE_NAME:Lorg/apache/hadoop/hbase/TableName;
       9: invokeinterface #23,  2           // InterfaceMethod org/apache/hadoop/hbase/client/Connection.getTable:(Lorg/apache/hadoop/hbase/TableName;)Lorg/apache/hadoop/hbase/client/Table;
      14: aload_0
      15: invokevirtual #24                 // Method createScanWithSizeLimit:()Lorg/apache/hadoop/hbase/client/Scan;
      18: invokeinterface #25,  2           // InterfaceMethod org/apache/hadoop/hbase/client/Table.getScanner:(Lorg/apache/hadoop/hbase/client/Scan;)Lorg/apache/hadoop/hbase/client/ResultScanner;
      23: astore_1
      24: aconst_null
      25: astore_2
      26: iconst_0
      27: istore_3
      28: aload_1
      29: invokeinterface #4,  1            // InterfaceMethod org/apache/hadoop/hbase/client/ResultScanner.next:()Lorg/apache/hadoop/hbase/client/Result;
      34: dup
      35: astore        4
      37: ifnull        131
      40: iload_3
      41: getstatic     #6                  // Field NUM_FAMILIES:I
      44: getstatic     #7                  // Field NUM_QUALIFIERS:I
      47: imul
      48: irem
      49: getstatic     #6                  // Field NUM_FAMILIES:I
      52: getstatic     #7                  // Field NUM_QUALIFIERS:I
      55: imul
      56: iconst_1
      57: isub
      58: if_icmpeq     96
      61: aload         4
      63: invokevirtual #8                  // Method org/apache/hadoop/hbase/client/Result.isCursor:()Z
      66: invokestatic  #9                  // Method org/junit/Assert.assertTrue:(Z)V
      69: getstatic     #10                 // Field ROWS:[[B
      72: iload_3
      73: getstatic     #6                  // Field NUM_FAMILIES:I
      76: idiv
      77: getstatic     #7                  // Field NUM_QUALIFIERS:I
      80: idiv
      81: aaload
      82: aload         4
      84: invokevirtual #11                 // Method org/apache/hadoop/hbase/client/Result.getCursor:()Lorg/apache/hadoop/hbase/client/Cursor;
      87: invokevirtual #12                 // Method org/apache/hadoop/hbase/client/Cursor.getRow:()[B
      90: invokestatic  #13                 // Method org/junit/Assert.assertArrayEquals:([B[B)V
      93: goto          125
      96: aload         4
      98: invokevirtual #8                  // Method org/apache/hadoop/hbase/client/Result.isCursor:()Z
     101: invokestatic  #14                 // Method org/junit/Assert.assertFalse:(Z)V
     104: getstatic     #10                 // Field ROWS:[[B
     107: iload_3
     108: getstatic     #6                  // Field NUM_FAMILIES:I
     111: idiv
     112: getstatic     #7                  // Field NUM_QUALIFIERS:I
     115: idiv
     116: aaload
     117: aload         4
     119: invokevirtual #15                 // Method org/apache/hadoop/hbase/client/Result.getRow:()[B
     122: invokestatic  #13                 // Method org/junit/Assert.assertArrayEquals:([B[B)V
     125: iinc          3, 1
     128: goto          28
     131: aload_1
     132: ifnull        210
     135: aload_2
     136: ifnull        157
     139: aload_1
     140: invokeinterface #16,  1           // InterfaceMethod org/apache/hadoop/hbase/client/ResultScanner.close:()V
     145: goto          210
     148: astore_3
     149: aload_2
     150: aload_3
     151: invokevirtual #18                 // Method java/lang/Throwable.addSuppressed:(Ljava/lang/Throwable;)V
     154: goto          210
     157: aload_1
     158: invokeinterface #16,  1           // InterfaceMethod org/apache/hadoop/hbase/client/ResultScanner.close:()V
     163: goto          210
     166: astore_3
     167: aload_3
     168: astore_2
     169: aload_3
     170: athrow
     171: astore        5
     173: aload_1
     174: ifnull        207
     177: aload_2
     178: ifnull        201
     181: aload_1
     182: invokeinterface #16,  1           // InterfaceMethod org/apache/hadoop/hbase/client/ResultScanner.close:()V
     187: goto          207
     190: astore        6
     192: aload_2
     193: aload         6
     195: invokevirtual #18                 // Method java/lang/Throwable.addSuppressed:(Ljava/lang/Throwable;)V
     198: goto          207
     201: aload_1
     202: invokeinterface #16,  1           // InterfaceMethod org/apache/hadoop/hbase/client/ResultScanner.close:()V
     207: aload         5
     209: athrow
     210: return
    Exception table:
       from    to  target type
         139   145   148   Class java/lang/Throwable
          26   131   166   Class java/lang/Throwable
          26   131   171   any
         181   187   190   Class java/lang/Throwable
         166   173   171   any
}
