Compiled from "AbstractHBaseTool.java"
class org.apache.hadoop.hbase.util.AbstractHBaseTool$OptionsOrderComparator implements java.util.Comparator<org.apache.hbase.thirdparty.org.apache.commons.cli.Option> {
  final org.apache.hadoop.hbase.util.AbstractHBaseTool this$0;

  public int compare(org.apache.hbase.thirdparty.org.apache.commons.cli.Option, org.apache.hbase.thirdparty.org.apache.commons.cli.Option);
    Code:
       0: aload_0
       1: getfield      #2                  // Field this$0:Lorg/apache/hadoop/hbase/util/AbstractHBaseTool;
       4: invokestatic  #4                  // Method org/apache/hadoop/hbase/util/AbstractHBaseTool.access$000:(Lorg/apache/hadoop/hbase/util/AbstractHBaseTool;)Ljava/util/HashMap;
       7: aload_1
       8: invokevirtual #5                  // Method java/util/HashMap.get:(Ljava/lang/Object;)Ljava/lang/Object;
      11: checkcast     #6                  // class java/lang/Integer
      14: invokevirtual #7                  // Method java/lang/Integer.intValue:()I
      17: aload_0
      18: getfield      #2                  // Field this$0:Lorg/apache/hadoop/hbase/util/AbstractHBaseTool;
      21: invokestatic  #4                  // Method org/apache/hadoop/hbase/util/AbstractHBaseTool.access$000:(Lorg/apache/hadoop/hbase/util/AbstractHBaseTool;)Ljava/util/HashMap;
      24: aload_2
      25: invokevirtual #5                  // Method java/util/HashMap.get:(Ljava/lang/Object;)Ljava/lang/Object;
      28: checkcast     #6                  // class java/lang/Integer
      31: invokevirtual #7                  // Method java/lang/Integer.intValue:()I
      34: isub
      35: ireturn

  public int compare(java.lang.Object, java.lang.Object);
    Code:
       0: aload_0
       1: aload_1
       2: checkcast     #8                  // class org/apache/hbase/thirdparty/org/apache/commons/cli/Option
       5: aload_2
       6: checkcast     #8                  // class org/apache/hbase/thirdparty/org/apache/commons/cli/Option
       9: invokevirtual #9                  // Method compare:(Lorg/apache/hbase/thirdparty/org/apache/commons/cli/Option;Lorg/apache/hbase/thirdparty/org/apache/commons/cli/Option;)I
      12: ireturn

  org.apache.hadoop.hbase.util.AbstractHBaseTool$OptionsOrderComparator(org.apache.hadoop.hbase.util.AbstractHBaseTool, org.apache.hadoop.hbase.util.AbstractHBaseTool$1);
    Code:
       0: aload_0
       1: aload_1
       2: invokespecial #1                  // Method "<init>":(Lorg/apache/hadoop/hbase/util/AbstractHBaseTool;)V
       5: return
}
