Compiled from "AbstractTestWALReplay.java"
class org.apache.hadoop.hbase.regionserver.wal.AbstractTestWALReplay$MockWAL extends org.apache.hadoop.hbase.regionserver.wal.FSHLog {
  boolean doCompleteCacheFlush;

  public org.apache.hadoop.hbase.regionserver.wal.AbstractTestWALReplay$MockWAL(org.apache.hadoop.fs.FileSystem, org.apache.hadoop.fs.Path, java.lang.String, org.apache.hadoop.conf.Configuration) throws java.io.IOException;
    Code:
       0: aload_0
       1: aload_1
       2: aload_2
       3: aload_3
       4: ldc           #2                  // String oldWALs
       6: aload         4
       8: aconst_null
       9: iconst_1
      10: aconst_null
      11: aconst_null
      12: invokespecial #3                  // Method org/apache/hadoop/hbase/regionserver/wal/FSHLog."<init>":(Lorg/apache/hadoop/fs/FileSystem;Lorg/apache/hadoop/fs/Path;Ljava/lang/String;Ljava/lang/String;Lorg/apache/hadoop/conf/Configuration;Ljava/util/List;ZLjava/lang/String;Ljava/lang/String;)V
      15: aload_0
      16: iconst_0
      17: putfield      #4                  // Field doCompleteCacheFlush:Z
      20: return

  public void completeCacheFlush(byte[]);
    Code:
       0: aload_0
       1: getfield      #4                  // Field doCompleteCacheFlush:Z
       4: ifne          8
       7: return
       8: aload_0
       9: aload_1
      10: invokespecial #5                  // Method org/apache/hadoop/hbase/regionserver/wal/FSHLog.completeCacheFlush:([B)V
      13: return
}
