Compiled from "AbstractTestCIRpcTimeout.java"
public abstract class org.apache.hadoop.hbase.client.AbstractTestCIRpcTimeout extends org.apache.hadoop.hbase.client.AbstractTestCITimeout {
  public org.apache.hadoop.hbase.client.AbstractTestCIRpcTimeout();
    Code:
       0: aload_0
       1: invokespecial #1                  // Method org/apache/hadoop/hbase/client/AbstractTestCITimeout."<init>":()V
       4: return

  public void setUp() throws java.io.IOException;
    Code:
       0: aload_0
       1: aload_0
       2: getfield      #2                  // Field name:Lorg/junit/rules/TestName;
       5: invokevirtual #3                  // Method org/junit/rules/TestName.getMethodName:()Ljava/lang/String;
       8: invokestatic  #4                  // Method org/apache/hadoop/hbase/TableName.valueOf:(Ljava/lang/String;)Lorg/apache/hadoop/hbase/TableName;
      11: putfield      #5                  // Field tableName:Lorg/apache/hadoop/hbase/TableName;
      14: aload_0
      15: getfield      #5                  // Field tableName:Lorg/apache/hadoop/hbase/TableName;
      18: invokestatic  #6                  // Method org/apache/hadoop/hbase/client/TableDescriptorBuilder.newBuilder:(Lorg/apache/hadoop/hbase/TableName;)Lorg/apache/hadoop/hbase/client/TableDescriptorBuilder;
      21: ldc           #7                  // class org/apache/hadoop/hbase/client/AbstractTestCITimeout$SleepCoprocessor
      23: invokevirtual #8                  // Method java/lang/Class.getName:()Ljava/lang/String;
      26: invokevirtual #9                  // Method org/apache/hadoop/hbase/client/TableDescriptorBuilder.setCoprocessor:(Ljava/lang/String;)Lorg/apache/hadoop/hbase/client/TableDescriptorBuilder;
      29: getstatic     #10                 // Field FAM_NAM:[B
      32: invokestatic  #11                 // Method org/apache/hadoop/hbase/client/ColumnFamilyDescriptorBuilder.of:([B)Lorg/apache/hadoop/hbase/client/ColumnFamilyDescriptor;
      35: invokevirtual #12                 // Method org/apache/hadoop/hbase/client/TableDescriptorBuilder.setColumnFamily:(Lorg/apache/hadoop/hbase/client/ColumnFamilyDescriptor;)Lorg/apache/hadoop/hbase/client/TableDescriptorBuilder;
      38: invokevirtual #13                 // Method org/apache/hadoop/hbase/client/TableDescriptorBuilder.build:()Lorg/apache/hadoop/hbase/client/TableDescriptor;
      41: astore_1
      42: getstatic     #14                 // Field TEST_UTIL:Lorg/apache/hadoop/hbase/HBaseTestingUtility;
      45: invokevirtual #15                 // Method org/apache/hadoop/hbase/HBaseTestingUtility.getAdmin:()Lorg/apache/hadoop/hbase/client/Admin;
      48: aload_1
      49: invokeinterface #16,  2           // InterfaceMethod org/apache/hadoop/hbase/client/Admin.createTable:(Lorg/apache/hadoop/hbase/client/TableDescriptor;)V
      54: return

  protected abstract void execute(org.apache.hadoop.hbase.client.Table) throws java.io.IOException;

  public void testRpcTimeout() throws java.io.IOException;
    Code:
       0: new           #17                 // class org/apache/hadoop/conf/Configuration
       3: dup
       4: getstatic     #14                 // Field TEST_UTIL:Lorg/apache/hadoop/hbase/HBaseTestingUtility;
       7: invokevirtual #18                 // Method org/apache/hadoop/hbase/HBaseTestingUtility.getConfiguration:()Lorg/apache/hadoop/conf/Configuration;
      10: invokespecial #19                 // Method org/apache/hadoop/conf/Configuration."<init>":(Lorg/apache/hadoop/conf/Configuration;)V
      13: astore_1
      14: getstatic     #14                 // Field TEST_UTIL:Lorg/apache/hadoop/hbase/HBaseTestingUtility;
      17: invokevirtual #20                 // Method org/apache/hadoop/hbase/HBaseTestingUtility.getConnection:()Lorg/apache/hadoop/hbase/client/Connection;
      20: aload_0
      21: getfield      #5                  // Field tableName:Lorg/apache/hadoop/hbase/TableName;
      24: aconst_null
      25: invokeinterface #21,  3           // InterfaceMethod org/apache/hadoop/hbase/client/Connection.getTableBuilder:(Lorg/apache/hadoop/hbase/TableName;Ljava/util/concurrent/ExecutorService;)Lorg/apache/hadoop/hbase/client/TableBuilder;
      30: sipush        2500
      33: invokeinterface #22,  2           // InterfaceMethod org/apache/hadoop/hbase/client/TableBuilder.setRpcTimeout:(I)Lorg/apache/hadoop/hbase/client/TableBuilder;
      38: sipush        2500
      41: invokeinterface #23,  2           // InterfaceMethod org/apache/hadoop/hbase/client/TableBuilder.setReadRpcTimeout:(I)Lorg/apache/hadoop/hbase/client/TableBuilder;
      46: sipush        2500
      49: invokeinterface #24,  2           // InterfaceMethod org/apache/hadoop/hbase/client/TableBuilder.setWriteRpcTimeout:(I)Lorg/apache/hadoop/hbase/client/TableBuilder;
      54: ldc           #25                 // int 500000
      56: invokeinterface #26,  2           // InterfaceMethod org/apache/hadoop/hbase/client/TableBuilder.setOperationTimeout:(I)Lorg/apache/hadoop/hbase/client/TableBuilder;
      61: invokeinterface #27,  1           // InterfaceMethod org/apache/hadoop/hbase/client/TableBuilder.build:()Lorg/apache/hadoop/hbase/client/Table;
      66: astore_2
      67: aconst_null
      68: astore_3
      69: aload_0
      70: aload_2
      71: invokevirtual #28                 // Method execute:(Lorg/apache/hadoop/hbase/client/Table;)V
      74: ldc           #29                 // String Get should not have succeeded
      76: invokestatic  #30                 // Method org/junit/Assert.fail:(Ljava/lang/String;)V
      79: aload_2
      80: ifnull        163
      83: aload_3
      84: ifnull        107
      87: aload_2
      88: invokeinterface #31,  1           // InterfaceMethod org/apache/hadoop/hbase/client/Table.close:()V
      93: goto          163
      96: astore        4
      98: aload_3
      99: aload         4
     101: invokevirtual #33                 // Method java/lang/Throwable.addSuppressed:(Ljava/lang/Throwable;)V
     104: goto          163
     107: aload_2
     108: invokeinterface #31,  1           // InterfaceMethod org/apache/hadoop/hbase/client/Table.close:()V
     113: goto          163
     116: astore        4
     118: aload         4
     120: astore_3
     121: aload         4
     123: athrow
     124: astore        5
     126: aload_2
     127: ifnull        160
     130: aload_3
     131: ifnull        154
     134: aload_2
     135: invokeinterface #31,  1           // InterfaceMethod org/apache/hadoop/hbase/client/Table.close:()V
     140: goto          160
     143: astore        6
     145: aload_3
     146: aload         6
     148: invokevirtual #33                 // Method java/lang/Throwable.addSuppressed:(Ljava/lang/Throwable;)V
     151: goto          160
     154: aload_2
     155: invokeinterface #31,  1           // InterfaceMethod org/apache/hadoop/hbase/client/Table.close:()V
     160: aload         5
     162: athrow
     163: goto          178
     166: astore_2
     167: getstatic     #35                 // Field LOG:Lorg/slf4j/Logger;
     170: ldc           #36                 // String We received an exception, as expected
     172: aload_2
     173: invokeinterface #37,  3           // InterfaceMethod org/slf4j/Logger.info:(Ljava/lang/String;Ljava/lang/Throwable;)V
     178: aload_1
     179: ldc           #39                 // String hbase.rpc.timeout
     181: sipush        2500
     184: invokevirtual #40                 // Method org/apache/hadoop/conf/Configuration.setInt:(Ljava/lang/String;I)V
     187: aload_1
     188: ldc           #41                 // String hbase.rpc.read.timeout
     190: sipush        2500
     193: invokevirtual #40                 // Method org/apache/hadoop/conf/Configuration.setInt:(Ljava/lang/String;I)V
     196: aload_1
     197: ldc           #42                 // String hbase.rpc.write.timeout
     199: sipush        2500
     202: invokevirtual #40                 // Method org/apache/hadoop/conf/Configuration.setInt:(Ljava/lang/String;I)V
     205: aload_1
     206: ldc           #43                 // String hbase.client.operation.timeout
     208: ldc           #25                 // int 500000
     210: invokevirtual #40                 // Method org/apache/hadoop/conf/Configuration.setInt:(Ljava/lang/String;I)V
     213: aload_1
     214: invokestatic  #44                 // Method org/apache/hadoop/hbase/client/ConnectionFactory.createConnection:(Lorg/apache/hadoop/conf/Configuration;)Lorg/apache/hadoop/hbase/client/Connection;
     217: astore_2
     218: aconst_null
     219: astore_3
     220: aload_2
     221: aload_0
     222: getfield      #5                  // Field tableName:Lorg/apache/hadoop/hbase/TableName;
     225: invokeinterface #45,  2           // InterfaceMethod org/apache/hadoop/hbase/client/Connection.getTable:(Lorg/apache/hadoop/hbase/TableName;)Lorg/apache/hadoop/hbase/client/Table;
     230: astore        4
     232: aconst_null
     233: astore        5
     235: aload_0
     236: aload         4
     238: invokevirtual #28                 // Method execute:(Lorg/apache/hadoop/hbase/client/Table;)V
     241: ldc           #29                 // String Get should not have succeeded
     243: invokestatic  #30                 // Method org/junit/Assert.fail:(Ljava/lang/String;)V
     246: aload         4
     248: ifnull        341
     251: aload         5
     253: ifnull        278
     256: aload         4
     258: invokeinterface #31,  1           // InterfaceMethod org/apache/hadoop/hbase/client/Table.close:()V
     263: goto          341
     266: astore        6
     268: aload         5
     270: aload         6
     272: invokevirtual #33                 // Method java/lang/Throwable.addSuppressed:(Ljava/lang/Throwable;)V
     275: goto          341
     278: aload         4
     280: invokeinterface #31,  1           // InterfaceMethod org/apache/hadoop/hbase/client/Table.close:()V
     285: goto          341
     288: astore        6
     290: aload         6
     292: astore        5
     294: aload         6
     296: athrow
     297: astore        7
     299: aload         4
     301: ifnull        338
     304: aload         5
     306: ifnull        331
     309: aload         4
     311: invokeinterface #31,  1           // InterfaceMethod org/apache/hadoop/hbase/client/Table.close:()V
     316: goto          338
     319: astore        8
     321: aload         5
     323: aload         8
     325: invokevirtual #33                 // Method java/lang/Throwable.addSuppressed:(Ljava/lang/Throwable;)V
     328: goto          338
     331: aload         4
     333: invokeinterface #31,  1           // InterfaceMethod org/apache/hadoop/hbase/client/Table.close:()V
     338: aload         7
     340: athrow
     341: goto          358
     344: astore        4
     346: getstatic     #35                 // Field LOG:Lorg/slf4j/Logger;
     349: ldc           #36                 // String We received an exception, as expected
     351: aload         4
     353: invokeinterface #37,  3           // InterfaceMethod org/slf4j/Logger.info:(Ljava/lang/String;Ljava/lang/Throwable;)V
     358: aload_2
     359: ifnull        442
     362: aload_3
     363: ifnull        386
     366: aload_2
     367: invokeinterface #46,  1           // InterfaceMethod org/apache/hadoop/hbase/client/Connection.close:()V
     372: goto          442
     375: astore        4
     377: aload_3
     378: aload         4
     380: invokevirtual #33                 // Method java/lang/Throwable.addSuppressed:(Ljava/lang/Throwable;)V
     383: goto          442
     386: aload_2
     387: invokeinterface #46,  1           // InterfaceMethod org/apache/hadoop/hbase/client/Connection.close:()V
     392: goto          442
     395: astore        4
     397: aload         4
     399: astore_3
     400: aload         4
     402: athrow
     403: astore        9
     405: aload_2
     406: ifnull        439
     409: aload_3
     410: ifnull        433
     413: aload_2
     414: invokeinterface #46,  1           // InterfaceMethod org/apache/hadoop/hbase/client/Connection.close:()V
     419: goto          439
     422: astore        10
     424: aload_3
     425: aload         10
     427: invokevirtual #33                 // Method java/lang/Throwable.addSuppressed:(Ljava/lang/Throwable;)V
     430: goto          439
     433: aload_2
     434: invokeinterface #46,  1           // InterfaceMethod org/apache/hadoop/hbase/client/Connection.close:()V
     439: aload         9
     441: athrow
     442: return
    Exception table:
       from    to  target type
          87    93    96   Class java/lang/Throwable
          69    79   116   Class java/lang/Throwable
          69    79   124   any
         134   140   143   Class java/lang/Throwable
         116   126   124   any
          14   163   166   Class org/apache/hadoop/hbase/client/RetriesExhaustedException
         256   263   266   Class java/lang/Throwable
         235   246   288   Class java/lang/Throwable
         235   246   297   any
         309   316   319   Class java/lang/Throwable
         288   299   297   any
         220   341   344   Class org/apache/hadoop/hbase/client/RetriesExhaustedException
         366   372   375   Class java/lang/Throwable
         220   358   395   Class java/lang/Throwable
         220   358   403   any
         413   419   422   Class java/lang/Throwable
         395   405   403   any

  static {};
    Code:
       0: ldc           #47                 // class org/apache/hadoop/hbase/client/AbstractTestCIRpcTimeout
       2: invokestatic  #48                 // Method org/slf4j/LoggerFactory.getLogger:(Ljava/lang/Class;)Lorg/slf4j/Logger;
       5: putstatic     #35                 // Field LOG:Lorg/slf4j/Logger;
       8: return
}
