Compiled from "AbstractFSWALProvider.java"
final class org.apache.hadoop.hbase.wal.AbstractFSWALProvider$1 implements org.apache.hadoop.hbase.util.CancelableProgressable {
  final org.apache.hadoop.fs.Path val$path;

  org.apache.hadoop.hbase.wal.AbstractFSWALProvider$1(org.apache.hadoop.fs.Path);
    Code:
       0: aload_0
       1: aload_1
       2: putfield      #1                  // Field val$path:Lorg/apache/hadoop/fs/Path;
       5: aload_0
       6: invokespecial #2                  // Method java/lang/Object."<init>":()V
       9: return

  public boolean progress();
    Code:
       0: invokestatic  #3                  // Method org/apache/hadoop/hbase/wal/AbstractFSWALProvider.access$000:()Lorg/slf4j/Logger;
       3: new           #4                  // class java/lang/StringBuilder
       6: dup
       7: invokespecial #5                  // Method java/lang/StringBuilder."<init>":()V
      10: ldc           #6                  // String Still trying to recover WAL lease:
      12: invokevirtual #7                  // Method java/lang/StringBuilder.append:(Ljava/lang/String;)Ljava/lang/StringBuilder;
      15: aload_0
      16: getfield      #1                  // Field val$path:Lorg/apache/hadoop/fs/Path;
      19: invokevirtual #8                  // Method java/lang/StringBuilder.append:(Ljava/lang/Object;)Ljava/lang/StringBuilder;
      22: invokevirtual #9                  // Method java/lang/StringBuilder.toString:()Ljava/lang/String;
      25: invokeinterface #10,  2           // InterfaceMethod org/slf4j/Logger.debug:(Ljava/lang/String;)V
      30: iconst_1
      31: ireturn
}
