Compiled from "AbstractFSWAL.java"
class org.apache.hadoop.hbase.regionserver.wal.AbstractFSWAL$1 implements org.apache.hadoop.fs.PathFilter {
  final org.apache.hadoop.hbase.regionserver.wal.AbstractFSWAL this$0;

  org.apache.hadoop.hbase.regionserver.wal.AbstractFSWAL$1(org.apache.hadoop.hbase.regionserver.wal.AbstractFSWAL);
    Code:
       0: aload_0
       1: aload_1
       2: putfield      #1                  // Field this$0:Lorg/apache/hadoop/hbase/regionserver/wal/AbstractFSWAL;
       5: aload_0
       6: invokespecial #2                  // Method java/lang/Object."<init>":()V
       9: return

  public boolean accept(org.apache.hadoop.fs.Path);
    Code:
       0: aload_1
       1: invokevirtual #3                  // Method org/apache/hadoop/fs/Path.toString:()Ljava/lang/String;
       4: astore_2
       5: aload_2
       6: aload_0
       7: getfield      #1                  // Field this$0:Lorg/apache/hadoop/hbase/regionserver/wal/AbstractFSWAL;
      10: getfield      #4                  // Field org/apache/hadoop/hbase/regionserver/wal/AbstractFSWAL.prefixPathStr:Ljava/lang/String;
      13: invokevirtual #5                  // Method java/lang/String.startsWith:(Ljava/lang/String;)Z
      16: ifne          21
      19: iconst_0
      20: ireturn
      21: aload_0
      22: getfield      #1                  // Field this$0:Lorg/apache/hadoop/hbase/regionserver/wal/AbstractFSWAL;
      25: getfield      #6                  // Field org/apache/hadoop/hbase/regionserver/wal/AbstractFSWAL.walFileSuffix:Ljava/lang/String;
      28: invokevirtual #7                  // Method java/lang/String.isEmpty:()Z
      31: ifeq          52
      34: aload_2
      35: aload_0
      36: getfield      #1                  // Field this$0:Lorg/apache/hadoop/hbase/regionserver/wal/AbstractFSWAL;
      39: getfield      #4                  // Field org/apache/hadoop/hbase/regionserver/wal/AbstractFSWAL.prefixPathStr:Ljava/lang/String;
      42: invokevirtual #8                  // Method java/lang/String.length:()I
      45: invokevirtual #9                  // Method java/lang/String.substring:(I)Ljava/lang/String;
      48: invokestatic  #10                 // Method org/apache/commons/lang3/StringUtils.isNumeric:(Ljava/lang/CharSequence;)Z
      51: ireturn
      52: aload_2
      53: aload_0
      54: getfield      #1                  // Field this$0:Lorg/apache/hadoop/hbase/regionserver/wal/AbstractFSWAL;
      57: getfield      #6                  // Field org/apache/hadoop/hbase/regionserver/wal/AbstractFSWAL.walFileSuffix:Ljava/lang/String;
      60: invokevirtual #11                 // Method java/lang/String.endsWith:(Ljava/lang/String;)Z
      63: ifne          68
      66: iconst_0
      67: ireturn
      68: iconst_1
      69: ireturn
}
