Compiled from "AbstractTestWALReplay.java"
class org.apache.hadoop.hbase.regionserver.wal.AbstractTestWALReplay$6 implements org.mockito.stubbing.Answer<org.apache.hadoop.fs.FSDataInputStream> {
  final long val$headerLength;

  final org.apache.hadoop.hbase.regionserver.wal.AbstractTestWALReplay this$0;

  org.apache.hadoop.hbase.regionserver.wal.AbstractTestWALReplay$6(org.apache.hadoop.hbase.regionserver.wal.AbstractTestWALReplay, long);
    Code:
       0: aload_0
       1: aload_1
       2: putfield      #1                  // Field this$0:Lorg/apache/hadoop/hbase/regionserver/wal/AbstractTestWALReplay;
       5: aload_0
       6: lload_2
       7: putfield      #2                  // Field val$headerLength:J
      10: aload_0
      11: invokespecial #3                  // Method java/lang/Object."<init>":()V
      14: return

  public org.apache.hadoop.fs.FSDataInputStream answer(org.mockito.invocation.InvocationOnMock) throws java.lang.Throwable;
    Code:
       0: aload_1
       1: invokeinterface #4,  1            // InterfaceMethod org/mockito/invocation/InvocationOnMock.callRealMethod:()Ljava/lang/Object;
       6: checkcast     #5                  // class org/apache/hadoop/fs/FSDataInputStream
       9: astore_2
      10: ldc           #6                  // class java/io/FilterInputStream
      12: ldc           #7                  // String in
      14: invokevirtual #8                  // Method java/lang/Class.getDeclaredField:(Ljava/lang/String;)Ljava/lang/reflect/Field;
      17: astore_3
      18: aload_3
      19: iconst_1
      20: invokevirtual #9                  // Method java/lang/reflect/Field.setAccessible:(Z)V
      23: aload_3
      24: aload_2
      25: invokevirtual #10                 // Method java/lang/reflect/Field.get:(Ljava/lang/Object;)Ljava/lang/Object;
      28: checkcast     #11                 // class org/apache/hadoop/hdfs/DFSInputStream
      31: astore        4
      33: aload         4
      35: invokestatic  #12                 // Method org/mockito/Mockito.spy:(Ljava/lang/Object;)Ljava/lang/Object;
      38: checkcast     #11                 // class org/apache/hadoop/hdfs/DFSInputStream
      41: astore        5
      43: new           #13                 // class org/apache/hadoop/hbase/regionserver/wal/AbstractTestWALReplay$6$1
      46: dup
      47: aload_0
      48: invokespecial #14                 // Method org/apache/hadoop/hbase/regionserver/wal/AbstractTestWALReplay$6$1."<init>":(Lorg/apache/hadoop/hbase/regionserver/wal/AbstractTestWALReplay$6;)V
      51: invokestatic  #15                 // Method org/mockito/Mockito.doAnswer:(Lorg/mockito/stubbing/Answer;)Lorg/mockito/stubbing/Stubber;
      54: aload         5
      56: invokeinterface #16,  2           // InterfaceMethod org/mockito/stubbing/Stubber.when:(Ljava/lang/Object;)Ljava/lang/Object;
      61: checkcast     #11                 // class org/apache/hadoop/hdfs/DFSInputStream
      64: ldc           #17                 // class "[B"
      66: invokestatic  #18                 // Method org/mockito/ArgumentMatchers.any:(Ljava/lang/Class;)Ljava/lang/Object;
      69: checkcast     #17                 // class "[B"
      72: invokestatic  #19                 // Method org/mockito/ArgumentMatchers.anyInt:()I
      75: invokestatic  #19                 // Method org/mockito/ArgumentMatchers.anyInt:()I
      78: invokevirtual #20                 // Method org/apache/hadoop/hdfs/DFSInputStream.read:([BII)I
      81: pop
      82: new           #21                 // class org/apache/hadoop/hbase/regionserver/wal/AbstractTestWALReplay$6$2
      85: dup
      86: aload_0
      87: aload         4
      89: invokespecial #22                 // Method org/apache/hadoop/hbase/regionserver/wal/AbstractTestWALReplay$6$2."<init>":(Lorg/apache/hadoop/hbase/regionserver/wal/AbstractTestWALReplay$6;Lorg/apache/hadoop/hdfs/DFSInputStream;)V
      92: invokestatic  #15                 // Method org/mockito/Mockito.doAnswer:(Lorg/mockito/stubbing/Answer;)Lorg/mockito/stubbing/Stubber;
      95: aload         5
      97: invokeinterface #16,  2           // InterfaceMethod org/mockito/stubbing/Stubber.when:(Ljava/lang/Object;)Ljava/lang/Object;
     102: checkcast     #11                 // class org/apache/hadoop/hdfs/DFSInputStream
     105: invokevirtual #23                 // Method org/apache/hadoop/hdfs/DFSInputStream.close:()V
     108: aload_3
     109: aload_2
     110: aload         5
     112: invokevirtual #24                 // Method java/lang/reflect/Field.set:(Ljava/lang/Object;Ljava/lang/Object;)V
     115: aload_2
     116: areturn

  public java.lang.Object answer(org.mockito.invocation.InvocationOnMock) throws java.lang.Throwable;
    Code:
       0: aload_0
       1: aload_1
       2: invokevirtual #25                 // Method answer:(Lorg/mockito/invocation/InvocationOnMock;)Lorg/apache/hadoop/fs/FSDataInputStream;
       5: areturn
}
