Compiled from "AbstractTestScanQueryMatcher.java"
public class org.apache.hadoop.hbase.regionserver.querymatcher.AbstractTestScanQueryMatcher {
  protected org.apache.hadoop.conf.Configuration conf;

  protected byte[] row1;

  protected byte[] row2;

  protected byte[] row3;

  protected byte[] fam1;

  protected byte[] fam2;

  protected byte[] col1;

  protected byte[] col2;

  protected byte[] col3;

  protected byte[] col4;

  protected byte[] col5;

  protected byte[] data;

  protected org.apache.hadoop.hbase.client.Get get;

  protected long ttl;

  protected org.apache.hadoop.hbase.CellComparator rowComparator;

  protected org.apache.hadoop.hbase.client.Scan scan;

  public org.apache.hadoop.hbase.regionserver.querymatcher.AbstractTestScanQueryMatcher();
    Code:
       0: aload_0
       1: invokespecial #1                  // Method java/lang/Object."<init>":()V
       4: aload_0
       5: ldc2_w        #3                  // long 9223372036854775807l
       8: putfield      #5                  // Field ttl:J
      11: return

  public void setUp() throws java.lang.Exception;
    Code:
       0: aload_0
       1: invokestatic  #6                  // Method org/apache/hadoop/hbase/HBaseConfiguration.create:()Lorg/apache/hadoop/conf/Configuration;
       4: putfield      #7                  // Field conf:Lorg/apache/hadoop/conf/Configuration;
       7: aload_0
       8: ldc           #8                  // String row1
      10: invokestatic  #9                  // Method org/apache/hadoop/hbase/util/Bytes.toBytes:(Ljava/lang/String;)[B
      13: putfield      #10                 // Field row1:[B
      16: aload_0
      17: ldc           #11                 // String row2
      19: invokestatic  #9                  // Method org/apache/hadoop/hbase/util/Bytes.toBytes:(Ljava/lang/String;)[B
      22: putfield      #12                 // Field row2:[B
      25: aload_0
      26: ldc           #13                 // String row3
      28: invokestatic  #9                  // Method org/apache/hadoop/hbase/util/Bytes.toBytes:(Ljava/lang/String;)[B
      31: putfield      #14                 // Field row3:[B
      34: aload_0
      35: ldc           #15                 // String fam1
      37: invokestatic  #9                  // Method org/apache/hadoop/hbase/util/Bytes.toBytes:(Ljava/lang/String;)[B
      40: putfield      #16                 // Field fam1:[B
      43: aload_0
      44: ldc           #17                 // String fam2
      46: invokestatic  #9                  // Method org/apache/hadoop/hbase/util/Bytes.toBytes:(Ljava/lang/String;)[B
      49: putfield      #18                 // Field fam2:[B
      52: aload_0
      53: ldc           #19                 // String col1
      55: invokestatic  #9                  // Method org/apache/hadoop/hbase/util/Bytes.toBytes:(Ljava/lang/String;)[B
      58: putfield      #20                 // Field col1:[B
      61: aload_0
      62: ldc           #21                 // String col2
      64: invokestatic  #9                  // Method org/apache/hadoop/hbase/util/Bytes.toBytes:(Ljava/lang/String;)[B
      67: putfield      #22                 // Field col2:[B
      70: aload_0
      71: ldc           #23                 // String col3
      73: invokestatic  #9                  // Method org/apache/hadoop/hbase/util/Bytes.toBytes:(Ljava/lang/String;)[B
      76: putfield      #24                 // Field col3:[B
      79: aload_0
      80: ldc           #25                 // String col4
      82: invokestatic  #9                  // Method org/apache/hadoop/hbase/util/Bytes.toBytes:(Ljava/lang/String;)[B
      85: putfield      #26                 // Field col4:[B
      88: aload_0
      89: ldc           #27                 // String col5
      91: invokestatic  #9                  // Method org/apache/hadoop/hbase/util/Bytes.toBytes:(Ljava/lang/String;)[B
      94: putfield      #28                 // Field col5:[B
      97: aload_0
      98: ldc           #29                 // String data
     100: invokestatic  #9                  // Method org/apache/hadoop/hbase/util/Bytes.toBytes:(Ljava/lang/String;)[B
     103: putfield      #30                 // Field data:[B
     106: aload_0
     107: new           #31                 // class org/apache/hadoop/hbase/client/Get
     110: dup
     111: aload_0
     112: getfield      #10                 // Field row1:[B
     115: invokespecial #32                 // Method org/apache/hadoop/hbase/client/Get."<init>":([B)V
     118: putfield      #33                 // Field get:Lorg/apache/hadoop/hbase/client/Get;
     121: aload_0
     122: getfield      #33                 // Field get:Lorg/apache/hadoop/hbase/client/Get;
     125: aload_0
     126: getfield      #16                 // Field fam1:[B
     129: invokevirtual #34                 // Method org/apache/hadoop/hbase/client/Get.addFamily:([B)Lorg/apache/hadoop/hbase/client/Get;
     132: pop
     133: aload_0
     134: getfield      #33                 // Field get:Lorg/apache/hadoop/hbase/client/Get;
     137: aload_0
     138: getfield      #18                 // Field fam2:[B
     141: aload_0
     142: getfield      #22                 // Field col2:[B
     145: invokevirtual #35                 // Method org/apache/hadoop/hbase/client/Get.addColumn:([B[B)Lorg/apache/hadoop/hbase/client/Get;
     148: pop
     149: aload_0
     150: getfield      #33                 // Field get:Lorg/apache/hadoop/hbase/client/Get;
     153: aload_0
     154: getfield      #18                 // Field fam2:[B
     157: aload_0
     158: getfield      #26                 // Field col4:[B
     161: invokevirtual #35                 // Method org/apache/hadoop/hbase/client/Get.addColumn:([B[B)Lorg/apache/hadoop/hbase/client/Get;
     164: pop
     165: aload_0
     166: getfield      #33                 // Field get:Lorg/apache/hadoop/hbase/client/Get;
     169: aload_0
     170: getfield      #18                 // Field fam2:[B
     173: aload_0
     174: getfield      #28                 // Field col5:[B
     177: invokevirtual #35                 // Method org/apache/hadoop/hbase/client/Get.addColumn:([B[B)Lorg/apache/hadoop/hbase/client/Get;
     180: pop
     181: aload_0
     182: new           #36                 // class org/apache/hadoop/hbase/client/Scan
     185: dup
     186: aload_0
     187: getfield      #33                 // Field get:Lorg/apache/hadoop/hbase/client/Get;
     190: invokespecial #37                 // Method org/apache/hadoop/hbase/client/Scan."<init>":(Lorg/apache/hadoop/hbase/client/Get;)V
     193: putfield      #38                 // Field scan:Lorg/apache/hadoop/hbase/client/Scan;
     196: aload_0
     197: invokestatic  #39                 // InterfaceMethod org/apache/hadoop/hbase/CellComparator.getInstance:()Lorg/apache/hadoop/hbase/CellComparator;
     200: putfield      #40                 // Field rowComparator:Lorg/apache/hadoop/hbase/CellComparator;
     203: return
}
