Compiled from "AbstractFSWAL.java"
class org.apache.hadoop.hbase.regionserver.wal.AbstractFSWAL$2 extends java.lang.ThreadLocal<org.apache.hadoop.hbase.regionserver.wal.SyncFuture> {
  final org.apache.hadoop.hbase.regionserver.wal.AbstractFSWAL this$0;

  org.apache.hadoop.hbase.regionserver.wal.AbstractFSWAL$2(org.apache.hadoop.hbase.regionserver.wal.AbstractFSWAL);
    Code:
       0: aload_0
       1: aload_1
       2: putfield      #1                  // Field this$0:Lorg/apache/hadoop/hbase/regionserver/wal/AbstractFSWAL;
       5: aload_0
       6: invokespecial #2                  // Method java/lang/ThreadLocal."<init>":()V
       9: return

  protected org.apache.hadoop.hbase.regionserver.wal.SyncFuture initialValue();
    Code:
       0: new           #3                  // class org/apache/hadoop/hbase/regionserver/wal/SyncFuture
       3: dup
       4: invokespecial #4                  // Method org/apache/hadoop/hbase/regionserver/wal/SyncFuture."<init>":()V
       7: areturn

  protected java.lang.Object initialValue();
    Code:
       0: aload_0
       1: invokevirtual #5                  // Method initialValue:()Lorg/apache/hadoop/hbase/regionserver/wal/SyncFuture;
       4: areturn
}
