Compiled from "AbstractFSWAL.java"
final class org.apache.hadoop.hbase.regionserver.wal.AbstractFSWAL$WalProps {
  public final java.util.Map<byte[], java.lang.Long> encodedName2HighestSequenceId;

  public final long logSize;

  public final long rollTimeNs;

  public org.apache.hadoop.hbase.regionserver.wal.AbstractFSWAL$WalProps(java.util.Map<byte[], java.lang.Long>, long);
    Code:
       0: aload_0
       1: invokespecial #1                  // Method java/lang/Object."<init>":()V
       4: aload_0
       5: aload_1
       6: putfield      #2                  // Field encodedName2HighestSequenceId:Ljava/util/Map;
       9: aload_0
      10: lload_2
      11: putfield      #3                  // Field logSize:J
      14: aload_0
      15: invokestatic  #4                  // Method java/lang/System.nanoTime:()J
      18: putfield      #5                  // Field rollTimeNs:J
      21: return
}
