Compiled from "AbstractTestRegionLocator.java"
public abstract class org.apache.hadoop.hbase.client.AbstractTestRegionLocator {
  protected static final org.apache.hadoop.hbase.HBaseTestingUtility UTIL;

  protected static org.apache.hadoop.hbase.TableName TABLE_NAME;

  protected static byte[] FAMILY;

  protected static int REGION_REPLICATION;

  protected static byte[][] SPLIT_KEYS;

  public org.apache.hadoop.hbase.client.AbstractTestRegionLocator();
    Code:
       0: aload_0
       1: invokespecial #1                  // Method java/lang/Object."<init>":()V
       4: return

  protected static void startClusterAndCreateTable() throws java.lang.Exception;
    Code:
       0: getstatic     #2                  // Field UTIL:Lorg/apache/hadoop/hbase/HBaseTestingUtility;
       3: invokevirtual #3                  // Method org/apache/hadoop/hbase/HBaseTestingUtility.getConfiguration:()Lorg/apache/hadoop/conf/Configuration;
       6: ldc           #5                  // String hbase.meta.replica.count
       8: getstatic     #6                  // Field REGION_REPLICATION:I
      11: invokevirtual #7                  // Method org/apache/hadoop/conf/Configuration.setInt:(Ljava/lang/String;I)V
      14: getstatic     #2                  // Field UTIL:Lorg/apache/hadoop/hbase/HBaseTestingUtility;
      17: iconst_3
      18: invokevirtual #8                  // Method org/apache/hadoop/hbase/HBaseTestingUtility.startMiniCluster:(I)Lorg/apache/hadoop/hbase/MiniHBaseCluster;
      21: pop
      22: getstatic     #9                  // Field TABLE_NAME:Lorg/apache/hadoop/hbase/TableName;
      25: invokestatic  #10                 // Method org/apache/hadoop/hbase/client/TableDescriptorBuilder.newBuilder:(Lorg/apache/hadoop/hbase/TableName;)Lorg/apache/hadoop/hbase/client/TableDescriptorBuilder;
      28: getstatic     #6                  // Field REGION_REPLICATION:I
      31: invokevirtual #11                 // Method org/apache/hadoop/hbase/client/TableDescriptorBuilder.setRegionReplication:(I)Lorg/apache/hadoop/hbase/client/TableDescriptorBuilder;
      34: getstatic     #12                 // Field FAMILY:[B
      37: invokestatic  #13                 // Method org/apache/hadoop/hbase/client/ColumnFamilyDescriptorBuilder.of:([B)Lorg/apache/hadoop/hbase/client/ColumnFamilyDescriptor;
      40: invokevirtual #14                 // Method org/apache/hadoop/hbase/client/TableDescriptorBuilder.setColumnFamily:(Lorg/apache/hadoop/hbase/client/ColumnFamilyDescriptor;)Lorg/apache/hadoop/hbase/client/TableDescriptorBuilder;
      43: invokevirtual #15                 // Method org/apache/hadoop/hbase/client/TableDescriptorBuilder.build:()Lorg/apache/hadoop/hbase/client/TableDescriptor;
      46: astore_0
      47: bipush        9
      49: anewarray     #16                 // class "[B"
      52: putstatic     #17                 // Field SPLIT_KEYS:[[B
      55: iconst_0
      56: istore_1
      57: iload_1
      58: bipush        9
      60: if_icmpge     83
      63: getstatic     #17                 // Field SPLIT_KEYS:[[B
      66: iload_1
      67: iload_1
      68: iconst_1
      69: iadd
      70: invokestatic  #18                 // Method java/lang/Integer.toString:(I)Ljava/lang/String;
      73: invokestatic  #19                 // Method org/apache/hadoop/hbase/util/Bytes.toBytes:(Ljava/lang/String;)[B
      76: aastore
      77: iinc          1, 1
      80: goto          57
      83: getstatic     #2                  // Field UTIL:Lorg/apache/hadoop/hbase/HBaseTestingUtility;
      86: invokevirtual #20                 // Method org/apache/hadoop/hbase/HBaseTestingUtility.getAdmin:()Lorg/apache/hadoop/hbase/client/Admin;
      89: aload_0
      90: getstatic     #17                 // Field SPLIT_KEYS:[[B
      93: invokeinterface #21,  3           // InterfaceMethod org/apache/hadoop/hbase/client/Admin.createTable:(Lorg/apache/hadoop/hbase/client/TableDescriptor;[[B)V
      98: getstatic     #2                  // Field UTIL:Lorg/apache/hadoop/hbase/HBaseTestingUtility;
     101: getstatic     #9                  // Field TABLE_NAME:Lorg/apache/hadoop/hbase/TableName;
     104: invokevirtual #22                 // Method org/apache/hadoop/hbase/HBaseTestingUtility.waitTableAvailable:(Lorg/apache/hadoop/hbase/TableName;)V
     107: getstatic     #2                  // Field UTIL:Lorg/apache/hadoop/hbase/HBaseTestingUtility;
     110: invokevirtual #3                  // Method org/apache/hadoop/hbase/HBaseTestingUtility.getConfiguration:()Lorg/apache/hadoop/conf/Configuration;
     113: invokestatic  #23                 // Method org/apache/hadoop/hbase/client/AsyncRegistryFactory.getRegistry:(Lorg/apache/hadoop/conf/Configuration;)Lorg/apache/hadoop/hbase/client/AsyncRegistry;
     116: astore_1
     117: aconst_null
     118: astore_2
     119: getstatic     #2                  // Field UTIL:Lorg/apache/hadoop/hbase/HBaseTestingUtility;
     122: invokevirtual #3                  // Method org/apache/hadoop/hbase/HBaseTestingUtility.getConfiguration:()Lorg/apache/hadoop/conf/Configuration;
     125: aload_1
     126: getstatic     #6                  // Field REGION_REPLICATION:I
     129: invokestatic  #24                 // Method org/apache/hadoop/hbase/client/RegionReplicaTestHelper.waitUntilAllMetaReplicasHavingRegionLocation:(Lorg/apache/hadoop/conf/Configuration;Lorg/apache/hadoop/hbase/client/AsyncRegistry;I)V
     132: aload_1
     133: ifnull        211
     136: aload_2
     137: ifnull        158
     140: aload_1
     141: invokeinterface #25,  1           // InterfaceMethod org/apache/hadoop/hbase/client/AsyncRegistry.close:()V
     146: goto          211
     149: astore_3
     150: aload_2
     151: aload_3
     152: invokevirtual #27                 // Method java/lang/Throwable.addSuppressed:(Ljava/lang/Throwable;)V
     155: goto          211
     158: aload_1
     159: invokeinterface #25,  1           // InterfaceMethod org/apache/hadoop/hbase/client/AsyncRegistry.close:()V
     164: goto          211
     167: astore_3
     168: aload_3
     169: astore_2
     170: aload_3
     171: athrow
     172: astore        4
     174: aload_1
     175: ifnull        208
     178: aload_2
     179: ifnull        202
     182: aload_1
     183: invokeinterface #25,  1           // InterfaceMethod org/apache/hadoop/hbase/client/AsyncRegistry.close:()V
     188: goto          208
     191: astore        5
     193: aload_2
     194: aload         5
     196: invokevirtual #27                 // Method java/lang/Throwable.addSuppressed:(Ljava/lang/Throwable;)V
     199: goto          208
     202: aload_1
     203: invokeinterface #25,  1           // InterfaceMethod org/apache/hadoop/hbase/client/AsyncRegistry.close:()V
     208: aload         4
     210: athrow
     211: getstatic     #2                  // Field UTIL:Lorg/apache/hadoop/hbase/HBaseTestingUtility;
     214: invokevirtual #20                 // Method org/apache/hadoop/hbase/HBaseTestingUtility.getAdmin:()Lorg/apache/hadoop/hbase/client/Admin;
     217: iconst_0
     218: iconst_1
     219: invokeinterface #28,  3           // InterfaceMethod org/apache/hadoop/hbase/client/Admin.balancerSwitch:(ZZ)Z
     224: pop
     225: return
    Exception table:
       from    to  target type
         140   146   149   Class java/lang/Throwable
         119   132   167   Class java/lang/Throwable
         119   132   172   any
         182   188   191   Class java/lang/Throwable
         167   174   172   any

  public void tearDownAfterTest() throws java.io.IOException;
    Code:
       0: aload_0
       1: getstatic     #9                  // Field TABLE_NAME:Lorg/apache/hadoop/hbase/TableName;
       4: invokevirtual #29                 // Method clearCache:(Lorg/apache/hadoop/hbase/TableName;)V
       7: aload_0
       8: getstatic     #30                 // Field org/apache/hadoop/hbase/TableName.META_TABLE_NAME:Lorg/apache/hadoop/hbase/TableName;
      11: invokevirtual #29                 // Method clearCache:(Lorg/apache/hadoop/hbase/TableName;)V
      14: return

  public void testStartEndKeys() throws java.io.IOException;
    Code:
       0: aload_0
       1: aload_0
       2: getstatic     #9                  // Field TABLE_NAME:Lorg/apache/hadoop/hbase/TableName;
       5: invokevirtual #37                 // Method getStartKeys:(Lorg/apache/hadoop/hbase/TableName;)[[B
       8: invokespecial #38                 // Method assertStartKeys:([[B)V
      11: aload_0
      12: aload_0
      13: getstatic     #9                  // Field TABLE_NAME:Lorg/apache/hadoop/hbase/TableName;
      16: invokevirtual #39                 // Method getEndKeys:(Lorg/apache/hadoop/hbase/TableName;)[[B
      19: invokespecial #40                 // Method assertEndKeys:([[B)V
      22: aload_0
      23: getstatic     #9                  // Field TABLE_NAME:Lorg/apache/hadoop/hbase/TableName;
      26: invokevirtual #41                 // Method getStartEndKeys:(Lorg/apache/hadoop/hbase/TableName;)Lorg/apache/hadoop/hbase/util/Pair;
      29: astore_1
      30: aload_0
      31: aload_1
      32: invokevirtual #42                 // Method org/apache/hadoop/hbase/util/Pair.getFirst:()Ljava/lang/Object;
      35: checkcast     #43                 // class "[[B"
      38: invokespecial #38                 // Method assertStartKeys:([[B)V
      41: aload_0
      42: aload_1
      43: invokevirtual #44                 // Method org/apache/hadoop/hbase/util/Pair.getSecond:()Ljava/lang/Object;
      46: checkcast     #43                 // class "[[B"
      49: invokespecial #40                 // Method assertEndKeys:([[B)V
      52: return

  public void testGetRegionLocation() throws java.io.IOException;
    Code:
       0: iconst_0
       1: istore_1
       2: iload_1
       3: getstatic     #17                 // Field SPLIT_KEYS:[[B
       6: arraylength
       7: if_icmpgt     50
      10: iconst_0
      11: istore_2
      12: iload_2
      13: getstatic     #6                  // Field REGION_REPLICATION:I
      16: if_icmpge     44
      19: aload_0
      20: aload_0
      21: getstatic     #9                  // Field TABLE_NAME:Lorg/apache/hadoop/hbase/TableName;
      24: aload_0
      25: iload_1
      26: invokespecial #34                 // Method getStartKey:(I)[B
      29: iload_2
      30: invokevirtual #63                 // Method getRegionLocation:(Lorg/apache/hadoop/hbase/TableName;[BI)Lorg/apache/hadoop/hbase/HRegionLocation;
      33: iload_1
      34: iload_2
      35: invokespecial #64                 // Method assertRegionLocation:(Lorg/apache/hadoop/hbase/HRegionLocation;II)V
      38: iinc          2, 1
      41: goto          12
      44: iinc          1, 1
      47: goto          2
      50: return

  public void testGetRegionLocations() throws java.io.IOException;
    Code:
       0: iconst_0
       1: istore_1
       2: iload_1
       3: getstatic     #17                 // Field SPLIT_KEYS:[[B
       6: arraylength
       7: if_icmpgt     74
      10: aload_0
      11: getstatic     #9                  // Field TABLE_NAME:Lorg/apache/hadoop/hbase/TableName;
      14: aload_0
      15: iload_1
      16: invokespecial #34                 // Method getStartKey:(I)[B
      19: invokevirtual #65                 // Method getRegionLocations:(Lorg/apache/hadoop/hbase/TableName;[B)Ljava/util/List;
      22: astore_2
      23: getstatic     #6                  // Field REGION_REPLICATION:I
      26: i2l
      27: aload_2
      28: invokeinterface #66,  1           // InterfaceMethod java/util/List.size:()I
      33: i2l
      34: invokestatic  #33                 // Method org/junit/Assert.assertEquals:(JJ)V
      37: iconst_0
      38: istore_3
      39: iload_3
      40: getstatic     #6                  // Field REGION_REPLICATION:I
      43: if_icmpge     68
      46: aload_0
      47: aload_2
      48: iload_3
      49: invokeinterface #67,  2           // InterfaceMethod java/util/List.get:(I)Ljava/lang/Object;
      54: checkcast     #68                 // class org/apache/hadoop/hbase/HRegionLocation
      57: iload_1
      58: iload_3
      59: invokespecial #64                 // Method assertRegionLocation:(Lorg/apache/hadoop/hbase/HRegionLocation;II)V
      62: iinc          3, 1
      65: goto          39
      68: iinc          1, 1
      71: goto          2
      74: return

  public void testGetAllRegionLocations() throws java.io.IOException;
    Code:
       0: aload_0
       1: getstatic     #9                  // Field TABLE_NAME:Lorg/apache/hadoop/hbase/TableName;
       4: invokevirtual #69                 // Method getAllRegionLocations:(Lorg/apache/hadoop/hbase/TableName;)Ljava/util/List;
       7: astore_1
       8: getstatic     #6                  // Field REGION_REPLICATION:I
      11: getstatic     #17                 // Field SPLIT_KEYS:[[B
      14: arraylength
      15: iconst_1
      16: iadd
      17: imul
      18: i2l
      19: aload_1
      20: invokeinterface #66,  1           // InterfaceMethod java/util/List.size:()I
      25: i2l
      26: invokestatic  #33                 // Method org/junit/Assert.assertEquals:(JJ)V
      29: aload_1
      30: invokedynamic #70,  0             // InvokeDynamic #2:compare:()Ljava/util/Comparator;
      35: invokestatic  #71                 // Method java/util/Collections.sort:(Ljava/util/List;Ljava/util/Comparator;)V
      38: iconst_0
      39: istore_2
      40: iload_2
      41: getstatic     #17                 // Field SPLIT_KEYS:[[B
      44: arraylength
      45: if_icmpgt     91
      48: iconst_0
      49: istore_3
      50: iload_3
      51: getstatic     #6                  // Field REGION_REPLICATION:I
      54: if_icmpge     85
      57: aload_0
      58: aload_1
      59: iload_2
      60: getstatic     #6                  // Field REGION_REPLICATION:I
      63: imul
      64: iload_3
      65: iadd
      66: invokeinterface #67,  2           // InterfaceMethod java/util/List.get:(I)Ljava/lang/Object;
      71: checkcast     #68                 // class org/apache/hadoop/hbase/HRegionLocation
      74: iload_2
      75: iload_3
      76: invokespecial #64                 // Method assertRegionLocation:(Lorg/apache/hadoop/hbase/HRegionLocation;II)V
      79: iinc          3, 1
      82: goto          50
      85: iinc          2, 1
      88: goto          40
      91: return

  public void testMeta() throws java.io.IOException;
    Code:
       0: aload_0
       1: aload_0
       2: getstatic     #30                 // Field org/apache/hadoop/hbase/TableName.META_TABLE_NAME:Lorg/apache/hadoop/hbase/TableName;
       5: invokevirtual #37                 // Method getStartKeys:(Lorg/apache/hadoop/hbase/TableName;)[[B
       8: invokespecial #74                 // Method assertMetaStartOrEndKeys:([[B)V
      11: aload_0
      12: aload_0
      13: getstatic     #30                 // Field org/apache/hadoop/hbase/TableName.META_TABLE_NAME:Lorg/apache/hadoop/hbase/TableName;
      16: invokevirtual #39                 // Method getEndKeys:(Lorg/apache/hadoop/hbase/TableName;)[[B
      19: invokespecial #74                 // Method assertMetaStartOrEndKeys:([[B)V
      22: aload_0
      23: getstatic     #30                 // Field org/apache/hadoop/hbase/TableName.META_TABLE_NAME:Lorg/apache/hadoop/hbase/TableName;
      26: invokevirtual #41                 // Method getStartEndKeys:(Lorg/apache/hadoop/hbase/TableName;)Lorg/apache/hadoop/hbase/util/Pair;
      29: astore_1
      30: aload_0
      31: aload_1
      32: invokevirtual #42                 // Method org/apache/hadoop/hbase/util/Pair.getFirst:()Ljava/lang/Object;
      35: checkcast     #43                 // class "[[B"
      38: invokespecial #74                 // Method assertMetaStartOrEndKeys:([[B)V
      41: aload_0
      42: aload_1
      43: invokevirtual #44                 // Method org/apache/hadoop/hbase/util/Pair.getSecond:()Ljava/lang/Object;
      46: checkcast     #43                 // class "[[B"
      49: invokespecial #74                 // Method assertMetaStartOrEndKeys:([[B)V
      52: iconst_0
      53: istore_2
      54: iload_2
      55: getstatic     #6                  // Field REGION_REPLICATION:I
      58: if_icmpge     83
      61: aload_0
      62: aload_0
      63: getstatic     #30                 // Field org/apache/hadoop/hbase/TableName.META_TABLE_NAME:Lorg/apache/hadoop/hbase/TableName;
      66: getstatic     #31                 // Field org/apache/hadoop/hbase/HConstants.EMPTY_START_ROW:[B
      69: iload_2
      70: invokevirtual #63                 // Method getRegionLocation:(Lorg/apache/hadoop/hbase/TableName;[BI)Lorg/apache/hadoop/hbase/HRegionLocation;
      73: iload_2
      74: invokespecial #73                 // Method assertMetaRegionLocation:(Lorg/apache/hadoop/hbase/HRegionLocation;I)V
      77: iinc          2, 1
      80: goto          54
      83: aload_0
      84: aload_0
      85: getstatic     #30                 // Field org/apache/hadoop/hbase/TableName.META_TABLE_NAME:Lorg/apache/hadoop/hbase/TableName;
      88: getstatic     #31                 // Field org/apache/hadoop/hbase/HConstants.EMPTY_START_ROW:[B
      91: invokevirtual #65                 // Method getRegionLocations:(Lorg/apache/hadoop/hbase/TableName;[B)Ljava/util/List;
      94: invokespecial #75                 // Method assertMetaRegionLocations:(Ljava/util/List;)V
      97: aload_0
      98: aload_0
      99: getstatic     #30                 // Field org/apache/hadoop/hbase/TableName.META_TABLE_NAME:Lorg/apache/hadoop/hbase/TableName;
     102: invokevirtual #69                 // Method getAllRegionLocations:(Lorg/apache/hadoop/hbase/TableName;)Ljava/util/List;
     105: invokespecial #75                 // Method assertMetaRegionLocations:(Ljava/util/List;)V
     108: return

  protected abstract byte[][] getStartKeys(org.apache.hadoop.hbase.TableName) throws java.io.IOException;

  protected abstract byte[][] getEndKeys(org.apache.hadoop.hbase.TableName) throws java.io.IOException;

  protected abstract org.apache.hadoop.hbase.util.Pair<byte[][], byte[][]> getStartEndKeys(org.apache.hadoop.hbase.TableName) throws java.io.IOException;

  protected abstract org.apache.hadoop.hbase.HRegionLocation getRegionLocation(org.apache.hadoop.hbase.TableName, byte[], int) throws java.io.IOException;

  protected abstract java.util.List<org.apache.hadoop.hbase.HRegionLocation> getRegionLocations(org.apache.hadoop.hbase.TableName, byte[]) throws java.io.IOException;

  protected abstract java.util.List<org.apache.hadoop.hbase.HRegionLocation> getAllRegionLocations(org.apache.hadoop.hbase.TableName) throws java.io.IOException;

  protected abstract void clearCache(org.apache.hadoop.hbase.TableName) throws java.io.IOException;

  static {};
    Code:
       0: new           #84                 // class org/apache/hadoop/hbase/HBaseTestingUtility
       3: dup
       4: invokespecial #85                 // Method org/apache/hadoop/hbase/HBaseTestingUtility."<init>":()V
       7: putstatic     #2                  // Field UTIL:Lorg/apache/hadoop/hbase/HBaseTestingUtility;
      10: ldc           #86                 // String Locator
      12: invokestatic  #87                 // Method org/apache/hadoop/hbase/TableName.valueOf:(Ljava/lang/String;)Lorg/apache/hadoop/hbase/TableName;
      15: putstatic     #9                  // Field TABLE_NAME:Lorg/apache/hadoop/hbase/TableName;
      18: ldc           #88                 // String family
      20: invokestatic  #19                 // Method org/apache/hadoop/hbase/util/Bytes.toBytes:(Ljava/lang/String;)[B
      23: putstatic     #12                 // Field FAMILY:[B
      26: iconst_3
      27: putstatic     #6                  // Field REGION_REPLICATION:I
      30: return
}
