Compiled from "AbstractMemStore.java"
public abstract class org.apache.hadoop.hbase.regionserver.AbstractMemStore implements org.apache.hadoop.hbase.regionserver.MemStore {
  protected volatile org.apache.hadoop.hbase.regionserver.ImmutableSegment snapshot;

  protected volatile long snapshotId;

  protected org.apache.hadoop.hbase.regionserver.RegionServicesForStores regionServices;

  public static final long FIXED_OVERHEAD;

  public static final long DEEP_OVERHEAD;

  public static void addToScanners(java.util.List<? extends org.apache.hadoop.hbase.regionserver.Segment>, long, java.util.List<org.apache.hadoop.hbase.regionserver.KeyValueScanner>);
    Code:
       0: aload_0
       1: invokeinterface #1,  1            // InterfaceMethod java/util/List.iterator:()Ljava/util/Iterator;
       6: astore        4
       8: aload         4
      10: invokeinterface #2,  1            // InterfaceMethod java/util/Iterator.hasNext:()Z
      15: ifeq          40
      18: aload         4
      20: invokeinterface #3,  1            // InterfaceMethod java/util/Iterator.next:()Ljava/lang/Object;
      25: checkcast     #4                  // class org/apache/hadoop/hbase/regionserver/Segment
      28: astore        5
      30: aload         5
      32: lload_1
      33: aload_3
      34: invokestatic  #5                  // Method addToScanners:(Lorg/apache/hadoop/hbase/regionserver/Segment;JLjava/util/List;)V
      37: goto          8
      40: return

  protected static void addToScanners(org.apache.hadoop.hbase.regionserver.Segment, long, java.util.List<org.apache.hadoop.hbase.regionserver.KeyValueScanner>);
    Code:
       0: aload_3
       1: aload_0
       2: lload_1
       3: invokevirtual #6                  // Method org/apache/hadoop/hbase/regionserver/Segment.getScanner:(J)Lorg/apache/hadoop/hbase/regionserver/KeyValueScanner;
       6: invokeinterface #7,  2            // InterfaceMethod java/util/List.add:(Ljava/lang/Object;)Z
      11: pop
      12: return

  protected org.apache.hadoop.hbase.regionserver.AbstractMemStore(org.apache.hadoop.conf.Configuration, org.apache.hadoop.hbase.CellComparator, org.apache.hadoop.hbase.regionserver.RegionServicesForStores);
    Code:
       0: aload_0
       1: invokespecial #8                  // Method java/lang/Object."<init>":()V
       4: aload_0
       5: aload_1
       6: putfield      #9                  // Field conf:Lorg/apache/hadoop/conf/Configuration;
       9: aload_0
      10: aload_2
      11: putfield      #10                 // Field comparator:Lorg/apache/hadoop/hbase/CellComparator;
      14: aload_0
      15: aload_3
      16: putfield      #11                 // Field regionServices:Lorg/apache/hadoop/hbase/regionserver/RegionServicesForStores;
      19: aload_0
      20: invokevirtual #12                 // Method resetActive:()V
      23: aload_0
      24: invokestatic  #13                 // Method org/apache/hadoop/hbase/regionserver/SegmentFactory.instance:()Lorg/apache/hadoop/hbase/regionserver/SegmentFactory;
      27: aload_2
      28: invokevirtual #14                 // Method org/apache/hadoop/hbase/regionserver/SegmentFactory.createImmutableSegment:(Lorg/apache/hadoop/hbase/CellComparator;)Lorg/apache/hadoop/hbase/regionserver/ImmutableSegment;
      31: putfield      #15                 // Field snapshot:Lorg/apache/hadoop/hbase/regionserver/ImmutableSegment;
      34: aload_0
      35: ldc2_w        #17                 // long -1l
      38: putfield      #19                 // Field snapshotId:J
      41: return

  protected void resetActive();
    Code:
       0: new           #20                 // class org/apache/hadoop/hbase/regionserver/NonThreadSafeMemStoreSizing
       3: dup
       4: invokespecial #21                 // Method org/apache/hadoop/hbase/regionserver/NonThreadSafeMemStoreSizing."<init>":()V
       7: astore_1
       8: aload_0
       9: invokestatic  #13                 // Method org/apache/hadoop/hbase/regionserver/SegmentFactory.instance:()Lorg/apache/hadoop/hbase/regionserver/SegmentFactory;
      12: aload_0
      13: getfield      #9                  // Field conf:Lorg/apache/hadoop/conf/Configuration;
      16: aload_0
      17: getfield      #10                 // Field comparator:Lorg/apache/hadoop/hbase/CellComparator;
      20: aload_1
      21: invokevirtual #22                 // Method org/apache/hadoop/hbase/regionserver/SegmentFactory.createMutableSegment:(Lorg/apache/hadoop/conf/Configuration;Lorg/apache/hadoop/hbase/CellComparator;Lorg/apache/hadoop/hbase/regionserver/MemStoreSizing;)Lorg/apache/hadoop/hbase/regionserver/MutableSegment;
      24: putfield      #23                 // Field active:Lorg/apache/hadoop/hbase/regionserver/MutableSegment;
      27: aload_0
      28: getfield      #11                 // Field regionServices:Lorg/apache/hadoop/hbase/regionserver/RegionServicesForStores;
      31: ifnull        65
      34: aload_0
      35: getfield      #11                 // Field regionServices:Lorg/apache/hadoop/hbase/regionserver/RegionServicesForStores;
      38: aload_1
      39: invokeinterface #24,  1           // InterfaceMethod org/apache/hadoop/hbase/regionserver/MemStoreSizing.getDataSize:()J
      44: aload_1
      45: invokeinterface #25,  1           // InterfaceMethod org/apache/hadoop/hbase/regionserver/MemStoreSizing.getHeapSize:()J
      50: aload_1
      51: invokeinterface #26,  1           // InterfaceMethod org/apache/hadoop/hbase/regionserver/MemStoreSizing.getOffHeapSize:()J
      56: aload_1
      57: invokeinterface #27,  1           // InterfaceMethod org/apache/hadoop/hbase/regionserver/MemStoreSizing.getCellsCount:()I
      62: invokevirtual #28                 // Method org/apache/hadoop/hbase/regionserver/RegionServicesForStores.addMemStoreSize:(JJJI)V
      65: aload_0
      66: ldc2_w        #30                 // long 9223372036854775807l
      69: putfield      #32                 // Field timeOfOldestEdit:J
      72: return

  public abstract void updateLowestUnflushedSequenceIdInWAL(boolean);

  public void add(java.lang.Iterable<org.apache.hadoop.hbase.Cell>, org.apache.hadoop.hbase.regionserver.MemStoreSizing);
    Code:
       0: aload_1
       1: invokeinterface #33,  1           // InterfaceMethod java/lang/Iterable.iterator:()Ljava/util/Iterator;
       6: astore_3
       7: aload_3
       8: invokeinterface #2,  1            // InterfaceMethod java/util/Iterator.hasNext:()Z
      13: ifeq          37
      16: aload_3
      17: invokeinterface #3,  1            // InterfaceMethod java/util/Iterator.next:()Ljava/lang/Object;
      22: checkcast     #34                 // class org/apache/hadoop/hbase/Cell
      25: astore        4
      27: aload_0
      28: aload         4
      30: aload_2
      31: invokevirtual #35                 // Method add:(Lorg/apache/hadoop/hbase/Cell;Lorg/apache/hadoop/hbase/regionserver/MemStoreSizing;)V
      34: goto          7
      37: return

  public void add(org.apache.hadoop.hbase.Cell, org.apache.hadoop.hbase.regionserver.MemStoreSizing);
    Code:
       0: aload_0
       1: aload_1
       2: lconst_0
       3: aload_2
       4: iconst_1
       5: invokespecial #36                 // Method doAddOrUpsert:(Lorg/apache/hadoop/hbase/Cell;JLorg/apache/hadoop/hbase/regionserver/MemStoreSizing;Z)V
       8: return

  protected abstract boolean preUpdate(org.apache.hadoop.hbase.regionserver.MutableSegment, org.apache.hadoop.hbase.Cell, org.apache.hadoop.hbase.regionserver.MemStoreSizing);

  protected abstract void postUpdate(org.apache.hadoop.hbase.regionserver.MutableSegment);

  public void upsert(java.lang.Iterable<org.apache.hadoop.hbase.Cell>, long, org.apache.hadoop.hbase.regionserver.MemStoreSizing);
    Code:
       0: aload_1
       1: invokeinterface #33,  1           // InterfaceMethod java/lang/Iterable.iterator:()Ljava/util/Iterator;
       6: astore        5
       8: aload         5
      10: invokeinterface #2,  1            // InterfaceMethod java/util/Iterator.hasNext:()Z
      15: ifeq          42
      18: aload         5
      20: invokeinterface #3,  1            // InterfaceMethod java/util/Iterator.next:()Ljava/lang/Object;
      25: checkcast     #34                 // class org/apache/hadoop/hbase/Cell
      28: astore        6
      30: aload_0
      31: aload         6
      33: lload_2
      34: aload         4
      36: invokespecial #50                 // Method upsert:(Lorg/apache/hadoop/hbase/Cell;JLorg/apache/hadoop/hbase/regionserver/MemStoreSizing;)V
      39: goto          8
      42: return

  public long timeOfOldestEdit();
    Code:
       0: aload_0
       1: getfield      #32                 // Field timeOfOldestEdit:J
       4: lreturn

  public void clearSnapshot(long) throws org.apache.hadoop.hbase.exceptions.UnexpectedStateException;
    Code:
       0: aload_0
       1: getfield      #19                 // Field snapshotId:J
       4: ldc2_w        #17                 // long -1l
       7: lcmp
       8: ifne          12
      11: return
      12: aload_0
      13: getfield      #19                 // Field snapshotId:J
      16: lload_1
      17: lcmp
      18: ifeq          60
      21: new           #51                 // class org/apache/hadoop/hbase/exceptions/UnexpectedStateException
      24: dup
      25: new           #52                 // class java/lang/StringBuilder
      28: dup
      29: invokespecial #53                 // Method java/lang/StringBuilder."<init>":()V
      32: ldc           #54                 // String Current snapshot id is
      34: invokevirtual #55                 // Method java/lang/StringBuilder.append:(Ljava/lang/String;)Ljava/lang/StringBuilder;
      37: aload_0
      38: getfield      #19                 // Field snapshotId:J
      41: invokevirtual #56                 // Method java/lang/StringBuilder.append:(J)Ljava/lang/StringBuilder;
      44: ldc           #57                 // String ,passed
      46: invokevirtual #55                 // Method java/lang/StringBuilder.append:(Ljava/lang/String;)Ljava/lang/StringBuilder;
      49: lload_1
      50: invokevirtual #56                 // Method java/lang/StringBuilder.append:(J)Ljava/lang/StringBuilder;
      53: invokevirtual #58                 // Method java/lang/StringBuilder.toString:()Ljava/lang/String;
      56: invokespecial #59                 // Method org/apache/hadoop/hbase/exceptions/UnexpectedStateException."<init>":(Ljava/lang/String;)V
      59: athrow
      60: aload_0
      61: getfield      #15                 // Field snapshot:Lorg/apache/hadoop/hbase/regionserver/ImmutableSegment;
      64: astore_3
      65: aload_0
      66: getfield      #15                 // Field snapshot:Lorg/apache/hadoop/hbase/regionserver/ImmutableSegment;
      69: invokevirtual #60                 // Method org/apache/hadoop/hbase/regionserver/ImmutableSegment.isEmpty:()Z
      72: ifne          89
      75: aload_0
      76: invokestatic  #13                 // Method org/apache/hadoop/hbase/regionserver/SegmentFactory.instance:()Lorg/apache/hadoop/hbase/regionserver/SegmentFactory;
      79: aload_0
      80: getfield      #10                 // Field comparator:Lorg/apache/hadoop/hbase/CellComparator;
      83: invokevirtual #14                 // Method org/apache/hadoop/hbase/regionserver/SegmentFactory.createImmutableSegment:(Lorg/apache/hadoop/hbase/CellComparator;)Lorg/apache/hadoop/hbase/regionserver/ImmutableSegment;
      86: putfield      #15                 // Field snapshot:Lorg/apache/hadoop/hbase/regionserver/ImmutableSegment;
      89: aload_0
      90: ldc2_w        #17                 // long -1l
      93: putfield      #19                 // Field snapshotId:J
      96: aload_3
      97: invokevirtual #61                 // Method org/apache/hadoop/hbase/regionserver/Segment.close:()V
     100: return

  public org.apache.hadoop.hbase.regionserver.MemStoreSize getSnapshotSize();
    Code:
       0: aload_0
       1: getfield      #15                 // Field snapshot:Lorg/apache/hadoop/hbase/regionserver/ImmutableSegment;
       4: invokevirtual #62                 // Method org/apache/hadoop/hbase/regionserver/ImmutableSegment.getMemStoreSize:()Lorg/apache/hadoop/hbase/regionserver/MemStoreSize;
       7: areturn

  public java.lang.String toString();
    Code:
       0: new           #52                 // class java/lang/StringBuilder
       3: dup
       4: invokespecial #53                 // Method java/lang/StringBuilder."<init>":()V
       7: astore_1
       8: iconst_1
       9: istore_2
      10: aload_0
      11: invokevirtual #63                 // Method getSegments:()Ljava/util/List;
      14: invokeinterface #1,  1            // InterfaceMethod java/util/List.iterator:()Ljava/util/Iterator;
      19: astore_3
      20: aload_3
      21: invokeinterface #2,  1            // InterfaceMethod java/util/Iterator.hasNext:()Z
      26: ifeq          88
      29: aload_3
      30: invokeinterface #3,  1            // InterfaceMethod java/util/Iterator.next:()Ljava/lang/Object;
      35: checkcast     #4                  // class org/apache/hadoop/hbase/regionserver/Segment
      38: astore        4
      40: aload_1
      41: new           #52                 // class java/lang/StringBuilder
      44: dup
      45: invokespecial #53                 // Method java/lang/StringBuilder."<init>":()V
      48: ldc           #64                 // String Segment (
      50: invokevirtual #55                 // Method java/lang/StringBuilder.append:(Ljava/lang/String;)Ljava/lang/StringBuilder;
      53: iload_2
      54: invokevirtual #65                 // Method java/lang/StringBuilder.append:(I)Ljava/lang/StringBuilder;
      57: ldc           #66                 // String )
      59: invokevirtual #55                 // Method java/lang/StringBuilder.append:(Ljava/lang/String;)Ljava/lang/StringBuilder;
      62: aload         4
      64: invokevirtual #67                 // Method org/apache/hadoop/hbase/regionserver/Segment.toString:()Ljava/lang/String;
      67: invokevirtual #55                 // Method java/lang/StringBuilder.append:(Ljava/lang/String;)Ljava/lang/StringBuilder;
      70: ldc           #68                 // String ;
      72: invokevirtual #55                 // Method java/lang/StringBuilder.append:(Ljava/lang/String;)Ljava/lang/StringBuilder;
      75: invokevirtual #58                 // Method java/lang/StringBuilder.toString:()Ljava/lang/String;
      78: invokevirtual #55                 // Method java/lang/StringBuilder.append:(Ljava/lang/String;)Ljava/lang/StringBuilder;
      81: pop
      82: iinc          2, 1
      85: goto          20
      88: goto          97
      91: astore_3
      92: aload_3
      93: invokevirtual #70                 // Method java/io/IOException.toString:()Ljava/lang/String;
      96: areturn
      97: aload_1
      98: invokevirtual #58                 // Method java/lang/StringBuilder.toString:()Ljava/lang/String;
     101: areturn
    Exception table:
       from    to  target type
          10    88    91   Class java/io/IOException

  protected org.apache.hadoop.conf.Configuration getConfiguration();
    Code:
       0: aload_0
       1: getfield      #9                  // Field conf:Lorg/apache/hadoop/conf/Configuration;
       4: areturn

  protected void dump(org.slf4j.Logger);
    Code:
       0: aload_0
       1: invokevirtual #37                 // Method getActive:()Lorg/apache/hadoop/hbase/regionserver/MutableSegment;
       4: aload_1
       5: invokevirtual #71                 // Method org/apache/hadoop/hbase/regionserver/MutableSegment.dump:(Lorg/slf4j/Logger;)V
       8: aload_0
       9: getfield      #15                 // Field snapshot:Lorg/apache/hadoop/hbase/regionserver/ImmutableSegment;
      12: aload_1
      13: invokevirtual #72                 // Method org/apache/hadoop/hbase/regionserver/ImmutableSegment.dump:(Lorg/slf4j/Logger;)V
      16: return

  protected org.apache.hadoop.hbase.Cell getLowest(org.apache.hadoop.hbase.Cell, org.apache.hadoop.hbase.Cell);
    Code:
       0: aload_1
       1: ifnonnull     6
       4: aload_2
       5: areturn
       6: aload_2
       7: ifnonnull     12
      10: aload_1
      11: areturn
      12: aload_0
      13: getfield      #10                 // Field comparator:Lorg/apache/hadoop/hbase/CellComparator;
      16: aload_1
      17: aload_2
      18: invokeinterface #73,  3           // InterfaceMethod org/apache/hadoop/hbase/CellComparator.compareRows:(Lorg/apache/hadoop/hbase/Cell;Lorg/apache/hadoop/hbase/Cell;)I
      23: ifgt          30
      26: aload_1
      27: goto          31
      30: aload_2
      31: areturn

  protected org.apache.hadoop.hbase.Cell getNextRow(org.apache.hadoop.hbase.Cell, java.util.NavigableSet<org.apache.hadoop.hbase.Cell>);
    Code:
       0: aconst_null
       1: astore_3
       2: aload_1
       3: ifnonnull     10
       6: aload_2
       7: goto          17
      10: aload_2
      11: aload_1
      12: invokeinterface #74,  2           // InterfaceMethod java/util/NavigableSet.tailSet:(Ljava/lang/Object;)Ljava/util/SortedSet;
      17: astore        4
      19: aload         4
      21: invokeinterface #75,  1           // InterfaceMethod java/util/SortedSet.iterator:()Ljava/util/Iterator;
      26: astore        5
      28: aload         5
      30: invokeinterface #2,  1            // InterfaceMethod java/util/Iterator.hasNext:()Z
      35: ifeq          74
      38: aload         5
      40: invokeinterface #3,  1            // InterfaceMethod java/util/Iterator.next:()Ljava/lang/Object;
      45: checkcast     #34                 // class org/apache/hadoop/hbase/Cell
      48: astore        6
      50: aload_0
      51: getfield      #10                 // Field comparator:Lorg/apache/hadoop/hbase/CellComparator;
      54: aload         6
      56: aload_1
      57: invokeinterface #73,  3           // InterfaceMethod org/apache/hadoop/hbase/CellComparator.compareRows:(Lorg/apache/hadoop/hbase/Cell;Lorg/apache/hadoop/hbase/Cell;)I
      62: ifgt          68
      65: goto          28
      68: aload         6
      70: astore_3
      71: goto          74
      74: aload_3
      75: areturn

  protected abstract boolean sizeAddedPreOperation();

  protected abstract long keySize();

  protected abstract long heapSize();

  protected org.apache.hadoop.hbase.CellComparator getComparator();
    Code:
       0: aload_0
       1: getfield      #10                 // Field comparator:Lorg/apache/hadoop/hbase/CellComparator;
       4: areturn

  org.apache.hadoop.hbase.regionserver.MutableSegment getActive();
    Code:
       0: aload_0
       1: getfield      #23                 // Field active:Lorg/apache/hadoop/hbase/regionserver/MutableSegment;
       4: areturn

  org.apache.hadoop.hbase.regionserver.ImmutableSegment getSnapshot();
    Code:
       0: aload_0
       1: getfield      #15                 // Field snapshot:Lorg/apache/hadoop/hbase/regionserver/ImmutableSegment;
       4: areturn

  protected abstract java.util.List<org.apache.hadoop.hbase.regionserver.Segment> getSegments() throws java.io.IOException;

  static {};
    Code:
       0: getstatic     #79                 // Field org/apache/hadoop/hbase/util/ClassSize.OBJECT:I
       3: i2l
       4: iconst_5
       5: getstatic     #80                 // Field org/apache/hadoop/hbase/util/ClassSize.REFERENCE:I
       8: imul
       9: i2l
      10: ladd
      11: ldc2_w        #82                 // long 16l
      14: ladd
      15: putstatic     #84                 // Field FIXED_OVERHEAD:J
      18: getstatic     #84                 // Field FIXED_OVERHEAD:J
      21: putstatic     #85                 // Field DEEP_OVERHEAD:J
      24: return
}
