Compiled from "AccessControlUtil.java"
public class org.apache.hadoop.hbase.security.access.AccessControlUtil {
  public static org.apache.hadoop.hbase.protobuf.generated.AccessControlProtos$GrantRequest buildGrantRequest(java.lang.String, org.apache.hadoop.hbase.TableName, byte[], byte[], boolean, org.apache.hadoop.hbase.protobuf.generated.AccessControlProtos$Permission$Action...);
    Code:
       0: invokestatic  #2                  // Method org/apache/hadoop/hbase/protobuf/generated/AccessControlProtos$Permission.newBuilder:()Lorg/apache/hadoop/hbase/protobuf/generated/AccessControlProtos$Permission$Builder;
       3: astore        6
       5: invokestatic  #3                  // Method org/apache/hadoop/hbase/protobuf/generated/AccessControlProtos$TablePermission.newBuilder:()Lorg/apache/hadoop/hbase/protobuf/generated/AccessControlProtos$TablePermission$Builder;
       8: astore        7
      10: aload         5
      12: astore        8
      14: aload         8
      16: arraylength
      17: istore        9
      19: iconst_0
      20: istore        10
      22: iload         10
      24: iload         9
      26: if_icmpge     50
      29: aload         8
      31: iload         10
      33: aaload
      34: astore        11
      36: aload         7
      38: aload         11
      40: invokevirtual #4                  // Method org/apache/hadoop/hbase/protobuf/generated/AccessControlProtos$TablePermission$Builder.addAction:(Lorg/apache/hadoop/hbase/protobuf/generated/AccessControlProtos$Permission$Action;)Lorg/apache/hadoop/hbase/protobuf/generated/AccessControlProtos$TablePermission$Builder;
      43: pop
      44: iinc          10, 1
      47: goto          22
      50: aload_1
      51: ifnonnull     64
      54: new           #5                  // class java/lang/NullPointerException
      57: dup
      58: ldc           #6                  // String TableName cannot be null
      60: invokespecial #7                  // Method java/lang/NullPointerException."<init>":(Ljava/lang/String;)V
      63: athrow
      64: aload         7
      66: aload_1
      67: invokestatic  #8                  // Method org/apache/hadoop/hbase/protobuf/ProtobufUtil.toProtoTableName:(Lorg/apache/hadoop/hbase/TableName;)Lorg/apache/hadoop/hbase/protobuf/generated/HBaseProtos$TableName;
      70: invokevirtual #9                  // Method org/apache/hadoop/hbase/protobuf/generated/AccessControlProtos$TablePermission$Builder.setTableName:(Lorg/apache/hadoop/hbase/protobuf/generated/HBaseProtos$TableName;)Lorg/apache/hadoop/hbase/protobuf/generated/AccessControlProtos$TablePermission$Builder;
      73: pop
      74: aload_2
      75: ifnull        88
      78: aload         7
      80: aload_2
      81: invokestatic  #10                 // Method org/apache/hadoop/hbase/util/ByteStringer.wrap:([B)Lcom/google/protobuf/ByteString;
      84: invokevirtual #11                 // Method org/apache/hadoop/hbase/protobuf/generated/AccessControlProtos$TablePermission$Builder.setFamily:(Lcom/google/protobuf/ByteString;)Lorg/apache/hadoop/hbase/protobuf/generated/AccessControlProtos$TablePermission$Builder;
      87: pop
      88: aload_3
      89: ifnull        102
      92: aload         7
      94: aload_3
      95: invokestatic  #10                 // Method org/apache/hadoop/hbase/util/ByteStringer.wrap:([B)Lcom/google/protobuf/ByteString;
      98: invokevirtual #12                 // Method org/apache/hadoop/hbase/protobuf/generated/AccessControlProtos$TablePermission$Builder.setQualifier:(Lcom/google/protobuf/ByteString;)Lorg/apache/hadoop/hbase/protobuf/generated/AccessControlProtos$TablePermission$Builder;
     101: pop
     102: aload         6
     104: getstatic     #13                 // Field org/apache/hadoop/hbase/protobuf/generated/AccessControlProtos$Permission$Type.Table:Lorg/apache/hadoop/hbase/protobuf/generated/AccessControlProtos$Permission$Type;
     107: invokevirtual #14                 // Method org/apache/hadoop/hbase/protobuf/generated/AccessControlProtos$Permission$Builder.setType:(Lorg/apache/hadoop/hbase/protobuf/generated/AccessControlProtos$Permission$Type;)Lorg/apache/hadoop/hbase/protobuf/generated/AccessControlProtos$Permission$Builder;
     110: aload         7
     112: invokevirtual #15                 // Method org/apache/hadoop/hbase/protobuf/generated/AccessControlProtos$Permission$Builder.setTablePermission:(Lorg/apache/hadoop/hbase/protobuf/generated/AccessControlProtos$TablePermission$Builder;)Lorg/apache/hadoop/hbase/protobuf/generated/AccessControlProtos$Permission$Builder;
     115: pop
     116: invokestatic  #16                 // Method org/apache/hadoop/hbase/protobuf/generated/AccessControlProtos$GrantRequest.newBuilder:()Lorg/apache/hadoop/hbase/protobuf/generated/AccessControlProtos$GrantRequest$Builder;
     119: invokestatic  #17                 // Method org/apache/hadoop/hbase/protobuf/generated/AccessControlProtos$UserPermission.newBuilder:()Lorg/apache/hadoop/hbase/protobuf/generated/AccessControlProtos$UserPermission$Builder;
     122: aload_0
     123: invokestatic  #18                 // Method com/google/protobuf/ByteString.copyFromUtf8:(Ljava/lang/String;)Lcom/google/protobuf/ByteString;
     126: invokevirtual #19                 // Method org/apache/hadoop/hbase/protobuf/generated/AccessControlProtos$UserPermission$Builder.setUser:(Lcom/google/protobuf/ByteString;)Lorg/apache/hadoop/hbase/protobuf/generated/AccessControlProtos$UserPermission$Builder;
     129: aload         6
     131: invokevirtual #20                 // Method org/apache/hadoop/hbase/protobuf/generated/AccessControlProtos$UserPermission$Builder.setPermission:(Lorg/apache/hadoop/hbase/protobuf/generated/AccessControlProtos$Permission$Builder;)Lorg/apache/hadoop/hbase/protobuf/generated/AccessControlProtos$UserPermission$Builder;
     134: invokevirtual #21                 // Method org/apache/hadoop/hbase/protobuf/generated/AccessControlProtos$GrantRequest$Builder.setUserPermission:(Lorg/apache/hadoop/hbase/protobuf/generated/AccessControlProtos$UserPermission$Builder;)Lorg/apache/hadoop/hbase/protobuf/generated/AccessControlProtos$GrantRequest$Builder;
     137: iload         4
     139: invokevirtual #22                 // Method org/apache/hadoop/hbase/protobuf/generated/AccessControlProtos$GrantRequest$Builder.setMergeExistingPermissions:(Z)Lorg/apache/hadoop/hbase/protobuf/generated/AccessControlProtos$GrantRequest$Builder;
     142: invokevirtual #23                 // Method org/apache/hadoop/hbase/protobuf/generated/AccessControlProtos$GrantRequest$Builder.build:()Lorg/apache/hadoop/hbase/protobuf/generated/AccessControlProtos$GrantRequest;
     145: areturn

  public static org.apache.hadoop.hbase.protobuf.generated.AccessControlProtos$GrantRequest buildGrantRequest(java.lang.String, java.lang.String, boolean, org.apache.hadoop.hbase.protobuf.generated.AccessControlProtos$Permission$Action...);
    Code:
       0: invokestatic  #2                  // Method org/apache/hadoop/hbase/protobuf/generated/AccessControlProtos$Permission.newBuilder:()Lorg/apache/hadoop/hbase/protobuf/generated/AccessControlProtos$Permission$Builder;
       3: astore        4
       5: invokestatic  #24                 // Method org/apache/hadoop/hbase/protobuf/generated/AccessControlProtos$NamespacePermission.newBuilder:()Lorg/apache/hadoop/hbase/protobuf/generated/AccessControlProtos$NamespacePermission$Builder;
       8: astore        5
      10: aload_3
      11: astore        6
      13: aload         6
      15: arraylength
      16: istore        7
      18: iconst_0
      19: istore        8
      21: iload         8
      23: iload         7
      25: if_icmpge     49
      28: aload         6
      30: iload         8
      32: aaload
      33: astore        9
      35: aload         5
      37: aload         9
      39: invokevirtual #25                 // Method org/apache/hadoop/hbase/protobuf/generated/AccessControlProtos$NamespacePermission$Builder.addAction:(Lorg/apache/hadoop/hbase/protobuf/generated/AccessControlProtos$Permission$Action;)Lorg/apache/hadoop/hbase/protobuf/generated/AccessControlProtos$NamespacePermission$Builder;
      42: pop
      43: iinc          8, 1
      46: goto          21
      49: aload_1
      50: ifnull        63
      53: aload         5
      55: aload_1
      56: invokestatic  #18                 // Method com/google/protobuf/ByteString.copyFromUtf8:(Ljava/lang/String;)Lcom/google/protobuf/ByteString;
      59: invokevirtual #26                 // Method org/apache/hadoop/hbase/protobuf/generated/AccessControlProtos$NamespacePermission$Builder.setNamespaceName:(Lcom/google/protobuf/ByteString;)Lorg/apache/hadoop/hbase/protobuf/generated/AccessControlProtos$NamespacePermission$Builder;
      62: pop
      63: aload         4
      65: getstatic     #27                 // Field org/apache/hadoop/hbase/protobuf/generated/AccessControlProtos$Permission$Type.Namespace:Lorg/apache/hadoop/hbase/protobuf/generated/AccessControlProtos$Permission$Type;
      68: invokevirtual #14                 // Method org/apache/hadoop/hbase/protobuf/generated/AccessControlProtos$Permission$Builder.setType:(Lorg/apache/hadoop/hbase/protobuf/generated/AccessControlProtos$Permission$Type;)Lorg/apache/hadoop/hbase/protobuf/generated/AccessControlProtos$Permission$Builder;
      71: aload         5
      73: invokevirtual #28                 // Method org/apache/hadoop/hbase/protobuf/generated/AccessControlProtos$Permission$Builder.setNamespacePermission:(Lorg/apache/hadoop/hbase/protobuf/generated/AccessControlProtos$NamespacePermission$Builder;)Lorg/apache/hadoop/hbase/protobuf/generated/AccessControlProtos$Permission$Builder;
      76: pop
      77: invokestatic  #16                 // Method org/apache/hadoop/hbase/protobuf/generated/AccessControlProtos$GrantRequest.newBuilder:()Lorg/apache/hadoop/hbase/protobuf/generated/AccessControlProtos$GrantRequest$Builder;
      80: invokestatic  #17                 // Method org/apache/hadoop/hbase/protobuf/generated/AccessControlProtos$UserPermission.newBuilder:()Lorg/apache/hadoop/hbase/protobuf/generated/AccessControlProtos$UserPermission$Builder;
      83: aload_0
      84: invokestatic  #18                 // Method com/google/protobuf/ByteString.copyFromUtf8:(Ljava/lang/String;)Lcom/google/protobuf/ByteString;
      87: invokevirtual #19                 // Method org/apache/hadoop/hbase/protobuf/generated/AccessControlProtos$UserPermission$Builder.setUser:(Lcom/google/protobuf/ByteString;)Lorg/apache/hadoop/hbase/protobuf/generated/AccessControlProtos$UserPermission$Builder;
      90: aload         4
      92: invokevirtual #20                 // Method org/apache/hadoop/hbase/protobuf/generated/AccessControlProtos$UserPermission$Builder.setPermission:(Lorg/apache/hadoop/hbase/protobuf/generated/AccessControlProtos$Permission$Builder;)Lorg/apache/hadoop/hbase/protobuf/generated/AccessControlProtos$UserPermission$Builder;
      95: invokevirtual #21                 // Method org/apache/hadoop/hbase/protobuf/generated/AccessControlProtos$GrantRequest$Builder.setUserPermission:(Lorg/apache/hadoop/hbase/protobuf/generated/AccessControlProtos$UserPermission$Builder;)Lorg/apache/hadoop/hbase/protobuf/generated/AccessControlProtos$GrantRequest$Builder;
      98: iload_2
      99: invokevirtual #22                 // Method org/apache/hadoop/hbase/protobuf/generated/AccessControlProtos$GrantRequest$Builder.setMergeExistingPermissions:(Z)Lorg/apache/hadoop/hbase/protobuf/generated/AccessControlProtos$GrantRequest$Builder;
     102: invokevirtual #23                 // Method org/apache/hadoop/hbase/protobuf/generated/AccessControlProtos$GrantRequest$Builder.build:()Lorg/apache/hadoop/hbase/protobuf/generated/AccessControlProtos$GrantRequest;
     105: areturn

  public static org.apache.hadoop.hbase.protobuf.generated.AccessControlProtos$RevokeRequest buildRevokeRequest(java.lang.String, org.apache.hadoop.hbase.protobuf.generated.AccessControlProtos$Permission$Action...);
    Code:
       0: invokestatic  #2                  // Method org/apache/hadoop/hbase/protobuf/generated/AccessControlProtos$Permission.newBuilder:()Lorg/apache/hadoop/hbase/protobuf/generated/AccessControlProtos$Permission$Builder;
       3: astore_2
       4: invokestatic  #29                 // Method org/apache/hadoop/hbase/protobuf/generated/AccessControlProtos$GlobalPermission.newBuilder:()Lorg/apache/hadoop/hbase/protobuf/generated/AccessControlProtos$GlobalPermission$Builder;
       7: astore_3
       8: aload_1
       9: astore        4
      11: aload         4
      13: arraylength
      14: istore        5
      16: iconst_0
      17: istore        6
      19: iload         6
      21: iload         5
      23: if_icmpge     46
      26: aload         4
      28: iload         6
      30: aaload
      31: astore        7
      33: aload_3
      34: aload         7
      36: invokevirtual #30                 // Method org/apache/hadoop/hbase/protobuf/generated/AccessControlProtos$GlobalPermission$Builder.addAction:(Lorg/apache/hadoop/hbase/protobuf/generated/AccessControlProtos$Permission$Action;)Lorg/apache/hadoop/hbase/protobuf/generated/AccessControlProtos$GlobalPermission$Builder;
      39: pop
      40: iinc          6, 1
      43: goto          19
      46: aload_2
      47: getstatic     #31                 // Field org/apache/hadoop/hbase/protobuf/generated/AccessControlProtos$Permission$Type.Global:Lorg/apache/hadoop/hbase/protobuf/generated/AccessControlProtos$Permission$Type;
      50: invokevirtual #14                 // Method org/apache/hadoop/hbase/protobuf/generated/AccessControlProtos$Permission$Builder.setType:(Lorg/apache/hadoop/hbase/protobuf/generated/AccessControlProtos$Permission$Type;)Lorg/apache/hadoop/hbase/protobuf/generated/AccessControlProtos$Permission$Builder;
      53: aload_3
      54: invokevirtual #32                 // Method org/apache/hadoop/hbase/protobuf/generated/AccessControlProtos$Permission$Builder.setGlobalPermission:(Lorg/apache/hadoop/hbase/protobuf/generated/AccessControlProtos$GlobalPermission$Builder;)Lorg/apache/hadoop/hbase/protobuf/generated/AccessControlProtos$Permission$Builder;
      57: pop
      58: invokestatic  #33                 // Method org/apache/hadoop/hbase/protobuf/generated/AccessControlProtos$RevokeRequest.newBuilder:()Lorg/apache/hadoop/hbase/protobuf/generated/AccessControlProtos$RevokeRequest$Builder;
      61: invokestatic  #17                 // Method org/apache/hadoop/hbase/protobuf/generated/AccessControlProtos$UserPermission.newBuilder:()Lorg/apache/hadoop/hbase/protobuf/generated/AccessControlProtos$UserPermission$Builder;
      64: aload_0
      65: invokestatic  #18                 // Method com/google/protobuf/ByteString.copyFromUtf8:(Ljava/lang/String;)Lcom/google/protobuf/ByteString;
      68: invokevirtual #19                 // Method org/apache/hadoop/hbase/protobuf/generated/AccessControlProtos$UserPermission$Builder.setUser:(Lcom/google/protobuf/ByteString;)Lorg/apache/hadoop/hbase/protobuf/generated/AccessControlProtos$UserPermission$Builder;
      71: aload_2
      72: invokevirtual #20                 // Method org/apache/hadoop/hbase/protobuf/generated/AccessControlProtos$UserPermission$Builder.setPermission:(Lorg/apache/hadoop/hbase/protobuf/generated/AccessControlProtos$Permission$Builder;)Lorg/apache/hadoop/hbase/protobuf/generated/AccessControlProtos$UserPermission$Builder;
      75: invokevirtual #34                 // Method org/apache/hadoop/hbase/protobuf/generated/AccessControlProtos$RevokeRequest$Builder.setUserPermission:(Lorg/apache/hadoop/hbase/protobuf/generated/AccessControlProtos$UserPermission$Builder;)Lorg/apache/hadoop/hbase/protobuf/generated/AccessControlProtos$RevokeRequest$Builder;
      78: invokevirtual #35                 // Method org/apache/hadoop/hbase/protobuf/generated/AccessControlProtos$RevokeRequest$Builder.build:()Lorg/apache/hadoop/hbase/protobuf/generated/AccessControlProtos$RevokeRequest;
      81: areturn

  public static org.apache.hadoop.hbase.protobuf.generated.AccessControlProtos$RevokeRequest buildRevokeRequest(java.lang.String, java.lang.String, org.apache.hadoop.hbase.protobuf.generated.AccessControlProtos$Permission$Action...);
    Code:
       0: invokestatic  #2                  // Method org/apache/hadoop/hbase/protobuf/generated/AccessControlProtos$Permission.newBuilder:()Lorg/apache/hadoop/hbase/protobuf/generated/AccessControlProtos$Permission$Builder;
       3: astore_3
       4: invokestatic  #24                 // Method org/apache/hadoop/hbase/protobuf/generated/AccessControlProtos$NamespacePermission.newBuilder:()Lorg/apache/hadoop/hbase/protobuf/generated/AccessControlProtos$NamespacePermission$Builder;
       7: astore        4
       9: aload_2
      10: astore        5
      12: aload         5
      14: arraylength
      15: istore        6
      17: iconst_0
      18: istore        7
      20: iload         7
      22: iload         6
      24: if_icmpge     48
      27: aload         5
      29: iload         7
      31: aaload
      32: astore        8
      34: aload         4
      36: aload         8
      38: invokevirtual #25                 // Method org/apache/hadoop/hbase/protobuf/generated/AccessControlProtos$NamespacePermission$Builder.addAction:(Lorg/apache/hadoop/hbase/protobuf/generated/AccessControlProtos$Permission$Action;)Lorg/apache/hadoop/hbase/protobuf/generated/AccessControlProtos$NamespacePermission$Builder;
      41: pop
      42: iinc          7, 1
      45: goto          20
      48: aload_1
      49: ifnull        62
      52: aload         4
      54: aload_1
      55: invokestatic  #18                 // Method com/google/protobuf/ByteString.copyFromUtf8:(Ljava/lang/String;)Lcom/google/protobuf/ByteString;
      58: invokevirtual #26                 // Method org/apache/hadoop/hbase/protobuf/generated/AccessControlProtos$NamespacePermission$Builder.setNamespaceName:(Lcom/google/protobuf/ByteString;)Lorg/apache/hadoop/hbase/protobuf/generated/AccessControlProtos$NamespacePermission$Builder;
      61: pop
      62: aload_3
      63: getstatic     #27                 // Field org/apache/hadoop/hbase/protobuf/generated/AccessControlProtos$Permission$Type.Namespace:Lorg/apache/hadoop/hbase/protobuf/generated/AccessControlProtos$Permission$Type;
      66: invokevirtual #14                 // Method org/apache/hadoop/hbase/protobuf/generated/AccessControlProtos$Permission$Builder.setType:(Lorg/apache/hadoop/hbase/protobuf/generated/AccessControlProtos$Permission$Type;)Lorg/apache/hadoop/hbase/protobuf/generated/AccessControlProtos$Permission$Builder;
      69: aload         4
      71: invokevirtual #28                 // Method org/apache/hadoop/hbase/protobuf/generated/AccessControlProtos$Permission$Builder.setNamespacePermission:(Lorg/apache/hadoop/hbase/protobuf/generated/AccessControlProtos$NamespacePermission$Builder;)Lorg/apache/hadoop/hbase/protobuf/generated/AccessControlProtos$Permission$Builder;
      74: pop
      75: invokestatic  #33                 // Method org/apache/hadoop/hbase/protobuf/generated/AccessControlProtos$RevokeRequest.newBuilder:()Lorg/apache/hadoop/hbase/protobuf/generated/AccessControlProtos$RevokeRequest$Builder;
      78: invokestatic  #17                 // Method org/apache/hadoop/hbase/protobuf/generated/AccessControlProtos$UserPermission.newBuilder:()Lorg/apache/hadoop/hbase/protobuf/generated/AccessControlProtos$UserPermission$Builder;
      81: aload_0
      82: invokestatic  #18                 // Method com/google/protobuf/ByteString.copyFromUtf8:(Ljava/lang/String;)Lcom/google/protobuf/ByteString;
      85: invokevirtual #19                 // Method org/apache/hadoop/hbase/protobuf/generated/AccessControlProtos$UserPermission$Builder.setUser:(Lcom/google/protobuf/ByteString;)Lorg/apache/hadoop/hbase/protobuf/generated/AccessControlProtos$UserPermission$Builder;
      88: aload_3
      89: invokevirtual #20                 // Method org/apache/hadoop/hbase/protobuf/generated/AccessControlProtos$UserPermission$Builder.setPermission:(Lorg/apache/hadoop/hbase/protobuf/generated/AccessControlProtos$Permission$Builder;)Lorg/apache/hadoop/hbase/protobuf/generated/AccessControlProtos$UserPermission$Builder;
      92: invokevirtual #34                 // Method org/apache/hadoop/hbase/protobuf/generated/AccessControlProtos$RevokeRequest$Builder.setUserPermission:(Lorg/apache/hadoop/hbase/protobuf/generated/AccessControlProtos$UserPermission$Builder;)Lorg/apache/hadoop/hbase/protobuf/generated/AccessControlProtos$RevokeRequest$Builder;
      95: invokevirtual #35                 // Method org/apache/hadoop/hbase/protobuf/generated/AccessControlProtos$RevokeRequest$Builder.build:()Lorg/apache/hadoop/hbase/protobuf/generated/AccessControlProtos$RevokeRequest;
      98: areturn

  public static org.apache.hadoop.hbase.protobuf.generated.AccessControlProtos$GrantRequest buildGrantRequest(java.lang.String, boolean, org.apache.hadoop.hbase.protobuf.generated.AccessControlProtos$Permission$Action...);
    Code:
       0: invokestatic  #2                  // Method org/apache/hadoop/hbase/protobuf/generated/AccessControlProtos$Permission.newBuilder:()Lorg/apache/hadoop/hbase/protobuf/generated/AccessControlProtos$Permission$Builder;
       3: astore_3
       4: invokestatic  #29                 // Method org/apache/hadoop/hbase/protobuf/generated/AccessControlProtos$GlobalPermission.newBuilder:()Lorg/apache/hadoop/hbase/protobuf/generated/AccessControlProtos$GlobalPermission$Builder;
       7: astore        4
       9: aload_2
      10: astore        5
      12: aload         5
      14: arraylength
      15: istore        6
      17: iconst_0
      18: istore        7
      20: iload         7
      22: iload         6
      24: if_icmpge     48
      27: aload         5
      29: iload         7
      31: aaload
      32: astore        8
      34: aload         4
      36: aload         8
      38: invokevirtual #30                 // Method org/apache/hadoop/hbase/protobuf/generated/AccessControlProtos$GlobalPermission$Builder.addAction:(Lorg/apache/hadoop/hbase/protobuf/generated/AccessControlProtos$Permission$Action;)Lorg/apache/hadoop/hbase/protobuf/generated/AccessControlProtos$GlobalPermission$Builder;
      41: pop
      42: iinc          7, 1
      45: goto          20
      48: aload_3
      49: getstatic     #31                 // Field org/apache/hadoop/hbase/protobuf/generated/AccessControlProtos$Permission$Type.Global:Lorg/apache/hadoop/hbase/protobuf/generated/AccessControlProtos$Permission$Type;
      52: invokevirtual #14                 // Method org/apache/hadoop/hbase/protobuf/generated/AccessControlProtos$Permission$Builder.setType:(Lorg/apache/hadoop/hbase/protobuf/generated/AccessControlProtos$Permission$Type;)Lorg/apache/hadoop/hbase/protobuf/generated/AccessControlProtos$Permission$Builder;
      55: aload         4
      57: invokevirtual #32                 // Method org/apache/hadoop/hbase/protobuf/generated/AccessControlProtos$Permission$Builder.setGlobalPermission:(Lorg/apache/hadoop/hbase/protobuf/generated/AccessControlProtos$GlobalPermission$Builder;)Lorg/apache/hadoop/hbase/protobuf/generated/AccessControlProtos$Permission$Builder;
      60: pop
      61: invokestatic  #16                 // Method org/apache/hadoop/hbase/protobuf/generated/AccessControlProtos$GrantRequest.newBuilder:()Lorg/apache/hadoop/hbase/protobuf/generated/AccessControlProtos$GrantRequest$Builder;
      64: invokestatic  #17                 // Method org/apache/hadoop/hbase/protobuf/generated/AccessControlProtos$UserPermission.newBuilder:()Lorg/apache/hadoop/hbase/protobuf/generated/AccessControlProtos$UserPermission$Builder;
      67: aload_0
      68: invokestatic  #18                 // Method com/google/protobuf/ByteString.copyFromUtf8:(Ljava/lang/String;)Lcom/google/protobuf/ByteString;
      71: invokevirtual #19                 // Method org/apache/hadoop/hbase/protobuf/generated/AccessControlProtos$UserPermission$Builder.setUser:(Lcom/google/protobuf/ByteString;)Lorg/apache/hadoop/hbase/protobuf/generated/AccessControlProtos$UserPermission$Builder;
      74: aload_3
      75: invokevirtual #20                 // Method org/apache/hadoop/hbase/protobuf/generated/AccessControlProtos$UserPermission$Builder.setPermission:(Lorg/apache/hadoop/hbase/protobuf/generated/AccessControlProtos$Permission$Builder;)Lorg/apache/hadoop/hbase/protobuf/generated/AccessControlProtos$UserPermission$Builder;
      78: invokevirtual #21                 // Method org/apache/hadoop/hbase/protobuf/generated/AccessControlProtos$GrantRequest$Builder.setUserPermission:(Lorg/apache/hadoop/hbase/protobuf/generated/AccessControlProtos$UserPermission$Builder;)Lorg/apache/hadoop/hbase/protobuf/generated/AccessControlProtos$GrantRequest$Builder;
      81: iload_1
      82: invokevirtual #22                 // Method org/apache/hadoop/hbase/protobuf/generated/AccessControlProtos$GrantRequest$Builder.setMergeExistingPermissions:(Z)Lorg/apache/hadoop/hbase/protobuf/generated/AccessControlProtos$GrantRequest$Builder;
      85: invokevirtual #23                 // Method org/apache/hadoop/hbase/protobuf/generated/AccessControlProtos$GrantRequest$Builder.build:()Lorg/apache/hadoop/hbase/protobuf/generated/AccessControlProtos$GrantRequest;
      88: areturn

  public static org.apache.hadoop.hbase.protobuf.generated.AccessControlProtos$UsersAndPermissions toUsersAndPermissions(java.lang.String, org.apache.hadoop.hbase.security.access.Permission);
    Code:
       0: invokestatic  #36                 // Method org/apache/hadoop/hbase/protobuf/generated/AccessControlProtos$UsersAndPermissions.newBuilder:()Lorg/apache/hadoop/hbase/protobuf/generated/AccessControlProtos$UsersAndPermissions$Builder;
       3: invokestatic  #37                 // Method org/apache/hadoop/hbase/protobuf/generated/AccessControlProtos$UsersAndPermissions$UserPermissions.newBuilder:()Lorg/apache/hadoop/hbase/protobuf/generated/AccessControlProtos$UsersAndPermissions$UserPermissions$Builder;
       6: aload_0
       7: invokestatic  #18                 // Method com/google/protobuf/ByteString.copyFromUtf8:(Ljava/lang/String;)Lcom/google/protobuf/ByteString;
      10: invokevirtual #38                 // Method org/apache/hadoop/hbase/protobuf/generated/AccessControlProtos$UsersAndPermissions$UserPermissions$Builder.setUser:(Lcom/google/protobuf/ByteString;)Lorg/apache/hadoop/hbase/protobuf/generated/AccessControlProtos$UsersAndPermissions$UserPermissions$Builder;
      13: aload_1
      14: invokestatic  #39                 // Method toPermission:(Lorg/apache/hadoop/hbase/security/access/Permission;)Lorg/apache/hadoop/hbase/protobuf/generated/AccessControlProtos$Permission;
      17: invokevirtual #40                 // Method org/apache/hadoop/hbase/protobuf/generated/AccessControlProtos$UsersAndPermissions$UserPermissions$Builder.addPermissions:(Lorg/apache/hadoop/hbase/protobuf/generated/AccessControlProtos$Permission;)Lorg/apache/hadoop/hbase/protobuf/generated/AccessControlProtos$UsersAndPermissions$UserPermissions$Builder;
      20: invokevirtual #41                 // Method org/apache/hadoop/hbase/protobuf/generated/AccessControlProtos$UsersAndPermissions$UserPermissions$Builder.build:()Lorg/apache/hadoop/hbase/protobuf/generated/AccessControlProtos$UsersAndPermissions$UserPermissions;
      23: invokevirtual #42                 // Method org/apache/hadoop/hbase/protobuf/generated/AccessControlProtos$UsersAndPermissions$Builder.addUserPermissions:(Lorg/apache/hadoop/hbase/protobuf/generated/AccessControlProtos$UsersAndPermissions$UserPermissions;)Lorg/apache/hadoop/hbase/protobuf/generated/AccessControlProtos$UsersAndPermissions$Builder;
      26: invokevirtual #43                 // Method org/apache/hadoop/hbase/protobuf/generated/AccessControlProtos$UsersAndPermissions$Builder.build:()Lorg/apache/hadoop/hbase/protobuf/generated/AccessControlProtos$UsersAndPermissions;
      29: areturn

  public static org.apache.hadoop.hbase.protobuf.generated.AccessControlProtos$UsersAndPermissions toUsersAndPermissions(org.apache.hbase.thirdparty.com.google.common.collect.ListMultimap<java.lang.String, org.apache.hadoop.hbase.security.access.Permission>);
    Code:
       0: invokestatic  #36                 // Method org/apache/hadoop/hbase/protobuf/generated/AccessControlProtos$UsersAndPermissions.newBuilder:()Lorg/apache/hadoop/hbase/protobuf/generated/AccessControlProtos$UsersAndPermissions$Builder;
       3: astore_1
       4: aload_0
       5: invokeinterface #44,  1           // InterfaceMethod org/apache/hbase/thirdparty/com/google/common/collect/ListMultimap.asMap:()Ljava/util/Map;
      10: invokeinterface #45,  1           // InterfaceMethod java/util/Map.entrySet:()Ljava/util/Set;
      15: invokeinterface #46,  1           // InterfaceMethod java/util/Set.iterator:()Ljava/util/Iterator;
      20: astore_2
      21: aload_2
      22: invokeinterface #47,  1           // InterfaceMethod java/util/Iterator.hasNext:()Z
      27: ifeq          128
      30: aload_2
      31: invokeinterface #48,  1           // InterfaceMethod java/util/Iterator.next:()Ljava/lang/Object;
      36: checkcast     #49                 // class java/util/Map$Entry
      39: astore_3
      40: invokestatic  #37                 // Method org/apache/hadoop/hbase/protobuf/generated/AccessControlProtos$UsersAndPermissions$UserPermissions.newBuilder:()Lorg/apache/hadoop/hbase/protobuf/generated/AccessControlProtos$UsersAndPermissions$UserPermissions$Builder;
      43: astore        4
      45: aload         4
      47: aload_3
      48: invokeinterface #50,  1           // InterfaceMethod java/util/Map$Entry.getKey:()Ljava/lang/Object;
      53: checkcast     #51                 // class java/lang/String
      56: invokestatic  #18                 // Method com/google/protobuf/ByteString.copyFromUtf8:(Ljava/lang/String;)Lcom/google/protobuf/ByteString;
      59: invokevirtual #38                 // Method org/apache/hadoop/hbase/protobuf/generated/AccessControlProtos$UsersAndPermissions$UserPermissions$Builder.setUser:(Lcom/google/protobuf/ByteString;)Lorg/apache/hadoop/hbase/protobuf/generated/AccessControlProtos$UsersAndPermissions$UserPermissions$Builder;
      62: pop
      63: aload_3
      64: invokeinterface #52,  1           // InterfaceMethod java/util/Map$Entry.getValue:()Ljava/lang/Object;
      69: checkcast     #53                 // class java/util/Collection
      72: invokeinterface #54,  1           // InterfaceMethod java/util/Collection.iterator:()Ljava/util/Iterator;
      77: astore        5
      79: aload         5
      81: invokeinterface #47,  1           // InterfaceMethod java/util/Iterator.hasNext:()Z
      86: ifeq          115
      89: aload         5
      91: invokeinterface #48,  1           // InterfaceMethod java/util/Iterator.next:()Ljava/lang/Object;
      96: checkcast     #55                 // class org/apache/hadoop/hbase/security/access/Permission
      99: astore        6
     101: aload         4
     103: aload         6
     105: invokestatic  #39                 // Method toPermission:(Lorg/apache/hadoop/hbase/security/access/Permission;)Lorg/apache/hadoop/hbase/protobuf/generated/AccessControlProtos$Permission;
     108: invokevirtual #40                 // Method org/apache/hadoop/hbase/protobuf/generated/AccessControlProtos$UsersAndPermissions$UserPermissions$Builder.addPermissions:(Lorg/apache/hadoop/hbase/protobuf/generated/AccessControlProtos$Permission;)Lorg/apache/hadoop/hbase/protobuf/generated/AccessControlProtos$UsersAndPermissions$UserPermissions$Builder;
     111: pop
     112: goto          79
     115: aload_1
     116: aload         4
     118: invokevirtual #41                 // Method org/apache/hadoop/hbase/protobuf/generated/AccessControlProtos$UsersAndPermissions$UserPermissions$Builder.build:()Lorg/apache/hadoop/hbase/protobuf/generated/AccessControlProtos$UsersAndPermissions$UserPermissions;
     121: invokevirtual #42                 // Method org/apache/hadoop/hbase/protobuf/generated/AccessControlProtos$UsersAndPermissions$Builder.addUserPermissions:(Lorg/apache/hadoop/hbase/protobuf/generated/AccessControlProtos$UsersAndPermissions$UserPermissions;)Lorg/apache/hadoop/hbase/protobuf/generated/AccessControlProtos$UsersAndPermissions$Builder;
     124: pop
     125: goto          21
     128: aload_1
     129: invokevirtual #43                 // Method org/apache/hadoop/hbase/protobuf/generated/AccessControlProtos$UsersAndPermissions$Builder.build:()Lorg/apache/hadoop/hbase/protobuf/generated/AccessControlProtos$UsersAndPermissions;
     132: areturn

  public static org.apache.hbase.thirdparty.com.google.common.collect.ListMultimap<java.lang.String, org.apache.hadoop.hbase.security.access.Permission> toUsersAndPermissions(org.apache.hadoop.hbase.protobuf.generated.AccessControlProtos$UsersAndPermissions);
    Code:
       0: invokestatic  #56                 // Method org/apache/hbase/thirdparty/com/google/common/collect/ArrayListMultimap.create:()Lorg/apache/hbase/thirdparty/com/google/common/collect/ArrayListMultimap;
       3: astore_1
       4: aload_0
       5: invokevirtual #57                 // Method org/apache/hadoop/hbase/protobuf/generated/AccessControlProtos$UsersAndPermissions.getUserPermissionsList:()Ljava/util/List;
       8: invokeinterface #58,  1           // InterfaceMethod java/util/List.iterator:()Ljava/util/Iterator;
      13: astore_2
      14: aload_2
      15: invokeinterface #47,  1           // InterfaceMethod java/util/Iterator.hasNext:()Z
      20: ifeq          95
      23: aload_2
      24: invokeinterface #48,  1           // InterfaceMethod java/util/Iterator.next:()Ljava/lang/Object;
      29: checkcast     #59                 // class org/apache/hadoop/hbase/protobuf/generated/AccessControlProtos$UsersAndPermissions$UserPermissions
      32: astore_3
      33: aload_3
      34: invokevirtual #60                 // Method org/apache/hadoop/hbase/protobuf/generated/AccessControlProtos$UsersAndPermissions$UserPermissions.getUser:()Lcom/google/protobuf/ByteString;
      37: invokevirtual #61                 // Method com/google/protobuf/ByteString.toStringUtf8:()Ljava/lang/String;
      40: astore        4
      42: aload_3
      43: invokevirtual #62                 // Method org/apache/hadoop/hbase/protobuf/generated/AccessControlProtos$UsersAndPermissions$UserPermissions.getPermissionsList:()Ljava/util/List;
      46: invokeinterface #58,  1           // InterfaceMethod java/util/List.iterator:()Ljava/util/Iterator;
      51: astore        5
      53: aload         5
      55: invokeinterface #47,  1           // InterfaceMethod java/util/Iterator.hasNext:()Z
      60: ifeq          92
      63: aload         5
      65: invokeinterface #48,  1           // InterfaceMethod java/util/Iterator.next:()Ljava/lang/Object;
      70: checkcast     #63                 // class org/apache/hadoop/hbase/protobuf/generated/AccessControlProtos$Permission
      73: astore        6
      75: aload_1
      76: aload         4
      78: aload         6
      80: invokestatic  #64                 // Method toPermission:(Lorg/apache/hadoop/hbase/protobuf/generated/AccessControlProtos$Permission;)Lorg/apache/hadoop/hbase/security/access/Permission;
      83: invokeinterface #65,  3           // InterfaceMethod org/apache/hbase/thirdparty/com/google/common/collect/ListMultimap.put:(Ljava/lang/Object;Ljava/lang/Object;)Z
      88: pop
      89: goto          53
      92: goto          14
      95: aload_1
      96: areturn

  public static org.apache.hadoop.hbase.security.access.TablePermission toTablePermission(org.apache.hadoop.hbase.protobuf.generated.AccessControlProtos$TablePermission);
    Code:
       0: aload_0
       1: invokevirtual #66                 // Method org/apache/hadoop/hbase/protobuf/generated/AccessControlProtos$TablePermission.getActionList:()Ljava/util/List;
       4: invokestatic  #67                 // Method toPermissionActions:(Ljava/util/List;)[Lorg/apache/hadoop/hbase/security/access/Permission$Action;
       7: astore_1
       8: aconst_null
       9: astore_2
      10: aconst_null
      11: astore_3
      12: aconst_null
      13: astore        4
      15: aload_0
      16: invokevirtual #68                 // Method org/apache/hadoop/hbase/protobuf/generated/AccessControlProtos$TablePermission.hasTableName:()Z
      19: ifne          32
      22: new           #69                 // class java/lang/IllegalStateException
      25: dup
      26: ldc           #70                 // String TableName cannot be empty
      28: invokespecial #71                 // Method java/lang/IllegalStateException."<init>":(Ljava/lang/String;)V
      31: athrow
      32: aload_0
      33: invokevirtual #72                 // Method org/apache/hadoop/hbase/protobuf/generated/AccessControlProtos$TablePermission.getTableName:()Lorg/apache/hadoop/hbase/protobuf/generated/HBaseProtos$TableName;
      36: invokestatic  #73                 // Method org/apache/hadoop/hbase/protobuf/ProtobufUtil.toTableName:(Lorg/apache/hadoop/hbase/protobuf/generated/HBaseProtos$TableName;)Lorg/apache/hadoop/hbase/TableName;
      39: astore_2
      40: aload_0
      41: invokevirtual #74                 // Method org/apache/hadoop/hbase/protobuf/generated/AccessControlProtos$TablePermission.hasFamily:()Z
      44: ifeq          56
      47: aload_0
      48: invokevirtual #75                 // Method org/apache/hadoop/hbase/protobuf/generated/AccessControlProtos$TablePermission.getFamily:()Lcom/google/protobuf/ByteString;
      51: invokevirtual #76                 // Method com/google/protobuf/ByteString.toByteArray:()[B
      54: astore        4
      56: aload_0
      57: invokevirtual #77                 // Method org/apache/hadoop/hbase/protobuf/generated/AccessControlProtos$TablePermission.hasQualifier:()Z
      60: ifeq          71
      63: aload_0
      64: invokevirtual #78                 // Method org/apache/hadoop/hbase/protobuf/generated/AccessControlProtos$TablePermission.getQualifier:()Lcom/google/protobuf/ByteString;
      67: invokevirtual #76                 // Method com/google/protobuf/ByteString.toByteArray:()[B
      70: astore_3
      71: new           #79                 // class org/apache/hadoop/hbase/security/access/TablePermission
      74: dup
      75: aload_2
      76: aload         4
      78: aload_3
      79: aload_1
      80: invokespecial #80                 // Method org/apache/hadoop/hbase/security/access/TablePermission."<init>":(Lorg/apache/hadoop/hbase/TableName;[B[B[Lorg/apache/hadoop/hbase/security/access/Permission$Action;)V
      83: areturn

  public static org.apache.hadoop.hbase.security.access.Permission toPermission(org.apache.hadoop.hbase.protobuf.generated.AccessControlProtos$Permission);
    Code:
       0: aload_0
       1: invokevirtual #81                 // Method org/apache/hadoop/hbase/protobuf/generated/AccessControlProtos$Permission.getType:()Lorg/apache/hadoop/hbase/protobuf/generated/AccessControlProtos$Permission$Type;
       4: getstatic     #31                 // Field org/apache/hadoop/hbase/protobuf/generated/AccessControlProtos$Permission$Type.Global:Lorg/apache/hadoop/hbase/protobuf/generated/AccessControlProtos$Permission$Type;
       7: if_acmpne     34
      10: aload_0
      11: invokevirtual #82                 // Method org/apache/hadoop/hbase/protobuf/generated/AccessControlProtos$Permission.getGlobalPermission:()Lorg/apache/hadoop/hbase/protobuf/generated/AccessControlProtos$GlobalPermission;
      14: astore_1
      15: aload_1
      16: invokevirtual #83                 // Method org/apache/hadoop/hbase/protobuf/generated/AccessControlProtos$GlobalPermission.getActionList:()Ljava/util/List;
      19: invokestatic  #67                 // Method toPermissionActions:(Ljava/util/List;)[Lorg/apache/hadoop/hbase/security/access/Permission$Action;
      22: astore_2
      23: invokestatic  #84                 // Method org/apache/hadoop/hbase/security/access/Permission.newBuilder:()Lorg/apache/hadoop/hbase/security/access/Permission$Builder;
      26: aload_2
      27: invokevirtual #85                 // Method org/apache/hadoop/hbase/security/access/Permission$Builder.withActions:([Lorg/apache/hadoop/hbase/security/access/Permission$Action;)Lorg/apache/hadoop/hbase/security/access/Permission$Builder;
      30: invokevirtual #86                 // Method org/apache/hadoop/hbase/security/access/Permission$Builder.build:()Lorg/apache/hadoop/hbase/security/access/Permission;
      33: areturn
      34: aload_0
      35: invokevirtual #81                 // Method org/apache/hadoop/hbase/protobuf/generated/AccessControlProtos$Permission.getType:()Lorg/apache/hadoop/hbase/protobuf/generated/AccessControlProtos$Permission$Type;
      38: getstatic     #27                 // Field org/apache/hadoop/hbase/protobuf/generated/AccessControlProtos$Permission$Type.Namespace:Lorg/apache/hadoop/hbase/protobuf/generated/AccessControlProtos$Permission$Type;
      41: if_acmpne     92
      44: aload_0
      45: invokevirtual #87                 // Method org/apache/hadoop/hbase/protobuf/generated/AccessControlProtos$Permission.getNamespacePermission:()Lorg/apache/hadoop/hbase/protobuf/generated/AccessControlProtos$NamespacePermission;
      48: astore_1
      49: aload_1
      50: invokevirtual #88                 // Method org/apache/hadoop/hbase/protobuf/generated/AccessControlProtos$NamespacePermission.getActionList:()Ljava/util/List;
      53: invokestatic  #67                 // Method toPermissionActions:(Ljava/util/List;)[Lorg/apache/hadoop/hbase/security/access/Permission$Action;
      56: astore_2
      57: aload_0
      58: invokevirtual #89                 // Method org/apache/hadoop/hbase/protobuf/generated/AccessControlProtos$Permission.hasNamespacePermission:()Z
      61: ifne          74
      64: new           #69                 // class java/lang/IllegalStateException
      67: dup
      68: ldc           #90                 // String Namespace must not be empty in NamespacePermission
      70: invokespecial #71                 // Method java/lang/IllegalStateException."<init>":(Ljava/lang/String;)V
      73: athrow
      74: aload_1
      75: invokevirtual #91                 // Method org/apache/hadoop/hbase/protobuf/generated/AccessControlProtos$NamespacePermission.getNamespaceName:()Lcom/google/protobuf/ByteString;
      78: invokevirtual #61                 // Method com/google/protobuf/ByteString.toStringUtf8:()Ljava/lang/String;
      81: invokestatic  #92                 // Method org/apache/hadoop/hbase/security/access/Permission.newBuilder:(Ljava/lang/String;)Lorg/apache/hadoop/hbase/security/access/Permission$Builder;
      84: aload_2
      85: invokevirtual #85                 // Method org/apache/hadoop/hbase/security/access/Permission$Builder.withActions:([Lorg/apache/hadoop/hbase/security/access/Permission$Action;)Lorg/apache/hadoop/hbase/security/access/Permission$Builder;
      88: invokevirtual #86                 // Method org/apache/hadoop/hbase/security/access/Permission$Builder.build:()Lorg/apache/hadoop/hbase/security/access/Permission;
      91: areturn
      92: aload_0
      93: invokevirtual #81                 // Method org/apache/hadoop/hbase/protobuf/generated/AccessControlProtos$Permission.getType:()Lorg/apache/hadoop/hbase/protobuf/generated/AccessControlProtos$Permission$Type;
      96: getstatic     #13                 // Field org/apache/hadoop/hbase/protobuf/generated/AccessControlProtos$Permission$Type.Table:Lorg/apache/hadoop/hbase/protobuf/generated/AccessControlProtos$Permission$Type;
      99: if_acmpne     202
     102: aload_0
     103: invokevirtual #93                 // Method org/apache/hadoop/hbase/protobuf/generated/AccessControlProtos$Permission.getTablePermission:()Lorg/apache/hadoop/hbase/protobuf/generated/AccessControlProtos$TablePermission;
     106: astore_1
     107: aload_1
     108: invokevirtual #66                 // Method org/apache/hadoop/hbase/protobuf/generated/AccessControlProtos$TablePermission.getActionList:()Ljava/util/List;
     111: invokestatic  #67                 // Method toPermissionActions:(Ljava/util/List;)[Lorg/apache/hadoop/hbase/security/access/Permission$Action;
     114: astore_2
     115: aconst_null
     116: astore_3
     117: aconst_null
     118: astore        4
     120: aconst_null
     121: astore        5
     123: aload_1
     124: invokevirtual #68                 // Method org/apache/hadoop/hbase/protobuf/generated/AccessControlProtos$TablePermission.hasTableName:()Z
     127: ifne          140
     130: new           #69                 // class java/lang/IllegalStateException
     133: dup
     134: ldc           #70                 // String TableName cannot be empty
     136: invokespecial #71                 // Method java/lang/IllegalStateException."<init>":(Ljava/lang/String;)V
     139: athrow
     140: aload_1
     141: invokevirtual #72                 // Method org/apache/hadoop/hbase/protobuf/generated/AccessControlProtos$TablePermission.getTableName:()Lorg/apache/hadoop/hbase/protobuf/generated/HBaseProtos$TableName;
     144: invokestatic  #73                 // Method org/apache/hadoop/hbase/protobuf/ProtobufUtil.toTableName:(Lorg/apache/hadoop/hbase/protobuf/generated/HBaseProtos$TableName;)Lorg/apache/hadoop/hbase/TableName;
     147: astore        5
     149: aload_1
     150: invokevirtual #74                 // Method org/apache/hadoop/hbase/protobuf/generated/AccessControlProtos$TablePermission.hasFamily:()Z
     153: ifeq          165
     156: aload_1
     157: invokevirtual #75                 // Method org/apache/hadoop/hbase/protobuf/generated/AccessControlProtos$TablePermission.getFamily:()Lcom/google/protobuf/ByteString;
     160: invokevirtual #76                 // Method com/google/protobuf/ByteString.toByteArray:()[B
     163: astore        4
     165: aload_1
     166: invokevirtual #77                 // Method org/apache/hadoop/hbase/protobuf/generated/AccessControlProtos$TablePermission.hasQualifier:()Z
     169: ifeq          180
     172: aload_1
     173: invokevirtual #78                 // Method org/apache/hadoop/hbase/protobuf/generated/AccessControlProtos$TablePermission.getQualifier:()Lcom/google/protobuf/ByteString;
     176: invokevirtual #76                 // Method com/google/protobuf/ByteString.toByteArray:()[B
     179: astore_3
     180: aload         5
     182: invokestatic  #94                 // Method org/apache/hadoop/hbase/security/access/Permission.newBuilder:(Lorg/apache/hadoop/hbase/TableName;)Lorg/apache/hadoop/hbase/security/access/Permission$Builder;
     185: aload         4
     187: invokevirtual #95                 // Method org/apache/hadoop/hbase/security/access/Permission$Builder.withFamily:([B)Lorg/apache/hadoop/hbase/security/access/Permission$Builder;
     190: aload_3
     191: invokevirtual #96                 // Method org/apache/hadoop/hbase/security/access/Permission$Builder.withQualifier:([B)Lorg/apache/hadoop/hbase/security/access/Permission$Builder;
     194: aload_2
     195: invokevirtual #85                 // Method org/apache/hadoop/hbase/security/access/Permission$Builder.withActions:([Lorg/apache/hadoop/hbase/security/access/Permission$Action;)Lorg/apache/hadoop/hbase/security/access/Permission$Builder;
     198: invokevirtual #86                 // Method org/apache/hadoop/hbase/security/access/Permission$Builder.build:()Lorg/apache/hadoop/hbase/security/access/Permission;
     201: areturn
     202: new           #69                 // class java/lang/IllegalStateException
     205: dup
     206: new           #97                 // class java/lang/StringBuilder
     209: dup
     210: invokespecial #98                 // Method java/lang/StringBuilder."<init>":()V
     213: ldc           #99                 // String Unrecognize Perm Type:
     215: invokevirtual #100                // Method java/lang/StringBuilder.append:(Ljava/lang/String;)Ljava/lang/StringBuilder;
     218: aload_0
     219: invokevirtual #81                 // Method org/apache/hadoop/hbase/protobuf/generated/AccessControlProtos$Permission.getType:()Lorg/apache/hadoop/hbase/protobuf/generated/AccessControlProtos$Permission$Type;
     222: invokevirtual #101                // Method java/lang/StringBuilder.append:(Ljava/lang/Object;)Ljava/lang/StringBuilder;
     225: invokevirtual #102                // Method java/lang/StringBuilder.toString:()Ljava/lang/String;
     228: invokespecial #71                 // Method java/lang/IllegalStateException."<init>":(Ljava/lang/String;)V
     231: athrow

  public static org.apache.hadoop.hbase.protobuf.generated.AccessControlProtos$Permission toPermission(org.apache.hadoop.hbase.security.access.Permission);
    Code:
       0: invokestatic  #2                  // Method org/apache/hadoop/hbase/protobuf/generated/AccessControlProtos$Permission.newBuilder:()Lorg/apache/hadoop/hbase/protobuf/generated/AccessControlProtos$Permission$Builder;
       3: astore_1
       4: aload_0
       5: instanceof    #103                // class org/apache/hadoop/hbase/security/access/NamespacePermission
       8: ifeq          102
      11: aload_0
      12: checkcast     #103                // class org/apache/hadoop/hbase/security/access/NamespacePermission
      15: astore_2
      16: aload_1
      17: getstatic     #27                 // Field org/apache/hadoop/hbase/protobuf/generated/AccessControlProtos$Permission$Type.Namespace:Lorg/apache/hadoop/hbase/protobuf/generated/AccessControlProtos$Permission$Type;
      20: invokevirtual #14                 // Method org/apache/hadoop/hbase/protobuf/generated/AccessControlProtos$Permission$Builder.setType:(Lorg/apache/hadoop/hbase/protobuf/generated/AccessControlProtos$Permission$Type;)Lorg/apache/hadoop/hbase/protobuf/generated/AccessControlProtos$Permission$Builder;
      23: pop
      24: invokestatic  #24                 // Method org/apache/hadoop/hbase/protobuf/generated/AccessControlProtos$NamespacePermission.newBuilder:()Lorg/apache/hadoop/hbase/protobuf/generated/AccessControlProtos$NamespacePermission$Builder;
      27: astore_3
      28: aload_3
      29: aload_2
      30: invokevirtual #104                // Method org/apache/hadoop/hbase/security/access/NamespacePermission.getNamespace:()Ljava/lang/String;
      33: invokestatic  #18                 // Method com/google/protobuf/ByteString.copyFromUtf8:(Ljava/lang/String;)Lcom/google/protobuf/ByteString;
      36: invokevirtual #26                 // Method org/apache/hadoop/hbase/protobuf/generated/AccessControlProtos$NamespacePermission$Builder.setNamespaceName:(Lcom/google/protobuf/ByteString;)Lorg/apache/hadoop/hbase/protobuf/generated/AccessControlProtos$NamespacePermission$Builder;
      39: pop
      40: aload_0
      41: invokevirtual #105                // Method org/apache/hadoop/hbase/security/access/Permission.getActions:()[Lorg/apache/hadoop/hbase/security/access/Permission$Action;
      44: astore        4
      46: aload         4
      48: ifnull        93
      51: aload         4
      53: astore        5
      55: aload         5
      57: arraylength
      58: istore        6
      60: iconst_0
      61: istore        7
      63: iload         7
      65: iload         6
      67: if_icmpge     93
      70: aload         5
      72: iload         7
      74: aaload
      75: astore        8
      77: aload_3
      78: aload         8
      80: invokestatic  #106                // Method toPermissionAction:(Lorg/apache/hadoop/hbase/security/access/Permission$Action;)Lorg/apache/hadoop/hbase/protobuf/generated/AccessControlProtos$Permission$Action;
      83: invokevirtual #25                 // Method org/apache/hadoop/hbase/protobuf/generated/AccessControlProtos$NamespacePermission$Builder.addAction:(Lorg/apache/hadoop/hbase/protobuf/generated/AccessControlProtos$Permission$Action;)Lorg/apache/hadoop/hbase/protobuf/generated/AccessControlProtos$NamespacePermission$Builder;
      86: pop
      87: iinc          7, 1
      90: goto          63
      93: aload_1
      94: aload_3
      95: invokevirtual #28                 // Method org/apache/hadoop/hbase/protobuf/generated/AccessControlProtos$Permission$Builder.setNamespacePermission:(Lorg/apache/hadoop/hbase/protobuf/generated/AccessControlProtos$NamespacePermission$Builder;)Lorg/apache/hadoop/hbase/protobuf/generated/AccessControlProtos$Permission$Builder;
      98: pop
      99: goto          306
     102: aload_0
     103: instanceof    #79                 // class org/apache/hadoop/hbase/security/access/TablePermission
     106: ifeq          238
     109: aload_0
     110: checkcast     #79                 // class org/apache/hadoop/hbase/security/access/TablePermission
     113: astore_2
     114: aload_1
     115: getstatic     #13                 // Field org/apache/hadoop/hbase/protobuf/generated/AccessControlProtos$Permission$Type.Table:Lorg/apache/hadoop/hbase/protobuf/generated/AccessControlProtos$Permission$Type;
     118: invokevirtual #14                 // Method org/apache/hadoop/hbase/protobuf/generated/AccessControlProtos$Permission$Builder.setType:(Lorg/apache/hadoop/hbase/protobuf/generated/AccessControlProtos$Permission$Type;)Lorg/apache/hadoop/hbase/protobuf/generated/AccessControlProtos$Permission$Builder;
     121: pop
     122: invokestatic  #3                  // Method org/apache/hadoop/hbase/protobuf/generated/AccessControlProtos$TablePermission.newBuilder:()Lorg/apache/hadoop/hbase/protobuf/generated/AccessControlProtos$TablePermission$Builder;
     125: astore_3
     126: aload_3
     127: aload_2
     128: invokevirtual #107                // Method org/apache/hadoop/hbase/security/access/TablePermission.getTableName:()Lorg/apache/hadoop/hbase/TableName;
     131: invokestatic  #8                  // Method org/apache/hadoop/hbase/protobuf/ProtobufUtil.toProtoTableName:(Lorg/apache/hadoop/hbase/TableName;)Lorg/apache/hadoop/hbase/protobuf/generated/HBaseProtos$TableName;
     134: invokevirtual #9                  // Method org/apache/hadoop/hbase/protobuf/generated/AccessControlProtos$TablePermission$Builder.setTableName:(Lorg/apache/hadoop/hbase/protobuf/generated/HBaseProtos$TableName;)Lorg/apache/hadoop/hbase/protobuf/generated/AccessControlProtos$TablePermission$Builder;
     137: pop
     138: aload_2
     139: invokevirtual #108                // Method org/apache/hadoop/hbase/security/access/TablePermission.hasFamily:()Z
     142: ifeq          157
     145: aload_3
     146: aload_2
     147: invokevirtual #109                // Method org/apache/hadoop/hbase/security/access/TablePermission.getFamily:()[B
     150: invokestatic  #10                 // Method org/apache/hadoop/hbase/util/ByteStringer.wrap:([B)Lcom/google/protobuf/ByteString;
     153: invokevirtual #11                 // Method org/apache/hadoop/hbase/protobuf/generated/AccessControlProtos$TablePermission$Builder.setFamily:(Lcom/google/protobuf/ByteString;)Lorg/apache/hadoop/hbase/protobuf/generated/AccessControlProtos$TablePermission$Builder;
     156: pop
     157: aload_2
     158: invokevirtual #110                // Method org/apache/hadoop/hbase/security/access/TablePermission.hasQualifier:()Z
     161: ifeq          176
     164: aload_3
     165: aload_2
     166: invokevirtual #111                // Method org/apache/hadoop/hbase/security/access/TablePermission.getQualifier:()[B
     169: invokestatic  #10                 // Method org/apache/hadoop/hbase/util/ByteStringer.wrap:([B)Lcom/google/protobuf/ByteString;
     172: invokevirtual #12                 // Method org/apache/hadoop/hbase/protobuf/generated/AccessControlProtos$TablePermission$Builder.setQualifier:(Lcom/google/protobuf/ByteString;)Lorg/apache/hadoop/hbase/protobuf/generated/AccessControlProtos$TablePermission$Builder;
     175: pop
     176: aload_0
     177: invokevirtual #105                // Method org/apache/hadoop/hbase/security/access/Permission.getActions:()[Lorg/apache/hadoop/hbase/security/access/Permission$Action;
     180: astore        4
     182: aload         4
     184: ifnull        229
     187: aload         4
     189: astore        5
     191: aload         5
     193: arraylength
     194: istore        6
     196: iconst_0
     197: istore        7
     199: iload         7
     201: iload         6
     203: if_icmpge     229
     206: aload         5
     208: iload         7
     210: aaload
     211: astore        8
     213: aload_3
     214: aload         8
     216: invokestatic  #106                // Method toPermissionAction:(Lorg/apache/hadoop/hbase/security/access/Permission$Action;)Lorg/apache/hadoop/hbase/protobuf/generated/AccessControlProtos$Permission$Action;
     219: invokevirtual #4                  // Method org/apache/hadoop/hbase/protobuf/generated/AccessControlProtos$TablePermission$Builder.addAction:(Lorg/apache/hadoop/hbase/protobuf/generated/AccessControlProtos$Permission$Action;)Lorg/apache/hadoop/hbase/protobuf/generated/AccessControlProtos$TablePermission$Builder;
     222: pop
     223: iinc          7, 1
     226: goto          199
     229: aload_1
     230: aload_3
     231: invokevirtual #15                 // Method org/apache/hadoop/hbase/protobuf/generated/AccessControlProtos$Permission$Builder.setTablePermission:(Lorg/apache/hadoop/hbase/protobuf/generated/AccessControlProtos$TablePermission$Builder;)Lorg/apache/hadoop/hbase/protobuf/generated/AccessControlProtos$Permission$Builder;
     234: pop
     235: goto          306
     238: aload_1
     239: getstatic     #31                 // Field org/apache/hadoop/hbase/protobuf/generated/AccessControlProtos$Permission$Type.Global:Lorg/apache/hadoop/hbase/protobuf/generated/AccessControlProtos$Permission$Type;
     242: invokevirtual #14                 // Method org/apache/hadoop/hbase/protobuf/generated/AccessControlProtos$Permission$Builder.setType:(Lorg/apache/hadoop/hbase/protobuf/generated/AccessControlProtos$Permission$Type;)Lorg/apache/hadoop/hbase/protobuf/generated/AccessControlProtos$Permission$Builder;
     245: pop
     246: invokestatic  #29                 // Method org/apache/hadoop/hbase/protobuf/generated/AccessControlProtos$GlobalPermission.newBuilder:()Lorg/apache/hadoop/hbase/protobuf/generated/AccessControlProtos$GlobalPermission$Builder;
     249: astore_2
     250: aload_0
     251: invokevirtual #105                // Method org/apache/hadoop/hbase/security/access/Permission.getActions:()[Lorg/apache/hadoop/hbase/security/access/Permission$Action;
     254: astore_3
     255: aload_3
     256: ifnull        300
     259: aload_3
     260: astore        4
     262: aload         4
     264: arraylength
     265: istore        5
     267: iconst_0
     268: istore        6
     270: iload         6
     272: iload         5
     274: if_icmpge     300
     277: aload         4
     279: iload         6
     281: aaload
     282: astore        7
     284: aload_2
     285: aload         7
     287: invokestatic  #106                // Method toPermissionAction:(Lorg/apache/hadoop/hbase/security/access/Permission$Action;)Lorg/apache/hadoop/hbase/protobuf/generated/AccessControlProtos$Permission$Action;
     290: invokevirtual #30                 // Method org/apache/hadoop/hbase/protobuf/generated/AccessControlProtos$GlobalPermission$Builder.addAction:(Lorg/apache/hadoop/hbase/protobuf/generated/AccessControlProtos$Permission$Action;)Lorg/apache/hadoop/hbase/protobuf/generated/AccessControlProtos$GlobalPermission$Builder;
     293: pop
     294: iinc          6, 1
     297: goto          270
     300: aload_1
     301: aload_2
     302: invokevirtual #32                 // Method org/apache/hadoop/hbase/protobuf/generated/AccessControlProtos$Permission$Builder.setGlobalPermission:(Lorg/apache/hadoop/hbase/protobuf/generated/AccessControlProtos$GlobalPermission$Builder;)Lorg/apache/hadoop/hbase/protobuf/generated/AccessControlProtos$Permission$Builder;
     305: pop
     306: aload_1
     307: invokevirtual #112                // Method org/apache/hadoop/hbase/protobuf/generated/AccessControlProtos$Permission$Builder.build:()Lorg/apache/hadoop/hbase/protobuf/generated/AccessControlProtos$Permission;
     310: areturn

  public static org.apache.hadoop.hbase.security.access.Permission$Action[] toPermissionActions(java.util.List<org.apache.hadoop.hbase.protobuf.generated.AccessControlProtos$Permission$Action>);
    Code:
       0: aload_0
       1: invokeinterface #113,  1          // InterfaceMethod java/util/List.size:()I
       6: anewarray     #114                // class org/apache/hadoop/hbase/security/access/Permission$Action
       9: astore_1
      10: iconst_0
      11: istore_2
      12: iload_2
      13: aload_0
      14: invokeinterface #113,  1          // InterfaceMethod java/util/List.size:()I
      19: if_icmpge     44
      22: aload_1
      23: iload_2
      24: aload_0
      25: iload_2
      26: invokeinterface #115,  2          // InterfaceMethod java/util/List.get:(I)Ljava/lang/Object;
      31: checkcast     #116                // class org/apache/hadoop/hbase/protobuf/generated/AccessControlProtos$Permission$Action
      34: invokestatic  #117                // Method toPermissionAction:(Lorg/apache/hadoop/hbase/protobuf/generated/AccessControlProtos$Permission$Action;)Lorg/apache/hadoop/hbase/security/access/Permission$Action;
      37: aastore
      38: iinc          2, 1
      41: goto          12
      44: aload_1
      45: areturn

  public static org.apache.hadoop.hbase.security.access.Permission$Action toPermissionAction(org.apache.hadoop.hbase.protobuf.generated.AccessControlProtos$Permission$Action);
    Code:
       0: getstatic     #118                // Field org/apache/hadoop/hbase/security/access/AccessControlUtil$1.$SwitchMap$org$apache$hadoop$hbase$protobuf$generated$AccessControlProtos$Permission$Action:[I
       3: aload_0
       4: invokevirtual #119                // Method org/apache/hadoop/hbase/protobuf/generated/AccessControlProtos$Permission$Action.ordinal:()I
       7: iaload
       8: tableswitch   { // 1 to 5
                     1: 44
                     2: 48
                     3: 52
                     4: 56
                     5: 60
               default: 64
          }
      44: getstatic     #120                // Field org/apache/hadoop/hbase/security/access/Permission$Action.READ:Lorg/apache/hadoop/hbase/security/access/Permission$Action;
      47: areturn
      48: getstatic     #121                // Field org/apache/hadoop/hbase/security/access/Permission$Action.WRITE:Lorg/apache/hadoop/hbase/security/access/Permission$Action;
      51: areturn
      52: getstatic     #122                // Field org/apache/hadoop/hbase/security/access/Permission$Action.EXEC:Lorg/apache/hadoop/hbase/security/access/Permission$Action;
      55: areturn
      56: getstatic     #123                // Field org/apache/hadoop/hbase/security/access/Permission$Action.CREATE:Lorg/apache/hadoop/hbase/security/access/Permission$Action;
      59: areturn
      60: getstatic     #124                // Field org/apache/hadoop/hbase/security/access/Permission$Action.ADMIN:Lorg/apache/hadoop/hbase/security/access/Permission$Action;
      63: areturn
      64: new           #125                // class java/lang/IllegalArgumentException
      67: dup
      68: new           #97                 // class java/lang/StringBuilder
      71: dup
      72: invokespecial #98                 // Method java/lang/StringBuilder."<init>":()V
      75: ldc           #126                // String Unknown action value
      77: invokevirtual #100                // Method java/lang/StringBuilder.append:(Ljava/lang/String;)Ljava/lang/StringBuilder;
      80: aload_0
      81: invokevirtual #127                // Method org/apache/hadoop/hbase/protobuf/generated/AccessControlProtos$Permission$Action.name:()Ljava/lang/String;
      84: invokevirtual #100                // Method java/lang/StringBuilder.append:(Ljava/lang/String;)Ljava/lang/StringBuilder;
      87: invokevirtual #102                // Method java/lang/StringBuilder.toString:()Ljava/lang/String;
      90: invokespecial #128                // Method java/lang/IllegalArgumentException."<init>":(Ljava/lang/String;)V
      93: athrow

  public static org.apache.hadoop.hbase.protobuf.generated.AccessControlProtos$Permission$Action toPermissionAction(org.apache.hadoop.hbase.security.access.Permission$Action);
    Code:
       0: getstatic     #129                // Field org/apache/hadoop/hbase/security/access/AccessControlUtil$1.$SwitchMap$org$apache$hadoop$hbase$security$access$Permission$Action:[I
       3: aload_0
       4: invokevirtual #130                // Method org/apache/hadoop/hbase/security/access/Permission$Action.ordinal:()I
       7: iaload
       8: tableswitch   { // 1 to 5
                     1: 44
                     2: 48
                     3: 52
                     4: 56
                     5: 60
               default: 64
          }
      44: getstatic     #131                // Field org/apache/hadoop/hbase/protobuf/generated/AccessControlProtos$Permission$Action.READ:Lorg/apache/hadoop/hbase/protobuf/generated/AccessControlProtos$Permission$Action;
      47: areturn
      48: getstatic     #132                // Field org/apache/hadoop/hbase/protobuf/generated/AccessControlProtos$Permission$Action.WRITE:Lorg/apache/hadoop/hbase/protobuf/generated/AccessControlProtos$Permission$Action;
      51: areturn
      52: getstatic     #133                // Field org/apache/hadoop/hbase/protobuf/generated/AccessControlProtos$Permission$Action.EXEC:Lorg/apache/hadoop/hbase/protobuf/generated/AccessControlProtos$Permission$Action;
      55: areturn
      56: getstatic     #134                // Field org/apache/hadoop/hbase/protobuf/generated/AccessControlProtos$Permission$Action.CREATE:Lorg/apache/hadoop/hbase/protobuf/generated/AccessControlProtos$Permission$Action;
      59: areturn
      60: getstatic     #135                // Field org/apache/hadoop/hbase/protobuf/generated/AccessControlProtos$Permission$Action.ADMIN:Lorg/apache/hadoop/hbase/protobuf/generated/AccessControlProtos$Permission$Action;
      63: areturn
      64: new           #125                // class java/lang/IllegalArgumentException
      67: dup
      68: new           #97                 // class java/lang/StringBuilder
      71: dup
      72: invokespecial #98                 // Method java/lang/StringBuilder."<init>":()V
      75: ldc           #126                // String Unknown action value
      77: invokevirtual #100                // Method java/lang/StringBuilder.append:(Ljava/lang/String;)Ljava/lang/StringBuilder;
      80: aload_0
      81: invokevirtual #136                // Method org/apache/hadoop/hbase/security/access/Permission$Action.name:()Ljava/lang/String;
      84: invokevirtual #100                // Method java/lang/StringBuilder.append:(Ljava/lang/String;)Ljava/lang/StringBuilder;
      87: invokevirtual #102                // Method java/lang/StringBuilder.toString:()Ljava/lang/String;
      90: invokespecial #128                // Method java/lang/IllegalArgumentException."<init>":(Ljava/lang/String;)V
      93: athrow

  public static org.apache.hadoop.hbase.protobuf.generated.AccessControlProtos$UserPermission toUserPermission(org.apache.hadoop.hbase.security.access.UserPermission);
    Code:
       0: invokestatic  #17                 // Method org/apache/hadoop/hbase/protobuf/generated/AccessControlProtos$UserPermission.newBuilder:()Lorg/apache/hadoop/hbase/protobuf/generated/AccessControlProtos$UserPermission$Builder;
       3: aload_0
       4: invokevirtual #137                // Method org/apache/hadoop/hbase/security/access/UserPermission.getUser:()Ljava/lang/String;
       7: invokestatic  #18                 // Method com/google/protobuf/ByteString.copyFromUtf8:(Ljava/lang/String;)Lcom/google/protobuf/ByteString;
      10: invokevirtual #19                 // Method org/apache/hadoop/hbase/protobuf/generated/AccessControlProtos$UserPermission$Builder.setUser:(Lcom/google/protobuf/ByteString;)Lorg/apache/hadoop/hbase/protobuf/generated/AccessControlProtos$UserPermission$Builder;
      13: aload_0
      14: invokevirtual #138                // Method org/apache/hadoop/hbase/security/access/UserPermission.getPermission:()Lorg/apache/hadoop/hbase/security/access/Permission;
      17: invokestatic  #39                 // Method toPermission:(Lorg/apache/hadoop/hbase/security/access/Permission;)Lorg/apache/hadoop/hbase/protobuf/generated/AccessControlProtos$Permission;
      20: invokevirtual #139                // Method org/apache/hadoop/hbase/protobuf/generated/AccessControlProtos$UserPermission$Builder.setPermission:(Lorg/apache/hadoop/hbase/protobuf/generated/AccessControlProtos$Permission;)Lorg/apache/hadoop/hbase/protobuf/generated/AccessControlProtos$UserPermission$Builder;
      23: invokevirtual #140                // Method org/apache/hadoop/hbase/protobuf/generated/AccessControlProtos$UserPermission$Builder.build:()Lorg/apache/hadoop/hbase/protobuf/generated/AccessControlProtos$UserPermission;
      26: areturn

  public static org.apache.hadoop.hbase.protobuf.generated.AccessControlProtos$GetUserPermissionsResponse buildGetUserPermissionsResponse(java.util.List<org.apache.hadoop.hbase.security.access.UserPermission>);
    Code:
       0: invokestatic  #141                // Method org/apache/hadoop/hbase/protobuf/generated/AccessControlProtos$GetUserPermissionsResponse.newBuilder:()Lorg/apache/hadoop/hbase/protobuf/generated/AccessControlProtos$GetUserPermissionsResponse$Builder;
       3: astore_1
       4: aload_0
       5: invokeinterface #58,  1           // InterfaceMethod java/util/List.iterator:()Ljava/util/Iterator;
      10: astore_2
      11: aload_2
      12: invokeinterface #47,  1           // InterfaceMethod java/util/Iterator.hasNext:()Z
      17: ifeq          42
      20: aload_2
      21: invokeinterface #48,  1           // InterfaceMethod java/util/Iterator.next:()Ljava/lang/Object;
      26: checkcast     #142                // class org/apache/hadoop/hbase/security/access/UserPermission
      29: astore_3
      30: aload_1
      31: aload_3
      32: invokestatic  #143                // Method toUserPermission:(Lorg/apache/hadoop/hbase/security/access/UserPermission;)Lorg/apache/hadoop/hbase/protobuf/generated/AccessControlProtos$UserPermission;
      35: invokevirtual #144                // Method org/apache/hadoop/hbase/protobuf/generated/AccessControlProtos$GetUserPermissionsResponse$Builder.addUserPermission:(Lorg/apache/hadoop/hbase/protobuf/generated/AccessControlProtos$UserPermission;)Lorg/apache/hadoop/hbase/protobuf/generated/AccessControlProtos$GetUserPermissionsResponse$Builder;
      38: pop
      39: goto          11
      42: aload_1
      43: invokevirtual #145                // Method org/apache/hadoop/hbase/protobuf/generated/AccessControlProtos$GetUserPermissionsResponse$Builder.build:()Lorg/apache/hadoop/hbase/protobuf/generated/AccessControlProtos$GetUserPermissionsResponse;
      46: areturn

  public static org.apache.hadoop.hbase.security.access.UserPermission toUserPermission(org.apache.hadoop.hbase.protobuf.generated.AccessControlProtos$UserPermission);
    Code:
       0: new           #142                // class org/apache/hadoop/hbase/security/access/UserPermission
       3: dup
       4: aload_0
       5: invokevirtual #146                // Method org/apache/hadoop/hbase/protobuf/generated/AccessControlProtos$UserPermission.getUser:()Lcom/google/protobuf/ByteString;
       8: invokevirtual #61                 // Method com/google/protobuf/ByteString.toStringUtf8:()Ljava/lang/String;
      11: aload_0
      12: invokevirtual #147                // Method org/apache/hadoop/hbase/protobuf/generated/AccessControlProtos$UserPermission.getPermission:()Lorg/apache/hadoop/hbase/protobuf/generated/AccessControlProtos$Permission;
      15: invokestatic  #64                 // Method toPermission:(Lorg/apache/hadoop/hbase/protobuf/generated/AccessControlProtos$Permission;)Lorg/apache/hadoop/hbase/security/access/Permission;
      18: invokespecial #148                // Method org/apache/hadoop/hbase/security/access/UserPermission."<init>":(Ljava/lang/String;Lorg/apache/hadoop/hbase/security/access/Permission;)V
      21: areturn

  public static org.apache.hadoop.hbase.protobuf.generated.AccessControlProtos$UsersAndPermissions toUserTablePermissions(org.apache.hbase.thirdparty.com.google.common.collect.ListMultimap<java.lang.String, org.apache.hadoop.hbase.security.access.UserPermission>);
    Code:
       0: invokestatic  #36                 // Method org/apache/hadoop/hbase/protobuf/generated/AccessControlProtos$UsersAndPermissions.newBuilder:()Lorg/apache/hadoop/hbase/protobuf/generated/AccessControlProtos$UsersAndPermissions$Builder;
       3: astore_1
       4: aload_0
       5: invokeinterface #44,  1           // InterfaceMethod org/apache/hbase/thirdparty/com/google/common/collect/ListMultimap.asMap:()Ljava/util/Map;
      10: invokeinterface #45,  1           // InterfaceMethod java/util/Map.entrySet:()Ljava/util/Set;
      15: invokeinterface #46,  1           // InterfaceMethod java/util/Set.iterator:()Ljava/util/Iterator;
      20: astore_2
      21: aload_2
      22: invokeinterface #47,  1           // InterfaceMethod java/util/Iterator.hasNext:()Z
      27: ifeq          131
      30: aload_2
      31: invokeinterface #48,  1           // InterfaceMethod java/util/Iterator.next:()Ljava/lang/Object;
      36: checkcast     #49                 // class java/util/Map$Entry
      39: astore_3
      40: invokestatic  #37                 // Method org/apache/hadoop/hbase/protobuf/generated/AccessControlProtos$UsersAndPermissions$UserPermissions.newBuilder:()Lorg/apache/hadoop/hbase/protobuf/generated/AccessControlProtos$UsersAndPermissions$UserPermissions$Builder;
      43: astore        4
      45: aload         4
      47: aload_3
      48: invokeinterface #50,  1           // InterfaceMethod java/util/Map$Entry.getKey:()Ljava/lang/Object;
      53: checkcast     #51                 // class java/lang/String
      56: invokestatic  #18                 // Method com/google/protobuf/ByteString.copyFromUtf8:(Ljava/lang/String;)Lcom/google/protobuf/ByteString;
      59: invokevirtual #38                 // Method org/apache/hadoop/hbase/protobuf/generated/AccessControlProtos$UsersAndPermissions$UserPermissions$Builder.setUser:(Lcom/google/protobuf/ByteString;)Lorg/apache/hadoop/hbase/protobuf/generated/AccessControlProtos$UsersAndPermissions$UserPermissions$Builder;
      62: pop
      63: aload_3
      64: invokeinterface #52,  1           // InterfaceMethod java/util/Map$Entry.getValue:()Ljava/lang/Object;
      69: checkcast     #53                 // class java/util/Collection
      72: invokeinterface #54,  1           // InterfaceMethod java/util/Collection.iterator:()Ljava/util/Iterator;
      77: astore        5
      79: aload         5
      81: invokeinterface #47,  1           // InterfaceMethod java/util/Iterator.hasNext:()Z
      86: ifeq          118
      89: aload         5
      91: invokeinterface #48,  1           // InterfaceMethod java/util/Iterator.next:()Ljava/lang/Object;
      96: checkcast     #142                // class org/apache/hadoop/hbase/security/access/UserPermission
      99: astore        6
     101: aload         4
     103: aload         6
     105: invokevirtual #138                // Method org/apache/hadoop/hbase/security/access/UserPermission.getPermission:()Lorg/apache/hadoop/hbase/security/access/Permission;
     108: invokestatic  #39                 // Method toPermission:(Lorg/apache/hadoop/hbase/security/access/Permission;)Lorg/apache/hadoop/hbase/protobuf/generated/AccessControlProtos$Permission;
     111: invokevirtual #40                 // Method org/apache/hadoop/hbase/protobuf/generated/AccessControlProtos$UsersAndPermissions$UserPermissions$Builder.addPermissions:(Lorg/apache/hadoop/hbase/protobuf/generated/AccessControlProtos$Permission;)Lorg/apache/hadoop/hbase/protobuf/generated/AccessControlProtos$UsersAndPermissions$UserPermissions$Builder;
     114: pop
     115: goto          79
     118: aload_1
     119: aload         4
     121: invokevirtual #41                 // Method org/apache/hadoop/hbase/protobuf/generated/AccessControlProtos$UsersAndPermissions$UserPermissions$Builder.build:()Lorg/apache/hadoop/hbase/protobuf/generated/AccessControlProtos$UsersAndPermissions$UserPermissions;
     124: invokevirtual #42                 // Method org/apache/hadoop/hbase/protobuf/generated/AccessControlProtos$UsersAndPermissions$Builder.addUserPermissions:(Lorg/apache/hadoop/hbase/protobuf/generated/AccessControlProtos$UsersAndPermissions$UserPermissions;)Lorg/apache/hadoop/hbase/protobuf/generated/AccessControlProtos$UsersAndPermissions$Builder;
     127: pop
     128: goto          21
     131: aload_1
     132: invokevirtual #43                 // Method org/apache/hadoop/hbase/protobuf/generated/AccessControlProtos$UsersAndPermissions$Builder.build:()Lorg/apache/hadoop/hbase/protobuf/generated/AccessControlProtos$UsersAndPermissions;
     135: areturn

  public static void grant(com.google.protobuf.RpcController, org.apache.hadoop.hbase.protobuf.generated.AccessControlProtos$AccessControlService$BlockingInterface, java.lang.String, boolean, org.apache.hadoop.hbase.security.access.Permission$Action...) throws com.google.protobuf.ServiceException;
    Code:
       0: aload         4
       2: arraylength
       3: invokestatic  #149                // Method org/apache/hbase/thirdparty/com/google/common/collect/Lists.newArrayListWithCapacity:(I)Ljava/util/ArrayList;
       6: astore        5
       8: aload         4
      10: astore        6
      12: aload         6
      14: arraylength
      15: istore        7
      17: iconst_0
      18: istore        8
      20: iload         8
      22: iload         7
      24: if_icmpge     53
      27: aload         6
      29: iload         8
      31: aaload
      32: astore        9
      34: aload         5
      36: aload         9
      38: invokestatic  #106                // Method toPermissionAction:(Lorg/apache/hadoop/hbase/security/access/Permission$Action;)Lorg/apache/hadoop/hbase/protobuf/generated/AccessControlProtos$Permission$Action;
      41: invokeinterface #150,  2          // InterfaceMethod java/util/List.add:(Ljava/lang/Object;)Z
      46: pop
      47: iinc          8, 1
      50: goto          20
      53: aload_2
      54: iload_3
      55: aload         5
      57: aload         4
      59: arraylength
      60: anewarray     #116                // class org/apache/hadoop/hbase/protobuf/generated/AccessControlProtos$Permission$Action
      63: invokeinterface #151,  2          // InterfaceMethod java/util/List.toArray:([Ljava/lang/Object;)[Ljava/lang/Object;
      68: checkcast     #152                // class "[Lorg/apache/hadoop/hbase/protobuf/generated/AccessControlProtos$Permission$Action;"
      71: invokestatic  #153                // Method buildGrantRequest:(Ljava/lang/String;Z[Lorg/apache/hadoop/hbase/protobuf/generated/AccessControlProtos$Permission$Action;)Lorg/apache/hadoop/hbase/protobuf/generated/AccessControlProtos$GrantRequest;
      74: astore        6
      76: aload_1
      77: aload_0
      78: aload         6
      80: invokeinterface #154,  3          // InterfaceMethod org/apache/hadoop/hbase/protobuf/generated/AccessControlProtos$AccessControlService$BlockingInterface.grant:(Lcom/google/protobuf/RpcController;Lorg/apache/hadoop/hbase/protobuf/generated/AccessControlProtos$GrantRequest;)Lorg/apache/hadoop/hbase/protobuf/generated/AccessControlProtos$GrantResponse;
      85: pop
      86: return

  public static void grant(com.google.protobuf.RpcController, org.apache.hadoop.hbase.protobuf.generated.AccessControlProtos$AccessControlService$BlockingInterface, java.lang.String, org.apache.hadoop.hbase.TableName, byte[], byte[], boolean, org.apache.hadoop.hbase.security.access.Permission$Action...) throws com.google.protobuf.ServiceException;
    Code:
       0: aload         7
       2: arraylength
       3: invokestatic  #149                // Method org/apache/hbase/thirdparty/com/google/common/collect/Lists.newArrayListWithCapacity:(I)Ljava/util/ArrayList;
       6: astore        8
       8: aload         7
      10: astore        9
      12: aload         9
      14: arraylength
      15: istore        10
      17: iconst_0
      18: istore        11
      20: iload         11
      22: iload         10
      24: if_icmpge     53
      27: aload         9
      29: iload         11
      31: aaload
      32: astore        12
      34: aload         8
      36: aload         12
      38: invokestatic  #106                // Method toPermissionAction:(Lorg/apache/hadoop/hbase/security/access/Permission$Action;)Lorg/apache/hadoop/hbase/protobuf/generated/AccessControlProtos$Permission$Action;
      41: invokeinterface #150,  2          // InterfaceMethod java/util/List.add:(Ljava/lang/Object;)Z
      46: pop
      47: iinc          11, 1
      50: goto          20
      53: aload_2
      54: aload_3
      55: aload         4
      57: aload         5
      59: iload         6
      61: aload         8
      63: aload         7
      65: arraylength
      66: anewarray     #116                // class org/apache/hadoop/hbase/protobuf/generated/AccessControlProtos$Permission$Action
      69: invokeinterface #151,  2          // InterfaceMethod java/util/List.toArray:([Ljava/lang/Object;)[Ljava/lang/Object;
      74: checkcast     #152                // class "[Lorg/apache/hadoop/hbase/protobuf/generated/AccessControlProtos$Permission$Action;"
      77: invokestatic  #155                // Method buildGrantRequest:(Ljava/lang/String;Lorg/apache/hadoop/hbase/TableName;[B[BZ[Lorg/apache/hadoop/hbase/protobuf/generated/AccessControlProtos$Permission$Action;)Lorg/apache/hadoop/hbase/protobuf/generated/AccessControlProtos$GrantRequest;
      80: astore        9
      82: aload_1
      83: aload_0
      84: aload         9
      86: invokeinterface #154,  3          // InterfaceMethod org/apache/hadoop/hbase/protobuf/generated/AccessControlProtos$AccessControlService$BlockingInterface.grant:(Lcom/google/protobuf/RpcController;Lorg/apache/hadoop/hbase/protobuf/generated/AccessControlProtos$GrantRequest;)Lorg/apache/hadoop/hbase/protobuf/generated/AccessControlProtos$GrantResponse;
      91: pop
      92: return

  public static void grant(com.google.protobuf.RpcController, org.apache.hadoop.hbase.protobuf.generated.AccessControlProtos$AccessControlService$BlockingInterface, java.lang.String, java.lang.String, boolean, org.apache.hadoop.hbase.security.access.Permission$Action...) throws com.google.protobuf.ServiceException;
    Code:
       0: aload         5
       2: arraylength
       3: invokestatic  #149                // Method org/apache/hbase/thirdparty/com/google/common/collect/Lists.newArrayListWithCapacity:(I)Ljava/util/ArrayList;
       6: astore        6
       8: aload         5
      10: astore        7
      12: aload         7
      14: arraylength
      15: istore        8
      17: iconst_0
      18: istore        9
      20: iload         9
      22: iload         8
      24: if_icmpge     53
      27: aload         7
      29: iload         9
      31: aaload
      32: astore        10
      34: aload         6
      36: aload         10
      38: invokestatic  #106                // Method toPermissionAction:(Lorg/apache/hadoop/hbase/security/access/Permission$Action;)Lorg/apache/hadoop/hbase/protobuf/generated/AccessControlProtos$Permission$Action;
      41: invokeinterface #150,  2          // InterfaceMethod java/util/List.add:(Ljava/lang/Object;)Z
      46: pop
      47: iinc          9, 1
      50: goto          20
      53: aload_2
      54: aload_3
      55: iload         4
      57: aload         6
      59: aload         5
      61: arraylength
      62: anewarray     #116                // class org/apache/hadoop/hbase/protobuf/generated/AccessControlProtos$Permission$Action
      65: invokeinterface #151,  2          // InterfaceMethod java/util/List.toArray:([Ljava/lang/Object;)[Ljava/lang/Object;
      70: checkcast     #152                // class "[Lorg/apache/hadoop/hbase/protobuf/generated/AccessControlProtos$Permission$Action;"
      73: invokestatic  #156                // Method buildGrantRequest:(Ljava/lang/String;Ljava/lang/String;Z[Lorg/apache/hadoop/hbase/protobuf/generated/AccessControlProtos$Permission$Action;)Lorg/apache/hadoop/hbase/protobuf/generated/AccessControlProtos$GrantRequest;
      76: astore        7
      78: aload_1
      79: aload_0
      80: aload         7
      82: invokeinterface #154,  3          // InterfaceMethod org/apache/hadoop/hbase/protobuf/generated/AccessControlProtos$AccessControlService$BlockingInterface.grant:(Lcom/google/protobuf/RpcController;Lorg/apache/hadoop/hbase/protobuf/generated/AccessControlProtos$GrantRequest;)Lorg/apache/hadoop/hbase/protobuf/generated/AccessControlProtos$GrantResponse;
      87: pop
      88: return

  public static void revoke(com.google.protobuf.RpcController, org.apache.hadoop.hbase.protobuf.generated.AccessControlProtos$AccessControlService$BlockingInterface, java.lang.String, org.apache.hadoop.hbase.security.access.Permission$Action...) throws com.google.protobuf.ServiceException;
    Code:
       0: aload_3
       1: arraylength
       2: invokestatic  #149                // Method org/apache/hbase/thirdparty/com/google/common/collect/Lists.newArrayListWithCapacity:(I)Ljava/util/ArrayList;
       5: astore        4
       7: aload_3
       8: astore        5
      10: aload         5
      12: arraylength
      13: istore        6
      15: iconst_0
      16: istore        7
      18: iload         7
      20: iload         6
      22: if_icmpge     51
      25: aload         5
      27: iload         7
      29: aaload
      30: astore        8
      32: aload         4
      34: aload         8
      36: invokestatic  #106                // Method toPermissionAction:(Lorg/apache/hadoop/hbase/security/access/Permission$Action;)Lorg/apache/hadoop/hbase/protobuf/generated/AccessControlProtos$Permission$Action;
      39: invokeinterface #150,  2          // InterfaceMethod java/util/List.add:(Ljava/lang/Object;)Z
      44: pop
      45: iinc          7, 1
      48: goto          18
      51: aload_2
      52: aload         4
      54: aload_3
      55: arraylength
      56: anewarray     #116                // class org/apache/hadoop/hbase/protobuf/generated/AccessControlProtos$Permission$Action
      59: invokeinterface #151,  2          // InterfaceMethod java/util/List.toArray:([Ljava/lang/Object;)[Ljava/lang/Object;
      64: checkcast     #152                // class "[Lorg/apache/hadoop/hbase/protobuf/generated/AccessControlProtos$Permission$Action;"
      67: invokestatic  #157                // Method buildRevokeRequest:(Ljava/lang/String;[Lorg/apache/hadoop/hbase/protobuf/generated/AccessControlProtos$Permission$Action;)Lorg/apache/hadoop/hbase/protobuf/generated/AccessControlProtos$RevokeRequest;
      70: astore        5
      72: aload_1
      73: aload_0
      74: aload         5
      76: invokeinterface #158,  3          // InterfaceMethod org/apache/hadoop/hbase/protobuf/generated/AccessControlProtos$AccessControlService$BlockingInterface.revoke:(Lcom/google/protobuf/RpcController;Lorg/apache/hadoop/hbase/protobuf/generated/AccessControlProtos$RevokeRequest;)Lorg/apache/hadoop/hbase/protobuf/generated/AccessControlProtos$RevokeResponse;
      81: pop
      82: return

  public static void revoke(com.google.protobuf.RpcController, org.apache.hadoop.hbase.protobuf.generated.AccessControlProtos$AccessControlService$BlockingInterface, java.lang.String, org.apache.hadoop.hbase.TableName, byte[], byte[], org.apache.hadoop.hbase.security.access.Permission$Action...) throws com.google.protobuf.ServiceException;
    Code:
       0: aload         6
       2: arraylength
       3: invokestatic  #149                // Method org/apache/hbase/thirdparty/com/google/common/collect/Lists.newArrayListWithCapacity:(I)Ljava/util/ArrayList;
       6: astore        7
       8: aload         6
      10: astore        8
      12: aload         8
      14: arraylength
      15: istore        9
      17: iconst_0
      18: istore        10
      20: iload         10
      22: iload         9
      24: if_icmpge     53
      27: aload         8
      29: iload         10
      31: aaload
      32: astore        11
      34: aload         7
      36: aload         11
      38: invokestatic  #106                // Method toPermissionAction:(Lorg/apache/hadoop/hbase/security/access/Permission$Action;)Lorg/apache/hadoop/hbase/protobuf/generated/AccessControlProtos$Permission$Action;
      41: invokeinterface #150,  2          // InterfaceMethod java/util/List.add:(Ljava/lang/Object;)Z
      46: pop
      47: iinc          10, 1
      50: goto          20
      53: aload_2
      54: aload_3
      55: aload         4
      57: aload         5
      59: aload         7
      61: aload         6
      63: arraylength
      64: anewarray     #116                // class org/apache/hadoop/hbase/protobuf/generated/AccessControlProtos$Permission$Action
      67: invokeinterface #151,  2          // InterfaceMethod java/util/List.toArray:([Ljava/lang/Object;)[Ljava/lang/Object;
      72: checkcast     #152                // class "[Lorg/apache/hadoop/hbase/protobuf/generated/AccessControlProtos$Permission$Action;"
      75: invokestatic  #159                // Method buildRevokeRequest:(Ljava/lang/String;Lorg/apache/hadoop/hbase/TableName;[B[B[Lorg/apache/hadoop/hbase/protobuf/generated/AccessControlProtos$Permission$Action;)Lorg/apache/hadoop/hbase/protobuf/generated/AccessControlProtos$RevokeRequest;
      78: astore        8
      80: aload_1
      81: aload_0
      82: aload         8
      84: invokeinterface #158,  3          // InterfaceMethod org/apache/hadoop/hbase/protobuf/generated/AccessControlProtos$AccessControlService$BlockingInterface.revoke:(Lcom/google/protobuf/RpcController;Lorg/apache/hadoop/hbase/protobuf/generated/AccessControlProtos$RevokeRequest;)Lorg/apache/hadoop/hbase/protobuf/generated/AccessControlProtos$RevokeResponse;
      89: pop
      90: return

  public static void revoke(com.google.protobuf.RpcController, org.apache.hadoop.hbase.protobuf.generated.AccessControlProtos$AccessControlService$BlockingInterface, java.lang.String, java.lang.String, org.apache.hadoop.hbase.security.access.Permission$Action...) throws com.google.protobuf.ServiceException;
    Code:
       0: aload         4
       2: arraylength
       3: invokestatic  #149                // Method org/apache/hbase/thirdparty/com/google/common/collect/Lists.newArrayListWithCapacity:(I)Ljava/util/ArrayList;
       6: astore        5
       8: aload         4
      10: astore        6
      12: aload         6
      14: arraylength
      15: istore        7
      17: iconst_0
      18: istore        8
      20: iload         8
      22: iload         7
      24: if_icmpge     53
      27: aload         6
      29: iload         8
      31: aaload
      32: astore        9
      34: aload         5
      36: aload         9
      38: invokestatic  #106                // Method toPermissionAction:(Lorg/apache/hadoop/hbase/security/access/Permission$Action;)Lorg/apache/hadoop/hbase/protobuf/generated/AccessControlProtos$Permission$Action;
      41: invokeinterface #150,  2          // InterfaceMethod java/util/List.add:(Ljava/lang/Object;)Z
      46: pop
      47: iinc          8, 1
      50: goto          20
      53: aload_2
      54: aload_3
      55: aload         5
      57: aload         4
      59: arraylength
      60: anewarray     #116                // class org/apache/hadoop/hbase/protobuf/generated/AccessControlProtos$Permission$Action
      63: invokeinterface #151,  2          // InterfaceMethod java/util/List.toArray:([Ljava/lang/Object;)[Ljava/lang/Object;
      68: checkcast     #152                // class "[Lorg/apache/hadoop/hbase/protobuf/generated/AccessControlProtos$Permission$Action;"
      71: invokestatic  #160                // Method buildRevokeRequest:(Ljava/lang/String;Ljava/lang/String;[Lorg/apache/hadoop/hbase/protobuf/generated/AccessControlProtos$Permission$Action;)Lorg/apache/hadoop/hbase/protobuf/generated/AccessControlProtos$RevokeRequest;
      74: astore        6
      76: aload_1
      77: aload_0
      78: aload         6
      80: invokeinterface #158,  3          // InterfaceMethod org/apache/hadoop/hbase/protobuf/generated/AccessControlProtos$AccessControlService$BlockingInterface.revoke:(Lcom/google/protobuf/RpcController;Lorg/apache/hadoop/hbase/protobuf/generated/AccessControlProtos$RevokeRequest;)Lorg/apache/hadoop/hbase/protobuf/generated/AccessControlProtos$RevokeResponse;
      85: pop
      86: return

  public static java.util.List<org.apache.hadoop.hbase.security.access.UserPermission> getUserPermissions(com.google.protobuf.RpcController, org.apache.hadoop.hbase.protobuf.generated.AccessControlProtos$AccessControlService$BlockingInterface) throws com.google.protobuf.ServiceException;
    Code:
       0: aload_0
       1: aload_1
       2: ldc           #162                // String
       4: invokestatic  #163                // Method getUserPermissions:(Lcom/google/protobuf/RpcController;Lorg/apache/hadoop/hbase/protobuf/generated/AccessControlProtos$AccessControlService$BlockingInterface;Ljava/lang/String;)Ljava/util/List;
       7: areturn

  public static java.util.List<org.apache.hadoop.hbase.security.access.UserPermission> getUserPermissions(com.google.protobuf.RpcController, org.apache.hadoop.hbase.protobuf.generated.AccessControlProtos$AccessControlService$BlockingInterface, java.lang.String) throws com.google.protobuf.ServiceException;
    Code:
       0: invokestatic  #164                // Method org/apache/hadoop/hbase/protobuf/generated/AccessControlProtos$GetUserPermissionsRequest.newBuilder:()Lorg/apache/hadoop/hbase/protobuf/generated/AccessControlProtos$GetUserPermissionsRequest$Builder;
       3: astore_3
       4: aload_3
       5: getstatic     #31                 // Field org/apache/hadoop/hbase/protobuf/generated/AccessControlProtos$Permission$Type.Global:Lorg/apache/hadoop/hbase/protobuf/generated/AccessControlProtos$Permission$Type;
       8: invokevirtual #165                // Method org/apache/hadoop/hbase/protobuf/generated/AccessControlProtos$GetUserPermissionsRequest$Builder.setType:(Lorg/apache/hadoop/hbase/protobuf/generated/AccessControlProtos$Permission$Type;)Lorg/apache/hadoop/hbase/protobuf/generated/AccessControlProtos$GetUserPermissionsRequest$Builder;
      11: pop
      12: aload_2
      13: invokestatic  #166                // Method org/apache/commons/lang3/StringUtils.isEmpty:(Ljava/lang/CharSequence;)Z
      16: ifne          28
      19: aload_3
      20: aload_2
      21: invokestatic  #18                 // Method com/google/protobuf/ByteString.copyFromUtf8:(Ljava/lang/String;)Lcom/google/protobuf/ByteString;
      24: invokevirtual #167                // Method org/apache/hadoop/hbase/protobuf/generated/AccessControlProtos$GetUserPermissionsRequest$Builder.setUserName:(Lcom/google/protobuf/ByteString;)Lorg/apache/hadoop/hbase/protobuf/generated/AccessControlProtos$GetUserPermissionsRequest$Builder;
      27: pop
      28: aload_3
      29: invokevirtual #168                // Method org/apache/hadoop/hbase/protobuf/generated/AccessControlProtos$GetUserPermissionsRequest$Builder.build:()Lorg/apache/hadoop/hbase/protobuf/generated/AccessControlProtos$GetUserPermissionsRequest;
      32: astore        4
      34: aload_1
      35: aload_0
      36: aload         4
      38: invokeinterface #169,  3          // InterfaceMethod org/apache/hadoop/hbase/protobuf/generated/AccessControlProtos$AccessControlService$BlockingInterface.getUserPermissions:(Lcom/google/protobuf/RpcController;Lorg/apache/hadoop/hbase/protobuf/generated/AccessControlProtos$GetUserPermissionsRequest;)Lorg/apache/hadoop/hbase/protobuf/generated/AccessControlProtos$GetUserPermissionsResponse;
      43: astore        5
      45: new           #170                // class java/util/ArrayList
      48: dup
      49: aload         5
      51: invokevirtual #171                // Method org/apache/hadoop/hbase/protobuf/generated/AccessControlProtos$GetUserPermissionsResponse.getUserPermissionCount:()I
      54: invokespecial #172                // Method java/util/ArrayList."<init>":(I)V
      57: astore        6
      59: aload         5
      61: invokevirtual #173                // Method org/apache/hadoop/hbase/protobuf/generated/AccessControlProtos$GetUserPermissionsResponse.getUserPermissionList:()Ljava/util/List;
      64: invokeinterface #58,  1           // InterfaceMethod java/util/List.iterator:()Ljava/util/Iterator;
      69: astore        7
      71: aload         7
      73: invokeinterface #47,  1           // InterfaceMethod java/util/Iterator.hasNext:()Z
      78: ifeq          109
      81: aload         7
      83: invokeinterface #48,  1           // InterfaceMethod java/util/Iterator.next:()Ljava/lang/Object;
      88: checkcast     #174                // class org/apache/hadoop/hbase/protobuf/generated/AccessControlProtos$UserPermission
      91: astore        8
      93: aload         6
      95: aload         8
      97: invokestatic  #175                // Method toUserPermission:(Lorg/apache/hadoop/hbase/protobuf/generated/AccessControlProtos$UserPermission;)Lorg/apache/hadoop/hbase/security/access/UserPermission;
     100: invokeinterface #150,  2          // InterfaceMethod java/util/List.add:(Ljava/lang/Object;)Z
     105: pop
     106: goto          71
     109: aload         6
     111: areturn

  public static java.util.List<org.apache.hadoop.hbase.security.access.UserPermission> getUserPermissions(com.google.protobuf.RpcController, org.apache.hadoop.hbase.protobuf.generated.AccessControlProtos$AccessControlService$BlockingInterface, org.apache.hadoop.hbase.TableName) throws com.google.protobuf.ServiceException;
    Code:
       0: aload_0
       1: aload_1
       2: aload_2
       3: aconst_null
       4: aconst_null
       5: ldc           #162                // String
       7: invokestatic  #176                // Method getUserPermissions:(Lcom/google/protobuf/RpcController;Lorg/apache/hadoop/hbase/protobuf/generated/AccessControlProtos$AccessControlService$BlockingInterface;Lorg/apache/hadoop/hbase/TableName;[B[BLjava/lang/String;)Ljava/util/List;
      10: areturn

  public static java.util.List<org.apache.hadoop.hbase.security.access.UserPermission> getUserPermissions(com.google.protobuf.RpcController, org.apache.hadoop.hbase.protobuf.generated.AccessControlProtos$AccessControlService$BlockingInterface, org.apache.hadoop.hbase.TableName, byte[], byte[], java.lang.String) throws com.google.protobuf.ServiceException;
    Code:
       0: invokestatic  #164                // Method org/apache/hadoop/hbase/protobuf/generated/AccessControlProtos$GetUserPermissionsRequest.newBuilder:()Lorg/apache/hadoop/hbase/protobuf/generated/AccessControlProtos$GetUserPermissionsRequest$Builder;
       3: astore        6
       5: aload_2
       6: ifnull        19
       9: aload         6
      11: aload_2
      12: invokestatic  #8                  // Method org/apache/hadoop/hbase/protobuf/ProtobufUtil.toProtoTableName:(Lorg/apache/hadoop/hbase/TableName;)Lorg/apache/hadoop/hbase/protobuf/generated/HBaseProtos$TableName;
      15: invokevirtual #177                // Method org/apache/hadoop/hbase/protobuf/generated/AccessControlProtos$GetUserPermissionsRequest$Builder.setTableName:(Lorg/apache/hadoop/hbase/protobuf/generated/HBaseProtos$TableName;)Lorg/apache/hadoop/hbase/protobuf/generated/AccessControlProtos$GetUserPermissionsRequest$Builder;
      18: pop
      19: aload_3
      20: invokestatic  #178                // Method org/apache/hadoop/hbase/util/Bytes.len:([B)I
      23: ifle          36
      26: aload         6
      28: aload_3
      29: invokestatic  #179                // Method com/google/protobuf/ByteString.copyFrom:([B)Lcom/google/protobuf/ByteString;
      32: invokevirtual #180                // Method org/apache/hadoop/hbase/protobuf/generated/AccessControlProtos$GetUserPermissionsRequest$Builder.setColumnFamily:(Lcom/google/protobuf/ByteString;)Lorg/apache/hadoop/hbase/protobuf/generated/AccessControlProtos$GetUserPermissionsRequest$Builder;
      35: pop
      36: aload         4
      38: invokestatic  #178                // Method org/apache/hadoop/hbase/util/Bytes.len:([B)I
      41: ifle          55
      44: aload         6
      46: aload         4
      48: invokestatic  #179                // Method com/google/protobuf/ByteString.copyFrom:([B)Lcom/google/protobuf/ByteString;
      51: invokevirtual #181                // Method org/apache/hadoop/hbase/protobuf/generated/AccessControlProtos$GetUserPermissionsRequest$Builder.setColumnQualifier:(Lcom/google/protobuf/ByteString;)Lorg/apache/hadoop/hbase/protobuf/generated/AccessControlProtos$GetUserPermissionsRequest$Builder;
      54: pop
      55: aload         5
      57: invokestatic  #166                // Method org/apache/commons/lang3/StringUtils.isEmpty:(Ljava/lang/CharSequence;)Z
      60: ifne          74
      63: aload         6
      65: aload         5
      67: invokestatic  #18                 // Method com/google/protobuf/ByteString.copyFromUtf8:(Ljava/lang/String;)Lcom/google/protobuf/ByteString;
      70: invokevirtual #167                // Method org/apache/hadoop/hbase/protobuf/generated/AccessControlProtos$GetUserPermissionsRequest$Builder.setUserName:(Lcom/google/protobuf/ByteString;)Lorg/apache/hadoop/hbase/protobuf/generated/AccessControlProtos$GetUserPermissionsRequest$Builder;
      73: pop
      74: aload         6
      76: getstatic     #13                 // Field org/apache/hadoop/hbase/protobuf/generated/AccessControlProtos$Permission$Type.Table:Lorg/apache/hadoop/hbase/protobuf/generated/AccessControlProtos$Permission$Type;
      79: invokevirtual #165                // Method org/apache/hadoop/hbase/protobuf/generated/AccessControlProtos$GetUserPermissionsRequest$Builder.setType:(Lorg/apache/hadoop/hbase/protobuf/generated/AccessControlProtos$Permission$Type;)Lorg/apache/hadoop/hbase/protobuf/generated/AccessControlProtos$GetUserPermissionsRequest$Builder;
      82: pop
      83: aload         6
      85: invokevirtual #168                // Method org/apache/hadoop/hbase/protobuf/generated/AccessControlProtos$GetUserPermissionsRequest$Builder.build:()Lorg/apache/hadoop/hbase/protobuf/generated/AccessControlProtos$GetUserPermissionsRequest;
      88: astore        7
      90: aload_1
      91: aload_0
      92: aload         7
      94: invokeinterface #169,  3          // InterfaceMethod org/apache/hadoop/hbase/protobuf/generated/AccessControlProtos$AccessControlService$BlockingInterface.getUserPermissions:(Lcom/google/protobuf/RpcController;Lorg/apache/hadoop/hbase/protobuf/generated/AccessControlProtos$GetUserPermissionsRequest;)Lorg/apache/hadoop/hbase/protobuf/generated/AccessControlProtos$GetUserPermissionsResponse;
      99: astore        8
     101: new           #170                // class java/util/ArrayList
     104: dup
     105: aload         8
     107: invokevirtual #171                // Method org/apache/hadoop/hbase/protobuf/generated/AccessControlProtos$GetUserPermissionsResponse.getUserPermissionCount:()I
     110: invokespecial #172                // Method java/util/ArrayList."<init>":(I)V
     113: astore        9
     115: aload         8
     117: invokevirtual #173                // Method org/apache/hadoop/hbase/protobuf/generated/AccessControlProtos$GetUserPermissionsResponse.getUserPermissionList:()Ljava/util/List;
     120: invokeinterface #58,  1           // InterfaceMethod java/util/List.iterator:()Ljava/util/Iterator;
     125: astore        10
     127: aload         10
     129: invokeinterface #47,  1           // InterfaceMethod java/util/Iterator.hasNext:()Z
     134: ifeq          165
     137: aload         10
     139: invokeinterface #48,  1           // InterfaceMethod java/util/Iterator.next:()Ljava/lang/Object;
     144: checkcast     #174                // class org/apache/hadoop/hbase/protobuf/generated/AccessControlProtos$UserPermission
     147: astore        11
     149: aload         9
     151: aload         11
     153: invokestatic  #175                // Method toUserPermission:(Lorg/apache/hadoop/hbase/protobuf/generated/AccessControlProtos$UserPermission;)Lorg/apache/hadoop/hbase/security/access/UserPermission;
     156: invokeinterface #150,  2          // InterfaceMethod java/util/List.add:(Ljava/lang/Object;)Z
     161: pop
     162: goto          127
     165: aload         9
     167: areturn

  public static java.util.List<org.apache.hadoop.hbase.security.access.UserPermission> getUserPermissions(com.google.protobuf.RpcController, org.apache.hadoop.hbase.protobuf.generated.AccessControlProtos$AccessControlService$BlockingInterface, byte[]) throws com.google.protobuf.ServiceException;
    Code:
       0: aload_0
       1: aload_1
       2: aload_2
       3: ldc           #162                // String
       5: invokestatic  #182                // Method getUserPermissions:(Lcom/google/protobuf/RpcController;Lorg/apache/hadoop/hbase/protobuf/generated/AccessControlProtos$AccessControlService$BlockingInterface;[BLjava/lang/String;)Ljava/util/List;
       8: areturn

  public static java.util.List<org.apache.hadoop.hbase.security.access.UserPermission> getUserPermissions(com.google.protobuf.RpcController, org.apache.hadoop.hbase.protobuf.generated.AccessControlProtos$AccessControlService$BlockingInterface, byte[], java.lang.String) throws com.google.protobuf.ServiceException;
    Code:
       0: invokestatic  #164                // Method org/apache/hadoop/hbase/protobuf/generated/AccessControlProtos$GetUserPermissionsRequest.newBuilder:()Lorg/apache/hadoop/hbase/protobuf/generated/AccessControlProtos$GetUserPermissionsRequest$Builder;
       3: astore        4
       5: aload_2
       6: ifnull        19
       9: aload         4
      11: aload_2
      12: invokestatic  #10                 // Method org/apache/hadoop/hbase/util/ByteStringer.wrap:([B)Lcom/google/protobuf/ByteString;
      15: invokevirtual #183                // Method org/apache/hadoop/hbase/protobuf/generated/AccessControlProtos$GetUserPermissionsRequest$Builder.setNamespaceName:(Lcom/google/protobuf/ByteString;)Lorg/apache/hadoop/hbase/protobuf/generated/AccessControlProtos$GetUserPermissionsRequest$Builder;
      18: pop
      19: aload_3
      20: invokestatic  #166                // Method org/apache/commons/lang3/StringUtils.isEmpty:(Ljava/lang/CharSequence;)Z
      23: ifne          36
      26: aload         4
      28: aload_3
      29: invokestatic  #18                 // Method com/google/protobuf/ByteString.copyFromUtf8:(Ljava/lang/String;)Lcom/google/protobuf/ByteString;
      32: invokevirtual #167                // Method org/apache/hadoop/hbase/protobuf/generated/AccessControlProtos$GetUserPermissionsRequest$Builder.setUserName:(Lcom/google/protobuf/ByteString;)Lorg/apache/hadoop/hbase/protobuf/generated/AccessControlProtos$GetUserPermissionsRequest$Builder;
      35: pop
      36: aload         4
      38: getstatic     #27                 // Field org/apache/hadoop/hbase/protobuf/generated/AccessControlProtos$Permission$Type.Namespace:Lorg/apache/hadoop/hbase/protobuf/generated/AccessControlProtos$Permission$Type;
      41: invokevirtual #165                // Method org/apache/hadoop/hbase/protobuf/generated/AccessControlProtos$GetUserPermissionsRequest$Builder.setType:(Lorg/apache/hadoop/hbase/protobuf/generated/AccessControlProtos$Permission$Type;)Lorg/apache/hadoop/hbase/protobuf/generated/AccessControlProtos$GetUserPermissionsRequest$Builder;
      44: pop
      45: aload         4
      47: invokevirtual #168                // Method org/apache/hadoop/hbase/protobuf/generated/AccessControlProtos$GetUserPermissionsRequest$Builder.build:()Lorg/apache/hadoop/hbase/protobuf/generated/AccessControlProtos$GetUserPermissionsRequest;
      50: astore        5
      52: aload_1
      53: aload_0
      54: aload         5
      56: invokeinterface #169,  3          // InterfaceMethod org/apache/hadoop/hbase/protobuf/generated/AccessControlProtos$AccessControlService$BlockingInterface.getUserPermissions:(Lcom/google/protobuf/RpcController;Lorg/apache/hadoop/hbase/protobuf/generated/AccessControlProtos$GetUserPermissionsRequest;)Lorg/apache/hadoop/hbase/protobuf/generated/AccessControlProtos$GetUserPermissionsResponse;
      61: astore        6
      63: new           #170                // class java/util/ArrayList
      66: dup
      67: aload         6
      69: invokevirtual #171                // Method org/apache/hadoop/hbase/protobuf/generated/AccessControlProtos$GetUserPermissionsResponse.getUserPermissionCount:()I
      72: invokespecial #172                // Method java/util/ArrayList."<init>":(I)V
      75: astore        7
      77: aload         6
      79: invokevirtual #173                // Method org/apache/hadoop/hbase/protobuf/generated/AccessControlProtos$GetUserPermissionsResponse.getUserPermissionList:()Ljava/util/List;
      82: invokeinterface #58,  1           // InterfaceMethod java/util/List.iterator:()Ljava/util/Iterator;
      87: astore        8
      89: aload         8
      91: invokeinterface #47,  1           // InterfaceMethod java/util/Iterator.hasNext:()Z
      96: ifeq          127
      99: aload         8
     101: invokeinterface #48,  1           // InterfaceMethod java/util/Iterator.next:()Ljava/lang/Object;
     106: checkcast     #174                // class org/apache/hadoop/hbase/protobuf/generated/AccessControlProtos$UserPermission
     109: astore        9
     111: aload         7
     113: aload         9
     115: invokestatic  #175                // Method toUserPermission:(Lorg/apache/hadoop/hbase/protobuf/generated/AccessControlProtos$UserPermission;)Lorg/apache/hadoop/hbase/security/access/UserPermission;
     118: invokeinterface #150,  2          // InterfaceMethod java/util/List.add:(Ljava/lang/Object;)Z
     123: pop
     124: goto          89
     127: aload         7
     129: areturn

  public static boolean hasPermission(com.google.protobuf.RpcController, org.apache.hadoop.hbase.protobuf.generated.AccessControlProtos$AccessControlService$BlockingInterface, org.apache.hadoop.hbase.TableName, byte[], byte[], java.lang.String, org.apache.hadoop.hbase.security.access.Permission$Action[]) throws com.google.protobuf.ServiceException;
    Code:
       0: invokestatic  #3                  // Method org/apache/hadoop/hbase/protobuf/generated/AccessControlProtos$TablePermission.newBuilder:()Lorg/apache/hadoop/hbase/protobuf/generated/AccessControlProtos$TablePermission$Builder;
       3: astore        7
       5: aload         7
       7: aload_2
       8: invokestatic  #8                  // Method org/apache/hadoop/hbase/protobuf/ProtobufUtil.toProtoTableName:(Lorg/apache/hadoop/hbase/TableName;)Lorg/apache/hadoop/hbase/protobuf/generated/HBaseProtos$TableName;
      11: invokevirtual #9                  // Method org/apache/hadoop/hbase/protobuf/generated/AccessControlProtos$TablePermission$Builder.setTableName:(Lorg/apache/hadoop/hbase/protobuf/generated/HBaseProtos$TableName;)Lorg/apache/hadoop/hbase/protobuf/generated/AccessControlProtos$TablePermission$Builder;
      14: pop
      15: aload_3
      16: invokestatic  #178                // Method org/apache/hadoop/hbase/util/Bytes.len:([B)I
      19: ifle          32
      22: aload         7
      24: aload_3
      25: invokestatic  #10                 // Method org/apache/hadoop/hbase/util/ByteStringer.wrap:([B)Lcom/google/protobuf/ByteString;
      28: invokevirtual #11                 // Method org/apache/hadoop/hbase/protobuf/generated/AccessControlProtos$TablePermission$Builder.setFamily:(Lcom/google/protobuf/ByteString;)Lorg/apache/hadoop/hbase/protobuf/generated/AccessControlProtos$TablePermission$Builder;
      31: pop
      32: aload         4
      34: invokestatic  #178                // Method org/apache/hadoop/hbase/util/Bytes.len:([B)I
      37: ifle          51
      40: aload         7
      42: aload         4
      44: invokestatic  #179                // Method com/google/protobuf/ByteString.copyFrom:([B)Lcom/google/protobuf/ByteString;
      47: invokevirtual #12                 // Method org/apache/hadoop/hbase/protobuf/generated/AccessControlProtos$TablePermission$Builder.setQualifier:(Lcom/google/protobuf/ByteString;)Lorg/apache/hadoop/hbase/protobuf/generated/AccessControlProtos$TablePermission$Builder;
      50: pop
      51: aload         6
      53: astore        8
      55: aload         8
      57: arraylength
      58: istore        9
      60: iconst_0
      61: istore        10
      63: iload         10
      65: iload         9
      67: if_icmpge     94
      70: aload         8
      72: iload         10
      74: aaload
      75: astore        11
      77: aload         7
      79: aload         11
      81: invokestatic  #106                // Method toPermissionAction:(Lorg/apache/hadoop/hbase/security/access/Permission$Action;)Lorg/apache/hadoop/hbase/protobuf/generated/AccessControlProtos$Permission$Action;
      84: invokevirtual #4                  // Method org/apache/hadoop/hbase/protobuf/generated/AccessControlProtos$TablePermission$Builder.addAction:(Lorg/apache/hadoop/hbase/protobuf/generated/AccessControlProtos$Permission$Action;)Lorg/apache/hadoop/hbase/protobuf/generated/AccessControlProtos$TablePermission$Builder;
      87: pop
      88: iinc          10, 1
      91: goto          63
      94: invokestatic  #184                // Method org/apache/hadoop/hbase/protobuf/generated/AccessControlProtos$HasPermissionRequest.newBuilder:()Lorg/apache/hadoop/hbase/protobuf/generated/AccessControlProtos$HasPermissionRequest$Builder;
      97: aload         7
      99: invokevirtual #185                // Method org/apache/hadoop/hbase/protobuf/generated/AccessControlProtos$HasPermissionRequest$Builder.setTablePermission:(Lorg/apache/hadoop/hbase/protobuf/generated/AccessControlProtos$TablePermission$Builder;)Lorg/apache/hadoop/hbase/protobuf/generated/AccessControlProtos$HasPermissionRequest$Builder;
     102: aload         5
     104: invokestatic  #18                 // Method com/google/protobuf/ByteString.copyFromUtf8:(Ljava/lang/String;)Lcom/google/protobuf/ByteString;
     107: invokevirtual #186                // Method org/apache/hadoop/hbase/protobuf/generated/AccessControlProtos$HasPermissionRequest$Builder.setUserName:(Lcom/google/protobuf/ByteString;)Lorg/apache/hadoop/hbase/protobuf/generated/AccessControlProtos$HasPermissionRequest$Builder;
     110: invokevirtual #187                // Method org/apache/hadoop/hbase/protobuf/generated/AccessControlProtos$HasPermissionRequest$Builder.build:()Lorg/apache/hadoop/hbase/protobuf/generated/AccessControlProtos$HasPermissionRequest;
     113: astore        8
     115: aload_1
     116: aload_0
     117: aload         8
     119: invokeinterface #188,  3          // InterfaceMethod org/apache/hadoop/hbase/protobuf/generated/AccessControlProtos$AccessControlService$BlockingInterface.hasPermission:(Lcom/google/protobuf/RpcController;Lorg/apache/hadoop/hbase/protobuf/generated/AccessControlProtos$HasPermissionRequest;)Lorg/apache/hadoop/hbase/protobuf/generated/AccessControlProtos$HasPermissionResponse;
     124: astore        9
     126: aload         9
     128: invokevirtual #189                // Method org/apache/hadoop/hbase/protobuf/generated/AccessControlProtos$HasPermissionResponse.getHasPermission:()Z
     131: ireturn

  public static org.apache.hbase.thirdparty.com.google.common.collect.ListMultimap<java.lang.String, org.apache.hadoop.hbase.security.access.UserPermission> toUserPermission(org.apache.hadoop.hbase.protobuf.generated.AccessControlProtos$UsersAndPermissions);
    Code:
       0: invokestatic  #56                 // Method org/apache/hbase/thirdparty/com/google/common/collect/ArrayListMultimap.create:()Lorg/apache/hbase/thirdparty/com/google/common/collect/ArrayListMultimap;
       3: astore_1
       4: iconst_0
       5: istore_3
       6: iload_3
       7: aload_0
       8: invokevirtual #190                // Method org/apache/hadoop/hbase/protobuf/generated/AccessControlProtos$UsersAndPermissions.getUserPermissionsCount:()I
      11: if_icmpge     80
      14: aload_0
      15: iload_3
      16: invokevirtual #191                // Method org/apache/hadoop/hbase/protobuf/generated/AccessControlProtos$UsersAndPermissions.getUserPermissions:(I)Lorg/apache/hadoop/hbase/protobuf/generated/AccessControlProtos$UsersAndPermissions$UserPermissions;
      19: astore_2
      20: aload_2
      21: invokevirtual #60                 // Method org/apache/hadoop/hbase/protobuf/generated/AccessControlProtos$UsersAndPermissions$UserPermissions.getUser:()Lcom/google/protobuf/ByteString;
      24: invokevirtual #61                 // Method com/google/protobuf/ByteString.toStringUtf8:()Ljava/lang/String;
      27: astore        4
      29: iconst_0
      30: istore        5
      32: iload         5
      34: aload_2
      35: invokevirtual #192                // Method org/apache/hadoop/hbase/protobuf/generated/AccessControlProtos$UsersAndPermissions$UserPermissions.getPermissionsCount:()I
      38: if_icmpge     74
      41: aload_1
      42: aload         4
      44: new           #142                // class org/apache/hadoop/hbase/security/access/UserPermission
      47: dup
      48: aload         4
      50: aload_2
      51: iload         5
      53: invokevirtual #193                // Method org/apache/hadoop/hbase/protobuf/generated/AccessControlProtos$UsersAndPermissions$UserPermissions.getPermissions:(I)Lorg/apache/hadoop/hbase/protobuf/generated/AccessControlProtos$Permission;
      56: invokestatic  #64                 // Method toPermission:(Lorg/apache/hadoop/hbase/protobuf/generated/AccessControlProtos$Permission;)Lorg/apache/hadoop/hbase/security/access/Permission;
      59: invokespecial #148                // Method org/apache/hadoop/hbase/security/access/UserPermission."<init>":(Ljava/lang/String;Lorg/apache/hadoop/hbase/security/access/Permission;)V
      62: invokeinterface #65,  3           // InterfaceMethod org/apache/hbase/thirdparty/com/google/common/collect/ListMultimap.put:(Ljava/lang/Object;Ljava/lang/Object;)Z
      67: pop
      68: iinc          5, 1
      71: goto          32
      74: iinc          3, 1
      77: goto          6
      80: aload_1
      81: areturn

  public static org.apache.hbase.thirdparty.com.google.common.collect.ListMultimap<java.lang.String, org.apache.hadoop.hbase.security.access.Permission> toPermission(org.apache.hadoop.hbase.protobuf.generated.AccessControlProtos$UsersAndPermissions);
    Code:
       0: invokestatic  #56                 // Method org/apache/hbase/thirdparty/com/google/common/collect/ArrayListMultimap.create:()Lorg/apache/hbase/thirdparty/com/google/common/collect/ArrayListMultimap;
       3: astore_1
       4: iconst_0
       5: istore_3
       6: iload_3
       7: aload_0
       8: invokevirtual #190                // Method org/apache/hadoop/hbase/protobuf/generated/AccessControlProtos$UsersAndPermissions.getUserPermissionsCount:()I
      11: if_icmpge     71
      14: aload_0
      15: iload_3
      16: invokevirtual #191                // Method org/apache/hadoop/hbase/protobuf/generated/AccessControlProtos$UsersAndPermissions.getUserPermissions:(I)Lorg/apache/hadoop/hbase/protobuf/generated/AccessControlProtos$UsersAndPermissions$UserPermissions;
      19: astore_2
      20: aload_2
      21: invokevirtual #60                 // Method org/apache/hadoop/hbase/protobuf/generated/AccessControlProtos$UsersAndPermissions$UserPermissions.getUser:()Lcom/google/protobuf/ByteString;
      24: invokevirtual #61                 // Method com/google/protobuf/ByteString.toStringUtf8:()Ljava/lang/String;
      27: astore        4
      29: iconst_0
      30: istore        5
      32: iload         5
      34: aload_2
      35: invokevirtual #192                // Method org/apache/hadoop/hbase/protobuf/generated/AccessControlProtos$UsersAndPermissions$UserPermissions.getPermissionsCount:()I
      38: if_icmpge     65
      41: aload_1
      42: aload         4
      44: aload_2
      45: iload         5
      47: invokevirtual #193                // Method org/apache/hadoop/hbase/protobuf/generated/AccessControlProtos$UsersAndPermissions$UserPermissions.getPermissions:(I)Lorg/apache/hadoop/hbase/protobuf/generated/AccessControlProtos$Permission;
      50: invokestatic  #64                 // Method toPermission:(Lorg/apache/hadoop/hbase/protobuf/generated/AccessControlProtos$Permission;)Lorg/apache/hadoop/hbase/security/access/Permission;
      53: invokeinterface #65,  3           // InterfaceMethod org/apache/hbase/thirdparty/com/google/common/collect/ListMultimap.put:(Ljava/lang/Object;Ljava/lang/Object;)Z
      58: pop
      59: iinc          5, 1
      62: goto          32
      65: iinc          3, 1
      68: goto          6
      71: aload_1
      72: areturn

  public static org.apache.hadoop.hbase.protobuf.generated.AccessControlProtos$RevokeRequest buildRevokeRequest(java.lang.String, org.apache.hadoop.hbase.TableName, byte[], byte[], org.apache.hadoop.hbase.protobuf.generated.AccessControlProtos$Permission$Action...);
    Code:
       0: invokestatic  #2                  // Method org/apache/hadoop/hbase/protobuf/generated/AccessControlProtos$Permission.newBuilder:()Lorg/apache/hadoop/hbase/protobuf/generated/AccessControlProtos$Permission$Builder;
       3: astore        5
       5: invokestatic  #3                  // Method org/apache/hadoop/hbase/protobuf/generated/AccessControlProtos$TablePermission.newBuilder:()Lorg/apache/hadoop/hbase/protobuf/generated/AccessControlProtos$TablePermission$Builder;
       8: astore        6
      10: aload         4
      12: astore        7
      14: aload         7
      16: arraylength
      17: istore        8
      19: iconst_0
      20: istore        9
      22: iload         9
      24: iload         8
      26: if_icmpge     50
      29: aload         7
      31: iload         9
      33: aaload
      34: astore        10
      36: aload         6
      38: aload         10
      40: invokevirtual #4                  // Method org/apache/hadoop/hbase/protobuf/generated/AccessControlProtos$TablePermission$Builder.addAction:(Lorg/apache/hadoop/hbase/protobuf/generated/AccessControlProtos$Permission$Action;)Lorg/apache/hadoop/hbase/protobuf/generated/AccessControlProtos$TablePermission$Builder;
      43: pop
      44: iinc          9, 1
      47: goto          22
      50: aload_1
      51: ifnull        64
      54: aload         6
      56: aload_1
      57: invokestatic  #8                  // Method org/apache/hadoop/hbase/protobuf/ProtobufUtil.toProtoTableName:(Lorg/apache/hadoop/hbase/TableName;)Lorg/apache/hadoop/hbase/protobuf/generated/HBaseProtos$TableName;
      60: invokevirtual #9                  // Method org/apache/hadoop/hbase/protobuf/generated/AccessControlProtos$TablePermission$Builder.setTableName:(Lorg/apache/hadoop/hbase/protobuf/generated/HBaseProtos$TableName;)Lorg/apache/hadoop/hbase/protobuf/generated/AccessControlProtos$TablePermission$Builder;
      63: pop
      64: aload_2
      65: ifnull        78
      68: aload         6
      70: aload_2
      71: invokestatic  #10                 // Method org/apache/hadoop/hbase/util/ByteStringer.wrap:([B)Lcom/google/protobuf/ByteString;
      74: invokevirtual #11                 // Method org/apache/hadoop/hbase/protobuf/generated/AccessControlProtos$TablePermission$Builder.setFamily:(Lcom/google/protobuf/ByteString;)Lorg/apache/hadoop/hbase/protobuf/generated/AccessControlProtos$TablePermission$Builder;
      77: pop
      78: aload_3
      79: ifnull        92
      82: aload         6
      84: aload_3
      85: invokestatic  #10                 // Method org/apache/hadoop/hbase/util/ByteStringer.wrap:([B)Lcom/google/protobuf/ByteString;
      88: invokevirtual #12                 // Method org/apache/hadoop/hbase/protobuf/generated/AccessControlProtos$TablePermission$Builder.setQualifier:(Lcom/google/protobuf/ByteString;)Lorg/apache/hadoop/hbase/protobuf/generated/AccessControlProtos$TablePermission$Builder;
      91: pop
      92: aload         5
      94: getstatic     #13                 // Field org/apache/hadoop/hbase/protobuf/generated/AccessControlProtos$Permission$Type.Table:Lorg/apache/hadoop/hbase/protobuf/generated/AccessControlProtos$Permission$Type;
      97: invokevirtual #14                 // Method org/apache/hadoop/hbase/protobuf/generated/AccessControlProtos$Permission$Builder.setType:(Lorg/apache/hadoop/hbase/protobuf/generated/AccessControlProtos$Permission$Type;)Lorg/apache/hadoop/hbase/protobuf/generated/AccessControlProtos$Permission$Builder;
     100: aload         6
     102: invokevirtual #15                 // Method org/apache/hadoop/hbase/protobuf/generated/AccessControlProtos$Permission$Builder.setTablePermission:(Lorg/apache/hadoop/hbase/protobuf/generated/AccessControlProtos$TablePermission$Builder;)Lorg/apache/hadoop/hbase/protobuf/generated/AccessControlProtos$Permission$Builder;
     105: pop
     106: invokestatic  #33                 // Method org/apache/hadoop/hbase/protobuf/generated/AccessControlProtos$RevokeRequest.newBuilder:()Lorg/apache/hadoop/hbase/protobuf/generated/AccessControlProtos$RevokeRequest$Builder;
     109: invokestatic  #17                 // Method org/apache/hadoop/hbase/protobuf/generated/AccessControlProtos$UserPermission.newBuilder:()Lorg/apache/hadoop/hbase/protobuf/generated/AccessControlProtos$UserPermission$Builder;
     112: aload_0
     113: invokestatic  #18                 // Method com/google/protobuf/ByteString.copyFromUtf8:(Ljava/lang/String;)Lcom/google/protobuf/ByteString;
     116: invokevirtual #19                 // Method org/apache/hadoop/hbase/protobuf/generated/AccessControlProtos$UserPermission$Builder.setUser:(Lcom/google/protobuf/ByteString;)Lorg/apache/hadoop/hbase/protobuf/generated/AccessControlProtos$UserPermission$Builder;
     119: aload         5
     121: invokevirtual #20                 // Method org/apache/hadoop/hbase/protobuf/generated/AccessControlProtos$UserPermission$Builder.setPermission:(Lorg/apache/hadoop/hbase/protobuf/generated/AccessControlProtos$Permission$Builder;)Lorg/apache/hadoop/hbase/protobuf/generated/AccessControlProtos$UserPermission$Builder;
     124: invokevirtual #34                 // Method org/apache/hadoop/hbase/protobuf/generated/AccessControlProtos$RevokeRequest$Builder.setUserPermission:(Lorg/apache/hadoop/hbase/protobuf/generated/AccessControlProtos$UserPermission$Builder;)Lorg/apache/hadoop/hbase/protobuf/generated/AccessControlProtos$RevokeRequest$Builder;
     127: invokevirtual #35                 // Method org/apache/hadoop/hbase/protobuf/generated/AccessControlProtos$RevokeRequest$Builder.build:()Lorg/apache/hadoop/hbase/protobuf/generated/AccessControlProtos$RevokeRequest;
     130: areturn
}
