Compiled from "AccessController.java"
class org.apache.hadoop.hbase.security.access.AccessController$5 implements java.security.PrivilegedExceptionAction<java.lang.Void> {
  final java.lang.String val$owner;

  final org.apache.hadoop.hbase.client.TableDescriptor val$currentDesc;

  final org.apache.hadoop.hbase.coprocessor.ObserverContext val$c;

  final org.apache.hadoop.conf.Configuration val$conf;

  final org.apache.hadoop.hbase.security.access.AccessController this$0;

  org.apache.hadoop.hbase.security.access.AccessController$5(org.apache.hadoop.hbase.security.access.AccessController, java.lang.String, org.apache.hadoop.hbase.client.TableDescriptor, org.apache.hadoop.hbase.coprocessor.ObserverContext, org.apache.hadoop.conf.Configuration);
    Code:
       0: aload_0
       1: aload_1
       2: putfield      #1                  // Field this$0:Lorg/apache/hadoop/hbase/security/access/AccessController;
       5: aload_0
       6: aload_2
       7: putfield      #2                  // Field val$owner:Ljava/lang/String;
      10: aload_0
      11: aload_3
      12: putfield      #3                  // Field val$currentDesc:Lorg/apache/hadoop/hbase/client/TableDescriptor;
      15: aload_0
      16: aload         4
      18: putfield      #4                  // Field val$c:Lorg/apache/hadoop/hbase/coprocessor/ObserverContext;
      21: aload_0
      22: aload         5
      24: putfield      #5                  // Field val$conf:Lorg/apache/hadoop/conf/Configuration;
      27: aload_0
      28: invokespecial #6                  // Method java/lang/Object."<init>":()V
      31: return

  public java.lang.Void run() throws java.lang.Exception;
    Code:
       0: new           #7                  // class org/apache/hadoop/hbase/security/access/UserPermission
       3: dup
       4: aload_0
       5: getfield      #2                  // Field val$owner:Ljava/lang/String;
       8: aload_0
       9: getfield      #3                  // Field val$currentDesc:Lorg/apache/hadoop/hbase/client/TableDescriptor;
      12: invokeinterface #8,  1            // InterfaceMethod org/apache/hadoop/hbase/client/TableDescriptor.getTableName:()Lorg/apache/hadoop/hbase/TableName;
      17: invokestatic  #9                  // Method org/apache/hadoop/hbase/security/access/Permission.newBuilder:(Lorg/apache/hadoop/hbase/TableName;)Lorg/apache/hadoop/hbase/security/access/Permission$Builder;
      20: invokestatic  #10                 // Method org/apache/hadoop/hbase/security/access/Permission$Action.values:()[Lorg/apache/hadoop/hbase/security/access/Permission$Action;
      23: invokevirtual #11                 // Method org/apache/hadoop/hbase/security/access/Permission$Builder.withActions:([Lorg/apache/hadoop/hbase/security/access/Permission$Action;)Lorg/apache/hadoop/hbase/security/access/Permission$Builder;
      26: invokevirtual #12                 // Method org/apache/hadoop/hbase/security/access/Permission$Builder.build:()Lorg/apache/hadoop/hbase/security/access/Permission;
      29: invokespecial #13                 // Method org/apache/hadoop/hbase/security/access/UserPermission."<init>":(Ljava/lang/String;Lorg/apache/hadoop/hbase/security/access/Permission;)V
      32: astore_1
      33: aload_0
      34: getfield      #4                  // Field val$c:Lorg/apache/hadoop/hbase/coprocessor/ObserverContext;
      37: invokeinterface #14,  1           // InterfaceMethod org/apache/hadoop/hbase/coprocessor/ObserverContext.getEnvironment:()Lorg/apache/hadoop/hbase/CoprocessorEnvironment;
      42: checkcast     #15                 // class org/apache/hadoop/hbase/coprocessor/MasterCoprocessorEnvironment
      45: invokeinterface #16,  1           // InterfaceMethod org/apache/hadoop/hbase/coprocessor/MasterCoprocessorEnvironment.getConnection:()Lorg/apache/hadoop/hbase/client/Connection;
      50: getstatic     #17                 // Field org/apache/hadoop/hbase/security/access/PermissionStorage.ACL_TABLE_NAME:Lorg/apache/hadoop/hbase/TableName;
      53: invokeinterface #18,  2           // InterfaceMethod org/apache/hadoop/hbase/client/Connection.getTable:(Lorg/apache/hadoop/hbase/TableName;)Lorg/apache/hadoop/hbase/client/Table;
      58: astore_2
      59: aconst_null
      60: astore_3
      61: aload_0
      62: getfield      #5                  // Field val$conf:Lorg/apache/hadoop/conf/Configuration;
      65: aload_1
      66: aload_2
      67: invokestatic  #19                 // Method org/apache/hadoop/hbase/security/access/PermissionStorage.addUserPermission:(Lorg/apache/hadoop/conf/Configuration;Lorg/apache/hadoop/hbase/security/access/UserPermission;Lorg/apache/hadoop/hbase/client/Table;)V
      70: aload_2
      71: ifnull        154
      74: aload_3
      75: ifnull        98
      78: aload_2
      79: invokeinterface #20,  1           // InterfaceMethod org/apache/hadoop/hbase/client/Table.close:()V
      84: goto          154
      87: astore        4
      89: aload_3
      90: aload         4
      92: invokevirtual #22                 // Method java/lang/Throwable.addSuppressed:(Ljava/lang/Throwable;)V
      95: goto          154
      98: aload_2
      99: invokeinterface #20,  1           // InterfaceMethod org/apache/hadoop/hbase/client/Table.close:()V
     104: goto          154
     107: astore        4
     109: aload         4
     111: astore_3
     112: aload         4
     114: athrow
     115: astore        5
     117: aload_2
     118: ifnull        151
     121: aload_3
     122: ifnull        145
     125: aload_2
     126: invokeinterface #20,  1           // InterfaceMethod org/apache/hadoop/hbase/client/Table.close:()V
     131: goto          151
     134: astore        6
     136: aload_3
     137: aload         6
     139: invokevirtual #22                 // Method java/lang/Throwable.addSuppressed:(Ljava/lang/Throwable;)V
     142: goto          151
     145: aload_2
     146: invokeinterface #20,  1           // InterfaceMethod org/apache/hadoop/hbase/client/Table.close:()V
     151: aload         5
     153: athrow
     154: aconst_null
     155: areturn
    Exception table:
       from    to  target type
          78    84    87   Class java/lang/Throwable
          61    70   107   Class java/lang/Throwable
          61    70   115   any
         125   131   134   Class java/lang/Throwable
         107   117   115   any

  public java.lang.Object run() throws java.lang.Exception;
    Code:
       0: aload_0
       1: invokevirtual #23                 // Method run:()Ljava/lang/Void;
       4: areturn
}
