Compiled from "AccessControlProtos.java"
final class org.apache.hadoop.hbase.protobuf.generated.AccessControlProtos$AccessControlService$1 extends org.apache.hadoop.hbase.protobuf.generated.AccessControlProtos$AccessControlService {
  final org.apache.hadoop.hbase.protobuf.generated.AccessControlProtos$AccessControlService$Interface val$impl;

  org.apache.hadoop.hbase.protobuf.generated.AccessControlProtos$AccessControlService$1(org.apache.hadoop.hbase.protobuf.generated.AccessControlProtos$AccessControlService$Interface);
    Code:
       0: aload_0
       1: aload_1
       2: putfield      #1                  // Field val$impl:Lorg/apache/hadoop/hbase/protobuf/generated/AccessControlProtos$AccessControlService$Interface;
       5: aload_0
       6: invokespecial #2                  // Method org/apache/hadoop/hbase/protobuf/generated/AccessControlProtos$AccessControlService."<init>":()V
       9: return

  public void grant(com.google.protobuf.RpcController, org.apache.hadoop.hbase.protobuf.generated.AccessControlProtos$GrantRequest, com.google.protobuf.RpcCallback<org.apache.hadoop.hbase.protobuf.generated.AccessControlProtos$GrantResponse>);
    Code:
       0: aload_0
       1: getfield      #1                  // Field val$impl:Lorg/apache/hadoop/hbase/protobuf/generated/AccessControlProtos$AccessControlService$Interface;
       4: aload_1
       5: aload_2
       6: aload_3
       7: invokeinterface #3,  4            // InterfaceMethod org/apache/hadoop/hbase/protobuf/generated/AccessControlProtos$AccessControlService$Interface.grant:(Lcom/google/protobuf/RpcController;Lorg/apache/hadoop/hbase/protobuf/generated/AccessControlProtos$GrantRequest;Lcom/google/protobuf/RpcCallback;)V
      12: return

  public void revoke(com.google.protobuf.RpcController, org.apache.hadoop.hbase.protobuf.generated.AccessControlProtos$RevokeRequest, com.google.protobuf.RpcCallback<org.apache.hadoop.hbase.protobuf.generated.AccessControlProtos$RevokeResponse>);
    Code:
       0: aload_0
       1: getfield      #1                  // Field val$impl:Lorg/apache/hadoop/hbase/protobuf/generated/AccessControlProtos$AccessControlService$Interface;
       4: aload_1
       5: aload_2
       6: aload_3
       7: invokeinterface #4,  4            // InterfaceMethod org/apache/hadoop/hbase/protobuf/generated/AccessControlProtos$AccessControlService$Interface.revoke:(Lcom/google/protobuf/RpcController;Lorg/apache/hadoop/hbase/protobuf/generated/AccessControlProtos$RevokeRequest;Lcom/google/protobuf/RpcCallback;)V
      12: return

  public void getUserPermissions(com.google.protobuf.RpcController, org.apache.hadoop.hbase.protobuf.generated.AccessControlProtos$GetUserPermissionsRequest, com.google.protobuf.RpcCallback<org.apache.hadoop.hbase.protobuf.generated.AccessControlProtos$GetUserPermissionsResponse>);
    Code:
       0: aload_0
       1: getfield      #1                  // Field val$impl:Lorg/apache/hadoop/hbase/protobuf/generated/AccessControlProtos$AccessControlService$Interface;
       4: aload_1
       5: aload_2
       6: aload_3
       7: invokeinterface #5,  4            // InterfaceMethod org/apache/hadoop/hbase/protobuf/generated/AccessControlProtos$AccessControlService$Interface.getUserPermissions:(Lcom/google/protobuf/RpcController;Lorg/apache/hadoop/hbase/protobuf/generated/AccessControlProtos$GetUserPermissionsRequest;Lcom/google/protobuf/RpcCallback;)V
      12: return

  public void checkPermissions(com.google.protobuf.RpcController, org.apache.hadoop.hbase.protobuf.generated.AccessControlProtos$CheckPermissionsRequest, com.google.protobuf.RpcCallback<org.apache.hadoop.hbase.protobuf.generated.AccessControlProtos$CheckPermissionsResponse>);
    Code:
       0: aload_0
       1: getfield      #1                  // Field val$impl:Lorg/apache/hadoop/hbase/protobuf/generated/AccessControlProtos$AccessControlService$Interface;
       4: aload_1
       5: aload_2
       6: aload_3
       7: invokeinterface #6,  4            // InterfaceMethod org/apache/hadoop/hbase/protobuf/generated/AccessControlProtos$AccessControlService$Interface.checkPermissions:(Lcom/google/protobuf/RpcController;Lorg/apache/hadoop/hbase/protobuf/generated/AccessControlProtos$CheckPermissionsRequest;Lcom/google/protobuf/RpcCallback;)V
      12: return

  public void hasPermission(com.google.protobuf.RpcController, org.apache.hadoop.hbase.protobuf.generated.AccessControlProtos$HasPermissionRequest, com.google.protobuf.RpcCallback<org.apache.hadoop.hbase.protobuf.generated.AccessControlProtos$HasPermissionResponse>);
    Code:
       0: aload_0
       1: getfield      #1                  // Field val$impl:Lorg/apache/hadoop/hbase/protobuf/generated/AccessControlProtos$AccessControlService$Interface;
       4: aload_1
       5: aload_2
       6: aload_3
       7: invokeinterface #7,  4            // InterfaceMethod org/apache/hadoop/hbase/protobuf/generated/AccessControlProtos$AccessControlService$Interface.hasPermission:(Lcom/google/protobuf/RpcController;Lorg/apache/hadoop/hbase/protobuf/generated/AccessControlProtos$HasPermissionRequest;Lcom/google/protobuf/RpcCallback;)V
      12: return
}
