Compiled from "AccessControlProtos.java"
final class org.apache.hadoop.hbase.protobuf.generated.AccessControlProtos$AccessControlService$BlockingStub implements org.apache.hadoop.hbase.protobuf.generated.AccessControlProtos$AccessControlService$BlockingInterface {
  public org.apache.hadoop.hbase.protobuf.generated.AccessControlProtos$GrantResponse grant(com.google.protobuf.RpcController, org.apache.hadoop.hbase.protobuf.generated.AccessControlProtos$GrantRequest) throws com.google.protobuf.ServiceException;
    Code:
       0: aload_0
       1: getfield      #3                  // Field channel:Lcom/google/protobuf/BlockingRpcChannel;
       4: invokestatic  #4                  // Method org/apache/hadoop/hbase/protobuf/generated/AccessControlProtos$AccessControlService.getDescriptor:()Lcom/google/protobuf/Descriptors$ServiceDescriptor;
       7: invokevirtual #5                  // Method com/google/protobuf/Descriptors$ServiceDescriptor.getMethods:()Ljava/util/List;
      10: iconst_0
      11: invokeinterface #6,  2            // InterfaceMethod java/util/List.get:(I)Ljava/lang/Object;
      16: checkcast     #7                  // class com/google/protobuf/Descriptors$MethodDescriptor
      19: aload_1
      20: aload_2
      21: invokestatic  #8                  // Method org/apache/hadoop/hbase/protobuf/generated/AccessControlProtos$GrantResponse.getDefaultInstance:()Lorg/apache/hadoop/hbase/protobuf/generated/AccessControlProtos$GrantResponse;
      24: invokeinterface #9,  5            // InterfaceMethod com/google/protobuf/BlockingRpcChannel.callBlockingMethod:(Lcom/google/protobuf/Descriptors$MethodDescriptor;Lcom/google/protobuf/RpcController;Lcom/google/protobuf/Message;Lcom/google/protobuf/Message;)Lcom/google/protobuf/Message;
      29: checkcast     #10                 // class org/apache/hadoop/hbase/protobuf/generated/AccessControlProtos$GrantResponse
      32: areturn

  public org.apache.hadoop.hbase.protobuf.generated.AccessControlProtos$RevokeResponse revoke(com.google.protobuf.RpcController, org.apache.hadoop.hbase.protobuf.generated.AccessControlProtos$RevokeRequest) throws com.google.protobuf.ServiceException;
    Code:
       0: aload_0
       1: getfield      #3                  // Field channel:Lcom/google/protobuf/BlockingRpcChannel;
       4: invokestatic  #4                  // Method org/apache/hadoop/hbase/protobuf/generated/AccessControlProtos$AccessControlService.getDescriptor:()Lcom/google/protobuf/Descriptors$ServiceDescriptor;
       7: invokevirtual #5                  // Method com/google/protobuf/Descriptors$ServiceDescriptor.getMethods:()Ljava/util/List;
      10: iconst_1
      11: invokeinterface #6,  2            // InterfaceMethod java/util/List.get:(I)Ljava/lang/Object;
      16: checkcast     #7                  // class com/google/protobuf/Descriptors$MethodDescriptor
      19: aload_1
      20: aload_2
      21: invokestatic  #11                 // Method org/apache/hadoop/hbase/protobuf/generated/AccessControlProtos$RevokeResponse.getDefaultInstance:()Lorg/apache/hadoop/hbase/protobuf/generated/AccessControlProtos$RevokeResponse;
      24: invokeinterface #9,  5            // InterfaceMethod com/google/protobuf/BlockingRpcChannel.callBlockingMethod:(Lcom/google/protobuf/Descriptors$MethodDescriptor;Lcom/google/protobuf/RpcController;Lcom/google/protobuf/Message;Lcom/google/protobuf/Message;)Lcom/google/protobuf/Message;
      29: checkcast     #12                 // class org/apache/hadoop/hbase/protobuf/generated/AccessControlProtos$RevokeResponse
      32: areturn

  public org.apache.hadoop.hbase.protobuf.generated.AccessControlProtos$GetUserPermissionsResponse getUserPermissions(com.google.protobuf.RpcController, org.apache.hadoop.hbase.protobuf.generated.AccessControlProtos$GetUserPermissionsRequest) throws com.google.protobuf.ServiceException;
    Code:
       0: aload_0
       1: getfield      #3                  // Field channel:Lcom/google/protobuf/BlockingRpcChannel;
       4: invokestatic  #4                  // Method org/apache/hadoop/hbase/protobuf/generated/AccessControlProtos$AccessControlService.getDescriptor:()Lcom/google/protobuf/Descriptors$ServiceDescriptor;
       7: invokevirtual #5                  // Method com/google/protobuf/Descriptors$ServiceDescriptor.getMethods:()Ljava/util/List;
      10: iconst_2
      11: invokeinterface #6,  2            // InterfaceMethod java/util/List.get:(I)Ljava/lang/Object;
      16: checkcast     #7                  // class com/google/protobuf/Descriptors$MethodDescriptor
      19: aload_1
      20: aload_2
      21: invokestatic  #13                 // Method org/apache/hadoop/hbase/protobuf/generated/AccessControlProtos$GetUserPermissionsResponse.getDefaultInstance:()Lorg/apache/hadoop/hbase/protobuf/generated/AccessControlProtos$GetUserPermissionsResponse;
      24: invokeinterface #9,  5            // InterfaceMethod com/google/protobuf/BlockingRpcChannel.callBlockingMethod:(Lcom/google/protobuf/Descriptors$MethodDescriptor;Lcom/google/protobuf/RpcController;Lcom/google/protobuf/Message;Lcom/google/protobuf/Message;)Lcom/google/protobuf/Message;
      29: checkcast     #14                 // class org/apache/hadoop/hbase/protobuf/generated/AccessControlProtos$GetUserPermissionsResponse
      32: areturn

  public org.apache.hadoop.hbase.protobuf.generated.AccessControlProtos$CheckPermissionsResponse checkPermissions(com.google.protobuf.RpcController, org.apache.hadoop.hbase.protobuf.generated.AccessControlProtos$CheckPermissionsRequest) throws com.google.protobuf.ServiceException;
    Code:
       0: aload_0
       1: getfield      #3                  // Field channel:Lcom/google/protobuf/BlockingRpcChannel;
       4: invokestatic  #4                  // Method org/apache/hadoop/hbase/protobuf/generated/AccessControlProtos$AccessControlService.getDescriptor:()Lcom/google/protobuf/Descriptors$ServiceDescriptor;
       7: invokevirtual #5                  // Method com/google/protobuf/Descriptors$ServiceDescriptor.getMethods:()Ljava/util/List;
      10: iconst_3
      11: invokeinterface #6,  2            // InterfaceMethod java/util/List.get:(I)Ljava/lang/Object;
      16: checkcast     #7                  // class com/google/protobuf/Descriptors$MethodDescriptor
      19: aload_1
      20: aload_2
      21: invokestatic  #15                 // Method org/apache/hadoop/hbase/protobuf/generated/AccessControlProtos$CheckPermissionsResponse.getDefaultInstance:()Lorg/apache/hadoop/hbase/protobuf/generated/AccessControlProtos$CheckPermissionsResponse;
      24: invokeinterface #9,  5            // InterfaceMethod com/google/protobuf/BlockingRpcChannel.callBlockingMethod:(Lcom/google/protobuf/Descriptors$MethodDescriptor;Lcom/google/protobuf/RpcController;Lcom/google/protobuf/Message;Lcom/google/protobuf/Message;)Lcom/google/protobuf/Message;
      29: checkcast     #16                 // class org/apache/hadoop/hbase/protobuf/generated/AccessControlProtos$CheckPermissionsResponse
      32: areturn

  public org.apache.hadoop.hbase.protobuf.generated.AccessControlProtos$HasPermissionResponse hasPermission(com.google.protobuf.RpcController, org.apache.hadoop.hbase.protobuf.generated.AccessControlProtos$HasPermissionRequest) throws com.google.protobuf.ServiceException;
    Code:
       0: aload_0
       1: getfield      #3                  // Field channel:Lcom/google/protobuf/BlockingRpcChannel;
       4: invokestatic  #4                  // Method org/apache/hadoop/hbase/protobuf/generated/AccessControlProtos$AccessControlService.getDescriptor:()Lcom/google/protobuf/Descriptors$ServiceDescriptor;
       7: invokevirtual #5                  // Method com/google/protobuf/Descriptors$ServiceDescriptor.getMethods:()Ljava/util/List;
      10: iconst_4
      11: invokeinterface #6,  2            // InterfaceMethod java/util/List.get:(I)Ljava/lang/Object;
      16: checkcast     #7                  // class com/google/protobuf/Descriptors$MethodDescriptor
      19: aload_1
      20: aload_2
      21: invokestatic  #17                 // Method org/apache/hadoop/hbase/protobuf/generated/AccessControlProtos$HasPermissionResponse.getDefaultInstance:()Lorg/apache/hadoop/hbase/protobuf/generated/AccessControlProtos$HasPermissionResponse;
      24: invokeinterface #9,  5            // InterfaceMethod com/google/protobuf/BlockingRpcChannel.callBlockingMethod:(Lcom/google/protobuf/Descriptors$MethodDescriptor;Lcom/google/protobuf/RpcController;Lcom/google/protobuf/Message;Lcom/google/protobuf/Message;)Lcom/google/protobuf/Message;
      29: checkcast     #18                 // class org/apache/hadoop/hbase/protobuf/generated/AccessControlProtos$HasPermissionResponse
      32: areturn

  org.apache.hadoop.hbase.protobuf.generated.AccessControlProtos$AccessControlService$BlockingStub(com.google.protobuf.BlockingRpcChannel, org.apache.hadoop.hbase.protobuf.generated.AccessControlProtos$1);
    Code:
       0: aload_0
       1: aload_1
       2: invokespecial #1                  // Method "<init>":(Lcom/google/protobuf/BlockingRpcChannel;)V
       5: return
}
