Compiled from "AccessDeniedException.java"
public class org.apache.hadoop.hbase.security.AccessDeniedException extends org.apache.hadoop.hbase.DoNotRetryIOException {
  public org.apache.hadoop.hbase.security.AccessDeniedException();
    Code:
       0: aload_0
       1: invokespecial #1                  // Method org/apache/hadoop/hbase/DoNotRetryIOException."<init>":()V
       4: return

  public org.apache.hadoop.hbase.security.AccessDeniedException(java.lang.Class<?>, java.lang.String);
    Code:
       0: aload_0
       1: new           #2                  // class java/lang/StringBuilder
       4: dup
       5: invokespecial #3                  // Method java/lang/StringBuilder."<init>":()V
       8: ldc           #4                  // String AccessDenied [
      10: invokevirtual #5                  // Method java/lang/StringBuilder.append:(Ljava/lang/String;)Ljava/lang/StringBuilder;
      13: aload_1
      14: invokevirtual #6                  // Method java/lang/Class.getName:()Ljava/lang/String;
      17: invokevirtual #5                  // Method java/lang/StringBuilder.append:(Ljava/lang/String;)Ljava/lang/StringBuilder;
      20: ldc           #7                  // String ]:
      22: invokevirtual #5                  // Method java/lang/StringBuilder.append:(Ljava/lang/String;)Ljava/lang/StringBuilder;
      25: aload_2
      26: invokevirtual #5                  // Method java/lang/StringBuilder.append:(Ljava/lang/String;)Ljava/lang/StringBuilder;
      29: invokevirtual #8                  // Method java/lang/StringBuilder.toString:()Ljava/lang/String;
      32: invokespecial #9                  // Method org/apache/hadoop/hbase/DoNotRetryIOException."<init>":(Ljava/lang/String;)V
      35: return

  public org.apache.hadoop.hbase.security.AccessDeniedException(java.lang.String);
    Code:
       0: aload_0
       1: aload_1
       2: invokespecial #9                  // Method org/apache/hadoop/hbase/DoNotRetryIOException."<init>":(Ljava/lang/String;)V
       5: return

  public org.apache.hadoop.hbase.security.AccessDeniedException(java.lang.Throwable);
    Code:
       0: aload_0
       1: aload_1
       2: invokespecial #10                 // Method org/apache/hadoop/hbase/DoNotRetryIOException."<init>":(Ljava/lang/Throwable;)V
       5: return
}
